{
  "type": "Feature",
  "properties": {
    "gn:admin1_code":"35.0",
    "gn:admin2_code":"436.0",
    "gn:asciiname":"Govardhanya",
    "gn:country_code":"IN",
    "gn:dem":484,
    "gn:feature_class":"P",
    "gn:feature_code":"PPL",
    "gn:name":"Govardhanya",
    "gn:population":0,
    "gn:timezone":"Asia/Kolkata",
    "iso:country":"IN",
    "wof:name":"Govardhanya",
    "wof:placetype":"locality"
},
  "geometry": {"coordinates":[76.75964999999999,23.21315],"type":"Point"}
}