{
  "type": "Feature",
  "properties": {
    "iso:country":"IN",
    "ks:ks_name":"Narsingh Dhar",
    "ks:ks_pop":165,
    "ks:ks_type":"VILLAGE",
    "name:eng_x_preferred":[
        "Narsingh Dhar"
    ],
    "wof:name":"Narsingh Dhar",
    "wof:placetype":"locality",
    "wof:population":165
},
  "geometry": {"coordinates":[78.397524,30.417732],"type":"Point"}
}