{
  "type": "Feature",
  "properties": {
    "iso:country":"IN",
    "ks:ks_name":"Pipariya Ghat",
    "ks:ks_pop":424,
    "ks:ks_type":"HABITATION",
    "name:eng_x_preferred":[
        "Pipariya Ghat"
    ],
    "wof:name":"Pipariya Ghat",
    "wof:placetype":"locality",
    "wof:population":424
},
  "geometry": {"coordinates":[77.933735,23.902034],"type":"Point"}
}