{
  "type": "Feature",
  "properties": {
    "gn:admin1_code":"25.0",
    "gn:admin2_code":"613.0",
    "gn:asciiname":"Moolimangalam",
    "gn:country_code":"IN",
    "gn:dem":157,
    "gn:feature_class":"P",
    "gn:feature_code":"PPL",
    "gn:name":"Moolimangalam",
    "gn:population":0,
    "gn:timezone":"Asia/Kolkata",
    "iso:country":"IN",
    "wof:name":"Moolimangalam",
    "wof:placetype":"locality"
},
  "geometry": {"coordinates":[78.00216,11.03782],"type":"Point"}
}