{
  "type": "Feature",
  "properties": {
    "iso:country":"IN",
    "ks:ks_name":"Ganiyari",
    "ks:ks_pop":0,
    "ks:ks_type":"VILLAGE",
    "name:eng_x_preferred":[
        "Ganiyari"
    ],
    "wof:name":"Ganiyari",
    "wof:placetype":"locality",
    "wof:population":0
},
  "geometry": {"coordinates":[80.302481,23.429384],"type":"Point"}
}