{
  "type": "Feature",
  "properties": {
    "gn:admin1_code":"16.0",
    "gn:admin2_code":"500.0",
    "gn:asciiname":"Shelgaon Raut",
    "gn:country_code":"IN",
    "gn:dem":525,
    "gn:feature_class":"P",
    "gn:feature_code":"PPL",
    "gn:name":"Shelgaon R\u0101ut",
    "gn:population":0,
    "gn:timezone":"Asia/Kolkata",
    "iso:country":"IN",
    "wof:name":"Shelgaon Raut",
    "wof:placetype":"locality"
},
  "geometry": {"coordinates":[76.21951,19.99455],"type":"Point"}
}