{
  "type": "Feature",
  "properties": {
    "gn:admin1_code":"36",
    "gn:admin2_code":"185.0",
    "gn:asciiname":"Badhar Khurd",
    "gn:country_code":"IN",
    "gn:dem":93,
    "gn:feature_class":"P",
    "gn:feature_code":"PPL",
    "gn:name":"Badhar Khurd",
    "gn:population":0,
    "gn:timezone":"Asia/Kolkata",
    "iso:country":"IN",
    "ks:ks_name":"Barhar Khurd",
    "ks:ks_pop":451,
    "ks:ks_type":"VILLAGE",
    "ks:ks_uagg_main":0,
    "name:eng_x_preferred":[
        "Barhar Khurd"
    ],
    "wof:name":"Barhar Khurd",
    "wof:placetype":"neighbourhood",
    "wof:population":451
},
  "geometry": {"coordinates":[82.429196,26.787063],"type":"Point"}
}