{
  "type": "Feature",
  "properties": {
    "iso:country":"IN",
    "ks:ks_name":"Manjhitola",
    "ks:ks_pop":221,
    "ks:ks_type":"HABITATION",
    "name:eng_x_preferred":[
        "Manjhitola"
    ],
    "wof:name":"Manjhitola",
    "wof:placetype":"locality",
    "wof:population":221
},
  "geometry": {"coordinates":[86.350781,24.339933],"type":"Point"}
}