{
  "type": "Feature",
  "properties": {
    "iso:country":"IN",
    "ks:ks_alt_nam":"wasubil 1",
    "ks:ks_name":"Wasubil 1",
    "ks:ks_pop":150,
    "ks:ks_type":"HABITATION",
    "ks:ks_uagg_main":0,
    "name:eng_x_preferred":[
        "Wasubil 1"
    ],
    "wof:name":"Wasubil 1",
    "wof:placetype":"neighbourhood",
    "wof:population":150
},
  "geometry": {"coordinates":[92.915672,25.744651],"type":"Point"}
}