{
  "type": "Feature",
  "properties": {
    "iso:country":"IN",
    "ks:ks_name":"Kallu Khan",
    "ks:ks_pop":157,
    "ks:ks_type":"HABITATION",
    "name:eng_x_preferred":[
        "Kallu Khan"
    ],
    "wof:name":"Kallu Khan",
    "wof:placetype":"locality",
    "wof:population":157
},
  "geometry": {"coordinates":[79.996691,29.332647],"type":"Point"}
}