{
  "type": "Feature",
  "properties": {
    "iso:country":"IN",
    "ks:ks_name":"Kuduvaladoddi",
    "ks:ks_pop":209,
    "ks:ks_type":"HABITATION",
    "name:eng_x_preferred":[
        "Kuduvaladoddi"
    ],
    "wof:name":"Kuduvaladoddi",
    "wof:placetype":"locality",
    "wof:population":209
},
  "geometry": {"coordinates":[77.279712,11.927175],"type":"Point"}
}