{
  "type": "Feature",
  "properties": {
    "iso:country":"IN",
    "ks:ks_name":"Kotepal",
    "ks:ks_pop":121,
    "ks:ks_type":"HABITATION",
    "name:eng_x_preferred":[
        "Kotepal"
    ],
    "wof:name":"Kotepal",
    "wof:placetype":"locality",
    "wof:population":121
},
  "geometry": {"coordinates":[74.49646,14.763473],"type":"Point"}
}