{
  "type": "Feature",
  "properties": {
    "gn:admin1_code":"39.0",
    "gn:admin2_code":"60.0",
    "gn:asciiname":"Joshi",
    "gn:country_code":"IN",
    "gn:dem":1227,
    "gn:feature_class":"P",
    "gn:feature_code":"PPL",
    "gn:name":"Joshi",
    "gn:population":0,
    "gn:timezone":"Asia/Kolkata",
    "iso:country":"IN",
    "name:rus_x_preferred":[
        "\u0414\u0436\u043e\u0448\u0438"
    ],
    "wof:name":"Joshi",
    "wof:placetype":"locality"
},
  "geometry": {"coordinates":[77.88896,30.58485],"type":"Point"}
}