{
  "type": "Feature",
  "properties": {
    "iso:country":"IN",
    "ks:ks_alt_nam":"Bekol\u0101lpur",
    "ks:ks_name":"Bekolalpur",
    "ks:ks_pop":665,
    "ks:ks_type":"VILLAGE",
    "name:eng_x_preferred":[
        "Bekolalpur"
    ],
    "name:eng_x_variant":[
        "Bekol\u0101lpur"
    ],
    "wof:name":"Bekolalpur",
    "wof:placetype":"locality",
    "wof:population":665
},
  "geometry": {"coordinates":[86.122738,24.181574],"type":"Point"}
}