{
  "type": "Feature",
  "properties": {
    "iso:country":"IN",
    "ks:ks_name":"Nandkarwadi",
    "ks:ks_pop":254,
    "ks:ks_type":"HABITATION",
    "name:eng_x_preferred":[
        "Nandkarwadi"
    ],
    "wof:name":"Nandkarwadi",
    "wof:placetype":"locality",
    "wof:population":254
},
  "geometry": {"coordinates":[73.767653,19.137473],"type":"Point"}
}