{
  "type": "Feature",
  "properties": {
    "gn:admin1_code":"39.0",
    "gn:admin2_code":"57.0",
    "gn:asciiname":"Arani",
    "gn:country_code":"IN",
    "gn:dem":1744,
    "gn:feature_class":"P",
    "gn:feature_code":"PPL",
    "gn:name":"Ar\u0101ni",
    "gn:population":0,
    "gn:timezone":"Asia/Kolkata",
    "iso:country":"IN",
    "name:ceb_x_preferred":[
        "Arani"
    ],
    "name:deu_x_preferred":[
        "Arani"
    ],
    "name:hin_x_preferred":[
        "\u0906\u0930\u0928\u0940"
    ],
    "name:ita_x_preferred":[
        "Arani"
    ],
    "name:msa_x_preferred":[
        "Arani"
    ],
    "name:nld_x_preferred":[
        "Arani"
    ],
    "name:spa_x_preferred":[
        "Arani"
    ],
    "name:swe_x_preferred":[
        "Arani"
    ],
    "name:tam_x_preferred":[
        "\u0b86\u0bb0\u0ba3\u0bbf"
    ],
    "wof:name":"Arani",
    "wof:placetype":"locality"
},
  "geometry": {"coordinates":[79.64398,30.12111],"type":"Point"}
}