{
  "type": "Feature",
  "properties": {
    "iso:country":"IN",
    "ks:ks_name":"Tola Dhawatanr",
    "ks:ks_pop":0,
    "ks:ks_type":"VILLAGE",
    "name:eng_x_preferred":[
        "Tola Dhawatanr"
    ],
    "wof:name":"Tola Dhawatanr",
    "wof:placetype":"locality",
    "wof:population":0
},
  "geometry": {"coordinates":[86.365166,24.813815],"type":"Point"}
}