{
  "type": "Feature",
  "properties": {
    "iso:country":"IN",
    "ks:ks_name":"Mahuari(hb)",
    "ks:ks_pop":435,
    "ks:ks_type":"HABITATION",
    "ks:ks_uagg_main":0,
    "name:eng_x_preferred":[
        "Mahuari(hb)"
    ],
    "wof:name":"Mahuari(hb)",
    "wof:placetype":"neighbourhood",
    "wof:population":435
},
  "geometry": {"coordinates":[82.83690199999999,25.603537],"type":"Point"}
}