{
  "type": "Feature",
  "properties": {
    "gn:admin1_code":"36",
    "gn:admin2_code":"144.0",
    "gn:asciiname":"Nagla Al",
    "gn:country_code":"IN",
    "gn:dem":177,
    "gn:feature_class":"P",
    "gn:feature_code":"PPL",
    "gn:name":"Nagla \u0100l",
    "gn:population":0,
    "gn:timezone":"Asia/Kolkata",
    "iso:country":"IN",
    "wof:name":"Nagla Al",
    "wof:placetype":"neighbourhood"
},
  "geometry": {"coordinates":[78.2176,27.60453],"type":"Point"}
}