{
  "type": "Feature",
  "properties": {
    "iso:country":"IN",
    "ks:ks_name":"Pilkhi Varuna Main",
    "ks:ks_pop":60,
    "ks:ks_type":"HABITATION",
    "ks:ks_uagg_main":0,
    "name:eng_x_preferred":[
        "Pilkhi Varuna Main"
    ],
    "wof:name":"Pilkhi Varuna Main",
    "wof:placetype":"neighbourhood",
    "wof:population":60
},
  "geometry": {"coordinates":[83.707193,25.933589],"type":"Point"}
}