{
  "type": "Feature",
  "properties": {
    "iso:country":"IN",
    "ks:ks_name":"Jagir Pipara",
    "ks:ks_pop":234,
    "ks:ks_type":"HABITATION",
    "name:eng_x_preferred":[
        "Jagir Pipara"
    ],
    "wof:name":"Jagir Pipara",
    "wof:placetype":"locality",
    "wof:population":234
},
  "geometry": {"coordinates":[87.480154,26.339357],"type":"Point"}
}