{
  "type": "Feature",
  "properties": {
    "iso:country":"IN",
    "ks:ks_name":"Gonbora",
    "ks:ks_pop":262,
    "ks:ks_type":"VILLAGE",
    "name:eng_x_preferred":[
        "Gonbora"
    ],
    "wof:name":"Gonbora",
    "wof:placetype":"locality",
    "wof:population":262
},
  "geometry": {"coordinates":[82.187281,20.714094],"type":"Point"}
}