{
  "type": "Feature",
  "properties": {
    "gn:admin1_code":"25.0",
    "gn:admin2_code":"631.0",
    "gn:asciiname":"Bettamugalalam",
    "gn:country_code":"IN",
    "gn:dem":1040,
    "gn:feature_class":"P",
    "gn:feature_code":"PPL",
    "gn:name":"Bettamugal\u0101lam",
    "gn:population":0,
    "gn:timezone":"Asia/Kolkata",
    "iso:country":"IN",
    "wof:name":"Bettamugalalam",
    "wof:placetype":"locality"
},
  "geometry": {"coordinates":[77.90989999999999,12.36909],"type":"Point"}
}