{
  "type": "Feature",
  "properties": {
    "iso:country":"IN",
    "ks:ks_alt_nam":"Chodeya khas",
    "ks:ks_name":"Chodeya Khas",
    "ks:ks_pop":646,
    "ks:ks_type":"HABITATION",
    "name:eng_x_preferred":[
        "Chodeya Khas"
    ],
    "wof:name":"Chodeya Khas",
    "wof:placetype":"locality",
    "wof:population":646
},
  "geometry": {"coordinates":[83.01769299999999,22.944343],"type":"Point"}
}