{
  "type": "Feature",
  "properties": {
    "iso:country":"IN",
    "ks:ks_alt_nam":"puldevibanda Thanda",
    "ks:ks_name":"Puldevibanda Thanda",
    "ks:ks_pop":73,
    "ks:ks_type":"HABITATION",
    "name:eng_x_preferred":[
        "Puldevibanda Thanda"
    ],
    "wof:name":"Puldevibanda Thanda",
    "wof:placetype":"locality",
    "wof:population":73
},
  "geometry": {"coordinates":[78.882994,16.510545],"type":"Point"}
}