{
  "type": "Feature",
  "properties": {
    "gn:admin1_code":"23.0",
    "gn:admin2_code":"36.0",
    "gn:asciiname":"Machhiwal Mand",
    "gn:country_code":"IN",
    "gn:dem":229,
    "gn:feature_class":"P",
    "gn:feature_code":"PPL",
    "gn:name":"Machhiw\u0101l Mand",
    "gn:population":0,
    "gn:timezone":"Asia/Kolkata",
    "iso:country":"IN",
    "wof:name":"Machhiwal Mand",
    "wof:placetype":"locality"
},
  "geometry": {"coordinates":[75.44356999999999,31.60711],"type":"Point"}
}