{
  "type": "Feature",
  "properties": {
    "iso:country":"IN",
    "ks:ks_name":"Shyam Nagar",
    "ks:ks_pop":185,
    "ks:ks_type":"HABITATION",
    "name:eng_x_preferred":[
        "Shyam Nagar"
    ],
    "wof:name":"Shyam Nagar",
    "wof:placetype":"locality",
    "wof:population":185
},
  "geometry": {"coordinates":[86.770318,22.698498],"type":"Point"}
}