{
  "type": "Feature",
  "properties": {
    "gn:admin1_code":"2.0",
    "gn:admin2_code":"542.0",
    "gn:asciiname":"Ruppannaguda",
    "gn:country_code":"IN",
    "gn:dem":392,
    "gn:feature_class":"P",
    "gn:feature_code":"PPL",
    "gn:name":"Ruppannag\u016bda",
    "gn:population":0,
    "gn:timezone":"Asia/Kolkata",
    "iso:country":"IN",
    "wof:name":"Ruppannaguda",
    "wof:placetype":"locality"
},
  "geometry": {"coordinates":[83.80062,18.71992],"type":"Point"}
}