{
  "type": "Feature",
  "properties": {
    "iso:country":"IN",
    "ks:ks_alt_nam":"niduiymeethal SC colony",
    "ks:ks_name":"Niduiymeethal Sc Colony",
    "ks:ks_pop":431,
    "ks:ks_type":"HABITATION",
    "name:eng_x_preferred":[
        "Niduiymeethal Sc Colony"
    ],
    "wof:name":"Niduiymeethal Sc Colony",
    "wof:placetype":"locality",
    "wof:population":431
},
  "geometry": {"coordinates":[75.786845,11.577725],"type":"Point"}
}