{
  "type": "Feature",
  "properties": {
    "iso:country":"IN",
    "ks:ks_name":"Ottarband",
    "ks:ks_pop":143,
    "ks:ks_type":"HABITATION",
    "name:eng_x_preferred":[
        "Ottarband"
    ],
    "wof:name":"Ottarband",
    "wof:placetype":"locality",
    "wof:population":143
},
  "geometry": {"coordinates":[89.896581,26.170206],"type":"Point"}
}