{
  "type": "Feature",
  "properties": {
    "gn:admin1_code":"36",
    "gn:admin2_code":"185.0",
    "gn:asciiname":"Tahirpur",
    "gn:country_code":"IN",
    "gn:dem":88,
    "gn:feature_class":"P",
    "gn:feature_code":"PPL",
    "gn:name":"T\u0101hirpur",
    "gn:population":0,
    "gn:timezone":"Asia/Kolkata",
    "iso:country":"IN",
    "ks:ks_alt_nam":"T\u0101hirpur",
    "ks:ks_name":"Tahirpur",
    "ks:ks_type":"VILLAGE",
    "name:eng_x_preferred":[
        "Tahirpur"
    ],
    "name:eng_x_variant":[
        "T\u0101hirpur"
    ],
    "wof:name":"Tahirpur",
    "wof:placetype":"locality"
},
  "geometry": {"coordinates":[82.669299,26.625192],"type":"Point"}
}