{
  "type": "Feature",
  "properties": {
    "iso:country":"IN",
    "ks:ks_alt_nam":"Tod\u0101ngh\u0101tu",
    "ks:ks_name":"Todanghatu",
    "ks:ks_pop":130,
    "ks:ks_type":"VILLAGE",
    "name:eng_x_preferred":[
        "Todanghatu"
    ],
    "name:eng_x_variant":[
        "Tod\u0101ngh\u0101tu"
    ],
    "wof:name":"Todanghatu",
    "wof:placetype":"locality",
    "wof:population":130
},
  "geometry": {"coordinates":[85.310923,22.770026],"type":"Point"}
}