{
  "type": "Feature",
  "properties": {
    "gn:admin1_code":"09",
    "gn:admin2_code":"488.0",
    "gn:asciiname":"Valia",
    "gn:country_code":"IN",
    "gn:dem":56,
    "gn:feature_class":"P",
    "gn:feature_code":"PPL",
    "gn:name":"V\u0101lia",
    "gn:population":0,
    "gn:timezone":"Asia/Kolkata",
    "iso:country":"IN",
    "name:ceb_x_preferred":[
        "Valia"
    ],
    "name:spa_x_preferred":[
        "Valia"
    ],
    "name:swe_x_preferred":[
        "Valia"
    ],
    "wof:name":"Valia",
    "wof:placetype":"locality"
},
  "geometry": {"coordinates":[73.16019,21.57076],"type":"Point"}
}