{
  "type": "Feature",
  "properties": {
    "gn:admin1_code":"34.0",
    "gn:admin2_code":"236.0",
    "gn:asciiname":"Dobhatanr",
    "gn:country_code":"IN",
    "gn:dem":183,
    "gn:feature_class":"P",
    "gn:feature_code":"PPL",
    "gn:name":"Dobh\u0101tanr",
    "gn:population":0,
    "gn:timezone":"Asia/Kolkata",
    "iso:country":"IN",
    "wof:name":"Dobhatanr",
    "wof:placetype":"locality"
},
  "geometry": {"coordinates":[85.29613000000001,24.58024],"type":"Point"}
}