{
  "type": "Feature",
  "properties": {
    "iso:country":"IN",
    "ks:ks_name":"Marli",
    "ks:ks_pop":68,
    "ks:ks_type":"HABITATION",
    "name:eng_x_preferred":[
        "Marli"
    ],
    "wof:name":"Marli",
    "wof:placetype":"locality",
    "wof:population":68
},
  "geometry": {"coordinates":[74.42084699999999,15.215548],"type":"Point"}
}