{
  "type": "Feature",
  "properties": {
    "iso:country":"IN",
    "ks:ks_name":"Simbli Gujjra",
    "ks:ks_pop":789,
    "ks:ks_type":"HABITATION",
    "name:eng_x_preferred":[
        "Simbli Gujjra"
    ],
    "wof:name":"Simbli Gujjra",
    "wof:placetype":"locality",
    "wof:population":789
},
  "geometry": {"coordinates":[75.620769,32.176126],"type":"Point"}
}