{
  "type": "Feature",
  "properties": {
    "gn:admin1_code":"12.0",
    "gn:admin2_code":"020",
    "gn:asciiname":"Dharhor",
    "gn:country_code":"IN",
    "gn:dem":622,
    "gn:feature_class":"P",
    "gn:feature_code":"PPL",
    "gn:name":"Dharhor",
    "gn:population":0,
    "gn:timezone":"Asia/Kolkata",
    "iso:country":"IN",
    "wof:name":"Dharhor",
    "wof:placetype":"locality"
},
  "geometry": {"coordinates":[74.92706,32.89908],"type":"Point"}
}