{
  "type": "Feature",
  "properties": {
    "gn:admin1_code":"24.0",
    "gn:admin2_code":"114",
    "gn:asciiname":"Khinya",
    "gn:country_code":"IN",
    "gn:dem":169,
    "gn:feature_class":"P",
    "gn:feature_code":"PPL",
    "gn:name":"Kh\u012bnya",
    "gn:population":0,
    "gn:timezone":"Asia/Kolkata",
    "iso:country":"IN",
    "name:und_x_variant":[
        "Khlnyan",
        "Kh\u012bnyan",
        "Kh\u012bnya"
    ],
    "wof:name":"Khinya",
    "wof:placetype":"locality"
},
  "geometry": {"coordinates":[70.85526999999998,27.32902],"type":"Point"}
}