{
  "type": "Feature",
  "properties": {
    "iso:country":"IN",
    "ks:ks_name":"Rautwadi",
    "ks:ks_pop":76,
    "ks:ks_type":"HABITATION",
    "name:eng_x_preferred":[
        "Rautwadi"
    ],
    "wof:name":"Rautwadi",
    "wof:placetype":"locality",
    "wof:population":76
},
  "geometry": {"coordinates":[73.726575,16.425665],"type":"Point"}
}