{
  "type": "Feature",
  "properties": {
    "iso:country":"IN",
    "ks:ks_name":"Ghanduha Ka Purwa",
    "ks:ks_pop":250,
    "ks:ks_type":"HABITATION",
    "ks:ks_uagg_main":0,
    "name:eng_x_preferred":[
        "Ghanduha Ka Purwa"
    ],
    "wof:name":"Ghanduha Ka Purwa",
    "wof:placetype":"neighbourhood",
    "wof:population":250
},
  "geometry": {"coordinates":[82.157695,26.706144],"type":"Point"}
}