{
  "type": "Feature",
  "properties": {
    "iso:country":"IN",
    "ks:ks_alt_nam":"KRUHUGUDA",
    "ks:ks_name":"Kruhuguda",
    "ks:ks_pop":165,
    "ks:ks_type":"HABITATION",
    "name:eng_x_preferred":[
        "Kruhuguda"
    ],
    "wof:name":"Kruhuguda",
    "wof:placetype":"locality",
    "wof:population":165
},
  "geometry": {"coordinates":[84.300943,19.995975],"type":"Point"}
}