{
  "type": "Feature",
  "properties": {
    "iso:country":"IN",
    "ks:ks_name":"Karsadewasti",
    "ks:ks_pop":100,
    "ks:ks_type":"HABITATION",
    "name:eng_x_preferred":[
        "Karsadewasti"
    ],
    "wof:name":"Karsadewasti",
    "wof:placetype":"locality",
    "wof:population":100
},
  "geometry": {"coordinates":[75.311092,18.499379],"type":"Point"}
}