{
  "type": "Feature",
  "properties": {
    "iso:country":"IN",
    "ks:ks_name":"Panapur",
    "ks:ks_pop":0,
    "ks:ks_type":"VILLAGE",
    "name:eng_x_preferred":[
        "Panapur"
    ],
    "wof:name":"Panapur",
    "wof:placetype":"locality",
    "wof:population":0
},
  "geometry": {"coordinates":[83.961787,25.316374],"type":"Point"}
}