{
  "type": "Feature",
  "properties": {
    "iso:country":"IN",
    "ks:ks_name":"Viraganur",
    "ks:ks_pop":3210,
    "ks:ks_type":"URBAN",
    "ks:ks_uagg_main":0,
    "name:eng_x_preferred":[
        "Viraganur"
    ],
    "wof:name":"Viraganur",
    "wof:placetype":"neighbourhood",
    "wof:population":3210
},
  "geometry": {"coordinates":[78.160121,9.903789],"type":"Point"}
}