{
  "type": "Feature",
  "properties": {
    "iso:country":"IN",
    "ks:ks_name":"Paraiur",
    "ks:ks_pop":167,
    "ks:ks_type":"HABITATION",
    "name:eng_x_preferred":[
        "Paraiur"
    ],
    "wof:name":"Paraiur",
    "wof:placetype":"locality",
    "wof:population":167
},
  "geometry": {"coordinates":[77.78649,10.482625],"type":"Point"}
}