{
  "type": "Feature",
  "properties": {
    "gn:admin1_code":"19.0",
    "gn:admin2_code":"583.0",
    "gn:asciiname":"Mutkur",
    "gn:country_code":"IN",
    "gn:dem":870,
    "gn:feature_class":"P",
    "gn:feature_code":"PPL",
    "gn:name":"Mutk\u016br",
    "gn:population":0,
    "gn:timezone":"Asia/Kolkata",
    "iso:country":"IN",
    "wof:name":"Mutkur",
    "wof:placetype":"locality"
},
  "geometry": {"coordinates":[77.80701999999999,12.95634],"type":"Point"}
}