{
  "type": "Feature",
  "properties": {
    "iso:country":"IN",
    "ks:ks_name":"Tiwari Tola.",
    "ks:ks_pop":231,
    "ks:ks_type":"HABITATION",
    "ks:ks_uagg_main":0,
    "name:eng_x_preferred":[
        "Tiwari Tola."
    ],
    "wof:name":"Tiwari Tola.",
    "wof:placetype":"neighbourhood",
    "wof:population":231
},
  "geometry": {"coordinates":[84.00031799999999,27.026011],"type":"Point"}
}