{
  "type": "Feature",
  "properties": {
    "iso:country":"IN",
    "ks:ks_name":"Kanduan Purwa",
    "ks:ks_pop":1101,
    "ks:ks_type":"HABITATION",
    "name:eng_x_preferred":[
        "Kanduan Purwa"
    ],
    "wof:name":"Kanduan Purwa",
    "wof:placetype":"locality",
    "wof:population":1101
},
  "geometry": {"coordinates":[81.967079,27.677029],"type":"Point"}
}