{
  "type": "Feature",
  "properties": {
    "iso:country":"IN",
    "ks:ks_name":"Bariarpur",
    "ks:ks_pop":140,
    "ks:ks_type":"VILLAGE",
    "name:eng_x_preferred":[
        "Bariarpur"
    ],
    "wof:name":"Bariarpur",
    "wof:placetype":"locality",
    "wof:population":140
},
  "geometry": {"coordinates":[82.267669,25.819197],"type":"Point"}
}