{
  "type": "Feature",
  "properties": {
    "iso:country":"IN",
    "ks:ks_name":"Handigadde",
    "ks:ks_pop":260,
    "ks:ks_type":"HABITATION",
    "name:eng_x_preferred":[
        "Handigadde"
    ],
    "wof:name":"Handigadde",
    "wof:placetype":"locality",
    "wof:population":260
},
  "geometry": {"coordinates":[74.287931,14.612024],"type":"Point"}
}