{
  "type": "Feature",
  "properties": {
    "gn:admin1_code":"36",
    "gn:admin2_code":"147.0",
    "gn:asciiname":"Nagla Maha Ram",
    "gn:country_code":"IN",
    "gn:dem":167,
    "gn:feature_class":"P",
    "gn:feature_code":"PPL",
    "gn:name":"Nagla Mah\u0101 R\u0101m",
    "gn:population":0,
    "gn:timezone":"Asia/Kolkata",
    "iso:country":"IN",
    "wof:name":"Nagla Maha Ram",
    "wof:placetype":"neighbourhood"
},
  "geometry": {"coordinates":[78.63702000000001,27.13114],"type":"Point"}
}