{
  "type": "Feature",
  "properties": {
    "iso:country":"IN",
    "ks:ks_name":"Chak Dilar",
    "ks:ks_pop":433,
    "ks:ks_type":"VILLAGE",
    "name:eng_x_preferred":[
        "Chak Dilar"
    ],
    "wof:name":"Chak Dilar",
    "wof:placetype":"locality",
    "wof:population":433
},
  "geometry": {"coordinates":[85.850831,25.6429],"type":"Point"}
}