{
  "type": "Feature",
  "properties": {
    "gn:admin1_code":"11.0",
    "gn:admin2_code":"32.0",
    "gn:asciiname":"Gagar Shakol",
    "gn:country_code":"IN",
    "gn:dem":1471,
    "gn:feature_class":"P",
    "gn:feature_code":"PPL",
    "gn:name":"G\u0101gar Shakol",
    "gn:population":0,
    "gn:timezone":"Asia/Kolkata",
    "iso:country":"IN",
    "wof:name":"Gagar Shakol",
    "wof:placetype":"locality"
},
  "geometry": {"coordinates":[77.24545000000001,30.66597],"type":"Point"}
}