{
  "type": "Feature",
  "properties": {
    "iso:country":"IN",
    "ks:ks_name":"Duliagaon",
    "ks:ks_pop":800,
    "ks:ks_type":"VILLAGE",
    "ks:ks_uagg_main":0,
    "name:eng_x_preferred":[
        "Duliagaon"
    ],
    "wof:name":"Duliagaon",
    "wof:placetype":"neighbourhood",
    "wof:population":800
},
  "geometry": {"coordinates":[93.946735,26.65437],"type":"Point"}
}