{
  "type": "Feature",
  "properties": {
    "gn:admin1_code":"24.0",
    "gn:admin2_code":"130.0",
    "gn:asciiname":"Ranpur",
    "gn:country_code":"IN",
    "gn:dem":498,
    "gn:feature_class":"P",
    "gn:feature_code":"PPL",
    "gn:name":"R\u0101npur",
    "gn:population":0,
    "gn:timezone":"Asia/Kolkata",
    "iso:country":"IN",
    "ks:ks_alt_nam":"R\u0101npur",
    "ks:ks_name":"Ranpur",
    "ks:ks_type":"VILLAGE",
    "name:cat_x_preferred":[
        "Ranpur"
    ],
    "name:eng_x_preferred":[
        "Ranpur"
    ],
    "name:eng_x_variant":[
        "R\u0101npur"
    ],
    "name:guj_x_preferred":[
        "\u0ab0\u0abe\u0aa3\u0aaa\u0ac1\u0ab0"
    ],
    "name:hin_x_preferred":[
        "\u0930\u093e\u0923\u092a\u0941\u0930"
    ],
    "wof:name":"Ranpur",
    "wof:placetype":"locality"
},
  "geometry": {"coordinates":[73.350713,24.480462],"type":"Point"}
}