{
  "type": "Feature",
  "properties": {
    "iso:country":"IN",
    "ks:ks_name":"Harijan Coloney",
    "ks:ks_pop":158,
    "ks:ks_type":"HABITATION",
    "ks:ks_uagg_main":0,
    "name:eng_x_preferred":[
        "Harijan Coloney"
    ],
    "wof:name":"Harijan Coloney",
    "wof:placetype":"neighbourhood",
    "wof:population":158
},
  "geometry": {"coordinates":[81.093839,26.108407],"type":"Point"}
}