{
  "type": "Feature",
  "properties": {
    "iso:country":"IN",
    "ks:ks_name":"Murgabani",
    "ks:ks_pop":155,
    "ks:ks_type":"VILLAGE",
    "name:eng_x_preferred":[
        "Murgabani"
    ],
    "wof:name":"Murgabani",
    "wof:placetype":"locality",
    "wof:population":155
},
  "geometry": {"coordinates":[87.537631,24.121695],"type":"Point"}
}