{
  "type": "Feature",
  "properties": {
    "iso:country":"IN",
    "ks:ks_alt_nam":"Asadull\u0101nagar",
    "ks:ks_name":"Asadullanagar",
    "ks:ks_type":"VILLAGE",
    "name:eng_x_preferred":[
        "Asadullanagar"
    ],
    "name:eng_x_variant":[
        "Asadull\u0101nagar"
    ],
    "wof:name":"Asadullanagar",
    "wof:placetype":"locality"
},
  "geometry": {"coordinates":[77.640162,29.252338],"type":"Point"}
}