{
  "type": "Feature",
  "properties": {
    "iso:country":"IN",
    "ks:ks_name":"Chirubera",
    "ks:ks_pop":80,
    "ks:ks_type":"HABITATION",
    "name:eng_x_preferred":[
        "Chirubera"
    ],
    "wof:name":"Chirubera",
    "wof:placetype":"locality",
    "wof:population":80
},
  "geometry": {"coordinates":[85.744114,22.973146],"type":"Point"}
}