{
  "type": "Feature",
  "properties": {
    "gn:admin1_code":"10.0",
    "gn:admin2_code":"70.0",
    "gn:asciiname":"Kurali",
    "gn:country_code":"IN",
    "gn:dem":310,
    "gn:feature_class":"P",
    "gn:feature_code":"PPL",
    "gn:name":"Kur\u0101li",
    "gn:population":0,
    "gn:timezone":"Asia/Kolkata",
    "iso:country":"IN",
    "name:ben_x_preferred":[
        "\u0995\u09c1\u09b0\u09bf\u09b2\u09bf"
    ],
    "name:bpy_x_preferred":[
        "\u0995\u09c1\u09b0\u09bf\u09b2\u09bf"
    ],
    "name:ceb_x_preferred":[
        "K\u016br\u0101li"
    ],
    "name:hin_x_preferred":[
        "\u0915\u0941\u0930\u093e\u0932\u0940"
    ],
    "name:ita_x_preferred":[
        "Kurali"
    ],
    "name:msa_x_preferred":[
        "Kurali"
    ],
    "name:new_x_preferred":[
        "\u0915\u0941\u0930\u093e\u0932\u0940"
    ],
    "name:nld_x_preferred":[
        "Kurali"
    ],
    "name:por_x_preferred":[
        "Kurali"
    ],
    "name:spa_x_preferred":[
        "Kurali"
    ],
    "name:swe_x_preferred":[
        "K\u016br\u0101li"
    ],
    "name:tam_x_preferred":[
        "\u0b95\u0bc1\u0bb0\u0bb3\u0bbf"
    ],
    "name:vie_x_preferred":[
        "Kurali"
    ],
    "name:zho_x_preferred":[
        "\u5e93\u62c9\u5229"
    ],
    "wof:name":"Kurali",
    "wof:placetype":"locality"
},
  "geometry": {"coordinates":[77.08136999999998,30.41344],"type":"Point"}
}