{
  "type": "Feature",
  "properties": {
    "iso:country":"IN",
    "ks:ks_name":"Brahman Tola",
    "ks:ks_pop":145,
    "ks:ks_type":"HABITATION",
    "name:eng_x_preferred":[
        "Brahman Tola"
    ],
    "wof:name":"Brahman Tola",
    "wof:placetype":"locality",
    "wof:population":145
},
  "geometry": {"coordinates":[86.37402,26.384289],"type":"Point"}
}