{
  "type": "Feature",
  "properties": {
    "iso:country":"IN",
    "ks:ks_name":"Thangar",
    "ks:ks_pop":36,
    "ks:ks_type":"VILLAGE",
    "name:eng_x_preferred":[
        "Thangar"
    ],
    "wof:name":"Thangar",
    "wof:placetype":"locality",
    "wof:population":36
},
  "geometry": {"coordinates":[78.678686,30.028389],"type":"Point"}
}