{
  "type": "Feature",
  "properties": {
    "iso:country":"IN",
    "ks:ks_name":"Kandhapali 2",
    "ks:ks_pop":57,
    "ks:ks_type":"HABITATION",
    "name:eng_x_preferred":[
        "Kandhapali 2"
    ],
    "wof:name":"Kandhapali 2",
    "wof:placetype":"locality",
    "wof:population":57
},
  "geometry": {"coordinates":[83.622393,20.858931],"type":"Point"}
}