{
  "type": "Feature",
  "properties": {
    "iso:country":"IN",
    "ks:ks_alt_nam":"BANDGAR VASTI",
    "ks:ks_name":"Bandgar Vasti",
    "ks:ks_pop":239,
    "ks:ks_type":"HABITATION",
    "name:eng_x_preferred":[
        "Bandgar Vasti"
    ],
    "wof:name":"Bandgar Vasti",
    "wof:placetype":"locality",
    "wof:population":239
},
  "geometry": {"coordinates":[74.76996,16.875633],"type":"Point"}
}