{
  "type": "Feature",
  "properties": {
    "iso:country":"IN",
    "ks:ks_alt_nam":"salaiya",
    "ks:ks_name":"Salaiya",
    "ks:ks_pop":389,
    "ks:ks_type":"HABITATION",
    "name:eng_x_preferred":[
        "Salaiya"
    ],
    "wof:name":"Salaiya",
    "wof:placetype":"locality",
    "wof:population":389
},
  "geometry": {"coordinates":[86.760772,24.607676],"type":"Point"}
}