{
  "type": "Feature",
  "properties": {
    "iso:country":"IN",
    "ks:ks_name":"Subbanaidu Kandriga",
    "ks:ks_pop":131,
    "ks:ks_type":"HABITATION",
    "name:eng_x_preferred":[
        "Subbanaidu Kandriga"
    ],
    "wof:name":"Subbanaidu Kandriga",
    "wof:placetype":"locality",
    "wof:population":131
},
  "geometry": {"coordinates":[79.926098,13.545766],"type":"Point"}
}