{
  "type": "Feature",
  "properties": {
    "iso:country":"IN",
    "ks:ks_name":"Lalyatanda",
    "ks:ks_pop":62,
    "ks:ks_type":"HABITATION",
    "name:eng_x_preferred":[
        "Lalyatanda"
    ],
    "wof:name":"Lalyatanda",
    "wof:placetype":"locality",
    "wof:population":62
},
  "geometry": {"coordinates":[78.087487,16.692676],"type":"Point"}
}