{
  "type": "Feature",
  "properties": {
    "iso:country":"IN",
    "ks:ks_name":"Ulubari",
    "ks:ks_pop":2083,
    "ks:ks_type":"VILLAGE",
    "ks:ks_uagg_main":0,
    "name:eng_x_preferred":[
        "Ulubari"
    ],
    "wof:name":"Ulubari",
    "wof:placetype":"neighbourhood",
    "wof:population":2083
},
  "geometry": {"coordinates":[92.14904199999999,26.594643],"type":"Point"}
}