{
  "type": "Feature",
  "properties": {
    "gn:admin1_code":"12.0",
    "gn:asciiname":"Kachal",
    "gn:country_code":"IN",
    "gn:dem":2679,
    "gn:feature_class":"P",
    "gn:feature_code":"PPL",
    "gn:name":"Kachal",
    "gn:population":0,
    "gn:timezone":"Asia/Kolkata",
    "iso:country":"IN",
    "wof:name":"Kachal",
    "wof:placetype":"locality"
},
  "geometry": {"coordinates":[73.97463,34.66001],"type":"Point"}
}