{
  "type": "Feature",
  "properties": {
    "iso:country":"IN",
    "ks:ks_alt_nam":"kumalan kuttai coloni",
    "ks:ks_name":"Kumalan Kuttai Coloni",
    "ks:ks_pop":100,
    "ks:ks_type":"HABITATION",
    "name:eng_x_preferred":[
        "Kumalan Kuttai Coloni"
    ],
    "wof:name":"Kumalan Kuttai Coloni",
    "wof:placetype":"locality",
    "wof:population":100
},
  "geometry": {"coordinates":[79.508922,12.3335],"type":"Point"}
}