{
  "type": "Feature",
  "properties": {
    "iso:country":"IN",
    "ks:ks_name":"Garoul",
    "ks:ks_pop":4709,
    "ks:ks_type":"HABITATION",
    "name:eng_x_preferred":[
        "Garoul"
    ],
    "wof:name":"Garoul",
    "wof:placetype":"locality",
    "wof:population":4709
},
  "geometry": {"coordinates":[86.230023,26.133869],"type":"Point"}
}