{
  "type": "Feature",
  "properties": {
    "iso:country":"IN",
    "ks:ks_name":"Majhtoliya-2",
    "ks:ks_pop":22,
    "ks:ks_type":"VILLAGE",
    "name:eng_x_preferred":[
        "Majhtoliya-2"
    ],
    "wof:name":"Majhtoliya-2",
    "wof:placetype":"locality",
    "wof:population":22
},
  "geometry": {"coordinates":[81.95100100000001,23.089426],"type":"Point"}
}