{
  "type": "Feature",
  "properties": {
    "gn:admin1_code":"37.0",
    "gn:admin2_code":"414.0",
    "gn:asciiname":"Bhanpur",
    "gn:country_code":"IN",
    "gn:dem":449,
    "gn:feature_class":"P",
    "gn:feature_code":"PPL",
    "gn:name":"Bhanpur",
    "gn:population":0,
    "gn:timezone":"Asia/Kolkata",
    "iso:country":"IN",
    "ks:ks_name":"Bahanpur",
    "ks:ks_pop":548,
    "ks:ks_type":"VILLAGE",
    "name:eng_x_preferred":[
        "Bahanpur"
    ],
    "name:eng_x_variant":[
        "Bhanpur"
    ],
    "wof:name":"Bahanpur",
    "wof:placetype":"locality",
    "wof:population":548
},
  "geometry": {"coordinates":[81.494851,18.986055],"type":"Point"}
}