{
  "type": "Feature",
  "properties": {
    "iso:country":"IN",
    "ks:ks_name":"Fakeer Shah",
    "ks:ks_pop":177,
    "ks:ks_type":"HABITATION",
    "ks:ks_uagg_main":0,
    "name:eng_x_preferred":[
        "Fakeer Shah"
    ],
    "wof:name":"Fakeer Shah",
    "wof:placetype":"neighbourhood",
    "wof:population":177
},
  "geometry": {"coordinates":[81.69473499999999,25.977037],"type":"Point"}
}