{
  "type": "Feature",
  "properties": {
    "iso:country":"IN",
    "ks:ks_name":"Manalvayal",
    "ks:ks_pop":440,
    "ks:ks_type":"HABITATION",
    "name:eng_x_preferred":[
        "Manalvayal"
    ],
    "wof:name":"Manalvayal",
    "wof:placetype":"locality",
    "wof:population":440
},
  "geometry": {"coordinates":[76.142163,11.681774],"type":"Point"}
}