{
  "type": "Feature",
  "properties": {
    "iso:country":"IN",
    "ks:ks_name":"Gram Panchayat",
    "ks:ks_pop":219,
    "ks:ks_type":"HABITATION",
    "name:eng_x_preferred":[
        "Gram Panchayat"
    ],
    "wof:name":"Gram Panchayat",
    "wof:placetype":"locality",
    "wof:population":219
},
  "geometry": {"coordinates":[74.318806,21.525389],"type":"Point"}
}