{
  "type": "Feature",
  "properties": {
    "iso:country":"IN",
    "ks:ks_name":"Jasapar",
    "ks:ks_pop":2659,
    "ks:ks_type":"VILLAGE",
    "ks:ks_uagg_main":0,
    "name:eng_x_preferred":[
        "Jasapar"
    ],
    "wof:name":"Jasapar",
    "wof:placetype":"neighbourhood",
    "wof:population":2659
},
  "geometry": {"coordinates":[70.49336099999999,21.887139],"type":"Point"}
}