{
  "type": "Feature",
  "properties": {
    "gn:admin1_code":"36",
    "gn:admin2_code":"193.0",
    "gn:asciiname":"Saryan Bagdeora",
    "gn:country_code":"IN",
    "gn:dem":72,
    "gn:feature_class":"P",
    "gn:feature_code":"PPL",
    "gn:name":"Sary\u0101n Bagdeor\u0101",
    "gn:population":0,
    "gn:timezone":"Asia/Kolkata",
    "iso:country":"IN",
    "wof:name":"Saryan Bagdeora",
    "wof:placetype":"locality"
},
  "geometry": {"coordinates":[83.93295999999999,25.93573],"type":"Point"}
}