{
  "type": "Feature",
  "properties": {
    "gn:admin1_code":"36",
    "gn:admin2_code":"134.0",
    "gn:asciiname":"Mukrabpur",
    "gn:country_code":"IN",
    "gn:dem":238,
    "gn:feature_class":"P",
    "gn:feature_code":"PPL",
    "gn:name":"Mukrabpur",
    "gn:population":0,
    "gn:timezone":"Asia/Kolkata",
    "iso:country":"IN",
    "ks:ks_name":"Mukrabpur",
    "ks:ks_pop":981,
    "ks:ks_type":"VILLAGE",
    "ks:ks_uagg_main":0,
    "name:eng_x_preferred":[
        "Mukrabpur"
    ],
    "wof:name":"Mukrabpur",
    "wof:placetype":"neighbourhood",
    "wof:population":981
},
  "geometry": {"coordinates":[78.39929100000001,29.307474],"type":"Point"}
}