{
  "type": "Feature",
  "properties": {
    "gn:admin1_code":"12",
    "gn:admin2_code":"3.0",
    "gn:asciiname":"Tiricha",
    "gn:country_code":"IN",
    "gn:dem":3227,
    "gn:feature_class":"P",
    "gn:feature_code":"PPL",
    "gn:name":"Tiricha",
    "gn:population":0,
    "gn:timezone":"Asia/Kolkata",
    "iso:country":"IN",
    "name:und_x_variant":[
        "Thiritsha",
        "Tiricha"
    ],
    "wof:name":"Tiricha",
    "wof:placetype":"locality"
},
  "geometry": {"coordinates":[77.57111999999999,34.73629],"type":"Point"}
}