{
  "type": "Feature",
  "properties": {
    "iso:country":"IN",
    "ks:ks_name":"Krishna Ballabhpur",
    "ks:ks_pop":951,
    "ks:ks_type":"VILLAGE",
    "name:eng_x_preferred":[
        "Krishna Ballabhpur"
    ],
    "wof:name":"Krishna Ballabhpur",
    "wof:placetype":"locality",
    "wof:population":951
},
  "geometry": {"coordinates":[87.850331,22.8372],"type":"Point"}
}