{
  "type": "Feature",
  "properties": {
    "gn:admin1_code":"2",
    "gn:admin2_code":"544.0",
    "gn:asciiname":"Krishnapuram",
    "gn:country_code":"IN",
    "gn:dem":810,
    "gn:feature_class":"P",
    "gn:feature_code":"PPL",
    "gn:name":"Krishn\u0101puram",
    "gn:population":0,
    "gn:timezone":"Asia/Kolkata",
    "iso:country":"IN",
    "ks:ks_alt_nam":"Krishn\u0101puram",
    "ks:ks_name":"Krishnapuram",
    "ks:ks_pop":270,
    "ks:ks_type":"VILLAGE",
    "name:eng_x_preferred":[
        "Krishnapuram"
    ],
    "name:eng_x_variant":[
        "Krishn\u0101puram"
    ],
    "wof:name":"Krishnapuram",
    "wof:placetype":"locality",
    "wof:population":270
},
  "geometry": {"coordinates":[82.48584200000001,17.885952],"type":"Point"}
}