{
  "type": "Feature",
  "properties": {
    "iso:country":"IN",
    "ks:ks_name":"Lal Purwa",
    "ks:ks_pop":100,
    "ks:ks_type":"HABITATION",
    "name:eng_x_preferred":[
        "Lal Purwa"
    ],
    "wof:name":"Lal Purwa",
    "wof:placetype":"locality",
    "wof:population":100
},
  "geometry": {"coordinates":[81.79481699999999,27.055186],"type":"Point"}
}