{
  "type": "Feature",
  "properties": {
    "gn:admin1_code":"36",
    "gn:admin2_code":"186.0",
    "gn:asciiname":"Lahrauli Pande",
    "gn:country_code":"IN",
    "gn:dem":85,
    "gn:feature_class":"P",
    "gn:feature_code":"PPL",
    "gn:name":"Lahrauli P\u0101nde",
    "gn:population":0,
    "gn:timezone":"Asia/Kolkata",
    "iso:country":"IN",
    "wof:name":"Lahrauli Pande",
    "wof:placetype":"locality"
},
  "geometry": {"coordinates":[83.10689000000001,26.98838],"type":"Point"}
}