{
  "type": "Feature",
  "properties": {
    "iso:country":"IN",
    "ks:ks_name":"Nathamadipatti",
    "ks:ks_pop":1851,
    "ks:ks_type":"HABITATION",
    "name:eng_x_preferred":[
        "Nathamadipatti"
    ],
    "wof:name":"Nathamadipatti",
    "wof:placetype":"locality",
    "wof:population":1851
},
  "geometry": {"coordinates":[78.73755,10.764185],"type":"Point"}
}