{
  "type": "Feature",
  "properties": {
    "iso:country":"IN",
    "ks:ks_name":"Pathan Purwa",
    "ks:ks_pop":195,
    "ks:ks_type":"HABITATION",
    "name:eng_x_preferred":[
        "Pathan Purwa"
    ],
    "wof:name":"Pathan Purwa",
    "wof:placetype":"locality",
    "wof:population":195
},
  "geometry": {"coordinates":[82.034863,27.099682],"type":"Point"}
}