{
  "type": "Feature",
  "properties": {
    "iso:country":"IN",
    "ks:ks_name":"Gollarahatti",
    "ks:ks_pop":26,
    "ks:ks_type":"HABITATION",
    "name:eng_x_preferred":[
        "Gollarahatti"
    ],
    "wof:name":"Gollarahatti",
    "wof:placetype":"locality",
    "wof:population":26
},
  "geometry": {"coordinates":[76.61363900000001,13.683848],"type":"Point"}
}