{
  "type": "Feature",
  "properties": {
    "iso:country":"IN",
    "ks:ks_name":"Karkaram",
    "ks:ks_pop":139,
    "ks:ks_type":"VILLAGE",
    "name:eng_x_preferred":[
        "Karkaram"
    ],
    "wof:name":"Karkaram",
    "wof:placetype":"locality",
    "wof:population":139
},
  "geometry": {"coordinates":[87.652148,24.945999],"type":"Point"}
}