{
  "type": "Feature",
  "properties": {
    "gn:admin1_code":"10.0",
    "gn:admin2_code":"78.0",
    "gn:asciiname":"Muhammadpur",
    "gn:country_code":"IN",
    "gn:dem":219,
    "gn:feature_class":"P",
    "gn:feature_code":"PPL",
    "gn:name":"Muhammadpur",
    "gn:population":0,
    "gn:timezone":"Asia/Kolkata",
    "iso:country":"IN",
    "wof:name":"Muhammadpur",
    "wof:placetype":"locality"
},
  "geometry": {"coordinates":[75.56589,29.46],"type":"Point"}
}