{
  "type": "Feature",
  "properties": {
    "gn:admin1_code":"37",
    "gn:admin2_code":"404.0",
    "gn:asciiname":"Pandripani",
    "gn:country_code":"IN",
    "gn:dem":534,
    "gn:feature_class":"P",
    "gn:feature_code":"PPL",
    "gn:name":"Pandr\u012bp\u0101ni",
    "gn:population":0,
    "gn:timezone":"Asia/Kolkata",
    "iso:country":"IN",
    "ks:ks_alt_nam":"Pandr\u012bp\u0101ni",
    "ks:ks_name":"Pandripani",
    "ks:ks_type":"VILLAGE",
    "name:eng_x_preferred":[
        "Pandripani"
    ],
    "name:eng_x_variant":[
        "Pandr\u012bp\u0101ni"
    ],
    "wof:name":"Pandripani",
    "wof:placetype":"locality"
},
  "geometry": {"coordinates":[82.187996,22.777025],"type":"Point"}
}