{
  "type": "Feature",
  "properties": {
    "gn:admin1_code":"16",
    "gn:admin2_code":"499.0",
    "gn:asciiname":"Manjardi",
    "gn:country_code":"IN",
    "gn:dem":181,
    "gn:feature_class":"P",
    "gn:feature_code":"PPL",
    "gn:name":"M\u0101njardi",
    "gn:population":0,
    "gn:timezone":"Asia/Kolkata",
    "iso:country":"IN",
    "ks:ks_alt_nam":"M\u0101njardi",
    "ks:ks_name":"Manjardi",
    "ks:ks_pop":664,
    "ks:ks_type":"VILLAGE",
    "ks:ks_uagg_main":0,
    "name:eng_x_preferred":[
        "Manjardi"
    ],
    "name:eng_x_variant":[
        "M\u0101njardi"
    ],
    "wof:name":"Manjardi",
    "wof:placetype":"neighbourhood",
    "wof:population":664
},
  "geometry": {"coordinates":[75.138842,21.082418],"type":"Point"}
}