{
  "type": "Feature",
  "properties": {
    "iso:country":"IN",
    "ks:ks_name":"Talaharganda",
    "ks:ks_pop":31,
    "ks:ks_type":"VILLAGE",
    "name:eng_x_preferred":[
        "Talaharganda"
    ],
    "wof:name":"Talaharganda",
    "wof:placetype":"locality",
    "wof:population":31
},
  "geometry": {"coordinates":[82.57477299999999,18.45999],"type":"Point"}
}