{
  "type": "Feature",
  "properties": {
    "iso:country":"IN",
    "ks:ks_name":"Ezaruddin Para",
    "ks:ks_pop":600,
    "ks:ks_type":"HABITATION",
    "name:eng_x_preferred":[
        "Ezaruddin Para"
    ],
    "wof:name":"Ezaruddin Para",
    "wof:placetype":"locality",
    "wof:population":600
},
  "geometry": {"coordinates":[88.716752,22.258104],"type":"Point"}
}