{
  "type": "Feature",
  "properties": {
    "gn:admin1_code":"24.0",
    "gn:admin2_code":"111",
    "gn:asciiname":"Baijupurohit ki Dhani",
    "gn:country_code":"IN",
    "gn:dem":315,
    "gn:feature_class":"P",
    "gn:feature_code":"PPL",
    "gn:name":"Baijupurohit ki Dh\u0101ni",
    "gn:population":0,
    "gn:timezone":"Asia/Kolkata",
    "iso:country":"IN",
    "name:und_x_variant":[
        "Baijupurohit ki Dh\u0101ni",
        "Dh\u0101ni"
    ],
    "wof:name":"Baijupurohit ki Dhani",
    "wof:placetype":"locality"
},
  "geometry": {"coordinates":[74.83444,28.05902],"type":"Point"}
}