{
  "type": "Feature",
  "properties": {
    "gn:admin1_code":"24.0",
    "gn:admin2_code":"124.0",
    "gn:asciiname":"Karori",
    "gn:country_code":"IN",
    "gn:dem":311,
    "gn:feature_class":"P",
    "gn:feature_code":"PPL",
    "gn:name":"Karori",
    "gn:population":0,
    "gn:timezone":"Asia/Kolkata",
    "iso:country":"IN",
    "name:hye_x_preferred":[
        "\u053f\u0561\u057c\u0578\u0580\u056b"
    ],
    "wof:name":"Karori",
    "wof:placetype":"locality"
},
  "geometry": {"coordinates":[73.60240999999998,23.83094],"type":"Point"}
}