{
  "type": "Feature",
  "properties": {
    "iso:country":"IN",
    "ks:ks_name":"Nagari",
    "ks:ks_pop":274,
    "ks:ks_type":"VILLAGE",
    "name:eng_x_preferred":[
        "Nagari"
    ],
    "wof:name":"Nagari",
    "wof:placetype":"locality",
    "wof:population":274
},
  "geometry": {"coordinates":[81.851249,23.551508],"type":"Point"}
}