{
  "type": "Feature",
  "properties": {
    "iso:country":"IN",
    "ks:ks_name":"Kovoor",
    "ks:ks_pop":1674,
    "ks:ks_type":"HABITATION",
    "name:eng_x_preferred":[
        "Kovoor"
    ],
    "wof:name":"Kovoor",
    "wof:placetype":"locality",
    "wof:population":1674
},
  "geometry": {"coordinates":[75.51054499999999,11.958589],"type":"Point"}
}