{
  "type": "Feature",
  "properties": {
    "iso:country":"IN",
    "ks:ks_name":"Puttarira",
    "ks:ks_pop":110,
    "ks:ks_type":"HABITATION",
    "name:eng_x_preferred":[
        "Puttarira"
    ],
    "wof:name":"Puttarira",
    "wof:placetype":"locality",
    "wof:population":110
},
  "geometry": {"coordinates":[75.825,12.365278],"type":"Point"}
}