{
  "type": "Feature",
  "properties": {
    "iso:country":"IN",
    "ks:ks_name":"Ellikkadu Start",
    "ks:ks_pop":360,
    "ks:ks_type":"HABITATION",
    "name:eng_x_preferred":[
        "Ellikkadu Start"
    ],
    "wof:name":"Ellikkadu Start",
    "wof:placetype":"locality",
    "wof:population":360
},
  "geometry": {"coordinates":[76.17546,10.376201],"type":"Point"}
}