{
  "type": "Feature",
  "properties": {
    "iso:country":"IN",
    "ks:ks_alt_nam":"malankara",
    "ks:ks_name":"Malankara",
    "ks:ks_pop":650,
    "ks:ks_type":"HABITATION",
    "name:eng_x_preferred":[
        "Malankara"
    ],
    "wof:name":"Malankara",
    "wof:placetype":"locality",
    "wof:population":650
},
  "geometry": {"coordinates":[76.732974,9.86498],"type":"Point"}
}