{
  "type": "Feature",
  "properties": {
    "gn:admin1_code":"25.0",
    "gn:admin2_code":"632.0",
    "gn:asciiname":"Puttur",
    "gn:country_code":"IN",
    "gn:dem":361,
    "gn:feature_class":"P",
    "gn:feature_code":"PPL",
    "gn:name":"Putt\u016br",
    "gn:population":0,
    "gn:timezone":"Asia/Kolkata",
    "iso:country":"IN",
    "name:ceb_x_preferred":[
        "Puttur"
    ],
    "name:deu_x_preferred":[
        "Puttur"
    ],
    "name:ita_x_preferred":[
        "Puttur"
    ],
    "name:mal_x_preferred":[
        "\u0d2a\u0d41\u0d24\u0d4d\u0d24\u0d42\u0d7c"
    ],
    "name:nld_x_preferred":[
        "Puttur"
    ],
    "name:pam_x_preferred":[
        "Puttur"
    ],
    "name:swe_x_preferred":[
        "Puttur"
    ],
    "name:vie_x_preferred":[
        "Puttur"
    ],
    "wof:name":"Puttur",
    "wof:placetype":"locality"
},
  "geometry": {"coordinates":[77.01763000000003,11.23406],"type":"Point"}
}