{
  "type": "Feature",
  "properties": {
    "gn:admin1_code":"35.0",
    "gn:admin2_code":"437.0",
    "gn:asciiname":"Sutaripura",
    "gn:country_code":"IN",
    "gn:dem":328,
    "gn:feature_class":"P",
    "gn:feature_code":"PPL",
    "gn:name":"Sut\u0101r\u012bpura",
    "gn:population":0,
    "gn:timezone":"Asia/Kolkata",
    "iso:country":"IN",
    "ks:ks_alt_nam":"Sut\u0101r\u012bpura",
    "ks:ks_name":"Sutaripura",
    "ks:ks_pop":522,
    "ks:ks_type":"VILLAGE",
    "name:eng_x_preferred":[
        "Sutaripura"
    ],
    "name:eng_x_variant":[
        "Sut\u0101r\u012bpura"
    ],
    "wof:name":"Sutaripura",
    "wof:placetype":"locality",
    "wof:population":522
},
  "geometry": {"coordinates":[76.417231,22.539972],"type":"Point"}
}