{
  "type": "Feature",
  "properties": {
    "gn:admin1_code":"36.0",
    "gn:admin2_code":"142.0",
    "gn:asciiname":"Ramgrh",
    "gn:country_code":"IN",
    "gn:dem":209,
    "gn:feature_class":"P",
    "gn:feature_code":"PPL",
    "gn:name":"R\u0101mgrh",
    "gn:population":0,
    "gn:timezone":"Asia/Kolkata",
    "iso:country":"IN",
    "wof:name":"Ramgrh",
    "wof:placetype":"locality"
},
  "geometry": {"coordinates":[77.98425,28.52447],"type":"Point"}
}