{
  "type": "Feature",
  "properties": {
    "iso:country":"IN",
    "ks:ks_name":"Thamba Faliya",
    "ks:ks_pop":264,
    "ks:ks_type":"HABITATION",
    "name:eng_x_preferred":[
        "Thamba Faliya"
    ],
    "wof:name":"Thamba Faliya",
    "wof:placetype":"locality",
    "wof:population":264
},
  "geometry": {"coordinates":[73.71487,23.095393],"type":"Point"}
}