{
  "type": "Feature",
  "properties": {
    "iso:country":"IN",
    "ks:ks_name":"Chore Kharak",
    "ks:ks_pop":30,
    "ks:ks_type":"HABITATION",
    "name:eng_x_preferred":[
        "Chore Kharak"
    ],
    "wof:name":"Chore Kharak",
    "wof:placetype":"locality",
    "wof:population":30
},
  "geometry": {"coordinates":[79.882729,30.007025],"type":"Point"}
}