{
  "type": "Feature",
  "properties": {
    "gn:admin1_code":"11",
    "gn:admin2_code":"23.0",
    "gn:asciiname":"Kuran",
    "gn:country_code":"IN",
    "gn:dem":1152,
    "gn:feature_class":"P",
    "gn:feature_code":"PPL",
    "gn:name":"Kur\u0101n",
    "gn:population":0,
    "gn:timezone":"Asia/Kolkata",
    "iso:country":"IN",
    "name:ceb_x_preferred":[
        "Kuran"
    ],
    "name:fas_x_preferred":[
        "\u06a9\u0648\u0631\u0646"
    ],
    "name:swe_x_preferred":[
        "Kuran"
    ],
    "wof:name":"Kuran",
    "wof:placetype":"locality"
},
  "geometry": {"coordinates":[76.17612,32.49365],"type":"Point"}
}