{
  "type": "Feature",
  "properties": {
    "gn:admin1_code":"36.0",
    "gn:admin2_code":"152.0",
    "gn:asciiname":"Dilawarpur Muttasil Ladhaula",
    "gn:country_code":"IN",
    "gn:dem":163,
    "gn:feature_class":"P",
    "gn:feature_code":"PPL",
    "gn:name":"Dil\u0101warpur Muttasil Ladhaula",
    "gn:population":0,
    "gn:timezone":"Asia/Kolkata",
    "iso:country":"IN",
    "wof:name":"Dilawarpur Muttasil Ladhaula",
    "wof:placetype":"locality"
},
  "geometry": {"coordinates":[79.94776,28.06539],"type":"Point"}
}