{
  "type": "Feature",
  "properties": {
    "gn:admin1_code":"36",
    "gn:admin2_code":"176.0",
    "gn:asciiname":"Jainpur",
    "gn:country_code":"IN",
    "gn:dem":123,
    "gn:feature_class":"P",
    "gn:feature_code":"PPL",
    "gn:name":"Jainpur",
    "gn:population":0,
    "gn:timezone":"Asia/Kolkata",
    "iso:country":"IN",
    "name:pan_x_preferred":[
        "\u0a1c\u0a48\u0a28\u0a2a\u0a41\u0a30"
    ],
    "wof:name":"Jainpur",
    "wof:placetype":"locality"
},
  "geometry": {"coordinates":[81.29071999999999,26.87332],"type":"Point"}
}