{
  "type": "Feature",
  "properties": {
    "iso:country":"IN",
    "ks:ks_name":"Aurjanr",
    "ks:ks_pop":25,
    "ks:ks_type":"VILLAGE",
    "name:eng_x_preferred":[
        "Aurjanr"
    ],
    "wof:name":"Aurjanr",
    "wof:placetype":"locality",
    "wof:population":25
},
  "geometry": {"coordinates":[87.54682,25.141042],"type":"Point"}
}