{
  "type": "Feature",
  "properties": {
    "iso:country":"IN",
    "ks:ks_name":"Mukhia Tola",
    "ks:ks_pop":181,
    "ks:ks_type":"HABITATION",
    "ks:ks_uagg_main":0,
    "name:eng_x_preferred":[
        "Mukhia Tola"
    ],
    "wof:name":"Mukhia Tola",
    "wof:placetype":"neighbourhood",
    "wof:population":181
},
  "geometry": {"coordinates":[87.58777000000001,25.93174],"type":"Point"}
}