{
  "type": "Feature",
  "properties": {
    "iso:country":"IN",
    "ks:ks_name":"Santhal Tola Lower",
    "ks:ks_pop":130,
    "ks:ks_type":"HABITATION",
    "name:eng_x_preferred":[
        "Santhal Tola Lower"
    ],
    "wof:name":"Santhal Tola Lower",
    "wof:placetype":"locality",
    "wof:population":130
},
  "geometry": {"coordinates":[86.477531,24.767564],"type":"Point"}
}