{
  "type": "Feature",
  "properties": {
    "gn:admin1_code":"34.0",
    "gn:admin2_code":"239.0",
    "gn:asciiname":"Nawabganj",
    "gn:country_code":"IN",
    "gn:dem":75,
    "gn:feature_class":"P",
    "gn:feature_code":"PPL",
    "gn:name":"Naw\u0101bganj",
    "gn:population":0,
    "gn:timezone":"Asia/Kolkata",
    "iso:country":"IN",
    "name:bpy_x_preferred":[
        "\u09a8\u09f1\u09be\u09ac\u0997\u099e\u09cd\u099c"
    ],
    "name:cat_x_preferred":[
        "Nawabganj"
    ],
    "name:ceb_x_preferred":[
        "Nawabganj"
    ],
    "name:ita_x_preferred":[
        "Nawabganj"
    ],
    "name:new_x_preferred":[
        "\u0928\u0935\u093e\u092c\u0917\u091e\u094d\u091c"
    ],
    "name:nld_x_preferred":[
        "Nawabganj"
    ],
    "name:pol_x_preferred":[
        "Nawabganj"
    ],
    "name:rus_x_preferred":[
        "\u041d\u0430\u0432\u0430\u0431\u0433\u0430\u043d\u0434\u0436"
    ],
    "name:swe_x_preferred":[
        "Nawabganj"
    ],
    "wof:name":"Nawabganj",
    "wof:placetype":"locality"
},
  "geometry": {"coordinates":[85.20600999999998,25.07743],"type":"Point"}
}