{
  "type": "Feature",
  "properties": {
    "iso:country":"IN",
    "ks:ks_name":"Bhaliaput",
    "ks:ks_pop":306,
    "ks:ks_type":"VILLAGE",
    "name:eng_x_preferred":[
        "Bhaliaput"
    ],
    "wof:name":"Bhaliaput",
    "wof:placetype":"locality",
    "wof:population":306
},
  "geometry": {"coordinates":[83.135683,18.828753],"type":"Point"}
}