{
  "type": "Feature",
  "properties": {
    "gn:admin1_code":"39.0",
    "gn:admin2_code":"64.0",
    "gn:asciiname":"Chapdola",
    "gn:country_code":"IN",
    "gn:dem":1520,
    "gn:feature_class":"P",
    "gn:feature_code":"PPL",
    "gn:name":"Chapdola",
    "gn:population":0,
    "gn:timezone":"Asia/Kolkata",
    "iso:country":"IN",
    "wof:name":"Chapdola",
    "wof:placetype":"locality"
},
  "geometry": {"coordinates":[79.94365999999999,29.566],"type":"Point"}
}