{
  "type": "Feature",
  "properties": {
    "gn:admin1_code":"40.0",
    "gn:admin2_code":"539",
    "gn:asciiname":"Edularepaku",
    "gn:country_code":"IN",
    "gn:dem":347,
    "gn:feature_class":"P",
    "gn:feature_code":"PPL",
    "gn:name":"Ed\u016blarep\u0101ku",
    "gn:population":0,
    "gn:timezone":"Asia/Kolkata",
    "iso:country":"IN",
    "wof:name":"Edularepaku",
    "wof:placetype":"neighbourhood"
},
  "geometry": {"coordinates":[79.00033000000001,17.41878],"type":"Point"}
}