{
  "type": "Feature",
  "properties": {
    "iso:country":"IN",
    "ks:ks_name":"Kargaon",
    "ks:ks_pop":316,
    "ks:ks_type":"VILLAGE",
    "name:eng_x_preferred":[
        "Kargaon"
    ],
    "wof:name":"Kargaon",
    "wof:placetype":"locality",
    "wof:population":316
},
  "geometry": {"coordinates":[73.790693,17.6564],"type":"Point"}
}