{
  "type": "Feature",
  "properties": {
    "iso:country":"IN",
    "ks:ks_name":"Bangaon",
    "ks:ks_pop":237,
    "ks:ks_type":"VILLAGE",
    "name:eng_x_preferred":[
        "Bangaon"
    ],
    "wof:name":"Bangaon",
    "wof:placetype":"locality",
    "wof:population":237
},
  "geometry": {"coordinates":[85.101832,23.529932],"type":"Point"}
}