{
  "type": "Feature",
  "properties": {
    "iso:country":"IN",
    "ks:ks_name":"Jarlangi",
    "ks:ks_pop":22,
    "ks:ks_type":"VILLAGE",
    "name:eng_x_preferred":[
        "Jarlangi"
    ],
    "wof:name":"Jarlangi",
    "wof:placetype":"locality",
    "wof:population":22
},
  "geometry": {"coordinates":[83.069816,18.376308],"type":"Point"}
}