{
  "type": "Feature",
  "properties": {
    "iso:country":"IN",
    "ks:ks_alt_nam":"Ramlanaik thanda",
    "ks:ks_name":"Ramlanaik Thanda",
    "ks:ks_pop":60,
    "ks:ks_type":"HABITATION",
    "name:eng_x_preferred":[
        "Ramlanaik Thanda"
    ],
    "wof:name":"Ramlanaik Thanda",
    "wof:placetype":"locality",
    "wof:population":60
},
  "geometry": {"coordinates":[78.09052800000001,18.563396],"type":"Point"}
}