{
  "type": "Feature",
  "properties": {
    "iso:country":"IN",
    "ks:ks_alt_nam":"kobiaasai",
    "ks:ks_name":"Kobiaasai",
    "ks:ks_pop":144,
    "ks:ks_type":"HABITATION",
    "name:eng_x_preferred":[
        "Kobiaasai"
    ],
    "wof:name":"Kobiaasai",
    "wof:placetype":"locality",
    "wof:population":144
},
  "geometry": {"coordinates":[85.79149200000001,22.056882],"type":"Point"}
}