{
  "type": "Feature",
  "properties": {
    "iso:country":"IN",
    "ks:ks_name":"Chiwtahiya",
    "ks:ks_pop":823,
    "ks:ks_type":"HABITATION",
    "name:eng_x_preferred":[
        "Chiwtahiya"
    ],
    "wof:name":"Chiwtahiya",
    "wof:placetype":"locality",
    "wof:population":823
},
  "geometry": {"coordinates":[83.05837699999999,24.477762],"type":"Point"}
}