{
  "type": "Feature",
  "properties": {
    "iso:country":"IN",
    "ks:ks_name":"Chandia",
    "ks:ks_pop":543,
    "ks:ks_type":"HABITATION",
    "name:eng_x_preferred":[
        "Chandia"
    ],
    "wof:name":"Chandia",
    "wof:placetype":"locality",
    "wof:population":543
},
  "geometry": {"coordinates":[86.01298199999999,20.927004],"type":"Point"}
}