{
  "type": "Feature",
  "properties": {
    "iso:country":"IN",
    "ks:ks_alt_nam":"Main\u0101hi",
    "ks:ks_name":"Mainahi",
    "ks:ks_pop":429,
    "ks:ks_type":"VILLAGE",
    "name:eng_x_preferred":[
        "Mainahi"
    ],
    "name:eng_x_variant":[
        "Main\u0101hi"
    ],
    "wof:name":"Mainahi",
    "wof:placetype":"locality",
    "wof:population":429
},
  "geometry": {"coordinates":[86.532515,26.138086],"type":"Point"}
}