{
  "type": "Feature",
  "properties": {
    "iso:country":"IN",
    "ks:ks_name":"Ghadshiwadi",
    "ks:ks_pop":272,
    "ks:ks_type":"HABITATION",
    "name:eng_x_preferred":[
        "Ghadshiwadi"
    ],
    "wof:name":"Ghadshiwadi",
    "wof:placetype":"locality",
    "wof:population":272
},
  "geometry": {"coordinates":[73.46333300000001,17.422222],"type":"Point"}
}