{
  "type": "Feature",
  "properties": {
    "iso:country":"IN",
    "ks:ks_name":"Tepewasti",
    "ks:ks_pop":290,
    "ks:ks_type":"HABITATION",
    "name:eng_x_preferred":[
        "Tepewasti"
    ],
    "wof:name":"Tepewasti",
    "wof:placetype":"locality",
    "wof:population":290
},
  "geometry": {"coordinates":[74.93265,17.19692],"type":"Point"}
}