{
  "type": "Feature",
  "properties": {
    "gn:admin1_code":"36",
    "gn:admin2_code":"191.0",
    "gn:asciiname":"Khatibpur",
    "gn:country_code":"IN",
    "gn:dem":82,
    "gn:feature_class":"P",
    "gn:feature_code":"PPL",
    "gn:name":"Khat\u012bbpur",
    "gn:population":0,
    "gn:timezone":"Asia/Kolkata",
    "iso:country":"IN",
    "ks:ks_alt_nam":"Khat\u012bbpur",
    "ks:ks_name":"Khatibpur",
    "ks:ks_type":"VILLAGE",
    "ks:ks_uagg_main":0,
    "name:eng_x_preferred":[
        "Khatibpur"
    ],
    "name:eng_x_variant":[
        "Khat\u012bbpur"
    ],
    "wof:name":"Khatibpur",
    "wof:placetype":"neighbourhood"
},
  "geometry": {"coordinates":[83.036174,26.043801],"type":"Point"}
}