{
  "type": "Feature",
  "properties": {
    "iso:country":"IN",
    "ks:ks_name":"Surajupur",
    "ks:ks_pop":6,
    "ks:ks_type":"VILLAGE",
    "name:eng_x_preferred":[
        "Surajupur"
    ],
    "wof:name":"Surajupur",
    "wof:placetype":"locality",
    "wof:population":6
},
  "geometry": {"coordinates":[79.704362,27.459722],"type":"Point"}
}