{
  "type": "Feature",
  "properties": {
    "iso:country":"IN",
    "ks:ks_name":"Subidpur",
    "ks:ks_pop":1818,
    "ks:ks_type":"VILLAGE",
    "ks:ks_uagg_main":0,
    "name:eng_x_preferred":[
        "Subidpur"
    ],
    "wof:name":"Subidpur",
    "wof:placetype":"neighbourhood",
    "wof:population":1818
},
  "geometry": {"coordinates":[88.885949,22.8974],"type":"Point"}
}