{
  "type": "Feature",
  "properties": {
    "gn:admin1_code":"39",
    "gn:admin2_code":"61.0",
    "gn:asciiname":"Chaproli",
    "gn:country_code":"IN",
    "gn:dem":1610,
    "gn:feature_class":"P",
    "gn:feature_code":"PPL",
    "gn:name":"Chaproli",
    "gn:population":0,
    "gn:timezone":"Asia/Kolkata",
    "iso:country":"IN",
    "wof:name":"Chaproli",
    "wof:placetype":"locality"
},
  "geometry": {"coordinates":[78.9165,30.01949],"type":"Point"}
}