{
  "type": "Feature",
  "properties": {
    "gn:admin1_code":"11.0",
    "gn:admin2_code":"26.0",
    "gn:asciiname":"Domar",
    "gn:country_code":"IN",
    "gn:dem":1950,
    "gn:feature_class":"P",
    "gn:feature_code":"PPL",
    "gn:name":"Domar",
    "gn:population":0,
    "gn:timezone":"Asia/Kolkata",
    "iso:country":"IN",
    "name:bul_x_preferred":[
        "\u0414\u0443\u043c\u0430\u0440"
    ],
    "name:fra_x_preferred":[
        "Domar"
    ],
    "name:ita_x_preferred":[
        "D\u00f3marr"
    ],
    "name:jpn_x_preferred":[
        "\u30c9\u30fc\u30de\u30eb"
    ],
    "name:msa_x_preferred":[
        "Domar"
    ],
    "name:nno_x_preferred":[
        "Domarr"
    ],
    "name:nor_x_preferred":[
        "Domar"
    ],
    "name:por_x_preferred":[
        "Domar"
    ],
    "name:spa_x_preferred":[
        "Domar"
    ],
    "name:swe_x_preferred":[
        "Domar"
    ],
    "wof:name":"Domar",
    "wof:placetype":"locality"
},
  "geometry": {"coordinates":[77.51245,31.45917],"type":"Point"}
}