{
  "type": "Feature",
  "properties": {
    "gn:admin1_code":"2",
    "gn:admin2_code":"549.0",
    "gn:asciiname":"Anantavaram",
    "gn:country_code":"IN",
    "gn:dem":27,
    "gn:feature_class":"P",
    "gn:feature_code":"PPL",
    "gn:name":"Anantavaram",
    "gn:population":0,
    "gn:timezone":"Asia/Kolkata",
    "iso:country":"IN",
    "wof:name":"Anantavaram",
    "wof:placetype":"locality"
},
  "geometry": {"coordinates":[80.16211,16.02814],"type":"Point"}
}