{
  "type": "Feature",
  "properties": {
    "iso:country":"IN",
    "ks:ks_name":"Hesapiri",
    "ks:ks_pop":115,
    "ks:ks_type":"HABITATION",
    "name:eng_x_preferred":[
        "Hesapiri"
    ],
    "wof:name":"Hesapiri",
    "wof:placetype":"locality",
    "wof:population":115
},
  "geometry": {"coordinates":[85.45837,23.209096],"type":"Point"}
}