{
  "type": "Feature",
  "properties": {
    "gn:admin1_code":"36",
    "gn:admin2_code":"200.0",
    "gn:asciiname":"Baurihwa",
    "gn:country_code":"IN",
    "gn:dem":271,
    "gn:feature_class":"P",
    "gn:feature_code":"PPL",
    "gn:name":"Baurihwa",
    "gn:population":0,
    "gn:timezone":"Asia/Kolkata",
    "iso:country":"IN",
    "ks:ks_name":"Baurihwa",
    "ks:ks_type":"VILLAGE",
    "name:eng_x_preferred":[
        "Baurihwa"
    ],
    "wof:name":"Baurihwa",
    "wof:placetype":"locality"
},
  "geometry": {"coordinates":[83.122327,24.318686],"type":"Point"}
}