{
  "type": "Feature",
  "properties": {
    "gn:admin1_code":"34.0",
    "gn:admin2_code":"207.0",
    "gn:asciiname":"Godhanpur",
    "gn:country_code":"IN",
    "gn:dem":59,
    "gn:feature_class":"P",
    "gn:feature_code":"PPL",
    "gn:name":"Godhanpur",
    "gn:population":0,
    "gn:timezone":"Asia/Kolkata",
    "iso:country":"IN",
    "ks:ks_name":"Godhanpur",
    "ks:ks_pop":1681,
    "ks:ks_type":"VILLAGE",
    "ks:ks_uagg_main":0,
    "name:eng_x_preferred":[
        "Godhanpur"
    ],
    "wof:name":"Godhanpur",
    "wof:placetype":"neighbourhood",
    "wof:population":1681
},
  "geometry": {"coordinates":[86.308187,26.248167],"type":"Point"}
}