{
  "type": "Feature",
  "properties": {
    "gn:admin1_code":"36.0",
    "gn:admin2_code":"153.0",
    "gn:asciiname":"Chaudhakpur",
    "gn:country_code":"IN",
    "gn:dem":152,
    "gn:feature_class":"P",
    "gn:feature_code":"PPL",
    "gn:name":"Chaudhakpur",
    "gn:population":0,
    "gn:timezone":"Asia/Kolkata",
    "iso:country":"IN",
    "ks:ks_name":"Chaudhakpur",
    "ks:ks_pop":843,
    "ks:ks_type":"VILLAGE",
    "ks:ks_uagg_main":0,
    "name:eng_x_preferred":[
        "Chaudhakpur"
    ],
    "wof:name":"Chaudhakpur",
    "wof:placetype":"neighbourhood",
    "wof:population":843
},
  "geometry": {"coordinates":[80.486678,27.931679],"type":"Point"}
}