{
  "type": "Feature",
  "properties": {
    "gn:admin1_code":"36",
    "gn:admin2_code":"185.0",
    "gn:asciiname":"Asiapar Riuhari",
    "gn:country_code":"IN",
    "gn:dem":86,
    "gn:feature_class":"P",
    "gn:feature_code":"PPL",
    "gn:name":"Asi\u0101p\u0101r Riuh\u0101ri",
    "gn:population":0,
    "gn:timezone":"Asia/Kolkata",
    "iso:country":"IN",
    "wof:name":"Asiapar Riuhari",
    "wof:placetype":"locality"
},
  "geometry": {"coordinates":[82.9325,26.71026],"type":"Point"}
}