{
  "type": "Feature",
  "properties": {
    "iso:country":"IN",
    "ks:ks_name":"Phasiatikar",
    "ks:ks_pop":151,
    "ks:ks_type":"VILLAGE",
    "name:eng_x_preferred":[
        "Phasiatikar"
    ],
    "wof:name":"Phasiatikar",
    "wof:placetype":"locality",
    "wof:population":151
},
  "geometry": {"coordinates":[87.23154,25.004523],"type":"Point"}
}