{
  "type": "Feature",
  "properties": {
    "gn:admin1_code":"11",
    "gn:admin2_code":"23.0",
    "gn:asciiname":"Haloli",
    "gn:country_code":"IN",
    "gn:dem":1952,
    "gn:feature_class":"P",
    "gn:feature_code":"PPL",
    "gn:name":"Haloli",
    "gn:population":0,
    "gn:timezone":"Asia/Kolkata",
    "iso:country":"IN",
    "wof:name":"Haloli",
    "wof:placetype":"locality"
},
  "geometry": {"coordinates":[76.08955999999998,32.77091],"type":"Point"}
}