{
  "type": "Feature",
  "properties": {
    "gn:admin1_code":"18",
    "gn:admin2_code":"293.0",
    "gn:asciiname":"Rongmachokgiri",
    "gn:country_code":"IN",
    "gn:dem":91,
    "gn:feature_class":"P",
    "gn:feature_code":"PPL",
    "gn:name":"Rongm\u0101chokgiri",
    "gn:population":0,
    "gn:timezone":"Asia/Kolkata",
    "iso:country":"IN",
    "wof:name":"Rongmachokgiri",
    "wof:placetype":"locality"
},
  "geometry": {"coordinates":[90.0681,25.80463],"type":"Point"}
}