{
  "type": "Feature",
  "properties": {
    "gn:admin1_code":"28.0",
    "gn:admin2_code":"337.0",
    "gn:asciiname":"Maligram",
    "gn:country_code":"IN",
    "gn:dem":14,
    "gn:feature_class":"P",
    "gn:feature_code":"PPL",
    "gn:name":"Maligram",
    "gn:population":0,
    "gn:timezone":"Asia/Kolkata",
    "iso:country":"IN",
    "wof:name":"Maligram",
    "wof:placetype":"locality"
},
  "geometry": {"coordinates":[88.63136999999998,22.7779],"type":"Point"}
}