{
  "type": "Feature",
  "properties": {
    "gn:admin1_code":"29.0",
    "gn:admin2_code":"243.0",
    "gn:asciiname":"Sumbuk",
    "gn:country_code":"IN",
    "gn:dem":887,
    "gn:feature_class":"P",
    "gn:feature_code":"PPL",
    "gn:name":"Sumbuk",
    "gn:population":0,
    "gn:timezone":"Asia/Kolkata",
    "iso:country":"IN",
    "name:ori_x_preferred":[
        "\u0b38\u0b41\u0b2e\u0b4d\u0b2c\u0b41\u0b15"
    ],
    "wof:name":"Sumbuk",
    "wof:placetype":"locality"
},
  "geometry": {"coordinates":[88.37233000000001,27.1179],"type":"Point"}
}