{
  "type": "Feature",
  "properties": {
    "gn:admin1_code":"34.0",
    "gn:admin2_code":"207.0",
    "gn:asciiname":"Khaparpura",
    "gn:country_code":"IN",
    "gn:dem":68,
    "gn:feature_class":"P",
    "gn:feature_code":"PPL",
    "gn:name":"Khaparpura",
    "gn:population":0,
    "gn:timezone":"Asia/Kolkata",
    "iso:country":"IN",
    "ks:ks_name":"Khaparpura",
    "ks:ks_pop":1050,
    "ks:ks_type":"HABITATION",
    "name:eng_x_preferred":[
        "Khaparpura"
    ],
    "wof:name":"Khaparpura",
    "wof:placetype":"locality",
    "wof:population":1050
},
  "geometry": {"coordinates":[86.049674,26.536619],"type":"Point"}
}