{
  "type": "Feature",
  "properties": {
    "gn:admin1_code":"2",
    "gn:admin2_code":"545.0",
    "gn:asciiname":"Taduvayi",
    "gn:country_code":"IN",
    "gn:dem":175,
    "gn:feature_class":"P",
    "gn:feature_code":"PPL",
    "gn:name":"T\u0101duv\u0101yi",
    "gn:population":0,
    "gn:timezone":"Asia/Kolkata",
    "iso:country":"IN",
    "ks:ks_name":"Thaduvai",
    "ks:ks_pop":88,
    "ks:ks_type":"VILLAGE",
    "name:eng_x_preferred":[
        "Thaduvai"
    ],
    "name:eng_x_variant":[
        "Taduvayi"
    ],
    "wof:name":"Thaduvai",
    "wof:placetype":"locality",
    "wof:population":88
},
  "geometry": {"coordinates":[82.279839,17.361481],"type":"Point"}
}