{
  "type": "Feature",
  "properties": {
    "iso:country":"IN",
    "ks:ks_name":"Chakroborty",
    "ks:ks_pop":247,
    "ks:ks_type":"HABITATION",
    "name:eng_x_preferred":[
        "Chakroborty"
    ],
    "wof:name":"Chakroborty",
    "wof:placetype":"locality",
    "wof:population":247
},
  "geometry": {"coordinates":[86.75341899999999,20.602562],"type":"Point"}
}