{
  "type": "Feature",
  "properties": {
    "iso:country":"IN",
    "ks:ks_name":"Tiplai Panbari",
    "ks:ks_pop":1002,
    "ks:ks_type":"VILLAGE",
    "ks:ks_uagg_main":0,
    "name:eng_x_preferred":[
        "Tiplai Panbari"
    ],
    "wof:name":"Tiplai Panbari",
    "wof:placetype":"neighbourhood",
    "wof:population":1002
},
  "geometry": {"coordinates":[91.199718,26.56612],"type":"Point"}
}