{
  "type": "Feature",
  "properties": {
    "iso:country":"IN",
    "ks:ks_name":"Bamhani",
    "ks:ks_type":"VILLAGE",
    "name:eng_x_preferred":[
        "Bamhani"
    ],
    "wof:name":"Bamhani",
    "wof:placetype":"locality"
},
  "geometry": {"coordinates":[81.41993600000001,27.10355],"type":"Point"}
}