{
  "type": "Feature",
  "properties": {
    "iso:country":"IN",
    "ks:ks_name":"Batula Banj",
    "ks:ks_pop":154,
    "ks:ks_type":"VILLAGE",
    "name:eng_x_preferred":[
        "Batula Banj"
    ],
    "wof:name":"Batula Banj",
    "wof:placetype":"locality",
    "wof:population":154
},
  "geometry": {"coordinates":[80.000084,29.375318],"type":"Point"}
}