{
  "type": "Feature",
  "properties": {
    "iso:country":"IN",
    "ks:ks_name":"Jorepakuri",
    "ks:ks_pop":431,
    "ks:ks_type":"HABITATION",
    "ks:ks_uagg_main":0,
    "name:eng_x_preferred":[
        "Jorepakuri"
    ],
    "wof:name":"Jorepakuri",
    "wof:placetype":"neighbourhood",
    "wof:population":431
},
  "geometry": {"coordinates":[88.159491,26.567925],"type":"Point"}
}