{
  "type": "Feature",
  "properties": {
    "iso:country":"IN",
    "ks:ks_alt_nam":"SURESH DAS PARA",
    "ks:ks_name":"Suresh Das Para",
    "ks:ks_pop":41,
    "ks:ks_type":"HABITATION",
    "name:eng_x_preferred":[
        "Suresh Das Para"
    ],
    "wof:name":"Suresh Das Para",
    "wof:placetype":"locality",
    "wof:population":41
},
  "geometry": {"coordinates":[91.21113099999999,23.674089],"type":"Point"}
}