{
  "type": "Feature",
  "properties": {
    "iso:country":"IN",
    "ks:ks_name":"Chitali",
    "ks:ks_pop":1324,
    "ks:ks_type":"VILLAGE",
    "name:eng_x_preferred":[
        "Chitali"
    ],
    "wof:name":"Chitali",
    "wof:placetype":"locality",
    "wof:population":1324
},
  "geometry": {"coordinates":[73.157901,20.89126],"type":"Point"}
}