{
  "type": "Feature",
  "properties": {
    "iso:country":"IN",
    "ks:ks_name":"Baghjant",
    "ks:ks_pop":100,
    "ks:ks_type":"VILLAGE",
    "name:eng_x_preferred":[
        "Baghjant"
    ],
    "wof:name":"Baghjant",
    "wof:placetype":"locality",
    "wof:population":100
},
  "geometry": {"coordinates":[85.83422899999999,24.58303],"type":"Point"}
}