{
  "type": "Feature",
  "properties": {
    "gn:admin1_code":"36",
    "gn:admin2_code":"136.0",
    "gn:asciiname":"Milk Siraswan Harchand",
    "gn:country_code":"IN",
    "gn:dem":205,
    "gn:feature_class":"P",
    "gn:feature_code":"PPL",
    "gn:name":"Milk Sirasw\u0101n Harchand",
    "gn:population":0,
    "gn:timezone":"Asia/Kolkata",
    "iso:country":"IN",
    "wof:name":"Milk Siraswan Harchand",
    "wof:placetype":"locality"
},
  "geometry": {"coordinates":[78.91207,28.95452],"type":"Point"}
}