{
  "type": "Feature",
  "properties": {
    "gn:admin1_code":"21",
    "gn:admin2_code":"393.0",
    "gn:asciiname":"Jhankarpali",
    "gn:country_code":"IN",
    "gn:dem":162,
    "gn:feature_class":"P",
    "gn:feature_code":"PPL",
    "gn:name":"Jh\u0101nkarp\u0101li",
    "gn:population":0,
    "gn:timezone":"Asia/Kolkata",
    "iso:country":"IN",
    "ks:ks_name":"Jhankarpali B",
    "ks:ks_pop":300,
    "ks:ks_type":"HABITATION",
    "name:eng_x_preferred":[
        "Jhankarpali B"
    ],
    "name:eng_x_variant":[
        "Jhankarpali"
    ],
    "wof:name":"Jhankarpali B",
    "wof:placetype":"locality",
    "wof:population":300
},
  "geometry": {"coordinates":[83.352648,21.028441],"type":"Point"}
}