{
  "type": "Feature",
  "properties": {
    "iso:country":"IN",
    "ks:ks_name":"Kachhar",
    "ks:ks_pop":1182,
    "ks:ks_type":"VILLAGE",
    "name:eng_x_preferred":[
        "Kachhar"
    ],
    "wof:name":"Kachhar",
    "wof:placetype":"locality",
    "wof:population":1182
},
  "geometry": {"coordinates":[83.580568,22.551442],"type":"Point"}
}