{
  "type": "Feature",
  "properties": {
    "iso:country":"IN",
    "ks:ks_name":"Chak Fajilpur",
    "ks:ks_pop":212,
    "ks:ks_type":"VILLAGE",
    "ks:ks_uagg_main":0,
    "name:eng_x_preferred":[
        "Chak Fajilpur"
    ],
    "wof:name":"Chak Fajilpur",
    "wof:placetype":"neighbourhood",
    "wof:population":212
},
  "geometry": {"coordinates":[81.901888,26.406261],"type":"Point"}
}