{
  "type": "Feature",
  "properties": {
    "iso:country":"IN",
    "ks:ks_name":"Chakram Krishnapur",
    "ks:ks_pop":31,
    "ks:ks_type":"VILLAGE",
    "name:eng_x_preferred":[
        "Chakram Krishnapur"
    ],
    "wof:name":"Chakram Krishnapur",
    "wof:placetype":"locality",
    "wof:population":31
},
  "geometry": {"coordinates":[88.796255,25.344601],"type":"Point"}
}