{
  "type": "Feature",
  "properties": {
    "gn:admin1_code":"24.0",
    "gn:admin2_code":"107.0",
    "gn:asciiname":"Nandpura",
    "gn:country_code":"IN",
    "gn:dem":220,
    "gn:feature_class":"P",
    "gn:feature_code":"PPL",
    "gn:name":"Nandpura",
    "gn:population":0,
    "gn:timezone":"Asia/Kolkata",
    "iso:country":"IN",
    "ks:ks_name":"Nandpura",
    "ks:ks_type":"VILLAGE",
    "name:eng_x_preferred":[
        "Nandpura"
    ],
    "wof:name":"Nandpura",
    "wof:placetype":"locality"
},
  "geometry": {"coordinates":[76.951691,26.812873],"type":"Point"}
}