{
  "type": "Feature",
  "properties": {
    "iso:country":"IN",
    "ks:ks_name":"Dombaragudisalu",
    "ks:ks_pop":113,
    "ks:ks_type":"HABITATION",
    "name:eng_x_preferred":[
        "Dombaragudisalu"
    ],
    "wof:name":"Dombaragudisalu",
    "wof:placetype":"locality",
    "wof:population":113
},
  "geometry": {"coordinates":[77.77691799999999,13.595938],"type":"Point"}
}