{
  "type": "Feature",
  "properties": {
    "gn:admin1_code":"9.0",
    "gn:admin2_code":"492",
    "gn:asciiname":"Bhimpur",
    "gn:country_code":"IN",
    "gn:dem":6,
    "gn:feature_class":"P",
    "gn:feature_code":"PPL",
    "gn:name":"Bhimpur",
    "gn:population":0,
    "gn:timezone":"Asia/Kolkata",
    "iso:country":"IN",
    "wof:name":"Bhimpur",
    "wof:placetype":"neighbourhood"
},
  "geometry": {"coordinates":[72.72866,21.08092],"type":"Point"}
}