{
  "type": "Feature",
  "properties": {
    "iso:country":"IN",
    "ks:ks_name":"Sela Chital",
    "ks:ks_pop":48,
    "ks:ks_type":"HABITATION",
    "name:eng_x_preferred":[
        "Sela Chital"
    ],
    "wof:name":"Sela Chital",
    "wof:placetype":"locality",
    "wof:population":48
},
  "geometry": {"coordinates":[80.253424,30.083496],"type":"Point"}
}