{
  "type": "Feature",
  "properties": {
    "gn:admin1_code":"16",
    "gn:admin2_code":"503.0",
    "gn:asciiname":"Koho",
    "gn:country_code":"IN",
    "gn:dem":316,
    "gn:feature_class":"P",
    "gn:feature_code":"PPL",
    "gn:name":"Koho",
    "gn:population":0,
    "gn:timezone":"Asia/Kolkata",
    "iso:country":"IN",
    "name:ceb_x_preferred":[
        "Koho"
    ],
    "name:deu_x_preferred":[
        "Koho"
    ],
    "name:fin_x_preferred":[
        "Koho"
    ],
    "name:swe_x_preferred":[
        "Koho"
    ],
    "wof:name":"Koho",
    "wof:placetype":"locality"
},
  "geometry": {"coordinates":[77.66665999999999,20.6812],"type":"Point"}
}