{
  "type": "Feature",
  "properties": {
    "iso:country":"IN",
    "ks:ks_alt_nam":"Palliv\u0101ramangalam",
    "ks:ks_name":"Pallivaramangalam",
    "ks:ks_pop":474,
    "ks:ks_type":"VILLAGE",
    "name:eng_x_preferred":[
        "Pallivaramangalam"
    ],
    "name:eng_x_variant":[
        "Palliv\u0101ramangalam"
    ],
    "wof:name":"Pallivaramangalam",
    "wof:placetype":"locality",
    "wof:population":474
},
  "geometry": {"coordinates":[79.670711,10.791991],"type":"Point"}
}