{
  "type": "Feature",
  "properties": {
    "gn:admin1_code":"35",
    "gn:admin2_code":"435.0",
    "gn:asciiname":"Orsinga",
    "gn:country_code":"IN",
    "gn:dem":487,
    "gn:feature_class":"P",
    "gn:feature_code":"PPL",
    "gn:name":"Orsinga",
    "gn:population":0,
    "gn:timezone":"Asia/Kolkata",
    "iso:country":"IN",
    "wof:name":"Orsinga",
    "wof:placetype":"neighbourhood"
},
  "geometry": {"coordinates":[75.43033,23.20673],"type":"Point"}
}