{
  "type": "Feature",
  "properties": {
    "iso:country":"IN",
    "ks:ks_name":"Busireddygari Palle",
    "ks:ks_pop":117,
    "ks:ks_type":"HABITATION",
    "name:eng_x_preferred":[
        "Busireddygari Palle"
    ],
    "wof:name":"Busireddygari Palle",
    "wof:placetype":"locality",
    "wof:population":117
},
  "geometry": {"coordinates":[78.514458,13.857122],"type":"Point"}
}