{
  "type": "Feature",
  "properties": {
    "iso:country":"IN",
    "ks:ks_name":"Thiriya Nizamat Khan",
    "ks:ks_pop":19251,
    "ks:ks_type":"URBAN",
    "ks:ks_uagg_main":1,
    "name:eng_x_preferred":[
        "Thiriya Nizamat Khan"
    ],
    "wof:name":"Thiriya Nizamat Khan",
    "wof:placetype":"neighbourhood",
    "wof:population":19251
},
  "geometry": {"coordinates":[79.464977,28.322574],"type":"Point"}
}