{
  "type": "Feature",
  "properties": {
    "iso:country":"IN",
    "ks:ks_alt_nam":"Chak Miy\u0101n",
    "ks:ks_name":"Chak Miyan",
    "ks:ks_type":"VILLAGE",
    "name:eng_x_preferred":[
        "Chak Miyan"
    ],
    "name:eng_x_variant":[
        "Chak Miy\u0101n"
    ],
    "wof:name":"Chak Miyan",
    "wof:placetype":"locality"
},
  "geometry": {"coordinates":[81.100235,25.972497],"type":"Point"}
}