{
  "type": "Feature",
  "properties": {
    "iso:country":"IN",
    "ks:ks_name":"Kamta Yadav Ka Dera",
    "ks:ks_pop":60,
    "ks:ks_type":"HABITATION",
    "name:eng_x_preferred":[
        "Kamta Yadav Ka Dera"
    ],
    "wof:name":"Kamta Yadav Ka Dera",
    "wof:placetype":"locality",
    "wof:population":60
},
  "geometry": {"coordinates":[81.198103,25.299996],"type":"Point"}
}