{
  "type": "Feature",
  "properties": {
    "gn:admin1_code":"34.0",
    "gn:admin2_code":"230.0",
    "gn:asciiname":"Madhopur",
    "gn:country_code":"IN",
    "gn:dem":52,
    "gn:feature_class":"P",
    "gn:feature_code":"PPL",
    "gn:name":"M\u0101dhopur",
    "gn:population":0,
    "gn:timezone":"Asia/Kolkata",
    "iso:country":"IN",
    "ks:ks_alt_nam":"M\u0101dhopur",
    "ks:ks_name":"Madhopur",
    "ks:ks_type":"VILLAGE",
    "ks:ks_uagg_main":0,
    "name:eng_x_preferred":[
        "Madhopur"
    ],
    "name:eng_x_variant":[
        "M\u0101dhopur"
    ],
    "wof:name":"Madhopur",
    "wof:placetype":"neighbourhood"
},
  "geometry": {"coordinates":[85.539686,25.458693],"type":"Point"}
}