{
  "type": "Feature",
  "properties": {
    "iso:country":"IN",
    "ks:ks_name":"Talai",
    "ks:ks_pop":142,
    "ks:ks_type":"VILLAGE",
    "ks:ks_uagg_main":0,
    "name:eng_x_preferred":[
        "Talai"
    ],
    "wof:name":"Talai",
    "wof:placetype":"neighbourhood",
    "wof:population":142
},
  "geometry": {"coordinates":[87.156115,22.27907],"type":"Point"}
}