{
  "type": "Feature",
  "properties": {
    "iso:country":"IN",
    "ks:ks_name":"Belalam",
    "ks:ks_pop":510,
    "ks:ks_type":"HABITATION",
    "name:eng_x_preferred":[
        "Belalam"
    ],
    "wof:name":"Belalam",
    "wof:placetype":"locality",
    "wof:population":510
},
  "geometry": {"coordinates":[77.78010500000001,12.459198],"type":"Point"}
}