{
  "type": "Feature",
  "properties": {
    "gn:admin1_code":"35.0",
    "gn:admin2_code":"443",
    "gn:asciiname":"Rasula",
    "gn:country_code":"IN",
    "gn:dem":423,
    "gn:feature_class":"P",
    "gn:feature_code":"PPL",
    "gn:name":"Ras\u016bla",
    "gn:population":0,
    "gn:timezone":"Asia/Kolkata",
    "iso:country":"IN",
    "wof:name":"Rasula",
    "wof:placetype":"locality"
},
  "geometry": {"coordinates":[78.17291,24.00692],"type":"Point"}
}