{
  "type": "Feature",
  "properties": {
    "iso:country":"IN",
    "ks:ks_name":"Bhilam",
    "ks:ks_pop":808,
    "ks:ks_type":"HABITATION",
    "name:eng_x_preferred":[
        "Bhilam"
    ],
    "wof:name":"Bhilam",
    "wof:placetype":"locality",
    "wof:population":808
},
  "geometry": {"coordinates":[77.972508,27.584337],"type":"Point"}
}