{
  "type": "Feature",
  "properties": {
    "gn:admin1_code":"02",
    "gn:admin2_code":"549.0",
    "gn:asciiname":"Peddaalavalapadu",
    "gn:country_code":"IN",
    "gn:dem":63,
    "gn:feature_class":"P",
    "gn:feature_code":"PPL",
    "gn:name":"Peddaalavalap\u0101du",
    "gn:population":0,
    "gn:timezone":"Asia/Kolkata",
    "iso:country":"IN",
    "name:und_x_variant":[
        "Peddaalavpad",
        "Peddaalavalap\u0101du",
        "Alavalapadu"
    ],
    "wof:name":"Peddaalavalapadu",
    "wof:placetype":"locality"
},
  "geometry": {"coordinates":[79.62475000000001,15.32806],"type":"Point"}
}