{
  "type": "Feature",
  "properties": {
    "gn:admin1_code":"19.0",
    "gn:admin2_code":"569.0",
    "gn:asciiname":"Lahri",
    "gn:country_code":"IN",
    "gn:dem":125,
    "gn:feature_class":"P",
    "gn:feature_code":"PPL",
    "gn:name":"Lahri",
    "gn:population":0,
    "gn:timezone":"Asia/Kolkata",
    "iso:country":"IN",
    "wof:name":"Lahri",
    "wof:placetype":"locality"
},
  "geometry": {"coordinates":[75.00343000000002,13.05688],"type":"Point"}
}