{
  "type": "Feature",
  "properties": {
    "iso:country":"IN",
    "ks:ks_alt_nam":"SINAI KAMI",
    "ks:ks_name":"Sinai Kami",
    "ks:ks_pop":531,
    "ks:ks_type":"HABITATION",
    "name:eng_x_preferred":[
        "Sinai Kami"
    ],
    "wof:name":"Sinai Kami",
    "wof:placetype":"locality",
    "wof:population":531
},
  "geometry": {"coordinates":[91.509747,23.815435],"type":"Point"}
}