{
  "type": "Feature",
  "properties": {
    "gn:admin1_code":"10",
    "gn:admin2_code":"82.0",
    "gn:asciiname":"Niganah",
    "gn:country_code":"IN",
    "gn:dem":223,
    "gn:feature_class":"P",
    "gn:feature_code":"PPL",
    "gn:name":"Nig\u0101n\u0101h",
    "gn:population":0,
    "gn:timezone":"Asia/Kolkata",
    "iso:country":"IN",
    "wof:name":"Niganah",
    "wof:placetype":"locality"
},
  "geometry": {"coordinates":[76.43638,28.77804],"type":"Point"}
}