{
  "type": "Feature",
  "properties": {
    "gn:admin1_code":"35.0",
    "gn:admin2_code":"444.0",
    "gn:asciiname":"Ratua",
    "gn:country_code":"IN",
    "gn:dem":477,
    "gn:feature_class":"P",
    "gn:feature_code":"PPL",
    "gn:name":"Ratua",
    "gn:population":0,
    "gn:timezone":"Asia/Kolkata",
    "iso:country":"IN",
    "wof:name":"Ratua",
    "wof:placetype":"locality"
},
  "geometry": {"coordinates":[77.40928000000002,23.52642],"type":"Point"}
}