{
  "type": "Feature",
  "properties": {
    "iso:country":"IN",
    "ks:ks_name":"Kanikamau",
    "ks:ks_pop":827,
    "ks:ks_type":"VILLAGE",
    "name:eng_x_preferred":[
        "Kanikamau"
    ],
    "wof:name":"Kanikamau",
    "wof:placetype":"locality",
    "wof:population":827
},
  "geometry": {"coordinates":[80.346858,26.55185],"type":"Point"}
}