{
  "type": "Feature",
  "properties": {
    "iso:country":"IN",
    "ks:ks_name":"Manjha Salempur",
    "ks:ks_pop":153,
    "ks:ks_type":"HABITATION",
    "name:eng_x_preferred":[
        "Manjha Salempur"
    ],
    "wof:name":"Manjha Salempur",
    "wof:placetype":"locality",
    "wof:population":153
},
  "geometry": {"coordinates":[82.262147,26.755486],"type":"Point"}
}