{
  "type": "Feature",
  "properties": {
    "iso:country":"IN",
    "ks:ks_name":"Kanharbahra",
    "ks:ks_pop":588,
    "ks:ks_type":"VILLAGE",
    "name:eng_x_preferred":[
        "Kanharbahra"
    ],
    "wof:name":"Kanharbahra",
    "wof:placetype":"locality",
    "wof:population":588
},
  "geometry": {"coordinates":[82.43809299999999,23.074882],"type":"Point"}
}