{
  "type": "Feature",
  "properties": {
    "gn:admin1_code":"28.0",
    "gn:admin2_code":"333.0",
    "gn:asciiname":"Kusumgachi",
    "gn:country_code":"IN",
    "gn:dem":28,
    "gn:feature_class":"P",
    "gn:feature_code":"PPL",
    "gn:name":"Kusumg\u0101chi",
    "gn:population":0,
    "gn:timezone":"Asia/Kolkata",
    "iso:country":"IN",
    "ks:ks_name":"Kusumgachhi",
    "ks:ks_pop":2624,
    "ks:ks_type":"VILLAGE",
    "ks:ks_uagg_main":0,
    "name:eng_x_preferred":[
        "Kusumgachhi"
    ],
    "wof:name":"Kusumgachhi",
    "wof:placetype":"neighbourhood",
    "wof:population":2624
},
  "geometry": {"coordinates":[87.940912,24.52642],"type":"Point"}
}