{
  "type": "Feature",
  "properties": {
    "iso:country":"IN",
    "ks:ks_name":"Birpahar",
    "ks:ks_pop":46,
    "ks:ks_type":"VILLAGE",
    "name:eng_x_preferred":[
        "Birpahar"
    ],
    "wof:name":"Birpahar",
    "wof:placetype":"locality",
    "wof:population":46
},
  "geometry": {"coordinates":[87.76774500000001,24.92554],"type":"Point"}
}