{
  "type": "Feature",
  "properties": {
    "gn:admin1_code":"12.0",
    "gn:asciiname":"Nawa",
    "gn:country_code":"IN",
    "gn:dem":1669,
    "gn:feature_class":"P",
    "gn:feature_code":"PPL",
    "gn:name":"N\u0101wa",
    "gn:population":0,
    "gn:timezone":"Asia/Kolkata",
    "iso:country":"IN",
    "name:ceb_x_preferred":[
        "Nawa"
    ],
    "name:deu_x_preferred":[
        "Nawa"
    ],
    "name:ita_x_preferred":[
        "Nawa"
    ],
    "name:pol_x_preferred":[
        "Nawa"
    ],
    "name:rus_x_preferred":[
        "\u041d\u0430\u0432\u0430"
    ],
    "name:swe_x_preferred":[
        "Nawa"
    ],
    "name:ukr_x_preferred":[
        "\u041d\u0430\u0432\u0430"
    ],
    "name:und_x_variant":[
        "N\u0101wa"
    ],
    "wof:name":"Nawa",
    "wof:placetype":"locality"
},
  "geometry": {"coordinates":[73.97141999999999,34.07799],"type":"Point"}
}