{
  "type": "Feature",
  "properties": {
    "iso:country":"IN",
    "ks:ks_name":"Devasya Kanajar",
    "ks:ks_pop":90,
    "ks:ks_type":"HABITATION",
    "name:eng_x_preferred":[
        "Devasya Kanajar"
    ],
    "wof:name":"Devasya Kanajar",
    "wof:placetype":"locality",
    "wof:population":90
},
  "geometry": {"coordinates":[74.88382,13.289458],"type":"Point"}
}