{
  "type": "Feature",
  "properties": {
    "iso:country":"IN",
    "ks:ks_name":"Tongodih",
    "ks:ks_pop":308,
    "ks:ks_type":"VILLAGE",
    "ks:ks_uagg_main":0,
    "name:eng_x_preferred":[
        "Tongodih"
    ],
    "wof:name":"Tongodih",
    "wof:placetype":"neighbourhood",
    "wof:population":308
},
  "geometry": {"coordinates":[86.586513,24.114346],"type":"Point"}
}