{
  "type": "Feature",
  "properties": {
    "gn:admin1_code":"25.0",
    "gn:admin2_code":"606.0",
    "gn:asciiname":"Appantangal",
    "gn:country_code":"IN",
    "gn:dem":149,
    "gn:feature_class":"P",
    "gn:feature_code":"PPL",
    "gn:name":"Appant\u0101ngal",
    "gn:population":0,
    "gn:timezone":"Asia/Kolkata",
    "iso:country":"IN",
    "name:und_x_variant":[
        "Appant\u0101ngal",
        "Kayapp\u0101kkam"
    ],
    "wof:name":"Appantangal",
    "wof:placetype":"locality"
},
  "geometry": {"coordinates":[79.30458,12.73695],"type":"Point"}
}