{
  "type": "Feature",
  "properties": {
    "iso:country":"IN",
    "ks:ks_name":"Kolimedu",
    "ks:ks_pop":248,
    "ks:ks_type":"HABITATION",
    "ks:ks_uagg_main":0,
    "name:eng_x_preferred":[
        "Kolimedu"
    ],
    "wof:name":"Kolimedu",
    "wof:placetype":"neighbourhood",
    "wof:population":248
},
  "geometry": {"coordinates":[76.287474,11.576019],"type":"Point"}
}