{
  "type": "Feature",
  "properties": {
    "iso:country":"IN",
    "ks:ks_name":"Dudharai",
    "ks:ks_pop":389,
    "ks:ks_type":"HABITATION",
    "name:eng_x_preferred":[
        "Dudharai"
    ],
    "wof:name":"Dudharai",
    "wof:placetype":"locality",
    "wof:population":389
},
  "geometry": {"coordinates":[78.649477,27.006131],"type":"Point"}
}