{
  "type": "Feature",
  "properties": {
    "iso:country":"IN",
    "ks:ks_alt_nam":"Biskut pt I",
    "ks:ks_name":"Biskut Pt I",
    "ks:ks_pop":793,
    "ks:ks_type":"HABITATION",
    "name:eng_x_preferred":[
        "Biskut Pt I"
    ],
    "wof:name":"Biskut Pt I",
    "wof:placetype":"locality",
    "wof:population":793
},
  "geometry": {"coordinates":[92.32379400000001,24.838815],"type":"Point"}
}