{
  "type": "Feature",
  "properties": {
    "gn:admin1_code":"40.0",
    "gn:admin2_code":"533.0",
    "gn:asciiname":"Lachhmapur",
    "gn:country_code":"IN",
    "gn:dem":405,
    "gn:feature_class":"P",
    "gn:feature_code":"PPL",
    "gn:name":"Lachhm\u0101pur",
    "gn:population":0,
    "gn:timezone":"Asia/Kolkata",
    "iso:country":"IN",
    "ks:ks_name":"Lakshmapur",
    "ks:ks_pop":1688,
    "ks:ks_type":"VILLAGE",
    "ks:ks_uagg_main":0,
    "name:eng_x_preferred":[
        "Lakshmapur"
    ],
    "wof:name":"Lakshmapur",
    "wof:placetype":"neighbourhood",
    "wof:population":1688
},
  "geometry": {"coordinates":[78.237015,18.748317],"type":"Point"}
}