{
  "type": "Feature",
  "properties": {
    "iso:country":"IN",
    "ks:ks_name":"Losangi",
    "ks:ks_pop":360,
    "ks:ks_type":"HABITATION",
    "name:eng_x_preferred":[
        "Losangi"
    ],
    "wof:name":"Losangi",
    "wof:placetype":"locality",
    "wof:population":360
},
  "geometry": {"coordinates":[83.053426,22.940018],"type":"Point"}
}