{
  "type": "Feature",
  "properties": {
    "gn:admin1_code":"11.0",
    "gn:admin2_code":"31.0",
    "gn:asciiname":"Phagora",
    "gn:country_code":"IN",
    "gn:dem":1381,
    "gn:feature_class":"P",
    "gn:feature_code":"PPL",
    "gn:name":"Phagora",
    "gn:population":0,
    "gn:timezone":"Asia/Kolkata",
    "iso:country":"IN",
    "name:fas_x_preferred":[
        "\u0641\u0627\u06af\u0648\u0631\u0627"
    ],
    "wof:name":"Phagora",
    "wof:placetype":"locality"
},
  "geometry": {"coordinates":[77.14357,30.99663],"type":"Point"}
}