{
  "type": "Feature",
  "properties": {
    "gn:admin1_code":"38.0",
    "gn:admin2_code":"358.0",
    "gn:asciiname":"Barhaidih",
    "gn:country_code":"IN",
    "gn:dem":295,
    "gn:feature_class":"P",
    "gn:feature_code":"PPL",
    "gn:name":"Barhaidih",
    "gn:population":0,
    "gn:timezone":"Asia/Kolkata",
    "iso:country":"IN",
    "wof:name":"Barhaidih",
    "wof:placetype":"locality"
},
  "geometry": {"coordinates":[84.31364000000001,24.20033],"type":"Point"}
}