{
  "type": "Feature",
  "properties": {
    "iso:country":"IN",
    "ks:ks_name":"Ramchandra Nagar",
    "ks:ks_pop":716,
    "ks:ks_type":"VILLAGE",
    "name:eng_x_preferred":[
        "Ramchandra Nagar"
    ],
    "wof:name":"Ramchandra Nagar",
    "wof:placetype":"locality",
    "wof:population":716
},
  "geometry": {"coordinates":[87.6737,21.716086],"type":"Point"}
}