{
  "type": "Feature",
  "properties": {
    "iso:country":"IN",
    "ks:ks_name":"Batiguda",
    "ks:ks_pop":66,
    "ks:ks_type":"HABITATION",
    "name:eng_x_preferred":[
        "Batiguda"
    ],
    "wof:name":"Batiguda",
    "wof:placetype":"locality",
    "wof:population":66
},
  "geometry": {"coordinates":[82.556172,18.74325],"type":"Point"}
}