{
  "type": "Feature",
  "properties": {
    "iso:country":"IN",
    "ks:ks_name":"Teluni",
    "ks:ks_pop":386,
    "ks:ks_type":"VILLAGE",
    "ks:ks_uagg_main":0,
    "name:eng_x_preferred":[
        "Teluni"
    ],
    "wof:name":"Teluni",
    "wof:placetype":"neighbourhood",
    "wof:population":386
},
  "geometry": {"coordinates":[87.15209,21.589021],"type":"Point"}
}