{
  "type": "Feature",
  "properties": {
    "gn:admin1_code":"16",
    "gn:admin2_code":"504.0",
    "gn:asciiname":"Goji",
    "gn:country_code":"IN",
    "gn:dem":239,
    "gn:feature_class":"P",
    "gn:feature_code":"PPL",
    "gn:name":"Goji",
    "gn:population":0,
    "gn:timezone":"Asia/Kolkata",
    "iso:country":"IN",
    "name:cat_x_preferred":[
        "Goji"
    ],
    "name:cdo_x_preferred":[
        "G\u0113u-g\u012b"
    ],
    "name:ces_x_preferred":[
        "God\u017ei"
    ],
    "name:ell_x_preferred":[
        "\u0393\u03ba\u03cc\u03c4\u03b6\u03b9"
    ],
    "name:fas_x_preferred":[
        "\u06af\u0648\u062c\u06cc\u200c\u0628\u0631\u06cc"
    ],
    "name:fin_x_preferred":[
        "Goji-marja"
    ],
    "name:glg_x_preferred":[
        "Goxi"
    ],
    "name:hun_x_preferred":[
        "Goji bogy\u00f3"
    ],
    "name:ita_x_preferred":[
        "Goji"
    ],
    "name:jav_x_preferred":[
        "Goji beri"
    ],
    "name:kor_x_preferred":[
        "\uad6c\uae30\uc790"
    ],
    "name:pol_x_preferred":[
        "Goji"
    ],
    "name:sqi_x_preferred":[
        "Goji"
    ],
    "name:srp_x_preferred":[
        "\u0413\u043e\u045f\u0438"
    ],
    "name:swe_x_preferred":[
        "Gojib\u00e4r"
    ],
    "name:tel_x_preferred":[
        "\u0c17\u0c4b\u0c1c\u0c40"
    ],
    "name:vie_x_preferred":[
        "C\u1ee7 kh\u1edfi"
    ],
    "name:zha_x_preferred":[
        "Gaeujgij"
    ],
    "wof:name":"Goji",
    "wof:placetype":"locality"
},
  "geometry": {"coordinates":[78.75219,20.62617],"type":"Point"}
}