{
  "type": "Feature",
  "properties": {
    "gn:admin1_code":"36",
    "gn:admin2_code":"154.0",
    "gn:asciiname":"Puranpur",
    "gn:country_code":"IN",
    "gn:dem":138,
    "gn:feature_class":"P",
    "gn:feature_code":"PPL",
    "gn:name":"Puranpur",
    "gn:population":0,
    "gn:timezone":"Asia/Kolkata",
    "iso:country":"IN",
    "name:bpy_x_preferred":[
        "\u09aa\u09c1\u09b0\u09be\u09a8\u09aa\u09c1\u09b0"
    ],
    "name:ceb_x_preferred":[
        "P\u016branpur"
    ],
    "name:fas_x_preferred":[
        "\u067e\u0648\u0631\u0627\u0646\u200c\u067e\u0648\u0631"
    ],
    "name:ita_x_preferred":[
        "Puranpur"
    ],
    "name:mlg_x_preferred":[
        "Puranpur"
    ],
    "name:msa_x_preferred":[
        "Puranpur"
    ],
    "name:nld_x_preferred":[
        "Puranpur"
    ],
    "name:ori_x_preferred":[
        "\u0b2a\u0b41\u0b30\u0b23\u0b2a\u0b41\u0b30"
    ],
    "name:pnb_x_preferred":[
        "\u067e\u0648\u0631\u0646 \u067e\u0648\u0631"
    ],
    "name:pol_x_preferred":[
        "Puranpur"
    ],
    "name:por_x_preferred":[
        "Puranpur"
    ],
    "name:swe_x_preferred":[
        "P\u016branpur"
    ],
    "name:urd_x_preferred":[
        "\u067e\u0648\u0631\u0646 \u067e\u0648\u0631"
    ],
    "name:vie_x_preferred":[
        "Puranpur"
    ],
    "name:zho_x_preferred":[
        "\u666e\u5170\u666e\u5c14"
    ],
    "wof:name":"Puranpur",
    "wof:placetype":"locality"
},
  "geometry": {"coordinates":[80.94658000000003,27.36502],"type":"Point"}
}