{
  "type": "Feature",
  "properties": {
    "iso:country":"IN",
    "ks:ks_name":"Duyaranda",
    "ks:ks_pop":212,
    "ks:ks_type":"VILLAGE",
    "name:eng_x_preferred":[
        "Duyaranda"
    ],
    "wof:name":"Duyaranda",
    "wof:placetype":"locality",
    "wof:population":212
},
  "geometry": {"coordinates":[87.043834,23.299776],"type":"Point"}
}