{
  "type": "Feature",
  "properties": {
    "gn:admin1_code":"36.0",
    "gn:admin2_code":"190.0",
    "gn:asciiname":"Badsara",
    "gn:country_code":"IN",
    "gn:dem":74,
    "gn:feature_class":"P",
    "gn:feature_code":"PPL",
    "gn:name":"Badsara",
    "gn:population":0,
    "gn:timezone":"Asia/Kolkata",
    "iso:country":"IN",
    "wof:name":"Badsara",
    "wof:placetype":"neighbourhood"
},
  "geometry": {"coordinates":[83.74288,26.28166],"type":"Point"}
}