{
  "type": "Feature",
  "properties": {
    "iso:country":"IN",
    "ks:ks_name":"3 BPSM",
    "ks:ks_pop":161,
    "ks:ks_type":"VILLAGE",
    "name:eng_x_preferred":[
        "3 BPSM"
    ],
    "wof:name":"3 BPSM",
    "wof:placetype":"locality",
    "wof:population":161
},
  "geometry": {"coordinates":[74.472889,29.310276],"type":"Point"}
}