{
  "type": "Feature",
  "properties": {
    "iso:country":"IN",
    "ks:ks_name":"Sirunda",
    "ks:ks_pop":107,
    "ks:ks_type":"VILLAGE",
    "name:eng_x_preferred":[
        "Sirunda"
    ],
    "wof:name":"Sirunda",
    "wof:placetype":"locality",
    "wof:population":107
},
  "geometry": {"coordinates":[78.838543,30.003358],"type":"Point"}
}