{
  "type": "Feature",
  "properties": {
    "iso:country":"IN",
    "ks:ks_name":"Soosaipatti",
    "ks:ks_pop":404,
    "ks:ks_type":"HABITATION",
    "name:eng_x_preferred":[
        "Soosaipatti"
    ],
    "wof:name":"Soosaipatti",
    "wof:placetype":"locality",
    "wof:population":404
},
  "geometry": {"coordinates":[77.91361999999999,10.338509],"type":"Point"}
}