{
  "type": "Feature",
  "properties": {
    "gn:admin1_code":"37.0",
    "gn:admin2_code":"417",
    "gn:asciiname":"Bhairamgarh",
    "gn:country_code":"IN",
    "gn:dem":335,
    "gn:feature_class":"P",
    "gn:feature_code":"PPL",
    "gn:name":"Bhairamgarh",
    "gn:population":0,
    "gn:timezone":"Asia/Kolkata",
    "iso:country":"IN",
    "name:und_x_variant":[
        "Byramgarh",
        "Bhairamgarh"
    ],
    "wof:name":"Bhairamgarh",
    "wof:placetype":"locality"
},
  "geometry": {"coordinates":[81.05916999999999,19.00641],"type":"Point"}
}