{
  "type": "Feature",
  "properties": {
    "iso:country":"IN",
    "ks:ks_alt_nam":"Kanagambal Koil ST",
    "ks:ks_name":"Kanagambal Koil St",
    "ks:ks_pop":156,
    "ks:ks_type":"HABITATION",
    "name:eng_x_preferred":[
        "Kanagambal Koil St"
    ],
    "wof:name":"Kanagambal Koil St",
    "wof:placetype":"locality",
    "wof:population":156
},
  "geometry": {"coordinates":[79.107342,10.19575],"type":"Point"}
}