{
  "type": "Feature",
  "properties": {
    "iso:country":"IN",
    "ks:ks_name":"Puran Chhapra",
    "ks:ks_pop":1826,
    "ks:ks_type":"VILLAGE",
    "ks:ks_uagg_main":0,
    "name:eng_x_preferred":[
        "Puran Chhapra"
    ],
    "wof:name":"Puran Chhapra",
    "wof:placetype":"neighbourhood",
    "wof:population":1826
},
  "geometry": {"coordinates":[85.00807,26.334494],"type":"Point"}
}