{
  "type": "Feature",
  "properties": {
    "iso:country":"IN",
    "ks:ks_name":"Karanjoida",
    "ks:ks_pop":212,
    "ks:ks_type":"HABITATION",
    "name:eng_x_preferred":[
        "Karanjoida"
    ],
    "wof:name":"Karanjoida",
    "wof:placetype":"locality",
    "wof:population":212
},
  "geometry": {"coordinates":[74.425623,15.177563],"type":"Point"}
}