{
  "type": "Feature",
  "properties": {
    "iso:country":"IN",
    "ks:ks_name":"Chauriadhipa",
    "ks:ks_pop":169,
    "ks:ks_type":"VILLAGE",
    "name:eng_x_preferred":[
        "Chauriadhipa"
    ],
    "wof:name":"Chauriadhipa",
    "wof:placetype":"locality",
    "wof:population":169
},
  "geometry": {"coordinates":[84.71942199999999,21.375268],"type":"Point"}
}