{
  "type": "Feature",
  "properties": {
    "gn:admin1_code":"34.0",
    "gn:admin2_code":"207.0",
    "gn:asciiname":"Chanaura Goth",
    "gn:country_code":"IN",
    "gn:dem":59,
    "gn:feature_class":"P",
    "gn:feature_code":"PPL",
    "gn:name":"Chanaura Goth",
    "gn:population":0,
    "gn:timezone":"Asia/Kolkata",
    "iso:country":"IN",
    "wof:name":"Chanaura Goth",
    "wof:placetype":"neighbourhood"
},
  "geometry": {"coordinates":[86.30916000000001,26.29556],"type":"Point"}
}