{
  "type": "Feature",
  "properties": {
    "gn:admin1_code":"35",
    "gn:admin2_code":"430.0",
    "gn:asciiname":"Damodargarh",
    "gn:country_code":"IN",
    "gn:dem":322,
    "gn:feature_class":"P",
    "gn:feature_code":"PPL",
    "gn:name":"D\u0101modargarh",
    "gn:population":0,
    "gn:timezone":"Asia/Kolkata",
    "iso:country":"IN",
    "wof:name":"Damodargarh",
    "wof:placetype":"locality"
},
  "geometry": {"coordinates":[82.0078,24.58803],"type":"Point"}
}