{
  "type": "Feature",
  "properties": {
    "iso:country":"IN",
    "ks:ks_name":"Dumaria",
    "ks:ks_pop":1527,
    "ks:ks_type":"VILLAGE",
    "name:eng_x_preferred":[
        "Dumaria"
    ],
    "wof:name":"Dumaria",
    "wof:placetype":"locality",
    "wof:population":1527
},
  "geometry": {"coordinates":[85.30628299999999,26.244504],"type":"Point"}
}