{
  "type": "Feature",
  "properties": {
    "iso:country":"IN",
    "ks:ks_alt_nam":"5 U (RURAL)",
    "ks:ks_name":"5 U (rural)",
    "ks:ks_pop":38,
    "ks:ks_type":"HABITATION",
    "name:eng_x_preferred":[
        "5 U (rural)"
    ],
    "wof:name":"5 U (rural)",
    "wof:placetype":"locality",
    "wof:population":38
},
  "geometry": {"coordinates":[73.63877100000001,29.929897],"type":"Point"}
}