{
  "type": "Feature",
  "properties": {
    "gn:admin1_code":"36.0",
    "gn:admin2_code":"161",
    "gn:asciiname":"Pata Jhari",
    "gn:country_code":"IN",
    "gn:dem":153,
    "gn:feature_class":"P",
    "gn:feature_code":"PPL",
    "gn:name":"Pata Jh\u0101ri",
    "gn:population":0,
    "gn:timezone":"Asia/Kolkata",
    "iso:country":"IN",
    "name:und_x_variant":[
        "Pata Jh\u0101ri",
        "P\u0101t\u0101jhari"
    ],
    "wof:name":"Pata Jhari",
    "wof:placetype":"locality"
},
  "geometry": {"coordinates":[79.01076999999999,26.82841],"type":"Point"}
}