{
  "type": "Feature",
  "properties": {
    "gn:admin1_code":"2",
    "gn:admin2_code":"544.0",
    "gn:asciiname":"Vijayaramapuram",
    "gn:country_code":"IN",
    "gn:dem":8,
    "gn:feature_class":"P",
    "gn:feature_code":"PPL",
    "gn:name":"Vijayar\u0101mapuram",
    "gn:population":0,
    "gn:timezone":"Asia/Kolkata",
    "iso:country":"IN",
    "wof:name":"Vijayaramapuram",
    "wof:placetype":"locality"
},
  "geometry": {"coordinates":[82.92928000000001,17.49859],"type":"Point"}
}