{
  "type": "Feature",
  "properties": {
    "gn:admin1_code":"10.0",
    "gn:admin2_code":"77.0",
    "gn:asciiname":"Kandela",
    "gn:country_code":"IN",
    "gn:dem":229,
    "gn:feature_class":"P",
    "gn:feature_code":"PPL",
    "gn:name":"Kandela",
    "gn:population":0,
    "gn:timezone":"Asia/Kolkata",
    "iso:country":"IN",
    "wof:name":"Kandela",
    "wof:placetype":"locality"
},
  "geometry": {"coordinates":[76.34144000000001,29.38453],"type":"Point"}
}