{
  "type": "Feature",
  "properties": {
    "gn:admin1_code":"12.0",
    "gn:admin2_code":"14.0",
    "gn:asciiname":"Shilinar",
    "gn:country_code":"IN",
    "gn:dem":2972,
    "gn:feature_class":"P",
    "gn:feature_code":"PPL",
    "gn:name":"Shilin\u0101r",
    "gn:population":0,
    "gn:timezone":"Asia/Kolkata",
    "iso:country":"IN",
    "wof:name":"Shilinar",
    "wof:placetype":"locality"
},
  "geometry": {"coordinates":[75.29295,33.45197],"type":"Point"}
}