{
  "type": "Feature",
  "properties": {
    "gn:admin1_code":"36.0",
    "gn:admin2_code":"153.0",
    "gn:asciiname":"Lalpur Grant",
    "gn:country_code":"IN",
    "gn:dem":152,
    "gn:feature_class":"P",
    "gn:feature_code":"PPL",
    "gn:name":"L\u0101lpur Grant",
    "gn:population":0,
    "gn:timezone":"Asia/Kolkata",
    "iso:country":"IN",
    "wof:name":"Lalpur Grant",
    "wof:placetype":"locality"
},
  "geometry": {"coordinates":[80.44686999999998,27.91338],"type":"Point"}
}