{
  "type": "Feature",
  "properties": {
    "iso:country":"IN",
    "ks:ks_name":"Lokhhria Purwa",
    "ks:ks_pop":247,
    "ks:ks_type":"HABITATION",
    "ks:ks_uagg_main":0,
    "name:eng_x_preferred":[
        "Lokhhria Purwa"
    ],
    "wof:name":"Lokhhria Purwa",
    "wof:placetype":"neighbourhood",
    "wof:population":247
},
  "geometry": {"coordinates":[81.376108,26.759719],"type":"Point"}
}