{
  "type": "Feature",
  "properties": {
    "iso:country":"IN",
    "ks:ks_name":"Pathai Mal",
    "ks:ks_pop":54,
    "ks:ks_type":"VILLAGE",
    "name:eng_x_preferred":[
        "Pathai Mal"
    ],
    "wof:name":"Pathai Mal",
    "wof:placetype":"locality",
    "wof:population":54
},
  "geometry": {"coordinates":[78.42850900000001,22.594523],"type":"Point"}
}