{
  "type": "Feature",
  "properties": {
    "iso:country":"IN",
    "ks:ks_name":"Ghadashiwadi",
    "ks:ks_pop":250,
    "ks:ks_type":"HABITATION",
    "name:eng_x_preferred":[
        "Ghadashiwadi"
    ],
    "wof:name":"Ghadashiwadi",
    "wof:placetype":"locality",
    "wof:population":250
},
  "geometry": {"coordinates":[73.51222199999999,17.287778],"type":"Point"}
}