{
  "type": "Feature",
  "properties": {
    "gn:admin1_code":"10",
    "gn:admin2_code":"75.0",
    "gn:asciiname":"Jhamba",
    "gn:country_code":"IN",
    "gn:dem":234,
    "gn:feature_class":"P",
    "gn:feature_code":"PPL",
    "gn:name":"Jh\u0101mba",
    "gn:population":0,
    "gn:timezone":"Asia/Kolkata",
    "iso:country":"IN",
    "ks:ks_alt_nam":"Jh\u0101mba",
    "ks:ks_name":"Jhamba",
    "ks:ks_pop":1549,
    "ks:ks_type":"VILLAGE",
    "ks:ks_uagg_main":0,
    "name:eng_x_preferred":[
        "Jhamba"
    ],
    "name:eng_x_variant":[
        "Jh\u0101mba"
    ],
    "wof:name":"Jhamba",
    "wof:placetype":"neighbourhood",
    "wof:population":1549
},
  "geometry": {"coordinates":[77.1087,29.388398],"type":"Point"}
}