{
  "type": "Feature",
  "properties": {
    "gn:admin1_code":"34.0",
    "gn:admin2_code":"217.0",
    "gn:asciiname":"Bhirgi Chak",
    "gn:country_code":"IN",
    "gn:dem":82,
    "gn:feature_class":"P",
    "gn:feature_code":"PPL",
    "gn:name":"Bhirgi Chak",
    "gn:population":0,
    "gn:timezone":"Asia/Kolkata",
    "iso:country":"IN",
    "ks:ks_name":"Bhirgi Chak",
    "ks:ks_pop":1155,
    "ks:ks_type":"VILLAGE",
    "name:eng_x_preferred":[
        "Bhirgi Chak"
    ],
    "wof:name":"Bhirgi Chak",
    "wof:placetype":"locality",
    "wof:population":1155
},
  "geometry": {"coordinates":[84.183896,26.541976],"type":"Point"}
}