{
  "type": "Feature",
  "properties": {
    "iso:country":"IN",
    "ks:ks_alt_nam":"pandepara",
    "ks:ks_name":"Pandepara",
    "ks:ks_pop":63,
    "ks:ks_type":"HABITATION",
    "name:eng_x_preferred":[
        "Pandepara"
    ],
    "wof:name":"Pandepara",
    "wof:placetype":"locality",
    "wof:population":63
},
  "geometry": {"coordinates":[81.7649,18.581728],"type":"Point"}
}