{
  "type": "Feature",
  "properties": {
    "gn:country":"IN",
    "gn:fcode":"PPL",
    "gn:pop":35134,
    "iso:country":"IN",
    "name:ben_x_preferred":[
        "\u09b8\u09c7\u09a1\u09bc\u09ae"
    ],
    "name:bpy_x_preferred":[
        "\u09b8\u09c7\u09a1\u09bc\u09ae"
    ],
    "name:chi_x_preferred":[
        "\u585e\u8fbe\u59c6"
    ],
    "name:dut_x_preferred":[
        "Sedam"
    ],
    "name:eng_x_preferred":[
        "Sedam"
    ],
    "name:fre_x_preferred":[
        "Sedam"
    ],
    "name:ger_x_preferred":[
        "Sedam"
    ],
    "name:guj_x_preferred":[
        "\u0ab8\u0ac7\u0aa1\u0aae"
    ],
    "name:ita_x_preferred":[
        "Sedam"
    ],
    "name:jpn_x_preferred":[
        "\u30bb\u30c0\u30e0"
    ],
    "name:kan_x_preferred":[
        "\u0cb8\u0cc7\u0ca1\u0cae\u0ccd"
    ],
    "name:kor_x_preferred":[
        "\uc138\ub2f4"
    ],
    "name:may_x_preferred":[
        "Sedam"
    ],
    "name:mlg_x_preferred":[
        "Sedam"
    ],
    "name:nan_x_preferred":[
        "Sedam"
    ],
    "name:ori_x_preferred":[
        "\u0b38\u0b47\u0b26\u0b3e\u0b2e"
    ],
    "name:por_x_preferred":[
        "Sedam"
    ],
    "name:rus_x_preferred":[
        "\u0421\u0435\u0440\u0430\u043c"
    ],
    "name:spa_x_preferred":[
        "Sedam"
    ],
    "name:swe_x_preferred":[
        "Seram"
    ],
    "name:tam_x_preferred":[
        "\u0b9a\u0bc7\u0b9f\u0bae\u0bcd"
    ],
    "name:tel_x_preferred":[
        "\u0c38\u0c47\u0c21\u0c02"
    ],
    "name:unk_x_variant":[
        "Sedam"
    ],
    "name:urd_x_preferred":[
        "\u0633\u06cc\u062f\u0627\u0645"
    ],
    "name:vie_x_preferred":[
        "Sedam"
    ],
    "qs:name":"Seram",
    "qs:photos_9r":0,
    "qs:photos_sr":0,
    "qs:pop_sr":"7",
    "wof:name":"Seram",
    "wof:placetype":"locality",
    "wof:population":35134
},
  "geometry": {"coordinates":[77.28998,17.17859],"type":"Point"}
}