{
  "type": "Feature",
  "properties": {
    "gn:admin1_code":"12.0",
    "gn:admin2_code":"001",
    "gn:asciiname":"Moghalpur",
    "gn:country_code":"IN",
    "gn:dem":1609,
    "gn:feature_class":"P",
    "gn:feature_code":"PPL",
    "gn:name":"Moghalpur",
    "gn:population":0,
    "gn:timezone":"Asia/Kolkata",
    "iso:country":"IN",
    "name:eng_x_preferred":[
        "Mughalpur"
    ],
    "wof:name":"Moghalpur",
    "wof:placetype":"locality"
},
  "geometry": {"coordinates":[74.25577,34.5057],"type":"Point"}
}