{
  "type": "Feature",
  "properties": {
    "gn:country":"IN",
    "gn:fcode":"PPL",
    "gn:pop":19166,
    "iso:country":"IN",
    "name:bpy_x_preferred":[
        "\u0987\u09b0\u09c1\u0997\u09c1\u09a1\u09bc"
    ],
    "name:ceb_x_preferred":[
        "Irug\u016br"
    ],
    "name:eng_x_preferred":[
        "Irugur"
    ],
    "name:ita_x_preferred":[
        "Irugur"
    ],
    "name:msa_x_preferred":[
        "Irugur"
    ],
    "name:nan_x_preferred":[
        "Irugur"
    ],
    "name:new_x_preferred":[
        "\u0907\u0930\u0941\u0917\u0941\u0930"
    ],
    "name:nld_x_preferred":[
        "Irugur"
    ],
    "name:por_x_preferred":[
        "Irugur"
    ],
    "name:swe_x_preferred":[
        "Irug\u016br"
    ],
    "name:tam_x_preferred":[
        "\u0b87\u0bb0\u0bc1\u0b95\u0bc2\u0bb0\u0bcd"
    ],
    "name:unk_x_variant":[
        "Irug\u016br"
    ],
    "name:vie_x_preferred":[
        "Irugur"
    ],
    "name:zho_x_preferred":[
        "\u4f0a\u9c81\u53e4\u5c14"
    ],
    "qs:name":"Irugur",
    "qs:name_adm0":"India",
    "qs:name_adm1":"Tamil Nadu",
    "qs:photos_9r":0,
    "qs:photos_sr":0,
    "qs:placetype":"Town",
    "qs:pop_sr":"6",
    "wd:wordcount":201,
    "wof:name":"Irugur",
    "wof:placetype":"locality",
    "wof:population":19166
},
  "geometry": {"coordinates":[77.06623999999999,11.01866],"type":"Point"}
}