{
  "type": "Feature",
  "properties": {
    "iso:country":"IN",
    "ks:ks_name":"Ramra",
    "ks:ks_pop":777,
    "ks:ks_type":"HABITATION",
    "name:eng_x_preferred":[
        "Ramra"
    ],
    "wof:name":"Ramra",
    "wof:placetype":"locality",
    "wof:population":777
},
  "geometry": {"coordinates":[72.886989,28.287039],"type":"Point"}
}