{
  "type": "Feature",
  "properties": {
    "iso:country":"IN",
    "ks:ks_name":"Kastnoli",
    "ks:ks_pop":58,
    "ks:ks_type":"HABITATION",
    "name:eng_x_preferred":[
        "Kastnoli"
    ],
    "wof:name":"Kastnoli",
    "wof:placetype":"locality",
    "wof:population":58
},
  "geometry": {"coordinates":[79.540238,29.50157],"type":"Point"}
}