{
  "type": "Feature",
  "properties": {
    "gn:admin1_code":"28.0",
    "gn:admin2_code":"330.0",
    "gn:asciiname":"Bahangaon",
    "gn:country_code":"IN",
    "gn:dem":37,
    "gn:feature_class":"P",
    "gn:feature_code":"PPL",
    "gn:name":"B\u0101hangaon",
    "gn:population":0,
    "gn:timezone":"Asia/Kolkata",
    "iso:country":"IN",
    "wof:name":"Bahangaon",
    "wof:placetype":"locality"
},
  "geometry": {"coordinates":[87.96798000000003,25.76667],"type":"Point"}
}