{
  "type": "Feature",
  "properties": {
    "gn:admin1_code":"16",
    "gn:admin2_code":"529.0",
    "gn:asciiname":"Pinguli",
    "gn:country_code":"IN",
    "gn:dem":27,
    "gn:feature_class":"P",
    "gn:feature_code":"PPL",
    "gn:name":"Pinguli",
    "gn:population":0,
    "gn:timezone":"Asia/Kolkata",
    "iso:country":"IN",
    "ks:ks_name":"Pinguli",
    "ks:ks_pop":1489,
    "ks:ks_type":"VILLAGE",
    "ks:ks_uagg_main":0,
    "name:eng_x_preferred":[
        "Pinguli"
    ],
    "wof:name":"Pinguli",
    "wof:placetype":"locality",
    "wof:population":1489
},
  "geometry": {"coordinates":[73.704661,15.978724],"type":"Point"}
}