{
  "type": "Feature",
  "properties": {
    "gn:admin1_code":"36",
    "gn:admin2_code":"149.0",
    "gn:asciiname":"Ranwaiya",
    "gn:country_code":"IN",
    "gn:dem":169,
    "gn:feature_class":"P",
    "gn:feature_code":"PPL",
    "gn:name":"Ranwaiya",
    "gn:population":0,
    "gn:timezone":"Asia/Kolkata",
    "iso:country":"IN",
    "wof:name":"Ranwaiya",
    "wof:placetype":"locality"
},
  "geometry": {"coordinates":[78.91319,27.98577],"type":"Point"}
}