{
  "type": "Feature",
  "properties": {
    "gn:admin1_code":"24",
    "gn:admin2_code":"105.0",
    "gn:asciiname":"Naugaon",
    "gn:country_code":"IN",
    "gn:dem":185,
    "gn:feature_class":"P",
    "gn:feature_code":"PPL",
    "gn:name":"Naugaon",
    "gn:population":0,
    "gn:timezone":"Asia/Kolkata",
    "iso:country":"IN",
    "wof:name":"Naugaon",
    "wof:placetype":"neighbourhood"
},
  "geometry": {"coordinates":[77.57872999999999,27.25003],"type":"Point"}
}