{
  "type": "Feature",
  "properties": {
    "iso:country":"IN",
    "ks:ks_name":"Asna",
    "ks:ks_pop":207,
    "ks:ks_type":"VILLAGE",
    "name:eng_x_preferred":[
        "Asna"
    ],
    "wof:name":"Asna",
    "wof:placetype":"locality",
    "wof:population":207
},
  "geometry": {"coordinates":[87.273348,24.392129],"type":"Point"}
}