{
  "type": "Feature",
  "properties": {
    "gn:admin1_code":"36",
    "gn:admin2_code":"195.0",
    "gn:asciiname":"Shriganj",
    "gn:country_code":"IN",
    "gn:dem":76,
    "gn:feature_class":"P",
    "gn:feature_code":"PPL",
    "gn:name":"Shr\u012bganj",
    "gn:population":0,
    "gn:timezone":"Asia/Kolkata",
    "iso:country":"IN",
    "name:und_x_variant":[
        "Shr\u012bganj",
        "Nandganj"
    ],
    "wof:name":"Shriganj",
    "wof:placetype":"neighbourhood"
},
  "geometry": {"coordinates":[83.41419999999999,25.54236],"type":"Point"}
}