{
  "type": "Feature",
  "properties": {
    "iso:country":"IN",
    "ks:ks_name":"Shivaji Nagar",
    "ks:ks_pop":105,
    "ks:ks_type":"HABITATION",
    "name:eng_x_preferred":[
        "Shivaji Nagar"
    ],
    "wof:name":"Shivaji Nagar",
    "wof:placetype":"locality",
    "wof:population":105
},
  "geometry": {"coordinates":[75.87701800000001,18.482223],"type":"Point"}
}