{
  "type": "Feature",
  "properties": {
    "iso:country":"IN",
    "ks:ks_name":"Shivaji Nagar",
    "ks:ks_pop":105,
    "ks:ks_type":"HABITATION",
    "name:eng_x_preferred":[
        "Shivaji Nagar"
    ],
    "name:hin_x_preferred":[
        "\u0936\u093f\u0935\u093e\u091c\u0940 \u0928\u0917\u0930"
    ],
    "name:mar_x_preferred":[
        "\u0936\u093f\u0935\u093e\u091c\u0940 \u0928\u0917\u0930"
    ],
    "wof:name":"Shivaji Nagar",
    "wof:placetype":"locality",
    "wof:population":105
},
  "geometry": {"coordinates":[75.87701800000001,18.482223],"type":"Point"}
}