{
  "type": "Feature",
  "properties": {
    "iso:country":"IN",
    "ks:ks_name":"Badiamunda",
    "ks:ks_pop":5,
    "ks:ks_type":"VILLAGE",
    "name:eng_x_preferred":[
        "Badiamunda"
    ],
    "wof:name":"Badiamunda",
    "wof:placetype":"locality",
    "wof:population":5
},
  "geometry": {"coordinates":[85.62316,21.181705],"type":"Point"}
}