{
  "type": "Feature",
  "properties": {
    "iso:country":"IN",
    "ks:ks_name":"Thala Fali",
    "ks:ks_pop":180,
    "ks:ks_type":"HABITATION",
    "name:eng_x_preferred":[
        "Thala Fali"
    ],
    "wof:name":"Thala Fali",
    "wof:placetype":"locality",
    "wof:population":180
},
  "geometry": {"coordinates":[72.97362800000001,24.502008],"type":"Point"}
}