{
  "type": "Feature",
  "properties": {
    "iso:country":"IN",
    "ks:ks_name":"Rajura",
    "ks:ks_pop":28,
    "ks:ks_type":"HABITATION",
    "name:eng_x_preferred":[
        "Rajura"
    ],
    "wof:name":"Rajura",
    "wof:placetype":"locality",
    "wof:population":28
},
  "geometry": {"coordinates":[77.548241,21.280388],"type":"Point"}
}