{
  "type": "Feature",
  "properties": {
    "gn:admin1_code":"19",
    "gn:admin2_code":"559.0",
    "gn:asciiname":"Bhogiramagudda",
    "gn:country_code":"IN",
    "gn:dem":442,
    "gn:feature_class":"P",
    "gn:feature_code":"PPL",
    "gn:name":"Bhog\u012br\u0101magudda",
    "gn:population":0,
    "gn:timezone":"Asia/Kolkata",
    "iso:country":"IN",
    "wof:name":"Bhogiramagudda",
    "wof:placetype":"locality"
},
  "geometry": {"coordinates":[76.77011,16.30851],"type":"Point"}
}