{
  "type": "Feature",
  "properties": {
    "gn:admin1_code":"34.0",
    "gn:admin2_code":"235.0",
    "gn:asciiname":"Harihar Bigha",
    "gn:country_code":"IN",
    "gn:dem":113,
    "gn:feature_class":"P",
    "gn:feature_code":"PPL",
    "gn:name":"Harihar Bigha",
    "gn:population":0,
    "gn:timezone":"Asia/Kolkata",
    "iso:country":"IN",
    "wof:name":"Harihar Bigha",
    "wof:placetype":"locality"
},
  "geometry": {"coordinates":[84.21881999999999,24.81582],"type":"Point"}
}