{
  "type": "Feature",
  "properties": {
    "iso:country":"IN",
    "ks:ks_name":"Rehaiya",
    "ks:ks_pop":220,
    "ks:ks_type":"HABITATION",
    "name:eng_x_preferred":[
        "Rehaiya"
    ],
    "wof:name":"Rehaiya",
    "wof:placetype":"locality",
    "wof:population":220
},
  "geometry": {"coordinates":[84.5351,23.680559],"type":"Point"}
}