{
  "type": "Feature",
  "properties": {
    "iso:country":"IN",
    "ks:ks_alt_nam":"Vil\u0101ngudi",
    "ks:ks_name":"Vilangudi",
    "ks:ks_type":"VILLAGE",
    "ks:ks_uagg_main":0,
    "name:eng_x_preferred":[
        "Vilangudi"
    ],
    "name:eng_x_variant":[
        "Vil\u0101ngudi"
    ],
    "wof:name":"Vilangudi",
    "wof:placetype":"neighbourhood"
},
  "geometry": {"coordinates":[78.09352199999999,9.945782],"type":"Point"}
}