{
  "type": "Feature",
  "properties": {
    "iso:country":"IN",
    "ks:ks_name":"Fateh Nagar",
    "ks:ks_pop":609,
    "ks:ks_type":"HABITATION",
    "name:eng_x_preferred":[
        "Fateh Nagar"
    ],
    "wof:name":"Fateh Nagar",
    "wof:placetype":"locality",
    "wof:population":609
},
  "geometry": {"coordinates":[71.844847,26.100725],"type":"Point"}
}