{
  "type": "Feature",
  "properties": {
    "gn:admin1_code":"36",
    "gn:admin2_code":"186.0",
    "gn:asciiname":"Umaria",
    "gn:country_code":"IN",
    "gn:dem":85,
    "gn:feature_class":"P",
    "gn:feature_code":"PPL",
    "gn:name":"Umaria",
    "gn:population":0,
    "gn:timezone":"Asia/Kolkata",
    "iso:country":"IN",
    "ks:ks_name":"Umaria",
    "ks:ks_pop":842,
    "ks:ks_type":"VILLAGE",
    "ks:ks_uagg_main":0,
    "name:ara_x_preferred":[
        "\u0623\u0648\u0645\u0627\u0631\u064a\u0627"
    ],
    "name:ben_bn_x_preferred":[
        "\u0989\u09ae\u09be\u09b0\u09bf\u09df\u09be"
    ],
    "name:ben_in_x_preferred":[
        "\u0989\u09ae\u09be\u09b0\u09bf\u09df\u09be"
    ],
    "name:ben_x_preferred":[
        "\u0989\u09ae\u09be\u09b0\u09bf\u09af\u09bc\u09be"
    ],
    "name:bpy_x_preferred":[
        "\u0989\u09ae\u09be\u09b0\u09bf\u09af\u09bc\u09be"
    ],
    "name:eng_x_preferred":[
        "Umaria"
    ],
    "name:fra_x_preferred":[
        "Umaria"
    ],
    "name:guj_x_preferred":[
        "\u0a89\u0aae\u0ab0\u0abf\u0aaf\u0abe"
    ],
    "name:guj_x_variant":[
        "\u0a89\u0aae\u0ab0\u0abf\u0aaf\u0abe"
    ],
    "name:hif_x_preferred":[
        "Umaria"
    ],
    "name:hin_x_preferred":[
        "\u0909\u092e\u0930\u093f\u092f\u093e"
    ],
    "name:ita_x_preferred":[
        "Umaria"
    ],
    "name:kan_x_preferred":[
        "\u0c89\u0cae\u0cb0\u0cbf\u0caf\u0cbe"
    ],
    "name:mal_x_preferred":[
        "\u0d09\u0d2e\u0d30\u0d3f\u0d2f"
    ],
    "name:mar_x_preferred":[
        "\u0909\u092e\u0930\u093f\u092f\u093e"
    ],
    "name:mlg_x_preferred":[
        "Umaria"
    ],
    "name:msa_x_preferred":[
        "Umaria"
    ],
    "name:pan_x_preferred":[
        "\u0a09\u0a2e\u0a3e\u0a30\u0a40\u0a06"
    ],
    "name:por_x_preferred":[
        "Umaria"
    ],
    "name:san_x_preferred":[
        "\u0909\u092e\u0930\u093f\u092f\u093e"
    ],
    "name:spa_x_preferred":[
        "Umaria"
    ],
    "name:swe_x_preferred":[
        "Umaria"
    ],
    "name:tam_x_preferred":[
        "\u0b89\u0bae\u0bcd\u0bae\u0bbe\u0bb0\u0bbf\u0baf\u0bbe"
    ],
    "name:tel_x_preferred":[
        "\u0c09\u0c2e\u0c3e\u0c30\u0c3f\u0c2f\u0c3e"
    ],
    "name:urd_x_preferred":[
        "\u0627\u0648\u0645\u0631\u06cc\u0627"
    ],
    "name:urd_x_variant":[
        "\u0627\u0648\u0645\u0627\u0631\u06cc\u0627"
    ],
    "name:vie_x_preferred":[
        "Umaria"
    ],
    "name:zho_x_preferred":[
        "\u4e4c\u9a6c\u91cc\u4e9a"
    ],
    "wof:name":"Umaria",
    "wof:placetype":"neighbourhood",
    "wof:population":842
},
  "geometry": {"coordinates":[82.992318,26.520938],"type":"Point"}
}