{
  "type": "Feature",
  "properties": {
    "iso:country":"IN",
    "ks:ks_name":"Balebhatle",
    "ks:ks_pop":147,
    "ks:ks_type":"HABITATION",
    "name:eng_x_preferred":[
        "Balebhatle"
    ],
    "wof:name":"Balebhatle",
    "wof:placetype":"locality",
    "wof:population":147
},
  "geometry": {"coordinates":[74.040755,16.014196],"type":"Point"}
}