{
  "type": "Feature",
  "properties": {
    "iso:country":"IN",
    "ks:ks_alt_nam":"V\u012br\u0101pur",
    "ks:ks_name":"Virapur",
    "ks:ks_type":"VILLAGE",
    "name:eng_x_preferred":[
        "Virapur"
    ],
    "name:eng_x_variant":[
        "V\u012br\u0101pur"
    ],
    "wof:name":"Virapur",
    "wof:placetype":"locality"
},
  "geometry": {"coordinates":[74.988118,14.821797],"type":"Point"}
}