{
  "type": "Feature",
  "properties": {
    "gn:admin1_code":"23.0",
    "gn:admin2_code":"48.0",
    "gn:asciiname":"Rurki",
    "gn:country_code":"IN",
    "gn:dem":262,
    "gn:feature_class":"P",
    "gn:feature_code":"PPL",
    "gn:name":"Rurki",
    "gn:population":0,
    "gn:timezone":"Asia/Kolkata",
    "iso:country":"IN",
    "name:fas_x_preferred":[
        "\u0631\u0648\u0631\u06a9\u06cc"
    ],
    "name:zho_x_preferred":[
        "\u5362\u5c14\u57fa"
    ],
    "wof:name":"Rurki",
    "wof:placetype":"locality"
},
  "geometry": {"coordinates":[76.47414999999999,30.36953],"type":"Point"}
}