{
  "type": "Feature",
  "properties": {
    "gn:admin1_code":"36.0",
    "gn:admin2_code":"139.0",
    "gn:asciiname":"Bilochpura",
    "gn:country_code":"IN",
    "gn:dem":226,
    "gn:feature_class":"P",
    "gn:feature_code":"PPL",
    "gn:name":"Bilochpura",
    "gn:population":0,
    "gn:timezone":"Asia/Kolkata",
    "iso:country":"IN",
    "wof:name":"Bilochpura",
    "wof:placetype":"locality"
},
  "geometry": {"coordinates":[77.34029,29.00573],"type":"Point"}
}