{
  "type": "Feature",
  "properties": {
    "iso:country":"IN",
    "ks:ks_name":"Gopalpur",
    "ks:ks_pop":740,
    "ks:ks_type":"VILLAGE",
    "ks:ks_uagg_main":0,
    "name:eng_x_preferred":[
        "Gopalpur"
    ],
    "wof:name":"Gopalpur",
    "wof:placetype":"neighbourhood",
    "wof:population":740
},
  "geometry": {"coordinates":[85.92971199999999,20.824805],"type":"Point"}
}