{
  "type": "Feature",
  "properties": {
    "gn:admin1_code":"34.0",
    "gn:admin2_code":"206",
    "gn:asciiname":"Bela Muchhpakauni",
    "gn:country_code":"IN",
    "gn:dem":80,
    "gn:feature_class":"P",
    "gn:feature_code":"PPL",
    "gn:name":"Bela Muchhpakauni",
    "gn:population":0,
    "gn:timezone":"Asia/Kolkata",
    "iso:country":"IN",
    "name:und_x_variant":[
        "Bela",
        "Bela Muchhpakauni"
    ],
    "wof:name":"Bela Muchhpakauni",
    "wof:placetype":"neighbourhood"
},
  "geometry": {"coordinates":[85.72821,26.77538],"type":"Point"}
}