{
  "type": "Feature",
  "properties": {
    "gn:admin1_code":"03",
    "gn:admin2_code":"324.0",
    "gn:asciiname":"Kumrikhata",
    "gn:country_code":"IN",
    "gn:dem":108,
    "gn:feature_class":"P",
    "gn:feature_code":"PPL",
    "gn:name":"Kumrikh\u0101ta",
    "gn:population":0,
    "gn:timezone":"Asia/Kolkata",
    "iso:country":"IN",
    "wof:name":"Kumrikhata",
    "wof:placetype":"locality"
},
  "geometry": {"coordinates":[91.55522000000001,26.73233],"type":"Point"}
}