{
  "type": "Feature",
  "properties": {
    "iso:country":"IN",
    "ks:ks_name":"Ramireddy Kottalu",
    "ks:ks_pop":14,
    "ks:ks_type":"HABITATION",
    "name:eng_x_preferred":[
        "Ramireddy Kottalu"
    ],
    "wof:name":"Ramireddy Kottalu",
    "wof:placetype":"locality",
    "wof:population":14
},
  "geometry": {"coordinates":[78.803364,14.601176],"type":"Point"}
}