{
  "type": "Feature",
  "properties": {
    "iso:country":"IN",
    "ks:ks_name":"Nagla Sakat",
    "ks:ks_pop":43,
    "ks:ks_type":"HABITATION",
    "name:eng_x_preferred":[
        "Nagla Sakat"
    ],
    "wof:name":"Nagla Sakat",
    "wof:placetype":"locality",
    "wof:population":43
},
  "geometry": {"coordinates":[79.364152,26.909464],"type":"Point"}
}