{
  "type": "Feature",
  "properties": {
    "iso:country":"IN",
    "ks:ks_name":"Singarguda",
    "ks:ks_pop":452,
    "ks:ks_type":"HABITATION",
    "name:eng_x_preferred":[
        "Singarguda"
    ],
    "wof:name":"Singarguda",
    "wof:placetype":"locality",
    "wof:population":452
},
  "geometry": {"coordinates":[82.06555299999999,19.675661],"type":"Point"}
}