{
  "type": "Feature",
  "properties": {
    "iso:country":"IN",
    "ks:ks_alt_nam":"Paradhi wasti E",
    "ks:ks_name":"Paradhi Wasti E",
    "ks:ks_pop":57,
    "ks:ks_type":"HABITATION",
    "name:eng_x_preferred":[
        "Paradhi Wasti E"
    ],
    "wof:name":"Paradhi Wasti E",
    "wof:placetype":"locality",
    "wof:population":57
},
  "geometry": {"coordinates":[75.957324,18.512191],"type":"Point"}
}