{
  "type": "Feature",
  "properties": {
    "iso:country":"IN",
    "ks:ks_alt_nam":"DHANAIPUR",
    "ks:ks_name":"Dhanaipur",
    "ks:ks_pop":402,
    "ks:ks_type":"HABITATION",
    "name:eng_x_preferred":[
        "Dhanaipur"
    ],
    "wof:name":"Dhanaipur",
    "wof:placetype":"locality",
    "wof:population":402
},
  "geometry": {"coordinates":[83.85707600000001,25.880808],"type":"Point"}
}