{
  "type": "Feature",
  "properties": {
    "gn:admin1_code":"36",
    "gn:admin2_code":"195.0",
    "gn:asciiname":"Bharatpur",
    "gn:country_code":"IN",
    "gn:dem":82,
    "gn:feature_class":"P",
    "gn:feature_code":"PPL",
    "gn:name":"Bharatpur",
    "gn:population":0,
    "gn:timezone":"Asia/Kolkata",
    "iso:country":"IN",
    "ks:ks_name":"Bharatpur",
    "ks:ks_pop":702,
    "ks:ks_type":"VILLAGE",
    "ks:ks_uagg_main":0,
    "name:ara_x_preferred":[
        "\u0628\u0647\u0627\u0631\u0627\u062a\u0628\u0648\u0631"
    ],
    "name:bar_x_preferred":[
        "Bharatpur"
    ],
    "name:ben_bn_x_preferred":[
        "\u09ad\u09b0\u09a4\u09aa\u09c1\u09b0"
    ],
    "name:ben_in_x_preferred":[
        "\u09ad\u09b0\u09a4\u09aa\u09c1\u09b0"
    ],
    "name:ceb_x_preferred":[
        "Bharatpur"
    ],
    "name:deu_x_preferred":[
        "Bharatpur"
    ],
    "name:eng_x_preferred":[
        "Bharatpur"
    ],
    "name:epo_x_preferred":[
        "Bharatpur"
    ],
    "name:fas_x_preferred":[
        "\u0628\u0647\u0627\u0631\u0627\u062a \u067e\u0648\u0631"
    ],
    "name:fra_x_preferred":[
        "Bharatpur"
    ],
    "name:guj_x_preferred":[
        "\u0aad\u0ab0\u0aa4\u0aaa\u0ac1\u0ab0"
    ],
    "name:heb_x_preferred":[
        "\u05d1\u05d7\u05d0\u05e8\u05d0\u05d8\u05e4\u05d5\u05e8"
    ],
    "name:hin_x_preferred":[
        "\u092d\u0930\u0924\u092a\u0941\u0930"
    ],
    "name:hun_x_preferred":[
        "Bharatpur"
    ],
    "name:ita_x_preferred":[
        "Bharatpur"
    ],
    "name:kan_x_preferred":[
        "\u0cad\u0cb0\u0ca4\u0ccd"
    ],
    "name:kor_x_preferred":[
        "\ubc14\ub78f\ud478\ub974"
    ],
    "name:mal_x_preferred":[
        "\u0d2d\u0d30\u0d24\u0d4d\u0d2a\u0d42\u0d7c"
    ],
    "name:mar_x_preferred":[
        "\u092d\u0930\u0924\u092a\u0942\u0930"
    ],
    "name:msa_x_preferred":[
        "Bharatpur"
    ],
    "name:new_x_preferred":[
        "\u092d\u0930\u0924\u092a\u0941\u0930 \u0968"
    ],
    "name:nld_x_preferred":[
        "Bharatpur"
    ],
    "name:pan_x_preferred":[
        "\u0a2d\u0a30\u0a24\u0a2a\u0a41\u0a30"
    ],
    "name:pnb_x_preferred":[
        "\u0628\u06c1\u0631\u062a \u067e\u0648\u0631"
    ],
    "name:swe_x_preferred":[
        "Bharatpur"
    ],
    "name:tam_x_preferred":[
        "\u0baa\u0bbe\u0bb0\u0ba4\u0bcd\u0baa\u0bc2\u0bb0\u0bcd"
    ],
    "name:tam_x_variant":[
        "\u0baa\u0bb0\u0ba4\u0bcd\u0baa\u0bc2\u0bb0\u0bcd"
    ],
    "name:tel_x_preferred":[
        "\u0c2d\u0c30\u0c24\u0c4d"
    ],
    "name:urd_x_preferred":[
        "\u0628\u06be\u0631\u062a \u067e\u0648\u0631"
    ],
    "wof:name":"Bharatpur",
    "wof:placetype":"neighbourhood",
    "wof:population":702
},
  "geometry": {"coordinates":[83.231296,25.736588],"type":"Point"}
}