{
  "type": "Feature",
  "properties": {
    "gn:admin1_code":"13.0",
    "gn:admin2_code":"592",
    "gn:asciiname":"Edayur",
    "gn:country_code":"IN",
    "gn:dem":54,
    "gn:feature_class":"P",
    "gn:feature_code":"PPL",
    "gn:name":"Eday\u016br",
    "gn:population":0,
    "gn:timezone":"Asia/Kolkata",
    "iso:country":"IN",
    "name:und_x_variant":[
        "Edayar",
        "Eday\u016br"
    ],
    "wof:name":"Edayur",
    "wof:placetype":"locality"
},
  "geometry": {"coordinates":[76.11194999999999,10.93492],"type":"Point"}
}