{
  "type": "Feature",
  "properties": {
    "iso:country":"IN",
    "ks:ks_name":"Sunkaravaripalle",
    "ks:ks_pop":125,
    "ks:ks_type":"VILLAGE",
    "name:eng_x_preferred":[
        "Sunkaravaripalle"
    ],
    "wof:name":"Sunkaravaripalle",
    "wof:placetype":"locality",
    "wof:population":125
},
  "geometry": {"coordinates":[79.55690800000001,13.951032],"type":"Point"}
}