{
  "type": "Feature",
  "properties": {
    "iso:country":"IN",
    "ks:ks_name":"Karnegandi",
    "ks:ks_pop":185,
    "ks:ks_type":"VILLAGE",
    "name:eng_x_preferred":[
        "Karnegandi"
    ],
    "wof:name":"Karnegandi",
    "wof:placetype":"locality",
    "wof:population":185
},
  "geometry": {"coordinates":[80.169653,17.959401],"type":"Point"}
}