{
  "type": "Feature",
  "properties": {
    "gn:admin1_code":"34.0",
    "gn:admin2_code":"221.0",
    "gn:asciiname":"Harpur Pusa",
    "gn:country_code":"IN",
    "gn:dem":53,
    "gn:feature_class":"P",
    "gn:feature_code":"PPL",
    "gn:name":"Harpur P\u016bsa",
    "gn:population":0,
    "gn:timezone":"Asia/Kolkata",
    "iso:country":"IN",
    "ks:ks_alt_nam":"Harpur P\u016bsa",
    "ks:ks_name":"Harpur Pusa",
    "ks:ks_pop":4889,
    "ks:ks_type":"VILLAGE",
    "name:eng_x_preferred":[
        "Harpur Pusa"
    ],
    "name:eng_x_variant":[
        "Harpur P\u016bsa"
    ],
    "wof:name":"Harpur Pusa",
    "wof:placetype":"locality",
    "wof:population":4889
},
  "geometry": {"coordinates":[85.661838,25.971484],"type":"Point"}
}