{
  "type": "Feature",
  "properties": {
    "iso:country":"IN",
    "ks:ks_name":"Kurmi Tola",
    "ks:ks_pop":285,
    "ks:ks_type":"HABITATION",
    "ks:ks_uagg_main":0,
    "name:eng_x_preferred":[
        "Kurmi Tola"
    ],
    "wof:name":"Kurmi Tola",
    "wof:placetype":"neighbourhood",
    "wof:population":285
},
  "geometry": {"coordinates":[86.401679,25.991149],"type":"Point"}
}