{
  "type": "Feature",
  "properties": {
    "gn:admin1_code":"11.0",
    "gn:admin2_code":"32.0",
    "gn:asciiname":"Shatri",
    "gn:country_code":"IN",
    "gn:dem":1307,
    "gn:feature_class":"P",
    "gn:feature_code":"PPL",
    "gn:name":"Sh\u0101tri",
    "gn:population":0,
    "gn:timezone":"Asia/Kolkata",
    "iso:country":"IN",
    "wof:name":"Shatri",
    "wof:placetype":"locality"
},
  "geometry": {"coordinates":[77.20696,30.67191],"type":"Point"}
}