{
  "type": "Feature",
  "properties": {
    "iso:country":"IN",
    "ks:ks_name":"Jonia",
    "ks:ks_pop":58,
    "ks:ks_type":"VILLAGE",
    "name:eng_x_preferred":[
        "Jonia"
    ],
    "wof:name":"Jonia",
    "wof:placetype":"locality",
    "wof:population":58
},
  "geometry": {"coordinates":[87.417134,24.872689],"type":"Point"}
}