{
  "type": "Feature",
  "properties": {
    "gn:admin1_code":"34.0",
    "gn:admin2_code":"217.0",
    "gn:asciiname":"Bankata",
    "gn:country_code":"IN",
    "gn:dem":81,
    "gn:feature_class":"P",
    "gn:feature_code":"PPL",
    "gn:name":"Bankat\u0101",
    "gn:population":0,
    "gn:timezone":"Asia/Kolkata",
    "iso:country":"IN",
    "name:nep_x_preferred":[
        "\u0935\u0928\u0915\u093e\u091f\u093e"
    ],
    "wof:name":"Bankata",
    "wof:placetype":"locality"
},
  "geometry": {"coordinates":[84.19565,26.5514],"type":"Point"}
}