{
  "type": "Feature",
  "properties": {
    "iso:country":"IN",
    "ks:ks_name":"Bhensia",
    "ks:ks_pop":8309,
    "ks:ks_type":"VILLAGE",
    "ks:ks_uagg_main":0,
    "name:eng_x_preferred":[
        "Bhensia"
    ],
    "wof:name":"Bhensia",
    "wof:placetype":"neighbourhood",
    "wof:population":8309
},
  "geometry": {"coordinates":[78.82890999999999,28.83888],"type":"Point"}
}