{
  "type": "Feature",
  "properties": {
    "iso:country":"IN",
    "ks:ks_name":"Jagat Khera",
    "ks:ks_pop":722,
    "ks:ks_type":"HABITATION",
    "name:eng_x_preferred":[
        "Jagat Khera"
    ],
    "wof:name":"Jagat Khera",
    "wof:placetype":"locality",
    "wof:population":722
},
  "geometry": {"coordinates":[80.72080099999999,26.383329],"type":"Point"}
}