{
  "type": "Feature",
  "properties": {
    "iso:country":"IN",
    "ks:ks_alt_nam":"Jah\u0101npur",
    "ks:ks_name":"Jahanpur",
    "ks:ks_type":"VILLAGE",
    "name:eng_x_preferred":[
        "Jahanpur"
    ],
    "name:eng_x_variant":[
        "Jah\u0101npur"
    ],
    "wof:name":"Jahanpur",
    "wof:placetype":"locality"
},
  "geometry": {"coordinates":[80.82503699999999,27.267618],"type":"Point"}
}