{
  "type": "Feature",
  "properties": {
    "gn:admin1_code":"23.0",
    "gn:admin2_code":"49.0",
    "gn:asciiname":"Qila Jiwan Singh",
    "gn:country_code":"IN",
    "gn:dem":231,
    "gn:feature_class":"P",
    "gn:feature_code":"PPL",
    "gn:name":"Qila J\u012bwan Singh",
    "gn:population":0,
    "gn:timezone":"Asia/Kolkata",
    "iso:country":"IN",
    "wof:name":"Qila Jiwan Singh",
    "wof:placetype":"locality"
},
  "geometry": {"coordinates":[74.97404,31.61823],"type":"Point"}
}