{
  "type": "Feature",
  "properties": {
    "iso:country":"IN",
    "name:eng_x_preferred":[
        "Habeliya"
    ],
    "qs:gn_local":0,
    "qs:local_max":139,
    "qs:local_sum":139,
    "qs:localhoods":1,
    "qs:name":"Habeliya",
    "qs:name_adm0":"India",
    "qs:name_adm1":"Uttar Pradesh",
    "qs:name_adm2":"Allahabad",
    "qs:name_local":"Jhusi Kohna",
    "qs:photo_max":65,
    "qs:photo_sum":139,
    "qs:placetype":"Suburb",
    "qs:quad_count":11,
    "qs:woe_adm0":23424848,
    "qs:woe_adm1":2345760,
    "qs:woe_adm2":12586715,
    "qs:woe_lau":0,
    "qs:woe_local":28999911,
    "qs:woe_ver":"7.10.0",
    "wof:lang":[
        "eng"
    ],
    "wof:name":"Habeliya",
    "wof:placetype":"neighbourhood"
},
  "geometry": {"coordinates":[81.908213,25.411961],"type":"Point"}
}