{
  "type": "Feature",
  "properties": {
    "iso:country":"IN",
    "name:ara_x_preferred":[
        "\u0647\u0627\u0628\u064a\u0644\u064a\u0627"
    ],
    "name:ben_bn_x_preferred":[
        "\u09b9\u09be\u09ac\u09c7\u09b2\u09bf\u09df\u09be"
    ],
    "name:ben_in_x_preferred":[
        "\u09b9\u09be\u09ac\u09c7\u09b2\u09bf\u09df\u09be"
    ],
    "name:eng_x_preferred":[
        "Habeliya"
    ],
    "name:guj_x_preferred":[
        "\u0ab9\u0aac\u0ac7\u0ab2\u0ac0\u0a86"
    ],
    "name:hin_x_preferred":[
        "\u0939\u092c\u0947\u0932\u093f\u092f\u093e"
    ],
    "name:kan_x_preferred":[
        "\u0cb9\u0cac\u0cc6\u0cb2\u0cbf\u0caf\u0cbe"
    ],
    "name:mal_x_preferred":[
        "\u0d39\u0d2c\u0d46\u0d32\u0d3f\u0d2f"
    ],
    "name:mar_x_preferred":[
        "\u0939\u092c\u0947\u0932\u093f\u092f\u093e"
    ],
    "name:pan_x_preferred":[
        "\u0a39\u0a3e\u0a2c\u0a48\u0a32\u0a40\u0a06"
    ],
    "name:tam_x_preferred":[
        "\u0bb9\u0baa\u0bc6\u0bb2\u0bbf\u0baf\u0bbe"
    ],
    "name:tel_x_preferred":[
        "\u0c39\u0c47\u0c2c\u0c46\u0c32\u0c3f\u0c2f\u0c3e"
    ],
    "name:urd_x_preferred":[
        "\u06c1\u0628\u06cc\u0644\u06cc\u0627"
    ],
    "qs:gn_local":0,
    "qs:local_max":139,
    "qs:local_sum":139,
    "qs:localhoods":1,
    "qs:name":"Habeliya",
    "qs:name_adm0":"India",
    "qs:name_adm1":"Uttar Pradesh",
    "qs:name_adm2":"Allahabad",
    "qs:name_local":"Jhusi Kohna",
    "qs:photo_max":65,
    "qs:photo_sum":139,
    "qs:placetype":"Suburb",
    "qs:quad_count":11,
    "qs:woe_adm0":23424848,
    "qs:woe_adm1":2345760,
    "qs:woe_adm2":12586715,
    "qs:woe_lau":0,
    "qs:woe_local":28999911,
    "qs:woe_ver":"7.10.0",
    "wof:lang":[
        "eng"
    ],
    "wof:name":"Habeliya",
    "wof:placetype":"neighbourhood"
},
  "geometry": {"coordinates":[81.908213,25.411961],"type":"Point"}
}