{
  "type": "Feature",
  "properties": {
    "gn:admin1_code":"13.0",
    "gn:admin2_code":"600.0",
    "gn:asciiname":"Kottukal",
    "gn:country_code":"IN",
    "gn:dem":71,
    "gn:feature_class":"P",
    "gn:feature_code":"PPL",
    "gn:name":"Kottukal",
    "gn:population":0,
    "gn:timezone":"Asia/Kolkata",
    "iso:country":"IN",
    "ks:ks_name":"Kottukkal",
    "ks:ks_pop":889,
    "ks:ks_type":"VILLAGE",
    "name:eng_x_preferred":[
        "Kottukkal"
    ],
    "name:eng_x_variant":[
        "Kottukal"
    ],
    "wof:name":"Kottukkal",
    "wof:placetype":"locality",
    "wof:population":889
},
  "geometry": {"coordinates":[76.907039,8.899309],"type":"Point"}
}