{
  "type": "Feature",
  "properties": {
    "iso:country":"IN",
    "ks:ks_name":"Khanivade",
    "ks:ks_pop":820,
    "ks:ks_type":"VILLAGE",
    "name:eng_x_preferred":[
        "Khanivade"
    ],
    "wof:name":"Khanivade",
    "wof:placetype":"locality",
    "wof:population":820
},
  "geometry": {"coordinates":[72.81363899999999,19.801806],"type":"Point"}
}