{
  "type": "Feature",
  "properties": {
    "gn:admin1_code":"25.0",
    "gn:asciiname":"Wadarkoppa",
    "gn:country_code":"IN",
    "gn:dem":758,
    "gn:feature_class":"P",
    "gn:feature_code":"PPL",
    "gn:name":"Wadarkoppa",
    "gn:population":0,
    "gn:timezone":"Asia/Kolkata",
    "iso:country":"IN",
    "wof:name":"Wadarkoppa",
    "wof:placetype":"locality"
},
  "geometry": {"coordinates":[77.59359000000001,12.64149],"type":"Point"}
}