{
  "type": "Feature",
  "properties": {
    "iso:country":"IN",
    "ks:ks_name":"Chora Khurd",
    "ks:ks_pop":745,
    "ks:ks_type":"VILLAGE",
    "name:eng_x_preferred":[
        "Chora Khurd"
    ],
    "wof:name":"Chora Khurd",
    "wof:placetype":"locality",
    "wof:population":745
},
  "geometry": {"coordinates":[74.348319,23.075592],"type":"Point"}
}