{
  "type": "Feature",
  "properties": {
    "iso:country":"IN",
    "ks:ks_name":"Itarangaon",
    "ks:ks_pop":287,
    "ks:ks_type":"HABITATION",
    "name:eng_x_preferred":[
        "Itarangaon"
    ],
    "wof:name":"Itarangaon",
    "wof:placetype":"locality",
    "wof:population":287
},
  "geometry": {"coordinates":[81.728798,24.878049],"type":"Point"}
}