{
  "type": "Feature",
  "properties": {
    "iso:country":"IN",
    "ks:ks_name":"Mahabirbari 765/348",
    "ks:ks_pop":265,
    "ks:ks_type":"VILLAGE",
    "ks:ks_uagg_main":0,
    "name:eng_x_preferred":[
        "Mahabirbari 765/348"
    ],
    "wof:name":"Mahabirbari 765/348",
    "wof:placetype":"neighbourhood",
    "wof:population":265
},
  "geometry": {"coordinates":[95.411393,27.359892],"type":"Point"}
}