{
  "type": "Feature",
  "properties": {
    "iso:country":"IN",
    "ks:ks_name":"Malli Pipali",
    "ks:ks_pop":153,
    "ks:ks_type":"VILLAGE",
    "name:eng_x_preferred":[
        "Malli Pipali"
    ],
    "wof:name":"Malli Pipali",
    "wof:placetype":"locality",
    "wof:population":153
},
  "geometry": {"coordinates":[79.838109,29.43862],"type":"Point"}
}