{
  "type": "Feature",
  "properties": {
    "gn:admin1_code":"11",
    "gn:admin2_code":"24.0",
    "gn:asciiname":"Jor",
    "gn:country_code":"IN",
    "gn:dem":549,
    "gn:feature_class":"P",
    "gn:feature_code":"PPL",
    "gn:name":"Jor",
    "gn:population":0,
    "gn:timezone":"Asia/Kolkata",
    "iso:country":"IN",
    "name:ceb_x_preferred":[
        "Jor"
    ],
    "name:swe_x_preferred":[
        "Jor"
    ],
    "wof:name":"Jor",
    "wof:placetype":"locality"
},
  "geometry": {"coordinates":[76.20404000000001,31.96338],"type":"Point"}
}