{
  "type": "Feature",
  "properties": {
    "gn:admin1_code":"09",
    "gn:admin2_code":"477.0",
    "gn:asciiname":"Luwarsal",
    "gn:country_code":"IN",
    "gn:dem":174,
    "gn:feature_class":"P",
    "gn:feature_code":"PPL",
    "gn:name":"Luw\u0101rs\u0101l",
    "gn:population":0,
    "gn:timezone":"Asia/Kolkata",
    "iso:country":"IN",
    "name:und_x_variant":[
        "Luvarsal",
        "Luw\u0101rs\u0101l"
    ],
    "wof:name":"Luwarsal",
    "wof:placetype":"locality"
},
  "geometry": {"coordinates":[70.13110999999999,22.09448],"type":"Point"}
}