{
  "type": "Feature",
  "properties": {
    "iso:country":"IN",
    "ks:ks_name":"Dhobean",
    "ks:ks_pop":335,
    "ks:ks_type":"HABITATION",
    "name:eng_x_preferred":[
        "Dhobean"
    ],
    "wof:name":"Dhobean",
    "wof:placetype":"locality",
    "wof:population":335
},
  "geometry": {"coordinates":[83.122271,25.486932],"type":"Point"}
}