{
  "type": "Feature",
  "properties": {
    "iso:country":"IN",
    "ks:ks_name":"Devpura",
    "ks:ks_pop":732,
    "ks:ks_type":"VILLAGE",
    "name:eng_x_preferred":[
        "Devpura"
    ],
    "wof:name":"Devpura",
    "wof:placetype":"locality",
    "wof:population":732
},
  "geometry": {"coordinates":[73.553917,22.614317],"type":"Point"}
}