{
  "type": "Feature",
  "properties": {
    "iso:country":"IN",
    "ks:ks_name":"Rikhari Dhorituri",
    "ks:ks_pop":162,
    "ks:ks_type":"HABITATION",
    "name:eng_x_preferred":[
        "Rikhari Dhorituri"
    ],
    "wof:name":"Rikhari Dhorituri",
    "wof:placetype":"locality",
    "wof:population":162
},
  "geometry": {"coordinates":[79.298389,29.782208],"type":"Point"}
}