{
  "type": "Feature",
  "properties": {
    "iso:country":"IN",
    "ks:ks_name":"Battuvanithanda",
    "ks:ks_pop":88,
    "ks:ks_type":"HABITATION",
    "name:eng_x_preferred":[
        "Battuvanithanda"
    ],
    "wof:name":"Battuvanithanda",
    "wof:placetype":"locality",
    "wof:population":88
},
  "geometry": {"coordinates":[79.261976,17.914116],"type":"Point"}
}