{
  "type": "Feature",
  "properties": {
    "gn:admin1_code":"19.0",
    "gn:admin2_code":"557.0",
    "gn:asciiname":"Chokavi",
    "gn:country_code":"IN",
    "gn:dem":533,
    "gn:feature_class":"P",
    "gn:feature_code":"PPL",
    "gn:name":"Chok\u0101vi",
    "gn:population":0,
    "gn:timezone":"Asia/Kolkata",
    "iso:country":"IN",
    "ks:ks_name":"Chokavi",
    "ks:ks_pop":641,
    "ks:ks_type":"VILLAGE",
    "ks:ks_uagg_main":0,
    "name:eng_x_preferred":[
        "Chokavi"
    ],
    "wof:name":"Chokavi",
    "wof:placetype":"neighbourhood",
    "wof:population":641
},
  "geometry": {"coordinates":[76.242467,16.537159],"type":"Point"}
}