{
  "type": "Feature",
  "properties": {
    "iso:country":"IN",
    "ks:ks_alt_nam":"PALAKUNNU",
    "ks:ks_name":"Palakunnu",
    "ks:ks_pop":280,
    "ks:ks_type":"HABITATION",
    "name:eng_x_preferred":[
        "Palakunnu"
    ],
    "wof:name":"Palakunnu",
    "wof:placetype":"locality",
    "wof:population":280
},
  "geometry": {"coordinates":[76.10552800000001,10.722678],"type":"Point"}
}