{
  "type": "Feature",
  "properties": {
    "iso:country":"IN",
    "ks:ks_name":"Alagapuram",
    "ks:ks_pop":245,
    "ks:ks_type":"HABITATION",
    "name:eng_x_preferred":[
        "Alagapuram"
    ],
    "wof:name":"Alagapuram",
    "wof:placetype":"locality",
    "wof:population":245
},
  "geometry": {"coordinates":[79.75822100000001,11.305187],"type":"Point"}
}