{
  "type": "Feature",
  "properties": {
    "gn:admin1_code":"40",
    "gn:admin2_code":"541.0",
    "gn:asciiname":"Lingapalem",
    "gn:country_code":"IN",
    "gn:dem":156,
    "gn:feature_class":"P",
    "gn:feature_code":"PPL",
    "gn:name":"Lingap\u0101lem",
    "gn:population":0,
    "gn:timezone":"Asia/Kolkata",
    "iso:country":"IN",
    "name:new_x_preferred":[
        "\u0932\u093f\u0902\u0917\u092a\u093e\u0932\u0947\u0902 \u092e\u0923\u094d\u0921\u0932"
    ],
    "name:tam_x_preferred":[
        "\u0bb2\u0bbf\u0b99\u0bcd\u0b95\u0baa\u0bbe\u0bb2\u0bae\u0bcd"
    ],
    "name:tel_x_preferred":[
        "\u0c32\u0c3f\u0c02\u0c17\u0c2a\u0c3e\u0c32\u0c46\u0c02 \u0c2e\u0c02\u0c21\u0c32\u0c02"
    ],
    "name:urd_x_preferred":[
        "\u0644\u0646\u06af\u0627\u067e\u0627\u0644\u06cc\u0645"
    ],
    "wof:name":"Lingapalem",
    "wof:placetype":"locality"
},
  "geometry": {"coordinates":[80.80819,17.14107000000001],"type":"Point"}
}