{
  "type": "Feature",
  "properties": {
    "iso:country":"IN",
    "ks:ks_name":"Karakoda",
    "ks:ks_pop":239,
    "ks:ks_type":"HABITATION",
    "name:eng_x_preferred":[
        "Karakoda"
    ],
    "wof:name":"Karakoda",
    "wof:placetype":"locality",
    "wof:population":239
},
  "geometry": {"coordinates":[80.46597,19.812742],"type":"Point"}
}