{
  "type": "Feature",
  "properties": {
    "gn:admin1_code":"36",
    "gn:admin2_code":"192.0",
    "gn:asciiname":"Thakurmanpur",
    "gn:country_code":"IN",
    "gn:dem":78,
    "gn:feature_class":"P",
    "gn:feature_code":"PPL",
    "gn:name":"Thakurmanpur",
    "gn:population":0,
    "gn:timezone":"Asia/Kolkata",
    "iso:country":"IN",
    "ks:ks_name":"Thakurmanpur",
    "ks:ks_pop":627,
    "ks:ks_type":"VILLAGE",
    "ks:ks_uagg_main":0,
    "name:eng_x_preferred":[
        "Thakurmanpur"
    ],
    "wof:name":"Thakurmanpur",
    "wof:placetype":"locality",
    "wof:population":627
},
  "geometry": {"coordinates":[83.510276,25.947996],"type":"Point"}
}