{
  "type": "Feature",
  "properties": {
    "iso:country":"IN",
    "ks:ks_name":"Pakariya Purwa",
    "ks:ks_pop":725,
    "ks:ks_type":"HABITATION",
    "ks:ks_uagg_main":0,
    "name:eng_x_preferred":[
        "Pakariya Purwa"
    ],
    "wof:name":"Pakariya Purwa",
    "wof:placetype":"neighbourhood",
    "wof:population":725
},
  "geometry": {"coordinates":[80.82341,28.122668],"type":"Point"}
}