{
  "type": "Feature",
  "properties": {
    "iso:country":"IN",
    "ks:ks_name":"Bhupati Nagar",
    "ks:ks_pop":889,
    "ks:ks_type":"VILLAGE",
    "name:eng_x_preferred":[
        "Bhupati Nagar"
    ],
    "wof:name":"Bhupati Nagar",
    "wof:placetype":"locality",
    "wof:population":889
},
  "geometry": {"coordinates":[88.08739300000001,22.126409],"type":"Point"}
}