{
  "type": "Feature",
  "properties": {
    "gn:admin1_code":"2.0",
    "gn:admin2_code":"554.0",
    "gn:asciiname":"Ayyavaripalaiyam",
    "gn:country_code":"IN",
    "gn:dem":19,
    "gn:feature_class":"P",
    "gn:feature_code":"PPL",
    "gn:name":"Ayyav\u0101rip\u0101laiyam",
    "gn:population":0,
    "gn:timezone":"Asia/Kolkata",
    "iso:country":"IN",
    "ks:ks_name":"Ayyavaripalem",
    "ks:ks_pop":593,
    "ks:ks_type":"VILLAGE",
    "name:eng_x_preferred":[
        "Ayyavaripalem"
    ],
    "name:eng_x_variant":[
        "Ayyavaripalaiyam"
    ],
    "wof:name":"Ayyavaripalem",
    "wof:placetype":"locality",
    "wof:population":593
},
  "geometry": {"coordinates":[79.909318,13.677716],"type":"Point"}
}