{
  "type": "Feature",
  "properties": {
    "iso:country":"IN",
    "ks:ks_name":"Arazi Kasba",
    "ks:ks_pop":201,
    "ks:ks_type":"VILLAGE",
    "ks:ks_uagg_main":0,
    "name:eng_x_preferred":[
        "Arazi Kasba"
    ],
    "wof:name":"Arazi Kasba",
    "wof:placetype":"neighbourhood",
    "wof:population":201
},
  "geometry": {"coordinates":[88.37356699999999,25.527353],"type":"Point"}
}