{
  "type": "Feature",
  "properties": {
    "iso:country":"IN",
    "ks:ks_name":"Sivangulapalem",
    "ks:ks_pop":257,
    "ks:ks_type":"VILLAGE",
    "ks:ks_uagg_main":0,
    "name:eng_x_preferred":[
        "Sivangulapalem"
    ],
    "wof:name":"Sivangulapalem",
    "wof:placetype":"neighbourhood",
    "wof:population":257
},
  "geometry": {"coordinates":[80.745679,16.082793],"type":"Point"}
}