{
  "type": "Feature",
  "properties": {
    "iso:country":"IN",
    "ks:ks_name":"Donkinavalasa",
    "ks:ks_pop":232,
    "ks:ks_type":"VILLAGE",
    "name:eng_x_preferred":[
        "Donkinavalasa"
    ],
    "wof:name":"Donkinavalasa",
    "wof:placetype":"locality",
    "wof:population":232
},
  "geometry": {"coordinates":[82.784032,18.082119],"type":"Point"}
}