{
  "type": "Feature",
  "properties": {
    "gn:admin1_code":"36",
    "gn:admin2_code":"180.0",
    "gn:asciiname":"Indnapur",
    "gn:country_code":"IN",
    "gn:dem":117,
    "gn:feature_class":"P",
    "gn:feature_code":"PPL",
    "gn:name":"Indn\u0101pur",
    "gn:population":0,
    "gn:timezone":"Asia/Kolkata",
    "iso:country":"IN",
    "ks:ks_alt_nam":"Indana pur",
    "ks:ks_name":"Indana Pur",
    "ks:ks_pop":423,
    "ks:ks_type":"HABITATION",
    "ks:ks_uagg_main":0,
    "name:eng_x_preferred":[
        "Indana Pur"
    ],
    "wof:name":"Indana Pur",
    "wof:placetype":"neighbourhood",
    "wof:population":423
},
  "geometry": {"coordinates":[81.52572000000001,27.49137],"type":"Point"}
}