{
  "type": "Feature",
  "properties": {
    "iso:country":"IN",
    "ks:ks_name":"Gobrasol",
    "ks:ks_pop":0,
    "ks:ks_type":"VILLAGE",
    "name:eng_x_preferred":[
        "Gobrasol"
    ],
    "wof:name":"Gobrasol",
    "wof:placetype":"locality",
    "wof:population":0
},
  "geometry": {"coordinates":[87.297875,22.536053],"type":"Point"}
}