{
  "type": "Feature",
  "properties": {
    "gn:admin1_code":"35",
    "gn:admin2_code":"443.0",
    "gn:asciiname":"Rolpura",
    "gn:country_code":"IN",
    "gn:dem":463,
    "gn:feature_class":"P",
    "gn:feature_code":"PPL",
    "gn:name":"Rolpura",
    "gn:population":0,
    "gn:timezone":"Asia/Kolkata",
    "iso:country":"IN",
    "wof:name":"Rolpura",
    "wof:placetype":"locality"
},
  "geometry": {"coordinates":[77.70175999999999,24.11812],"type":"Point"}
}