{
  "type": "Feature",
  "properties": {
    "iso:country":"IN",
    "ks:ks_name":"Bonguguda",
    "ks:ks_pop":203,
    "ks:ks_type":"HABITATION",
    "name:eng_x_preferred":[
        "Bonguguda"
    ],
    "wof:name":"Bonguguda",
    "wof:placetype":"locality",
    "wof:population":203
},
  "geometry": {"coordinates":[82.422546,17.909544],"type":"Point"}
}