{
  "type": "Feature",
  "properties": {
    "gn:admin1_code":"12.0",
    "gn:admin2_code":"1.0",
    "gn:asciiname":"Sar Baihk",
    "gn:country_code":"IN",
    "gn:dem":1709,
    "gn:feature_class":"P",
    "gn:feature_code":"PPL",
    "gn:name":"Sar Baihk",
    "gn:population":0,
    "gn:timezone":"Asia/Kolkata",
    "iso:country":"IN",
    "wof:name":"Sar Baihk",
    "wof:placetype":"locality"
},
  "geometry": {"coordinates":[74.32674,34.54804],"type":"Point"}
}