{
  "type": "Feature",
  "properties": {
    "iso:country":"IN",
    "ks:ks_name":"Kaunsipal",
    "ks:ks_pop":17,
    "ks:ks_type":"HABITATION",
    "name:eng_x_preferred":[
        "Kaunsipal"
    ],
    "wof:name":"Kaunsipal",
    "wof:placetype":"locality",
    "wof:population":17
},
  "geometry": {"coordinates":[84.531125,21.474943],"type":"Point"}
}