{
  "type": "Feature",
  "properties": {
    "iso:country":"IN",
    "ks:ks_name":"Dakpur",
    "ks:ks_pop":337,
    "ks:ks_type":"VILLAGE",
    "ks:ks_uagg_main":0,
    "name:eng_x_preferred":[
        "Dakpur"
    ],
    "wof:name":"Dakpur",
    "wof:placetype":"neighbourhood",
    "wof:population":337
},
  "geometry": {"coordinates":[81.36279,25.94642],"type":"Point"}
}