{
  "type": "Feature",
  "properties": {
    "gn:admin1_code":"39",
    "gn:admin2_code":"61.0",
    "gn:asciiname":"Bindalgaon",
    "gn:country_code":"IN",
    "gn:dem":959,
    "gn:feature_class":"P",
    "gn:feature_code":"PPL",
    "gn:name":"Bindalgaon",
    "gn:population":0,
    "gn:timezone":"Asia/Kolkata",
    "iso:country":"IN",
    "ks:ks_name":"Bindalgaon",
    "ks:ks_type":"VILLAGE",
    "name:eng_x_preferred":[
        "Bindalgaon"
    ],
    "wof:name":"Bindalgaon",
    "wof:placetype":"locality"
},
  "geometry": {"coordinates":[78.490072,29.871471],"type":"Point"}
}