{
  "type": "Feature",
  "properties": {
    "iso:country":"IN",
    "ks:ks_name":"Bedia Chak",
    "ks:ks_pop":713,
    "ks:ks_type":"VILLAGE",
    "name:eng_x_preferred":[
        "Bedia Chak"
    ],
    "wof:name":"Bedia Chak",
    "wof:placetype":"locality",
    "wof:population":713
},
  "geometry": {"coordinates":[87.032734,24.173643],"type":"Point"}
}