{
  "type": "Feature",
  "properties": {
    "iso:country":"IN",
    "ks:ks_name":"Sakeri",
    "ks:ks_pop":68,
    "ks:ks_type":"VILLAGE",
    "name:eng_x_preferred":[
        "Sakeri"
    ],
    "wof:name":"Sakeri",
    "wof:placetype":"locality",
    "wof:population":68
},
  "geometry": {"coordinates":[73.608558,19.123435],"type":"Point"}
}