{
  "type": "Feature",
  "properties": {
    "iso:country":"IN",
    "ks:ks_name":"Ambatapas",
    "ks:ks_pop":0,
    "ks:ks_type":"VILLAGE",
    "name:eng_x_preferred":[
        "Ambatapas"
    ],
    "wof:name":"Ambatapas",
    "wof:placetype":"locality",
    "wof:population":0
},
  "geometry": {"coordinates":[82.807956,19.297608],"type":"Point"}
}