{
  "type": "Feature",
  "properties": {
    "iso:country":"IN",
    "ks:ks_alt_nam":"Kaliabor TE No.1",
    "ks:ks_name":"Kaliabor Te No.1",
    "ks:ks_pop":485,
    "ks:ks_type":"HABITATION",
    "name:eng_x_preferred":[
        "Kaliabor Te No.1"
    ],
    "wof:name":"Kaliabor Te No.1",
    "wof:placetype":"locality",
    "wof:population":485
},
  "geometry": {"coordinates":[92.961252,26.616839],"type":"Point"}
}