{
  "type": "Feature",
  "properties": {
    "gn:admin1_code":"16.0",
    "gn:asciiname":"Lodhi Tola",
    "gn:country_code":"IN",
    "gn:dem":279,
    "gn:feature_class":"P",
    "gn:feature_code":"PPL",
    "gn:name":"Lodh\u012b Tol\u0101",
    "gn:population":0,
    "gn:timezone":"Asia/Kolkata",
    "iso:country":"IN",
    "wof:name":"Lodhi Tola",
    "wof:placetype":"locality"
},
  "geometry": {"coordinates":[80.02497,21.55536],"type":"Point"}
}