{
  "type": "Feature",
  "properties": {
    "iso:country":"IN",
    "ks:ks_name":"Keekanam",
    "ks:ks_pop":1765,
    "ks:ks_type":"HABITATION",
    "name:eng_x_preferred":[
        "Keekanam"
    ],
    "wof:name":"Keekanam",
    "wof:placetype":"locality",
    "wof:population":1765
},
  "geometry": {"coordinates":[75.06026300000001,12.436251],"type":"Point"}
}