{
  "type": "Feature",
  "properties": {
    "gn:admin1_code":"35.0",
    "gn:admin2_code":"457.0",
    "gn:asciiname":"Dadkasa",
    "gn:country_code":"IN",
    "gn:dem":627,
    "gn:feature_class":"P",
    "gn:feature_code":"PPL",
    "gn:name":"Dadkas\u0101",
    "gn:population":0,
    "gn:timezone":"Asia/Kolkata",
    "iso:country":"IN",
    "ks:ks_name":"Dadkasa",
    "ks:ks_pop":1171,
    "ks:ks_type":"VILLAGE",
    "name:eng_x_preferred":[
        "Dadkasa"
    ],
    "wof:name":"Dadkasa",
    "wof:placetype":"locality",
    "wof:population":1171
},
  "geometry": {"coordinates":[80.597933,21.686433],"type":"Point"}
}