{
  "type": "Feature",
  "properties": {
    "iso:country":"IN",
    "ks:ks_name":"Kalasa Estate",
    "ks:ks_pop":110,
    "ks:ks_type":"HABITATION",
    "name:eng_x_preferred":[
        "Kalasa Estate"
    ],
    "wof:name":"Kalasa Estate",
    "wof:placetype":"locality",
    "wof:population":110
},
  "geometry": {"coordinates":[75.38035600000001,13.221798],"type":"Point"}
}