{
  "type": "Feature",
  "properties": {
    "iso:country":"IN",
    "ks:ks_name":"Tindni Madiyadoh",
    "ks:ks_pop":725,
    "ks:ks_type":"VILLAGE",
    "name:eng_x_preferred":[
        "Tindni Madiyadoh"
    ],
    "wof:name":"Tindni Madiyadoh",
    "wof:placetype":"locality",
    "wof:population":725
},
  "geometry": {"coordinates":[79.694585,24.304232],"type":"Point"}
}