{
  "type": "Feature",
  "properties": {
    "iso:country":"IN",
    "ks:ks_name":"Chhota Dhamni",
    "ks:ks_pop":1450,
    "ks:ks_type":"HABITATION",
    "name:eng_x_preferred":[
        "Chhota Dhamni"
    ],
    "wof:name":"Chhota Dhamni",
    "wof:placetype":"locality",
    "wof:population":1450
},
  "geometry": {"coordinates":[87.332166,24.846865],"type":"Point"}
}