{
  "type": "Feature",
  "properties": {
    "iso:country":"IN",
    "ks:ks_name":"Vilatpada",
    "ks:ks_pop":638,
    "ks:ks_type":"HABITATION",
    "name:eng_x_preferred":[
        "Vilatpada"
    ],
    "wof:name":"Vilatpada",
    "wof:placetype":"locality",
    "wof:population":638
},
  "geometry": {"coordinates":[72.71764400000001,20.071517],"type":"Point"}
}