{
  "type": "Feature",
  "properties": {
    "iso:country":"IN",
    "ks:ks_alt_nam":"harijan tola",
    "ks:ks_name":"Harijan Tola",
    "ks:ks_pop":120,
    "ks:ks_type":"HABITATION",
    "name:eng_x_preferred":[
        "Harijan Tola"
    ],
    "wof:name":"Harijan Tola",
    "wof:placetype":"locality",
    "wof:population":120
},
  "geometry": {"coordinates":[84.26160299999999,25.610747],"type":"Point"}
}