{
  "type": "Feature",
  "properties": {
    "iso:country":"IN",
    "ks:ks_name":"Kirabahal",
    "ks:ks_pop":127,
    "ks:ks_type":"VILLAGE",
    "name:eng_x_preferred":[
        "Kirabahal"
    ],
    "wof:name":"Kirabahal",
    "wof:placetype":"locality",
    "wof:population":127
},
  "geometry": {"coordinates":[82.90430000000001,20.270673],"type":"Point"}
}