{
  "type": "Feature",
  "properties": {
    "gn:admin1_code":"36.0",
    "gn:admin2_code":"179.0",
    "gn:asciiname":"Purwa Nepal",
    "gn:country_code":"IN",
    "gn:dem":107,
    "gn:feature_class":"P",
    "gn:feature_code":"PPL",
    "gn:name":"Purwa Nep\u0101l",
    "gn:population":0,
    "gn:timezone":"Asia/Kolkata",
    "iso:country":"IN",
    "wof:name":"Purwa Nepal",
    "wof:placetype":"locality"
},
  "geometry": {"coordinates":[81.95567,26.4673],"type":"Point"}
}