{
  "type": "Feature",
  "properties": {
    "iso:country":"IN",
    "ks:ks_name":"North Badalpur I",
    "ks:ks_pop":1847,
    "ks:ks_type":"HABITATION",
    "name:eng_x_preferred":[
        "North Badalpur I"
    ],
    "wof:name":"North Badalpur I",
    "wof:placetype":"locality",
    "wof:population":1847
},
  "geometry": {"coordinates":[87.618139,21.788353],"type":"Point"}
}