{
  "type": "Feature",
  "properties": {
    "iso:country":"IN",
    "ks:ks_name":"Ghiluguri",
    "ks:ks_pop":900,
    "ks:ks_type":"VILLAGE",
    "name:eng_x_preferred":[
        "Ghiluguri"
    ],
    "wof:name":"Ghiluguri",
    "wof:placetype":"locality",
    "wof:population":900
},
  "geometry": {"coordinates":[90.438143,26.453096],"type":"Point"}
}