{
  "type": "Feature",
  "properties": {
    "iso:country":"IN",
    "ks:ks_alt_nam":"Kanjirode kunnu",
    "ks:ks_name":"Kanjirode Kunnu",
    "ks:ks_pop":1889,
    "ks:ks_type":"HABITATION",
    "name:eng_x_preferred":[
        "Kanjirode Kunnu"
    ],
    "wof:name":"Kanjirode Kunnu",
    "wof:placetype":"locality",
    "wof:population":1889
},
  "geometry": {"coordinates":[77.04652299999999,8.900386],"type":"Point"}
}