{
  "type": "Feature",
  "properties": {
    "iso:country":"IN",
    "ks:ks_name":"Kurmiyan Tola",
    "ks:ks_pop":465,
    "ks:ks_type":"HABITATION",
    "ks:ks_uagg_main":0,
    "name:eng_x_preferred":[
        "Kurmiyan Tola"
    ],
    "wof:name":"Kurmiyan Tola",
    "wof:placetype":"neighbourhood",
    "wof:population":465
},
  "geometry": {"coordinates":[83.42168599999999,26.732122],"type":"Point"}
}