{
  "type": "Feature",
  "properties": {
    "gn:admin1_code":"37.0",
    "gn:admin2_code":"405.0",
    "gn:asciiname":"Lewai",
    "gn:country_code":"IN",
    "gn:dem":294,
    "gn:feature_class":"P",
    "gn:feature_code":"PPL",
    "gn:name":"Lewai",
    "gn:population":0,
    "gn:timezone":"Asia/Kolkata",
    "iso:country":"IN",
    "wof:name":"Lewai",
    "wof:placetype":"locality"
},
  "geometry": {"coordinates":[82.55915999999998,22.19064],"type":"Point"}
}