{
  "type": "Feature",
  "properties": {
    "iso:country":"IN",
    "ks:ks_name":"Charah Gaon",
    "ks:ks_pop":661,
    "ks:ks_type":"HABITATION",
    "name:eng_x_preferred":[
        "Charah Gaon"
    ],
    "wof:name":"Charah Gaon",
    "wof:placetype":"locality",
    "wof:population":661
},
  "geometry": {"coordinates":[95.569998,27.84503],"type":"Point"}
}