{
  "type": "Feature",
  "properties": {
    "iso:country":"IN",
    "ks:ks_name":"Bhom Bilniyasar",
    "ks:ks_pop":583,
    "ks:ks_type":"HABITATION",
    "name:eng_x_preferred":[
        "Bhom Bilniyasar"
    ],
    "wof:name":"Bhom Bilniyasar",
    "wof:placetype":"locality",
    "wof:population":583
},
  "geometry": {"coordinates":[73.88255599999999,27.606553],"type":"Point"}
}