{
  "type": "Feature",
  "properties": {
    "gn:admin1_code":"40.0",
    "gn:admin2_code":"534.0",
    "gn:asciiname":"Kannur",
    "gn:country_code":"IN",
    "gn:dem":239,
    "gn:feature_class":"P",
    "gn:feature_code":"PPL",
    "gn:name":"Kann\u016br",
    "gn:population":0,
    "gn:timezone":"Asia/Kolkata",
    "iso:country":"IN",
    "name:ben_x_preferred":[
        "\u0995\u09c1\u09a8\u09cd\u09a8\u09c1\u09b0"
    ],
    "name:bpy_x_preferred":[
        "\u0995\u09a8\u09cd\u09a8\u09c1\u09b0"
    ],
    "name:cat_x_preferred":[
        "Kannur"
    ],
    "name:deu_x_preferred":[
        "Kannur"
    ],
    "name:fas_x_preferred":[
        "\u06a9\u0627\u0646\u0648\u0631"
    ],
    "name:fra_x_preferred":[
        "Cannanore"
    ],
    "name:guj_x_preferred":[
        "\u0a95\u0aa3\u0acd\u0aa3\u0ac2\u0ab0"
    ],
    "name:hif_x_preferred":[
        "Kannur"
    ],
    "name:hin_x_preferred":[
        "\u0915\u0928\u094d\u0928\u0942\u0930"
    ],
    "name:hun_x_preferred":[
        "Kann\u00far"
    ],
    "name:ind_x_preferred":[
        "Kannur"
    ],
    "name:ita_x_preferred":[
        "Kannur"
    ],
    "name:jpn_x_preferred":[
        "\u30ab\u30f3\u30cc\u30fc\u30eb"
    ],
    "name:kan_x_preferred":[
        "\u0c95\u0ca3\u0ccd\u0ca3\u0cbe\u0ca8\u0cc2\u0cb0\u0cc1"
    ],
    "name:mai_x_preferred":[
        "\u0915\u0928\u094d\u0928\u0942\u0930"
    ],
    "name:mal_x_preferred":[
        "\u0d15\u0d23\u0d4d\u0d23\u0d42\u0d7c"
    ],
    "name:mar_x_preferred":[
        "\u0915\u0923\u094d\u0923\u0941\u0930"
    ],
    "name:mlg_x_preferred":[
        "Kannur"
    ],
    "name:msa_x_preferred":[
        "Kannur"
    ],
    "name:new_x_preferred":[
        "\u0915\u0923\u094d\u0923\u0942\u0930"
    ],
    "name:nor_x_preferred":[
        "Kannur"
    ],
    "name:ori_x_preferred":[
        "\u0b15\u0b3e\u0b28\u0b4d\u0b28\u0b30"
    ],
    "name:pam_x_preferred":[
        "Kannur"
    ],
    "name:pan_x_preferred":[
        "\u0a15\u0a28\u0a42\u0a30"
    ],
    "name:pol_x_preferred":[
        "Kannur"
    ],
    "name:por_x_preferred":[
        "Cananor"
    ],
    "name:rus_x_preferred":[
        "\u041a\u0430\u043d\u043d\u0443\u0440"
    ],
    "name:spa_x_preferred":[
        "Cananor"
    ],
    "name:swe_x_preferred":[
        "Kannur"
    ],
    "name:tam_x_preferred":[
        "\u0b95\u0ba3\u0bcd\u0ba3\u0bc2\u0bb0\u0bcd"
    ],
    "name:tcy_x_preferred":[
        "\u0c95\u0ca3\u0ccd\u0ca3\u0cc2\u0cb0\u0ccd"
    ],
    "name:urd_x_preferred":[
        "\u06a9\u0646\u0648\u0631"
    ],
    "name:vie_x_preferred":[
        "Kannur"
    ],
    "name:war_x_preferred":[
        "Kannur"
    ],
    "wof:name":"Kannur",
    "wof:placetype":"locality"
},
  "geometry": {"coordinates":[79.50668,18.20617],"type":"Point"}
}