{
  "type": "Feature",
  "properties": {
    "gn:admin1_code":"23.0",
    "gn:admin2_code":"48.0",
    "gn:asciiname":"Ladhaheri",
    "gn:country_code":"IN",
    "gn:dem":249,
    "gn:feature_class":"P",
    "gn:feature_code":"PPL",
    "gn:name":"Ladh\u0101heri",
    "gn:population":0,
    "gn:timezone":"Asia/Kolkata",
    "iso:country":"IN",
    "wof:name":"Ladhaheri",
    "wof:placetype":"locality"
},
  "geometry": {"coordinates":[76.07403000000002,30.39817],"type":"Point"}
}