{
  "type": "Feature",
  "properties": {
    "iso:country":"IN",
    "ks:ks_name":"Savri F",
    "ks:ks_pop":329,
    "ks:ks_type":"HABITATION",
    "name:eng_x_preferred":[
        "Savri F"
    ],
    "wof:name":"Savri F",
    "wof:placetype":"locality",
    "wof:population":329
},
  "geometry": {"coordinates":[73.28361099999999,20.655667],"type":"Point"}
}