{
  "type": "Feature",
  "properties": {
    "iso:country":"IN",
    "ks:ks_name":"Tagaria Gopalpur",
    "ks:ks_pop":397,
    "ks:ks_type":"VILLAGE",
    "name:eng_x_preferred":[
        "Tagaria Gopalpur"
    ],
    "wof:name":"Tagaria Gopalpur",
    "wof:placetype":"locality",
    "wof:population":397
},
  "geometry": {"coordinates":[87.706462,21.773535],"type":"Point"}
}