{
  "type": "Feature",
  "properties": {
    "iso:country":"IN",
    "ks:ks_name":"Jhutamara",
    "ks:ks_pop":102,
    "ks:ks_type":"HABITATION",
    "name:eng_x_preferred":[
        "Jhutamara"
    ],
    "wof:name":"Jhutamara",
    "wof:placetype":"locality",
    "wof:population":102
},
  "geometry": {"coordinates":[84.896226,20.390345],"type":"Point"}
}