{
  "type": "Feature",
  "properties": {
    "gn:admin1_code":"35.0",
    "gn:admin2_code":"463.0",
    "gn:asciiname":"Sidhari",
    "gn:country_code":"IN",
    "gn:dem":330,
    "gn:feature_class":"P",
    "gn:feature_code":"PPL",
    "gn:name":"Sidhari",
    "gn:population":0,
    "gn:timezone":"Asia/Kolkata",
    "iso:country":"IN",
    "ks:ks_name":"Sidhari",
    "ks:ks_pop":581,
    "ks:ks_type":"VILLAGE",
    "name:eng_x_preferred":[
        "Sidhari"
    ],
    "wof:name":"Sidhari",
    "wof:placetype":"locality",
    "wof:population":581
},
  "geometry": {"coordinates":[82.74138499999999,24.324265],"type":"Point"}
}