{
  "type": "Feature",
  "properties": {
    "iso:country":"IN",
    "ks:ks_name":"Dakshin Tola",
    "ks:ks_pop":400,
    "ks:ks_type":"HABITATION",
    "name:eng_x_preferred":[
        "Dakshin Tola"
    ],
    "wof:name":"Dakshin Tola",
    "wof:placetype":"locality",
    "wof:population":400
},
  "geometry": {"coordinates":[83.754682,26.926284],"type":"Point"}
}