{
  "type": "Feature",
  "properties": {
    "gn:admin1_code":"35",
    "gn:admin2_code":"425.0",
    "gn:asciiname":"Bajrangpur",
    "gn:country_code":"IN",
    "gn:dem":162,
    "gn:feature_class":"P",
    "gn:feature_code":"PPL",
    "gn:name":"Bajrangpur",
    "gn:population":0,
    "gn:timezone":"Asia/Kolkata",
    "iso:country":"IN",
    "name:eng_x_preferred":[
        "Bajrangpur"
    ],
    "wof:name":"Bajrangpur",
    "wof:placetype":"locality"
},
  "geometry": {"coordinates":[80.08315999999998,25.25694],"type":"Point"}
}