{
  "type": "Feature",
  "properties": {
    "iso:country":"IN",
    "ks:ks_name":"Karnetpura",
    "ks:ks_pop":574,
    "ks:ks_type":"VILLAGE",
    "name:eng_x_preferred":[
        "Karnetpura"
    ],
    "wof:name":"Karnetpura",
    "wof:placetype":"locality",
    "wof:population":574
},
  "geometry": {"coordinates":[73.522058,27.434333],"type":"Point"}
}