{
  "type": "Feature",
  "properties": {
    "iso:country":"IN",
    "ks:ks_name":"Singhodi",
    "ks:ks_pop":218,
    "ks:ks_type":"HABITATION",
    "name:eng_x_preferred":[
        "Singhodi"
    ],
    "wof:name":"Singhodi",
    "wof:placetype":"locality",
    "wof:population":218
},
  "geometry": {"coordinates":[80.50490000000001,22.104455],"type":"Point"}
}