{
  "type": "Feature",
  "properties": {
    "gn:admin1_code":"36",
    "gn:admin2_code":"137.0",
    "gn:asciiname":"Bazidpur",
    "gn:country_code":"IN",
    "gn:dem":211,
    "gn:feature_class":"P",
    "gn:feature_code":"PPL",
    "gn:name":"B\u0101zidpur",
    "gn:population":0,
    "gn:timezone":"Asia/Kolkata",
    "iso:country":"IN",
    "name:fas_x_preferred":[
        "\u0628\u0627\u0632\u06cc\u062f\u067e\u0648\u0631"
    ],
    "name:urd_x_preferred":[
        "\u0628\u0627\u0632\u06cc\u062f \u067e\u0648\u0631"
    ],
    "wof:name":"Bazidpur",
    "wof:placetype":"locality"
},
  "geometry": {"coordinates":[78.16391999999998,28.93497],"type":"Point"}
}