{
  "type": "Feature",
  "properties": {
    "gn:admin1_code":"23.0",
    "gn:admin2_code":"48.0",
    "gn:asciiname":"Phalauli",
    "gn:country_code":"IN",
    "gn:dem":257,
    "gn:feature_class":"P",
    "gn:feature_code":"PPL",
    "gn:name":"Phalauli",
    "gn:population":0,
    "gn:timezone":"Asia/Kolkata",
    "iso:country":"IN",
    "ks:ks_name":"Phalauli",
    "ks:ks_pop":184,
    "ks:ks_type":"VILLAGE",
    "ks:ks_uagg_main":0,
    "name:eng_x_preferred":[
        "Phalauli"
    ],
    "wof:name":"Phalauli",
    "wof:placetype":"locality",
    "wof:population":184
},
  "geometry": {"coordinates":[76.440759,30.362154],"type":"Point"}
}