{
  "type": "Feature",
  "properties": {
    "gn:admin1_code":"36",
    "gn:admin2_code":"155.0",
    "gn:asciiname":"Daulatiapur",
    "gn:country_code":"IN",
    "gn:dem":145,
    "gn:feature_class":"P",
    "gn:feature_code":"PPL",
    "gn:name":"Daulati\u0101pur",
    "gn:population":0,
    "gn:timezone":"Asia/Kolkata",
    "iso:country":"IN",
    "ks:ks_alt_nam":"Daulati\u0101pur",
    "ks:ks_name":"Daulatiapur",
    "ks:ks_pop":1037,
    "ks:ks_type":"VILLAGE",
    "ks:ks_uagg_main":0,
    "name:eng_x_preferred":[
        "Daulatiapur"
    ],
    "name:eng_x_variant":[
        "Daulati\u0101pur"
    ],
    "wof:name":"Daulatiapur",
    "wof:placetype":"neighbourhood",
    "wof:population":1037
},
  "geometry": {"coordinates":[79.930772,27.597226],"type":"Point"}
}