{
  "type": "Feature",
  "properties": {
    "gn:admin1_code":"21.0",
    "gn:admin2_code":"398.0",
    "gn:asciiname":"Singiriguda",
    "gn:country_code":"IN",
    "gn:dem":918,
    "gn:feature_class":"P",
    "gn:feature_code":"PPL",
    "gn:name":"Singiriguda",
    "gn:population":0,
    "gn:timezone":"Asia/Kolkata",
    "iso:country":"IN",
    "wof:name":"Singiriguda",
    "wof:placetype":"locality"
},
  "geometry": {"coordinates":[82.93556,18.56996],"type":"Point"}
}