{
  "type": "Feature",
  "properties": {
    "iso:country":"IN",
    "ks:ks_alt_nam":"AUTADEWASTI",
    "ks:ks_name":"Autadewasti",
    "ks:ks_pop":151,
    "ks:ks_type":"HABITATION",
    "name:eng_x_preferred":[
        "Autadewasti"
    ],
    "wof:name":"Autadewasti",
    "wof:placetype":"locality",
    "wof:population":151
},
  "geometry": {"coordinates":[74.940038,17.548605],"type":"Point"}
}