{
  "type": "Feature",
  "properties": {
    "iso:country":"IN",
    "ks:ks_name":"Chyaprashi",
    "ks:ks_pop":1585,
    "ks:ks_type":"HABITATION",
    "ks:ks_uagg_main":0,
    "name:eng_x_preferred":[
        "Chyaprashi"
    ],
    "wof:name":"Chyaprashi",
    "wof:placetype":"neighbourhood",
    "wof:population":1585
},
  "geometry": {"coordinates":[88.73544800000001,22.439747],"type":"Point"}
}