{
  "type": "Feature",
  "properties": {
    "gn:admin1_code":"10.0",
    "gn:admin2_code":"072",
    "gn:asciiname":"Katlaheri",
    "gn:country_code":"IN",
    "gn:dem":261,
    "gn:feature_class":"P",
    "gn:feature_code":"PPL",
    "gn:name":"Katl\u0101heri",
    "gn:population":0,
    "gn:timezone":"Asia/Kolkata",
    "iso:country":"IN",
    "name:und_x_variant":[
        "Katl\u0101heri"
    ],
    "wof:name":"Katlaheri",
    "wof:placetype":"locality"
},
  "geometry": {"coordinates":[76.83376,30.1001],"type":"Point"}
}