{
  "type": "Feature",
  "properties": {
    "gn:admin1_code":"37.0",
    "gn:admin2_code":"414.0",
    "gn:asciiname":"Dilmili",
    "gn:country_code":"IN",
    "gn:dem":714,
    "gn:feature_class":"P",
    "gn:feature_code":"PPL",
    "gn:name":"Dilmili",
    "gn:population":0,
    "gn:timezone":"Asia/Kolkata",
    "iso:country":"IN",
    "wof:name":"Dilmili",
    "wof:placetype":"locality"
},
  "geometry": {"coordinates":[81.73912,18.97102000000001],"type":"Point"}
}