{
  "type": "Feature",
  "properties": {
    "gn:admin1_code":"39.0",
    "gn:admin2_code":"060",
    "gn:asciiname":"Sabhawala",
    "gn:country_code":"IN",
    "gn:dem":503,
    "gn:feature_class":"P",
    "gn:feature_code":"PPL",
    "gn:name":"S\u0101bh\u0101w\u0101la",
    "gn:population":0,
    "gn:timezone":"Asia/Kolkata",
    "iso:country":"IN",
    "ks:ks_alt_nam":"S\u0101bh\u0101w\u0101la",
    "ks:ks_name":"Sabhawala",
    "ks:ks_pop":3741,
    "ks:ks_type":"VILLAGE",
    "ks:ks_uagg_main":0,
    "name:eng_x_preferred":[
        "Sabhawala"
    ],
    "name:eng_x_variant":[
        "S\u0101bh\u0101w\u0101la"
    ],
    "name:und_x_variant":[
        "S\u0101bh\u0101w\u0101la",
        "S\u0101hh\u0101w\u0101la"
    ],
    "wof:name":"Sabhawala",
    "wof:placetype":"neighbourhood",
    "wof:population":3741
},
  "geometry": {"coordinates":[77.791788,30.36949],"type":"Point"}
}