{
  "type": "Feature",
  "properties": {
    "iso:country":"IN",
    "ks:ks_alt_nam":"chhapradand",
    "ks:ks_name":"Chhapradand",
    "ks:ks_pop":255,
    "ks:ks_type":"HABITATION",
    "name:eng_x_preferred":[
        "Chhapradand"
    ],
    "wof:name":"Chhapradand",
    "wof:placetype":"locality",
    "wof:population":255
},
  "geometry": {"coordinates":[83.187332,22.750678],"type":"Point"}
}