{
  "type": "Feature",
  "properties": {
    "iso:country":"IN",
    "ks:ks_name":"Dandtoli",
    "ks:ks_pop":337,
    "ks:ks_type":"HABITATION",
    "name:eng_x_preferred":[
        "Dandtoli"
    ],
    "wof:name":"Dandtoli",
    "wof:placetype":"locality",
    "wof:population":337
},
  "geometry": {"coordinates":[84.86389800000001,22.807975],"type":"Point"}
}