{
  "type": "Feature",
  "properties": {
    "iso:country":"IN",
    "ks:ks_name":"Mahamayapur",
    "ks:ks_pop":951,
    "ks:ks_type":"VILLAGE",
    "ks:ks_uagg_main":0,
    "name:eng_x_preferred":[
        "Mahamayapur"
    ],
    "wof:name":"Mahamayapur",
    "wof:placetype":"locality",
    "wof:population":951
},
  "geometry": {"coordinates":[88.200087,22.371516],"type":"Point"}
}