{
  "type": "Feature",
  "properties": {
    "iso:country":"IN",
    "ks:ks_name":"Lakpur",
    "ks:ks_pop":185,
    "ks:ks_type":"HABITATION",
    "ks:ks_uagg_main":0,
    "name:eng_x_preferred":[
        "Lakpur"
    ],
    "wof:name":"Lakpur",
    "wof:placetype":"neighbourhood",
    "wof:population":185
},
  "geometry": {"coordinates":[80.470157,27.710734],"type":"Point"}
}