{
  "type": "Feature",
  "properties": {
    "gn:admin1_code":"9.0",
    "gn:admin2_code":"484.0",
    "gn:asciiname":"Raghao Mota",
    "gn:country_code":"IN",
    "gn:dem":103,
    "gn:feature_class":"P",
    "gn:feature_code":"PPL",
    "gn:name":"R\u0101ghao Mota",
    "gn:population":0,
    "gn:timezone":"Asia/Kolkata",
    "iso:country":"IN",
    "wof:name":"Raghao Mota",
    "wof:placetype":"neighbourhood"
},
  "geometry": {"coordinates":[73.53780999999999,23.02695],"type":"Point"}
}