{
  "type": "Feature",
  "properties": {
    "gn:admin1_code":"39.0",
    "gn:admin2_code":"59.0",
    "gn:asciiname":"Pratap Nagar",
    "gn:country_code":"IN",
    "gn:dem":1955,
    "gn:feature_class":"P",
    "gn:feature_code":"PPL",
    "gn:name":"Pratap Nagar",
    "gn:population":0,
    "gn:timezone":"Asia/Kolkata",
    "iso:country":"IN",
    "wof:name":"Pratap Nagar",
    "wof:placetype":"locality"
},
  "geometry": {"coordinates":[78.47804000000002,30.44973],"type":"Point"}
}