{
  "type": "Feature",
  "properties": {
    "gn:admin1_code":"13.0",
    "gn:admin2_code":"600.0",
    "gn:asciiname":"Kalluvathukkal",
    "gn:country_code":"IN",
    "gn:dem":50,
    "gn:feature_class":"P",
    "gn:feature_code":"PPL",
    "gn:name":"Kalluvathukkal",
    "gn:population":0,
    "gn:timezone":"Asia/Kolkata",
    "iso:country":"IN",
    "name:mal_x_preferred":[
        "\u0d15\u0d32\u0d4d\u0d32\u0d41\u0d35\u0d3e\u0d24\u0d41\u0d15\u0d4d\u0d15\u0d7d"
    ],
    "wof:name":"Kalluvathukkal",
    "wof:placetype":"locality"
},
  "geometry": {"coordinates":[76.74899000000001,8.82795],"type":"Point"}
}