{
  "type": "Feature",
  "properties": {
    "gn:admin1_code":"35.0",
    "gn:admin2_code":"434.0",
    "gn:asciiname":"Khari",
    "gn:country_code":"IN",
    "gn:dem":391,
    "gn:feature_class":"P",
    "gn:feature_code":"PPL",
    "gn:name":"Kh\u0101ri",
    "gn:population":0,
    "gn:timezone":"Asia/Kolkata",
    "iso:country":"IN",
    "ks:ks_alt_nam":"Kh\u0101ri",
    "ks:ks_name":"Khari",
    "ks:ks_pop":1192,
    "ks:ks_type":"VILLAGE",
    "name:ceb_x_preferred":[
        "Khari"
    ],
    "name:deu_x_preferred":[
        "Khari"
    ],
    "name:eng_x_preferred":[
        "Khari"
    ],
    "name:eng_x_variant":[
        "Kh\u0101ri"
    ],
    "name:msa_x_preferred":[
        "Khari"
    ],
    "name:new_x_preferred":[
        "\u0916\u0930\u0940"
    ],
    "name:pol_x_preferred":[
        "Khari"
    ],
    "wof:name":"Khari",
    "wof:placetype":"locality",
    "wof:population":1192
},
  "geometry": {"coordinates":[75.00376199999999,23.112446],"type":"Point"}
}