{
  "type": "Feature",
  "properties": {
    "iso:country":"IN",
    "ks:ks_name":"Kusamha",
    "ks:ks_pop":420,
    "ks:ks_type":"VILLAGE",
    "name:eng_x_preferred":[
        "Kusamha"
    ],
    "wof:name":"Kusamha",
    "wof:placetype":"locality",
    "wof:population":420
},
  "geometry": {"coordinates":[86.757092,24.566399],"type":"Point"}
}