{
  "type": "Feature",
  "properties": {
    "gn:admin1_code":"34.0",
    "gn:admin2_code":"219.0",
    "gn:asciiname":"Methwalia",
    "gn:country_code":"IN",
    "gn:dem":58,
    "gn:feature_class":"P",
    "gn:feature_code":"PPL",
    "gn:name":"Methwalia",
    "gn:population":0,
    "gn:timezone":"Asia/Kolkata",
    "iso:country":"IN",
    "ks:ks_name":"Methwalia",
    "ks:ks_pop":1980,
    "ks:ks_type":"VILLAGE",
    "ks:ks_uagg_main":0,
    "name:eng_x_preferred":[
        "Methwalia"
    ],
    "wof:name":"Methwalia",
    "wof:placetype":"locality",
    "wof:population":1980
},
  "geometry": {"coordinates":[84.749235,25.809753],"type":"Point"}
}