{
  "type": "Feature",
  "properties": {
    "iso:country":"IN",
    "ks:ks_name":"Nikkunnadi",
    "ks:ks_pop":840,
    "ks:ks_type":"HABITATION",
    "name:eng_x_preferred":[
        "Nikkunnadi"
    ],
    "wof:name":"Nikkunnadi",
    "wof:placetype":"locality",
    "wof:population":840
},
  "geometry": {"coordinates":[76.03219900000001,11.703872],"type":"Point"}
}