{
  "type": "Feature",
  "properties": {
    "gn:admin1_code":"25.0",
    "gn:admin2_code":"619.0",
    "gn:asciiname":"Navalur",
    "gn:country_code":"IN",
    "gn:dem":22,
    "gn:feature_class":"P",
    "gn:feature_code":"PPL",
    "gn:name":"N\u0101val\u016br",
    "gn:population":0,
    "gn:timezone":"Asia/Kolkata",
    "iso:country":"IN",
    "name:tam_x_preferred":[
        "\u0ba8\u0bbe\u0bb5\u0bb2\u0bc2\u0bb0\u0bcd"
    ],
    "wof:name":"Navalur",
    "wof:placetype":"locality"
},
  "geometry": {"coordinates":[79.4669,10.83],"type":"Point"}
}