{
  "type": "Feature",
  "properties": {
    "iso:country":"IN",
    "ks:ks_name":"Garudwadi",
    "ks:ks_pop":86,
    "ks:ks_type":"HABITATION",
    "name:eng_x_preferred":[
        "Garudwadi"
    ],
    "wof:name":"Garudwadi",
    "wof:placetype":"locality",
    "wof:population":86
},
  "geometry": {"coordinates":[73.595117,16.636725],"type":"Point"}
}