{
  "type": "Feature",
  "properties": {
    "iso:country":"IN",
    "ks:ks_name":"Onimakki",
    "ks:ks_pop":30,
    "ks:ks_type":"HABITATION",
    "name:eng_x_preferred":[
        "Onimakki"
    ],
    "wof:name":"Onimakki",
    "wof:placetype":"locality",
    "wof:population":30
},
  "geometry": {"coordinates":[74.684111,14.4226],"type":"Point"}
}