{
  "type": "Feature",
  "properties": {
    "gn:admin1_code":"35",
    "gn:admin2_code":"426.0",
    "gn:asciiname":"Paltara",
    "gn:country_code":"IN",
    "gn:dem":379,
    "gn:feature_class":"P",
    "gn:feature_code":"PPL",
    "gn:name":"Palt\u0101ra",
    "gn:population":0,
    "gn:timezone":"Asia/Kolkata",
    "iso:country":"IN",
    "ks:ks_name":"Palthara",
    "ks:ks_pop":120,
    "ks:ks_type":"VILLAGE",
    "name:eng_x_preferred":[
        "Palthara"
    ],
    "name:eng_x_variant":[
        "Paltara"
    ],
    "wof:name":"Palthara",
    "wof:placetype":"locality",
    "wof:population":120
},
  "geometry": {"coordinates":[80.320921,24.821006],"type":"Point"}
}