{
  "type": "Feature",
  "properties": {
    "iso:country":"IN",
    "ks:ks_name":"Takasingha",
    "ks:ks_pop":123,
    "ks:ks_type":"VILLAGE",
    "name:eng_x_preferred":[
        "Takasingha"
    ],
    "wof:name":"Takasingha",
    "wof:placetype":"locality",
    "wof:population":123
},
  "geometry": {"coordinates":[83.824039,20.340149],"type":"Point"}
}