{
  "type": "Feature",
  "properties": {
    "iso:country":"IN",
    "ks:ks_alt_nam":"PURE BINDA",
    "ks:ks_name":"Pure Binda",
    "ks:ks_pop":148,
    "ks:ks_type":"HABITATION",
    "name:eng_x_preferred":[
        "Pure Binda"
    ],
    "wof:name":"Pure Binda",
    "wof:placetype":"locality",
    "wof:population":148
},
  "geometry": {"coordinates":[81.43640000000001,26.485],"type":"Point"}
}