{
  "type": "Feature",
  "properties": {
    "iso:country":"IN",
    "ks:ks_name":"Fardas Para",
    "ks:ks_pop":49,
    "ks:ks_type":"HABITATION",
    "name:eng_x_preferred":[
        "Fardas Para"
    ],
    "wof:name":"Fardas Para",
    "wof:placetype":"locality",
    "wof:population":49
},
  "geometry": {"coordinates":[91.964147,23.946469],"type":"Point"}
}