{
  "type": "Feature",
  "properties": {
    "gn:admin1_code":"23",
    "gn:admin2_code":"35.0",
    "gn:asciiname":"Kishanpur",
    "gn:country_code":"IN",
    "gn:dem":243,
    "gn:feature_class":"P",
    "gn:feature_code":"PPL",
    "gn:name":"Kishanpur",
    "gn:population":0,
    "gn:timezone":"Asia/Kolkata",
    "iso:country":"IN",
    "wof:name":"Kishanpur",
    "wof:placetype":"locality"
},
  "geometry": {"coordinates":[75.52334999999999,31.92675],"type":"Point"}
}