{
  "type": "Feature",
  "properties": {
    "gn:admin1_code":"19.0",
    "gn:admin2_code":"568.0",
    "gn:asciiname":"Hasarmane",
    "gn:country_code":"IN",
    "gn:dem":640,
    "gn:feature_class":"P",
    "gn:feature_code":"PPL",
    "gn:name":"Hasarman\u0113",
    "gn:population":0,
    "gn:timezone":"Asia/Kolkata",
    "iso:country":"IN",
    "ks:ks_alt_nam":"HASIRUMANE",
    "ks:ks_name":"Hasirumane",
    "ks:ks_pop":99,
    "ks:ks_type":"HABITATION",
    "name:eng_x_preferred":[
        "Hasirumane"
    ],
    "name:eng_x_variant":[
        "Hasarmane"
    ],
    "wof:name":"Hasirumane",
    "wof:placetype":"locality",
    "wof:population":99
},
  "geometry": {"coordinates":[75.117197,13.577969],"type":"Point"}
}