{
  "type": "Feature",
  "properties": {
    "gn:admin1_code":"35.0",
    "gn:admin2_code":"424",
    "gn:asciiname":"Paniyarakhera",
    "gn:country_code":"IN",
    "gn:dem":321,
    "gn:feature_class":"P",
    "gn:feature_code":"PPL",
    "gn:name":"Paniy\u0101r\u0101khera",
    "gn:population":0,
    "gn:timezone":"Asia/Kolkata",
    "iso:country":"IN",
    "ks:ks_alt_nam":"Paniy\u0101r\u0101khera",
    "ks:ks_name":"Paniyarakhera",
    "ks:ks_type":"VILLAGE",
    "name:eng_x_preferred":[
        "Paniyarakhera"
    ],
    "name:eng_x_variant":[
        "Paniy\u0101r\u0101khera"
    ],
    "wof:name":"Paniyarakhera",
    "wof:placetype":"locality"
},
  "geometry": {"coordinates":[78.907059,24.881589],"type":"Point"}
}