{
  "type": "Feature",
  "properties": {
    "iso:country":"IN",
    "ks:ks_alt_nam":"Anid\u012bh",
    "ks:ks_name":"Anidih",
    "ks:ks_type":"VILLAGE",
    "name:eng_x_preferred":[
        "Anidih"
    ],
    "name:eng_x_variant":[
        "Anid\u012bh"
    ],
    "wof:name":"Anidih",
    "wof:placetype":"locality"
},
  "geometry": {"coordinates":[85.335409,23.182084],"type":"Point"}
}