{
  "type": "Feature",
  "properties": {
    "iso:country":"IN",
    "ks:ks_name":"Kochila Gadia",
    "ks:ks_pop":26,
    "ks:ks_type":"VILLAGE",
    "name:eng_x_preferred":[
        "Kochila Gadia"
    ],
    "wof:name":"Kochila Gadia",
    "wof:placetype":"locality",
    "wof:population":26
},
  "geometry": {"coordinates":[86.05295700000001,20.727602],"type":"Point"}
}