{
  "type": "Feature",
  "properties": {
    "gn:admin1_code":"25.0",
    "gn:admin2_code":"627.0",
    "gn:asciiname":"Alankinaru",
    "gn:country_code":"IN",
    "gn:dem":40,
    "gn:feature_class":"P",
    "gn:feature_code":"PPL",
    "gn:name":"\u0100lankinaru",
    "gn:population":0,
    "gn:timezone":"Asia/Kolkata",
    "iso:country":"IN",
    "wof:name":"Alankinaru",
    "wof:placetype":"locality"
},
  "geometry": {"coordinates":[77.86028,8.41105],"type":"Point"}
}