{
  "type": "Feature",
  "properties": {
    "iso:country":"IN",
    "ks:ks_name":"Kottarkavu",
    "ks:ks_pop":1200,
    "ks:ks_type":"HABITATION",
    "name:eng_x_preferred":[
        "Kottarkavu"
    ],
    "wof:name":"Kottarkavu",
    "wof:placetype":"locality",
    "wof:population":1200
},
  "geometry": {"coordinates":[76.534448,9.306141],"type":"Point"}
}