{
  "type": "Feature",
  "properties": {
    "iso:country":"IN",
    "ks:ks_name":"Gobardhanpur",
    "ks:ks_pop":496,
    "ks:ks_type":"VILLAGE",
    "name:eng_x_preferred":[
        "Gobardhanpur"
    ],
    "wof:name":"Gobardhanpur",
    "wof:placetype":"locality",
    "wof:population":496
},
  "geometry": {"coordinates":[85.136539,20.692642],"type":"Point"}
}