{
  "type": "Feature",
  "properties": {
    "gn:admin1_code":"2.0",
    "gn:admin2_code":"554.0",
    "gn:asciiname":"Maddulapalli",
    "gn:country_code":"IN",
    "gn:dem":342,
    "gn:feature_class":"P",
    "gn:feature_code":"PPL",
    "gn:name":"Maddulapalli",
    "gn:population":0,
    "gn:timezone":"Asia/Kolkata",
    "iso:country":"IN",
    "wof:name":"Maddulapalli",
    "wof:placetype":"locality"
},
  "geometry": {"coordinates":[79.06201999999998,13.35491],"type":"Point"}
}