{
  "type": "Feature",
  "properties": {
    "gn:admin1_code":"36",
    "gn:admin2_code":"173.0",
    "gn:asciiname":"Bigha",
    "gn:country_code":"IN",
    "gn:dem":96,
    "gn:feature_class":"P",
    "gn:feature_code":"PPL",
    "gn:name":"B\u012bgha",
    "gn:population":0,
    "gn:timezone":"Asia/Kolkata",
    "iso:country":"IN",
    "name:asm_x_preferred":[
        "\u09ac\u09bf\u0998\u09be"
    ],
    "name:ben_x_preferred":[
        "\u09ac\u09bf\u0998\u09be"
    ],
    "name:ces_x_preferred":[
        "Biggah"
    ],
    "name:deu_x_preferred":[
        "Bigha"
    ],
    "name:guj_x_preferred":[
        "\u0ab5\u0abf\u0a98\u0abe"
    ],
    "name:hin_x_preferred":[
        "\u092c\u0940\u0918\u093e"
    ],
    "name:pan_x_preferred":[
        "\u0a35\u0a3f\u0a71\u0a18\u0a3e"
    ],
    "wof:name":"Bigha",
    "wof:placetype":"locality"
},
  "geometry": {"coordinates":[82.12935999999998,25.93768],"type":"Point"}
}