{
  "type": "Feature",
  "properties": {
    "iso:country":"IN",
    "ks:ks_name":"Puthilakaje",
    "ks:ks_pop":103,
    "ks:ks_type":"HABITATION",
    "name:eng_x_preferred":[
        "Puthilakaje"
    ],
    "wof:name":"Puthilakaje",
    "wof:placetype":"locality",
    "wof:population":103
},
  "geometry": {"coordinates":[75.14560299999999,13.037697],"type":"Point"}
}