{
  "type": "Feature",
  "properties": {
    "iso:country":"IN",
    "ks:ks_name":"Ponnalikottai",
    "ks:ks_pop":392,
    "ks:ks_type":"VILLAGE",
    "name:eng_x_preferred":[
        "Ponnalikottai"
    ],
    "wof:name":"Ponnalikottai",
    "wof:placetype":"locality",
    "wof:population":392
},
  "geometry": {"coordinates":[78.752683,9.837673],"type":"Point"}
}