{
  "type": "Feature",
  "properties": {
    "gn:admin1_code":"13.0",
    "gn:admin2_code":"592.0",
    "gn:asciiname":"Pottanur",
    "gn:country_code":"IN",
    "gn:dem":15,
    "gn:feature_class":"P",
    "gn:feature_code":"PPL",
    "gn:name":"P\u014dttan\u016br",
    "gn:population":0,
    "gn:timezone":"Asia/Kolkata",
    "iso:country":"IN",
    "ks:ks_name":"Pothannur",
    "ks:ks_pop":173,
    "ks:ks_type":"HABITATION",
    "ks:ks_uagg_main":0,
    "name:eng_x_preferred":[
        "Pothannur"
    ],
    "wof:name":"Pothannur",
    "wof:placetype":"neighbourhood",
    "wof:population":173
},
  "geometry": {"coordinates":[75.980171,10.805265],"type":"Point"}
}