{
  "type": "Feature",
  "properties": {
    "iso:country":"IN",
    "ks:ks_alt_nam":"Takht Gos\u0101in",
    "ks:ks_name":"Takht Gosain",
    "ks:ks_type":"VILLAGE",
    "name:eng_x_preferred":[
        "Takht Gosain"
    ],
    "name:eng_x_variant":[
        "Takht Gos\u0101in"
    ],
    "wof:name":"Takht Gosain",
    "wof:placetype":"locality"
},
  "geometry": {"coordinates":[78.579511,28.591884],"type":"Point"}
}