{
  "type": "Feature",
  "properties": {
    "gn:admin1_code":"34.0",
    "gn:admin2_code":"219.0",
    "gn:asciiname":"Basahi",
    "gn:country_code":"IN",
    "gn:dem":66,
    "gn:feature_class":"P",
    "gn:feature_code":"PPL",
    "gn:name":"Basahi",
    "gn:population":0,
    "gn:timezone":"Asia/Kolkata",
    "iso:country":"IN",
    "ks:ks_name":"Basah",
    "ks:ks_pop":3887,
    "ks:ks_type":"VILLAGE",
    "name:eng_x_preferred":[
        "Basah"
    ],
    "name:eng_x_variant":[
        "Basahi"
    ],
    "wof:name":"Basah",
    "wof:placetype":"locality",
    "wof:population":3887
},
  "geometry": {"coordinates":[84.642363,26.040567],"type":"Point"}
}