{
  "type": "Feature",
  "properties": {
    "gn:admin1_code":"2.0",
    "gn:asciiname":"Nallakhandriga",
    "gn:country_code":"IN",
    "gn:dem":124,
    "gn:feature_class":"P",
    "gn:feature_code":"PPL",
    "gn:name":"Nallakhandriga",
    "gn:population":0,
    "gn:timezone":"Asia/Kolkata",
    "iso:country":"IN",
    "wof:name":"Nallakhandriga",
    "wof:placetype":"neighbourhood"
},
  "geometry": {"coordinates":[79.54882000000001,13.302],"type":"Point"}
}