{
  "type": "Feature",
  "properties": {
    "gn:admin1_code":"2",
    "gn:admin2_code":"545.0",
    "gn:asciiname":"Burugubanda",
    "gn:country_code":"IN",
    "gn:dem":112,
    "gn:feature_class":"P",
    "gn:feature_code":"PPL",
    "gn:name":"B\u016brugubanda",
    "gn:population":0,
    "gn:timezone":"Asia/Kolkata",
    "iso:country":"IN",
    "ks:ks_name":"M Burugubanda",
    "ks:ks_pop":136,
    "ks:ks_type":"HABITATION",
    "name:eng_x_preferred":[
        "M Burugubanda"
    ],
    "name:eng_x_variant":[
        "Burugubanda"
    ],
    "wof:name":"M Burugubanda",
    "wof:placetype":"locality",
    "wof:population":136
},
  "geometry": {"coordinates":[81.781408,17.312175],"type":"Point"}
}