{
  "type": "Feature",
  "properties": {
    "gn:admin1_code":"34.0",
    "gn:admin2_code":"221.0",
    "gn:asciiname":"Dharampur Asli",
    "gn:country_code":"IN",
    "gn:dem":51,
    "gn:feature_class":"P",
    "gn:feature_code":"PPL",
    "gn:name":"Dharampur Asli",
    "gn:population":0,
    "gn:timezone":"Asia/Kolkata",
    "iso:country":"IN",
    "name:eng_x_preferred":[
        "Dharampur Asli"
    ],
    "wof:name":"Dharampur Asli",
    "wof:placetype":"locality"
},
  "geometry": {"coordinates":[85.57318000000002,25.67966],"type":"Point"}
}