{
  "type": "Feature",
  "properties": {
    "gn:admin1_code":"36.0",
    "gn:admin2_code":"148",
    "gn:asciiname":"Sakatpur",
    "gn:country_code":"IN",
    "gn:dem":154,
    "gn:feature_class":"P",
    "gn:feature_code":"PPL",
    "gn:name":"Sakatpur",
    "gn:population":0,
    "gn:timezone":"Asia/Kolkata",
    "iso:country":"IN",
    "name:msa_x_preferred":[
        "Sakatpur"
    ],
    "wof:name":"Sakatpur",
    "wof:placetype":"locality"
},
  "geometry": {"coordinates":[79.27495,27.05398],"type":"Point"}
}