{
  "type": "Feature",
  "properties": {
    "iso:country":"IN",
    "ks:ks_name":"Jamdiha",
    "ks:ks_pop":591,
    "ks:ks_type":"VILLAGE",
    "name:eng_x_preferred":[
        "Jamdiha"
    ],
    "wof:name":"Jamdiha",
    "wof:placetype":"locality",
    "wof:population":591
},
  "geometry": {"coordinates":[86.552302,23.92177],"type":"Point"}
}