{
  "type": "Feature",
  "properties": {
    "gn:admin1_code":"37.0",
    "gn:admin2_code":"417.0",
    "gn:asciiname":"Peddapal",
    "gn:country_code":"IN",
    "gn:dem":386,
    "gn:feature_class":"P",
    "gn:feature_code":"PPL",
    "gn:name":"Peddap\u0101l",
    "gn:population":0,
    "gn:timezone":"Asia/Kolkata",
    "iso:country":"IN",
    "ks:ks_name":"Pedapal",
    "ks:ks_pop":119,
    "ks:ks_type":"HABITATION",
    "name:eng_x_preferred":[
        "Pedapal"
    ],
    "name:eng_x_variant":[
        "Peddapal"
    ],
    "wof:name":"Pedapal",
    "wof:placetype":"locality",
    "wof:population":119
},
  "geometry": {"coordinates":[81.20398299999999,18.878182],"type":"Point"}
}