{
  "type": "Feature",
  "properties": {
    "gn:admin1_code":"28.0",
    "gn:admin2_code":"333.0",
    "gn:asciiname":"Bhabanipur",
    "gn:country_code":"IN",
    "gn:dem":29,
    "gn:feature_class":"P",
    "gn:feature_code":"PPL",
    "gn:name":"Bhab\u0101nipur",
    "gn:population":0,
    "gn:timezone":"Asia/Kolkata",
    "iso:country":"IN",
    "name:ben_x_preferred":[
        "\u09ad\u09ac\u09be\u09a8\u09c0\u09aa\u09c1\u09b0"
    ],
    "wof:name":"Bhabanipur",
    "wof:placetype":"locality"
},
  "geometry": {"coordinates":[87.92504,24.71315],"type":"Point"}
}