{
  "type": "Feature",
  "properties": {
    "iso:country":"IN",
    "ks:ks_name":"Dabhilwadi",
    "ks:ks_pop":302,
    "ks:ks_type":"HABITATION",
    "name:eng_x_preferred":[
        "Dabhilwadi"
    ],
    "wof:name":"Dabhilwadi",
    "wof:placetype":"locality",
    "wof:population":302
},
  "geometry": {"coordinates":[73.356537,16.787796],"type":"Point"}
}