{
  "type": "Feature",
  "properties": {
    "gn:admin1_code":"36.0",
    "gn:admin2_code":"175.0",
    "gn:asciiname":"Pandit ka Pura",
    "gn:country_code":"IN",
    "gn:dem":96,
    "gn:feature_class":"P",
    "gn:feature_code":"PPL",
    "gn:name":"Pandit ka Pura",
    "gn:population":0,
    "gn:timezone":"Asia/Kolkata",
    "iso:country":"IN",
    "name:und_x_variant":[
        "Kh\u016bjhi"
    ],
    "wof:name":"Pandit ka Pura",
    "wof:placetype":"locality"
},
  "geometry": {"coordinates":[81.81506,25.15189],"type":"Point"}
}