{
  "type": "Feature",
  "properties": {
    "iso:country":"IN",
    "ks:ks_alt_nam":"CHAK SALEMPUR",
    "ks:ks_name":"Chak Salempur",
    "ks:ks_pop":355,
    "ks:ks_type":"HABITATION",
    "name:eng_x_preferred":[
        "Chak Salempur"
    ],
    "wof:name":"Chak Salempur",
    "wof:placetype":"locality",
    "wof:population":355
},
  "geometry": {"coordinates":[86.23732,25.24789],"type":"Point"}
}