{
  "type": "Feature",
  "properties": {
    "iso:country":"IN",
    "ks:ks_name":"Kallumarpatti",
    "ks:ks_pop":826,
    "ks:ks_type":"VILLAGE",
    "name:eng_x_preferred":[
        "Kallumarpatti"
    ],
    "wof:name":"Kallumarpatti",
    "wof:placetype":"locality",
    "wof:population":826
},
  "geometry": {"coordinates":[77.96488600000001,9.5104],"type":"Point"}
}