{
  "type": "Feature",
  "properties": {
    "gn:admin1_code":"35",
    "gn:admin2_code":"426.0",
    "gn:asciiname":"Sunadar",
    "gn:country_code":"IN",
    "gn:dem":328,
    "gn:feature_class":"P",
    "gn:feature_code":"PPL",
    "gn:name":"Sun\u0101dar",
    "gn:population":0,
    "gn:timezone":"Asia/Kolkata",
    "iso:country":"IN",
    "ks:ks_alt_nam":"Sun\u0101dar",
    "ks:ks_name":"Sunadar",
    "ks:ks_type":"VILLAGE",
    "name:eng_x_preferred":[
        "Sunadar"
    ],
    "name:eng_x_variant":[
        "Sun\u0101dar"
    ],
    "wof:name":"Sunadar",
    "wof:placetype":"locality"
},
  "geometry": {"coordinates":[80.146461,24.236412],"type":"Point"}
}