{
  "type": "Feature",
  "properties": {
    "iso:country":"IN",
    "ks:ks_alt_nam":"B.Kutung",
    "ks:ks_name":"B.kutung",
    "ks:ks_pop":457,
    "ks:ks_type":"HABITATION",
    "name:eng_x_preferred":[
        "B.kutung"
    ],
    "wof:name":"B.kutung",
    "wof:placetype":"locality",
    "wof:population":457
},
  "geometry": {"coordinates":[86.11104,22.6425],"type":"Point"}
}