{
  "type": "Feature",
  "properties": {
    "iso:country":"IN",
    "ks:ks_name":"Rameikhamar",
    "ks:ks_pop":942,
    "ks:ks_type":"VILLAGE",
    "name:eng_x_preferred":[
        "Rameikhamar"
    ],
    "wof:name":"Rameikhamar",
    "wof:placetype":"locality",
    "wof:population":942
},
  "geometry": {"coordinates":[85.84844699999999,20.726764],"type":"Point"}
}