{
  "type": "Feature",
  "properties": {
    "iso:country":"IN",
    "ks:ks_name":"Akaria",
    "ks:ks_pop":1039,
    "ks:ks_type":"HABITATION",
    "name:eng_x_preferred":[
        "Akaria"
    ],
    "wof:name":"Akaria",
    "wof:placetype":"locality",
    "wof:population":1039
},
  "geometry": {"coordinates":[84.822896,24.877884],"type":"Point"}
}