{
  "type": "Feature",
  "properties": {
    "iso:country":"IN",
    "ks:ks_name":"Dhanouchhi",
    "ks:ks_pop":86,
    "ks:ks_type":"HABITATION",
    "name:eng_x_preferred":[
        "Dhanouchhi"
    ],
    "wof:name":"Dhanouchhi",
    "wof:placetype":"locality",
    "wof:population":86
},
  "geometry": {"coordinates":[86.639983,24.773099],"type":"Point"}
}