{
  "type": "Feature",
  "properties": {
    "iso:country":"IN",
    "ks:ks_name":"Kavumpadi",
    "ks:ks_pop":1725,
    "ks:ks_type":"HABITATION",
    "ks:ks_uagg_main":0,
    "name:eng_x_preferred":[
        "Kavumpadi"
    ],
    "wof:name":"Kavumpadi",
    "wof:placetype":"neighbourhood",
    "wof:population":1725
},
  "geometry": {"coordinates":[76.506534,10.939224],"type":"Point"}
}