{
  "type": "Feature",
  "properties": {
    "iso:country":"IN",
    "ks:ks_name":"Junjuroda",
    "ks:ks_pop":45,
    "ks:ks_type":"HABITATION",
    "name:eng_x_preferred":[
        "Junjuroda"
    ],
    "wof:name":"Junjuroda",
    "wof:placetype":"locality",
    "wof:population":45
},
  "geometry": {"coordinates":[82.758084,18.009303],"type":"Point"}
}