{
  "type": "Feature",
  "properties": {
    "gn:admin1_code":"19.0",
    "gn:admin2_code":"574.0",
    "gn:asciiname":"Yarehallipalya",
    "gn:country_code":"IN",
    "gn:dem":786,
    "gn:feature_class":"P",
    "gn:feature_code":"PPL",
    "gn:name":"Yarehallip\u0101lya",
    "gn:population":0,
    "gn:timezone":"Asia/Kolkata",
    "iso:country":"IN",
    "wof:name":"Yarehallipalya",
    "wof:placetype":"locality"
},
  "geometry": {"coordinates":[76.39641,13.47992],"type":"Point"}
}