{
  "type": "Feature",
  "properties": {
    "iso:country":"IN",
    "ks:ks_name":"Salrapada",
    "ks:ks_pop":588,
    "ks:ks_type":"HABITATION",
    "name:eng_x_preferred":[
        "Salrapada"
    ],
    "wof:name":"Salrapada",
    "wof:placetype":"locality",
    "wof:population":588
},
  "geometry": {"coordinates":[74.783441,23.495989],"type":"Point"}
}