{
  "type": "Feature",
  "properties": {
    "iso:country":"IN",
    "ks:ks_name":"Moharli",
    "ks:ks_pop":192,
    "ks:ks_type":"HABITATION",
    "name:eng_x_preferred":[
        "Moharli"
    ],
    "wof:name":"Moharli",
    "wof:placetype":"locality",
    "wof:population":192
},
  "geometry": {"coordinates":[80.358586,19.664167],"type":"Point"}
}