{
  "type": "Feature",
  "properties": {
    "iso:country":"IN",
    "ks:ks_name":"Tola Madhuwa",
    "ks:ks_pop":27,
    "ks:ks_type":"VILLAGE",
    "name:eng_x_preferred":[
        "Tola Madhuwa"
    ],
    "wof:name":"Tola Madhuwa",
    "wof:placetype":"locality",
    "wof:population":27
},
  "geometry": {"coordinates":[86.31654399999999,24.514936],"type":"Point"}
}