{
  "type": "Feature",
  "properties": {
    "iso:country":"IN",
    "ks:ks_name":"Rengaguda",
    "ks:ks_pop":141,
    "ks:ks_type":"HABITATION",
    "name:eng_x_preferred":[
        "Rengaguda"
    ],
    "wof:name":"Rengaguda",
    "wof:placetype":"locality",
    "wof:population":141
},
  "geometry": {"coordinates":[81.279754,19.595324],"type":"Point"}
}