{
  "type": "Feature",
  "properties": {
    "iso:country":"IN",
    "ks:ks_name":"Kalyanpura",
    "ks:ks_pop":0,
    "ks:ks_type":"VILLAGE",
    "name:eng_x_preferred":[
        "Kalyanpura"
    ],
    "wof:name":"Kalyanpura",
    "wof:placetype":"locality",
    "wof:population":0
},
  "geometry": {"coordinates":[75.484398,21.801932],"type":"Point"}
}