{
  "type": "Feature",
  "properties": {
    "gn:admin1_code":"16",
    "gn:admin2_code":"506.0",
    "gn:asciiname":"Kamkasur",
    "gn:country_code":"IN",
    "gn:dem":347,
    "gn:feature_class":"P",
    "gn:feature_code":"PPL",
    "gn:name":"Kamk\u0101sur",
    "gn:population":0,
    "gn:timezone":"Asia/Kolkata",
    "iso:country":"IN",
    "ks:ks_alt_nam":"Kamk\u0101sur",
    "ks:ks_name":"Kamkasur",
    "ks:ks_type":"VILLAGE",
    "name:eng_x_preferred":[
        "Kamkasur"
    ],
    "name:eng_x_variant":[
        "Kamk\u0101sur"
    ],
    "wof:name":"Kamkasur",
    "wof:placetype":"locality"
},
  "geometry": {"coordinates":[79.515694,21.516929],"type":"Point"}
}