{
  "type": "Feature",
  "properties": {
    "gn:admin1_code":"11.0",
    "gn:admin2_code":"33.0",
    "gn:asciiname":"Narenti",
    "gn:country_code":"IN",
    "gn:dem":2071,
    "gn:feature_class":"P",
    "gn:feature_code":"PPL",
    "gn:name":"Narenti",
    "gn:population":0,
    "gn:timezone":"Asia/Kolkata",
    "iso:country":"IN",
    "wof:name":"Narenti",
    "wof:placetype":"locality"
},
  "geometry": {"coordinates":[77.43805999999999,31.06997],"type":"Point"}
}