{
  "type": "Feature",
  "properties": {
    "iso:country":"IN",
    "ks:ks_name":"Paral",
    "ks:ks_pop":287,
    "ks:ks_type":"VILLAGE",
    "name:eng_x_preferred":[
        "Paral"
    ],
    "wof:name":"Paral",
    "wof:placetype":"locality",
    "wof:population":287
},
  "geometry": {"coordinates":[85.347977,22.414512],"type":"Point"}
}