{
  "type": "Feature",
  "properties": {
    "iso:country":"IN",
    "ks:ks_name":"Bodisatram",
    "ks:ks_pop":287,
    "ks:ks_type":"HABITATION",
    "name:eng_x_preferred":[
        "Bodisatram"
    ],
    "wof:name":"Bodisatram",
    "wof:placetype":"locality",
    "wof:population":287
},
  "geometry": {"coordinates":[80.048703,14.667396],"type":"Point"}
}