{
  "type": "Feature",
  "properties": {
    "iso:country":"IN",
    "ks:ks_name":"Kokasur",
    "ks:ks_pop":63,
    "ks:ks_type":"VILLAGE",
    "name:eng_x_preferred":[
        "Kokasur"
    ],
    "wof:name":"Kokasur",
    "wof:placetype":"locality",
    "wof:population":63
},
  "geometry": {"coordinates":[83.319434,19.731895],"type":"Point"}
}