{
  "type": "Feature",
  "properties": {
    "iso:country":"IN",
    "ks:ks_name":"Dhanga Dungri",
    "ks:ks_pop":0,
    "ks:ks_type":"VILLAGE",
    "name:eng_x_preferred":[
        "Dhanga Dungri"
    ],
    "wof:name":"Dhanga Dungri",
    "wof:placetype":"locality",
    "wof:population":0
},
  "geometry": {"coordinates":[86.82292200000001,23.054188],"type":"Point"}
}