{
  "type": "Feature",
  "properties": {
    "iso:country":"IN",
    "ks:ks_name":"Kapasbera",
    "ks:ks_pop":90,
    "ks:ks_type":"VILLAGE",
    "name:eng_x_preferred":[
        "Kapasbera"
    ],
    "wof:name":"Kapasbera",
    "wof:placetype":"locality",
    "wof:population":90
},
  "geometry": {"coordinates":[87.498261,24.8737],"type":"Point"}
}