{
  "type": "Feature",
  "properties": {
    "iso:country":"IN",
    "ks:ks_alt_nam":"Na patia",
    "ks:ks_name":"Na Patia",
    "ks:ks_pop":199,
    "ks:ks_type":"HABITATION",
    "name:eng_x_preferred":[
        "Na Patia"
    ],
    "wof:name":"Na Patia",
    "wof:placetype":"locality",
    "wof:population":199
},
  "geometry": {"coordinates":[95.89011600000001,27.87929],"type":"Point"}
}