{
  "type": "Feature",
  "properties": {
    "iso:country":"IN",
    "ks:ks_alt_nam":"Kazimache temb",
    "ks:ks_name":"Kazimache Temb",
    "ks:ks_pop":152,
    "ks:ks_type":"HABITATION",
    "name:eng_x_preferred":[
        "Kazimache Temb"
    ],
    "wof:name":"Kazimache Temb",
    "wof:placetype":"locality",
    "wof:population":152
},
  "geometry": {"coordinates":[73.827567,16.143613],"type":"Point"}
}