{
  "type": "Feature",
  "properties": {
    "gn:admin1_code":"35.0",
    "gn:admin2_code":"425.0",
    "gn:asciiname":"Sati",
    "gn:country_code":"IN",
    "gn:dem":234,
    "gn:feature_class":"P",
    "gn:feature_code":"PPL",
    "gn:name":"Sati",
    "gn:population":0,
    "gn:timezone":"Asia/Kolkata",
    "iso:country":"IN",
    "name:ara_x_preferred":[
        "\u0633\u0627\u062a\u064a"
    ],
    "name:ben_bn_x_preferred":[
        "\u09b8\u09a4\u09c0"
    ],
    "name:ben_in_x_preferred":[
        "\u09b8\u09a4\u09c0"
    ],
    "name:bih_x_preferred":[
        "\u0938\u0924\u0940"
    ],
    "name:bul_x_preferred":[
        "\u0421\u0430\u0442\u0438"
    ],
    "name:cat_x_preferred":[
        "Sati"
    ],
    "name:ceb_x_preferred":[
        "Sati"
    ],
    "name:ces_x_preferred":[
        "Sat\u00ed"
    ],
    "name:dan_x_preferred":[
        "Sati"
    ],
    "name:deu_x_preferred":[
        "Sati"
    ],
    "name:fas_x_preferred":[
        "\u0633\u0627\u062a\u06cc"
    ],
    "name:fra_x_preferred":[
        "Sati"
    ],
    "name:guj_x_preferred":[
        "\u0ab8\u0aa4\u0ac0"
    ],
    "name:hin_x_preferred":[
        "\u0938\u0924\u0940"
    ],
    "name:ind_x_preferred":[
        "Sati"
    ],
    "name:jpn_x_preferred":[
        "\u30b5\u30c6\u30a3"
    ],
    "name:kan_x_preferred":[
        "\u0cb8\u0ca4\u0cbf"
    ],
    "name:lit_x_preferred":[
        "Sati"
    ],
    "name:mal_x_preferred":[
        "\u0d38\u0d24\u0d3f"
    ],
    "name:mar_x_preferred":[
        "\u0938\u0924\u0940"
    ],
    "name:msa_x_preferred":[
        "Sati"
    ],
    "name:nld_x_preferred":[
        "Sati"
    ],
    "name:nor_x_preferred":[
        "Sati"
    ],
    "name:pan_x_preferred":[
        "\u0a38\u0a24\u0a40"
    ],
    "name:pol_x_preferred":[
        "Sati"
    ],
    "name:rus_x_preferred":[
        "\u0421\u0430\u0442\u0438"
    ],
    "name:sco_x_preferred":[
        "Sati"
    ],
    "name:spa_x_preferred":[
        "Sati"
    ],
    "name:srp_x_preferred":[
        "\u0421\u0430\u0442\u0438"
    ],
    "name:swe_x_preferred":[
        "Sati"
    ],
    "name:tam_x_preferred":[
        "\u0b9a\u0ba4\u0bbf"
    ],
    "name:tel_x_preferred":[
        "\u0c38\u0c24\u0c3f"
    ],
    "name:tha_x_preferred":[
        "\u0e2a\u0e15\u0e35"
    ],
    "name:ukr_x_preferred":[
        "\u0421\u0430\u0442\u0456"
    ],
    "name:urd_x_preferred":[
        "\u0633\u062a\u06cc"
    ],
    "wof:name":"Sati",
    "wof:placetype":"locality"
},
  "geometry": {"coordinates":[79.39771999999998,24.97707],"type":"Point"}
}