{
  "type": "Feature",
  "properties": {
    "iso:country":"IN",
    "ks:ks_name":"Sarhikita Arazi",
    "ks:ks_pop":0,
    "ks:ks_type":"VILLAGE",
    "name:eng_x_preferred":[
        "Sarhikita Arazi"
    ],
    "wof:name":"Sarhikita Arazi",
    "wof:placetype":"locality",
    "wof:population":0
},
  "geometry": {"coordinates":[86.796245,25.114163],"type":"Point"}
}