{
  "type": "Feature",
  "properties": {
    "iso:country":"IN",
    "ks:ks_name":"Garhi Harlal",
    "ks:ks_pop":196,
    "ks:ks_type":"HABITATION",
    "name:eng_x_preferred":[
        "Garhi Harlal"
    ],
    "wof:name":"Garhi Harlal",
    "wof:placetype":"locality",
    "wof:population":196
},
  "geometry": {"coordinates":[78.053259,26.982311],"type":"Point"}
}