{
  "type": "Feature",
  "properties": {
    "iso:country":"IN",
    "ks:ks_name":"Telangaput",
    "ks:ks_pop":38,
    "ks:ks_type":"HABITATION",
    "name:eng_x_preferred":[
        "Telangaput"
    ],
    "wof:name":"Telangaput",
    "wof:placetype":"locality",
    "wof:population":38
},
  "geometry": {"coordinates":[82.652822,18.363167],"type":"Point"}
}