{
  "type": "Feature",
  "properties": {
    "iso:country":"IN",
    "ks:ks_name":"Meharpur",
    "ks:ks_type":"VILLAGE",
    "name:eng_x_preferred":[
        "Meharpur"
    ],
    "wof:name":"Meharpur",
    "wof:placetype":"locality"
},
  "geometry": {"coordinates":[77.296408,29.943306],"type":"Point"}
}