{
  "type": "Feature",
  "properties": {
    "gn:admin1_code":"36",
    "gn:admin2_code":"196.0",
    "gn:asciiname":"Sain",
    "gn:country_code":"IN",
    "gn:dem":82,
    "gn:feature_class":"P",
    "gn:feature_code":"PPL",
    "gn:name":"S\u0101\u012bn",
    "gn:population":0,
    "gn:timezone":"Asia/Kolkata",
    "iso:country":"IN",
    "name:bre_x_preferred":[
        "Sain"
    ],
    "name:rus_x_preferred":[
        "Sain Records"
    ],
    "wof:name":"Sain",
    "wof:placetype":"locality"
},
  "geometry": {"coordinates":[83.18347,25.32947],"type":"Point"}
}