{
  "type": "Feature",
  "properties": {
    "iso:country":"IN",
    "ks:ks_name":"Goalbil",
    "ks:ks_pop":459,
    "ks:ks_type":"VILLAGE",
    "ks:ks_uagg_main":0,
    "name:eng_x_preferred":[
        "Goalbil"
    ],
    "wof:name":"Goalbil",
    "wof:placetype":"neighbourhood",
    "wof:population":459
},
  "geometry": {"coordinates":[91.494484,26.584839],"type":"Point"}
}