{
  "type": "Feature",
  "properties": {
    "iso:country":"IN",
    "ks:ks_name":"Nalagadde",
    "ks:ks_pop":70,
    "ks:ks_type":"HABITATION",
    "name:eng_x_preferred":[
        "Nalagadde"
    ],
    "wof:name":"Nalagadde",
    "wof:placetype":"locality",
    "wof:population":70
},
  "geometry": {"coordinates":[75.487292,13.537808],"type":"Point"}
}