{
  "type": "Feature",
  "properties": {
    "iso:country":"IN",
    "ks:ks_name":"Gunhera",
    "ks:ks_pop":575,
    "ks:ks_type":"VILLAGE",
    "name:eng_x_preferred":[
        "Gunhera"
    ],
    "wof:name":"Gunhera",
    "wof:placetype":"locality",
    "wof:population":575
},
  "geometry": {"coordinates":[75.4515,22.46785],"type":"Point"}
}