{
  "type": "Feature",
  "properties": {
    "gn:admin1_code":"9.0",
    "gn:admin2_code":"484.0",
    "gn:asciiname":"Sir Nani Muwara",
    "gn:country_code":"IN",
    "gn:dem":166,
    "gn:feature_class":"P",
    "gn:feature_code":"PPL",
    "gn:name":"Sir Nani Muw\u0101ra",
    "gn:population":0,
    "gn:timezone":"Asia/Kolkata",
    "iso:country":"IN",
    "wof:name":"Sir Nani Muwara",
    "wof:placetype":"locality"
},
  "geometry": {"coordinates":[73.89158,23.1319],"type":"Point"}
}