{
  "type": "Feature",
  "properties": {
    "gn:admin1_code":"36",
    "gn:admin2_code":"173.0",
    "gn:asciiname":"Bihariganj",
    "gn:country_code":"IN",
    "gn:dem":103,
    "gn:feature_class":"P",
    "gn:feature_code":"PPL",
    "gn:name":"Bih\u0101r\u012bganj",
    "gn:population":0,
    "gn:timezone":"Asia/Kolkata",
    "iso:country":"IN",
    "name:ceb_x_preferred":[
        "Bih\u0101r\u012bganj"
    ],
    "name:swe_x_preferred":[
        "Bih\u0101r\u012bganj"
    ],
    "wof:name":"Bihariganj",
    "wof:placetype":"locality"
},
  "geometry": {"coordinates":[81.67149000000001,25.86543],"type":"Point"}
}