{
  "type": "Feature",
  "properties": {
    "gn:admin1_code":"38.0",
    "gn:admin2_code":"348.0",
    "gn:asciiname":"Chadra",
    "gn:country_code":"IN",
    "gn:dem":353,
    "gn:feature_class":"P",
    "gn:feature_code":"PPL",
    "gn:name":"Chadr\u0101",
    "gn:population":0,
    "gn:timezone":"Asia/Kolkata",
    "iso:country":"IN",
    "name:ita_x_preferred":[
        "Chadra"
    ],
    "wof:name":"Chadra",
    "wof:placetype":"locality"
},
  "geometry": {"coordinates":[85.73899999999998,24.35817],"type":"Point"}
}