{
  "type": "Feature",
  "properties": {
    "iso:country":"IN",
    "ks:ks_name":"Baligaon",
    "ks:ks_pop":316,
    "ks:ks_type":"VILLAGE",
    "name:eng_x_preferred":[
        "Baligaon"
    ],
    "wof:name":"Baligaon",
    "wof:placetype":"locality",
    "wof:population":316
},
  "geometry": {"coordinates":[93.85934,26.875059],"type":"Point"}
}