{
  "type": "Feature",
  "properties": {
    "gn:admin1_code":"11",
    "gn:admin2_code":"33.0",
    "gn:asciiname":"Dhugna",
    "gn:country_code":"IN",
    "gn:dem":2095,
    "gn:feature_class":"P",
    "gn:feature_code":"PPL",
    "gn:name":"Dhugna",
    "gn:population":0,
    "gn:timezone":"Asia/Kolkata",
    "iso:country":"IN",
    "wof:name":"Dhugna",
    "wof:placetype":"locality"
},
  "geometry": {"coordinates":[77.53719,30.90022],"type":"Point"}
}