{
  "type": "Feature",
  "properties": {
    "gn:admin1_code":"34.0",
    "gn:admin2_code":"231.0",
    "gn:asciiname":"Dhangawan",
    "gn:country_code":"IN",
    "gn:dem":87,
    "gn:feature_class":"P",
    "gn:feature_code":"PPL",
    "gn:name":"Dhang\u0101w\u0101n",
    "gn:population":0,
    "gn:timezone":"Asia/Kolkata",
    "iso:country":"IN",
    "wof:name":"Dhangawan",
    "wof:placetype":"locality"
},
  "geometry": {"coordinates":[84.43947,25.23095],"type":"Point"}
}