{
  "type": "Feature",
  "properties": {
    "gn:admin1_code":"34.0",
    "gn:admin2_code":"204.0",
    "gn:asciiname":"Katkenwa",
    "gn:country_code":"IN",
    "gn:dem":76,
    "gn:feature_class":"P",
    "gn:feature_code":"PPL",
    "gn:name":"Katkenwa",
    "gn:population":0,
    "gn:timezone":"Asia/Kolkata",
    "iso:country":"IN",
    "ks:ks_name":"Katkenwa",
    "ks:ks_pop":900,
    "ks:ks_type":"HABITATION",
    "ks:ks_uagg_main":0,
    "name:eng_x_preferred":[
        "Katkenwa"
    ],
    "wof:name":"Katkenwa",
    "wof:placetype":"neighbourhood",
    "wof:population":900
},
  "geometry": {"coordinates":[84.75156200000001,26.816453],"type":"Point"}
}