{
  "type": "Feature",
  "properties": {
    "gn:admin1_code":"37",
    "gn:admin2_code":"406.0",
    "gn:asciiname":"Baharmunda",
    "gn:country_code":"IN",
    "gn:dem":294,
    "gn:feature_class":"P",
    "gn:feature_code":"PPL",
    "gn:name":"Bah\u0101rmunda",
    "gn:population":0,
    "gn:timezone":"Asia/Kolkata",
    "iso:country":"IN",
    "ks:ks_alt_nam":"BAHARMUDA",
    "ks:ks_name":"Baharmuda",
    "ks:ks_pop":80,
    "ks:ks_type":"HABITATION",
    "name:eng_x_preferred":[
        "Baharmuda"
    ],
    "name:eng_x_variant":[
        "Baharmunda"
    ],
    "wof:name":"Baharmuda",
    "wof:placetype":"locality",
    "wof:population":80
},
  "geometry": {"coordinates":[81.600669,22.030558],"type":"Point"}
}