{
  "type": "Feature",
  "properties": {
    "iso:country":"IN",
    "ks:ks_alt_nam":"SUKALKAR WASTI",
    "ks:ks_name":"Sukalkar Wasti",
    "ks:ks_pop":100,
    "ks:ks_type":"HABITATION",
    "name:eng_x_preferred":[
        "Sukalkar Wasti"
    ],
    "wof:name":"Sukalkar Wasti",
    "wof:placetype":"locality",
    "wof:population":100
},
  "geometry": {"coordinates":[74.91970600000001,19.484738],"type":"Point"}
}