{
  "type": "Feature",
  "properties": {
    "iso:country":"IN",
    "ks:ks_name":"Semwal Gaon",
    "ks:ks_pop":21,
    "ks:ks_type":"HABITATION",
    "name:eng_x_preferred":[
        "Semwal Gaon"
    ],
    "wof:name":"Semwal Gaon",
    "wof:placetype":"locality",
    "wof:population":21
},
  "geometry": {"coordinates":[78.75493899999999,30.263237],"type":"Point"}
}