{
  "type": "Feature",
  "properties": {
    "iso:country":"IN",
    "ks:ks_name":"Bil Begampur",
    "ks:ks_pop":0,
    "ks:ks_type":"VILLAGE",
    "name:eng_x_preferred":[
        "Bil Begampur"
    ],
    "wof:name":"Bil Begampur",
    "wof:placetype":"locality",
    "wof:population":0
},
  "geometry": {"coordinates":[88.166061,24.099611],"type":"Point"}
}