{
  "type": "Feature",
  "properties": {
    "gn:admin1_code":"21.0",
    "gn:admin2_code":"382.0",
    "gn:asciiname":"Naranapur",
    "gn:country_code":"IN",
    "gn:dem":11,
    "gn:feature_class":"P",
    "gn:feature_code":"PPL",
    "gn:name":"Naranapur",
    "gn:population":0,
    "gn:timezone":"Asia/Kolkata",
    "iso:country":"IN",
    "wof:name":"Naranapur",
    "wof:placetype":"locality"
},
  "geometry": {"coordinates":[86.40101,20.68973],"type":"Point"}
}