{
  "type": "Feature",
  "properties": {
    "iso:country":"IN",
    "ks:ks_name":"Chinargaon",
    "ks:ks_pop":123,
    "ks:ks_type":"VILLAGE",
    "name:eng_x_preferred":[
        "Chinargaon"
    ],
    "wof:name":"Chinargaon",
    "wof:placetype":"locality",
    "wof:population":123
},
  "geometry": {"coordinates":[78.42285200000001,30.666145],"type":"Point"}
}