{
  "type": "Feature",
  "properties": {
    "iso:country":"IN",
    "qs:name":"Suruiyammapet",
    "qs:name_adm0":"India",
    "qs:name_adm1":"Tamil Nadu",
    "qs:photos":19,
    "qs:photos_1k":4,
    "qs:photos_9k":1,
    "qs:photos_9r":1,
    "qs:photos_all":19,
    "qs:photos_sr":1,
    "qs:placetype":"Suburb",
    "qs:pop_sr":"0",
    "wof:name":"Suruiyammapet",
    "wof:placetype":"neighbourhood"
},
  "geometry": {"coordinates":[80.224296,13.022171],"type":"Point"}
}