{
  "type": "Feature",
  "properties": {
    "iso:country":"IN",
    "ks:ks_name":"Holekai",
    "ks:ks_pop":112,
    "ks:ks_type":"HABITATION",
    "name:eng_x_preferred":[
        "Holekai"
    ],
    "wof:name":"Holekai",
    "wof:placetype":"locality",
    "wof:population":112
},
  "geometry": {"coordinates":[74.813625,14.556948],"type":"Point"}
}