{
  "type": "Feature",
  "properties": {
    "gn:admin1_code":"12.0",
    "gn:admin2_code":"14.0",
    "gn:asciiname":"Tsandund",
    "gn:country_code":"IN",
    "gn:dem":2817,
    "gn:feature_class":"P",
    "gn:feature_code":"PPL",
    "gn:name":"Tsandund",
    "gn:population":0,
    "gn:timezone":"Asia/Kolkata",
    "iso:country":"IN",
    "wof:name":"Tsandund",
    "wof:placetype":"locality"
},
  "geometry": {"coordinates":[75.52176,33.4808],"type":"Point"}
}