{
  "type": "Feature",
  "properties": {
    "gn:admin1_code":"34",
    "gn:admin2_code":"218.0",
    "gn:asciiname":"Chhapiya Khurd",
    "gn:country_code":"IN",
    "gn:dem":68,
    "gn:feature_class":"P",
    "gn:feature_code":"PPL",
    "gn:name":"Chhapiya Khurd",
    "gn:population":0,
    "gn:timezone":"Asia/Kolkata",
    "iso:country":"IN",
    "ks:ks_name":"Chhapiya Khurd",
    "ks:ks_pop":1910,
    "ks:ks_type":"VILLAGE",
    "ks:ks_uagg_main":0,
    "name:eng_x_preferred":[
        "Chhapiya Khurd"
    ],
    "wof:name":"Chhapiya Khurd",
    "wof:placetype":"locality",
    "wof:population":1910
},
  "geometry": {"coordinates":[84.361216,26.195072],"type":"Point"}
}