{
  "type": "Feature",
  "properties": {
    "gn:admin1_code":"23.0",
    "gn:admin2_code":"36.0",
    "gn:asciiname":"Subhanpur",
    "gn:country_code":"IN",
    "gn:dem":223,
    "gn:feature_class":"P",
    "gn:feature_code":"PPL",
    "gn:name":"Subh\u0101npur",
    "gn:population":0,
    "gn:timezone":"Asia/Kolkata",
    "iso:country":"IN",
    "ks:ks_alt_nam":"Subh\u0101npur",
    "ks:ks_name":"Subhanpur",
    "ks:ks_pop":486,
    "ks:ks_type":"VILLAGE",
    "ks:ks_uagg_main":0,
    "name:eng_x_preferred":[
        "Subhanpur"
    ],
    "name:eng_x_variant":[
        "Subh\u0101npur"
    ],
    "wof:name":"Subhanpur",
    "wof:placetype":"neighbourhood",
    "wof:population":486
},
  "geometry": {"coordinates":[75.405304,31.465962],"type":"Point"}
}