{
  "type": "Feature",
  "properties": {
    "iso:country":"IN",
    "ks:ks_alt_nam":"tepra",
    "ks:ks_name":"Tepra",
    "ks:ks_pop":79,
    "ks:ks_type":"HABITATION",
    "name:eng_x_preferred":[
        "Tepra"
    ],
    "wof:name":"Tepra",
    "wof:placetype":"locality",
    "wof:population":79
},
  "geometry": {"coordinates":[81.667922,27.474212],"type":"Point"}
}