{
  "type": "Feature",
  "properties": {
    "iso:country":"IN",
    "ks:ks_name":"Shinde Wasti",
    "ks:ks_pop":120,
    "ks:ks_type":"HABITATION",
    "name:eng_x_preferred":[
        "Shinde Wasti"
    ],
    "wof:name":"Shinde Wasti",
    "wof:placetype":"locality",
    "wof:population":120
},
  "geometry": {"coordinates":[75.74782999999999,18.447247],"type":"Point"}
}