{
  "type": "Feature",
  "properties": {
    "iso:country":"IN",
    "ks:ks_name":"Khopaganj",
    "ks:ks_pop":0,
    "ks:ks_type":"VILLAGE",
    "name:eng_x_preferred":[
        "Khopaganj"
    ],
    "wof:name":"Khopaganj",
    "wof:placetype":"locality",
    "wof:population":0
},
  "geometry": {"coordinates":[87.19527600000001,23.366501],"type":"Point"}
}