{
  "type": "Feature",
  "properties": {
    "iso:country":"IN",
    "ks:ks_name":"Duba",
    "ks:ks_pop":175,
    "ks:ks_type":"VILLAGE",
    "name:eng_x_preferred":[
        "Duba"
    ],
    "wof:name":"Duba",
    "wof:placetype":"locality",
    "wof:population":175
},
  "geometry": {"coordinates":[84.345265,19.954695],"type":"Point"}
}