{
  "type": "Feature",
  "properties": {
    "gn:admin1_code":"10.0",
    "gn:admin2_code":"87.0",
    "gn:asciiname":"Chilaoli",
    "gn:country_code":"IN",
    "gn:dem":284,
    "gn:feature_class":"P",
    "gn:feature_code":"PPL",
    "gn:name":"Chilaoli",
    "gn:population":0,
    "gn:timezone":"Asia/Kolkata",
    "iso:country":"IN",
    "wof:name":"Chilaoli",
    "wof:placetype":"locality"
},
  "geometry": {"coordinates":[76.94601999999998,28.17137],"type":"Point"}
}