{
  "type": "Feature",
  "properties": {
    "iso:country":"IN",
    "ks:ks_name":"Donala Chak.",
    "ks:ks_pop":0,
    "ks:ks_type":"VILLAGE",
    "name:eng_x_preferred":[
        "Donala Chak."
    ],
    "wof:name":"Donala Chak.",
    "wof:placetype":"locality",
    "wof:population":0
},
  "geometry": {"coordinates":[79.95998299999999,20.02737],"type":"Point"}
}