{
  "type": "Feature",
  "properties": {
    "iso:country":"IN",
    "ks:ks_name":"Bhediya",
    "ks:ks_pop":1223,
    "ks:ks_type":"VILLAGE",
    "name:eng_x_preferred":[
        "Bhediya"
    ],
    "wof:name":"Bhediya",
    "wof:placetype":"locality",
    "wof:population":1223
},
  "geometry": {"coordinates":[83.15439499999999,23.596827],"type":"Point"}
}