{
  "type": "Feature",
  "properties": {
    "gn:admin1_code":"12.0",
    "gn:admin2_code":"17.0",
    "gn:asciiname":"Nakka",
    "gn:country_code":"IN",
    "gn:dem":2698,
    "gn:feature_class":"P",
    "gn:feature_code":"PPL",
    "gn:name":"Nakka",
    "gn:population":0,
    "gn:timezone":"Asia/Kolkata",
    "iso:country":"IN",
    "wof:name":"Nakka",
    "wof:placetype":"locality"
},
  "geometry": {"coordinates":[75.27391999999998,33.40494],"type":"Point"}
}