{
  "type": "Feature",
  "properties": {
    "iso:country":"IN",
    "ks:ks_alt_nam":"D\u012bh Bharauwa",
    "ks:ks_name":"Dih Bharauwa",
    "ks:ks_pop":95,
    "ks:ks_type":"VILLAGE",
    "name:eng_x_preferred":[
        "Dih Bharauwa"
    ],
    "name:eng_x_variant":[
        "D\u012bh Bharauwa"
    ],
    "wof:name":"Dih Bharauwa",
    "wof:placetype":"locality",
    "wof:population":95
},
  "geometry": {"coordinates":[84.404948,26.679531],"type":"Point"}
}