{
  "type": "Feature",
  "properties": {
    "gn:admin1_code":"19.0",
    "gn:admin2_code":"573.0",
    "gn:asciiname":"Ankegaudanakoppal",
    "gn:country_code":"IN",
    "gn:dem":807,
    "gn:feature_class":"P",
    "gn:feature_code":"PPL",
    "gn:name":"Ankegaudanakoppal",
    "gn:population":0,
    "gn:timezone":"Asia/Kolkata",
    "iso:country":"IN",
    "ks:ks_name":"Ankegowdanakoppalu",
    "ks:ks_pop":242,
    "ks:ks_type":"HABITATION",
    "name:eng_x_preferred":[
        "Ankegowdanakoppalu"
    ],
    "name:eng_x_variant":[
        "Ankegaudanakoppal"
    ],
    "wof:name":"Ankegowdanakoppalu",
    "wof:placetype":"locality",
    "wof:population":242
},
  "geometry": {"coordinates":[76.592521,12.548175],"type":"Point"}
}