{
  "type": "Feature",
  "properties": {
    "iso:country":"IN",
    "ks:ks_name":"Pachwadeshwar",
    "ks:ks_pop":515,
    "ks:ks_type":"HABITATION",
    "name:eng_x_preferred":[
        "Pachwadeshwar"
    ],
    "wof:name":"Pachwadeshwar",
    "wof:placetype":"locality",
    "wof:population":515
},
  "geometry": {"coordinates":[74.18483000000001,17.221499],"type":"Point"}
}