{
  "type": "Feature",
  "properties": {
    "iso:country":"IN",
    "ks:ks_name":"Daktia",
    "ks:ks_pop":266,
    "ks:ks_type":"HABITATION",
    "name:eng_x_preferred":[
        "Daktia"
    ],
    "wof:name":"Daktia",
    "wof:placetype":"locality",
    "wof:population":266
},
  "geometry": {"coordinates":[91.379234,23.121296],"type":"Point"}
}