{
  "type": "Feature",
  "properties": {
    "iso:country":"IN",
    "ks:ks_name":"Kharavira Nes",
    "ks:ks_pop":109,
    "ks:ks_type":"HABITATION",
    "name:eng_x_preferred":[
        "Kharavira Nes"
    ],
    "wof:name":"Kharavira Nes",
    "wof:placetype":"locality",
    "wof:population":109
},
  "geometry": {"coordinates":[69.710258,21.794444],"type":"Point"}
}