{
  "type": "Feature",
  "properties": {
    "iso:country":"IN",
    "ks:ks_name":"Kanwarpara",
    "ks:ks_pop":141,
    "ks:ks_type":"HABITATION",
    "name:eng_x_preferred":[
        "Kanwarpara"
    ],
    "wof:name":"Kanwarpara",
    "wof:placetype":"locality",
    "wof:population":141
},
  "geometry": {"coordinates":[83.63870199999999,22.391041],"type":"Point"}
}