{
  "type": "Feature",
  "properties": {
    "iso:country":"IN",
    "ks:ks_name":"Lulagaon Forest",
    "ks:ks_pop":12,
    "ks:ks_type":"VILLAGE",
    "name:eng_x_preferred":[
        "Lulagaon Forest"
    ],
    "wof:name":"Lulagaon Forest",
    "wof:placetype":"locality",
    "wof:population":12
},
  "geometry": {"coordinates":[88.542525,27.013131],"type":"Point"}
}