{
  "type": "Feature",
  "properties": {
    "gn:admin1_code":"38.0",
    "gn:admin2_code":"353.0",
    "gn:asciiname":"Guakola",
    "gn:country_code":"IN",
    "gn:dem":59,
    "gn:feature_class":"P",
    "gn:feature_code":"PPL",
    "gn:name":"Gu\u0101kola",
    "gn:population":0,
    "gn:timezone":"Asia/Kolkata",
    "iso:country":"IN",
    "ks:ks_name":"Guakaola",
    "ks:ks_pop":63,
    "ks:ks_type":"VILLAGE",
    "name:eng_x_preferred":[
        "Guakaola"
    ],
    "name:eng_x_variant":[
        "Guakola"
    ],
    "wof:name":"Guakaola",
    "wof:placetype":"locality",
    "wof:population":63
},
  "geometry": {"coordinates":[87.71789200000001,24.737038],"type":"Point"}
}