{
  "type": "Feature",
  "properties": {
    "gn:admin1_code":"38",
    "gn:admin2_code":"346.0",
    "gn:asciiname":"Garda",
    "gn:country_code":"IN",
    "gn:dem":235,
    "gn:feature_class":"P",
    "gn:feature_code":"PPL",
    "gn:name":"G\u0101rda",
    "gn:population":0,
    "gn:timezone":"Asia/Kolkata",
    "iso:country":"IN",
    "ks:ks_alt_nam":"G\u0101rda",
    "ks:ks_name":"Garda",
    "ks:ks_pop":290,
    "ks:ks_type":"VILLAGE",
    "name:ceb_x_preferred":[
        "Garda"
    ],
    "name:ces_x_preferred":[
        "Garda"
    ],
    "name:deu_x_preferred":[
        "Garda"
    ],
    "name:eng_x_preferred":[
        "Garda"
    ],
    "name:eng_x_variant":[
        "G\u0101rda"
    ],
    "name:eus_x_preferred":[
        "Garda"
    ],
    "name:fin_x_preferred":[
        "Garda"
    ],
    "name:fra_x_preferred":[
        "Garda"
    ],
    "name:hun_x_preferred":[
        "Garda"
    ],
    "name:hye_x_preferred":[
        "\u0533\u0561\u0580\u0564\u0561"
    ],
    "name:ita_x_preferred":[
        "Garda"
    ],
    "name:jpn_x_preferred":[
        "\u30ac\u30eb\u30c0"
    ],
    "name:kor_x_preferred":[
        "\uac00\ub974\ub2e4"
    ],
    "name:lat_x_preferred":[
        "Garda"
    ],
    "name:lit_x_preferred":[
        "Garda"
    ],
    "name:lmo_x_preferred":[
        "Garda"
    ],
    "name:nld_x_preferred":[
        "Garda"
    ],
    "name:nor_x_preferred":[
        "Garda"
    ],
    "name:pol_x_preferred":[
        "Garda"
    ],
    "name:por_x_preferred":[
        "Garda"
    ],
    "name:ron_x_preferred":[
        "Garda"
    ],
    "name:rus_x_preferred":[
        "\u0413\u0430\u0440\u0434\u0430"
    ],
    "name:slv_x_preferred":[
        "Garda"
    ],
    "name:srp_x_preferred":[
        "\u0413\u0430\u0440\u0434\u0430"
    ],
    "name:swe_x_preferred":[
        "Garda"
    ],
    "name:ukr_x_preferred":[
        "\u0413\u0430\u0440\u0434\u0430"
    ],
    "wof:name":"Garda",
    "wof:placetype":"locality",
    "wof:population":290
},
  "geometry": {"coordinates":[83.574145,24.427416],"type":"Point"}
}