{
  "type": "Feature",
  "properties": {
    "gn:admin1_code":"24.0",
    "gn:admin2_code":"109.0",
    "gn:asciiname":"Bidarkha",
    "gn:country_code":"IN",
    "gn:dem":298,
    "gn:feature_class":"P",
    "gn:feature_code":"PPL",
    "gn:name":"Bidarkha",
    "gn:population":0,
    "gn:timezone":"Asia/Kolkata",
    "iso:country":"IN",
    "wof:name":"Bidarkha",
    "wof:placetype":"locality"
},
  "geometry": {"coordinates":[76.20506999999998,26.65207],"type":"Point"}
}