{
  "type": "Feature",
  "properties": {
    "iso:country":"IN",
    "ks:ks_name":"Khiriya Navalshah",
    "ks:ks_pop":359,
    "ks:ks_type":"VILLAGE",
    "name:eng_x_preferred":[
        "Khiriya Navalshah"
    ],
    "wof:name":"Khiriya Navalshah",
    "wof:placetype":"locality",
    "wof:population":359
},
  "geometry": {"coordinates":[78.36113899999999,23.487632],"type":"Point"}
}