{
  "type": "Feature",
  "properties": {
    "iso:country":"IN",
    "ks:ks_name":"Mundramcumuli",
    "ks:ks_pop":297,
    "ks:ks_type":"HABITATION",
    "name:eng_x_preferred":[
        "Mundramcumuli"
    ],
    "wof:name":"Mundramcumuli",
    "wof:placetype":"locality",
    "wof:population":297
},
  "geometry": {"coordinates":[78.89604300000001,10.847248],"type":"Point"}
}