{
  "type": "Feature",
  "properties": {
    "iso:country":"IN",
    "ks:ks_name":"Nibbugeri Area",
    "ks:ks_pop":124,
    "ks:ks_type":"HABITATION",
    "name:eng_x_preferred":[
        "Nibbugeri Area"
    ],
    "wof:name":"Nibbugeri Area",
    "wof:placetype":"locality",
    "wof:population":124
},
  "geometry": {"coordinates":[75.708611,12.293333],"type":"Point"}
}