{
  "type": "Feature",
  "properties": {
    "gn:admin1_code":"10",
    "gn:admin2_code":"81.0",
    "gn:asciiname":"Brahamanan ki Dhani",
    "gn:country_code":"IN",
    "gn:dem":227,
    "gn:feature_class":"P",
    "gn:feature_code":"PPL",
    "gn:name":"Brahaman\u0101n ki Dh\u0101ni",
    "gn:population":0,
    "gn:timezone":"Asia/Kolkata",
    "iso:country":"IN",
    "name:und_x_variant":[
        "Brahaman\u0101n ki Dh\u0101ni",
        "Shankar ki Dh\u0101ni"
    ],
    "wof:name":"Brahamanan ki Dhani",
    "wof:placetype":"locality"
},
  "geometry": {"coordinates":[75.98761999999998,28.67395],"type":"Point"}
}