{
  "type": "Feature",
  "properties": {
    "iso:country":"IN",
    "ks:ks_alt_nam":"KHOTMALA",
    "ks:ks_name":"Khotmala",
    "ks:ks_pop":142,
    "ks:ks_type":"HABITATION",
    "ks:ks_uagg_main":0,
    "name:eng_x_preferred":[
        "Khotmala"
    ],
    "wof:name":"Khotmala",
    "wof:placetype":"neighbourhood",
    "wof:population":142
},
  "geometry": {"coordinates":[74.2423,16.839339],"type":"Point"}
}