{
  "type": "Feature",
  "properties": {
    "iso:country":"IN",
    "ks:ks_alt_nam":"javalgundi",
    "ks:ks_name":"Javalgundi",
    "ks:ks_pop":439,
    "ks:ks_type":"HABITATION",
    "name:eng_x_preferred":[
        "Javalgundi"
    ],
    "wof:name":"Javalgundi",
    "wof:placetype":"locality",
    "wof:population":439
},
  "geometry": {"coordinates":[74.87059499999999,14.637459],"type":"Point"}
}