{
  "type": "Feature",
  "properties": {
    "iso:country":"IN",
    "ks:ks_name":"Guru Thapal",
    "ks:ks_pop":83,
    "ks:ks_type":"VILLAGE",
    "name:eng_x_preferred":[
        "Guru Thapal"
    ],
    "wof:name":"Guru Thapal",
    "wof:placetype":"locality",
    "wof:population":83
},
  "geometry": {"coordinates":[87.48762600000001,22.473559],"type":"Point"}
}