{
  "type": "Feature",
  "properties": {
    "iso:country":"IN",
    "ks:ks_name":"Tagatarlaghat",
    "ks:ks_pop":298,
    "ks:ks_type":"VILLAGE",
    "name:eng_x_preferred":[
        "Tagatarlaghat"
    ],
    "wof:name":"Tagatarlaghat",
    "wof:placetype":"locality",
    "wof:population":298
},
  "geometry": {"coordinates":[82.83904,19.161531],"type":"Point"}
}