{
  "type": "Feature",
  "properties": {
    "iso:country":"IN",
    "ks:ks_name":"Bechan Mehta Tola",
    "ks:ks_pop":122,
    "ks:ks_type":"HABITATION",
    "ks:ks_uagg_main":0,
    "name:eng_x_preferred":[
        "Bechan Mehta Tola"
    ],
    "wof:name":"Bechan Mehta Tola",
    "wof:placetype":"neighbourhood",
    "wof:population":122
},
  "geometry": {"coordinates":[86.835921,26.391312],"type":"Point"}
}