{
  "type": "Feature",
  "properties": {
    "iso:country":"IN",
    "ks:ks_name":"Dinakobrapara",
    "ks:ks_pop":1097,
    "ks:ks_type":"VILLAGE",
    "name:eng_x_preferred":[
        "Dinakobrapara"
    ],
    "wof:name":"Dinakobrapara",
    "wof:placetype":"locality",
    "wof:population":1097
},
  "geometry": {"coordinates":[91.52197,23.868139],"type":"Point"}
}