{
  "type": "Feature",
  "properties": {
    "iso:country":"IN",
    "ks:ks_name":"Angraje",
    "ks:ks_pop":266,
    "ks:ks_type":"HABITATION",
    "ks:ks_uagg_main":0,
    "name:eng_x_preferred":[
        "Angraje"
    ],
    "wof:name":"Angraje",
    "wof:placetype":"neighbourhood",
    "wof:population":266
},
  "geometry": {"coordinates":[75.14903099999999,12.814638],"type":"Point"}
}