{
  "type": "Feature",
  "properties": {
    "iso:country":"IN",
    "ks:ks_name":"Jigra",
    "ks:ks_pop":713,
    "ks:ks_type":"VILLAGE",
    "ks:ks_uagg_main":0,
    "name:eng_x_preferred":[
        "Jigra"
    ],
    "wof:name":"Jigra",
    "wof:placetype":"neighbourhood",
    "wof:population":713
},
  "geometry": {"coordinates":[88.075935,22.855091],"type":"Point"}
}