{
  "type": "Feature",
  "properties": {
    "gn:admin1_code":"34",
    "gn:admin2_code":"233.0",
    "gn:asciiname":"Misraulia",
    "gn:country_code":"IN",
    "gn:dem":74,
    "gn:feature_class":"P",
    "gn:feature_code":"PPL",
    "gn:name":"Misraulia",
    "gn:population":0,
    "gn:timezone":"Asia/Kolkata",
    "iso:country":"IN",
    "wof:name":"Misraulia",
    "wof:placetype":"neighbourhood"
},
  "geometry": {"coordinates":[83.79224000000001,25.23216],"type":"Point"}
}