{
  "type": "Feature",
  "properties": {
    "gn:admin1_code":"35",
    "gn:admin2_code":"455.0",
    "gn:asciiname":"Rahiwara",
    "gn:country_code":"IN",
    "gn:dem":716,
    "gn:feature_class":"P",
    "gn:feature_code":"PPL",
    "gn:name":"R\u0101h\u012bw\u0101ra",
    "gn:population":0,
    "gn:timezone":"Asia/Kolkata",
    "iso:country":"IN",
    "wof:name":"Rahiwara",
    "wof:placetype":"locality"
},
  "geometry": {"coordinates":[78.98318,22.25036],"type":"Point"}
}