{
  "type": "Feature",
  "properties": {
    "iso:country":"IN",
    "ks:ks_name":"Paschim Chakpanchghora",
    "ks:ks_pop":1975,
    "ks:ks_type":"VILLAGE",
    "ks:ks_uagg_main":0,
    "name:eng_x_preferred":[
        "Paschim Chakpanchghora"
    ],
    "wof:name":"Paschim Chakpanchghora",
    "wof:placetype":"neighbourhood",
    "wof:population":1975
},
  "geometry": {"coordinates":[88.468733,22.259404],"type":"Point"}
}