{
  "type": "Feature",
  "properties": {
    "iso:country":"IN",
    "ks:ks_name":"Udesi Arazi",
    "ks:ks_pop":0,
    "ks:ks_type":"VILLAGE",
    "name:eng_x_preferred":[
        "Udesi Arazi"
    ],
    "wof:name":"Udesi Arazi",
    "wof:placetype":"locality",
    "wof:population":0
},
  "geometry": {"coordinates":[86.95199100000001,25.134441],"type":"Point"}
}