{
  "type": "Feature",
  "properties": {
    "gn:admin1_code":"24.0",
    "gn:admin2_code":"126",
    "gn:asciiname":"Kapasan",
    "gn:cc2":"IN",
    "gn:country_code":"IN",
    "gn:dem":449,
    "gn:feature_class":"P",
    "gn:feature_code":"PPL",
    "gn:name":"Kapasan",
    "gn:population":0,
    "gn:timezone":"Asia/Kolkata",
    "iso:country":"IN",
    "name:ben_x_preferred":[
        "\u0995\u09be\u09aa\u09be\u09b8\u09be\u09a8"
    ],
    "name:bpy_x_preferred":[
        "\u0995\u09be\u09aa\u09be\u09b8\u09be\u09a8"
    ],
    "name:cat_x_preferred":[
        "Kapasan"
    ],
    "name:ceb_x_preferred":[
        "Kapasan"
    ],
    "name:hin_x_preferred":[
        "\u0915\u092a\u093e\u0938\u0928"
    ],
    "name:ita_x_preferred":[
        "Kapasan"
    ],
    "name:mlg_x_preferred":[
        "Kapasan"
    ],
    "name:msa_x_preferred":[
        "Kapasan"
    ],
    "name:new_x_preferred":[
        "\u0915\u092a\u093e\u0938\u0928"
    ],
    "name:por_x_preferred":[
        "Kapasan"
    ],
    "name:und_x_variant":[
        "Kap\u0101san",
        "Kap\u0101sin"
    ],
    "name:vie_x_preferred":[
        "Kapasan"
    ],
    "name:zho_x_preferred":[
        "\u5361\u5e15\u6851"
    ],
    "wof:name":"Kapasan",
    "wof:placetype":"locality"
},
  "geometry": {"coordinates":[74.31667,24.8894],"type":"Point"}
}