{
  "type": "Feature",
  "properties": {
    "gn:admin1_code":"24.0",
    "gn:admin2_code":"126",
    "gn:asciiname":"Kapasan",
    "gn:cc2":"IN",
    "gn:country_code":"IN",
    "gn:dem":449,
    "gn:feature_class":"P",
    "gn:feature_code":"PPL",
    "gn:name":"Kapasan",
    "gn:population":0,
    "gn:timezone":"Asia/Kolkata",
    "iso:country":"IN",
    "name:und_x_variant":[
        "Kap\u0101san",
        "Kap\u0101sin"
    ],
    "wof:name":"Kapasan",
    "wof:placetype":"locality"
},
  "geometry": {"coordinates":[74.31667,24.8894],"type":"Point"}
}