{
  "type": "Feature",
  "properties": {
    "gn:admin1_code":"36",
    "gn:admin2_code":"132.0",
    "gn:asciiname":"Hafizpur",
    "gn:country_code":"IN",
    "gn:dem":280,
    "gn:feature_class":"P",
    "gn:feature_code":"PPL",
    "gn:name":"H\u0101fizpur",
    "gn:population":0,
    "gn:timezone":"Asia/Kolkata",
    "iso:country":"IN",
    "name:bpy_x_preferred":[
        "\u09b9\u09be\u09ab\u09bf\u099c\u09aa\u09c1\u09b0"
    ],
    "name:ita_x_preferred":[
        "Hafizpur"
    ],
    "name:msa_x_preferred":[
        "Hafizpur"
    ],
    "name:new_x_preferred":[
        "\u0939\u092b\u093f\u091c\u092a\u0941\u0930"
    ],
    "name:nld_x_preferred":[
        "Hafizpur"
    ],
    "name:pol_x_preferred":[
        "Hafizpur"
    ],
    "name:por_x_preferred":[
        "Hafizpur"
    ],
    "name:urd_x_preferred":[
        "\u062d\u0627\u0641\u0638 \u067e\u0648\u0631"
    ],
    "name:vie_x_preferred":[
        "Hafizpur"
    ],
    "name:zho_x_preferred":[
        "\u54c8\u83f2\u5179\u666e\u5c14"
    ],
    "wof:name":"Hafizpur",
    "wof:placetype":"locality"
},
  "geometry": {"coordinates":[77.55663,30.00948],"type":"Point"}
}