{
  "type": "Feature",
  "properties": {
    "iso:country":"IN",
    "ks:ks_name":"Ghughrupat",
    "ks:ks_pop":142,
    "ks:ks_type":"HABITATION",
    "name:eng_x_preferred":[
        "Ghughrupat"
    ],
    "wof:name":"Ghughrupat",
    "wof:placetype":"locality",
    "wof:population":142
},
  "geometry": {"coordinates":[84.40633800000001,23.287165],"type":"Point"}
}