{
  "type": "Feature",
  "properties": {
    "iso:country":"IN",
    "ks:ks_name":"Nanpa",
    "ks:ks_pop":833,
    "ks:ks_type":"VILLAGE",
    "name:eng_x_preferred":[
        "Nanpa"
    ],
    "wof:name":"Nanpa",
    "wof:placetype":"locality",
    "wof:population":833
},
  "geometry": {"coordinates":[77.52116100000001,22.645733],"type":"Point"}
}