{
  "type": "Feature",
  "properties": {
    "iso:country":"IN",
    "ks:ks_name":"S. Basti Pure Parmeswar",
    "ks:ks_pop":87,
    "ks:ks_type":"HABITATION",
    "name:eng_x_preferred":[
        "S. Basti Pure Parmeswar"
    ],
    "wof:name":"S. Basti Pure Parmeswar",
    "wof:placetype":"locality",
    "wof:population":87
},
  "geometry": {"coordinates":[81.81200800000001,26.019434],"type":"Point"}
}