{
  "type": "Feature",
  "properties": {
    "gn:admin1_code":"24.0",
    "gn:admin2_code":"113.0",
    "gn:asciiname":"Khuntlia",
    "gn:country_code":"IN",
    "gn:dem":240,
    "gn:feature_class":"P",
    "gn:feature_code":"PPL",
    "gn:name":"Khuntlia",
    "gn:population":0,
    "gn:timezone":"Asia/Kolkata",
    "iso:country":"IN",
    "wof:name":"Khuntlia",
    "wof:placetype":"neighbourhood"
},
  "geometry": {"coordinates":[73.51062,26.09157],"type":"Point"}
}