{
  "type": "Feature",
  "properties": {
    "gn:admin1_code":"39.0",
    "gn:admin2_code":"64.0",
    "gn:asciiname":"Budhena Rajbar",
    "gn:country_code":"IN",
    "gn:dem":1150,
    "gn:feature_class":"P",
    "gn:feature_code":"PPL",
    "gn:name":"Budhena Rajb\u0101r",
    "gn:population":0,
    "gn:timezone":"Asia/Kolkata",
    "iso:country":"IN",
    "wof:name":"Budhena Rajbar",
    "wof:placetype":"locality"
},
  "geometry": {"coordinates":[79.34379,29.72466],"type":"Point"}
}