{
  "type": "Feature",
  "properties": {
    "iso:country":"IN",
    "ks:ks_name":"Baori Khurd",
    "ks:ks_pop":587,
    "ks:ks_type":"HABITATION",
    "name:eng_x_preferred":[
        "Baori Khurd"
    ],
    "wof:name":"Baori Khurd",
    "wof:placetype":"locality",
    "wof:population":587
},
  "geometry": {"coordinates":[71.87007800000001,25.716064],"type":"Point"}
}