{
  "type": "Feature",
  "properties": {
    "iso:country":"IN",
    "ks:ks_name":"Suriaposi",
    "ks:ks_pop":365,
    "ks:ks_type":"VILLAGE",
    "name:eng_x_preferred":[
        "Suriaposi"
    ],
    "wof:name":"Suriaposi",
    "wof:placetype":"locality",
    "wof:population":365
},
  "geometry": {"coordinates":[85.94182600000001,22.632668],"type":"Point"}
}