{
  "type": "Feature",
  "properties": {
    "iso:country":"IN",
    "ks:ks_name":"Chandratoli",
    "ks:ks_pop":35,
    "ks:ks_type":"HABITATION",
    "name:eng_x_preferred":[
        "Chandratoli"
    ],
    "wof:name":"Chandratoli",
    "wof:placetype":"locality",
    "wof:population":35
},
  "geometry": {"coordinates":[85.527748,23.394389],"type":"Point"}
}