{
  "type": "Feature",
  "properties": {
    "iso:country":"IN",
    "ks:ks_name":"Bihajori",
    "ks:ks_pop":77,
    "ks:ks_type":"VILLAGE",
    "name:eng_x_preferred":[
        "Bihajori"
    ],
    "wof:name":"Bihajori",
    "wof:placetype":"locality",
    "wof:population":77
},
  "geometry": {"coordinates":[86.599563,24.106436],"type":"Point"}
}