{
  "type": "Feature",
  "properties": {
    "gn:country":"IN",
    "gn:fcode":"PPL",
    "gn:population":0,
    "iso:country":"IN",
    "name:und_x_variant":[
        "Mo\u0101r"
    ],
    "qs:name":"Mor",
    "qs:name_adm0":"India",
    "qs:name_adm1":"Rajasthan",
    "qs:photos_9r":0,
    "qs:photos_sr":0,
    "qs:placetype":"Town",
    "qs:pop_sr":"0",
    "wof:name":"Mor",
    "wof:placetype":"locality",
    "wof:population":0
},
  "geometry": {"coordinates":[74.88812,23.13232],"type":"Point"}
}