{
  "type": "Feature",
  "properties": {
    "gn:admin1_code":"35",
    "gn:admin2_code":"462.0",
    "gn:asciiname":"Thakurdewa",
    "gn:country_code":"IN",
    "gn:dem":288,
    "gn:feature_class":"P",
    "gn:feature_code":"PPL",
    "gn:name":"Thakurdewa",
    "gn:population":0,
    "gn:timezone":"Asia/Kolkata",
    "iso:country":"IN",
    "wof:name":"Thakurdewa",
    "wof:placetype":"locality"
},
  "geometry": {"coordinates":[81.70116999999998,24.38518],"type":"Point"}
}