{
  "type": "Feature",
  "properties": {
    "iso:country":"IN",
    "ks:ks_name":"Puduvengur",
    "ks:ks_pop":680,
    "ks:ks_type":"HABITATION",
    "name:eng_x_preferred":[
        "Puduvengur"
    ],
    "wof:name":"Puduvengur",
    "wof:placetype":"locality",
    "wof:population":680
},
  "geometry": {"coordinates":[79.184117,11.888677],"type":"Point"}
}