{
  "type": "Feature",
  "properties": {
    "iso:country":"IN",
    "ks:ks_name":"No.4 Sarjan",
    "ks:ks_pop":444,
    "ks:ks_type":"VILLAGE",
    "ks:ks_uagg_main":0,
    "name:eng_x_preferred":[
        "No.4 Sarjan"
    ],
    "wof:name":"No.4 Sarjan",
    "wof:placetype":"neighbourhood",
    "wof:population":444
},
  "geometry": {"coordinates":[93.877776,27.001936],"type":"Point"}
}