{
  "type": "Feature",
  "properties": {
    "iso:country":"IN",
    "ks:ks_alt_nam":"KALI TILLA",
    "ks:ks_name":"Kali Tilla",
    "ks:ks_pop":556,
    "ks:ks_type":"HABITATION",
    "name:eng_x_preferred":[
        "Kali Tilla"
    ],
    "wof:name":"Kali Tilla",
    "wof:placetype":"locality",
    "wof:population":556
},
  "geometry": {"coordinates":[91.327806,23.870917],"type":"Point"}
}