{
  "type": "Feature",
  "properties": {
    "gn:admin1_code":"19.0",
    "gn:admin2_code":"575.0",
    "gn:asciiname":"Shibaje",
    "gn:country_code":"IN",
    "gn:dem":120,
    "gn:feature_class":"P",
    "gn:feature_code":"PPL",
    "gn:name":"Shib\u0101je",
    "gn:population":0,
    "gn:timezone":"Asia/Kolkata",
    "iso:country":"IN",
    "ks:ks_alt_nam":"Shib\u0101je",
    "ks:ks_name":"Shibaje",
    "ks:ks_pop":344,
    "ks:ks_type":"VILLAGE",
    "name:eng_x_preferred":[
        "Shibaje"
    ],
    "name:eng_x_variant":[
        "Shib\u0101je"
    ],
    "wof:name":"Shibaje",
    "wof:placetype":"locality",
    "wof:population":344
},
  "geometry": {"coordinates":[75.50169,12.875491],"type":"Point"}
}