{
  "type": "Feature",
  "properties": {
    "iso:country":"IN",
    "ks:ks_alt_nam":"kalepara",
    "ks:ks_name":"Kalepara",
    "ks:ks_pop":508,
    "ks:ks_type":"HABITATION",
    "name:eng_x_preferred":[
        "Kalepara"
    ],
    "wof:name":"Kalepara",
    "wof:placetype":"locality",
    "wof:population":508
},
  "geometry": {"coordinates":[81.332444,18.7561],"type":"Point"}
}