{
  "type": "Feature",
  "properties": {
    "iso:country":"IN",
    "ks:ks_alt_nam":"gudasai",
    "ks:ks_name":"Gudasai",
    "ks:ks_pop":333,
    "ks:ks_type":"HABITATION",
    "name:eng_x_preferred":[
        "Gudasai"
    ],
    "wof:name":"Gudasai",
    "wof:placetype":"locality",
    "wof:population":333
},
  "geometry": {"coordinates":[85.796898,22.063202],"type":"Point"}
}