{
  "type": "Feature",
  "properties": {
    "gn:admin1_code":"16",
    "gn:admin2_code":"527.0",
    "gn:asciiname":"Pusesavli",
    "gn:country_code":"IN",
    "gn:dem":726,
    "gn:feature_class":"P",
    "gn:feature_code":"PPL",
    "gn:name":"Puses\u0101vli",
    "gn:population":0,
    "gn:timezone":"Asia/Kolkata",
    "iso:country":"IN",
    "wof:name":"Pusesavli",
    "wof:placetype":"neighbourhood"
},
  "geometry": {"coordinates":[74.31802999999999,17.46133],"type":"Point"}
}