{
  "type": "Feature",
  "properties": {
    "iso:country":"IN",
    "ks:ks_name":"Sunsuna",
    "ks:ks_pop":91,
    "ks:ks_type":"VILLAGE",
    "name:eng_x_preferred":[
        "Sunsuna"
    ],
    "wof:name":"Sunsuna",
    "wof:placetype":"locality",
    "wof:population":91
},
  "geometry": {"coordinates":[85.173474,22.353095],"type":"Point"}
}