{
  "type": "Feature",
  "properties": {
    "iso:country":"IN",
    "ks:ks_name":"Peed Lagga Bajgel",
    "ks:ks_pop":44,
    "ks:ks_type":"HABITATION",
    "name:eng_x_preferred":[
        "Peed Lagga Bajgel"
    ],
    "wof:name":"Peed Lagga Bajgel",
    "wof:placetype":"locality",
    "wof:population":44
},
  "geometry": {"coordinates":[80.19405999999999,29.380515],"type":"Point"}
}