{
  "type": "Feature",
  "properties": {
    "gn:admin1_code":"19.0",
    "gn:admin2_code":"581.0",
    "gn:asciiname":"Bettabelachenahalli",
    "gn:country_code":"IN",
    "gn:dem":906,
    "gn:feature_class":"P",
    "gn:feature_code":"PPL",
    "gn:name":"Bettabelachenahalli",
    "gn:population":0,
    "gn:timezone":"Asia/Kolkata",
    "iso:country":"IN",
    "wof:name":"Bettabelachenahalli",
    "wof:placetype":"locality"
},
  "geometry": {"coordinates":[78.05164000000001,13.08842],"type":"Point"}
}