{
  "type": "Feature",
  "properties": {
    "gn:admin1_code":"23.0",
    "gn:admin2_code":"51.0",
    "gn:asciiname":"Bahrampur",
    "gn:country_code":"IN",
    "gn:dem":282,
    "gn:feature_class":"P",
    "gn:feature_code":"PPL",
    "gn:name":"Bahr\u0101mpur",
    "gn:population":0,
    "gn:timezone":"Asia/Kolkata",
    "iso:country":"IN",
    "ks:ks_alt_nam":"Bahr\u0101mpur",
    "ks:ks_name":"Bahrampur",
    "ks:ks_type":"VILLAGE",
    "ks:ks_uagg_main":0,
    "name:eng_x_preferred":[
        "Bahrampur"
    ],
    "name:eng_x_variant":[
        "Bahr\u0101mpur"
    ],
    "wof:name":"Bahrampur",
    "wof:placetype":"neighbourhood"
},
  "geometry": {"coordinates":[76.531139,30.907789],"type":"Point"}
}