{
  "type": "Feature",
  "properties": {
    "gn:admin1_code":"39.0",
    "gn:admin2_code":"64.0",
    "gn:asciiname":"Rawalsera",
    "gn:country_code":"IN",
    "gn:dem":1315,
    "gn:feature_class":"P",
    "gn:feature_code":"PPL",
    "gn:name":"R\u0101walsera",
    "gn:population":0,
    "gn:timezone":"Asia/Kolkata",
    "iso:country":"IN",
    "ks:ks_alt_nam":"R\u0101walsera",
    "ks:ks_name":"Rawalsera",
    "ks:ks_type":"VILLAGE",
    "name:eng_x_preferred":[
        "Rawalsera"
    ],
    "name:eng_x_variant":[
        "R\u0101walsera"
    ],
    "wof:name":"Rawalsera",
    "wof:placetype":"locality"
},
  "geometry": {"coordinates":[79.48025800000001,29.740089],"type":"Point"}
}