{
  "type": "Feature",
  "properties": {
    "gn:admin1_code":"39.0",
    "gn:admin2_code":"64.0",
    "gn:asciiname":"Nainoli",
    "gn:country_code":"IN",
    "gn:dem":1599,
    "gn:feature_class":"P",
    "gn:feature_code":"PPL",
    "gn:name":"Nainoli",
    "gn:population":0,
    "gn:timezone":"Asia/Kolkata",
    "iso:country":"IN",
    "ks:ks_name":"Nainoli",
    "ks:ks_pop":409,
    "ks:ks_type":"VILLAGE",
    "name:eng_x_preferred":[
        "Nainoli"
    ],
    "wof:name":"Nainoli",
    "wof:placetype":"locality",
    "wof:population":409
},
  "geometry": {"coordinates":[79.620977,29.694887],"type":"Point"}
}