{
  "type": "Feature",
  "properties": {
    "gn:admin1_code":"24.0",
    "gn:admin2_code":"130.0",
    "gn:asciiname":"Bichawera",
    "gn:country_code":"IN",
    "gn:dem":524,
    "gn:feature_class":"P",
    "gn:feature_code":"PPL",
    "gn:name":"Bich\u0101wera",
    "gn:population":0,
    "gn:timezone":"Asia/Kolkata",
    "iso:country":"IN",
    "ks:ks_name":"Bichhawera",
    "ks:ks_pop":1075,
    "ks:ks_type":"VILLAGE",
    "ks:ks_uagg_main":0,
    "name:eng_x_preferred":[
        "Bichhawera"
    ],
    "wof:name":"Bichhawera",
    "wof:placetype":"neighbourhood",
    "wof:population":1075
},
  "geometry": {"coordinates":[73.943011,24.569608],"type":"Point"}
}