{
  "type": "Feature",
  "properties": {
    "iso:country":"IN",
    "ks:ks_name":"Khamhar",
    "ks:ks_pop":268,
    "ks:ks_type":"VILLAGE",
    "name:eng_x_preferred":[
        "Khamhar"
    ],
    "wof:name":"Khamhar",
    "wof:placetype":"locality",
    "wof:population":268
},
  "geometry": {"coordinates":[84.68056300000001,23.583411],"type":"Point"}
}