{
  "type": "Feature",
  "properties": {
    "iso:country":"IN",
    "ks:ks_name":"Seetapur",
    "ks:ks_pop":401,
    "ks:ks_type":"VILLAGE",
    "name:eng_x_preferred":[
        "Seetapur"
    ],
    "wof:name":"Seetapur",
    "wof:placetype":"locality",
    "wof:population":401
},
  "geometry": {"coordinates":[83.73568400000001,19.045437],"type":"Point"}
}