{
  "type": "Feature",
  "properties": {
    "iso:country":"IN",
    "ks:ks_name":"Sonkuriha Uttar",
    "ks:ks_pop":400,
    "ks:ks_type":"HABITATION",
    "name:eng_x_preferred":[
        "Sonkuriha Uttar"
    ],
    "wof:name":"Sonkuriha Uttar",
    "wof:placetype":"locality",
    "wof:population":400
},
  "geometry": {"coordinates":[91.53179900000001,26.532596],"type":"Point"}
}