{
  "type": "Feature",
  "properties": {
    "iso:country":"IN",
    "ks:ks_name":"Dumerguda Para",
    "ks:ks_pop":132,
    "ks:ks_type":"HABITATION",
    "name:eng_x_preferred":[
        "Dumerguda Para"
    ],
    "wof:name":"Dumerguda Para",
    "wof:placetype":"locality",
    "wof:population":132
},
  "geometry": {"coordinates":[82.120447,19.401181],"type":"Point"}
}