{
  "type": "Feature",
  "properties": {
    "iso:country":"IN",
    "ks:ks_name":"Rampara",
    "ks:ks_pop":384,
    "ks:ks_type":"HABITATION",
    "name:eng_x_preferred":[
        "Rampara"
    ],
    "wof:name":"Rampara",
    "wof:placetype":"locality",
    "wof:population":384
},
  "geometry": {"coordinates":[69.27080599999999,22.242167],"type":"Point"}
}