{
  "type": "Feature",
  "properties": {
    "gn:admin1_code":"36",
    "gn:admin2_code":"179.0",
    "gn:asciiname":"Purwa Jodhai",
    "gn:country_code":"IN",
    "gn:dem":108,
    "gn:feature_class":"P",
    "gn:feature_code":"PPL",
    "gn:name":"Purwa Jodhai",
    "gn:population":0,
    "gn:timezone":"Asia/Kolkata",
    "iso:country":"IN",
    "ks:ks_name":"Pure Jodhai",
    "ks:ks_pop":236,
    "ks:ks_type":"HABITATION",
    "name:eng_x_preferred":[
        "Pure Jodhai"
    ],
    "name:eng_x_variant":[
        "Purwa Jodhai"
    ],
    "wof:name":"Pure Jodhai",
    "wof:placetype":"locality",
    "wof:population":236
},
  "geometry": {"coordinates":[82.002527,26.444359],"type":"Point"}
}