{
  "type": "Feature",
  "properties": {
    "iso:country":"IN",
    "ks:ks_name":"Sinhwwaheni Mandir",
    "ks:ks_pop":113,
    "ks:ks_type":"HABITATION",
    "name:eng_x_preferred":[
        "Sinhwwaheni Mandir"
    ],
    "wof:name":"Sinhwwaheni Mandir",
    "wof:placetype":"locality",
    "wof:population":113
},
  "geometry": {"coordinates":[80.994088,25.567788],"type":"Point"}
}