{
  "type": "Feature",
  "properties": {
    "iso:country":"IN",
    "ks:ks_name":"1 RJM",
    "ks:ks_pop":100,
    "ks:ks_type":"VILLAGE",
    "name:eng_x_preferred":[
        "1 RJM"
    ],
    "wof:name":"1 RJM",
    "wof:placetype":"locality",
    "wof:population":100
},
  "geometry": {"coordinates":[73.099051,28.812945],"type":"Point"}
}