{
  "type": "Feature",
  "properties": {
    "iso:country":"IN",
    "ks:ks_alt_nam":"NAWATOLA",
    "ks:ks_name":"Nawatola",
    "ks:ks_pop":250,
    "ks:ks_type":"HABITATION",
    "name:eng_x_preferred":[
        "Nawatola"
    ],
    "wof:name":"Nawatola",
    "wof:placetype":"locality",
    "wof:population":250
},
  "geometry": {"coordinates":[82.788628,23.894807],"type":"Point"}
}