{
  "type": "Feature",
  "properties": {
    "iso:country":"IN",
    "ks:ks_name":"Dhekua",
    "ks:ks_pop":15,
    "ks:ks_type":"HABITATION",
    "name:eng_x_preferred":[
        "Dhekua"
    ],
    "wof:name":"Dhekua",
    "wof:placetype":"locality",
    "wof:population":15
},
  "geometry": {"coordinates":[82.314751,24.565618],"type":"Point"}
}