{
  "type": "Feature",
  "properties": {
    "iso:country":"IN",
    "ks:ks_alt_nam":"B\u016bdhpur B\u012bj\u0101pur",
    "ks:ks_name":"Budhpur Bijapur",
    "ks:ks_type":"VILLAGE",
    "ks:ks_uagg_main":0,
    "name:eng_x_preferred":[
        "Budhpur Bijapur"
    ],
    "name:eng_x_variant":[
        "B\u016bdhpur B\u012bj\u0101pur"
    ],
    "wof:name":"Budhpur Bijapur",
    "wof:placetype":"neighbourhood"
},
  "geometry": {"coordinates":[77.13842099999999,28.781412],"type":"Point"}
}