{
  "type": "Feature",
  "properties": {
    "iso:country":"IN",
    "ks:ks_name":"Tadwada",
    "ks:ks_pop":16,
    "ks:ks_type":"HABITATION",
    "name:eng_x_preferred":[
        "Tadwada"
    ],
    "wof:name":"Tadwada",
    "wof:placetype":"locality",
    "wof:population":16
},
  "geometry": {"coordinates":[80.985591,19.54958],"type":"Point"}
}