{
  "type": "Feature",
  "properties": {
    "gn:admin1_code":"02",
    "gn:admin2_code":"542.0",
    "gn:asciiname":"Pedda Palipeta",
    "gn:cc2":"IN",
    "gn:country_code":"IN",
    "gn:dem":3,
    "gn:feature_class":"P",
    "gn:feature_code":"PPL",
    "gn:name":"Pedda P\u0101lipeta",
    "gn:population":0,
    "gn:timezone":"Asia/Kolkata",
    "iso:country":"IN",
    "ks:ks_name":"Pedda Pallipeta",
    "ks:ks_pop":690,
    "ks:ks_type":"HABITATION",
    "ks:ks_uagg_main":0,
    "name:eng_x_preferred":[
        "Pedda Pallipeta"
    ],
    "name:und_x_variant":[
        "Peddapalli",
        "Pedda P\u0101lipeta"
    ],
    "wof:name":"Pedda Pallipeta",
    "wof:placetype":"neighbourhood",
    "wof:population":690
},
  "geometry": {"coordinates":[84.11527700000001,18.341986],"type":"Point"}
}