{
  "type": "Feature",
  "properties": {
    "iso:country":"IN",
    "ks:ks_name":"Kodabereni",
    "ks:ks_pop":1265,
    "ks:ks_type":"HABITATION",
    "name:eng_x_preferred":[
        "Kodabereni"
    ],
    "wof:name":"Kodabereni",
    "wof:placetype":"locality",
    "wof:population":1265
},
  "geometry": {"coordinates":[85.37592600000001,20.274636],"type":"Point"}
}