{
  "type": "Feature",
  "properties": {
    "iso:country":"IN",
    "ks:ks_name":"Malikpur Khiala",
    "ks:ks_pop":2347,
    "ks:ks_type":"VILLAGE",
    "ks:ks_uagg_main":0,
    "name:eng_x_preferred":[
        "Malikpur Khiala"
    ],
    "wof:name":"Malikpur Khiala",
    "wof:placetype":"neighbourhood",
    "wof:population":2347
},
  "geometry": {"coordinates":[75.426726,30.045429],"type":"Point"}
}