{
  "type": "Feature",
  "properties": {
    "iso:country":"IN",
    "ks:ks_name":"Veerhar",
    "ks:ks_pop":522,
    "ks:ks_type":"HABITATION",
    "ks:ks_uagg_main":0,
    "name:eng_x_preferred":[
        "Veerhar"
    ],
    "wof:name":"Veerhar",
    "wof:placetype":"neighbourhood",
    "wof:population":522
},
  "geometry": {"coordinates":[79.795755,26.871732],"type":"Point"}
}