{
  "type": "Feature",
  "properties": {
    "iso:country":"IN",
    "ks:ks_name":"Mudumotalabai",
    "ks:ks_pop":35,
    "ks:ks_type":"HABITATION",
    "name:eng_x_preferred":[
        "Mudumotalabai"
    ],
    "wof:name":"Mudumotalabai",
    "wof:placetype":"locality",
    "wof:population":35
},
  "geometry": {"coordinates":[78.98417999999999,17.456533],"type":"Point"}
}