{
  "type": "Feature",
  "properties": {
    "iso:country":"IN",
    "ks:ks_name":"Chandipur",
    "ks:ks_pop":1066,
    "ks:ks_type":"VILLAGE",
    "ks:ks_uagg_main":0,
    "name:eng_x_preferred":[
        "Chandipur"
    ],
    "wof:name":"Chandipur",
    "wof:placetype":"neighbourhood",
    "wof:population":1066
},
  "geometry": {"coordinates":[87.55096500000001,22.313473],"type":"Point"}
}