{
  "type": "Feature",
  "properties": {
    "iso:country":"IN",
    "ks:ks_name":"Sakletong",
    "ks:ks_pop":267,
    "ks:ks_type":"HABITATION",
    "name:eng_x_preferred":[
        "Sakletong"
    ],
    "wof:name":"Sakletong",
    "wof:placetype":"locality",
    "wof:population":267
},
  "geometry": {"coordinates":[81.11277699999999,18.152473],"type":"Point"}
}