{
  "type": "Feature",
  "properties": {
    "gn:admin1_code":"2.0",
    "gn:admin2_code":"544.0",
    "gn:asciiname":"Gabbangi",
    "gn:country_code":"IN",
    "gn:dem":947,
    "gn:feature_class":"P",
    "gn:feature_code":"PPL",
    "gn:name":"Gabbangi",
    "gn:population":0,
    "gn:timezone":"Asia/Kolkata",
    "iso:country":"IN",
    "wof:name":"Gabbangi",
    "wof:placetype":"locality"
},
  "geometry": {"coordinates":[82.65680999999999,18.11798],"type":"Point"}
}