{
  "type": "Feature",
  "properties": {
    "iso:country":"IN",
    "ks:ks_alt_nam":"DINA BANDHU PARA",
    "ks:ks_name":"Dina Bandhu Para",
    "ks:ks_pop":99,
    "ks:ks_type":"HABITATION",
    "ks:ks_uagg_main":0,
    "name:eng_x_preferred":[
        "Dina Bandhu Para"
    ],
    "wof:name":"Dina Bandhu Para",
    "wof:placetype":"neighbourhood",
    "wof:population":99
},
  "geometry": {"coordinates":[91.41585499999999,23.912853],"type":"Point"}
}