{
  "type": "Feature",
  "properties": {
    "iso:country":"IN",
    "ks:ks_name":"Lalchanddih",
    "ks:ks_pop":856,
    "ks:ks_type":"VILLAGE",
    "name:eng_x_preferred":[
        "Lalchanddih"
    ],
    "wof:name":"Lalchanddih",
    "wof:placetype":"locality",
    "wof:population":856
},
  "geometry": {"coordinates":[86.565712,24.088798],"type":"Point"}
}