{
  "type": "Feature",
  "properties": {
    "iso:country":"IN",
    "ks:ks_name":"Valiyamavu Jn",
    "ks:ks_pop":440,
    "ks:ks_type":"HABITATION",
    "name:eng_x_preferred":[
        "Valiyamavu Jn"
    ],
    "wof:name":"Valiyamavu Jn",
    "wof:placetype":"locality",
    "wof:population":440
},
  "geometry": {"coordinates":[76.893508,9.818881],"type":"Point"}
}