{
  "type": "Feature",
  "properties": {
    "gn:admin1_code":"2.0",
    "gn:admin2_code":"551",
    "gn:asciiname":"Khajipeta",
    "gn:country_code":"IN",
    "gn:dem":142,
    "gn:feature_class":"P",
    "gn:feature_code":"PPL",
    "gn:name":"Kh\u0101jipeta",
    "gn:population":0,
    "gn:timezone":"Asia/Kolkata",
    "iso:country":"IN",
    "wof:name":"Khajipeta",
    "wof:placetype":"locality"
},
  "geometry": {"coordinates":[78.77020999999998,14.65091],"type":"Point"}
}