{
  "type": "Feature",
  "properties": {
    "iso:country":"IN",
    "ks:ks_name":"Kuchagao",
    "ks:ks_pop":49,
    "ks:ks_type":"HABITATION",
    "name:eng_x_preferred":[
        "Kuchagao"
    ],
    "wof:name":"Kuchagao",
    "wof:placetype":"locality",
    "wof:population":49
},
  "geometry": {"coordinates":[74.751492,14.971882],"type":"Point"}
}