{
  "type": "Feature",
  "properties": {
    "iso:country":"IN",
    "ks:ks_name":"Laptain Purwa",
    "ks:ks_pop":122,
    "ks:ks_type":"HABITATION",
    "name:eng_x_preferred":[
        "Laptain Purwa"
    ],
    "wof:name":"Laptain Purwa",
    "wof:placetype":"locality",
    "wof:population":122
},
  "geometry": {"coordinates":[82.221153,27.437635],"type":"Point"}
}