{
  "type": "Feature",
  "properties": {
    "iso:country":"IN",
    "ks:ks_name":"Bibihawa",
    "ks:ks_pop":564,
    "ks:ks_type":"HABITATION",
    "name:eng_x_preferred":[
        "Bibihawa"
    ],
    "wof:name":"Bibihawa",
    "wof:placetype":"locality",
    "wof:population":564
},
  "geometry": {"coordinates":[83.215844,27.380796],"type":"Point"}
}