{
  "type": "Feature",
  "properties": {
    "iso:country":"IN",
    "ks:ks_alt_nam":"RABBUR BAGAN PARA",
    "ks:ks_name":"Rabbur Bagan Para",
    "ks:ks_pop":459,
    "ks:ks_type":"HABITATION",
    "name:eng_x_preferred":[
        "Rabbur Bagan Para"
    ],
    "wof:name":"Rabbur Bagan Para",
    "wof:placetype":"locality",
    "wof:population":459
},
  "geometry": {"coordinates":[91.694783,23.965701],"type":"Point"}
}