{
  "type": "Feature",
  "properties": {
    "iso:country":"IN",
    "ks:ks_name":"Kadam Chandra",
    "ks:ks_pop":188,
    "ks:ks_type":"HABITATION",
    "name:eng_x_preferred":[
        "Kadam Chandra"
    ],
    "wof:name":"Kadam Chandra",
    "wof:placetype":"locality",
    "wof:population":188
},
  "geometry": {"coordinates":[91.681203,23.72677],"type":"Point"}
}