{
  "type": "Feature",
  "properties": {
    "iso:country":"IN",
    "ks:ks_name":"Budhawadi",
    "ks:ks_pop":100,
    "ks:ks_type":"HABITATION",
    "ks:ks_uagg_main":0,
    "name:eng_x_preferred":[
        "Budhawadi"
    ],
    "wof:name":"Budhawadi",
    "wof:placetype":"neighbourhood",
    "wof:population":100
},
  "geometry": {"coordinates":[73.490319,17.630053],"type":"Point"}
}