{
  "type": "Feature",
  "properties": {
    "iso:country":"IN",
    "ks:ks_name":"Mondal Para",
    "ks:ks_pop":1200,
    "ks:ks_type":"HABITATION",
    "name:eng_x_preferred":[
        "Mondal Para"
    ],
    "wof:name":"Mondal Para",
    "wof:placetype":"locality",
    "wof:population":1200
},
  "geometry": {"coordinates":[88.492633,22.263117],"type":"Point"}
}