{
  "type": "Feature",
  "properties": {
    "iso:country":"IN",
    "ks:ks_name":"Ghoda Falia",
    "ks:ks_pop":404,
    "ks:ks_type":"HABITATION",
    "name:eng_x_preferred":[
        "Ghoda Falia"
    ],
    "wof:name":"Ghoda Falia",
    "wof:placetype":"locality",
    "wof:population":404
},
  "geometry": {"coordinates":[73.447076,22.709271],"type":"Point"}
}