{
  "type": "Feature",
  "properties": {
    "iso:country":"IN",
    "ks:ks_name":"Konulampallam",
    "ks:ks_pop":755,
    "ks:ks_type":"HABITATION",
    "name:eng_x_preferred":[
        "Konulampallam"
    ],
    "wof:name":"Konulampallam",
    "wof:placetype":"locality",
    "wof:population":755
},
  "geometry": {"coordinates":[79.497315,11.150506],"type":"Point"}
}