{
  "type": "Feature",
  "properties": {
    "iso:country":"IN",
    "ks:ks_name":"Rangadih",
    "ks:ks_pop":875,
    "ks:ks_type":"VILLAGE",
    "ks:ks_uagg_main":0,
    "name:eng_x_preferred":[
        "Rangadih"
    ],
    "wof:name":"Rangadih",
    "wof:placetype":"locality",
    "wof:population":875
},
  "geometry": {"coordinates":[86.267792,23.845329],"type":"Point"}
}