{
  "type": "Feature",
  "properties": {
    "iso:country":"IN",
    "ks:ks_name":"Melmury",
    "ks:ks_pop":3100,
    "ks:ks_type":"HABITATION",
    "name:eng_x_preferred":[
        "Melmury"
    ],
    "wof:name":"Melmury",
    "wof:placetype":"locality",
    "wof:population":3100
},
  "geometry": {"coordinates":[76.12085399999999,10.934347],"type":"Point"}
}