{
  "type": "Feature",
  "properties": {
    "gn:admin1_code":"34.0",
    "gn:admin2_code":"222.0",
    "gn:asciiname":"Jaimangalpur",
    "gn:country_code":"IN",
    "gn:dem":40,
    "gn:feature_class":"P",
    "gn:feature_code":"PPL",
    "gn:name":"Jaimangalpur",
    "gn:population":0,
    "gn:timezone":"Asia/Kolkata",
    "iso:country":"IN",
    "name:mai_x_preferred":[
        "\u091c\u0948\u092e\u0919\u094d\u0917\u0932\u093e\u092a\u0941\u0930"
    ],
    "wof:name":"Jaimangalpur",
    "wof:placetype":"locality"
},
  "geometry": {"coordinates":[86.16171999999997,25.58627000000001],"type":"Point"}
}