{
  "type": "Feature",
  "properties": {
    "iso:country":"IN",
    "ks:ks_name":"Phainti Gunth",
    "ks:ks_pop":39,
    "ks:ks_type":"HABITATION",
    "name:eng_x_preferred":[
        "Phainti Gunth"
    ],
    "wof:name":"Phainti Gunth",
    "wof:placetype":"locality",
    "wof:population":39
},
  "geometry": {"coordinates":[79.636381,30.040968],"type":"Point"}
}