{
  "type": "Feature",
  "properties": {
    "gn:admin1_code":"36",
    "gn:admin2_code":"185.0",
    "gn:asciiname":"Sirpalpur Hata Jangal",
    "gn:country_code":"IN",
    "gn:dem":93,
    "gn:feature_class":"P",
    "gn:feature_code":"PPL",
    "gn:name":"Sirp\u0101lpur H\u0101ta Jangal",
    "gn:population":0,
    "gn:timezone":"Asia/Kolkata",
    "iso:country":"IN",
    "wof:name":"Sirpalpur Hata Jangal",
    "wof:placetype":"locality"
},
  "geometry": {"coordinates":[82.7187,26.84429],"type":"Point"}
}