{
  "type": "Feature",
  "properties": {
    "iso:country":"IN",
    "ks:ks_alt_nam":"B.Ambala",
    "ks:ks_name":"B.ambala",
    "ks:ks_pop":22,
    "ks:ks_type":"HABITATION",
    "name:eng_x_preferred":[
        "B.ambala"
    ],
    "wof:name":"B.ambala",
    "wof:placetype":"locality",
    "wof:population":22
},
  "geometry": {"coordinates":[75.996111,12.112222],"type":"Point"}
}