{
  "type": "Feature",
  "properties": {
    "gn:admin1_code":"5",
    "gn:asciiname":"Sangariwala",
    "gn:country_code":"IN",
    "gn:dem":366,
    "gn:feature_class":"P",
    "gn:feature_code":"PPL",
    "gn:name":"Sang\u0101riw\u0101la",
    "gn:population":0,
    "gn:timezone":"Asia/Kolkata",
    "iso:country":"IN",
    "ks:ks_name":"Shingariwala",
    "ks:ks_pop":623,
    "ks:ks_type":"VILLAGE",
    "name:eng_x_preferred":[
        "Shingariwala"
    ],
    "name:eng_x_variant":[
        "Sangariwala"
    ],
    "wof:name":"Shingariwala",
    "wof:placetype":"locality",
    "wof:population":623
},
  "geometry": {"coordinates":[76.759477,30.792158],"type":"Point"}
}