{
  "type": "Feature",
  "properties": {
    "iso:country":"IN",
    "ks:ks_name":"Gori Topara",
    "ks:ks_pop":45,
    "ks:ks_type":"HABITATION",
    "name:eng_x_preferred":[
        "Gori Topara"
    ],
    "wof:name":"Gori Topara",
    "wof:placetype":"locality",
    "wof:population":45
},
  "geometry": {"coordinates":[71.519442,21.304711],"type":"Point"}
}