{
  "type": "Feature",
  "properties": {
    "iso:country":"IN",
    "ks:ks_name":"Gurna",
    "ks:ks_pop":74,
    "ks:ks_type":"VILLAGE",
    "name:eng_x_preferred":[
        "Gurna"
    ],
    "wof:name":"Gurna",
    "wof:placetype":"locality",
    "wof:population":74
},
  "geometry": {"coordinates":[80.159688,29.270313],"type":"Point"}
}