{
  "type": "Feature",
  "properties": {
    "iso:country":"IN",
    "ks:ks_name":"Mangalam",
    "ks:ks_type":"VILLAGE",
    "ks:ks_uagg_main":0,
    "name:eng_x_preferred":[
        "Mangalam"
    ],
    "wof:name":"Mangalam",
    "wof:placetype":"neighbourhood"
},
  "geometry": {"coordinates":[79.735297,11.893294],"type":"Point"}
}