{
  "type": "Feature",
  "properties": {
    "iso:country":"IN",
    "ks:ks_alt_nam":"Aduppil tribal colony",
    "ks:ks_name":"Aduppil Tribal Colony",
    "ks:ks_pop":694,
    "ks:ks_type":"HABITATION",
    "name:eng_x_preferred":[
        "Aduppil Tribal Colony"
    ],
    "wof:name":"Aduppil Tribal Colony",
    "wof:placetype":"locality",
    "wof:population":694
},
  "geometry": {"coordinates":[75.75034100000001,11.77001],"type":"Point"}
}