{
  "type": "Feature",
  "properties": {
    "gn:admin1_code":"35",
    "gn:admin2_code":"456.0",
    "gn:asciiname":"Dalal",
    "gn:country_code":"IN",
    "gn:dem":587,
    "gn:feature_class":"P",
    "gn:feature_code":"PPL",
    "gn:name":"Dal\u0101l",
    "gn:population":0,
    "gn:timezone":"Asia/Kolkata",
    "iso:country":"IN",
    "name:ara_x_preferred":[
        "\u062f\u0644\u0627\u0644"
    ],
    "name:deu_x_preferred":[
        "Dalal"
    ],
    "wof:name":"Dalal",
    "wof:placetype":"locality"
},
  "geometry": {"coordinates":[79.64825999999999,21.96364],"type":"Point"}
}