{
  "type": "Feature",
  "properties": {
    "gn:admin1_code":"35",
    "gn:admin2_code":"456.0",
    "gn:asciiname":"Dalal",
    "gn:country_code":"IN",
    "gn:dem":587,
    "gn:feature_class":"P",
    "gn:feature_code":"PPL",
    "gn:name":"Dal\u0101l",
    "gn:population":0,
    "gn:timezone":"Asia/Kolkata",
    "iso:country":"IN",
    "ks:ks_alt_nam":"Dal\u0101l",
    "ks:ks_name":"Dalal",
    "ks:ks_pop":519,
    "ks:ks_type":"VILLAGE",
    "name:ara_x_preferred":[
        "\u062f\u0644\u0627\u0644"
    ],
    "name:deu_x_preferred":[
        "Dalal"
    ],
    "name:eng_x_preferred":[
        "Dalal"
    ],
    "name:eng_x_variant":[
        "Dal\u0101l"
    ],
    "wof:name":"Dalal",
    "wof:placetype":"locality",
    "wof:population":519
},
  "geometry": {"coordinates":[79.646755,21.963678],"type":"Point"}
}