{
  "type": "Feature",
  "properties": {
    "gn:admin1_code":"19.0",
    "gn:admin2_code":"582.0",
    "gn:asciiname":"Teligruahalli",
    "gn:country_code":"IN",
    "gn:dem":858,
    "gn:feature_class":"P",
    "gn:feature_code":"PPL",
    "gn:name":"Teligruahalli",
    "gn:population":0,
    "gn:timezone":"Asia/Kolkata",
    "iso:country":"IN",
    "wof:name":"Teligruahalli",
    "wof:placetype":"locality"
},
  "geometry": {"coordinates":[77.81558000000003,13.54504],"type":"Point"}
}