{
  "type": "Feature",
  "properties": {
    "iso:country":"IN",
    "ks:ks_name":"Bijirubailu",
    "ks:ks_pop":15,
    "ks:ks_type":"HABITATION",
    "name:eng_x_preferred":[
        "Bijirubailu"
    ],
    "wof:name":"Bijirubailu",
    "wof:placetype":"locality",
    "wof:population":15
},
  "geometry": {"coordinates":[75.44898999999999,12.795778],"type":"Point"}
}