{
  "type": "Feature",
  "properties": {
    "iso:country":"IN",
    "ks:ks_alt_nam":"DIPASAI",
    "ks:ks_name":"Dipasai",
    "ks:ks_pop":558,
    "ks:ks_type":"HABITATION",
    "name:eng_x_preferred":[
        "Dipasai"
    ],
    "wof:name":"Dipasai",
    "wof:placetype":"locality",
    "wof:population":558
},
  "geometry": {"coordinates":[85.811239,22.418876],"type":"Point"}
}