{
  "type": "Feature",
  "properties": {
    "iso:country":"IN",
    "ks:ks_name":"Imadpur",
    "ks:ks_pop":82,
    "ks:ks_type":"VILLAGE",
    "ks:ks_uagg_main":0,
    "name:eng_x_preferred":[
        "Imadpur"
    ],
    "wof:name":"Imadpur",
    "wof:placetype":"neighbourhood",
    "wof:population":82
},
  "geometry": {"coordinates":[88.18178399999999,25.729839],"type":"Point"}
}