{
  "type": "Feature",
  "properties": {
    "iso:country":"IN",
    "ks:ks_name":"Sulif",
    "ks:ks_pop":621,
    "ks:ks_type":"VILLAGE",
    "ks:ks_uagg_main":0,
    "name:eng_x_preferred":[
        "Sulif"
    ],
    "wof:name":"Sulif",
    "wof:placetype":"neighbourhood",
    "wof:population":621
},
  "geometry": {"coordinates":[88.015382,25.697398],"type":"Point"}
}