{
  "type": "Feature",
  "properties": {
    "gn:admin1_code":"36",
    "gn:admin2_code":"179.0",
    "gn:asciiname":"Baldeo",
    "gn:country_code":"IN",
    "gn:dem":108,
    "gn:feature_class":"P",
    "gn:feature_code":"PPL",
    "gn:name":"Baldeo",
    "gn:population":0,
    "gn:timezone":"Asia/Kolkata",
    "iso:country":"IN",
    "name:bpy_x_preferred":[
        "\u09ac\u09be\u09b2\u09a6\u09c7\u0993"
    ],
    "name:ceb_x_preferred":[
        "Baldev"
    ],
    "name:hin_x_preferred":[
        "\u092c\u0932\u094d\u0926\u0947\u0935"
    ],
    "name:ita_x_preferred":[
        "Baldeo"
    ],
    "name:mlg_x_preferred":[
        "Baldeo"
    ],
    "name:msa_x_preferred":[
        "Baldeo"
    ],
    "name:new_x_preferred":[
        "\u092c\u0932\u0926\u0947\u0935"
    ],
    "name:nld_x_preferred":[
        "Baldeo"
    ],
    "name:pol_x_preferred":[
        "Baldeo"
    ],
    "name:por_x_preferred":[
        "Baldeo"
    ],
    "name:rus_x_preferred":[
        "\u0411\u0430\u043b\u0434\u0435\u043e"
    ],
    "name:swe_x_preferred":[
        "Baldev"
    ],
    "name:urd_x_preferred":[
        "\u0628\u0627\u0644 \u062f\u06cc\u0648"
    ],
    "name:vie_x_preferred":[
        "Baldeo"
    ],
    "name:zho_x_preferred":[
        "\u5df4\u5c14\u5fb7\u5965"
    ],
    "wof:name":"Baldeo",
    "wof:placetype":"neighbourhood"
},
  "geometry": {"coordinates":[81.70986000000001,26.30237],"type":"Point"}
}