{
  "type": "Feature",
  "properties": {
    "iso:country":"IN",
    "ks:ks_name":"Deana Forest",
    "ks:ks_pop":50,
    "ks:ks_type":"VILLAGE",
    "name:eng_x_preferred":[
        "Deana Forest"
    ],
    "wof:name":"Deana Forest",
    "wof:placetype":"locality",
    "wof:population":50
},
  "geometry": {"coordinates":[88.959022,26.854652],"type":"Point"}
}