{
  "type": "Feature",
  "properties": {
    "iso:country":"IN",
    "ks:ks_name":"Veiyapurikottam",
    "ks:ks_pop":303,
    "ks:ks_type":"HABITATION",
    "name:eng_x_preferred":[
        "Veiyapurikottam"
    ],
    "wof:name":"Veiyapurikottam",
    "wof:placetype":"locality",
    "wof:population":303
},
  "geometry": {"coordinates":[78.62391700000001,10.976759],"type":"Point"}
}