{
  "type": "Feature",
  "properties": {
    "iso:country":"IN",
    "ks:ks_name":"Tola Panchkathia",
    "ks:ks_pop":540,
    "ks:ks_type":"VILLAGE",
    "name:eng_x_preferred":[
        "Tola Panchkathia"
    ],
    "wof:name":"Tola Panchkathia",
    "wof:placetype":"locality",
    "wof:population":540
},
  "geometry": {"coordinates":[86.802706,24.686287],"type":"Point"}
}