{
  "type": "Feature",
  "properties": {
    "gn:admin1_code":"38",
    "gn:admin2_code":"354.0",
    "gn:asciiname":"Lohpiti",
    "gn:country_code":"IN",
    "gn:dem":213,
    "gn:feature_class":"P",
    "gn:feature_code":"PPL",
    "gn:name":"Lohpiti",
    "gn:population":0,
    "gn:timezone":"Asia/Kolkata",
    "iso:country":"IN",
    "wof:name":"Lohpiti",
    "wof:placetype":"locality"
},
  "geometry": {"coordinates":[86.19718,23.73729],"type":"Point"}
}