{
  "type": "Feature",
  "properties": {
    "gn:admin1_code":"39",
    "gn:admin2_code":"58.0",
    "gn:asciiname":"Painj",
    "gn:country_code":"IN",
    "gn:dem":2353,
    "gn:feature_class":"P",
    "gn:feature_code":"PPL",
    "gn:name":"Painj",
    "gn:population":0,
    "gn:timezone":"Asia/Kolkata",
    "iso:country":"IN",
    "wof:name":"Painj",
    "wof:placetype":"locality"
},
  "geometry": {"coordinates":[79.18709,30.50363],"type":"Point"}
}