{
  "type": "Feature",
  "properties": {
    "iso:country":"IN",
    "ks:ks_name":"Veloorkettu Manal",
    "ks:ks_pop":382,
    "ks:ks_type":"HABITATION",
    "name:eng_x_preferred":[
        "Veloorkettu Manal"
    ],
    "wof:name":"Veloorkettu Manal",
    "wof:placetype":"locality",
    "wof:population":382
},
  "geometry": {"coordinates":[76.39143900000001,10.751821],"type":"Point"}
}