{
  "type": "Feature",
  "properties": {
    "iso:country":"IN",
    "ks:ks_alt_nam":"13 MLD-B",
    "ks:ks_name":"13 Mld-b",
    "ks:ks_pop":25,
    "ks:ks_type":"HABITATION",
    "name:eng_x_preferred":[
        "13 Mld-b"
    ],
    "wof:name":"13 Mld-b",
    "wof:placetype":"locality",
    "wof:population":25
},
  "geometry": {"coordinates":[72.96000600000001,28.912647],"type":"Point"}
}