{
  "type": "Feature",
  "properties": {
    "gn:admin1_code":"16",
    "gn:admin2_code":"505.0",
    "gn:asciiname":"Sarandi",
    "gn:country_code":"IN",
    "gn:dem":277,
    "gn:feature_class":"P",
    "gn:feature_code":"PPL",
    "gn:name":"Sar\u0101ndi",
    "gn:population":0,
    "gn:timezone":"Asia/Kolkata",
    "iso:country":"IN",
    "name:ceb_x_preferred":[
        "Sarandi"
    ],
    "name:fra_x_preferred":[
        "Sarandi"
    ],
    "name:ita_x_preferred":[
        "Sarandi"
    ],
    "name:mlg_x_preferred":[
        "Sarandi"
    ],
    "name:nld_x_preferred":[
        "Sarandi"
    ],
    "name:nor_x_preferred":[
        "Sarandi"
    ],
    "name:por_x_preferred":[
        "Sarandi"
    ],
    "name:rus_x_preferred":[
        "\u0421\u0430\u0440\u0430\u043d\u0434\u0438"
    ],
    "name:sco_x_preferred":[
        "Sarandi"
    ],
    "name:spa_x_preferred":[
        "Sarandi"
    ],
    "name:swe_x_preferred":[
        "Sarandi"
    ],
    "name:vie_x_preferred":[
        "Sarandi"
    ],
    "name:vol_x_preferred":[
        "Sarandi"
    ],
    "wof:name":"Sarandi",
    "wof:placetype":"locality"
},
  "geometry": {"coordinates":[79.38558,20.77232],"type":"Point"}
}