{
  "type": "Feature",
  "properties": {
    "iso:country":"IN",
    "ks:ks_name":"Barakatha",
    "ks:ks_pop":543,
    "ks:ks_type":"HABITATION",
    "name:eng_x_preferred":[
        "Barakatha"
    ],
    "wof:name":"Barakatha",
    "wof:placetype":"locality",
    "wof:population":543
},
  "geometry": {"coordinates":[89.518553,26.399336],"type":"Point"}
}