{
  "type": "Feature",
  "properties": {
    "iso:country":"IN",
    "ks:ks_alt_nam":"SONYAL WASTI",
    "ks:ks_name":"Sonyal Wasti",
    "ks:ks_pop":117,
    "ks:ks_type":"HABITATION",
    "name:eng_x_preferred":[
        "Sonyal Wasti"
    ],
    "wof:name":"Sonyal Wasti",
    "wof:placetype":"locality",
    "wof:population":117
},
  "geometry": {"coordinates":[75.502015,17.086599],"type":"Point"}
}