{
  "type": "Feature",
  "properties": {
    "gn:admin1_code":"16",
    "gn:admin2_code":"503.0",
    "gn:asciiname":"Mogarda",
    "gn:country_code":"IN",
    "gn:dem":359,
    "gn:feature_class":"P",
    "gn:feature_code":"PPL",
    "gn:name":"Mogarda",
    "gn:population":0,
    "gn:timezone":"Asia/Kolkata",
    "iso:country":"IN",
    "wof:name":"Mogarda",
    "wof:placetype":"locality"
},
  "geometry": {"coordinates":[76.92559,21.4439],"type":"Point"}
}