{
  "type": "Feature",
  "properties": {
    "iso:country":"IN",
    "ks:ks_alt_nam":"P\u0101li",
    "ks:ks_name":"Pali",
    "ks:ks_pop":308,
    "ks:ks_type":"VILLAGE",
    "name:eng_x_preferred":[
        "Pali"
    ],
    "name:eng_x_variant":[
        "P\u0101li"
    ],
    "wof:name":"Pali",
    "wof:placetype":"locality",
    "wof:population":308
},
  "geometry": {"coordinates":[82.40406400000001,22.972273],"type":"Point"}
}