{
  "type": "Feature",
  "properties": {
    "gn:admin1_code":"2",
    "gn:admin2_code":"544.0",
    "gn:asciiname":"Pujariguda",
    "gn:country_code":"IN",
    "gn:dem":1019,
    "gn:feature_class":"P",
    "gn:feature_code":"PPL",
    "gn:name":"Pujarig\u016bda",
    "gn:population":0,
    "gn:timezone":"Asia/Kolkata",
    "iso:country":"IN",
    "wof:name":"Pujariguda",
    "wof:placetype":"locality"
},
  "geometry": {"coordinates":[82.95591,18.29282000000001],"type":"Point"}
}