{
  "type": "Feature",
  "properties": {
    "iso:country":"IN",
    "ks:ks_name":"Semrahiya Tola",
    "ks:ks_pop":50,
    "ks:ks_type":"HABITATION",
    "name:eng_x_preferred":[
        "Semrahiya Tola"
    ],
    "wof:name":"Semrahiya Tola",
    "wof:placetype":"locality",
    "wof:population":50
},
  "geometry": {"coordinates":[83.25896899999999,26.576929],"type":"Point"}
}