{
  "type": "Feature",
  "properties": {
    "iso:country":"IN",
    "ks:ks_name":"Jala Bishwanathpur",
    "ks:ks_pop":7292,
    "ks:ks_type":"VILLAGE",
    "ks:ks_uagg_main":0,
    "name:eng_x_preferred":[
        "Jala Bishwanathpur"
    ],
    "wof:name":"Jala Bishwanathpur",
    "wof:placetype":"locality",
    "wof:population":7292
},
  "geometry": {"coordinates":[88.109058,22.556341],"type":"Point"}
}