{
  "type": "Feature",
  "properties": {
    "iso:country":"IN",
    "ks:ks_name":"Masrundipada",
    "ks:ks_pop":100,
    "ks:ks_type":"HABITATION",
    "name:eng_x_preferred":[
        "Masrundipada"
    ],
    "wof:name":"Masrundipada",
    "wof:placetype":"locality",
    "wof:population":100
},
  "geometry": {"coordinates":[73.28965700000001,19.251198],"type":"Point"}
}