{
  "type": "Feature",
  "properties": {
    "iso:country":"IN",
    "ks:ks_alt_nam":"kalubar",
    "ks:ks_name":"Kalubar",
    "ks:ks_pop":287,
    "ks:ks_type":"HABITATION",
    "name:eng_x_preferred":[
        "Kalubar"
    ],
    "wof:name":"Kalubar",
    "wof:placetype":"locality",
    "wof:population":287
},
  "geometry": {"coordinates":[74.613541,13.9973],"type":"Point"}
}