{
  "type": "Feature",
  "properties": {
    "iso:country":"IN",
    "ks:ks_name":"Bendopani",
    "ks:ks_pop":132,
    "ks:ks_type":"HABITATION",
    "name:eng_x_preferred":[
        "Bendopani"
    ],
    "wof:name":"Bendopani",
    "wof:placetype":"locality",
    "wof:population":132
},
  "geometry": {"coordinates":[83.306156,22.657145],"type":"Point"}
}