{
  "type": "Feature",
  "properties": {
    "iso:country":"IN",
    "ks:ks_alt_nam":"Fakir tola",
    "ks:ks_name":"Fakir Tola",
    "ks:ks_pop":501,
    "ks:ks_type":"HABITATION",
    "name:eng_x_preferred":[
        "Fakir Tola"
    ],
    "wof:name":"Fakir Tola",
    "wof:placetype":"locality",
    "wof:population":501
},
  "geometry": {"coordinates":[87.89144400000001,26.142748],"type":"Point"}
}