{
  "type": "Feature",
  "properties": {
    "iso:country":"IN",
    "ks:ks_name":"Phucho",
    "ks:ks_pop":702,
    "ks:ks_type":"VILLAGE",
    "ks:ks_uagg_main":0,
    "name:eng_x_preferred":[
        "Phucho"
    ],
    "wof:name":"Phucho",
    "wof:placetype":"neighbourhood",
    "wof:population":702
},
  "geometry": {"coordinates":[86.43131099999999,24.263141],"type":"Point"}
}