{
  "type": "Feature",
  "properties": {
    "iso:country":"IN",
    "ks:ks_name":"Mijrpalla",
    "ks:ks_pop":1308,
    "ks:ks_type":"HABITATION",
    "ks:ks_uagg_main":0,
    "name:eng_x_preferred":[
        "Mijrpalla"
    ],
    "wof:name":"Mijrpalla",
    "wof:placetype":"neighbourhood",
    "wof:population":1308
},
  "geometry": {"coordinates":[74.94699799999999,12.754917],"type":"Point"}
}