{
  "type": "Feature",
  "properties": {
    "iso:country":"IN",
    "ks:ks_alt_nam":"PALASHIPARA BAZAR",
    "ks:ks_name":"Palashipara Bazar",
    "ks:ks_pop":4421,
    "ks:ks_type":"HABITATION",
    "ks:ks_uagg_main":0,
    "name:eng_x_preferred":[
        "Palashipara Bazar"
    ],
    "wof:name":"Palashipara Bazar",
    "wof:placetype":"neighbourhood",
    "wof:population":4421
},
  "geometry": {"coordinates":[88.43823,23.791496],"type":"Point"}
}