{
  "type": "Feature",
  "properties": {
    "iso:country":"IN",
    "ks:ks_alt_nam":"Mhase pada",
    "ks:ks_name":"Mhase Pada",
    "ks:ks_pop":127,
    "ks:ks_type":"HABITATION",
    "name:eng_x_preferred":[
        "Mhase Pada"
    ],
    "wof:name":"Mhase Pada",
    "wof:placetype":"locality",
    "wof:population":127
},
  "geometry": {"coordinates":[73.16855,19.74637],"type":"Point"}
}