{
  "type": "Feature",
  "properties": {
    "iso:country":"IN",
    "ks:ks_name":"Chowdireddipalle",
    "ks:ks_pop":0,
    "ks:ks_type":"VILLAGE",
    "name:eng_x_preferred":[
        "Chowdireddipalle"
    ],
    "wof:name":"Chowdireddipalle",
    "wof:placetype":"locality",
    "wof:population":0
},
  "geometry": {"coordinates":[77.787873,13.866293],"type":"Point"}
}