{
  "type": "Feature",
  "properties": {
    "iso:country":"IN",
    "ks:ks_alt_nam":"MUSLIM CHOWK",
    "ks:ks_name":"Muslim Chowk",
    "ks:ks_pop":646,
    "ks:ks_type":"HABITATION",
    "name:eng_x_preferred":[
        "Muslim Chowk"
    ],
    "wof:name":"Muslim Chowk",
    "wof:placetype":"locality",
    "wof:population":646
},
  "geometry": {"coordinates":[85.363975,24.089296],"type":"Point"}
}