{
  "type": "Feature",
  "properties": {
    "iso:country":"IN",
    "ks:ks_alt_nam":"KEWTAN",
    "ks:ks_name":"Kewtan",
    "ks:ks_pop":665,
    "ks:ks_type":"HABITATION",
    "name:eng_x_preferred":[
        "Kewtan"
    ],
    "wof:name":"Kewtan",
    "wof:placetype":"locality",
    "wof:population":665
},
  "geometry": {"coordinates":[82.17834999999999,25.520612],"type":"Point"}
}