{
  "type": "Feature",
  "properties": {
    "gn:admin1_code":"28.0",
    "gn:admin2_code":"345",
    "gn:asciiname":"Paran",
    "gn:country_code":"IN",
    "gn:dem":9,
    "gn:feature_class":"P",
    "gn:feature_code":"PPL",
    "gn:name":"Paran",
    "gn:population":0,
    "gn:timezone":"Asia/Kolkata",
    "iso:country":"IN",
    "name:ceb_x_preferred":[
        "Paran"
    ],
    "name:heb_x_preferred":[
        "\u05e4\u05d0\u05e8\u05df"
    ],
    "name:swe_x_preferred":[
        "Paran"
    ],
    "wof:name":"Paran",
    "wof:placetype":"locality"
},
  "geometry": {"coordinates":[88.11694,22.08],"type":"Point"}
}