{
  "type": "Feature",
  "properties": {
    "gn:country":"IN",
    "gn:fcode":"PPL",
    "gn:pop":3857,
    "iso:country":"IN",
    "qs:name":"Thanna Mandi",
    "qs:photos_9r":0,
    "qs:photos_sr":0,
    "qs:pop_sr":"4",
    "wd:wordcount":403,
    "wof:name":"Thanna Mandi",
    "wof:placetype":"locality",
    "wof:population":3857
},
  "geometry": {"coordinates":[74.38030999999999,33.54228],"type":"Point"}
}