{
  "type": "Feature",
  "properties": {
    "gn:country":"IN",
    "gn:fcode":"PPL",
    "gn:population":3857,
    "iso:country":"IN",
    "name:bpy_x_preferred":[
        "\u09a5\u09be\u09a8\u09be\u09ae\u09be\u09a8\u09cd\u09a6\u09bf"
    ],
    "name:ceb_x_preferred":[
        "Thanna Mandi"
    ],
    "name:eng_x_preferred":[
        "Thanamandi Tehsil"
    ],
    "name:hin_x_preferred":[
        "\u0925\u0928\u093e\u092e\u0902\u0921\u0940"
    ],
    "name:ita_x_preferred":[
        "Thanamandi"
    ],
    "name:mlg_x_preferred":[
        "Thanamandi"
    ],
    "name:msa_x_preferred":[
        "Thanamandi"
    ],
    "name:nan_x_preferred":[
        "Thanamandi"
    ],
    "name:nld_x_preferred":[
        "Thanamandi"
    ],
    "name:por_x_preferred":[
        "Thanamandi"
    ],
    "name:swe_x_preferred":[
        "Thanna Mandi"
    ],
    "name:urd_x_preferred":[
        "\u062a\u06be\u0646\u06c1 \u0645\u0646\u0688\u06cc"
    ],
    "name:vie_x_preferred":[
        "Thanamandi"
    ],
    "name:zho_x_preferred":[
        "\u5854\u7eb3\u66fc\u8fea"
    ],
    "qs:name":"Thanna Mandi",
    "qs:photos_9r":0,
    "qs:photos_sr":0,
    "qs:pop_sr":"4",
    "wd:wordcount":403,
    "wof:name":"Thanna Mandi",
    "wof:placetype":"locality",
    "wof:population":3857
},
  "geometry": {"coordinates":[74.38030999999999,33.54228],"type":"Point"}
}