{
  "type": "Feature",
  "properties": {
    "iso:country":"IN",
    "ks:ks_name":"Dabhole",
    "ks:ks_pop":2136,
    "ks:ks_type":"VILLAGE",
    "name:eng_x_preferred":[
        "Dabhole"
    ],
    "wof:name":"Dabhole",
    "wof:placetype":"locality",
    "wof:population":2136
},
  "geometry": {"coordinates":[73.455074,16.379458],"type":"Point"}
}