{
  "type": "Feature",
  "properties": {
    "gn:admin1_code":"34.0",
    "gn:admin2_code":"235.0",
    "gn:asciiname":"Kajpa",
    "gn:country_code":"IN",
    "gn:dem":96,
    "gn:feature_class":"P",
    "gn:feature_code":"PPL",
    "gn:name":"Kajpa",
    "gn:population":0,
    "gn:timezone":"Asia/Kolkata",
    "iso:country":"IN",
    "name:hif_x_preferred":[
        "Kajpa"
    ],
    "wof:name":"Kajpa",
    "wof:placetype":"locality"
},
  "geometry": {"coordinates":[84.52356,24.82677],"type":"Point"}
}