{
  "type": "Feature",
  "properties": {
    "iso:country":"IN",
    "ks:ks_name":"Falaudi",
    "ks:ks_pop":1021,
    "ks:ks_type":"VILLAGE",
    "ks:ks_uagg_main":0,
    "name:eng_x_preferred":[
        "Falaudi"
    ],
    "wof:name":"Falaudi",
    "wof:placetype":"neighbourhood",
    "wof:population":1021
},
  "geometry": {"coordinates":[78.37276199999999,29.286055],"type":"Point"}
}