{
  "type": "Feature",
  "properties": {
    "iso:country":"IN",
    "ks:ks_name":"Dhamsoo",
    "ks:ks_pop":123,
    "ks:ks_type":"VILLAGE",
    "name:eng_x_preferred":[
        "Dhamsoo"
    ],
    "wof:name":"Dhamsoo",
    "wof:placetype":"locality",
    "wof:population":123
},
  "geometry": {"coordinates":[77.005968,30.780365],"type":"Point"}
}