{
  "type": "Feature",
  "properties": {
    "iso:country":"IN",
    "ks:ks_name":"Kudakuda",
    "ks:ks_pop":5689,
    "ks:ks_type":"VILLAGE",
    "ks:ks_uagg_main":0,
    "name:eng_x_preferred":[
        "Kudakuda"
    ],
    "wof:name":"Kudakuda",
    "wof:placetype":"neighbourhood",
    "wof:population":5689
},
  "geometry": {"coordinates":[79.628002,17.164577],"type":"Point"}
}