{
  "type": "Feature",
  "properties": {
    "gn:admin1_code":"35",
    "gn:asciiname":"Barawali",
    "gn:country_code":"IN",
    "gn:dem":155,
    "gn:feature_class":"P",
    "gn:feature_code":"PPL",
    "gn:name":"Bar\u0101wali",
    "gn:population":0,
    "gn:timezone":"Asia/Kolkata",
    "iso:country":"IN",
    "wof:name":"Barawali",
    "wof:placetype":"locality"
},
  "geometry": {"coordinates":[77.5551,26.43605],"type":"Point"}
}