{
  "type": "Feature",
  "properties": {
    "gn:admin1_code":"25.0",
    "gn:admin2_code":"605.0",
    "gn:asciiname":"Pusareyur",
    "gn:country_code":"IN",
    "gn:dem":422,
    "gn:feature_class":"P",
    "gn:feature_code":"PPL",
    "gn:name":"P\u016bs\u0101rey\u016br",
    "gn:population":0,
    "gn:timezone":"Asia/Kolkata",
    "iso:country":"IN",
    "wof:name":"Pusareyur",
    "wof:placetype":"locality"
},
  "geometry": {"coordinates":[78.53355999999999,12.58446],"type":"Point"}
}