{
  "type": "Feature",
  "properties": {
    "iso:country":"IN",
    "ks:ks_name":"Muzhuvancherry Bridge",
    "ks:ks_pop":363,
    "ks:ks_type":"HABITATION",
    "name:eng_x_preferred":[
        "Muzhuvancherry Bridge"
    ],
    "wof:name":"Muzhuvancherry Bridge",
    "wof:placetype":"locality",
    "wof:population":363
},
  "geometry": {"coordinates":[76.17144399999999,10.301558],"type":"Point"}
}