{
  "type": "Feature",
  "properties": {
    "iso:country":"IN",
    "ks:ks_alt_nam":"Naraiha para",
    "ks:ks_name":"Naraiha Para",
    "ks:ks_pop":133,
    "ks:ks_type":"HABITATION",
    "ks:ks_uagg_main":0,
    "name:eng_x_preferred":[
        "Naraiha Para"
    ],
    "wof:name":"Naraiha Para",
    "wof:placetype":"neighbourhood",
    "wof:population":133
},
  "geometry": {"coordinates":[91.75477100000001,23.343672],"type":"Point"}
}