{
  "type": "Feature",
  "properties": {
    "iso:country":"IN",
    "ks:ks_name":"Vilakannur",
    "ks:ks_pop":1397,
    "ks:ks_type":"HABITATION",
    "name:eng_x_preferred":[
        "Vilakannur"
    ],
    "wof:name":"Vilakannur",
    "wof:placetype":"locality",
    "wof:population":1397
},
  "geometry": {"coordinates":[75.457275,12.136642],"type":"Point"}
}