{
  "type": "Feature",
  "properties": {
    "gn:admin1_code":"34.0",
    "gn:admin2_code":"235.0",
    "gn:asciiname":"Khairi",
    "gn:country_code":"IN",
    "gn:dem":102,
    "gn:feature_class":"P",
    "gn:feature_code":"PPL",
    "gn:name":"Khairi",
    "gn:population":0,
    "gn:timezone":"Asia/Kolkata",
    "iso:country":"IN",
    "ks:ks_name":"Khairi",
    "ks:ks_pop":457,
    "ks:ks_type":"VILLAGE",
    "name:eng_x_preferred":[
        "Khairi"
    ],
    "wof:name":"Khairi",
    "wof:placetype":"locality",
    "wof:population":457
},
  "geometry": {"coordinates":[84.630133,24.839619],"type":"Point"}
}