{
  "type": "Feature",
  "properties": {
    "iso:country":"IN",
    "ks:ks_alt_nam":"Kotha thadna",
    "ks:ks_name":"Kotha Thadna",
    "ks:ks_pop":284,
    "ks:ks_type":"HABITATION",
    "name:eng_x_preferred":[
        "Kotha Thadna"
    ],
    "wof:name":"Kotha Thadna",
    "wof:placetype":"locality",
    "wof:population":284
},
  "geometry": {"coordinates":[79.70158499999999,17.725761],"type":"Point"}
}