{
  "type": "Feature",
  "properties": {
    "gn:admin1_code":"35.0",
    "gn:admin2_code":"430.0",
    "gn:asciiname":"Kanpura",
    "gn:country_code":"IN",
    "gn:dem":113,
    "gn:feature_class":"P",
    "gn:feature_code":"PPL",
    "gn:name":"Kanpura",
    "gn:population":0,
    "gn:timezone":"Asia/Kolkata",
    "iso:country":"IN",
    "ks:ks_name":"Kanpura",
    "ks:ks_pop":845,
    "ks:ks_type":"VILLAGE",
    "name:eng_x_preferred":[
        "Kanpura"
    ],
    "wof:name":"Kanpura",
    "wof:placetype":"locality",
    "wof:population":845
},
  "geometry": {"coordinates":[81.51598,25.025312],"type":"Point"}
}