{
  "type": "Feature",
  "properties": {
    "iso:country":"IN",
    "ks:ks_name":"Kadamgadi",
    "ks:ks_pop":210,
    "ks:ks_type":"VILLAGE",
    "name:eng_x_preferred":[
        "Kadamgadi"
    ],
    "wof:name":"Kadamgadi",
    "wof:placetype":"locality",
    "wof:population":210
},
  "geometry": {"coordinates":[86.66553500000001,21.517719],"type":"Point"}
}