{
  "type": "Feature",
  "properties": {
    "iso:country":"IN",
    "ks:ks_name":"Uparbandhi",
    "ks:ks_pop":94,
    "ks:ks_type":"VILLAGE",
    "name:eng_x_preferred":[
        "Uparbandhi"
    ],
    "wof:name":"Uparbandhi",
    "wof:placetype":"locality",
    "wof:population":94
},
  "geometry": {"coordinates":[86.78330099999999,24.197821],"type":"Point"}
}