{
  "type": "Feature",
  "properties": {
    "iso:country":"IN",
    "ks:ks_name":"Bajan Ka Pura",
    "ks:ks_pop":319,
    "ks:ks_type":"HABITATION",
    "ks:ks_uagg_main":0,
    "name:eng_x_preferred":[
        "Bajan Ka Pura"
    ],
    "wof:name":"Bajan Ka Pura",
    "wof:placetype":"neighbourhood",
    "wof:population":319
},
  "geometry": {"coordinates":[82.68652299999999,26.301513],"type":"Point"}
}