{
  "type": "Feature",
  "properties": {
    "iso:country":"IN",
    "ks:ks_name":"Nochiyur",
    "ks:ks_pop":1075,
    "ks:ks_type":"VILLAGE",
    "name:eng_x_preferred":[
        "Nochiyur"
    ],
    "wof:name":"Nochiyur",
    "wof:placetype":"locality",
    "wof:population":1075
},
  "geometry": {"coordinates":[79.51160900000001,10.446597],"type":"Point"}
}