{
  "type": "Feature",
  "properties": {
    "iso:country":"IN",
    "ks:ks_name":"Badakhaman",
    "ks:ks_pop":1800,
    "ks:ks_type":"VILLAGE",
    "name:eng_x_preferred":[
        "Badakhaman"
    ],
    "wof:name":"Badakhaman",
    "wof:placetype":"locality",
    "wof:population":1800
},
  "geometry": {"coordinates":[86.478599,21.613797],"type":"Point"}
}