{
  "type": "Feature",
  "properties": {
    "iso:country":"IN",
    "ks:ks_name":"Biligirikoppa",
    "ks:ks_pop":149,
    "ks:ks_type":"HABITATION",
    "name:eng_x_preferred":[
        "Biligirikoppa"
    ],
    "wof:name":"Biligirikoppa",
    "wof:placetype":"locality",
    "wof:population":149
},
  "geometry": {"coordinates":[74.883871,14.590478],"type":"Point"}
}