{
  "type": "Feature",
  "properties": {
    "gn:admin1_code":"2.0",
    "gn:admin2_code":"543.0",
    "gn:asciiname":"Koyyanapeta",
    "gn:country_code":"IN",
    "gn:dem":132,
    "gn:feature_class":"P",
    "gn:feature_code":"PPL",
    "gn:name":"Koyy\u0101napeta",
    "gn:population":0,
    "gn:timezone":"Asia/Kolkata",
    "iso:country":"IN",
    "wof:name":"Koyyanapeta",
    "wof:placetype":"locality"
},
  "geometry": {"coordinates":[83.30053000000002,18.67625],"type":"Point"}
}