{
  "type": "Feature",
  "properties": {
    "iso:country":"IN",
    "ks:ks_name":"Kollakata",
    "ks:ks_pop":1800,
    "ks:ks_type":"HABITATION",
    "name:eng_x_preferred":[
        "Kollakata"
    ],
    "wof:name":"Kollakata",
    "wof:placetype":"locality",
    "wof:population":1800
},
  "geometry": {"coordinates":[89.00000300000001,26.491384],"type":"Point"}
}