{
  "type": "Feature",
  "properties": {
    "iso:country":"IN",
    "ks:ks_name":"Madhiya Bidhau",
    "ks:ks_pop":188,
    "ks:ks_type":"HABITATION",
    "name:eng_x_preferred":[
        "Madhiya Bidhau"
    ],
    "wof:name":"Madhiya Bidhau",
    "wof:placetype":"locality",
    "wof:population":188
},
  "geometry": {"coordinates":[79.197148,28.82911],"type":"Point"}
}