{
  "type": "Feature",
  "properties": {
    "iso:country":"IN",
    "ks:ks_name":"Imrit Pali",
    "ks:ks_pop":403,
    "ks:ks_type":"VILLAGE",
    "ks:ks_uagg_main":0,
    "name:eng_x_preferred":[
        "Imrit Pali"
    ],
    "wof:name":"Imrit Pali",
    "wof:placetype":"neighbourhood",
    "wof:population":403
},
  "geometry": {"coordinates":[84.1678,25.764972],"type":"Point"}
}