{
  "type": "Feature",
  "properties": {
    "iso:country":"IN",
    "ks:ks_name":"Laxmanpur",
    "ks:ks_pop":53,
    "ks:ks_type":"HABITATION",
    "name:eng_x_preferred":[
        "Laxmanpur"
    ],
    "wof:name":"Laxmanpur",
    "wof:placetype":"locality",
    "wof:population":53
},
  "geometry": {"coordinates":[82.349835,18.61482],"type":"Point"}
}