{
  "type": "Feature",
  "properties": {
    "iso:country":"IN",
    "ks:ks_name":"Boddecherla Malawada",
    "ks:ks_pop":373,
    "ks:ks_type":"HABITATION",
    "name:eng_x_preferred":[
        "Boddecherla Malawada"
    ],
    "wof:name":"Boddecherla Malawada",
    "wof:placetype":"locality",
    "wof:population":373
},
  "geometry": {"coordinates":[79.186941,14.558097],"type":"Point"}
}