{
  "type": "Feature",
  "properties": {
    "iso:country":"IN",
    "ks:ks_name":"Krisi Para",
    "ks:ks_pop":58,
    "ks:ks_type":"HABITATION",
    "ks:ks_uagg_main":0,
    "name:eng_x_preferred":[
        "Krisi Para"
    ],
    "wof:name":"Krisi Para",
    "wof:placetype":"neighbourhood",
    "wof:population":58
},
  "geometry": {"coordinates":[81.216424,19.736467],"type":"Point"}
}