{
  "type": "Feature",
  "properties": {
    "iso:country":"IN",
    "ks:ks_name":"Tilaw No.1",
    "ks:ks_pop":427,
    "ks:ks_type":"VILLAGE",
    "name:eng_x_preferred":[
        "Tilaw No.1"
    ],
    "wof:name":"Tilaw No.1",
    "wof:placetype":"locality",
    "wof:population":427
},
  "geometry": {"coordinates":[82.329052,24.934048],"type":"Point"}
}