{
  "type": "Feature",
  "properties": {
    "iso:country":"IN",
    "ks:ks_alt_nam":"Harijan toli",
    "ks:ks_name":"Harijan Toli",
    "ks:ks_pop":375,
    "ks:ks_type":"HABITATION",
    "name:eng_x_preferred":[
        "Harijan Toli"
    ],
    "wof:name":"Harijan Toli",
    "wof:placetype":"locality",
    "wof:population":375
},
  "geometry": {"coordinates":[86.15854,26.120664],"type":"Point"}
}