{
  "type": "Feature",
  "properties": {
    "iso:country":"IN",
    "ks:ks_name":"Melinguli",
    "ks:ks_pop":471,
    "ks:ks_type":"HABITATION",
    "name:eng_x_preferred":[
        "Melinguli"
    ],
    "wof:name":"Melinguli",
    "wof:placetype":"locality",
    "wof:population":471
},
  "geometry": {"coordinates":[74.39995500000001,14.624054],"type":"Point"}
}