{
  "type": "Feature",
  "properties": {
    "iso:country":"IN",
    "ks:ks_name":"Chandragutta",
    "ks:ks_pop":46,
    "ks:ks_type":"HABITATION",
    "name:eng_x_preferred":[
        "Chandragutta"
    ],
    "wof:name":"Chandragutta",
    "wof:placetype":"locality",
    "wof:population":46
},
  "geometry": {"coordinates":[77.916652,17.104591],"type":"Point"}
}