{
  "type": "Feature",
  "properties": {
    "gn:admin1_code":"36.0",
    "gn:admin2_code":"151.0",
    "gn:asciiname":"Methi Sadullahganj",
    "gn:country_code":"IN",
    "gn:dem":190,
    "gn:feature_class":"P",
    "gn:feature_code":"PPL",
    "gn:name":"Methi S\u0101dullahganj",
    "gn:population":0,
    "gn:timezone":"Asia/Kolkata",
    "iso:country":"IN",
    "wof:name":"Methi Sadullahganj",
    "wof:placetype":"locality"
},
  "geometry": {"coordinates":[79.88918000000002,28.69232],"type":"Point"}
}