{
  "type": "Feature",
  "properties": {
    "iso:country":"IN",
    "ks:ks_name":"Dhaneli",
    "ks:ks_pop":560,
    "ks:ks_type":"VILLAGE",
    "name:eng_x_preferred":[
        "Dhaneli"
    ],
    "wof:name":"Dhaneli",
    "wof:placetype":"locality",
    "wof:population":560
},
  "geometry": {"coordinates":[70.60229200000001,26.561325],"type":"Point"}
}