{
  "type": "Feature",
  "properties": {
    "iso:country":"IN",
    "ks:ks_name":"Sukdevpur",
    "ks:ks_pop":0,
    "ks:ks_type":"VILLAGE",
    "name:eng_x_preferred":[
        "Sukdevpur"
    ],
    "wof:name":"Sukdevpur",
    "wof:placetype":"locality",
    "wof:population":0
},
  "geometry": {"coordinates":[86.747676,20.561302],"type":"Point"}
}