{
  "type": "Feature",
  "properties": {
    "iso:country":"IN",
    "ks:ks_name":"Jagamvarigudem",
    "ks:ks_pop":207,
    "ks:ks_type":"HABITATION",
    "name:eng_x_preferred":[
        "Jagamvarigudem"
    ],
    "wof:name":"Jagamvarigudem",
    "wof:placetype":"locality",
    "wof:population":207
},
  "geometry": {"coordinates":[78.753282,17.353627],"type":"Point"}
}