{
  "type": "Feature",
  "properties": {
    "gn:admin1_code":"2.0",
    "gn:admin2_code":"549.0",
    "gn:asciiname":"Nikarampalle",
    "gn:country_code":"IN",
    "gn:dem":155,
    "gn:feature_class":"P",
    "gn:feature_code":"PPL",
    "gn:name":"Nikarampalle",
    "gn:population":0,
    "gn:timezone":"Asia/Kolkata",
    "iso:country":"IN",
    "ks:ks_name":"Nikaram Palle",
    "ks:ks_pop":2023,
    "ks:ks_type":"VILLAGE",
    "ks:ks_uagg_main":0,
    "name:eng_x_preferred":[
        "Nikaram Palle"
    ],
    "wof:name":"Nikaram Palle",
    "wof:placetype":"neighbourhood",
    "wof:population":2023
},
  "geometry": {"coordinates":[79.23903799999999,15.763825],"type":"Point"}
}