{
  "type": "Feature",
  "properties": {
    "iso:country":"IN",
    "ks:ks_name":"Kazipura",
    "ks:ks_pop":0,
    "ks:ks_type":"VILLAGE",
    "name:eng_x_preferred":[
        "Kazipura"
    ],
    "wof:name":"Kazipura",
    "wof:placetype":"locality",
    "wof:population":0
},
  "geometry": {"coordinates":[77.38352500000001,29.953767],"type":"Point"}
}