{
  "type": "Feature",
  "properties": {
    "iso:country":"IN",
    "ks:ks_name":"Tanda",
    "ks:ks_pop":473,
    "ks:ks_type":"VILLAGE",
    "name:eng_x_preferred":[
        "Tanda"
    ],
    "name:hin_x_preferred":[
        "\u091f\u093e\u0902\u0921\u093e"
    ],
    "wof:name":"Tanda",
    "wof:placetype":"locality",
    "wof:population":473
},
  "geometry": {"coordinates":[75.682812,23.459242],"type":"Point"}
}