{
  "type": "Feature",
  "properties": {
    "gn:admin1_code":"36",
    "gn:admin2_code":"179.0",
    "gn:asciiname":"Sia",
    "gn:country_code":"IN",
    "gn:dem":104,
    "gn:feature_class":"P",
    "gn:feature_code":"PPL",
    "gn:name":"S\u012ba",
    "gn:population":0,
    "gn:timezone":"Asia/Kolkata",
    "iso:country":"IN",
    "name:ceb_x_preferred":[
        "Sia"
    ],
    "name:ces_x_preferred":[
        "Sia"
    ],
    "name:dan_x_preferred":[
        "Sia"
    ],
    "name:deu_x_preferred":[
        "Sia"
    ],
    "name:est_x_preferred":[
        "Sia"
    ],
    "name:hye_x_preferred":[
        "\u054d\u056b\u0561"
    ],
    "name:isl_x_preferred":[
        "S\u00eda"
    ],
    "name:lat_x_preferred":[
        "Sia"
    ],
    "name:nld_x_preferred":[
        "Sia"
    ],
    "name:por_x_preferred":[
        "Sia"
    ],
    "name:sco_x_preferred":[
        "Sia"
    ],
    "name:slk_x_preferred":[
        "Sia"
    ],
    "name:spa_x_preferred":[
        "Sia"
    ],
    "name:swe_x_preferred":[
        "Sia"
    ],
    "wof:name":"Sia",
    "wof:placetype":"locality"
},
  "geometry": {"coordinates":[82.10618000000002,26.40518],"type":"Point"}
}