{
  "type": "Feature",
  "properties": {
    "iso:country":"IN",
    "ks:ks_name":"Kumhna",
    "ks:ks_pop":94,
    "ks:ks_type":"VILLAGE",
    "name:eng_x_preferred":[
        "Kumhna"
    ],
    "wof:name":"Kumhna",
    "wof:placetype":"locality",
    "wof:population":94
},
  "geometry": {"coordinates":[79.215763,29.680662],"type":"Point"}
}