{
  "type": "Feature",
  "properties": {
    "iso:country":"IN",
    "ks:ks_name":"Guleth",
    "ks:ks_pop":32,
    "ks:ks_type":"VILLAGE",
    "name:eng_x_preferred":[
        "Guleth"
    ],
    "wof:name":"Guleth",
    "wof:placetype":"locality",
    "wof:population":32
},
  "geometry": {"coordinates":[78.771428,30.199811],"type":"Point"}
}