{
  "type": "Feature",
  "properties": {
    "iso:country":"IN",
    "ks:ks_name":"Pathanarasannagaripalle",
    "ks:ks_pop":136,
    "ks:ks_type":"HABITATION",
    "ks:ks_uagg_main":0,
    "name:eng_x_preferred":[
        "Pathanarasannagaripalle"
    ],
    "wof:name":"Pathanarasannagaripalle",
    "wof:placetype":"neighbourhood",
    "wof:population":136
},
  "geometry": {"coordinates":[78.78219799999999,14.438055],"type":"Point"}
}