{
  "type": "Feature",
  "properties": {
    "gn:country":"IN",
    "gn:fcode":"PPL",
    "gn:population":12055,
    "iso:country":"IN",
    "name:bpy_x_preferred":[
        "\u09b8\u09cc\u09b0\u09bf\u0996"
    ],
    "name:bul_x_preferred":[
        "\u0421\u0430\u0443\u0440\u0438\u043a\u0445"
    ],
    "name:ceb_x_preferred":[
        "Saurikh"
    ],
    "name:eng_x_preferred":[
        "Saurikh"
    ],
    "name:fra_x_preferred":[
        "Saurikh"
    ],
    "name:ita_x_preferred":[
        "Saurikh"
    ],
    "name:mlg_x_preferred":[
        "Saurikh"
    ],
    "name:msa_x_preferred":[
        "Saurikh"
    ],
    "name:nan_x_preferred":[
        "Saurikh"
    ],
    "name:nld_x_preferred":[
        "Saurikh"
    ],
    "name:pol_x_preferred":[
        "Saurikh"
    ],
    "name:por_x_preferred":[
        "Saurikh"
    ],
    "name:rus_x_preferred":[
        "\u0421\u0430\u0443\u0440\u0438\u043a\u0445"
    ],
    "name:swe_x_preferred":[
        "Saurikh"
    ],
    "name:und_x_variant":[
        "Saurnikh"
    ],
    "name:urd_x_preferred":[
        "\u0633\u0648\u0631\u06a9\u06be"
    ],
    "name:vie_x_preferred":[
        "Saurikh"
    ],
    "name:zho_x_preferred":[
        "\u7ecd\u91cc\u514b"
    ],
    "qs:name":"Saurikh",
    "qs:photos_9r":0,
    "qs:photos_sr":0,
    "qs:pop_sr":"6",
    "wd:wordcount":288,
    "wof:name":"Saurikh",
    "wof:placetype":"locality",
    "wof:population":12055
},
  "geometry": {"coordinates":[79.48784999999999,27.02965],"type":"Point"}
}