{
  "type": "Feature",
  "properties": {
    "iso:country":"IN",
    "ks:ks_name":"Khemapur",
    "ks:ks_pop":0,
    "ks:ks_type":"VILLAGE",
    "name:eng_x_preferred":[
        "Khemapur"
    ],
    "wof:name":"Khemapur",
    "wof:placetype":"locality",
    "wof:population":0
},
  "geometry": {"coordinates":[83.82982699999999,25.4879],"type":"Point"}
}