{
  "type": "Feature",
  "properties": {
    "iso:country":"IN",
    "ks:ks_name":"Enumulavaripalle",
    "ks:ks_pop":22,
    "ks:ks_type":"HABITATION",
    "name:eng_x_preferred":[
        "Enumulavaripalle"
    ],
    "wof:name":"Enumulavaripalle",
    "wof:placetype":"locality",
    "wof:population":22
},
  "geometry": {"coordinates":[78.47247299999999,13.790722],"type":"Point"}
}