{
  "type": "Feature",
  "properties": {
    "iso:country":"IN",
    "ks:ks_alt_nam":"SANTUDAS PARA",
    "ks:ks_name":"Santudas Para",
    "ks:ks_pop":97,
    "ks:ks_type":"HABITATION",
    "name:eng_x_preferred":[
        "Santudas Para"
    ],
    "wof:name":"Santudas Para",
    "wof:placetype":"locality",
    "wof:population":97
},
  "geometry": {"coordinates":[91.556944,23.983333],"type":"Point"}
}