{
  "type": "Feature",
  "properties": {
    "gn:admin1_code":"19.0",
    "gn:admin2_code":"568.0",
    "gn:asciiname":"Bannikere",
    "gn:country_code":"IN",
    "gn:dem":632,
    "gn:feature_class":"P",
    "gn:feature_code":"PPL",
    "gn:name":"Bannikere",
    "gn:population":0,
    "gn:timezone":"Asia/Kolkata",
    "iso:country":"IN",
    "wof:name":"Bannikere",
    "wof:placetype":"locality"
},
  "geometry": {"coordinates":[75.60938,14.04212],"type":"Point"}
}