{
  "type": "Feature",
  "properties": {
    "iso:country":"IN",
    "ks:ks_name":"Dhayapuram",
    "ks:ks_pop":30,
    "ks:ks_type":"HABITATION",
    "name:eng_x_preferred":[
        "Dhayapuram"
    ],
    "wof:name":"Dhayapuram",
    "wof:placetype":"locality",
    "wof:population":30
},
  "geometry": {"coordinates":[78.78723100000001,12.833597],"type":"Point"}
}