{
  "type": "Feature",
  "properties": {
    "gn:admin1_code":"35",
    "gn:admin2_code":"428.0",
    "gn:asciiname":"Jhamra",
    "gn:country_code":"IN",
    "gn:dem":401,
    "gn:feature_class":"P",
    "gn:feature_code":"PPL",
    "gn:name":"Jhamra",
    "gn:population":0,
    "gn:timezone":"Asia/Kolkata",
    "iso:country":"IN",
    "name:pnb_x_preferred":[
        "\u062c\u06be\u0627\u0645\u0631\u06c1"
    ],
    "name:urd_x_preferred":[
        "\u062c\u06be\u0627\u0645\u0631\u06c1"
    ],
    "wof:name":"Jhamra",
    "wof:placetype":"locality"
},
  "geometry": {"coordinates":[79.29571,23.2933],"type":"Point"}
}