{
  "type": "Feature",
  "properties": {
    "iso:country":"IN",
    "ks:ks_alt_nam":"T\u012bkri Khurd",
    "ks:ks_name":"Tikri Khurd",
    "ks:ks_type":"VILLAGE",
    "ks:ks_uagg_main":0,
    "name:eng_x_preferred":[
        "Tikri Khurd"
    ],
    "name:eng_x_variant":[
        "T\u012bkri Khurd"
    ],
    "wof:name":"Tikri Khurd",
    "wof:placetype":"neighbourhood"
},
  "geometry": {"coordinates":[77.119495,28.835393],"type":"Point"}
}