{
  "type": "Feature",
  "properties": {
    "gn:admin1_code":"37",
    "gn:admin2_code":"404.0",
    "gn:asciiname":"Pathardand",
    "gn:country_code":"IN",
    "gn:dem":550,
    "gn:feature_class":"P",
    "gn:feature_code":"PPL",
    "gn:name":"P\u0101thard\u0101nd",
    "gn:population":0,
    "gn:timezone":"Asia/Kolkata",
    "iso:country":"IN",
    "ks:ks_name":"Patradand",
    "ks:ks_pop":255,
    "ks:ks_type":"HABITATION",
    "name:eng_x_preferred":[
        "Patradand"
    ],
    "name:eng_x_variant":[
        "Pathardand"
    ],
    "wof:name":"Patradand",
    "wof:placetype":"locality",
    "wof:population":255
},
  "geometry": {"coordinates":[82.18516099999999,22.73852],"type":"Point"}
}