{
  "type": "Feature",
  "properties": {
    "gn:admin1_code":"36",
    "gn:admin2_code":"194.0",
    "gn:asciiname":"Bhataura",
    "gn:country_code":"IN",
    "gn:dem":88,
    "gn:feature_class":"P",
    "gn:feature_code":"PPL",
    "gn:name":"Bhataura",
    "gn:population":0,
    "gn:timezone":"Asia/Kolkata",
    "iso:country":"IN",
    "ks:ks_name":"Bhateora",
    "ks:ks_pop":1773,
    "ks:ks_type":"VILLAGE",
    "name:eng_x_preferred":[
        "Bhateora"
    ],
    "name:eng_x_variant":[
        "Bhataura"
    ],
    "wof:name":"Bhateora",
    "wof:placetype":"locality",
    "wof:population":1773
},
  "geometry": {"coordinates":[82.63796600000001,25.809059],"type":"Point"}
}