{
  "type": "Feature",
  "properties": {
    "iso:country":"IN",
    "ks:ks_name":"Chikkalavaripeta",
    "ks:ks_pop":184,
    "ks:ks_type":"HABITATION",
    "name:eng_x_preferred":[
        "Chikkalavaripeta"
    ],
    "wof:name":"Chikkalavaripeta",
    "wof:placetype":"locality",
    "wof:population":184
},
  "geometry": {"coordinates":[81.929197,16.652471],"type":"Point"}
}