{
  "type": "Feature",
  "properties": {
    "iso:country":"IN",
    "ks:ks_name":"Bangrahan",
    "ks:ks_pop":180,
    "ks:ks_type":"HABITATION",
    "name:eng_x_preferred":[
        "Bangrahan"
    ],
    "wof:name":"Bangrahan",
    "wof:placetype":"locality",
    "wof:population":180
},
  "geometry": {"coordinates":[81.97356600000001,26.886279],"type":"Point"}
}