{
  "type": "Feature",
  "properties": {
    "iso:country":"IN",
    "ks:ks_name":"Balidih",
    "ks:ks_pop":514,
    "ks:ks_type":"VILLAGE",
    "name:eng_x_preferred":[
        "Balidih"
    ],
    "wof:name":"Balidih",
    "wof:placetype":"locality",
    "wof:population":514
},
  "geometry": {"coordinates":[86.008906,22.930496],"type":"Point"}
}