{
  "type": "Feature",
  "properties": {
    "gn:admin1_code":"11.0",
    "gn:asciiname":"Bunga",
    "gn:country_code":"IN",
    "gn:dem":1189,
    "gn:feature_class":"P",
    "gn:feature_code":"PPL",
    "gn:name":"Bunga",
    "gn:population":0,
    "gn:timezone":"Asia/Kolkata",
    "iso:country":"IN",
    "name:ceb_x_preferred":[
        "Bunga"
    ],
    "name:ind_x_preferred":[
        "Bunga"
    ],
    "name:swe_x_preferred":[
        "Bunga"
    ],
    "name:tgl_x_preferred":[
        "Bunga"
    ],
    "wof:name":"Bunga",
    "wof:placetype":"locality"
},
  "geometry": {"coordinates":[77.16297,30.68593],"type":"Point"}
}