{
  "type": "Feature",
  "properties": {
    "gn:admin1_code":"34.0",
    "gn:admin2_code":"212.0",
    "gn:asciiname":"Jitwarpur",
    "gn:country_code":"IN",
    "gn:dem":40,
    "gn:feature_class":"P",
    "gn:feature_code":"PPL",
    "gn:name":"Jitw\u0101rpur",
    "gn:population":0,
    "gn:timezone":"Asia/Kolkata",
    "iso:country":"IN",
    "ks:ks_alt_nam":"Jitw\u0101rpur",
    "ks:ks_name":"Jitwarpur",
    "ks:ks_pop":1340,
    "ks:ks_type":"VILLAGE",
    "ks:ks_uagg_main":0,
    "name:eng_x_preferred":[
        "Jitwarpur"
    ],
    "name:eng_x_variant":[
        "Jitw\u0101rpur"
    ],
    "wof:name":"Jitwarpur",
    "wof:placetype":"neighbourhood",
    "wof:population":1340
},
  "geometry": {"coordinates":[87.834209,25.691995],"type":"Point"}
}