{
  "type": "Feature",
  "properties": {
    "gn:admin1_code":"40",
    "gn:admin2_code":"541.0",
    "gn:asciiname":"Pallevada",
    "gn:country_code":"IN",
    "gn:dem":117,
    "gn:feature_class":"P",
    "gn:feature_code":"PPL",
    "gn:name":"Pallev\u0101da",
    "gn:population":0,
    "gn:timezone":"Asia/Kolkata",
    "iso:country":"IN",
    "ks:ks_alt_nam":"Pallev\u0101da",
    "ks:ks_name":"Pallevada",
    "ks:ks_pop":1214,
    "ks:ks_type":"VILLAGE",
    "name:ceb_x_preferred":[
        "Pallev\u0101da"
    ],
    "name:eng_x_preferred":[
        "Pallevada"
    ],
    "name:eng_x_variant":[
        "Pallev\u0101da"
    ],
    "name:hin_x_preferred":[
        "\u092a\u0932\u0946\u0935\u093e\u0921"
    ],
    "name:new_x_preferred":[
        "\u092a\u0932\u0946\u0935\u093e\u0921"
    ],
    "name:swe_x_preferred":[
        "Pallev\u0101da"
    ],
    "name:tel_x_preferred":[
        "\u0c2a\u0c32\u0c4d\u0c32\u0c46\u0c35\u0c3e\u0c21"
    ],
    "wof:name":"Pallevada",
    "wof:placetype":"locality",
    "wof:population":1214
},
  "geometry": {"coordinates":[80.729645,17.16876],"type":"Point"}
}