{
  "type": "Feature",
  "properties": {
    "iso:country":"IN",
    "ks:ks_alt_nam":"GARASAI",
    "ks:ks_name":"Garasai",
    "ks:ks_pop":58,
    "ks:ks_type":"HABITATION",
    "name:eng_x_preferred":[
        "Garasai"
    ],
    "wof:name":"Garasai",
    "wof:placetype":"locality",
    "wof:population":58
},
  "geometry": {"coordinates":[85.611768,22.401255],"type":"Point"}
}