{
  "type": "Feature",
  "properties": {
    "gn:admin1_code":"10.0",
    "gn:admin2_code":"76.0",
    "gn:asciiname":"Pabnera",
    "gn:country_code":"IN",
    "gn:dem":221,
    "gn:feature_class":"P",
    "gn:feature_code":"PPL",
    "gn:name":"Pabnera",
    "gn:population":0,
    "gn:timezone":"Asia/Kolkata",
    "iso:country":"IN",
    "wof:name":"Pabnera",
    "wof:placetype":"locality"
},
  "geometry": {"coordinates":[77.12418000000002,29.11661],"type":"Point"}
}