{
  "type": "Feature",
  "properties": {
    "iso:country":"IN",
    "name:bul_x_preferred":[
        "\u042e\u043a\u0441\u043e\u043c"
    ],
    "name:cat_x_preferred":[
        "Yuksom"
    ],
    "name:ceb_x_preferred":[
        "Yuksom"
    ],
    "name:cym_x_preferred":[
        "Yuksom"
    ],
    "name:deu_x_preferred":[
        "Yuksom"
    ],
    "name:eng_x_preferred":[
        "Yuksom"
    ],
    "name:fra_x_preferred":[
        "Yuksom"
    ],
    "name:hun_x_preferred":[
        "Yuksom"
    ],
    "name:ita_x_preferred":[
        "Yuksom"
    ],
    "name:jpn_x_preferred":[
        "\u30e8\u30af\u30b5\u30e0"
    ],
    "name:mal_x_preferred":[
        "\u0d2f\u0d41\u0d15\u0d4d\u0d38\u0d4b\u0d02"
    ],
    "name:nld_x_preferred":[
        "Yuksom"
    ],
    "name:pol_x_preferred":[
        "Yuksom"
    ],
    "name:por_x_preferred":[
        "Yuksom"
    ],
    "name:rus_x_preferred":[
        "\u042e\u043a\u0441\u043e\u043c"
    ],
    "name:spa_x_preferred":[
        "Yuksom"
    ],
    "name:swe_x_preferred":[
        "Yuksom"
    ],
    "name:ukr_x_preferred":[
        "\u042e\u043a\u0441\u043e\u043c"
    ],
    "name:urd_x_preferred":[
        "\u06cc\u06a9\u0633\u0648\u0645"
    ],
    "qs:name":"Yuksam",
    "qs:name_adm0":"India",
    "qs:name_adm1":"Sikkim",
    "qs:photos":269,
    "qs:photos_1k":55,
    "qs:photos_9k":1,
    "qs:photos_9r":4,
    "qs:photos_all":269,
    "qs:photos_sr":5,
    "qs:placetype":"Town",
    "qs:pop_sr":"0",
    "wd:wordcount":2139,
    "wof:name":"Yuksam",
    "wof:placetype":"locality"
},
  "geometry": {"coordinates":[88.234033,27.392878],"type":"Point"}
}