{
  "type": "Feature",
  "properties": {
    "iso:country":"IN",
    "qs:name":"Yuksam",
    "qs:name_adm0":"India",
    "qs:name_adm1":"Sikkim",
    "qs:photos":269,
    "qs:photos_1k":55,
    "qs:photos_9k":1,
    "qs:photos_9r":4,
    "qs:photos_all":269,
    "qs:photos_sr":5,
    "qs:placetype":"Town",
    "qs:pop_sr":"0",
    "wd:wordcount":2139,
    "wof:name":"Yuksam",
    "wof:placetype":"locality"
},
  "geometry": {"coordinates":[88.234033,27.392878],"type":"Point"}
}