{
  "type": "Feature",
  "properties": {
    "iso:country":"IN",
    "ks:ks_name":"Chaudiyar",
    "ks:ks_pop":791,
    "ks:ks_type":"HABITATION",
    "name:eng_x_preferred":[
        "Chaudiyar"
    ],
    "wof:name":"Chaudiyar",
    "wof:placetype":"locality",
    "wof:population":791
},
  "geometry": {"coordinates":[81.497795,24.484902],"type":"Point"}
}