{
  "type": "Feature",
  "properties": {
    "iso:country":"IN",
    "ks:ks_name":"Jayapur",
    "ks:ks_pop":187,
    "ks:ks_type":"VILLAGE",
    "name:eng_x_preferred":[
        "Jayapur"
    ],
    "wof:name":"Jayapur",
    "wof:placetype":"locality",
    "wof:population":187
},
  "geometry": {"coordinates":[85.127323,21.446631],"type":"Point"}
}