{
  "type": "Feature",
  "properties": {
    "iso:country":"IN",
    "ks:ks_name":"Tala Chhelianalo",
    "ks:ks_pop":138,
    "ks:ks_type":"HABITATION",
    "name:eng_x_preferred":[
        "Tala Chhelianalo"
    ],
    "wof:name":"Tala Chhelianalo",
    "wof:placetype":"locality",
    "wof:population":138
},
  "geometry": {"coordinates":[83.485876,19.65438],"type":"Point"}
}