{
  "type": "Feature",
  "properties": {
    "iso:country":"IN",
    "ks:ks_name":"Kandige",
    "ks:ks_pop":250,
    "ks:ks_type":"HABITATION",
    "name:eng_x_preferred":[
        "Kandige"
    ],
    "wof:name":"Kandige",
    "wof:placetype":"locality",
    "wof:population":250
},
  "geometry": {"coordinates":[75.129788,13.023144],"type":"Point"}
}