{
  "type": "Feature",
  "properties": {
    "iso:country":"IN",
    "ks:ks_name":"Thotadamane",
    "ks:ks_pop":19,
    "ks:ks_type":"HABITATION",
    "name:eng_x_preferred":[
        "Thotadamane"
    ],
    "wof:name":"Thotadamane",
    "wof:placetype":"locality",
    "wof:population":19
},
  "geometry": {"coordinates":[75.18419799999999,13.423985],"type":"Point"}
}