{
  "type": "Feature",
  "properties": {
    "iso:country":"IN",
    "ks:ks_alt_nam":"JANKAR WASTI",
    "ks:ks_name":"Jankar Wasti",
    "ks:ks_pop":120,
    "ks:ks_type":"HABITATION",
    "name:eng_x_preferred":[
        "Jankar Wasti"
    ],
    "wof:name":"Jankar Wasti",
    "wof:placetype":"locality",
    "wof:population":120
},
  "geometry": {"coordinates":[75.154338,17.071728],"type":"Point"}
}