{
  "type": "Feature",
  "properties": {
    "iso:country":"IN",
    "ks:ks_name":"Seelakarattur",
    "ks:ks_pop":390,
    "ks:ks_type":"HABITATION",
    "ks:ks_uagg_main":0,
    "name:eng_x_preferred":[
        "Seelakarattur"
    ],
    "wof:name":"Seelakarattur",
    "wof:placetype":"neighbourhood",
    "wof:population":390
},
  "geometry": {"coordinates":[78.009361,11.782837],"type":"Point"}
}