{
  "type": "Feature",
  "properties": {
    "iso:country":"IN",
    "ks:ks_name":"Tola Karka",
    "ks:ks_pop":0,
    "ks:ks_type":"VILLAGE",
    "name:eng_x_preferred":[
        "Tola Karka"
    ],
    "wof:name":"Tola Karka",
    "wof:placetype":"locality",
    "wof:population":0
},
  "geometry": {"coordinates":[86.509587,24.618999],"type":"Point"}
}