{
  "type": "Feature",
  "properties": {
    "iso:country":"IN",
    "ks:ks_alt_nam":"inchathal",
    "ks:ks_name":"Inchathal",
    "ks:ks_pop":251,
    "ks:ks_type":"HABITATION",
    "name:eng_x_preferred":[
        "Inchathal"
    ],
    "wof:name":"Inchathal",
    "wof:placetype":"locality",
    "wof:population":251
},
  "geometry": {"coordinates":[76.98722100000001,9.953889],"type":"Point"}
}