{
  "type": "Feature",
  "properties": {
    "gn:admin1_code":"19.0",
    "gn:admin2_code":"574.0",
    "gn:asciiname":"Kabbinahalli",
    "gn:country_code":"IN",
    "gn:dem":941,
    "gn:feature_class":"P",
    "gn:feature_code":"PPL",
    "gn:name":"Kabbinahalli",
    "gn:population":0,
    "gn:timezone":"Asia/Kolkata",
    "iso:country":"IN",
    "wof:name":"Kabbinahalli",
    "wof:placetype":"locality"
},
  "geometry": {"coordinates":[76.03256999999998,12.94422],"type":"Point"}
}