{
  "type": "Feature",
  "properties": {
    "gn:admin1_code":"21",
    "gn:admin2_code":"398.0",
    "gn:asciiname":"Mekalmetta",
    "gn:country_code":"IN",
    "gn:dem":1194,
    "gn:feature_class":"P",
    "gn:feature_code":"PPL",
    "gn:name":"Mekalmetta",
    "gn:population":0,
    "gn:timezone":"Asia/Kolkata",
    "iso:country":"IN",
    "wof:name":"Mekalmetta",
    "wof:placetype":"locality"
},
  "geometry": {"coordinates":[82.85663000000002,18.45107],"type":"Point"}
}