{
  "type": "Feature",
  "properties": {
    "gn:admin1_code":"36.0",
    "gn:admin2_code":"183.0",
    "gn:asciiname":"Munnipur",
    "gn:country_code":"IN",
    "gn:dem":104,
    "gn:feature_class":"P",
    "gn:feature_code":"PPL",
    "gn:name":"Munn\u012bpur",
    "gn:population":0,
    "gn:timezone":"Asia/Kolkata",
    "iso:country":"IN",
    "wof:name":"Munnipur",
    "wof:placetype":"locality"
},
  "geometry": {"coordinates":[82.22561,27.14431],"type":"Point"}
}