{
  "type": "Feature",
  "properties": {
    "iso:country":"IN",
    "ks:ks_name":"Bhagabatipur",
    "ks:ks_pop":2331,
    "ks:ks_type":"VILLAGE",
    "ks:ks_uagg_main":0,
    "name:eng_x_preferred":[
        "Bhagabatipur"
    ],
    "wof:name":"Bhagabatipur",
    "wof:placetype":"neighbourhood",
    "wof:population":2331
},
  "geometry": {"coordinates":[87.700149,23.824043],"type":"Point"}
}