{
  "type": "Feature",
  "properties": {
    "gn:admin1_code":"35",
    "gn:admin2_code":"430.0",
    "gn:asciiname":"Gambhirpurwa",
    "gn:country_code":"IN",
    "gn:dem":106,
    "gn:feature_class":"P",
    "gn:feature_code":"PPL",
    "gn:name":"Gambhirpurwa",
    "gn:population":0,
    "gn:timezone":"Asia/Kolkata",
    "iso:country":"IN",
    "wof:name":"Gambhirpurwa",
    "wof:placetype":"locality"
},
  "geometry": {"coordinates":[81.7436,24.98482000000001],"type":"Point"}
}