{
  "type": "Feature",
  "properties": {
    "gn:admin1_code":"19.0",
    "gn:admin2_code":"574.0",
    "gn:asciiname":"Hoshalli",
    "gn:country_code":"IN",
    "gn:dem":931,
    "gn:feature_class":"P",
    "gn:feature_code":"PPL",
    "gn:name":"Hoshalli",
    "gn:population":0,
    "gn:timezone":"Asia/Kolkata",
    "iso:country":"IN",
    "wof:name":"Hoshalli",
    "wof:placetype":"locality"
},
  "geometry": {"coordinates":[75.99278000000002,12.91674],"type":"Point"}
}