{
  "type": "Feature",
  "properties": {
    "iso:country":"IN",
    "ks:ks_alt_nam":"badalgora",
    "ks:ks_name":"Badalgora",
    "ks:ks_pop":465,
    "ks:ks_type":"HABITATION",
    "name:eng_x_preferred":[
        "Badalgora"
    ],
    "wof:name":"Badalgora",
    "wof:placetype":"locality",
    "wof:population":465
},
  "geometry": {"coordinates":[86.32593900000001,22.469662],"type":"Point"}
}