{
  "type": "Feature",
  "properties": {
    "iso:country":"IN",
    "ks:ks_name":"Chora",
    "ks:ks_pop":669,
    "ks:ks_type":"HABITATION",
    "name:eng_x_preferred":[
        "Chora"
    ],
    "wof:name":"Chora",
    "wof:placetype":"locality",
    "wof:population":669
},
  "geometry": {"coordinates":[73.961303,24.529394],"type":"Point"}
}