{
  "type": "Feature",
  "properties": {
    "gn:admin1_code":"34.0",
    "gn:admin2_code":"239.0",
    "gn:asciiname":"Bansi Bigha",
    "gn:country_code":"IN",
    "gn:dem":80,
    "gn:feature_class":"P",
    "gn:feature_code":"PPL",
    "gn:name":"Bansi Bigha",
    "gn:population":0,
    "gn:timezone":"Asia/Kolkata",
    "iso:country":"IN",
    "wof:name":"Bansi Bigha",
    "wof:placetype":"locality"
},
  "geometry": {"coordinates":[85.09681999999999,25.0846],"type":"Point"}
}