{
  "type": "Feature",
  "properties": {
    "iso:country":"IN",
    "ks:ks_name":"1 KNJ",
    "ks:ks_pop":1940,
    "ks:ks_type":"VILLAGE",
    "name:eng_x_preferred":[
        "1 KNJ"
    ],
    "wof:name":"1 KNJ",
    "wof:placetype":"locality",
    "wof:population":1940
},
  "geometry": {"coordinates":[74.266819,29.604136],"type":"Point"}
}