{
  "type": "Feature",
  "properties": {
    "gn:admin1_code":"36.0",
    "gn:admin2_code":"174.0",
    "gn:asciiname":"Makhdumpur Doksaha",
    "gn:country_code":"IN",
    "gn:dem":106,
    "gn:feature_class":"P",
    "gn:feature_code":"PPL",
    "gn:name":"Makhd\u016bmpur Doks\u0101ha",
    "gn:population":0,
    "gn:timezone":"Asia/Kolkata",
    "iso:country":"IN",
    "ks:ks_name":"Makadumpur Dhokasaha",
    "ks:ks_pop":2057,
    "ks:ks_type":"VILLAGE",
    "name:eng_x_preferred":[
        "Makadumpur Dhokasaha"
    ],
    "name:eng_x_variant":[
        "Makhdumpur Doksaha"
    ],
    "wof:name":"Makadumpur Dhokasaha",
    "wof:placetype":"locality",
    "wof:population":2057
},
  "geometry": {"coordinates":[81.420503,25.348396],"type":"Point"}
}