{
  "type": "Feature",
  "properties": {
    "gn:admin1_code":"36.0",
    "gn:admin2_code":"174.0",
    "gn:asciiname":"Makhdumpur Doksaha",
    "gn:country_code":"IN",
    "gn:dem":106,
    "gn:feature_class":"P",
    "gn:feature_code":"PPL",
    "gn:name":"Makhd\u016bmpur Doks\u0101ha",
    "gn:population":0,
    "gn:timezone":"Asia/Kolkata",
    "iso:country":"IN",
    "wof:name":"Makhdumpur Doksaha",
    "wof:placetype":"locality"
},
  "geometry": {"coordinates":[81.42531,25.34739],"type":"Point"}
}