{
  "type": "Feature",
  "properties": {
    "iso:country":"IN",
    "ks:ks_name":"Sindhupali",
    "ks:ks_pop":102,
    "ks:ks_type":"VILLAGE",
    "name:eng_x_preferred":[
        "Sindhupali"
    ],
    "wof:name":"Sindhupali",
    "wof:placetype":"locality",
    "wof:population":102
},
  "geometry": {"coordinates":[84.69136,21.38254],"type":"Point"}
}