{
  "type": "Feature",
  "properties": {
    "iso:country":"IN",
    "ks:ks_alt_nam":"Abuchani chamrut",
    "ks:ks_name":"Abuchani Chamrut",
    "ks:ks_pop":200,
    "ks:ks_type":"HABITATION",
    "name:eng_x_preferred":[
        "Abuchani Chamrut"
    ],
    "wof:name":"Abuchani Chamrut",
    "wof:placetype":"locality",
    "wof:population":200
},
  "geometry": {"coordinates":[81.90163800000001,25.57757],"type":"Point"}
}