{
  "type": "Feature",
  "properties": {
    "iso:country":"IN",
    "ks:ks_name":"Patharia",
    "ks:ks_pop":960,
    "ks:ks_type":"HABITATION",
    "name:eng_x_preferred":[
        "Patharia"
    ],
    "wof:name":"Patharia",
    "wof:placetype":"locality",
    "wof:population":960
},
  "geometry": {"coordinates":[87.01263899999999,24.67929],"type":"Point"}
}