{
  "type": "Feature",
  "properties": {
    "iso:country":"IN",
    "ks:ks_name":"Arihan",
    "ks:ks_pop":403,
    "ks:ks_type":"HABITATION",
    "name:eng_x_preferred":[
        "Arihan"
    ],
    "wof:name":"Arihan",
    "wof:placetype":"locality",
    "wof:population":403
},
  "geometry": {"coordinates":[82.450574,25.176832],"type":"Point"}
}