{
  "type": "Feature",
  "properties": {
    "iso:country":"IN",
    "ks:ks_alt_nam":"Bhalulata basti",
    "ks:ks_name":"Bhalulata Basti",
    "ks:ks_pop":712,
    "ks:ks_type":"HABITATION",
    "name:eng_x_preferred":[
        "Bhalulata Basti"
    ],
    "wof:name":"Bhalulata Basti",
    "wof:placetype":"locality",
    "wof:population":712
},
  "geometry": {"coordinates":[84.980076,22.249232],"type":"Point"}
}