{
  "type": "Feature",
  "properties": {
    "gn:admin1_code":"11",
    "gn:admin2_code":"23.0",
    "gn:asciiname":"Balot",
    "gn:country_code":"IN",
    "gn:dem":1180,
    "gn:feature_class":"P",
    "gn:feature_code":"PPL",
    "gn:name":"Balot",
    "gn:population":0,
    "gn:timezone":"Asia/Kolkata",
    "iso:country":"IN",
    "name:ceb_x_preferred":[
        "Balot"
    ],
    "name:pol_x_preferred":[
        "Balot"
    ],
    "wof:name":"Balot",
    "wof:placetype":"locality"
},
  "geometry": {"coordinates":[76.35748000000002,32.49694],"type":"Point"}
}