{
  "type": "Feature",
  "properties": {
    "iso:country":"IN",
    "ks:ks_name":"Malakavaripalli Eguvathanda",
    "ks:ks_pop":596,
    "ks:ks_type":"HABITATION",
    "name:eng_x_preferred":[
        "Malakavaripalli Eguvathanda"
    ],
    "wof:name":"Malakavaripalli Eguvathanda",
    "wof:placetype":"locality",
    "wof:population":596
},
  "geometry": {"coordinates":[78.081216,13.941366],"type":"Point"}
}