{
  "type": "Feature",
  "properties": {
    "iso:country":"IN",
    "ks:ks_name":"Garudaiahanapalya",
    "ks:ks_pop":242,
    "ks:ks_type":"HABITATION",
    "name:eng_x_preferred":[
        "Garudaiahanapalya"
    ],
    "wof:name":"Garudaiahanapalya",
    "wof:placetype":"locality",
    "wof:population":242
},
  "geometry": {"coordinates":[76.987441,13.224682],"type":"Point"}
}