{
  "type": "Feature",
  "properties": {
    "iso:country":"IN",
    "ks:ks_name":"Korkuti",
    "ks:ks_pop":45,
    "ks:ks_type":"VILLAGE",
    "name:eng_x_preferred":[
        "Korkuti"
    ],
    "wof:name":"Korkuti",
    "wof:placetype":"locality",
    "wof:population":45
},
  "geometry": {"coordinates":[80.247786,19.959764],"type":"Point"}
}