{
  "type": "Feature",
  "properties": {
    "iso:country":"IN",
    "ks:ks_name":"Makka Nivada",
    "ks:ks_pop":512,
    "ks:ks_type":"HABITATION",
    "name:eng_x_preferred":[
        "Makka Nivada"
    ],
    "wof:name":"Makka Nivada",
    "wof:placetype":"locality",
    "wof:population":512
},
  "geometry": {"coordinates":[79.93651,26.668638],"type":"Point"}
}