{
  "type": "Feature",
  "properties": {
    "gn:admin1_code":"23.0",
    "gn:admin2_code":"43.0",
    "gn:asciiname":"Hanumangarh",
    "gn:country_code":"IN",
    "gn:dem":190,
    "gn:feature_class":"P",
    "gn:feature_code":"PPL",
    "gn:name":"Hanum\u0101ngarh",
    "gn:population":0,
    "gn:timezone":"Asia/Kolkata",
    "iso:country":"IN",
    "name:und_x_variant":[
        "Hanum\u0101ngarh",
        "Burj\u0101n"
    ],
    "wof:name":"Hanumangarh",
    "wof:placetype":"locality"
},
  "geometry": {"coordinates":[74.24321999999999,30.30356],"type":"Point"}
}