{
  "type": "Feature",
  "properties": {
    "iso:country":"IN",
    "ks:ks_name":"Kumhraula",
    "ks:ks_pop":76,
    "ks:ks_type":"VILLAGE",
    "name:eng_x_preferred":[
        "Kumhraula"
    ],
    "wof:name":"Kumhraula",
    "wof:placetype":"locality",
    "wof:population":76
},
  "geometry": {"coordinates":[80.89906000000001,24.762504],"type":"Point"}
}