{
  "type": "Feature",
  "properties": {
    "gn:admin1_code":"16.0",
    "gn:admin2_code":"499.0",
    "gn:asciiname":"Hanmanthkheda Budrukh",
    "gn:country_code":"IN",
    "gn:dem":235,
    "gn:feature_class":"P",
    "gn:feature_code":"PPL",
    "gn:name":"Hanmanthkheda Budr\u016bkh",
    "gn:population":0,
    "gn:timezone":"Asia/Kolkata",
    "iso:country":"IN",
    "wof:name":"Hanmanthkheda Budrukh",
    "wof:placetype":"locality"
},
  "geometry": {"coordinates":[75.29727,20.86892000000001],"type":"Point"}
}