{
  "type": "Feature",
  "properties": {
    "gn:admin1_code":"35.0",
    "gn:admin2_code":"457.0",
    "gn:asciiname":"Eko",
    "gn:country_code":"IN",
    "gn:dem":603,
    "gn:feature_class":"P",
    "gn:feature_code":"PPL",
    "gn:name":"Eko",
    "gn:population":0,
    "gn:timezone":"Asia/Kolkata",
    "iso:country":"IN",
    "wof:name":"Eko",
    "wof:placetype":"locality"
},
  "geometry": {"coordinates":[80.52523000000002,21.76046],"type":"Point"}
}