{
  "type": "Feature",
  "properties": {
    "gn:admin1_code":"28.0",
    "gn:admin2_code":"333.0",
    "gn:asciiname":"Dahina",
    "gn:country_code":"IN",
    "gn:dem":29,
    "gn:feature_class":"P",
    "gn:feature_code":"PPL",
    "gn:name":"D\u0101hina",
    "gn:population":0,
    "gn:timezone":"Asia/Kolkata",
    "iso:country":"IN",
    "ks:ks_alt_nam":"D\u0101hina",
    "ks:ks_name":"Dahina",
    "ks:ks_pop":1685,
    "ks:ks_type":"VILLAGE",
    "ks:ks_uagg_main":0,
    "name:eng_x_preferred":[
        "Dahina"
    ],
    "name:eng_x_variant":[
        "D\u0101hina"
    ],
    "wof:name":"Dahina",
    "wof:placetype":"neighbourhood",
    "wof:population":1685
},
  "geometry": {"coordinates":[87.981624,24.522437],"type":"Point"}
}