{
  "type": "Feature",
  "properties": {
    "iso:country":"IN",
    "ks:ks_name":"Holeswar Devalaya",
    "ks:ks_pop":1016,
    "ks:ks_type":"VILLAGE",
    "ks:ks_uagg_main":0,
    "name:eng_x_preferred":[
        "Holeswar Devalaya"
    ],
    "wof:name":"Holeswar Devalaya",
    "wof:placetype":"locality",
    "wof:population":1016
},
  "geometry": {"coordinates":[92.767055,26.708169],"type":"Point"}
}