{
  "type": "Feature",
  "properties": {
    "gn:admin1_code":"39",
    "gn:admin2_code":"60.0",
    "gn:asciiname":"Mohana Chak",
    "gn:country_code":"IN",
    "gn:dem":2075,
    "gn:feature_class":"P",
    "gn:feature_code":"PPL",
    "gn:name":"Mohana Chak",
    "gn:population":0,
    "gn:timezone":"Asia/Kolkata",
    "iso:country":"IN",
    "wof:name":"Mohana Chak",
    "wof:placetype":"locality"
},
  "geometry": {"coordinates":[77.91586,30.80568],"type":"Point"}
}