{
  "type": "Feature",
  "properties": {
    "gn:admin1_code":"34.0",
    "gn:admin2_code":"209.0",
    "gn:asciiname":"Asura Kalan Khola",
    "gn:country_code":"IN",
    "gn:dem":70,
    "gn:feature_class":"P",
    "gn:feature_code":"PPL",
    "gn:name":"Asura Kal\u0101n Khola",
    "gn:population":0,
    "gn:timezone":"Asia/Kolkata",
    "iso:country":"IN",
    "ks:ks_alt_nam":"Asura Kal\u0101n Khola",
    "ks:ks_name":"Asura Kalan Khola",
    "ks:ks_pop":2341,
    "ks:ks_type":"VILLAGE",
    "ks:ks_uagg_main":0,
    "name:eng_x_preferred":[
        "Asura Kalan Khola"
    ],
    "name:eng_x_variant":[
        "Asura Kal\u0101n Khola"
    ],
    "wof:name":"Asura Kalan Khola",
    "wof:placetype":"neighbourhood",
    "wof:population":2341
},
  "geometry": {"coordinates":[87.44486499999999,26.424805],"type":"Point"}
}