{
  "type": "Feature",
  "properties": {
    "gn:admin1_code":"19.0",
    "gn:admin2_code":"567.0",
    "gn:asciiname":"Alur",
    "gn:country_code":"IN",
    "gn:dem":608,
    "gn:feature_class":"P",
    "gn:feature_code":"PPL",
    "gn:name":"\u0100lur",
    "gn:population":0,
    "gn:timezone":"Asia/Kolkata",
    "iso:country":"IN",
    "ks:ks_alt_nam":"\u0100lur",
    "ks:ks_name":"Alur",
    "ks:ks_pop":1321,
    "ks:ks_type":"VILLAGE",
    "name:eng_x_preferred":[
        "Alur"
    ],
    "name:eng_x_variant":[
        "\u0100lur"
    ],
    "name:fra_x_preferred":[
        "Alur"
    ],
    "name:ita_x_preferred":[
        "Alur"
    ],
    "name:nor_x_preferred":[
        "Alur"
    ],
    "name:rus_x_preferred":[
        "\u0410\u043b\u0443\u0440"
    ],
    "wof:name":"Alur",
    "wof:placetype":"locality",
    "wof:population":1321
},
  "geometry": {"coordinates":[75.92941,14.193063],"type":"Point"}
}