{
  "type": "Feature",
  "properties": {
    "iso:country":"IN",
    "ks:ks_name":"Chhota Supaisai",
    "ks:ks_pop":0,
    "ks:ks_type":"VILLAGE",
    "name:eng_x_preferred":[
        "Chhota Supaisai"
    ],
    "wof:name":"Chhota Supaisai",
    "wof:placetype":"locality",
    "wof:population":0
},
  "geometry": {"coordinates":[85.712166,22.726063],"type":"Point"}
}