{
  "type": "Feature",
  "properties": {
    "gn:admin1_code":"23.0",
    "gn:admin2_code":"40.0",
    "gn:asciiname":"Mansurpur",
    "gn:country_code":"IN",
    "gn:dem":276,
    "gn:feature_class":"P",
    "gn:feature_code":"PPL",
    "gn:name":"Mans\u016brpur",
    "gn:population":0,
    "gn:timezone":"Asia/Kolkata",
    "iso:country":"IN",
    "wof:name":"Mansurpur",
    "wof:placetype":"locality"
},
  "geometry": {"coordinates":[76.34106,30.83592],"type":"Point"}
}