{
  "type": "Feature",
  "properties": {
    "iso:country":"IN",
    "ks:ks_name":"Chhota Kukra Aul",
    "ks:ks_pop":921,
    "ks:ks_type":"VILLAGE",
    "name:eng_x_preferred":[
        "Chhota Kukra Aul"
    ],
    "wof:name":"Chhota Kukra Aul",
    "wof:placetype":"locality",
    "wof:population":921
},
  "geometry": {"coordinates":[87.797437,21.823071],"type":"Point"}
}