{
  "type": "Feature",
  "properties": {
    "iso:country":"IN",
    "ks:ks_name":"Dandi",
    "ks:ks_pop":155,
    "ks:ks_type":"VILLAGE",
    "name:eng_x_preferred":[
        "Dandi"
    ],
    "wof:name":"Dandi",
    "wof:placetype":"locality",
    "wof:population":155
},
  "geometry": {"coordinates":[78.322109,30.477243],"type":"Point"}
}