{
  "type": "Feature",
  "properties": {
    "gn:admin1_code":"36",
    "gn:admin2_code":"171.0",
    "gn:asciiname":"Chilla Muafi",
    "gn:country_code":"IN",
    "gn:dem":123,
    "gn:feature_class":"P",
    "gn:feature_code":"PPL",
    "gn:name":"Chilla Mu\u0101f\u012b",
    "gn:population":0,
    "gn:timezone":"Asia/Kolkata",
    "iso:country":"IN",
    "wof:name":"Chilla Muafi",
    "wof:placetype":"locality"
},
  "geometry": {"coordinates":[80.89941999999998,25.32202],"type":"Point"}
}