{
  "type": "Feature",
  "properties": {
    "iso:country":"IN",
    "ks:ks_name":"Kamalpur",
    "ks:ks_pop":818,
    "ks:ks_type":"VILLAGE",
    "ks:ks_uagg_main":0,
    "name:eng_x_preferred":[
        "Kamalpur"
    ],
    "wof:name":"Kamalpur",
    "wof:placetype":"neighbourhood",
    "wof:population":818
},
  "geometry": {"coordinates":[85.04444599999999,24.801872],"type":"Point"}
}