{
  "type": "Feature",
  "properties": {
    "gn:admin1_code":"36.0",
    "gn:admin2_code":"193.0",
    "gn:asciiname":"Pritam Chhapra",
    "gn:country_code":"IN",
    "gn:dem":63,
    "gn:feature_class":"P",
    "gn:feature_code":"PPL",
    "gn:name":"Pritam Chhapra",
    "gn:population":0,
    "gn:timezone":"Asia/Kolkata",
    "iso:country":"IN",
    "wof:name":"Pritam Chhapra",
    "wof:placetype":"locality"
},
  "geometry": {"coordinates":[84.51815999999999,25.75936],"type":"Point"}
}