{
  "type": "Feature",
  "properties": {
    "iso:country":"IN",
    "ks:ks_name":"Saradahikore",
    "ks:ks_pop":292,
    "ks:ks_type":"VILLAGE",
    "name:eng_x_preferred":[
        "Saradahikore"
    ],
    "wof:name":"Saradahikore",
    "wof:placetype":"locality",
    "wof:population":292
},
  "geometry": {"coordinates":[85.67361699999999,20.600676],"type":"Point"}
}