{
  "type": "Feature",
  "properties": {
    "gn:admin1_code":"25.0",
    "gn:admin2_code":"620.0",
    "gn:asciiname":"Kadakadappai",
    "gn:country_code":"IN",
    "gn:dem":42,
    "gn:feature_class":"P",
    "gn:feature_code":"PPL",
    "gn:name":"Kadakadappai",
    "gn:population":0,
    "gn:timezone":"Asia/Kolkata",
    "iso:country":"IN",
    "ks:ks_name":"Kadakadappai",
    "ks:ks_pop":387,
    "ks:ks_type":"VILLAGE",
    "name:eng_x_preferred":[
        "Kadakadappai"
    ],
    "name:tam_x_preferred":[
        "\u0b95\u0b9f\u0b95\u0ba4\u0baa\u0bcd\u0baa\u0bc8"
    ],
    "wof:name":"Kadakadappai",
    "wof:placetype":"locality",
    "wof:population":387
},
  "geometry": {"coordinates":[79.17571599999999,10.798701],"type":"Point"}
}