{
  "type": "Feature",
  "properties": {
    "gn:admin1_code":"34.0",
    "gn:admin2_code":"218.0",
    "gn:asciiname":"Rimafat Chhapra",
    "gn:country_code":"IN",
    "gn:dem":68,
    "gn:feature_class":"P",
    "gn:feature_code":"PPL",
    "gn:name":"Rimafat Chh\u0101pra",
    "gn:population":0,
    "gn:timezone":"Asia/Kolkata",
    "iso:country":"IN",
    "ks:ks_alt_nam":"Rimafat Chh\u0101pra",
    "ks:ks_name":"Rimafat Chhapra",
    "ks:ks_type":"VILLAGE",
    "ks:ks_uagg_main":0,
    "name:eng_x_preferred":[
        "Rimafat Chhapra"
    ],
    "name:eng_x_variant":[
        "Rimafat Chh\u0101pra"
    ],
    "wof:name":"Rimafat Chhapra",
    "wof:placetype":"neighbourhood"
},
  "geometry": {"coordinates":[84.11325600000001,26.19385],"type":"Point"}
}