{
  "type": "Feature",
  "properties": {
    "iso:country":"IN",
    "ks:ks_alt_nam":"ADDA NIHAL",
    "ks:ks_name":"Adda Nihal",
    "ks:ks_pop":305,
    "ks:ks_type":"HABITATION",
    "name:eng_x_preferred":[
        "Adda Nihal"
    ],
    "wof:name":"Adda Nihal",
    "wof:placetype":"locality",
    "wof:population":305
},
  "geometry": {"coordinates":[79.052761,26.767333],"type":"Point"}
}