{
  "type": "Feature",
  "properties": {
    "iso:country":"IN",
    "ks:ks_alt_nam":"makkimanne",
    "ks:ks_name":"Makkimanne",
    "ks:ks_pop":76,
    "ks:ks_type":"HABITATION",
    "name:eng_x_preferred":[
        "Makkimanne"
    ],
    "wof:name":"Makkimanne",
    "wof:placetype":"locality",
    "wof:population":76
},
  "geometry": {"coordinates":[75.18665799999999,13.474849],"type":"Point"}
}