{
  "type": "Feature",
  "properties": {
    "gn:admin1_code":"36.0",
    "gn:admin2_code":"179.0",
    "gn:asciiname":"Basantpur",
    "gn:country_code":"IN",
    "gn:dem":95,
    "gn:feature_class":"P",
    "gn:feature_code":"PPL",
    "gn:name":"Basantpur",
    "gn:population":0,
    "gn:timezone":"Asia/Kolkata",
    "iso:country":"IN",
    "name:pol_x_preferred":[
        "Basantpur"
    ],
    "wof:name":"Basantpur",
    "wof:placetype":"locality"
},
  "geometry": {"coordinates":[81.97679000000002,26.41101],"type":"Point"}
}