{
  "type": "Feature",
  "properties": {
    "gn:admin1_code":"2",
    "gn:admin2_code":"548.0",
    "gn:asciiname":"Annavaram",
    "gn:country_code":"IN",
    "gn:dem":22,
    "gn:feature_class":"P",
    "gn:feature_code":"PPL",
    "gn:name":"Annavaram",
    "gn:population":0,
    "gn:timezone":"Asia/Kolkata",
    "iso:country":"IN",
    "name:ceb_x_preferred":[
        "Annavaram"
    ],
    "name:msa_x_preferred":[
        "Annavaram"
    ],
    "name:ori_x_preferred":[
        "\u0b06\u0b28\u0b4d\u0b28\u0b3e\u0b2d\u0b30\u0b2e \u0b2e\u0b28\u0b4d\u0b26\u0b3f\u0b30"
    ],
    "name:por_x_preferred":[
        "Annavaram"
    ],
    "name:swe_x_preferred":[
        "Annavaram"
    ],
    "name:tel_x_preferred":[
        "\u0c05\u0c28\u0c4d\u0c28\u0c35\u0c30\u0c02"
    ],
    "name:urd_x_preferred":[
        "\u0627\u0646\u0627\u0648\u0627\u0631\u0627\u0645"
    ],
    "wof:name":"Annavaram",
    "wof:placetype":"locality"
},
  "geometry": {"coordinates":[80.26698,16.08762999999999],"type":"Point"}
}