{
  "type": "Feature",
  "properties": {
    "iso:country":"IN",
    "ks:ks_name":"Mettukollai",
    "ks:ks_pop":107,
    "ks:ks_type":"HABITATION",
    "name:eng_x_preferred":[
        "Mettukollai"
    ],
    "wof:name":"Mettukollai",
    "wof:placetype":"locality",
    "wof:population":107
},
  "geometry": {"coordinates":[79.794608,12.567193],"type":"Point"}
}