{
  "type": "Feature",
  "properties": {
    "iso:country":"IN",
    "ks:ks_name":"No.1 Amguri",
    "ks:ks_pop":375,
    "ks:ks_type":"VILLAGE",
    "name:eng_x_preferred":[
        "No.1 Amguri"
    ],
    "wof:name":"No.1 Amguri",
    "wof:placetype":"locality",
    "wof:population":375
},
  "geometry": {"coordinates":[94.636771,27.441384],"type":"Point"}
}