{
  "type": "Feature",
  "properties": {
    "iso:country":"IN",
    "ks:ks_name":"Jhulendihi",
    "ks:ks_pop":251,
    "ks:ks_type":"VILLAGE",
    "name:eng_x_preferred":[
        "Jhulendihi"
    ],
    "wof:name":"Jhulendihi",
    "wof:placetype":"locality",
    "wof:population":251
},
  "geometry": {"coordinates":[83.872668,22.06797],"type":"Point"}
}