{
  "type": "Feature",
  "properties": {
    "iso:country":"IN",
    "ks:ks_name":"Gavalwadi",
    "ks:ks_pop":254,
    "ks:ks_type":"HABITATION",
    "name:eng_x_preferred":[
        "Gavalwadi"
    ],
    "wof:name":"Gavalwadi",
    "wof:placetype":"locality",
    "wof:population":254
},
  "geometry": {"coordinates":[73.31546899999999,17.828067],"type":"Point"}
}