{
  "type": "Feature",
  "properties": {
    "iso:country":"IN",
    "ks:ks_alt_nam":"GODARON KI DHANI",
    "ks:ks_name":"Godaron Ki Dhani",
    "ks:ks_pop":120,
    "ks:ks_type":"HABITATION",
    "name:eng_x_preferred":[
        "Godaron Ki Dhani"
    ],
    "wof:name":"Godaron Ki Dhani",
    "wof:placetype":"locality",
    "wof:population":120
},
  "geometry": {"coordinates":[71.457464,26.190919],"type":"Point"}
}