{
  "type": "Feature",
  "properties": {
    "iso:country":"IN",
    "ks:ks_name":"Senthal",
    "ks:ks_pop":624,
    "ks:ks_type":"VILLAGE",
    "name:eng_x_preferred":[
        "Senthal"
    ],
    "wof:name":"Senthal",
    "wof:placetype":"locality",
    "wof:population":624
},
  "geometry": {"coordinates":[73.82343299999999,24.092894],"type":"Point"}
}