{
  "type": "Feature",
  "properties": {
    "gn:admin1_code":"16",
    "gn:admin2_code":"516.0",
    "gn:asciiname":"Saptashring",
    "gn:country_code":"IN",
    "gn:dem":1149,
    "gn:feature_class":"P",
    "gn:feature_code":"PPL",
    "gn:name":"Saptashring",
    "gn:population":0,
    "gn:timezone":"Asia/Kolkata",
    "iso:country":"IN",
    "name:und_x_variant":[
        "Saptasring",
        "Saptashring"
    ],
    "wof:name":"Saptashring",
    "wof:placetype":"neighbourhood"
},
  "geometry": {"coordinates":[73.90961,20.39022],"type":"Point"}
}