{
  "type": "Feature",
  "properties": {
    "iso:country":"IN",
    "ks:ks_name":"Khajuriguda",
    "ks:ks_pop":253,
    "ks:ks_type":"HABITATION",
    "name:eng_x_preferred":[
        "Khajuriguda"
    ],
    "wof:name":"Khajuriguda",
    "wof:placetype":"locality",
    "wof:population":253
},
  "geometry": {"coordinates":[82.884366,19.03203],"type":"Point"}
}