{
  "type": "Feature",
  "properties": {
    "gn:admin1_code":"12.0",
    "gn:admin2_code":"18.0",
    "gn:asciiname":"Bejmandu",
    "gn:country_code":"IN",
    "gn:dem":2921,
    "gn:feature_class":"P",
    "gn:feature_code":"PPL",
    "gn:name":"Bejmandu",
    "gn:population":0,
    "gn:timezone":"Asia/Kolkata",
    "iso:country":"IN",
    "wof:name":"Bejmandu",
    "wof:placetype":"locality"
},
  "geometry": {"coordinates":[75.64188,33.47170999999999],"type":"Point"}
}