{
  "type": "Feature",
  "properties": {
    "gn:admin1_code":"36",
    "gn:admin2_code":"183.0",
    "gn:asciiname":"Subhagpur",
    "gn:country_code":"IN",
    "gn:dem":114,
    "gn:feature_class":"P",
    "gn:feature_code":"PPL",
    "gn:name":"Subh\u0101gpur",
    "gn:population":0,
    "gn:timezone":"Asia/Kolkata",
    "iso:country":"IN",
    "wof:name":"Subhagpur",
    "wof:placetype":"locality"
},
  "geometry": {"coordinates":[81.98835,27.20506],"type":"Point"}
}