{
  "type": "Feature",
  "properties": {
    "gn:admin1_code":"13.0",
    "gn:admin2_code":"601.0",
    "gn:asciiname":"Kavalur",
    "gn:country_code":"IN",
    "gn:dem":31,
    "gn:feature_class":"P",
    "gn:feature_code":"PPL",
    "gn:name":"Kaval\u016br",
    "gn:population":0,
    "gn:timezone":"Asia/Kolkata",
    "iso:country":"IN",
    "name:ceb_x_preferred":[
        "Kaval\u016br"
    ],
    "name:fra_x_preferred":[
        "Kavalur"
    ],
    "name:swe_x_preferred":[
        "Kaval\u016br"
    ],
    "name:tam_x_preferred":[
        "\u0b95\u0bbe\u0bb5\u0bb2\u0bc2\u0bb0\u0bcd"
    ],
    "wof:name":"Kavalur",
    "wof:placetype":"locality"
},
  "geometry": {"coordinates":[76.78466,8.71885],"type":"Point"}
}