{
  "type": "Feature",
  "properties": {
    "iso:country":"IN",
    "ks:ks_name":"Bhatwadi",
    "ks:ks_pop":25,
    "ks:ks_type":"HABITATION",
    "name:eng_x_preferred":[
        "Bhatwadi"
    ],
    "wof:name":"Bhatwadi",
    "wof:placetype":"locality",
    "wof:population":25
},
  "geometry": {"coordinates":[73.754037,16.222439],"type":"Point"}
}