{
  "type": "Feature",
  "properties": {
    "iso:country":"IN",
    "ks:ks_name":"Parsaniya",
    "ks:ks_pop":214,
    "ks:ks_type":"HABITATION",
    "name:eng_x_preferred":[
        "Parsaniya"
    ],
    "wof:name":"Parsaniya",
    "wof:placetype":"locality",
    "wof:population":214
},
  "geometry": {"coordinates":[84.365291,23.521782],"type":"Point"}
}