{
  "type": "Feature",
  "properties": {
    "gn:admin1_code":"3.0",
    "gn:admin2_code":"302",
    "gn:asciiname":"Dudhnai",
    "gn:country_code":"IN",
    "gn:dem":55,
    "gn:feature_class":"P",
    "gn:feature_code":"PPL",
    "gn:name":"Dudhnai",
    "gn:population":0,
    "gn:timezone":"Asia/Kolkata",
    "iso:country":"IN",
    "wof:name":"Dudhnai",
    "wof:placetype":"neighbourhood"
},
  "geometry": {"coordinates":[90.78207999999999,25.98283],"type":"Point"}
}