{
  "type": "Feature",
  "properties": {
    "iso:country":"IN",
    "ks:ks_alt_nam":"K\u0101juri",
    "ks:ks_name":"Kajuri",
    "ks:ks_type":"VILLAGE",
    "name:eng_x_preferred":[
        "Kajuri"
    ],
    "name:eng_x_variant":[
        "K\u0101juri"
    ],
    "wof:name":"Kajuri",
    "wof:placetype":"locality"
},
  "geometry": {"coordinates":[84.22115100000001,20.030338],"type":"Point"}
}