{
  "type": "Feature",
  "properties": {
    "gn:admin1_code":"36",
    "gn:admin2_code":"188.0",
    "gn:asciiname":"Dusi",
    "gn:country_code":"IN",
    "gn:dem":84,
    "gn:feature_class":"P",
    "gn:feature_code":"PPL",
    "gn:name":"D\u016bsi",
    "gn:population":0,
    "gn:timezone":"Asia/Kolkata",
    "iso:country":"IN",
    "name:ceb_x_preferred":[
        "Dusi"
    ],
    "name:swe_x_preferred":[
        "Dusi"
    ],
    "wof:name":"Dusi",
    "wof:placetype":"locality"
},
  "geometry": {"coordinates":[83.40666999999998,26.92875],"type":"Point"}
}