{
  "type": "Feature",
  "properties": {
    "iso:country":"IN",
    "ks:ks_name":"Pitchiguntapallli",
    "ks:ks_pop":152,
    "ks:ks_type":"HABITATION",
    "name:eng_x_preferred":[
        "Pitchiguntapallli"
    ],
    "wof:name":"Pitchiguntapallli",
    "wof:placetype":"locality",
    "wof:population":152
},
  "geometry": {"coordinates":[78.836401,14.137975],"type":"Point"}
}