{
  "type": "Feature",
  "properties": {
    "iso:country":"IN",
    "ks:ks_name":"Chittemputtu",
    "ks:ks_pop":88,
    "ks:ks_type":"HABITATION",
    "name:eng_x_preferred":[
        "Chittemputtu"
    ],
    "wof:name":"Chittemputtu",
    "wof:placetype":"locality",
    "wof:population":88
},
  "geometry": {"coordinates":[82.440307,18.045979],"type":"Point"}
}