{
  "type": "Feature",
  "properties": {
    "gn:admin1_code":"24.0",
    "gn:admin2_code":"116",
    "gn:asciiname":"Ghana",
    "gn:country_code":"IN",
    "gn:dem":164,
    "gn:feature_class":"P",
    "gn:feature_code":"PPL",
    "gn:name":"Gh\u0101na",
    "gn:population":0,
    "gn:timezone":"Asia/Kolkata",
    "iso:country":"IN",
    "name:und_x_variant":[
        "Gh\u0101na",
        "Ghona"
    ],
    "wof:name":"Ghana",
    "wof:placetype":"locality"
},
  "geometry": {"coordinates":[72.82292,25.75661],"type":"Point"}
}