{
  "type": "Feature",
  "properties": {
    "gn:admin1_code":"34.0",
    "gn:admin2_code":"229.0",
    "gn:asciiname":"Pawa",
    "gn:country_code":"IN",
    "gn:dem":69,
    "gn:feature_class":"P",
    "gn:feature_code":"PPL",
    "gn:name":"P\u0101wa",
    "gn:population":0,
    "gn:timezone":"Asia/Kolkata",
    "iso:country":"IN",
    "name:ceb_x_preferred":[
        "Pawa"
    ],
    "name:deu_x_preferred":[
        "Pawa"
    ],
    "wof:name":"Pawa",
    "wof:placetype":"locality"
},
  "geometry": {"coordinates":[85.55253,25.1129],"type":"Point"}
}