{
  "type": "Feature",
  "properties": {
    "iso:country":"IN",
    "ks:ks_name":"Kundalamkuzhi",
    "ks:ks_pop":301,
    "ks:ks_type":"HABITATION",
    "name:eng_x_preferred":[
        "Kundalamkuzhi"
    ],
    "wof:name":"Kundalamkuzhi",
    "wof:placetype":"locality",
    "wof:population":301
},
  "geometry": {"coordinates":[77.078818,8.697951],"type":"Point"}
}