{
  "type": "Feature",
  "properties": {
    "iso:country":"IN",
    "ks:ks_name":"Gandabandaurf Baijkot",
    "ks:ks_pop":84,
    "ks:ks_type":"HABITATION",
    "name:eng_x_preferred":[
        "Gandabandaurf Baijkot"
    ],
    "wof:name":"Gandabandaurf Baijkot",
    "wof:placetype":"locality",
    "wof:population":84
},
  "geometry": {"coordinates":[78.371641,30.662899],"type":"Point"}
}