{
  "type": "Feature",
  "properties": {
    "iso:country":"IN",
    "ks:ks_name":"Kailhai",
    "ks:ks_pop":202,
    "ks:ks_type":"HABITATION",
    "name:eng_x_preferred":[
        "Kailhai"
    ],
    "wof:name":"Kailhai",
    "wof:placetype":"locality",
    "wof:population":202
},
  "geometry": {"coordinates":[79.51295399999999,27.554564],"type":"Point"}
}