{
  "type": "Feature",
  "properties": {
    "iso:country":"IN",
    "ks:ks_name":"Paschim Kolobari",
    "ks:ks_pop":60,
    "ks:ks_type":"HABITATION",
    "name:eng_x_preferred":[
        "Paschim Kolobari"
    ],
    "wof:name":"Paschim Kolobari",
    "wof:placetype":"locality",
    "wof:population":60
},
  "geometry": {"coordinates":[90.128145,26.539147],"type":"Point"}
}