{
  "type": "Feature",
  "properties": {
    "iso:country":"IN",
    "ks:ks_name":"Purankattanpuliyur",
    "ks:ks_pop":189,
    "ks:ks_type":"HABITATION",
    "name:eng_x_preferred":[
        "Purankattanpuliyur"
    ],
    "wof:name":"Purankattanpuliyur",
    "wof:placetype":"locality",
    "wof:population":189
},
  "geometry": {"coordinates":[77.378772,8.828007],"type":"Point"}
}