{
  "type": "Feature",
  "properties": {
    "gn:admin1_code":"35.0",
    "gn:admin2_code":"467",
    "gn:asciiname":"Ichhapur",
    "gn:country_code":"IN",
    "gn:dem":252,
    "gn:feature_class":"P",
    "gn:feature_code":"PPL",
    "gn:name":"Ichh\u0101pur",
    "gn:population":0,
    "gn:timezone":"Asia/Kolkata",
    "iso:country":"IN",
    "name:und_x_variant":[
        "Chh\u0101pur",
        "Ichh\u0101pur"
    ],
    "wof:name":"Ichhapur",
    "wof:placetype":"locality"
},
  "geometry": {"coordinates":[76.15555999999999,21.15511],"type":"Point"}
}