{
  "type": "Feature",
  "properties": {
    "gn:country":"IN",
    "gn:fcode":"PPL",
    "gn:pop":14375,
    "iso:country":"IN",
    "name:cat_x_preferred":[
        "Dewa"
    ],
    "name:ceb_x_preferred":[
        "Dewa"
    ],
    "name:eng_x_preferred":[
        "Dewa"
    ],
    "name:ita_x_preferred":[
        "Dewa"
    ],
    "name:msa_x_preferred":[
        "Dewa"
    ],
    "name:nan_x_preferred":[
        "Dewa"
    ],
    "name:nld_x_preferred":[
        "Dewa"
    ],
    "name:pol_x_preferred":[
        "Dewa"
    ],
    "name:swe_x_preferred":[
        "Dewa"
    ],
    "name:unk_x_variant":[
        "Dewa"
    ],
    "name:urd_x_preferred":[
        "\u062f\u06cc\u0648\u0627\u060c \u0628\u06be\u0627\u0631\u062a"
    ],
    "name:urd_x_variant":[
        "\u062f\u06cc\u0648\u0627"
    ],
    "qs:name":"Dehwa",
    "qs:name_adm0":"India",
    "qs:name_adm1":"Uttar Pradesh",
    "qs:photos_9r":0,
    "qs:photos_sr":0,
    "qs:placetype":"Town",
    "qs:pop_sr":"6",
    "wof:name":"Dehwa",
    "wof:placetype":"locality",
    "wof:population":14375
},
  "geometry": {"coordinates":[81.16708,27.03584],"type":"Point"}
}