{
  "type": "Feature",
  "properties": {
    "iso:country":"IN",
    "ks:ks_name":"Puraman Bhawan",
    "ks:ks_pop":271,
    "ks:ks_type":"HABITATION",
    "name:eng_x_preferred":[
        "Puraman Bhawan"
    ],
    "wof:name":"Puraman Bhawan",
    "wof:placetype":"locality",
    "wof:population":271
},
  "geometry": {"coordinates":[77.41273,23.333294],"type":"Point"}
}