{
  "type": "Feature",
  "properties": {
    "iso:country":"IN",
    "ks:ks_name":"Kollesagu",
    "ks:ks_pop":17,
    "ks:ks_type":"HABITATION",
    "name:eng_x_preferred":[
        "Kollesagu"
    ],
    "wof:name":"Kollesagu",
    "wof:placetype":"locality",
    "wof:population":17
},
  "geometry": {"coordinates":[75.487621,12.751274],"type":"Point"}
}