{
  "type": "Feature",
  "properties": {
    "iso:country":"IN",
    "ks:ks_name":"Sangrampur",
    "ks:ks_pop":4059,
    "ks:ks_type":"VILLAGE",
    "ks:ks_uagg_main":0,
    "name:eng_x_preferred":[
        "Sangrampur"
    ],
    "wof:name":"Sangrampur",
    "wof:placetype":"neighbourhood",
    "wof:population":4059
},
  "geometry": {"coordinates":[88.24333,22.246839],"type":"Point"}
}