{
  "type": "Feature",
  "properties": {
    "gn:admin1_code":"39.0",
    "gn:admin2_code":"64.0",
    "gn:asciiname":"Bhanriyakali",
    "gn:country_code":"IN",
    "gn:dem":1356,
    "gn:feature_class":"P",
    "gn:feature_code":"PPL",
    "gn:name":"Bhanriy\u0101kali",
    "gn:population":0,
    "gn:timezone":"Asia/Kolkata",
    "iso:country":"IN",
    "wof:name":"Bhanriyakali",
    "wof:placetype":"locality"
},
  "geometry": {"coordinates":[79.22028,29.92528],"type":"Point"}
}