{
  "type": "Feature",
  "properties": {
    "gn:admin1_code":"39.0",
    "gn:admin2_code":"64.0",
    "gn:asciiname":"Bhanriyakali",
    "gn:country_code":"IN",
    "gn:dem":1356,
    "gn:feature_class":"P",
    "gn:feature_code":"PPL",
    "gn:name":"Bhanriy\u0101kali",
    "gn:population":0,
    "gn:timezone":"Asia/Kolkata",
    "iso:country":"IN",
    "ks:ks_name":"Bhanriakali",
    "ks:ks_pop":57,
    "ks:ks_type":"VILLAGE",
    "name:eng_x_preferred":[
        "Bhanriakali"
    ],
    "name:eng_x_variant":[
        "Bhanriyakali"
    ],
    "wof:name":"Bhanriakali",
    "wof:placetype":"locality",
    "wof:population":57
},
  "geometry": {"coordinates":[79.22057100000001,29.923207],"type":"Point"}
}