{
  "type": "Feature",
  "properties": {
    "gn:admin1_code":"35",
    "gn:admin2_code":"448.0",
    "gn:asciiname":"Kalpi",
    "gn:country_code":"IN",
    "gn:dem":319,
    "gn:feature_class":"P",
    "gn:feature_code":"PPL",
    "gn:name":"K\u0101lpi",
    "gn:population":0,
    "gn:timezone":"Asia/Kolkata",
    "iso:country":"IN",
    "name:bih_x_preferred":[
        "\u0915\u093e\u0932\u092a\u0940"
    ],
    "name:bpy_x_preferred":[
        "\u0995\u09be\u09b2\u09cd\u09aa\u09bf"
    ],
    "name:cat_x_preferred":[
        "Kalpi"
    ],
    "name:ceb_x_preferred":[
        "K\u0101lpi"
    ],
    "name:fra_x_preferred":[
        "Kalp\u00ee"
    ],
    "name:hin_x_preferred":[
        "\u0915\u093e\u0932\u092a\u0940"
    ],
    "name:ita_x_preferred":[
        "Kalpi"
    ],
    "name:jpn_x_preferred":[
        "\u30ab\u30fc\u30eb\u30d4\u30fc"
    ],
    "name:mal_x_preferred":[
        "\u0d15\u0d7d\u0d2a\u0d3f"
    ],
    "name:mlg_x_preferred":[
        "Kalpi"
    ],
    "name:msa_x_preferred":[
        "Kalpi"
    ],
    "name:new_x_preferred":[
        "\u0915\u0932\u094d\u092a\u0940"
    ],
    "name:nld_x_preferred":[
        "Kalpi"
    ],
    "name:ori_x_preferred":[
        "\u0b15\u0b3e\u0b32\u0b4d\u200c\u0b2a\u0b3f"
    ],
    "name:pol_x_preferred":[
        "Kalpi"
    ],
    "name:rus_x_preferred":[
        "\u041a\u0430\u043b\u043f\u0438"
    ],
    "name:swe_x_preferred":[
        "K\u0101lpi"
    ],
    "name:urd_x_preferred":[
        "\u06a9\u0627\u0644\u067e\u06cc"
    ],
    "name:vie_x_preferred":[
        "Kalpi"
    ],
    "name:zho_x_preferred":[
        "\u5361\u5c14\u76ae"
    ],
    "wof:name":"Kalpi",
    "wof:placetype":"locality"
},
  "geometry": {"coordinates":[77.25631,22.26624],"type":"Point"}
}