{
  "type": "Feature",
  "properties": {
    "iso:country":"IN",
    "ks:ks_name":"Indirapura",
    "ks:ks_pop":299,
    "ks:ks_type":"HABITATION",
    "name:eng_x_preferred":[
        "Indirapura"
    ],
    "wof:name":"Indirapura",
    "wof:placetype":"locality",
    "wof:population":299
},
  "geometry": {"coordinates":[72.65386100000001,22.438861],"type":"Point"}
}