{
  "type": "Feature",
  "properties": {
    "gn:admin1_code":"36",
    "gn:admin2_code":"185.0",
    "gn:asciiname":"Nawela",
    "gn:country_code":"IN",
    "gn:dem":93,
    "gn:feature_class":"P",
    "gn:feature_code":"PPL",
    "gn:name":"Nawela",
    "gn:population":0,
    "gn:timezone":"Asia/Kolkata",
    "iso:country":"IN",
    "ks:ks_name":"Navela",
    "ks:ks_pop":110,
    "ks:ks_type":"HABITATION",
    "ks:ks_uagg_main":0,
    "name:eng_x_preferred":[
        "Navela"
    ],
    "wof:name":"Navela",
    "wof:placetype":"neighbourhood",
    "wof:population":110
},
  "geometry": {"coordinates":[82.651678,26.977756],"type":"Point"}
}