{
  "type": "Feature",
  "properties": {
    "iso:country":"IN",
    "ks:ks_name":"Pannikkunnu",
    "ks:ks_pop":523,
    "ks:ks_type":"HABITATION",
    "name:eng_x_preferred":[
        "Pannikkunnu"
    ],
    "wof:name":"Pannikkunnu",
    "wof:placetype":"locality",
    "wof:population":523
},
  "geometry": {"coordinates":[76.36511,11.121579],"type":"Point"}
}