{
  "type": "Feature",
  "properties": {
    "iso:country":"IN",
    "ks:ks_alt_nam":"KHOKHNAHA BELA",
    "ks:ks_name":"Khokhnaha Bela",
    "ks:ks_pop":600,
    "ks:ks_type":"HABITATION",
    "name:eng_x_preferred":[
        "Khokhnaha Bela"
    ],
    "wof:name":"Khokhnaha Bela",
    "wof:placetype":"locality",
    "wof:population":600
},
  "geometry": {"coordinates":[86.553468,26.197461],"type":"Point"}
}