{
  "type": "Feature",
  "properties": {
    "iso:country":"IN",
    "ks:ks_name":"Shankarpura",
    "ks:ks_pop":345,
    "ks:ks_type":"HABITATION",
    "name:eng_x_preferred":[
        "Shankarpura"
    ],
    "wof:name":"Shankarpura",
    "wof:placetype":"locality",
    "wof:population":345
},
  "geometry": {"coordinates":[72.80634000000001,22.36508],"type":"Point"}
}