{
  "type": "Feature",
  "properties": {
    "gn:admin1_code":"12.0",
    "gn:admin2_code":"009",
    "gn:asciiname":"Choatar",
    "gn:country_code":"IN",
    "gn:dem":2962,
    "gn:feature_class":"P",
    "gn:feature_code":"PPL",
    "gn:name":"Choatar",
    "gn:population":0,
    "gn:timezone":"Asia/Kolkata",
    "iso:country":"IN",
    "wof:name":"Choatar",
    "wof:placetype":"locality"
},
  "geometry": {"coordinates":[74.80139,34.49028],"type":"Point"}
}