{
  "type": "Feature",
  "properties": {
    "iso:country":"IN",
    "ks:ks_name":"Mamirguda",
    "ks:ks_pop":363,
    "ks:ks_type":"HABITATION",
    "name:eng_x_preferred":[
        "Mamirguda"
    ],
    "wof:name":"Mamirguda",
    "wof:placetype":"locality",
    "wof:population":363
},
  "geometry": {"coordinates":[81.076571,17.925485],"type":"Point"}
}