{
  "type": "Feature",
  "properties": {
    "iso:country":"IN",
    "ks:ks_name":"Tiwaritola",
    "ks:ks_pop":645,
    "ks:ks_type":"HABITATION",
    "name:eng_x_preferred":[
        "Tiwaritola"
    ],
    "wof:name":"Tiwaritola",
    "wof:placetype":"locality",
    "wof:population":645
},
  "geometry": {"coordinates":[83.79409800000001,26.677594],"type":"Point"}
}