{
  "type": "Feature",
  "properties": {
    "iso:country":"IN",
    "ks:ks_name":"Balsamle",
    "ks:ks_pop":187,
    "ks:ks_type":"HABITATION",
    "name:eng_x_preferred":[
        "Balsamle"
    ],
    "wof:name":"Balsamle",
    "wof:placetype":"locality",
    "wof:population":187
},
  "geometry": {"coordinates":[73.271111,20.365],"type":"Point"}
}