{
  "type": "Feature",
  "properties": {
    "iso:country":"IN",
    "ks:ks_name":"Sunabeda",
    "ks:ks_pop":156,
    "ks:ks_type":"HABITATION",
    "name:eng_x_preferred":[
        "Sunabeda"
    ],
    "wof:name":"Sunabeda",
    "wof:placetype":"locality",
    "wof:population":156
},
  "geometry": {"coordinates":[81.533714,17.828981],"type":"Point"}
}