{
  "type": "Feature",
  "properties": {
    "iso:country":"IN",
    "ks:ks_name":"Bara Mirglingi",
    "ks:ks_pop":989,
    "ks:ks_type":"HABITATION",
    "name:eng_x_preferred":[
        "Bara Mirglingi"
    ],
    "wof:name":"Bara Mirglingi",
    "wof:placetype":"locality",
    "wof:population":989
},
  "geometry": {"coordinates":[85.70526599999999,22.286868],"type":"Point"}
}