{
  "type": "Feature",
  "properties": {
    "gn:admin1_code":"9.0",
    "gn:admin2_code":"487",
    "gn:asciiname":"Bhanadra",
    "gn:country_code":"IN",
    "gn:dem":75,
    "gn:feature_class":"P",
    "gn:feature_code":"PPL",
    "gn:name":"Bhanadra",
    "gn:population":0,
    "gn:timezone":"Asia/Kolkata",
    "iso:country":"IN",
    "wof:name":"Bhanadra",
    "wof:placetype":"locality"
},
  "geometry": {"coordinates":[73.63462,21.86107],"type":"Point"}
}