{
  "type": "Feature",
  "properties": {
    "iso:country":"IN",
    "ks:ks_name":"Murdahiya",
    "ks:ks_pop":65,
    "ks:ks_type":"HABITATION",
    "ks:ks_uagg_main":0,
    "name:eng_x_preferred":[
        "Murdahiya"
    ],
    "wof:name":"Murdahiya",
    "wof:placetype":"neighbourhood",
    "wof:population":65
},
  "geometry": {"coordinates":[83.431543,26.892449],"type":"Point"}
}