{
  "type": "Feature",
  "properties": {
    "iso:country":"IN",
    "ks:ks_name":"Jamunkita",
    "ks:ks_pop":0,
    "ks:ks_type":"VILLAGE",
    "name:eng_x_preferred":[
        "Jamunkita"
    ],
    "wof:name":"Jamunkita",
    "wof:placetype":"locality",
    "wof:population":0
},
  "geometry": {"coordinates":[87.057225,24.611668],"type":"Point"}
}