{
  "type": "Feature",
  "properties": {
    "iso:country":"IN",
    "ks:ks_name":"Boddigaruvu",
    "ks:ks_pop":25,
    "ks:ks_type":"HABITATION",
    "name:eng_x_preferred":[
        "Boddigaruvu"
    ],
    "wof:name":"Boddigaruvu",
    "wof:placetype":"locality",
    "wof:population":25
},
  "geometry": {"coordinates":[82.952629,17.959613],"type":"Point"}
}