{
  "type": "Feature",
  "properties": {
    "iso:country":"IN",
    "ks:ks_alt_nam":"Ganguda faliya",
    "ks:ks_name":"Ganguda Faliya",
    "ks:ks_pop":171,
    "ks:ks_type":"HABITATION",
    "ks:ks_uagg_main":0,
    "name:eng_x_preferred":[
        "Ganguda Faliya"
    ],
    "wof:name":"Ganguda Faliya",
    "wof:placetype":"neighbourhood",
    "wof:population":171
},
  "geometry": {"coordinates":[73.217752,20.556523],"type":"Point"}
}