{
  "type": "Feature",
  "properties": {
    "iso:country":"IN",
    "ks:ks_name":"Lonara",
    "ks:ks_pop":121,
    "ks:ks_type":"VILLAGE",
    "name:eng_x_preferred":[
        "Lonara"
    ],
    "wof:name":"Lonara",
    "wof:placetype":"locality",
    "wof:population":121
},
  "geometry": {"coordinates":[75.684209,21.67088],"type":"Point"}
}