{
  "type": "Feature",
  "properties": {
    "iso:country":"IN",
    "ks:ks_name":"Kheersar",
    "ks:ks_pop":377,
    "ks:ks_type":"HABITATION",
    "name:eng_x_preferred":[
        "Kheersar"
    ],
    "wof:name":"Kheersar",
    "wof:placetype":"locality",
    "wof:population":377
},
  "geometry": {"coordinates":[72.81747799999999,28.729528],"type":"Point"}
}