{
  "type": "Feature",
  "properties": {
    "iso:country":"IN",
    "ks:ks_alt_nam":"HARA FALI",
    "ks:ks_name":"Hara Fali",
    "ks:ks_pop":50,
    "ks:ks_type":"HABITATION",
    "name:eng_x_preferred":[
        "Hara Fali"
    ],
    "wof:name":"Hara Fali",
    "wof:placetype":"locality",
    "wof:population":50
},
  "geometry": {"coordinates":[72.881361,24.471447],"type":"Point"}
}