{
  "type": "Feature",
  "properties": {
    "gn:admin1_code":"36",
    "gn:admin2_code":"194.0",
    "gn:asciiname":"Dhanuhan",
    "gn:country_code":"IN",
    "gn:dem":89,
    "gn:feature_class":"P",
    "gn:feature_code":"PPL",
    "gn:name":"Dhanuh\u0101n",
    "gn:population":0,
    "gn:timezone":"Asia/Kolkata",
    "iso:country":"IN",
    "ks:ks_alt_nam":"Dhanuh\u0101n",
    "ks:ks_name":"Dhanuhan",
    "ks:ks_type":"VILLAGE",
    "ks:ks_uagg_main":0,
    "name:eng_x_preferred":[
        "Dhanuhan"
    ],
    "name:eng_x_variant":[
        "Dhanuh\u0101n"
    ],
    "wof:name":"Dhanuhan",
    "wof:placetype":"neighbourhood"
},
  "geometry": {"coordinates":[82.572041,25.473464],"type":"Point"}
}