{
  "type": "Feature",
  "properties": {
    "gn:admin1_code":"11.0",
    "gn:admin2_code":"32.0",
    "gn:asciiname":"Dabri",
    "gn:country_code":"IN",
    "gn:dem":1194,
    "gn:feature_class":"P",
    "gn:feature_code":"PPL",
    "gn:name":"D\u0101bri",
    "gn:population":0,
    "gn:timezone":"Asia/Kolkata",
    "iso:country":"IN",
    "name:urd_x_preferred":[
        "\u062f\u0627\u0628\u0691\u06cc"
    ],
    "wof:name":"Dabri",
    "wof:placetype":"locality"
},
  "geometry": {"coordinates":[77.70728000000003,30.60216],"type":"Point"}
}