{
  "type": "Feature",
  "properties": {
    "iso:country":"IN",
    "ks:ks_name":"Chittegudde",
    "ks:ks_pop":13,
    "ks:ks_type":"HABITATION",
    "name:eng_x_preferred":[
        "Chittegudde"
    ],
    "wof:name":"Chittegudde",
    "wof:placetype":"locality",
    "wof:population":13
},
  "geometry": {"coordinates":[75.579804,12.717658],"type":"Point"}
}