{
  "type": "Feature",
  "properties": {
    "gn:admin1_code":"25.0",
    "gn:admin2_code":"610.0",
    "gn:asciiname":"Girisandu",
    "gn:country_code":"IN",
    "gn:dem":1042,
    "gn:feature_class":"P",
    "gn:feature_code":"PPL",
    "gn:name":"Girisandu",
    "gn:population":0,
    "gn:timezone":"Asia/Kolkata",
    "iso:country":"IN",
    "wof:name":"Girisandu",
    "wof:placetype":"locality"
},
  "geometry": {"coordinates":[77.47134,11.72495],"type":"Point"}
}