{
  "type": "Feature",
  "properties": {
    "iso:country":"IN",
    "ks:ks_alt_nam":"Lotloni tanda",
    "ks:ks_name":"Lotloni Tanda",
    "ks:ks_pop":143,
    "ks:ks_type":"HABITATION",
    "name:eng_x_preferred":[
        "Lotloni Tanda"
    ],
    "wof:name":"Lotloni Tanda",
    "wof:placetype":"locality",
    "wof:population":143
},
  "geometry": {"coordinates":[78.18415,16.629655],"type":"Point"}
}