{
  "type": "Feature",
  "properties": {
    "iso:country":"IN",
    "ks:ks_name":"Paloli",
    "ks:ks_pop":518,
    "ks:ks_type":"HABITATION",
    "name:eng_x_preferred":[
        "Paloli"
    ],
    "wof:name":"Paloli",
    "wof:placetype":"locality",
    "wof:population":518
},
  "geometry": {"coordinates":[75.76688900000001,11.696693],"type":"Point"}
}