{
  "type": "Feature",
  "properties": {
    "iso:country":"IN",
    "ks:ks_name":"Barakhandia",
    "ks:ks_pop":1100,
    "ks:ks_type":"VILLAGE",
    "name:eng_x_preferred":[
        "Barakhandia"
    ],
    "wof:name":"Barakhandia",
    "wof:placetype":"locality",
    "wof:population":1100
},
  "geometry": {"coordinates":[85.609308,21.887553],"type":"Point"}
}