{
  "type": "Feature",
  "properties": {
    "iso:country":"IN",
    "ks:ks_name":"Sheetala Mata Fali",
    "ks:ks_pop":50,
    "ks:ks_type":"HABITATION",
    "name:eng_x_preferred":[
        "Sheetala Mata Fali"
    ],
    "wof:name":"Sheetala Mata Fali",
    "wof:placetype":"locality",
    "wof:population":50
},
  "geometry": {"coordinates":[72.76280300000001,24.504753],"type":"Point"}
}