{
  "type": "Feature",
  "properties": {
    "iso:country":"IN",
    "ks:ks_name":"Thimmanur",
    "ks:ks_pop":495,
    "ks:ks_type":"HABITATION",
    "name:eng_x_preferred":[
        "Thimmanur"
    ],
    "wof:name":"Thimmanur",
    "wof:placetype":"locality",
    "wof:population":495
},
  "geometry": {"coordinates":[78.643371,12.646049],"type":"Point"}
}