{
  "type": "Feature",
  "properties": {
    "iso:country":"IN",
    "ks:ks_name":"Nabarangapur",
    "ks:ks_pop":28,
    "ks:ks_type":"VILLAGE",
    "name:eng_x_preferred":[
        "Nabarangapur"
    ],
    "wof:name":"Nabarangapur",
    "wof:placetype":"locality",
    "wof:population":28
},
  "geometry": {"coordinates":[85.04132300000001,21.5025],"type":"Point"}
}