{
  "type": "Feature",
  "properties": {
    "gn:admin1_code":"19",
    "gn:admin2_code":"558.0",
    "gn:asciiname":"Torna",
    "gn:country_code":"IN",
    "gn:dem":577,
    "gn:feature_class":"P",
    "gn:feature_code":"PPL",
    "gn:name":"Torna",
    "gn:population":0,
    "gn:timezone":"Asia/Kolkata",
    "iso:country":"IN",
    "name:ceb_x_preferred":[
        "Torna"
    ],
    "name:deu_x_preferred":[
        "Torna"
    ],
    "name:swe_x_preferred":[
        "Torna"
    ],
    "wof:name":"Torna",
    "wof:placetype":"locality"
},
  "geometry": {"coordinates":[77.26723,18.23267],"type":"Point"}
}