{
  "type": "Feature",
  "properties": {
    "gn:admin1_code":"36.0",
    "gn:admin2_code":"176",
    "gn:asciiname":"Bara Banki",
    "gn:country_code":"IN",
    "gn:dem":125,
    "gn:feature_class":"P",
    "gn:feature_code":"PPL",
    "gn:name":"B\u0101ra Bank\u012b",
    "gn:population":0,
    "gn:timezone":"Asia/Kolkata",
    "iso:country":"IN",
    "name:und_x_variant":[
        "B\u0101ra Bank\u012b",
        "B\u0101ra Banki"
    ],
    "wof:name":"Bara Banki",
    "wof:placetype":"locality"
},
  "geometry": {"coordinates":[81.17926999999997,26.92384],"type":"Point"}
}