{
  "type": "Feature",
  "properties": {
    "gn:admin1_code":"12.0",
    "gn:asciiname":"Rajao",
    "gn:country_code":"IN",
    "gn:dem":900,
    "gn:feature_class":"P",
    "gn:feature_code":"PPL",
    "gn:name":"Raj\u0101o",
    "gn:population":0,
    "gn:timezone":"Asia/Kolkata",
    "iso:country":"IN",
    "name:und_x_variant":[
        "Raj\u0101o",
        "Raj\u016ba"
    ],
    "wof:name":"Rajao",
    "wof:placetype":"locality"
},
  "geometry": {"coordinates":[74.11750000000001,33.25994],"type":"Point"}
}