{
  "type": "Feature",
  "properties": {
    "gn:admin1_code":"10.0",
    "gn:admin2_code":"072",
    "gn:asciiname":"Dao Majra",
    "gn:country_code":"IN",
    "gn:dem":268,
    "gn:feature_class":"P",
    "gn:feature_code":"PPL",
    "gn:name":"D\u0101o M\u0101jra",
    "gn:population":0,
    "gn:timezone":"Asia/Kolkata",
    "iso:country":"IN",
    "wof:name":"Dao Majra",
    "wof:placetype":"locality"
},
  "geometry": {"coordinates":[76.87524999999999,30.21103],"type":"Point"}
}