{
  "type": "Feature",
  "properties": {
    "iso:country":"IN",
    "ks:ks_name":"Bhulsibhawana",
    "ks:ks_pop":162,
    "ks:ks_type":"HABITATION",
    "name:eng_x_preferred":[
        "Bhulsibhawana"
    ],
    "wof:name":"Bhulsibhawana",
    "wof:placetype":"locality",
    "wof:population":162
},
  "geometry": {"coordinates":[82.65465500000001,22.762261],"type":"Point"}
}