{
  "type": "Feature",
  "properties": {
    "iso:country":"IN",
    "ks:ks_name":"Latadadar",
    "ks:ks_pop":117,
    "ks:ks_type":"VILLAGE",
    "name:eng_x_preferred":[
        "Latadadar"
    ],
    "wof:name":"Latadadar",
    "wof:placetype":"locality",
    "wof:population":117
},
  "geometry": {"coordinates":[82.422539,21.420488],"type":"Point"}
}