{
  "type": "Feature",
  "properties": {
    "gn:admin1_code":"36",
    "gn:admin2_code":"192.0",
    "gn:asciiname":"Arazi Saraunda",
    "gn:country_code":"IN",
    "gn:dem":74,
    "gn:feature_class":"P",
    "gn:feature_code":"PPL",
    "gn:name":"Ar\u0101zi Saraunda",
    "gn:population":0,
    "gn:timezone":"Asia/Kolkata",
    "iso:country":"IN",
    "ks:ks_alt_nam":"Ar\u0101zi Saraunda",
    "ks:ks_name":"Arazi Saraunda",
    "ks:ks_type":"VILLAGE",
    "name:eng_x_preferred":[
        "Arazi Saraunda"
    ],
    "name:eng_x_variant":[
        "Ar\u0101zi Saraunda"
    ],
    "wof:name":"Arazi Saraunda",
    "wof:placetype":"locality"
},
  "geometry": {"coordinates":[83.38888799999999,25.876394],"type":"Point"}
}