{
  "type": "Feature",
  "properties": {
    "iso:country":"IN",
    "ks:ks_name":"Jot Kamal",
    "ks:ks_pop":6194,
    "ks:ks_type":"URBAN",
    "ks:ks_uagg_main":0,
    "name:eng_x_preferred":[
        "Jot Kamal"
    ],
    "wof:name":"Jot Kamal",
    "wof:placetype":"neighbourhood",
    "wof:population":6194
},
  "geometry": {"coordinates":[88.091781,24.465562],"type":"Point"}
}