{
  "type": "Feature",
  "properties": {
    "gn:admin1_code":"19.0",
    "gn:admin2_code":"574.0",
    "gn:asciiname":"Mallisettihalli",
    "gn:country_code":"IN",
    "gn:dem":880,
    "gn:feature_class":"P",
    "gn:feature_code":"PPL",
    "gn:name":"Mallisettihalli",
    "gn:population":0,
    "gn:timezone":"Asia/Kolkata",
    "iso:country":"IN",
    "wof:name":"Mallisettihalli",
    "wof:placetype":"locality"
},
  "geometry": {"coordinates":[76.51090000000001,12.91758],"type":"Point"}
}