{
  "type": "Feature",
  "properties": {
    "iso:country":"IN",
    "ks:ks_name":"Satmatwadi",
    "ks:ks_pop":425,
    "ks:ks_type":"HABITATION",
    "name:eng_x_preferred":[
        "Satmatwadi"
    ],
    "wof:name":"Satmatwadi",
    "wof:placetype":"locality",
    "wof:population":425
},
  "geometry": {"coordinates":[73.872784,15.805102],"type":"Point"}
}