{
  "type": "Feature",
  "properties": {
    "iso:country":"IN",
    "ks:ks_name":"Simaria",
    "ks:ks_pop":0,
    "ks:ks_type":"VILLAGE",
    "name:eng_x_preferred":[
        "Simaria"
    ],
    "wof:name":"Simaria",
    "wof:placetype":"locality",
    "wof:population":0
},
  "geometry": {"coordinates":[84.98773300000001,24.235951],"type":"Point"}
}