{
  "type": "Feature",
  "properties": {
    "iso:country":"IN",
    "ks:ks_name":"Paniyeli",
    "ks:ks_pop":1018,
    "ks:ks_type":"HABITATION",
    "name:eng_x_preferred":[
        "Paniyeli"
    ],
    "wof:name":"Paniyeli",
    "wof:placetype":"locality",
    "wof:population":1018
},
  "geometry": {"coordinates":[76.59229999999999,10.171058],"type":"Point"}
}