{
  "type": "Feature",
  "properties": {
    "gn:admin1_code":"2",
    "gn:admin2_code":"544.0",
    "gn:asciiname":"Somidevipalle",
    "gn:country_code":"IN",
    "gn:dem":22,
    "gn:feature_class":"P",
    "gn:feature_code":"PPL",
    "gn:name":"Somidevipalle",
    "gn:population":0,
    "gn:timezone":"Asia/Kolkata",
    "iso:country":"IN",
    "wof:name":"Somidevipalle",
    "wof:placetype":"locality"
},
  "geometry": {"coordinates":[82.75111,17.47416],"type":"Point"}
}