{
  "type": "Feature",
  "properties": {
    "iso:country":"IN",
    "ks:ks_name":"Ranewadi",
    "ks:ks_pop":378,
    "ks:ks_type":"HABITATION",
    "name:eng_x_preferred":[
        "Ranewadi"
    ],
    "wof:name":"Ranewadi",
    "wof:placetype":"locality",
    "wof:population":378
},
  "geometry": {"coordinates":[73.955298,16.869183],"type":"Point"}
}