{
  "type": "Feature",
  "properties": {
    "gn:admin1_code":"37.0",
    "gn:admin2_code":"402",
    "gn:asciiname":"Dhoribahal",
    "gn:country_code":"IN",
    "gn:dem":409,
    "gn:feature_class":"P",
    "gn:feature_code":"PPL",
    "gn:name":"Dhoribah\u0101l",
    "gn:population":0,
    "gn:timezone":"Asia/Kolkata",
    "iso:country":"IN",
    "wof:name":"Dhoribahal",
    "wof:placetype":"locality"
},
  "geometry": {"coordinates":[83.89009,22.69462],"type":"Point"}
}