{
  "type": "Feature",
  "properties": {
    "gn:admin1_code":"35",
    "gn:admin2_code":"458.0",
    "gn:asciiname":"Kharela",
    "gn:country_code":"IN",
    "gn:dem":449,
    "gn:feature_class":"P",
    "gn:feature_code":"PPL",
    "gn:name":"Kharela",
    "gn:population":0,
    "gn:timezone":"Asia/Kolkata",
    "iso:country":"IN",
    "name:bpy_x_preferred":[
        "\u0996\u09be\u09b0\u09c7\u09b2\u09be"
    ],
    "name:ceb_x_preferred":[
        "Kharel\u0101"
    ],
    "name:ita_x_preferred":[
        "Kharela"
    ],
    "name:mlg_x_preferred":[
        "Kharela"
    ],
    "name:msa_x_preferred":[
        "Kharela"
    ],
    "name:new_x_preferred":[
        "\u0916\u0930\u0947\u0932\u093e"
    ],
    "name:nld_x_preferred":[
        "Kharela"
    ],
    "name:pol_x_preferred":[
        "Kharela"
    ],
    "name:por_x_preferred":[
        "Kharela"
    ],
    "name:swe_x_preferred":[
        "Kharel\u0101"
    ],
    "name:urd_x_preferred":[
        "\u06a9\u06be\u0631\u06cc\u0644\u0627"
    ],
    "name:vie_x_preferred":[
        "Kharela"
    ],
    "wof:name":"Kharela",
    "wof:placetype":"locality"
},
  "geometry": {"coordinates":[77.1485,24.88778],"type":"Point"}
}