{
  "type": "Feature",
  "properties": {
    "iso:country":"IN",
    "ks:ks_alt_nam":"Nu\u0101g\u0101n",
    "ks:ks_name":"Nuagan",
    "ks:ks_pop":433,
    "ks:ks_type":"VILLAGE",
    "name:eng_x_preferred":[
        "Nuagan"
    ],
    "name:eng_x_variant":[
        "Nu\u0101g\u0101n"
    ],
    "wof:name":"Nuagan",
    "wof:placetype":"locality",
    "wof:population":433
},
  "geometry": {"coordinates":[85.25250800000001,21.266679],"type":"Point"}
}