{
  "type": "Feature",
  "properties": {
    "gn:admin1_code":"25.0",
    "gn:admin2_code":"610.0",
    "gn:asciiname":"Surampatti",
    "gn:country_code":"IN",
    "gn:dem":177,
    "gn:feature_class":"P",
    "gn:feature_code":"PPL",
    "gn:name":"S\u016brampatti",
    "gn:population":0,
    "gn:timezone":"Asia/Kolkata",
    "iso:country":"IN",
    "ks:ks_alt_nam":"S\u016brampatti",
    "ks:ks_name":"Surampatti",
    "ks:ks_type":"VILLAGE",
    "ks:ks_uagg_main":0,
    "name:bpy_x_preferred":[
        "\u09b8\u09c1\u09b0\u09be\u09ae\u09aa\u09be\u09a4\u09cd\u09a4\u09bf"
    ],
    "name:ind_x_preferred":[
        "Surampatti"
    ],
    "name:ita_x_preferred":[
        "Surampatti"
    ],
    "name:msa_x_preferred":[
        "Surampatti"
    ],
    "name:nld_x_preferred":[
        "Surampatti"
    ],
    "name:por_x_preferred":[
        "Surampatti"
    ],
    "name:tam_x_preferred":[
        "\u0b9a\u0bc2\u0bb0\u0bae\u0bcd\u0baa\u0b9f\u0bcd\u0b9f\u0bbf"
    ],
    "name:vie_x_preferred":[
        "Surampatti"
    ],
    "name:zho_x_preferred":[
        "\u82cf\u62c9\u59c6\u5e15\u8482"
    ],
    "wof:name":"Surampatti",
    "wof:placetype":"neighbourhood"
},
  "geometry": {"coordinates":[77.71122,11.32726],"type":"Point"}
}