{
  "type": "Feature",
  "properties": {
    "gn:admin1_code":"36",
    "gn:admin2_code":"178.0",
    "gn:asciiname":"Jot Awasthi",
    "gn:country_code":"IN",
    "gn:dem":89,
    "gn:feature_class":"P",
    "gn:feature_code":"PPL",
    "gn:name":"Jot Awasthi",
    "gn:population":0,
    "gn:timezone":"Asia/Kolkata",
    "iso:country":"IN",
    "ks:ks_name":"Jot Awasthi",
    "ks:ks_type":"VILLAGE",
    "name:eng_x_preferred":[
        "Jot Awasthi"
    ],
    "wof:name":"Jot Awasthi",
    "wof:placetype":"locality"
},
  "geometry": {"coordinates":[82.689594,26.525286],"type":"Point"}
}