{
  "type": "Feature",
  "properties": {
    "iso:country":"IN",
    "ks:ks_alt_nam":"G\u0101di",
    "ks:ks_name":"Gadi",
    "ks:ks_pop":500,
    "ks:ks_type":"VILLAGE",
    "ks:ks_uagg_main":0,
    "name:eng_x_preferred":[
        "Gadi"
    ],
    "name:eng_x_variant":[
        "G\u0101di"
    ],
    "wof:name":"Gadi",
    "wof:placetype":"neighbourhood",
    "wof:population":500
},
  "geometry": {"coordinates":[85.80713799999999,24.361477],"type":"Point"}
}