{
  "type": "Feature",
  "properties": {
    "iso:country":"IN",
    "ks:ks_alt_nam":"Juriy\u0101",
    "ks:ks_name":"Juriya",
    "ks:ks_pop":5398,
    "ks:ks_type":"VILLAGE",
    "ks:ks_uagg_main":0,
    "name:eng_x_preferred":[
        "Juriya"
    ],
    "name:eng_x_variant":[
        "Juriy\u0101"
    ],
    "wof:name":"Juriya",
    "wof:placetype":"locality",
    "wof:population":5398
},
  "geometry": {"coordinates":[84.69431400000001,23.427137],"type":"Point"}
}