{
  "type": "Feature",
  "properties": {
    "gn:admin1_code":"11.0",
    "gn:admin2_code":"32.0",
    "gn:asciiname":"Koyra",
    "gn:country_code":"IN",
    "gn:dem":1597,
    "gn:feature_class":"P",
    "gn:feature_code":"PPL",
    "gn:name":"Koyra",
    "gn:population":0,
    "gn:timezone":"Asia/Kolkata",
    "iso:country":"IN",
    "wof:name":"Koyra",
    "wof:placetype":"locality"
},
  "geometry": {"coordinates":[77.44674999999999,30.69143],"type":"Point"}
}