{
  "type": "Feature",
  "properties": {
    "iso:country":"IN",
    "ks:ks_name":"Titardand",
    "ks:ks_pop":69,
    "ks:ks_type":"HABITATION",
    "name:eng_x_preferred":[
        "Titardand"
    ],
    "wof:name":"Titardand",
    "wof:placetype":"locality",
    "wof:population":69
},
  "geometry": {"coordinates":[83.01755,22.551749],"type":"Point"}
}