{
  "type": "Feature",
  "properties": {
    "iso:country":"IN",
    "ks:ks_name":"Kempashanaiahanapalya",
    "ks:ks_pop":80,
    "ks:ks_type":"HABITATION",
    "name:eng_x_preferred":[
        "Kempashanaiahanapalya"
    ],
    "wof:name":"Kempashanaiahanapalya",
    "wof:placetype":"locality",
    "wof:population":80
},
  "geometry": {"coordinates":[77.03239600000001,13.094592],"type":"Point"}
}