{
  "type": "Feature",
  "properties": {
    "iso:country":"IN",
    "ks:ks_name":"Gahrathipada",
    "ks:ks_pop":27,
    "ks:ks_type":"HABITATION",
    "name:eng_x_preferred":[
        "Gahrathipada"
    ],
    "wof:name":"Gahrathipada",
    "wof:placetype":"locality",
    "wof:population":27
},
  "geometry": {"coordinates":[72.91507900000001,19.968054],"type":"Point"}
}