{
  "type": "Feature",
  "properties": {
    "gn:admin1_code":"23.0",
    "gn:admin2_code":"35.0",
    "gn:asciiname":"Dhilwan",
    "gn:country_code":"IN",
    "gn:dem":242,
    "gn:feature_class":"P",
    "gn:feature_code":"PPL",
    "gn:name":"Dhilw\u0101n",
    "gn:population":0,
    "gn:timezone":"Asia/Kolkata",
    "iso:country":"IN",
    "name:ben_x_preferred":[
        "\u09a7\u09bf\u09b2\u0993\u09af\u09bc\u09be\u09a8"
    ],
    "name:bpy_x_preferred":[
        "\u09a7\u09bf\u09b2\u09f1\u09be\u09a8"
    ],
    "name:ceb_x_preferred":[
        "Dhilw\u0101n"
    ],
    "name:ita_x_preferred":[
        "Dhilwan"
    ],
    "name:msa_x_preferred":[
        "Dhilwan"
    ],
    "name:new_x_preferred":[
        "\u0927\u093f\u0932\u094d\u0935\u0928"
    ],
    "name:nld_x_preferred":[
        "Dhilwan"
    ],
    "name:por_x_preferred":[
        "Dhilwan"
    ],
    "name:swe_x_preferred":[
        "Dhilw\u0101n"
    ],
    "name:vie_x_preferred":[
        "Dhilwan"
    ],
    "name:zho_x_preferred":[
        "\u8fea\u5c14\u4e07"
    ],
    "wof:name":"Dhilwan",
    "wof:placetype":"locality"
},
  "geometry": {"coordinates":[75.08385,31.94729],"type":"Point"}
}