{
  "type": "Feature",
  "properties": {
    "gn:admin1_code":"24",
    "gn:admin2_code":"131.0",
    "gn:asciiname":"Sohagpura",
    "gn:country_code":"IN",
    "gn:dem":389,
    "gn:feature_class":"P",
    "gn:feature_code":"PPL",
    "gn:name":"Soh\u0101gpura",
    "gn:population":0,
    "gn:timezone":"Asia/Kolkata",
    "iso:country":"IN",
    "wof:name":"Sohagpura",
    "wof:placetype":"locality"
},
  "geometry": {"coordinates":[74.70891999999998,23.91966],"type":"Point"}
}