{
  "type": "Feature",
  "properties": {
    "iso:country":"IN",
    "ks:ks_name":"Palri Vyasan",
    "ks:ks_pop":315,
    "ks:ks_type":"HABITATION",
    "name:eng_x_preferred":[
        "Palri Vyasan"
    ],
    "wof:name":"Palri Vyasan",
    "wof:placetype":"locality",
    "wof:population":315
},
  "geometry": {"coordinates":[73.629597,27.031617],"type":"Point"}
}