{
  "type": "Feature",
  "properties": {
    "gn:admin1_code":"2.0",
    "gn:admin2_code":"551.0",
    "gn:asciiname":"Utukuru",
    "gn:country_code":"IN",
    "gn:dem":141,
    "gn:feature_class":"P",
    "gn:feature_code":"PPL",
    "gn:name":"\u016atuk\u016bru",
    "gn:population":0,
    "gn:timezone":"Asia/Kolkata",
    "iso:country":"IN",
    "ks:ks_alt_nam":"\u016atuk\u016bru",
    "ks:ks_name":"Utukuru",
    "ks:ks_type":"VILLAGE",
    "ks:ks_uagg_main":0,
    "name:eng_x_preferred":[
        "Utukuru"
    ],
    "name:eng_x_variant":[
        "\u016atuk\u016bru"
    ],
    "wof:name":"Utukuru",
    "wof:placetype":"locality"
},
  "geometry": {"coordinates":[78.812228,14.450895],"type":"Point"}
}