{
  "type": "Feature",
  "properties": {
    "iso:country":"IN",
    "ks:ks_name":"Samiyapillaipatti",
    "ks:ks_pop":155,
    "ks:ks_type":"HABITATION",
    "name:eng_x_preferred":[
        "Samiyapillaipatti"
    ],
    "wof:name":"Samiyapillaipatti",
    "wof:placetype":"locality",
    "wof:population":155
},
  "geometry": {"coordinates":[78.613612,10.717954],"type":"Point"}
}