{
  "type": "Feature",
  "properties": {
    "gn:admin1_code":"36",
    "gn:admin2_code":"158.0",
    "gn:asciiname":"Purwa Narsingh Narayan",
    "gn:country_code":"IN",
    "gn:dem":117,
    "gn:feature_class":"P",
    "gn:feature_code":"PPL",
    "gn:name":"Purwa Narsingh Nar\u0101yan",
    "gn:population":0,
    "gn:timezone":"Asia/Kolkata",
    "iso:country":"IN",
    "wof:name":"Purwa Narsingh Narayan",
    "wof:placetype":"locality"
},
  "geometry": {"coordinates":[81.45475,26.51076],"type":"Point"}
}