{
  "type": "Feature",
  "properties": {
    "iso:country":"IN",
    "ks:ks_name":"Ponmari",
    "ks:ks_pop":80,
    "ks:ks_type":"HABITATION",
    "name:eng_x_preferred":[
        "Ponmari"
    ],
    "wof:name":"Ponmari",
    "wof:placetype":"locality",
    "wof:population":80
},
  "geometry": {"coordinates":[78.855492,9.596429],"type":"Point"}
}