{
  "type": "Feature",
  "properties": {
    "gn:admin1_code":"34.0",
    "gn:admin2_code":"222.0",
    "gn:asciiname":"Sanok",
    "gn:country_code":"IN",
    "gn:dem":44,
    "gn:feature_class":"P",
    "gn:feature_code":"PPL",
    "gn:name":"S\u0101nok",
    "gn:population":0,
    "gn:timezone":"Asia/Kolkata",
    "iso:country":"IN",
    "name:ara_x_preferred":[
        "\u0633\u0627\u0646\u0648\u0643"
    ],
    "name:bel_x_preferred":[
        "\u0421\u0430\u043d\u0430\u043a"
    ],
    "name:bul_x_preferred":[
        "\u0421\u0430\u043d\u043e\u043a"
    ],
    "name:ces_x_preferred":[
        "Sanok"
    ],
    "name:dan_x_preferred":[
        "Sanok"
    ],
    "name:deu_x_preferred":[
        "Sanok"
    ],
    "name:dsb_x_preferred":[
        "Sanok"
    ],
    "name:epo_x_preferred":[
        "Sanok"
    ],
    "name:est_x_preferred":[
        "Sanok"
    ],
    "name:eus_x_preferred":[
        "Sanok"
    ],
    "name:fas_x_preferred":[
        "\u0633\u0627\u0646\u0648\u06a9"
    ],
    "name:fin_x_preferred":[
        "Sanok"
    ],
    "name:fra_x_preferred":[
        "Sanok"
    ],
    "name:hak_x_preferred":[
        "Sanok"
    ],
    "name:heb_x_preferred":[
        "\u05e1\u05d0\u05e0\u05d5\u05e7"
    ],
    "name:hun_x_preferred":[
        "Sanok"
    ],
    "name:hye_x_preferred":[
        "\u054d\u0561\u0576\u0578\u056f"
    ],
    "name:ind_x_preferred":[
        "Sanok"
    ],
    "name:isl_x_preferred":[
        "Sanok"
    ],
    "name:ita_x_preferred":[
        "Sanok"
    ],
    "name:jav_x_preferred":[
        "Sanok"
    ],
    "name:jpn_x_preferred":[
        "\u30b5\u30ce\u30af"
    ],
    "name:kat_x_preferred":[
        "\u10e1\u10d0\u10dc\u10dd\u10d9\u10d8"
    ],
    "name:kor_x_preferred":[
        "\uc0ac\ub178\ud06c"
    ],
    "name:lat_x_preferred":[
        "Sanocum"
    ],
    "name:lav_x_preferred":[
        "Sanoka"
    ],
    "name:lit_x_preferred":[
        "Sanokas"
    ],
    "name:msa_x_preferred":[
        "Sanok"
    ],
    "name:nld_x_preferred":[
        "Sanok"
    ],
    "name:nno_x_preferred":[
        "Sanok"
    ],
    "name:nor_x_preferred":[
        "Sanok"
    ],
    "name:pol_x_preferred":[
        "Sanok"
    ],
    "name:por_x_preferred":[
        "Sanok"
    ],
    "name:ron_x_preferred":[
        "Sanok"
    ],
    "name:rue_x_preferred":[
        "\u0421\u0430\u043d\u043e\u043a"
    ],
    "name:rus_x_preferred":[
        "\u0421\u0430\u043d\u043e\u043a"
    ],
    "name:sco_x_preferred":[
        "Sanok"
    ],
    "name:slk_x_preferred":[
        "Sanok"
    ],
    "name:spa_x_preferred":[
        "Sanok"
    ],
    "name:srp_x_preferred":[
        "\u0421\u0430\u043d\u043e\u043a"
    ],
    "name:swe_x_preferred":[
        "Sanok"
    ],
    "name:szl_x_preferred":[
        "Sanok"
    ],
    "name:tur_x_preferred":[
        "Sanok"
    ],
    "name:ukr_x_preferred":[
        "\u0421\u044f\u043d\u0456\u043a"
    ],
    "name:vie_x_preferred":[
        "Sanok"
    ],
    "name:war_x_preferred":[
        "Sanok"
    ],
    "name:yid_x_preferred":[
        "\u05e1\u05d0\u05e0\u05d9\u05e7"
    ],
    "name:zho_x_preferred":[
        "\u8428\u8bfa\u514b"
    ],
    "wof:name":"Sanok",
    "wof:placetype":"neighbourhood"
},
  "geometry": {"coordinates":[86.1709,25.46594],"type":"Point"}
}