{
  "type": "Feature",
  "properties": {
    "iso:country":"IN",
    "ks:ks_name":"Shitamau",
    "ks:ks_pop":3,
    "ks:ks_type":"HABITATION",
    "name:eng_x_preferred":[
        "Shitamau"
    ],
    "wof:name":"Shitamau",
    "wof:placetype":"locality",
    "wof:population":3
},
  "geometry": {"coordinates":[75.71311,22.216173],"type":"Point"}
}