{
  "type": "Feature",
  "properties": {
    "iso:country":"IN",
    "ks:ks_name":"Dhumalwadi",
    "ks:ks_pop":221,
    "ks:ks_type":"HABITATION",
    "name:eng_x_preferred":[
        "Dhumalwadi"
    ],
    "wof:name":"Dhumalwadi",
    "wof:placetype":"locality",
    "wof:population":221
},
  "geometry": {"coordinates":[73.89224400000001,16.575331],"type":"Point"}
}