{
  "type": "Feature",
  "properties": {
    "iso:country":"IN",
    "ks:ks_name":"Rawra",
    "ks:ks_pop":591,
    "ks:ks_type":"VILLAGE",
    "name:eng_x_preferred":[
        "Rawra"
    ],
    "wof:name":"Rawra",
    "wof:placetype":"locality",
    "wof:population":591
},
  "geometry": {"coordinates":[72.16861400000001,27.394628],"type":"Point"}
}