{
  "type": "Feature",
  "properties": {
    "iso:country":"IN",
    "ks:ks_alt_nam":"KURMI TOLA",
    "ks:ks_name":"Kurmi Tola",
    "ks:ks_pop":418,
    "ks:ks_type":"HABITATION",
    "name:eng_x_preferred":[
        "Kurmi Tola"
    ],
    "wof:name":"Kurmi Tola",
    "wof:placetype":"locality",
    "wof:population":418
},
  "geometry": {"coordinates":[84.022848,26.508369],"type":"Point"}
}