{
  "type": "Feature",
  "properties": {
    "iso:country":"IN",
    "ks:ks_name":"Uzayar Deeh",
    "ks:ks_pop":127,
    "ks:ks_type":"HABITATION",
    "name:eng_x_preferred":[
        "Uzayar Deeh"
    ],
    "wof:name":"Uzayar Deeh",
    "wof:placetype":"locality",
    "wof:population":127
},
  "geometry": {"coordinates":[82.342607,27.179938],"type":"Point"}
}