{
  "type": "Feature",
  "properties": {
    "iso:country":"IN",
    "ks:ks_name":"Batula",
    "ks:ks_pop":60,
    "ks:ks_type":"HABITATION",
    "name:eng_x_preferred":[
        "Batula"
    ],
    "wof:name":"Batula",
    "wof:placetype":"locality",
    "wof:population":60
},
  "geometry": {"coordinates":[79.28766400000001,29.786187],"type":"Point"}
}