{
  "type": "Feature",
  "properties": {
    "iso:country":"IN",
    "ks:ks_name":"Kamarkoda",
    "ks:ks_pop":120,
    "ks:ks_type":"VILLAGE",
    "name:eng_x_preferred":[
        "Kamarkoda"
    ],
    "wof:name":"Kamarkoda",
    "wof:placetype":"locality",
    "wof:population":120
},
  "geometry": {"coordinates":[84.144955,20.584142],"type":"Point"}
}