{
  "type": "Feature",
  "properties": {
    "iso:country":"IN",
    "ks:ks_name":"Chenkalpotta",
    "ks:ks_pop":225,
    "ks:ks_type":"HABITATION",
    "name:eng_x_preferred":[
        "Chenkalpotta"
    ],
    "wof:name":"Chenkalpotta",
    "wof:placetype":"locality",
    "wof:population":225
},
  "geometry": {"coordinates":[76.551092,10.623299],"type":"Point"}
}