{
  "type": "Feature",
  "properties": {
    "iso:country":"IN",
    "ks:ks_name":"Kannayyapeta",
    "ks:ks_pop":71,
    "ks:ks_type":"HABITATION",
    "name:eng_x_preferred":[
        "Kannayyapeta"
    ],
    "wof:name":"Kannayyapeta",
    "wof:placetype":"locality",
    "wof:population":71
},
  "geometry": {"coordinates":[84.12272900000001,18.681928],"type":"Point"}
}