{
  "type": "Feature",
  "properties": {
    "gn:country":"IN",
    "gn:fcode":"PPL",
    "gn:pop":11432,
    "iso:country":"IN",
    "name:bpy_x_preferred":[
        "\u09a8\u09be\u09b0\u09be\u09af\u09bc\u09a8\u09f1\u09a8\u09ae"
    ],
    "name:chi_x_preferred":[
        "\u7eb3\u62c9\u8036\u7eb3\u74e6\u7eb3\u59c6"
    ],
    "name:dut_x_preferred":[
        "Narayanavanam"
    ],
    "name:eng_x_preferred":[
        "Narayanavanam"
    ],
    "name:ita_x_preferred":[
        "Narayanavanam"
    ],
    "name:may_x_preferred":[
        "Narayanavanam"
    ],
    "name:nan_x_preferred":[
        "Narayanavanam"
    ],
    "name:new_x_preferred":[
        "\u0928\u093e\u0930\u093e\u092f\u0923\u0935\u0928\u092e"
    ],
    "name:pam_x_preferred":[
        "Narayanavanam"
    ],
    "name:por_x_preferred":[
        "Narayanavanam"
    ],
    "name:swe_x_preferred":[
        "N\u0101r\u0101yanavanam"
    ],
    "name:tam_x_preferred":[
        "\u0ba8\u0bbe\u0bb0\u0bbe\u0baf\u0ba3\u0bb5\u0ba9\u0bae\u0bcd"
    ],
    "name:tel_x_preferred":[
        "\u0c28\u0c3e\u0c30\u0c3e\u0c2f\u0c23\u0c35\u0c28\u0c02"
    ],
    "name:unk_x_variant":[
        "N\u0101r\u0101yanavanam"
    ],
    "name:urd_x_preferred":[
        "\u0646\u0627\u0631\u0627\u06cc\u0646\u0627\u0648\u0646\u0645"
    ],
    "name:vie_x_preferred":[
        "Narayanavanam"
    ],
    "qs:name":"Narayanavanam",
    "qs:name_adm0":"India",
    "qs:name_adm1":"Andhra Pradesh",
    "qs:photos_9k":1,
    "qs:photos_9r":1,
    "qs:photos_all":1,
    "qs:photos_sr":0,
    "qs:placetype":"Town",
    "qs:pop_sr":"6",
    "wd:wordcount":241,
    "wof:name":"Narayanavanam",
    "wof:placetype":"locality",
    "wof:population":11432
},
  "geometry": {"coordinates":[79.58882,13.42565],"type":"Point"}
}