{
  "type": "Feature",
  "properties": {
    "iso:country":"IN",
    "name:eng_x_preferred":[
        "Brahmpuri"
    ],
    "qs:gn_adm0_cc":"IN",
    "qs:gn_local":1270351,
    "qs:gn_nam_loc":"Haridwar, Hardwar, Uttarakhand, IN",
    "qs:gn_namadm1":"39",
    "qs:local_max":899,
    "qs:local_sum":2009,
    "qs:localhoods":5,
    "qs:name":"Brahmpuri",
    "qs:name_adm0":"India",
    "qs:name_adm1":"Uttarakhand",
    "qs:name_adm2":"Haridwar",
    "qs:name_local":"Hardwar",
    "qs:photo_max":62,
    "qs:photo_sum":372,
    "qs:placetype":"Suburb",
    "qs:quad_count":14,
    "qs:woe_adm0":23424848,
    "qs:woe_adm1":20070462,
    "qs:woe_adm2":12586750,
    "qs:woe_lau":0,
    "qs:woe_local":2294971,
    "qs:woe_ver":"7.10.0",
    "wof:lang":[
        "eng"
    ],
    "wof:name":"Brahmpuri",
    "wof:placetype":"neighbourhood"
},
  "geometry": {"coordinates":[78.16068799999999,29.948028],"type":"Point"}
}