{
  "type": "Feature",
  "properties": {
    "iso:country":"IN",
    "name:ara_x_preferred":[
        "\u0628\u0631\u0627\u0645\u0628\u0648\u0631\u064a"
    ],
    "name:ben_bn_x_preferred":[
        "\u09ac\u09cd\u09b0\u09b9\u09cd\u09ae\u09aa\u09c1\u09b0\u09c0"
    ],
    "name:ben_in_x_preferred":[
        "\u09ac\u09cd\u09b0\u09b9\u09cd\u09ae\u09aa\u09c1\u09b0\u09c0"
    ],
    "name:eng_x_preferred":[
        "Brahmpuri"
    ],
    "name:guj_x_preferred":[
        "\u0aac\u0acd\u0ab0\u0ab9\u0aae\u0aaa\u0ac1\u0ab0\u0ac0"
    ],
    "name:hin_x_preferred":[
        "\u092c\u094d\u0930\u0939\u094d\u092e\u092a\u0941\u0930\u0940"
    ],
    "name:kan_x_preferred":[
        "\u0cac\u0ccd\u0cb0\u0cb9\u0ccd\u0cae\u0caa\u0cc1\u0cb0\u0cbf"
    ],
    "name:mal_x_preferred":[
        "\u0d2c\u0d4d\u0d30\u0d39\u0d4d\u0d2e\u0d2a\u0d41\u0d30\u0d3f"
    ],
    "name:mar_x_preferred":[
        "\u092c\u094d\u0930\u0939\u094d\u092e\u092a\u0941\u0930\u0940"
    ],
    "name:pan_x_preferred":[
        "\u0a2c\u0a4d\u0a30\u0a39\u0a2e\u0a2a\u0a41\u0a30\u0a40"
    ],
    "name:tam_x_preferred":[
        "\u0baa\u0bbf\u0bb0\u0bae\u0bcd\u0bae\u0baa\u0bc1\u0bb0\u0bbf"
    ],
    "name:tel_x_preferred":[
        "\u0c2c\u0c4d\u0c30\u0c39\u0c4d\u0c2e\u0c4d"
    ],
    "name:urd_x_preferred":[
        "\u0628\u0631\u06c1\u0645 \u067e\u0648\u0631\u06cc"
    ],
    "qs:gn_adm0_cc":"IN",
    "qs:gn_local":1270351,
    "qs:gn_nam_loc":"Haridwar, Hardwar, Uttarakhand, IN",
    "qs:gn_namadm1":"39",
    "qs:local_max":899,
    "qs:local_sum":2009,
    "qs:localhoods":5,
    "qs:name":"Brahmpuri",
    "qs:name_adm0":"India",
    "qs:name_adm1":"Uttarakhand",
    "qs:name_adm2":"Haridwar",
    "qs:name_local":"Hardwar",
    "qs:photo_max":62,
    "qs:photo_sum":372,
    "qs:placetype":"Suburb",
    "qs:quad_count":14,
    "qs:woe_adm0":23424848,
    "qs:woe_adm1":20070462,
    "qs:woe_adm2":12586750,
    "qs:woe_lau":0,
    "qs:woe_local":2294971,
    "qs:woe_ver":"7.10.0",
    "wof:lang":[
        "eng"
    ],
    "wof:name":"Brahmpuri",
    "wof:placetype":"neighbourhood"
},
  "geometry": {"coordinates":[78.16068799999999,29.948028],"type":"Point"}
}