{
  "type": "Feature",
  "properties": {
    "gn:admin1_code":"25",
    "gn:admin2_code":"631.0",
    "gn:asciiname":"Vepanappalle",
    "gn:country_code":"IN",
    "gn:dem":585,
    "gn:feature_class":"P",
    "gn:feature_code":"PPL",
    "gn:name":"Vepanappalle",
    "gn:population":0,
    "gn:timezone":"Asia/Kolkata",
    "iso:country":"IN",
    "name:und_x_variant":[
        "Vepanapalli",
        "Veppanapalli",
        "Vepanappalle"
    ],
    "wof:name":"Vepanappalle",
    "wof:placetype":"locality"
},
  "geometry": {"coordinates":[78.19521,12.70236],"type":"Point"}
}