{
  "type": "Feature",
  "properties": {
    "gn:admin1_code":"36",
    "gn:admin2_code":"168.0",
    "gn:asciiname":"Belpur",
    "gn:country_code":"IN",
    "gn:dem":136,
    "gn:feature_class":"P",
    "gn:feature_code":"PPL",
    "gn:name":"Belpur",
    "gn:population":0,
    "gn:timezone":"Asia/Kolkata",
    "iso:country":"IN",
    "ks:ks_name":"Bilpur",
    "ks:ks_pop":1073,
    "ks:ks_type":"VILLAGE",
    "ks:ks_uagg_main":0,
    "name:eng_x_preferred":[
        "Bilpur"
    ],
    "wof:name":"Bilpur",
    "wof:placetype":"neighbourhood",
    "wof:population":1073
},
  "geometry": {"coordinates":[79.741556,25.797964],"type":"Point"}
}