{
  "type": "Feature",
  "properties": {
    "gn:admin1_code":"12.0",
    "gn:admin2_code":"016",
    "gn:asciiname":"Dranga",
    "gn:country_code":"IN",
    "gn:dem":1408,
    "gn:feature_class":"P",
    "gn:feature_code":"PPL",
    "gn:name":"Dranga",
    "gn:population":0,
    "gn:timezone":"Asia/Kolkata",
    "iso:country":"IN",
    "wof:name":"Dranga",
    "wof:placetype":"locality"
},
  "geometry": {"coordinates":[75.67095,33.01673],"type":"Point"}
}