{
  "type": "Feature",
  "properties": {
    "iso:country":"IN",
    "ks:ks_name":"Bhaskarapuram",
    "ks:ks_pop":88,
    "ks:ks_type":"HABITATION",
    "name:eng_x_preferred":[
        "Bhaskarapuram"
    ],
    "wof:name":"Bhaskarapuram",
    "wof:placetype":"locality",
    "wof:population":88
},
  "geometry": {"coordinates":[79.15177199999999,13.277944],"type":"Point"}
}