{
  "type": "Feature",
  "properties": {
    "iso:country":"IN",
    "ks:ks_alt_nam":"NadaniGaigotha",
    "ks:ks_name":"Nadanigaigotha",
    "ks:ks_pop":110,
    "ks:ks_type":"HABITATION",
    "name:eng_x_preferred":[
        "Nadanigaigotha"
    ],
    "wof:name":"Nadanigaigotha",
    "wof:placetype":"locality",
    "wof:population":110
},
  "geometry": {"coordinates":[73.016735,19.546636],"type":"Point"}
}