{
  "type": "Feature",
  "properties": {
    "iso:country":"IN",
    "ks:ks_name":"Masanithippa",
    "ks:ks_pop":410,
    "ks:ks_type":"HABITATION",
    "name:eng_x_preferred":[
        "Masanithippa"
    ],
    "wof:name":"Masanithippa",
    "wof:placetype":"locality",
    "wof:population":410
},
  "geometry": {"coordinates":[82.273821,16.665359],"type":"Point"}
}