{
  "type": "Feature",
  "properties": {
    "iso:country":"IN",
    "ks:ks_name":"Rajpur",
    "ks:ks_pop":41,
    "ks:ks_type":"VILLAGE",
    "name:eng_x_preferred":[
        "Rajpur"
    ],
    "wof:name":"Rajpur",
    "wof:placetype":"locality",
    "wof:population":41
},
  "geometry": {"coordinates":[83.40711899999999,25.072886],"type":"Point"}
}