{
  "type": "Feature",
  "properties": {
    "gn:admin1_code":"11",
    "gn:admin2_code":"27.0",
    "gn:asciiname":"Kehnchri",
    "gn:country_code":"IN",
    "gn:dem":1036,
    "gn:feature_class":"P",
    "gn:feature_code":"PPL",
    "gn:name":"Kehnchri",
    "gn:population":0,
    "gn:timezone":"Asia/Kolkata",
    "iso:country":"IN",
    "wof:name":"Kehnchri",
    "wof:placetype":"locality"
},
  "geometry": {"coordinates":[76.97851999999997,31.55774000000001],"type":"Point"}
}