{
  "type": "Feature",
  "properties": {
    "iso:country":"IN",
    "ks:ks_name":"Padhipali",
    "ks:ks_pop":134,
    "ks:ks_type":"VILLAGE",
    "name:eng_x_preferred":[
        "Padhipali"
    ],
    "wof:name":"Padhipali",
    "wof:placetype":"locality",
    "wof:population":134
},
  "geometry": {"coordinates":[83.781752,20.988282],"type":"Point"}
}