{
  "type": "Feature",
  "properties": {
    "iso:country":"IN",
    "ks:ks_name":"Piwara",
    "ks:ks_pop":1163,
    "ks:ks_type":"VILLAGE",
    "ks:ks_uagg_main":0,
    "name:eng_x_preferred":[
        "Piwara"
    ],
    "wof:name":"Piwara",
    "wof:placetype":"locality",
    "wof:population":1163
},
  "geometry": {"coordinates":[76.634326,28.181109],"type":"Point"}
}