{
  "type": "Feature",
  "properties": {
    "iso:country":"IN",
    "ks:ks_name":"Harpur Phatikwara",
    "ks:ks_pop":1567,
    "ks:ks_type":"VILLAGE",
    "name:eng_x_preferred":[
        "Harpur Phatikwara"
    ],
    "wof:name":"Harpur Phatikwara",
    "wof:placetype":"locality",
    "wof:population":1567
},
  "geometry": {"coordinates":[85.53544599999999,25.640796],"type":"Point"}
}