{
  "type": "Feature",
  "properties": {
    "iso:country":"IN",
    "ks:ks_name":"Melanpur",
    "ks:ks_pop":116,
    "ks:ks_type":"VILLAGE",
    "ks:ks_uagg_main":0,
    "name:eng_x_preferred":[
        "Melanpur"
    ],
    "wof:name":"Melanpur",
    "wof:placetype":"neighbourhood",
    "wof:population":116
},
  "geometry": {"coordinates":[88.476575,24.253175],"type":"Point"}
}