{
  "type": "Feature",
  "properties": {
    "iso:country":"IN",
    "ks:ks_name":"Vilavayal",
    "ks:ks_pop":397,
    "ks:ks_type":"HABITATION",
    "name:eng_x_preferred":[
        "Vilavayal"
    ],
    "wof:name":"Vilavayal",
    "wof:placetype":"locality",
    "wof:population":397
},
  "geometry": {"coordinates":[78.840109,10.581342],"type":"Point"}
}