{
  "type": "Feature",
  "properties": {
    "iso:country":"IN",
    "ks:ks_name":"Harnau",
    "ks:ks_pop":147,
    "ks:ks_type":"VILLAGE",
    "name:eng_x_preferred":[
        "Harnau"
    ],
    "wof:name":"Harnau",
    "wof:placetype":"locality",
    "wof:population":147
},
  "geometry": {"coordinates":[69.980585,26.741083],"type":"Point"}
}