{
  "type": "Feature",
  "properties": {
    "iso:country":"IN",
    "ks:ks_name":"Upli Fali",
    "ks:ks_pop":80,
    "ks:ks_type":"HABITATION",
    "name:eng_x_preferred":[
        "Upli Fali"
    ],
    "wof:name":"Upli Fali",
    "wof:placetype":"locality",
    "wof:population":80
},
  "geometry": {"coordinates":[72.889256,24.484611],"type":"Point"}
}