{
  "type": "Feature",
  "properties": {
    "iso:country":"IN",
    "ks:ks_alt_nam":"Anna nagar colony",
    "ks:ks_name":"Anna Nagar Colony",
    "ks:ks_pop":1100,
    "ks:ks_type":"HABITATION",
    "name:eng_x_preferred":[
        "Anna Nagar Colony"
    ],
    "wof:name":"Anna Nagar Colony",
    "wof:placetype":"locality",
    "wof:population":1100
},
  "geometry": {"coordinates":[79.51259,11.135454],"type":"Point"}
}