{
  "type": "Feature",
  "properties": {
    "gn:admin1_code":"11.0",
    "gn:admin2_code":"27.0",
    "gn:asciiname":"Shuhlu",
    "gn:country_code":"IN",
    "gn:dem":1045,
    "gn:feature_class":"P",
    "gn:feature_code":"PPL",
    "gn:name":"Sh\u016bhlu",
    "gn:population":0,
    "gn:timezone":"Asia/Kolkata",
    "iso:country":"IN",
    "wof:name":"Shuhlu",
    "wof:placetype":"locality"
},
  "geometry": {"coordinates":[77.07926999999999,31.27122],"type":"Point"}
}