{
  "type": "Feature",
  "properties": {
    "iso:country":"IN",
    "ks:ks_name":"Tamli",
    "ks:ks_pop":697,
    "ks:ks_type":"VILLAGE",
    "name:eng_x_preferred":[
        "Tamli"
    ],
    "wof:name":"Tamli",
    "wof:placetype":"locality",
    "wof:population":697
},
  "geometry": {"coordinates":[80.287221,29.293395],"type":"Point"}
}