{
  "type": "Feature",
  "properties": {
    "gn:admin1_code":"39.0",
    "gn:admin2_code":"60.0",
    "gn:asciiname":"Sirwalgarh",
    "gn:country_code":"IN",
    "gn:dem":671,
    "gn:feature_class":"P",
    "gn:feature_code":"PPL",
    "gn:name":"Sirw\u0101lgarh",
    "gn:population":0,
    "gn:timezone":"Asia/Kolkata",
    "iso:country":"IN",
    "wof:name":"Sirwalgarh",
    "wof:placetype":"locality"
},
  "geometry": {"coordinates":[78.14849,30.28195],"type":"Point"}
}