{
  "type": "Feature",
  "properties": {
    "iso:country":"IN",
    "ks:ks_name":"Dasanagadde",
    "ks:ks_pop":8,
    "ks:ks_type":"HABITATION",
    "name:eng_x_preferred":[
        "Dasanagadde"
    ],
    "wof:name":"Dasanagadde",
    "wof:placetype":"locality",
    "wof:population":8
},
  "geometry": {"coordinates":[75.065983,13.781604],"type":"Point"}
}