{
  "type": "Feature",
  "properties": {
    "gn:admin1_code":"21.0",
    "gn:admin2_code":"396.0",
    "gn:asciiname":"Disaliguda",
    "gn:country_code":"IN",
    "gn:dem":822,
    "gn:feature_class":"P",
    "gn:feature_code":"PPL",
    "gn:name":"Dis\u0101liguda",
    "gn:population":0,
    "gn:timezone":"Asia/Kolkata",
    "iso:country":"IN",
    "ks:ks_name":"Dishariguda",
    "ks:ks_pop":253,
    "ks:ks_type":"HABITATION",
    "name:eng_x_preferred":[
        "Dishariguda"
    ],
    "name:eng_x_variant":[
        "Disaliguda"
    ],
    "wof:name":"Dishariguda",
    "wof:placetype":"locality",
    "wof:population":253
},
  "geometry": {"coordinates":[83.06143,19.150556],"type":"Point"}
}