{
  "type": "Feature",
  "properties": {
    "gn:admin1_code":"35.0",
    "gn:admin2_code":"441.0",
    "gn:asciiname":"Morkatta",
    "gn:country_code":"IN",
    "gn:dem":141,
    "gn:feature_class":"P",
    "gn:feature_code":"PPL",
    "gn:name":"Morkatta",
    "gn:population":0,
    "gn:timezone":"Asia/Kolkata",
    "iso:country":"IN",
    "ks:ks_name":"Morkatta",
    "ks:ks_pop":1305,
    "ks:ks_type":"HABITATION",
    "name:eng_x_preferred":[
        "Morkatta"
    ],
    "wof:name":"Morkatta",
    "wof:placetype":"locality",
    "wof:population":1305
},
  "geometry": {"coordinates":[74.696612,22.041692],"type":"Point"}
}