{
  "type": "Feature",
  "properties": {
    "gn:admin1_code":"34.0",
    "gn:admin2_code":"217.0",
    "gn:asciiname":"Kanchanpur",
    "gn:country_code":"IN",
    "gn:dem":79,
    "gn:feature_class":"P",
    "gn:feature_code":"PPL",
    "gn:name":"K\u0101nchanpur",
    "gn:population":0,
    "gn:timezone":"Asia/Kolkata",
    "iso:country":"IN",
    "ks:ks_alt_nam":"K\u0101nchanpur",
    "ks:ks_name":"Kanchanpur",
    "ks:ks_pop":307,
    "ks:ks_type":"VILLAGE",
    "name:ceb_x_preferred":[
        "Kanchanpur"
    ],
    "name:eng_x_preferred":[
        "Kanchanpur"
    ],
    "name:eng_x_variant":[
        "K\u0101nchanpur"
    ],
    "name:nld_x_preferred":[
        "Kanchanpur"
    ],
    "wof:name":"Kanchanpur",
    "wof:placetype":"locality",
    "wof:population":307
},
  "geometry": {"coordinates":[84.154489,26.513395],"type":"Point"}
}