{
  "type": "Feature",
  "properties": {
    "gn:admin1_code":"19.0",
    "gn:admin2_code":"568.0",
    "gn:asciiname":"Balekoppa",
    "gn:country_code":"IN",
    "gn:dem":579,
    "gn:feature_class":"P",
    "gn:feature_code":"PPL",
    "gn:name":"B\u0101lekoppa",
    "gn:population":0,
    "gn:timezone":"Asia/Kolkata",
    "iso:country":"IN",
    "ks:ks_alt_nam":"B\u0101lekoppa",
    "ks:ks_name":"Balekoppa",
    "ks:ks_type":"VILLAGE",
    "name:eng_x_preferred":[
        "Balekoppa"
    ],
    "name:eng_x_variant":[
        "B\u0101lekoppa"
    ],
    "wof:name":"Balekoppa",
    "wof:placetype":"locality"
},
  "geometry": {"coordinates":[75.036818,13.887463],"type":"Point"}
}