{
  "type": "Feature",
  "properties": {
    "iso:country":"IN",
    "ks:ks_name":"Dungariya",
    "ks:ks_pop":0,
    "ks:ks_type":"VILLAGE",
    "name:eng_x_preferred":[
        "Dungariya"
    ],
    "wof:name":"Dungariya",
    "wof:placetype":"locality",
    "wof:population":0
},
  "geometry": {"coordinates":[75.165813,24.920947],"type":"Point"}
}