{
  "type": "Feature",
  "properties": {
    "iso:country":"IN",
    "ks:ks_name":"Kagade Wasti",
    "ks:ks_pop":562,
    "ks:ks_type":"HABITATION",
    "name:eng_x_preferred":[
        "Kagade Wasti"
    ],
    "wof:name":"Kagade Wasti",
    "wof:placetype":"locality",
    "wof:population":562
},
  "geometry": {"coordinates":[75.4141,17.7387],"type":"Point"}
}