{
  "type": "Feature",
  "properties": {
    "iso:country":"IN",
    "ks:ks_name":"Kurmi Basti",
    "ks:ks_pop":711,
    "ks:ks_type":"HABITATION",
    "name:eng_x_preferred":[
        "Kurmi Basti"
    ],
    "wof:name":"Kurmi Basti",
    "wof:placetype":"locality",
    "wof:population":711
},
  "geometry": {"coordinates":[82.802505,25.326834],"type":"Point"}
}