{
  "type": "Feature",
  "properties": {
    "gn:admin1_code":"2.0",
    "gn:asciiname":"Eguva Sembi",
    "gn:country_code":"IN",
    "gn:dem":732,
    "gn:feature_class":"P",
    "gn:feature_code":"PPL",
    "gn:name":"Eguva Sembi",
    "gn:population":0,
    "gn:timezone":"Asia/Kolkata",
    "iso:country":"IN",
    "wof:name":"Eguva Sembi",
    "wof:placetype":"locality"
},
  "geometry": {"coordinates":[83.07843000000003,18.64897],"type":"Point"}
}