{
  "type": "Feature",
  "properties": {
    "gn:admin1_code":"25.0",
    "gn:admin2_code":"611.0",
    "gn:asciiname":"Onnemund",
    "gn:country_code":"IN",
    "gn:dem":2228,
    "gn:feature_class":"P",
    "gn:feature_code":"PPL",
    "gn:name":"Onnemund",
    "gn:population":0,
    "gn:timezone":"Asia/Kolkata",
    "iso:country":"IN",
    "wof:name":"Onnemund",
    "wof:placetype":"locality"
},
  "geometry": {"coordinates":[76.58977,11.22743],"type":"Point"}
}