{
  "type": "Feature",
  "properties": {
    "iso:country":"IN",
    "ks:ks_alt_nam":"SARATH CHANDRA PARA",
    "ks:ks_name":"Sarath Chandra Para",
    "ks:ks_pop":149,
    "ks:ks_type":"HABITATION",
    "name:eng_x_preferred":[
        "Sarath Chandra Para"
    ],
    "wof:name":"Sarath Chandra Para",
    "wof:placetype":"locality",
    "wof:population":149
},
  "geometry": {"coordinates":[91.695379,23.850306],"type":"Point"}
}