{
  "type": "Feature",
  "properties": {
    "iso:country":"IN",
    "ks:ks_name":"Bazar Tola",
    "ks:ks_pop":1022,
    "ks:ks_type":"HABITATION",
    "name:eng_x_preferred":[
        "Bazar Tola"
    ],
    "wof:name":"Bazar Tola",
    "wof:placetype":"locality",
    "wof:population":1022
},
  "geometry": {"coordinates":[84.21606,26.104414],"type":"Point"}
}