{
  "type": "Feature",
  "properties": {
    "iso:country":"IN",
    "ks:ks_name":"Sivasakthi Nagar",
    "ks:ks_pop":386,
    "ks:ks_type":"HABITATION",
    "ks:ks_uagg_main":0,
    "name:eng_x_preferred":[
        "Sivasakthi Nagar"
    ],
    "wof:name":"Sivasakthi Nagar",
    "wof:placetype":"neighbourhood",
    "wof:population":386
},
  "geometry": {"coordinates":[78.345089,11.716123],"type":"Point"}
}