{
  "type": "Feature",
  "properties": {
    "iso:country":"IN",
    "ks:ks_alt_nam":"SurangpanKhas",
    "ks:ks_name":"Surangpankhas",
    "ks:ks_pop":260,
    "ks:ks_type":"HABITATION",
    "name:eng_x_preferred":[
        "Surangpankhas"
    ],
    "wof:name":"Surangpankhas",
    "wof:placetype":"locality",
    "wof:population":260
},
  "geometry": {"coordinates":[83.437697,23.953804],"type":"Point"}
}