{
  "type": "Feature",
  "properties": {
    "iso:country":"IN",
    "ks:ks_name":"Kalyanpur",
    "ks:ks_pop":928,
    "ks:ks_type":"HABITATION",
    "name:eng_x_preferred":[
        "Kalyanpur"
    ],
    "wof:name":"Kalyanpur",
    "wof:placetype":"locality",
    "wof:population":928
},
  "geometry": {"coordinates":[87.564368,24.939015],"type":"Point"}
}