{
  "type": "Feature",
  "properties": {
    "gn:admin1_code":"35.0",
    "gn:admin2_code":"458",
    "gn:asciiname":"Bandha",
    "gn:country_code":"IN",
    "gn:dem":490,
    "gn:feature_class":"P",
    "gn:feature_code":"PPL",
    "gn:name":"Bandha",
    "gn:population":0,
    "gn:timezone":"Asia/Kolkata",
    "iso:country":"IN",
    "ks:ks_name":"Bandha",
    "ks:ks_pop":574,
    "ks:ks_type":"HABITATION",
    "name:eng_x_preferred":[
        "Bandha"
    ],
    "wof:name":"Bandha",
    "wof:placetype":"locality",
    "wof:population":574
},
  "geometry": {"coordinates":[77.301889,24.88356],"type":"Point"}
}