{
  "type": "Feature",
  "properties": {
    "gn:admin1_code":"37",
    "gn:admin2_code":"410.0",
    "gn:asciiname":"Baunapara",
    "gn:country_code":"IN",
    "gn:dem":329,
    "gn:feature_class":"P",
    "gn:feature_code":"PPL",
    "gn:name":"Baunap\u0101ra",
    "gn:population":0,
    "gn:timezone":"Asia/Kolkata",
    "iso:country":"IN",
    "ks:ks_name":"Banvapara",
    "ks:ks_pop":416,
    "ks:ks_type":"VILLAGE",
    "name:eng_x_preferred":[
        "Banvapara"
    ],
    "name:eng_x_variant":[
        "Baunapara"
    ],
    "wof:name":"Banvapara",
    "wof:placetype":"locality",
    "wof:population":416
},
  "geometry": {"coordinates":[82.478077,20.024743],"type":"Point"}
}