{
  "type": "Feature",
  "properties": {
    "iso:country":"IN",
    "ks:ks_name":"Sundarpur",
    "ks:ks_pop":75,
    "ks:ks_type":"VILLAGE",
    "name:eng_x_preferred":[
        "Sundarpur"
    ],
    "wof:name":"Sundarpur",
    "wof:placetype":"locality",
    "wof:population":75
},
  "geometry": {"coordinates":[85.390068,26.455305],"type":"Point"}
}