{
  "type": "Feature",
  "properties": {
    "iso:country":"IN",
    "ks:ks_name":"Bellumbi",
    "ks:ks_pop":192,
    "ks:ks_type":"HABITATION",
    "name:eng_x_preferred":[
        "Bellumbi"
    ],
    "wof:name":"Bellumbi",
    "wof:placetype":"locality",
    "wof:population":192
},
  "geometry": {"coordinates":[74.882549,14.779518],"type":"Point"}
}