{
  "type": "Feature",
  "properties": {
    "iso:country":"IN",
    "ks:ks_name":"Boga Para",
    "ks:ks_pop":55,
    "ks:ks_type":"HABITATION",
    "name:eng_x_preferred":[
        "Boga Para"
    ],
    "wof:name":"Boga Para",
    "wof:placetype":"locality",
    "wof:population":55
},
  "geometry": {"coordinates":[81.669895,19.325133],"type":"Point"}
}