{
  "type": "Feature",
  "properties": {
    "iso:country":"IN",
    "ks:ks_name":"Dagaon No 2",
    "ks:ks_pop":272,
    "ks:ks_type":"HABITATION",
    "name:eng_x_preferred":[
        "Dagaon No 2"
    ],
    "wof:name":"Dagaon No 2",
    "wof:placetype":"locality",
    "wof:population":272
},
  "geometry": {"coordinates":[93.832272,26.023751],"type":"Point"}
}