{
  "type": "Feature",
  "properties": {
    "gn:admin1_code":"39.0",
    "gn:admin2_code":"64.0",
    "gn:asciiname":"Kanalgaon",
    "gn:country_code":"IN",
    "gn:dem":1274,
    "gn:feature_class":"P",
    "gn:feature_code":"PPL",
    "gn:name":"Kanalgaon",
    "gn:population":0,
    "gn:timezone":"Asia/Kolkata",
    "iso:country":"IN",
    "wof:name":"Kanalgaon",
    "wof:placetype":"locality"
},
  "geometry": {"coordinates":[79.49228000000002,29.74821],"type":"Point"}
}