{
  "type": "Feature",
  "properties": {
    "gn:admin1_code":"21",
    "gn:admin2_code":"374.0",
    "gn:asciiname":"Kharu",
    "gn:country_code":"IN",
    "gn:dem":307,
    "gn:feature_class":"P",
    "gn:feature_code":"PPL",
    "gn:name":"Kh\u0101ru",
    "gn:population":0,
    "gn:timezone":"Asia/Kolkata",
    "iso:country":"IN",
    "ks:ks_name":"Khadu",
    "ks:ks_pop":88,
    "ks:ks_type":"VILLAGE",
    "name:eng_x_preferred":[
        "Khadu"
    ],
    "name:eng_x_variant":[
        "Kharu"
    ],
    "wof:name":"Khadu",
    "wof:placetype":"locality",
    "wof:population":88
},
  "geometry": {"coordinates":[83.57614,21.999294],"type":"Point"}
}