{
  "type": "Feature",
  "properties": {
    "gn:admin1_code":"19.0",
    "gn:admin2_code":"563.0",
    "gn:asciiname":"Vajgod",
    "gn:country_code":"IN",
    "gn:dem":548,
    "gn:feature_class":"P",
    "gn:feature_code":"PPL",
    "gn:name":"V\u0101jgod",
    "gn:population":0,
    "gn:timezone":"Asia/Kolkata",
    "iso:country":"IN",
    "ks:ks_alt_nam":"V\u0101jgod",
    "ks:ks_name":"Vajgod",
    "ks:ks_type":"VILLAGE",
    "name:eng_x_preferred":[
        "Vajgod"
    ],
    "name:eng_x_variant":[
        "V\u0101jgod"
    ],
    "wof:name":"Vajgod",
    "wof:placetype":"locality"
},
  "geometry": {"coordinates":[74.725216,14.31273],"type":"Point"}
}