{
  "type": "Feature",
  "properties": {
    "iso:country":"IN",
    "ks:ks_name":"Patti Deeh",
    "ks:ks_pop":273,
    "ks:ks_type":"HABITATION",
    "name:eng_x_preferred":[
        "Patti Deeh"
    ],
    "wof:name":"Patti Deeh",
    "wof:placetype":"locality",
    "wof:population":273
},
  "geometry": {"coordinates":[82.933677,27.337407],"type":"Point"}
}