{
  "type": "Feature",
  "properties": {
    "gn:admin1_code":"37",
    "gn:admin2_code":"414.0",
    "gn:asciiname":"Suliagam",
    "gn:country_code":"IN",
    "gn:dem":567,
    "gn:feature_class":"P",
    "gn:feature_code":"PPL",
    "gn:name":"Suli\u0101g\u0101m",
    "gn:population":0,
    "gn:timezone":"Asia/Kolkata",
    "iso:country":"IN",
    "wof:name":"Suliagam",
    "wof:placetype":"locality"
},
  "geometry": {"coordinates":[82.07380000000001,19.03642],"type":"Point"}
}