{
  "type": "Feature",
  "properties": {
    "iso:country":"IN",
    "ks:ks_alt_nam":"Kishanpuri",
    "ks:ks_name":"Kishanpur",
    "ks:ks_type":"VILLAGE",
    "name:eng_x_preferred":[
        "Kishanpur"
    ],
    "name:eng_x_variant":[
        "Kishanpuri"
    ],
    "wof:name":"Kishanpur",
    "wof:placetype":"locality"
},
  "geometry": {"coordinates":[81.548277,20.520463],"type":"Point"}
}