{
  "type": "Feature",
  "properties": {
    "iso:country":"IN",
    "ks:ks_name":"Udhawa Kathra",
    "ks:ks_pop":564,
    "ks:ks_type":"HABITATION",
    "name:eng_x_preferred":[
        "Udhawa Kathra"
    ],
    "wof:name":"Udhawa Kathra",
    "wof:placetype":"locality",
    "wof:population":564
},
  "geometry": {"coordinates":[83.31090399999999,23.320428],"type":"Point"}
}