{
  "type": "Feature",
  "properties": {
    "iso:country":"IN",
    "ks:ks_name":"Mahipal",
    "ks:ks_pop":1549,
    "ks:ks_type":"VILLAGE",
    "ks:ks_uagg_main":0,
    "name:eng_x_preferred":[
        "Mahipal"
    ],
    "wof:name":"Mahipal",
    "wof:placetype":"neighbourhood",
    "wof:population":1549
},
  "geometry": {"coordinates":[88.346144,26.589995],"type":"Point"}
}