{
  "type": "Feature",
  "properties": {
    "gn:admin1_code":"36.0",
    "gn:admin2_code":"173.0",
    "gn:asciiname":"Rangauli",
    "gn:country_code":"IN",
    "gn:dem":104,
    "gn:feature_class":"P",
    "gn:feature_code":"PPL",
    "gn:name":"Rangauli",
    "gn:population":0,
    "gn:timezone":"Asia/Kolkata",
    "iso:country":"IN",
    "wof:name":"Rangauli",
    "wof:placetype":"locality"
},
  "geometry": {"coordinates":[81.94556999999998,25.83126],"type":"Point"}
}