{
  "type": "Feature",
  "properties": {
    "iso:country":"IN",
    "ks:ks_name":"No.1 Bishnupur",
    "ks:ks_pop":529,
    "ks:ks_type":"VILLAGE",
    "ks:ks_uagg_main":0,
    "name:eng_x_preferred":[
        "No.1 Bishnupur"
    ],
    "wof:name":"No.1 Bishnupur",
    "wof:placetype":"neighbourhood",
    "wof:population":529
},
  "geometry": {"coordinates":[94.518756,27.526803],"type":"Point"}
}