{
  "type": "Feature",
  "properties": {
    "gn:admin1_code":"36.0",
    "gn:admin2_code":"173.0",
    "gn:asciiname":"Kamas",
    "gn:country_code":"IN",
    "gn:dem":101,
    "gn:feature_class":"P",
    "gn:feature_code":"PPL",
    "gn:name":"Kam\u0101s",
    "gn:population":0,
    "gn:timezone":"Asia/Kolkata",
    "iso:country":"IN",
    "name:ceb_x_preferred":[
        "Kamas"
    ],
    "name:ces_x_preferred":[
        "Kamas"
    ],
    "wof:name":"Kamas",
    "wof:placetype":"locality"
},
  "geometry": {"coordinates":[81.99523000000001,25.98696],"type":"Point"}
}