{
  "type": "Feature",
  "properties": {
    "iso:country":"IN",
    "ks:ks_name":"Sharifabad",
    "ks:ks_pop":551,
    "ks:ks_type":"VILLAGE",
    "name:eng_x_preferred":[
        "Sharifabad"
    ],
    "wof:name":"Sharifabad",
    "wof:placetype":"locality",
    "wof:population":551
},
  "geometry": {"coordinates":[78.080094,28.723534],"type":"Point"}
}