{
  "type": "Feature",
  "properties": {
    "iso:country":"IN",
    "ks:ks_alt_nam":"Andh\u0101ri",
    "ks:ks_name":"Andhari",
    "ks:ks_pop":385,
    "ks:ks_type":"VILLAGE",
    "name:eng_x_preferred":[
        "Andhari"
    ],
    "name:eng_x_variant":[
        "Andh\u0101ri"
    ],
    "wof:name":"Andhari",
    "wof:placetype":"locality",
    "wof:population":385
},
  "geometry": {"coordinates":[86.07819000000001,24.09588],"type":"Point"}
}