{
  "type": "Feature",
  "properties": {
    "iso:country":"IN",
    "ks:ks_name":"Vadakattalai",
    "ks:ks_pop":501,
    "ks:ks_type":"HABITATION",
    "name:eng_x_preferred":[
        "Vadakattalai"
    ],
    "wof:name":"Vadakattalai",
    "wof:placetype":"locality",
    "wof:population":501
},
  "geometry": {"coordinates":[79.81783,11.097453],"type":"Point"}
}