{
  "type": "Feature",
  "properties": {
    "iso:country":"IN",
    "ks:ks_name":"Remu",
    "ks:ks_pop":1913,
    "ks:ks_type":"VILLAGE",
    "ks:ks_uagg_main":0,
    "name:eng_x_preferred":[
        "Remu"
    ],
    "wof:name":"Remu",
    "wof:placetype":"neighbourhood",
    "wof:population":1913
},
  "geometry": {"coordinates":[87.21350700000001,21.670133],"type":"Point"}
}