{
  "type": "Feature",
  "properties": {
    "iso:country":"IN",
    "ks:ks_name":"Lakrapahari",
    "ks:ks_pop":226,
    "ks:ks_type":"VILLAGE",
    "name:eng_x_preferred":[
        "Lakrapahari"
    ],
    "wof:name":"Lakrapahari",
    "wof:placetype":"locality",
    "wof:population":226
},
  "geometry": {"coordinates":[86.94592799999999,24.381126],"type":"Point"}
}