{
  "type": "Feature",
  "properties": {
    "gn:admin1_code":"37",
    "gn:admin2_code":"410.0",
    "gn:asciiname":"Nahinbiri",
    "gn:country_code":"IN",
    "gn:dem":489,
    "gn:feature_class":"P",
    "gn:feature_code":"PPL",
    "gn:name":"N\u0101hinbiri",
    "gn:population":0,
    "gn:timezone":"Asia/Kolkata",
    "iso:country":"IN",
    "wof:name":"Nahinbiri",
    "wof:placetype":"locality"
},
  "geometry": {"coordinates":[82.22045,20.28471],"type":"Point"}
}