{
  "type": "Feature",
  "properties": {
    "gn:admin1_code":"36.0",
    "gn:admin2_code":"133.0",
    "gn:asciiname":"Tajpur Kalan",
    "gn:country_code":"IN",
    "gn:dem":254,
    "gn:feature_class":"P",
    "gn:feature_code":"PPL",
    "gn:name":"T\u0101jpur Kal\u0101n",
    "gn:population":0,
    "gn:timezone":"Asia/Kolkata",
    "iso:country":"IN",
    "name:ara_x_preferred":[
        "\u062a\u0627\u062c\u0628\u0648\u0631 \u0643\u0627\u0644\u0627\u0646"
    ],
    "name:ben_bn_x_preferred":[
        "\u09a4\u09be\u099c\u09aa\u09c1\u09b0 \u0995\u09be\u09b2\u09be\u09a8"
    ],
    "name:ben_in_x_preferred":[
        "\u09a4\u09be\u099c\u09aa\u09c1\u09b0 \u0995\u09be\u09b2\u09be\u09a8"
    ],
    "name:guj_x_preferred":[
        "\u0aa4\u0abe\u0a9c\u0aaa\u0ac1\u0ab0 \u0a95\u0abe\u0ab2\u0aa8"
    ],
    "name:hin_x_preferred":[
        "\u0924\u093e\u091c\u092a\u0941\u0930 \u0915\u0932\u093e\u0902"
    ],
    "name:kan_x_preferred":[
        "\u0ca4\u0cbe\u0c9c\u0ccd"
    ],
    "name:mal_x_preferred":[
        "\u0d24\u0d3e\u0d1c\u0d4d\u0d2a\u0d42\u0d7c \u0d15\u0d32\u0d3e\u0d7b"
    ],
    "name:mar_x_preferred":[
        "\u0924\u093e\u091c\u092a\u0942\u0930 \u0915\u0932\u093e\u0928"
    ],
    "name:pan_x_preferred":[
        "\u0a24\u0a3e\u0a1c\u0a2a\u0a41\u0a30 \u0a15\u0a32\u0a3e\u0a02"
    ],
    "name:tam_x_preferred":[
        "\u0ba4\u0bbe\u0b9c\u0bcd\u0baa\u0bc2\u0bb0\u0bcd \u0b95\u0bb2\u0ba9\u0bcd"
    ],
    "name:tel_x_preferred":[
        "\u0c24\u0c47\u0c1c\u0c4d"
    ],
    "name:urd_x_preferred":[
        "\u062a\u0627\u062c \u067e\u0648\u0631 \u06a9\u0644\u0627\u06ba"
    ],
    "wof:name":"Tajpur Kalan",
    "wof:placetype":"neighbourhood"
},
  "geometry": {"coordinates":[77.79579,29.58886],"type":"Point"}
}