{
  "type": "Feature",
  "properties": {
    "iso:country":"IN",
    "ks:ks_name":"Parewa",
    "ks:ks_pop":3630,
    "ks:ks_type":"VILLAGE",
    "ks:ks_uagg_main":0,
    "name:eng_x_preferred":[
        "Parewa"
    ],
    "wof:name":"Parewa",
    "wof:placetype":"neighbourhood",
    "wof:population":3630
},
  "geometry": {"coordinates":[85.098074,26.63472],"type":"Point"}
}