{
  "type": "Feature",
  "properties": {
    "iso:country":"IN",
    "ks:ks_name":"Pathakhole",
    "ks:ks_pop":271,
    "ks:ks_type":"HABITATION",
    "name:eng_x_preferred":[
        "Pathakhole"
    ],
    "wof:name":"Pathakhole",
    "wof:placetype":"locality",
    "wof:population":271
},
  "geometry": {"coordinates":[84.200177,20.320101],"type":"Point"}
}