{
  "type": "Feature",
  "properties": {
    "iso:country":"IN",
    "ks:ks_name":"Dhanua Khera",
    "ks:ks_pop":0,
    "ks:ks_type":"VILLAGE",
    "name:eng_x_preferred":[
        "Dhanua Khera"
    ],
    "wof:name":"Dhanua Khera",
    "wof:placetype":"locality",
    "wof:population":0
},
  "geometry": {"coordinates":[79.822097,27.766048],"type":"Point"}
}