{
  "type": "Feature",
  "properties": {
    "gn:admin1_code":"40",
    "gn:admin2_code":"539.0",
    "gn:asciiname":"Bharatpur",
    "gn:country_code":"IN",
    "gn:dem":241,
    "gn:feature_class":"P",
    "gn:feature_code":"PPL",
    "gn:name":"Bharatpur",
    "gn:population":0,
    "gn:timezone":"Asia/Kolkata",
    "iso:country":"IN",
    "wof:name":"Bharatpur",
    "wof:placetype":"locality"
},
  "geometry": {"coordinates":[79.08752,16.74114],"type":"Point"}
}