{
  "type": "Feature",
  "properties": {
    "iso:country":"IN",
    "ks:ks_name":"Adarsh Dharasar",
    "ks:ks_pop":142,
    "ks:ks_type":"VILLAGE",
    "name:eng_x_preferred":[
        "Adarsh Dharasar"
    ],
    "wof:name":"Adarsh Dharasar",
    "wof:placetype":"locality",
    "wof:population":142
},
  "geometry": {"coordinates":[70.97706100000001,25.537781],"type":"Point"}
}