{
  "type": "Feature",
  "properties": {
    "iso:country":"IN",
    "ks:ks_name":"Khamar Simulia",
    "ks:ks_pop":0,
    "ks:ks_type":"VILLAGE",
    "name:eng_x_preferred":[
        "Khamar Simulia"
    ],
    "wof:name":"Khamar Simulia",
    "wof:placetype":"locality",
    "wof:population":0
},
  "geometry": {"coordinates":[88.52228700000001,23.331246],"type":"Point"}
}