{
  "type": "Feature",
  "properties": {
    "iso:country":"IN",
    "ks:ks_name":"Paiza",
    "ks:ks_pop":132,
    "ks:ks_type":"HABITATION",
    "name:eng_x_preferred":[
        "Paiza"
    ],
    "wof:name":"Paiza",
    "wof:placetype":"locality",
    "wof:population":132
},
  "geometry": {"coordinates":[92.955364,25.274785],"type":"Point"}
}