{
  "type": "Feature",
  "properties": {
    "gn:admin1_code":"13.0",
    "gn:admin2_code":"595.0",
    "gn:asciiname":"Vengola Padinjarattumbagam",
    "gn:country_code":"IN",
    "gn:dem":30,
    "gn:feature_class":"P",
    "gn:feature_code":"PPL",
    "gn:name":"Vengola Padinj\u0101rattumb\u0101gam",
    "gn:population":0,
    "gn:timezone":"Asia/Kolkata",
    "iso:country":"IN",
    "wof:name":"Vengola Padinjarattumbagam",
    "wof:placetype":"locality"
},
  "geometry": {"coordinates":[76.44344,10.07348],"type":"Point"}
}