{
  "type": "Feature",
  "properties": {
    "gn:admin1_code":"36",
    "gn:admin2_code":"201.0",
    "gn:asciiname":"Kosman",
    "gn:country_code":"IN",
    "gn:dem":174,
    "gn:feature_class":"P",
    "gn:feature_code":"PPL",
    "gn:name":"Kosm\u0101n",
    "gn:population":0,
    "gn:timezone":"Asia/Kolkata",
    "iso:country":"IN",
    "name:bos_x_preferred":[
        "Kosman"
    ],
    "name:fra_x_preferred":[
        "Kosman"
    ],
    "name:hrv_x_preferred":[
        "Kosman"
    ],
    "name:srp_x_preferred":[
        "\u041a\u043e\u0441\u043c\u0430\u043d"
    ],
    "wof:name":"Kosman",
    "wof:placetype":"locality"
},
  "geometry": {"coordinates":[78.29385000000001,27.44224],"type":"Point"}
}