{
  "type": "Feature",
  "properties": {
    "gn:admin1_code":"36.0",
    "gn:admin2_code":"140.0",
    "gn:asciiname":"Gotra",
    "gn:country_code":"IN",
    "gn:dem":220,
    "gn:feature_class":"P",
    "gn:feature_code":"PPL",
    "gn:name":"Gotra",
    "gn:population":0,
    "gn:timezone":"Asia/Kolkata",
    "iso:country":"IN",
    "name:deu_x_preferred":[
        "Gotra"
    ],
    "name:fra_x_preferred":[
        "Gotra"
    ],
    "name:hin_x_preferred":[
        "\u0917\u094b\u0924\u094d\u0930"
    ],
    "name:ita_x_preferred":[
        "Gotra"
    ],
    "name:jpn_x_preferred":[
        "\u30b4\u30fc\u30c8\u30e9"
    ],
    "name:lit_x_preferred":[
        "Gotra"
    ],
    "name:mar_x_preferred":[
        "\u0917\u094b\u0924\u094d\u0930"
    ],
    "name:nep_x_preferred":[
        "\u0917\u094b\u0924\u094d\u0930"
    ],
    "name:new_x_preferred":[
        "\u0917\u094b\u0924\u094d\u0930"
    ],
    "name:por_x_preferred":[
        "Gotra"
    ],
    "name:rus_x_preferred":[
        "\u0413\u043e\u0442\u0440\u0430"
    ],
    "name:spa_x_preferred":[
        "Gotra"
    ],
    "name:swe_x_preferred":[
        "Gotra"
    ],
    "name:tam_x_preferred":[
        "\u0b95\u0bcb\u0ba4\u0bcd\u0ba4\u0bbf\u0bb0\u0bae\u0bcd"
    ],
    "name:tel_x_preferred":[
        "\u0c17\u0c4b\u0c24\u0c4d\u0c30\u0c2e\u0c41\u0c32\u0c41"
    ],
    "name:urd_x_preferred":[
        "\u06af\u0648\u062a\u0631"
    ],
    "name:vie_x_preferred":[
        "Gothra"
    ],
    "wof:name":"Gotra",
    "wof:placetype":"locality"
},
  "geometry": {"coordinates":[77.29798000000002,28.81735],"type":"Point"}
}