{
  "type": "Feature",
  "properties": {
    "gn:admin1_code":"2.0",
    "gn:admin2_code":"546.0",
    "gn:asciiname":"Goglanka",
    "gn:country_code":"IN",
    "gn:dem":503,
    "gn:feature_class":"P",
    "gn:feature_code":"PPL",
    "gn:name":"Goglanka",
    "gn:population":0,
    "gn:timezone":"Asia/Kolkata",
    "iso:country":"IN",
    "wof:name":"Goglanka",
    "wof:placetype":"locality"
},
  "geometry": {"coordinates":[81.42715,17.36705],"type":"Point"}
}