{
  "type": "Feature",
  "properties": {
    "iso:country":"IN",
    "ks:ks_alt_nam":"MENDH VASAHAT",
    "ks:ks_name":"Mendh Vasahat",
    "ks:ks_pop":75,
    "ks:ks_type":"HABITATION",
    "name:eng_x_preferred":[
        "Mendh Vasahat"
    ],
    "wof:name":"Mendh Vasahat",
    "wof:placetype":"locality",
    "wof:population":75
},
  "geometry": {"coordinates":[74.297881,17.351539],"type":"Point"}
}