{
  "type": "Feature",
  "properties": {
    "iso:country":"IN",
    "ks:ks_name":"No 2 Chelajan Kachari",
    "ks:ks_pop":381,
    "ks:ks_type":"HABITATION",
    "name:eng_x_preferred":[
        "No 2 Chelajan Kachari"
    ],
    "wof:name":"No 2 Chelajan Kachari",
    "wof:placetype":"locality",
    "wof:population":381
},
  "geometry": {"coordinates":[94.35859600000001,27.373718],"type":"Point"}
}