{
  "type": "Feature",
  "properties": {
    "gn:admin1_code":"36",
    "gn:admin2_code":"200.0",
    "gn:asciiname":"Sundari",
    "gn:country_code":"IN",
    "gn:dem":258,
    "gn:feature_class":"P",
    "gn:feature_code":"PPL",
    "gn:name":"Sundari",
    "gn:population":0,
    "gn:timezone":"Asia/Kolkata",
    "iso:country":"IN",
    "ks:ks_name":"Sundari",
    "ks:ks_pop":2466,
    "ks:ks_type":"VILLAGE",
    "name:eng_x_preferred":[
        "Sundari"
    ],
    "wof:name":"Sundari",
    "wof:placetype":"locality",
    "wof:population":2466
},
  "geometry": {"coordinates":[83.30006299999999,24.100851],"type":"Point"}
}