{
  "type": "Feature",
  "properties": {
    "iso:country":"IN",
    "ks:ks_name":"Bazartilla",
    "ks:ks_pop":235,
    "ks:ks_type":"HABITATION",
    "ks:ks_uagg_main":0,
    "name:eng_x_preferred":[
        "Bazartilla"
    ],
    "wof:name":"Bazartilla",
    "wof:placetype":"neighbourhood",
    "wof:population":235
},
  "geometry": {"coordinates":[91.19638,23.586845],"type":"Point"}
}