{
  "type": "Feature",
  "properties": {
    "iso:country":"IN",
    "ks:ks_name":"Shettarakudru",
    "ks:ks_pop":140,
    "ks:ks_type":"HABITATION",
    "name:eng_x_preferred":[
        "Shettarakudru"
    ],
    "wof:name":"Shettarakudru",
    "wof:placetype":"locality",
    "wof:population":140
},
  "geometry": {"coordinates":[74.757059,13.456444],"type":"Point"}
}