{
  "type": "Feature",
  "properties": {
    "iso:country":"IN",
    "ks:ks_name":"Kunjamahul",
    "ks:ks_pop":239,
    "ks:ks_type":"VILLAGE",
    "name:eng_x_preferred":[
        "Kunjamahul"
    ],
    "wof:name":"Kunjamahul",
    "wof:placetype":"locality",
    "wof:population":239
},
  "geometry": {"coordinates":[84.260104,20.896194],"type":"Point"}
}