{
  "type": "Feature",
  "properties": {
    "iso:country":"IN",
    "ks:ks_name":"Arenoor",
    "ks:ks_pop":64,
    "ks:ks_type":"HABITATION",
    "name:eng_x_preferred":[
        "Arenoor"
    ],
    "wof:name":"Arenoor",
    "wof:placetype":"locality",
    "wof:population":64
},
  "geometry": {"coordinates":[75.42911100000001,13.337923],"type":"Point"}
}