{
  "type": "Feature",
  "properties": {
    "gn:admin1_code":"36",
    "gn:admin2_code":"134.0",
    "gn:asciiname":"Prithvipur",
    "gn:country_code":"IN",
    "gn:dem":226,
    "gn:feature_class":"P",
    "gn:feature_code":"PPL",
    "gn:name":"Prithv\u012bpur",
    "gn:population":0,
    "gn:timezone":"Asia/Kolkata",
    "iso:country":"IN",
    "name:ben_x_preferred":[
        "\u09aa\u09c3\u09a5\u09cd\u09ac\u09c0\u09aa\u09c1\u09b0"
    ],
    "name:bpy_x_preferred":[
        "\u09aa\u09c3\u09a5\u09ac\u09c0\u09aa\u09c1\u09b0"
    ],
    "name:ita_x_preferred":[
        "Prithvipur"
    ],
    "name:msa_x_preferred":[
        "Prithvipur"
    ],
    "name:nld_x_preferred":[
        "Prithvipur"
    ],
    "name:ori_x_preferred":[
        "\u0b2a\u0b43\u0b25\u0b3f\u0b2c\u0b40\u0b2a\u0b41\u0b30"
    ],
    "name:por_x_preferred":[
        "Prithvipur"
    ],
    "name:spa_x_preferred":[
        "Prithvipur"
    ],
    "name:vie_x_preferred":[
        "Prithvipur"
    ],
    "name:zho_x_preferred":[
        "\u666e\u91cc\u7279\u7ef4\u666e\u5c14"
    ],
    "wof:name":"Prithvipur",
    "wof:placetype":"locality"
},
  "geometry": {"coordinates":[78.23730999999999,29.08619],"type":"Point"}
}