{
  "type": "Feature",
  "properties": {
    "iso:country":"IN",
    "ks:ks_name":"Sutara",
    "ks:ks_pop":227,
    "ks:ks_type":"HABITATION",
    "name:eng_x_preferred":[
        "Sutara"
    ],
    "wof:name":"Sutara",
    "wof:placetype":"locality",
    "wof:population":227
},
  "geometry": {"coordinates":[79.256254,28.312431],"type":"Point"}
}