{
  "type": "Feature",
  "properties": {
    "gn:country":"IN",
    "gn:fcode":"PPL",
    "gn:pop":6244,
    "iso:country":"IN",
    "qs:name":"Sankarpur",
    "qs:name_adm0":"India",
    "qs:name_adm1":"West Bengal",
    "qs:photos_9r":0,
    "qs:photos_sr":0,
    "qs:placetype":"Town",
    "qs:pop_sr":"5",
    "wd:wordcount":12,
    "wof:name":"Sankarpur",
    "wof:placetype":"locality",
    "wof:population":6244
},
  "geometry": {"coordinates":[88.45126,22.84839],"type":"Point"}
}