{
  "type": "Feature",
  "properties": {
    "iso:country":"IN",
    "ks:ks_name":"Misrana",
    "ks:ks_pop":300,
    "ks:ks_type":"HABITATION",
    "name:eng_x_preferred":[
        "Misrana"
    ],
    "wof:name":"Misrana",
    "wof:placetype":"locality",
    "wof:population":300
},
  "geometry": {"coordinates":[82.676513,26.265429],"type":"Point"}
}