{
  "type": "Feature",
  "properties": {
    "iso:country":"IN",
    "ks:ks_name":"Virahimpur",
    "ks:ks_pop":17,
    "ks:ks_type":"VILLAGE",
    "name:eng_x_preferred":[
        "Virahimpur"
    ],
    "wof:name":"Virahimpur",
    "wof:placetype":"locality",
    "wof:population":17
},
  "geometry": {"coordinates":[82.18754300000001,26.841701],"type":"Point"}
}