{
  "type": "Feature",
  "properties": {
    "iso:country":"IN",
    "ks:ks_name":"Challewada",
    "ks:ks_pop":3148,
    "ks:ks_type":"HABITATION",
    "name:eng_x_preferred":[
        "Challewada"
    ],
    "wof:name":"Challewada",
    "wof:placetype":"locality",
    "wof:population":3148
},
  "geometry": {"coordinates":[80.180474,19.226618],"type":"Point"}
}