{
  "type": "Feature",
  "properties": {
    "iso:country":"IN",
    "ks:ks_name":"Fafal I",
    "ks:ks_pop":920,
    "ks:ks_type":"HABITATION",
    "name:eng_x_preferred":[
        "Fafal I"
    ],
    "wof:name":"Fafal I",
    "wof:placetype":"locality",
    "wof:population":920
},
  "geometry": {"coordinates":[90.820885,25.991811],"type":"Point"}
}