{
  "type": "Feature",
  "properties": {
    "gn:admin1_code":"16.0",
    "gn:admin2_code":"499.0",
    "gn:asciiname":"Nimbhori Budrukh",
    "gn:country_code":"IN",
    "gn:dem":269,
    "gn:feature_class":"P",
    "gn:feature_code":"PPL",
    "gn:name":"Nimbhori Budrukh",
    "gn:population":0,
    "gn:timezone":"Asia/Kolkata",
    "iso:country":"IN",
    "ks:ks_name":"Nimbhori Budrukh",
    "ks:ks_type":"VILLAGE",
    "ks:ks_uagg_main":0,
    "name:eng_x_preferred":[
        "Nimbhori Budrukh"
    ],
    "wof:name":"Nimbhori Budrukh",
    "wof:placetype":"neighbourhood"
},
  "geometry": {"coordinates":[75.414666,20.626435],"type":"Point"}
}