{
  "type": "Feature",
  "properties": {
    "iso:country":"IN",
    "ks:ks_name":"Kukurghrhi",
    "ks:ks_pop":0,
    "ks:ks_type":"VILLAGE",
    "name:eng_x_preferred":[
        "Kukurghrhi"
    ],
    "wof:name":"Kukurghrhi",
    "wof:placetype":"locality",
    "wof:population":0
},
  "geometry": {"coordinates":[82.489474,26.119693],"type":"Point"}
}