{
  "type": "Feature",
  "properties": {
    "iso:country":"IN",
    "ks:ks_name":"Rajajan",
    "ks:ks_pop":361,
    "ks:ks_type":"VILLAGE",
    "ks:ks_uagg_main":0,
    "name:eng_x_preferred":[
        "Rajajan"
    ],
    "wof:name":"Rajajan",
    "wof:placetype":"neighbourhood",
    "wof:population":361
},
  "geometry": {"coordinates":[90.46811700000001,26.531381],"type":"Point"}
}