{
  "type": "Feature",
  "properties": {
    "iso:country":"IN",
    "ks:ks_name":"Jala",
    "ks:ks_pop":57,
    "ks:ks_type":"VILLAGE",
    "name:eng_x_preferred":[
        "Jala"
    ],
    "wof:name":"Jala",
    "wof:placetype":"locality",
    "wof:population":57
},
  "geometry": {"coordinates":[86.678742,24.977473],"type":"Point"}
}