{
  "type": "Feature",
  "properties": {
    "iso:country":"IN",
    "ks:ks_alt_nam":"Khori pada",
    "ks:ks_name":"Khori Pada",
    "ks:ks_pop":266,
    "ks:ks_type":"HABITATION",
    "name:eng_x_preferred":[
        "Khori Pada"
    ],
    "wof:name":"Khori Pada",
    "wof:placetype":"locality",
    "wof:population":266
},
  "geometry": {"coordinates":[72.993967,19.818179],"type":"Point"}
}