{
  "type": "Feature",
  "properties": {
    "iso:country":"IN",
    "ks:ks_name":"Lalsinghpura",
    "ks:ks_pop":638,
    "ks:ks_type":"HABITATION",
    "name:eng_x_preferred":[
        "Lalsinghpura"
    ],
    "wof:name":"Lalsinghpura",
    "wof:placetype":"locality",
    "wof:population":638
},
  "geometry": {"coordinates":[73.614518,27.964609],"type":"Point"}
}