{
  "type": "Feature",
  "properties": {
    "iso:country":"IN",
    "ks:ks_name":"Jerrai",
    "ks:ks_pop":189,
    "ks:ks_type":"HABITATION",
    "name:eng_x_preferred":[
        "Jerrai"
    ],
    "wof:name":"Jerrai",
    "wof:placetype":"locality",
    "wof:population":189
},
  "geometry": {"coordinates":[82.62038,17.982459],"type":"Point"}
}