{
  "type": "Feature",
  "properties": {
    "gn:admin1_code":"36.0",
    "gn:admin2_code":"184.0",
    "gn:asciiname":"Gauri",
    "gn:country_code":"IN",
    "gn:dem":92,
    "gn:feature_class":"P",
    "gn:feature_code":"PPL",
    "gn:name":"Gauri",
    "gn:population":0,
    "gn:timezone":"Asia/Kolkata",
    "iso:country":"IN",
    "ks:ks_name":"Gauri",
    "ks:ks_type":"VILLAGE",
    "ks:ks_uagg_main":0,
    "name:ceb_x_preferred":[
        "Gauri"
    ],
    "name:eng_x_preferred":[
        "Gauri"
    ],
    "name:fra_x_preferred":[
        "Gaur\u00ee"
    ],
    "name:hin_x_preferred":[
        "\u0917\u094c\u0930\u0940"
    ],
    "name:kor_x_preferred":[
        "\uac00\uc6b0\ub9ac"
    ],
    "name:ori_x_preferred":[
        "\u0b17\u0b4c\u0b30\u0b40"
    ],
    "wof:name":"Gauri",
    "wof:placetype":"neighbourhood"
},
  "geometry": {"coordinates":[82.911834,27.164057],"type":"Point"}
}