{
  "type": "Feature",
  "properties": {
    "iso:country":"IN",
    "ks:ks_name":"Nai Basti",
    "ks:ks_pop":265,
    "ks:ks_type":"HABITATION",
    "name:eng_x_preferred":[
        "Nai Basti"
    ],
    "wof:name":"Nai Basti",
    "wof:placetype":"locality",
    "wof:population":265
},
  "geometry": {"coordinates":[83.657651,26.85561],"type":"Point"}
}