{
  "type": "Feature",
  "properties": {
    "gn:admin1_code":"3.0",
    "gn:admin2_code":"323.0",
    "gn:asciiname":"Sandheli",
    "gn:country_code":"IN",
    "gn:dem":54,
    "gn:feature_class":"P",
    "gn:feature_code":"PPL",
    "gn:name":"Sandheli",
    "gn:population":0,
    "gn:timezone":"Asia/Kolkata",
    "iso:country":"IN",
    "ks:ks_name":"Sandheli",
    "ks:ks_pop":269,
    "ks:ks_type":"VILLAGE",
    "name:eng_x_preferred":[
        "Sandheli"
    ],
    "wof:name":"Sandheli",
    "wof:placetype":"locality",
    "wof:population":269
},
  "geometry": {"coordinates":[91.412327,26.426757],"type":"Point"}
}