{
  "type": "Feature",
  "properties": {
    "gn:admin1_code":"3.0",
    "gn:admin2_code":"323.0",
    "gn:asciiname":"Sandheli",
    "gn:country_code":"IN",
    "gn:dem":54,
    "gn:feature_class":"P",
    "gn:feature_code":"PPL",
    "gn:name":"Sandheli",
    "gn:population":0,
    "gn:timezone":"Asia/Kolkata",
    "iso:country":"IN",
    "wof:name":"Sandheli",
    "wof:placetype":"locality"
},
  "geometry": {"coordinates":[91.42655999999999,26.43886],"type":"Point"}
}