{
  "type": "Feature",
  "properties": {
    "iso:country":"IN",
    "ks:ks_name":"Punjihalli",
    "ks:ks_pop":33,
    "ks:ks_type":"VILLAGE",
    "name:eng_x_preferred":[
        "Punjihalli"
    ],
    "wof:name":"Punjihalli",
    "wof:placetype":"locality",
    "wof:population":33
},
  "geometry": {"coordinates":[76.868544,13.623297],"type":"Point"}
}