{
  "type": "Feature",
  "properties": {
    "gn:country":"IN",
    "gn:fcode":"PPL",
    "gn:population":17748,
    "iso:country":"IN",
    "name:ara_x_preferred":[
        "\u062f\u0648\u062f\u0627"
    ],
    "name:ben_bn_x_preferred":[
        "\u09a1\u09cb\u09a1\u09be"
    ],
    "name:ben_in_x_preferred":[
        "\u09a1\u09cb\u09a1\u09be"
    ],
    "name:bpy_x_preferred":[
        "\u09a6\u09cb\u09a6\u09be"
    ],
    "name:ceb_x_preferred":[
        "Doda"
    ],
    "name:deu_x_preferred":[
        "Doda"
    ],
    "name:eng_x_preferred":[
        "Doda"
    ],
    "name:fra_x_preferred":[
        "Doda"
    ],
    "name:guj_x_preferred":[
        "\u0aa1\u0acb\u0aa1\u0abe"
    ],
    "name:hin_x_preferred":[
        "\u0921\u094b\u0921\u093e"
    ],
    "name:ind_x_preferred":[
        "Doda"
    ],
    "name:ita_x_preferred":[
        "Doda"
    ],
    "name:kan_x_preferred":[
        "\u0ca6\u0ccb\u0ca1\u0cbe"
    ],
    "name:mal_x_preferred":[
        "\u0d21\u0d4b\u0d21"
    ],
    "name:mal_x_variant":[
        "\u0d26\u0d4b\u0d21"
    ],
    "name:mar_x_preferred":[
        "\u0921\u094b\u0921\u093e"
    ],
    "name:mar_x_variant":[
        "\u0926\u094b\u0921\u093e"
    ],
    "name:msa_x_preferred":[
        "Doda"
    ],
    "name:nan_x_preferred":[
        "Doda"
    ],
    "name:new_x_preferred":[
        "\u0921\u094b\u0921\u093e"
    ],
    "name:nld_x_preferred":[
        "Doda"
    ],
    "name:pan_x_preferred":[
        "\u0a21\u0a4b\u0a3e"
    ],
    "name:pnb_x_preferred":[
        "\u0688\u0648\u0688\u06c1"
    ],
    "name:rus_x_preferred":[
        "\u0414\u043e\u0434\u0430"
    ],
    "name:san_x_preferred":[
        "\u0921\u094b\u0921\u093e"
    ],
    "name:spa_x_preferred":[
        "Doda"
    ],
    "name:swe_x_preferred":[
        "Doda"
    ],
    "name:tam_x_preferred":[
        "\u0b9f\u0bcb\u0b9f\u0bbe"
    ],
    "name:tel_x_preferred":[
        "\u0c26\u0c4b\u0c21\u0c3e"
    ],
    "name:und_x_variant":[
        "Doda District (India)"
    ],
    "name:urd_x_preferred":[
        "\u0688\u0648\u0688\u06c1"
    ],
    "name:urd_x_variant":[
        "\u0688\u0648\u0688\u0627"
    ],
    "name:vie_x_preferred":[
        "Doda"
    ],
    "name:zho_x_preferred":[
        "\u591a\u8fbe"
    ],
    "qs:name":"Doda",
    "qs:name_adm0":"India",
    "qs:name_adm1":"Jammu and Kashmir",
    "qs:photos_9k":1,
    "qs:photos_9r":1,
    "qs:photos_all":5,
    "qs:photos_sr":0,
    "qs:placetype":"Town",
    "qs:pop_sr":"6",
    "wd:wordcount":237,
    "wof:name":"Doda",
    "wof:placetype":"locality",
    "wof:population":17748
},
  "geometry": {"coordinates":[75.54611,33.14875],"type":"Point"}
}