{
  "type": "Feature",
  "properties": {
    "gn:admin1_code":"16",
    "gn:admin2_code":"510.0",
    "gn:asciiname":"Sawitri",
    "gn:country_code":"IN",
    "gn:dem":218,
    "gn:feature_class":"P",
    "gn:feature_code":"PPL",
    "gn:name":"S\u0101witri",
    "gn:population":0,
    "gn:timezone":"Asia/Kolkata",
    "iso:country":"IN",
    "wof:name":"Sawitri",
    "wof:placetype":"locality"
},
  "geometry": {"coordinates":[78.73846999999998,20.26207],"type":"Point"}
}