{
  "type": "Feature",
  "properties": {
    "iso:country":"IN",
    "ks:ks_name":"Palanazhi",
    "ks:ks_pop":950,
    "ks:ks_type":"HABITATION",
    "name:eng_x_preferred":[
        "Palanazhi"
    ],
    "wof:name":"Palanazhi",
    "wof:placetype":"locality",
    "wof:population":950
},
  "geometry": {"coordinates":[76.32348399999999,10.991091],"type":"Point"}
}