{
  "type": "Feature",
  "properties": {
    "iso:country":"IN",
    "ks:ks_name":"Halumalledevara Kaval",
    "ks:ks_pop":365,
    "ks:ks_type":"VILLAGE",
    "name:eng_x_preferred":[
        "Halumalledevara Kaval"
    ],
    "wof:name":"Halumalledevara Kaval",
    "wof:placetype":"locality",
    "wof:population":365
},
  "geometry": {"coordinates":[76.408614,13.53436],"type":"Point"}
}