{
  "type": "Feature",
  "properties": {
    "iso:country":"IN",
    "ks:ks_alt_nam":"B\u0101ri",
    "ks:ks_name":"Bari",
    "ks:ks_pop":688,
    "ks:ks_type":"VILLAGE",
    "name:eng_x_preferred":[
        "Bari"
    ],
    "name:eng_x_variant":[
        "B\u0101ri"
    ],
    "wof:name":"Bari",
    "wof:placetype":"locality",
    "wof:population":688
},
  "geometry": {"coordinates":[85.389697,23.015126],"type":"Point"}
}