{
  "type": "Feature",
  "properties": {
    "iso:country":"IN",
    "ks:ks_name":"Phuljhari",
    "ks:ks_pop":406,
    "ks:ks_type":"VILLAGE",
    "name:eng_x_preferred":[
        "Phuljhari"
    ],
    "wof:name":"Phuljhari",
    "wof:placetype":"locality",
    "wof:population":406
},
  "geometry": {"coordinates":[86.330167,22.39373],"type":"Point"}
}