{
  "type": "Feature",
  "properties": {
    "iso:country":"IN",
    "ks:ks_name":"Hadiguda",
    "ks:ks_pop":68,
    "ks:ks_type":"VILLAGE",
    "name:eng_x_preferred":[
        "Hadiguda"
    ],
    "wof:name":"Hadiguda",
    "wof:placetype":"locality",
    "wof:population":68
},
  "geometry": {"coordinates":[82.033779,18.332543],"type":"Point"}
}