{
  "type": "Feature",
  "properties": {
    "iso:country":"IN",
    "ks:ks_name":"Kot Amori",
    "ks:ks_pop":760,
    "ks:ks_type":"VILLAGE",
    "name:eng_x_preferred":[
        "Kot Amori"
    ],
    "wof:name":"Kot Amori",
    "wof:placetype":"locality",
    "wof:population":760
},
  "geometry": {"coordinates":[80.048638,29.226088],"type":"Point"}
}