{
  "type": "Feature",
  "properties": {
    "gn:admin1_code":"39.0",
    "gn:admin2_code":"64.0",
    "gn:asciiname":"Baisi Simar",
    "gn:country_code":"IN",
    "gn:dem":1643,
    "gn:feature_class":"P",
    "gn:feature_code":"PPL",
    "gn:name":"Baisi Sim\u0101r",
    "gn:population":0,
    "gn:timezone":"Asia/Kolkata",
    "iso:country":"IN",
    "wof:name":"Baisi Simar",
    "wof:placetype":"locality"
},
  "geometry": {"coordinates":[79.20350000000001,29.73],"type":"Point"}
}