{
  "type": "Feature",
  "properties": {
    "gn:admin1_code":"24.0",
    "gn:admin2_code":"103",
    "gn:asciiname":"Bibasar",
    "gn:country_code":"IN",
    "gn:dem":356,
    "gn:feature_class":"P",
    "gn:feature_code":"PPL",
    "gn:name":"B\u012bb\u0101sar",
    "gn:population":0,
    "gn:timezone":"Asia/Kolkata",
    "iso:country":"IN",
    "name:und_x_variant":[
        "B\u012bb\u0101sar",
        "Bib\u0101sar"
    ],
    "wof:name":"Bibasar",
    "wof:placetype":"neighbourhood"
},
  "geometry": {"coordinates":[75.36071,28.02576],"type":"Point"}
}