{
  "type": "Feature",
  "properties": {
    "gn:admin1_code":"36.0",
    "gn:admin2_code":"135.0",
    "gn:asciiname":"Khanpur Sarai",
    "gn:country_code":"IN",
    "gn:dem":200,
    "gn:feature_class":"P",
    "gn:feature_code":"PPL",
    "gn:name":"Kh\u0101npur Sar\u0101i",
    "gn:population":0,
    "gn:timezone":"Asia/Kolkata",
    "iso:country":"IN",
    "name:und_x_variant":[
        "Kh\u0101npur Sar\u0101i",
        "\u0100lampur"
    ],
    "wof:name":"Khanpur Sarai",
    "wof:placetype":"locality"
},
  "geometry": {"coordinates":[78.6742,28.57801],"type":"Point"}
}