{
  "type": "Feature",
  "properties": {
    "iso:country":"IN",
    "ks:ks_name":"Shrabandi",
    "ks:ks_pop":1091,
    "ks:ks_type":"VILLAGE",
    "name:eng_x_preferred":[
        "Shrabandi"
    ],
    "wof:name":"Shrabandi",
    "wof:placetype":"locality",
    "wof:population":1091
},
  "geometry": {"coordinates":[86.024908,23.157156],"type":"Point"}
}