{
  "type": "Feature",
  "properties": {
    "iso:country":"IN",
    "ks:ks_name":"Nadukattabettu",
    "ks:ks_pop":40,
    "ks:ks_type":"HABITATION",
    "name:eng_x_preferred":[
        "Nadukattabettu"
    ],
    "wof:name":"Nadukattabettu",
    "wof:placetype":"locality",
    "wof:population":40
},
  "geometry": {"coordinates":[76.95769,11.457977],"type":"Point"}
}