{
  "type": "Feature",
  "properties": {
    "gn:admin1_code":"25.0",
    "gn:admin2_code":"633.0",
    "gn:asciiname":"Ponneri",
    "gn:country_code":"IN",
    "gn:dem":346,
    "gn:feature_class":"P",
    "gn:feature_code":"PPL",
    "gn:name":"Ponneri",
    "gn:population":0,
    "gn:timezone":"Asia/Kolkata",
    "iso:country":"IN",
    "name:bpy_x_preferred":[
        "\u09aa\u09cb\u09a8\u09cd\u09a8\u09c7\u09b0\u09bf"
    ],
    "name:ceb_x_preferred":[
        "Ponneri"
    ],
    "name:deu_x_preferred":[
        "Ponneri"
    ],
    "name:hif_x_preferred":[
        "Ponneri"
    ],
    "name:ita_x_preferred":[
        "Ponneri"
    ],
    "name:kan_x_preferred":[
        "\u0caa\u0cca\u0ca8\u0ccd\u0ca8\u0cc7\u0cb0\u0cbf"
    ],
    "name:mlg_x_preferred":[
        "Ponneri"
    ],
    "name:msa_x_preferred":[
        "Ponneri"
    ],
    "name:nld_x_preferred":[
        "Ponneri"
    ],
    "name:ori_x_preferred":[
        "\u0b2a\u0b4b\u0b28\u0b4d\u0b28\u0b47\u0b30\u0b3f"
    ],
    "name:por_x_preferred":[
        "Ponneri"
    ],
    "name:swe_x_preferred":[
        "Ponneri"
    ],
    "name:tam_x_preferred":[
        "\u0baa\u0bca\u0ba9\u0bcd\u0ba9\u0bc7\u0bb0\u0bbf"
    ],
    "name:vie_x_preferred":[
        "Ponneri"
    ],
    "name:zho_x_preferred":[
        "\u6ce2\u5185\u91cc"
    ],
    "wof:name":"Ponneri",
    "wof:placetype":"locality"
},
  "geometry": {"coordinates":[77.2658,10.64176],"type":"Point"}
}