{
  "type": "Feature",
  "properties": {
    "iso:country":"IN",
    "ks:ks_name":"Kalamangi",
    "ks:ks_pop":36,
    "ks:ks_type":"HABITATION",
    "name:eng_x_preferred":[
        "Kalamangi"
    ],
    "wof:name":"Kalamangi",
    "wof:placetype":"locality",
    "wof:population":36
},
  "geometry": {"coordinates":[74.83413,14.173623],"type":"Point"}
}