{
  "type": "Feature",
  "properties": {
    "iso:country":"IN",
    "ks:ks_alt_nam":"TELIWASTI",
    "ks:ks_name":"Teliwasti",
    "ks:ks_pop":40,
    "ks:ks_type":"HABITATION",
    "name:eng_x_preferred":[
        "Teliwasti"
    ],
    "wof:name":"Teliwasti",
    "wof:placetype":"locality",
    "wof:population":40
},
  "geometry": {"coordinates":[74.260857,17.150596],"type":"Point"}
}