{
  "type": "Feature",
  "properties": {
    "iso:country":"IN",
    "ks:ks_name":"Turkapara",
    "ks:ks_pop":174,
    "ks:ks_type":"HABITATION",
    "name:eng_x_preferred":[
        "Turkapara"
    ],
    "wof:name":"Turkapara",
    "wof:placetype":"locality",
    "wof:population":174
},
  "geometry": {"coordinates":[83.764635,22.30867],"type":"Point"}
}