{
  "type": "Feature",
  "properties": {
    "gn:admin1_code":"16",
    "gn:admin2_code":"504.0",
    "gn:asciiname":"Vallabhnagar",
    "gn:country_code":"IN",
    "gn:dem":272,
    "gn:feature_class":"P",
    "gn:feature_code":"PPL",
    "gn:name":"Vallabhnagar",
    "gn:population":0,
    "gn:timezone":"Asia/Kolkata",
    "iso:country":"IN",
    "name:ceb_x_preferred":[
        "Vallabhnagar"
    ],
    "name:swe_x_preferred":[
        "Vallabhnagar"
    ],
    "wof:name":"Vallabhnagar",
    "wof:placetype":"neighbourhood"
},
  "geometry": {"coordinates":[78.32192000000001,20.74197],"type":"Point"}
}