{
  "type": "Feature",
  "properties": {
    "gn:admin1_code":"35",
    "gn:admin2_code":"426.0",
    "gn:asciiname":"Jhiuna",
    "gn:country_code":"IN",
    "gn:dem":391,
    "gn:feature_class":"P",
    "gn:feature_code":"PPL",
    "gn:name":"Jhiuna",
    "gn:population":0,
    "gn:timezone":"Asia/Kolkata",
    "iso:country":"IN",
    "wof:name":"Jhiuna",
    "wof:placetype":"locality"
},
  "geometry": {"coordinates":[80.23881999999998,24.01049],"type":"Point"}
}