{
  "type": "Feature",
  "properties": {
    "iso:country":"IN",
    "ks:ks_alt_nam":"J.P NAGAR",
    "ks:ks_name":"J.p Nagar",
    "ks:ks_pop":484,
    "ks:ks_type":"HABITATION",
    "name:eng_x_preferred":[
        "J.p Nagar"
    ],
    "wof:name":"J.p Nagar",
    "wof:placetype":"locality",
    "wof:population":484
},
  "geometry": {"coordinates":[85.614796,24.796538],"type":"Point"}
}