{
  "type": "Feature",
  "properties": {
    "iso:country":"IN",
    "ks:ks_alt_nam":"JJnagar",
    "ks:ks_name":"Jjnagar",
    "ks:ks_pop":162,
    "ks:ks_type":"HABITATION",
    "name:eng_x_preferred":[
        "Jjnagar"
    ],
    "wof:name":"Jjnagar",
    "wof:placetype":"locality",
    "wof:population":162
},
  "geometry": {"coordinates":[77.501621,9.716291],"type":"Point"}
}