{
  "type": "Feature",
  "properties": {
    "gn:admin1_code":"37.0",
    "gn:admin2_code":"402",
    "gn:asciiname":"Bagicha",
    "gn:country_code":"IN",
    "gn:dem":680,
    "gn:feature_class":"P",
    "gn:feature_code":"PPL",
    "gn:name":"Bagicha",
    "gn:population":0,
    "gn:timezone":"Asia/Kolkata",
    "iso:country":"IN",
    "wof:name":"Bagicha",
    "wof:placetype":"locality"
},
  "geometry": {"coordinates":[83.65705,22.9773],"type":"Point"}
}