{
  "type": "Feature",
  "properties": {
    "iso:country":"IN",
    "ks:ks_name":"Sangama",
    "ks:ks_pop":25,
    "ks:ks_type":"HABITATION",
    "name:eng_x_preferred":[
        "Sangama"
    ],
    "wof:name":"Sangama",
    "wof:placetype":"locality",
    "wof:population":25
},
  "geometry": {"coordinates":[76.47672300000001,12.09226],"type":"Point"}
}