{
  "type": "Feature",
  "properties": {
    "iso:country":"IN",
    "ks:ks_name":"Aurang Nagar Khera",
    "ks:ks_pop":1185,
    "ks:ks_type":"HABITATION",
    "name:eng_x_preferred":[
        "Aurang Nagar Khera"
    ],
    "wof:name":"Aurang Nagar Khera",
    "wof:placetype":"locality",
    "wof:population":1185
},
  "geometry": {"coordinates":[79.34706,28.785742],"type":"Point"}
}