{
  "type": "Feature",
  "properties": {
    "iso:country":"IN",
    "ks:ks_name":"Kadamalli",
    "ks:ks_pop":87,
    "ks:ks_type":"VILLAGE",
    "name:eng_x_preferred":[
        "Kadamalli"
    ],
    "wof:name":"Kadamalli",
    "wof:placetype":"locality",
    "wof:population":87
},
  "geometry": {"coordinates":[84.40287499999999,19.306784],"type":"Point"}
}