{
  "type": "Feature",
  "properties": {
    "iso:country":"IN",
    "ks:ks_alt_nam":"MALAKAR PARA",
    "ks:ks_name":"Malakar Para",
    "ks:ks_pop":510,
    "ks:ks_type":"HABITATION",
    "name:eng_x_preferred":[
        "Malakar Para"
    ],
    "wof:name":"Malakar Para",
    "wof:placetype":"locality",
    "wof:population":510
},
  "geometry": {"coordinates":[91.393106,24.004953],"type":"Point"}
}