{
  "type": "Feature",
  "properties": {
    "iso:country":"IN",
    "ks:ks_name":"Habibulla Chak",
    "ks:ks_pop":243,
    "ks:ks_type":"VILLAGE",
    "name:eng_x_preferred":[
        "Habibulla Chak"
    ],
    "wof:name":"Habibulla Chak",
    "wof:placetype":"locality",
    "wof:population":243
},
  "geometry": {"coordinates":[85.124408,25.945787],"type":"Point"}
}