{
  "type": "Feature",
  "properties": {
    "iso:country":"IN",
    "ks:ks_name":"Sumho",
    "ks:ks_pop":457,
    "ks:ks_type":"HABITATION",
    "name:eng_x_preferred":[
        "Sumho"
    ],
    "wof:name":"Sumho",
    "wof:placetype":"locality",
    "wof:population":457
},
  "geometry": {"coordinates":[82.808369,27.15419],"type":"Point"}
}