{
  "type": "Feature",
  "properties": {
    "gn:admin1_code":"35",
    "gn:admin2_code":"463.0",
    "gn:asciiname":"Biradar",
    "gn:country_code":"IN",
    "gn:dem":368,
    "gn:feature_class":"P",
    "gn:feature_code":"PPL",
    "gn:name":"Bir\u0101d\u0101r",
    "gn:population":0,
    "gn:timezone":"Asia/Kolkata",
    "iso:country":"IN",
    "wof:name":"Biradar",
    "wof:placetype":"locality"
},
  "geometry": {"coordinates":[82.39381,24.23503],"type":"Point"}
}