{
  "type": "Feature",
  "properties": {
    "iso:country":"IN",
    "ks:ks_alt_nam":"GARERAIN KA PURWA",
    "ks:ks_name":"Garerain Ka Purwa",
    "ks:ks_pop":241,
    "ks:ks_type":"HABITATION",
    "name:eng_x_preferred":[
        "Garerain Ka Purwa"
    ],
    "wof:name":"Garerain Ka Purwa",
    "wof:placetype":"locality",
    "wof:population":241
},
  "geometry": {"coordinates":[81.28214,25.33426],"type":"Point"}
}