{
  "type": "Feature",
  "properties": {
    "iso:country":"IN",
    "ks:ks_name":"Gwrmohanpur",
    "ks:ks_pop":560,
    "ks:ks_type":"HABITATION",
    "name:eng_x_preferred":[
        "Gwrmohanpur"
    ],
    "wof:name":"Gwrmohanpur",
    "wof:placetype":"locality",
    "wof:population":560
},
  "geometry": {"coordinates":[87.323047,23.38474],"type":"Point"}
}