{
  "type": "Feature",
  "properties": {
    "gn:admin1_code":"36.0",
    "gn:admin2_code":"177.0",
    "gn:asciiname":"Haibatpur",
    "gn:country_code":"IN",
    "gn:dem":102,
    "gn:feature_class":"P",
    "gn:feature_code":"PPL",
    "gn:name":"Haibatpur",
    "gn:population":0,
    "gn:timezone":"Asia/Kolkata",
    "iso:country":"IN",
    "ks:ks_name":"Haibatpur",
    "ks:ks_pop":1234,
    "ks:ks_type":"HABITATION",
    "ks:ks_uagg_main":0,
    "name:eng_x_preferred":[
        "Haibatpur"
    ],
    "wof:name":"Haibatpur",
    "wof:placetype":"locality",
    "wof:population":1234
},
  "geometry": {"coordinates":[82.196162,26.775118],"type":"Point"}
}