{
  "type": "Feature",
  "properties": {
    "iso:country":"IN",
    "ks:ks_name":"Dhoha",
    "ks:ks_pop":172,
    "ks:ks_type":"VILLAGE",
    "name:eng_x_preferred":[
        "Dhoha"
    ],
    "wof:name":"Dhoha",
    "wof:placetype":"locality",
    "wof:population":172
},
  "geometry": {"coordinates":[78.60789800000001,23.607591],"type":"Point"}
}