{
  "type": "Feature",
  "properties": {
    "iso:country":"IN",
    "ks:ks_name":"Ikodiya",
    "ks:ks_pop":366,
    "ks:ks_type":"VILLAGE",
    "name:eng_x_preferred":[
        "Ikodiya"
    ],
    "wof:name":"Ikodiya",
    "wof:placetype":"locality",
    "wof:population":366
},
  "geometry": {"coordinates":[77.316293,24.924731],"type":"Point"}
}