{
  "type": "Feature",
  "properties": {
    "iso:country":"IN",
    "ks:ks_name":"Gamelput",
    "ks:ks_pop":247,
    "ks:ks_type":"HABITATION",
    "name:eng_x_preferred":[
        "Gamelput"
    ],
    "wof:name":"Gamelput",
    "wof:placetype":"locality",
    "wof:population":247
},
  "geometry": {"coordinates":[82.67888600000001,18.364017],"type":"Point"}
}