{
  "type": "Feature",
  "properties": {
    "gn:admin1_code":"36.0",
    "gn:admin2_code":"189.0",
    "gn:asciiname":"Balua Rampur Sirpal",
    "gn:country_code":"IN",
    "gn:dem":88,
    "gn:feature_class":"P",
    "gn:feature_code":"PPL",
    "gn:name":"Balua R\u0101mpur Sirp\u0101l",
    "gn:population":0,
    "gn:timezone":"Asia/Kolkata",
    "iso:country":"IN",
    "wof:name":"Balua Rampur Sirpal",
    "wof:placetype":"locality"
},
  "geometry": {"coordinates":[83.70779,26.69704],"type":"Point"}
}