{
  "type": "Feature",
  "properties": {
    "iso:country":"IN",
    "ks:ks_name":"Nero",
    "ks:ks_pop":207,
    "ks:ks_type":"VILLAGE",
    "name:eng_x_preferred":[
        "Nero"
    ],
    "wof:name":"Nero",
    "wof:placetype":"locality",
    "wof:population":207
},
  "geometry": {"coordinates":[86.071871,24.423989],"type":"Point"}
}