{
  "type": "Feature",
  "properties": {
    "gn:admin1_code":"13.0",
    "gn:admin2_code":"601.0",
    "gn:asciiname":"Oruvadalkotta",
    "gn:country_code":"IN",
    "gn:dem":23,
    "gn:feature_class":"P",
    "gn:feature_code":"PPL",
    "gn:name":"Oruvad\u0101lkotta",
    "gn:population":0,
    "gn:timezone":"Asia/Kolkata",
    "iso:country":"IN",
    "wof:name":"Oruvadalkotta",
    "wof:placetype":"locality"
},
  "geometry": {"coordinates":[76.90094999999999,8.51748],"type":"Point"}
}