{
  "type": "Feature",
  "properties": {
    "gn:admin1_code":"21",
    "gn:admin2_code":"390.0",
    "gn:asciiname":"Bikapanga",
    "gn:country_code":"IN",
    "gn:dem":726,
    "gn:feature_class":"P",
    "gn:feature_code":"PPL",
    "gn:name":"Bik\u0101panga",
    "gn:population":0,
    "gn:timezone":"Asia/Kolkata",
    "iso:country":"IN",
    "ks:ks_alt_nam":"Bik\u0101panga",
    "ks:ks_name":"Bikapanga",
    "ks:ks_type":"VILLAGE",
    "name:eng_x_preferred":[
        "Bikapanga"
    ],
    "name:eng_x_variant":[
        "Bik\u0101panga"
    ],
    "wof:name":"Bikapanga",
    "wof:placetype":"locality"
},
  "geometry": {"coordinates":[83.569028,19.900359],"type":"Point"}
}