{
  "type": "Feature",
  "properties": {
    "iso:country":"IN",
    "name:eng_x_preferred":[
        "Kalamboli"
    ],
    "name:hin_x_preferred":[
        "\u0915\u0932\u0902\u092c\u094b\u0932\u0940"
    ],
    "name:mar_x_preferred":[
        "\u0915\u0933\u0902\u092c\u094b\u0932\u0940"
    ],
    "name:unk_x_variant":[
        "Kalamboli"
    ],
    "qs:gn_fcode":"PPL",
    "qs:gn_local":0,
    "qs:gn_namadm1":"16",
    "qs:gn_name":"Kalamboli",
    "qs:local_max":353,
    "qs:local_sum":1613,
    "qs:localhoods":12,
    "qs:name":"Kalamboli",
    "qs:name_adm0":"India",
    "qs:name_adm1":"Maharashtra",
    "qs:name_adm2":"Raigarh",
    "qs:name_local":"Navi Mumbai",
    "qs:photo_max":148,
    "qs:photo_sum":198,
    "qs:placetype":"Suburb",
    "qs:quad_count":19,
    "qs:woe_adm0":23424848,
    "qs:woe_adm1":2345750,
    "qs:woe_adm2":12586545,
    "qs:woe_lau":0,
    "qs:woe_local":28999056,
    "qs:woe_ver":"7.10.0",
    "wof:lang":[
        "eng"
    ],
    "wof:name":"Kalamboli",
    "wof:placetype":"neighbourhood"
},
  "geometry": {"coordinates":[73.098276,19.033855],"type":"Point"}
}