{
  "type": "Feature",
  "properties": {
    "iso:country":"IN",
    "name:ara_x_preferred":[
        "\u0643\u0627\u0644\u0645\u0628\u0648\u0644\u064a"
    ],
    "name:ben_bn_x_preferred":[
        "\u0995\u09be\u09b2\u09be\u09ae\u09ac\u09cb\u09b2\u09bf"
    ],
    "name:ben_in_x_preferred":[
        "\u0995\u09be\u09b2\u09be\u09ae\u09ac\u09cb\u09b2\u09bf"
    ],
    "name:eng_x_preferred":[
        "Kalamboli"
    ],
    "name:guj_x_preferred":[
        "\u0a95\u0ab2\u0aae\u0aac\u0acb\u0ab2\u0ac0"
    ],
    "name:hin_x_preferred":[
        "\u0915\u0932\u0902\u092c\u094b\u0932\u0940"
    ],
    "name:kan_x_preferred":[
        "\u0c95\u0cb2\u0c82\u0cac\u0ccb\u0cb2\u0cbf"
    ],
    "name:mal_x_preferred":[
        "\u0d15\u0d32\u0d3e\u0d02\u0d2c\u0d4b\u0d33\u0d3f"
    ],
    "name:mar_x_preferred":[
        "\u0915\u0933\u0902\u092c\u094b\u0932\u0940"
    ],
    "name:pan_x_preferred":[
        "\u0a15\u0a32\u0a2e\u0a2c\u0a4b\u0a32\u0a40"
    ],
    "name:tam_x_preferred":[
        "\u0b95\u0bb2\u0bbe\u0bae\u0bcd\u0baa\u0bca\u0bb2\u0bbf"
    ],
    "name:tel_x_preferred":[
        "\u0c15\u0c32\u0c02\u0c2c\u0c4b\u0c32\u0c3f"
    ],
    "name:urd_x_preferred":[
        "\u06a9\u0627\u0644\u0645\u0628\u0648\u0644\u06cc"
    ],
    "name:zho_x_preferred":[
        "\u5361\u6717\u535a\u91cc"
    ],
    "qs:gn_fcode":"PPL",
    "qs:gn_local":0,
    "qs:gn_namadm1":"16",
    "qs:gn_name":"Kalamboli",
    "qs:local_max":353,
    "qs:local_sum":1613,
    "qs:localhoods":12,
    "qs:name":"Kalamboli",
    "qs:name_adm0":"India",
    "qs:name_adm1":"Maharashtra",
    "qs:name_adm2":"Raigarh",
    "qs:name_local":"Navi Mumbai",
    "qs:photo_max":148,
    "qs:photo_sum":198,
    "qs:placetype":"Suburb",
    "qs:quad_count":19,
    "qs:woe_adm0":23424848,
    "qs:woe_adm1":2345750,
    "qs:woe_adm2":12586545,
    "qs:woe_lau":0,
    "qs:woe_local":28999056,
    "qs:woe_ver":"7.10.0",
    "wof:lang":[
        "eng"
    ],
    "wof:name":"Kalamboli",
    "wof:placetype":"neighbourhood"
},
  "geometry": {"coordinates":[73.098276,19.033855],"type":"Point"}
}