{
  "type": "Feature",
  "properties": {
    "gn:admin1_code":"36.0",
    "gn:admin2_code":"136.0",
    "gn:asciiname":"Kajarhai",
    "gn:country_code":"IN",
    "gn:dem":189,
    "gn:feature_class":"P",
    "gn:feature_code":"PPL",
    "gn:name":"Kajarh\u0101\u012b",
    "gn:population":0,
    "gn:timezone":"Asia/Kolkata",
    "iso:country":"IN",
    "ks:ks_alt_nam":"Kajarh\u0101\u012b",
    "ks:ks_name":"Kajarhai",
    "ks:ks_type":"VILLAGE",
    "name:eng_x_preferred":[
        "Kajarhai"
    ],
    "name:eng_x_variant":[
        "Kajarh\u0101\u012b"
    ],
    "wof:name":"Kajarhai",
    "wof:placetype":"locality"
},
  "geometry": {"coordinates":[79.143832,28.827667],"type":"Point"}
}