{
  "type": "Feature",
  "properties": {
    "iso:country":"IN",
    "ks:ks_name":"Nuagaon",
    "ks:ks_pop":0,
    "ks:ks_type":"VILLAGE",
    "name:eng_x_preferred":[
        "Nuagaon"
    ],
    "wof:name":"Nuagaon",
    "wof:placetype":"locality",
    "wof:population":0
},
  "geometry": {"coordinates":[85.898687,21.25996],"type":"Point"}
}