{
  "type": "Feature",
  "properties": {
    "gn:admin1_code":"19.0",
    "gn:admin2_code":"570.0",
    "gn:asciiname":"Balugaru",
    "gn:country_code":"IN",
    "gn:dem":740,
    "gn:feature_class":"P",
    "gn:feature_code":"PPL",
    "gn:name":"B\u0101lug\u0101ru",
    "gn:population":0,
    "gn:timezone":"Asia/Kolkata",
    "iso:country":"IN",
    "ks:ks_name":"Balagaru",
    "ks:ks_pop":117,
    "ks:ks_type":"HABITATION",
    "name:eng_x_preferred":[
        "Balagaru"
    ],
    "name:eng_x_variant":[
        "Balugaru"
    ],
    "wof:name":"Balagaru",
    "wof:placetype":"locality",
    "wof:population":117
},
  "geometry": {"coordinates":[75.395709,13.535184],"type":"Point"}
}