{
  "type": "Feature",
  "properties": {
    "gn:admin1_code":"19.0",
    "gn:admin2_code":"570.0",
    "gn:asciiname":"Balugaru",
    "gn:country_code":"IN",
    "gn:dem":740,
    "gn:feature_class":"P",
    "gn:feature_code":"PPL",
    "gn:name":"B\u0101lug\u0101ru",
    "gn:population":0,
    "gn:timezone":"Asia/Kolkata",
    "iso:country":"IN",
    "wof:name":"Balugaru",
    "wof:placetype":"locality"
},
  "geometry": {"coordinates":[75.39775999999998,13.53055],"type":"Point"}
}