{
  "type": "Feature",
  "properties": {
    "gn:admin1_code":"36.0",
    "gn:admin2_code":"141.0",
    "gn:asciiname":"Bisrakh",
    "gn:country_code":"IN",
    "gn:dem":209,
    "gn:feature_class":"P",
    "gn:feature_code":"PPL",
    "gn:name":"Bisrakh",
    "gn:population":0,
    "gn:timezone":"Asia/Kolkata",
    "iso:country":"IN",
    "name:eng_x_preferred":[
        "Bisrakh"
    ],
    "name:hin_x_preferred":[
        "\u092c\u093f\u0938\u0930\u0916"
    ],
    "name:mal_x_preferred":[
        "\u0d2c\u0d3f\u0d38\u0d4d\u0d30\u0d3e\u0d16\u0d4d"
    ],
    "name:sin_x_preferred":[
        "\u0db6\u0dd2\u0dc3\u0dca\u0dbb\u0d9b\u0dca"
    ],
    "wof:name":"Bisrakh",
    "wof:placetype":"neighbourhood"
},
  "geometry": {"coordinates":[77.43724,28.56902],"type":"Point"}
}