{
  "type": "Feature",
  "properties": {
    "iso:country":"IN",
    "ks:ks_alt_nam":"cHANDRAIAHNAPALYA",
    "ks:ks_name":"Chandraiahnapalya",
    "ks:ks_pop":50,
    "ks:ks_type":"HABITATION",
    "name:eng_x_preferred":[
        "Chandraiahnapalya"
    ],
    "wof:name":"Chandraiahnapalya",
    "wof:placetype":"locality",
    "wof:population":50
},
  "geometry": {"coordinates":[77.125601,12.919241],"type":"Point"}
}