{
  "type": "Feature",
  "properties": {
    "gn:admin1_code":"2.0",
    "gn:admin2_code":"552.0",
    "gn:asciiname":"Govindinne",
    "gn:country_code":"IN",
    "gn:dem":191,
    "gn:feature_class":"P",
    "gn:feature_code":"PPL",
    "gn:name":"Govindinne",
    "gn:population":0,
    "gn:timezone":"Asia/Kolkata",
    "iso:country":"IN",
    "name:und_x_variant":[
        "Uppun\u012blla"
    ],
    "wof:name":"Govindinne",
    "wof:placetype":"locality"
},
  "geometry": {"coordinates":[78.40392,15.26065],"type":"Point"}
}