{
  "type": "Feature",
  "properties": {
    "iso:country":"IN",
    "ks:ks_name":"Jaltha Kot",
    "ks:ks_pop":224,
    "ks:ks_type":"HABITATION",
    "name:eng_x_preferred":[
        "Jaltha Kot"
    ],
    "wof:name":"Jaltha Kot",
    "wof:placetype":"locality",
    "wof:population":224
},
  "geometry": {"coordinates":[79.84902599999999,29.833734],"type":"Point"}
}