{
  "type": "Feature",
  "properties": {
    "iso:country":"IN",
    "ks:ks_name":"Ram Pura",
    "ks:ks_pop":1718,
    "ks:ks_type":"VILLAGE",
    "name:eng_x_preferred":[
        "Ram Pura"
    ],
    "wof:name":"Ram Pura",
    "wof:placetype":"locality",
    "wof:population":1718
},
  "geometry": {"coordinates":[79.336185,25.527668],"type":"Point"}
}