{
  "type": "Feature",
  "properties": {
    "iso:country":"IN",
    "ks:ks_name":"Chettakalu",
    "ks:ks_pop":354,
    "ks:ks_type":"HABITATION",
    "name:eng_x_preferred":[
        "Chettakalu"
    ],
    "wof:name":"Chettakalu",
    "wof:placetype":"locality",
    "wof:population":354
},
  "geometry": {"coordinates":[75.530475,12.489692],"type":"Point"}
}