{
  "type": "Feature",
  "properties": {
    "iso:country":"IN",
    "ks:ks_name":"Katara Falia",
    "ks:ks_pop":563,
    "ks:ks_type":"HABITATION",
    "name:eng_x_preferred":[
        "Katara Falia"
    ],
    "wof:name":"Katara Falia",
    "wof:placetype":"locality",
    "wof:population":563
},
  "geometry": {"coordinates":[74.19627800000001,23.168611],"type":"Point"}
}