{
  "type": "Feature",
  "properties": {
    "iso:country":"IN",
    "ks:ks_name":"Palsamal",
    "ks:ks_pop":223,
    "ks:ks_type":"VILLAGE",
    "name:eng_x_preferred":[
        "Palsamal"
    ],
    "wof:name":"Palsamal",
    "wof:placetype":"locality",
    "wof:population":223
},
  "geometry": {"coordinates":[84.101901,21.129451],"type":"Point"}
}