{
  "type": "Feature",
  "properties": {
    "gn:admin1_code":"36.0",
    "gn:admin2_code":"149",
    "gn:asciiname":"Pasei",
    "gn:country_code":"IN",
    "gn:dem":172,
    "gn:feature_class":"P",
    "gn:feature_code":"PPL",
    "gn:name":"Pasei",
    "gn:population":0,
    "gn:timezone":"Asia/Kolkata",
    "iso:country":"IN",
    "wof:name":"Pasei",
    "wof:placetype":"locality"
},
  "geometry": {"coordinates":[79.10869,27.97374000000001],"type":"Point"}
}