{
  "type": "Feature",
  "properties": {
    "iso:country":"IN",
    "ks:ks_name":"Vimawal",
    "ks:ks_pop":512,
    "ks:ks_type":"HABITATION",
    "ks:ks_uagg_main":0,
    "name:eng_x_preferred":[
        "Vimawal"
    ],
    "wof:name":"Vimawal",
    "wof:placetype":"neighbourhood",
    "wof:population":512
},
  "geometry": {"coordinates":[82.895492,26.452599],"type":"Point"}
}