{
  "type": "Feature",
  "properties": {
    "iso:country":"IN",
    "ks:ks_name":"Durgapur",
    "ks:ks_pop":135,
    "ks:ks_type":"HABITATION",
    "name:eng_x_preferred":[
        "Durgapur"
    ],
    "wof:name":"Durgapur",
    "wof:placetype":"locality",
    "wof:population":135
},
  "geometry": {"coordinates":[93.121798,26.107813],"type":"Point"}
}