{
  "type": "Feature",
  "properties": {
    "gn:admin1_code":"35",
    "gn:admin2_code":"436.0",
    "gn:asciiname":"Bhimlod",
    "gn:country_code":"IN",
    "gn:dem":489,
    "gn:feature_class":"P",
    "gn:feature_code":"PPL",
    "gn:name":"Bh\u012bmlod",
    "gn:population":0,
    "gn:timezone":"Asia/Kolkata",
    "iso:country":"IN",
    "name:und_x_variant":[
        "Bh\u012bmlod",
        "Panch\u0101rundi"
    ],
    "wof:name":"Bhimlod",
    "wof:placetype":"locality"
},
  "geometry": {"coordinates":[76.03989,23.7862],"type":"Point"}
}