{
  "type": "Feature",
  "properties": {
    "iso:country":"IN",
    "ks:ks_name":"Siyalkuri",
    "ks:ks_pop":490,
    "ks:ks_type":"HABITATION",
    "name:eng_x_preferred":[
        "Siyalkuri"
    ],
    "wof:name":"Siyalkuri",
    "wof:placetype":"locality",
    "wof:population":490
},
  "geometry": {"coordinates":[88.169642,25.341846],"type":"Point"}
}