{
  "type": "Feature",
  "properties": {
    "gn:admin1_code":"10.0",
    "gn:admin2_code":"071",
    "gn:asciiname":"Sandhali",
    "gn:country_code":"IN",
    "gn:dem":262,
    "gn:feature_class":"P",
    "gn:feature_code":"PPL",
    "gn:name":"Sandh\u0101li",
    "gn:population":0,
    "gn:timezone":"Asia/Kolkata",
    "iso:country":"IN",
    "name:und_x_variant":[
        "S\u0101ndh\u0101li",
        "S\u0101ndh\u0101ll",
        "Sandh\u0101li"
    ],
    "wof:name":"Sandhali",
    "wof:placetype":"locality"
},
  "geometry": {"coordinates":[77.21592,29.98239],"type":"Point"}
}