{
  "type": "Feature",
  "properties": {
    "gn:admin1_code":"37.0",
    "gn:admin2_code":"417.0",
    "gn:asciiname":"Kottapalli",
    "gn:country_code":"IN",
    "gn:dem":142,
    "gn:feature_class":"P",
    "gn:feature_code":"PPL",
    "gn:name":"Kottapalli",
    "gn:population":0,
    "gn:timezone":"Asia/Kolkata",
    "iso:country":"IN",
    "ks:ks_name":"Kottapalli",
    "ks:ks_pop":379,
    "ks:ks_type":"VILLAGE",
    "name:eng_x_preferred":[
        "Kottapalli"
    ],
    "wof:name":"Kottapalli",
    "wof:placetype":"locality",
    "wof:population":379
},
  "geometry": {"coordinates":[80.584805,18.704485],"type":"Point"}
}