{
  "type": "Feature",
  "properties": {
    "iso:country":"IN",
    "ks:ks_name":"Adaiyapulam",
    "ks:ks_pop":2174,
    "ks:ks_type":"VILLAGE",
    "name:eng_x_preferred":[
        "Adaiyapulam"
    ],
    "wof:name":"Adaiyapulam",
    "wof:placetype":"locality",
    "wof:population":2174
},
  "geometry": {"coordinates":[79.248076,12.710657],"type":"Point"}
}