{
  "type": "Feature",
  "properties": {
    "gn:admin1_code":"21.0",
    "gn:admin2_code":"398.0",
    "gn:asciiname":"Ballapodoro",
    "gn:country_code":"IN",
    "gn:dem":589,
    "gn:feature_class":"P",
    "gn:feature_code":"PPL",
    "gn:name":"Ballapodoro",
    "gn:population":0,
    "gn:timezone":"Asia/Kolkata",
    "iso:country":"IN",
    "wof:name":"Ballapodoro",
    "wof:placetype":"locality"
},
  "geometry": {"coordinates":[82.39660000000001,18.63316],"type":"Point"}
}