{
  "type": "Feature",
  "properties": {
    "iso:country":"IN",
    "ks:ks_name":"Newati",
    "ks:ks_pop":350,
    "ks:ks_type":"HABITATION",
    "name:eng_x_preferred":[
        "Newati"
    ],
    "wof:name":"Newati",
    "wof:placetype":"locality",
    "wof:population":350
},
  "geometry": {"coordinates":[85.795086,24.763025],"type":"Point"}
}