{
  "type": "Feature",
  "properties": {
    "iso:country":"IN",
    "name:ara_x_preferred":[
        "\u0645\u0633\u062a\u0639\u0645\u0631\u0629 \u0645\u0648\u0646\u0634\u064a\u0631\u0627\u0645"
    ],
    "name:ben_bn_x_preferred":[
        "\u09ae\u09c1\u09a8\u09cd\u09b8\u09bf\u09b0\u09be\u09ae \u0995\u09b2\u09cb\u09a8\u09c0"
    ],
    "name:ben_in_x_preferred":[
        "\u09ae\u09c1\u09a8\u09cd\u09b8\u09bf\u09b0\u09be\u09ae \u0995\u09b2\u09cb\u09a8\u09c0"
    ],
    "name:eng_x_preferred":[
        "Munshiram Colony"
    ],
    "name:guj_x_preferred":[
        "\u0aae\u0ac1\u0aa8\u0ab6\u0ac0\u0ab0\u0abe\u0aae \u0a95\u0acb\u0ab2\u0acb\u0aa8\u0ac0"
    ],
    "name:hin_x_preferred":[
        "\u092e\u0941\u0902\u0936\u0940\u0930\u093e\u092e \u0915\u0949\u0932\u094b\u0928\u0940"
    ],
    "name:kan_x_preferred":[
        "\u0cae\u0cc1\u0ca8\u0ccd\u0cb6\u0cbf\u0cb0\u0cbe\u0cae\u0ccd"
    ],
    "name:mal_x_preferred":[
        "\u0d2e\u0d41\u0d7b\u0d37\u0d3f\u0d31\u0d3e\u0d02 \u0d15\u0d4b\u0d33\u0d28\u0d3f"
    ],
    "name:mar_x_preferred":[
        "\u092e\u0941\u0902\u0936\u0940\u0930\u093e\u092e \u0915\u0949\u0932\u0928\u0940"
    ],
    "name:pan_x_preferred":[
        "\u0a2e\u0a41\u0a28\u0a36\u0a40\u0a30\u0a3e\u0a2e \u0a15\u0a32\u0a4c\u0a28\u0a40"
    ],
    "name:tam_x_preferred":[
        "\u0bae\u0bc1\u0ba9\u0bcd\u0bb7\u0bbf\u0bb0\u0bbe\u0bae\u0bcd \u0b95\u0bc1\u0b9f\u0bbf\u0baf\u0bbf\u0bb0\u0bc1\u0baa\u0bcd\u0baa\u0bc1"
    ],
    "name:tel_x_preferred":[
        "\u0c2e\u0c41\u0c28\u0c4d\u0c37\u0c3f\u0c30\u0c3e\u0c2e\u0c4d \u0c15\u0c3e\u0c32\u0c28\u0c40"
    ],
    "name:urd_x_preferred":[
        "\u0645\u0646\u0634\u06cc \u0631\u0627\u0645 \u06a9\u0627\u0644\u0648\u0646\u06cc"
    ],
    "qs:gn_adm0_cc":"IN",
    "qs:gn_local":1253405,
    "qs:gn_nam_loc":"Varanasi, Varanasi, Uttar Pradesh, IN",
    "qs:gn_namadm1":"36",
    "qs:local_max":11649,
    "qs:local_sum":17228,
    "qs:localhoods":15,
    "qs:name":"Munshiram Colony",
    "qs:name_adm0":"India",
    "qs:name_adm1":"Uttar Pradesh",
    "qs:name_adm2":"Varanasi",
    "qs:name_local":"Varanasi",
    "qs:photo_max":95,
    "qs:photo_sum":152,
    "qs:placetype":"Suburb",
    "qs:quad_count":6,
    "qs:woe_adm0":23424848,
    "qs:woe_adm1":2345760,
    "qs:woe_adm2":12586794,
    "qs:woe_lau":0,
    "qs:woe_local":2295380,
    "qs:woe_ver":"7.10.0",
    "wof:lang":[
        "eng"
    ],
    "wof:name":"Munshiram Colony",
    "wof:placetype":"neighbourhood"
},
  "geometry": {"coordinates":[82.987691,25.327976],"type":"Point"}
}