{
  "type": "Feature",
  "properties": {
    "iso:country":"IN",
    "ks:ks_name":"Vazhikadavu",
    "ks:ks_pop":826,
    "ks:ks_type":"HABITATION",
    "name:eng_x_preferred":[
        "Vazhikadavu"
    ],
    "wof:name":"Vazhikadavu",
    "wof:placetype":"locality",
    "wof:population":826
},
  "geometry": {"coordinates":[76.03685,11.378608],"type":"Point"}
}