{
  "type": "Feature",
  "properties": {
    "gn:admin1_code":"25.0",
    "gn:admin2_code":"605.0",
    "gn:asciiname":"Kilur",
    "gn:country_code":"IN",
    "gn:dem":277,
    "gn:feature_class":"P",
    "gn:feature_code":"PPL",
    "gn:name":"K\u012bl\u016br",
    "gn:population":0,
    "gn:timezone":"Asia/Kolkata",
    "iso:country":"IN",
    "wof:name":"Kilur",
    "wof:placetype":"neighbourhood"
},
  "geometry": {"coordinates":[78.85845999999999,12.89999],"type":"Point"}
}