{
  "type": "Feature",
  "properties": {
    "iso:country":"IN",
    "ks:ks_alt_nam":"thakarwadi",
    "ks:ks_name":"Thakarwadi",
    "ks:ks_pop":765,
    "ks:ks_type":"HABITATION",
    "name:eng_x_preferred":[
        "Thakarwadi"
    ],
    "wof:name":"Thakarwadi",
    "wof:placetype":"locality",
    "wof:population":765
},
  "geometry": {"coordinates":[73.591858,18.861336],"type":"Point"}
}