{
  "type": "Feature",
  "properties": {
    "iso:country":"IN",
    "ks:ks_name":"Vijayapuram",
    "ks:ks_pop":324,
    "ks:ks_type":"HABITATION",
    "name:eng_x_preferred":[
        "Vijayapuram"
    ],
    "wof:name":"Vijayapuram",
    "wof:placetype":"locality",
    "wof:population":324
},
  "geometry": {"coordinates":[78.49285399999999,10.378761],"type":"Point"}
}