{
  "type": "Feature",
  "properties": {
    "iso:country":"IN",
    "ks:ks_name":"Saroli",
    "ks:ks_pop":2878,
    "ks:ks_type":"VILLAGE",
    "ks:ks_uagg_main":0,
    "name:eng_x_preferred":[
        "Saroli"
    ],
    "wof:name":"Saroli",
    "wof:placetype":"neighbourhood",
    "wof:population":2878
},
  "geometry": {"coordinates":[72.888944,21.191361],"type":"Point"}
}