{
  "type": "Feature",
  "properties": {
    "iso:country":"IN",
    "ks:ks_name":"Kosiari",
    "ks:ks_pop":0,
    "ks:ks_type":"VILLAGE",
    "name:eng_x_preferred":[
        "Kosiari"
    ],
    "wof:name":"Kosiari",
    "wof:placetype":"locality",
    "wof:population":0
},
  "geometry": {"coordinates":[85.767595,24.603779],"type":"Point"}
}