{
  "type": "Feature",
  "properties": {
    "iso:country":"IN",
    "ks:ks_name":"Bid Chhoti",
    "ks:ks_pop":57,
    "ks:ks_type":"HABITATION",
    "name:eng_x_preferred":[
        "Bid Chhoti"
    ],
    "wof:name":"Bid Chhoti",
    "wof:placetype":"locality",
    "wof:population":57
},
  "geometry": {"coordinates":[74.69315400000001,22.508958],"type":"Point"}
}