{
  "type": "Feature",
  "properties": {
    "iso:country":"IN",
    "ks:ks_name":"Varachi Dhangarwadi",
    "ks:ks_pop":157,
    "ks:ks_type":"HABITATION",
    "name:eng_x_preferred":[
        "Varachi Dhangarwadi"
    ],
    "wof:name":"Varachi Dhangarwadi",
    "wof:placetype":"locality",
    "wof:population":157
},
  "geometry": {"coordinates":[73.64526600000001,16.383275],"type":"Point"}
}