{
  "type": "Feature",
  "properties": {
    "iso:country":"IN",
    "ks:ks_name":"Bartoli",
    "ks:ks_pop":326,
    "ks:ks_type":"VILLAGE",
    "name:eng_x_preferred":[
        "Bartoli"
    ],
    "wof:name":"Bartoli",
    "wof:placetype":"locality",
    "wof:population":326
},
  "geometry": {"coordinates":[79.79933699999999,29.629778],"type":"Point"}
}