{
  "type": "Feature",
  "properties": {
    "gn:admin1_code":"19.0",
    "gn:admin2_code":"578.0",
    "gn:asciiname":"Marihoshalli",
    "gn:country_code":"IN",
    "gn:dem":876,
    "gn:feature_class":"P",
    "gn:feature_code":"PPL",
    "gn:name":"M\u0101rihoshalli",
    "gn:population":0,
    "gn:timezone":"Asia/Kolkata",
    "iso:country":"IN",
    "wof:name":"Marihoshalli",
    "wof:placetype":"locality"
},
  "geometry": {"coordinates":[76.76884,11.75443],"type":"Point"}
}