{
  "type": "Feature",
  "properties": {
    "gn:admin1_code":"19.0",
    "gn:admin2_code":"578.0",
    "gn:asciiname":"Marihoshalli",
    "gn:country_code":"IN",
    "gn:dem":876,
    "gn:feature_class":"P",
    "gn:feature_code":"PPL",
    "gn:name":"M\u0101rihoshalli",
    "gn:population":0,
    "gn:timezone":"Asia/Kolkata",
    "iso:country":"IN",
    "ks:ks_name":"Marihosahalli",
    "ks:ks_type":"VILLAGE",
    "name:eng_x_preferred":[
        "Marihosahalli"
    ],
    "name:eng_x_variant":[
        "Marihoshalli"
    ],
    "wof:name":"Marihosahalli",
    "wof:placetype":"locality"
},
  "geometry": {"coordinates":[76.779121,11.757437],"type":"Point"}
}