{
  "type": "Feature",
  "properties": {
    "iso:country":"IN",
    "ks:ks_name":"Jamadarguda",
    "ks:ks_pop":31,
    "ks:ks_type":"HABITATION",
    "name:eng_x_preferred":[
        "Jamadarguda"
    ],
    "wof:name":"Jamadarguda",
    "wof:placetype":"locality",
    "wof:population":31
},
  "geometry": {"coordinates":[82.71753099999999,18.873498],"type":"Point"}
}