{
  "type": "Feature",
  "properties": {
    "iso:country":"IN",
    "ks:ks_name":"Saltaria",
    "ks:ks_pop":139,
    "ks:ks_type":"VILLAGE",
    "name:eng_x_preferred":[
        "Saltaria"
    ],
    "wof:name":"Saltaria",
    "wof:placetype":"locality",
    "wof:population":139
},
  "geometry": {"coordinates":[87.05365999999999,22.200088],"type":"Point"}
}