{
  "type": "Feature",
  "properties": {
    "gn:admin1_code":"35.0",
    "gn:admin2_code":"465.0",
    "gn:asciiname":"Chikhora",
    "gn:country_code":"IN",
    "gn:dem":270,
    "gn:feature_class":"P",
    "gn:feature_code":"PPL",
    "gn:name":"Chikhora",
    "gn:population":0,
    "gn:timezone":"Asia/Kolkata",
    "iso:country":"IN",
    "ks:ks_name":"Chikhola",
    "ks:ks_pop":1424,
    "ks:ks_type":"VILLAGE",
    "name:eng_x_preferred":[
        "Chikhola"
    ],
    "name:eng_x_variant":[
        "Chikhora"
    ],
    "wof:name":"Chikhola",
    "wof:placetype":"locality",
    "wof:population":1424
},
  "geometry": {"coordinates":[74.209861,22.156461],"type":"Point"}
}