{
  "type": "Feature",
  "properties": {
    "gn:admin1_code":"35.0",
    "gn:admin2_code":"465.0",
    "gn:asciiname":"Chikhora",
    "gn:country_code":"IN",
    "gn:dem":270,
    "gn:feature_class":"P",
    "gn:feature_code":"PPL",
    "gn:name":"Chikhora",
    "gn:population":0,
    "gn:timezone":"Asia/Kolkata",
    "iso:country":"IN",
    "wof:name":"Chikhora",
    "wof:placetype":"locality"
},
  "geometry": {"coordinates":[74.21684999999999,22.15592],"type":"Point"}
}