{
  "type": "Feature",
  "properties": {
    "iso:country":"IN",
    "ks:ks_name":"Shiwapur Ry Chak",
    "ks:ks_pop":229,
    "ks:ks_type":"HABITATION",
    "ks:ks_uagg_main":0,
    "name:eng_x_preferred":[
        "Shiwapur Ry Chak"
    ],
    "wof:name":"Shiwapur Ry Chak",
    "wof:placetype":"neighbourhood",
    "wof:population":229
},
  "geometry": {"coordinates":[79.65790800000001,20.148864],"type":"Point"}
}