{
  "type": "Feature",
  "properties": {
    "iso:country":"IN",
    "ks:ks_name":"Abhayapur Rampur Kham",
    "ks:ks_type":"VILLAGE",
    "name:eng_x_preferred":[
        "Abhayapur Rampur Kham"
    ],
    "wof:name":"Abhayapur Rampur Kham",
    "wof:placetype":"locality"
},
  "geometry": {"coordinates":[78.6126,27.994803],"type":"Point"}
}