{
  "type": "Feature",
  "properties": {
    "gn:admin1_code":"2.0",
    "gn:admin2_code":"546.0",
    "gn:asciiname":"Krishnampalem",
    "gn:country_code":"IN",
    "gn:dem":79,
    "gn:feature_class":"P",
    "gn:feature_code":"PPL",
    "gn:name":"Krishnamp\u0101lem",
    "gn:population":0,
    "gn:timezone":"Asia/Kolkata",
    "iso:country":"IN",
    "wof:name":"Krishnampalem",
    "wof:placetype":"locality"
},
  "geometry": {"coordinates":[81.40315,17.10466],"type":"Point"}
}