{
  "type": "Feature",
  "properties": {
    "iso:country":"IN",
    "ks:ks_alt_nam":"Kotha thanda",
    "ks:ks_name":"Kotha Thanda",
    "ks:ks_pop":89,
    "ks:ks_type":"HABITATION",
    "name:eng_x_preferred":[
        "Kotha Thanda"
    ],
    "wof:name":"Kotha Thanda",
    "wof:placetype":"locality",
    "wof:population":89
},
  "geometry": {"coordinates":[79.231095,17.819989],"type":"Point"}
}