{
  "type": "Feature",
  "properties": {
    "iso:country":"IN",
    "ks:ks_name":"Boalea Pt.II",
    "ks:ks_pop":2206,
    "ks:ks_type":"VILLAGE",
    "name:eng_x_preferred":[
        "Boalea Pt.II"
    ],
    "wof:name":"Boalea Pt.II",
    "wof:placetype":"locality",
    "wof:population":2206
},
  "geometry": {"coordinates":[89.930148,25.798097],"type":"Point"}
}