{
  "type": "Feature",
  "properties": {
    "iso:country":"IN",
    "ks:ks_alt_nam":"MATHI KA PURA",
    "ks:ks_name":"Mathi Ka Pura",
    "ks:ks_pop":589,
    "ks:ks_type":"HABITATION",
    "name:eng_x_preferred":[
        "Mathi Ka Pura"
    ],
    "wof:name":"Mathi Ka Pura",
    "wof:placetype":"locality",
    "wof:population":589
},
  "geometry": {"coordinates":[79.028402,26.661199],"type":"Point"}
}