{
  "type": "Feature",
  "properties": {
    "gn:admin1_code":"16",
    "gn:admin2_code":"499.0",
    "gn:asciiname":"Rau Chinchola",
    "gn:country_code":"IN",
    "gn:dem":289,
    "gn:feature_class":"P",
    "gn:feature_code":"PPL",
    "gn:name":"R\u0101u Chinchola",
    "gn:population":0,
    "gn:timezone":"Asia/Kolkata",
    "iso:country":"IN",
    "ks:ks_alt_nam":"R\u0101u Chinchola",
    "ks:ks_name":"Rau Chinchola",
    "ks:ks_type":"VILLAGE",
    "name:eng_x_preferred":[
        "Rau Chinchola"
    ],
    "name:eng_x_variant":[
        "R\u0101u Chinchola"
    ],
    "wof:name":"Rau Chinchola",
    "wof:placetype":"locality"
},
  "geometry": {"coordinates":[76.04183500000001,20.815438],"type":"Point"}
}