{
  "type": "Feature",
  "properties": {
    "iso:country":"IN",
    "ks:ks_name":"Kochpara",
    "ks:ks_pop":322,
    "ks:ks_type":"HABITATION",
    "ks:ks_uagg_main":0,
    "name:eng_x_preferred":[
        "Kochpara"
    ],
    "wof:name":"Kochpara",
    "wof:placetype":"locality",
    "wof:population":322
},
  "geometry": {"coordinates":[91.475149,26.107084],"type":"Point"}
}