{
  "type": "Feature",
  "properties": {
    "iso:country":"IN",
    "ks:ks_name":"Ayyarkollai",
    "ks:ks_pop":150,
    "ks:ks_type":"HABITATION",
    "name:eng_x_preferred":[
        "Ayyarkollai"
    ],
    "wof:name":"Ayyarkollai",
    "wof:placetype":"locality",
    "wof:population":150
},
  "geometry": {"coordinates":[80.08198299999999,12.715255],"type":"Point"}
}