{
  "type": "Feature",
  "properties": {
    "gn:admin1_code":"19.0",
    "gn:admin2_code":"568.0",
    "gn:asciiname":"Kumbarageri",
    "gn:country_code":"IN",
    "gn:dem":583,
    "gn:feature_class":"P",
    "gn:feature_code":"PPL",
    "gn:name":"Kumb\u0101rageri",
    "gn:population":0,
    "gn:timezone":"Asia/Kolkata",
    "iso:country":"IN",
    "wof:name":"Kumbarageri",
    "wof:placetype":"locality"
},
  "geometry": {"coordinates":[75.09225000000001,13.89234],"type":"Point"}
}