{
  "type": "Feature",
  "properties": {
    "gn:admin1_code":"2",
    "gn:admin2_code":"544.0",
    "gn:asciiname":"Parsel",
    "gn:country_code":"IN",
    "gn:dem":1018,
    "gn:feature_class":"P",
    "gn:feature_code":"PPL",
    "gn:name":"Parsel",
    "gn:population":0,
    "gn:timezone":"Asia/Kolkata",
    "iso:country":"IN",
    "wof:name":"Parsel",
    "wof:placetype":"neighbourhood"
},
  "geometry": {"coordinates":[82.84283000000001,18.23608],"type":"Point"}
}