{
  "type": "Feature",
  "properties": {
    "iso:country":"IN",
    "ks:ks_name":"Tola Karmatanr",
    "ks:ks_pop":0,
    "ks:ks_type":"VILLAGE",
    "name:eng_x_preferred":[
        "Tola Karmatanr"
    ],
    "wof:name":"Tola Karmatanr",
    "wof:placetype":"locality",
    "wof:population":0
},
  "geometry": {"coordinates":[86.513261,24.743857],"type":"Point"}
}