{
  "type": "Feature",
  "properties": {
    "iso:country":"IN",
    "ks:ks_name":"Punnapuzhi Jn",
    "ks:ks_pop":1845,
    "ks:ks_type":"HABITATION",
    "name:eng_x_preferred":[
        "Punnapuzhi Jn"
    ],
    "wof:name":"Punnapuzhi Jn",
    "wof:placetype":"locality",
    "wof:population":1845
},
  "geometry": {"coordinates":[76.434996,9.695999],"type":"Point"}
}