{
  "type": "Feature",
  "properties": {
    "gn:admin1_code":"38.0",
    "gn:admin2_code":"360",
    "gn:asciiname":"Bishungarh",
    "gn:country_code":"IN",
    "gn:dem":453,
    "gn:feature_class":"P",
    "gn:feature_code":"PPL",
    "gn:name":"Bishungarh",
    "gn:population":0,
    "gn:timezone":"Asia/Kolkata",
    "iso:country":"IN",
    "wof:name":"Bishungarh",
    "wof:placetype":"locality"
},
  "geometry": {"coordinates":[85.75544000000002,24.01514],"type":"Point"}
}