{
  "type": "Feature",
  "properties": {
    "gn:admin1_code":"36",
    "gn:admin2_code":"201.0",
    "gn:asciiname":"Aun",
    "gn:country_code":"IN",
    "gn:dem":172,
    "gn:feature_class":"P",
    "gn:feature_code":"PPL",
    "gn:name":"Aun",
    "gn:population":0,
    "gn:timezone":"Asia/Kolkata",
    "iso:country":"IN",
    "name:bul_x_preferred":[
        "\u0410\u0443\u043d \u0421\u0442\u0430\u0440\u0438\u044f"
    ],
    "name:cat_x_preferred":[
        "Aun"
    ],
    "name:ita_x_preferred":[
        "Aun"
    ],
    "name:por_x_preferred":[
        "Aun"
    ],
    "name:rus_x_preferred":[
        "\u0410\u0443\u043d \u0421\u0442\u0430\u0440\u044b\u0439"
    ],
    "name:spa_x_preferred":[
        "Aun"
    ],
    "name:ukr_x_preferred":[
        "\u0410\u0443\u043d \u0421\u0442\u0430\u0440\u0438\u0439"
    ],
    "wof:name":"Aun",
    "wof:placetype":"neighbourhood"
},
  "geometry": {"coordinates":[78.79327000000001,27.61308],"type":"Point"}
}