{
  "type": "Feature",
  "properties": {
    "iso:country":"IN",
    "ks:ks_name":"Myyolli",
    "ks:ks_pop":115,
    "ks:ks_type":"HABITATION",
    "name:eng_x_preferred":[
        "Myyolli"
    ],
    "wof:name":"Myyolli",
    "wof:placetype":"locality",
    "wof:population":115
},
  "geometry": {"coordinates":[74.726071,14.07692],"type":"Point"}
}