{
  "type": "Feature",
  "properties": {
    "gn:admin1_code":"36.0",
    "gn:admin2_code":"138.0",
    "gn:asciiname":"Piplikhera",
    "gn:country_code":"IN",
    "gn:dem":219,
    "gn:feature_class":"P",
    "gn:feature_code":"PPL",
    "gn:name":"Pipl\u012bkhera",
    "gn:population":0,
    "gn:timezone":"Asia/Kolkata",
    "iso:country":"IN",
    "wof:name":"Piplikhera",
    "wof:placetype":"locality"
},
  "geometry": {"coordinates":[77.77043,28.88331],"type":"Point"}
}