{
  "type": "Feature",
  "properties": {
    "iso:country":"IN",
    "ks:ks_name":"Khariapalli",
    "ks:ks_pop":431,
    "ks:ks_type":"VILLAGE",
    "name:eng_x_preferred":[
        "Khariapalli"
    ],
    "wof:name":"Khariapalli",
    "wof:placetype":"locality",
    "wof:population":431
},
  "geometry": {"coordinates":[85.066858,19.851501],"type":"Point"}
}