{
  "type": "Feature",
  "properties": {
    "iso:country":"IN",
    "ks:ks_name":"Ramna Dadpur",
    "ks:ks_pop":2630,
    "ks:ks_type":"VILLAGE",
    "ks:ks_uagg_main":0,
    "name:eng_x_preferred":[
        "Ramna Dadpur"
    ],
    "wof:name":"Ramna Dadpur",
    "wof:placetype":"neighbourhood",
    "wof:population":2630
},
  "geometry": {"coordinates":[88.240317,23.872013],"type":"Point"}
}