{
  "type": "Feature",
  "properties": {
    "iso:country":"IN",
    "ks:ks_name":"Balabhadraprasad",
    "ks:ks_pop":576,
    "ks:ks_type":"VILLAGE",
    "ks:ks_uagg_main":0,
    "name:eng_x_preferred":[
        "Balabhadraprasad"
    ],
    "wof:name":"Balabhadraprasad",
    "wof:placetype":"neighbourhood",
    "wof:population":576
},
  "geometry": {"coordinates":[86.713775,20.632237],"type":"Point"}
}