{
  "type": "Feature",
  "properties": {
    "iso:country":"IN",
    "ks:ks_alt_nam":"madhliwadi",
    "ks:ks_name":"Madhliwadi",
    "ks:ks_pop":100,
    "ks:ks_type":"HABITATION",
    "name:eng_x_preferred":[
        "Madhliwadi"
    ],
    "wof:name":"Madhliwadi",
    "wof:placetype":"locality",
    "wof:population":100
},
  "geometry": {"coordinates":[73.375833,17.414444],"type":"Point"}
}