{
  "type": "Feature",
  "properties": {
    "iso:country":"IN",
    "ks:ks_name":"Chelod",
    "ks:ks_pop":460,
    "ks:ks_type":"HABITATION",
    "name:eng_x_preferred":[
        "Chelod"
    ],
    "wof:name":"Chelod",
    "wof:placetype":"locality",
    "wof:population":460
},
  "geometry": {"coordinates":[76.04465999999999,11.572456],"type":"Point"}
}