{
  "type": "Feature",
  "properties": {
    "iso:country":"IN",
    "ks:ks_name":"Hedo",
    "ks:ks_pop":543,
    "ks:ks_type":"VILLAGE",
    "name:eng_x_preferred":[
        "Hedo"
    ],
    "wof:name":"Hedo",
    "wof:placetype":"locality",
    "wof:population":543
},
  "geometry": {"coordinates":[72.700078,24.209005],"type":"Point"}
}