{
  "type": "Feature",
  "properties": {
    "iso:country":"IN",
    "ks:ks_name":"Neelya",
    "ks:ks_pop":505,
    "ks:ks_type":"HABITATION",
    "name:eng_x_preferred":[
        "Neelya"
    ],
    "wof:name":"Neelya",
    "wof:placetype":"locality",
    "wof:population":505
},
  "geometry": {"coordinates":[75.16994800000001,12.885502],"type":"Point"}
}