{
  "type": "Feature",
  "properties": {
    "gn:admin1_code":"25.0",
    "gn:admin2_code":"632.0",
    "gn:asciiname":"Oddarpalaiyampudur",
    "gn:country_code":"IN",
    "gn:dem":386,
    "gn:feature_class":"P",
    "gn:feature_code":"PPL",
    "gn:name":"Oddarp\u0101laiyampudur",
    "gn:population":0,
    "gn:timezone":"Asia/Kolkata",
    "iso:country":"IN",
    "wof:name":"Oddarpalaiyampudur",
    "wof:placetype":"locality"
},
  "geometry": {"coordinates":[77.09222,11.23625],"type":"Point"}
}