{
  "type": "Feature",
  "properties": {
    "iso:country":"IN",
    "ks:ks_alt_nam":"KALE WASTI",
    "ks:ks_name":"Kale Wasti",
    "ks:ks_pop":149,
    "ks:ks_type":"HABITATION",
    "name:eng_x_preferred":[
        "Kale Wasti"
    ],
    "wof:name":"Kale Wasti",
    "wof:placetype":"locality",
    "wof:population":149
},
  "geometry": {"coordinates":[74.741747,19.613385],"type":"Point"}
}