{
  "type": "Feature",
  "properties": {
    "gn:admin1_code":"21",
    "gn:admin2_code":"392.0",
    "gn:asciiname":"Sindol",
    "gn:country_code":"IN",
    "gn:dem":132,
    "gn:feature_class":"P",
    "gn:feature_code":"PPL",
    "gn:name":"Sindol",
    "gn:population":0,
    "gn:timezone":"Asia/Kolkata",
    "iso:country":"IN",
    "wof:name":"Sindol",
    "wof:placetype":"locality"
},
  "geometry": {"coordinates":[83.85094000000002,21.08814],"type":"Point"}
}