{
  "type": "Feature",
  "properties": {
    "iso:country":"IN",
    "ks:ks_name":"Hatibandha No 1",
    "ks:ks_pop":218,
    "ks:ks_type":"HABITATION",
    "name:eng_x_preferred":[
        "Hatibandha No 1"
    ],
    "wof:name":"Hatibandha No 1",
    "wof:placetype":"locality",
    "wof:population":218
},
  "geometry": {"coordinates":[95.16885000000001,27.346227],"type":"Point"}
}