{
  "type": "Feature",
  "properties": {
    "iso:country":"IN",
    "ks:ks_name":"Patelwadi",
    "ks:ks_pop":213,
    "ks:ks_type":"HABITATION",
    "name:eng_x_preferred":[
        "Patelwadi"
    ],
    "wof:name":"Patelwadi",
    "wof:placetype":"locality",
    "wof:population":213
},
  "geometry": {"coordinates":[73.790204,16.242539],"type":"Point"}
}