{
  "type": "Feature",
  "properties": {
    "iso:country":"IN",
    "ks:ks_name":"Gowal",
    "ks:ks_pop":23,
    "ks:ks_type":"VILLAGE",
    "name:eng_x_preferred":[
        "Gowal"
    ],
    "wof:name":"Gowal",
    "wof:placetype":"locality",
    "wof:population":23
},
  "geometry": {"coordinates":[73.36696499999999,17.921649],"type":"Point"}
}