{
  "type": "Feature",
  "properties": {
    "gn:admin1_code":"2.0",
    "gn:admin2_code":"549.0",
    "gn:asciiname":"Gangavaram Santanutalapadu",
    "gn:country_code":"IN",
    "gn:dem":35,
    "gn:feature_class":"P",
    "gn:feature_code":"PPL",
    "gn:name":"Gangav\u0101ram Santan\u016btalap\u0101du",
    "gn:population":0,
    "gn:timezone":"Asia/Kolkata",
    "iso:country":"IN",
    "wof:name":"Gangavaram Santanutalapadu",
    "wof:placetype":"neighbourhood"
},
  "geometry": {"coordinates":[79.94059,15.54307],"type":"Point"}
}