{
  "type": "Feature",
  "properties": {
    "gn:admin1_code":"25.0",
    "gn:admin2_code":"602.0",
    "gn:asciiname":"Nelvay",
    "gn:country_code":"IN",
    "gn:dem":30,
    "gn:feature_class":"P",
    "gn:feature_code":"PPL",
    "gn:name":"Nelv\u0101y",
    "gn:population":0,
    "gn:timezone":"Asia/Kolkata",
    "iso:country":"IN",
    "wof:name":"Nelvay",
    "wof:placetype":"locality"
},
  "geometry": {"coordinates":[80.03524,13.33147],"type":"Point"}
}