{
  "type": "Feature",
  "properties": {
    "iso:country":"IN",
    "ks:ks_name":"Kushahi",
    "ks:ks_pop":152,
    "ks:ks_type":"VILLAGE",
    "name:eng_x_preferred":[
        "Kushahi"
    ],
    "wof:name":"Kushahi",
    "wof:placetype":"locality",
    "wof:population":152
},
  "geometry": {"coordinates":[83.952344,25.439297],"type":"Point"}
}