{
  "type": "Feature",
  "properties": {
    "iso:country":"IN",
    "ks:ks_name":"Kalimali",
    "ks:ks_pop":695,
    "ks:ks_type":"HABITATION",
    "name:eng_x_preferred":[
        "Kalimali"
    ],
    "wof:name":"Kalimali",
    "wof:placetype":"locality",
    "wof:population":695
},
  "geometry": {"coordinates":[72.54371399999999,27.106383],"type":"Point"}
}