{
  "type": "Feature",
  "properties": {
    "iso:country":"IN",
    "qs:name":"Kundarghat",
    "qs:name_adm0":"India",
    "qs:name_adm1":"Himachal Pradesh",
    "qs:photos":82,
    "qs:photos_1k":17,
    "qs:photos_9k":1,
    "qs:photos_9r":3,
    "qs:photos_all":82,
    "qs:photos_sr":3,
    "qs:placetype":"Town",
    "qs:pop_sr":"0",
    "wof:name":"Kundarghat",
    "wof:placetype":"locality"
},
  "geometry": {"coordinates":[77.113298,31.001467],"type":"Point"}
}