{
  "type": "Feature",
  "properties": {
    "iso:country":"IN",
    "ks:ks_alt_nam":"Pem\u0101dih",
    "ks:ks_name":"Pemadih",
    "ks:ks_pop":193,
    "ks:ks_type":"VILLAGE",
    "name:eng_x_preferred":[
        "Pemadih"
    ],
    "name:eng_x_variant":[
        "Pem\u0101dih"
    ],
    "wof:name":"Pemadih",
    "wof:placetype":"locality",
    "wof:population":193
},
  "geometry": {"coordinates":[86.445944,24.954572],"type":"Point"}
}