{
  "type": "Feature",
  "properties": {
    "gn:admin1_code":"19.0",
    "gn:admin2_code":"563",
    "gn:asciiname":"Halge",
    "gn:country_code":"IN",
    "gn:dem":13,
    "gn:feature_class":"P",
    "gn:feature_code":"PPL",
    "gn:name":"Halge",
    "gn:population":0,
    "gn:timezone":"Asia/Kolkata",
    "iso:country":"IN",
    "wof:name":"Halge",
    "wof:placetype":"locality"
},
  "geometry": {"coordinates":[74.22572,14.88557],"type":"Point"}
}