{
  "type": "Feature",
  "properties": {
    "iso:country":"IN",
    "ks:ks_name":"Sale Para",
    "ks:ks_pop":231,
    "ks:ks_type":"HABITATION",
    "name:eng_x_preferred":[
        "Sale Para"
    ],
    "wof:name":"Sale Para",
    "wof:placetype":"locality",
    "wof:population":231
},
  "geometry": {"coordinates":[81.910056,19.483681],"type":"Point"}
}