{
  "type": "Feature",
  "properties": {
    "gn:admin1_code":"39.0",
    "gn:admin2_code":"65.0",
    "gn:asciiname":"Mathiabanj",
    "gn:country_code":"IN",
    "gn:dem":1550,
    "gn:feature_class":"P",
    "gn:feature_code":"PPL",
    "gn:name":"Mathi\u0101b\u0101nj",
    "gn:population":0,
    "gn:timezone":"Asia/Kolkata",
    "iso:country":"IN",
    "ks:ks_name":"Mathiya Baj",
    "ks:ks_pop":517,
    "ks:ks_type":"VILLAGE",
    "name:eng_x_preferred":[
        "Mathiya Baj"
    ],
    "name:eng_x_variant":[
        "Mathiabanj"
    ],
    "wof:name":"Mathiya Baj",
    "wof:placetype":"locality",
    "wof:population":517
},
  "geometry": {"coordinates":[80.035639,29.164443],"type":"Point"}
}