{
  "type": "Feature",
  "properties": {
    "iso:country":"IN",
    "ks:ks_name":"Kurubagere",
    "ks:ks_pop":249,
    "ks:ks_type":"VILLAGE",
    "ks:ks_uagg_main":0,
    "name:eng_x_preferred":[
        "Kurubagere"
    ],
    "wof:name":"Kurubagere",
    "wof:placetype":"neighbourhood",
    "wof:population":249
},
  "geometry": {"coordinates":[75.997407,13.495444],"type":"Point"}
}