{
  "type": "Feature",
  "properties": {
    "gn:admin1_code":"35.0",
    "gn:admin2_code":"427.0",
    "gn:asciiname":"Pagara",
    "gn:country_code":"IN",
    "gn:dem":447,
    "gn:feature_class":"P",
    "gn:feature_code":"PPL",
    "gn:name":"Pagara",
    "gn:population":0,
    "gn:timezone":"Asia/Kolkata",
    "iso:country":"IN",
    "name:ceb_x_preferred":[
        "Pagara"
    ],
    "name:por_x_preferred":[
        "Pagara"
    ],
    "name:ron_x_preferred":[
        "Pagara"
    ],
    "name:swe_x_preferred":[
        "Pagara"
    ],
    "name:war_x_preferred":[
        "Pagara"
    ],
    "wof:name":"Pagara",
    "wof:placetype":"locality"
},
  "geometry": {"coordinates":[79.0934,24.07277],"type":"Point"}
}