{
  "type": "Feature",
  "properties": {
    "iso:country":"IN",
    "ks:ks_name":"Mangalapalem",
    "ks:ks_pop":370,
    "ks:ks_type":"VILLAGE",
    "name:eng_x_preferred":[
        "Mangalapalem"
    ],
    "wof:name":"Mangalapalem",
    "wof:placetype":"locality",
    "wof:population":370
},
  "geometry": {"coordinates":[82.23250299999999,17.822503],"type":"Point"}
}