{
  "type": "Feature",
  "properties": {
    "iso:country":"IN",
    "ks:ks_name":"Derla",
    "ks:ks_pop":523,
    "ks:ks_type":"HABITATION",
    "name:eng_x_preferred":[
        "Derla"
    ],
    "wof:name":"Derla",
    "wof:placetype":"locality",
    "wof:population":523
},
  "geometry": {"coordinates":[75.278723,12.675427],"type":"Point"}
}