{
  "type": "Feature",
  "properties": {
    "iso:country":"IN",
    "ks:ks_name":"Chandaliya",
    "ks:ks_pop":2099,
    "ks:ks_type":"VILLAGE",
    "name:eng_x_preferred":[
        "Chandaliya"
    ],
    "wof:name":"Chandaliya",
    "wof:placetype":"locality",
    "wof:population":2099
},
  "geometry": {"coordinates":[72.74318599999999,26.596056],"type":"Point"}
}