{
  "type": "Feature",
  "properties": {
    "gn:admin1_code":"25.0",
    "gn:admin2_code":"631.0",
    "gn:asciiname":"Kasuvugatta",
    "gn:country_code":"IN",
    "gn:dem":841,
    "gn:feature_class":"P",
    "gn:feature_code":"PPL",
    "gn:name":"Kasuvugatta",
    "gn:population":0,
    "gn:timezone":"Asia/Kolkata",
    "iso:country":"IN",
    "wof:name":"Kasuvugatta",
    "wof:placetype":"locality"
},
  "geometry": {"coordinates":[77.85876,12.71474],"type":"Point"}
}