{
  "type": "Feature",
  "properties": {
    "gn:admin1_code":"34.0",
    "gn:admin2_code":"218.0",
    "gn:asciiname":"Chaumukha Khurd",
    "gn:country_code":"IN",
    "gn:dem":71,
    "gn:feature_class":"P",
    "gn:feature_code":"PPL",
    "gn:name":"Chaumukha Khurd",
    "gn:population":0,
    "gn:timezone":"Asia/Kolkata",
    "iso:country":"IN",
    "ks:ks_name":"Chaumukha Khurd",
    "ks:ks_type":"VILLAGE",
    "ks:ks_uagg_main":0,
    "name:eng_x_preferred":[
        "Chaumukha Khurd"
    ],
    "wof:name":"Chaumukha Khurd",
    "wof:placetype":"neighbourhood"
},
  "geometry": {"coordinates":[84.113685,26.218656],"type":"Point"}
}