{
  "type": "Feature",
  "properties": {
    "gn:admin1_code":"39",
    "gn:admin2_code":"60.0",
    "gn:asciiname":"Lokar",
    "gn:country_code":"IN",
    "gn:dem":2228,
    "gn:feature_class":"P",
    "gn:feature_code":"PPL",
    "gn:name":"Lok\u0101r",
    "gn:population":0,
    "gn:timezone":"Asia/Kolkata",
    "iso:country":"IN",
    "wof:name":"Lokar",
    "wof:placetype":"locality"
},
  "geometry": {"coordinates":[77.97095,30.85329],"type":"Point"}
}