{
  "type": "Feature",
  "properties": {
    "iso:country":"IN",
    "ks:ks_name":"Jhagru Chak",
    "ks:ks_type":"VILLAGE",
    "name:eng_x_preferred":[
        "Jhagru Chak"
    ],
    "wof:name":"Jhagru Chak",
    "wof:placetype":"locality"
},
  "geometry": {"coordinates":[83.46961,25.343636],"type":"Point"}
}