{
  "type": "Feature",
  "properties": {
    "gn:admin1_code":"24.0",
    "gn:admin2_code":"124.0",
    "gn:asciiname":"Gokalpura",
    "gn:country_code":"IN",
    "gn:dem":308,
    "gn:feature_class":"P",
    "gn:feature_code":"PPL",
    "gn:name":"Gokalpura",
    "gn:population":0,
    "gn:timezone":"Asia/Kolkata",
    "iso:country":"IN",
    "ks:ks_name":"Gokal Pura",
    "ks:ks_pop":1243,
    "ks:ks_type":"VILLAGE",
    "ks:ks_uagg_main":0,
    "name:ara_x_preferred":[
        "\u062c\u0648\u0643\u0627\u0644\u0628\u0648\u0631\u0627"
    ],
    "name:ben_bn_x_preferred":[
        "\u0997\u09cb\u0995\u09be\u09b2\u09aa\u09c1\u09b0\u09be"
    ],
    "name:ben_in_x_preferred":[
        "\u0997\u09cb\u0995\u09be\u09b2\u09aa\u09c1\u09b0\u09be"
    ],
    "name:eng_x_preferred":[
        "Gokal Pura"
    ],
    "name:guj_x_preferred":[
        "\u0a97\u0acb\u0a95\u0ab2\u0aaa\u0ac1\u0ab0\u0abe"
    ],
    "name:hin_x_preferred":[
        "\u0917\u094b\u0915\u0932\u092a\u0941\u0930\u093e"
    ],
    "name:kan_x_preferred":[
        "\u0c97\u0ccb\u0c95\u0cb2\u0ccd"
    ],
    "name:mal_x_preferred":[
        "\u0d17\u0d4b\u0d15\u0d7d\u0d2a\u0d41\u0d30"
    ],
    "name:mar_x_preferred":[
        "\u0917\u094b\u0915\u0932\u092a\u0941\u0930\u093e"
    ],
    "name:pan_x_preferred":[
        "\u0a17\u0a4b\u0a15\u0a32\u0a2a\u0a41\u0a30\u0a3e"
    ],
    "name:tam_x_preferred":[
        "\u0b95\u0bcb\u0b95\u0bb2\u0bcd\u0baa\u0bc1\u0bb0\u0bbe"
    ],
    "name:tel_x_preferred":[
        "\u0c17\u0c4b\u0c15\u0c32\u0c4d"
    ],
    "name:urd_x_preferred":[
        "\u06af\u0648\u06a9\u0644 \u067e\u0648\u0631\u06cc"
    ],
    "wof:name":"Gokal Pura",
    "wof:placetype":"neighbourhood",
    "wof:population":1243
},
  "geometry": {"coordinates":[73.72766799999999,23.858463],"type":"Point"}
}