{
  "type": "Feature",
  "properties": {
    "iso:country":"IN",
    "ks:ks_name":"Shermuntilla",
    "ks:ks_pop":345,
    "ks:ks_type":"HABITATION",
    "name:eng_x_preferred":[
        "Shermuntilla"
    ],
    "wof:name":"Shermuntilla",
    "wof:placetype":"locality",
    "wof:population":345
},
  "geometry": {"coordinates":[92.090402,24.159939],"type":"Point"}
}