{
  "type": "Feature",
  "properties": {
    "iso:country":"IN",
    "ks:ks_alt_nam":"rengarampatty",
    "ks:ks_name":"Rengarampatty",
    "ks:ks_pop":465,
    "ks:ks_type":"HABITATION",
    "ks:ks_uagg_main":0,
    "name:eng_x_preferred":[
        "Rengarampatty"
    ],
    "wof:name":"Rengarampatty",
    "wof:placetype":"neighbourhood",
    "wof:population":465
},
  "geometry": {"coordinates":[77.64027299999999,9.968938],"type":"Point"}
}