{
  "type": "Feature",
  "properties": {
    "iso:country":"IN",
    "ks:ks_name":"Jotmari",
    "ks:ks_pop":273,
    "ks:ks_type":"VILLAGE",
    "ks:ks_uagg_main":0,
    "name:eng_x_preferred":[
        "Jotmari"
    ],
    "wof:name":"Jotmari",
    "wof:placetype":"neighbourhood",
    "wof:population":273
},
  "geometry": {"coordinates":[87.682205,22.557415],"type":"Point"}
}