{
  "type": "Feature",
  "properties": {
    "iso:country":"IN",
    "ks:ks_name":"Godisahi",
    "ks:ks_pop":330,
    "ks:ks_type":"HABITATION",
    "name:eng_x_preferred":[
        "Godisahi"
    ],
    "wof:name":"Godisahi",
    "wof:placetype":"locality",
    "wof:population":330
},
  "geometry": {"coordinates":[85.606841,21.000683],"type":"Point"}
}