{
  "type": "Feature",
  "properties": {
    "gn:admin1_code":"36",
    "gn:admin2_code":"178.0",
    "gn:asciiname":"Fatehpur Pakri",
    "gn:country_code":"IN",
    "gn:dem":92,
    "gn:feature_class":"P",
    "gn:feature_code":"PPL",
    "gn:name":"Fatehpur Pakri",
    "gn:population":0,
    "gn:timezone":"Asia/Kolkata",
    "iso:country":"IN",
    "ks:ks_name":"Fatehpur Pakri",
    "ks:ks_type":"VILLAGE",
    "ks:ks_uagg_main":0,
    "name:eng_x_preferred":[
        "Fatehpur Pakri"
    ],
    "wof:name":"Fatehpur Pakri",
    "wof:placetype":"neighbourhood"
},
  "geometry": {"coordinates":[82.53112400000001,26.415638],"type":"Point"}
}