{
  "type": "Feature",
  "properties": {
    "gn:admin1_code":"9.0",
    "gn:admin2_code":"492.0",
    "gn:asciiname":"Barbodhan",
    "gn:country_code":"IN",
    "gn:dem":10,
    "gn:feature_class":"P",
    "gn:feature_code":"PPL",
    "gn:name":"Barbodhan",
    "gn:population":0,
    "gn:timezone":"Asia/Kolkata",
    "iso:country":"IN",
    "wof:name":"Barbodhan",
    "wof:placetype":"locality"
},
  "geometry": {"coordinates":[72.70924000000002,21.22394],"type":"Point"}
}