{
  "type": "Feature",
  "properties": {
    "iso:country":"IN",
    "ks:ks_name":"Mota Jampur",
    "ks:ks_pop":3793,
    "ks:ks_type":"VILLAGE",
    "name:eng_x_preferred":[
        "Mota Jampur"
    ],
    "wof:name":"Mota Jampur",
    "wof:placetype":"locality",
    "wof:population":3793
},
  "geometry": {"coordinates":[71.88140199999999,23.915943],"type":"Point"}
}