{
  "type": "Feature",
  "properties": {
    "gn:admin1_code":"28",
    "gn:admin2_code":"327.0",
    "gn:asciiname":"Lebong Canttonment",
    "gn:country_code":"IN",
    "gn:dem":1646,
    "gn:feature_class":"P",
    "gn:feature_code":"PPL",
    "gn:name":"Lebong Canttonment",
    "gn:population":0,
    "gn:timezone":"Asia/Kolkata",
    "iso:country":"IN",
    "name:fra_x_preferred":[
        "Lebong"
    ],
    "name:und_x_variant":[
        "Lebong",
        "Lebong Canttonment"
    ],
    "wof:name":"Lebong Canttonment",
    "wof:placetype":"locality"
},
  "geometry": {"coordinates":[88.28293000000002,27.06232],"type":"Point"}
}