{
  "type": "Feature",
  "properties": {
    "iso:country":"IN",
    "ks:ks_alt_nam":"MUSAHARI",
    "ks:ks_name":"Musahari",
    "ks:ks_pop":211,
    "ks:ks_type":"HABITATION",
    "name:eng_x_preferred":[
        "Musahari"
    ],
    "wof:name":"Musahari",
    "wof:placetype":"locality",
    "wof:population":211
},
  "geometry": {"coordinates":[86.24306,25.86968],"type":"Point"}
}