{
  "type": "Feature",
  "properties": {
    "iso:country":"IN",
    "ks:ks_name":"Bishambharpur",
    "ks:ks_pop":1059,
    "ks:ks_type":"VILLAGE",
    "ks:ks_uagg_main":0,
    "name:eng_x_preferred":[
        "Bishambharpur"
    ],
    "wof:name":"Bishambharpur",
    "wof:placetype":"locality",
    "wof:population":1059
},
  "geometry": {"coordinates":[84.487475,26.345431],"type":"Point"}
}