{
  "type": "Feature",
  "properties": {
    "gn:admin1_code":"34.0",
    "gn:admin2_code":"213.0",
    "gn:asciiname":"Murwala",
    "gn:country_code":"IN",
    "gn:dem":50,
    "gn:feature_class":"P",
    "gn:feature_code":"PPL",
    "gn:name":"Murw\u0101la",
    "gn:population":0,
    "gn:timezone":"Asia/Kolkata",
    "iso:country":"IN",
    "ks:ks_alt_nam":"Murw\u0101la",
    "ks:ks_alt_nam_2":"Murwala",
    "ks:ks_name":"Mudwala",
    "ks:ks_pop":482,
    "ks:ks_type":"VILLAGE",
    "ks:ks_uagg_main":0,
    "name:eng_x_preferred":[
        "Mudwala"
    ],
    "name:eng_x_variant":[
        "Murw\u0101la",
        "Murwala"
    ],
    "wof:name":"Mudwala",
    "wof:placetype":"neighbourhood",
    "wof:population":482
},
  "geometry": {"coordinates":[86.74006900000001,25.871704],"type":"Point"}
}