{
  "type": "Feature",
  "properties": {
    "iso:country":"IN",
    "ks:ks_name":"Bheroo Nagar",
    "ks:ks_pop":249,
    "ks:ks_type":"HABITATION",
    "name:eng_x_preferred":[
        "Bheroo Nagar"
    ],
    "wof:name":"Bheroo Nagar",
    "wof:placetype":"locality",
    "wof:population":249
},
  "geometry": {"coordinates":[72.720489,26.457672],"type":"Point"}
}