{
  "type": "Feature",
  "properties": {
    "iso:country":"IN",
    "ks:ks_alt_nam":"Khadia sahi",
    "ks:ks_name":"Khadia Sahi",
    "ks:ks_pop":250,
    "ks:ks_type":"HABITATION",
    "name:eng_x_preferred":[
        "Khadia Sahi"
    ],
    "wof:name":"Khadia Sahi",
    "wof:placetype":"locality",
    "wof:population":250
},
  "geometry": {"coordinates":[86.25834999999999,22.307851],"type":"Point"}
}