{
  "type": "Feature",
  "properties": {
    "gn:admin1_code":"34",
    "gn:admin2_code":"233.0",
    "gn:asciiname":"Gangapur",
    "gn:country_code":"IN",
    "gn:dem":85,
    "gn:feature_class":"P",
    "gn:feature_code":"PPL",
    "gn:name":"Gang\u0101pur",
    "gn:population":0,
    "gn:timezone":"Asia/Kolkata",
    "iso:country":"IN",
    "ks:ks_name":"Gangapur",
    "ks:ks_pop":667,
    "ks:ks_type":"VILLAGE",
    "name:bih_x_preferred":[
        "\u0917\u0902\u0917\u093e\u092a\u0941\u0930"
    ],
    "name:ceb_x_preferred":[
        "Gangapur"
    ],
    "name:eng_x_preferred":[
        "Gangapur"
    ],
    "name:ita_x_preferred":[
        "Gangapur"
    ],
    "name:pol_x_preferred":[
        "Gangapur"
    ],
    "name:swe_x_preferred":[
        "Gangapur"
    ],
    "name:vie_x_preferred":[
        "Gangapur"
    ],
    "wof:name":"Gangapur",
    "wof:placetype":"locality",
    "wof:population":667
},
  "geometry": {"coordinates":[83.480206,25.073034],"type":"Point"}
}