{
  "type": "Feature",
  "properties": {
    "iso:country":"IN",
    "ks:ks_name":"Jambooth",
    "ks:ks_pop":203,
    "ks:ks_type":"HABITATION",
    "ks:ks_uagg_main":0,
    "name:eng_x_preferred":[
        "Jambooth"
    ],
    "wof:name":"Jambooth",
    "wof:placetype":"neighbourhood",
    "wof:population":203
},
  "geometry": {"coordinates":[78.117802,12.382397],"type":"Point"}
}