{
  "type": "Feature",
  "properties": {
    "iso:country":"IN",
    "ks:ks_name":"Kalathur",
    "ks:ks_pop":78,
    "ks:ks_type":"HABITATION",
    "name:eng_x_preferred":[
        "Kalathur"
    ],
    "wof:name":"Kalathur",
    "wof:placetype":"locality",
    "wof:population":78
},
  "geometry": {"coordinates":[78.093424,10.504189],"type":"Point"}
}