{
  "type": "Feature",
  "properties": {
    "iso:country":"IN",
    "ks:ks_alt_nam":"Kenchanahalli AKC",
    "ks:ks_name":"Kenchanahalli Akc",
    "ks:ks_pop":40,
    "ks:ks_type":"HABITATION",
    "name:eng_x_preferred":[
        "Kenchanahalli Akc"
    ],
    "wof:name":"Kenchanahalli Akc",
    "wof:placetype":"locality",
    "wof:population":40
},
  "geometry": {"coordinates":[76.83502799999999,13.30143],"type":"Point"}
}