{
  "type": "Feature",
  "properties": {
    "iso:country":"IN",
    "ks:ks_name":"Paswan Tola",
    "ks:ks_pop":175,
    "ks:ks_type":"HABITATION",
    "ks:ks_uagg_main":0,
    "name:eng_x_preferred":[
        "Paswan Tola"
    ],
    "wof:name":"Paswan Tola",
    "wof:placetype":"neighbourhood",
    "wof:population":175
},
  "geometry": {"coordinates":[86.419355,26.022875],"type":"Point"}
}