{
  "type": "Feature",
  "properties": {
    "gn:admin1_code":"10",
    "gn:admin2_code":"69.0",
    "gn:asciiname":"Majri Satan",
    "gn:country_code":"IN",
    "gn:dem":518,
    "gn:feature_class":"P",
    "gn:feature_code":"PPL",
    "gn:name":"M\u0101jri Sat\u0101n",
    "gn:population":0,
    "gn:timezone":"Asia/Kolkata",
    "iso:country":"IN",
    "ks:ks_name":"Majri Jattan",
    "ks:ks_pop":630,
    "ks:ks_type":"VILLAGE",
    "ks:ks_uagg_main":0,
    "name:eng_x_preferred":[
        "Majri Jattan"
    ],
    "wof:name":"Majri Jattan",
    "wof:placetype":"neighbourhood",
    "wof:population":630
},
  "geometry": {"coordinates":[76.87720400000001,30.819195],"type":"Point"}
}