{
  "type": "Feature",
  "properties": {
    "iso:country":"IN",
    "ks:ks_name":"Shyamsundarpur",
    "ks:ks_pop":649,
    "ks:ks_type":"VILLAGE",
    "ks:ks_uagg_main":0,
    "name:eng_x_preferred":[
        "Shyamsundarpur"
    ],
    "wof:name":"Shyamsundarpur",
    "wof:placetype":"neighbourhood",
    "wof:population":649
},
  "geometry": {"coordinates":[86.52870900000001,22.109165],"type":"Point"}
}