{
  "type": "Feature",
  "properties": {
    "gn:country":"IN",
    "gn:fcode":"PPL",
    "gn:pop":111475,
    "iso:country":"IN",
    "qs:name":"Ashoknagar Kalyangarh",
    "qs:name_adm0":"India",
    "qs:name_adm1":"West Bengal",
    "qs:photos_9k":1,
    "qs:photos_9r":1,
    "qs:photos_all":4,
    "qs:photos_sr":0,
    "qs:placetype":"Town",
    "qs:pop_sr":"9",
    "wof:name":"Ashoknagar Kalyangarh",
    "wof:placetype":"locality",
    "wof:population":111475
},
  "geometry": {"coordinates":[88.63701,22.86416],"type":"Point"}
}