{
  "type": "Feature",
  "properties": {
    "gn:country":"IN",
    "gn:fcode":"PPL",
    "gn:pop":111475,
    "iso:country":"IN",
    "name:ben_x_preferred":[
        "\u0985\u09b6\u09cb\u0995\u09a8\u0997\u09b0 \u0995\u09b2\u09cd\u09af\u09be\u09a3\u0997\u09a1\u09bc"
    ],
    "name:bih_x_preferred":[
        "\u0905\u0936\u094b\u0915\u0928\u0917\u0930"
    ],
    "name:ceb_x_preferred":[
        "Ashoknagar Kalyangarh"
    ],
    "name:ita_x_preferred":[
        "Ashoknagar Kalyangarh"
    ],
    "name:msa_x_preferred":[
        "Ashoknagar Kalyangarh"
    ],
    "name:new_x_preferred":[
        "\u0905\u0936\u094b\u0915\u0928\u0917\u0930 \u0915\u0932\u094d\u092f\u093e\u0923\u0917\u0922"
    ],
    "name:por_x_preferred":[
        "Ashoknagar Kalyangarh"
    ],
    "name:spa_x_preferred":[
        "Ashoknagar Kalyangarh"
    ],
    "name:swe_x_preferred":[
        "Ashoknagar Kalyangarh"
    ],
    "name:vie_x_preferred":[
        "Ashoknagar Kalyangarh"
    ],
    "name:zho_x_preferred":[
        "\u963f\u65af\u970d\u514b\u7eb3\u52a0\u5c14\u5361\u5c14\u82f1\u683c\u963f\u5c14"
    ],
    "qs:name":"Ashoknagar Kalyangarh",
    "qs:name_adm0":"India",
    "qs:name_adm1":"West Bengal",
    "qs:photos_9k":1,
    "qs:photos_9r":1,
    "qs:photos_all":4,
    "qs:photos_sr":0,
    "qs:placetype":"Town",
    "qs:pop_sr":"9",
    "wof:name":"Ashoknagar Kalyangarh",
    "wof:placetype":"locality",
    "wof:population":111475
},
  "geometry": {"coordinates":[88.63701,22.86416],"type":"Point"}
}