{
  "type": "Feature",
  "properties": {
    "gn:admin1_code":"39",
    "gn:asciiname":"Lodaru Dogri",
    "gn:country_code":"IN",
    "gn:dem":1372,
    "gn:feature_class":"P",
    "gn:feature_code":"PPL",
    "gn:name":"Lod\u0101ru Dogri",
    "gn:population":0,
    "gn:timezone":"Asia/Kolkata",
    "iso:country":"IN",
    "wof:name":"Lodaru Dogri",
    "wof:placetype":"locality"
},
  "geometry": {"coordinates":[77.81816999999999,30.98977],"type":"Point"}
}