{
  "type": "Feature",
  "properties": {
    "gn:admin1_code":"19.0",
    "gn:admin2_code":"567.0",
    "gn:asciiname":"Devaratimmalapuram",
    "gn:country_code":"IN",
    "gn:dem":641,
    "gn:feature_class":"P",
    "gn:feature_code":"PPL",
    "gn:name":"Devaratimmal\u0101puram",
    "gn:population":0,
    "gn:timezone":"Asia/Kolkata",
    "iso:country":"IN",
    "wof:name":"Devaratimmalapuram",
    "wof:placetype":"locality"
},
  "geometry": {"coordinates":[76.00009,14.77655],"type":"Point"}
}