{
  "type": "Feature",
  "properties": {
    "iso:country":"IN",
    "ks:ks_name":"Neelamal",
    "ks:ks_pop":650,
    "ks:ks_type":"HABITATION",
    "name:eng_x_preferred":[
        "Neelamal"
    ],
    "wof:name":"Neelamal",
    "wof:placetype":"locality",
    "wof:population":650
},
  "geometry": {"coordinates":[76.93791,8.981261],"type":"Point"}
}