{
  "type": "Feature",
  "properties": {
    "iso:country":"IN",
    "ks:ks_name":"Gawala",
    "ks:ks_pop":441,
    "ks:ks_type":"HABITATION",
    "name:eng_x_preferred":[
        "Gawala"
    ],
    "wof:name":"Gawala",
    "wof:placetype":"locality",
    "wof:population":441
},
  "geometry": {"coordinates":[75.59619600000001,22.224951],"type":"Point"}
}