{
  "type": "Feature",
  "properties": {
    "iso:country":"IN",
    "ks:ks_name":"Beri Talli",
    "ks:ks_pop":240,
    "ks:ks_type":"VILLAGE",
    "name:eng_x_preferred":[
        "Beri Talli"
    ],
    "wof:name":"Beri Talli",
    "wof:placetype":"locality",
    "wof:population":240
},
  "geometry": {"coordinates":[79.246959,30.132212],"type":"Point"}
}