{
  "type": "Feature",
  "properties": {
    "gn:admin1_code":"35",
    "gn:admin2_code":"459.0",
    "gn:asciiname":"Silwara Khurd",
    "gn:country_code":"IN",
    "gn:dem":423,
    "gn:feature_class":"P",
    "gn:feature_code":"PPL",
    "gn:name":"Silw\u0101ra Khurd",
    "gn:population":0,
    "gn:timezone":"Asia/Kolkata",
    "iso:country":"IN",
    "ks:ks_alt_nam":"Silw\u0101ra Khurd",
    "ks:ks_name":"Silwara Khurd",
    "ks:ks_pop":256,
    "ks:ks_type":"VILLAGE",
    "name:eng_x_preferred":[
        "Silwara Khurd"
    ],
    "name:eng_x_variant":[
        "Silw\u0101ra Khurd"
    ],
    "wof:name":"Silwara Khurd",
    "wof:placetype":"locality",
    "wof:population":256
},
  "geometry": {"coordinates":[78.036574,24.558361],"type":"Point"}
}