{
  "type": "Feature",
  "properties": {
    "iso:country":"IN",
    "ks:ks_alt_nam":"Lakhtokia NC",
    "ks:ks_name":"Lakhtokia Nc",
    "ks:ks_pop":418,
    "ks:ks_type":"HABITATION",
    "name:eng_x_preferred":[
        "Lakhtokia Nc"
    ],
    "wof:name":"Lakhtokia Nc",
    "wof:placetype":"locality",
    "wof:population":418
},
  "geometry": {"coordinates":[94.470456,27.352032],"type":"Point"}
}