{
  "type": "Feature",
  "properties": {
    "gn:admin1_code":"36",
    "gn:admin2_code":"154.0",
    "gn:asciiname":"Allawalpur",
    "gn:country_code":"IN",
    "gn:dem":119,
    "gn:feature_class":"P",
    "gn:feature_code":"PPL",
    "gn:name":"All\u0101walpur",
    "gn:population":0,
    "gn:timezone":"Asia/Kolkata",
    "iso:country":"IN",
    "ks:ks_alt_nam":"All\u0101walpur",
    "ks:ks_alt_nam_2":"Allawalpur",
    "ks:ks_name":"Alawalpur",
    "ks:ks_pop":0,
    "ks:ks_type":"VILLAGE",
    "name:eng_x_preferred":[
        "Alawalpur"
    ],
    "name:eng_x_variant":[
        "Allawalpur",
        "All\u0101walpur"
    ],
    "wof:name":"Alawalpur",
    "wof:placetype":"locality",
    "wof:population":0
},
  "geometry": {"coordinates":[81.149714,27.432097],"type":"Point"}
}