{
  "type": "Feature",
  "properties": {
    "iso:country":"IN",
    "ks:ks_name":"Kolu Khedi",
    "ks:ks_pop":1263,
    "ks:ks_type":"VILLAGE",
    "name:eng_x_preferred":[
        "Kolu Khedi"
    ],
    "wof:name":"Kolu Khedi",
    "wof:placetype":"locality",
    "wof:population":1263
},
  "geometry": {"coordinates":[77.281986,23.249387],"type":"Point"}
}