{
  "type": "Feature",
  "properties": {
    "iso:country":"IN",
    "ks:ks_name":"Turli Gangasoda",
    "ks:ks_pop":37,
    "ks:ks_type":"HABITATION",
    "name:eng_x_preferred":[
        "Turli Gangasoda"
    ],
    "wof:name":"Turli Gangasoda",
    "wof:placetype":"locality",
    "wof:population":37
},
  "geometry": {"coordinates":[83.07353999999999,18.811129],"type":"Point"}
}