{
  "type": "Feature",
  "properties": {
    "gn:admin1_code":"11",
    "gn:admin2_code":"23.0",
    "gn:asciiname":"Charauri",
    "gn:country_code":"IN",
    "gn:dem":3217,
    "gn:feature_class":"P",
    "gn:feature_code":"PPL",
    "gn:name":"Charauri",
    "gn:population":0,
    "gn:timezone":"Asia/Kolkata",
    "iso:country":"IN",
    "wof:name":"Charauri",
    "wof:placetype":"locality"
},
  "geometry": {"coordinates":[76.22396999999999,32.68479],"type":"Point"}
}