{
  "type": "Feature",
  "properties": {
    "iso:country":"IN",
    "ks:ks_name":"Sanga Ki Bari",
    "ks:ks_pop":110,
    "ks:ks_type":"VILLAGE",
    "name:eng_x_preferred":[
        "Sanga Ki Bari"
    ],
    "wof:name":"Sanga Ki Bari",
    "wof:placetype":"locality",
    "wof:population":110
},
  "geometry": {"coordinates":[75.306211,24.868728],"type":"Point"}
}