{
  "type": "Feature",
  "properties": {
    "iso:country":"IN",
    "ks:ks_name":"Sirsa Khap",
    "ks:ks_pop":3170,
    "ks:ks_type":"VILLAGE",
    "ks:ks_uagg_main":0,
    "name:eng_x_preferred":[
        "Sirsa Khap"
    ],
    "wof:name":"Sirsa Khap",
    "wof:placetype":"neighbourhood",
    "wof:population":3170
},
  "geometry": {"coordinates":[85.005295,26.598593],"type":"Point"}
}