{
  "type": "Feature",
  "properties": {
    "iso:country":"IN",
    "ks:ks_name":"Dudiyo Ki Dhani",
    "ks:ks_pop":100,
    "ks:ks_type":"VILLAGE",
    "name:eng_x_preferred":[
        "Dudiyo Ki Dhani"
    ],
    "wof:name":"Dudiyo Ki Dhani",
    "wof:placetype":"locality",
    "wof:population":100
},
  "geometry": {"coordinates":[71.624194,25.667978],"type":"Point"}
}