{
  "type": "Feature",
  "properties": {
    "iso:country":"IN",
    "ks:ks_name":"Takar",
    "ks:ks_pop":439,
    "ks:ks_type":"VILLAGE",
    "name:eng_x_preferred":[
        "Takar"
    ],
    "wof:name":"Takar",
    "wof:placetype":"locality",
    "wof:population":439
},
  "geometry": {"coordinates":[82.71313000000001,22.996562],"type":"Point"}
}