{
  "type": "Feature",
  "properties": {
    "iso:country":"IN",
    "ks:ks_name":"Buruguda",
    "ks:ks_pop":252,
    "ks:ks_type":"HABITATION",
    "name:eng_x_preferred":[
        "Buruguda"
    ],
    "wof:name":"Buruguda",
    "wof:placetype":"locality",
    "wof:population":252
},
  "geometry": {"coordinates":[83.880167,19.577008],"type":"Point"}
}