{
  "type": "Feature",
  "properties": {
    "iso:country":"IN",
    "ks:ks_name":"Pujariguda 2",
    "ks:ks_pop":42,
    "ks:ks_type":"HABITATION",
    "name:eng_x_preferred":[
        "Pujariguda 2"
    ],
    "wof:name":"Pujariguda 2",
    "wof:placetype":"locality",
    "wof:population":42
},
  "geometry": {"coordinates":[82.206762,18.384549],"type":"Point"}
}