{
  "type": "Feature",
  "properties": {
    "iso:country":"IN",
    "ks:ks_alt_nam":"Puttaiahna palya",
    "ks:ks_name":"Puttaiahna Palya",
    "ks:ks_pop":78,
    "ks:ks_type":"HABITATION",
    "name:eng_x_preferred":[
        "Puttaiahna Palya"
    ],
    "wof:name":"Puttaiahna Palya",
    "wof:placetype":"locality",
    "wof:population":78
},
  "geometry": {"coordinates":[77.378449,12.895493],"type":"Point"}
}