{
  "type": "Feature",
  "properties": {
    "iso:country":"IN",
    "ks:ks_name":"Mohazari Patch",
    "ks:ks_pop":215,
    "ks:ks_type":"VILLAGE",
    "ks:ks_uagg_main":0,
    "name:eng_x_preferred":[
        "Mohazari Patch"
    ],
    "wof:name":"Mohazari Patch",
    "wof:placetype":"neighbourhood",
    "wof:population":215
},
  "geometry": {"coordinates":[79.985404,20.283063],"type":"Point"}
}