{
  "type": "Feature",
  "properties": {
    "gn:admin1_code":"35.0",
    "gn:admin2_code":"454.0",
    "gn:asciiname":"Sondhar",
    "gn:country_code":"IN",
    "gn:dem":553,
    "gn:feature_class":"P",
    "gn:feature_code":"PPL",
    "gn:name":"Sondhar",
    "gn:population":0,
    "gn:timezone":"Asia/Kolkata",
    "iso:country":"IN",
    "ks:ks_name":"Sondhar",
    "ks:ks_type":"VILLAGE",
    "name:eng_x_preferred":[
        "Sondhar"
    ],
    "wof:name":"Sondhar",
    "wof:placetype":"locality"
},
  "geometry": {"coordinates":[80.538708,22.365988],"type":"Point"}
}