{
  "type": "Feature",
  "properties": {
    "iso:country":"IN",
    "ks:ks_name":"Ganga Cheri",
    "ks:ks_pop":2008,
    "ks:ks_type":"VILLAGE",
    "name:eng_x_preferred":[
        "Ganga Cheri"
    ],
    "wof:name":"Ganga Cheri",
    "wof:placetype":"locality",
    "wof:population":2008
},
  "geometry": {"coordinates":[88.67591299999999,22.405984],"type":"Point"}
}