{
  "type": "Feature",
  "properties": {
    "iso:country":"IN",
    "ks:ks_alt_nam":"KORGAI",
    "ks:ks_name":"Korgai",
    "ks:ks_pop":800,
    "ks:ks_type":"HABITATION",
    "name:eng_x_preferred":[
        "Korgai"
    ],
    "wof:name":"Korgai",
    "wof:placetype":"locality",
    "wof:population":800
},
  "geometry": {"coordinates":[83.83508999999999,24.452461],"type":"Point"}
}