{
  "type": "Feature",
  "properties": {
    "gn:admin1_code":"36",
    "gn:admin2_code":"134.0",
    "gn:asciiname":"Shekhpur Lala",
    "gn:country_code":"IN",
    "gn:dem":233,
    "gn:feature_class":"P",
    "gn:feature_code":"PPL",
    "gn:name":"Shekhpur L\u0101la",
    "gn:population":0,
    "gn:timezone":"Asia/Kolkata",
    "iso:country":"IN",
    "ks:ks_alt_nam":"Shekhpur L\u0101la",
    "ks:ks_name":"Shekhpur Lala",
    "ks:ks_type":"VILLAGE",
    "ks:ks_uagg_main":0,
    "name:eng_x_preferred":[
        "Shekhpur Lala"
    ],
    "name:eng_x_variant":[
        "Shekhpur L\u0101la"
    ],
    "wof:name":"Shekhpur Lala",
    "wof:placetype":"neighbourhood"
},
  "geometry": {"coordinates":[78.364053,29.236165],"type":"Point"}
}