{
  "type": "Feature",
  "properties": {
    "iso:country":"IN",
    "ks:ks_name":"Nimgaon Korhale",
    "ks:ks_pop":3392,
    "ks:ks_type":"VILLAGE",
    "ks:ks_uagg_main":0,
    "name:eng_x_preferred":[
        "Nimgaon Korhale"
    ],
    "wof:name":"Nimgaon Korhale",
    "wof:placetype":"neighbourhood",
    "wof:population":3392
},
  "geometry": {"coordinates":[74.467454,19.784591],"type":"Point"}
}