{
  "type": "Feature",
  "properties": {
    "iso:country":"IN",
    "ks:ks_alt_nam":"Aris muhalla",
    "ks:ks_name":"Aris Muhalla",
    "ks:ks_pop":800,
    "ks:ks_type":"HABITATION",
    "name:eng_x_preferred":[
        "Aris Muhalla"
    ],
    "wof:name":"Aris Muhalla",
    "wof:placetype":"locality",
    "wof:population":800
},
  "geometry": {"coordinates":[81.85384999999999,25.60872],"type":"Point"}
}