{
  "type": "Feature",
  "properties": {
    "iso:country":"IN",
    "ks:ks_name":"Dulapara",
    "ks:ks_pop":46,
    "ks:ks_type":"HABITATION",
    "name:eng_x_preferred":[
        "Dulapara"
    ],
    "wof:name":"Dulapara",
    "wof:placetype":"locality",
    "wof:population":46
},
  "geometry": {"coordinates":[81.67075,19.13686],"type":"Point"}
}