{
  "type": "Feature",
  "properties": {
    "iso:country":"IN",
    "ks:ks_name":"Kauguda",
    "ks:ks_pop":16,
    "ks:ks_type":"VILLAGE",
    "name:eng_x_preferred":[
        "Kauguda"
    ],
    "wof:name":"Kauguda",
    "wof:placetype":"locality",
    "wof:population":16
},
  "geometry": {"coordinates":[83.108441,19.200959],"type":"Point"}
}