{
  "type": "Feature",
  "properties": {
    "iso:country":"IN",
    "ks:ks_name":"Satnara Kothar",
    "ks:ks_pop":568,
    "ks:ks_type":"VILLAGE",
    "name:eng_x_preferred":[
        "Satnara Kothar"
    ],
    "wof:name":"Satnara Kothar",
    "wof:placetype":"locality",
    "wof:population":568
},
  "geometry": {"coordinates":[81.92404000000001,24.347457],"type":"Point"}
}