{
  "type": "Feature",
  "properties": {
    "iso:country":"IN",
    "ks:ks_name":"Aunti",
    "ks:ks_type":"VILLAGE",
    "name:eng_x_preferred":[
        "Aunti"
    ],
    "wof:name":"Aunti",
    "wof:placetype":"locality"
},
  "geometry": {"coordinates":[83.183894,26.143672],"type":"Point"}
}