{
  "type": "Feature",
  "properties": {
    "gn:admin1_code":"30",
    "gn:admin2_code":"246.0",
    "gn:asciiname":"Rupa",
    "gn:country_code":"IN",
    "gn:dem":1478,
    "gn:feature_class":"P",
    "gn:feature_code":"PPL",
    "gn:name":"Rupa",
    "gn:population":0,
    "gn:timezone":"Asia/Kolkata",
    "iso:country":"IN",
    "name:bos_x_preferred":[
        "Rupa"
    ],
    "name:ceb_x_preferred":[
        "Rupa"
    ],
    "name:fra_x_preferred":[
        "Rupa"
    ],
    "name:hun_x_preferred":[
        "Rupa"
    ],
    "name:nld_x_preferred":[
        "Rupa"
    ],
    "name:rus_x_preferred":[
        "\u0420\u0443\u043f\u0430"
    ],
    "name:swe_x_preferred":[
        "Rupa"
    ],
    "name:und_x_variant":[
        "Dukpen",
        "Rupa"
    ],
    "wof:name":"Rupa",
    "wof:placetype":"locality"
},
  "geometry": {"coordinates":[92.4008,27.20484],"type":"Point"}
}