{
  "type": "Feature",
  "properties": {
    "iso:country":"IN",
    "ks:ks_name":"Nakhi Ii",
    "ks:ks_pop":126,
    "ks:ks_type":"HABITATION",
    "name:eng_x_preferred":[
        "Nakhi Ii"
    ],
    "wof:name":"Nakhi Ii",
    "wof:placetype":"locality",
    "wof:population":126
},
  "geometry": {"coordinates":[81.838347,27.260269],"type":"Point"}
}