{
  "type": "Feature",
  "properties": {
    "gn:admin1_code":"2.0",
    "gn:admin2_code":"553.0",
    "gn:asciiname":"Govindapalle",
    "gn:country_code":"IN",
    "gn:dem":322,
    "gn:feature_class":"P",
    "gn:feature_code":"PPL",
    "gn:name":"Govindapalle",
    "gn:population":0,
    "gn:timezone":"Asia/Kolkata",
    "iso:country":"IN",
    "ks:ks_name":"Govindapalle",
    "ks:ks_pop":1258,
    "ks:ks_type":"VILLAGE",
    "name:eng_x_preferred":[
        "Govindapalle"
    ],
    "wof:name":"Govindapalle",
    "wof:placetype":"locality",
    "wof:population":1258
},
  "geometry": {"coordinates":[77.63558,14.754572],"type":"Point"}
}