{
  "type": "Feature",
  "properties": {
    "iso:country":"IN",
    "ks:ks_name":"Samya Thanda",
    "ks:ks_pop":142,
    "ks:ks_type":"HABITATION",
    "name:eng_x_preferred":[
        "Samya Thanda"
    ],
    "wof:name":"Samya Thanda",
    "wof:placetype":"locality",
    "wof:population":142
},
  "geometry": {"coordinates":[79.830679,17.450068],"type":"Point"}
}