{
  "type": "Feature",
  "properties": {
    "iso:country":"IN",
    "ks:ks_name":"Vaghsepa Nana",
    "ks:ks_pop":285,
    "ks:ks_type":"VILLAGE",
    "name:eng_x_preferred":[
        "Vaghsepa Nana"
    ],
    "wof:name":"Vaghsepa Nana",
    "wof:placetype":"locality",
    "wof:population":285
},
  "geometry": {"coordinates":[73.84591,21.282865],"type":"Point"}
}