{
  "type": "Feature",
  "properties": {
    "gn:admin1_code":"12.0",
    "gn:asciiname":"Tunra da Kalia",
    "gn:country_code":"IN",
    "gn:dem":676,
    "gn:feature_class":"P",
    "gn:feature_code":"PPL",
    "gn:name":"Tunra da Kalia",
    "gn:population":0,
    "gn:timezone":"Asia/Kolkata",
    "iso:country":"IN",
    "name:und_x_variant":[
        "Tunia da Kalla"
    ],
    "wof:name":"Tunra da Kalia",
    "wof:placetype":"locality"
},
  "geometry": {"coordinates":[74.1953,33.09139],"type":"Point"}
}