{
  "type": "Feature",
  "properties": {
    "iso:country":"IN",
    "ks:ks_name":"Morepada",
    "ks:ks_pop":116,
    "ks:ks_type":"HABITATION",
    "name:eng_x_preferred":[
        "Morepada"
    ],
    "wof:name":"Morepada",
    "wof:placetype":"locality",
    "wof:population":116
},
  "geometry": {"coordinates":[73.418407,19.342573],"type":"Point"}
}