{
  "type": "Feature",
  "properties": {
    "gn:admin1_code":"17.0",
    "gn:admin2_code":"279",
    "gn:asciiname":"Humine",
    "gn:country_code":"IN",
    "gn:dem":269,
    "gn:feature_class":"P",
    "gn:feature_code":"PPL",
    "gn:name":"Humine",
    "gn:population":0,
    "gn:timezone":"Asia/Kolkata",
    "iso:country":"IN",
    "wof:name":"Humine",
    "wof:placetype":"locality"
},
  "geometry": {"coordinates":[94.56667,24.71667],"type":"Point"}
}