{
  "type": "Feature",
  "properties": {
    "iso:country":"IN",
    "ks:ks_name":"Kayyalipadam Mundappalli",
    "ks:ks_pop":533,
    "ks:ks_type":"HABITATION",
    "name:eng_x_preferred":[
        "Kayyalipadam Mundappalli"
    ],
    "wof:name":"Kayyalipadam Mundappalli",
    "wof:placetype":"locality",
    "wof:population":533
},
  "geometry": {"coordinates":[76.232432,10.590738],"type":"Point"}
}