{
  "type": "Feature",
  "properties": {
    "iso:country":"IN",
    "ks:ks_name":"Tola Rajla Khurd",
    "ks:ks_pop":285,
    "ks:ks_type":"VILLAGE",
    "name:eng_x_preferred":[
        "Tola Rajla Khurd"
    ],
    "wof:name":"Tola Rajla Khurd",
    "wof:placetype":"locality",
    "wof:population":285
},
  "geometry": {"coordinates":[86.437584,24.754804],"type":"Point"}
}