{
  "type": "Feature",
  "properties": {
    "iso:country":"IN",
    "ks:ks_name":"Haregadde",
    "ks:ks_pop":611,
    "ks:ks_type":"HABITATION",
    "name:eng_x_preferred":[
        "Haregadde"
    ],
    "wof:name":"Haregadde",
    "wof:placetype":"locality",
    "wof:population":611
},
  "geometry": {"coordinates":[75.1545,13.742803],"type":"Point"}
}