{
  "type": "Feature",
  "properties": {
    "iso:country":"IN",
    "ks:ks_name":"Chaure",
    "ks:ks_pop":425,
    "ks:ks_type":"HABITATION",
    "name:eng_x_preferred":[
        "Chaure"
    ],
    "wof:name":"Chaure",
    "wof:placetype":"locality",
    "wof:population":425
},
  "geometry": {"coordinates":[82.936763,25.609179],"type":"Point"}
}