{
  "type": "Feature",
  "properties": {
    "iso:country":"IN",
    "ks:ks_alt_nam":"June gavthan",
    "ks:ks_name":"June Gavthan",
    "ks:ks_pop":608,
    "ks:ks_type":"HABITATION",
    "ks:ks_uagg_main":0,
    "name:eng_x_preferred":[
        "June Gavthan"
    ],
    "wof:name":"June Gavthan",
    "wof:placetype":"neighbourhood",
    "wof:population":608
},
  "geometry": {"coordinates":[74.056439,17.339949],"type":"Point"}
}