{
  "type": "Feature",
  "properties": {
    "iso:country":"IN",
    "ks:ks_name":"Jamda",
    "ks:ks_pop":157,
    "ks:ks_type":"VILLAGE",
    "ks:ks_uagg_main":0,
    "name:eng_x_preferred":[
        "Jamda"
    ],
    "wof:name":"Jamda",
    "wof:placetype":"neighbourhood",
    "wof:population":157
},
  "geometry": {"coordinates":[86.65176,22.016661],"type":"Point"}
}