{
  "type": "Feature",
  "properties": {
    "iso:country":"IN",
    "ks:ks_name":"Vanmanush Tola",
    "ks:ks_pop":254,
    "ks:ks_type":"HABITATION",
    "ks:ks_uagg_main":0,
    "name:eng_x_preferred":[
        "Vanmanush Tola"
    ],
    "wof:name":"Vanmanush Tola",
    "wof:placetype":"neighbourhood",
    "wof:population":254
},
  "geometry": {"coordinates":[81.858144,26.069509],"type":"Point"}
}