{
  "type": "Feature",
  "properties": {
    "iso:country":"IN",
    "name:cat_x_preferred":[
        "Luing"
    ],
    "name:ceb_x_preferred":[
        "Luing"
    ],
    "name:deu_x_preferred":[
        "Luing"
    ],
    "name:ell_x_preferred":[
        "\u039b\u03bf\u03cd\u03b9\u03bd\u03b3\u03ba"
    ],
    "name:fra_x_preferred":[
        "Luing"
    ],
    "name:gla_x_preferred":[
        "Luinn"
    ],
    "name:gle_x_preferred":[
        "Luinn"
    ],
    "name:ita_x_preferred":[
        "Luing"
    ],
    "name:swe_x_preferred":[
        "Luing"
    ],
    "name:zho_x_preferred":[
        "\u6797\u5cf6"
    ],
    "qs:name":"Luing",
    "qs:name_adm0":"India",
    "qs:name_adm1":"Sikkim",
    "qs:photos":69,
    "qs:photos_1k":14,
    "qs:photos_9k":1,
    "qs:photos_9r":2,
    "qs:photos_all":69,
    "qs:photos_sr":2,
    "qs:placetype":"Town",
    "qs:pop_sr":"0",
    "wd:wordcount":580,
    "wof:name":"Luing",
    "wof:placetype":"neighbourhood"
},
  "geometry": {"coordinates":[88.612289,27.338682],"type":"Point"}
}