{
  "type": "Feature",
  "properties": {
    "gn:admin1_code":"23",
    "gn:admin2_code":"48.0",
    "gn:asciiname":"Marori",
    "gn:country_code":"IN",
    "gn:dem":244,
    "gn:feature_class":"P",
    "gn:feature_code":"PPL",
    "gn:name":"Marori",
    "gn:population":0,
    "gn:timezone":"Asia/Kolkata",
    "iso:country":"IN",
    "ks:ks_alt_nam":"Marori Distributary",
    "ks:ks_name":"Marori",
    "ks:ks_pop":2793,
    "ks:ks_type":"VILLAGE",
    "name:eng_x_preferred":[
        "Marori"
    ],
    "name:eng_x_variant":[
        "Marori Distributary"
    ],
    "wof:name":"Marori",
    "wof:placetype":"locality",
    "wof:population":2793
},
  "geometry": {"coordinates":[76.229263,30.077121],"type":"Point"}
}