{
  "type": "Feature",
  "properties": {
    "iso:country":"IN",
    "ks:ks_alt_nam":"ISLAMPUR SAUTH",
    "ks:ks_name":"Islampur Sauth",
    "ks:ks_pop":406,
    "ks:ks_type":"HABITATION",
    "name:eng_x_preferred":[
        "Islampur Sauth"
    ],
    "wof:name":"Islampur Sauth",
    "wof:placetype":"locality",
    "wof:population":406
},
  "geometry": {"coordinates":[87.375522,25.833243],"type":"Point"}
}