{
  "type": "Feature",
  "properties": {
    "iso:country":"IN",
    "ks:ks_name":"Dumeipur",
    "ks:ks_pop":520,
    "ks:ks_type":"VILLAGE",
    "ks:ks_uagg_main":0,
    "name:eng_x_preferred":[
        "Dumeipur"
    ],
    "wof:name":"Dumeipur",
    "wof:placetype":"locality",
    "wof:population":520
},
  "geometry": {"coordinates":[87.434628,21.644501],"type":"Point"}
}