{
  "type": "Feature",
  "properties": {
    "gn:admin1_code":"12.0",
    "gn:admin2_code":"006",
    "gn:asciiname":"Nao Girar",
    "gn:country_code":"IN",
    "gn:dem":877,
    "gn:feature_class":"P",
    "gn:feature_code":"PPL",
    "gn:name":"Nao Gir\u0101r",
    "gn:population":0,
    "gn:timezone":"Asia/Kolkata",
    "iso:country":"IN",
    "name:und_x_variant":[
        "Nao Gir\u0101r",
        "N\u0101o Gir\u0101r"
    ],
    "wof:name":"Nao Girar",
    "wof:placetype":"locality"
},
  "geometry": {"coordinates":[74.1977,33.26331],"type":"Point"}
}