{
  "type": "Feature",
  "properties": {
    "gn:admin1_code":"16",
    "gn:admin2_code":"510.0",
    "gn:asciiname":"Sunna",
    "gn:country_code":"IN",
    "gn:dem":241,
    "gn:feature_class":"P",
    "gn:feature_code":"PPL",
    "gn:name":"Sunna",
    "gn:population":0,
    "gn:timezone":"Asia/Kolkata",
    "iso:country":"IN",
    "name:als_x_preferred":[
        "Sunna"
    ],
    "name:ceb_x_preferred":[
        "Sunna"
    ],
    "name:deu_x_preferred":[
        "Sunna"
    ],
    "name:nld_x_preferred":[
        "Sunna"
    ],
    "name:ron_x_preferred":[
        "Sunna"
    ],
    "name:slk_x_preferred":[
        "Sunna"
    ],
    "name:spa_x_preferred":[
        "Sunna"
    ],
    "name:swe_x_preferred":[
        "Sunna"
    ],
    "wof:name":"Sunna",
    "wof:placetype":"locality"
},
  "geometry": {"coordinates":[78.53516999999999,19.92178],"type":"Point"}
}