{
  "type": "Feature",
  "properties": {
    "iso:country":"IN",
    "ks:ks_name":"Amrutguda",
    "ks:ks_pop":151,
    "ks:ks_type":"HABITATION",
    "name:eng_x_preferred":[
        "Amrutguda"
    ],
    "wof:name":"Amrutguda",
    "wof:placetype":"locality",
    "wof:population":151
},
  "geometry": {"coordinates":[79.515552,19.529277],"type":"Point"}
}