{
  "type": "Feature",
  "properties": {
    "iso:country":"IN",
    "ks:ks_name":"Nadupatti",
    "ks:ks_pop":275,
    "ks:ks_type":"HABITATION",
    "name:eng_x_preferred":[
        "Nadupatti"
    ],
    "wof:name":"Nadupatti",
    "wof:placetype":"locality",
    "wof:population":275
},
  "geometry": {"coordinates":[77.835673,9.899548],"type":"Point"}
}