{
  "type": "Feature",
  "properties": {
    "gn:admin1_code":"35.0",
    "gn:admin2_code":"446.0",
    "gn:asciiname":"Arka",
    "gn:country_code":"IN",
    "gn:dem":320,
    "gn:feature_class":"P",
    "gn:feature_code":"PPL",
    "gn:name":"Arka",
    "gn:population":0,
    "gn:timezone":"Asia/Kolkata",
    "iso:country":"IN",
    "name:ceb_x_preferred":[
        "Arka"
    ],
    "name:deu_x_preferred":[
        "Arka"
    ],
    "name:nld_x_preferred":[
        "Arka"
    ],
    "name:pol_x_preferred":[
        "Arka"
    ],
    "wof:name":"Arka",
    "wof:placetype":"locality"
},
  "geometry": {"coordinates":[78.03475999999998,22.87273],"type":"Point"}
}