{
  "type": "Feature",
  "properties": {
    "iso:country":"IN",
    "ks:ks_name":"Devalewadi",
    "ks:ks_pop":172,
    "ks:ks_type":"HABITATION",
    "name:eng_x_preferred":[
        "Devalewadi"
    ],
    "wof:name":"Devalewadi",
    "wof:placetype":"locality",
    "wof:population":172
},
  "geometry": {"coordinates":[73.56277799999999,17.123333],"type":"Point"}
}