{
  "type": "Feature",
  "properties": {
    "gn:admin1_code":"34",
    "gn:admin2_code":"233.0",
    "gn:asciiname":"Basantpur",
    "gn:country_code":"IN",
    "gn:dem":78,
    "gn:feature_class":"P",
    "gn:feature_code":"PPL",
    "gn:name":"Basantpur",
    "gn:population":0,
    "gn:timezone":"Asia/Kolkata",
    "iso:country":"IN",
    "name:pol_x_preferred":[
        "Basantpur"
    ],
    "wof:name":"Basantpur",
    "wof:placetype":"locality"
},
  "geometry": {"coordinates":[83.64775,25.18363],"type":"Point"}
}