{
  "type": "Feature",
  "properties": {
    "gn:admin1_code":"36",
    "gn:admin2_code":"195.0",
    "gn:asciiname":"Shekhanpur",
    "gn:country_code":"IN",
    "gn:dem":72,
    "gn:feature_class":"P",
    "gn:feature_code":"PPL",
    "gn:name":"Shekhanpur",
    "gn:population":0,
    "gn:timezone":"Asia/Kolkata",
    "iso:country":"IN",
    "ks:ks_name":"Shekhanpur",
    "ks:ks_pop":1340,
    "ks:ks_type":"VILLAGE",
    "ks:ks_uagg_main":0,
    "name:eng_x_preferred":[
        "Shekhanpur"
    ],
    "wof:name":"Shekhanpur",
    "wof:placetype":"neighbourhood",
    "wof:population":1340
},
  "geometry": {"coordinates":[83.66501599999999,25.765476],"type":"Point"}
}