{
  "type": "Feature",
  "properties": {
    "iso:country":"IN",
    "ks:ks_name":"Daradapari",
    "ks:ks_pop":1226,
    "ks:ks_type":"VILLAGE",
    "name:eng_x_preferred":[
        "Daradapari"
    ],
    "wof:name":"Daradapari",
    "wof:placetype":"locality",
    "wof:population":1226
},
  "geometry": {"coordinates":[86.019408,20.385609],"type":"Point"}
}