{
  "type": "Feature",
  "properties": {
    "iso:country":"IN",
    "ks:ks_name":"Chorchita Dakshin",
    "ks:ks_pop":1868,
    "ks:ks_type":"HABITATION",
    "ks:ks_uagg_main":0,
    "name:eng_x_preferred":[
        "Chorchita Dakshin"
    ],
    "wof:name":"Chorchita Dakshin",
    "wof:placetype":"neighbourhood",
    "wof:population":1868
},
  "geometry": {"coordinates":[86.855695,22.213683],"type":"Point"}
}