{
  "type": "Feature",
  "properties": {
    "iso:country":"IN",
    "ks:ks_name":"Kumaitha Arazi",
    "ks:ks_pop":0,
    "ks:ks_type":"VILLAGE",
    "name:eng_x_preferred":[
        "Kumaitha Arazi"
    ],
    "wof:name":"Kumaitha Arazi",
    "wof:placetype":"locality",
    "wof:population":0
},
  "geometry": {"coordinates":[86.747227,25.171682],"type":"Point"}
}