{
  "type": "Feature",
  "properties": {
    "gn:admin1_code":"25.0",
    "gn:admin2_code":"608.0",
    "gn:asciiname":"Karikattuvellateruvu",
    "gn:country_code":"IN",
    "gn:dem":266,
    "gn:feature_class":"P",
    "gn:feature_code":"PPL",
    "gn:name":"K\u0101rik\u0101ttuvell\u0101teruvu",
    "gn:population":0,
    "gn:timezone":"Asia/Kolkata",
    "iso:country":"IN",
    "wof:name":"Karikattuvellateruvu",
    "wof:placetype":"locality"
},
  "geometry": {"coordinates":[77.95263,11.6962],"type":"Point"}
}