{
  "type": "Feature",
  "properties": {
    "gn:admin1_code":"35",
    "gn:admin2_code":"425.0",
    "gn:asciiname":"Mankari",
    "gn:country_code":"IN",
    "gn:dem":328,
    "gn:feature_class":"P",
    "gn:feature_code":"PPL",
    "gn:name":"Mank\u0101ri",
    "gn:population":0,
    "gn:timezone":"Asia/Kolkata",
    "iso:country":"IN",
    "name:nor_x_preferred":[
        "Mankari"
    ],
    "wof:name":"Mankari",
    "wof:placetype":"locality"
},
  "geometry": {"coordinates":[79.3746,24.59697],"type":"Point"}
}