{
  "type": "Feature",
  "properties": {
    "iso:country":"IN",
    "ks:ks_name":"Manmodi",
    "ks:ks_pop":293,
    "ks:ks_type":"HABITATION",
    "name:eng_x_preferred":[
        "Manmodi"
    ],
    "wof:name":"Manmodi",
    "wof:placetype":"locality",
    "wof:population":293
},
  "geometry": {"coordinates":[73.88500500000001,19.637611],"type":"Point"}
}