{
  "type": "Feature",
  "properties": {
    "gn:admin1_code":"35",
    "gn:admin2_code":"420.0",
    "gn:asciiname":"Dighi",
    "gn:country_code":"IN",
    "gn:dem":156,
    "gn:feature_class":"P",
    "gn:feature_code":"PPL",
    "gn:name":"Dighi",
    "gn:population":0,
    "gn:timezone":"Asia/Kolkata",
    "iso:country":"IN",
    "ks:ks_name":"Dighi",
    "ks:ks_type":"VILLAGE",
    "name:eng_x_preferred":[
        "Dighi"
    ],
    "wof:name":"Dighi",
    "wof:placetype":"locality"
},
  "geometry": {"coordinates":[78.67614500000001,26.514102],"type":"Point"}
}