{
  "type": "Feature",
  "properties": {
    "gn:admin1_code":"7.0",
    "gn:admin2_code":"93.0",
    "gn:asciiname":"Lahri Colony",
    "gn:country_code":"IN",
    "gn:dem":210,
    "gn:feature_class":"P",
    "gn:feature_code":"PPL",
    "gn:name":"Lahri Colony",
    "gn:population":0,
    "gn:timezone":"Asia/Kolkata",
    "iso:country":"IN",
    "wof:name":"Lahri Colony",
    "wof:placetype":"locality"
},
  "geometry": {"coordinates":[77.29579,28.65691],"type":"Point"}
}