{
  "type": "Feature",
  "properties": {
    "iso:country":"IN",
    "ks:ks_name":"Jyotipur No 1",
    "ks:ks_pop":337,
    "ks:ks_type":"HABITATION",
    "ks:ks_uagg_main":0,
    "name:eng_x_preferred":[
        "Jyotipur No 1"
    ],
    "wof:name":"Jyotipur No 1",
    "wof:placetype":"neighbourhood",
    "wof:population":337
},
  "geometry": {"coordinates":[94.05825299999999,26.390468],"type":"Point"}
}