{
  "type": "Feature",
  "properties": {
    "gn:admin1_code":"24.0",
    "gn:admin2_code":"104.0",
    "gn:asciiname":"Roja",
    "gn:country_code":"IN",
    "gn:dem":298,
    "gn:feature_class":"P",
    "gn:feature_code":"PPL",
    "gn:name":"Roja",
    "gn:population":0,
    "gn:timezone":"Asia/Kolkata",
    "iso:country":"IN",
    "name:ben_x_preferred":[
        "\u09b0\u09cb\u099c\u09be"
    ],
    "name:fas_x_preferred":[
        "\u0631\u0648\u062c\u0627"
    ],
    "name:fra_x_preferred":[
        "Roja"
    ],
    "name:jpn_x_preferred":[
        "\u30ed\u30fc\u30b8\u30e3\u30fc"
    ],
    "name:kan_x_preferred":[
        "\u0cb0\u0ccb\u0c9c\u0cbe"
    ],
    "name:mal_x_preferred":[
        "\u0d31\u0d4b\u0d1c"
    ],
    "name:mar_x_preferred":[
        "\u0930\u094b\u091c\u093e"
    ],
    "name:pol_x_preferred":[
        "Roja"
    ],
    "name:sin_x_preferred":[
        "\u0dbb\u0ddd\u0da2\u0dcf"
    ],
    "name:spa_x_preferred":[
        "Roja"
    ],
    "name:tam_x_preferred":[
        "\u0bb0\u0bcb\u0b9c\u0bbe"
    ],
    "name:tgl_x_preferred":[
        "Roja"
    ],
    "wof:name":"Roja",
    "wof:placetype":"locality"
},
  "geometry": {"coordinates":[76.57394000000002,27.70129],"type":"Point"}
}