{
  "type": "Feature",
  "properties": {
    "iso:country":"IN",
    "ks:ks_name":"Gonawadi Fakeer",
    "ks:ks_pop":129,
    "ks:ks_type":"HABITATION",
    "name:eng_x_preferred":[
        "Gonawadi Fakeer"
    ],
    "wof:name":"Gonawadi Fakeer",
    "wof:placetype":"locality",
    "wof:population":129
},
  "geometry": {"coordinates":[78.88492599999999,21.915354],"type":"Point"}
}