{
  "type": "Feature",
  "properties": {
    "iso:country":"IN",
    "ks:ks_name":"Desurpalayam",
    "ks:ks_pop":1236,
    "ks:ks_type":"HABITATION",
    "name:eng_x_preferred":[
        "Desurpalayam"
    ],
    "wof:name":"Desurpalayam",
    "wof:placetype":"locality",
    "wof:population":1236
},
  "geometry": {"coordinates":[78.947901,12.178712],"type":"Point"}
}