{
  "type": "Feature",
  "properties": {
    "iso:country":"IN",
    "ks:ks_name":"Aksi",
    "ks:ks_pop":947,
    "ks:ks_type":"VILLAGE",
    "name:eng_x_preferred":[
        "Aksi"
    ],
    "wof:name":"Aksi",
    "wof:placetype":"locality",
    "wof:population":947
},
  "geometry": {"coordinates":[84.11620499999999,23.510727],"type":"Point"}
}