{
  "type": "Feature",
  "properties": {
    "iso:country":"IN",
    "ks:ks_name":"Nanhi Kewat Purwa",
    "ks:ks_pop":180,
    "ks:ks_type":"HABITATION",
    "name:eng_x_preferred":[
        "Nanhi Kewat Purwa"
    ],
    "wof:name":"Nanhi Kewat Purwa",
    "wof:placetype":"locality",
    "wof:population":180
},
  "geometry": {"coordinates":[81.083716,25.48315],"type":"Point"}
}