{
  "type": "Feature",
  "properties": {
    "iso:country":"IN",
    "ks:ks_name":"Monipara",
    "ks:ks_pop":728,
    "ks:ks_type":"HABITATION",
    "name:eng_x_preferred":[
        "Monipara"
    ],
    "wof:name":"Monipara",
    "wof:placetype":"locality",
    "wof:population":728
},
  "geometry": {"coordinates":[74.391706,23.289603],"type":"Point"}
}