{
  "type": "Feature",
  "properties": {
    "gn:country":"IN",
    "gn:fcode":"PPL",
    "gn:pop":29016,
    "iso:country":"IN",
    "name:bar_x_preferred":[
        "Sandur"
    ],
    "name:ben_x_preferred":[
        "\u09b8\u09be\u09a8\u09cd\u09a6\u09c1\u09b0"
    ],
    "name:bpy_x_preferred":[
        "\u09b8\u09be\u09a8\u09cd\u09a6\u09c1\u09b0"
    ],
    "name:cat_x_preferred":[
        "Sandur"
    ],
    "name:ceb_x_preferred":[
        "Sand\u016br"
    ],
    "name:deu_x_preferred":[
        "Sandur"
    ],
    "name:eng_x_preferred":[
        "Sanduru"
    ],
    "name:fra_x_preferred":[
        "Sandur"
    ],
    "name:guj_x_preferred":[
        "\u0ab8\u0abe\u0a82\u0aa6\u0ac1\u0ab0\u0ac1\u0a82"
    ],
    "name:hif_x_preferred":[
        "Sanduru"
    ],
    "name:ita_x_preferred":[
        "Sandur"
    ],
    "name:jpn_x_preferred":[
        "\u30b5\u30f3\u30c9\u30a5\u30eb"
    ],
    "name:kan_x_preferred":[
        "\u0cb8\u0c82\u0ca1\u0cc2\u0cb0\u0cc1"
    ],
    "name:kor_x_preferred":[
        "\uc0b0\ub450\ub974"
    ],
    "name:nan_x_preferred":[
        "Sandur"
    ],
    "name:nld_x_preferred":[
        "Sandur"
    ],
    "name:ori_x_preferred":[
        "\u0b38\u0b3e\u0b23\u0b4d\u0b21\u0b41\u0b30\u0b41"
    ],
    "name:por_x_preferred":[
        "Sanduru"
    ],
    "name:rus_x_preferred":[
        "\u0421\u0430\u043d\u0434\u0443\u0440\u0443"
    ],
    "name:spa_x_preferred":[
        "Sandur"
    ],
    "name:swe_x_preferred":[
        "Sandur"
    ],
    "name:tam_x_preferred":[
        "\u0b9a\u0ba8\u0bcd\u0ba4\u0bc1\u0bb0\u0bc1"
    ],
    "name:tel_x_preferred":[
        "\u0c38\u0c02\u0c21\u0c41\u0c30\u0c41"
    ],
    "name:urd_x_preferred":[
        "\u0633\u0627\u0646\u062f\u0648\u0631\u0648"
    ],
    "qs:name":"Sand\u016br",
    "qs:photos_9r":0,
    "qs:photos_sr":0,
    "qs:pop_sr":"7",
    "wd:wordcount":42,
    "wof:name":"Sand\u016br",
    "wof:placetype":"locality",
    "wof:population":29016
},
  "geometry": {"coordinates":[76.54692,15.08613],"type":"Point"}
}