{
  "type": "Feature",
  "properties": {
    "gn:admin1_code":"12.0",
    "gn:admin2_code":"008",
    "gn:asciiname":"Rangawar",
    "gn:country_code":"IN",
    "gn:dem":2404,
    "gn:feature_class":"P",
    "gn:feature_code":"PPL",
    "gn:name":"Rangaw\u0101r",
    "gn:population":0,
    "gn:timezone":"Asia/Kolkata",
    "iso:country":"IN",
    "wof:name":"Rangawar",
    "wof:placetype":"locality"
},
  "geometry": {"coordinates":[74.12834000000002,34.29678],"type":"Point"}
}