{
  "type": "Feature",
  "properties": {
    "iso:country":"IN",
    "ks:ks_name":"Dhundaguda",
    "ks:ks_pop":96,
    "ks:ks_type":"HABITATION",
    "name:eng_x_preferred":[
        "Dhundaguda"
    ],
    "wof:name":"Dhundaguda",
    "wof:placetype":"locality",
    "wof:population":96
},
  "geometry": {"coordinates":[82.597613,19.132441],"type":"Point"}
}