{
  "type": "Feature",
  "properties": {
    "gn:admin1_code":"13.0",
    "gn:admin2_code":"595.0",
    "gn:asciiname":"Kizhakkumbagam",
    "gn:country_code":"IN",
    "gn:dem":28,
    "gn:feature_class":"P",
    "gn:feature_code":"PPL",
    "gn:name":"Kizhakkumb\u0101gam",
    "gn:population":0,
    "gn:timezone":"Asia/Kolkata",
    "iso:country":"IN",
    "ks:ks_alt_nam":"Kizhakkumb\u0101gam",
    "ks:ks_alt_nam_2":"Kizhakkumbagam",
    "ks:ks_name":"Kizhakkumbhagom",
    "ks:ks_pop":10038,
    "ks:ks_type":"VILLAGE",
    "ks:ks_uagg_main":0,
    "name:eng_x_preferred":[
        "Kizhakkumbhagom"
    ],
    "name:eng_x_variant":[
        "Kizhakkumb\u0101gam",
        "Kizhakkumbagam"
    ],
    "wof:name":"Kizhakkumbhagom",
    "wof:placetype":"neighbourhood",
    "wof:population":10038
},
  "geometry": {"coordinates":[76.44465599999999,10.131513],"type":"Point"}
}