{
  "type": "Feature",
  "properties": {
    "iso:country":"IN",
    "ks:ks_name":"Shyamnagar",
    "ks:ks_pop":934,
    "ks:ks_type":"VILLAGE",
    "name:ben_x_preferred":[
        "\u09b6\u09cd\u09af\u09be\u09ae\u09a8\u0997\u09b0"
    ],
    "name:eng_x_preferred":[
        "Shyamnagar"
    ],
    "name:hin_x_preferred":[
        "\u0936\u094d\u092f\u093e\u092e\u0928\u0917\u0930"
    ],
    "wof:name":"Shyamnagar",
    "wof:placetype":"locality",
    "wof:population":934
},
  "geometry": {"coordinates":[88.43251600000001,23.425891],"type":"Point"}
}