{
  "type": "Feature",
  "properties": {
    "iso:country":"IN",
    "ks:ks_name":"Ismailpur",
    "ks:ks_pop":248,
    "ks:ks_type":"VILLAGE",
    "name:eng_x_preferred":[
        "Ismailpur"
    ],
    "wof:name":"Ismailpur",
    "wof:placetype":"locality",
    "wof:population":248
},
  "geometry": {"coordinates":[85.443594,25.549361],"type":"Point"}
}