{
  "type": "Feature",
  "properties": {
    "gn:admin1_code":"34.0",
    "gn:admin2_code":"229.0",
    "gn:asciiname":"Maulanagar",
    "gn:country_code":"IN",
    "gn:dem":62,
    "gn:feature_class":"P",
    "gn:feature_code":"PPL",
    "gn:name":"Maul\u0101nagar",
    "gn:population":0,
    "gn:timezone":"Asia/Kolkata",
    "iso:country":"IN",
    "wof:name":"Maulanagar",
    "wof:placetype":"neighbourhood"
},
  "geometry": {"coordinates":[85.47838,25.16789],"type":"Point"}
}