{
  "type": "Feature",
  "properties": {
    "iso:country":"IN",
    "ks:ks_alt_nam":"SANGAMNAGAR",
    "ks:ks_name":"Sangamnagar",
    "ks:ks_pop":442,
    "ks:ks_type":"HABITATION",
    "ks:ks_uagg_main":0,
    "name:eng_x_preferred":[
        "Sangamnagar"
    ],
    "wof:name":"Sangamnagar",
    "wof:placetype":"neighbourhood",
    "wof:population":442
},
  "geometry": {"coordinates":[74.251423,17.17789],"type":"Point"}
}