{
  "type": "Feature",
  "properties": {
    "gn:admin1_code":"16",
    "gn:admin2_code":"505.0",
    "gn:asciiname":"Khumari",
    "gn:country_code":"IN",
    "gn:dem":341,
    "gn:feature_class":"P",
    "gn:feature_code":"PPL",
    "gn:name":"Khum\u0101ri",
    "gn:population":0,
    "gn:timezone":"Asia/Kolkata",
    "iso:country":"IN",
    "wof:name":"Khumari",
    "wof:placetype":"locality"
},
  "geometry": {"coordinates":[79.29403000000001,21.4469],"type":"Point"}
}