{
  "type": "Feature",
  "properties": {
    "iso:country":"IN",
    "ks:ks_name":"Pipaliya Shah",
    "ks:ks_pop":181,
    "ks:ks_type":"VILLAGE",
    "ks:ks_uagg_main":0,
    "name:eng_x_preferred":[
        "Pipaliya Shah"
    ],
    "wof:name":"Pipaliya Shah",
    "wof:placetype":"neighbourhood",
    "wof:population":181
},
  "geometry": {"coordinates":[76.10636,23.580365],"type":"Point"}
}