{
  "type": "Feature",
  "properties": {
    "gn:admin1_code":"36",
    "gn:admin2_code":"199.0",
    "gn:asciiname":"Kothi Dhaukalsingh",
    "gn:country_code":"IN",
    "gn:dem":145,
    "gn:feature_class":"P",
    "gn:feature_code":"PPL",
    "gn:name":"Kothi Dhaukalsingh",
    "gn:population":0,
    "gn:timezone":"Asia/Kolkata",
    "iso:country":"IN",
    "wof:name":"Kothi Dhaukalsingh",
    "wof:placetype":"locality"
},
  "geometry": {"coordinates":[82.26738,24.92013],"type":"Point"}
}