{
  "type": "Feature",
  "properties": {
    "gn:admin1_code":"34.0",
    "gn:admin2_code":"224.0",
    "gn:asciiname":"Kadua",
    "gn:country_code":"IN",
    "gn:dem":38,
    "gn:feature_class":"P",
    "gn:feature_code":"PPL",
    "gn:name":"Kadua",
    "gn:population":0,
    "gn:timezone":"Asia/Kolkata",
    "iso:country":"IN",
    "name:ceb_x_preferred":[
        "Kadua"
    ],
    "name:deu_x_preferred":[
        "Kadua"
    ],
    "name:spa_x_preferred":[
        "Kadua"
    ],
    "name:swe_x_preferred":[
        "Kadua"
    ],
    "name:vie_x_preferred":[
        "Kadua"
    ],
    "name:war_x_preferred":[
        "Kadua"
    ],
    "wof:name":"Kadua",
    "wof:placetype":"neighbourhood"
},
  "geometry": {"coordinates":[87.07525,25.46646],"type":"Point"}
}