{
  "type": "Feature",
  "properties": {
    "gn:admin1_code":"36.0",
    "gn:admin2_code":"195.0",
    "gn:asciiname":"Mahui",
    "gn:country_code":"IN",
    "gn:dem":74,
    "gn:feature_class":"P",
    "gn:feature_code":"PPL",
    "gn:name":"Mahu\u012b",
    "gn:population":0,
    "gn:timezone":"Asia/Kolkata",
    "iso:country":"IN",
    "ks:ks_alt_nam":"Mahu\u012b",
    "ks:ks_name":"Mahui",
    "ks:ks_type":"VILLAGE",
    "ks:ks_uagg_main":0,
    "name:eng_x_preferred":[
        "Mahui"
    ],
    "name:eng_x_variant":[
        "Mahu\u012b"
    ],
    "wof:name":"Mahui",
    "wof:placetype":"neighbourhood"
},
  "geometry": {"coordinates":[83.695436,25.65707],"type":"Point"}
}