{
  "type": "Feature",
  "properties": {
    "iso:country":"IN",
    "ks:ks_alt_nam":"TELIVSTI IRRPPA",
    "ks:ks_name":"Telivsti Irrppa",
    "ks:ks_pop":119,
    "ks:ks_type":"HABITATION",
    "name:eng_x_preferred":[
        "Telivsti Irrppa"
    ],
    "wof:name":"Telivsti Irrppa",
    "wof:placetype":"locality",
    "wof:population":119
},
  "geometry": {"coordinates":[75.488248,17.22197],"type":"Point"}
}