{
  "type": "Feature",
  "properties": {
    "iso:country":"IN",
    "ks:ks_name":"Itaha Khas",
    "ks:ks_pop":4658,
    "ks:ks_type":"HABITATION",
    "name:eng_x_preferred":[
        "Itaha Khas"
    ],
    "wof:name":"Itaha Khas",
    "wof:placetype":"locality",
    "wof:population":4658
},
  "geometry": {"coordinates":[81.46447499999999,27.736683],"type":"Point"}
}