{
  "type": "Feature",
  "properties": {
    "gn:admin1_code":"35",
    "gn:admin2_code":"451.0",
    "gn:asciiname":"Singpur",
    "gn:country_code":"IN",
    "gn:dem":356,
    "gn:feature_class":"P",
    "gn:feature_code":"PPL",
    "gn:name":"Singpur",
    "gn:population":0,
    "gn:timezone":"Asia/Kolkata",
    "iso:country":"IN",
    "ks:ks_name":"Singpur",
    "ks:ks_pop":390,
    "ks:ks_type":"VILLAGE",
    "name:eng_x_preferred":[
        "Singpur"
    ],
    "wof:name":"Singpur",
    "wof:placetype":"locality",
    "wof:population":390
},
  "geometry": {"coordinates":[79.428039,23.172622],"type":"Point"}
}