{
  "type": "Feature",
  "properties": {
    "gn:admin1_code":"02",
    "gn:admin2_code":"550.0",
    "gn:asciiname":"Peddapariya",
    "gn:country_code":"IN",
    "gn:dem":41,
    "gn:feature_class":"P",
    "gn:feature_code":"PPL",
    "gn:name":"Peddapariya",
    "gn:population":0,
    "gn:timezone":"Asia/Kolkata",
    "iso:country":"IN",
    "name:und_x_variant":[
        "Pedapariya",
        "Peddapariya"
    ],
    "wof:name":"Peddapariya",
    "wof:placetype":"locality"
},
  "geometry": {"coordinates":[79.87291999999999,14.02963],"type":"Point"}
}