{
  "type": "Feature",
  "properties": {
    "iso:country":"IN",
    "ks:ks_alt_nam":"Pudhu nagar",
    "ks:ks_name":"Pudhu Nagar",
    "ks:ks_pop":239,
    "ks:ks_type":"HABITATION",
    "ks:ks_uagg_main":0,
    "name:eng_x_preferred":[
        "Pudhu Nagar"
    ],
    "wof:name":"Pudhu Nagar",
    "wof:placetype":"neighbourhood",
    "wof:population":239
},
  "geometry": {"coordinates":[79.49802699999999,12.116018],"type":"Point"}
}