{
  "type": "Feature",
  "properties": {
    "gn:admin1_code":"38",
    "gn:admin2_code":"365.0",
    "gn:asciiname":"Torpa",
    "gn:country_code":"IN",
    "gn:dem":522,
    "gn:feature_class":"P",
    "gn:feature_code":"PPL",
    "gn:name":"Torpa",
    "gn:population":0,
    "gn:timezone":"Asia/Kolkata",
    "iso:country":"IN",
    "wof:name":"Torpa",
    "wof:placetype":"locality"
},
  "geometry": {"coordinates":[85.08892,22.93605],"type":"Point"}
}