{
  "type": "Feature",
  "properties": {
    "gn:admin1_code":"34",
    "gn:admin2_code":"233.0",
    "gn:asciiname":"Barka Kalan",
    "gn:country_code":"IN",
    "gn:dem":317,
    "gn:feature_class":"P",
    "gn:feature_code":"PPL",
    "gn:name":"B\u0101rka Kal\u0101n",
    "gn:population":0,
    "gn:timezone":"Asia/Kolkata",
    "iso:country":"IN",
    "ks:ks_name":"Barwan Kalan",
    "ks:ks_pop":1148,
    "ks:ks_type":"VILLAGE",
    "name:eng_x_preferred":[
        "Barwan Kalan"
    ],
    "name:eng_x_variant":[
        "Barka Kalan"
    ],
    "wof:name":"Barwan Kalan",
    "wof:placetype":"locality",
    "wof:population":1148
},
  "geometry": {"coordinates":[83.66243299999999,24.89015],"type":"Point"}
}