{
  "type": "Feature",
  "properties": {
    "gn:admin1_code":"34.0",
    "gn:admin2_code":"221.0",
    "gn:asciiname":"Somnaha",
    "gn:country_code":"IN",
    "gn:dem":53,
    "gn:feature_class":"P",
    "gn:feature_code":"PPL",
    "gn:name":"Somn\u0101ha",
    "gn:population":0,
    "gn:timezone":"Asia/Kolkata",
    "iso:country":"IN",
    "ks:ks_alt_nam":"Somn\u0101ha",
    "ks:ks_name":"Somnaha",
    "ks:ks_pop":1621,
    "ks:ks_type":"VILLAGE",
    "name:eng_x_preferred":[
        "Somnaha"
    ],
    "name:eng_x_variant":[
        "Somn\u0101ha"
    ],
    "wof:name":"Somnaha",
    "wof:placetype":"locality",
    "wof:population":1621
},
  "geometry": {"coordinates":[85.697428,25.948965],"type":"Point"}
}