{
  "type": "Feature",
  "properties": {
    "iso:country":"IN",
    "ks:ks_name":"West Tola",
    "ks:ks_pop":426,
    "ks:ks_type":"HABITATION",
    "ks:ks_uagg_main":0,
    "name:eng_x_preferred":[
        "West Tola"
    ],
    "wof:name":"West Tola",
    "wof:placetype":"neighbourhood",
    "wof:population":426
},
  "geometry": {"coordinates":[85.960796,25.816101],"type":"Point"}
}