{
  "type": "Feature",
  "properties": {
    "iso:country":"IN",
    "ks:ks_name":"Silli Sera",
    "ks:ks_pop":286,
    "ks:ks_type":"HABITATION",
    "name:eng_x_preferred":[
        "Silli Sera"
    ],
    "wof:name":"Silli Sera",
    "wof:placetype":"locality",
    "wof:population":286
},
  "geometry": {"coordinates":[79.074322,30.453316],"type":"Point"}
}