{
  "type": "Feature",
  "properties": {
    "gn:admin1_code":"12",
    "gn:admin2_code":"20.0",
    "gn:asciiname":"Sabas",
    "gn:country_code":"IN",
    "gn:dem":1470,
    "gn:feature_class":"P",
    "gn:feature_code":"PPL",
    "gn:name":"Sab\u0101s",
    "gn:population":0,
    "gn:timezone":"Asia/Kolkata",
    "iso:country":"IN",
    "name:deu_x_preferred":[
        "Sabas"
    ],
    "name:fra_x_preferred":[
        "Sabas"
    ],
    "wof:name":"Sabas",
    "wof:placetype":"locality"
},
  "geometry": {"coordinates":[74.77209999999999,33.27673],"type":"Point"}
}