{
  "type": "Feature",
  "properties": {
    "iso:country":"IN",
    "ks:ks_name":"Manglapara",
    "ks:ks_pop":85,
    "ks:ks_type":"VILLAGE",
    "name:eng_x_preferred":[
        "Manglapara"
    ],
    "wof:name":"Manglapara",
    "wof:placetype":"locality",
    "wof:population":85
},
  "geometry": {"coordinates":[87.695351,24.550106],"type":"Point"}
}