{
  "type": "Feature",
  "properties": {
    "iso:country":"IN",
    "ks:ks_name":"Kattipparuthi",
    "ks:ks_pop":35795,
    "ks:ks_type":"VILLAGE",
    "ks:ks_uagg_main":1,
    "name:eng_x_preferred":[
        "Kattipparuthi"
    ],
    "wof:name":"Kattipparuthi",
    "wof:placetype":"neighbourhood",
    "wof:population":35795
},
  "geometry": {"coordinates":[76.05569,10.870724],"type":"Point"}
}