{
  "type": "Feature",
  "properties": {
    "iso:country":"IN",
    "ks:ks_alt_nam":"PUJARIHATTI WASTI",
    "ks:ks_name":"Pujarihatti Wasti",
    "ks:ks_pop":117,
    "ks:ks_type":"HABITATION",
    "name:eng_x_preferred":[
        "Pujarihatti Wasti"
    ],
    "wof:name":"Pujarihatti Wasti",
    "wof:placetype":"locality",
    "wof:population":117
},
  "geometry": {"coordinates":[75.45269500000001,17.191917],"type":"Point"}
}