{
  "type": "Feature",
  "properties": {
    "gn:admin1_code":"36",
    "gn:admin2_code":"157.0",
    "gn:asciiname":"Doria",
    "gn:country_code":"IN",
    "gn:dem":122,
    "gn:feature_class":"P",
    "gn:feature_code":"PPL",
    "gn:name":"Doria",
    "gn:population":0,
    "gn:timezone":"Asia/Kolkata",
    "iso:country":"IN",
    "name:ceb_x_preferred":[
        "Doria"
    ],
    "name:deu_x_preferred":[
        "Doria"
    ],
    "name:fra_x_preferred":[
        "Doria"
    ],
    "name:heb_x_preferred":[
        "\u05d3\u05d5\u05e8\u05d9\u05d4"
    ],
    "name:hun_x_preferred":[
        "Doria"
    ],
    "name:ita_x_preferred":[
        "Doria"
    ],
    "name:jpn_x_preferred":[
        "\u30c9\u30fc\u30ea\u30a2"
    ],
    "name:kor_x_preferred":[
        "\ub3c4\ub9ac\uc544"
    ],
    "name:lij_x_preferred":[
        "Doia"
    ],
    "name:rus_x_preferred":[
        "\u0414\u043e\u0440\u0438\u0430"
    ],
    "name:swe_x_preferred":[
        "Doria"
    ],
    "name:ukr_x_preferred":[
        "\u0414\u043e\u0440\u0456\u0430"
    ],
    "wof:name":"Doria",
    "wof:placetype":"neighbourhood"
},
  "geometry": {"coordinates":[81.15069,26.67],"type":"Point"}
}