{
  "type": "Feature",
  "properties": {
    "gn:admin1_code":"21",
    "gn:admin2_code":"370.0",
    "gn:asciiname":"Sayan",
    "gn:country_code":"IN",
    "gn:dem":179,
    "gn:feature_class":"P",
    "gn:feature_code":"PPL",
    "gn:name":"S\u0101y\u0101n",
    "gn:population":0,
    "gn:timezone":"Asia/Kolkata",
    "iso:country":"IN",
    "name:ceb_x_preferred":[
        "Sayan"
    ],
    "name:deu_x_preferred":[
        "Sayan"
    ],
    "name:ita_x_preferred":[
        "Sayan"
    ],
    "name:msa_x_preferred":[
        "Sayan"
    ],
    "name:nld_x_preferred":[
        "Sayan"
    ],
    "name:swe_x_preferred":[
        "Sayan"
    ],
    "wof:name":"Sayan",
    "wof:placetype":"locality"
},
  "geometry": {"coordinates":[83.57435,21.35128],"type":"Point"}
}