{
  "type": "Feature",
  "properties": {
    "gn:admin1_code":"34.0",
    "gn:admin2_code":"229.0",
    "gn:asciiname":"Gopalganj",
    "gn:country_code":"IN",
    "gn:dem":75,
    "gn:feature_class":"P",
    "gn:feature_code":"PPL",
    "gn:name":"Gop\u0101lganj",
    "gn:population":0,
    "gn:timezone":"Asia/Kolkata",
    "iso:country":"IN",
    "name:ben_x_preferred":[
        "\u0997\u09cb\u09aa\u09be\u09b2\u0997\u099e\u09cd\u099c"
    ],
    "name:ceb_x_preferred":[
        "Gopalganj"
    ],
    "name:deu_x_preferred":[
        "Gopalganj"
    ],
    "name:nld_x_preferred":[
        "Gopalganj"
    ],
    "name:sco_x_preferred":[
        "Gopalganj"
    ],
    "name:swe_x_preferred":[
        "Gopalganj"
    ],
    "wof:name":"Gopalganj",
    "wof:placetype":"locality"
},
  "geometry": {"coordinates":[85.17891999999998,25.12751],"type":"Point"}
}