{
  "type": "Feature",
  "properties": {
    "gn:admin1_code":"2",
    "gn:admin2_code":"546.0",
    "gn:asciiname":"Kedaram",
    "gn:country_code":"IN",
    "gn:dem":9,
    "gn:feature_class":"P",
    "gn:feature_code":"PPL",
    "gn:name":"Kedaram",
    "gn:population":0,
    "gn:timezone":"Asia/Kolkata",
    "iso:country":"IN",
    "name:tam_x_preferred":[
        "\u0b95\u0bc7\u0ba4\u0bbe\u0bb0\u0bae\u0bcd"
    ],
    "wof:name":"Kedaram",
    "wof:placetype":"neighbourhood"
},
  "geometry": {"coordinates":[81.24536999999999,16.73017],"type":"Point"}
}