{
  "type": "Feature",
  "properties": {
    "iso:country":"IN",
    "ks:ks_name":"Hattimardu",
    "ks:ks_pop":16,
    "ks:ks_type":"HABITATION",
    "name:eng_x_preferred":[
        "Hattimardu"
    ],
    "wof:name":"Hattimardu",
    "wof:placetype":"locality",
    "wof:population":16
},
  "geometry": {"coordinates":[74.804908,14.449071],"type":"Point"}
}