{
  "type": "Feature",
  "properties": {
    "gn:admin1_code":"36",
    "gn:admin2_code":"199.0",
    "gn:asciiname":"Parhi",
    "gn:country_code":"IN",
    "gn:dem":299,
    "gn:feature_class":"P",
    "gn:feature_code":"PPL",
    "gn:name":"Parhi",
    "gn:population":0,
    "gn:timezone":"Asia/Kolkata",
    "iso:country":"IN",
    "ks:ks_name":"Parahi",
    "ks:ks_pop":602,
    "ks:ks_type":"VILLAGE",
    "name:eng_x_preferred":[
        "Parahi"
    ],
    "name:eng_x_variant":[
        "Parhi"
    ],
    "wof:name":"Parahi",
    "wof:placetype":"locality",
    "wof:population":602
},
  "geometry": {"coordinates":[83.039621,24.826368],"type":"Point"}
}