{
  "type": "Feature",
  "properties": {
    "gn:admin1_code":"35",
    "gn:admin2_code":"429.0",
    "gn:asciiname":"Parewa",
    "gn:country_code":"IN",
    "gn:dem":368,
    "gn:feature_class":"P",
    "gn:feature_code":"PPL",
    "gn:name":"Parewa",
    "gn:population":0,
    "gn:timezone":"Asia/Kolkata",
    "iso:country":"IN",
    "name:und_x_variant":[
        "Chandeni"
    ],
    "wof:name":"Parewa",
    "wof:placetype":"locality"
},
  "geometry": {"coordinates":[80.83197,24.87918],"type":"Point"}
}