{
  "type": "Feature",
  "properties": {
    "iso:country":"IN",
    "ks:ks_name":"Tola Chhawni",
    "ks:ks_pop":2662,
    "ks:ks_type":"VILLAGE",
    "ks:ks_uagg_main":0,
    "name:eng_x_preferred":[
        "Tola Chhawni"
    ],
    "wof:name":"Tola Chhawni",
    "wof:placetype":"neighbourhood",
    "wof:population":2662
},
  "geometry": {"coordinates":[84.504159,26.816589],"type":"Point"}
}