{
  "type": "Feature",
  "properties": {
    "iso:country":"IN",
    "ks:ks_name":"Chakkumplavu",
    "ks:ks_pop":689,
    "ks:ks_type":"HABITATION",
    "name:eng_x_preferred":[
        "Chakkumplavu"
    ],
    "wof:name":"Chakkumplavu",
    "wof:placetype":"locality",
    "wof:population":689
},
  "geometry": {"coordinates":[76.299339,11.098608],"type":"Point"}
}