{
  "type": "Feature",
  "properties": {
    "iso:country":"IN",
    "ks:ks_alt_nam":"PURAB TOLA",
    "ks:ks_name":"Purab Tola",
    "ks:ks_pop":515,
    "ks:ks_type":"HABITATION",
    "name:eng_x_preferred":[
        "Purab Tola"
    ],
    "wof:name":"Purab Tola",
    "wof:placetype":"locality",
    "wof:population":515
},
  "geometry": {"coordinates":[84.203774,25.400035],"type":"Point"}
}