{
  "type": "Feature",
  "properties": {
    "iso:country":"IN",
    "ks:ks_name":"Pakaripat",
    "ks:ks_pop":283,
    "ks:ks_type":"HABITATION",
    "name:eng_x_preferred":[
        "Pakaripat"
    ],
    "wof:name":"Pakaripat",
    "wof:placetype":"locality",
    "wof:population":283
},
  "geometry": {"coordinates":[84.445463,23.358051],"type":"Point"}
}