{
  "type": "Feature",
  "properties": {
    "iso:country":"IN",
    "ks:ks_name":"Junapara",
    "ks:ks_pop":56,
    "ks:ks_type":"HABITATION",
    "name:eng_x_preferred":[
        "Junapara"
    ],
    "wof:name":"Junapara",
    "wof:placetype":"locality",
    "wof:population":56
},
  "geometry": {"coordinates":[82.39959899999999,22.952318],"type":"Point"}
}