{
  "type": "Feature",
  "properties": {
    "iso:country":"IN",
    "ks:ks_alt_nam":"laman tanda",
    "ks:ks_name":"Laman Tanda",
    "ks:ks_pop":149,
    "ks:ks_type":"HABITATION",
    "name:eng_x_preferred":[
        "Laman Tanda"
    ],
    "wof:name":"Laman Tanda",
    "wof:placetype":"locality",
    "wof:population":149
},
  "geometry": {"coordinates":[76.011529,17.419232],"type":"Point"}
}