{
  "type": "Feature",
  "properties": {
    "iso:country":"IN",
    "ks:ks_alt_nam":"GANDHIPURAM",
    "ks:ks_name":"Gandhipuram",
    "ks:ks_pop":90,
    "ks:ks_type":"HABITATION",
    "name:eng_x_preferred":[
        "Gandhipuram"
    ],
    "wof:name":"Gandhipuram",
    "wof:placetype":"locality",
    "wof:population":90
},
  "geometry": {"coordinates":[79.103283,13.40441],"type":"Point"}
}