{
  "type": "Feature",
  "properties": {
    "gn:admin1_code":"36",
    "gn:admin2_code":"198.0",
    "gn:asciiname":"Chak Harbans Bhatan",
    "gn:country_code":"IN",
    "gn:dem":89,
    "gn:feature_class":"P",
    "gn:feature_code":"PPL",
    "gn:name":"Chak Harbans Bhat\u0101n",
    "gn:population":0,
    "gn:timezone":"Asia/Kolkata",
    "iso:country":"IN",
    "ks:ks_alt_nam":"Chak Harbans Bhat\u0101n",
    "ks:ks_name":"Chak Harbans Bhatan",
    "ks:ks_type":"VILLAGE",
    "ks:ks_uagg_main":0,
    "name:eng_x_preferred":[
        "Chak Harbans Bhatan"
    ],
    "name:eng_x_variant":[
        "Chak Harbans Bhat\u0101n"
    ],
    "wof:name":"Chak Harbans Bhatan",
    "wof:placetype":"neighbourhood"
},
  "geometry": {"coordinates":[82.544877,25.346755],"type":"Point"}
}