{
  "type": "Feature",
  "properties": {
    "gn:admin1_code":"19.0",
    "gn:admin2_code":"574.0",
    "gn:asciiname":"Arakaravalli",
    "gn:country_code":"IN",
    "gn:dem":1033,
    "gn:feature_class":"P",
    "gn:feature_code":"PPL",
    "gn:name":"Arakaravalli",
    "gn:population":0,
    "gn:timezone":"Asia/Kolkata",
    "iso:country":"IN",
    "wof:name":"Arakaravalli",
    "wof:placetype":"locality"
},
  "geometry": {"coordinates":[75.85574,13.06425],"type":"Point"}
}