{
  "type": "Feature",
  "properties": {
    "gn:admin1_code":"19.0",
    "gn:admin2_code":"574.0",
    "gn:asciiname":"Arakaravalli",
    "gn:country_code":"IN",
    "gn:dem":1033,
    "gn:feature_class":"P",
    "gn:feature_code":"PPL",
    "gn:name":"Arakaravalli",
    "gn:population":0,
    "gn:timezone":"Asia/Kolkata",
    "iso:country":"IN",
    "ks:ks_name":"Arakaravally",
    "ks:ks_pop":203,
    "ks:ks_type":"HABITATION",
    "name:eng_x_preferred":[
        "Arakaravally"
    ],
    "name:eng_x_variant":[
        "Arakaravalli"
    ],
    "wof:name":"Arakaravally",
    "wof:placetype":"locality",
    "wof:population":203
},
  "geometry": {"coordinates":[75.86415100000001,13.066776],"type":"Point"}
}