{
  "type": "Feature",
  "properties": {
    "gn:admin1_code":"36.0",
    "gn:admin2_code":"202.0",
    "gn:asciiname":"Maidawali",
    "gn:country_code":"IN",
    "gn:dem":170,
    "gn:feature_class":"P",
    "gn:feature_code":"PPL",
    "gn:name":"Maid\u0101wali",
    "gn:population":0,
    "gn:timezone":"Asia/Kolkata",
    "iso:country":"IN",
    "ks:ks_alt_nam":"Maid\u0101wali",
    "ks:ks_name":"Maidawali",
    "ks:ks_type":"VILLAGE",
    "name:eng_x_preferred":[
        "Maidawali"
    ],
    "name:eng_x_variant":[
        "Maid\u0101wali"
    ],
    "wof:name":"Maidawali",
    "wof:placetype":"locality"
},
  "geometry": {"coordinates":[78.61794999999999,28.005339],"type":"Point"}
}