{
  "type": "Feature",
  "properties": {
    "gn:admin1_code":"36.0",
    "gn:admin2_code":"202.0",
    "gn:asciiname":"Maidawali",
    "gn:country_code":"IN",
    "gn:dem":170,
    "gn:feature_class":"P",
    "gn:feature_code":"PPL",
    "gn:name":"Maid\u0101wali",
    "gn:population":0,
    "gn:timezone":"Asia/Kolkata",
    "iso:country":"IN",
    "wof:name":"Maidawali",
    "wof:placetype":"locality"
},
  "geometry": {"coordinates":[78.61794999999999,28.00534],"type":"Point"}
}