{
  "type": "Feature",
  "properties": {
    "iso:country":"IN",
    "ks:ks_name":"Nikamwasti",
    "ks:ks_pop":121,
    "ks:ks_type":"HABITATION",
    "name:eng_x_preferred":[
        "Nikamwasti"
    ],
    "wof:name":"Nikamwasti",
    "wof:placetype":"locality",
    "wof:population":121
},
  "geometry": {"coordinates":[74.38484699999999,17.500222],"type":"Point"}
}