{
  "type": "Feature",
  "properties": {
    "iso:country":"IN",
    "ks:ks_alt_nam":"Guvvulakunta thanda",
    "ks:ks_name":"Guvvulakunta Thanda",
    "ks:ks_pop":54,
    "ks:ks_type":"HABITATION",
    "name:eng_x_preferred":[
        "Guvvulakunta Thanda"
    ],
    "wof:name":"Guvvulakunta Thanda",
    "wof:placetype":"locality",
    "wof:population":54
},
  "geometry": {"coordinates":[78.18187,16.393095],"type":"Point"}
}