{
  "type": "Feature",
  "properties": {
    "iso:country":"IN",
    "ks:ks_name":"Birlok",
    "ks:ks_pop":941,
    "ks:ks_type":"VILLAGE",
    "ks:ks_uagg_main":0,
    "name:eng_x_preferred":[
        "Birlok"
    ],
    "wof:name":"Birlok",
    "wof:placetype":"neighbourhood",
    "wof:population":941
},
  "geometry": {"coordinates":[87.851556,22.715711],"type":"Point"}
}