{
  "type": "Feature",
  "properties": {
    "iso:country":"IN",
    "ks:ks_name":"Andipatti",
    "ks:ks_pop":354,
    "ks:ks_type":"HABITATION",
    "name:eng_x_preferred":[
        "Andipatti"
    ],
    "wof:name":"Andipatti",
    "wof:placetype":"locality",
    "wof:population":354
},
  "geometry": {"coordinates":[78.4907,12.258957],"type":"Point"}
}