{
  "type": "Feature",
  "properties": {
    "iso:country":"IN",
    "ks:ks_name":"Valthathankottai",
    "ks:ks_pop":450,
    "ks:ks_type":"HABITATION",
    "name:eng_x_preferred":[
        "Valthathankottai"
    ],
    "wof:name":"Valthathankottai",
    "wof:placetype":"locality",
    "wof:population":450
},
  "geometry": {"coordinates":[78.217742,12.151228],"type":"Point"}
}