{
  "type": "Feature",
  "properties": {
    "iso:country":"IN",
    "ks:ks_name":"Lalitmohanpur",
    "ks:ks_pop":185,
    "ks:ks_type":"HABITATION",
    "name:eng_x_preferred":[
        "Lalitmohanpur"
    ],
    "wof:name":"Lalitmohanpur",
    "wof:placetype":"locality",
    "wof:population":185
},
  "geometry": {"coordinates":[85.042613,21.506444],"type":"Point"}
}