{
  "type": "Feature",
  "properties": {
    "gn:admin1_code":"24.0",
    "gn:admin2_code":"102.0",
    "gn:asciiname":"Dolaniva Bas",
    "gn:country_code":"IN",
    "gn:dem":261,
    "gn:feature_class":"P",
    "gn:feature_code":"PPL",
    "gn:name":"Dol\u0101niva Bas",
    "gn:population":0,
    "gn:timezone":"Asia/Kolkata",
    "iso:country":"IN",
    "name:und_x_variant":[
        "Dol\u0101niya Bas",
        "Dolariya B\u016bs",
        "Dol\u0101niva Bas"
    ],
    "wof:name":"Dolaniva Bas",
    "wof:placetype":"locality"
},
  "geometry": {"coordinates":[74.42048,28.40751],"type":"Point"}
}