{
  "type": "Feature",
  "properties": {
    "iso:country":"IN",
    "ks:ks_name":"Cheenikuzhy",
    "ks:ks_pop":1056,
    "ks:ks_type":"HABITATION",
    "name:eng_x_preferred":[
        "Cheenikuzhy"
    ],
    "wof:name":"Cheenikuzhy",
    "wof:placetype":"locality",
    "wof:population":1056
},
  "geometry": {"coordinates":[76.426165,9.967332],"type":"Point"}
}