{
  "type": "Feature",
  "properties": {
    "iso:country":"IN",
    "ks:ks_name":"Karkachia",
    "ks:ks_pop":35,
    "ks:ks_type":"HABITATION",
    "name:eng_x_preferred":[
        "Karkachia"
    ],
    "wof:name":"Karkachia",
    "wof:placetype":"locality",
    "wof:population":35
},
  "geometry": {"coordinates":[86.33571999999999,22.032084],"type":"Point"}
}