{
  "type": "Feature",
  "properties": {
    "gn:admin1_code":"24.0",
    "gn:admin2_code":"109.0",
    "gn:asciiname":"Thumri",
    "gn:country_code":"IN",
    "gn:dem":391,
    "gn:feature_class":"P",
    "gn:feature_code":"PPL",
    "gn:name":"Th\u016bmri",
    "gn:population":0,
    "gn:timezone":"Asia/Kolkata",
    "iso:country":"IN",
    "name:deu_x_preferred":[
        "Thumri"
    ],
    "name:fra_x_preferred":[
        "Thumri"
    ],
    "name:hin_x_preferred":[
        "\u0920\u0941\u092e\u0930\u0940"
    ],
    "name:ind_x_preferred":[
        "Thumri"
    ],
    "name:kan_x_preferred":[
        "\u0ca0\u0cc1\u0cae\u0ccd\u0cb0\u0cbf"
    ],
    "name:mal_x_preferred":[
        "\u0d20\u0d41\u0d2e\u0d4d\u0d30\u0d3f"
    ],
    "name:mar_x_preferred":[
        "\u0920\u0941\u092e\u0930\u0940"
    ],
    "name:pan_x_preferred":[
        "\u0a20\u0a41\u0a2e\u0a30\u0a40"
    ],
    "name:pnb_x_preferred":[
        "\u0679\u06be\u0645\u0631\u06cc"
    ],
    "name:san_x_preferred":[
        "\u0920\u0941\u092e\u0930\u093f"
    ],
    "name:tel_x_preferred":[
        "\u0c20\u0c41\u0c2e\u0c4d\u0c30\u0c3f"
    ],
    "name:urd_x_preferred":[
        "\u0679\u06be\u0645\u0631\u06cc"
    ],
    "wof:name":"Thumri",
    "wof:placetype":"locality"
},
  "geometry": {"coordinates":[76.44394,26.72745],"type":"Point"}
}