{
  "type": "Feature",
  "properties": {
    "iso:country":"IN",
    "ks:ks_name":"Antlavada",
    "ks:ks_pop":81,
    "ks:ks_type":"HABITATION",
    "name:eng_x_preferred":[
        "Antlavada"
    ],
    "wof:name":"Antlavada",
    "wof:placetype":"locality",
    "wof:population":81
},
  "geometry": {"coordinates":[82.364741,18.322477],"type":"Point"}
}