{
  "type": "Feature",
  "properties": {
    "iso:country":"IN",
    "ks:ks_name":"Kumguri",
    "ks:ks_pop":2198,
    "ks:ks_type":"VILLAGE",
    "ks:ks_uagg_main":0,
    "name:eng_x_preferred":[
        "Kumguri"
    ],
    "wof:name":"Kumguri",
    "wof:placetype":"neighbourhood",
    "wof:population":2198
},
  "geometry": {"coordinates":[90.070212,26.380249],"type":"Point"}
}