{
  "type": "Feature",
  "properties": {
    "gn:admin1_code":"02",
    "gn:admin2_code":"548.0",
    "gn:asciiname":"Tangeda",
    "gn:country_code":"IN",
    "gn:dem":71,
    "gn:feature_class":"P",
    "gn:feature_code":"PPL",
    "gn:name":"Tangeda",
    "gn:population":0,
    "gn:timezone":"Asia/Kolkata",
    "iso:country":"IN",
    "wof:name":"Tangeda",
    "wof:placetype":"locality"
},
  "geometry": {"coordinates":[79.81714000000002,16.66736],"type":"Point"}
}