{
  "type": "Feature",
  "properties": {
    "iso:country":"IN",
    "ks:ks_name":"Rengania Alias Goia",
    "ks:ks_pop":58,
    "ks:ks_type":"VILLAGE",
    "name:eng_x_preferred":[
        "Rengania Alias Goia"
    ],
    "wof:name":"Rengania Alias Goia",
    "wof:placetype":"locality",
    "wof:population":58
},
  "geometry": {"coordinates":[84.231335,24.465507],"type":"Point"}
}