{
  "type": "Feature",
  "properties": {
    "iso:country":"IN",
    "ks:ks_name":"Rajwapur Urf Belwa",
    "ks:ks_pop":337,
    "ks:ks_type":"HABITATION",
    "name:eng_x_preferred":[
        "Rajwapur Urf Belwa"
    ],
    "wof:name":"Rajwapur Urf Belwa",
    "wof:placetype":"locality",
    "wof:population":337
},
  "geometry": {"coordinates":[82.745237,27.221215],"type":"Point"}
}