{
  "type": "Feature",
  "properties": {
    "gn:admin1_code":"36.0",
    "gn:admin2_code":"150.0",
    "gn:asciiname":"Lohangpur",
    "gn:country_code":"IN",
    "gn:dem":167,
    "gn:feature_class":"P",
    "gn:feature_code":"PPL",
    "gn:name":"Lohangpur",
    "gn:population":0,
    "gn:timezone":"Asia/Kolkata",
    "iso:country":"IN",
    "wof:name":"Lohangpur",
    "wof:placetype":"locality"
},
  "geometry": {"coordinates":[79.49379999999999,28.20818],"type":"Point"}
}