{
  "type": "Feature",
  "properties": {
    "iso:country":"IN",
    "ks:ks_alt_nam":"mathawadi",
    "ks:ks_name":"Mathawadi",
    "ks:ks_pop":180,
    "ks:ks_type":"HABITATION",
    "name:eng_x_preferred":[
        "Mathawadi"
    ],
    "wof:name":"Mathawadi",
    "wof:placetype":"locality",
    "wof:population":180
},
  "geometry": {"coordinates":[73.372997,16.61808],"type":"Point"}
}