{
  "type": "Feature",
  "properties": {
    "iso:country":"IN",
    "ks:ks_name":"Pujari Vasti",
    "ks:ks_pop":327,
    "ks:ks_type":"HABITATION",
    "name:eng_x_preferred":[
        "Pujari Vasti"
    ],
    "wof:name":"Pujari Vasti",
    "wof:placetype":"locality",
    "wof:population":327
},
  "geometry": {"coordinates":[76.058584,17.197001],"type":"Point"}
}