{
  "type": "Feature",
  "properties": {
    "iso:country":"IN",
    "ks:ks_name":"Annavaram",
    "ks:ks_pop":72,
    "ks:ks_type":"VILLAGE",
    "name:eng_x_preferred":[
        "Annavaram"
    ],
    "wof:name":"Annavaram",
    "wof:placetype":"locality",
    "wof:population":72
},
  "geometry": {"coordinates":[82.041213,17.940507],"type":"Point"}
}