{
  "type": "Feature",
  "properties": {
    "gn:admin1_code":"34.0",
    "gn:admin2_code":"213.0",
    "gn:asciiname":"Tema",
    "gn:country_code":"IN",
    "gn:dem":46,
    "gn:feature_class":"P",
    "gn:feature_code":"PPL",
    "gn:name":"Tema",
    "gn:population":0,
    "gn:timezone":"Asia/Kolkata",
    "iso:country":"IN",
    "name:aka_x_preferred":[
        "Tema"
    ],
    "name:ara_x_preferred":[
        "\u062a\u064a\u0645\u0627"
    ],
    "name:azb_x_preferred":[
        "\u062a\u0645\u0627"
    ],
    "name:cat_x_preferred":[
        "Tema"
    ],
    "name:ceb_x_preferred":[
        "Tema"
    ],
    "name:dan_x_preferred":[
        "Tema"
    ],
    "name:deu_x_preferred":[
        "Tema"
    ],
    "name:epo_x_preferred":[
        "Tema"
    ],
    "name:fas_x_preferred":[
        "\u062a\u0645\u0627"
    ],
    "name:fin_x_preferred":[
        "Tema"
    ],
    "name:fra_x_preferred":[
        "Tema"
    ],
    "name:hrv_x_preferred":[
        "Tema"
    ],
    "name:hun_x_preferred":[
        "Tema"
    ],
    "name:ita_x_preferred":[
        "Tema"
    ],
    "name:jpn_x_preferred":[
        "\u30c6\u30de"
    ],
    "name:kor_x_preferred":[
        "\ud14c\ub9c8"
    ],
    "name:lit_x_preferred":[
        "Tema"
    ],
    "name:ltz_x_preferred":[
        "Tema"
    ],
    "name:nld_x_preferred":[
        "Tema"
    ],
    "name:pol_x_preferred":[
        "Tema"
    ],
    "name:por_x_preferred":[
        "Tema"
    ],
    "name:ron_x_preferred":[
        "Tema"
    ],
    "name:rus_x_preferred":[
        "\u0422\u0435\u043c\u0430"
    ],
    "name:spa_x_preferred":[
        "Tema"
    ],
    "name:swa_x_preferred":[
        "Tema"
    ],
    "name:swe_x_preferred":[
        "Tema"
    ],
    "name:szl_x_preferred":[
        "Tema"
    ],
    "name:urd_x_preferred":[
        "\u062a\u06cc\u0645\u0627"
    ],
    "name:vie_x_preferred":[
        "Tema"
    ],
    "name:vol_x_preferred":[
        "Tema"
    ],
    "wof:name":"Tema",
    "wof:placetype":"locality"
},
  "geometry": {"coordinates":[86.91970999999999,25.79665],"type":"Point"}
}