{
  "type": "Feature",
  "properties": {
    "iso:country":"IN",
    "ks:ks_name":"Cheerakuzhi",
    "ks:ks_pop":958,
    "ks:ks_type":"HABITATION",
    "name:eng_x_preferred":[
        "Cheerakuzhi"
    ],
    "wof:name":"Cheerakuzhi",
    "wof:placetype":"locality",
    "wof:population":958
},
  "geometry": {"coordinates":[76.294459,11.313225],"type":"Point"}
}