{
  "type": "Feature",
  "properties": {
    "iso:country":"IN",
    "ks:ks_name":"Baseli",
    "ks:ks_pop":371,
    "ks:ks_type":"VILLAGE",
    "name:eng_x_preferred":[
        "Baseli"
    ],
    "wof:name":"Baseli",
    "wof:placetype":"locality",
    "wof:population":371
},
  "geometry": {"coordinates":[78.46173,30.44921],"type":"Point"}
}