{
  "type": "Feature",
  "properties": {
    "iso:country":"IN",
    "ks:ks_name":"Netrampur",
    "ks:ks_pop":612,
    "ks:ks_type":"HABITATION",
    "name:eng_x_preferred":[
        "Netrampur"
    ],
    "wof:name":"Netrampur",
    "wof:placetype":"locality",
    "wof:population":612
},
  "geometry": {"coordinates":[77.736233,28.442483],"type":"Point"}
}