{
  "type": "Feature",
  "properties": {
    "gn:admin1_code":"2.0",
    "gn:admin2_code":"544.0",
    "gn:asciiname":"Chintalavalasa",
    "gn:country_code":"IN",
    "gn:dem":460,
    "gn:feature_class":"P",
    "gn:feature_code":"PPL",
    "gn:name":"Chintalavalasa",
    "gn:population":0,
    "gn:timezone":"Asia/Kolkata",
    "iso:country":"IN",
    "name:bpy_x_preferred":[
        "\u099a\u09bf\u09a8\u09cd\u09a4\u09b2\u09be\u09ac\u09be\u09b2\u09be\u09b8\u09be"
    ],
    "name:ita_x_preferred":[
        "Chintalavalasa"
    ],
    "name:msa_x_preferred":[
        "Chintalavalasa"
    ],
    "name:new_x_preferred":[
        "\u091a\u093f\u0928\u094d\u0924\u0932\u092d\u0932\u0938\u093e"
    ],
    "name:nld_x_preferred":[
        "Chintalavalasa"
    ],
    "name:por_x_preferred":[
        "Chintalavalasa"
    ],
    "name:vie_x_preferred":[
        "Chintalavalasa"
    ],
    "name:zho_x_preferred":[
        "\u94a6\u5854\u62c9\u74e6\u62c9\u8428"
    ],
    "wof:name":"Chintalavalasa",
    "wof:placetype":"locality"
},
  "geometry": {"coordinates":[83.08639000000002,18.41168],"type":"Point"}
}