{
  "type": "Feature",
  "properties": {
    "gn:admin1_code":"34.0",
    "gn:admin2_code":"216.0",
    "gn:asciiname":"Madhubani",
    "gn:country_code":"IN",
    "gn:dem":66,
    "gn:feature_class":"P",
    "gn:feature_code":"PPL",
    "gn:name":"Madhubani",
    "gn:population":0,
    "gn:timezone":"Asia/Kolkata",
    "iso:country":"IN",
    "ks:ks_name":"Madhubani",
    "ks:ks_pop":896,
    "ks:ks_type":"VILLAGE",
    "ks:ks_uagg_main":0,
    "name:ara_x_preferred":[
        "\u0645\u0627\u062f\u0647\u0648\u0628\u0627\u0646\u064a"
    ],
    "name:ara_x_variant":[
        "\u0645\u0627\u062f\u0647\u0648\u0628\u0627\u0646\u0649"
    ],
    "name:ben_bn_x_preferred":[
        "\u09ae\u09a7\u09c1\u09ac\u09a3\u09c0"
    ],
    "name:ben_in_x_preferred":[
        "\u09ae\u09a7\u09c1\u09ac\u09a3\u09c0"
    ],
    "name:ceb_x_preferred":[
        "Madhubani"
    ],
    "name:deu_x_preferred":[
        "Madhubani"
    ],
    "name:eng_x_preferred":[
        "Madhubani"
    ],
    "name:guj_x_preferred":[
        "\u0aae\u0aa7\u0ac1\u0aac\u0abe\u0aa8\u0ac0"
    ],
    "name:hin_x_preferred":[
        "\u092e\u0927\u0941\u092c\u0928\u0940"
    ],
    "name:kan_x_preferred":[
        "\u0cae\u0ca7\u0cc1\u0cac\u0ca8\u0cbf"
    ],
    "name:mal_x_preferred":[
        "\u0d2e\u0d27\u0d41\u0d2c\u0d3e\u0d28\u0d3f"
    ],
    "name:mar_x_preferred":[
        "\u092e\u0927\u0941\u092c\u0928\u0940"
    ],
    "name:nld_x_preferred":[
        "Madhubani"
    ],
    "name:pan_x_preferred":[
        "\u0a2e\u0a27\u0a42\u0a2c\u0a28\u0a40"
    ],
    "name:swe_x_preferred":[
        "Madhubani"
    ],
    "name:tam_x_preferred":[
        "\u0bae\u0ba4\u0bc1\u0baa\u0bbe\u0ba9\u0bbf"
    ],
    "name:tel_x_preferred":[
        "\u0c2e\u0c27\u0c41\u0c2c\u0c28\u0c3f"
    ],
    "name:urd_x_preferred":[
        "\u0645\u062f\u06be\u0648\u0628\u0646\u06cc"
    ],
    "wof:name":"Madhubani",
    "wof:placetype":"neighbourhood",
    "wof:population":896
},
  "geometry": {"coordinates":[84.96581399999999,26.306474],"type":"Point"}
}