{
  "type": "Feature",
  "properties": {
    "iso:country":"IN",
    "ks:ks_name":"Pure Tarsavan",
    "ks:ks_pop":300,
    "ks:ks_type":"HABITATION",
    "ks:ks_uagg_main":0,
    "name:eng_x_preferred":[
        "Pure Tarsavan"
    ],
    "wof:name":"Pure Tarsavan",
    "wof:placetype":"neighbourhood",
    "wof:population":300
},
  "geometry": {"coordinates":[81.978182,26.716517],"type":"Point"}
}