{
  "type": "Feature",
  "properties": {
    "gn:admin1_code":"36",
    "gn:admin2_code":"145.0",
    "gn:asciiname":"Baikunthpur",
    "gn:country_code":"IN",
    "gn:dem":177,
    "gn:feature_class":"P",
    "gn:feature_code":"PPL",
    "gn:name":"Baikunthpur",
    "gn:population":0,
    "gn:timezone":"Asia/Kolkata",
    "iso:country":"IN",
    "name:ceb_x_preferred":[
        "Baikunthpur"
    ],
    "name:ita_x_preferred":[
        "Baikunthpur"
    ],
    "name:nld_x_preferred":[
        "Baikunthpur"
    ],
    "name:swe_x_preferred":[
        "Baikunthpur"
    ],
    "wof:name":"Baikunthpur",
    "wof:placetype":"locality"
},
  "geometry": {"coordinates":[77.71944999999999,27.72735],"type":"Point"}
}