{
  "type": "Feature",
  "properties": {
    "iso:country":"IN",
    "ks:ks_name":"Janglekhas",
    "ks:ks_pop":203,
    "ks:ks_type":"HABITATION",
    "name:eng_x_preferred":[
        "Janglekhas"
    ],
    "wof:name":"Janglekhas",
    "wof:placetype":"locality",
    "wof:population":203
},
  "geometry": {"coordinates":[87.08232599999999,22.711388],"type":"Point"}
}