{
  "type": "Feature",
  "properties": {
    "gn:admin1_code":"12",
    "gn:admin2_code":"14.0",
    "gn:asciiname":"Hugom",
    "gn:country_code":"IN",
    "gn:dem":1664,
    "gn:feature_class":"P",
    "gn:feature_code":"PPL",
    "gn:name":"Hug\u014dm",
    "gn:population":0,
    "gn:timezone":"Asia/Kolkata",
    "iso:country":"IN",
    "wof:name":"Hugom",
    "wof:placetype":"locality"
},
  "geometry": {"coordinates":[75.19847,33.80198],"type":"Point"}
}