{
  "type": "Feature",
  "properties": {
    "gn:admin1_code":"34.0",
    "gn:admin2_code":"229",
    "gn:asciiname":"Dipnagar",
    "gn:country_code":"IN",
    "gn:dem":65,
    "gn:feature_class":"P",
    "gn:feature_code":"PPL",
    "gn:name":"D\u012bpnagar",
    "gn:population":0,
    "gn:timezone":"Asia/Kolkata",
    "iso:country":"IN",
    "ks:ks_name":"Deep Nagar",
    "ks:ks_pop":4882,
    "ks:ks_type":"HABITATION",
    "ks:ks_uagg_main":0,
    "name:eng_x_preferred":[
        "Deep Nagar"
    ],
    "wof:name":"Deep Nagar",
    "wof:placetype":"locality",
    "wof:population":4882
},
  "geometry": {"coordinates":[85.489305,25.153529],"type":"Point"}
}