{
  "type": "Feature",
  "properties": {
    "gn:admin1_code":"36",
    "gn:admin2_code":"196.0",
    "gn:asciiname":"Siwan",
    "gn:country_code":"IN",
    "gn:dem":78,
    "gn:feature_class":"P",
    "gn:feature_code":"PPL",
    "gn:name":"Siw\u0101n",
    "gn:population":0,
    "gn:timezone":"Asia/Kolkata",
    "iso:country":"IN",
    "name:ara_x_preferred":[
        "\u0633\u064a\u0648\u0627\u0646"
    ],
    "name:bih_x_preferred":[
        "\u0938\u093f\u0935\u093e\u0928"
    ],
    "name:bpy_x_preferred":[
        "\u09b8\u09bf\u09f1\u09be\u09a8"
    ],
    "name:bre_x_preferred":[
        "Siwan"
    ],
    "name:cym_x_preferred":[
        "Siwan"
    ],
    "name:deu_x_preferred":[
        "Siwan"
    ],
    "name:ind_x_preferred":[
        "Siwan"
    ],
    "name:msa_x_preferred":[
        "Siwan"
    ],
    "wof:name":"Siwan",
    "wof:placetype":"locality"
},
  "geometry": {"coordinates":[83.25334000000002,25.4022],"type":"Point"}
}