{
  "type": "Feature",
  "properties": {
    "iso:country":"IN",
    "ks:ks_name":"Pachinampatti",
    "ks:ks_pop":612,
    "ks:ks_type":"HABITATION",
    "name:eng_x_preferred":[
        "Pachinampatti"
    ],
    "wof:name":"Pachinampatti",
    "wof:placetype":"locality",
    "wof:population":612
},
  "geometry": {"coordinates":[78.401627,12.216446],"type":"Point"}
}