{
  "type": "Feature",
  "properties": {
    "iso:country":"IN",
    "ks:ks_name":"Kishtanaik Tanda",
    "ks:ks_pop":276,
    "ks:ks_type":"HABITATION",
    "name:eng_x_preferred":[
        "Kishtanaik Tanda"
    ],
    "wof:name":"Kishtanaik Tanda",
    "wof:placetype":"locality",
    "wof:population":276
},
  "geometry": {"coordinates":[78.62688300000001,19.229315],"type":"Point"}
}