{
  "type": "Feature",
  "properties": {
    "iso:country":"IN",
    "ks:ks_name":"Kharkoli",
    "ks:ks_pop":285,
    "ks:ks_type":"VILLAGE",
    "name:eng_x_preferred":[
        "Kharkoli"
    ],
    "wof:name":"Kharkoli",
    "wof:placetype":"locality",
    "wof:population":285
},
  "geometry": {"coordinates":[80.075367,29.537924],"type":"Point"}
}