{
  "type": "Feature",
  "properties": {
    "gn:admin1_code":"24.0",
    "gn:admin2_code":"110.0",
    "gn:asciiname":"Lachhminarayanpura",
    "gn:country_code":"IN",
    "gn:dem":465,
    "gn:feature_class":"P",
    "gn:feature_code":"PPL",
    "gn:name":"Lachhm\u012bn\u0101r\u0101yanpura",
    "gn:population":0,
    "gn:timezone":"Asia/Kolkata",
    "iso:country":"IN",
    "wof:name":"Lachhminarayanpura",
    "wof:placetype":"locality"
},
  "geometry": {"coordinates":[75.79689,27.0255],"type":"Point"}
}