{
  "type": "Feature",
  "properties": {
    "iso:country":"IN",
    "ks:ks_name":"Padampur",
    "ks:ks_pop":83,
    "ks:ks_type":"VILLAGE",
    "name:eng_x_preferred":[
        "Padampur"
    ],
    "wof:name":"Padampur",
    "wof:placetype":"locality",
    "wof:population":83
},
  "geometry": {"coordinates":[78.858492,27.774857],"type":"Point"}
}