{
  "type": "Feature",
  "properties": {
    "iso:country":"IN",
    "ks:ks_alt_nam":"Gavali daddi BALGUND",
    "ks:ks_name":"Gavali Daddi Balgund",
    "ks:ks_pop":79,
    "ks:ks_type":"HABITATION",
    "name:eng_x_preferred":[
        "Gavali Daddi Balgund"
    ],
    "wof:name":"Gavali Daddi Balgund",
    "wof:placetype":"locality",
    "wof:population":79
},
  "geometry": {"coordinates":[74.65872,15.440598],"type":"Point"}
}