{
  "type": "Feature",
  "properties": {
    "iso:country":"IN",
    "ks:ks_name":"Pure Ganga Urf Jadaipur",
    "ks:ks_pop":346,
    "ks:ks_type":"VILLAGE",
    "name:eng_x_preferred":[
        "Pure Ganga Urf Jadaipur"
    ],
    "wof:name":"Pure Ganga Urf Jadaipur",
    "wof:placetype":"locality",
    "wof:population":346
},
  "geometry": {"coordinates":[82.38311,26.761764],"type":"Point"}
}