{
  "type": "Feature",
  "properties": {
    "iso:country":"IN",
    "ks:ks_name":"Kompada",
    "ks:ks_pop":252,
    "ks:ks_type":"HABITATION",
    "name:eng_x_preferred":[
        "Kompada"
    ],
    "wof:name":"Kompada",
    "wof:placetype":"locality",
    "wof:population":252
},
  "geometry": {"coordinates":[72.910212,19.953638],"type":"Point"}
}