{
  "type": "Feature",
  "properties": {
    "iso:country":"IN",
    "ks:ks_name":"Thotaguda",
    "ks:ks_pop":16,
    "ks:ks_type":"HABITATION",
    "name:eng_x_preferred":[
        "Thotaguda"
    ],
    "wof:name":"Thotaguda",
    "wof:placetype":"locality",
    "wof:population":16
},
  "geometry": {"coordinates":[79.221008,19.200512],"type":"Point"}
}