{
  "type": "Feature",
  "properties": {
    "iso:country":"IN",
    "ks:ks_name":"Bellupadra",
    "ks:ks_pop":99,
    "ks:ks_type":"HABITATION",
    "name:eng_x_preferred":[
        "Bellupadra"
    ],
    "wof:name":"Bellupadra",
    "wof:placetype":"locality",
    "wof:population":99
},
  "geometry": {"coordinates":[84.436812,18.9105],"type":"Point"}
}