{
  "type": "Feature",
  "properties": {
    "iso:country":"IN",
    "ks:ks_name":"Sakla Kala",
    "ks:ks_pop":41,
    "ks:ks_type":"VILLAGE",
    "name:eng_x_preferred":[
        "Sakla Kala"
    ],
    "wof:name":"Sakla Kala",
    "wof:placetype":"locality",
    "wof:population":41
},
  "geometry": {"coordinates":[83.876717,25.582632],"type":"Point"}
}