{
  "type": "Feature",
  "properties": {
    "iso:country":"IN",
    "ks:ks_alt_nam":"CHAMPIA TOLI",
    "ks:ks_name":"Champia Toli",
    "ks:ks_pop":190,
    "ks:ks_type":"HABITATION",
    "name:eng_x_preferred":[
        "Champia Toli"
    ],
    "wof:name":"Champia Toli",
    "wof:placetype":"locality",
    "wof:population":190
},
  "geometry": {"coordinates":[85.425101,22.25604],"type":"Point"}
}