{
  "type": "Feature",
  "properties": {
    "iso:country":"IN",
    "ks:ks_name":"Khaira Marar",
    "ks:ks_pop":382,
    "ks:ks_type":"HABITATION",
    "name:eng_x_preferred":[
        "Khaira Marar"
    ],
    "wof:name":"Khaira Marar",
    "wof:placetype":"locality",
    "wof:population":382
},
  "geometry": {"coordinates":[85.376116,26.418035],"type":"Point"}
}