{
  "type": "Feature",
  "properties": {
    "gn:admin1_code":"33",
    "gn:admin2_code":"586.0",
    "gn:asciiname":"Potrem",
    "gn:country_code":"IN",
    "gn:dem":58,
    "gn:feature_class":"P",
    "gn:feature_code":"PPL",
    "gn:name":"Potrem",
    "gn:population":0,
    "gn:timezone":"Asia/Kolkata",
    "iso:country":"IN",
    "ks:ks_name":"Potrem",
    "ks:ks_pop":157,
    "ks:ks_type":"VILLAGE",
    "name:eng_x_preferred":[
        "Potrem"
    ],
    "wof:name":"Potrem",
    "wof:placetype":"locality",
    "wof:population":157
},
  "geometry": {"coordinates":[74.26333,15.202701],"type":"Point"}
}