{
  "type": "Feature",
  "properties": {
    "gn:admin1_code":"10",
    "gn:admin2_code":"82.0",
    "gn:asciiname":"Kheri Maham",
    "gn:country_code":"IN",
    "gn:dem":222,
    "gn:feature_class":"P",
    "gn:feature_code":"PPL",
    "gn:name":"Kheri Maham",
    "gn:population":0,
    "gn:timezone":"Asia/Kolkata",
    "iso:country":"IN",
    "wof:name":"Kheri Maham",
    "wof:placetype":"locality"
},
  "geometry": {"coordinates":[76.30644000000002,28.97691],"type":"Point"}
}