{
  "type": "Feature",
  "properties": {
    "iso:country":"IN",
    "ks:ks_name":"Grandhamvandlapalli",
    "ks:ks_pop":100,
    "ks:ks_type":"HABITATION",
    "name:eng_x_preferred":[
        "Grandhamvandlapalli"
    ],
    "wof:name":"Grandhamvandlapalli",
    "wof:placetype":"locality",
    "wof:population":100
},
  "geometry": {"coordinates":[78.67025700000001,14.14019],"type":"Point"}
}