{
  "type": "Feature",
  "properties": {
    "iso:country":"IN",
    "ks:ks_name":"Kuranganiparai",
    "ks:ks_pop":132,
    "ks:ks_type":"HABITATION",
    "name:eng_x_preferred":[
        "Kuranganiparai"
    ],
    "wof:name":"Kuranganiparai",
    "wof:placetype":"locality",
    "wof:population":132
},
  "geometry": {"coordinates":[77.66968900000001,10.370927],"type":"Point"}
}