{
  "type": "Feature",
  "properties": {
    "gn:admin1_code":"37",
    "gn:admin2_code":"404.0",
    "gn:asciiname":"Bari Umrao",
    "gn:country_code":"IN",
    "gn:dem":674,
    "gn:feature_class":"P",
    "gn:feature_code":"PPL",
    "gn:name":"B\u0101r\u012b Umrao",
    "gn:population":0,
    "gn:timezone":"Asia/Kolkata",
    "iso:country":"IN",
    "ks:ks_alt_nam":"B\u0101r\u012b Umrao",
    "ks:ks_name":"Bari Umrao",
    "ks:ks_type":"VILLAGE",
    "name:eng_x_preferred":[
        "Bari Umrao"
    ],
    "name:eng_x_variant":[
        "B\u0101r\u012b Umrao"
    ],
    "wof:name":"Bari Umrao",
    "wof:placetype":"locality"
},
  "geometry": {"coordinates":[82.32912399999999,22.478479],"type":"Point"}
}