{
  "type": "Feature",
  "properties": {
    "iso:country":"IN",
    "ks:ks_name":"Hewara",
    "ks:ks_pop":490,
    "ks:ks_type":"HABITATION",
    "name:eng_x_preferred":[
        "Hewara"
    ],
    "wof:name":"Hewara",
    "wof:placetype":"locality",
    "wof:population":490
},
  "geometry": {"coordinates":[81.822138,26.977184],"type":"Point"}
}