{
  "type": "Feature",
  "properties": {
    "iso:country":"IN",
    "ks:ks_name":"Chamelikund",
    "ks:ks_pop":217,
    "ks:ks_type":"HABITATION",
    "name:eng_x_preferred":[
        "Chamelikund"
    ],
    "wof:name":"Chamelikund",
    "wof:placetype":"locality",
    "wof:population":217
},
  "geometry": {"coordinates":[82.26778400000001,18.737592],"type":"Point"}
}