{
  "type": "Feature",
  "properties": {
    "gn:admin1_code":"2.0",
    "gn:admin2_code":"553.0",
    "gn:asciiname":"Virappagaripalle",
    "gn:country_code":"IN",
    "gn:dem":505,
    "gn:feature_class":"P",
    "gn:feature_code":"PPL",
    "gn:name":"V\u012brappag\u0101ripalle",
    "gn:population":0,
    "gn:timezone":"Asia/Kolkata",
    "iso:country":"IN",
    "wof:name":"Virappagaripalle",
    "wof:placetype":"locality"
},
  "geometry": {"coordinates":[78.19103,14.26231],"type":"Point"}
}