{
  "type": "Feature",
  "properties": {
    "gn:admin1_code":"38",
    "gn:admin2_code":"346.0",
    "gn:asciiname":"Kochia",
    "gn:country_code":"IN",
    "gn:dem":201,
    "gn:feature_class":"P",
    "gn:feature_code":"PPL",
    "gn:name":"Kochia",
    "gn:population":0,
    "gn:timezone":"Asia/Kolkata",
    "iso:country":"IN",
    "name:bel_x_preferred":[
        "\u041f\u0440\u0443\u0442\u043d\u044f\u043a"
    ],
    "name:kaz_x_preferred":[
        "\u0418\u0437\u0435\u043d"
    ],
    "name:kir_x_preferred":[
        "\u0416\u044b\u043b\u0442\u044b\u0440\u043a\u0430\u043d"
    ],
    "name:por_x_preferred":[
        "Kochia"
    ],
    "name:rus_x_preferred":[
        "\u041a\u043e\u0445\u0438\u044f"
    ],
    "name:spa_x_preferred":[
        "Kochia"
    ],
    "name:zho_x_preferred":[
        "\u5730\u80a4\u5c5e"
    ],
    "wof:name":"Kochia",
    "wof:placetype":"locality"
},
  "geometry": {"coordinates":[83.64961,24.28977],"type":"Point"}
}