{
  "type": "Feature",
  "properties": {
    "iso:country":"IN",
    "ks:ks_name":"Paria",
    "ks:ks_pop":4960,
    "ks:ks_type":"URBAN",
    "name:eng_x_preferred":[
        "Paria"
    ],
    "wof:name":"Paria",
    "wof:placetype":"locality",
    "wof:population":4960
},
  "geometry": {"coordinates":[86.57628200000001,25.278982],"type":"Point"}
}