{
  "type": "Feature",
  "properties": {
    "iso:country":"IN",
    "ks:ks_name":"Rui Dhamna",
    "ks:ks_pop":0,
    "ks:ks_type":"VILLAGE",
    "name:eng_x_preferred":[
        "Rui Dhamna"
    ],
    "wof:name":"Rui Dhamna",
    "wof:placetype":"locality",
    "wof:population":0
},
  "geometry": {"coordinates":[85.287943,24.54749],"type":"Point"}
}