{
  "type": "Feature",
  "properties": {
    "gn:admin1_code":"34.0",
    "gn:admin2_code":"226.0",
    "gn:asciiname":"Goarwadih",
    "gn:country_code":"IN",
    "gn:dem":63,
    "gn:feature_class":"P",
    "gn:feature_code":"PPL",
    "gn:name":"Goarw\u0101dih",
    "gn:population":0,
    "gn:timezone":"Asia/Kolkata",
    "iso:country":"IN",
    "ks:ks_alt_nam":"Goarw\u0101dih",
    "ks:ks_name":"Goarwadih",
    "ks:ks_pop":442,
    "ks:ks_type":"VILLAGE",
    "ks:ks_uagg_main":0,
    "name:eng_x_preferred":[
        "Goarwadih"
    ],
    "name:eng_x_variant":[
        "Goarw\u0101dih"
    ],
    "wof:name":"Goarwadih",
    "wof:placetype":"neighbourhood",
    "wof:population":442
},
  "geometry": {"coordinates":[86.557827,25.053161],"type":"Point"}
}