{
  "type": "Feature",
  "properties": {
    "gn:admin1_code":"35.0",
    "gn:admin2_code":"457.0",
    "gn:asciiname":"Sugi",
    "gn:country_code":"IN",
    "gn:dem":578,
    "gn:feature_class":"P",
    "gn:feature_code":"PPL",
    "gn:name":"Sug\u012b",
    "gn:population":0,
    "gn:timezone":"Asia/Kolkata",
    "iso:country":"IN",
    "ks:ks_name":"Suji",
    "ks:ks_pop":381,
    "ks:ks_type":"VILLAGE",
    "name:eng_x_preferred":[
        "Suji"
    ],
    "name:eng_x_variant":[
        "Sugi"
    ],
    "wof:name":"Suji",
    "wof:placetype":"locality",
    "wof:population":381
},
  "geometry": {"coordinates":[80.681668,22.007668],"type":"Point"}
}