{
  "type": "Feature",
  "properties": {
    "iso:country":"IN",
    "ks:ks_name":"Fasatpur",
    "ks:ks_pop":703,
    "ks:ks_type":"HABITATION",
    "ks:ks_uagg_main":0,
    "name:eng_x_preferred":[
        "Fasatpur"
    ],
    "wof:name":"Fasatpur",
    "wof:placetype":"neighbourhood",
    "wof:population":703
},
  "geometry": {"coordinates":[90.079819,26.156849],"type":"Point"}
}