{
  "type": "Feature",
  "properties": {
    "iso:country":"IN",
    "ks:ks_name":"Pasiyana East",
    "ks:ks_pop":412,
    "ks:ks_type":"HABITATION",
    "name:eng_x_preferred":[
        "Pasiyana East"
    ],
    "wof:name":"Pasiyana East",
    "wof:placetype":"locality",
    "wof:population":412
},
  "geometry": {"coordinates":[83.162177,25.804989],"type":"Point"}
}