{
  "type": "Feature",
  "properties": {
    "gn:admin1_code":"19.0",
    "gn:admin2_code":"577.0",
    "gn:asciiname":"Shankahalli",
    "gn:country_code":"IN",
    "gn:dem":794,
    "gn:feature_class":"P",
    "gn:feature_code":"PPL",
    "gn:name":"Shankahalli",
    "gn:population":0,
    "gn:timezone":"Asia/Kolkata",
    "iso:country":"IN",
    "wof:name":"Shankahalli",
    "wof:placetype":"locality"
},
  "geometry": {"coordinates":[76.44626,12.28085],"type":"Point"}
}