{
  "type": "Feature",
  "properties": {
    "gn:admin1_code":"19.0",
    "gn:admin2_code":"555.0",
    "gn:asciiname":"Hindalgi",
    "gn:country_code":"IN",
    "gn:dem":747,
    "gn:feature_class":"P",
    "gn:feature_code":"PPL",
    "gn:name":"Hindalgi",
    "gn:population":0,
    "gn:timezone":"Asia/Kolkata",
    "iso:country":"IN",
    "ks:ks_name":"Hindalgi",
    "ks:ks_pop":10862,
    "ks:ks_type":"VILLAGE",
    "ks:ks_uagg_main":0,
    "name:ben_x_preferred":[
        "\u09b9\u09bf\u09a8\u09cd\u09a6\u09be\u09b2\u0997\u09bf"
    ],
    "name:bpy_x_preferred":[
        "\u09b9\u09bf\u09a8\u09cd\u09a6\u09be\u09b2\u0997\u09bf"
    ],
    "name:ita_x_preferred":[
        "Hindalgi"
    ],
    "name:mlg_x_preferred":[
        "Hindalgi"
    ],
    "name:msa_x_preferred":[
        "Hindalgi"
    ],
    "name:new_x_preferred":[
        "\u0939\u093f\u0928\u094d\u0926\u0932\u094d\u0917\u0940"
    ],
    "name:nld_x_preferred":[
        "Hindalgi"
    ],
    "name:por_x_preferred":[
        "Hindalgi"
    ],
    "name:vie_x_preferred":[
        "Hindalgi"
    ],
    "name:zho_x_preferred":[
        "\u5e0c\u6069\u8fbe\u5c14\u5409"
    ],
    "wof:name":"Hindalgi",
    "wof:placetype":"neighbourhood"
},
  "geometry": {"coordinates":[74.47205,15.87495],"type":"Point"}
}