{
  "type": "Feature",
  "properties": {
    "gn:admin1_code":"21",
    "gn:admin2_code":"399.0",
    "gn:asciiname":"Kammaruguda",
    "gn:country_code":"IN",
    "gn:dem":253,
    "gn:feature_class":"P",
    "gn:feature_code":"PPL",
    "gn:name":"Kamm\u0101ruguda",
    "gn:population":0,
    "gn:timezone":"Asia/Kolkata",
    "iso:country":"IN",
    "wof:name":"Kammaruguda",
    "wof:placetype":"locality"
},
  "geometry": {"coordinates":[82.13019,18.48964],"type":"Point"}
}