{
  "type": "Feature",
  "properties": {
    "iso:country":"IN",
    "ks:ks_name":"Korakara",
    "ks:ks_pop":1595,
    "ks:ks_type":"VILLAGE",
    "name:eng_x_preferred":[
        "Korakara"
    ],
    "wof:name":"Korakara",
    "wof:placetype":"locality",
    "wof:population":1595
},
  "geometry": {"coordinates":[86.508466,21.023222],"type":"Point"}
}