{
  "type": "Feature",
  "properties": {
    "iso:country":"IN",
    "ks:ks_name":"Jhadiaguda",
    "ks:ks_pop":236,
    "ks:ks_type":"HABITATION",
    "name:eng_x_preferred":[
        "Jhadiaguda"
    ],
    "wof:name":"Jhadiaguda",
    "wof:placetype":"locality",
    "wof:population":236
},
  "geometry": {"coordinates":[82.332464,19.601311],"type":"Point"}
}