{
  "type": "Feature",
  "properties": {
    "iso:country":"IN",
    "ks:ks_alt_nam":"silwa",
    "ks:ks_name":"Silwa",
    "ks:ks_pop":180,
    "ks:ks_type":"HABITATION",
    "name:eng_x_preferred":[
        "Silwa"
    ],
    "wof:name":"Silwa",
    "wof:placetype":"locality",
    "wof:population":180
},
  "geometry": {"coordinates":[86.893889,24.463396],"type":"Point"}
}