{
  "type": "Feature",
  "properties": {
    "iso:country":"IN",
    "ks:ks_name":"Katra",
    "ks:ks_type":"VILLAGE",
    "ks:ks_uagg_main":0,
    "name:eng_x_preferred":[
        "Katra"
    ],
    "wof:name":"Katra",
    "wof:placetype":"neighbourhood"
},
  "geometry": {"coordinates":[82.71620900000001,26.793452],"type":"Point"}
}