{
  "type": "Feature",
  "properties": {
    "iso:country":"IN",
    "ks:ks_name":"Dighi",
    "ks:ks_pop":1108,
    "ks:ks_type":"VILLAGE",
    "name:eng_x_preferred":[
        "Dighi"
    ],
    "wof:name":"Dighi",
    "wof:placetype":"locality",
    "wof:population":1108
},
  "geometry": {"coordinates":[86.488877,22.3016],"type":"Point"}
}