{
  "type": "Feature",
  "properties": {
    "iso:country":"IN",
    "ks:ks_name":"Solpat",
    "ks:ks_pop":1373,
    "ks:ks_type":"VILLAGE",
    "ks:ks_uagg_main":0,
    "name:eng_x_preferred":[
        "Solpat"
    ],
    "wof:name":"Solpat",
    "wof:placetype":"neighbourhood",
    "wof:population":1373
},
  "geometry": {"coordinates":[86.573521,20.827245],"type":"Point"}
}