{
  "type": "Feature",
  "properties": {
    "iso:country":"IN",
    "ks:ks_name":"Arlapadu Srirampuram",
    "ks:ks_pop":362,
    "ks:ks_type":"HABITATION",
    "ks:ks_uagg_main":0,
    "name:eng_x_preferred":[
        "Arlapadu Srirampuram"
    ],
    "wof:name":"Arlapadu Srirampuram",
    "wof:placetype":"neighbourhood",
    "wof:population":362
},
  "geometry": {"coordinates":[80.59982100000001,17.428451],"type":"Point"}
}