{
  "type": "Feature",
  "properties": {
    "iso:country":"IN",
    "ks:ks_name":"Poolabanda",
    "ks:ks_pop":88,
    "ks:ks_type":"HABITATION",
    "name:eng_x_preferred":[
        "Poolabanda"
    ],
    "wof:name":"Poolabanda",
    "wof:placetype":"locality",
    "wof:population":88
},
  "geometry": {"coordinates":[82.37875699999999,18.274521],"type":"Point"}
}