{
  "type": "Feature",
  "properties": {
    "iso:country":"IN",
    "ks:ks_name":"Gala Talawadi",
    "ks:ks_pop":223,
    "ks:ks_type":"VILLAGE",
    "name:eng_x_preferred":[
        "Gala Talawadi"
    ],
    "wof:name":"Gala Talawadi",
    "wof:placetype":"locality",
    "wof:population":223
},
  "geometry": {"coordinates":[73.795154,23.178388],"type":"Point"}
}