{
  "type": "Feature",
  "properties": {
    "gn:admin1_code":"35",
    "gn:admin2_code":"455.0",
    "gn:asciiname":"Gaikhuri",
    "gn:country_code":"IN",
    "gn:dem":560,
    "gn:feature_class":"P",
    "gn:feature_code":"PPL",
    "gn:name":"G\u0101ikhuri",
    "gn:population":0,
    "gn:timezone":"Asia/Kolkata",
    "iso:country":"IN",
    "wof:name":"Gaikhuri",
    "wof:placetype":"locality"
},
  "geometry": {"coordinates":[78.55128000000001,21.72013],"type":"Point"}
}