{
  "type": "Feature",
  "properties": {
    "iso:country":"IN",
    "ks:ks_name":"Mundakasseri",
    "ks:ks_pop":1211,
    "ks:ks_type":"HABITATION",
    "ks:ks_uagg_main":0,
    "name:eng_x_preferred":[
        "Mundakasseri"
    ],
    "wof:name":"Mundakasseri",
    "wof:placetype":"neighbourhood",
    "wof:population":1211
},
  "geometry": {"coordinates":[75.913763,11.222068],"type":"Point"}
}