{
  "type": "Feature",
  "properties": {
    "gn:admin1_code":"19.0",
    "gn:admin2_code":"567.0",
    "gn:asciiname":"Ajjihalli",
    "gn:country_code":"IN",
    "gn:dem":703,
    "gn:feature_class":"P",
    "gn:feature_code":"PPL",
    "gn:name":"Ajjihalli",
    "gn:population":0,
    "gn:timezone":"Asia/Kolkata",
    "iso:country":"IN",
    "wof:name":"Ajjihalli",
    "wof:placetype":"locality"
},
  "geometry": {"coordinates":[75.90125999999999,14.01921],"type":"Point"}
}