{
  "type": "Feature",
  "properties": {
    "iso:country":"IN",
    "name:ara_x_preferred":[
        "\u062c\u0627\u064a\u0645\u0627\u0647\u0644"
    ],
    "name:ben_bn_x_preferred":[
        "\u099c\u09df\u09be\u09ae\u09b9\u09b2"
    ],
    "name:ben_in_x_preferred":[
        "\u099c\u09df\u09be\u09ae\u09b9\u09b2"
    ],
    "name:eng_x_preferred":[
        "Jayamahal"
    ],
    "name:guj_x_preferred":[
        "\u0a9c\u0aaf\u0abe\u0aae\u0ab9\u0ab2"
    ],
    "name:hin_x_preferred":[
        "\u091c\u092f\u093e\u092e\u0939\u0932"
    ],
    "name:kan_x_preferred":[
        "\u0c9c\u0caf\u0cae\u0cb9\u0cb2\u0ccd"
    ],
    "name:mal_x_preferred":[
        "\u0d1c\u0d2f\u0d2e\u0d39\u0d7d"
    ],
    "name:mar_x_preferred":[
        "\u091c\u092f\u093e\u092e\u0939\u0932"
    ],
    "name:pan_x_preferred":[
        "\u0a1c\u0a2f\u0a3e\u0a2e\u0a3e\u0a39\u0a32"
    ],
    "name:tam_x_preferred":[
        "\u0b9c\u0bc6\u0baf\u0bae\u0b95\u0bbe\u0bb2\u0bcd"
    ],
    "name:tel_x_preferred":[
        "\u0c1c\u0c2f\u0c3e\u0c2e\u0c39\u0c32\u0c4d"
    ],
    "name:urd_x_preferred":[
        "\u062c\u06cc\u0627 \u0645\u062d\u0644"
    ],
    "qs:gn_adm0_cc":"IN",
    "qs:gn_local":1277333,
    "qs:gn_nam_loc":"Bangalore, Bangalore, Karnataka, IN",
    "qs:gn_namadm1":"19",
    "qs:local_max":7342,
    "qs:local_sum":38996,
    "qs:localhoods":89,
    "qs:name":"Jayamahal",
    "qs:name_adm0":"India",
    "qs:name_adm1":"Karnataka",
    "qs:name_adm2":"Bangalore",
    "qs:name_local":"Bangalore",
    "qs:photo_max":311,
    "qs:photo_sum":1175,
    "qs:placetype":"Suburb",
    "qs:quad_count":27,
    "qs:woe_adm0":23424848,
    "qs:woe_adm1":2345753,
    "qs:woe_adm2":12586572,
    "qs:woe_lau":0,
    "qs:woe_local":2295420,
    "qs:woe_ver":"7.10.0",
    "wof:lang":[
        "eng"
    ],
    "wof:name":"Jayamahal",
    "wof:placetype":"neighbourhood"
},
  "geometry": {"coordinates":[77.587632,13.00575],"type":"Point"}
}