{
  "type": "Feature",
  "properties": {
    "gn:admin1_code":"36.0",
    "gn:admin2_code":"160",
    "gn:asciiname":"Kullukhera",
    "gn:country_code":"IN",
    "gn:dem":150,
    "gn:feature_class":"P",
    "gn:feature_code":"PPL",
    "gn:name":"Kullukhera",
    "gn:population":0,
    "gn:timezone":"Asia/Kolkata",
    "iso:country":"IN",
    "wof:name":"Kullukhera",
    "wof:placetype":"locality"
},
  "geometry": {"coordinates":[79.43556,27.05995],"type":"Point"}
}