{
  "type": "Feature",
  "properties": {
    "iso:country":"IN",
    "ks:ks_name":"Baligere",
    "ks:ks_pop":10,
    "ks:ks_type":"HABITATION",
    "name:eng_x_preferred":[
        "Baligere"
    ],
    "wof:name":"Baligere",
    "wof:placetype":"locality",
    "wof:population":10
},
  "geometry": {"coordinates":[74.773999,13.95078],"type":"Point"}
}