{
  "type": "Feature",
  "properties": {
    "gn:admin1_code":"36.0",
    "gn:admin2_code":"166.0",
    "gn:asciiname":"Siaori",
    "gn:country_code":"IN",
    "gn:dem":211,
    "gn:feature_class":"P",
    "gn:feature_code":"PPL",
    "gn:name":"Si\u0101or\u012b",
    "gn:population":0,
    "gn:timezone":"Asia/Kolkata",
    "iso:country":"IN",
    "ks:ks_alt_nam":"Si\u0101or\u012b",
    "ks:ks_name":"Siaori",
    "ks:ks_pop":7043,
    "ks:ks_type":"VILLAGE",
    "ks:ks_uagg_main":0,
    "name:eng_x_preferred":[
        "Siaori"
    ],
    "name:eng_x_variant":[
        "Si\u0101or\u012b"
    ],
    "name:und_x_variant":[
        "Si\u0101or\u012b",
        "Si\u0101ri"
    ],
    "wof:name":"Siaori",
    "wof:placetype":"neighbourhood",
    "wof:population":7043
},
  "geometry": {"coordinates":[79.111352,25.327148],"type":"Point"}
}