{
  "type": "Feature",
  "properties": {
    "iso:country":"IN",
    "ks:ks_name":"Soolaimeni Colony",
    "ks:ks_pop":760,
    "ks:ks_type":"HABITATION",
    "name:eng_x_preferred":[
        "Soolaimeni Colony"
    ],
    "wof:name":"Soolaimeni Colony",
    "wof:placetype":"locality",
    "wof:population":760
},
  "geometry": {"coordinates":[79.985517,13.313691],"type":"Point"}
}