{
  "type": "Feature",
  "properties": {
    "iso:country":"IN",
    "ks:ks_name":"Gashbari",
    "ks:ks_pop":1817,
    "ks:ks_type":"HABITATION",
    "name:eng_x_preferred":[
        "Gashbari"
    ],
    "wof:name":"Gashbari",
    "wof:placetype":"locality",
    "wof:population":1817
},
  "geometry": {"coordinates":[92.105664,26.370384],"type":"Point"}
}