{
  "type": "Feature",
  "properties": {
    "iso:country":"IN",
    "ks:ks_name":"Dighola Gaon",
    "ks:ks_pop":548,
    "ks:ks_type":"HABITATION",
    "name:eng_x_preferred":[
        "Dighola Gaon"
    ],
    "wof:name":"Dighola Gaon",
    "wof:placetype":"locality",
    "wof:population":548
},
  "geometry": {"coordinates":[94.81263,27.407517],"type":"Point"}
}