{
  "type": "Feature",
  "properties": {
    "gn:admin1_code":"25.0",
    "gn:admin2_code":"632.0",
    "gn:asciiname":"Kavundanpalaiyam",
    "gn:country_code":"IN",
    "gn:dem":388,
    "gn:feature_class":"P",
    "gn:feature_code":"PPL",
    "gn:name":"Kavundanp\u0101laiyam",
    "gn:population":0,
    "gn:timezone":"Asia/Kolkata",
    "iso:country":"IN",
    "wof:name":"Kavundanpalaiyam",
    "wof:placetype":"neighbourhood"
},
  "geometry": {"coordinates":[77.22292,10.89219],"type":"Point"}
}