{
  "type": "Feature",
  "properties": {
    "iso:country":"IN",
    "ks:ks_name":"Panchaetbhawan Tola",
    "ks:ks_pop":259,
    "ks:ks_type":"HABITATION",
    "name:eng_x_preferred":[
        "Panchaetbhawan Tola"
    ],
    "wof:name":"Panchaetbhawan Tola",
    "wof:placetype":"locality",
    "wof:population":259
},
  "geometry": {"coordinates":[84.009855,26.919079],"type":"Point"}
}