{
  "type": "Feature",
  "properties": {
    "iso:country":"IN",
    "ks:ks_name":"Sarry Tola",
    "ks:ks_pop":138,
    "ks:ks_type":"HABITATION",
    "name:eng_x_preferred":[
        "Sarry Tola"
    ],
    "wof:name":"Sarry Tola",
    "wof:placetype":"locality",
    "wof:population":138
},
  "geometry": {"coordinates":[86.84669,24.7537],"type":"Point"}
}