{
  "type": "Feature",
  "properties": {
    "gn:admin1_code":"40.0",
    "gn:admin2_code":"538.0",
    "gn:asciiname":"Pamregadi",
    "gn:country_code":"IN",
    "gn:dem":432,
    "gn:feature_class":"P",
    "gn:feature_code":"PPL",
    "gn:name":"Pamregadi",
    "gn:population":0,
    "gn:timezone":"Asia/Kolkata",
    "iso:country":"IN",
    "wof:name":"Pamregadi",
    "wof:placetype":"locality"
},
  "geometry": {"coordinates":[79.04800999999998,16.33094],"type":"Point"}
}