{
  "type": "Feature",
  "properties": {
    "gn:admin1_code":"2.0",
    "gn:admin2_code":"550.0",
    "gn:asciiname":"Bandepalli",
    "gn:country_code":"IN",
    "gn:dem":70,
    "gn:feature_class":"P",
    "gn:feature_code":"PPL",
    "gn:name":"Bandepalli",
    "gn:population":0,
    "gn:timezone":"Asia/Kolkata",
    "iso:country":"IN",
    "ks:ks_name":"Bandepalle",
    "ks:ks_pop":267,
    "ks:ks_type":"VILLAGE",
    "ks:ks_uagg_main":0,
    "name:eng_x_preferred":[
        "Bandepalle"
    ],
    "wof:name":"Bandepalle",
    "wof:placetype":"neighbourhood",
    "wof:population":267
},
  "geometry": {"coordinates":[79.553425,14.181357],"type":"Point"}
}