{
  "type": "Feature",
  "properties": {
    "iso:country":"IN",
    "ks:ks_name":"Dusadh Tola",
    "ks:ks_pop":209,
    "ks:ks_type":"HABITATION",
    "ks:ks_uagg_main":0,
    "name:eng_x_preferred":[
        "Dusadh Tola"
    ],
    "wof:name":"Dusadh Tola",
    "wof:placetype":"neighbourhood",
    "wof:population":209
},
  "geometry": {"coordinates":[84.397071,26.39105],"type":"Point"}
}