{
  "type": "Feature",
  "properties": {
    "gn:admin1_code":"36.0",
    "gn:admin2_code":"166.0",
    "gn:asciiname":"Bargaon",
    "gn:country_code":"IN",
    "gn:dem":185,
    "gn:feature_class":"P",
    "gn:feature_code":"PPL",
    "gn:name":"Bargaon",
    "gn:population":0,
    "gn:timezone":"Asia/Kolkata",
    "iso:country":"IN",
    "wof:name":"Bargaon",
    "wof:placetype":"locality"
},
  "geometry": {"coordinates":[79.15111,25.63079],"type":"Point"}
}