{
  "type": "Feature",
  "properties": {
    "iso:country":"IN",
    "ks:ks_name":"Darkala",
    "ks:ks_pop":35,
    "ks:ks_type":"VILLAGE",
    "name:eng_x_preferred":[
        "Darkala"
    ],
    "wof:name":"Darkala",
    "wof:placetype":"locality",
    "wof:population":35
},
  "geometry": {"coordinates":[87.72367800000001,25.205184],"type":"Point"}
}