{
  "type": "Feature",
  "properties": {
    "gn:admin1_code":"36.0",
    "gn:admin2_code":"193.0",
    "gn:asciiname":"Ahera",
    "gn:country_code":"IN",
    "gn:dem":68,
    "gn:feature_class":"P",
    "gn:feature_code":"PPL",
    "gn:name":"Ahera",
    "gn:population":0,
    "gn:timezone":"Asia/Kolkata",
    "iso:country":"IN",
    "ks:ks_name":"Ahara",
    "ks:ks_pop":1162,
    "ks:ks_type":"HABITATION",
    "name:eng_x_preferred":[
        "Ahara"
    ],
    "name:eng_x_variant":[
        "Ahera"
    ],
    "wof:name":"Ahara",
    "wof:placetype":"locality",
    "wof:population":1162
},
  "geometry": {"coordinates":[84.102942,25.868665],"type":"Point"}
}