{
  "type": "Feature",
  "properties": {
    "iso:country":"IN",
    "ks:ks_name":"Dhooli Bhakhri",
    "ks:ks_pop":106,
    "ks:ks_type":"HABITATION",
    "name:eng_x_preferred":[
        "Dhooli Bhakhri"
    ],
    "wof:name":"Dhooli Bhakhri",
    "wof:placetype":"locality",
    "wof:population":106
},
  "geometry": {"coordinates":[73.38413300000001,24.478183],"type":"Point"}
}