{
  "type": "Feature",
  "properties": {
    "gn:admin1_code":"34.0",
    "gn:admin2_code":"236",
    "gn:asciiname":"Khizr Sarai",
    "gn:country_code":"IN",
    "gn:dem":93,
    "gn:feature_class":"P",
    "gn:feature_code":"PPL",
    "gn:name":"Khizr Sar\u0101i",
    "gn:population":0,
    "gn:timezone":"Asia/Kolkata",
    "iso:country":"IN",
    "name:und_x_variant":[
        "Khidar Sar\u0101y",
        "Khizr Sar\u0101i"
    ],
    "wof:name":"Khizr Sarai",
    "wof:placetype":"locality"
},
  "geometry": {"coordinates":[85.09206,24.96789],"type":"Point"}
}