{
  "type": "Feature",
  "properties": {
    "gn:admin1_code":"36",
    "gn:admin2_code":"196.0",
    "gn:asciiname":"Maharajganj",
    "gn:country_code":"IN",
    "gn:dem":74,
    "gn:feature_class":"P",
    "gn:feature_code":"PPL",
    "gn:name":"Mah\u0101r\u0101jganj",
    "gn:population":0,
    "gn:timezone":"Asia/Kolkata",
    "iso:country":"IN",
    "name:ceb_x_preferred":[
        "Maharajganj"
    ],
    "name:deu_x_preferred":[
        "Maharajganj"
    ],
    "name:nld_x_preferred":[
        "Maharajganj"
    ],
    "name:pol_x_preferred":[
        "Maharajganj"
    ],
    "name:swe_x_preferred":[
        "Maharajganj"
    ],
    "wof:name":"Maharajganj",
    "wof:placetype":"locality"
},
  "geometry": {"coordinates":[83.26236999999998,25.4645],"type":"Point"}
}