{
  "type": "Feature",
  "properties": {
    "iso:country":"IN",
    "ks:ks_name":"Dongabhawana",
    "ks:ks_pop":190,
    "ks:ks_type":"HABITATION",
    "name:eng_x_preferred":[
        "Dongabhawana"
    ],
    "wof:name":"Dongabhawana",
    "wof:placetype":"locality",
    "wof:population":190
},
  "geometry": {"coordinates":[83.491721,22.313213],"type":"Point"}
}