{
  "type": "Feature",
  "properties": {
    "iso:country":"IN",
    "ks:ks_name":"Dhediyano Nalo",
    "ks:ks_pop":239,
    "ks:ks_type":"VILLAGE",
    "name:eng_x_preferred":[
        "Dhediyano Nalo"
    ],
    "wof:name":"Dhediyano Nalo",
    "wof:placetype":"locality",
    "wof:population":239
},
  "geometry": {"coordinates":[73.934907,23.049844],"type":"Point"}
}