{
  "type": "Feature",
  "properties": {
    "iso:country":"IN",
    "ks:ks_alt_nam":"Mangalath Granites road",
    "ks:ks_name":"Mangalath Granites Road",
    "ks:ks_pop":113,
    "ks:ks_type":"HABITATION",
    "name:eng_x_preferred":[
        "Mangalath Granites Road"
    ],
    "wof:name":"Mangalath Granites Road",
    "wof:placetype":"locality",
    "wof:population":113
},
  "geometry": {"coordinates":[76.35212300000001,10.730627],"type":"Point"}
}