{
  "type": "Feature",
  "properties": {
    "iso:country":"IN",
    "ks:ks_name":"Balu Bapu Kampa",
    "ks:ks_pop":70,
    "ks:ks_type":"HABITATION",
    "name:eng_x_preferred":[
        "Balu Bapu Kampa"
    ],
    "wof:name":"Balu Bapu Kampa",
    "wof:placetype":"locality",
    "wof:population":70
},
  "geometry": {"coordinates":[73.313361,23.599389],"type":"Point"}
}