{
  "type": "Feature",
  "properties": {
    "gn:admin1_code":"3.0",
    "gn:admin2_code":"300.0",
    "gn:asciiname":"Panwari",
    "gn:country_code":"IN",
    "gn:dem":57,
    "gn:feature_class":"P",
    "gn:feature_code":"PPL",
    "gn:name":"P\u0101nw\u0101ri",
    "gn:population":0,
    "gn:timezone":"Asia/Kolkata",
    "iso:country":"IN",
    "wof:name":"Panwari",
    "wof:placetype":"locality"
},
  "geometry": {"coordinates":[89.95513000000003,26.48659],"type":"Point"}
}