{
  "type": "Feature",
  "properties": {
    "gn:admin1_code":"12.0",
    "gn:asciiname":"Bari Pattan",
    "gn:country_code":"IN",
    "gn:dem":503,
    "gn:feature_class":"P",
    "gn:feature_code":"PPL",
    "gn:name":"Bari Pattan",
    "gn:population":0,
    "gn:timezone":"Asia/Kolkata",
    "iso:country":"IN",
    "name:und_x_variant":[
        "Beri Pattan",
        "Bari Pattan"
    ],
    "wof:name":"Bari Pattan",
    "wof:placetype":"locality"
},
  "geometry": {"coordinates":[74.35996,33.06708],"type":"Point"}
}