{
  "type": "Feature",
  "properties": {
    "gn:admin1_code":"36",
    "gn:admin2_code":"190.0",
    "gn:asciiname":"Bhola Singh",
    "gn:country_code":"IN",
    "gn:dem":73,
    "gn:feature_class":"P",
    "gn:feature_code":"PPL",
    "gn:name":"Bhola Singh",
    "gn:population":0,
    "gn:timezone":"Asia/Kolkata",
    "iso:country":"IN",
    "wof:name":"Bhola Singh",
    "wof:placetype":"locality"
},
  "geometry": {"coordinates":[83.49975999999999,26.46721],"type":"Point"}
}