{
  "type": "Feature",
  "properties": {
    "iso:country":"IN",
    "ks:ks_name":"Charali Ka",
    "ks:ks_pop":679,
    "ks:ks_type":"HABITATION",
    "ks:ks_uagg_main":0,
    "name:eng_x_preferred":[
        "Charali Ka"
    ],
    "wof:name":"Charali Ka",
    "wof:placetype":"neighbourhood",
    "wof:population":679
},
  "geometry": {"coordinates":[92.39878400000001,26.746788],"type":"Point"}
}