{
  "type": "Feature",
  "properties": {
    "iso:country":"IN",
    "ks:ks_name":"Boudhawadi",
    "ks:ks_pop":102,
    "ks:ks_type":"HABITATION",
    "name:eng_x_preferred":[
        "Boudhawadi"
    ],
    "wof:name":"Boudhawadi",
    "wof:placetype":"locality",
    "wof:population":102
},
  "geometry": {"coordinates":[73.365736,17.812586],"type":"Point"}
}