{
  "type": "Feature",
  "properties": {
    "iso:country":"IN",
    "ks:ks_name":"Agoia",
    "ks:ks_pop":166,
    "ks:ks_type":"HABITATION",
    "name:eng_x_preferred":[
        "Agoia"
    ],
    "wof:name":"Agoia",
    "wof:placetype":"locality",
    "wof:population":166
},
  "geometry": {"coordinates":[86.965886,24.452522],"type":"Point"}
}