{
  "type": "Feature",
  "properties": {
    "iso:country":"IN",
    "ks:ks_name":"Karanimitta",
    "ks:ks_pop":915,
    "ks:ks_type":"HABITATION",
    "name:eng_x_preferred":[
        "Karanimitta"
    ],
    "wof:name":"Karanimitta",
    "wof:placetype":"locality",
    "wof:population":915
},
  "geometry": {"coordinates":[79.871273,13.671886],"type":"Point"}
}