{
  "type": "Feature",
  "properties": {
    "iso:country":"IN",
    "ks:ks_name":"Makan Pur",
    "ks:ks_pop":471,
    "ks:ks_type":"VILLAGE",
    "ks:ks_uagg_main":0,
    "name:eng_x_preferred":[
        "Makan Pur"
    ],
    "wof:name":"Makan Pur",
    "wof:placetype":"neighbourhood",
    "wof:population":471
},
  "geometry": {"coordinates":[86.581543,24.975713],"type":"Point"}
}