{
  "type": "Feature",
  "properties": {
    "iso:country":"IN",
    "ks:ks_name":"Sivalingapuram",
    "ks:ks_pop":71,
    "ks:ks_type":"HABITATION",
    "name:eng_x_preferred":[
        "Sivalingapuram"
    ],
    "wof:name":"Sivalingapuram",
    "wof:placetype":"locality",
    "wof:population":71
},
  "geometry": {"coordinates":[83.16539,18.427796],"type":"Point"}
}