{
  "type": "Feature",
  "properties": {
    "iso:country":"IN",
    "ks:ks_name":"Gaura Deopali",
    "ks:ks_pop":553,
    "ks:ks_type":"VILLAGE",
    "name:eng_x_preferred":[
        "Gaura Deopali"
    ],
    "wof:name":"Gaura Deopali",
    "wof:placetype":"locality",
    "wof:population":553
},
  "geometry": {"coordinates":[82.822957,19.26441],"type":"Point"}
}