{
  "type": "Feature",
  "properties": {
    "gn:admin1_code":"36",
    "gn:admin2_code":"176.0",
    "gn:asciiname":"Atrauli",
    "gn:country_code":"IN",
    "gn:dem":100,
    "gn:feature_class":"P",
    "gn:feature_code":"PPL",
    "gn:name":"Atrauli",
    "gn:population":0,
    "gn:timezone":"Asia/Kolkata",
    "iso:country":"IN",
    "ks:ks_name":"Atrauli",
    "ks:ks_type":"VILLAGE",
    "name:bih_x_preferred":[
        "\u0905\u0924\u0930\u094c\u0932\u0940"
    ],
    "name:bpy_x_preferred":[
        "\u0986\u09a4\u09cd\u09b0\u09cc\u09b2\u09bf"
    ],
    "name:cat_x_preferred":[
        "Atrauli"
    ],
    "name:ceb_x_preferred":[
        "Atrauli"
    ],
    "name:eng_x_preferred":[
        "Atrauli"
    ],
    "name:hin_x_preferred":[
        "\u0905\u0924\u0930\u094c\u0932\u0940 \u0939\u0930\u0926\u094b\u0908"
    ],
    "name:ita_x_preferred":[
        "Atrauli"
    ],
    "name:mlg_x_preferred":[
        "Atrauli"
    ],
    "name:msa_x_preferred":[
        "Atrauli"
    ],
    "name:nld_x_preferred":[
        "Atrauli"
    ],
    "name:pol_x_preferred":[
        "Atrauli"
    ],
    "name:por_x_preferred":[
        "Atrauli"
    ],
    "name:urd_x_preferred":[
        "\u0627\u062a\u0631\u0627\u0624\u0644\u06cc"
    ],
    "name:vie_x_preferred":[
        "Atrauli"
    ],
    "name:zho_x_preferred":[
        "\u963f\u7279\u52b3\u5229"
    ],
    "wof:name":"Atrauli",
    "wof:placetype":"locality"
},
  "geometry": {"coordinates":[81.59153000000001,26.992657],"type":"Point"}
}