{
  "type": "Feature",
  "properties": {
    "iso:country":"IN",
    "ks:ks_name":"Seelamvaripalem",
    "ks:ks_pop":449,
    "ks:ks_type":"HABITATION",
    "ks:ks_uagg_main":0,
    "name:eng_x_preferred":[
        "Seelamvaripalem"
    ],
    "wof:name":"Seelamvaripalem",
    "wof:placetype":"neighbourhood",
    "wof:population":449
},
  "geometry": {"coordinates":[80.861541,16.175346],"type":"Point"}
}