{
  "type": "Feature",
  "properties": {
    "iso:country":"IN",
    "ks:ks_name":"Kaikure",
    "ks:ks_pop":160,
    "ks:ks_type":"HABITATION",
    "name:eng_x_preferred":[
        "Kaikure"
    ],
    "wof:name":"Kaikure",
    "wof:placetype":"locality",
    "wof:population":160
},
  "geometry": {"coordinates":[75.50606999999999,12.768474],"type":"Point"}
}