{
  "type": "Feature",
  "properties": {
    "iso:country":"IN",
    "ks:ks_name":"Gashiyapara",
    "ks:ks_pop":362,
    "ks:ks_type":"HABITATION",
    "name:eng_x_preferred":[
        "Gashiyapara"
    ],
    "wof:name":"Gashiyapara",
    "wof:placetype":"locality",
    "wof:population":362
},
  "geometry": {"coordinates":[83.444565,22.941245],"type":"Point"}
}