{
  "type": "Feature",
  "properties": {
    "iso:country":"IN",
    "ks:ks_name":"Appukodige Tribal C",
    "ks:ks_pop":79,
    "ks:ks_type":"HABITATION",
    "name:eng_x_preferred":[
        "Appukodige Tribal C"
    ],
    "wof:name":"Appukodige Tribal C",
    "wof:placetype":"locality",
    "wof:population":79
},
  "geometry": {"coordinates":[75.351682,13.336428],"type":"Point"}
}