{
  "type": "Feature",
  "properties": {
    "gn:admin1_code":"2",
    "gn:admin2_code":"546.0",
    "gn:asciiname":"Pallapur",
    "gn:country_code":"IN",
    "gn:dem":43,
    "gn:feature_class":"P",
    "gn:feature_code":"PPL",
    "gn:name":"Pall\u0101pur",
    "gn:population":0,
    "gn:timezone":"Asia/Kolkata",
    "iso:country":"IN",
    "ks:ks_name":"Pallapuru",
    "ks:ks_pop":77,
    "ks:ks_type":"HABITATION",
    "name:eng_x_preferred":[
        "Pallapuru"
    ],
    "name:eng_x_variant":[
        "Pallapur"
    ],
    "wof:name":"Pallapuru",
    "wof:placetype":"locality",
    "wof:population":77
},
  "geometry": {"coordinates":[81.581131,17.384692],"type":"Point"}
}