{
  "type": "Feature",
  "properties": {
    "gn:admin1_code":"13.0",
    "gn:admin2_code":"591.0",
    "gn:asciiname":"Onchiyam",
    "gn:country_code":"IN",
    "gn:dem":10,
    "gn:feature_class":"P",
    "gn:feature_code":"PPL",
    "gn:name":"Onchiyam",
    "gn:population":0,
    "gn:timezone":"Asia/Kolkata",
    "iso:country":"IN",
    "ks:ks_name":"Onchiyam",
    "ks:ks_pop":2654,
    "ks:ks_type":"VILLAGE",
    "name:eng_x_preferred":[
        "Onchiyam"
    ],
    "wof:name":"Onchiyam",
    "wof:placetype":"locality",
    "wof:population":2654
},
  "geometry": {"coordinates":[75.57333199999999,11.659745],"type":"Point"}
}