{
  "type": "Feature",
  "properties": {
    "iso:country":"IN",
    "ks:ks_name":"Aliya",
    "ks:ks_pop":287,
    "ks:ks_type":"HABITATION",
    "name:eng_x_preferred":[
        "Aliya"
    ],
    "wof:name":"Aliya",
    "wof:placetype":"locality",
    "wof:population":287
},
  "geometry": {"coordinates":[79.677842,26.968545],"type":"Point"}
}