{
  "type": "Feature",
  "properties": {
    "gn:admin1_code":"16.0",
    "gn:admin2_code":"513.0",
    "gn:asciiname":"Mudgal",
    "gn:country_code":"IN",
    "gn:dem":395,
    "gn:feature_class":"P",
    "gn:feature_code":"PPL",
    "gn:name":"Mudgal",
    "gn:population":0,
    "gn:timezone":"Asia/Kolkata",
    "iso:country":"IN",
    "name:ben_x_preferred":[
        "\u09ae\u09c1\u09a6\u0997\u09be\u09b2"
    ],
    "name:bpy_x_preferred":[
        "\u09ae\u09c1\u09a6\u0997\u09be\u09b2"
    ],
    "name:cat_x_preferred":[
        "Mudgal"
    ],
    "name:ceb_x_preferred":[
        "Mudgal"
    ],
    "name:ita_x_preferred":[
        "Mudgal"
    ],
    "name:jpn_x_preferred":[
        "\u30e0\u30c9\u30ac\u30eb"
    ],
    "name:kan_x_preferred":[
        "\u0cae\u0cc1\u0ca6\u0c97\u0cb2\u0ccd"
    ],
    "name:mlg_x_preferred":[
        "Mudgal"
    ],
    "name:msa_x_preferred":[
        "Mudgal"
    ],
    "name:new_x_preferred":[
        "\u092e\u093f\u0926\u094d\u0917\u0932"
    ],
    "name:nld_x_preferred":[
        "Mudgal"
    ],
    "name:por_x_preferred":[
        "Mudgal"
    ],
    "name:spa_x_preferred":[
        "Mudgal"
    ],
    "name:swe_x_preferred":[
        "Mudgal"
    ],
    "name:vie_x_preferred":[
        "Mudgal"
    ],
    "name:zho_x_preferred":[
        "\u7a46\u5fb7\u52a0\u5c14"
    ],
    "wof:name":"Mudgal",
    "wof:placetype":"locality"
},
  "geometry": {"coordinates":[76.49299000000001,19.09097],"type":"Point"}
}