{
  "type": "Feature",
  "properties": {
    "gn:admin1_code":"16.0",
    "gn:admin2_code":"513.0",
    "gn:asciiname":"Mudgal",
    "gn:country_code":"IN",
    "gn:dem":395,
    "gn:feature_class":"P",
    "gn:feature_code":"PPL",
    "gn:name":"Mudgal",
    "gn:population":0,
    "gn:timezone":"Asia/Kolkata",
    "iso:country":"IN",
    "wof:name":"Mudgal",
    "wof:placetype":"locality"
},
  "geometry": {"coordinates":[76.49299000000001,19.09097],"type":"Point"}
}