{
  "type": "Feature",
  "properties": {
    "gn:admin1_code":"34.0",
    "gn:admin2_code":"237.0",
    "gn:asciiname":"Pipra Khurd",
    "gn:country_code":"IN",
    "gn:dem":112,
    "gn:feature_class":"P",
    "gn:feature_code":"PPL",
    "gn:name":"Pipra Khurd",
    "gn:population":0,
    "gn:timezone":"Asia/Kolkata",
    "iso:country":"IN",
    "ks:ks_name":"Pipra Khurd",
    "ks:ks_pop":706,
    "ks:ks_type":"VILLAGE",
    "ks:ks_uagg_main":0,
    "name:eng_x_preferred":[
        "Pipra Khurd"
    ],
    "wof:name":"Pipra Khurd",
    "wof:placetype":"neighbourhood",
    "wof:population":706
},
  "geometry": {"coordinates":[85.561442,24.771109],"type":"Point"}
}