{
  "type": "Feature",
  "properties": {
    "gn:admin1_code":"23.0",
    "gn:admin2_code":"35.0",
    "gn:asciiname":"Padda",
    "gn:country_code":"IN",
    "gn:dem":237,
    "gn:feature_class":"P",
    "gn:feature_code":"PPL",
    "gn:name":"Padda",
    "gn:population":0,
    "gn:timezone":"Asia/Kolkata",
    "iso:country":"IN",
    "name:ceb_x_preferred":[
        "Padda"
    ],
    "name:ces_x_preferred":[
        "Padda"
    ],
    "name:deu_x_preferred":[
        "Reisfinken"
    ],
    "name:hun_x_preferred":[
        "Padda"
    ],
    "name:ind_x_preferred":[
        "Gelatik"
    ],
    "name:ita_x_preferred":[
        "Padda"
    ],
    "name:jav_x_preferred":[
        "Glathik"
    ],
    "name:por_x_preferred":[
        "Padda"
    ],
    "name:spa_x_preferred":[
        "Padda"
    ],
    "name:war_x_preferred":[
        "Padda"
    ],
    "name:zho_x_preferred":[
        "\u79be\u96c0\u5c5e"
    ],
    "wof:name":"Padda",
    "wof:placetype":"locality"
},
  "geometry": {"coordinates":[75.02494,31.9715],"type":"Point"}
}