{
  "type": "Feature",
  "properties": {
    "iso:country":"IN",
    "ks:ks_name":"Phulasar Chhota",
    "ks:ks_pop":2170,
    "ks:ks_type":"HABITATION",
    "name:eng_x_preferred":[
        "Phulasar Chhota"
    ],
    "wof:name":"Phulasar Chhota",
    "wof:placetype":"locality",
    "wof:population":2170
},
  "geometry": {"coordinates":[72.348061,27.882372],"type":"Point"}
}