{
  "type": "Feature",
  "properties": {
    "gn:admin1_code":"37",
    "gn:admin2_code":"408.0",
    "gn:asciiname":"Job",
    "gn:country_code":"IN",
    "gn:dem":369,
    "gn:feature_class":"P",
    "gn:feature_code":"PPL",
    "gn:name":"Job",
    "gn:population":0,
    "gn:timezone":"Asia/Kolkata",
    "iso:country":"IN",
    "name:ben_x_preferred":[
        "\u099a\u09be\u0995\u09b0\u09bf"
    ],
    "name:ces_x_preferred":[
        "Povol\u00e1n\u00ed"
    ],
    "name:epo_x_preferred":[
        "Verko"
    ],
    "name:fas_x_preferred":[
        "\u0634\u063a\u0644"
    ],
    "name:fry_x_preferred":[
        "Arbeid"
    ],
    "name:gla_x_preferred":[
        "Dreuchdan"
    ],
    "name:guj_x_preferred":[
        "\u0ab5\u0acd\u0aaf\u0ab5\u0ab8\u0abe\u0aaf"
    ],
    "name:hat_x_preferred":[
        "Travay"
    ],
    "name:heb_x_preferred":[
        "\u05de\u05e9\u05e8\u05d4"
    ],
    "name:kan_x_preferred":[
        "\u0c89\u0ca6\u0ccd\u0caf\u0ccb\u0c97"
    ],
    "name:mal_x_preferred":[
        "\u0d1c\u0d4b\u0d32\u0d3f"
    ],
    "name:new_x_preferred":[
        "\u0932\u091c\u0917\u093e"
    ],
    "name:nld_x_preferred":[
        "Arbeid"
    ],
    "name:nno_x_preferred":[
        "Yrke"
    ],
    "name:nor_x_preferred":[
        "Yrke"
    ],
    "name:por_x_preferred":[
        "Day job"
    ],
    "name:pus_x_preferred":[
        "\u06a9\u0627\u0631"
    ],
    "name:sna_x_preferred":[
        "Basa"
    ],
    "name:som_x_preferred":[
        "Shaqo"
    ],
    "name:tam_x_preferred":[
        "\u0ba4\u0bca\u0bb4\u0bbf\u0bb2\u0bcd"
    ],
    "name:tgl_x_preferred":[
        "Hanapbuhay"
    ],
    "name:ukr_x_preferred":[
        "\u0420\u043e\u0431\u043e\u0442\u0430"
    ],
    "name:vie_x_preferred":[
        "Vi\u1ec7c l\u00e0m"
    ],
    "name:yid_x_preferred":[
        "\u05e9\u05d8\u05e2\u05dc\u05e2"
    ],
    "wof:name":"Job",
    "wof:placetype":"locality"
},
  "geometry": {"coordinates":[80.52691,21.00343],"type":"Point"}
}