{
  "type": "Feature",
  "properties": {
    "iso:country":"IN",
    "ks:ks_alt_nam":"PURE PASI",
    "ks:ks_name":"Pure Pasi",
    "ks:ks_pop":27,
    "ks:ks_type":"HABITATION",
    "ks:ks_uagg_main":0,
    "name:eng_x_preferred":[
        "Pure Pasi"
    ],
    "wof:name":"Pure Pasi",
    "wof:placetype":"neighbourhood",
    "wof:population":27
},
  "geometry": {"coordinates":[81.745132,26.445409],"type":"Point"}
}