{
  "type": "Feature",
  "properties": {
    "gn:admin1_code":"25.0",
    "gn:admin2_code":"633.0",
    "gn:asciiname":"Virugalpatti Pudur",
    "gn:country_code":"IN",
    "gn:dem":361,
    "gn:feature_class":"P",
    "gn:feature_code":"PPL",
    "gn:name":"Virugalpatti Pud\u016br",
    "gn:population":0,
    "gn:timezone":"Asia/Kolkata",
    "iso:country":"IN",
    "wof:name":"Virugalpatti Pudur",
    "wof:placetype":"locality"
},
  "geometry": {"coordinates":[77.15517,10.72311],"type":"Point"}
}