{
  "type": "Feature",
  "properties": {
    "iso:country":"IN",
    "ks:ks_name":"Schoolpara",
    "ks:ks_pop":217,
    "ks:ks_type":"HABITATION",
    "name:eng_x_preferred":[
        "Schoolpara"
    ],
    "wof:name":"Schoolpara",
    "wof:placetype":"locality",
    "wof:population":217
},
  "geometry": {"coordinates":[82.016047,18.885309],"type":"Point"}
}