{
  "type": "Feature",
  "properties": {
    "gn:admin1_code":"35.0",
    "gn:admin2_code":"425.0",
    "gn:asciiname":"Sagari",
    "gn:country_code":"IN",
    "gn:dem":477,
    "gn:feature_class":"P",
    "gn:feature_code":"PPL",
    "gn:name":"Sag\u0101ri",
    "gn:population":0,
    "gn:timezone":"Asia/Kolkata",
    "iso:country":"IN",
    "wof:name":"Sagari",
    "wof:placetype":"locality"
},
  "geometry": {"coordinates":[79.18505999999999,24.18656],"type":"Point"}
}