{
  "type": "Feature",
  "properties": {
    "iso:country":"IN",
    "ks:ks_alt_nam":"Seera goundenally",
    "ks:ks_name":"Seera Goundenally",
    "ks:ks_pop":115,
    "ks:ks_type":"HABITATION",
    "name:eng_x_preferred":[
        "Seera Goundenally"
    ],
    "wof:name":"Seera Goundenally",
    "wof:placetype":"locality",
    "wof:population":115
},
  "geometry": {"coordinates":[76.998051,11.62782],"type":"Point"}
}