{
  "type": "Feature",
  "properties": {
    "iso:country":"IN",
    "ks:ks_alt_nam":"Mirjapur camp",
    "ks:ks_name":"Mirjapur Camp",
    "ks:ks_pop":200,
    "ks:ks_type":"HABITATION",
    "name:eng_x_preferred":[
        "Mirjapur Camp"
    ],
    "wof:name":"Mirjapur Camp",
    "wof:placetype":"locality",
    "wof:population":200
},
  "geometry": {"coordinates":[77.48674200000001,15.975614],"type":"Point"}
}