{
  "type": "Feature",
  "properties": {
    "iso:country":"IN",
    "ks:ks_name":"Garbeytar",
    "ks:ks_pop":637,
    "ks:ks_type":"HABITATION",
    "name:eng_x_preferred":[
        "Garbeytar"
    ],
    "wof:name":"Garbeytar",
    "wof:placetype":"locality",
    "wof:population":637
},
  "geometry": {"coordinates":[88.25236099999999,27.121752],"type":"Point"}
}