{
  "type": "Feature",
  "properties": {
    "iso:country":"IN",
    "ks:ks_name":"Eruttuthodu",
    "ks:ks_pop":550,
    "ks:ks_type":"HABITATION",
    "name:eng_x_preferred":[
        "Eruttuthodu"
    ],
    "wof:name":"Eruttuthodu",
    "wof:placetype":"locality",
    "wof:population":550
},
  "geometry": {"coordinates":[76.65972499999999,9.887905],"type":"Point"}
}