{
  "type": "Feature",
  "properties": {
    "gn:admin1_code":"16",
    "gn:admin2_code":"503.0",
    "gn:asciiname":"Kund",
    "gn:country_code":"IN",
    "gn:dem":502,
    "gn:feature_class":"P",
    "gn:feature_code":"PPL",
    "gn:name":"Kund",
    "gn:population":0,
    "gn:timezone":"Asia/Kolkata",
    "iso:country":"IN",
    "name:fas_x_preferred":[
        "\u06a9\u0646\u062f"
    ],
    "name:urd_x_preferred":[
        "\u06a9\u0646\u0688"
    ],
    "wof:name":"Kund",
    "wof:placetype":"locality"
},
  "geometry": {"coordinates":[77.18739000000002,21.43803],"type":"Point"}
}