{
  "type": "Feature",
  "properties": {
    "iso:country":"IN",
    "ks:ks_name":"Sankhala",
    "ks:ks_pop":636,
    "ks:ks_type":"HABITATION",
    "name:eng_x_preferred":[
        "Sankhala"
    ],
    "wof:name":"Sankhala",
    "wof:placetype":"locality",
    "wof:population":636
},
  "geometry": {"coordinates":[76.728889,27.516944],"type":"Point"}
}