{
  "type": "Feature",
  "properties": {
    "iso:country":"IN",
    "ks:ks_name":"Bilabari",
    "ks:ks_pop":174,
    "ks:ks_type":"VILLAGE",
    "name:eng_x_preferred":[
        "Bilabari"
    ],
    "wof:name":"Bilabari",
    "wof:placetype":"locality",
    "wof:population":174
},
  "geometry": {"coordinates":[84.307739,20.468289],"type":"Point"}
}