{
  "type": "Feature",
  "properties": {
    "iso:country":"IN",
    "ks:ks_name":"Dhapnikacha",
    "ks:ks_pop":127,
    "ks:ks_type":"HABITATION",
    "name:eng_x_preferred":[
        "Dhapnikacha"
    ],
    "wof:name":"Dhapnikacha",
    "wof:placetype":"locality",
    "wof:population":127
},
  "geometry": {"coordinates":[86.293786,22.301516],"type":"Point"}
}