{
  "type": "Feature",
  "properties": {
    "iso:country":"IN",
    "ks:ks_name":"Sara Manpur",
    "ks:ks_pop":861,
    "ks:ks_type":"VILLAGE",
    "name:eng_x_preferred":[
        "Sara Manpur"
    ],
    "wof:name":"Sara Manpur",
    "wof:placetype":"locality",
    "wof:population":861
},
  "geometry": {"coordinates":[74.24295600000001,24.147939],"type":"Point"}
}