{
  "type": "Feature",
  "properties": {
    "gn:admin1_code":"21",
    "gn:admin2_code":"394.0",
    "gn:asciiname":"Patharpunji",
    "gn:country_code":"IN",
    "gn:dem":339,
    "gn:feature_class":"P",
    "gn:feature_code":"PPL",
    "gn:name":"P\u0101tharpunji",
    "gn:population":0,
    "gn:timezone":"Asia/Kolkata",
    "iso:country":"IN",
    "ks:ks_name":"Patharapunji",
    "ks:ks_pop":146,
    "ks:ks_type":"VILLAGE",
    "name:eng_x_preferred":[
        "Patharapunji"
    ],
    "name:eng_x_variant":[
        "Patharpunji"
    ],
    "wof:name":"Patharapunji",
    "wof:placetype":"locality",
    "wof:population":146
},
  "geometry": {"coordinates":[82.44032300000001,20.751698],"type":"Point"}
}