{
  "type": "Feature",
  "properties": {
    "iso:country":"IN",
    "ks:ks_name":"Mannapara",
    "ks:ks_pop":540,
    "ks:ks_type":"HABITATION",
    "name:eng_x_preferred":[
        "Mannapara"
    ],
    "wof:name":"Mannapara",
    "wof:placetype":"locality",
    "wof:population":540
},
  "geometry": {"coordinates":[87.93997,22.547429],"type":"Point"}
}