{
  "type": "Feature",
  "properties": {
    "iso:country":"IN",
    "ks:ks_alt_nam":"mallemvandlapalli",
    "ks:ks_name":"Mallemvandlapalli",
    "ks:ks_pop":448,
    "ks:ks_type":"HABITATION",
    "name:eng_x_preferred":[
        "Mallemvandlapalli"
    ],
    "wof:name":"Mallemvandlapalli",
    "wof:placetype":"locality",
    "wof:population":448
},
  "geometry": {"coordinates":[78.044363,14.00863],"type":"Point"}
}