{
  "type": "Feature",
  "properties": {
    "iso:country":"IN",
    "ks:ks_name":"Nonoi Chakarigaon",
    "ks:ks_pop":696,
    "ks:ks_type":"HABITATION",
    "name:eng_x_preferred":[
        "Nonoi Chakarigaon"
    ],
    "wof:name":"Nonoi Chakarigaon",
    "wof:placetype":"locality",
    "wof:population":696
},
  "geometry": {"coordinates":[92.69882,26.244953],"type":"Point"}
}