{
  "type": "Feature",
  "properties": {
    "gn:admin1_code":"34.0",
    "gn:admin2_code":"211.0",
    "gn:asciiname":"Khata",
    "gn:country_code":"IN",
    "gn:dem":48,
    "gn:feature_class":"P",
    "gn:feature_code":"PPL",
    "gn:name":"Khata",
    "gn:population":0,
    "gn:timezone":"Asia/Kolkata",
    "iso:country":"IN",
    "name:bod_x_preferred":[
        "\u0f41\u0f0b\u0f56\u0f4f\u0f42\u0f66\u0f0d"
    ],
    "name:bxr_x_preferred":[
        "\u0425\u0430\u0434\u0430\u0433"
    ],
    "name:deu_x_preferred":[
        "Khata"
    ],
    "name:epo_x_preferred":[
        "Khato"
    ],
    "name:fra_x_preferred":[
        "Khata"
    ],
    "name:nld_x_preferred":[
        "Khata"
    ],
    "name:pol_x_preferred":[
        "Khata"
    ],
    "name:por_x_preferred":[
        "Khata"
    ],
    "name:rus_x_preferred":[
        "\u0425\u0430\u0434\u0430\u043a"
    ],
    "name:slk_x_preferred":[
        "Khatag"
    ],
    "name:spa_x_preferred":[
        "Khata"
    ],
    "name:tyv_x_preferred":[
        "\u041a\u0430\u0434\u0430\u043a"
    ],
    "wof:name":"Khata",
    "wof:placetype":"locality"
},
  "geometry": {"coordinates":[87.79575,26.05071],"type":"Point"}
}