{
  "type": "Feature",
  "properties": {
    "gn:admin1_code":"19.0",
    "gn:admin2_code":"569.0",
    "gn:asciiname":"Bailur",
    "gn:country_code":"IN",
    "gn:dem":32,
    "gn:feature_class":"P",
    "gn:feature_code":"PPL",
    "gn:name":"Bail\u016br",
    "gn:population":0,
    "gn:timezone":"Asia/Kolkata",
    "iso:country":"IN",
    "name:ceb_x_preferred":[
        "Bail\u016br"
    ],
    "name:swe_x_preferred":[
        "Bail\u016br"
    ],
    "name:vie_x_preferred":[
        "Bailur"
    ],
    "wof:name":"Bailur",
    "wof:placetype":"neighbourhood"
},
  "geometry": {"coordinates":[74.82011,13.62747],"type":"Point"}
}