{
  "type": "Feature",
  "properties": {
    "gn:admin1_code":"12",
    "gn:admin2_code":"18.0",
    "gn:asciiname":"Khatasar",
    "gn:country_code":"IN",
    "gn:dem":3109,
    "gn:feature_class":"P",
    "gn:feature_code":"PPL",
    "gn:name":"Khat\u0101sar",
    "gn:population":0,
    "gn:timezone":"Asia/Kolkata",
    "iso:country":"IN",
    "wof:name":"Khatasar",
    "wof:placetype":"locality"
},
  "geometry": {"coordinates":[76.13979999999999,33.29554],"type":"Point"}
}