{
  "type": "Feature",
  "properties": {
    "iso:country":"IN",
    "ks:ks_alt_nam":"D konanahalli",
    "ks:ks_name":"D Konanahalli",
    "ks:ks_pop":481,
    "ks:ks_type":"HABITATION",
    "name:eng_x_preferred":[
        "D Konanahalli"
    ],
    "wof:name":"D Konanahalli",
    "wof:placetype":"locality",
    "wof:population":481
},
  "geometry": {"coordinates":[76.64644,12.685627],"type":"Point"}
}