{
  "type": "Feature",
  "properties": {
    "iso:country":"IN",
    "ks:ks_name":"Katimada",
    "ks:ks_pop":94,
    "ks:ks_type":"HABITATION",
    "name:eng_x_preferred":[
        "Katimada"
    ],
    "wof:name":"Katimada",
    "wof:placetype":"locality",
    "wof:population":94
},
  "geometry": {"coordinates":[75.981944,12.122222],"type":"Point"}
}