{
  "type": "Feature",
  "properties": {
    "iso:country":"IN",
    "ks:ks_name":"Zari",
    "ks:ks_pop":2978,
    "ks:ks_type":"VILLAGE",
    "name:eng_x_preferred":[
        "Zari"
    ],
    "wof:name":"Zari",
    "wof:placetype":"locality",
    "wof:population":2978
},
  "geometry": {"coordinates":[73.22664399999999,20.775211],"type":"Point"}
}