{
  "type": "Feature",
  "properties": {
    "gn:admin1_code":"34.0",
    "gn:admin2_code":"203.0",
    "gn:asciiname":"Tola Nura Khap",
    "gn:country_code":"IN",
    "gn:dem":79,
    "gn:feature_class":"P",
    "gn:feature_code":"PPL",
    "gn:name":"Tola Nura Kh\u0101p",
    "gn:population":0,
    "gn:timezone":"Asia/Kolkata",
    "iso:country":"IN",
    "name:und_x_variant":[
        "Tola Nura Kh\u0101p",
        "Baswari\u0101"
    ],
    "wof:name":"Tola Nura Khap",
    "wof:placetype":"locality"
},
  "geometry": {"coordinates":[84.51047,26.77736],"type":"Point"}
}