{
  "type": "Feature",
  "properties": {
    "iso:country":"IN",
    "ks:ks_name":"Madhya Pally",
    "ks:ks_pop":1470,
    "ks:ks_type":"HABITATION",
    "name:eng_x_preferred":[
        "Madhya Pally"
    ],
    "wof:name":"Madhya Pally",
    "wof:placetype":"locality",
    "wof:population":1470
},
  "geometry": {"coordinates":[88.46229200000001,21.864884],"type":"Point"}
}