{
  "type": "Feature",
  "properties": {
    "iso:country":"IN",
    "ks:ks_name":"Agani",
    "ks:ks_pop":166,
    "ks:ks_type":"HABITATION",
    "name:eng_x_preferred":[
        "Agani"
    ],
    "wof:name":"Agani",
    "wof:placetype":"locality",
    "wof:population":166
},
  "geometry": {"coordinates":[75.612452,13.02633],"type":"Point"}
}