{
  "type": "Feature",
  "properties": {
    "iso:country":"IN",
    "ks:ks_name":"Radhakantapur",
    "ks:ks_pop":3,
    "ks:ks_type":"VILLAGE",
    "name:eng_x_preferred":[
        "Radhakantapur"
    ],
    "wof:name":"Radhakantapur",
    "wof:placetype":"locality",
    "wof:population":3
},
  "geometry": {"coordinates":[84.465414,19.32453],"type":"Point"}
}