{
  "type": "Feature",
  "properties": {
    "gn:admin1_code":"37.0",
    "gn:admin2_code":"414.0",
    "gn:asciiname":"Siwanidei",
    "gn:country_code":"IN",
    "gn:dem":635,
    "gn:feature_class":"P",
    "gn:feature_code":"PPL",
    "gn:name":"Siw\u0101nidei",
    "gn:population":0,
    "gn:timezone":"Asia/Kolkata",
    "iso:country":"IN",
    "wof:name":"Siwanidei",
    "wof:placetype":"neighbourhood"
},
  "geometry": {"coordinates":[81.79407,19.98785],"type":"Point"}
}