{
  "type": "Feature",
  "properties": {
    "iso:country":"IN",
    "ks:ks_name":"Kenduatanr",
    "ks:ks_pop":667,
    "ks:ks_type":"VILLAGE",
    "ks:ks_uagg_main":0,
    "name:eng_x_preferred":[
        "Kenduatanr"
    ],
    "wof:name":"Kenduatanr",
    "wof:placetype":"neighbourhood",
    "wof:population":667
},
  "geometry": {"coordinates":[86.631173,24.116035],"type":"Point"}
}