{
  "type": "Feature",
  "properties": {
    "iso:country":"IN",
    "ks:ks_name":"Vaisen Purwa",
    "ks:ks_pop":150,
    "ks:ks_type":"HABITATION",
    "name:eng_x_preferred":[
        "Vaisen Purwa"
    ],
    "wof:name":"Vaisen Purwa",
    "wof:placetype":"locality",
    "wof:population":150
},
  "geometry": {"coordinates":[81.72423000000001,27.04414],"type":"Point"}
}