{
  "type": "Feature",
  "properties": {
    "gn:admin1_code":"36",
    "gn:admin2_code":"173.0",
    "gn:asciiname":"Pura Dasi",
    "gn:country_code":"IN",
    "gn:dem":110,
    "gn:feature_class":"P",
    "gn:feature_code":"PPL",
    "gn:name":"Pura D\u0101si",
    "gn:population":0,
    "gn:timezone":"Asia/Kolkata",
    "iso:country":"IN",
    "wof:name":"Pura Dasi",
    "wof:placetype":"locality"
},
  "geometry": {"coordinates":[81.54983,26.05289],"type":"Point"}
}