{
  "type": "Feature",
  "properties": {
    "gn:admin1_code":"24.0",
    "gn:admin2_code":"114",
    "gn:asciiname":"Jeniyo",
    "gn:country_code":"IN",
    "gn:dem":75,
    "gn:feature_class":"P",
    "gn:feature_code":"PPL",
    "gn:name":"Jeniyo",
    "gn:population":0,
    "gn:timezone":"Asia/Kolkata",
    "iso:country":"IN",
    "name:und_x_variant":[
        "Jannio"
    ],
    "wof:name":"Jeniyo",
    "wof:placetype":"locality"
},
  "geometry": {"coordinates":[69.50464000000001,26.89244],"type":"Point"}
}