{
  "type": "Feature",
  "properties": {
    "iso:country":"IN",
    "ks:ks_alt_nam":"VIR WADI",
    "ks:ks_name":"Vir Wadi",
    "ks:ks_pop":75,
    "ks:ks_type":"HABITATION",
    "name:eng_x_preferred":[
        "Vir Wadi"
    ],
    "wof:name":"Vir Wadi",
    "wof:placetype":"locality",
    "wof:population":75
},
  "geometry": {"coordinates":[74.047207,17.055763],"type":"Point"}
}