{
  "type": "Feature",
  "properties": {
    "iso:country":"IN",
    "ks:ks_name":"Thamasadahamane",
    "ks:ks_pop":11,
    "ks:ks_type":"HABITATION",
    "name:eng_x_preferred":[
        "Thamasadahamane"
    ],
    "wof:name":"Thamasadahamane",
    "wof:placetype":"locality",
    "wof:population":11
},
  "geometry": {"coordinates":[74.987377,13.876215],"type":"Point"}
}