{
  "type": "Feature",
  "properties": {
    "iso:country":"IN",
    "ks:ks_name":"Tutki",
    "ks:ks_pop":451,
    "ks:ks_type":"VILLAGE",
    "name:eng_x_preferred":[
        "Tutki"
    ],
    "wof:name":"Tutki",
    "wof:placetype":"locality",
    "wof:population":451
},
  "geometry": {"coordinates":[85.103995,23.982377],"type":"Point"}
}