{
  "type": "Feature",
  "properties": {
    "iso:country":"IN",
    "ks:ks_name":"Hondakataguda",
    "ks:ks_pop":246,
    "ks:ks_type":"HABITATION",
    "name:eng_x_preferred":[
        "Hondakataguda"
    ],
    "wof:name":"Hondakataguda",
    "wof:placetype":"locality",
    "wof:population":246
},
  "geometry": {"coordinates":[82.58293999999999,18.976711],"type":"Point"}
}