{
  "type": "Feature",
  "properties": {
    "gn:admin1_code":"39.0",
    "gn:admin2_code":"64.0",
    "gn:asciiname":"Deolikhan",
    "gn:country_code":"IN",
    "gn:dem":1688,
    "gn:feature_class":"P",
    "gn:feature_code":"PPL",
    "gn:name":"Deolikh\u0101n",
    "gn:population":0,
    "gn:timezone":"Asia/Kolkata",
    "iso:country":"IN",
    "ks:ks_name":"Deoli Khan",
    "ks:ks_pop":427,
    "ks:ks_type":"VILLAGE",
    "name:eng_x_preferred":[
        "Deoli Khan"
    ],
    "name:eng_x_variant":[
        "Deolikhan"
    ],
    "wof:name":"Deoli Khan",
    "wof:placetype":"locality",
    "wof:population":427
},
  "geometry": {"coordinates":[79.540854,29.634216],"type":"Point"}
}