{
  "type": "Feature",
  "properties": {
    "iso:country":"IN",
    "ks:ks_name":"Chandranagar",
    "ks:ks_pop":314,
    "ks:ks_type":"HABITATION",
    "name:eng_x_preferred":[
        "Chandranagar"
    ],
    "wof:name":"Chandranagar",
    "wof:placetype":"locality",
    "wof:population":314
},
  "geometry": {"coordinates":[82.817977,21.543888],"type":"Point"}
}