{
  "type": "Feature",
  "properties": {
    "gn:admin1_code":"37",
    "gn:admin2_code":"401.0",
    "gn:asciiname":"Rajkheta",
    "gn:country_code":"IN",
    "gn:dem":460,
    "gn:feature_class":"P",
    "gn:feature_code":"PPL",
    "gn:name":"R\u0101jkheta",
    "gn:population":0,
    "gn:timezone":"Asia/Kolkata",
    "iso:country":"IN",
    "ks:ks_alt_nam":"R\u0101jkheta",
    "ks:ks_name":"Rajkheta",
    "ks:ks_pop":2143,
    "ks:ks_type":"VILLAGE",
    "ks:ks_uagg_main":0,
    "name:eng_x_preferred":[
        "Rajkheta"
    ],
    "name:eng_x_variant":[
        "R\u0101jkheta"
    ],
    "wof:name":"Rajkheta",
    "wof:placetype":"neighbourhood",
    "wof:population":2143
},
  "geometry": {"coordinates":[83.20901600000001,23.750335],"type":"Point"}
}