{
  "type": "Feature",
  "properties": {
    "iso:country":"IN",
    "ks:ks_name":"Jind Pur",
    "ks:ks_pop":181,
    "ks:ks_type":"HABITATION",
    "name:eng_x_preferred":[
        "Jind Pur"
    ],
    "wof:name":"Jind Pur",
    "wof:placetype":"locality",
    "wof:population":181
},
  "geometry": {"coordinates":[80.018215,26.663484],"type":"Point"}
}