{
  "type": "Feature",
  "properties": {
    "iso:country":"IN",
    "ks:ks_name":"Talab Fali",
    "ks:ks_pop":180,
    "ks:ks_type":"HABITATION",
    "name:eng_x_preferred":[
        "Talab Fali"
    ],
    "wof:name":"Talab Fali",
    "wof:placetype":"locality",
    "wof:population":180
},
  "geometry": {"coordinates":[72.800853,24.465172],"type":"Point"}
}