{
  "type": "Feature",
  "properties": {
    "iso:country":"IN",
    "ks:ks_name":"Baburiya Nayal",
    "ks:ks_pop":130,
    "ks:ks_type":"HABITATION",
    "name:eng_x_preferred":[
        "Baburiya Nayal"
    ],
    "wof:name":"Baburiya Nayal",
    "wof:placetype":"locality",
    "wof:population":130
},
  "geometry": {"coordinates":[79.788872,29.688747],"type":"Point"}
}