{
  "type": "Feature",
  "properties": {
    "iso:country":"IN",
    "ks:ks_name":"Golagodu",
    "ks:ks_pop":20,
    "ks:ks_type":"HABITATION",
    "name:eng_x_preferred":[
        "Golagodu"
    ],
    "wof:name":"Golagodu",
    "wof:placetype":"locality",
    "wof:population":20
},
  "geometry": {"coordinates":[75.185907,13.397608],"type":"Point"}
}