{
  "type": "Feature",
  "properties": {
    "gn:admin1_code":"25.0",
    "gn:admin2_code":"631.0",
    "gn:asciiname":"Bodanattam",
    "gn:country_code":"IN",
    "gn:dem":828,
    "gn:feature_class":"P",
    "gn:feature_code":"PPL",
    "gn:name":"B\u014ddanattam",
    "gn:population":0,
    "gn:timezone":"Asia/Kolkata",
    "iso:country":"IN",
    "wof:name":"Bodanattam",
    "wof:placetype":"neighbourhood"
},
  "geometry": {"coordinates":[77.89133,12.74959],"type":"Point"}
}