{
  "type": "Feature",
  "properties": {
    "iso:country":"IN",
    "ks:ks_name":"Harachandapur",
    "ks:ks_pop":2079,
    "ks:ks_type":"VILLAGE",
    "ks:ks_uagg_main":0,
    "name:eng_x_preferred":[
        "Harachandapur"
    ],
    "wof:name":"Harachandapur",
    "wof:placetype":"neighbourhood",
    "wof:population":2079
},
  "geometry": {"coordinates":[87.817021,25.156271],"type":"Point"}
}