{
  "type": "Feature",
  "properties": {
    "iso:country":"IN",
    "ks:ks_name":"Jamhati Thantola",
    "ks:ks_pop":315,
    "ks:ks_type":"HABITATION",
    "name:eng_x_preferred":[
        "Jamhati Thantola"
    ],
    "wof:name":"Jamhati Thantola",
    "wof:placetype":"locality",
    "wof:population":315
},
  "geometry": {"coordinates":[83.681119,23.232234],"type":"Point"}
}