{
  "type": "Feature",
  "properties": {
    "iso:country":"IN",
    "ks:ks_alt_nam":"maldabasti",
    "ks:ks_name":"Maldabasti",
    "ks:ks_pop":355,
    "ks:ks_type":"HABITATION",
    "name:eng_x_preferred":[
        "Maldabasti"
    ],
    "wof:name":"Maldabasti",
    "wof:placetype":"locality",
    "wof:population":355
},
  "geometry": {"coordinates":[85.225661,21.886469],"type":"Point"}
}