{
  "type": "Feature",
  "properties": {
    "iso:country":"IN",
    "ks:ks_name":"Pure Ganeghar",
    "ks:ks_pop":127,
    "ks:ks_type":"HABITATION",
    "name:eng_x_preferred":[
        "Pure Ganeghar"
    ],
    "wof:name":"Pure Ganeghar",
    "wof:placetype":"locality",
    "wof:population":127
},
  "geometry": {"coordinates":[82.416342,26.846555],"type":"Point"}
}