{
  "type": "Feature",
  "properties": {
    "gn:admin1_code":"11.0",
    "gn:admin2_code":"23.0",
    "gn:asciiname":"Horha",
    "gn:country_code":"IN",
    "gn:dem":944,
    "gn:feature_class":"P",
    "gn:feature_code":"PPL",
    "gn:name":"Horha",
    "gn:population":0,
    "gn:timezone":"Asia/Kolkata",
    "iso:country":"IN",
    "wof:name":"Horha",
    "wof:placetype":"locality"
},
  "geometry": {"coordinates":[75.95403,32.43584],"type":"Point"}
}