{
  "type": "Feature",
  "properties": {
    "iso:country":"IN",
    "ks:ks_alt_nam":"Kohani ryt karondi mal",
    "ks:ks_name":"Kohani Ryt Karondi Mal",
    "ks:ks_pop":576,
    "ks:ks_type":"HABITATION",
    "name:eng_x_preferred":[
        "Kohani Ryt Karondi Mal"
    ],
    "wof:name":"Kohani Ryt Karondi Mal",
    "wof:placetype":"locality",
    "wof:population":576
},
  "geometry": {"coordinates":[80.565915,23.199192],"type":"Point"}
}