{
  "type": "Feature",
  "properties": {
    "iso:country":"IN",
    "ks:ks_name":"Kikirpara",
    "ks:ks_pop":188,
    "ks:ks_type":"HABITATION",
    "name:eng_x_preferred":[
        "Kikirpara"
    ],
    "wof:name":"Kikirpara",
    "wof:placetype":"locality",
    "wof:population":188
},
  "geometry": {"coordinates":[81.34166500000001,18.504491],"type":"Point"}
}