{
  "type": "Feature",
  "properties": {
    "iso:country":"IN",
    "ks:ks_alt_nam":"Jogid\u0101ru",
    "ks:ks_name":"Jogidaru",
    "ks:ks_pop":380,
    "ks:ks_type":"VILLAGE",
    "name:eng_x_preferred":[
        "Jogidaru"
    ],
    "name:eng_x_variant":[
        "Jogid\u0101ru"
    ],
    "wof:name":"Jogidaru",
    "wof:placetype":"locality",
    "wof:population":380
},
  "geometry": {"coordinates":[85.671605,22.512463],"type":"Point"}
}