{
  "type": "Feature",
  "properties": {
    "iso:country":"IN",
    "ks:ks_name":"Lakshmanpur",
    "ks:ks_pop":137,
    "ks:ks_type":"HABITATION",
    "name:eng_x_preferred":[
        "Lakshmanpur"
    ],
    "wof:name":"Lakshmanpur",
    "wof:placetype":"locality",
    "wof:population":137
},
  "geometry": {"coordinates":[78.20756299999999,27.743566],"type":"Point"}
}