{
  "type": "Feature",
  "properties": {
    "iso:country":"IN",
    "name:eng_x_preferred":[
        "Warje"
    ],
    "wof:name":"Warje",
    "wof:placetype":"neighbourhood"
},
  "geometry": {"coordinates":[73.80003987096676,18.48277909974816],"type":"Point"}
}