{
  "type": "Feature",
  "properties": {
    "iso:country":"IN",
    "name:ara_x_preferred":[
        "\u0648\u0627\u0631\u062c\u064a"
    ],
    "name:ben_bn_x_preferred":[
        "\u0993\u09df\u09be\u09b0\u099c\u09c7"
    ],
    "name:ben_in_x_preferred":[
        "\u0993\u09df\u09be\u09b0\u099c\u09c7"
    ],
    "name:eng_x_preferred":[
        "Warje"
    ],
    "name:guj_x_preferred":[
        "\u0ab5\u0ab0\u0acd\u0a9c\u0ac7"
    ],
    "name:hin_x_preferred":[
        "\u0935\u0930\u094d\u091c\u0947"
    ],
    "name:kan_x_preferred":[
        "\u0cb5\u0cb0\u0ccd\u0c9c\u0cc6"
    ],
    "name:mal_x_preferred":[
        "\u0d35\u0d3e\u0d7c\u0d1c\u0d46"
    ],
    "name:mar_x_preferred":[
        "\u0935\u093e\u0930\u091c\u0947"
    ],
    "name:pan_x_preferred":[
        "\u0a35\u0a30\u0a1c\u0a48"
    ],
    "name:tam_x_preferred":[
        "\u0bb5\u0bb0\u0bcd\u0b9c\u0bc6"
    ],
    "name:tel_x_preferred":[
        "\u0c35\u0c3e\u0c30\u0c4d\u0c1c\u0c46"
    ],
    "name:urd_x_preferred":[
        "\u0648\u0631\u062c\u06d2"
    ],
    "wof:name":"Warje",
    "wof:placetype":"neighbourhood"
},
  "geometry": {"coordinates":[73.80003987096676,18.48277909974816],"type":"Point"}
}