{
  "type": "Feature",
  "properties": {
    "iso:country":"IN",
    "ks:ks_alt_nam":"CHHOTAKARM",
    "ks:ks_name":"Chhotakarm",
    "ks:ks_pop":189,
    "ks:ks_type":"HABITATION",
    "name:eng_x_preferred":[
        "Chhotakarm"
    ],
    "wof:name":"Chhotakarm",
    "wof:placetype":"locality",
    "wof:population":189
},
  "geometry": {"coordinates":[86.553713,24.561077],"type":"Point"}
}