{
  "type": "Feature",
  "properties": {
    "iso:country":"IN",
    "ks:ks_name":"Kundacheri",
    "ks:ks_pop":497,
    "ks:ks_type":"VILLAGE",
    "name:eng_x_preferred":[
        "Kundacheri"
    ],
    "wof:name":"Kundacheri",
    "wof:placetype":"locality",
    "wof:population":497
},
  "geometry": {"coordinates":[75.57351199999999,12.395761],"type":"Point"}
}