{
  "type": "Feature",
  "properties": {
    "iso:country":"IN",
    "ks:ks_name":"Bhom Sagar",
    "ks:ks_pop":1365,
    "ks:ks_type":"VILLAGE",
    "name:eng_x_preferred":[
        "Bhom Sagar"
    ],
    "wof:name":"Bhom Sagar",
    "wof:placetype":"locality",
    "wof:population":1365
},
  "geometry": {"coordinates":[72.094633,26.385447],"type":"Point"}
}