{
  "type": "Feature",
  "properties": {
    "gn:admin1_code":"38.0",
    "gn:admin2_code":"351.0",
    "gn:asciiname":"Siripur",
    "gn:country_code":"IN",
    "gn:dem":78,
    "gn:feature_class":"P",
    "gn:feature_code":"PPL",
    "gn:name":"Siripur",
    "gn:population":0,
    "gn:timezone":"Asia/Kolkata",
    "iso:country":"IN",
    "ks:ks_name":"Siripur",
    "ks:ks_pop":329,
    "ks:ks_type":"VILLAGE",
    "ks:ks_uagg_main":0,
    "name:eng_x_preferred":[
        "Siripur"
    ],
    "wof:name":"Siripur",
    "wof:placetype":"neighbourhood",
    "wof:population":329
},
  "geometry": {"coordinates":[87.24260599999999,24.923286],"type":"Point"}
}