{
  "type": "Feature",
  "properties": {
    "gn:admin1_code":"36.0",
    "gn:admin2_code":"150.0",
    "gn:asciiname":"Malhpur",
    "gn:country_code":"IN",
    "gn:dem":184,
    "gn:feature_class":"P",
    "gn:feature_code":"PPL",
    "gn:name":"Malhpur",
    "gn:population":0,
    "gn:timezone":"Asia/Kolkata",
    "iso:country":"IN",
    "ks:ks_name":"Malhpur",
    "ks:ks_type":"VILLAGE",
    "name:eng_x_preferred":[
        "Malhpur"
    ],
    "wof:name":"Malhpur",
    "wof:placetype":"locality"
},
  "geometry": {"coordinates":[79.48790200000001,28.551641],"type":"Point"}
}