{
  "type": "Feature",
  "properties": {
    "iso:country":"IN",
    "ks:ks_name":"Ujaria",
    "ks:ks_pop":0,
    "ks:ks_type":"VILLAGE",
    "name:eng_x_preferred":[
        "Ujaria"
    ],
    "wof:name":"Ujaria",
    "wof:placetype":"locality",
    "wof:population":0
},
  "geometry": {"coordinates":[83.67731000000001,24.993739],"type":"Point"}
}