{
  "type": "Feature",
  "properties": {
    "iso:country":"IN",
    "ks:ks_alt_nam":"BRAHMAN TOLA",
    "ks:ks_name":"Brahman Tola",
    "ks:ks_pop":382,
    "ks:ks_type":"HABITATION",
    "name:eng_x_preferred":[
        "Brahman Tola"
    ],
    "wof:name":"Brahman Tola",
    "wof:placetype":"locality",
    "wof:population":382
},
  "geometry": {"coordinates":[83.927695,26.460407],"type":"Point"}
}