{
  "type": "Feature",
  "properties": {
    "gn:admin1_code":"39.0",
    "gn:admin2_code":"57.0",
    "gn:asciiname":"Juwagwar",
    "gn:country_code":"IN",
    "gn:dem":2129,
    "gn:feature_class":"P",
    "gn:feature_code":"PPL",
    "gn:name":"J\u016bw\u0101gw\u0101r",
    "gn:population":0,
    "gn:timezone":"Asia/Kolkata",
    "iso:country":"IN",
    "ks:ks_alt_nam":"J\u016bw\u0101gw\u0101r",
    "ks:ks_name":"Juwagwar",
    "ks:ks_pop":59,
    "ks:ks_type":"VILLAGE",
    "name:eng_x_preferred":[
        "Juwagwar"
    ],
    "name:eng_x_variant":[
        "J\u016bw\u0101gw\u0101r"
    ],
    "wof:name":"Juwagwar",
    "wof:placetype":"locality",
    "wof:population":59
},
  "geometry": {"coordinates":[79.674702,30.493683],"type":"Point"}
}