{
  "type": "Feature",
  "properties": {
    "gn:admin1_code":"39.0",
    "gn:admin2_code":"57.0",
    "gn:asciiname":"Juwagwar",
    "gn:country_code":"IN",
    "gn:dem":2129,
    "gn:feature_class":"P",
    "gn:feature_code":"PPL",
    "gn:name":"J\u016bw\u0101gw\u0101r",
    "gn:population":0,
    "gn:timezone":"Asia/Kolkata",
    "iso:country":"IN",
    "wof:name":"Juwagwar",
    "wof:placetype":"locality"
},
  "geometry": {"coordinates":[79.6743,30.4944],"type":"Point"}
}