{
  "type": "Feature",
  "properties": {
    "iso:country":"IN",
    "ks:ks_alt_nam":"adijabavalucolony",
    "ks:ks_name":"Adijabavalucolony",
    "ks:ks_pop":249,
    "ks:ks_type":"HABITATION",
    "name:eng_x_preferred":[
        "Adijabavalucolony"
    ],
    "wof:name":"Adijabavalucolony",
    "wof:placetype":"locality",
    "wof:population":249
},
  "geometry": {"coordinates":[76.32458200000001,12.543082],"type":"Point"}
}