{
  "type": "Feature",
  "properties": {
    "iso:country":"IN",
    "ks:ks_name":"Bhikhoa",
    "ks:ks_pop":606,
    "ks:ks_type":"VILLAGE",
    "ks:ks_uagg_main":0,
    "name:eng_x_preferred":[
        "Bhikhoa"
    ],
    "wof:name":"Bhikhoa",
    "wof:placetype":"locality",
    "wof:population":606
},
  "geometry": {"coordinates":[86.71343299999999,24.460641],"type":"Point"}
}