{
  "type": "Feature",
  "properties": {
    "iso:country":"IN",
    "ks:ks_name":"Paharpur",
    "ks:ks_pop":0,
    "ks:ks_type":"VILLAGE",
    "name:eng_x_preferred":[
        "Paharpur"
    ],
    "wof:name":"Paharpur",
    "wof:placetype":"locality",
    "wof:population":0
},
  "geometry": {"coordinates":[85.215569,25.750387],"type":"Point"}
}