{
  "type": "Feature",
  "properties": {
    "iso:country":"IN",
    "ks:ks_name":"Khemanda",
    "ks:ks_pop":50,
    "ks:ks_type":"VILLAGE",
    "name:eng_x_preferred":[
        "Khemanda"
    ],
    "wof:name":"Khemanda",
    "wof:placetype":"locality",
    "wof:population":50
},
  "geometry": {"coordinates":[84.608223,19.259153],"type":"Point"}
}