{
  "type": "Feature",
  "properties": {
    "gn:admin1_code":"11.0",
    "gn:admin2_code":"27.0",
    "gn:asciiname":"Najjun",
    "gn:country_code":"IN",
    "gn:dem":2103,
    "gn:feature_class":"P",
    "gn:feature_code":"PPL",
    "gn:name":"Najj\u016bn",
    "gn:population":0,
    "gn:timezone":"Asia/Kolkata",
    "iso:country":"IN",
    "wof:name":"Najjun",
    "wof:placetype":"locality"
},
  "geometry": {"coordinates":[77.02579,31.49451],"type":"Point"}
}