{
  "type": "Feature",
  "properties": {
    "iso:country":"IN",
    "ks:ks_name":"Rengapod",
    "ks:ks_pop":52,
    "ks:ks_type":"HABITATION",
    "name:eng_x_preferred":[
        "Rengapod"
    ],
    "wof:name":"Rengapod",
    "wof:placetype":"locality",
    "wof:population":52
},
  "geometry": {"coordinates":[78.665218,19.926433],"type":"Point"}
}