{
  "type": "Feature",
  "properties": {
    "iso:country":"IN",
    "ks:ks_name":"Satera",
    "ks:ks_pop":583,
    "ks:ks_type":"VILLAGE",
    "name:eng_x_preferred":[
        "Satera"
    ],
    "wof:name":"Satera",
    "wof:placetype":"locality",
    "wof:population":583
},
  "geometry": {"coordinates":[78.993993,30.33202],"type":"Point"}
}