{
  "type": "Feature",
  "properties": {
    "gn:admin1_code":"19.0",
    "gn:admin2_code":"568.0",
    "gn:asciiname":"Sigalemane",
    "gn:country_code":"IN",
    "gn:dem":641,
    "gn:feature_class":"P",
    "gn:feature_code":"PPL",
    "gn:name":"Sigalemane",
    "gn:population":0,
    "gn:timezone":"Asia/Kolkata",
    "iso:country":"IN",
    "ks:ks_name":"Gigalemane",
    "ks:ks_pop":273,
    "ks:ks_type":"HABITATION",
    "name:eng_x_preferred":[
        "Gigalemane"
    ],
    "name:eng_x_variant":[
        "Sigalemane"
    ],
    "wof:name":"Gigalemane",
    "wof:placetype":"locality",
    "wof:population":273
},
  "geometry": {"coordinates":[75.130261,14.159342],"type":"Point"}
}