{
  "type": "Feature",
  "properties": {
    "iso:country":"IN",
    "ks:ks_alt_nam":"MALHAUTI",
    "ks:ks_name":"Malhauti",
    "ks:ks_pop":1147,
    "ks:ks_type":"HABITATION",
    "name:eng_x_preferred":[
        "Malhauti"
    ],
    "wof:name":"Malhauti",
    "wof:placetype":"locality",
    "wof:population":1147
},
  "geometry": {"coordinates":[82.027601,26.403088],"type":"Point"}
}