{
  "type": "Feature",
  "properties": {
    "gn:admin1_code":"21.0",
    "gn:admin2_code":"384.0",
    "gn:asciiname":"Kendupali",
    "gn:country_code":"IN",
    "gn:dem":77,
    "gn:feature_class":"P",
    "gn:feature_code":"PPL",
    "gn:name":"Kendupali",
    "gn:population":0,
    "gn:timezone":"Asia/Kolkata",
    "iso:country":"IN",
    "wof:name":"Kendupali",
    "wof:placetype":"locality"
},
  "geometry": {"coordinates":[85.1931,20.9056],"type":"Point"}
}