{
  "type": "Feature",
  "properties": {
    "iso:country":"IN",
    "ks:ks_alt_nam":"santhanur kottai",
    "ks:ks_name":"Santhanur Kottai",
    "ks:ks_pop":195,
    "ks:ks_type":"HABITATION",
    "ks:ks_uagg_main":0,
    "name:eng_x_preferred":[
        "Santhanur Kottai"
    ],
    "wof:name":"Santhanur Kottai",
    "wof:placetype":"neighbourhood",
    "wof:population":195
},
  "geometry": {"coordinates":[78.184302,12.108727],"type":"Point"}
}