{
  "type": "Feature",
  "properties": {
    "iso:country":"IN",
    "ks:ks_name":"Seeniyapuram",
    "ks:ks_pop":506,
    "ks:ks_type":"HABITATION",
    "ks:ks_uagg_main":0,
    "name:eng_x_preferred":[
        "Seeniyapuram"
    ],
    "wof:name":"Seeniyapuram",
    "wof:placetype":"neighbourhood",
    "wof:population":506
},
  "geometry": {"coordinates":[77.384117,8.817757],"type":"Point"}
}