{
  "type": "Feature",
  "properties": {
    "iso:country":"IN",
    "ks:ks_name":"Sumari",
    "ks:ks_pop":75,
    "ks:ks_type":"VILLAGE",
    "name:eng_x_preferred":[
        "Sumari"
    ],
    "wof:name":"Sumari",
    "wof:placetype":"locality",
    "wof:population":75
},
  "geometry": {"coordinates":[78.737695,30.307774],"type":"Point"}
}