{
  "type": "Feature",
  "properties": {
    "iso:country":"IN",
    "ks:ks_name":"Turibhita",
    "ks:ks_pop":931,
    "ks:ks_type":"VILLAGE",
    "name:eng_x_preferred":[
        "Turibhita"
    ],
    "wof:name":"Turibhita",
    "wof:placetype":"locality",
    "wof:population":931
},
  "geometry": {"coordinates":[88.327637,26.664786],"type":"Point"}
}