{
  "type": "Feature",
  "properties": {
    "iso:country":"IN",
    "ks:ks_name":"Uramg Tilla",
    "ks:ks_pop":524,
    "ks:ks_type":"HABITATION",
    "name:eng_x_preferred":[
        "Uramg Tilla"
    ],
    "wof:name":"Uramg Tilla",
    "wof:placetype":"locality",
    "wof:population":524
},
  "geometry": {"coordinates":[92.027371,24.226562],"type":"Point"}
}