{
  "type": "Feature",
  "properties": {
    "iso:country":"IN",
    "ks:ks_name":"Konkay",
    "ks:ks_pop":28,
    "ks:ks_type":"HABITATION",
    "name:eng_x_preferred":[
        "Konkay"
    ],
    "wof:name":"Konkay",
    "wof:placetype":"locality",
    "wof:population":28
},
  "geometry": {"coordinates":[74.962276,13.261572],"type":"Point"}
}