{
  "type": "Feature",
  "properties": {
    "gn:admin1_code":"35",
    "gn:admin2_code":"425.0",
    "gn:asciiname":"Thane Pukhra",
    "gn:country_code":"IN",
    "gn:dem":144,
    "gn:feature_class":"P",
    "gn:feature_code":"PPL",
    "gn:name":"Th\u0101ne Pukhra",
    "gn:population":0,
    "gn:timezone":"Asia/Kolkata",
    "iso:country":"IN",
    "name:eng_x_preferred":[
        "Th\u0101ne Pukhra"
    ],
    "wof:name":"Thane Pukhra",
    "wof:placetype":"neighbourhood"
},
  "geometry": {"coordinates":[80.23407,25.27244],"type":"Point"}
}