{
  "type": "Feature",
  "properties": {
    "iso:country":"IN",
    "ks:ks_name":"Chokhawada",
    "ks:ks_pop":3473,
    "ks:ks_type":"VILLAGE",
    "name:eng_x_preferred":[
        "Chokhawada"
    ],
    "wof:name":"Chokhawada",
    "wof:placetype":"locality",
    "wof:population":3473
},
  "geometry": {"coordinates":[74.389026,23.013201],"type":"Point"}
}