{
  "type": "Feature",
  "properties": {
    "gn:admin1_code":"34",
    "gn:admin2_code":"218.0",
    "gn:asciiname":"Majhaulia",
    "gn:country_code":"IN",
    "gn:dem":69,
    "gn:feature_class":"P",
    "gn:feature_code":"PPL",
    "gn:name":"Majhaulia",
    "gn:population":0,
    "gn:timezone":"Asia/Kolkata",
    "iso:country":"IN",
    "ks:ks_name":"Majhaulia",
    "ks:ks_pop":911,
    "ks:ks_type":"VILLAGE",
    "ks:ks_uagg_main":0,
    "name:eng_x_preferred":[
        "Majhaulia"
    ],
    "wof:name":"Majhaulia",
    "wof:placetype":"neighbourhood",
    "wof:population":911
},
  "geometry": {"coordinates":[84.434281,26.218405],"type":"Point"}
}