{
  "type": "Feature",
  "properties": {
    "gn:admin1_code":"39",
    "gn:admin2_code":"56.0",
    "gn:asciiname":"Paoli",
    "gn:country_code":"IN",
    "gn:dem":1835,
    "gn:feature_class":"P",
    "gn:feature_code":"PPL",
    "gn:name":"P\u0101oli",
    "gn:population":0,
    "gn:timezone":"Asia/Kolkata",
    "iso:country":"IN",
    "name:cat_x_preferred":[
        "Paoli"
    ],
    "name:ceb_x_preferred":[
        "Paoli"
    ],
    "name:deu_x_preferred":[
        "Paoli"
    ],
    "name:fra_x_preferred":[
        "Paoli"
    ],
    "name:ita_x_preferred":[
        "Paoli"
    ],
    "name:kor_x_preferred":[
        "\ud30c\uc62c\ub9ac"
    ],
    "name:lav_x_preferred":[
        "Paoli"
    ],
    "name:nld_x_preferred":[
        "Paoli"
    ],
    "name:pol_x_preferred":[
        "Paoli"
    ],
    "name:por_x_preferred":[
        "Paoli"
    ],
    "name:rus_x_preferred":[
        "\u041f\u0430\u043e\u043b\u0438"
    ],
    "name:srp_x_preferred":[
        "\u041f\u0430\u043e\u043b\u0438"
    ],
    "name:swe_x_preferred":[
        "Paoli"
    ],
    "name:ukr_x_preferred":[
        "\u041f\u0430\u043e\u043b\u0456"
    ],
    "name:vol_x_preferred":[
        "Paoli"
    ],
    "wof:name":"Paoli",
    "wof:placetype":"locality"
},
  "geometry": {"coordinates":[77.85630999999999,30.98955],"type":"Point"}
}