{
  "type": "Feature",
  "properties": {
    "iso:country":"IN",
    "ks:ks_name":"Ghograpura",
    "ks:ks_pop":847,
    "ks:ks_type":"VILLAGE",
    "name:eng_x_preferred":[
        "Ghograpura"
    ],
    "wof:name":"Ghograpura",
    "wof:placetype":"locality",
    "wof:population":847
},
  "geometry": {"coordinates":[77.852277,22.434883],"type":"Point"}
}