{
  "type": "Feature",
  "properties": {
    "iso:country":"IN",
    "ks:ks_name":"Repura Urf Rampur Sikandar",
    "ks:ks_pop":511,
    "ks:ks_type":"VILLAGE",
    "name:eng_x_preferred":[
        "Repura Urf Rampur Sikandar"
    ],
    "wof:name":"Repura Urf Rampur Sikandar",
    "wof:placetype":"locality",
    "wof:population":511
},
  "geometry": {"coordinates":[85.525161,25.845434],"type":"Point"}
}