{
  "type": "Feature",
  "properties": {
    "gn:admin1_code":"19.0",
    "gn:admin2_code":"569.0",
    "gn:asciiname":"Manigere",
    "gn:country_code":"IN",
    "gn:dem":20,
    "gn:feature_class":"P",
    "gn:feature_code":"PPL",
    "gn:name":"Maniger\u0113",
    "gn:population":0,
    "gn:timezone":"Asia/Kolkata",
    "iso:country":"IN",
    "ks:ks_name":"Manigeri",
    "ks:ks_pop":144,
    "ks:ks_type":"HABITATION",
    "name:eng_x_preferred":[
        "Manigeri"
    ],
    "name:eng_x_variant":[
        "Manigere"
    ],
    "wof:name":"Manigeri",
    "wof:placetype":"locality",
    "wof:population":144
},
  "geometry": {"coordinates":[74.83719600000001,13.577603],"type":"Point"}
}