{
  "type": "Feature",
  "properties": {
    "gn:admin1_code":"38",
    "gn:admin2_code":"358.0",
    "gn:asciiname":"Kothimahua",
    "gn:country_code":"IN",
    "gn:dem":308,
    "gn:feature_class":"P",
    "gn:feature_code":"PPL",
    "gn:name":"Kothimahu\u0101",
    "gn:population":0,
    "gn:timezone":"Asia/Kolkata",
    "iso:country":"IN",
    "wof:name":"Kothimahua",
    "wof:placetype":"locality"
},
  "geometry": {"coordinates":[83.91709,23.95676],"type":"Point"}
}