{
  "type": "Feature",
  "properties": {
    "iso:country":"IN",
    "ks:ks_name":"Bansdiha",
    "ks:ks_pop":0,
    "ks:ks_type":"VILLAGE",
    "name:eng_x_preferred":[
        "Bansdiha"
    ],
    "wof:name":"Bansdiha",
    "wof:placetype":"locality",
    "wof:population":0
},
  "geometry": {"coordinates":[87.251346,22.869096],"type":"Point"}
}