{
  "type": "Feature",
  "properties": {
    "iso:country":"IN",
    "ks:ks_alt_nam":"pujdev singh ka pura",
    "ks:ks_name":"Pujdev Singh Ka Pura",
    "ks:ks_pop":294,
    "ks:ks_type":"HABITATION",
    "name:eng_x_preferred":[
        "Pujdev Singh Ka Pura"
    ],
    "wof:name":"Pujdev Singh Ka Pura",
    "wof:placetype":"locality",
    "wof:population":294
},
  "geometry": {"coordinates":[83.821506,26.026998],"type":"Point"}
}