{
  "type": "Feature",
  "properties": {
    "iso:country":"IN",
    "ks:ks_name":"Badapatna",
    "ks:ks_pop":710,
    "ks:ks_type":"VILLAGE",
    "ks:ks_uagg_main":0,
    "name:eng_x_preferred":[
        "Badapatna"
    ],
    "wof:name":"Badapatna",
    "wof:placetype":"neighbourhood",
    "wof:population":710
},
  "geometry": {"coordinates":[85.52683500000001,19.984094],"type":"Point"}
}