{
  "type": "Feature",
  "properties": {
    "gn:admin1_code":"12",
    "gn:admin2_code":"3.0",
    "gn:asciiname":"Lazing",
    "gn:country_code":"IN",
    "gn:dem":3831,
    "gn:feature_class":"P",
    "gn:feature_code":"PPL",
    "gn:name":"Lazing",
    "gn:population":0,
    "gn:timezone":"Asia/Kolkata",
    "iso:country":"IN",
    "wof:name":"Lazing",
    "wof:placetype":"locality"
},
  "geometry": {"coordinates":[77.30382,34.29133],"type":"Point"}
}