{
  "type": "Feature",
  "properties": {
    "gn:admin1_code":"11",
    "gn:admin2_code":"27.0",
    "gn:asciiname":"Patti",
    "gn:country_code":"IN",
    "gn:dem":850,
    "gn:feature_class":"P",
    "gn:feature_code":"PPL",
    "gn:name":"Patti",
    "gn:population":0,
    "gn:timezone":"Asia/Kolkata",
    "iso:country":"IN",
    "wof:name":"Patti",
    "wof:placetype":"locality"
},
  "geometry": {"coordinates":[76.80716,31.93069],"type":"Point"}
}