{
  "type": "Feature",
  "properties": {
    "iso:country":"IN",
    "ks:ks_name":"Kuntikana",
    "ks:ks_pop":167,
    "ks:ks_type":"HABITATION",
    "name:eng_x_preferred":[
        "Kuntikana"
    ],
    "wof:name":"Kuntikana",
    "wof:placetype":"locality",
    "wof:population":167
},
  "geometry": {"coordinates":[75.586845,12.497149],"type":"Point"}
}