{
  "type": "Feature",
  "properties": {
    "iso:country":"IN",
    "ks:ks_name":"Kharti",
    "ks:ks_pop":0,
    "ks:ks_type":"VILLAGE",
    "name:eng_x_preferred":[
        "Kharti"
    ],
    "wof:name":"Kharti",
    "wof:placetype":"locality",
    "wof:population":0
},
  "geometry": {"coordinates":[86.278301,24.249977],"type":"Point"}
}