{
  "type": "Feature",
  "properties": {
    "gn:admin1_code":"21",
    "gn:admin2_code":"371.0",
    "gn:asciiname":"Barpali",
    "gn:country_code":"IN",
    "gn:dem":208,
    "gn:feature_class":"P",
    "gn:feature_code":"PPL",
    "gn:name":"Barp\u0101li",
    "gn:population":0,
    "gn:timezone":"Asia/Kolkata",
    "iso:country":"IN",
    "ks:ks_alt_nam":"Barp\u0101li",
    "ks:ks_name":"Barpali",
    "ks:ks_pop":873,
    "ks:ks_type":"VILLAGE",
    "name:eng_x_preferred":[
        "Barpali"
    ],
    "name:eng_x_variant":[
        "Barp\u0101li"
    ],
    "wof:name":"Barpali",
    "wof:placetype":"locality",
    "wof:population":873
},
  "geometry": {"coordinates":[83.927475,21.903192],"type":"Point"}
}