{
  "type": "Feature",
  "properties": {
    "gn:admin1_code":"37",
    "gn:admin2_code":"413.0",
    "gn:asciiname":"Ghotulmunda",
    "gn:country_code":"IN",
    "gn:dem":375,
    "gn:feature_class":"P",
    "gn:feature_code":"PPL",
    "gn:name":"Ghotulmunda",
    "gn:population":0,
    "gn:timezone":"Asia/Kolkata",
    "iso:country":"IN",
    "ks:ks_name":"Ghotulmunda",
    "ks:ks_pop":380,
    "ks:ks_type":"VILLAGE",
    "name:eng_x_preferred":[
        "Ghotulmunda"
    ],
    "wof:name":"Ghotulmunda",
    "wof:placetype":"locality",
    "wof:population":380
},
  "geometry": {"coordinates":[80.933346,20.371627],"type":"Point"}
}