{
  "type": "Feature",
  "properties": {
    "iso:country":"IN",
    "ks:ks_name":"Mailinkad",
    "ks:ks_pop":832,
    "ks:ks_type":"HABITATION",
    "name:eng_x_preferred":[
        "Mailinkad"
    ],
    "wof:name":"Mailinkad",
    "wof:placetype":"locality",
    "wof:population":832
},
  "geometry": {"coordinates":[75.736844,11.775819],"type":"Point"}
}