{
  "type": "Feature",
  "properties": {
    "iso:country":"IN",
    "ks:ks_name":"Kandali Pathar",
    "ks:ks_pop":202,
    "ks:ks_type":"VILLAGE",
    "name:eng_x_preferred":[
        "Kandali Pathar"
    ],
    "wof:name":"Kandali Pathar",
    "wof:placetype":"locality",
    "wof:population":202
},
  "geometry": {"coordinates":[94.12860499999999,27.106071],"type":"Point"}
}