{
  "type": "Feature",
  "properties": {
    "iso:country":"IN",
    "ks:ks_name":"Kothar",
    "ks:ks_pop":1125,
    "ks:ks_type":"VILLAGE",
    "name:eng_x_preferred":[
        "Kothar"
    ],
    "wof:name":"Kothar",
    "wof:placetype":"locality",
    "wof:population":1125
},
  "geometry": {"coordinates":[78.599498,22.077297],"type":"Point"}
}