{
  "type": "Feature",
  "properties": {
    "iso:country":"IN",
    "ks:ks_alt_nam":"wagadpada",
    "ks:ks_name":"Wagadpada",
    "ks:ks_pop":10,
    "ks:ks_type":"HABITATION",
    "name:eng_x_preferred":[
        "Wagadpada"
    ],
    "wof:name":"Wagadpada",
    "wof:placetype":"locality",
    "wof:population":10
},
  "geometry": {"coordinates":[73.218475,19.643114],"type":"Point"}
}