{
  "type": "Feature",
  "properties": {
    "iso:country":"IN",
    "ks:ks_name":"Dighit",
    "ks:ks_pop":193,
    "ks:ks_type":"VILLAGE",
    "name:eng_x_preferred":[
        "Dighit"
    ],
    "wof:name":"Dighit",
    "wof:placetype":"locality",
    "wof:population":193
},
  "geometry": {"coordinates":[86.940026,23.596096],"type":"Point"}
}