{
  "type": "Feature",
  "properties": {
    "gn:admin1_code":"9.0",
    "gn:admin2_code":"475",
    "gn:asciiname":"Gundiali",
    "gn:country_code":"IN",
    "gn:dem":87,
    "gn:feature_class":"P",
    "gn:feature_code":"PPL",
    "gn:name":"Gundi\u0101li",
    "gn:population":0,
    "gn:timezone":"Asia/Kolkata",
    "iso:country":"IN",
    "name:cat_x_preferred":[
        "Gundiali"
    ],
    "wof:name":"Gundiali",
    "wof:placetype":"locality"
},
  "geometry": {"coordinates":[71.61598000000002,22.61025],"type":"Point"}
}