{
  "type": "Feature",
  "properties": {
    "iso:country":"IN",
    "ks:ks_name":"Deogaon",
    "ks:ks_pop":30,
    "ks:ks_type":"HABITATION",
    "name:eng_x_preferred":[
        "Deogaon"
    ],
    "wof:name":"Deogaon",
    "wof:placetype":"locality",
    "wof:population":30
},
  "geometry": {"coordinates":[82.624246,21.073772],"type":"Point"}
}