{
  "type": "Feature",
  "properties": {
    "iso:country":"IN",
    "ks:ks_alt_nam":"PURE BALDI SUBEDAR",
    "ks:ks_name":"Pure Baldi Subedar",
    "ks:ks_pop":94,
    "ks:ks_type":"HABITATION",
    "ks:ks_uagg_main":0,
    "name:eng_x_preferred":[
        "Pure Baldi Subedar"
    ],
    "wof:name":"Pure Baldi Subedar",
    "wof:placetype":"neighbourhood",
    "wof:population":94
},
  "geometry": {"coordinates":[81.885246,26.530115],"type":"Point"}
}