{
  "type": "Feature",
  "properties": {
    "iso:country":"IN",
    "ks:ks_name":"Yenkabettu",
    "ks:ks_pop":75,
    "ks:ks_type":"HABITATION",
    "name:eng_x_preferred":[
        "Yenkabettu"
    ],
    "wof:name":"Yenkabettu",
    "wof:placetype":"locality",
    "wof:population":75
},
  "geometry": {"coordinates":[74.851668,13.477306],"type":"Point"}
}