{
  "type": "Feature",
  "properties": {
    "iso:country":"IN",
    "ks:ks_alt_nam":"MIRJEVASTI",
    "ks:ks_name":"Mirjevasti",
    "ks:ks_pop":160,
    "ks:ks_type":"HABITATION",
    "name:eng_x_preferred":[
        "Mirjevasti"
    ],
    "wof:name":"Mirjevasti",
    "wof:placetype":"locality",
    "wof:population":160
},
  "geometry": {"coordinates":[74.82602199999999,16.950001],"type":"Point"}
}