{
  "type": "Feature",
  "properties": {
    "iso:country":"IN",
    "ks:ks_name":"Kolumulapalle Madigawada",
    "ks:ks_pop":41,
    "ks:ks_type":"HABITATION",
    "name:eng_x_preferred":[
        "Kolumulapalle Madigawada"
    ],
    "wof:name":"Kolumulapalle Madigawada",
    "wof:placetype":"locality",
    "wof:population":41
},
  "geometry": {"coordinates":[78.80372,14.407404],"type":"Point"}
}