{
  "type": "Feature",
  "properties": {
    "iso:country":"IN",
    "ks:ks_name":"Kotebettu",
    "ks:ks_pop":384,
    "ks:ks_type":"HABITATION",
    "name:eng_x_preferred":[
        "Kotebettu"
    ],
    "wof:name":"Kotebettu",
    "wof:placetype":"locality",
    "wof:population":384
},
  "geometry": {"coordinates":[74.69658200000001,13.667993],"type":"Point"}
}