{
  "type": "Feature",
  "properties": {
    "iso:country":"IN",
    "ks:ks_name":"R S Colony",
    "ks:ks_pop":13,
    "ks:ks_type":"HABITATION",
    "name:eng_x_preferred":[
        "R S Colony"
    ],
    "wof:name":"R S Colony",
    "wof:placetype":"locality",
    "wof:population":13
},
  "geometry": {"coordinates":[78.198463,13.920997],"type":"Point"}
}