{
  "type": "Feature",
  "properties": {
    "iso:country":"IN",
    "ks:ks_name":"Laxminagar",
    "ks:ks_pop":126,
    "ks:ks_type":"HABITATION",
    "name:eng_x_preferred":[
        "Laxminagar"
    ],
    "wof:name":"Laxminagar",
    "wof:placetype":"locality",
    "wof:population":126
},
  "geometry": {"coordinates":[72.300698,24.098583],"type":"Point"}
}