{
  "type": "Feature",
  "properties": {
    "gn:admin1_code":"25.0",
    "gn:admin2_code":"611.0",
    "gn:asciiname":"Nundala",
    "gn:country_code":"IN",
    "gn:dem":2042,
    "gn:feature_class":"P",
    "gn:feature_code":"PPL",
    "gn:name":"Nund\u0101l\u0101",
    "gn:population":0,
    "gn:timezone":"Asia/Kolkata",
    "iso:country":"IN",
    "wof:name":"Nundala",
    "wof:placetype":"neighbourhood"
},
  "geometry": {"coordinates":[76.68174,11.35142],"type":"Point"}
}