{
  "type": "Feature",
  "properties": {
    "gn:country":"IN",
    "gn:fcode":"PPL",
    "gn:population":39041,
    "iso:country":"IN",
    "name:bpy_x_preferred":[
        "\u09a8\u09be\u09b0\u09be\u09af\u09bc\u09a8\u09aa\u09c7\u09a4"
    ],
    "name:ceb_x_preferred":[
        "N\u0101r\u0101yanpet"
    ],
    "name:eng_x_preferred":[
        "Narayanpet"
    ],
    "name:fra_x_preferred":[
        "Narayanpet"
    ],
    "name:hif_x_preferred":[
        "Narayanpet"
    ],
    "name:hin_x_preferred":[
        "\u0928\u093e\u0930\u093e\u092f\u0923\u092a\u0947\u091f"
    ],
    "name:ita_x_preferred":[
        "Narayanpet"
    ],
    "name:mlg_x_preferred":[
        "Narayanpet"
    ],
    "name:msa_x_preferred":[
        "Narayanpet"
    ],
    "name:nan_x_preferred":[
        "Narayanpet"
    ],
    "name:new_x_preferred":[
        "\u0928\u093e\u0930\u093e\u092f\u0923\u092a\u0947\u091f"
    ],
    "name:nld_x_preferred":[
        "Narayanpet"
    ],
    "name:ori_x_preferred":[
        "\u0b28\u0b3e\u0b30\u0b3e\u0b5f\u0b23\u0b2a\u0b47\u0b1f\u0b4d"
    ],
    "name:swe_x_preferred":[
        "N\u0101r\u0101yanpet"
    ],
    "name:tel_x_preferred":[
        "\u0c28\u0c3e\u0c30\u0c3e\u0c2f\u0c23\u0c2a\u0c47\u0c1f"
    ],
    "name:urd_x_preferred":[
        "\u0646\u0627\u0631\u0627\u06cc\u0646 \u067e\u06cc\u0679"
    ],
    "name:vie_x_preferred":[
        "Narayanpet"
    ],
    "name:zho_x_preferred":[
        "\u7eb3\u62c9\u8036\u6069\u4f69\u7279"
    ],
    "qs:name":"N\u0101r\u0101yanpet",
    "qs:photos_9r":0,
    "qs:photos_sr":0,
    "qs:pop_sr":"7",
    "wd:wordcount":274,
    "wof:name":"N\u0101r\u0101yanpet",
    "wof:placetype":"locality",
    "wof:population":39041
},
  "geometry": {"coordinates":[77.4954,16.74799],"type":"Point"}
}