{
  "type": "Feature",
  "properties": {
    "iso:country":"IN",
    "ks:ks_name":"Mavinkatte",
    "ks:ks_pop":889,
    "ks:ks_type":"HABITATION",
    "name:eng_x_preferred":[
        "Mavinkatte"
    ],
    "wof:name":"Mavinkatte",
    "wof:placetype":"locality",
    "wof:population":889
},
  "geometry": {"coordinates":[74.617414,14.250206],"type":"Point"}
}