{
  "type": "Feature",
  "properties": {
    "iso:country":"IN",
    "ks:ks_name":"N. Matiyari",
    "ks:ks_pop":128,
    "ks:ks_type":"HABITATION",
    "name:eng_x_preferred":[
        "N. Matiyari"
    ],
    "wof:name":"N. Matiyari",
    "wof:placetype":"locality",
    "wof:population":128
},
  "geometry": {"coordinates":[78.733158,27.019299],"type":"Point"}
}