{
  "type": "Feature",
  "properties": {
    "iso:country":"IN",
    "ks:ks_name":"Khangkraidisa",
    "ks:ks_pop":205,
    "ks:ks_type":"HABITATION",
    "name:eng_x_preferred":[
        "Khangkraidisa"
    ],
    "wof:name":"Khangkraidisa",
    "wof:placetype":"locality",
    "wof:population":205
},
  "geometry": {"coordinates":[93.567971,25.761264],"type":"Point"}
}