{
  "type": "Feature",
  "properties": {
    "iso:country":"IN",
    "ks:ks_name":"Prabhunagar",
    "ks:ks_pop":705,
    "ks:ks_type":"HABITATION",
    "name:eng_x_preferred":[
        "Prabhunagar"
    ],
    "wof:name":"Prabhunagar",
    "wof:placetype":"locality",
    "wof:population":705
},
  "geometry": {"coordinates":[74.498527,15.715481],"type":"Point"}
}