{
  "type": "Feature",
  "properties": {
    "iso:country":"IN",
    "ks:ks_name":"Maradi",
    "ks:ks_pop":34,
    "ks:ks_type":"VILLAGE",
    "name:eng_x_preferred":[
        "Maradi"
    ],
    "wof:name":"Maradi",
    "wof:placetype":"locality",
    "wof:population":34
},
  "geometry": {"coordinates":[84.563592,20.530764],"type":"Point"}
}