{
  "type": "Feature",
  "properties": {
    "iso:country":"IN",
    "ks:ks_name":"Gudibania",
    "ks:ks_pop":118,
    "ks:ks_type":"HABITATION",
    "name:eng_x_preferred":[
        "Gudibania"
    ],
    "wof:name":"Gudibania",
    "wof:placetype":"locality",
    "wof:population":118
},
  "geometry": {"coordinates":[86.647879,21.510221],"type":"Point"}
}