{
  "type": "Feature",
  "properties": {
    "iso:country":"IN",
    "ks:ks_name":"Jateshwar",
    "ks:ks_pop":7640,
    "ks:ks_type":"URBAN",
    "name:eng_x_preferred":[
        "Jateshwar"
    ],
    "wof:name":"Jateshwar",
    "wof:placetype":"locality",
    "wof:population":7640
},
  "geometry": {"coordinates":[89.149018,26.599582],"type":"Point"}
}