{
  "type": "Feature",
  "properties": {
    "iso:country":"IN",
    "ks:ks_name":"Burnad",
    "ks:ks_pop":3097,
    "ks:ks_type":"HABITATION",
    "name:eng_x_preferred":[
        "Burnad"
    ],
    "wof:name":"Burnad",
    "wof:placetype":"locality",
    "wof:population":3097
},
  "geometry": {"coordinates":[76.335016,9.564635],"type":"Point"}
}