{
  "type": "Feature",
  "properties": {
    "gn:admin1_code":"21",
    "gn:admin2_code":"384.0",
    "gn:asciiname":"Thakurgarh",
    "gn:country_code":"IN",
    "gn:dem":157,
    "gn:feature_class":"P",
    "gn:feature_code":"PPL",
    "gn:name":"Th\u0101kurgarh",
    "gn:population":0,
    "gn:timezone":"Asia/Kolkata",
    "iso:country":"IN",
    "wof:name":"Thakurgarh",
    "wof:placetype":"locality"
},
  "geometry": {"coordinates":[84.63154,20.81353],"type":"Point"}
}