{
  "type": "Feature",
  "properties": {
    "gn:admin1_code":"2.0",
    "gn:admin2_code":"554.0",
    "gn:asciiname":"Ayyavaripalle",
    "gn:country_code":"IN",
    "gn:dem":669,
    "gn:feature_class":"P",
    "gn:feature_code":"PPL",
    "gn:name":"Ayyav\u0101ripalle",
    "gn:population":0,
    "gn:timezone":"Asia/Kolkata",
    "iso:country":"IN",
    "ks:ks_name":"Ayyavaripalle",
    "ks:ks_pop":81,
    "ks:ks_type":"HABITATION",
    "name:eng_x_preferred":[
        "Ayyavaripalle"
    ],
    "wof:name":"Ayyavaripalle",
    "wof:placetype":"locality",
    "wof:population":81
},
  "geometry": {"coordinates":[78.26253800000001,13.63297],"type":"Point"}
}