{
  "type": "Feature",
  "properties": {
    "iso:country":"IN",
    "ks:ks_name":"Palsod",
    "ks:ks_pop":1175,
    "ks:ks_type":"VILLAGE",
    "name:eng_x_preferred":[
        "Palsod"
    ],
    "wof:name":"Palsod",
    "wof:placetype":"locality",
    "wof:population":1175
},
  "geometry": {"coordinates":[73.166417,21.169222],"type":"Point"}
}