{
  "type": "Feature",
  "properties": {
    "gn:admin1_code":"12",
    "gn:asciiname":"Chotali",
    "gn:country_code":"IN",
    "gn:dem":2046,
    "gn:feature_class":"P",
    "gn:feature_code":"PPL",
    "gn:name":"Chot\u0101li",
    "gn:population":0,
    "gn:timezone":"Asia/Kolkata",
    "iso:country":"IN",
    "wof:name":"Chotali",
    "wof:placetype":"locality"
},
  "geometry": {"coordinates":[74.20779,34.04895],"type":"Point"}
}