{
  "type": "Feature",
  "properties": {
    "gn:admin1_code":"34.0",
    "gn:admin2_code":"212.0",
    "gn:asciiname":"Jamra",
    "gn:country_code":"IN",
    "gn:dem":37,
    "gn:feature_class":"P",
    "gn:feature_code":"PPL",
    "gn:name":"Jamra",
    "gn:population":0,
    "gn:timezone":"Asia/Kolkata",
    "iso:country":"IN",
    "name:snd_x_preferred":[
        "\u0684\u0627\u0645\u0699\u0648"
    ],
    "wof:name":"Jamra",
    "wof:placetype":"locality"
},
  "geometry": {"coordinates":[87.96141,25.62838],"type":"Point"}
}