{
  "type": "Feature",
  "properties": {
    "gn:admin1_code":"12.0",
    "gn:admin2_code":"021",
    "gn:asciiname":"Sar Rakwalan",
    "gn:country_code":"IN",
    "gn:dem":273,
    "gn:feature_class":"P",
    "gn:feature_code":"PPL",
    "gn:name":"S\u0101r Rakw\u0101l\u0101n",
    "gn:population":0,
    "gn:timezone":"Asia/Kolkata",
    "iso:country":"IN",
    "name:und_x_variant":[
        "S\u0101r Rakw\u0101l\u0101n",
        "S\u0101ri Rakwal\u0101n"
    ],
    "wof:name":"Sar Rakwalan",
    "wof:placetype":"locality"
},
  "geometry": {"coordinates":[74.77643,32.72841],"type":"Point"}
}