{
  "type": "Feature",
  "properties": {
    "gn:admin1_code":"13.0",
    "gn:admin2_code":"601.0",
    "gn:asciiname":"Menamkulam",
    "gn:country_code":"IN",
    "gn:dem":14,
    "gn:feature_class":"P",
    "gn:feature_code":"PPL",
    "gn:name":"Menamkulam",
    "gn:population":0,
    "gn:timezone":"Asia/Kolkata",
    "iso:country":"IN",
    "ks:ks_name":"Menamkulam",
    "ks:ks_type":"VILLAGE",
    "name:eng_x_preferred":[
        "Menamkulam"
    ],
    "wof:name":"Menamkulam",
    "wof:placetype":"locality"
},
  "geometry": {"coordinates":[76.85930399999999,8.564618],"type":"Point"}
}