{
  "type": "Feature",
  "properties": {
    "iso:country":"IN",
    "ks:ks_name":"Chay Tola",
    "ks:ks_pop":206,
    "ks:ks_type":"HABITATION",
    "name:eng_x_preferred":[
        "Chay Tola"
    ],
    "wof:name":"Chay Tola",
    "wof:placetype":"locality",
    "wof:population":206
},
  "geometry": {"coordinates":[86.965813,25.211353],"type":"Point"}
}