{
  "type": "Feature",
  "properties": {
    "gn:admin1_code":"16",
    "gn:admin2_code":"526.0",
    "gn:asciiname":"Banajgol",
    "gn:country_code":"IN",
    "gn:dem":462,
    "gn:feature_class":"P",
    "gn:feature_code":"PPL",
    "gn:name":"Banajgol",
    "gn:population":0,
    "gn:timezone":"Asia/Kolkata",
    "iso:country":"IN",
    "wof:name":"Banajgol",
    "wof:placetype":"locality"
},
  "geometry": {"coordinates":[76.27193,17.54459],"type":"Point"}
}