{
  "type": "Feature",
  "properties": {
    "gn:admin1_code":"13.0",
    "gn:admin2_code":"596.0",
    "gn:asciiname":"Magazine",
    "gn:country_code":"IN",
    "gn:dem":1008,
    "gn:feature_class":"P",
    "gn:feature_code":"PPL",
    "gn:name":"Magazine",
    "gn:population":0,
    "gn:timezone":"Asia/Kolkata",
    "iso:country":"IN",
    "wof:name":"Magazine",
    "wof:placetype":"locality"
},
  "geometry": {"coordinates":[76.99401999999998,9.56344],"type":"Point"}
}