{
  "type": "Feature",
  "properties": {
    "iso:country":"IN",
    "ks:ks_name":"Prempur",
    "ks:ks_pop":77,
    "ks:ks_type":"HABITATION",
    "name:eng_x_preferred":[
        "Prempur"
    ],
    "wof:name":"Prempur",
    "wof:placetype":"locality",
    "wof:population":77
},
  "geometry": {"coordinates":[77.784194,28.49315],"type":"Point"}
}