{
  "type": "Feature",
  "properties": {
    "iso:country":"IN",
    "ks:ks_name":"Terka",
    "ks:ks_pop":0,
    "ks:ks_type":"VILLAGE",
    "name:eng_x_preferred":[
        "Terka"
    ],
    "wof:name":"Terka",
    "wof:placetype":"locality",
    "wof:population":0
},
  "geometry": {"coordinates":[77.525766,20.304811],"type":"Point"}
}