{
  "type": "Feature",
  "properties": {
    "gn:admin1_code":"11.0",
    "gn:admin2_code":"27.0",
    "gn:asciiname":"Burna",
    "gn:country_code":"IN",
    "gn:dem":2624,
    "gn:feature_class":"P",
    "gn:feature_code":"PPL",
    "gn:name":"B\u016brna",
    "gn:population":0,
    "gn:timezone":"Asia/Kolkata",
    "iso:country":"IN",
    "wof:name":"Burna",
    "wof:placetype":"locality"
},
  "geometry": {"coordinates":[77.22561,31.67763],"type":"Point"}
}