{
  "type": "Feature",
  "properties": {
    "gn:admin1_code":"19.0",
    "gn:admin2_code":"581.0",
    "gn:asciiname":"Puramakanahalli",
    "gn:country_code":"IN",
    "gn:dem":882,
    "gn:feature_class":"P",
    "gn:feature_code":"PPL",
    "gn:name":"P\u016bram\u0101kanahalli",
    "gn:population":0,
    "gn:timezone":"Asia/Kolkata",
    "iso:country":"IN",
    "wof:name":"Puramakanahalli",
    "wof:placetype":"locality"
},
  "geometry": {"coordinates":[78.00076999999997,13.02243],"type":"Point"}
}