{
  "type": "Feature",
  "properties": {
    "gn:admin1_code":"36.0",
    "gn:admin2_code":"151.0",
    "gn:asciiname":"Amkhiria",
    "gn:country_code":"IN",
    "gn:dem":190,
    "gn:feature_class":"P",
    "gn:feature_code":"PPL",
    "gn:name":"\u0100mkhiria",
    "gn:population":0,
    "gn:timezone":"Asia/Kolkata",
    "iso:country":"IN",
    "ks:ks_alt_nam":"\u0100mkhiria",
    "ks:ks_name":"Amkhiria",
    "ks:ks_type":"VILLAGE",
    "name:eng_x_preferred":[
        "Amkhiria"
    ],
    "name:eng_x_variant":[
        "\u0100mkhiria"
    ],
    "wof:name":"Amkhiria",
    "wof:placetype":"locality"
},
  "geometry": {"coordinates":[79.69561,28.681613],"type":"Point"}
}