{
  "type": "Feature",
  "properties": {
    "iso:country":"IN",
    "ks:ks_alt_nam":"PAYTANGI TANDA",
    "ks:ks_name":"Paytangi Tanda",
    "ks:ks_pop":290,
    "ks:ks_type":"HABITATION",
    "name:eng_x_preferred":[
        "Paytangi Tanda"
    ],
    "wof:name":"Paytangi Tanda",
    "wof:placetype":"locality",
    "wof:population":290
},
  "geometry": {"coordinates":[76.34180600000001,19.052689],"type":"Point"}
}