{
  "type": "Feature",
  "properties": {
    "iso:country":"IN",
    "ks:ks_name":"Pabhuthan",
    "ks:ks_pop":764,
    "ks:ks_type":"HABITATION",
    "name:eng_x_preferred":[
        "Pabhuthan"
    ],
    "wof:name":"Pabhuthan",
    "wof:placetype":"locality",
    "wof:population":764
},
  "geometry": {"coordinates":[74.50273300000001,26.228325],"type":"Point"}
}