{
  "type": "Feature",
  "properties": {
    "gn:admin1_code":"12.0",
    "gn:asciiname":"Parokhin",
    "gn:country_code":"IN",
    "gn:dem":899,
    "gn:feature_class":"P",
    "gn:feature_code":"PPL",
    "gn:name":"Parokhin",
    "gn:population":0,
    "gn:timezone":"Asia/Kolkata",
    "iso:country":"IN",
    "name:und_x_variant":[
        "Parokh\u0101i"
    ],
    "wof:name":"Parokhin",
    "wof:placetype":"locality"
},
  "geometry": {"coordinates":[74.05821,33.25462],"type":"Point"}
}