{
  "type": "Feature",
  "properties": {
    "iso:country":"IN",
    "ks:ks_name":"Bahvas Khas",
    "ks:ks_pop":1415,
    "ks:ks_type":"HABITATION",
    "ks:ks_uagg_main":0,
    "name:eng_x_preferred":[
        "Bahvas Khas"
    ],
    "wof:name":"Bahvas Khas",
    "wof:placetype":"neighbourhood",
    "wof:population":1415
},
  "geometry": {"coordinates":[83.72396500000001,26.879028],"type":"Point"}
}