{
  "type": "Feature",
  "properties": {
    "iso:country":"IN",
    "ks:ks_name":"Elappupara",
    "ks:ks_pop":748,
    "ks:ks_type":"HABITATION",
    "name:eng_x_preferred":[
        "Elappupara"
    ],
    "wof:name":"Elappupara",
    "wof:placetype":"locality",
    "wof:population":748
},
  "geometry": {"coordinates":[76.87388300000001,9.102945],"type":"Point"}
}