{
  "type": "Feature",
  "properties": {
    "iso:country":"IN",
    "ks:ks_alt_nam":"Munderi seed farm",
    "ks:ks_name":"Munderi Seed Farm",
    "ks:ks_pop":524,
    "ks:ks_type":"HABITATION",
    "name:eng_x_preferred":[
        "Munderi Seed Farm"
    ],
    "wof:name":"Munderi Seed Farm",
    "wof:placetype":"locality",
    "wof:population":524
},
  "geometry": {"coordinates":[76.239897,11.459324],"type":"Point"}
}