{
  "type": "Feature",
  "properties": {
    "gn:admin1_code":"36.0",
    "gn:admin2_code":"152",
    "gn:asciiname":"Keseri Kalan",
    "gn:country_code":"IN",
    "gn:dem":141,
    "gn:feature_class":"P",
    "gn:feature_code":"PPL",
    "gn:name":"Keseri Kal\u0101n",
    "gn:population":0,
    "gn:timezone":"Asia/Kolkata",
    "iso:country":"IN",
    "ks:ks_name":"Kasari Kalan",
    "ks:ks_pop":0,
    "ks:ks_type":"VILLAGE",
    "name:eng_x_preferred":[
        "Kasari Kalan"
    ],
    "name:eng_x_variant":[
        "Keseri Kalan"
    ],
    "wof:name":"Kasari Kalan",
    "wof:placetype":"locality",
    "wof:population":0
},
  "geometry": {"coordinates":[79.610851,27.686092],"type":"Point"}
}