{
  "type": "Feature",
  "properties": {
    "gn:admin1_code":"21.0",
    "gn:admin2_code":"399.0",
    "gn:asciiname":"Tekiguda",
    "gn:country_code":"IN",
    "gn:dem":168,
    "gn:feature_class":"P",
    "gn:feature_code":"PPL",
    "gn:name":"Tekig\u016bda",
    "gn:population":0,
    "gn:timezone":"Asia/Kolkata",
    "iso:country":"IN",
    "ks:ks_name":"Tekaguda",
    "ks:ks_pop":303,
    "ks:ks_type":"HABITATION",
    "name:eng_x_preferred":[
        "Tekaguda"
    ],
    "name:eng_x_variant":[
        "Tekiguda"
    ],
    "wof:name":"Tekaguda",
    "wof:placetype":"locality",
    "wof:population":303
},
  "geometry": {"coordinates":[81.864357,18.071762],"type":"Point"}
}