{
  "type": "Feature",
  "properties": {
    "gn:admin1_code":"34.0",
    "gn:admin2_code":"235.0",
    "gn:asciiname":"Kara",
    "gn:country_code":"IN",
    "gn:dem":98,
    "gn:feature_class":"P",
    "gn:feature_code":"PPL",
    "gn:name":"K\u0101ra",
    "gn:population":0,
    "gn:timezone":"Asia/Kolkata",
    "iso:country":"IN",
    "name:ara_x_preferred":[
        "\u0643\u0627\u0631\u0627"
    ],
    "name:bel_x_preferred":[
        "\u041a\u0430\u0440\u0430"
    ],
    "name:cat_x_preferred":[
        "Kara"
    ],
    "name:ceb_x_preferred":[
        "Kara"
    ],
    "name:ces_x_preferred":[
        "Kara"
    ],
    "name:dan_x_preferred":[
        "Kara"
    ],
    "name:deu_x_preferred":[
        "Kara"
    ],
    "name:epo_x_preferred":[
        "Kara"
    ],
    "name:fas_x_preferred":[
        "\u06a9\u0627\u0631\u0627"
    ],
    "name:fin_x_preferred":[
        "Kara"
    ],
    "name:fra_x_preferred":[
        "Kara"
    ],
    "name:heb_x_preferred":[
        "\u05e7\u05d0\u05e8\u05d4"
    ],
    "name:hun_x_preferred":[
        "Kara"
    ],
    "name:ind_x_preferred":[
        "Kara"
    ],
    "name:ita_x_preferred":[
        "Kara"
    ],
    "name:khm_x_preferred":[
        "Kara"
    ],
    "name:nld_x_preferred":[
        "Kara"
    ],
    "name:nno_x_preferred":[
        "Kara"
    ],
    "name:nor_x_preferred":[
        "Kara"
    ],
    "name:pol_x_preferred":[
        "Kara"
    ],
    "name:por_x_preferred":[
        "Kara"
    ],
    "name:rus_x_preferred":[
        "\u041a\u0430\u0440\u0430"
    ],
    "name:spa_x_preferred":[
        "Kara"
    ],
    "name:srp_x_preferred":[
        "\u041a\u0430\u0440\u0430"
    ],
    "name:swe_x_preferred":[
        "Kara"
    ],
    "name:tur_x_preferred":[
        "Kara"
    ],
    "name:ukr_x_preferred":[
        "\u041a\u0430\u0440\u0430"
    ],
    "name:vep_x_preferred":[
        "Kara"
    ],
    "name:vie_x_preferred":[
        "Kara"
    ],
    "wof:name":"Kara",
    "wof:placetype":"locality"
},
  "geometry": {"coordinates":[84.35316999999998,24.91821],"type":"Point"}
}