{
  "type": "Feature",
  "properties": {
    "gn:admin1_code":"25.0",
    "gn:admin2_code":"614",
    "gn:asciiname":"Appananallur",
    "gn:country_code":"IN",
    "gn:dem":115,
    "gn:feature_class":"P",
    "gn:feature_code":"PPL",
    "gn:name":"Appananall\u016br",
    "gn:population":0,
    "gn:timezone":"Asia/Kolkata",
    "iso:country":"IN",
    "ks:ks_name":"Appanallur",
    "ks:ks_pop":2265,
    "ks:ks_type":"VILLAGE",
    "ks:ks_uagg_main":0,
    "name:eng_x_preferred":[
        "Appanallur"
    ],
    "name:und_x_variant":[
        "Appananall\u016br"
    ],
    "wof:name":"Appanallur",
    "wof:placetype":"neighbourhood",
    "wof:population":2265
},
  "geometry": {"coordinates":[78.385313,11.031755],"type":"Point"}
}