{
  "type": "Feature",
  "properties": {
    "gn:admin1_code":"24.0",
    "gn:admin2_code":"104.0",
    "gn:asciiname":"Bhojrajka Ki Dhani",
    "gn:country_code":"IN",
    "gn:dem":268,
    "gn:feature_class":"P",
    "gn:feature_code":"PPL",
    "gn:name":"Bhojr\u0101jka Ki Dh\u0101ni",
    "gn:population":0,
    "gn:timezone":"Asia/Kolkata",
    "iso:country":"IN",
    "wof:name":"Bhojrajka Ki Dhani",
    "wof:placetype":"neighbourhood"
},
  "geometry": {"coordinates":[76.73390000000001,27.95644],"type":"Point"}
}