{
  "type": "Feature",
  "properties": {
    "iso:country":"IN",
    "ks:ks_name":"Old Ananderi",
    "ks:ks_pop":222,
    "ks:ks_type":"HABITATION",
    "name:eng_x_preferred":[
        "Old Ananderi"
    ],
    "wof:name":"Old Ananderi",
    "wof:placetype":"locality",
    "wof:population":222
},
  "geometry": {"coordinates":[79.904691,13.322291],"type":"Point"}
}