{
  "type": "Feature",
  "properties": {
    "gn:admin1_code":"36",
    "gn:admin2_code":"152.0",
    "gn:asciiname":"Umarpur",
    "gn:country_code":"IN",
    "gn:dem":146,
    "gn:feature_class":"P",
    "gn:feature_code":"PPL",
    "gn:name":"Umarpur",
    "gn:population":0,
    "gn:timezone":"Asia/Kolkata",
    "iso:country":"IN",
    "ks:ks_name":"Umarpur",
    "ks:ks_pop":0,
    "ks:ks_type":"VILLAGE",
    "name:eng_x_preferred":[
        "Umarpur"
    ],
    "name:urd_x_preferred":[
        "\u0639\u0645\u0631\u067e\u0648\u0631"
    ],
    "wof:name":"Umarpur",
    "wof:placetype":"locality",
    "wof:population":0
},
  "geometry": {"coordinates":[79.544456,27.767635],"type":"Point"}
}