{
  "type": "Feature",
  "properties": {
    "iso:country":"IN",
    "ks:ks_name":"Bandaradi",
    "ks:ks_pop":90,
    "ks:ks_type":"HABITATION",
    "name:eng_x_preferred":[
        "Bandaradi"
    ],
    "wof:name":"Bandaradi",
    "wof:placetype":"locality",
    "wof:population":90
},
  "geometry": {"coordinates":[74.816074,13.701694],"type":"Point"}
}