{
  "type": "Feature",
  "properties": {
    "gn:admin1_code":"34.0",
    "gn:admin2_code":"231.0",
    "gn:asciiname":"Sripur",
    "gn:country_code":"IN",
    "gn:dem":74,
    "gn:feature_class":"P",
    "gn:feature_code":"PPL",
    "gn:name":"Sr\u012bpur",
    "gn:population":0,
    "gn:timezone":"Asia/Kolkata",
    "iso:country":"IN",
    "name:bih_x_preferred":[
        "\u0936\u094d\u0930\u0940\u092a\u0941\u0930"
    ],
    "wof:name":"Sripur",
    "wof:placetype":"neighbourhood"
},
  "geometry": {"coordinates":[84.49024,25.45491],"type":"Point"}
}