{
  "type": "Feature",
  "properties": {
    "gn:admin1_code":"36.0",
    "gn:admin2_code":"184.0",
    "gn:asciiname":"Bijaura",
    "gn:country_code":"IN",
    "gn:dem":100,
    "gn:feature_class":"P",
    "gn:feature_code":"PPL",
    "gn:name":"Bijaura",
    "gn:population":0,
    "gn:timezone":"Asia/Kolkata",
    "iso:country":"IN",
    "name:ceb_x_preferred":[
        "Bijaura"
    ],
    "name:fra_x_preferred":[
        "Bijaura"
    ],
    "name:mai_x_preferred":[
        "\u0935\u093f\u091c\u094c\u0930\u093e"
    ],
    "name:msa_x_preferred":[
        "Bijaura"
    ],
    "name:nep_x_preferred":[
        "\u092c\u093f\u091c\u094c\u0930\u093e"
    ],
    "name:new_x_preferred":[
        "\u092c\u093f\u091c\u094c\u0930\u093e"
    ],
    "name:pol_x_preferred":[
        "Bijaura"
    ],
    "wof:name":"Bijaura",
    "wof:placetype":"locality"
},
  "geometry": {"coordinates":[82.51884,27.30571],"type":"Point"}
}