{
  "type": "Feature",
  "properties": {
    "gn:admin1_code":"36",
    "gn:admin2_code":"188.0",
    "gn:asciiname":"Sahaspur",
    "gn:country_code":"IN",
    "gn:dem":85,
    "gn:feature_class":"P",
    "gn:feature_code":"PPL",
    "gn:name":"Sahaspur",
    "gn:population":0,
    "gn:timezone":"Asia/Kolkata",
    "iso:country":"IN",
    "ks:ks_name":"Sahaspur",
    "ks:ks_pop":99,
    "ks:ks_type":"VILLAGE",
    "ks:ks_uagg_main":0,
    "name:bpy_x_preferred":[
        "\u09b8\u09be\u09b9\u09b8\u09aa\u09c1\u09b0"
    ],
    "name:ceb_x_preferred":[
        "Sahaspur"
    ],
    "name:eng_x_preferred":[
        "Sahaspur"
    ],
    "name:ita_x_preferred":[
        "Sahaspur"
    ],
    "name:mlg_x_preferred":[
        "Sahaspur"
    ],
    "name:msa_x_preferred":[
        "Sahaspur"
    ],
    "name:nld_x_preferred":[
        "Sahaspur"
    ],
    "name:ori_x_preferred":[
        "\u0b38\u0b3e\u0b39\u0b3e\u0b38\u0b2a\u0b41\u0b30"
    ],
    "name:pnb_x_preferred":[
        "\u0633\u06c1\u0627\u0633\u067e\u0648\u0631"
    ],
    "name:pol_x_preferred":[
        "Sahaspur"
    ],
    "name:por_x_preferred":[
        "Sahaspur"
    ],
    "name:swe_x_preferred":[
        "Sahaspur"
    ],
    "name:urd_x_preferred":[
        "\u0633\u06c1\u0627\u0633\u067e\u0648\u0631"
    ],
    "name:vie_x_preferred":[
        "Sahaspur"
    ],
    "name:zho_x_preferred":[
        "\u8428\u54c8\u65af\u666e\u5c14"
    ],
    "wof:name":"Sahaspur",
    "wof:placetype":"neighbourhood",
    "wof:population":99
},
  "geometry": {"coordinates":[83.277719,26.631958],"type":"Point"}
}