{
  "type": "Feature",
  "properties": {
    "iso:country":"IN",
    "ks:ks_name":"Fatatuli",
    "ks:ks_pop":281,
    "ks:ks_type":"HABITATION",
    "ks:ks_uagg_main":0,
    "name:eng_x_preferred":[
        "Fatatuli"
    ],
    "wof:name":"Fatatuli",
    "wof:placetype":"locality",
    "wof:population":281
},
  "geometry": {"coordinates":[88.22532200000001,25.520038],"type":"Point"}
}