{
  "type": "Feature",
  "properties": {
    "iso:country":"IN",
    "ks:ks_name":"Gavathe",
    "ks:ks_pop":26,
    "ks:ks_type":"HABITATION",
    "name:eng_x_preferred":[
        "Gavathe"
    ],
    "wof:name":"Gavathe",
    "wof:placetype":"locality",
    "wof:population":26
},
  "geometry": {"coordinates":[74.237487,14.892082],"type":"Point"}
}