{
  "type": "Feature",
  "properties": {
    "gn:admin1_code":"36",
    "gn:admin2_code":"147.0",
    "gn:asciiname":"Rajaram",
    "gn:country_code":"IN",
    "gn:dem":168,
    "gn:feature_class":"P",
    "gn:feature_code":"PPL",
    "gn:name":"R\u0101j\u0101r\u0101m",
    "gn:population":0,
    "gn:timezone":"Asia/Kolkata",
    "iso:country":"IN",
    "name:hin_x_preferred":[
        "\u0930\u093e\u091c\u093e\u0930\u093e\u092e"
    ],
    "name:nld_x_preferred":[
        "Rajaram"
    ],
    "name:tel_x_preferred":[
        "\u0c30\u0c3e\u0c1c\u0c3e\u0c30\u0c3e\u0c02"
    ],
    "wof:name":"Rajaram",
    "wof:placetype":"neighbourhood"
},
  "geometry": {"coordinates":[78.68661,27.37025],"type":"Point"}
}