{
  "type": "Feature",
  "properties": {
    "iso:country":"IN",
    "ks:ks_name":"B Nuaguda",
    "ks:ks_pop":276,
    "ks:ks_type":"HABITATION",
    "name:eng_x_preferred":[
        "B Nuaguda"
    ],
    "wof:name":"B Nuaguda",
    "wof:placetype":"locality",
    "wof:population":276
},
  "geometry": {"coordinates":[82.921049,18.992566],"type":"Point"}
}