{
  "type": "Feature",
  "properties": {
    "gn:admin1_code":"11",
    "gn:admin2_code":"31.0",
    "gn:asciiname":"Palodhan",
    "gn:country_code":"IN",
    "gn:dem":1451,
    "gn:feature_class":"P",
    "gn:feature_code":"PPL",
    "gn:name":"Palodhan",
    "gn:population":0,
    "gn:timezone":"Asia/Kolkata",
    "iso:country":"IN",
    "wof:name":"Palodhan",
    "wof:placetype":"locality"
},
  "geometry": {"coordinates":[76.94811999999997,31.2788],"type":"Point"}
}