{
  "type": "Feature",
  "properties": {
    "iso:country":"IN",
    "ks:ks_alt_nam":"chickasandra",
    "ks:ks_name":"Chickasandra",
    "ks:ks_pop":15,
    "ks:ks_type":"HABITATION",
    "name:eng_x_preferred":[
        "Chickasandra"
    ],
    "wof:name":"Chickasandra",
    "wof:placetype":"locality",
    "wof:population":15
},
  "geometry": {"coordinates":[77.695348,13.098555],"type":"Point"}
}