{
  "type": "Feature",
  "properties": {
    "iso:country":"IN",
    "ks:ks_name":"Raidang T.E",
    "ks:ks_pop":288,
    "ks:ks_type":"VILLAGE",
    "name:eng_x_preferred":[
        "Raidang T.E"
    ],
    "wof:name":"Raidang T.E",
    "wof:placetype":"locality",
    "wof:population":288
},
  "geometry": {"coordinates":[95.206914,27.122111],"type":"Point"}
}