{
  "type": "Feature",
  "properties": {
    "iso:country":"IN",
    "ks:ks_name":"Bhoyantola",
    "ks:ks_pop":193,
    "ks:ks_type":"HABITATION",
    "name:eng_x_preferred":[
        "Bhoyantola"
    ],
    "wof:name":"Bhoyantola",
    "wof:placetype":"locality",
    "wof:population":193
},
  "geometry": {"coordinates":[84.875753,22.160474],"type":"Point"}
}