{
  "type": "Feature",
  "properties": {
    "iso:country":"IN",
    "ks:ks_name":"Khijoorbeda",
    "ks:ks_pop":90,
    "ks:ks_type":"HABITATION",
    "name:eng_x_preferred":[
        "Khijoorbeda"
    ],
    "wof:name":"Khijoorbeda",
    "wof:placetype":"locality",
    "wof:population":90
},
  "geometry": {"coordinates":[84.640765,22.588239],"type":"Point"}
}