{
  "type": "Feature",
  "properties": {
    "iso:country":"IN",
    "ks:ks_name":"Chura Tanda",
    "ks:ks_pop":879,
    "ks:ks_type":"HABITATION",
    "name:eng_x_preferred":[
        "Chura Tanda"
    ],
    "wof:name":"Chura Tanda",
    "wof:placetype":"locality",
    "wof:population":879
},
  "geometry": {"coordinates":[80.549104,28.311993],"type":"Point"}
}