{
  "type": "Feature",
  "properties": {
    "iso:country":"IN",
    "ks:ks_name":"Aladiha",
    "ks:ks_pop":3903,
    "ks:ks_type":"VILLAGE",
    "ks:ks_uagg_main":0,
    "name:eng_x_preferred":[
        "Aladiha"
    ],
    "wof:name":"Aladiha",
    "wof:placetype":"neighbourhood",
    "wof:population":3903
},
  "geometry": {"coordinates":[87.254829,21.577373],"type":"Point"}
}