{
  "type": "Feature",
  "properties": {
    "iso:country":"IN",
    "ks:ks_name":"Bhoslewasti",
    "ks:ks_pop":152,
    "ks:ks_type":"HABITATION",
    "name:eng_x_preferred":[
        "Bhoslewasti"
    ],
    "wof:name":"Bhoslewasti",
    "wof:placetype":"locality",
    "wof:population":152
},
  "geometry": {"coordinates":[74.352935,19.627119],"type":"Point"}
}