{
  "type": "Feature",
  "properties": {
    "gn:admin1_code":"36",
    "gn:admin2_code":"173.0",
    "gn:asciiname":"Astura",
    "gn:country_code":"IN",
    "gn:dem":96,
    "gn:feature_class":"P",
    "gn:feature_code":"PPL",
    "gn:name":"Astura",
    "gn:population":0,
    "gn:timezone":"Asia/Kolkata",
    "iso:country":"IN",
    "name:deu_x_preferred":[
        "Astura"
    ],
    "name:ita_x_preferred":[
        "Astura"
    ],
    "name:rus_x_preferred":[
        "\u0410\u0441\u0442\u0443\u0440\u0430"
    ],
    "wof:name":"Astura",
    "wof:placetype":"locality"
},
  "geometry": {"coordinates":[82.14521999999999,26.00393],"type":"Point"}
}