{
  "type": "Feature",
  "properties": {
    "iso:country":"IN",
    "ks:ks_name":"Pujaripara",
    "ks:ks_pop":441,
    "ks:ks_type":"HABITATION",
    "name:eng_x_preferred":[
        "Pujaripara"
    ],
    "wof:name":"Pujaripara",
    "wof:placetype":"locality",
    "wof:population":441
},
  "geometry": {"coordinates":[81.850661,18.999395],"type":"Point"}
}