{
  "type": "Feature",
  "properties": {
    "gn:admin1_code":"35.0",
    "gn:admin2_code":"449.0",
    "gn:asciiname":"Mado",
    "gn:country_code":"IN",
    "gn:dem":368,
    "gn:feature_class":"P",
    "gn:feature_code":"PPL",
    "gn:name":"M\u0101do",
    "gn:population":0,
    "gn:timezone":"Asia/Kolkata",
    "iso:country":"IN",
    "name:ceb_x_preferred":[
        "Mado"
    ],
    "name:nld_x_preferred":[
        "Mado"
    ],
    "name:swe_x_preferred":[
        "Mado"
    ],
    "wof:name":"Mado",
    "wof:placetype":"locality"
},
  "geometry": {"coordinates":[78.40482,22.67688],"type":"Point"}
}