{
  "type": "Feature",
  "properties": {
    "gn:admin1_code":"38.0",
    "gn:admin2_code":"353.0",
    "gn:asciiname":"Banskendri",
    "gn:country_code":"IN",
    "gn:dem":81,
    "gn:feature_class":"P",
    "gn:feature_code":"PPL",
    "gn:name":"B\u0101nskendri",
    "gn:population":0,
    "gn:timezone":"Asia/Kolkata",
    "iso:country":"IN",
    "ks:ks_name":"Banskondri",
    "ks:ks_pop":2584,
    "ks:ks_type":"VILLAGE",
    "name:eng_x_preferred":[
        "Banskondri"
    ],
    "name:eng_x_variant":[
        "Banskendri"
    ],
    "wof:name":"Banskondri",
    "wof:placetype":"locality",
    "wof:population":2584
},
  "geometry": {"coordinates":[87.60868499999999,24.525698],"type":"Point"}
}