{
  "type": "Feature",
  "properties": {
    "gn:admin1_code":"39.0",
    "gn:admin2_code":"66.0",
    "gn:asciiname":"Seluwa Kanla",
    "gn:country_code":"IN",
    "gn:dem":1739,
    "gn:feature_class":"P",
    "gn:feature_code":"PPL",
    "gn:name":"Seluwa K\u0101nla",
    "gn:population":0,
    "gn:timezone":"Asia/Kolkata",
    "iso:country":"IN",
    "wof:name":"Seluwa Kanla",
    "wof:placetype":"locality"
},
  "geometry": {"coordinates":[79.62475000000001,29.37821],"type":"Point"}
}