{
  "type": "Feature",
  "properties": {
    "gn:admin1_code":"25.0",
    "gn:admin2_code":"609.0",
    "gn:asciiname":"Sikkinayakkanpalaiyam",
    "gn:country_code":"IN",
    "gn:dem":174,
    "gn:feature_class":"P",
    "gn:feature_code":"PPL",
    "gn:name":"Sikkin\u0101yakkanp\u0101laiyam",
    "gn:population":0,
    "gn:timezone":"Asia/Kolkata",
    "iso:country":"IN",
    "wof:name":"Sikkinayakkanpalaiyam",
    "wof:placetype":"locality"
},
  "geometry": {"coordinates":[77.97421999999997,11.21556],"type":"Point"}
}