{
  "type": "Feature",
  "properties": {
    "gn:admin1_code":"25.0",
    "gn:admin2_code":"630.0",
    "gn:asciiname":"Kallur",
    "gn:country_code":"IN",
    "gn:dem":418,
    "gn:feature_class":"P",
    "gn:feature_code":"PPL",
    "gn:name":"Kall\u016br",
    "gn:population":0,
    "gn:timezone":"Asia/Kolkata",
    "iso:country":"IN",
    "name:deu_x_preferred":[
        "Kallur"
    ],
    "name:swe_x_preferred":[
        "Kallur"
    ],
    "wof:name":"Kallur",
    "wof:placetype":"locality"
},
  "geometry": {"coordinates":[78.40993,12.11265],"type":"Point"}
}