{
  "type": "Feature",
  "properties": {
    "gn:admin1_code":"36.0",
    "gn:admin2_code":"153.0",
    "gn:asciiname":"Hayatpur",
    "gn:country_code":"IN",
    "gn:dem":156,
    "gn:feature_class":"P",
    "gn:feature_code":"PPL",
    "gn:name":"Hay\u0101tpur",
    "gn:population":0,
    "gn:timezone":"Asia/Kolkata",
    "iso:country":"IN",
    "name:ara_x_preferred":[
        "\u062d\u064a\u0627\u062a \u0628\u0648\u0631"
    ],
    "name:ben_bn_x_preferred":[
        "\u09b9\u09be\u09df\u09be\u09a4\u09aa\u09c1\u09b0"
    ],
    "name:ben_in_x_preferred":[
        "\u09b9\u09be\u09df\u09be\u09a4\u09aa\u09c1\u09b0"
    ],
    "name:guj_x_preferred":[
        "\u0ab9\u0ac8\u0aaf\u0abe\u0aa4\u0aaa\u0ac1\u0ab0"
    ],
    "name:hin_x_preferred":[
        "\u0939\u092f\u093e\u0924\u092a\u0941\u0930"
    ],
    "name:kan_x_preferred":[
        "\u0cb9\u0caf\u0cbe\u0ca4\u0ccd"
    ],
    "name:mal_x_preferred":[
        "\u0d39\u0d2f\u0d3e\u0d24\u0d4d\u0d2a\u0d42\u0d7c"
    ],
    "name:mar_x_preferred":[
        "\u0939\u092f\u093e\u0924\u092a\u0942\u0930"
    ],
    "name:pan_x_preferred":[
        "\u0a39\u0a2f\u0a3e\u0a24\u0a2a\u0a41\u0a30"
    ],
    "name:tam_x_preferred":[
        "\u0bb9\u0baf\u0bbe\u0ba4\u0bcd\u0baa\u0bc2\u0bb0\u0bcd"
    ],
    "name:tel_x_preferred":[
        "\u0c39\u0c2f\u0c24\u0c4d"
    ],
    "name:urd_x_preferred":[
        "\u062d\u06cc\u0627\u062a \u067e\u0648\u0631"
    ],
    "wof:name":"Hayatpur",
    "wof:placetype":"locality"
},
  "geometry": {"coordinates":[80.47861999999998,27.97633],"type":"Point"}
}