{
  "type": "Feature",
  "properties": {
    "iso:country":"IN",
    "ks:ks_name":"Gobal",
    "ks:ks_pop":176,
    "ks:ks_type":"VILLAGE",
    "ks:ks_uagg_main":0,
    "name:eng_x_preferred":[
        "Gobal"
    ],
    "wof:name":"Gobal",
    "wof:placetype":"neighbourhood",
    "wof:population":176
},
  "geometry": {"coordinates":[90.33331,25.990099],"type":"Point"}
}