{
  "type": "Feature",
  "properties": {
    "iso:country":"IN",
    "ks:ks_name":"Harijanpada",
    "ks:ks_pop":50,
    "ks:ks_type":"HABITATION",
    "name:eng_x_preferred":[
        "Harijanpada"
    ],
    "wof:name":"Harijanpada",
    "wof:placetype":"locality",
    "wof:population":50
},
  "geometry": {"coordinates":[83.41119999999999,19.82282],"type":"Point"}
}