{
  "type": "Feature",
  "properties": {
    "gn:country":"IN",
    "gn:fcode":"PPL",
    "gn:population":0,
    "iso:country":"IN",
    "name:ceb_x_preferred":[
        "Sherpur"
    ],
    "name:nld_x_preferred":[
        "Sherpur"
    ],
    "name:rus_x_preferred":[
        "\u0428\u0435\u0440\u043f\u0443\u0440"
    ],
    "name:swe_x_preferred":[
        "Sherpur"
    ],
    "qs:name":"Sherpur",
    "qs:name_adm0":"India",
    "qs:name_adm1":"Himachal Pradesh",
    "qs:photos":2,
    "qs:photos_1k":1,
    "qs:photos_9k":1,
    "qs:photos_9r":1,
    "qs:photos_all":2,
    "qs:photos_sr":1,
    "qs:placetype":"Suburb",
    "qs:pop_sr":"0",
    "wd:wordcount":78,
    "wof:name":"Sherpur",
    "wof:placetype":"neighbourhood",
    "wof:population":0
},
  "geometry": {"coordinates":[77.84989,30.33791],"type":"Point"}
}