{
  "type": "Feature",
  "properties": {
    "gn:admin1_code":"34.0",
    "gn:admin2_code":"231.0",
    "gn:asciiname":"Chela",
    "gn:country_code":"IN",
    "gn:dem":70,
    "gn:feature_class":"P",
    "gn:feature_code":"PPL",
    "gn:name":"Chela",
    "gn:population":0,
    "gn:timezone":"Asia/Kolkata",
    "iso:country":"IN",
    "name:ceb_x_preferred":[
        "Chela"
    ],
    "name:deu_x_preferred":[
        "Chela"
    ],
    "name:ita_x_preferred":[
        "Chela"
    ],
    "name:nds_x_preferred":[
        "Chela"
    ],
    "name:nor_x_preferred":[
        "Chela"
    ],
    "name:pol_x_preferred":[
        "Chela"
    ],
    "name:spa_x_preferred":[
        "Chela"
    ],
    "name:swe_x_preferred":[
        "Chela"
    ],
    "wof:name":"Chela",
    "wof:placetype":"locality"
},
  "geometry": {"coordinates":[84.71525,25.39718],"type":"Point"}
}