{
  "type": "Feature",
  "properties": {
    "iso:country":"IN",
    "ks:ks_alt_nam":"SARKARPARA",
    "ks:ks_name":"Sarkarpara",
    "ks:ks_pop":526,
    "ks:ks_type":"HABITATION",
    "name:eng_x_preferred":[
        "Sarkarpara"
    ],
    "wof:name":"Sarkarpara",
    "wof:placetype":"locality",
    "wof:population":526
},
  "geometry": {"coordinates":[89.40324,26.498475],"type":"Point"}
}