{
  "type": "Feature",
  "properties": {
    "iso:country":"IN",
    "ks:ks_name":"Kohadi.",
    "ks:ks_pop":337,
    "ks:ks_type":"HABITATION",
    "ks:ks_uagg_main":0,
    "name:eng_x_preferred":[
        "Kohadi."
    ],
    "wof:name":"Kohadi.",
    "wof:placetype":"neighbourhood",
    "wof:population":337
},
  "geometry": {"coordinates":[83.27017499999999,26.137453],"type":"Point"}
}