{
  "type": "Feature",
  "properties": {
    "gn:admin1_code":"12.0",
    "gn:admin2_code":"17.0",
    "gn:asciiname":"Sangaidan",
    "gn:country_code":"IN",
    "gn:dem":1213,
    "gn:feature_class":"P",
    "gn:feature_code":"PPL",
    "gn:name":"Sangaidan",
    "gn:population":0,
    "gn:timezone":"Asia/Kolkata",
    "iso:country":"IN",
    "wof:name":"Sangaidan",
    "wof:placetype":"locality"
},
  "geometry": {"coordinates":[75.0915,33.24593],"type":"Point"}
}