{
  "type": "Feature",
  "properties": {
    "iso:country":"IN",
    "ks:ks_name":"Surya Thanda",
    "ks:ks_pop":54,
    "ks:ks_type":"HABITATION",
    "name:eng_x_preferred":[
        "Surya Thanda"
    ],
    "wof:name":"Surya Thanda",
    "wof:placetype":"locality",
    "wof:population":54
},
  "geometry": {"coordinates":[79.62070900000001,17.547659],"type":"Point"}
}