{
  "type": "Feature",
  "properties": {
    "gn:admin1_code":"12.0",
    "gn:admin2_code":"7.0",
    "gn:asciiname":"Rapar",
    "gn:country_code":"IN",
    "gn:dem":691,
    "gn:feature_class":"P",
    "gn:feature_code":"PPL",
    "gn:name":"R\u0101par",
    "gn:population":0,
    "gn:timezone":"Asia/Kolkata",
    "iso:country":"IN",
    "name:bpy_x_preferred":[
        "\u09b0\u09be\u09aa\u09be\u09b0"
    ],
    "name:ceb_x_preferred":[
        "R\u0101par"
    ],
    "name:guj_x_preferred":[
        "\u0ab0\u0abe\u0aaa\u0ab0"
    ],
    "name:ita_x_preferred":[
        "Rapar"
    ],
    "name:msa_x_preferred":[
        "Rapar"
    ],
    "name:ori_x_preferred":[
        "\u0b30\u0b3e\u0b2a\u0b3e\u0b30"
    ],
    "name:por_x_preferred":[
        "Rapar"
    ],
    "name:spa_x_preferred":[
        "Rapar"
    ],
    "name:swe_x_preferred":[
        "R\u0101par"
    ],
    "name:vie_x_preferred":[
        "Rapar"
    ],
    "wof:name":"Rapar",
    "wof:placetype":"locality"
},
  "geometry": {"coordinates":[75.64309,32.55996],"type":"Point"}
}