{
  "type": "Feature",
  "properties": {
    "gn:admin1_code":"36",
    "gn:admin2_code":"133.0",
    "gn:asciiname":"Patti Sadad",
    "gn:country_code":"IN",
    "gn:dem":238,
    "gn:feature_class":"P",
    "gn:feature_code":"PPL",
    "gn:name":"Patti S\u0101d\u0101d",
    "gn:population":0,
    "gn:timezone":"Asia/Kolkata",
    "iso:country":"IN",
    "wof:name":"Patti Sadad",
    "wof:placetype":"neighbourhood"
},
  "geometry": {"coordinates":[77.20995000000001,29.31106],"type":"Point"}
}