{
  "type": "Feature",
  "properties": {
    "gn:admin1_code":"36",
    "gn:admin2_code":"176.0",
    "gn:asciiname":"Karauli",
    "gn:country_code":"IN",
    "gn:dem":121,
    "gn:feature_class":"P",
    "gn:feature_code":"PPL",
    "gn:name":"Karauli",
    "gn:population":0,
    "gn:timezone":"Asia/Kolkata",
    "iso:country":"IN",
    "ks:ks_name":"Kurauli",
    "ks:ks_pop":1817,
    "ks:ks_type":"VILLAGE",
    "ks:ks_uagg_main":0,
    "name:ara_x_preferred":[
        "\u0643\u0627\u0631\u0627\u0648\u0644\u064a"
    ],
    "name:ben_bn_x_preferred":[
        "\u0995\u09be\u09b0\u09be\u0989\u09b2\u09bf"
    ],
    "name:ben_in_x_preferred":[
        "\u0995\u09be\u09b0\u09be\u0989\u09b2\u09bf"
    ],
    "name:ben_x_preferred":[
        "\u0995\u09be\u09b0\u09cc\u09b2\u09bf"
    ],
    "name:bpy_x_preferred":[
        "\u0995\u09be\u09b0\u09cc\u09b2\u09bf"
    ],
    "name:cat_x_preferred":[
        "Karauli"
    ],
    "name:ceb_x_preferred":[
        "Karauli"
    ],
    "name:deu_x_preferred":[
        "Karauli"
    ],
    "name:eng_x_preferred":[
        "Kurauli"
    ],
    "name:fra_x_preferred":[
        "Karauli"
    ],
    "name:guj_x_preferred":[
        "\u0a95\u0abe\u0ab0\u0acc\u0ab2\u0ac0"
    ],
    "name:guj_x_variant":[
        "\u0a95\u0ab0\u0acc\u0ab2\u0ac0"
    ],
    "name:hin_x_preferred":[
        "\u0915\u0930\u094c\u0932\u0940"
    ],
    "name:ita_x_preferred":[
        "Karauli"
    ],
    "name:kan_x_preferred":[
        "\u0c95\u0cb0\u0ccc\u0cb2\u0cbf"
    ],
    "name:mal_x_preferred":[
        "\u0d15\u0d30\u0d57\u0d32\u0d3f"
    ],
    "name:mar_x_preferred":[
        "\u0915\u0930\u094c\u0932\u0940"
    ],
    "name:mlg_x_preferred":[
        "Karauli"
    ],
    "name:msa_x_preferred":[
        "Karauli"
    ],
    "name:new_x_preferred":[
        "\u0915\u0930\u094c\u0932\u0940"
    ],
    "name:pan_x_preferred":[
        "\u0a15\u0a30\u0a4c\u0a32\u0a40"
    ],
    "name:rus_x_preferred":[
        "\u041a\u0430\u0440\u0430\u0443\u043b\u0438"
    ],
    "name:san_x_preferred":[
        "\u0915\u0930\u094c\u0932\u0940"
    ],
    "name:swe_x_preferred":[
        "Karauli"
    ],
    "name:tam_x_preferred":[
        "\u0b95\u0bb0\u0bcc\u0bb2\u0bbf"
    ],
    "name:tel_x_preferred":[
        "\u0c15\u0c30\u0c4c\u0c32\u0c3f"
    ],
    "name:urd_x_preferred":[
        "\u06a9\u0631\u0648\u0644\u06cc"
    ],
    "name:urd_x_variant":[
        "\u06a9\u0627\u0631\u0648\u0644\u06cc"
    ],
    "name:vie_x_preferred":[
        "Karauli"
    ],
    "name:xmf_x_preferred":[
        "\u10d9\u10d0\u10e0\u10d0\u10e3\u10da\u10d8"
    ],
    "name:zho_x_preferred":[
        "\u5361\u52b3\u5229"
    ],
    "wof:name":"Kurauli",
    "wof:placetype":"neighbourhood",
    "wof:population":1817
},
  "geometry": {"coordinates":[81.154725,26.911935],"type":"Point"}
}