{
  "type": "Feature",
  "properties": {
    "gn:admin1_code":"19.0",
    "gn:admin2_code":"570.0",
    "gn:asciiname":"Kallenahalli",
    "gn:country_code":"IN",
    "gn:dem":792,
    "gn:feature_class":"P",
    "gn:feature_code":"PPL",
    "gn:name":"Kallenahalli",
    "gn:population":0,
    "gn:timezone":"Asia/Kolkata",
    "iso:country":"IN",
    "ks:ks_name":"Kallenahalli",
    "ks:ks_pop":992,
    "ks:ks_type":"VILLAGE",
    "name:eng_x_preferred":[
        "Kallenahalli"
    ],
    "wof:name":"Kallenahalli",
    "wof:placetype":"locality",
    "wof:population":992
},
  "geometry": {"coordinates":[76.045478,13.859991],"type":"Point"}
}