{
  "type": "Feature",
  "properties": {
    "gn:admin1_code":"24.0",
    "gn:admin2_code":"109.0",
    "gn:asciiname":"Balera ka Jhonpara",
    "gn:country_code":"IN",
    "gn:dem":279,
    "gn:feature_class":"P",
    "gn:feature_code":"PPL",
    "gn:name":"B\u0101lera ka Jhonpara",
    "gn:population":0,
    "gn:timezone":"Asia/Kolkata",
    "iso:country":"IN",
    "wof:name":"Balera ka Jhonpara",
    "wof:placetype":"locality"
},
  "geometry": {"coordinates":[76.26100000000002,26.48604000000001],"type":"Point"}
}