{
  "type": "Feature",
  "properties": {
    "gn:admin1_code":"11",
    "gn:admin2_code":"27.0",
    "gn:asciiname":"Giunkra",
    "gn:country_code":"IN",
    "gn:dem":1658,
    "gn:feature_class":"P",
    "gn:feature_code":"PPL",
    "gn:name":"Gi\u016bnkra",
    "gn:population":0,
    "gn:timezone":"Asia/Kolkata",
    "iso:country":"IN",
    "wof:name":"Giunkra",
    "wof:placetype":"locality"
},
  "geometry": {"coordinates":[76.99336,31.51023],"type":"Point"}
}