{
  "type": "Feature",
  "properties": {
    "gn:admin1_code":"2.0",
    "gn:asciiname":"Wangavapet",
    "gn:country_code":"IN",
    "gn:dem":341,
    "gn:feature_class":"P",
    "gn:feature_code":"PPL",
    "gn:name":"Wangavapet",
    "gn:population":0,
    "gn:timezone":"Asia/Kolkata",
    "iso:country":"IN",
    "wof:name":"Wangavapet",
    "wof:placetype":"locality"
},
  "geometry": {"coordinates":[78.31113000000001,19.1209],"type":"Point"}
}