{
  "type": "Feature",
  "properties": {
    "iso:country":"IN",
    "ks:ks_name":"Naudhiyaprahalad",
    "ks:ks_pop":1428,
    "ks:ks_type":"HABITATION",
    "name:eng_x_preferred":[
        "Naudhiyaprahalad"
    ],
    "wof:name":"Naudhiyaprahalad",
    "wof:placetype":"locality",
    "wof:population":1428
},
  "geometry": {"coordinates":[81.768119,24.651062],"type":"Point"}
}