{
  "type": "Feature",
  "properties": {
    "iso:country":"IN",
    "ks:ks_name":"G K Vandlavooru",
    "ks:ks_pop":454,
    "ks:ks_type":"HABITATION",
    "ks:ks_uagg_main":0,
    "name:eng_x_preferred":[
        "G K Vandlavooru"
    ],
    "wof:name":"G K Vandlavooru",
    "wof:placetype":"neighbourhood",
    "wof:population":454
},
  "geometry": {"coordinates":[78.898933,13.179192],"type":"Point"}
}