{
  "type": "Feature",
  "properties": {
    "iso:country":"IN",
    "ks:ks_name":"Gumari",
    "ks:ks_pop":10,
    "ks:ks_type":"HABITATION",
    "name:eng_x_preferred":[
        "Gumari"
    ],
    "wof:name":"Gumari",
    "wof:placetype":"locality",
    "wof:population":10
},
  "geometry": {"coordinates":[81.317212,25.069974],"type":"Point"}
}