{
  "type": "Feature",
  "properties": {
    "iso:country":"IN",
    "ks:ks_name":"Ravalpura",
    "ks:ks_pop":336,
    "ks:ks_type":"HABITATION",
    "name:eng_x_preferred":[
        "Ravalpura"
    ],
    "wof:name":"Ravalpura",
    "wof:placetype":"locality",
    "wof:population":336
},
  "geometry": {"coordinates":[72.79133299999999,22.379444],"type":"Point"}
}