{
  "type": "Feature",
  "properties": {
    "iso:country":"IN",
    "ks:ks_alt_nam":"Sataguri II",
    "ks:ks_name":"Sataguri Ii",
    "ks:ks_pop":519,
    "ks:ks_type":"HABITATION",
    "name:eng_x_preferred":[
        "Sataguri Ii"
    ],
    "wof:name":"Sataguri Ii",
    "wof:placetype":"locality",
    "wof:population":519
},
  "geometry": {"coordinates":[90.07384399999999,26.167148],"type":"Point"}
}