{
  "type": "Feature",
  "properties": {
    "iso:country":"IN",
    "name:heb_x_preferred":[
        "\u05d8\u05d5\u05d8\u05d9\u05e7\u05d5\u05e8\u05d9\u05df"
    ],
    "name:hun_x_preferred":[
        "Tuticorin"
    ],
    "ne:ADM0CAP":0.0,
    "ne:ADM0NAME":"India",
    "ne:ADM0_A3":"IND",
    "ne:ADM1NAME":"Tamil Nadu",
    "ne:ADMIN1_COD":0,
    "ne:CAPALT":0,
    "ne:CHANGED":1,
    "ne:CHECKME":0,
    "ne:COMPARE":0,
    "ne:DIFFASCII":0,
    "ne:DIFFNOTE":"Changed scale rank.",
    "ne:ELEVATION":0.0,
    "ne:FEATURECLA":"Populated place",
    "ne:GEONAMEID":-1,
    "ne:GN_POP":0,
    "ne:GTOPO30":0.0,
    "ne:ISO_A2":"IN",
    "ne:LABELRANK":1,
    "ne:LATITUDE":8.81999,
    "ne:LONGITUDE":78.130001,
    "ne:LS_MATCH":1,
    "ne:LS_NAME":"Tuticorin",
    "ne:MAX_AREAKM":68.0,
    "ne:MAX_AREAMI":26.0,
    "ne:MAX_BBXMAX":78.166667,
    "ne:MAX_BBXMIN":78.091667,
    "ne:MAX_BBYMAX":8.883333,
    "ne:MAX_BBYMIN":8.766667,
    "ne:MAX_NATSCA":20.0,
    "ne:MAX_PERKM":64.0,
    "ne:MAX_PERMI":40.0,
    "ne:MAX_POP10":367668,
    "ne:MAX_POP20":367668,
    "ne:MAX_POP300":0,
    "ne:MAX_POP310":0,
    "ne:MAX_POP50":0,
    "ne:MEAN_BBXC":78.133646,
    "ne:MEAN_BBYC":8.817292,
    "ne:MEGACITY":0,
    "ne:MIN_AREAKM":68.0,
    "ne:MIN_AREAMI":26.0,
    "ne:MIN_BBXMAX":78.166667,
    "ne:MIN_BBXMIN":78.091667,
    "ne:MIN_BBYMAX":8.883333,
    "ne:MIN_BBYMIN":8.766667,
    "ne:MIN_PERKM":64.0,
    "ne:MIN_PERMI":40.0,
    "ne:NAME":"Tuticorin",
    "ne:NAMEASCII":"Tuticorin",
    "ne:NAMEDIFF":0,
    "ne:NATSCALE":30,
    "ne:POP1950":0,
    "ne:POP1955":0,
    "ne:POP1960":0,
    "ne:POP1965":0,
    "ne:POP1970":0,
    "ne:POP1975":0,
    "ne:POP1980":0,
    "ne:POP1985":0,
    "ne:POP1990":0,
    "ne:POP1995":0,
    "ne:POP2000":0,
    "ne:POP2005":0,
    "ne:POP2010":0,
    "ne:POP2015":0,
    "ne:POP2020":0,
    "ne:POP2025":0,
    "ne:POP2050":0,
    "ne:POP_MAX":436094,
    "ne:POP_MIN":436094,
    "ne:POP_OTHER":694586,
    "ne:RANK_MAX":10,
    "ne:RANK_MIN":10,
    "ne:SCALERANK":6,
    "ne:SOV0NAME":"India",
    "ne:SOV_A3":"IND",
    "ne:UN_FID":0,
    "ne:UN_LAT":0.0,
    "ne:UN_LONG":0.0,
    "ne:WORLDCITY":0,
    "ne:min_zoom":6.0,
    "wof:name":"Tuticorin",
    "wof:placetype":"neighbourhood"
},
  "geometry": {"coordinates":[78.13000099999999,8.81999],"type":"Point"}
}