{
  "type": "Feature",
  "properties": {
    "gn:admin1_code":"37",
    "gn:admin2_code":"410.0",
    "gn:asciiname":"Kosmi",
    "gn:country_code":"IN",
    "gn:dem":353,
    "gn:feature_class":"P",
    "gn:feature_code":"PPL",
    "gn:name":"Kosmi",
    "gn:population":0,
    "gn:timezone":"Asia/Kolkata",
    "iso:country":"IN",
    "wof:name":"Kosmi",
    "wof:placetype":"locality"
},
  "geometry": {"coordinates":[82.11584000000001,20.69383],"type":"Point"}
}