{
  "type": "Feature",
  "properties": {
    "iso:country":"IN",
    "ks:ks_name":"Dhankowali",
    "ks:ks_pop":92,
    "ks:ks_type":"HABITATION",
    "name:eng_x_preferred":[
        "Dhankowali"
    ],
    "wof:name":"Dhankowali",
    "wof:placetype":"locality",
    "wof:population":92
},
  "geometry": {"coordinates":[78.181862,28.957756],"type":"Point"}
}