{
  "type": "Feature",
  "properties": {
    "iso:country":"IN",
    "ks:ks_name":"Ambalpuram",
    "ks:ks_pop":102,
    "ks:ks_type":"HABITATION",
    "ks:ks_uagg_main":0,
    "name:eng_x_preferred":[
        "Ambalpuram"
    ],
    "wof:name":"Ambalpuram",
    "wof:placetype":"neighbourhood",
    "wof:population":102
},
  "geometry": {"coordinates":[78.88259600000001,10.426165],"type":"Point"}
}