{
  "type": "Feature",
  "properties": {
    "iso:country":"IN",
    "ks:ks_name":"Latulia",
    "ks:ks_pop":447,
    "ks:ks_type":"VILLAGE",
    "name:eng_x_preferred":[
        "Latulia"
    ],
    "wof:name":"Latulia",
    "wof:placetype":"locality",
    "wof:population":447
},
  "geometry": {"coordinates":[86.96198699999999,23.465185],"type":"Point"}
}