{
  "type": "Feature",
  "properties": {
    "iso:country":"IN",
    "ks:ks_name":"Bhilon Ka Tala",
    "ks:ks_pop":203,
    "ks:ks_type":"VILLAGE",
    "name:eng_x_preferred":[
        "Bhilon Ka Tala"
    ],
    "wof:name":"Bhilon Ka Tala",
    "wof:placetype":"locality",
    "wof:population":203
},
  "geometry": {"coordinates":[70.691093,25.459526],"type":"Point"}
}