{
  "type": "Feature",
  "properties": {
    "iso:country":"IN",
    "ks:ks_name":"Dhakane Wasti",
    "ks:ks_pop":422,
    "ks:ks_type":"HABITATION",
    "name:eng_x_preferred":[
        "Dhakane Wasti"
    ],
    "wof:name":"Dhakane Wasti",
    "wof:placetype":"locality",
    "wof:population":422
},
  "geometry": {"coordinates":[75.241327,19.347954],"type":"Point"}
}