{
  "type": "Feature",
  "properties": {
    "iso:country":"IN",
    "ks:ks_name":"Karawndia",
    "ks:ks_pop":350,
    "ks:ks_type":"HABITATION",
    "name:eng_x_preferred":[
        "Karawndia"
    ],
    "wof:name":"Karawndia",
    "wof:placetype":"locality",
    "wof:population":350
},
  "geometry": {"coordinates":[83.25489899999999,24.641748],"type":"Point"}
}