{
  "type": "Feature",
  "properties": {
    "iso:country":"IN",
    "ks:ks_name":"Aolet",
    "ks:ks_pop":129,
    "ks:ks_type":"HABITATION",
    "name:eng_x_preferred":[
        "Aolet"
    ],
    "wof:name":"Aolet",
    "wof:placetype":"locality",
    "wof:population":129
},
  "geometry": {"coordinates":[79.149326,29.642429],"type":"Point"}
}