{
  "type": "Feature",
  "properties": {
    "iso:country":"IN",
    "ks:ks_name":"Bidve Wasti",
    "ks:ks_pop":59,
    "ks:ks_type":"HABITATION",
    "name:eng_x_preferred":[
        "Bidve Wasti"
    ],
    "wof:name":"Bidve Wasti",
    "wof:placetype":"locality",
    "wof:population":59
},
  "geometry": {"coordinates":[75.384231,18.445534],"type":"Point"}
}