{
  "type": "Feature",
  "properties": {
    "gn:admin1_code":"39",
    "gn:admin2_code":"61.0",
    "gn:asciiname":"Khadrasi",
    "gn:country_code":"IN",
    "gn:dem":636,
    "gn:feature_class":"P",
    "gn:feature_code":"PPL",
    "gn:name":"Khadr\u0101si",
    "gn:population":0,
    "gn:timezone":"Asia/Kolkata",
    "iso:country":"IN",
    "wof:name":"Khadrasi",
    "wof:placetype":"locality"
},
  "geometry": {"coordinates":[78.95084,29.64042],"type":"Point"}
}