{
  "type": "Feature",
  "properties": {
    "gn:admin1_code":"35",
    "gn:admin2_code":"423.0",
    "gn:asciiname":"Sihor",
    "gn:country_code":"IN",
    "gn:dem":241,
    "gn:feature_class":"P",
    "gn:feature_code":"PPL",
    "gn:name":"Sihor",
    "gn:population":0,
    "gn:timezone":"Asia/Kolkata",
    "iso:country":"IN",
    "name:bpy_x_preferred":[
        "\u09b8\u09bf\u09b9\u09cb\u09b0"
    ],
    "name:ceb_x_preferred":[
        "Sihor"
    ],
    "name:guj_x_preferred":[
        "\u0ab8\u0abf\u0ab9\u0acb\u0ab0"
    ],
    "name:hin_x_preferred":[
        "\u0938\u093f\u0939\u094b\u0930"
    ],
    "name:ind_x_preferred":[
        "Sihor"
    ],
    "name:ita_x_preferred":[
        "Sihor"
    ],
    "name:mar_x_preferred":[
        "\u0938\u093f\u0939\u094b\u0930"
    ],
    "name:msa_x_preferred":[
        "Sihor"
    ],
    "name:ori_x_preferred":[
        "Sihor"
    ],
    "name:pnb_x_preferred":[
        "\u0633\u0650\u06c1\u0648\u0631"
    ],
    "name:por_x_preferred":[
        "Sihor"
    ],
    "name:spa_x_preferred":[
        "Sihor"
    ],
    "name:swe_x_preferred":[
        "Sihor"
    ],
    "name:vie_x_preferred":[
        "Sihor"
    ],
    "name:zho_x_preferred":[
        "\u897f\u970d\u5c14"
    ],
    "wof:name":"Sihor",
    "wof:placetype":"locality"
},
  "geometry": {"coordinates":[78.10449,25.67246],"type":"Point"}
}