{
  "type": "Feature",
  "properties": {
    "gn:admin1_code":"11.0",
    "gn:admin2_code":"33.0",
    "gn:asciiname":"Rajtari",
    "gn:country_code":"IN",
    "gn:dem":2320,
    "gn:feature_class":"P",
    "gn:feature_code":"PPL",
    "gn:name":"Rajt\u0101ri",
    "gn:population":0,
    "gn:timezone":"Asia/Kolkata",
    "iso:country":"IN",
    "wof:name":"Rajtari",
    "wof:placetype":"locality"
},
  "geometry": {"coordinates":[77.51819999999999,31.20018],"type":"Point"}
}