{
  "type": "Feature",
  "properties": {
    "iso:country":"IN",
    "ks:ks_name":"Tibupada",
    "ks:ks_pop":73,
    "ks:ks_type":"VILLAGE",
    "name:eng_x_preferred":[
        "Tibupada"
    ],
    "wof:name":"Tibupada",
    "wof:placetype":"locality",
    "wof:population":73
},
  "geometry": {"coordinates":[84.92049900000001,21.87966],"type":"Point"}
}