{
  "type": "Feature",
  "properties": {
    "iso:country":"IN",
    "ks:ks_name":"Mel Syndicate",
    "ks:ks_pop":103,
    "ks:ks_type":"HABITATION",
    "name:eng_x_preferred":[
        "Mel Syndicate"
    ],
    "wof:name":"Mel Syndicate",
    "wof:placetype":"locality",
    "wof:population":103
},
  "geometry": {"coordinates":[79.41794,12.946351],"type":"Point"}
}