{
  "type": "Feature",
  "properties": {
    "iso:country":"IN",
    "ks:ks_name":"Munasari Barani",
    "ks:ks_pop":74,
    "ks:ks_type":"VILLAGE",
    "name:eng_x_preferred":[
        "Munasari Barani"
    ],
    "wof:name":"Munasari Barani",
    "wof:placetype":"locality",
    "wof:population":74
},
  "geometry": {"coordinates":[75.029149,29.10174],"type":"Point"}
}