{
  "type": "Feature",
  "properties": {
    "iso:country":"IN",
    "ks:ks_name":"Bele Chitte Keri",
    "ks:ks_pop":216,
    "ks:ks_type":"HABITATION",
    "name:eng_x_preferred":[
        "Bele Chitte Keri"
    ],
    "wof:name":"Bele Chitte Keri",
    "wof:placetype":"locality",
    "wof:population":216
},
  "geometry": {"coordinates":[74.422719,14.377026],"type":"Point"}
}