{
  "type": "Feature",
  "properties": {
    "iso:country":"IN",
    "ks:ks_name":"Ratghar Muafi",
    "ks:ks_pop":20,
    "ks:ks_type":"VILLAGE",
    "name:eng_x_preferred":[
        "Ratghar Muafi"
    ],
    "wof:name":"Ratghar Muafi",
    "wof:placetype":"locality",
    "wof:population":20
},
  "geometry": {"coordinates":[79.959508,29.787398],"type":"Point"}
}