{
  "type": "Feature",
  "properties": {
    "iso:country":"IN",
    "ks:ks_name":"Thirumangalapattinam",
    "ks:ks_pop":135,
    "ks:ks_type":"HABITATION",
    "ks:ks_uagg_main":0,
    "name:eng_x_preferred":[
        "Thirumangalapattinam"
    ],
    "wof:name":"Thirumangalapattinam",
    "wof:placetype":"neighbourhood",
    "wof:population":135
},
  "geometry": {"coordinates":[79.219521,10.09438],"type":"Point"}
}