{
  "type": "Feature",
  "properties": {
    "gn:admin1_code":"2.0",
    "gn:admin2_code":"543.0",
    "gn:asciiname":"Kella",
    "gn:country_code":"IN",
    "gn:dem":51,
    "gn:feature_class":"P",
    "gn:feature_code":"PPL",
    "gn:name":"Kella",
    "gn:population":0,
    "gn:timezone":"Asia/Kolkata",
    "iso:country":"IN",
    "name:bak_x_preferred":[
        "\u041a\u0435\u043b\u043b\u0430"
    ],
    "name:ceb_x_preferred":[
        "Kella"
    ],
    "name:deu_x_preferred":[
        "Kella"
    ],
    "name:epo_x_preferred":[
        "Kella"
    ],
    "name:eus_x_preferred":[
        "Kella"
    ],
    "name:fra_x_preferred":[
        "Kella"
    ],
    "name:hun_x_preferred":[
        "Kella"
    ],
    "name:ita_x_preferred":[
        "Kella"
    ],
    "name:kaz_x_preferred":[
        "\u041a\u0435\u043b\u043b\u0430"
    ],
    "name:kir_x_preferred":[
        "\u041a\u0435\u043b\u043b\u0430"
    ],
    "name:mkd_x_preferred":[
        "\u041a\u0435\u043b\u0430"
    ],
    "name:msa_x_preferred":[
        "Kella"
    ],
    "name:nld_x_preferred":[
        "Kella"
    ],
    "name:pol_x_preferred":[
        "Kella"
    ],
    "name:por_x_preferred":[
        "Kella"
    ],
    "name:ron_x_preferred":[
        "Kella"
    ],
    "name:rus_x_preferred":[
        "\u041a\u0435\u043b\u043b\u0430"
    ],
    "name:spa_x_preferred":[
        "Kella"
    ],
    "name:srp_x_preferred":[
        "\u041a\u0435\u043b\u0430"
    ],
    "name:ukr_x_preferred":[
        "\u041a\u0435\u043b\u043b\u0430"
    ],
    "name:uzb_x_preferred":[
        "Kella"
    ],
    "name:vie_x_preferred":[
        "Kella"
    ],
    "name:vol_x_preferred":[
        "Kella"
    ],
    "name:war_x_preferred":[
        "Kella"
    ],
    "wof:name":"Kella",
    "wof:placetype":"locality"
},
  "geometry": {"coordinates":[83.48841,18.21044],"type":"Point"}
}