{
  "type": "Feature",
  "properties": {
    "gn:admin1_code":"34.0",
    "gn:admin2_code":"203.0",
    "gn:asciiname":"Mathauli",
    "gn:country_code":"IN",
    "gn:dem":79,
    "gn:feature_class":"P",
    "gn:feature_code":"PPL",
    "gn:name":"Mathauli",
    "gn:population":0,
    "gn:timezone":"Asia/Kolkata",
    "iso:country":"IN",
    "ks:ks_name":"Mathauli",
    "ks:ks_pop":1386,
    "ks:ks_type":"VILLAGE",
    "ks:ks_uagg_main":0,
    "name:eng_x_preferred":[
        "Mathauli"
    ],
    "wof:name":"Mathauli",
    "wof:placetype":"neighbourhood",
    "wof:population":1386
},
  "geometry": {"coordinates":[84.468281,26.803641],"type":"Point"}
}