{
  "type": "Feature",
  "properties": {
    "gn:admin1_code":"11",
    "gn:admin2_code":"33.0",
    "gn:asciiname":"Daluri",
    "gn:country_code":"IN",
    "gn:dem":1889,
    "gn:feature_class":"P",
    "gn:feature_code":"PPL",
    "gn:name":"Daluri",
    "gn:population":0,
    "gn:timezone":"Asia/Kolkata",
    "iso:country":"IN",
    "wof:name":"Daluri",
    "wof:placetype":"locality"
},
  "geometry": {"coordinates":[77.65774,30.82234],"type":"Point"}
}