{
  "type": "Feature",
  "properties": {
    "iso:country":"IN",
    "ks:ks_name":"Jivajihatti",
    "ks:ks_pop":130,
    "ks:ks_type":"HABITATION",
    "name:eng_x_preferred":[
        "Jivajihatti"
    ],
    "wof:name":"Jivajihatti",
    "wof:placetype":"locality",
    "wof:population":130
},
  "geometry": {"coordinates":[76.947351,13.083783],"type":"Point"}
}