{
  "type": "Feature",
  "properties": {
    "iso:country":"IN",
    "ks:ks_name":"Neemkhedi",
    "ks:ks_pop":358,
    "ks:ks_type":"VILLAGE",
    "name:eng_x_preferred":[
        "Neemkhedi"
    ],
    "wof:name":"Neemkhedi",
    "wof:placetype":"locality",
    "wof:population":358
},
  "geometry": {"coordinates":[75.963823,22.11815],"type":"Point"}
}