{
  "type": "Feature",
  "properties": {
    "gn:admin1_code":"38.0",
    "gn:admin2_code":"358.0",
    "gn:asciiname":"Tandwa",
    "gn:country_code":"IN",
    "gn:dem":343,
    "gn:feature_class":"P",
    "gn:feature_code":"PPL",
    "gn:name":"Tandw\u0101",
    "gn:population":0,
    "gn:timezone":"Asia/Kolkata",
    "iso:country":"IN",
    "ks:ks_name":"Tanrwa",
    "ks:ks_pop":441,
    "ks:ks_type":"VILLAGE",
    "name:eng_x_preferred":[
        "Tanrwa"
    ],
    "name:eng_x_variant":[
        "Tandwa"
    ],
    "wof:name":"Tanrwa",
    "wof:placetype":"locality",
    "wof:population":441
},
  "geometry": {"coordinates":[84.379642,24.233055],"type":"Point"}
}