{
  "type": "Feature",
  "properties": {
    "iso:country":"IN",
    "ks:ks_name":"Goraitamaran",
    "ks:ks_pop":311,
    "ks:ks_type":"VILLAGE",
    "ks:ks_uagg_main":0,
    "name:eng_x_preferred":[
        "Goraitamaran"
    ],
    "wof:name":"Goraitamaran",
    "wof:placetype":"neighbourhood",
    "wof:population":311
},
  "geometry": {"coordinates":[85.944836,24.329394],"type":"Point"}
}