{
  "type": "Feature",
  "properties": {
    "gn:admin1_code":"24.0",
    "gn:admin2_code":"102",
    "gn:asciiname":"Thathawta",
    "gn:country_code":"IN",
    "gn:dem":318,
    "gn:feature_class":"P",
    "gn:feature_code":"PPL",
    "gn:name":"Thath\u0101wta",
    "gn:population":0,
    "gn:timezone":"Asia/Kolkata",
    "iso:country":"IN",
    "name:und_x_variant":[
        "Thath\u0101wta",
        "Tath\u0101to"
    ],
    "wof:name":"Thathawta",
    "wof:placetype":"locality"
},
  "geometry": {"coordinates":[74.77019,28.0147],"type":"Point"}
}