{
  "type": "Feature",
  "properties": {
    "gn:admin1_code":"24.0",
    "gn:admin2_code":"122.0",
    "gn:asciiname":"Daulatpura",
    "gn:country_code":"IN",
    "gn:dem":417,
    "gn:feature_class":"P",
    "gn:feature_code":"PPL",
    "gn:name":"Daulatpura",
    "gn:population":0,
    "gn:timezone":"Asia/Kolkata",
    "iso:country":"IN",
    "wof:name":"Daulatpura",
    "wof:placetype":"locality"
},
  "geometry": {"coordinates":[74.71084,25.43602000000001],"type":"Point"}
}