{
  "type": "Feature",
  "properties": {
    "iso:country":"IN",
    "ks:ks_name":"Anapperuvazhi",
    "ks:ks_pop":62,
    "ks:ks_type":"HABITATION",
    "ks:ks_uagg_main":0,
    "name:eng_x_preferred":[
        "Anapperuvazhi"
    ],
    "wof:name":"Anapperuvazhi",
    "wof:placetype":"neighbourhood",
    "wof:population":62
},
  "geometry": {"coordinates":[76.241496,10.608426],"type":"Point"}
}