{
  "type": "Feature",
  "properties": {
    "iso:country":"IN",
    "ks:ks_alt_nam":"dhoodhnathpurwa",
    "ks:ks_name":"Dhoodhnathpurwa",
    "ks:ks_pop":450,
    "ks:ks_type":"HABITATION",
    "name:eng_x_preferred":[
        "Dhoodhnathpurwa"
    ],
    "wof:name":"Dhoodhnathpurwa",
    "wof:placetype":"locality",
    "wof:population":450
},
  "geometry": {"coordinates":[81.10696900000001,28.243314],"type":"Point"}
}