{
  "type": "Feature",
  "properties": {
    "iso:country":"IN",
    "ks:ks_name":"Mithilakodi",
    "ks:ks_pop":142,
    "ks:ks_type":"HABITATION",
    "name:eng_x_preferred":[
        "Mithilakodi"
    ],
    "wof:name":"Mithilakodi",
    "wof:placetype":"locality",
    "wof:population":142
},
  "geometry": {"coordinates":[75.070733,12.880466],"type":"Point"}
}