{
  "type": "Feature",
  "properties": {
    "iso:country":"IN",
    "ks:ks_name":"7PHM",
    "ks:ks_pop":2504,
    "ks:ks_type":"VILLAGE",
    "name:eng_x_preferred":[
        "7PHM"
    ],
    "wof:name":"7PHM",
    "wof:placetype":"locality",
    "wof:population":2504
},
  "geometry": {"coordinates":[72.65213199999999,28.749144],"type":"Point"}
}