{
  "type": "Feature",
  "properties": {
    "iso:country":"IN",
    "ks:ks_name":"Sengulathupatti",
    "ks:ks_pop":186,
    "ks:ks_type":"HABITATION",
    "name:eng_x_preferred":[
        "Sengulathupatti"
    ],
    "wof:name":"Sengulathupatti",
    "wof:placetype":"locality",
    "wof:population":186
},
  "geometry": {"coordinates":[78.05592799999999,10.602393],"type":"Point"}
}