{
  "type": "Feature",
  "properties": {
    "gn:admin1_code":"39",
    "gn:admin2_code":"61.0",
    "gn:asciiname":"Sainji",
    "gn:country_code":"IN",
    "gn:dem":1620,
    "gn:feature_class":"P",
    "gn:feature_code":"PPL",
    "gn:name":"Sainji",
    "gn:population":0,
    "gn:timezone":"Asia/Kolkata",
    "iso:country":"IN",
    "ks:ks_name":"Saiji",
    "ks:ks_pop":880,
    "ks:ks_type":"VILLAGE",
    "name:eng_x_preferred":[
        "Saiji"
    ],
    "name:eng_x_variant":[
        "Sainji"
    ],
    "wof:name":"Saiji",
    "wof:placetype":"locality",
    "wof:population":880
},
  "geometry": {"coordinates":[78.967471,30.070116],"type":"Point"}
}