{
  "type": "Feature",
  "properties": {
    "iso:country":"IN",
    "ks:ks_name":"Roluguntapadu",
    "ks:ks_pop":189,
    "ks:ks_type":"HABITATION",
    "name:eng_x_preferred":[
        "Roluguntapadu"
    ],
    "wof:name":"Roluguntapadu",
    "wof:placetype":"locality",
    "wof:population":189
},
  "geometry": {"coordinates":[82.47896799999999,17.789251],"type":"Point"}
}