{
  "type": "Feature",
  "properties": {
    "gn:admin1_code":"19.0",
    "gn:admin2_code":"574.0",
    "gn:asciiname":"Chilakura",
    "gn:country_code":"IN",
    "gn:dem":977,
    "gn:feature_class":"P",
    "gn:feature_code":"PPL",
    "gn:name":"Chilak\u016bra",
    "gn:population":0,
    "gn:timezone":"Asia/Kolkata",
    "iso:country":"IN",
    "wof:name":"Chilakura",
    "wof:placetype":"neighbourhood"
},
  "geometry": {"coordinates":[75.92643,13.14404],"type":"Point"}
}