{
  "type": "Feature",
  "properties": {
    "iso:country":"IN",
    "ks:ks_name":"Manhguwan",
    "ks:ks_pop":827,
    "ks:ks_type":"HABITATION",
    "name:eng_x_preferred":[
        "Manhguwan"
    ],
    "wof:name":"Manhguwan",
    "wof:placetype":"locality",
    "wof:population":827
},
  "geometry": {"coordinates":[79.250274,23.647047],"type":"Point"}
}