{
  "type": "Feature",
  "properties": {
    "gn:admin1_code":"24.0",
    "gn:admin2_code":"108.0",
    "gn:asciiname":"Phuledi",
    "gn:country_code":"IN",
    "gn:dem":230,
    "gn:feature_class":"P",
    "gn:feature_code":"PPL",
    "gn:name":"Phuledi",
    "gn:population":0,
    "gn:timezone":"Asia/Kolkata",
    "iso:country":"IN",
    "name:und_x_variant":[
        "Anantpura"
    ],
    "wof:name":"Phuledi",
    "wof:placetype":"locality"
},
  "geometry": {"coordinates":[76.59256999999999,25.99102],"type":"Point"}
}