{
  "type": "Feature",
  "properties": {
    "gn:admin1_code":"34.0",
    "gn:admin2_code":"218.0",
    "gn:asciiname":"Dagri",
    "gn:country_code":"IN",
    "gn:dem":70,
    "gn:feature_class":"P",
    "gn:feature_code":"PPL",
    "gn:name":"Dagri",
    "gn:population":0,
    "gn:timezone":"Asia/Kolkata",
    "iso:country":"IN",
    "name:msa_x_preferred":[
        "Dagri"
    ],
    "name:und_x_variant":[
        "Mathia"
    ],
    "wof:name":"Dagri",
    "wof:placetype":"neighbourhood"
},
  "geometry": {"coordinates":[84.58734,26.27394],"type":"Point"}
}