{
  "type": "Feature",
  "properties": {
    "iso:country":"IN",
    "ks:ks_alt_nam":"R.S.H.T.",
    "ks:ks_name":"R.s.h.t.",
    "ks:ks_pop":169,
    "ks:ks_type":"HABITATION",
    "name:eng_x_preferred":[
        "R.s.h.t."
    ],
    "wof:name":"R.s.h.t.",
    "wof:placetype":"locality",
    "wof:population":169
},
  "geometry": {"coordinates":[83.72635,25.0699],"type":"Point"}
}