{
  "type": "Feature",
  "properties": {
    "iso:country":"IN",
    "ks:ks_name":"Gusayo Ki Dhani",
    "ks:ks_pop":30,
    "ks:ks_type":"HABITATION",
    "name:eng_x_preferred":[
        "Gusayo Ki Dhani"
    ],
    "wof:name":"Gusayo Ki Dhani",
    "wof:placetype":"locality",
    "wof:population":30
},
  "geometry": {"coordinates":[75.322417,28.252722],"type":"Point"}
}