{
  "type": "Feature",
  "properties": {
    "iso:country":"IN",
    "ks:ks_name":"Pachaghar",
    "ks:ks_pop":81,
    "ks:ks_type":"VILLAGE",
    "name:eng_x_preferred":[
        "Pachaghar"
    ],
    "wof:name":"Pachaghar",
    "wof:placetype":"locality",
    "wof:population":81
},
  "geometry": {"coordinates":[73.173171,18.272884],"type":"Point"}
}