{
  "type": "Feature",
  "properties": {
    "iso:country":"IN",
    "ks:ks_alt_nam":"R\u0101mnagar",
    "ks:ks_name":"Ramnagar",
    "ks:ks_pop":340,
    "ks:ks_type":"VILLAGE",
    "name:eng_x_preferred":[
        "Ramnagar"
    ],
    "name:eng_x_variant":[
        "R\u0101mnagar"
    ],
    "wof:name":"Ramnagar",
    "wof:placetype":"locality",
    "wof:population":340
},
  "geometry": {"coordinates":[79.467826,24.178441],"type":"Point"}
}