{
  "type": "Feature",
  "properties": {
    "gn:admin1_code":"39",
    "gn:admin2_code":"61.0",
    "gn:asciiname":"Khandorah",
    "gn:country_code":"IN",
    "gn:dem":1129,
    "gn:feature_class":"P",
    "gn:feature_code":"PPL",
    "gn:name":"Khandorah",
    "gn:population":0,
    "gn:timezone":"Asia/Kolkata",
    "iso:country":"IN",
    "wof:name":"Khandorah",
    "wof:placetype":"locality"
},
  "geometry": {"coordinates":[78.80556,30.0121],"type":"Point"}
}