{
  "type": "Feature",
  "properties": {
    "iso:country":"IN",
    "ks:ks_alt_nam":"BIRITIYA DANDAR",
    "ks:ks_name":"Biritiya Dandar",
    "ks:ks_pop":229,
    "ks:ks_type":"HABITATION",
    "name:eng_x_preferred":[
        "Biritiya Dandar"
    ],
    "wof:name":"Biritiya Dandar",
    "wof:placetype":"locality",
    "wof:population":229
},
  "geometry": {"coordinates":[84.326324,24.013216],"type":"Point"}
}