{
  "type": "Feature",
  "properties": {
    "gn:admin1_code":"37",
    "gn:admin2_code":"406.0",
    "gn:asciiname":"Dhepnipani",
    "gn:country_code":"IN",
    "gn:dem":466,
    "gn:feature_class":"P",
    "gn:feature_code":"PPL",
    "gn:name":"Dhepn\u012bp\u0101ni",
    "gn:population":0,
    "gn:timezone":"Asia/Kolkata",
    "iso:country":"IN",
    "ks:ks_alt_nam":"DHAPNIPANI",
    "ks:ks_name":"Dhapnipani",
    "ks:ks_pop":486,
    "ks:ks_type":"HABITATION",
    "name:eng_x_preferred":[
        "Dhapnipani"
    ],
    "name:eng_x_variant":[
        "Dhepnipani"
    ],
    "wof:name":"Dhapnipani",
    "wof:placetype":"locality",
    "wof:population":486
},
  "geometry": {"coordinates":[82.15235300000001,22.999702],"type":"Point"}
}