{
  "type": "Feature",
  "properties": {
    "iso:country":"IN",
    "ks:ks_name":"Bellari",
    "ks:ks_pop":30,
    "ks:ks_type":"HABITATION",
    "name:eng_x_preferred":[
        "Bellari"
    ],
    "wof:name":"Bellari",
    "wof:placetype":"locality",
    "wof:population":30
},
  "geometry": {"coordinates":[74.493577,14.29988],"type":"Point"}
}