{
  "type": "Feature",
  "properties": {
    "gn:admin1_code":"39.0",
    "gn:admin2_code":"64.0",
    "gn:asciiname":"Phalson",
    "gn:country_code":"IN",
    "gn:dem":1346,
    "gn:feature_class":"P",
    "gn:feature_code":"PPL",
    "gn:name":"Phalson",
    "gn:population":0,
    "gn:timezone":"Asia/Kolkata",
    "iso:country":"IN",
    "ks:ks_name":"Phalson",
    "ks:ks_type":"VILLAGE",
    "name:eng_x_preferred":[
        "Phalson"
    ],
    "wof:name":"Phalson",
    "wof:placetype":"locality"
},
  "geometry": {"coordinates":[79.27203900000001,29.616263],"type":"Point"}
}