{
  "type": "Feature",
  "properties": {
    "iso:country":"IN",
    "ks:ks_name":"Pambola",
    "ks:ks_pop":890,
    "ks:ks_type":"HABITATION",
    "name:eng_x_preferred":[
        "Pambola"
    ],
    "wof:name":"Pambola",
    "wof:placetype":"locality",
    "wof:population":890
},
  "geometry": {"coordinates":[75.852271,11.788546],"type":"Point"}
}