{
  "type": "Feature",
  "properties": {
    "iso:country":"IN",
    "ks:ks_alt_nam":"LALA PUR",
    "ks:ks_name":"Lala Pur",
    "ks:ks_pop":247,
    "ks:ks_type":"HABITATION",
    "name:eng_x_preferred":[
        "Lala Pur"
    ],
    "wof:name":"Lala Pur",
    "wof:placetype":"locality",
    "wof:population":247
},
  "geometry": {"coordinates":[82.710408,25.278076],"type":"Point"}
}