{
  "type": "Feature",
  "properties": {
    "iso:country":"IN",
    "ks:ks_name":"Matkhar",
    "ks:ks_pop":30,
    "ks:ks_type":"HABITATION",
    "name:eng_x_preferred":[
        "Matkhar"
    ],
    "wof:name":"Matkhar",
    "wof:placetype":"locality",
    "wof:population":30
},
  "geometry": {"coordinates":[84.493278,23.674484],"type":"Point"}
}