{
  "type": "Feature",
  "properties": {
    "iso:country":"IN",
    "ks:ks_name":"Jhumukadiha",
    "ks:ks_pop":30,
    "ks:ks_type":"VILLAGE",
    "name:eng_x_preferred":[
        "Jhumukadiha"
    ],
    "wof:name":"Jhumukadiha",
    "wof:placetype":"locality",
    "wof:population":30
},
  "geometry": {"coordinates":[84.349546,19.150489],"type":"Point"}
}