{
  "type": "Feature",
  "properties": {
    "iso:country":"IN",
    "ks:ks_name":"Gurdhanpur",
    "ks:ks_pop":8,
    "ks:ks_type":"HABITATION",
    "name:eng_x_preferred":[
        "Gurdhanpur"
    ],
    "wof:name":"Gurdhanpur",
    "wof:placetype":"locality",
    "wof:population":8
},
  "geometry": {"coordinates":[77.385825,30.255631],"type":"Point"}
}