{
  "type": "Feature",
  "properties": {
    "gn:admin1_code":"11",
    "gn:admin2_code":"23.0",
    "gn:asciiname":"Challa",
    "gn:country_code":"IN",
    "gn:dem":3080,
    "gn:feature_class":"P",
    "gn:feature_code":"PPL",
    "gn:name":"Challa",
    "gn:population":0,
    "gn:timezone":"Asia/Kolkata",
    "iso:country":"IN",
    "name:nld_x_preferred":[
        "Challa"
    ],
    "name:tel_x_preferred":[
        "\u0c1a\u0c32\u0c4d\u0c32\u0c3e"
    ],
    "wof:name":"Challa",
    "wof:placetype":"locality"
},
  "geometry": {"coordinates":[76.23218,32.68295],"type":"Point"}
}