{
  "type": "Feature",
  "properties": {
    "iso:country":"IN",
    "ks:ks_name":"Jairam Pur",
    "ks:ks_pop":65,
    "ks:ks_type":"VILLAGE",
    "name:eng_x_preferred":[
        "Jairam Pur"
    ],
    "wof:name":"Jairam Pur",
    "wof:placetype":"locality",
    "wof:population":65
},
  "geometry": {"coordinates":[82.993437,25.901492],"type":"Point"}
}