{
  "type": "Feature",
  "properties": {
    "gn:admin1_code":"9.0",
    "gn:admin2_code":"484.0",
    "gn:asciiname":"Amba",
    "gn:country_code":"IN",
    "gn:dem":156,
    "gn:feature_class":"P",
    "gn:feature_code":"PPL",
    "gn:name":"Amba",
    "gn:population":0,
    "gn:timezone":"Asia/Kolkata",
    "iso:country":"IN",
    "ks:ks_name":"Amba",
    "ks:ks_pop":259,
    "ks:ks_type":"VILLAGE",
    "name:ceb_x_preferred":[
        "Amba"
    ],
    "name:eng_x_preferred":[
        "Amba"
    ],
    "name:fra_x_preferred":[
        "Amba"
    ],
    "name:ita_x_preferred":[
        "Amba"
    ],
    "name:pol_x_preferred":[
        "Amba"
    ],
    "name:rus_x_preferred":[
        "\u0410\u043c\u0431\u0430"
    ],
    "name:spa_x_preferred":[
        "Amba"
    ],
    "name:swe_x_preferred":[
        "Amba"
    ],
    "wof:name":"Amba",
    "wof:placetype":"locality",
    "wof:population":259
},
  "geometry": {"coordinates":[73.88883300000001,23.09475],"type":"Point"}
}