{
  "type": "Feature",
  "properties": {
    "gn:admin1_code":"36.0",
    "gn:admin2_code":"135.0",
    "gn:asciiname":"Sarai Panju",
    "gn:country_code":"IN",
    "gn:dem":199,
    "gn:feature_class":"P",
    "gn:feature_code":"PPL",
    "gn:name":"Sar\u0101i Panju",
    "gn:population":0,
    "gn:timezone":"Asia/Kolkata",
    "iso:country":"IN",
    "ks:ks_alt_nam":"Sar\u0101i Panju",
    "ks:ks_name":"Sarai Panju",
    "ks:ks_type":"VILLAGE",
    "name:eng_x_preferred":[
        "Sarai Panju"
    ],
    "name:eng_x_variant":[
        "Sar\u0101i Panju"
    ],
    "wof:name":"Sarai Panju",
    "wof:placetype":"locality"
},
  "geometry": {"coordinates":[78.751203,28.671467],"type":"Point"}
}