{
  "type": "Feature",
  "properties": {
    "iso:country":"IN",
    "ks:ks_alt_nam":"Kusm\u0101ha",
    "ks:ks_name":"Kusmaha",
    "ks:ks_pop":589,
    "ks:ks_type":"VILLAGE",
    "name:eng_x_preferred":[
        "Kusmaha"
    ],
    "name:eng_x_variant":[
        "Kusm\u0101ha"
    ],
    "wof:name":"Kusmaha",
    "wof:placetype":"locality",
    "wof:population":589
},
  "geometry": {"coordinates":[84.863474,24.355922],"type":"Point"}
}