{
  "type": "Feature",
  "properties": {
    "gn:admin1_code":"37",
    "gn:admin2_code":"410.0",
    "gn:asciiname":"Hardi",
    "gn:country_code":"IN",
    "gn:dem":241,
    "gn:feature_class":"P",
    "gn:feature_code":"PPL",
    "gn:name":"Hardi",
    "gn:population":0,
    "gn:timezone":"Asia/Kolkata",
    "iso:country":"IN",
    "wof:name":"Hardi",
    "wof:placetype":"locality"
},
  "geometry": {"coordinates":[82.35975999999999,21.60469],"type":"Point"}
}