{
  "type": "Feature",
  "properties": {
    "gn:admin1_code":"12.0",
    "gn:admin2_code":"2.0",
    "gn:asciiname":"Gazargund",
    "gn:country_code":"IN",
    "gn:dem":1762,
    "gn:feature_class":"P",
    "gn:feature_code":"PPL",
    "gn:name":"Gazargund",
    "gn:population":0,
    "gn:timezone":"Asia/Kolkata",
    "iso:country":"IN",
    "wof:name":"Gazargund",
    "wof:placetype":"locality"
},
  "geometry": {"coordinates":[74.70518,33.99438],"type":"Point"}
}