{
  "type": "Feature",
  "properties": {
    "iso:country":"IN",
    "ks:ks_name":"Soiya Tola",
    "ks:ks_pop":470,
    "ks:ks_type":"HABITATION",
    "name:eng_x_preferred":[
        "Soiya Tola"
    ],
    "wof:name":"Soiya Tola",
    "wof:placetype":"locality",
    "wof:population":470
},
  "geometry": {"coordinates":[83.420534,26.963732],"type":"Point"}
}