{
  "type": "Feature",
  "properties": {
    "iso:country":"IN",
    "ks:ks_name":"Dhungiaatala",
    "ks:ks_pop":31,
    "ks:ks_type":"HABITATION",
    "name:eng_x_preferred":[
        "Dhungiaatala"
    ],
    "wof:name":"Dhungiaatala",
    "wof:placetype":"locality",
    "wof:population":31
},
  "geometry": {"coordinates":[82.172871,18.733021],"type":"Point"}
}