{
  "type": "Feature",
  "properties": {
    "gn:admin1_code":"35",
    "gn:admin2_code":"434.0",
    "gn:asciiname":"Mamatkhera",
    "gn:country_code":"IN",
    "gn:dem":504,
    "gn:feature_class":"P",
    "gn:feature_code":"PPL",
    "gn:name":"M\u0101matkhera",
    "gn:population":0,
    "gn:timezone":"Asia/Kolkata",
    "iso:country":"IN",
    "wof:name":"Mamatkhera",
    "wof:placetype":"locality"
},
  "geometry": {"coordinates":[75.08320999999999,23.66802],"type":"Point"}
}