{
  "type": "Feature",
  "properties": {
    "iso:country":"IN",
    "ks:ks_name":"Khorari",
    "ks:ks_pop":524,
    "ks:ks_type":"VILLAGE",
    "name:eng_x_preferred":[
        "Khorari"
    ],
    "wof:name":"Khorari",
    "wof:placetype":"locality",
    "wof:population":524
},
  "geometry": {"coordinates":[82.496279,27.027798],"type":"Point"}
}