{
  "type": "Feature",
  "properties": {
    "iso:country":"IN",
    "ks:ks_name":"Janpar Chuk",
    "ks:ks_pop":410,
    "ks:ks_type":"HABITATION",
    "ks:ks_uagg_main":0,
    "name:eng_x_preferred":[
        "Janpar Chuk"
    ],
    "wof:name":"Janpar Chuk",
    "wof:placetype":"neighbourhood",
    "wof:population":410
},
  "geometry": {"coordinates":[93.82389499999999,26.625109],"type":"Point"}
}