{
  "type": "Feature",
  "properties": {
    "iso:country":"IN",
    "ks:ks_name":"Papahra",
    "ks:ks_pop":0,
    "ks:ks_type":"VILLAGE",
    "name:eng_x_preferred":[
        "Papahra"
    ],
    "wof:name":"Papahra",
    "wof:placetype":"locality",
    "wof:population":0
},
  "geometry": {"coordinates":[83.59205900000001,24.965235],"type":"Point"}
}