{
  "type": "Feature",
  "properties": {
    "gn:admin1_code":"36",
    "gn:admin2_code":"187.0",
    "gn:asciiname":"Bartolia",
    "gn:country_code":"IN",
    "gn:dem":86,
    "gn:feature_class":"P",
    "gn:feature_code":"PPL",
    "gn:name":"Bartolia",
    "gn:population":0,
    "gn:timezone":"Asia/Kolkata",
    "iso:country":"IN",
    "ks:ks_name":"Bari Tola",
    "ks:ks_pop":455,
    "ks:ks_type":"HABITATION",
    "name:eng_x_preferred":[
        "Bari Tola"
    ],
    "name:eng_x_variant":[
        "Bartolia"
    ],
    "wof:name":"Bari Tola",
    "wof:placetype":"locality",
    "wof:population":455
},
  "geometry": {"coordinates":[83.491212,26.939391],"type":"Point"}
}