{
  "type": "Feature",
  "properties": {
    "iso:country":"IN",
    "ks:ks_name":"Gopalpur Tola 2",
    "ks:ks_pop":720,
    "ks:ks_type":"HABITATION",
    "name:eng_x_preferred":[
        "Gopalpur Tola 2"
    ],
    "wof:name":"Gopalpur Tola 2",
    "wof:placetype":"locality",
    "wof:population":720
},
  "geometry": {"coordinates":[86.81513699999999,23.496316],"type":"Point"}
}