{
  "type": "Feature",
  "properties": {
    "iso:country":"IN",
    "ks:ks_name":"Gaidhanewasti",
    "ks:ks_pop":237,
    "ks:ks_type":"HABITATION",
    "name:eng_x_preferred":[
        "Gaidhanewasti"
    ],
    "wof:name":"Gaidhanewasti",
    "wof:placetype":"locality",
    "wof:population":237
},
  "geometry": {"coordinates":[75.18583099999999,19.462988],"type":"Point"}
}