{
  "type": "Feature",
  "properties": {
    "iso:country":"IN",
    "ks:ks_name":"Biranchiya",
    "ks:ks_pop":727,
    "ks:ks_type":"HABITATION",
    "name:eng_x_preferred":[
        "Biranchiya"
    ],
    "wof:name":"Biranchiya",
    "wof:placetype":"locality",
    "wof:population":727
},
  "geometry": {"coordinates":[87.138867,25.836601],"type":"Point"}
}