{
  "type": "Feature",
  "properties": {
    "gn:admin1_code":"35",
    "gn:admin2_code":"448.0",
    "gn:asciiname":"Undhal",
    "gn:country_code":"IN",
    "gn:dem":268,
    "gn:feature_class":"P",
    "gn:feature_code":"PPL",
    "gn:name":"\u016andh\u0101l",
    "gn:population":0,
    "gn:timezone":"Asia/Kolkata",
    "iso:country":"IN",
    "ks:ks_alt_nam":"\u016andh\u0101l",
    "ks:ks_name":"Undhal",
    "ks:ks_pop":244,
    "ks:ks_type":"VILLAGE",
    "name:eng_x_preferred":[
        "Undhal"
    ],
    "name:eng_x_variant":[
        "\u016andh\u0101l"
    ],
    "wof:name":"Undhal",
    "wof:placetype":"locality",
    "wof:population":244
},
  "geometry": {"coordinates":[76.841711,22.445109],"type":"Point"}
}