{
  "type": "Feature",
  "properties": {
    "gn:admin1_code":"40.0",
    "gn:admin2_code":"534.0",
    "gn:asciiname":"Aknepalli",
    "gn:country_code":"IN",
    "gn:dem":162,
    "gn:feature_class":"P",
    "gn:feature_code":"PPL",
    "gn:name":"Aknepalli",
    "gn:population":0,
    "gn:timezone":"Asia/Kolkata",
    "iso:country":"IN",
    "wof:name":"Aknepalli",
    "wof:placetype":"locality"
},
  "geometry": {"coordinates":[79.36764000000002,18.7903],"type":"Point"}
}