{
  "type": "Feature",
  "properties": {
    "iso:country":"IN",
    "ks:ks_name":"Kondajji",
    "ks:ks_type":"VILLAGE",
    "name:eng_x_preferred":[
        "Kondajji"
    ],
    "wof:name":"Kondajji",
    "wof:placetype":"locality"
},
  "geometry": {"coordinates":[75.495831,14.075022],"type":"Point"}
}