{
  "type": "Feature",
  "properties": {
    "iso:country":"IN",
    "ks:ks_name":"Gajadhar Tola",
    "ks:ks_pop":794,
    "ks:ks_type":"VILLAGE",
    "name:eng_x_preferred":[
        "Gajadhar Tola"
    ],
    "wof:name":"Gajadhar Tola",
    "wof:placetype":"locality",
    "wof:population":794
},
  "geometry": {"coordinates":[84.404605,26.427938],"type":"Point"}
}