{
  "type": "Feature",
  "properties": {
    "gn:admin1_code":"36",
    "gn:admin2_code":"201.0",
    "gn:asciiname":"Pipargaon",
    "gn:country_code":"IN",
    "gn:dem":157,
    "gn:feature_class":"P",
    "gn:feature_code":"PPL",
    "gn:name":"Pipargaon",
    "gn:population":0,
    "gn:timezone":"Asia/Kolkata",
    "iso:country":"IN",
    "ks:ks_name":"Pipargaon",
    "ks:ks_type":"VILLAGE",
    "name:eng_x_preferred":[
        "Pipargaon"
    ],
    "wof:name":"Pipargaon",
    "wof:placetype":"locality"
},
  "geometry": {"coordinates":[79.21734499999999,27.458032],"type":"Point"}
}