{
  "type": "Feature",
  "properties": {
    "iso:country":"IN",
    "ks:ks_name":"Shiroli",
    "ks:ks_pop":21671,
    "ks:ks_type":"VILLAGE",
    "name:eng_x_preferred":[
        "Shiroli"
    ],
    "wof:name":"Shiroli",
    "wof:placetype":"neighbourhood",
    "wof:population":21671
},
  "geometry": {"coordinates":[74.27351299999999,16.758373],"type":"Point"}
}