{
  "type": "Feature",
  "properties": {
    "iso:country":"IN",
    "ks:ks_alt_nam":"Pamatikunta tanda",
    "ks:ks_name":"Pamatikunta Tanda",
    "ks:ks_pop":50,
    "ks:ks_type":"HABITATION",
    "name:eng_x_preferred":[
        "Pamatikunta Tanda"
    ],
    "wof:name":"Pamatikunta Tanda",
    "wof:placetype":"locality",
    "wof:population":50
},
  "geometry": {"coordinates":[78.313537,16.76835],"type":"Point"}
}