{
  "type": "Feature",
  "properties": {
    "iso:country":"IN",
    "ks:ks_name":"Sanjambani",
    "ks:ks_pop":186,
    "ks:ks_type":"VILLAGE",
    "name:eng_x_preferred":[
        "Sanjambani"
    ],
    "wof:name":"Sanjambani",
    "wof:placetype":"locality",
    "wof:population":186
},
  "geometry": {"coordinates":[86.85726200000001,21.870804],"type":"Point"}
}