{
  "type": "Feature",
  "properties": {
    "iso:country":"IN",
    "ks:ks_name":"Sah Tola",
    "ks:ks_pop":83,
    "ks:ks_type":"HABITATION",
    "name:eng_x_preferred":[
        "Sah Tola"
    ],
    "wof:name":"Sah Tola",
    "wof:placetype":"locality",
    "wof:population":83
},
  "geometry": {"coordinates":[83.56057300000001,24.182216],"type":"Point"}
}