{
  "type": "Feature",
  "properties": {
    "gn:admin1_code":"23",
    "gn:admin2_code":"37.0",
    "gn:asciiname":"Chhawala",
    "gn:country_code":"IN",
    "gn:dem":241,
    "gn:feature_class":"P",
    "gn:feature_code":"PPL",
    "gn:name":"Chhaw\u0101la",
    "gn:population":0,
    "gn:timezone":"Asia/Kolkata",
    "iso:country":"IN",
    "ks:ks_name":"Chhaula",
    "ks:ks_pop":486,
    "ks:ks_type":"VILLAGE",
    "name:ara_x_preferred":[
        "\u062a\u0634\u0627\u0648\u0644\u0627"
    ],
    "name:ben_bn_x_preferred":[
        "\u099b\u09be\u0993\u09df\u09be\u09b2\u09be"
    ],
    "name:ben_in_x_preferred":[
        "\u099b\u09be\u0993\u09df\u09be\u09b2\u09be"
    ],
    "name:eng_x_preferred":[
        "Chhaula"
    ],
    "name:eng_x_variant":[
        "Chhawala"
    ],
    "name:guj_x_preferred":[
        "\u0a9b\u0ab5\u0abe\u0ab2\u0abe"
    ],
    "name:hin_x_preferred":[
        "\u091b\u093e\u0935\u0932\u093e"
    ],
    "name:kan_x_preferred":[
        "\u0c9b\u0cb5\u0cbe\u0cb2\u0cbe"
    ],
    "name:mal_x_preferred":[
        "\u0d1a\u0d4d\u0d1a\u0d57\u0d33"
    ],
    "name:mar_x_preferred":[
        "\u091b\u093e\u0935\u093e\u0932\u093e"
    ],
    "name:pan_x_preferred":[
        "\u0a1b\u0a3e\u0a35\u0a3e\u0a32\u0a3e"
    ],
    "name:tam_x_preferred":[
        "\u0b9a\u0bcd\u0bb9\u0bb5\u0bbe\u0bb2\u0bbe"
    ],
    "name:tel_x_preferred":[
        "\u0c1b\u0c3e\u0c35\u0c32\u0c3e"
    ],
    "name:urd_x_preferred":[
        "\u0686\u06be\u0627\u0624\u0644\u0627"
    ],
    "wof:name":"Chhaula",
    "wof:placetype":"locality",
    "wof:population":486
},
  "geometry": {"coordinates":[75.845467,31.003713],"type":"Point"}
}