{
  "type": "Feature",
  "properties": {
    "iso:country":"IN",
    "ks:ks_alt_nam":"CT estate",
    "ks:ks_name":"Ct Estate",
    "ks:ks_pop":810,
    "ks:ks_type":"HABITATION",
    "name:eng_x_preferred":[
        "Ct Estate"
    ],
    "wof:name":"Ct Estate",
    "wof:placetype":"locality",
    "wof:population":810
},
  "geometry": {"coordinates":[76.380714,11.136032],"type":"Point"}
}