{
  "type": "Feature",
  "properties": {
    "iso:country":"IN",
    "ks:ks_name":"Sain",
    "ks:ks_pop":4,
    "ks:ks_type":"HABITATION",
    "name:eng_x_preferred":[
        "Sain"
    ],
    "wof:name":"Sain",
    "wof:placetype":"locality",
    "wof:population":4
},
  "geometry": {"coordinates":[78.660042,30.171384],"type":"Point"}
}