{
  "type": "Feature",
  "properties": {
    "gn:admin1_code":"2",
    "gn:admin2_code":"545.0",
    "gn:asciiname":"Yarlagadda",
    "gn:country_code":"IN",
    "gn:dem":358,
    "gn:feature_class":"P",
    "gn:feature_code":"PPL",
    "gn:name":"Y\u0101rlagadda",
    "gn:population":0,
    "gn:timezone":"Asia/Kolkata",
    "iso:country":"IN",
    "name:tel_x_preferred":[
        "\u0c2f\u0c3e\u0c30\u0c4d\u0c32\u0c17\u0c21\u0c4d\u0c21"
    ],
    "name:urd_x_preferred":[
        "\u06cc\u0627\u0631\u0644\u06af\u062f"
    ],
    "wof:name":"Yarlagadda",
    "wof:placetype":"locality"
},
  "geometry": {"coordinates":[81.95891999999998,17.68879],"type":"Point"}
}