{
  "type": "Feature",
  "properties": {
    "iso:country":"IN",
    "ks:ks_name":"75 RD",
    "ks:ks_pop":404,
    "ks:ks_type":"VILLAGE",
    "name:eng_x_preferred":[
        "75 RD"
    ],
    "wof:name":"75 RD",
    "wof:placetype":"locality",
    "wof:population":404
},
  "geometry": {"coordinates":[74.347579,29.296832],"type":"Point"}
}