{
  "type": "Feature",
  "properties": {
    "gn:admin1_code":"24",
    "gn:admin2_code":"127.0",
    "gn:asciiname":"Asan Nakti",
    "gn:country_code":"IN",
    "gn:dem":253,
    "gn:feature_class":"P",
    "gn:feature_code":"PPL",
    "gn:name":"\u0100san Nakti",
    "gn:population":0,
    "gn:timezone":"Asia/Kolkata",
    "iso:country":"IN",
    "wof:name":"Asan Nakti",
    "wof:placetype":"locality"
},
  "geometry": {"coordinates":[76.28437,24.9878],"type":"Point"}
}