{
  "type": "Feature",
  "properties": {
    "iso:country":"IN",
    "ks:ks_alt_nam":"Beher\u0101m\u0101l",
    "ks:ks_name":"Beheramal",
    "ks:ks_pop":913,
    "ks:ks_type":"VILLAGE",
    "name:eng_x_preferred":[
        "Beheramal"
    ],
    "name:eng_x_variant":[
        "Beher\u0101m\u0101l"
    ],
    "wof:name":"Beheramal",
    "wof:placetype":"locality",
    "wof:population":913
},
  "geometry": {"coordinates":[84.243539,21.402381],"type":"Point"}
}