{
  "type": "Feature",
  "properties": {
    "gn:admin1_code":"35",
    "gn:admin2_code":"425.0",
    "gn:asciiname":"Bajna",
    "gn:country_code":"IN",
    "gn:dem":315,
    "gn:feature_class":"P",
    "gn:feature_code":"PPL",
    "gn:name":"B\u0101jna",
    "gn:population":0,
    "gn:timezone":"Asia/Kolkata",
    "iso:country":"IN",
    "name:ceb_x_preferred":[
        "Bajna"
    ],
    "name:hun_x_preferred":[
        "Bajna"
    ],
    "name:nld_x_preferred":[
        "Bajna"
    ],
    "name:swe_x_preferred":[
        "Bajna"
    ],
    "wof:name":"Bajna",
    "wof:placetype":"locality"
},
  "geometry": {"coordinates":[79.50765,24.87855],"type":"Point"}
}