{
  "type": "Feature",
  "properties": {
    "iso:country":"IN",
    "ks:ks_name":"Badiguda Para",
    "ks:ks_pop":69,
    "ks:ks_type":"HABITATION",
    "ks:ks_uagg_main":0,
    "name:eng_x_preferred":[
        "Badiguda Para"
    ],
    "wof:name":"Badiguda Para",
    "wof:placetype":"neighbourhood",
    "wof:population":69
},
  "geometry": {"coordinates":[81.983026,19.270712],"type":"Point"}
}