{
  "type": "Feature",
  "properties": {
    "iso:country":"IN",
    "ks:ks_name":"Kadokota",
    "ks:ks_pop":536,
    "ks:ks_type":"VILLAGE",
    "name:eng_x_preferred":[
        "Kadokota"
    ],
    "wof:name":"Kadokota",
    "wof:placetype":"locality",
    "wof:population":536
},
  "geometry": {"coordinates":[86.700463,22.356203],"type":"Point"}
}