{
  "type": "Feature",
  "properties": {
    "gn:admin1_code":"25.0",
    "gn:admin2_code":"616.0",
    "gn:asciiname":"Uttirakkudi",
    "gn:country_code":"IN",
    "gn:dem":50,
    "gn:feature_class":"P",
    "gn:feature_code":"PPL",
    "gn:name":"Uttirakkudi",
    "gn:population":0,
    "gn:timezone":"Asia/Kolkata",
    "iso:country":"IN",
    "wof:name":"Uttirakkudi",
    "wof:placetype":"locality"
},
  "geometry": {"coordinates":[79.37054000000001,11.17695],"type":"Point"}
}