{
  "type": "Feature",
  "properties": {
    "iso:country":"IN",
    "ks:ks_name":"Burusahi",
    "ks:ks_pop":125,
    "ks:ks_type":"HABITATION",
    "name:eng_x_preferred":[
        "Burusahi"
    ],
    "wof:name":"Burusahi",
    "wof:placetype":"locality",
    "wof:population":125
},
  "geometry": {"coordinates":[86.132013,21.455779],"type":"Point"}
}