{
  "type": "Feature",
  "properties": {
    "iso:country":"IN",
    "ks:ks_name":"Kuldum",
    "ks:ks_pop":513,
    "ks:ks_type":"HABITATION",
    "name:eng_x_preferred":[
        "Kuldum"
    ],
    "wof:name":"Kuldum",
    "wof:placetype":"locality",
    "wof:population":513
},
  "geometry": {"coordinates":[85.500184,22.100877],"type":"Point"}
}