{
  "type": "Feature",
  "properties": {
    "iso:country":"IN",
    "ks:ks_name":"Mohkhuli Gaon",
    "ks:ks_pop":1959,
    "ks:ks_type":"VILLAGE",
    "ks:ks_uagg_main":0,
    "name:eng_x_preferred":[
        "Mohkhuli Gaon"
    ],
    "wof:name":"Mohkhuli Gaon",
    "wof:placetype":"locality",
    "wof:population":1959
},
  "geometry": {"coordinates":[95.327528,27.427395],"type":"Point"}
}