{
  "type": "Feature",
  "properties": {
    "iso:country":"IN",
    "ks:ks_name":"Banskaro",
    "ks:ks_pop":213,
    "ks:ks_type":"VILLAGE",
    "name:eng_x_preferred":[
        "Banskaro"
    ],
    "wof:name":"Banskaro",
    "wof:placetype":"locality",
    "wof:population":213
},
  "geometry": {"coordinates":[86.195554,24.332881],"type":"Point"}
}