{
  "type": "Feature",
  "properties": {
    "iso:country":"IN",
    "ks:ks_name":"Chhotepalli",
    "ks:ks_pop":79,
    "ks:ks_type":"VILLAGE",
    "name:eng_x_preferred":[
        "Chhotepalli"
    ],
    "wof:name":"Chhotepalli",
    "wof:placetype":"locality",
    "wof:population":79
},
  "geometry": {"coordinates":[81.03872,19.114559],"type":"Point"}
}