{
  "type": "Feature",
  "properties": {
    "iso:country":"IN",
    "ks:ks_name":"Balua Urf Dumri Gobind",
    "ks:ks_pop":1112,
    "ks:ks_type":"VILLAGE",
    "name:eng_x_preferred":[
        "Balua Urf Dumri Gobind"
    ],
    "wof:name":"Balua Urf Dumri Gobind",
    "wof:placetype":"locality",
    "wof:population":1112
},
  "geometry": {"coordinates":[85.154212,26.593177],"type":"Point"}
}