{
  "type": "Feature",
  "properties": {
    "gn:admin1_code":"24",
    "gn:admin2_code":"128.0",
    "gn:asciiname":"Gordhanpura",
    "gn:country_code":"IN",
    "gn:dem":299,
    "gn:feature_class":"P",
    "gn:feature_code":"PPL",
    "gn:name":"Gordhanpura",
    "gn:population":0,
    "gn:timezone":"Asia/Kolkata",
    "iso:country":"IN",
    "wof:name":"Gordhanpura",
    "wof:placetype":"locality"
},
  "geometry": {"coordinates":[77.22941999999998,25.30542],"type":"Point"}
}