{
  "type": "Feature",
  "properties": {
    "gn:admin1_code":"23",
    "gn:admin2_code":"52.0",
    "gn:asciiname":"Tarak",
    "gn:country_code":"IN",
    "gn:dem":298,
    "gn:feature_class":"P",
    "gn:feature_code":"PPL",
    "gn:name":"Tarak",
    "gn:population":0,
    "gn:timezone":"Asia/Kolkata",
    "iso:country":"IN",
    "wof:name":"Tarak",
    "wof:placetype":"locality"
},
  "geometry": {"coordinates":[76.89587,30.49869],"type":"Point"}
}