{
  "type": "Feature",
  "properties": {
    "iso:country":"IN",
    "ks:ks_name":"Gendabasa",
    "ks:ks_pop":140,
    "ks:ks_type":"HABITATION",
    "name:eng_x_preferred":[
        "Gendabasa"
    ],
    "wof:name":"Gendabasa",
    "wof:placetype":"locality",
    "wof:population":140
},
  "geometry": {"coordinates":[86.09623000000001,21.375745],"type":"Point"}
}