{
  "type": "Feature",
  "properties": {
    "iso:country":"IN",
    "ks:ks_name":"Bamnor Ameershah",
    "ks:ks_pop":1120,
    "ks:ks_type":"HABITATION",
    "name:eng_x_preferred":[
        "Bamnor Ameershah"
    ],
    "wof:name":"Bamnor Ameershah",
    "wof:placetype":"locality",
    "wof:population":1120
},
  "geometry": {"coordinates":[71.307495,25.304952],"type":"Point"}
}