{
  "type": "Feature",
  "properties": {
    "iso:country":"IN",
    "ks:ks_alt_nam":"H.Tola",
    "ks:ks_name":"H.tola",
    "ks:ks_pop":336,
    "ks:ks_type":"HABITATION",
    "name:eng_x_preferred":[
        "H.tola"
    ],
    "wof:name":"H.tola",
    "wof:placetype":"locality",
    "wof:population":336
},
  "geometry": {"coordinates":[86.653519,24.757797],"type":"Point"}
}