{
  "type": "Feature",
  "properties": {
    "iso:country":"IN",
    "ks:ks_name":"Koibartya Para",
    "ks:ks_pop":402,
    "ks:ks_type":"HABITATION",
    "ks:ks_uagg_main":0,
    "name:eng_x_preferred":[
        "Koibartya Para"
    ],
    "wof:name":"Koibartya Para",
    "wof:placetype":"locality",
    "wof:population":402
},
  "geometry": {"coordinates":[91.48345,26.114066],"type":"Point"}
}