{
  "type": "Feature",
  "properties": {
    "iso:country":"IN",
    "ks:ks_name":"Hachebettu",
    "ks:ks_pop":50,
    "ks:ks_type":"HABITATION",
    "name:eng_x_preferred":[
        "Hachebettu"
    ],
    "wof:name":"Hachebettu",
    "wof:placetype":"locality",
    "wof:population":50
},
  "geometry": {"coordinates":[74.900578,13.304312],"type":"Point"}
}