{
  "type": "Feature",
  "properties": {
    "iso:country":"IN",
    "ks:ks_name":"Divdiya",
    "ks:ks_pop":29,
    "ks:ks_type":"HABITATION",
    "name:eng_x_preferred":[
        "Divdiya"
    ],
    "wof:name":"Divdiya",
    "wof:placetype":"locality",
    "wof:population":29
},
  "geometry": {"coordinates":[79.78855299999999,29.630647],"type":"Point"}
}