{
  "type": "Feature",
  "properties": {
    "gn:admin1_code":"40",
    "gn:admin2_code":"535.0",
    "gn:asciiname":"Mothey",
    "gn:country_code":"IN",
    "gn:dem":491,
    "gn:feature_class":"P",
    "gn:feature_code":"PPL",
    "gn:name":"Mothey",
    "gn:population":0,
    "gn:timezone":"Asia/Kolkata",
    "iso:country":"IN",
    "wof:name":"Mothey",
    "wof:placetype":"locality"
},
  "geometry": {"coordinates":[78.62886999999998,18.11155],"type":"Point"}
}