{
  "type": "Feature",
  "properties": {
    "iso:country":"IN",
    "ks:ks_name":"Bherampura",
    "ks:ks_type":"VILLAGE",
    "name:eng_x_preferred":[
        "Bherampura"
    ],
    "wof:name":"Bherampura",
    "wof:placetype":"locality"
},
  "geometry": {"coordinates":[78.952778,25.614635],"type":"Point"}
}