{
  "type": "Feature",
  "properties": {
    "gn:admin1_code":"12.0",
    "gn:admin2_code":"16.0",
    "gn:asciiname":"Jaba",
    "gn:country_code":"IN",
    "gn:dem":2814,
    "gn:feature_class":"P",
    "gn:feature_code":"PPL",
    "gn:name":"J\u0101ba",
    "gn:population":0,
    "gn:timezone":"Asia/Kolkata",
    "iso:country":"IN",
    "name:ceb_x_preferred":[
        "Jaba"
    ],
    "name:deu_x_preferred":[
        "Jaba"
    ],
    "name:fra_x_preferred":[
        "Jaba"
    ],
    "name:heb_x_preferred":[
        "\u05d2'\u05d1\u05e2"
    ],
    "name:hun_x_preferred":[
        "Jaba"
    ],
    "name:ita_x_preferred":[
        "Jaba"
    ],
    "name:nld_x_preferred":[
        "Jaba"
    ],
    "name:pol_x_preferred":[
        "Jaba"
    ],
    "name:por_x_preferred":[
        "Jab\u00e1"
    ],
    "name:rus_x_preferred":[
        "\u0414\u0436\u0430\u0431\u0430"
    ],
    "name:swe_x_preferred":[
        "Jaba"
    ],
    "wof:name":"Jaba",
    "wof:placetype":"locality"
},
  "geometry": {"coordinates":[75.48129,33.2572],"type":"Point"}
}