{
  "type": "Feature",
  "properties": {
    "gn:admin1_code":"34.0",
    "gn:admin2_code":"228.0",
    "gn:asciiname":"Purankanwan",
    "gn:country_code":"IN",
    "gn:dem":51,
    "gn:feature_class":"P",
    "gn:feature_code":"PPL",
    "gn:name":"Purank\u0101nw\u0101n",
    "gn:population":0,
    "gn:timezone":"Asia/Kolkata",
    "iso:country":"IN",
    "wof:name":"Purankanwan",
    "wof:placetype":"locality"
},
  "geometry": {"coordinates":[85.81931,25.15629],"type":"Point"}
}