{
  "type": "Feature",
  "properties": {
    "gn:admin1_code":"21.0",
    "gn:admin2_code":"398.0",
    "gn:asciiname":"Eguva Gummadi",
    "gn:country_code":"IN",
    "gn:dem":997,
    "gn:feature_class":"P",
    "gn:feature_code":"PPL",
    "gn:name":"Eguva Gummadi",
    "gn:population":0,
    "gn:timezone":"Asia/Kolkata",
    "iso:country":"IN",
    "wof:name":"Eguva Gummadi",
    "wof:placetype":"neighbourhood"
},
  "geometry": {"coordinates":[83.0707,18.75885],"type":"Point"}
}