{
  "type": "Feature",
  "properties": {
    "iso:country":"IN",
    "ks:ks_name":"Sankhabhaguni",
    "ks:ks_pop":265,
    "ks:ks_type":"VILLAGE",
    "name:eng_x_preferred":[
        "Sankhabhaguni"
    ],
    "wof:name":"Sankhabhaguni",
    "wof:placetype":"locality",
    "wof:population":265
},
  "geometry": {"coordinates":[84.325273,21.240223],"type":"Point"}
}