{
  "type": "Feature",
  "properties": {
    "iso:country":"IN",
    "ks:ks_alt_nam":"J hill",
    "ks:ks_name":"J Hill",
    "ks:ks_pop":475,
    "ks:ks_type":"HABITATION",
    "name:eng_x_preferred":[
        "J Hill"
    ],
    "wof:name":"J Hill",
    "wof:placetype":"locality",
    "wof:population":475
},
  "geometry": {"coordinates":[84.75998300000001,19.629398],"type":"Point"}
}