{
  "type": "Feature",
  "properties": {
    "gn:admin1_code":"37",
    "gn:admin2_code":"413.0",
    "gn:asciiname":"Mardei",
    "gn:country_code":"IN",
    "gn:dem":403,
    "gn:feature_class":"P",
    "gn:feature_code":"PPL",
    "gn:name":"Mardei",
    "gn:population":0,
    "gn:timezone":"Asia/Kolkata",
    "iso:country":"IN",
    "ks:ks_name":"Mardel",
    "ks:ks_pop":426,
    "ks:ks_type":"VILLAGE",
    "name:eng_x_preferred":[
        "Mardel"
    ],
    "name:eng_x_variant":[
        "Mardei"
    ],
    "wof:name":"Mardel",
    "wof:placetype":"locality",
    "wof:population":426
},
  "geometry": {"coordinates":[81.107691,20.36408],"type":"Point"}
}