{
  "type": "Feature",
  "properties": {
    "iso:country":"IN",
    "ks:ks_name":"Dholabera",
    "ks:ks_pop":780,
    "ks:ks_type":"VILLAGE",
    "name:eng_x_preferred":[
        "Dholabera"
    ],
    "wof:name":"Dholabera",
    "wof:placetype":"locality",
    "wof:population":780
},
  "geometry": {"coordinates":[86.353106,22.403333],"type":"Point"}
}