{
  "type": "Feature",
  "properties": {
    "gn:admin1_code":"16",
    "gn:admin2_code":"504.0",
    "gn:asciiname":"Belodi",
    "gn:country_code":"IN",
    "gn:dem":249,
    "gn:feature_class":"P",
    "gn:feature_code":"PPL",
    "gn:name":"Belodi",
    "gn:population":0,
    "gn:timezone":"Asia/Kolkata",
    "iso:country":"IN",
    "wof:name":"Belodi",
    "wof:placetype":"locality"
},
  "geometry": {"coordinates":[78.83830999999998,20.81172],"type":"Point"}
}