{
  "type": "Feature",
  "properties": {
    "iso:country":"IN",
    "ks:ks_name":"Poonchhari",
    "ks:ks_pop":0,
    "ks:ks_type":"VILLAGE",
    "ks:ks_uagg_main":0,
    "name:eng_x_preferred":[
        "Poonchhari"
    ],
    "wof:name":"Poonchhari",
    "wof:placetype":"locality",
    "wof:population":0
},
  "geometry": {"coordinates":[78.11657099999999,26.196637],"type":"Point"}
}