{
  "type": "Feature",
  "properties": {
    "iso:country":"IN",
    "ks:ks_name":"Navanagar",
    "ks:ks_pop":776,
    "ks:ks_type":"HABITATION",
    "name:eng_x_preferred":[
        "Navanagar"
    ],
    "wof:name":"Navanagar",
    "wof:placetype":"locality",
    "wof:population":776
},
  "geometry": {"coordinates":[73.38207800000001,16.51152],"type":"Point"}
}