{
  "type": "Feature",
  "properties": {
    "iso:country":"IN",
    "ks:ks_name":"Ladhupurwa",
    "ks:ks_pop":218,
    "ks:ks_type":"HABITATION",
    "name:eng_x_preferred":[
        "Ladhupurwa"
    ],
    "wof:name":"Ladhupurwa",
    "wof:placetype":"locality",
    "wof:population":218
},
  "geometry": {"coordinates":[83.081823,27.245576],"type":"Point"}
}