{
  "type": "Feature",
  "properties": {
    "iso:country":"IN",
    "ks:ks_name":"Palanigoundenputhur",
    "ks:ks_pop":657,
    "ks:ks_type":"HABITATION",
    "ks:ks_uagg_main":0,
    "name:eng_x_preferred":[
        "Palanigoundenputhur"
    ],
    "wof:name":"Palanigoundenputhur",
    "wof:placetype":"neighbourhood",
    "wof:population":657
},
  "geometry": {"coordinates":[77.447194,10.620995],"type":"Point"}
}