{
  "type": "Feature",
  "properties": {
    "iso:country":"IN",
    "ks:ks_name":"Mangitungi",
    "ks:ks_pop":100,
    "ks:ks_type":"HABITATION",
    "name:eng_x_preferred":[
        "Mangitungi"
    ],
    "wof:name":"Mangitungi",
    "wof:placetype":"locality",
    "wof:population":100
},
  "geometry": {"coordinates":[74.087288,20.839073],"type":"Point"}
}