{
  "type": "Feature",
  "properties": {
    "gn:admin1_code":"13.0",
    "gn:admin2_code":"592.0",
    "gn:asciiname":"Kaladittara",
    "gn:country_code":"IN",
    "gn:dem":20,
    "gn:feature_class":"P",
    "gn:feature_code":"PPL",
    "gn:name":"Kaladittara",
    "gn:population":0,
    "gn:timezone":"Asia/Kolkata",
    "iso:country":"IN",
    "wof:name":"Kaladittara",
    "wof:placetype":"locality"
},
  "geometry": {"coordinates":[75.99004000000002,10.88933],"type":"Point"}
}