{
  "type": "Feature",
  "properties": {
    "iso:country":"IN",
    "ks:ks_name":"Jammaduguda",
    "ks:ks_pop":96,
    "ks:ks_type":"HABITATION",
    "name:eng_x_preferred":[
        "Jammaduguda"
    ],
    "wof:name":"Jammaduguda",
    "wof:placetype":"locality",
    "wof:population":96
},
  "geometry": {"coordinates":[83.791166,18.717874],"type":"Point"}
}