{
  "type": "Feature",
  "properties": {
    "gn:admin1_code":"13.0",
    "gn:admin2_code":"593.0",
    "gn:asciiname":"Mayikkampadam",
    "gn:country_code":"IN",
    "gn:dem":78,
    "gn:feature_class":"P",
    "gn:feature_code":"PPL",
    "gn:name":"Mayikkamp\u0101dam",
    "gn:population":0,
    "gn:timezone":"Asia/Kolkata",
    "iso:country":"IN",
    "ks:ks_name":"Manakkampadam",
    "ks:ks_pop":1820,
    "ks:ks_type":"HABITATION",
    "name:eng_x_preferred":[
        "Manakkampadam"
    ],
    "name:eng_x_variant":[
        "Mayikkampadam"
    ],
    "wof:name":"Manakkampadam",
    "wof:placetype":"locality",
    "wof:population":1820
},
  "geometry": {"coordinates":[76.567736,10.807854],"type":"Point"}
}