{
  "type": "Feature",
  "properties": {
    "gn:admin1_code":"17",
    "gn:admin2_code":"273.0",
    "gn:asciiname":"Tairenpokpi",
    "gn:country_code":"IN",
    "gn:dem":865,
    "gn:feature_class":"P",
    "gn:feature_code":"PPL",
    "gn:name":"Tairenpokpi",
    "gn:population":0,
    "gn:timezone":"Asia/Kolkata",
    "iso:country":"IN",
    "wof:name":"Tairenpokpi",
    "wof:placetype":"locality"
},
  "geometry": {"coordinates":[93.67028000000001,24.64317],"type":"Point"}
}