{
  "type": "Feature",
  "properties": {
    "iso:country":"IN",
    "ks:ks_name":"Gobindpur",
    "ks:ks_pop":411,
    "ks:ks_type":"HABITATION",
    "name:eng_x_preferred":[
        "Gobindpur"
    ],
    "wof:name":"Gobindpur",
    "wof:placetype":"locality",
    "wof:population":411
},
  "geometry": {"coordinates":[83.74361399999999,25.549902],"type":"Point"}
}