{
  "type": "Feature",
  "properties": {
    "gn:admin1_code":"21.0",
    "gn:admin2_code":"386",
    "gn:asciiname":"Kuhurhi",
    "gn:cc2":"IN",
    "gn:country_code":"IN",
    "gn:dem":22,
    "gn:feature_class":"P",
    "gn:feature_code":"PPL",
    "gn:name":"Kuhurhi",
    "gn:population":0,
    "gn:timezone":"Asia/Kolkata",
    "iso:country":"IN",
    "name:und_x_variant":[
        "Kuhuri",
        "Kuhurhi"
    ],
    "wof:name":"Kuhurhi",
    "wof:placetype":"locality"
},
  "geometry": {"coordinates":[85.36667,19.86667000000001],"type":"Point"}
}