{
  "type": "Feature",
  "properties": {
    "gn:admin1_code":"36.0",
    "gn:admin2_code":"161",
    "gn:asciiname":"Kalianpur Rahan",
    "gn:country_code":"IN",
    "gn:dem":154,
    "gn:feature_class":"P",
    "gn:feature_code":"PPL",
    "gn:name":"Kali\u0101npur R\u0101han",
    "gn:population":0,
    "gn:timezone":"Asia/Kolkata",
    "iso:country":"IN",
    "name:und_x_variant":[
        "Kali\u0101npur R\u0101han",
        "Kaly\u0101npur R\u0101han"
    ],
    "wof:name":"Kalianpur Rahan",
    "wof:placetype":"locality"
},
  "geometry": {"coordinates":[79.09921999999997,26.91499],"type":"Point"}
}