{
  "type": "Feature",
  "properties": {
    "iso:country":"IN",
    "ks:ks_name":"Gandhak",
    "ks:ks_pop":1724,
    "ks:ks_type":"VILLAGE",
    "name:eng_x_preferred":[
        "Gandhak"
    ],
    "wof:name":"Gandhak",
    "wof:placetype":"locality",
    "wof:population":1724
},
  "geometry": {"coordinates":[92.250117,24.853987],"type":"Point"}
}