{
  "type": "Feature",
  "properties": {
    "iso:country":"IN",
    "ks:ks_name":"Kasgeri",
    "ks:ks_pop":150,
    "ks:ks_type":"HABITATION",
    "name:eng_x_preferred":[
        "Kasgeri"
    ],
    "wof:name":"Kasgeri",
    "wof:placetype":"locality",
    "wof:population":150
},
  "geometry": {"coordinates":[74.50320000000001,14.145807],"type":"Point"}
}