{
  "type": "Feature",
  "properties": {
    "gn:admin1_code":"36",
    "gn:admin2_code":"185.0",
    "gn:asciiname":"Muradpur",
    "gn:country_code":"IN",
    "gn:dem":88,
    "gn:feature_class":"P",
    "gn:feature_code":"PPL",
    "gn:name":"Mur\u0101dpur",
    "gn:population":0,
    "gn:timezone":"Asia/Kolkata",
    "iso:country":"IN",
    "ks:ks_alt_nam":"Mur\u0101dpur",
    "ks:ks_name":"Muradpur",
    "ks:ks_type":"VILLAGE",
    "ks:ks_uagg_main":0,
    "name:eng_x_preferred":[
        "Muradpur"
    ],
    "name:eng_x_variant":[
        "Mur\u0101dpur"
    ],
    "wof:name":"Muradpur",
    "wof:placetype":"neighbourhood"
},
  "geometry": {"coordinates":[82.816002,26.716492],"type":"Point"}
}