{
  "type": "Feature",
  "properties": {
    "iso:country":"IN",
    "ks:ks_name":"Bhairai Banger",
    "ks:ks_pop":2035,
    "ks:ks_type":"VILLAGE",
    "name:eng_x_preferred":[
        "Bhairai Banger"
    ],
    "wof:name":"Bhairai Banger",
    "wof:placetype":"locality",
    "wof:population":2035
},
  "geometry": {"coordinates":[77.606465,27.867088],"type":"Point"}
}