{
  "type": "Feature",
  "properties": {
    "iso:country":"IN",
    "ks:ks_alt_nam":"Vakkal belse",
    "ks:ks_name":"Vakkal Belse",
    "ks:ks_pop":420,
    "ks:ks_type":"HABITATION",
    "name:eng_x_preferred":[
        "Vakkal Belse"
    ],
    "wof:name":"Vakkal Belse",
    "wof:placetype":"locality",
    "wof:population":420
},
  "geometry": {"coordinates":[74.365201,14.629343],"type":"Point"}
}