{
  "type": "Feature",
  "properties": {
    "gn:admin1_code":"12.0",
    "gn:admin2_code":"021",
    "gn:asciiname":"Manglal Lalu",
    "gn:country_code":"IN",
    "gn:dem":253,
    "gn:feature_class":"P",
    "gn:feature_code":"PPL",
    "gn:name":"Mangl\u0101l L\u0101lu",
    "gn:population":0,
    "gn:timezone":"Asia/Kolkata",
    "iso:country":"IN",
    "name:und_x_variant":[
        "Mangl\u0101l L\u0101lu",
        "Mangi\u0101l L\u0101lu"
    ],
    "wof:name":"Manglal Lalu",
    "wof:placetype":"locality"
},
  "geometry": {"coordinates":[74.49460999999999,32.78605],"type":"Point"}
}