{
  "type": "Feature",
  "properties": {
    "gn:admin1_code":"37.0",
    "gn:admin2_code":"407.0",
    "gn:asciiname":"Tatawahi",
    "gn:country_code":"IN",
    "gn:dem":364,
    "gn:feature_class":"P",
    "gn:feature_code":"PPL",
    "gn:name":"T\u0101t\u0101w\u0101hi",
    "gn:population":0,
    "gn:timezone":"Asia/Kolkata",
    "iso:country":"IN",
    "name:eng_x_preferred":[
        "T\u0101t\u0101w\u0101hi"
    ],
    "wof:name":"Tatawahi",
    "wof:placetype":"locality"
},
  "geometry": {"coordinates":[81.0932,21.7447],"type":"Point"}
}