{
  "type": "Feature",
  "properties": {
    "iso:country":"IN",
    "ks:ks_name":"Fakir Tola East",
    "ks:ks_pop":313,
    "ks:ks_type":"HABITATION",
    "name:eng_x_preferred":[
        "Fakir Tola East"
    ],
    "wof:name":"Fakir Tola East",
    "wof:placetype":"locality",
    "wof:population":313
},
  "geometry": {"coordinates":[87.718034,26.271892],"type":"Point"}
}