{
  "type": "Feature",
  "properties": {
    "iso:country":"IN",
    "ks:ks_name":"Chichawali",
    "ks:ks_pop":60,
    "ks:ks_type":"HABITATION",
    "name:eng_x_preferred":[
        "Chichawali"
    ],
    "wof:name":"Chichawali",
    "wof:placetype":"locality",
    "wof:population":60
},
  "geometry": {"coordinates":[79.170115,25.993864],"type":"Point"}
}