{
  "type": "Feature",
  "properties": {
    "iso:country":"IN",
    "ks:ks_name":"Roy Para Colony",
    "ks:ks_pop":789,
    "ks:ks_type":"HABITATION",
    "name:eng_x_preferred":[
        "Roy Para Colony"
    ],
    "wof:name":"Roy Para Colony",
    "wof:placetype":"locality",
    "wof:population":789
},
  "geometry": {"coordinates":[89.37337599999999,26.478908],"type":"Point"}
}