{
  "type": "Feature",
  "properties": {
    "iso:country":"IN",
    "ks:ks_name":"Rajya Harni Dih",
    "ks:ks_pop":255,
    "ks:ks_type":"HABITATION",
    "name:eng_x_preferred":[
        "Rajya Harni Dih"
    ],
    "wof:name":"Rajya Harni Dih",
    "wof:placetype":"locality",
    "wof:population":255
},
  "geometry": {"coordinates":[82.426382,27.31488],"type":"Point"}
}