{
  "type": "Feature",
  "properties": {
    "iso:country":"IN",
    "ks:ks_name":"Chavanwadi",
    "ks:ks_pop":115,
    "ks:ks_type":"HABITATION",
    "name:eng_x_preferred":[
        "Chavanwadi"
    ],
    "wof:name":"Chavanwadi",
    "wof:placetype":"locality",
    "wof:population":115
},
  "geometry": {"coordinates":[73.49799,16.977024],"type":"Point"}
}