{
  "type": "Feature",
  "properties": {
    "iso:country":"IN",
    "ks:ks_name":"7 Barani",
    "ks:ks_pop":1164,
    "ks:ks_type":"VILLAGE",
    "name:eng_x_preferred":[
        "7 Barani"
    ],
    "wof:name":"7 Barani",
    "wof:placetype":"locality",
    "wof:population":1164
},
  "geometry": {"coordinates":[74.978877,29.251483],"type":"Point"}
}