{
  "type": "Feature",
  "properties": {
    "iso:country":"IN",
    "ks:ks_name":"Dadoo Ka Gaon",
    "ks:ks_pop":495,
    "ks:ks_type":"VILLAGE",
    "name:eng_x_preferred":[
        "Dadoo Ka Gaon"
    ],
    "wof:name":"Dadoo Ka Gaon",
    "wof:placetype":"locality",
    "wof:population":495
},
  "geometry": {"coordinates":[72.284594,27.561228],"type":"Point"}
}