{
  "type": "Feature",
  "properties": {
    "gn:admin1_code":"16",
    "gn:admin2_code":"523.0",
    "gn:asciiname":"Sawargaon",
    "gn:country_code":"IN",
    "gn:dem":685,
    "gn:feature_class":"P",
    "gn:feature_code":"PPL",
    "gn:name":"S\u0101wargaon",
    "gn:population":0,
    "gn:timezone":"Asia/Kolkata",
    "iso:country":"IN",
    "wof:name":"Sawargaon",
    "wof:placetype":"locality"
},
  "geometry": {"coordinates":[76.20623000000001,18.71909],"type":"Point"}
}