{
  "type": "Feature",
  "properties": {
    "iso:country":"IN",
    "ks:ks_name":"Masahalli",
    "ks:ks_type":"VILLAGE",
    "name:eng_x_preferred":[
        "Masahalli"
    ],
    "wof:name":"Masahalli",
    "wof:placetype":"locality"
},
  "geometry": {"coordinates":[76.600573,11.803167],"type":"Point"}
}