{
  "type": "Feature",
  "properties": {
    "iso:country":"IN",
    "ks:ks_name":"Dhobin Purwa",
    "ks:ks_pop":250,
    "ks:ks_type":"HABITATION",
    "name:eng_x_preferred":[
        "Dhobin Purwa"
    ],
    "wof:name":"Dhobin Purwa",
    "wof:placetype":"locality",
    "wof:population":250
},
  "geometry": {"coordinates":[81.005681,25.212316],"type":"Point"}
}