{
  "type": "Feature",
  "properties": {
    "gn:admin1_code":"35.0",
    "gn:admin2_code":"427",
    "gn:asciiname":"Jamunia",
    "gn:country_code":"IN",
    "gn:dem":473,
    "gn:feature_class":"P",
    "gn:feature_code":"PPL",
    "gn:name":"Jamunia",
    "gn:population":0,
    "gn:timezone":"Asia/Kolkata",
    "iso:country":"IN",
    "ks:ks_name":"Jamuniya",
    "ks:ks_pop":2534,
    "ks:ks_type":"VILLAGE",
    "ks:ks_uagg_main":0,
    "name:eng_x_preferred":[
        "Jamuniya"
    ],
    "wof:name":"Jamuniya",
    "wof:placetype":"neighbourhood",
    "wof:population":2534
},
  "geometry": {"coordinates":[78.97060999999999,24.05762],"type":"Point"}
}