{
  "type": "Feature",
  "properties": {
    "gn:admin1_code":"34.0",
    "gn:admin2_code":"210.0",
    "gn:asciiname":"Dohalia",
    "gn:country_code":"IN",
    "gn:dem":57,
    "gn:feature_class":"P",
    "gn:feature_code":"PPL",
    "gn:name":"Dohalia",
    "gn:population":0,
    "gn:timezone":"Asia/Kolkata",
    "iso:country":"IN",
    "ks:ks_alt_nam":"DUHALIA",
    "ks:ks_name":"Duhalia",
    "ks:ks_pop":438,
    "ks:ks_type":"HABITATION",
    "ks:ks_uagg_main":0,
    "name:eng_x_preferred":[
        "Duhalia"
    ],
    "wof:name":"Duhalia",
    "wof:placetype":"neighbourhood",
    "wof:population":438
},
  "geometry": {"coordinates":[87.88939000000001,26.255922],"type":"Point"}
}