{
  "type": "Feature",
  "properties": {
    "iso:country":"IN",
    "ks:ks_name":"Surnadehi Ryt",
    "ks:ks_pop":242,
    "ks:ks_type":"HABITATION",
    "name:eng_x_preferred":[
        "Surnadehi Ryt"
    ],
    "wof:name":"Surnadehi Ryt",
    "wof:placetype":"locality",
    "wof:population":242
},
  "geometry": {"coordinates":[78.35971000000001,22.06998],"type":"Point"}
}