{
  "type": "Feature",
  "properties": {
    "gn:admin1_code":"38.0",
    "gn:admin2_code":"351.0",
    "gn:asciiname":"Ghori",
    "gn:country_code":"IN",
    "gn:dem":50,
    "gn:feature_class":"P",
    "gn:feature_code":"PPL",
    "gn:name":"Ghori",
    "gn:population":0,
    "gn:timezone":"Asia/Kolkata",
    "iso:country":"IN",
    "wof:name":"Ghori",
    "wof:placetype":"locality"
},
  "geometry": {"coordinates":[87.32156999999999,25.15579],"type":"Point"}
}