{
  "type": "Feature",
  "properties": {
    "gn:admin1_code":"40",
    "gn:admin2_code":"532.0",
    "gn:asciiname":"Darli",
    "gn:country_code":"IN",
    "gn:dem":308,
    "gn:feature_class":"P",
    "gn:feature_code":"PPL",
    "gn:name":"Darli",
    "gn:population":0,
    "gn:timezone":"Asia/Kolkata",
    "iso:country":"IN",
    "wof:name":"Darli",
    "wof:placetype":"locality"
},
  "geometry": {"coordinates":[78.37206999999999,19.63825],"type":"Point"}
}