{
  "type": "Feature",
  "properties": {
    "iso:country":"IN",
    "ks:ks_name":"Dackreswar",
    "ks:ks_pop":940,
    "ks:ks_type":"VILLAGE",
    "ks:ks_uagg_main":0,
    "name:eng_x_preferred":[
        "Dackreswar"
    ],
    "wof:name":"Dackreswar",
    "wof:placetype":"neighbourhood",
    "wof:population":940
},
  "geometry": {"coordinates":[91.077832,26.256024],"type":"Point"}
}