{
  "type": "Feature",
  "properties": {
    "gn:admin1_code":"2.0",
    "gn:asciiname":"Sidivalasa",
    "gn:country_code":"IN",
    "gn:dem":828,
    "gn:feature_class":"P",
    "gn:feature_code":"PPL",
    "gn:name":"S\u012bdivalasa",
    "gn:population":0,
    "gn:timezone":"Asia/Kolkata",
    "iso:country":"IN",
    "wof:name":"Sidivalasa",
    "wof:placetype":"locality"
},
  "geometry": {"coordinates":[83.05362,18.63213],"type":"Point"}
}