{
  "type": "Feature",
  "properties": {
    "gn:admin1_code":"36.0",
    "gn:admin2_code":"133.0",
    "gn:asciiname":"Lalpur",
    "gn:country_code":"IN",
    "gn:dem":216,
    "gn:feature_class":"P",
    "gn:feature_code":"PPL",
    "gn:name":"L\u0101lpur",
    "gn:population":0,
    "gn:timezone":"Asia/Kolkata",
    "iso:country":"IN",
    "ks:ks_alt_nam":"L\u0101lpur",
    "ks:ks_name":"Lalpur",
    "ks:ks_type":"VILLAGE",
    "ks:ks_uagg_main":0,
    "name:ceb_x_preferred":[
        "Lalpur"
    ],
    "name:eng_x_preferred":[
        "Lalpur"
    ],
    "name:eng_x_variant":[
        "L\u0101lpur"
    ],
    "name:pol_x_preferred":[
        "Lalpur"
    ],
    "name:swe_x_preferred":[
        "Lalpur"
    ],
    "wof:name":"Lalpur",
    "wof:placetype":"neighbourhood"
},
  "geometry": {"coordinates":[78.068365,29.279274],"type":"Point"}
}