{
  "type": "Feature",
  "properties": {
    "iso:country":"IN",
    "ks:ks_name":"Khana",
    "ks:ks_pop":509,
    "ks:ks_type":"HABITATION",
    "name:eng_x_preferred":[
        "Khana"
    ],
    "wof:name":"Khana",
    "wof:placetype":"locality",
    "wof:population":509
},
  "geometry": {"coordinates":[74.99060799999999,13.092344],"type":"Point"}
}