{
  "type": "Feature",
  "properties": {
    "iso:country":"IN",
    "ks:ks_name":"Valacode",
    "ks:ks_pop":112,
    "ks:ks_type":"VILLAGE",
    "name:eng_x_preferred":[
        "Valacode"
    ],
    "wof:name":"Valacode",
    "wof:placetype":"locality",
    "wof:population":112
},
  "geometry": {"coordinates":[76.944952,9.01651],"type":"Point"}
}