{
  "type": "Feature",
  "properties": {
    "gn:admin1_code":"13.0",
    "gn:admin2_code":"601.0",
    "gn:asciiname":"Vadakkevila",
    "gn:country_code":"IN",
    "gn:dem":8,
    "gn:feature_class":"P",
    "gn:feature_code":"PPL",
    "gn:name":"Vadakkevila",
    "gn:population":0,
    "gn:timezone":"Asia/Kolkata",
    "iso:country":"IN",
    "name:mal_x_preferred":[
        "\u0d35\u0d1f\u0d15\u0d4d\u0d15\u0d47\u0d35\u0d3f\u0d33"
    ],
    "wof:name":"Vadakkevila",
    "wof:placetype":"locality"
},
  "geometry": {"coordinates":[76.81489000000001,8.61005],"type":"Point"}
}