{
  "type": "Feature",
  "properties": {
    "iso:country":"IN",
    "ks:ks_name":"Baringiput",
    "ks:ks_pop":174,
    "ks:ks_type":"HABITATION",
    "name:eng_x_preferred":[
        "Baringiput"
    ],
    "wof:name":"Baringiput",
    "wof:placetype":"locality",
    "wof:population":174
},
  "geometry": {"coordinates":[82.52928900000001,18.589665],"type":"Point"}
}