{
  "type": "Feature",
  "properties": {
    "iso:country":"IN",
    "ks:ks_name":"Sanjeevarayanipatteda",
    "ks:ks_pop":267,
    "ks:ks_type":"VILLAGE",
    "name:eng_x_preferred":[
        "Sanjeevarayanipatteda"
    ],
    "wof:name":"Sanjeevarayanipatteda",
    "wof:placetype":"neighbourhood",
    "wof:population":267
},
  "geometry": {"coordinates":[79.479857,13.614874],"type":"Point"}
}