{
  "type": "Feature",
  "properties": {
    "iso:country":"IN",
    "ks:ks_name":"Barbil",
    "ks:ks_pop":16,
    "ks:ks_type":"VILLAGE",
    "ks:ks_uagg_main":0,
    "name:eng_x_preferred":[
        "Barbil"
    ],
    "name:hin_x_preferred":[
        "\u092c\u0921\u093c\u092c\u093f\u0932"
    ],
    "wof:name":"Barbil",
    "wof:placetype":"neighbourhood",
    "wof:population":16
},
  "geometry": {"coordinates":[85.908666,22.712747],"type":"Point"}
}