{
  "type": "Feature",
  "properties": {
    "gn:admin1_code":"35",
    "gn:admin2_code":"425.0",
    "gn:asciiname":"Patna",
    "gn:country_code":"IN",
    "gn:dem":184,
    "gn:feature_class":"P",
    "gn:feature_code":"PPL",
    "gn:name":"Patna",
    "gn:population":0,
    "gn:timezone":"Asia/Kolkata",
    "iso:country":"IN",
    "wof:name":"Patna",
    "wof:placetype":"locality"
},
  "geometry": {"coordinates":[80.10443000000002,25.10956],"type":"Point"}
}