{
  "type": "Feature",
  "properties": {
    "iso:country":"IN",
    "ks:ks_name":"Pal Basti",
    "ks:ks_pop":460,
    "ks:ks_type":"HABITATION",
    "name:eng_x_preferred":[
        "Pal Basti"
    ],
    "wof:name":"Pal Basti",
    "wof:placetype":"locality",
    "wof:population":460
},
  "geometry": {"coordinates":[82.653772,25.651135],"type":"Point"}
}