{
  "type": "Feature",
  "properties": {
    "iso:country":"IN",
    "ks:ks_alt_nam":"Mad\u0101puri",
    "ks:ks_name":"Madapuri",
    "ks:ks_type":"VILLAGE",
    "name:eng_x_preferred":[
        "Madapuri"
    ],
    "name:eng_x_variant":[
        "Mad\u0101puri"
    ],
    "wof:name":"Madapuri",
    "wof:placetype":"locality"
},
  "geometry": {"coordinates":[77.98260399999999,21.32056],"type":"Point"}
}