{
  "type": "Feature",
  "properties": {
    "iso:country":"IN",
    "ks:ks_name":"Jamuguri Konwori Pathar",
    "ks:ks_pop":662,
    "ks:ks_type":"VILLAGE",
    "name:eng_x_preferred":[
        "Jamuguri Konwori Pathar"
    ],
    "wof:name":"Jamuguri Konwori Pathar",
    "wof:placetype":"locality",
    "wof:population":662
},
  "geometry": {"coordinates":[95.208445,27.269287],"type":"Point"}
}