{
  "type": "Feature",
  "properties": {
    "iso:country":"IN",
    "ks:ks_name":"Bagpali",
    "ks:ks_pop":270,
    "ks:ks_type":"HABITATION",
    "name:eng_x_preferred":[
        "Bagpali"
    ],
    "wof:name":"Bagpali",
    "wof:placetype":"locality",
    "wof:population":270
},
  "geometry": {"coordinates":[83.610636,20.78419],"type":"Point"}
}