{
  "type": "Feature",
  "properties": {
    "iso:country":"IN",
    "ks:ks_name":"Thekedar Purwa",
    "ks:ks_pop":360,
    "ks:ks_type":"HABITATION",
    "name:eng_x_preferred":[
        "Thekedar Purwa"
    ],
    "wof:name":"Thekedar Purwa",
    "wof:placetype":"locality",
    "wof:population":360
},
  "geometry": {"coordinates":[81.826705,27.209232],"type":"Point"}
}