{
  "type": "Feature",
  "properties": {
    "gn:admin1_code":"40",
    "gn:admin2_code":"541.0",
    "gn:asciiname":"Jagannathapuram",
    "gn:country_code":"IN",
    "gn:dem":168,
    "gn:feature_class":"P",
    "gn:feature_code":"PPL",
    "gn:name":"Jagannathapuram",
    "gn:population":0,
    "gn:timezone":"Asia/Kolkata",
    "iso:country":"IN",
    "ks:ks_name":"Jagannadhapuram",
    "ks:ks_pop":257,
    "ks:ks_type":"VILLAGE",
    "name:eng_x_preferred":[
        "Jagannadhapuram"
    ],
    "name:eng_x_variant":[
        "Jagannathapuram"
    ],
    "wof:name":"Jagannadhapuram",
    "wof:placetype":"locality",
    "wof:population":257
},
  "geometry": {"coordinates":[80.789806,17.236675],"type":"Point"}
}