{
  "type": "Feature",
  "properties": {
    "gn:admin1_code":"19.0",
    "gn:admin2_code":"561",
    "gn:asciiname":"Betigeri",
    "gn:country_code":"IN",
    "gn:dem":648,
    "gn:feature_class":"P",
    "gn:feature_code":"PPL",
    "gn:name":"Betigeri",
    "gn:population":0,
    "gn:timezone":"Asia/Kolkata",
    "iso:country":"IN",
    "wof:name":"Betigeri",
    "wof:placetype":"locality"
},
  "geometry": {"coordinates":[75.64419000000002,15.44303],"type":"Point"}
}