{
  "type": "Feature",
  "properties": {
    "iso:country":"IN",
    "ks:ks_name":"Manjunathapura",
    "ks:ks_pop":241,
    "ks:ks_type":"HABITATION",
    "name:eng_x_preferred":[
        "Manjunathapura"
    ],
    "wof:name":"Manjunathapura",
    "wof:placetype":"locality",
    "wof:population":241
},
  "geometry": {"coordinates":[76.43134999999999,13.359279],"type":"Point"}
}