{
  "type": "Feature",
  "properties": {
    "iso:country":"IN",
    "ks:ks_name":"Bellibettu Nallur",
    "ks:ks_pop":234,
    "ks:ks_type":"HABITATION",
    "name:eng_x_preferred":[
        "Bellibettu Nallur"
    ],
    "wof:name":"Bellibettu Nallur",
    "wof:placetype":"locality",
    "wof:population":234
},
  "geometry": {"coordinates":[75.045087,13.173893],"type":"Point"}
}