{
  "type": "Feature",
  "properties": {
    "gn:admin1_code":"35",
    "gn:admin2_code":"419.0",
    "gn:asciiname":"Atar",
    "gn:country_code":"IN",
    "gn:dem":186,
    "gn:feature_class":"P",
    "gn:feature_code":"PPL",
    "gn:name":"At\u0101r",
    "gn:population":0,
    "gn:timezone":"Asia/Kolkata",
    "iso:country":"IN",
    "name:cat_x_preferred":[
        "Atar"
    ],
    "name:diq_x_preferred":[
        "Atar"
    ],
    "name:fas_x_preferred":[
        "\u0622\u0630\u0631"
    ],
    "name:fra_x_preferred":[
        "Atar"
    ],
    "name:hun_x_preferred":[
        "Atar"
    ],
    "name:jpn_x_preferred":[
        "\u30a2\u30fc\u30bf\u30eb"
    ],
    "name:nld_x_preferred":[
        "\u00c2tash"
    ],
    "name:nno_x_preferred":[
        "Atar"
    ],
    "name:pol_x_preferred":[
        "Atar"
    ],
    "name:ron_x_preferred":[
        "Atar"
    ],
    "name:rus_x_preferred":[
        "\u0410\u0442\u0430\u0440"
    ],
    "name:swe_x_preferred":[
        "Atar"
    ],
    "name:tur_x_preferred":[
        "Atar"
    ],
    "wof:name":"Atar",
    "wof:placetype":"locality"
},
  "geometry": {"coordinates":[77.64787,26.37005],"type":"Point"}
}