{
  "type": "Feature",
  "properties": {
    "gn:admin1_code":"19.0",
    "gn:admin2_code":"574.0",
    "gn:asciiname":"Kannakalli",
    "gn:country_code":"IN",
    "gn:dem":834,
    "gn:feature_class":"P",
    "gn:feature_code":"PPL",
    "gn:name":"K\u0101nnakalli",
    "gn:population":0,
    "gn:timezone":"Asia/Kolkata",
    "iso:country":"IN",
    "wof:name":"Kannakalli",
    "wof:placetype":"neighbourhood"
},
  "geometry": {"coordinates":[76.14236,12.61003],"type":"Point"}
}