{
  "type": "Feature",
  "properties": {
    "gn:admin1_code":"19.0",
    "gn:admin2_code":"581.0",
    "gn:asciiname":"Seshapura",
    "gn:country_code":"IN",
    "gn:dem":853,
    "gn:feature_class":"P",
    "gn:feature_code":"PPL",
    "gn:name":"Sesh\u0101pura",
    "gn:population":0,
    "gn:timezone":"Asia/Kolkata",
    "iso:country":"IN",
    "wof:name":"Seshapura",
    "wof:placetype":"locality"
},
  "geometry": {"coordinates":[78.32509,13.45121],"type":"Point"}
}