{
  "type": "Feature",
  "properties": {
    "gn:admin1_code":"25.0",
    "gn:admin2_code":"631.0",
    "gn:asciiname":"Sadinayakkanapalli",
    "gn:country_code":"IN",
    "gn:dem":881,
    "gn:feature_class":"P",
    "gn:feature_code":"PPL",
    "gn:name":"S\u0101din\u0101yakkanapalli",
    "gn:population":0,
    "gn:timezone":"Asia/Kolkata",
    "iso:country":"IN",
    "wof:name":"Sadinayakkanapalli",
    "wof:placetype":"locality"
},
  "geometry": {"coordinates":[77.73411,12.56316],"type":"Point"}
}