{
  "type": "Feature",
  "properties": {
    "iso:country":"IN",
    "ks:ks_alt_nam":"BAZARTOLI",
    "ks:ks_name":"Bazartoli",
    "ks:ks_pop":228,
    "ks:ks_type":"HABITATION",
    "name:eng_x_preferred":[
        "Bazartoli"
    ],
    "wof:name":"Bazartoli",
    "wof:placetype":"locality",
    "wof:population":228
},
  "geometry": {"coordinates":[84.817178,22.956416],"type":"Point"}
}