{
  "type": "Feature",
  "properties": {
    "gn:admin1_code":"16.0",
    "gn:admin2_code":"499",
    "gn:asciiname":"Betavad",
    "gn:country_code":"IN",
    "gn:dem":348,
    "gn:feature_class":"P",
    "gn:feature_code":"PPL",
    "gn:name":"Bet\u0101vad",
    "gn:population":0,
    "gn:timezone":"Asia/Kolkata",
    "iso:country":"IN",
    "wof:name":"Betavad",
    "wof:placetype":"locality"
},
  "geometry": {"coordinates":[75.96666999999999,20.76667],"type":"Point"}
}