{
  "type": "Feature",
  "properties": {
    "iso:country":"IN",
    "ks:ks_name":"Jankarwasti",
    "ks:ks_pop":50,
    "ks:ks_type":"HABITATION",
    "name:eng_x_preferred":[
        "Jankarwasti"
    ],
    "wof:name":"Jankarwasti",
    "wof:placetype":"locality",
    "wof:population":50
},
  "geometry": {"coordinates":[75.310339,17.413191],"type":"Point"}
}