{
  "type": "Feature",
  "properties": {
    "gn:admin1_code":"36.0",
    "gn:admin2_code":"183.0",
    "gn:asciiname":"Nawagaon",
    "gn:country_code":"IN",
    "gn:dem":109,
    "gn:feature_class":"P",
    "gn:feature_code":"PPL",
    "gn:name":"Naw\u0101g\u0101on",
    "gn:population":0,
    "gn:timezone":"Asia/Kolkata",
    "iso:country":"IN",
    "wof:name":"Nawagaon",
    "wof:placetype":"locality"
},
  "geometry": {"coordinates":[82.08214,27.2096],"type":"Point"}
}