{
  "type": "Feature",
  "properties": {
    "iso:country":"IN",
    "ks:ks_name":"Ghormara",
    "ks:ks_pop":78,
    "ks:ks_type":"HABITATION",
    "name:eng_x_preferred":[
        "Ghormara"
    ],
    "wof:name":"Ghormara",
    "wof:placetype":"locality",
    "wof:population":78
},
  "geometry": {"coordinates":[87.131995,24.406187],"type":"Point"}
}