{
  "type": "Feature",
  "properties": {
    "iso:country":"IN",
    "ks:ks_name":"Namsol",
    "ks:ks_pop":620,
    "ks:ks_type":"VILLAGE",
    "name:eng_x_preferred":[
        "Namsol"
    ],
    "wof:name":"Namsol",
    "wof:placetype":"locality",
    "wof:population":620
},
  "geometry": {"coordinates":[86.322422,22.95982],"type":"Point"}
}