{
  "type": "Feature",
  "properties": {
    "gn:admin1_code":"36.0",
    "gn:admin2_code":"183.0",
    "gn:asciiname":"Suchet",
    "gn:country_code":"IN",
    "gn:dem":106,
    "gn:feature_class":"P",
    "gn:feature_code":"PPL",
    "gn:name":"Suchet",
    "gn:population":0,
    "gn:timezone":"Asia/Kolkata",
    "iso:country":"IN",
    "name:rus_x_preferred":[
        "\u0421\u0443\u0448\u0435"
    ],
    "wof:name":"Suchet",
    "wof:placetype":"neighbourhood"
},
  "geometry": {"coordinates":[81.67944,27.01543],"type":"Point"}
}