{
  "type": "Feature",
  "properties": {
    "iso:country":"IN",
    "ks:ks_alt_nam":"Bandh pur",
    "ks:ks_name":"Bandh Pur",
    "ks:ks_pop":294,
    "ks:ks_type":"HABITATION",
    "name:eng_x_preferred":[
        "Bandh Pur"
    ],
    "wof:name":"Bandh Pur",
    "wof:placetype":"locality",
    "wof:population":294
},
  "geometry": {"coordinates":[83.79541399999999,26.020176],"type":"Point"}
}