{
  "type": "Feature",
  "properties": {
    "iso:country":"IN",
    "ks:ks_name":"Mungda",
    "ks:ks_pop":386,
    "ks:ks_type":"HABITATION",
    "name:eng_x_preferred":[
        "Mungda"
    ],
    "wof:name":"Mungda",
    "wof:placetype":"locality",
    "wof:population":386
},
  "geometry": {"coordinates":[83.76333,23.927479],"type":"Point"}
}