{
  "type": "Feature",
  "properties": {
    "iso:country":"IN",
    "ks:ks_name":"Nizampur",
    "ks:ks_pop":600,
    "ks:ks_type":"HABITATION",
    "name:eng_x_preferred":[
        "Nizampur"
    ],
    "wof:name":"Nizampur",
    "wof:placetype":"locality",
    "wof:population":600
},
  "geometry": {"coordinates":[72.709333,22.847028],"type":"Point"}
}