{
  "type": "Feature",
  "properties": {
    "gn:admin1_code":"13.0",
    "gn:admin2_code":"593.0",
    "gn:asciiname":"Keralassheri",
    "gn:country_code":"IN",
    "gn:dem":78,
    "gn:feature_class":"P",
    "gn:feature_code":"PPL",
    "gn:name":"K\u0113ralassh\u0113ri",
    "gn:population":0,
    "gn:timezone":"Asia/Kolkata",
    "iso:country":"IN",
    "ks:ks_name":"Keralassery",
    "ks:ks_pop":1099,
    "ks:ks_type":"VILLAGE",
    "name:eng_x_preferred":[
        "Keralassery"
    ],
    "name:eng_x_variant":[
        "Keralassheri"
    ],
    "wof:name":"Keralassery",
    "wof:placetype":"locality",
    "wof:population":1099
},
  "geometry": {"coordinates":[76.502015,10.825336],"type":"Point"}
}