{
  "type": "Feature",
  "properties": {
    "gn:admin1_code":"39.0",
    "gn:admin2_code":"64.0",
    "gn:asciiname":"Inda",
    "gn:country_code":"IN",
    "gn:dem":1167,
    "gn:feature_class":"P",
    "gn:feature_code":"PPL",
    "gn:name":"Inda",
    "gn:population":0,
    "gn:timezone":"Asia/Kolkata",
    "iso:country":"IN",
    "ks:ks_name":"Inda",
    "ks:ks_type":"VILLAGE",
    "name:ceb_x_preferred":[
        "Inda"
    ],
    "name:deu_x_preferred":[
        "Inda"
    ],
    "name:eng_x_preferred":[
        "Inda"
    ],
    "name:swe_x_preferred":[
        "Inda"
    ],
    "wof:name":"Inda",
    "wof:placetype":"locality"
},
  "geometry": {"coordinates":[79.268991,29.733247],"type":"Point"}
}