{
  "type": "Feature",
  "properties": {
    "gn:admin1_code":"36",
    "gn:admin2_code":"194.0",
    "gn:asciiname":"Marhi",
    "gn:country_code":"IN",
    "gn:dem":87,
    "gn:feature_class":"P",
    "gn:feature_code":"PPL",
    "gn:name":"Marhi",
    "gn:population":0,
    "gn:timezone":"Asia/Kolkata",
    "iso:country":"IN",
    "name:pan_x_preferred":[
        "\u0a2e\u0a5c\u0a4d\u0a39\u0a40"
    ],
    "wof:name":"Marhi",
    "wof:placetype":"locality"
},
  "geometry": {"coordinates":[82.71587,25.50684],"type":"Point"}
}