{
  "type": "Feature",
  "properties": {
    "iso:country":"IN",
    "ks:ks_name":"Gopitalav",
    "ks:ks_pop":140,
    "ks:ks_type":"HABITATION",
    "name:eng_x_preferred":[
        "Gopitalav"
    ],
    "wof:name":"Gopitalav",
    "wof:placetype":"locality",
    "wof:population":140
},
  "geometry": {"coordinates":[72.896,22.598083],"type":"Point"}
}