{
  "type": "Feature",
  "properties": {
    "iso:country":"IN",
    "ks:ks_name":"Modisahi",
    "ks:ks_pop":230,
    "ks:ks_type":"HABITATION",
    "name:eng_x_preferred":[
        "Modisahi"
    ],
    "wof:name":"Modisahi",
    "wof:placetype":"locality",
    "wof:population":230
},
  "geometry": {"coordinates":[86.086634,21.249843],"type":"Point"}
}