{
  "type": "Feature",
  "properties": {
    "iso:country":"IN",
    "ks:ks_name":"Mahankhal",
    "ks:ks_pop":585,
    "ks:ks_type":"HABITATION",
    "name:eng_x_preferred":[
        "Mahankhal"
    ],
    "wof:name":"Mahankhal",
    "wof:placetype":"locality",
    "wof:population":585
},
  "geometry": {"coordinates":[92.988696,24.672912],"type":"Point"}
}