{
  "type": "Feature",
  "properties": {
    "gn:admin1_code":"24.0",
    "gn:admin2_code":"103",
    "gn:asciiname":"Sisian",
    "gn:country_code":"IN",
    "gn:dem":359,
    "gn:feature_class":"P",
    "gn:feature_code":"PPL",
    "gn:name":"Sisi\u0101n",
    "gn:population":0,
    "gn:timezone":"Asia/Kolkata",
    "iso:country":"IN",
    "name:ara_x_preferred":[
        "\u0633\u064a\u0633\u064a\u0627\u0646"
    ],
    "name:azb_x_preferred":[
        "\u0633\u06cc\u0633\u06cc\u0627\u0646"
    ],
    "name:aze_x_preferred":[
        "Sisian"
    ],
    "name:bel_x_preferred":[
        "\u0421\u0456\u0441\u0456\u044f\u043d"
    ],
    "name:bul_x_preferred":[
        "\u0421\u0438\u0441\u0438\u0430\u043d"
    ],
    "name:ces_x_preferred":[
        "Sisian"
    ],
    "name:che_x_preferred":[
        "\u0421\u0438\u0441\u0438\u0430\u043d"
    ],
    "name:cym_x_preferred":[
        "Sisian"
    ],
    "name:deu_x_preferred":[
        "Sissian"
    ],
    "name:ell_x_preferred":[
        "\u03a3\u03b9\u03c3\u03b9\u03ac\u03bd"
    ],
    "name:epo_x_preferred":[
        "Sisian"
    ],
    "name:est_x_preferred":[
        "Sisian"
    ],
    "name:fas_x_preferred":[
        "\u0633\u06cc\u0633\u06cc\u0627\u0646"
    ],
    "name:fra_x_preferred":[
        "Sisian"
    ],
    "name:hsb_x_preferred":[
        "Sisian"
    ],
    "name:hye_x_preferred":[
        "\u054d\u056b\u057d\u056b\u0561\u0576"
    ],
    "name:ind_x_preferred":[
        "Sisian"
    ],
    "name:ita_x_preferred":[
        "Sisian"
    ],
    "name:kat_x_preferred":[
        "\u10e1\u10d8\u10e1\u10d8\u10d0\u10dc\u10d8"
    ],
    "name:kor_x_preferred":[
        "\uc2dc\uc2dc\uc548"
    ],
    "name:lit_x_preferred":[
        "Sisianas"
    ],
    "name:msa_x_preferred":[
        "Sisian"
    ],
    "name:mzn_x_preferred":[
        "\u0633\u06cc\u0633\u06cc\u0627\u0646"
    ],
    "name:nld_x_preferred":[
        "Sisian"
    ],
    "name:pol_x_preferred":[
        "Sisjan"
    ],
    "name:ron_x_preferred":[
        "Sisian"
    ],
    "name:rus_x_preferred":[
        "\u0421\u0438\u0441\u0438\u0430\u043d"
    ],
    "name:sco_x_preferred":[
        "Sisian"
    ],
    "name:spa_x_preferred":[
        "Sisian"
    ],
    "name:srp_x_preferred":[
        "\u0421\u0438\u0441\u0438\u0458\u0430\u043d"
    ],
    "name:swe_x_preferred":[
        "Sisian"
    ],
    "name:tur_x_preferred":[
        "Sisian"
    ],
    "name:ukr_x_preferred":[
        "\u0421\u0456\u0441\u0456\u0430\u043d"
    ],
    "name:urd_x_preferred":[
        "\u0633\u06cc\u0633\u06cc\u0627\u0646"
    ],
    "name:vie_x_preferred":[
        "Sisian"
    ],
    "name:zho_x_preferred":[
        "\u932b\u897f\u5b89"
    ],
    "wof:name":"Sisian",
    "wof:placetype":"locality"
},
  "geometry": {"coordinates":[75.40104000000002,28.01885],"type":"Point"}
}