{
  "type": "Feature",
  "properties": {
    "gn:admin1_code":"35",
    "gn:admin2_code":"441.0",
    "gn:asciiname":"Pipri Buzurg",
    "gn:country_code":"IN",
    "gn:dem":230,
    "gn:feature_class":"P",
    "gn:feature_code":"PPL",
    "gn:name":"Pipri Buzurg",
    "gn:population":0,
    "gn:timezone":"Asia/Kolkata",
    "iso:country":"IN",
    "name:und_x_variant":[
        "Pipri",
        "Pipri Buzurg"
    ],
    "wof:name":"Pipri Buzurg",
    "wof:placetype":"locality"
},
  "geometry": {"coordinates":[75.19735,21.94846],"type":"Point"}
}