{
  "type": "Feature",
  "properties": {
    "gn:admin1_code":"36.0",
    "gn:admin2_code":"150.0",
    "gn:asciiname":"Dubari",
    "gn:country_code":"IN",
    "gn:dem":165,
    "gn:feature_class":"P",
    "gn:feature_code":"PPL",
    "gn:name":"Dub\u0101ri",
    "gn:population":0,
    "gn:timezone":"Asia/Kolkata",
    "iso:country":"IN",
    "ks:ks_alt_nam":"Dub\u0101ri",
    "ks:ks_name":"Dubari",
    "ks:ks_pop":367,
    "ks:ks_type":"VILLAGE",
    "ks:ks_uagg_main":0,
    "name:eng_x_preferred":[
        "Dubari"
    ],
    "name:eng_x_variant":[
        "Dub\u0101ri"
    ],
    "wof:name":"Dubari",
    "wof:placetype":"neighbourhood",
    "wof:population":367
},
  "geometry": {"coordinates":[79.43310200000001,28.281987],"type":"Point"}
}