{
  "type": "Feature",
  "properties": {
    "gn:admin1_code":"36",
    "gn:admin2_code":"175.0",
    "gn:asciiname":"Pura Jai Singh",
    "gn:country_code":"IN",
    "gn:dem":93,
    "gn:feature_class":"P",
    "gn:feature_code":"PPL",
    "gn:name":"Pura Jai Singh",
    "gn:population":0,
    "gn:timezone":"Asia/Kolkata",
    "iso:country":"IN",
    "ks:ks_name":"Pure Jaysingh",
    "ks:ks_pop":182,
    "ks:ks_type":"VILLAGE",
    "ks:ks_uagg_main":0,
    "name:eng_x_preferred":[
        "Pure Jaysingh"
    ],
    "wof:name":"Pure Jaysingh",
    "wof:placetype":"neighbourhood",
    "wof:population":182
},
  "geometry": {"coordinates":[82.320616,25.520697],"type":"Point"}
}