{
  "type": "Feature",
  "properties": {
    "iso:country":"IN",
    "ks:ks_name":"Tetelia",
    "ks:ks_pop":271,
    "ks:ks_type":"VILLAGE",
    "name:eng_x_preferred":[
        "Tetelia"
    ],
    "wof:name":"Tetelia",
    "wof:placetype":"locality",
    "wof:population":271
},
  "geometry": {"coordinates":[91.604057,26.29158],"type":"Point"}
}