{
  "type": "Feature",
  "properties": {
    "gn:admin1_code":"19.0",
    "gn:admin2_code":"570.0",
    "gn:asciiname":"Kodakodagi",
    "gn:country_code":"IN",
    "gn:dem":720,
    "gn:feature_class":"P",
    "gn:feature_code":"PPL",
    "gn:name":"Kodakodagi",
    "gn:population":0,
    "gn:timezone":"Asia/Kolkata",
    "iso:country":"IN",
    "wof:name":"Kodakodagi",
    "wof:placetype":"locality"
},
  "geometry": {"coordinates":[75.49219000000002,13.44653],"type":"Point"}
}