{
  "type": "Feature",
  "properties": {
    "iso:country":"IN",
    "ks:ks_name":"Kelagina Vajagar",
    "ks:ks_pop":20,
    "ks:ks_type":"HABITATION",
    "name:eng_x_preferred":[
        "Kelagina Vajagar"
    ],
    "wof:name":"Kelagina Vajagar",
    "wof:placetype":"locality",
    "wof:population":20
},
  "geometry": {"coordinates":[74.729722,14.434122],"type":"Point"}
}