{
  "type": "Feature",
  "properties": {
    "gn:admin1_code":"40.0",
    "gn:admin2_code":"539",
    "gn:asciiname":"Datarpalli",
    "gn:country_code":"IN",
    "gn:dem":454,
    "gn:feature_class":"P",
    "gn:feature_code":"PPL",
    "gn:name":"Datarpalli",
    "gn:population":0,
    "gn:timezone":"Asia/Kolkata",
    "iso:country":"IN",
    "wof:name":"Datarpalli",
    "wof:placetype":"locality"
},
  "geometry": {"coordinates":[78.89761999999997,17.59424],"type":"Point"}
}