{
  "type": "Feature",
  "properties": {
    "iso:country":"IN",
    "ks:ks_name":"Vasuki Nagar",
    "ks:ks_pop":275,
    "ks:ks_type":"HABITATION",
    "ks:ks_uagg_main":0,
    "name:eng_x_preferred":[
        "Vasuki Nagar"
    ],
    "wof:name":"Vasuki Nagar",
    "wof:placetype":"locality",
    "wof:population":275
},
  "geometry": {"coordinates":[76.772998,11.34843],"type":"Point"}
}