{
  "type": "Feature",
  "properties": {
    "iso:country":"IN",
    "ks:ks_alt_nam":"Chinnanahalli",
    "ks:ks_name":"Channenahalli",
    "ks:ks_pop":68,
    "ks:ks_type":"VILLAGE",
    "name:eng_x_preferred":[
        "Channenahalli"
    ],
    "name:eng_x_variant":[
        "Chinnanahalli"
    ],
    "wof:name":"Channenahalli",
    "wof:placetype":"locality",
    "wof:population":68
},
  "geometry": {"coordinates":[77.008645,13.625828],"type":"Point"}
}