{
  "type": "Feature",
  "properties": {
    "gn:admin1_code":"28.0",
    "gn:admin2_code":"338",
    "gn:asciiname":"Dhaniakhali",
    "gn:country_code":"IN",
    "gn:dem":18,
    "gn:feature_class":"P",
    "gn:feature_code":"PPL",
    "gn:name":"Dhan\u012bakh\u0101li",
    "gn:population":0,
    "gn:timezone":"Asia/Kolkata",
    "iso:country":"IN",
    "ks:ks_name":"Dhaniakhali",
    "ks:ks_pop":3539,
    "ks:ks_type":"VILLAGE",
    "ks:ks_uagg_main":0,
    "name:eng_x_preferred":[
        "Dhaniakhali"
    ],
    "name:und_x_variant":[
        "Dhan\u012bakh\u0101li"
    ],
    "wof:name":"Dhaniakhali",
    "wof:placetype":"neighbourhood",
    "wof:population":3539
},
  "geometry": {"coordinates":[88.100747,22.968175],"type":"Point"}
}