{
  "type": "Feature",
  "properties": {
    "iso:country":"IN",
    "ks:ks_alt_nam":"BELTALA",
    "ks:ks_name":"Beltala",
    "ks:ks_pop":1237,
    "ks:ks_type":"HABITATION",
    "name:eng_x_preferred":[
        "Beltala"
    ],
    "wof:name":"Beltala",
    "wof:placetype":"locality",
    "wof:population":1237
},
  "geometry": {"coordinates":[88.717161,26.383649],"type":"Point"}
}