{
  "type": "Feature",
  "properties": {
    "iso:country":"IN",
    "ks:ks_alt_nam":"Bhagacha tanda",
    "ks:ks_name":"Bhagacha Tanda",
    "ks:ks_pop":245,
    "ks:ks_type":"HABITATION",
    "name:eng_x_preferred":[
        "Bhagacha Tanda"
    ],
    "wof:name":"Bhagacha Tanda",
    "wof:placetype":"locality",
    "wof:population":245
},
  "geometry": {"coordinates":[76.331824,17.867591],"type":"Point"}
}