{
  "type": "Feature",
  "properties": {
    "iso:country":"IN",
    "ks:ks_name":"Luhar Falia",
    "ks:ks_pop":237,
    "ks:ks_type":"HABITATION",
    "name:eng_x_preferred":[
        "Luhar Falia"
    ],
    "wof:name":"Luhar Falia",
    "wof:placetype":"locality",
    "wof:population":237
},
  "geometry": {"coordinates":[73.478083,20.828806],"type":"Point"}
}