{
  "type": "Feature",
  "properties": {
    "iso:country":"IN",
    "ks:ks_name":"Neikunni",
    "ks:ks_pop":480,
    "ks:ks_type":"HABITATION",
    "name:eng_x_preferred":[
        "Neikunni"
    ],
    "wof:name":"Neikunni",
    "wof:placetype":"locality",
    "wof:population":480
},
  "geometry": {"coordinates":[79.21257900000001,12.34733],"type":"Point"}
}