{
  "type": "Feature",
  "properties": {
    "gn:admin1_code":"19.0",
    "gn:admin2_code":"572.0",
    "gn:asciiname":"Mugalur",
    "gn:country_code":"IN",
    "gn:dem":860,
    "gn:feature_class":"P",
    "gn:feature_code":"PPL",
    "gn:name":"Mugal\u016br",
    "gn:population":0,
    "gn:timezone":"Asia/Kolkata",
    "iso:country":"IN",
    "wof:name":"Mugalur",
    "wof:placetype":"locality"
},
  "geometry": {"coordinates":[77.82183000000001,12.89356],"type":"Point"}
}