{
  "type": "Feature",
  "properties": {
    "iso:country":"IN",
    "ks:ks_name":"Chavanmala",
    "ks:ks_pop":140,
    "ks:ks_type":"HABITATION",
    "name:eng_x_preferred":[
        "Chavanmala"
    ],
    "wof:name":"Chavanmala",
    "wof:placetype":"locality",
    "wof:population":140
},
  "geometry": {"coordinates":[74.664759,18.739839],"type":"Point"}
}