{
  "type": "Feature",
  "properties": {
    "iso:country":"IN",
    "ks:ks_name":"Jafarpur Majra Gharora",
    "ks:ks_pop":31,
    "ks:ks_type":"HABITATION",
    "name:eng_x_preferred":[
        "Jafarpur Majra Gharora"
    ],
    "wof:name":"Jafarpur Majra Gharora",
    "wof:placetype":"locality",
    "wof:population":31
},
  "geometry": {"coordinates":[77.442841,28.357974],"type":"Point"}
}