{
  "type": "Feature",
  "properties": {
    "iso:country":"IN",
    "ks:ks_name":"Kateora",
    "ks:ks_type":"VILLAGE",
    "name:eng_x_preferred":[
        "Kateora"
    ],
    "wof:name":"Kateora",
    "wof:placetype":"neighbourhood"
},
  "geometry": {"coordinates":[76.976502,28.803348],"type":"Point"}
}