{
  "type": "Feature",
  "properties": {
    "iso:country":"IN",
    "ks:ks_name":"Pitchandampalayam",
    "ks:ks_pop":424,
    "ks:ks_type":"HABITATION",
    "ks:ks_uagg_main":0,
    "name:eng_x_preferred":[
        "Pitchandampalayam"
    ],
    "wof:name":"Pitchandampalayam",
    "wof:placetype":"locality",
    "wof:population":424
},
  "geometry": {"coordinates":[77.618655,11.290392],"type":"Point"}
}