{
  "type": "Feature",
  "properties": {
    "iso:country":"IN",
    "ks:ks_name":"Manjguni",
    "ks:ks_pop":624,
    "ks:ks_type":"HABITATION",
    "name:eng_x_preferred":[
        "Manjguni"
    ],
    "wof:name":"Manjguni",
    "wof:placetype":"locality",
    "wof:population":624
},
  "geometry": {"coordinates":[74.29842499999999,14.606034],"type":"Point"}
}