{
  "type": "Feature",
  "properties": {
    "iso:country":"IN",
    "ks:ks_name":"Ramghatroad",
    "ks:ks_pop":42,
    "ks:ks_type":"HABITATION",
    "name:eng_x_preferred":[
        "Ramghatroad"
    ],
    "wof:name":"Ramghatroad",
    "wof:placetype":"locality",
    "wof:population":42
},
  "geometry": {"coordinates":[73.656323,15.85411],"type":"Point"}
}