{
  "type": "Feature",
  "properties": {
    "gn:admin1_code":"34.0",
    "gn:admin2_code":"214.0",
    "gn:asciiname":"Dharmpur",
    "gn:country_code":"IN",
    "gn:dem":50,
    "gn:feature_class":"P",
    "gn:feature_code":"PPL",
    "gn:name":"Dharmpur",
    "gn:population":0,
    "gn:timezone":"Asia/Kolkata",
    "iso:country":"IN",
    "ks:ks_name":"Dharampur",
    "ks:ks_pop":852,
    "ks:ks_type":"VILLAGE",
    "name:eng_x_preferred":[
        "Dharampur"
    ],
    "name:eng_x_variant":[
        "Dharmpur"
    ],
    "name:fra_x_preferred":[
        "Dharampur"
    ],
    "name:new_x_preferred":[
        "\u0927\u0930\u094d\u092e\u092a\u0941\u0930 \u0969"
    ],
    "name:pol_x_preferred":[
        "Dharampur"
    ],
    "wof:name":"Dharampur",
    "wof:placetype":"locality",
    "wof:population":852
},
  "geometry": {"coordinates":[86.483931,26.016236],"type":"Point"}
}