{
  "type": "Feature",
  "properties": {
    "iso:country":"IN",
    "ks:ks_name":"Bendegadde",
    "ks:ks_pop":32,
    "ks:ks_type":"HABITATION",
    "name:eng_x_preferred":[
        "Bendegadde"
    ],
    "wof:name":"Bendegadde",
    "wof:placetype":"locality",
    "wof:population":32
},
  "geometry": {"coordinates":[74.84059499999999,14.721801],"type":"Point"}
}