{
  "type": "Feature",
  "properties": {
    "gn:admin1_code":"37.0",
    "gn:admin2_code":"416",
    "gn:asciiname":"Chintalnar",
    "gn:country_code":"IN",
    "gn:dem":187,
    "gn:feature_class":"P",
    "gn:feature_code":"PPL",
    "gn:name":"Chintaln\u0101r",
    "gn:population":0,
    "gn:timezone":"Asia/Kolkata",
    "iso:country":"IN",
    "ks:ks_alt_nam":"Chintaln\u0101r",
    "ks:ks_name":"Chintalnar",
    "ks:ks_pop":1314,
    "ks:ks_type":"VILLAGE",
    "name:eng_x_preferred":[
        "Chintalnar"
    ],
    "name:eng_x_variant":[
        "Chintaln\u0101r"
    ],
    "name:und_x_variant":[
        "Chintulnar",
        "Chintaln\u0101r"
    ],
    "wof:name":"Chintalnar",
    "wof:placetype":"locality",
    "wof:population":1314
},
  "geometry": {"coordinates":[81.187185,18.341417],"type":"Point"}
}