{
  "type": "Feature",
  "properties": {
    "gn:admin1_code":"37.0",
    "gn:admin2_code":"416",
    "gn:asciiname":"Chintalnar",
    "gn:country_code":"IN",
    "gn:dem":187,
    "gn:feature_class":"P",
    "gn:feature_code":"PPL",
    "gn:name":"Chintaln\u0101r",
    "gn:population":0,
    "gn:timezone":"Asia/Kolkata",
    "iso:country":"IN",
    "name:und_x_variant":[
        "Chintulnar",
        "Chintaln\u0101r"
    ],
    "wof:name":"Chintalnar",
    "wof:placetype":"locality"
},
  "geometry": {"coordinates":[81.18015,18.3418],"type":"Point"}
}