{
  "type": "Feature",
  "properties": {
    "gn:admin1_code":"16.0",
    "gn:admin2_code":"523.0",
    "gn:asciiname":"Mangrul Tanda",
    "gn:country_code":"IN",
    "gn:dem":453,
    "gn:feature_class":"P",
    "gn:feature_code":"PPL",
    "gn:name":"Mangr\u016bl T\u0101nda",
    "gn:population":0,
    "gn:timezone":"Asia/Kolkata",
    "iso:country":"IN",
    "wof:name":"Mangrul Tanda",
    "wof:placetype":"locality"
},
  "geometry": {"coordinates":[76.12048,19.16274],"type":"Point"}
}