{
  "type": "Feature",
  "properties": {
    "gn:admin1_code":"19.0",
    "gn:admin2_code":"563.0",
    "gn:asciiname":"Bellur",
    "gn:country_code":"IN",
    "gn:dem":29,
    "gn:feature_class":"P",
    "gn:feature_code":"PPL",
    "gn:name":"Bell\u016br",
    "gn:population":0,
    "gn:timezone":"Asia/Kolkata",
    "iso:country":"IN",
    "ks:ks_name":"Belur",
    "ks:ks_pop":112,
    "ks:ks_type":"VILLAGE",
    "name:eng_x_preferred":[
        "Belur"
    ],
    "name:eng_x_variant":[
        "Bellur"
    ],
    "wof:name":"Belur",
    "wof:placetype":"locality",
    "wof:population":112
},
  "geometry": {"coordinates":[74.245739,14.831075],"type":"Point"}
}