{
  "type": "Feature",
  "properties": {
    "gn:admin1_code":"19",
    "gn:admin2_code":"563.0",
    "gn:asciiname":"Hosmane",
    "gn:country_code":"IN",
    "gn:dem":613,
    "gn:feature_class":"P",
    "gn:feature_code":"PPL",
    "gn:name":"Hosmane",
    "gn:population":0,
    "gn:timezone":"Asia/Kolkata",
    "iso:country":"IN",
    "wof:name":"Hosmane",
    "wof:placetype":"locality"
},
  "geometry": {"coordinates":[74.8468,14.22233],"type":"Point"}
}