{
  "type": "Feature",
  "properties": {
    "iso:country":"IN",
    "ks:ks_name":"Jadghavwasti",
    "ks:ks_pop":120,
    "ks:ks_type":"HABITATION",
    "name:eng_x_preferred":[
        "Jadghavwasti"
    ],
    "wof:name":"Jadghavwasti",
    "wof:placetype":"locality",
    "wof:population":120
},
  "geometry": {"coordinates":[74.642493,17.871228],"type":"Point"}
}