{
  "type": "Feature",
  "properties": {
    "iso:country":"IN",
    "ks:ks_alt_nam":"Jall\u0101pur",
    "ks:ks_name":"Jallapur",
    "ks:ks_type":"VILLAGE",
    "ks:ks_uagg_main":0,
    "name:eng_x_preferred":[
        "Jallapur"
    ],
    "name:eng_x_variant":[
        "Jall\u0101pur"
    ],
    "wof:name":"Jallapur",
    "wof:placetype":"neighbourhood"
},
  "geometry": {"coordinates":[82.583546,25.392351],"type":"Point"}
}