{
  "type": "Feature",
  "properties": {
    "iso:country":"IN",
    "ks:ks_name":"Bhawan Singh Nawar",
    "ks:ks_pop":708,
    "ks:ks_type":"VILLAGE",
    "ks:ks_uagg_main":0,
    "name:eng_x_preferred":[
        "Bhawan Singh Nawar"
    ],
    "wof:name":"Bhawan Singh Nawar",
    "wof:placetype":"neighbourhood",
    "wof:population":708
},
  "geometry": {"coordinates":[79.534094,29.131335],"type":"Point"}
}