{
  "type": "Feature",
  "properties": {
    "gn:admin1_code":"35",
    "gn:admin2_code":"456.0",
    "gn:asciiname":"Janawarkheda",
    "gn:country_code":"IN",
    "gn:dem":601,
    "gn:feature_class":"P",
    "gn:feature_code":"PPL",
    "gn:name":"Jan\u0101warkheda",
    "gn:population":0,
    "gn:timezone":"Asia/Kolkata",
    "iso:country":"IN",
    "ks:ks_alt_nam":"Jan\u0101warkheda",
    "ks:ks_name":"Janawarkheda",
    "ks:ks_pop":402,
    "ks:ks_type":"VILLAGE",
    "name:eng_x_preferred":[
        "Janawarkheda"
    ],
    "name:eng_x_variant":[
        "Jan\u0101warkheda"
    ],
    "wof:name":"Janawarkheda",
    "wof:placetype":"locality",
    "wof:population":402
},
  "geometry": {"coordinates":[79.462959,21.926838],"type":"Point"}
}