{
  "type": "Feature",
  "properties": {
    "iso:country":"IN",
    "ks:ks_name":"Sahab Rampur",
    "ks:ks_pop":63,
    "ks:ks_type":"VILLAGE",
    "name:eng_x_preferred":[
        "Sahab Rampur"
    ],
    "wof:name":"Sahab Rampur",
    "wof:placetype":"locality",
    "wof:population":63
},
  "geometry": {"coordinates":[78.888398,27.000001],"type":"Point"}
}