{
  "type": "Feature",
  "properties": {
    "iso:country":"IN",
    "ks:ks_name":"Mahadev Falia",
    "ks:ks_pop":223,
    "ks:ks_type":"HABITATION",
    "name:eng_x_preferred":[
        "Mahadev Falia"
    ],
    "wof:name":"Mahadev Falia",
    "wof:placetype":"locality",
    "wof:population":223
},
  "geometry": {"coordinates":[73.84863900000001,23.397806],"type":"Point"}
}