{
  "type": "Feature",
  "properties": {
    "gn:admin1_code":"36.0",
    "gn:admin2_code":"149.0",
    "gn:asciiname":"Son Kalan",
    "gn:country_code":"IN",
    "gn:dem":173,
    "gn:feature_class":"P",
    "gn:feature_code":"PPL",
    "gn:name":"Son Kal\u0101n",
    "gn:population":0,
    "gn:timezone":"Asia/Kolkata",
    "iso:country":"IN",
    "ks:ks_name":"Sonkala",
    "ks:ks_type":"VILLAGE",
    "name:eng_x_preferred":[
        "Sonkala"
    ],
    "name:eng_x_variant":[
        "Son Kalan"
    ],
    "wof:name":"Sonkala",
    "wof:placetype":"locality"
},
  "geometry": {"coordinates":[78.586718,28.059895],"type":"Point"}
}