{
  "type": "Feature",
  "properties": {
    "gn:admin1_code":"02",
    "gn:admin2_code":"549.0",
    "gn:asciiname":"Racherla",
    "gn:country_code":"IN",
    "gn:dem":238,
    "gn:feature_class":"P",
    "gn:feature_code":"PPL",
    "gn:name":"R\u0101cherla",
    "gn:population":0,
    "gn:timezone":"Asia/Kolkata",
    "iso:country":"IN",
    "name:ceb_x_preferred":[
        "R\u0101cherla"
    ],
    "name:swe_x_preferred":[
        "R\u0101cherla"
    ],
    "name:tel_x_preferred":[
        "\u0c30\u0c3e\u0c1a\u0c30\u0c4d\u0c32"
    ],
    "name:urd_x_preferred":[
        "\u0631\u0627\u0686\u06cc\u0631\u0644\u0627"
    ],
    "wof:name":"Racherla",
    "wof:placetype":"locality"
},
  "geometry": {"coordinates":[78.96587,15.46298],"type":"Point"}
}