{
  "type": "Feature",
  "properties": {
    "gn:admin1_code":"02",
    "gn:admin2_code":"549.0",
    "gn:asciiname":"Racherla",
    "gn:country_code":"IN",
    "gn:dem":238,
    "gn:feature_class":"P",
    "gn:feature_code":"PPL",
    "gn:name":"R\u0101cherla",
    "gn:population":0,
    "gn:timezone":"Asia/Kolkata",
    "iso:country":"IN",
    "name:und_x_variant":[
        "R\u0101cherla"
    ],
    "wof:name":"Racherla",
    "wof:placetype":"locality"
},
  "geometry": {"coordinates":[78.96587,15.46298],"type":"Point"}
}