{
  "type": "Feature",
  "properties": {
    "iso:country":"IN",
    "ks:ks_name":"Kesharpura Parsa",
    "ks:ks_pop":498,
    "ks:ks_type":"HABITATION",
    "name:eng_x_preferred":[
        "Kesharpura Parsa"
    ],
    "wof:name":"Kesharpura Parsa",
    "wof:placetype":"locality",
    "wof:population":498
},
  "geometry": {"coordinates":[74.30024400000001,26.052931],"type":"Point"}
}