{
  "type": "Feature",
  "properties": {
    "gn:country":"IN",
    "gn:fcode":"PPL",
    "gn:population":164810,
    "iso:country":"IN",
    "name:ara_x_preferred":[
        "\u0635\u0627\u0644\u0648\u0646\u064a"
    ],
    "name:ben_bn_x_preferred":[
        "\u09b8\u09be\u09b2\u09cb\u09a8\u09bf"
    ],
    "name:ben_in_x_preferred":[
        "\u09b8\u09be\u09b2\u09cb\u09a8\u09bf"
    ],
    "name:bpy_x_preferred":[
        "\u09b2\u09cb\u09a8\u09bf"
    ],
    "name:ceb_x_preferred":[
        "Loni"
    ],
    "name:deu_x_preferred":[
        "Loni"
    ],
    "name:eng_x_preferred":[
        "Loni"
    ],
    "name:fas_x_preferred":[
        "\u0644\u0648\u0646\u06cc"
    ],
    "name:fra_x_preferred":[
        "Loni"
    ],
    "name:guj_x_preferred":[
        "\u0ab8\u0ab2\u0acb\u0aa8\u0ac0"
    ],
    "name:hif_x_preferred":[
        "Loni"
    ],
    "name:hin_x_preferred":[
        "\u0938\u0932\u094b\u0928\u0940"
    ],
    "name:hin_x_variant":[
        "\u0932\u094b\u0928\u0940"
    ],
    "name:ita_x_preferred":[
        "Loni"
    ],
    "name:jpn_x_preferred":[
        "\u30ed\u30cb"
    ],
    "name:kan_x_preferred":[
        "\u0cb8\u0cb2\u0ccb\u0ca8\u0cbf"
    ],
    "name:mal_x_preferred":[
        "\u0d38\u0d32\u0d4b\u0d28\u0d3f"
    ],
    "name:mar_x_preferred":[
        "\u0938\u0932\u094b\u0928\u0940"
    ],
    "name:msa_x_preferred":[
        "Loni"
    ],
    "name:nan_x_preferred":[
        "Loni"
    ],
    "name:new_x_preferred":[
        "\u0932\u094b\u0928\u0940"
    ],
    "name:nld_x_preferred":[
        "Loni"
    ],
    "name:ori_x_preferred":[
        "Loni"
    ],
    "name:pan_x_preferred":[
        "\u0a38\u0a3e\u0a32\u0a4c\u0a28\u0a40"
    ],
    "name:pol_x_preferred":[
        "Loni"
    ],
    "name:rus_x_preferred":[
        "\u041b\u043e\u043d\u0435"
    ],
    "name:srp_x_preferred":[
        "\u041b\u043e\u043d\u0438"
    ],
    "name:swe_x_preferred":[
        "Loni"
    ],
    "name:tam_x_preferred":[
        "\u0b9a\u0bb2\u0bcb\u0ba9\u0bbf"
    ],
    "name:tam_x_variant":[
        "\u0bb2\u0bcb\u0ba9\u0bbf"
    ],
    "name:tel_x_preferred":[
        "\u0c38\u0c32\u0c4b\u0c28\u0c3f"
    ],
    "name:urd_x_preferred":[
        "\u0633\u0644\u0648\u0646\u06cc"
    ],
    "name:urd_x_variant":[
        "\u0644\u0648\u0646\u06cc\u060c \u0628\u06be\u0627\u0631\u062a",
        "\u0644\u0648\u0646\u06cc"
    ],
    "name:vie_x_preferred":[
        "Loni"
    ],
    "qs_pg:aaroncc":"IN",
    "qs_pg:gn_country":"IN",
    "qs_pg:gn_fcode":"PPL",
    "qs_pg:gn_pop":164810,
    "qs_pg:name":"Saloni",
    "qs_pg:name_adm0":"India",
    "qs_pg:name_adm1":"Uttar Pradesh",
    "qs_pg:photos_9r":0,
    "qs_pg:photos_sr":0,
    "qs_pg:pop_sr":9,
    "qs_pg:qs_pg_placetype":"locality",
    "qs_pg:qs_pg_placetype_gp":"Town",
    "qs_pg:woe_adm0":23424848,
    "woe:adm0_id":23424848,
    "woe:name_adm0":"India",
    "woe:name_adm1":"Uttar Pradesh",
    "woe:placetype":"Town",
    "wof:name":"Saloni",
    "wof:placetype":"neighbourhood",
    "wof:population":164810
},
  "geometry": {"coordinates":[77.288,28.75153],"type":"Point"}
}