{
  "type": "Feature",
  "properties": {
    "iso:country":"IN",
    "ks:ks_name":"Barbari",
    "ks:ks_pop":1425,
    "ks:ks_type":"VILLAGE",
    "ks:ks_uagg_main":0,
    "name:eng_x_preferred":[
        "Barbari"
    ],
    "wof:name":"Barbari",
    "wof:placetype":"neighbourhood",
    "wof:population":1425
},
  "geometry": {"coordinates":[91.270696,26.486425],"type":"Point"}
}