{
  "type": "Feature",
  "properties": {
    "iso:country":"IN",
    "ks:ks_name":"Anara",
    "ks:ks_pop":1895,
    "ks:ks_type":"HABITATION",
    "name:eng_x_preferred":[
        "Anara"
    ],
    "wof:name":"Anara",
    "wof:placetype":"locality",
    "wof:population":1895
},
  "geometry": {"coordinates":[75.62457999999999,12.077879],"type":"Point"}
}