{
  "type": "Feature",
  "properties": {
    "iso:country":"IN",
    "ks:ks_name":"Kallootu Kunnu",
    "ks:ks_pop":400,
    "ks:ks_type":"HABITATION",
    "name:eng_x_preferred":[
        "Kallootu Kunnu"
    ],
    "wof:name":"Kallootu Kunnu",
    "wof:placetype":"locality",
    "wof:population":400
},
  "geometry": {"coordinates":[75.794061,11.473007],"type":"Point"}
}