{
  "type": "Feature",
  "properties": {
    "gn:admin1_code":"35",
    "gn:admin2_code":"454.0",
    "gn:asciiname":"Khar Deori",
    "gn:country_code":"IN",
    "gn:dem":607,
    "gn:feature_class":"P",
    "gn:feature_code":"PPL",
    "gn:name":"Khar Deori",
    "gn:population":0,
    "gn:timezone":"Asia/Kolkata",
    "iso:country":"IN",
    "ks:ks_name":"Khardeori",
    "ks:ks_pop":403,
    "ks:ks_type":"HABITATION",
    "name:eng_x_preferred":[
        "Khardeori"
    ],
    "name:eng_x_variant":[
        "Khar Deori"
    ],
    "wof:name":"Khardeori",
    "wof:placetype":"locality",
    "wof:population":403
},
  "geometry": {"coordinates":[81.026972,22.551954],"type":"Point"}
}