{
  "type": "Feature",
  "properties": {
    "gn:admin1_code":"23.0",
    "gn:admin2_code":"49.0",
    "gn:asciiname":"Budha Varsal",
    "gn:country_code":"IN",
    "gn:dem":225,
    "gn:feature_class":"P",
    "gn:feature_code":"PPL",
    "gn:name":"Budha Vars\u0101l",
    "gn:population":0,
    "gn:timezone":"Asia/Karachi",
    "iso:country":"IN",
    "wof:name":"Budha Varsal",
    "wof:placetype":"locality"
},
  "geometry": {"coordinates":[74.78498,31.94539],"type":"Point"}
}