{
  "type": "Feature",
  "properties": {
    "gn:admin1_code":"23.0",
    "gn:admin2_code":"49.0",
    "gn:asciiname":"Budha Varsal",
    "gn:country_code":"IN",
    "gn:dem":225,
    "gn:feature_class":"P",
    "gn:feature_code":"PPL",
    "gn:name":"Budha Vars\u0101l",
    "gn:population":0,
    "gn:timezone":"Asia/Karachi",
    "iso:country":"IN",
    "ks:ks_name":"Budha Warsal",
    "ks:ks_pop":0,
    "ks:ks_type":"VILLAGE",
    "name:eng_x_preferred":[
        "Budha Warsal"
    ],
    "name:eng_x_variant":[
        "Budha Varsal"
    ],
    "wof:name":"Budha Warsal",
    "wof:placetype":"locality",
    "wof:population":0
},
  "geometry": {"coordinates":[74.79298300000001,31.947085],"type":"Point"}
}