{
  "type": "Feature",
  "properties": {
    "iso:country":"IN",
    "ks:ks_name":"Charno Ki Dhani",
    "ks:ks_pop":1039,
    "ks:ks_type":"VILLAGE",
    "name:eng_x_preferred":[
        "Charno Ki Dhani"
    ],
    "wof:name":"Charno Ki Dhani",
    "wof:placetype":"locality",
    "wof:population":1039
},
  "geometry": {"coordinates":[70.847669,25.858883],"type":"Point"}
}