{
  "type": "Feature",
  "properties": {
    "iso:country":"IN",
    "ks:ks_name":"Kala Bahadurpur",
    "ks:ks_pop":137,
    "ks:ks_type":"HABITATION",
    "name:eng_x_preferred":[
        "Kala Bahadurpur"
    ],
    "wof:name":"Kala Bahadurpur",
    "wof:placetype":"locality",
    "wof:population":137
},
  "geometry": {"coordinates":[80.965943,27.656003],"type":"Point"}
}