{
  "type": "Feature",
  "properties": {
    "iso:country":"IN",
    "ks:ks_name":"Munda Tola",
    "ks:ks_type":"VILLAGE",
    "name:eng_x_preferred":[
        "Munda Tola"
    ],
    "wof:name":"Munda Tola",
    "wof:placetype":"locality"
},
  "geometry": {"coordinates":[81.00098800000001,20.807881],"type":"Point"}
}