{
  "type": "Feature",
  "properties": {
    "iso:country":"IN",
    "ks:ks_alt_nam":"UP Seema",
    "ks:ks_name":"Up Seema",
    "ks:ks_pop":671,
    "ks:ks_type":"HABITATION",
    "ks:ks_uagg_main":0,
    "name:eng_x_preferred":[
        "Up Seema"
    ],
    "wof:name":"Up Seema",
    "wof:placetype":"neighbourhood",
    "wof:population":671
},
  "geometry": {"coordinates":[83.963566,27.138883],"type":"Point"}
}