{
  "type": "Feature",
  "properties": {
    "iso:country":"IN",
    "ks:ks_name":"Kusumaguda",
    "ks:ks_pop":85,
    "ks:ks_type":"VILLAGE",
    "name:eng_x_preferred":[
        "Kusumaguda"
    ],
    "wof:name":"Kusumaguda",
    "wof:placetype":"locality",
    "wof:population":85
},
  "geometry": {"coordinates":[83.711789,19.046482],"type":"Point"}
}