{
  "type": "Feature",
  "properties": {
    "iso:country":"IN",
    "ks:ks_name":"Hasdoba",
    "ks:ks_pop":271,
    "ks:ks_type":"HABITATION",
    "name:eng_x_preferred":[
        "Hasdoba"
    ],
    "wof:name":"Hasdoba",
    "wof:placetype":"locality",
    "wof:population":271
},
  "geometry": {"coordinates":[90.377765,26.477412],"type":"Point"}
}