{
  "type": "Feature",
  "properties": {
    "iso:country":"IN",
    "ks:ks_name":"Arjuna Tanr",
    "ks:ks_pop":269,
    "ks:ks_type":"HABITATION",
    "name:eng_x_preferred":[
        "Arjuna Tanr"
    ],
    "wof:name":"Arjuna Tanr",
    "wof:placetype":"locality",
    "wof:population":269
},
  "geometry": {"coordinates":[85.61524300000001,23.721405],"type":"Point"}
}