{
  "type": "Feature",
  "properties": {
    "iso:country":"IN",
    "ks:ks_name":"Tughro",
    "ks:ks_pop":512,
    "ks:ks_type":"HABITATION",
    "name:eng_x_preferred":[
        "Tughro"
    ],
    "wof:name":"Tughro",
    "wof:placetype":"locality",
    "wof:population":512
},
  "geometry": {"coordinates":[86.76527900000001,24.87604],"type":"Point"}
}