{
  "type": "Feature",
  "properties": {
    "iso:country":"IN",
    "ks:ks_name":"Nupurjuli 1",
    "ks:ks_pop":1448,
    "ks:ks_type":"HABITATION",
    "name:eng_x_preferred":[
        "Nupurjuli 1"
    ],
    "wof:name":"Nupurjuli 1",
    "wof:placetype":"locality",
    "wof:population":1448
},
  "geometry": {"coordinates":[92.38951900000001,26.685956],"type":"Point"}
}