{
  "type": "Feature",
  "properties": {
    "iso:country":"IN",
    "ks:ks_name":"Dumana Paikbar",
    "ks:ks_pop":303,
    "ks:ks_type":"VILLAGE",
    "name:eng_x_preferred":[
        "Dumana Paikbar"
    ],
    "wof:name":"Dumana Paikbar",
    "wof:placetype":"locality",
    "wof:population":303
},
  "geometry": {"coordinates":[87.624636,21.759018],"type":"Point"}
}