{
  "type": "Feature",
  "properties": {
    "iso:country":"IN",
    "ks:ks_name":"Hinjalkhal",
    "ks:ks_pop":453,
    "ks:ks_type":"VILLAGE",
    "ks:ks_uagg_main":0,
    "name:eng_x_preferred":[
        "Hinjalkhal"
    ],
    "wof:name":"Hinjalkhal",
    "wof:placetype":"neighbourhood",
    "wof:population":453
},
  "geometry": {"coordinates":[84.946258,20.527129],"type":"Point"}
}