{
  "type": "Feature",
  "properties": {
    "iso:country":"IN",
    "ks:ks_name":"Navnathnagar",
    "ks:ks_pop":260,
    "ks:ks_type":"HABITATION",
    "name:eng_x_preferred":[
        "Navnathnagar"
    ],
    "wof:name":"Navnathnagar",
    "wof:placetype":"locality",
    "wof:population":260
},
  "geometry": {"coordinates":[74.68538700000001,18.51475],"type":"Point"}
}