{
  "type": "Feature",
  "properties": {
    "iso:country":"IN",
    "ks:ks_name":"Anjari",
    "ks:ks_pop":224,
    "ks:ks_type":"VILLAGE",
    "name:eng_x_preferred":[
        "Anjari"
    ],
    "wof:name":"Anjari",
    "wof:placetype":"locality",
    "wof:population":224
},
  "geometry": {"coordinates":[77.213514,27.481291],"type":"Point"}
}