{
  "type": "Feature",
  "properties": {
    "iso:country":"IN",
    "ks:ks_name":"Uday Chandrapur",
    "ks:ks_pop":3687,
    "ks:ks_type":"VILLAGE",
    "ks:ks_uagg_main":0,
    "name:eng_x_preferred":[
        "Uday Chandrapur"
    ],
    "wof:name":"Uday Chandrapur",
    "wof:placetype":"neighbourhood",
    "wof:population":3687
},
  "geometry": {"coordinates":[88.310551,23.558614],"type":"Point"}
}