{
  "type": "Feature",
  "properties": {
    "iso:country":"IN",
    "ks:ks_name":"Saida Fv",
    "ks:ks_pop":540,
    "ks:ks_type":"HABITATION",
    "name:eng_x_preferred":[
        "Saida Fv"
    ],
    "wof:name":"Saida Fv",
    "wof:placetype":"locality",
    "wof:population":540
},
  "geometry": {"coordinates":[80.977281,22.442081],"type":"Point"}
}