{
  "type": "Feature",
  "properties": {
    "iso:country":"IN",
    "ks:ks_name":"Thar Gimi Pal",
    "ks:ks_pop":35,
    "ks:ks_type":"HABITATION",
    "name:eng_x_preferred":[
        "Thar Gimi Pal"
    ],
    "wof:name":"Thar Gimi Pal",
    "wof:placetype":"locality",
    "wof:population":35
},
  "geometry": {"coordinates":[78.239846,27.152466],"type":"Point"}
}