{
  "type": "Feature",
  "properties": {
    "gn:admin1_code":"36",
    "gn:admin2_code":"191.0",
    "gn:asciiname":"Tirwa",
    "gn:country_code":"IN",
    "gn:dem":78,
    "gn:feature_class":"P",
    "gn:feature_code":"PPL",
    "gn:name":"Tirwa",
    "gn:population":0,
    "gn:timezone":"Asia/Kolkata",
    "iso:country":"IN",
    "name:hin_x_preferred":[
        "\u0924\u093f\u0930\u094d\u0935\u093e"
    ],
    "wof:name":"Tirwa",
    "wof:placetype":"neighbourhood"
},
  "geometry": {"coordinates":[83.21702999999999,26.2765],"type":"Point"}
}