{
  "type": "Feature",
  "properties": {
    "iso:country":"IN",
    "ks:ks_name":"Thachankunnu",
    "ks:ks_pop":680,
    "ks:ks_type":"HABITATION",
    "name:eng_x_preferred":[
        "Thachankunnu"
    ],
    "wof:name":"Thachankunnu",
    "wof:placetype":"locality",
    "wof:population":680
},
  "geometry": {"coordinates":[76.194751,10.746686],"type":"Point"}
}