{
  "type": "Feature",
  "properties": {
    "iso:country":"IN",
    "ks:ks_name":"Mallah Tola",
    "ks:ks_pop":132,
    "ks:ks_type":"HABITATION",
    "name:eng_x_preferred":[
        "Mallah Tola"
    ],
    "wof:name":"Mallah Tola",
    "wof:placetype":"locality",
    "wof:population":132
},
  "geometry": {"coordinates":[84.18556100000001,26.189225],"type":"Point"}
}