{
  "type": "Feature",
  "properties": {
    "iso:country":"IN",
    "ks:ks_name":"Udanikhas",
    "ks:ks_pop":1015,
    "ks:ks_type":"HABITATION",
    "name:eng_x_preferred":[
        "Udanikhas"
    ],
    "wof:name":"Udanikhas",
    "wof:placetype":"locality",
    "wof:population":1015
},
  "geometry": {"coordinates":[84.165705,23.313265],"type":"Point"}
}