{
  "type": "Feature",
  "properties": {
    "iso:country":"IN",
    "ks:ks_name":"Peddapara",
    "ks:ks_pop":257,
    "ks:ks_type":"HABITATION",
    "name:eng_x_preferred":[
        "Peddapara"
    ],
    "wof:name":"Peddapara",
    "wof:placetype":"locality",
    "wof:population":257
},
  "geometry": {"coordinates":[81.091064,18.742657],"type":"Point"}
}