{
  "type": "Feature",
  "properties": {
    "iso:country":"IN",
    "ks:ks_name":"Manakkachira",
    "ks:ks_pop":963,
    "ks:ks_type":"HABITATION",
    "name:eng_x_preferred":[
        "Manakkachira"
    ],
    "wof:name":"Manakkachira",
    "wof:placetype":"locality",
    "wof:population":963
},
  "geometry": {"coordinates":[76.44148800000001,9.758467],"type":"Point"}
}