{
  "type": "Feature",
  "properties": {
    "iso:country":"IN",
    "ks:ks_alt_nam":"Bhugmari NC",
    "ks:ks_name":"Bhugmari Nc",
    "ks:ks_pop":248,
    "ks:ks_type":"HABITATION",
    "name:eng_x_preferred":[
        "Bhugmari Nc"
    ],
    "wof:name":"Bhugmari Nc",
    "wof:placetype":"locality",
    "wof:population":248
},
  "geometry": {"coordinates":[94.832166,27.295665],"type":"Point"}
}