{
  "type": "Feature",
  "properties": {
    "gn:admin1_code":"34.0",
    "gn:admin2_code":"216.0",
    "gn:asciiname":"Mohanpur Asli",
    "gn:country_code":"IN",
    "gn:dem":60,
    "gn:feature_class":"P",
    "gn:feature_code":"PPL",
    "gn:name":"Mohanpur Asli",
    "gn:population":0,
    "gn:timezone":"Asia/Kolkata",
    "iso:country":"IN",
    "ks:ks_name":"Mohanpur Asli",
    "ks:ks_pop":902,
    "ks:ks_type":"VILLAGE",
    "name:eng_x_preferred":[
        "Mohanpur Asli"
    ],
    "wof:name":"Mohanpur Asli",
    "wof:placetype":"locality",
    "wof:population":902
},
  "geometry": {"coordinates":[85.318477,25.943768],"type":"Point"}
}