{
  "type": "Feature",
  "properties": {
    "iso:country":"IN",
    "ks:ks_name":"Karlabudia",
    "ks:ks_pop":249,
    "ks:ks_type":"HABITATION",
    "name:eng_x_preferred":[
        "Karlabudia"
    ],
    "wof:name":"Karlabudia",
    "wof:placetype":"locality",
    "wof:population":249
},
  "geometry": {"coordinates":[84.085257,21.701115],"type":"Point"}
}