{
  "type": "Feature",
  "properties": {
    "iso:country":"IN",
    "ks:ks_name":"Barda Falia",
    "ks:ks_pop":124,
    "ks:ks_type":"HABITATION",
    "name:eng_x_preferred":[
        "Barda Falia"
    ],
    "wof:name":"Barda Falia",
    "wof:placetype":"locality",
    "wof:population":124
},
  "geometry": {"coordinates":[73.131056,20.247089],"type":"Point"}
}