{
  "type": "Feature",
  "properties": {
    "gn:admin1_code":"38.0",
    "gn:admin2_code":"347.0",
    "gn:asciiname":"Bongagarha",
    "gn:country_code":"IN",
    "gn:dem":548,
    "gn:feature_class":"P",
    "gn:feature_code":"PPL",
    "gn:name":"Bong\u0101garh\u0101",
    "gn:population":0,
    "gn:timezone":"Asia/Kolkata",
    "iso:country":"IN",
    "ks:ks_alt_nam":"Bong\u0101garh\u0101",
    "ks:ks_name":"Bongagarha",
    "ks:ks_pop":104,
    "ks:ks_type":"VILLAGE",
    "name:eng_x_preferred":[
        "Bongagarha"
    ],
    "name:eng_x_variant":[
        "Bong\u0101garh\u0101"
    ],
    "wof:name":"Bongagarha",
    "wof:placetype":"locality",
    "wof:population":104
},
  "geometry": {"coordinates":[85.001237,24.010397],"type":"Point"}
}