{
  "type": "Feature",
  "properties": {
    "gn:admin1_code":"12",
    "gn:admin2_code":"14.0",
    "gn:asciiname":"Chhitrus Budur",
    "gn:country_code":"IN",
    "gn:dem":1741,
    "gn:feature_class":"P",
    "gn:feature_code":"PPL",
    "gn:name":"Chhitrus Budur",
    "gn:population":0,
    "gn:timezone":"Asia/Kolkata",
    "iso:country":"IN",
    "wof:name":"Chhitrus Budur",
    "wof:placetype":"locality"
},
  "geometry": {"coordinates":[75.23409000000002,33.83954],"type":"Point"}
}