{
  "type": "Feature",
  "properties": {
    "iso:country":"IN",
    "ks:ks_name":"Dandasur",
    "ks:ks_pop":233,
    "ks:ks_type":"HABITATION",
    "name:eng_x_preferred":[
        "Dandasur"
    ],
    "wof:name":"Dandasur",
    "wof:placetype":"locality",
    "wof:population":233
},
  "geometry": {"coordinates":[80.605778,20.61216],"type":"Point"}
}