{
  "type": "Feature",
  "properties": {
    "iso:country":"IN",
    "ks:ks_name":"Salpur",
    "ks:ks_pop":40,
    "ks:ks_type":"VILLAGE",
    "name:eng_x_preferred":[
        "Salpur"
    ],
    "wof:name":"Salpur",
    "wof:placetype":"locality",
    "wof:population":40
},
  "geometry": {"coordinates":[79.37247000000001,30.092606],"type":"Point"}
}