{
  "type": "Feature",
  "properties": {
    "iso:country":"IN",
    "ks:ks_alt_nam":"HARNESWARMANDIR",
    "ks:ks_name":"Harneswarmandir",
    "ks:ks_pop":225,
    "ks:ks_type":"HABITATION",
    "name:eng_x_preferred":[
        "Harneswarmandir"
    ],
    "wof:name":"Harneswarmandir",
    "wof:placetype":"locality",
    "wof:population":225
},
  "geometry": {"coordinates":[74.903212,17.140297],"type":"Point"}
}