{
  "type": "Feature",
  "properties": {
    "gn:admin1_code":"35",
    "gn:admin2_code":"463.0",
    "gn:asciiname":"Majholi",
    "gn:country_code":"IN",
    "gn:dem":383,
    "gn:feature_class":"P",
    "gn:feature_code":"PPL",
    "gn:name":"Majholi",
    "gn:population":0,
    "gn:timezone":"Asia/Kolkata",
    "iso:country":"IN",
    "name:ben_x_preferred":[
        "\u09ae\u09be\u099d\u09cb\u09b2\u09bf"
    ],
    "name:bpy_x_preferred":[
        "\u09ae\u09be\u099d\u09cb\u09b2\u09bf"
    ],
    "name:ceb_x_preferred":[
        "Majhol\u012b"
    ],
    "name:ita_x_preferred":[
        "Majholi"
    ],
    "name:msa_x_preferred":[
        "Majholi"
    ],
    "name:new_x_preferred":[
        "\u092e\u091d\u094b\u0932\u0940"
    ],
    "name:nld_x_preferred":[
        "Majholi"
    ],
    "name:por_x_preferred":[
        "Majholi"
    ],
    "name:swe_x_preferred":[
        "Majhol\u012b"
    ],
    "name:vie_x_preferred":[
        "Majholi"
    ],
    "name:zho_x_preferred":[
        "\u9a6c\u4e54\u5229"
    ],
    "wof:name":"Majholi",
    "wof:placetype":"locality"
},
  "geometry": {"coordinates":[82.41424000000001,24.21459],"type":"Point"}
}