{
  "type": "Feature",
  "properties": {
    "gn:admin1_code":"36.0",
    "gn:admin2_code":"148",
    "gn:asciiname":"Bhawalpur",
    "gn:country_code":"IN",
    "gn:dem":154,
    "gn:feature_class":"P",
    "gn:feature_code":"PPL",
    "gn:name":"Bh\u0101walpur",
    "gn:population":0,
    "gn:timezone":"Asia/Kolkata",
    "iso:country":"IN",
    "ks:ks_name":"Bhawalpur",
    "ks:ks_pop":437,
    "ks:ks_type":"VILLAGE",
    "name:eng_x_preferred":[
        "Bhawalpur"
    ],
    "wof:name":"Bhawalpur",
    "wof:placetype":"locality",
    "wof:population":437
},
  "geometry": {"coordinates":[79.30051,27.201658],"type":"Point"}
}