{
  "type": "Feature",
  "properties": {
    "gn:admin1_code":"34.0",
    "gn:admin2_code":"219.0",
    "gn:asciiname":"Parsotimpur",
    "gn:country_code":"IN",
    "gn:dem":56,
    "gn:feature_class":"P",
    "gn:feature_code":"PPL",
    "gn:name":"Parsotimpur",
    "gn:population":0,
    "gn:timezone":"Asia/Kolkata",
    "iso:country":"IN",
    "ks:ks_name":"Parsotimpur",
    "ks:ks_pop":1002,
    "ks:ks_type":"VILLAGE",
    "ks:ks_uagg_main":0,
    "name:eng_x_preferred":[
        "Parsotimpur"
    ],
    "wof:name":"Parsotimpur",
    "wof:placetype":"neighbourhood",
    "wof:population":1002
},
  "geometry": {"coordinates":[85.055094,25.77196],"type":"Point"}
}