{
  "type": "Feature",
  "properties": {
    "iso:country":"IN",
    "ks:ks_name":"Chimtapally",
    "ks:ks_pop":37,
    "ks:ks_type":"HABITATION",
    "ks:ks_uagg_main":0,
    "name:eng_x_preferred":[
        "Chimtapally"
    ],
    "wof:name":"Chimtapally",
    "wof:placetype":"neighbourhood",
    "wof:population":37
},
  "geometry": {"coordinates":[82.28291400000001,18.575255],"type":"Point"}
}