{
  "type": "Feature",
  "properties": {
    "iso:country":"IN",
    "ks:ks_name":"Champanagar",
    "ks:ks_pop":345,
    "ks:ks_type":"VILLAGE",
    "name:eng_x_preferred":[
        "Champanagar"
    ],
    "wof:name":"Champanagar",
    "wof:placetype":"locality",
    "wof:population":345
},
  "geometry": {"coordinates":[83.82546000000001,23.363925],"type":"Point"}
}