{
  "type": "Feature",
  "properties": {
    "iso:country":"IN",
    "ks:ks_alt_nam":"Feekya naik tanda",
    "ks:ks_name":"Feekya Naik Tanda",
    "ks:ks_pop":186,
    "ks:ks_type":"HABITATION",
    "name:eng_x_preferred":[
        "Feekya Naik Tanda"
    ],
    "wof:name":"Feekya Naik Tanda",
    "wof:placetype":"locality",
    "wof:population":186
},
  "geometry": {"coordinates":[78.146979,18.210719],"type":"Point"}
}