{
  "type": "Feature",
  "properties": {
    "iso:country":"IN",
    "ks:ks_name":"Saguni More Dom Tola",
    "ks:ks_pop":567,
    "ks:ks_type":"HABITATION",
    "ks:ks_uagg_main":0,
    "name:eng_x_preferred":[
        "Saguni More Dom Tola"
    ],
    "wof:name":"Saguni More Dom Tola",
    "wof:placetype":"neighbourhood",
    "wof:population":567
},
  "geometry": {"coordinates":[87.207804,25.570454],"type":"Point"}
}