{
  "type": "Feature",
  "properties": {
    "iso:country":"IN",
    "ks:ks_alt_nam":"Sakurpur Bah\u0101durpur",
    "ks:ks_name":"Sakurpur Bahadurpur",
    "ks:ks_type":"VILLAGE",
    "name:eng_x_preferred":[
        "Sakurpur Bahadurpur"
    ],
    "name:eng_x_variant":[
        "Sakurpur Bah\u0101durpur"
    ],
    "wof:name":"Sakurpur Bahadurpur",
    "wof:placetype":"locality"
},
  "geometry": {"coordinates":[78.26373100000001,29.579749],"type":"Point"}
}