{
  "type": "Feature",
  "properties": {
    "iso:country":"IN",
    "ks:ks_alt_nam":"Poddar tola.",
    "ks:ks_name":"Poddar Tola.",
    "ks:ks_pop":196,
    "ks:ks_type":"HABITATION",
    "name:eng_x_preferred":[
        "Poddar Tola."
    ],
    "wof:name":"Poddar Tola.",
    "wof:placetype":"locality",
    "wof:population":196
},
  "geometry": {"coordinates":[86.51810999999999,25.766701],"type":"Point"}
}