{
  "type": "Feature",
  "properties": {
    "iso:country":"IN",
    "ks:ks_name":"Sukhai",
    "ks:ks_pop":492,
    "ks:ks_type":"VILLAGE",
    "name:eng_x_preferred":[
        "Sukhai"
    ],
    "wof:name":"Sukhai",
    "wof:placetype":"locality",
    "wof:population":492
},
  "geometry": {"coordinates":[80.975528,20.169494],"type":"Point"}
}