{
  "type": "Feature",
  "properties": {
    "gn:admin1_code":"25.0",
    "gn:admin2_code":"631.0",
    "gn:asciiname":"Okkandoddi",
    "gn:country_code":"IN",
    "gn:dem":936,
    "gn:feature_class":"P",
    "gn:feature_code":"PPL",
    "gn:name":"Okkandoddi",
    "gn:population":0,
    "gn:timezone":"Asia/Kolkata",
    "iso:country":"IN",
    "wof:name":"Okkandoddi",
    "wof:placetype":"neighbourhood"
},
  "geometry": {"coordinates":[77.66654,12.52763],"type":"Point"}
}