{
  "type": "Feature",
  "properties": {
    "iso:country":"IN",
    "ks:ks_name":"Sanawara Khurd",
    "ks:ks_pop":625,
    "ks:ks_type":"VILLAGE",
    "name:eng_x_preferred":[
        "Sanawara Khurd"
    ],
    "wof:name":"Sanawara Khurd",
    "wof:placetype":"locality",
    "wof:population":625
},
  "geometry": {"coordinates":[71.67975800000001,25.075422],"type":"Point"}
}