{
  "type": "Feature",
  "properties": {
    "gn:admin1_code":"35.0",
    "gn:admin2_code":"457.0",
    "gn:asciiname":"Khara",
    "gn:country_code":"IN",
    "gn:dem":565,
    "gn:feature_class":"P",
    "gn:feature_code":"PPL",
    "gn:name":"Kh\u0101r\u0101",
    "gn:population":0,
    "gn:timezone":"Asia/Kolkata",
    "iso:country":"IN",
    "ks:ks_name":"Kharra",
    "ks:ks_pop":576,
    "ks:ks_type":"VILLAGE",
    "name:ceb_x_preferred":[
        "Khara"
    ],
    "name:deu_x_preferred":[
        "Khara"
    ],
    "name:eng_x_preferred":[
        "Kharra"
    ],
    "name:eng_x_variant":[
        "Khara"
    ],
    "name:new_x_preferred":[
        "\u0916\u0930\u093e"
    ],
    "name:swe_x_preferred":[
        "Khara"
    ],
    "wof:name":"Kharra",
    "wof:placetype":"locality",
    "wof:population":576
},
  "geometry": {"coordinates":[80.30490899999999,22.262504],"type":"Point"}
}