{
  "type": "Feature",
  "properties": {
    "iso:country":"IN",
    "ks:ks_alt_nam":"Bih\u0101ripur",
    "ks:ks_name":"Biharipur",
    "ks:ks_type":"VILLAGE",
    "ks:ks_uagg_main":0,
    "name:eng_x_preferred":[
        "Biharipur"
    ],
    "name:eng_x_variant":[
        "Bih\u0101ripur"
    ],
    "wof:name":"Biharipur",
    "wof:placetype":"neighbourhood"
},
  "geometry": {"coordinates":[77.263262,28.713723],"type":"Point"}
}