{
  "type": "Feature",
  "properties": {
    "gn:admin1_code":"34.0",
    "gn:admin2_code":"235.0",
    "gn:asciiname":"Bharaundhi",
    "gn:country_code":"IN",
    "gn:dem":151,
    "gn:feature_class":"P",
    "gn:feature_code":"PPL",
    "gn:name":"Bharaundh\u012b",
    "gn:population":0,
    "gn:timezone":"Asia/Kolkata",
    "iso:country":"IN",
    "ks:ks_alt_nam":"Bharaundh\u012b",
    "ks:ks_name":"Bharaundhi",
    "ks:ks_pop":31,
    "ks:ks_type":"VILLAGE",
    "name:eng_x_preferred":[
        "Bharaundhi"
    ],
    "name:eng_x_variant":[
        "Bharaundh\u012b"
    ],
    "wof:name":"Bharaundhi",
    "wof:placetype":"locality",
    "wof:population":31
},
  "geometry": {"coordinates":[84.07844,24.593083],"type":"Point"}
}