{
  "type": "Feature",
  "properties": {
    "iso:country":"IN",
    "ks:ks_name":"Haletota",
    "ks:ks_pop":81,
    "ks:ks_type":"HABITATION",
    "name:eng_x_preferred":[
        "Haletota"
    ],
    "wof:name":"Haletota",
    "wof:placetype":"locality",
    "wof:population":81
},
  "geometry": {"coordinates":[74.506778,14.330598],"type":"Point"}
}