{
  "type": "Feature",
  "properties": {
    "gn:admin1_code":"12.0",
    "gn:admin2_code":"17.0",
    "gn:asciiname":"Tharmola",
    "gn:country_code":"IN",
    "gn:dem":2155,
    "gn:feature_class":"P",
    "gn:feature_code":"PPL",
    "gn:name":"Tharmola",
    "gn:population":0,
    "gn:timezone":"Asia/Kolkata",
    "iso:country":"IN",
    "wof:name":"Tharmola",
    "wof:placetype":"locality"
},
  "geometry": {"coordinates":[75.27688000000001,33.27276],"type":"Point"}
}