{
  "type": "Feature",
  "properties": {
    "gn:admin1_code":"36.0",
    "gn:admin2_code":"182.0",
    "gn:asciiname":"Dani Dih",
    "gn:country_code":"IN",
    "gn:dem":127,
    "gn:feature_class":"P",
    "gn:feature_code":"PPL",
    "gn:name":"D\u0101ni D\u012bh",
    "gn:population":0,
    "gn:timezone":"Asia/Kolkata",
    "iso:country":"IN",
    "wof:name":"Dani Dih",
    "wof:placetype":"locality"
},
  "geometry": {"coordinates":[82.17335,27.65634],"type":"Point"}
}