{
  "type": "Feature",
  "properties": {
    "iso:country":"IN",
    "ks:ks_alt_nam":"Bur\u0101ri",
    "ks:ks_name":"Burari",
    "ks:ks_type":"VILLAGE",
    "ks:ks_uagg_main":0,
    "name:eng_x_preferred":[
        "Burari"
    ],
    "name:eng_x_variant":[
        "Bur\u0101ri"
    ],
    "wof:name":"Burari",
    "wof:placetype":"neighbourhood"
},
  "geometry": {"coordinates":[77.199409,28.755699],"type":"Point"}
}