{
  "type": "Feature",
  "properties": {
    "gn:admin1_code":"16",
    "gn:admin2_code":"500.0",
    "gn:asciiname":"Pimpalgaon Devi",
    "gn:country_code":"IN",
    "gn:dem":322,
    "gn:feature_class":"P",
    "gn:feature_code":"PPL",
    "gn:name":"Pimpalgaon Devi",
    "gn:population":0,
    "gn:timezone":"Asia/Kolkata",
    "iso:country":"IN",
    "wof:name":"Pimpalgaon Devi",
    "wof:placetype":"locality"
},
  "geometry": {"coordinates":[76.02426,20.76682000000001],"type":"Point"}
}