{
  "type": "Feature",
  "properties": {
    "iso:country":"IN",
    "ks:ks_name":"Bhandartoli",
    "ks:ks_pop":96,
    "ks:ks_type":"HABITATION",
    "name:eng_x_preferred":[
        "Bhandartoli"
    ],
    "wof:name":"Bhandartoli",
    "wof:placetype":"locality",
    "wof:population":96
},
  "geometry": {"coordinates":[84.240351,22.509096],"type":"Point"}
}