{
  "type": "Feature",
  "properties": {
    "gn:admin1_code":"39.0",
    "gn:admin2_code":"057",
    "gn:asciiname":"Hanuman Chatti",
    "gn:country_code":"IN",
    "gn:dem":2575,
    "gn:feature_class":"P",
    "gn:feature_code":"PPL",
    "gn:name":"Hanum\u0101n Chatti",
    "gn:population":0,
    "gn:timezone":"Asia/Kolkata",
    "iso:country":"IN",
    "wof:name":"Hanuman Chatti",
    "wof:placetype":"locality"
},
  "geometry": {"coordinates":[79.51576999999997,30.69601],"type":"Point"}
}