{
  "type": "Feature",
  "properties": {
    "gn:admin1_code":"16",
    "gn:admin2_code":"510.0",
    "gn:asciiname":"Kund",
    "gn:country_code":"IN",
    "gn:dem":383,
    "gn:feature_class":"P",
    "gn:feature_code":"PPL",
    "gn:name":"Kund",
    "gn:population":0,
    "gn:timezone":"Asia/Kolkata",
    "iso:country":"IN",
    "name:fas_x_preferred":[
        "\u06a9\u0646\u062f"
    ],
    "name:urd_x_preferred":[
        "\u06a9\u0646\u0688"
    ],
    "wof:name":"Kund",
    "wof:placetype":"locality"
},
  "geometry": {"coordinates":[77.65701999999997,20.36511],"type":"Point"}
}