{
  "type": "Feature",
  "properties": {
    "iso:country":"IN",
    "ks:ks_name":"Iyava",
    "ks:ks_pop":646,
    "ks:ks_type":"HABITATION",
    "name:eng_x_preferred":[
        "Iyava"
    ],
    "wof:name":"Iyava",
    "wof:placetype":"locality",
    "wof:population":646
},
  "geometry": {"coordinates":[72.73518900000001,22.779332],"type":"Point"}
}