{
  "type": "Feature",
  "properties": {
    "iso:country":"IN",
    "ks:ks_name":"Eturu Madigawada",
    "ks:ks_pop":180,
    "ks:ks_type":"HABITATION",
    "ks:ks_uagg_main":0,
    "name:eng_x_preferred":[
        "Eturu Madigawada"
    ],
    "wof:name":"Eturu Madigawada",
    "wof:placetype":"neighbourhood",
    "wof:population":180
},
  "geometry": {"coordinates":[78.690228,14.634741],"type":"Point"}
}