{
  "type": "Feature",
  "properties": {
    "iso:country":"IN",
    "ks:ks_name":"Bhandarber",
    "ks:ks_pop":384,
    "ks:ks_type":"VILLAGE",
    "ks:ks_uagg_main":0,
    "name:eng_x_preferred":[
        "Bhandarber"
    ],
    "wof:name":"Bhandarber",
    "wof:placetype":"neighbourhood",
    "wof:population":384
},
  "geometry": {"coordinates":[87.247545,22.688775],"type":"Point"}
}