{
  "type": "Feature",
  "properties": {
    "gn:admin1_code":"21.0",
    "gn:admin2_code":"396.0",
    "gn:asciiname":"Toram",
    "gn:country_code":"IN",
    "gn:dem":548,
    "gn:feature_class":"P",
    "gn:feature_code":"PPL",
    "gn:name":"Tor\u0101m",
    "gn:population":0,
    "gn:timezone":"Asia/Kolkata",
    "iso:country":"IN",
    "ks:ks_name":"Taram",
    "ks:ks_pop":186,
    "ks:ks_type":"VILLAGE",
    "name:eng_x_preferred":[
        "Taram"
    ],
    "name:eng_x_variant":[
        "Toram"
    ],
    "wof:name":"Taram",
    "wof:placetype":"locality",
    "wof:population":186
},
  "geometry": {"coordinates":[83.47490999999999,19.012469],"type":"Point"}
}