{
  "type": "Feature",
  "properties": {
    "gn:admin1_code":"19.0",
    "gn:admin2_code":"573.0",
    "gn:asciiname":"Garudapura",
    "gn:country_code":"IN",
    "gn:dem":869,
    "gn:feature_class":"P",
    "gn:feature_code":"PPL",
    "gn:name":"Garudapura",
    "gn:population":0,
    "gn:timezone":"Asia/Kolkata",
    "iso:country":"IN",
    "wof:name":"Garudapura",
    "wof:placetype":"locality"
},
  "geometry": {"coordinates":[76.64775999999998,12.88871],"type":"Point"}
}