{
  "type": "Feature",
  "properties": {
    "iso:country":"IN",
    "ks:ks_name":"Odichakunnu",
    "ks:ks_pop":995,
    "ks:ks_type":"HABITATION",
    "name:eng_x_preferred":[
        "Odichakunnu"
    ],
    "wof:name":"Odichakunnu",
    "wof:placetype":"locality",
    "wof:population":995
},
  "geometry": {"coordinates":[75.727334,12.040274],"type":"Point"}
}