{
  "type": "Feature",
  "properties": {
    "iso:country":"IN",
    "ks:ks_name":"Jatkal Kota",
    "ks:ks_pop":96,
    "ks:ks_type":"HABITATION",
    "name:eng_x_preferred":[
        "Jatkal Kota"
    ],
    "wof:name":"Jatkal Kota",
    "wof:placetype":"locality",
    "wof:population":96
},
  "geometry": {"coordinates":[74.520698,14.163141],"type":"Point"}
}