{
  "type": "Feature",
  "properties": {
    "gn:admin1_code":"10.0",
    "gn:admin2_code":"86.0",
    "gn:asciiname":"Meoka",
    "gn:country_code":"IN",
    "gn:dem":227,
    "gn:feature_class":"P",
    "gn:feature_code":"PPL",
    "gn:name":"Meoka",
    "gn:population":0,
    "gn:timezone":"Asia/Kolkata",
    "iso:country":"IN",
    "wof:name":"Meoka",
    "wof:placetype":"locality"
},
  "geometry": {"coordinates":[76.91674999999999,28.409],"type":"Point"}
}