{
  "type": "Feature",
  "properties": {
    "gn:admin1_code":"36",
    "gn:admin2_code":"152.0",
    "gn:asciiname":"Champapur",
    "gn:country_code":"IN",
    "gn:dem":154,
    "gn:feature_class":"P",
    "gn:feature_code":"PPL",
    "gn:name":"Champ\u0101pur",
    "gn:population":0,
    "gn:timezone":"Asia/Kolkata",
    "iso:country":"IN",
    "name:ori_x_preferred":[
        "\u0b1a\u0b2e\u0b4d\u0b2a\u0b3e\u0b2a\u0b41\u0b30"
    ],
    "wof:name":"Champapur",
    "wof:placetype":"locality"
},
  "geometry": {"coordinates":[79.93141999999997,27.74773],"type":"Point"}
}