{
  "type": "Feature",
  "properties": {
    "iso:country":"IN",
    "ks:ks_name":"Padamjhori",
    "ks:ks_pop":429,
    "ks:ks_type":"HABITATION",
    "name:eng_x_preferred":[
        "Padamjhori"
    ],
    "wof:name":"Padamjhori",
    "wof:placetype":"locality",
    "wof:population":429
},
  "geometry": {"coordinates":[82.295203,19.849656],"type":"Point"}
}