{
  "type": "Feature",
  "properties": {
    "iso:country":"IN",
    "ks:ks_name":"Nawapara",
    "ks:ks_pop":150,
    "ks:ks_type":"HABITATION",
    "name:eng_x_preferred":[
        "Nawapara"
    ],
    "wof:name":"Nawapara",
    "wof:placetype":"locality",
    "wof:population":150
},
  "geometry": {"coordinates":[82.683442,23.419323],"type":"Point"}
}