{
  "type": "Feature",
  "properties": {
    "iso:country":"IN",
    "ks:ks_name":"Hinauti Chandail",
    "ks:ks_pop":4,
    "ks:ks_type":"VILLAGE",
    "ks:ks_uagg_main":0,
    "name:eng_x_preferred":[
        "Hinauti Chandail"
    ],
    "wof:name":"Hinauti Chandail",
    "wof:placetype":"neighbourhood",
    "wof:population":4
},
  "geometry": {"coordinates":[81.731223,25.079821],"type":"Point"}
}