{
  "type": "Feature",
  "properties": {
    "iso:country":"IN",
    "ks:ks_name":"Hadikerebettu",
    "ks:ks_pop":237,
    "ks:ks_type":"HABITATION",
    "ks:ks_uagg_main":0,
    "name:eng_x_preferred":[
        "Hadikerebettu"
    ],
    "wof:name":"Hadikerebettu",
    "wof:placetype":"neighbourhood",
    "wof:population":237
},
  "geometry": {"coordinates":[74.70750200000001,13.525139],"type":"Point"}
}