{
  "type": "Feature",
  "properties": {
    "iso:country":"IN",
    "ks:ks_name":"Khekdi",
    "ks:ks_type":"VILLAGE",
    "name:eng_x_preferred":[
        "Khekdi"
    ],
    "wof:name":"Khekdi",
    "wof:placetype":"locality"
},
  "geometry": {"coordinates":[78.812044,19.894337],"type":"Point"}
}