{
  "type": "Feature",
  "properties": {
    "gn:admin1_code":"12.0",
    "gn:admin2_code":"021",
    "gn:asciiname":"Karli",
    "gn:country_code":"IN",
    "gn:dem":384,
    "gn:feature_class":"P",
    "gn:feature_code":"PPL",
    "gn:name":"Karli",
    "gn:population":0,
    "gn:timezone":"Asia/Kolkata",
    "iso:country":"IN",
    "name:deu_x_preferred":[
        "Karli"
    ],
    "name:isl_x_preferred":[
        "Karli"
    ],
    "name:pol_x_preferred":[
        "Karli"
    ],
    "name:slv_x_preferred":[
        "Karli"
    ],
    "wof:name":"Karli",
    "wof:placetype":"locality"
},
  "geometry": {"coordinates":[74.89624000000001,32.82163],"type":"Point"}
}