{
  "type": "Feature",
  "properties": {
    "iso:country":"IN",
    "ks:ks_name":"Parande Barakardewasti",
    "ks:ks_pop":516,
    "ks:ks_type":"HABITATION",
    "name:eng_x_preferred":[
        "Parande Barakardewasti"
    ],
    "wof:name":"Parande Barakardewasti",
    "wof:placetype":"locality",
    "wof:population":516
},
  "geometry": {"coordinates":[74.946,18.036],"type":"Point"}
}