{
  "type": "Feature",
  "properties": {
    "iso:country":"IN",
    "ks:ks_name":"Paragi Purwa",
    "ks:ks_pop":124,
    "ks:ks_type":"HABITATION",
    "ks:ks_uagg_main":0,
    "name:eng_x_preferred":[
        "Paragi Purwa"
    ],
    "wof:name":"Paragi Purwa",
    "wof:placetype":"neighbourhood",
    "wof:population":124
},
  "geometry": {"coordinates":[81.769947,27.321507],"type":"Point"}
}