{
  "type": "Feature",
  "properties": {
    "iso:country":"IN",
    "ks:ks_name":"Jeori",
    "ks:ks_type":"VILLAGE",
    "name:eng_x_preferred":[
        "Jeori"
    ],
    "wof:name":"Jeori",
    "wof:placetype":"locality"
},
  "geometry": {"coordinates":[82.821923,25.169234],"type":"Point"}
}