{
  "type": "Feature",
  "properties": {
    "iso:country":"IN",
    "ks:ks_name":"Manjhaghat",
    "ks:ks_pop":57,
    "ks:ks_type":"HABITATION",
    "name:eng_x_preferred":[
        "Manjhaghat"
    ],
    "wof:name":"Manjhaghat",
    "wof:placetype":"locality",
    "wof:population":57
},
  "geometry": {"coordinates":[84.252567,22.682431],"type":"Point"}
}