{
  "type": "Feature",
  "properties": {
    "iso:country":"IN",
    "ks:ks_name":"Pattharwadi",
    "ks:ks_pop":384,
    "ks:ks_type":"HABITATION",
    "name:eng_x_preferred":[
        "Pattharwadi"
    ],
    "wof:name":"Pattharwadi",
    "wof:placetype":"locality",
    "wof:population":384
},
  "geometry": {"coordinates":[73.43951199999999,16.365752],"type":"Point"}
}