{
  "type": "Feature",
  "properties": {
    "gn:admin1_code":"24.0",
    "gn:admin2_code":"131",
    "gn:asciiname":"Chiklar",
    "gn:country_code":"IN",
    "gn:dem":415,
    "gn:feature_class":"P",
    "gn:feature_code":"PPL",
    "gn:name":"Ch\u012bkl\u0101r",
    "gn:population":0,
    "gn:timezone":"Asia/Kolkata",
    "iso:country":"IN",
    "name:und_x_variant":[
        "Chikklar",
        "Ch\u012bkl\u0101r"
    ],
    "wof:name":"Chiklar",
    "wof:placetype":"locality"
},
  "geometry": {"coordinates":[74.6153,24.0534],"type":"Point"}
}