{
  "type": "Feature",
  "properties": {
    "iso:country":"IN",
    "ks:ks_name":"Varragumpu",
    "ks:ks_pop":114,
    "ks:ks_type":"HABITATION",
    "name:eng_x_preferred":[
        "Varragumpu"
    ],
    "wof:name":"Varragumpu",
    "wof:placetype":"locality",
    "wof:population":114
},
  "geometry": {"coordinates":[80.94461,17.335861],"type":"Point"}
}