{
  "type": "Feature",
  "properties": {
    "iso:country":"IN",
    "ks:ks_alt_nam":"Hanuman faliya",
    "ks:ks_name":"Hanuman Faliya",
    "ks:ks_pop":67,
    "ks:ks_type":"HABITATION",
    "name:eng_x_preferred":[
        "Hanuman Faliya"
    ],
    "wof:name":"Hanuman Faliya",
    "wof:placetype":"locality",
    "wof:population":67
},
  "geometry": {"coordinates":[73.146056,20.483694],"type":"Point"}
}