{
  "type": "Feature",
  "properties": {
    "iso:country":"IN",
    "ks:ks_name":"Abbihittal",
    "ks:ks_pop":95,
    "ks:ks_type":"HABITATION",
    "name:eng_x_preferred":[
        "Abbihittal"
    ],
    "wof:name":"Abbihittal",
    "wof:placetype":"locality",
    "wof:population":95
},
  "geometry": {"coordinates":[74.587157,13.945983],"type":"Point"}
}