{
  "type": "Feature",
  "properties": {
    "gn:admin1_code":"34.0",
    "gn:admin2_code":"203.0",
    "gn:asciiname":"Majhariya",
    "gn:country_code":"IN",
    "gn:dem":99,
    "gn:feature_class":"P",
    "gn:feature_code":"PPL",
    "gn:name":"Majhariy\u0101",
    "gn:population":0,
    "gn:timezone":"Asia/Kolkata",
    "iso:country":"IN",
    "ks:ks_name":"Majharia",
    "ks:ks_pop":1659,
    "ks:ks_type":"VILLAGE",
    "name:eng_x_preferred":[
        "Majharia"
    ],
    "name:eng_x_variant":[
        "Majhariya"
    ],
    "name:fra_x_preferred":[
        "Majhariya"
    ],
    "name:mai_x_preferred":[
        "\u092e\u091d\u0930\u093f\u092f\u093e"
    ],
    "name:msa_x_preferred":[
        "Majhariya"
    ],
    "name:nep_x_preferred":[
        "\u092e\u091d\u0930\u093f\u092f\u093e"
    ],
    "name:new_x_preferred":[
        "\u092e\u091d\u0930\u093f\u092f\u093e"
    ],
    "name:pol_x_preferred":[
        "Majhariya"
    ],
    "wof:name":"Majharia",
    "wof:placetype":"locality",
    "wof:population":1659
},
  "geometry": {"coordinates":[84.444661,27.204483],"type":"Point"}
}