{
  "type": "Feature",
  "properties": {
    "gn:admin1_code":"12.0",
    "gn:asciiname":"Gratnar",
    "gn:country_code":"IN",
    "gn:dem":2771,
    "gn:feature_class":"P",
    "gn:feature_code":"PPL",
    "gn:name":"Gratn\u0101r",
    "gn:population":0,
    "gn:timezone":"Asia/Kolkata",
    "iso:country":"IN",
    "wof:name":"Gratnar",
    "wof:placetype":"locality"
},
  "geometry": {"coordinates":[75.06389,34.55278],"type":"Point"}
}