{
  "type": "Feature",
  "properties": {
    "iso:country":"IN",
    "ks:ks_alt_nam":"Bhim para 1",
    "ks:ks_name":"Bhim Para 1",
    "ks:ks_pop":329,
    "ks:ks_type":"HABITATION",
    "ks:ks_uagg_main":0,
    "name:eng_x_preferred":[
        "Bhim Para 1"
    ],
    "wof:name":"Bhim Para 1",
    "wof:placetype":"neighbourhood",
    "wof:population":329
},
  "geometry": {"coordinates":[94.701154,27.16535],"type":"Point"}
}