{
  "type": "Feature",
  "properties": {
    "iso:country":"IN",
    "ks:ks_name":"Udayanagara",
    "ks:ks_pop":123,
    "ks:ks_type":"HABITATION",
    "name:eng_x_preferred":[
        "Udayanagara"
    ],
    "wof:name":"Udayanagara",
    "wof:placetype":"locality",
    "wof:population":123
},
  "geometry": {"coordinates":[75.832928,13.882147],"type":"Point"}
}