{
  "type": "Feature",
  "properties": {
    "iso:country":"IN",
    "ks:ks_name":"Salpara",
    "ks:ks_pop":2216,
    "ks:ks_type":"VILLAGE",
    "ks:ks_uagg_main":0,
    "name:eng_x_preferred":[
        "Salpara"
    ],
    "wof:name":"Salpara",
    "wof:placetype":"neighbourhood",
    "wof:population":2216
},
  "geometry": {"coordinates":[92.605783,26.451084],"type":"Point"}
}