{
  "type": "Feature",
  "properties": {
    "iso:country":"IN",
    "ks:ks_name":"Kondwadi",
    "ks:ks_pop":290,
    "ks:ks_type":"HABITATION",
    "name:eng_x_preferred":[
        "Kondwadi"
    ],
    "wof:name":"Kondwadi",
    "wof:placetype":"locality",
    "wof:population":290
},
  "geometry": {"coordinates":[73.264867,17.641311],"type":"Point"}
}