{
  "type": "Feature",
  "properties": {
    "iso:country":"IN",
    "ks:ks_name":"Bhatitola",
    "ks:ks_pop":121,
    "ks:ks_type":"HABITATION",
    "name:eng_x_preferred":[
        "Bhatitola"
    ],
    "wof:name":"Bhatitola",
    "wof:placetype":"locality",
    "wof:population":121
},
  "geometry": {"coordinates":[84.890191,22.117642],"type":"Point"}
}