{
  "type": "Feature",
  "properties": {
    "gn:admin1_code":"10.0",
    "gn:admin2_code":"85.0",
    "gn:asciiname":"Gujarwas",
    "gn:country_code":"IN",
    "gn:dem":240,
    "gn:feature_class":"P",
    "gn:feature_code":"PPL",
    "gn:name":"Gujarw\u0101s",
    "gn:population":0,
    "gn:timezone":"Asia/Kolkata",
    "iso:country":"IN",
    "name:tam_x_preferred":[
        "\u0b95\u0bc1\u0baf\u0bb0\u0bcd\u0bb5\u0bbe\u0b9a\u0bc1"
    ],
    "wof:name":"Gujarwas",
    "wof:placetype":"locality"
},
  "geometry": {"coordinates":[76.38252,28.38883],"type":"Point"}
}