{
  "type": "Feature",
  "properties": {
    "iso:country":"IN",
    "ks:ks_name":"Tunga Dhua",
    "ks:ks_pop":94,
    "ks:ks_type":"VILLAGE",
    "name:eng_x_preferred":[
        "Tunga Dhua"
    ],
    "wof:name":"Tunga Dhua",
    "wof:placetype":"locality",
    "wof:population":94
},
  "geometry": {"coordinates":[87.06076400000001,22.074742],"type":"Point"}
}