{
  "type": "Feature",
  "properties": {
    "iso:country":"IN",
    "ks:ks_name":"Gollapallevandlapalle",
    "ks:ks_pop":283,
    "ks:ks_type":"HABITATION",
    "name:eng_x_preferred":[
        "Gollapallevandlapalle"
    ],
    "wof:name":"Gollapallevandlapalle",
    "wof:placetype":"locality",
    "wof:population":283
},
  "geometry": {"coordinates":[78.44108,13.840642],"type":"Point"}
}