{
  "type": "Feature",
  "properties": {
    "gn:admin1_code":"36",
    "gn:admin2_code":"174.0",
    "gn:asciiname":"Dorma",
    "gn:country_code":"IN",
    "gn:dem":109,
    "gn:feature_class":"P",
    "gn:feature_code":"PPL",
    "gn:name":"Dorma",
    "gn:population":0,
    "gn:timezone":"Asia/Kolkata",
    "iso:country":"IN",
    "name:deu_x_preferred":[
        "Dorma"
    ],
    "name:rus_x_preferred":[
        "Dormakaba"
    ],
    "name:swe_x_preferred":[
        "Dorma"
    ],
    "name:ukr_x_preferred":[
        "Dorma"
    ],
    "wof:name":"Dorma",
    "wof:placetype":"locality"
},
  "geometry": {"coordinates":[81.29489000000002,25.6796],"type":"Point"}
}