{
  "type": "Feature",
  "properties": {
    "iso:country":"IN",
    "ks:ks_name":"Uttar Para Western Part",
    "ks:ks_pop":1038,
    "ks:ks_type":"HABITATION",
    "name:eng_x_preferred":[
        "Uttar Para Western Part"
    ],
    "wof:name":"Uttar Para Western Part",
    "wof:placetype":"locality",
    "wof:population":1038
},
  "geometry": {"coordinates":[88.127948,21.826759],"type":"Point"}
}