{
  "type": "Feature",
  "properties": {
    "iso:country":"IN",
    "ks:ks_name":"Thevarani",
    "ks:ks_pop":918,
    "ks:ks_type":"HABITATION",
    "name:eng_x_preferred":[
        "Thevarani"
    ],
    "wof:name":"Thevarani",
    "wof:placetype":"locality",
    "wof:population":918
},
  "geometry": {"coordinates":[76.71056299999999,9.812464],"type":"Point"}
}