{
  "type": "Feature",
  "properties": {
    "gn:admin1_code":"19.0",
    "gn:admin2_code":"578.0",
    "gn:asciiname":"Chikkayalur",
    "gn:country_code":"IN",
    "gn:dem":591,
    "gn:feature_class":"P",
    "gn:feature_code":"PPL",
    "gn:name":"Chikkayalur",
    "gn:population":0,
    "gn:timezone":"Asia/Kolkata",
    "iso:country":"IN",
    "ks:ks_name":"Chikkallur",
    "ks:ks_pop":1700,
    "ks:ks_type":"HABITATION",
    "name:eng_x_preferred":[
        "Chikkallur"
    ],
    "name:eng_x_variant":[
        "Chikkayalur"
    ],
    "wof:name":"Chikkallur",
    "wof:placetype":"locality",
    "wof:population":1700
},
  "geometry": {"coordinates":[77.28866600000001,12.250505],"type":"Point"}
}