{
  "type": "Feature",
  "properties": {
    "iso:country":"IN",
    "ks:ks_name":"Kudumguda",
    "ks:ks_pop":262,
    "ks:ks_type":"VILLAGE",
    "name:eng_x_preferred":[
        "Kudumguda"
    ],
    "wof:name":"Kudumguda",
    "wof:placetype":"locality",
    "wof:population":262
},
  "geometry": {"coordinates":[83.836866,19.688846],"type":"Point"}
}