{
  "type": "Feature",
  "properties": {
    "iso:country":"IN",
    "ks:ks_alt_nam":"TULSIBARI",
    "ks:ks_name":"Tulsibari",
    "ks:ks_pop":1217,
    "ks:ks_type":"HABITATION",
    "name:eng_x_preferred":[
        "Tulsibari"
    ],
    "wof:name":"Tulsibari",
    "wof:placetype":"locality",
    "wof:population":1217
},
  "geometry": {"coordinates":[89.763485,26.513135],"type":"Point"}
}