{
  "type": "Feature",
  "properties": {
    "gn:admin1_code":"16",
    "gn:admin2_code":"503.0",
    "gn:asciiname":"Kothara",
    "gn:country_code":"IN",
    "gn:dem":406,
    "gn:feature_class":"P",
    "gn:feature_code":"PPL",
    "gn:name":"Koth\u0101ra",
    "gn:population":0,
    "gn:timezone":"Asia/Kolkata",
    "iso:country":"IN",
    "wof:name":"Kothara",
    "wof:placetype":"locality"
},
  "geometry": {"coordinates":[77.54489000000002,21.32028],"type":"Point"}
}