{
  "type": "Feature",
  "properties": {
    "iso:country":"IN",
    "ks:ks_name":"Khariya Khera",
    "ks:ks_pop":487,
    "ks:ks_type":"VILLAGE",
    "name:eng_x_preferred":[
        "Khariya Khera"
    ],
    "wof:name":"Khariya Khera",
    "wof:placetype":"locality",
    "wof:population":487
},
  "geometry": {"coordinates":[74.26165399999999,26.056406],"type":"Point"}
}