{
  "type": "Feature",
  "properties": {
    "gn:admin1_code":"37",
    "gn:admin2_code":"401.0",
    "gn:asciiname":"Matringa",
    "gn:country_code":"IN",
    "gn:dem":691,
    "gn:feature_class":"P",
    "gn:feature_code":"PPL",
    "gn:name":"Matringa",
    "gn:population":0,
    "gn:timezone":"Asia/Kolkata",
    "iso:country":"IN",
    "ks:ks_name":"Matringa",
    "ks:ks_pop":316,
    "ks:ks_type":"VILLAGE",
    "name:eng_x_preferred":[
        "Matringa"
    ],
    "wof:name":"Matringa",
    "wof:placetype":"locality",
    "wof:population":316
},
  "geometry": {"coordinates":[83.042918,22.668549],"type":"Point"}
}