{
  "type": "Feature",
  "properties": {
    "gn:admin1_code":"21.0",
    "gn:admin2_code":"370",
    "gn:asciiname":"Khutpali",
    "gn:country_code":"IN",
    "gn:dem":194,
    "gn:feature_class":"P",
    "gn:feature_code":"PPL",
    "gn:name":"Khutp\u0101li",
    "gn:population":0,
    "gn:timezone":"Asia/Kolkata",
    "iso:country":"IN",
    "wof:name":"Khutpali",
    "wof:placetype":"locality"
},
  "geometry": {"coordinates":[83.21666999999999,20.95],"type":"Point"}
}