{
  "type": "Feature",
  "properties": {
    "iso:country":"IN",
    "ks:ks_name":"Berai",
    "ks:ks_pop":464,
    "ks:ks_type":"VILLAGE",
    "name:eng_x_preferred":[
        "Berai"
    ],
    "wof:name":"Berai",
    "wof:placetype":"locality",
    "wof:population":464
},
  "geometry": {"coordinates":[76.754256,26.113642],"type":"Point"}
}