{
  "type": "Feature",
  "properties": {
    "iso:country":"IN",
    "ks:ks_name":"Madhu Pure",
    "ks:ks_pop":117,
    "ks:ks_type":"HABITATION",
    "ks:ks_uagg_main":0,
    "name:eng_x_preferred":[
        "Madhu Pure"
    ],
    "wof:name":"Madhu Pure",
    "wof:placetype":"neighbourhood",
    "wof:population":117
},
  "geometry": {"coordinates":[79.781391,27.331084],"type":"Point"}
}