{
  "type": "Feature",
  "properties": {
    "iso:country":"IN",
    "ks:ks_name":"Kanya",
    "ks:ks_pop":66,
    "ks:ks_type":"VILLAGE",
    "name:eng_x_preferred":[
        "Kanya"
    ],
    "wof:name":"Kanya",
    "wof:placetype":"locality",
    "wof:population":66
},
  "geometry": {"coordinates":[79.893896,29.572372],"type":"Point"}
}