{
  "type": "Feature",
  "properties": {
    "iso:country":"IN",
    "ks:ks_name":"Nepali Basti",
    "ks:ks_pop":710,
    "ks:ks_type":"HABITATION",
    "ks:ks_uagg_main":0,
    "name:eng_x_preferred":[
        "Nepali Basti"
    ],
    "wof:name":"Nepali Basti",
    "wof:placetype":"neighbourhood",
    "wof:population":710
},
  "geometry": {"coordinates":[89.35661899999999,26.470774],"type":"Point"}
}