{
  "type": "Feature",
  "properties": {
    "iso:country":"IN",
    "ks:ks_name":"Thimmasandra",
    "ks:ks_pop":555,
    "ks:ks_type":"VILLAGE",
    "ks:ks_uagg_main":0,
    "name:eng_x_preferred":[
        "Thimmasandra"
    ],
    "wof:name":"Thimmasandra",
    "wof:placetype":"neighbourhood",
    "wof:population":555
},
  "geometry": {"coordinates":[77.76958999999999,13.12388],"type":"Point"}
}