{
  "type": "Feature",
  "properties": {
    "iso:country":"IN",
    "ks:ks_name":"Dawraigabnai",
    "ks:ks_pop":511,
    "ks:ks_type":"HABITATION",
    "name:eng_x_preferred":[
        "Dawraigabnai"
    ],
    "wof:name":"Dawraigabnai",
    "wof:placetype":"locality",
    "wof:population":511
},
  "geometry": {"coordinates":[90.411473,26.757023],"type":"Point"}
}