{
  "type": "Feature",
  "properties": {
    "gn:admin1_code":"16",
    "gn:admin2_code":"503.0",
    "gn:asciiname":"Saoli",
    "gn:country_code":"IN",
    "gn:dem":397,
    "gn:feature_class":"P",
    "gn:feature_code":"PPL",
    "gn:name":"S\u0101oli",
    "gn:population":0,
    "gn:timezone":"Asia/Kolkata",
    "iso:country":"IN",
    "name:ceb_x_preferred":[
        "S\u0101oli"
    ],
    "name:guj_x_preferred":[
        "\u0ab8\u0abe\u0ab5\u0ab2\u0ac0"
    ],
    "name:swe_x_preferred":[
        "S\u0101oli"
    ],
    "name:urd_x_preferred":[
        "\u0633\u0627\u0624\u0644\u06cc"
    ],
    "wof:name":"Saoli",
    "wof:placetype":"neighbourhood"
},
  "geometry": {"coordinates":[77.48054999999999,21.30177],"type":"Point"}
}