{
  "type": "Feature",
  "properties": {
    "iso:country":"IN",
    "ks:ks_name":"4 SKM-A",
    "ks:ks_pop":125,
    "ks:ks_type":"VILLAGE",
    "name:eng_x_preferred":[
        "4 SKM-A"
    ],
    "wof:name":"4 SKM-A",
    "wof:placetype":"locality",
    "wof:population":125
},
  "geometry": {"coordinates":[72.903229,28.931568],"type":"Point"}
}