{
  "type": "Feature",
  "properties": {
    "gn:admin1_code":"23",
    "gn:admin2_code":"37.0",
    "gn:asciiname":"Nangal Kalan",
    "gn:country_code":"IN",
    "gn:dem":220,
    "gn:feature_class":"P",
    "gn:feature_code":"PPL",
    "gn:name":"Nangal Kal\u0101n",
    "gn:population":0,
    "gn:timezone":"Asia/Kolkata",
    "iso:country":"IN",
    "name:pan_x_preferred":[
        "\u0a28\u0a70\u0a17\u0a32 \u0a15\u0a32\u0a3e\u0a02"
    ],
    "wof:name":"Nangal Kalan",
    "wof:placetype":"locality"
},
  "geometry": {"coordinates":[75.361,31.06939],"type":"Point"}
}