{
  "type": "Feature",
  "properties": {
    "gn:admin1_code":"36",
    "gn:admin2_code":"154.0",
    "gn:asciiname":"Cheni",
    "gn:country_code":"IN",
    "gn:dem":121,
    "gn:feature_class":"P",
    "gn:feature_code":"PPL",
    "gn:name":"Cheni",
    "gn:population":0,
    "gn:timezone":"Asia/Kolkata",
    "iso:country":"IN",
    "wof:name":"Cheni",
    "wof:placetype":"locality"
},
  "geometry": {"coordinates":[81.16611999999998,27.52342],"type":"Point"}
}