{
  "type": "Feature",
  "properties": {
    "iso:country":"IN",
    "ks:ks_name":"Uttar Sagarbar",
    "ks:ks_pop":468,
    "ks:ks_type":"VILLAGE",
    "name:eng_x_preferred":[
        "Uttar Sagarbar"
    ],
    "wof:name":"Uttar Sagarbar",
    "wof:placetype":"locality",
    "wof:population":468
},
  "geometry": {"coordinates":[87.827814,22.42634],"type":"Point"}
}