{
  "type": "Feature",
  "properties": {
    "iso:country":"IN",
    "ks:ks_name":"Yettinakotti",
    "ks:ks_pop":21,
    "ks:ks_type":"HABITATION",
    "name:eng_x_preferred":[
        "Yettinakotti"
    ],
    "wof:name":"Yettinakotti",
    "wof:placetype":"locality",
    "wof:population":21
},
  "geometry": {"coordinates":[74.90244800000001,13.89379],"type":"Point"}
}