{
  "type": "Feature",
  "properties": {
    "iso:country":"IN",
    "ks:ks_alt_nam":"Dullavcherra grant",
    "ks:ks_name":"Dullavcherra Grant",
    "ks:ks_pop":989,
    "ks:ks_type":"HABITATION",
    "name:eng_x_preferred":[
        "Dullavcherra Grant"
    ],
    "wof:name":"Dullavcherra Grant",
    "wof:placetype":"locality",
    "wof:population":989
},
  "geometry": {"coordinates":[92.433249,24.478134],"type":"Point"}
}