{
  "type": "Feature",
  "properties": {
    "iso:country":"IN",
    "ks:ks_name":"Palakhedi",
    "ks:ks_pop":1448,
    "ks:ks_type":"VILLAGE",
    "name:eng_x_preferred":[
        "Palakhedi"
    ],
    "wof:name":"Palakhedi",
    "wof:placetype":"neighbourhood",
    "wof:population":1448
},
  "geometry": {"coordinates":[75.80555,22.783629],"type":"Point"}
}