{
  "type": "Feature",
  "properties": {
    "iso:country":"IN",
    "ks:ks_name":"Borapura",
    "ks:ks_pop":255,
    "ks:ks_type":"VILLAGE",
    "name:eng_x_preferred":[
        "Borapura"
    ],
    "wof:name":"Borapura",
    "wof:placetype":"locality",
    "wof:population":255
},
  "geometry": {"coordinates":[76.40668599999999,12.717474],"type":"Point"}
}