{
  "type": "Feature",
  "properties": {
    "iso:country":"IN",
    "ks:ks_name":"Kathgaon",
    "ks:ks_pop":194,
    "ks:ks_type":"VILLAGE",
    "ks:ks_uagg_main":0,
    "name:eng_x_preferred":[
        "Kathgaon"
    ],
    "wof:name":"Kathgaon",
    "wof:placetype":"neighbourhood",
    "wof:population":194
},
  "geometry": {"coordinates":[94.97688100000001,27.438685],"type":"Point"}
}