{
  "type": "Feature",
  "properties": {
    "iso:country":"IN",
    "ks:ks_name":"Kalkalikond",
    "ks:ks_pop":233,
    "ks:ks_type":"HABITATION",
    "name:eng_x_preferred":[
        "Kalkalikond"
    ],
    "wof:name":"Kalkalikond",
    "wof:placetype":"locality",
    "wof:population":233
},
  "geometry": {"coordinates":[73.441667,18.163778],"type":"Point"}
}