{
  "type": "Feature",
  "properties": {
    "gn:admin1_code":"39.0",
    "gn:admin2_code":"61.0",
    "gn:asciiname":"Jhurangu",
    "gn:country_code":"IN",
    "gn:dem":1103,
    "gn:feature_class":"P",
    "gn:feature_code":"PPL",
    "gn:name":"Jhurangu",
    "gn:population":0,
    "gn:timezone":"Asia/Kolkata",
    "iso:country":"IN",
    "wof:name":"Jhurangu",
    "wof:placetype":"locality"
},
  "geometry": {"coordinates":[79.0077,29.61838],"type":"Point"}
}