{
  "type": "Feature",
  "properties": {
    "iso:country":"IN",
    "ks:ks_name":"Wadipir",
    "ks:ks_pop":2376,
    "ks:ks_type":"VILLAGE",
    "name:eng_x_preferred":[
        "Wadipir"
    ],
    "wof:name":"Wadipir",
    "wof:placetype":"neighbourhood",
    "wof:population":2376
},
  "geometry": {"coordinates":[74.18374300000001,16.654943],"type":"Point"}
}