{
  "type": "Feature",
  "properties": {
    "iso:country":"IN",
    "ks:ks_name":"Surayapalem",
    "ks:ks_pop":918,
    "ks:ks_type":"HABITATION",
    "name:eng_x_preferred":[
        "Surayapalem"
    ],
    "wof:name":"Surayapalem",
    "wof:placetype":"neighbourhood",
    "wof:population":918
},
  "geometry": {"coordinates":[80.56248600000001,16.549032],"type":"Point"}
}