{
  "type": "Feature",
  "properties": {
    "iso:country":"IN",
    "ks:ks_name":"Vuramadigapalle",
    "ks:ks_pop":135,
    "ks:ks_type":"HABITATION",
    "name:eng_x_preferred":[
        "Vuramadigapalle"
    ],
    "wof:name":"Vuramadigapalle",
    "wof:placetype":"locality",
    "wof:population":135
},
  "geometry": {"coordinates":[78.777928,13.55182],"type":"Point"}
}