{
  "type": "Feature",
  "properties": {
    "iso:country":"IN",
    "ks:ks_name":"Satyanarayanapuram",
    "ks:ks_pop":90,
    "ks:ks_type":"HABITATION",
    "name:eng_x_preferred":[
        "Satyanarayanapuram"
    ],
    "wof:name":"Satyanarayanapuram",
    "wof:placetype":"locality",
    "wof:population":90
},
  "geometry": {"coordinates":[81.221242,17.02902],"type":"Point"}
}