{
  "type": "Feature",
  "properties": {
    "gn:admin1_code":"37.0",
    "gn:admin2_code":"408.0",
    "gn:asciiname":"Bendri",
    "gn:country_code":"IN",
    "gn:dem":317,
    "gn:feature_class":"P",
    "gn:feature_code":"PPL",
    "gn:name":"Bendri",
    "gn:population":0,
    "gn:timezone":"Asia/Kolkata",
    "iso:country":"IN",
    "ks:ks_name":"Bendri",
    "ks:ks_pop":185,
    "ks:ks_type":"VILLAGE",
    "name:eng_x_preferred":[
        "Bendri"
    ],
    "wof:name":"Bendri",
    "wof:placetype":"locality",
    "wof:population":185
},
  "geometry": {"coordinates":[81.139443,21.677121],"type":"Point"}
}