{
  "type": "Feature",
  "properties": {
    "gn:admin1_code":"36.0",
    "gn:admin2_code":"165",
    "gn:asciiname":"Kailor",
    "gn:country_code":"IN",
    "gn:dem":150,
    "gn:feature_class":"P",
    "gn:feature_code":"PPL",
    "gn:name":"Kailor",
    "gn:population":0,
    "gn:timezone":"Asia/Kolkata",
    "iso:country":"IN",
    "ks:ks_name":"Kailor",
    "ks:ks_pop":2174,
    "ks:ks_type":"VILLAGE",
    "name:eng_x_preferred":[
        "Kailor"
    ],
    "wof:name":"Kailor",
    "wof:placetype":"locality",
    "wof:population":2174
},
  "geometry": {"coordinates":[79.19152200000001,26.255089],"type":"Point"}
}