{
  "type": "Feature",
  "properties": {
    "gn:admin1_code":"16.0",
    "gn:admin2_code":"509.0",
    "gn:asciiname":"Kosambi",
    "gn:country_code":"IN",
    "gn:dem":194,
    "gn:feature_class":"P",
    "gn:feature_code":"PPL",
    "gn:name":"Kosamb\u012b",
    "gn:population":0,
    "gn:timezone":"Asia/Kolkata",
    "iso:country":"IN",
    "name:bih_x_preferred":[
        "\u0915\u094c\u0936\u093e\u0902\u092c\u0940"
    ],
    "name:cat_x_preferred":[
        "Kausambi"
    ],
    "name:ces_x_preferred":[
        "K\u00f3samb\u00ed"
    ],
    "name:fas_x_preferred":[
        "\u06a9\u0648\u0633\u0627\u0645\u0628\u06cc"
    ],
    "name:fra_x_preferred":[
        "Kosambi"
    ],
    "name:jpn_x_preferred":[
        "\u30ab\u30a6\u30b7\u30e3\u30fc\u30f3\u30d3\u30fc"
    ],
    "name:kor_x_preferred":[
        "\uce74\uc6b0\uc0f4\ube44"
    ],
    "name:mar_x_preferred":[
        "\u0915\u094b\u0938\u093e\u0902\u092c\u0940"
    ],
    "name:rus_x_preferred":[
        "\u041a\u0430\u0443\u0441\u0430\u043c\u0431\u0438"
    ],
    "name:tam_x_preferred":[
        "\u0b95\u0bcb\u0b9a\u0bbe\u0bae\u0bcd\u0baa\u0bbf"
    ],
    "name:tha_x_preferred":[
        "\u0e42\u0e01\u0e2a\u0e31\u0e21\u0e1e\u0e35"
    ],
    "name:urd_x_preferred":[
        "\u06a9\u0648\u0633\u0627\u0645\u0628\u06cc"
    ],
    "name:zho_x_preferred":[
        "\u618d\u8cde\u5f4c"
    ],
    "wof:name":"Kosambi",
    "wof:placetype":"locality"
},
  "geometry": {"coordinates":[79.66441,20.09661],"type":"Point"}
}