{
  "type": "Feature",
  "properties": {
    "gn:admin1_code":"34.0",
    "gn:admin2_code":"211.0",
    "gn:asciiname":"Amgachhi",
    "gn:country_code":"IN",
    "gn:dem":47,
    "gn:feature_class":"P",
    "gn:feature_code":"PPL",
    "gn:name":"\u0100mg\u0101chhi",
    "gn:population":0,
    "gn:timezone":"Asia/Kolkata",
    "iso:country":"IN",
    "name:ceb_x_preferred":[
        "Amgachhi"
    ],
    "name:fas_x_preferred":[
        "\u0627\u0645\u06af\u0627\u0686\u06cc"
    ],
    "name:msa_x_preferred":[
        "Amgachhi"
    ],
    "name:new_x_preferred":[
        "\u0906\u092e\u0917\u093e\u091b\u0940"
    ],
    "name:pol_x_preferred":[
        "Amgachhi"
    ],
    "wof:name":"Amgachhi",
    "wof:placetype":"locality"
},
  "geometry": {"coordinates":[87.65257,25.92529],"type":"Point"}
}