{
  "type": "Feature",
  "properties": {
    "iso:country":"IN",
    "ks:ks_name":"Karmali",
    "ks:ks_pop":945,
    "ks:ks_type":"VILLAGE",
    "ks:ks_uagg_main":0,
    "name:eng_x_preferred":[
        "Karmali"
    ],
    "wof:name":"Karmali",
    "wof:placetype":"neighbourhood",
    "wof:population":945
},
  "geometry": {"coordinates":[72.93525,21.531944],"type":"Point"}
}