{
  "type": "Feature",
  "properties": {
    "iso:country":"IN",
    "ks:ks_name":"Pulikukku",
    "ks:ks_pop":356,
    "ks:ks_type":"HABITATION",
    "name:eng_x_preferred":[
        "Pulikukku"
    ],
    "wof:name":"Pulikukku",
    "wof:placetype":"locality",
    "wof:population":356
},
  "geometry": {"coordinates":[75.457002,12.71487],"type":"Point"}
}