{
  "type": "Feature",
  "properties": {
    "iso:country":"IN",
    "ks:ks_name":"Jhapra Tola",
    "ks:ks_pop":231,
    "ks:ks_type":"HABITATION",
    "name:eng_x_preferred":[
        "Jhapra Tola"
    ],
    "wof:name":"Jhapra Tola",
    "wof:placetype":"locality",
    "wof:population":231
},
  "geometry": {"coordinates":[83.062938,23.996206],"type":"Point"}
}