{
  "type": "Feature",
  "properties": {
    "gn:admin1_code":"19.0",
    "gn:admin2_code":"574.0",
    "gn:asciiname":"Begadhalli",
    "gn:country_code":"IN",
    "gn:dem":935,
    "gn:feature_class":"P",
    "gn:feature_code":"PPL",
    "gn:name":"Begadhalli",
    "gn:population":0,
    "gn:timezone":"Asia/Kolkata",
    "iso:country":"IN",
    "wof:name":"Begadhalli",
    "wof:placetype":"locality"
},
  "geometry": {"coordinates":[75.76033000000002,12.74661],"type":"Point"}
}