{
  "type": "Feature",
  "properties": {
    "iso:country":"IN",
    "ks:ks_name":"Kattalaiyoor",
    "ks:ks_pop":277,
    "ks:ks_type":"HABITATION",
    "ks:ks_uagg_main":0,
    "name:eng_x_preferred":[
        "Kattalaiyoor"
    ],
    "wof:name":"Kattalaiyoor",
    "wof:placetype":"neighbourhood",
    "wof:population":277
},
  "geometry": {"coordinates":[77.442275,8.82241],"type":"Point"}
}