{
  "type": "Feature",
  "properties": {
    "gn:admin1_code":"34.0",
    "gn:admin2_code":"221.0",
    "gn:asciiname":"Dharampur",
    "gn:country_code":"IN",
    "gn:dem":53,
    "gn:feature_class":"P",
    "gn:feature_code":"PPL",
    "gn:name":"Dharampur",
    "gn:population":0,
    "gn:timezone":"Asia/Kolkata",
    "iso:country":"IN",
    "ks:ks_name":"Dharampur",
    "ks:ks_pop":1126,
    "ks:ks_type":"VILLAGE",
    "name:ara_x_preferred":[
        "\u062f\u0631\u0645\u0628\u0648\u0631"
    ],
    "name:ben_bn_x_preferred":[
        "\u09a7\u09b0\u09ae\u09aa\u09c1\u09b0"
    ],
    "name:ben_in_x_preferred":[
        "\u09a7\u09b0\u09ae\u09aa\u09c1\u09b0"
    ],
    "name:eng_x_preferred":[
        "Dharampur"
    ],
    "name:guj_x_preferred":[
        "\u0aa7\u0ab0\u0aae\u0aaa\u0ac1\u0ab0"
    ],
    "name:hin_x_preferred":[
        "\u0927\u0930\u092e\u092a\u0941\u0930"
    ],
    "name:kan_x_preferred":[
        "\u0ca7\u0cb0\u0cae\u0ccd"
    ],
    "name:mal_x_preferred":[
        "\u0d27\u0d30\u0d02\u0d2a\u0d42\u0d7c"
    ],
    "name:mar_x_preferred":[
        "\u0927\u0930\u092e\u092a\u0942\u0930"
    ],
    "name:pan_x_preferred":[
        "\u0a27\u0a30\u0a2e\u0a2a\u0a41\u0a30"
    ],
    "name:tam_x_preferred":[
        "\u0ba4\u0bb0\u0bae\u0bcd\u0baa\u0bc2\u0bb0\u0bcd"
    ],
    "name:tel_x_preferred":[
        "\u0c27\u0c30\u0c2e\u0c4d"
    ],
    "name:urd_x_preferred":[
        "\u062f\u06be\u0631\u0645\u067e\u0648\u0631"
    ],
    "wof:name":"Dharampur",
    "wof:placetype":"locality",
    "wof:population":1126
},
  "geometry": {"coordinates":[85.744435,25.997027],"type":"Point"}
}