{
  "type": "Feature",
  "properties": {
    "iso:country":"IN",
    "ks:ks_name":"Dashiya",
    "ks:ks_pop":236,
    "ks:ks_type":"HABITATION",
    "name:eng_x_preferred":[
        "Dashiya"
    ],
    "wof:name":"Dashiya",
    "wof:placetype":"locality",
    "wof:population":236
},
  "geometry": {"coordinates":[80.003524,29.436007],"type":"Point"}
}