{
  "type": "Feature",
  "properties": {
    "iso:country":"IN",
    "ks:ks_name":"Khaira Chak",
    "ks:ks_pop":44,
    "ks:ks_type":"VILLAGE",
    "name:eng_x_preferred":[
        "Khaira Chak"
    ],
    "wof:name":"Khaira Chak",
    "wof:placetype":"locality",
    "wof:population":44
},
  "geometry": {"coordinates":[86.55730699999999,23.549275],"type":"Point"}
}