{
  "type": "Feature",
  "properties": {
    "iso:country":"IN",
    "ks:ks_name":"Nasirpur",
    "ks:ks_pop":68,
    "ks:ks_type":"VILLAGE",
    "name:eng_x_preferred":[
        "Nasirpur"
    ],
    "wof:name":"Nasirpur",
    "wof:placetype":"locality",
    "wof:population":68
},
  "geometry": {"coordinates":[76.80935599999999,25.858954],"type":"Point"}
}