{
  "type": "Feature",
  "properties": {
    "gn:country":"IN",
    "gn:fcode":"PPL",
    "gn:pop":21015,
    "iso:country":"IN",
    "name:ara_x_preferred":[
        "\u0642\u0627\u062f\u064a\u0627\u0646"
    ],
    "name:ben_x_preferred":[
        "\u0995\u09be\u09a6\u09bf\u09af\u09bc\u09be\u09a8"
    ],
    "name:bpy_x_preferred":[
        "\u0995\u09be\u09a6\u09bf\u09af\u09bc\u09be\u09a8"
    ],
    "name:cat_x_preferred":[
        "Qadian"
    ],
    "name:ceb_x_preferred":[
        "Q\u0101di\u0101n"
    ],
    "name:deu_x_preferred":[
        "Qadian"
    ],
    "name:eng_x_preferred":[
        "Qadian"
    ],
    "name:fra_x_preferred":[
        "Qadian"
    ],
    "name:hin_x_preferred":[
        "\u0915\u093c\u093e\u0926\u093f\u092f\u093e\u0901"
    ],
    "name:ind_x_preferred":[
        "Qadian"
    ],
    "name:ita_x_preferred":[
        "Qadian"
    ],
    "name:kaz_x_preferred":[
        "\u049a\u0430\u0434\u0438\u0430\u043d"
    ],
    "name:mal_x_preferred":[
        "\u0d16\u0d3e\u0d26\u0d3f\u0d2f\u0d3e\u0d7b"
    ],
    "name:mlg_x_preferred":[
        "Qadian"
    ],
    "name:msa_x_preferred":[
        "Qadian"
    ],
    "name:nan_x_preferred":[
        "Qadian"
    ],
    "name:nld_x_preferred":[
        "Qadian"
    ],
    "name:ori_x_preferred":[
        "\u0b15\u0b3e\u0b21\u0b3c\u0b3f\u0b06\u0b01"
    ],
    "name:pan_x_preferred":[
        "\u0a15\u0a3c\u0a3e\u0a26\u0a40\u0a06\u0a02"
    ],
    "name:pnb_x_preferred":[
        "\u0642\u0627\u062f\u06cc\u0627\u0646"
    ],
    "name:rus_x_preferred":[
        "\u041a\u0430\u0434\u0438\u0430\u043d"
    ],
    "name:spa_x_preferred":[
        "Qadian"
    ],
    "name:sqi_x_preferred":[
        "Qadian"
    ],
    "name:swe_x_preferred":[
        "Q\u0101di\u0101n"
    ],
    "name:unk_x_variant":[
        "K\u0101di\u0101n"
    ],
    "name:urd_x_preferred":[
        "\u0642\u0627\u062f\u06cc\u0627\u0646"
    ],
    "name:vie_x_preferred":[
        "Qadian"
    ],
    "name:zho_x_preferred":[
        "\u5361\u8fea\u4e9a\u6069"
    ],
    "qs:name":"Qadian",
    "qs:name_adm0":"India",
    "qs:name_adm1":"Punjab",
    "qs:photos_9k":1,
    "qs:photos_9r":1,
    "qs:photos_all":14,
    "qs:photos_sr":0,
    "qs:placetype":"Town",
    "qs:pop_sr":"7",
    "wd:wordcount":945,
    "wof:name":"Qadian",
    "wof:placetype":"locality",
    "wof:population":21015
},
  "geometry": {"coordinates":[75.37663000000001,31.82198],"type":"Point"}
}