{
  "type": "Feature",
  "properties": {
    "gn:admin1_code":"16",
    "gn:admin2_code":"526.0",
    "gn:asciiname":"Musti",
    "gn:country_code":"IN",
    "gn:dem":484,
    "gn:feature_class":"P",
    "gn:feature_code":"PPL",
    "gn:name":"Musti",
    "gn:population":0,
    "gn:timezone":"Asia/Kolkata",
    "iso:country":"IN",
    "name:ceb_x_preferred":[
        "Musti"
    ],
    "name:deu_x_preferred":[
        "Musti"
    ],
    "name:fin_x_preferred":[
        "Musti"
    ],
    "name:ita_x_preferred":[
        "Musti"
    ],
    "name:swe_x_preferred":[
        "Musti"
    ],
    "name:tur_x_preferred":[
        "Musti"
    ],
    "wof:name":"Musti",
    "wof:placetype":"locality"
},
  "geometry": {"coordinates":[76.12026999999998,17.72679],"type":"Point"}
}