{
  "type": "Feature",
  "properties": {
    "gn:admin1_code":"36",
    "gn:admin2_code":"169.0",
    "gn:asciiname":"Sirmaur",
    "gn:country_code":"IN",
    "gn:dem":189,
    "gn:feature_class":"P",
    "gn:feature_code":"PPL",
    "gn:name":"Sirmaur",
    "gn:population":0,
    "gn:timezone":"Asia/Kolkata",
    "iso:country":"IN",
    "wof:name":"Sirmaur",
    "wof:placetype":"locality"
},
  "geometry": {"coordinates":[79.6832,25.32881],"type":"Point"}
}