{
  "type": "Feature",
  "properties": {
    "gn:admin1_code":"36",
    "gn:admin2_code":"169.0",
    "gn:asciiname":"Sirmaur",
    "gn:country_code":"IN",
    "gn:dem":189,
    "gn:feature_class":"P",
    "gn:feature_code":"PPL",
    "gn:name":"Sirmaur",
    "gn:population":0,
    "gn:timezone":"Asia/Kolkata",
    "iso:country":"IN",
    "name:ara_x_preferred":[
        "\u0633\u064a\u0631\u0645\u0648\u0631"
    ],
    "name:ben_x_preferred":[
        "\u09b8\u09bf\u09b0\u09ae\u09cc\u09b0"
    ],
    "name:ceb_x_preferred":[
        "Sirmaur"
    ],
    "name:mar_x_preferred":[
        "\u0938\u093f\u0930\u092e\u094c\u0930"
    ],
    "name:nld_x_preferred":[
        "Sirmaur"
    ],
    "name:swe_x_preferred":[
        "Sirmaur"
    ],
    "wof:name":"Sirmaur",
    "wof:placetype":"locality"
},
  "geometry": {"coordinates":[79.6832,25.32881],"type":"Point"}
}