{
  "type": "Feature",
  "properties": {
    "gn:admin1_code":"36",
    "gn:admin2_code":"169.0",
    "gn:asciiname":"Sirmaur",
    "gn:country_code":"IN",
    "gn:dem":189,
    "gn:feature_class":"P",
    "gn:feature_code":"PPL",
    "gn:name":"Sirmaur",
    "gn:population":0,
    "gn:timezone":"Asia/Kolkata",
    "iso:country":"IN",
    "name:ara_x_preferred":[
        "\u0633\u064a\u0631\u0645\u0648\u0631"
    ],
    "name:ben_bn_x_preferred":[
        "\u09b8\u09bf\u09b0\u09ae\u09be\u0989\u09b0"
    ],
    "name:ben_in_x_preferred":[
        "\u09b8\u09bf\u09b0\u09ae\u09be\u0989\u09b0"
    ],
    "name:ben_x_preferred":[
        "\u09b8\u09bf\u09b0\u09ae\u09cc\u09b0"
    ],
    "name:ceb_x_preferred":[
        "Sirmaur"
    ],
    "name:guj_x_preferred":[
        "\u0ab8\u0abf\u0ab0\u0aae\u0acc\u0ab0"
    ],
    "name:hin_x_preferred":[
        "\u0938\u093f\u0930\u092e\u094c\u0930"
    ],
    "name:kan_x_preferred":[
        "\u0cb8\u0cbf\u0cb0\u0ccd\u0cae\u0ccc\u0cb0\u0ccd"
    ],
    "name:mal_x_preferred":[
        "\u0d38\u0d3f\u0d7c\u0d2e\u0d57\u0d7c"
    ],
    "name:mar_x_preferred":[
        "\u0938\u093f\u0930\u092e\u094c\u0930"
    ],
    "name:nld_x_preferred":[
        "Sirmaur"
    ],
    "name:pan_x_preferred":[
        "\u0a38\u0a3f\u0a30\u0a2e\u0a4c\u0a30"
    ],
    "name:swe_x_preferred":[
        "Sirmaur"
    ],
    "name:tam_x_preferred":[
        "\u0b9a\u0bbf\u0bb0\u0bcd\u0bae\u0bcc\u0bb0\u0bcd"
    ],
    "name:tel_x_preferred":[
        "\u0c38\u0c3f\u0c30\u0c4d\u0c2e\u0c4c\u0c30\u0c4d"
    ],
    "name:urd_x_preferred":[
        "\u0633\u0631\u0645\u0624\u0631"
    ],
    "wof:name":"Sirmaur",
    "wof:placetype":"locality"
},
  "geometry": {"coordinates":[79.6832,25.32881],"type":"Point"}
}