{
  "type": "Feature",
  "properties": {
    "gn:admin1_code":"19.0",
    "gn:admin2_code":"555.0",
    "gn:asciiname":"Hindalgi",
    "gn:country_code":"IN",
    "gn:dem":747,
    "gn:feature_class":"P",
    "gn:feature_code":"PPL",
    "gn:name":"Hindalgi",
    "gn:population":0,
    "gn:timezone":"Asia/Kolkata",
    "iso:country":"IN",
    "wof:name":"Hindalgi",
    "wof:placetype":"locality"
},
  "geometry": {"coordinates":[74.47205,15.87495],"type":"Point"}
}