{
  "type": "Feature",
  "properties": {
    "gn:admin1_code":"16",
    "gn:admin2_code":"511.0",
    "gn:asciiname":"Pipalgaon",
    "gn:country_code":"IN",
    "gn:dem":340,
    "gn:feature_class":"P",
    "gn:feature_code":"PPL",
    "gn:name":"Pipalgaon",
    "gn:population":0,
    "gn:timezone":"Asia/Kolkata",
    "iso:country":"IN",
    "name:und_x_variant":[
        "P\u012bpalgaon"
    ],
    "wof:name":"Pipalgaon",
    "wof:placetype":"locality"
},
  "geometry": {"coordinates":[78.30896,19.73053],"type":"Point"}
}