{
  "type": "Feature",
  "properties": {
    "gn:admin1_code":"37",
    "gn:admin2_code":"409.0",
    "gn:asciiname":"Lata",
    "gn:country_code":"IN",
    "gn:dem":269,
    "gn:feature_class":"P",
    "gn:feature_code":"PPL",
    "gn:name":"L\u0101ta",
    "gn:population":0,
    "gn:timezone":"Asia/Kolkata",
    "iso:country":"IN",
    "name:heb_x_preferred":[
        "\u05dc\u05d0\u05d8\u05d4"
    ],
    "name:hun_x_preferred":[
        "Lata"
    ],
    "wof:name":"Lata",
    "wof:placetype":"locality"
},
  "geometry": {"coordinates":[81.60536,21.38305],"type":"Point"}
}