{
  "type": "Feature",
  "properties": {
    "gn:admin1_code":"35",
    "gn:admin2_code":"454.0",
    "gn:asciiname":"Putarra",
    "gn:country_code":"IN",
    "gn:dem":468,
    "gn:feature_class":"P",
    "gn:feature_code":"PPL",
    "gn:name":"Putarra",
    "gn:population":0,
    "gn:timezone":"Asia/Kolkata",
    "iso:country":"IN",
    "wof:name":"Putarra",
    "wof:placetype":"locality"
},
  "geometry": {"coordinates":[79.99924,22.5537],"type":"Point"}
}