{
  "type": "Feature",
  "properties": {
    "iso:country":"IN",
    "ks:ks_name":"Torada",
    "ks:ks_pop":617,
    "ks:ks_type":"VILLAGE",
    "name:eng_x_preferred":[
        "Torada"
    ],
    "wof:name":"Torada",
    "wof:placetype":"locality",
    "wof:population":617
},
  "geometry": {"coordinates":[86.229287,20.763274],"type":"Point"}
}