{
  "type": "Feature",
  "properties": {
    "gn:admin1_code":"37",
    "gn:admin2_code":"409.0",
    "gn:asciiname":"Khairkatta",
    "gn:country_code":"IN",
    "gn:dem":350,
    "gn:feature_class":"P",
    "gn:feature_code":"PPL",
    "gn:name":"Khairkatta",
    "gn:population":0,
    "gn:timezone":"Asia/Kolkata",
    "iso:country":"IN",
    "wof:name":"Khairkatta",
    "wof:placetype":"locality"
},
  "geometry": {"coordinates":[80.94989,20.7621],"type":"Point"}
}