{
  "type": "Feature",
  "properties": {
    "iso:country":"IN",
    "ks:ks_name":"Penula Ramsen",
    "ks:ks_pop":436,
    "ks:ks_type":"VILLAGE",
    "ks:ks_uagg_main":0,
    "name:eng_x_preferred":[
        "Penula Ramsen"
    ],
    "wof:name":"Penula Ramsen",
    "wof:placetype":"neighbourhood",
    "wof:population":436
},
  "geometry": {"coordinates":[84.273701,26.493237],"type":"Point"}
}