{
  "type": "Feature",
  "properties": {
    "iso:country":"IN",
    "ks:ks_name":"Kotha Arundathiwada",
    "ks:ks_pop":144,
    "ks:ks_type":"HABITATION",
    "name:eng_x_preferred":[
        "Kotha Arundathiwada"
    ],
    "wof:name":"Kotha Arundathiwada",
    "wof:placetype":"locality",
    "wof:population":144
},
  "geometry": {"coordinates":[79.60493700000001,13.602319],"type":"Point"}
}