{
  "type": "Feature",
  "properties": {
    "iso:country":"IN",
    "ks:ks_name":"Lahadi",
    "ks:ks_pop":319,
    "ks:ks_type":"VILLAGE",
    "name:eng_x_preferred":[
        "Lahadi"
    ],
    "wof:name":"Lahadi",
    "wof:placetype":"locality",
    "wof:population":319
},
  "geometry": {"coordinates":[83.732229,20.157203],"type":"Point"}
}