{
  "type": "Feature",
  "properties": {
    "iso:country":"IN",
    "ks:ks_name":"Gudigadde",
    "ks:ks_pop":12,
    "ks:ks_type":"HABITATION",
    "name:eng_x_preferred":[
        "Gudigadde"
    ],
    "wof:name":"Gudigadde",
    "wof:placetype":"locality",
    "wof:population":12
},
  "geometry": {"coordinates":[75.501589,12.488544],"type":"Point"}
}