{
  "type": "Feature",
  "properties": {
    "iso:country":"IN",
    "ks:ks_name":"Shampur",
    "ks:ks_pop":358,
    "ks:ks_type":"VILLAGE",
    "name:eng_x_preferred":[
        "Shampur"
    ],
    "wof:name":"Shampur",
    "wof:placetype":"locality",
    "wof:population":358
},
  "geometry": {"coordinates":[87.32893300000001,24.714262],"type":"Point"}
}