{
  "type": "Feature",
  "properties": {
    "iso:country":"IN",
    "ks:ks_name":"Aambedkarnagar",
    "ks:ks_pop":238,
    "ks:ks_type":"HABITATION",
    "name:eng_x_preferred":[
        "Aambedkarnagar"
    ],
    "wof:name":"Aambedkarnagar",
    "wof:placetype":"locality",
    "wof:population":238
},
  "geometry": {"coordinates":[73.679534,16.054095],"type":"Point"}
}