{
  "type": "Feature",
  "properties": {
    "gn:admin1_code":"19.0",
    "gn:admin2_code":"581.0",
    "gn:asciiname":"Kambhampalli",
    "gn:country_code":"IN",
    "gn:dem":819,
    "gn:feature_class":"P",
    "gn:feature_code":"PPL",
    "gn:name":"Kambhampalli",
    "gn:population":0,
    "gn:timezone":"Asia/Kolkata",
    "iso:country":"IN",
    "wof:name":"Kambhampalli",
    "wof:placetype":"locality"
},
  "geometry": {"coordinates":[78.28570000000001,12.9361],"type":"Point"}
}