{
  "type": "Feature",
  "properties": {
    "gn:admin1_code":"12.0",
    "gn:admin2_code":"005",
    "gn:asciiname":"Markot",
    "gn:country_code":"IN",
    "gn:dem":1991,
    "gn:feature_class":"P",
    "gn:feature_code":"PPL",
    "gn:name":"Markot",
    "gn:population":0,
    "gn:timezone":"Asia/Kolkata",
    "iso:country":"IN",
    "name:pol_x_preferred":[
        "Markot"
    ],
    "wof:name":"Markot",
    "wof:placetype":"locality"
},
  "geometry": {"coordinates":[74.29012,33.81925],"type":"Point"}
}