{
  "type": "Feature",
  "properties": {
    "iso:country":"IN",
    "ks:ks_alt_nam":"Borka Deka suba",
    "ks:ks_name":"Borka Deka Suba",
    "ks:ks_pop":300,
    "ks:ks_type":"HABITATION",
    "ks:ks_uagg_main":0,
    "name:eng_x_preferred":[
        "Borka Deka Suba"
    ],
    "wof:name":"Borka Deka Suba",
    "wof:placetype":"neighbourhood",
    "wof:population":300
},
  "geometry": {"coordinates":[91.664801,26.283583],"type":"Point"}
}