{
  "type": "Feature",
  "properties": {
    "gn:admin1_code":"23.0",
    "gn:admin2_code":"44.0",
    "gn:asciiname":"Sarai Nanga",
    "gn:country_code":"IN",
    "gn:dem":205,
    "gn:feature_class":"P",
    "gn:feature_code":"PPL",
    "gn:name":"Sarai Nanga",
    "gn:population":0,
    "gn:timezone":"Asia/Kolkata",
    "iso:country":"IN",
    "wof:name":"Sarai Nanga",
    "wof:placetype":"locality"
},
  "geometry": {"coordinates":[74.66969,30.51393],"type":"Point"}
}