{
  "type": "Feature",
  "properties": {
    "gn:admin1_code":"37",
    "gn:admin2_code":"404.0",
    "gn:asciiname":"Dumardih",
    "gn:country_code":"IN",
    "gn:dem":359,
    "gn:feature_class":"P",
    "gn:feature_code":"PPL",
    "gn:name":"D\u016bmard\u012bh",
    "gn:population":0,
    "gn:timezone":"Asia/Kolkata",
    "iso:country":"IN",
    "ks:ks_alt_nam":"D\u016bmard\u012bh",
    "ks:ks_name":"Dumardih",
    "ks:ks_type":"VILLAGE",
    "name:eng_x_preferred":[
        "Dumardih"
    ],
    "name:eng_x_variant":[
        "D\u016bmard\u012bh"
    ],
    "wof:name":"Dumardih",
    "wof:placetype":"locality"
},
  "geometry": {"coordinates":[82.99846599999999,22.498374],"type":"Point"}
}