{
  "type": "Feature",
  "properties": {
    "gn:admin1_code":"34.0",
    "gn:admin2_code":"220.0",
    "gn:asciiname":"Chak Faiz",
    "gn:country_code":"IN",
    "gn:dem":55,
    "gn:feature_class":"P",
    "gn:feature_code":"PPL",
    "gn:name":"Chak Faiz",
    "gn:population":0,
    "gn:timezone":"Asia/Kolkata",
    "iso:country":"IN",
    "ks:ks_name":"Chak Faiz",
    "ks:ks_pop":1096,
    "ks:ks_type":"VILLAGE",
    "name:eng_x_preferred":[
        "Chak Faiz"
    ],
    "wof:name":"Chak Faiz",
    "wof:placetype":"locality",
    "wof:population":1096
},
  "geometry": {"coordinates":[85.478962,25.898845],"type":"Point"}
}