{
  "type": "Feature",
  "properties": {
    "gn:admin1_code":"36",
    "gn:admin2_code":"200.0",
    "gn:asciiname":"Tumiya",
    "gn:country_code":"IN",
    "gn:dem":251,
    "gn:feature_class":"P",
    "gn:feature_code":"PPL",
    "gn:name":"Tumiya",
    "gn:population":0,
    "gn:timezone":"Asia/Kolkata",
    "iso:country":"IN",
    "ks:ks_name":"Tumiya",
    "ks:ks_pop":1111,
    "ks:ks_type":"HABITATION",
    "name:eng_x_preferred":[
        "Tumiya"
    ],
    "wof:name":"Tumiya",
    "wof:placetype":"locality",
    "wof:population":1111
},
  "geometry": {"coordinates":[83.34402,24.318396],"type":"Point"}
}