{
  "type": "Feature",
  "properties": {
    "iso:country":"IN",
    "ks:ks_name":"Dhavalewasti",
    "ks:ks_pop":100,
    "ks:ks_type":"HABITATION",
    "name:eng_x_preferred":[
        "Dhavalewasti"
    ],
    "wof:name":"Dhavalewasti",
    "wof:placetype":"locality",
    "wof:population":100
},
  "geometry": {"coordinates":[73.666667,19.172222],"type":"Point"}
}