{
  "type": "Feature",
  "properties": {
    "iso:country":"IN",
    "ks:ks_name":"Raval Faliya",
    "ks:ks_pop":180,
    "ks:ks_type":"HABITATION",
    "name:eng_x_preferred":[
        "Raval Faliya"
    ],
    "wof:name":"Raval Faliya",
    "wof:placetype":"locality",
    "wof:population":180
},
  "geometry": {"coordinates":[73.69798299999999,22.8324],"type":"Point"}
}