{
  "type": "Feature",
  "properties": {
    "gn:admin1_code":"19.0",
    "gn:admin2_code":"581.0",
    "gn:asciiname":"Vardenhalli",
    "gn:country_code":"IN",
    "gn:dem":883,
    "gn:feature_class":"P",
    "gn:feature_code":"PPL",
    "gn:name":"Vardenhalli",
    "gn:population":0,
    "gn:timezone":"Asia/Kolkata",
    "iso:country":"IN",
    "wof:name":"Vardenhalli",
    "wof:placetype":"locality"
},
  "geometry": {"coordinates":[77.98859,13.04217],"type":"Point"}
}