{
  "type": "Feature",
  "properties": {
    "gn:admin1_code":"36.0",
    "gn:admin2_code":"183.0",
    "gn:asciiname":"Gangan",
    "gn:country_code":"IN",
    "gn:dem":109,
    "gn:feature_class":"P",
    "gn:feature_code":"PPL",
    "gn:name":"Gangan",
    "gn:population":0,
    "gn:timezone":"Asia/Kolkata",
    "iso:country":"IN",
    "name:ceb_x_preferred":[
        "Gangan"
    ],
    "name:deu_x_preferred":[
        "Gangan Verlag"
    ],
    "name:fra_x_preferred":[
        "Gangan"
    ],
    "name:jpn_x_preferred":[
        "\u30ac\u30f3\u30ac\u30f3"
    ],
    "wof:name":"Gangan",
    "wof:placetype":"locality"
},
  "geometry": {"coordinates":[81.64553000000002,27.08491],"type":"Point"}
}