{
  "type": "Feature",
  "properties": {
    "iso:country":"IN",
    "ks:ks_name":"Dhobi Tola",
    "ks:ks_pop":316,
    "ks:ks_type":"HABITATION",
    "name:eng_x_preferred":[
        "Dhobi Tola"
    ],
    "wof:name":"Dhobi Tola",
    "wof:placetype":"locality",
    "wof:population":316
},
  "geometry": {"coordinates":[83.749157,26.81744],"type":"Point"}
}