{
  "type": "Feature",
  "properties": {
    "iso:country":"IN",
    "ks:ks_name":"Kasia Alias Surjabasa",
    "ks:ks_pop":605,
    "ks:ks_type":"VILLAGE",
    "name:eng_x_preferred":[
        "Kasia Alias Surjabasa"
    ],
    "wof:name":"Kasia Alias Surjabasa",
    "wof:placetype":"locality",
    "wof:population":605
},
  "geometry": {"coordinates":[85.771794,22.468136],"type":"Point"}
}