{
  "type": "Feature",
  "properties": {
    "iso:country":"IN",
    "ks:ks_name":"Seethurani",
    "ks:ks_pop":447,
    "ks:ks_type":"HABITATION",
    "ks:ks_uagg_main":0,
    "name:eng_x_preferred":[
        "Seethurani"
    ],
    "wof:name":"Seethurani",
    "wof:placetype":"neighbourhood",
    "wof:population":447
},
  "geometry": {"coordinates":[78.638975,9.625114],"type":"Point"}
}