{
  "type": "Feature",
  "properties": {
    "iso:country":"IN",
    "ks:ks_name":"Dhiuli Dhauni",
    "ks:ks_pop":186,
    "ks:ks_type":"VILLAGE",
    "name:eng_x_preferred":[
        "Dhiuli Dhauni"
    ],
    "wof:name":"Dhiuli Dhauni",
    "wof:placetype":"locality",
    "wof:population":186
},
  "geometry": {"coordinates":[79.80199399999999,29.513188],"type":"Point"}
}