{
  "type": "Feature",
  "properties": {
    "iso:country":"IN",
    "ks:ks_name":"Bandakadithanda",
    "ks:ks_pop":40,
    "ks:ks_type":"HABITATION",
    "name:eng_x_preferred":[
        "Bandakadithanda"
    ],
    "wof:name":"Bandakadithanda",
    "wof:placetype":"locality",
    "wof:population":40
},
  "geometry": {"coordinates":[79.523201,17.670962],"type":"Point"}
}