{
  "type": "Feature",
  "properties": {
    "iso:country":"IN",
    "ks:ks_name":"Gavii",
    "ks:ks_pop":311,
    "ks:ks_type":"HABITATION",
    "name:eng_x_preferred":[
        "Gavii"
    ],
    "wof:name":"Gavii",
    "wof:placetype":"locality",
    "wof:population":311
},
  "geometry": {"coordinates":[77.076249,9.391661],"type":"Point"}
}