{
  "type": "Feature",
  "properties": {
    "iso:country":"IN",
    "ks:ks_name":"Naya Tola",
    "ks:ks_pop":249,
    "ks:ks_type":"HABITATION",
    "name:eng_x_preferred":[
        "Naya Tola"
    ],
    "wof:name":"Naya Tola",
    "wof:placetype":"locality",
    "wof:population":249
},
  "geometry": {"coordinates":[85.428726,25.290583],"type":"Point"}
}