{
  "type": "Feature",
  "properties": {
    "gn:admin1_code":"36.0",
    "gn:admin2_code":"175.0",
    "gn:asciiname":"Mansurabad",
    "gn:country_code":"IN",
    "gn:dem":102,
    "gn:feature_class":"P",
    "gn:feature_code":"PPL",
    "gn:name":"Mans\u016br\u0101b\u0101d",
    "gn:population":0,
    "gn:timezone":"Asia/Kolkata",
    "iso:country":"IN",
    "name:aze_x_preferred":[
        "M\u0259nsurabad"
    ],
    "name:fas_x_preferred":[
        "\u0645\u0646\u0635\u0648\u0631\u0622\u0628\u0627\u062f"
    ],
    "wof:name":"Mansurabad",
    "wof:placetype":"locality"
},
  "geometry": {"coordinates":[81.67114000000002,25.59032],"type":"Point"}
}