{
  "type": "Feature",
  "properties": {
    "iso:country":"IN",
    "ks:ks_name":"Osita Ahtmali",
    "ks:ks_pop":0,
    "ks:ks_type":"VILLAGE",
    "name:eng_x_preferred":[
        "Osita Ahtmali"
    ],
    "wof:name":"Osita Ahtmali",
    "wof:placetype":"locality",
    "wof:population":0
},
  "geometry": {"coordinates":[78.146795,28.783812],"type":"Point"}
}