{
  "type": "Feature",
  "properties": {
    "iso:country":"IN",
    "ks:ks_name":"Hachya Thanda",
    "ks:ks_pop":39,
    "ks:ks_type":"HABITATION",
    "name:eng_x_preferred":[
        "Hachya Thanda"
    ],
    "wof:name":"Hachya Thanda",
    "wof:placetype":"locality",
    "wof:population":39
},
  "geometry": {"coordinates":[78.23889699999999,17.757524],"type":"Point"}
}