{
  "type": "Feature",
  "properties": {
    "iso:country":"IN",
    "ks:ks_name":"Undrumi Mukkulam",
    "ks:ks_pop":951,
    "ks:ks_type":"HABITATION",
    "name:eng_x_preferred":[
        "Undrumi Mukkulam"
    ],
    "wof:name":"Undrumi Mukkulam",
    "wof:placetype":"locality",
    "wof:population":951
},
  "geometry": {"coordinates":[78.26321,9.705428],"type":"Point"}
}