{
  "type": "Feature",
  "properties": {
    "iso:country":"IN",
    "ks:ks_name":"Kamrudden Nagar",
    "ks:ks_pop":2687,
    "ks:ks_type":"HABITATION",
    "name:eng_x_preferred":[
        "Kamrudden Nagar"
    ],
    "wof:name":"Kamrudden Nagar",
    "wof:placetype":"locality",
    "wof:population":2687
},
  "geometry": {"coordinates":[77.361176,29.272544],"type":"Point"}
}