{
  "type": "Feature",
  "properties": {
    "iso:country":"IN",
    "ks:ks_name":"Dungariya",
    "ks:ks_pop":4163,
    "ks:ks_type":"HABITATION",
    "name:eng_x_preferred":[
        "Dungariya"
    ],
    "wof:name":"Dungariya",
    "wof:placetype":"locality",
    "wof:population":4163
},
  "geometry": {"coordinates":[77.79994499999999,23.117741],"type":"Point"}
}