{
  "type": "Feature",
  "properties": {
    "gn:admin1_code":"23.0",
    "gn:admin2_code":"40.0",
    "gn:asciiname":"Ramgarh",
    "gn:country_code":"IN",
    "gn:dem":273,
    "gn:feature_class":"P",
    "gn:feature_code":"PPL",
    "gn:name":"R\u0101mgarh",
    "gn:population":0,
    "gn:timezone":"Asia/Kolkata",
    "iso:country":"IN",
    "name:ara_x_preferred":[
        "\u0631\u0627\u0645\u062c\u0631\u0627\u0647"
    ],
    "name:ben_bn_x_preferred":[
        "\u09b0\u09be\u09ae\u0997\u09dc"
    ],
    "name:ben_in_x_preferred":[
        "\u09b0\u09be\u09ae\u0997\u09dc"
    ],
    "name:cat_x_preferred":[
        "Ramgarh"
    ],
    "name:ceb_x_preferred":[
        "Ramgarh"
    ],
    "name:deu_x_preferred":[
        "Ramgarh"
    ],
    "name:guj_x_preferred":[
        "\u0ab0\u0abe\u0aae\u0a97\u0aa2"
    ],
    "name:hin_x_preferred":[
        "\u0930\u093e\u092e\u0917\u095d"
    ],
    "name:ita_x_preferred":[
        "Ramgarh"
    ],
    "name:kan_x_preferred":[
        "\u0cb0\u0cbe\u0cae\u0c97\u0ccd"
    ],
    "name:mal_x_preferred":[
        "\u0d30\u0d3e\u0d02\u0d17\u0d21\u0d4d"
    ],
    "name:mar_x_preferred":[
        "\u0930\u093e\u092e\u0917\u0921"
    ],
    "name:pan_x_preferred":[
        "\u0a30\u0a3e\u0a2e\u0a17\u0a5c\u0a4d\u0a39"
    ],
    "name:pol_x_preferred":[
        "Ramgarh"
    ],
    "name:rus_x_preferred":[
        "\u0420\u0430\u043c\u0433\u0430\u0440\u0445"
    ],
    "name:swe_x_preferred":[
        "Ramgarh"
    ],
    "name:tam_x_preferred":[
        "\u0bb0\u0bbe\u0bae\u0bcd\u0b95\u0bb0\u0bcd"
    ],
    "name:tel_x_preferred":[
        "\u0c30\u0c3e\u0c2e\u0c4d"
    ],
    "name:urd_x_preferred":[
        "\u0631\u0627\u0645 \u06af\u0691\u06be"
    ],
    "wof:name":"Ramgarh",
    "wof:placetype":"locality"
},
  "geometry": {"coordinates":[76.3233,30.85564],"type":"Point"}
}