{
  "type": "Feature",
  "properties": {
    "iso:country":"IN",
    "ks:ks_name":"Rugurbasa",
    "ks:ks_pop":449,
    "ks:ks_type":"HABITATION",
    "name:eng_x_preferred":[
        "Rugurbasa"
    ],
    "wof:name":"Rugurbasa",
    "wof:placetype":"locality",
    "wof:population":449
},
  "geometry": {"coordinates":[85.816582,22.451252],"type":"Point"}
}