{
  "type": "Feature",
  "properties": {
    "iso:country":"IN",
    "ks:ks_name":"Kuravanpady",
    "ks:ks_pop":1128,
    "ks:ks_type":"HABITATION",
    "name:eng_x_preferred":[
        "Kuravanpady"
    ],
    "wof:name":"Kuravanpady",
    "wof:placetype":"locality",
    "wof:population":1128
},
  "geometry": {"coordinates":[76.65399600000001,11.034388],"type":"Point"}
}