{
  "type": "Feature",
  "properties": {
    "iso:country":"IN",
    "ks:ks_name":"Khori",
    "ks:ks_pop":235,
    "ks:ks_type":"HABITATION",
    "name:eng_x_preferred":[
        "Khori"
    ],
    "wof:name":"Khori",
    "wof:placetype":"locality",
    "wof:population":235
},
  "geometry": {"coordinates":[86.44577,24.41046],"type":"Point"}
}