{
  "type": "Feature",
  "properties": {
    "iso:country":"IN",
    "ks:ks_alt_nam":"BHITARSERKA",
    "ks:ks_name":"Bhitarserka",
    "ks:ks_pop":530,
    "ks:ks_type":"HABITATION",
    "name:eng_x_preferred":[
        "Bhitarserka"
    ],
    "wof:name":"Bhitarserka",
    "wof:placetype":"locality",
    "wof:population":530
},
  "geometry": {"coordinates":[84.40479999999999,23.37789],"type":"Point"}
}