{
  "type": "Feature",
  "properties": {
    "iso:country":"IN",
    "ks:ks_name":"Mandaba Mettukuppam",
    "ks:ks_pop":650,
    "ks:ks_type":"HABITATION",
    "name:eng_x_preferred":[
        "Mandaba Mettukuppam"
    ],
    "wof:name":"Mandaba Mettukuppam",
    "wof:placetype":"locality",
    "wof:population":650
},
  "geometry": {"coordinates":[79.607831,11.55694],"type":"Point"}
}