{
  "type": "Feature",
  "properties": {
    "iso:country":"IN",
    "ks:ks_name":"Uttarjhitkipota",
    "ks:ks_pop":1499,
    "ks:ks_type":"VILLAGE",
    "ks:ks_uagg_main":0,
    "name:eng_x_preferred":[
        "Uttarjhitkipota"
    ],
    "wof:name":"Uttarjhitkipota",
    "wof:placetype":"neighbourhood",
    "wof:population":1499
},
  "geometry": {"coordinates":[88.473099,23.480301],"type":"Point"}
}