{
  "type": "Feature",
  "properties": {
    "iso:country":"IN",
    "ks:ks_name":"Rajput Tola",
    "ks:ks_pop":548,
    "ks:ks_type":"HABITATION",
    "name:eng_x_preferred":[
        "Rajput Tola"
    ],
    "wof:name":"Rajput Tola",
    "wof:placetype":"locality",
    "wof:population":548
},
  "geometry": {"coordinates":[85.09276800000001,26.202802],"type":"Point"}
}