{
  "type": "Feature",
  "properties": {
    "gn:admin1_code":"34.0",
    "gn:admin2_code":"230.0",
    "gn:asciiname":"Kanchanpur",
    "gn:country_code":"IN",
    "gn:dem":57,
    "gn:feature_class":"P",
    "gn:feature_code":"PPL",
    "gn:name":"Kanchanpur",
    "gn:population":0,
    "gn:timezone":"Asia/Kolkata",
    "iso:country":"IN",
    "name:ceb_x_preferred":[
        "Kanchanpur"
    ],
    "name:nld_x_preferred":[
        "Kanchanpur"
    ],
    "wof:name":"Kanchanpur",
    "wof:placetype":"locality"
},
  "geometry": {"coordinates":[85.24998000000002,25.4464],"type":"Point"}
}