{
  "type": "Feature",
  "properties": {
    "iso:country":"IN",
    "ks:ks_name":"Mamudpur",
    "ks:ks_pop":794,
    "ks:ks_type":"VILLAGE",
    "name:eng_x_preferred":[
        "Mamudpur"
    ],
    "wof:name":"Mamudpur",
    "wof:placetype":"locality",
    "wof:population":794
},
  "geometry": {"coordinates":[87.600684,23.242199],"type":"Point"}
}