{
  "type": "Feature",
  "properties": {
    "gn:admin1_code":"35.0",
    "gn:admin2_code":"454.0",
    "gn:asciiname":"Salaiya",
    "gn:country_code":"IN",
    "gn:dem":519,
    "gn:feature_class":"P",
    "gn:feature_code":"PPL",
    "gn:name":"Salaiya",
    "gn:population":0,
    "gn:timezone":"Asia/Kolkata",
    "iso:country":"IN",
    "ks:ks_name":"Salaiya",
    "ks:ks_type":"VILLAGE",
    "name:eng_x_preferred":[
        "Salaiya"
    ],
    "wof:name":"Salaiya",
    "wof:placetype":"locality"
},
  "geometry": {"coordinates":[80.17021800000001,22.981427],"type":"Point"}
}