{
  "type": "Feature",
  "properties": {
    "iso:country":"IN",
    "ks:ks_name":"Motukpalli S",
    "ks:ks_pop":110,
    "ks:ks_type":"VILLAGE",
    "name:eng_x_preferred":[
        "Motukpalli S"
    ],
    "wof:name":"Motukpalli S",
    "wof:placetype":"locality",
    "wof:population":110
},
  "geometry": {"coordinates":[79.99695,19.09065],"type":"Point"}
}