{
  "type": "Feature",
  "properties": {
    "gn:admin1_code":"19.0",
    "gn:admin2_code":"573.0",
    "gn:asciiname":"Kenchegaudanakoppal",
    "gn:country_code":"IN",
    "gn:dem":760,
    "gn:feature_class":"P",
    "gn:feature_code":"PPL",
    "gn:name":"Kenchegaudanakoppal",
    "gn:population":0,
    "gn:timezone":"Asia/Kolkata",
    "iso:country":"IN",
    "wof:name":"Kenchegaudanakoppal",
    "wof:placetype":"locality"
},
  "geometry": {"coordinates":[76.80419000000001,12.85129],"type":"Point"}
}