{
  "type": "Feature",
  "properties": {
    "gn:admin1_code":"23",
    "gn:admin2_code":"51.0",
    "gn:asciiname":"Takhtgarh",
    "gn:country_code":"IN",
    "gn:dem":299,
    "gn:feature_class":"P",
    "gn:feature_code":"PPL",
    "gn:name":"Takhtgarh",
    "gn:population":0,
    "gn:timezone":"Asia/Kolkata",
    "iso:country":"IN",
    "wof:name":"Takhtgarh",
    "wof:placetype":"locality"
},
  "geometry": {"coordinates":[76.51094999999999,31.12505],"type":"Point"}
}