{
  "type": "Feature",
  "properties": {
    "gn:admin1_code":"16.0",
    "gn:admin2_code":"529.0",
    "gn:asciiname":"Marathivadi",
    "gn:country_code":"IN",
    "gn:dem":794,
    "gn:feature_class":"P",
    "gn:feature_code":"PPL",
    "gn:name":"Mar\u0101thiv\u0101di",
    "gn:population":0,
    "gn:timezone":"Asia/Kolkata",
    "iso:country":"IN",
    "wof:name":"Marathivadi",
    "wof:placetype":"locality"
},
  "geometry": {"coordinates":[74.03729,15.92732],"type":"Point"}
}