{
  "type": "Feature",
  "properties": {
    "iso:country":"IN",
    "ks:ks_name":"Pipli Kheda",
    "ks:ks_pop":242,
    "ks:ks_type":"HABITATION",
    "name:eng_x_preferred":[
        "Pipli Kheda"
    ],
    "wof:name":"Pipli Kheda",
    "wof:placetype":"locality",
    "wof:population":242
},
  "geometry": {"coordinates":[75.678472,23.508301],"type":"Point"}
}