{
  "type": "Feature",
  "properties": {
    "gn:admin1_code":"36.0",
    "gn:admin2_code":"150.0",
    "gn:asciiname":"Kashinathpur",
    "gn:country_code":"IN",
    "gn:dem":170,
    "gn:feature_class":"P",
    "gn:feature_code":"PPL",
    "gn:name":"K\u0101shin\u0101thpur",
    "gn:population":0,
    "gn:timezone":"Asia/Kolkata",
    "iso:country":"IN",
    "ks:ks_name":"Kashinathpur",
    "ks:ks_pop":774,
    "ks:ks_type":"HABITATION",
    "name:eng_x_preferred":[
        "Kashinathpur"
    ],
    "wof:name":"Kashinathpur",
    "wof:placetype":"locality",
    "wof:population":774
},
  "geometry": {"coordinates":[79.181763,28.462355],"type":"Point"}
}