{
  "type": "Feature",
  "properties": {
    "iso:country":"IN",
    "ks:ks_alt_nam":"BEHEWA TARI",
    "ks:ks_name":"Behewa Tari",
    "ks:ks_pop":50,
    "ks:ks_type":"HABITATION",
    "name:eng_x_preferred":[
        "Behewa Tari"
    ],
    "wof:name":"Behewa Tari",
    "wof:placetype":"locality",
    "wof:population":50
},
  "geometry": {"coordinates":[85.662834,24.626349],"type":"Point"}
}