{
  "type": "Feature",
  "properties": {
    "gn:admin1_code":"35",
    "gn:admin2_code":"461.0",
    "gn:asciiname":"Terhi",
    "gn:country_code":"IN",
    "gn:dem":722,
    "gn:feature_class":"P",
    "gn:feature_code":"PPL",
    "gn:name":"Terhi",
    "gn:population":0,
    "gn:timezone":"Asia/Kolkata",
    "iso:country":"IN",
    "wof:name":"Terhi",
    "wof:placetype":"locality"
},
  "geometry": {"coordinates":[81.30561999999998,22.88491],"type":"Point"}
}