{
  "type": "Feature",
  "properties": {
    "iso:country":"IN",
    "ks:ks_name":"Khacharapada",
    "ks:ks_pop":78,
    "ks:ks_type":"HABITATION",
    "name:eng_x_preferred":[
        "Khacharapada"
    ],
    "wof:name":"Khacharapada",
    "wof:placetype":"locality",
    "wof:population":78
},
  "geometry": {"coordinates":[82.666184,20.109475],"type":"Point"}
}