{
  "type": "Feature",
  "properties": {
    "gn:admin1_code":"16.0",
    "gn:admin2_code":"504.0",
    "gn:asciiname":"Moti Dhawdi",
    "gn:country_code":"IN",
    "gn:dem":447,
    "gn:feature_class":"P",
    "gn:feature_code":"PPL",
    "gn:name":"Moti Dh\u0101wdi",
    "gn:population":0,
    "gn:timezone":"Asia/Kolkata",
    "iso:country":"IN",
    "wof:name":"Moti Dhawdi",
    "wof:placetype":"neighbourhood"
},
  "geometry": {"coordinates":[78.39302000000001,21.13581],"type":"Point"}
}