{
  "type": "Feature",
  "properties": {
    "iso:country":"IN",
    "ks:ks_alt_nam":"hariya musalman tolla",
    "ks:ks_name":"Hariya Musalman Tolla",
    "ks:ks_pop":634,
    "ks:ks_type":"HABITATION",
    "name:eng_x_preferred":[
        "Hariya Musalman Tolla"
    ],
    "wof:name":"Hariya Musalman Tolla",
    "wof:placetype":"locality",
    "wof:population":634
},
  "geometry": {"coordinates":[87.7289,26.05782],"type":"Point"}
}