{
  "type": "Feature",
  "properties": {
    "gn:admin1_code":"35",
    "gn:admin2_code":"458.0",
    "gn:asciiname":"Manpura",
    "gn:country_code":"IN",
    "gn:dem":435,
    "gn:feature_class":"P",
    "gn:feature_code":"PPL",
    "gn:name":"M\u0101npura",
    "gn:population":0,
    "gn:timezone":"Asia/Kolkata",
    "iso:country":"IN",
    "ks:ks_alt_nam":"M\u0101npura",
    "ks:ks_name":"Manpura",
    "ks:ks_type":"VILLAGE",
    "name:eng_x_preferred":[
        "Manpura"
    ],
    "name:eng_x_variant":[
        "M\u0101npura"
    ],
    "wof:name":"Manpura",
    "wof:placetype":"locality"
},
  "geometry": {"coordinates":[77.251457,24.180979],"type":"Point"}
}