{
  "type": "Feature",
  "properties": {
    "iso:country":"IN",
    "ks:ks_alt_nam":"Sakhar boudhwadi",
    "ks:ks_name":"Sakhar Boudhwadi",
    "ks:ks_pop":154,
    "ks:ks_type":"HABITATION",
    "name:eng_x_preferred":[
        "Sakhar Boudhwadi"
    ],
    "wof:name":"Sakhar Boudhwadi",
    "wof:placetype":"locality",
    "wof:population":154
},
  "geometry": {"coordinates":[73.30591,17.040226],"type":"Point"}
}