{
  "type": "Feature",
  "properties": {
    "gn:admin1_code":"21.0",
    "gn:admin2_code":"396.0",
    "gn:asciiname":"Deppaguda",
    "gn:country_code":"IN",
    "gn:dem":375,
    "gn:feature_class":"P",
    "gn:feature_code":"PPL",
    "gn:name":"Depp\u0101guda",
    "gn:population":0,
    "gn:timezone":"Asia/Kolkata",
    "iso:country":"IN",
    "ks:ks_name":"Dhepaguda",
    "ks:ks_pop":296,
    "ks:ks_type":"VILLAGE",
    "name:eng_x_preferred":[
        "Dhepaguda"
    ],
    "name:eng_x_variant":[
        "Deppaguda"
    ],
    "wof:name":"Dhepaguda",
    "wof:placetype":"locality",
    "wof:population":296
},
  "geometry": {"coordinates":[83.526889,19.395113],"type":"Point"}
}