{
  "type": "Feature",
  "properties": {
    "iso:country":"IN",
    "ks:ks_name":"Samadhiyapura",
    "ks:ks_pop":92,
    "ks:ks_type":"HABITATION",
    "name:eng_x_preferred":[
        "Samadhiyapura"
    ],
    "wof:name":"Samadhiyapura",
    "wof:placetype":"locality",
    "wof:population":92
},
  "geometry": {"coordinates":[77.76301100000001,26.671728],"type":"Point"}
}