{
  "type": "Feature",
  "properties": {
    "gn:admin1_code":"36",
    "gn:admin2_code":"186.0",
    "gn:asciiname":"Karahi",
    "gn:country_code":"IN",
    "gn:dem":89,
    "gn:feature_class":"P",
    "gn:feature_code":"PPL",
    "gn:name":"Karahi",
    "gn:population":0,
    "gn:timezone":"Asia/Kolkata",
    "iso:country":"IN",
    "name:ben_x_preferred":[
        "\u0995\u09a1\u09bc\u09be\u0987"
    ],
    "name:eus_x_preferred":[
        "Karahi"
    ],
    "name:kan_x_preferred":[
        "\u0c95\u0ca1\u0cbe\u0caf\u0cbf"
    ],
    "name:mar_x_preferred":[
        "\u0915\u0922\u0908"
    ],
    "name:spa_x_preferred":[
        "Karahi"
    ],
    "name:ukr_x_preferred":[
        "\u041a\u0430\u0440\u0430\u0457"
    ],
    "name:zho_x_preferred":[
        "Karahi"
    ],
    "wof:name":"Karahi",
    "wof:placetype":"locality"
},
  "geometry": {"coordinates":[83.05696999999998,27.02258],"type":"Point"}
}