{
  "type": "Feature",
  "properties": {
    "gn:admin1_code":"36",
    "gn:admin2_code":"159.0",
    "gn:asciiname":"Zainapur Maheshpur",
    "gn:country_code":"IN",
    "gn:dem":145,
    "gn:feature_class":"P",
    "gn:feature_code":"PPL",
    "gn:name":"Zain\u0101pur Maheshpur",
    "gn:population":0,
    "gn:timezone":"Asia/Kolkata",
    "iso:country":"IN",
    "wof:name":"Zainapur Maheshpur",
    "wof:placetype":"locality"
},
  "geometry": {"coordinates":[79.69088000000001,27.47616],"type":"Point"}
}