{
  "type": "Feature",
  "properties": {
    "iso:country":"IN",
    "ks:ks_name":"52 PBN",
    "ks:ks_pop":3,
    "ks:ks_type":"VILLAGE",
    "name:eng_x_preferred":[
        "52 PBN"
    ],
    "wof:name":"52 PBN",
    "wof:placetype":"locality",
    "wof:population":3
},
  "geometry": {"coordinates":[73.720111,29.328333],"type":"Point"}
}