{
  "type": "Feature",
  "properties": {
    "gn:admin1_code":"35",
    "gn:admin2_code":"420.0",
    "gn:asciiname":"Prithwipura",
    "gn:country_code":"IN",
    "gn:dem":157,
    "gn:feature_class":"P",
    "gn:feature_code":"PPL",
    "gn:name":"Prithw\u012bpura",
    "gn:population":0,
    "gn:timezone":"Asia/Kolkata",
    "iso:country":"IN",
    "name:und_x_variant":[
        "Prithw\u012bpura",
        "Semarpura"
    ],
    "wof:name":"Prithwipura",
    "wof:placetype":"locality"
},
  "geometry": {"coordinates":[78.69465,26.53363],"type":"Point"}
}