{
  "type": "Feature",
  "properties": {
    "iso:country":"IN",
    "ks:ks_name":"Baghlaria",
    "ks:ks_pop":61,
    "ks:ks_type":"VILLAGE",
    "name:eng_x_preferred":[
        "Baghlaria"
    ],
    "wof:name":"Baghlaria",
    "wof:placetype":"locality",
    "wof:population":61
},
  "geometry": {"coordinates":[85.83514099999999,24.579762],"type":"Point"}
}