{
  "type": "Feature",
  "properties": {
    "iso:country":"IN",
    "ks:ks_alt_nam":"MUSAHARI",
    "ks:ks_name":"Musahari",
    "ks:ks_pop":240,
    "ks:ks_type":"HABITATION",
    "name:eng_x_preferred":[
        "Musahari"
    ],
    "wof:name":"Musahari",
    "wof:placetype":"locality",
    "wof:population":240
},
  "geometry": {"coordinates":[86.40187899999999,26.248259],"type":"Point"}
}