{
  "type": "Feature",
  "properties": {
    "iso:country":"IN",
    "ks:ks_name":"Thanual",
    "ks:ks_pop":1366,
    "ks:ks_type":"VILLAGE",
    "name:eng_x_preferred":[
        "Thanual"
    ],
    "wof:name":"Thanual",
    "wof:placetype":"locality",
    "wof:population":1366
},
  "geometry": {"coordinates":[86.116152,20.754335],"type":"Point"}
}