{
  "type": "Feature",
  "properties": {
    "iso:country":"IN",
    "ks:ks_name":"Chamaran Purwa",
    "ks:ks_pop":293,
    "ks:ks_type":"HABITATION",
    "name:eng_x_preferred":[
        "Chamaran Purwa"
    ],
    "wof:name":"Chamaran Purwa",
    "wof:placetype":"locality",
    "wof:population":293
},
  "geometry": {"coordinates":[80.998158,28.12109],"type":"Point"}
}