{
  "type": "Feature",
  "properties": {
    "gn:admin1_code":"19.0",
    "gn:admin2_code":"571.0",
    "gn:asciiname":"Gudipalya",
    "gn:country_code":"IN",
    "gn:dem":935,
    "gn:feature_class":"P",
    "gn:feature_code":"PPL",
    "gn:name":"Gudip\u0101lya",
    "gn:population":0,
    "gn:timezone":"Asia/Kolkata",
    "iso:country":"IN",
    "wof:name":"Gudipalya",
    "wof:placetype":"locality"
},
  "geometry": {"coordinates":[77.28159000000002,13.3331],"type":"Point"}
}