{
  "type": "Feature",
  "properties": {
    "iso:country":"IN",
    "ks:ks_name":"Pachasachak",
    "ks:ks_pop":0,
    "ks:ks_type":"VILLAGE",
    "name:eng_x_preferred":[
        "Pachasachak"
    ],
    "wof:name":"Pachasachak",
    "wof:placetype":"locality",
    "wof:population":0
},
  "geometry": {"coordinates":[84.919838,25.254639],"type":"Point"}
}