{
  "type": "Feature",
  "properties": {
    "iso:country":"IN",
    "ks:ks_name":"Kenja Para",
    "ks:ks_pop":502,
    "ks:ks_type":"VILLAGE",
    "name:eng_x_preferred":[
        "Kenja Para"
    ],
    "wof:name":"Kenja Para",
    "wof:placetype":"locality",
    "wof:population":502
},
  "geometry": {"coordinates":[87.34670199999999,22.630404],"type":"Point"}
}