{
  "type": "Feature",
  "properties": {
    "iso:country":"IN",
    "ks:ks_name":"Turkinjor",
    "ks:ks_pop":35,
    "ks:ks_type":"HABITATION",
    "name:eng_x_preferred":[
        "Turkinjor"
    ],
    "wof:name":"Turkinjor",
    "wof:placetype":"locality",
    "wof:population":35
},
  "geometry": {"coordinates":[84.232384,22.510407],"type":"Point"}
}