{
  "type": "Feature",
  "properties": {
    "iso:country":"IN",
    "ks:ks_name":"Narajpur",
    "ks:ks_pop":573,
    "ks:ks_type":"VILLAGE",
    "ks:ks_uagg_main":0,
    "name:eng_x_preferred":[
        "Narajpur"
    ],
    "wof:name":"Narajpur",
    "wof:placetype":"neighbourhood",
    "wof:population":573
},
  "geometry": {"coordinates":[87.593591,21.931239],"type":"Point"}
}