{
  "type": "Feature",
  "properties": {
    "iso:country":"IN",
    "ks:ks_name":"Ahar",
    "ks:ks_pop":728,
    "ks:ks_type":"HABITATION",
    "name:eng_x_preferred":[
        "Ahar"
    ],
    "wof:name":"Ahar",
    "wof:placetype":"locality",
    "wof:population":728
},
  "geometry": {"coordinates":[82.943433,27.291053],"type":"Point"}
}