{
  "type": "Feature",
  "properties": {
    "iso:country":"IN",
    "ks:ks_name":"Alekki",
    "ks:ks_pop":94,
    "ks:ks_type":"HABITATION",
    "name:eng_x_preferred":[
        "Alekki"
    ],
    "wof:name":"Alekki",
    "wof:placetype":"locality",
    "wof:population":94
},
  "geometry": {"coordinates":[75.35301,12.829689],"type":"Point"}
}