{
  "type": "Feature",
  "properties": {
    "gn:admin1_code":"19.0",
    "gn:admin2_code":"566.0",
    "gn:asciiname":"Palanayakanakote",
    "gn:country_code":"IN",
    "gn:dem":561,
    "gn:feature_class":"P",
    "gn:feature_code":"PPL",
    "gn:name":"P\u0101lan\u0101yakanakote",
    "gn:population":0,
    "gn:timezone":"Asia/Kolkata",
    "iso:country":"IN",
    "ks:ks_name":"Palanayakanakote",
    "ks:ks_pop":495,
    "ks:ks_type":"HABITATION",
    "name:eng_x_preferred":[
        "Palanayakanakote"
    ],
    "wof:name":"Palanayakanakote",
    "wof:placetype":"locality",
    "wof:population":495
},
  "geometry": {"coordinates":[76.69712800000001,14.529038],"type":"Point"}
}