{
  "type": "Feature",
  "properties": {
    "gn:admin1_code":"28.0",
    "gn:admin2_code":"343",
    "gn:asciiname":"Achna",
    "gn:country_code":"IN",
    "gn:dem":7,
    "gn:feature_class":"P",
    "gn:feature_code":"PPL",
    "gn:name":"\u0100chna",
    "gn:population":0,
    "gn:timezone":"Asia/Kolkata",
    "iso:country":"IN",
    "name:bul_x_preferred":[
        "\u0410\u0445\u043d\u0430"
    ],
    "name:ceb_x_preferred":[
        "\u00c1chna"
    ],
    "name:deu_x_preferred":[
        "Achna/D\u00fczce"
    ],
    "name:ell_x_preferred":[
        "\u039d\u03c4\u03bf\u03cd\u03b6\u03c4\u03b6\u03b5"
    ],
    "name:fas_x_preferred":[
        "\u0627\u0686\u0646\u0627"
    ],
    "name:fin_x_preferred":[
        "\u00c1chna"
    ],
    "name:fra_x_preferred":[
        "Akhna"
    ],
    "name:hye_x_preferred":[
        "\u0531\u056d\u0576\u0561"
    ],
    "name:kat_x_preferred":[
        "\u10d0\u10ee\u10dc\u10d0"
    ],
    "name:lit_x_preferred":[
        "Achna"
    ],
    "name:msa_x_preferred":[
        "Achna"
    ],
    "name:nno_x_preferred":[
        "\u00c1khna"
    ],
    "name:pol_x_preferred":[
        "Achna"
    ],
    "name:por_x_preferred":[
        "Achna"
    ],
    "name:rus_x_preferred":[
        "\u0410\u0445\u043d\u0430"
    ],
    "name:sco_x_preferred":[
        "Achna"
    ],
    "name:spa_x_preferred":[
        "Achna"
    ],
    "name:swe_x_preferred":[
        "Achna"
    ],
    "name:urd_x_preferred":[
        "\u0627\u062e\u0646\u0627"
    ],
    "wof:name":"Achna",
    "wof:placetype":"locality"
},
  "geometry": {"coordinates":[88.33,22.13278],"type":"Point"}
}