{
  "type": "Feature",
  "properties": {
    "iso:country":"IN",
    "ks:ks_name":"Shyamlal Ka Purwa",
    "ks:ks_pop":50,
    "ks:ks_type":"HABITATION",
    "name:eng_x_preferred":[
        "Shyamlal Ka Purwa"
    ],
    "wof:name":"Shyamlal Ka Purwa",
    "wof:placetype":"locality",
    "wof:population":50
},
  "geometry": {"coordinates":[81.021359,25.187553],"type":"Point"}
}