{
  "type": "Feature",
  "properties": {
    "iso:country":"IN",
    "ks:ks_name":"Kusgaon",
    "ks:ks_pop":8567,
    "ks:ks_type":"VILLAGE",
    "ks:ks_uagg_main":0,
    "name:eng_x_preferred":[
        "Kusgaon"
    ],
    "wof:name":"Kusgaon",
    "wof:placetype":"locality",
    "wof:population":8567
},
  "geometry": {"coordinates":[73.42262700000001,18.741146],"type":"Point"}
}