{
  "type": "Feature",
  "properties": {
    "gn:admin1_code":"24.0",
    "gn:admin2_code":"130.0",
    "gn:asciiname":"Bara",
    "gn:country_code":"IN",
    "gn:dem":423,
    "gn:feature_class":"P",
    "gn:feature_code":"PPL",
    "gn:name":"B\u0101ra",
    "gn:population":0,
    "gn:timezone":"Asia/Kolkata",
    "iso:country":"IN",
    "wof:name":"Bara",
    "wof:placetype":"locality"
},
  "geometry": {"coordinates":[73.69168000000001,24.22647000000001],"type":"Point"}
}