{
  "type": "Feature",
  "properties": {
    "iso:country":"IN",
    "ks:ks_alt_nam":"Gangaram tanda",
    "ks:ks_name":"Gangaram Tanda",
    "ks:ks_pop":66,
    "ks:ks_type":"HABITATION",
    "name:eng_x_preferred":[
        "Gangaram Tanda"
    ],
    "wof:name":"Gangaram Tanda",
    "wof:placetype":"locality",
    "wof:population":66
},
  "geometry": {"coordinates":[77.383938,18.147752],"type":"Point"}
}