{
  "type": "Feature",
  "properties": {
    "iso:country":"IN",
    "ks:ks_alt_nam":"CHORMUNDA",
    "ks:ks_name":"Chormunda",
    "ks:ks_pop":985,
    "ks:ks_type":"HABITATION",
    "name:eng_x_preferred":[
        "Chormunda"
    ],
    "wof:name":"Chormunda",
    "wof:placetype":"locality",
    "wof:population":985
},
  "geometry": {"coordinates":[84.234765,23.354484],"type":"Point"}
}