{
  "type": "Feature",
  "properties": {
    "gn:admin1_code":"16.0",
    "gn:admin2_code":"500.0",
    "gn:asciiname":"Palaskhed Jhalta",
    "gn:country_code":"IN",
    "gn:dem":545,
    "gn:feature_class":"P",
    "gn:feature_code":"PPL",
    "gn:name":"Palaskhed Jh\u0101lta",
    "gn:population":0,
    "gn:timezone":"Asia/Kolkata",
    "iso:country":"IN",
    "wof:name":"Palaskhed Jhalta",
    "wof:placetype":"locality"
},
  "geometry": {"coordinates":[76.10628,19.98834],"type":"Point"}
}