{
  "type": "Feature",
  "properties": {
    "iso:country":"IN",
    "ks:ks_name":"Kahandolpada",
    "ks:ks_pop":352,
    "ks:ks_type":"HABITATION",
    "name:eng_x_preferred":[
        "Kahandolpada"
    ],
    "wof:name":"Kahandolpada",
    "wof:placetype":"locality",
    "wof:population":352
},
  "geometry": {"coordinates":[73.49524599999999,20.199582],"type":"Point"}
}