{
  "type": "Feature",
  "properties": {
    "iso:country":"IN",
    "ks:ks_name":"Chariyani Lagga Dabar",
    "ks:ks_pop":112,
    "ks:ks_type":"HABITATION",
    "name:eng_x_preferred":[
        "Chariyani Lagga Dabar"
    ],
    "wof:name":"Chariyani Lagga Dabar",
    "wof:placetype":"locality",
    "wof:population":112
},
  "geometry": {"coordinates":[78.887851,29.728645],"type":"Point"}
}