{
  "type": "Feature",
  "properties": {
    "iso:country":"IN",
    "ks:ks_name":"Bhanjibeda",
    "ks:ks_pop":153,
    "ks:ks_type":"VILLAGE",
    "name:eng_x_preferred":[
        "Bhanjibeda"
    ],
    "wof:name":"Bhanjibeda",
    "wof:placetype":"locality",
    "wof:population":153
},
  "geometry": {"coordinates":[83.740522,20.495075],"type":"Point"}
}