{
  "type": "Feature",
  "properties": {
    "gn:admin1_code":"38.0",
    "gn:admin2_code":"358.0",
    "gn:asciiname":"Naukurwatoli",
    "gn:country_code":"IN",
    "gn:dem":190,
    "gn:feature_class":"P",
    "gn:feature_code":"PPL",
    "gn:name":"Naukurw\u0101tol\u012b",
    "gn:population":0,
    "gn:timezone":"Asia/Kolkata",
    "iso:country":"IN",
    "wof:name":"Naukurwatoli",
    "wof:placetype":"locality"
},
  "geometry": {"coordinates":[84.27565,24.46761],"type":"Point"}
}