{
  "type": "Feature",
  "properties": {
    "iso:country":"IN",
    "ks:ks_name":"Bena Bandi",
    "ks:ks_pop":10,
    "ks:ks_type":"VILLAGE",
    "name:eng_x_preferred":[
        "Bena Bandi"
    ],
    "wof:name":"Bena Bandi",
    "wof:placetype":"locality",
    "wof:population":10
},
  "geometry": {"coordinates":[87.482266,22.629377],"type":"Point"}
}