{
  "type": "Feature",
  "properties": {
    "iso:country":"IN",
    "ks:ks_name":"Ch Rompivalasa",
    "ks:ks_pop":509,
    "ks:ks_type":"HABITATION",
    "name:eng_x_preferred":[
        "Ch Rompivalasa"
    ],
    "wof:name":"Ch Rompivalasa",
    "wof:placetype":"locality",
    "wof:population":509
},
  "geometry": {"coordinates":[83.762062,18.222738],"type":"Point"}
}