{
  "type": "Feature",
  "properties": {
    "iso:country":"IN",
    "ks:ks_name":"Bordipitha",
    "ks:ks_pop":99,
    "ks:ks_type":"HABITATION",
    "name:eng_x_preferred":[
        "Bordipitha"
    ],
    "wof:name":"Bordipitha",
    "wof:placetype":"locality",
    "wof:population":99
},
  "geometry": {"coordinates":[73.262575,21.65579],"type":"Point"}
}