{
  "type": "Feature",
  "properties": {
    "gn:admin1_code":"34",
    "gn:admin2_code":"232.0",
    "gn:asciiname":"Bahuwara",
    "gn:country_code":"IN",
    "gn:dem":79,
    "gn:feature_class":"P",
    "gn:feature_code":"PPL",
    "gn:name":"Bahuw\u0101ra",
    "gn:population":0,
    "gn:timezone":"Asia/Kolkata",
    "iso:country":"IN",
    "wof:name":"Bahuwara",
    "wof:placetype":"locality"
},
  "geometry": {"coordinates":[83.92749000000001,25.33064],"type":"Point"}
}