{
  "type": "Feature",
  "properties": {
    "gn:admin1_code":"19.0",
    "gn:admin2_code":"571.0",
    "gn:asciiname":"Golhalli",
    "gn:country_code":"IN",
    "gn:dem":815,
    "gn:feature_class":"P",
    "gn:feature_code":"PPL",
    "gn:name":"Golhalli",
    "gn:population":0,
    "gn:timezone":"Asia/Kolkata",
    "iso:country":"IN",
    "ks:ks_name":"Gollahalli",
    "ks:ks_pop":416,
    "ks:ks_type":"VILLAGE",
    "name:eng_x_preferred":[
        "Gollahalli"
    ],
    "name:eng_x_variant":[
        "Golhalli"
    ],
    "wof:name":"Gollahalli",
    "wof:placetype":"locality",
    "wof:population":416
},
  "geometry": {"coordinates":[77.015756,13.246556],"type":"Point"}
}