{
  "type": "Feature",
  "properties": {
    "iso:country":"IN",
    "ks:ks_name":"Karangarh",
    "ks:ks_pop":47,
    "ks:ks_type":"VILLAGE",
    "name:eng_x_preferred":[
        "Karangarh"
    ],
    "wof:name":"Karangarh",
    "wof:placetype":"locality",
    "wof:population":47
},
  "geometry": {"coordinates":[78.21618700000001,24.41791],"type":"Point"}
}