{
  "type": "Feature",
  "properties": {
    "iso:country":"IN",
    "ks:ks_name":"Satigachha",
    "ks:ks_pop":8406,
    "ks:ks_type":"VILLAGE",
    "ks:ks_uagg_main":0,
    "name:eng_x_preferred":[
        "Satigachha"
    ],
    "wof:name":"Satigachha",
    "wof:placetype":"neighbourhood",
    "wof:population":8406
},
  "geometry": {"coordinates":[88.54888699999999,23.16729],"type":"Point"}
}