{
  "type": "Feature",
  "properties": {
    "gn:admin1_code":"39",
    "gn:admin2_code":"61.0",
    "gn:asciiname":"Boransi",
    "gn:country_code":"IN",
    "gn:dem":1788,
    "gn:feature_class":"P",
    "gn:feature_code":"PPL",
    "gn:name":"Bor\u0101nsi",
    "gn:population":0,
    "gn:timezone":"Asia/Kolkata",
    "iso:country":"IN",
    "ks:ks_name":"Buransi",
    "ks:ks_pop":1361,
    "ks:ks_type":"VILLAGE",
    "name:eng_x_preferred":[
        "Buransi"
    ],
    "name:eng_x_variant":[
        "Boransi"
    ],
    "wof:name":"Buransi",
    "wof:placetype":"locality",
    "wof:population":1361
},
  "geometry": {"coordinates":[78.983384,30.078348],"type":"Point"}
}