{
  "type": "Feature",
  "properties": {
    "iso:country":"IN",
    "ks:ks_name":"Hatibondha Pathar",
    "ks:ks_pop":420,
    "ks:ks_type":"VILLAGE",
    "name:eng_x_preferred":[
        "Hatibondha Pathar"
    ],
    "wof:name":"Hatibondha Pathar",
    "wof:placetype":"locality",
    "wof:population":420
},
  "geometry": {"coordinates":[95.089529,27.125179],"type":"Point"}
}