{
  "type": "Feature",
  "properties": {
    "gn:admin1_code":"39.0",
    "gn:admin2_code":"061",
    "gn:asciiname":"Bachhell",
    "gn:country_code":"IN",
    "gn:dem":984,
    "gn:feature_class":"P",
    "gn:feature_code":"PPL",
    "gn:name":"Bachhell",
    "gn:population":0,
    "gn:timezone":"Asia/Kolkata",
    "iso:country":"IN",
    "wof:name":"Bachhell",
    "wof:placetype":"locality"
},
  "geometry": {"coordinates":[78.60642,29.87521],"type":"Point"}
}