{
  "type": "Feature",
  "properties": {
    "gn:admin1_code":"12.0",
    "gn:admin2_code":"14.0",
    "gn:asciiname":"Chanpari",
    "gn:country_code":"IN",
    "gn:dem":2476,
    "gn:feature_class":"P",
    "gn:feature_code":"PPL",
    "gn:name":"Chanp\u0101ri",
    "gn:population":0,
    "gn:timezone":"Asia/Kolkata",
    "iso:country":"IN",
    "wof:name":"Chanpari",
    "wof:placetype":"locality"
},
  "geometry": {"coordinates":[75.31801999999998,33.44814],"type":"Point"}
}