{
  "type": "Feature",
  "properties": {
    "iso:country":"IN",
    "ks:ks_name":"Padaharam",
    "ks:ks_pop":2800,
    "ks:ks_type":"HABITATION",
    "name:eng_x_preferred":[
        "Padaharam"
    ],
    "wof:name":"Padaharam",
    "wof:placetype":"locality",
    "wof:population":2800
},
  "geometry": {"coordinates":[76.408528,9.397265],"type":"Point"}
}