{
  "type": "Feature",
  "properties": {
    "iso:country":"IN",
    "ks:ks_name":"Diara Bijaypur Hissa",
    "ks:ks_pop":509,
    "ks:ks_type":"VILLAGE",
    "name:eng_x_preferred":[
        "Diara Bijaypur Hissa"
    ],
    "wof:name":"Diara Bijaypur Hissa",
    "wof:placetype":"locality",
    "wof:population":509
},
  "geometry": {"coordinates":[84.397864,26.557056],"type":"Point"}
}