{
  "type": "Feature",
  "properties": {
    "gn:admin1_code":"24.0",
    "gn:admin2_code":"103.0",
    "gn:asciiname":"Singhana Dhano",
    "gn:country_code":"IN",
    "gn:dem":343,
    "gn:feature_class":"P",
    "gn:feature_code":"PPL",
    "gn:name":"Singh\u0101na Dh\u0101no",
    "gn:population":0,
    "gn:timezone":"Asia/Kolkata",
    "iso:country":"IN",
    "wof:name":"Singhana Dhano",
    "wof:placetype":"neighbourhood"
},
  "geometry": {"coordinates":[75.85075999999999,28.08768],"type":"Point"}
}