{
  "type": "Feature",
  "properties": {
    "iso:country":"IN",
    "ks:ks_name":"Udepur",
    "ks:ks_pop":152,
    "ks:ks_type":"VILLAGE",
    "name:eng_x_preferred":[
        "Udepur"
    ],
    "wof:name":"Udepur",
    "wof:placetype":"locality",
    "wof:population":152
},
  "geometry": {"coordinates":[82.891267,20.048893],"type":"Point"}
}