{
  "type": "Feature",
  "properties": {
    "gn:admin1_code":"37",
    "gn:admin2_code":"413.0",
    "gn:asciiname":"Gondpal",
    "gn:country_code":"IN",
    "gn:dem":334,
    "gn:feature_class":"P",
    "gn:feature_code":"PPL",
    "gn:name":"Gondp\u0101l",
    "gn:population":0,
    "gn:timezone":"Asia/Kolkata",
    "iso:country":"IN",
    "ks:ks_name":"Gondpal",
    "ks:ks_pop":752,
    "ks:ks_type":"HABITATION",
    "name:eng_x_preferred":[
        "Gondpal"
    ],
    "wof:name":"Gondpal",
    "wof:placetype":"locality",
    "wof:population":752
},
  "geometry": {"coordinates":[80.760189,20.267242],"type":"Point"}
}