{
  "type": "Feature",
  "properties": {
    "iso:country":"IN",
    "ks:ks_name":"Mangalguda",
    "ks:ks_pop":104,
    "ks:ks_type":"VILLAGE",
    "name:eng_x_preferred":[
        "Mangalguda"
    ],
    "wof:name":"Mangalguda",
    "wof:placetype":"locality",
    "wof:population":104
},
  "geometry": {"coordinates":[81.32588199999999,17.817014],"type":"Point"}
}