{
  "type": "Feature",
  "properties": {
    "iso:country":"IN",
    "name:dut_x_preferred":[
        "Karimannoor"
    ],
    "name:eng_x_preferred":[
        "Karimannoor"
    ],
    "name:mal_x_preferred":[
        "\u0d15\u0d30\u0d3f\u0d2e\u0d23\u0d4d\u0d23\u0d42\u0d7c"
    ],
    "qs:name":"Karimannoor",
    "qs:name_adm0":"India",
    "qs:name_adm1":"Kerala",
    "qs:photos":40,
    "qs:photos_1k":8,
    "qs:photos_9k":1,
    "qs:photos_9r":2,
    "qs:photos_all":40,
    "qs:photos_sr":2,
    "qs:placetype":"Town",
    "qs:pop_sr":"0",
    "wd:elevation":60.0,
    "wd:wordcount":198,
    "wof:name":"Karimannoor",
    "wof:placetype":"locality"
},
  "geometry": {"coordinates":[76.779499,9.917618],"type":"Point"}
}