{
  "type": "Feature",
  "properties": {
    "gn:admin1_code":"36.0",
    "gn:admin2_code":"161",
    "gn:asciiname":"Ghughalpir",
    "gn:country_code":"IN",
    "gn:dem":153,
    "gn:feature_class":"P",
    "gn:feature_code":"PPL",
    "gn:name":"Ghughalpir",
    "gn:population":0,
    "gn:timezone":"Asia/Kolkata",
    "iso:country":"IN",
    "name:und_x_variant":[
        "Ghughaipur"
    ],
    "wof:name":"Ghughalpir",
    "wof:placetype":"locality"
},
  "geometry": {"coordinates":[79.03223,26.8075],"type":"Point"}
}