{
  "type": "Feature",
  "properties": {
    "gn:admin1_code":"36.0",
    "gn:admin2_code":"161",
    "gn:asciiname":"Ghughalpir",
    "gn:country_code":"IN",
    "gn:dem":153,
    "gn:feature_class":"P",
    "gn:feature_code":"PPL",
    "gn:name":"Ghughalpir",
    "gn:population":0,
    "gn:timezone":"Asia/Kolkata",
    "iso:country":"IN",
    "ks:ks_name":"Ghughalpur",
    "ks:ks_pop":467,
    "ks:ks_type":"VILLAGE",
    "name:eng_x_preferred":[
        "Ghughalpur"
    ],
    "name:eng_x_variant":[
        "Ghughalpir"
    ],
    "name:und_x_variant":[
        "Ghughaipur"
    ],
    "wof:name":"Ghughalpur",
    "wof:placetype":"locality",
    "wof:population":467
},
  "geometry": {"coordinates":[79.032375,26.80736],"type":"Point"}
}