{
  "type": "Feature",
  "properties": {
    "gn:admin1_code":"36",
    "gn:admin2_code":"168.0",
    "gn:asciiname":"Sikraudha Rath",
    "gn:country_code":"IN",
    "gn:dem":167,
    "gn:feature_class":"P",
    "gn:feature_code":"PPL",
    "gn:name":"Sikraudha R\u0101th",
    "gn:population":0,
    "gn:timezone":"Asia/Kolkata",
    "iso:country":"IN",
    "wof:name":"Sikraudha Rath",
    "wof:placetype":"locality"
},
  "geometry": {"coordinates":[79.43356,25.53487],"type":"Point"}
}