{
  "type": "Feature",
  "properties": {
    "gn:admin1_code":"40",
    "gn:admin2_code":"538.0",
    "gn:asciiname":"Mulamaduta Tanda",
    "gn:country_code":"IN",
    "gn:dem":395,
    "gn:feature_class":"P",
    "gn:feature_code":"PPL",
    "gn:name":"M\u016blamaduta T\u0101nda",
    "gn:population":0,
    "gn:timezone":"Asia/Kolkata",
    "iso:country":"IN",
    "wof:name":"Mulamaduta Tanda",
    "wof:placetype":"locality"
},
  "geometry": {"coordinates":[78.23309999999999,16.22468],"type":"Point"}
}