{
  "type": "Feature",
  "properties": {
    "gn:admin1_code":"36",
    "gn:admin2_code":"188.0",
    "gn:asciiname":"Nawapar",
    "gn:country_code":"IN",
    "gn:dem":81,
    "gn:feature_class":"P",
    "gn:feature_code":"PPL",
    "gn:name":"Naw\u0101p\u0101r",
    "gn:population":0,
    "gn:timezone":"Asia/Kolkata",
    "iso:country":"IN",
    "ks:ks_alt_nam":"Naw\u0101p\u0101r",
    "ks:ks_name":"Nawapar",
    "ks:ks_pop":280,
    "ks:ks_type":"VILLAGE",
    "ks:ks_uagg_main":0,
    "name:eng_x_preferred":[
        "Nawapar"
    ],
    "name:eng_x_variant":[
        "Naw\u0101p\u0101r"
    ],
    "wof:name":"Nawapar",
    "wof:placetype":"neighbourhood",
    "wof:population":280
},
  "geometry": {"coordinates":[83.437949,26.619023],"type":"Point"}
}