{
  "type": "Feature",
  "properties": {
    "iso:country":"IN",
    "ks:ks_alt_nam":"Regulaguda colony",
    "ks:ks_name":"Regulaguda Colony",
    "ks:ks_pop":174,
    "ks:ks_type":"HABITATION",
    "name:eng_x_preferred":[
        "Regulaguda Colony"
    ],
    "wof:name":"Regulaguda Colony",
    "wof:placetype":"locality",
    "wof:population":174
},
  "geometry": {"coordinates":[83.864727,18.748463],"type":"Point"}
}