{
  "type": "Feature",
  "properties": {
    "iso:country":"IN",
    "ks:ks_alt_nam":"Leor\u0101",
    "ks:ks_name":"Leora",
    "ks:ks_pop":1357,
    "ks:ks_type":"VILLAGE",
    "ks:ks_uagg_main":0,
    "name:eng_x_preferred":[
        "Leora"
    ],
    "name:eng_x_variant":[
        "Leor\u0101"
    ],
    "wof:name":"Leora",
    "wof:placetype":"neighbourhood",
    "wof:population":1357
},
  "geometry": {"coordinates":[85.873761,24.223747],"type":"Point"}
}