{
  "type": "Feature",
  "properties": {
    "iso:country":"IN",
    "ks:ks_name":"Talakalabailu",
    "ks:ks_pop":1382,
    "ks:ks_type":"HABITATION",
    "name:eng_x_preferred":[
        "Talakalabailu"
    ],
    "wof:name":"Talakalabailu",
    "wof:placetype":"locality",
    "wof:population":1382
},
  "geometry": {"coordinates":[74.897538,12.966583],"type":"Point"}
}