{
  "type": "Feature",
  "properties": {
    "gn:admin1_code":"16",
    "gn:admin2_code":"511.0",
    "gn:asciiname":"Sawali Tanda",
    "gn:country_code":"IN",
    "gn:dem":468,
    "gn:feature_class":"P",
    "gn:feature_code":"PPL",
    "gn:name":"S\u0101wali T\u0101nda",
    "gn:population":0,
    "gn:timezone":"Asia/Kolkata",
    "iso:country":"IN",
    "wof:name":"Sawali Tanda",
    "wof:placetype":"locality"
},
  "geometry": {"coordinates":[77.43343,18.45096],"type":"Point"}
}