{
  "type": "Feature",
  "properties": {
    "gn:admin1_code":"37",
    "gn:admin2_code":"413.0",
    "gn:asciiname":"Ainhurtola",
    "gn:country_code":"IN",
    "gn:dem":336,
    "gn:feature_class":"P",
    "gn:feature_code":"PPL",
    "gn:name":"Ainh\u016brtola",
    "gn:population":0,
    "gn:timezone":"Asia/Kolkata",
    "iso:country":"IN",
    "ks:ks_alt_nam":"Ainh\u016brtola",
    "ks:ks_name":"Ainhurtola",
    "ks:ks_type":"VILLAGE",
    "name:eng_x_preferred":[
        "Ainhurtola"
    ],
    "name:eng_x_variant":[
        "Ainh\u016brtola"
    ],
    "wof:name":"Ainhurtola",
    "wof:placetype":"locality"
},
  "geometry": {"coordinates":[80.76961300000001,20.183976],"type":"Point"}
}