{
  "type": "Feature",
  "properties": {
    "iso:country":"IN",
    "ks:ks_name":"Pura Bhawani",
    "ks:ks_pop":182,
    "ks:ks_type":"HABITATION",
    "name:eng_x_preferred":[
        "Pura Bhawani"
    ],
    "wof:name":"Pura Bhawani",
    "wof:placetype":"locality",
    "wof:population":182
},
  "geometry": {"coordinates":[81.68695,26.556884],"type":"Point"}
}