{
  "type": "Feature",
  "properties": {
    "iso:country":"IN",
    "ks:ks_alt_nam":"Madhab Pur H.Basti",
    "ks:ks_name":"Madhab Pur H.basti",
    "ks:ks_pop":57,
    "ks:ks_type":"HABITATION",
    "name:eng_x_preferred":[
        "Madhab Pur H.basti"
    ],
    "wof:name":"Madhab Pur H.basti",
    "wof:placetype":"locality",
    "wof:population":57
},
  "geometry": {"coordinates":[92.21375,24.262542],"type":"Point"}
}