{
  "type": "Feature",
  "properties": {
    "iso:country":"IN",
    "ks:ks_name":"Pure Allah Nagar",
    "ks:ks_pop":89,
    "ks:ks_type":"HABITATION",
    "name:eng_x_preferred":[
        "Pure Allah Nagar"
    ],
    "wof:name":"Pure Allah Nagar",
    "wof:placetype":"locality",
    "wof:population":89
},
  "geometry": {"coordinates":[81.4997,26.4534],"type":"Point"}
}