{
  "type": "Feature",
  "properties": {
    "gn:admin1_code":"34",
    "gn:admin2_code":"225.0",
    "gn:asciiname":"Panjwara",
    "gn:country_code":"IN",
    "gn:dem":83,
    "gn:feature_class":"P",
    "gn:feature_code":"PPL",
    "gn:name":"P\u0101njw\u0101ra",
    "gn:population":0,
    "gn:timezone":"Asia/Kolkata",
    "iso:country":"IN",
    "wof:name":"Panjwara",
    "wof:placetype":"locality"
},
  "geometry": {"coordinates":[87.09650999999999,24.85424],"type":"Point"}
}