{
  "type": "Feature",
  "properties": {
    "iso:country":"IN",
    "ks:ks_name":"Dhavdadeh",
    "ks:ks_pop":738,
    "ks:ks_type":"VILLAGE",
    "name:eng_x_preferred":[
        "Dhavdadeh"
    ],
    "wof:name":"Dhavdadeh",
    "wof:placetype":"locality",
    "wof:population":738
},
  "geometry": {"coordinates":[74.705433,23.301194],"type":"Point"}
}