{
  "type": "Feature",
  "properties": {
    "gn:admin1_code":"24.0",
    "gn:admin2_code":"119.0",
    "gn:asciiname":"Ajgara",
    "gn:country_code":"IN",
    "gn:dem":347,
    "gn:feature_class":"P",
    "gn:feature_code":"PPL",
    "gn:name":"Ajgara",
    "gn:population":0,
    "gn:timezone":"Asia/Kolkata",
    "iso:country":"IN",
    "ks:ks_name":"Ajgara",
    "ks:ks_pop":1991,
    "ks:ks_type":"VILLAGE",
    "name:eng_x_preferred":[
        "Ajgara"
    ],
    "wof:name":"Ajgara",
    "wof:placetype":"locality",
    "wof:population":1991
},
  "geometry": {"coordinates":[75.097497,26.014225],"type":"Point"}
}