{
  "type": "Feature",
  "properties": {
    "iso:country":"IN",
    "ks:ks_name":"Tokarpada Falia",
    "ks:ks_pop":348,
    "ks:ks_type":"HABITATION",
    "name:eng_x_preferred":[
        "Tokarpada Falia"
    ],
    "wof:name":"Tokarpada Falia",
    "wof:placetype":"locality",
    "wof:population":348
},
  "geometry": {"coordinates":[73.244417,20.306],"type":"Point"}
}