{
  "type": "Feature",
  "properties": {
    "gn:admin1_code":"34.0",
    "gn:admin2_code":"229.0",
    "gn:asciiname":"Harbanspur",
    "gn:country_code":"IN",
    "gn:dem":69,
    "gn:feature_class":"P",
    "gn:feature_code":"PPL",
    "gn:name":"Harbanspur",
    "gn:population":0,
    "gn:timezone":"Asia/Kolkata",
    "iso:country":"IN",
    "ks:ks_name":"Harbanspur",
    "ks:ks_pop":1616,
    "ks:ks_type":"VILLAGE",
    "ks:ks_uagg_main":0,
    "name:eng_x_preferred":[
        "Harbanspur"
    ],
    "wof:name":"Harbanspur",
    "wof:placetype":"neighbourhood",
    "wof:population":1616
},
  "geometry": {"coordinates":[85.211077,25.146971],"type":"Point"}
}