{
  "type": "Feature",
  "properties": {
    "iso:country":"IN",
    "ks:ks_name":"Dadpur",
    "ks:ks_pop":1379,
    "ks:ks_type":"VILLAGE",
    "ks:ks_uagg_main":0,
    "name:eng_x_preferred":[
        "Dadpur"
    ],
    "wof:name":"Dadpur",
    "wof:placetype":"locality",
    "wof:population":1379
},
  "geometry": {"coordinates":[88.18942300000001,22.540775],"type":"Point"}
}