{
  "type": "Feature",
  "properties": {
    "iso:country":"IN",
    "ks:ks_name":"Jambuguri",
    "ks:ks_pop":725,
    "ks:ks_type":"HABITATION",
    "name:eng_x_preferred":[
        "Jambuguri"
    ],
    "wof:name":"Jambuguri",
    "wof:placetype":"locality",
    "wof:population":725
},
  "geometry": {"coordinates":[90.34040400000001,26.54528],"type":"Point"}
}