{
  "type": "Feature",
  "properties": {
    "iso:country":"IN",
    "ks:ks_name":"Bhandrakeri",
    "ks:ks_pop":39,
    "ks:ks_type":"HABITATION",
    "name:eng_x_preferred":[
        "Bhandrakeri"
    ],
    "wof:name":"Bhandrakeri",
    "wof:placetype":"locality",
    "wof:population":39
},
  "geometry": {"coordinates":[74.99467300000001,14.534883],"type":"Point"}
}