{
  "type": "Feature",
  "properties": {
    "iso:country":"IN",
    "ks:ks_name":"Panditpara",
    "ks:ks_pop":595,
    "ks:ks_type":"HABITATION",
    "name:eng_x_preferred":[
        "Panditpara"
    ],
    "wof:name":"Panditpara",
    "wof:placetype":"locality",
    "wof:population":595
},
  "geometry": {"coordinates":[87.870643,22.591392],"type":"Point"}
}