{
  "type": "Feature",
  "properties": {
    "gn:admin1_code":"19.0",
    "gn:admin2_code":"572.0",
    "gn:asciiname":"Hunsur",
    "gn:country_code":"IN",
    "gn:dem":889,
    "gn:feature_class":"P",
    "gn:feature_code":"PPL",
    "gn:name":"Huns\u016br",
    "gn:population":0,
    "gn:timezone":"Asia/Kolkata",
    "iso:country":"IN",
    "name:ben_x_preferred":[
        "\u09b9\u09c1\u09a8\u09b8\u09c1\u09b0"
    ],
    "name:bpy_x_preferred":[
        "\u09b9\u09c1\u09a8\u09b8\u09c1\u09b0"
    ],
    "name:ceb_x_preferred":[
        "Huns\u016br"
    ],
    "name:ita_x_preferred":[
        "Hunsur"
    ],
    "name:kan_x_preferred":[
        "\u0cb9\u0cc1\u0ca3\u0cb8\u0cc2\u0cb0\u0cc1"
    ],
    "name:mlg_x_preferred":[
        "Hunsur"
    ],
    "name:msa_x_preferred":[
        "Hunsur"
    ],
    "name:new_x_preferred":[
        "\u0939\u0941\u0928\u094d\u0938\u0941\u0930"
    ],
    "name:nld_x_preferred":[
        "Hunsur"
    ],
    "name:por_x_preferred":[
        "Hunsur"
    ],
    "name:rus_x_preferred":[
        "\u0425\u0443\u043d\u0441\u0443\u0440"
    ],
    "name:spa_x_preferred":[
        "Hunsur"
    ],
    "name:swe_x_preferred":[
        "Huns\u016br"
    ],
    "name:vie_x_preferred":[
        "Hunsur"
    ],
    "name:zho_x_preferred":[
        "\u80e1\u6069\u82cf\u5c14"
    ],
    "wof:name":"Hunsur",
    "wof:placetype":"neighbourhood"
},
  "geometry": {"coordinates":[77.71142999999999,13.1802],"type":"Point"}
}