{
  "type": "Feature",
  "properties": {
    "iso:country":"IN",
    "ks:ks_name":"Bichul",
    "ks:ks_pop":378,
    "ks:ks_type":"VILLAGE",
    "name:eng_x_preferred":[
        "Bichul"
    ],
    "wof:name":"Bichul",
    "wof:placetype":"locality",
    "wof:population":378
},
  "geometry": {"coordinates":[80.225694,29.666989],"type":"Point"}
}