{
  "type": "Feature",
  "properties": {
    "iso:country":"IN",
    "ks:ks_name":"Eguva Nallabonthu",
    "ks:ks_pop":45,
    "ks:ks_type":"HABITATION",
    "name:eng_x_preferred":[
        "Eguva Nallabonthu"
    ],
    "wof:name":"Eguva Nallabonthu",
    "wof:placetype":"locality",
    "wof:population":45
},
  "geometry": {"coordinates":[84.045806,18.777317],"type":"Point"}
}