{
  "type": "Feature",
  "properties": {
    "iso:country":"IN",
    "ks:ks_name":"Paschim Para",
    "ks:ks_pop":1654,
    "ks:ks_type":"HABITATION",
    "name:eng_x_preferred":[
        "Paschim Para"
    ],
    "wof:name":"Paschim Para",
    "wof:placetype":"locality",
    "wof:population":1654
},
  "geometry": {"coordinates":[88.149067,21.713636],"type":"Point"}
}