{
  "type": "Feature",
  "properties": {
    "gn:admin1_code":"10.0",
    "gn:admin2_code":"77.0",
    "gn:asciiname":"Barta",
    "gn:country_code":"IN",
    "gn:dem":236,
    "gn:feature_class":"P",
    "gn:feature_code":"PPL",
    "gn:name":"Barta",
    "gn:population":0,
    "gn:timezone":"Asia/Kolkata",
    "iso:country":"IN",
    "name:ceb_x_preferred":[
        "Barta"
    ],
    "name:deu_x_preferred":[
        "Barta"
    ],
    "name:fra_x_preferred":[
        "Barta"
    ],
    "name:hun_x_preferred":[
        "Barta"
    ],
    "name:ita_x_preferred":[
        "Barta"
    ],
    "name:jpn_x_preferred":[
        "\u30d0\u30eb\u30bf"
    ],
    "name:nld_x_preferred":[
        "Barta"
    ],
    "name:pol_x_preferred":[
        "Barta"
    ],
    "name:ron_x_preferred":[
        "Barta"
    ],
    "name:rus_x_preferred":[
        "\u0411\u0430\u0440\u0442\u043e\u0432\u0430"
    ],
    "name:slk_x_preferred":[
        "Barta"
    ],
    "wof:name":"Barta",
    "wof:placetype":"locality"
},
  "geometry": {"coordinates":[76.20939,29.81582],"type":"Point"}
}