{
  "type": "Feature",
  "properties": {
    "iso:country":"IN",
    "ks:ks_name":"Laloti",
    "ks:ks_pop":10,
    "ks:ks_type":"VILLAGE",
    "name:eng_x_preferred":[
        "Laloti"
    ],
    "wof:name":"Laloti",
    "wof:placetype":"locality",
    "wof:population":10
},
  "geometry": {"coordinates":[79.23814299999999,30.184936],"type":"Point"}
}