{
  "type": "Feature",
  "properties": {
    "iso:country":"IN",
    "ks:ks_name":"Kotiya Deegor",
    "ks:ks_pop":776,
    "ks:ks_type":"HABITATION",
    "name:eng_x_preferred":[
        "Kotiya Deegor"
    ],
    "wof:name":"Kotiya Deegor",
    "wof:placetype":"locality",
    "wof:population":776
},
  "geometry": {"coordinates":[82.902344,27.385529],"type":"Point"}
}