{
  "type": "Feature",
  "properties": {
    "gn:admin1_code":"11",
    "gn:admin2_code":"24.0",
    "gn:asciiname":"Dadh Jikla",
    "gn:country_code":"IN",
    "gn:dem":1090,
    "gn:feature_class":"P",
    "gn:feature_code":"PPL",
    "gn:name":"D\u0101dh Jikla",
    "gn:population":0,
    "gn:timezone":"Asia/Kolkata",
    "iso:country":"IN",
    "wof:name":"Dadh Jikla",
    "wof:placetype":"locality"
},
  "geometry": {"coordinates":[76.42001999999999,32.14518],"type":"Point"}
}