{
  "type": "Feature",
  "properties": {
    "iso:country":"IN",
    "ks:ks_name":"Diguvarudi",
    "ks:ks_pop":114,
    "ks:ks_type":"HABITATION",
    "name:eng_x_preferred":[
        "Diguvarudi"
    ],
    "wof:name":"Diguvarudi",
    "wof:placetype":"locality",
    "wof:population":114
},
  "geometry": {"coordinates":[83.085027,18.6498],"type":"Point"}
}