{
  "type": "Feature",
  "properties": {
    "gn:admin1_code":"2.0",
    "gn:admin2_code":"543.0",
    "gn:asciiname":"Kannammapeta",
    "gn:country_code":"IN",
    "gn:dem":135,
    "gn:feature_class":"P",
    "gn:feature_code":"PPL",
    "gn:name":"Kannammapeta",
    "gn:population":0,
    "gn:timezone":"Asia/Kolkata",
    "iso:country":"IN",
    "wof:name":"Kannammapeta",
    "wof:placetype":"locality"
},
  "geometry": {"coordinates":[83.30412,18.63357],"type":"Point"}
}