{
  "type": "Feature",
  "properties": {
    "gn:admin1_code":"09",
    "gn:admin2_code":"470.0",
    "gn:asciiname":"Ved",
    "gn:country_code":"IN",
    "gn:dem":24,
    "gn:feature_class":"P",
    "gn:feature_code":"PPL",
    "gn:name":"Ved",
    "gn:population":0,
    "gn:timezone":"Asia/Kolkata",
    "iso:country":"IN",
    "wof:name":"Ved",
    "wof:placetype":"locality"
},
  "geometry": {"coordinates":[71.50905999999998,23.64645],"type":"Point"}
}