{
  "type": "Feature",
  "properties": {
    "iso:country":"IN",
    "ks:ks_name":"Senpara",
    "ks:ks_pop":663,
    "ks:ks_type":"VILLAGE",
    "ks:ks_uagg_main":0,
    "name:eng_x_preferred":[
        "Senpara"
    ],
    "wof:name":"Senpara",
    "wof:placetype":"neighbourhood",
    "wof:population":663
},
  "geometry": {"coordinates":[88.07579200000001,23.681955],"type":"Point"}
}