{
  "type": "Feature",
  "properties": {
    "gn:admin1_code":"11",
    "gn:admin2_code":"33.0",
    "gn:asciiname":"Khobtuwari",
    "gn:country_code":"IN",
    "gn:dem":2324,
    "gn:feature_class":"P",
    "gn:feature_code":"PPL",
    "gn:name":"Khobtuw\u0101ri",
    "gn:population":0,
    "gn:timezone":"Asia/Kolkata",
    "iso:country":"IN",
    "wof:name":"Khobtuwari",
    "wof:placetype":"locality"
},
  "geometry": {"coordinates":[77.92531,31.22674],"type":"Point"}
}