{
  "type": "Feature",
  "properties": {
    "gn:admin1_code":"35.0",
    "gn:admin2_code":"441.0",
    "gn:asciiname":"Lonsarai Khurd",
    "gn:country_code":"IN",
    "gn:dem":198,
    "gn:feature_class":"P",
    "gn:feature_code":"PPL",
    "gn:name":"Lonsar\u0101i Khurd",
    "gn:population":0,
    "gn:timezone":"Asia/Kolkata",
    "iso:country":"IN",
    "ks:ks_name":"Lonsara Khurd",
    "ks:ks_pop":1869,
    "ks:ks_type":"VILLAGE",
    "ks:ks_uagg_main":0,
    "name:eng_x_preferred":[
        "Lonsara Khurd"
    ],
    "wof:name":"Lonsara Khurd",
    "wof:placetype":"neighbourhood",
    "wof:population":1869
},
  "geometry": {"coordinates":[74.98345399999999,22.012818],"type":"Point"}
}