{
  "type": "Feature",
  "properties": {
    "iso:country":"IN",
    "ks:ks_name":"Tharnes",
    "ks:ks_pop":40,
    "ks:ks_type":"HABITATION",
    "name:eng_x_preferred":[
        "Tharnes"
    ],
    "wof:name":"Tharnes",
    "wof:placetype":"locality",
    "wof:population":40
},
  "geometry": {"coordinates":[69.761444,21.83025],"type":"Point"}
}