{
  "type": "Feature",
  "properties": {
    "iso:country":"IN",
    "ks:ks_alt_nam":"CHIRIYA",
    "ks:ks_name":"Chiriya",
    "ks:ks_pop":103,
    "ks:ks_type":"HABITATION",
    "name:eng_x_preferred":[
        "Chiriya"
    ],
    "wof:name":"Chiriya",
    "wof:placetype":"locality",
    "wof:population":103
},
  "geometry": {"coordinates":[85.598609,22.49268],"type":"Point"}
}