{
  "type": "Feature",
  "properties": {
    "iso:country":"IN",
    "ks:ks_name":"Jugpur",
    "ks:ks_pop":1200,
    "ks:ks_type":"VILLAGE",
    "name:eng_x_preferred":[
        "Jugpur"
    ],
    "wof:name":"Jugpur",
    "wof:placetype":"locality",
    "wof:population":1200
},
  "geometry": {"coordinates":[88.406519,23.579219],"type":"Point"}
}