{
  "type": "Feature",
  "properties": {
    "iso:country":"IN",
    "ks:ks_name":"Malli",
    "ks:ks_pop":18,
    "ks:ks_type":"VILLAGE",
    "name:eng_x_preferred":[
        "Malli"
    ],
    "wof:name":"Malli",
    "wof:placetype":"locality",
    "wof:population":18
},
  "geometry": {"coordinates":[78.659882,30.012841],"type":"Point"}
}