{
  "type": "Feature",
  "properties": {
    "iso:country":"IN",
    "ks:ks_alt_nam":"Pong-Cherra",
    "ks:ks_name":"Pong-cherra",
    "ks:ks_pop":277,
    "ks:ks_type":"HABITATION",
    "name:eng_x_preferred":[
        "Pong-cherra"
    ],
    "wof:name":"Pong-cherra",
    "wof:placetype":"locality",
    "wof:population":277
},
  "geometry": {"coordinates":[92.07450300000001,24.17412],"type":"Point"}
}