{
  "type": "Feature",
  "properties": {
    "iso:country":"IN",
    "ks:ks_name":"Varahasandra",
    "ks:ks_pop":479,
    "ks:ks_type":"VILLAGE",
    "name:eng_x_preferred":[
        "Varahasandra"
    ],
    "wof:name":"Varahasandra",
    "wof:placetype":"neighbourhood",
    "wof:population":479
},
  "geometry": {"coordinates":[77.49089600000001,12.877191],"type":"Point"}
}