{
  "type": "Feature",
  "properties": {
    "iso:country":"IN",
    "ks:ks_name":"Dimiriguda",
    "ks:ks_pop":56,
    "ks:ks_type":"VILLAGE",
    "name:eng_x_preferred":[
        "Dimiriguda"
    ],
    "wof:name":"Dimiriguda",
    "wof:placetype":"locality",
    "wof:population":56
},
  "geometry": {"coordinates":[83.673818,19.590043],"type":"Point"}
}