{
  "type": "Feature",
  "properties": {
    "iso:country":"IN",
    "ks:ks_name":"Borichibari",
    "ks:ks_pop":974,
    "ks:ks_type":"HABITATION",
    "name:eng_x_preferred":[
        "Borichibari"
    ],
    "wof:name":"Borichibari",
    "wof:placetype":"locality",
    "wof:population":974
},
  "geometry": {"coordinates":[73.463275,20.302981],"type":"Point"}
}