{
  "type": "Feature",
  "properties": {
    "gn:admin1_code":"11.0",
    "gn:admin2_code":"32.0",
    "gn:asciiname":"Drabala",
    "gn:country_code":"IN",
    "gn:dem":1426,
    "gn:feature_class":"P",
    "gn:feature_code":"PPL",
    "gn:name":"Dr\u0101bala",
    "gn:population":0,
    "gn:timezone":"Asia/Kolkata",
    "iso:country":"IN",
    "wof:name":"Drabala",
    "wof:placetype":"locality"
},
  "geometry": {"coordinates":[77.32491,30.95132000000001],"type":"Point"}
}