{
  "type": "Feature",
  "properties": {
    "iso:country":"IN",
    "ks:ks_name":"Sarain Raja",
    "ks:ks_pop":330,
    "ks:ks_type":"VILLAGE",
    "ks:ks_uagg_main":0,
    "name:eng_x_preferred":[
        "Sarain Raja"
    ],
    "wof:name":"Sarain Raja",
    "wof:placetype":"neighbourhood",
    "wof:population":330
},
  "geometry": {"coordinates":[80.69701000000001,27.803775],"type":"Point"}
}