{
  "type": "Feature",
  "properties": {
    "gn:admin1_code":"2",
    "gn:admin2_code":"544.0",
    "gn:asciiname":"Badanapadu",
    "gn:country_code":"IN",
    "gn:dem":116,
    "gn:feature_class":"P",
    "gn:feature_code":"PPL",
    "gn:name":"B\u0101danap\u0101du",
    "gn:population":0,
    "gn:timezone":"Asia/Kolkata",
    "iso:country":"IN",
    "ks:ks_alt_nam":"B\u0101danap\u0101du",
    "ks:ks_name":"Badanapadu",
    "ks:ks_pop":108,
    "ks:ks_type":"VILLAGE",
    "name:eng_x_preferred":[
        "Badanapadu"
    ],
    "name:eng_x_variant":[
        "B\u0101danap\u0101du"
    ],
    "wof:name":"Badanapadu",
    "wof:placetype":"locality",
    "wof:population":108
},
  "geometry": {"coordinates":[82.75364500000001,17.796702],"type":"Point"}
}