{
  "type": "Feature",
  "properties": {
    "iso:country":"IN",
    "ks:ks_name":"Ratanpura Ghata",
    "ks:ks_pop":427,
    "ks:ks_type":"VILLAGE",
    "ks:ks_uagg_main":0,
    "name:eng_x_preferred":[
        "Ratanpura Ghata"
    ],
    "wof:name":"Ratanpura Ghata",
    "wof:placetype":"neighbourhood",
    "wof:population":427
},
  "geometry": {"coordinates":[74.389436,25.995568],"type":"Point"}
}