{
  "type": "Feature",
  "properties": {
    "iso:country":"IN",
    "ks:ks_name":"Budhistpara",
    "ks:ks_pop":111,
    "ks:ks_type":"HABITATION",
    "name:eng_x_preferred":[
        "Budhistpara"
    ],
    "wof:name":"Budhistpara",
    "wof:placetype":"locality",
    "wof:population":111
},
  "geometry": {"coordinates":[80.802172,20.694715],"type":"Point"}
}