{
  "type": "Feature",
  "properties": {
    "iso:country":"IN",
    "ks:ks_name":"Bhains Kot",
    "ks:ks_pop":37,
    "ks:ks_type":"VILLAGE",
    "name:eng_x_preferred":[
        "Bhains Kot"
    ],
    "wof:name":"Bhains Kot",
    "wof:placetype":"locality",
    "wof:population":37
},
  "geometry": {"coordinates":[78.870672,30.104222],"type":"Point"}
}