{
  "type": "Feature",
  "properties": {
    "iso:country":"IN",
    "ks:ks_alt_nam":"SRF Nagar",
    "ks:ks_name":"Srf Nagar",
    "ks:ks_pop":200,
    "ks:ks_type":"HABITATION",
    "name:eng_x_preferred":[
        "Srf Nagar"
    ],
    "wof:name":"Srf Nagar",
    "wof:placetype":"locality",
    "wof:population":200
},
  "geometry": {"coordinates":[78.566793,10.630208],"type":"Point"}
}