{
  "type": "Feature",
  "properties": {
    "iso:country":"IN",
    "ks:ks_name":"Kodugudde",
    "ks:ks_pop":929,
    "ks:ks_type":"HABITATION",
    "name:eng_x_preferred":[
        "Kodugudde"
    ],
    "wof:name":"Kodugudde",
    "wof:placetype":"locality",
    "wof:population":929
},
  "geometry": {"coordinates":[74.814285,13.236481],"type":"Point"}
}