{
  "type": "Feature",
  "properties": {
    "gn:admin1_code":"21",
    "gn:admin2_code":"397.0",
    "gn:asciiname":"Mohara",
    "gn:country_code":"IN",
    "gn:dem":285,
    "gn:feature_class":"P",
    "gn:feature_code":"PPL",
    "gn:name":"Mohara",
    "gn:population":0,
    "gn:timezone":"Asia/Kolkata",
    "iso:country":"IN",
    "name:ceb_x_preferred":[
        "Mo\u1e29ar\u0101"
    ],
    "name:fas_x_preferred":[
        "\u0645\u062d\u0631\u0627"
    ],
    "name:msa_x_preferred":[
        "Mohara"
    ],
    "name:swe_x_preferred":[
        "Mo\u1e29ar\u0101"
    ],
    "wof:name":"Mohara",
    "wof:placetype":"locality"
},
  "geometry": {"coordinates":[82.49609,19.86684],"type":"Point"}
}