{
  "type": "Feature",
  "properties": {
    "iso:country":"IN",
    "ks:ks_name":"Birkera",
    "ks:ks_pop":297,
    "ks:ks_type":"VILLAGE",
    "name:eng_x_preferred":[
        "Birkera"
    ],
    "wof:name":"Birkera",
    "wof:placetype":"locality",
    "wof:population":297
},
  "geometry": {"coordinates":[84.232592,22.989488],"type":"Point"}
}