{
  "type": "Feature",
  "properties": {
    "iso:country":"IN",
    "ks:ks_name":"Kattampatti",
    "ks:ks_pop":1142,
    "ks:ks_type":"HABITATION",
    "name:eng_x_preferred":[
        "Kattampatti"
    ],
    "wof:name":"Kattampatti",
    "wof:placetype":"locality",
    "wof:population":1142
},
  "geometry": {"coordinates":[78.120926,12.258935],"type":"Point"}
}