{
  "type": "Feature",
  "properties": {
    "gn:admin1_code":"36",
    "gn:admin2_code":"134.0",
    "gn:asciiname":"Mausanpur Suleman Sakhopur",
    "gn:country_code":"IN",
    "gn:dem":245,
    "gn:feature_class":"P",
    "gn:feature_code":"PPL",
    "gn:name":"Mausanpur Sulem\u0101n Sakhopur",
    "gn:population":0,
    "gn:timezone":"Asia/Kolkata",
    "iso:country":"IN",
    "wof:name":"Mausanpur Suleman Sakhopur",
    "wof:placetype":"locality"
},
  "geometry": {"coordinates":[78.41495999999999,29.40858],"type":"Point"}
}