{
  "type": "Feature",
  "properties": {
    "gn:admin1_code":"35.0",
    "gn:admin2_code":"427.0",
    "gn:asciiname":"Barkhuo",
    "gn:country_code":"IN",
    "gn:dem":493,
    "gn:feature_class":"P",
    "gn:feature_code":"PPL",
    "gn:name":"Barkhuo",
    "gn:population":0,
    "gn:timezone":"Asia/Kolkata",
    "iso:country":"IN",
    "wof:name":"Barkhuo",
    "wof:placetype":"locality"
},
  "geometry": {"coordinates":[78.86813000000002,23.68265],"type":"Point"}
}