{
  "type": "Feature",
  "properties": {
    "iso:country":"IN",
    "ks:ks_alt_nam":"nambram kunnu",
    "ks:ks_name":"Nambram Kunnu",
    "ks:ks_pop":285,
    "ks:ks_type":"HABITATION",
    "name:eng_x_preferred":[
        "Nambram Kunnu"
    ],
    "wof:name":"Nambram Kunnu",
    "wof:placetype":"locality",
    "wof:population":285
},
  "geometry": {"coordinates":[75.793818,11.526049],"type":"Point"}
}