{
  "type": "Feature",
  "properties": {
    "iso:country":"IN",
    "ks:ks_name":"C Kankanadu",
    "ks:ks_pop":455,
    "ks:ks_type":"HABITATION",
    "name:eng_x_preferred":[
        "C Kankanadu"
    ],
    "wof:name":"C Kankanadu",
    "wof:placetype":"locality",
    "wof:population":455
},
  "geometry": {"coordinates":[85.817553,20.017798],"type":"Point"}
}