{
  "type": "Feature",
  "properties": {
    "gn:admin1_code":"2.0",
    "gn:admin2_code":"544.0",
    "gn:asciiname":"Khilomangi",
    "gn:country_code":"IN",
    "gn:dem":954,
    "gn:feature_class":"P",
    "gn:feature_code":"PPL",
    "gn:name":"Khilomangi",
    "gn:population":0,
    "gn:timezone":"Asia/Kolkata",
    "iso:country":"IN",
    "wof:name":"Khilomangi",
    "wof:placetype":"locality"
},
  "geometry": {"coordinates":[82.42822,18.31985],"type":"Point"}
}