{
  "type": "Feature",
  "properties": {
    "iso:country":"IN",
    "ks:ks_name":"Tengeri",
    "ks:ks_pop":226,
    "ks:ks_type":"VILLAGE",
    "name:eng_x_preferred":[
        "Tengeri"
    ],
    "wof:name":"Tengeri",
    "wof:placetype":"locality",
    "wof:population":226
},
  "geometry": {"coordinates":[83.770853,20.114419],"type":"Point"}
}