{
  "type": "Feature",
  "properties": {
    "gn:admin1_code":"35",
    "gn:admin2_code":"445.0",
    "gn:asciiname":"Chichlaya Kalan",
    "gn:country_code":"IN",
    "gn:dem":311,
    "gn:feature_class":"P",
    "gn:feature_code":"PPL",
    "gn:name":"Chichl\u0101ya Kal\u0101n",
    "gn:population":0,
    "gn:timezone":"Asia/Kolkata",
    "iso:country":"IN",
    "wof:name":"Chichlaya Kalan",
    "wof:placetype":"locality"
},
  "geometry": {"coordinates":[77.37735000000001,22.74826],"type":"Point"}
}