{
  "type": "Feature",
  "properties": {
    "gn:admin1_code":"25.0",
    "gn:admin2_code":"608.0",
    "gn:asciiname":"Jedappatti",
    "gn:country_code":"IN",
    "gn:dem":273,
    "gn:feature_class":"P",
    "gn:feature_code":"PPL",
    "gn:name":"Jedappatti",
    "gn:population":0,
    "gn:timezone":"Asia/Kolkata",
    "iso:country":"IN",
    "wof:name":"Jedappatti",
    "wof:placetype":"locality"
},
  "geometry": {"coordinates":[77.94718,11.71003],"type":"Point"}
}