{
  "type": "Feature",
  "properties": {
    "iso:country":"IN",
    "ks:ks_name":"Baraikhuwa",
    "ks:ks_pop":515,
    "ks:ks_type":"VILLAGE",
    "ks:ks_uagg_main":0,
    "name:eng_x_preferred":[
        "Baraikhuwa"
    ],
    "wof:name":"Baraikhuwa",
    "wof:placetype":"neighbourhood",
    "wof:population":515
},
  "geometry": {"coordinates":[93.73560000000001,26.667587],"type":"Point"}
}