{
  "type": "Feature",
  "properties": {
    "iso:country":"IN",
    "ks:ks_name":"Gadiyappanahatti",
    "ks:ks_pop":162,
    "ks:ks_type":"HABITATION",
    "name:eng_x_preferred":[
        "Gadiyappanahatti"
    ],
    "wof:name":"Gadiyappanahatti",
    "wof:placetype":"locality",
    "wof:population":162
},
  "geometry": {"coordinates":[76.388915,13.873515],"type":"Point"}
}