{
  "type": "Feature",
  "properties": {
    "gn:admin1_code":"35",
    "gn:admin2_code":"447.0",
    "gn:asciiname":"Jhapandri",
    "gn:country_code":"IN",
    "gn:dem":1038,
    "gn:feature_class":"P",
    "gn:feature_code":"PPL",
    "gn:name":"Jhapandri",
    "gn:population":0,
    "gn:timezone":"Asia/Kolkata",
    "iso:country":"IN",
    "wof:name":"Jhapandri",
    "wof:placetype":"locality"
},
  "geometry": {"coordinates":[77.45841,21.51721],"type":"Point"}
}