{
  "type": "Feature",
  "properties": {
    "iso:country":"IN",
    "ks:ks_alt_nam":"SORENGBASA",
    "ks:ks_name":"Sorengbasa",
    "ks:ks_pop":96,
    "ks:ks_type":"HABITATION",
    "name:eng_x_preferred":[
        "Sorengbasa"
    ],
    "wof:name":"Sorengbasa",
    "wof:placetype":"locality",
    "wof:population":96
},
  "geometry": {"coordinates":[85.727963,22.214098],"type":"Point"}
}