{
  "type": "Feature",
  "properties": {
    "iso:country":"IN",
    "ks:ks_name":"Charmkrwadi",
    "ks:ks_pop":262,
    "ks:ks_type":"HABITATION",
    "ks:ks_uagg_main":0,
    "name:eng_x_preferred":[
        "Charmkrwadi"
    ],
    "wof:name":"Charmkrwadi",
    "wof:placetype":"neighbourhood",
    "wof:population":262
},
  "geometry": {"coordinates":[73.630589,17.058347],"type":"Point"}
}