{
  "type": "Feature",
  "properties": {
    "iso:country":"IN",
    "ks:ks_name":"Kansa Patti",
    "ks:ks_type":"VILLAGE",
    "name:eng_x_preferred":[
        "Kansa Patti"
    ],
    "wof:name":"Kansa Patti",
    "wof:placetype":"locality"
},
  "geometry": {"coordinates":[82.90771599999999,26.341224],"type":"Point"}
}