{
  "type": "Feature",
  "properties": {
    "iso:country":"IN",
    "ks:ks_name":"Pasalavandlapalle",
    "ks:ks_pop":65,
    "ks:ks_type":"HABITATION",
    "name:eng_x_preferred":[
        "Pasalavandlapalle"
    ],
    "wof:name":"Pasalavandlapalle",
    "wof:placetype":"locality",
    "wof:population":65
},
  "geometry": {"coordinates":[78.550618,13.923069],"type":"Point"}
}