{
  "type": "Feature",
  "properties": {
    "gn:admin1_code":"21",
    "gn:admin2_code":"390.0",
    "gn:asciiname":"Jamdari",
    "gn:country_code":"IN",
    "gn:dem":495,
    "gn:feature_class":"P",
    "gn:feature_code":"PPL",
    "gn:name":"Jamd\u0101ri",
    "gn:population":0,
    "gn:timezone":"Asia/Kolkata",
    "iso:country":"IN",
    "wof:name":"Jamdari",
    "wof:placetype":"locality"
},
  "geometry": {"coordinates":[83.55858000000001,19.99669],"type":"Point"}
}