{
  "type": "Feature",
  "properties": {
    "gn:admin1_code":"39",
    "gn:admin2_code":"61.0",
    "gn:asciiname":"Budesu",
    "gn:country_code":"IN",
    "gn:dem":1617,
    "gn:feature_class":"P",
    "gn:feature_code":"PPL",
    "gn:name":"Budesu",
    "gn:population":0,
    "gn:timezone":"Asia/Kolkata",
    "iso:country":"IN",
    "wof:name":"Budesu",
    "wof:placetype":"locality"
},
  "geometry": {"coordinates":[78.88346999999997,30.18784],"type":"Point"}
}