{
  "type": "Feature",
  "properties": {
    "gn:admin1_code":"23.0",
    "gn:admin2_code":"35.0",
    "gn:asciiname":"Kilaspur",
    "gn:country_code":"IN",
    "gn:dem":333,
    "gn:feature_class":"P",
    "gn:feature_code":"PPL",
    "gn:name":"Kil\u0101spur",
    "gn:population":0,
    "gn:timezone":"Asia/Kolkata",
    "iso:country":"IN",
    "wof:name":"Kilaspur",
    "wof:placetype":"locality"
},
  "geometry": {"coordinates":[75.59703,32.31937],"type":"Point"}
}