{
  "type": "Feature",
  "properties": {
    "iso:country":"IN",
    "ks:ks_alt_nam":"Chandri camp",
    "ks:ks_name":"Chandri Camp",
    "ks:ks_pop":140,
    "ks:ks_type":"HABITATION",
    "name:eng_x_preferred":[
        "Chandri Camp"
    ],
    "wof:name":"Chandri Camp",
    "wof:placetype":"locality",
    "wof:population":140
},
  "geometry": {"coordinates":[76.954984,15.698875],"type":"Point"}
}