{
  "type": "Feature",
  "properties": {
    "iso:country":"IN",
    "ks:ks_alt_nam":"Cheerane.H.C.",
    "ks:ks_name":"Cheerane.h.c.",
    "ks:ks_pop":28,
    "ks:ks_type":"HABITATION",
    "name:eng_x_preferred":[
        "Cheerane.h.c."
    ],
    "wof:name":"Cheerane.h.c.",
    "wof:placetype":"locality",
    "wof:population":28
},
  "geometry": {"coordinates":[75.839167,12.224444],"type":"Point"}
}