{
  "type": "Feature",
  "properties": {
    "iso:country":"IN",
    "ks:ks_name":"Chamaran Purwa",
    "ks:ks_pop":236,
    "ks:ks_type":"HABITATION",
    "ks:ks_uagg_main":0,
    "name:eng_x_preferred":[
        "Chamaran Purwa"
    ],
    "wof:name":"Chamaran Purwa",
    "wof:placetype":"neighbourhood",
    "wof:population":236
},
  "geometry": {"coordinates":[80.03931799999999,26.811009],"type":"Point"}
}