{
  "type": "Feature",
  "properties": {
    "gn:admin1_code":"35",
    "gn:admin2_code":"429.0",
    "gn:asciiname":"Naina",
    "gn:country_code":"IN",
    "gn:dem":333,
    "gn:feature_class":"P",
    "gn:feature_code":"PPL",
    "gn:name":"Naina",
    "gn:population":0,
    "gn:timezone":"Asia/Kolkata",
    "iso:country":"IN",
    "ks:ks_name":"Naina",
    "ks:ks_pop":276,
    "ks:ks_type":"VILLAGE",
    "name:eng_x_preferred":[
        "Naina"
    ],
    "wof:name":"Naina",
    "wof:placetype":"locality",
    "wof:population":276
},
  "geometry": {"coordinates":[81.031935,24.436519],"type":"Point"}
}