{
  "type": "Feature",
  "properties": {
    "gn:admin1_code":"23.0",
    "gn:admin2_code":"52.0",
    "gn:asciiname":"Gunun Majra",
    "gn:country_code":"IN",
    "gn:dem":318,
    "gn:feature_class":"P",
    "gn:feature_code":"PPL",
    "gn:name":"Gunun M\u0101jra",
    "gn:population":0,
    "gn:timezone":"Asia/Kolkata",
    "iso:country":"IN",
    "wof:name":"Gunun Majra",
    "wof:placetype":"locality"
},
  "geometry": {"coordinates":[76.63191999999999,30.85123],"type":"Point"}
}