{
  "type": "Feature",
  "properties": {
    "iso:country":"IN",
    "ks:ks_name":"Kadhariya",
    "ks:ks_pop":343,
    "ks:ks_type":"HABITATION",
    "name:eng_x_preferred":[
        "Kadhariya"
    ],
    "wof:name":"Kadhariya",
    "wof:placetype":"locality",
    "wof:population":343
},
  "geometry": {"coordinates":[85.135131,24.772174],"type":"Point"}
}