{
  "type": "Feature",
  "properties": {
    "gn:admin1_code":"36",
    "gn:admin2_code":"200.0",
    "gn:asciiname":"Kaithi",
    "gn:country_code":"IN",
    "gn:dem":309,
    "gn:feature_class":"P",
    "gn:feature_code":"PPL",
    "gn:name":"Kaithi",
    "gn:population":0,
    "gn:timezone":"Asia/Kolkata",
    "iso:country":"IN",
    "ks:ks_name":"Kaithi",
    "ks:ks_pop":843,
    "ks:ks_type":"VILLAGE",
    "name:bih_x_preferred":[
        "\u0915\u0948\u0925\u0940"
    ],
    "name:ces_x_preferred":[
        "Kaithi"
    ],
    "name:deu_x_preferred":[
        "Kaithi-Schrift"
    ],
    "name:eng_x_preferred":[
        "Kaithi"
    ],
    "name:fin_x_preferred":[
        "Kaithi"
    ],
    "name:fra_x_preferred":[
        "Ka\u00efthi"
    ],
    "name:hin_x_preferred":[
        "\u0915\u0948\u0925\u0940"
    ],
    "name:ind_x_preferred":[
        "Kaithi"
    ],
    "name:jpn_x_preferred":[
        "\u30ab\u30a4\u30c6\u30a3\u30fc\u6587\u5b57"
    ],
    "name:mai_x_preferred":[
        "\u0915\u0948\u0925\u0940"
    ],
    "name:nep_x_preferred":[
        "\u0915\u0948\u0925\u0940"
    ],
    "name:pan_x_preferred":[
        "\u0a15\u0a48\u0a25\u0a40"
    ],
    "name:pnb_x_preferred":[
        "\u06a9\u06cc\u062a\u06be\u06cc \u0644\u067e\u06cc"
    ],
    "name:pol_x_preferred":[
        "Kaithi"
    ],
    "name:por_x_preferred":[
        "Escrita caiti"
    ],
    "name:rus_x_preferred":[
        "\u041a\u0430\u0439\u0442\u0445\u0438"
    ],
    "name:swe_x_preferred":[
        "Kaith\u012b"
    ],
    "name:tha_x_preferred":[
        "\u0e2d\u0e31\u0e01\u0e29\u0e23\u0e44\u0e01\u0e16\u0e35"
    ],
    "name:zho_x_preferred":[
        "\u51f1\u63d0\u6587"
    ],
    "wof:name":"Kaithi",
    "wof:placetype":"locality",
    "wof:population":843
},
  "geometry": {"coordinates":[83.114315,24.742485],"type":"Point"}
}