{
  "type": "Feature",
  "properties": {
    "iso:country":"IN",
    "ks:ks_name":"Benudharpur",
    "ks:ks_pop":29,
    "ks:ks_type":"VILLAGE",
    "name:eng_x_preferred":[
        "Benudharpur"
    ],
    "wof:name":"Benudharpur",
    "wof:placetype":"locality",
    "wof:population":29
},
  "geometry": {"coordinates":[85.271264,20.444136],"type":"Point"}
}