{
  "type": "Feature",
  "properties": {
    "gn:admin1_code":"11",
    "gn:admin2_code":"31.0",
    "gn:asciiname":"Joghon",
    "gn:country_code":"IN",
    "gn:dem":461,
    "gn:feature_class":"P",
    "gn:feature_code":"PPL",
    "gn:name":"Joghon",
    "gn:population":0,
    "gn:timezone":"Asia/Kolkata",
    "iso:country":"IN",
    "wof:name":"Joghon",
    "wof:placetype":"locality"
},
  "geometry": {"coordinates":[76.68474999999999,31.17331],"type":"Point"}
}