{
  "type": "Feature",
  "properties": {
    "iso:country":"IN",
    "ks:ks_name":"Galetivaripalle",
    "ks:ks_pop":27,
    "ks:ks_type":"HABITATION",
    "name:eng_x_preferred":[
        "Galetivaripalle"
    ],
    "wof:name":"Galetivaripalle",
    "wof:placetype":"locality",
    "wof:population":27
},
  "geometry": {"coordinates":[78.579584,13.529673],"type":"Point"}
}