{
  "type": "Feature",
  "properties": {
    "gn:admin1_code":"31.0",
    "gn:admin2_code":"284.0",
    "gn:asciiname":"Biale",
    "gn:country_code":"IN",
    "gn:dem":1244,
    "gn:feature_class":"P",
    "gn:feature_code":"PPL",
    "gn:name":"Biale",
    "gn:population":0,
    "gn:timezone":"Asia/Kolkata",
    "iso:country":"IN",
    "wof:name":"Biale",
    "wof:placetype":"locality"
},
  "geometry": {"coordinates":[93.12701,23.24275],"type":"Point"}
}