{
  "type": "Feature",
  "properties": {
    "gn:admin1_code":"13.0",
    "gn:admin2_code":"600.0",
    "gn:asciiname":"Chandanathope",
    "gn:country_code":"IN",
    "gn:dem":29,
    "gn:feature_class":"P",
    "gn:feature_code":"PPL",
    "gn:name":"Chandanathope",
    "gn:population":0,
    "gn:timezone":"Asia/Kolkata",
    "iso:country":"IN",
    "name:mal_x_preferred":[
        "\u0d1a\u0d28\u0d4d\u0d26\u0d28\u0d24\u0d4d\u0d24\u0d4b\u0d2a\u0d4d\u0d2a\u0d4d"
    ],
    "name:und_x_variant":[
        "Chandanathoppu"
    ],
    "wof:name":"Chandanathope",
    "wof:placetype":"neighbourhood"
},
  "geometry": {"coordinates":[76.64093,8.92924],"type":"Point"}
}