{
  "type": "Feature",
  "properties": {
    "iso:country":"IN",
    "ks:ks_name":"Sarnatoli",
    "ks:ks_pop":245,
    "ks:ks_type":"HABITATION",
    "name:eng_x_preferred":[
        "Sarnatoli"
    ],
    "wof:name":"Sarnatoli",
    "wof:placetype":"locality",
    "wof:population":245
},
  "geometry": {"coordinates":[84.94529900000001,23.354394],"type":"Point"}
}