{
  "type": "Feature",
  "properties": {
    "iso:country":"IN",
    "ks:ks_name":"Narvad",
    "ks:ks_pop":1743,
    "ks:ks_type":"VILLAGE",
    "name:eng_x_preferred":[
        "Narvad"
    ],
    "wof:name":"Narvad",
    "wof:placetype":"locality",
    "wof:population":1743
},
  "geometry": {"coordinates":[73.32761600000001,20.292082],"type":"Point"}
}