{
  "type": "Feature",
  "properties": {
    "gn:admin1_code":"19.0",
    "gn:admin2_code":"583.0",
    "gn:asciiname":"Mallenhalli",
    "gn:country_code":"IN",
    "gn:dem":912,
    "gn:feature_class":"P",
    "gn:feature_code":"PPL",
    "gn:name":"Mallenhalli",
    "gn:population":0,
    "gn:timezone":"Asia/Kolkata",
    "iso:country":"IN",
    "wof:name":"Mallenhalli",
    "wof:placetype":"locality"
},
  "geometry": {"coordinates":[77.47659,13.32844],"type":"Point"}
}