{
  "type": "Feature",
  "properties": {
    "gn:admin1_code":"10",
    "gn:admin2_code":"81.0",
    "gn:asciiname":"Karirupa",
    "gn:country_code":"IN",
    "gn:dem":248,
    "gn:feature_class":"P",
    "gn:feature_code":"PPL",
    "gn:name":"K\u0101r\u012br\u016bpa",
    "gn:population":0,
    "gn:timezone":"Asia/Kolkata",
    "iso:country":"IN",
    "ks:ks_alt_nam":"K\u0101r\u012br\u016bpa",
    "ks:ks_name":"Karirupa",
    "ks:ks_type":"VILLAGE",
    "name:eng_x_preferred":[
        "Karirupa"
    ],
    "name:eng_x_variant":[
        "K\u0101r\u012br\u016bpa"
    ],
    "wof:name":"Karirupa",
    "wof:placetype":"locality"
},
  "geometry": {"coordinates":[75.871234,28.543329],"type":"Point"}
}