{
  "type": "Feature",
  "properties": {
    "gn:admin1_code":"10",
    "gn:admin2_code":"81.0",
    "gn:asciiname":"Karirupa",
    "gn:country_code":"IN",
    "gn:dem":248,
    "gn:feature_class":"P",
    "gn:feature_code":"PPL",
    "gn:name":"K\u0101r\u012br\u016bpa",
    "gn:population":0,
    "gn:timezone":"Asia/Kolkata",
    "iso:country":"IN",
    "wof:name":"Karirupa",
    "wof:placetype":"locality"
},
  "geometry": {"coordinates":[75.87123000000003,28.54333],"type":"Point"}
}