{
  "type": "Feature",
  "properties": {
    "iso:country":"IN",
    "ks:ks_name":"Hegdekeri",
    "ks:ks_pop":146,
    "ks:ks_type":"HABITATION",
    "name:eng_x_preferred":[
        "Hegdekeri"
    ],
    "wof:name":"Hegdekeri",
    "wof:placetype":"locality",
    "wof:population":146
},
  "geometry": {"coordinates":[74.443275,14.390646],"type":"Point"}
}