{
  "type": "Feature",
  "properties": {
    "gn:admin1_code":"36",
    "gn:admin2_code":"134.0",
    "gn:asciiname":"Lalwala",
    "gn:country_code":"IN",
    "gn:dem":246,
    "gn:feature_class":"P",
    "gn:feature_code":"PPL",
    "gn:name":"L\u0101lw\u0101la",
    "gn:population":0,
    "gn:timezone":"Asia/Kolkata",
    "iso:country":"IN",
    "name:und_x_variant":[
        "L\u0101lw\u0101la",
        "Saidpur Muhammad"
    ],
    "wof:name":"Lalwala",
    "wof:placetype":"neighbourhood"
},
  "geometry": {"coordinates":[78.43083,29.41602],"type":"Point"}
}