{
  "type": "Feature",
  "properties": {
    "iso:country":"IN",
    "ks:ks_name":"Mayaram",
    "ks:ks_pop":0,
    "ks:ks_type":"VILLAGE",
    "name:eng_x_preferred":[
        "Mayaram"
    ],
    "wof:name":"Mayaram",
    "wof:placetype":"locality",
    "wof:population":0
},
  "geometry": {"coordinates":[88.320734,26.718405],"type":"Point"}
}