{
  "type": "Feature",
  "properties": {
    "iso:country":"IN",
    "ks:ks_name":"Sukh Nagar",
    "ks:ks_pop":42,
    "ks:ks_type":"HABITATION",
    "name:eng_x_preferred":[
        "Sukh Nagar"
    ],
    "wof:name":"Sukh Nagar",
    "wof:placetype":"locality",
    "wof:population":42
},
  "geometry": {"coordinates":[71.103094,27.525686],"type":"Point"}
}