{
  "type": "Feature",
  "properties": {
    "gn:admin1_code":"35",
    "gn:admin2_code":"420.0",
    "gn:asciiname":"Nakhloli",
    "gn:country_code":"IN",
    "gn:dem":138,
    "gn:feature_class":"P",
    "gn:feature_code":"PPL",
    "gn:name":"Nakhloli",
    "gn:population":0,
    "gn:timezone":"Asia/Kolkata",
    "iso:country":"IN",
    "ks:ks_name":"Nakhloli",
    "ks:ks_type":"VILLAGE",
    "name:eng_x_preferred":[
        "Nakhloli"
    ],
    "wof:name":"Nakhloli",
    "wof:placetype":"locality"
},
  "geometry": {"coordinates":[78.758762,26.771884],"type":"Point"}
}