{
  "type": "Feature",
  "properties": {
    "iso:country":"IN",
    "ks:ks_alt_nam":"Harijan basti Paschim",
    "ks:ks_name":"Harijan Basti Paschim",
    "ks:ks_pop":557,
    "ks:ks_type":"HABITATION",
    "name:eng_x_preferred":[
        "Harijan Basti Paschim"
    ],
    "wof:name":"Harijan Basti Paschim",
    "wof:placetype":"locality",
    "wof:population":557
},
  "geometry": {"coordinates":[82.837112,25.452406],"type":"Point"}
}