{
  "type": "Feature",
  "properties": {
    "iso:country":"IN",
    "ks:ks_name":"Kattakindi Tanda",
    "ks:ks_pop":40,
    "ks:ks_type":"HABITATION",
    "name:eng_x_preferred":[
        "Kattakindi Tanda"
    ],
    "wof:name":"Kattakindi Tanda",
    "wof:placetype":"locality",
    "wof:population":40
},
  "geometry": {"coordinates":[77.998948,18.249719],"type":"Point"}
}