{
  "type": "Feature",
  "properties": {
    "iso:country":"IN",
    "ks:ks_name":"Chak Krishna Ballabhpur",
    "ks:ks_pop":695,
    "ks:ks_type":"VILLAGE",
    "ks:ks_uagg_main":0,
    "name:eng_x_preferred":[
        "Chak Krishna Ballabhpur"
    ],
    "wof:name":"Chak Krishna Ballabhpur",
    "wof:placetype":"neighbourhood",
    "wof:population":695
},
  "geometry": {"coordinates":[88.255481,22.038568],"type":"Point"}
}