{
  "type": "Feature",
  "properties": {
    "iso:country":"IN",
    "ks:ks_name":"Sindriguda",
    "ks:ks_pop":46,
    "ks:ks_type":"HABITATION",
    "name:eng_x_preferred":[
        "Sindriguda"
    ],
    "wof:name":"Sindriguda",
    "wof:placetype":"locality",
    "wof:population":46
},
  "geometry": {"coordinates":[82.742315,18.325805],"type":"Point"}
}