{
  "type": "Feature",
  "properties": {
    "iso:country":"IN",
    "ks:ks_name":"Garbhudih Milik",
    "ks:ks_pop":609,
    "ks:ks_type":"VILLAGE",
    "ks:ks_uagg_main":0,
    "name:eng_x_preferred":[
        "Garbhudih Milik"
    ],
    "wof:name":"Garbhudih Milik",
    "wof:placetype":"neighbourhood",
    "wof:population":609
},
  "geometry": {"coordinates":[87.201746,25.156596],"type":"Point"}
}