{
  "type": "Feature",
  "properties": {
    "iso:country":"IN",
    "ks:ks_name":"Murali Khas",
    "ks:ks_pop":774,
    "ks:ks_type":"HABITATION",
    "name:eng_x_preferred":[
        "Murali Khas"
    ],
    "wof:name":"Murali Khas",
    "wof:placetype":"locality",
    "wof:population":774
},
  "geometry": {"coordinates":[82.96589899999999,25.510719],"type":"Point"}
}