{
  "type": "Feature",
  "properties": {
    "gn:admin1_code":"36.0",
    "gn:admin2_code":"152.0",
    "gn:asciiname":"Talgaon",
    "gn:country_code":"IN",
    "gn:dem":166,
    "gn:feature_class":"P",
    "gn:feature_code":"PPL",
    "gn:name":"T\u0101lg\u0101on",
    "gn:population":0,
    "gn:timezone":"Asia/Kolkata",
    "iso:country":"IN",
    "wof:name":"Talgaon",
    "wof:placetype":"locality"
},
  "geometry": {"coordinates":[79.84244,28.22798],"type":"Point"}
}