{
  "type": "Feature",
  "properties": {
    "iso:country":"IN",
    "ks:ks_name":"Tokavalasa",
    "ks:ks_pop":209,
    "ks:ks_type":"VILLAGE",
    "name:eng_x_preferred":[
        "Tokavalasa"
    ],
    "wof:name":"Tokavalasa",
    "wof:placetype":"locality",
    "wof:population":209
},
  "geometry": {"coordinates":[83.05858600000001,18.376717],"type":"Point"}
}