{
  "type": "Feature",
  "properties": {
    "gn:admin1_code":"34.0",
    "gn:admin2_code":"204.0",
    "gn:asciiname":"Malahi",
    "gn:country_code":"IN",
    "gn:dem":70,
    "gn:feature_class":"P",
    "gn:feature_code":"PPL",
    "gn:name":"Mal\u0101hi",
    "gn:population":0,
    "gn:timezone":"Asia/Kolkata",
    "iso:country":"IN",
    "name:ceb_x_preferred":[
        "Malahi"
    ],
    "name:msa_x_preferred":[
        "Malahi"
    ],
    "name:new_x_preferred":[
        "\u092e\u0932\u0939\u0940"
    ],
    "name:pol_x_preferred":[
        "Malahi"
    ],
    "wof:name":"Malahi",
    "wof:placetype":"locality"
},
  "geometry": {"coordinates":[84.9957,26.7637],"type":"Point"}
}