{
  "type": "Feature",
  "properties": {
    "iso:country":"IN",
    "ks:ks_name":"Pagra Khurd",
    "ks:ks_pop":0,
    "ks:ks_type":"VILLAGE",
    "name:eng_x_preferred":[
        "Pagra Khurd"
    ],
    "wof:name":"Pagra Khurd",
    "wof:placetype":"locality",
    "wof:population":0
},
  "geometry": {"coordinates":[83.931718,26.468279],"type":"Point"}
}