{
  "type": "Feature",
  "properties": {
    "iso:country":"IN",
    "ks:ks_name":"Jawakpura",
    "ks:ks_pop":2,
    "ks:ks_type":"VILLAGE",
    "name:eng_x_preferred":[
        "Jawakpura"
    ],
    "wof:name":"Jawakpura",
    "wof:placetype":"locality",
    "wof:population":2
},
  "geometry": {"coordinates":[79.10615199999999,26.108872],"type":"Point"}
}