{
  "type": "Feature",
  "properties": {
    "iso:country":"IN",
    "ks:ks_name":"Surajpur",
    "ks:ks_pop":184,
    "ks:ks_type":"VILLAGE",
    "name:eng_x_preferred":[
        "Surajpur"
    ],
    "wof:name":"Surajpur",
    "wof:placetype":"locality",
    "wof:population":184
},
  "geometry": {"coordinates":[83.96329900000001,27.220556],"type":"Point"}
}