{
  "type": "Feature",
  "properties": {
    "iso:country":"IN",
    "ks:ks_name":"Reddies Nagar",
    "ks:ks_pop":148,
    "ks:ks_type":"HABITATION",
    "name:eng_x_preferred":[
        "Reddies Nagar"
    ],
    "wof:name":"Reddies Nagar",
    "wof:placetype":"locality",
    "wof:population":148
},
  "geometry": {"coordinates":[76.76936499999999,15.821379],"type":"Point"}
}