{
  "type": "Feature",
  "properties": {
    "iso:country":"IN",
    "ks:ks_name":"Durganagar V",
    "ks:ks_pop":6695,
    "ks:ks_type":"VILLAGE",
    "ks:ks_uagg_main":0,
    "name:eng_x_preferred":[
        "Durganagar V"
    ],
    "wof:name":"Durganagar V",
    "wof:placetype":"neighbourhood",
    "wof:population":6695
},
  "geometry": {"coordinates":[92.88122300000001,24.884076],"type":"Point"}
}