{
  "type": "Feature",
  "properties": {
    "iso:country":"IN",
    "ks:ks_alt_nam":"T\u0101jpur",
    "ks:ks_name":"Tajpur",
    "ks:ks_type":"VILLAGE",
    "ks:ks_uagg_main":0,
    "name:eng_x_preferred":[
        "Tajpur"
    ],
    "name:eng_x_variant":[
        "T\u0101jpur"
    ],
    "wof:name":"Tajpur",
    "wof:placetype":"neighbourhood"
},
  "geometry": {"coordinates":[77.31325,28.495511],"type":"Point"}
}