{
  "type": "Feature",
  "properties": {
    "iso:country":"IN",
    "ks:ks_name":"Soardihi",
    "ks:ks_pop":0,
    "ks:ks_type":"VILLAGE",
    "name:eng_x_preferred":[
        "Soardihi"
    ],
    "wof:name":"Soardihi",
    "wof:placetype":"locality",
    "wof:population":0
},
  "geometry": {"coordinates":[86.625253,23.536663],"type":"Point"}
}