{
  "type": "Feature",
  "properties": {
    "gn:admin1_code":"36",
    "gn:admin2_code":"134.0",
    "gn:asciiname":"Islampur Bishnoi",
    "gn:country_code":"IN",
    "gn:dem":246,
    "gn:feature_class":"P",
    "gn:feature_code":"PPL",
    "gn:name":"Isl\u0101mpur Bishnoi",
    "gn:population":0,
    "gn:timezone":"Asia/Kolkata",
    "iso:country":"IN",
    "ks:ks_alt_nam":"Isl\u0101mpur Bishnoi",
    "ks:ks_name":"Islampur Bishnoi",
    "ks:ks_pop":1171,
    "ks:ks_type":"VILLAGE",
    "ks:ks_uagg_main":0,
    "name:eng_x_preferred":[
        "Islampur Bishnoi"
    ],
    "name:eng_x_variant":[
        "Isl\u0101mpur Bishnoi"
    ],
    "wof:name":"Islampur Bishnoi",
    "wof:placetype":"neighbourhood",
    "wof:population":1171
},
  "geometry": {"coordinates":[78.312718,29.423971],"type":"Point"}
}