{
  "type": "Feature",
  "properties": {
    "gn:admin1_code":"36",
    "gn:admin2_code":"155.0",
    "gn:asciiname":"Kasiapur",
    "gn:country_code":"IN",
    "gn:dem":133,
    "gn:feature_class":"P",
    "gn:feature_code":"PPL",
    "gn:name":"Kasi\u0101pur",
    "gn:population":0,
    "gn:timezone":"Asia/Kolkata",
    "iso:country":"IN",
    "wof:name":"Kasiapur",
    "wof:placetype":"locality"
},
  "geometry": {"coordinates":[80.69192,27.16181],"type":"Point"}
}