{
  "type": "Feature",
  "properties": {
    "iso:country":"IN",
    "ks:ks_name":"Changkhuti",
    "ks:ks_pop":550,
    "ks:ks_type":"HABITATION",
    "name:eng_x_preferred":[
        "Changkhuti"
    ],
    "wof:name":"Changkhuti",
    "wof:placetype":"locality",
    "wof:population":550
},
  "geometry": {"coordinates":[94.165046,26.481275],"type":"Point"}
}