{
  "type": "Feature",
  "properties": {
    "iso:country":"IN",
    "ks:ks_alt_nam":"NALAWADEVASTI",
    "ks:ks_name":"Nalawadevasti",
    "ks:ks_pop":54,
    "ks:ks_type":"HABITATION",
    "name:eng_x_preferred":[
        "Nalawadevasti"
    ],
    "wof:name":"Nalawadevasti",
    "wof:placetype":"locality",
    "wof:population":54
},
  "geometry": {"coordinates":[74.79949499999999,17.216813],"type":"Point"}
}