{
  "type": "Feature",
  "properties": {
    "iso:country":"IN",
    "ks:ks_name":"Aleesar",
    "ks:ks_pop":2475,
    "ks:ks_type":"VILLAGE",
    "name:eng_x_preferred":[
        "Aleesar"
    ],
    "wof:name":"Aleesar",
    "wof:placetype":"locality",
    "wof:population":2475
},
  "geometry": {"coordinates":[75.58345,27.238936],"type":"Point"}
}