{
  "type": "Feature",
  "properties": {
    "gn:admin1_code":"34.0",
    "gn:admin2_code":"217.0",
    "gn:asciiname":"Lohar Patti",
    "gn:country_code":"IN",
    "gn:dem":77,
    "gn:feature_class":"P",
    "gn:feature_code":"PPL",
    "gn:name":"Lohar Patti",
    "gn:population":0,
    "gn:timezone":"Asia/Kolkata",
    "iso:country":"IN",
    "ks:ks_name":"Lohar Patti",
    "ks:ks_pop":600,
    "ks:ks_type":"VILLAGE",
    "name:eng_x_preferred":[
        "Lohar Patti"
    ],
    "wof:name":"Lohar Patti",
    "wof:placetype":"locality",
    "wof:population":600
},
  "geometry": {"coordinates":[84.308764,26.58479],"type":"Point"}
}