{
  "type": "Feature",
  "properties": {
    "iso:country":"IN",
    "ks:ks_name":"Nadamel",
    "ks:ks_pop":0,
    "ks:ks_type":"VILLAGE",
    "name:eng_x_preferred":[
        "Nadamel"
    ],
    "wof:name":"Nadamel",
    "wof:placetype":"locality",
    "wof:population":0
},
  "geometry": {"coordinates":[76.337965,9.964003],"type":"Point"}
}