{
  "type": "Feature",
  "properties": {
    "iso:country":"IN",
    "ks:ks_name":"Badraksi",
    "ks:ks_pop":427,
    "ks:ks_type":"VILLAGE",
    "name:eng_x_preferred":[
        "Badraksi"
    ],
    "wof:name":"Badraksi",
    "wof:placetype":"locality",
    "wof:population":427
},
  "geometry": {"coordinates":[85.074257,22.040318],"type":"Point"}
}