{
  "type": "Feature",
  "properties": {
    "iso:country":"IN",
    "ks:ks_name":"Bidrewadi",
    "ks:ks_pop":998,
    "ks:ks_type":"VILLAGE",
    "ks:ks_uagg_main":0,
    "name:eng_x_preferred":[
        "Bidrewadi"
    ],
    "wof:name":"Bidrewadi",
    "wof:placetype":"neighbourhood",
    "wof:population":998
},
  "geometry": {"coordinates":[74.44452,16.090271],"type":"Point"}
}