{
  "type": "Feature",
  "properties": {
    "iso:country":"IN",
    "ks:ks_name":"Karichandra Para",
    "ks:ks_pop":260,
    "ks:ks_type":"HABITATION",
    "ks:ks_uagg_main":0,
    "name:eng_x_preferred":[
        "Karichandra Para"
    ],
    "wof:name":"Karichandra Para",
    "wof:placetype":"neighbourhood",
    "wof:population":260
},
  "geometry": {"coordinates":[91.66421800000001,23.021009],"type":"Point"}
}