{
  "type": "Feature",
  "properties": {
    "gn:admin1_code":"9.0",
    "gn:admin2_code":"486.0",
    "gn:asciiname":"Siada",
    "gn:country_code":"IN",
    "gn:dem":175,
    "gn:feature_class":"P",
    "gn:feature_code":"PPL",
    "gn:name":"Siada",
    "gn:population":0,
    "gn:timezone":"Asia/Kolkata",
    "iso:country":"IN",
    "wof:name":"Siada",
    "wof:placetype":"neighbourhood"
},
  "geometry": {"coordinates":[74.05092,22.22212],"type":"Point"}
}