{
  "type": "Feature",
  "properties": {
    "iso:country":"IN",
    "ks:ks_name":"Kataraguda",
    "ks:ks_pop":58,
    "ks:ks_type":"VILLAGE",
    "name:eng_x_preferred":[
        "Kataraguda"
    ],
    "wof:name":"Kataraguda",
    "wof:placetype":"locality",
    "wof:population":58
},
  "geometry": {"coordinates":[83.706267,19.34747],"type":"Point"}
}