{
  "type": "Feature",
  "properties": {
    "iso:country":"IN",
    "ks:ks_name":"Bhadaura",
    "ks:ks_pop":32,
    "ks:ks_type":"HABITATION",
    "name:eng_x_preferred":[
        "Bhadaura"
    ],
    "wof:name":"Bhadaura",
    "wof:placetype":"locality",
    "wof:population":32
},
  "geometry": {"coordinates":[79.862776,29.971963],"type":"Point"}
}