{
  "type": "Feature",
  "properties": {
    "iso:country":"IN",
    "ks:ks_alt_nam":"Nalge wasti",
    "ks:ks_name":"Nalge Wasti",
    "ks:ks_pop":249,
    "ks:ks_type":"HABITATION",
    "name:eng_x_preferred":[
        "Nalge Wasti"
    ],
    "wof:name":"Nalge Wasti",
    "wof:placetype":"locality",
    "wof:population":249
},
  "geometry": {"coordinates":[75.305465,19.409644],"type":"Point"}
}