{
  "type": "Feature",
  "properties": {
    "iso:country":"IN",
    "ks:ks_name":"Tilla Basti",
    "ks:ks_pop":602,
    "ks:ks_type":"HABITATION",
    "ks:ks_uagg_main":0,
    "name:eng_x_preferred":[
        "Tilla Basti"
    ],
    "wof:name":"Tilla Basti",
    "wof:placetype":"neighbourhood",
    "wof:population":602
},
  "geometry": {"coordinates":[93.119632,25.17833],"type":"Point"}
}