{
  "type": "Feature",
  "properties": {
    "iso:country":"IN",
    "ks:ks_name":"Dhobni",
    "ks:ks_pop":872,
    "ks:ks_type":"VILLAGE",
    "name:eng_x_preferred":[
        "Dhobni"
    ],
    "wof:name":"Dhobni",
    "wof:placetype":"neighbourhood",
    "wof:population":872
},
  "geometry": {"coordinates":[86.355767,23.762276],"type":"Point"}
}