{
  "type": "Feature",
  "properties": {
    "iso:country":"IN",
    "ks:ks_name":"Thalaikulam",
    "ks:ks_pop":500,
    "ks:ks_type":"HABITATION",
    "name:eng_x_preferred":[
        "Thalaikulam"
    ],
    "wof:name":"Thalaikulam",
    "wof:placetype":"locality",
    "wof:population":500
},
  "geometry": {"coordinates":[77.669161,8.537208],"type":"Point"}
}