{
  "type": "Feature",
  "properties": {
    "gn:admin1_code":"36",
    "gn:admin2_code":"158.0",
    "gn:asciiname":"Pura Rameshwardatt Pandit",
    "gn:country_code":"IN",
    "gn:dem":115,
    "gn:feature_class":"P",
    "gn:feature_code":"PPL",
    "gn:name":"Pura R\u0101meshwardatt Pandit",
    "gn:population":0,
    "gn:timezone":"Asia/Kolkata",
    "iso:country":"IN",
    "wof:name":"Pura Rameshwardatt Pandit",
    "wof:placetype":"neighbourhood"
},
  "geometry": {"coordinates":[81.25154999999999,26.47304],"type":"Point"}
}