{
  "type": "Feature",
  "properties": {
    "iso:country":"IN",
    "ks:ks_name":"Mandha",
    "ks:ks_pop":744,
    "ks:ks_type":"VILLAGE",
    "name:eng_x_preferred":[
        "Mandha"
    ],
    "wof:name":"Mandha",
    "wof:placetype":"locality",
    "wof:population":744
},
  "geometry": {"coordinates":[70.90798599999999,27.332049],"type":"Point"}
}