{
  "type": "Feature",
  "properties": {
    "iso:country":"IN",
    "ks:ks_name":"Kandhaipurwa",
    "ks:ks_pop":193,
    "ks:ks_type":"HABITATION",
    "ks:ks_uagg_main":0,
    "name:eng_x_preferred":[
        "Kandhaipurwa"
    ],
    "wof:name":"Kandhaipurwa",
    "wof:placetype":"neighbourhood",
    "wof:population":193
},
  "geometry": {"coordinates":[81.109351,27.877717],"type":"Point"}
}