{
  "type": "Feature",
  "properties": {
    "gn:admin1_code":"38.0",
    "gn:admin2_code":"348.0",
    "gn:asciiname":"Baghmara",
    "gn:country_code":"IN",
    "gn:dem":371,
    "gn:feature_class":"P",
    "gn:feature_code":"PPL",
    "gn:name":"Baghm\u0101r\u0101",
    "gn:population":0,
    "gn:timezone":"Asia/Kolkata",
    "iso:country":"IN",
    "ks:ks_alt_nam":"Baghm\u0101r\u0101",
    "ks:ks_name":"Baghmara",
    "ks:ks_pop":445,
    "ks:ks_type":"VILLAGE",
    "ks:ks_uagg_main":0,
    "name:eng_x_preferred":[
        "Baghmara"
    ],
    "name:eng_x_variant":[
        "Baghm\u0101r\u0101"
    ],
    "wof:name":"Baghmara",
    "wof:placetype":"neighbourhood",
    "wof:population":445
},
  "geometry": {"coordinates":[85.709591,24.344912],"type":"Point"}
}