{
  "type": "Feature",
  "properties": {
    "iso:country":"IN",
    "ks:ks_name":"Kohbari",
    "ks:ks_pop":91,
    "ks:ks_type":"VILLAGE",
    "name:eng_x_preferred":[
        "Kohbari"
    ],
    "wof:name":"Kohbari",
    "wof:placetype":"locality",
    "wof:population":91
},
  "geometry": {"coordinates":[85.04998999999999,24.512271],"type":"Point"}
}