{
  "type": "Feature",
  "properties": {
    "iso:country":"IN",
    "ks:ks_name":"Rahura",
    "ks:ks_pop":505,
    "ks:ks_type":"VILLAGE",
    "ks:ks_uagg_main":0,
    "name:eng_x_preferred":[
        "Rahura"
    ],
    "wof:name":"Rahura",
    "wof:placetype":"neighbourhood",
    "wof:population":505
},
  "geometry": {"coordinates":[85.94896,20.324882],"type":"Point"}
}