{
  "type": "Feature",
  "properties": {
    "gn:admin1_code":"36.0",
    "gn:admin2_code":"153.0",
    "gn:asciiname":"Sheikhpur",
    "gn:country_code":"IN",
    "gn:dem":155,
    "gn:feature_class":"P",
    "gn:feature_code":"PPL",
    "gn:name":"Sheikhpur",
    "gn:population":0,
    "gn:timezone":"Asia/Kolkata",
    "iso:country":"IN",
    "ks:ks_name":"Shekhpur",
    "ks:ks_pop":235,
    "ks:ks_type":"HABITATION",
    "name:eng_x_preferred":[
        "Shekhpur"
    ],
    "name:eng_x_variant":[
        "Sheikhpur"
    ],
    "wof:name":"Shekhpur",
    "wof:placetype":"locality",
    "wof:population":235
},
  "geometry": {"coordinates":[80.25453400000001,27.861585],"type":"Point"}
}