{
  "type": "Feature",
  "properties": {
    "iso:country":"IN",
    "ks:ks_name":"Kunabiwadi",
    "ks:ks_pop":147,
    "ks:ks_type":"HABITATION",
    "name:eng_x_preferred":[
        "Kunabiwadi"
    ],
    "wof:name":"Kunabiwadi",
    "wof:placetype":"locality",
    "wof:population":147
},
  "geometry": {"coordinates":[73.72533300000001,16.590608],"type":"Point"}
}