{
  "type": "Feature",
  "properties": {
    "iso:country":"IN",
    "ks:ks_name":"Malang Gaon",
    "ks:ks_pop":1691,
    "ks:ks_type":"HABITATION",
    "ks:ks_uagg_main":0,
    "name:eng_x_preferred":[
        "Malang Gaon"
    ],
    "wof:name":"Malang Gaon",
    "wof:placetype":"neighbourhood",
    "wof:population":1691
},
  "geometry": {"coordinates":[81.767799,27.874525],"type":"Point"}
}