{
  "type": "Feature",
  "properties": {
    "iso:country":"IN",
    "ks:ks_alt_nam":"PURANTUIHACHIN BARI",
    "ks:ks_name":"Purantuihachin Bari",
    "ks:ks_pop":75,
    "ks:ks_type":"HABITATION",
    "name:eng_x_preferred":[
        "Purantuihachin Bari"
    ],
    "wof:name":"Purantuihachin Bari",
    "wof:placetype":"locality",
    "wof:population":75
},
  "geometry": {"coordinates":[91.531644,23.981243],"type":"Point"}
}