{
  "type": "Feature",
  "properties": {
    "iso:country":"IN",
    "ks:ks_name":"Gaundwadi",
    "ks:ks_pop":125,
    "ks:ks_type":"HABITATION",
    "name:eng_x_preferred":[
        "Gaundwadi"
    ],
    "wof:name":"Gaundwadi",
    "wof:placetype":"locality",
    "wof:population":125
},
  "geometry": {"coordinates":[76.895048,18.71532],"type":"Point"}
}