{
  "type": "Feature",
  "properties": {
    "iso:country":"IN",
    "ks:ks_name":"Kakragaon",
    "ks:ks_pop":541,
    "ks:ks_type":"VILLAGE",
    "name:eng_x_preferred":[
        "Kakragaon"
    ],
    "wof:name":"Kakragaon",
    "wof:placetype":"locality",
    "wof:population":541
},
  "geometry": {"coordinates":[90.46090100000001,26.454171],"type":"Point"}
}