{
  "type": "Feature",
  "properties": {
    "iso:country":"IN",
    "ks:ks_name":"Pipali Puna Gaon",
    "ks:ks_pop":93,
    "ks:ks_type":"VILLAGE",
    "name:eng_x_preferred":[
        "Pipali Puna Gaon"
    ],
    "wof:name":"Pipali Puna Gaon",
    "wof:placetype":"locality",
    "wof:population":93
},
  "geometry": {"coordinates":[80.08225299999999,29.802662],"type":"Point"}
}