{
  "type": "Feature",
  "properties": {
    "gn:admin1_code":"25.0",
    "gn:admin2_code":"617.0",
    "gn:asciiname":"Visalur",
    "gn:country_code":"IN",
    "gn:dem":73,
    "gn:feature_class":"P",
    "gn:feature_code":"PPL",
    "gn:name":"Visal\u016br",
    "gn:population":0,
    "gn:timezone":"Asia/Kolkata",
    "iso:country":"IN",
    "name:deu_x_preferred":[
        "Visalur"
    ],
    "name:tam_x_preferred":[
        "\u0bb5\u0bbf\u0b9a\u0bb2\u0bc2\u0bb0\u0bcd"
    ],
    "wof:name":"Visalur",
    "wof:placetype":"locality"
},
  "geometry": {"coordinates":[79.25699,11.64581],"type":"Point"}
}