{
  "type": "Feature",
  "properties": {
    "iso:country":"IN",
    "ks:ks_name":"Veluthur",
    "ks:ks_pop":1965,
    "ks:ks_type":"HABITATION",
    "name:eng_x_preferred":[
        "Veluthur"
    ],
    "wof:name":"Veluthur",
    "wof:placetype":"locality",
    "wof:population":1965
},
  "geometry": {"coordinates":[76.145471,10.531691],"type":"Point"}
}