{
  "type": "Feature",
  "properties": {
    "iso:country":"IN",
    "ks:ks_name":"Tentulipadara",
    "ks:ks_pop":105,
    "ks:ks_type":"VILLAGE",
    "name:eng_x_preferred":[
        "Tentulipadara"
    ],
    "wof:name":"Tentulipadara",
    "wof:placetype":"locality",
    "wof:population":105
},
  "geometry": {"coordinates":[83.135025,19.198906],"type":"Point"}
}