{
  "type": "Feature",
  "properties": {
    "gn:admin1_code":"11",
    "gn:admin2_code":"23.0",
    "gn:asciiname":"Pabin",
    "gn:country_code":"IN",
    "gn:dem":1209,
    "gn:feature_class":"P",
    "gn:feature_code":"PPL",
    "gn:name":"Pabin",
    "gn:population":0,
    "gn:timezone":"Asia/Kolkata",
    "iso:country":"IN",
    "wof:name":"Pabin",
    "wof:placetype":"locality"
},
  "geometry": {"coordinates":[76.00893000000001,32.65334],"type":"Point"}
}