{
  "type": "Feature",
  "properties": {
    "iso:country":"IN",
    "ks:ks_name":"Kakatapanga",
    "ks:ks_pop":110,
    "ks:ks_type":"HABITATION",
    "name:eng_x_preferred":[
        "Kakatapanga"
    ],
    "wof:name":"Kakatapanga",
    "wof:placetype":"locality",
    "wof:population":110
},
  "geometry": {"coordinates":[84.009024,20.629537],"type":"Point"}
}