{
  "type": "Feature",
  "properties": {
    "iso:country":"IN",
    "ks:ks_name":"Palthaje",
    "ks:ks_pop":9,
    "ks:ks_type":"HABITATION",
    "name:eng_x_preferred":[
        "Palthaje"
    ],
    "wof:name":"Palthaje",
    "wof:placetype":"locality",
    "wof:population":9
},
  "geometry": {"coordinates":[75.557029,12.736262],"type":"Point"}
}