{
  "type": "Feature",
  "properties": {
    "gn:admin1_code":"35",
    "gn:admin2_code":"451.0",
    "gn:asciiname":"Dulhankhera",
    "gn:country_code":"IN",
    "gn:dem":380,
    "gn:feature_class":"P",
    "gn:feature_code":"PPL",
    "gn:name":"Dulhankhera",
    "gn:population":0,
    "gn:timezone":"Asia/Kolkata",
    "iso:country":"IN",
    "ks:ks_name":"Dulhankhera",
    "ks:ks_type":"VILLAGE",
    "name:eng_x_preferred":[
        "Dulhankhera"
    ],
    "wof:name":"Dulhankhera",
    "wof:placetype":"locality"
},
  "geometry": {"coordinates":[79.71515100000001,23.095814],"type":"Point"}
}