{
  "type": "Feature",
  "properties": {
    "gn:admin1_code":"38",
    "gn:admin2_code":"346.0",
    "gn:asciiname":"Tarhe",
    "gn:country_code":"IN",
    "gn:dem":181,
    "gn:feature_class":"P",
    "gn:feature_code":"PPL",
    "gn:name":"Tarhe",
    "gn:population":0,
    "gn:timezone":"Asia/Kolkata",
    "iso:country":"IN",
    "name:cat_x_preferred":[
        "The Crane"
    ],
    "name:fin_x_preferred":[
        "Tarhe"
    ],
    "name:pol_x_preferred":[
        "Tarhe"
    ],
    "wof:name":"Tarhe",
    "wof:placetype":"locality"
},
  "geometry": {"coordinates":[83.71608000000001,24.31704],"type":"Point"}
}