{
  "type": "Feature",
  "properties": {
    "iso:country":"IN",
    "ks:ks_name":"Pananthopu",
    "ks:ks_pop":120,
    "ks:ks_type":"HABITATION",
    "name:eng_x_preferred":[
        "Pananthopu"
    ],
    "wof:name":"Pananthopu",
    "wof:placetype":"locality",
    "wof:population":120
},
  "geometry": {"coordinates":[78.39004799999999,11.702535],"type":"Point"}
}