{
  "type": "Feature",
  "properties": {
    "iso:country":"IN",
    "ks:ks_name":"Aduadih",
    "ks:ks_pop":455,
    "ks:ks_type":"VILLAGE",
    "ks:ks_uagg_main":0,
    "name:eng_x_preferred":[
        "Aduadih"
    ],
    "wof:name":"Aduadih",
    "wof:placetype":"neighbourhood",
    "wof:population":455
},
  "geometry": {"coordinates":[86.165527,24.345004],"type":"Point"}
}