{
  "type": "Feature",
  "properties": {
    "iso:country":"IN",
    "ks:ks_name":"Dev Kheda",
    "ks:ks_pop":107,
    "ks:ks_type":"HABITATION",
    "name:eng_x_preferred":[
        "Dev Kheda"
    ],
    "wof:name":"Dev Kheda",
    "wof:placetype":"locality",
    "wof:population":107
},
  "geometry": {"coordinates":[80.367362,26.90238],"type":"Point"}
}