{
  "type": "Feature",
  "properties": {
    "iso:country":"IN",
    "ks:ks_name":"Sonarmala",
    "ks:ks_pop":234,
    "ks:ks_type":"HABITATION",
    "name:eng_x_preferred":[
        "Sonarmala"
    ],
    "wof:name":"Sonarmala",
    "wof:placetype":"locality",
    "wof:population":234
},
  "geometry": {"coordinates":[75.423187,18.011589],"type":"Point"}
}