{
  "type": "Feature",
  "properties": {
    "iso:country":"IN",
    "ks:ks_name":"Mealanada",
    "ks:ks_pop":24,
    "ks:ks_type":"HABITATION",
    "name:eng_x_preferred":[
        "Mealanada"
    ],
    "wof:name":"Mealanada",
    "wof:placetype":"locality",
    "wof:population":24
},
  "geometry": {"coordinates":[75.597362,12.667478],"type":"Point"}
}