{
  "type": "Feature",
  "properties": {
    "iso:country":"IN",
    "ks:ks_name":"Ambilipada",
    "ks:ks_pop":37,
    "ks:ks_type":"VILLAGE",
    "name:eng_x_preferred":[
        "Ambilipada"
    ],
    "wof:name":"Ambilipada",
    "wof:placetype":"locality",
    "wof:population":37
},
  "geometry": {"coordinates":[84.125006,20.152033],"type":"Point"}
}