{
  "type": "Feature",
  "properties": {
    "iso:country":"IN",
    "name:eng_x_preferred":[
        "Kumbra"
    ],
    "qs:gn_adm0_cc":"IN",
    "qs:gn_fcode":"PPL",
    "qs:gn_local":6992326,
    "qs:gn_nam_loc":"mohali",
    "qs:gn_namadm1":"23",
    "qs:gn_name":"Humbra",
    "qs:local_max":40,
    "qs:local_sum":54,
    "qs:localhoods":2,
    "qs:name":"Kumbra",
    "qs:name_adm0":"India",
    "qs:name_adm1":"Punjab",
    "qs:name_adm2":"Rupnagar",
    "qs:name_local":"Mohali",
    "qs:photo_max":30,
    "qs:photo_sum":40,
    "qs:placetype":"Suburb",
    "qs:quad_count":4,
    "qs:woe_adm0":23424848,
    "qs:woe_adm1":2345756,
    "qs:woe_adm2":12586644,
    "qs:woe_lau":0,
    "qs:woe_local":2290786,
    "qs:woe_ver":"7.10.0",
    "wof:lang":[
        "eng"
    ],
    "wof:name":"Kumbra",
    "wof:placetype":"neighbourhood"
},
  "geometry": {"coordinates":[76.733047,30.69107],"type":"Point"}
}