{
  "type": "Feature",
  "properties": {
    "iso:country":"IN",
    "ks:ks_name":"Badvav",
    "ks:ks_pop":588,
    "ks:ks_type":"VILLAGE",
    "name:eng_x_preferred":[
        "Badvav"
    ],
    "wof:name":"Badvav",
    "wof:placetype":"locality",
    "wof:population":588
},
  "geometry": {"coordinates":[74.012058,22.206321],"type":"Point"}
}