{
  "type": "Feature",
  "properties": {
    "iso:country":"IN",
    "ks:ks_name":"Ahir Tola",
    "ks:ks_pop":15,
    "ks:ks_type":"HABITATION",
    "name:eng_x_preferred":[
        "Ahir Tola"
    ],
    "wof:name":"Ahir Tola",
    "wof:placetype":"locality",
    "wof:population":15
},
  "geometry": {"coordinates":[83.97565,25.395823],"type":"Point"}
}