{
  "type": "Feature",
  "properties": {
    "gn:admin1_code":"36",
    "gn:admin2_code":"191.0",
    "gn:asciiname":"Burhapur Fateh Ali",
    "gn:country_code":"IN",
    "gn:dem":86,
    "gn:feature_class":"P",
    "gn:feature_code":"PPL",
    "gn:name":"B\u016brh\u0101pur Fateh Ali",
    "gn:population":0,
    "gn:timezone":"Asia/Kolkata",
    "iso:country":"IN",
    "wof:name":"Burhapur Fateh Ali",
    "wof:placetype":"locality"
},
  "geometry": {"coordinates":[82.82679,26.07434],"type":"Point"}
}