{
  "type": "Feature",
  "properties": {
    "gn:admin1_code":"2.0",
    "gn:admin2_code":"543.0",
    "gn:asciiname":"Mettuvalasa",
    "gn:country_code":"IN",
    "gn:dem":830,
    "gn:feature_class":"P",
    "gn:feature_code":"PPL",
    "gn:name":"Mettuvalasa",
    "gn:population":0,
    "gn:timezone":"Asia/Kolkata",
    "iso:country":"IN",
    "wof:name":"Mettuvalasa",
    "wof:placetype":"locality"
},
  "geometry": {"coordinates":[83.08346999999998,18.33696],"type":"Point"}
}