{
  "type": "Feature",
  "properties": {
    "gn:admin1_code":"35.0",
    "gn:admin2_code":"454.0",
    "gn:asciiname":"Bagli",
    "gn:country_code":"IN",
    "gn:dem":457,
    "gn:feature_class":"P",
    "gn:feature_code":"PPL",
    "gn:name":"Bagl\u012b",
    "gn:population":0,
    "gn:timezone":"Asia/Kolkata",
    "iso:country":"IN",
    "ks:ks_alt_nam":"Bagl\u012b",
    "ks:ks_name":"Bagli",
    "ks:ks_pop":501,
    "ks:ks_type":"VILLAGE",
    "name:ceb_x_preferred":[
        "Bagli"
    ],
    "name:eng_x_preferred":[
        "Bagli"
    ],
    "name:eng_x_variant":[
        "Bagl\u012b"
    ],
    "name:nld_x_preferred":[
        "Bagli"
    ],
    "wof:name":"Bagli",
    "wof:placetype":"locality",
    "wof:population":501
},
  "geometry": {"coordinates":[80.44876600000001,22.498581],"type":"Point"}
}