{
  "type": "Feature",
  "properties": {
    "iso:country":"IN",
    "ks:ks_alt_nam":"hollade",
    "ks:ks_name":"Hollade",
    "ks:ks_pop":50,
    "ks:ks_type":"HABITATION",
    "name:eng_x_preferred":[
        "Hollade"
    ],
    "wof:name":"Hollade",
    "wof:placetype":"locality",
    "wof:population":50
},
  "geometry": {"coordinates":[74.76566200000001,14.46275],"type":"Point"}
}