{
  "type": "Feature",
  "properties": {
    "iso:country":"IN",
    "ks:ks_name":"Ghanta Kheri",
    "ks:ks_type":"VILLAGE",
    "name:eng_x_preferred":[
        "Ghanta Kheri"
    ],
    "wof:name":"Ghanta Kheri",
    "wof:placetype":"locality"
},
  "geometry": {"coordinates":[76.58842300000001,23.99333],"type":"Point"}
}