{
  "type": "Feature",
  "properties": {
    "iso:country":"IN",
    "ks:ks_alt_nam":"Kund\u0101d\u012bh",
    "ks:ks_name":"Kundadih",
    "ks:ks_pop":0,
    "ks:ks_type":"VILLAGE",
    "name:eng_x_preferred":[
        "Kundadih"
    ],
    "name:eng_x_variant":[
        "Kund\u0101d\u012bh"
    ],
    "wof:name":"Kundadih",
    "wof:placetype":"locality",
    "wof:population":0
},
  "geometry": {"coordinates":[83.629447,24.650925],"type":"Point"}
}