{
  "type": "Feature",
  "properties": {
    "iso:country":"IN",
    "ks:ks_name":"Indra Nagar",
    "ks:ks_pop":76,
    "ks:ks_type":"HABITATION",
    "name:eng_x_preferred":[
        "Indra Nagar"
    ],
    "wof:name":"Indra Nagar",
    "wof:placetype":"locality",
    "wof:population":76
},
  "geometry": {"coordinates":[78.94961499999999,10.81079],"type":"Point"}
}