{
  "type": "Feature",
  "properties": {
    "iso:country":"IN",
    "ks:ks_name":"Barikapali",
    "ks:ks_pop":868,
    "ks:ks_type":"HABITATION",
    "ks:ks_uagg_main":0,
    "name:eng_x_preferred":[
        "Barikapali"
    ],
    "wof:name":"Barikapali",
    "wof:placetype":"neighbourhood",
    "wof:population":868
},
  "geometry": {"coordinates":[84.75368,19.819424],"type":"Point"}
}