{
  "type": "Feature",
  "properties": {
    "gn:admin1_code":"24.0",
    "gn:admin2_code":"127",
    "gn:asciiname":"Dhulet",
    "gn:country_code":"IN",
    "gn:dem":275,
    "gn:feature_class":"P",
    "gn:feature_code":"PPL",
    "gn:name":"Dh\u016blet",
    "gn:population":0,
    "gn:timezone":"Asia/Kolkata",
    "iso:country":"IN",
    "name:und_x_variant":[
        "Dh\u016blet",
        "Dhulet"
    ],
    "wof:name":"Dhulet",
    "wof:placetype":"locality"
},
  "geometry": {"coordinates":[76.20626999999998,24.81717],"type":"Point"}
}