{
  "type": "Feature",
  "properties": {
    "iso:country":"IN",
    "ks:ks_name":"Nana Pada",
    "ks:ks_pop":193,
    "ks:ks_type":"HABITATION",
    "ks:ks_uagg_main":0,
    "name:eng_x_preferred":[
        "Nana Pada"
    ],
    "wof:name":"Nana Pada",
    "wof:placetype":"neighbourhood",
    "wof:population":193
},
  "geometry": {"coordinates":[73.360722,20.308722],"type":"Point"}
}