{
  "type": "Feature",
  "properties": {
    "gn:admin1_code":"36",
    "gn:admin2_code":"199.0",
    "gn:asciiname":"Khera Bhabutaprasad",
    "gn:country_code":"IN",
    "gn:dem":146,
    "gn:feature_class":"P",
    "gn:feature_code":"PPL",
    "gn:name":"Khera Bhab\u016bt\u0101pras\u0101d",
    "gn:population":0,
    "gn:timezone":"Asia/Kolkata",
    "iso:country":"IN",
    "ks:ks_name":"Khairabha Bhuta Prasad",
    "ks:ks_pop":411,
    "ks:ks_type":"VILLAGE",
    "name:eng_x_preferred":[
        "Khairabha Bhuta Prasad"
    ],
    "name:eng_x_variant":[
        "Khera Bhabutaprasad"
    ],
    "wof:name":"Khairabha Bhuta Prasad",
    "wof:placetype":"locality",
    "wof:population":411
},
  "geometry": {"coordinates":[82.277665,24.965795],"type":"Point"}
}