{
  "type": "Feature",
  "properties": {
    "gn:admin1_code":"36",
    "gn:admin2_code":"199.0",
    "gn:asciiname":"Khera Bhabutaprasad",
    "gn:country_code":"IN",
    "gn:dem":146,
    "gn:feature_class":"P",
    "gn:feature_code":"PPL",
    "gn:name":"Khera Bhab\u016bt\u0101pras\u0101d",
    "gn:population":0,
    "gn:timezone":"Asia/Kolkata",
    "iso:country":"IN",
    "wof:name":"Khera Bhabutaprasad",
    "wof:placetype":"locality"
},
  "geometry": {"coordinates":[82.27654,24.96169],"type":"Point"}
}