{
  "type": "Feature",
  "properties": {
    "iso:country":"IN",
    "ks:ks_alt_nam":"MANUKAR VASTI",
    "ks:ks_name":"Manukar Vasti",
    "ks:ks_pop":98,
    "ks:ks_type":"HABITATION",
    "name:eng_x_preferred":[
        "Manukar Vasti"
    ],
    "wof:name":"Manukar Vasti",
    "wof:placetype":"locality",
    "wof:population":98
},
  "geometry": {"coordinates":[74.757468,16.853265],"type":"Point"}
}