{
  "type": "Feature",
  "properties": {
    "gn:admin1_code":"11.0",
    "gn:admin2_code":"32.0",
    "gn:asciiname":"Ghundwi",
    "gn:country_code":"IN",
    "gn:dem":1694,
    "gn:feature_class":"P",
    "gn:feature_code":"PPL",
    "gn:name":"Ghundwi",
    "gn:population":0,
    "gn:timezone":"Asia/Kolkata",
    "iso:country":"IN",
    "wof:name":"Ghundwi",
    "wof:placetype":"locality"
},
  "geometry": {"coordinates":[77.63784,30.73069000000001],"type":"Point"}
}