{
  "type": "Feature",
  "properties": {
    "gn:admin1_code":"36",
    "gn:admin2_code":"169.0",
    "gn:asciiname":"Majhgawan Khurd",
    "gn:country_code":"IN",
    "gn:dem":244,
    "gn:feature_class":"P",
    "gn:feature_code":"PPL",
    "gn:name":"Majhgaw\u0101n Khurd",
    "gn:population":0,
    "gn:timezone":"Asia/Kolkata",
    "iso:country":"IN",
    "ks:ks_name":"Majhgawan Khurd",
    "ks:ks_pop":661,
    "ks:ks_type":"HABITATION",
    "ks:ks_uagg_main":0,
    "name:eng_x_preferred":[
        "Majhgawan Khurd"
    ],
    "wof:name":"Majhgawan Khurd",
    "wof:placetype":"neighbourhood",
    "wof:population":661
},
  "geometry": {"coordinates":[79.65481800000001,25.172345],"type":"Point"}
}