{
  "type": "Feature",
  "properties": {
    "iso:country":"IN",
    "ks:ks_name":"Barbera",
    "ks:ks_pop":292,
    "ks:ks_type":"VILLAGE",
    "name:eng_x_preferred":[
        "Barbera"
    ],
    "wof:name":"Barbera",
    "wof:placetype":"locality",
    "wof:population":292
},
  "geometry": {"coordinates":[84.90182,22.560267],"type":"Point"}
}