{
  "type": "Feature",
  "properties": {
    "gn:admin1_code":"19.0",
    "gn:admin2_code":"581.0",
    "gn:asciiname":"Hiripalya",
    "gn:country_code":"IN",
    "gn:dem":877,
    "gn:feature_class":"P",
    "gn:feature_code":"PPL",
    "gn:name":"Hirip\u0101lya",
    "gn:population":0,
    "gn:timezone":"Asia/Kolkata",
    "iso:country":"IN",
    "ks:ks_name":"Hirepalya",
    "ks:ks_pop":598,
    "ks:ks_type":"VILLAGE",
    "ks:ks_uagg_main":0,
    "name:eng_x_preferred":[
        "Hirepalya"
    ],
    "wof:name":"Hirepalya",
    "wof:placetype":"neighbourhood",
    "wof:population":598
},
  "geometry": {"coordinates":[77.959231,13.284549],"type":"Point"}
}