{
  "type": "Feature",
  "properties": {
    "gn:admin1_code":"24",
    "gn:admin2_code":"114.0",
    "gn:asciiname":"Sadhan",
    "gn:country_code":"IN",
    "gn:dem":131,
    "gn:feature_class":"P",
    "gn:feature_code":"PPL",
    "gn:name":"S\u0101dhan",
    "gn:population":0,
    "gn:timezone":"Asia/Kolkata",
    "iso:country":"IN",
    "name:und_x_variant":[
        "S\u0101dhan",
        "Sadhan"
    ],
    "wof:name":"Sadhan",
    "wof:placetype":"neighbourhood"
},
  "geometry": {"coordinates":[70.69347,27.48429],"type":"Point"}
}