{
  "type": "Feature",
  "properties": {
    "iso:country":"IN",
    "ks:ks_name":"Tushyama",
    "ks:ks_pop":425,
    "ks:ks_type":"VILLAGE",
    "name:eng_x_preferred":[
        "Tushyama"
    ],
    "wof:name":"Tushyama",
    "wof:placetype":"locality",
    "wof:population":425
},
  "geometry": {"coordinates":[86.648218,23.116289],"type":"Point"}
}