{
  "type": "Feature",
  "properties": {
    "iso:country":"IN",
    "ks:ks_name":"Jharnapani",
    "ks:ks_pop":40,
    "ks:ks_type":"HABITATION",
    "name:eng_x_preferred":[
        "Jharnapani"
    ],
    "wof:name":"Jharnapani",
    "wof:placetype":"locality",
    "wof:population":40
},
  "geometry": {"coordinates":[85.517095,23.409793],"type":"Point"}
}