{
  "type": "Feature",
  "properties": {
    "iso:country":"IN",
    "ks:ks_alt_nam":"vettukadu",
    "ks:ks_name":"Vettukadu",
    "ks:ks_pop":34,
    "ks:ks_type":"HABITATION",
    "ks:ks_uagg_main":0,
    "name:eng_x_preferred":[
        "Vettukadu"
    ],
    "wof:name":"Vettukadu",
    "wof:placetype":"neighbourhood",
    "wof:population":34
},
  "geometry": {"coordinates":[77.947354,10.986376],"type":"Point"}
}