{
  "type": "Feature",
  "properties": {
    "gn:admin1_code":"12.0",
    "gn:admin2_code":"2.0",
    "gn:asciiname":"Ratinpur",
    "gn:country_code":"IN",
    "gn:dem":1755,
    "gn:feature_class":"P",
    "gn:feature_code":"PPL",
    "gn:name":"Ratinpur",
    "gn:population":0,
    "gn:timezone":"Asia/Kolkata",
    "iso:country":"IN",
    "wof:name":"Ratinpur",
    "wof:placetype":"locality"
},
  "geometry": {"coordinates":[74.71810000000001,33.98388],"type":"Point"}
}