{
  "type": "Feature",
  "properties": {
    "iso:country":"IN",
    "ks:ks_name":"Jot Lachhmi",
    "ks:ks_pop":1516,
    "ks:ks_type":"VILLAGE",
    "ks:ks_uagg_main":0,
    "name:eng_x_preferred":[
        "Jot Lachhmi"
    ],
    "wof:name":"Jot Lachhmi",
    "wof:placetype":"neighbourhood",
    "wof:population":1516
},
  "geometry": {"coordinates":[87.93762599999999,25.169038],"type":"Point"}
}