{
  "type": "Feature",
  "properties": {
    "iso:country":"IN",
    "ks:ks_name":"Narayan Kheda",
    "ks:ks_pop":260,
    "ks:ks_type":"HABITATION",
    "ks:ks_uagg_main":0,
    "name:eng_x_preferred":[
        "Narayan Kheda"
    ],
    "wof:name":"Narayan Kheda",
    "wof:placetype":"neighbourhood",
    "wof:population":260
},
  "geometry": {"coordinates":[80.687521,27.174612],"type":"Point"}
}