{
  "type": "Feature",
  "properties": {
    "iso:country":"IN",
    "ks:ks_name":"Hakkalageri",
    "ks:ks_pop":21,
    "ks:ks_type":"HABITATION",
    "name:eng_x_preferred":[
        "Hakkalageri"
    ],
    "wof:name":"Hakkalageri",
    "wof:placetype":"locality",
    "wof:population":21
},
  "geometry": {"coordinates":[74.941463,14.765542],"type":"Point"}
}