{
  "type": "Feature",
  "properties": {
    "gn:admin1_code":"11",
    "gn:admin2_code":"23.0",
    "gn:asciiname":"Gwar",
    "gn:country_code":"IN",
    "gn:dem":1796,
    "gn:feature_class":"P",
    "gn:feature_code":"PPL",
    "gn:name":"Gw\u0101r",
    "gn:population":0,
    "gn:timezone":"Asia/Kolkata",
    "iso:country":"IN",
    "name:deu_x_preferred":[
        "Gwar"
    ],
    "name:ell_x_preferred":[
        "Gwar"
    ],
    "name:fra_x_preferred":[
        "Gwar"
    ],
    "name:jpn_x_preferred":[
        "\u30b0\u30ef\u30a1\u30fc"
    ],
    "name:pol_x_preferred":[
        "Gwar"
    ],
    "name:por_x_preferred":[
        "Gwar"
    ],
    "name:spa_x_preferred":[
        "Gwar"
    ],
    "wof:name":"Gwar",
    "wof:placetype":"locality"
},
  "geometry": {"coordinates":[76.33787,32.48308],"type":"Point"}
}