{
  "type": "Feature",
  "properties": {
    "gn:admin1_code":"36",
    "gn:admin2_code":"160.0",
    "gn:asciiname":"Bhara",
    "gn:country_code":"IN",
    "gn:dem":145,
    "gn:feature_class":"P",
    "gn:feature_code":"PPL",
    "gn:name":"Bh\u0101ra",
    "gn:population":0,
    "gn:timezone":"Asia/Kolkata",
    "iso:country":"IN",
    "wof:name":"Bhara",
    "wof:placetype":"neighbourhood"
},
  "geometry": {"coordinates":[79.56001000000001,27.02064],"type":"Point"}
}