{
  "type": "Feature",
  "properties": {
    "iso:country":"IN",
    "ks:ks_name":"Machalpura",
    "ks:ks_pop":6590,
    "ks:ks_type":"VILLAGE",
    "name:eng_x_preferred":[
        "Machalpura"
    ],
    "wof:name":"Machalpura",
    "wof:placetype":"locality",
    "wof:population":6590
},
  "geometry": {"coordinates":[76.266289,21.368265],"type":"Point"}
}