{
  "type": "Feature",
  "properties": {
    "iso:country":"IN",
    "ks:ks_name":"Badaheren",
    "ks:ks_pop":134,
    "ks:ks_type":"HABITATION",
    "name:eng_x_preferred":[
        "Badaheren"
    ],
    "wof:name":"Badaheren",
    "wof:placetype":"locality",
    "wof:population":134
},
  "geometry": {"coordinates":[83.44775799999999,20.240233],"type":"Point"}
}