{
  "type": "Feature",
  "properties": {
    "gn:admin1_code":"36.0",
    "gn:admin2_code":"164.0",
    "gn:asciiname":"Ram Khera",
    "gn:country_code":"IN",
    "gn:dem":129,
    "gn:feature_class":"P",
    "gn:feature_code":"PPL",
    "gn:name":"R\u0101m Khera",
    "gn:population":0,
    "gn:timezone":"Asia/Kolkata",
    "iso:country":"IN",
    "wof:name":"Ram Khera",
    "wof:placetype":"locality"
},
  "geometry": {"coordinates":[80.27981,26.28277000000001],"type":"Point"}
}