{
  "type": "Feature",
  "properties": {
    "gn:admin1_code":"19.0",
    "gn:admin2_code":"572.0",
    "gn:asciiname":"Kandaikanpalli",
    "gn:country_code":"IN",
    "gn:dem":945,
    "gn:feature_class":"P",
    "gn:feature_code":"PPL",
    "gn:name":"Kand\u0101ikanpalli",
    "gn:population":0,
    "gn:timezone":"Asia/Kolkata",
    "iso:country":"IN",
    "wof:name":"Kandaikanpalli",
    "wof:placetype":"locality"
},
  "geometry": {"coordinates":[77.68058000000001,12.6734],"type":"Point"}
}