{
  "type": "Feature",
  "properties": {
    "iso:country":"IN",
    "ks:ks_name":"Dabrimunda",
    "ks:ks_pop":34,
    "ks:ks_type":"HABITATION",
    "name:eng_x_preferred":[
        "Dabrimunda"
    ],
    "wof:name":"Dabrimunda",
    "wof:placetype":"locality",
    "wof:population":34
},
  "geometry": {"coordinates":[82.423633,19.634973],"type":"Point"}
}