{
  "type": "Feature",
  "properties": {
    "gn:admin1_code":"7.0",
    "gn:admin2_code":"96.0",
    "gn:asciiname":"Nangloi Saiyea",
    "gn:country_code":"IN",
    "gn:dem":217,
    "gn:feature_class":"P",
    "gn:feature_code":"PPL",
    "gn:name":"N\u0101ngloi Saiyea",
    "gn:population":0,
    "gn:timezone":"Asia/Kolkata",
    "iso:country":"IN",
    "wof:name":"Nangloi Saiyea",
    "wof:placetype":"locality"
},
  "geometry": {"coordinates":[77.08426,28.66121],"type":"Point"}
}