{
  "type": "Feature",
  "properties": {
    "gn:admin1_code":"36",
    "gn:admin2_code":"158.0",
    "gn:asciiname":"Purwa Chaudhri Sahib",
    "gn:country_code":"IN",
    "gn:dem":116,
    "gn:feature_class":"P",
    "gn:feature_code":"PPL",
    "gn:name":"Purwa Chaudhri S\u0101hib",
    "gn:population":0,
    "gn:timezone":"Asia/Kolkata",
    "iso:country":"IN",
    "wof:name":"Purwa Chaudhri Sahib",
    "wof:placetype":"locality"
},
  "geometry": {"coordinates":[81.19773000000001,26.38583],"type":"Point"}
}