{
  "type": "Feature",
  "properties": {
    "iso:country":"IN",
    "ks:ks_name":"Bhaukmari",
    "ks:ks_pop":32,
    "ks:ks_type":"VILLAGE",
    "name:eng_x_preferred":[
        "Bhaukmari"
    ],
    "wof:name":"Bhaukmari",
    "wof:placetype":"locality",
    "wof:population":32
},
  "geometry": {"coordinates":[87.276928,22.583304],"type":"Point"}
}