{
  "type": "Feature",
  "properties": {
    "gn:admin1_code":"35.0",
    "gn:admin2_code":"439.0",
    "gn:asciiname":"Sukhnivas",
    "gn:country_code":"IN",
    "gn:dem":583,
    "gn:feature_class":"P",
    "gn:feature_code":"PPL",
    "gn:name":"Sukhniv\u0101s",
    "gn:population":0,
    "gn:timezone":"Asia/Kolkata",
    "iso:country":"IN",
    "wof:name":"Sukhnivas",
    "wof:placetype":"neighbourhood"
},
  "geometry": {"coordinates":[75.79742,22.67256],"type":"Point"}
}