{
  "type": "Feature",
  "properties": {
    "iso:country":"IN",
    "ks:ks_name":"Chinnagangapur",
    "ks:ks_pop":178,
    "ks:ks_type":"HABITATION",
    "name:eng_x_preferred":[
        "Chinnagangapur"
    ],
    "wof:name":"Chinnagangapur",
    "wof:placetype":"locality",
    "wof:population":178
},
  "geometry": {"coordinates":[78.73490700000001,19.367783],"type":"Point"}
}