{
  "type": "Feature",
  "properties": {
    "iso:country":"IN",
    "ks:ks_name":"Chutru",
    "ks:ks_pop":197,
    "ks:ks_type":"VILLAGE",
    "name:eng_x_preferred":[
        "Chutru"
    ],
    "wof:name":"Chutru",
    "wof:placetype":"locality",
    "wof:population":197
},
  "geometry": {"coordinates":[85.55395300000001,23.17482],"type":"Point"}
}