{
  "type": "Feature",
  "properties": {
    "iso:country":"IN",
    "ks:ks_name":"Kadamgudapara",
    "ks:ks_pop":390,
    "ks:ks_type":"HABITATION",
    "ks:ks_uagg_main":0,
    "name:eng_x_preferred":[
        "Kadamgudapara"
    ],
    "wof:name":"Kadamgudapara",
    "wof:placetype":"neighbourhood",
    "wof:population":390
},
  "geometry": {"coordinates":[81.845271,19.140551],"type":"Point"}
}