{
  "type": "Feature",
  "properties": {
    "iso:country":"IN",
    "ks:ks_alt_nam":"Tat\u0101rpur",
    "ks:ks_name":"Tatarpur",
    "ks:ks_type":"VILLAGE",
    "ks:ks_uagg_main":0,
    "name:eng_x_preferred":[
        "Tatarpur"
    ],
    "name:eng_x_variant":[
        "Tat\u0101rpur"
    ],
    "wof:name":"Tatarpur",
    "wof:placetype":"neighbourhood"
},
  "geometry": {"coordinates":[80.27684499999999,26.46638],"type":"Point"}
}