{
  "type": "Feature",
  "properties": {
    "gn:admin1_code":"12.0",
    "gn:admin2_code":"17.0",
    "gn:asciiname":"Bagen",
    "gn:country_code":"IN",
    "gn:dem":2241,
    "gn:feature_class":"P",
    "gn:feature_code":"PPL",
    "gn:name":"Bag\u0113n",
    "gn:population":0,
    "gn:timezone":"Asia/Kolkata",
    "iso:country":"IN",
    "wof:name":"Bagen",
    "wof:placetype":"locality"
},
  "geometry": {"coordinates":[75.28449999999999,33.3088],"type":"Point"}
}