{
  "type": "Feature",
  "properties": {
    "iso:country":"IN",
    "ks:ks_name":"Gunailanka",
    "ks:ks_pop":75,
    "ks:ks_type":"HABITATION",
    "name:eng_x_preferred":[
        "Gunailanka"
    ],
    "wof:name":"Gunailanka",
    "wof:placetype":"locality",
    "wof:population":75
},
  "geometry": {"coordinates":[82.240101,17.832462],"type":"Point"}
}