{
  "type": "Feature",
  "properties": {
    "iso:country":"IN",
    "ks:ks_alt_nam":"Talav faliya",
    "ks:ks_name":"Talav Faliya",
    "ks:ks_pop":50,
    "ks:ks_type":"HABITATION",
    "name:eng_x_preferred":[
        "Talav Faliya"
    ],
    "wof:name":"Talav Faliya",
    "wof:placetype":"locality",
    "wof:population":50
},
  "geometry": {"coordinates":[73.472762,20.530109],"type":"Point"}
}