{
  "type": "Feature",
  "properties": {
    "gn:admin1_code":"36",
    "gn:admin2_code":"146.0",
    "gn:asciiname":"Banjaran",
    "gn:country_code":"IN",
    "gn:dem":167,
    "gn:feature_class":"P",
    "gn:feature_code":"PPL",
    "gn:name":"Banj\u0101r\u0101n",
    "gn:population":0,
    "gn:timezone":"Asia/Kolkata",
    "iso:country":"IN",
    "name:fas_x_preferred":[
        "\u0628\u0627\u0646\u062c\u0627\u0631\u0627\u0646"
    ],
    "name:mlg_x_preferred":[
        "Banjaran"
    ],
    "name:new_x_preferred":[
        "\u092c\u0902\u091c\u093e\u0930\u0928"
    ],
    "wof:name":"Banjaran",
    "wof:placetype":"locality"
},
  "geometry": {"coordinates":[78.22178000000002,27.0173],"type":"Point"}
}