{
  "type": "Feature",
  "properties": {
    "iso:country":"IN",
    "ks:ks_alt_nam":"KALAMALA",
    "ks:ks_name":"Kalamala",
    "ks:ks_pop":130,
    "ks:ks_type":"HABITATION",
    "name:eng_x_preferred":[
        "Kalamala"
    ],
    "wof:name":"Kalamala",
    "wof:placetype":"locality",
    "wof:population":130
},
  "geometry": {"coordinates":[75.023163,17.152172],"type":"Point"}
}