{
  "type": "Feature",
  "properties": {
    "iso:country":"IN",
    "ks:ks_name":"Sonatungri",
    "ks:ks_pop":175,
    "ks:ks_type":"HABITATION",
    "name:eng_x_preferred":[
        "Sonatungri"
    ],
    "wof:name":"Sonatungri",
    "wof:placetype":"locality",
    "wof:population":175
},
  "geometry": {"coordinates":[85.77605800000001,23.446699],"type":"Point"}
}