{
  "type": "Feature",
  "properties": {
    "gn:admin1_code":"16.0",
    "gn:admin2_code":"530",
    "gn:asciiname":"Alta",
    "gn:country_code":"IN",
    "gn:dem":612,
    "gn:feature_class":"P",
    "gn:feature_code":"PPL",
    "gn:name":"Alta",
    "gn:population":0,
    "gn:timezone":"Asia/Kolkata",
    "iso:country":"IN",
    "name:ben_x_preferred":[
        "\u0986\u09b2\u09a4\u09be"
    ],
    "name:bpy_x_preferred":[
        "\u0986\u09b2\u099f\u09be"
    ],
    "name:ceb_x_preferred":[
        "Alta"
    ],
    "name:ces_x_preferred":[
        "Alta"
    ],
    "name:dan_x_preferred":[
        "Alta"
    ],
    "name:deu_x_preferred":[
        "Alta"
    ],
    "name:ell_x_preferred":[
        "\u0386\u03bb\u03c4\u03b1"
    ],
    "name:est_x_preferred":[
        "Alta"
    ],
    "name:fra_x_preferred":[
        "Alta"
    ],
    "name:glg_x_preferred":[
        "Alta"
    ],
    "name:heb_x_preferred":[
        "\u05d0\u05dc\u05d8\u05d0"
    ],
    "name:hin_x_preferred":[
        "\u0906\u0932\u094d\u091f\u093e"
    ],
    "name:hun_x_preferred":[
        "Alta"
    ],
    "name:ind_x_preferred":[
        "Alta"
    ],
    "name:ita_x_preferred":[
        "Alta"
    ],
    "name:jpn_x_preferred":[
        "\u30a2\u30eb\u30bf"
    ],
    "name:kor_x_preferred":[
        "\uc54c\ud0c0"
    ],
    "name:nld_x_preferred":[
        "Alta"
    ],
    "name:nor_x_preferred":[
        "Alta"
    ],
    "name:pol_x_preferred":[
        "Alta"
    ],
    "name:por_x_preferred":[
        "Alta"
    ],
    "name:ron_x_preferred":[
        "Alta"
    ],
    "name:rus_x_preferred":[
        "\u0410\u043b\u044c\u0442\u0430"
    ],
    "name:slv_x_preferred":[
        "Alta"
    ],
    "name:spa_x_preferred":[
        "Alta"
    ],
    "name:srp_x_preferred":[
        "\u0410\u043b\u0442\u0430"
    ],
    "name:swe_x_preferred":[
        "Alta"
    ],
    "name:tur_x_preferred":[
        "Alta"
    ],
    "name:ukr_x_preferred":[
        "\u0410\u043b\u044c\u0442\u0430"
    ],
    "name:und_x_variant":[
        "Alate"
    ],
    "name:urd_x_preferred":[
        "\u0622\u0644\u0679\u0627"
    ],
    "name:vie_x_preferred":[
        "Alta"
    ],
    "name:vol_x_preferred":[
        "Alta"
    ],
    "wof:name":"Alta",
    "wof:placetype":"locality"
},
  "geometry": {"coordinates":[74.40434,16.77026],"type":"Point"}
}