{
  "type": "Feature",
  "properties": {
    "gn:admin1_code":"16.0",
    "gn:admin2_code":"530",
    "gn:asciiname":"Alta",
    "gn:country_code":"IN",
    "gn:dem":612,
    "gn:feature_class":"P",
    "gn:feature_code":"PPL",
    "gn:name":"Alta",
    "gn:population":0,
    "gn:timezone":"Asia/Kolkata",
    "iso:country":"IN",
    "name:und_x_variant":[
        "Alate",
        "Alta"
    ],
    "wof:name":"Alta",
    "wof:placetype":"locality"
},
  "geometry": {"coordinates":[74.40434,16.77026],"type":"Point"}
}