{
  "type": "Feature",
  "properties": {
    "iso:country":"IN",
    "ks:ks_name":"Kushdadar",
    "ks:ks_pop":385,
    "ks:ks_type":"VILLAGE",
    "name:eng_x_preferred":[
        "Kushdadar"
    ],
    "wof:name":"Kushdadar",
    "wof:placetype":"locality",
    "wof:population":385
},
  "geometry": {"coordinates":[83.66095300000001,21.032856],"type":"Point"}
}