{
  "type": "Feature",
  "properties": {
    "gn:admin1_code":"35",
    "gn:admin2_code":"460.0",
    "gn:asciiname":"Hinauta",
    "gn:country_code":"IN",
    "gn:dem":363,
    "gn:feature_class":"P",
    "gn:feature_code":"PPL",
    "gn:name":"Hinauta",
    "gn:population":0,
    "gn:timezone":"Asia/Kolkata",
    "iso:country":"IN",
    "ks:ks_name":"Hinauta",
    "ks:ks_pop":44,
    "ks:ks_type":"VILLAGE",
    "name:eng_x_preferred":[
        "Hinauta"
    ],
    "wof:name":"Hinauta",
    "wof:placetype":"locality",
    "wof:population":44
},
  "geometry": {"coordinates":[81.11497799999999,24.067701],"type":"Point"}
}