{
  "type": "Feature",
  "properties": {
    "iso:country":"IN",
    "ks:ks_alt_nam":"Hanum\u0101n Nagar",
    "ks:ks_name":"Hanuman Nagar",
    "ks:ks_type":"VILLAGE",
    "ks:ks_uagg_main":0,
    "name:eng_x_preferred":[
        "Hanuman Nagar"
    ],
    "name:eng_x_variant":[
        "Hanum\u0101n Nagar"
    ],
    "wof:name":"Hanuman Nagar",
    "wof:placetype":"neighbourhood"
},
  "geometry": {"coordinates":[85.164705,25.591981],"type":"Point"}
}