{
  "type": "Feature",
  "properties": {
    "gn:admin1_code":"12.0",
    "gn:admin2_code":"001",
    "gn:asciiname":"Tsaraligund",
    "gn:country_code":"IN",
    "gn:dem":1717,
    "gn:feature_class":"P",
    "gn:feature_code":"PPL",
    "gn:name":"Tsar\u0101ligund",
    "gn:population":0,
    "gn:timezone":"Asia/Kolkata",
    "iso:country":"IN",
    "wof:name":"Tsaraligund",
    "wof:placetype":"locality"
},
  "geometry": {"coordinates":[74.42599,34.4903],"type":"Point"}
}