{
  "type": "Feature",
  "properties": {
    "iso:country":"IN",
    "ks:ks_name":"Baduguvaripeta",
    "ks:ks_pop":1080,
    "ks:ks_type":"HABITATION",
    "name:eng_x_preferred":[
        "Baduguvaripeta"
    ],
    "wof:name":"Baduguvaripeta",
    "wof:placetype":"locality",
    "wof:population":1080
},
  "geometry": {"coordinates":[82.026672,16.566864],"type":"Point"}
}