{
  "type": "Feature",
  "properties": {
    "iso:country":"IN",
    "ks:ks_name":"Kodaguda",
    "ks:ks_pop":7,
    "ks:ks_type":"HABITATION",
    "name:eng_x_preferred":[
        "Kodaguda"
    ],
    "wof:name":"Kodaguda",
    "wof:placetype":"locality",
    "wof:population":7
},
  "geometry": {"coordinates":[82.302623,18.405383],"type":"Point"}
}