{
  "type": "Feature",
  "properties": {
    "gn:admin1_code":"36.0",
    "gn:admin2_code":"183.0",
    "gn:asciiname":"Pura Nirman Singh",
    "gn:country_code":"IN",
    "gn:dem":102,
    "gn:feature_class":"P",
    "gn:feature_code":"PPL",
    "gn:name":"Pura Nirman Singh",
    "gn:population":0,
    "gn:timezone":"Asia/Kolkata",
    "iso:country":"IN",
    "wof:name":"Pura Nirman Singh",
    "wof:placetype":"locality"
},
  "geometry": {"coordinates":[82.15575,26.94768],"type":"Point"}
}