{
  "type": "Feature",
  "properties": {
    "iso:country":"IN",
    "ks:ks_name":"Gholpukuria East",
    "ks:ks_pop":2120,
    "ks:ks_type":"HABITATION",
    "name:eng_x_preferred":[
        "Gholpukuria East"
    ],
    "wof:name":"Gholpukuria East",
    "wof:placetype":"locality",
    "wof:population":2120
},
  "geometry": {"coordinates":[87.867766,22.008093],"type":"Point"}
}