{
  "type": "Feature",
  "properties": {
    "gn:admin1_code":"28.0",
    "gn:admin2_code":"328.0",
    "gn:asciiname":"Diana",
    "gn:country_code":"IN",
    "gn:dem":200,
    "gn:feature_class":"P",
    "gn:feature_code":"PPL",
    "gn:name":"Diana",
    "gn:population":0,
    "gn:timezone":"Asia/Kolkata",
    "iso:country":"IN",
    "wof:name":"Diana",
    "wof:placetype":"locality"
},
  "geometry": {"coordinates":[89.00059,26.85446],"type":"Point"}
}