{
  "type": "Feature",
  "properties": {
    "gn:admin1_code":"37",
    "gn:admin2_code":"406.0",
    "gn:asciiname":"Lusda",
    "gn:country_code":"IN",
    "gn:dem":390,
    "gn:feature_class":"P",
    "gn:feature_code":"PPL",
    "gn:name":"Lusda",
    "gn:population":0,
    "gn:timezone":"Asia/Kolkata",
    "iso:country":"IN",
    "ks:ks_name":"Lusda",
    "ks:ks_type":"VILLAGE",
    "name:eng_x_preferred":[
        "Lusda"
    ],
    "wof:name":"Lusda",
    "wof:placetype":"locality"
},
  "geometry": {"coordinates":[82.13825900000001,22.568701],"type":"Point"}
}