{
  "type": "Feature",
  "properties": {
    "gn:admin1_code":"11",
    "gn:admin2_code":"33.0",
    "gn:asciiname":"Behrog",
    "gn:country_code":"IN",
    "gn:dem":2275,
    "gn:feature_class":"P",
    "gn:feature_code":"PPL",
    "gn:name":"Behrog",
    "gn:population":0,
    "gn:timezone":"Asia/Kolkata",
    "iso:country":"IN",
    "wof:name":"Behrog",
    "wof:placetype":"locality"
},
  "geometry": {"coordinates":[77.69701999999999,30.98939],"type":"Point"}
}