{
  "type": "Feature",
  "properties": {
    "gn:admin1_code":"24.0",
    "gn:admin2_code":"100.0",
    "gn:asciiname":"Mehliya",
    "gn:country_code":"IN",
    "gn:dem":202,
    "gn:feature_class":"P",
    "gn:feature_code":"PPL",
    "gn:name":"Mehliya",
    "gn:population":0,
    "gn:timezone":"Asia/Kolkata",
    "iso:country":"IN",
    "ks:ks_name":"Mehliya",
    "ks:ks_pop":876,
    "ks:ks_type":"VILLAGE",
    "name:eng_x_preferred":[
        "Mehliya"
    ],
    "wof:name":"Mehliya",
    "wof:placetype":"locality",
    "wof:population":876
},
  "geometry": {"coordinates":[75.046069,28.962131],"type":"Point"}
}