{
  "type": "Feature",
  "properties": {
    "gn:admin1_code":"24.0",
    "gn:admin2_code":"118",
    "gn:asciiname":"Dholerao ki Dhani",
    "gn:country_code":"IN",
    "gn:dem":219,
    "gn:feature_class":"P",
    "gn:feature_code":"PPL",
    "gn:name":"Dholerao ki Dh\u0101ni",
    "gn:population":0,
    "gn:timezone":"Asia/Kolkata",
    "iso:country":"IN",
    "name:und_x_variant":[
        "Dholerao ki Dh\u0101ni",
        "Dholerao"
    ],
    "wof:name":"Dholerao ki Dhani",
    "wof:placetype":"neighbourhood"
},
  "geometry": {"coordinates":[73.36612,25.95424],"type":"Point"}
}