{
  "type": "Feature",
  "properties": {
    "gn:admin1_code":"36",
    "gn:admin2_code":"180.0",
    "gn:asciiname":"Bankati",
    "gn:country_code":"IN",
    "gn:dem":141,
    "gn:feature_class":"P",
    "gn:feature_code":"PPL",
    "gn:name":"Bankati",
    "gn:population":0,
    "gn:timezone":"Asia/Kolkata",
    "iso:country":"IN",
    "ks:ks_alt_nam":"BANKATI",
    "ks:ks_name":"Bankati",
    "ks:ks_pop":402,
    "ks:ks_type":"HABITATION",
    "name:eng_x_preferred":[
        "Bankati"
    ],
    "wof:name":"Bankati",
    "wof:placetype":"locality",
    "wof:population":402
},
  "geometry": {"coordinates":[81.44962,27.975918],"type":"Point"}
}