{
  "type": "Feature",
  "properties": {
    "iso:country":"IN",
    "ks:ks_name":"Daulaniyonka Tala",
    "ks:ks_pop":1058,
    "ks:ks_type":"VILLAGE",
    "name:eng_x_preferred":[
        "Daulaniyonka Tala"
    ],
    "wof:name":"Daulaniyonka Tala",
    "wof:placetype":"locality",
    "wof:population":1058
},
  "geometry": {"coordinates":[71.66981699999999,25.637428],"type":"Point"}
}