{
  "type": "Feature",
  "properties": {
    "iso:country":"IN",
    "ks:ks_alt_nam":"shuklanpurwa",
    "ks:ks_name":"Shuklanpurwa",
    "ks:ks_pop":120,
    "ks:ks_type":"HABITATION",
    "ks:ks_uagg_main":0,
    "name:eng_x_preferred":[
        "Shuklanpurwa"
    ],
    "wof:name":"Shuklanpurwa",
    "wof:placetype":"neighbourhood",
    "wof:population":120
},
  "geometry": {"coordinates":[81.791073,27.323615],"type":"Point"}
}