{
  "type": "Feature",
  "properties": {
    "gn:admin1_code":"10.0",
    "gn:admin2_code":"82.0",
    "gn:asciiname":"Sukhpura",
    "gn:country_code":"IN",
    "gn:dem":223,
    "gn:feature_class":"P",
    "gn:feature_code":"PPL",
    "gn:name":"Sukhpura",
    "gn:population":0,
    "gn:timezone":"Asia/Kolkata",
    "iso:country":"IN",
    "wof:name":"Sukhpura",
    "wof:placetype":"locality"
},
  "geometry": {"coordinates":[76.59398,28.91149],"type":"Point"}
}