{
  "type": "Feature",
  "properties": {
    "iso:country":"IN",
    "ks:ks_name":"Gundlamadugu",
    "ks:ks_pop":107,
    "ks:ks_type":"HABITATION",
    "name:eng_x_preferred":[
        "Gundlamadugu"
    ],
    "wof:name":"Gundlamadugu",
    "wof:placetype":"locality",
    "wof:population":107
},
  "geometry": {"coordinates":[80.580516,17.603318],"type":"Point"}
}