{
  "type": "Feature",
  "properties": {
    "iso:country":"IN",
    "ks:ks_name":"Karradand",
    "ks:ks_pop":510,
    "ks:ks_type":"HABITATION",
    "name:eng_x_preferred":[
        "Karradand"
    ],
    "wof:name":"Karradand",
    "wof:placetype":"locality",
    "wof:population":510
},
  "geometry": {"coordinates":[83.963375,23.253451],"type":"Point"}
}