{
  "type": "Feature",
  "properties": {
    "iso:country":"IN",
    "ks:ks_name":"Kadachhala",
    "ks:ks_pop":847,
    "ks:ks_type":"VILLAGE",
    "ks:ks_uagg_main":0,
    "name:eng_x_preferred":[
        "Kadachhala"
    ],
    "wof:name":"Kadachhala",
    "wof:placetype":"neighbourhood",
    "wof:population":847
},
  "geometry": {"coordinates":[73.329083,22.698889],"type":"Point"}
}