{
  "type": "Feature",
  "properties": {
    "gn:admin1_code":"36.0",
    "gn:admin2_code":"161",
    "gn:asciiname":"Bhajupura",
    "gn:country_code":"IN",
    "gn:dem":122,
    "gn:feature_class":"P",
    "gn:feature_code":"PPL",
    "gn:name":"Bh\u0101jupura",
    "gn:population":0,
    "gn:timezone":"Asia/Kolkata",
    "iso:country":"IN",
    "name:und_x_variant":[
        "Bhajanpura",
        "Bh\u0101jupura"
    ],
    "wof:name":"Bhajupura",
    "wof:placetype":"locality"
},
  "geometry": {"coordinates":[79.19899000000002,26.43453],"type":"Point"}
}