{
  "type": "Feature",
  "properties": {
    "gn:admin1_code":"35",
    "gn:admin2_code":"430.0",
    "gn:asciiname":"Bajrangpur",
    "gn:country_code":"IN",
    "gn:dem":319,
    "gn:feature_class":"P",
    "gn:feature_code":"PPL",
    "gn:name":"Bajrangpur",
    "gn:population":0,
    "gn:timezone":"Asia/Kolkata",
    "iso:country":"IN",
    "ks:ks_name":"Bajrangpur",
    "ks:ks_pop":541,
    "ks:ks_type":"VILLAGE",
    "ks:ks_uagg_main":0,
    "name:eng_x_preferred":[
        "Bajrangpur"
    ],
    "wof:name":"Bajrangpur",
    "wof:placetype":"neighbourhood",
    "wof:population":541
},
  "geometry": {"coordinates":[81.403976,24.459594],"type":"Point"}
}