{
  "type": "Feature",
  "properties": {
    "iso:country":"IN",
    "ks:ks_name":"8 KKM",
    "ks:ks_pop":1112,
    "ks:ks_type":"VILLAGE",
    "ks:ks_uagg_main":0,
    "name:eng_x_preferred":[
        "8 KKM"
    ],
    "wof:name":"8 KKM",
    "wof:placetype":"neighbourhood",
    "wof:population":1112
},
  "geometry": {"coordinates":[74.44398700000001,29.083736],"type":"Point"}
}