{
  "type": "Feature",
  "properties": {
    "iso:country":"IN",
    "ks:ks_name":"Goraha",
    "ks:ks_pop":39,
    "ks:ks_type":"VILLAGE",
    "name:eng_x_preferred":[
        "Goraha"
    ],
    "wof:name":"Goraha",
    "wof:placetype":"locality",
    "wof:population":39
},
  "geometry": {"coordinates":[83.504295,24.595176],"type":"Point"}
}