{
  "type": "Feature",
  "properties": {
    "iso:country":"IN",
    "ks:ks_name":"Akardh",
    "ks:ks_pop":499,
    "ks:ks_type":"HABITATION",
    "ks:ks_uagg_main":0,
    "name:eng_x_preferred":[
        "Akardh"
    ],
    "wof:name":"Akardh",
    "wof:placetype":"neighbourhood",
    "wof:population":499
},
  "geometry": {"coordinates":[86.456481,25.962789],"type":"Point"}
}