{
  "type": "Feature",
  "properties": {
    "iso:country":"IN",
    "ks:ks_name":"Mamli",
    "ks:ks_pop":1200,
    "ks:ks_type":"VILLAGE",
    "ks:ks_uagg_main":0,
    "name:eng_x_preferred":[
        "Mamli"
    ],
    "wof:name":"Mamli",
    "wof:placetype":"neighbourhood",
    "wof:population":1200
},
  "geometry": {"coordinates":[77.310867,30.220249],"type":"Point"}
}