{
  "type": "Feature",
  "properties": {
    "iso:country":"IN",
    "ks:ks_name":"Nalwadewasti",
    "ks:ks_pop":1440,
    "ks:ks_type":"HABITATION",
    "ks:ks_uagg_main":0,
    "name:eng_x_preferred":[
        "Nalwadewasti"
    ],
    "wof:name":"Nalwadewasti",
    "wof:placetype":"neighbourhood",
    "wof:population":1440
},
  "geometry": {"coordinates":[74.788702,18.032665],"type":"Point"}
}