{
  "type": "Feature",
  "properties": {
    "iso:country":"IN",
    "ks:ks_name":"Raypur",
    "ks:ks_pop":813,
    "ks:ks_type":"VILLAGE",
    "ks:ks_uagg_main":0,
    "name:eng_x_preferred":[
        "Raypur"
    ],
    "wof:name":"Raypur",
    "wof:placetype":"locality",
    "wof:population":813
},
  "geometry": {"coordinates":[88.285431,25.572113],"type":"Point"}
}