{
  "type": "Feature",
  "properties": {
    "iso:country":"IN",
    "ks:ks_name":"A N Kunta",
    "ks:ks_pop":436,
    "ks:ks_type":"HABITATION",
    "ks:ks_uagg_main":0,
    "name:eng_x_preferred":[
        "A N Kunta"
    ],
    "wof:name":"A N Kunta",
    "wof:placetype":"neighbourhood",
    "wof:population":436
},
  "geometry": {"coordinates":[78.58869199999999,13.409562],"type":"Point"}
}