{
  "type": "Feature",
  "properties": {
    "iso:country":"IN",
    "ks:ks_name":"Sanglikuppam",
    "ks:ks_pop":218,
    "ks:ks_type":"HABITATION",
    "ks:ks_uagg_main":0,
    "name:eng_x_preferred":[
        "Sanglikuppam"
    ],
    "wof:name":"Sanglikuppam",
    "wof:placetype":"neighbourhood",
    "wof:population":218
},
  "geometry": {"coordinates":[79.846351,10.738228],"type":"Point"}
}