{
  "type": "Feature",
  "properties": {
    "iso:country":"IN",
    "ks:ks_alt_nam":"GULE IMADE WASTI",
    "ks:ks_name":"Gule Imade Wasti",
    "ks:ks_pop":100,
    "ks:ks_type":"HABITATION",
    "name:eng_x_preferred":[
        "Gule Imade Wasti"
    ],
    "wof:name":"Gule Imade Wasti",
    "wof:placetype":"locality",
    "wof:population":100
},
  "geometry": {"coordinates":[74.953307,17.05931],"type":"Point"}
}