{
  "type": "Feature",
  "properties": {
    "iso:country":"IN",
    "ks:ks_name":"Dundi",
    "ks:ks_pop":6,
    "ks:ks_type":"VILLAGE",
    "name:eng_x_preferred":[
        "Dundi"
    ],
    "wof:name":"Dundi",
    "wof:placetype":"locality",
    "wof:population":6
},
  "geometry": {"coordinates":[80.306611,23.456181],"type":"Point"}
}