{
  "type": "Feature",
  "properties": {
    "gn:admin1_code":"35",
    "gn:admin2_code":"428.0",
    "gn:asciiname":"Kindraha",
    "gn:country_code":"IN",
    "gn:dem":369,
    "gn:feature_class":"P",
    "gn:feature_code":"PPL",
    "gn:name":"Kindraha",
    "gn:population":0,
    "gn:timezone":"Asia/Kolkata",
    "iso:country":"IN",
    "name:und_x_variant":[
        "Kindaraho"
    ],
    "wof:name":"Kindraha",
    "wof:placetype":"locality"
},
  "geometry": {"coordinates":[79.24434000000002,23.91058],"type":"Point"}
}