{
  "type": "Feature",
  "properties": {
    "iso:country":"IN",
    "ks:ks_name":"Tarchool",
    "ks:ks_pop":791,
    "ks:ks_type":"HABITATION",
    "name:eng_x_preferred":[
        "Tarchool"
    ],
    "wof:name":"Tarchool",
    "wof:placetype":"locality",
    "wof:population":791
},
  "geometry": {"coordinates":[80.962582,20.347227],"type":"Point"}
}