{
  "type": "Feature",
  "properties": {
    "iso:country":"IN",
    "ks:ks_name":"Latigram",
    "ks:ks_pop":2513,
    "ks:ks_type":"VILLAGE",
    "ks:ks_uagg_main":0,
    "name:eng_x_preferred":[
        "Latigram"
    ],
    "wof:name":"Latigram",
    "wof:placetype":"neighbourhood",
    "wof:population":2513
},
  "geometry": {"coordinates":[92.85861199999999,24.890749],"type":"Point"}
}