{
  "type": "Feature",
  "properties": {
    "iso:country":"IN",
    "ks:ks_name":"Adiwas",
    "ks:ks_pop":277,
    "ks:ks_type":"VILLAGE",
    "name:eng_x_preferred":[
        "Adiwas"
    ],
    "wof:name":"Adiwas",
    "wof:placetype":"locality",
    "wof:population":277
},
  "geometry": {"coordinates":[73.356133,24.352547],"type":"Point"}
}