{
  "type": "Feature",
  "properties": {
    "iso:country":"IN",
    "ks:ks_name":"Ramel Bangar",
    "ks:ks_pop":1358,
    "ks:ks_type":"VILLAGE",
    "ks:ks_uagg_main":0,
    "name:eng_x_preferred":[
        "Ramel Bangar"
    ],
    "wof:name":"Ramel Bangar",
    "wof:placetype":"neighbourhood",
    "wof:population":1358
},
  "geometry": {"coordinates":[80.269718,26.592885],"type":"Point"}
}