{
  "type": "Feature",
  "properties": {
    "gn:admin1_code":"36",
    "gn:admin2_code":"145.0",
    "gn:asciiname":"Rasmai",
    "gn:country_code":"IN",
    "gn:dem":175,
    "gn:feature_class":"P",
    "gn:feature_code":"PPL",
    "gn:name":"Rasmai",
    "gn:population":0,
    "gn:timezone":"Asia/Kolkata",
    "iso:country":"IN",
    "ks:ks_name":"Rasmai",
    "ks:ks_pop":1166,
    "ks:ks_type":"HABITATION",
    "name:eng_x_preferred":[
        "Rasmai"
    ],
    "wof:name":"Rasmai",
    "wof:placetype":"locality",
    "wof:population":1166
},
  "geometry": {"coordinates":[77.93498599999999,27.478583],"type":"Point"}
}