{
  "type": "Feature",
  "properties": {
    "iso:country":"IN",
    "ks:ks_name":"Ochinda",
    "ks:ks_pop":15,
    "ks:ks_type":"VILLAGE",
    "name:eng_x_preferred":[
        "Ochinda"
    ],
    "wof:name":"Ochinda",
    "wof:placetype":"locality",
    "wof:population":15
},
  "geometry": {"coordinates":[86.393631,20.222731],"type":"Point"}
}