{
  "type": "Feature",
  "properties": {
    "iso:country":"IN",
    "ks:ks_name":"Bujjikattavara",
    "ks:ks_pop":25,
    "ks:ks_type":"HABITATION",
    "name:eng_x_preferred":[
        "Bujjikattavara"
    ],
    "wof:name":"Bujjikattavara",
    "wof:placetype":"locality",
    "wof:population":25
},
  "geometry": {"coordinates":[75.873611,12.744444],"type":"Point"}
}