{
  "type": "Feature",
  "properties": {
    "iso:country":"IN",
    "ks:ks_name":"Rangaiahnapalya",
    "ks:ks_pop":322,
    "ks:ks_type":"HABITATION",
    "name:eng_x_preferred":[
        "Rangaiahnapalya"
    ],
    "wof:name":"Rangaiahnapalya",
    "wof:placetype":"locality",
    "wof:population":322
},
  "geometry": {"coordinates":[77.203632,13.099711],"type":"Point"}
}