{
  "type": "Feature",
  "properties": {
    "gn:admin1_code":"36",
    "gn:admin2_code":"159.0",
    "gn:asciiname":"Lalaur Jumardaran",
    "gn:country_code":"IN",
    "gn:dem":156,
    "gn:feature_class":"P",
    "gn:feature_code":"PPL",
    "gn:name":"Lalaur Jum\u0101rd\u0101ran",
    "gn:population":0,
    "gn:timezone":"Asia/Kolkata",
    "iso:country":"IN",
    "wof:name":"Lalaur Jumardaran",
    "wof:placetype":"neighbourhood"
},
  "geometry": {"coordinates":[79.46987,27.50578],"type":"Point"}
}