{
  "type": "Feature",
  "properties": {
    "gn:admin1_code":"25.0",
    "gn:admin2_code":"632.0",
    "gn:asciiname":"Thondamuthur",
    "gn:country_code":"IN",
    "gn:dem":450,
    "gn:feature_class":"P",
    "gn:feature_code":"PPL",
    "gn:name":"Thondamuthur",
    "gn:population":0,
    "gn:timezone":"Asia/Kolkata",
    "iso:country":"IN",
    "name:bpy_x_preferred":[
        "\u09a5\u09cb\u09a8\u09cd\u09a6\u09be\u09ae\u0989\u09a5\u09c1\u09b0"
    ],
    "name:ceb_x_preferred":[
        "Thondamuthur"
    ],
    "name:ita_x_preferred":[
        "Thondamuthur"
    ],
    "name:msa_x_preferred":[
        "Thondamuthur"
    ],
    "name:nld_x_preferred":[
        "Thondamuthur"
    ],
    "name:por_x_preferred":[
        "Thondamuthur"
    ],
    "name:swe_x_preferred":[
        "Thondamuthur"
    ],
    "name:tam_x_preferred":[
        "\u0ba4\u0bca\u0ba3\u0bcd\u0b9f\u0bbe\u0bae\u0bc1\u0ba4\u0bcd\u0ba4\u0bc2\u0bb0\u0bcd"
    ],
    "name:vie_x_preferred":[
        "Thondamuthur"
    ],
    "name:zho_x_preferred":[
        "\u901a\u8fbe\u7a46\u56fe\u5c14"
    ],
    "wof:name":"Thondamuthur",
    "wof:placetype":"locality"
},
  "geometry": {"coordinates":[76.84181,10.99082],"type":"Point"}
}