{
  "type": "Feature",
  "properties": {
    "gn:admin1_code":"35.0",
    "gn:admin2_code":"464",
    "gn:asciiname":"Karwar",
    "gn:country_code":"IN",
    "gn:dem":400,
    "gn:feature_class":"P",
    "gn:feature_code":"PPL",
    "gn:name":"Karwar",
    "gn:population":0,
    "gn:timezone":"Asia/Kolkata",
    "iso:country":"IN",
    "name:bar_x_preferred":[
        "Karwar"
    ],
    "name:ben_x_preferred":[
        "\u0995\u09be\u09b0\u0993\u09af\u09bc\u09be\u09b0"
    ],
    "name:bpy_x_preferred":[
        "\u0995\u09be\u09b0\u09f1\u09be\u09b0"
    ],
    "name:cat_x_preferred":[
        "Karwar"
    ],
    "name:ceb_x_preferred":[
        "Karwar"
    ],
    "name:deu_x_preferred":[
        "Karwar"
    ],
    "name:fas_x_preferred":[
        "\u06a9\u0631\u0648\u0627\u0631"
    ],
    "name:fra_x_preferred":[
        "Karwar"
    ],
    "name:gom_x_preferred":[
        "\u0915\u093e\u0930\u0935\u093e\u0930"
    ],
    "name:guj_x_preferred":[
        "\u0a95\u0abe\u0ab0\u0ab5\u0abe\u0ab0"
    ],
    "name:hin_x_preferred":[
        "\u0915\u093e\u0930\u0935\u093e\u0930"
    ],
    "name:hun_x_preferred":[
        "K\u00e1rv\u00e1r"
    ],
    "name:ita_x_preferred":[
        "Karwar"
    ],
    "name:kan_x_preferred":[
        "\u0c95\u0cbe\u0cb0\u0cb5\u0cbe\u0cb0"
    ],
    "name:mar_x_preferred":[
        "\u0915\u093e\u0930\u0935\u093e\u0930"
    ],
    "name:mlg_x_preferred":[
        "Karwar"
    ],
    "name:msa_x_preferred":[
        "Karwar"
    ],
    "name:new_x_preferred":[
        "\u0915\u093e\u0930\u0935\u093e\u0930"
    ],
    "name:nld_x_preferred":[
        "Karwar"
    ],
    "name:nor_x_preferred":[
        "Karwar"
    ],
    "name:ori_x_preferred":[
        "\u0b15\u0b3e\u0b30\u0b4d\u0b71\u0b3e\u0b30\u0b4d"
    ],
    "name:pam_x_preferred":[
        "Karwar"
    ],
    "name:pol_x_preferred":[
        "Karwar"
    ],
    "name:por_x_preferred":[
        "Karwar"
    ],
    "name:rus_x_preferred":[
        "\u041a\u0430\u0440\u0432\u0430\u0440"
    ],
    "name:san_x_preferred":[
        "\u0915\u093e\u0930\u0935\u093e\u0930\u092e\u094d"
    ],
    "name:spa_x_preferred":[
        "Karwar"
    ],
    "name:swe_x_preferred":[
        "Karwar"
    ],
    "name:tam_x_preferred":[
        "\u0b95\u0bbe\u0bb0\u0bcd\u0bb5\u0bbe\u0bb0\u0bcd"
    ],
    "name:tcy_x_preferred":[
        "\u0c95\u0cbe\u0cb0\u0cb5\u0cbe\u0cb0"
    ],
    "name:urd_x_preferred":[
        "\u06a9\u0627\u0631\u0648\u0627\u0631"
    ],
    "name:vie_x_preferred":[
        "Karwar"
    ],
    "name:zho_x_preferred":[
        "\u5361\u5c14\u74e6\u5c14"
    ],
    "wof:name":"Karwar",
    "wof:placetype":"locality"
},
  "geometry": {"coordinates":[74.86938000000001,23.105],"type":"Point"}
}