{
  "type": "Feature",
  "properties": {
    "gn:admin1_code":"35.0",
    "gn:admin2_code":"464",
    "gn:asciiname":"Karwar",
    "gn:country_code":"IN",
    "gn:dem":400,
    "gn:feature_class":"P",
    "gn:feature_code":"PPL",
    "gn:name":"Karwar",
    "gn:population":0,
    "gn:timezone":"Asia/Kolkata",
    "iso:country":"IN",
    "wof:name":"Karwar",
    "wof:placetype":"locality"
},
  "geometry": {"coordinates":[74.86938000000001,23.105],"type":"Point"}
}