{
  "type": "Feature",
  "properties": {
    "iso:country":"IN",
    "ks:ks_name":"Jugatipura",
    "ks:ks_pop":45,
    "ks:ks_type":"VILLAGE",
    "name:eng_x_preferred":[
        "Jugatipura"
    ],
    "wof:name":"Jugatipura",
    "wof:placetype":"locality",
    "wof:population":45
},
  "geometry": {"coordinates":[77.451352,26.20249],"type":"Point"}
}