{
  "type": "Feature",
  "properties": {
    "iso:country":"IN",
    "ks:ks_name":"Krishnaperi",
    "ks:ks_pop":40,
    "ks:ks_type":"HABITATION",
    "ks:ks_uagg_main":0,
    "name:eng_x_preferred":[
        "Krishnaperi"
    ],
    "wof:name":"Krishnaperi",
    "wof:placetype":"neighbourhood",
    "wof:population":40
},
  "geometry": {"coordinates":[77.416371,8.87205],"type":"Point"}
}