{
  "type": "Feature",
  "properties": {
    "iso:country":"IN",
    "ks:ks_name":"Thindurpatti",
    "ks:ks_pop":246,
    "ks:ks_type":"HABITATION",
    "ks:ks_uagg_main":0,
    "name:eng_x_preferred":[
        "Thindurpatti"
    ],
    "wof:name":"Thindurpatti",
    "wof:placetype":"neighbourhood",
    "wof:population":246
},
  "geometry": {"coordinates":[78.342105,11.291425],"type":"Point"}
}