{
  "type": "Feature",
  "properties": {
    "iso:country":"IN",
    "ks:ks_name":"Mugwali",
    "ks:ks_pop":300,
    "ks:ks_type":"HABITATION",
    "name:eng_x_preferred":[
        "Mugwali"
    ],
    "wof:name":"Mugwali",
    "wof:placetype":"locality",
    "wof:population":300
},
  "geometry": {"coordinates":[73.310902,18.207009],"type":"Point"}
}