{
  "type": "Feature",
  "properties": {
    "gn:admin1_code":"35",
    "gn:admin2_code":"452.0",
    "gn:asciiname":"Shrinagar",
    "gn:country_code":"IN",
    "gn:dem":399,
    "gn:feature_class":"P",
    "gn:feature_code":"PPL",
    "gn:name":"Shr\u012bnagar",
    "gn:population":0,
    "gn:timezone":"Asia/Kolkata",
    "iso:country":"IN",
    "name:und_x_variant":[
        "Sr\u012bnagar",
        "Shr\u012bnagar"
    ],
    "wof:name":"Shrinagar",
    "wof:placetype":"locality"
},
  "geometry": {"coordinates":[79.5198,22.95216],"type":"Point"}
}