{
  "type": "Feature",
  "properties": {
    "iso:country":"IN",
    "ks:ks_name":"Kallikattur",
    "ks:ks_pop":110,
    "ks:ks_type":"HABITATION",
    "name:eng_x_preferred":[
        "Kallikattur"
    ],
    "wof:name":"Kallikattur",
    "wof:placetype":"locality",
    "wof:population":110
},
  "geometry": {"coordinates":[77.822034,10.990345],"type":"Point"}
}