{
  "type": "Feature",
  "properties": {
    "gn:admin1_code":"12.0",
    "gn:admin2_code":"2.0",
    "gn:asciiname":"Naupur",
    "gn:country_code":"IN",
    "gn:dem":1637,
    "gn:feature_class":"P",
    "gn:feature_code":"PPL",
    "gn:name":"Naupur",
    "gn:population":0,
    "gn:timezone":"Asia/Kolkata",
    "iso:country":"IN",
    "wof:name":"Naupur",
    "wof:placetype":"locality"
},
  "geometry": {"coordinates":[74.87510999999998,33.91273],"type":"Point"}
}