{
  "type": "Feature",
  "properties": {
    "iso:country":"IN",
    "ks:ks_name":"Kollottu-1",
    "ks:ks_pop":1252,
    "ks:ks_type":"HABITATION",
    "name:eng_x_preferred":[
        "Kollottu-1"
    ],
    "wof:name":"Kollottu-1",
    "wof:placetype":"locality",
    "wof:population":1252
},
  "geometry": {"coordinates":[74.89012099999999,13.008145],"type":"Point"}
}