{
  "type": "Feature",
  "properties": {
    "gn:admin1_code":"35",
    "gn:admin2_code":"462.0",
    "gn:asciiname":"Bhatha",
    "gn:country_code":"IN",
    "gn:dem":337,
    "gn:feature_class":"P",
    "gn:feature_code":"PPL",
    "gn:name":"Bh\u0101tha",
    "gn:population":0,
    "gn:timezone":"Asia/Kolkata",
    "iso:country":"IN",
    "ks:ks_alt_nam":"Bh\u0101tha",
    "ks:ks_name":"Bhatha",
    "ks:ks_pop":2446,
    "ks:ks_type":"VILLAGE",
    "name:eng_x_preferred":[
        "Bhatha"
    ],
    "name:eng_x_variant":[
        "Bh\u0101tha"
    ],
    "wof:name":"Bhatha",
    "wof:placetype":"locality",
    "wof:population":2446
},
  "geometry": {"coordinates":[82.003726,24.331852],"type":"Point"}
}