{
  "type": "Feature",
  "properties": {
    "iso:country":"IN",
    "ks:ks_name":"Karangode",
    "ks:ks_pop":486,
    "ks:ks_type":"HABITATION",
    "name:eng_x_preferred":[
        "Karangode"
    ],
    "wof:name":"Karangode",
    "wof:placetype":"locality",
    "wof:population":486
},
  "geometry": {"coordinates":[75.87193600000001,11.820829],"type":"Point"}
}