{
  "type": "Feature",
  "properties": {
    "iso:country":"IN",
    "ks:ks_name":"Chak Jati",
    "ks:ks_pop":879,
    "ks:ks_type":"VILLAGE",
    "name:eng_x_preferred":[
        "Chak Jati"
    ],
    "wof:name":"Chak Jati",
    "wof:placetype":"locality",
    "wof:population":879
},
  "geometry": {"coordinates":[87.421083,22.224065],"type":"Point"}
}