{
  "type": "Feature",
  "properties": {
    "iso:country":"IN",
    "ks:ks_name":"Bilasuni",
    "ks:ks_pop":2524,
    "ks:ks_type":"VILLAGE",
    "ks:ks_uagg_main":0,
    "name:eng_x_preferred":[
        "Bilasuni"
    ],
    "wof:name":"Bilasuni",
    "wof:placetype":"neighbourhood",
    "wof:population":2524
},
  "geometry": {"coordinates":[86.088725,20.178244],"type":"Point"}
}