{
  "type": "Feature",
  "properties": {
    "iso:country":"IN",
    "ks:ks_name":"Gillibaddu",
    "ks:ks_pop":155,
    "ks:ks_type":"HABITATION",
    "name:eng_x_preferred":[
        "Gillibaddu"
    ],
    "wof:name":"Gillibaddu",
    "wof:placetype":"locality",
    "wof:population":155
},
  "geometry": {"coordinates":[82.78427499999999,18.086473],"type":"Point"}
}