{
  "type": "Feature",
  "properties": {
    "gn:admin1_code":"34.0",
    "gn:admin2_code":"211.0",
    "gn:asciiname":"Lakhanjhari",
    "gn:country_code":"IN",
    "gn:dem":42,
    "gn:feature_class":"P",
    "gn:feature_code":"PPL",
    "gn:name":"Lakhanjhari",
    "gn:population":0,
    "gn:timezone":"Asia/Kolkata",
    "iso:country":"IN",
    "ks:ks_alt_nam":"Lakhanjhari",
    "ks:ks_name":"Lakhanjhar",
    "ks:ks_type":"VILLAGE",
    "ks:ks_uagg_main":0,
    "name:eng_x_preferred":[
        "Lakhanjhar"
    ],
    "name:eng_x_variant":[
        "Lakhanjhari"
    ],
    "wof:name":"Lakhanjhar",
    "wof:placetype":"neighbourhood"
},
  "geometry": {"coordinates":[87.55247300000001,25.792435],"type":"Point"}
}