{
  "type": "Feature",
  "properties": {
    "gn:admin1_code":"24",
    "gn:admin2_code":"105.0",
    "gn:asciiname":"Ulanda",
    "gn:country_code":"IN",
    "gn:dem":219,
    "gn:feature_class":"P",
    "gn:feature_code":"PPL",
    "gn:name":"Ulanda",
    "gn:population":0,
    "gn:timezone":"Asia/Kolkata",
    "iso:country":"IN",
    "name:swa_x_preferred":[
        "Ulanda"
    ],
    "wof:name":"Ulanda",
    "wof:placetype":"neighbourhood"
},
  "geometry": {"coordinates":[77.17241,27.57878],"type":"Point"}
}