{
  "type": "Feature",
  "properties": {
    "gn:admin1_code":"36",
    "gn:admin2_code":"191.0",
    "gn:asciiname":"Kakrahi Dular",
    "gn:country_code":"IN",
    "gn:dem":82,
    "gn:feature_class":"P",
    "gn:feature_code":"PPL",
    "gn:name":"Kakrahi Dul\u0101r",
    "gn:population":0,
    "gn:timezone":"Asia/Kolkata",
    "iso:country":"IN",
    "ks:ks_name":"Kakrahi Dular",
    "ks:ks_pop":438,
    "ks:ks_type":"VILLAGE",
    "ks:ks_uagg_main":0,
    "name:eng_x_preferred":[
        "Kakrahi Dular"
    ],
    "wof:name":"Kakrahi Dular",
    "wof:placetype":"neighbourhood",
    "wof:population":438
},
  "geometry": {"coordinates":[83.212362,26.224169],"type":"Point"}
}