{
  "type": "Feature",
  "properties": {
    "gn:admin1_code":"35.0",
    "gn:admin2_code":"465.0",
    "gn:asciiname":"Keljhar",
    "gn:country_code":"IN",
    "gn:dem":402,
    "gn:feature_class":"P",
    "gn:feature_code":"PPL",
    "gn:name":"Keljhar",
    "gn:population":0,
    "gn:timezone":"Asia/Kolkata",
    "iso:country":"IN",
    "ks:ks_name":"Keljhara",
    "ks:ks_pop":543,
    "ks:ks_type":"VILLAGE",
    "name:eng_x_preferred":[
        "Keljhara"
    ],
    "name:eng_x_variant":[
        "Keljhar"
    ],
    "wof:name":"Keljhara",
    "wof:placetype":"locality",
    "wof:population":543
},
  "geometry": {"coordinates":[74.689199,22.528229],"type":"Point"}
}