{
  "type": "Feature",
  "properties": {
    "gn:admin1_code":"35",
    "gn:admin2_code":"462.0",
    "gn:asciiname":"Malkham",
    "gn:country_code":"IN",
    "gn:dem":345,
    "gn:feature_class":"P",
    "gn:feature_code":"PPL",
    "gn:name":"Malkham",
    "gn:population":0,
    "gn:timezone":"Asia/Kolkata",
    "iso:country":"IN",
    "ks:ks_name":"Malkham",
    "ks:ks_pop":943,
    "ks:ks_type":"VILLAGE",
    "name:eng_x_preferred":[
        "Malkham"
    ],
    "wof:name":"Malkham",
    "wof:placetype":"locality",
    "wof:population":943
},
  "geometry": {"coordinates":[82.05944100000001,24.402285],"type":"Point"}
}