{
  "type": "Feature",
  "properties": {
    "gn:admin1_code":"12.0",
    "gn:admin2_code":"011",
    "gn:asciiname":"Chitardalau",
    "gn:country_code":"IN",
    "gn:dem":3091,
    "gn:feature_class":"P",
    "gn:feature_code":"PPL",
    "gn:name":"Chitardalau",
    "gn:population":0,
    "gn:timezone":"Asia/Kolkata",
    "iso:country":"IN",
    "wof:name":"Chitardalau",
    "wof:placetype":"locality"
},
  "geometry": {"coordinates":[74.9931,34.40782],"type":"Point"}
}