{
  "type": "Feature",
  "properties": {
    "gn:admin1_code":"29.0",
    "gn:admin2_code":"241",
    "gn:asciiname":"Chhuba",
    "gn:country_code":"IN",
    "gn:dem":2985,
    "gn:feature_class":"P",
    "gn:feature_code":"PPL",
    "gn:name":"Chhuba",
    "gn:population":0,
    "gn:timezone":"Asia/Kolkata",
    "iso:country":"IN",
    "name:und_x_variant":[
        "Chubha"
    ],
    "wof:name":"Chhuba",
    "wof:placetype":"locality"
},
  "geometry": {"coordinates":[88.74975999999999,27.72283],"type":"Point"}
}