{
  "type": "Feature",
  "properties": {
    "iso:country":"IN",
    "ks:ks_name":"Adlispura",
    "ks:ks_pop":0,
    "ks:ks_type":"VILLAGE",
    "name:eng_x_preferred":[
        "Adlispura"
    ],
    "wof:name":"Adlispura",
    "wof:placetype":"locality",
    "wof:population":0
},
  "geometry": {"coordinates":[78.705637,26.040286],"type":"Point"}
}