{
  "type": "Feature",
  "properties": {
    "iso:country":"IN",
    "name:pan_x_preferred":[
        "\u0a1c\u0a48\u0a2a\u0a41\u0a30\u0a3e"
    ],
    "name:urd_x_preferred":[
        "\u062c\u06cc\u067e\u0631\u0627"
    ],
    "qs:name":"Jaipura",
    "qs:name_adm0":"India",
    "qs:name_adm1":"Rajasthan",
    "qs:photos":4,
    "qs:photos_1k":1,
    "qs:photos_9k":1,
    "qs:photos_9r":1,
    "qs:photos_all":4,
    "qs:photos_sr":1,
    "qs:placetype":"Suburb",
    "qs:pop_sr":"0",
    "wd:wordcount":64,
    "wof:name":"Jaipura",
    "wof:placetype":"neighbourhood"
},
  "geometry": {"coordinates":[75.795536,26.902629],"type":"Point"}
}