{
  "type": "Feature",
  "properties": {
    "iso:country":"IN",
    "ks:ks_name":"Shahpur",
    "ks:ks_pop":767,
    "ks:ks_type":"VILLAGE",
    "ks:ks_uagg_main":0,
    "name:eng_x_preferred":[
        "Shahpur"
    ],
    "wof:name":"Shahpur",
    "wof:placetype":"neighbourhood",
    "wof:population":767
},
  "geometry": {"coordinates":[85.704476,26.295059],"type":"Point"}
}