{
  "type": "Feature",
  "properties": {
    "gn:admin1_code":"34.0",
    "gn:admin2_code":"220.0",
    "gn:asciiname":"Shambhupur Kuari",
    "gn:country_code":"IN",
    "gn:dem":55,
    "gn:feature_class":"P",
    "gn:feature_code":"PPL",
    "gn:name":"Shambhupur Ku\u0101ri",
    "gn:population":0,
    "gn:timezone":"Asia/Kolkata",
    "iso:country":"IN",
    "ks:ks_name":"Shambhupur Kauri",
    "ks:ks_pop":3779,
    "ks:ks_type":"VILLAGE",
    "name:eng_x_preferred":[
        "Shambhupur Kauri"
    ],
    "name:eng_x_variant":[
        "Shambhupur Kuari"
    ],
    "wof:name":"Shambhupur Kauri",
    "wof:placetype":"locality",
    "wof:population":3779
},
  "geometry": {"coordinates":[85.316714,25.811236],"type":"Point"}
}