{
  "type": "Feature",
  "properties": {
    "gn:admin1_code":"34.0",
    "gn:admin2_code":"229.0",
    "gn:asciiname":"Garab Chak",
    "gn:country_code":"IN",
    "gn:dem":63,
    "gn:feature_class":"P",
    "gn:feature_code":"PPL",
    "gn:name":"Garab Chak",
    "gn:population":0,
    "gn:timezone":"Asia/Kolkata",
    "iso:country":"IN",
    "ks:ks_name":"Gaurav Chak",
    "ks:ks_pop":313,
    "ks:ks_type":"HABITATION",
    "name:eng_x_preferred":[
        "Gaurav Chak"
    ],
    "name:eng_x_variant":[
        "Garab Chak"
    ],
    "wof:name":"Gaurav Chak",
    "wof:placetype":"locality",
    "wof:population":313
},
  "geometry": {"coordinates":[85.221305,25.202148],"type":"Point"}
}