{
  "type": "Feature",
  "properties": {
    "gn:admin1_code":"40",
    "gn:admin2_code":"539.0",
    "gn:asciiname":"Venkapalli",
    "gn:country_code":"IN",
    "gn:dem":192,
    "gn:feature_class":"P",
    "gn:feature_code":"PPL",
    "gn:name":"Venkapalli",
    "gn:population":0,
    "gn:timezone":"Asia/Kolkata",
    "iso:country":"IN",
    "wof:name":"Venkapalli",
    "wof:placetype":"locality"
},
  "geometry": {"coordinates":[79.64138,17.34542],"type":"Point"}
}