{
  "type": "Feature",
  "properties": {
    "iso:country":"IN",
    "ks:ks_name":"New Nagrai",
    "ks:ks_pop":636,
    "ks:ks_type":"HABITATION",
    "name:eng_x_preferred":[
        "New Nagrai"
    ],
    "wof:name":"New Nagrai",
    "wof:placetype":"locality",
    "wof:population":636
},
  "geometry": {"coordinates":[91.620667,23.60929],"type":"Point"}
}