{
  "type": "Feature",
  "properties": {
    "iso:country":"IN",
    "ks:ks_name":"Vindhane",
    "ks:ks_pop":2272,
    "ks:ks_type":"VILLAGE",
    "ks:ks_uagg_main":0,
    "name:eng_x_preferred":[
        "Vindhane"
    ],
    "wof:name":"Vindhane",
    "wof:placetype":"neighbourhood",
    "wof:population":2272
},
  "geometry": {"coordinates":[73.045193,18.898208],"type":"Point"}
}