{
  "type": "Feature",
  "properties": {
    "iso:country":"IN",
    "ks:ks_alt_nam":"Tholappan pannai",
    "ks:ks_name":"Tholappan Pannai",
    "ks:ks_pop":1142,
    "ks:ks_type":"HABITATION",
    "name:eng_x_preferred":[
        "Tholappan Pannai"
    ],
    "wof:name":"Tholappan Pannai",
    "wof:placetype":"locality",
    "wof:population":1142
},
  "geometry": {"coordinates":[77.90796899999999,8.652359],"type":"Point"}
}