{
  "type": "Feature",
  "properties": {
    "iso:country":"IN",
    "ks:ks_alt_nam":"Mizo Teron gaon",
    "ks:ks_name":"Mizo Teron Gaon",
    "ks:ks_pop":282,
    "ks:ks_type":"HABITATION",
    "ks:ks_uagg_main":0,
    "name:eng_x_preferred":[
        "Mizo Teron Gaon"
    ],
    "wof:name":"Mizo Teron Gaon",
    "wof:placetype":"neighbourhood",
    "wof:population":282
},
  "geometry": {"coordinates":[93.145225,26.16437],"type":"Point"}
}