{
  "type": "Feature",
  "properties": {
    "iso:country":"IN",
    "ks:ks_alt_nam":"Banarsi ka pura",
    "ks:ks_name":"Banarsi Ka Pura",
    "ks:ks_pop":100,
    "ks:ks_type":"HABITATION",
    "name:eng_x_preferred":[
        "Banarsi Ka Pura"
    ],
    "wof:name":"Banarsi Ka Pura",
    "wof:placetype":"locality",
    "wof:population":100
},
  "geometry": {"coordinates":[81.78827,25.27866],"type":"Point"}
}