{
  "type": "Feature",
  "properties": {
    "gn:admin1_code":"19.0",
    "gn:admin2_code":"573.0",
    "gn:asciiname":"Yaladhalli",
    "gn:country_code":"IN",
    "gn:dem":665,
    "gn:feature_class":"P",
    "gn:feature_code":"PPL",
    "gn:name":"Yal\u0101dhalli",
    "gn:population":0,
    "gn:timezone":"Asia/Kolkata",
    "iso:country":"IN",
    "wof:name":"Yaladhalli",
    "wof:placetype":"locality"
},
  "geometry": {"coordinates":[77.00561999999999,12.45564],"type":"Point"}
}