{
  "type": "Feature",
  "properties": {
    "iso:country":"IN",
    "ks:ks_name":"Jagadih",
    "ks:ks_pop":648,
    "ks:ks_type":"VILLAGE",
    "ks:ks_uagg_main":0,
    "name:eng_x_preferred":[
        "Jagadih"
    ],
    "wof:name":"Jagadih",
    "wof:placetype":"neighbourhood",
    "wof:population":648
},
  "geometry": {"coordinates":[86.655911,24.161274],"type":"Point"}
}