{
  "type": "Feature",
  "properties": {
    "iso:country":"IN",
    "ks:ks_name":"Lilabaran",
    "ks:ks_pop":131,
    "ks:ks_type":"VILLAGE",
    "name:eng_x_preferred":[
        "Lilabaran"
    ],
    "wof:name":"Lilabaran",
    "wof:placetype":"locality",
    "wof:population":131
},
  "geometry": {"coordinates":[86.958169,24.582889],"type":"Point"}
}