{
  "type": "Feature",
  "properties": {
    "iso:country":"IN",
    "ks:ks_name":"Lundruju",
    "ks:ks_pop":268,
    "ks:ks_type":"VILLAGE",
    "name:eng_x_preferred":[
        "Lundruju"
    ],
    "wof:name":"Lundruju",
    "wof:placetype":"locality",
    "wof:population":268
},
  "geometry": {"coordinates":[84.168446,19.358613],"type":"Point"}
}