{
  "type": "Feature",
  "properties": {
    "iso:country":"IN",
    "ks:ks_alt_nam":"Brahman fa",
    "ks:ks_name":"Brahman Fa",
    "ks:ks_pop":348,
    "ks:ks_type":"HABITATION",
    "name:eng_x_preferred":[
        "Brahman Fa"
    ],
    "wof:name":"Brahman Fa",
    "wof:placetype":"locality",
    "wof:population":348
},
  "geometry": {"coordinates":[72.991309,20.468788],"type":"Point"}
}