{
  "type": "Feature",
  "properties": {
    "iso:country":"IN",
    "ks:ks_name":"Kunjunnipadi",
    "ks:ks_pop":1115,
    "ks:ks_type":"HABITATION",
    "name:eng_x_preferred":[
        "Kunjunnipadi"
    ],
    "wof:name":"Kunjunnipadi",
    "wof:placetype":"locality",
    "wof:population":1115
},
  "geometry": {"coordinates":[76.11960000000001,11.626882],"type":"Point"}
}