{
  "type": "Feature",
  "properties": {
    "gn:admin1_code":"19.0",
    "gn:admin2_code":"583.0",
    "gn:asciiname":"Dod Uganvadi",
    "gn:country_code":"IN",
    "gn:dem":901,
    "gn:feature_class":"P",
    "gn:feature_code":"PPL",
    "gn:name":"Dod Uganv\u0101di",
    "gn:population":0,
    "gn:timezone":"Asia/Kolkata",
    "iso:country":"IN",
    "wof:name":"Dod Uganvadi",
    "wof:placetype":"locality"
},
  "geometry": {"coordinates":[77.6579,13.23908],"type":"Point"}
}