{
  "type": "Feature",
  "properties": {
    "gn:admin1_code":"16",
    "gn:admin2_code":"503.0",
    "gn:asciiname":"Nardu",
    "gn:country_code":"IN",
    "gn:dem":349,
    "gn:feature_class":"P",
    "gn:feature_code":"PPL",
    "gn:name":"N\u0101rdu",
    "gn:population":0,
    "gn:timezone":"Asia/Kolkata",
    "iso:country":"IN",
    "wof:name":"Nardu",
    "wof:placetype":"locality"
},
  "geometry": {"coordinates":[76.76172,21.37694],"type":"Point"}
}