{
  "type": "Feature",
  "properties": {
    "iso:country":"IN",
    "ks:ks_name":"Mahalanga",
    "ks:ks_pop":78,
    "ks:ks_type":"VILLAGE",
    "name:eng_x_preferred":[
        "Mahalanga"
    ],
    "wof:name":"Mahalanga",
    "wof:placetype":"locality",
    "wof:population":78
},
  "geometry": {"coordinates":[84.050551,20.251568],"type":"Point"}
}