{
  "type": "Feature",
  "properties": {
    "iso:country":"IN",
    "ks:ks_alt_nam":"NARSINGHPURA BARANI",
    "ks:ks_name":"Narsinghpura Barani",
    "ks:ks_pop":15,
    "ks:ks_type":"HABITATION",
    "name:eng_x_preferred":[
        "Narsinghpura Barani"
    ],
    "wof:name":"Narsinghpura Barani",
    "wof:placetype":"locality",
    "wof:population":15
},
  "geometry": {"coordinates":[73.874864,29.714969],"type":"Point"}
}