{
  "type": "Feature",
  "properties": {
    "iso:country":"IN",
    "ks:ks_name":"Poovattikal",
    "ks:ks_pop":166,
    "ks:ks_type":"HABITATION",
    "name:eng_x_preferred":[
        "Poovattikal"
    ],
    "wof:name":"Poovattikal",
    "wof:placetype":"locality",
    "wof:population":166
},
  "geometry": {"coordinates":[75.77596200000001,11.720529],"type":"Point"}
}