{
  "type": "Feature",
  "properties": {
    "iso:country":"IN",
    "ks:ks_name":"Semriha",
    "ks:ks_pop":1104,
    "ks:ks_type":"VILLAGE",
    "name:eng_x_preferred":[
        "Semriha"
    ],
    "wof:name":"Semriha",
    "wof:placetype":"locality",
    "wof:population":1104
},
  "geometry": {"coordinates":[81.8242,23.755287],"type":"Point"}
}