{
  "type": "Feature",
  "properties": {
    "iso:country":"IN",
    "ks:ks_name":"Tatkarewadi",
    "ks:ks_pop":5,
    "ks:ks_type":"HABITATION",
    "name:eng_x_preferred":[
        "Tatkarewadi"
    ],
    "wof:name":"Tatkarewadi",
    "wof:placetype":"locality",
    "wof:population":5
},
  "geometry": {"coordinates":[73.410128,18.029218],"type":"Point"}
}