{
  "type": "Feature",
  "properties": {
    "iso:country":"IN",
    "ks:ks_alt_nam":"Nai\u0101dih",
    "ks:ks_name":"Naiadih",
    "ks:ks_pop":124,
    "ks:ks_type":"VILLAGE",
    "name:eng_x_preferred":[
        "Naiadih"
    ],
    "name:eng_x_variant":[
        "Nai\u0101dih"
    ],
    "wof:name":"Naiadih",
    "wof:placetype":"locality",
    "wof:population":124
},
  "geometry": {"coordinates":[86.476545,24.399104],"type":"Point"}
}