{
  "type": "Feature",
  "properties": {
    "iso:country":"IN",
    "ks:ks_name":"Bhuruduchampa",
    "ks:ks_pop":103,
    "ks:ks_type":"VILLAGE",
    "name:eng_x_preferred":[
        "Bhuruduchampa"
    ],
    "wof:name":"Bhuruduchampa",
    "wof:placetype":"locality",
    "wof:population":103
},
  "geometry": {"coordinates":[86.581962,21.767271],"type":"Point"}
}