{
  "type": "Feature",
  "properties": {
    "gn:admin1_code":"12.0",
    "gn:admin2_code":"5.0",
    "gn:asciiname":"Gagar Bhata",
    "gn:country_code":"IN",
    "gn:dem":1736,
    "gn:feature_class":"P",
    "gn:feature_code":"PPL",
    "gn:name":"Gagar Bh\u0101ta",
    "gn:population":0,
    "gn:timezone":"Asia/Kolkata",
    "iso:country":"IN",
    "wof:name":"Gagar Bhata",
    "wof:placetype":"locality"
},
  "geometry": {"coordinates":[74.37321,33.6183],"type":"Point"}
}