{
  "type": "Feature",
  "properties": {
    "iso:country":"IN",
    "ks:ks_name":"Dineshpur",
    "ks:ks_pop":768,
    "ks:ks_type":"HABITATION",
    "ks:ks_uagg_main":0,
    "name:eng_x_preferred":[
        "Dineshpur"
    ],
    "wof:name":"Dineshpur",
    "wof:placetype":"neighbourhood",
    "wof:population":768
},
  "geometry": {"coordinates":[94.025368,26.233601],"type":"Point"}
}