{
  "type": "Feature",
  "properties": {
    "iso:country":"IN",
    "ks:ks_name":"Upper Tola",
    "ks:ks_pop":214,
    "ks:ks_type":"HABITATION",
    "ks:ks_uagg_main":0,
    "name:eng_x_preferred":[
        "Upper Tola"
    ],
    "wof:name":"Upper Tola",
    "wof:placetype":"neighbourhood",
    "wof:population":214
},
  "geometry": {"coordinates":[86.600101,24.805163],"type":"Point"}
}