{
  "type": "Feature",
  "properties": {
    "gn:admin1_code":"36",
    "gn:admin2_code":"193.0",
    "gn:asciiname":"Basawan",
    "gn:country_code":"IN",
    "gn:dem":71,
    "gn:feature_class":"P",
    "gn:feature_code":"PPL",
    "gn:name":"Basawan",
    "gn:population":0,
    "gn:timezone":"Asia/Kolkata",
    "iso:country":"IN",
    "name:deu_x_preferred":[
        "Basawan"
    ],
    "name:eus_x_preferred":[
        "Basawan"
    ],
    "name:fas_x_preferred":[
        "\u0628\u0627\u0633\u0627\u0648\u0627\u0646"
    ],
    "name:fra_x_preferred":[
        "Basawan"
    ],
    "name:ita_x_preferred":[
        "Basawan"
    ],
    "name:kaz_x_preferred":[
        "\u0411\u0430\u0441\u0430\u0432\u0430\u043d"
    ],
    "name:nno_x_preferred":[
        "Basavan"
    ],
    "name:pol_x_preferred":[
        "Basawan"
    ],
    "name:rus_x_preferred":[
        "\u0411\u0430\u0441\u0430\u0432\u0430\u043d"
    ],
    "name:ukr_x_preferred":[
        "\u0411\u0430\u0441\u0430\u0432\u0430\u043d"
    ],
    "wof:name":"Basawan",
    "wof:placetype":"neighbourhood"
},
  "geometry": {"coordinates":[83.82288,25.78511],"type":"Point"}
}