{
  "type": "Feature",
  "properties": {
    "iso:country":"IN",
    "ks:ks_alt_nam":"KATHAL BARI",
    "ks:ks_name":"Kathal Bari",
    "ks:ks_pop":192,
    "ks:ks_type":"HABITATION",
    "ks:ks_uagg_main":0,
    "name:eng_x_preferred":[
        "Kathal Bari"
    ],
    "wof:name":"Kathal Bari",
    "wof:placetype":"neighbourhood",
    "wof:population":192
},
  "geometry": {"coordinates":[91.607339,23.972792],"type":"Point"}
}