{
  "type": "Feature",
  "properties": {
    "iso:country":"IN",
    "ks:ks_alt_nam":"Polo sahi",
    "ks:ks_name":"Polo Sahi",
    "ks:ks_pop":200,
    "ks:ks_type":"HABITATION",
    "name:eng_x_preferred":[
        "Polo Sahi"
    ],
    "wof:name":"Polo Sahi",
    "wof:placetype":"locality",
    "wof:population":200
},
  "geometry": {"coordinates":[86.234765,22.326128],"type":"Point"}
}