{
  "type": "Feature",
  "properties": {
    "iso:country":"IN",
    "ks:ks_name":"Kaldang Agitok",
    "ks:ks_pop":190,
    "ks:ks_type":"HABITATION",
    "name:eng_x_preferred":[
        "Kaldang Agitok"
    ],
    "wof:name":"Kaldang Agitok",
    "wof:placetype":"locality",
    "wof:population":190
},
  "geometry": {"coordinates":[90.58217399999999,25.956746],"type":"Point"}
}