{
  "type": "Feature",
  "properties": {
    "iso:country":"IN",
    "ks:ks_name":"Bherbheri-Bill",
    "ks:ks_pop":3692,
    "ks:ks_type":"VILLAGE",
    "name:eng_x_preferred":[
        "Bherbheri-Bill"
    ],
    "wof:name":"Bherbheri-Bill",
    "wof:placetype":"locality",
    "wof:population":3692
},
  "geometry": {"coordinates":[92.04195199999999,26.609325],"type":"Point"}
}