{
  "type": "Feature",
  "properties": {
    "iso:country":"IN",
    "ks:ks_name":"Bangarujadu",
    "ks:ks_pop":12,
    "ks:ks_type":"HABITATION",
    "name:eng_x_preferred":[
        "Bangarujadu"
    ],
    "wof:name":"Bangarujadu",
    "wof:placetype":"locality",
    "wof:population":12
},
  "geometry": {"coordinates":[74.728346,14.279903],"type":"Point"}
}