{
  "type": "Feature",
  "properties": {
    "iso:country":"IN",
    "ks:ks_name":"Veeram Reddigaripalle",
    "ks:ks_pop":196,
    "ks:ks_type":"HABITATION",
    "ks:ks_uagg_main":0,
    "name:eng_x_preferred":[
        "Veeram Reddigaripalle"
    ],
    "wof:name":"Veeram Reddigaripalle",
    "wof:placetype":"neighbourhood",
    "wof:population":196
},
  "geometry": {"coordinates":[78.729981,13.54702],"type":"Point"}
}