{
  "type": "Feature",
  "properties": {
    "iso:country":"IN",
    "qs:name":"Rajhans Colony",
    "qs:name_adm0":"India",
    "qs:name_adm1":"Rajasthan",
    "qs:photos":121,
    "qs:photos_1k":25,
    "qs:photos_9k":1,
    "qs:photos_9r":3,
    "qs:photos_all":121,
    "qs:photos_sr":3,
    "qs:placetype":"Suburb",
    "qs:pop_sr":"0",
    "wof:name":"Rajhans Colony",
    "wof:placetype":"neighbourhood"
},
  "geometry": {"coordinates":[75.823516,26.928957],"type":"Point"}
}