{
  "type": "Feature",
  "properties": {
    "gn:admin1_code":"36.0",
    "gn:admin2_code":"171.0",
    "gn:asciiname":"Barua",
    "gn:country_code":"IN",
    "gn:dem":100,
    "gn:feature_class":"P",
    "gn:feature_code":"PPL",
    "gn:name":"Barua",
    "gn:population":0,
    "gn:timezone":"Asia/Kolkata",
    "iso:country":"IN",
    "name:deu_x_preferred":[
        "Barua"
    ],
    "name:fra_x_preferred":[
        "Barua"
    ],
    "name:zho_x_preferred":[
        "\u5df4\u9b6f\u963f"
    ],
    "wof:name":"Barua",
    "wof:placetype":"neighbourhood"
},
  "geometry": {"coordinates":[81.24017000000001,25.33147],"type":"Point"}
}