{
  "type": "Feature",
  "properties": {
    "gn:admin1_code":"36",
    "gn:admin2_code":"183.0",
    "gn:asciiname":"Gewar",
    "gn:country_code":"IN",
    "gn:dem":109,
    "gn:feature_class":"P",
    "gn:feature_code":"PPL",
    "gn:name":"Gewar",
    "gn:population":0,
    "gn:timezone":"Asia/Kolkata",
    "iso:country":"IN",
    "wof:name":"Gewar",
    "wof:placetype":"locality"
},
  "geometry": {"coordinates":[81.77405999999998,27.14909],"type":"Point"}
}