{
  "type": "Feature",
  "properties": {
    "iso:country":"IN",
    "ks:ks_name":"Mahuagarh",
    "ks:ks_pop":570,
    "ks:ks_type":"HABITATION",
    "name:eng_x_preferred":[
        "Mahuagarh"
    ],
    "wof:name":"Mahuagarh",
    "wof:placetype":"locality",
    "wof:population":570
},
  "geometry": {"coordinates":[82.28008199999999,24.826041],"type":"Point"}
}