{
  "type": "Feature",
  "properties": {
    "iso:country":"IN",
    "ks:ks_name":"Chariwade",
    "ks:ks_pop":38,
    "ks:ks_type":"HABITATION",
    "name:eng_x_preferred":[
        "Chariwade"
    ],
    "wof:name":"Chariwade",
    "wof:placetype":"locality",
    "wof:population":38
},
  "geometry": {"coordinates":[73.531308,16.193297],"type":"Point"}
}