{
  "type": "Feature",
  "properties": {
    "gn:admin1_code":"39",
    "gn:admin2_code":"61.0",
    "gn:asciiname":"Malai",
    "gn:country_code":"IN",
    "gn:dem":1901,
    "gn:feature_class":"P",
    "gn:feature_code":"PPL",
    "gn:name":"Malai",
    "gn:population":0,
    "gn:timezone":"Asia/Kolkata",
    "iso:country":"IN",
    "name:hin_x_preferred":[
        "\u092e\u0932\u093e\u0908"
    ],
    "name:jpn_x_preferred":[
        "\u30de\u30e9\u30a4"
    ],
    "name:kan_x_preferred":[
        "\u0cae\u0cb2\u0cbe\u0caf\u0cbf"
    ],
    "name:kor_x_preferred":[
        "\ub9d0\ub77c\uc774"
    ],
    "name:mal_x_preferred":[
        "\u0d2e\u0d32\u0d3e\u0d2f\u0d4d"
    ],
    "name:nld_x_preferred":[
        "Malai"
    ],
    "name:spa_x_preferred":[
        "Malai"
    ],
    "wof:name":"Malai",
    "wof:placetype":"locality"
},
  "geometry": {"coordinates":[78.97411,30.00151],"type":"Point"}
}