{
  "type": "Feature",
  "properties": {
    "iso:country":"IN",
    "ks:ks_name":"Ghodsakhare",
    "ks:ks_pop":174,
    "ks:ks_type":"HABITATION",
    "name:eng_x_preferred":[
        "Ghodsakhare"
    ],
    "wof:name":"Ghodsakhare",
    "wof:placetype":"locality",
    "wof:population":174
},
  "geometry": {"coordinates":[73.303273,19.701099],"type":"Point"}
}