{
  "type": "Feature",
  "properties": {
    "iso:country":"IN",
    "ks:ks_name":"Vavdi",
    "ks:ks_pop":0,
    "ks:ks_type":"VILLAGE",
    "name:eng_x_preferred":[
        "Vavdi"
    ],
    "wof:name":"Vavdi",
    "wof:placetype":"locality",
    "wof:population":0
},
  "geometry": {"coordinates":[69.844527,23.172105],"type":"Point"}
}