{
  "type": "Feature",
  "properties": {
    "iso:country":"IN",
    "ks:ks_name":"Birajpur",
    "ks:ks_pop":9,
    "ks:ks_type":"VILLAGE",
    "name:eng_x_preferred":[
        "Birajpur"
    ],
    "wof:name":"Birajpur",
    "wof:placetype":"locality",
    "wof:population":9
},
  "geometry": {"coordinates":[86.54597099999999,24.313223],"type":"Point"}
}