{
  "type": "Feature",
  "properties": {
    "iso:country":"IN",
    "ks:ks_name":"Kantabanji",
    "ks:ks_pop":118,
    "ks:ks_type":"VILLAGE",
    "name:eng_x_preferred":[
        "Kantabanji"
    ],
    "wof:name":"Kantabanji",
    "wof:placetype":"locality",
    "wof:population":118
},
  "geometry": {"coordinates":[83.05387899999999,19.572457],"type":"Point"}
}