{
  "type": "Feature",
  "properties": {
    "iso:country":"IN",
    "ks:ks_name":"Bera Reserved Forest",
    "ks:ks_type":"VILLAGE",
    "name:eng_x_preferred":[
        "Bera Reserved Forest"
    ],
    "wof:name":"Bera Reserved Forest",
    "wof:placetype":"locality"
},
  "geometry": {"coordinates":[85.338908,22.56828],"type":"Point"}
}