{
  "type": "Feature",
  "properties": {
    "gn:admin1_code":"36",
    "gn:admin2_code":"201.0",
    "gn:asciiname":"Gularia Konchi",
    "gn:country_code":"IN",
    "gn:dem":166,
    "gn:feature_class":"P",
    "gn:feature_code":"PPL",
    "gn:name":"Gularia Konchi",
    "gn:population":0,
    "gn:timezone":"Asia/Kolkata",
    "iso:country":"IN",
    "ks:ks_name":"Gulariya Konchi",
    "ks:ks_pop":131,
    "ks:ks_type":"HABITATION",
    "name:eng_x_preferred":[
        "Gulariya Konchi"
    ],
    "name:eng_x_variant":[
        "Gularia Konchi"
    ],
    "wof:name":"Gulariya Konchi",
    "wof:placetype":"locality",
    "wof:population":131
},
  "geometry": {"coordinates":[78.786901,27.364966],"type":"Point"}
}