{
  "type": "Feature",
  "properties": {
    "iso:country":"IN",
    "ks:ks_name":"Thakurbari Tola",
    "ks:ks_pop":756,
    "ks:ks_type":"HABITATION",
    "ks:ks_uagg_main":0,
    "name:eng_x_preferred":[
        "Thakurbari Tola"
    ],
    "wof:name":"Thakurbari Tola",
    "wof:placetype":"neighbourhood",
    "wof:population":756
},
  "geometry": {"coordinates":[86.850994,25.473616],"type":"Point"}
}