{
  "type": "Feature",
  "properties": {
    "gn:admin1_code":"12.0",
    "gn:asciiname":"Khudiri",
    "gn:country_code":"IN",
    "gn:dem":2756,
    "gn:feature_class":"P",
    "gn:feature_code":"PPL",
    "gn:name":"Khudiri",
    "gn:population":0,
    "gn:timezone":"Asia/Kolkata",
    "iso:country":"IN",
    "name:und_x_variant":[
        "Khudi"
    ],
    "wof:name":"Khudiri",
    "wof:placetype":"locality"
},
  "geometry": {"coordinates":[73.97728000000002,34.59922],"type":"Point"}
}