{
  "type": "Feature",
  "properties": {
    "iso:country":"IN",
    "ks:ks_name":"Venthampatty",
    "ks:ks_pop":719,
    "ks:ks_type":"HABITATION",
    "ks:ks_uagg_main":0,
    "name:eng_x_preferred":[
        "Venthampatty"
    ],
    "wof:name":"Venthampatty",
    "wof:placetype":"neighbourhood",
    "wof:population":719
},
  "geometry": {"coordinates":[78.512771,10.250867],"type":"Point"}
}