{
  "type": "Feature",
  "properties": {
    "iso:country":"IN",
    "ks:ks_name":"Aawaspara",
    "ks:ks_pop":151,
    "ks:ks_type":"HABITATION",
    "name:eng_x_preferred":[
        "Aawaspara"
    ],
    "wof:name":"Aawaspara",
    "wof:placetype":"locality",
    "wof:population":151
},
  "geometry": {"coordinates":[81.201699,20.091063],"type":"Point"}
}