{
  "type": "Feature",
  "properties": {
    "iso:country":"IN",
    "ks:ks_name":"Metrathi",
    "ks:ks_pop":1027,
    "ks:ks_type":"VILLAGE",
    "name:eng_x_preferred":[
        "Metrathi"
    ],
    "wof:name":"Metrathi",
    "wof:placetype":"locality",
    "wof:population":1027
},
  "geometry": {"coordinates":[77.357558,10.652694],"type":"Point"}
}