{
  "type": "Feature",
  "properties": {
    "iso:country":"IN",
    "ks:ks_name":"Mundfanewasti",
    "ks:ks_pop":705,
    "ks:ks_type":"HABITATION",
    "name:eng_x_preferred":[
        "Mundfanewasti"
    ],
    "wof:name":"Mundfanewasti",
    "wof:placetype":"locality",
    "wof:population":705
},
  "geometry": {"coordinates":[75.081001,17.872358],"type":"Point"}
}