{
  "type": "Feature",
  "properties": {
    "iso:country":"IN",
    "ks:ks_alt_nam":"MANNEPURAM",
    "ks:ks_name":"Mannepuram",
    "ks:ks_pop":390,
    "ks:ks_type":"HABITATION",
    "ks:ks_uagg_main":0,
    "name:eng_x_preferred":[
        "Mannepuram"
    ],
    "wof:name":"Mannepuram",
    "wof:placetype":"neighbourhood",
    "wof:population":390
},
  "geometry": {"coordinates":[80.750632,16.015042],"type":"Point"}
}