{
  "type": "Feature",
  "properties": {
    "iso:country":"IN",
    "ks:ks_alt_nam":"Dudukabada dakili",
    "ks:ks_name":"Dudukabada Dakili",
    "ks:ks_pop":172,
    "ks:ks_type":"HABITATION",
    "name:eng_x_preferred":[
        "Dudukabada Dakili"
    ],
    "wof:name":"Dudukabada Dakili",
    "wof:placetype":"locality",
    "wof:population":172
},
  "geometry": {"coordinates":[83.10121700000001,19.197143],"type":"Point"}
}