{
  "type": "Feature",
  "properties": {
    "iso:country":"IN",
    "ks:ks_alt_nam":"GAURI TOLA",
    "ks:ks_name":"Gauri Tola",
    "ks:ks_pop":301,
    "ks:ks_type":"HABITATION",
    "ks:ks_uagg_main":0,
    "name:eng_x_preferred":[
        "Gauri Tola"
    ],
    "wof:name":"Gauri Tola",
    "wof:placetype":"neighbourhood",
    "wof:population":301
},
  "geometry": {"coordinates":[87.42674,25.86874],"type":"Point"}
}