{
  "type": "Feature",
  "properties": {
    "iso:country":"IN",
    "ks:ks_name":"Bokhri Kalan",
    "ks:ks_pop":445,
    "ks:ks_type":"VILLAGE",
    "ks:ks_uagg_main":0,
    "name:eng_x_preferred":[
        "Bokhri Kalan"
    ],
    "wof:name":"Bokhri Kalan",
    "wof:placetype":"neighbourhood",
    "wof:population":445
},
  "geometry": {"coordinates":[75.97405999999999,30.923835],"type":"Point"}
}