{
  "type": "Feature",
  "properties": {
    "gn:admin1_code":"19",
    "gn:admin2_code":"559.0",
    "gn:asciiname":"Bayyapur",
    "gn:country_code":"IN",
    "gn:dem":516,
    "gn:feature_class":"P",
    "gn:feature_code":"PPL",
    "gn:name":"Bayy\u0101pur",
    "gn:population":0,
    "gn:timezone":"Asia/Kolkata",
    "iso:country":"IN",
    "wof:name":"Bayyapur",
    "wof:placetype":"locality"
},
  "geometry": {"coordinates":[76.34721,16.0864],"type":"Point"}
}