{
  "type": "Feature",
  "properties": {
    "iso:country":"IN",
    "ks:ks_name":"Ratanpur",
    "ks:ks_pop":836,
    "ks:ks_type":"VILLAGE",
    "name:eng_x_preferred":[
        "Ratanpur"
    ],
    "wof:name":"Ratanpur",
    "wof:placetype":"locality",
    "wof:population":836
},
  "geometry": {"coordinates":[95.688571,27.900504],"type":"Point"}
}