{
  "type": "Feature",
  "properties": {
    "gn:admin1_code":"34.0",
    "gn:admin2_code":"221.0",
    "gn:asciiname":"Dhobgawan",
    "gn:country_code":"IN",
    "gn:dem":52,
    "gn:feature_class":"P",
    "gn:feature_code":"PPL",
    "gn:name":"Dhobg\u0101w\u0101n",
    "gn:population":0,
    "gn:timezone":"Asia/Kolkata",
    "iso:country":"IN",
    "name:und_x_variant":[
        "Dhobg\u0101w\u0101n",
        "Dhobg\u0101wan"
    ],
    "wof:name":"Dhobgawan",
    "wof:placetype":"locality"
},
  "geometry": {"coordinates":[85.80783000000002,25.97177000000001],"type":"Point"}
}