{
  "type": "Feature",
  "properties": {
    "iso:country":"IN",
    "ks:ks_alt_nam":"KURAN MALA",
    "ks:ks_name":"Kuran Mala",
    "ks:ks_pop":232,
    "ks:ks_type":"HABITATION",
    "name:eng_x_preferred":[
        "Kuran Mala"
    ],
    "wof:name":"Kuran Mala",
    "wof:placetype":"locality",
    "wof:population":232
},
  "geometry": {"coordinates":[74.48917,17.11919],"type":"Point"}
}