{
  "type": "Feature",
  "properties": {
    "iso:country":"IN",
    "ks:ks_name":"Baigna",
    "ks:ks_pop":204,
    "ks:ks_type":"VILLAGE",
    "name:eng_x_preferred":[
        "Baigna"
    ],
    "wof:name":"Baigna",
    "wof:placetype":"locality",
    "wof:population":204
},
  "geometry": {"coordinates":[85.878242,24.757737],"type":"Point"}
}