{
  "type": "Feature",
  "properties": {
    "iso:country":"IN",
    "ks:ks_name":"Samerana Muvada Gamtal",
    "ks:ks_pop":130,
    "ks:ks_type":"HABITATION",
    "name:eng_x_preferred":[
        "Samerana Muvada Gamtal"
    ],
    "wof:name":"Samerana Muvada Gamtal",
    "wof:placetype":"locality",
    "wof:population":130
},
  "geometry": {"coordinates":[73.574389,23.133083],"type":"Point"}
}