{
  "type": "Feature",
  "properties": {
    "iso:country":"IN",
    "ks:ks_name":"Dhuria Neelkanthpur",
    "ks:ks_pop":177,
    "ks:ks_type":"HABITATION",
    "name:eng_x_preferred":[
        "Dhuria Neelkanthpur"
    ],
    "wof:name":"Dhuria Neelkanthpur",
    "wof:placetype":"locality",
    "wof:population":177
},
  "geometry": {"coordinates":[83.093429,23.564849],"type":"Point"}
}