{
  "type": "Feature",
  "properties": {
    "iso:country":"IN",
    "ks:ks_name":"Mahanth Dina Ram Das",
    "ks:ks_pop":84,
    "ks:ks_type":"VILLAGE",
    "name:eng_x_preferred":[
        "Mahanth Dina Ram Das"
    ],
    "wof:name":"Mahanth Dina Ram Das",
    "wof:placetype":"locality",
    "wof:population":84
},
  "geometry": {"coordinates":[87.141876,25.659566],"type":"Point"}
}