{
  "type": "Feature",
  "properties": {
    "iso:country":"IN",
    "ks:ks_name":"Duglai",
    "ks:ks_pop":124,
    "ks:ks_type":"HABITATION",
    "name:eng_x_preferred":[
        "Duglai"
    ],
    "wof:name":"Duglai",
    "wof:placetype":"locality",
    "wof:population":124
},
  "geometry": {"coordinates":[80.475553,21.863399],"type":"Point"}
}