{
  "type": "Feature",
  "properties": {
    "iso:country":"IN",
    "ks:ks_name":"Budhamba",
    "ks:ks_pop":80,
    "ks:ks_type":"HABITATION",
    "name:eng_x_preferred":[
        "Budhamba"
    ],
    "wof:name":"Budhamba",
    "wof:placetype":"locality",
    "wof:population":80
},
  "geometry": {"coordinates":[85.446186,21.287385],"type":"Point"}
}