{
  "type": "Feature",
  "properties": {
    "iso:country":"IN",
    "ks:ks_name":"Akhari Poorvi",
    "ks:ks_pop":90,
    "ks:ks_type":"HABITATION",
    "name:eng_x_preferred":[
        "Akhari Poorvi"
    ],
    "wof:name":"Akhari Poorvi",
    "wof:placetype":"locality",
    "wof:population":90
},
  "geometry": {"coordinates":[81.273838,27.341444],"type":"Point"}
}