{
  "type": "Feature",
  "properties": {
    "gn:admin1_code":"09",
    "gn:admin2_code":"468.0",
    "gn:asciiname":"Luna",
    "gn:country_code":"IN",
    "gn:dem":7,
    "gn:feature_class":"P",
    "gn:feature_code":"PPL",
    "gn:name":"Luna",
    "gn:population":0,
    "gn:timezone":"Asia/Kolkata",
    "iso:country":"IN",
    "name:ara_x_preferred":[
        "\u0644\u0648\u0646\u0627"
    ],
    "name:arg_x_preferred":[
        "Luna"
    ],
    "name:bre_x_preferred":[
        "Luna"
    ],
    "name:bul_x_preferred":[
        "\u041b\u0443\u043d\u0430"
    ],
    "name:cat_x_preferred":[
        "Luna"
    ],
    "name:ceb_x_preferred":[
        "Luna"
    ],
    "name:ces_x_preferred":[
        "Luna"
    ],
    "name:deu_x_preferred":[
        "Luna"
    ],
    "name:epo_x_preferred":[
        "Luna"
    ],
    "name:est_x_preferred":[
        "Luna"
    ],
    "name:eus_x_preferred":[
        "Luna"
    ],
    "name:fas_x_preferred":[
        "\u0644\u0648\u0646\u0627"
    ],
    "name:fin_x_preferred":[
        "Luna"
    ],
    "name:fra_x_preferred":[
        "Luna"
    ],
    "name:glg_x_preferred":[
        "Luna"
    ],
    "name:heb_x_preferred":[
        "\u05dc\u05d5\u05e0\u05d4"
    ],
    "name:hun_x_preferred":[
        "Luna"
    ],
    "name:hye_x_preferred":[
        "\u053c\u0578\u0582\u0576\u0561"
    ],
    "name:ilo_x_preferred":[
        "Luna"
    ],
    "name:ita_x_preferred":[
        "Luna"
    ],
    "name:jpn_x_preferred":[
        "\u30eb\u30ca"
    ],
    "name:lat_x_preferred":[
        "Luna"
    ],
    "name:msa_x_preferred":[
        "Luna"
    ],
    "name:nld_x_preferred":[
        "Luna"
    ],
    "name:pol_x_preferred":[
        "Luna"
    ],
    "name:por_x_preferred":[
        "Luna"
    ],
    "name:ron_x_preferred":[
        "Lun\u0103"
    ],
    "name:rus_x_preferred":[
        "\u041b\u0443\u043d\u0430"
    ],
    "name:slk_x_preferred":[
        "Luna"
    ],
    "name:slv_x_preferred":[
        "Luna"
    ],
    "name:spa_x_preferred":[
        "Luna"
    ],
    "name:srp_x_preferred":[
        "\u041b\u0443\u043d\u0430"
    ],
    "name:swe_x_preferred":[
        "Luna"
    ],
    "name:tgl_x_preferred":[
        "Luna"
    ],
    "name:tur_x_preferred":[
        "Luna"
    ],
    "name:ukr_x_preferred":[
        "\u041b\u0443\u043d\u0430"
    ],
    "name:und_x_variant":[
        "Lama"
    ],
    "name:uzb_x_preferred":[
        "Luna"
    ],
    "name:vol_x_preferred":[
        "Luna"
    ],
    "name:war_x_preferred":[
        "Luna"
    ],
    "name:zho_x_preferred":[
        "Luna"
    ],
    "wof:name":"Luna",
    "wof:placetype":"locality"
},
  "geometry": {"coordinates":[69.25133000000001,23.71316],"type":"Point"}
}