{
  "type": "Feature",
  "properties": {
    "iso:country":"IN",
    "ks:ks_name":"Saradiha",
    "ks:ks_pop":160,
    "ks:ks_type":"VILLAGE",
    "name:eng_x_preferred":[
        "Saradiha"
    ],
    "wof:name":"Saradiha",
    "wof:placetype":"locality",
    "wof:population":160
},
  "geometry": {"coordinates":[86.966143,21.728071],"type":"Point"}
}