{
  "type": "Feature",
  "properties": {
    "iso:country":"IN",
    "ks:ks_alt_nam":"CHARMKAR PANAND",
    "ks:ks_name":"Charmkar Panand",
    "ks:ks_pop":90,
    "ks:ks_type":"HABITATION",
    "name:eng_x_preferred":[
        "Charmkar Panand"
    ],
    "wof:name":"Charmkar Panand",
    "wof:placetype":"locality",
    "wof:population":90
},
  "geometry": {"coordinates":[74.109667,16.918724],"type":"Point"}
}