{
  "type": "Feature",
  "properties": {
    "iso:country":"IN",
    "ks:ks_name":"Durgi",
    "ks:ks_pop":63,
    "ks:ks_type":"HABITATION",
    "name:eng_x_preferred":[
        "Durgi"
    ],
    "wof:name":"Durgi",
    "wof:placetype":"locality",
    "wof:population":63
},
  "geometry": {"coordinates":[83.282112,19.065566],"type":"Point"}
}