{
  "type": "Feature",
  "properties": {
    "iso:country":"IN",
    "ks:ks_alt_nam":"Kaith\u0101",
    "ks:ks_name":"Kaitha",
    "ks:ks_pop":2984,
    "ks:ks_type":"VILLAGE",
    "ks:ks_uagg_main":0,
    "name:eng_x_preferred":[
        "Kaitha"
    ],
    "name:eng_x_variant":[
        "Kaith\u0101"
    ],
    "wof:name":"Kaitha",
    "wof:placetype":"locality",
    "wof:population":2984
},
  "geometry": {"coordinates":[85.544158,23.623779],"type":"Point"}
}