{
  "type": "Feature",
  "properties": {
    "iso:country":"IN",
    "ks:ks_name":"Kashipur",
    "ks:ks_pop":0,
    "ks:ks_type":"VILLAGE",
    "name:eng_x_preferred":[
        "Kashipur"
    ],
    "wof:name":"Kashipur",
    "wof:placetype":"locality",
    "wof:population":0
},
  "geometry": {"coordinates":[83.81149499999999,25.660613],"type":"Point"}
}