{
  "type": "Feature",
  "properties": {
    "gn:admin1_code":"21",
    "gn:admin2_code":"390.0",
    "gn:asciiname":"Asabali",
    "gn:country_code":"IN",
    "gn:dem":735,
    "gn:feature_class":"P",
    "gn:feature_code":"PPL",
    "gn:name":"Asabali",
    "gn:population":0,
    "gn:timezone":"Asia/Kolkata",
    "iso:country":"IN",
    "ks:ks_name":"Usabali",
    "ks:ks_pop":129,
    "ks:ks_type":"VILLAGE",
    "name:eng_x_preferred":[
        "Usabali"
    ],
    "name:eng_x_variant":[
        "Asabali"
    ],
    "wof:name":"Usabali",
    "wof:placetype":"locality",
    "wof:population":129
},
  "geometry": {"coordinates":[83.660933,19.943178],"type":"Point"}
}