{
  "type": "Feature",
  "properties": {
    "gn:admin1_code":"11.0",
    "gn:admin2_code":"27.0",
    "gn:asciiname":"Chakrar",
    "gn:country_code":"IN",
    "gn:dem":2362,
    "gn:feature_class":"P",
    "gn:feature_code":"PPL",
    "gn:name":"Chakr\u0101r",
    "gn:population":0,
    "gn:timezone":"Asia/Kolkata",
    "iso:country":"IN",
    "wof:name":"Chakrar",
    "wof:placetype":"locality"
},
  "geometry": {"coordinates":[77.09354999999999,31.44633],"type":"Point"}
}