{
  "type": "Feature",
  "properties": {
    "iso:country":"IN",
    "ks:ks_name":"Bindirangroi",
    "ks:ks_pop":110,
    "ks:ks_type":"VILLAGE",
    "name:eng_x_preferred":[
        "Bindirangroi"
    ],
    "wof:name":"Bindirangroi",
    "wof:placetype":"locality",
    "wof:population":110
},
  "geometry": {"coordinates":[85.73767599999999,22.641464],"type":"Point"}
}