{
  "type": "Feature",
  "properties": {
    "gn:admin1_code":"23",
    "gn:admin2_code":"38.0",
    "gn:asciiname":"Labar",
    "gn:country_code":"IN",
    "gn:dem":516,
    "gn:feature_class":"P",
    "gn:feature_code":"PPL",
    "gn:name":"Labar",
    "gn:population":0,
    "gn:timezone":"Asia/Kolkata",
    "iso:country":"IN",
    "ks:ks_name":"Labar",
    "ks:ks_pop":563,
    "ks:ks_type":"VILLAGE",
    "name:eng_x_preferred":[
        "Labar"
    ],
    "wof:name":"Labar",
    "wof:placetype":"locality",
    "wof:population":563
},
  "geometry": {"coordinates":[75.863298,31.826326],"type":"Point"}
}