{
  "type": "Feature",
  "properties": {
    "iso:country":"IN",
    "ks:ks_name":"Dharapura",
    "ks:ks_pop":980,
    "ks:ks_type":"HABITATION",
    "name:eng_x_preferred":[
        "Dharapura"
    ],
    "wof:name":"Dharapura",
    "wof:placetype":"locality",
    "wof:population":980
},
  "geometry": {"coordinates":[78.125657,26.812456],"type":"Point"}
}