{
  "type": "Feature",
  "properties": {
    "gn:admin1_code":"23.0",
    "gn:admin2_code":"50.0",
    "gn:asciiname":"Chambal",
    "gn:country_code":"IN",
    "gn:dem":222,
    "gn:feature_class":"P",
    "gn:feature_code":"PPL",
    "gn:name":"Chambal",
    "gn:population":0,
    "gn:timezone":"Asia/Kolkata",
    "iso:country":"IN",
    "name:ceb_x_preferred":[
        "Chambal"
    ],
    "name:nld_x_preferred":[
        "Chambal"
    ],
    "name:swe_x_preferred":[
        "Chambal"
    ],
    "wof:name":"Chambal",
    "wof:placetype":"locality"
},
  "geometry": {"coordinates":[74.93499,31.3747],"type":"Point"}
}