{
  "type": "Feature",
  "properties": {
    "iso:country":"IN",
    "ks:ks_alt_nam":"PAHARPUR",
    "ks:ks_name":"Paharpur",
    "ks:ks_pop":82,
    "ks:ks_type":"HABITATION",
    "name:eng_x_preferred":[
        "Paharpur"
    ],
    "wof:name":"Paharpur",
    "wof:placetype":"locality",
    "wof:population":82
},
  "geometry": {"coordinates":[85.542812,24.324126],"type":"Point"}
}