{
  "type": "Feature",
  "properties": {
    "iso:country":"IN",
    "ks:ks_name":"Gullipalli",
    "ks:ks_pop":48,
    "ks:ks_type":"HABITATION",
    "name:eng_x_preferred":[
        "Gullipalli"
    ],
    "wof:name":"Gullipalli",
    "wof:placetype":"locality",
    "wof:population":48
},
  "geometry": {"coordinates":[82.83153,18.045432],"type":"Point"}
}