{
  "type": "Feature",
  "properties": {
    "iso:country":"IN",
    "ks:ks_name":"Thatchampadi",
    "ks:ks_pop":1583,
    "ks:ks_type":"HABITATION",
    "name:eng_x_preferred":[
        "Thatchampadi"
    ],
    "wof:name":"Thatchampadi",
    "wof:placetype":"locality",
    "wof:population":1583
},
  "geometry": {"coordinates":[79.266412,12.495917],"type":"Point"}
}