{
  "type": "Feature",
  "properties": {
    "iso:country":"IN",
    "ks:ks_name":"Saunsa",
    "ks:ks_pop":41,
    "ks:ks_type":"VILLAGE",
    "name:eng_x_preferred":[
        "Saunsa"
    ],
    "wof:name":"Saunsa",
    "wof:placetype":"locality",
    "wof:population":41
},
  "geometry": {"coordinates":[77.872578,25.511601],"type":"Point"}
}