{
  "type": "Feature",
  "properties": {
    "gn:admin1_code":"11",
    "gn:admin2_code":"33.0",
    "gn:asciiname":"Kurari",
    "gn:country_code":"IN",
    "gn:dem":2082,
    "gn:feature_class":"P",
    "gn:feature_code":"PPL",
    "gn:name":"Kur\u0101ri",
    "gn:population":0,
    "gn:timezone":"Asia/Kolkata",
    "iso:country":"IN",
    "wof:name":"Kurari",
    "wof:placetype":"locality"
},
  "geometry": {"coordinates":[77.53458000000001,30.93074],"type":"Point"}
}