{
  "type": "Feature",
  "properties": {
    "iso:country":"IN",
    "ks:ks_alt_nam":"North of Pali Road",
    "ks:ks_name":"North Of Pali Road",
    "ks:ks_pop":135,
    "ks:ks_type":"HABITATION",
    "ks:ks_uagg_main":0,
    "name:eng_x_preferred":[
        "North Of Pali Road"
    ],
    "wof:name":"North Of Pali Road",
    "wof:placetype":"locality",
    "wof:population":135
},
  "geometry": {"coordinates":[84.42734900000001,26.464421],"type":"Point"}
}