{
  "type": "Feature",
  "properties": {
    "iso:country":"IN",
    "ks:ks_name":"Dhabai Purwa",
    "ks:ks_pop":115,
    "ks:ks_type":"HABITATION",
    "ks:ks_uagg_main":0,
    "name:eng_x_preferred":[
        "Dhabai Purwa"
    ],
    "wof:name":"Dhabai Purwa",
    "wof:placetype":"neighbourhood",
    "wof:population":115
},
  "geometry": {"coordinates":[80.916526,28.205311],"type":"Point"}
}