{
  "type": "Feature",
  "properties": {
    "iso:country":"IN",
    "ks:ks_name":"Halowagaon",
    "ks:ks_pop":1000,
    "ks:ks_type":"VILLAGE",
    "name:eng_x_preferred":[
        "Halowagaon"
    ],
    "wof:name":"Halowagaon",
    "wof:placetype":"locality",
    "wof:population":1000
},
  "geometry": {"coordinates":[92.93539699999999,26.491677],"type":"Point"}
}