{
  "type": "Feature",
  "properties": {
    "gn:admin1_code":"36",
    "gn:admin2_code":"157.0",
    "gn:asciiname":"Salahimau",
    "gn:country_code":"IN",
    "gn:dem":114,
    "gn:feature_class":"P",
    "gn:feature_code":"PPL",
    "gn:name":"Sal\u0101himau",
    "gn:population":0,
    "gn:timezone":"Asia/Kolkata",
    "iso:country":"IN",
    "wof:name":"Salahimau",
    "wof:placetype":"locality"
},
  "geometry": {"coordinates":[81.08813000000001,26.83214000000001],"type":"Point"}
}