{
  "type": "Feature",
  "properties": {
    "gn:admin1_code":"39.0",
    "gn:admin2_code":"66.0",
    "gn:asciiname":"Kaudiar",
    "gn:country_code":"IN",
    "gn:dem":1341,
    "gn:feature_class":"P",
    "gn:feature_code":"PPL",
    "gn:name":"Kaudi\u0101r",
    "gn:population":0,
    "gn:timezone":"Asia/Kolkata",
    "iso:country":"IN",
    "wof:name":"Kaudiar",
    "wof:placetype":"locality"
},
  "geometry": {"coordinates":[79.80526999999999,29.29122000000001],"type":"Point"}
}