{
  "type": "Feature",
  "properties": {
    "gn:admin1_code":"39.0",
    "gn:admin2_code":"66.0",
    "gn:asciiname":"Kaudiar",
    "gn:country_code":"IN",
    "gn:dem":1341,
    "gn:feature_class":"P",
    "gn:feature_code":"PPL",
    "gn:name":"Kaudi\u0101r",
    "gn:population":0,
    "gn:timezone":"Asia/Kolkata",
    "iso:country":"IN",
    "ks:ks_alt_nam":"Kaudi\u0101r",
    "ks:ks_name":"Kaudiar",
    "ks:ks_type":"VILLAGE",
    "name:eng_x_preferred":[
        "Kaudiar"
    ],
    "name:eng_x_variant":[
        "Kaudi\u0101r"
    ],
    "wof:name":"Kaudiar",
    "wof:placetype":"locality"
},
  "geometry": {"coordinates":[79.805274,29.291215],"type":"Point"}
}