{
  "type": "Feature",
  "properties": {
    "iso:country":"IN",
    "ks:ks_name":"Kasipally",
    "ks:ks_pop":107,
    "ks:ks_type":"HABITATION",
    "name:eng_x_preferred":[
        "Kasipally"
    ],
    "wof:name":"Kasipally",
    "wof:placetype":"locality",
    "wof:population":107
},
  "geometry": {"coordinates":[79.124706,19.025012],"type":"Point"}
}