{
  "type": "Feature",
  "properties": {
    "iso:country":"IN",
    "ks:ks_name":"Obarthi",
    "ks:ks_pop":96,
    "ks:ks_type":"VILLAGE",
    "name:eng_x_preferred":[
        "Obarthi"
    ],
    "wof:name":"Obarthi",
    "wof:placetype":"locality",
    "wof:population":96
},
  "geometry": {"coordinates":[82.746809,17.961684],"type":"Point"}
}