{
  "type": "Feature",
  "properties": {
    "iso:country":"IN",
    "ks:ks_alt_nam":"ISUKAMITTA",
    "ks:ks_name":"Isukamitta",
    "ks:ks_pop":49,
    "ks:ks_type":"HABITATION",
    "ks:ks_uagg_main":0,
    "name:eng_x_preferred":[
        "Isukamitta"
    ],
    "wof:name":"Isukamitta",
    "wof:placetype":"neighbourhood",
    "wof:population":49
},
  "geometry": {"coordinates":[79.513689,13.578731],"type":"Point"}
}