{
  "type": "Feature",
  "properties": {
    "iso:country":"IN",
    "ks:ks_name":"Loharwadi",
    "ks:ks_pop":65,
    "ks:ks_type":"HABITATION",
    "name:eng_x_preferred":[
        "Loharwadi"
    ],
    "wof:name":"Loharwadi",
    "wof:placetype":"locality",
    "wof:population":65
},
  "geometry": {"coordinates":[73.40699600000001,16.929209],"type":"Point"}
}