{
  "type": "Feature",
  "properties": {
    "iso:country":"IN",
    "ks:ks_name":"Arthe Bk.",
    "ks:ks_pop":3079,
    "ks:ks_type":"VILLAGE",
    "ks:ks_uagg_main":0,
    "name:eng_x_preferred":[
        "Arthe Bk."
    ],
    "wof:name":"Arthe Bk.",
    "wof:placetype":"neighbourhood",
    "wof:population":3079
},
  "geometry": {"coordinates":[74.820964,21.403569],"type":"Point"}
}