{
  "type": "Feature",
  "properties": {
    "iso:country":"IN",
    "ks:ks_name":"Kodarma",
    "ks:ks_pop":17246,
    "ks:ks_type":"URBAN",
    "ks:ks_uagg_main":0,
    "name:eng_x_preferred":[
        "Kodarma"
    ],
    "wof:name":"Kodarma",
    "wof:placetype":"locality",
    "wof:population":17246
},
  "geometry": {"coordinates":[85.593051,24.466099],"type":"Point"}
}