{
  "type": "Feature",
  "properties": {
    "iso:country":"IN",
    "ks:ks_name":"Mullippatti",
    "ks:ks_pop":439,
    "ks:ks_type":"HABITATION",
    "ks:ks_uagg_main":0,
    "name:eng_x_preferred":[
        "Mullippatti"
    ],
    "wof:name":"Mullippatti",
    "wof:placetype":"neighbourhood",
    "wof:population":439
},
  "geometry": {"coordinates":[78.694957,10.697793],"type":"Point"}
}