{
  "type": "Feature",
  "properties": {
    "iso:country":"IN",
    "ks:ks_name":"Kottaiyur",
    "ks:ks_pop":387,
    "ks:ks_type":"HABITATION",
    "ks:ks_uagg_main":0,
    "name:eng_x_preferred":[
        "Kottaiyur"
    ],
    "wof:name":"Kottaiyur",
    "wof:placetype":"neighbourhood",
    "wof:population":387
},
  "geometry": {"coordinates":[78.22814200000001,9.423088],"type":"Point"}
}