{
  "type": "Feature",
  "properties": {
    "iso:country":"IN",
    "ks:ks_alt_nam":"KURMIYAN",
    "ks:ks_name":"Kurmiyan",
    "ks:ks_pop":381,
    "ks:ks_type":"HABITATION",
    "name:eng_x_preferred":[
        "Kurmiyan"
    ],
    "wof:name":"Kurmiyan",
    "wof:placetype":"locality",
    "wof:population":381
},
  "geometry": {"coordinates":[82.244748,25.560883],"type":"Point"}
}