{
  "type": "Feature",
  "properties": {
    "iso:country":"IN",
    "ks:ks_name":"Garh Patti",
    "ks:ks_pop":889,
    "ks:ks_type":"HABITATION",
    "ks:ks_uagg_main":0,
    "name:eng_x_preferred":[
        "Garh Patti"
    ],
    "wof:name":"Garh Patti",
    "wof:placetype":"locality",
    "wof:population":889
},
  "geometry": {"coordinates":[84.719796,25.833641],"type":"Point"}
}