{
  "type": "Feature",
  "properties": {
    "iso:country":"IN",
    "ks:ks_name":"Dandpani",
    "ks:ks_pop":168,
    "ks:ks_type":"HABITATION",
    "name:eng_x_preferred":[
        "Dandpani"
    ],
    "wof:name":"Dandpani",
    "wof:placetype":"locality",
    "wof:population":168
},
  "geometry": {"coordinates":[83.89255,22.33121],"type":"Point"}
}