{
  "type": "Feature",
  "properties": {
    "iso:country":"IN",
    "ks:ks_name":"Lower Keshopur",
    "ks:ks_pop":694,
    "ks:ks_type":"HABITATION",
    "name:eng_x_preferred":[
        "Lower Keshopur"
    ],
    "wof:name":"Lower Keshopur",
    "wof:placetype":"locality",
    "wof:population":694
},
  "geometry": {"coordinates":[86.336467,24.818373],"type":"Point"}
}