{
  "type": "Feature",
  "properties": {
    "iso:country":"IN",
    "ks:ks_name":"Poonkulanji Junction",
    "ks:ks_pop":613,
    "ks:ks_type":"HABITATION",
    "name:eng_x_preferred":[
        "Poonkulanji Junction"
    ],
    "wof:name":"Poonkulanji Junction",
    "wof:placetype":"locality",
    "wof:population":613
},
  "geometry": {"coordinates":[76.906921,9.107726],"type":"Point"}
}