{
  "type": "Feature",
  "properties": {
    "gn:admin1_code":"37",
    "gn:admin2_code":"407.0",
    "gn:asciiname":"Marpa",
    "gn:country_code":"IN",
    "gn:dem":339,
    "gn:feature_class":"P",
    "gn:feature_code":"PPL",
    "gn:name":"Marpa",
    "gn:population":0,
    "gn:timezone":"Asia/Kolkata",
    "iso:country":"IN",
    "name:fra_x_preferred":[
        "Marpa"
    ],
    "wof:name":"Marpa",
    "wof:placetype":"locality"
},
  "geometry": {"coordinates":[81.27079000000001,22.01069],"type":"Point"}
}