{
  "type": "Feature",
  "properties": {
    "iso:country":"IN",
    "ks:ks_name":"Raniberna",
    "ks:ks_pop":375,
    "ks:ks_type":"VILLAGE",
    "name:eng_x_preferred":[
        "Raniberna"
    ],
    "wof:name":"Raniberna",
    "wof:placetype":"locality",
    "wof:population":375
},
  "geometry": {"coordinates":[84.910073,22.11249],"type":"Point"}
}