{
  "type": "Feature",
  "properties": {
    "iso:country":"IN",
    "ks:ks_alt_nam":"Ranipur WalanKa Dera",
    "ks:ks_name":"Ranipur Walanka Dera",
    "ks:ks_pop":125,
    "ks:ks_type":"HABITATION",
    "name:eng_x_preferred":[
        "Ranipur Walanka Dera"
    ],
    "wof:name":"Ranipur Walanka Dera",
    "wof:placetype":"locality",
    "wof:population":125
},
  "geometry": {"coordinates":[80.847256,25.254047],"type":"Point"}
}