{
  "type": "Feature",
  "properties": {
    "iso:country":"IN",
    "ks:ks_name":"Abadi Ratta Gudda",
    "ks:ks_pop":200,
    "ks:ks_type":"HABITATION",
    "name:eng_x_preferred":[
        "Abadi Ratta Gudda"
    ],
    "wof:name":"Abadi Ratta Gudda",
    "wof:placetype":"locality",
    "wof:population":200
},
  "geometry": {"coordinates":[74.921204,31.230558],"type":"Point"}
}