{
  "type": "Feature",
  "properties": {
    "gn:admin1_code":"36",
    "gn:admin2_code":"166.0",
    "gn:asciiname":"Gohana",
    "gn:country_code":"IN",
    "gn:dem":162,
    "gn:feature_class":"P",
    "gn:feature_code":"PPL",
    "gn:name":"Goh\u0101na",
    "gn:population":0,
    "gn:timezone":"Asia/Kolkata",
    "iso:country":"IN",
    "name:ben_x_preferred":[
        "\u0997\u09cb\u09b9\u09be\u09a8\u09be"
    ],
    "name:bpy_x_preferred":[
        "\u0997\u09cb\u09b9\u09be\u09a8\u09be"
    ],
    "name:ceb_x_preferred":[
        "Goh\u0101na"
    ],
    "name:deu_x_preferred":[
        "Gohana"
    ],
    "name:hin_x_preferred":[
        "\u0917\u094b\u0939\u093e\u0928\u093e"
    ],
    "name:ita_x_preferred":[
        "Gohana"
    ],
    "name:msa_x_preferred":[
        "Gohana"
    ],
    "name:nep_x_preferred":[
        "\u0917\u094b\u0939\u093e\u0928\u093e"
    ],
    "name:new_x_preferred":[
        "\u0917\u094b\u0939\u093e\u0928\u093e"
    ],
    "name:nld_x_preferred":[
        "Gohana"
    ],
    "name:ori_x_preferred":[
        "\u0b17\u0b4b\u0b39\u0b3e\u0b28\u0b3e"
    ],
    "name:por_x_preferred":[
        "Gohana"
    ],
    "name:spa_x_preferred":[
        "Gohana"
    ],
    "name:swe_x_preferred":[
        "Goh\u0101na"
    ],
    "name:urd_x_preferred":[
        "\u06af\u0648\u06c1\u0627\u0646\u0627"
    ],
    "name:vie_x_preferred":[
        "Gohana"
    ],
    "name:zho_x_preferred":[
        "\u6208\u54c8\u7eb3"
    ],
    "wof:name":"Gohana",
    "wof:placetype":"locality"
},
  "geometry": {"coordinates":[79.27078,25.55651],"type":"Point"}
}