{
  "type": "Feature",
  "properties": {
    "gn:admin1_code":"21",
    "gn:admin2_code":"396.0",
    "gn:asciiname":"Dingirpanga",
    "gn:country_code":"IN",
    "gn:dem":394,
    "gn:feature_class":"P",
    "gn:feature_code":"PPL",
    "gn:name":"Dingirpanga",
    "gn:population":0,
    "gn:timezone":"Asia/Kolkata",
    "iso:country":"IN",
    "ks:ks_name":"Dingarapanga",
    "ks:ks_pop":12,
    "ks:ks_type":"VILLAGE",
    "name:eng_x_preferred":[
        "Dingarapanga"
    ],
    "name:eng_x_variant":[
        "Dingirpanga"
    ],
    "wof:name":"Dingarapanga",
    "wof:placetype":"locality",
    "wof:population":12
},
  "geometry": {"coordinates":[83.56412400000001,19.779869],"type":"Point"}
}