{
  "type": "Feature",
  "properties": {
    "gn:admin1_code":"19.0",
    "gn:admin2_code":"563.0",
    "gn:asciiname":"Negar",
    "gn:country_code":"IN",
    "gn:dem":523,
    "gn:feature_class":"P",
    "gn:feature_code":"PPL",
    "gn:name":"Neg\u0101r",
    "gn:population":0,
    "gn:timezone":"Asia/Kolkata",
    "iso:country":"IN",
    "name:ara_x_preferred":[
        "\u0646\u063a\u0627\u0631"
    ],
    "name:aze_x_preferred":[
        "Nigar"
    ],
    "name:ceb_x_preferred":[
        "Neg\u0101r"
    ],
    "name:fas_x_preferred":[
        "\u0646\u06af\u0627\u0631"
    ],
    "name:ita_x_preferred":[
        "Negar"
    ],
    "name:mlg_x_preferred":[
        "Negar"
    ],
    "name:nor_x_preferred":[
        "Nigar"
    ],
    "name:swe_x_preferred":[
        "Neg\u0101r"
    ],
    "name:tur_x_preferred":[
        "Nigar"
    ],
    "wof:name":"Negar",
    "wof:placetype":"locality"
},
  "geometry": {"coordinates":[74.73732,14.4526],"type":"Point"}
}