{
  "type": "Feature",
  "properties": {
    "gn:admin1_code":"39.0",
    "gn:admin2_code":"66.0",
    "gn:asciiname":"Deodhura",
    "gn:country_code":"IN",
    "gn:dem":1359,
    "gn:feature_class":"P",
    "gn:feature_code":"PPL",
    "gn:name":"Deodhura",
    "gn:population":0,
    "gn:timezone":"Asia/Kolkata",
    "iso:country":"IN",
    "wof:name":"Deodhura",
    "wof:placetype":"locality"
},
  "geometry": {"coordinates":[79.43355,29.34274000000001],"type":"Point"}
}