{
  "type": "Feature",
  "properties": {
    "gn:admin1_code":"11.0",
    "gn:admin2_code":"24.0",
    "gn:asciiname":"Gor",
    "gn:country_code":"IN",
    "gn:dem":588,
    "gn:feature_class":"P",
    "gn:feature_code":"PPL",
    "gn:name":"Gor",
    "gn:population":0,
    "gn:timezone":"Asia/Kolkata",
    "iso:country":"IN",
    "wof:name":"Gor",
    "wof:placetype":"locality"
},
  "geometry": {"coordinates":[75.87993,32.17616],"type":"Point"}
}