{
  "type": "Feature",
  "properties": {
    "gn:admin1_code":"2.0",
    "gn:admin2_code":"543.0",
    "gn:asciiname":"Kotarakota",
    "gn:country_code":"IN",
    "gn:dem":570,
    "gn:feature_class":"P",
    "gn:feature_code":"PPL",
    "gn:name":"Kot\u0101rakota",
    "gn:population":0,
    "gn:timezone":"Asia/Kolkata",
    "iso:country":"IN",
    "ks:ks_name":"Katarikota",
    "ks:ks_pop":131,
    "ks:ks_type":"VILLAGE",
    "name:eng_x_preferred":[
        "Katarikota"
    ],
    "name:eng_x_variant":[
        "Kotarakota"
    ],
    "wof:name":"Katarikota",
    "wof:placetype":"locality",
    "wof:population":131
},
  "geometry": {"coordinates":[83.203906,18.417378],"type":"Point"}
}