{
  "type": "Feature",
  "properties": {
    "iso:country":"IN",
    "ks:ks_name":"Kolan Basti",
    "ks:ks_pop":188,
    "ks:ks_type":"HABITATION",
    "name:eng_x_preferred":[
        "Kolan Basti"
    ],
    "wof:name":"Kolan Basti",
    "wof:placetype":"locality",
    "wof:population":188
},
  "geometry": {"coordinates":[82.28179799999999,24.900445],"type":"Point"}
}