{
  "type": "Feature",
  "properties": {
    "gn:admin1_code":"24",
    "gn:admin2_code":"109.0",
    "gn:asciiname":"Lowan",
    "gn:country_code":"IN",
    "gn:dem":320,
    "gn:feature_class":"P",
    "gn:feature_code":"PPL",
    "gn:name":"Low\u0101n",
    "gn:population":0,
    "gn:timezone":"Asia/Kolkata",
    "iso:country":"IN",
    "wof:name":"Lowan",
    "wof:placetype":"locality"
},
  "geometry": {"coordinates":[76.21339,26.76977],"type":"Point"}
}