{
  "type": "Feature",
  "properties": {
    "gn:admin1_code":"35",
    "gn:admin2_code":"426.0",
    "gn:asciiname":"Makkapala",
    "gn:country_code":"IN",
    "gn:dem":422,
    "gn:feature_class":"P",
    "gn:feature_code":"PPL",
    "gn:name":"Makk\u0101p\u0101la",
    "gn:population":0,
    "gn:timezone":"Asia/Kolkata",
    "iso:country":"IN",
    "ks:ks_name":"Makepala",
    "ks:ks_pop":381,
    "ks:ks_type":"HABITATION",
    "name:eng_x_preferred":[
        "Makepala"
    ],
    "name:eng_x_variant":[
        "Makkapala"
    ],
    "wof:name":"Makepala",
    "wof:placetype":"locality",
    "wof:population":381
},
  "geometry": {"coordinates":[79.929316,24.04396],"type":"Point"}
}