{
  "type": "Feature",
  "properties": {
    "gn:admin1_code":"34.0",
    "gn:admin2_code":"240.0",
    "gn:asciiname":"Utrapatti",
    "gn:country_code":"IN",
    "gn:dem":78,
    "gn:feature_class":"P",
    "gn:feature_code":"PPL",
    "gn:name":"Utr\u0101patti",
    "gn:population":0,
    "gn:timezone":"Asia/Kolkata",
    "iso:country":"IN",
    "wof:name":"Utrapatti",
    "wof:placetype":"locality"
},
  "geometry": {"coordinates":[84.86236,25.09384],"type":"Point"}
}