{
  "type": "Feature",
  "properties": {
    "gn:admin1_code":"16.0",
    "gn:admin2_code":"529",
    "gn:asciiname":"Avalegaon",
    "gn:country_code":"IN",
    "gn:dem":43,
    "gn:feature_class":"P",
    "gn:feature_code":"PPL",
    "gn:name":"Avalegaon",
    "gn:population":0,
    "gn:timezone":"Asia/Kolkata",
    "iso:country":"IN",
    "wof:name":"Avalegaon",
    "wof:placetype":"locality"
},
  "geometry": {"coordinates":[73.75709000000001,16.11392],"type":"Point"}
}