{
  "type": "Feature",
  "properties": {
    "iso:country":"IN",
    "ks:ks_alt_nam":"PAYAVU BRIDGE",
    "ks:ks_name":"Payavu Bridge",
    "ks:ks_pop":62,
    "ks:ks_type":"HABITATION",
    "name:eng_x_preferred":[
        "Payavu Bridge"
    ],
    "wof:name":"Payavu Bridge",
    "wof:placetype":"locality",
    "wof:population":62
},
  "geometry": {"coordinates":[76.730572,9.980908],"type":"Point"}
}