{
  "type": "Feature",
  "properties": {
    "gn:admin1_code":"34.0",
    "gn:admin2_code":"211.0",
    "gn:asciiname":"Sukhasan",
    "gn:country_code":"IN",
    "gn:dem":46,
    "gn:feature_class":"P",
    "gn:feature_code":"PPL",
    "gn:name":"Sukh\u0101san",
    "gn:population":0,
    "gn:timezone":"Asia/Kolkata",
    "iso:country":"IN",
    "wof:name":"Sukhasan",
    "wof:placetype":"locality"
},
  "geometry": {"coordinates":[87.15111999999998,25.84547],"type":"Point"}
}