{
  "type": "Feature",
  "properties": {
    "iso:country":"IN",
    "ks:ks_alt_nam":"Shiml\u012bpur",
    "ks:ks_name":"Shimlipur",
    "ks:ks_type":"VILLAGE",
    "name:eng_x_preferred":[
        "Shimlipur"
    ],
    "name:eng_x_variant":[
        "Shiml\u012bpur"
    ],
    "wof:name":"Shimlipur",
    "wof:placetype":"locality"
},
  "geometry": {"coordinates":[76.925489,30.648326],"type":"Point"}
}