{
  "type": "Feature",
  "properties": {
    "iso:country":"IN",
    "ks:ks_name":"Sherebhorwadi",
    "ks:ks_pop":457,
    "ks:ks_type":"HABITATION",
    "name:eng_x_preferred":[
        "Sherebhorwadi"
    ],
    "wof:name":"Sherebhorwadi",
    "wof:placetype":"locality",
    "wof:population":457
},
  "geometry": {"coordinates":[73.34331899999999,17.572672],"type":"Point"}
}