{
  "type": "Feature",
  "properties": {
    "gn:admin1_code":"19.0",
    "gn:admin2_code":"573.0",
    "gn:asciiname":"Talemaledoddi",
    "gn:country_code":"IN",
    "gn:dem":700,
    "gn:feature_class":"P",
    "gn:feature_code":"PPL",
    "gn:name":"T\u0101lemaledoddi",
    "gn:population":0,
    "gn:timezone":"Asia/Kolkata",
    "iso:country":"IN",
    "ks:ks_name":"Thalemeledoddi",
    "ks:ks_pop":344,
    "ks:ks_type":"HABITATION",
    "name:eng_x_preferred":[
        "Thalemeledoddi"
    ],
    "name:eng_x_variant":[
        "Talemaledoddi"
    ],
    "wof:name":"Thalemeledoddi",
    "wof:placetype":"locality",
    "wof:population":344
},
  "geometry": {"coordinates":[76.908047,12.641147],"type":"Point"}
}