{
  "type": "Feature",
  "properties": {
    "iso:country":"IN",
    "ks:ks_name":"Teliwadi",
    "ks:ks_pop":84,
    "ks:ks_type":"HABITATION",
    "name:eng_x_preferred":[
        "Teliwadi"
    ],
    "wof:name":"Teliwadi",
    "wof:placetype":"locality",
    "wof:population":84
},
  "geometry": {"coordinates":[73.353889,17.493056],"type":"Point"}
}