{
  "type": "Feature",
  "properties": {
    "gn:admin1_code":"10.0",
    "gn:admin2_code":"83.0",
    "gn:asciiname":"Achhej",
    "gn:country_code":"IN",
    "gn:dem":220,
    "gn:feature_class":"P",
    "gn:feature_code":"PPL",
    "gn:name":"Achhej",
    "gn:population":0,
    "gn:timezone":"Asia/Kolkata",
    "iso:country":"IN",
    "wof:name":"Achhej",
    "wof:placetype":"neighbourhood"
},
  "geometry": {"coordinates":[76.49973,28.61915],"type":"Point"}
}