{
  "type": "Feature",
  "properties": {
    "iso:country":"IN",
    "ks:ks_name":"Goalgaon",
    "ks:ks_pop":598,
    "ks:ks_type":"HABITATION",
    "ks:ks_uagg_main":0,
    "name:eng_x_preferred":[
        "Goalgaon"
    ],
    "wof:name":"Goalgaon",
    "wof:placetype":"neighbourhood",
    "wof:population":598
},
  "geometry": {"coordinates":[94.00346500000001,26.1979],"type":"Point"}
}