{
  "type": "Feature",
  "properties": {
    "iso:country":"IN",
    "ks:ks_name":"Gadikallu",
    "ks:ks_pop":194,
    "ks:ks_type":"HABITATION",
    "name:eng_x_preferred":[
        "Gadikallu"
    ],
    "wof:name":"Gadikallu",
    "wof:placetype":"locality",
    "wof:population":194
},
  "geometry": {"coordinates":[75.625765,12.558692],"type":"Point"}
}