{
  "type": "Feature",
  "properties": {
    "iso:country":"IN",
    "ks:ks_name":"Napun",
    "ks:ks_pop":926,
    "ks:ks_type":"HABITATION",
    "name:eng_x_preferred":[
        "Napun"
    ],
    "wof:name":"Napun",
    "wof:placetype":"locality",
    "wof:population":926
},
  "geometry": {"coordinates":[95.511563,27.846418],"type":"Point"}
}