{
  "type": "Feature",
  "properties": {
    "gn:admin1_code":"9.0",
    "gn:admin2_code":"493.0",
    "gn:asciiname":"Rajpur",
    "gn:country_code":"IN",
    "gn:dem":121,
    "gn:feature_class":"P",
    "gn:feature_code":"PPL",
    "gn:name":"Rajpur",
    "gn:population":0,
    "gn:timezone":"Asia/Kolkata",
    "iso:country":"IN",
    "name:ara_x_preferred":[
        "\u0631\u0627\u062c\u0628\u0648\u0631"
    ],
    "name:ben_bn_x_preferred":[
        "\u09b0\u09be\u099c\u09aa\u09c1\u09b0"
    ],
    "name:ben_in_x_preferred":[
        "\u09b0\u09be\u099c\u09aa\u09c1\u09b0"
    ],
    "name:cat_x_preferred":[
        "Rajpur"
    ],
    "name:ceb_x_preferred":[
        "Rajpur"
    ],
    "name:guj_x_preferred":[
        "\u0ab0\u0abe\u0a9c\u0aaa\u0ac1\u0ab0"
    ],
    "name:hin_x_preferred":[
        "\u0930\u093e\u091c\u092a\u0941\u0930"
    ],
    "name:kan_x_preferred":[
        "\u0cb0\u0cbe\u0c9c\u0ccd"
    ],
    "name:mal_x_preferred":[
        "\u0d30\u0d3e\u0d1c\u0d4d\u0d2a\u0d42\u0d7c"
    ],
    "name:mar_x_preferred":[
        "\u0930\u093e\u091c\u092a\u0941\u0930"
    ],
    "name:pan_x_preferred":[
        "\u0a30\u0a3e\u0a1c\u0a2a\u0a41\u0a30"
    ],
    "name:pol_x_preferred":[
        "Rajpur"
    ],
    "name:spa_x_preferred":[
        "Rajpur"
    ],
    "name:swe_x_preferred":[
        "Rajpur"
    ],
    "name:tam_x_preferred":[
        "\u0bb0\u0bbe\u0b9c\u0bcd\u0baa\u0bc2\u0bb0\u0bcd"
    ],
    "name:tel_x_preferred":[
        "\u0c30\u0c3e\u0c1c\u0c4d"
    ],
    "name:urd_x_preferred":[
        "\u0631\u0627\u062c\u067e\u0648\u0631"
    ],
    "wof:name":"Rajpur",
    "wof:placetype":"locality"
},
  "geometry": {"coordinates":[74.08988000000002,21.54742],"type":"Point"}
}