{
  "type": "Feature",
  "properties": {
    "iso:country":"IN",
    "ks:ks_name":"Saaymal",
    "ks:ks_pop":150,
    "ks:ks_type":"HABITATION",
    "name:eng_x_preferred":[
        "Saaymal"
    ],
    "wof:name":"Saaymal",
    "wof:placetype":"locality",
    "wof:population":150
},
  "geometry": {"coordinates":[73.026488,18.778932],"type":"Point"}
}