{
  "type": "Feature",
  "properties": {
    "gn:admin1_code":"35",
    "gn:admin2_code":"443.0",
    "gn:asciiname":"Mahuwakhera Ustad",
    "gn:country_code":"IN",
    "gn:dem":513,
    "gn:feature_class":"P",
    "gn:feature_code":"PPL",
    "gn:name":"Mahuw\u0101khera Ust\u0101d",
    "gn:population":0,
    "gn:timezone":"Asia/Kolkata",
    "iso:country":"IN",
    "wof:name":"Mahuwakhera Ustad",
    "wof:placetype":"locality"
},
  "geometry": {"coordinates":[77.65835,24.03203],"type":"Point"}
}