{
  "type": "Feature",
  "properties": {
    "iso:country":"IN",
    "ks:ks_name":"Kaladu",
    "ks:ks_pop":96,
    "ks:ks_type":"HABITATION",
    "name:eng_x_preferred":[
        "Kaladu"
    ],
    "wof:name":"Kaladu",
    "wof:placetype":"locality",
    "wof:population":96
},
  "geometry": {"coordinates":[85.116519,21.541984],"type":"Point"}
}