{
  "type": "Feature",
  "properties": {
    "gn:admin1_code":"16.0",
    "gn:admin2_code":"508.0",
    "gn:asciiname":"Darba",
    "gn:country_code":"IN",
    "gn:dem":226,
    "gn:feature_class":"P",
    "gn:feature_code":"PPL",
    "gn:name":"Darba",
    "gn:population":0,
    "gn:timezone":"Asia/Kolkata",
    "iso:country":"IN",
    "ks:ks_name":"Darbha",
    "ks:ks_pop":294,
    "ks:ks_type":"VILLAGE",
    "name:eng_x_preferred":[
        "Darbha"
    ],
    "name:eng_x_variant":[
        "Darba"
    ],
    "wof:name":"Darbha",
    "wof:placetype":"locality",
    "wof:population":294
},
  "geometry": {"coordinates":[80.62309999999999,19.36937],"type":"Point"}
}