{
  "type": "Feature",
  "properties": {
    "iso:country":"IN",
    "ks:ks_name":"Ratas Urf Kaptanganj",
    "ks:ks_pop":462,
    "ks:ks_type":"VILLAGE",
    "name:eng_x_preferred":[
        "Ratas Urf Kaptanganj"
    ],
    "wof:name":"Ratas Urf Kaptanganj",
    "wof:placetype":"locality",
    "wof:population":462
},
  "geometry": {"coordinates":[82.584234,26.762415],"type":"Point"}
}