{
  "type": "Feature",
  "properties": {
    "iso:country":"IN",
    "ks:ks_name":"Mohanpur",
    "ks:ks_pop":2195,
    "ks:ks_type":"VILLAGE",
    "ks:ks_uagg_main":0,
    "name:eng_x_preferred":[
        "Mohanpur"
    ],
    "wof:name":"Mohanpur",
    "wof:placetype":"neighbourhood",
    "wof:population":2195
},
  "geometry": {"coordinates":[87.793601,23.377952],"type":"Point"}
}