{
  "type": "Feature",
  "properties": {
    "gn:admin1_code":"11",
    "gn:admin2_code":"33.0",
    "gn:asciiname":"Chatiar",
    "gn:country_code":"IN",
    "gn:dem":1353,
    "gn:feature_class":"P",
    "gn:feature_code":"PPL",
    "gn:name":"Chat\u012b\u0101r",
    "gn:population":0,
    "gn:timezone":"Asia/Kolkata",
    "iso:country":"IN",
    "wof:name":"Chatiar",
    "wof:placetype":"locality"
},
  "geometry": {"coordinates":[77.14740999999999,31.19088],"type":"Point"}
}