{
  "type": "Feature",
  "properties": {
    "gn:admin1_code":"19.0",
    "gn:admin2_code":"563.0",
    "gn:asciiname":"Nirhakkal",
    "gn:country_code":"IN",
    "gn:dem":591,
    "gn:feature_class":"P",
    "gn:feature_code":"PPL",
    "gn:name":"Nirhakkal",
    "gn:population":0,
    "gn:timezone":"Asia/Kolkata",
    "iso:country":"IN",
    "ks:ks_name":"Nirahakkal",
    "ks:ks_pop":13,
    "ks:ks_type":"HABITATION",
    "name:eng_x_preferred":[
        "Nirahakkal"
    ],
    "name:eng_x_variant":[
        "Nirhakkal"
    ],
    "wof:name":"Nirahakkal",
    "wof:placetype":"locality",
    "wof:population":13
},
  "geometry": {"coordinates":[74.47473100000001,14.811864],"type":"Point"}
}