{
  "type": "Feature",
  "properties": {
    "iso:country":"IN",
    "ks:ks_name":"Lamba Pipla",
    "ks:ks_pop":871,
    "ks:ks_type":"HABITATION",
    "name:eng_x_preferred":[
        "Lamba Pipla"
    ],
    "wof:name":"Lamba Pipla",
    "wof:placetype":"locality",
    "wof:population":871
},
  "geometry": {"coordinates":[73.89073,23.604775],"type":"Point"}
}