{
  "type": "Feature",
  "properties": {
    "iso:country":"IN",
    "ks:ks_alt_nam":"Tokrapara Gaon Pt II",
    "ks:ks_name":"Tokrapara Gaon Pt Ii",
    "ks:ks_pop":91,
    "ks:ks_type":"HABITATION",
    "name:eng_x_preferred":[
        "Tokrapara Gaon Pt Ii"
    ],
    "wof:name":"Tokrapara Gaon Pt Ii",
    "wof:placetype":"locality",
    "wof:population":91
},
  "geometry": {"coordinates":[90.01779000000001,26.314908],"type":"Point"}
}