{
  "type": "Feature",
  "properties": {
    "gn:admin1_code":"36",
    "gn:admin2_code":"200.0",
    "gn:asciiname":"Khairahi",
    "gn:country_code":"IN",
    "gn:dem":304,
    "gn:feature_class":"P",
    "gn:feature_code":"PPL",
    "gn:name":"Khair\u0101hi",
    "gn:population":0,
    "gn:timezone":"Asia/Kolkata",
    "iso:country":"IN",
    "ks:ks_name":"Khairahi",
    "ks:ks_pop":565,
    "ks:ks_type":"HABITATION",
    "name:eng_x_preferred":[
        "Khairahi"
    ],
    "wof:name":"Khairahi",
    "wof:placetype":"locality",
    "wof:population":565
},
  "geometry": {"coordinates":[82.890354,24.357366],"type":"Point"}
}