{
  "type": "Feature",
  "properties": {
    "iso:country":"IN",
    "ks:ks_name":"Islampur",
    "ks:ks_pop":275,
    "ks:ks_type":"HABITATION",
    "name:eng_x_preferred":[
        "Islampur"
    ],
    "wof:name":"Islampur",
    "wof:placetype":"locality",
    "wof:population":275
},
  "geometry": {"coordinates":[93.14442200000001,25.915243],"type":"Point"}
}