{
  "type": "Feature",
  "properties": {
    "gn:admin1_code":"38.0",
    "gn:admin2_code":"353.0",
    "gn:asciiname":"Jamkanali",
    "gn:country_code":"IN",
    "gn:dem":99,
    "gn:feature_class":"P",
    "gn:feature_code":"PPL",
    "gn:name":"J\u0101mk\u0101n\u0101li",
    "gn:population":0,
    "gn:timezone":"Asia/Kolkata",
    "iso:country":"IN",
    "ks:ks_alt_nam":"J\u0101mk\u0101n\u0101li",
    "ks:ks_name":"Jamkanali",
    "ks:ks_pop":1577,
    "ks:ks_type":"VILLAGE",
    "name:eng_x_preferred":[
        "Jamkanali"
    ],
    "name:eng_x_variant":[
        "J\u0101mk\u0101n\u0101li"
    ],
    "wof:name":"Jamkanali",
    "wof:placetype":"locality",
    "wof:population":1577
},
  "geometry": {"coordinates":[87.618544,24.585765],"type":"Point"}
}