{
  "type": "Feature",
  "properties": {
    "iso:country":"IN",
    "ks:ks_name":"Kapahuwa Gaon",
    "ks:ks_pop":438,
    "ks:ks_type":"HABITATION",
    "name:eng_x_preferred":[
        "Kapahuwa Gaon"
    ],
    "wof:name":"Kapahuwa Gaon",
    "wof:placetype":"locality",
    "wof:population":438
},
  "geometry": {"coordinates":[95.546181,27.415338],"type":"Point"}
}