{
  "type": "Feature",
  "properties": {
    "gn:admin1_code":"36",
    "gn:admin2_code":"193.0",
    "gn:asciiname":"Amahra",
    "gn:country_code":"IN",
    "gn:dem":70,
    "gn:feature_class":"P",
    "gn:feature_code":"PPL",
    "gn:name":"Amahr\u0101",
    "gn:population":0,
    "gn:timezone":"Asia/Kolkata",
    "iso:country":"IN",
    "wof:name":"Amahra",
    "wof:placetype":"locality"
},
  "geometry": {"coordinates":[83.78560999999998,25.8238],"type":"Point"}
}