{
  "type": "Feature",
  "properties": {
    "iso:country":"IN",
    "ks:ks_name":"Ghasua",
    "ks:ks_pop":256,
    "ks:ks_type":"VILLAGE",
    "name:eng_x_preferred":[
        "Ghasua"
    ],
    "wof:name":"Ghasua",
    "wof:placetype":"locality",
    "wof:population":256
},
  "geometry": {"coordinates":[86.68720399999999,21.22258],"type":"Point"}
}