{
  "type": "Feature",
  "properties": {
    "gn:admin1_code":"36",
    "gn:admin2_code":"195.0",
    "gn:asciiname":"Birbhanpur",
    "gn:country_code":"IN",
    "gn:dem":70,
    "gn:feature_class":"P",
    "gn:feature_code":"PPL",
    "gn:name":"B\u012brbhanpur",
    "gn:population":0,
    "gn:timezone":"Asia/Kolkata",
    "iso:country":"IN",
    "name:urd_x_preferred":[
        "\u0628\u0631\u0628\u06be\u0627\u0646 \u067e\u0648\u0631"
    ],
    "wof:name":"Birbhanpur",
    "wof:placetype":"locality"
},
  "geometry": {"coordinates":[83.89572,25.66198],"type":"Point"}
}