{
  "type": "Feature",
  "properties": {
    "iso:country":"IN",
    "ks:ks_name":"Koluha Bhoj",
    "ks:ks_pop":294,
    "ks:ks_type":"HABITATION",
    "name:eng_x_preferred":[
        "Koluha Bhoj"
    ],
    "wof:name":"Koluha Bhoj",
    "wof:placetype":"locality",
    "wof:population":294
},
  "geometry": {"coordinates":[82.4939,25.228199],"type":"Point"}
}