{
  "type": "Feature",
  "properties": {
    "gn:admin1_code":"40",
    "gn:admin2_code":"540.0",
    "gn:asciiname":"Gagilapuram",
    "gn:country_code":"IN",
    "gn:dem":455,
    "gn:feature_class":"P",
    "gn:feature_code":"PPL",
    "gn:name":"G\u0101gil\u0101puram",
    "gn:population":0,
    "gn:timezone":"Asia/Kolkata",
    "iso:country":"IN",
    "wof:name":"Gagilapuram",
    "wof:placetype":"neighbourhood"
},
  "geometry": {"coordinates":[79.05158,17.94127],"type":"Point"}
}