{
  "type": "Feature",
  "properties": {
    "iso:country":"IN",
    "ks:ks_name":"Nanarahi Uttar",
    "ks:ks_pop":1994,
    "ks:ks_type":"HABITATION",
    "name:eng_x_preferred":[
        "Nanarahi Uttar"
    ],
    "wof:name":"Nanarahi Uttar",
    "wof:placetype":"locality",
    "wof:population":1994
},
  "geometry": {"coordinates":[87.84116899999999,25.431513],"type":"Point"}
}