{
  "type": "Feature",
  "properties": {
    "gn:admin1_code":"34.0",
    "gn:admin2_code":"217.0",
    "gn:asciiname":"Bhatwa Khurd",
    "gn:country_code":"IN",
    "gn:dem":82,
    "gn:feature_class":"P",
    "gn:feature_code":"PPL",
    "gn:name":"Bhatw\u0101 Khurd",
    "gn:population":0,
    "gn:timezone":"Asia/Kolkata",
    "iso:country":"IN",
    "ks:ks_alt_nam":"Bhatw\u0101 Khurd",
    "ks:ks_name":"Bhatwa Khurd",
    "ks:ks_pop":621,
    "ks:ks_type":"VILLAGE",
    "name:eng_x_preferred":[
        "Bhatwa Khurd"
    ],
    "name:eng_x_variant":[
        "Bhatw\u0101 Khurd"
    ],
    "wof:name":"Bhatwa Khurd",
    "wof:placetype":"locality",
    "wof:population":621
},
  "geometry": {"coordinates":[84.173323,26.605288],"type":"Point"}
}