{
  "type": "Feature",
  "properties": {
    "iso:country":"IN",
    "ks:ks_alt_nam":"Pah\u0101rpur",
    "ks:ks_name":"Paharpur",
    "ks:ks_pop":80,
    "ks:ks_type":"VILLAGE",
    "name:eng_x_preferred":[
        "Paharpur"
    ],
    "name:eng_x_variant":[
        "Pah\u0101rpur"
    ],
    "wof:name":"Paharpur",
    "wof:placetype":"locality",
    "wof:population":80
},
  "geometry": {"coordinates":[86.19553500000001,24.645012],"type":"Point"}
}