{
  "type": "Feature",
  "properties": {
    "gn:admin1_code":"13.0",
    "gn:admin2_code":"600.0",
    "gn:asciiname":"Anjuvilamud",
    "gn:country_code":"IN",
    "gn:dem":24,
    "gn:feature_class":"P",
    "gn:feature_code":"PPL",
    "gn:name":"Anjuvilam\u016bd",
    "gn:population":0,
    "gn:timezone":"Asia/Kolkata",
    "iso:country":"IN",
    "wof:name":"Anjuvilamud",
    "wof:placetype":"locality"
},
  "geometry": {"coordinates":[76.60881999999999,8.93206],"type":"Point"}
}