{
  "type": "Feature",
  "properties": {
    "iso:country":"IN",
    "ks:ks_name":"Porabali",
    "ks:ks_pop":381,
    "ks:ks_type":"VILLAGE",
    "ks:ks_uagg_main":0,
    "name:eng_x_preferred":[
        "Porabali"
    ],
    "wof:name":"Porabali",
    "wof:placetype":"neighbourhood",
    "wof:population":381
},
  "geometry": {"coordinates":[87.552196,24.017025],"type":"Point"}
}