{
  "type": "Feature",
  "properties": {
    "gn:admin1_code":"36",
    "gn:admin2_code":"145.0",
    "gn:asciiname":"Aurangabad",
    "gn:country_code":"IN",
    "gn:dem":173,
    "gn:feature_class":"P",
    "gn:feature_code":"PPL",
    "gn:name":"Aurang\u0101b\u0101d",
    "gn:population":0,
    "gn:timezone":"Asia/Kolkata",
    "iso:country":"IN",
    "name:ara_x_preferred":[
        "\u0623\u0648\u0631\u0627\u0646\u062c\u0627\u0628\u0627\u062f"
    ],
    "name:ben_x_preferred":[
        "\u0994\u09b0\u0999\u09cd\u0997\u09be\u09ac\u09be\u09a6"
    ],
    "name:bih_x_preferred":[
        "\u0914\u0930\u0902\u0917\u093e\u092c\u093e\u0926"
    ],
    "name:cat_x_preferred":[
        "Aurangabad"
    ],
    "name:deu_x_preferred":[
        "Aurangabad"
    ],
    "name:hin_x_preferred":[
        "\u0914\u0930\u0902\u0917\u093e\u092c\u093e\u0926"
    ],
    "name:ita_x_preferred":[
        "Aurangabad"
    ],
    "name:nld_x_preferred":[
        "Aurangabad"
    ],
    "name:nor_x_preferred":[
        "Aurangabad"
    ],
    "name:pol_x_preferred":[
        "Aurangabad"
    ],
    "name:pus_x_preferred":[
        "\u0627\u0648\u0631\u0646\u06af \u0627\u0628\u0627\u062f"
    ],
    "name:rus_x_preferred":[
        "\u0410\u0443\u0440\u0430\u043d\u0433\u0430\u0431\u0430\u0434"
    ],
    "name:san_x_preferred":[
        "\u0914\u0930\u0919\u094d\u0917\u093e\u092c\u093e\u0926"
    ],
    "name:spa_x_preferred":[
        "Aurangabad"
    ],
    "name:swe_x_preferred":[
        "Aurangabad"
    ],
    "name:ukr_x_preferred":[
        "\u0410\u0443\u0440\u0430\u043d\u0433\u0430\u0431\u0430\u0434"
    ],
    "name:urd_x_preferred":[
        "\u0627\u0648\u0631\u0646\u06af \u0622\u0628\u0627\u062f"
    ],
    "wof:name":"Aurangabad",
    "wof:placetype":"locality"
},
  "geometry": {"coordinates":[77.7055,27.44267],"type":"Point"}
}