{
  "type": "Feature",
  "properties": {
    "iso:country":"IN",
    "ks:ks_name":"Puthagalur",
    "ks:ks_pop":778,
    "ks:ks_type":"HABITATION",
    "name:eng_x_preferred":[
        "Puthagalur"
    ],
    "wof:name":"Puthagalur",
    "wof:placetype":"locality",
    "wof:population":778
},
  "geometry": {"coordinates":[79.564449,10.90592],"type":"Point"}
}