{
  "type": "Feature",
  "properties": {
    "iso:country":"IN",
    "ks:ks_name":"Pindi",
    "ks:ks_pop":1225,
    "ks:ks_type":"VILLAGE",
    "ks:ks_uagg_main":0,
    "name:eng_x_preferred":[
        "Pindi"
    ],
    "wof:name":"Pindi",
    "wof:placetype":"neighbourhood",
    "wof:population":1225
},
  "geometry": {"coordinates":[75.39850300000001,32.138968],"type":"Point"}
}