{
  "type": "Feature",
  "properties": {
    "gn:admin1_code":"34.0",
    "gn:admin2_code":"236.0",
    "gn:asciiname":"Rangpur",
    "gn:country_code":"IN",
    "gn:dem":125,
    "gn:feature_class":"P",
    "gn:feature_code":"PPL",
    "gn:name":"Rangpur",
    "gn:population":0,
    "gn:timezone":"Asia/Kolkata",
    "iso:country":"IN",
    "name:ben_x_preferred":[
        "\u09b0\u0982\u09aa\u09c1\u09b0"
    ],
    "name:ceb_x_preferred":[
        "Rangpur"
    ],
    "name:deu_x_preferred":[
        "Rangpur"
    ],
    "name:fra_x_preferred":[
        "Rangpur"
    ],
    "name:ind_x_preferred":[
        "Rangpur"
    ],
    "name:mal_x_preferred":[
        "\u0d30\u0d02\u0d17\u0d4d\u200d\u0d2a\u0d42\u0d7c \u0d2a\u0d1f\u0d4d\u0d1f\u0d23\u0d02"
    ],
    "name:nld_x_preferred":[
        "Rangpur"
    ],
    "name:rus_x_preferred":[
        "\u0420\u0430\u043d\u0433\u043f\u0443\u0440"
    ],
    "name:swe_x_preferred":[
        "Rangpur"
    ],
    "name:ukr_x_preferred":[
        "\u0420\u0430\u043d\u0433\u043f\u0443\u0440"
    ],
    "wof:name":"Rangpur",
    "wof:placetype":"locality"
},
  "geometry": {"coordinates":[85.34536999999997,24.97167],"type":"Point"}
}