{
  "type": "Feature",
  "properties": {
    "gn:admin1_code":"34.0",
    "gn:admin2_code":"236.0",
    "gn:asciiname":"Rangpur",
    "gn:country_code":"IN",
    "gn:dem":125,
    "gn:feature_class":"P",
    "gn:feature_code":"PPL",
    "gn:name":"Rangpur",
    "gn:population":0,
    "gn:timezone":"Asia/Kolkata",
    "iso:country":"IN",
    "name:ara_x_preferred":[
        "\u0631\u0627\u0646\u062c\u0628\u0648\u0631"
    ],
    "name:ben_bn_x_preferred":[
        "\u09b0\u0982\u09aa\u09c1\u09b0"
    ],
    "name:ben_in_x_preferred":[
        "\u09b0\u0982\u09aa\u09c1\u09b0"
    ],
    "name:ben_x_preferred":[
        "\u09b0\u0982\u09aa\u09c1\u09b0"
    ],
    "name:ceb_x_preferred":[
        "Rangpur"
    ],
    "name:deu_x_preferred":[
        "Rangpur"
    ],
    "name:fra_x_preferred":[
        "Rangpur"
    ],
    "name:guj_x_preferred":[
        "\u0ab0\u0a82\u0a97\u0aaa\u0ac1\u0ab0"
    ],
    "name:hin_x_preferred":[
        "\u0930\u0902\u0917\u092a\u0941\u0930"
    ],
    "name:ind_x_preferred":[
        "Rangpur"
    ],
    "name:kan_x_preferred":[
        "\u0cb0\u0c82\u0c97\u0caa\u0cc1\u0cb0"
    ],
    "name:mal_x_preferred":[
        "\u0d30\u0d02\u0d17\u0d4d\u0d2a\u0d42\u0d7c"
    ],
    "name:mal_x_variant":[
        "\u0d30\u0d02\u0d17\u0d4d\u200d\u0d2a\u0d42\u0d7c \u0d2a\u0d1f\u0d4d\u0d1f\u0d23\u0d02"
    ],
    "name:mar_x_preferred":[
        "\u0930\u0902\u0917\u092a\u0942\u0930"
    ],
    "name:nld_x_preferred":[
        "Rangpur"
    ],
    "name:pan_x_preferred":[
        "\u0a30\u0a70\u0a17\u0a2a\u0a41\u0a30"
    ],
    "name:rus_x_preferred":[
        "\u0420\u0430\u043d\u0433\u043f\u0443\u0440"
    ],
    "name:swe_x_preferred":[
        "Rangpur"
    ],
    "name:tam_x_preferred":[
        "\u0bb0\u0b99\u0bcd\u0baa\u0bc2\u0bb0\u0bcd"
    ],
    "name:tel_x_preferred":[
        "\u0c30\u0c02\u0c17\u0c4d"
    ],
    "name:ukr_x_preferred":[
        "\u0420\u0430\u043d\u0433\u043f\u0443\u0440"
    ],
    "name:urd_x_preferred":[
        "\u0631\u0646\u06af \u067e\u0648\u0631"
    ],
    "wof:name":"Rangpur",
    "wof:placetype":"locality"
},
  "geometry": {"coordinates":[85.34536999999997,24.97167],"type":"Point"}
}