{
  "type": "Feature",
  "properties": {
    "iso:country":"IN",
    "ks:ks_name":"Karapatwadi",
    "ks:ks_pop":275,
    "ks:ks_type":"HABITATION",
    "name:eng_x_preferred":[
        "Karapatwadi"
    ],
    "wof:name":"Karapatwadi",
    "wof:placetype":"locality",
    "wof:population":275
},
  "geometry": {"coordinates":[73.56381500000001,19.419572],"type":"Point"}
}