{
  "type": "Feature",
  "properties": {
    "gn:admin1_code":"24",
    "gn:admin2_code":"125.0",
    "gn:asciiname":"Rola",
    "gn:country_code":"IN",
    "gn:dem":237,
    "gn:feature_class":"P",
    "gn:feature_code":"PPL",
    "gn:name":"Rola",
    "gn:population":0,
    "gn:timezone":"Asia/Kolkata",
    "iso:country":"IN",
    "ks:ks_name":"Rola",
    "ks:ks_type":"VILLAGE",
    "name:deu_x_preferred":[
        "Rola"
    ],
    "name:eng_x_preferred":[
        "Rola"
    ],
    "name:ita_x_preferred":[
        "Rola"
    ],
    "name:pol_x_preferred":[
        "Rola"
    ],
    "name:por_x_preferred":[
        "Rola"
    ],
    "name:slk_x_preferred":[
        "Rola"
    ],
    "name:srp_x_preferred":[
        "\u0420\u043e\u043b\u0430"
    ],
    "name:ukr_x_preferred":[
        "\u0420\u043e\u043b\u0430"
    ],
    "wof:name":"Rola",
    "wof:placetype":"locality"
},
  "geometry": {"coordinates":[74.20088800000001,23.21436],"type":"Point"}
}