{
  "type": "Feature",
  "properties": {
    "iso:country":"IN",
    "ks:ks_name":"Sukhpura",
    "ks:ks_type":"VILLAGE",
    "ks:ks_uagg_main":0,
    "name:eng_x_preferred":[
        "Sukhpura"
    ],
    "wof:name":"Sukhpura",
    "wof:placetype":"neighbourhood"
},
  "geometry": {"coordinates":[75.82497499999999,26.783682],"type":"Point"}
}