{
  "type": "Feature",
  "properties": {
    "gn:admin1_code":"39.0",
    "gn:admin2_code":"68.0",
    "gn:asciiname":"Mundakhera Khurd",
    "gn:country_code":"IN",
    "gn:dem":233,
    "gn:feature_class":"P",
    "gn:feature_code":"PPL",
    "gn:name":"Mund\u0101khera Khurd",
    "gn:population":0,
    "gn:timezone":"Asia/Kolkata",
    "iso:country":"IN",
    "ks:ks_alt_nam":"Mund\u0101khera Khurd",
    "ks:ks_name":"Mundakhera Khurd",
    "ks:ks_pop":380,
    "ks:ks_type":"VILLAGE",
    "ks:ks_uagg_main":0,
    "name:eng_x_preferred":[
        "Mundakhera Khurd"
    ],
    "name:eng_x_variant":[
        "Mund\u0101khera Khurd"
    ],
    "wof:name":"Mundakhera Khurd",
    "wof:placetype":"neighbourhood",
    "wof:population":380
},
  "geometry": {"coordinates":[78.042039,29.705292],"type":"Point"}
}