{
  "type": "Feature",
  "properties": {
    "gn:admin1_code":"12.0",
    "gn:admin2_code":"6.0",
    "gn:asciiname":"Patiari",
    "gn:country_code":"IN",
    "gn:dem":1506,
    "gn:feature_class":"P",
    "gn:feature_code":"PPL",
    "gn:name":"Pati\u0101ri",
    "gn:population":0,
    "gn:timezone":"Asia/Kolkata",
    "iso:country":"IN",
    "wof:name":"Patiari",
    "wof:placetype":"locality"
},
  "geometry": {"coordinates":[74.39523,33.45146],"type":"Point"}
}