{
  "type": "Feature",
  "properties": {
    "iso:country":"IN",
    "ks:ks_alt_nam":"Kanak\u0101pur",
    "ks:ks_name":"Kanakapur",
    "ks:ks_type":"VILLAGE",
    "name:eng_x_preferred":[
        "Kanakapur"
    ],
    "name:eng_x_variant":[
        "Kanak\u0101pur"
    ],
    "wof:name":"Kanakapur",
    "wof:placetype":"locality"
},
  "geometry": {"coordinates":[75.4729,15.087918],"type":"Point"}
}