{
  "type": "Feature",
  "properties": {
    "iso:country":"IN",
    "ks:ks_alt_nam":"Bhawai khurd",
    "ks:ks_name":"Bhawai Khurd",
    "ks:ks_pop":388,
    "ks:ks_type":"HABITATION",
    "name:eng_x_preferred":[
        "Bhawai Khurd"
    ],
    "wof:name":"Bhawai Khurd",
    "wof:placetype":"locality",
    "wof:population":388
},
  "geometry": {"coordinates":[78.510255,22.140717],"type":"Point"}
}