{
  "type": "Feature",
  "properties": {
    "iso:country":"IN",
    "ks:ks_name":"Lalpura",
    "ks:ks_pop":511,
    "ks:ks_type":"VILLAGE",
    "name:eng_x_preferred":[
        "Lalpura"
    ],
    "wof:name":"Lalpura",
    "wof:placetype":"locality",
    "wof:population":511
},
  "geometry": {"coordinates":[74.776445,23.561305],"type":"Point"}
}