{
  "type": "Feature",
  "properties": {
    "iso:country":"IN",
    "ks:ks_alt_nam":"SHIBA BRATA PARA",
    "ks:ks_name":"Shiba Brata Para",
    "ks:ks_pop":140,
    "ks:ks_type":"HABITATION",
    "ks:ks_uagg_main":0,
    "name:eng_x_preferred":[
        "Shiba Brata Para"
    ],
    "wof:name":"Shiba Brata Para",
    "wof:placetype":"locality",
    "wof:population":140
},
  "geometry": {"coordinates":[91.263921,23.757618],"type":"Point"}
}