{
  "type": "Feature",
  "properties": {
    "gn:admin1_code":"36",
    "gn:admin2_code":"197.0",
    "gn:asciiname":"Hardasipur",
    "gn:country_code":"IN",
    "gn:dem":81,
    "gn:feature_class":"P",
    "gn:feature_code":"PPL",
    "gn:name":"Hard\u0101s\u012bpur",
    "gn:population":0,
    "gn:timezone":"Asia/Kolkata",
    "iso:country":"IN",
    "wof:name":"Hardasipur",
    "wof:placetype":"locality"
},
  "geometry": {"coordinates":[83.03596999999998,25.53078],"type":"Point"}
}