{
  "type": "Feature",
  "properties": {
    "iso:country":"IN",
    "ks:ks_name":"Hatigarh",
    "ks:ks_pop":174,
    "ks:ks_type":"HABITATION",
    "name:eng_x_preferred":[
        "Hatigarh"
    ],
    "wof:name":"Hatigarh",
    "wof:placetype":"locality",
    "wof:population":174
},
  "geometry": {"coordinates":[92.01522300000001,26.208216],"type":"Point"}
}