{
  "type": "Feature",
  "properties": {
    "gn:admin1_code":"39",
    "gn:admin2_code":"61.0",
    "gn:asciiname":"Chaur ka Danda",
    "gn:country_code":"IN",
    "gn:dem":1292,
    "gn:feature_class":"P",
    "gn:feature_code":"PPL",
    "gn:name":"Chaur ka D\u0101nda",
    "gn:population":0,
    "gn:timezone":"Asia/Kolkata",
    "iso:country":"IN",
    "wof:name":"Chaur ka Danda",
    "wof:placetype":"locality"
},
  "geometry": {"coordinates":[78.86745999999999,29.73592],"type":"Point"}
}