{
  "type": "Feature",
  "properties": {
    "iso:country":"IN",
    "ks:ks_alt_nam":"khedado ki Dhani",
    "ks:ks_name":"Khedado Ki Dhani",
    "ks:ks_pop":231,
    "ks:ks_type":"HABITATION",
    "name:eng_x_preferred":[
        "Khedado Ki Dhani"
    ],
    "wof:name":"Khedado Ki Dhani",
    "wof:placetype":"locality",
    "wof:population":231
},
  "geometry": {"coordinates":[75.376481,27.841305],"type":"Point"}
}