{
  "type": "Feature",
  "properties": {
    "iso:country":"IN",
    "ks:ks_alt_nam":"Kilputhur village",
    "ks:ks_name":"Kilputhur Village",
    "ks:ks_pop":128,
    "ks:ks_type":"HABITATION",
    "name:eng_x_preferred":[
        "Kilputhur Village"
    ],
    "wof:name":"Kilputhur Village",
    "wof:placetype":"locality",
    "wof:population":128
},
  "geometry": {"coordinates":[79.788242,12.749683],"type":"Point"}
}