{
  "type": "Feature",
  "properties": {
    "iso:country":"IN",
    "ks:ks_name":"Yewalewasti",
    "ks:ks_pop":158,
    "ks:ks_type":"HABITATION",
    "name:eng_x_preferred":[
        "Yewalewasti"
    ],
    "wof:name":"Yewalewasti",
    "wof:placetype":"locality",
    "wof:population":158
},
  "geometry": {"coordinates":[74.156722,19.018342],"type":"Point"}
}