{
  "type": "Feature",
  "properties": {
    "iso:country":"IN",
    "ks:ks_name":"Math Tagarpur",
    "ks:ks_pop":0,
    "ks:ks_type":"VILLAGE",
    "name:eng_x_preferred":[
        "Math Tagarpur"
    ],
    "wof:name":"Math Tagarpur",
    "wof:placetype":"locality",
    "wof:population":0
},
  "geometry": {"coordinates":[88.136354,24.268718],"type":"Point"}
}