{
  "type": "Feature",
  "properties": {
    "iso:country":"IN",
    "ks:ks_name":"Gangani",
    "ks:ks_pop":2164,
    "ks:ks_type":"VILLAGE",
    "name:eng_x_preferred":[
        "Gangani"
    ],
    "wof:name":"Gangani",
    "wof:placetype":"locality",
    "wof:population":2164
},
  "geometry": {"coordinates":[87.341735,22.85726],"type":"Point"}
}