{
  "type": "Feature",
  "properties": {
    "iso:country":"IN",
    "ks:ks_name":"Satkhand",
    "ks:ks_pop":67,
    "ks:ks_type":"HABITATION",
    "name:eng_x_preferred":[
        "Satkhand"
    ],
    "wof:name":"Satkhand",
    "wof:placetype":"locality",
    "wof:population":67
},
  "geometry": {"coordinates":[74.61628,15.155968],"type":"Point"}
}