{
  "type": "Feature",
  "properties": {
    "gn:admin1_code":"12",
    "gn:admin2_code":"17.0",
    "gn:asciiname":"Naugam",
    "gn:country_code":"IN",
    "gn:dem":2039,
    "gn:feature_class":"P",
    "gn:feature_code":"PPL",
    "gn:name":"Naugam",
    "gn:population":0,
    "gn:timezone":"Asia/Kolkata",
    "iso:country":"IN",
    "wof:name":"Naugam",
    "wof:placetype":"locality"
},
  "geometry": {"coordinates":[75.16994,33.50176],"type":"Point"}
}