{
  "type": "Feature",
  "properties": {
    "iso:country":"IN",
    "ks:ks_name":"Nadode",
    "ks:ks_pop":618,
    "ks:ks_type":"VILLAGE",
    "name:eng_x_preferred":[
        "Nadode"
    ],
    "wof:name":"Nadode",
    "wof:placetype":"locality",
    "wof:population":618
},
  "geometry": {"coordinates":[73.261847,18.848416],"type":"Point"}
}