{
  "type": "Feature",
  "properties": {
    "iso:country":"IN",
    "ks:ks_alt_nam":"P\u0101lkia",
    "ks:ks_name":"Palkia",
    "ks:ks_pop":782,
    "ks:ks_type":"VILLAGE",
    "name:eng_x_preferred":[
        "Palkia"
    ],
    "name:eng_x_variant":[
        "P\u0101lkia"
    ],
    "wof:name":"Palkia",
    "wof:placetype":"locality",
    "wof:population":782
},
  "geometry": {"coordinates":[86.381238,24.065954],"type":"Point"}
}