{
  "type": "Feature",
  "properties": {
    "iso:country":"IN",
    "ks:ks_name":"Neri Digar",
    "ks:ks_pop":3715,
    "ks:ks_type":"VILLAGE",
    "ks:ks_uagg_main":0,
    "name:eng_x_preferred":[
        "Neri Digar"
    ],
    "wof:name":"Neri Digar",
    "wof:placetype":"neighbourhood",
    "wof:population":3715
},
  "geometry": {"coordinates":[75.652416,20.848701],"type":"Point"}
}