{
  "type": "Feature",
  "properties": {
    "iso:country":"IN",
    "ks:ks_name":"Kullathanil",
    "ks:ks_pop":554,
    "ks:ks_type":"HABITATION",
    "name:eng_x_preferred":[
        "Kullathanil"
    ],
    "wof:name":"Kullathanil",
    "wof:placetype":"locality",
    "wof:population":554
},
  "geometry": {"coordinates":[76.78697200000001,9.349782],"type":"Point"}
}