{
  "type": "Feature",
  "properties": {
    "iso:country":"IN",
    "ks:ks_name":"Kombadpada",
    "ks:ks_pop":63,
    "ks:ks_type":"HABITATION",
    "name:eng_x_preferred":[
        "Kombadpada"
    ],
    "wof:name":"Kombadpada",
    "wof:placetype":"locality",
    "wof:population":63
},
  "geometry": {"coordinates":[73.759722,19.353889],"type":"Point"}
}