{
  "type": "Feature",
  "properties": {
    "iso:country":"IN",
    "ks:ks_name":"Parsa Bujurg Khurd",
    "ks:ks_pop":1410,
    "ks:ks_type":"HABITATION",
    "name:eng_x_preferred":[
        "Parsa Bujurg Khurd"
    ],
    "wof:name":"Parsa Bujurg Khurd",
    "wof:placetype":"locality",
    "wof:population":1410
},
  "geometry": {"coordinates":[82.684147,27.370862],"type":"Point"}
}