{
  "type": "Feature",
  "properties": {
    "iso:country":"IN",
    "ks:ks_name":"Daser",
    "ks:ks_pop":337,
    "ks:ks_type":"VILLAGE",
    "name:eng_x_preferred":[
        "Daser"
    ],
    "wof:name":"Daser",
    "wof:placetype":"locality",
    "wof:population":337
},
  "geometry": {"coordinates":[82.437685,23.792395],"type":"Point"}
}