{
  "type": "Feature",
  "properties": {
    "iso:country":"IN",
    "ks:ks_name":"Birar",
    "ks:ks_pop":7,
    "ks:ks_type":"VILLAGE",
    "ks:ks_uagg_main":0,
    "name:eng_x_preferred":[
        "Birar"
    ],
    "wof:name":"Birar",
    "wof:placetype":"neighbourhood",
    "wof:population":7
},
  "geometry": {"coordinates":[85.487829,24.403282],"type":"Point"}
}