{
  "type": "Feature",
  "properties": {
    "iso:country":"IN",
    "ks:ks_name":"Jashpara",
    "ks:ks_pop":896,
    "ks:ks_type":"VILLAGE",
    "name:eng_x_preferred":[
        "Jashpara"
    ],
    "wof:name":"Jashpara",
    "wof:placetype":"locality",
    "wof:population":896
},
  "geometry": {"coordinates":[86.94476400000001,22.760819],"type":"Point"}
}