{
  "type": "Feature",
  "properties": {
    "gn:admin1_code":"36",
    "gn:admin2_code":"199.0",
    "gn:asciiname":"Kanohi Raja",
    "gn:country_code":"IN",
    "gn:dem":159,
    "gn:feature_class":"P",
    "gn:feature_code":"PPL",
    "gn:name":"Kanohi R\u0101ja",
    "gn:population":0,
    "gn:timezone":"Asia/Kolkata",
    "iso:country":"IN",
    "ks:ks_alt_nam":"Kanohi R\u0101ja",
    "ks:ks_name":"Kanohi Raja",
    "ks:ks_type":"VILLAGE",
    "ks:ks_uagg_main":0,
    "name:eng_x_preferred":[
        "Kanohi Raja"
    ],
    "name:eng_x_variant":[
        "Kanohi R\u0101ja"
    ],
    "wof:name":"Kanohi Raja",
    "wof:placetype":"neighbourhood"
},
  "geometry": {"coordinates":[82.320159,25.036851],"type":"Point"}
}