{
  "type": "Feature",
  "properties": {
    "gn:admin1_code":"29",
    "gn:admin2_code":"241.0",
    "gn:asciiname":"Tumlong",
    "gn:country_code":"IN",
    "gn:dem":1780,
    "gn:feature_class":"P",
    "gn:feature_code":"PPL",
    "gn:name":"Tumlong",
    "gn:population":0,
    "gn:timezone":"Asia/Kolkata",
    "iso:country":"IN",
    "wof:name":"Tumlong",
    "wof:placetype":"locality"
},
  "geometry": {"coordinates":[88.58333,27.41667],"type":"Point"}
}