{
  "type": "Feature",
  "properties": {
    "gn:admin1_code":"29",
    "gn:admin2_code":"241.0",
    "gn:asciiname":"Tumlong",
    "gn:country_code":"IN",
    "gn:dem":1780,
    "gn:feature_class":"P",
    "gn:feature_code":"PPL",
    "gn:name":"Tumlong",
    "gn:population":0,
    "gn:timezone":"Asia/Kolkata",
    "iso:country":"IN",
    "name:ara_x_preferred":[
        "\u062a\u0645\u0644\u0648\u0646\u0643"
    ],
    "name:hun_x_preferred":[
        "Tumlong"
    ],
    "name:ind_x_preferred":[
        "Tumlong"
    ],
    "name:jpn_x_preferred":[
        "\u30c8\u30a5\u30e0\u30ed\u30f3"
    ],
    "name:spa_x_preferred":[
        "Tumlong"
    ],
    "name:ukr_x_preferred":[
        "\u0422\u0443\u043c\u043b\u043e\u043d\u0491"
    ],
    "wof:name":"Tumlong",
    "wof:placetype":"locality"
},
  "geometry": {"coordinates":[88.58333,27.41667],"type":"Point"}
}