{
  "type": "Feature",
  "properties": {
    "iso:country":"IN",
    "ks:ks_name":"Empalpatty",
    "ks:ks_pop":130,
    "ks:ks_type":"HABITATION",
    "name:eng_x_preferred":[
        "Empalpatty"
    ],
    "wof:name":"Empalpatty",
    "wof:placetype":"locality",
    "wof:population":130
},
  "geometry": {"coordinates":[78.56913299999999,10.340799],"type":"Point"}
}