{
  "type": "Feature",
  "properties": {
    "gn:admin1_code":"12.0",
    "gn:admin2_code":"7.0",
    "gn:asciiname":"Thal",
    "gn:country_code":"IN",
    "gn:dem":450,
    "gn:feature_class":"P",
    "gn:feature_code":"PPL",
    "gn:name":"Thal",
    "gn:population":0,
    "gn:timezone":"Asia/Kolkata",
    "iso:country":"IN",
    "name:als_x_preferred":[
        "Thal"
    ],
    "name:ceb_x_preferred":[
        "Thal"
    ],
    "name:deu_x_preferred":[
        "Thal"
    ],
    "name:epo_x_preferred":[
        "Thal"
    ],
    "name:fra_x_preferred":[
        "Thal"
    ],
    "name:ita_x_preferred":[
        "Thal"
    ],
    "name:nld_x_preferred":[
        "Thal"
    ],
    "name:pol_x_preferred":[
        "Thal"
    ],
    "name:spa_x_preferred":[
        "Thal"
    ],
    "name:swe_x_preferred":[
        "Thal"
    ],
    "name:vol_x_preferred":[
        "Thal"
    ],
    "wof:name":"Thal",
    "wof:placetype":"locality"
},
  "geometry": {"coordinates":[75.35314,32.48016],"type":"Point"}
}