{
  "type": "Feature",
  "properties": {
    "iso:country":"IN",
    "ks:ks_alt_nam":"CHAHALAWA GHAT",
    "ks:ks_name":"Chahalawa Ghat",
    "ks:ks_pop":55,
    "ks:ks_type":"HABITATION",
    "name:eng_x_preferred":[
        "Chahalawa Ghat"
    ],
    "wof:name":"Chahalawa Ghat",
    "wof:placetype":"locality",
    "wof:population":55
},
  "geometry": {"coordinates":[81.70625699999999,27.28798],"type":"Point"}
}