{
  "type": "Feature",
  "properties": {
    "iso:country":"IN",
    "ks:ks_alt_nam":"BASASAI",
    "ks:ks_name":"Basasai",
    "ks:ks_pop":96,
    "ks:ks_type":"HABITATION",
    "name:eng_x_preferred":[
        "Basasai"
    ],
    "wof:name":"Basasai",
    "wof:placetype":"locality",
    "wof:population":96
},
  "geometry": {"coordinates":[85.96572,22.1348],"type":"Point"}
}