{
  "type": "Feature",
  "properties": {
    "iso:country":"IN",
    "ks:ks_name":"Karimachak",
    "ks:ks_pop":0,
    "ks:ks_type":"VILLAGE",
    "name:eng_x_preferred":[
        "Karimachak"
    ],
    "wof:name":"Karimachak",
    "wof:placetype":"locality",
    "wof:population":0
},
  "geometry": {"coordinates":[87.006094,25.341539],"type":"Point"}
}