{
  "type": "Feature",
  "properties": {
    "gn:admin1_code":"30.0",
    "gn:admin2_code":"245",
    "gn:asciiname":"Kangkar",
    "gn:country_code":"IN",
    "gn:dem":2427,
    "gn:feature_class":"P",
    "gn:feature_code":"PPL",
    "gn:name":"Kangkar",
    "gn:population":0,
    "gn:timezone":"Asia/Kolkata",
    "iso:country":"IN",
    "wof:name":"Kangkar",
    "wof:placetype":"locality"
},
  "geometry": {"coordinates":[91.90000000000001,27.53333],"type":"Point"}
}