{
  "type": "Feature",
  "properties": {
    "iso:country":"IN",
    "name:eng_x_preferred":[
        "MIDC"
    ],
    "qs:gn_local":0,
    "qs:local_max":353,
    "qs:local_sum":1613,
    "qs:localhoods":12,
    "qs:name":"MIDC",
    "qs:name_adm0":"India",
    "qs:name_adm1":"Maharashtra",
    "qs:name_adm2":"Thane",
    "qs:name_local":"Navi Mumbai",
    "qs:photo_max":44,
    "qs:photo_sum":65,
    "qs:placetype":"Suburb",
    "qs:quad_count":11,
    "qs:woe_adm0":23424848,
    "qs:woe_adm1":2345750,
    "qs:woe_adm2":12586551,
    "qs:woe_lau":0,
    "qs:woe_local":28999056,
    "qs:woe_ver":"7.10.0",
    "wof:lang":[
        "eng"
    ],
    "wof:name":"MIDC",
    "wof:placetype":"neighbourhood"
},
  "geometry": {"coordinates":[73.02119999999999,19.076994],"type":"Point"}
}