{
  "type": "Feature",
  "properties": {
    "iso:country":"IN",
    "ks:ks_name":"Bishunpur",
    "ks:ks_pop":93,
    "ks:ks_type":"VILLAGE",
    "name:eng_x_preferred":[
        "Bishunpur"
    ],
    "wof:name":"Bishunpur",
    "wof:placetype":"locality",
    "wof:population":93
},
  "geometry": {"coordinates":[87.40204,24.861095],"type":"Point"}
}