{
  "type": "Feature",
  "properties": {
    "iso:country":"IN",
    "ks:ks_name":"Mikirgaon",
    "ks:ks_pop":513,
    "ks:ks_type":"VILLAGE",
    "ks:ks_uagg_main":0,
    "name:eng_x_preferred":[
        "Mikirgaon"
    ],
    "wof:name":"Mikirgaon",
    "wof:placetype":"neighbourhood",
    "wof:population":513
},
  "geometry": {"coordinates":[92.749415,26.158964],"type":"Point"}
}