{
  "type": "Feature",
  "properties": {
    "iso:country":"IN",
    "ks:ks_name":"Kiruhale Devimane",
    "ks:ks_pop":232,
    "ks:ks_type":"HABITATION",
    "name:eng_x_preferred":[
        "Kiruhale Devimane"
    ],
    "wof:name":"Kiruhale Devimane",
    "wof:placetype":"locality",
    "wof:population":232
},
  "geometry": {"coordinates":[74.57860599999999,13.933581],"type":"Point"}
}