{
  "type": "Feature",
  "properties": {
    "iso:country":"IN",
    "ks:ks_name":"Nagla Jatav",
    "ks:ks_pop":350,
    "ks:ks_type":"HABITATION",
    "name:eng_x_preferred":[
        "Nagla Jatav"
    ],
    "wof:name":"Nagla Jatav",
    "wof:placetype":"locality",
    "wof:population":350
},
  "geometry": {"coordinates":[78.091092,27.176927],"type":"Point"}
}