{
  "type": "Feature",
  "properties": {
    "iso:country":"IN",
    "ks:ks_name":"Ugawatwadi",
    "ks:ks_pop":489,
    "ks:ks_type":"HABITATION",
    "name:eng_x_preferred":[
        "Ugawatwadi"
    ],
    "wof:name":"Ugawatwadi",
    "wof:placetype":"locality",
    "wof:population":489
},
  "geometry": {"coordinates":[73.558333,16.809444],"type":"Point"}
}