{
  "type": "Feature",
  "properties": {
    "iso:country":"IN",
    "ks:ks_alt_nam":"khodademal",
    "ks:ks_name":"Khodademal",
    "ks:ks_pop":598,
    "ks:ks_type":"HABITATION",
    "name:eng_x_preferred":[
        "Khodademal"
    ],
    "wof:name":"Khodademal",
    "wof:placetype":"locality",
    "wof:population":598
},
  "geometry": {"coordinates":[74.44031200000001,19.011491],"type":"Point"}
}