{
  "type": "Feature",
  "properties": {
    "iso:country":"IN",
    "ks:ks_alt_nam":"GADRIYAN KA PURWA",
    "ks:ks_name":"Gadriyan Ka Purwa",
    "ks:ks_pop":200,
    "ks:ks_type":"HABITATION",
    "name:eng_x_preferred":[
        "Gadriyan Ka Purwa"
    ],
    "wof:name":"Gadriyan Ka Purwa",
    "wof:placetype":"locality",
    "wof:population":200
},
  "geometry": {"coordinates":[81.428527,26.233897],"type":"Point"}
}