{
  "type": "Feature",
  "properties": {
    "gn:admin1_code":"19.0",
    "gn:admin2_code":"563.0",
    "gn:asciiname":"Kelgin Sasi",
    "gn:country_code":"IN",
    "gn:dem":530,
    "gn:feature_class":"P",
    "gn:feature_code":"PPL",
    "gn:name":"Kelgin Sasi",
    "gn:population":0,
    "gn:timezone":"Asia/Kolkata",
    "iso:country":"IN",
    "ks:ks_name":"Kelaginasasi",
    "ks:ks_pop":65,
    "ks:ks_type":"HABITATION",
    "name:eng_x_preferred":[
        "Kelaginasasi"
    ],
    "name:eng_x_variant":[
        "Kelgin Sasi"
    ],
    "wof:name":"Kelaginasasi",
    "wof:placetype":"locality",
    "wof:population":65
},
  "geometry": {"coordinates":[74.725638,14.321268],"type":"Point"}
}