{
  "type": "Feature",
  "properties": {
    "gn:admin1_code":"39.0",
    "gn:admin2_code":"61.0",
    "gn:asciiname":"Halon",
    "gn:country_code":"IN",
    "gn:dem":1678,
    "gn:feature_class":"P",
    "gn:feature_code":"PPL",
    "gn:name":"H\u0101lon",
    "gn:population":0,
    "gn:timezone":"Asia/Kolkata",
    "iso:country":"IN",
    "name:deu_x_preferred":[
        "Halon"
    ],
    "name:rus_x_preferred":[
        "\u0425\u043b\u0430\u0434\u043e\u043d"
    ],
    "name:swe_x_preferred":[
        "Halon"
    ],
    "wof:name":"Halon",
    "wof:placetype":"locality"
},
  "geometry": {"coordinates":[79.01246,29.93138],"type":"Point"}
}