{
  "type": "Feature",
  "properties": {
    "iso:country":"IN",
    "qs:name":"New Rajendra Nagar",
    "qs:name_adm0":"India",
    "qs:name_adm1":"Delhi",
    "qs:photos":6,
    "qs:photos_1k":1,
    "qs:photos_9k":1,
    "qs:photos_9r":1,
    "qs:photos_all":6,
    "qs:photos_sr":1,
    "qs:placetype":"Suburb",
    "qs:pop_sr":"0",
    "wof:name":"New Rajendra Nagar",
    "wof:placetype":"neighbourhood"
},
  "geometry": {"coordinates":[77.17715750000001,28.632579],"type":"Point"}
}