{
  "type": "Feature",
  "properties": {
    "gn:admin1_code":"35",
    "gn:admin2_code":"443.0",
    "gn:asciiname":"Aligarh",
    "gn:country_code":"IN",
    "gn:dem":515,
    "gn:feature_class":"P",
    "gn:feature_code":"PPL",
    "gn:name":"Al\u012bgarh",
    "gn:population":0,
    "gn:timezone":"Asia/Kolkata",
    "iso:country":"IN",
    "name:und_x_variant":[
        "Al\u012bgarh",
        "Al\u012bnagar"
    ],
    "wof:name":"Aligarh",
    "wof:placetype":"locality"
},
  "geometry": {"coordinates":[77.53158000000001,24.09158],"type":"Point"}
}