{
  "type": "Feature",
  "properties": {
    "gn:admin1_code":"29.0",
    "gn:admin2_code":"244.0",
    "gn:asciiname":"Burung",
    "gn:country_code":"IN",
    "gn:dem":553,
    "gn:feature_class":"P",
    "gn:feature_code":"PPL",
    "gn:name":"Burung",
    "gn:population":0,
    "gn:timezone":"Asia/Kolkata",
    "iso:country":"IN",
    "wof:name":"Burung",
    "wof:placetype":"locality"
},
  "geometry": {"coordinates":[88.52424999999999,27.24699],"type":"Point"}
}