{
  "type": "Feature",
  "properties": {
    "iso:country":"IN",
    "ks:ks_name":"Dwarikapur Jatt",
    "ks:ks_pop":1248,
    "ks:ks_type":"HABITATION",
    "ks:ks_uagg_main":0,
    "name:eng_x_preferred":[
        "Dwarikapur Jatt"
    ],
    "wof:name":"Dwarikapur Jatt",
    "wof:placetype":"neighbourhood",
    "wof:population":1248
},
  "geometry": {"coordinates":[80.342718,26.118564],"type":"Point"}
}