{
  "type": "Feature",
  "properties": {
    "gn:admin1_code":"38",
    "gn:admin2_code":"346.0",
    "gn:asciiname":"Jirhula",
    "gn:country_code":"IN",
    "gn:dem":234,
    "gn:feature_class":"P",
    "gn:feature_code":"PPL",
    "gn:name":"Jirhula",
    "gn:population":0,
    "gn:timezone":"Asia/Kolkata",
    "iso:country":"IN",
    "ks:ks_alt_nam":"JIRHULLA",
    "ks:ks_name":"Jirhulla",
    "ks:ks_pop":315,
    "ks:ks_type":"HABITATION",
    "name:eng_x_preferred":[
        "Jirhulla"
    ],
    "name:eng_x_variant":[
        "Jirhula"
    ],
    "wof:name":"Jirhulla",
    "wof:placetype":"locality",
    "wof:population":315
},
  "geometry": {"coordinates":[83.537358,24.383929],"type":"Point"}
}