{
  "type": "Feature",
  "properties": {
    "gn:admin1_code":"24.0",
    "gn:admin2_code":"130.0",
    "gn:asciiname":"Dhani Rewari ki Wali",
    "gn:country_code":"IN",
    "gn:dem":259,
    "gn:feature_class":"P",
    "gn:feature_code":"PPL",
    "gn:name":"Dh\u0101ni Rew\u0101ri ki W\u0101li",
    "gn:population":0,
    "gn:timezone":"Asia/Kolkata",
    "iso:country":"IN",
    "wof:name":"Dhani Rewari ki Wali",
    "wof:placetype":"neighbourhood"
},
  "geometry": {"coordinates":[73.83519,24.04601],"type":"Point"}
}