{
  "type": "Feature",
  "properties": {
    "gn:admin1_code":"39",
    "gn:admin2_code":"60.0",
    "gn:asciiname":"Badiar Khera",
    "gn:country_code":"IN",
    "gn:dem":1136,
    "gn:feature_class":"P",
    "gn:feature_code":"PPL",
    "gn:name":"Badi\u0101r Khera",
    "gn:population":0,
    "gn:timezone":"Asia/Kolkata",
    "iso:country":"IN",
    "wof:name":"Badiar Khera",
    "wof:placetype":"locality"
},
  "geometry": {"coordinates":[77.85755999999998,30.86939000000001],"type":"Point"}
}