{
  "type": "Feature",
  "properties": {
    "gn:admin1_code":"19.0",
    "gn:admin2_code":"560.0",
    "gn:asciiname":"Chenduru",
    "gn:country_code":"IN",
    "gn:dem":557,
    "gn:feature_class":"P",
    "gn:feature_code":"PPL",
    "gn:name":"Chend\u016bru",
    "gn:population":0,
    "gn:timezone":"Asia/Kolkata",
    "iso:country":"IN",
    "wof:name":"Chenduru",
    "wof:placetype":"neighbourhood"
},
  "geometry": {"coordinates":[76.07192999999999,15.45401],"type":"Point"}
}