{
  "type": "Feature",
  "properties": {
    "gn:admin1_code":"38.0",
    "gn:admin2_code":"360.0",
    "gn:asciiname":"Nawadih Kalan",
    "gn:country_code":"IN",
    "gn:dem":438,
    "gn:feature_class":"P",
    "gn:feature_code":"PPL",
    "gn:name":"Naw\u0101dih Kal\u0101n",
    "gn:population":0,
    "gn:timezone":"Asia/Kolkata",
    "iso:country":"IN",
    "ks:ks_alt_nam":"Naw\u0101dih Kal\u0101n",
    "ks:ks_name":"Nawadih Kalan",
    "ks:ks_pop":1571,
    "ks:ks_type":"VILLAGE",
    "ks:ks_uagg_main":0,
    "name:eng_x_preferred":[
        "Nawadih Kalan"
    ],
    "name:eng_x_variant":[
        "Naw\u0101dih Kal\u0101n"
    ],
    "wof:name":"Nawadih Kalan",
    "wof:placetype":"neighbourhood",
    "wof:population":1571
},
  "geometry": {"coordinates":[85.31365700000001,24.179382],"type":"Point"}
}