{
  "type": "Feature",
  "properties": {
    "iso:country":"IN",
    "ks:ks_name":"Mitgai Parasatola",
    "ks:ks_pop":1440,
    "ks:ks_type":"HABITATION",
    "name:eng_x_preferred":[
        "Mitgai Parasatola"
    ],
    "wof:name":"Mitgai Parasatola",
    "wof:placetype":"locality",
    "wof:population":1440
},
  "geometry": {"coordinates":[83.625488,23.775105],"type":"Point"}
}