{
  "type": "Feature",
  "properties": {
    "iso:country":"IN",
    "ks:ks_alt_nam":"East Girijana Colony of Panchedu",
    "ks:ks_name":"East Girijana Colony Of Panchedu",
    "ks:ks_pop":345,
    "ks:ks_type":"HABITATION",
    "ks:ks_uagg_main":0,
    "name:eng_x_preferred":[
        "East Girijana Colony Of Panchedu"
    ],
    "wof:name":"East Girijana Colony Of Panchedu",
    "wof:placetype":"neighbourhood",
    "wof:population":345
},
  "geometry": {"coordinates":[79.874258,14.516699],"type":"Point"}
}