{
  "type": "Feature",
  "properties": {
    "iso:country":"IN",
    "ks:ks_alt_nam":"BARSKAR WASTI",
    "ks:ks_name":"Barskar Wasti",
    "ks:ks_pop":51,
    "ks:ks_type":"HABITATION",
    "ks:ks_uagg_main":0,
    "name:eng_x_preferred":[
        "Barskar Wasti"
    ],
    "wof:name":"Barskar Wasti",
    "wof:placetype":"neighbourhood",
    "wof:population":51
},
  "geometry": {"coordinates":[74.813228,19.676305],"type":"Point"}
}