{
  "type": "Feature",
  "properties": {
    "gn:admin1_code":"2",
    "gn:admin2_code":"545.0",
    "gn:asciiname":"Allurukota",
    "gn:country_code":"IN",
    "gn:dem":632,
    "gn:feature_class":"P",
    "gn:feature_code":"PPL",
    "gn:name":"All\u016brukota",
    "gn:population":0,
    "gn:timezone":"Asia/Kolkata",
    "iso:country":"IN",
    "wof:name":"Allurukota",
    "wof:placetype":"locality"
},
  "geometry": {"coordinates":[81.9286,17.84677000000001],"type":"Point"}
}