{
  "type": "Feature",
  "properties": {
    "gn:admin1_code":"36.0",
    "gn:admin2_code":"184.0",
    "gn:asciiname":"Banrahwa",
    "gn:country_code":"IN",
    "gn:dem":90,
    "gn:feature_class":"P",
    "gn:feature_code":"PPL",
    "gn:name":"Banr\u0101hwa",
    "gn:population":0,
    "gn:timezone":"Asia/Kolkata",
    "iso:country":"IN",
    "ks:ks_name":"Banrahi",
    "ks:ks_pop":437,
    "ks:ks_type":"HABITATION",
    "name:eng_x_preferred":[
        "Banrahi"
    ],
    "name:eng_x_variant":[
        "Banrahwa"
    ],
    "wof:name":"Banrahi",
    "wof:placetype":"locality",
    "wof:population":437
},
  "geometry": {"coordinates":[82.908441,27.212547],"type":"Point"}
}