{
  "type": "Feature",
  "properties": {
    "iso:country":"IN",
    "ks:ks_name":"Gaya Tola",
    "ks:ks_pop":215,
    "ks:ks_type":"HABITATION",
    "ks:ks_uagg_main":0,
    "name:eng_x_preferred":[
        "Gaya Tola"
    ],
    "wof:name":"Gaya Tola",
    "wof:placetype":"neighbourhood",
    "wof:population":215
},
  "geometry": {"coordinates":[84.337374,26.666158],"type":"Point"}
}