{
  "type": "Feature",
  "properties": {
    "gn:admin1_code":"19.0",
    "gn:admin2_code":"577.0",
    "gn:asciiname":"Basvanhalli",
    "gn:country_code":"IN",
    "gn:dem":928,
    "gn:feature_class":"P",
    "gn:feature_code":"PPL",
    "gn:name":"Basvanhalli",
    "gn:population":0,
    "gn:timezone":"Asia/Kolkata",
    "iso:country":"IN",
    "wof:name":"Basvanhalli",
    "wof:placetype":"neighbourhood"
},
  "geometry": {"coordinates":[76.04705,12.41207],"type":"Point"}
}