{
  "type": "Feature",
  "properties": {
    "gn:admin1_code":"19.0",
    "gn:admin2_code":"583.0",
    "gn:asciiname":"Kumbarhoshalli",
    "gn:country_code":"IN",
    "gn:dem":878,
    "gn:feature_class":"P",
    "gn:feature_code":"PPL",
    "gn:name":"Kumbarhoshalli",
    "gn:population":0,
    "gn:timezone":"Asia/Kolkata",
    "iso:country":"IN",
    "wof:name":"Kumbarhoshalli",
    "wof:placetype":"neighbourhood"
},
  "geometry": {"coordinates":[77.52485,13.25707],"type":"Point"}
}