{
  "type": "Feature",
  "properties": {
    "gn:admin1_code":"19.0",
    "gn:admin2_code":"568.0",
    "gn:asciiname":"Mudi",
    "gn:country_code":"IN",
    "gn:dem":551,
    "gn:feature_class":"P",
    "gn:feature_code":"PPL",
    "gn:name":"M\u016bdi",
    "gn:population":0,
    "gn:timezone":"Asia/Kolkata",
    "iso:country":"IN",
    "ks:ks_name":"Modi",
    "ks:ks_pop":610,
    "ks:ks_type":"HABITATION",
    "name:bul_x_preferred":[
        "\u041c\u0443\u0434\u0438"
    ],
    "name:ces_x_preferred":[
        "Mudi"
    ],
    "name:deu_x_preferred":[
        "Mudi"
    ],
    "name:eng_x_preferred":[
        "Modi"
    ],
    "name:eng_x_variant":[
        "Mudi"
    ],
    "name:epo_x_preferred":[
        "Mudi-hundo"
    ],
    "name:est_x_preferred":[
        "Mudi"
    ],
    "name:fin_x_preferred":[
        "Mudi"
    ],
    "name:fra_x_preferred":[
        "Mudi"
    ],
    "name:heb_x_preferred":[
        "\u05de\u05d5\u05d3\u05d9"
    ],
    "name:hun_x_preferred":[
        "Mudi"
    ],
    "name:ita_x_preferred":[
        "Mudi"
    ],
    "name:jpn_x_preferred":[
        "\u30e0\u30fc\u30c7\u30a3"
    ],
    "name:kat_x_preferred":[
        "\u10db\u10e3\u10d3\u10d8"
    ],
    "name:mkd_x_preferred":[
        "\u041c\u0443\u0434\u0438"
    ],
    "name:msa_x_preferred":[
        "Mudi"
    ],
    "name:nld_x_preferred":[
        "Mudi"
    ],
    "name:nor_x_preferred":[
        "Mudi"
    ],
    "name:pnb_x_preferred":[
        "\u0645\u0648\u0688\u06cc"
    ],
    "name:pol_x_preferred":[
        "Mudi"
    ],
    "name:por_x_preferred":[
        "Mudi"
    ],
    "name:rus_x_preferred":[
        "\u041c\u0443\u0434\u0438"
    ],
    "name:slk_x_preferred":[
        "Mudi"
    ],
    "name:spa_x_preferred":[
        "Mudi"
    ],
    "name:srp_x_preferred":[
        "\u041c\u0443\u0434\u0438"
    ],
    "name:swe_x_preferred":[
        "Mudi"
    ],
    "wof:name":"Modi",
    "wof:placetype":"locality",
    "wof:population":610
},
  "geometry": {"coordinates":[75.19547799999999,14.620832],"type":"Point"}
}