{
  "type": "Feature",
  "properties": {
    "gn:admin1_code":"19.0",
    "gn:admin2_code":"574.0",
    "gn:asciiname":"Hasgavalli",
    "gn:country_code":"IN",
    "gn:dem":980,
    "gn:feature_class":"P",
    "gn:feature_code":"PPL",
    "gn:name":"Hasgavalli",
    "gn:population":0,
    "gn:timezone":"Asia/Kolkata",
    "iso:country":"IN",
    "wof:name":"Hasgavalli",
    "wof:placetype":"locality"
},
  "geometry": {"coordinates":[75.89558000000002,12.95421],"type":"Point"}
}