{
  "type": "Feature",
  "properties": {
    "gn:admin1_code":"19.0",
    "gn:admin2_code":"574.0",
    "gn:asciiname":"Hasgavalli",
    "gn:country_code":"IN",
    "gn:dem":980,
    "gn:feature_class":"P",
    "gn:feature_code":"PPL",
    "gn:name":"Hasgavalli",
    "gn:population":0,
    "gn:timezone":"Asia/Kolkata",
    "iso:country":"IN",
    "ks:ks_name":"Hasugavalli",
    "ks:ks_pop":1434,
    "ks:ks_type":"VILLAGE",
    "name:eng_x_preferred":[
        "Hasugavalli"
    ],
    "name:eng_x_variant":[
        "Hasgavalli"
    ],
    "wof:name":"Hasugavalli",
    "wof:placetype":"locality",
    "wof:population":1434
},
  "geometry": {"coordinates":[75.89680199999999,12.948852],"type":"Point"}
}