{
  "type": "Feature",
  "properties": {
    "gn:admin1_code":"23.0",
    "gn:admin2_code":"50.0",
    "gn:asciiname":"Dhok Mari Dur Singh",
    "gn:country_code":"IN",
    "gn:dem":215,
    "gn:feature_class":"P",
    "gn:feature_code":"PPL",
    "gn:name":"Dhok M\u0101ri Dur Singh",
    "gn:population":0,
    "gn:timezone":"Asia/Kolkata",
    "iso:country":"IN",
    "wof:name":"Dhok Mari Dur Singh",
    "wof:placetype":"locality"
},
  "geometry": {"coordinates":[74.67895,31.31349],"type":"Point"}
}