{
  "type": "Feature",
  "properties": {
    "gn:admin1_code":"37",
    "gn:admin2_code":"412.0",
    "gn:asciiname":"Giroladih",
    "gn:country_code":"IN",
    "gn:dem":418,
    "gn:feature_class":"P",
    "gn:feature_code":"PPL",
    "gn:name":"Giroladih",
    "gn:population":0,
    "gn:timezone":"Asia/Kolkata",
    "iso:country":"IN",
    "wof:name":"Giroladih",
    "wof:placetype":"locality"
},
  "geometry": {"coordinates":[81.88701,20.60661],"type":"Point"}
}