{
  "type": "Feature",
  "properties": {
    "iso:country":"IN",
    "ks:ks_name":"Palavantangai",
    "ks:ks_type":"VILLAGE",
    "ks:ks_uagg_main":0,
    "name:eng_x_preferred":[
        "Palavantangai"
    ],
    "wof:name":"Palavantangai",
    "wof:placetype":"neighbourhood"
},
  "geometry": {"coordinates":[80.187956,12.987217],"type":"Point"}
}