{
  "type": "Feature",
  "properties": {
    "iso:country":"IN",
    "ks:ks_name":"Kudalkarwadi",
    "ks:ks_pop":99,
    "ks:ks_type":"HABITATION",
    "name:eng_x_preferred":[
        "Kudalkarwadi"
    ],
    "wof:name":"Kudalkarwadi",
    "wof:placetype":"locality",
    "wof:population":99
},
  "geometry": {"coordinates":[73.66572499999999,16.531607],"type":"Point"}
}