{
  "type": "Feature",
  "properties": {
    "gn:admin1_code":"23",
    "gn:admin2_code":"39.0",
    "gn:asciiname":"Sanawa",
    "gn:country_code":"IN",
    "gn:dem":261,
    "gn:feature_class":"P",
    "gn:feature_code":"PPL",
    "gn:name":"San\u0101wa",
    "gn:population":0,
    "gn:timezone":"Asia/Kolkata",
    "iso:country":"IN",
    "name:por_x_preferred":[
        "Sanawa"
    ],
    "wof:name":"Sanawa",
    "wof:placetype":"locality"
},
  "geometry": {"coordinates":[76.19197,31.09561],"type":"Point"}
}