{
  "type": "Feature",
  "properties": {
    "iso:country":"IN",
    "ks:ks_alt_nam":"GAIKWADKASHIDWASTI",
    "ks:ks_name":"Gaikwadkashidwasti",
    "ks:ks_pop":75,
    "ks:ks_type":"HABITATION",
    "name:eng_x_preferred":[
        "Gaikwadkashidwasti"
    ],
    "wof:name":"Gaikwadkashidwasti",
    "wof:placetype":"locality",
    "wof:population":75
},
  "geometry": {"coordinates":[75.15627000000001,17.194451],"type":"Point"}
}