{
  "type": "Feature",
  "properties": {
    "iso:country":"IN",
    "ks:ks_name":"Ekullapur",
    "ks:ks_pop":483,
    "ks:ks_type":"VILLAGE",
    "ks:ks_uagg_main":0,
    "name:eng_x_preferred":[
        "Ekullapur"
    ],
    "wof:name":"Ekullapur",
    "wof:placetype":"neighbourhood",
    "wof:population":483
},
  "geometry": {"coordinates":[82.843459,26.267856],"type":"Point"}
}