{
  "type": "Feature",
  "properties": {
    "gn:admin1_code":"38",
    "gn:admin2_code":"346.0",
    "gn:asciiname":"Nawadih",
    "gn:country_code":"IN",
    "gn:dem":224,
    "gn:feature_class":"P",
    "gn:feature_code":"PPL",
    "gn:name":"Naw\u0101d\u012bh",
    "gn:population":0,
    "gn:timezone":"Asia/Kolkata",
    "iso:country":"IN",
    "wof:name":"Nawadih",
    "wof:placetype":"locality"
},
  "geometry": {"coordinates":[83.64601999999999,24.32665],"type":"Point"}
}