{
  "type": "Feature",
  "properties": {
    "gn:admin1_code":"35.0",
    "gn:admin2_code":"427",
    "gn:asciiname":"Magardha",
    "gn:country_code":"IN",
    "gn:dem":475,
    "gn:feature_class":"P",
    "gn:feature_code":"PPL",
    "gn:name":"Magardha",
    "gn:population":0,
    "gn:timezone":"Asia/Kolkata",
    "iso:country":"IN",
    "wof:name":"Magardha",
    "wof:placetype":"locality"
},
  "geometry": {"coordinates":[78.83821999999998,24.03801],"type":"Point"}
}