{
  "type": "Feature",
  "properties": {
    "iso:country":"IN",
    "ks:ks_name":"Purba Rajnagar",
    "ks:ks_pop":3032,
    "ks:ks_type":"VILLAGE",
    "name:eng_x_preferred":[
        "Purba Rajnagar"
    ],
    "wof:name":"Purba Rajnagar",
    "wof:placetype":"locality",
    "wof:population":3032
},
  "geometry": {"coordinates":[91.697491,24.025562],"type":"Point"}
}