{
  "type": "Feature",
  "properties": {
    "gn:admin1_code":"11",
    "gn:admin2_code":"23.0",
    "gn:asciiname":"Malla",
    "gn:country_code":"IN",
    "gn:dem":1450,
    "gn:feature_class":"P",
    "gn:feature_code":"PPL",
    "gn:name":"Malla",
    "gn:population":0,
    "gn:timezone":"Asia/Kolkata",
    "iso:country":"IN",
    "name:arg_x_preferred":[
        "Malla"
    ],
    "name:cat_x_preferred":[
        "Malla"
    ],
    "name:ceb_x_preferred":[
        "Malla"
    ],
    "name:deu_x_preferred":[
        "Malla"
    ],
    "name:fin_x_preferred":[
        "Malla"
    ],
    "name:fra_x_preferred":[
        "Malla"
    ],
    "name:hye_x_preferred":[
        "\u0544\u0561\u056c\u0575\u0561"
    ],
    "name:ita_x_preferred":[
        "Malla"
    ],
    "name:nld_x_preferred":[
        "Malla"
    ],
    "name:por_x_preferred":[
        "Malla"
    ],
    "name:rus_x_preferred":[
        "\u041c\u0430\u043b\u043b\u0430"
    ],
    "name:spa_x_preferred":[
        "Malla"
    ],
    "name:swe_x_preferred":[
        "Malla"
    ],
    "wof:name":"Malla",
    "wof:placetype":"locality"
},
  "geometry": {"coordinates":[76.34173,32.49006],"type":"Point"}
}