{
  "type": "Feature",
  "properties": {
    "iso:country":"IN",
    "ks:ks_alt_nam":"JOLLY BOARD CHAVAN WASTI",
    "ks:ks_name":"Jolly Board Chavan Wasti",
    "ks:ks_pop":83,
    "ks:ks_type":"HABITATION",
    "name:eng_x_preferred":[
        "Jolly Board Chavan Wasti"
    ],
    "wof:name":"Jolly Board Chavan Wasti",
    "wof:placetype":"locality",
    "wof:population":83
},
  "geometry": {"coordinates":[74.800015,16.991532],"type":"Point"}
}