{
  "type": "Feature",
  "properties": {
    "iso:country":"IN",
    "ks:ks_name":"Kuzhinada",
    "ks:ks_pop":996,
    "ks:ks_type":"HABITATION",
    "ks:ks_uagg_main":0,
    "name:eng_x_preferred":[
        "Kuzhinada"
    ],
    "wof:name":"Kuzhinada",
    "wof:placetype":"neighbourhood",
    "wof:population":996
},
  "geometry": {"coordinates":[77.008188,8.670747],"type":"Point"}
}