{
  "type": "Feature",
  "properties": {
    "gn:admin1_code":"35",
    "gn:admin2_code":"448.0",
    "gn:asciiname":"Nimacha Kalan",
    "gn:country_code":"IN",
    "gn:dem":311,
    "gn:feature_class":"P",
    "gn:feature_code":"PPL",
    "gn:name":"Nim\u0101cha Kal\u0101n",
    "gn:population":0,
    "gn:timezone":"Asia/Kolkata",
    "iso:country":"IN",
    "wof:name":"Nimacha Kalan",
    "wof:placetype":"locality"
},
  "geometry": {"coordinates":[77.24805000000001,22.3554],"type":"Point"}
}