{
  "type": "Feature",
  "properties": {
    "iso:country":"IN",
    "ks:ks_name":"Chandrapadiguda",
    "ks:ks_pop":107,
    "ks:ks_type":"HABITATION",
    "name:eng_x_preferred":[
        "Chandrapadiguda"
    ],
    "wof:name":"Chandrapadiguda",
    "wof:placetype":"locality",
    "wof:population":107
},
  "geometry": {"coordinates":[82.362897,18.893558],"type":"Point"}
}