{
  "type": "Feature",
  "properties": {
    "iso:country":"IN",
    "ks:ks_alt_nam":"Egudalabavi indlu",
    "ks:ks_name":"Egudalabavi Indlu",
    "ks:ks_pop":27,
    "ks:ks_type":"HABITATION",
    "name:eng_x_preferred":[
        "Egudalabavi Indlu"
    ],
    "wof:name":"Egudalabavi Indlu",
    "wof:placetype":"locality",
    "wof:population":27
},
  "geometry": {"coordinates":[79.299148,13.522989],"type":"Point"}
}