{
  "type": "Feature",
  "properties": {
    "gn:admin1_code":"36",
    "gn:admin2_code":"195.0",
    "gn:asciiname":"Aspur",
    "gn:country_code":"IN",
    "gn:dem":74,
    "gn:feature_class":"P",
    "gn:feature_code":"PPL",
    "gn:name":"\u0100spur",
    "gn:population":0,
    "gn:timezone":"Asia/Kolkata",
    "iso:country":"IN",
    "name:fas_x_preferred":[
        "\u0627\u0633\u067e\u0648\u0631"
    ],
    "wof:name":"Aspur",
    "wof:placetype":"locality"
},
  "geometry": {"coordinates":[83.27553,25.69866],"type":"Point"}
}