{
  "type": "Feature",
  "properties": {
    "iso:country":"IN",
    "ks:ks_name":"Kotwalguda",
    "ks:ks_pop":95,
    "ks:ks_type":"HABITATION",
    "name:eng_x_preferred":[
        "Kotwalguda"
    ],
    "wof:name":"Kotwalguda",
    "wof:placetype":"locality",
    "wof:population":95
},
  "geometry": {"coordinates":[78.523194,19.591482],"type":"Point"}
}