{
  "type": "Feature",
  "properties": {
    "gn:admin1_code":"10.0",
    "gn:admin2_code":"82.0",
    "gn:asciiname":"Kahni",
    "gn:country_code":"IN",
    "gn:dem":223,
    "gn:feature_class":"P",
    "gn:feature_code":"PPL",
    "gn:name":"K\u0101hni",
    "gn:population":0,
    "gn:timezone":"Asia/Kolkata",
    "iso:country":"IN",
    "wof:name":"Kahni",
    "wof:placetype":"neighbourhood"
},
  "geometry": {"coordinates":[76.67582,29.01494],"type":"Point"}
}