{
  "type": "Feature",
  "properties": {
    "iso:country":"IN",
    "name:cat_x_preferred":[
        "Alipur"
    ],
    "name:ceb_x_preferred":[
        "Alipur"
    ],
    "name:swe_x_preferred":[
        "Alipur"
    ],
    "qs:name":"Alipur",
    "qs:name_adm0":"India",
    "qs:name_adm1":"Delhi",
    "qs:photos":2,
    "qs:photos_1k":1,
    "qs:photos_9k":1,
    "qs:photos_9r":1,
    "qs:photos_all":2,
    "qs:photos_sr":1,
    "qs:placetype":"Suburb",
    "qs:pop_sr":"0",
    "wd:wordcount":69,
    "wof:name":"Alipur",
    "wof:placetype":"neighbourhood"
},
  "geometry": {"coordinates":[77.13151000000001,28.79961],"type":"Point"}
}