{
  "type": "Feature",
  "properties": {
    "iso:country":"IN",
    "qs:name":"Chamarajasagar",
    "qs:name_adm0":"India",
    "qs:name_adm1":"Karnataka",
    "qs:photos":8,
    "qs:photos_1k":2,
    "qs:photos_9k":1,
    "qs:photos_9r":1,
    "qs:photos_all":8,
    "qs:photos_sr":1,
    "qs:placetype":"Town",
    "qs:pop_sr":"0",
    "wof:name":"Chamarajasagar",
    "wof:placetype":"locality"
},
  "geometry": {"coordinates":[77.343234,12.9810565],"type":"Point"}
}