{
  "type": "Feature",
  "properties": {
    "gn:admin1_code":"21.0",
    "gn:admin2_code":"398.0",
    "gn:asciiname":"Dokiripada",
    "gn:country_code":"IN",
    "gn:dem":787,
    "gn:feature_class":"P",
    "gn:feature_code":"PPL",
    "gn:name":"Dokirip\u0101da",
    "gn:population":0,
    "gn:timezone":"Asia/Kolkata",
    "iso:country":"IN",
    "ks:ks_name":"Dokripada",
    "ks:ks_pop":110,
    "ks:ks_type":"VILLAGE",
    "name:eng_x_preferred":[
        "Dokripada"
    ],
    "name:eng_x_variant":[
        "Dokiripada"
    ],
    "wof:name":"Dokripada",
    "wof:placetype":"locality",
    "wof:population":110
},
  "geometry": {"coordinates":[82.457075,18.663527],"type":"Point"}
}