{
  "type": "Feature",
  "properties": {
    "gn:admin1_code":"21.0",
    "gn:admin2_code":"398.0",
    "gn:asciiname":"Dokiripada",
    "gn:country_code":"IN",
    "gn:dem":787,
    "gn:feature_class":"P",
    "gn:feature_code":"PPL",
    "gn:name":"Dokirip\u0101da",
    "gn:population":0,
    "gn:timezone":"Asia/Kolkata",
    "iso:country":"IN",
    "wof:name":"Dokiripada",
    "wof:placetype":"locality"
},
  "geometry": {"coordinates":[82.45728000000003,18.66361],"type":"Point"}
}