{
  "type": "Feature",
  "properties": {
    "gn:admin1_code":"38.0",
    "gn:admin2_code":"351.0",
    "gn:asciiname":"Gopi Chak",
    "gn:country_code":"IN",
    "gn:dem":53,
    "gn:feature_class":"P",
    "gn:feature_code":"PPL",
    "gn:name":"Gopi Chak",
    "gn:population":0,
    "gn:timezone":"Asia/Kolkata",
    "iso:country":"IN",
    "ks:ks_name":"Gopichak",
    "ks:ks_pop":883,
    "ks:ks_type":"VILLAGE",
    "ks:ks_uagg_main":0,
    "name:eng_x_preferred":[
        "Gopichak"
    ],
    "wof:name":"Gopichak",
    "wof:placetype":"neighbourhood",
    "wof:population":883
},
  "geometry": {"coordinates":[87.195759,25.01494],"type":"Point"}
}