{
  "type": "Feature",
  "properties": {
    "iso:country":"IN",
    "ks:ks_name":"Devimanekeri",
    "ks:ks_pop":51,
    "ks:ks_type":"HABITATION",
    "name:eng_x_preferred":[
        "Devimanekeri"
    ],
    "wof:name":"Devimanekeri",
    "wof:placetype":"locality",
    "wof:population":51
},
  "geometry": {"coordinates":[74.56327899999999,14.908728],"type":"Point"}
}