{
  "type": "Feature",
  "properties": {
    "iso:country":"IN",
    "ks:ks_name":"Kumbharwadi",
    "ks:ks_pop":145,
    "ks:ks_type":"HABITATION",
    "name:eng_x_preferred":[
        "Kumbharwadi"
    ],
    "wof:name":"Kumbharwadi",
    "wof:placetype":"locality",
    "wof:population":145
},
  "geometry": {"coordinates":[73.568889,16.990556],"type":"Point"}
}