{
  "type": "Feature",
  "properties": {
    "gn:admin1_code":"10",
    "gn:admin2_code":"77.0",
    "gn:asciiname":"Baroda",
    "gn:country_code":"IN",
    "gn:dem":230,
    "gn:feature_class":"P",
    "gn:feature_code":"PPL",
    "gn:name":"Baroda",
    "gn:population":0,
    "gn:timezone":"Asia/Kolkata",
    "iso:country":"IN",
    "wof:name":"Baroda",
    "wof:placetype":"locality"
},
  "geometry": {"coordinates":[76.20817,29.43847],"type":"Point"}
}