{
  "type": "Feature",
  "properties": {
    "iso:country":"IN",
    "ks:ks_name":"Sanya Phaliya Lagga Khunari",
    "ks:ks_pop":11,
    "ks:ks_type":"HABITATION",
    "name:eng_x_preferred":[
        "Sanya Phaliya Lagga Khunari"
    ],
    "wof:name":"Sanya Phaliya Lagga Khunari",
    "wof:placetype":"locality",
    "wof:population":11
},
  "geometry": {"coordinates":[80.047331,29.362332],"type":"Point"}
}