{
  "type": "Feature",
  "properties": {
    "gn:admin1_code":"37",
    "gn:admin2_code":"401.0",
    "gn:asciiname":"Chaki",
    "gn:country_code":"IN",
    "gn:dem":445,
    "gn:feature_class":"P",
    "gn:feature_code":"PPL",
    "gn:name":"Ch\u0101k\u012b",
    "gn:population":0,
    "gn:timezone":"Asia/Kolkata",
    "iso:country":"IN",
    "name:epo_x_preferred":[
        "Chaki"
    ],
    "name:ita_x_preferred":[
        "Chaki"
    ],
    "wof:name":"Chaki",
    "wof:placetype":"locality"
},
  "geometry": {"coordinates":[83.50733000000002,23.79822],"type":"Point"}
}