{
  "type": "Feature",
  "properties": {
    "gn:admin1_code":"24.0",
    "gn:admin2_code":"101",
    "gn:asciiname":"Garabdesar",
    "gn:country_code":"IN",
    "gn:dem":214,
    "gn:feature_class":"P",
    "gn:feature_code":"PPL",
    "gn:name":"G\u0101rabdesar",
    "gn:population":0,
    "gn:timezone":"Asia/Kolkata",
    "iso:country":"IN",
    "ks:ks_alt_nam":"G\u0101rabdesar",
    "ks:ks_name":"Garabdesar",
    "ks:ks_pop":3683,
    "ks:ks_type":"VILLAGE",
    "name:eng_x_preferred":[
        "Garabdesar"
    ],
    "name:eng_x_variant":[
        "G\u0101rabdesar"
    ],
    "name:und_x_variant":[
        "G\u0101rabdenar",
        "G\u0101rabdesar"
    ],
    "wof:name":"Garabdesar",
    "wof:placetype":"locality",
    "wof:population":3683
},
  "geometry": {"coordinates":[74.012444,28.439697],"type":"Point"}
}