{
  "type": "Feature",
  "properties": {
    "iso:country":"IN",
    "ks:ks_name":"Sarupalli",
    "ks:ks_pop":931,
    "ks:ks_type":"HABITATION",
    "name:eng_x_preferred":[
        "Sarupalli"
    ],
    "wof:name":"Sarupalli",
    "wof:placetype":"locality",
    "wof:population":931
},
  "geometry": {"coordinates":[83.27450899999999,18.936278],"type":"Point"}
}