{
  "type": "Feature",
  "properties": {
    "iso:country":"IN",
    "ks:ks_name":"Yemai Wasti",
    "ks:ks_pop":86,
    "ks:ks_type":"HABITATION",
    "name:eng_x_preferred":[
        "Yemai Wasti"
    ],
    "wof:name":"Yemai Wasti",
    "wof:placetype":"locality",
    "wof:population":86
},
  "geometry": {"coordinates":[75.486259,18.450156],"type":"Point"}
}