{
  "type": "Feature",
  "properties": {
    "iso:country":"IN",
    "ks:ks_name":"Baliarpur",
    "ks:ks_pop":328,
    "ks:ks_type":"VILLAGE",
    "name:eng_x_preferred":[
        "Baliarpur"
    ],
    "wof:name":"Baliarpur",
    "wof:placetype":"locality",
    "wof:population":328
},
  "geometry": {"coordinates":[86.878406,20.864511],"type":"Point"}
}