{
  "type": "Feature",
  "properties": {
    "gn:admin1_code":"39",
    "gn:admin2_code":"61.0",
    "gn:asciiname":"Bidurgaon",
    "gn:country_code":"IN",
    "gn:dem":1656,
    "gn:feature_class":"P",
    "gn:feature_code":"PPL",
    "gn:name":"Bidurgaon",
    "gn:population":0,
    "gn:timezone":"Asia/Kolkata",
    "iso:country":"IN",
    "ks:ks_name":"Bidurgaon",
    "ks:ks_type":"VILLAGE",
    "name:eng_x_preferred":[
        "Bidurgaon"
    ],
    "wof:name":"Bidurgaon",
    "wof:placetype":"locality"
},
  "geometry": {"coordinates":[78.784363,29.801259],"type":"Point"}
}