{
  "type": "Feature",
  "properties": {
    "iso:country":"IN",
    "ks:ks_name":"Yadavwadi",
    "ks:ks_pop":480,
    "ks:ks_type":"HABITATION",
    "name:eng_x_preferred":[
        "Yadavwadi"
    ],
    "wof:name":"Yadavwadi",
    "wof:placetype":"locality",
    "wof:population":480
},
  "geometry": {"coordinates":[74.988,18.029],"type":"Point"}
}