{
  "type": "Feature",
  "properties": {
    "gn:admin1_code":"19.0",
    "gn:admin2_code":"562.0",
    "gn:asciiname":"Bamsamudra",
    "gn:country_code":"IN",
    "gn:dem":590,
    "gn:feature_class":"P",
    "gn:feature_code":"PPL",
    "gn:name":"Bamsamudra",
    "gn:population":0,
    "gn:timezone":"Asia/Kolkata",
    "iso:country":"IN",
    "wof:name":"Bamsamudra",
    "wof:placetype":"neighbourhood"
},
  "geometry": {"coordinates":[75.1173,15.23746],"type":"Point"}
}