{
  "type": "Feature",
  "properties": {
    "iso:country":"IN",
    "ks:ks_alt_nam":"Holi falia",
    "ks:ks_name":"Holi Falia",
    "ks:ks_pop":555,
    "ks:ks_type":"HABITATION",
    "ks:ks_uagg_main":0,
    "name:eng_x_preferred":[
        "Holi Falia"
    ],
    "wof:name":"Holi Falia",
    "wof:placetype":"neighbourhood",
    "wof:population":555
},
  "geometry": {"coordinates":[74.223889,22.688444],"type":"Point"}
}