{
  "type": "Feature",
  "properties": {
    "iso:country":"IN",
    "ks:ks_name":"Kait-tarai",
    "ks:ks_pop":289,
    "ks:ks_type":"HABITATION",
    "name:eng_x_preferred":[
        "Kait-tarai"
    ],
    "wof:name":"Kait-tarai",
    "wof:placetype":"locality",
    "wof:population":289
},
  "geometry": {"coordinates":[81.911754,20.281203],"type":"Point"}
}