{
  "type": "Feature",
  "properties": {
    "iso:country":"IN",
    "ks:ks_name":"Chopada",
    "ks:ks_pop":207,
    "ks:ks_type":"HABITATION",
    "name:eng_x_preferred":[
        "Chopada"
    ],
    "wof:name":"Chopada",
    "wof:placetype":"locality",
    "wof:population":207
},
  "geometry": {"coordinates":[77.405181,23.891591],"type":"Point"}
}