{
  "type": "Feature",
  "properties": {
    "iso:country":"IN",
    "ks:ks_name":"Padi",
    "ks:ks_pop":648,
    "ks:ks_type":"VILLAGE",
    "ks:ks_uagg_main":0,
    "name:eng_x_preferred":[
        "Padi"
    ],
    "wof:name":"Padi",
    "wof:placetype":"neighbourhood",
    "wof:population":648
},
  "geometry": {"coordinates":[86.351101,21.163597],"type":"Point"}
}