{
  "type": "Feature",
  "properties": {
    "iso:country":"IN",
    "ks:ks_name":"Manda Laga Siman",
    "ks:ks_pop":61,
    "ks:ks_type":"VILLAGE",
    "name:eng_x_preferred":[
        "Manda Laga Siman"
    ],
    "wof:name":"Manda Laga Siman",
    "wof:placetype":"locality",
    "wof:population":61
},
  "geometry": {"coordinates":[79.298631,30.01938],"type":"Point"}
}