{
  "type": "Feature",
  "properties": {
    "gn:admin1_code":"16",
    "gn:admin2_code":"510.0",
    "gn:asciiname":"Vagad Buzurg",
    "gn:country_code":"IN",
    "gn:dem":406,
    "gn:feature_class":"P",
    "gn:feature_code":"PPL",
    "gn:name":"V\u0101gad Buzurg",
    "gn:population":0,
    "gn:timezone":"Asia/Kolkata",
    "iso:country":"IN",
    "wof:name":"Vagad Buzurg",
    "wof:placetype":"locality"
},
  "geometry": {"coordinates":[77.60396,20.30063],"type":"Point"}
}