{
  "type": "Feature",
  "properties": {
    "iso:country":"IN",
    "ks:ks_name":"Dom Toli",
    "ks:ks_pop":737,
    "ks:ks_type":"HABITATION",
    "ks:ks_uagg_main":0,
    "name:eng_x_preferred":[
        "Dom Toli"
    ],
    "wof:name":"Dom Toli",
    "wof:placetype":"neighbourhood",
    "wof:population":737
},
  "geometry": {"coordinates":[84.52737999999999,27.227398],"type":"Point"}
}