{
  "type": "Feature",
  "properties": {
    "gn:admin1_code":"39.0",
    "gn:admin2_code":"64.0",
    "gn:asciiname":"Kotila",
    "gn:country_code":"IN",
    "gn:dem":1166,
    "gn:feature_class":"P",
    "gn:feature_code":"PPL",
    "gn:name":"Kotila",
    "gn:population":0,
    "gn:timezone":"Asia/Kolkata",
    "iso:country":"IN",
    "name:fin_x_preferred":[
        "Kotila"
    ],
    "name:fra_x_preferred":[
        "Kotila"
    ],
    "name:new_x_preferred":[
        "\u0915\u094b\u0924\u093f\u0932\u093e \u0968"
    ],
    "name:pol_x_preferred":[
        "Kotila"
    ],
    "wof:name":"Kotila",
    "wof:placetype":"locality"
},
  "geometry": {"coordinates":[79.45326999999997,29.55976],"type":"Point"}
}