{
  "type": "Feature",
  "properties": {
    "iso:country":"IN",
    "ks:ks_name":"Kuriunja",
    "ks:ks_pop":174,
    "ks:ks_type":"HABITATION",
    "name:eng_x_preferred":[
        "Kuriunja"
    ],
    "wof:name":"Kuriunja",
    "wof:placetype":"locality",
    "wof:population":174
},
  "geometry": {"coordinates":[75.49926000000001,12.880832],"type":"Point"}
}