{
  "type": "Feature",
  "properties": {
    "gn:admin1_code":"13.0",
    "gn:admin2_code":"590.0",
    "gn:asciiname":"Ballarchang",
    "gn:country_code":"IN",
    "gn:dem":750,
    "gn:feature_class":"P",
    "gn:feature_code":"PPL",
    "gn:name":"Ballarchang",
    "gn:population":0,
    "gn:timezone":"Asia/Kolkata",
    "iso:country":"IN",
    "wof:name":"Ballarchang",
    "wof:placetype":"locality"
},
  "geometry": {"coordinates":[75.85185,11.81917],"type":"Point"}
}