{
  "type": "Feature",
  "properties": {
    "gn:admin1_code":"21.0",
    "gn:admin2_code":"374",
    "gn:asciiname":"Balia",
    "gn:country_code":"IN",
    "gn:dem":370,
    "gn:feature_class":"P",
    "gn:feature_code":"PPL",
    "gn:name":"B\u0101lia",
    "gn:population":0,
    "gn:timezone":"Asia/Kolkata",
    "iso:country":"IN",
    "name:hin_x_preferred":[
        "\u092c\u0932\u093f\u092f\u093e"
    ],
    "wof:name":"Balia",
    "wof:placetype":"locality"
},
  "geometry": {"coordinates":[84.66257,21.78415],"type":"Point"}
}