{
  "type": "Feature",
  "properties": {
    "gn:admin1_code":"2.0",
    "gn:admin2_code":"543.0",
    "gn:asciiname":"Nuravarahalapeta",
    "gn:country_code":"IN",
    "gn:dem":807,
    "gn:feature_class":"P",
    "gn:feature_code":"PPL",
    "gn:name":"N\u016bravarah\u0101lapeta",
    "gn:population":0,
    "gn:timezone":"Asia/Kolkata",
    "iso:country":"IN",
    "ks:ks_name":"Nuruvarahalapadu",
    "ks:ks_pop":111,
    "ks:ks_type":"HABITATION",
    "name:eng_x_preferred":[
        "Nuruvarahalapadu"
    ],
    "name:eng_x_variant":[
        "Nuravarahalapeta"
    ],
    "wof:name":"Nuruvarahalapadu",
    "wof:placetype":"locality",
    "wof:population":111
},
  "geometry": {"coordinates":[83.162068,18.36891],"type":"Point"}
}