{
  "type": "Feature",
  "properties": {
    "iso:country":"IN",
    "ks:ks_alt_nam":"Gandhi nagar",
    "ks:ks_name":"Gandhi Nagar",
    "ks:ks_pop":353,
    "ks:ks_type":"HABITATION",
    "name:eng_x_preferred":[
        "Gandhi Nagar"
    ],
    "wof:name":"Gandhi Nagar",
    "wof:placetype":"locality",
    "wof:population":353
},
  "geometry": {"coordinates":[76.101749,18.493795],"type":"Point"}
}