{
  "type": "Feature",
  "properties": {
    "iso:country":"IN",
    "ks:ks_name":"Mavilangai",
    "ks:ks_pop":142,
    "ks:ks_type":"HABITATION",
    "name:eng_x_preferred":[
        "Mavilangai"
    ],
    "wof:name":"Mavilangai",
    "wof:placetype":"locality",
    "wof:population":142
},
  "geometry": {"coordinates":[78.63973900000001,9.73867],"type":"Point"}
}