{
  "type": "Feature",
  "properties": {
    "gn:admin1_code":"12.0",
    "gn:admin2_code":"1.0",
    "gn:asciiname":"Khohalmarg",
    "gn:country_code":"IN",
    "gn:dem":3179,
    "gn:feature_class":"P",
    "gn:feature_code":"PPL",
    "gn:name":"Khohalmarg",
    "gn:population":0,
    "gn:timezone":"Asia/Kolkata",
    "iso:country":"IN",
    "wof:name":"Khohalmarg",
    "wof:placetype":"locality"
},
  "geometry": {"coordinates":[74.41764000000001,34.58649],"type":"Point"}
}