{
  "type": "Feature",
  "properties": {
    "iso:country":"IN",
    "ks:ks_name":"Padepara",
    "ks:ks_pop":517,
    "ks:ks_type":"HABITATION",
    "name:eng_x_preferred":[
        "Padepara"
    ],
    "wof:name":"Padepara",
    "wof:placetype":"locality",
    "wof:population":517
},
  "geometry": {"coordinates":[81.532641,19.060046],"type":"Point"}
}