{
  "type": "Feature",
  "properties": {
    "iso:country":"IN",
    "ks:ks_name":"Sankargarh",
    "ks:ks_pop":849,
    "ks:ks_type":"VILLAGE",
    "name:eng_x_preferred":[
        "Sankargarh"
    ],
    "wof:name":"Sankargarh",
    "wof:placetype":"locality",
    "wof:population":849
},
  "geometry": {"coordinates":[82.24364300000001,23.290818],"type":"Point"}
}