{
  "type": "Feature",
  "properties": {
    "iso:country":"IN",
    "ks:ks_name":"Arazi Uchaith",
    "ks:ks_pop":438,
    "ks:ks_type":"VILLAGE",
    "name:eng_x_preferred":[
        "Arazi Uchaith"
    ],
    "wof:name":"Arazi Uchaith",
    "wof:placetype":"locality",
    "wof:population":438
},
  "geometry": {"coordinates":[85.878052,26.465279],"type":"Point"}
}