{
  "type": "Feature",
  "properties": {
    "iso:country":"IN",
    "ks:ks_alt_nam":"Bara K\u0101ta",
    "ks:ks_name":"Bara Kata",
    "ks:ks_type":"VILLAGE",
    "name:eng_x_preferred":[
        "Bara Kata"
    ],
    "name:eng_x_variant":[
        "Bara K\u0101ta"
    ],
    "wof:name":"Bara Kata",
    "wof:placetype":"locality"
},
  "geometry": {"coordinates":[85.935222,22.077312],"type":"Point"}
}