{
  "type": "Feature",
  "properties": {
    "gn:admin1_code":"25.0",
    "gn:admin2_code":"631.0",
    "gn:asciiname":"Nayaganapalli",
    "gn:country_code":"IN",
    "gn:dem":758,
    "gn:feature_class":"P",
    "gn:feature_code":"PPL",
    "gn:name":"N\u0101yag\u0101napalli",
    "gn:population":0,
    "gn:timezone":"Asia/Kolkata",
    "iso:country":"IN",
    "wof:name":"Nayaganapalli",
    "wof:placetype":"locality"
},
  "geometry": {"coordinates":[77.92128000000002,12.65392],"type":"Point"}
}