{
  "type": "Feature",
  "properties": {
    "iso:country":"IN",
    "ks:ks_name":"Sakka",
    "ks:ks_pop":265,
    "ks:ks_type":"HABITATION",
    "name:eng_x_preferred":[
        "Sakka"
    ],
    "wof:name":"Sakka",
    "wof:placetype":"locality",
    "wof:population":265
},
  "geometry": {"coordinates":[78.435059,27.486437],"type":"Point"}
}