{
  "type": "Feature",
  "properties": {
    "gn:admin1_code":"36",
    "gn:admin2_code":"188.0",
    "gn:asciiname":"Chaura",
    "gn:country_code":"IN",
    "gn:dem":84,
    "gn:feature_class":"P",
    "gn:feature_code":"PPL",
    "gn:name":"Chaura",
    "gn:population":0,
    "gn:timezone":"Asia/Kolkata",
    "iso:country":"IN",
    "ks:ks_name":"Chaura",
    "ks:ks_pop":4057,
    "ks:ks_type":"VILLAGE",
    "ks:ks_uagg_main":0,
    "name:ceb_x_preferred":[
        "Chaura"
    ],
    "name:eng_x_preferred":[
        "Chaura"
    ],
    "name:swe_x_preferred":[
        "Chaura"
    ],
    "wof:name":"Chaura",
    "wof:placetype":"neighbourhood",
    "wof:population":4057
},
  "geometry": {"coordinates":[83.589933,26.640335],"type":"Point"}
}