{
  "type": "Feature",
  "properties": {
    "iso:country":"IN",
    "ks:ks_name":"Kalimati",
    "ks:ks_pop":55,
    "ks:ks_type":"VILLAGE",
    "name:eng_x_preferred":[
        "Kalimati"
    ],
    "wof:name":"Kalimati",
    "wof:placetype":"locality",
    "wof:population":55
},
  "geometry": {"coordinates":[84.455882,20.538629],"type":"Point"}
}