{
  "type": "Feature",
  "properties": {
    "iso:country":"IN",
    "ks:ks_name":"Landamunda",
    "ks:ks_pop":223,
    "ks:ks_type":"VILLAGE",
    "name:eng_x_preferred":[
        "Landamunda"
    ],
    "wof:name":"Landamunda",
    "wof:placetype":"locality",
    "wof:population":223
},
  "geometry": {"coordinates":[85.059012,21.827134],"type":"Point"}
}