{
  "type": "Feature",
  "properties": {
    "iso:country":"IN",
    "ks:ks_name":"Dhupai Tola",
    "ks:ks_pop":150,
    "ks:ks_type":"HABITATION",
    "name:eng_x_preferred":[
        "Dhupai Tola"
    ],
    "wof:name":"Dhupai Tola",
    "wof:placetype":"locality",
    "wof:population":150
},
  "geometry": {"coordinates":[83.77672099999999,26.935853],"type":"Point"}
}