{
  "type": "Feature",
  "properties": {
    "iso:country":"IN",
    "ks:ks_name":"Sukh Dharanpur Kithawan",
    "ks:ks_pop":455,
    "ks:ks_type":"HABITATION",
    "name:eng_x_preferred":[
        "Sukh Dharanpur Kithawan"
    ],
    "wof:name":"Sukh Dharanpur Kithawan",
    "wof:placetype":"locality",
    "wof:population":455
},
  "geometry": {"coordinates":[81.34171000000001,25.67717],"type":"Point"}
}