{
  "type": "Feature",
  "properties": {
    "gn:admin1_code":"34.0",
    "gn:admin2_code":"229.0",
    "gn:asciiname":"Puraini",
    "gn:country_code":"IN",
    "gn:dem":75,
    "gn:feature_class":"P",
    "gn:feature_code":"PPL",
    "gn:name":"Puraini",
    "gn:population":0,
    "gn:timezone":"Asia/Kolkata",
    "iso:country":"IN",
    "name:ceb_x_preferred":[
        "Puraini"
    ],
    "name:mai_x_preferred":[
        "\u092a\u0941\u0930\u0948\u0928\u0940"
    ],
    "name:msa_x_preferred":[
        "Puraini"
    ],
    "name:nep_x_preferred":[
        "\u092a\u0941\u0930\u0948\u0928\u0940"
    ],
    "name:new_x_preferred":[
        "\u092a\u0941\u0930\u0948\u0928\u0940"
    ],
    "name:pol_x_preferred":[
        "Puraini"
    ],
    "wof:name":"Puraini",
    "wof:placetype":"locality"
},
  "geometry": {"coordinates":[85.5348,25.01332],"type":"Point"}
}