{
  "type": "Feature",
  "properties": {
    "iso:country":"IN",
    "ks:ks_name":"Haljent",
    "ks:ks_pop":55,
    "ks:ks_type":"VILLAGE",
    "name:eng_x_preferred":[
        "Haljent"
    ],
    "wof:name":"Haljent",
    "wof:placetype":"locality",
    "wof:population":55
},
  "geometry": {"coordinates":[78.49544,30.276209],"type":"Point"}
}