{
  "type": "Feature",
  "properties": {
    "iso:country":"IN",
    "ks:ks_name":"Uttar Namcharia",
    "ks:ks_pop":145,
    "ks:ks_type":"HABITATION",
    "name:eng_x_preferred":[
        "Uttar Namcharia"
    ],
    "wof:name":"Uttar Namcharia",
    "wof:placetype":"locality",
    "wof:population":145
},
  "geometry": {"coordinates":[91.517692,26.633007],"type":"Point"}
}