{
  "type": "Feature",
  "properties": {
    "iso:country":"IN",
    "ks:ks_name":"Ganti",
    "ks:ks_pop":1560,
    "ks:ks_type":"VILLAGE",
    "name:eng_x_preferred":[
        "Ganti"
    ],
    "wof:name":"Ganti",
    "wof:placetype":"locality",
    "wof:population":1560
},
  "geometry": {"coordinates":[88.703312,22.427501],"type":"Point"}
}