{
  "type": "Feature",
  "properties": {
    "iso:country":"IN",
    "ks:ks_name":"Sakavaripeta",
    "ks:ks_pop":369,
    "ks:ks_type":"HABITATION",
    "name:eng_x_preferred":[
        "Sakavaripeta"
    ],
    "wof:name":"Sakavaripeta",
    "wof:placetype":"locality",
    "wof:population":369
},
  "geometry": {"coordinates":[81.781384,16.516053],"type":"Point"}
}