{
  "type": "Feature",
  "properties": {
    "gn:admin1_code":"35",
    "gn:admin2_code":"421.0",
    "gn:asciiname":"Senthri",
    "gn:country_code":"IN",
    "gn:dem":198,
    "gn:feature_class":"P",
    "gn:feature_code":"PPL",
    "gn:name":"Senthri",
    "gn:population":0,
    "gn:timezone":"Asia/Kolkata",
    "iso:country":"IN",
    "ks:ks_name":"Senthri",
    "ks:ks_pop":1386,
    "ks:ks_type":"HABITATION",
    "wof:name":"Senthri",
    "wof:placetype":"neighbourhood"
},
  "geometry": {"coordinates":[78.20525000000001,26.29639],"type":"Point"}
}