{
  "type": "Feature",
  "properties": {
    "iso:country":"IN",
    "ks:ks_name":"Kureichuan",
    "ks:ks_pop":203,
    "ks:ks_type":"VILLAGE",
    "name:eng_x_preferred":[
        "Kureichuan"
    ],
    "wof:name":"Kureichuan",
    "wof:placetype":"locality",
    "wof:population":203
},
  "geometry": {"coordinates":[84.539143,21.726023],"type":"Point"}
}