{
  "type": "Feature",
  "properties": {
    "iso:country":"IN",
    "ks:ks_name":"Hakma Tola",
    "ks:ks_pop":163,
    "ks:ks_type":"HABITATION",
    "ks:ks_uagg_main":0,
    "name:eng_x_preferred":[
        "Hakma Tola"
    ],
    "wof:name":"Hakma Tola",
    "wof:placetype":"neighbourhood",
    "wof:population":163
},
  "geometry": {"coordinates":[84.292309,26.117581],"type":"Point"}
}