{
  "type": "Feature",
  "properties": {
    "iso:country":"IN",
    "ks:ks_name":"Chinnakotamakinepalle",
    "ks:ks_pop":153,
    "ks:ks_type":"HABITATION",
    "name:eng_x_preferred":[
        "Chinnakotamakinepalle"
    ],
    "wof:name":"Chinnakotamakinepalle",
    "wof:placetype":"locality",
    "wof:population":153
},
  "geometry": {"coordinates":[78.219722,12.701946],"type":"Point"}
}