{
  "type": "Feature",
  "properties": {
    "gn:admin1_code":"11",
    "gn:admin2_code":"23.0",
    "gn:asciiname":"Bedraru Got",
    "gn:country_code":"IN",
    "gn:dem":1830,
    "gn:feature_class":"P",
    "gn:feature_code":"PPL",
    "gn:name":"Bedr\u0101ru Got",
    "gn:population":0,
    "gn:timezone":"Asia/Kolkata",
    "iso:country":"IN",
    "wof:name":"Bedraru Got",
    "wof:placetype":"locality"
},
  "geometry": {"coordinates":[76.26195,32.8452],"type":"Point"}
}