{
  "type": "Feature",
  "properties": {
    "gn:admin1_code":"2",
    "gn:asciiname":"Kiramamidi",
    "gn:country_code":"IN",
    "gn:dem":1055,
    "gn:feature_class":"P",
    "gn:feature_code":"PPL",
    "gn:name":"Kiram\u0101midi",
    "gn:population":0,
    "gn:timezone":"Asia/Kolkata",
    "iso:country":"IN",
    "wof:name":"Kiramamidi",
    "wof:placetype":"locality"
},
  "geometry": {"coordinates":[82.78352,18.41528],"type":"Point"}
}