{
  "type": "Feature",
  "properties": {
    "iso:country":"IN",
    "ks:ks_alt_nam":"Gopu tanda",
    "ks:ks_name":"Gopu Tanda",
    "ks:ks_pop":89,
    "ks:ks_type":"HABITATION",
    "name:eng_x_preferred":[
        "Gopu Tanda"
    ],
    "wof:name":"Gopu Tanda",
    "wof:placetype":"locality",
    "wof:population":89
},
  "geometry": {"coordinates":[77.579533,18.119417],"type":"Point"}
}