{
  "type": "Feature",
  "properties": {
    "gn:admin1_code":"37",
    "gn:admin2_code":"403.0",
    "gn:asciiname":"Surajgarh",
    "gn:country_code":"IN",
    "gn:dem":202,
    "gn:feature_class":"P",
    "gn:feature_code":"PPL",
    "gn:name":"S\u016brajgarh",
    "gn:population":0,
    "gn:timezone":"Asia/Kolkata",
    "iso:country":"IN",
    "name:ben_x_preferred":[
        "\u09b8\u09c1\u09b0\u09af\u0997\u09a1\u09bc"
    ],
    "name:bpy_x_preferred":[
        "\u09b8\u09c1\u09b0\u09af\u0997\u09a1\u09bc"
    ],
    "name:cat_x_preferred":[
        "Surajgarh"
    ],
    "name:ceb_x_preferred":[
        "S\u016brajgarh"
    ],
    "name:deu_x_preferred":[
        "Surajgarh"
    ],
    "name:ita_x_preferred":[
        "Surajgarh"
    ],
    "name:msa_x_preferred":[
        "Surajgarh"
    ],
    "name:por_x_preferred":[
        "Surajgarh"
    ],
    "name:swe_x_preferred":[
        "Surajgarh"
    ],
    "name:vie_x_preferred":[
        "Surajgarh"
    ],
    "name:zho_x_preferred":[
        "\u82cf\u62c9\u6770\u52a0\u5c14"
    ],
    "wof:name":"Surajgarh",
    "wof:placetype":"locality"
},
  "geometry": {"coordinates":[83.3754,21.69475],"type":"Point"}
}