{
  "type": "Feature",
  "properties": {
    "gn:admin1_code":"11",
    "gn:admin2_code":"27.0",
    "gn:asciiname":"Mashogi",
    "gn:country_code":"IN",
    "gn:dem":1177,
    "gn:feature_class":"P",
    "gn:feature_code":"PPL",
    "gn:name":"Mashogi",
    "gn:population":0,
    "gn:timezone":"Asia/Kolkata",
    "iso:country":"IN",
    "wof:name":"Mashogi",
    "wof:placetype":"locality"
},
  "geometry": {"coordinates":[76.82271999999998,31.48543],"type":"Point"}
}