{
  "type": "Feature",
  "properties": {
    "gn:admin1_code":"34.0",
    "gn:admin2_code":"235.0",
    "gn:asciiname":"Mungia",
    "gn:country_code":"IN",
    "gn:dem":169,
    "gn:feature_class":"P",
    "gn:feature_code":"PPL",
    "gn:name":"Mung\u012b\u0101",
    "gn:population":0,
    "gn:timezone":"Asia/Kolkata",
    "iso:country":"IN",
    "name:ara_x_preferred":[
        "\u0645\u0648\u063a\u0627\u064a\u0646\u0627"
    ],
    "name:arg_x_preferred":[
        "Mungia"
    ],
    "name:cat_x_preferred":[
        "Mungia"
    ],
    "name:ceb_x_preferred":[
        "Mungia"
    ],
    "name:ell_x_preferred":[
        "\u039c\u03bf\u03c5\u03bd\u03b3\u03ba\u03af\u03b1"
    ],
    "name:epo_x_preferred":[
        "Mungio"
    ],
    "name:eus_x_preferred":[
        "Mungia"
    ],
    "name:fra_x_preferred":[
        "Mungia"
    ],
    "name:glg_x_preferred":[
        "Mungia"
    ],
    "name:hun_x_preferred":[
        "Mungia"
    ],
    "name:ita_x_preferred":[
        "Mungia"
    ],
    "name:jpn_x_preferred":[
        "\u30e0\u30f3\u30ae\u30a2"
    ],
    "name:lat_x_preferred":[
        "Mungu\u00eda"
    ],
    "name:msa_x_preferred":[
        "Mungia"
    ],
    "name:nld_x_preferred":[
        "Mungia"
    ],
    "name:oci_x_preferred":[
        "Mungia"
    ],
    "name:pol_x_preferred":[
        "Mungia"
    ],
    "name:por_x_preferred":[
        "Mungu\u00eda"
    ],
    "name:rus_x_preferred":[
        "\u041c\u0443\u043d\u0433\u0438\u044f"
    ],
    "name:spa_x_preferred":[
        "Mungu\u00eda"
    ],
    "name:sqi_x_preferred":[
        "Mungia"
    ],
    "name:swe_x_preferred":[
        "Mungia"
    ],
    "name:ukr_x_preferred":[
        "\u041c\u0443\u043d\u0433\u0456\u044f"
    ],
    "name:uzb_x_preferred":[
        "Mungu\u00eda"
    ],
    "name:war_x_preferred":[
        "Mungia"
    ],
    "name:zho_x_preferred":[
        "\u8499\u5e0c\u4e9a"
    ],
    "wof:name":"Mungia",
    "wof:placetype":"locality"
},
  "geometry": {"coordinates":[84.10285,24.52554],"type":"Point"}
}