{
  "type": "Feature",
  "properties": {
    "gn:admin1_code":"21.0",
    "gn:admin2_code":"377",
    "gn:asciiname":"Iswerpur",
    "gn:country_code":"IN",
    "gn:dem":31,
    "gn:feature_class":"P",
    "gn:feature_code":"PPL",
    "gn:name":"Iswerpur",
    "gn:population":0,
    "gn:timezone":"Asia/Kolkata",
    "iso:country":"IN",
    "wof:name":"Iswerpur",
    "wof:placetype":"locality"
},
  "geometry": {"coordinates":[86.7303,21.3503],"type":"Point"}
}