{
  "type": "Feature",
  "properties": {
    "iso:country":"IN",
    "ks:ks_name":"Kurauthi Sagar",
    "ks:ks_pop":957,
    "ks:ks_type":"VILLAGE",
    "ks:ks_uagg_main":0,
    "name:eng_x_preferred":[
        "Kurauthi Sagar"
    ],
    "wof:name":"Kurauthi Sagar",
    "wof:placetype":"neighbourhood",
    "wof:population":957
},
  "geometry": {"coordinates":[82.37851999999999,25.232503],"type":"Point"}
}