{
  "type": "Feature",
  "properties": {
    "gn:admin1_code":"19.0",
    "gn:admin2_code":"573.0",
    "gn:asciiname":"Bolamaranhalli",
    "gn:country_code":"IN",
    "gn:dem":832,
    "gn:feature_class":"P",
    "gn:feature_code":"PPL",
    "gn:name":"Bolam\u0101ranhalli",
    "gn:population":0,
    "gn:timezone":"Asia/Kolkata",
    "iso:country":"IN",
    "wof:name":"Bolamaranhalli",
    "wof:placetype":"locality"
},
  "geometry": {"coordinates":[76.39018,12.8284],"type":"Point"}
}