{
  "type": "Feature",
  "properties": {
    "gn:admin1_code":"19.0",
    "gn:admin2_code":"584.0",
    "gn:asciiname":"Kariyanpalya",
    "gn:country_code":"IN",
    "gn:dem":859,
    "gn:feature_class":"P",
    "gn:feature_code":"PPL",
    "gn:name":"Kariyanp\u0101lya",
    "gn:population":0,
    "gn:timezone":"Asia/Kolkata",
    "iso:country":"IN",
    "wof:name":"Kariyanpalya",
    "wof:placetype":"neighbourhood"
},
  "geometry": {"coordinates":[77.25517000000001,12.93138],"type":"Point"}
}