{
  "type": "Feature",
  "properties": {
    "iso:country":"IN",
    "ks:ks_alt_nam":"philipnagar",
    "ks:ks_name":"Philipnagar",
    "ks:ks_pop":25,
    "ks:ks_type":"HABITATION",
    "name:eng_x_preferred":[
        "Philipnagar"
    ],
    "wof:name":"Philipnagar",
    "wof:placetype":"locality",
    "wof:population":25
},
  "geometry": {"coordinates":[83.46764400000001,18.774442],"type":"Point"}
}