{
  "type": "Feature",
  "properties": {
    "iso:country":"IN",
    "ks:ks_name":"Srinivasapuram",
    "ks:ks_pop":99,
    "ks:ks_type":"HABITATION",
    "name:eng_x_preferred":[
        "Srinivasapuram"
    ],
    "wof:name":"Srinivasapuram",
    "wof:placetype":"locality",
    "wof:population":99
},
  "geometry": {"coordinates":[84.0889,18.501705],"type":"Point"}
}