{
  "type": "Feature",
  "properties": {
    "iso:country":"IN",
    "ks:ks_alt_nam":"Apparajupeta (Old)",
    "ks:ks_name":"Apparajupeta (old)",
    "ks:ks_pop":43,
    "ks:ks_type":"HABITATION",
    "name:eng_x_preferred":[
        "Apparajupeta (old)"
    ],
    "wof:name":"Apparajupeta (old)",
    "wof:placetype":"locality",
    "wof:population":43
},
  "geometry": {"coordinates":[79.052142,14.63866],"type":"Point"}
}