{
  "type": "Feature",
  "properties": {
    "iso:country":"IN",
    "ks:ks_name":"Karoor Ajjibal",
    "ks:ks_pop":322,
    "ks:ks_type":"HABITATION",
    "name:eng_x_preferred":[
        "Karoor Ajjibal"
    ],
    "wof:name":"Karoor Ajjibal",
    "wof:placetype":"locality",
    "wof:population":322
},
  "geometry": {"coordinates":[74.820787,14.531873],"type":"Point"}
}