{
  "type": "Feature",
  "properties": {
    "gn:admin1_code":"36.0",
    "gn:admin2_code":"145.0",
    "gn:asciiname":"Mukhrai",
    "gn:country_code":"IN",
    "gn:dem":186,
    "gn:feature_class":"P",
    "gn:feature_code":"PPL",
    "gn:name":"Mukhr\u0101i",
    "gn:population":0,
    "gn:timezone":"Asia/Kolkata",
    "iso:country":"IN",
    "wof:name":"Mukhrai",
    "wof:placetype":"locality"
},
  "geometry": {"coordinates":[77.49815,27.50925],"type":"Point"}
}