{
  "type": "Feature",
  "properties": {
    "iso:country":"IN",
    "ks:ks_alt_nam":"SAPHI",
    "ks:ks_name":"Saphi",
    "ks:ks_pop":260,
    "ks:ks_type":"HABITATION",
    "name:eng_x_preferred":[
        "Saphi"
    ],
    "wof:name":"Saphi",
    "wof:placetype":"locality",
    "wof:population":260
},
  "geometry": {"coordinates":[85.66901,24.581462],"type":"Point"}
}