{
  "type": "Feature",
  "properties": {
    "gn:admin1_code":"25.0",
    "gn:admin2_code":"631",
    "gn:asciiname":"Andevanapalli",
    "gn:country_code":"IN",
    "gn:dem":828,
    "gn:feature_class":"P",
    "gn:feature_code":"PPL",
    "gn:name":"And\u0113vanapalli",
    "gn:population":0,
    "gn:timezone":"Asia/Kolkata",
    "iso:country":"IN",
    "name:und_x_variant":[
        "And\u0113vanapalli",
        "Andevanahalli"
    ],
    "wof:name":"Andevanapalli",
    "wof:placetype":"locality"
},
  "geometry": {"coordinates":[77.76227,12.46198],"type":"Point"}
}