{
  "type": "Feature",
  "properties": {
    "iso:country":"IN",
    "ks:ks_name":"Gopal Nagar",
    "ks:ks_pop":61,
    "ks:ks_type":"VILLAGE",
    "name:eng_x_preferred":[
        "Gopal Nagar"
    ],
    "wof:name":"Gopal Nagar",
    "wof:placetype":"locality",
    "wof:population":61
},
  "geometry": {"coordinates":[84.512711,25.820373],"type":"Point"}
}