{
  "type": "Feature",
  "properties": {
    "iso:country":"IN",
    "ks:ks_name":"Rajpura",
    "ks:ks_pop":29,
    "ks:ks_type":"HABITATION",
    "name:eng_x_preferred":[
        "Rajpura"
    ],
    "wof:name":"Rajpura",
    "wof:placetype":"locality",
    "wof:population":29
},
  "geometry": {"coordinates":[76.814047,24.023235],"type":"Point"}
}