{
  "type": "Feature",
  "properties": {
    "iso:country":"IN",
    "ks:ks_name":"Gumati",
    "ks:ks_pop":417,
    "ks:ks_type":"HABITATION",
    "name:eng_x_preferred":[
        "Gumati"
    ],
    "wof:name":"Gumati",
    "wof:placetype":"locality",
    "wof:population":417
},
  "geometry": {"coordinates":[79.186797,29.792228],"type":"Point"}
}