{
  "type": "Feature",
  "properties": {
    "iso:country":"IN",
    "ks:ks_name":"Bandhaguda",
    "ks:ks_pop":239,
    "ks:ks_type":"HABITATION",
    "name:eng_x_preferred":[
        "Bandhaguda"
    ],
    "wof:name":"Bandhaguda",
    "wof:placetype":"locality",
    "wof:population":239
},
  "geometry": {"coordinates":[82.91526399999999,18.63445],"type":"Point"}
}