{
  "type": "Feature",
  "properties": {
    "iso:country":"IN",
    "ks:ks_name":"Mukkatti Paisary",
    "ks:ks_pop":118,
    "ks:ks_type":"HABITATION",
    "name:eng_x_preferred":[
        "Mukkatti Paisary"
    ],
    "wof:name":"Mukkatti Paisary",
    "wof:placetype":"locality",
    "wof:population":118
},
  "geometry": {"coordinates":[75.75749999999999,12.409167],"type":"Point"}
}