{
  "type": "Feature",
  "properties": {
    "iso:country":"IN",
    "ks:ks_name":"Gudsakal",
    "ks:ks_pop":40,
    "ks:ks_type":"VILLAGE",
    "name:eng_x_preferred":[
        "Gudsakal"
    ],
    "wof:name":"Gudsakal",
    "wof:placetype":"locality",
    "wof:population":40
},
  "geometry": {"coordinates":[81.043705,19.080659],"type":"Point"}
}