{
  "type": "Feature",
  "properties": {
    "iso:country":"IN",
    "ks:ks_alt_nam":"Trikumar para",
    "ks:ks_name":"Trikumar Para",
    "ks:ks_pop":224,
    "ks:ks_type":"HABITATION",
    "name:eng_x_preferred":[
        "Trikumar Para"
    ],
    "wof:name":"Trikumar Para",
    "wof:placetype":"locality",
    "wof:population":224
},
  "geometry": {"coordinates":[91.797771,23.080399],"type":"Point"}
}