{
  "type": "Feature",
  "properties": {
    "gn:admin1_code":"24.0",
    "gn:admin2_code":"130.0",
    "gn:asciiname":"Akoladar",
    "gn:country_code":"IN",
    "gn:dem":444,
    "gn:feature_class":"P",
    "gn:feature_code":"PPL",
    "gn:name":"Akoladar",
    "gn:population":0,
    "gn:timezone":"Asia/Kolkata",
    "iso:country":"IN",
    "wof:name":"Akoladar",
    "wof:placetype":"locality"
},
  "geometry": {"coordinates":[73.32189,24.29084],"type":"Point"}
}