{
  "type": "Feature",
  "properties": {
    "iso:country":"IN",
    "ks:ks_alt_nam":"Chak D\u012bh\u0101r\u0101m",
    "ks:ks_name":"Chak Diharam",
    "ks:ks_type":"VILLAGE",
    "name:eng_x_preferred":[
        "Chak Diharam"
    ],
    "name:eng_x_variant":[
        "Chak D\u012bh\u0101r\u0101m"
    ],
    "wof:name":"Chak Diharam",
    "wof:placetype":"locality"
},
  "geometry": {"coordinates":[82.032372,25.31119],"type":"Point"}
}