{
  "type": "Feature",
  "properties": {
    "iso:country":"IN",
    "ks:ks_name":"Patal Malla",
    "ks:ks_pop":108,
    "ks:ks_type":"VILLAGE",
    "name:eng_x_preferred":[
        "Patal Malla"
    ],
    "wof:name":"Patal Malla",
    "wof:placetype":"locality",
    "wof:population":108
},
  "geometry": {"coordinates":[79.104131,29.674764],"type":"Point"}
}