{
  "type": "Feature",
  "properties": {
    "iso:country":"IN",
    "ks:ks_alt_nam":"Munshi purwa",
    "ks:ks_name":"Munshi Purwa",
    "ks:ks_pop":183,
    "ks:ks_type":"HABITATION",
    "name:eng_x_preferred":[
        "Munshi Purwa"
    ],
    "wof:name":"Munshi Purwa",
    "wof:placetype":"locality",
    "wof:population":183
},
  "geometry": {"coordinates":[79.889241,26.82472],"type":"Point"}
}