{
  "type": "Feature",
  "properties": {
    "gn:admin1_code":"28.0",
    "gn:admin2_code":"345",
    "gn:asciiname":"Geonkhali",
    "gn:country_code":"IN",
    "gn:dem":10,
    "gn:feature_class":"P",
    "gn:feature_code":"PPL",
    "gn:name":"Geonkh\u0101li",
    "gn:population":0,
    "gn:timezone":"Asia/Kolkata",
    "iso:country":"IN",
    "name:und_x_variant":[
        "Geonkh\u0101li"
    ],
    "wof:name":"Geonkhali",
    "wof:placetype":"locality"
},
  "geometry": {"coordinates":[88.04942,22.20139],"type":"Point"}
}