{
  "type": "Feature",
  "properties": {
    "iso:country":"IN",
    "ks:ks_name":"Poothikagaruvu",
    "ks:ks_pop":44,
    "ks:ks_type":"HABITATION",
    "name:eng_x_preferred":[
        "Poothikagaruvu"
    ],
    "wof:name":"Poothikagaruvu",
    "wof:placetype":"locality",
    "wof:population":44
},
  "geometry": {"coordinates":[82.78518699999999,17.958877],"type":"Point"}
}