{
  "type": "Feature",
  "properties": {
    "gn:admin1_code":"21.0",
    "gn:admin2_code":"398.0",
    "gn:asciiname":"Potumari",
    "gn:country_code":"IN",
    "gn:dem":867,
    "gn:feature_class":"P",
    "gn:feature_code":"PPL",
    "gn:name":"Potumari",
    "gn:population":0,
    "gn:timezone":"Asia/Kolkata",
    "iso:country":"IN",
    "ks:ks_name":"Putmari",
    "ks:ks_pop":80,
    "ks:ks_type":"HABITATION",
    "name:eng_x_preferred":[
        "Putmari"
    ],
    "name:eng_x_variant":[
        "Potumari"
    ],
    "wof:name":"Putmari",
    "wof:placetype":"locality",
    "wof:population":80
},
  "geometry": {"coordinates":[82.83799,18.953599],"type":"Point"}
}