{
  "type": "Feature",
  "properties": {
    "iso:country":"IN",
    "ks:ks_name":"Budhha Pura",
    "ks:ks_pop":915,
    "ks:ks_type":"HABITATION",
    "name:eng_x_preferred":[
        "Budhha Pura"
    ],
    "wof:name":"Budhha Pura",
    "wof:placetype":"locality",
    "wof:population":915
},
  "geometry": {"coordinates":[77.402241,26.356141],"type":"Point"}
}