{
  "type": "Feature",
  "properties": {
    "iso:country":"IN",
    "ks:ks_name":"Kalchunda",
    "ks:ks_pop":391,
    "ks:ks_type":"VILLAGE",
    "name:eng_x_preferred":[
        "Kalchunda"
    ],
    "wof:name":"Kalchunda",
    "wof:placetype":"locality",
    "wof:population":391
},
  "geometry": {"coordinates":[79.40400699999999,29.961797],"type":"Point"}
}