{
  "type": "Feature",
  "properties": {
    "iso:country":"IN",
    "ks:ks_alt_nam":"SUKVASIPARA",
    "ks:ks_name":"Sukvasipara",
    "ks:ks_pop":238,
    "ks:ks_type":"HABITATION",
    "name:eng_x_preferred":[
        "Sukvasipara"
    ],
    "wof:name":"Sukvasipara",
    "wof:placetype":"locality",
    "wof:population":238
},
  "geometry": {"coordinates":[83.597026,22.550823],"type":"Point"}
}