{
  "type": "Feature",
  "properties": {
    "gn:admin1_code":"36.0",
    "gn:admin2_code":"142",
    "gn:asciiname":"Arnia Khurd",
    "gn:country_code":"IN",
    "gn:dem":198,
    "gn:feature_class":"P",
    "gn:feature_code":"PPL",
    "gn:name":"Arnia Khurd",
    "gn:population":0,
    "gn:timezone":"Asia/Kolkata",
    "iso:country":"IN",
    "name:und_x_variant":[
        "Arnia",
        "Arnia Khurd"
    ],
    "wof:name":"Arnia Khurd",
    "wof:placetype":"locality"
},
  "geometry": {"coordinates":[77.91856999999997,28.13466],"type":"Point"}
}