{
  "type": "Feature",
  "properties": {
    "iso:country":"IN",
    "ks:ks_name":"Kia",
    "ks:ks_pop":2480,
    "ks:ks_type":"VILLAGE",
    "ks:ks_uagg_main":0,
    "name:eng_x_preferred":[
        "Kia"
    ],
    "wof:name":"Kia",
    "wof:placetype":"neighbourhood",
    "wof:population":2480
},
  "geometry": {"coordinates":[87.475463,21.867884],"type":"Point"}
}