{
  "type": "Feature",
  "properties": {
    "iso:country":"IN",
    "ks:ks_name":"Madavaram",
    "ks:ks_pop":222,
    "ks:ks_type":"HABITATION",
    "name:eng_x_preferred":[
        "Madavaram"
    ],
    "wof:name":"Madavaram",
    "wof:placetype":"locality",
    "wof:population":222
},
  "geometry": {"coordinates":[80.209254,13.846934],"type":"Point"}
}