{
  "type": "Feature",
  "properties": {
    "gn:admin1_code":"21",
    "gn:admin2_code":"396.0",
    "gn:asciiname":"Penjaballi",
    "gn:country_code":"IN",
    "gn:dem":683,
    "gn:feature_class":"P",
    "gn:feature_code":"PPL",
    "gn:name":"Penjaballi",
    "gn:population":0,
    "gn:timezone":"Asia/Kolkata",
    "iso:country":"IN",
    "wof:name":"Penjaballi",
    "wof:placetype":"locality"
},
  "geometry": {"coordinates":[83.42053,19.64097000000001],"type":"Point"}
}