{
  "type": "Feature",
  "properties": {
    "gn:admin1_code":"11.0",
    "gn:admin2_code":"32.0",
    "gn:asciiname":"Piplat",
    "gn:country_code":"IN",
    "gn:dem":1550,
    "gn:feature_class":"P",
    "gn:feature_code":"PPL",
    "gn:name":"Pipl\u0101t",
    "gn:population":0,
    "gn:timezone":"Asia/Kolkata",
    "iso:country":"IN",
    "wof:name":"Piplat",
    "wof:placetype":"locality"
},
  "geometry": {"coordinates":[77.54403000000001,30.606],"type":"Point"}
}