{
  "type": "Feature",
  "properties": {
    "iso:country":"IN",
    "ks:ks_name":"Bariyarpur",
    "ks:ks_pop":1845,
    "ks:ks_type":"VILLAGE",
    "ks:ks_uagg_main":0,
    "name:eng_x_preferred":[
        "Bariyarpur"
    ],
    "wof:name":"Bariyarpur",
    "wof:placetype":"neighbourhood",
    "wof:population":1845
},
  "geometry": {"coordinates":[86.77656899999999,24.048485],"type":"Point"}
}