{
  "type": "Feature",
  "properties": {
    "iso:country":"IN",
    "ks:ks_name":"Tikandewasti",
    "ks:ks_pop":224,
    "ks:ks_type":"HABITATION",
    "name:eng_x_preferred":[
        "Tikandewasti"
    ],
    "wof:name":"Tikandewasti",
    "wof:placetype":"locality",
    "wof:population":224
},
  "geometry": {"coordinates":[73.99985,19.558294],"type":"Point"}
}