{
  "type": "Feature",
  "properties": {
    "iso:country":"IN",
    "ks:ks_name":"Karvadi Road Vasti",
    "ks:ks_pop":304,
    "ks:ks_type":"HABITATION",
    "name:eng_x_preferred":[
        "Karvadi Road Vasti"
    ],
    "wof:name":"Karvadi Road Vasti",
    "wof:placetype":"locality",
    "wof:population":304
},
  "geometry": {"coordinates":[74.79494099999999,19.469708],"type":"Point"}
}