{
  "type": "Feature",
  "properties": {
    "gn:admin1_code":"25.0",
    "gn:admin2_code":"631.0",
    "gn:asciiname":"Gangasandiram",
    "gn:country_code":"IN",
    "gn:dem":737,
    "gn:feature_class":"P",
    "gn:feature_code":"PPL",
    "gn:name":"Gangasandiram",
    "gn:population":0,
    "gn:timezone":"Asia/Kolkata",
    "iso:country":"IN",
    "ks:ks_name":"Gangasandiram",
    "ks:ks_pop":330,
    "ks:ks_type":"HABITATION",
    "name:eng_x_preferred":[
        "Gangasandiram"
    ],
    "wof:name":"Gangasandiram",
    "wof:placetype":"locality",
    "wof:population":330
},
  "geometry": {"coordinates":[78.035826,12.733396],"type":"Point"}
}