{
  "type": "Feature",
  "properties": {
    "iso:country":"IN",
    "ks:ks_name":"Kettuvalasai",
    "ks:ks_pop":896,
    "ks:ks_type":"HABITATION",
    "ks:ks_uagg_main":0,
    "name:eng_x_preferred":[
        "Kettuvalasai"
    ],
    "wof:name":"Kettuvalasai",
    "wof:placetype":"neighbourhood",
    "wof:population":896
},
  "geometry": {"coordinates":[79.01221,9.309317],"type":"Point"}
}