{
  "type": "Feature",
  "properties": {
    "gn:admin1_code":"34.0",
    "gn:admin2_code":"220.0",
    "gn:asciiname":"Kiratpur Rajaram",
    "gn:country_code":"IN",
    "gn:dem":57,
    "gn:feature_class":"P",
    "gn:feature_code":"PPL",
    "gn:name":"Kiratpur R\u0101j\u0101r\u0101m",
    "gn:population":0,
    "gn:timezone":"Asia/Kolkata",
    "iso:country":"IN",
    "ks:ks_name":"Kiratpur Raja Ram",
    "ks:ks_pop":2360,
    "ks:ks_type":"VILLAGE",
    "name:eng_x_preferred":[
        "Kiratpur Raja Ram"
    ],
    "name:eng_x_variant":[
        "Kiratpur Rajaram"
    ],
    "wof:name":"Kiratpur Raja Ram",
    "wof:placetype":"locality",
    "wof:population":2360
},
  "geometry": {"coordinates":[85.289912,25.858488],"type":"Point"}
}