{
  "type": "Feature",
  "properties": {
    "iso:country":"IN",
    "ks:ks_name":"Haldicha Kana",
    "ks:ks_pop":246,
    "ks:ks_type":"HABITATION",
    "name:eng_x_preferred":[
        "Haldicha Kana"
    ],
    "wof:name":"Haldicha Kana",
    "wof:placetype":"locality",
    "wof:population":246
},
  "geometry": {"coordinates":[73.860011,15.920045],"type":"Point"}
}