{
  "type": "Feature",
  "properties": {
    "gn:admin1_code":"24.0",
    "gn:admin2_code":"118.0",
    "gn:asciiname":"Nimbara",
    "gn:country_code":"IN",
    "gn:dem":267,
    "gn:feature_class":"P",
    "gn:feature_code":"PPL",
    "gn:name":"Nimb\u0101ra",
    "gn:population":0,
    "gn:timezone":"Asia/Kolkata",
    "iso:country":"IN",
    "wof:name":"Nimbara",
    "wof:placetype":"neighbourhood"
},
  "geometry": {"coordinates":[73.44829,25.5441],"type":"Point"}
}