{
  "type": "Feature",
  "properties": {
    "iso:country":"IN",
    "ks:ks_name":"Ghata Ki Nal",
    "ks:ks_pop":903,
    "ks:ks_type":"VILLAGE",
    "name:eng_x_preferred":[
        "Ghata Ki Nal"
    ],
    "wof:name":"Ghata Ki Nal",
    "wof:placetype":"locality",
    "wof:population":903
},
  "geometry": {"coordinates":[74.493889,23.643189],"type":"Point"}
}