{
  "type": "Feature",
  "properties": {
    "gn:admin1_code":"2.0",
    "gn:admin2_code":"550.0",
    "gn:asciiname":"Gollapeta",
    "gn:country_code":"IN",
    "gn:dem":55,
    "gn:feature_class":"P",
    "gn:feature_code":"PPL",
    "gn:name":"Gollapeta",
    "gn:population":0,
    "gn:timezone":"Asia/Kolkata",
    "iso:country":"IN",
    "name:und_x_variant":[
        "Ras\u016bl\u0101b\u0101d"
    ],
    "wof:name":"Gollapeta",
    "wof:placetype":"locality"
},
  "geometry": {"coordinates":[79.70899,14.76302],"type":"Point"}
}