{
  "type": "Feature",
  "properties": {
    "iso:country":"IN",
    "ks:ks_name":"Palod",
    "ks:ks_pop":3922,
    "ks:ks_type":"VILLAGE",
    "ks:ks_uagg_main":0,
    "name:eng_x_preferred":[
        "Palod"
    ],
    "wof:name":"Palod",
    "wof:placetype":"neighbourhood",
    "wof:population":3922
},
  "geometry": {"coordinates":[72.962028,21.393389],"type":"Point"}
}