{
  "type": "Feature",
  "properties": {
    "iso:country":"IN",
    "ks:ks_name":"Banihari",
    "ks:ks_pop":990,
    "ks:ks_type":"VILLAGE",
    "name:eng_x_preferred":[
        "Banihari"
    ],
    "wof:name":"Banihari",
    "wof:placetype":"locality",
    "wof:population":990
},
  "geometry": {"coordinates":[88.603087,25.426203],"type":"Point"}
}