{
  "type": "Feature",
  "properties": {
    "iso:country":"IN",
    "ks:ks_name":"Konikhurd",
    "ks:ks_pop":1767,
    "ks:ks_type":"HABITATION",
    "name:eng_x_preferred":[
        "Konikhurd"
    ],
    "wof:name":"Konikhurd",
    "wof:placetype":"locality",
    "wof:population":1767
},
  "geometry": {"coordinates":[81.799628,24.996149],"type":"Point"}
}