{
  "type": "Feature",
  "properties": {
    "iso:country":"IN",
    "ks:ks_alt_nam":"KACHARWA",
    "ks:ks_name":"Kacharwa",
    "ks:ks_pop":540,
    "ks:ks_type":"HABITATION",
    "name:eng_x_preferred":[
        "Kacharwa"
    ],
    "wof:name":"Kacharwa",
    "wof:placetype":"locality",
    "wof:population":540
},
  "geometry": {"coordinates":[83.49097399999999,24.371189],"type":"Point"}
}