{
  "type": "Feature",
  "properties": {
    "iso:country":"IN",
    "ks:ks_name":"Tilagadia",
    "ks:ks_pop":442,
    "ks:ks_type":"VILLAGE",
    "name:eng_x_preferred":[
        "Tilagadia"
    ],
    "wof:name":"Tilagadia",
    "wof:placetype":"locality",
    "wof:population":442
},
  "geometry": {"coordinates":[86.678624,22.05761],"type":"Point"}
}