{
  "type": "Feature",
  "properties": {
    "gn:admin1_code":"17",
    "gn:admin2_code":"279.0",
    "gn:asciiname":"Sakok",
    "gn:country_code":"IN",
    "gn:dem":1282,
    "gn:feature_class":"P",
    "gn:feature_code":"PPL",
    "gn:name":"Sakok",
    "gn:population":0,
    "gn:timezone":"Asia/Kolkata",
    "iso:country":"IN",
    "wof:name":"Sakok",
    "wof:placetype":"locality"
},
  "geometry": {"coordinates":[94.31326,24.87418],"type":"Point"}
}