{
  "type": "Feature",
  "properties": {
    "iso:country":"IN",
    "ks:ks_name":"Gira",
    "ks:ks_pop":1895,
    "ks:ks_type":"VILLAGE",
    "name:eng_x_preferred":[
        "Gira"
    ],
    "wof:name":"Gira",
    "wof:placetype":"locality",
    "wof:population":1895
},
  "geometry": {"coordinates":[71.26106900000001,24.814253],"type":"Point"}
}