{
  "type": "Feature",
  "properties": {
    "gn:admin1_code":"23.0",
    "gn:admin2_code":"35.0",
    "gn:asciiname":"Kalara",
    "gn:country_code":"IN",
    "gn:dem":534,
    "gn:feature_class":"P",
    "gn:feature_code":"PPL",
    "gn:name":"Kal\u0101ra",
    "gn:population":0,
    "gn:timezone":"Asia/Kolkata",
    "iso:country":"IN",
    "name:ben_x_preferred":[
        "\u0995\u09cb\u09b2\u09a1\u09bc\u09be"
    ],
    "name:bpy_x_preferred":[
        "\u0995\u09be\u09b2\u09be\u09b0\u09be"
    ],
    "name:hif_x_preferred":[
        "Kalara"
    ],
    "name:ita_x_preferred":[
        "Kalara"
    ],
    "name:msa_x_preferred":[
        "Kalara"
    ],
    "name:new_x_preferred":[
        "\u0915\u0932\u0930\u093e"
    ],
    "name:nld_x_preferred":[
        "Kalara"
    ],
    "name:por_x_preferred":[
        "Kalara"
    ],
    "name:vie_x_preferred":[
        "Kalara"
    ],
    "wof:name":"Kalara",
    "wof:placetype":"locality"
},
  "geometry": {"coordinates":[75.81369000000002,32.43048],"type":"Point"}
}