{
  "type": "Feature",
  "properties": {
    "iso:country":"IN",
    "ks:ks_name":"Beekaran",
    "ks:ks_pop":226,
    "ks:ks_type":"VILLAGE",
    "name:eng_x_preferred":[
        "Beekaran"
    ],
    "wof:name":"Beekaran",
    "wof:placetype":"locality",
    "wof:population":226
},
  "geometry": {"coordinates":[75.466148,25.619355],"type":"Point"}
}