{
  "type": "Feature",
  "properties": {
    "iso:country":"IN",
    "ks:ks_name":"Kurkutia",
    "ks:ks_pop":274,
    "ks:ks_type":"HABITATION",
    "name:eng_x_preferred":[
        "Kurkutia"
    ],
    "wof:name":"Kurkutia",
    "wof:placetype":"locality",
    "wof:population":274
},
  "geometry": {"coordinates":[87.183689,22.997854],"type":"Point"}
}