{
  "type": "Feature",
  "properties": {
    "iso:country":"IN",
    "ks:ks_name":"Pagewadi",
    "ks:ks_pop":148,
    "ks:ks_type":"HABITATION",
    "name:eng_x_preferred":[
        "Pagewadi"
    ],
    "wof:name":"Pagewadi",
    "wof:placetype":"locality",
    "wof:population":148
},
  "geometry": {"coordinates":[74.02489,18.263348],"type":"Point"}
}