{
  "type": "Feature",
  "properties": {
    "iso:country":"IN",
    "ks:ks_name":"Jaynagar",
    "ks:ks_pop":649,
    "ks:ks_type":"VILLAGE",
    "name:eng_x_preferred":[
        "Jaynagar"
    ],
    "wof:name":"Jaynagar",
    "wof:placetype":"locality",
    "wof:population":649
},
  "geometry": {"coordinates":[87.744039,24.408188],"type":"Point"}
}