{
  "type": "Feature",
  "properties": {
    "iso:country":"IN",
    "ks:ks_name":"Bagada",
    "ks:ks_pop":546,
    "ks:ks_type":"VILLAGE",
    "name:eng_x_preferred":[
        "Bagada"
    ],
    "wof:name":"Bagada",
    "wof:placetype":"locality",
    "wof:population":546
},
  "geometry": {"coordinates":[87.236126,21.58819],"type":"Point"}
}