{
  "type": "Feature",
  "properties": {
    "iso:country":"IN",
    "ks:ks_name":"Kakkihalli",
    "ks:ks_pop":468,
    "ks:ks_type":"VILLAGE",
    "name:eng_x_preferred":[
        "Kakkihalli"
    ],
    "wof:name":"Kakkihalli",
    "wof:placetype":"locality",
    "wof:population":468
},
  "geometry": {"coordinates":[76.40293200000001,13.099687],"type":"Point"}
}