{
  "type": "Feature",
  "properties": {
    "iso:country":"IN",
    "ks:ks_name":"Kairabani",
    "ks:ks_pop":61,
    "ks:ks_type":"VILLAGE",
    "name:eng_x_preferred":[
        "Kairabani"
    ],
    "wof:name":"Kairabani",
    "wof:placetype":"locality",
    "wof:population":61
},
  "geometry": {"coordinates":[87.38574,24.625381],"type":"Point"}
}