{
  "type": "Feature",
  "properties": {
    "iso:country":"IN",
    "ks:ks_name":"Ramachandarapur",
    "ks:ks_pop":2819,
    "ks:ks_type":"VILLAGE",
    "name:eng_x_preferred":[
        "Ramachandarapur"
    ],
    "wof:name":"Ramachandarapur",
    "wof:placetype":"locality",
    "wof:population":2819
},
  "geometry": {"coordinates":[85.494592,20.356805],"type":"Point"}
}