{
  "type": "Feature",
  "properties": {
    "gn:admin1_code":"25.0",
    "gn:admin2_code":"602",
    "gn:asciiname":"Kondakarainattam",
    "gn:country_code":"IN",
    "gn:dem":10,
    "gn:feature_class":"P",
    "gn:feature_code":"PPL",
    "gn:name":"Kondakarainattam",
    "gn:population":0,
    "gn:timezone":"Asia/Kolkata",
    "iso:country":"IN",
    "wof:name":"Kondakarainattam",
    "wof:placetype":"locality"
},
  "geometry": {"coordinates":[80.27459,13.23714],"type":"Point"}
}