{
  "type": "Feature",
  "properties": {
    "iso:country":"IN",
    "ks:ks_name":"Singheswar",
    "ks:ks_pop":1496,
    "ks:ks_type":"VILLAGE",
    "ks:ks_uagg_main":0,
    "name:eng_x_preferred":[
        "Singheswar"
    ],
    "wof:name":"Singheswar",
    "wof:placetype":"neighbourhood",
    "wof:population":1496
},
  "geometry": {"coordinates":[85.215236,19.755283],"type":"Point"}
}