{
  "type": "Feature",
  "properties": {
    "iso:country":"IN",
    "ks:ks_name":"Karmala",
    "ks:ks_pop":199,
    "ks:ks_type":"HABITATION",
    "name:eng_x_preferred":[
        "Karmala"
    ],
    "wof:name":"Karmala",
    "wof:placetype":"locality",
    "wof:population":199
},
  "geometry": {"coordinates":[74.07427,19.086009],"type":"Point"}
}