{
  "type": "Feature",
  "properties": {
    "iso:country":"IN",
    "ks:ks_name":"Kumbarwada",
    "ks:ks_pop":42,
    "ks:ks_type":"HABITATION",
    "ks:ks_uagg_main":0,
    "name:eng_x_preferred":[
        "Kumbarwada"
    ],
    "wof:name":"Kumbarwada",
    "wof:placetype":"neighbourhood",
    "wof:population":42
},
  "geometry": {"coordinates":[74.179779,14.829629],"type":"Point"}
}