{
  "type": "Feature",
  "properties": {
    "iso:country":"IN",
    "ks:ks_name":"Kashipura",
    "ks:ks_pop":78,
    "ks:ks_type":"VILLAGE",
    "name:eng_x_preferred":[
        "Kashipura"
    ],
    "wof:name":"Kashipura",
    "wof:placetype":"locality",
    "wof:population":78
},
  "geometry": {"coordinates":[77.13315799999999,14.171133],"type":"Point"}
}