{
  "type": "Feature",
  "properties": {
    "iso:country":"IN",
    "ks:ks_name":"Kandri",
    "ks:ks_pop":693,
    "ks:ks_type":"VILLAGE",
    "ks:ks_uagg_main":0,
    "name:eng_x_preferred":[
        "Kandri"
    ],
    "wof:name":"Kandri",
    "wof:placetype":"neighbourhood",
    "wof:population":693
},
  "geometry": {"coordinates":[85.110428,23.451043],"type":"Point"}
}