{
  "type": "Feature",
  "properties": {
    "iso:country":"IN",
    "ks:ks_alt_nam":"NITOOHI",
    "ks:ks_name":"Nitoohi",
    "ks:ks_pop":35,
    "ks:ks_type":"HABITATION",
    "ks:ks_uagg_main":0,
    "name:eng_x_preferred":[
        "Nitoohi"
    ],
    "wof:name":"Nitoohi",
    "wof:placetype":"neighbourhood",
    "wof:population":35
},
  "geometry": {"coordinates":[81.66025,27.481795],"type":"Point"}
}