{
  "type": "Feature",
  "properties": {
    "iso:country":"IN",
    "ks:ks_name":"Dhumadar",
    "ks:ks_pop":287,
    "ks:ks_type":"HABITATION",
    "name:eng_x_preferred":[
        "Dhumadar"
    ],
    "wof:name":"Dhumadar",
    "wof:placetype":"locality",
    "wof:population":287
},
  "geometry": {"coordinates":[84.604021,22.441538],"type":"Point"}
}