{
  "type": "Feature",
  "properties": {
    "gn:admin1_code":"11.0",
    "gn:admin2_code":"33.0",
    "gn:asciiname":"Mahori",
    "gn:country_code":"IN",
    "gn:dem":1785,
    "gn:feature_class":"P",
    "gn:feature_code":"PPL",
    "gn:name":"M\u0101hori",
    "gn:population":0,
    "gn:timezone":"Asia/Kolkata",
    "iso:country":"IN",
    "name:fin_x_preferred":[
        "Mohori"
    ],
    "name:tha_x_preferred":[
        "\u0e27\u0e07\u0e21\u0e42\u0e2b\u0e23\u0e35"
    ],
    "wof:name":"Mahori",
    "wof:placetype":"locality"
},
  "geometry": {"coordinates":[77.42261999999999,31.1679],"type":"Point"}
}