{
  "type": "Feature",
  "properties": {
    "gn:admin1_code":"34.0",
    "gn:admin2_code":"229.0",
    "gn:asciiname":"Kedu Bigha",
    "gn:country_code":"IN",
    "gn:dem":60,
    "gn:feature_class":"P",
    "gn:feature_code":"PPL",
    "gn:name":"Kedu Bigha",
    "gn:population":0,
    "gn:timezone":"Asia/Kolkata",
    "iso:country":"IN",
    "wof:name":"Kedu Bigha",
    "wof:placetype":"locality"
},
  "geometry": {"coordinates":[85.38741,25.18663],"type":"Point"}
}