{
  "type": "Feature",
  "properties": {
    "iso:country":"IN",
    "ks:ks_name":"14 DOL-B",
    "ks:ks_pop":257,
    "ks:ks_type":"VILLAGE",
    "name:eng_x_preferred":[
        "14 DOL-B"
    ],
    "wof:name":"14 DOL-B",
    "wof:placetype":"locality",
    "wof:population":257
},
  "geometry": {"coordinates":[72.746296,28.85226],"type":"Point"}
}