{
  "type": "Feature",
  "properties": {
    "iso:country":"IN",
    "ks:ks_name":"Farhiya",
    "ks:ks_pop":100,
    "ks:ks_type":"HABITATION",
    "ks:ks_uagg_main":0,
    "name:eng_x_preferred":[
        "Farhiya"
    ],
    "wof:name":"Farhiya",
    "wof:placetype":"neighbourhood",
    "wof:population":100
},
  "geometry": {"coordinates":[81.828503,27.005616],"type":"Point"}
}