{
  "type": "Feature",
  "properties": {
    "gn:admin1_code":"34.0",
    "gn:admin2_code":"219.0",
    "gn:asciiname":"Khudaibagh Bazar",
    "gn:country_code":"IN",
    "gn:dem":61,
    "gn:feature_class":"P",
    "gn:feature_code":"PPL",
    "gn:name":"Khud\u0101\u012bb\u0101gh B\u0101z\u0101r",
    "gn:population":0,
    "gn:timezone":"Asia/Kolkata",
    "iso:country":"IN",
    "wof:name":"Khudaibagh Bazar",
    "wof:placetype":"neighbourhood"
},
  "geometry": {"coordinates":[84.80670000000001,25.88625],"type":"Point"}
}