{
  "type": "Feature",
  "properties": {
    "gn:admin1_code":"34",
    "gn:admin2_code":"234.0",
    "gn:asciiname":"Hardaspur",
    "gn:country_code":"IN",
    "gn:dem":75,
    "gn:feature_class":"P",
    "gn:feature_code":"PPL",
    "gn:name":"Hard\u0101spur",
    "gn:population":0,
    "gn:timezone":"Asia/Kolkata",
    "iso:country":"IN",
    "ks:ks_name":"Hardaspur",
    "ks:ks_pop":720,
    "ks:ks_type":"VILLAGE",
    "name:eng_x_preferred":[
        "Hardaspur"
    ],
    "wof:name":"Hardaspur",
    "wof:placetype":"locality",
    "wof:population":720
},
  "geometry": {"coordinates":[83.935722,25.28481],"type":"Point"}
}