{
  "type": "Feature",
  "properties": {
    "iso:country":"IN",
    "ks:ks_name":"Bishunpur Basant Urf Bishunpur",
    "ks:ks_pop":1108,
    "ks:ks_type":"VILLAGE",
    "name:eng_x_preferred":[
        "Bishunpur Basant Urf Bishunpur"
    ],
    "wof:name":"Bishunpur Basant Urf Bishunpur",
    "wof:placetype":"locality",
    "wof:population":1108
},
  "geometry": {"coordinates":[85.09950600000001,25.997498],"type":"Point"}
}