{
  "type": "Feature",
  "properties": {
    "iso:country":"IN",
    "ks:ks_alt_nam":"Meethale punnad",
    "ks:ks_name":"Meethale Punnad",
    "ks:ks_pop":1950,
    "ks:ks_type":"HABITATION",
    "name:eng_x_preferred":[
        "Meethale Punnad"
    ],
    "wof:name":"Meethale Punnad",
    "wof:placetype":"locality",
    "wof:population":1950
},
  "geometry": {"coordinates":[75.66970600000001,11.956572],"type":"Point"}
}