{
  "type": "Feature",
  "properties": {
    "iso:country":"IN",
    "ks:ks_name":"Battala",
    "ks:ks_pop":815,
    "ks:ks_type":"HABITATION",
    "name:eng_x_preferred":[
        "Battala"
    ],
    "wof:name":"Battala",
    "wof:placetype":"locality",
    "wof:population":815
},
  "geometry": {"coordinates":[89.646489,26.318323],"type":"Point"}
}