{
  "type": "Feature",
  "properties": {
    "iso:country":"IN",
    "ks:ks_name":"Chamunda Nagar",
    "ks:ks_pop":1016,
    "ks:ks_type":"HABITATION",
    "name:eng_x_preferred":[
        "Chamunda Nagar"
    ],
    "wof:name":"Chamunda Nagar",
    "wof:placetype":"locality",
    "wof:population":1016
},
  "geometry": {"coordinates":[71.314336,24.758636],"type":"Point"}
}