{
  "type": "Feature",
  "properties": {
    "iso:country":"IN",
    "ks:ks_name":"Arapothu",
    "ks:ks_pop":27,
    "ks:ks_type":"HABITATION",
    "name:eng_x_preferred":[
        "Arapothu"
    ],
    "wof:name":"Arapothu",
    "wof:placetype":"locality",
    "wof:population":27
},
  "geometry": {"coordinates":[78.600607,9.322205],"type":"Point"}
}