{
  "type": "Feature",
  "properties": {
    "iso:country":"IN",
    "ks:ks_name":"Indira Colony",
    "ks:ks_pop":234,
    "ks:ks_type":"HABITATION",
    "name:eng_x_preferred":[
        "Indira Colony"
    ],
    "wof:name":"Indira Colony",
    "wof:placetype":"locality",
    "wof:population":234
},
  "geometry": {"coordinates":[79.033328,10.243465],"type":"Point"}
}