{
  "type": "Feature",
  "properties": {
    "iso:country":"IN",
    "ks:ks_name":"Uksi",
    "ks:ks_type":"VILLAGE",
    "name:eng_x_preferred":[
        "Uksi"
    ],
    "wof:name":"Uksi",
    "wof:placetype":"locality"
},
  "geometry": {"coordinates":[78.91415000000001,28.590141],"type":"Point"}
}