{
  "type": "Feature",
  "properties": {
    "gn:admin1_code":"39.0",
    "gn:admin2_code":"66.0",
    "gn:asciiname":"Dola",
    "gn:country_code":"IN",
    "gn:dem":1116,
    "gn:feature_class":"P",
    "gn:feature_code":"PPL",
    "gn:name":"Dola",
    "gn:population":0,
    "gn:timezone":"Asia/Kolkata",
    "iso:country":"IN",
    "ks:ks_name":"Dola",
    "ks:ks_pop":169,
    "ks:ks_type":"VILLAGE",
    "name:ben_x_preferred":[
        "\u09a6\u09cb\u09b2\u09be"
    ],
    "name:ceb_x_preferred":[
        "Dola"
    ],
    "name:deu_x_preferred":[
        "Dola"
    ],
    "name:eng_x_preferred":[
        "Dola"
    ],
    "name:fra_x_preferred":[
        "Dola"
    ],
    "name:ind_x_preferred":[
        "Dola"
    ],
    "name:nld_x_preferred":[
        "Dola"
    ],
    "name:pol_x_preferred":[
        "Dola"
    ],
    "name:por_x_preferred":[
        "Dola"
    ],
    "name:rus_x_preferred":[
        "\u0414\u043e\u043b\u044f"
    ],
    "name:swe_x_preferred":[
        "Dola"
    ],
    "name:tur_x_preferred":[
        "Dola"
    ],
    "name:ukr_x_preferred":[
        "\u0414\u043e\u043b\u044f"
    ],
    "name:vie_x_preferred":[
        "Dola"
    ],
    "wof:name":"Dola",
    "wof:placetype":"locality",
    "wof:population":169
},
  "geometry": {"coordinates":[79.311577,29.441862],"type":"Point"}
}