{
  "type": "Feature",
  "properties": {
    "gn:admin1_code":"40",
    "gn:admin2_code":"538.0",
    "gn:asciiname":"Pulsumamdi",
    "gn:country_code":"IN",
    "gn:dem":652,
    "gn:feature_class":"P",
    "gn:feature_code":"PPL",
    "gn:name":"Pulsum\u0101mdi",
    "gn:population":0,
    "gn:timezone":"Asia/Kolkata",
    "iso:country":"IN",
    "wof:name":"Pulsumamdi",
    "wof:placetype":"locality"
},
  "geometry": {"coordinates":[78.06511,17.0859],"type":"Point"}
}