{
  "type": "Feature",
  "properties": {
    "iso:country":"IN",
    "ks:ks_name":"Gavkarwadi",
    "ks:ks_pop":306,
    "ks:ks_type":"HABITATION",
    "name:eng_x_preferred":[
        "Gavkarwadi"
    ],
    "wof:name":"Gavkarwadi",
    "wof:placetype":"locality",
    "wof:population":306
},
  "geometry": {"coordinates":[73.794873,15.878089],"type":"Point"}
}