{
  "type": "Feature",
  "properties": {
    "iso:country":"IN",
    "ks:ks_alt_nam":"29 APD",
    "ks:ks_name":"29 Apd",
    "ks:ks_pop":283,
    "ks:ks_type":"HABITATION",
    "name:eng_x_preferred":[
        "29 Apd"
    ],
    "wof:name":"29 Apd",
    "wof:placetype":"locality",
    "wof:population":283
},
  "geometry": {"coordinates":[73.185829,29.27718],"type":"Point"}
}