{
  "type": "Feature",
  "properties": {
    "gn:admin1_code":"35",
    "gn:admin2_code":"434.0",
    "gn:asciiname":"Seogarh",
    "gn:country_code":"IN",
    "gn:dem":407,
    "gn:feature_class":"P",
    "gn:feature_code":"PPL",
    "gn:name":"Seogarh",
    "gn:population":0,
    "gn:timezone":"Asia/Kolkata",
    "iso:country":"IN",
    "wof:name":"Seogarh",
    "wof:placetype":"neighbourhood"
},
  "geometry": {"coordinates":[74.8562,23.3534],"type":"Point"}
}