{
  "type": "Feature",
  "properties": {
    "iso:country":"IN",
    "ks:ks_name":"Suriyapalayam Weavers Colony",
    "ks:ks_pop":764,
    "ks:ks_type":"HABITATION",
    "name:eng_x_preferred":[
        "Suriyapalayam Weavers Colony"
    ],
    "wof:name":"Suriyapalayam Weavers Colony",
    "wof:placetype":"locality",
    "wof:population":764
},
  "geometry": {"coordinates":[77.816785,11.364726],"type":"Point"}
}