{
  "type": "Feature",
  "properties": {
    "gn:admin1_code":"19.0",
    "gn:admin2_code":"563.0",
    "gn:asciiname":"Katni",
    "gn:country_code":"IN",
    "gn:dem":9,
    "gn:feature_class":"P",
    "gn:feature_code":"PPL",
    "gn:name":"K\u0101tni",
    "gn:population":0,
    "gn:timezone":"Asia/Kolkata",
    "iso:country":"IN",
    "ks:ks_name":"Katne",
    "ks:ks_pop":209,
    "ks:ks_type":"HABITATION",
    "name:ara_x_preferred":[
        "\u0643\u0627\u062a\u0646\u064a"
    ],
    "name:ben_bn_x_preferred":[
        "\u0995\u09be\u099f\u09a8\u09bf"
    ],
    "name:ben_in_x_preferred":[
        "\u0995\u09be\u099f\u09a8\u09bf"
    ],
    "name:ben_x_preferred":[
        "\u09ae\u09c1\u09b0\u0993\u09af\u09bc\u09be\u09b0\u09be"
    ],
    "name:bih_x_preferred":[
        "\u0915\u091f\u0928\u0940"
    ],
    "name:bpy_x_preferred":[
        "\u09ae\u09c1\u09b0\u09f1\u09be\u09b0\u09be"
    ],
    "name:ceb_x_preferred":[
        "Murw\u0101ra"
    ],
    "name:deu_x_preferred":[
        "Katni"
    ],
    "name:eng_x_preferred":[
        "Katne"
    ],
    "name:eng_x_variant":[
        "Katni"
    ],
    "name:fas_x_preferred":[
        "\u0645\u0648\u0631\u0648\u0627\u0631\u0627"
    ],
    "name:fin_x_preferred":[
        "Katni"
    ],
    "name:fra_x_preferred":[
        "Katni"
    ],
    "name:guj_x_preferred":[
        "\u0a95\u0abe\u0aa4\u0acd\u0aa8\u0ac0"
    ],
    "name:guj_x_variant":[
        "\u0a95\u0a9f\u0aa8\u0ac0"
    ],
    "name:hin_x_preferred":[
        "\u0915\u091f\u0928\u0940"
    ],
    "name:ita_x_preferred":[
        "Murwara"
    ],
    "name:kan_x_preferred":[
        "\u0c95\u0c9f\u0ccd\u0ca8\u0cbf"
    ],
    "name:mal_x_preferred":[
        "\u0d15\u0d1f\u0d4d\u0d28\u0d3f"
    ],
    "name:mar_x_preferred":[
        "\u0915\u091f\u0928\u0940"
    ],
    "name:msa_x_preferred":[
        "Murwara"
    ],
    "name:new_x_preferred":[
        "\u092e\u0941\u0930\u094d\u0935\u093e\u0930\u093e"
    ],
    "name:ori_x_preferred":[
        "\u0b15\u0b1f\u0b28\u0b40"
    ],
    "name:pam_x_preferred":[
        "Katni"
    ],
    "name:pan_x_preferred":[
        "\u0a15\u0a1f\u0a28\u0a40"
    ],
    "name:pol_x_preferred":[
        "Katni"
    ],
    "name:por_x_preferred":[
        "Murwara"
    ],
    "name:san_x_preferred":[
        "\u0915\u091f\u0928\u0940"
    ],
    "name:spa_x_preferred":[
        "Katni"
    ],
    "name:srp_x_preferred":[
        "\u041c\u0443\u0440\u0432\u0430\u0440\u0430"
    ],
    "name:swe_x_preferred":[
        "Murwara"
    ],
    "name:tam_x_preferred":[
        "\u0b95\u0b9f\u0bcd\u0ba9\u0bbf"
    ],
    "name:tel_x_preferred":[
        "\u0c15\u0c1f\u0c4d\u0c28\u0c3f"
    ],
    "name:urd_x_preferred":[
        "\u06a9\u0679\u0646\u06cc"
    ],
    "name:vie_x_preferred":[
        "Murwara"
    ],
    "name:war_x_preferred":[
        "Katni"
    ],
    "name:zho_x_preferred":[
        "\u7a46\u5c14\u74e6\u62c9"
    ],
    "wof:name":"Katne",
    "wof:placetype":"locality",
    "wof:population":209
},
  "geometry": {"coordinates":[74.214974,14.878331],"type":"Point"}
}