{
  "type": "Feature",
  "properties": {
    "gn:admin1_code":"19",
    "gn:admin2_code":"563.0",
    "gn:asciiname":"Haladkatte",
    "gn:country_code":"IN",
    "gn:dem":586,
    "gn:feature_class":"P",
    "gn:feature_code":"PPL",
    "gn:name":"H\u0101ladkatte",
    "gn:population":0,
    "gn:timezone":"Asia/Kolkata",
    "iso:country":"IN",
    "wof:name":"Haladkatte",
    "wof:placetype":"neighbourhood"
},
  "geometry": {"coordinates":[74.90192,14.33843],"type":"Point"}
}