{
  "type": "Feature",
  "properties": {
    "gn:admin1_code":"12.0",
    "gn:admin2_code":"16.0",
    "gn:asciiname":"Pharsial",
    "gn:country_code":"IN",
    "gn:dem":2897,
    "gn:feature_class":"P",
    "gn:feature_code":"PPL",
    "gn:name":"Pharsi\u0101l",
    "gn:population":0,
    "gn:timezone":"Asia/Kolkata",
    "iso:country":"IN",
    "wof:name":"Pharsial",
    "wof:placetype":"locality"
},
  "geometry": {"coordinates":[75.50664999999999,33.28184],"type":"Point"}
}