{
  "type": "Feature",
  "properties": {
    "gn:admin1_code":"16.0",
    "gn:admin2_code":"527.0",
    "gn:asciiname":"Chilarewadi",
    "gn:country_code":"IN",
    "gn:dem":786,
    "gn:feature_class":"P",
    "gn:feature_code":"PPL",
    "gn:name":"Chilarewadi",
    "gn:population":0,
    "gn:timezone":"Asia/Kolkata",
    "iso:country":"IN",
    "wof:name":"Chilarewadi",
    "wof:placetype":"locality"
},
  "geometry": {"coordinates":[74.69110999999999,17.51306],"type":"Point"}
}