{
  "type": "Feature",
  "properties": {
    "iso:country":"IN",
    "ks:ks_name":"Hale Adur",
    "ks:ks_pop":246,
    "ks:ks_type":"HABITATION",
    "name:eng_x_preferred":[
        "Hale Adur"
    ],
    "wof:name":"Hale Adur",
    "wof:placetype":"locality",
    "wof:population":246
},
  "geometry": {"coordinates":[75.65909600000001,13.237765],"type":"Point"}
}