{
  "type": "Feature",
  "properties": {
    "gn:admin1_code":"35",
    "gn:admin2_code":"463.0",
    "gn:asciiname":"Hariharpur",
    "gn:country_code":"IN",
    "gn:dem":348,
    "gn:feature_class":"P",
    "gn:feature_code":"PPL",
    "gn:name":"Hariharpur",
    "gn:population":0,
    "gn:timezone":"Asia/Kolkata",
    "iso:country":"IN",
    "ks:ks_name":"Hariharpur",
    "ks:ks_pop":878,
    "ks:ks_type":"VILLAGE",
    "name:eng_x_preferred":[
        "Hariharpur"
    ],
    "name:fra_x_preferred":[
        "Hariharpur"
    ],
    "name:new_x_preferred":[
        "\u0939\u0930\u093f\u0939\u0930\u092a\u0941\u0930 \u0917\u093e\u0935\u093f\u0938"
    ],
    "name:pol_x_preferred":[
        "Hariharpur"
    ],
    "wof:name":"Hariharpur",
    "wof:placetype":"locality",
    "wof:population":878
},
  "geometry": {"coordinates":[81.968684,24.046965],"type":"Point"}
}