{
  "type": "Feature",
  "properties": {
    "iso:country":"IN",
    "ks:ks_name":"Priloo",
    "ks:ks_pop":370,
    "ks:ks_type":"HABITATION",
    "ks:ks_uagg_main":0,
    "name:eng_x_preferred":[
        "Priloo"
    ],
    "wof:name":"Priloo",
    "wof:placetype":"neighbourhood",
    "wof:population":370
},
  "geometry": {"coordinates":[92.837217,25.877259],"type":"Point"}
}