{
  "type": "Feature",
  "properties": {
    "iso:country":"IN",
    "ks:ks_name":"Patamechla",
    "ks:ks_pop":604,
    "ks:ks_type":"VILLAGE",
    "name:eng_x_preferred":[
        "Patamechla"
    ],
    "wof:name":"Patamechla",
    "wof:placetype":"locality",
    "wof:population":604
},
  "geometry": {"coordinates":[87.095883,22.925746],"type":"Point"}
}