{
  "type": "Feature",
  "properties": {
    "iso:country":"IN",
    "ks:ks_name":"Ippaguda",
    "ks:ks_pop":29,
    "ks:ks_type":"HABITATION",
    "name:eng_x_preferred":[
        "Ippaguda"
    ],
    "wof:name":"Ippaguda",
    "wof:placetype":"locality",
    "wof:population":29
},
  "geometry": {"coordinates":[83.69599100000001,18.770803],"type":"Point"}
}