{
  "type": "Feature",
  "properties": {
    "gn:admin1_code":"10",
    "gn:admin2_code":"73.0",
    "gn:asciiname":"Narwal",
    "gn:country_code":"IN",
    "gn:dem":235,
    "gn:feature_class":"P",
    "gn:feature_code":"PPL",
    "gn:name":"Narw\u0101l",
    "gn:population":0,
    "gn:timezone":"Asia/Kolkata",
    "iso:country":"IN",
    "name:ara_x_preferred":[
        "\u0646\u0627\u0631\u0648\u0627\u0644"
    ],
    "name:ben_bn_x_preferred":[
        "\u09a8\u09be\u09b0\u0993\u09df\u09be\u09b2"
    ],
    "name:ben_in_x_preferred":[
        "\u09a8\u09be\u09b0\u0993\u09df\u09be\u09b2"
    ],
    "name:deu_x_preferred":[
        "Narwal"
    ],
    "name:guj_x_preferred":[
        "\u0aa8\u0abe\u0ab0\u0acd\u0ab5\u0abe\u0ab2"
    ],
    "name:hin_x_preferred":[
        "\u0928\u0930\u0935\u093e\u0932"
    ],
    "name:kan_x_preferred":[
        "\u0ca8\u0cb0\u0ccd\u0cb5\u0cbe\u0cb2\u0ccd"
    ],
    "name:mal_x_preferred":[
        "\u0d28\u0d7c\u0d35\u0d3e\u0d7e"
    ],
    "name:mar_x_preferred":[
        "\u0928\u0930\u0935\u093e\u0932"
    ],
    "name:pan_x_preferred":[
        "\u0a28\u0a30\u0a35\u0a3e\u0a32"
    ],
    "name:tam_x_preferred":[
        "\u0ba8\u0bb0\u0bcd\u0bb5\u0bbe\u0bb2\u0bcd"
    ],
    "name:tel_x_preferred":[
        "\u0c28\u0c3e\u0c30\u0c4d\u0c35\u0c3e\u0c32\u0c4d"
    ],
    "name:urd_x_preferred":[
        "\u0646\u0631\u0648\u0644"
    ],
    "wof:name":"Narwal",
    "wof:placetype":"locality"
},
  "geometry": {"coordinates":[76.46533000000002,29.59621],"type":"Point"}
}