{
  "type": "Feature",
  "properties": {
    "iso:country":"IN",
    "ks:ks_name":"Mesagandhi",
    "ks:ks_pop":127,
    "ks:ks_type":"HABITATION",
    "name:eng_x_preferred":[
        "Mesagandhi"
    ],
    "wof:name":"Mesagandhi",
    "wof:placetype":"locality",
    "wof:population":127
},
  "geometry": {"coordinates":[81.910459,18.647371],"type":"Point"}
}