{
  "type": "Feature",
  "properties": {
    "iso:country":"IN",
    "ks:ks_name":"Kali Khol",
    "ks:ks_pop":762,
    "ks:ks_type":"VILLAGE",
    "name:eng_x_preferred":[
        "Kali Khol"
    ],
    "wof:name":"Kali Khol",
    "wof:placetype":"locality",
    "wof:population":762
},
  "geometry": {"coordinates":[74.985595,25.120108],"type":"Point"}
}