{
  "type": "Feature",
  "properties": {
    "iso:country":"IN",
    "ks:ks_name":"Jothipura",
    "ks:ks_pop":979,
    "ks:ks_type":"VILLAGE",
    "name:eng_x_preferred":[
        "Jothipura"
    ],
    "wof:name":"Jothipura",
    "wof:placetype":"locality",
    "wof:population":979
},
  "geometry": {"coordinates":[77.745276,13.107034],"type":"Point"}
}