{
  "type": "Feature",
  "properties": {
    "iso:country":"IN",
    "ks:ks_alt_nam":"kuravar colony",
    "ks:ks_name":"Kuravar Colony",
    "ks:ks_pop":136,
    "ks:ks_type":"HABITATION",
    "name:eng_x_preferred":[
        "Kuravar Colony"
    ],
    "wof:name":"Kuravar Colony",
    "wof:placetype":"locality",
    "wof:population":136
},
  "geometry": {"coordinates":[78.66951400000001,11.479561],"type":"Point"}
}