{
  "type": "Feature",
  "properties": {
    "iso:country":"IN",
    "ks:ks_alt_nam":"mahato Toli",
    "ks:ks_name":"Mahato Toli",
    "ks:ks_pop":165,
    "ks:ks_type":"HABITATION",
    "ks:ks_uagg_main":0,
    "name:eng_x_preferred":[
        "Mahato Toli"
    ],
    "wof:name":"Mahato Toli",
    "wof:placetype":"neighbourhood",
    "wof:population":165
},
  "geometry": {"coordinates":[85.22480299999999,24.736239],"type":"Point"}
}