{
  "type": "Feature",
  "properties": {
    "gn:admin1_code":"36.0",
    "gn:admin2_code":"140.0",
    "gn:asciiname":"Chandpura",
    "gn:country_code":"IN",
    "gn:dem":213,
    "gn:feature_class":"P",
    "gn:feature_code":"PPL",
    "gn:name":"Chandpura",
    "gn:population":0,
    "gn:timezone":"Asia/Kolkata",
    "iso:country":"IN",
    "ks:ks_name":"Chandpura",
    "ks:ks_pop":477,
    "ks:ks_type":"VILLAGE",
    "name:eng_x_preferred":[
        "Chandpura"
    ],
    "wof:name":"Chandpura",
    "wof:placetype":"locality",
    "wof:population":477
},
  "geometry": {"coordinates":[77.723742,28.68632],"type":"Point"}
}