{
  "type": "Feature",
  "properties": {
    "iso:country":"IN",
    "ks:ks_name":"Mammal",
    "ks:ks_pop":477,
    "ks:ks_type":"HABITATION",
    "name:eng_x_preferred":[
        "Mammal"
    ],
    "wof:name":"Mammal",
    "wof:placetype":"locality",
    "wof:population":477
},
  "geometry": {"coordinates":[77.248167,10.184459],"type":"Point"}
}