{
  "type": "Feature",
  "properties": {
    "iso:country":"IN",
    "ks:ks_alt_nam":"MAIRUNG KURAI PARA",
    "ks:ks_name":"Mairung Kurai Para",
    "ks:ks_pop":498,
    "ks:ks_type":"HABITATION",
    "name:eng_x_preferred":[
        "Mairung Kurai Para"
    ],
    "wof:name":"Mairung Kurai Para",
    "wof:placetype":"locality",
    "wof:population":498
},
  "geometry": {"coordinates":[91.677195,23.970348],"type":"Point"}
}