{
  "type": "Feature",
  "properties": {
    "gn:admin1_code":"38",
    "gn:admin2_code":"362.0",
    "gn:asciiname":"Purnia",
    "gn:country_code":"IN",
    "gn:dem":249,
    "gn:feature_class":"P",
    "gn:feature_code":"PPL",
    "gn:name":"Purnia",
    "gn:population":0,
    "gn:timezone":"Asia/Kolkata",
    "iso:country":"IN",
    "wof:name":"Purnia",
    "wof:placetype":"locality"
},
  "geometry": {"coordinates":[87.13333,24.51667],"type":"Point"}
}