{
  "type": "Feature",
  "properties": {
    "gn:admin1_code":"38.0",
    "gn:admin2_code":"362.0",
    "gn:asciiname":"Daldali",
    "gn:country_code":"IN",
    "gn:dem":165,
    "gn:feature_class":"P",
    "gn:feature_code":"PPL",
    "gn:name":"Daldali",
    "gn:population":0,
    "gn:timezone":"Asia/Kolkata",
    "iso:country":"IN",
    "ks:ks_name":"Daldali",
    "ks:ks_pop":179,
    "ks:ks_type":"VILLAGE",
    "name:eng_x_preferred":[
        "Daldali"
    ],
    "wof:name":"Daldali",
    "wof:placetype":"locality",
    "wof:population":179
},
  "geometry": {"coordinates":[87.56055000000001,24.21706],"type":"Point"}
}