{
  "type": "Feature",
  "properties": {
    "iso:country":"IN",
    "ks:ks_name":"Sriramapuram",
    "ks:ks_pop":204,
    "ks:ks_type":"HABITATION",
    "ks:ks_uagg_main":0,
    "name:eng_x_preferred":[
        "Sriramapuram"
    ],
    "wof:name":"Sriramapuram",
    "wof:placetype":"neighbourhood",
    "wof:population":204
},
  "geometry": {"coordinates":[81.00482700000001,17.018396],"type":"Point"}
}