{
  "type": "Feature",
  "properties": {
    "iso:country":"IN",
    "ks:ks_name":"Palewadi",
    "ks:ks_pop":260,
    "ks:ks_type":"HABITATION",
    "name:eng_x_preferred":[
        "Palewadi"
    ],
    "wof:name":"Palewadi",
    "wof:placetype":"locality",
    "wof:population":260
},
  "geometry": {"coordinates":[73.45694399999999,17.391389],"type":"Point"}
}