{
  "type": "Feature",
  "properties": {
    "iso:country":"IN",
    "ks:ks_name":"Thakurwatari",
    "ks:ks_pop":446,
    "ks:ks_type":"HABITATION",
    "name:eng_x_preferred":[
        "Thakurwatari"
    ],
    "wof:name":"Thakurwatari",
    "wof:placetype":"locality",
    "wof:population":446
},
  "geometry": {"coordinates":[86.457086,24.838924],"type":"Point"}
}