{
  "type": "Feature",
  "properties": {
    "gn:admin1_code":"2.0",
    "gn:admin2_code":"543.0",
    "gn:asciiname":"Nilakanthapuram",
    "gn:country_code":"IN",
    "gn:dem":127,
    "gn:feature_class":"P",
    "gn:feature_code":"PPL",
    "gn:name":"N\u012blakanthapuram",
    "gn:population":0,
    "gn:timezone":"Asia/Kolkata",
    "iso:country":"IN",
    "ks:ks_name":"Neelakantapuram",
    "ks:ks_pop":106,
    "ks:ks_type":"HABITATION",
    "name:eng_x_preferred":[
        "Neelakantapuram"
    ],
    "name:eng_x_variant":[
        "Nilakanthapuram"
    ],
    "wof:name":"Neelakantapuram",
    "wof:placetype":"locality",
    "wof:population":106
},
  "geometry": {"coordinates":[83.60353600000001,18.819722],"type":"Point"}
}