{
  "type": "Feature",
  "properties": {
    "gn:admin1_code":"2.0",
    "gn:admin2_code":"543.0",
    "gn:asciiname":"Nilakanthapuram",
    "gn:country_code":"IN",
    "gn:dem":127,
    "gn:feature_class":"P",
    "gn:feature_code":"PPL",
    "gn:name":"N\u012blakanthapuram",
    "gn:population":0,
    "gn:timezone":"Asia/Kolkata",
    "iso:country":"IN",
    "wof:name":"Nilakanthapuram",
    "wof:placetype":"locality"
},
  "geometry": {"coordinates":[83.60285,18.81958],"type":"Point"}
}