{
  "type": "Feature",
  "properties": {
    "gn:admin1_code":"38",
    "gn:admin2_code":"367.0",
    "gn:asciiname":"Parba",
    "gn:country_code":"IN",
    "gn:dem":246,
    "gn:feature_class":"P",
    "gn:feature_code":"PPL",
    "gn:name":"Parba",
    "gn:population":0,
    "gn:timezone":"Asia/Kolkata",
    "iso:country":"IN",
    "wof:name":"Parba",
    "wof:placetype":"locality"
},
  "geometry": {"coordinates":[84.8528,22.45629],"type":"Point"}
}