{
  "type": "Feature",
  "properties": {
    "gn:admin1_code":"19.0",
    "gn:admin2_code":"578.0",
    "gn:asciiname":"Kaniyanpur",
    "gn:country_code":"IN",
    "gn:dem":946,
    "gn:feature_class":"P",
    "gn:feature_code":"PPL",
    "gn:name":"Kaniyanp\u016br",
    "gn:population":0,
    "gn:timezone":"Asia/Kolkata",
    "iso:country":"IN",
    "wof:name":"Kaniyanpur",
    "wof:placetype":"locality"
},
  "geometry": {"coordinates":[76.66856999999997,11.63558],"type":"Point"}
}