{
  "type": "Feature",
  "properties": {
    "iso:country":"IN",
    "ks:ks_name":"10 SBN",
    "ks:ks_pop":245,
    "ks:ks_type":"VILLAGE",
    "name:eng_x_preferred":[
        "10 SBN"
    ],
    "wof:name":"10 SBN",
    "wof:placetype":"locality",
    "wof:population":245
},
  "geometry": {"coordinates":[74.471391,29.728336],"type":"Point"}
}