{
  "type": "Feature",
  "properties": {
    "iso:country":"IN",
    "ks:ks_name":"Gajalia",
    "ks:ks_pop":141,
    "ks:ks_type":"HABITATION",
    "name:eng_x_preferred":[
        "Gajalia"
    ],
    "wof:name":"Gajalia",
    "wof:placetype":"locality",
    "wof:population":141
},
  "geometry": {"coordinates":[87.285442,22.01813],"type":"Point"}
}