{
  "type": "Feature",
  "properties": {
    "iso:country":"IN",
    "ks:ks_name":"Panigan",
    "ks:ks_pop":249,
    "ks:ks_type":"VILLAGE",
    "name:eng_x_preferred":[
        "Panigan"
    ],
    "wof:name":"Panigan",
    "wof:placetype":"locality",
    "wof:population":249
},
  "geometry": {"coordinates":[82.713454,19.677474],"type":"Point"}
}