{
  "type": "Feature",
  "properties": {
    "iso:country":"IN",
    "ks:ks_name":"Kilakkulam",
    "ks:ks_pop":89,
    "ks:ks_type":"HABITATION",
    "name:eng_x_preferred":[
        "Kilakkulam"
    ],
    "wof:name":"Kilakkulam",
    "wof:placetype":"locality",
    "wof:population":89
},
  "geometry": {"coordinates":[78.53639699999999,9.485327],"type":"Point"}
}