{
  "type": "Feature",
  "properties": {
    "iso:country":"IN",
    "ks:ks_name":"Na Khangia Gaon",
    "ks:ks_pop":645,
    "ks:ks_type":"HABITATION",
    "name:eng_x_preferred":[
        "Na Khangia Gaon"
    ],
    "wof:name":"Na Khangia Gaon",
    "wof:placetype":"locality",
    "wof:population":645
},
  "geometry": {"coordinates":[95.16486500000001,27.357776],"type":"Point"}
}