{
  "type": "Feature",
  "properties": {
    "iso:country":"IN",
    "ks:ks_name":"Rohidaswadi",
    "ks:ks_pop":72,
    "ks:ks_type":"HABITATION",
    "name:eng_x_preferred":[
        "Rohidaswadi"
    ],
    "wof:name":"Rohidaswadi",
    "wof:placetype":"locality",
    "wof:population":72
},
  "geometry": {"coordinates":[73.43404099999999,17.400009],"type":"Point"}
}