{
  "type": "Feature",
  "properties": {
    "gn:admin1_code":"40.0",
    "gn:admin2_code":"534.0",
    "gn:asciiname":"Siddipet",
    "gn:country_code":"IN",
    "gn:dem":174,
    "gn:feature_class":"P",
    "gn:feature_code":"PPL",
    "gn:name":"Siddipet",
    "gn:population":0,
    "gn:timezone":"Asia/Kolkata",
    "iso:country":"IN",
    "name:bpy_x_preferred":[
        "\u09b8\u09bf\u09a6\u09cd\u09a6\u09bf\u09aa\u09c7\u09a4"
    ],
    "name:ceb_x_preferred":[
        "Siddipet"
    ],
    "name:hif_x_preferred":[
        "Siddipet"
    ],
    "name:hin_x_preferred":[
        "\u0938\u093f\u0926\u094d\u0926\u093f\u092a\u0947\u091f"
    ],
    "name:ita_x_preferred":[
        "Siddipet"
    ],
    "name:mlg_x_preferred":[
        "Siddipet"
    ],
    "name:msa_x_preferred":[
        "Siddipet"
    ],
    "name:new_x_preferred":[
        "\u0938\u093f\u0926\u094d\u0926\u093f\u092a\u0947\u091f \u092e\u0923\u094d\u0921\u0932"
    ],
    "name:ori_x_preferred":[
        "\u0b38\u0b3f\u0b26\u0b4d\u0b26\u0b3f\u0b2a\u0b47\u0b1f"
    ],
    "name:pam_x_preferred":[
        "Siddipet"
    ],
    "name:swe_x_preferred":[
        "Siddipet"
    ],
    "name:tel_x_preferred":[
        "\u0c38\u0c3f\u0c26\u0c4d\u0c26\u0c3f\u0c2a\u0c47\u0c1f"
    ],
    "name:urd_x_preferred":[
        "\u0633\u062f\u06cc \u067e\u06cc\u0679"
    ],
    "name:vie_x_preferred":[
        "Siddipet"
    ],
    "name:zho_x_preferred":[
        "\u897f\u5fb7\u8fea\u4f69\u7279"
    ],
    "wof:name":"Siddipet",
    "wof:placetype":"locality"
},
  "geometry": {"coordinates":[79.49422,18.6702],"type":"Point"}
}