{
  "type": "Feature",
  "properties": {
    "gn:admin1_code":"11",
    "gn:admin2_code":"27.0",
    "gn:asciiname":"Gutkar",
    "gn:country_code":"IN",
    "gn:dem":770,
    "gn:feature_class":"P",
    "gn:feature_code":"PPL",
    "gn:name":"Gutkar",
    "gn:population":0,
    "gn:timezone":"Asia/Kolkata",
    "iso:country":"IN",
    "wof:name":"Gutkar",
    "wof:placetype":"locality"
},
  "geometry": {"coordinates":[76.94469000000002,31.65804],"type":"Point"}
}