{
  "type": "Feature",
  "properties": {
    "gn:country":"IN",
    "gn:fcode":"PPL",
    "gn:population":10983,
    "iso:country":"IN",
    "name:azb_x_preferred":[
        "\u0633\u0627\u0631\u0642\u0648\u0631"
    ],
    "name:ceb_x_preferred":[
        "Sarg\u016br"
    ],
    "name:eng_x_preferred":[
        "Sargur"
    ],
    "name:hin_x_preferred":[
        "\u0938\u0930\u0917\u0942\u0930"
    ],
    "name:kan_x_preferred":[
        "\u0cb8\u0cb0\u0c97\u0cc2\u0cb0\u0cc1"
    ],
    "name:nld_x_preferred":[
        "Sargur"
    ],
    "name:swe_x_preferred":[
        "Sarg\u016br"
    ],
    "name:vie_x_preferred":[
        "Kelginmane"
    ],
    "qs:name":"Sarg\u016br",
    "qs:photos_9r":0,
    "qs:photos_sr":0,
    "qs:pop_sr":"6",
    "wof:name":"Sarg\u016br",
    "wof:placetype":"locality",
    "wof:population":10983
},
  "geometry": {"coordinates":[76.41667,11.98333],"type":"Point"}
}