{
  "type": "Feature",
  "properties": {
    "gn:country":"IN",
    "gn:fcode":"PPL",
    "gn:population":10983,
    "iso:country":"IN",
    "name:ceb_x_preferred":[
        "Sarg\u016br"
    ],
    "name:eng_x_preferred":[
        "Sargur"
    ],
    "name:nld_x_preferred":[
        "Sargur"
    ],
    "name:swe_x_preferred":[
        "Sarg\u016br"
    ],
    "name:vie_x_preferred":[
        "Kelginmane"
    ],
    "qs:name":"Sarg\u016br",
    "qs:photos_9r":0,
    "qs:photos_sr":0,
    "qs:pop_sr":"6",
    "wof:name":"Sarg\u016br",
    "wof:placetype":"locality",
    "wof:population":10983
},
  "geometry": {"coordinates":[76.41667,11.98333],"type":"Point"}
}