{
  "type": "Feature",
  "properties": {
    "iso:country":"IN",
    "ks:ks_name":"Kothadi",
    "ks:ks_pop":283,
    "ks:ks_type":"VILLAGE",
    "name:eng_x_preferred":[
        "Kothadi"
    ],
    "wof:name":"Kothadi",
    "wof:placetype":"locality",
    "wof:population":283
},
  "geometry": {"coordinates":[74.676456,22.398593],"type":"Point"}
}