{
  "type": "Feature",
  "properties": {
    "gn:admin1_code":"12.0",
    "gn:admin2_code":"004",
    "gn:asciiname":"Kakshar",
    "gn:country_code":"IN",
    "gn:dem":2957,
    "gn:feature_class":"P",
    "gn:feature_code":"PPL",
    "gn:name":"Kakshar",
    "gn:population":0,
    "gn:timezone":"Asia/Kolkata",
    "iso:country":"IN",
    "wof:name":"Kakshar",
    "wof:placetype":"locality"
},
  "geometry": {"coordinates":[75.98153000000001,34.58308],"type":"Point"}
}