{
  "type": "Feature",
  "properties": {
    "iso:country":"IN",
    "ks:ks_name":"Illangudi",
    "ks:ks_pop":135,
    "ks:ks_type":"HABITATION",
    "name:eng_x_preferred":[
        "Illangudi"
    ],
    "wof:name":"Illangudi",
    "wof:placetype":"locality",
    "wof:population":135
},
  "geometry": {"coordinates":[78.94653,10.131993],"type":"Point"}
}