{
  "type": "Feature",
  "properties": {
    "iso:country":"IN",
    "ks:ks_name":"Pokrasar",
    "ks:ks_pop":856,
    "ks:ks_type":"VILLAGE",
    "name:eng_x_preferred":[
        "Pokrasar"
    ],
    "wof:name":"Pokrasar",
    "wof:placetype":"locality",
    "wof:population":856
},
  "geometry": {"coordinates":[71.20121899999999,25.415419],"type":"Point"}
}