{
  "type": "Feature",
  "properties": {
    "iso:country":"IN",
    "ks:ks_alt_nam":"D\u0101ru\u0101r\u0101",
    "ks:ks_name":"Daruara",
    "ks:ks_pop":394,
    "ks:ks_type":"VILLAGE",
    "name:eng_x_preferred":[
        "Daruara"
    ],
    "name:eng_x_variant":[
        "D\u0101ru\u0101r\u0101"
    ],
    "wof:name":"Daruara",
    "wof:placetype":"locality",
    "wof:population":394
},
  "geometry": {"coordinates":[85.700969,23.148745],"type":"Point"}
}