{
  "type": "Feature",
  "properties": {
    "iso:country":"IN",
    "ks:ks_name":"Goja Bandha",
    "ks:ks_pop":905,
    "ks:ks_type":"VILLAGE",
    "ks:ks_uagg_main":0,
    "name:eng_x_preferred":[
        "Goja Bandha"
    ],
    "wof:name":"Goja Bandha",
    "wof:placetype":"neighbourhood",
    "wof:population":905
},
  "geometry": {"coordinates":[86.604513,20.381319],"type":"Point"}
}