{
  "type": "Feature",
  "properties": {
    "iso:country":"IN",
    "ks:ks_name":"Jaspura",
    "ks:ks_pop":312,
    "ks:ks_type":"VILLAGE",
    "name:eng_x_preferred":[
        "Jaspura"
    ],
    "wof:name":"Jaspura",
    "wof:placetype":"locality",
    "wof:population":312
},
  "geometry": {"coordinates":[73.89605299999999,24.448894],"type":"Point"}
}