{
  "type": "Feature",
  "properties": {
    "iso:country":"IN",
    "ks:ks_name":"Balaji Nagar",
    "ks:ks_pop":1579,
    "ks:ks_type":"VILLAGE",
    "name:eng_x_preferred":[
        "Balaji Nagar"
    ],
    "wof:name":"Balaji Nagar",
    "wof:placetype":"locality",
    "wof:population":1579
},
  "geometry": {"coordinates":[73.074614,26.184208],"type":"Point"}
}