{
  "type": "Feature",
  "properties": {
    "iso:country":"IN",
    "ks:ks_name":"Rarua",
    "ks:ks_pop":130,
    "ks:ks_type":"VILLAGE",
    "name:eng_x_preferred":[
        "Rarua"
    ],
    "wof:name":"Rarua",
    "wof:placetype":"locality",
    "wof:population":130
},
  "geometry": {"coordinates":[80.27799899999999,28.313072],"type":"Point"}
}