{
  "type": "Feature",
  "properties": {
    "iso:country":"IN",
    "ks:ks_name":"Panawadi",
    "ks:ks_pop":19,
    "ks:ks_type":"HABITATION",
    "name:eng_x_preferred":[
        "Panawadi"
    ],
    "wof:name":"Panawadi",
    "wof:placetype":"locality",
    "wof:population":19
},
  "geometry": {"coordinates":[75.39,12.444722],"type":"Point"}
}