{
  "type": "Feature",
  "properties": {
    "gn:admin1_code":"36.0",
    "gn:admin2_code":"137.0",
    "gn:asciiname":"Dagrauli",
    "gn:country_code":"IN",
    "gn:dem":197,
    "gn:feature_class":"P",
    "gn:feature_code":"PPL",
    "gn:name":"Dagrauli",
    "gn:population":0,
    "gn:timezone":"Asia/Kolkata",
    "iso:country":"IN",
    "ks:ks_name":"Dagrouli",
    "ks:ks_pop":898,
    "ks:ks_type":"VILLAGE",
    "ks:ks_uagg_main":0,
    "name:eng_x_preferred":[
        "Dagrouli"
    ],
    "wof:name":"Dagrouli",
    "wof:placetype":"locality",
    "wof:population":898
},
  "geometry": {"coordinates":[78.26845,28.691995],"type":"Point"}
}