{
  "type": "Feature",
  "properties": {
    "gn:admin1_code":"11.0",
    "gn:admin2_code":"32.0",
    "gn:asciiname":"Ghatol",
    "gn:country_code":"IN",
    "gn:dem":1542,
    "gn:feature_class":"P",
    "gn:feature_code":"PPL",
    "gn:name":"Ghatol",
    "gn:population":0,
    "gn:timezone":"Asia/Kolkata",
    "iso:country":"IN",
    "wof:name":"Ghatol",
    "wof:placetype":"locality"
},
  "geometry": {"coordinates":[77.64033000000001,30.68709],"type":"Point"}
}