{
  "type": "Feature",
  "properties": {
    "iso:country":"IN",
    "ks:ks_alt_nam":"CHONDRO BASA",
    "ks:ks_name":"Chondro Basa",
    "ks:ks_pop":176,
    "ks:ks_type":"HABITATION",
    "name:eng_x_preferred":[
        "Chondro Basa"
    ],
    "wof:name":"Chondro Basa",
    "wof:placetype":"locality",
    "wof:population":176
},
  "geometry": {"coordinates":[85.708246,22.184631],"type":"Point"}
}