{
  "type": "Feature",
  "properties": {
    "iso:country":"IN",
    "ks:ks_name":"Mundawada",
    "ks:ks_pop":98,
    "ks:ks_type":"HABITATION",
    "name:eng_x_preferred":[
        "Mundawada"
    ],
    "wof:name":"Mundawada",
    "wof:placetype":"locality",
    "wof:population":98
},
  "geometry": {"coordinates":[74.77230299999999,15.058187],"type":"Point"}
}