{
  "type": "Feature",
  "properties": {
    "gn:admin1_code":"02",
    "gn:admin2_code":"554.0",
    "gn:asciiname":"Satyavedu",
    "gn:country_code":"IN",
    "gn:dem":54,
    "gn:feature_class":"P",
    "gn:feature_code":"PPL",
    "gn:name":"Satyavedu",
    "gn:population":0,
    "gn:timezone":"Asia/Kolkata",
    "iso:country":"IN",
    "name:und_x_variant":[
        "Sattivedu",
        "Satyavedu"
    ],
    "wof:name":"Satyavedu",
    "wof:placetype":"locality"
},
  "geometry": {"coordinates":[79.95774,13.43661],"type":"Point"}
}