{
  "type": "Feature",
  "properties": {
    "gn:admin1_code":"02",
    "gn:admin2_code":"554.0",
    "gn:asciiname":"Satyavedu",
    "gn:country_code":"IN",
    "gn:dem":54,
    "gn:feature_class":"P",
    "gn:feature_code":"PPL",
    "gn:name":"Satyavedu",
    "gn:population":0,
    "gn:timezone":"Asia/Kolkata",
    "iso:country":"IN",
    "name:new_x_preferred":[
        "\u0938\u0924\u094d\u092f\u0935\u0940\u0921\u0941 \u092e\u0923\u094d\u0921\u0932"
    ],
    "name:pam_x_preferred":[
        "Satyavedu"
    ],
    "name:tam_x_preferred":[
        "\u0b9a\u0ba4\u0bcd\u0ba4\u0bbf\u0baf\u0bb5\u0bc7\u0b9f\u0bc1"
    ],
    "name:tel_x_preferred":[
        "\u0c38\u0c24\u0c4d\u0c2f\u0c35\u0c47\u0c21\u0c41"
    ],
    "name:tgl_x_preferred":[
        "Satyavedu"
    ],
    "name:und_x_variant":[
        "Sattivedu"
    ],
    "name:urd_x_preferred":[
        "\u0633\u062a\u06cc\u0627\u0648\u06cc\u0688\u0648"
    ],
    "name:vie_x_preferred":[
        "Satyavedu"
    ],
    "wof:name":"Satyavedu",
    "wof:placetype":"locality"
},
  "geometry": {"coordinates":[79.95774,13.43661],"type":"Point"}
}