{
  "type": "Feature",
  "properties": {
    "iso:country":"IN",
    "ks:ks_name":"Damor Faliya",
    "ks:ks_pop":501,
    "ks:ks_type":"HABITATION",
    "ks:ks_uagg_main":0,
    "name:eng_x_preferred":[
        "Damor Faliya"
    ],
    "wof:name":"Damor Faliya",
    "wof:placetype":"neighbourhood",
    "wof:population":501
},
  "geometry": {"coordinates":[73.785217,22.850417],"type":"Point"}
}