{
  "type": "Feature",
  "properties": {
    "iso:country":"IN",
    "ks:ks_name":"Majdia",
    "ks:ks_pop":1049,
    "ks:ks_type":"VILLAGE",
    "ks:ks_uagg_main":0,
    "name:eng_x_preferred":[
        "Majdia"
    ],
    "wof:name":"Majdia",
    "wof:placetype":"neighbourhood",
    "wof:population":1049
},
  "geometry": {"coordinates":[91.43465999999999,26.427532],"type":"Point"}
}