{
  "type": "Feature",
  "properties": {
    "iso:country":"IN",
    "ks:ks_name":"Kaligaon",
    "ks:ks_pop":1307,
    "ks:ks_type":"VILLAGE",
    "ks:ks_uagg_main":0,
    "name:eng_x_preferred":[
        "Kaligaon"
    ],
    "wof:name":"Kaligaon",
    "wof:placetype":"locality",
    "wof:population":1307
},
  "geometry": {"coordinates":[80.098386,29.406358],"type":"Point"}
}