{
  "type": "Feature",
  "properties": {
    "gn:admin1_code":"11",
    "gn:admin2_code":"24.0",
    "gn:asciiname":"Nera",
    "gn:country_code":"IN",
    "gn:dem":571,
    "gn:feature_class":"P",
    "gn:feature_code":"PPL",
    "gn:name":"Nera",
    "gn:population":0,
    "gn:timezone":"Asia/Kolkata",
    "iso:country":"IN",
    "name:bul_x_preferred":[
        "\u041d\u0435\u0440\u0430"
    ],
    "name:ceb_x_preferred":[
        "Nera"
    ],
    "name:dan_x_preferred":[
        "Nera"
    ],
    "name:deu_x_preferred":[
        "Nera"
    ],
    "name:est_x_preferred":[
        "Nera"
    ],
    "name:fra_x_preferred":[
        "Nera"
    ],
    "name:ita_x_preferred":[
        "Nera"
    ],
    "name:lit_x_preferred":[
        "Nera"
    ],
    "name:nld_x_preferred":[
        "Nera"
    ],
    "name:nor_x_preferred":[
        "Nera"
    ],
    "name:pol_x_preferred":[
        "Nera"
    ],
    "name:ron_x_preferred":[
        "Nera"
    ],
    "name:rus_x_preferred":[
        "\u041d\u0435\u0440\u0430"
    ],
    "name:srp_x_preferred":[
        "\u041d\u0435\u0440\u0430"
    ],
    "name:swe_x_preferred":[
        "Nera"
    ],
    "wof:name":"Nera",
    "wof:placetype":"locality"
},
  "geometry": {"coordinates":[76.05313000000002,32.23338],"type":"Point"}
}