{
  "type": "Feature",
  "properties": {
    "iso:country":"IN",
    "ks:ks_name":"Pendharmal",
    "ks:ks_pop":221,
    "ks:ks_type":"HABITATION",
    "name:eng_x_preferred":[
        "Pendharmal"
    ],
    "wof:name":"Pendharmal",
    "wof:placetype":"locality",
    "wof:population":221
},
  "geometry": {"coordinates":[73.306313,18.677911],"type":"Point"}
}