{
  "type": "Feature",
  "properties": {
    "iso:country":"IN",
    "ks:ks_name":"Kannanthangal",
    "ks:ks_pop":492,
    "ks:ks_type":"HABITATION",
    "name:eng_x_preferred":[
        "Kannanthangal"
    ],
    "wof:name":"Kannanthangal",
    "wof:placetype":"locality",
    "wof:population":492
},
  "geometry": {"coordinates":[80.037362,12.401923],"type":"Point"}
}