{
  "type": "Feature",
  "properties": {
    "iso:country":"IN",
    "ks:ks_name":"Talaipara",
    "ks:ks_pop":298,
    "ks:ks_type":"VILLAGE",
    "name:eng_x_preferred":[
        "Talaipara"
    ],
    "wof:name":"Talaipara",
    "wof:placetype":"locality",
    "wof:population":298
},
  "geometry": {"coordinates":[74.503924,23.311384],"type":"Point"}
}