{
  "type": "Feature",
  "properties": {
    "iso:country":"IN",
    "ks:ks_alt_nam":"MAROLMALA RD",
    "ks:ks_name":"Marolmala Rd",
    "ks:ks_pop":65,
    "ks:ks_type":"HABITATION",
    "name:eng_x_preferred":[
        "Marolmala Rd"
    ],
    "wof:name":"Marolmala Rd",
    "wof:placetype":"locality",
    "wof:population":65
},
  "geometry": {"coordinates":[74.871332,17.16714],"type":"Point"}
}