{
  "type": "Feature",
  "properties": {
    "iso:country":"IN",
    "ks:ks_name":"Huliyar Maruthinagar",
    "ks:ks_pop":85,
    "ks:ks_type":"HABITATION",
    "name:eng_x_preferred":[
        "Huliyar Maruthinagar"
    ],
    "wof:name":"Huliyar Maruthinagar",
    "wof:placetype":"locality",
    "wof:population":85
},
  "geometry": {"coordinates":[76.57822400000001,13.615497],"type":"Point"}
}