{
  "type": "Feature",
  "properties": {
    "gn:admin1_code":"36",
    "gn:admin2_code":"148.0",
    "gn:asciiname":"Bhogpur",
    "gn:country_code":"IN",
    "gn:dem":156,
    "gn:feature_class":"P",
    "gn:feature_code":"PPL",
    "gn:name":"Bhogpur",
    "gn:population":0,
    "gn:timezone":"Asia/Kolkata",
    "iso:country":"IN",
    "name:ben_x_preferred":[
        "\u09ad\u09cb\u0997\u09aa\u09c1\u09b0"
    ],
    "name:bpy_x_preferred":[
        "\u09ad\u09cb\u0997\u09aa\u09c1\u09b0"
    ],
    "name:ceb_x_preferred":[
        "Bhogpur"
    ],
    "name:ita_x_preferred":[
        "Bhogpur"
    ],
    "name:mlg_x_preferred":[
        "Bhogpur"
    ],
    "name:msa_x_preferred":[
        "Bhogpur"
    ],
    "name:new_x_preferred":[
        "\u092d\u094b\u0917\u092a\u0941\u0930"
    ],
    "name:nld_x_preferred":[
        "Bhogpur"
    ],
    "name:por_x_preferred":[
        "Bhogpur"
    ],
    "name:spa_x_preferred":[
        "Bhogpur"
    ],
    "name:swe_x_preferred":[
        "Bhogpur"
    ],
    "name:vie_x_preferred":[
        "Bhogpur"
    ],
    "name:zho_x_preferred":[
        "\u535a\u683c\u666e\u5c14"
    ],
    "wof:name":"Bhogpur",
    "wof:placetype":"neighbourhood"
},
  "geometry": {"coordinates":[79.06216999999999,27.05776],"type":"Point"}
}