{
  "type": "Feature",
  "properties": {
    "iso:country":"IN",
    "ks:ks_alt_nam":"Mah\u0101dewa",
    "ks:ks_name":"Mahadewa",
    "ks:ks_type":"VILLAGE",
    "ks:ks_uagg_main":0,
    "name:eng_x_preferred":[
        "Mahadewa"
    ],
    "name:eng_x_variant":[
        "Mah\u0101dewa"
    ],
    "wof:name":"Mahadewa",
    "wof:placetype":"neighbourhood"
},
  "geometry": {"coordinates":[84.360269,26.231938],"type":"Point"}
}