{
  "type": "Feature",
  "properties": {
    "gn:admin1_code":"34.0",
    "gn:admin2_code":"214.0",
    "gn:asciiname":"Hempur",
    "gn:country_code":"IN",
    "gn:dem":49,
    "gn:feature_class":"P",
    "gn:feature_code":"PPL",
    "gn:name":"Hempur",
    "gn:population":0,
    "gn:timezone":"Asia/Kolkata",
    "iso:country":"IN",
    "ks:ks_name":"Hempur",
    "ks:ks_pop":1780,
    "ks:ks_type":"VILLAGE",
    "ks:ks_uagg_main":0,
    "name:ceb_x_preferred":[
        "Hempur"
    ],
    "name:eng_x_preferred":[
        "Hempur"
    ],
    "name:fra_x_preferred":[
        "Hempur"
    ],
    "name:mai_x_preferred":[
        "\u0939\u0947\u092e\u092a\u0941\u0930"
    ],
    "name:nep_x_preferred":[
        "\u0939\u0947\u092e\u092a\u0941\u0930"
    ],
    "name:new_x_preferred":[
        "\u0939\u0947\u092e\u092a\u0941\u0930"
    ],
    "name:pol_x_preferred":[
        "Hempur"
    ],
    "wof:name":"Hempur",
    "wof:placetype":"neighbourhood",
    "wof:population":1780
},
  "geometry": {"coordinates":[86.486709,26.010131],"type":"Point"}
}