{
  "type": "Feature",
  "properties": {
    "iso:country":"IN",
    "ks:ks_alt_nam":"Ourtol supa",
    "ks:ks_name":"Ourtol Supa",
    "ks:ks_pop":206,
    "ks:ks_type":"HABITATION",
    "name:eng_x_preferred":[
        "Ourtol Supa"
    ],
    "wof:name":"Ourtol Supa",
    "wof:placetype":"locality",
    "wof:population":206
},
  "geometry": {"coordinates":[91.455668,26.702814],"type":"Point"}
}