{
  "type": "Feature",
  "properties": {
    "gn:admin1_code":"9.0",
    "gn:admin2_code":"493.0",
    "gn:asciiname":"Mendpur",
    "gn:country_code":"IN",
    "gn:dem":120,
    "gn:feature_class":"P",
    "gn:feature_code":"PPL",
    "gn:name":"Mendpur",
    "gn:population":0,
    "gn:timezone":"Asia/Kolkata",
    "iso:country":"IN",
    "wof:name":"Mendpur",
    "wof:placetype":"locality"
},
  "geometry": {"coordinates":[74.05981,21.53963],"type":"Point"}
}