{
  "type": "Feature",
  "properties": {
    "iso:country":"IN",
    "ks:ks_name":"Haldu",
    "ks:ks_pop":395,
    "ks:ks_type":"VILLAGE",
    "name:eng_x_preferred":[
        "Haldu"
    ],
    "wof:name":"Haldu",
    "wof:placetype":"locality",
    "wof:population":395
},
  "geometry": {"coordinates":[80.286473,29.453187],"type":"Point"}
}