{
  "type": "Feature",
  "properties": {
    "iso:country":"IN",
    "ks:ks_name":"Neduvanvila",
    "ks:ks_pop":3005,
    "ks:ks_type":"HABITATION",
    "name:eng_x_preferred":[
        "Neduvanvila"
    ],
    "wof:name":"Neduvanvila",
    "wof:placetype":"locality",
    "wof:population":3005
},
  "geometry": {"coordinates":[77.16039499999999,8.347372],"type":"Point"}
}