{
  "type": "Feature",
  "properties": {
    "iso:country":"IN",
    "ks:ks_name":"Beethatippu",
    "ks:ks_pop":348,
    "ks:ks_type":"HABITATION",
    "name:eng_x_preferred":[
        "Beethatippu"
    ],
    "wof:name":"Beethatippu",
    "wof:placetype":"locality",
    "wof:population":348
},
  "geometry": {"coordinates":[75.234351,12.825535],"type":"Point"}
}