{
  "type": "Feature",
  "properties": {
    "gn:admin1_code":"24.0",
    "gn:admin2_code":"125.0",
    "gn:asciiname":"Andog",
    "gn:country_code":"IN",
    "gn:dem":373,
    "gn:feature_class":"P",
    "gn:feature_code":"PPL",
    "gn:name":"Andog",
    "gn:population":0,
    "gn:timezone":"Asia/Kolkata",
    "iso:country":"IN",
    "ks:ks_name":"Andok",
    "ks:ks_pop":354,
    "ks:ks_type":"VILLAGE",
    "name:eng_x_preferred":[
        "Andok"
    ],
    "name:eng_x_variant":[
        "Andog"
    ],
    "wof:name":"Andok",
    "wof:placetype":"locality",
    "wof:population":354
},
  "geometry": {"coordinates":[74.601254,23.145933],"type":"Point"}
}