{
  "type": "Feature",
  "properties": {
    "iso:country":"IN",
    "ks:ks_name":"Maruthalimedu",
    "ks:ks_pop":114,
    "ks:ks_type":"HABITATION",
    "name:eng_x_preferred":[
        "Maruthalimedu"
    ],
    "wof:name":"Maruthalimedu",
    "wof:placetype":"locality",
    "wof:population":114
},
  "geometry": {"coordinates":[79.015533,12.805456],"type":"Point"}
}