{
  "type": "Feature",
  "properties": {
    "iso:country":"IN",
    "ks:ks_name":"Umapur",
    "ks:ks_pop":1100,
    "ks:ks_type":"VILLAGE",
    "ks:ks_uagg_main":0,
    "name:eng_x_preferred":[
        "Umapur"
    ],
    "wof:name":"Umapur",
    "wof:placetype":"locality",
    "wof:population":1100
},
  "geometry": {"coordinates":[88.45566599999999,23.017218],"type":"Point"}
}