{
  "type": "Feature",
  "properties": {
    "gn:admin1_code":"21.0",
    "gn:admin2_code":"398.0",
    "gn:asciiname":"Belgaon",
    "gn:country_code":"IN",
    "gn:dem":896,
    "gn:feature_class":"P",
    "gn:feature_code":"PPL",
    "gn:name":"Belgaon",
    "gn:population":0,
    "gn:timezone":"Asia/Kolkata",
    "iso:country":"IN",
    "wof:name":"Belgaon",
    "wof:placetype":"neighbourhood"
},
  "geometry": {"coordinates":[82.68464,18.56844],"type":"Point"}
}