{
  "type": "Feature",
  "properties": {
    "iso:country":"IN",
    "ks:ks_name":"Maniraj Batitaki",
    "ks:ks_pop":189,
    "ks:ks_type":"VILLAGE",
    "name:eng_x_preferred":[
        "Maniraj Batitaki"
    ],
    "wof:name":"Maniraj Batitaki",
    "wof:placetype":"locality",
    "wof:population":189
},
  "geometry": {"coordinates":[87.35326999999999,22.111152],"type":"Point"}
}