{
  "type": "Feature",
  "properties": {
    "iso:country":"IN",
    "ks:ks_name":"Kandharamunda",
    "ks:ks_pop":221,
    "ks:ks_type":"VILLAGE",
    "name:eng_x_preferred":[
        "Kandharamunda"
    ],
    "wof:name":"Kandharamunda",
    "wof:placetype":"locality",
    "wof:population":221
},
  "geometry": {"coordinates":[84.563997,20.950883],"type":"Point"}
}