{
  "type": "Feature",
  "properties": {
    "iso:country":"IN",
    "ks:ks_name":"Urkhel Gaon",
    "ks:ks_pop":107,
    "ks:ks_type":"HABITATION",
    "name:eng_x_preferred":[
        "Urkhel Gaon"
    ],
    "wof:name":"Urkhel Gaon",
    "wof:placetype":"locality",
    "wof:population":107
},
  "geometry": {"coordinates":[78.57924199999999,29.862183],"type":"Point"}
}