{
  "type": "Feature",
  "properties": {
    "gn:admin1_code":"37",
    "gn:admin2_code":"409.0",
    "gn:asciiname":"Sandkapat",
    "gn:country_code":"IN",
    "gn:dem":278,
    "gn:feature_class":"P",
    "gn:feature_code":"PPL",
    "gn:name":"Sandkap\u0101t",
    "gn:population":0,
    "gn:timezone":"Asia/Kolkata",
    "iso:country":"IN",
    "ks:ks_name":"Sankapat",
    "ks:ks_pop":415,
    "ks:ks_type":"VILLAGE",
    "ks:ks_uagg_main":0,
    "name:eng_x_preferred":[
        "Sankapat"
    ],
    "wof:name":"Sankapat",
    "wof:placetype":"neighbourhood",
    "wof:population":415
},
  "geometry": {"coordinates":[81.601484,21.76285],"type":"Point"}
}