{
  "type": "Feature",
  "properties": {
    "gn:admin1_code":"11",
    "gn:admin2_code":"31.0",
    "gn:asciiname":"Goera",
    "gn:country_code":"IN",
    "gn:dem":450,
    "gn:feature_class":"P",
    "gn:feature_code":"PPL",
    "gn:name":"Goera",
    "gn:population":0,
    "gn:timezone":"Asia/Kolkata",
    "iso:country":"IN",
    "name:ceb_x_preferred":[
        "Goera"
    ],
    "name:nld_x_preferred":[
        "Goera"
    ],
    "name:swe_x_preferred":[
        "Goera"
    ],
    "name:war_x_preferred":[
        "Goera"
    ],
    "wof:name":"Goera",
    "wof:placetype":"neighbourhood"
},
  "geometry": {"coordinates":[76.80234,30.97776],"type":"Point"}
}