{
  "type": "Feature",
  "properties": {
    "iso:country":"IN",
    "ks:ks_name":"Surangapur",
    "ks:ks_pop":468,
    "ks:ks_type":"VILLAGE",
    "ks:ks_uagg_main":0,
    "name:eng_x_preferred":[
        "Surangapur"
    ],
    "wof:name":"Surangapur",
    "wof:placetype":"neighbourhood",
    "wof:population":468
},
  "geometry": {"coordinates":[85.75433,20.126912],"type":"Point"}
}