{
  "type": "Feature",
  "properties": {
    "gn:admin1_code":"23.0",
    "gn:admin2_code":"52.0",
    "gn:asciiname":"Parol",
    "gn:country_code":"IN",
    "gn:dem":362,
    "gn:feature_class":"P",
    "gn:feature_code":"PPL",
    "gn:name":"Parol",
    "gn:population":0,
    "gn:timezone":"Asia/Kolkata",
    "iso:country":"IN",
    "name:ceb_x_preferred":[
        "Parol"
    ],
    "name:nor_x_preferred":[
        "Parol"
    ],
    "name:tgl_x_preferred":[
        "Parol"
    ],
    "wof:name":"Parol",
    "wof:placetype":"locality"
},
  "geometry": {"coordinates":[76.74033,30.83181],"type":"Point"}
}