{
  "type": "Feature",
  "properties": {
    "iso:country":"IN",
    "ks:ks_name":"Eram",
    "ks:ks_pop":3634,
    "ks:ks_type":"VILLAGE",
    "ks:ks_uagg_main":0,
    "name:eng_x_preferred":[
        "Eram"
    ],
    "wof:name":"Eram",
    "wof:placetype":"neighbourhood",
    "wof:population":3634
},
  "geometry": {"coordinates":[86.790834,21.157651],"type":"Point"}
}