{
  "type": "Feature",
  "properties": {
    "iso:country":"IN",
    "ks:ks_name":"Chokkodu",
    "ks:ks_pop":29,
    "ks:ks_type":"HABITATION",
    "name:eng_x_preferred":[
        "Chokkodu"
    ],
    "wof:name":"Chokkodu",
    "wof:placetype":"locality",
    "wof:population":29
},
  "geometry": {"coordinates":[75.13979399999999,13.839872],"type":"Point"}
}