{
  "type": "Feature",
  "properties": {
    "gn:admin1_code":"39.0",
    "gn:admin2_code":"64.0",
    "gn:asciiname":"Chaura",
    "gn:country_code":"IN",
    "gn:dem":1369,
    "gn:feature_class":"P",
    "gn:feature_code":"PPL",
    "gn:name":"Chaura",
    "gn:population":0,
    "gn:timezone":"Asia/Kolkata",
    "iso:country":"IN",
    "name:ceb_x_preferred":[
        "Chaura"
    ],
    "name:swe_x_preferred":[
        "Chaura"
    ],
    "wof:name":"Chaura",
    "wof:placetype":"locality"
},
  "geometry": {"coordinates":[79.7084,29.5013],"type":"Point"}
}