{
  "type": "Feature",
  "properties": {
    "gn:admin1_code":"39.0",
    "gn:admin2_code":"64.0",
    "gn:asciiname":"Chaura",
    "gn:country_code":"IN",
    "gn:dem":1369,
    "gn:feature_class":"P",
    "gn:feature_code":"PPL",
    "gn:name":"Chaura",
    "gn:population":0,
    "gn:timezone":"Asia/Kolkata",
    "iso:country":"IN",
    "ks:ks_name":"Choura",
    "ks:ks_pop":71,
    "ks:ks_type":"HABITATION",
    "name:ceb_x_preferred":[
        "Chaura"
    ],
    "name:eng_x_preferred":[
        "Choura"
    ],
    "name:eng_x_variant":[
        "Chaura"
    ],
    "name:swe_x_preferred":[
        "Chaura"
    ],
    "wof:name":"Choura",
    "wof:placetype":"locality",
    "wof:population":71
},
  "geometry": {"coordinates":[79.700626,29.496472],"type":"Point"}
}