{
  "type": "Feature",
  "properties": {
    "iso:country":"IN",
    "ks:ks_name":"Jamunaposi",
    "ks:ks_pop":220,
    "ks:ks_type":"HABITATION",
    "name:eng_x_preferred":[
        "Jamunaposi"
    ],
    "wof:name":"Jamunaposi",
    "wof:placetype":"locality",
    "wof:population":220
},
  "geometry": {"coordinates":[85.477799,21.89355],"type":"Point"}
}