{
  "type": "Feature",
  "properties": {
    "iso:country":"IN",
    "ks:ks_name":"Batka",
    "ks:ks_pop":12,
    "ks:ks_type":"VILLAGE",
    "name:eng_x_preferred":[
        "Batka"
    ],
    "wof:name":"Batka",
    "wof:placetype":"locality",
    "wof:population":12
},
  "geometry": {"coordinates":[79.455665,23.591331],"type":"Point"}
}