{
  "type": "Feature",
  "properties": {
    "gn:admin1_code":"35",
    "gn:admin2_code":"457.0",
    "gn:asciiname":"Bahrabhata",
    "gn:country_code":"IN",
    "gn:dem":615,
    "gn:feature_class":"P",
    "gn:feature_code":"PPL",
    "gn:name":"Bahr\u0101bh\u0101ta",
    "gn:population":0,
    "gn:timezone":"Asia/Kolkata",
    "iso:country":"IN",
    "ks:ks_name":"Baherabhata",
    "ks:ks_pop":1952,
    "ks:ks_type":"VILLAGE",
    "ks:ks_uagg_main":0,
    "name:eng_x_preferred":[
        "Baherabhata"
    ],
    "wof:name":"Baherabhata",
    "wof:placetype":"neighbourhood",
    "wof:population":1952
},
  "geometry": {"coordinates":[80.824465,21.794049],"type":"Point"}
}