{
  "type": "Feature",
  "properties": {
    "iso:country":"IN",
    "name:eng_x_preferred":[
        "Khetwadi"
    ],
    "name:und_x_variant":[
        "Khetw\u0101di"
    ],
    "qs:gn_adm0_cc":"IN",
    "qs:gn_fcode":"PPLX",
    "qs:gn_local":1275339,
    "qs:gn_namadm1":"16",
    "qs:gn_name":"Khetw\u0101di",
    "qs:local_max":3819,
    "qs:local_sum":50908,
    "qs:localhoods":70,
    "qs:name":"Khetwadi",
    "qs:name_adm0":"India",
    "qs:name_adm1":"Maharashtra",
    "qs:name_adm2":"Mumbai",
    "qs:name_local":"Mumbai",
    "qs:photo_max":105,
    "qs:photo_sum":1327,
    "qs:placetype":"Suburb",
    "qs:quad_count":52,
    "qs:woe_adm0":23424848,
    "qs:woe_adm1":2345750,
    "qs:woe_adm2":12586539,
    "qs:woe_lau":0,
    "qs:woe_local":2295411,
    "qs:woe_ver":"7.10.0",
    "wof:lang":[
        "eng"
    ],
    "wof:name":"Khetwadi",
    "wof:placetype":"neighbourhood"
},
  "geometry": {"coordinates":[72.825002,18.944628],"type":"Point"}
}