{
  "type": "Feature",
  "properties": {
    "iso:country":"IN",
    "ks:ks_name":"Gadrewasti",
    "ks:ks_pop":214,
    "ks:ks_type":"HABITATION",
    "name:eng_x_preferred":[
        "Gadrewasti"
    ],
    "wof:name":"Gadrewasti",
    "wof:placetype":"locality",
    "wof:population":214
},
  "geometry": {"coordinates":[74.272475,18.415001],"type":"Point"}
}