{
  "type": "Feature",
  "properties": {
    "gn:admin1_code":"36",
    "gn:admin2_code":"173.0",
    "gn:asciiname":"Chitpur",
    "gn:country_code":"IN",
    "gn:dem":101,
    "gn:feature_class":"P",
    "gn:feature_code":"PPL",
    "gn:name":"Chitpur",
    "gn:population":0,
    "gn:timezone":"Asia/Kolkata",
    "iso:country":"IN",
    "name:ara_x_preferred":[
        "\u062a\u0634\u064a\u062a\u0628\u0648\u0631"
    ],
    "name:ben_bn_x_preferred":[
        "\u099a\u09bf\u09ce\u09aa\u09c1\u09b0"
    ],
    "name:ben_in_x_preferred":[
        "\u099a\u09bf\u09ce\u09aa\u09c1\u09b0"
    ],
    "name:ben_x_preferred":[
        "\u099a\u09bf\u09ce\u09aa\u09c1\u09b0"
    ],
    "name:guj_x_preferred":[
        "\u0a9a\u0abf\u0aa4\u0aaa\u0ac1\u0ab0"
    ],
    "name:hin_x_preferred":[
        "\u091a\u093f\u0924\u092a\u0941\u0930"
    ],
    "name:kan_x_preferred":[
        "\u0c9a\u0cbf\u0ca4\u0ccd"
    ],
    "name:mal_x_preferred":[
        "\u0d1a\u0d3f\u0d24\u0d4d\u0d2a\u0d42\u0d7c"
    ],
    "name:mar_x_preferred":[
        "\u091a\u093f\u0924\u092a\u0942\u0930"
    ],
    "name:pan_x_preferred":[
        "\u0a1a\u0a3f\u0a71\u0a24\u0a2a\u0a41\u0a30"
    ],
    "name:tam_x_preferred":[
        "\u0b9a\u0bbf\u0ba4\u0bcd\u0baa\u0bc2\u0bb0\u0bcd"
    ],
    "name:tel_x_preferred":[
        "\u0c1a\u0c3f\u0c1f\u0c4d"
    ],
    "name:urd_x_preferred":[
        "\u0686\u062a \u067e\u0648\u0631"
    ],
    "wof:name":"Chitpur",
    "wof:placetype":"neighbourhood"
},
  "geometry": {"coordinates":[82.03317,25.89549],"type":"Point"}
}