{
  "type": "Feature",
  "properties": {
    "iso:country":"IN",
    "ks:ks_name":"Kotarkona",
    "ks:ks_pop":226,
    "ks:ks_type":"HABITATION",
    "name:eng_x_preferred":[
        "Kotarkona"
    ],
    "wof:name":"Kotarkona",
    "wof:placetype":"locality",
    "wof:population":226
},
  "geometry": {"coordinates":[84.571501,22.936618],"type":"Point"}
}