{
  "type": "Feature",
  "properties": {
    "iso:country":"IN",
    "ks:ks_name":"Kosh Falia",
    "ks:ks_pop":367,
    "ks:ks_type":"HABITATION",
    "name:eng_x_preferred":[
        "Kosh Falia"
    ],
    "wof:name":"Kosh Falia",
    "wof:placetype":"locality",
    "wof:population":367
},
  "geometry": {"coordinates":[73.267416,20.148732],"type":"Point"}
}