{
  "type": "Feature",
  "properties": {
    "gn:admin1_code":"36",
    "gn:admin2_code":"194.0",
    "gn:asciiname":"Baraich",
    "gn:country_code":"IN",
    "gn:dem":80,
    "gn:feature_class":"P",
    "gn:feature_code":"PPL",
    "gn:name":"Baraich",
    "gn:population":0,
    "gn:timezone":"Asia/Kolkata",
    "iso:country":"IN",
    "name:pan_x_preferred":[
        "\u0a2c\u0a5c\u0a48\u0a1a"
    ],
    "wof:name":"Baraich",
    "wof:placetype":"neighbourhood"
},
  "geometry": {"coordinates":[82.97008,25.59027],"type":"Point"}
}