{
  "type": "Feature",
  "properties": {
    "iso:country":"IN",
    "ks:ks_alt_nam":"GONHA",
    "ks:ks_name":"Gonha",
    "ks:ks_pop":307,
    "ks:ks_type":"HABITATION",
    "ks:ks_uagg_main":0,
    "name:eng_x_preferred":[
        "Gonha"
    ],
    "wof:name":"Gonha",
    "wof:placetype":"neighbourhood",
    "wof:population":307
},
  "geometry": {"coordinates":[81.946769,25.573511],"type":"Point"}
}