{
  "type": "Feature",
  "properties": {
    "iso:country":"IN",
    "ks:ks_name":"Appekere",
    "ks:ks_pop":390,
    "ks:ks_type":"HABITATION",
    "name:eng_x_preferred":[
        "Appekere"
    ],
    "wof:name":"Appekere",
    "wof:placetype":"locality",
    "wof:population":390
},
  "geometry": {"coordinates":[74.435419,14.32635],"type":"Point"}
}