{
  "type": "Feature",
  "properties": {
    "iso:country":"IN",
    "ks:ks_name":"Naduvalur",
    "ks:ks_pop":1299,
    "ks:ks_type":"HABITATION",
    "name:eng_x_preferred":[
        "Naduvalur"
    ],
    "wof:name":"Naduvalur",
    "wof:placetype":"locality",
    "wof:population":1299
},
  "geometry": {"coordinates":[78.647845,11.10376],"type":"Point"}
}