{
  "type": "Feature",
  "properties": {
    "iso:country":"IN",
    "ks:ks_name":"Salmari No 2",
    "ks:ks_pop":750,
    "ks:ks_type":"HABITATION",
    "name:eng_x_preferred":[
        "Salmari No 2"
    ],
    "wof:name":"Salmari No 2",
    "wof:placetype":"locality",
    "wof:population":750
},
  "geometry": {"coordinates":[95.11201699999999,27.268945],"type":"Point"}
}