{
  "type": "Feature",
  "properties": {
    "gn:admin1_code":"35.0",
    "gn:admin2_code":"453.0",
    "gn:asciiname":"Keolardar",
    "gn:country_code":"IN",
    "gn:dem":645,
    "gn:feature_class":"P",
    "gn:feature_code":"PPL",
    "gn:name":"Keol\u0101rdar",
    "gn:population":0,
    "gn:timezone":"Asia/Kolkata",
    "iso:country":"IN",
    "ks:ks_alt_nam":"Keol\u0101rdar",
    "ks:ks_name":"Keolardar",
    "ks:ks_type":"VILLAGE",
    "name:eng_x_preferred":[
        "Keolardar"
    ],
    "name:eng_x_variant":[
        "Keol\u0101rdar"
    ],
    "wof:name":"Keolardar",
    "wof:placetype":"locality"
},
  "geometry": {"coordinates":[80.769419,22.897874],"type":"Point"}
}