{
  "type": "Feature",
  "properties": {
    "gn:admin1_code":"35.0",
    "gn:admin2_code":"436.0",
    "gn:asciiname":"Bankakheri",
    "gn:country_code":"IN",
    "gn:dem":450,
    "gn:feature_class":"P",
    "gn:feature_code":"PPL",
    "gn:name":"B\u0101nk\u0101kheri",
    "gn:population":0,
    "gn:timezone":"Asia/Kolkata",
    "iso:country":"IN",
    "wof:name":"Bankakheri",
    "wof:placetype":"locality"
},
  "geometry": {"coordinates":[76.65579,23.30056],"type":"Point"}
}