{
  "type": "Feature",
  "properties": {
    "iso:country":"IN",
    "ks:ks_name":"Mangobawasti",
    "ks:ks_pop":413,
    "ks:ks_type":"HABITATION",
    "name:eng_x_preferred":[
        "Mangobawasti"
    ],
    "wof:name":"Mangobawasti",
    "wof:placetype":"locality",
    "wof:population":413
},
  "geometry": {"coordinates":[74.0081,17.8051],"type":"Point"}
}