{
  "type": "Feature",
  "properties": {
    "gn:admin1_code":"36.0",
    "gn:admin2_code":"133.0",
    "gn:asciiname":"Kabirpur",
    "gn:country_code":"IN",
    "gn:dem":244,
    "gn:feature_class":"P",
    "gn:feature_code":"PPL",
    "gn:name":"Kab\u012brpur",
    "gn:population":0,
    "gn:timezone":"Asia/Kolkata",
    "iso:country":"IN",
    "ks:ks_alt_nam":"Kab\u012brpur",
    "ks:ks_name":"Kabirpur",
    "ks:ks_pop":1212,
    "ks:ks_type":"VILLAGE",
    "ks:ks_uagg_main":0,
    "name:eng_x_preferred":[
        "Kabirpur"
    ],
    "name:eng_x_variant":[
        "Kab\u012brpur"
    ],
    "wof:name":"Kabirpur",
    "wof:placetype":"neighbourhood",
    "wof:population":1212
},
  "geometry": {"coordinates":[77.579448,29.398269],"type":"Point"}
}