{
  "type": "Feature",
  "properties": {
    "gn:admin1_code":"13.0",
    "gn:admin2_code":"593.0",
    "gn:asciiname":"Muthutala",
    "gn:country_code":"IN",
    "gn:dem":30,
    "gn:feature_class":"P",
    "gn:feature_code":"PPL",
    "gn:name":"Muthutala",
    "gn:population":0,
    "gn:timezone":"Asia/Kolkata",
    "iso:country":"IN",
    "wof:name":"Muthutala",
    "wof:placetype":"locality"
},
  "geometry": {"coordinates":[76.15958000000001,10.83544],"type":"Point"}
}