{
  "type": "Feature",
  "properties": {
    "gn:admin1_code":"34.0",
    "gn:admin2_code":"218.0",
    "gn:asciiname":"Sughri",
    "gn:country_code":"IN",
    "gn:dem":64,
    "gn:feature_class":"P",
    "gn:feature_code":"PPL",
    "gn:name":"Sughri",
    "gn:population":0,
    "gn:timezone":"Asia/Kolkata",
    "iso:country":"IN",
    "ks:ks_name":"Sughri",
    "ks:ks_pop":2693,
    "ks:ks_type":"VILLAGE",
    "ks:ks_uagg_main":0,
    "name:eng_x_preferred":[
        "Sughri"
    ],
    "wof:name":"Sughri",
    "wof:placetype":"neighbourhood",
    "wof:population":2693
},
  "geometry": {"coordinates":[84.70720900000001,26.152475],"type":"Point"}
}