{
  "type": "Feature",
  "properties": {
    "iso:country":"IN",
    "ks:ks_name":"Kumar Gaon",
    "ks:ks_pop":175,
    "ks:ks_type":"VILLAGE",
    "ks:ks_uagg_main":0,
    "name:eng_x_preferred":[
        "Kumar Gaon"
    ],
    "wof:name":"Kumar Gaon",
    "wof:placetype":"locality",
    "wof:population":175
},
  "geometry": {"coordinates":[92.759052,26.652673],"type":"Point"}
}