{
  "type": "Feature",
  "properties": {
    "iso:country":"IN",
    "ks:ks_name":"Korwa Tola",
    "ks:ks_pop":315,
    "ks:ks_type":"HABITATION",
    "name:eng_x_preferred":[
        "Korwa Tola"
    ],
    "wof:name":"Korwa Tola",
    "wof:placetype":"locality",
    "wof:population":315
},
  "geometry": {"coordinates":[83.53164700000001,24.138426],"type":"Point"}
}