{
  "type": "Feature",
  "properties": {
    "iso:country":"IN",
    "ks:ks_name":"Ghoghodih",
    "ks:ks_pop":0,
    "ks:ks_type":"VILLAGE",
    "name:eng_x_preferred":[
        "Ghoghodih"
    ],
    "wof:name":"Ghoghodih",
    "wof:placetype":"locality",
    "wof:population":0
},
  "geometry": {"coordinates":[83.825238,25.663577],"type":"Point"}
}