{
  "type": "Feature",
  "properties": {
    "iso:country":"IN",
    "ks:ks_name":"Begar-Kash",
    "ks:ks_pop":1799,
    "ks:ks_type":"VILLAGE",
    "ks:ks_uagg_main":0,
    "name:eng_x_preferred":[
        "Begar-Kash"
    ],
    "wof:name":"Begar-Kash",
    "wof:placetype":"neighbourhood",
    "wof:population":1799
},
  "geometry": {"coordinates":[92.093217,26.636236],"type":"Point"}
}