{
  "type": "Feature",
  "properties": {
    "iso:country":"IN",
    "ks:ks_name":"Addagaddeagrahara",
    "ks:ks_pop":36,
    "ks:ks_type":"HABITATION",
    "name:eng_x_preferred":[
        "Addagaddeagrahara"
    ],
    "wof:name":"Addagaddeagrahara",
    "wof:placetype":"locality",
    "wof:population":36
},
  "geometry": {"coordinates":[75.274061,13.454829],"type":"Point"}
}