{
  "type": "Feature",
  "properties": {
    "iso:country":"IN",
    "ks:ks_alt_nam":"PASWAN TOLA",
    "ks:ks_name":"Paswan Tola",
    "ks:ks_pop":160,
    "ks:ks_type":"HABITATION",
    "name:eng_x_preferred":[
        "Paswan Tola"
    ],
    "wof:name":"Paswan Tola",
    "wof:placetype":"locality",
    "wof:population":160
},
  "geometry": {"coordinates":[86.427091,24.963082],"type":"Point"}
}