{
  "type": "Feature",
  "properties": {
    "gn:admin1_code":"35",
    "gn:admin2_code":"455.0",
    "gn:asciiname":"Sagonia",
    "gn:country_code":"IN",
    "gn:dem":687,
    "gn:feature_class":"P",
    "gn:feature_code":"PPL",
    "gn:name":"Sagonia",
    "gn:population":0,
    "gn:timezone":"Asia/Kolkata",
    "iso:country":"IN",
    "ks:ks_name":"Sagonia",
    "ks:ks_pop":538,
    "ks:ks_type":"HABITATION",
    "name:eng_x_preferred":[
        "Sagonia"
    ],
    "wof:name":"Sagonia",
    "wof:placetype":"locality",
    "wof:population":538
},
  "geometry": {"coordinates":[79.005803,22.206106],"type":"Point"}
}