{
  "type": "Feature",
  "properties": {
    "gn:admin1_code":"19.0",
    "gn:admin2_code":"574.0",
    "gn:asciiname":"Chikka Gadduvalli",
    "gn:country_code":"IN",
    "gn:dem":1000,
    "gn:feature_class":"P",
    "gn:feature_code":"PPL",
    "gn:name":"Chikka Gadduvalli",
    "gn:population":0,
    "gn:timezone":"Asia/Kolkata",
    "iso:country":"IN",
    "wof:name":"Chikka Gadduvalli",
    "wof:placetype":"locality"
},
  "geometry": {"coordinates":[76.0162,13.09644],"type":"Point"}
}