{
  "type": "Feature",
  "properties": {
    "gn:admin1_code":"10.0",
    "gn:admin2_code":"74.0",
    "gn:asciiname":"Katlaheri",
    "gn:country_code":"IN",
    "gn:dem":245,
    "gn:feature_class":"P",
    "gn:feature_code":"PPL",
    "gn:name":"Katlaheri",
    "gn:population":0,
    "gn:timezone":"Asia/Kolkata",
    "iso:country":"IN",
    "wof:name":"Katlaheri",
    "wof:placetype":"locality"
},
  "geometry": {"coordinates":[76.82199,29.64663],"type":"Point"}
}