{
  "type": "Feature",
  "properties": {
    "gn:admin1_code":"11.0",
    "gn:admin2_code":"32.0",
    "gn:asciiname":"Kangra",
    "gn:country_code":"IN",
    "gn:dem":1069,
    "gn:feature_class":"P",
    "gn:feature_code":"PPL",
    "gn:name":"K\u0101ngra",
    "gn:population":0,
    "gn:timezone":"Asia/Kolkata",
    "iso:country":"IN",
    "name:ara_x_preferred":[
        "\u0643\u0627\u0646\u062c\u0631\u0627"
    ],
    "name:ben_bn_x_preferred":[
        "\u0995\u09be\u0982\u09dc\u09be"
    ],
    "name:ben_in_x_preferred":[
        "\u0995\u09be\u0982\u09dc\u09be"
    ],
    "name:guj_x_preferred":[
        "\u0a95\u0abe\u0a82\u0a97\u0acd\u0ab0\u0abe"
    ],
    "name:hin_x_preferred":[
        "\u0915\u093e\u0902\u0917\u095c\u093e"
    ],
    "name:kan_x_preferred":[
        "\u0c95\u0c82\u0c97\u0ccd\u0cb0"
    ],
    "name:mal_x_preferred":[
        "\u0d15\u0d3e\u0d7b\u0d17\u0d4d\u0d30"
    ],
    "name:mar_x_preferred":[
        "\u0915\u093e\u0902\u0917\u0930\u093e"
    ],
    "name:nld_x_preferred":[
        "Kangra"
    ],
    "name:pan_x_preferred":[
        "\u0a15\u0a3e\u0a02\u0a17\u0a5c\u0a3e"
    ],
    "name:pol_x_preferred":[
        "Kangra"
    ],
    "name:rus_x_preferred":[
        "\u041a\u0430\u043d\u0433\u0440\u0430"
    ],
    "name:swe_x_preferred":[
        "Kangra"
    ],
    "name:tam_x_preferred":[
        "\u0b95\u0b99\u0bcd\u0b95\u0bcd\u0bb0\u0bbe"
    ],
    "name:tel_x_preferred":[
        "\u0c15\u0c02\u0c17\u0c4d\u0c30\u0c3e"
    ],
    "name:urd_x_preferred":[
        "\u06a9\u0627\u0646\u06af\u0691\u06c1"
    ],
    "wof:name":"Kangra",
    "wof:placetype":"locality"
},
  "geometry": {"coordinates":[77.73084,30.54718],"type":"Point"}
}