{
  "type": "Feature",
  "properties": {
    "gn:admin1_code":"34.0",
    "gn:admin2_code":"204.0",
    "gn:asciiname":"Hira Chapra",
    "gn:country_code":"IN",
    "gn:dem":69,
    "gn:feature_class":"P",
    "gn:feature_code":"PPL",
    "gn:name":"H\u012br\u0101 Ch\u0101pra",
    "gn:population":0,
    "gn:timezone":"Asia/Kolkata",
    "iso:country":"IN",
    "wof:name":"Hira Chapra",
    "wof:placetype":"locality"
},
  "geometry": {"coordinates":[84.89228,26.41014],"type":"Point"}
}