{
  "type": "Feature",
  "properties": {
    "gn:admin1_code":"36",
    "gn:admin2_code":"202.0",
    "gn:asciiname":"Mindol Khurd",
    "gn:country_code":"IN",
    "gn:dem":171,
    "gn:feature_class":"P",
    "gn:feature_code":"PPL",
    "gn:name":"Mindol Khurd",
    "gn:population":0,
    "gn:timezone":"Asia/Kolkata",
    "iso:country":"IN",
    "ks:ks_name":"Mindaul Khurd",
    "ks:ks_pop":216,
    "ks:ks_type":"VILLAGE",
    "ks:ks_uagg_main":0,
    "name:eng_x_preferred":[
        "Mindaul Khurd"
    ],
    "wof:name":"Mindaul Khurd",
    "wof:placetype":"neighbourhood",
    "wof:population":216
},
  "geometry": {"coordinates":[78.81356700000001,27.727295],"type":"Point"}
}