{
  "type": "Feature",
  "properties": {
    "gn:admin1_code":"21.0",
    "gn:admin2_code":"371.0",
    "gn:asciiname":"Ludung",
    "gn:country_code":"IN",
    "gn:dem":249,
    "gn:feature_class":"P",
    "gn:feature_code":"PPL",
    "gn:name":"Ludung",
    "gn:population":0,
    "gn:timezone":"Asia/Kolkata",
    "iso:country":"IN",
    "wof:name":"Ludung",
    "wof:placetype":"locality"
},
  "geometry": {"coordinates":[84.27561,21.82007],"type":"Point"}
}