{
  "type": "Feature",
  "properties": {
    "iso:country":"IN",
    "ks:ks_name":"Bangarada",
    "ks:ks_pop":96,
    "ks:ks_type":"VILLAGE",
    "name:eng_x_preferred":[
        "Bangarada"
    ],
    "wof:name":"Bangarada",
    "wof:placetype":"locality",
    "wof:population":96
},
  "geometry": {"coordinates":[84.13988999999999,18.854196],"type":"Point"}
}