{
  "type": "Feature",
  "properties": {
    "iso:country":"IN",
    "ks:ks_name":"Dasaripalem",
    "ks:ks_pop":5239,
    "ks:ks_type":"VILLAGE",
    "name:eng_x_preferred":[
        "Dasaripalem"
    ],
    "wof:name":"Dasaripalem",
    "wof:placetype":"locality",
    "wof:population":5239
},
  "geometry": {"coordinates":[79.902902,16.212091],"type":"Point"}
}