{
  "type": "Feature",
  "properties": {
    "gn:admin1_code":"36",
    "gn:admin2_code":"194.0",
    "gn:asciiname":"Inglis Pali Chak",
    "gn:country_code":"IN",
    "gn:dem":92,
    "gn:feature_class":"P",
    "gn:feature_code":"PPL",
    "gn:name":"Inglis P\u0101l\u012b Chak",
    "gn:population":0,
    "gn:timezone":"Asia/Kolkata",
    "iso:country":"IN",
    "wof:name":"Inglis Pali Chak",
    "wof:placetype":"neighbourhood"
},
  "geometry": {"coordinates":[82.48654999999999,25.55848],"type":"Point"}
}