{
  "type": "Feature",
  "properties": {
    "iso:country":"IN",
    "ks:ks_name":"Manglasar",
    "ks:ks_pop":377,
    "ks:ks_type":"HABITATION",
    "name:eng_x_preferred":[
        "Manglasar"
    ],
    "wof:name":"Manglasar",
    "wof:placetype":"locality",
    "wof:population":377
},
  "geometry": {"coordinates":[71.558628,25.053642],"type":"Point"}
}