{
  "type": "Feature",
  "properties": {
    "iso:country":"IN",
    "ks:ks_name":"Chinnaboompatti",
    "ks:ks_pop":242,
    "ks:ks_type":"HABITATION",
    "name:eng_x_preferred":[
        "Chinnaboompatti"
    ],
    "wof:name":"Chinnaboompatti",
    "wof:placetype":"locality",
    "wof:population":242
},
  "geometry": {"coordinates":[78.51650100000001,12.230995],"type":"Point"}
}