{
  "type": "Feature",
  "properties": {
    "iso:country":"IN",
    "ks:ks_name":"Munyanaikthanda",
    "ks:ks_pop":41,
    "ks:ks_type":"HABITATION",
    "name:eng_x_preferred":[
        "Munyanaikthanda"
    ],
    "wof:name":"Munyanaikthanda",
    "wof:placetype":"locality",
    "wof:population":41
},
  "geometry": {"coordinates":[79.248062,17.939726],"type":"Point"}
}