{
  "type": "Feature",
  "properties": {
    "iso:country":"IN",
    "ks:ks_name":"Harthaje",
    "ks:ks_pop":120,
    "ks:ks_type":"HABITATION",
    "name:eng_x_preferred":[
        "Harthaje"
    ],
    "wof:name":"Harthaje",
    "wof:placetype":"locality",
    "wof:population":120
},
  "geometry": {"coordinates":[75.353448,13.094736],"type":"Point"}
}