{
  "type": "Feature",
  "properties": {
    "gn:admin1_code":"35.0",
    "gn:admin2_code":"425.0",
    "gn:asciiname":"Mariya Chhoti",
    "gn:country_code":"IN",
    "gn:dem":469,
    "gn:feature_class":"P",
    "gn:feature_code":"PPL",
    "gn:name":"Mariy\u0101 Chhoti",
    "gn:population":0,
    "gn:timezone":"Asia/Kolkata",
    "iso:country":"IN",
    "wof:name":"Mariya Chhoti",
    "wof:placetype":"locality"
},
  "geometry": {"coordinates":[79.18764,24.14515],"type":"Point"}
}