{
  "type": "Feature",
  "properties": {
    "gn:admin1_code":"36.0",
    "gn:admin2_code":"138",
    "gn:asciiname":"Jani Khurd",
    "gn:country_code":"IN",
    "gn:dem":226,
    "gn:feature_class":"P",
    "gn:feature_code":"PPL",
    "gn:name":"J\u0101ni Khurd",
    "gn:population":0,
    "gn:timezone":"Asia/Kolkata",
    "iso:country":"IN",
    "name:und_x_variant":[
        "J\u0101ni Khurd",
        "J\u0101ni"
    ],
    "wof:name":"Jani Khurd",
    "wof:placetype":"locality"
},
  "geometry": {"coordinates":[77.56278,28.96195],"type":"Point"}
}