{
  "type": "Feature",
  "properties": {
    "iso:country":"IN",
    "ks:ks_name":"Rashkhali",
    "ks:ks_pop":7391,
    "ks:ks_type":"VILLAGE",
    "name:eng_x_preferred":[
        "Rashkhali"
    ],
    "wof:name":"Rashkhali",
    "wof:placetype":"locality",
    "wof:population":7391
},
  "geometry": {"coordinates":[88.35462699999999,22.334629],"type":"Point"}
}