{
  "type": "Feature",
  "properties": {
    "gn:admin1_code":"02",
    "gn:admin2_code":"549.0",
    "gn:asciiname":"Paruchuru",
    "gn:country_code":"IN",
    "gn:dem":15,
    "gn:feature_class":"P",
    "gn:feature_code":"PPL",
    "gn:name":"Paruch\u016bru",
    "gn:population":0,
    "gn:timezone":"Asia/Kolkata",
    "iso:country":"IN",
    "wof:name":"Paruchuru",
    "wof:placetype":"neighbourhood"
},
  "geometry": {"coordinates":[80.27493,15.97091],"type":"Point"}
}