{
  "type": "Feature",
  "properties": {
    "iso:country":"IN",
    "ks:ks_name":"Rajaveli",
    "ks:ks_pop":153,
    "ks:ks_type":"HABITATION",
    "name:eng_x_preferred":[
        "Rajaveli"
    ],
    "wof:name":"Rajaveli",
    "wof:placetype":"locality",
    "wof:population":153
},
  "geometry": {"coordinates":[78.88681200000001,9.300151],"type":"Point"}
}