{
  "type": "Feature",
  "properties": {
    "gn:admin1_code":"24",
    "gn:admin2_code":"118.0",
    "gn:asciiname":"Pandon ka Gudha",
    "gn:country_code":"IN",
    "gn:dem":359,
    "gn:feature_class":"P",
    "gn:feature_code":"PPL",
    "gn:name":"Pandon ka G\u016bdha",
    "gn:population":0,
    "gn:timezone":"Asia/Kolkata",
    "iso:country":"IN",
    "wof:name":"Pandon ka Gudha",
    "wof:placetype":"neighbourhood"
},
  "geometry": {"coordinates":[73.81681,25.68445],"type":"Point"}
}