{
  "type": "Feature",
  "properties": {
    "iso:country":"IN",
    "ks:ks_name":"Navinvasahat",
    "ks:ks_pop":39,
    "ks:ks_type":"HABITATION",
    "name:eng_x_preferred":[
        "Navinvasahat"
    ],
    "wof:name":"Navinvasahat",
    "wof:placetype":"locality",
    "wof:population":39
},
  "geometry": {"coordinates":[73.60803300000001,17.049172],"type":"Point"}
}