{
  "type": "Feature",
  "properties": {
    "iso:country":"IN",
    "ks:ks_name":"Belambar",
    "ks:ks_pop":202,
    "ks:ks_type":"HABITATION",
    "name:eng_x_preferred":[
        "Belambar"
    ],
    "wof:name":"Belambar",
    "wof:placetype":"locality",
    "wof:population":202
},
  "geometry": {"coordinates":[74.29244,14.648739],"type":"Point"}
}