{
  "type": "Feature",
  "properties": {
    "gn:admin1_code":"35.0",
    "gn:admin2_code":"432.0",
    "gn:asciiname":"Deopura",
    "gn:country_code":"IN",
    "gn:dem":379,
    "gn:feature_class":"P",
    "gn:feature_code":"PPL",
    "gn:name":"Deopura",
    "gn:population":0,
    "gn:timezone":"Asia/Kolkata",
    "iso:country":"IN",
    "wof:name":"Deopura",
    "wof:placetype":"locality"
},
  "geometry": {"coordinates":[75.14814,24.78661],"type":"Point"}
}