{
  "type": "Feature",
  "properties": {
    "iso:country":"IN",
    "ks:ks_name":"Kundikheda",
    "ks:ks_pop":577,
    "ks:ks_type":"HABITATION",
    "name:eng_x_preferred":[
        "Kundikheda"
    ],
    "wof:name":"Kundikheda",
    "wof:placetype":"locality",
    "wof:population":577
},
  "geometry": {"coordinates":[76.29301599999999,24.157302],"type":"Point"}
}