{
  "type": "Feature",
  "properties": {
    "iso:country":"IN",
    "ks:ks_name":"Sultanpur Hai",
    "ks:ks_pop":85,
    "ks:ks_type":"VILLAGE",
    "ks:ks_uagg_main":0,
    "name:eng_x_preferred":[
        "Sultanpur Hai"
    ],
    "wof:name":"Sultanpur Hai",
    "wof:placetype":"locality",
    "wof:population":85
},
  "geometry": {"coordinates":[82.693753,25.775474],"type":"Point"}
}