{
  "type": "Feature",
  "properties": {
    "iso:country":"IN",
    "ks:ks_name":"Deliya Kheri",
    "ks:ks_pop":214,
    "ks:ks_type":"HABITATION",
    "name:eng_x_preferred":[
        "Deliya Kheri"
    ],
    "wof:name":"Deliya Kheri",
    "wof:placetype":"locality",
    "wof:population":214
},
  "geometry": {"coordinates":[75.792947,24.450614],"type":"Point"}
}