{
  "type": "Feature",
  "properties": {
    "iso:country":"IN",
    "ks:ks_name":"Rupwaliya",
    "ks:ks_pop":452,
    "ks:ks_type":"VILLAGE",
    "name:eng_x_preferred":[
        "Rupwaliya"
    ],
    "wof:name":"Rupwaliya",
    "wof:placetype":"locality",
    "wof:population":452
},
  "geometry": {"coordinates":[84.169995,27.373844],"type":"Point"}
}