{
  "type": "Feature",
  "properties": {
    "iso:country":"IN",
    "ks:ks_alt_nam":"EttalKadu",
    "ks:ks_name":"Ettalkadu",
    "ks:ks_pop":110,
    "ks:ks_type":"HABITATION",
    "name:eng_x_preferred":[
        "Ettalkadu"
    ],
    "wof:name":"Ettalkadu",
    "wof:placetype":"locality",
    "wof:population":110
},
  "geometry": {"coordinates":[78.11187200000001,11.954895],"type":"Point"}
}