{
  "type": "Feature",
  "properties": {
    "iso:country":"IN",
    "ks:ks_name":"Jot Sahabaj",
    "ks:ks_pop":1489,
    "ks:ks_type":"VILLAGE",
    "ks:ks_uagg_main":0,
    "name:eng_x_preferred":[
        "Jot Sahabaj"
    ],
    "wof:name":"Jot Sahabaj",
    "wof:placetype":"neighbourhood",
    "wof:population":1489
},
  "geometry": {"coordinates":[88.35169,24.267441],"type":"Point"}
}