{
  "type": "Feature",
  "properties": {
    "iso:country":"IN",
    "ks:ks_name":"Jamin Hathipur",
    "ks:ks_pop":363,
    "ks:ks_type":"HABITATION",
    "name:eng_x_preferred":[
        "Jamin Hathipur"
    ],
    "wof:name":"Jamin Hathipur",
    "wof:placetype":"locality",
    "wof:population":363
},
  "geometry": {"coordinates":[83.536559,25.895948],"type":"Point"}
}