{
  "type": "Feature",
  "properties": {
    "iso:country":"IN",
    "ks:ks_name":"Phillobari T E 284 285",
    "ks:ks_pop":1302,
    "ks:ks_type":"HABITATION",
    "name:eng_x_preferred":[
        "Phillobari T E 284 285"
    ],
    "wof:name":"Phillobari T E 284 285",
    "wof:placetype":"locality",
    "wof:population":1302
},
  "geometry": {"coordinates":[95.75258599999999,27.541181],"type":"Point"}
}