{
  "type": "Feature",
  "properties": {
    "iso:country":"IN",
    "ks:ks_name":"Chikaldongri",
    "ks:ks_type":"VILLAGE",
    "name:eng_x_preferred":[
        "Chikaldongri"
    ],
    "wof:name":"Chikaldongri",
    "wof:placetype":"neighbourhood"
},
  "geometry": {"coordinates":[72.78621699999999,19.480773],"type":"Point"}
}