{
  "type": "Feature",
  "properties": {
    "iso:country":"IN",
    "ks:ks_alt_nam":"Janda  keri",
    "ks:ks_name":"Janda Keri",
    "ks:ks_pop":112,
    "ks:ks_type":"HABITATION",
    "name:eng_x_preferred":[
        "Janda Keri"
    ],
    "name:eng_x_variant":[
        "Janda  keri"
    ],
    "wof:name":"Janda Keri",
    "wof:placetype":"locality",
    "wof:population":112
},
  "geometry": {"coordinates":[75.014527,14.551138],"type":"Point"}
}