{
  "type": "Feature",
  "properties": {
    "iso:country":"IN",
    "ks:ks_name":"Alinagar",
    "ks:ks_pop":164,
    "ks:ks_type":"VILLAGE",
    "name:eng_x_preferred":[
        "Alinagar"
    ],
    "wof:name":"Alinagar",
    "wof:placetype":"locality",
    "wof:population":164
},
  "geometry": {"coordinates":[78.26848,26.093305],"type":"Point"}
}