{
  "type": "Feature",
  "properties": {
    "iso:country":"IN",
    "ks:ks_name":"Hathiyar Khurd",
    "ks:ks_pop":259,
    "ks:ks_type":"HABITATION",
    "name:eng_x_preferred":[
        "Hathiyar Khurd"
    ],
    "wof:name":"Hathiyar Khurd",
    "wof:placetype":"locality",
    "wof:population":259
},
  "geometry": {"coordinates":[83.050577,25.50198],"type":"Point"}
}