{
  "type": "Feature",
  "properties": {
    "gn:admin1_code":"10.0",
    "gn:admin2_code":"076",
    "gn:asciiname":"Chhota Khanda",
    "gn:country_code":"IN",
    "gn:dem":223,
    "gn:feature_class":"P",
    "gn:feature_code":"PPL",
    "gn:name":"Chhota Kh\u0101nda",
    "gn:population":0,
    "gn:timezone":"Asia/Kolkata",
    "iso:country":"IN",
    "wof:name":"Chhota Khanda",
    "wof:placetype":"locality"
},
  "geometry": {"coordinates":[76.92464,28.94302],"type":"Point"}
}