{
  "type": "Feature",
  "properties": {
    "gn:admin1_code":"38.0",
    "gn:admin2_code":"347.0",
    "gn:asciiname":"Badhar",
    "gn:country_code":"IN",
    "gn:dem":275,
    "gn:feature_class":"P",
    "gn:feature_code":"PPL",
    "gn:name":"Badh\u0101r",
    "gn:population":0,
    "gn:timezone":"Asia/Kolkata",
    "iso:country":"IN",
    "ks:ks_alt_nam":"Badh\u0101r",
    "ks:ks_name":"Badhar",
    "ks:ks_pop":374,
    "ks:ks_type":"VILLAGE",
    "name:eng_x_preferred":[
        "Badhar"
    ],
    "name:eng_x_variant":[
        "Badh\u0101r"
    ],
    "wof:name":"Badhar",
    "wof:placetype":"locality",
    "wof:population":374
},
  "geometry": {"coordinates":[84.468284,24.246777],"type":"Point"}
}