{
  "type": "Feature",
  "properties": {
    "iso:country":"IN",
    "ks:ks_name":"Jhunkoli",
    "ks:ks_pop":112,
    "ks:ks_type":"VILLAGE",
    "name:eng_x_preferred":[
        "Jhunkoli"
    ],
    "wof:name":"Jhunkoli",
    "wof:placetype":"locality",
    "wof:population":112
},
  "geometry": {"coordinates":[80.153802,29.647571],"type":"Point"}
}