{
  "type": "Feature",
  "properties": {
    "iso:country":"IN",
    "ks:ks_name":"Adavale Kh.",
    "ks:ks_pop":426,
    "ks:ks_type":"VILLAGE",
    "name:eng_x_preferred":[
        "Adavale Kh."
    ],
    "wof:name":"Adavale Kh.",
    "wof:placetype":"locality",
    "wof:population":426
},
  "geometry": {"coordinates":[73.536991,18.014649],"type":"Point"}
}