{
  "type": "Feature",
  "properties": {
    "iso:country":"IN",
    "ks:ks_name":"Khajuripada",
    "ks:ks_pop":1995,
    "ks:ks_type":"VILLAGE",
    "ks:ks_uagg_main":0,
    "name:eng_x_preferred":[
        "Khajuripada"
    ],
    "wof:name":"Khajuripada",
    "wof:placetype":"neighbourhood",
    "wof:population":1995
},
  "geometry": {"coordinates":[85.52439699999999,20.003253],"type":"Point"}
}