{
  "type": "Feature",
  "properties": {
    "iso:country":"IN",
    "ks:ks_name":"Mudhojiwadi",
    "ks:ks_pop":83,
    "ks:ks_type":"VILLAGE",
    "name:eng_x_preferred":[
        "Mudhojiwadi"
    ],
    "wof:name":"Mudhojiwadi",
    "wof:placetype":"locality",
    "wof:population":83
},
  "geometry": {"coordinates":[78.217213,18.400809],"type":"Point"}
}