{
  "type": "Feature",
  "properties": {
    "iso:country":"IN",
    "ks:ks_name":"Somaregadi Tanda I",
    "ks:ks_pop":74,
    "ks:ks_type":"HABITATION",
    "name:eng_x_preferred":[
        "Somaregadi Tanda I"
    ],
    "wof:name":"Somaregadi Tanda I",
    "wof:placetype":"locality",
    "wof:population":74
},
  "geometry": {"coordinates":[78.059732,18.181777],"type":"Point"}
}