{
  "type": "Feature",
  "properties": {
    "gn:admin1_code":"34.0",
    "gn:admin2_code":"236.0",
    "gn:asciiname":"Harakuraha",
    "gn:country_code":"IN",
    "gn:dem":183,
    "gn:feature_class":"P",
    "gn:feature_code":"PPL",
    "gn:name":"Har\u0101kur\u0101ha",
    "gn:population":0,
    "gn:timezone":"Asia/Kolkata",
    "iso:country":"IN",
    "ks:ks_name":"Hara Kuraha",
    "ks:ks_pop":655,
    "ks:ks_type":"VILLAGE",
    "ks:ks_uagg_main":0,
    "name:eng_x_preferred":[
        "Hara Kuraha"
    ],
    "wof:name":"Hara Kuraha",
    "wof:placetype":"neighbourhood",
    "wof:population":655
},
  "geometry": {"coordinates":[85.237492,24.5336],"type":"Point"}
}