{
  "type": "Feature",
  "properties": {
    "iso:country":"IN",
    "ks:ks_name":"Fulhara",
    "ks:ks_pop":395,
    "ks:ks_type":"HABITATION",
    "name:eng_x_preferred":[
        "Fulhara"
    ],
    "wof:name":"Fulhara",
    "wof:placetype":"locality",
    "wof:population":395
},
  "geometry": {"coordinates":[86.568101,24.802918],"type":"Point"}
}