{
  "type": "Feature",
  "properties": {
    "iso:country":"IN",
    "ks:ks_name":"Pritamnagar",
    "ks:ks_pop":120,
    "ks:ks_type":"HABITATION",
    "name:eng_x_preferred":[
        "Pritamnagar"
    ],
    "wof:name":"Pritamnagar",
    "wof:placetype":"locality",
    "wof:population":120
},
  "geometry": {"coordinates":[78.935405,28.041637],"type":"Point"}
}