{
  "type": "Feature",
  "properties": {
    "iso:country":"IN",
    "ks:ks_name":"Baibera",
    "ks:ks_pop":257,
    "ks:ks_type":"VILLAGE",
    "name:eng_x_preferred":[
        "Baibera"
    ],
    "wof:name":"Baibera",
    "wof:placetype":"locality",
    "wof:population":257
},
  "geometry": {"coordinates":[85.40438,22.621333],"type":"Point"}
}