{
  "type": "Feature",
  "properties": {
    "gn:admin1_code":"36",
    "gn:admin2_code":"184.0",
    "gn:asciiname":"Gopiapur",
    "gn:country_code":"IN",
    "gn:dem":86,
    "gn:feature_class":"P",
    "gn:feature_code":"PPL",
    "gn:name":"Gopi\u0101pur",
    "gn:population":0,
    "gn:timezone":"Asia/Kolkata",
    "iso:country":"IN",
    "ks:ks_name":"Gopipur",
    "ks:ks_pop":156,
    "ks:ks_type":"HABITATION",
    "name:eng_x_preferred":[
        "Gopipur"
    ],
    "name:eng_x_variant":[
        "Gopiapur"
    ],
    "wof:name":"Gopipur",
    "wof:placetype":"locality",
    "wof:population":156
},
  "geometry": {"coordinates":[83.15404599999999,27.229811],"type":"Point"}
}