{
  "type": "Feature",
  "properties": {
    "iso:country":"IN",
    "ks:ks_name":"Jhariwada",
    "ks:ks_pop":191,
    "ks:ks_type":"HABITATION",
    "name:eng_x_preferred":[
        "Jhariwada"
    ],
    "wof:name":"Jhariwada",
    "wof:placetype":"locality",
    "wof:population":191
},
  "geometry": {"coordinates":[74.17668,14.844101],"type":"Point"}
}