{
  "type": "Feature",
  "properties": {
    "iso:country":"IN",
    "ks:ks_alt_nam":"MEETHARIYA TALA",
    "ks:ks_name":"Meethariya Tala",
    "ks:ks_pop":400,
    "ks:ks_type":"HABITATION",
    "name:eng_x_preferred":[
        "Meethariya Tala"
    ],
    "wof:name":"Meethariya Tala",
    "wof:placetype":"locality",
    "wof:population":400
},
  "geometry": {"coordinates":[71.120006,25.668164],"type":"Point"}
}