{
  "type": "Feature",
  "properties": {
    "gn:admin1_code":"23",
    "gn:admin2_code":"38.0",
    "gn:asciiname":"Khera",
    "gn:country_code":"IN",
    "gn:dem":274,
    "gn:feature_class":"P",
    "gn:feature_code":"PPL",
    "gn:name":"Khera",
    "gn:population":0,
    "gn:timezone":"Asia/Kolkata",
    "iso:country":"IN",
    "wof:name":"Khera",
    "wof:placetype":"locality"
},
  "geometry": {"coordinates":[75.92071999999997,31.4299],"type":"Point"}
}