{
  "type": "Feature",
  "properties": {
    "iso:country":"IN",
    "ks:ks_name":"Pendri",
    "ks:ks_pop":559,
    "ks:ks_type":"VILLAGE",
    "name:eng_x_preferred":[
        "Pendri"
    ],
    "wof:name":"Pendri",
    "wof:placetype":"locality",
    "wof:population":559
},
  "geometry": {"coordinates":[82.253643,23.344614],"type":"Point"}
}