{
  "type": "Feature",
  "properties": {
    "iso:country":"IN",
    "ks:ks_name":"Sahasram",
    "ks:ks_pop":441,
    "ks:ks_type":"VILLAGE",
    "name:eng_x_preferred":[
        "Sahasram"
    ],
    "wof:name":"Sahasram",
    "wof:placetype":"locality",
    "wof:population":441
},
  "geometry": {"coordinates":[86.992171,24.703536],"type":"Point"}
}