{
  "type": "Feature",
  "properties": {
    "iso:country":"IN",
    "ks:ks_name":"Jampara",
    "ks:ks_pop":52,
    "ks:ks_type":"HABITATION",
    "name:eng_x_preferred":[
        "Jampara"
    ],
    "wof:name":"Jampara",
    "wof:placetype":"locality",
    "wof:population":52
},
  "geometry": {"coordinates":[84.391351,22.239904],"type":"Point"}
}