{
  "type": "Feature",
  "properties": {
    "iso:country":"IN",
    "ks:ks_name":"Ramdevpur",
    "ks:ks_pop":40,
    "ks:ks_type":"HABITATION",
    "name:eng_x_preferred":[
        "Ramdevpur"
    ],
    "wof:name":"Ramdevpur",
    "wof:placetype":"locality",
    "wof:population":40
},
  "geometry": {"coordinates":[81.47635099999999,25.17355],"type":"Point"}
}