{
  "type": "Feature",
  "properties": {
    "iso:country":"IN",
    "ks:ks_name":"Gottalgudam",
    "ks:ks_pop":198,
    "ks:ks_type":"HABITATION",
    "name:eng_x_preferred":[
        "Gottalgudam"
    ],
    "wof:name":"Gottalgudam",
    "wof:placetype":"locality",
    "wof:population":198
},
  "geometry": {"coordinates":[79.967114,19.494857],"type":"Point"}
}