{
  "type": "Feature",
  "properties": {
    "iso:country":"IN",
    "ks:ks_alt_nam":"Dhage wasti",
    "ks:ks_name":"Dhage Wasti",
    "ks:ks_pop":5,
    "ks:ks_type":"HABITATION",
    "name:eng_x_preferred":[
        "Dhage Wasti"
    ],
    "wof:name":"Dhage Wasti",
    "wof:placetype":"locality",
    "wof:population":5
},
  "geometry": {"coordinates":[74.99042,18.860343],"type":"Point"}
}