{
  "type": "Feature",
  "properties": {
    "iso:country":"IN",
    "ks:ks_name":"Sanaramchandrapur",
    "ks:ks_pop":253,
    "ks:ks_type":"HABITATION",
    "name:eng_x_preferred":[
        "Sanaramchandrapur"
    ],
    "wof:name":"Sanaramchandrapur",
    "wof:placetype":"locality",
    "wof:population":253
},
  "geometry": {"coordinates":[86.127247,21.768765],"type":"Point"}
}