{
  "type": "Feature",
  "properties": {
    "gn:admin1_code":"36",
    "gn:admin2_code":"199.0",
    "gn:asciiname":"Dhobaha Deoghata",
    "gn:country_code":"IN",
    "gn:dem":167,
    "gn:feature_class":"P",
    "gn:feature_code":"PPL",
    "gn:name":"Dhobaha Deoghata",
    "gn:population":0,
    "gn:timezone":"Asia/Kolkata",
    "iso:country":"IN",
    "ks:ks_name":"Dhobaha Dewghata",
    "ks:ks_pop":982,
    "ks:ks_type":"VILLAGE",
    "name:eng_x_preferred":[
        "Dhobaha Dewghata"
    ],
    "name:eng_x_variant":[
        "Dhobaha Deoghata"
    ],
    "wof:name":"Dhobaha Dewghata",
    "wof:placetype":"locality",
    "wof:population":982
},
  "geometry": {"coordinates":[82.359182,24.903828],"type":"Point"}
}