{
  "type": "Feature",
  "properties": {
    "gn:admin1_code":"21",
    "gn:admin2_code":"395.0",
    "gn:asciiname":"Sulia",
    "gn:country_code":"IN",
    "gn:dem":517,
    "gn:feature_class":"P",
    "gn:feature_code":"PPL",
    "gn:name":"Sulia",
    "gn:population":0,
    "gn:timezone":"Asia/Kolkata",
    "iso:country":"IN",
    "ks:ks_name":"Suliya",
    "ks:ks_pop":142,
    "ks:ks_type":"VILLAGE",
    "name:eng_x_preferred":[
        "Suliya"
    ],
    "name:eng_x_variant":[
        "Sulia"
    ],
    "wof:name":"Suliya",
    "wof:placetype":"locality",
    "wof:population":142
},
  "geometry": {"coordinates":[83.269459,19.860905],"type":"Point"}
}