{
  "type": "Feature",
  "properties": {
    "iso:country":"IN",
    "ks:ks_name":"Patha Rajanpalem",
    "ks:ks_pop":446,
    "ks:ks_type":"HABITATION",
    "name:eng_x_preferred":[
        "Patha Rajanpalem"
    ],
    "wof:name":"Patha Rajanpalem",
    "wof:placetype":"locality",
    "wof:population":446
},
  "geometry": {"coordinates":[83.065561,17.55874],"type":"Point"}
}