{
  "type": "Feature",
  "properties": {
    "iso:country":"IN",
    "ks:ks_name":"Buripara",
    "ks:ks_pop":162,
    "ks:ks_type":"VILLAGE",
    "name:eng_x_preferred":[
        "Buripara"
    ],
    "wof:name":"Buripara",
    "wof:placetype":"locality",
    "wof:population":162
},
  "geometry": {"coordinates":[86.879132,23.239391],"type":"Point"}
}