{
  "type": "Feature",
  "properties": {
    "gn:admin1_code":"2.0",
    "gn:admin2_code":"548.0",
    "gn:asciiname":"Mallampudi",
    "gn:country_code":"IN",
    "gn:dem":23,
    "gn:feature_class":"P",
    "gn:feature_code":"PPL",
    "gn:name":"Mallamp\u016bdi",
    "gn:population":0,
    "gn:timezone":"Asia/Kolkata",
    "iso:country":"IN",
    "wof:name":"Mallampudi",
    "wof:placetype":"locality"
},
  "geometry": {"coordinates":[80.62685,16.42562],"type":"Point"}
}