{
  "type": "Feature",
  "properties": {
    "gn:admin1_code":"34.0",
    "gn:admin2_code":"209.0",
    "gn:asciiname":"Barakamat Chistipur",
    "gn:country_code":"IN",
    "gn:dem":55,
    "gn:feature_class":"P",
    "gn:feature_code":"PPL",
    "gn:name":"B\u0101r\u0101k\u0101mat Chist\u012bpur",
    "gn:population":0,
    "gn:timezone":"Asia/Kolkata",
    "iso:country":"IN",
    "ks:ks_alt_nam":"B\u0101r\u0101k\u0101mat Chist\u012bpur",
    "ks:ks_name":"Barakamat Chistipur",
    "ks:ks_pop":743,
    "ks:ks_type":"VILLAGE",
    "ks:ks_uagg_main":0,
    "name:eng_x_preferred":[
        "Barakamat Chistipur"
    ],
    "name:eng_x_variant":[
        "B\u0101r\u0101k\u0101mat Chist\u012bpur"
    ],
    "wof:name":"Barakamat Chistipur",
    "wof:placetype":"locality",
    "wof:population":743
},
  "geometry": {"coordinates":[87.44089200000001,26.156437],"type":"Point"}
}