{
  "type": "Feature",
  "properties": {
    "iso:country":"IN",
    "ks:ks_name":"Anna Nagar",
    "ks:ks_pop":345,
    "ks:ks_type":"HABITATION",
    "ks:ks_uagg_main":0,
    "name:eng_x_preferred":[
        "Anna Nagar"
    ],
    "wof:name":"Anna Nagar",
    "wof:placetype":"neighbourhood",
    "wof:population":345
},
  "geometry": {"coordinates":[79.657023,11.540127],"type":"Point"}
}