{
  "type": "Feature",
  "properties": {
    "gn:admin1_code":"19.0",
    "gn:admin2_code":"575.0",
    "gn:asciiname":"Kamila",
    "gn:country_code":"IN",
    "gn:dem":130,
    "gn:feature_class":"P",
    "gn:feature_code":"PPL",
    "gn:name":"Kamila",
    "gn:population":0,
    "gn:timezone":"Asia/Kolkata",
    "iso:country":"IN",
    "ks:ks_name":"Kamila",
    "ks:ks_pop":18,
    "ks:ks_type":"HABITATION",
    "name:eng_x_preferred":[
        "Kamila"
    ],
    "wof:name":"Kamila",
    "wof:placetype":"locality",
    "wof:population":18
},
  "geometry": {"coordinates":[75.521697,12.655288],"type":"Point"}
}