{
  "type": "Feature",
  "properties": {
    "gn:admin1_code":"35",
    "gn:admin2_code":"452.0",
    "gn:asciiname":"Sivni",
    "gn:country_code":"IN",
    "gn:dem":446,
    "gn:feature_class":"P",
    "gn:feature_code":"PPL",
    "gn:name":"Sivni",
    "gn:population":0,
    "gn:timezone":"Asia/Kolkata",
    "iso:country":"IN",
    "wof:name":"Sivni",
    "wof:placetype":"neighbourhood"
},
  "geometry": {"coordinates":[79.45225000000001,22.89],"type":"Point"}
}