{
  "type": "Feature",
  "properties": {
    "iso:country":"IN",
    "ks:ks_name":"Upasapura",
    "ks:ks_pop":390,
    "ks:ks_type":"VILLAGE",
    "name:eng_x_preferred":[
        "Upasapura"
    ],
    "wof:name":"Upasapura",
    "wof:placetype":"locality",
    "wof:population":390
},
  "geometry": {"coordinates":[78.133922,12.887601],"type":"Point"}
}