{
  "type": "Feature",
  "properties": {
    "iso:country":"IN",
    "ks:ks_name":"Ratanpuria",
    "ks:ks_pop":75,
    "ks:ks_type":"HABITATION",
    "name:eng_x_preferred":[
        "Ratanpuria"
    ],
    "wof:name":"Ratanpuria",
    "wof:placetype":"locality",
    "wof:population":75
},
  "geometry": {"coordinates":[76.818073,24.083046],"type":"Point"}
}