{
  "type": "Feature",
  "properties": {
    "iso:country":"IN",
    "ks:ks_name":"Pettippara",
    "ks:ks_pop":324,
    "ks:ks_type":"HABITATION",
    "name:eng_x_preferred":[
        "Pettippara"
    ],
    "wof:name":"Pettippara",
    "wof:placetype":"locality",
    "wof:population":324
},
  "geometry": {"coordinates":[77.15277500000001,8.519383],"type":"Point"}
}