{
  "type": "Feature",
  "properties": {
    "iso:country":"IN",
    "ks:ks_name":"Kumharan Purwa",
    "ks:ks_pop":195,
    "ks:ks_type":"HABITATION",
    "ks:ks_uagg_main":0,
    "name:eng_x_preferred":[
        "Kumharan Purwa"
    ],
    "wof:name":"Kumharan Purwa",
    "wof:placetype":"neighbourhood",
    "wof:population":195
},
  "geometry": {"coordinates":[82.072357,27.272573],"type":"Point"}
}