{
  "type": "Feature",
  "properties": {
    "iso:country":"IN",
    "ks:ks_name":"Manjlagudde",
    "ks:ks_pop":153,
    "ks:ks_type":"HABITATION",
    "name:eng_x_preferred":[
        "Manjlagudde"
    ],
    "wof:name":"Manjlagudde",
    "wof:placetype":"locality",
    "wof:population":153
},
  "geometry": {"coordinates":[74.956587,13.067347],"type":"Point"}
}