{
  "type": "Feature",
  "properties": {
    "iso:country":"IN",
    "ks:ks_name":"Adharhedi Msisopur Must",
    "ks:ks_pop":86,
    "ks:ks_type":"HABITATION",
    "name:eng_x_preferred":[
        "Adharhedi Msisopur Must"
    ],
    "wof:name":"Adharhedi Msisopur Must",
    "wof:placetype":"locality",
    "wof:population":86
},
  "geometry": {"coordinates":[77.66119500000001,29.960815],"type":"Point"}
}