{
  "type": "Feature",
  "properties": {
    "iso:country":"IN",
    "ks:ks_name":"Garhi Sanjar Khan",
    "ks:ks_pop":2607,
    "ks:ks_type":"VILLAGE",
    "ks:ks_uagg_main":0,
    "name:eng_x_preferred":[
        "Garhi Sanjar Khan"
    ],
    "wof:name":"Garhi Sanjar Khan",
    "wof:placetype":"neighbourhood",
    "wof:population":2607
},
  "geometry": {"coordinates":[80.69489299999999,26.915536],"type":"Point"}
}