{
  "type": "Feature",
  "properties": {
    "iso:country":"IN",
    "ks:ks_name":"Pedakothuru",
    "ks:ks_pop":277,
    "ks:ks_type":"HABITATION",
    "name:eng_x_preferred":[
        "Pedakothuru"
    ],
    "wof:name":"Pedakothuru",
    "wof:placetype":"locality",
    "wof:population":277
},
  "geometry": {"coordinates":[82.534323,17.946354],"type":"Point"}
}