{
  "type": "Feature",
  "properties": {
    "gn:admin1_code":"30.0",
    "gn:admin2_code":"253.0",
    "gn:asciiname":"Changlang",
    "gn:country_code":"IN",
    "gn:dem":371,
    "gn:feature_class":"P",
    "gn:feature_code":"PPL",
    "gn:name":"Changlang",
    "gn:population":0,
    "gn:timezone":"Asia/Kolkata",
    "iso:country":"IN",
    "name:ara_x_preferred":[
        "\u0634\u0627\u0646\u062c\u0644\u0627\u0646\u062c"
    ],
    "name:ben_x_preferred":[
        "\u099a\u09cd\u09af\u09be\u0982\u09b2\u09be\u0982"
    ],
    "name:bpy_x_preferred":[
        "\u099a\u09cd\u09af\u09be\u0982\u09b2\u09be\u0982"
    ],
    "name:fra_x_preferred":[
        "Changlang"
    ],
    "name:guj_x_preferred":[
        "\u0a9a\u0ac7\u0a82\u0a97\u0ab2\u0acb\u0aa8\u0acd\u0a97"
    ],
    "name:hin_x_preferred":[
        "\u091a\u093e\u0902\u0917\u0932\u093e\u0902\u0917"
    ],
    "name:ita_x_preferred":[
        "Changlang"
    ],
    "name:mlg_x_preferred":[
        "Changlang"
    ],
    "name:msa_x_preferred":[
        "Changlang"
    ],
    "name:new_x_preferred":[
        "\u091a\u093e\u0919\u0932\u093e\u0919"
    ],
    "name:nld_x_preferred":[
        "Changlang"
    ],
    "name:rus_x_preferred":[
        "\u0427\u0430\u043d\u0433\u043b\u0430\u043d\u0433"
    ],
    "name:spa_x_preferred":[
        "Changlang"
    ],
    "name:tam_x_preferred":[
        "\u0b9a\u0b99\u0bcd\u0bb2\u0b99\u0bcd"
    ],
    "name:tgl_x_preferred":[
        "Changlang"
    ],
    "name:urd_x_preferred":[
        "\u0686\u0627\u0646\u06af \u0644\u0627\u0646\u06af"
    ],
    "name:vie_x_preferred":[
        "Changlang"
    ],
    "wof:name":"Changlang",
    "wof:placetype":"locality"
},
  "geometry": {"coordinates":[95.73486,27.13177],"type":"Point"}
}