{
  "type": "Feature",
  "properties": {
    "gn:admin1_code":"30.0",
    "gn:admin2_code":"253.0",
    "gn:asciiname":"Changlang",
    "gn:country_code":"IN",
    "gn:dem":371,
    "gn:feature_class":"P",
    "gn:feature_code":"PPL",
    "gn:name":"Changlang",
    "gn:population":0,
    "gn:timezone":"Asia/Kolkata",
    "iso:country":"IN",
    "wof:name":"Changlang",
    "wof:placetype":"locality"
},
  "geometry": {"coordinates":[95.73486,27.13177],"type":"Point"}
}