{
  "type": "Feature",
  "properties": {
    "gn:admin1_code":"30.0",
    "gn:admin2_code":"253.0",
    "gn:asciiname":"Changlang",
    "gn:country_code":"IN",
    "gn:dem":371,
    "gn:feature_class":"P",
    "gn:feature_code":"PPL",
    "gn:name":"Changlang",
    "gn:population":0,
    "gn:timezone":"Asia/Kolkata",
    "iso:country":"IN",
    "name:ara_x_preferred":[
        "\u0634\u0627\u0646\u062c\u0644\u0627\u0646\u062c"
    ],
    "name:ben_bn_x_preferred":[
        "\u099a\u09be\u0982\u09b2\u09be\u0982"
    ],
    "name:ben_in_x_preferred":[
        "\u099a\u09be\u0982\u09b2\u09be\u0982"
    ],
    "name:ben_x_preferred":[
        "\u099a\u09cd\u09af\u09be\u0982\u09b2\u09be\u0982"
    ],
    "name:bpy_x_preferred":[
        "\u099a\u09cd\u09af\u09be\u0982\u09b2\u09be\u0982"
    ],
    "name:fra_x_preferred":[
        "Changlang"
    ],
    "name:guj_x_preferred":[
        "\u0a9a\u0abe\u0a82\u0a97\u0ab2\u0abe\u0a82\u0a97"
    ],
    "name:guj_x_variant":[
        "\u0a9a\u0ac7\u0a82\u0a97\u0ab2\u0acb\u0aa8\u0acd\u0a97"
    ],
    "name:hin_x_preferred":[
        "\u091a\u093e\u0902\u0917\u0932\u093e\u0902\u0917"
    ],
    "name:hin_x_variant":[
        "\u091a\u0902\u0917\u0932\u093e\u0902\u0917"
    ],
    "name:ita_x_preferred":[
        "Changlang"
    ],
    "name:kan_x_preferred":[
        "\u0c9a\u0cbe\u0c82\u0c97\u0ccd\u0cb2\u0cbe\u0c82\u0c97\u0ccd"
    ],
    "name:mal_x_preferred":[
        "\u0d1a\u0d3e\u0d02\u0d17\u0d4d\u0d32\u0d3e\u0d19\u0d4d"
    ],
    "name:mar_x_preferred":[
        "\u091a\u093e\u0902\u0917\u0932\u0902\u0917"
    ],
    "name:mlg_x_preferred":[
        "Changlang"
    ],
    "name:msa_x_preferred":[
        "Changlang"
    ],
    "name:new_x_preferred":[
        "\u091a\u093e\u0919\u0932\u093e\u0919"
    ],
    "name:nld_x_preferred":[
        "Changlang"
    ],
    "name:pan_x_preferred":[
        "\u0a1a\u0a48\u0a02\u0a17\u0a32\u0a48\u0a02\u0a17"
    ],
    "name:rus_x_preferred":[
        "\u0427\u0430\u043d\u0433\u043b\u0430\u043d\u0433"
    ],
    "name:spa_x_preferred":[
        "Changlang"
    ],
    "name:tam_x_preferred":[
        "\u0b9a\u0b99\u0bcd\u0b95\u0bcd\u0bb2\u0bbe\u0b99\u0bcd"
    ],
    "name:tam_x_variant":[
        "\u0b9a\u0b99\u0bcd\u0bb2\u0b99\u0bcd"
    ],
    "name:tel_x_preferred":[
        "\u0c1a\u0c3e\u0c02\u0c17\u0c4d"
    ],
    "name:tgl_x_preferred":[
        "Changlang"
    ],
    "name:urd_x_preferred":[
        "\u0686\u0646\u06af\u0644\u0627\u0646\u06af"
    ],
    "name:urd_x_variant":[
        "\u0686\u0627\u0646\u06af \u0644\u0627\u0646\u06af"
    ],
    "name:vie_x_preferred":[
        "Changlang"
    ],
    "wof:name":"Changlang",
    "wof:placetype":"locality"
},
  "geometry": {"coordinates":[95.73486,27.13177],"type":"Point"}
}