{
  "type": "Feature",
  "properties": {
    "iso:country":"IN",
    "ks:ks_name":"Ankhali",
    "ks:ks_pop":1163,
    "ks:ks_type":"VILLAGE",
    "ks:ks_uagg_main":0,
    "name:eng_x_preferred":[
        "Ankhali"
    ],
    "wof:name":"Ankhali",
    "wof:placetype":"neighbourhood",
    "wof:population":1163
},
  "geometry": {"coordinates":[76.94614799999999,19.493358],"type":"Point"}
}