{
  "type": "Feature",
  "properties": {
    "gn:admin1_code":"28.0",
    "gn:admin2_code":"334.0",
    "gn:asciiname":"Kamra",
    "gn:country_code":"IN",
    "gn:dem":30,
    "gn:feature_class":"P",
    "gn:feature_code":"PPL",
    "gn:name":"K\u0101mra",
    "gn:population":0,
    "gn:timezone":"Asia/Kolkata",
    "iso:country":"IN",
    "name:ara_x_preferred":[
        "\u0643\u0627\u0645\u0631\u0647"
    ],
    "name:fas_x_preferred":[
        "\u06a9\u0627\u0645\u0631\u0647"
    ],
    "name:fra_x_preferred":[
        "Kamra"
    ],
    "name:pnb_x_preferred":[
        "\u06a9\u0627\u0645\u0631\u0627"
    ],
    "name:por_x_preferred":[
        "Kamra"
    ],
    "name:rus_x_preferred":[
        "\u041a\u0430\u043c\u0440\u0430"
    ],
    "name:spa_x_preferred":[
        "Kamra"
    ],
    "name:urd_x_preferred":[
        "\u06a9\u0627\u0645\u0631\u06c1"
    ],
    "wof:name":"Kamra",
    "wof:placetype":"locality"
},
  "geometry": {"coordinates":[87.92367,24.18118],"type":"Point"}
}