{
  "type": "Feature",
  "properties": {
    "iso:country":"IN",
    "ks:ks_alt_nam":"Dharamd\u0101spur",
    "ks:ks_name":"Dharamdaspur",
    "ks:ks_type":"VILLAGE",
    "ks:ks_uagg_main":0,
    "name:eng_x_preferred":[
        "Dharamdaspur"
    ],
    "name:eng_x_variant":[
        "Dharamd\u0101spur"
    ],
    "wof:name":"Dharamdaspur",
    "wof:placetype":"neighbourhood"
},
  "geometry": {"coordinates":[82.957224,26.109953],"type":"Point"}
}