{
  "type": "Feature",
  "properties": {
    "gn:admin1_code":"11.0",
    "gn:admin2_code":"33.0",
    "gn:asciiname":"Dhalth",
    "gn:country_code":"IN",
    "gn:dem":2164,
    "gn:feature_class":"P",
    "gn:feature_code":"PPL",
    "gn:name":"Dhalth",
    "gn:population":0,
    "gn:timezone":"Asia/Kolkata",
    "iso:country":"IN",
    "wof:name":"Dhalth",
    "wof:placetype":"locality"
},
  "geometry": {"coordinates":[77.48348,31.29469000000001],"type":"Point"}
}