{
  "type": "Feature",
  "properties": {
    "gn:admin1_code":"9.0",
    "gn:admin2_code":"487",
    "gn:asciiname":"Dumkhal",
    "gn:country_code":"IN",
    "gn:dem":200,
    "gn:feature_class":"P",
    "gn:feature_code":"PPL",
    "gn:name":"Dumkhal",
    "gn:population":0,
    "gn:timezone":"Asia/Kolkata",
    "iso:country":"IN",
    "wof:name":"Dumkhal",
    "wof:placetype":"locality"
},
  "geometry": {"coordinates":[73.84174,21.73727],"type":"Point"}
}