{
  "type": "Feature",
  "properties": {
    "iso:country":"IN",
    "ks:ks_name":"21 HMH-A",
    "ks:ks_pop":312,
    "ks:ks_type":"VILLAGE",
    "ks:ks_uagg_main":0,
    "name:eng_x_preferred":[
        "21 HMH-A"
    ],
    "wof:name":"21 HMH-A",
    "wof:placetype":"neighbourhood",
    "wof:population":312
},
  "geometry": {"coordinates":[74.273141,29.544432],"type":"Point"}
}