{
  "type": "Feature",
  "properties": {
    "iso:country":"IN",
    "ks:ks_alt_nam":"11 SGR",
    "ks:ks_name":"11 Sgr",
    "ks:ks_pop":70,
    "ks:ks_type":"HABITATION",
    "name:eng_x_preferred":[
        "11 Sgr"
    ],
    "wof:name":"11 Sgr",
    "wof:placetype":"locality",
    "wof:population":70
},
  "geometry": {"coordinates":[73.902179,29.443247],"type":"Point"}
}