{
  "type": "Feature",
  "properties": {
    "gn:admin1_code":"35.0",
    "gn:admin2_code":"431.0",
    "gn:asciiname":"Barwar",
    "gn:country_code":"IN",
    "gn:dem":414,
    "gn:feature_class":"P",
    "gn:feature_code":"PPL",
    "gn:name":"Barw\u0101r",
    "gn:population":0,
    "gn:timezone":"Asia/Kolkata",
    "iso:country":"IN",
    "ks:ks_name":"Badwar",
    "ks:ks_pop":238,
    "ks:ks_type":"VILLAGE",
    "name:eng_x_preferred":[
        "Badwar"
    ],
    "name:eng_x_variant":[
        "Barwar"
    ],
    "wof:name":"Badwar",
    "wof:placetype":"locality",
    "wof:population":238
},
  "geometry": {"coordinates":[80.739853,23.627005],"type":"Point"}
}