{
  "type": "Feature",
  "properties": {
    "iso:country":"IN",
    "ks:ks_name":"Rohela Teje Ka",
    "ks:ks_pop":698,
    "ks:ks_type":"VILLAGE",
    "name:eng_x_preferred":[
        "Rohela Teje Ka"
    ],
    "wof:name":"Rohela Teje Ka",
    "wof:placetype":"locality",
    "wof:population":698
},
  "geometry": {"coordinates":[73.981291,30.473196],"type":"Point"}
}