{
  "type": "Feature",
  "properties": {
    "iso:country":"IN",
    "ks:ks_name":"Mura Basti",
    "ks:ks_pop":495,
    "ks:ks_type":"HABITATION",
    "ks:ks_uagg_main":0,
    "name:eng_x_preferred":[
        "Mura Basti"
    ],
    "wof:name":"Mura Basti",
    "wof:placetype":"neighbourhood",
    "wof:population":495
},
  "geometry": {"coordinates":[95.02398100000001,27.057847],"type":"Point"}
}