{
  "type": "Feature",
  "properties": {
    "iso:country":"IN",
    "ks:ks_alt_nam":"bangalipada",
    "ks:ks_name":"Bangalipada",
    "ks:ks_pop":85,
    "ks:ks_type":"HABITATION",
    "name:eng_x_preferred":[
        "Bangalipada"
    ],
    "wof:name":"Bangalipada",
    "wof:placetype":"locality",
    "wof:population":85
},
  "geometry": {"coordinates":[83.15268,20.118277],"type":"Point"}
}