{
  "type": "Feature",
  "properties": {
    "iso:country":"IN",
    "ks:ks_name":"Bhitarideeh",
    "ks:ks_pop":500,
    "ks:ks_type":"HABITATION",
    "name:eng_x_preferred":[
        "Bhitarideeh"
    ],
    "wof:name":"Bhitarideeh",
    "wof:placetype":"locality",
    "wof:population":500
},
  "geometry": {"coordinates":[82.526027,26.305189],"type":"Point"}
}