{
  "type": "Feature",
  "properties": {
    "iso:country":"IN",
    "ks:ks_name":"Satwaiwasti",
    "ks:ks_pop":330,
    "ks:ks_type":"HABITATION",
    "name:eng_x_preferred":[
        "Satwaiwasti"
    ],
    "wof:name":"Satwaiwasti",
    "wof:placetype":"locality",
    "wof:population":330
},
  "geometry": {"coordinates":[74.727682,18.487625],"type":"Point"}
}