{
  "type": "Feature",
  "properties": {
    "iso:country":"IN",
    "ks:ks_alt_nam":"Dungri falia",
    "ks:ks_name":"Dungri Falia",
    "ks:ks_pop":168,
    "ks:ks_type":"HABITATION",
    "name:eng_x_preferred":[
        "Dungri Falia"
    ],
    "wof:name":"Dungri Falia",
    "wof:placetype":"locality",
    "wof:population":168
},
  "geometry": {"coordinates":[73.464389,21.025028],"type":"Point"}
}