{
  "type": "Feature",
  "properties": {
    "iso:country":"IN",
    "ks:ks_name":"Banjhdih",
    "ks:ks_pop":192,
    "ks:ks_type":"VILLAGE",
    "name:eng_x_preferred":[
        "Banjhdih"
    ],
    "wof:name":"Banjhdih",
    "wof:placetype":"locality",
    "wof:population":192
},
  "geometry": {"coordinates":[80.577444,22.835065],"type":"Point"}
}