{
  "type": "Feature",
  "properties": {
    "iso:country":"IN",
    "ks:ks_name":"Sidelhanpurwa",
    "ks:ks_pop":236,
    "ks:ks_type":"HABITATION",
    "ks:ks_uagg_main":0,
    "name:eng_x_preferred":[
        "Sidelhanpurwa"
    ],
    "wof:name":"Sidelhanpurwa",
    "wof:placetype":"neighbourhood",
    "wof:population":236
},
  "geometry": {"coordinates":[81.44654,27.829305],"type":"Point"}
}