{
  "type": "Feature",
  "properties": {
    "iso:country":"IN",
    "ks:ks_name":"Dhena",
    "ks:ks_pop":336,
    "ks:ks_type":"HABITATION",
    "name:eng_x_preferred":[
        "Dhena"
    ],
    "wof:name":"Dhena",
    "wof:placetype":"locality",
    "wof:population":336
},
  "geometry": {"coordinates":[79.854812,29.348591],"type":"Point"}
}