{
  "type": "Feature",
  "properties": {
    "iso:country":"IN",
    "ks:ks_name":"Jambhulwadi",
    "ks:ks_pop":585,
    "ks:ks_type":"HABITATION",
    "name:eng_x_preferred":[
        "Jambhulwadi"
    ],
    "wof:name":"Jambhulwadi",
    "wof:placetype":"locality",
    "wof:population":585
},
  "geometry": {"coordinates":[73.670891,16.426434],"type":"Point"}
}