{
  "type": "Feature",
  "properties": {
    "iso:country":"IN",
    "ks:ks_name":"Chelakaveedhi",
    "ks:ks_pop":60,
    "ks:ks_type":"HABITATION",
    "name:eng_x_preferred":[
        "Chelakaveedhi"
    ],
    "wof:name":"Chelakaveedhi",
    "wof:placetype":"locality",
    "wof:population":60
},
  "geometry": {"coordinates":[82.190139,17.941692],"type":"Point"}
}