{
  "type": "Feature",
  "properties": {
    "gn:admin1_code":"39.0",
    "gn:admin2_code":"61.0",
    "gn:asciiname":"Kinati",
    "gn:country_code":"IN",
    "gn:dem":1307,
    "gn:feature_class":"P",
    "gn:feature_code":"PPL",
    "gn:name":"Kinati",
    "gn:population":0,
    "gn:timezone":"Asia/Kolkata",
    "iso:country":"IN",
    "ks:ks_name":"Kinathi",
    "ks:ks_pop":326,
    "ks:ks_type":"VILLAGE",
    "name:eng_x_preferred":[
        "Kinathi"
    ],
    "name:eng_x_variant":[
        "Kinati"
    ],
    "wof:name":"Kinathi",
    "wof:placetype":"locality",
    "wof:population":326
},
  "geometry": {"coordinates":[79.051081,29.722239],"type":"Point"}
}