{
  "type": "Feature",
  "properties": {
    "iso:country":"IN",
    "ks:ks_name":"Majhiguda",
    "ks:ks_pop":86,
    "ks:ks_type":"HABITATION",
    "name:eng_x_preferred":[
        "Majhiguda"
    ],
    "wof:name":"Majhiguda",
    "wof:placetype":"locality",
    "wof:population":86
},
  "geometry": {"coordinates":[82.807214,18.5284],"type":"Point"}
}