{
  "type": "Feature",
  "properties": {
    "gn:admin1_code":"39.0",
    "gn:admin2_code":"67.0",
    "gn:asciiname":"Devipura",
    "gn:country_code":"IN",
    "gn:dem":233,
    "gn:feature_class":"P",
    "gn:feature_code":"PPL",
    "gn:name":"Dev\u012bpura",
    "gn:population":0,
    "gn:timezone":"Asia/Kolkata",
    "iso:country":"IN",
    "name:und_x_variant":[
        "Dev\u012bpura",
        "Kharakpur"
    ],
    "wof:name":"Devipura",
    "wof:placetype":"neighbourhood"
},
  "geometry": {"coordinates":[78.9743,29.19212],"type":"Point"}
}