{
  "type": "Feature",
  "properties": {
    "gn:admin1_code":"11",
    "gn:admin2_code":"33.0",
    "gn:asciiname":"Sanna",
    "gn:country_code":"IN",
    "gn:dem":1781,
    "gn:feature_class":"P",
    "gn:feature_code":"PPL",
    "gn:name":"S\u0101nna",
    "gn:population":0,
    "gn:timezone":"Asia/Kolkata",
    "iso:country":"IN",
    "name:ceb_x_preferred":[
        "Sanna"
    ],
    "name:deu_x_preferred":[
        "Sanna"
    ],
    "name:fra_x_preferred":[
        "Sanna"
    ],
    "name:ita_x_preferred":[
        "Sanna"
    ],
    "name:nld_x_preferred":[
        "Sanna"
    ],
    "name:nor_x_preferred":[
        "Sanna"
    ],
    "name:pol_x_preferred":[
        "Sanna"
    ],
    "name:swe_x_preferred":[
        "Sanna"
    ],
    "wof:name":"Sanna",
    "wof:placetype":"locality"
},
  "geometry": {"coordinates":[77.67595,30.98575],"type":"Point"}
}