{
  "type": "Feature",
  "properties": {
    "iso:country":"IN",
    "ks:ks_name":"Marlepada",
    "ks:ks_pop":86,
    "ks:ks_type":"HABITATION",
    "name:eng_x_preferred":[
        "Marlepada"
    ],
    "wof:name":"Marlepada",
    "wof:placetype":"locality",
    "wof:population":86
},
  "geometry": {"coordinates":[73.04416500000001,19.674905],"type":"Point"}
}