{
  "type": "Feature",
  "properties": {
    "gn:admin1_code":"9.0",
    "gn:admin2_code":"486.0",
    "gn:asciiname":"Chikli",
    "gn:country_code":"IN",
    "gn:dem":246,
    "gn:feature_class":"P",
    "gn:feature_code":"PPL",
    "gn:name":"Chikli",
    "gn:population":0,
    "gn:timezone":"Asia/Kolkata",
    "iso:country":"IN",
    "wof:name":"Chikli",
    "wof:placetype":"locality"
},
  "geometry": {"coordinates":[74.04103000000001,22.05312],"type":"Point"}
}