{
  "type": "Feature",
  "properties": {
    "iso:country":"IN",
    "ks:ks_name":"Dholtaila",
    "ks:ks_pop":115,
    "ks:ks_type":"HABITATION",
    "name:eng_x_preferred":[
        "Dholtaila"
    ],
    "wof:name":"Dholtaila",
    "wof:placetype":"locality",
    "wof:population":115
},
  "geometry": {"coordinates":[84.902061,21.344485],"type":"Point"}
}