{
  "type": "Feature",
  "properties": {
    "iso:country":"IN",
    "ks:ks_name":"Chaman Nagariya",
    "ks:ks_pop":172,
    "ks:ks_type":"HABITATION",
    "name:eng_x_preferred":[
        "Chaman Nagariya"
    ],
    "wof:name":"Chaman Nagariya",
    "wof:placetype":"locality",
    "wof:population":172
},
  "geometry": {"coordinates":[79.15898199999999,27.69616],"type":"Point"}
}