{
  "type": "Feature",
  "properties": {
    "gn:admin1_code":"36",
    "gn:admin2_code":"185.0",
    "gn:asciiname":"Laukiha",
    "gn:country_code":"IN",
    "gn:dem":84,
    "gn:feature_class":"P",
    "gn:feature_code":"PPL",
    "gn:name":"Laukiha",
    "gn:population":0,
    "gn:timezone":"Asia/Kolkata",
    "iso:country":"IN",
    "ks:ks_name":"Laukiha",
    "ks:ks_pop":625,
    "ks:ks_type":"VILLAGE",
    "ks:ks_uagg_main":0,
    "name:eng_x_preferred":[
        "Laukiha"
    ],
    "wof:name":"Laukiha",
    "wof:placetype":"neighbourhood",
    "wof:population":625
},
  "geometry": {"coordinates":[82.876037,26.577682],"type":"Point"}
}