{
  "type": "Feature",
  "properties": {
    "iso:country":"IN",
    "ks:ks_name":"Rakshabera",
    "ks:ks_pop":0,
    "ks:ks_type":"VILLAGE",
    "name:eng_x_preferred":[
        "Rakshabera"
    ],
    "wof:name":"Rakshabera",
    "wof:placetype":"locality",
    "wof:population":0
},
  "geometry": {"coordinates":[85.884395,23.472761],"type":"Point"}
}