{
  "type": "Feature",
  "properties": {
    "gn:admin1_code":"36",
    "gn:admin2_code":"145.0",
    "gn:asciiname":"Nagla Bharu",
    "gn:country_code":"IN",
    "gn:dem":178,
    "gn:feature_class":"P",
    "gn:feature_code":"PPL",
    "gn:name":"Nagla Bharu",
    "gn:population":0,
    "gn:timezone":"Asia/Kolkata",
    "iso:country":"IN",
    "wof:name":"Nagla Bharu",
    "wof:placetype":"locality"
},
  "geometry": {"coordinates":[77.87779999999999,27.47382],"type":"Point"}
}