{
  "type": "Feature",
  "properties": {
    "iso:country":"IN",
    "ks:ks_name":"Wadgera Tanda",
    "ks:ks_pop":359,
    "ks:ks_type":"HABITATION",
    "name:eng_x_preferred":[
        "Wadgera Tanda"
    ],
    "wof:name":"Wadgera Tanda",
    "wof:placetype":"locality",
    "wof:population":359
},
  "geometry": {"coordinates":[77.057569,16.569868],"type":"Point"}
}