{
  "type": "Feature",
  "properties": {
    "iso:country":"IN",
    "ks:ks_alt_nam":"Dhungidh\u0101r Reserved Forest",
    "ks:ks_name":"Dhungidhar Reserved Forest",
    "ks:ks_type":"VILLAGE",
    "name:eng_x_preferred":[
        "Dhungidhar Reserved Forest"
    ],
    "name:eng_x_variant":[
        "Dhungidh\u0101r Reserved Forest"
    ],
    "wof:name":"Dhungidhar Reserved Forest",
    "wof:placetype":"locality"
},
  "geometry": {"coordinates":[79.816092,29.796179],"type":"Point"}
}