{
  "type": "Feature",
  "properties": {
    "iso:country":"IN",
    "ks:ks_name":"Kurmiyan Ka Purwa",
    "ks:ks_pop":123,
    "ks:ks_type":"HABITATION",
    "name:eng_x_preferred":[
        "Kurmiyan Ka Purwa"
    ],
    "wof:name":"Kurmiyan Ka Purwa",
    "wof:placetype":"locality",
    "wof:population":123
},
  "geometry": {"coordinates":[81.500378,25.50043],"type":"Point"}
}