{
  "type": "Feature",
  "properties": {
    "iso:country":"IN",
    "ks:ks_name":"Hardi Chhapra",
    "ks:ks_pop":737,
    "ks:ks_type":"VILLAGE",
    "ks:ks_uagg_main":0,
    "name:eng_x_preferred":[
        "Hardi Chhapra"
    ],
    "wof:name":"Hardi Chhapra",
    "wof:placetype":"neighbourhood",
    "wof:population":737
},
  "geometry": {"coordinates":[84.75575600000001,25.852789],"type":"Point"}
}