{
  "type": "Feature",
  "properties": {
    "iso:country":"IN",
    "ks:ks_name":"Ayee",
    "ks:ks_pop":1544,
    "ks:ks_type":"VILLAGE",
    "name:eng_x_preferred":[
        "Ayee"
    ],
    "wof:name":"Ayee",
    "wof:placetype":"locality",
    "wof:population":1544
},
  "geometry": {"coordinates":[74.012929,15.616881],"type":"Point"}
}