{
  "type": "Feature",
  "properties": {
    "iso:country":"IN",
    "ks:ks_name":"Gaura Upaday",
    "ks:ks_pop":456,
    "ks:ks_type":"VILLAGE",
    "ks:ks_uagg_main":0,
    "name:eng_x_preferred":[
        "Gaura Upaday"
    ],
    "wof:name":"Gaura Upaday",
    "wof:placetype":"neighbourhood",
    "wof:population":456
},
  "geometry": {"coordinates":[82.83091,26.706678],"type":"Point"}
}