{
  "type": "Feature",
  "properties": {
    "iso:country":"IN",
    "ks:ks_name":"Jamli Damami",
    "ks:ks_pop":496,
    "ks:ks_type":"HABITATION",
    "name:eng_x_preferred":[
        "Jamli Damami"
    ],
    "wof:name":"Jamli Damami",
    "wof:placetype":"locality",
    "wof:population":496
},
  "geometry": {"coordinates":[76.91959900000001,22.315792],"type":"Point"}
}