{
  "type": "Feature",
  "properties": {
    "iso:country":"IN",
    "ks:ks_alt_nam":"RAM COLONY",
    "ks:ks_name":"Ram Colony",
    "ks:ks_pop":721,
    "ks:ks_type":"HABITATION",
    "name:eng_x_preferred":[
        "Ram Colony"
    ],
    "wof:name":"Ram Colony",
    "wof:placetype":"locality",
    "wof:population":721
},
  "geometry": {"coordinates":[89.81899799999999,26.476881],"type":"Point"}
}