{
  "type": "Feature",
  "properties": {
    "iso:country":"IN",
    "ks:ks_name":"Puranewasti",
    "ks:ks_pop":134,
    "ks:ks_type":"HABITATION",
    "name:eng_x_preferred":[
        "Puranewasti"
    ],
    "wof:name":"Puranewasti",
    "wof:placetype":"locality",
    "wof:population":134
},
  "geometry": {"coordinates":[74.72505099999999,18.555672],"type":"Point"}
}