{
  "type": "Feature",
  "properties": {
    "iso:country":"IN",
    "ks:ks_name":"Tambalwadi",
    "ks:ks_pop":57,
    "ks:ks_type":"HABITATION",
    "name:eng_x_preferred":[
        "Tambalwadi"
    ],
    "wof:name":"Tambalwadi",
    "wof:placetype":"locality",
    "wof:population":57
},
  "geometry": {"coordinates":[73.621667,17.135833],"type":"Point"}
}