{
  "type": "Feature",
  "properties": {
    "gn:admin1_code":"2.0",
    "gn:admin2_code":"553.0",
    "gn:asciiname":"Ragikuntapalle",
    "gn:country_code":"IN",
    "gn:dem":619,
    "gn:feature_class":"P",
    "gn:feature_code":"PPL",
    "gn:name":"R\u0101gikuntapalle",
    "gn:population":0,
    "gn:timezone":"Asia/Kolkata",
    "iso:country":"IN",
    "wof:name":"Ragikuntapalle",
    "wof:placetype":"neighbourhood"
},
  "geometry": {"coordinates":[78.14755,13.89166],"type":"Point"}
}