{
  "type": "Feature",
  "properties": {
    "iso:country":"IN",
    "ks:ks_name":"Bhakatpara",
    "ks:ks_pop":105,
    "ks:ks_type":"HABITATION",
    "name:eng_x_preferred":[
        "Bhakatpara"
    ],
    "wof:name":"Bhakatpara",
    "wof:placetype":"locality",
    "wof:population":105
},
  "geometry": {"coordinates":[91.467061,25.967959],"type":"Point"}
}