{
  "type": "Feature",
  "properties": {
    "iso:country":"IN",
    "ks:ks_name":"Bhootwar",
    "ks:ks_pop":678,
    "ks:ks_type":"VILLAGE",
    "name:eng_x_preferred":[
        "Bhootwar"
    ],
    "wof:name":"Bhootwar",
    "wof:placetype":"locality",
    "wof:population":678
},
  "geometry": {"coordinates":[73.311626,24.788126],"type":"Point"}
}