{
  "type": "Feature",
  "properties": {
    "iso:country":"IN",
    "ks:ks_name":"Sunnangla",
    "ks:ks_pop":505,
    "ks:ks_type":"HABITATION",
    "name:eng_x_preferred":[
        "Sunnangla"
    ],
    "wof:name":"Sunnangla",
    "wof:placetype":"locality",
    "wof:population":505
},
  "geometry": {"coordinates":[74.930065,12.770558],"type":"Point"}
}