{
  "type": "Feature",
  "properties": {
    "iso:country":"IN",
    "ks:ks_name":"Dumer",
    "ks:ks_pop":353,
    "ks:ks_type":"VILLAGE",
    "name:eng_x_preferred":[
        "Dumer"
    ],
    "wof:name":"Dumer",
    "wof:placetype":"locality",
    "wof:population":353
},
  "geometry": {"coordinates":[83.568558,20.091522],"type":"Point"}
}