{
  "type": "Feature",
  "properties": {
    "gn:admin1_code":"36",
    "gn:admin2_code":"158.0",
    "gn:asciiname":"Nawagarh",
    "gn:country_code":"IN",
    "gn:dem":116,
    "gn:feature_class":"P",
    "gn:feature_code":"PPL",
    "gn:name":"Naw\u0101garh",
    "gn:population":0,
    "gn:timezone":"Asia/Kolkata",
    "iso:country":"IN",
    "name:spa_x_preferred":[
        "Nawagarh"
    ],
    "name:tgl_x_preferred":[
        "Nawagarh"
    ],
    "wof:name":"Nawagarh",
    "wof:placetype":"neighbourhood"
},
  "geometry": {"coordinates":[81.44158,26.54004],"type":"Point"}
}