{
  "type": "Feature",
  "properties": {
    "gn:admin1_code":"37",
    "gn:admin2_code":"403.0",
    "gn:asciiname":"Karradhorhi",
    "gn:country_code":"IN",
    "gn:dem":216,
    "gn:feature_class":"P",
    "gn:feature_code":"PPL",
    "gn:name":"Karradhorhi",
    "gn:population":0,
    "gn:timezone":"Asia/Kolkata",
    "iso:country":"IN",
    "name:und_x_variant":[
        "Keotindhorhi"
    ],
    "wof:name":"Karradhorhi",
    "wof:placetype":"locality"
},
  "geometry": {"coordinates":[83.13958000000002,21.59812],"type":"Point"}
}