{
  "type": "Feature",
  "properties": {
    "gn:admin1_code":"35",
    "gn:admin2_code":"455.0",
    "gn:asciiname":"Danwan",
    "gn:country_code":"IN",
    "gn:dem":475,
    "gn:feature_class":"P",
    "gn:feature_code":"PPL",
    "gn:name":"D\u0101nw\u0101n",
    "gn:population":0,
    "gn:timezone":"Asia/Kolkata",
    "iso:country":"IN",
    "ks:ks_name":"Danwa",
    "ks:ks_pop":313,
    "ks:ks_type":"VILLAGE",
    "name:eng_x_preferred":[
        "Danwa"
    ],
    "name:eng_x_variant":[
        "Danwan"
    ],
    "wof:name":"Danwa",
    "wof:placetype":"locality",
    "wof:population":313
},
  "geometry": {"coordinates":[78.27957499999999,22.157602],"type":"Point"}
}