{
  "type": "Feature",
  "properties": {
    "gn:admin1_code":"19.0",
    "gn:admin2_code":"574.0",
    "gn:asciiname":"Ningapur",
    "gn:country_code":"IN",
    "gn:dem":965,
    "gn:feature_class":"P",
    "gn:feature_code":"PPL",
    "gn:name":"Ningapur",
    "gn:population":0,
    "gn:timezone":"Asia/Kolkata",
    "iso:country":"IN",
    "ks:ks_name":"Ningapura",
    "ks:ks_pop":140,
    "ks:ks_type":"HABITATION",
    "name:eng_x_preferred":[
        "Ningapura"
    ],
    "name:eng_x_variant":[
        "Ningapur"
    ],
    "wof:name":"Ningapura",
    "wof:placetype":"locality",
    "wof:population":140
},
  "geometry": {"coordinates":[75.871082,12.677917],"type":"Point"}
}