{
  "type": "Feature",
  "properties": {
    "gn:admin1_code":"10.0",
    "gn:admin2_code":"81.0",
    "gn:asciiname":"Dhani Sukkhan",
    "gn:country_code":"IN",
    "gn:dem":218,
    "gn:feature_class":"P",
    "gn:feature_code":"PPL",
    "gn:name":"Dh\u0101ni Sukkhan",
    "gn:population":0,
    "gn:timezone":"Asia/Kolkata",
    "iso:country":"IN",
    "name:und_x_variant":[
        "Dh\u0101ni Sukkhan",
        "Dh\u0101ni Sukhan"
    ],
    "wof:name":"Dhani Sukkhan",
    "wof:placetype":"locality"
},
  "geometry": {"coordinates":[76.18971999999999,28.85254],"type":"Point"}
}