{
  "type": "Feature",
  "properties": {
    "gn:admin1_code":"11",
    "gn:admin2_code":"27.0",
    "gn:asciiname":"Dhanwan",
    "gn:country_code":"IN",
    "gn:dem":1734,
    "gn:feature_class":"P",
    "gn:feature_code":"PPL",
    "gn:name":"Dhanw\u0101n",
    "gn:population":0,
    "gn:timezone":"Asia/Kolkata",
    "iso:country":"IN",
    "name:hin_x_preferred":[
        "\u0927\u0928\u0935\u093e\u0928"
    ],
    "wof:name":"Dhanwan",
    "wof:placetype":"locality"
},
  "geometry": {"coordinates":[76.9308,31.92005],"type":"Point"}
}