{
  "type": "Feature",
  "properties": {
    "gn:admin1_code":"36",
    "gn:admin2_code":"153.0",
    "gn:asciiname":"Maksoha",
    "gn:country_code":"IN",
    "gn:dem":140,
    "gn:feature_class":"P",
    "gn:feature_code":"PPL",
    "gn:name":"Maksoha",
    "gn:population":0,
    "gn:timezone":"Asia/Kolkata",
    "iso:country":"IN",
    "wof:name":"Maksoha",
    "wof:placetype":"locality"
},
  "geometry": {"coordinates":[80.84439,27.99793],"type":"Point"}
}