{
  "type": "Feature",
  "properties": {
    "iso:country":"IN",
    "ks:ks_name":"Janjali",
    "ks:ks_pop":810,
    "ks:ks_type":"VILLAGE",
    "name:eng_x_preferred":[
        "Janjali"
    ],
    "wof:name":"Janjali",
    "wof:placetype":"locality",
    "wof:population":810
},
  "geometry": {"coordinates":[86.112098,21.451869],"type":"Point"}
}