{
  "type": "Feature",
  "properties": {
    "iso:country":"IN",
    "ks:ks_name":"Malayakonam",
    "ks:ks_pop":450,
    "ks:ks_type":"HABITATION",
    "name:eng_x_preferred":[
        "Malayakonam"
    ],
    "wof:name":"Malayakonam",
    "wof:placetype":"locality",
    "wof:population":450
},
  "geometry": {"coordinates":[77.240407,8.33439],"type":"Point"}
}