{
  "type": "Feature",
  "properties": {
    "iso:country":"IN",
    "ks:ks_name":"Srinivasapuram",
    "ks:ks_pop":127,
    "ks:ks_type":"HABITATION",
    "name:eng_x_preferred":[
        "Srinivasapuram"
    ],
    "wof:name":"Srinivasapuram",
    "wof:placetype":"locality",
    "wof:population":127
},
  "geometry": {"coordinates":[79.41106600000001,14.555278],"type":"Point"}
}