{
  "type": "Feature",
  "properties": {
    "iso:country":"IN",
    "ks:ks_name":"Bhainsaghat",
    "ks:ks_pop":481,
    "ks:ks_type":"VILLAGE",
    "name:eng_x_preferred":[
        "Bhainsaghat"
    ],
    "wof:name":"Bhainsaghat",
    "wof:placetype":"locality",
    "wof:population":481
},
  "geometry": {"coordinates":[82.11170199999999,18.619323],"type":"Point"}
}