{
  "type": "Feature",
  "properties": {
    "gn:admin1_code":"28.0",
    "gn:admin2_code":"336.0",
    "gn:asciiname":"Chandirampur",
    "gn:country_code":"IN",
    "gn:dem":12,
    "gn:feature_class":"P",
    "gn:feature_code":"PPL",
    "gn:name":"Chandirampur",
    "gn:population":0,
    "gn:timezone":"Asia/Kolkata",
    "iso:country":"IN",
    "wof:name":"Chandirampur",
    "wof:placetype":"locality"
},
  "geometry": {"coordinates":[88.53115,22.99294],"type":"Point"}
}