{
  "type": "Feature",
  "properties": {
    "iso:country":"IN",
    "ks:ks_name":"Mijikajan T E P K P No 2",
    "ks:ks_pop":115,
    "ks:ks_type":"HABITATION",
    "ks:ks_uagg_main":0,
    "name:eng_x_preferred":[
        "Mijikajan T E P K P No 2"
    ],
    "wof:name":"Mijikajan T E P K P No 2",
    "wof:placetype":"neighbourhood",
    "wof:population":115
},
  "geometry": {"coordinates":[93.190562,26.830178],"type":"Point"}
}