{
  "type": "Feature",
  "properties": {
    "iso:country":"IN",
    "ks:ks_alt_nam":"Navajyoti No 1 and 2",
    "ks:ks_name":"Navajyoti No 1 And 2",
    "ks:ks_pop":1047,
    "ks:ks_type":"HABITATION",
    "ks:ks_uagg_main":0,
    "name:eng_x_preferred":[
        "Navajyoti No 1 And 2"
    ],
    "wof:name":"Navajyoti No 1 And 2",
    "wof:placetype":"neighbourhood",
    "wof:population":1047
},
  "geometry": {"coordinates":[94.048627,26.375547],"type":"Point"}
}