{
  "type": "Feature",
  "properties": {
    "iso:country":"IN",
    "ks:ks_name":"Banwook",
    "ks:ks_pop":541,
    "ks:ks_type":"VILLAGE",
    "name:eng_x_preferred":[
        "Banwook"
    ],
    "wof:name":"Banwook",
    "wof:placetype":"locality",
    "wof:population":541
},
  "geometry": {"coordinates":[81.384349,26.980423],"type":"Point"}
}