{
  "type": "Feature",
  "properties": {
    "gn:admin1_code":"34.0",
    "gn:admin2_code":"219.0",
    "gn:asciiname":"Naukarha Chhatar",
    "gn:country_code":"IN",
    "gn:dem":59,
    "gn:feature_class":"P",
    "gn:feature_code":"PPL",
    "gn:name":"Naukarha Chhatar",
    "gn:population":0,
    "gn:timezone":"Asia/Kolkata",
    "iso:country":"IN",
    "wof:name":"Naukarha Chhatar",
    "wof:placetype":"locality"
},
  "geometry": {"coordinates":[84.9834,25.99378],"type":"Point"}
}