{
  "type": "Feature",
  "properties": {
    "iso:country":"IN",
    "ks:ks_alt_nam":"Khamarb\u0101d",
    "ks:ks_name":"Khamarbad",
    "ks:ks_pop":140,
    "ks:ks_type":"VILLAGE",
    "name:eng_x_preferred":[
        "Khamarbad"
    ],
    "name:eng_x_variant":[
        "Khamarb\u0101d"
    ],
    "wof:name":"Khamarbad",
    "wof:placetype":"locality",
    "wof:population":140
},
  "geometry": {"coordinates":[86.491936,24.162292],"type":"Point"}
}