{
  "type": "Feature",
  "properties": {
    "gn:admin1_code":"28.0",
    "gn:admin2_code":"341",
    "gn:asciiname":"Kanaidanga",
    "gn:country_code":"IN",
    "gn:dem":6,
    "gn:feature_class":"P",
    "gn:feature_code":"PPL",
    "gn:name":"K\u0101n\u0101id\u0101nga",
    "gn:population":0,
    "gn:timezone":"Asia/Kolkata",
    "iso:country":"IN",
    "ks:ks_alt_nam":"K\u0101n\u0101id\u0101nga",
    "ks:ks_name":"Kanaidanga",
    "ks:ks_pop":4173,
    "ks:ks_type":"VILLAGE",
    "name:eng_x_preferred":[
        "Kanaidanga"
    ],
    "name:eng_x_variant":[
        "K\u0101n\u0101id\u0101nga"
    ],
    "wof:name":"Kanaidanga",
    "wof:placetype":"locality",
    "wof:population":4173
},
  "geometry": {"coordinates":[88.175556,22.678611],"type":"Point"}
}