{
  "type": "Feature",
  "properties": {
    "iso:country":"IN",
    "ks:ks_name":"Hudagodmakki",
    "ks:ks_pop":85,
    "ks:ks_type":"HABITATION",
    "name:eng_x_preferred":[
        "Hudagodmakki"
    ],
    "wof:name":"Hudagodmakki",
    "wof:placetype":"locality",
    "wof:population":85
},
  "geometry": {"coordinates":[74.489355,14.325815],"type":"Point"}
}