{
  "type": "Feature",
  "properties": {
    "gn:country":"IN",
    "gn:fcode":"PPL",
    "gn:pop":0,
    "iso:country":"IN",
    "name:ceb_x_preferred":[
        "Jagatpur"
    ],
    "name:pol_x_preferred":[
        "Jagatpur"
    ],
    "name:swe_x_preferred":[
        "Jagatpur"
    ],
    "qs:name":"Jagatpur",
    "qs:name_adm0":"India",
    "qs:name_adm1":"Orissa",
    "qs:photos":1,
    "qs:photos_1k":1,
    "qs:photos_9k":1,
    "qs:photos_9r":1,
    "qs:photos_all":1,
    "qs:photos_sr":1,
    "qs:placetype":"Suburb",
    "qs:pop_sr":"0",
    "wd:wordcount":15,
    "wof:name":"Jagatpur",
    "wof:placetype":"neighbourhood",
    "wof:population":0
},
  "geometry": {"coordinates":[85.92491,20.5096],"type":"Point"}
}