{
  "type": "Feature",
  "properties": {
    "iso:country":"IN",
    "ks:ks_name":"Bideshini",
    "ks:ks_pop":0,
    "ks:ks_type":"VILLAGE",
    "name:eng_x_preferred":[
        "Bideshini"
    ],
    "wof:name":"Bideshini",
    "wof:placetype":"locality",
    "wof:population":0
},
  "geometry": {"coordinates":[87.650791,23.954979],"type":"Point"}
}