{
  "type": "Feature",
  "properties": {
    "iso:country":"IN",
    "ks:ks_name":"Rangdi",
    "ks:ks_pop":556,
    "ks:ks_type":"VILLAGE",
    "ks:ks_uagg_main":0,
    "name:eng_x_preferred":[
        "Rangdi"
    ],
    "wof:name":"Rangdi",
    "wof:placetype":"locality",
    "wof:population":556
},
  "geometry": {"coordinates":[86.50135299999999,23.844547],"type":"Point"}
}