{
  "type": "Feature",
  "properties": {
    "iso:country":"IN",
    "ks:ks_name":"Vanniyampatti",
    "ks:ks_pop":250,
    "ks:ks_type":"HABITATION",
    "name:eng_x_preferred":[
        "Vanniyampatti"
    ],
    "wof:name":"Vanniyampatti",
    "wof:placetype":"locality",
    "wof:population":250
},
  "geometry": {"coordinates":[79.05073899999999,10.561333],"type":"Point"}
}