{
  "type": "Feature",
  "properties": {
    "iso:country":"IN",
    "ks:ks_alt_nam":"Mgr nagar Alinjivakkam",
    "ks:ks_name":"Mgr Nagar Alinjivakkam",
    "ks:ks_pop":249,
    "ks:ks_type":"HABITATION",
    "name:eng_x_preferred":[
        "Mgr Nagar Alinjivakkam"
    ],
    "wof:name":"Mgr Nagar Alinjivakkam",
    "wof:placetype":"locality",
    "wof:population":249
},
  "geometry": {"coordinates":[80.141794,13.263404],"type":"Point"}
}