{
  "type": "Feature",
  "properties": {
    "iso:country":"IN",
    "ks:ks_name":"Mogarvane",
    "ks:ks_pop":310,
    "ks:ks_type":"HABITATION",
    "name:eng_x_preferred":[
        "Mogarvane"
    ],
    "wof:name":"Mogarvane",
    "wof:placetype":"locality",
    "wof:population":310
},
  "geometry": {"coordinates":[73.60444200000001,17.028661],"type":"Point"}
}