{
  "type": "Feature",
  "properties": {
    "iso:country":"IN",
    "ks:ks_alt_nam":"Sailoon or Salon",
    "ks:ks_name":"Sailoon Or Salon",
    "ks:ks_pop":688,
    "ks:ks_type":"HABITATION",
    "name:eng_x_preferred":[
        "Sailoon Or Salon"
    ],
    "wof:name":"Sailoon Or Salon",
    "wof:placetype":"locality",
    "wof:population":688
},
  "geometry": {"coordinates":[79.063301,30.077937],"type":"Point"}
}