{
  "type": "Feature",
  "properties": {
    "gn:admin1_code":"19",
    "gn:admin2_code":"563.0",
    "gn:asciiname":"Harlikop",
    "gn:country_code":"IN",
    "gn:dem":578,
    "gn:feature_class":"P",
    "gn:feature_code":"PPL",
    "gn:name":"Harlikop",
    "gn:population":0,
    "gn:timezone":"Asia/Kolkata",
    "iso:country":"IN",
    "wof:name":"Harlikop",
    "wof:placetype":"locality"
},
  "geometry": {"coordinates":[74.86497,14.29494],"type":"Point"}
}