{
  "type": "Feature",
  "properties": {
    "gn:admin1_code":"34.0",
    "gn:admin2_code":"229.0",
    "gn:asciiname":"Tandapar",
    "gn:country_code":"IN",
    "gn:dem":49,
    "gn:feature_class":"P",
    "gn:feature_code":"PPL",
    "gn:name":"T\u0101nd\u0101par",
    "gn:population":0,
    "gn:timezone":"Asia/Kolkata",
    "iso:country":"IN",
    "ks:ks_name":"Tada Par",
    "ks:ks_pop":582,
    "ks:ks_type":"HABITATION",
    "name:eng_x_preferred":[
        "Tada Par"
    ],
    "name:eng_x_variant":[
        "Tandapar"
    ],
    "wof:name":"Tada Par",
    "wof:placetype":"locality",
    "wof:population":582
},
  "geometry": {"coordinates":[85.483834,25.394324],"type":"Point"}
}