{
  "type": "Feature",
  "properties": {
    "gn:admin1_code":"19.0",
    "gn:admin2_code":"567.0",
    "gn:asciiname":"Kallugudi",
    "gn:country_code":"IN",
    "gn:dem":649,
    "gn:feature_class":"P",
    "gn:feature_code":"PPL",
    "gn:name":"Kallugudi",
    "gn:population":0,
    "gn:timezone":"Asia/Kolkata",
    "iso:country":"IN",
    "ks:ks_name":"Kallugudi",
    "ks:ks_pop":713,
    "ks:ks_type":"VILLAGE",
    "name:eng_x_preferred":[
        "Kallugudi"
    ],
    "wof:name":"Kallugudi",
    "wof:placetype":"locality",
    "wof:population":713
},
  "geometry": {"coordinates":[76.048649,14.581215],"type":"Point"}
}