{
  "type": "Feature",
  "properties": {
    "iso:country":"IN",
    "ks:ks_name":"Patharkhuniya",
    "ks:ks_pop":483,
    "ks:ks_type":"VILLAGE",
    "name:eng_x_preferred":[
        "Patharkhuniya"
    ],
    "wof:name":"Patharkhuniya",
    "wof:placetype":"locality",
    "wof:population":483
},
  "geometry": {"coordinates":[86.864037,23.164335],"type":"Point"}
}