{
  "type": "Feature",
  "properties": {
    "gn:admin1_code":"36",
    "gn:admin2_code":"192.0",
    "gn:asciiname":"Kajha",
    "gn:country_code":"IN",
    "gn:dem":76,
    "gn:feature_class":"P",
    "gn:feature_code":"PPL",
    "gn:name":"K\u0101jha",
    "gn:population":0,
    "gn:timezone":"Asia/Kolkata",
    "iso:country":"IN",
    "wof:name":"Kajha",
    "wof:placetype":"locality"
},
  "geometry": {"coordinates":[83.41546,25.87109],"type":"Point"}
}