{
  "type": "Feature",
  "properties": {
    "iso:country":"IN",
    "ks:ks_alt_nam":"paravoor",
    "ks:ks_name":"Paravoor",
    "ks:ks_pop":263,
    "ks:ks_type":"HABITATION",
    "name:eng_x_preferred":[
        "Paravoor"
    ],
    "wof:name":"Paravoor",
    "wof:placetype":"locality",
    "wof:population":263
},
  "geometry": {"coordinates":[75.363501,12.130177],"type":"Point"}
}