{
  "type": "Feature",
  "properties": {
    "iso:country":"IN",
    "ks:ks_name":"Keolari Ryt.",
    "ks:ks_pop":108,
    "ks:ks_type":"VILLAGE",
    "name:eng_x_preferred":[
        "Keolari Ryt."
    ],
    "wof:name":"Keolari Ryt.",
    "wof:placetype":"locality",
    "wof:population":108
},
  "geometry": {"coordinates":[78.47516,22.091947],"type":"Point"}
}