{
  "type": "Feature",
  "properties": {
    "gn:admin1_code":"35.0",
    "gn:admin2_code":"425.0",
    "gn:asciiname":"Maharajpur",
    "gn:country_code":"IN",
    "gn:dem":340,
    "gn:feature_class":"P",
    "gn:feature_code":"PPL",
    "gn:name":"Mah\u0101r\u0101jpur",
    "gn:population":0,
    "gn:timezone":"Asia/Kolkata",
    "iso:country":"IN",
    "wof:name":"Maharajpur",
    "wof:placetype":"locality"
},
  "geometry": {"coordinates":[79.13521999999998,24.51107],"type":"Point"}
}