{
  "type": "Feature",
  "properties": {
    "iso:country":"IN",
    "ks:ks_name":"Durgapur",
    "ks:ks_pop":671,
    "ks:ks_type":"HABITATION",
    "name:eng_x_preferred":[
        "Durgapur"
    ],
    "wof:name":"Durgapur",
    "wof:placetype":"locality",
    "wof:population":671
},
  "geometry": {"coordinates":[85.601016,20.105384],"type":"Point"}
}