{
  "type": "Feature",
  "properties": {
    "iso:country":"IN",
    "ks:ks_name":"Pure Bhagwandeen",
    "ks:ks_pop":58,
    "ks:ks_type":"HABITATION",
    "ks:ks_uagg_main":0,
    "name:eng_x_preferred":[
        "Pure Bhagwandeen"
    ],
    "wof:name":"Pure Bhagwandeen",
    "wof:placetype":"neighbourhood",
    "wof:population":58
},
  "geometry": {"coordinates":[81.784391,26.039932],"type":"Point"}
}