{
  "type": "Feature",
  "properties": {
    "iso:country":"IN",
    "ks:ks_alt_nam":"PURE OJHA",
    "ks:ks_name":"Pure Ojha",
    "ks:ks_pop":68,
    "ks:ks_type":"HABITATION",
    "ks:ks_uagg_main":0,
    "name:eng_x_preferred":[
        "Pure Ojha"
    ],
    "wof:name":"Pure Ojha",
    "wof:placetype":"neighbourhood",
    "wof:population":68
},
  "geometry": {"coordinates":[81.948166,26.093501],"type":"Point"}
}