{
  "type": "Feature",
  "properties": {
    "iso:country":"IN",
    "ks:ks_name":"Hira Ki Dhani",
    "ks:ks_pop":1610,
    "ks:ks_type":"VILLAGE",
    "name:eng_x_preferred":[
        "Hira Ki Dhani"
    ],
    "wof:name":"Hira Ki Dhani",
    "wof:placetype":"locality",
    "wof:population":1610
},
  "geometry": {"coordinates":[71.931017,26.280733],"type":"Point"}
}