{
  "type": "Feature",
  "properties": {
    "gn:admin1_code":"34.0",
    "gn:admin2_code":"203.0",
    "gn:asciiname":"Barhara",
    "gn:country_code":"IN",
    "gn:dem":86,
    "gn:feature_class":"P",
    "gn:feature_code":"PPL",
    "gn:name":"Barhara",
    "gn:population":0,
    "gn:timezone":"Asia/Kolkata",
    "iso:country":"IN",
    "ks:ks_name":"Barhara",
    "ks:ks_pop":1417,
    "ks:ks_type":"VILLAGE",
    "ks:ks_uagg_main":0,
    "name:eng_x_preferred":[
        "Barhara"
    ],
    "wof:name":"Barhara",
    "wof:placetype":"neighbourhood",
    "wof:population":1417
},
  "geometry": {"coordinates":[84.169951,26.917415],"type":"Point"}
}