{
  "type": "Feature",
  "properties": {
    "iso:country":"IN",
    "ks:ks_name":"Mauje Kasarwada",
    "ks:ks_pop":1168,
    "ks:ks_type":"VILLAGE",
    "ks:ks_uagg_main":0,
    "name:eng_x_preferred":[
        "Mauje Kasarwada"
    ],
    "wof:name":"Mauje Kasarwada",
    "wof:placetype":"neighbourhood",
    "wof:population":1168
},
  "geometry": {"coordinates":[74.077167,16.398742],"type":"Point"}
}