{
  "type": "Feature",
  "properties": {
    "gn:admin1_code":"16",
    "gn:admin2_code":"510.0",
    "gn:asciiname":"Pachpor",
    "gn:country_code":"IN",
    "gn:dem":295,
    "gn:feature_class":"P",
    "gn:feature_code":"PPL",
    "gn:name":"P\u0101chpor",
    "gn:population":0,
    "gn:timezone":"Asia/Kolkata",
    "iso:country":"IN",
    "ks:ks_alt_nam":"P\u0101chpor",
    "ks:ks_name":"Pachpor",
    "ks:ks_type":"VILLAGE",
    "name:eng_x_preferred":[
        "Pachpor"
    ],
    "name:eng_x_variant":[
        "P\u0101chpor"
    ],
    "wof:name":"Pachpor",
    "wof:placetype":"locality"
},
  "geometry": {"coordinates":[78.668249,19.98908],"type":"Point"}
}