{
  "type": "Feature",
  "properties": {
    "gn:admin1_code":"36",
    "gn:admin2_code":"185.0",
    "gn:asciiname":"Marautia Asre",
    "gn:country_code":"IN",
    "gn:dem":90,
    "gn:feature_class":"P",
    "gn:feature_code":"PPL",
    "gn:name":"Marautia \u0100sre",
    "gn:population":0,
    "gn:timezone":"Asia/Kolkata",
    "iso:country":"IN",
    "ks:ks_name":"Marwatia Asre",
    "ks:ks_pop":287,
    "ks:ks_type":"HABITATION",
    "name:eng_x_preferred":[
        "Marwatia Asre"
    ],
    "name:eng_x_variant":[
        "Marautia Asre"
    ],
    "wof:name":"Marwatia Asre",
    "wof:placetype":"locality",
    "wof:population":287
},
  "geometry": {"coordinates":[82.82209899999999,26.903005],"type":"Point"}
}