{
  "type": "Feature",
  "properties": {
    "iso:country":"IN",
    "ks:ks_name":"Bhaisapur",
    "ks:ks_pop":215,
    "ks:ks_type":"HABITATION",
    "name:eng_x_preferred":[
        "Bhaisapur"
    ],
    "wof:name":"Bhaisapur",
    "wof:placetype":"locality",
    "wof:population":215
},
  "geometry": {"coordinates":[82.712737,26.434273],"type":"Point"}
}