{
  "type": "Feature",
  "properties": {
    "gn:admin1_code":"34",
    "gn:admin2_code":"218.0",
    "gn:asciiname":"Banthu Solona",
    "gn:country_code":"IN",
    "gn:dem":67,
    "gn:feature_class":"P",
    "gn:feature_code":"PPL",
    "gn:name":"Banthu Solona",
    "gn:population":0,
    "gn:timezone":"Asia/Kolkata",
    "iso:country":"IN",
    "ks:ks_name":"Banthu Salona",
    "ks:ks_pop":492,
    "ks:ks_type":"VILLAGE",
    "name:eng_x_preferred":[
        "Banthu Salona"
    ],
    "name:eng_x_variant":[
        "Banthu Solona"
    ],
    "wof:name":"Banthu Salona",
    "wof:placetype":"locality",
    "wof:population":492
},
  "geometry": {"coordinates":[84.239771,26.142359],"type":"Point"}
}