{
  "type": "Feature",
  "properties": {
    "iso:country":"IN",
    "ks:ks_name":"7 NZP",
    "ks:ks_pop":97,
    "ks:ks_type":"VILLAGE",
    "name:eng_x_preferred":[
        "7 NZP"
    ],
    "wof:name":"7 NZP",
    "wof:placetype":"locality",
    "wof:population":97
},
  "geometry": {"coordinates":[73.44453900000001,29.378846],"type":"Point"}
}