{
  "type": "Feature",
  "properties": {
    "gn:admin1_code":"36",
    "gn:admin2_code":"168.0",
    "gn:asciiname":"Sarha",
    "gn:country_code":"IN",
    "gn:dem":118,
    "gn:feature_class":"P",
    "gn:feature_code":"PPL",
    "gn:name":"Sarha",
    "gn:population":0,
    "gn:timezone":"Asia/Kolkata",
    "iso:country":"IN",
    "ks:ks_name":"Sarha",
    "ks:ks_pop":177,
    "ks:ks_type":"VILLAGE",
    "name:ara_x_preferred":[
        "\u0633\u0631\u062d\u0627"
    ],
    "name:eng_x_preferred":[
        "Sarha"
    ],
    "name:fas_x_preferred":[
        "\u0633\u0631\u062d\u0627"
    ],
    "name:pol_x_preferred":[
        "Sarha"
    ],
    "name:vie_x_preferred":[
        "Sarha"
    ],
    "wof:name":"Sarha",
    "wof:placetype":"locality",
    "wof:population":177
},
  "geometry": {"coordinates":[80.175859,25.684439],"type":"Point"}
}