{
  "type": "Feature",
  "properties": {
    "iso:country":"IN",
    "ks:ks_name":"Prempura",
    "ks:ks_pop":491,
    "ks:ks_type":"HABITATION",
    "name:eng_x_preferred":[
        "Prempura"
    ],
    "wof:name":"Prempura",
    "wof:placetype":"locality",
    "wof:population":491
},
  "geometry": {"coordinates":[75.302795,27.037507],"type":"Point"}
}