{
  "type": "Feature",
  "properties": {
    "gn:admin1_code":"16",
    "gn:admin2_code":"521.0",
    "gn:asciiname":"Malthan",
    "gn:country_code":"IN",
    "gn:dem":595,
    "gn:feature_class":"P",
    "gn:feature_code":"PPL",
    "gn:name":"Malthan",
    "gn:population":0,
    "gn:timezone":"Asia/Kolkata",
    "iso:country":"IN",
    "wof:name":"Malthan",
    "wof:placetype":"neighbourhood"
},
  "geometry": {"coordinates":[74.22790999999999,18.83854],"type":"Point"}
}