{
  "type": "Feature",
  "properties": {
    "iso:country":"IN",
    "ks:ks_name":"Hirapur",
    "ks:ks_pop":702,
    "ks:ks_type":"VILLAGE",
    "ks:ks_uagg_main":0,
    "name:eng_x_preferred":[
        "Hirapur"
    ],
    "wof:name":"Hirapur",
    "wof:placetype":"neighbourhood",
    "wof:population":702
},
  "geometry": {"coordinates":[86.732744,24.076162],"type":"Point"}
}