{
  "type": "Feature",
  "properties": {
    "iso:country":"IN",
    "ks:ks_name":"Powa Saikia",
    "ks:ks_pop":435,
    "ks:ks_type":"VILLAGE",
    "ks:ks_uagg_main":0,
    "name:eng_x_preferred":[
        "Powa Saikia"
    ],
    "wof:name":"Powa Saikia",
    "wof:placetype":"neighbourhood",
    "wof:population":435
},
  "geometry": {"coordinates":[94.49779700000001,27.380103],"type":"Point"}
}