{
  "type": "Feature",
  "properties": {
    "gn:admin1_code":"16.0",
    "gn:admin2_code":"498.0",
    "gn:asciiname":"Vadna",
    "gn:country_code":"IN",
    "gn:dem":273,
    "gn:feature_class":"P",
    "gn:feature_code":"PPL",
    "gn:name":"Vadna",
    "gn:population":0,
    "gn:timezone":"Asia/Kolkata",
    "iso:country":"IN",
    "name:deu_x_preferred":[
        "Vadna"
    ],
    "name:epo_x_preferred":[
        "Vadna"
    ],
    "name:fas_x_preferred":[
        "\u0648\u0627\u062f\u0646\u0627"
    ],
    "name:fra_x_preferred":[
        "Vadna"
    ],
    "name:heb_x_preferred":[
        "\u05d5\u05d3\u05e0\u05d4"
    ],
    "name:hun_x_preferred":[
        "Vadna"
    ],
    "name:ita_x_preferred":[
        "Vadna"
    ],
    "name:msa_x_preferred":[
        "Vadna"
    ],
    "name:nld_x_preferred":[
        "Vadna"
    ],
    "name:pol_x_preferred":[
        "Vadna"
    ],
    "name:ron_x_preferred":[
        "Vadna"
    ],
    "name:slk_x_preferred":[
        "Vadna"
    ],
    "name:slv_x_preferred":[
        "Vadna"
    ],
    "name:vie_x_preferred":[
        "Vadna"
    ],
    "name:zho_x_preferred":[
        "\u6c83\u5fb7\u7459"
    ],
    "wof:name":"Vadna",
    "wof:placetype":"neighbourhood"
},
  "geometry": {"coordinates":[74.6802,21.0748],"type":"Point"}
}