{
  "type": "Feature",
  "properties": {
    "gn:admin1_code":"23",
    "gn:admin2_code":"48.0",
    "gn:asciiname":"Ranon Chhota",
    "gn:country_code":"IN",
    "gn:dem":258,
    "gn:feature_class":"P",
    "gn:feature_code":"PPL",
    "gn:name":"Ranon Chhota",
    "gn:population":0,
    "gn:timezone":"Asia/Kolkata",
    "iso:country":"IN",
    "wof:name":"Ranon Chhota",
    "wof:placetype":"locality"
},
  "geometry": {"coordinates":[76.28473000000002,30.51917000000001],"type":"Point"}
}