{
  "type": "Feature",
  "properties": {
    "gn:admin1_code":"23",
    "gn:admin2_code":"48.0",
    "gn:asciiname":"Ranon Chhota",
    "gn:country_code":"IN",
    "gn:dem":258,
    "gn:feature_class":"P",
    "gn:feature_code":"PPL",
    "gn:name":"Ranon Chhota",
    "gn:population":0,
    "gn:timezone":"Asia/Kolkata",
    "iso:country":"IN",
    "ks:ks_name":"Ranon Chhota",
    "ks:ks_pop":648,
    "ks:ks_type":"VILLAGE",
    "name:eng_x_preferred":[
        "Ranon Chhota"
    ],
    "wof:name":"Ranon Chhota",
    "wof:placetype":"locality",
    "wof:population":648
},
  "geometry": {"coordinates":[76.284729,30.519174],"type":"Point"}
}