{
  "type": "Feature",
  "properties": {
    "iso:country":"IN",
    "ks:ks_name":"Velimukku",
    "ks:ks_pop":951,
    "ks:ks_type":"HABITATION",
    "name:eng_x_preferred":[
        "Velimukku"
    ],
    "wof:name":"Velimukku",
    "wof:placetype":"locality",
    "wof:population":951
},
  "geometry": {"coordinates":[75.90201500000001,11.080323],"type":"Point"}
}