{
  "type": "Feature",
  "properties": {
    "iso:country":"IN",
    "ks:ks_alt_nam":"P\u016br\u016bsottampur",
    "ks:ks_name":"Purusottampur",
    "ks:ks_type":"VILLAGE",
    "name:eng_x_preferred":[
        "Purusottampur"
    ],
    "name:eng_x_variant":[
        "P\u016br\u016bsottampur"
    ],
    "wof:name":"Purusottampur",
    "wof:placetype":"locality"
},
  "geometry": {"coordinates":[85.219086,20.605468],"type":"Point"}
}