{
  "type": "Feature",
  "properties": {
    "iso:country":"IN",
    "ks:ks_alt_nam":"DUSADH  TOLA",
    "ks:ks_name":"Dusadh Tola",
    "ks:ks_pop":212,
    "ks:ks_type":"HABITATION",
    "name:eng_x_preferred":[
        "Dusadh Tola"
    ],
    "name:eng_x_variant":[
        "DUSADH  TOLA"
    ],
    "wof:name":"Dusadh Tola",
    "wof:placetype":"locality",
    "wof:population":212
},
  "geometry": {"coordinates":[83.449583,25.037096],"type":"Point"}
}