{
  "type": "Feature",
  "properties": {
    "gn:admin1_code":"36",
    "gn:admin2_code":"176.0",
    "gn:asciiname":"Ahmadnagar",
    "gn:country_code":"IN",
    "gn:dem":125,
    "gn:feature_class":"P",
    "gn:feature_code":"PPL",
    "gn:name":"Ahmadnagar",
    "gn:population":0,
    "gn:timezone":"Asia/Kolkata",
    "iso:country":"IN",
    "ks:ks_name":"Ahmed Nagar",
    "ks:ks_pop":110,
    "ks:ks_type":"HABITATION",
    "ks:ks_uagg_main":0,
    "name:ara_x_preferred":[
        "\u0623\u062d\u0645\u062f \u0646\u0627\u062c\u0627\u0631"
    ],
    "name:ben_bn_x_preferred":[
        "\u0986\u09b9\u09ae\u09c7\u09a6\u09a8\u0997\u09b0"
    ],
    "name:ben_in_x_preferred":[
        "\u0986\u09b9\u09ae\u09c7\u09a6\u09a8\u0997\u09b0"
    ],
    "name:eng_x_preferred":[
        "Ahmed Nagar"
    ],
    "name:guj_x_preferred":[
        "\u0a85\u0ab9\u0aae\u0aa6\u0aa8\u0a97\u0ab0"
    ],
    "name:hin_x_preferred":[
        "\u0905\u0939\u092e\u0926 \u0928\u0917\u0930"
    ],
    "name:kan_x_preferred":[
        "\u0c85\u0cb9\u0cae\u0ca6\u0ccd"
    ],
    "name:mal_x_preferred":[
        "\u0d05\u0d39\u0d4d\u0d2e\u0d26\u0d4d"
    ],
    "name:mar_x_preferred":[
        "\u0905\u0939\u092e\u0926\u0928\u0917\u0930"
    ],
    "name:pan_x_preferred":[
        "\u0a05\u0a39\u0a3f\u0a2e\u0a26\u0a28\u0a17\u0a30"
    ],
    "name:tam_x_preferred":[
        "\u0b85\u0b95\u0bae\u0ba4\u0bcd\u0ba8\u0b95\u0bb0\u0bcd"
    ],
    "name:tel_x_preferred":[
        "\u0c05\u0c39\u0c4d\u0c2e\u0c26\u0c4d"
    ],
    "name:urd_x_preferred":[
        "\u0627\u062d\u0645\u062f \u0646\u06af\u0631"
    ],
    "wof:name":"Ahmed Nagar",
    "wof:placetype":"neighbourhood",
    "wof:population":110
},
  "geometry": {"coordinates":[81.08130199999999,27.057785],"type":"Point"}
}