{
  "type": "Feature",
  "properties": {
    "gn:admin1_code":"19.0",
    "gn:admin2_code":"583.0",
    "gn:asciiname":"Ramgovindapura",
    "gn:country_code":"IN",
    "gn:dem":905,
    "gn:feature_class":"P",
    "gn:feature_code":"PPL",
    "gn:name":"R\u0101mgovindapura",
    "gn:population":0,
    "gn:timezone":"Asia/Kolkata",
    "iso:country":"IN",
    "wof:name":"Ramgovindapura",
    "wof:placetype":"locality"
},
  "geometry": {"coordinates":[77.87911,13.20828],"type":"Point"}
}