{
  "type": "Feature",
  "properties": {
    "iso:country":"IN",
    "ks:ks_name":"Poduru",
    "ks:ks_pop":612,
    "ks:ks_type":"VILLAGE",
    "ks:ks_uagg_main":0,
    "name:eng_x_preferred":[
        "Poduru"
    ],
    "wof:name":"Poduru",
    "wof:placetype":"neighbourhood",
    "wof:population":612
},
  "geometry": {"coordinates":[78.372316,12.808084],"type":"Point"}
}