{
  "type": "Feature",
  "properties": {
    "iso:country":"IN",
    "ks:ks_name":"Ranewadi",
    "ks:ks_pop":81,
    "ks:ks_type":"HABITATION",
    "name:eng_x_preferred":[
        "Ranewadi"
    ],
    "wof:name":"Ranewadi",
    "wof:placetype":"locality",
    "wof:population":81
},
  "geometry": {"coordinates":[73.733211,15.772773],"type":"Point"}
}