{
  "type": "Feature",
  "properties": {
    "iso:country":"IN",
    "ks:ks_name":"Khadiness",
    "ks:ks_pop":140,
    "ks:ks_type":"HABITATION",
    "name:eng_x_preferred":[
        "Khadiness"
    ],
    "wof:name":"Khadiness",
    "wof:placetype":"locality",
    "wof:population":140
},
  "geometry": {"coordinates":[70.133194,21.830611],"type":"Point"}
}