{
  "type": "Feature",
  "properties": {
    "iso:country":"IN",
    "ks:ks_name":"Musaithi Bengla",
    "ks:ks_pop":28,
    "ks:ks_type":"VILLAGE",
    "name:eng_x_preferred":[
        "Musaithi Bengla"
    ],
    "wof:name":"Musaithi Bengla",
    "wof:placetype":"locality",
    "wof:population":28
},
  "geometry": {"coordinates":[79.031644,30.025573],"type":"Point"}
}