{
  "type": "Feature",
  "properties": {
    "gn:admin1_code":"34.0",
    "gn:admin2_code":"234.0",
    "gn:asciiname":"Shivpur",
    "gn:country_code":"IN",
    "gn:dem":124,
    "gn:feature_class":"P",
    "gn:feature_code":"PPL",
    "gn:name":"Shivpur",
    "gn:population":0,
    "gn:timezone":"Asia/Kolkata",
    "iso:country":"IN",
    "ks:ks_name":"Shiupur",
    "ks:ks_pop":567,
    "ks:ks_type":"VILLAGE",
    "name:eng_x_preferred":[
        "Shiupur"
    ],
    "name:eng_x_variant":[
        "Shivpur"
    ],
    "wof:name":"Shiupur",
    "wof:placetype":"locality",
    "wof:population":567
},
  "geometry": {"coordinates":[84.028655,24.849442],"type":"Point"}
}