{
  "type": "Feature",
  "properties": {
    "gn:admin1_code":"24",
    "gn:admin2_code":"125.0",
    "gn:asciiname":"Bhuri Ser",
    "gn:country_code":"IN",
    "gn:dem":266,
    "gn:feature_class":"P",
    "gn:feature_code":"PPL",
    "gn:name":"Bh\u016bri Ser",
    "gn:population":0,
    "gn:timezone":"Asia/Kolkata",
    "iso:country":"IN",
    "ks:ks_alt_nam":"Bh\u016bri Ser",
    "ks:ks_name":"Bhuri Ser",
    "ks:ks_type":"VILLAGE",
    "name:eng_x_preferred":[
        "Bhuri Ser"
    ],
    "name:eng_x_variant":[
        "Bh\u016bri Ser"
    ],
    "wof:name":"Bhuri Ser",
    "wof:placetype":"locality"
},
  "geometry": {"coordinates":[74.176418,23.20443],"type":"Point"}
}