{
  "type": "Feature",
  "properties": {
    "gn:admin1_code":"34.0",
    "gn:admin2_code":"221.0",
    "gn:asciiname":"Kishunpur",
    "gn:country_code":"IN",
    "gn:dem":53,
    "gn:feature_class":"P",
    "gn:feature_code":"PPL",
    "gn:name":"Kishunpur",
    "gn:population":0,
    "gn:timezone":"Asia/Kolkata",
    "iso:country":"IN",
    "name:bpy_x_preferred":[
        "\u0995\u09bf\u09b6\u09c1\u09a8\u09aa\u09c1\u09b0"
    ],
    "name:hin_x_preferred":[
        "\u0915\u093f\u0936\u0941\u0928\u092a\u0941\u0930"
    ],
    "name:ita_x_preferred":[
        "Kishunpur"
    ],
    "name:msa_x_preferred":[
        "Kishunpur"
    ],
    "name:new_x_preferred":[
        "\u0915\u093f\u0936\u0941\u0928\u092a\u0941\u0930"
    ],
    "name:nld_x_preferred":[
        "Kishunpur"
    ],
    "name:pol_x_preferred":[
        "Kishunpur"
    ],
    "name:por_x_preferred":[
        "Kishunpur"
    ],
    "name:urd_x_preferred":[
        "\u06a9\u0634\u0648\u0646 \u067e\u0648\u0631"
    ],
    "name:vie_x_preferred":[
        "Kishunpur"
    ],
    "name:zho_x_preferred":[
        "\u57fa\u65af\u6d2a\u666e\u5c14"
    ],
    "wof:name":"Kishunpur",
    "wof:placetype":"locality"
},
  "geometry": {"coordinates":[85.95726999999999,25.95094],"type":"Point"}
}