{
  "type": "Feature",
  "properties": {
    "iso:country":"IN",
    "ks:ks_name":"Chotka Deeh",
    "ks:ks_pop":431,
    "ks:ks_type":"HABITATION",
    "name:eng_x_preferred":[
        "Chotka Deeh"
    ],
    "wof:name":"Chotka Deeh",
    "wof:placetype":"locality",
    "wof:population":431
},
  "geometry": {"coordinates":[82.986481,27.181472],"type":"Point"}
}