{
  "type": "Feature",
  "properties": {
    "iso:country":"IN",
    "ks:ks_name":"Amalagachhi Naraintola",
    "ks:ks_pop":191,
    "ks:ks_type":"VILLAGE",
    "name:eng_x_preferred":[
        "Amalagachhi Naraintola"
    ],
    "wof:name":"Amalagachhi Naraintola",
    "wof:placetype":"locality",
    "wof:population":191
},
  "geometry": {"coordinates":[87.716498,24.54897],"type":"Point"}
}