{
  "type": "Feature",
  "properties": {
    "iso:country":"IN",
    "ks:ks_alt_nam":"Rayabhari hatti",
    "ks:ks_name":"Rayabhari Hatti",
    "ks:ks_pop":241,
    "ks:ks_type":"HABITATION",
    "name:eng_x_preferred":[
        "Rayabhari Hatti"
    ],
    "wof:name":"Rayabhari Hatti",
    "wof:placetype":"locality",
    "wof:population":241
},
  "geometry": {"coordinates":[76.56,14.314167],"type":"Point"}
}