{
  "type": "Feature",
  "properties": {
    "gn:admin1_code":"28.0",
    "gn:admin2_code":"332.0",
    "gn:asciiname":"Imamganj",
    "gn:country_code":"IN",
    "gn:dem":31,
    "gn:feature_class":"P",
    "gn:feature_code":"PPL",
    "gn:name":"Im\u0101mganj",
    "gn:population":0,
    "gn:timezone":"Asia/Kolkata",
    "iso:country":"IN",
    "wof:name":"Imamganj",
    "wof:placetype":"neighbourhood"
},
  "geometry": {"coordinates":[87.78915000000001,25.39656],"type":"Point"}
}