{
  "type": "Feature",
  "properties": {
    "iso:country":"IN",
    "ks:ks_name":"Pura Gujaran",
    "ks:ks_pop":197,
    "ks:ks_type":"HABITATION",
    "name:eng_x_preferred":[
        "Pura Gujaran"
    ],
    "wof:name":"Pura Gujaran",
    "wof:placetype":"locality",
    "wof:population":197
},
  "geometry": {"coordinates":[81.58072300000001,26.587245],"type":"Point"}
}