{
  "type": "Feature",
  "properties": {
    "iso:country":"IN",
    "qs:name":"Paravur",
    "qs:name_adm0":"India",
    "qs:name_adm1":"Kerala",
    "qs:photos":56,
    "qs:photos_1k":11,
    "qs:photos_9k":2,
    "qs:photos_9r":5,
    "qs:photos_all":430,
    "qs:photos_sr":2,
    "qs:placetype":"Town",
    "qs:pop_sr":"0",
    "wd:wordcount":72,
    "wof:name":"Paravur",
    "wof:placetype":"locality"
},
  "geometry": {"coordinates":[76.221084,10.152746],"type":"Point"}
}