{
  "type": "Feature",
  "properties": {
    "iso:country":"IN",
    "ks:ks_alt_nam":"Sumdirimukh N.C.",
    "ks:ks_name":"Sumdirimukh N.c.",
    "ks:ks_pop":920,
    "ks:ks_type":"HABITATION",
    "name:eng_x_preferred":[
        "Sumdirimukh N.c."
    ],
    "wof:name":"Sumdirimukh N.c.",
    "wof:placetype":"locality",
    "wof:population":920
},
  "geometry": {"coordinates":[94.15768,27.204491],"type":"Point"}
}