{
  "type": "Feature",
  "properties": {
    "iso:country":"IN",
    "ks:ks_name":"Melavalasai",
    "ks:ks_pop":583,
    "ks:ks_type":"HABITATION",
    "ks:ks_uagg_main":0,
    "name:eng_x_preferred":[
        "Melavalasai"
    ],
    "wof:name":"Melavalasai",
    "wof:placetype":"neighbourhood",
    "wof:population":583
},
  "geometry": {"coordinates":[78.397802,9.994392],"type":"Point"}
}