{
  "type": "Feature",
  "properties": {
    "iso:country":"IN",
    "ks:ks_name":"Bogori Gaon-1",
    "ks:ks_pop":111,
    "ks:ks_type":"HABITATION",
    "ks:ks_uagg_main":0,
    "name:eng_x_preferred":[
        "Bogori Gaon-1"
    ],
    "wof:name":"Bogori Gaon-1",
    "wof:placetype":"neighbourhood",
    "wof:population":111
},
  "geometry": {"coordinates":[92.682716,25.971932],"type":"Point"}
}