{
  "type": "Feature",
  "properties": {
    "iso:country":"IN",
    "ks:ks_name":"Mandramalaipatti",
    "ks:ks_pop":116,
    "ks:ks_type":"HABITATION",
    "ks:ks_uagg_main":0,
    "name:eng_x_preferred":[
        "Mandramalaipatti"
    ],
    "wof:name":"Mandramalaipatti",
    "wof:placetype":"neighbourhood",
    "wof:population":116
},
  "geometry": {"coordinates":[78.398419,10.002617],"type":"Point"}
}