{
  "type": "Feature",
  "properties": {
    "iso:country":"IN",
    "ks:ks_name":"Kundadka",
    "ks:ks_pop":204,
    "ks:ks_type":"HABITATION",
    "name:eng_x_preferred":[
        "Kundadka"
    ],
    "wof:name":"Kundadka",
    "wof:placetype":"locality",
    "wof:population":204
},
  "geometry": {"coordinates":[75.34016800000001,12.909987],"type":"Point"}
}