{
  "type": "Feature",
  "properties": {
    "iso:country":"IN",
    "ks:ks_name":"Pungodu",
    "ks:ks_pop":645,
    "ks:ks_type":"HABITATION",
    "name:eng_x_preferred":[
        "Pungodu"
    ],
    "wof:name":"Pungodu",
    "wof:placetype":"locality",
    "wof:population":645
},
  "geometry": {"coordinates":[76.289248,11.151739],"type":"Point"}
}