{
  "type": "Feature",
  "properties": {
    "gn:admin1_code":"12.0",
    "gn:admin2_code":"010",
    "gn:asciiname":"Saidapor Hamchi",
    "gn:country_code":"IN",
    "gn:dem":1618,
    "gn:feature_class":"P",
    "gn:feature_code":"PPL",
    "gn:name":"Saidapor Hamchi",
    "gn:population":0,
    "gn:timezone":"Asia/Kolkata",
    "iso:country":"IN",
    "wof:name":"Saidapor Hamchi",
    "wof:placetype":"locality"
},
  "geometry": {"coordinates":[74.84116,34.17336],"type":"Point"}
}