{
  "type": "Feature",
  "properties": {
    "iso:country":"IN",
    "ks:ks_name":"Dakshin Bhalukabari",
    "ks:ks_pop":511,
    "ks:ks_type":"HABITATION",
    "name:eng_x_preferred":[
        "Dakshin Bhalukabari"
    ],
    "wof:name":"Dakshin Bhalukabari",
    "wof:placetype":"locality",
    "wof:population":511
},
  "geometry": {"coordinates":[91.197678,26.085579],"type":"Point"}
}