{
  "type": "Feature",
  "properties": {
    "iso:country":"IN",
    "ks:ks_name":"Gadhapar",
    "ks:ks_pop":85,
    "ks:ks_type":"HABITATION",
    "name:eng_x_preferred":[
        "Gadhapar"
    ],
    "wof:name":"Gadhapar",
    "wof:placetype":"locality",
    "wof:population":85
},
  "geometry": {"coordinates":[80.74606199999999,27.07198],"type":"Point"}
}