{
  "type": "Feature",
  "properties": {
    "iso:country":"IN",
    "ks:ks_name":"Jadishpur",
    "ks:ks_pop":254,
    "ks:ks_type":"VILLAGE",
    "ks:ks_uagg_main":0,
    "name:eng_x_preferred":[
        "Jadishpur"
    ],
    "wof:name":"Jadishpur",
    "wof:placetype":"neighbourhood",
    "wof:population":254
},
  "geometry": {"coordinates":[82.91957499999999,26.726852],"type":"Point"}
}