{
  "type": "Feature",
  "properties": {
    "gn:admin1_code":"36",
    "gn:admin2_code":"176.0",
    "gn:asciiname":"Ajgana",
    "gn:country_code":"IN",
    "gn:dem":125,
    "gn:feature_class":"P",
    "gn:feature_code":"PPL",
    "gn:name":"Ajgana",
    "gn:population":0,
    "gn:timezone":"Asia/Kolkata",
    "iso:country":"IN",
    "ks:ks_name":"Ajgana",
    "ks:ks_pop":1138,
    "ks:ks_type":"VILLAGE",
    "ks:ks_uagg_main":0,
    "name:eng_x_preferred":[
        "Ajgana"
    ],
    "wof:name":"Ajgana",
    "wof:placetype":"neighbourhood",
    "wof:population":1138
},
  "geometry": {"coordinates":[81.244902,27.031261],"type":"Point"}
}