{
  "type": "Feature",
  "properties": {
    "gn:admin1_code":"2.0",
    "gn:admin2_code":"544.0",
    "gn:asciiname":"Sitampeta",
    "gn:country_code":"IN",
    "gn:dem":125,
    "gn:feature_class":"P",
    "gn:feature_code":"PPL",
    "gn:name":"S\u012btampeta",
    "gn:population":0,
    "gn:timezone":"Asia/Kolkata",
    "iso:country":"IN",
    "ks:ks_name":"Seetampeta",
    "ks:ks_pop":163,
    "ks:ks_type":"VILLAGE",
    "name:eng_x_preferred":[
        "Seetampeta"
    ],
    "name:eng_x_variant":[
        "Sitampeta"
    ],
    "wof:name":"Seetampeta",
    "wof:placetype":"locality",
    "wof:population":163
},
  "geometry": {"coordinates":[83.114108,18.241201],"type":"Point"}
}