{
  "type": "Feature",
  "properties": {
    "iso:country":"IN",
    "ks:ks_name":"Khamala",
    "ks:ks_pop":1461,
    "ks:ks_type":"VILLAGE",
    "name:eng_x_preferred":[
        "Khamala"
    ],
    "wof:name":"Khamala",
    "wof:placetype":"locality",
    "wof:population":1461
},
  "geometry": {"coordinates":[74.331846,21.749536],"type":"Point"}
}