{
  "type": "Feature",
  "properties": {
    "iso:country":"IN",
    "ks:ks_name":"Adavilopalli",
    "ks:ks_pop":291,
    "ks:ks_type":"HABITATION",
    "name:eng_x_preferred":[
        "Adavilopalli"
    ],
    "wof:name":"Adavilopalli",
    "wof:placetype":"locality",
    "wof:population":291
},
  "geometry": {"coordinates":[79.59622299999999,15.177075],"type":"Point"}
}