{
  "type": "Feature",
  "properties": {
    "iso:country":"IN",
    "ks:ks_name":"Kiratpur Sahib",
    "ks:ks_pop":2004,
    "ks:ks_type":"URBAN",
    "ks:ks_uagg_main":0,
    "name:eng_x_preferred":[
        "Kiratpur Sahib"
    ],
    "name:fra_x_preferred":[
        "Kiratpur Sahib"
    ],
    "name:nld_x_preferred":[
        "Kiratpur Sahib"
    ],
    "name:pan_x_preferred":[
        "\u0a15\u0a40\u0a30\u0a24\u0a2a\u0a41\u0a30 \u0a38\u0a3e\u0a39\u0a3f\u0a2c"
    ],
    "name:urd_x_preferred":[
        "\u06a9\u0631\u062a\u067e\u0648\u0631 \u0635\u0627\u062d\u0628"
    ],
    "qs:name":"Kiratpur Sahib",
    "qs:name_adm0":"India",
    "qs:name_adm1":"Punjab",
    "qs:photos":13,
    "qs:photos_1k":3,
    "qs:photos_9k":1,
    "qs:photos_9r":1,
    "qs:photos_all":13,
    "qs:photos_sr":1,
    "qs:placetype":"Town",
    "qs:pop_sr":"0",
    "wof:name":"Kiratpur Sahib",
    "wof:placetype":"neighbourhood",
    "wof:population":2004
},
  "geometry": {"coordinates":[76.567786,31.184962],"type":"Point"}
}