{
  "type": "Feature",
  "properties": {
    "iso:country":"IN",
    "ks:ks_name":"Mevasa",
    "ks:ks_pop":555,
    "ks:ks_type":"VILLAGE",
    "name:eng_x_preferred":[
        "Mevasa"
    ],
    "wof:name":"Mevasa",
    "wof:placetype":"locality",
    "wof:population":555
},
  "geometry": {"coordinates":[71.46299999999999,21.3464],"type":"Point"}
}