{
  "type": "Feature",
  "properties": {
    "iso:country":"IN",
    "ks:ks_name":"Shiv Sthan Tola",
    "ks:ks_pop":350,
    "ks:ks_type":"HABITATION",
    "name:eng_x_preferred":[
        "Shiv Sthan Tola"
    ],
    "wof:name":"Shiv Sthan Tola",
    "wof:placetype":"locality",
    "wof:population":350
},
  "geometry": {"coordinates":[83.81778,26.889564],"type":"Point"}
}