{
  "type": "Feature",
  "properties": {
    "iso:country":"IN",
    "ks:ks_name":"Kujoli",
    "ks:ks_pop":42,
    "ks:ks_type":"HABITATION",
    "name:eng_x_preferred":[
        "Kujoli"
    ],
    "wof:name":"Kujoli",
    "wof:placetype":"locality",
    "wof:population":42
},
  "geometry": {"coordinates":[79.45205900000001,29.468312],"type":"Point"}
}