{
  "type": "Feature",
  "properties": {
    "gn:admin1_code":"36",
    "gn:admin2_code":"195.0",
    "gn:asciiname":"Gaura Namzad",
    "gn:country_code":"IN",
    "gn:dem":77,
    "gn:feature_class":"P",
    "gn:feature_code":"PPL",
    "gn:name":"Gaura N\u0101mz\u0101d",
    "gn:population":0,
    "gn:timezone":"Asia/Kolkata",
    "iso:country":"IN",
    "name:und_x_variant":[
        "Gaura N\u0101mz\u0101d",
        "L\u0101l\u0101pur"
    ],
    "wof:name":"Gaura Namzad",
    "wof:placetype":"locality"
},
  "geometry": {"coordinates":[83.37344,25.76021],"type":"Point"}
}