{
  "type": "Feature",
  "properties": {
    "iso:country":"IN",
    "ks:ks_name":"Bichkora",
    "ks:ks_pop":192,
    "ks:ks_type":"VILLAGE",
    "name:eng_x_preferred":[
        "Bichkora"
    ],
    "wof:name":"Bichkora",
    "wof:placetype":"locality",
    "wof:population":192
},
  "geometry": {"coordinates":[87.207821,24.239471],"type":"Point"}
}