{
  "type": "Feature",
  "properties": {
    "iso:country":"IN",
    "ks:ks_alt_nam":"Kant\u0101b\u0101h\u0101l",
    "ks:ks_name":"Kantabahal",
    "ks:ks_pop":1087,
    "ks:ks_type":"VILLAGE",
    "name:eng_x_preferred":[
        "Kantabahal"
    ],
    "name:eng_x_variant":[
        "Kant\u0101b\u0101h\u0101l"
    ],
    "wof:name":"Kantabahal",
    "wof:placetype":"locality",
    "wof:population":1087
},
  "geometry": {"coordinates":[84.811429,21.334916],"type":"Point"}
}