{
  "type": "Feature",
  "properties": {
    "iso:country":"IN",
    "ks:ks_name":"Nona Narayanchak",
    "ks:ks_pop":557,
    "ks:ks_type":"HABITATION",
    "name:eng_x_preferred":[
        "Nona Narayanchak"
    ],
    "wof:name":"Nona Narayanchak",
    "wof:placetype":"locality",
    "wof:population":557
},
  "geometry": {"coordinates":[87.82801499999999,22.501426],"type":"Point"}
}