{
  "type": "Feature",
  "properties": {
    "gn:admin1_code":"37.0",
    "gn:admin2_code":"404.0",
    "gn:asciiname":"Jemra",
    "gn:country_code":"IN",
    "gn:dem":590,
    "gn:feature_class":"P",
    "gn:feature_code":"PPL",
    "gn:name":"Jemra",
    "gn:population":0,
    "gn:timezone":"Asia/Kolkata",
    "iso:country":"IN",
    "ks:ks_name":"Jemra",
    "ks:ks_pop":919,
    "ks:ks_type":"VILLAGE",
    "name:eng_x_preferred":[
        "Jemra"
    ],
    "wof:name":"Jemra",
    "wof:placetype":"locality",
    "wof:population":919
},
  "geometry": {"coordinates":[82.244242,22.514377],"type":"Point"}
}