{
  "type": "Feature",
  "properties": {
    "iso:country":"IN",
    "ks:ks_name":"Sardar Ka Purwa",
    "ks:ks_pop":312,
    "ks:ks_type":"HABITATION",
    "name:eng_x_preferred":[
        "Sardar Ka Purwa"
    ],
    "wof:name":"Sardar Ka Purwa",
    "wof:placetype":"locality",
    "wof:population":312
},
  "geometry": {"coordinates":[81.405511,25.902787],"type":"Point"}
}