{
  "type": "Feature",
  "properties": {
    "gn:admin1_code":"25.0",
    "gn:admin2_code":"611.0",
    "gn:asciiname":"Manjavayal",
    "gn:country_code":"IN",
    "gn:dem":917,
    "gn:feature_class":"P",
    "gn:feature_code":"PPL",
    "gn:name":"Manjavayal",
    "gn:population":0,
    "gn:timezone":"Asia/Kolkata",
    "iso:country":"IN",
    "ks:ks_name":"Mangamvayal",
    "ks:ks_pop":301,
    "ks:ks_type":"HABITATION",
    "name:eng_x_preferred":[
        "Mangamvayal"
    ],
    "name:eng_x_variant":[
        "Manjavayal"
    ],
    "wof:name":"Mangamvayal",
    "wof:placetype":"locality",
    "wof:population":301
},
  "geometry": {"coordinates":[76.36283899999999,11.548976],"type":"Point"}
}