{
  "type": "Feature",
  "properties": {
    "iso:country":"IN",
    "ks:ks_name":"Gokalsar",
    "ks:ks_pop":498,
    "ks:ks_type":"HABITATION",
    "name:eng_x_preferred":[
        "Gokalsar"
    ],
    "wof:name":"Gokalsar",
    "wof:placetype":"locality",
    "wof:population":498
},
  "geometry": {"coordinates":[71.452758,25.255106],"type":"Point"}
}