{
  "type": "Feature",
  "properties": {
    "iso:country":"IN",
    "ks:ks_name":"Kantlia",
    "ks:ks_pop":7371,
    "ks:ks_type":"VILLAGE",
    "ks:ks_uagg_main":0,
    "name:eng_x_preferred":[
        "Kantlia"
    ],
    "wof:name":"Kantlia",
    "wof:placetype":"neighbourhood",
    "wof:population":7371
},
  "geometry": {"coordinates":[88.252555,22.617604],"type":"Point"}
}