{
  "type": "Feature",
  "properties": {
    "gn:admin1_code":"11.0",
    "gn:admin2_code":"27.0",
    "gn:asciiname":"Kamand",
    "gn:country_code":"IN",
    "gn:dem":2125,
    "gn:feature_class":"P",
    "gn:feature_code":"PPL",
    "gn:name":"Kam\u0101nd",
    "gn:population":0,
    "gn:timezone":"Asia/Kolkata",
    "iso:country":"IN",
    "wof:name":"Kamand",
    "wof:placetype":"locality"
},
  "geometry": {"coordinates":[77.27176,31.33908],"type":"Point"}
}