{
  "type": "Feature",
  "properties": {
    "iso:country":"IN",
    "ks:ks_name":"Karjani",
    "ks:ks_pop":1552,
    "ks:ks_type":"VILLAGE",
    "name:eng_x_preferred":[
        "Karjani"
    ],
    "wof:name":"Karjani",
    "wof:placetype":"locality",
    "wof:population":1552
},
  "geometry": {"coordinates":[85.20680299999999,24.85327],"type":"Point"}
}