{
  "type": "Feature",
  "properties": {
    "gn:admin1_code":"21",
    "gn:admin2_code":"396.0",
    "gn:asciiname":"Kadanibaru",
    "gn:country_code":"IN",
    "gn:dem":457,
    "gn:feature_class":"P",
    "gn:feature_code":"PPL",
    "gn:name":"Kadanib\u0101ru",
    "gn:population":0,
    "gn:timezone":"Asia/Kolkata",
    "iso:country":"IN",
    "ks:ks_name":"Kadanibaru",
    "ks:ks_pop":57,
    "ks:ks_type":"HABITATION",
    "name:eng_x_preferred":[
        "Kadanibaru"
    ],
    "wof:name":"Kadanibaru",
    "wof:placetype":"locality",
    "wof:population":57
},
  "geometry": {"coordinates":[83.456001,19.939228],"type":"Point"}
}