{
  "type": "Feature",
  "properties": {
    "iso:country":"IN",
    "ks:ks_name":"Jamadalu",
    "ks:ks_pop":123,
    "ks:ks_type":"HABITATION",
    "name:eng_x_preferred":[
        "Jamadalu"
    ],
    "wof:name":"Jamadalu",
    "wof:placetype":"locality",
    "wof:population":123
},
  "geometry": {"coordinates":[82.568518,18.139468],"type":"Point"}
}