{
  "type": "Feature",
  "properties": {
    "iso:country":"IN",
    "ks:ks_name":"Krishna Chak",
    "ks:ks_pop":2242,
    "ks:ks_type":"VILLAGE",
    "ks:ks_uagg_main":0,
    "name:eng_x_preferred":[
        "Krishna Chak"
    ],
    "wof:name":"Krishna Chak",
    "wof:placetype":"neighbourhood",
    "wof:population":2242
},
  "geometry": {"coordinates":[88.007924,22.651057],"type":"Point"}
}