{
  "type": "Feature",
  "properties": {
    "gn:admin1_code":"16.0",
    "gn:admin2_code":"517",
    "gn:asciiname":"Kasara",
    "gn:country_code":"IN",
    "gn:dem":289,
    "gn:feature_class":"P",
    "gn:feature_code":"PPL",
    "gn:name":"Kas\u0101ra",
    "gn:population":0,
    "gn:timezone":"Asia/Kolkata",
    "iso:country":"IN",
    "name:und_x_variant":[
        "Kas\u0101ra"
    ],
    "wof:name":"Kasara",
    "wof:placetype":"locality"
},
  "geometry": {"coordinates":[73.47434,19.6451],"type":"Point"}
}