{
  "type": "Feature",
  "properties": {
    "gn:admin1_code":"16.0",
    "gn:admin2_code":"517",
    "gn:asciiname":"Kasara",
    "gn:country_code":"IN",
    "gn:dem":289,
    "gn:feature_class":"P",
    "gn:feature_code":"PPL",
    "gn:name":"Kas\u0101ra",
    "gn:population":0,
    "gn:timezone":"Asia/Kolkata",
    "iso:country":"IN",
    "name:ben_x_preferred":[
        "\u0995\u09be\u09b8\u09be\u09b0\u09be \u09ac\u09c1\u09a6\u09b0\u09c1\u0995"
    ],
    "name:bpy_x_preferred":[
        "\u0995\u09be\u09b8\u09be\u09b0\u09be \u09ac\u09c1\u09a6\u09b0\u09c1\u0995"
    ],
    "name:hin_x_preferred":[
        "\u0915\u0938\u093e\u0930\u093e"
    ],
    "name:ita_x_preferred":[
        "Kasara Budruk"
    ],
    "name:mar_x_preferred":[
        "\u0915\u0938\u093e\u0930\u093e"
    ],
    "name:msa_x_preferred":[
        "Kasara Budruk"
    ],
    "name:new_x_preferred":[
        "\u0915\u0938\u0930\u093e \u092c\u0941\u0926\u094d\u0930\u0941\u0915"
    ],
    "name:nld_x_preferred":[
        "Kasara Budruk"
    ],
    "name:por_x_preferred":[
        "Kasara Budruk"
    ],
    "name:und_x_variant":[
        "Kas\u0101ra"
    ],
    "name:urd_x_preferred":[
        "\u06a9\u0633\u0627\u0631\u0627"
    ],
    "name:vie_x_preferred":[
        "Kasara Budruk"
    ],
    "name:zho_x_preferred":[
        "\u5361\u8428\u62c9\u5e03\u5fb7\u9c81\u514b"
    ],
    "wof:name":"Kasara",
    "wof:placetype":"locality"
},
  "geometry": {"coordinates":[73.47434,19.6451],"type":"Point"}
}