{
  "type": "Feature",
  "properties": {
    "iso:country":"IN",
    "ks:ks_name":"Amabhatha",
    "ks:ks_pop":219,
    "ks:ks_type":"HABITATION",
    "name:eng_x_preferred":[
        "Amabhatha"
    ],
    "wof:name":"Amabhatha",
    "wof:placetype":"locality",
    "wof:population":219
},
  "geometry": {"coordinates":[82.420919,22.610502],"type":"Point"}
}