{
  "type": "Feature",
  "properties": {
    "iso:country":"IN",
    "ks:ks_name":"Chibitabichia Pt X",
    "ks:ks_type":"VILLAGE",
    "name:eng_x_preferred":[
        "Chibitabichia Pt X"
    ],
    "wof:name":"Chibitabichia Pt X",
    "wof:placetype":"locality"
},
  "geometry": {"coordinates":[92.69010900000001,24.703853],"type":"Point"}
}