{
  "type": "Feature",
  "properties": {
    "gn:admin1_code":"12.0",
    "gn:admin2_code":"008",
    "gn:asciiname":"Takia",
    "gn:country_code":"IN",
    "gn:dem":1586,
    "gn:feature_class":"P",
    "gn:feature_code":"PPL",
    "gn:name":"Takia",
    "gn:population":0,
    "gn:timezone":"Asia/Kolkata",
    "iso:country":"IN",
    "name:ceb_x_preferred":[
        "Takia"
    ],
    "name:deu_x_preferred":[
        "Takia"
    ],
    "name:swe_x_preferred":[
        "Takia"
    ],
    "wof:name":"Takia",
    "wof:placetype":"locality"
},
  "geometry": {"coordinates":[74.7423,34.12879],"type":"Point"}
}