{
  "type": "Feature",
  "properties": {
    "gn:admin1_code":"36.0",
    "gn:admin2_code":"135.0",
    "gn:asciiname":"Birpur",
    "gn:country_code":"IN",
    "gn:dem":222,
    "gn:feature_class":"P",
    "gn:feature_code":"PPL",
    "gn:name":"B\u012brpur",
    "gn:population":0,
    "gn:timezone":"Asia/Kolkata",
    "iso:country":"IN",
    "name:und_x_variant":[
        "B\u012brpur",
        "Fatehull\u0101hpur"
    ],
    "wof:name":"Birpur",
    "wof:placetype":"locality"
},
  "geometry": {"coordinates":[78.9616,29.11832],"type":"Point"}
}