{
  "type": "Feature",
  "properties": {
    "iso:country":"IN",
    "ks:ks_alt_nam":"COLONY NO-2",
    "ks:ks_name":"Colony No-2",
    "ks:ks_pop":178,
    "ks:ks_type":"HABITATION",
    "name:eng_x_preferred":[
        "Colony No-2"
    ],
    "wof:name":"Colony No-2",
    "wof:placetype":"locality",
    "wof:population":178
},
  "geometry": {"coordinates":[91.482821,23.66958],"type":"Point"}
}