{
  "type": "Feature",
  "properties": {
    "iso:country":"IN",
    "ks:ks_name":"Kothanalloor",
    "ks:ks_pop":12021,
    "ks:ks_type":"VILLAGE",
    "name:eng_x_preferred":[
        "Kothanalloor"
    ],
    "wof:name":"Kothanalloor",
    "wof:placetype":"locality",
    "wof:population":12021
},
  "geometry": {"coordinates":[76.532252,9.717402],"type":"Point"}
}