{
  "type": "Feature",
  "properties": {
    "gn:admin1_code":"36",
    "gn:admin2_code":"191.0",
    "gn:asciiname":"Chak Chorra",
    "gn:country_code":"IN",
    "gn:dem":85,
    "gn:feature_class":"P",
    "gn:feature_code":"PPL",
    "gn:name":"Chak Chorra",
    "gn:population":0,
    "gn:timezone":"Asia/Kolkata",
    "iso:country":"IN",
    "ks:ks_name":"Chak Chorra",
    "ks:ks_type":"VILLAGE",
    "name:eng_x_preferred":[
        "Chak Chorra"
    ],
    "wof:name":"Chak Chorra",
    "wof:placetype":"locality"
},
  "geometry": {"coordinates":[82.798107,25.870717],"type":"Point"}
}