{
  "type": "Feature",
  "properties": {
    "iso:country":"IN",
    "ks:ks_name":"Pakurkala",
    "ks:ks_pop":264,
    "ks:ks_type":"VILLAGE",
    "name:eng_x_preferred":[
        "Pakurkala"
    ],
    "wof:name":"Pakurkala",
    "wof:placetype":"locality",
    "wof:population":264
},
  "geometry": {"coordinates":[80.62782300000001,19.797521],"type":"Point"}
}