{
  "type": "Feature",
  "properties": {
    "iso:country":"IN",
    "ks:ks_alt_nam":"Reddypalli BC Colony",
    "ks:ks_name":"Reddypalli Bc Colony",
    "ks:ks_pop":259,
    "ks:ks_type":"HABITATION",
    "name:eng_x_preferred":[
        "Reddypalli Bc Colony"
    ],
    "wof:name":"Reddypalli Bc Colony",
    "wof:placetype":"locality",
    "wof:population":259
},
  "geometry": {"coordinates":[79.03382000000001,14.583661],"type":"Point"}
}