{
  "type": "Feature",
  "properties": {
    "gn:admin1_code":"10.0",
    "gn:admin2_code":"74.0",
    "gn:asciiname":"Baldhi",
    "gn:country_code":"IN",
    "gn:dem":253,
    "gn:feature_class":"P",
    "gn:feature_code":"PPL",
    "gn:name":"Baldhi",
    "gn:population":0,
    "gn:timezone":"Asia/Kolkata",
    "iso:country":"IN",
    "ks:ks_name":"Baldhi",
    "ks:ks_pop":3122,
    "ks:ks_type":"VILLAGE",
    "ks:ks_uagg_main":0,
    "name:eng_x_preferred":[
        "Baldhi"
    ],
    "wof:name":"Baldhi",
    "wof:placetype":"neighbourhood",
    "wof:population":3122
},
  "geometry": {"coordinates":[76.99003999999999,29.719403],"type":"Point"}
}