{
  "type": "Feature",
  "properties": {
    "gn:admin1_code":"12.0",
    "gn:admin2_code":"7.0",
    "gn:asciiname":"Simti",
    "gn:country_code":"IN",
    "gn:dem":1023,
    "gn:feature_class":"P",
    "gn:feature_code":"PPL",
    "gn:name":"Simti",
    "gn:population":0,
    "gn:timezone":"Asia/Kolkata",
    "iso:country":"IN",
    "wof:name":"Simti",
    "wof:placetype":"locality"
},
  "geometry": {"coordinates":[75.68144000000002,32.56856],"type":"Point"}
}