{
  "type": "Feature",
  "properties": {
    "iso:country":"IN",
    "ks:ks_name":"Kuthegaon",
    "ks:ks_pop":499,
    "ks:ks_type":"VILLAGE",
    "name:eng_x_preferred":[
        "Kuthegaon"
    ],
    "wof:name":"Kuthegaon",
    "wof:placetype":"locality",
    "wof:population":499
},
  "geometry": {"coordinates":[80.07088299999999,19.984537],"type":"Point"}
}