{
  "type": "Feature",
  "properties": {
    "iso:country":"IN",
    "ks:ks_name":"Mannu Machhi Chak",
    "ks:ks_pop":40,
    "ks:ks_type":"VILLAGE",
    "name:eng_x_preferred":[
        "Mannu Machhi Chak"
    ],
    "wof:name":"Mannu Machhi Chak",
    "wof:placetype":"locality",
    "wof:population":40
},
  "geometry": {"coordinates":[75.074958,31.132739],"type":"Point"}
}