{
  "type": "Feature",
  "properties": {
    "iso:country":"IN",
    "ks:ks_name":"Sekhachak",
    "ks:ks_pop":433,
    "ks:ks_type":"VILLAGE",
    "name:eng_x_preferred":[
        "Sekhachak"
    ],
    "wof:name":"Sekhachak",
    "wof:placetype":"locality",
    "wof:population":433
},
  "geometry": {"coordinates":[87.76645600000001,25.040079],"type":"Point"}
}