{
  "type": "Feature",
  "properties": {
    "iso:country":"IN",
    "ks:ks_name":"Burj Hakim",
    "ks:ks_pop":1105,
    "ks:ks_type":"VILLAGE",
    "name:eng_x_preferred":[
        "Burj Hakim"
    ],
    "wof:name":"Burj Hakim",
    "wof:placetype":"locality",
    "wof:population":1105
},
  "geometry": {"coordinates":[75.662553,30.686966],"type":"Point"}
}