{
  "type": "Feature",
  "properties": {
    "iso:country":"IN",
    "ks:ks_alt_nam":"P\u0101ndedih",
    "ks:ks_name":"Pandedih",
    "ks:ks_pop":201,
    "ks:ks_type":"VILLAGE",
    "name:eng_x_preferred":[
        "Pandedih"
    ],
    "name:eng_x_variant":[
        "P\u0101ndedih"
    ],
    "wof:name":"Pandedih",
    "wof:placetype":"locality",
    "wof:population":201
},
  "geometry": {"coordinates":[86.188778,24.077856],"type":"Point"}
}