{
  "type": "Feature",
  "properties": {
    "iso:country":"IN",
    "ks:ks_alt_nam":"BAGRAI BARI",
    "ks:ks_name":"Bagrai Bari",
    "ks:ks_pop":45,
    "ks:ks_type":"HABITATION",
    "name:eng_x_preferred":[
        "Bagrai Bari"
    ],
    "wof:name":"Bagrai Bari",
    "wof:placetype":"locality",
    "wof:population":45
},
  "geometry": {"coordinates":[91.65170999999999,24.136407],"type":"Point"}
}