{
  "type": "Feature",
  "properties": {
    "iso:country":"IN",
    "ks:ks_name":"Jalahati",
    "ks:ks_pop":3943,
    "ks:ks_type":"VILLAGE",
    "ks:ks_uagg_main":0,
    "name:eng_x_preferred":[
        "Jalahati"
    ],
    "wof:name":"Jalahati",
    "wof:placetype":"locality",
    "wof:population":3943
},
  "geometry": {"coordinates":[88.320329,23.35064],"type":"Point"}
}