{
  "type": "Feature",
  "properties": {
    "iso:country":"IN",
    "ks:ks_alt_nam":"VARMA BASTI",
    "ks:ks_name":"Varma Basti",
    "ks:ks_pop":60,
    "ks:ks_type":"HABITATION",
    "ks:ks_uagg_main":0,
    "name:eng_x_preferred":[
        "Varma Basti"
    ],
    "wof:name":"Varma Basti",
    "wof:placetype":"neighbourhood",
    "wof:population":60
},
  "geometry": {"coordinates":[82.570649,26.19367],"type":"Point"}
}