{
  "type": "Feature",
  "properties": {
    "iso:country":"IN",
    "ks:ks_name":"18 Bosti",
    "ks:ks_pop":250,
    "ks:ks_type":"HABITATION",
    "name:eng_x_preferred":[
        "18 Bosti"
    ],
    "wof:name":"18 Bosti",
    "wof:placetype":"locality",
    "wof:population":250
},
  "geometry": {"coordinates":[90.718977,26.634305],"type":"Point"}
}