{
  "type": "Feature",
  "properties": {
    "iso:country":"IN",
    "ks:ks_name":"Sagpada",
    "ks:ks_pop":169,
    "ks:ks_type":"HABITATION",
    "name:eng_x_preferred":[
        "Sagpada"
    ],
    "wof:name":"Sagpada",
    "wof:placetype":"locality",
    "wof:population":169
},
  "geometry": {"coordinates":[72.861096,19.83167],"type":"Point"}
}