{
  "type": "Feature",
  "properties": {
    "iso:country":"IN",
    "ks:ks_name":"Paraspura",
    "ks:ks_pop":0,
    "ks:ks_type":"VILLAGE",
    "name:eng_x_preferred":[
        "Paraspura"
    ],
    "wof:name":"Paraspura",
    "wof:placetype":"locality",
    "wof:population":0
},
  "geometry": {"coordinates":[83.854339,25.138849],"type":"Point"}
}