{
  "type": "Feature",
  "properties": {
    "iso:country":"IN",
    "ks:ks_name":"Maujampur",
    "ks:ks_pop":891,
    "ks:ks_type":"HABITATION",
    "name:eng_x_preferred":[
        "Maujampur"
    ],
    "wof:name":"Maujampur",
    "wof:placetype":"locality",
    "wof:population":891
},
  "geometry": {"coordinates":[79.899052,26.801781],"type":"Point"}
}