{
  "type": "Feature",
  "properties": {
    "gn:admin1_code":"11",
    "gn:admin2_code":"23.0",
    "gn:asciiname":"Mandrala",
    "gn:country_code":"IN",
    "gn:dem":2471,
    "gn:feature_class":"P",
    "gn:feature_code":"PPL",
    "gn:name":"Mandr\u0101la",
    "gn:population":0,
    "gn:timezone":"Asia/Kolkata",
    "iso:country":"IN",
    "wof:name":"Mandrala",
    "wof:placetype":"locality"
},
  "geometry": {"coordinates":[76.14754000000001,32.43805],"type":"Point"}
}