{
  "type": "Feature",
  "properties": {
    "iso:country":"IN",
    "ks:ks_name":"Lumbininagar",
    "ks:ks_pop":245,
    "ks:ks_type":"HABITATION",
    "name:eng_x_preferred":[
        "Lumbininagar"
    ],
    "wof:name":"Lumbininagar",
    "wof:placetype":"locality",
    "wof:population":245
},
  "geometry": {"coordinates":[79.760783,19.400392],"type":"Point"}
}