{
  "type": "Feature",
  "properties": {
    "iso:country":"IN",
    "ks:ks_name":"Jannivaniguda",
    "ks:ks_pop":58,
    "ks:ks_type":"HABITATION",
    "name:eng_x_preferred":[
        "Jannivaniguda"
    ],
    "wof:name":"Jannivaniguda",
    "wof:placetype":"locality",
    "wof:population":58
},
  "geometry": {"coordinates":[83.889357,18.717008],"type":"Point"}
}