{
  "type": "Feature",
  "properties": {
    "iso:country":"IN",
    "ks:ks_name":"Gothanya Khurd",
    "ks:ks_pop":471,
    "ks:ks_type":"HABITATION",
    "name:eng_x_preferred":[
        "Gothanya Khurd"
    ],
    "wof:name":"Gothanya Khurd",
    "wof:placetype":"locality",
    "wof:population":471
},
  "geometry": {"coordinates":[74.916393,22.982112],"type":"Point"}
}