{
  "type": "Feature",
  "properties": {
    "iso:country":"IN",
    "ks:ks_alt_nam":"CHANDRADHAN PARA",
    "ks:ks_name":"Chandradhan Para",
    "ks:ks_pop":135,
    "ks:ks_type":"HABITATION",
    "ks:ks_uagg_main":0,
    "name:eng_x_preferred":[
        "Chandradhan Para"
    ],
    "wof:name":"Chandradhan Para",
    "wof:placetype":"neighbourhood",
    "wof:population":135
},
  "geometry": {"coordinates":[91.57013600000001,23.938493],"type":"Point"}
}