{
  "type": "Feature",
  "properties": {
    "gn:admin1_code":"23.0",
    "gn:admin2_code":"50.0",
    "gn:asciiname":"Pindori Gola",
    "gn:country_code":"IN",
    "gn:dem":228,
    "gn:feature_class":"P",
    "gn:feature_code":"PPL",
    "gn:name":"Pindori Gola",
    "gn:population":0,
    "gn:timezone":"Asia/Kolkata",
    "iso:country":"IN",
    "wof:name":"Pindori Gola",
    "wof:placetype":"locality"
},
  "geometry": {"coordinates":[74.95957,31.45568],"type":"Point"}
}