{
  "type": "Feature",
  "properties": {
    "iso:country":"IN",
    "ks:ks_name":"Gandhinagar",
    "ks:ks_pop":615,
    "ks:ks_type":"HABITATION",
    "ks:ks_uagg_main":0,
    "name:eng_x_preferred":[
        "Gandhinagar"
    ],
    "wof:name":"Gandhinagar",
    "wof:placetype":"neighbourhood",
    "wof:population":615
},
  "geometry": {"coordinates":[77.76544800000001,11.286378],"type":"Point"}
}