{
  "type": "Feature",
  "properties": {
    "iso:country":"IN",
    "ks:ks_name":"Hakhyabari",
    "ks:ks_pop":106,
    "ks:ks_type":"HABITATION",
    "name:eng_x_preferred":[
        "Hakhyabari"
    ],
    "wof:name":"Hakhyabari",
    "wof:placetype":"neighbourhood",
    "wof:population":106
},
  "geometry": {"coordinates":[91.565693,26.04857],"type":"Point"}
}