{
  "type": "Feature",
  "properties": {
    "iso:country":"IN",
    "ks:ks_name":"Chhota Khunta",
    "ks:ks_pop":303,
    "ks:ks_type":"HABITATION",
    "ks:ks_uagg_main":0,
    "name:eng_x_preferred":[
        "Chhota Khunta"
    ],
    "wof:name":"Chhota Khunta",
    "wof:placetype":"neighbourhood",
    "wof:population":303
},
  "geometry": {"coordinates":[85.167219,23.296601],"type":"Point"}
}