{
  "type": "Feature",
  "properties": {
    "gn:admin1_code":"25.0",
    "gn:admin2_code":"606.0",
    "gn:asciiname":"Perumpandi",
    "gn:country_code":"IN",
    "gn:dem":111,
    "gn:feature_class":"P",
    "gn:feature_code":"PPL",
    "gn:name":"Perump\u0101ndi",
    "gn:population":0,
    "gn:timezone":"Asia/Kolkata",
    "iso:country":"IN",
    "ks:ks_alt_nam":"Perump\u0101ndi",
    "ks:ks_name":"Perumpandi",
    "ks:ks_type":"VILLAGE",
    "name:eng_x_preferred":[
        "Perumpandi"
    ],
    "name:eng_x_variant":[
        "Perump\u0101ndi"
    ],
    "wof:name":"Perumpandi",
    "wof:placetype":"locality"
},
  "geometry": {"coordinates":[79.558505,12.731488],"type":"Point"}
}