{
  "type": "Feature",
  "properties": {
    "iso:country":"IN",
    "ks:ks_name":"Chhidirpur Khas",
    "ks:ks_pop":414,
    "ks:ks_type":"HABITATION",
    "name:eng_x_preferred":[
        "Chhidirpur Khas"
    ],
    "wof:name":"Chhidirpur Khas",
    "wof:placetype":"locality",
    "wof:population":414
},
  "geometry": {"coordinates":[82.470214,26.438697],"type":"Point"}
}