{
  "type": "Feature",
  "properties": {
    "gn:admin1_code":"19.0",
    "gn:admin2_code":"565.0",
    "gn:asciiname":"Kuruvatti",
    "gn:country_code":"IN",
    "gn:dem":525,
    "gn:feature_class":"P",
    "gn:feature_code":"PPL",
    "gn:name":"Kuruvatti",
    "gn:population":0,
    "gn:timezone":"Asia/Kolkata",
    "iso:country":"IN",
    "wof:name":"Kuruvatti",
    "wof:placetype":"locality"
},
  "geometry": {"coordinates":[75.70170999999998,14.78495],"type":"Point"}
}