{
  "type": "Feature",
  "properties": {
    "iso:country":"IN",
    "ks:ks_name":"Managerbungle",
    "ks:ks_pop":166,
    "ks:ks_type":"HABITATION",
    "name:eng_x_preferred":[
        "Managerbungle"
    ],
    "wof:name":"Managerbungle",
    "wof:placetype":"locality",
    "wof:population":166
},
  "geometry": {"coordinates":[75.828611,12.540833],"type":"Point"}
}