{
  "type": "Feature",
  "properties": {
    "gn:admin1_code":"13.0",
    "gn:admin2_code":"589.0",
    "gn:asciiname":"Palayat",
    "gn:country_code":"IN",
    "gn:dem":33,
    "gn:feature_class":"P",
    "gn:feature_code":"PPL",
    "gn:name":"Palayat",
    "gn:population":0,
    "gn:timezone":"Asia/Kolkata",
    "iso:country":"IN",
    "wof:name":"Palayat",
    "wof:placetype":"neighbourhood"
},
  "geometry": {"coordinates":[75.47667,11.7796],"type":"Point"}
}