{
  "type": "Feature",
  "properties": {
    "iso:country":"IN",
    "ks:ks_name":"Adasingi",
    "ks:ks_pop":112,
    "ks:ks_type":"VILLAGE",
    "name:eng_x_preferred":[
        "Adasingi"
    ],
    "wof:name":"Adasingi",
    "wof:placetype":"locality",
    "wof:population":112
},
  "geometry": {"coordinates":[83.964254,20.626864],"type":"Point"}
}