{
  "type": "Feature",
  "properties": {
    "iso:country":"IN",
    "ks:ks_name":"Krishnpura",
    "ks:ks_pop":242,
    "ks:ks_type":"HABITATION",
    "name:eng_x_preferred":[
        "Krishnpura"
    ],
    "wof:name":"Krishnpura",
    "wof:placetype":"locality",
    "wof:population":242
},
  "geometry": {"coordinates":[76.352628,13.657962],"type":"Point"}
}