{
  "type": "Feature",
  "properties": {
    "gn:admin1_code":"37",
    "gn:admin2_code":"406.0",
    "gn:asciiname":"Sawatpur",
    "gn:country_code":"IN",
    "gn:dem":318,
    "gn:feature_class":"P",
    "gn:feature_code":"PPL",
    "gn:name":"S\u0101watpur",
    "gn:population":0,
    "gn:timezone":"Asia/Kolkata",
    "iso:country":"IN",
    "ks:ks_alt_nam":"SAWANTPUR",
    "ks:ks_name":"Sawantpur",
    "ks:ks_pop":128,
    "ks:ks_type":"HABITATION",
    "name:eng_x_preferred":[
        "Sawantpur"
    ],
    "name:eng_x_variant":[
        "Sawatpur"
    ],
    "wof:name":"Sawantpur",
    "wof:placetype":"locality",
    "wof:population":128
},
  "geometry": {"coordinates":[81.777411,22.283934],"type":"Point"}
}