{
  "type": "Feature",
  "properties": {
    "gn:admin1_code":"10",
    "gn:admin2_code":"80.0",
    "gn:asciiname":"Bhaini",
    "gn:country_code":"IN",
    "gn:dem":223,
    "gn:feature_class":"P",
    "gn:feature_code":"PPL",
    "gn:name":"Bhaini",
    "gn:population":0,
    "gn:timezone":"Asia/Kolkata",
    "iso:country":"IN",
    "wof:name":"Bhaini",
    "wof:placetype":"locality"
},
  "geometry": {"coordinates":[76.15985999999999,29.24496],"type":"Point"}
}