{
  "type": "Feature",
  "properties": {
    "iso:country":"IN",
    "ks:ks_name":"Doraguda",
    "ks:ks_pop":57,
    "ks:ks_type":"HABITATION",
    "name:eng_x_preferred":[
        "Doraguda"
    ],
    "wof:name":"Doraguda",
    "wof:placetype":"locality",
    "wof:population":57
},
  "geometry": {"coordinates":[81.94443800000001,18.51483],"type":"Point"}
}