{
  "type": "Feature",
  "properties": {
    "iso:country":"IN",
    "ks:ks_name":"Purab Tola",
    "ks:ks_pop":348,
    "ks:ks_type":"HABITATION",
    "name:eng_x_preferred":[
        "Purab Tola"
    ],
    "wof:name":"Purab Tola",
    "wof:placetype":"locality",
    "wof:population":348
},
  "geometry": {"coordinates":[87.881199,26.168406],"type":"Point"}
}