{
  "type": "Feature",
  "properties": {
    "gn:admin1_code":"35",
    "gn:admin2_code":"462.0",
    "gn:asciiname":"Kham",
    "gn:country_code":"IN",
    "gn:dem":372,
    "gn:feature_class":"P",
    "gn:feature_code":"PPL",
    "gn:name":"Kh\u0101m",
    "gn:population":0,
    "gn:timezone":"Asia/Kolkata",
    "iso:country":"IN",
    "name:bod_x_preferred":[
        "\u0f41\u0f58\u0f66\u0f0d"
    ],
    "name:ces_x_preferred":[
        "Kham"
    ],
    "name:dan_x_preferred":[
        "Kham"
    ],
    "name:deu_x_preferred":[
        "Kham"
    ],
    "name:epo_x_preferred":[
        "Kham"
    ],
    "name:est_x_preferred":[
        "Kham"
    ],
    "name:fra_x_preferred":[
        "Kham"
    ],
    "name:gle_x_preferred":[
        "Kham"
    ],
    "name:ind_x_preferred":[
        "Kham"
    ],
    "name:ita_x_preferred":[
        "Kham"
    ],
    "name:jpn_x_preferred":[
        "\u30ab\u30e0"
    ],
    "name:kat_x_preferred":[
        "\u10d9\u10d0\u10db\u10d8"
    ],
    "name:kaz_x_preferred":[
        "\u041a\u0430\u043c"
    ],
    "name:kor_x_preferred":[
        "\uce84"
    ],
    "name:lit_x_preferred":[
        "Khamas"
    ],
    "name:nld_x_preferred":[
        "Kham"
    ],
    "name:nor_x_preferred":[
        "Kham"
    ],
    "name:pol_x_preferred":[
        "Kham"
    ],
    "name:por_x_preferred":[
        "Kham"
    ],
    "name:rus_x_preferred":[
        "\u041a\u0430\u043c"
    ],
    "name:spa_x_preferred":[
        "Kham"
    ],
    "name:swe_x_preferred":[
        "Kham"
    ],
    "name:ukr_x_preferred":[
        "\u041a\u0445\u0430\u043c"
    ],
    "name:uzb_x_preferred":[
        "Kam"
    ],
    "name:vie_x_preferred":[
        "Kham"
    ],
    "wof:name":"Kham",
    "wof:placetype":"locality"
},
  "geometry": {"coordinates":[81.74355,24.24128],"type":"Point"}
}