{
  "type": "Feature",
  "properties": {
    "gn:admin1_code":"35",
    "gn:admin2_code":"462.0",
    "gn:asciiname":"Kham",
    "gn:country_code":"IN",
    "gn:dem":372,
    "gn:feature_class":"P",
    "gn:feature_code":"PPL",
    "gn:name":"Kh\u0101m",
    "gn:population":0,
    "gn:timezone":"Asia/Kolkata",
    "iso:country":"IN",
    "wof:name":"Kham",
    "wof:placetype":"locality"
},
  "geometry": {"coordinates":[81.74355,24.24128],"type":"Point"}
}