{
  "type": "Feature",
  "properties": {
    "iso:country":"IN",
    "ks:ks_name":"Udela",
    "ks:ks_pop":768,
    "ks:ks_type":"VILLAGE",
    "name:eng_x_preferred":[
        "Udela"
    ],
    "wof:name":"Udela",
    "wof:placetype":"locality",
    "wof:population":768
},
  "geometry": {"coordinates":[74.083118,23.514606],"type":"Point"}
}