{
  "type": "Feature",
  "properties": {
    "gn:admin1_code":"35.0",
    "gn:admin2_code":"439",
    "gn:asciiname":"Fatehabad Chandrawatiganj",
    "gn:country_code":"IN",
    "gn:dem":508,
    "gn:feature_class":"P",
    "gn:feature_code":"PPL",
    "gn:name":"Fateh\u0101b\u0101d Chandr\u0101watiganj",
    "gn:population":0,
    "gn:timezone":"Asia/Kolkata",
    "iso:country":"IN",
    "name:und_x_variant":[
        "Fateh\u0101b\u0101d Chandr\u0101watiganj"
    ],
    "wof:name":"Fatehabad Chandrawatiganj",
    "wof:placetype":"neighbourhood"
},
  "geometry": {"coordinates":[75.65642,23.00306],"type":"Point"}
}