{
  "type": "Feature",
  "properties": {
    "gn:admin1_code":"19.0",
    "gn:admin2_code":"572.0",
    "gn:asciiname":"Madavar",
    "gn:country_code":"IN",
    "gn:dem":861,
    "gn:feature_class":"P",
    "gn:feature_code":"PPL",
    "gn:name":"M\u0101davar",
    "gn:population":0,
    "gn:timezone":"Asia/Kolkata",
    "iso:country":"IN",
    "ks:ks_name":"Madavara",
    "ks:ks_pop":3544,
    "ks:ks_type":"VILLAGE",
    "ks:ks_uagg_main":0,
    "name:eng_x_preferred":[
        "Madavara"
    ],
    "wof:name":"Madavara",
    "wof:placetype":"locality",
    "wof:population":3544
},
  "geometry": {"coordinates":[77.47186000000001,13.053431],"type":"Point"}
}