{
  "type": "Feature",
  "properties": {
    "gn:admin1_code":"19.0",
    "gn:admin2_code":"565.0",
    "gn:asciiname":"Masudupuram",
    "gn:country_code":"IN",
    "gn:dem":406,
    "gn:feature_class":"P",
    "gn:feature_code":"PPL",
    "gn:name":"Mas\u016bdupuram",
    "gn:population":0,
    "gn:timezone":"Asia/Kolkata",
    "iso:country":"IN",
    "ks:ks_name":"Masudipura",
    "ks:ks_pop":1145,
    "ks:ks_type":"VILLAGE",
    "name:eng_x_preferred":[
        "Masudipura"
    ],
    "name:eng_x_variant":[
        "Masudupuram"
    ],
    "wof:name":"Masudipura",
    "wof:placetype":"locality",
    "wof:population":1145
},
  "geometry": {"coordinates":[77.01213,15.278923],"type":"Point"}
}