{
  "type": "Feature",
  "properties": {
    "iso:country":"IN",
    "ks:ks_name":"Derhganw",
    "ks:ks_pop":279,
    "ks:ks_type":"VILLAGE",
    "name:eng_x_preferred":[
        "Derhganw"
    ],
    "wof:name":"Derhganw",
    "wof:placetype":"locality",
    "wof:population":279
},
  "geometry": {"coordinates":[84.131072,23.592801],"type":"Point"}
}