{
  "type": "Feature",
  "properties": {
    "gn:admin1_code":"19.0",
    "gn:admin2_code":"574.0",
    "gn:asciiname":"Kavari",
    "gn:country_code":"IN",
    "gn:dem":1047,
    "gn:feature_class":"P",
    "gn:feature_code":"PPL",
    "gn:name":"Kavari",
    "gn:population":0,
    "gn:timezone":"Asia/Kolkata",
    "iso:country":"IN",
    "name:fas_x_preferred":[
        "\u06a9\u0627\u0648\u0627\u0631\u06cc"
    ],
    "wof:name":"Kavari",
    "wof:placetype":"locality"
},
  "geometry": {"coordinates":[75.82961,13.09846],"type":"Point"}
}