{
  "type": "Feature",
  "properties": {
    "iso:country":"IN",
    "ks:ks_name":"Bethiasahi",
    "ks:ks_pop":260,
    "ks:ks_type":"HABITATION",
    "name:eng_x_preferred":[
        "Bethiasahi"
    ],
    "wof:name":"Bethiasahi",
    "wof:placetype":"locality",
    "wof:population":260
},
  "geometry": {"coordinates":[84.874916,20.486827],"type":"Point"}
}