{
  "type": "Feature",
  "properties": {
    "iso:country":"IN",
    "ks:ks_name":"Chintaram Para",
    "ks:ks_pop":84,
    "ks:ks_type":"HABITATION",
    "name:eng_x_preferred":[
        "Chintaram Para"
    ],
    "wof:name":"Chintaram Para",
    "wof:placetype":"locality",
    "wof:population":84
},
  "geometry": {"coordinates":[91.838275,23.888904],"type":"Point"}
}