{
  "type": "Feature",
  "properties": {
    "iso:country":"IN",
    "ks:ks_name":"Bodamunda",
    "ks:ks_pop":641,
    "ks:ks_type":"VILLAGE",
    "name:eng_x_preferred":[
        "Bodamunda"
    ],
    "wof:name":"Bodamunda",
    "wof:placetype":"locality",
    "wof:population":641
},
  "geometry": {"coordinates":[83.00921,20.656334],"type":"Point"}
}