{
  "type": "Feature",
  "properties": {
    "iso:country":"IN",
    "ks:ks_alt_nam":"PAHADPUR KALA",
    "ks:ks_name":"Pahadpur Kala",
    "ks:ks_pop":280,
    "ks:ks_type":"HABITATION",
    "ks:ks_uagg_main":0,
    "name:eng_x_preferred":[
        "Pahadpur Kala"
    ],
    "wof:name":"Pahadpur Kala",
    "wof:placetype":"neighbourhood",
    "wof:population":280
},
  "geometry": {"coordinates":[80.99216800000001,26.378285],"type":"Point"}
}