{
  "type": "Feature",
  "properties": {
    "iso:country":"IN",
    "ks:ks_name":"Nayapara",
    "ks:ks_pop":182,
    "ks:ks_type":"HABITATION",
    "name:eng_x_preferred":[
        "Nayapara"
    ],
    "wof:name":"Nayapara",
    "wof:placetype":"locality",
    "wof:population":182
},
  "geometry": {"coordinates":[81.19078,19.00613],"type":"Point"}
}