{
  "type": "Feature",
  "properties": {
    "iso:country":"IN",
    "ks:ks_name":"Chichewada",
    "ks:ks_pop":326,
    "ks:ks_type":"HABITATION",
    "name:eng_x_preferred":[
        "Chichewada"
    ],
    "wof:name":"Chichewada",
    "wof:placetype":"locality",
    "wof:population":326
},
  "geometry": {"coordinates":[74.22508000000001,14.856053],"type":"Point"}
}