{
  "type": "Feature",
  "properties": {
    "iso:country":"IN",
    "ks:ks_alt_nam":"PAKERKUDAR",
    "ks:ks_name":"Pakerkudar",
    "ks:ks_pop":529,
    "ks:ks_type":"HABITATION",
    "name:eng_x_preferred":[
        "Pakerkudar"
    ],
    "wof:name":"Pakerkudar",
    "wof:placetype":"locality",
    "wof:population":529
},
  "geometry": {"coordinates":[84.02414,22.824619],"type":"Point"}
}