{
  "type": "Feature",
  "properties": {
    "gn:admin1_code":"35.0",
    "gn:admin2_code":"427.0",
    "gn:asciiname":"Torka",
    "gn:country_code":"IN",
    "gn:dem":431,
    "gn:feature_class":"P",
    "gn:feature_code":"PPL",
    "gn:name":"Torka",
    "gn:population":0,
    "gn:timezone":"Asia/Kolkata",
    "iso:country":"IN",
    "name:bos_x_preferred":[
        "Torka"
    ],
    "name:hrv_x_preferred":[
        "Torka"
    ],
    "name:nld_x_preferred":[
        "Torka"
    ],
    "name:pol_x_preferred":[
        "Torka"
    ],
    "name:ron_x_preferred":[
        "Torka"
    ],
    "name:slv_x_preferred":[
        "Torka"
    ],
    "name:ukr_x_preferred":[
        "\u0422\u043e\u0440\u043a\u0430"
    ],
    "wof:name":"Torka",
    "wof:placetype":"locality"
},
  "geometry": {"coordinates":[78.89586,23.2452],"type":"Point"}
}