{
  "type": "Feature",
  "properties": {
    "gn:country":"IN",
    "gn:fcode":"PPL",
    "gn:pop":17446,
    "iso:country":"IN",
    "name:ben_x_preferred":[
        "\u0995\u09be\u09b2\u09be\u0999\u09cd\u0997\u09c1\u09a4"
    ],
    "name:bpy_x_preferred":[
        "\u0995\u09be\u09b2\u09be\u0999\u09cd\u0997\u09c1\u09a4"
    ],
    "name:eng_x_preferred":[
        "Calangute"
    ],
    "name:fra_x_preferred":[
        "Calangute"
    ],
    "name:ind_x_preferred":[
        "Calangute"
    ],
    "name:ita_x_preferred":[
        "Calangute"
    ],
    "name:mlg_x_preferred":[
        "Calangute"
    ],
    "name:msa_x_preferred":[
        "Calangute"
    ],
    "name:nan_x_preferred":[
        "Calangute"
    ],
    "name:new_x_preferred":[
        "\u0915\u0932\u0902\u0917\u0941\u091f\u0947"
    ],
    "name:nld_x_preferred":[
        "Calangute"
    ],
    "name:por_x_preferred":[
        "Calangute"
    ],
    "name:rus_x_preferred":[
        "\u041a\u0430\u043b\u0430\u043d\u0433\u0443\u0442"
    ],
    "name:swe_x_preferred":[
        "Calangute"
    ],
    "name:tam_x_preferred":[
        "\u0b95\u0bb2\u0b99\u0bcd\u0b95\u0bc1\u0b9f\u0bcd"
    ],
    "name:vie_x_preferred":[
        "Calangute"
    ],
    "name:zho_x_preferred":[
        "\u6070\u6717\u683c\u4e4c\u6cf0"
    ],
    "qs:name":"Calangute",
    "qs:name_adm0":"India",
    "qs:name_adm1":"Goa",
    "qs:photos":1635,
    "qs:photos_1k":331,
    "qs:photos_9k":21,
    "qs:photos_9r":13,
    "qs:photos_all":4665,
    "qs:photos_sr":13,
    "qs:placetype":"Town",
    "qs:pop_sr":"6",
    "wd:wordcount":242,
    "wof:name":"Calangute",
    "wof:placetype":"locality",
    "wof:population":17446
},
  "geometry": {"coordinates":[73.75530000000001,15.5439],"type":"Point"}
}