{
  "type": "Feature",
  "properties": {
    "iso:country":"IN",
    "ks:ks_name":"Jhakra",
    "ks:ks_pop":11,
    "ks:ks_type":"VILLAGE",
    "ks:ks_uagg_main":0,
    "name:eng_x_preferred":[
        "Jhakra"
    ],
    "wof:name":"Jhakra",
    "wof:placetype":"neighbourhood",
    "wof:population":11
},
  "geometry": {"coordinates":[85.172921,24.321937],"type":"Point"}
}