{
  "type": "Feature",
  "properties": {
    "iso:country":"IN",
    "ks:ks_name":"Puduvettu",
    "ks:ks_pop":305,
    "ks:ks_type":"VILLAGE",
    "name:eng_x_preferred":[
        "Puduvettu"
    ],
    "wof:name":"Puduvettu",
    "wof:placetype":"locality",
    "wof:population":305
},
  "geometry": {"coordinates":[75.407447,12.946134],"type":"Point"}
}