{
  "type": "Feature",
  "properties": {
    "gn:admin1_code":"23.0",
    "gn:admin2_code":"50.0",
    "gn:asciiname":"Kalia",
    "gn:country_code":"IN",
    "gn:dem":208,
    "gn:feature_class":"P",
    "gn:feature_code":"PPL",
    "gn:name":"K\u0101lia",
    "gn:population":0,
    "gn:timezone":"Asia/Kolkata",
    "iso:country":"IN",
    "ks:ks_name":"Kalia",
    "ks:ks_pop":909,
    "ks:ks_type":"VILLAGE",
    "ks:ks_uagg_main":0,
    "name:ceb_x_preferred":[
        "Kalia"
    ],
    "name:eng_x_preferred":[
        "Kalia"
    ],
    "name:fra_x_preferred":[
        "Kalia"
    ],
    "name:ind_x_preferred":[
        "Kalia"
    ],
    "name:nld_x_preferred":[
        "Kalia"
    ],
    "name:swe_x_preferred":[
        "Kalia"
    ],
    "wof:name":"Kalia",
    "wof:placetype":"neighbourhood",
    "wof:population":909
},
  "geometry": {"coordinates":[74.54316,31.222817],"type":"Point"}
}