{
  "type": "Feature",
  "properties": {
    "gn:admin1_code":"36",
    "gn:admin2_code":"200.0",
    "gn:asciiname":"Khajuri Khurd",
    "gn:country_code":"IN",
    "gn:dem":311,
    "gn:feature_class":"P",
    "gn:feature_code":"PPL",
    "gn:name":"Khajuri Khurd",
    "gn:population":0,
    "gn:timezone":"Asia/Kolkata",
    "iso:country":"IN",
    "ks:ks_name":"Khajurikhurd",
    "ks:ks_pop":219,
    "ks:ks_type":"VILLAGE",
    "name:eng_x_preferred":[
        "Khajurikhurd"
    ],
    "name:eng_x_variant":[
        "Khajuri Khurd"
    ],
    "wof:name":"Khajurikhurd",
    "wof:placetype":"locality",
    "wof:population":219
},
  "geometry": {"coordinates":[82.94958699999999,24.718383],"type":"Point"}
}