{
  "type": "Feature",
  "properties": {
    "iso:country":"IN",
    "ks:ks_name":"Boi",
    "ks:ks_pop":673,
    "ks:ks_type":"VILLAGE",
    "name:eng_x_preferred":[
        "Boi"
    ],
    "wof:name":"Boi",
    "wof:placetype":"locality",
    "wof:population":673
},
  "geometry": {"coordinates":[70.29513900000001,26.086289],"type":"Point"}
}