{
  "type": "Feature",
  "properties": {
    "iso:country":"IN",
    "ks:ks_name":"Dattatreyapeeta",
    "ks:ks_pop":16,
    "ks:ks_type":"HABITATION",
    "name:eng_x_preferred":[
        "Dattatreyapeeta"
    ],
    "wof:name":"Dattatreyapeeta",
    "wof:placetype":"locality",
    "wof:population":16
},
  "geometry": {"coordinates":[75.765928,13.438132],"type":"Point"}
}