{
  "type": "Feature",
  "properties": {
    "iso:country":"IN",
    "ks:ks_name":"Muhrai Madiyadoh",
    "ks:ks_pop":690,
    "ks:ks_type":"VILLAGE",
    "ks:ks_uagg_main":0,
    "name:eng_x_preferred":[
        "Muhrai Madiyadoh"
    ],
    "wof:name":"Muhrai Madiyadoh",
    "wof:placetype":"neighbourhood",
    "wof:population":690
},
  "geometry": {"coordinates":[79.700078,24.257741],"type":"Point"}
}