{
  "type": "Feature",
  "properties": {
    "iso:country":"IN",
    "ks:ks_name":"Marropaharia",
    "ks:ks_pop":109,
    "ks:ks_type":"VILLAGE",
    "name:eng_x_preferred":[
        "Marropaharia"
    ],
    "wof:name":"Marropaharia",
    "wof:placetype":"locality",
    "wof:population":109
},
  "geometry": {"coordinates":[87.537038,24.588527],"type":"Point"}
}