{
  "type": "Feature",
  "properties": {
    "iso:country":"IN",
    "ks:ks_name":"Boomanaickenpatty",
    "ks:ks_pop":204,
    "ks:ks_type":"HABITATION",
    "name:eng_x_preferred":[
        "Boomanaickenpatty"
    ],
    "wof:name":"Boomanaickenpatty",
    "wof:placetype":"locality",
    "wof:population":204
},
  "geometry": {"coordinates":[77.122569,10.608935],"type":"Point"}
}