{
  "type": "Feature",
  "properties": {
    "iso:country":"IN",
    "ks:ks_name":"Goudkenduguda",
    "ks:ks_pop":53,
    "ks:ks_type":"VILLAGE",
    "name:eng_x_preferred":[
        "Goudkenduguda"
    ],
    "wof:name":"Goudkenduguda",
    "wof:placetype":"locality",
    "wof:population":53
},
  "geometry": {"coordinates":[82.916978,19.596345],"type":"Point"}
}