{
  "type": "Feature",
  "properties": {
    "iso:country":"IN",
    "ks:ks_name":"Vazhmala",
    "ks:ks_pop":980,
    "ks:ks_type":"HABITATION",
    "name:eng_x_preferred":[
        "Vazhmala"
    ],
    "wof:name":"Vazhmala",
    "wof:placetype":"locality",
    "wof:population":980
},
  "geometry": {"coordinates":[75.679829,11.797326],"type":"Point"}
}