{
  "type": "Feature",
  "properties": {
    "iso:country":"IN",
    "ks:ks_name":"Thukaram Thanda",
    "ks:ks_pop":101,
    "ks:ks_type":"HABITATION",
    "name:eng_x_preferred":[
        "Thukaram Thanda"
    ],
    "wof:name":"Thukaram Thanda",
    "wof:placetype":"locality",
    "wof:population":101
},
  "geometry": {"coordinates":[77.631399,18.12772],"type":"Point"}
}