{
  "type": "Feature",
  "properties": {
    "iso:country":"IN",
    "ks:ks_alt_nam":"TALEWASTI",
    "ks:ks_name":"Talewasti",
    "ks:ks_pop":131,
    "ks:ks_type":"HABITATION",
    "name:eng_x_preferred":[
        "Talewasti"
    ],
    "wof:name":"Talewasti",
    "wof:placetype":"locality",
    "wof:population":131
},
  "geometry": {"coordinates":[74.88639499999999,17.267045],"type":"Point"}
}