{
  "type": "Feature",
  "properties": {
    "gn:admin1_code":"37",
    "gn:admin2_code":"407.0",
    "gn:asciiname":"Bakela",
    "gn:country_code":"IN",
    "gn:dem":398,
    "gn:feature_class":"P",
    "gn:feature_code":"PPL",
    "gn:name":"Bakela",
    "gn:population":0,
    "gn:timezone":"Asia/Kolkata",
    "iso:country":"IN",
    "ks:ks_alt_nam":"BAKELA",
    "ks:ks_name":"Bakela",
    "ks:ks_pop":181,
    "ks:ks_type":"HABITATION",
    "name:eng_x_preferred":[
        "Bakela"
    ],
    "wof:name":"Bakela",
    "wof:placetype":"locality",
    "wof:population":181
},
  "geometry": {"coordinates":[81.308285,22.300382],"type":"Point"}
}