{
  "type": "Feature",
  "properties": {
    "iso:country":"IN",
    "ks:ks_alt_nam":"KRISHNA SARDAR PARA",
    "ks:ks_name":"Krishna Sardar Para",
    "ks:ks_pop":84,
    "ks:ks_type":"HABITATION",
    "name:eng_x_preferred":[
        "Krishna Sardar Para"
    ],
    "wof:name":"Krishna Sardar Para",
    "wof:placetype":"locality",
    "wof:population":84
},
  "geometry": {"coordinates":[91.682283,23.830821],"type":"Point"}
}