{
  "type": "Feature",
  "properties": {
    "iso:country":"IN",
    "ks:ks_name":"Panchikeri",
    "ks:ks_pop":28,
    "ks:ks_type":"HABITATION",
    "name:eng_x_preferred":[
        "Panchikeri"
    ],
    "wof:name":"Panchikeri",
    "wof:placetype":"locality",
    "wof:population":28
},
  "geometry": {"coordinates":[74.63387899999999,14.766351],"type":"Point"}
}