{
  "type": "Feature",
  "properties": {
    "iso:country":"IN",
    "ks:ks_name":"Hagalakata",
    "ks:ks_pop":798,
    "ks:ks_type":"HABITATION",
    "ks:ks_uagg_main":0,
    "name:eng_x_preferred":[
        "Hagalakata"
    ],
    "wof:name":"Hagalakata",
    "wof:placetype":"neighbourhood",
    "wof:population":798
},
  "geometry": {"coordinates":[93.177717,26.074915],"type":"Point"}
}