{
  "type": "Feature",
  "properties": {
    "gn:admin1_code":"16.0",
    "gn:admin2_code":"505.0",
    "gn:asciiname":"Sumthana",
    "gn:country_code":"IN",
    "gn:dem":291,
    "gn:feature_class":"P",
    "gn:feature_code":"PPL",
    "gn:name":"Sumth\u0101na",
    "gn:population":0,
    "gn:timezone":"Asia/Kolkata",
    "iso:country":"IN",
    "wof:name":"Sumthana",
    "wof:placetype":"locality"
},
  "geometry": {"coordinates":[78.99789,21.04763],"type":"Point"}
}