{
  "type": "Feature",
  "properties": {
    "iso:country":"IN",
    "ks:ks_alt_nam":"manikoth",
    "ks:ks_name":"Manikoth",
    "ks:ks_pop":413,
    "ks:ks_type":"HABITATION",
    "ks:ks_uagg_main":0,
    "name:eng_x_preferred":[
        "Manikoth"
    ],
    "wof:name":"Manikoth",
    "wof:placetype":"neighbourhood",
    "wof:population":413
},
  "geometry": {"coordinates":[75.718154,11.564601],"type":"Point"}
}