{
  "type": "Feature",
  "properties": {
    "gn:admin1_code":"35.0",
    "gn:admin2_code":"420",
    "gn:asciiname":"Sanawai",
    "gn:country_code":"IN",
    "gn:dem":145,
    "gn:feature_class":"P",
    "gn:feature_code":"PPL",
    "gn:name":"San\u0101w\u0101i",
    "gn:population":0,
    "gn:timezone":"Asia/Kolkata",
    "iso:country":"IN",
    "name:und_x_variant":[
        "San\u0101w\u0101i",
        "San\u0101wai"
    ],
    "wof:name":"Sanawai",
    "wof:placetype":"locality"
},
  "geometry": {"coordinates":[79.11175,26.44087],"type":"Point"}
}