{
  "type": "Feature",
  "properties": {
    "gn:admin1_code":"36.0",
    "gn:admin2_code":"190.0",
    "gn:asciiname":"Birni",
    "gn:country_code":"IN",
    "gn:dem":70,
    "gn:feature_class":"P",
    "gn:feature_code":"PPL",
    "gn:name":"Birni",
    "gn:population":0,
    "gn:timezone":"Asia/Kolkata",
    "iso:country":"IN",
    "name:ceb_x_preferred":[
        "Birni"
    ],
    "name:ita_x_preferred":[
        "Birni"
    ],
    "name:msa_x_preferred":[
        "Birni"
    ],
    "name:swe_x_preferred":[
        "Birni"
    ],
    "wof:name":"Birni",
    "wof:placetype":"locality"
},
  "geometry": {"coordinates":[83.93138,26.15417],"type":"Point"}
}