{
  "type": "Feature",
  "properties": {
    "gn:admin1_code":"12.0",
    "gn:admin2_code":"005",
    "gn:asciiname":"Arai",
    "gn:country_code":"IN",
    "gn:dem":1761,
    "gn:feature_class":"P",
    "gn:feature_code":"PPL",
    "gn:name":"Ar\u0101i",
    "gn:population":0,
    "gn:timezone":"Asia/Kolkata",
    "iso:country":"IN",
    "name:deu_x_preferred":[
        "Arai"
    ],
    "name:fra_x_preferred":[
        "Arai"
    ],
    "name:ita_x_preferred":[
        "Arai"
    ],
    "name:kor_x_preferred":[
        "\uc544\ub77c\uc774"
    ],
    "name:mlg_x_preferred":[
        "Arai"
    ],
    "name:rus_x_preferred":[
        "\u0410\u0440\u0430\u0438"
    ],
    "name:spa_x_preferred":[
        "Arai"
    ],
    "name:swe_x_preferred":[
        "Arai"
    ],
    "name:ukr_x_preferred":[
        "\u0410\u0440\u0430\u0457"
    ],
    "wof:name":"Arai",
    "wof:placetype":"locality"
},
  "geometry": {"coordinates":[74.27656,33.79020999999999],"type":"Point"}
}