{
  "type": "Feature",
  "properties": {
    "iso:country":"IN",
    "ks:ks_name":"Nagla Samawadi",
    "ks:ks_pop":1652,
    "ks:ks_type":"VILLAGE",
    "ks:ks_uagg_main":0,
    "name:eng_x_preferred":[
        "Nagla Samawadi"
    ],
    "wof:name":"Nagla Samawadi",
    "wof:placetype":"neighbourhood",
    "wof:population":1652
},
  "geometry": {"coordinates":[76.625778,27.612864],"type":"Point"}
}