{
  "type": "Feature",
  "properties": {
    "gn:admin1_code":"30",
    "gn:asciiname":"Likhapani",
    "gn:country_code":"IN",
    "gn:dem":147,
    "gn:feature_class":"P",
    "gn:feature_code":"PPL",
    "gn:name":"Likhap\u0101ni",
    "gn:population":0,
    "gn:timezone":"Asia/Kolkata",
    "iso:country":"IN",
    "name:mar_x_preferred":[
        "\u0932\u0947\u0916\u093e\u092a\u093e\u0928\u0940"
    ],
    "name:und_x_variant":[
        "Lekhapani",
        "Likhap\u0101ni"
    ],
    "wof:name":"Likhapani",
    "wof:placetype":"locality"
},
  "geometry": {"coordinates":[95.81699999999999,27.32381],"type":"Point"}
}