{
  "type": "Feature",
  "properties": {
    "iso:country":"IN",
    "ks:ks_alt_nam":"Gaja urf Kaleth",
    "ks:ks_name":"Gaja Urf Kaleth",
    "ks:ks_pop":57,
    "ks:ks_type":"HABITATION",
    "name:eng_x_preferred":[
        "Gaja Urf Kaleth"
    ],
    "wof:name":"Gaja Urf Kaleth",
    "wof:placetype":"locality",
    "wof:population":57
},
  "geometry": {"coordinates":[78.71005,29.764569],"type":"Point"}
}