{
  "type": "Feature",
  "properties": {
    "gn:admin1_code":"40.0",
    "gn:admin2_code":"532.0",
    "gn:asciiname":"Rompalli",
    "gn:country_code":"IN",
    "gn:dem":366,
    "gn:feature_class":"P",
    "gn:feature_code":"PPL",
    "gn:name":"Rompalli",
    "gn:population":0,
    "gn:timezone":"Asia/Kolkata",
    "iso:country":"IN",
    "ks:ks_name":"Rompalli",
    "ks:ks_pop":199,
    "ks:ks_type":"VILLAGE",
    "name:eng_x_preferred":[
        "Rompalli"
    ],
    "wof:name":"Rompalli",
    "wof:placetype":"locality",
    "wof:population":199
},
  "geometry": {"coordinates":[79.243134,19.099873],"type":"Point"}
}