{
  "type": "Feature",
  "properties": {
    "gn:admin1_code":"19",
    "gn:admin2_code":"558.0",
    "gn:asciiname":"Mangalgi",
    "gn:country_code":"IN",
    "gn:dem":603,
    "gn:feature_class":"P",
    "gn:feature_code":"PPL",
    "gn:name":"Mangalgi",
    "gn:population":0,
    "gn:timezone":"Asia/Kolkata",
    "iso:country":"IN",
    "name:und_x_variant":[
        "Mangalgee",
        "Mangalgi"
    ],
    "wof:name":"Mangalgi",
    "wof:placetype":"locality"
},
  "geometry": {"coordinates":[77.30287,17.74991],"type":"Point"}
}