{
  "type": "Feature",
  "properties": {
    "iso:country":"IN",
    "ks:ks_name":"Khapanewadi",
    "ks:ks_pop":145,
    "ks:ks_type":"HABITATION",
    "name:eng_x_preferred":[
        "Khapanewadi"
    ],
    "wof:name":"Khapanewadi",
    "wof:placetype":"locality",
    "wof:population":145
},
  "geometry": {"coordinates":[73.71324799999999,16.741693],"type":"Point"}
}