{
  "type": "Feature",
  "properties": {
    "gn:admin1_code":"35",
    "gn:admin2_code":"446.0",
    "gn:asciiname":"Bankheri",
    "gn:country_code":"IN",
    "gn:dem":460,
    "gn:feature_class":"P",
    "gn:feature_code":"PPL",
    "gn:name":"Bankheri",
    "gn:population":0,
    "gn:timezone":"Asia/Kolkata",
    "iso:country":"IN",
    "ks:ks_name":"Bankhedi",
    "ks:ks_pop":992,
    "ks:ks_type":"VILLAGE",
    "name:eng_x_preferred":[
        "Bankhedi"
    ],
    "name:eng_x_variant":[
        "Bankheri"
    ],
    "wof:name":"Bankhedi",
    "wof:placetype":"locality",
    "wof:population":992
},
  "geometry": {"coordinates":[77.89280599999999,23.320911],"type":"Point"}
}