{
  "type": "Feature",
  "properties": {
    "gn:admin1_code":"36",
    "gn:admin2_code":"199.0",
    "gn:asciiname":"Kohad Nunber Two",
    "gn:country_code":"IN",
    "gn:dem":166,
    "gn:feature_class":"P",
    "gn:feature_code":"PPL",
    "gn:name":"Kohad Nunber Two",
    "gn:population":0,
    "gn:timezone":"Asia/Kolkata",
    "iso:country":"IN",
    "wof:name":"Kohad Nunber Two",
    "wof:placetype":"neighbourhood"
},
  "geometry": {"coordinates":[82.36913,24.93934],"type":"Point"}
}