{
  "type": "Feature",
  "properties": {
    "iso:country":"IN",
    "ks:ks_name":"Bagtan Nagar",
    "ks:ks_pop":700,
    "ks:ks_type":"HABITATION",
    "name:eng_x_preferred":[
        "Bagtan Nagar"
    ],
    "wof:name":"Bagtan Nagar",
    "wof:placetype":"locality",
    "wof:population":700
},
  "geometry": {"coordinates":[72.543487,26.690765],"type":"Point"}
}