{
  "type": "Feature",
  "properties": {
    "iso:country":"IN",
    "ks:ks_alt_nam":"GULA SAI",
    "ks:ks_name":"Gula Sai",
    "ks:ks_pop":93,
    "ks:ks_type":"HABITATION",
    "name:eng_x_preferred":[
        "Gula Sai"
    ],
    "wof:name":"Gula Sai",
    "wof:placetype":"locality",
    "wof:population":93
},
  "geometry": {"coordinates":[85.48348,22.237058],"type":"Point"}
}