{
  "type": "Feature",
  "properties": {
    "gn:admin1_code":"9.0",
    "gn:admin2_code":"474",
    "gn:asciiname":"Detroj",
    "gn:country_code":"IN",
    "gn:dem":58,
    "gn:feature_class":"P",
    "gn:feature_code":"PPL",
    "gn:name":"Detroj",
    "gn:population":0,
    "gn:timezone":"Asia/Kolkata",
    "iso:country":"IN",
    "name:guj_x_preferred":[
        "\u0aa6\u0ac7\u0aa4\u0acd\u0ab0\u0acb\u0a9c"
    ],
    "wof:name":"Detroj",
    "wof:placetype":"locality"
},
  "geometry": {"coordinates":[72.18885,23.33326],"type":"Point"}
}