{
  "type": "Feature",
  "properties": {
    "iso:country":"IN",
    "ks:ks_name":"Bagayatwadi",
    "ks:ks_pop":283,
    "ks:ks_type":"HABITATION",
    "name:eng_x_preferred":[
        "Bagayatwadi"
    ],
    "wof:name":"Bagayatwadi",
    "wof:placetype":"locality",
    "wof:population":283
},
  "geometry": {"coordinates":[73.70959999999999,15.798148],"type":"Point"}
}