{
  "type": "Feature",
  "properties": {
    "iso:country":"IN",
    "ks:ks_name":"Bansduma",
    "ks:ks_pop":113,
    "ks:ks_type":"VILLAGE",
    "name:eng_x_preferred":[
        "Bansduma"
    ],
    "wof:name":"Bansduma",
    "wof:placetype":"locality",
    "wof:population":113
},
  "geometry": {"coordinates":[87.306417,24.493758],"type":"Point"}
}