{
  "type": "Feature",
  "properties": {
    "iso:country":"IN",
    "ks:ks_name":"Dharam Purwa",
    "ks:ks_pop":740,
    "ks:ks_type":"HABITATION",
    "name:eng_x_preferred":[
        "Dharam Purwa"
    ],
    "wof:name":"Dharam Purwa",
    "wof:placetype":"locality",
    "wof:population":740
},
  "geometry": {"coordinates":[83.123878,27.150203],"type":"Point"}
}