{
  "type": "Feature",
  "properties": {
    "gn:admin1_code":"19.0",
    "gn:admin2_code":"570.0",
    "gn:asciiname":"Bonnabilalu",
    "gn:country_code":"IN",
    "gn:dem":699,
    "gn:feature_class":"P",
    "gn:feature_code":"PPL",
    "gn:name":"Bonn\u0101bil\u0101lu",
    "gn:population":0,
    "gn:timezone":"Asia/Kolkata",
    "iso:country":"IN",
    "wof:name":"Bonnabilalu",
    "wof:placetype":"locality"
},
  "geometry": {"coordinates":[75.34159,13.56814],"type":"Point"}
}