{
  "type": "Feature",
  "properties": {
    "iso:country":"IN",
    "ks:ks_name":"Laharia",
    "ks:ks_pop":280,
    "ks:ks_type":"VILLAGE",
    "name:eng_x_preferred":[
        "Laharia"
    ],
    "wof:name":"Laharia",
    "wof:placetype":"locality",
    "wof:population":280
},
  "geometry": {"coordinates":[85.99305099999999,24.503538],"type":"Point"}
}