{
  "type": "Feature",
  "properties": {
    "gn:admin1_code":"35",
    "gn:admin2_code":"451.0",
    "gn:asciiname":"Baghori",
    "gn:country_code":"IN",
    "gn:dem":380,
    "gn:feature_class":"P",
    "gn:feature_code":"PPL",
    "gn:name":"Baghori",
    "gn:population":0,
    "gn:timezone":"Asia/Kolkata",
    "iso:country":"IN",
    "ks:ks_name":"Baghodi",
    "ks:ks_pop":1100,
    "ks:ks_type":"VILLAGE",
    "name:eng_x_preferred":[
        "Baghodi"
    ],
    "name:eng_x_variant":[
        "Baghori"
    ],
    "wof:name":"Baghodi",
    "wof:placetype":"locality",
    "wof:population":1100
},
  "geometry": {"coordinates":[79.866094,23.292159],"type":"Point"}
}