{
  "type": "Feature",
  "properties": {
    "gn:admin1_code":"36",
    "gn:admin2_code":"184.0",
    "gn:asciiname":"Rampurwa",
    "gn:country_code":"IN",
    "gn:dem":89,
    "gn:feature_class":"P",
    "gn:feature_code":"PPL",
    "gn:name":"Rampurwa",
    "gn:population":0,
    "gn:timezone":"Asia/Kolkata",
    "iso:country":"IN",
    "wof:name":"Rampurwa",
    "wof:placetype":"locality"
},
  "geometry": {"coordinates":[83.03586,27.22207],"type":"Point"}
}