{
  "type": "Feature",
  "properties": {
    "gn:admin1_code":"12.0",
    "gn:admin2_code":"010",
    "gn:asciiname":"Chak-i-Watalbagh",
    "gn:country_code":"IN",
    "gn:dem":1614,
    "gn:feature_class":"P",
    "gn:feature_code":"PPL",
    "gn:name":"Chak-i-W\u0101talb\u0101gh",
    "gn:population":0,
    "gn:timezone":"Asia/Kolkata",
    "iso:country":"IN",
    "wof:name":"Chak-i-Watalbagh",
    "wof:placetype":"locality"
},
  "geometry": {"coordinates":[74.7653,34.25169],"type":"Point"}
}