{
  "type": "Feature",
  "properties": {
    "gn:admin1_code":"34.0",
    "gn:admin2_code":"228.0",
    "gn:asciiname":"Maldah",
    "gn:country_code":"IN",
    "gn:dem":58,
    "gn:feature_class":"P",
    "gn:feature_code":"PPL",
    "gn:name":"M\u0101ldah",
    "gn:population":0,
    "gn:timezone":"Asia/Kolkata",
    "iso:country":"IN",
    "wof:name":"Maldah",
    "wof:placetype":"locality"
},
  "geometry": {"coordinates":[85.75990999999998,25.17399],"type":"Point"}
}