{
  "type": "Feature",
  "properties": {
    "iso:country":"IN",
    "ks:ks_name":"Kakkencheri",
    "ks:ks_pop":1240,
    "ks:ks_type":"HABITATION",
    "name:eng_x_preferred":[
        "Kakkencheri"
    ],
    "wof:name":"Kakkencheri",
    "wof:placetype":"locality",
    "wof:population":1240
},
  "geometry": {"coordinates":[75.959936,11.714287],"type":"Point"}
}