{
  "type": "Feature",
  "properties": {
    "gn:admin1_code":"35",
    "gn:admin2_code":"449.0",
    "gn:asciiname":"Khamda",
    "gn:country_code":"IN",
    "gn:dem":366,
    "gn:feature_class":"P",
    "gn:feature_code":"PPL",
    "gn:name":"Kh\u0101mda",
    "gn:population":0,
    "gn:timezone":"Asia/Kolkata",
    "iso:country":"IN",
    "ks:ks_name":"Khamda",
    "ks:ks_pop":302,
    "ks:ks_type":"HABITATION",
    "name:eng_x_preferred":[
        "Khamda"
    ],
    "wof:name":"Khamda",
    "wof:placetype":"locality",
    "wof:population":302
},
  "geometry": {"coordinates":[77.93372100000001,22.40854],"type":"Point"}
}