{
  "type": "Feature",
  "properties": {
    "gn:admin1_code":"36",
    "gn:admin2_code":"188.0",
    "gn:asciiname":"Bahadurabad",
    "gn:country_code":"IN",
    "gn:dem":80,
    "gn:feature_class":"P",
    "gn:feature_code":"PPL",
    "gn:name":"Bah\u0101dur\u0101b\u0101d",
    "gn:population":0,
    "gn:timezone":"Asia/Kolkata",
    "iso:country":"IN",
    "name:urd_x_preferred":[
        "\u0628\u06c1\u0627\u062f\u0631 \u0622\u0628\u0627\u062f"
    ],
    "wof:name":"Bahadurabad",
    "wof:placetype":"locality"
},
  "geometry": {"coordinates":[83.42485000000001,26.29944],"type":"Point"}
}