{
  "type": "Feature",
  "properties": {
    "iso:country":"IN",
    "ks:ks_name":"Koiridih",
    "ks:ks_pop":111,
    "ks:ks_type":"VILLAGE",
    "ks:ks_uagg_main":0,
    "name:eng_x_preferred":[
        "Koiridih"
    ],
    "wof:name":"Koiridih",
    "wof:placetype":"neighbourhood",
    "wof:population":111
},
  "geometry": {"coordinates":[86.514437,24.091573],"type":"Point"}
}