{
  "type": "Feature",
  "properties": {
    "iso:country":"IN",
    "ks:ks_name":"Hasanpur",
    "ks:ks_pop":441,
    "ks:ks_type":"VILLAGE",
    "name:eng_x_preferred":[
        "Hasanpur"
    ],
    "wof:name":"Hasanpur",
    "wof:placetype":"locality",
    "wof:population":441
},
  "geometry": {"coordinates":[87.019763,21.500069],"type":"Point"}
}