{
  "type": "Feature",
  "properties": {
    "iso:country":"IN",
    "ks:ks_name":"Bhumihar Tola",
    "ks:ks_pop":93,
    "ks:ks_type":"HABITATION",
    "name:eng_x_preferred":[
        "Bhumihar Tola"
    ],
    "wof:name":"Bhumihar Tola",
    "wof:placetype":"locality",
    "wof:population":93
},
  "geometry": {"coordinates":[85.950807,25.603909],"type":"Point"}
}