{
  "type": "Feature",
  "properties": {
    "iso:country":"IN",
    "ks:ks_name":"Temgirewasti",
    "ks:ks_pop":239,
    "ks:ks_type":"HABITATION",
    "name:eng_x_preferred":[
        "Temgirewasti"
    ],
    "wof:name":"Temgirewasti",
    "wof:placetype":"locality",
    "wof:population":239
},
  "geometry": {"coordinates":[74.40677700000001,18.822956],"type":"Point"}
}