{
  "type": "Feature",
  "properties": {
    "iso:country":"IN",
    "ks:ks_name":"Kuldiha",
    "ks:ks_pop":453,
    "ks:ks_type":"VILLAGE",
    "name:eng_x_preferred":[
        "Kuldiha"
    ],
    "wof:name":"Kuldiha",
    "wof:placetype":"locality",
    "wof:population":453
},
  "geometry": {"coordinates":[86.426907,24.071457],"type":"Point"}
}