{
  "type": "Feature",
  "properties": {
    "iso:country":"IN",
    "ks:ks_name":"Birnathpur",
    "ks:ks_pop":1151,
    "ks:ks_type":"VILLAGE",
    "name:eng_x_preferred":[
        "Birnathpur"
    ],
    "wof:name":"Birnathpur",
    "wof:placetype":"locality",
    "wof:population":1151
},
  "geometry": {"coordinates":[87.833923,24.814518],"type":"Point"}
}