{
  "type": "Feature",
  "properties": {
    "gn:admin1_code":"39.0",
    "gn:admin2_code":"59.0",
    "gn:asciiname":"Maid",
    "gn:country_code":"IN",
    "gn:dem":1533,
    "gn:feature_class":"P",
    "gn:feature_code":"PPL",
    "gn:name":"Maid",
    "gn:population":0,
    "gn:timezone":"Asia/Kolkata",
    "iso:country":"IN",
    "name:ara_x_preferred":[
        "\u062e\u0627\u062f\u0645\u0629 \u0627\u0644\u0645\u0646\u0632\u0644"
    ],
    "name:bod_x_preferred":[
        "\u0f42\u0f61\u0f7c\u0f42\u0f0b\u0f58\u0f7c\u0f0d"
    ],
    "name:bre_x_preferred":[
        "Matezh"
    ],
    "name:ces_x_preferred":[
        "Pokojsk\u00e1"
    ],
    "name:dan_x_preferred":[
        "Husassistent"
    ],
    "name:deu_x_preferred":[
        "Magd"
    ],
    "name:eus_x_preferred":[
        "Neskame"
    ],
    "name:fas_x_preferred":[
        "\u06a9\u0644\u0641\u062a"
    ],
    "name:isl_x_preferred":[
        "Vinnukona"
    ],
    "name:jpn_x_preferred":[
        "\u30e1\u30a4\u30c9"
    ],
    "name:kaz_x_preferred":[
        "\u041d\u04e9\u043c\u0456\u0440\u0434\u0456 \u0442\u0430\u0437\u0430\u043b\u0430\u0443\u0448\u044b"
    ],
    "name:nld_x_preferred":[
        "Bediende"
    ],
    "name:nno_x_preferred":[
        "Hushjelp"
    ],
    "name:nor_x_preferred":[
        "Hushjelp"
    ],
    "name:pol_x_preferred":[
        "Pokoj\u00f3wka"
    ],
    "name:rus_x_preferred":[
        "\u0413\u043e\u0440\u043d\u0438\u0447\u043d\u0430\u044f"
    ],
    "name:scn_x_preferred":[
        "Criata"
    ],
    "name:slv_x_preferred":[
        "Dekla"
    ],
    "name:spa_x_preferred":[
        "Sirvienta"
    ],
    "name:swe_x_preferred":[
        "Hembitr\u00e4de"
    ],
    "name:tur_x_preferred":[
        "Hizmet\u00e7i"
    ],
    "name:ukr_x_preferred":[
        "\u041f\u043e\u043a\u043e\u0457\u0432\u043a\u0430"
    ],
    "wof:name":"Maid",
    "wof:placetype":"locality"
},
  "geometry": {"coordinates":[78.19617,30.49669],"type":"Point"}
}