{
  "type": "Feature",
  "properties": {
    "gn:admin1_code":"39.0",
    "gn:admin2_code":"59.0",
    "gn:asciiname":"Maid",
    "gn:country_code":"IN",
    "gn:dem":1533,
    "gn:feature_class":"P",
    "gn:feature_code":"PPL",
    "gn:name":"Maid",
    "gn:population":0,
    "gn:timezone":"Asia/Kolkata",
    "iso:country":"IN",
    "wof:name":"Maid",
    "wof:placetype":"locality"
},
  "geometry": {"coordinates":[78.19617,30.49669],"type":"Point"}
}