{
  "type": "Feature",
  "properties": {
    "iso:country":"IN",
    "ks:ks_name":"Rangpur Pt V",
    "ks:ks_pop":1847,
    "ks:ks_type":"HABITATION",
    "name:eng_x_preferred":[
        "Rangpur Pt V"
    ],
    "wof:name":"Rangpur Pt V",
    "wof:placetype":"locality",
    "wof:population":1847
},
  "geometry": {"coordinates":[92.585032,24.531367],"type":"Point"}
}