{
  "type": "Feature",
  "properties": {
    "iso:country":"IN",
    "ks:ks_alt_nam":"Tangaon Pt III",
    "ks:ks_name":"Tangaon Pt Iii",
    "ks:ks_pop":1643,
    "ks:ks_type":"HABITATION",
    "name:eng_x_preferred":[
        "Tangaon Pt Iii"
    ],
    "wof:name":"Tangaon Pt Iii",
    "wof:placetype":"locality",
    "wof:population":1643
},
  "geometry": {"coordinates":[89.97247400000001,25.632878],"type":"Point"}
}