{
  "type": "Feature",
  "properties": {
    "gn:admin1_code":"35",
    "gn:admin2_code":"430.0",
    "gn:asciiname":"Chhivliq",
    "gn:country_code":"IN",
    "gn:dem":336,
    "gn:feature_class":"P",
    "gn:feature_code":"PPL",
    "gn:name":"Chhivliq",
    "gn:population":0,
    "gn:timezone":"Asia/Kolkata",
    "iso:country":"IN",
    "wof:name":"Chhivliq",
    "wof:placetype":"locality"
},
  "geometry": {"coordinates":[81.71405,24.84179],"type":"Point"}
}