{
  "type": "Feature",
  "properties": {
    "iso:country":"IN",
    "ks:ks_name":"Japhri",
    "ks:ks_pop":141,
    "ks:ks_type":"VILLAGE",
    "name:eng_x_preferred":[
        "Japhri"
    ],
    "wof:name":"Japhri",
    "wof:placetype":"locality",
    "wof:population":141
},
  "geometry": {"coordinates":[87.595147,24.708524],"type":"Point"}
}