{
  "type": "Feature",
  "properties": {
    "iso:country":"IN",
    "ks:ks_alt_nam":"DEVCHARAN PARA",
    "ks:ks_name":"Devcharan Para",
    "ks:ks_pop":184,
    "ks:ks_type":"HABITATION",
    "name:eng_x_preferred":[
        "Devcharan Para"
    ],
    "wof:name":"Devcharan Para",
    "wof:placetype":"locality",
    "wof:population":184
},
  "geometry": {"coordinates":[91.472723,23.864375],"type":"Point"}
}