{
  "type": "Feature",
  "properties": {
    "gn:admin1_code":"21.0",
    "gn:admin2_code":"398.0",
    "gn:asciiname":"Pasupukunta",
    "gn:country_code":"IN",
    "gn:dem":951,
    "gn:feature_class":"P",
    "gn:feature_code":"PPL",
    "gn:name":"Pasupukunta",
    "gn:population":0,
    "gn:timezone":"Asia/Kolkata",
    "iso:country":"IN",
    "wof:name":"Pasupukunta",
    "wof:placetype":"locality"
},
  "geometry": {"coordinates":[82.91305,18.52644],"type":"Point"}
}