{
  "type": "Feature",
  "properties": {
    "gn:country":"IN",
    "gn:fcode":"PPL",
    "gn:population":22120,
    "iso:country":"IN",
    "name:ben_x_preferred":[
        "\u0995\u09c8\u09b2\u09be\u09b8\u09b9\u09b0"
    ],
    "name:bpy_x_preferred":[
        "\u0995\u09c8\u09b2\u09be\u09b6\u09b9\u09b0"
    ],
    "name:ceb_x_preferred":[
        "Kail\u0101shahar"
    ],
    "name:deu_x_preferred":[
        "Kailashahar"
    ],
    "name:eng_x_preferred":[
        "Kailashahar"
    ],
    "name:fra_x_preferred":[
        "Kailashahar"
    ],
    "name:guj_x_preferred":[
        "\u0a95\u0ac8\u0ab2\u0abe\u0ab6\u0ab9\u0ab0"
    ],
    "name:hif_x_preferred":[
        "Kailasahar"
    ],
    "name:hin_x_preferred":[
        "\u0915\u0948\u0932\u093e\u0936\u0939\u0930"
    ],
    "name:ita_x_preferred":[
        "Kailashahar"
    ],
    "name:jpn_x_preferred":[
        "\u30ab\u30a4\u30e9\u30b7\u30e3\u30cf\u30fc\u30eb"
    ],
    "name:kan_x_preferred":[
        "\u0c95\u0cc8\u0cb2\u0cbe\u0cb6\u0cb9\u0cbe\u0cb0\u0ccd"
    ],
    "name:kor_x_preferred":[
        "\uce74\uc77c\ub77c\uc0e4\ud558\ub974"
    ],
    "name:mar_x_preferred":[
        "\u0915\u0948\u0932\u093e\u0938\u0939\u0930"
    ],
    "name:mlg_x_preferred":[
        "Kailashahar"
    ],
    "name:msa_x_preferred":[
        "Kailasahar"
    ],
    "name:nan_x_preferred":[
        "Kailasahar"
    ],
    "name:new_x_preferred":[
        "\u0915\u0948\u0932\u093e\u0938\u0939\u0930"
    ],
    "name:nld_x_preferred":[
        "Kailasahar"
    ],
    "name:ori_x_preferred":[
        "\u0b15\u0b3e\u0b07\u0b32\u0b3e\u0b38\u0b39\u0b30"
    ],
    "name:por_x_preferred":[
        "Kailashahar"
    ],
    "name:rus_x_preferred":[
        "\u041a\u0430\u0439\u043b\u0430\u0448\u0430\u0445\u0430\u0440"
    ],
    "name:san_x_preferred":[
        "\u0915\u0948\u0932\u093e\u0938\u0939\u0930\u094d"
    ],
    "name:spa_x_preferred":[
        "Kailashahar"
    ],
    "name:swe_x_preferred":[
        "Kail\u0101shahar"
    ],
    "name:tam_x_preferred":[
        "\u0b95\u0bc8\u0bb2\u0bbe\u0bb7\u0b95\u0bb0\u0bcd"
    ],
    "name:tel_x_preferred":[
        "\u0c15\u0c48\u0c32\u0c37\u0c39\u0c30\u0c4d"
    ],
    "name:urd_x_preferred":[
        "\u06a9\u0627\u0626\u0644\u0627\u0634\u06c1\u0631"
    ],
    "name:vie_x_preferred":[
        "Kailasahar"
    ],
    "name:zho_x_preferred":[
        "\u51ef\u62c9\u8428\u54c8\u5c14"
    ],
    "qs:name":"Kailasahar",
    "qs:name_adm0":"India",
    "qs:name_adm1":"Tripura",
    "qs:photos_9r":0,
    "qs:photos_sr":0,
    "qs:placetype":"Town",
    "qs:pop_sr":"7",
    "wd:wordcount":621,
    "wof:name":"Kailasahar",
    "wof:placetype":"locality",
    "wof:population":22120
},
  "geometry": {"coordinates":[92.00391,24.332],"type":"Point"}
}