{
  "type": "Feature",
  "properties": {
    "iso:country":"IN",
    "ks:ks_name":"Pachim Deeh",
    "ks:ks_pop":70,
    "ks:ks_type":"HABITATION",
    "name:eng_x_preferred":[
        "Pachim Deeh"
    ],
    "wof:name":"Pachim Deeh",
    "wof:placetype":"locality",
    "wof:population":70
},
  "geometry": {"coordinates":[82.943647,27.230567],"type":"Point"}
}