{
  "type": "Feature",
  "properties": {
    "iso:country":"IN",
    "ks:ks_name":"Ahiran Purwa 1",
    "ks:ks_pop":342,
    "ks:ks_type":"HABITATION",
    "name:eng_x_preferred":[
        "Ahiran Purwa 1"
    ],
    "wof:name":"Ahiran Purwa 1",
    "wof:placetype":"locality",
    "wof:population":342
},
  "geometry": {"coordinates":[80.61689800000001,25.252272],"type":"Point"}
}