{
  "type": "Feature",
  "properties": {
    "iso:country":"IN",
    "ks:ks_name":"Jhusha Purwa",
    "ks:ks_pop":99,
    "ks:ks_type":"HABITATION",
    "name:eng_x_preferred":[
        "Jhusha Purwa"
    ],
    "wof:name":"Jhusha Purwa",
    "wof:placetype":"locality",
    "wof:population":99
},
  "geometry": {"coordinates":[80.371469,25.44692],"type":"Point"}
}