{
  "type": "Feature",
  "properties": {
    "iso:country":"IN",
    "ks:ks_name":"Hazipur",
    "ks:ks_pop":2109,
    "ks:ks_type":"VILLAGE",
    "ks:ks_uagg_main":0,
    "name:eng_x_preferred":[
        "Hazipur"
    ],
    "wof:name":"Hazipur",
    "wof:placetype":"locality",
    "wof:population":2109
},
  "geometry": {"coordinates":[88.78043099999999,25.260204],"type":"Point"}
}