{
  "type": "Feature",
  "properties": {
    "iso:country":"IN",
    "ks:ks_alt_nam":"Baisi\u0101 Kh\u0101p",
    "ks:ks_name":"Baisia Khap",
    "ks:ks_pop":100,
    "ks:ks_type":"VILLAGE",
    "name:eng_x_preferred":[
        "Baisia Khap"
    ],
    "name:eng_x_variant":[
        "Baisi\u0101 Kh\u0101p"
    ],
    "wof:name":"Baisia Khap",
    "wof:placetype":"locality",
    "wof:population":100
},
  "geometry": {"coordinates":[84.329983,26.847959],"type":"Point"}
}