{
  "type": "Feature",
  "properties": {
    "iso:country":"IN",
    "ks:ks_name":"Sulugodu",
    "ks:ks_pop":72,
    "ks:ks_type":"HABITATION",
    "name:eng_x_preferred":[
        "Sulugodu"
    ],
    "wof:name":"Sulugodu",
    "wof:placetype":"locality",
    "wof:population":72
},
  "geometry": {"coordinates":[74.898867,13.927907],"type":"Point"}
}