{
  "type": "Feature",
  "properties": {
    "iso:country":"IN",
    "ks:ks_name":"Olaba",
    "ks:ks_pop":414,
    "ks:ks_type":"VILLAGE",
    "name:eng_x_preferred":[
        "Olaba"
    ],
    "wof:name":"Olaba",
    "wof:placetype":"locality",
    "wof:population":414
},
  "geometry": {"coordinates":[85.21791,20.50512],"type":"Point"}
}