{
  "type": "Feature",
  "properties": {
    "iso:country":"IN",
    "ks:ks_alt_nam":"RUPNAR WASTI",
    "ks:ks_name":"Rupnar Wasti",
    "ks:ks_pop":153,
    "ks:ks_type":"HABITATION",
    "name:eng_x_preferred":[
        "Rupnar Wasti"
    ],
    "wof:name":"Rupnar Wasti",
    "wof:placetype":"locality",
    "wof:population":153
},
  "geometry": {"coordinates":[75.034702,17.177129],"type":"Point"}
}