{
  "type": "Feature",
  "properties": {
    "gn:admin1_code":"28",
    "gn:admin2_code":"329.0",
    "gn:asciiname":"Mahishkuchi",
    "gn:country_code":"IN",
    "gn:dem":44,
    "gn:feature_class":"P",
    "gn:feature_code":"PPL",
    "gn:name":"Mahishkuchi",
    "gn:population":0,
    "gn:timezone":"Asia/Kolkata",
    "iso:country":"IN",
    "wof:name":"Mahishkuchi",
    "wof:placetype":"locality"
},
  "geometry": {"coordinates":[89.73572,26.39515],"type":"Point"}
}