{
  "type": "Feature",
  "properties": {
    "gn:admin1_code":"34.0",
    "gn:admin2_code":"237.0",
    "gn:asciiname":"Berri",
    "gn:country_code":"IN",
    "gn:dem":125,
    "gn:feature_class":"P",
    "gn:feature_code":"PPL",
    "gn:name":"Berri",
    "gn:population":0,
    "gn:timezone":"Asia/Kolkata",
    "iso:country":"IN",
    "name:ara_x_preferred":[
        "\u0628\u0631\u064a"
    ],
    "name:ben_x_preferred":[
        "\u09ac\u09c7\u09b0\u09bf"
    ],
    "name:ceb_x_preferred":[
        "Berri"
    ],
    "name:deu_x_preferred":[
        "Berri"
    ],
    "name:ell_x_preferred":[
        "\u039c\u03c0\u03ad\u03c1\u03b9"
    ],
    "name:fra_x_preferred":[
        "Berri"
    ],
    "name:hun_x_preferred":[
        "Berri"
    ],
    "name:ind_x_preferred":[
        "Berri"
    ],
    "name:ita_x_preferred":[
        "Berri"
    ],
    "name:kor_x_preferred":[
        "\ubca0\ub9ac"
    ],
    "name:por_x_preferred":[
        "Berri"
    ],
    "name:rus_x_preferred":[
        "\u0411\u0435\u0440\u0440\u0438"
    ],
    "name:swe_x_preferred":[
        "Berri"
    ],
    "name:tur_x_preferred":[
        "Berri"
    ],
    "name:ukr_x_preferred":[
        "\u0411\u0435\u0440\u0440\u0456"
    ],
    "name:vie_x_preferred":[
        "Berri"
    ],
    "name:zho_cn_x_preferred":[
        "\u8d1d\u91cc"
    ],
    "name:zho_tw_x_preferred":[
        "\u8c9d\u91cc"
    ],
    "wof:name":"Berri",
    "wof:placetype":"locality"
},
  "geometry": {"coordinates":[85.43933,24.72158],"type":"Point"}
}