{
  "type": "Feature",
  "properties": {
    "gn:admin1_code":"34.0",
    "gn:admin2_code":"237.0",
    "gn:asciiname":"Berri",
    "gn:country_code":"IN",
    "gn:dem":125,
    "gn:feature_class":"P",
    "gn:feature_code":"PPL",
    "gn:name":"Berri",
    "gn:population":0,
    "gn:timezone":"Asia/Kolkata",
    "iso:country":"IN",
    "name:ceb_x_preferred":[
        "Berri"
    ],
    "name:deu_x_preferred":[
        "Berri"
    ],
    "name:fra_x_preferred":[
        "Berri"
    ],
    "name:ita_x_preferred":[
        "Berri"
    ],
    "name:swe_x_preferred":[
        "Berri"
    ],
    "wof:name":"Berri",
    "wof:placetype":"locality"
},
  "geometry": {"coordinates":[85.43933,24.72158],"type":"Point"}
}