{
  "type": "Feature",
  "properties": {
    "iso:country":"IN",
    "ks:ks_name":"Devali",
    "ks:ks_pop":304,
    "ks:ks_type":"VILLAGE",
    "name:eng_x_preferred":[
        "Devali"
    ],
    "wof:name":"Devali",
    "wof:placetype":"locality",
    "wof:population":304
},
  "geometry": {"coordinates":[73.150508,19.690163],"type":"Point"}
}