{
  "type": "Feature",
  "properties": {
    "iso:country":"IN",
    "ks:ks_name":"Lakshmanankottai",
    "ks:ks_pop":441,
    "ks:ks_type":"HABITATION",
    "name:eng_x_preferred":[
        "Lakshmanankottai"
    ],
    "wof:name":"Lakshmanankottai",
    "wof:placetype":"locality",
    "wof:population":441
},
  "geometry": {"coordinates":[78.502228,12.354685],"type":"Point"}
}