{
  "type": "Feature",
  "properties": {
    "gn:admin1_code":"12.0",
    "gn:admin2_code":"7.0",
    "gn:asciiname":"Danna",
    "gn:country_code":"IN",
    "gn:dem":730,
    "gn:feature_class":"P",
    "gn:feature_code":"PPL",
    "gn:name":"Danna",
    "gn:population":0,
    "gn:timezone":"Asia/Kolkata",
    "iso:country":"IN",
    "name:ceb_x_preferred":[
        "Danna"
    ],
    "name:deu_x_preferred":[
        "Danna"
    ],
    "name:fra_x_preferred":[
        "Danna"
    ],
    "name:ita_x_preferred":[
        "Danna"
    ],
    "name:rus_x_preferred":[
        "\u0414\u0430\u043d\u043d\u0430"
    ],
    "name:swe_x_preferred":[
        "Danna"
    ],
    "wof:name":"Danna",
    "wof:placetype":"locality"
},
  "geometry": {"coordinates":[75.43793000000002,32.63095999999999],"type":"Point"}
}