{
  "type": "Feature",
  "properties": {
    "iso:country":"IN",
    "ks:ks_name":"Suradiya",
    "ks:ks_pop":2141,
    "ks:ks_type":"VILLAGE",
    "name:eng_x_preferred":[
        "Suradiya"
    ],
    "wof:name":"Suradiya",
    "wof:placetype":"locality",
    "wof:population":2141
},
  "geometry": {"coordinates":[74.270414,25.966494],"type":"Point"}
}