{
  "type": "Feature",
  "properties": {
    "gn:admin1_code":"11",
    "gn:admin2_code":"23.0",
    "gn:asciiname":"Ghelu",
    "gn:country_code":"IN",
    "gn:dem":1939,
    "gn:feature_class":"P",
    "gn:feature_code":"PPL",
    "gn:name":"Ghelu",
    "gn:population":0,
    "gn:timezone":"Asia/Kolkata",
    "iso:country":"IN",
    "wof:name":"Ghelu",
    "wof:placetype":"locality"
},
  "geometry": {"coordinates":[76.15260000000001,32.67413],"type":"Point"}
}