{
  "type": "Feature",
  "properties": {
    "iso:country":"IN",
    "ks:ks_name":"Adampur",
    "ks:ks_pop":596,
    "ks:ks_type":"VILLAGE",
    "name:eng_x_preferred":[
        "Adampur"
    ],
    "wof:name":"Adampur",
    "wof:placetype":"locality",
    "wof:population":596
},
  "geometry": {"coordinates":[87.46434000000001,22.097292],"type":"Point"}
}