{
  "type": "Feature",
  "properties": {
    "gn:admin1_code":"36.0",
    "gn:admin2_code":"139.0",
    "gn:asciiname":"Gathiabad",
    "gn:country_code":"IN",
    "gn:dem":235,
    "gn:feature_class":"P",
    "gn:feature_code":"PPL",
    "gn:name":"Gathi\u0101b\u0101d",
    "gn:population":0,
    "gn:timezone":"Asia/Kolkata",
    "iso:country":"IN",
    "name:und_x_variant":[
        "Gathi\u0101b\u0101d",
        "Garhi"
    ],
    "wof:name":"Gathiabad",
    "wof:placetype":"neighbourhood"
},
  "geometry": {"coordinates":[77.41862999999999,29.19584],"type":"Point"}
}