{
  "type": "Feature",
  "properties": {
    "iso:country":"IN",
    "ks:ks_name":"Bomnabilu",
    "ks:ks_pop":85,
    "ks:ks_type":"HABITATION",
    "name:eng_x_preferred":[
        "Bomnabilu"
    ],
    "wof:name":"Bomnabilu",
    "wof:placetype":"locality",
    "wof:population":85
},
  "geometry": {"coordinates":[74.974801,14.672272],"type":"Point"}
}