{
  "type": "Feature",
  "properties": {
    "gn:admin1_code":"16",
    "gn:admin2_code":"513.0",
    "gn:asciiname":"Karam",
    "gn:country_code":"IN",
    "gn:dem":408,
    "gn:feature_class":"P",
    "gn:feature_code":"PPL",
    "gn:name":"Karam",
    "gn:population":0,
    "gn:timezone":"Asia/Kolkata",
    "iso:country":"IN",
    "name:aze_x_preferred":[
        "K\u0259r\u0259m"
    ],
    "name:ceb_x_preferred":[
        "Karam"
    ],
    "name:deu_x_preferred":[
        "Karam"
    ],
    "name:fra_x_preferred":[
        "Karam"
    ],
    "name:ita_x_preferred":[
        "Karam"
    ],
    "name:rus_x_preferred":[
        "\u041a\u0430\u0440\u0430\u043c"
    ],
    "name:ukr_x_preferred":[
        "\u041a\u0430\u0440\u0430\u043c"
    ],
    "wof:name":"Karam",
    "wof:placetype":"locality"
},
  "geometry": {"coordinates":[76.60151999999999,18.92884],"type":"Point"}
}