{
  "type": "Feature",
  "properties": {
    "gn:admin1_code":"24",
    "gn:admin2_code":"120.0",
    "gn:asciiname":"Indarpura",
    "gn:country_code":"IN",
    "gn:dem":319,
    "gn:feature_class":"P",
    "gn:feature_code":"PPL",
    "gn:name":"Indarpura",
    "gn:population":0,
    "gn:timezone":"Asia/Kolkata",
    "iso:country":"IN",
    "wof:name":"Indarpura",
    "wof:placetype":"locality"
},
  "geometry": {"coordinates":[75.35409,25.81371],"type":"Point"}
}