{
  "type": "Feature",
  "properties": {
    "iso:country":"IN",
    "ks:ks_name":"Gundala",
    "ks:ks_pop":48,
    "ks:ks_type":"HABITATION",
    "name:eng_x_preferred":[
        "Gundala"
    ],
    "wof:name":"Gundala",
    "wof:placetype":"locality",
    "wof:population":48
},
  "geometry": {"coordinates":[74.97577099999999,13.418491],"type":"Point"}
}