{
  "type": "Feature",
  "properties": {
    "iso:country":"IN",
    "ks:ks_name":"Amila Chiraidand",
    "ks:ks_pop":384,
    "ks:ks_type":"HABITATION",
    "ks:ks_uagg_main":0,
    "name:eng_x_preferred":[
        "Amila Chiraidand"
    ],
    "wof:name":"Amila Chiraidand",
    "wof:placetype":"neighbourhood",
    "wof:population":384
},
  "geometry": {"coordinates":[83.539861,26.154679],"type":"Point"}
}