{
  "type": "Feature",
  "properties": {
    "iso:country":"IN",
    "ks:ks_name":"Jambeshvar Nagari",
    "ks:ks_pop":568,
    "ks:ks_type":"HABITATION",
    "name:eng_x_preferred":[
        "Jambeshvar Nagari"
    ],
    "wof:name":"Jambeshvar Nagari",
    "wof:placetype":"locality",
    "wof:population":568
},
  "geometry": {"coordinates":[72.58773100000001,27.297344],"type":"Point"}
}