{
  "type": "Feature",
  "properties": {
    "iso:country":"IN",
    "ks:ks_name":"Meda Falia",
    "ks:ks_pop":326,
    "ks:ks_type":"HABITATION",
    "name:eng_x_preferred":[
        "Meda Falia"
    ],
    "wof:name":"Meda Falia",
    "wof:placetype":"locality",
    "wof:population":326
},
  "geometry": {"coordinates":[74.17272199999999,22.848833],"type":"Point"}
}