{
  "type": "Feature",
  "properties": {
    "iso:country":"IN",
    "ks:ks_name":"Kahikuchi Muslim Gaon",
    "ks:ks_pop":305,
    "ks:ks_type":"HABITATION",
    "ks:ks_uagg_main":0,
    "name:eng_x_preferred":[
        "Kahikuchi Muslim Gaon"
    ],
    "wof:name":"Kahikuchi Muslim Gaon",
    "wof:placetype":"neighbourhood",
    "wof:population":305
},
  "geometry": {"coordinates":[91.506067,26.021442],"type":"Point"}
}