{
  "type": "Feature",
  "properties": {
    "iso:country":"IN",
    "ks:ks_alt_nam":"LONDE WASTI",
    "ks:ks_name":"Londe Wasti",
    "ks:ks_pop":1,
    "ks:ks_type":"HABITATION",
    "name:eng_x_preferred":[
        "Londe Wasti"
    ],
    "wof:name":"Londe Wasti",
    "wof:placetype":"locality",
    "wof:population":1
},
  "geometry": {"coordinates":[75.58429599999999,17.930584],"type":"Point"}
}