{
  "type": "Feature",
  "properties": {
    "gn:admin1_code":"35.0",
    "gn:admin2_code":"424",
    "gn:asciiname":"Hiranagar",
    "gn:country_code":"IN",
    "gn:dem":371,
    "gn:feature_class":"P",
    "gn:feature_code":"PPL",
    "gn:name":"H\u012br\u0101nagar",
    "gn:population":0,
    "gn:timezone":"Asia/Kolkata",
    "iso:country":"IN",
    "name:bpy_x_preferred":[
        "\u09b9\u09bf\u09b0\u09be\u09a8\u0997\u09b0"
    ],
    "name:ceb_x_preferred":[
        "H\u012br\u0101nagar"
    ],
    "name:hin_x_preferred":[
        "\u0939\u0940\u0930\u093e\u0928\u0917\u0930"
    ],
    "name:ita_x_preferred":[
        "Hiranagar"
    ],
    "name:mlg_x_preferred":[
        "Hiranagar"
    ],
    "name:msa_x_preferred":[
        "Hiranagar"
    ],
    "name:new_x_preferred":[
        "\u0939\u093f\u0930\u093e\u0928\u0917\u0930"
    ],
    "name:nld_x_preferred":[
        "Hiranagar"
    ],
    "name:por_x_preferred":[
        "Hiranagar"
    ],
    "name:rus_x_preferred":[
        "\u0425\u0438\u0440\u0430\u043d\u0430\u0433\u0430\u0440"
    ],
    "name:swe_x_preferred":[
        "H\u012br\u0101nagar"
    ],
    "name:urd_x_preferred":[
        "\u06c1\u06cc\u0631\u0627 \u0646\u06af\u0631"
    ],
    "name:vie_x_preferred":[
        "Hiranagar"
    ],
    "name:zho_x_preferred":[
        "\u5e0c\u62c9\u7eb3\u52a0\u5c14"
    ],
    "wof:name":"Hiranagar",
    "wof:placetype":"locality"
},
  "geometry": {"coordinates":[78.87220000000001,24.66369],"type":"Point"}
}