{
  "type": "Feature",
  "properties": {
    "iso:country":"IN",
    "ks:ks_alt_nam":"Gore wasti",
    "ks:ks_name":"Gore Wasti",
    "ks:ks_pop":65,
    "ks:ks_type":"HABITATION",
    "name:eng_x_preferred":[
        "Gore Wasti"
    ],
    "wof:name":"Gore Wasti",
    "wof:placetype":"locality",
    "wof:population":65
},
  "geometry": {"coordinates":[75.500878,18.313356],"type":"Point"}
}