{
  "type": "Feature",
  "properties": {
    "iso:country":"IN",
    "ks:ks_name":"Keelvilagam",
    "ks:ks_pop":444,
    "ks:ks_type":"VILLAGE",
    "ks:ks_uagg_main":0,
    "name:eng_x_preferred":[
        "Keelvilagam"
    ],
    "wof:name":"Keelvilagam",
    "wof:placetype":"neighbourhood",
    "wof:population":444
},
  "geometry": {"coordinates":[79.829362,13.125366],"type":"Point"}
}