{
  "type": "Feature",
  "properties": {
    "gn:admin1_code":"36",
    "gn:admin2_code":"174.0",
    "gn:asciiname":"Basohni",
    "gn:country_code":"IN",
    "gn:dem":108,
    "gn:feature_class":"P",
    "gn:feature_code":"PPL",
    "gn:name":"Basohni",
    "gn:population":0,
    "gn:timezone":"Asia/Kolkata",
    "iso:country":"IN",
    "ks:ks_name":"Basohani",
    "ks:ks_pop":621,
    "ks:ks_type":"VILLAGE",
    "name:eng_x_preferred":[
        "Basohani"
    ],
    "name:eng_x_variant":[
        "Basohni"
    ],
    "wof:name":"Basohani",
    "wof:placetype":"locality",
    "wof:population":621
},
  "geometry": {"coordinates":[81.39120200000001,25.558056],"type":"Point"}
}