{
  "type": "Feature",
  "properties": {
    "iso:country":"IN",
    "ks:ks_alt_nam":"HARIJAN TOLI",
    "ks:ks_name":"Harijan Toli",
    "ks:ks_pop":138,
    "ks:ks_type":"HABITATION",
    "name:eng_x_preferred":[
        "Harijan Toli"
    ],
    "wof:name":"Harijan Toli",
    "wof:placetype":"locality",
    "wof:population":138
},
  "geometry": {"coordinates":[83.99585,25.34485],"type":"Point"}
}