{
  "type": "Feature",
  "properties": {
    "iso:country":"IN",
    "ks:ks_alt_nam":"MURAR PUR",
    "ks:ks_name":"Murar Pur",
    "ks:ks_pop":133,
    "ks:ks_type":"HABITATION",
    "name:eng_x_preferred":[
        "Murar Pur"
    ],
    "wof:name":"Murar Pur",
    "wof:placetype":"locality",
    "wof:population":133
},
  "geometry": {"coordinates":[81.8411,26.159828],"type":"Point"}
}