{
  "type": "Feature",
  "properties": {
    "gn:admin1_code":"37",
    "gn:admin2_code":"410.0",
    "gn:asciiname":"Pharsara",
    "gn:country_code":"IN",
    "gn:dem":447,
    "gn:feature_class":"P",
    "gn:feature_code":"PPL",
    "gn:name":"Pharsara",
    "gn:population":0,
    "gn:timezone":"Asia/Kolkata",
    "iso:country":"IN",
    "ks:ks_name":"Pharsara",
    "ks:ks_type":"VILLAGE",
    "name:eng_x_preferred":[
        "Pharsara"
    ],
    "wof:name":"Pharsara",
    "wof:placetype":"locality"
},
  "geometry": {"coordinates":[82.284013,20.356829],"type":"Point"}
}