{
  "type": "Feature",
  "properties": {
    "gn:admin1_code":"36",
    "gn:admin2_code":"143.0",
    "gn:asciiname":"Nagla Devisingh",
    "gn:country_code":"IN",
    "gn:dem":193,
    "gn:feature_class":"P",
    "gn:feature_code":"PPL",
    "gn:name":"Nagla Dev\u012bsingh",
    "gn:population":0,
    "gn:timezone":"Asia/Kolkata",
    "iso:country":"IN",
    "name:und_x_variant":[
        "Nagla Dev\u012bsingh",
        "Nagla Assu"
    ],
    "wof:name":"Nagla Devisingh",
    "wof:placetype":"locality"
},
  "geometry": {"coordinates":[77.7915,28.00358],"type":"Point"}
}