{
  "type": "Feature",
  "properties": {
    "gn:admin1_code":"9.0",
    "gn:admin2_code":"478",
    "gn:asciiname":"Tukda Miyani",
    "gn:country_code":"IN",
    "gn:dem":21,
    "gn:feature_class":"P",
    "gn:feature_code":"PPL",
    "gn:name":"Tukda Miy\u0101ni",
    "gn:population":0,
    "gn:timezone":"Asia/Kolkata",
    "iso:country":"IN",
    "wof:name":"Tukda Miyani",
    "wof:placetype":"locality"
},
  "geometry": {"coordinates":[69.42654,21.79228],"type":"Point"}
}