{
  "type": "Feature",
  "properties": {
    "iso:country":"IN",
    "ks:ks_name":"Asogwa Pur",
    "ks:ks_pop":372,
    "ks:ks_type":"HABITATION",
    "name:eng_x_preferred":[
        "Asogwa Pur"
    ],
    "wof:name":"Asogwa Pur",
    "wof:placetype":"locality",
    "wof:population":372
},
  "geometry": {"coordinates":[81.733272,27.257294],"type":"Point"}
}