{
  "type": "Feature",
  "properties": {
    "iso:country":"IN",
    "ks:ks_name":"Nuabeda",
    "ks:ks_pop":108,
    "ks:ks_type":"HABITATION",
    "name:eng_x_preferred":[
        "Nuabeda"
    ],
    "wof:name":"Nuabeda",
    "wof:placetype":"locality",
    "wof:population":108
},
  "geometry": {"coordinates":[85.882195,21.13838],"type":"Point"}
}