{
  "type": "Feature",
  "properties": {
    "iso:country":"IN",
    "ks:ks_alt_nam":"NAUTOD",
    "ks:ks_name":"Nautod",
    "ks:ks_pop":223,
    "ks:ks_type":"HABITATION",
    "ks:ks_uagg_main":0,
    "name:eng_x_preferred":[
        "Nautod"
    ],
    "wof:name":"Nautod",
    "wof:placetype":"neighbourhood",
    "wof:population":223
},
  "geometry": {"coordinates":[81.20335799999999,28.23654],"type":"Point"}
}