{
  "type": "Feature",
  "properties": {
    "gn:admin1_code":"36.0",
    "gn:admin2_code":"133.0",
    "gn:asciiname":"Hajipur Jahangirpur",
    "gn:country_code":"IN",
    "gn:dem":226,
    "gn:feature_class":"P",
    "gn:feature_code":"PPL",
    "gn:name":"H\u0101j\u012bpur Jah\u0101ng\u012brpur",
    "gn:population":0,
    "gn:timezone":"Asia/Kolkata",
    "iso:country":"IN",
    "wof:name":"Hajipur Jahangirpur",
    "wof:placetype":"locality"
},
  "geometry": {"coordinates":[77.96914,29.53253],"type":"Point"}
}