{
  "type": "Feature",
  "properties": {
    "iso:country":"IN",
    "ks:ks_name":"Kata Kati",
    "ks:ks_pop":303,
    "ks:ks_type":"VILLAGE",
    "name:eng_x_preferred":[
        "Kata Kati"
    ],
    "wof:name":"Kata Kati",
    "wof:placetype":"locality",
    "wof:population":303
},
  "geometry": {"coordinates":[86.438937,22.376395],"type":"Point"}
}