{
  "type": "Feature",
  "properties": {
    "iso:country":"IN",
    "ks:ks_name":"Ontikumpa",
    "ks:ks_pop":25,
    "ks:ks_type":"HABITATION",
    "ks:ks_uagg_main":0,
    "name:eng_x_preferred":[
        "Ontikumpa"
    ],
    "wof:name":"Ontikumpa",
    "wof:placetype":"neighbourhood",
    "wof:population":25
},
  "geometry": {"coordinates":[81.01724900000001,17.579614],"type":"Point"}
}