{
  "type": "Feature",
  "properties": {
    "iso:country":"IN",
    "ks:ks_name":"Mauje Sukene",
    "ks:ks_pop":4356,
    "ks:ks_type":"VILLAGE",
    "ks:ks_uagg_main":0,
    "name:eng_x_preferred":[
        "Mauje Sukene"
    ],
    "wof:name":"Mauje Sukene",
    "wof:placetype":"neighbourhood",
    "wof:population":4356
},
  "geometry": {"coordinates":[74.0136,20.0748],"type":"Point"}
}