{
  "type": "Feature",
  "properties": {
    "iso:country":"IN",
    "ks:ks_name":"Bhalki Tola Khaira",
    "ks:ks_pop":213,
    "ks:ks_type":"VILLAGE",
    "ks:ks_uagg_main":0,
    "name:eng_x_preferred":[
        "Bhalki Tola Khaira"
    ],
    "wof:name":"Bhalki Tola Khaira",
    "wof:placetype":"neighbourhood",
    "wof:population":213
},
  "geometry": {"coordinates":[86.96157599999999,24.64158],"type":"Point"}
}