{
  "type": "Feature",
  "properties": {
    "iso:country":"IN",
    "ks:ks_name":"Gor Tola",
    "ks:ks_pop":138,
    "ks:ks_type":"HABITATION",
    "name:eng_x_preferred":[
        "Gor Tola"
    ],
    "wof:name":"Gor Tola",
    "wof:placetype":"locality",
    "wof:population":138
},
  "geometry": {"coordinates":[84.294408,26.54314],"type":"Point"}
}