{
  "type": "Feature",
  "properties": {
    "iso:country":"IN",
    "ks:ks_name":"Bhulia",
    "ks:ks_pop":838,
    "ks:ks_type":"VILLAGE",
    "name:eng_x_preferred":[
        "Bhulia"
    ],
    "wof:name":"Bhulia",
    "wof:placetype":"locality",
    "wof:population":838
},
  "geometry": {"coordinates":[86.699428,26.326687],"type":"Point"}
}