{
  "type": "Feature",
  "properties": {
    "gn:admin1_code":"25.0",
    "gn:admin2_code":"631.0",
    "gn:asciiname":"Tammandrapalli",
    "gn:country_code":"IN",
    "gn:dem":801,
    "gn:feature_class":"P",
    "gn:feature_code":"PPL",
    "gn:name":"Tammandrapalli",
    "gn:population":0,
    "gn:timezone":"Asia/Kolkata",
    "iso:country":"IN",
    "wof:name":"Tammandrapalli",
    "wof:placetype":"neighbourhood"
},
  "geometry": {"coordinates":[77.92937999999999,12.70421],"type":"Point"}
}