{
  "type": "Feature",
  "properties": {
    "iso:country":"IN",
    "ks:ks_alt_nam":"tirmunda",
    "ks:ks_name":"Tirmunda",
    "ks:ks_pop":252,
    "ks:ks_type":"HABITATION",
    "name:eng_x_preferred":[
        "Tirmunda"
    ],
    "wof:name":"Tirmunda",
    "wof:placetype":"locality",
    "wof:population":252
},
  "geometry": {"coordinates":[85.152766,22.306779],"type":"Point"}
}