{
  "type": "Feature",
  "properties": {
    "gn:admin1_code":"02",
    "gn:admin2_code":"550.0",
    "gn:asciiname":"Sitarampuram",
    "gn:country_code":"IN",
    "gn:dem":239,
    "gn:feature_class":"P",
    "gn:feature_code":"PPL",
    "gn:name":"S\u012btar\u0101mpuram",
    "gn:population":0,
    "gn:timezone":"Asia/Kolkata",
    "iso:country":"IN",
    "name:und_x_variant":[
        "S\u012btar\u0101mpuram",
        "Sit\u0101r\u0101mpuram"
    ],
    "wof:name":"Sitarampuram",
    "wof:placetype":"neighbourhood"
},
  "geometry": {"coordinates":[79.13674,15.01587],"type":"Point"}
}