{
  "type": "Feature",
  "properties": {
    "gn:admin1_code":"34.0",
    "gn:admin2_code":"211",
    "gn:asciiname":"Baisi",
    "gn:country_code":"IN",
    "gn:dem":42,
    "gn:feature_class":"P",
    "gn:feature_code":"PPL",
    "gn:name":"Baisi",
    "gn:population":1319,
    "gn:timezone":"Asia/Kolkata",
    "iso:country":"IN",
    "wof:name":"Baisi",
    "wof:placetype":"locality",
    "wof:population":1319
},
  "geometry": {"coordinates":[87.74486999999998,25.86302],"type":"Point"}
}