{
  "type": "Feature",
  "properties": {
    "iso:country":"IN",
    "ks:ks_name":"Thanelanka",
    "ks:ks_pop":895,
    "ks:ks_type":"HABITATION",
    "name:eng_x_preferred":[
        "Thanelanka"
    ],
    "wof:name":"Thanelanka",
    "wof:placetype":"locality",
    "wof:population":895
},
  "geometry": {"coordinates":[82.10201499999999,16.664425],"type":"Point"}
}