{
  "type": "Feature",
  "properties": {
    "iso:country":"IN",
    "ks:ks_name":"Rani Chak",
    "ks:ks_pop":2695,
    "ks:ks_type":"VILLAGE",
    "name:eng_x_preferred":[
        "Rani Chak"
    ],
    "wof:name":"Rani Chak",
    "wof:placetype":"locality",
    "wof:population":2695
},
  "geometry": {"coordinates":[87.91801,21.955753],"type":"Point"}
}