{
  "type": "Feature",
  "properties": {
    "iso:country":"IN",
    "ks:ks_name":"Bandhawadi",
    "ks:ks_pop":197,
    "ks:ks_type":"HABITATION",
    "name:eng_x_preferred":[
        "Bandhawadi"
    ],
    "wof:name":"Bandhawadi",
    "wof:placetype":"locality",
    "wof:population":197
},
  "geometry": {"coordinates":[73.80582800000001,16.292362],"type":"Point"}
}