{
  "type": "Feature",
  "properties": {
    "iso:country":"IN",
    "ks:ks_alt_nam":"Godhi bigha",
    "ks:ks_name":"Godhi Bigha",
    "ks:ks_pop":245,
    "ks:ks_type":"HABITATION",
    "name:eng_x_preferred":[
        "Godhi Bigha"
    ],
    "wof:name":"Godhi Bigha",
    "wof:placetype":"locality",
    "wof:population":245
},
  "geometry": {"coordinates":[84.64113500000001,24.831305],"type":"Point"}
}