{
  "type": "Feature",
  "properties": {
    "iso:country":"IN",
    "ks:ks_name":"Sanewadi",
    "ks:ks_pop":50,
    "ks:ks_type":"HABITATION",
    "name:eng_x_preferred":[
        "Sanewadi"
    ],
    "wof:name":"Sanewadi",
    "wof:placetype":"locality",
    "wof:population":50
},
  "geometry": {"coordinates":[73.548457,17.938804],"type":"Point"}
}