{
  "type": "Feature",
  "properties": {
    "gn:admin1_code":"36.0",
    "gn:admin2_code":"192.0",
    "gn:asciiname":"Bhadaura Hosiar Rai",
    "gn:country_code":"IN",
    "gn:dem":67,
    "gn:feature_class":"P",
    "gn:feature_code":"PPL",
    "gn:name":"Bhadaura Hosi\u0101r Rai",
    "gn:population":0,
    "gn:timezone":"Asia/Kolkata",
    "iso:country":"IN",
    "wof:name":"Bhadaura Hosiar Rai",
    "wof:placetype":"neighbourhood"
},
  "geometry": {"coordinates":[83.75129,26.16539],"type":"Point"}
}