{
  "type": "Feature",
  "properties": {
    "iso:country":"IN",
    "ks:ks_name":"Chimatewadi",
    "ks:ks_pop":714,
    "ks:ks_type":"HABITATION",
    "name:eng_x_preferred":[
        "Chimatewadi"
    ],
    "wof:name":"Chimatewadi",
    "wof:placetype":"locality",
    "wof:population":714
},
  "geometry": {"coordinates":[73.73690999999999,18.934518],"type":"Point"}
}