{
  "type": "Feature",
  "properties": {
    "iso:country":"IN",
    "ks:ks_name":"Piligudde",
    "ks:ks_pop":213,
    "ks:ks_type":"HABITATION",
    "name:eng_x_preferred":[
        "Piligudde"
    ],
    "wof:name":"Piligudde",
    "wof:placetype":"locality",
    "wof:population":213
},
  "geometry": {"coordinates":[75.076807,13.002152],"type":"Point"}
}