{
  "type": "Feature",
  "properties": {
    "gn:admin1_code":"36.0",
    "gn:admin2_code":"183.0",
    "gn:asciiname":"Naya Purwa Ganga",
    "gn:country_code":"IN",
    "gn:dem":104,
    "gn:feature_class":"P",
    "gn:feature_code":"PPL",
    "gn:name":"Naya Purwa Ganga",
    "gn:population":0,
    "gn:timezone":"Asia/Kolkata",
    "iso:country":"IN",
    "wof:name":"Naya Purwa Ganga",
    "wof:placetype":"neighbourhood"
},
  "geometry": {"coordinates":[81.74397999999999,27.00593],"type":"Point"}
}