{
  "type": "Feature",
  "properties": {
    "iso:country":"IN",
    "ks:ks_alt_nam":"AHIR TOLA",
    "ks:ks_name":"Ahir Tola",
    "ks:ks_pop":580,
    "ks:ks_type":"HABITATION",
    "ks:ks_uagg_main":0,
    "name:eng_x_preferred":[
        "Ahir Tola"
    ],
    "wof:name":"Ahir Tola",
    "wof:placetype":"neighbourhood",
    "wof:population":580
},
  "geometry": {"coordinates":[84.554869,26.313014],"type":"Point"}
}