{
  "type": "Feature",
  "properties": {
    "iso:country":"IN",
    "ks:ks_name":"Shakarpur",
    "ks:ks_pop":402,
    "ks:ks_type":"HABITATION",
    "name:eng_x_preferred":[
        "Shakarpur"
    ],
    "wof:name":"Shakarpur",
    "wof:placetype":"neighbourhood",
    "wof:population":402
},
  "geometry": {"coordinates":[77.66431900000001,28.892751],"type":"Point"}
}