{
  "type": "Feature",
  "properties": {
    "iso:country":"IN",
    "ks:ks_name":"Kunchoor",
    "ks:ks_pop":258,
    "ks:ks_type":"HABITATION",
    "name:eng_x_preferred":[
        "Kunchoor"
    ],
    "wof:name":"Kunchoor",
    "wof:placetype":"locality",
    "wof:population":258
},
  "geometry": {"coordinates":[76.594097,11.071497],"type":"Point"}
}