{
  "type": "Feature",
  "properties": {
    "iso:country":"IN",
    "ks:ks_name":"Chowluru",
    "ks:ks_pop":72,
    "ks:ks_type":"VILLAGE",
    "name:eng_x_preferred":[
        "Chowluru"
    ],
    "wof:name":"Chowluru",
    "wof:placetype":"locality",
    "wof:population":72
},
  "geometry": {"coordinates":[81.494811,17.714396],"type":"Point"}
}