{
  "type": "Feature",
  "properties": {
    "gn:admin1_code":"36.0",
    "gn:admin2_code":"175.0",
    "gn:asciiname":"Siswan",
    "gn:country_code":"IN",
    "gn:dem":105,
    "gn:feature_class":"P",
    "gn:feature_code":"PPL",
    "gn:name":"Sisw\u0101n",
    "gn:population":0,
    "gn:timezone":"Asia/Kolkata",
    "iso:country":"IN",
    "name:bih_x_preferred":[
        "\u0938\u093f\u0938\u0935\u093e\u0901"
    ],
    "name:hin_x_preferred":[
        "\u0938\u093f\u0938\u0935\u093e\u0928 \u092a\u094d\u0930\u0916\u0923\u094d\u0921"
    ],
    "wof:name":"Siswan",
    "wof:placetype":"neighbourhood"
},
  "geometry": {"coordinates":[81.83826999999999,25.7133],"type":"Point"}
}