{
  "type": "Feature",
  "properties": {
    "gn:admin1_code":"24.0",
    "gn:admin2_code":"126.0",
    "gn:asciiname":"Lambiya",
    "gn:country_code":"IN",
    "gn:dem":432,
    "gn:feature_class":"P",
    "gn:feature_code":"PPL",
    "gn:name":"L\u0101mb\u012bya",
    "gn:population":0,
    "gn:timezone":"Asia/Kolkata",
    "iso:country":"IN",
    "wof:name":"Lambiya",
    "wof:placetype":"locality"
},
  "geometry": {"coordinates":[74.59595,25.02736],"type":"Point"}
}