{
  "type": "Feature",
  "properties": {
    "gn:admin1_code":"19.0",
    "gn:admin2_code":"583.0",
    "gn:asciiname":"Arlesandra",
    "gn:country_code":"IN",
    "gn:dem":863,
    "gn:feature_class":"P",
    "gn:feature_code":"PPL",
    "gn:name":"Arlesandra",
    "gn:population":0,
    "gn:timezone":"Asia/Kolkata",
    "iso:country":"IN",
    "wof:name":"Arlesandra",
    "wof:placetype":"locality"
},
  "geometry": {"coordinates":[77.31702,13.12658],"type":"Point"}
}