{
  "type": "Feature",
  "properties": {
    "gn:admin1_code":"40",
    "gn:admin2_code":"538.0",
    "gn:asciiname":"Irannapalli",
    "gn:country_code":"IN",
    "gn:dem":599,
    "gn:feature_class":"P",
    "gn:feature_code":"PPL",
    "gn:name":"\u012arannapalli",
    "gn:population":0,
    "gn:timezone":"Asia/Kolkata",
    "iso:country":"IN",
    "wof:name":"Irannapalli",
    "wof:placetype":"locality"
},
  "geometry": {"coordinates":[78.09605000000001,16.97036],"type":"Point"}
}