{
  "type": "Feature",
  "properties": {
    "iso:country":"IN",
    "ks:ks_name":"Soorakuppam",
    "ks:ks_pop":1709,
    "ks:ks_type":"HABITATION",
    "name:eng_x_preferred":[
        "Soorakuppam"
    ],
    "wof:name":"Soorakuppam",
    "wof:placetype":"locality",
    "wof:population":1709
},
  "geometry": {"coordinates":[79.571378,11.8045],"type":"Point"}
}