{
  "type": "Feature",
  "properties": {
    "gn:admin1_code":"40.0",
    "gn:admin2_code":"532.0",
    "gn:asciiname":"Mangi",
    "gn:country_code":"IN",
    "gn:dem":503,
    "gn:feature_class":"P",
    "gn:feature_code":"PPL",
    "gn:name":"M\u0101ngi",
    "gn:population":0,
    "gn:timezone":"Asia/Kolkata",
    "iso:country":"IN",
    "name:ceb_x_preferred":[
        "Mangi"
    ],
    "name:snd_x_preferred":[
        "\u0645\u0646\u06af\u064a"
    ],
    "name:swe_x_preferred":[
        "Mangi"
    ],
    "wof:name":"Mangi",
    "wof:placetype":"locality"
},
  "geometry": {"coordinates":[79.15422,19.13087],"type":"Point"}
}