{
  "type": "Feature",
  "properties": {
    "gn:admin1_code":"12.0",
    "gn:admin2_code":"7.0",
    "gn:asciiname":"Nota",
    "gn:country_code":"IN",
    "gn:dem":436,
    "gn:feature_class":"P",
    "gn:feature_code":"PPL",
    "gn:name":"Nota",
    "gn:population":0,
    "gn:timezone":"Asia/Kolkata",
    "iso:country":"IN",
    "name:nld_x_preferred":[
        "Nota"
    ],
    "wof:name":"Nota",
    "wof:placetype":"locality"
},
  "geometry": {"coordinates":[75.51755,32.42528],"type":"Point"}
}