{
  "type": "Feature",
  "properties": {
    "iso:country":"IN",
    "ks:ks_name":"Murakata",
    "ks:ks_pop":1665,
    "ks:ks_type":"VILLAGE",
    "name:eng_x_preferred":[
        "Murakata"
    ],
    "wof:name":"Murakata",
    "wof:placetype":"locality",
    "wof:population":1665
},
  "geometry": {"coordinates":[87.364588,22.219158],"type":"Point"}
}