{
  "type": "Feature",
  "properties": {
    "iso:country":"IN",
    "ks:ks_name":"Ulta Chopra",
    "ks:ks_pop":1648,
    "ks:ks_type":"HABITATION",
    "name:eng_x_preferred":[
        "Ulta Chopra"
    ],
    "wof:name":"Ulta Chopra",
    "wof:placetype":"locality",
    "wof:population":1648
},
  "geometry": {"coordinates":[88.300842,26.417772],"type":"Point"}
}