{
  "type": "Feature",
  "properties": {
    "iso:country":"IN",
    "ks:ks_name":"Vithalwadi",
    "ks:ks_pop":144,
    "ks:ks_type":"HABITATION",
    "name:eng_x_preferred":[
        "Vithalwadi"
    ],
    "wof:name":"Vithalwadi",
    "wof:placetype":"locality",
    "wof:population":144
},
  "geometry": {"coordinates":[75.940393,18.297013],"type":"Point"}
}