{
  "type": "Feature",
  "properties": {
    "iso:country":"IN",
    "ks:ks_name":"Kaneri Shetti Mala",
    "ks:ks_pop":90,
    "ks:ks_type":"HABITATION",
    "name:eng_x_preferred":[
        "Kaneri Shetti Mala"
    ],
    "wof:name":"Kaneri Shetti Mala",
    "wof:placetype":"locality",
    "wof:population":90
},
  "geometry": {"coordinates":[74.21705300000001,16.877272],"type":"Point"}
}