{
  "type": "Feature",
  "properties": {
    "gn:admin1_code":"25.0",
    "gn:admin2_code":"616.0",
    "gn:asciiname":"Sengarayapuram",
    "gn:country_code":"IN",
    "gn:dem":49,
    "gn:feature_class":"P",
    "gn:feature_code":"PPL",
    "gn:name":"Sengar\u0101yapuram",
    "gn:population":0,
    "gn:timezone":"Asia/Kolkata",
    "iso:country":"IN",
    "wof:name":"Sengarayapuram",
    "wof:placetype":"locality"
},
  "geometry": {"coordinates":[79.31411,11.11316],"type":"Point"}
}