{
  "type": "Feature",
  "properties": {
    "gn:admin1_code":"2.0",
    "gn:admin2_code":"552.0",
    "gn:asciiname":"Naranapuram",
    "gn:country_code":"IN",
    "gn:dem":357,
    "gn:feature_class":"P",
    "gn:feature_code":"PPL",
    "gn:name":"N\u0101ran\u0101puram",
    "gn:population":0,
    "gn:timezone":"Asia/Kolkata",
    "iso:country":"IN",
    "name:bpy_x_preferred":[
        "\u09a8\u09b0\u09a8\u09be\u09aa\u09c1\u09b0\u09ae"
    ],
    "name:ita_x_preferred":[
        "Naranapuram"
    ],
    "name:msa_x_preferred":[
        "Naranapuram"
    ],
    "name:new_x_preferred":[
        "\u0928\u0930\u0928\u092a\u0941\u0930\u092e"
    ],
    "name:nld_x_preferred":[
        "Naranapuram"
    ],
    "name:por_x_preferred":[
        "Naranapuram"
    ],
    "name:tam_x_preferred":[
        "\u0ba8\u0bbe\u0bb0\u0ba3\u0bbe\u0baa\u0bc1\u0bb0\u0bae\u0bcd"
    ],
    "name:vie_x_preferred":[
        "Naranapuram"
    ],
    "name:zho_x_preferred":[
        "\u7eb3\u62c9\u7eb3\u666e\u62c9\u59c6"
    ],
    "wof:name":"Naranapuram",
    "wof:placetype":"neighbourhood"
},
  "geometry": {"coordinates":[77.52074,15.77904],"type":"Point"}
}