{
  "type": "Feature",
  "properties": {
    "iso:country":"IN",
    "ks:ks_name":"Narenga 1",
    "ks:ks_pop":160,
    "ks:ks_type":"HABITATION",
    "name:eng_x_preferred":[
        "Narenga 1"
    ],
    "wof:name":"Narenga 1",
    "wof:placetype":"locality",
    "wof:population":160
},
  "geometry": {"coordinates":[91.219539,26.003714],"type":"Point"}
}