{
  "type": "Feature",
  "properties": {
    "iso:country":"IN",
    "ks:ks_name":"Nidde",
    "ks:ks_pop":313,
    "ks:ks_type":"VILLAGE",
    "name:eng_x_preferred":[
        "Nidde"
    ],
    "wof:name":"Nidde",
    "wof:placetype":"locality",
    "wof:population":313
},
  "geometry": {"coordinates":[80.614908,19.952194],"type":"Point"}
}