{
  "type": "Feature",
  "properties": {
    "iso:country":"IN",
    "ks:ks_name":"Bari Barai",
    "ks:ks_pop":884,
    "ks:ks_type":"HABITATION",
    "name:eng_x_preferred":[
        "Bari Barai"
    ],
    "wof:name":"Bari Barai",
    "wof:placetype":"locality",
    "wof:population":884
},
  "geometry": {"coordinates":[81.605334,25.368921],"type":"Point"}
}