{
  "type": "Feature",
  "properties": {
    "iso:country":"IN",
    "ks:ks_name":"Sapghar",
    "ks:ks_pop":382,
    "ks:ks_type":"VILLAGE",
    "name:eng_x_preferred":[
        "Sapghar"
    ],
    "wof:name":"Sapghar",
    "wof:placetype":"locality",
    "wof:population":382
},
  "geometry": {"coordinates":[84.093962,22.641052],"type":"Point"}
}