{
  "type": "Feature",
  "properties": {
    "iso:country":"IN",
    "ks:ks_alt_nam":"Rajput tola",
    "ks:ks_name":"Rajput Tola",
    "ks:ks_pop":288,
    "ks:ks_type":"HABITATION",
    "name:eng_x_preferred":[
        "Rajput Tola"
    ],
    "wof:name":"Rajput Tola",
    "wof:placetype":"locality",
    "wof:population":288
},
  "geometry": {"coordinates":[87.281667,26.218403],"type":"Point"}
}