{
  "type": "Feature",
  "properties": {
    "iso:country":"IN",
    "ks:ks_name":"Barohiya",
    "ks:ks_pop":550,
    "ks:ks_type":"HABITATION",
    "name:eng_x_preferred":[
        "Barohiya"
    ],
    "wof:name":"Barohiya",
    "wof:placetype":"locality",
    "wof:population":550
},
  "geometry": {"coordinates":[82.853979,23.97372],"type":"Point"}
}