{
  "type": "Feature",
  "properties": {
    "iso:country":"IN",
    "ks:ks_name":"Ghoramara",
    "ks:ks_pop":1259,
    "ks:ks_type":"VILLAGE",
    "name:eng_x_preferred":[
        "Ghoramara"
    ],
    "wof:name":"Ghoramara",
    "wof:placetype":"locality",
    "wof:population":1259
},
  "geometry": {"coordinates":[87.600229,22.294638],"type":"Point"}
}