{
  "type": "Feature",
  "properties": {
    "iso:country":"IN",
    "ks:ks_alt_nam":"Jose Villa Rd jun",
    "ks:ks_name":"Jose Villa Rd Jun",
    "ks:ks_pop":245,
    "ks:ks_type":"HABITATION",
    "ks:ks_uagg_main":0,
    "name:eng_x_preferred":[
        "Jose Villa Rd Jun"
    ],
    "wof:name":"Jose Villa Rd Jun",
    "wof:placetype":"neighbourhood",
    "wof:population":245
},
  "geometry": {"coordinates":[76.10029299999999,10.481372],"type":"Point"}
}