{
  "type": "Feature",
  "properties": {
    "gn:admin1_code":"19.0",
    "gn:admin2_code":"582.0",
    "gn:asciiname":"Patakote",
    "gn:country_code":"IN",
    "gn:dem":765,
    "gn:feature_class":"P",
    "gn:feature_code":"PPL",
    "gn:name":"P\u0101takote",
    "gn:population":0,
    "gn:timezone":"Asia/Kolkata",
    "iso:country":"IN",
    "ks:ks_alt_nam":"P\u0101takote",
    "ks:ks_name":"Patakote",
    "ks:ks_type":"VILLAGE",
    "name:eng_x_preferred":[
        "Patakote"
    ],
    "name:eng_x_variant":[
        "P\u0101takote"
    ],
    "wof:name":"Patakote",
    "wof:placetype":"locality"
},
  "geometry": {"coordinates":[78.180691,13.510817],"type":"Point"}
}