{
  "type": "Feature",
  "properties": {
    "gn:admin1_code":"24.0",
    "gn:admin2_code":"100",
    "gn:asciiname":"Dandu",
    "gn:country_code":"IN",
    "gn:dem":191,
    "gn:feature_class":"P",
    "gn:feature_code":"PPL",
    "gn:name":"Dandu",
    "gn:population":0,
    "gn:timezone":"Asia/Kolkata",
    "iso:country":"IN",
    "wof:name":"Dandu",
    "wof:placetype":"neighbourhood"
},
  "geometry": {"coordinates":[74.15582999999999,29.0781],"type":"Point"}
}