{
  "type": "Feature",
  "properties": {
    "iso:country":"IN",
    "ks:ks_alt_nam":"Keotan Tola bechan Tola",
    "ks:ks_name":"Keotan Tola Bechan Tola",
    "ks:ks_pop":196,
    "ks:ks_type":"HABITATION",
    "ks:ks_uagg_main":0,
    "name:eng_x_preferred":[
        "Keotan Tola Bechan Tola"
    ],
    "wof:name":"Keotan Tola Bechan Tola",
    "wof:placetype":"neighbourhood",
    "wof:population":196
},
  "geometry": {"coordinates":[83.466735,26.893695],"type":"Point"}
}