{
  "type": "Feature",
  "properties": {
    "iso:country":"IN",
    "ks:ks_name":"Tejavath Thanda",
    "ks:ks_pop":139,
    "ks:ks_type":"HABITATION",
    "name:eng_x_preferred":[
        "Tejavath Thanda"
    ],
    "wof:name":"Tejavath Thanda",
    "wof:placetype":"locality",
    "wof:population":139
},
  "geometry": {"coordinates":[79.93170600000001,17.441713],"type":"Point"}
}