{
  "type": "Feature",
  "properties": {
    "iso:country":"IN",
    "ks:ks_name":"Sadpur",
    "ks:ks_pop":303,
    "ks:ks_type":"HABITATION",
    "name:eng_x_preferred":[
        "Sadpur"
    ],
    "wof:name":"Sadpur",
    "wof:placetype":"locality",
    "wof:population":303
},
  "geometry": {"coordinates":[81.644554,25.37709],"type":"Point"}
}