{
  "type": "Feature",
  "properties": {
    "iso:country":"IN",
    "ks:ks_name":"Khadikajodi",
    "ks:ks_pop":188,
    "ks:ks_type":"HABITATION",
    "name:eng_x_preferred":[
        "Khadikajodi"
    ],
    "wof:name":"Khadikajodi",
    "wof:placetype":"locality",
    "wof:population":188
},
  "geometry": {"coordinates":[82.01204,18.363516],"type":"Point"}
}