{
  "type": "Feature",
  "properties": {
    "iso:country":"IN",
    "ks:ks_name":"Pirdhi Majra",
    "ks:ks_pop":11,
    "ks:ks_type":"HABITATION",
    "ks:ks_uagg_main":0,
    "name:eng_x_preferred":[
        "Pirdhi Majra"
    ],
    "wof:name":"Pirdhi Majra",
    "wof:placetype":"neighbourhood",
    "wof:population":11
},
  "geometry": {"coordinates":[77.331762,29.794008],"type":"Point"}
}