{
  "type": "Feature",
  "properties": {
    "iso:country":"IN",
    "ks:ks_name":"Pindra Sawanpur",
    "ks:ks_pop":3675,
    "ks:ks_type":"HABITATION",
    "name:eng_x_preferred":[
        "Pindra Sawanpur"
    ],
    "wof:name":"Pindra Sawanpur",
    "wof:placetype":"locality",
    "wof:population":3675
},
  "geometry": {"coordinates":[81.447222,25.448581],"type":"Point"}
}