{
  "type": "Feature",
  "properties": {
    "iso:country":"IN",
    "ks:ks_name":"Bilbagaur",
    "ks:ks_pop":0,
    "ks:ks_type":"VILLAGE",
    "name:eng_x_preferred":[
        "Bilbagaur"
    ],
    "wof:name":"Bilbagaur",
    "wof:placetype":"locality",
    "wof:population":0
},
  "geometry": {"coordinates":[88.172361,24.103393],"type":"Point"}
}