{
  "type": "Feature",
  "properties": {
    "gn:admin1_code":"25.0",
    "gn:admin2_code":"610",
    "gn:asciiname":"Gettavadi",
    "gn:country_code":"IN",
    "gn:dem":880,
    "gn:feature_class":"P",
    "gn:feature_code":"PPL",
    "gn:name":"Gettav\u0101di",
    "gn:population":0,
    "gn:timezone":"Asia/Kolkata",
    "iso:country":"IN",
    "wof:name":"Gettavadi",
    "wof:placetype":"locality"
},
  "geometry": {"coordinates":[76.90684,11.655],"type":"Point"}
}