{
  "type": "Feature",
  "properties": {
    "iso:country":"IN",
    "ks:ks_name":"Bajag Ryt",
    "ks:ks_pop":1435,
    "ks:ks_type":"HABITATION",
    "name:eng_x_preferred":[
        "Bajag Ryt"
    ],
    "wof:name":"Bajag Ryt",
    "wof:placetype":"locality",
    "wof:population":1435
},
  "geometry": {"coordinates":[81.34309500000001,22.669435],"type":"Point"}
}