{
  "type": "Feature",
  "properties": {
    "iso:country":"IN",
    "ks:ks_alt_nam":"GHUSH KI TOLA",
    "ks:ks_name":"Ghush Ki Tola",
    "ks:ks_pop":851,
    "ks:ks_type":"HABITATION",
    "ks:ks_uagg_main":0,
    "name:eng_x_preferred":[
        "Ghush Ki Tola"
    ],
    "wof:name":"Ghush Ki Tola",
    "wof:placetype":"neighbourhood",
    "wof:population":851
},
  "geometry": {"coordinates":[87.32696199999999,25.83889],"type":"Point"}
}