{
  "type": "Feature",
  "properties": {
    "iso:country":"IN",
    "ks:ks_name":"Chirakuta Pt.II",
    "ks:ks_pop":453,
    "ks:ks_type":"VILLAGE",
    "ks:ks_uagg_main":0,
    "name:eng_x_preferred":[
        "Chirakuta Pt.II"
    ],
    "wof:name":"Chirakuta Pt.II",
    "wof:placetype":"neighbourhood",
    "wof:population":453
},
  "geometry": {"coordinates":[90.293369,26.213824],"type":"Point"}
}