{
  "type": "Feature",
  "properties": {
    "iso:country":"IN",
    "ks:ks_name":"Baidbar",
    "ks:ks_pop":154,
    "ks:ks_type":"VILLAGE",
    "name:eng_x_preferred":[
        "Baidbar"
    ],
    "wof:name":"Baidbar",
    "wof:placetype":"locality",
    "wof:population":154
},
  "geometry": {"coordinates":[85.77960899999999,24.451582],"type":"Point"}
}