{
  "type": "Feature",
  "properties": {
    "gn:admin1_code":"28",
    "gn:admin2_code":"336.0",
    "gn:asciiname":"Santipur",
    "gn:country_code":"IN",
    "gn:dem":19,
    "gn:feature_class":"P",
    "gn:feature_code":"PPL",
    "gn:name":"S\u0101ntipur",
    "gn:population":0,
    "gn:timezone":"Asia/Kolkata",
    "iso:country":"IN",
    "name:und_x_variant":[
        "S\u0101ntipur"
    ],
    "wof:name":"Santipur",
    "wof:placetype":"locality"
},
  "geometry": {"coordinates":[88.43333,23.25],"type":"Point"}
}