{
  "type": "Feature",
  "properties": {
    "gn:admin1_code":"35.0",
    "gn:admin2_code":"441",
    "gn:asciiname":"Borghat",
    "gn:country_code":"IN",
    "gn:dem":535,
    "gn:feature_class":"P",
    "gn:feature_code":"PPL",
    "gn:name":"Borghat",
    "gn:population":0,
    "gn:timezone":"Asia/Kolkata",
    "iso:country":"IN",
    "name:und_x_variant":[
        "Borgh\u0101t"
    ],
    "wof:name":"Borghat",
    "wof:placetype":"locality"
},
  "geometry": {"coordinates":[75.05949,21.57833],"type":"Point"}
}