{
  "type": "Feature",
  "properties": {
    "gn:admin1_code":"36",
    "gn:admin2_code":"177.0",
    "gn:asciiname":"Purwa Sultan Begam",
    "gn:country_code":"IN",
    "gn:dem":104,
    "gn:feature_class":"P",
    "gn:feature_code":"PPL",
    "gn:name":"Purwa Sult\u0101n Begam",
    "gn:population":0,
    "gn:timezone":"Asia/Kolkata",
    "iso:country":"IN",
    "wof:name":"Purwa Sultan Begam",
    "wof:placetype":"locality"
},
  "geometry": {"coordinates":[82.11175,26.57576],"type":"Point"}
}