{
  "type": "Feature",
  "properties": {
    "iso:country":"IN",
    "ks:ks_alt_nam":"chamana koppalu",
    "ks:ks_name":"Chamana Koppalu",
    "ks:ks_pop":173,
    "ks:ks_type":"HABITATION",
    "name:eng_x_preferred":[
        "Chamana Koppalu"
    ],
    "wof:name":"Chamana Koppalu",
    "wof:placetype":"locality",
    "wof:population":173
},
  "geometry": {"coordinates":[76.688479,12.961983],"type":"Point"}
}