{
  "type": "Feature",
  "properties": {
    "iso:country":"IN",
    "ks:ks_name":"Getipada",
    "ks:ks_pop":205,
    "ks:ks_type":"HABITATION",
    "name:eng_x_preferred":[
        "Getipada"
    ],
    "wof:name":"Getipada",
    "wof:placetype":"locality",
    "wof:population":205
},
  "geometry": {"coordinates":[73.00987000000001,19.962832],"type":"Point"}
}