{
  "type": "Feature",
  "properties": {
    "iso:country":"IN",
    "ks:ks_name":"Panduripathar",
    "ks:ks_pop":479,
    "ks:ks_type":"VILLAGE",
    "ks:ks_uagg_main":0,
    "name:eng_x_preferred":[
        "Panduripathar"
    ],
    "wof:name":"Panduripathar",
    "wof:placetype":"neighbourhood",
    "wof:population":479
},
  "geometry": {"coordinates":[84.466037,20.948024],"type":"Point"}
}