{
  "type": "Feature",
  "properties": {
    "iso:country":"IN",
    "ks:ks_name":"Mallatti",
    "ks:ks_pop":316,
    "ks:ks_type":"HABITATION",
    "name:eng_x_preferred":[
        "Mallatti"
    ],
    "wof:name":"Mallatti",
    "wof:placetype":"locality",
    "wof:population":316
},
  "geometry": {"coordinates":[74.492248,16.061852],"type":"Point"}
}