{
  "type": "Feature",
  "properties": {
    "gn:admin1_code":"2.0",
    "gn:admin2_code":"550",
    "gn:asciiname":"Aduripalli",
    "gn:country_code":"IN",
    "gn:dem":95,
    "gn:feature_class":"P",
    "gn:feature_code":"PPL",
    "gn:name":"\u0100duripalli",
    "gn:population":0,
    "gn:timezone":"Asia/Kolkata",
    "iso:country":"IN",
    "name:und_x_variant":[
        "\u0100duripalli",
        "\u0100d\u016bripalle"
    ],
    "wof:name":"Aduripalli",
    "wof:placetype":"locality"
},
  "geometry": {"coordinates":[79.60164,14.44349],"type":"Point"}
}