{
  "type": "Feature",
  "properties": {
    "iso:country":"IN",
    "qs:name":"Indok",
    "qs:name_adm0":"India",
    "qs:name_adm1":"Rajasthan",
    "qs:photos":54,
    "qs:photos_1k":11,
    "qs:photos_9k":1,
    "qs:photos_9r":2,
    "qs:photos_all":54,
    "qs:photos_sr":2,
    "qs:placetype":"Town",
    "qs:pop_sr":"0",
    "wof:name":"Indok",
    "wof:placetype":"locality"
},
  "geometry": {"coordinates":[76.39377500000001,27.403775],"type":"Point"}
}