{
  "type": "Feature",
  "properties": {
    "iso:country":"IN",
    "ks:ks_name":"Abid Nagar",
    "ks:ks_pop":98,
    "ks:ks_type":"HABITATION",
    "ks:ks_uagg_main":0,
    "name:eng_x_preferred":[
        "Abid Nagar"
    ],
    "wof:name":"Abid Nagar",
    "wof:placetype":"neighbourhood",
    "wof:population":98
},
  "geometry": {"coordinates":[81.51581299999999,27.711682],"type":"Point"}
}