{
  "type": "Feature",
  "properties": {
    "gn:admin1_code":"2",
    "gn:admin2_code":"545.0",
    "gn:asciiname":"Gavarayyapeta",
    "gn:country_code":"IN",
    "gn:dem":150,
    "gn:feature_class":"P",
    "gn:feature_code":"PPL",
    "gn:name":"Gavarayyapeta",
    "gn:population":0,
    "gn:timezone":"Asia/Kolkata",
    "iso:country":"IN",
    "ks:ks_name":"Gavarayyapeta",
    "ks:ks_pop":272,
    "ks:ks_type":"VILLAGE",
    "name:eng_x_preferred":[
        "Gavarayyapeta"
    ],
    "wof:name":"Gavarayyapeta",
    "wof:placetype":"locality",
    "wof:population":272
},
  "geometry": {"coordinates":[82.110775,17.461247],"type":"Point"}
}