{
  "type": "Feature",
  "properties": {
    "iso:country":"IN",
    "ks:ks_name":"Janiguda",
    "ks:ks_pop":50,
    "ks:ks_type":"HABITATION",
    "name:eng_x_preferred":[
        "Janiguda"
    ],
    "wof:name":"Janiguda",
    "wof:placetype":"locality",
    "wof:population":50
},
  "geometry": {"coordinates":[82.921851,18.866741],"type":"Point"}
}