{
  "type": "Feature",
  "properties": {
    "iso:country":"IN",
    "ks:ks_name":"Sibnagar",
    "ks:ks_pop":96,
    "ks:ks_type":"HABITATION",
    "name:eng_x_preferred":[
        "Sibnagar"
    ],
    "wof:name":"Sibnagar",
    "wof:placetype":"locality",
    "wof:population":96
},
  "geometry": {"coordinates":[93.072062,24.944615],"type":"Point"}
}