{
  "type": "Feature",
  "properties": {
    "gn:admin1_code":"13.0",
    "gn:admin2_code":"600.0",
    "gn:asciiname":"Kottiyam",
    "gn:country_code":"IN",
    "gn:dem":41,
    "gn:feature_class":"P",
    "gn:feature_code":"PPL",
    "gn:name":"Kottiyam",
    "gn:population":0,
    "gn:timezone":"Asia/Kolkata",
    "iso:country":"IN",
    "name:mal_x_preferred":[
        "\u0d15\u0d4a\u0d1f\u0d4d\u0d1f\u0d3f\u0d2f\u0d02"
    ],
    "wof:name":"Kottiyam",
    "wof:placetype":"locality"
},
  "geometry": {"coordinates":[76.66998000000002,8.86569],"type":"Point"}
}