{
  "type": "Feature",
  "properties": {
    "gn:admin1_code":"34.0",
    "gn:admin2_code":"222.0",
    "gn:asciiname":"Basahi",
    "gn:country_code":"IN",
    "gn:dem":49,
    "gn:feature_class":"P",
    "gn:feature_code":"PPL",
    "gn:name":"Basahi",
    "gn:population":0,
    "gn:timezone":"Asia/Kolkata",
    "iso:country":"IN",
    "wof:name":"Basahi",
    "wof:placetype":"locality"
},
  "geometry": {"coordinates":[86.00315000000001,25.54567],"type":"Point"}
}