{
  "type": "Feature",
  "properties": {
    "gn:admin1_code":"40.0",
    "gn:admin2_code":"535.0",
    "gn:asciiname":"Kamalabad",
    "gn:country_code":"IN",
    "gn:dem":597,
    "gn:feature_class":"P",
    "gn:feature_code":"PPL",
    "gn:name":"Kam\u0101l\u0101b\u0101d",
    "gn:population":0,
    "gn:timezone":"Asia/Kolkata",
    "iso:country":"IN",
    "name:ceb_x_preferred":[
        "Kamalabad"
    ],
    "name:fas_x_preferred":[
        "\u06a9\u0645\u0627\u0644\u200c\u0622\u0628\u0627\u062f"
    ],
    "name:swe_x_preferred":[
        "Kamalabad"
    ],
    "wof:name":"Kamalabad",
    "wof:placetype":"locality"
},
  "geometry": {"coordinates":[78.64782,17.70889],"type":"Point"}
}