{
  "type": "Feature",
  "properties": {
    "iso:country":"IN",
    "ks:ks_name":"Karode",
    "ks:ks_pop":31506,
    "ks:ks_type":"VILLAGE",
    "name:eng_x_preferred":[
        "Karode"
    ],
    "wof:name":"Karode",
    "wof:placetype":"locality",
    "wof:population":31506
},
  "geometry": {"coordinates":[77.123589,8.32751],"type":"Point"}
}