{
  "type": "Feature",
  "properties": {
    "iso:country":"IN",
    "ks:ks_name":"Khedi",
    "ks:ks_pop":695,
    "ks:ks_type":"VILLAGE",
    "name:eng_x_preferred":[
        "Khedi"
    ],
    "wof:name":"Khedi",
    "wof:placetype":"locality",
    "wof:population":695
},
  "geometry": {"coordinates":[74.74769999999999,23.284118],"type":"Point"}
}