{
  "type": "Feature",
  "properties": {
    "iso:country":"IN",
    "ks:ks_alt_nam":"Sonapur NC",
    "ks:ks_name":"Sonapur Nc",
    "ks:ks_pop":310,
    "ks:ks_type":"HABITATION",
    "name:eng_x_preferred":[
        "Sonapur Nc"
    ],
    "wof:name":"Sonapur Nc",
    "wof:placetype":"locality",
    "wof:population":310
},
  "geometry": {"coordinates":[91.966904,26.159701],"type":"Point"}
}