{
  "type": "Feature",
  "properties": {
    "iso:country":"IN",
    "ks:ks_name":"Rasbar Tola",
    "ks:ks_pop":95,
    "ks:ks_type":"HABITATION",
    "name:eng_x_preferred":[
        "Rasbar Tola"
    ],
    "wof:name":"Rasbar Tola",
    "wof:placetype":"locality",
    "wof:population":95
},
  "geometry": {"coordinates":[86.181104,24.016818],"type":"Point"}
}