{
  "type": "Feature",
  "properties": {
    "iso:country":"IN",
    "ks:ks_alt_nam":"Tivs\u0101la Reserved Forest",
    "ks:ks_alt_nam_2":"Tivsala Reserved Forest",
    "ks:ks_name":"Tivsala",
    "ks:ks_pop":0,
    "ks:ks_type":"VILLAGE",
    "name:eng_x_preferred":[
        "Tivsala"
    ],
    "name:eng_x_variant":[
        "Tivs\u0101la Reserved Forest",
        "Tivsala Reserved Forest"
    ],
    "wof:name":"Tivsala",
    "wof:placetype":"locality",
    "wof:population":0
},
  "geometry": {"coordinates":[78.641066,20.118109],"type":"Point"}
}