{
  "type": "Feature",
  "properties": {
    "iso:country":"IN",
    "ks:ks_name":"Kendua",
    "ks:ks_pop":21,
    "ks:ks_type":"VILLAGE",
    "name:eng_x_preferred":[
        "Kendua"
    ],
    "wof:name":"Kendua",
    "wof:placetype":"locality",
    "wof:population":21
},
  "geometry": {"coordinates":[87.283182,22.028242],"type":"Point"}
}