{
  "type": "Feature",
  "properties": {
    "iso:country":"IN",
    "ks:ks_name":"Moggehalla",
    "ks:ks_pop":69,
    "ks:ks_type":"HABITATION",
    "name:eng_x_preferred":[
        "Moggehalla"
    ],
    "wof:name":"Moggehalla",
    "wof:placetype":"locality",
    "wof:population":69
},
  "geometry": {"coordinates":[74.647187,14.239555],"type":"Point"}
}