{
  "type": "Feature",
  "properties": {
    "gn:admin1_code":"3.0",
    "gn:admin2_code":"321.0",
    "gn:asciiname":"Mandirapathar",
    "gn:country_code":"IN",
    "gn:dem":38,
    "gn:feature_class":"P",
    "gn:feature_code":"PPL",
    "gn:name":"Mandirapathar",
    "gn:population":0,
    "gn:timezone":"Asia/Kolkata",
    "iso:country":"IN",
    "wof:name":"Mandirapathar",
    "wof:placetype":"locality"
},
  "geometry": {"coordinates":[91.10173,26.04312],"type":"Point"}
}