{
  "type": "Feature",
  "properties": {
    "iso:country":"IN",
    "ks:ks_alt_nam":"Lakshmi puram",
    "ks:ks_name":"Lakshmi Puram",
    "ks:ks_pop":35,
    "ks:ks_type":"HABITATION",
    "name:eng_x_preferred":[
        "Lakshmi Puram"
    ],
    "wof:name":"Lakshmi Puram",
    "wof:placetype":"locality",
    "wof:population":35
},
  "geometry": {"coordinates":[79.422349,13.528803],"type":"Point"}
}