{
  "type": "Feature",
  "properties": {
    "gn:admin1_code":"36",
    "gn:admin2_code":"197.0",
    "gn:asciiname":"Kitta",
    "gn:country_code":"IN",
    "gn:dem":82,
    "gn:feature_class":"P",
    "gn:feature_code":"PPL",
    "gn:name":"Kitta",
    "gn:population":0,
    "gn:timezone":"Asia/Kolkata",
    "iso:country":"IN",
    "name:ell_x_preferred":[
        "\u039a\u03af\u03c4\u03c4\u03b1 \u039b\u03b1\u03ba\u03c9\u03bd\u03af\u03b1\u03c2"
    ],
    "wof:name":"Kitta",
    "wof:placetype":"locality"
},
  "geometry": {"coordinates":[83.07583000000002,25.40259],"type":"Point"}
}