{
  "type": "Feature",
  "properties": {
    "iso:country":"IN",
    "ks:ks_name":"Mahuatanr",
    "ks:ks_pop":189,
    "ks:ks_type":"VILLAGE",
    "name:eng_x_preferred":[
        "Mahuatanr"
    ],
    "wof:name":"Mahuatanr",
    "wof:placetype":"locality",
    "wof:population":189
},
  "geometry": {"coordinates":[85.955541,24.333957],"type":"Point"}
}