{
  "type": "Feature",
  "properties": {
    "gn:admin1_code":"36.0",
    "gn:admin2_code":"133.0",
    "gn:asciiname":"Bina Mazra",
    "gn:country_code":"IN",
    "gn:dem":246,
    "gn:feature_class":"P",
    "gn:feature_code":"PPL",
    "gn:name":"B\u012bna M\u0101zra",
    "gn:population":0,
    "gn:timezone":"Asia/Kolkata",
    "iso:country":"IN",
    "ks:ks_alt_nam":"B\u012bna M\u0101zra",
    "ks:ks_name":"Bina Mazra",
    "ks:ks_pop":1158,
    "ks:ks_type":"VILLAGE",
    "ks:ks_uagg_main":0,
    "name:eng_x_preferred":[
        "Bina Mazra"
    ],
    "name:eng_x_variant":[
        "B\u012bna M\u0101zra"
    ],
    "wof:name":"Bina Mazra",
    "wof:placetype":"neighbourhood",
    "wof:population":1158
},
  "geometry": {"coordinates":[77.175658,29.599968],"type":"Point"}
}