{
  "type": "Feature",
  "properties": {
    "iso:country":"IN",
    "ks:ks_name":"Godari No.5",
    "ks:ks_pop":10,
    "ks:ks_type":"HABITATION",
    "name:eng_x_preferred":[
        "Godari No.5"
    ],
    "wof:name":"Godari No.5",
    "wof:placetype":"locality",
    "wof:population":10
},
  "geometry": {"coordinates":[81.538951,24.670892],"type":"Point"}
}