{
  "type": "Feature",
  "properties": {
    "iso:country":"IN",
    "ks:ks_name":"Bandhasahi",
    "ks:ks_pop":522,
    "ks:ks_type":"VILLAGE",
    "name:eng_x_preferred":[
        "Bandhasahi"
    ],
    "wof:name":"Bandhasahi",
    "wof:placetype":"locality",
    "wof:population":522
},
  "geometry": {"coordinates":[85.015016,19.991562],"type":"Point"}
}