{
  "type": "Feature",
  "properties": {
    "iso:country":"IN",
    "ks:ks_name":"Andakottai",
    "ks:ks_pop":335,
    "ks:ks_type":"VILLAGE",
    "ks:ks_uagg_main":0,
    "name:eng_x_preferred":[
        "Andakottai"
    ],
    "wof:name":"Andakottai",
    "wof:placetype":"neighbourhood",
    "wof:population":335
},
  "geometry": {"coordinates":[79.13242200000001,10.266182],"type":"Point"}
}