{
  "type": "Feature",
  "properties": {
    "iso:country":"IN",
    "ks:ks_name":"Bokanwa",
    "ks:ks_pop":120,
    "ks:ks_type":"HABITATION",
    "name:eng_x_preferred":[
        "Bokanwa"
    ],
    "wof:name":"Bokanwa",
    "wof:placetype":"locality",
    "wof:population":120
},
  "geometry": {"coordinates":[86.857462,24.710546],"type":"Point"}
}