{
  "type": "Feature",
  "properties": {
    "iso:country":"IN",
    "ks:ks_name":"Nepalipara 2 A",
    "ks:ks_pop":337,
    "ks:ks_type":"HABITATION",
    "name:eng_x_preferred":[
        "Nepalipara 2 A"
    ],
    "wof:name":"Nepalipara 2 A",
    "wof:placetype":"locality",
    "wof:population":337
},
  "geometry": {"coordinates":[92.24549399999999,26.761513],"type":"Point"}
}