{
  "type": "Feature",
  "properties": {
    "gn:admin1_code":"19.0",
    "gn:admin2_code":"569.0",
    "gn:asciiname":"Hirebail",
    "gn:country_code":"IN",
    "gn:dem":23,
    "gn:feature_class":"P",
    "gn:feature_code":"PPL",
    "gn:name":"Hirebail",
    "gn:population":0,
    "gn:timezone":"Asia/Kolkata",
    "iso:country":"IN",
    "ks:ks_name":"Herebailu",
    "ks:ks_pop":26,
    "ks:ks_type":"HABITATION",
    "name:eng_x_preferred":[
        "Herebailu"
    ],
    "name:eng_x_variant":[
        "Hirebail"
    ],
    "wof:name":"Herebailu",
    "wof:placetype":"locality",
    "wof:population":26
},
  "geometry": {"coordinates":[74.843783,13.611552],"type":"Point"}
}