{
  "type": "Feature",
  "properties": {
    "iso:country":"IN",
    "ks:ks_alt_nam":"LELUKA",
    "ks:ks_name":"Leluka",
    "ks:ks_pop":331,
    "ks:ks_type":"HABITATION",
    "name:eng_x_preferred":[
        "Leluka"
    ],
    "wof:name":"Leluka",
    "wof:placetype":"locality",
    "wof:population":331
},
  "geometry": {"coordinates":[87.77582200000001,25.796622],"type":"Point"}
}