{
  "type": "Feature",
  "properties": {
    "iso:country":"IN",
    "ks:ks_name":"Pipraha",
    "ks:ks_pop":392,
    "ks:ks_type":"VILLAGE",
    "name:eng_x_preferred":[
        "Pipraha"
    ],
    "wof:name":"Pipraha",
    "wof:placetype":"locality",
    "wof:population":392
},
  "geometry": {"coordinates":[81.696319,23.890302],"type":"Point"}
}