{
  "type": "Feature",
  "properties": {
    "iso:country":"IN",
    "ks:ks_name":"Annanagar",
    "ks:ks_pop":202,
    "ks:ks_type":"HABITATION",
    "name:eng_x_preferred":[
        "Annanagar"
    ],
    "wof:name":"Annanagar",
    "wof:placetype":"locality",
    "wof:population":202
},
  "geometry": {"coordinates":[78.62083699999999,12.237143],"type":"Point"}
}