{
  "type": "Feature",
  "properties": {
    "iso:country":"IN",
    "ks:ks_alt_nam":"SADHUAPURA",
    "ks:ks_name":"Sadhuapura",
    "ks:ks_pop":524,
    "ks:ks_type":"HABITATION",
    "name:eng_x_preferred":[
        "Sadhuapura"
    ],
    "wof:name":"Sadhuapura",
    "wof:placetype":"locality",
    "wof:population":524
},
  "geometry": {"coordinates":[79.070154,26.511802],"type":"Point"}
}