{
  "type": "Feature",
  "properties": {
    "iso:country":"IN",
    "ks:ks_name":"Gottamaranahalli",
    "ks:ks_pop":43,
    "ks:ks_type":"VILLAGE",
    "name:eng_x_preferred":[
        "Gottamaranahalli"
    ],
    "wof:name":"Gottamaranahalli",
    "wof:placetype":"locality",
    "wof:population":43
},
  "geometry": {"coordinates":[77.707978,12.843723],"type":"Point"}
}