{
  "type": "Feature",
  "properties": {
    "gn:admin1_code":"19.0",
    "gn:admin2_code":"555.0",
    "gn:asciiname":"Chivatgundi",
    "gn:country_code":"IN",
    "gn:dem":688,
    "gn:feature_class":"P",
    "gn:feature_code":"PPL",
    "gn:name":"Chivatgundi",
    "gn:population":0,
    "gn:timezone":"Asia/Kolkata",
    "iso:country":"IN",
    "wof:name":"Chivatgundi",
    "wof:placetype":"locality"
},
  "geometry": {"coordinates":[74.79696,15.81934],"type":"Point"}
}