{
  "type": "Feature",
  "properties": {
    "iso:country":"IN",
    "ks:ks_name":"Harebailu",
    "ks:ks_pop":205,
    "ks:ks_type":"HABITATION",
    "name:eng_x_preferred":[
        "Harebailu"
    ],
    "wof:name":"Harebailu",
    "wof:placetype":"locality",
    "wof:population":205
},
  "geometry": {"coordinates":[75.273253,13.544651],"type":"Point"}
}