{
  "type": "Feature",
  "properties": {
    "gn:admin1_code":"35",
    "gn:admin2_code":"452.0",
    "gn:asciiname":"Kunri",
    "gn:country_code":"IN",
    "gn:dem":344,
    "gn:feature_class":"P",
    "gn:feature_code":"PPL",
    "gn:name":"Kunri",
    "gn:population":0,
    "gn:timezone":"Asia/Kolkata",
    "iso:country":"IN",
    "name:fas_x_preferred":[
        "\u06a9\u0646\u0631\u06cc"
    ],
    "name:snd_x_preferred":[
        "\u06aa\u0646\u0631\u064a"
    ],
    "wof:name":"Kunri",
    "wof:placetype":"neighbourhood"
},
  "geometry": {"coordinates":[79.08710000000001,23.02947],"type":"Point"}
}