{
  "type": "Feature",
  "properties": {
    "gn:admin1_code":"10.0",
    "gn:admin2_code":"69.0",
    "gn:asciiname":"Thana",
    "gn:country_code":"IN",
    "gn:dem":949,
    "gn:feature_class":"P",
    "gn:feature_code":"PPL",
    "gn:name":"Th\u0101na",
    "gn:population":0,
    "gn:timezone":"Asia/Kolkata",
    "iso:country":"IN",
    "name:ben_x_preferred":[
        "\u09a5\u09be\u09a8\u09be"
    ],
    "name:deu_x_preferred":[
        "Thana"
    ],
    "name:fra_x_preferred":[
        "Thana"
    ],
    "name:hun_x_preferred":[
        "Thana"
    ],
    "wof:name":"Thana",
    "wof:placetype":"locality"
},
  "geometry": {"coordinates":[77.13396,30.66803],"type":"Point"}
}