{
  "type": "Feature",
  "properties": {
    "iso:country":"IN",
    "ks:ks_name":"Kadokota",
    "ks:ks_pop":126,
    "ks:ks_type":"VILLAGE",
    "name:eng_x_preferred":[
        "Kadokota"
    ],
    "wof:name":"Kadokota",
    "wof:placetype":"locality",
    "wof:population":126
},
  "geometry": {"coordinates":[86.972993,22.110876],"type":"Point"}
}