{
  "type": "Feature",
  "properties": {
    "iso:country":"IN",
    "ks:ks_name":"Alankarpur",
    "ks:ks_pop":1307,
    "ks:ks_type":"VILLAGE",
    "ks:ks_uagg_main":0,
    "name:eng_x_preferred":[
        "Alankarpur"
    ],
    "wof:name":"Alankarpur",
    "wof:placetype":"locality",
    "wof:population":1307
},
  "geometry": {"coordinates":[87.53244100000001,21.648841],"type":"Point"}
}