{
  "type": "Feature",
  "properties": {
    "iso:country":"IN",
    "ks:ks_name":"Ranhat",
    "ks:ks_pop":955,
    "ks:ks_type":"VILLAGE",
    "name:eng_x_preferred":[
        "Ranhat"
    ],
    "wof:name":"Ranhat",
    "wof:placetype":"locality",
    "wof:population":955
},
  "geometry": {"coordinates":[83.32486,23.540781],"type":"Point"}
}