{
  "type": "Feature",
  "properties": {
    "iso:country":"IN",
    "ks:ks_name":"Badegoda Maqo I",
    "ks:ks_pop":0,
    "ks:ks_type":"VILLAGE",
    "name:eng_x_preferred":[
        "Badegoda Maqo I"
    ],
    "wof:name":"Badegoda Maqo I",
    "wof:placetype":"locality",
    "wof:population":0
},
  "geometry": {"coordinates":[87.629473,24.848868],"type":"Point"}
}