{
  "type": "Feature",
  "properties": {
    "gn:admin1_code":"36.0",
    "gn:admin2_code":"167",
    "gn:asciiname":"Tera",
    "gn:country_code":"IN",
    "gn:dem":351,
    "gn:feature_class":"P",
    "gn:feature_code":"PPL",
    "gn:name":"Tera",
    "gn:population":0,
    "gn:timezone":"Asia/Kolkata",
    "iso:country":"IN",
    "name:bul_x_preferred":[
        "\u0422\u0435\u0440\u0430"
    ],
    "name:ceb_x_preferred":[
        "Tera"
    ],
    "name:deu_x_preferred":[
        "Tera"
    ],
    "name:eus_x_preferred":[
        "Tera"
    ],
    "name:fas_x_preferred":[
        "\u062a\u0631\u0627"
    ],
    "name:fin_x_preferred":[
        "Tera"
    ],
    "name:fra_x_preferred":[
        "Tera"
    ],
    "name:glg_x_preferred":[
        "Tera"
    ],
    "name:ita_x_preferred":[
        "Tera"
    ],
    "name:nds_x_preferred":[
        "Tera"
    ],
    "name:pap_x_preferred":[
        "Tera"
    ],
    "name:pol_x_preferred":[
        "Tera"
    ],
    "name:por_x_preferred":[
        "Tera"
    ],
    "name:rus_x_preferred":[
        "\u0422\u0435\u0440\u0430"
    ],
    "name:spa_x_preferred":[
        "Tera"
    ],
    "name:swe_x_preferred":[
        "Tera"
    ],
    "wof:name":"Tera",
    "wof:placetype":"locality"
},
  "geometry": {"coordinates":[78.53059,24.75032],"type":"Point"}
}