{
  "type": "Feature",
  "properties": {
    "iso:country":"IN",
    "ks:ks_name":"Nelagamdinni",
    "ks:ks_pop":255,
    "ks:ks_type":"VILLAGE",
    "name:eng_x_preferred":[
        "Nelagamdinni"
    ],
    "wof:name":"Nelagamdinni",
    "wof:placetype":"locality",
    "wof:population":255
},
  "geometry": {"coordinates":[76.96579800000001,15.877579],"type":"Point"}
}