{
  "type": "Feature",
  "properties": {
    "gn:admin1_code":"11",
    "gn:admin2_code":"31.0",
    "gn:asciiname":"Mahla",
    "gn:country_code":"IN",
    "gn:dem":1387,
    "gn:feature_class":"P",
    "gn:feature_code":"PPL",
    "gn:name":"M\u0101hla",
    "gn:population":0,
    "gn:timezone":"Asia/Kolkata",
    "iso:country":"IN",
    "name:spa_x_preferred":[
        "Mahla"
    ],
    "wof:name":"Mahla",
    "wof:placetype":"locality"
},
  "geometry": {"coordinates":[77.07139000000002,31.07381],"type":"Point"}
}