{
  "type": "Feature",
  "properties": {
    "iso:country":"IN",
    "ks:ks_name":"Leel",
    "ks:ks_pop":19,
    "ks:ks_type":"VILLAGE",
    "name:eng_x_preferred":[
        "Leel"
    ],
    "wof:name":"Leel",
    "wof:placetype":"locality",
    "wof:population":19
},
  "geometry": {"coordinates":[75.58210699999999,31.146694],"type":"Point"}
}