{
  "type": "Feature",
  "properties": {
    "gn:admin1_code":"19.0",
    "gn:admin2_code":"574.0",
    "gn:asciiname":"Kerodi",
    "gn:country_code":"IN",
    "gn:dem":918,
    "gn:feature_class":"P",
    "gn:feature_code":"PPL",
    "gn:name":"Kerodi",
    "gn:population":0,
    "gn:timezone":"Asia/Kolkata",
    "iso:country":"IN",
    "ks:ks_name":"Kerodi",
    "ks:ks_pop":906,
    "ks:ks_type":"VILLAGE",
    "name:eng_x_preferred":[
        "Kerodi"
    ],
    "wof:name":"Kerodi",
    "wof:placetype":"locality",
    "wof:population":906
},
  "geometry": {"coordinates":[75.851266,12.810717],"type":"Point"}
}