{
  "type": "Feature",
  "properties": {
    "iso:country":"IN",
    "ks:ks_name":"Morga",
    "ks:ks_pop":1658,
    "ks:ks_type":"HABITATION",
    "name:eng_x_preferred":[
        "Morga"
    ],
    "wof:name":"Morga",
    "wof:placetype":"locality",
    "wof:population":1658
},
  "geometry": {"coordinates":[82.654105,22.78511],"type":"Point"}
}