{
  "type": "Feature",
  "properties": {
    "iso:country":"IN",
    "ks:ks_name":"Melina Bannige",
    "ks:ks_pop":55,
    "ks:ks_type":"HABITATION",
    "name:eng_x_preferred":[
        "Melina Bannige"
    ],
    "wof:name":"Melina Bannige",
    "wof:placetype":"locality",
    "wof:population":55
},
  "geometry": {"coordinates":[74.807631,14.493421],"type":"Point"}
}