{
  "type": "Feature",
  "properties": {
    "iso:country":"IN",
    "ks:ks_name":"Hydelapur",
    "ks:ks_pop":216,
    "ks:ks_type":"VILLAGE",
    "name:eng_x_preferred":[
        "Hydelapur"
    ],
    "wof:name":"Hydelapur",
    "wof:placetype":"locality",
    "wof:population":216
},
  "geometry": {"coordinates":[78.85255100000001,16.877541],"type":"Point"}
}