{
  "type": "Feature",
  "properties": {
    "iso:country":"IN",
    "ks:ks_name":"Madampoondi",
    "ks:ks_pop":897,
    "ks:ks_type":"VILLAGE",
    "name:eng_x_preferred":[
        "Madampoondi"
    ],
    "wof:name":"Madampoondi",
    "wof:placetype":"locality",
    "wof:population":897
},
  "geometry": {"coordinates":[79.08509100000001,11.943622],"type":"Point"}
}