{
  "type": "Feature",
  "properties": {
    "iso:country":"IN",
    "ks:ks_name":"Danda",
    "ks:ks_pop":414,
    "ks:ks_type":"HABITATION",
    "ks:ks_uagg_main":0,
    "name:eng_x_preferred":[
        "Danda"
    ],
    "wof:name":"Danda",
    "wof:placetype":"neighbourhood",
    "wof:population":414
},
  "geometry": {"coordinates":[82.42657199999999,26.32133],"type":"Point"}
}