{
  "type": "Feature",
  "properties": {
    "iso:country":"IN",
    "ks:ks_name":"Mirzapur",
    "ks:ks_pop":754,
    "ks:ks_type":"VILLAGE",
    "name:eng_x_preferred":[
        "Mirzapur"
    ],
    "wof:name":"Mirzapur",
    "wof:placetype":"locality",
    "wof:population":754
},
  "geometry": {"coordinates":[85.100177,26.061383],"type":"Point"}
}