{
  "type": "Feature",
  "properties": {
    "gn:admin1_code":"28.0",
    "gn:admin2_code":"338",
    "gn:asciiname":"Mele",
    "gn:country_code":"IN",
    "gn:dem":16,
    "gn:feature_class":"P",
    "gn:feature_code":"PPL",
    "gn:name":"Mele",
    "gn:population":0,
    "gn:timezone":"Asia/Kolkata",
    "iso:country":"IN",
    "name:bel_x_preferred":[
        "\u041c\u0435\u043b\u0435"
    ],
    "name:bul_x_preferred":[
        "\u041c\u0435\u043b\u0435"
    ],
    "name:cat_x_preferred":[
        "Mele"
    ],
    "name:ceb_x_preferred":[
        "Mele"
    ],
    "name:deu_x_preferred":[
        "Mele"
    ],
    "name:epo_x_preferred":[
        "Mele"
    ],
    "name:eus_x_preferred":[
        "Mele"
    ],
    "name:fra_x_preferred":[
        "Mele"
    ],
    "name:hun_x_preferred":[
        "Mele"
    ],
    "name:hye_x_preferred":[
        "\u0544\u0565\u056c\u0565"
    ],
    "name:ina_x_preferred":[
        "Mele"
    ],
    "name:ita_x_preferred":[
        "Mele"
    ],
    "name:jpn_x_preferred":[
        "\u30e1\u30fc\u30ec"
    ],
    "name:kaz_x_preferred":[
        "\u041c\u0435\u043b\u0435"
    ],
    "name:lat_x_preferred":[
        "Melae"
    ],
    "name:lmo_x_preferred":[
        "Mele"
    ],
    "name:msa_x_preferred":[
        "Mele"
    ],
    "name:nap_x_preferred":[
        "Mele"
    ],
    "name:nld_x_preferred":[
        "Mele"
    ],
    "name:pms_x_preferred":[
        "Mele"
    ],
    "name:pol_x_preferred":[
        "Mele"
    ],
    "name:por_x_preferred":[
        "Mele"
    ],
    "name:ron_x_preferred":[
        "Mele"
    ],
    "name:rus_x_preferred":[
        "\u041c\u0435\u043b\u0435"
    ],
    "name:scn_x_preferred":[
        "Mele"
    ],
    "name:smo_x_preferred":[
        "Mele"
    ],
    "name:spa_x_preferred":[
        "Mele"
    ],
    "name:srp_x_preferred":[
        "\u041c\u0435\u043b\u0435"
    ],
    "name:ukr_x_preferred":[
        "\u041c\u0435\u043b\u0435"
    ],
    "name:uzb_x_preferred":[
        "Mele"
    ],
    "name:vie_x_preferred":[
        "Mele"
    ],
    "name:vol_x_preferred":[
        "Mele"
    ],
    "name:war_x_preferred":[
        "Mele"
    ],
    "name:zho_x_preferred":[
        "\u6885\u83b1"
    ],
    "wof:name":"Mele",
    "wof:placetype":"neighbourhood"
},
  "geometry": {"coordinates":[88.1352,22.8271],"type":"Point"}
}