{
  "type": "Feature",
  "properties": {
    "iso:country":"IN",
    "ks:ks_alt_nam":"D\u016bndaheri",
    "ks:ks_name":"Dundaheri",
    "ks:ks_type":"VILLAGE",
    "ks:ks_uagg_main":0,
    "name:eng_x_preferred":[
        "Dundaheri"
    ],
    "name:eng_x_variant":[
        "D\u016bndaheri"
    ],
    "wof:name":"Dundaheri",
    "wof:placetype":"neighbourhood"
},
  "geometry": {"coordinates":[77.078502,28.513514],"type":"Point"}
}