{
  "type": "Feature",
  "properties": {
    "iso:country":"IN",
    "ks:ks_alt_nam":"Mub\u0101rakpur",
    "ks:ks_name":"Mubarakpur",
    "ks:ks_pop":208,
    "ks:ks_type":"VILLAGE",
    "ks:ks_uagg_main":0,
    "name:eng_x_preferred":[
        "Mubarakpur"
    ],
    "name:eng_x_variant":[
        "Mub\u0101rakpur"
    ],
    "name:hin_x_preferred":[
        "\u092e\u0941\u092c\u093e\u0930\u0915\u092a\u0941\u0930"
    ],
    "wof:name":"Mubarakpur",
    "wof:placetype":"neighbourhood",
    "wof:population":208
},
  "geometry": {"coordinates":[77.463369,28.483859],"type":"Point"}
}