{
  "type": "Feature",
  "properties": {
    "iso:country":"IN",
    "ks:ks_name":"Nagulwadi m",
    "ks:ks_pop":181,
    "ks:ks_type":"HABITATION",
    "name:eng_x_preferred":[
        "Nagulwadi m"
    ],
    "wof:name":"Nagulwadi m",
    "wof:placetype":"locality",
    "wof:population":181
},
  "geometry": {"coordinates":[80.33273800000001,19.670314],"type":"Point"}
}