{
  "type": "Feature",
  "properties": {
    "gn:admin1_code":"36",
    "gn:admin2_code":"186.0",
    "gn:asciiname":"Pura Jiawan Kharai",
    "gn:country_code":"IN",
    "gn:dem":85,
    "gn:feature_class":"P",
    "gn:feature_code":"PPL",
    "gn:name":"Pura Ji\u0101wan Kharai",
    "gn:population":0,
    "gn:timezone":"Asia/Kolkata",
    "iso:country":"IN",
    "wof:name":"Pura Jiawan Kharai",
    "wof:placetype":"locality"
},
  "geometry": {"coordinates":[82.96188000000002,26.87713],"type":"Point"}
}