{
  "type": "Feature",
  "properties": {
    "iso:country":"IN",
    "ks:ks_alt_nam":"Kale wasti",
    "ks:ks_name":"Kale Wasti",
    "ks:ks_pop":99,
    "ks:ks_type":"HABITATION",
    "name:eng_x_preferred":[
        "Kale Wasti"
    ],
    "wof:name":"Kale Wasti",
    "wof:placetype":"locality",
    "wof:population":99
},
  "geometry": {"coordinates":[75.37248099999999,18.55467],"type":"Point"}
}