{
  "type": "Feature",
  "properties": {
    "gn:admin1_code":"25.0",
    "gn:admin2_code":"633.0",
    "gn:asciiname":"Ammankovilpati",
    "gn:country_code":"IN",
    "gn:dem":316,
    "gn:feature_class":"P",
    "gn:feature_code":"PPL",
    "gn:name":"Ammankovilpati",
    "gn:population":0,
    "gn:timezone":"Asia/Kolkata",
    "iso:country":"IN",
    "name:tam_x_preferred":[
        "\u0b85\u0bae\u0bcd\u0bae\u0ba9\u0bcd\u0b95\u0bcb\u0bb5\u0bbf\u0bb2\u0bcd\u0baa\u0b9f\u0bcd\u0b9f\u0bbf"
    ],
    "wof:name":"Ammankovilpati",
    "wof:placetype":"locality"
},
  "geometry": {"coordinates":[77.39523,11.24193],"type":"Point"}
}