{
  "type": "Feature",
  "properties": {
    "iso:country":"IN",
    "ks:ks_name":"Deshmukh Wasti",
    "ks:ks_pop":129,
    "ks:ks_type":"HABITATION",
    "name:eng_x_preferred":[
        "Deshmukh Wasti"
    ],
    "wof:name":"Deshmukh Wasti",
    "wof:placetype":"locality",
    "wof:population":129
},
  "geometry": {"coordinates":[74.86799999999999,17.974],"type":"Point"}
}