{
  "type": "Feature",
  "properties": {
    "iso:country":"IN",
    "ks:ks_alt_nam":"MALLAH TOLA",
    "ks:ks_name":"Mallah Tola",
    "ks:ks_pop":100,
    "ks:ks_type":"HABITATION",
    "ks:ks_uagg_main":0,
    "name:eng_x_preferred":[
        "Mallah Tola"
    ],
    "wof:name":"Mallah Tola",
    "wof:placetype":"neighbourhood",
    "wof:population":100
},
  "geometry": {"coordinates":[84.325554,25.642079],"type":"Point"}
}