{
  "type": "Feature",
  "properties": {
    "iso:country":"IN",
    "ks:ks_name":"Bhainswal Kalan Mithan",
    "ks:ks_pop":4129,
    "ks:ks_type":"VILLAGE",
    "name:eng_x_preferred":[
        "Bhainswal Kalan Mithan"
    ],
    "wof:name":"Bhainswal Kalan Mithan",
    "wof:placetype":"locality",
    "wof:population":4129
},
  "geometry": {"coordinates":[76.807703,29.035216],"type":"Point"}
}