{
  "type": "Feature",
  "properties": {
    "iso:country":"IN",
    "ks:ks_name":"Gond Mahalla",
    "ks:ks_pop":82,
    "ks:ks_type":"HABITATION",
    "name:eng_x_preferred":[
        "Gond Mahalla"
    ],
    "wof:name":"Gond Mahalla",
    "wof:placetype":"locality",
    "wof:population":82
},
  "geometry": {"coordinates":[84.212616,25.831616],"type":"Point"}
}