{
  "type": "Feature",
  "properties": {
    "iso:country":"IN",
    "ks:ks_alt_nam":"SAMEKIYA H2",
    "ks:ks_name":"Samekiya H2",
    "ks:ks_pop":353,
    "ks:ks_type":"HABITATION",
    "ks:ks_uagg_main":0,
    "name:eng_x_preferred":[
        "Samekiya H2"
    ],
    "wof:name":"Samekiya H2",
    "wof:placetype":"neighbourhood",
    "wof:population":353
},
  "geometry": {"coordinates":[84.500293,25.716437],"type":"Point"}
}