{
  "type": "Feature",
  "properties": {
    "gn:admin1_code":"35",
    "gn:admin2_code":"420.0",
    "gn:asciiname":"Chhidiyapura",
    "gn:country_code":"IN",
    "gn:dem":156,
    "gn:feature_class":"P",
    "gn:feature_code":"PPL",
    "gn:name":"Chhidiy\u0101pura",
    "gn:population":0,
    "gn:timezone":"Asia/Kolkata",
    "iso:country":"IN",
    "ks:ks_name":"Chhidiya Pura",
    "ks:ks_pop":697,
    "ks:ks_type":"HABITATION",
    "ks:ks_uagg_main":0,
    "name:eng_x_preferred":[
        "Chhidiya Pura"
    ],
    "wof:name":"Chhidiya Pura",
    "wof:placetype":"neighbourhood",
    "wof:population":697
},
  "geometry": {"coordinates":[78.724442,26.710317],"type":"Point"}
}