{
  "type": "Feature",
  "properties": {
    "gn:country":"IN",
    "gn:fcode":"PPL",
    "gn:population":20323,
    "iso:country":"IN",
    "name:ast_x_preferred":[
        "Baindur"
    ],
    "name:bul_x_preferred":[
        "\u0411\u0439\u043d\u0434\u043e\u0440"
    ],
    "name:ceb_x_preferred":[
        "Byndoor"
    ],
    "name:eng_x_preferred":[
        "Byndoor"
    ],
    "name:eng_x_variant":[
        "Baindur"
    ],
    "name:kan_x_preferred":[
        "\u0cac\u0cc8\u0c82\u0ca6\u0cc2\u0cb0\u0cc1"
    ],
    "name:mal_x_preferred":[
        "\u0d2c\u0d48\u0d28\u0d4d\u0d26\u0d42\u0d7c"
    ],
    "name:nld_x_preferred":[
        "Baindur"
    ],
    "name:swe_x_preferred":[
        "Byndoor"
    ],
    "name:und_x_variant":[
        "Baind\u016br"
    ],
    "name:urd_x_preferred":[
        "\u0628\u0646\u062f\u0648\u0631"
    ],
    "name:vie_x_preferred":[
        "Byndoor"
    ],
    "qs_pg:aaroncc":"IN",
    "qs_pg:gn_country":"IN",
    "qs_pg:gn_fcode":"PPL",
    "qs_pg:gn_pop":20323,
    "qs_pg:name":"Banur",
    "qs_pg:name_adm0":"India",
    "qs_pg:name_adm1":"Karnataka",
    "qs_pg:photos_9r":0,
    "qs_pg:photos_sr":0,
    "qs_pg:pop_sr":7,
    "qs_pg:qs_pg_placetype":"locality",
    "qs_pg:qs_pg_placetype_gp":"Town",
    "qs_pg:woe_adm0":23424848,
    "woe:adm0_id":23424848,
    "woe:name_adm0":"India",
    "woe:name_adm1":"Karnataka",
    "woe:placetype":"Town",
    "wof:name":"Banur",
    "wof:placetype":"neighbourhood",
    "wof:population":20323
},
  "geometry": {"coordinates":[74.63333,13.86667],"type":"Point"}
}