{
  "type": "Feature",
  "properties": {
    "gn:admin1_code":"36.0",
    "gn:admin2_code":"181.0",
    "gn:asciiname":"Bargadhi",
    "gn:country_code":"IN",
    "gn:dem":113,
    "gn:feature_class":"P",
    "gn:feature_code":"PPL",
    "gn:name":"Bargadhi",
    "gn:population":0,
    "gn:timezone":"Asia/Kolkata",
    "iso:country":"IN",
    "ks:ks_name":"Bargadhi",
    "ks:ks_pop":699,
    "ks:ks_type":"HABITATION",
    "name:eng_x_preferred":[
        "Bargadhi"
    ],
    "wof:name":"Bargadhi",
    "wof:placetype":"locality",
    "wof:population":699
},
  "geometry": {"coordinates":[82.00053699999999,27.457749],"type":"Point"}
}