{
  "type": "Feature",
  "properties": {
    "iso:country":"IN",
    "ks:ks_name":"Makrandpur Urf Makrampur",
    "ks:ks_pop":2201,
    "ks:ks_type":"VILLAGE",
    "name:eng_x_preferred":[
        "Makrandpur Urf Makrampur"
    ],
    "wof:name":"Makrandpur Urf Makrampur",
    "wof:placetype":"locality",
    "wof:population":2201
},
  "geometry": {"coordinates":[85.658152,26.127311],"type":"Point"}
}