{
  "type": "Feature",
  "properties": {
    "iso:country":"IN",
    "ks:ks_name":"Phool Pur",
    "ks:ks_pop":150,
    "ks:ks_type":"HABITATION",
    "name:eng_x_preferred":[
        "Phool Pur"
    ],
    "wof:name":"Phool Pur",
    "wof:placetype":"locality",
    "wof:population":150
},
  "geometry": {"coordinates":[78.441672,25.179311],"type":"Point"}
}