{
  "type": "Feature",
  "properties": {
    "iso:country":"IN",
    "ks:ks_name":"Nagla Tufya",
    "ks:ks_pop":525,
    "ks:ks_type":"HABITATION",
    "name:eng_x_preferred":[
        "Nagla Tufya"
    ],
    "wof:name":"Nagla Tufya",
    "wof:placetype":"locality",
    "wof:population":525
},
  "geometry": {"coordinates":[78.19718899999999,27.816063],"type":"Point"}
}