{
  "type": "Feature",
  "properties": {
    "gn:admin1_code":"39.0",
    "gn:admin2_code":"64.0",
    "gn:asciiname":"Gajar",
    "gn:country_code":"IN",
    "gn:dem":1214,
    "gn:feature_class":"P",
    "gn:feature_code":"PPL",
    "gn:name":"Gaj\u0101r",
    "gn:population":0,
    "gn:timezone":"Asia/Kolkata",
    "iso:country":"IN",
    "ks:ks_alt_nam":"Gaj\u0101r",
    "ks:ks_name":"Gajar",
    "ks:ks_type":"VILLAGE",
    "name:eng_x_preferred":[
        "Gajar"
    ],
    "name:eng_x_variant":[
        "Gaj\u0101r"
    ],
    "wof:name":"Gajar",
    "wof:placetype":"locality"
},
  "geometry": {"coordinates":[79.447923,29.933192],"type":"Point"}
}