{
  "type": "Feature",
  "properties": {
    "iso:country":"IN",
    "ks:ks_name":"Gosaijika Dhora",
    "ks:ks_pop":517,
    "ks:ks_type":"HABITATION",
    "name:eng_x_preferred":[
        "Gosaijika Dhora"
    ],
    "wof:name":"Gosaijika Dhora",
    "wof:placetype":"locality",
    "wof:population":517
},
  "geometry": {"coordinates":[73.09014999999999,27.180511],"type":"Point"}
}