{
  "type": "Feature",
  "properties": {
    "iso:country":"IN",
    "ks:ks_name":"Senkuzhi",
    "ks:ks_pop":501,
    "ks:ks_type":"HABITATION",
    "name:eng_x_preferred":[
        "Senkuzhi"
    ],
    "wof:name":"Senkuzhi",
    "wof:placetype":"locality",
    "wof:population":501
},
  "geometry": {"coordinates":[79.20822800000001,11.072872],"type":"Point"}
}