{
  "type": "Feature",
  "properties": {
    "iso:country":"IN",
    "ks:ks_alt_nam":"DONDLE WAIFALKAR BHOSALE PAWARVASTI",
    "ks:ks_name":"Dondle Waifalkar Bhosale Pawarvasti",
    "ks:ks_pop":77,
    "ks:ks_type":"HABITATION",
    "name:eng_x_preferred":[
        "Dondle Waifalkar Bhosale Pawarvasti"
    ],
    "wof:name":"Dondle Waifalkar Bhosale Pawarvasti",
    "wof:placetype":"locality",
    "wof:population":77
},
  "geometry": {"coordinates":[75.529574,17.016855],"type":"Point"}
}