{
  "type": "Feature",
  "properties": {
    "iso:country":"IN",
    "ks:ks_name":"Doddi",
    "ks:ks_pop":322,
    "ks:ks_type":"HABITATION",
    "name:eng_x_preferred":[
        "Doddi"
    ],
    "wof:name":"Doddi",
    "wof:placetype":"locality",
    "wof:population":322
},
  "geometry": {"coordinates":[75.686502,13.308145],"type":"Point"}
}