{
  "type": "Feature",
  "properties": {
    "iso:country":"IN",
    "ks:ks_name":"Gamayanmane",
    "ks:ks_pop":44,
    "ks:ks_type":"HABITATION",
    "name:eng_x_preferred":[
        "Gamayanmane"
    ],
    "wof:name":"Gamayanmane",
    "wof:placetype":"locality",
    "wof:population":44
},
  "geometry": {"coordinates":[74.716537,14.682548],"type":"Point"}
}