{
  "type": "Feature",
  "properties": {
    "iso:country":"IN",
    "ks:ks_name":"Musalmanwadi",
    "ks:ks_pop":78,
    "ks:ks_type":"HABITATION",
    "name:eng_x_preferred":[
        "Musalmanwadi"
    ],
    "wof:name":"Musalmanwadi",
    "wof:placetype":"locality",
    "wof:population":78
},
  "geometry": {"coordinates":[73.45959000000001,16.41715],"type":"Point"}
}