{
  "type": "Feature",
  "properties": {
    "iso:country":"IN",
    "ks:ks_name":"Safarda",
    "ks:ks_pop":633,
    "ks:ks_type":"VILLAGE",
    "ks:ks_uagg_main":0,
    "name:eng_x_preferred":[
        "Safarda"
    ],
    "wof:name":"Safarda",
    "wof:placetype":"neighbourhood",
    "wof:population":633
},
  "geometry": {"coordinates":[88.16029,23.400308],"type":"Point"}
}