{
  "type": "Feature",
  "properties": {
    "iso:country":"IN",
    "ks:ks_name":"Badavathanda",
    "ks:ks_pop":375,
    "ks:ks_type":"HABITATION",
    "ks:ks_uagg_main":0,
    "name:eng_x_preferred":[
        "Badavathanda"
    ],
    "wof:name":"Badavathanda",
    "wof:placetype":"neighbourhood",
    "wof:population":375
},
  "geometry": {"coordinates":[79.804672,16.8013],"type":"Point"}
}