{
  "type": "Feature",
  "properties": {
    "iso:country":"IN",
    "ks:ks_name":"Kuldadihi",
    "ks:ks_pop":394,
    "ks:ks_type":"VILLAGE",
    "name:eng_x_preferred":[
        "Kuldadihi"
    ],
    "wof:name":"Kuldadihi",
    "wof:placetype":"locality",
    "wof:population":394
},
  "geometry": {"coordinates":[81.791524,19.919442],"type":"Point"}
}