{
  "type": "Feature",
  "properties": {
    "iso:country":"IN",
    "ks:ks_alt_nam":"AJJIKODIGE",
    "ks:ks_name":"Ajjikodige",
    "ks:ks_pop":74,
    "ks:ks_type":"HABITATION",
    "name:eng_x_preferred":[
        "Ajjikodige"
    ],
    "wof:name":"Ajjikodige",
    "wof:placetype":"locality",
    "wof:population":74
},
  "geometry": {"coordinates":[75.221616,13.605964],"type":"Point"}
}