{
  "type": "Feature",
  "properties": {
    "gn:admin1_code":"36",
    "gn:admin2_code":"176.0",
    "gn:asciiname":"Karimabad",
    "gn:country_code":"IN",
    "gn:dem":124,
    "gn:feature_class":"P",
    "gn:feature_code":"PPL",
    "gn:name":"Kar\u012bm\u0101b\u0101d",
    "gn:population":0,
    "gn:timezone":"Asia/Kolkata",
    "iso:country":"IN",
    "name:aze_x_preferred":[
        "K\u0259rimabad"
    ],
    "name:deu_x_preferred":[
        "Karimabad"
    ],
    "name:fas_x_preferred":[
        "\u06a9\u0631\u06cc\u0645\u200c\u0622\u0628\u0627\u062f"
    ],
    "name:ita_x_preferred":[
        "Karimabad"
    ],
    "wof:name":"Karimabad",
    "wof:placetype":"locality"
},
  "geometry": {"coordinates":[81.29397,27.09852],"type":"Point"}
}