{
  "type": "Feature",
  "properties": {
    "gn:admin1_code":"11.0",
    "gn:admin2_code":"27.0",
    "gn:asciiname":"Moru",
    "gn:country_code":"IN",
    "gn:dem":1745,
    "gn:feature_class":"P",
    "gn:feature_code":"PPL",
    "gn:name":"Moru",
    "gn:population":0,
    "gn:timezone":"Asia/Kolkata",
    "iso:country":"IN",
    "name:ast_x_preferred":[
        "Moru"
    ],
    "name:ceb_x_preferred":[
        "Moru"
    ],
    "name:swe_x_preferred":[
        "Moru"
    ],
    "wof:name":"Moru",
    "wof:placetype":"locality"
},
  "geometry": {"coordinates":[77.11879,31.30256],"type":"Point"}
}