{
  "type": "Feature",
  "properties": {
    "iso:country":"IN",
    "ks:ks_name":"Hapania",
    "ks:ks_pop":2085,
    "ks:ks_type":"VILLAGE",
    "ks:ks_uagg_main":0,
    "name:eng_x_preferred":[
        "Hapania"
    ],
    "wof:name":"Hapania",
    "wof:placetype":"locality",
    "wof:population":2085
},
  "geometry": {"coordinates":[88.64323400000001,22.929783],"type":"Point"}
}