{
  "type": "Feature",
  "properties": {
    "iso:country":"IN",
    "ks:ks_name":"Dindikoppa",
    "ks:ks_pop":19,
    "ks:ks_type":"HABITATION",
    "name:eng_x_preferred":[
        "Dindikoppa"
    ],
    "wof:name":"Dindikoppa",
    "wof:placetype":"locality",
    "wof:population":19
},
  "geometry": {"coordinates":[74.87546500000001,14.035559],"type":"Point"}
}