{
  "type": "Feature",
  "properties": {
    "iso:country":"IN",
    "ks:ks_alt_nam":"BOLARAHAMAN T",
    "ks:ks_name":"Bolarahaman T",
    "ks:ks_pop":282,
    "ks:ks_type":"HABITATION",
    "name:eng_x_preferred":[
        "Bolarahaman T"
    ],
    "wof:name":"Bolarahaman T",
    "wof:placetype":"locality",
    "wof:population":282
},
  "geometry": {"coordinates":[86.66148200000001,25.45042],"type":"Point"}
}