{
  "type": "Feature",
  "properties": {
    "iso:country":"IN",
    "ks:ks_name":"Varachiwadi",
    "ks:ks_pop":268,
    "ks:ks_type":"HABITATION",
    "name:eng_x_preferred":[
        "Varachiwadi"
    ],
    "wof:name":"Varachiwadi",
    "wof:placetype":"locality",
    "wof:population":268
},
  "geometry": {"coordinates":[73.762393,16.16956],"type":"Point"}
}