{
  "type": "Feature",
  "properties": {
    "iso:country":"IN",
    "ks:ks_name":"Konibail",
    "ks:ks_pop":1065,
    "ks:ks_type":"HABITATION",
    "name:eng_x_preferred":[
        "Konibail"
    ],
    "wof:name":"Konibail",
    "wof:placetype":"locality",
    "wof:population":1065
},
  "geometry": {"coordinates":[74.98689,12.760581],"type":"Point"}
}