{
  "type": "Feature",
  "properties": {
    "iso:country":"IN",
    "ks:ks_name":"Jasipur",
    "ks:ks_pop":50,
    "ks:ks_type":"VILLAGE",
    "name:eng_x_preferred":[
        "Jasipur"
    ],
    "wof:name":"Jasipur",
    "wof:placetype":"locality",
    "wof:population":50
},
  "geometry": {"coordinates":[84.951883,20.454276],"type":"Point"}
}