{
  "type": "Feature",
  "properties": {
    "gn:admin1_code":"36",
    "gn:admin2_code":"134.0",
    "gn:asciiname":"Milak",
    "gn:country_code":"IN",
    "gn:dem":259,
    "gn:feature_class":"P",
    "gn:feature_code":"PPL",
    "gn:name":"Milak",
    "gn:population":0,
    "gn:timezone":"Asia/Kolkata",
    "iso:country":"IN",
    "name:bpy_x_preferred":[
        "\u09ae\u09bf\u09b2\u09be\u0995"
    ],
    "name:ceb_x_preferred":[
        "Milak"
    ],
    "name:ita_x_preferred":[
        "Milak"
    ],
    "name:mlg_x_preferred":[
        "Milak"
    ],
    "name:msa_x_preferred":[
        "Milak"
    ],
    "name:new_x_preferred":[
        "\u092e\u093f\u0932\u0915"
    ],
    "name:nld_x_preferred":[
        "Milak"
    ],
    "name:pol_x_preferred":[
        "Milak"
    ],
    "name:por_x_preferred":[
        "Milak"
    ],
    "name:swe_x_preferred":[
        "Milak"
    ],
    "name:urd_x_preferred":[
        "\u0645\u06cc\u0644\u06a9"
    ],
    "name:vie_x_preferred":[
        "Milak"
    ],
    "name:zho_x_preferred":[
        "\u7c73\u62c9\u514b"
    ],
    "wof:name":"Milak",
    "wof:placetype":"neighbourhood"
},
  "geometry": {"coordinates":[78.33497,29.54477],"type":"Point"}
}