{
  "type": "Feature",
  "properties": {
    "iso:country":"IN",
    "ks:ks_name":"Vehare",
    "ks:ks_pop":426,
    "ks:ks_type":"VILLAGE",
    "name:eng_x_preferred":[
        "Vehare"
    ],
    "wof:name":"Vehare",
    "wof:placetype":"locality",
    "wof:population":426
},
  "geometry": {"coordinates":[73.396389,19.226111],"type":"Point"}
}