{
  "type": "Feature",
  "properties": {
    "iso:country":"IN",
    "ks:ks_name":"Bhagia",
    "ks:ks_pop":409,
    "ks:ks_type":"HABITATION",
    "ks:ks_uagg_main":0,
    "name:eng_x_preferred":[
        "Bhagia"
    ],
    "wof:name":"Bhagia",
    "wof:placetype":"neighbourhood",
    "wof:population":409
},
  "geometry": {"coordinates":[79.984915,27.010217],"type":"Point"}
}