{
  "type": "Feature",
  "properties": {
    "iso:country":"IN",
    "ks:ks_name":"Padri",
    "ks:ks_type":"VILLAGE",
    "name:eng_x_preferred":[
        "Padri"
    ],
    "wof:name":"Padri",
    "wof:placetype":"locality"
},
  "geometry": {"coordinates":[84.07780200000001,26.830909],"type":"Point"}
}