{
  "type": "Feature",
  "properties": {
    "iso:country":"IN",
    "ks:ks_name":"Bahoni",
    "ks:ks_pop":78,
    "ks:ks_type":"HABITATION",
    "ks:ks_uagg_main":0,
    "name:eng_x_preferred":[
        "Bahoni"
    ],
    "wof:name":"Bahoni",
    "wof:placetype":"neighbourhood",
    "wof:population":78
},
  "geometry": {"coordinates":[93.177221,26.071049],"type":"Point"}
}