{
  "type": "Feature",
  "properties": {
    "iso:country":"IN",
    "ks:ks_name":"Laliabari",
    "ks:ks_pop":7024,
    "ks:ks_type":"VILLAGE",
    "name:eng_x_preferred":[
        "Laliabari"
    ],
    "wof:name":"Laliabari",
    "wof:placetype":"locality",
    "wof:population":7024
},
  "geometry": {"coordinates":[87.919915,25.28788],"type":"Point"}
}