{
  "type": "Feature",
  "properties": {
    "iso:country":"IN",
    "ks:ks_name":"Rampur Ratnakar",
    "ks:ks_pop":1453,
    "ks:ks_type":"VILLAGE",
    "name:eng_x_preferred":[
        "Rampur Ratnakar"
    ],
    "wof:name":"Rampur Ratnakar",
    "wof:placetype":"locality",
    "wof:population":1453
},
  "geometry": {"coordinates":[85.313131,25.795191],"type":"Point"}
}