{
  "type": "Feature",
  "properties": {
    "iso:country":"IN",
    "ks:ks_name":"Bijadih",
    "ks:ks_pop":288,
    "ks:ks_type":"HABITATION",
    "name:eng_x_preferred":[
        "Bijadih"
    ],
    "wof:name":"Bijadih",
    "wof:placetype":"locality",
    "wof:population":288
},
  "geometry": {"coordinates":[84.42362300000001,22.414242],"type":"Point"}
}