{
  "type": "Feature",
  "properties": {
    "gn:admin1_code":"19",
    "gn:admin2_code":"580.0",
    "gn:asciiname":"Yalisati",
    "gn:country_code":"IN",
    "gn:dem":405,
    "gn:feature_class":"P",
    "gn:feature_code":"PPL",
    "gn:name":"Yalisati",
    "gn:population":0,
    "gn:timezone":"Asia/Kolkata",
    "iso:country":"IN",
    "wof:name":"Yalisati",
    "wof:placetype":"locality"
},
  "geometry": {"coordinates":[77.36171,16.68464],"type":"Point"}
}