{
  "type": "Feature",
  "properties": {
    "iso:country":"IN",
    "ks:ks_name":"Bargad Purwa",
    "ks:ks_pop":21,
    "ks:ks_type":"HABITATION",
    "name:eng_x_preferred":[
        "Bargad Purwa"
    ],
    "wof:name":"Bargad Purwa",
    "wof:placetype":"locality",
    "wof:population":21
},
  "geometry": {"coordinates":[81.51826699999999,27.724838],"type":"Point"}
}