{
  "type": "Feature",
  "properties": {
    "gn:admin1_code":"10.0",
    "gn:admin2_code":"69.0",
    "gn:asciiname":"Chhan",
    "gn:country_code":"IN",
    "gn:dem":1050,
    "gn:feature_class":"P",
    "gn:feature_code":"PPL",
    "gn:name":"Chh\u0101n",
    "gn:population":0,
    "gn:timezone":"Asia/Kolkata",
    "iso:country":"IN",
    "wof:name":"Chhan",
    "wof:placetype":"locality"
},
  "geometry": {"coordinates":[77.09102,30.71802000000001],"type":"Point"}
}