{
  "type": "Feature",
  "properties": {
    "iso:country":"IN",
    "ks:ks_name":"1 APD",
    "ks:ks_pop":284,
    "ks:ks_type":"VILLAGE",
    "name:eng_x_preferred":[
        "1 APD"
    ],
    "wof:name":"1 APD",
    "wof:placetype":"locality",
    "wof:population":284
},
  "geometry": {"coordinates":[73.38146,29.313757],"type":"Point"}
}