{
  "type": "Feature",
  "properties": {
    "iso:country":"IN",
    "ks:ks_name":"Holi Falia",
    "ks:ks_pop":626,
    "ks:ks_type":"HABITATION",
    "name:eng_x_preferred":[
        "Holi Falia"
    ],
    "wof:name":"Holi Falia",
    "wof:placetype":"locality",
    "wof:population":626
},
  "geometry": {"coordinates":[74.08494399999999,23.120139],"type":"Point"}
}