{
  "type": "Feature",
  "properties": {
    "iso:country":"IN",
    "ks:ks_name":"Jhargaon",
    "ks:ks_pop":1303,
    "ks:ks_type":"VILLAGE",
    "ks:ks_uagg_main":0,
    "name:eng_x_preferred":[
        "Jhargaon"
    ],
    "wof:name":"Jhargaon",
    "wof:placetype":"neighbourhood",
    "wof:population":1303
},
  "geometry": {"coordinates":[92.263023,26.659798],"type":"Point"}
}