{
  "type": "Feature",
  "properties": {
    "iso:country":"IN",
    "ks:ks_name":"Purani Matapung No-2",
    "ks:ks_pop":1398,
    "ks:ks_type":"VILLAGE",
    "name:eng_x_preferred":[
        "Purani Matapung No-2"
    ],
    "wof:name":"Purani Matapung No-2",
    "wof:placetype":"locality",
    "wof:population":1398
},
  "geometry": {"coordinates":[95.400057,27.553303],"type":"Point"}
}