{
  "type": "Feature",
  "properties": {
    "iso:country":"IN",
    "ks:ks_name":"Durgapur Bangaon",
    "ks:ks_pop":1277,
    "ks:ks_type":"VILLAGE",
    "name:eng_x_preferred":[
        "Durgapur Bangaon"
    ],
    "wof:name":"Durgapur Bangaon",
    "wof:placetype":"locality",
    "wof:population":1277
},
  "geometry": {"coordinates":[87.68223399999999,26.254117],"type":"Point"}
}