{
  "type": "Feature",
  "properties": {
    "iso:country":"IN",
    "ks:ks_alt_nam":"M\u0101ngli",
    "ks:ks_name":"Mangli",
    "ks:ks_type":"VILLAGE",
    "name:eng_x_preferred":[
        "Mangli"
    ],
    "name:eng_x_variant":[
        "M\u0101ngli"
    ],
    "wof:name":"Mangli",
    "wof:placetype":"locality"
},
  "geometry": {"coordinates":[78.355602,20.066045],"type":"Point"}
}