{
  "type": "Feature",
  "properties": {
    "gn:admin1_code":"25.0",
    "gn:admin2_code":"620.0",
    "gn:asciiname":"Sakkaraisamantam",
    "gn:country_code":"IN",
    "gn:dem":46,
    "gn:feature_class":"P",
    "gn:feature_code":"PPL",
    "gn:name":"Sakkarais\u0101mantam",
    "gn:population":0,
    "gn:timezone":"Asia/Kolkata",
    "iso:country":"IN",
    "ks:ks_name":"Sakkarasamandam",
    "ks:ks_pop":1066,
    "ks:ks_type":"VILLAGE",
    "name:eng_x_preferred":[
        "Sakkarasamandam"
    ],
    "name:eng_x_variant":[
        "Sakkaraisamantam"
    ],
    "wof:name":"Sakkarasamandam",
    "wof:placetype":"locality",
    "wof:population":1066
},
  "geometry": {"coordinates":[79.08875999999999,10.807443],"type":"Point"}
}