{
  "type": "Feature",
  "properties": {
    "iso:country":"IN",
    "ks:ks_name":"Tulasi",
    "ks:ks_pop":879,
    "ks:ks_type":"VILLAGE",
    "name:eng_x_preferred":[
        "Tulasi"
    ],
    "wof:name":"Tulasi",
    "wof:placetype":"locality",
    "wof:population":879
},
  "geometry": {"coordinates":[81.979544,18.681403],"type":"Point"}
}