{
  "type": "Feature",
  "properties": {
    "iso:country":"IN",
    "ks:ks_name":"Jareikera",
    "ks:ks_pop":410,
    "ks:ks_type":"VILLAGE",
    "name:eng_x_preferred":[
        "Jareikera"
    ],
    "wof:name":"Jareikera",
    "wof:placetype":"locality",
    "wof:population":410
},
  "geometry": {"coordinates":[82.497215,19.003447],"type":"Point"}
}