{
  "type": "Feature",
  "properties": {
    "iso:country":"IN",
    "ks:ks_name":"Chamta Das Para",
    "ks:ks_pop":614,
    "ks:ks_type":"HABITATION",
    "name:eng_x_preferred":[
        "Chamta Das Para"
    ],
    "wof:name":"Chamta Das Para",
    "wof:placetype":"locality",
    "wof:population":614
},
  "geometry": {"coordinates":[89.66379499999999,26.294477],"type":"Point"}
}