{
  "type": "Feature",
  "properties": {
    "gn:admin1_code":"21",
    "gn:admin2_code":"398.0",
    "gn:asciiname":"Kodikal",
    "gn:country_code":"IN",
    "gn:dem":914,
    "gn:feature_class":"P",
    "gn:feature_code":"PPL",
    "gn:name":"Kodikal",
    "gn:population":0,
    "gn:timezone":"Asia/Kolkata",
    "iso:country":"IN",
    "wof:name":"Kodikal",
    "wof:placetype":"locality"
},
  "geometry": {"coordinates":[82.76693,18.3632],"type":"Point"}
}