{
  "type": "Feature",
  "properties": {
    "iso:country":"IN",
    "ks:ks_name":"Pure Dilip Shah",
    "ks:ks_pop":126,
    "ks:ks_type":"HABITATION",
    "name:eng_x_preferred":[
        "Pure Dilip Shah"
    ],
    "wof:name":"Pure Dilip Shah",
    "wof:placetype":"locality",
    "wof:population":126
},
  "geometry": {"coordinates":[81.5346,26.416],"type":"Point"}
}