{
  "type": "Feature",
  "properties": {
    "gn:admin1_code":"36",
    "gn:admin2_code":"194.0",
    "gn:asciiname":"Mahrupur",
    "gn:country_code":"IN",
    "gn:dem":85,
    "gn:feature_class":"P",
    "gn:feature_code":"PPL",
    "gn:name":"Mahr\u016bpur",
    "gn:population":0,
    "gn:timezone":"Asia/Kolkata",
    "iso:country":"IN",
    "ks:ks_alt_nam":"Mahr\u016bpur",
    "ks:ks_name":"Mahrupur",
    "ks:ks_pop":2353,
    "ks:ks_type":"VILLAGE",
    "ks:ks_uagg_main":0,
    "name:eng_x_preferred":[
        "Mahrupur"
    ],
    "name:eng_x_variant":[
        "Mahr\u016bpur"
    ],
    "wof:name":"Mahrupur",
    "wof:placetype":"neighbourhood",
    "wof:population":2353
},
  "geometry": {"coordinates":[82.704104,25.697091],"type":"Point"}
}