{
  "type": "Feature",
  "properties": {
    "gn:admin1_code":"38.0",
    "gn:admin2_code":"347.0",
    "gn:asciiname":"Ichatu",
    "gn:country_code":"IN",
    "gn:dem":416,
    "gn:feature_class":"P",
    "gn:feature_code":"PPL",
    "gn:name":"Ich\u0101tu",
    "gn:population":0,
    "gn:timezone":"Asia/Kolkata",
    "iso:country":"IN",
    "ks:ks_alt_nam":"Ich\u0101tu",
    "ks:ks_name":"Ichatu",
    "ks:ks_pop":252,
    "ks:ks_type":"VILLAGE",
    "name:eng_x_preferred":[
        "Ichatu"
    ],
    "name:eng_x_variant":[
        "Ich\u0101tu"
    ],
    "wof:name":"Ichatu",
    "wof:placetype":"locality",
    "wof:population":252
},
  "geometry": {"coordinates":[84.675569,24.231123],"type":"Point"}
}