{
  "type": "Feature",
  "properties": {
    "iso:country":"IN",
    "ks:ks_name":"Kothapalli",
    "ks:ks_pop":87,
    "ks:ks_type":"HABITATION",
    "name:eng_x_preferred":[
        "Kothapalli"
    ],
    "wof:name":"Kothapalli",
    "wof:placetype":"locality",
    "wof:population":87
},
  "geometry": {"coordinates":[79.317334,18.062852],"type":"Point"}
}