{
  "type": "Feature",
  "properties": {
    "iso:country":"IN",
    "ks:ks_name":"Nokhroy Bongali Gaon",
    "ks:ks_pop":268,
    "ks:ks_type":"VILLAGE",
    "name:eng_x_preferred":[
        "Nokhroy Bongali Gaon"
    ],
    "wof:name":"Nokhroy Bongali Gaon",
    "wof:placetype":"locality",
    "wof:population":268
},
  "geometry": {"coordinates":[95.319819,27.507538],"type":"Point"}
}