{
  "type": "Feature",
  "properties": {
    "gn:admin1_code":"2.0",
    "gn:admin2_code":"543.0",
    "gn:asciiname":"Loddalupadu",
    "gn:country_code":"IN",
    "gn:dem":278,
    "gn:feature_class":"P",
    "gn:feature_code":"PPL",
    "gn:name":"Loddalup\u0101du",
    "gn:population":0,
    "gn:timezone":"Asia/Kolkata",
    "iso:country":"IN",
    "wof:name":"Loddalupadu",
    "wof:placetype":"locality"
},
  "geometry": {"coordinates":[83.43236999999998,18.9273],"type":"Point"}
}