{
  "type": "Feature",
  "properties": {
    "iso:country":"IN",
    "ks:ks_name":"Dongarewadi",
    "ks:ks_pop":268,
    "ks:ks_type":"HABITATION",
    "name:eng_x_preferred":[
        "Dongarewadi"
    ],
    "wof:name":"Dongarewadi",
    "wof:placetype":"locality",
    "wof:population":268
},
  "geometry": {"coordinates":[73.779275,16.419533],"type":"Point"}
}