{
  "type": "Feature",
  "properties": {
    "iso:country":"IN",
    "ks:ks_name":"Dhemsaguda",
    "ks:ks_pop":93,
    "ks:ks_type":"HABITATION",
    "name:eng_x_preferred":[
        "Dhemsaguda"
    ],
    "wof:name":"Dhemsaguda",
    "wof:placetype":"locality",
    "wof:population":93
},
  "geometry": {"coordinates":[82.872185,18.4838],"type":"Point"}
}