{
  "type": "Feature",
  "properties": {
    "iso:country":"IN",
    "ks:ks_name":"Ranghopur",
    "ks:ks_pop":0,
    "ks:ks_type":"VILLAGE",
    "name:eng_x_preferred":[
        "Ranghopur"
    ],
    "wof:name":"Ranghopur",
    "wof:placetype":"locality",
    "wof:population":0
},
  "geometry": {"coordinates":[79.321865,28.362505],"type":"Point"}
}