{
  "type": "Feature",
  "properties": {
    "iso:country":"IN",
    "ks:ks_name":"Chapaphuli",
    "ks:ks_pop":160,
    "ks:ks_type":"VILLAGE",
    "name:eng_x_preferred":[
        "Chapaphuli"
    ],
    "wof:name":"Chapaphuli",
    "wof:placetype":"locality",
    "wof:population":160
},
  "geometry": {"coordinates":[87.40503099999999,24.012578],"type":"Point"}
}