{
  "type": "Feature",
  "properties": {
    "iso:country":"IN",
    "ks:ks_name":"Tibisinga",
    "ks:ks_pop":743,
    "ks:ks_type":"VILLAGE",
    "name:eng_x_preferred":[
        "Tibisinga"
    ],
    "wof:name":"Tibisinga",
    "wof:placetype":"locality",
    "wof:population":743
},
  "geometry": {"coordinates":[84.07396799999999,18.917667],"type":"Point"}
}