{
  "type": "Feature",
  "properties": {
    "gn:admin1_code":"34.0",
    "gn:admin2_code":"210.0",
    "gn:asciiname":"Barbata",
    "gn:country_code":"IN",
    "gn:dem":49,
    "gn:feature_class":"P",
    "gn:feature_code":"PPL",
    "gn:name":"Barbata",
    "gn:population":0,
    "gn:timezone":"Asia/Kolkata",
    "iso:country":"IN",
    "wof:name":"Barbata",
    "wof:placetype":"locality"
},
  "geometry": {"coordinates":[87.75399,26.12829],"type":"Point"}
}