{
  "type": "Feature",
  "properties": {
    "iso:country":"IN",
    "ks:ks_name":"Simri Yadab Tola",
    "ks:ks_pop":420,
    "ks:ks_type":"HABITATION",
    "name:eng_x_preferred":[
        "Simri Yadab Tola"
    ],
    "wof:name":"Simri Yadab Tola",
    "wof:placetype":"locality",
    "wof:population":420
},
  "geometry": {"coordinates":[86.817291,25.900375],"type":"Point"}
}