{
  "type": "Feature",
  "properties": {
    "iso:country":"IN",
    "ks:ks_name":"Fuljhar",
    "ks:ks_pop":140,
    "ks:ks_type":"VILLAGE",
    "name:eng_x_preferred":[
        "Fuljhar"
    ],
    "wof:name":"Fuljhar",
    "wof:placetype":"locality",
    "wof:population":140
},
  "geometry": {"coordinates":[85.03919,21.822158],"type":"Point"}
}