{
  "type": "Feature",
  "properties": {
    "iso:country":"IN",
    "ks:ks_name":"Baghmunda",
    "ks:ks_pop":634,
    "ks:ks_type":"VILLAGE",
    "name:eng_x_preferred":[
        "Baghmunda"
    ],
    "wof:name":"Baghmunda",
    "wof:placetype":"locality",
    "wof:population":634
},
  "geometry": {"coordinates":[87.25884499999999,24.669121],"type":"Point"}
}