{
  "type": "Feature",
  "properties": {
    "iso:country":"IN",
    "ks:ks_name":"1 CS",
    "ks:ks_pop":94,
    "ks:ks_type":"VILLAGE",
    "name:eng_x_preferred":[
        "1 CS"
    ],
    "wof:name":"1 CS",
    "wof:placetype":"locality",
    "wof:population":94
},
  "geometry": {"coordinates":[74.264464,29.380522],"type":"Point"}
}