{
  "type": "Feature",
  "properties": {
    "iso:country":"IN",
    "ks:ks_alt_nam":"pahantoli",
    "ks:ks_name":"Pahantoli",
    "ks:ks_pop":390,
    "ks:ks_type":"HABITATION",
    "name:eng_x_preferred":[
        "Pahantoli"
    ],
    "wof:name":"Pahantoli",
    "wof:placetype":"locality",
    "wof:population":390
},
  "geometry": {"coordinates":[84.692652,23.068022],"type":"Point"}
}