{
  "type": "Feature",
  "properties": {
    "iso:country":"IN",
    "ks:ks_name":"Joshiwadi",
    "ks:ks_pop":95,
    "ks:ks_type":"HABITATION",
    "name:eng_x_preferred":[
        "Joshiwadi"
    ],
    "wof:name":"Joshiwadi",
    "wof:placetype":"locality",
    "wof:population":95
},
  "geometry": {"coordinates":[73.5425,17.385278],"type":"Point"}
}