{
  "type": "Feature",
  "properties": {
    "gn:admin1_code":"37.0",
    "gn:admin2_code":"416.0",
    "gn:asciiname":"Siyanar",
    "gn:country_code":"IN",
    "gn:dem":351,
    "gn:feature_class":"P",
    "gn:feature_code":"PPL",
    "gn:name":"Siy\u0101n\u0101r",
    "gn:population":0,
    "gn:timezone":"Asia/Kolkata",
    "iso:country":"IN",
    "ks:ks_alt_nam":"Siy\u0101n\u0101r",
    "ks:ks_name":"Siyanar",
    "ks:ks_pop":231,
    "ks:ks_type":"VILLAGE",
    "name:eng_x_preferred":[
        "Siyanar"
    ],
    "name:eng_x_variant":[
        "Siy\u0101n\u0101r"
    ],
    "wof:name":"Siyanar",
    "wof:placetype":"locality",
    "wof:population":231
},
  "geometry": {"coordinates":[81.296645,18.963091],"type":"Point"}
}