{
  "type": "Feature",
  "properties": {
    "iso:country":"IN",
    "ks:ks_name":"Mograwadi",
    "ks:ks_pop":1921,
    "ks:ks_type":"VILLAGE",
    "name:eng_x_preferred":[
        "Mograwadi"
    ],
    "wof:name":"Mograwadi",
    "wof:placetype":"locality",
    "wof:population":1921
},
  "geometry": {"coordinates":[73.126886,20.693946],"type":"Point"}
}