{
  "type": "Feature",
  "properties": {
    "iso:country":"IN",
    "ks:ks_name":"Machali",
    "ks:ks_pop":225,
    "ks:ks_type":"VILLAGE",
    "name:eng_x_preferred":[
        "Machali"
    ],
    "wof:name":"Machali",
    "wof:placetype":"locality",
    "wof:population":225
},
  "geometry": {"coordinates":[74.52503,15.465948],"type":"Point"}
}