{
  "type": "Feature",
  "properties": {
    "iso:country":"IN",
    "ks:ks_name":"Endalkarai",
    "ks:ks_pop":140,
    "ks:ks_type":"HABITATION",
    "name:eng_x_preferred":[
        "Endalkarai"
    ],
    "wof:name":"Endalkarai",
    "wof:placetype":"locality",
    "wof:population":140
},
  "geometry": {"coordinates":[78.773286,9.761792],"type":"Point"}
}