{
  "type": "Feature",
  "properties": {
    "iso:country":"IN",
    "ks:ks_name":"Sagahan No 1",
    "ks:ks_pop":199,
    "ks:ks_type":"HABITATION",
    "name:eng_x_preferred":[
        "Sagahan No 1"
    ],
    "wof:name":"Sagahan No 1",
    "wof:placetype":"locality",
    "wof:population":199
},
  "geometry": {"coordinates":[81.96307299999999,24.746088],"type":"Point"}
}