{
  "type": "Feature",
  "properties": {
    "iso:country":"IN",
    "ks:ks_name":"Dudhpatil Pt I",
    "ks:ks_pop":498,
    "ks:ks_type":"VILLAGE",
    "name:eng_x_preferred":[
        "Dudhpatil Pt I"
    ],
    "wof:name":"Dudhpatil Pt I",
    "wof:placetype":"locality",
    "wof:population":498
},
  "geometry": {"coordinates":[92.796453,24.887843],"type":"Point"}
}