{
  "type": "Feature",
  "properties": {
    "iso:country":"IN",
    "ks:ks_name":"Pahladpur",
    "ks:ks_pop":3016,
    "ks:ks_type":"VILLAGE",
    "name:eng_x_preferred":[
        "Pahladpur"
    ],
    "wof:name":"Pahladpur",
    "wof:placetype":"locality",
    "wof:population":3016
},
  "geometry": {"coordinates":[85.442166,26.079915],"type":"Point"}
}