{
  "type": "Feature",
  "properties": {
    "iso:country":"IN",
    "ks:ks_name":"South Jaridharia",
    "ks:ks_pop":843,
    "ks:ks_type":"HABITATION",
    "name:eng_x_preferred":[
        "South Jaridharia"
    ],
    "wof:name":"South Jaridharia",
    "wof:placetype":"locality",
    "wof:population":843
},
  "geometry": {"coordinates":[89.40908899999999,26.147378],"type":"Point"}
}