{
  "type": "Feature",
  "properties": {
    "gn:admin1_code":"10.0",
    "gn:admin2_code":"072",
    "gn:asciiname":"Sulakhni",
    "gn:country_code":"IN",
    "gn:dem":261,
    "gn:feature_class":"P",
    "gn:feature_code":"PPL",
    "gn:name":"Sulakhni",
    "gn:population":0,
    "gn:timezone":"Asia/Kolkata",
    "iso:country":"IN",
    "ks:ks_name":"Sulkhani",
    "ks:ks_pop":937,
    "ks:ks_type":"VILLAGE",
    "name:eng_x_preferred":[
        "Sulkhani"
    ],
    "name:eng_x_variant":[
        "Sulakhni"
    ],
    "wof:name":"Sulkhani",
    "wof:placetype":"locality",
    "wof:population":937
},
  "geometry": {"coordinates":[76.806369,30.193333],"type":"Point"}
}