{
  "type": "Feature",
  "properties": {
    "iso:country":"IN",
    "ks:ks_name":"Sikakhal",
    "ks:ks_pop":3,
    "ks:ks_type":"VILLAGE",
    "name:eng_x_preferred":[
        "Sikakhal"
    ],
    "wof:name":"Sikakhal",
    "wof:placetype":"locality",
    "wof:population":3
},
  "geometry": {"coordinates":[83.621375,19.671848],"type":"Point"}
}