{
  "type": "Feature",
  "properties": {
    "iso:country":"IN",
    "qs:name":"Nani Pipli",
    "qs:name_adm0":"India",
    "qs:name_adm1":"Gujarat",
    "qs:photos":5,
    "qs:photos_1k":1,
    "qs:photos_9k":1,
    "qs:photos_9r":1,
    "qs:photos_all":5,
    "qs:photos_sr":1,
    "qs:placetype":"Town",
    "qs:pop_sr":"0",
    "wof:name":"Nani Pipli",
    "wof:placetype":"locality"
},
  "geometry": {"coordinates":[71.51073,23.80609],"type":"Point"}
}