{
  "type": "Feature",
  "properties": {
    "iso:country":"IN",
    "ks:ks_name":"Chamanamadanahalli",
    "ks:ks_pop":299,
    "ks:ks_type":"VILLAGE",
    "name:eng_x_preferred":[
        "Chamanamadanahalli"
    ],
    "wof:name":"Chamanamadanahalli",
    "wof:placetype":"locality",
    "wof:population":299
},
  "geometry": {"coordinates":[76.554874,12.063674],"type":"Point"}
}