{
  "type": "Feature",
  "properties": {
    "iso:country":"IN",
    "ks:ks_name":"Chapri Bara",
    "ks:ks_pop":117,
    "ks:ks_type":"VILLAGE",
    "name:eng_x_preferred":[
        "Chapri Bara"
    ],
    "wof:name":"Chapri Bara",
    "wof:placetype":"locality",
    "wof:population":117
},
  "geometry": {"coordinates":[87.459648,24.913292],"type":"Point"}
}