{
  "type": "Feature",
  "properties": {
    "iso:country":"IN",
    "ks:ks_name":"Laxmipura",
    "ks:ks_pop":110,
    "ks:ks_type":"HABITATION",
    "name:eng_x_preferred":[
        "Laxmipura"
    ],
    "wof:name":"Laxmipura",
    "wof:placetype":"locality",
    "wof:population":110
},
  "geometry": {"coordinates":[75.72689,13.888868],"type":"Point"}
}