{
  "type": "Feature",
  "properties": {
    "iso:country":"IN",
    "ks:ks_name":"Mohkam Pur Khurd",
    "ks:ks_pop":2231,
    "ks:ks_type":"VILLAGE",
    "ks:ks_uagg_main":0,
    "name:eng_x_preferred":[
        "Mohkam Pur Khurd"
    ],
    "wof:name":"Mohkam Pur Khurd",
    "wof:placetype":"neighbourhood",
    "wof:population":2231
},
  "geometry": {"coordinates":[78.07693500000001,30.277544],"type":"Point"}
}