{
  "type": "Feature",
  "properties": {
    "gn:admin1_code":"21",
    "gn:admin2_code":"397.0",
    "gn:asciiname":"Titalguda",
    "gn:country_code":"IN",
    "gn:dem":629,
    "gn:feature_class":"P",
    "gn:feature_code":"PPL",
    "gn:name":"Titalguda",
    "gn:population":0,
    "gn:timezone":"Asia/Kolkata",
    "iso:country":"IN",
    "wof:name":"Titalguda",
    "wof:placetype":"locality"
},
  "geometry": {"coordinates":[82.16429000000002,19.46046],"type":"Point"}
}