{
  "type": "Feature",
  "properties": {
    "gn:admin1_code":"19.0",
    "gn:admin2_code":"563.0",
    "gn:asciiname":"Madgeri",
    "gn:country_code":"IN",
    "gn:dem":14,
    "gn:feature_class":"P",
    "gn:feature_code":"PPL",
    "gn:name":"M\u0101dgeri",
    "gn:population":0,
    "gn:timezone":"Asia/Kolkata",
    "iso:country":"IN",
    "ks:ks_name":"Madageri",
    "ks:ks_pop":80,
    "ks:ks_type":"HABITATION",
    "name:eng_x_preferred":[
        "Madageri"
    ],
    "name:eng_x_variant":[
        "Madgeri"
    ],
    "wof:name":"Madageri",
    "wof:placetype":"locality",
    "wof:population":80
},
  "geometry": {"coordinates":[74.436826,14.365849],"type":"Point"}
}