{
  "type": "Feature",
  "properties": {
    "gn:admin1_code":"39",
    "gn:admin2_code":"60.0",
    "gn:asciiname":"Kararu",
    "gn:country_code":"IN",
    "gn:dem":984,
    "gn:feature_class":"P",
    "gn:feature_code":"PPL",
    "gn:name":"Kararu",
    "gn:population":0,
    "gn:timezone":"Asia/Kolkata",
    "iso:country":"IN",
    "wof:name":"Kararu",
    "wof:placetype":"locality"
},
  "geometry": {"coordinates":[77.83915999999998,30.87053],"type":"Point"}
}