{
  "type": "Feature",
  "properties": {
    "gn:admin1_code":"10",
    "gn:admin2_code":"70.0",
    "gn:asciiname":"Khuddi",
    "gn:country_code":"IN",
    "gn:dem":281,
    "gn:feature_class":"P",
    "gn:feature_code":"PPL",
    "gn:name":"Khuddi",
    "gn:population":0,
    "gn:timezone":"Asia/Kolkata",
    "iso:country":"IN",
    "ks:ks_name":"Khuddi",
    "ks:ks_pop":100,
    "ks:ks_type":"VILLAGE",
    "ks:ks_uagg_main":0,
    "name:eng_x_preferred":[
        "Khuddi"
    ],
    "wof:name":"Khuddi",
    "wof:placetype":"neighbourhood",
    "wof:population":100
},
  "geometry": {"coordinates":[76.916416,30.32104],"type":"Point"}
}