{
  "type": "Feature",
  "properties": {
    "gn:admin1_code":"33.0",
    "gn:admin2_code":"586",
    "gn:asciiname":"Gaundongrem",
    "gn:country_code":"IN",
    "gn:dem":80,
    "gn:feature_class":"P",
    "gn:feature_code":"PPL",
    "gn:name":"Gaundongrem",
    "gn:population":0,
    "gn:timezone":"Asia/Kolkata",
    "iso:country":"IN",
    "wof:name":"Gaundongrem",
    "wof:placetype":"locality"
},
  "geometry": {"coordinates":[74.11667,15.03333],"type":"Point"}
}