{
  "type": "Feature",
  "properties": {
    "gn:admin1_code":"36",
    "gn:admin2_code":"174.0",
    "gn:asciiname":"Naudiha Karenti",
    "gn:country_code":"IN",
    "gn:dem":106,
    "gn:feature_class":"P",
    "gn:feature_code":"PPL",
    "gn:name":"Naud\u012bh\u0101 Karenti",
    "gn:population":0,
    "gn:timezone":"Asia/Kolkata",
    "iso:country":"IN",
    "wof:name":"Naudiha Karenti",
    "wof:placetype":"locality"
},
  "geometry": {"coordinates":[81.47839999999999,25.59504],"type":"Point"}
}