{
  "type": "Feature",
  "properties": {
    "iso:country":"IN",
    "ks:ks_name":"Garhuapur",
    "ks:ks_pop":997,
    "ks:ks_type":"VILLAGE",
    "name:eng_x_preferred":[
        "Garhuapur"
    ],
    "wof:name":"Garhuapur",
    "wof:placetype":"locality",
    "wof:population":997
},
  "geometry": {"coordinates":[79.830015,27.50258],"type":"Point"}
}