{
  "type": "Feature",
  "properties": {
    "gn:admin1_code":"19.0",
    "gn:admin2_code":"564.0",
    "gn:asciiname":"Anaji",
    "gn:country_code":"IN",
    "gn:dem":603,
    "gn:feature_class":"P",
    "gn:feature_code":"PPL",
    "gn:name":"Anaji",
    "gn:population":0,
    "gn:timezone":"Asia/Kolkata",
    "iso:country":"IN",
    "name:azb_x_preferred":[
        "\u0627\u0646\u0627\u062c\u06cc"
    ],
    "name:fas_x_preferred":[
        "\u0627\u0646\u0627\u062c\u06cc"
    ],
    "name:vie_x_preferred":[
        "Anaji"
    ],
    "wof:name":"Anaji",
    "wof:placetype":"locality"
},
  "geometry": {"coordinates":[75.55565,14.31612],"type":"Point"}
}