{
  "type": "Feature",
  "properties": {
    "iso:country":"IN",
    "ks:ks_name":"Bhola Tanr",
    "ks:ks_pop":192,
    "ks:ks_type":"HABITATION",
    "name:eng_x_preferred":[
        "Bhola Tanr"
    ],
    "wof:name":"Bhola Tanr",
    "wof:placetype":"locality",
    "wof:population":192
},
  "geometry": {"coordinates":[86.32490199999999,24.010817],"type":"Point"}
}