{
  "type": "Feature",
  "properties": {
    "iso:country":"IN",
    "ks:ks_name":"Karaikadu",
    "ks:ks_pop":510,
    "ks:ks_type":"HABITATION",
    "name:eng_x_preferred":[
        "Karaikadu"
    ],
    "wof:name":"Karaikadu",
    "wof:placetype":"locality",
    "wof:population":510
},
  "geometry": {"coordinates":[77.680311,11.931089],"type":"Point"}
}