{
  "type": "Feature",
  "properties": {
    "iso:country":"IN",
    "ks:ks_name":"Sighni",
    "ks:ks_pop":1009,
    "ks:ks_type":"VILLAGE",
    "ks:ks_uagg_main":0,
    "name:eng_x_preferred":[
        "Sighni"
    ],
    "wof:name":"Sighni",
    "wof:placetype":"neighbourhood",
    "wof:population":1009
},
  "geometry": {"coordinates":[81.900195,26.500014],"type":"Point"}
}