{
  "type": "Feature",
  "properties": {
    "iso:country":"IN",
    "ks:ks_name":"Mundaplavil",
    "ks:ks_pop":846,
    "ks:ks_type":"HABITATION",
    "name:eng_x_preferred":[
        "Mundaplavil"
    ],
    "wof:name":"Mundaplavil",
    "wof:placetype":"locality",
    "wof:population":846
},
  "geometry": {"coordinates":[75.641074,11.571449],"type":"Point"}
}