{
  "type": "Feature",
  "properties": {
    "iso:country":"IN",
    "ks:ks_alt_nam":"Dinpur Ch\u0101ndan",
    "ks:ks_name":"Dinpur Chandan",
    "ks:ks_pop":0,
    "ks:ks_type":"VILLAGE",
    "name:eng_x_preferred":[
        "Dinpur Chandan"
    ],
    "name:eng_x_variant":[
        "Dinpur Ch\u0101ndan"
    ],
    "wof:name":"Dinpur Chandan",
    "wof:placetype":"locality",
    "wof:population":0
},
  "geometry": {"coordinates":[79.37272400000001,26.911221],"type":"Point"}
}