{
  "type": "Feature",
  "properties": {
    "gn:admin1_code":"25.0",
    "gn:admin2_code":"604.0",
    "gn:asciiname":"Nelli",
    "gn:country_code":"IN",
    "gn:dem":62,
    "gn:feature_class":"P",
    "gn:feature_code":"PPL",
    "gn:name":"Nelli",
    "gn:population":0,
    "gn:timezone":"Asia/Kolkata",
    "iso:country":"IN",
    "name:deu_x_preferred":[
        "Nelli"
    ],
    "name:ita_x_preferred":[
        "Nelli"
    ],
    "wof:name":"Nelli",
    "wof:placetype":"locality"
},
  "geometry": {"coordinates":[79.76039,12.55687],"type":"Point"}
}