{
  "type": "Feature",
  "properties": {
    "iso:country":"IN",
    "ks:ks_alt_nam":"LODHEN PURWA",
    "ks:ks_name":"Lodhen Purwa",
    "ks:ks_pop":236,
    "ks:ks_type":"HABITATION",
    "name:eng_x_preferred":[
        "Lodhen Purwa"
    ],
    "wof:name":"Lodhen Purwa",
    "wof:placetype":"locality",
    "wof:population":236
},
  "geometry": {"coordinates":[81.799915,27.550576],"type":"Point"}
}