{
  "type": "Feature",
  "properties": {
    "iso:country":"IN",
    "ks:ks_name":"Thokkiguda",
    "ks:ks_pop":75,
    "ks:ks_type":"HABITATION",
    "name:eng_x_preferred":[
        "Thokkiguda"
    ],
    "wof:name":"Thokkiguda",
    "wof:placetype":"locality",
    "wof:population":75
},
  "geometry": {"coordinates":[79.134576,19.139278],"type":"Point"}
}