{
  "type": "Feature",
  "properties": {
    "iso:country":"IN",
    "ks:ks_name":"Phulwaria",
    "ks:ks_pop":0,
    "ks:ks_type":"VILLAGE",
    "name:eng_x_preferred":[
        "Phulwaria"
    ],
    "wof:name":"Phulwaria",
    "wof:placetype":"locality",
    "wof:population":0
},
  "geometry": {"coordinates":[83.809082,24.784151],"type":"Point"}
}