{
  "type": "Feature",
  "properties": {
    "gn:admin1_code":"40",
    "gn:admin2_code":"540.0",
    "gn:asciiname":"Kotur",
    "gn:country_code":"IN",
    "gn:dem":184,
    "gn:feature_class":"P",
    "gn:feature_code":"PPL",
    "gn:name":"Kot\u016br",
    "gn:population":0,
    "gn:timezone":"Asia/Kolkata",
    "iso:country":"IN",
    "name:eng_x_preferred":[
        "Kot\u016br"
    ],
    "name:fas_x_preferred":[
        "\u06a9\u062a\u0648\u0631"
    ],
    "wof:name":"Kotur",
    "wof:placetype":"locality"
},
  "geometry": {"coordinates":[79.99785,17.46711],"type":"Point"}
}