{
  "type": "Feature",
  "properties": {
    "gn:admin1_code":"39.0",
    "gn:admin2_code":"61.0",
    "gn:asciiname":"Deochuli",
    "gn:country_code":"IN",
    "gn:dem":1346,
    "gn:feature_class":"P",
    "gn:feature_code":"PPL",
    "gn:name":"Deochuli",
    "gn:population":0,
    "gn:timezone":"Asia/Kolkata",
    "iso:country":"IN",
    "wof:name":"Deochuli",
    "wof:placetype":"locality"
},
  "geometry": {"coordinates":[79.05164000000001,29.64068],"type":"Point"}
}