{
  "type": "Feature",
  "properties": {
    "gn:admin1_code":"11",
    "gn:admin2_code":"23.0",
    "gn:asciiname":"Chil",
    "gn:country_code":"IN",
    "gn:dem":1320,
    "gn:feature_class":"P",
    "gn:feature_code":"PPL",
    "gn:name":"Chil",
    "gn:population":0,
    "gn:timezone":"Asia/Kolkata",
    "iso:country":"IN",
    "name:ceb_x_preferred":[
        "Chil"
    ],
    "name:swe_x_preferred":[
        "Chil"
    ],
    "wof:name":"Chil",
    "wof:placetype":"locality"
},
  "geometry": {"coordinates":[76.14516999999999,32.8048],"type":"Point"}
}