{
  "type": "Feature",
  "properties": {
    "iso:country":"IN",
    "ks:ks_name":"Buttaipeta",
    "ks:ks_pop":216,
    "ks:ks_type":"HABITATION",
    "name:eng_x_preferred":[
        "Buttaipeta"
    ],
    "wof:name":"Buttaipeta",
    "wof:placetype":"locality",
    "wof:population":216
},
  "geometry": {"coordinates":[82.009552,16.810089],"type":"Point"}
}