{
  "type": "Feature",
  "properties": {
    "iso:country":"IN",
    "ks:ks_name":"Sonarwdi",
    "ks:ks_pop":75,
    "ks:ks_type":"HABITATION",
    "name:eng_x_preferred":[
        "Sonarwdi"
    ],
    "wof:name":"Sonarwdi",
    "wof:placetype":"locality",
    "wof:population":75
},
  "geometry": {"coordinates":[73.38054200000001,17.200074],"type":"Point"}
}