{
  "type": "Feature",
  "properties": {
    "iso:country":"IN",
    "ks:ks_name":"Dayalchak",
    "ks:ks_pop":0,
    "ks:ks_type":"VILLAGE",
    "name:eng_x_preferred":[
        "Dayalchak"
    ],
    "wof:name":"Dayalchak",
    "wof:placetype":"locality",
    "wof:population":0
},
  "geometry": {"coordinates":[87.479893,22.270184],"type":"Point"}
}