{
  "type": "Feature",
  "properties": {
    "iso:country":"IN",
    "ks:ks_name":"Khadagpur",
    "ks:ks_pop":599,
    "ks:ks_type":"HABITATION",
    "name:eng_x_preferred":[
        "Khadagpur"
    ],
    "wof:name":"Khadagpur",
    "wof:placetype":"locality",
    "wof:population":599
},
  "geometry": {"coordinates":[80.41000699999999,26.336298],"type":"Point"}
}