{
  "type": "Feature",
  "properties": {
    "iso:country":"IN",
    "ks:ks_name":"Diguva Deruvada",
    "ks:ks_pop":278,
    "ks:ks_type":"HABITATION",
    "name:eng_x_preferred":[
        "Diguva Deruvada"
    ],
    "wof:name":"Diguva Deruvada",
    "wof:placetype":"locality",
    "wof:population":278
},
  "geometry": {"coordinates":[83.535416,18.973409],"type":"Point"}
}