{
  "type": "Feature",
  "properties": {
    "iso:country":"IN",
    "ks:ks_alt_nam":"Pure duver",
    "ks:ks_name":"Pure Duver",
    "ks:ks_pop":186,
    "ks:ks_type":"HABITATION",
    "name:eng_x_preferred":[
        "Pure Duver"
    ],
    "wof:name":"Pure Duver",
    "wof:placetype":"locality",
    "wof:population":186
},
  "geometry": {"coordinates":[81.5277,26.3762],"type":"Point"}
}