{
  "type": "Feature",
  "properties": {
    "iso:country":"IN",
    "ks:ks_name":"Basahi",
    "ks:ks_pop":846,
    "ks:ks_type":"VILLAGE",
    "name:eng_x_preferred":[
        "Basahi"
    ],
    "wof:name":"Basahi",
    "wof:placetype":"locality",
    "wof:population":846
},
  "geometry": {"coordinates":[81.293235,23.925278],"type":"Point"}
}