{
  "type": "Feature",
  "properties": {
    "iso:country":"IN",
    "ks:ks_name":"Srgodu",
    "ks:ks_pop":31,
    "ks:ks_type":"HABITATION",
    "name:eng_x_preferred":[
        "Srgodu"
    ],
    "wof:name":"Srgodu",
    "wof:placetype":"locality",
    "wof:population":31
},
  "geometry": {"coordinates":[75.220142,13.401434],"type":"Point"}
}