{
  "type": "Feature",
  "properties": {
    "gn:admin1_code":"35.0",
    "gn:admin2_code":"424.0",
    "gn:asciiname":"Lidhora",
    "gn:country_code":"IN",
    "gn:dem":209,
    "gn:feature_class":"P",
    "gn:feature_code":"PPL",
    "gn:name":"Lidhora",
    "gn:population":0,
    "gn:timezone":"Asia/Kolkata",
    "iso:country":"IN",
    "wof:name":"Lidhora",
    "wof:placetype":"locality"
},
  "geometry": {"coordinates":[78.67108,25.35108],"type":"Point"}
}