{
  "type": "Feature",
  "properties": {
    "iso:country":"IN",
    "ks:ks_alt_nam":"BIDYA MURA SOUTH",
    "ks:ks_name":"Bidya Mura South",
    "ks:ks_pop":59,
    "ks:ks_type":"HABITATION",
    "name:eng_x_preferred":[
        "Bidya Mura South"
    ],
    "wof:name":"Bidya Mura South",
    "wof:placetype":"locality",
    "wof:population":59
},
  "geometry": {"coordinates":[91.49854499999999,23.85279],"type":"Point"}
}