{
  "type": "Feature",
  "properties": {
    "gn:admin1_code":"34.0",
    "gn:admin2_code":"221.0",
    "gn:asciiname":"Paroria",
    "gn:country_code":"IN",
    "gn:dem":49,
    "gn:feature_class":"P",
    "gn:feature_code":"PPL",
    "gn:name":"Paroria",
    "gn:population":0,
    "gn:timezone":"Asia/Kolkata",
    "iso:country":"IN",
    "ks:ks_name":"Paroria",
    "ks:ks_pop":4413,
    "ks:ks_type":"VILLAGE",
    "name:eng_x_preferred":[
        "Paroria"
    ],
    "wof:name":"Paroria",
    "wof:placetype":"locality",
    "wof:population":4413
},
  "geometry": {"coordinates":[85.759131,25.724289],"type":"Point"}
}