{
  "type": "Feature",
  "properties": {
    "iso:country":"IN",
    "ks:ks_name":"Duligaon Pt.II",
    "ks:ks_pop":61,
    "ks:ks_type":"VILLAGE",
    "name:eng_x_preferred":[
        "Duligaon Pt.II"
    ],
    "wof:name":"Duligaon Pt.II",
    "wof:placetype":"locality",
    "wof:population":61
},
  "geometry": {"coordinates":[90.061944,26.251319],"type":"Point"}
}