{
  "type": "Feature",
  "properties": {
    "gn:admin1_code":"25",
    "gn:admin2_code":"610.0",
    "gn:asciiname":"Kurumandur",
    "gn:country_code":"IN",
    "gn:dem":249,
    "gn:feature_class":"P",
    "gn:feature_code":"PPL",
    "gn:name":"Kurumand\u016br",
    "gn:population":0,
    "gn:timezone":"Asia/Kolkata",
    "iso:country":"IN",
    "ks:ks_alt_nam":"Kurumand\u016br",
    "ks:ks_name":"Kurumandur",
    "ks:ks_pop":4175,
    "ks:ks_type":"VILLAGE",
    "ks:ks_uagg_main":0,
    "name:eng_x_preferred":[
        "Kurumandur"
    ],
    "name:eng_x_variant":[
        "Kurumand\u016br"
    ],
    "name:und_x_variant":[
        "Kurumand\u016br"
    ],
    "wof:name":"Kurumandur",
    "wof:placetype":"neighbourhood",
    "wof:population":4175
},
  "geometry": {"coordinates":[77.348243,11.420442],"type":"Point"}
}