{
  "type": "Feature",
  "properties": {
    "iso:country":"IN",
    "ks:ks_name":"Dikrongmukgh",
    "ks:ks_pop":222,
    "ks:ks_type":"HABITATION",
    "name:eng_x_preferred":[
        "Dikrongmukgh"
    ],
    "wof:name":"Dikrongmukgh",
    "wof:placetype":"locality",
    "wof:population":222
},
  "geometry": {"coordinates":[93.904099,26.941143],"type":"Point"}
}