{
  "type": "Feature",
  "properties": {
    "iso:country":"IN",
    "ks:ks_name":"Chitrakul",
    "ks:ks_pop":929,
    "ks:ks_type":"VILLAGE",
    "name:eng_x_preferred":[
        "Chitrakul"
    ],
    "wof:name":"Chitrakul",
    "wof:placetype":"locality",
    "wof:population":929
},
  "geometry": {"coordinates":[86.16050300000001,20.808302],"type":"Point"}
}