{
  "type": "Feature",
  "properties": {
    "iso:country":"IN",
    "ks:ks_name":"Ghiladhari Basti",
    "ks:ks_pop":155,
    "ks:ks_type":"VILLAGE",
    "ks:ks_uagg_main":0,
    "name:eng_x_preferred":[
        "Ghiladhari Basti"
    ],
    "wof:name":"Ghiladhari Basti",
    "wof:placetype":"neighbourhood",
    "wof:population":155
},
  "geometry": {"coordinates":[93.055215,26.806524],"type":"Point"}
}