{
  "type": "Feature",
  "properties": {
    "iso:country":"IN",
    "ks:ks_name":"Bheroowas",
    "ks:ks_pop":734,
    "ks:ks_type":"HABITATION",
    "name:eng_x_preferred":[
        "Bheroowas"
    ],
    "wof:name":"Bheroowas",
    "wof:placetype":"locality",
    "wof:population":734
},
  "geometry": {"coordinates":[76.388231,26.552106],"type":"Point"}
}