{
  "type": "Feature",
  "properties": {
    "gn:admin1_code":"7.0",
    "gn:admin2_code":"98.0",
    "gn:asciiname":"Khitki",
    "gn:country_code":"IN",
    "gn:dem":225,
    "gn:feature_class":"P",
    "gn:feature_code":"PPL",
    "gn:name":"Khitki",
    "gn:population":0,
    "gn:timezone":"Asia/Kolkata",
    "iso:country":"IN",
    "wof:name":"Khitki",
    "wof:placetype":"neighbourhood"
},
  "geometry": {"coordinates":[77.22143,28.53161],"type":"Point"}
}