{
  "type": "Feature",
  "properties": {
    "gn:admin1_code":"36",
    "gn:admin2_code":"188.0",
    "gn:asciiname":"Panika",
    "gn:country_code":"IN",
    "gn:dem":83,
    "gn:feature_class":"P",
    "gn:feature_code":"PPL",
    "gn:name":"Panika",
    "gn:population":0,
    "gn:timezone":"Asia/Kolkata",
    "iso:country":"IN",
    "name:hrv_x_preferred":[
        "Panika"
    ],
    "wof:name":"Panika",
    "wof:placetype":"locality"
},
  "geometry": {"coordinates":[83.13176,26.84491],"type":"Point"}
}