{
  "type": "Feature",
  "properties": {
    "gn:admin1_code":"16.0",
    "gn:admin2_code":"508.0",
    "gn:asciiname":"Lankalguda",
    "gn:country_code":"IN",
    "gn:dem":189,
    "gn:feature_class":"P",
    "gn:feature_code":"PPL",
    "gn:name":"Lankalguda",
    "gn:population":0,
    "gn:timezone":"Asia/Kolkata",
    "iso:country":"IN",
    "ks:ks_name":"Lakhalguda",
    "ks:ks_pop":448,
    "ks:ks_type":"HABITATION",
    "name:eng_x_preferred":[
        "Lakhalguda"
    ],
    "name:eng_x_variant":[
        "Lankalguda"
    ],
    "wof:name":"Lakhalguda",
    "wof:placetype":"locality",
    "wof:population":448
},
  "geometry": {"coordinates":[80.43223,19.2805],"type":"Point"}
}