{
  "type": "Feature",
  "properties": {
    "iso:country":"IN",
    "ks:ks_alt_nam":"krischanwadi",
    "ks:ks_name":"Krischanwadi",
    "ks:ks_pop":17,
    "ks:ks_type":"HABITATION",
    "name:eng_x_preferred":[
        "Krischanwadi"
    ],
    "wof:name":"Krischanwadi",
    "wof:placetype":"locality",
    "wof:population":17
},
  "geometry": {"coordinates":[73.966222,15.786722],"type":"Point"}
}