{
  "type": "Feature",
  "properties": {
    "iso:country":"IN",
    "ks:ks_name":"Thapla Lagga Airadi",
    "ks:ks_pop":5,
    "ks:ks_type":"HABITATION",
    "name:eng_x_preferred":[
        "Thapla Lagga Airadi"
    ],
    "wof:name":"Thapla Lagga Airadi",
    "wof:placetype":"locality",
    "wof:population":5
},
  "geometry": {"coordinates":[78.778887,30.287409],"type":"Point"}
}