{
  "type": "Feature",
  "properties": {
    "iso:country":"IN",
    "ks:ks_name":"Jambhuldara",
    "ks:ks_pop":289,
    "ks:ks_type":"HABITATION",
    "name:eng_x_preferred":[
        "Jambhuldara"
    ],
    "wof:name":"Jambhuldara",
    "wof:placetype":"locality",
    "wof:population":289
},
  "geometry": {"coordinates":[74.085494,19.348971],"type":"Point"}
}