{
  "type": "Feature",
  "properties": {
    "gn:admin1_code":"28.0",
    "gn:admin2_code":"344",
    "gn:asciiname":"Daspur",
    "gn:country_code":"IN",
    "gn:dem":17,
    "gn:feature_class":"P",
    "gn:feature_code":"PPL",
    "gn:name":"D\u0101spur",
    "gn:population":0,
    "gn:timezone":"Asia/Kolkata",
    "iso:country":"IN",
    "ks:ks_name":"Daspur",
    "ks:ks_pop":3104,
    "ks:ks_type":"VILLAGE",
    "ks:ks_uagg_main":0,
    "name:eng_x_preferred":[
        "Daspur"
    ],
    "name:und_x_variant":[
        "D\u0101spur"
    ],
    "wof:name":"Daspur",
    "wof:placetype":"neighbourhood",
    "wof:population":3104
},
  "geometry": {"coordinates":[87.724234,22.605674],"type":"Point"}
}