{
  "type": "Feature",
  "properties": {
    "iso:country":"IN",
    "ks:ks_name":"Rajapur",
    "ks:ks_pop":3942,
    "ks:ks_type":"VILLAGE",
    "name:eng_x_preferred":[
        "Rajapur"
    ],
    "wof:name":"Rajapur",
    "wof:placetype":"locality",
    "wof:population":3942
},
  "geometry": {"coordinates":[88.481613,23.873019],"type":"Point"}
}