{
  "type": "Feature",
  "properties": {
    "iso:country":"IN",
    "ks:ks_name":"Makadiapadar",
    "ks:ks_pop":43,
    "ks:ks_type":"VILLAGE",
    "name:eng_x_preferred":[
        "Makadiapadar"
    ],
    "wof:name":"Makadiapadar",
    "wof:placetype":"locality",
    "wof:population":43
},
  "geometry": {"coordinates":[83.84712500000001,20.667264],"type":"Point"}
}