{
  "type": "Feature",
  "properties": {
    "gn:admin1_code":"36.0",
    "gn:admin2_code":"171.0",
    "gn:asciiname":"Maini",
    "gn:country_code":"IN",
    "gn:dem":121,
    "gn:feature_class":"P",
    "gn:feature_code":"PPL",
    "gn:name":"Maini",
    "gn:population":0,
    "gn:timezone":"Asia/Kolkata",
    "iso:country":"IN",
    "name:fas_x_preferred":[
        "\u0645\u0627\u0626\u0646\u06cc"
    ],
    "name:urd_x_preferred":[
        "\u0645\u0627\u0626\u0646\u06cc"
    ],
    "wof:name":"Maini",
    "wof:placetype":"locality"
},
  "geometry": {"coordinates":[81.13468,25.21899],"type":"Point"}
}