{
  "type": "Feature",
  "properties": {
    "iso:country":"IN",
    "ks:ks_name":"Naya Deeh",
    "ks:ks_pop":64,
    "ks:ks_type":"HABITATION",
    "name:eng_x_preferred":[
        "Naya Deeh"
    ],
    "wof:name":"Naya Deeh",
    "wof:placetype":"locality",
    "wof:population":64
},
  "geometry": {"coordinates":[82.84389899999999,27.372796],"type":"Point"}
}