{
  "type": "Feature",
  "properties": {
    "iso:country":"IN",
    "ks:ks_name":"Ghaura Walla",
    "ks:ks_pop":85,
    "ks:ks_type":"VILLAGE",
    "name:eng_x_preferred":[
        "Ghaura Walla"
    ],
    "wof:name":"Ghaura Walla",
    "wof:placetype":"locality",
    "wof:population":85
},
  "geometry": {"coordinates":[78.711538,29.786744],"type":"Point"}
}