{
  "type": "Feature",
  "properties": {
    "iso:country":"IN",
    "ks:ks_name":"Potayyas Peta",
    "ks:ks_pop":100,
    "ks:ks_type":"HABITATION",
    "ks:ks_uagg_main":0,
    "name:eng_x_preferred":[
        "Potayyas Peta"
    ],
    "wof:name":"Potayyas Peta",
    "wof:placetype":"neighbourhood",
    "wof:population":100
},
  "geometry": {"coordinates":[84.45683099999999,18.759587],"type":"Point"}
}