{
  "type": "Feature",
  "properties": {
    "iso:country":"IN",
    "ks:ks_name":"Katakheda Chanderi",
    "ks:ks_pop":245,
    "ks:ks_type":"VILLAGE",
    "name:eng_x_preferred":[
        "Katakheda Chanderi"
    ],
    "wof:name":"Katakheda Chanderi",
    "wof:placetype":"locality",
    "wof:population":245
},
  "geometry": {"coordinates":[78.173168,24.565862],"type":"Point"}
}