{
  "type": "Feature",
  "properties": {
    "gn:admin1_code":"39.0",
    "gn:admin2_code":"61.0",
    "gn:asciiname":"Bajakhal",
    "gn:country_code":"IN",
    "gn:dem":1701,
    "gn:feature_class":"P",
    "gn:feature_code":"PPL",
    "gn:name":"B\u0101j\u0101kh\u0101l",
    "gn:population":0,
    "gn:timezone":"Asia/Kolkata",
    "iso:country":"IN",
    "wof:name":"Bajakhal",
    "wof:placetype":"locality"
},
  "geometry": {"coordinates":[79.01326999999998,29.81116],"type":"Point"}
}