{
  "type": "Feature",
  "properties": {
    "iso:country":"IN",
    "ks:ks_name":"Raksa",
    "ks:ks_pop":204,
    "ks:ks_type":"VILLAGE",
    "name:eng_x_preferred":[
        "Raksa"
    ],
    "wof:name":"Raksa",
    "wof:placetype":"locality",
    "wof:population":204
},
  "geometry": {"coordinates":[86.784565,24.594865],"type":"Point"}
}