{
  "type": "Feature",
  "properties": {
    "gn:admin1_code":"34.0",
    "gn:admin2_code":"216.0",
    "gn:asciiname":"Shahpur Juned",
    "gn:country_code":"IN",
    "gn:dem":54,
    "gn:feature_class":"P",
    "gn:feature_code":"PPL",
    "gn:name":"Sh\u0101hpur Juned",
    "gn:population":0,
    "gn:timezone":"Asia/Kolkata",
    "iso:country":"IN",
    "ks:ks_alt_nam":"Sh\u0101hpur Juned",
    "ks:ks_name":"Shahpur Juned",
    "ks:ks_pop":2339,
    "ks:ks_type":"VILLAGE",
    "name:eng_x_preferred":[
        "Shahpur Juned"
    ],
    "name:eng_x_variant":[
        "Sh\u0101hpur Juned"
    ],
    "wof:name":"Shahpur Juned",
    "wof:placetype":"locality",
    "wof:population":2339
},
  "geometry": {"coordinates":[85.44472,25.941231],"type":"Point"}
}