{
  "type": "Feature",
  "properties": {
    "iso:country":"IN",
    "ks:ks_name":"V Nerkunam Old",
    "ks:ks_pop":298,
    "ks:ks_type":"HABITATION",
    "name:eng_x_preferred":[
        "V Nerkunam Old"
    ],
    "wof:name":"V Nerkunam Old",
    "wof:placetype":"locality",
    "wof:population":298
},
  "geometry": {"coordinates":[79.68009000000001,11.981993],"type":"Point"}
}