{
  "type": "Feature",
  "properties": {
    "iso:country":"IN",
    "ks:ks_name":"Harkalpara",
    "ks:ks_pop":551,
    "ks:ks_type":"HABITATION",
    "name:eng_x_preferred":[
        "Harkalpara"
    ],
    "wof:name":"Harkalpara",
    "wof:placetype":"locality",
    "wof:population":551
},
  "geometry": {"coordinates":[88.076083,22.42284],"type":"Point"}
}