{
  "type": "Feature",
  "properties": {
    "iso:country":"IN",
    "ks:ks_name":"Rabanaguda",
    "ks:ks_pop":94,
    "ks:ks_type":"VILLAGE",
    "name:eng_x_preferred":[
        "Rabanaguda"
    ],
    "wof:name":"Rabanaguda",
    "wof:placetype":"locality",
    "wof:population":94
},
  "geometry": {"coordinates":[83.590188,21.085703],"type":"Point"}
}