{
  "type": "Feature",
  "properties": {
    "iso:country":"IN",
    "ks:ks_name":"Bhajea",
    "ks:ks_pop":0,
    "ks:ks_type":"VILLAGE",
    "name:eng_x_preferred":[
        "Bhajea"
    ],
    "wof:name":"Bhajea",
    "wof:placetype":"locality",
    "wof:population":0
},
  "geometry": {"coordinates":[84.14159100000001,24.993416],"type":"Point"}
}