{
  "type": "Feature",
  "properties": {
    "gn:admin1_code":"34.0",
    "gn:admin2_code":"231.0",
    "gn:asciiname":"Baga",
    "gn:country_code":"IN",
    "gn:dem":76,
    "gn:feature_class":"P",
    "gn:feature_code":"PPL",
    "gn:name":"B\u0101ga",
    "gn:population":0,
    "gn:timezone":"Asia/Kolkata",
    "iso:country":"IN",
    "name:ara_x_preferred":[
        "\u0628\u0627\u062c\u0627"
    ],
    "name:ben_bn_x_preferred":[
        "\u09ac\u09be\u0997\u09be"
    ],
    "name:ben_in_x_preferred":[
        "\u09ac\u09be\u0997\u09be"
    ],
    "name:ceb_x_preferred":[
        "Baga"
    ],
    "name:deu_x_preferred":[
        "Baga"
    ],
    "name:eus_x_preferred":[
        "Baga"
    ],
    "name:fao_x_preferred":[
        "Baga"
    ],
    "name:fra_x_preferred":[
        "Baga"
    ],
    "name:guj_x_preferred":[
        "\u0aac\u0abe\u0a97"
    ],
    "name:hin_x_preferred":[
        "\u092c\u093e\u0917\u093e"
    ],
    "name:hye_x_preferred":[
        "\u0532\u0561\u0563\u0561"
    ],
    "name:ita_x_preferred":[
        "Baga"
    ],
    "name:kan_x_preferred":[
        "\u0cac\u0cbe\u0c97\u0cbe"
    ],
    "name:kat_x_preferred":[
        "\u10d1\u10d0\u10d2\u10d0"
    ],
    "name:mal_x_preferred":[
        "\u0d2c\u0d3e\u0d17"
    ],
    "name:mar_x_preferred":[
        "\u092c\u093e\u0917\u093e"
    ],
    "name:nld_x_preferred":[
        "Baga"
    ],
    "name:pan_x_preferred":[
        "\u0a2c\u0a3e\u0a17\u0a3e"
    ],
    "name:por_x_preferred":[
        "Baga"
    ],
    "name:rus_x_preferred":[
        "\u0411\u0430\u0433\u0430"
    ],
    "name:swe_x_preferred":[
        "Baga"
    ],
    "name:tam_x_preferred":[
        "\u0baa\u0b95\u0bbe"
    ],
    "name:tel_x_preferred":[
        "\u0c2c\u0c17\u0c3e"
    ],
    "name:tgl_x_preferred":[
        "Baga"
    ],
    "name:ukr_x_preferred":[
        "\u0411\u0430\u0433\u0430"
    ],
    "name:urd_x_preferred":[
        "\u0628\u0627\u06af\u0627"
    ],
    "wof:name":"Baga",
    "wof:placetype":"locality"
},
  "geometry": {"coordinates":[84.71071999999999,25.34627],"type":"Point"}
}