{
  "type": "Feature",
  "properties": {
    "iso:country":"IN",
    "ks:ks_alt_nam":"Pachim Tola High school",
    "ks:ks_name":"Pachim Tola High School",
    "ks:ks_pop":256,
    "ks:ks_type":"HABITATION",
    "ks:ks_uagg_main":0,
    "name:eng_x_preferred":[
        "Pachim Tola High School"
    ],
    "wof:name":"Pachim Tola High School",
    "wof:placetype":"neighbourhood",
    "wof:population":256
},
  "geometry": {"coordinates":[84.294506,25.625092],"type":"Point"}
}