{
  "type": "Feature",
  "properties": {
    "gn:admin1_code":"25.0",
    "gn:admin2_code":"606.0",
    "gn:asciiname":"Melvanakkambadi",
    "gn:country_code":"IN",
    "gn:dem":297,
    "gn:feature_class":"P",
    "gn:feature_code":"PPL",
    "gn:name":"Melvanakkamb\u0101di",
    "gn:population":0,
    "gn:timezone":"Asia/Kolkata",
    "iso:country":"IN",
    "ks:ks_alt_nam":"Melvanakkamb\u0101di",
    "ks:ks_name":"Melvanakkambadi",
    "ks:ks_pop":3338,
    "ks:ks_type":"VILLAGE",
    "name:eng_x_preferred":[
        "Melvanakkambadi"
    ],
    "name:eng_x_variant":[
        "Melvanakkamb\u0101di"
    ],
    "wof:name":"Melvanakkambadi",
    "wof:placetype":"locality",
    "wof:population":3338
},
  "geometry": {"coordinates":[78.75004,12.243497],"type":"Point"}
}