{
  "type": "Feature",
  "properties": {
    "gn:admin1_code":"11.0",
    "gn:admin2_code":"33.0",
    "gn:asciiname":"Gran",
    "gn:country_code":"IN",
    "gn:dem":1695,
    "gn:feature_class":"P",
    "gn:feature_code":"PPL",
    "gn:name":"Gr\u0101n",
    "gn:population":0,
    "gn:timezone":"Asia/Kolkata",
    "iso:country":"IN",
    "name:bpy_x_preferred":[
        "\u0997\u09cd\u09b0\u09be\u09a8"
    ],
    "name:ceb_x_preferred":[
        "Gran"
    ],
    "name:dan_x_preferred":[
        "Gran"
    ],
    "name:deu_x_preferred":[
        "Gran"
    ],
    "name:epo_x_preferred":[
        "Gran"
    ],
    "name:eus_x_preferred":[
        "Gran"
    ],
    "name:fra_x_preferred":[
        "Gran"
    ],
    "name:glg_x_preferred":[
        "Gran"
    ],
    "name:hrv_x_preferred":[
        "Gran"
    ],
    "name:hun_x_preferred":[
        "Gran"
    ],
    "name:ita_x_preferred":[
        "Gran"
    ],
    "name:lim_x_preferred":[
        "Gran"
    ],
    "name:nld_x_preferred":[
        "Gran"
    ],
    "name:nno_x_preferred":[
        "Gran"
    ],
    "name:nor_x_preferred":[
        "Gran"
    ],
    "name:pol_x_preferred":[
        "Gran"
    ],
    "name:ron_x_preferred":[
        "Gran"
    ],
    "name:spa_x_preferred":[
        "Gran"
    ],
    "name:swe_x_preferred":[
        "Gran"
    ],
    "name:ukr_x_preferred":[
        "\u0413\u0440\u0430\u043d"
    ],
    "name:uzb_x_preferred":[
        "Gran"
    ],
    "wof:name":"Gran",
    "wof:placetype":"locality"
},
  "geometry": {"coordinates":[77.44662,30.94823],"type":"Point"}
}