{
  "type": "Feature",
  "properties": {
    "iso:country":"IN",
    "ks:ks_name":"Garbher",
    "ks:ks_pop":0,
    "ks:ks_type":"VILLAGE",
    "name:eng_x_preferred":[
        "Garbher"
    ],
    "wof:name":"Garbher",
    "wof:placetype":"locality",
    "wof:population":0
},
  "geometry": {"coordinates":[86.993504,24.533255],"type":"Point"}
}