{
  "type": "Feature",
  "properties": {
    "gn:admin1_code":"39.0",
    "gn:admin2_code":"57.0",
    "gn:asciiname":"Ganai Spring",
    "gn:country_code":"IN",
    "gn:dem":1768,
    "gn:feature_class":"P",
    "gn:feature_code":"PPL",
    "gn:name":"Gan\u0101i Spring",
    "gn:population":0,
    "gn:timezone":"Asia/Kolkata",
    "iso:country":"IN",
    "wof:name":"Ganai Spring",
    "wof:placetype":"locality"
},
  "geometry": {"coordinates":[79.50369000000001,30.47302],"type":"Point"}
}