{
  "type": "Feature",
  "properties": {
    "gn:admin1_code":"19.0",
    "gn:admin2_code":"565.0",
    "gn:asciiname":"Kenchatnahalli",
    "gn:country_code":"IN",
    "gn:dem":509,
    "gn:feature_class":"P",
    "gn:feature_code":"PPL",
    "gn:name":"Kenchatnahalli",
    "gn:population":0,
    "gn:timezone":"Asia/Kolkata",
    "iso:country":"IN",
    "wof:name":"Kenchatnahalli",
    "wof:placetype":"locality"
},
  "geometry": {"coordinates":[76.29966999999998,15.1469],"type":"Point"}
}