{
  "type": "Feature",
  "properties": {
    "iso:country":"IN",
    "ks:ks_name":"Nipendra Colony",
    "ks:ks_pop":196,
    "ks:ks_type":"HABITATION",
    "name:eng_x_preferred":[
        "Nipendra Colony"
    ],
    "wof:name":"Nipendra Colony",
    "wof:placetype":"locality",
    "wof:population":196
},
  "geometry": {"coordinates":[91.64936400000001,23.50727],"type":"Point"}
}