{
  "type": "Feature",
  "properties": {
    "iso:country":"IN",
    "ks:ks_name":"Asanbera",
    "ks:ks_pop":370,
    "ks:ks_type":"HABITATION",
    "name:eng_x_preferred":[
        "Asanbera"
    ],
    "wof:name":"Asanbera",
    "wof:placetype":"locality",
    "wof:population":370
},
  "geometry": {"coordinates":[84.219984,22.593627],"type":"Point"}
}