{
  "type": "Feature",
  "properties": {
    "iso:country":"IN",
    "ks:ks_name":"Reeval Ka Purwa / Chamrhi",
    "ks:ks_pop":106,
    "ks:ks_type":"HABITATION",
    "ks:ks_uagg_main":0,
    "name:eng_x_preferred":[
        "Reeval Ka Purwa / Chamrhi"
    ],
    "wof:name":"Reeval Ka Purwa / Chamrhi",
    "wof:placetype":"neighbourhood",
    "wof:population":106
},
  "geometry": {"coordinates":[82.157521,26.595146],"type":"Point"}
}