{
  "type": "Feature",
  "properties": {
    "gn:admin1_code":"36",
    "gn:admin2_code":"200.0",
    "gn:asciiname":"Dharmauli",
    "gn:country_code":"IN",
    "gn:dem":296,
    "gn:feature_class":"P",
    "gn:feature_code":"PPL",
    "gn:name":"Dharmauli",
    "gn:population":0,
    "gn:timezone":"Asia/Kolkata",
    "iso:country":"IN",
    "wof:name":"Dharmauli",
    "wof:placetype":"locality"
},
  "geometry": {"coordinates":[82.83601999999998,24.74344],"type":"Point"}
}