{
  "type": "Feature",
  "properties": {
    "iso:country":"IN",
    "ks:ks_name":"Madanpur",
    "ks:ks_pop":1037,
    "ks:ks_type":"VILLAGE",
    "name:eng_x_preferred":[
        "Madanpur"
    ],
    "wof:name":"Madanpur",
    "wof:placetype":"locality",
    "wof:population":1037
},
  "geometry": {"coordinates":[85.321265,23.512717],"type":"Point"}
}