{
  "type": "Feature",
  "properties": {
    "iso:country":"IN",
    "ks:ks_name":"Nagla Jamuni",
    "ks:ks_pop":333,
    "ks:ks_type":"HABITATION",
    "name:eng_x_preferred":[
        "Nagla Jamuni"
    ],
    "wof:name":"Nagla Jamuni",
    "wof:placetype":"locality",
    "wof:population":333
},
  "geometry": {"coordinates":[78.497519,26.974302],"type":"Point"}
}