{
  "type": "Feature",
  "properties": {
    "gn:admin1_code":"11.0",
    "gn:admin2_code":"32.0",
    "gn:asciiname":"Simbal",
    "gn:country_code":"IN",
    "gn:dem":1180,
    "gn:feature_class":"P",
    "gn:feature_code":"PPL",
    "gn:name":"Simbal",
    "gn:population":0,
    "gn:timezone":"Asia/Kolkata",
    "iso:country":"IN",
    "name:cat_x_preferred":[
        "Simbal"
    ],
    "name:spa_x_preferred":[
        "Simbal"
    ],
    "wof:name":"Simbal",
    "wof:placetype":"locality"
},
  "geometry": {"coordinates":[77.10195,30.81341],"type":"Point"}
}