{
  "type": "Feature",
  "properties": {
    "iso:country":"IN",
    "ks:ks_name":"Kambakuruchivayal",
    "ks:ks_pop":100,
    "ks:ks_type":"HABITATION",
    "name:eng_x_preferred":[
        "Kambakuruchivayal"
    ],
    "wof:name":"Kambakuruchivayal",
    "wof:placetype":"locality",
    "wof:population":100
},
  "geometry": {"coordinates":[78.761343,10.617006],"type":"Point"}
}