{
  "type": "Feature",
  "properties": {
    "gn:admin1_code":"34.0",
    "gn:admin2_code":"203.0",
    "gn:asciiname":"Baldiha",
    "gn:country_code":"IN",
    "gn:dem":85,
    "gn:feature_class":"P",
    "gn:feature_code":"PPL",
    "gn:name":"Bald\u012bha",
    "gn:population":0,
    "gn:timezone":"Asia/Kolkata",
    "iso:country":"IN",
    "ks:ks_alt_nam":"Bald\u012bha",
    "ks:ks_name":"Baldiha",
    "ks:ks_pop":1633,
    "ks:ks_type":"VILLAGE",
    "ks:ks_uagg_main":0,
    "name:eng_x_preferred":[
        "Baldiha"
    ],
    "name:eng_x_variant":[
        "Bald\u012bha"
    ],
    "wof:name":"Baldiha",
    "wof:placetype":"neighbourhood",
    "wof:population":1633
},
  "geometry": {"coordinates":[84.335065,26.947025],"type":"Point"}
}