{
  "type": "Feature",
  "properties": {
    "iso:country":"IN",
    "ks:ks_alt_nam":"Peda HPeta",
    "ks:ks_name":"Peda Hpeta",
    "ks:ks_pop":228,
    "ks:ks_type":"HABITATION",
    "name:eng_x_preferred":[
        "Peda Hpeta"
    ],
    "wof:name":"Peda Hpeta",
    "wof:placetype":"locality",
    "wof:population":228
},
  "geometry": {"coordinates":[81.97725699999999,16.612878],"type":"Point"}
}