{
  "type": "Feature",
  "properties": {
    "iso:country":"IN",
    "name:ara_x_preferred":[
        "\u0634\u064a\u0641\u0627\u062c\u064a\u0631\u064a \u062a\u0631\u0627\u064a\u0644\u0633"
    ],
    "name:ben_bn_x_preferred":[
        "\u09b6\u09bf\u09ac\u0997\u09bf\u09b0\u09bf \u099f\u09cd\u09b0\u09c7\u0987\u09b2\u09b8"
    ],
    "name:ben_in_x_preferred":[
        "\u09b6\u09bf\u09ac\u0997\u09bf\u09b0\u09bf \u099f\u09cd\u09b0\u09c7\u0987\u09b2\u09b8"
    ],
    "name:eng_x_preferred":[
        "Shivigiri Trails"
    ],
    "name:guj_x_preferred":[
        "\u0ab6\u0abf\u0ab5\u0abf\u0a97\u0abf\u0ab0\u0abf \u0a97\u0abe\u0aa1\u0ac0\u0a93"
    ],
    "name:hin_x_preferred":[
        "\u0936\u093f\u0935\u0940\u0917\u093f\u0930\u0940 \u091f\u094d\u0930\u0947\u0932\u094d\u0938"
    ],
    "name:kan_x_preferred":[
        "\u0cb6\u0cbf\u0cb5\u0c97\u0cbf\u0cb0\u0cbf \u0c9f\u0ccd\u0cb0\u0cc7\u0cb2\u0ccd\u0cb8\u0ccd"
    ],
    "name:mal_x_preferred":[
        "\u0d36\u0d3f\u0d35\u0d3f\u0d17\u0d3f\u0d30\u0d3f \u0d2a\u0d3e\u0d24\u0d15\u0d7e"
    ],
    "name:mar_x_preferred":[
        "\u0936\u093f\u0935\u0917\u093f\u0930\u0940 \u091f\u094d\u0930\u0947\u0932\u094d\u0938"
    ],
    "name:pan_x_preferred":[
        "\u0a36\u0a3f\u0a35\u0a17\u0a3f\u0a30\u0a40 \u0a1f\u0a30\u0a47\u0a32\u0a1c\u0a3c"
    ],
    "name:tam_x_preferred":[
        "\u0bb7\u0bbf\u0bb5\u0b95\u0bbf\u0bb0\u0bbf \u0baa\u0bbe\u0ba4\u0bc8\u0b95\u0bb3\u0bcd"
    ],
    "name:tel_x_preferred":[
        "\u0c36\u0c3f\u0c35\u0c17\u0c3f\u0c30\u0c3f \u0c1f\u0c4d\u0c30\u0c46\u0c2f\u0c3f\u0c32\u0c4d\u0c38\u0c4d"
    ],
    "name:urd_x_preferred":[
        "\u0634\u06cc\u0648\u06cc\u06af\u06cc\u0631\u06cc \u0679\u0631\u0627\u0626\u0644\u0632"
    ],
    "qs:gn_adm0_cc":"IN",
    "qs:gn_local":1273574,
    "qs:gn_nam_loc":"dandeli",
    "qs:gn_namadm1":"19",
    "qs:local_max":80,
    "qs:local_sum":80,
    "qs:localhoods":1,
    "qs:name":"Shivigiri Trails",
    "qs:name_adm0":"India",
    "qs:name_adm1":"Karnataka",
    "qs:name_adm2":"Uttara Kannada",
    "qs:name_local":"Dandeli",
    "qs:photo_max":27,
    "qs:photo_sum":80,
    "qs:placetype":"Suburb",
    "qs:quad_count":8,
    "qs:woe_adm0":23424848,
    "qs:woe_adm1":2345753,
    "qs:woe_adm2":12586590,
    "qs:woe_lau":0,
    "qs:woe_local":2295254,
    "qs:woe_ver":"7.10.0",
    "wof:lang":[
        "eng"
    ],
    "wof:name":"Shivigiri Trails",
    "wof:placetype":"neighbourhood"
},
  "geometry": {"coordinates":[74.62133799999999,15.254708],"type":"Point"}
}