{
  "type": "Feature",
  "properties": {
    "iso:country":"IN",
    "name:eng_x_preferred":[
        "Shivigiri Trails"
    ],
    "qs:gn_adm0_cc":"IN",
    "qs:gn_local":1273574,
    "qs:gn_nam_loc":"dandeli",
    "qs:gn_namadm1":"19",
    "qs:local_max":80,
    "qs:local_sum":80,
    "qs:localhoods":1,
    "qs:name":"Shivigiri Trails",
    "qs:name_adm0":"India",
    "qs:name_adm1":"Karnataka",
    "qs:name_adm2":"Uttara Kannada",
    "qs:name_local":"Dandeli",
    "qs:photo_max":27,
    "qs:photo_sum":80,
    "qs:placetype":"Suburb",
    "qs:quad_count":8,
    "qs:woe_adm0":23424848,
    "qs:woe_adm1":2345753,
    "qs:woe_adm2":12586590,
    "qs:woe_lau":0,
    "qs:woe_local":2295254,
    "qs:woe_ver":"7.10.0",
    "wof:lang":[
        "eng"
    ],
    "wof:name":"Shivigiri Trails",
    "wof:placetype":"neighbourhood"
},
  "geometry": {"coordinates":[74.62133799999999,15.254708],"type":"Point"}
}