{
  "type": "Feature",
  "properties": {
    "gn:admin1_code":"23.0",
    "gn:admin2_code":"49.0",
    "gn:asciiname":"Kammoke",
    "gn:country_code":"IN",
    "gn:dem":234,
    "gn:feature_class":"P",
    "gn:feature_code":"PPL",
    "gn:name":"Kammoke",
    "gn:population":0,
    "gn:timezone":"Asia/Kolkata",
    "iso:country":"IN",
    "ks:ks_name":"Kammoke",
    "ks:ks_pop":1474,
    "ks:ks_type":"VILLAGE",
    "name:eng_x_preferred":[
        "Kammoke"
    ],
    "wof:name":"Kammoke",
    "wof:placetype":"locality",
    "wof:population":1474
},
  "geometry": {"coordinates":[75.32568000000001,31.615626],"type":"Point"}
}