{
  "type": "Feature",
  "properties": {
    "iso:country":"IN",
    "ks:ks_name":"Devpara Anandpur",
    "ks:ks_pop":1124,
    "ks:ks_type":"HABITATION",
    "name:eng_x_preferred":[
        "Devpara Anandpur"
    ],
    "wof:name":"Devpara Anandpur",
    "wof:placetype":"locality",
    "wof:population":1124
},
  "geometry": {"coordinates":[71.18154800000001,22.230714],"type":"Point"}
}