{
  "type": "Feature",
  "properties": {
    "iso:country":"IN",
    "ks:ks_name":"Sudalakkollai",
    "ks:ks_pop":200,
    "ks:ks_type":"HABITATION",
    "name:eng_x_preferred":[
        "Sudalakkollai"
    ],
    "wof:name":"Sudalakkollai",
    "wof:placetype":"locality",
    "wof:population":200
},
  "geometry": {"coordinates":[78.987345,10.398383],"type":"Point"}
}