{
  "type": "Feature",
  "properties": {
    "gn:admin1_code":"19.0",
    "gn:admin2_code":"565.0",
    "gn:asciiname":"Maturu",
    "gn:country_code":"IN",
    "gn:dem":352,
    "gn:feature_class":"P",
    "gn:feature_code":"PPL",
    "gn:name":"M\u0101t\u016bru",
    "gn:population":0,
    "gn:timezone":"Asia/Kolkata",
    "iso:country":"IN",
    "ks:ks_name":"Matur",
    "ks:ks_pop":498,
    "ks:ks_type":"VILLAGE",
    "name:eng_x_preferred":[
        "Matur"
    ],
    "name:eng_x_variant":[
        "Maturu"
    ],
    "wof:name":"Matur",
    "wof:placetype":"locality",
    "wof:population":498
},
  "geometry": {"coordinates":[77.016471,15.815892],"type":"Point"}
}