{
  "type": "Feature",
  "properties": {
    "iso:country":"IN",
    "ks:ks_name":"Kurthia",
    "ks:ks_pop":452,
    "ks:ks_type":"HABITATION",
    "name:eng_x_preferred":[
        "Kurthia"
    ],
    "wof:name":"Kurthia",
    "wof:placetype":"locality",
    "wof:population":452
},
  "geometry": {"coordinates":[82.90264000000001,27.043414],"type":"Point"}
}