{
  "type": "Feature",
  "properties": {
    "iso:country":"IN",
    "ks:ks_alt_nam":"PURE MATH",
    "ks:ks_name":"Pure Math",
    "ks:ks_pop":335,
    "ks:ks_type":"HABITATION",
    "name:eng_x_preferred":[
        "Pure Math"
    ],
    "wof:name":"Pure Math",
    "wof:placetype":"locality",
    "wof:population":335
},
  "geometry": {"coordinates":[81.4903,26.4456],"type":"Point"}
}