{
  "type": "Feature",
  "properties": {
    "iso:country":"IN",
    "ks:ks_name":"Thota Para",
    "ks:ks_pop":100,
    "ks:ks_type":"HABITATION",
    "name:eng_x_preferred":[
        "Thota Para"
    ],
    "wof:name":"Thota Para",
    "wof:placetype":"locality",
    "wof:population":100
},
  "geometry": {"coordinates":[81.76558300000001,19.195671],"type":"Point"}
}