{
  "type": "Feature",
  "properties": {
    "iso:country":"IN",
    "ks:ks_name":"Purankadu",
    "ks:ks_pop":307,
    "ks:ks_type":"HABITATION",
    "name:eng_x_preferred":[
        "Purankadu"
    ],
    "wof:name":"Purankadu",
    "wof:placetype":"locality",
    "wof:population":307
},
  "geometry": {"coordinates":[79.13343,10.146987],"type":"Point"}
}