{
  "type": "Feature",
  "properties": {
    "gn:admin1_code":"12.0",
    "gn:admin2_code":"1.0",
    "gn:asciiname":"Bad Bair",
    "gn:country_code":"IN",
    "gn:dem":1734,
    "gn:feature_class":"P",
    "gn:feature_code":"PPL",
    "gn:name":"Bad Bair",
    "gn:population":0,
    "gn:timezone":"Asia/Kolkata",
    "iso:country":"IN",
    "wof:name":"Bad Bair",
    "wof:placetype":"locality"
},
  "geometry": {"coordinates":[74.41399,34.51219],"type":"Point"}
}