{
  "type": "Feature",
  "properties": {
    "iso:country":"IN",
    "ks:ks_name":"Narendranagar",
    "ks:ks_pop":144,
    "ks:ks_type":"HABITATION",
    "ks:ks_uagg_main":0,
    "name:eng_x_preferred":[
        "Narendranagar"
    ],
    "wof:name":"Narendranagar",
    "wof:placetype":"neighbourhood",
    "wof:population":144
},
  "geometry": {"coordinates":[81.299072,25.992687],"type":"Point"}
}