{
  "type": "Feature",
  "properties": {
    "iso:country":"IN",
    "ks:ks_name":"Khadakiya",
    "ks:ks_pop":115,
    "ks:ks_type":"VILLAGE",
    "name:eng_x_preferred":[
        "Khadakiya"
    ],
    "wof:name":"Khadakiya",
    "wof:placetype":"locality",
    "wof:population":115
},
  "geometry": {"coordinates":[73.82699100000001,22.05859],"type":"Point"}
}