{
  "type": "Feature",
  "properties": {
    "iso:country":"IN",
    "ks:ks_name":"Kulinjal",
    "ks:ks_pop":896,
    "ks:ks_type":"HABITATION",
    "name:eng_x_preferred":[
        "Kulinjal"
    ],
    "wof:name":"Kulinjal",
    "wof:placetype":"locality",
    "wof:population":896
},
  "geometry": {"coordinates":[75.936589,11.712532],"type":"Point"}
}