{
  "type": "Feature",
  "properties": {
    "iso:country":"IN",
    "ks:ks_name":"Kothamadigapalle",
    "ks:ks_pop":76,
    "ks:ks_type":"HABITATION",
    "name:eng_x_preferred":[
        "Kothamadigapalle"
    ],
    "wof:name":"Kothamadigapalle",
    "wof:placetype":"locality",
    "wof:population":76
},
  "geometry": {"coordinates":[78.70167499999999,14.151668],"type":"Point"}
}