{
  "type": "Feature",
  "properties": {
    "iso:country":"IN",
    "ks:ks_name":"Kilwapur",
    "ks:ks_pop":406,
    "ks:ks_type":"VILLAGE",
    "ks:ks_uagg_main":0,
    "name:eng_x_preferred":[
        "Kilwapur"
    ],
    "wof:name":"Kilwapur",
    "wof:placetype":"neighbourhood",
    "wof:population":406
},
  "geometry": {"coordinates":[79.933626,26.998947],"type":"Point"}
}