{
  "type": "Feature",
  "properties": {
    "gn:admin1_code":"35",
    "gn:admin2_code":"425.0",
    "gn:asciiname":"Siddhpur",
    "gn:country_code":"IN",
    "gn:dem":191,
    "gn:feature_class":"P",
    "gn:feature_code":"PPL",
    "gn:name":"Siddhpur",
    "gn:population":0,
    "gn:timezone":"Asia/Kolkata",
    "iso:country":"IN",
    "name:bpy_x_preferred":[
        "\u09b8\u09bf\u09a7\u09aa\u09c1\u09b0"
    ],
    "name:cat_x_preferred":[
        "Sidhpur"
    ],
    "name:ceb_x_preferred":[
        "Siddhapur"
    ],
    "name:fra_x_preferred":[
        "Sidhpur"
    ],
    "name:guj_x_preferred":[
        "\u0ab8\u0abf\u0aa6\u0acd\u0aa7\u0aaa\u0ac1\u0ab0"
    ],
    "name:hin_x_preferred":[
        "\u0938\u093f\u0926\u094d\u0927\u092a\u0941\u0930"
    ],
    "name:ita_x_preferred":[
        "Sidhpur"
    ],
    "name:msa_x_preferred":[
        "Sidhpur"
    ],
    "name:ori_x_preferred":[
        "\u0b38\u0b3f\u0b26\u0b4d\u0b27\u0b2a\u0b41\u0b30"
    ],
    "name:pnb_x_preferred":[
        "\u0633\u062f\u06be\u067e\u0648\u0631"
    ],
    "name:san_x_preferred":[
        "\u092e\u093e\u0924\u0943\u0917\u092f\u093e"
    ],
    "name:spa_x_preferred":[
        "Sidhpur"
    ],
    "name:swe_x_preferred":[
        "Siddhapur"
    ],
    "name:vie_x_preferred":[
        "Sidhpur"
    ],
    "name:zho_x_preferred":[
        "\u897f\u5fb7\u666e\u5c14"
    ],
    "wof:name":"Siddhpur",
    "wof:placetype":"locality"
},
  "geometry": {"coordinates":[80.16251,25.07016],"type":"Point"}
}