{
  "type": "Feature",
  "properties": {
    "gn:admin1_code":"34.0",
    "gn:admin2_code":"223.0",
    "gn:asciiname":"Tartar",
    "gn:country_code":"IN",
    "gn:dem":42,
    "gn:feature_class":"P",
    "gn:feature_code":"PPL",
    "gn:name":"T\u0101rtar",
    "gn:population":0,
    "gn:timezone":"Asia/Kolkata",
    "iso:country":"IN",
    "name:bre_x_preferred":[
        "Tartar"
    ],
    "name:cat_x_preferred":[
        "T\u00e0rtar"
    ],
    "name:deu_x_preferred":[
        "Tartar"
    ],
    "name:fas_x_preferred":[
        "\u062a\u0627\u0631\u062a\u0627\u0631"
    ],
    "name:fin_x_preferred":[
        "Tartar"
    ],
    "name:fra_x_preferred":[
        "Tartar"
    ],
    "name:hrv_x_preferred":[
        "Tartar"
    ],
    "name:ita_x_preferred":[
        "Tartar"
    ],
    "name:jpn_x_preferred":[
        "\u30bf\u30eb\u30bf\u30eb"
    ],
    "name:slk_x_preferred":[
        "Tartar"
    ],
    "name:swe_x_preferred":[
        "Tartar"
    ],
    "name:ukr_x_preferred":[
        "\u0422\u0430\u0440\u0442\u0430\u0440"
    ],
    "wof:name":"Tartar",
    "wof:placetype":"locality"
},
  "geometry": {"coordinates":[86.43809,25.47378],"type":"Point"}
}