{
  "type": "Feature",
  "properties": {
    "iso:country":"IN",
    "ks:ks_name":"Jukala",
    "ks:ks_pop":3,
    "ks:ks_type":"VILLAGE",
    "name:eng_x_preferred":[
        "Jukala"
    ],
    "wof:name":"Jukala",
    "wof:placetype":"locality",
    "wof:population":3
},
  "geometry": {"coordinates":[78.441805,30.034467],"type":"Point"}
}