{
  "type": "Feature",
  "properties": {
    "gn:admin1_code":"34.0",
    "gn:admin2_code":"235.0",
    "gn:asciiname":"Adma",
    "gn:country_code":"IN",
    "gn:dem":100,
    "gn:feature_class":"P",
    "gn:feature_code":"PPL",
    "gn:name":"Adma",
    "gn:population":0,
    "gn:timezone":"Asia/Kolkata",
    "iso:country":"IN",
    "wof:name":"Adma",
    "wof:placetype":"locality"
},
  "geometry": {"coordinates":[84.39299,24.86723],"type":"Point"}
}