{
  "type": "Feature",
  "properties": {
    "gn:admin1_code":"34.0",
    "gn:admin2_code":"219.0",
    "gn:asciiname":"Edilpur",
    "gn:country_code":"IN",
    "gn:dem":58,
    "gn:feature_class":"P",
    "gn:feature_code":"PPL",
    "gn:name":"Edilpur",
    "gn:population":0,
    "gn:timezone":"Asia/Kolkata",
    "iso:country":"IN",
    "ks:ks_name":"Edilpur",
    "ks:ks_pop":870,
    "ks:ks_type":"VILLAGE",
    "ks:ks_uagg_main":0,
    "name:eng_x_preferred":[
        "Edilpur"
    ],
    "wof:name":"Edilpur",
    "wof:placetype":"neighbourhood",
    "wof:population":870
},
  "geometry": {"coordinates":[85.114132,25.854803],"type":"Point"}
}