{
  "type": "Feature",
  "properties": {
    "iso:country":"IN",
    "ks:ks_alt_nam":"Pagh\u0101ri",
    "ks:ks_name":"Paghari",
    "ks:ks_pop":3188,
    "ks:ks_type":"VILLAGE",
    "ks:ks_uagg_main":0,
    "name:eng_x_preferred":[
        "Paghari"
    ],
    "name:eng_x_variant":[
        "Pagh\u0101ri"
    ],
    "wof:name":"Paghari",
    "wof:placetype":"neighbourhood",
    "wof:population":3188
},
  "geometry": {"coordinates":[86.29129500000001,25.90381],"type":"Point"}
}