{
  "type": "Feature",
  "properties": {
    "gn:admin1_code":"37",
    "gn:admin2_code":"414.0",
    "gn:asciiname":"Gumalvada",
    "gn:country_code":"IN",
    "gn:dem":504,
    "gn:feature_class":"P",
    "gn:feature_code":"PPL",
    "gn:name":"Gumalv\u0101da",
    "gn:population":0,
    "gn:timezone":"Asia/Kolkata",
    "iso:country":"IN",
    "wof:name":"Gumalvada",
    "wof:placetype":"locality"
},
  "geometry": {"coordinates":[82.13441,18.90631],"type":"Point"}
}