{
  "type": "Feature",
  "properties": {
    "gn:admin1_code":"37",
    "gn:admin2_code":"414.0",
    "gn:asciiname":"Gumalvada",
    "gn:country_code":"IN",
    "gn:dem":504,
    "gn:feature_class":"P",
    "gn:feature_code":"PPL",
    "gn:name":"Gumalv\u0101da",
    "gn:population":0,
    "gn:timezone":"Asia/Kolkata",
    "iso:country":"IN",
    "ks:ks_alt_nam":"Gumalv\u0101da",
    "ks:ks_name":"Gumalvada",
    "ks:ks_pop":415,
    "ks:ks_type":"VILLAGE",
    "name:eng_x_preferred":[
        "Gumalvada"
    ],
    "name:eng_x_variant":[
        "Gumalv\u0101da"
    ],
    "wof:name":"Gumalvada",
    "wof:placetype":"locality",
    "wof:population":415
},
  "geometry": {"coordinates":[82.13440900000001,18.906312],"type":"Point"}
}