{
  "type": "Feature",
  "properties": {
    "iso:country":"IN",
    "ks:ks_name":"Pandeypurva",
    "ks:ks_pop":211,
    "ks:ks_type":"HABITATION",
    "ks:ks_uagg_main":0,
    "name:eng_x_preferred":[
        "Pandeypurva"
    ],
    "wof:name":"Pandeypurva",
    "wof:placetype":"neighbourhood",
    "wof:population":211
},
  "geometry": {"coordinates":[82.17117500000001,27.61362],"type":"Point"}
}