{
  "type": "Feature",
  "properties": {
    "iso:country":"IN",
    "ks:ks_name":"Santipur 1",
    "ks:ks_pop":203,
    "ks:ks_type":"HABITATION",
    "name:eng_x_preferred":[
        "Santipur 1"
    ],
    "wof:name":"Santipur 1",
    "wof:placetype":"locality",
    "wof:population":203
},
  "geometry": {"coordinates":[91.443651,26.577314],"type":"Point"}
}