{
  "type": "Feature",
  "properties": {
    "gn:admin1_code":"19.0",
    "gn:admin2_code":"582.0",
    "gn:asciiname":"Kachanayakanahalli",
    "gn:country_code":"IN",
    "gn:dem":843,
    "gn:feature_class":"P",
    "gn:feature_code":"PPL",
    "gn:name":"Kachanayak\u0101nahalli",
    "gn:population":0,
    "gn:timezone":"Asia/Kolkata",
    "iso:country":"IN",
    "wof:name":"Kachanayakanahalli",
    "wof:placetype":"locality"
},
  "geometry": {"coordinates":[77.88038,13.52246],"type":"Point"}
}