{
  "type": "Feature",
  "properties": {
    "iso:country":"IN",
    "ks:ks_name":"Begampet",
    "ks:ks_type":"VILLAGE",
    "ks:ks_uagg_main":0,
    "name:eng_x_preferred":[
        "Begampet"
    ],
    "wof:name":"Begampet",
    "wof:placetype":"neighbourhood"
},
  "geometry": {"coordinates":[78.462564,17.444911],"type":"Point"}
}