{
  "type": "Feature",
  "properties": {
    "iso:country":"IN",
    "ks:ks_name":"Muna Kote",
    "ks:ks_pop":714,
    "ks:ks_type":"VILLAGE",
    "name:eng_x_preferred":[
        "Muna Kote"
    ],
    "wof:name":"Muna Kote",
    "wof:placetype":"locality",
    "wof:population":714
},
  "geometry": {"coordinates":[80.292952,29.571542],"type":"Point"}
}