{
  "type": "Feature",
  "properties": {
    "iso:country":"IN",
    "ks:ks_name":"Dubbagudam",
    "ks:ks_pop":54,
    "ks:ks_type":"VILLAGE",
    "name:eng_x_preferred":[
        "Dubbagudam"
    ],
    "wof:name":"Dubbagudam",
    "wof:placetype":"locality",
    "wof:population":54
},
  "geometry": {"coordinates":[80.00386,19.08834],"type":"Point"}
}