{
  "type": "Feature",
  "properties": {
    "iso:country":"IN",
    "ks:ks_name":"Kirakumbathi",
    "ks:ks_pop":28,
    "ks:ks_type":"HABITATION",
    "name:eng_x_preferred":[
        "Kirakumbathi"
    ],
    "wof:name":"Kirakumbathi",
    "wof:placetype":"locality",
    "wof:population":28
},
  "geometry": {"coordinates":[74.73201,14.872307],"type":"Point"}
}