{
  "type": "Feature",
  "properties": {
    "gn:admin1_code":"11.0",
    "gn:admin2_code":"32.0",
    "gn:asciiname":"Dera",
    "gn:country_code":"IN",
    "gn:dem":1269,
    "gn:feature_class":"P",
    "gn:feature_code":"PPL",
    "gn:name":"Dera",
    "gn:population":0,
    "gn:timezone":"Asia/Kolkata",
    "iso:country":"IN",
    "name:fra_x_preferred":[
        "Dera"
    ],
    "name:snd_x_preferred":[
        "\u062f\u064a\u0631\u0648"
    ],
    "name:urd_x_preferred":[
        "\u0688\u06cc\u0631\u06c1"
    ],
    "wof:name":"Dera",
    "wof:placetype":"locality"
},
  "geometry": {"coordinates":[77.31525000000001,30.70808],"type":"Point"}
}