{
  "type": "Feature",
  "properties": {
    "iso:country":"IN",
    "ks:ks_name":"Narangi",
    "ks:ks_pop":34,
    "ks:ks_type":"VILLAGE",
    "name:eng_x_preferred":[
        "Narangi"
    ],
    "wof:name":"Narangi",
    "wof:placetype":"locality",
    "wof:population":34
},
  "geometry": {"coordinates":[78.375169,30.334007],"type":"Point"}
}