{
  "type": "Feature",
  "properties": {
    "gn:admin1_code":"11",
    "gn:admin2_code":"28.0",
    "gn:asciiname":"Jalari Bhandiaran",
    "gn:country_code":"IN",
    "gn:dem":563,
    "gn:feature_class":"P",
    "gn:feature_code":"PPL",
    "gn:name":"Jal\u0101ri Bhandi\u0101r\u0101n",
    "gn:population":0,
    "gn:timezone":"Asia/Kolkata",
    "iso:country":"IN",
    "wof:name":"Jalari Bhandiaran",
    "wof:placetype":"locality"
},
  "geometry": {"coordinates":[76.37085,31.76158],"type":"Point"}
}