{
  "type": "Feature",
  "properties": {
    "iso:country":"IN",
    "ks:ks_name":"Notiyar Bhakhari",
    "ks:ks_pop":110,
    "ks:ks_type":"VILLAGE",
    "name:eng_x_preferred":[
        "Notiyar Bhakhari"
    ],
    "wof:name":"Notiyar Bhakhari",
    "wof:placetype":"locality",
    "wof:population":110
},
  "geometry": {"coordinates":[69.613208,23.368704],"type":"Point"}
}