{
  "type": "Feature",
  "properties": {
    "iso:country":"IN",
    "ks:ks_name":"Dharahara",
    "ks:ks_pop":435,
    "ks:ks_type":"HABITATION",
    "name:eng_x_preferred":[
        "Dharahara"
    ],
    "wof:name":"Dharahara",
    "wof:placetype":"locality",
    "wof:population":435
},
  "geometry": {"coordinates":[82.43898900000001,25.640704],"type":"Point"}
}