{
  "type": "Feature",
  "properties": {
    "iso:country":"IN",
    "ks:ks_name":"Uleikundi",
    "ks:ks_pop":458,
    "ks:ks_type":"VILLAGE",
    "name:eng_x_preferred":[
        "Uleikundi"
    ],
    "wof:name":"Uleikundi",
    "wof:placetype":"locality",
    "wof:population":458
},
  "geometry": {"coordinates":[85.829331,21.901348],"type":"Point"}
}