{
  "type": "Feature",
  "properties": {
    "iso:country":"IN",
    "ks:ks_name":"Chholabald",
    "ks:ks_pop":182,
    "ks:ks_type":"HABITATION",
    "name:eng_x_preferred":[
        "Chholabald"
    ],
    "wof:name":"Chholabald",
    "wof:placetype":"locality",
    "wof:population":182
},
  "geometry": {"coordinates":[87.026856,23.389389],"type":"Point"}
}