{
  "type": "Feature",
  "properties": {
    "iso:country":"IN",
    "ks:ks_name":"Demupadar",
    "ks:ks_pop":92,
    "ks:ks_type":"VILLAGE",
    "name:eng_x_preferred":[
        "Demupadar"
    ],
    "wof:name":"Demupadar",
    "wof:placetype":"locality",
    "wof:population":92
},
  "geometry": {"coordinates":[83.491587,19.930112],"type":"Point"}
}