{
  "type": "Feature",
  "properties": {
    "gn:admin1_code":"36",
    "gn:admin2_code":"172.0",
    "gn:asciiname":"Kodhai",
    "gn:country_code":"IN",
    "gn:dem":120,
    "gn:feature_class":"P",
    "gn:feature_code":"PPL",
    "gn:name":"Kodha\u012b",
    "gn:population":0,
    "gn:timezone":"Asia/Kolkata",
    "iso:country":"IN",
    "wof:name":"Kodhai",
    "wof:placetype":"locality"
},
  "geometry": {"coordinates":[80.75802,25.92938],"type":"Point"}
}