{
  "type": "Feature",
  "properties": {
    "gn:admin1_code":"16.0",
    "gn:asciiname":"Karadge",
    "gn:country_code":"IN",
    "gn:dem":547,
    "gn:feature_class":"P",
    "gn:feature_code":"PPL",
    "gn:name":"Karadge",
    "gn:population":0,
    "gn:timezone":"Asia/Kolkata",
    "iso:country":"IN",
    "name:und_x_variant":[
        "K\u00e1radga",
        "Karadge"
    ],
    "wof:name":"Karadge",
    "wof:placetype":"neighbourhood"
},
  "geometry": {"coordinates":[74.44624,16.56692],"type":"Point"}
}