{
  "type": "Feature",
  "properties": {
    "gn:admin1_code":"36",
    "gn:admin2_code":"180.0",
    "gn:asciiname":"Jogin Purwa",
    "gn:country_code":"IN",
    "gn:dem":115,
    "gn:feature_class":"P",
    "gn:feature_code":"PPL",
    "gn:name":"Jogin Purwa",
    "gn:population":0,
    "gn:timezone":"Asia/Kolkata",
    "iso:country":"IN",
    "ks:ks_name":"Joginapurwa",
    "ks:ks_pop":26,
    "ks:ks_type":"HABITATION",
    "name:eng_x_preferred":[
        "Joginapurwa"
    ],
    "name:eng_x_variant":[
        "Jogin Purwa"
    ],
    "wof:name":"Joginapurwa",
    "wof:placetype":"locality",
    "wof:population":26
},
  "geometry": {"coordinates":[81.526782,27.470335],"type":"Point"}
}