{
  "type": "Feature",
  "properties": {
    "iso:country":"IN",
    "ks:ks_name":"Tambadagewadi",
    "ks:ks_pop":201,
    "ks:ks_type":"HABITATION",
    "name:eng_x_preferred":[
        "Tambadagewadi"
    ],
    "wof:name":"Tambadagewadi",
    "wof:placetype":"locality",
    "wof:population":201
},
  "geometry": {"coordinates":[73.65070299999999,15.955229],"type":"Point"}
}