{
  "type": "Feature",
  "properties": {
    "iso:country":"IN",
    "ks:ks_name":"G Dhari Bagicha 70 88",
    "ks:ks_pop":172,
    "ks:ks_type":"HABITATION",
    "name:eng_x_preferred":[
        "G Dhari Bagicha 70 88"
    ],
    "wof:name":"G Dhari Bagicha 70 88",
    "wof:placetype":"locality",
    "wof:population":172
},
  "geometry": {"coordinates":[93.044996,26.833476],"type":"Point"}
}