{
  "type": "Feature",
  "properties": {
    "gn:admin1_code":"36",
    "gn:admin2_code":"195.0",
    "gn:asciiname":"Ghatampur",
    "gn:country_code":"IN",
    "gn:dem":67,
    "gn:feature_class":"P",
    "gn:feature_code":"PPL",
    "gn:name":"Gh\u0101tampur",
    "gn:population":0,
    "gn:timezone":"Asia/Kolkata",
    "iso:country":"IN",
    "name:bpy_x_preferred":[
        "\u0998\u09be\u09a4\u09be\u09ae\u09aa\u09c1\u09b0"
    ],
    "name:ceb_x_preferred":[
        "Gh\u0101tampur"
    ],
    "name:hin_x_preferred":[
        "\u0918\u093e\u091f\u092e\u092a\u0941\u0930"
    ],
    "name:ita_x_preferred":[
        "Ghatampur"
    ],
    "name:mlg_x_preferred":[
        "Ghatampur"
    ],
    "name:msa_x_preferred":[
        "Ghatampur"
    ],
    "name:new_x_preferred":[
        "\u0918\u0924\u092e\u094d\u092a\u0941\u0930"
    ],
    "name:nld_x_preferred":[
        "Ghatampur"
    ],
    "name:pol_x_preferred":[
        "Ghatampur"
    ],
    "name:por_x_preferred":[
        "Ghatampur"
    ],
    "name:swe_x_preferred":[
        "Gh\u0101tampur"
    ],
    "name:und_x_variant":[
        "Gh\u0101n\u0101pur"
    ],
    "name:urd_x_preferred":[
        "\u06af\u06be\u062a\u0645 \u067e\u0648\u0631"
    ],
    "name:vie_x_preferred":[
        "Ghatampur"
    ],
    "name:zho_x_preferred":[
        "\u52a0\u5854\u59c6\u666e\u5c14"
    ],
    "wof:name":"Ghatampur",
    "wof:placetype":"locality"
},
  "geometry": {"coordinates":[83.78867,25.4763],"type":"Point"}
}