{
  "type": "Feature",
  "properties": {
    "gn:admin1_code":"36",
    "gn:admin2_code":"195.0",
    "gn:asciiname":"Ghatampur",
    "gn:country_code":"IN",
    "gn:dem":67,
    "gn:feature_class":"P",
    "gn:feature_code":"PPL",
    "gn:name":"Gh\u0101tampur",
    "gn:population":0,
    "gn:timezone":"Asia/Kolkata",
    "iso:country":"IN",
    "name:und_x_variant":[
        "Gh\u0101tampur",
        "Gh\u0101n\u0101pur"
    ],
    "wof:name":"Ghatampur",
    "wof:placetype":"locality"
},
  "geometry": {"coordinates":[83.78867,25.4763],"type":"Point"}
}