{
  "type": "Feature",
  "properties": {
    "iso:country":"IN",
    "ks:ks_name":"Chatariya Kheri",
    "ks:ks_pop":446,
    "ks:ks_type":"VILLAGE",
    "name:eng_x_preferred":[
        "Chatariya Kheri"
    ],
    "wof:name":"Chatariya Kheri",
    "wof:placetype":"locality",
    "wof:population":446
},
  "geometry": {"coordinates":[74.74253299999999,23.992132],"type":"Point"}
}