{
  "type": "Feature",
  "properties": {
    "gn:admin1_code":"24.0",
    "gn:admin2_code":"114.0",
    "gn:asciiname":"Sutarwala Tibba",
    "gn:country_code":"IN",
    "gn:dem":114,
    "gn:feature_class":"P",
    "gn:feature_code":"PPL",
    "gn:name":"Sut\u0101rw\u0101la Tibba",
    "gn:population":0,
    "gn:timezone":"Asia/Kolkata",
    "iso:country":"IN",
    "wof:name":"Sutarwala Tibba",
    "wof:placetype":"locality"
},
  "geometry": {"coordinates":[71.11651999999999,27.57993],"type":"Point"}
}