{
  "type": "Feature",
  "properties": {
    "gn:admin1_code":"35",
    "gn:admin2_code":"430.0",
    "gn:asciiname":"Khairhan",
    "gn:country_code":"IN",
    "gn:dem":313,
    "gn:feature_class":"P",
    "gn:feature_code":"PPL",
    "gn:name":"Khairh\u0101n",
    "gn:population":0,
    "gn:timezone":"Asia/Kolkata",
    "iso:country":"IN",
    "ks:ks_alt_nam":"Khairh\u0101n",
    "ks:ks_name":"Khairhan",
    "ks:ks_pop":1779,
    "ks:ks_type":"VILLAGE",
    "name:eng_x_preferred":[
        "Khairhan"
    ],
    "name:eng_x_variant":[
        "Khairh\u0101n"
    ],
    "wof:name":"Khairhan",
    "wof:placetype":"locality",
    "wof:population":1779
},
  "geometry": {"coordinates":[81.387981,24.795102],"type":"Point"}
}