{
  "type": "Feature",
  "properties": {
    "gn:admin1_code":"25.0",
    "gn:admin2_code":"609.0",
    "gn:asciiname":"Velakavundanpalaiyam",
    "gn:country_code":"IN",
    "gn:dem":189,
    "gn:feature_class":"P",
    "gn:feature_code":"PPL",
    "gn:name":"Vel\u0101kavundanp\u0101laiyam",
    "gn:population":0,
    "gn:timezone":"Asia/Kolkata",
    "iso:country":"IN",
    "wof:name":"Velakavundanpalaiyam",
    "wof:placetype":"neighbourhood"
},
  "geometry": {"coordinates":[77.83199999999999,11.33013],"type":"Point"}
}