{
  "type": "Feature",
  "properties": {
    "gn:admin1_code":"37",
    "gn:admin2_code":"407.0",
    "gn:asciiname":"Partapgarh",
    "gn:country_code":"IN",
    "gn:dem":730,
    "gn:feature_class":"P",
    "gn:feature_code":"PPL",
    "gn:name":"Part\u0101pgarh",
    "gn:population":0,
    "gn:timezone":"Asia/Kolkata",
    "iso:country":"IN",
    "ks:ks_name":"Pratapgarh",
    "ks:ks_pop":25,
    "ks:ks_type":"HABITATION",
    "name:eng_x_preferred":[
        "Pratapgarh"
    ],
    "name:eng_x_variant":[
        "Partapgarh"
    ],
    "wof:name":"Pratapgarh",
    "wof:placetype":"locality",
    "wof:population":25
},
  "geometry": {"coordinates":[81.06024600000001,22.022605],"type":"Point"}
}