{
  "type": "Feature",
  "properties": {
    "iso:country":"IN",
    "ks:ks_name":"Khatik Tola",
    "ks:ks_pop":350,
    "ks:ks_type":"HABITATION",
    "name:eng_x_preferred":[
        "Khatik Tola"
    ],
    "wof:name":"Khatik Tola",
    "wof:placetype":"locality",
    "wof:population":350
},
  "geometry": {"coordinates":[83.82383400000001,26.887518],"type":"Point"}
}