{
  "type": "Feature",
  "properties": {
    "gn:admin1_code":"23.0",
    "gn:admin2_code":"43.0",
    "gn:asciiname":"Chuharanwali",
    "gn:country_code":"IN",
    "gn:dem":180,
    "gn:feature_class":"P",
    "gn:feature_code":"PPL",
    "gn:name":"Chuh\u0101r\u0101nw\u0101li",
    "gn:population":0,
    "gn:timezone":"Asia/Kolkata",
    "iso:country":"IN",
    "name:und_x_variant":[
        "Chuh\u0101r\u0101nw\u0101li",
        "Pharw\u0101nw\u0101la"
    ],
    "wof:name":"Chuharanwali",
    "wof:placetype":"locality"
},
  "geometry": {"coordinates":[74.08783000000003,30.39167],"type":"Point"}
}