{
  "type": "Feature",
  "properties": {
    "iso:country":"IN",
    "ks:ks_name":"Basiviran",
    "ks:ks_pop":37,
    "ks:ks_type":"VILLAGE",
    "ks:ks_uagg_main":0,
    "name:eng_x_preferred":[
        "Basiviran"
    ],
    "wof:name":"Basiviran",
    "wof:placetype":"neighbourhood",
    "wof:population":37
},
  "geometry": {"coordinates":[77.967946,29.196604],"type":"Point"}
}