{
  "type": "Feature",
  "properties": {
    "iso:country":"IN",
    "ks:ks_alt_nam":"SHEKDARMALA",
    "ks:ks_name":"Shekdarmala",
    "ks:ks_pop":151,
    "ks:ks_type":"HABITATION",
    "name:eng_x_preferred":[
        "Shekdarmala"
    ],
    "wof:name":"Shekdarmala",
    "wof:placetype":"locality",
    "wof:population":151
},
  "geometry": {"coordinates":[74.91170700000001,17.423124],"type":"Point"}
}