{
  "type": "Feature",
  "properties": {
    "iso:country":"IN",
    "ks:ks_name":"Chunikaka Lat",
    "ks:ks_pop":134,
    "ks:ks_type":"HABITATION",
    "name:eng_x_preferred":[
        "Chunikaka Lat"
    ],
    "wof:name":"Chunikaka Lat",
    "wof:placetype":"locality",
    "wof:population":134
},
  "geometry": {"coordinates":[72.57799199999999,22.856689],"type":"Point"}
}