{
  "type": "Feature",
  "properties": {
    "gn:admin1_code":"13",
    "gn:admin2_code":"596.0",
    "gn:asciiname":"Pirmed",
    "gn:country_code":"IN",
    "gn:dem":996,
    "gn:feature_class":"P",
    "gn:feature_code":"PPL",
    "gn:name":"P\u012brmed",
    "gn:population":0,
    "gn:timezone":"Asia/Kolkata",
    "iso:country":"IN",
    "name:und_x_variant":[
        "Peermade",
        "P\u012brmed"
    ],
    "wof:name":"Pirmed",
    "wof:placetype":"locality"
},
  "geometry": {"coordinates":[76.99335000000001,9.57161],"type":"Point"}
}