{
  "type": "Feature",
  "properties": {
    "iso:country":"IN",
    "ks:ks_name":"Swamiji Ka Purwa",
    "ks:ks_pop":358,
    "ks:ks_type":"HABITATION",
    "name:eng_x_preferred":[
        "Swamiji Ka Purwa"
    ],
    "wof:name":"Swamiji Ka Purwa",
    "wof:placetype":"locality",
    "wof:population":358
},
  "geometry": {"coordinates":[81.000186,27.708917],"type":"Point"}
}