{
  "type": "Feature",
  "properties": {
    "gn:admin1_code":"35",
    "gn:admin2_code":"424.0",
    "gn:asciiname":"Dargain Kalan",
    "gn:country_code":"IN",
    "gn:dem":340,
    "gn:feature_class":"P",
    "gn:feature_code":"PPL",
    "gn:name":"Darg\u0101in Kal\u0101n",
    "gn:population":0,
    "gn:timezone":"Asia/Kolkata",
    "iso:country":"IN",
    "ks:ks_name":"Dargay Kalan",
    "ks:ks_pop":1171,
    "ks:ks_type":"VILLAGE",
    "name:eng_x_preferred":[
        "Dargay Kalan"
    ],
    "name:eng_x_variant":[
        "Dargain Kalan"
    ],
    "wof:name":"Dargay Kalan",
    "wof:placetype":"locality",
    "wof:population":1171
},
  "geometry": {"coordinates":[78.724327,24.976089],"type":"Point"}
}