{
  "type": "Feature",
  "properties": {
    "iso:country":"IN",
    "ks:ks_name":"Deoli Kalan",
    "ks:ks_pop":6432,
    "ks:ks_type":"VILLAGE",
    "name:eng_x_preferred":[
        "Deoli Kalan"
    ],
    "wof:name":"Deoli Kalan",
    "wof:placetype":"locality",
    "wof:population":6432
},
  "geometry": {"coordinates":[73.82748599999999,26.069672],"type":"Point"}
}