{
  "type": "Feature",
  "properties": {
    "iso:country":"IN",
    "name:ben_x_preferred":[
        "\u09b0\u09be\u09ae\u09a8\u0997\u09b0"
    ],
    "name:cat_x_preferred":[
        "Ramnagar"
    ],
    "name:ceb_x_preferred":[
        "Ramnagar"
    ],
    "name:fra_x_preferred":[
        "Ramnagar"
    ],
    "name:hin_x_preferred":[
        "\u0930\u093e\u092e\u0928\u0917\u0930"
    ],
    "name:new_x_preferred":[
        "\u0930\u093e\u092e\u0928\u0917\u0930"
    ],
    "name:nld_x_preferred":[
        "Ramnagar"
    ],
    "name:pol_x_preferred":[
        "Ramnagar"
    ],
    "name:rus_x_preferred":[
        "\u0420\u0430\u043c\u043d\u0430\u0433\u0430\u0440"
    ],
    "name:swe_x_preferred":[
        "Ramnagar"
    ],
    "qs:name":"Ramnagar",
    "qs:name_adm0":"India",
    "qs:name_adm1":"Uttar Pradesh",
    "qs:photos":1,
    "qs:photos_1k":1,
    "qs:photos_9k":1,
    "qs:photos_9r":1,
    "qs:photos_all":1,
    "qs:photos_sr":1,
    "qs:placetype":"Suburb",
    "qs:pop_sr":"0",
    "wd:wordcount":231,
    "wof:name":"Ramnagar",
    "wof:placetype":"neighbourhood"
},
  "geometry": {"coordinates":[78.977966,28.80497],"type":"Point"}
}