{
  "type": "Feature",
  "properties": {
    "iso:country":"IN",
    "ks:ks_name":"Venkatachalapuram",
    "ks:ks_pop":812,
    "ks:ks_type":"HABITATION",
    "name:eng_x_preferred":[
        "Venkatachalapuram"
    ],
    "wof:name":"Venkatachalapuram",
    "wof:placetype":"locality",
    "wof:population":812
},
  "geometry": {"coordinates":[77.86476999999999,9.660947],"type":"Point"}
}