{
  "type": "Feature",
  "properties": {
    "iso:country":"IN",
    "ks:ks_name":"Pachra",
    "ks:ks_pop":764,
    "ks:ks_type":"VILLAGE",
    "ks:ks_uagg_main":0,
    "name:eng_x_preferred":[
        "Pachra"
    ],
    "wof:name":"Pachra",
    "wof:placetype":"neighbourhood",
    "wof:population":764
},
  "geometry": {"coordinates":[87.42596,22.562093],"type":"Point"}
}