{
  "type": "Feature",
  "properties": {
    "gn:admin1_code":"36",
    "gn:admin2_code":"186.0",
    "gn:asciiname":"Rajhauli",
    "gn:country_code":"IN",
    "gn:dem":86,
    "gn:feature_class":"P",
    "gn:feature_code":"PPL",
    "gn:name":"Rajhauli",
    "gn:population":0,
    "gn:timezone":"Asia/Kolkata",
    "iso:country":"IN",
    "ks:ks_name":"Rajnauli",
    "ks:ks_pop":473,
    "ks:ks_type":"VILLAGE",
    "ks:ks_uagg_main":0,
    "name:eng_x_preferred":[
        "Rajnauli"
    ],
    "wof:name":"Rajnauli",
    "wof:placetype":"neighbourhood",
    "wof:population":473
},
  "geometry": {"coordinates":[82.97516899999999,26.617675],"type":"Point"}
}