{
  "type": "Feature",
  "properties": {
    "gn:admin1_code":"10.0",
    "gn:admin2_code":"86.0",
    "gn:asciiname":"Baskusla",
    "gn:country_code":"IN",
    "gn:dem":242,
    "gn:feature_class":"P",
    "gn:feature_code":"PPL",
    "gn:name":"B\u0101skusla",
    "gn:population":0,
    "gn:timezone":"Asia/Kolkata",
    "iso:country":"IN",
    "ks:ks_name":"Baskushla",
    "ks:ks_pop":1679,
    "ks:ks_type":"VILLAGE",
    "ks:ks_uagg_main":0,
    "name:eng_x_preferred":[
        "Baskushla"
    ],
    "wof:name":"Baskushla",
    "wof:placetype":"neighbourhood",
    "wof:population":1679
},
  "geometry": {"coordinates":[76.903724,28.377086],"type":"Point"}
}