{
  "type": "Feature",
  "properties": {
    "iso:country":"IN",
    "ks:ks_name":"Dalki",
    "ks:ks_pop":854,
    "ks:ks_type":"VILLAGE",
    "name:eng_x_preferred":[
        "Dalki"
    ],
    "wof:name":"Dalki",
    "wof:placetype":"locality",
    "wof:population":854
},
  "geometry": {"coordinates":[86.845961,21.675439],"type":"Point"}
}