{
  "type": "Feature",
  "properties": {
    "iso:country":"IN",
    "ks:ks_name":"Padolwasti",
    "ks:ks_pop":105,
    "ks:ks_type":"HABITATION",
    "name:eng_x_preferred":[
        "Padolwasti"
    ],
    "wof:name":"Padolwasti",
    "wof:placetype":"locality",
    "wof:population":105
},
  "geometry": {"coordinates":[75.834459,20.102689],"type":"Point"}
}