{
  "type": "Feature",
  "properties": {
    "iso:country":"IN",
    "ks:ks_name":"Jaruadi",
    "ks:ks_pop":0,
    "ks:ks_type":"VILLAGE",
    "name:eng_x_preferred":[
        "Jaruadi"
    ],
    "wof:name":"Jaruadi",
    "wof:placetype":"locality",
    "wof:population":0
},
  "geometry": {"coordinates":[86.449775,23.976791],"type":"Point"}
}