{
  "type": "Feature",
  "properties": {
    "gn:admin1_code":"2.0",
    "gn:admin2_code":"545",
    "gn:asciiname":"Alamuru",
    "gn:country_code":"IN",
    "gn:dem":10,
    "gn:feature_class":"P",
    "gn:feature_code":"PPL",
    "gn:name":"\u0100lam\u016bru",
    "gn:population":0,
    "gn:timezone":"Asia/Kolkata",
    "iso:country":"IN",
    "name:fas_x_preferred":[
        "\u0627\u0644\u0627\u0645\u0648\u0631\u0648"
    ],
    "name:tel_x_preferred":[
        "\u0c06\u0c32\u0c2e\u0c42\u0c30\u0c41"
    ],
    "name:tgl_x_preferred":[
        "Alamuru"
    ],
    "name:und_x_variant":[
        "\u0100lam\u016bru"
    ],
    "name:urd_x_preferred":[
        "\u0627\u0644\u0627\u0645\u0648\u0631\u0648"
    ],
    "name:vie_x_preferred":[
        "Alamuru"
    ],
    "wof:name":"Alamuru",
    "wof:placetype":"locality"
},
  "geometry": {"coordinates":[81.90000000000001,16.78333],"type":"Point"}
}