{
  "type": "Feature",
  "properties": {
    "iso:country":"IN",
    "ks:ks_alt_nam":"Esar and Nepalgunje",
    "ks:ks_name":"Esar And Nepalgunje",
    "ks:ks_pop":1100,
    "ks:ks_type":"HABITATION",
    "ks:ks_uagg_main":0,
    "name:eng_x_preferred":[
        "Esar And Nepalgunje"
    ],
    "wof:name":"Esar And Nepalgunje",
    "wof:placetype":"locality",
    "wof:population":1100
},
  "geometry": {"coordinates":[88.346214,22.413054],"type":"Point"}
}