{
  "type": "Feature",
  "properties": {
    "gn:admin1_code":"19.0",
    "gn:admin2_code":"577.0",
    "gn:asciiname":"Horalahalli",
    "gn:country_code":"IN",
    "gn:dem":669,
    "gn:feature_class":"P",
    "gn:feature_code":"PPL",
    "gn:name":"Horalahalli",
    "gn:population":0,
    "gn:timezone":"Asia/Kolkata",
    "iso:country":"IN",
    "wof:name":"Horalahalli",
    "wof:placetype":"locality"
},
  "geometry": {"coordinates":[76.93607,12.25051],"type":"Point"}
}