{
  "type": "Feature",
  "properties": {
    "iso:country":"IN",
    "ks:ks_alt_nam":"sakharbhatale",
    "ks:ks_name":"Sakharbhatale",
    "ks:ks_pop":23,
    "ks:ks_type":"HABITATION",
    "name:eng_x_preferred":[
        "Sakharbhatale"
    ],
    "wof:name":"Sakharbhatale",
    "wof:placetype":"locality",
    "wof:population":23
},
  "geometry": {"coordinates":[73.413939,17.19995],"type":"Point"}
}