{
  "type": "Feature",
  "properties": {
    "gn:admin1_code":"36.0",
    "gn:admin2_code":"181.0",
    "gn:asciiname":"Lalpur Ulahwa Kalan",
    "gn:country_code":"IN",
    "gn:dem":132,
    "gn:feature_class":"P",
    "gn:feature_code":"PPL",
    "gn:name":"L\u0101lpur Ulahwa Kal\u0101n",
    "gn:population":0,
    "gn:timezone":"Asia/Kolkata",
    "iso:country":"IN",
    "wof:name":"Lalpur Ulahwa Kalan",
    "wof:placetype":"neighbourhood"
},
  "geometry": {"coordinates":[82.00032,27.80751],"type":"Point"}
}