{
  "type": "Feature",
  "properties": {
    "iso:country":"IN",
    "ks:ks_name":"Badyar",
    "ks:ks_pop":512,
    "ks:ks_type":"HABITATION",
    "name:eng_x_preferred":[
        "Badyar"
    ],
    "wof:name":"Badyar",
    "wof:placetype":"locality",
    "wof:population":512
},
  "geometry": {"coordinates":[75.23144000000001,12.996725],"type":"Point"}
}