{
  "type": "Feature",
  "properties": {
    "gn:admin1_code":"34",
    "gn:admin2_code":"234.0",
    "gn:asciiname":"Tiara Khurd",
    "gn:country_code":"IN",
    "gn:dem":145,
    "gn:feature_class":"P",
    "gn:feature_code":"PPL",
    "gn:name":"Tiara Khurd",
    "gn:population":0,
    "gn:timezone":"Asia/Kolkata",
    "iso:country":"IN",
    "ks:ks_alt_nam":"TIYARA KHURD",
    "ks:ks_name":"Tiyara Khurd",
    "ks:ks_pop":1096,
    "ks:ks_type":"HABITATION",
    "name:eng_x_preferred":[
        "Tiyara Khurd"
    ],
    "name:eng_x_variant":[
        "Tiara Khurd"
    ],
    "wof:name":"Tiyara Khurd",
    "wof:placetype":"locality",
    "wof:population":1096
},
  "geometry": {"coordinates":[83.70516000000001,24.518959],"type":"Point"}
}