{
  "type": "Feature",
  "properties": {
    "gn:admin1_code":"35",
    "gn:admin2_code":"443.0",
    "gn:asciiname":"Barakhera",
    "gn:country_code":"IN",
    "gn:dem":428,
    "gn:feature_class":"P",
    "gn:feature_code":"PPL",
    "gn:name":"Bar\u0101khera",
    "gn:population":0,
    "gn:timezone":"Asia/Kolkata",
    "iso:country":"IN",
    "wof:name":"Barakhera",
    "wof:placetype":"locality"
},
  "geometry": {"coordinates":[77.84518,23.54787],"type":"Point"}
}