{
  "type": "Feature",
  "properties": {
    "gn:admin1_code":"36.0",
    "gn:admin2_code":"165.0",
    "gn:asciiname":"Lohi",
    "gn:country_code":"IN",
    "gn:dem":158,
    "gn:feature_class":"P",
    "gn:feature_code":"PPL",
    "gn:name":"Loh\u012b",
    "gn:population":0,
    "gn:timezone":"Asia/Kolkata",
    "iso:country":"IN",
    "name:fas_x_preferred":[
        "\u0644\u0648\u0647\u06cc"
    ],
    "wof:name":"Lohi",
    "wof:placetype":"locality"
},
  "geometry": {"coordinates":[79.08048000000002,26.12104],"type":"Point"}
}