{
  "type": "Feature",
  "properties": {
    "gn:admin1_code":"19.0",
    "gn:admin2_code":"568.0",
    "gn:asciiname":"Hiriyur",
    "gn:country_code":"IN",
    "gn:dem":624,
    "gn:feature_class":"P",
    "gn:feature_code":"PPL",
    "gn:name":"Hiriy\u016br",
    "gn:population":0,
    "gn:timezone":"Asia/Kolkata",
    "iso:country":"IN",
    "name:ben_x_preferred":[
        "\u09b9\u09bf\u09b0\u09bf\u09af\u09bc\u09c1\u09b0"
    ],
    "name:bpy_x_preferred":[
        "\u09b9\u09bf\u09b0\u09bf\u09af\u09bc\u09c1\u09b0"
    ],
    "name:ceb_x_preferred":[
        "Hiriy\u016br"
    ],
    "name:ita_x_preferred":[
        "Hiriyur"
    ],
    "name:kan_x_preferred":[
        "\u0cb9\u0cbf\u0cb0\u0cbf\u0caf\u0cc2\u0cb0\u0cc1"
    ],
    "name:mlg_x_preferred":[
        "Hiriyur"
    ],
    "name:msa_x_preferred":[
        "Hiriyur"
    ],
    "name:new_x_preferred":[
        "\u0939\u093f\u0930\u093f\u092f\u0941\u0930"
    ],
    "name:nld_x_preferred":[
        "Hiriyur"
    ],
    "name:spa_x_preferred":[
        "Hiriyur"
    ],
    "name:swe_x_preferred":[
        "Hiriy\u016br"
    ],
    "name:vie_x_preferred":[
        "Hiriyur"
    ],
    "name:zho_x_preferred":[
        "\u5e0c\u91cc\u5c24\u5c14"
    ],
    "wof:name":"Hiriyur",
    "wof:placetype":"locality"
},
  "geometry": {"coordinates":[75.67865,13.79699],"type":"Point"}
}