{
  "type": "Feature",
  "properties": {
    "iso:country":"IN",
    "ks:ks_name":"Purba Matiari",
    "ks:ks_pop":1533,
    "ks:ks_type":"VILLAGE",
    "name:eng_x_preferred":[
        "Purba Matiari"
    ],
    "wof:name":"Purba Matiari",
    "wof:placetype":"locality",
    "wof:population":1533
},
  "geometry": {"coordinates":[87.875365,25.909204],"type":"Point"}
}