{
  "type": "Feature",
  "properties": {
    "gn:admin1_code":"36.0",
    "gn:admin2_code":"152",
    "gn:asciiname":"Jagpur",
    "gn:country_code":"IN",
    "gn:dem":148,
    "gn:feature_class":"P",
    "gn:feature_code":"PPL",
    "gn:name":"Jagpur",
    "gn:population":0,
    "gn:timezone":"Asia/Kolkata",
    "iso:country":"IN",
    "wof:name":"Jagpur",
    "wof:placetype":"locality"
},
  "geometry": {"coordinates":[79.53539000000001,27.70114],"type":"Point"}
}