{
  "type": "Feature",
  "properties": {
    "gn:admin1_code":"19",
    "gn:admin2_code":"575.0",
    "gn:asciiname":"Panja",
    "gn:cc2":"IN",
    "gn:country_code":"IN",
    "gn:dem":111,
    "gn:feature_class":"P",
    "gn:feature_code":"PPL",
    "gn:name":"Panja",
    "gn:population":0,
    "gn:timezone":"Asia/Kolkata",
    "iso:country":"IN",
    "name:und_x_variant":[
        "P\u0101n\u0101je",
        "Panje",
        "Panja"
    ],
    "wof:name":"Panja",
    "wof:placetype":"locality"
},
  "geometry": {"coordinates":[75.47821999999999,12.67534],"type":"Point"}
}