{
  "type": "Feature",
  "properties": {
    "iso:country":"IN",
    "ks:ks_name":"Koda",
    "ks:ks_pop":658,
    "ks:ks_type":"VILLAGE",
    "name:eng_x_preferred":[
        "Koda"
    ],
    "wof:name":"Koda",
    "wof:placetype":"locality",
    "wof:population":658
},
  "geometry": {"coordinates":[79.835356,24.857168],"type":"Point"}
}