{
  "type": "Feature",
  "properties": {
    "iso:country":"IN",
    "ks:ks_name":"Jhalar",
    "ks:ks_pop":1810,
    "ks:ks_type":"HABITATION",
    "name:eng_x_preferred":[
        "Jhalar"
    ],
    "wof:name":"Jhalar",
    "wof:placetype":"locality",
    "wof:population":1810
},
  "geometry": {"coordinates":[86.97439799999999,24.649468],"type":"Point"}
}