{
  "type": "Feature",
  "properties": {
    "gn:admin1_code":"2.0",
    "gn:admin2_code":"549.0",
    "gn:asciiname":"Brahmanapalle",
    "gn:country_code":"IN",
    "gn:dem":35,
    "gn:feature_class":"P",
    "gn:feature_code":"PPL",
    "gn:name":"Br\u0101hmanapalle",
    "gn:population":0,
    "gn:timezone":"Asia/Kolkata",
    "iso:country":"IN",
    "ks:ks_name":"Brahmanapalli",
    "ks:ks_pop":140,
    "ks:ks_type":"HABITATION",
    "name:eng_x_preferred":[
        "Brahmanapalli"
    ],
    "name:eng_x_variant":[
        "Brahmanapalle"
    ],
    "wof:name":"Brahmanapalli",
    "wof:placetype":"locality",
    "wof:population":140
},
  "geometry": {"coordinates":[79.772924,15.072546],"type":"Point"}
}