{
  "type": "Feature",
  "properties": {
    "iso:country":"IN",
    "ks:ks_name":"Handijogipalya",
    "ks:ks_pop":48,
    "ks:ks_type":"HABITATION",
    "name:eng_x_preferred":[
        "Handijogipalya"
    ],
    "wof:name":"Handijogipalya",
    "wof:placetype":"locality",
    "wof:population":48
},
  "geometry": {"coordinates":[76.720726,13.072348],"type":"Point"}
}