{
  "type": "Feature",
  "properties": {
    "iso:country":"IN",
    "ks:ks_name":"Pure Bhaiya Tiwari Purwa",
    "ks:ks_pop":600,
    "ks:ks_type":"HABITATION",
    "ks:ks_uagg_main":0,
    "name:eng_x_preferred":[
        "Pure Bhaiya Tiwari Purwa"
    ],
    "wof:name":"Pure Bhaiya Tiwari Purwa",
    "wof:placetype":"neighbourhood",
    "wof:population":600
},
  "geometry": {"coordinates":[81.990267,25.943249],"type":"Point"}
}