{
  "type": "Feature",
  "properties": {
    "iso:country":"IN",
    "ks:ks_name":"10 STB",
    "ks:ks_pop":64,
    "ks:ks_type":"VILLAGE",
    "name:eng_x_preferred":[
        "10 STB"
    ],
    "wof:name":"10 STB",
    "wof:placetype":"locality",
    "wof:population":64
},
  "geometry": {"coordinates":[74.080825,29.385742],"type":"Point"}
}