{
  "type": "Feature",
  "properties": {
    "gn:admin1_code":"25.0",
    "gn:admin2_code":"610.0",
    "gn:asciiname":"Semur",
    "gn:country_code":"IN",
    "gn:dem":198,
    "gn:feature_class":"P",
    "gn:feature_code":"PPL",
    "gn:name":"Sem\u016br",
    "gn:population":0,
    "gn:timezone":"Asia/Kolkata",
    "iso:country":"IN",
    "name:ceb_x_preferred":[
        "Semur"
    ],
    "name:deu_x_preferred":[
        "Semur"
    ],
    "name:fra_x_preferred":[
        "Semur"
    ],
    "name:swe_x_preferred":[
        "Semur"
    ],
    "wof:name":"Semur",
    "wof:placetype":"locality"
},
  "geometry": {"coordinates":[77.75539000000001,11.21358],"type":"Point"}
}