{
  "type": "Feature",
  "properties": {
    "iso:country":"IN",
    "ks:ks_name":"Nathu Pasi Ka Dera",
    "ks:ks_pop":50,
    "ks:ks_type":"HABITATION",
    "name:eng_x_preferred":[
        "Nathu Pasi Ka Dera"
    ],
    "wof:name":"Nathu Pasi Ka Dera",
    "wof:placetype":"locality",
    "wof:population":50
},
  "geometry": {"coordinates":[81.32472,25.40788],"type":"Point"}
}