{
  "type": "Feature",
  "properties": {
    "iso:country":"IN",
    "ks:ks_name":"Yamaiwasti",
    "ks:ks_pop":65,
    "ks:ks_type":"HABITATION",
    "name:eng_x_preferred":[
        "Yamaiwasti"
    ],
    "wof:name":"Yamaiwasti",
    "wof:placetype":"locality",
    "wof:population":65
},
  "geometry": {"coordinates":[74.04494800000001,19.160698],"type":"Point"}
}