{
  "type": "Feature",
  "properties": {
    "gn:admin1_code":"36",
    "gn:admin2_code":"194.0",
    "gn:asciiname":"Khushupur",
    "gn:country_code":"IN",
    "gn:dem":86,
    "gn:feature_class":"P",
    "gn:feature_code":"PPL",
    "gn:name":"Kh\u016bsh\u016bpur",
    "gn:population":0,
    "gn:timezone":"Asia/Kolkata",
    "iso:country":"IN",
    "wof:name":"Khushupur",
    "wof:placetype":"locality"
},
  "geometry": {"coordinates":[82.57439000000002,25.81556],"type":"Point"}
}