{
  "type": "Feature",
  "properties": {
    "iso:country":"IN",
    "ks:ks_name":"Soyalaguda",
    "ks:ks_pop":100,
    "ks:ks_type":"HABITATION",
    "name:eng_x_preferred":[
        "Soyalaguda"
    ],
    "wof:name":"Soyalaguda",
    "wof:placetype":"locality",
    "wof:population":100
},
  "geometry": {"coordinates":[83.847159,18.635342],"type":"Point"}
}