{
  "type": "Feature",
  "properties": {
    "gn:admin1_code":"2.0",
    "gn:admin2_code":"548.0",
    "gn:asciiname":"Janapadu",
    "gn:country_code":"IN",
    "gn:dem":110,
    "gn:feature_class":"P",
    "gn:feature_code":"PPL",
    "gn:name":"J\u0101nap\u0101du",
    "gn:population":0,
    "gn:timezone":"Asia/Kolkata",
    "iso:country":"IN",
    "ks:ks_alt_nam":"J\u0101nap\u0101du",
    "ks:ks_name":"Janapadu",
    "ks:ks_pop":11318,
    "ks:ks_type":"VILLAGE",
    "ks:ks_uagg_main":0,
    "name:eng_x_preferred":[
        "Janapadu"
    ],
    "name:eng_x_variant":[
        "J\u0101nap\u0101du"
    ],
    "wof:name":"Janapadu",
    "wof:placetype":"neighbourhood",
    "wof:population":11318
},
  "geometry": {"coordinates":[79.869479,16.459592],"type":"Point"}
}