{
  "type": "Feature",
  "properties": {
    "iso:country":"IN",
    "ks:ks_alt_nam":"musalman tola",
    "ks:ks_name":"Musalman Tola",
    "ks:ks_pop":826,
    "ks:ks_type":"HABITATION",
    "name:eng_x_preferred":[
        "Musalman Tola"
    ],
    "wof:name":"Musalman Tola",
    "wof:placetype":"locality",
    "wof:population":826
},
  "geometry": {"coordinates":[86.930904,26.17333],"type":"Point"}
}