{
  "type": "Feature",
  "properties": {
    "iso:country":"IN",
    "ks:ks_name":"Amagar",
    "ks:ks_pop":109,
    "ks:ks_type":"VILLAGE",
    "name:eng_x_preferred":[
        "Amagar"
    ],
    "wof:name":"Amagar",
    "wof:placetype":"locality",
    "wof:population":109
},
  "geometry": {"coordinates":[82.097571,22.514735],"type":"Point"}
}