{
  "type": "Feature",
  "properties": {
    "iso:country":"IN",
    "ks:ks_name":"Aujhaguri",
    "ks:ks_pop":250,
    "ks:ks_type":"HABITATION",
    "name:eng_x_preferred":[
        "Aujhaguri"
    ],
    "wof:name":"Aujhaguri",
    "wof:placetype":"locality",
    "wof:population":250
},
  "geometry": {"coordinates":[90.735873,26.641296],"type":"Point"}
}