{
  "type": "Feature",
  "properties": {
    "iso:country":"IN",
    "ks:ks_name":"Bhounra",
    "ks:ks_pop":631,
    "ks:ks_type":"HABITATION",
    "name:eng_x_preferred":[
        "Bhounra"
    ],
    "wof:name":"Bhounra",
    "wof:placetype":"locality",
    "wof:population":631
},
  "geometry": {"coordinates":[86.793201,24.831243],"type":"Point"}
}