{
  "type": "Feature",
  "properties": {
    "iso:country":"IN",
    "ks:ks_name":"Burakot",
    "ks:ks_pop":145,
    "ks:ks_type":"VILLAGE",
    "name:eng_x_preferred":[
        "Burakot"
    ],
    "wof:name":"Burakot",
    "wof:placetype":"locality",
    "wof:population":145
},
  "geometry": {"coordinates":[78.77072,29.846833],"type":"Point"}
}