{
  "type": "Feature",
  "properties": {
    "iso:country":"IN",
    "ks:ks_name":"Oderipoyil",
    "ks:ks_pop":190,
    "ks:ks_type":"HABITATION",
    "name:eng_x_preferred":[
        "Oderipoyil"
    ],
    "wof:name":"Oderipoyil",
    "wof:placetype":"locality",
    "wof:population":190
},
  "geometry": {"coordinates":[75.78377999999999,11.698536],"type":"Point"}
}