{
  "type": "Feature",
  "properties": {
    "gn:admin1_code":"2.0",
    "gn:admin2_code":"544.0",
    "gn:asciiname":"Musidiguda",
    "gn:country_code":"IN",
    "gn:dem":1059,
    "gn:feature_class":"P",
    "gn:feature_code":"PPL",
    "gn:name":"Musidig\u016bda",
    "gn:population":0,
    "gn:timezone":"Asia/Kolkata",
    "iso:country":"IN",
    "ks:ks_name":"Musiriguda",
    "ks:ks_pop":120,
    "ks:ks_type":"VILLAGE",
    "name:eng_x_preferred":[
        "Musiriguda"
    ],
    "name:eng_x_variant":[
        "Musidiguda"
    ],
    "wof:name":"Musiriguda",
    "wof:placetype":"locality",
    "wof:population":120
},
  "geometry": {"coordinates":[83.073044,18.356853],"type":"Point"}
}