{
  "type": "Feature",
  "properties": {
    "iso:country":"IN",
    "ks:ks_name":"Y.b.",
    "ks:ks_pop":208,
    "ks:ks_type":"HABITATION",
    "name:eng_x_preferred":[
        "Y.b."
    ],
    "wof:name":"Y.b.",
    "wof:placetype":"locality",
    "wof:population":208
},
  "geometry": {"coordinates":[83.144293,25.802733],"type":"Point"}
}