{
  "type": "Feature",
  "properties": {
    "gn:admin1_code":"23.0",
    "gn:admin2_code":"43.0",
    "gn:asciiname":"Chak Dumal",
    "gn:country_code":"IN",
    "gn:dem":182,
    "gn:feature_class":"P",
    "gn:feature_code":"PPL",
    "gn:name":"Chak Dum\u0101l",
    "gn:population":0,
    "gn:timezone":"Asia/Kolkata",
    "iso:country":"IN",
    "name:und_x_variant":[
        "Chak Dum\u0101l",
        "Tind\u0101nw\u0101la"
    ],
    "wof:name":"Chak Dumal",
    "wof:placetype":"locality"
},
  "geometry": {"coordinates":[74.21398000000001,30.52258],"type":"Point"}
}