{
  "type": "Feature",
  "properties": {
    "iso:country":"IN",
    "ks:ks_name":"Dongripara",
    "ks:ks_pop":26,
    "ks:ks_type":"HABITATION",
    "name:eng_x_preferred":[
        "Dongripara"
    ],
    "wof:name":"Dongripara",
    "wof:placetype":"locality",
    "wof:population":26
},
  "geometry": {"coordinates":[81.059909,19.12932],"type":"Point"}
}