{
  "type": "Feature",
  "properties": {
    "gn:admin1_code":"36",
    "gn:admin2_code":"200.0",
    "gn:asciiname":"Patera",
    "gn:country_code":"IN",
    "gn:dem":188,
    "gn:feature_class":"P",
    "gn:feature_code":"PPL",
    "gn:name":"Patera",
    "gn:population":0,
    "gn:timezone":"Asia/Kolkata",
    "iso:country":"IN",
    "name:bul_x_preferred":[
        "\u041f\u0430\u0442\u0435\u0440\u0430"
    ],
    "name:cat_x_preferred":[
        "P\u00e0tera"
    ],
    "name:deu_x_preferred":[
        "Patera"
    ],
    "name:fas_x_preferred":[
        "\u067e\u06cc\u0627\u0644\u0647"
    ],
    "name:fra_x_preferred":[
        "Pat\u00e8re"
    ],
    "name:hun_x_preferred":[
        "Patera"
    ],
    "name:ita_x_preferred":[
        "Patera"
    ],
    "name:nld_x_preferred":[
        "Patera"
    ],
    "name:pol_x_preferred":[
        "Patera"
    ],
    "name:por_x_preferred":[
        "P\u00e1tera"
    ],
    "name:rus_x_preferred":[
        "\u041f\u0430\u0442\u0435\u0440\u0430"
    ],
    "name:slv_x_preferred":[
        "Patera"
    ],
    "name:spa_x_preferred":[
        "P\u00e1tera"
    ],
    "name:tur_x_preferred":[
        "Hamam tas\u0131"
    ],
    "wof:name":"Patera",
    "wof:placetype":"locality"
},
  "geometry": {"coordinates":[82.91023,24.61271],"type":"Point"}
}