{
  "type": "Feature",
  "properties": {
    "iso:country":"IN",
    "ks:ks_name":"Baradavalli",
    "ks:ks_pop":341,
    "ks:ks_type":"HABITATION",
    "name:eng_x_preferred":[
        "Baradavalli"
    ],
    "wof:name":"Baradavalli",
    "wof:placetype":"locality",
    "wof:population":341
},
  "geometry": {"coordinates":[74.95100499999999,14.45414],"type":"Point"}
}