{
  "type": "Feature",
  "properties": {
    "gn:admin1_code":"12.0",
    "gn:admin2_code":"005",
    "gn:asciiname":"Kanoiyah",
    "gn:country_code":"IN",
    "gn:dem":1030,
    "gn:feature_class":"P",
    "gn:feature_code":"PPL",
    "gn:name":"Kanoiy\u0101h",
    "gn:population":0,
    "gn:timezone":"Asia/Kolkata",
    "iso:country":"IN",
    "name:und_x_variant":[
        "Kanoiy\u0101h",
        "Kanoiy\u0101n",
        "Kunoiyan"
    ],
    "wof:name":"Kanoiyah",
    "wof:placetype":"locality"
},
  "geometry": {"coordinates":[74.09854,33.75092],"type":"Point"}
}