{
  "type": "Feature",
  "properties": {
    "iso:country":"IN",
    "ks:ks_name":"Thakarwadi",
    "ks:ks_pop":700,
    "ks:ks_type":"HABITATION",
    "name:eng_x_preferred":[
        "Thakarwadi"
    ],
    "wof:name":"Thakarwadi",
    "wof:placetype":"locality",
    "wof:population":700
},
  "geometry": {"coordinates":[74.46413699999999,19.276357],"type":"Point"}
}