{
  "type": "Feature",
  "properties": {
    "iso:country":"IN",
    "ks:ks_name":"Talap Bagan Gaon",
    "ks:ks_pop":353,
    "ks:ks_type":"VILLAGE",
    "name:eng_x_preferred":[
        "Talap Bagan Gaon"
    ],
    "wof:name":"Talap Bagan Gaon",
    "wof:placetype":"locality",
    "wof:population":353
},
  "geometry": {"coordinates":[95.58129599999999,27.648954],"type":"Point"}
}