{
  "type": "Feature",
  "properties": {
    "iso:country":"IN",
    "ks:ks_name":"Therkukottagai",
    "ks:ks_pop":122,
    "ks:ks_type":"HABITATION",
    "name:eng_x_preferred":[
        "Therkukottagai"
    ],
    "wof:name":"Therkukottagai",
    "wof:placetype":"locality",
    "wof:population":122
},
  "geometry": {"coordinates":[78.47682399999999,9.242544],"type":"Point"}
}