{
  "type": "Feature",
  "properties": {
    "iso:country":"IN",
    "ks:ks_alt_nam":"3 BLM-A",
    "ks:ks_name":"3 Blm-a",
    "ks:ks_pop":200,
    "ks:ks_type":"HABITATION",
    "name:eng_x_preferred":[
        "3 Blm-a"
    ],
    "wof:name":"3 Blm-a",
    "wof:placetype":"locality",
    "wof:population":200
},
  "geometry": {"coordinates":[73.521111,29.292778],"type":"Point"}
}