{
  "type": "Feature",
  "properties": {
    "iso:country":"IN",
    "ks:ks_name":"Anei",
    "ks:ks_pop":1263,
    "ks:ks_type":"VILLAGE",
    "ks:ks_uagg_main":0,
    "name:eng_x_preferred":[
        "Anei"
    ],
    "wof:name":"Anei",
    "wof:placetype":"neighbourhood",
    "wof:population":1263
},
  "geometry": {"coordinates":[80.015647,26.744331],"type":"Point"}
}