{
  "type": "Feature",
  "properties": {
    "iso:country":"IN",
    "ks:ks_name":"Vadahatti",
    "ks:ks_pop":28,
    "ks:ks_type":"HABITATION",
    "ks:ks_uagg_main":0,
    "name:eng_x_preferred":[
        "Vadahatti"
    ],
    "wof:name":"Vadahatti",
    "wof:placetype":"neighbourhood",
    "wof:population":28
},
  "geometry": {"coordinates":[76.414096,13.30199],"type":"Point"}
}