{
  "type": "Feature",
  "properties": {
    "iso:country":"IN",
    "ks:ks_name":"Masapura",
    "ks:ks_pop":449,
    "ks:ks_type":"HABITATION",
    "name:eng_x_preferred":[
        "Masapura"
    ],
    "wof:name":"Masapura",
    "wof:placetype":"locality",
    "wof:population":449
},
  "geometry": {"coordinates":[71.63341800000001,24.176139],"type":"Point"}
}