{
  "type": "Feature",
  "properties": {
    "iso:country":"IN",
    "ks:ks_name":"Parit Wasti",
    "ks:ks_pop":365,
    "ks:ks_type":"HABITATION",
    "name:eng_x_preferred":[
        "Parit Wasti"
    ],
    "wof:name":"Parit Wasti",
    "wof:placetype":"locality",
    "wof:population":365
},
  "geometry": {"coordinates":[75.910436,18.151938],"type":"Point"}
}