{
  "type": "Feature",
  "properties": {
    "iso:country":"IN",
    "ks:ks_name":"Didimbila",
    "ks:ks_pop":157,
    "ks:ks_type":"HABITATION",
    "name:eng_x_preferred":[
        "Didimbila"
    ],
    "wof:name":"Didimbila",
    "wof:placetype":"locality",
    "wof:population":157
},
  "geometry": {"coordinates":[75.183786,12.882104],"type":"Point"}
}