{
  "type": "Feature",
  "properties": {
    "gn:admin1_code":"13.0",
    "gn:admin2_code":"596.0",
    "gn:asciiname":"Nettigudi",
    "gn:country_code":"IN",
    "gn:dem":1546,
    "gn:feature_class":"P",
    "gn:feature_code":"PPL",
    "gn:name":"Nettigudi",
    "gn:population":0,
    "gn:timezone":"Asia/Kolkata",
    "iso:country":"IN",
    "wof:name":"Nettigudi",
    "wof:placetype":"locality"
},
  "geometry": {"coordinates":[77.10934,10.08839],"type":"Point"}
}