{
  "type": "Feature",
  "properties": {
    "iso:country":"IN",
    "ks:ks_name":"Devichapada",
    "ks:ks_pop":5574,
    "ks:ks_type":"VILLAGE",
    "name:eng_x_preferred":[
        "Devichapada"
    ],
    "wof:name":"Devichapada",
    "wof:placetype":"locality",
    "wof:population":5574
},
  "geometry": {"coordinates":[73.14058,19.072701],"type":"Point"}
}