{
  "type": "Feature",
  "properties": {
    "gn:admin1_code":"36",
    "gn:admin2_code":"145.0",
    "gn:asciiname":"Mahrauli",
    "gn:country_code":"IN",
    "gn:dem":192,
    "gn:feature_class":"P",
    "gn:feature_code":"PPL",
    "gn:name":"Mahrauli",
    "gn:population":0,
    "gn:timezone":"Asia/Kolkata",
    "iso:country":"IN",
    "name:ara_x_preferred":[
        "\u0645\u0627\u0647\u0631\u0648\u0644\u064a"
    ],
    "name:ben_bn_x_preferred":[
        "\u09ae\u09be\u09b9\u09b0\u09cc\u09b2\u09bf"
    ],
    "name:ben_in_x_preferred":[
        "\u09ae\u09be\u09b9\u09b0\u09cc\u09b2\u09bf"
    ],
    "name:guj_x_preferred":[
        "\u0aae\u0ab9\u0abe\u0ab0\u0acc\u0ab2\u0ac0"
    ],
    "name:hin_x_preferred":[
        "\u092e\u0939\u0930\u094c\u0932\u0940"
    ],
    "name:kan_x_preferred":[
        "\u0cae\u0cb9\u0ccd\u0cb0\u0ccc\u0cb2\u0cbf"
    ],
    "name:mal_x_preferred":[
        "\u0d2e\u0d39\u0d4d"
    ],
    "name:mar_x_preferred":[
        "\u092e\u0939\u0930\u094c\u0932\u0940"
    ],
    "name:pan_x_preferred":[
        "\u0a2e\u0a39\u0a3f\u0a30\u0a4c\u0a32\u0a40"
    ],
    "name:tam_x_preferred":[
        "\u0bae\u0bb9\u0bcd\u0bb0\u0bcc\u0bb2\u0bbf"
    ],
    "name:tel_x_preferred":[
        "\u0c2e\u0c39\u0c4d\u0c30\u0c4c\u0c32\u0c3f"
    ],
    "name:urd_x_preferred":[
        "\u0645\u06c1\u0631\u0648\u0644\u06cc"
    ],
    "wof:name":"Mahrauli",
    "wof:placetype":"locality"
},
  "geometry": {"coordinates":[77.51411999999998,27.81758],"type":"Point"}
}