{
  "type": "Feature",
  "properties": {
    "iso:country":"IN",
    "qs:name":"Thalaghattapura",
    "qs:name_adm0":"India",
    "qs:name_adm1":"Karnataka",
    "qs:photos":59,
    "qs:photos_1k":12,
    "qs:photos_9k":1,
    "qs:photos_9r":2,
    "qs:photos_all":59,
    "qs:photos_sr":2,
    "qs:placetype":"Town",
    "qs:pop_sr":"0",
    "wof:name":"Thalaghattapura",
    "wof:placetype":"neighbourhood"
},
  "geometry": {"coordinates":[77.532062,12.868204],"type":"Point"}
}