{
  "type": "Feature",
  "properties": {
    "iso:country":"IN",
    "ks:ks_name":"Thamarakulam",
    "ks:ks_pop":604,
    "ks:ks_type":"HABITATION",
    "name:eng_x_preferred":[
        "Thamarakulam"
    ],
    "wof:name":"Thamarakulam",
    "wof:placetype":"locality",
    "wof:population":604
},
  "geometry": {"coordinates":[76.600712,9.171025],"type":"Point"}
}