{
  "type": "Feature",
  "properties": {
    "iso:country":"IN",
    "ks:ks_name":"Madarkhat Gaon",
    "ks:ks_pop":436,
    "ks:ks_type":"VILLAGE",
    "name:eng_x_preferred":[
        "Madarkhat Gaon"
    ],
    "wof:name":"Madarkhat Gaon",
    "wof:placetype":"locality",
    "wof:population":436
},
  "geometry": {"coordinates":[95.77554600000001,27.588033],"type":"Point"}
}