{
  "type": "Feature",
  "properties": {
    "iso:country":"IN",
    "ks:ks_name":"Udayagiri Colony",
    "ks:ks_pop":38,
    "ks:ks_type":"HABITATION",
    "name:eng_x_preferred":[
        "Udayagiri Colony"
    ],
    "wof:name":"Udayagiri Colony",
    "wof:placetype":"locality",
    "wof:population":38
},
  "geometry": {"coordinates":[75.754167,12.456111],"type":"Point"}
}