{
  "type": "Feature",
  "properties": {
    "iso:country":"IN",
    "ks:ks_name":"Jadhavwadi",
    "ks:ks_pop":93,
    "ks:ks_type":"VILLAGE",
    "name:eng_x_preferred":[
        "Jadhavwadi"
    ],
    "wof:name":"Jadhavwadi",
    "wof:placetype":"locality",
    "wof:population":93
},
  "geometry": {"coordinates":[73.592647,18.260235],"type":"Point"}
}