{
  "type": "Feature",
  "properties": {
    "iso:country":"IN",
    "ks:ks_alt_nam":"\u0100ta",
    "ks:ks_name":"Ata",
    "ks:ks_pop":2500,
    "ks:ks_type":"VILLAGE",
    "name:eng_x_preferred":[
        "Ata"
    ],
    "name:eng_x_variant":[
        "\u0100ta"
    ],
    "wof:name":"Ata",
    "wof:placetype":"neighbourhood",
    "wof:population":2500
},
  "geometry": {"coordinates":[78.73813699999999,28.452795],"type":"Point"}
}