{
  "type": "Feature",
  "properties": {
    "iso:country":"IN",
    "ks:ks_alt_nam":"JILDA-PATELPARA",
    "ks:ks_name":"Jilda-patelpara",
    "ks:ks_pop":184,
    "ks:ks_type":"HABITATION",
    "name:eng_x_preferred":[
        "Jilda-patelpara"
    ],
    "wof:name":"Jilda-patelpara",
    "wof:placetype":"locality",
    "wof:population":184
},
  "geometry": {"coordinates":[82.158798,22.716504],"type":"Point"}
}