{
  "type": "Feature",
  "properties": {
    "gn:admin1_code":"36",
    "gn:admin2_code":"197.0",
    "gn:asciiname":"Khardaha",
    "gn:country_code":"IN",
    "gn:dem":82,
    "gn:feature_class":"P",
    "gn:feature_code":"PPL",
    "gn:name":"Khardaha",
    "gn:population":0,
    "gn:timezone":"Asia/Kolkata",
    "iso:country":"IN",
    "name:ben_x_preferred":[
        "\u0996\u09a1\u09bc\u09a6\u09b9"
    ],
    "name:bih_x_preferred":[
        "\u0916\u0930\u0926\u0939\u093e"
    ],
    "name:bpy_x_preferred":[
        "\u0996\u09a1\u09bc\u09a6\u09be"
    ],
    "name:ceb_x_preferred":[
        "Khardah"
    ],
    "name:ita_x_preferred":[
        "Khardaha"
    ],
    "name:mlg_x_preferred":[
        "Khardaha"
    ],
    "name:msa_x_preferred":[
        "Khardaha"
    ],
    "name:new_x_preferred":[
        "\u0916\u0930\u094d\u0926\u0939\u093e"
    ],
    "name:spa_x_preferred":[
        "Khardaha"
    ],
    "name:swe_x_preferred":[
        "Khardaha"
    ],
    "name:vie_x_preferred":[
        "Khardaha"
    ],
    "name:zho_x_preferred":[
        "\u5361\u5c14\u8fbe\u54c8"
    ],
    "wof:name":"Khardaha",
    "wof:placetype":"locality"
},
  "geometry": {"coordinates":[83.03161,25.51689],"type":"Point"}
}