{
  "type": "Feature",
  "properties": {
    "gn:admin1_code":"40",
    "gn:admin2_code":"540.0",
    "gn:asciiname":"Vavilala",
    "gn:country_code":"IN",
    "gn:dem":276,
    "gn:feature_class":"P",
    "gn:feature_code":"PPL",
    "gn:name":"V\u0101vil\u0101la",
    "gn:population":0,
    "gn:timezone":"Asia/Kolkata",
    "iso:country":"IN",
    "name:fas_x_preferred":[
        "\u0648\u0648\u06cc\u0644\u0644\u0627"
    ],
    "name:hin_x_preferred":[
        "\u0935\u093e\u0935\u093f\u0932\u093e\u0932"
    ],
    "name:new_x_preferred":[
        "\u0935\u093e\u0935\u093f\u0932\u093e\u0932"
    ],
    "name:tel_x_preferred":[
        "\u0c35\u0c3e\u0c35\u0c3f\u0c32\u0c3e\u0c32"
    ],
    "wof:name":"Vavilala",
    "wof:placetype":"locality"
},
  "geometry": {"coordinates":[79.51649999999999,17.61565],"type":"Point"}
}