{
  "type": "Feature",
  "properties": {
    "iso:country":"IN",
    "ks:ks_alt_nam":"Heeryanaik tanda",
    "ks:ks_name":"Heeryanaik Tanda",
    "ks:ks_pop":165,
    "ks:ks_type":"HABITATION",
    "name:eng_x_preferred":[
        "Heeryanaik Tanda"
    ],
    "wof:name":"Heeryanaik Tanda",
    "wof:placetype":"locality",
    "wof:population":165
},
  "geometry": {"coordinates":[77.804164,16.995812],"type":"Point"}
}