{
  "type": "Feature",
  "properties": {
    "iso:country":"IN",
    "ks:ks_name":"Nayacheecha",
    "ks:ks_pop":884,
    "ks:ks_type":"HABITATION",
    "name:eng_x_preferred":[
        "Nayacheecha"
    ],
    "wof:name":"Nayacheecha",
    "wof:placetype":"locality",
    "wof:population":884
},
  "geometry": {"coordinates":[77.91371100000001,22.545021],"type":"Point"}
}