{
  "type": "Feature",
  "properties": {
    "iso:country":"IN",
    "ks:ks_alt_nam":"Maruthi tanda",
    "ks:ks_name":"Maruthi Tanda",
    "ks:ks_pop":28,
    "ks:ks_type":"HABITATION",
    "name:eng_x_preferred":[
        "Maruthi Tanda"
    ],
    "wof:name":"Maruthi Tanda",
    "wof:placetype":"locality",
    "wof:population":28
},
  "geometry": {"coordinates":[78.113738,18.267802],"type":"Point"}
}