{
  "type": "Feature",
  "properties": {
    "iso:country":"IN",
    "ks:ks_name":"Kokilipaarai",
    "ks:ks_pop":26,
    "ks:ks_type":"HABITATION",
    "name:eng_x_preferred":[
        "Kokilipaarai"
    ],
    "wof:name":"Kokilipaarai",
    "wof:placetype":"locality",
    "wof:population":26
},
  "geometry": {"coordinates":[78.417868,11.307373],"type":"Point"}
}