{
  "type": "Feature",
  "properties": {
    "iso:country":"IN",
    "ks:ks_name":"Balegadde",
    "ks:ks_pop":4,
    "ks:ks_type":"HABITATION",
    "name:eng_x_preferred":[
        "Balegadde"
    ],
    "wof:name":"Balegadde",
    "wof:placetype":"locality",
    "wof:population":4
},
  "geometry": {"coordinates":[74.689651,14.313774],"type":"Point"}
}