{
  "type": "Feature",
  "properties": {
    "iso:country":"IN",
    "ks:ks_alt_nam":"Tumb\u0101",
    "ks:ks_name":"Tumba",
    "ks:ks_pop":678,
    "ks:ks_type":"VILLAGE",
    "ks:ks_uagg_main":0,
    "name:eng_x_preferred":[
        "Tumba"
    ],
    "name:eng_x_variant":[
        "Tumb\u0101"
    ],
    "wof:name":"Tumba",
    "wof:placetype":"neighbourhood",
    "wof:population":678
},
  "geometry": {"coordinates":[85.39066699999999,23.914729],"type":"Point"}
}