{
  "type": "Feature",
  "properties": {
    "iso:country":"IN",
    "ks:ks_alt_nam":"pasiyan  thakur basti",
    "ks:ks_name":"Pasiyan Thakur Basti",
    "ks:ks_pop":600,
    "ks:ks_type":"HABITATION",
    "name:eng_x_preferred":[
        "Pasiyan Thakur Basti"
    ],
    "name:eng_x_variant":[
        "pasiyan  thakur basti"
    ],
    "wof:name":"Pasiyan Thakur Basti",
    "wof:placetype":"locality",
    "wof:population":600
},
  "geometry": {"coordinates":[82.14331,25.231897],"type":"Point"}
}