{
  "type": "Feature",
  "properties": {
    "gn:admin1_code":"16",
    "gn:admin2_code":"524.0",
    "gn:asciiname":"Ganeshwadi",
    "gn:country_code":"IN",
    "gn:dem":628,
    "gn:feature_class":"P",
    "gn:feature_code":"PPL",
    "gn:name":"Ganeshw\u0101di",
    "gn:population":0,
    "gn:timezone":"Asia/Kolkata",
    "iso:country":"IN",
    "name:vie_x_preferred":[
        "Ganeshwadi"
    ],
    "wof:name":"Ganeshwadi",
    "wof:placetype":"locality"
},
  "geometry": {"coordinates":[76.75369000000001,18.35879],"type":"Point"}
}