{
  "type": "Feature",
  "properties": {
    "iso:country":"IN",
    "ks:ks_alt_nam":"Khet\u0101p\u0101ju",
    "ks:ks_name":"Khetapaju",
    "ks:ks_pop":48,
    "ks:ks_type":"VILLAGE",
    "name:eng_x_preferred":[
        "Khetapaju"
    ],
    "name:eng_x_variant":[
        "Khet\u0101p\u0101ju"
    ],
    "wof:name":"Khetapaju",
    "wof:placetype":"locality",
    "wof:population":48
},
  "geometry": {"coordinates":[84.155275,20.560026],"type":"Point"}
}