{
  "type": "Feature",
  "properties": {
    "iso:country":"IN",
    "ks:ks_name":"Bankajol",
    "ks:ks_pop":68,
    "ks:ks_type":"HABITATION",
    "name:eng_x_preferred":[
        "Bankajol"
    ],
    "wof:name":"Bankajol",
    "wof:placetype":"locality",
    "wof:population":68
},
  "geometry": {"coordinates":[87.58563100000001,22.919611],"type":"Point"}
}