{
  "type": "Feature",
  "properties": {
    "iso:country":"IN",
    "ks:ks_name":"Kharauni",
    "ks:ks_type":"VILLAGE",
    "ks:ks_uagg_main":0,
    "name:eng_x_preferred":[
        "Kharauni"
    ],
    "wof:name":"Kharauni",
    "wof:placetype":"neighbourhood"
},
  "geometry": {"coordinates":[84.456666,25.608407],"type":"Point"}
}