{
  "type": "Feature",
  "properties": {
    "iso:country":"IN",
    "ks:ks_name":"Birajpur",
    "ks:ks_pop":200,
    "ks:ks_type":"VILLAGE",
    "name:eng_x_preferred":[
        "Birajpur"
    ],
    "wof:name":"Birajpur",
    "wof:placetype":"locality",
    "wof:population":200
},
  "geometry": {"coordinates":[86.640512,23.981681],"type":"Point"}
}