{
  "type": "Feature",
  "properties": {
    "gn:admin1_code":"36",
    "gn:admin2_code":"191.0",
    "gn:asciiname":"Dehri",
    "gn:country_code":"IN",
    "gn:dem":89,
    "gn:feature_class":"P",
    "gn:feature_code":"PPL",
    "gn:name":"Dehri",
    "gn:population":0,
    "gn:timezone":"Asia/Kolkata",
    "iso:country":"IN",
    "name:ben_x_preferred":[
        "\u09a6\u09c7\u09b9\u09b0\u09c0"
    ],
    "name:bih_x_preferred":[
        "\u0921\u0947\u0939\u0930\u0940"
    ],
    "name:bpy_x_preferred":[
        "\u09a6\u09c7\u09b9\u09b0\u09c0"
    ],
    "name:ceb_x_preferred":[
        "Dehri"
    ],
    "name:deu_x_preferred":[
        "Dehri"
    ],
    "name:fra_x_preferred":[
        "Dehri"
    ],
    "name:ita_x_preferred":[
        "Dehri"
    ],
    "name:msa_x_preferred":[
        "Dehri"
    ],
    "name:nep_x_preferred":[
        "\u0921\u0947\u0939\u0930\u0940"
    ],
    "name:new_x_preferred":[
        "\u0926\u0947\u0939\u094d\u0930\u0940"
    ],
    "name:ori_x_preferred":[
        "\u0b26\u0b47\u0b39\u0b30\u0b3f"
    ],
    "name:por_x_preferred":[
        "Dehri"
    ],
    "name:rus_x_preferred":[
        "\u0414\u0435\u0445\u0440\u0438"
    ],
    "name:spa_x_preferred":[
        "Dehri"
    ],
    "name:swe_x_preferred":[
        "Dehri"
    ],
    "name:urd_x_preferred":[
        "\u062f\u06cc\u06c1\u0631\u06cc"
    ],
    "name:vie_x_preferred":[
        "Dehri"
    ],
    "name:zho_x_preferred":[
        "\u5fb7\u8d6b\u91cc"
    ],
    "wof:name":"Dehri",
    "wof:placetype":"locality"
},
  "geometry": {"coordinates":[82.74854000000001,26.12237],"type":"Point"}
}