{
  "type": "Feature",
  "properties": {
    "iso:country":"IN",
    "ks:ks_name":"Itaura",
    "ks:ks_pop":157,
    "ks:ks_type":"HABITATION",
    "name:eng_x_preferred":[
        "Itaura"
    ],
    "wof:name":"Itaura",
    "wof:placetype":"locality",
    "wof:population":157
},
  "geometry": {"coordinates":[81.599299,25.052199],"type":"Point"}
}