{
  "type": "Feature",
  "properties": {
    "gn:admin1_code":"36.0",
    "gn:admin2_code":"149",
    "gn:asciiname":"Garaulia",
    "gn:country_code":"IN",
    "gn:dem":165,
    "gn:feature_class":"P",
    "gn:feature_code":"PPL",
    "gn:name":"Garaulia",
    "gn:population":0,
    "gn:timezone":"Asia/Kolkata",
    "iso:country":"IN",
    "name:und_x_variant":[
        "Garaulla"
    ],
    "wof:name":"Garaulia",
    "wof:placetype":"neighbourhood"
},
  "geometry": {"coordinates":[79.06322,27.90056],"type":"Point"}
}