{
  "type": "Feature",
  "properties": {
    "iso:country":"IN",
    "ks:ks_name":"Salibhui",
    "ks:ks_pop":700,
    "ks:ks_type":"VILLAGE",
    "name:eng_x_preferred":[
        "Salibhui"
    ],
    "wof:name":"Salibhui",
    "wof:placetype":"locality",
    "wof:population":700
},
  "geometry": {"coordinates":[89.985676,25.625568],"type":"Point"}
}