{
  "type": "Feature",
  "properties": {
    "iso:country":"IN",
    "ks:ks_name":"Kondapa",
    "ks:ks_pop":281,
    "ks:ks_type":"VILLAGE",
    "name:eng_x_preferred":[
        "Kondapa"
    ],
    "wof:name":"Kondapa",
    "wof:placetype":"locality",
    "wof:population":281
},
  "geometry": {"coordinates":[74.599867,15.274554],"type":"Point"}
}