{
  "type": "Feature",
  "properties": {
    "iso:country":"IN",
    "ks:ks_name":"Maskand Chhit",
    "ks:ks_pop":308,
    "ks:ks_type":"VILLAGE",
    "ks:ks_uagg_main":0,
    "name:eng_x_preferred":[
        "Maskand Chhit"
    ],
    "wof:name":"Maskand Chhit",
    "wof:placetype":"neighbourhood",
    "wof:population":308
},
  "geometry": {"coordinates":[87.315667,25.036996],"type":"Point"}
}