{
  "type": "Feature",
  "properties": {
    "iso:country":"IN",
    "ks:ks_name":"Rajkumar Barmanpara",
    "ks:ks_pop":614,
    "ks:ks_type":"HABITATION",
    "name:eng_x_preferred":[
        "Rajkumar Barmanpara"
    ],
    "wof:name":"Rajkumar Barmanpara",
    "wof:placetype":"locality",
    "wof:population":614
},
  "geometry": {"coordinates":[89.64566600000001,26.270354],"type":"Point"}
}