{
  "type": "Feature",
  "properties": {
    "gn:admin1_code":"11",
    "gn:admin2_code":"28.0",
    "gn:asciiname":"Rakkar",
    "gn:country_code":"IN",
    "gn:dem":556,
    "gn:feature_class":"P",
    "gn:feature_code":"PPL",
    "gn:name":"Rakkar",
    "gn:population":0,
    "gn:timezone":"Asia/Kolkata",
    "iso:country":"IN",
    "wof:name":"Rakkar",
    "wof:placetype":"locality"
},
  "geometry": {"coordinates":[76.42608,31.75343],"type":"Point"}
}