{
  "type": "Feature",
  "properties": {
    "gn:admin1_code":"34.0",
    "gn:admin2_code":"220.0",
    "gn:asciiname":"Sapha",
    "gn:country_code":"IN",
    "gn:dem":54,
    "gn:feature_class":"P",
    "gn:feature_code":"PPL",
    "gn:name":"S\u0101pha",
    "gn:population":0,
    "gn:timezone":"Asia/Kolkata",
    "iso:country":"IN",
    "ks:ks_name":"Sopha",
    "ks:ks_pop":1097,
    "ks:ks_type":"VILLAGE",
    "name:eng_x_preferred":[
        "Sopha"
    ],
    "name:eng_x_variant":[
        "Sapha"
    ],
    "wof:name":"Sopha",
    "wof:placetype":"locality",
    "wof:population":1097
},
  "geometry": {"coordinates":[85.315234,25.72146],"type":"Point"}
}