{
  "type": "Feature",
  "properties": {
    "gn:admin1_code":"36.0",
    "gn:admin2_code":"135.0",
    "gn:asciiname":"Chak Hamidpur",
    "gn:country_code":"IN",
    "gn:dem":206,
    "gn:feature_class":"P",
    "gn:feature_code":"PPL",
    "gn:name":"Chak Ham\u012bdpur",
    "gn:population":0,
    "gn:timezone":"Asia/Kolkata",
    "iso:country":"IN",
    "wof:name":"Chak Hamidpur",
    "wof:placetype":"locality"
},
  "geometry": {"coordinates":[78.67650999999999,28.92404],"type":"Point"}
}