{
  "type": "Feature",
  "properties": {
    "iso:country":"IN",
    "ks:ks_alt_nam":"Karbhari faliya",
    "ks:ks_name":"Karbhari Faliya",
    "ks:ks_pop":170,
    "ks:ks_type":"HABITATION",
    "name:eng_x_preferred":[
        "Karbhari Faliya"
    ],
    "wof:name":"Karbhari Faliya",
    "wof:placetype":"locality",
    "wof:population":170
},
  "geometry": {"coordinates":[73.23820000000001,20.495589],"type":"Point"}
}