{
  "type": "Feature",
  "properties": {
    "iso:country":"IN",
    "ks:ks_name":"Champia",
    "ks:ks_pop":230,
    "ks:ks_type":"HABITATION",
    "name:eng_x_preferred":[
        "Champia"
    ],
    "wof:name":"Champia",
    "wof:placetype":"locality",
    "wof:population":230
},
  "geometry": {"coordinates":[83.903578,22.052673],"type":"Point"}
}