{
  "type": "Feature",
  "properties": {
    "iso:country":"IN",
    "ks:ks_name":"Khijarabad",
    "ks:ks_pop":777,
    "ks:ks_type":"VILLAGE",
    "ks:ks_uagg_main":0,
    "name:eng_x_preferred":[
        "Khijarabad"
    ],
    "wof:name":"Khijarabad",
    "wof:placetype":"neighbourhood",
    "wof:population":777
},
  "geometry": {"coordinates":[78.13007,28.380711],"type":"Point"}
}