{
  "type": "Feature",
  "properties": {
    "iso:country":"IN",
    "ks:ks_name":"Harijanwadi",
    "ks:ks_pop":26,
    "ks:ks_type":"HABITATION",
    "name:eng_x_preferred":[
        "Harijanwadi"
    ],
    "wof:name":"Harijanwadi",
    "wof:placetype":"locality",
    "wof:population":26
},
  "geometry": {"coordinates":[73.82174000000001,16.068506],"type":"Point"}
}