{
  "type": "Feature",
  "properties": {
    "gn:admin1_code":"36.0",
    "gn:admin2_code":"192.0",
    "gn:asciiname":"Gangupur",
    "gn:country_code":"IN",
    "gn:dem":73,
    "gn:feature_class":"P",
    "gn:feature_code":"PPL",
    "gn:name":"Gangupur",
    "gn:population":0,
    "gn:timezone":"Asia/Kolkata",
    "iso:country":"IN",
    "wof:name":"Gangupur",
    "wof:placetype":"neighbourhood"
},
  "geometry": {"coordinates":[83.70675,26.1825],"type":"Point"}
}