{
  "type": "Feature",
  "properties": {
    "gn:admin1_code":"25.0",
    "gn:admin2_code":"621.0",
    "gn:asciiname":"Osuvappatti",
    "gn:country_code":"IN",
    "gn:dem":91,
    "gn:feature_class":"P",
    "gn:feature_code":"PPL",
    "gn:name":"Osuvappatti",
    "gn:population":0,
    "gn:timezone":"Asia/Kolkata",
    "iso:country":"IN",
    "wof:name":"Osuvappatti",
    "wof:placetype":"locality"
},
  "geometry": {"coordinates":[79.01121999999999,10.52173],"type":"Point"}
}