{
  "type": "Feature",
  "properties": {
    "iso:country":"IN",
    "ks:ks_name":"Nishchintpur",
    "ks:ks_pop":293,
    "ks:ks_type":"VILLAGE",
    "ks:ks_uagg_main":0,
    "name:eng_x_preferred":[
        "Nishchintpur"
    ],
    "wof:name":"Nishchintpur",
    "wof:placetype":"neighbourhood",
    "wof:population":293
},
  "geometry": {"coordinates":[86.438761,22.43923],"type":"Point"}
}