{
  "type": "Feature",
  "properties": {
    "gn:admin1_code":"39.0",
    "gn:admin2_code":"63.0",
    "gn:asciiname":"Pandrapali",
    "gn:country_code":"IN",
    "gn:dem":1069,
    "gn:feature_class":"P",
    "gn:feature_code":"PPL",
    "gn:name":"Pandrap\u0101li",
    "gn:population":0,
    "gn:timezone":"Asia/Kolkata",
    "iso:country":"IN",
    "ks:ks_name":"Pandra Pali",
    "ks:ks_pop":714,
    "ks:ks_type":"VILLAGE",
    "name:eng_x_preferred":[
        "Pandra Pali"
    ],
    "name:eng_x_variant":[
        "Pandrapali"
    ],
    "wof:name":"Pandra Pali",
    "wof:placetype":"locality",
    "wof:population":714
},
  "geometry": {"coordinates":[79.765417,29.896034],"type":"Point"}
}