{
  "type": "Feature",
  "properties": {
    "gn:admin1_code":"25.0",
    "gn:admin2_code":"630.0",
    "gn:asciiname":"Peddanahalli",
    "gn:country_code":"IN",
    "gn:dem":507,
    "gn:feature_class":"P",
    "gn:feature_code":"PPL",
    "gn:name":"Peddanahalli",
    "gn:population":0,
    "gn:timezone":"Asia/Kolkata",
    "iso:country":"IN",
    "wof:name":"Peddanahalli",
    "wof:placetype":"neighbourhood"
},
  "geometry": {"coordinates":[77.94336,12.14101],"type":"Point"}
}