{
  "type": "Feature",
  "properties": {
    "iso:country":"IN",
    "ks:ks_name":"Baisa",
    "ks:ks_pop":171,
    "ks:ks_type":"VILLAGE",
    "ks:ks_uagg_main":0,
    "name:eng_x_preferred":[
        "Baisa"
    ],
    "wof:name":"Baisa",
    "wof:placetype":"neighbourhood",
    "wof:population":171
},
  "geometry": {"coordinates":[86.788802,26.358371],"type":"Point"}
}