{
  "type": "Feature",
  "properties": {
    "iso:country":"IN",
    "ks:ks_name":"Deogan Lalauna",
    "ks:ks_pop":381,
    "ks:ks_type":"HABITATION",
    "name:eng_x_preferred":[
        "Deogan Lalauna"
    ],
    "wof:name":"Deogan Lalauna",
    "wof:placetype":"locality",
    "wof:population":381
},
  "geometry": {"coordinates":[85.524528,26.195176],"type":"Point"}
}