{
  "type": "Feature",
  "properties": {
    "iso:country":"IN",
    "ks:ks_name":"Doliguda",
    "ks:ks_pop":266,
    "ks:ks_type":"HABITATION",
    "name:eng_x_preferred":[
        "Doliguda"
    ],
    "wof:name":"Doliguda",
    "wof:placetype":"locality",
    "wof:population":266
},
  "geometry": {"coordinates":[82.07488600000001,18.164087],"type":"Point"}
}