{
  "type": "Feature",
  "properties": {
    "gn:admin1_code":"39.0",
    "gn:admin2_code":"65.0",
    "gn:asciiname":"Odali",
    "gn:country_code":"IN",
    "gn:dem":964,
    "gn:feature_class":"P",
    "gn:feature_code":"PPL",
    "gn:name":"Od\u0101l\u012b",
    "gn:population":0,
    "gn:timezone":"Asia/Kolkata",
    "iso:country":"IN",
    "wof:name":"Odali",
    "wof:placetype":"locality"
},
  "geometry": {"coordinates":[80.10623000000002,29.18875],"type":"Point"}
}