{
  "type": "Feature",
  "properties": {
    "iso:country":"IN",
    "ks:ks_alt_nam":"Jambadia-II",
    "ks:ks_name":"Jambadia-ii",
    "ks:ks_pop":268,
    "ks:ks_type":"HABITATION",
    "name:eng_x_preferred":[
        "Jambadia-ii"
    ],
    "wof:name":"Jambadia-ii",
    "wof:placetype":"locality",
    "wof:population":268
},
  "geometry": {"coordinates":[87.05760100000001,22.246656],"type":"Point"}
}