{
  "type": "Feature",
  "properties": {
    "iso:country":"IN",
    "ks:ks_name":"Malupur",
    "ks:ks_pop":2389,
    "ks:ks_type":"VILLAGE",
    "name:eng_x_preferred":[
        "Malupur"
    ],
    "wof:name":"Malupur",
    "wof:placetype":"neighbourhood",
    "wof:population":2389
},
  "geometry": {"coordinates":[78.020104,27.294078],"type":"Point"}
}