{
  "type": "Feature",
  "properties": {
    "gn:admin1_code":"25.0",
    "gn:admin2_code":"606.0",
    "gn:asciiname":"Pudurnattam",
    "gn:country_code":"IN",
    "gn:dem":199,
    "gn:feature_class":"P",
    "gn:feature_code":"PPL",
    "gn:name":"Pud\u016brnattam",
    "gn:population":0,
    "gn:timezone":"Asia/Kolkata",
    "iso:country":"IN",
    "wof:name":"Pudurnattam",
    "wof:placetype":"locality"
},
  "geometry": {"coordinates":[78.86622,12.13283],"type":"Point"}
}