{
  "type": "Feature",
  "properties": {
    "iso:country":"IN",
    "ks:ks_name":"20 RWD-B",
    "ks:ks_pop":49,
    "ks:ks_type":"VILLAGE",
    "name:eng_x_preferred":[
        "20 RWD-B"
    ],
    "wof:name":"20 RWD-B",
    "wof:placetype":"locality",
    "wof:population":49
},
  "geometry": {"coordinates":[74.60317499999999,29.273575],"type":"Point"}
}