{
  "type": "Feature",
  "properties": {
    "iso:country":"IN",
    "ks:ks_alt_nam":"Chettupally thanda",
    "ks:ks_name":"Chettupally Thanda",
    "ks:ks_pop":136,
    "ks:ks_type":"HABITATION",
    "name:eng_x_preferred":[
        "Chettupally Thanda"
    ],
    "wof:name":"Chettupally Thanda",
    "wof:placetype":"locality",
    "wof:population":136
},
  "geometry": {"coordinates":[77.669518,17.09915],"type":"Point"}
}