{
  "type": "Feature",
  "properties": {
    "iso:country":"IN",
    "ks:ks_name":"Bigha",
    "ks:ks_pop":1399,
    "ks:ks_type":"HABITATION",
    "name:eng_x_preferred":[
        "Bigha"
    ],
    "wof:name":"Bigha",
    "wof:placetype":"locality",
    "wof:population":1399
},
  "geometry": {"coordinates":[85.36201199999999,24.398465],"type":"Point"}
}