{
  "type": "Feature",
  "properties": {
    "iso:country":"IN",
    "ks:ks_name":"Manikattiyental",
    "ks:ks_pop":96,
    "ks:ks_type":"HABITATION",
    "name:eng_x_preferred":[
        "Manikattiyental"
    ],
    "wof:name":"Manikattiyental",
    "wof:placetype":"locality",
    "wof:population":96
},
  "geometry": {"coordinates":[78.33930700000001,9.633003],"type":"Point"}
}