{
  "type": "Feature",
  "properties": {
    "iso:country":"IN",
    "ks:ks_alt_nam":"FITTINGPARA",
    "ks:ks_name":"Fittingpara",
    "ks:ks_pop":165,
    "ks:ks_type":"HABITATION",
    "name:eng_x_preferred":[
        "Fittingpara"
    ],
    "wof:name":"Fittingpara",
    "wof:placetype":"locality",
    "wof:population":165
},
  "geometry": {"coordinates":[83.722335,22.43045],"type":"Point"}
}