{
  "type": "Feature",
  "properties": {
    "gn:admin1_code":"36.0",
    "gn:admin2_code":"175.0",
    "gn:asciiname":"Dandupur",
    "gn:country_code":"IN",
    "gn:dem":97,
    "gn:feature_class":"P",
    "gn:feature_code":"PPL",
    "gn:name":"D\u0101nd\u016bpur",
    "gn:population":0,
    "gn:timezone":"Asia/Kolkata",
    "iso:country":"IN",
    "ks:ks_alt_nam":"D\u0101nd\u016bpur",
    "ks:ks_name":"Dandupur",
    "ks:ks_pop":1850,
    "ks:ks_type":"VILLAGE",
    "ks:ks_uagg_main":0,
    "name:eng_x_preferred":[
        "Dandupur"
    ],
    "name:eng_x_variant":[
        "D\u0101nd\u016bpur"
    ],
    "wof:name":"Dandupur",
    "wof:placetype":"neighbourhood",
    "wof:population":1850
},
  "geometry": {"coordinates":[81.829933,25.353975],"type":"Point"}
}