{
  "type": "Feature",
  "properties": {
    "iso:country":"IN",
    "ks:ks_name":"Fikarchak",
    "ks:ks_pop":349,
    "ks:ks_type":"HABITATION",
    "name:eng_x_preferred":[
        "Fikarchak"
    ],
    "wof:name":"Fikarchak",
    "wof:placetype":"locality",
    "wof:population":349
},
  "geometry": {"coordinates":[85.0432,25.471],"type":"Point"}
}