{
  "type": "Feature",
  "properties": {
    "iso:country":"IN",
    "ks:ks_name":"Gaja Pagina Muvada",
    "ks:ks_pop":1305,
    "ks:ks_type":"VILLAGE",
    "name:eng_x_preferred":[
        "Gaja Pagina Muvada"
    ],
    "wof:name":"Gaja Pagina Muvada",
    "wof:placetype":"locality",
    "wof:population":1305
},
  "geometry": {"coordinates":[73.313365,23.0087],"type":"Point"}
}