{
  "type": "Feature",
  "properties": {
    "gn:country":"IN",
    "gn:fcode":"PPL",
    "gn:population":0,
    "iso:country":"IN",
    "ks:ks_alt_nam":"B\u0101dsh\u0101hpur",
    "ks:ks_name":"Badshahpur",
    "ks:ks_pop":15593,
    "ks:ks_type":"VILLAGE",
    "ks:ks_uagg_main":0,
    "name:ara_x_preferred":[
        "\u0628\u0627\u062f\u0634\u0627\u0647\u0628\u0648\u0631"
    ],
    "name:ast_x_preferred":[
        "Badshahpur"
    ],
    "name:azb_x_preferred":[
        "\u0628\u0627\u062f\u0634\u0627\u0647\u067e\u0648\u0631"
    ],
    "name:ben_bn_x_preferred":[
        "\u09ac\u09be\u09a6\u09b6\u09be\u09b9\u09aa\u09c1\u09b0"
    ],
    "name:ben_in_x_preferred":[
        "\u09ac\u09be\u09a6\u09b6\u09be\u09b9\u09aa\u09c1\u09b0"
    ],
    "name:ceb_x_preferred":[
        "B\u0101dsh\u0101hpur"
    ],
    "name:eng_x_preferred":[
        "Badshahpur"
    ],
    "name:guj_x_preferred":[
        "\u0aac\u0abe\u0aa6\u0ab6\u0abe\u0ab9\u0aaa\u0ac1\u0ab0"
    ],
    "name:hin_x_preferred":[
        "\u092c\u093e\u0926\u0936\u093e\u0939\u092a\u0941\u0930"
    ],
    "name:kan_x_preferred":[
        "\u0cac\u0cbe\u0ca6\u0ccd"
    ],
    "name:mal_x_preferred":[
        "\u0d2c\u0d3e\u0d26\u0d4d"
    ],
    "name:mar_x_preferred":[
        "\u092c\u093e\u0926\u0936\u093e\u0939\u092a\u0942\u0930"
    ],
    "name:nld_x_preferred":[
        "Badshahpur"
    ],
    "name:pan_x_preferred":[
        "\u0a2c\u0a21\u0a36\u0a3e\u0a39\u0a2a\u0a41\u0a30"
    ],
    "name:swe_x_preferred":[
        "B\u0101dsh\u0101hpur"
    ],
    "name:tam_x_preferred":[
        "\u0baa\u0bbe\u0ba4\u0bcd\u0bb7\u0bbe\u0baa\u0bc2\u0bb0\u0bcd"
    ],
    "name:tel_x_preferred":[
        "\u0c2c\u0c3e\u0c26\u0c4d\u0c37\u0c3e\u0c2a\u0c42\u0c30\u0c4d"
    ],
    "name:urd_x_preferred":[
        "\u0628\u0627\u062f\u0634\u0627\u06c1 \u067e\u0648\u0631"
    ],
    "qs:name":"Badshahpur",
    "qs:name_adm0":"India",
    "qs:name_adm1":"Haryana",
    "qs:photos":3,
    "qs:photos_1k":1,
    "qs:photos_9k":1,
    "qs:photos_9r":1,
    "qs:photos_all":3,
    "qs:photos_sr":1,
    "qs:placetype":"Suburb",
    "qs:pop_sr":"0",
    "wd:elevation":240.0,
    "wd:wordcount":403,
    "wof:name":"Badshahpur",
    "wof:placetype":"neighbourhood",
    "wof:population":0
},
  "geometry": {"coordinates":[77.04919,28.39318],"type":"Point"}
}