{
  "type": "Feature",
  "properties": {
    "gn:country":"IN",
    "gn:fcode":"PPL",
    "gn:pop":0,
    "iso:country":"IN",
    "name:ast_x_preferred":[
        "Badshahpur"
    ],
    "name:ceb_x_preferred":[
        "B\u0101dsh\u0101hpur"
    ],
    "name:eng_x_preferred":[
        "Badshahpur"
    ],
    "name:nld_x_preferred":[
        "Badshahpur"
    ],
    "name:swe_x_preferred":[
        "B\u0101dsh\u0101hpur"
    ],
    "name:unk_x_variant":[
        "B\u0101dsh\u0101hpur"
    ],
    "qs:name":"Badshahpur",
    "qs:name_adm0":"India",
    "qs:name_adm1":"Haryana",
    "qs:photos":3,
    "qs:photos_1k":1,
    "qs:photos_9k":1,
    "qs:photos_9r":1,
    "qs:photos_all":3,
    "qs:photos_sr":1,
    "qs:placetype":"Suburb",
    "qs:pop_sr":"0",
    "wd:elevation":240.0,
    "wd:wordcount":403,
    "wof:name":"Badshahpur",
    "wof:placetype":"neighbourhood",
    "wof:population":0
},
  "geometry": {"coordinates":[77.04919,28.39318],"type":"Point"}
}