{
  "type": "Feature",
  "properties": {
    "iso:country":"IN",
    "ks:ks_alt_nam":"Muthusamy nagar H",
    "ks:ks_name":"Muthusamy Nagar H",
    "ks:ks_pop":300,
    "ks:ks_type":"HABITATION",
    "ks:ks_uagg_main":0,
    "name:eng_x_preferred":[
        "Muthusamy Nagar H"
    ],
    "wof:name":"Muthusamy Nagar H",
    "wof:placetype":"neighbourhood",
    "wof:population":300
},
  "geometry": {"coordinates":[76.769828,11.47695],"type":"Point"}
}