{
  "type": "Feature",
  "properties": {
    "gn:admin1_code":"38.0",
    "gn:admin2_code":"362.0",
    "gn:asciiname":"Siulibana",
    "gn:country_code":"IN",
    "gn:dem":148,
    "gn:feature_class":"P",
    "gn:feature_code":"PPL",
    "gn:name":"Siulib\u0101na",
    "gn:population":0,
    "gn:timezone":"Asia/Kolkata",
    "iso:country":"IN",
    "ks:ks_alt_nam":"Siulib\u0101na",
    "ks:ks_name":"Siulibana",
    "ks:ks_pop":133,
    "ks:ks_type":"VILLAGE",
    "name:eng_x_preferred":[
        "Siulibana"
    ],
    "name:eng_x_variant":[
        "Siulib\u0101na"
    ],
    "wof:name":"Siulibana",
    "wof:placetype":"locality",
    "wof:population":133
},
  "geometry": {"coordinates":[87.56611100000001,24.145644],"type":"Point"}
}