{
  "type": "Feature",
  "properties": {
    "iso:country":"IN",
    "ks:ks_name":"Mazrowmari Kachari",
    "ks:ks_pop":612,
    "ks:ks_type":"VILLAGE",
    "ks:ks_uagg_main":0,
    "name:eng_x_preferred":[
        "Mazrowmari Kachari"
    ],
    "wof:name":"Mazrowmari Kachari",
    "wof:placetype":"neighbourhood",
    "wof:population":612
},
  "geometry": {"coordinates":[92.362054,26.757085],"type":"Point"}
}