{
  "type": "Feature",
  "properties": {
    "iso:country":"IN",
    "ks:ks_name":"Chheliabeda",
    "ks:ks_pop":18,
    "ks:ks_type":"VILLAGE",
    "name:eng_x_preferred":[
        "Chheliabeda"
    ],
    "wof:name":"Chheliabeda",
    "wof:placetype":"locality",
    "wof:population":18
},
  "geometry": {"coordinates":[85.57853900000001,20.939318],"type":"Point"}
}