{
  "type": "Feature",
  "properties": {
    "iso:country":"IN",
    "ks:ks_name":"Balahadlu",
    "ks:ks_pop":158,
    "ks:ks_type":"HABITATION",
    "name:eng_x_preferred":[
        "Balahadlu"
    ],
    "wof:name":"Balahadlu",
    "wof:placetype":"locality",
    "wof:population":158
},
  "geometry": {"coordinates":[75.44300800000001,13.189404],"type":"Point"}
}