{
  "type": "Feature",
  "properties": {
    "iso:country":"IN",
    "ks:ks_alt_nam":"N\u012blamdippa",
    "ks:ks_name":"Nilamdippa",
    "ks:ks_type":"VILLAGE",
    "name:eng_x_preferred":[
        "Nilamdippa"
    ],
    "name:eng_x_variant":[
        "N\u012blamdippa"
    ],
    "wof:name":"Nilamdippa",
    "wof:placetype":"locality"
},
  "geometry": {"coordinates":[80.463866,18.67834],"type":"Point"}
}