{
  "type": "Feature",
  "properties": {
    "gn:admin1_code":"36.0",
    "gn:admin2_code":"184.0",
    "gn:asciiname":"Kaharpurwa",
    "gn:country_code":"IN",
    "gn:dem":90,
    "gn:feature_class":"P",
    "gn:feature_code":"PPL",
    "gn:name":"Kah\u0101rpurwa",
    "gn:population":0,
    "gn:timezone":"Asia/Kolkata",
    "iso:country":"IN",
    "ks:ks_name":"Kaharpurwa",
    "ks:ks_pop":381,
    "ks:ks_type":"VILLAGE",
    "name:eng_x_preferred":[
        "Kaharpurwa"
    ],
    "wof:name":"Kaharpurwa",
    "wof:placetype":"locality",
    "wof:population":381
},
  "geometry": {"coordinates":[82.864813,27.068026],"type":"Point"}
}