{
  "type": "Feature",
  "properties": {
    "iso:country":"IN",
    "ks:ks_name":"Pakahi",
    "ks:ks_pop":188,
    "ks:ks_type":"HABITATION",
    "name:eng_x_preferred":[
        "Pakahi"
    ],
    "wof:name":"Pakahi",
    "wof:placetype":"locality",
    "wof:population":188
},
  "geometry": {"coordinates":[84.960875,24.955027],"type":"Point"}
}