{
  "type": "Feature",
  "properties": {
    "iso:country":"IN",
    "ks:ks_name":"Nalajhar",
    "ks:ks_pop":550,
    "ks:ks_type":"VILLAGE",
    "name:eng_x_preferred":[
        "Nalajhar"
    ],
    "wof:name":"Nalajhar",
    "wof:placetype":"locality",
    "wof:population":550
},
  "geometry": {"coordinates":[81.689408,19.8222],"type":"Point"}
}