{
  "type": "Feature",
  "properties": {
    "iso:country":"IN",
    "ks:ks_name":"Piyola",
    "ks:ks_pop":1083,
    "ks:ks_type":"VILLAGE",
    "name:eng_x_preferred":[
        "Piyola"
    ],
    "wof:name":"Piyola",
    "wof:placetype":"locality",
    "wof:population":1083
},
  "geometry": {"coordinates":[73.919152,23.40653],"type":"Point"}
}