{
  "type": "Feature",
  "properties": {
    "iso:country":"IN",
    "ks:ks_name":"Eduravada",
    "ks:ks_pop":111,
    "ks:ks_type":"HABITATION",
    "name:eng_x_preferred":[
        "Eduravada"
    ],
    "wof:name":"Eduravada",
    "wof:placetype":"locality",
    "wof:population":111
},
  "geometry": {"coordinates":[83.78868799999999,18.713524],"type":"Point"}
}