{
  "type": "Feature",
  "properties": {
    "iso:country":"IN",
    "ks:ks_name":"Bichali",
    "ks:ks_pop":140,
    "ks:ks_type":"HABITATION",
    "name:eng_x_preferred":[
        "Bichali"
    ],
    "wof:name":"Bichali",
    "wof:placetype":"locality",
    "wof:population":140
},
  "geometry": {"coordinates":[72.960178,24.507189],"type":"Point"}
}