{
  "type": "Feature",
  "properties": {
    "iso:country":"IN",
    "ks:ks_name":"Dhobapalli",
    "ks:ks_pop":43,
    "ks:ks_type":"VILLAGE",
    "name:eng_x_preferred":[
        "Dhobapalli"
    ],
    "wof:name":"Dhobapalli",
    "wof:placetype":"locality",
    "wof:population":43
},
  "geometry": {"coordinates":[84.530975,19.618249],"type":"Point"}
}