{
  "type": "Feature",
  "properties": {
    "iso:country":"IN",
    "ks:ks_name":"Kamal Chak",
    "ks:ks_pop":888,
    "ks:ks_type":"VILLAGE",
    "ks:ks_uagg_main":0,
    "name:eng_x_preferred":[
        "Kamal Chak"
    ],
    "wof:name":"Kamal Chak",
    "wof:placetype":"neighbourhood",
    "wof:population":888
},
  "geometry": {"coordinates":[88.36516899999999,24.252357],"type":"Point"}
}