{
  "type": "Feature",
  "properties": {
    "iso:country":"IN",
    "ks:ks_alt_nam":"Sreeramnagar colony",
    "ks:ks_name":"Sreeramnagar Colony",
    "ks:ks_pop":201,
    "ks:ks_type":"HABITATION",
    "name:eng_x_preferred":[
        "Sreeramnagar Colony"
    ],
    "wof:name":"Sreeramnagar Colony",
    "wof:placetype":"locality",
    "wof:population":201
},
  "geometry": {"coordinates":[80.02037300000001,14.70523],"type":"Point"}
}