{
  "type": "Feature",
  "properties": {
    "iso:country":"IN",
    "ks:ks_name":"Bijanu",
    "ks:ks_pop":410,
    "ks:ks_type":"HABITATION",
    "name:eng_x_preferred":[
        "Bijanu"
    ],
    "wof:name":"Bijanu",
    "wof:placetype":"locality",
    "wof:population":410
},
  "geometry": {"coordinates":[77.968155,30.705117],"type":"Point"}
}