{
  "type": "Feature",
  "properties": {
    "iso:country":"IN",
    "ks:ks_name":"Pendarpani",
    "ks:ks_pop":88,
    "ks:ks_type":"HABITATION",
    "name:eng_x_preferred":[
        "Pendarpani"
    ],
    "wof:name":"Pendarpani",
    "wof:placetype":"locality",
    "wof:population":88
},
  "geometry": {"coordinates":[81.03884600000001,20.438496],"type":"Point"}
}