{
  "type": "Feature",
  "properties": {
    "gn:admin1_code":"9.0",
    "gn:admin2_code":"485.0",
    "gn:asciiname":"Gamla",
    "gn:country_code":"IN",
    "gn:dem":318,
    "gn:feature_class":"P",
    "gn:feature_code":"PPL",
    "gn:name":"Gamla",
    "gn:population":0,
    "gn:timezone":"Asia/Kolkata",
    "iso:country":"IN",
    "name:ara_x_preferred":[
        "\u062c\u0645\u0627\u0644\u0627"
    ],
    "name:bul_x_preferred":[
        "\u0413\u0430\u043c\u043b\u0430"
    ],
    "name:cat_x_preferred":[
        "Gamala"
    ],
    "name:ces_x_preferred":[
        "Gamla"
    ],
    "name:deu_x_preferred":[
        "Gamla"
    ],
    "name:fra_x_preferred":[
        "Gamla"
    ],
    "name:heb_x_preferred":[
        "\u05d2\u05de\u05dc\u05d0"
    ],
    "name:hye_x_preferred":[
        "\u0533\u0561\u0574\u056c\u0561"
    ],
    "name:ita_x_preferred":[
        "Gamala"
    ],
    "name:nor_x_preferred":[
        "Gamla"
    ],
    "name:pol_x_preferred":[
        "Gamla"
    ],
    "name:rus_x_preferred":[
        "\u0413\u0430\u043c\u043b\u0430"
    ],
    "name:spa_x_preferred":[
        "Gamala"
    ],
    "name:ukr_x_preferred":[
        "\u0413\u0430\u043c\u043b\u0430"
    ],
    "wof:name":"Gamla",
    "wof:placetype":"locality"
},
  "geometry": {"coordinates":[74.32292,22.79891],"type":"Point"}
}