{
  "type": "Feature",
  "properties": {
    "gn:admin1_code":"35",
    "gn:admin2_code":"457.0",
    "gn:asciiname":"Bitli",
    "gn:country_code":"IN",
    "gn:dem":771,
    "gn:feature_class":"P",
    "gn:feature_code":"PPL",
    "gn:name":"Bitli",
    "gn:population":0,
    "gn:timezone":"Asia/Kolkata",
    "iso:country":"IN",
    "ks:ks_name":"Bithli",
    "ks:ks_pop":1121,
    "ks:ks_type":"HABITATION",
    "name:eng_x_preferred":[
        "Bithli"
    ],
    "name:eng_x_variant":[
        "Bitli"
    ],
    "wof:name":"Bithli",
    "wof:placetype":"locality",
    "wof:population":1121
},
  "geometry": {"coordinates":[81.006557,22.154341],"type":"Point"}
}