{
  "type": "Feature",
  "properties": {
    "gn:admin1_code":"36.0",
    "gn:admin2_code":"156.0",
    "gn:asciiname":"Hindu Khera",
    "gn:country_code":"IN",
    "gn:dem":128,
    "gn:feature_class":"P",
    "gn:feature_code":"PPL",
    "gn:name":"Hindu Khera",
    "gn:population":0,
    "gn:timezone":"Asia/Kolkata",
    "iso:country":"IN",
    "wof:name":"Hindu Khera",
    "wof:placetype":"locality"
},
  "geometry": {"coordinates":[80.49743000000002,26.49302],"type":"Point"}
}