{
  "type": "Feature",
  "properties": {
    "gn:admin1_code":"37",
    "gn:admin2_code":"404.0",
    "gn:asciiname":"Saraipali",
    "gn:country_code":"IN",
    "gn:dem":269,
    "gn:feature_class":"P",
    "gn:feature_code":"PPL",
    "gn:name":"Saraip\u0101li",
    "gn:population":0,
    "gn:timezone":"Asia/Kolkata",
    "iso:country":"IN",
    "name:ben_x_preferred":[
        "\u09b8\u09b0\u09be\u0987\u09aa\u09be\u09b2\u09bf"
    ],
    "name:bpy_x_preferred":[
        "\u09b8\u09b0\u09be\u0987\u09aa\u09be\u09b2\u09bf"
    ],
    "name:ceb_x_preferred":[
        "Saraip\u0101li"
    ],
    "name:hin_x_preferred":[
        "\u0938\u0930\u093e\u092f\u092a\u093e\u0932\u0940"
    ],
    "name:ita_x_preferred":[
        "Saraipali"
    ],
    "name:msa_x_preferred":[
        "Saraipali"
    ],
    "name:nld_x_preferred":[
        "Saraipali"
    ],
    "name:ori_x_preferred":[
        "\u0b38\u0b30\u0b3e\u0b07\u0b2a\u0b3e\u0b33\u0b3f"
    ],
    "name:por_x_preferred":[
        "Saraipali"
    ],
    "name:spa_x_preferred":[
        "Saraipali"
    ],
    "name:swe_x_preferred":[
        "Saraip\u0101li"
    ],
    "name:tgl_x_preferred":[
        "Saraipali"
    ],
    "name:urd_x_preferred":[
        "\u0633\u0631\u0626\u06cc \u067e\u0644\u06cc"
    ],
    "name:vie_x_preferred":[
        "Saraipali"
    ],
    "name:zho_x_preferred":[
        "\u8428\u8d56\u5e15\u5229"
    ],
    "wof:name":"Saraipali",
    "wof:placetype":"locality"
},
  "geometry": {"coordinates":[82.67007,22.08667],"type":"Point"}
}