{
  "type": "Feature",
  "properties": {
    "iso:country":"IN",
    "ks:ks_name":"jhapusabari Pt IV",
    "ks:ks_pop":2445,
    "ks:ks_type":"VILLAGE",
    "name:eng_x_preferred":[
        "jhapusabari Pt IV"
    ],
    "wof:name":"jhapusabari Pt IV",
    "wof:placetype":"locality",
    "wof:population":2445
},
  "geometry": {"coordinates":[89.715757,26.179451],"type":"Point"}
}