{
  "type": "Feature",
  "properties": {
    "iso:country":"IN",
    "ks:ks_name":"Mampoke",
    "ks:ks_pop":660,
    "ks:ks_type":"HABITATION",
    "name:eng_x_preferred":[
        "Mampoke"
    ],
    "wof:name":"Mampoke",
    "wof:placetype":"locality",
    "wof:population":660
},
  "geometry": {"coordinates":[76.514216,10.972862],"type":"Point"}
}