{
  "type": "Feature",
  "properties": {
    "gn:admin1_code":"11.0",
    "gn:admin2_code":"32.0",
    "gn:asciiname":"Drolt",
    "gn:country_code":"IN",
    "gn:dem":1962,
    "gn:feature_class":"P",
    "gn:feature_code":"PPL",
    "gn:name":"Drolt",
    "gn:population":0,
    "gn:timezone":"Asia/Kolkata",
    "iso:country":"IN",
    "wof:name":"Drolt",
    "wof:placetype":"locality"
},
  "geometry": {"coordinates":[77.43014000000002,30.94006],"type":"Point"}
}