{
  "type": "Feature",
  "properties": {
    "iso:country":"IN",
    "ks:ks_name":"Kanthariya",
    "ks:ks_pop":705,
    "ks:ks_type":"VILLAGE",
    "name:eng_x_preferred":[
        "Kanthariya"
    ],
    "wof:name":"Kanthariya",
    "wof:placetype":"locality",
    "wof:population":705
},
  "geometry": {"coordinates":[73.34397199999999,24.059472],"type":"Point"}
}