{
  "type": "Feature",
  "properties": {
    "iso:country":"IN",
    "ks:ks_alt_nam":"MAGDUM MALA",
    "ks:ks_name":"Magdum Mala",
    "ks:ks_pop":109,
    "ks:ks_type":"HABITATION",
    "name:eng_x_preferred":[
        "Magdum Mala"
    ],
    "wof:name":"Magdum Mala",
    "wof:placetype":"locality",
    "wof:population":109
},
  "geometry": {"coordinates":[74.65202499999999,16.747931],"type":"Point"}
}