{
  "type": "Feature",
  "properties": {
    "gn:admin1_code":"39.0",
    "gn:admin2_code":"66.0",
    "gn:asciiname":"Haripur Motia",
    "gn:country_code":"IN",
    "gn:dem":332,
    "gn:feature_class":"P",
    "gn:feature_code":"PPL",
    "gn:name":"Har\u012bpur Motia",
    "gn:population":0,
    "gn:timezone":"Asia/Kolkata",
    "iso:country":"IN",
    "ks:ks_alt_nam":"Har\u012bpur Motia",
    "ks:ks_name":"Haripur Motia",
    "ks:ks_type":"VILLAGE",
    "ks:ks_uagg_main":0,
    "name:eng_x_preferred":[
        "Haripur Motia"
    ],
    "name:eng_x_variant":[
        "Har\u012bpur Motia"
    ],
    "wof:name":"Haripur Motia",
    "wof:placetype":"neighbourhood"
},
  "geometry": {"coordinates":[79.474965,29.151851],"type":"Point"}
}