{
  "type": "Feature",
  "properties": {
    "iso:country":"IN",
    "ks:ks_alt_nam":"Kadav\u0101sal",
    "ks:ks_name":"Kadavasal",
    "ks:ks_pop":667,
    "ks:ks_type":"VILLAGE",
    "name:eng_x_preferred":[
        "Kadavasal"
    ],
    "name:eng_x_variant":[
        "Kadav\u0101sal"
    ],
    "wof:name":"Kadavasal",
    "wof:placetype":"locality",
    "wof:population":667
},
  "geometry": {"coordinates":[79.767027,11.255563],"type":"Point"}
}