{
  "type": "Feature",
  "properties": {
    "gn:admin1_code":"12.0",
    "gn:admin2_code":"2.0",
    "gn:asciiname":"Kuthipur",
    "gn:country_code":"IN",
    "gn:dem":1597,
    "gn:feature_class":"P",
    "gn:feature_code":"PPL",
    "gn:name":"Kuthipur",
    "gn:population":0,
    "gn:timezone":"Asia/Kolkata",
    "iso:country":"IN",
    "wof:name":"Kuthipur",
    "wof:placetype":"locality"
},
  "geometry": {"coordinates":[74.85129000000001,33.99545],"type":"Point"}
}