{
  "type": "Feature",
  "properties": {
    "iso:country":"IN",
    "ks:ks_name":"Sarandhichak",
    "ks:ks_pop":50,
    "ks:ks_type":"HABITATION",
    "ks:ks_uagg_main":0,
    "name:eng_x_preferred":[
        "Sarandhichak"
    ],
    "wof:name":"Sarandhichak",
    "wof:placetype":"neighbourhood",
    "wof:population":50
},
  "geometry": {"coordinates":[81.545813,27.531332],"type":"Point"}
}