{
  "type": "Feature",
  "properties": {
    "iso:country":"IN",
    "ks:ks_name":"Petkhola",
    "ks:ks_pop":44,
    "ks:ks_type":"HABITATION",
    "name:eng_x_preferred":[
        "Petkhola"
    ],
    "wof:name":"Petkhola",
    "wof:placetype":"locality",
    "wof:population":44
},
  "geometry": {"coordinates":[80.15794,29.698319],"type":"Point"}
}