{
  "type": "Feature",
  "properties": {
    "gn:admin1_code":"19.0",
    "gn:admin2_code":"564.0",
    "gn:asciiname":"Bhardi",
    "gn:country_code":"IN",
    "gn:dem":604,
    "gn:feature_class":"P",
    "gn:feature_code":"PPL",
    "gn:name":"Bhardi",
    "gn:population":0,
    "gn:timezone":"Asia/Kolkata",
    "iso:country":"IN",
    "wof:name":"Bhardi",
    "wof:placetype":"locality"
},
  "geometry": {"coordinates":[75.56676999999998,14.78502],"type":"Point"}
}