{
  "type": "Feature",
  "properties": {
    "iso:country":"IN",
    "ks:ks_name":"Badha Tola",
    "ks:ks_pop":253,
    "ks:ks_type":"HABITATION",
    "name:eng_x_preferred":[
        "Badha Tola"
    ],
    "wof:name":"Badha Tola",
    "wof:placetype":"locality",
    "wof:population":253
},
  "geometry": {"coordinates":[83.011571,24.596944],"type":"Point"}
}