{
  "type": "Feature",
  "properties": {
    "iso:country":"IN",
    "ks:ks_name":"Hedpada",
    "ks:ks_pop":186,
    "ks:ks_type":"HABITATION",
    "name:eng_x_preferred":[
        "Hedpada"
    ],
    "wof:name":"Hedpada",
    "wof:placetype":"locality",
    "wof:population":186
},
  "geometry": {"coordinates":[73.450278,20.003889],"type":"Point"}
}