{
  "type": "Feature",
  "properties": {
    "iso:country":"IN",
    "ks:ks_name":"Kodagihalli",
    "ks:ks_pop":254,
    "ks:ks_type":"HABITATION",
    "name:eng_x_preferred":[
        "Kodagihalli"
    ],
    "wof:name":"Kodagihalli",
    "wof:placetype":"locality",
    "wof:population":254
},
  "geometry": {"coordinates":[75.956686,12.993586],"type":"Point"}
}