{
  "type": "Feature",
  "properties": {
    "iso:country":"IN",
    "ks:ks_name":"Topadihi",
    "ks:ks_pop":658,
    "ks:ks_type":"VILLAGE",
    "name:eng_x_preferred":[
        "Topadihi"
    ],
    "wof:name":"Topadihi",
    "wof:placetype":"locality",
    "wof:population":658
},
  "geometry": {"coordinates":[85.196257,22.052302],"type":"Point"}
}