{
  "type": "Feature",
  "properties": {
    "iso:country":"IN",
    "ks:ks_name":"Lizziepur Tea Garden",
    "ks:ks_pop":1671,
    "ks:ks_type":"VILLAGE",
    "name:eng_x_preferred":[
        "Lizziepur Tea Garden"
    ],
    "wof:name":"Lizziepur Tea Garden",
    "wof:placetype":"locality",
    "wof:population":1671
},
  "geometry": {"coordinates":[88.325039,26.877649],"type":"Point"}
}