{
  "type": "Feature",
  "properties": {
    "iso:country":"IN",
    "ks:ks_alt_nam":"NAWAB KOLHI DEEH",
    "ks:ks_name":"Nawab Kolhi Deeh",
    "ks:ks_pop":245,
    "ks:ks_type":"HABITATION",
    "name:eng_x_preferred":[
        "Nawab Kolhi Deeh"
    ],
    "wof:name":"Nawab Kolhi Deeh",
    "wof:placetype":"locality",
    "wof:population":245
},
  "geometry": {"coordinates":[82.230039,27.653215],"type":"Point"}
}