{
  "type": "Feature",
  "properties": {
    "iso:country":"IN",
    "ks:ks_alt_nam":"Bavi osmanabad",
    "ks:ks_name":"Bavi Osmanabad",
    "ks:ks_pop":832,
    "ks:ks_type":"HABITATION",
    "name:eng_x_preferred":[
        "Bavi Osmanabad"
    ],
    "wof:name":"Bavi Osmanabad",
    "wof:placetype":"locality",
    "wof:population":832
},
  "geometry": {"coordinates":[76.117225,18.375205],"type":"Point"}
}