{
  "type": "Feature",
  "properties": {
    "iso:country":"IN",
    "ks:ks_name":"Jamuguri",
    "ks:ks_pop":526,
    "ks:ks_type":"VILLAGE",
    "ks:ks_uagg_main":0,
    "name:eng_x_preferred":[
        "Jamuguri"
    ],
    "wof:name":"Jamuguri",
    "wof:placetype":"neighbourhood",
    "wof:population":526
},
  "geometry": {"coordinates":[94.60489800000001,27.533753],"type":"Point"}
}