{
  "type": "Feature",
  "properties": {
    "iso:country":"IN",
    "ks:ks_name":"Jogipura",
    "ks:ks_pop":175,
    "ks:ks_type":"HABITATION",
    "name:eng_x_preferred":[
        "Jogipura"
    ],
    "wof:name":"Jogipura",
    "wof:placetype":"locality",
    "wof:population":175
},
  "geometry": {"coordinates":[76.672102,24.010592],"type":"Point"}
}