{
  "type": "Feature",
  "properties": {
    "iso:country":"IN",
    "ks:ks_name":"Khonjiguda",
    "ks:ks_pop":60,
    "ks:ks_type":"VILLAGE",
    "name:eng_x_preferred":[
        "Khonjiguda"
    ],
    "wof:name":"Khonjiguda",
    "wof:placetype":"locality",
    "wof:population":60
},
  "geometry": {"coordinates":[82.28269899999999,19.0395],"type":"Point"}
}