{
  "type": "Feature",
  "properties": {
    "iso:country":"IN",
    "ks:ks_name":"Unhari Kheda Mal",
    "ks:ks_pop":299,
    "ks:ks_type":"VILLAGE",
    "name:eng_x_preferred":[
        "Unhari Kheda Mal"
    ],
    "wof:name":"Unhari Kheda Mal",
    "wof:placetype":"locality",
    "wof:population":299
},
  "geometry": {"coordinates":[79.292311,23.466942],"type":"Point"}
}