{
  "type": "Feature",
  "properties": {
    "gn:admin1_code":"21",
    "gn:admin2_code":"371.0",
    "gn:asciiname":"Jogidhipa",
    "gn:country_code":"IN",
    "gn:dem":230,
    "gn:feature_class":"P",
    "gn:feature_code":"PPL",
    "gn:name":"Jogidh\u012bpa",
    "gn:population":0,
    "gn:timezone":"Asia/Kolkata",
    "iso:country":"IN",
    "ks:ks_alt_nam":"Jogidh\u012bpa",
    "ks:ks_name":"Jogidhipa",
    "ks:ks_pop":128,
    "ks:ks_type":"VILLAGE",
    "name:eng_x_preferred":[
        "Jogidhipa"
    ],
    "name:eng_x_variant":[
        "Jogidh\u012bpa"
    ],
    "wof:name":"Jogidhipa",
    "wof:placetype":"locality",
    "wof:population":128
},
  "geometry": {"coordinates":[83.627723,21.82401],"type":"Point"}
}