{
  "type": "Feature",
  "properties": {
    "iso:country":"IN",
    "ks:ks_name":"Jhikipada",
    "ks:ks_pop":173,
    "ks:ks_type":"HABITATION",
    "name:eng_x_preferred":[
        "Jhikipada"
    ],
    "wof:name":"Jhikipada",
    "wof:placetype":"locality",
    "wof:population":173
},
  "geometry": {"coordinates":[82.94295200000001,19.779448],"type":"Point"}
}