{
  "type": "Feature",
  "properties": {
    "iso:country":"IN",
    "ks:ks_name":"N. Mansingh",
    "ks:ks_pop":510,
    "ks:ks_type":"HABITATION",
    "name:eng_x_preferred":[
        "N. Mansingh"
    ],
    "wof:name":"N. Mansingh",
    "wof:placetype":"locality",
    "wof:population":510
},
  "geometry": {"coordinates":[78.517989,27.149601],"type":"Point"}
}