{
  "type": "Feature",
  "properties": {
    "iso:country":"IN",
    "ks:ks_alt_nam":"Bhagat wasti",
    "ks:ks_name":"Bhagat Wasti",
    "ks:ks_pop":150,
    "ks:ks_type":"HABITATION",
    "name:eng_x_preferred":[
        "Bhagat Wasti"
    ],
    "wof:name":"Bhagat Wasti",
    "wof:placetype":"locality",
    "wof:population":150
},
  "geometry": {"coordinates":[75.875342,18.635624],"type":"Point"}
}