{
  "type": "Feature",
  "properties": {
    "iso:country":"IN",
    "ks:ks_alt_nam":"GORIHIYAHI",
    "ks:ks_name":"Gorihiyahi",
    "ks:ks_pop":536,
    "ks:ks_type":"HABITATION",
    "name:eng_x_preferred":[
        "Gorihiyahi"
    ],
    "wof:name":"Gorihiyahi",
    "wof:placetype":"locality",
    "wof:population":536
},
  "geometry": {"coordinates":[86.631525,26.218938],"type":"Point"}
}