{
  "type": "Feature",
  "properties": {
    "iso:country":"IN",
    "ks:ks_name":"Naranapur",
    "ks:ks_pop":212,
    "ks:ks_type":"VILLAGE",
    "name:eng_x_preferred":[
        "Naranapur"
    ],
    "wof:name":"Naranapur",
    "wof:placetype":"locality",
    "wof:population":212
},
  "geometry": {"coordinates":[86.21474000000001,20.083948],"type":"Point"}
}