{
  "type": "Feature",
  "properties": {
    "iso:country":"IN",
    "ks:ks_alt_nam":"Harijan tola",
    "ks:ks_name":"Harijan Tola",
    "ks:ks_pop":458,
    "ks:ks_type":"HABITATION",
    "name:eng_x_preferred":[
        "Harijan Tola"
    ],
    "wof:name":"Harijan Tola",
    "wof:placetype":"locality",
    "wof:population":458
},
  "geometry": {"coordinates":[87.35465499999999,26.3213],"type":"Point"}
}