{
  "type": "Feature",
  "properties": {
    "iso:country":"IN",
    "ks:ks_name":"Gond Rampur",
    "ks:ks_pop":182,
    "ks:ks_type":"HABITATION",
    "name:eng_x_preferred":[
        "Gond Rampur"
    ],
    "wof:name":"Gond Rampur",
    "wof:placetype":"locality",
    "wof:population":182
},
  "geometry": {"coordinates":[78.40563899999999,19.464919],"type":"Point"}
}