{
  "type": "Feature",
  "properties": {
    "gn:admin1_code":"16.0",
    "gn:admin2_code":"497.0",
    "gn:asciiname":"Khamgaon",
    "gn:country_code":"IN",
    "gn:dem":218,
    "gn:feature_class":"P",
    "gn:feature_code":"PPL",
    "gn:name":"Kh\u0101mgaon",
    "gn:population":0,
    "gn:timezone":"Asia/Kolkata",
    "iso:country":"IN",
    "name:ben_x_preferred":[
        "\u0996\u09be\u09ae\u0997\u09be\u0981\u0993"
    ],
    "name:bpy_x_preferred":[
        "\u0996\u09be\u09ae\u0997\u09be\u0981\u0993"
    ],
    "name:ceb_x_preferred":[
        "Kh\u0101mgaon"
    ],
    "name:deu_x_preferred":[
        "Khamgaon"
    ],
    "name:ita_x_preferred":[
        "Khamgaon"
    ],
    "name:mlg_x_preferred":[
        "Khamgaon"
    ],
    "name:msa_x_preferred":[
        "Khamgaon"
    ],
    "name:new_x_preferred":[
        "\u0916\u092e\u094d\u0917\u093e\u0902\u0935"
    ],
    "name:nld_x_preferred":[
        "Khamgaon"
    ],
    "name:swe_x_preferred":[
        "Khamgaon"
    ],
    "name:urd_x_preferred":[
        "\u062e\u0627\u0645 \u06af\u0627\u0624\u06ba"
    ],
    "name:vie_x_preferred":[
        "Khamgaon"
    ],
    "name:zho_x_preferred":[
        "\u5361\u59c6\u52a0\u5965\u6069"
    ],
    "wof:name":"Khamgaon",
    "wof:placetype":"locality"
},
  "geometry": {"coordinates":[74.19634000000001,21.35364],"type":"Point"}
}