{
  "type": "Feature",
  "properties": {
    "gn:admin1_code":"24",
    "gn:admin2_code":"107.0",
    "gn:asciiname":"Maramda",
    "gn:country_code":"IN",
    "gn:dem":343,
    "gn:feature_class":"P",
    "gn:feature_code":"PPL",
    "gn:name":"Maramd\u0101",
    "gn:population":0,
    "gn:timezone":"Asia/Kolkata",
    "iso:country":"IN",
    "wof:name":"Maramda",
    "wof:placetype":"locality"
},
  "geometry": {"coordinates":[76.89583,26.26811],"type":"Point"}
}