{
  "type": "Feature",
  "properties": {
    "iso:country":"IN",
    "ks:ks_name":"Bellene",
    "ks:ks_pop":109,
    "ks:ks_type":"HABITATION",
    "name:eng_x_preferred":[
        "Bellene"
    ],
    "wof:name":"Bellene",
    "wof:placetype":"locality",
    "wof:population":109
},
  "geometry": {"coordinates":[74.905705,14.184101],"type":"Point"}
}