{
  "type": "Feature",
  "properties": {
    "gn:admin1_code":"2.0",
    "gn:admin2_code":"542.0",
    "gn:asciiname":"Chintadipapadupeta",
    "gn:country_code":"IN",
    "gn:dem":19,
    "gn:feature_class":"P",
    "gn:feature_code":"PPL",
    "gn:name":"Chint\u0101dip\u0101padupeta",
    "gn:population":0,
    "gn:timezone":"Asia/Kolkata",
    "iso:country":"IN",
    "wof:name":"Chintadipapadupeta",
    "wof:placetype":"locality"
},
  "geometry": {"coordinates":[83.98706999999997,18.40987],"type":"Point"}
}