{
  "type": "Feature",
  "properties": {
    "gn:admin1_code":"28.0",
    "gn:admin2_code":"338",
    "gn:asciiname":"Champadanga",
    "gn:country_code":"IN",
    "gn:dem":19,
    "gn:feature_class":"P",
    "gn:feature_code":"PPL",
    "gn:name":"Champ\u0101d\u0101nga",
    "gn:population":0,
    "gn:timezone":"Asia/Kolkata",
    "iso:country":"IN",
    "name:und_x_variant":[
        "Champ\u0101d\u0101nga"
    ],
    "wof:name":"Champadanga",
    "wof:placetype":"locality"
},
  "geometry": {"coordinates":[87.97575000000001,22.83771],"type":"Point"}
}