{
  "type": "Feature",
  "properties": {
    "gn:admin1_code":"40",
    "gn:admin2_code":"539.0",
    "gn:asciiname":"Korlapahad",
    "gn:country_code":"IN",
    "gn:dem":198,
    "gn:feature_class":"P",
    "gn:feature_code":"PPL",
    "gn:name":"Korlapah\u0101d",
    "gn:population":0,
    "gn:timezone":"Asia/Kolkata",
    "iso:country":"IN",
    "wof:name":"Korlapahad",
    "wof:placetype":"locality"
},
  "geometry": {"coordinates":[79.48629,17.16232999999999],"type":"Point"}
}