{
  "type": "Feature",
  "properties": {
    "iso:country":"IN",
    "ks:ks_alt_nam":"valliyakoli",
    "ks:ks_name":"Valliyakoli",
    "ks:ks_pop":280,
    "ks:ks_type":"HABITATION",
    "name:eng_x_preferred":[
        "Valliyakoli"
    ],
    "wof:name":"Valliyakoli",
    "wof:placetype":"locality",
    "wof:population":280
},
  "geometry": {"coordinates":[75.825322,11.628578],"type":"Point"}
}