{
  "type": "Feature",
  "properties": {
    "gn:admin1_code":"24.0",
    "gn:admin2_code":"123.0",
    "gn:asciiname":"Makra",
    "gn:country_code":"IN",
    "gn:dem":607,
    "gn:feature_class":"P",
    "gn:feature_code":"PPL",
    "gn:name":"M\u0101kra",
    "gn:population":0,
    "gn:timezone":"Asia/Kolkata",
    "iso:country":"IN",
    "name:ceb_x_preferred":[
        "Makra"
    ],
    "name:deu_x_preferred":[
        "Makra"
    ],
    "name:fra_x_preferred":[
        "Makra"
    ],
    "name:swe_x_preferred":[
        "Makra"
    ],
    "wof:name":"Makra",
    "wof:placetype":"locality"
},
  "geometry": {"coordinates":[74.00265999999998,25.33535],"type":"Point"}
}