{
  "type": "Feature",
  "properties": {
    "iso:country":"IN",
    "ks:ks_name":"Kesarpur",
    "ks:ks_pop":2,
    "ks:ks_type":"VILLAGE",
    "name:eng_x_preferred":[
        "Kesarpur"
    ],
    "wof:name":"Kesarpur",
    "wof:placetype":"locality",
    "wof:population":2
},
  "geometry": {"coordinates":[86.318063,20.040408],"type":"Point"}
}