{
  "type": "Feature",
  "properties": {
    "iso:country":"IN",
    "ks:ks_name":"Madhu Patti",
    "ks:ks_pop":505,
    "ks:ks_type":"VILLAGE",
    "ks:ks_uagg_main":0,
    "name:eng_x_preferred":[
        "Madhu Patti"
    ],
    "wof:name":"Madhu Patti",
    "wof:placetype":"locality",
    "wof:population":505
},
  "geometry": {"coordinates":[85.938563,26.044595],"type":"Point"}
}