{
  "type": "Feature",
  "properties": {
    "iso:country":"IN",
    "ks:ks_name":"Ettadipaarai",
    "ks:ks_pop":26,
    "ks:ks_type":"HABITATION",
    "name:eng_x_preferred":[
        "Ettadipaarai"
    ],
    "wof:name":"Ettadipaarai",
    "wof:placetype":"locality",
    "wof:population":26
},
  "geometry": {"coordinates":[78.41664299999999,11.30311],"type":"Point"}
}