{
  "type": "Feature",
  "properties": {
    "iso:country":"IN",
    "ks:ks_name":"Sadankhedi",
    "ks:ks_pop":440,
    "ks:ks_type":"HABITATION",
    "name:eng_x_preferred":[
        "Sadankhedi"
    ],
    "wof:name":"Sadankhedi",
    "wof:placetype":"locality",
    "wof:population":440
},
  "geometry": {"coordinates":[76.589597,23.587346],"type":"Point"}
}