{
  "type": "Feature",
  "properties": {
    "iso:country":"IN",
    "ks:ks_alt_nam":"Tadirayi at Makkuva",
    "ks:ks_name":"Tadirayi At Makkuva",
    "ks:ks_pop":80,
    "ks:ks_type":"HABITATION",
    "name:eng_x_preferred":[
        "Tadirayi At Makkuva"
    ],
    "wof:name":"Tadirayi At Makkuva",
    "wof:placetype":"locality",
    "wof:population":80
},
  "geometry": {"coordinates":[83.16684100000001,18.374159],"type":"Point"}
}