{
  "type": "Feature",
  "properties": {
    "iso:country":"IN",
    "ks:ks_name":"Jharnidih",
    "ks:ks_pop":128,
    "ks:ks_type":"VILLAGE",
    "name:eng_x_preferred":[
        "Jharnidih"
    ],
    "wof:name":"Jharnidih",
    "wof:placetype":"locality",
    "wof:population":128
},
  "geometry": {"coordinates":[82.71516800000001,21.580812],"type":"Point"}
}