{
  "type": "Feature",
  "properties": {
    "iso:country":"IN",
    "ks:ks_name":"Abadalapur",
    "ks:ks_pop":299,
    "ks:ks_type":"VILLAGE",
    "name:eng_x_preferred":[
        "Abadalapur"
    ],
    "wof:name":"Abadalapur",
    "wof:placetype":"locality",
    "wof:population":299
},
  "geometry": {"coordinates":[86.188169,20.111626],"type":"Point"}
}