{
  "type": "Feature",
  "properties": {
    "iso:country":"IN",
    "ks:ks_name":"Madkara",
    "ks:ks_pop":330,
    "ks:ks_type":"VILLAGE",
    "name:eng_x_preferred":[
        "Madkara"
    ],
    "wof:name":"Madkara",
    "wof:placetype":"locality",
    "wof:population":330
},
  "geometry": {"coordinates":[81.458162,19.81338],"type":"Point"}
}