{
  "type": "Feature",
  "properties": {
    "iso:country":"IN",
    "ks:ks_name":"Eguvabhudidaguntapalle",
    "ks:ks_pop":182,
    "ks:ks_type":"HABITATION",
    "name:eng_x_preferred":[
        "Eguvabhudidaguntapalle"
    ],
    "wof:name":"Eguvabhudidaguntapalle",
    "wof:placetype":"locality",
    "wof:population":182
},
  "geometry": {"coordinates":[78.711715,14.138427],"type":"Point"}
}