{
  "type": "Feature",
  "properties": {
    "iso:country":"IN",
    "ks:ks_name":"Mailgar",
    "ks:ks_pop":115,
    "ks:ks_type":"HABITATION",
    "name:eng_x_preferred":[
        "Mailgar"
    ],
    "wof:name":"Mailgar",
    "wof:placetype":"locality",
    "wof:population":115
},
  "geometry": {"coordinates":[77.99521,30.53209],"type":"Point"}
}