{
  "type": "Feature",
  "properties": {
    "iso:country":"IN",
    "ks:ks_alt_nam":"BHARATCHANDRA PARA",
    "ks:ks_name":"Bharatchandra Para",
    "ks:ks_pop":195,
    "ks:ks_type":"HABITATION",
    "ks:ks_uagg_main":0,
    "name:eng_x_preferred":[
        "Bharatchandra Para"
    ],
    "wof:name":"Bharatchandra Para",
    "wof:placetype":"neighbourhood",
    "wof:population":195
},
  "geometry": {"coordinates":[91.41654800000001,23.609475],"type":"Point"}
}