{
  "type": "Feature",
  "properties": {
    "iso:country":"IN",
    "ks:ks_name":"Bhagsar",
    "ks:ks_pop":129,
    "ks:ks_type":"VILLAGE",
    "ks:ks_uagg_main":0,
    "name:eng_x_preferred":[
        "Bhagsar"
    ],
    "wof:name":"Bhagsar",
    "wof:placetype":"neighbourhood",
    "wof:population":129
},
  "geometry": {"coordinates":[73.62822199999999,29.469833],"type":"Point"}
}