{
  "type": "Feature",
  "properties": {
    "iso:country":"IN",
    "ks:ks_name":"Mecode",
    "ks:ks_pop":5009,
    "ks:ks_type":"VILLAGE",
    "name:eng_x_preferred":[
        "Mecode"
    ],
    "wof:name":"Mecode",
    "wof:placetype":"locality",
    "wof:population":5009
},
  "geometry": {"coordinates":[77.288786,8.316561],"type":"Point"}
}