{
  "type": "Feature",
  "properties": {
    "iso:country":"IN",
    "ks:ks_name":"Kattoor",
    "ks:ks_pop":202,
    "ks:ks_type":"HABITATION",
    "name:eng_x_preferred":[
        "Kattoor"
    ],
    "wof:name":"Kattoor",
    "wof:placetype":"locality",
    "wof:population":202
},
  "geometry": {"coordinates":[79.656851,11.579596],"type":"Point"}
}