{
  "type": "Feature",
  "properties": {
    "iso:country":"IN",
    "ks:ks_name":"Brahmakundal",
    "ks:ks_pop":619,
    "ks:ks_type":"VILLAGE",
    "name:eng_x_preferred":[
        "Brahmakundal"
    ],
    "wof:name":"Brahmakundal",
    "wof:placetype":"locality",
    "wof:population":619
},
  "geometry": {"coordinates":[85.77339600000001,20.203432],"type":"Point"}
}