{
  "type": "Feature",
  "properties": {
    "iso:country":"IN",
    "ks:ks_alt_nam":"GULIASAI",
    "ks:ks_name":"Guliasai",
    "ks:ks_pop":238,
    "ks:ks_type":"HABITATION",
    "name:eng_x_preferred":[
        "Guliasai"
    ],
    "wof:name":"Guliasai",
    "wof:placetype":"locality",
    "wof:population":238
},
  "geometry": {"coordinates":[85.88293899999999,22.202803],"type":"Point"}
}