{
  "type": "Feature",
  "properties": {
    "gn:admin1_code":"36",
    "gn:admin2_code":"173.0",
    "gn:asciiname":"Sarmanpur",
    "gn:country_code":"IN",
    "gn:dem":99,
    "gn:feature_class":"P",
    "gn:feature_code":"PPL",
    "gn:name":"Sarm\u0101npur",
    "gn:population":0,
    "gn:timezone":"Asia/Kolkata",
    "iso:country":"IN",
    "wof:name":"Sarmanpur",
    "wof:placetype":"locality"
},
  "geometry": {"coordinates":[82.03744,25.73792000000001],"type":"Point"}
}