{
  "type": "Feature",
  "properties": {
    "gn:admin1_code":"12.0",
    "gn:asciiname":"Kothi",
    "gn:country_code":"IN",
    "gn:dem":760,
    "gn:feature_class":"P",
    "gn:feature_code":"PPL",
    "gn:name":"Kothi",
    "gn:population":0,
    "gn:timezone":"Asia/Kolkata",
    "iso:country":"IN",
    "wof:name":"Kothi",
    "wof:placetype":"locality"
},
  "geometry": {"coordinates":[74.09338000000002,33.20706],"type":"Point"}
}