{
  "type": "Feature",
  "properties": {
    "iso:country":"IN",
    "ks:ks_name":"Gurramadhira",
    "ks:ks_pop":102,
    "ks:ks_type":"HABITATION",
    "name:eng_x_preferred":[
        "Gurramadhira"
    ],
    "wof:name":"Gurramadhira",
    "wof:placetype":"locality",
    "wof:population":102
},
  "geometry": {"coordinates":[78.742864,19.234572],"type":"Point"}
}