{
  "type": "Feature",
  "properties": {
    "iso:country":"IN",
    "ks:ks_name":"Bardih",
    "ks:ks_pop":448,
    "ks:ks_type":"VILLAGE",
    "name:eng_x_preferred":[
        "Bardih"
    ],
    "wof:name":"Bardih",
    "wof:placetype":"locality",
    "wof:population":448
},
  "geometry": {"coordinates":[83.544833,22.259698],"type":"Point"}
}