{
  "type": "Feature",
  "properties": {
    "iso:country":"IN",
    "ks:ks_name":"Gadkot",
    "ks:ks_pop":47,
    "ks:ks_type":"VILLAGE",
    "name:eng_x_preferred":[
        "Gadkot"
    ],
    "wof:name":"Gadkot",
    "wof:placetype":"locality",
    "wof:population":47
},
  "geometry": {"coordinates":[78.37271200000001,29.905685],"type":"Point"}
}