{
  "type": "Feature",
  "properties": {
    "iso:country":"IN",
    "ks:ks_name":"Mandir Falia",
    "ks:ks_pop":958,
    "ks:ks_type":"HABITATION",
    "name:eng_x_preferred":[
        "Mandir Falia"
    ],
    "wof:name":"Mandir Falia",
    "wof:placetype":"locality",
    "wof:population":958
},
  "geometry": {"coordinates":[74.056833,22.690556],"type":"Point"}
}