{
  "type": "Feature",
  "properties": {
    "gn:admin1_code":"28.0",
    "gn:admin2_code":"332.0",
    "gn:asciiname":"Bansdol",
    "gn:country_code":"IN",
    "gn:dem":33,
    "gn:feature_class":"P",
    "gn:feature_code":"PPL",
    "gn:name":"B\u0101nsdol",
    "gn:population":0,
    "gn:timezone":"Asia/Kolkata",
    "iso:country":"IN",
    "ks:ks_alt_nam":"B\u0101nsdol",
    "ks:ks_name":"Bansdol",
    "ks:ks_pop":1933,
    "ks:ks_type":"VILLAGE",
    "ks:ks_uagg_main":0,
    "name:eng_x_preferred":[
        "Bansdol"
    ],
    "name:eng_x_variant":[
        "B\u0101nsdol"
    ],
    "wof:name":"Bansdol",
    "wof:placetype":"neighbourhood",
    "wof:population":1933
},
  "geometry": {"coordinates":[87.916376,25.373998],"type":"Point"}
}