{
  "type": "Feature",
  "properties": {
    "iso:country":"IN",
    "ks:ks_name":"Vadachiwadi",
    "ks:ks_pop":13,
    "ks:ks_type":"HABITATION",
    "name:eng_x_preferred":[
        "Vadachiwadi"
    ],
    "wof:name":"Vadachiwadi",
    "wof:placetype":"locality",
    "wof:population":13
},
  "geometry": {"coordinates":[73.55949200000001,17.676147],"type":"Point"}
}