{
  "type": "Feature",
  "properties": {
    "iso:country":"IN",
    "ks:ks_name":"Asnir",
    "ks:ks_pop":11,
    "ks:ks_type":"HABITATION",
    "name:eng_x_preferred":[
        "Asnir"
    ],
    "wof:name":"Asnir",
    "wof:placetype":"locality",
    "wof:population":11
},
  "geometry": {"coordinates":[74.539368,14.638667],"type":"Point"}
}