{
  "type": "Feature",
  "properties": {
    "iso:country":"IN",
    "ks:ks_name":"Bajyun",
    "ks:ks_pop":405,
    "ks:ks_type":"VILLAGE",
    "name:eng_x_preferred":[
        "Bajyun"
    ],
    "wof:name":"Bajyun",
    "wof:placetype":"locality",
    "wof:population":405
},
  "geometry": {"coordinates":[79.06115200000001,30.337552],"type":"Point"}
}