{
  "type": "Feature",
  "properties": {
    "gn:admin1_code":"19.0",
    "gn:admin2_code":"573.0",
    "gn:asciiname":"Jakkanahalli",
    "gn:country_code":"IN",
    "gn:dem":838,
    "gn:feature_class":"P",
    "gn:feature_code":"PPL",
    "gn:name":"Jakkanahalli",
    "gn:population":0,
    "gn:timezone":"Asia/Kolkata",
    "iso:country":"IN",
    "wof:name":"Jakkanahalli",
    "wof:placetype":"locality"
},
  "geometry": {"coordinates":[76.53913,12.63135],"type":"Point"}
}