{
  "type": "Feature",
  "properties": {
    "iso:country":"IN",
    "ks:ks_name":"Mirja Para",
    "ks:ks_pop":516,
    "ks:ks_type":"HABITATION",
    "name:eng_x_preferred":[
        "Mirja Para"
    ],
    "wof:name":"Mirja Para",
    "wof:placetype":"locality",
    "wof:population":516
},
  "geometry": {"coordinates":[88.24615300000001,22.373918],"type":"Point"}
}