{
  "type": "Feature",
  "properties": {
    "iso:country":"IN",
    "ks:ks_name":"Makha Pur",
    "ks:ks_pop":882,
    "ks:ks_type":"VILLAGE",
    "ks:ks_uagg_main":0,
    "name:eng_x_preferred":[
        "Makha Pur"
    ],
    "wof:name":"Makha Pur",
    "wof:placetype":"locality",
    "wof:population":882
},
  "geometry": {"coordinates":[82.190727,26.774148],"type":"Point"}
}