{
  "type": "Feature",
  "properties": {
    "iso:country":"IN",
    "ks:ks_name":"Kulba",
    "ks:ks_pop":1884,
    "ks:ks_type":"VILLAGE",
    "name:eng_x_preferred":[
        "Kulba"
    ],
    "wof:name":"Kulba",
    "wof:placetype":"locality",
    "wof:population":1884
},
  "geometry": {"coordinates":[84.049468,22.222074],"type":"Point"}
}