{
  "type": "Feature",
  "properties": {
    "gn:admin1_code":"35",
    "gn:admin2_code":"425.0",
    "gn:asciiname":"Rhamrari Ki Rasoiya",
    "gn:country_code":"IN",
    "gn:dem":304,
    "gn:feature_class":"P",
    "gn:feature_code":"PPL",
    "gn:name":"Rhamr\u0101ri Ki Rasoiya",
    "gn:population":0,
    "gn:timezone":"Asia/Kolkata",
    "iso:country":"IN",
    "wof:name":"Rhamrari Ki Rasoiya",
    "wof:placetype":"locality"
},
  "geometry": {"coordinates":[79.5095,24.86376],"type":"Point"}
}