{
  "type": "Feature",
  "properties": {
    "iso:country":"IN",
    "ks:ks_name":"Nagla Sucharam",
    "ks:ks_pop":108,
    "ks:ks_type":"HABITATION",
    "name:eng_x_preferred":[
        "Nagla Sucharam"
    ],
    "wof:name":"Nagla Sucharam",
    "wof:placetype":"locality",
    "wof:population":108
},
  "geometry": {"coordinates":[77.74127,27.659646],"type":"Point"}
}