{
  "type": "Feature",
  "properties": {
    "iso:country":"IN",
    "ks:ks_name":"Basona",
    "ks:ks_pop":459,
    "ks:ks_type":"HABITATION",
    "name:eng_x_preferred":[
        "Basona"
    ],
    "wof:name":"Basona",
    "wof:placetype":"locality",
    "wof:population":459
},
  "geometry": {"coordinates":[77.02386300000001,26.069377],"type":"Point"}
}