{
  "type": "Feature",
  "properties": {
    "iso:country":"IN",
    "ks:ks_alt_nam":"Gol\u0101d\u0101bar",
    "ks:ks_name":"Goladabar",
    "ks:ks_pop":182,
    "ks:ks_type":"VILLAGE",
    "name:eng_x_preferred":[
        "Goladabar"
    ],
    "name:eng_x_variant":[
        "Gol\u0101d\u0101bar"
    ],
    "wof:name":"Goladabar",
    "wof:placetype":"locality",
    "wof:population":182
},
  "geometry": {"coordinates":[86.202911,24.039721],"type":"Point"}
}