{
  "type": "Feature",
  "properties": {
    "iso:country":"IN",
    "ks:ks_name":"Gurutuan",
    "ks:ks_pop":531,
    "ks:ks_type":"HABITATION",
    "name:eng_x_preferred":[
        "Gurutuan"
    ],
    "wof:name":"Gurutuan",
    "wof:placetype":"locality",
    "wof:population":531
},
  "geometry": {"coordinates":[85.455215,21.92008],"type":"Point"}
}