{
  "type": "Feature",
  "properties": {
    "iso:country":"IN",
    "ks:ks_name":"Madhab",
    "ks:ks_pop":540,
    "ks:ks_type":"HABITATION",
    "ks:ks_uagg_main":0,
    "name:eng_x_preferred":[
        "Madhab"
    ],
    "wof:name":"Madhab",
    "wof:placetype":"neighbourhood",
    "wof:population":540
},
  "geometry": {"coordinates":[92.937518,26.736233],"type":"Point"}
}