{
  "type": "Feature",
  "properties": {
    "iso:country":"IN",
    "ks:ks_name":"Shinde Wasti",
    "ks:ks_pop":450,
    "ks:ks_type":"HABITATION",
    "name:eng_x_preferred":[
        "Shinde Wasti"
    ],
    "wof:name":"Shinde Wasti",
    "wof:placetype":"locality",
    "wof:population":450
},
  "geometry": {"coordinates":[74.23403500000001,18.768118],"type":"Point"}
}