{
  "type": "Feature",
  "properties": {
    "iso:country":"IN",
    "ks:ks_name":"Narasimhadevarabetta",
    "ks:ks_pop":137,
    "ks:ks_type":"HABITATION",
    "name:eng_x_preferred":[
        "Narasimhadevarabetta"
    ],
    "wof:name":"Narasimhadevarabetta",
    "wof:placetype":"locality",
    "wof:population":137
},
  "geometry": {"coordinates":[77.70262,13.479778],"type":"Point"}
}