{
  "type": "Feature",
  "properties": {
    "iso:country":"IN",
    "ks:ks_name":"Dalhagoda",
    "ks:ks_pop":374,
    "ks:ks_type":"VILLAGE",
    "ks:ks_uagg_main":0,
    "name:eng_x_preferred":[
        "Dalhagoda"
    ],
    "wof:name":"Dalhagoda",
    "wof:placetype":"neighbourhood",
    "wof:population":374
},
  "geometry": {"coordinates":[83.83529299999999,22.599673],"type":"Point"}
}