{
  "type": "Feature",
  "properties": {
    "gn:admin1_code":"13",
    "gn:admin2_code":"601.0",
    "gn:asciiname":"Vellanad",
    "gn:country_code":"IN",
    "gn:dem":66,
    "gn:feature_class":"P",
    "gn:feature_code":"PPL",
    "gn:name":"Vellan\u0101d",
    "gn:population":0,
    "gn:timezone":"Asia/Kolkata",
    "iso:country":"IN",
    "name:ceb_x_preferred":[
        "Vellan\u0101d"
    ],
    "name:fas_x_preferred":[
        "\u0648\u0644\u0646\u062f"
    ],
    "name:mal_x_preferred":[
        "\u0d35\u0d46\u0d33\u0d4d\u0d33\u0d28\u0d3e\u0d1f\u0d4d \u0d17\u0d4d\u0d30\u0d3e\u0d2e\u0d2a\u0d1e\u0d4d\u0d1a\u0d3e\u0d2f\u0d24\u0d4d\u0d24\u0d4d"
    ],
    "name:swe_x_preferred":[
        "Vellan\u0101d"
    ],
    "wof:name":"Vellanad",
    "wof:placetype":"locality"
},
  "geometry": {"coordinates":[77.05033,8.55979],"type":"Point"}
}