{
  "type": "Feature",
  "properties": {
    "gn:admin1_code":"13",
    "gn:admin2_code":"601.0",
    "gn:asciiname":"Vellanad",
    "gn:country_code":"IN",
    "gn:dem":66,
    "gn:feature_class":"P",
    "gn:feature_code":"PPL",
    "gn:name":"Vellan\u0101d",
    "gn:population":0,
    "gn:timezone":"Asia/Kolkata",
    "iso:country":"IN",
    "name:und_x_variant":[
        "Vellan\u0101d"
    ],
    "wof:name":"Vellanad",
    "wof:placetype":"locality"
},
  "geometry": {"coordinates":[77.05033,8.55979],"type":"Point"}
}