{
  "type": "Feature",
  "properties": {
    "iso:country":"IN",
    "ks:ks_name":"Hinjala",
    "ks:ks_pop":60,
    "ks:ks_type":"VILLAGE",
    "name:eng_x_preferred":[
        "Hinjala"
    ],
    "wof:name":"Hinjala",
    "wof:placetype":"locality",
    "wof:population":60
},
  "geometry": {"coordinates":[86.079718,20.62291],"type":"Point"}
}