{
  "type": "Feature",
  "properties": {
    "gn:admin1_code":"21.0",
    "gn:admin2_code":"396.0",
    "gn:asciiname":"Bechhudi",
    "gn:country_code":"IN",
    "gn:dem":382,
    "gn:feature_class":"P",
    "gn:feature_code":"PPL",
    "gn:name":"Bechhudi",
    "gn:population":0,
    "gn:timezone":"Asia/Kolkata",
    "iso:country":"IN",
    "ks:ks_name":"Bechadi",
    "ks:ks_pop":57,
    "ks:ks_type":"VILLAGE",
    "name:eng_x_preferred":[
        "Bechadi"
    ],
    "name:eng_x_variant":[
        "Bechhudi"
    ],
    "wof:name":"Bechadi",
    "wof:placetype":"locality",
    "wof:population":57
},
  "geometry": {"coordinates":[83.69022,19.317145],"type":"Point"}
}