{
  "type": "Feature",
  "properties": {
    "iso:country":"IN",
    "ks:ks_name":"Binjhagiri",
    "ks:ks_pop":28,
    "ks:ks_type":"VILLAGE",
    "name:eng_x_preferred":[
        "Binjhagiri"
    ],
    "wof:name":"Binjhagiri",
    "wof:placetype":"locality",
    "wof:population":28
},
  "geometry": {"coordinates":[84.584277,19.683466],"type":"Point"}
}