{
  "type": "Feature",
  "properties": {
    "iso:country":"IN",
    "ks:ks_name":"Dhamoi",
    "ks:ks_pop":794,
    "ks:ks_type":"VILLAGE",
    "name:eng_x_preferred":[
        "Dhamoi"
    ],
    "wof:name":"Dhamoi",
    "wof:placetype":"locality",
    "wof:population":794
},
  "geometry": {"coordinates":[74.729495,22.623813],"type":"Point"}
}