{
  "type": "Feature",
  "properties": {
    "iso:country":"IN",
    "ks:ks_name":"Banjgadu",
    "ks:ks_pop":139,
    "ks:ks_type":"VILLAGE",
    "name:eng_x_preferred":[
        "Banjgadu"
    ],
    "wof:name":"Banjgadu",
    "wof:placetype":"locality",
    "wof:population":139
},
  "geometry": {"coordinates":[79.086271,30.402296],"type":"Point"}
}