{
  "type": "Feature",
  "properties": {
    "iso:country":"IN",
    "ks:ks_name":"Kotgari",
    "ks:ks_pop":29,
    "ks:ks_type":"VILLAGE",
    "name:eng_x_preferred":[
        "Kotgari"
    ],
    "wof:name":"Kotgari",
    "wof:placetype":"locality",
    "wof:population":29
},
  "geometry": {"coordinates":[78.348884,30.620528],"type":"Point"}
}