{
  "type": "Feature",
  "properties": {
    "iso:country":"IN",
    "ks:ks_alt_nam":"Sathrukunta thanda",
    "ks:ks_name":"Sathrukunta Thanda",
    "ks:ks_pop":101,
    "ks:ks_type":"HABITATION",
    "name:eng_x_preferred":[
        "Sathrukunta Thanda"
    ],
    "wof:name":"Sathrukunta Thanda",
    "wof:placetype":"locality",
    "wof:population":101
},
  "geometry": {"coordinates":[77.709889,17.110482],"type":"Point"}
}