{
  "type": "Feature",
  "properties": {
    "iso:country":"IN",
    "ks:ks_name":"Kulapathar",
    "ks:ks_pop":360,
    "ks:ks_type":"VILLAGE",
    "name:eng_x_preferred":[
        "Kulapathar"
    ],
    "wof:name":"Kulapathar",
    "wof:placetype":"locality",
    "wof:population":360
},
  "geometry": {"coordinates":[86.435671,22.276128],"type":"Point"}
}