{
  "type": "Feature",
  "properties": {
    "iso:country":"IN",
    "ks:ks_name":"Kusumdaha",
    "ks:ks_pop":485,
    "ks:ks_type":"VILLAGE",
    "name:eng_x_preferred":[
        "Kusumdaha"
    ],
    "wof:name":"Kusumdaha",
    "wof:placetype":"locality",
    "wof:population":485
},
  "geometry": {"coordinates":[86.946494,23.925393],"type":"Point"}
}