{
  "type": "Feature",
  "properties": {
    "iso:country":"IN",
    "ks:ks_name":"Alupara",
    "ks:ks_pop":96,
    "ks:ks_type":"HABITATION",
    "name:eng_x_preferred":[
        "Alupara"
    ],
    "wof:name":"Alupara",
    "wof:placetype":"locality",
    "wof:population":96
},
  "geometry": {"coordinates":[81.416633,18.512279],"type":"Point"}
}