{
  "type": "Feature",
  "properties": {
    "iso:country":"IN",
    "ks:ks_alt_nam":"L\u0101lpur",
    "ks:ks_name":"Lalpur",
    "ks:ks_pop":64,
    "ks:ks_type":"VILLAGE",
    "name:eng_x_preferred":[
        "Lalpur"
    ],
    "name:eng_x_variant":[
        "L\u0101lpur"
    ],
    "wof:name":"Lalpur",
    "wof:placetype":"locality",
    "wof:population":64
},
  "geometry": {"coordinates":[86.117135,24.648138],"type":"Point"}
}