{
  "type": "Feature",
  "properties": {
    "gn:admin1_code":"13.0",
    "gn:admin2_code":"600.0",
    "gn:asciiname":"Perumtottattu Kilakkekara",
    "gn:country_code":"IN",
    "gn:dem":21,
    "gn:feature_class":"P",
    "gn:feature_code":"PPL",
    "gn:name":"Perumtottattu Kilakkekara",
    "gn:population":0,
    "gn:timezone":"Asia/Kolkata",
    "iso:country":"IN",
    "wof:name":"Perumtottattu Kilakkekara",
    "wof:placetype":"locality"
},
  "geometry": {"coordinates":[76.57481,8.99179],"type":"Point"}
}