{
  "type": "Feature",
  "properties": {
    "iso:country":"IN",
    "ks:ks_name":"Malkapur",
    "ks:ks_type":"VILLAGE",
    "name:eng_x_preferred":[
        "Malkapur"
    ],
    "name:hin_x_preferred":[
        "\u092e\u0932\u094d\u0915\u093e\u092a\u0941\u0930"
    ],
    "name:mar_x_preferred":[
        "\u092e\u0932\u0915\u093e\u092a\u0942\u0930"
    ],
    "wof:name":"Malkapur",
    "wof:placetype":"locality"
},
  "geometry": {"coordinates":[77.786816,18.777765],"type":"Point"}
}