{
  "type": "Feature",
  "properties": {
    "iso:country":"IN",
    "ks:ks_name":"Malkapur",
    "ks:ks_type":"VILLAGE",
    "name:eng_x_preferred":[
        "Malkapur"
    ],
    "wof:name":"Malkapur",
    "wof:placetype":"locality"
},
  "geometry": {"coordinates":[77.786816,18.777765],"type":"Point"}
}