{
  "type": "Feature",
  "properties": {
    "iso:country":"IN",
    "ks:ks_alt_nam":"Ashtamudi boat jetty",
    "ks:ks_name":"Ashtamudi Boat Jetty",
    "ks:ks_pop":1097,
    "ks:ks_type":"HABITATION",
    "name:eng_x_preferred":[
        "Ashtamudi Boat Jetty"
    ],
    "wof:name":"Ashtamudi Boat Jetty",
    "wof:placetype":"locality",
    "wof:population":1097
},
  "geometry": {"coordinates":[76.597454,8.959125],"type":"Point"}
}