{
  "type": "Feature",
  "properties": {
    "gn:admin1_code":"35",
    "gn:admin2_code":"452.0",
    "gn:asciiname":"Hadikat",
    "gn:country_code":"IN",
    "gn:dem":483,
    "gn:feature_class":"P",
    "gn:feature_code":"PPL",
    "gn:name":"H\u0101d\u012bk\u0101t",
    "gn:population":0,
    "gn:timezone":"Asia/Kolkata",
    "iso:country":"IN",
    "ks:ks_alt_nam":"H\u0101d\u012bk\u0101t",
    "ks:ks_name":"Hadikat",
    "ks:ks_pop":291,
    "ks:ks_type":"VILLAGE",
    "name:eng_x_preferred":[
        "Hadikat"
    ],
    "name:eng_x_variant":[
        "H\u0101d\u012bk\u0101t"
    ],
    "wof:name":"Hadikat",
    "wof:placetype":"locality",
    "wof:population":291
},
  "geometry": {"coordinates":[79.215316,23.216054],"type":"Point"}
}