{
  "type": "Feature",
  "properties": {
    "gn:admin1_code":"12.0",
    "gn:admin2_code":"19.0",
    "gn:asciiname":"Jangal Gali",
    "gn:country_code":"IN",
    "gn:dem":1282,
    "gn:feature_class":"P",
    "gn:feature_code":"PPL",
    "gn:name":"Jangal Gal\u012b",
    "gn:population":0,
    "gn:timezone":"Asia/Kolkata",
    "iso:country":"IN",
    "wof:name":"Jangal Gali",
    "wof:placetype":"locality"
},
  "geometry": {"coordinates":[75.04648,33.00592],"type":"Point"}
}