{
  "type": "Feature",
  "properties": {
    "gn:admin1_code":"19.0",
    "gn:admin2_code":"581.0",
    "gn:asciiname":"Natta",
    "gn:country_code":"IN",
    "gn:dem":790,
    "gn:feature_class":"P",
    "gn:feature_code":"PPL",
    "gn:name":"Natta",
    "gn:population":0,
    "gn:timezone":"Asia/Kolkata",
    "iso:country":"IN",
    "name:ceb_x_preferred":[
        "Natta"
    ],
    "name:fra_x_preferred":[
        "Natta"
    ],
    "name:ita_x_preferred":[
        "Natta"
    ],
    "name:nld_x_preferred":[
        "Natta"
    ],
    "name:ron_x_preferred":[
        "Natta"
    ],
    "name:swe_x_preferred":[
        "Natta"
    ],
    "name:vie_x_preferred":[
        "Natta"
    ],
    "name:war_x_preferred":[
        "Natta"
    ],
    "wof:name":"Natta",
    "wof:placetype":"locality"
},
  "geometry": {"coordinates":[78.31492,13.04635],"type":"Point"}
}