{
  "type": "Feature",
  "properties": {
    "gn:country":"IN",
    "gn:fcode":"PPL",
    "gn:population":17260,
    "iso:country":"IN",
    "name:ara_x_preferred":[
        "\u0625\u0628\u0631\u0627\u0647\u064a\u0645 \u0628\u0648\u0631"
    ],
    "name:ben_bn_x_preferred":[
        "\u0987\u09ac\u09cd\u09b0\u09be\u09b9\u09bf\u09ae\u09aa\u09c1\u09b0"
    ],
    "name:ben_in_x_preferred":[
        "\u0987\u09ac\u09cd\u09b0\u09be\u09b9\u09bf\u09ae\u09aa\u09c1\u09b0"
    ],
    "name:ben_x_preferred":[
        "\u09b0\u09be\u09b9\u09bf\u09ae\u09a4\u09aa\u09c1\u09b0"
    ],
    "name:bpy_x_preferred":[
        "\u09b0\u09be\u09b9\u09bf\u09ae\u09a4\u09aa\u09c1\u09b0"
    ],
    "name:bul_x_preferred":[
        "\u0420\u0430\u0445\u0438\u043c\u0430\u0442\u043f\u0443\u0440"
    ],
    "name:ceb_x_preferred":[
        "Rahimatpur"
    ],
    "name:eng_x_preferred":[
        "Rahimatpur"
    ],
    "name:fra_x_preferred":[
        "Rahimatpur"
    ],
    "name:guj_x_preferred":[
        "\u0a87\u0aac\u0acd\u0ab0\u0abe\u0ab9\u0ac0\u0aae\u0aaa\u0ac1\u0ab0"
    ],
    "name:hin_x_preferred":[
        "\u0907\u092c\u094d\u0930\u093e\u0939\u093f\u092e\u092a\u0941\u0930"
    ],
    "name:ita_x_preferred":[
        "Rahimatpur"
    ],
    "name:kan_x_preferred":[
        "\u0c87\u0cac\u0ccd\u0cb0\u0cbe\u0cb9\u0cbf\u0cae\u0ccd"
    ],
    "name:mal_x_preferred":[
        "\u0d07\u0d2c\u0d4d\u0d30\u0d3e\u0d39\u0d3f\u0d02\u0d2a\u0d42\u0d7c"
    ],
    "name:mar_x_preferred":[
        "\u0907\u092c\u094d\u0930\u093e\u0939\u093f\u092e\u092a\u0942\u0930"
    ],
    "name:mar_x_variant":[
        "\u0930\u0939\u093f\u092e\u0924\u092a\u0942\u0930"
    ],
    "name:msa_x_preferred":[
        "Rahimatpur"
    ],
    "name:nan_x_preferred":[
        "Rahimatpur"
    ],
    "name:nld_x_preferred":[
        "Rahimatpur"
    ],
    "name:pan_x_preferred":[
        "\u0a07\u0a2c\u0a30\u0a3e\u0a39\u0a3f\u0a2e\u0a2a\u0a41\u0a30"
    ],
    "name:por_x_preferred":[
        "Rahimatpur"
    ],
    "name:swe_x_preferred":[
        "Rahimatpur"
    ],
    "name:tam_x_preferred":[
        "\u0b87\u0baa\u0bcd\u0bb0\u0bbe\u0bb9\u0bbf\u0bae\u0bcd\u0baa\u0bc2\u0bb0\u0bcd"
    ],
    "name:tel_x_preferred":[
        "\u0c07\u0c2c\u0c4d\u0c30\u0c39\u0c3f\u0c02\u0c2a\u0c42\u0c30\u0c4d"
    ],
    "name:und_x_variant":[
        "Rahunatpur"
    ],
    "name:urd_x_preferred":[
        "\u0627\u0628\u0631\u0627\u06c1\u06cc\u0645 \u067e\u0648\u0631"
    ],
    "name:urd_x_variant":[
        "\u0631\u062d\u0645\u062a \u067e\u0648\u0631"
    ],
    "name:vie_x_preferred":[
        "Rahimatpur"
    ],
    "name:zho_x_preferred":[
        "\u62c9\u5e0c\u9a6c\u7279\u666e\u5c14"
    ],
    "qs:name":"Ibrahimpur",
    "qs:name_adm0":"India",
    "qs:name_adm1":"Maharashtra",
    "qs:photos_9r":0,
    "qs:photos_sr":0,
    "qs:placetype":"Town",
    "qs:pop_sr":"6",
    "wd:wordcount":90,
    "wof:name":"Ibrahimpur",
    "wof:placetype":"locality",
    "wof:population":17260
},
  "geometry": {"coordinates":[74.19965999999999,17.5921],"type":"Point"}
}