{
  "type": "Feature",
  "properties": {
    "gn:country":"IN",
    "gn:fcode":"PPL",
    "gn:pop":17260,
    "iso:country":"IN",
    "name:ben_x_preferred":[
        "\u09b0\u09be\u09b9\u09bf\u09ae\u09a4\u09aa\u09c1\u09b0"
    ],
    "name:bpy_x_preferred":[
        "\u09b0\u09be\u09b9\u09bf\u09ae\u09a4\u09aa\u09c1\u09b0"
    ],
    "name:bul_x_preferred":[
        "\u0420\u0430\u0445\u0438\u043c\u0430\u0442\u043f\u0443\u0440"
    ],
    "name:ceb_x_preferred":[
        "Rahimatpur"
    ],
    "name:eng_x_preferred":[
        "Rahimatpur"
    ],
    "name:fra_x_preferred":[
        "Rahimatpur"
    ],
    "name:ita_x_preferred":[
        "Rahimatpur"
    ],
    "name:mar_x_preferred":[
        "\u0930\u0939\u093f\u092e\u0924\u092a\u0942\u0930"
    ],
    "name:msa_x_preferred":[
        "Rahimatpur"
    ],
    "name:nan_x_preferred":[
        "Rahimatpur"
    ],
    "name:nld_x_preferred":[
        "Rahimatpur"
    ],
    "name:por_x_preferred":[
        "Rahimatpur"
    ],
    "name:swe_x_preferred":[
        "Rahimatpur"
    ],
    "name:unk_x_variant":[
        "Rahunatpur"
    ],
    "name:urd_x_preferred":[
        "\u0631\u062d\u0645\u062a \u067e\u0648\u0631"
    ],
    "name:vie_x_preferred":[
        "Rahimatpur"
    ],
    "name:zho_x_preferred":[
        "\u62c9\u5e0c\u9a6c\u7279\u666e\u5c14"
    ],
    "qs:name":"Ibrahimpur",
    "qs:name_adm0":"India",
    "qs:name_adm1":"Maharashtra",
    "qs:photos_9r":0,
    "qs:photos_sr":0,
    "qs:placetype":"Town",
    "qs:pop_sr":"6",
    "wd:wordcount":90,
    "wof:name":"Ibrahimpur",
    "wof:placetype":"locality",
    "wof:population":17260
},
  "geometry": {"coordinates":[74.19965999999999,17.5921],"type":"Point"}
}