{
  "type": "Feature",
  "properties": {
    "iso:country":"IN",
    "ks:ks_alt_nam":"MAHRANIYA",
    "ks:ks_name":"Mahraniya",
    "ks:ks_pop":563,
    "ks:ks_type":"HABITATION",
    "ks:ks_uagg_main":0,
    "name:eng_x_preferred":[
        "Mahraniya"
    ],
    "wof:name":"Mahraniya",
    "wof:placetype":"neighbourhood",
    "wof:population":563
},
  "geometry": {"coordinates":[81.4136,26.2566],"type":"Point"}
}