{
  "type": "Feature",
  "properties": {
    "iso:country":"IN",
    "ks:ks_name":"Binjhe",
    "ks:ks_pop":1202,
    "ks:ks_type":"VILLAGE",
    "name:eng_x_preferred":[
        "Binjhe"
    ],
    "wof:name":"Binjhe",
    "wof:placetype":"locality",
    "wof:population":1202
},
  "geometry": {"coordinates":[81.38247699999999,19.970221],"type":"Point"}
}