{
  "type": "Feature",
  "properties": {
    "gn:admin1_code":"36.0",
    "gn:admin2_code":"175.0",
    "gn:asciiname":"Bhadeora",
    "gn:country_code":"IN",
    "gn:dem":101,
    "gn:feature_class":"P",
    "gn:feature_code":"PPL",
    "gn:name":"Bhadeora",
    "gn:population":0,
    "gn:timezone":"Asia/Kolkata",
    "iso:country":"IN",
    "name:hin_x_preferred":[
        "\u092d\u0926\u0947\u0935\u0930\u093e"
    ],
    "wof:name":"Bhadeora",
    "wof:placetype":"neighbourhood"
},
  "geometry": {"coordinates":[81.93971000000001,25.55757],"type":"Point"}
}