{
  "type": "Feature",
  "properties": {
    "iso:country":"IN",
    "ks:ks_name":"Ramnathpur",
    "ks:ks_pop":544,
    "ks:ks_type":"HABITATION",
    "ks:ks_uagg_main":0,
    "name:eng_x_preferred":[
        "Ramnathpur"
    ],
    "wof:name":"Ramnathpur",
    "wof:placetype":"neighbourhood",
    "wof:population":544
},
  "geometry": {"coordinates":[87.982522,23.08963],"type":"Point"}
}