{
  "type": "Feature",
  "properties": {
    "iso:country":"IN",
    "name:ara_x_preferred":[
        "\u0643\u0648\u064a\u0644\u0645\u0628\u0627\u0643\u0645"
    ],
    "name:ben_bn_x_preferred":[
        "\u0995\u09c8\u09b2\u09be\u09ae\u09ac\u09be\u0995\u09cd\u0995\u09be\u09ae"
    ],
    "name:ben_in_x_preferred":[
        "\u0995\u09c8\u09b2\u09be\u09ae\u09ac\u09be\u0995\u09cd\u0995\u09be\u09ae"
    ],
    "name:eng_x_preferred":[
        "Kovilambakkam"
    ],
    "name:guj_x_preferred":[
        "\u0a95\u0acb\u0a87\u0ab2\u0abe\u0aae\u0acd\u0aac\u0a95\u0acd\u0a95\u0aae"
    ],
    "name:hin_x_preferred":[
        "\u0915\u094b\u0907\u0932\u092e\u094d\u092c\u0915\u094d\u0915\u092e"
    ],
    "name:kan_x_preferred":[
        "\u0c95\u0cca\u0caf\u0ccd\u0cb2\u0c82\u0cac\u0cbe\u0c95\u0cae\u0ccd"
    ],
    "name:mal_x_preferred":[
        "\u0d15\u0d4a\u0d2f\u0d3f\u0d32\u0d2e\u0d4d\u0d2a\u0d3e\u0d15\u0d4d\u0d15\u0d02"
    ],
    "name:mar_x_preferred":[
        "\u0915\u094b\u0908\u0932\u0902\u092c\u0915\u094d\u0915\u092e"
    ],
    "name:pan_x_preferred":[
        "\u0a15\u0a4b\u0a07\u0a32\u0a2e\u0a2c\u0a71\u0a15\u0a2e"
    ],
    "name:tam_x_preferred":[
        "\u0b95\u0bcb\u0baf\u0bbf\u0bb2\u0bae\u0bcd\u0baa\u0bbe\u0b95\u0bcd\u0b95\u0bae\u0bcd"
    ],
    "name:tel_x_preferred":[
        "\u0c15\u0c4b\u0c2f\u0c3f\u0c32\u0c02\u0c2c\u0c3e\u0c15\u0c4d\u0c15\u0c02"
    ],
    "name:urd_x_preferred":[
        "\u06a9\u0648\u0626\u0644\u0645 \u0628\u0627\u06a9\u0651\u0645"
    ],
    "qs:name":"Koilambakkam",
    "qs:name_adm0":"India",
    "qs:name_adm1":"Tamil Nadu",
    "qs:photos":1,
    "qs:photos_1k":1,
    "qs:photos_9k":1,
    "qs:photos_9r":1,
    "qs:photos_all":1,
    "qs:photos_sr":1,
    "qs:placetype":"Suburb",
    "qs:pop_sr":"0",
    "wof:name":"Koilambakkam",
    "wof:placetype":"neighbourhood"
},
  "geometry": {"coordinates":[80.121917,12.946261],"type":"Point"}
}