{
  "type": "Feature",
  "properties": {
    "iso:country":"IN",
    "ks:ks_name":"Devnagar",
    "ks:ks_pop":457,
    "ks:ks_type":"HABITATION",
    "name:eng_x_preferred":[
        "Devnagar"
    ],
    "wof:name":"Devnagar",
    "wof:placetype":"locality",
    "wof:population":457
},
  "geometry": {"coordinates":[73.078306,27.179406],"type":"Point"}
}