{
  "type": "Feature",
  "properties": {
    "iso:country":"IN",
    "ks:ks_name":"Ala Center Jn",
    "ks:ks_pop":354,
    "ks:ks_type":"HABITATION",
    "ks:ks_uagg_main":0,
    "name:eng_x_preferred":[
        "Ala Center Jn"
    ],
    "wof:name":"Ala Center Jn",
    "wof:placetype":"neighbourhood",
    "wof:population":354
},
  "geometry": {"coordinates":[76.14334599999999,10.430601],"type":"Point"}
}