{
  "type": "Feature",
  "properties": {
    "iso:country":"IN",
    "ks:ks_name":"Somanahalli",
    "ks:ks_pop":21,
    "ks:ks_type":"VILLAGE",
    "name:eng_x_preferred":[
        "Somanahalli"
    ],
    "wof:name":"Somanahalli",
    "wof:placetype":"locality",
    "wof:population":21
},
  "geometry": {"coordinates":[76.26636499999999,13.623253],"type":"Point"}
}