{
  "type": "Feature",
  "properties": {
    "gn:admin1_code":"39.0",
    "gn:admin2_code":"57.0",
    "gn:asciiname":"Banjbagar",
    "gn:country_code":"IN",
    "gn:dem":2630,
    "gn:feature_class":"P",
    "gn:feature_code":"PPL",
    "gn:name":"B\u0101njbagar",
    "gn:population":0,
    "gn:timezone":"Asia/Kolkata",
    "iso:country":"IN",
    "wof:name":"Banjbagar",
    "wof:placetype":"locality"
},
  "geometry": {"coordinates":[79.50053,30.21446],"type":"Point"}
}