{
  "type": "Feature",
  "properties": {
    "gn:admin1_code":"36.0",
    "gn:admin2_code":"134.0",
    "gn:asciiname":"Morjhari",
    "gn:country_code":"IN",
    "gn:dem":234,
    "gn:feature_class":"P",
    "gn:feature_code":"PPL",
    "gn:name":"Morjhari",
    "gn:population":0,
    "gn:timezone":"Asia/Kolkata",
    "iso:country":"IN",
    "ks:ks_name":"Morjhari",
    "ks:ks_type":"VILLAGE",
    "name:eng_x_preferred":[
        "Morjhari"
    ],
    "wof:name":"Morjhari",
    "wof:placetype":"locality"
},
  "geometry": {"coordinates":[78.665549,29.441303],"type":"Point"}
}