{
  "type": "Feature",
  "properties": {
    "iso:country":"IN",
    "ks:ks_name":"Namda Thanda",
    "ks:ks_pop":179,
    "ks:ks_type":"HABITATION",
    "name:eng_x_preferred":[
        "Namda Thanda"
    ],
    "wof:name":"Namda Thanda",
    "wof:placetype":"locality",
    "wof:population":179
},
  "geometry": {"coordinates":[78.466994,18.485134],"type":"Point"}
}