{
  "type": "Feature",
  "properties": {
    "iso:country":"IN",
    "ks:ks_name":"Tataihnapalya",
    "ks:ks_pop":109,
    "ks:ks_type":"HABITATION",
    "name:eng_x_preferred":[
        "Tataihnapalya"
    ],
    "wof:name":"Tataihnapalya",
    "wof:placetype":"locality",
    "wof:population":109
},
  "geometry": {"coordinates":[76.889893,13.052491],"type":"Point"}
}