{
  "type": "Feature",
  "properties": {
    "iso:country":"IN",
    "ks:ks_name":"Lakhangarh",
    "ks:ks_pop":98,
    "ks:ks_type":"VILLAGE",
    "name:eng_x_preferred":[
        "Lakhangarh"
    ],
    "wof:name":"Lakhangarh",
    "wof:placetype":"locality",
    "wof:population":98
},
  "geometry": {"coordinates":[75.01664599999999,23.25688],"type":"Point"}
}