{
  "type": "Feature",
  "properties": {
    "iso:country":"IN",
    "ks:ks_name":"Chakaliguda",
    "ks:ks_pop":57,
    "ks:ks_type":"HABITATION",
    "name:eng_x_preferred":[
        "Chakaliguda"
    ],
    "wof:name":"Chakaliguda",
    "wof:placetype":"locality",
    "wof:population":57
},
  "geometry": {"coordinates":[79.065378,16.742634],"type":"Point"}
}