{
  "type": "Feature",
  "properties": {
    "gn:admin1_code":"21.0",
    "gn:admin2_code":"396.0",
    "gn:asciiname":"Surupadi",
    "gn:country_code":"IN",
    "gn:dem":299,
    "gn:feature_class":"P",
    "gn:feature_code":"PPL",
    "gn:name":"Surup\u0101di",
    "gn:population":0,
    "gn:timezone":"Asia/Kolkata",
    "iso:country":"IN",
    "ks:ks_name":"Sarupadu",
    "ks:ks_pop":53,
    "ks:ks_type":"VILLAGE",
    "name:eng_x_preferred":[
        "Sarupadu"
    ],
    "name:eng_x_variant":[
        "Surupadi"
    ],
    "wof:name":"Sarupadu",
    "wof:placetype":"locality",
    "wof:population":53
},
  "geometry": {"coordinates":[83.80381,19.528409],"type":"Point"}
}