{
  "type": "Feature",
  "properties": {
    "iso:country":"IN",
    "ks:ks_name":"Sandhimunda",
    "ks:ks_pop":46,
    "ks:ks_type":"HABITATION",
    "name:eng_x_preferred":[
        "Sandhimunda"
    ],
    "wof:name":"Sandhimunda",
    "wof:placetype":"locality",
    "wof:population":46
},
  "geometry": {"coordinates":[82.138445,18.629036],"type":"Point"}
}