{
  "type": "Feature",
  "properties": {
    "gn:admin1_code":"36",
    "gn:admin2_code":"162.0",
    "gn:asciiname":"Bika Purwa",
    "gn:country_code":"IN",
    "gn:dem":142,
    "gn:feature_class":"P",
    "gn:feature_code":"PPL",
    "gn:name":"B\u012bka Purwa",
    "gn:population":0,
    "gn:timezone":"Asia/Kolkata",
    "iso:country":"IN",
    "ks:ks_name":"Bhika Purwa",
    "ks:ks_pop":242,
    "ks:ks_type":"HABITATION",
    "ks:ks_uagg_main":0,
    "name:eng_x_preferred":[
        "Bhika Purwa"
    ],
    "wof:name":"Bhika Purwa",
    "wof:placetype":"neighbourhood",
    "wof:population":242
},
  "geometry": {"coordinates":[79.631668,26.697499],"type":"Point"}
}