{
  "type": "Feature",
  "properties": {
    "gn:admin1_code":"3.0",
    "gn:admin2_code":"300.0",
    "gn:asciiname":"Santhalpara",
    "gn:country_code":"IN",
    "gn:dem":54,
    "gn:feature_class":"P",
    "gn:feature_code":"PPL",
    "gn:name":"Santh\u0101lp\u0101ra",
    "gn:population":0,
    "gn:timezone":"Asia/Kolkata",
    "iso:country":"IN",
    "wof:name":"Santhalpara",
    "wof:placetype":"locality"
},
  "geometry": {"coordinates":[89.92874999999999,26.45344],"type":"Point"}
}