{
  "type": "Feature",
  "properties": {
    "gn:admin1_code":"19.0",
    "gn:admin2_code":"575.0",
    "gn:asciiname":"Bolugallu",
    "gn:country_code":"IN",
    "gn:dem":122,
    "gn:feature_class":"P",
    "gn:feature_code":"PPL",
    "gn:name":"Bol\u016bg\u0101llu",
    "gn:population":0,
    "gn:timezone":"Asia/Kolkata",
    "iso:country":"IN",
    "wof:name":"Bolugallu",
    "wof:placetype":"locality"
},
  "geometry": {"coordinates":[75.28482,12.53946],"type":"Point"}
}