{
  "type": "Feature",
  "properties": {
    "iso:country":"IN",
    "ks:ks_alt_nam":"Sumarm\u0101ra",
    "ks:ks_name":"Sumarmara",
    "ks:ks_pop":275,
    "ks:ks_type":"VILLAGE",
    "name:eng_x_preferred":[
        "Sumarmara"
    ],
    "name:eng_x_variant":[
        "Sumarm\u0101ra"
    ],
    "wof:name":"Sumarmara",
    "wof:placetype":"locality",
    "wof:population":275
},
  "geometry": {"coordinates":[86.18567299999999,24.618193],"type":"Point"}
}