{
  "type": "Feature",
  "properties": {
    "iso:country":"IN",
    "ks:ks_name":"Popkoda",
    "ks:ks_pop":147,
    "ks:ks_type":"VILLAGE",
    "name:eng_x_preferred":[
        "Popkoda"
    ],
    "wof:name":"Popkoda",
    "wof:placetype":"locality",
    "wof:population":147
},
  "geometry": {"coordinates":[85.349146,22.438002],"type":"Point"}
}