{
  "type": "Feature",
  "properties": {
    "iso:country":"IN",
    "ks:ks_name":"Katahia Tola",
    "ks:ks_pop":190,
    "ks:ks_type":"HABITATION",
    "ks:ks_uagg_main":0,
    "name:eng_x_preferred":[
        "Katahia Tola"
    ],
    "wof:name":"Katahia Tola",
    "wof:placetype":"neighbourhood",
    "wof:population":190
},
  "geometry": {"coordinates":[84.250806,26.790465],"type":"Point"}
}