{
  "type": "Feature",
  "properties": {
    "iso:country":"IN",
    "ks:ks_alt_nam":"MOULANA TOLA",
    "ks:ks_name":"Moulana Tola",
    "ks:ks_pop":247,
    "ks:ks_type":"HABITATION",
    "ks:ks_uagg_main":0,
    "name:eng_x_preferred":[
        "Moulana Tola"
    ],
    "wof:name":"Moulana Tola",
    "wof:placetype":"neighbourhood",
    "wof:population":247
},
  "geometry": {"coordinates":[86.10248300000001,25.555421],"type":"Point"}
}