{
  "type": "Feature",
  "properties": {
    "gn:admin1_code":"25.0",
    "gn:admin2_code":"607.0",
    "gn:asciiname":"Indirasankuppam",
    "gn:country_code":"IN",
    "gn:dem":74,
    "gn:feature_class":"P",
    "gn:feature_code":"PPL",
    "gn:name":"Indirasankuppam",
    "gn:population":0,
    "gn:timezone":"Asia/Kolkata",
    "iso:country":"IN",
    "wof:name":"Indirasankuppam",
    "wof:placetype":"locality"
},
  "geometry": {"coordinates":[79.53222,12.28404],"type":"Point"}
}