{
  "type": "Feature",
  "properties": {
    "gn:admin1_code":"36",
    "gn:admin2_code":"170.0",
    "gn:asciiname":"Phaphundi",
    "gn:country_code":"IN",
    "gn:dem":129,
    "gn:feature_class":"P",
    "gn:feature_code":"PPL",
    "gn:name":"Phaph\u016bndi",
    "gn:population":0,
    "gn:timezone":"Asia/Kolkata",
    "iso:country":"IN",
    "wof:name":"Phaphundi",
    "wof:placetype":"locality"
},
  "geometry": {"coordinates":[80.70509,25.49369],"type":"Point"}
}