{
  "type": "Feature",
  "properties": {
    "gn:admin1_code":"40.0",
    "gn:admin2_code":"535.0",
    "gn:asciiname":"Masanpalli",
    "gn:country_code":"IN",
    "gn:dem":556,
    "gn:feature_class":"P",
    "gn:feature_code":"PPL",
    "gn:name":"M\u0101s\u0101npalli",
    "gn:population":0,
    "gn:timezone":"Asia/Kolkata",
    "iso:country":"IN",
    "wof:name":"Masanpalli",
    "wof:placetype":"locality"
},
  "geometry": {"coordinates":[78.65333000000003,17.92217999999999],"type":"Point"}
}