{
  "type": "Feature",
  "properties": {
    "iso:country":"IN",
    "ks:ks_name":"Gatia Faliya",
    "ks:ks_pop":1012,
    "ks:ks_type":"HABITATION",
    "name:eng_x_preferred":[
        "Gatia Faliya"
    ],
    "wof:name":"Gatia Faliya",
    "wof:placetype":"locality",
    "wof:population":1012
},
  "geometry": {"coordinates":[73.96290999999999,23.1794],"type":"Point"}
}