{
  "type": "Feature",
  "properties": {
    "iso:country":"IN",
    "ks:ks_name":"Sooka",
    "ks:ks_pop":255,
    "ks:ks_type":"VILLAGE",
    "name:eng_x_preferred":[
        "Sooka"
    ],
    "wof:name":"Sooka",
    "wof:placetype":"locality",
    "wof:population":255
},
  "geometry": {"coordinates":[79.35442399999999,29.51652],"type":"Point"}
}