{
  "type": "Feature",
  "properties": {
    "gn:admin1_code":"12",
    "gn:admin2_code":"14.0",
    "gn:asciiname":"Wujur",
    "gn:country_code":"IN",
    "gn:dem":1754,
    "gn:feature_class":"P",
    "gn:feature_code":"PPL",
    "gn:name":"Wujur",
    "gn:population":0,
    "gn:timezone":"Asia/Kolkata",
    "iso:country":"IN",
    "wof:name":"Wujur",
    "wof:placetype":"locality"
},
  "geometry": {"coordinates":[75.19096999999999,33.57014],"type":"Point"}
}