{
  "type": "Feature",
  "properties": {
    "gn:admin1_code":"39.0",
    "gn:admin2_code":"66.0",
    "gn:asciiname":"Gaibua Khas",
    "gn:country_code":"IN",
    "gn:dem":326,
    "gn:feature_class":"P",
    "gn:feature_code":"PPL",
    "gn:name":"Gaibu\u0101 Kh\u0101s",
    "gn:population":0,
    "gn:timezone":"Asia/Kolkata",
    "iso:country":"IN",
    "ks:ks_alt_nam":"Gaibu\u0101 Kh\u0101s",
    "ks:ks_name":"Gaibua Khas",
    "ks:ks_type":"VILLAGE",
    "name:eng_x_preferred":[
        "Gaibua Khas"
    ],
    "name:eng_x_variant":[
        "Gaibu\u0101 Kh\u0101s"
    ],
    "wof:name":"Gaibua Khas",
    "wof:placetype":"locality"
},
  "geometry": {"coordinates":[79.17291899999999,29.32162],"type":"Point"}
}