{
  "type": "Feature",
  "properties": {
    "iso:country":"IN",
    "ks:ks_name":"Madhuwa Nagri Mustqil",
    "ks:ks_pop":575,
    "ks:ks_type":"VILLAGE",
    "ks:ks_uagg_main":0,
    "name:eng_x_preferred":[
        "Madhuwa Nagri Mustqil"
    ],
    "wof:name":"Madhuwa Nagri Mustqil",
    "wof:placetype":"neighbourhood",
    "wof:population":575
},
  "geometry": {"coordinates":[79.77277599999999,28.604646],"type":"Point"}
}