{
  "type": "Feature",
  "properties": {
    "gn:country":"IN",
    "gn:fcode":"PPL",
    "gn:pop":77070,
    "iso:country":"IN",
    "name:ben_x_preferred":[
        "\u09a7\u09c1\u09b2\u09bf\u09af\u09bc\u09be\u09a8"
    ],
    "name:bpy_x_preferred":[
        "\u09a7\u09c1\u09b2\u09bf\u09af\u09bc\u09be\u09a8"
    ],
    "name:eng_x_preferred":[
        "Dhulian"
    ],
    "name:fra_x_preferred":[
        "Dhulian"
    ],
    "name:ita_x_preferred":[
        "Dhulian"
    ],
    "name:msa_x_preferred":[
        "Dhulian"
    ],
    "name:new_x_preferred":[
        "\u0927\u0941\u0932\u093f\u092f\u0928"
    ],
    "name:nld_x_preferred":[
        "Dhulian"
    ],
    "name:pam_x_preferred":[
        "Dhulian"
    ],
    "name:por_x_preferred":[
        "Dhulian"
    ],
    "name:rus_x_preferred":[
        "\u0414\u0445\u0443\u043b\u0438\u044f\u043d"
    ],
    "name:spa_x_preferred":[
        "Dhulian"
    ],
    "name:swe_x_preferred":[
        "Dhulian"
    ],
    "name:unk_x_variant":[
        "Dhuli\u0101n"
    ],
    "name:vie_x_preferred":[
        "Dhulian"
    ],
    "name:zho_x_preferred":[
        "\u675c\u5229\u4e9a\u6069"
    ],
    "qs:name":"Dhulian",
    "qs:name_adm0":"India",
    "qs:name_adm1":"West Bengal",
    "qs:photos_9r":0,
    "qs:photos_sr":0,
    "qs:placetype":"Town",
    "qs:pop_sr":"8",
    "wd:wordcount":334,
    "wof:name":"Dhulian",
    "wof:placetype":"locality",
    "wof:population":77070
},
  "geometry": {"coordinates":[87.96666999999999,24.68333],"type":"Point"}
}