{
  "type": "Feature",
  "properties": {
    "iso:country":"IN",
    "ks:ks_name":"Dabhil Ambere",
    "ks:ks_pop":638,
    "ks:ks_type":"VILLAGE",
    "name:eng_x_preferred":[
        "Dabhil Ambere"
    ],
    "wof:name":"Dabhil Ambere",
    "wof:placetype":"locality",
    "wof:population":638
},
  "geometry": {"coordinates":[73.356081,16.779966],"type":"Point"}
}