{
  "type": "Feature",
  "properties": {
    "gn:admin1_code":"34.0",
    "gn:admin2_code":"220.0",
    "gn:asciiname":"Satkurwa",
    "gn:country_code":"IN",
    "gn:dem":56,
    "gn:feature_class":"P",
    "gn:feature_code":"PPL",
    "gn:name":"Satkurwa",
    "gn:population":0,
    "gn:timezone":"Asia/Kolkata",
    "iso:country":"IN",
    "ks:ks_name":"Sat Kurwa",
    "ks:ks_pop":404,
    "ks:ks_type":"VILLAGE",
    "name:eng_x_preferred":[
        "Sat Kurwa"
    ],
    "name:eng_x_variant":[
        "Satkurwa"
    ],
    "wof:name":"Sat Kurwa",
    "wof:placetype":"locality",
    "wof:population":404
},
  "geometry": {"coordinates":[85.455068,25.907836],"type":"Point"}
}