{
  "type": "Feature",
  "properties": {
    "iso:country":"IN",
    "ks:ks_name":"Bhaluarchar",
    "ks:ks_pop":2845,
    "ks:ks_type":"VILLAGE",
    "name:eng_x_preferred":[
        "Bhaluarchar"
    ],
    "wof:name":"Bhaluarchar",
    "wof:placetype":"locality",
    "wof:population":2845
},
  "geometry": {"coordinates":[91.20674699999999,23.633883],"type":"Point"}
}