{
  "type": "Feature",
  "properties": {
    "iso:country":"IN",
    "ks:ks_name":"Bagicha Kumar Chak",
    "ks:ks_pop":2116,
    "ks:ks_type":"VILLAGE",
    "name:eng_x_preferred":[
        "Bagicha Kumar Chak"
    ],
    "wof:name":"Bagicha Kumar Chak",
    "wof:placetype":"locality",
    "wof:population":2116
},
  "geometry": {"coordinates":[87.843159,22.388148],"type":"Point"}
}