{
  "type": "Feature",
  "properties": {
    "iso:country":"IN",
    "ks:ks_name":"Bhogpunji",
    "ks:ks_pop":1415,
    "ks:ks_type":"VILLAGE",
    "name:eng_x_preferred":[
        "Bhogpunji"
    ],
    "wof:name":"Bhogpunji",
    "wof:placetype":"locality",
    "wof:population":1415
},
  "geometry": {"coordinates":[88.215374,22.260004],"type":"Point"}
}