{
  "type": "Feature",
  "properties": {
    "gn:admin1_code":"34.0",
    "gn:admin2_code":"219.0",
    "gn:asciiname":"Basatpur",
    "gn:country_code":"IN",
    "gn:dem":59,
    "gn:feature_class":"P",
    "gn:feature_code":"PPL",
    "gn:name":"Basatpur",
    "gn:population":0,
    "gn:timezone":"Asia/Kolkata",
    "iso:country":"IN",
    "ks:ks_name":"Basant Pur",
    "ks:ks_pop":911,
    "ks:ks_type":"VILLAGE",
    "ks:ks_uagg_main":0,
    "name:eng_x_preferred":[
        "Basant Pur"
    ],
    "name:mai_x_preferred":[
        "\u092c\u0938\u0924\u092a\u0941\u0930"
    ],
    "name:msa_x_preferred":[
        "Basatpur"
    ],
    "name:new_x_preferred":[
        "\u092c\u0938\u0928\u094d\u0924\u092a\u0941\u0930 \u0917\u093e\u0935\u093f\u0938"
    ],
    "name:pol_x_preferred":[
        "Basatpur"
    ],
    "wof:name":"Basant Pur",
    "wof:placetype":"neighbourhood",
    "wof:population":911
},
  "geometry": {"coordinates":[84.960594,25.991117],"type":"Point"}
}