{
  "type": "Feature",
  "properties": {
    "iso:country":"IN",
    "ks:ks_alt_nam":"Talabahali Badasada GP",
    "ks:ks_name":"Talabahali Badasada Gp",
    "ks:ks_pop":58,
    "ks:ks_type":"HABITATION",
    "name:eng_x_preferred":[
        "Talabahali Badasada Gp"
    ],
    "wof:name":"Talabahali Badasada Gp",
    "wof:placetype":"locality",
    "wof:population":58
},
  "geometry": {"coordinates":[85.235021,21.32624],"type":"Point"}
}