{
  "type": "Feature",
  "properties": {
    "iso:country":"IN",
    "ks:ks_name":"Badkherwa",
    "ks:ks_pop":523,
    "ks:ks_type":"VILLAGE",
    "ks:ks_uagg_main":0,
    "name:eng_x_preferred":[
        "Badkherwa"
    ],
    "wof:name":"Badkherwa",
    "wof:placetype":"neighbourhood",
    "wof:population":523
},
  "geometry": {"coordinates":[80.728208,27.686573],"type":"Point"}
}