{
  "type": "Feature",
  "properties": {
    "gn:admin1_code":"37",
    "gn:admin2_code":"413.0",
    "gn:asciiname":"Konechur",
    "gn:country_code":"IN",
    "gn:dem":376,
    "gn:feature_class":"P",
    "gn:feature_code":"PPL",
    "gn:name":"Konech\u016br",
    "gn:population":0,
    "gn:timezone":"Asia/Kolkata",
    "iso:country":"IN",
    "wof:name":"Konechur",
    "wof:placetype":"locality"
},
  "geometry": {"coordinates":[81.06573,20.10757000000001],"type":"Point"}
}