{
  "type": "Feature",
  "properties": {
    "gn:admin1_code":"37",
    "gn:admin2_code":"413.0",
    "gn:asciiname":"Konechur",
    "gn:country_code":"IN",
    "gn:dem":376,
    "gn:feature_class":"P",
    "gn:feature_code":"PPL",
    "gn:name":"Konech\u016br",
    "gn:population":0,
    "gn:timezone":"Asia/Kolkata",
    "iso:country":"IN",
    "ks:ks_alt_nam":"Konech\u016br",
    "ks:ks_name":"Konechur",
    "ks:ks_type":"VILLAGE",
    "name:eng_x_preferred":[
        "Konechur"
    ],
    "name:eng_x_variant":[
        "Konech\u016br"
    ],
    "wof:name":"Konechur",
    "wof:placetype":"locality"
},
  "geometry": {"coordinates":[81.065729,20.107573],"type":"Point"}
}