{
  "type": "Feature",
  "properties": {
    "gn:admin1_code":"28.0",
    "gn:admin2_code":"338",
    "gn:asciiname":"Mora",
    "gn:country_code":"IN",
    "gn:dem":17,
    "gn:feature_class":"P",
    "gn:feature_code":"PPL",
    "gn:name":"Mora",
    "gn:population":0,
    "gn:timezone":"Asia/Kolkata",
    "iso:country":"IN",
    "wof:name":"Mora",
    "wof:placetype":"locality"
},
  "geometry": {"coordinates":[88.05003000000001,22.82328],"type":"Point"}
}