{
  "type": "Feature",
  "properties": {
    "iso:country":"IN",
    "name:eng_x_preferred":[
        "Balewadi Phata"
    ],
    "wof:name":"Balewadi Phata",
    "wof:placetype":"neighbourhood"
},
  "geometry": {"coordinates":[73.78263645218485,18.56377415040627],"type":"Point"}
}