{
  "type": "Feature",
  "properties": {
    "iso:country":"IN",
    "name:ara_x_preferred":[
        "\u0628\u0627\u0644\u0641\u0627\u062f\u064a \u0641\u0627\u062a\u0627"
    ],
    "name:ben_bn_x_preferred":[
        "\u09ac\u09be\u09b2\u09c7\u0993\u09df\u09be\u09a1\u09bf \u09ab\u09be\u099f\u09be"
    ],
    "name:ben_in_x_preferred":[
        "\u09ac\u09be\u09b2\u09c7\u0993\u09df\u09be\u09a1\u09bf \u09ab\u09be\u099f\u09be"
    ],
    "name:eng_x_preferred":[
        "Balewadi Phata"
    ],
    "name:guj_x_preferred":[
        "\u0aac\u0ab3\u0ac7\u0ab5\u0abe\u0aa1\u0ac0 \u0aab\u0abe\u0aa4\u0abe"
    ],
    "name:hin_x_preferred":[
        "\u092c\u093e\u0932\u0947\u0935\u093e\u095c\u0940 \u092b\u093e\u091f\u093e"
    ],
    "name:kan_x_preferred":[
        "\u0cac\u0cbe\u0cb2\u0cc6\u0cb5\u0cbe\u0ca1\u0cbf \u0cab\u0c9f\u0cbe"
    ],
    "name:mal_x_preferred":[
        "\u0d2c\u0d3e\u0d32\u0d47\u0d35\u0d3e\u0d1f\u0d3f \u0d2b\u0d3e\u0d31\u0d4d\u0d31"
    ],
    "name:mar_x_preferred":[
        "\u092c\u093e\u0932\u0947\u0935\u093e\u0921\u0940 \u092b\u093e\u091f\u093e"
    ],
    "name:pan_x_preferred":[
        "\u0a2c\u0a3e\u0a32\u0a47\u0a35\u0a3e\u0a5c\u0a40 \u0a2b\u0a71\u0a24\u0a3e"
    ],
    "name:tam_x_preferred":[
        "\u0baa\u0bb2\u0bc7\u0bb5\u0bbe\u0b9f\u0bbf \u0b83\u0baa\u0b9f\u0bbe"
    ],
    "name:tel_x_preferred":[
        "\u0c2c\u0c32\u0c46\u0c35\u0c3e\u0c21\u0c3f \u0c2a\u0c3e\u0c1f\u0c3e"
    ],
    "name:urd_x_preferred":[
        "\u0628\u0627\u0644\u06cc \u0648\u0627\u0688\u06cc \u067e\u06be\u0627\u0679\u0627"
    ],
    "wof:name":"Balewadi Phata",
    "wof:placetype":"neighbourhood"
},
  "geometry": {"coordinates":[73.78263645218485,18.56377415040627],"type":"Point"}
}