{
  "type": "Feature",
  "properties": {
    "gn:admin1_code":"36",
    "gn:admin2_code":"132.0",
    "gn:asciiname":"Muhammadpur",
    "gn:country_code":"IN",
    "gn:dem":285,
    "gn:feature_class":"P",
    "gn:feature_code":"PPL",
    "gn:name":"Muhammadpur",
    "gn:population":0,
    "gn:timezone":"Asia/Kolkata",
    "iso:country":"IN",
    "name:und_x_variant":[
        "Sada Mazra"
    ],
    "wof:name":"Muhammadpur",
    "wof:placetype":"neighbourhood"
},
  "geometry": {"coordinates":[77.65448000000001,30.02448],"type":"Point"}
}