{
  "type": "Feature",
  "properties": {
    "iso:country":"IN",
    "ks:ks_name":"Khatanaga",
    "ks:ks_pop":1366,
    "ks:ks_type":"VILLAGE",
    "ks:ks_uagg_main":0,
    "name:eng_x_preferred":[
        "Khatanaga"
    ],
    "wof:name":"Khatanaga",
    "wof:placetype":"neighbourhood",
    "wof:population":1366
},
  "geometry": {"coordinates":[85.403567,23.378631],"type":"Point"}
}