{
  "type": "Feature",
  "properties": {
    "gn:admin1_code":"34.0",
    "gn:admin2_code":"211.0",
    "gn:asciiname":"Bhukraha",
    "gn:country_code":"IN",
    "gn:dem":43,
    "gn:feature_class":"P",
    "gn:feature_code":"PPL",
    "gn:name":"Bhukr\u0101ha",
    "gn:population":0,
    "gn:timezone":"Asia/Kolkata",
    "iso:country":"IN",
    "ks:ks_alt_nam":"BHOK RAHA",
    "ks:ks_name":"Bhok Raha",
    "ks:ks_pop":580,
    "ks:ks_type":"HABITATION",
    "ks:ks_uagg_main":0,
    "name:eng_x_preferred":[
        "Bhok Raha"
    ],
    "wof:name":"Bhok Raha",
    "wof:placetype":"neighbourhood",
    "wof:population":580
},
  "geometry": {"coordinates":[87.388147,25.832228],"type":"Point"}
}