{
  "type": "Feature",
  "properties": {
    "iso:country":"IN",
    "ks:ks_name":"Nanakpur Muhal",
    "ks:ks_pop":96,
    "ks:ks_type":"VILLAGE",
    "name:eng_x_preferred":[
        "Nanakpur Muhal"
    ],
    "wof:name":"Nanakpur Muhal",
    "wof:placetype":"locality",
    "wof:population":96
},
  "geometry": {"coordinates":[77.81801900000001,24.667117],"type":"Point"}
}