{
  "type": "Feature",
  "properties": {
    "iso:country":"IN",
    "ks:ks_name":"Kokebera",
    "ks:ks_pop":176,
    "ks:ks_type":"VILLAGE",
    "name:eng_x_preferred":[
        "Kokebera"
    ],
    "wof:name":"Kokebera",
    "wof:placetype":"locality",
    "wof:population":176
},
  "geometry": {"coordinates":[85.949158,22.950548],"type":"Point"}
}