{
  "type": "Feature",
  "properties": {
    "iso:country":"IN",
    "ks:ks_name":"Gumpu",
    "ks:ks_pop":34,
    "ks:ks_type":"VILLAGE",
    "ks:ks_uagg_main":0,
    "name:eng_x_preferred":[
        "Gumpu"
    ],
    "wof:name":"Gumpu",
    "wof:placetype":"neighbourhood",
    "wof:population":34
},
  "geometry": {"coordinates":[85.76389899999999,22.868085],"type":"Point"}
}