{
  "type": "Feature",
  "properties": {
    "iso:country":"IN",
    "ks:ks_name":"Gollarahatti",
    "ks:ks_pop":220,
    "ks:ks_type":"HABITATION",
    "name:eng_x_preferred":[
        "Gollarahatti"
    ],
    "wof:name":"Gollarahatti",
    "wof:placetype":"locality",
    "wof:population":220
},
  "geometry": {"coordinates":[76.41605199999999,13.320027],"type":"Point"}
}