{
  "type": "Feature",
  "properties": {
    "gn:admin1_code":"34",
    "gn:admin2_code":"203.0",
    "gn:asciiname":"Mainatanr",
    "gn:country_code":"IN",
    "gn:dem":92,
    "gn:feature_class":"P",
    "gn:feature_code":"PPL",
    "gn:name":"Main\u0101t\u0101nr",
    "gn:population":0,
    "gn:timezone":"Asia/Kolkata",
    "iso:country":"IN",
    "ks:ks_alt_nam":"Main\u0101t\u0101nr",
    "ks:ks_name":"Mainatanr",
    "ks:ks_pop":4669,
    "ks:ks_type":"VILLAGE",
    "ks:ks_uagg_main":0,
    "name:eng_x_preferred":[
        "Mainatanr"
    ],
    "name:eng_x_variant":[
        "Main\u0101t\u0101nr"
    ],
    "name:und_x_variant":[
        "Mam\u0101t\u0101nr",
        "Main\u0101t\u0101nr"
    ],
    "wof:name":"Mainatanr",
    "wof:placetype":"neighbourhood",
    "wof:population":4669
},
  "geometry": {"coordinates":[84.643872,27.093026],"type":"Point"}
}