{
  "type": "Feature",
  "properties": {
    "gn:admin1_code":"2.0",
    "gn:admin2_code":"554.0",
    "gn:asciiname":"Sampatikota",
    "gn:country_code":"IN",
    "gn:dem":677,
    "gn:feature_class":"P",
    "gn:feature_code":"PPL",
    "gn:name":"Sampatikota",
    "gn:population":0,
    "gn:timezone":"Asia/Kolkata",
    "iso:country":"IN",
    "wof:name":"Sampatikota",
    "wof:placetype":"locality"
},
  "geometry": {"coordinates":[78.21639,13.62824],"type":"Point"}
}