{
  "type": "Feature",
  "properties": {
    "iso:country":"IN",
    "ks:ks_name":"Harilatanr",
    "ks:ks_pop":427,
    "ks:ks_type":"HABITATION",
    "name:eng_x_preferred":[
        "Harilatanr"
    ],
    "wof:name":"Harilatanr",
    "wof:placetype":"locality",
    "wof:population":427
},
  "geometry": {"coordinates":[86.304058,24.313543],"type":"Point"}
}