{
  "type": "Feature",
  "properties": {
    "gn:admin1_code":"16",
    "gn:admin2_code":"529.0",
    "gn:asciiname":"Pombhurla",
    "gn:country_code":"IN",
    "gn:dem":53,
    "gn:feature_class":"P",
    "gn:feature_code":"PPL",
    "gn:name":"Pombhurla",
    "gn:population":0,
    "gn:timezone":"Asia/Kolkata",
    "iso:country":"IN",
    "wof:name":"Pombhurla",
    "wof:placetype":"locality"
},
  "geometry": {"coordinates":[73.55152,16.51696],"type":"Point"}
}