{
  "type": "Feature",
  "properties": {
    "iso:country":"IN",
    "ks:ks_name":"Mirza Inamutulla Pur",
    "ks:ks_pop":362,
    "ks:ks_type":"HABITATION",
    "ks:ks_uagg_main":0,
    "name:eng_x_preferred":[
        "Mirza Inamutulla Pur"
    ],
    "wof:name":"Mirza Inamutulla Pur",
    "wof:placetype":"neighbourhood",
    "wof:population":362
},
  "geometry": {"coordinates":[81.239807,25.950425],"type":"Point"}
}