{
  "type": "Feature",
  "properties": {
    "iso:country":"IN",
    "ks:ks_alt_nam":"Ammiyam manna",
    "ks:ks_name":"Ammiyam Manna",
    "ks:ks_pop":140,
    "ks:ks_type":"HABITATION",
    "name:eng_x_preferred":[
        "Ammiyam Manna"
    ],
    "wof:name":"Ammiyam Manna",
    "wof:placetype":"locality",
    "wof:population":140
},
  "geometry": {"coordinates":[75.80820199999999,11.635236],"type":"Point"}
}