{
  "type": "Feature",
  "properties": {
    "gn:admin1_code":"36",
    "gn:admin2_code":"173.0",
    "gn:asciiname":"Kahla",
    "gn:country_code":"IN",
    "gn:dem":101,
    "gn:feature_class":"P",
    "gn:feature_code":"PPL",
    "gn:name":"Kahla",
    "gn:population":0,
    "gn:timezone":"Asia/Kolkata",
    "iso:country":"IN",
    "name:ara_x_preferred":[
        "\u0643\u0627\u0644\u0627"
    ],
    "name:azb_x_preferred":[
        "\u06a9\u0627\u0644\u0627"
    ],
    "name:bak_x_preferred":[
        "\u041a\u0430\u043b\u0430"
    ],
    "name:deu_x_preferred":[
        "Kahla"
    ],
    "name:epo_x_preferred":[
        "Kahla"
    ],
    "name:fas_x_preferred":[
        "\u06a9\u0627\u0644\u0627"
    ],
    "name:fra_x_preferred":[
        "Kahla"
    ],
    "name:hun_x_preferred":[
        "Kahla"
    ],
    "name:ita_x_preferred":[
        "Kahla"
    ],
    "name:kaz_x_preferred":[
        "\u041a\u0430\u043b\u0430"
    ],
    "name:mkd_x_preferred":[
        "\u041a\u0430\u043b\u0430"
    ],
    "name:msa_x_preferred":[
        "Kahla"
    ],
    "name:nld_x_preferred":[
        "Kahla"
    ],
    "name:pol_x_preferred":[
        "Kahla"
    ],
    "name:por_x_preferred":[
        "Kahla"
    ],
    "name:ron_x_preferred":[
        "Kahla"
    ],
    "name:rus_x_preferred":[
        "\u041a\u0430\u043b\u0430"
    ],
    "name:sco_x_preferred":[
        "Kahla"
    ],
    "name:spa_x_preferred":[
        "Kahla"
    ],
    "name:srp_x_preferred":[
        "\u041a\u0430\u043b\u0430"
    ],
    "name:swe_x_preferred":[
        "Kahla"
    ],
    "name:tur_x_preferred":[
        "Kahla"
    ],
    "name:ukr_x_preferred":[
        "\u041a\u0430\u043b\u0430"
    ],
    "name:uzb_x_preferred":[
        "Kahla"
    ],
    "name:vie_x_preferred":[
        "Kahla"
    ],
    "name:vol_x_preferred":[
        "Kahla"
    ],
    "name:war_x_preferred":[
        "Kahla"
    ],
    "wof:name":"Kahla",
    "wof:placetype":"locality"
},
  "geometry": {"coordinates":[82.08866999999999,25.7099],"type":"Point"}
}