{
  "type": "Feature",
  "properties": {
    "iso:country":"IN",
    "ks:ks_name":"Khalchi Benwadi",
    "ks:ks_pop":196,
    "ks:ks_type":"HABITATION",
    "name:eng_x_preferred":[
        "Khalchi Benwadi"
    ],
    "wof:name":"Khalchi Benwadi",
    "wof:placetype":"locality",
    "wof:population":196
},
  "geometry": {"coordinates":[73.796824,15.993087],"type":"Point"}
}