{
  "type": "Feature",
  "properties": {
    "iso:country":"IN",
    "ks:ks_name":"Fatehpur Saraiya Uparhar",
    "ks:ks_pop":1294,
    "ks:ks_type":"VILLAGE",
    "name:eng_x_preferred":[
        "Fatehpur Saraiya Uparhar"
    ],
    "wof:name":"Fatehpur Saraiya Uparhar",
    "wof:placetype":"locality",
    "wof:population":1294
},
  "geometry": {"coordinates":[82.04608500000001,26.773615],"type":"Point"}
}