{
  "type": "Feature",
  "properties": {
    "iso:country":"IN",
    "ks:ks_name":"Surimane",
    "ks:ks_pop":32,
    "ks:ks_type":"HABITATION",
    "name:eng_x_preferred":[
        "Surimane"
    ],
    "wof:name":"Surimane",
    "wof:placetype":"locality",
    "wof:population":32
},
  "geometry": {"coordinates":[74.84223299999999,14.767526],"type":"Point"}
}