{
  "type": "Feature",
  "properties": {
    "iso:country":"IN",
    "ks:ks_name":"Gopangi",
    "ks:ks_pop":144,
    "ks:ks_type":"HABITATION",
    "name:eng_x_preferred":[
        "Gopangi"
    ],
    "wof:name":"Gopangi",
    "wof:placetype":"locality",
    "wof:population":144
},
  "geometry": {"coordinates":[80.552093,22.587014],"type":"Point"}
}