{
  "type": "Feature",
  "properties": {
    "iso:country":"IN",
    "ks:ks_name":"Sherpur",
    "ks:ks_pop":2745,
    "ks:ks_type":"VILLAGE",
    "name:eng_x_preferred":[
        "Sherpur"
    ],
    "wof:name":"Sherpur",
    "wof:placetype":"locality",
    "wof:population":2745
},
  "geometry": {"coordinates":[85.401145,26.09518],"type":"Point"}
}