{
  "type": "Feature",
  "properties": {
    "iso:country":"IN",
    "ks:ks_name":"Pattibargau Hissa Samogar",
    "ks:ks_pop":1017,
    "ks:ks_type":"VILLAGE",
    "name:eng_x_preferred":[
        "Pattibargau Hissa Samogar"
    ],
    "wof:name":"Pattibargau Hissa Samogar",
    "wof:placetype":"locality",
    "wof:population":1017
},
  "geometry": {"coordinates":[83.18629900000001,26.518591],"type":"Point"}
}