{
  "type": "Feature",
  "properties": {
    "gn:admin1_code":"3.0",
    "gn:admin2_code":"309.0",
    "gn:asciiname":"Pengri",
    "gn:country_code":"IN",
    "gn:dem":164,
    "gn:feature_class":"P",
    "gn:feature_code":"PPL",
    "gn:name":"Pengri",
    "gn:population":0,
    "gn:timezone":"Asia/Kolkata",
    "iso:country":"IN",
    "name:eng_x_colloquial":[
        "Pengeri"
    ],
    "name:eng_x_preferred":[
        "Pengeri"
    ],
    "wof:name":"Pengri",
    "wof:placetype":"locality"
},
  "geometry": {"coordinates":[95.76519999999999,27.42285],"type":"Point"}
}