{
  "type": "Feature",
  "properties": {
    "iso:country":"IN",
    "ks:ks_name":"Barapurikia",
    "ks:ks_pop":39,
    "ks:ks_type":"VILLAGE",
    "name:eng_x_preferred":[
        "Barapurikia"
    ],
    "wof:name":"Barapurikia",
    "wof:placetype":"locality",
    "wof:population":39
},
  "geometry": {"coordinates":[84.95919499999999,20.035663],"type":"Point"}
}