{
  "type": "Feature",
  "properties": {
    "iso:country":"IN",
    "ks:ks_name":"Madhusudanchak",
    "ks:ks_pop":1733,
    "ks:ks_type":"VILLAGE",
    "ks:ks_uagg_main":0,
    "name:eng_x_preferred":[
        "Madhusudanchak"
    ],
    "wof:name":"Madhusudanchak",
    "wof:placetype":"neighbourhood",
    "wof:population":1733
},
  "geometry": {"coordinates":[87.834806,21.999873],"type":"Point"}
}