{
  "type": "Feature",
  "properties": {
    "iso:country":"IN",
    "ks:ks_name":"Selliyamman Nagar Kattu Valavu",
    "ks:ks_pop":515,
    "ks:ks_type":"HABITATION",
    "name:eng_x_preferred":[
        "Selliyamman Nagar Kattu Valavu"
    ],
    "wof:name":"Selliyamman Nagar Kattu Valavu",
    "wof:placetype":"locality",
    "wof:population":515
},
  "geometry": {"coordinates":[78.318518,11.678755],"type":"Point"}
}