{
  "type": "Feature",
  "properties": {
    "iso:country":"IN",
    "ks:ks_name":"Malla Kuva",
    "ks:ks_pop":300,
    "ks:ks_type":"HABITATION",
    "name:eng_x_preferred":[
        "Malla Kuva"
    ],
    "wof:name":"Malla Kuva",
    "wof:placetype":"locality",
    "wof:population":300
},
  "geometry": {"coordinates":[73.741417,22.7408],"type":"Point"}
}