{
  "type": "Feature",
  "properties": {
    "gn:admin1_code":"19.0",
    "gn:admin2_code":"570.0",
    "gn:asciiname":"Hyarambi",
    "gn:country_code":"IN",
    "gn:dem":754,
    "gn:feature_class":"P",
    "gn:feature_code":"PPL",
    "gn:name":"Hy\u0101rambi",
    "gn:population":0,
    "gn:timezone":"Asia/Kolkata",
    "iso:country":"IN",
    "ks:ks_alt_nam":"Hy\u0101rambi",
    "ks:ks_name":"Hyarambi",
    "ks:ks_pop":1108,
    "ks:ks_type":"VILLAGE",
    "name:eng_x_preferred":[
        "Hyarambi"
    ],
    "name:eng_x_variant":[
        "Hy\u0101rambi"
    ],
    "wof:name":"Hyarambi",
    "wof:placetype":"locality",
    "wof:population":1108
},
  "geometry": {"coordinates":[75.549198,13.34115],"type":"Point"}
}