{
  "type": "Feature",
  "properties": {
    "iso:country":"IN",
    "ks:ks_name":"Sirkapi",
    "ks:ks_pop":77,
    "ks:ks_type":"HABITATION",
    "name:eng_x_preferred":[
        "Sirkapi"
    ],
    "wof:name":"Sirkapi",
    "wof:placetype":"locality",
    "wof:population":77
},
  "geometry": {"coordinates":[85.82860100000001,22.234968],"type":"Point"}
}