{
  "type": "Feature",
  "properties": {
    "gn:admin1_code":"37",
    "gn:admin2_code":"410.0",
    "gn:asciiname":"Riko",
    "gn:country_code":"IN",
    "gn:dem":311,
    "gn:feature_class":"P",
    "gn:feature_code":"PPL",
    "gn:name":"R\u012bko",
    "gn:population":0,
    "gn:timezone":"Asia/Kolkata",
    "iso:country":"IN",
    "name:ind_x_preferred":[
        "Riko"
    ],
    "wof:name":"Riko",
    "wof:placetype":"locality"
},
  "geometry": {"coordinates":[81.78766,21.20375],"type":"Point"}
}