{
  "type": "Feature",
  "properties": {
    "iso:country":"IN",
    "ks:ks_name":"Lakhanpur",
    "ks:ks_pop":1486,
    "ks:ks_type":"HABITATION",
    "name:eng_x_preferred":[
        "Lakhanpur"
    ],
    "wof:name":"Lakhanpur",
    "wof:placetype":"locality",
    "wof:population":1486
},
  "geometry": {"coordinates":[82.595834,25.37469],"type":"Point"}
}