{
  "type": "Feature",
  "properties": {
    "gn:admin1_code":"11",
    "gn:admin2_code":"31.0",
    "gn:asciiname":"Sanawar",
    "gn:country_code":"IN",
    "gn:dem":1490,
    "gn:feature_class":"P",
    "gn:feature_code":"PPL",
    "gn:name":"San\u0101war",
    "gn:population":0,
    "gn:timezone":"Asia/Kolkata",
    "iso:country":"IN",
    "name:ara_x_preferred":[
        "\u0633\u0627\u0646\u0648\u0627\u0631"
    ],
    "name:ben_bn_x_preferred":[
        "\u09b8\u09be\u09a8\u09be\u0993\u09df\u09be\u09b0"
    ],
    "name:ben_in_x_preferred":[
        "\u09b8\u09be\u09a8\u09be\u0993\u09df\u09be\u09b0"
    ],
    "name:guj_x_preferred":[
        "\u0ab8\u0aa8\u0abe\u0ab5\u0ab0"
    ],
    "name:hin_x_preferred":[
        "\u0938\u0928\u093e\u0935\u0930"
    ],
    "name:kan_x_preferred":[
        "\u0cb8\u0ca8\u0cb5\u0cb0\u0ccd"
    ],
    "name:mal_x_preferred":[
        "\u0d38\u0d28\u0d35\u0d7c"
    ],
    "name:mar_x_preferred":[
        "\u0938\u0928\u0935\u093e\u0930"
    ],
    "name:pan_x_preferred":[
        "\u0a38\u0a28\u0a3e\u0a35\u0a30"
    ],
    "name:tam_x_preferred":[
        "\u0b9a\u0ba9\u0bb5\u0bb0\u0bcd"
    ],
    "name:tel_x_preferred":[
        "\u0c38\u0c28\u0c3e\u0c35\u0c3e\u0c30\u0c4d"
    ],
    "name:urd_x_preferred":[
        "\u0633\u0646\u0627\u0648\u0631"
    ],
    "wof:name":"Sanawar",
    "wof:placetype":"locality"
},
  "geometry": {"coordinates":[76.99398000000002,30.89414],"type":"Point"}
}