{
  "type": "Feature",
  "properties": {
    "gn:admin1_code":"24.0",
    "gn:admin2_code":"115.0",
    "gn:asciiname":"Purpuriya",
    "gn:country_code":"IN",
    "gn:dem":169,
    "gn:feature_class":"P",
    "gn:feature_code":"PPL",
    "gn:name":"Purpuriya",
    "gn:population":0,
    "gn:timezone":"Asia/Kolkata",
    "iso:country":"IN",
    "wof:name":"Purpuriya",
    "wof:placetype":"locality"
},
  "geometry": {"coordinates":[70.7488,25.64732],"type":"Point"}
}