{
  "type": "Feature",
  "properties": {
    "iso:country":"IN",
    "ks:ks_name":"Rajapur",
    "ks:ks_pop":1094,
    "ks:ks_type":"VILLAGE",
    "ks:ks_uagg_main":0,
    "name:eng_x_preferred":[
        "Rajapur"
    ],
    "wof:name":"Rajapur",
    "wof:placetype":"neighbourhood",
    "wof:population":1094
},
  "geometry": {"coordinates":[86.939717,25.079173],"type":"Point"}
}