{
  "type": "Feature",
  "properties": {
    "iso:country":"IN",
    "ks:ks_name":"Doddahitlu",
    "ks:ks_pop":74,
    "ks:ks_type":"HABITATION",
    "name:eng_x_preferred":[
        "Doddahitlu"
    ],
    "wof:name":"Doddahitlu",
    "wof:placetype":"locality",
    "wof:population":74
},
  "geometry": {"coordinates":[74.48633,14.310628],"type":"Point"}
}