{
  "type": "Feature",
  "properties": {
    "gn:admin1_code":"39.0",
    "gn:admin2_code":"60.0",
    "gn:asciiname":"Kalia",
    "gn:country_code":"IN",
    "gn:dem":1128,
    "gn:feature_class":"P",
    "gn:feature_code":"PPL",
    "gn:name":"Kalia",
    "gn:population":0,
    "gn:timezone":"Asia/Kolkata",
    "iso:country":"IN",
    "name:ceb_x_preferred":[
        "Kalia"
    ],
    "name:fra_x_preferred":[
        "Kalia"
    ],
    "name:ind_x_preferred":[
        "Kalia"
    ],
    "name:nld_x_preferred":[
        "Kalia"
    ],
    "name:swe_x_preferred":[
        "Kalia"
    ],
    "wof:name":"Kalia",
    "wof:placetype":"locality"
},
  "geometry": {"coordinates":[77.89759000000002,30.55222],"type":"Point"}
}