{
  "type": "Feature",
  "properties": {
    "iso:country":"IN",
    "ks:ks_alt_nam":"PURAB TOLA",
    "ks:ks_name":"Purab Tola",
    "ks:ks_pop":322,
    "ks:ks_type":"HABITATION",
    "name:eng_x_preferred":[
        "Purab Tola"
    ],
    "wof:name":"Purab Tola",
    "wof:placetype":"locality",
    "wof:population":322
},
  "geometry": {"coordinates":[84.331036,25.43694],"type":"Point"}
}