{
  "type": "Feature",
  "properties": {
    "gn:admin1_code":"11.0",
    "gn:asciiname":"Bori Nagli",
    "gn:country_code":"IN",
    "gn:dem":452,
    "gn:feature_class":"P",
    "gn:feature_code":"PPL",
    "gn:name":"Bori Nagli",
    "gn:population":0,
    "gn:timezone":"Asia/Kolkata",
    "iso:country":"IN",
    "ks:ks_name":"Bari Nagli",
    "ks:ks_type":"VILLAGE",
    "name:eng_x_preferred":[
        "Bari Nagli"
    ],
    "name:eng_x_variant":[
        "Bori Nagli"
    ],
    "wof:name":"Bari Nagli",
    "wof:placetype":"locality"
},
  "geometry": {"coordinates":[77.446209,30.431865],"type":"Point"}
}