{
  "type": "Feature",
  "properties": {
    "iso:country":"IN",
    "ks:ks_name":"Gadri",
    "ks:ks_pop":163,
    "ks:ks_type":"VILLAGE",
    "name:eng_x_preferred":[
        "Gadri"
    ],
    "wof:name":"Gadri",
    "wof:placetype":"locality",
    "wof:population":163
},
  "geometry": {"coordinates":[78.559757,25.795073],"type":"Point"}
}