{
  "type": "Feature",
  "properties": {
    "iso:country":"IN",
    "ks:ks_name":"Pure Baisan",
    "ks:ks_pop":381,
    "ks:ks_type":"HABITATION",
    "ks:ks_uagg_main":0,
    "name:eng_x_preferred":[
        "Pure Baisan"
    ],
    "wof:name":"Pure Baisan",
    "wof:placetype":"neighbourhood",
    "wof:population":381
},
  "geometry": {"coordinates":[81.20819899999999,26.338338],"type":"Point"}
}