{
  "type": "Feature",
  "properties": {
    "iso:country":"IN",
    "ks:ks_name":"Kandhora",
    "ks:ks_pop":72,
    "ks:ks_type":"VILLAGE",
    "name:eng_x_preferred":[
        "Kandhora"
    ],
    "wof:name":"Kandhora",
    "wof:placetype":"locality",
    "wof:population":72
},
  "geometry": {"coordinates":[68.89786700000001,23.473719],"type":"Point"}
}