{
  "type": "Feature",
  "properties": {
    "gn:admin1_code":"24.0",
    "gn:admin2_code":"113",
    "gn:asciiname":"Ghevra",
    "gn:country_code":"IN",
    "gn:dem":266,
    "gn:feature_class":"P",
    "gn:feature_code":"PPL",
    "gn:name":"Ghevra",
    "gn:population":0,
    "gn:timezone":"Asia/Kolkata",
    "iso:country":"IN",
    "name:ben_x_preferred":[
        "\u0998\u09c7\u0993\u09b0\u09be"
    ],
    "name:bpy_x_preferred":[
        "\u0998\u09c7\u0993\u09b0\u09be"
    ],
    "name:ita_x_preferred":[
        "Gheora"
    ],
    "name:msa_x_preferred":[
        "Gheora"
    ],
    "name:new_x_preferred":[
        "\u0918\u0947\u0913\u0930\u093e"
    ],
    "name:nld_x_preferred":[
        "Gheora"
    ],
    "name:por_x_preferred":[
        "Gheora"
    ],
    "name:und_x_variant":[
        "Gheura"
    ],
    "name:vie_x_preferred":[
        "Gheora"
    ],
    "name:zho_x_preferred":[
        "\u76d6\u5965\u62c9"
    ],
    "wof:name":"Ghevra",
    "wof:placetype":"locality"
},
  "geometry": {"coordinates":[72.79084,26.59476],"type":"Point"}
}