{
  "type": "Feature",
  "properties": {
    "iso:country":"IN",
    "ks:ks_name":"Govind Ka Purwa",
    "ks:ks_pop":20,
    "ks:ks_type":"HABITATION",
    "name:eng_x_preferred":[
        "Govind Ka Purwa"
    ],
    "wof:name":"Govind Ka Purwa",
    "wof:placetype":"locality",
    "wof:population":20
},
  "geometry": {"coordinates":[80.98971,25.248897],"type":"Point"}
}