{
  "type": "Feature",
  "properties": {
    "gn:admin1_code":"19.0",
    "gn:admin2_code":"581.0",
    "gn:asciiname":"Hosballahalli",
    "gn:country_code":"IN",
    "gn:dem":851,
    "gn:feature_class":"P",
    "gn:feature_code":"PPL",
    "gn:name":"Hosballahalli",
    "gn:population":0,
    "gn:timezone":"Asia/Kolkata",
    "iso:country":"IN",
    "name:und_x_variant":[
        "Haleballahalli"
    ],
    "wof:name":"Hosballahalli",
    "wof:placetype":"locality"
},
  "geometry": {"coordinates":[78.05625000000001,12.96587],"type":"Point"}
}