{
  "type": "Feature",
  "properties": {
    "iso:country":"IN",
    "ks:ks_alt_nam":"Dayoli_Dhauli",
    "ks:ks_name":"Dayoli_dhauli",
    "ks:ks_pop":73,
    "ks:ks_type":"HABITATION",
    "name:eng_x_preferred":[
        "Dayoli_dhauli"
    ],
    "wof:name":"Dayoli_dhauli",
    "wof:placetype":"locality",
    "wof:population":73
},
  "geometry": {"coordinates":[80.025811,29.255325],"type":"Point"}
}