{
  "type": "Feature",
  "properties": {
    "iso:country":"IN",
    "ks:ks_name":"Poovathani",
    "ks:ks_pop":1994,
    "ks:ks_type":"HABITATION",
    "name:eng_x_preferred":[
        "Poovathani"
    ],
    "wof:name":"Poovathani",
    "wof:placetype":"locality",
    "wof:population":1994
},
  "geometry": {"coordinates":[76.322159,10.941397],"type":"Point"}
}