{
  "type": "Feature",
  "properties": {
    "gn:admin1_code":"12.0",
    "gn:admin2_code":"005",
    "gn:asciiname":"Satharban",
    "gn:country_code":"IN",
    "gn:dem":2400,
    "gn:feature_class":"P",
    "gn:feature_code":"PPL",
    "gn:name":"Satharban",
    "gn:population":0,
    "gn:timezone":"Asia/Kolkata",
    "iso:country":"IN",
    "wof:name":"Satharban",
    "wof:placetype":"locality"
},
  "geometry": {"coordinates":[74.33145,33.88515],"type":"Point"}
}