{
  "type": "Feature",
  "properties": {
    "gn:admin1_code":"36",
    "gn:admin2_code":"188.0",
    "gn:asciiname":"Mohania",
    "gn:country_code":"IN",
    "gn:dem":73,
    "gn:feature_class":"P",
    "gn:feature_code":"PPL",
    "gn:name":"Mohania",
    "gn:population":0,
    "gn:timezone":"Asia/Kolkata",
    "iso:country":"IN",
    "name:ceb_x_preferred":[
        "Mohani\u0101"
    ],
    "name:swe_x_preferred":[
        "Mohani\u0101"
    ],
    "name:urd_x_preferred":[
        "\u0645\u0648\u06c1\u0646\u06cc\u0627"
    ],
    "wof:name":"Mohania",
    "wof:placetype":"neighbourhood"
},
  "geometry": {"coordinates":[83.46854999999999,26.34391],"type":"Point"}
}