{
  "type": "Feature",
  "properties": {
    "iso:country":"IN",
    "ks:ks_name":"Dadayapada",
    "ks:ks_pop":203,
    "ks:ks_type":"HABITATION",
    "name:eng_x_preferred":[
        "Dadayapada"
    ],
    "wof:name":"Dadayapada",
    "wof:placetype":"locality",
    "wof:population":203
},
  "geometry": {"coordinates":[73.304524,20.523976],"type":"Point"}
}