{
  "type": "Feature",
  "properties": {
    "gn:admin1_code":"35.0",
    "gn:admin2_code":"465",
    "gn:asciiname":"Chaktalao",
    "gn:country_code":"IN",
    "gn:dem":291,
    "gn:feature_class":"P",
    "gn:feature_code":"PPL",
    "gn:name":"Chaktalao",
    "gn:population":0,
    "gn:timezone":"Asia/Kolkata",
    "iso:country":"IN",
    "name:und_x_variant":[
        "Chhaktala"
    ],
    "wof:name":"Chaktalao",
    "wof:placetype":"locality"
},
  "geometry": {"coordinates":[74.17463000000002,22.09506],"type":"Point"}
}