{
  "type": "Feature",
  "properties": {
    "iso:country":"IN",
    "ks:ks_name":"Banshu Purwa",
    "ks:ks_pop":293,
    "ks:ks_type":"HABITATION",
    "ks:ks_uagg_main":0,
    "name:eng_x_preferred":[
        "Banshu Purwa"
    ],
    "wof:name":"Banshu Purwa",
    "wof:placetype":"neighbourhood",
    "wof:population":293
},
  "geometry": {"coordinates":[80.52404,25.355314],"type":"Point"}
}