{
  "type": "Feature",
  "properties": {
    "gn:admin1_code":"36.0",
    "gn:admin2_code":"152.0",
    "gn:asciiname":"Makrandpur",
    "gn:country_code":"IN",
    "gn:dem":162,
    "gn:feature_class":"P",
    "gn:feature_code":"PPL",
    "gn:name":"Makrandpur",
    "gn:population":0,
    "gn:timezone":"Asia/Kolkata",
    "iso:country":"IN",
    "name:und_x_variant":[
        "Dh\u012bmarpur"
    ],
    "wof:name":"Makrandpur",
    "wof:placetype":"neighbourhood"
},
  "geometry": {"coordinates":[79.76090000000001,28.11827],"type":"Point"}
}