{
  "type": "Feature",
  "properties": {
    "iso:country":"IN",
    "ks:ks_name":"Bodamara",
    "ks:ks_pop":0,
    "ks:ks_type":"VILLAGE",
    "name:eng_x_preferred":[
        "Bodamara"
    ],
    "wof:name":"Bodamara",
    "wof:placetype":"locality",
    "wof:population":0
},
  "geometry": {"coordinates":[87.319951,22.082505],"type":"Point"}
}