{
  "type": "Feature",
  "properties": {
    "gn:admin1_code":"36",
    "gn:admin2_code":"154.0",
    "gn:asciiname":"Barbata",
    "gn:country_code":"IN",
    "gn:dem":125,
    "gn:feature_class":"P",
    "gn:feature_code":"PPL",
    "gn:name":"Barb\u0101ta",
    "gn:population":0,
    "gn:timezone":"Asia/Kolkata",
    "iso:country":"IN",
    "name:azb_x_preferred":[
        "\u0628\u0627\u0631\u0628\u0627\u062a\u0627"
    ],
    "name:ceb_x_preferred":[
        "Barbata"
    ],
    "name:deu_x_preferred":[
        "Barbata"
    ],
    "name:epo_x_preferred":[
        "Barbata"
    ],
    "name:eus_x_preferred":[
        "Barbata"
    ],
    "name:fas_x_preferred":[
        "\u0628\u0627\u0631\u0628\u0627\u062a\u0627"
    ],
    "name:fra_x_preferred":[
        "Barbata"
    ],
    "name:hun_x_preferred":[
        "Barbata"
    ],
    "name:hye_x_preferred":[
        "\u0532\u0561\u0580\u0562\u0561\u057f\u0561"
    ],
    "name:ina_x_preferred":[
        "Barbata"
    ],
    "name:ita_x_preferred":[
        "Barbata"
    ],
    "name:jpn_x_preferred":[
        "\u30d0\u30eb\u30d0\u30fc\u30bf"
    ],
    "name:lat_x_preferred":[
        "Castrum Barbatae"
    ],
    "name:lmo_x_preferred":[
        "Barbada"
    ],
    "name:msa_x_preferred":[
        "Barbata"
    ],
    "name:nap_x_preferred":[
        "Barbata"
    ],
    "name:nld_x_preferred":[
        "Barbata"
    ],
    "name:pms_x_preferred":[
        "Barbata"
    ],
    "name:pol_x_preferred":[
        "Barbata"
    ],
    "name:por_x_preferred":[
        "Barbata"
    ],
    "name:ron_x_preferred":[
        "Barbata"
    ],
    "name:rus_x_preferred":[
        "\u0411\u0430\u0440\u0431\u0430\u0442\u0430"
    ],
    "name:scn_x_preferred":[
        "Barbata"
    ],
    "name:spa_x_preferred":[
        "Barbata"
    ],
    "name:srp_x_preferred":[
        "\u0411\u0430\u0440\u0431\u0430\u0442\u0430"
    ],
    "name:tgl_x_preferred":[
        "Barbata"
    ],
    "name:ukr_x_preferred":[
        "\u0411\u0430\u0440\u0431\u0430\u0442\u0430"
    ],
    "name:vie_x_preferred":[
        "Barbata"
    ],
    "name:vol_x_preferred":[
        "Barbata"
    ],
    "name:war_x_preferred":[
        "Barbata"
    ],
    "name:zho_x_preferred":[
        "\u5df4\u5c14\u5df4\u5854"
    ],
    "wof:name":"Barbata",
    "wof:placetype":"locality"
},
  "geometry": {"coordinates":[81.11928,27.62107],"type":"Point"}
}