{
  "type": "Feature",
  "properties": {
    "gn:admin1_code":"36",
    "gn:admin2_code":"194.0",
    "gn:asciiname":"Akhipur",
    "gn:country_code":"IN",
    "gn:dem":86,
    "gn:feature_class":"P",
    "gn:feature_code":"PPL",
    "gn:name":"Akh\u012bpur",
    "gn:population":0,
    "gn:timezone":"Asia/Kolkata",
    "iso:country":"IN",
    "ks:ks_name":"Akhaipur",
    "ks:ks_pop":600,
    "ks:ks_type":"VILLAGE",
    "name:eng_x_preferred":[
        "Akhaipur"
    ],
    "name:eng_x_variant":[
        "Akhipur"
    ],
    "wof:name":"Akhaipur",
    "wof:placetype":"locality",
    "wof:population":600
},
  "geometry": {"coordinates":[82.97405000000001,25.648822],"type":"Point"}
}