{
  "type": "Feature",
  "properties": {
    "iso:country":"IN",
    "ks:ks_name":"Buzrurchandra",
    "ks:ks_pop":508,
    "ks:ks_type":"VILLAGE",
    "ks:ks_uagg_main":0,
    "name:eng_x_preferred":[
        "Buzrurchandra"
    ],
    "wof:name":"Buzrurchandra",
    "wof:placetype":"neighbourhood",
    "wof:population":508
},
  "geometry": {"coordinates":[87.46541499999999,23.819368],"type":"Point"}
}