{
  "type": "Feature",
  "properties": {
    "iso:country":"IN",
    "ks:ks_name":"Fakiran",
    "ks:ks_pop":223,
    "ks:ks_type":"HABITATION",
    "name:eng_x_preferred":[
        "Fakiran"
    ],
    "wof:name":"Fakiran",
    "wof:placetype":"locality",
    "wof:population":223
},
  "geometry": {"coordinates":[82.61473599999999,25.637399],"type":"Point"}
}