{
  "type": "Feature",
  "properties": {
    "gn:admin1_code":"36",
    "gn:admin2_code":"171.0",
    "gn:asciiname":"Ramganj",
    "gn:country_code":"IN",
    "gn:dem":132,
    "gn:feature_class":"P",
    "gn:feature_code":"PPL",
    "gn:name":"R\u0101mganj",
    "gn:population":0,
    "gn:timezone":"Asia/Kolkata",
    "iso:country":"IN",
    "wof:name":"Ramganj",
    "wof:placetype":"locality"
},
  "geometry": {"coordinates":[80.77679999999999,25.25513],"type":"Point"}
}