{
  "type": "Feature",
  "properties": {
    "iso:country":"IN",
    "ks:ks_name":"Naudihwa",
    "ks:ks_pop":90,
    "ks:ks_type":"HABITATION",
    "ks:ks_uagg_main":0,
    "name:eng_x_preferred":[
        "Naudihwa"
    ],
    "wof:name":"Naudihwa",
    "wof:placetype":"neighbourhood",
    "wof:population":90
},
  "geometry": {"coordinates":[83.353312,26.914931],"type":"Point"}
}