{
  "type": "Feature",
  "properties": {
    "iso:country":"IN",
    "ks:ks_name":"Dera Arlok",
    "ks:ks_pop":250,
    "ks:ks_type":"HABITATION",
    "name:eng_x_preferred":[
        "Dera Arlok"
    ],
    "wof:name":"Dera Arlok",
    "wof:placetype":"locality",
    "wof:population":250
},
  "geometry": {"coordinates":[92.70581199999999,25.827967],"type":"Point"}
}