{
  "type": "Feature",
  "properties": {
    "iso:country":"IN",
    "ks:ks_name":"Bahadurpur",
    "ks:ks_pop":525,
    "ks:ks_type":"VILLAGE",
    "ks:ks_uagg_main":0,
    "name:eng_x_preferred":[
        "Bahadurpur"
    ],
    "wof:name":"Bahadurpur",
    "wof:placetype":"neighbourhood",
    "wof:population":525
},
  "geometry": {"coordinates":[86.131056,24.121978],"type":"Point"}
}