{
  "type": "Feature",
  "properties": {
    "gn:admin1_code":"36",
    "gn:admin2_code":"188.0",
    "gn:asciiname":"Chikanian",
    "gn:country_code":"IN",
    "gn:dem":82,
    "gn:feature_class":"P",
    "gn:feature_code":"PPL",
    "gn:name":"Chikani\u0101n",
    "gn:population":0,
    "gn:timezone":"Asia/Kolkata",
    "iso:country":"IN",
    "ks:ks_alt_nam":"Chikani\u0101n",
    "ks:ks_alt_nam_2":"Chikanian",
    "ks:ks_name":"Chikania",
    "ks:ks_type":"VILLAGE",
    "ks:ks_uagg_main":0,
    "name:eng_x_preferred":[
        "Chikania"
    ],
    "name:eng_x_variant":[
        "Chikani\u0101n",
        "Chikanian"
    ],
    "wof:name":"Chikania",
    "wof:placetype":"neighbourhood"
},
  "geometry": {"coordinates":[83.352861,26.350377],"type":"Point"}
}