{
  "type": "Feature",
  "properties": {
    "gn:admin1_code":"36",
    "gn:admin2_code":"176.0",
    "gn:asciiname":"Mahanpur",
    "gn:country_code":"IN",
    "gn:dem":125,
    "gn:feature_class":"P",
    "gn:feature_code":"PPL",
    "gn:name":"Mahanpur",
    "gn:population":0,
    "gn:timezone":"Asia/Kolkata",
    "iso:country":"IN",
    "name:hin_x_preferred":[
        "\u092e\u0939\u093e\u0928\u092a\u0941\u0930"
    ],
    "wof:name":"Mahanpur",
    "wof:placetype":"locality"
},
  "geometry": {"coordinates":[81.22506,27.09724000000001],"type":"Point"}
}