{
  "type": "Feature",
  "properties": {
    "iso:country":"IN",
    "ks:ks_name":"Dhadagpada",
    "ks:ks_pop":359,
    "ks:ks_type":"HABITATION",
    "name:eng_x_preferred":[
        "Dhadagpada"
    ],
    "wof:name":"Dhadagpada",
    "wof:placetype":"locality",
    "wof:population":359
},
  "geometry": {"coordinates":[72.99060799999999,19.877151],"type":"Point"}
}