{
  "type": "Feature",
  "properties": {
    "iso:country":"IN",
    "ks:ks_name":"Hanigodu",
    "ks:ks_pop":41,
    "ks:ks_type":"HABITATION",
    "name:eng_x_preferred":[
        "Hanigodu"
    ],
    "wof:name":"Hanigodu",
    "wof:placetype":"locality",
    "wof:population":41
},
  "geometry": {"coordinates":[74.978532,13.508798],"type":"Point"}
}