{
  "type": "Feature",
  "properties": {
    "iso:country":"IN",
    "ks:ks_name":"Muknakwadi",
    "ks:ks_pop":77,
    "ks:ks_type":"HABITATION",
    "name:eng_x_preferred":[
        "Muknakwadi"
    ],
    "wof:name":"Muknakwadi",
    "wof:placetype":"locality",
    "wof:population":77
},
  "geometry": {"coordinates":[73.502781,17.422703],"type":"Point"}
}