{
  "type": "Feature",
  "properties": {
    "gn:admin1_code":"36",
    "gn:admin2_code":"134.0",
    "gn:asciiname":"Bhatiana Khushhalpur",
    "gn:country_code":"IN",
    "gn:dem":237,
    "gn:feature_class":"P",
    "gn:feature_code":"PPL",
    "gn:name":"Bhati\u0101na Khushh\u0101lpur",
    "gn:population":0,
    "gn:timezone":"Asia/Kolkata",
    "iso:country":"IN",
    "wof:name":"Bhatiana Khushhalpur",
    "wof:placetype":"locality"
},
  "geometry": {"coordinates":[78.43534,29.28352000000001],"type":"Point"}
}