{
  "type": "Feature",
  "properties": {
    "iso:country":"IN",
    "ks:ks_name":"Ruikot",
    "ks:ks_type":"VILLAGE",
    "name:eng_x_preferred":[
        "Ruikot"
    ],
    "wof:name":"Ruikot",
    "wof:placetype":"locality"
},
  "geometry": {"coordinates":[78.83865,19.828537],"type":"Point"}
}