{
  "type": "Feature",
  "properties": {
    "iso:country":"IN",
    "ks:ks_name":"Navakkadu",
    "ks:ks_pop":163,
    "ks:ks_type":"HABITATION",
    "name:eng_x_preferred":[
        "Navakkadu"
    ],
    "wof:name":"Navakkadu",
    "wof:placetype":"locality",
    "wof:population":163
},
  "geometry": {"coordinates":[78.08060399999999,11.349503],"type":"Point"}
}