{
  "type": "Feature",
  "properties": {
    "iso:country":"IN",
    "ks:ks_name":"Pettai",
    "ks:ks_pop":166,
    "ks:ks_type":"HABITATION",
    "name:eng_x_preferred":[
        "Pettai"
    ],
    "wof:name":"Pettai",
    "wof:placetype":"locality",
    "wof:population":166
},
  "geometry": {"coordinates":[79.354145,10.846087],"type":"Point"}
}