{
  "type": "Feature",
  "properties": {
    "gn:admin1_code":"23.0",
    "gn:admin2_code":"36.0",
    "gn:asciiname":"Mundi",
    "gn:country_code":"IN",
    "gn:dem":213,
    "gn:feature_class":"P",
    "gn:feature_code":"PPL",
    "gn:name":"Mundi",
    "gn:population":0,
    "gn:timezone":"Asia/Kolkata",
    "iso:country":"IN",
    "name:ben_x_preferred":[
        "\u09ae\u09c1\u09a8\u09cd\u09a6\u09c0"
    ],
    "name:bpy_x_preferred":[
        "\u09ae\u09c1\u09a8\u09cd\u09a6\u09c0"
    ],
    "name:ceb_x_preferred":[
        "Mundi"
    ],
    "name:ita_x_preferred":[
        "Mundi"
    ],
    "name:mlg_x_preferred":[
        "Mundi"
    ],
    "name:msa_x_preferred":[
        "Mundi"
    ],
    "name:new_x_preferred":[
        "\u092e\u0941\u0928\u094d\u0926\u0940"
    ],
    "name:nld_x_preferred":[
        "Mundi"
    ],
    "name:ori_x_preferred":[
        "\u0b2e\u0b41\u0b28\u0b4d\u0b26\u0b3f"
    ],
    "name:por_x_preferred":[
        "Mundi"
    ],
    "name:swe_x_preferred":[
        "Mundi"
    ],
    "name:urd_x_preferred":[
        "\u0645\u0646\u0688\u06cc"
    ],
    "name:vie_x_preferred":[
        "Mundi"
    ],
    "name:zho_x_preferred":[
        "\u7a46\u6069\u8fea"
    ],
    "wof:name":"Mundi",
    "wof:placetype":"locality"
},
  "geometry": {"coordinates":[75.20829000000001,31.36748],"type":"Point"}
}