{
  "type": "Feature",
  "properties": {
    "gn:admin1_code":"36",
    "gn:admin2_code":"202.0",
    "gn:asciiname":"Dadwara",
    "gn:country_code":"IN",
    "gn:dem":170,
    "gn:feature_class":"P",
    "gn:feature_code":"PPL",
    "gn:name":"Dadw\u0101ra",
    "gn:population":0,
    "gn:timezone":"Asia/Kolkata",
    "iso:country":"IN",
    "ks:ks_alt_nam":"Dadw\u0101ra",
    "ks:ks_name":"Dadwara",
    "ks:ks_type":"VILLAGE",
    "ks:ks_uagg_main":0,
    "name:eng_x_preferred":[
        "Dadwara"
    ],
    "name:eng_x_variant":[
        "Dadw\u0101ra"
    ],
    "wof:name":"Dadwara",
    "wof:placetype":"neighbourhood"
},
  "geometry": {"coordinates":[78.74275900000001,27.711131],"type":"Point"}
}