{
  "type": "Feature",
  "properties": {
    "iso:country":"IN",
    "ks:ks_name":"Shibpur",
    "ks:ks_pop":533,
    "ks:ks_type":"HABITATION",
    "ks:ks_uagg_main":0,
    "name:eng_x_preferred":[
        "Shibpur"
    ],
    "wof:name":"Shibpur",
    "wof:placetype":"neighbourhood",
    "wof:population":533
},
  "geometry": {"coordinates":[88.264062,21.950773],"type":"Point"}
}