{
  "type": "Feature",
  "properties": {
    "iso:country":"IN",
    "ks:ks_name":"Venkatapalem",
    "ks:ks_pop":35,
    "ks:ks_type":"HABITATION",
    "name:eng_x_preferred":[
        "Venkatapalem"
    ],
    "wof:name":"Venkatapalem",
    "wof:placetype":"locality",
    "wof:population":35
},
  "geometry": {"coordinates":[82.517224,18.067915],"type":"Point"}
}