{
  "type": "Feature",
  "properties": {
    "gn:admin1_code":"35",
    "gn:admin2_code":"455.0",
    "gn:asciiname":"Dhawansi",
    "gn:country_code":"IN",
    "gn:dem":867,
    "gn:feature_class":"P",
    "gn:feature_code":"PPL",
    "gn:name":"Dhaw\u0101nsi",
    "gn:population":0,
    "gn:timezone":"Asia/Kolkata",
    "iso:country":"IN",
    "wof:name":"Dhawansi",
    "wof:placetype":"locality"
},
  "geometry": {"coordinates":[78.37987,22.35497],"type":"Point"}
}