{
  "type": "Feature",
  "properties": {
    "iso:country":"IN",
    "ks:ks_name":"Jugisol",
    "ks:ks_pop":1042,
    "ks:ks_type":"VILLAGE",
    "name:eng_x_preferred":[
        "Jugisol"
    ],
    "wof:name":"Jugisol",
    "wof:placetype":"locality",
    "wof:population":1042
},
  "geometry": {"coordinates":[87.15522199999999,21.972736],"type":"Point"}
}