{
  "type": "Feature",
  "properties": {
    "gn:admin1_code":"23",
    "gn:admin2_code":"37.0",
    "gn:asciiname":"Nahol",
    "gn:country_code":"IN",
    "gn:dem":237,
    "gn:feature_class":"P",
    "gn:feature_code":"PPL",
    "gn:name":"Nahol",
    "gn:population":0,
    "gn:timezone":"Asia/Kolkata",
    "iso:country":"IN",
    "wof:name":"Nahol",
    "wof:placetype":"locality"
},
  "geometry": {"coordinates":[75.60894,31.10986],"type":"Point"}
}