{
  "type": "Feature",
  "properties": {
    "iso:country":"IN",
    "ks:ks_name":"Melachua",
    "ks:ks_pop":146,
    "ks:ks_type":"VILLAGE",
    "name:eng_x_preferred":[
        "Melachua"
    ],
    "wof:name":"Melachua",
    "wof:placetype":"locality",
    "wof:population":146
},
  "geometry": {"coordinates":[83.52210700000001,19.832581],"type":"Point"}
}