{
  "type": "Feature",
  "properties": {
    "gn:admin1_code":"24",
    "gn:admin2_code":"123.0",
    "gn:asciiname":"Piplantri",
    "gn:country_code":"IN",
    "gn:dem":649,
    "gn:feature_class":"P",
    "gn:feature_code":"PPL",
    "gn:name":"Pipl\u0101ntri",
    "gn:population":0,
    "gn:timezone":"Asia/Kolkata",
    "iso:country":"IN",
    "name:mal_x_preferred":[
        "\u0d2a\u0d3f\u0d2a\u0d4d\u0d2a\u0d32\u0d3e\u0d28\u0d4d\u0d24\u0d4d\u0d30\u0d3f"
    ],
    "wof:name":"Piplantri",
    "wof:placetype":"neighbourhood"
},
  "geometry": {"coordinates":[73.78827,25.11231],"type":"Point"}
}