{
  "type": "Feature",
  "properties": {
    "iso:country":"IN",
    "ks:ks_name":"Chhote",
    "ks:ks_pop":74,
    "ks:ks_type":"HABITATION",
    "ks:ks_uagg_main":0,
    "name:eng_x_preferred":[
        "Chhote"
    ],
    "wof:name":"Chhote",
    "wof:placetype":"neighbourhood",
    "wof:population":74
},
  "geometry": {"coordinates":[78.299876,27.102494],"type":"Point"}
}