{
  "type": "Feature",
  "properties": {
    "gn:admin1_code":"38.0",
    "gn:admin2_code":"351.0",
    "gn:asciiname":"Malna Kita",
    "gn:country_code":"IN",
    "gn:dem":79,
    "gn:feature_class":"P",
    "gn:feature_code":"PPL",
    "gn:name":"Malna Kita",
    "gn:population":0,
    "gn:timezone":"Asia/Kolkata",
    "iso:country":"IN",
    "wof:name":"Malna Kita",
    "wof:placetype":"locality"
},
  "geometry": {"coordinates":[87.19893,24.87078],"type":"Point"}
}