{
  "type": "Feature",
  "properties": {
    "iso:country":"IN",
    "ks:ks_name":"Jamanpada Falia",
    "ks:ks_pop":382,
    "ks:ks_type":"HABITATION",
    "name:eng_x_preferred":[
        "Jamanpada Falia"
    ],
    "wof:name":"Jamanpada Falia",
    "wof:placetype":"locality",
    "wof:population":382
},
  "geometry": {"coordinates":[73.18002799999999,20.256222],"type":"Point"}
}