{
  "type": "Feature",
  "properties": {
    "gn:admin1_code":"35.0",
    "gn:admin2_code":"454.0",
    "gn:asciiname":"Jhigarhata",
    "gn:country_code":"IN",
    "gn:dem":517,
    "gn:feature_class":"P",
    "gn:feature_code":"PPL",
    "gn:name":"Jhigarhat\u0101",
    "gn:population":0,
    "gn:timezone":"Asia/Kolkata",
    "iso:country":"IN",
    "ks:ks_name":"Jhigar Ghata",
    "ks:ks_pop":413,
    "ks:ks_type":"VILLAGE",
    "name:eng_x_preferred":[
        "Jhigar Ghata"
    ],
    "name:eng_x_variant":[
        "Jhigarhata"
    ],
    "wof:name":"Jhigar Ghata",
    "wof:placetype":"locality",
    "wof:population":413
},
  "geometry": {"coordinates":[80.67613799999999,22.698231],"type":"Point"}
}