{
  "type": "Feature",
  "properties": {
    "gn:admin1_code":"11",
    "gn:admin2_code":"27.0",
    "gn:asciiname":"Sai",
    "gn:country_code":"IN",
    "gn:dem":1129,
    "gn:feature_class":"P",
    "gn:feature_code":"PPL",
    "gn:name":"S\u0101i",
    "gn:population":0,
    "gn:timezone":"Asia/Kolkata",
    "iso:country":"IN",
    "name:ara_x_preferred":[
        "\u0633\u0627\u064a"
    ],
    "name:cat_x_preferred":[
        "Sai"
    ],
    "name:cdo_x_preferred":[
        "S\u0103i"
    ],
    "name:ceb_x_preferred":[
        "Sai"
    ],
    "name:est_x_preferred":[
        "Sai"
    ],
    "name:fra_x_preferred":[
        "Sai"
    ],
    "name:ind_x_preferred":[
        "Sai"
    ],
    "name:msa_x_preferred":[
        "Sai"
    ],
    "name:nld_x_preferred":[
        "Sai"
    ],
    "name:pol_x_preferred":[
        "Sai"
    ],
    "name:por_x_preferred":[
        "Sai"
    ],
    "name:spa_x_preferred":[
        "Sai"
    ],
    "name:swe_x_preferred":[
        "Sai"
    ],
    "wof:name":"Sai",
    "wof:placetype":"locality"
},
  "geometry": {"coordinates":[76.90178,31.74585],"type":"Point"}
}