{
  "type": "Feature",
  "properties": {
    "gn:admin1_code":"11",
    "gn:admin2_code":"27.0",
    "gn:asciiname":"Sai",
    "gn:country_code":"IN",
    "gn:dem":1129,
    "gn:feature_class":"P",
    "gn:feature_code":"PPL",
    "gn:name":"S\u0101i",
    "gn:population":0,
    "gn:timezone":"Asia/Kolkata",
    "iso:country":"IN",
    "wof:name":"Sai",
    "wof:placetype":"locality"
},
  "geometry": {"coordinates":[76.90178,31.74585],"type":"Point"}
}