{
  "type": "Feature",
  "properties": {
    "iso:country":"IN",
    "ks:ks_name":"Puluguvandlapalli",
    "ks:ks_pop":13,
    "ks:ks_type":"HABITATION",
    "name:eng_x_preferred":[
        "Puluguvandlapalli"
    ],
    "wof:name":"Puluguvandlapalli",
    "wof:placetype":"locality",
    "wof:population":13
},
  "geometry": {"coordinates":[78.82521800000001,14.130203],"type":"Point"}
}