{
  "type": "Feature",
  "properties": {
    "gn:admin1_code":"2.0",
    "gn:asciiname":"Karambar",
    "gn:country_code":"IN",
    "gn:dem":653,
    "gn:feature_class":"P",
    "gn:feature_code":"PPL",
    "gn:name":"Karambar",
    "gn:population":0,
    "gn:timezone":"Asia/Kolkata",
    "iso:country":"IN",
    "wof:name":"Karambar",
    "wof:placetype":"locality"
},
  "geometry": {"coordinates":[78.67954,13.01542],"type":"Point"}
}