{
  "type": "Feature",
  "properties": {
    "iso:country":"IN",
    "ks:ks_name":"Kainbili",
    "ks:ks_pop":257,
    "ks:ks_type":"HABITATION",
    "name:eng_x_preferred":[
        "Kainbili"
    ],
    "wof:name":"Kainbili",
    "wof:placetype":"locality",
    "wof:population":257
},
  "geometry": {"coordinates":[85.508391,20.921979],"type":"Point"}
}