{
  "type": "Feature",
  "properties": {
    "gn:admin1_code":"28.0",
    "gn:admin2_code":"330.0",
    "gn:asciiname":"Matiari",
    "gn:country_code":"IN",
    "gn:dem":42,
    "gn:feature_class":"P",
    "gn:feature_code":"PPL",
    "gn:name":"Mati\u0101ri",
    "gn:population":0,
    "gn:timezone":"Asia/Kolkata",
    "iso:country":"IN",
    "name:ceb_x_preferred":[
        "Mati\u0101ri"
    ],
    "name:fas_x_preferred":[
        "\u0645\u062a\u06cc\u0627\u0631\u06cc"
    ],
    "name:fra_x_preferred":[
        "Matiari"
    ],
    "name:pnb_x_preferred":[
        "\u0645\u0679\u06cc\u0627\u0631\u06cc"
    ],
    "name:rus_x_preferred":[
        "\u041c\u0430\u0442\u0438\u044f\u0440\u0438"
    ],
    "name:snd_x_preferred":[
        "\u0645\u067d\u064a\u0627\u0631\u064a"
    ],
    "name:swe_x_preferred":[
        "Matiari"
    ],
    "name:urd_x_preferred":[
        "\u0645\u0679\u06cc\u0627\u0631\u06cc"
    ],
    "wof:name":"Matiari",
    "wof:placetype":"locality"
},
  "geometry": {"coordinates":[87.87441,25.9085],"type":"Point"}
}