{
  "type": "Feature",
  "properties": {
    "iso:country":"IN",
    "ks:ks_alt_nam":"DHARWARIYAPUR",
    "ks:ks_name":"Dharwariyapur",
    "ks:ks_pop":62,
    "ks:ks_type":"HABITATION",
    "ks:ks_uagg_main":0,
    "name:eng_x_preferred":[
        "Dharwariyapur"
    ],
    "wof:name":"Dharwariyapur",
    "wof:placetype":"neighbourhood",
    "wof:population":62
},
  "geometry": {"coordinates":[81.76959100000001,26.246693],"type":"Point"}
}