{
  "type": "Feature",
  "properties": {
    "gn:admin1_code":"11",
    "gn:admin2_code":"23.0",
    "gn:asciiname":"Beroti",
    "gn:country_code":"IN",
    "gn:dem":1329,
    "gn:feature_class":"P",
    "gn:feature_code":"PPL",
    "gn:name":"Beroti",
    "gn:population":0,
    "gn:timezone":"Asia/Kolkata",
    "iso:country":"IN",
    "wof:name":"Beroti",
    "wof:placetype":"locality"
},
  "geometry": {"coordinates":[76.07831999999998,32.7437],"type":"Point"}
}