{
  "type": "Feature",
  "properties": {
    "iso:country":"IN",
    "ks:ks_name":"Kaniajan No 2",
    "ks:ks_pop":145,
    "ks:ks_type":"VILLAGE",
    "ks:ks_uagg_main":0,
    "name:eng_x_preferred":[
        "Kaniajan No 2"
    ],
    "wof:name":"Kaniajan No 2",
    "wof:placetype":"neighbourhood",
    "wof:population":145
},
  "geometry": {"coordinates":[94.04394000000001,26.987417],"type":"Point"}
}