{
  "type": "Feature",
  "properties": {
    "gn:admin1_code":"12.0",
    "gn:admin2_code":"1.0",
    "gn:asciiname":"Chandankhal",
    "gn:country_code":"IN",
    "gn:dem":2967,
    "gn:feature_class":"P",
    "gn:feature_code":"PPL",
    "gn:name":"Chandankhal",
    "gn:population":0,
    "gn:timezone":"Asia/Kolkata",
    "iso:country":"IN",
    "wof:name":"Chandankhal",
    "wof:placetype":"locality"
},
  "geometry": {"coordinates":[74.41768,34.58016],"type":"Point"}
}