{
  "type": "Feature",
  "properties": {
    "gn:admin1_code":"34",
    "gn:admin2_code":"234.0",
    "gn:asciiname":"Magajpura",
    "gn:country_code":"IN",
    "gn:dem":109,
    "gn:feature_class":"P",
    "gn:feature_code":"PPL",
    "gn:name":"Magajpura",
    "gn:population":0,
    "gn:timezone":"Asia/Kolkata",
    "iso:country":"IN",
    "ks:ks_name":"Magajpura",
    "ks:ks_pop":788,
    "ks:ks_type":"VILLAGE",
    "name:eng_x_preferred":[
        "Magajpura"
    ],
    "wof:name":"Magajpura",
    "wof:placetype":"locality",
    "wof:population":788
},
  "geometry": {"coordinates":[83.85166099999999,24.853385],"type":"Point"}
}