{
  "type": "Feature",
  "properties": {
    "gn:admin1_code":"39",
    "gn:admin2_code":"61.0",
    "gn:asciiname":"Bangajhalun",
    "gn:country_code":"IN",
    "gn:dem":1735,
    "gn:feature_class":"P",
    "gn:feature_code":"PPL",
    "gn:name":"Bang\u0101jh\u0101l\u016bn",
    "gn:population":0,
    "gn:timezone":"Asia/Kolkata",
    "iso:country":"IN",
    "wof:name":"Bangajhalun",
    "wof:placetype":"locality"
},
  "geometry": {"coordinates":[78.97196,29.92413],"type":"Point"}
}