{
  "type": "Feature",
  "properties": {
    "iso:country":"IN",
    "ks:ks_name":"Ambalag",
    "ks:ks_pop":1223,
    "ks:ks_type":"VILLAGE",
    "name:eng_x_preferred":[
        "Ambalag"
    ],
    "wof:name":"Ambalag",
    "wof:placetype":"locality",
    "wof:population":1223
},
  "geometry": {"coordinates":[73.919434,22.15659],"type":"Point"}
}