{
  "type": "Feature",
  "properties": {
    "gn:admin1_code":"16.0",
    "gn:admin2_code":"508.0",
    "gn:asciiname":"Haldi",
    "gn:country_code":"IN",
    "gn:dem":178,
    "gn:feature_class":"P",
    "gn:feature_code":"PPL",
    "gn:name":"Haldi",
    "gn:population":0,
    "gn:timezone":"Asia/Kolkata",
    "iso:country":"IN",
    "name:ceb_x_preferred":[
        "Haldi"
    ],
    "name:deu_x_preferred":[
        "Haldi"
    ],
    "name:sco_x_preferred":[
        "Haldi"
    ],
    "name:swe_x_preferred":[
        "Haldi"
    ],
    "wof:name":"Haldi",
    "wof:placetype":"locality"
},
  "geometry": {"coordinates":[79.78945,19.86126],"type":"Point"}
}