{
  "type": "Feature",
  "properties": {
    "gn:admin1_code":"35",
    "gn:admin2_code":"427.0",
    "gn:asciiname":"Mehar",
    "gn:country_code":"IN",
    "gn:dem":480,
    "gn:feature_class":"P",
    "gn:feature_code":"PPL",
    "gn:name":"Mehar",
    "gn:population":0,
    "gn:timezone":"Asia/Kolkata",
    "iso:country":"IN",
    "name:hin_x_preferred":[
        "\u092e\u0947\u0939\u0930"
    ],
    "name:pnb_x_preferred":[
        "\u0645\u06be\u0631"
    ],
    "wof:name":"Mehar",
    "wof:placetype":"locality"
},
  "geometry": {"coordinates":[78.6588,23.98672],"type":"Point"}
}