{
  "type": "Feature",
  "properties": {
    "iso:country":"IN",
    "ks:ks_name":"Moolagadu",
    "ks:ks_pop":26,
    "ks:ks_type":"HABITATION",
    "name:eng_x_preferred":[
        "Moolagadu"
    ],
    "wof:name":"Moolagadu",
    "wof:placetype":"locality",
    "wof:population":26
},
  "geometry": {"coordinates":[78.413212,11.345364],"type":"Point"}
}