{
  "type": "Feature",
  "properties": {
    "iso:country":"IN",
    "ks:ks_name":"Madhurapilli",
    "ks:ks_pop":508,
    "ks:ks_type":"HABITATION",
    "name:eng_x_preferred":[
        "Madhurapilli"
    ],
    "wof:name":"Madhurapilli",
    "wof:placetype":"locality",
    "wof:population":508
},
  "geometry": {"coordinates":[76.151826,10.356829],"type":"Point"}
}