{
  "type": "Feature",
  "properties": {
    "iso:country":"IN",
    "ks:ks_name":"Chhat Panisala",
    "ks:ks_pop":390,
    "ks:ks_type":"VILLAGE",
    "name:eng_x_preferred":[
        "Chhat Panisala"
    ],
    "wof:name":"Chhat Panisala",
    "wof:placetype":"locality",
    "wof:population":390
},
  "geometry": {"coordinates":[89.533107,26.25321],"type":"Point"}
}