{
  "type": "Feature",
  "properties": {
    "iso:country":"IN",
    "ks:ks_name":"Hematpur",
    "ks:ks_pop":1505,
    "ks:ks_type":"VILLAGE",
    "name:eng_x_preferred":[
        "Hematpur"
    ],
    "wof:name":"Hematpur",
    "wof:placetype":"locality",
    "wof:population":1505
},
  "geometry": {"coordinates":[85.743028,23.54565],"type":"Point"}
}