{
  "type": "Feature",
  "properties": {
    "gn:admin1_code":"11",
    "gn:admin2_code":"30.0",
    "gn:asciiname":"Majhari",
    "gn:country_code":"IN",
    "gn:dem":1090,
    "gn:feature_class":"P",
    "gn:feature_code":"PPL",
    "gn:name":"Majh\u0101ri",
    "gn:population":0,
    "gn:timezone":"Asia/Kolkata",
    "iso:country":"IN",
    "wof:name":"Majhari",
    "wof:placetype":"locality"
},
  "geometry": {"coordinates":[76.89816,31.30066],"type":"Point"}
}