{
  "type": "Feature",
  "properties": {
    "iso:country":"IN",
    "ks:ks_name":"Anaguni",
    "ks:ks_pop":83,
    "ks:ks_type":"HABITATION",
    "name:eng_x_preferred":[
        "Anaguni"
    ],
    "wof:name":"Anaguni",
    "wof:placetype":"locality",
    "wof:population":83
},
  "geometry": {"coordinates":[74.818457,14.69067],"type":"Point"}
}