{
  "type": "Feature",
  "properties": {
    "iso:country":"IN",
    "ks:ks_name":"Rangamati",
    "ks:ks_pop":354,
    "ks:ks_type":"HABITATION",
    "name:eng_x_preferred":[
        "Rangamati"
    ],
    "wof:name":"Rangamati",
    "wof:placetype":"locality",
    "wof:population":354
},
  "geometry": {"coordinates":[84.355441,22.509444],"type":"Point"}
}