{
  "type": "Feature",
  "properties": {
    "iso:country":"IN",
    "ks:ks_name":"Naini Mahar",
    "ks:ks_pop":111,
    "ks:ks_type":"VILLAGE",
    "name:eng_x_preferred":[
        "Naini Mahar"
    ],
    "wof:name":"Naini Mahar",
    "wof:placetype":"locality",
    "wof:population":111
},
  "geometry": {"coordinates":[80.11913800000001,29.442678],"type":"Point"}
}