{
  "type": "Feature",
  "properties": {
    "iso:country":"IN",
    "ks:ks_alt_nam":"KAPARPHUTUWA",
    "ks:ks_name":"Kaparphutuwa",
    "ks:ks_pop":540,
    "ks:ks_type":"HABITATION",
    "name:eng_x_preferred":[
        "Kaparphutuwa"
    ],
    "wof:name":"Kaparphutuwa",
    "wof:placetype":"locality",
    "wof:population":540
},
  "geometry": {"coordinates":[85.467508,23.727854],"type":"Point"}
}