{
  "type": "Feature",
  "properties": {
    "iso:country":"IN",
    "ks:ks_name":"Japandih",
    "ks:ks_pop":135,
    "ks:ks_type":"HABITATION",
    "name:eng_x_preferred":[
        "Japandih"
    ],
    "wof:name":"Japandih",
    "wof:placetype":"locality",
    "wof:population":135
},
  "geometry": {"coordinates":[85.512019,22.93865],"type":"Point"}
}