{
  "type": "Feature",
  "properties": {
    "iso:country":"IN",
    "ks:ks_name":"Narasimharajapura Agraharam",
    "ks:ks_pop":2998,
    "ks:ks_type":"VILLAGE",
    "ks:ks_uagg_main":0,
    "name:eng_x_preferred":[
        "Narasimharajapura Agraharam"
    ],
    "wof:name":"Narasimharajapura Agraharam",
    "wof:placetype":"neighbourhood",
    "wof:population":2998
},
  "geometry": {"coordinates":[81.47366100000001,16.582998],"type":"Point"}
}