{
  "type": "Feature",
  "properties": {
    "gn:admin1_code":"16",
    "gn:admin2_code":"531.0",
    "gn:asciiname":"Lakda",
    "gn:country_code":"IN",
    "gn:dem":577,
    "gn:feature_class":"P",
    "gn:feature_code":"PPL",
    "gn:name":"Lakda",
    "gn:population":0,
    "gn:timezone":"Asia/Kolkata",
    "iso:country":"IN",
    "wof:name":"Lakda",
    "wof:placetype":"locality"
},
  "geometry": {"coordinates":[75.41667,17.18333],"type":"Point"}
}