{
  "type": "Feature",
  "properties": {
    "iso:country":"IN",
    "ks:ks_name":"Gondipeta",
    "ks:ks_pop":150,
    "ks:ks_type":"HABITATION",
    "name:eng_x_preferred":[
        "Gondipeta"
    ],
    "wof:name":"Gondipeta",
    "wof:placetype":"locality",
    "wof:population":150
},
  "geometry": {"coordinates":[82.74199400000001,18.116239],"type":"Point"}
}