{
  "type": "Feature",
  "properties": {
    "gn:admin1_code":"16.0",
    "gn:admin2_code":"505",
    "gn:asciiname":"Dighori Buzurg",
    "gn:country_code":"IN",
    "gn:dem":279,
    "gn:feature_class":"P",
    "gn:feature_code":"PPL",
    "gn:name":"Dighori Buzurg",
    "gn:population":0,
    "gn:timezone":"Asia/Kolkata",
    "iso:country":"IN",
    "name:und_x_variant":[
        "Dighori",
        "Dighori Buzurg"
    ],
    "wof:name":"Dighori Buzurg",
    "wof:placetype":"locality"
},
  "geometry": {"coordinates":[79.23005999999999,21.11759],"type":"Point"}
}