{
  "type": "Feature",
  "properties": {
    "gn:admin1_code":"21",
    "gn:admin2_code":"394.0",
    "gn:asciiname":"Dargaon",
    "gn:country_code":"IN",
    "gn:dem":257,
    "gn:feature_class":"P",
    "gn:feature_code":"PPL",
    "gn:name":"Dargaon",
    "gn:population":0,
    "gn:timezone":"Asia/Kolkata",
    "iso:country":"IN",
    "ks:ks_name":"Daragaon",
    "ks:ks_pop":1250,
    "ks:ks_type":"VILLAGE",
    "name:eng_x_preferred":[
        "Daragaon"
    ],
    "name:eng_x_variant":[
        "Dargaon"
    ],
    "wof:name":"Daragaon",
    "wof:placetype":"locality",
    "wof:population":1250
},
  "geometry": {"coordinates":[82.63992500000001,20.390463],"type":"Point"}
}