{
  "type": "Feature",
  "properties": {
    "gn:admin1_code":"36",
    "gn:admin2_code":"143.0",
    "gn:asciiname":"Jatanpur Chakawati",
    "gn:country_code":"IN",
    "gn:dem":194,
    "gn:feature_class":"P",
    "gn:feature_code":"PPL",
    "gn:name":"Jatanpur Chak\u0101wati",
    "gn:population":0,
    "gn:timezone":"Asia/Kolkata",
    "iso:country":"IN",
    "wof:name":"Jatanpur Chakawati",
    "wof:placetype":"locality"
},
  "geometry": {"coordinates":[78.01361,27.91237000000001],"type":"Point"}
}