{
  "type": "Feature",
  "properties": {
    "iso:country":"IN",
    "ks:ks_name":"Singapatna",
    "ks:ks_pop":324,
    "ks:ks_type":"VILLAGE",
    "name:eng_x_preferred":[
        "Singapatna"
    ],
    "wof:name":"Singapatna",
    "wof:placetype":"locality",
    "wof:population":324
},
  "geometry": {"coordinates":[76.312602,11.936173],"type":"Point"}
}