{
  "type": "Feature",
  "properties": {
    "iso:country":"IN",
    "ks:ks_name":"Newachh",
    "ks:ks_pop":188,
    "ks:ks_type":"VILLAGE",
    "name:eng_x_preferred":[
        "Newachh"
    ],
    "wof:name":"Newachh",
    "wof:placetype":"locality",
    "wof:population":188
},
  "geometry": {"coordinates":[81.82338900000001,23.500783],"type":"Point"}
}