{
  "type": "Feature",
  "properties": {
    "iso:country":"IN",
    "ks:ks_name":"Huvina Ane",
    "ks:ks_pop":4,
    "ks:ks_type":"VILLAGE",
    "ks:ks_uagg_main":0,
    "name:eng_x_preferred":[
        "Huvina Ane"
    ],
    "wof:name":"Huvina Ane",
    "wof:placetype":"locality",
    "wof:population":4
},
  "geometry": {"coordinates":[77.703656,13.054003],"type":"Point"}
}