{
  "type": "Feature",
  "properties": {
    "gn:admin1_code":"40.0",
    "gn:admin2_code":"537",
    "gn:asciiname":"Parweda",
    "gn:country_code":"IN",
    "gn:dem":615,
    "gn:feature_class":"P",
    "gn:feature_code":"PPL",
    "gn:name":"Parweda",
    "gn:population":0,
    "gn:timezone":"Asia/Kolkata",
    "iso:country":"IN",
    "wof:name":"Parweda",
    "wof:placetype":"neighbourhood"
},
  "geometry": {"coordinates":[78.09941000000001,17.40644],"type":"Point"}
}