{
  "type": "Feature",
  "properties": {
    "gn:admin1_code":"34.0",
    "gn:admin2_code":"212.0",
    "gn:asciiname":"Kumhra",
    "gn:country_code":"IN",
    "gn:dem":39,
    "gn:feature_class":"P",
    "gn:feature_code":"PPL",
    "gn:name":"Kumhra",
    "gn:population":0,
    "gn:timezone":"Asia/Kolkata",
    "iso:country":"IN",
    "wof:name":"Kumhra",
    "wof:placetype":"locality"
},
  "geometry": {"coordinates":[87.47766,25.6713],"type":"Point"}
}