{
  "type": "Feature",
  "properties": {
    "gn:admin1_code":"9.0",
    "gn:admin2_code":"476",
    "gn:asciiname":"Ghunada",
    "gn:country_code":"IN",
    "gn:dem":40,
    "gn:feature_class":"P",
    "gn:feature_code":"PPL",
    "gn:name":"Ghunada",
    "gn:population":0,
    "gn:timezone":"Asia/Kolkata",
    "iso:country":"IN",
    "wof:name":"Ghunada",
    "wof:placetype":"neighbourhood"
},
  "geometry": {"coordinates":[70.63428,22.69288],"type":"Point"}
}