{
  "type": "Feature",
  "properties": {
    "iso:country":"IN",
    "ks:ks_name":"Vadakeghatta",
    "ks:ks_pop":737,
    "ks:ks_type":"HABITATION",
    "name:eng_x_preferred":[
        "Vadakeghatta"
    ],
    "wof:name":"Vadakeghatta",
    "wof:placetype":"locality",
    "wof:population":737
},
  "geometry": {"coordinates":[76.638902,13.026244],"type":"Point"}
}