{
  "type": "Feature",
  "properties": {
    "iso:country":"IN",
    "ks:ks_name":"Romai Bongali Gaon",
    "ks:ks_pop":788,
    "ks:ks_type":"HABITATION",
    "name:eng_x_preferred":[
        "Romai Bongali Gaon"
    ],
    "wof:name":"Romai Bongali Gaon",
    "wof:placetype":"locality",
    "wof:population":788
},
  "geometry": {"coordinates":[95.053793,27.403836],"type":"Point"}
}