{
  "type": "Feature",
  "properties": {
    "gn:admin1_code":"36",
    "gn:admin2_code":"172.0",
    "gn:asciiname":"Kasiyapur",
    "gn:country_code":"IN",
    "gn:dem":122,
    "gn:feature_class":"P",
    "gn:feature_code":"PPL",
    "gn:name":"Kasiy\u0101pur",
    "gn:population":0,
    "gn:timezone":"Asia/Kolkata",
    "iso:country":"IN",
    "wof:name":"Kasiyapur",
    "wof:placetype":"locality"
},
  "geometry": {"coordinates":[80.50813000000002,25.94166],"type":"Point"}
}