{
  "type": "Feature",
  "properties": {
    "iso:country":"IN",
    "ks:ks_alt_nam":"Tilaiy\u0101",
    "ks:ks_name":"Tilaiya",
    "ks:ks_pop":1561,
    "ks:ks_type":"VILLAGE",
    "name:eng_x_preferred":[
        "Tilaiya"
    ],
    "name:eng_x_variant":[
        "Tilaiy\u0101"
    ],
    "wof:name":"Tilaiya",
    "wof:placetype":"locality",
    "wof:population":1561
},
  "geometry": {"coordinates":[85.952172,23.582288],"type":"Point"}
}