{
  "type": "Feature",
  "properties": {
    "gn:admin1_code":"36.0",
    "gn:admin2_code":"189.0",
    "gn:asciiname":"Amhi",
    "gn:country_code":"IN",
    "gn:dem":86,
    "gn:feature_class":"P",
    "gn:feature_code":"PPL",
    "gn:name":"Amhi",
    "gn:population":0,
    "gn:timezone":"Asia/Kolkata",
    "iso:country":"IN",
    "ks:ks_name":"Amhi",
    "ks:ks_type":"VILLAGE",
    "name:eng_x_preferred":[
        "Amhi"
    ],
    "wof:name":"Amhi",
    "wof:placetype":"locality"
},
  "geometry": {"coordinates":[84.113472,26.790415],"type":"Point"}
}