{
  "type": "Feature",
  "properties": {
    "iso:country":"IN",
    "ks:ks_name":"Heggar",
    "ks:ks_pop":63,
    "ks:ks_type":"HABITATION",
    "name:eng_x_preferred":[
        "Heggar"
    ],
    "wof:name":"Heggar",
    "wof:placetype":"locality",
    "wof:population":63
},
  "geometry": {"coordinates":[74.42616599999999,14.687653],"type":"Point"}
}