{
  "type": "Feature",
  "properties": {
    "gn:admin1_code":"23",
    "gn:admin2_code":"35.0",
    "gn:asciiname":"Phulra",
    "gn:country_code":"IN",
    "gn:dem":235,
    "gn:feature_class":"P",
    "gn:feature_code":"PPL",
    "gn:name":"Phulra",
    "gn:population":0,
    "gn:timezone":"Asia/Kolkata",
    "iso:country":"IN",
    "name:cat_x_preferred":[
        "Phulra"
    ],
    "name:ita_x_preferred":[
        "Phulra"
    ],
    "name:urd_x_preferred":[
        "\u0631\u06cc\u0627\u0633\u062a \u067e\u06be\u0644\u0631\u0627"
    ],
    "wof:name":"Phulra",
    "wof:placetype":"locality"
},
  "geometry": {"coordinates":[75.56304,31.78488],"type":"Point"}
}