{
  "type": "Feature",
  "properties": {
    "gn:admin1_code":"35",
    "gn:admin2_code":"447.0",
    "gn:asciiname":"Khaprabari",
    "gn:country_code":"IN",
    "gn:dem":638,
    "gn:feature_class":"P",
    "gn:feature_code":"PPL",
    "gn:name":"Khapr\u0101b\u0101ri",
    "gn:population":0,
    "gn:timezone":"Asia/Kolkata",
    "iso:country":"IN",
    "ks:ks_name":"Khaprawadi",
    "ks:ks_pop":256,
    "ks:ks_type":"VILLAGE",
    "name:eng_x_preferred":[
        "Khaprawadi"
    ],
    "name:eng_x_variant":[
        "Khaprabari"
    ],
    "wof:name":"Khaprawadi",
    "wof:placetype":"locality",
    "wof:population":256
},
  "geometry": {"coordinates":[77.61561500000001,22.144309],"type":"Point"}
}