{
  "type": "Feature",
  "properties": {
    "gn:admin1_code":"2.0",
    "gn:admin2_code":"544.0",
    "gn:asciiname":"Torolosingo",
    "gn:country_code":"IN",
    "gn:dem":969,
    "gn:feature_class":"P",
    "gn:feature_code":"PPL",
    "gn:name":"Torolosingo",
    "gn:population":0,
    "gn:timezone":"Asia/Kolkata",
    "iso:country":"IN",
    "wof:name":"Torolosingo",
    "wof:placetype":"locality"
},
  "geometry": {"coordinates":[82.47400999999998,18.18162],"type":"Point"}
}