{
  "type": "Feature",
  "properties": {
    "iso:country":"IN",
    "ks:ks_alt_nam":"KuthirakulamE",
    "ks:ks_name":"Kuthirakulame",
    "ks:ks_pop":273,
    "ks:ks_type":"HABITATION",
    "name:eng_x_preferred":[
        "Kuthirakulame"
    ],
    "wof:name":"Kuthirakulame",
    "wof:placetype":"locality",
    "wof:population":273
},
  "geometry": {"coordinates":[76.932036,8.664469],"type":"Point"}
}