{
  "type": "Feature",
  "properties": {
    "iso:country":"IN",
    "ks:ks_name":"Mahinagar",
    "ks:ks_pop":2655,
    "ks:ks_type":"VILLAGE",
    "ks:ks_uagg_main":0,
    "name:eng_x_preferred":[
        "Mahinagar"
    ],
    "wof:name":"Mahinagar",
    "wof:placetype":"locality",
    "wof:population":2655
},
  "geometry": {"coordinates":[88.345675,25.674742],"type":"Point"}
}