{
  "type": "Feature",
  "properties": {
    "gn:admin1_code":"36",
    "gn:admin2_code":"179.0",
    "gn:asciiname":"Piarepur",
    "gn:country_code":"IN",
    "gn:dem":94,
    "gn:feature_class":"P",
    "gn:feature_code":"PPL",
    "gn:name":"Pi\u0101repur",
    "gn:population":0,
    "gn:timezone":"Asia/Kolkata",
    "iso:country":"IN",
    "ks:ks_name":"Piyare Pur",
    "ks:ks_pop":576,
    "ks:ks_type":"VILLAGE",
    "ks:ks_uagg_main":0,
    "name:eng_x_preferred":[
        "Piyare Pur"
    ],
    "wof:name":"Piyare Pur",
    "wof:placetype":"neighbourhood",
    "wof:population":576
},
  "geometry": {"coordinates":[82.240247,26.056626],"type":"Point"}
}