{
  "type": "Feature",
  "properties": {
    "iso:country":"IN",
    "ks:ks_name":"Ghagwadi",
    "ks:ks_pop":76,
    "ks:ks_type":"HABITATION",
    "name:eng_x_preferred":[
        "Ghagwadi"
    ],
    "wof:name":"Ghagwadi",
    "wof:placetype":"locality",
    "wof:population":76
},
  "geometry": {"coordinates":[73.104692,17.829906],"type":"Point"}
}