{
  "type": "Feature",
  "properties": {
    "gn:admin1_code":"19.0",
    "gn:admin2_code":"571.0",
    "gn:asciiname":"Muggondanahalli",
    "gn:country_code":"IN",
    "gn:dem":755,
    "gn:feature_class":"P",
    "gn:feature_code":"PPL",
    "gn:name":"Muggondanahalli",
    "gn:population":0,
    "gn:timezone":"Asia/Kolkata",
    "iso:country":"IN",
    "wof:name":"Muggondanahalli",
    "wof:placetype":"locality"
},
  "geometry": {"coordinates":[77.24195,13.55902],"type":"Point"}
}