{
  "type": "Feature",
  "properties": {
    "gn:admin1_code":"39.0",
    "gn:admin2_code":"64.0",
    "gn:asciiname":"Gwaldeh",
    "gn:country_code":"IN",
    "gn:dem":1467,
    "gn:feature_class":"P",
    "gn:feature_code":"PPL",
    "gn:name":"Gw\u0101ldeh",
    "gn:population":0,
    "gn:timezone":"Asia/Kolkata",
    "iso:country":"IN",
    "ks:ks_alt_nam":"Gw\u0101ldeh",
    "ks:ks_name":"Gwaldeh",
    "ks:ks_pop":251,
    "ks:ks_type":"VILLAGE",
    "ks:ks_uagg_main":0,
    "name:eng_x_preferred":[
        "Gwaldeh"
    ],
    "name:eng_x_variant":[
        "Gw\u0101ldeh"
    ],
    "wof:name":"Gwaldeh",
    "wof:placetype":"neighbourhood",
    "wof:population":251
},
  "geometry": {"coordinates":[79.404051,29.610851],"type":"Point"}
}