{
  "type": "Feature",
  "properties": {
    "gn:admin1_code":"36",
    "gn:admin2_code":"179.0",
    "gn:asciiname":"Pura Dhanesargir",
    "gn:country_code":"IN",
    "gn:dem":110,
    "gn:feature_class":"P",
    "gn:feature_code":"PPL",
    "gn:name":"Pura Dhanesargir",
    "gn:population":0,
    "gn:timezone":"Asia/Kolkata",
    "iso:country":"IN",
    "wof:name":"Pura Dhanesargir",
    "wof:placetype":"locality"
},
  "geometry": {"coordinates":[81.56610999999999,26.32657],"type":"Point"}
}