{
  "type": "Feature",
  "properties": {
    "iso:country":"IN",
    "ks:ks_name":"Sukanbil 2",
    "ks:ks_pop":270,
    "ks:ks_type":"HABITATION",
    "name:eng_x_preferred":[
        "Sukanbil 2"
    ],
    "wof:name":"Sukanbil 2",
    "wof:placetype":"locality",
    "wof:population":270
},
  "geometry": {"coordinates":[94.004007,26.245053],"type":"Point"}
}