{
  "type": "Feature",
  "properties": {
    "iso:country":"IN",
    "ks:ks_name":"Taralinga",
    "ks:ks_pop":325,
    "ks:ks_type":"VILLAGE",
    "name:eng_x_preferred":[
        "Taralinga"
    ],
    "wof:name":"Taralinga",
    "wof:placetype":"locality",
    "wof:population":325
},
  "geometry": {"coordinates":[83.667401,19.288371],"type":"Point"}
}