{
  "type": "Feature",
  "properties": {
    "iso:country":"IN",
    "ks:ks_alt_nam":"NAGLA JAMAN",
    "ks:ks_name":"Nagla Jaman",
    "ks:ks_pop":110,
    "ks:ks_type":"HABITATION",
    "name:eng_x_preferred":[
        "Nagla Jaman"
    ],
    "wof:name":"Nagla Jaman",
    "wof:placetype":"locality",
    "wof:population":110
},
  "geometry": {"coordinates":[79.308032,26.893481],"type":"Point"}
}