{
  "type": "Feature",
  "properties": {
    "iso:country":"IN",
    "ks:ks_name":"Hasidi",
    "ks:ks_pop":28,
    "ks:ks_type":"HABITATION",
    "name:eng_x_preferred":[
        "Hasidi"
    ],
    "wof:name":"Hasidi",
    "wof:placetype":"locality",
    "wof:population":28
},
  "geometry": {"coordinates":[75.309911,13.553175],"type":"Point"}
}