{
  "type": "Feature",
  "properties": {
    "gn:admin1_code":"21.0",
    "gn:admin2_code":"377.0",
    "gn:asciiname":"Munida",
    "gn:country_code":"IN",
    "gn:dem":32,
    "gn:feature_class":"P",
    "gn:feature_code":"PPL",
    "gn:name":"Munida",
    "gn:population":0,
    "gn:timezone":"Asia/Kolkata",
    "iso:country":"IN",
    "name:ceb_x_preferred":[
        "Munida"
    ],
    "name:fra_x_preferred":[
        "Munida"
    ],
    "name:ita_x_preferred":[
        "Munida"
    ],
    "name:nld_x_preferred":[
        "Munida"
    ],
    "name:spa_x_preferred":[
        "Munida"
    ],
    "name:swe_x_preferred":[
        "Munida"
    ],
    "name:war_x_preferred":[
        "Munida"
    ],
    "wof:name":"Munida",
    "wof:placetype":"locality"
},
  "geometry": {"coordinates":[86.55395,21.31941],"type":"Point"}
}