{
  "type": "Feature",
  "properties": {
    "gn:admin1_code":"34.0",
    "gn:admin2_code":"203.0",
    "gn:asciiname":"Tola Majhariya",
    "gn:country_code":"IN",
    "gn:dem":88,
    "gn:feature_class":"P",
    "gn:feature_code":"PPL",
    "gn:name":"Tola Majhariy\u0101",
    "gn:population":0,
    "gn:timezone":"Asia/Kolkata",
    "iso:country":"IN",
    "ks:ks_name":"Tola Majharia",
    "ks:ks_pop":545,
    "ks:ks_type":"VILLAGE",
    "name:eng_x_preferred":[
        "Tola Majharia"
    ],
    "name:eng_x_variant":[
        "Tola Majhariya"
    ],
    "wof:name":"Tola Majharia",
    "wof:placetype":"locality",
    "wof:population":545
},
  "geometry": {"coordinates":[84.28463600000001,26.981764],"type":"Point"}
}