{
  "type": "Feature",
  "properties": {
    "iso:country":"IN",
    "ks:ks_name":"Addagadde",
    "ks:ks_pop":142,
    "ks:ks_type":"HABITATION",
    "name:eng_x_preferred":[
        "Addagadde"
    ],
    "wof:name":"Addagadde",
    "wof:placetype":"locality",
    "wof:population":142
},
  "geometry": {"coordinates":[75.269637,13.460008],"type":"Point"}
}