{
  "type": "Feature",
  "properties": {
    "gn:admin1_code":"23.0",
    "gn:admin2_code":"43.0",
    "gn:asciiname":"Chak Khuranj",
    "gn:country_code":"IN",
    "gn:dem":187,
    "gn:feature_class":"P",
    "gn:feature_code":"PPL",
    "gn:name":"Chak Khuranj",
    "gn:population":0,
    "gn:timezone":"Asia/Kolkata",
    "iso:country":"IN",
    "name:und_x_variant":[
        "Kh\u0101new\u0101la"
    ],
    "wof:name":"Chak Khuranj",
    "wof:placetype":"locality"
},
  "geometry": {"coordinates":[74.30558000000001,30.4767],"type":"Point"}
}