{
  "type": "Feature",
  "properties": {
    "iso:country":"IN",
    "ks:ks_name":"Kolamala",
    "ks:ks_pop":198,
    "ks:ks_type":"HABITATION",
    "name:eng_x_preferred":[
        "Kolamala"
    ],
    "wof:name":"Kolamala",
    "wof:placetype":"locality",
    "wof:population":198
},
  "geometry": {"coordinates":[76.86802900000001,9.378665],"type":"Point"}
}