{
  "type": "Feature",
  "properties": {
    "iso:country":"IN",
    "ks:ks_name":"Dharampur",
    "ks:ks_pop":1276,
    "ks:ks_type":"VILLAGE",
    "ks:ks_uagg_main":0,
    "name:eng_x_preferred":[
        "Dharampur"
    ],
    "wof:name":"Dharampur",
    "wof:placetype":"neighbourhood",
    "wof:population":1276
},
  "geometry": {"coordinates":[83.052691,23.307407],"type":"Point"}
}