{
  "type": "Feature",
  "properties": {
    "iso:country":"IN",
    "ks:ks_name":"Bhojaparu",
    "ks:ks_pop":410,
    "ks:ks_type":"HABITATION",
    "name:eng_x_preferred":[
        "Bhojaparu"
    ],
    "wof:name":"Bhojaparu",
    "wof:placetype":"locality",
    "wof:population":410
},
  "geometry": {"coordinates":[72.32544300000001,23.832175],"type":"Point"}
}