{
  "type": "Feature",
  "properties": {
    "gn:admin1_code":"34.0",
    "gn:admin2_code":"217.0",
    "gn:asciiname":"Chak Manjhan",
    "gn:country_code":"IN",
    "gn:dem":70,
    "gn:feature_class":"P",
    "gn:feature_code":"PPL",
    "gn:name":"Chak Manjhan",
    "gn:population":0,
    "gn:timezone":"Asia/Kolkata",
    "iso:country":"IN",
    "ks:ks_name":"Chak Manjhan",
    "ks:ks_pop":808,
    "ks:ks_type":"VILLAGE",
    "ks:ks_uagg_main":0,
    "name:eng_x_preferred":[
        "Chak Manjhan"
    ],
    "wof:name":"Chak Manjhan",
    "wof:placetype":"neighbourhood",
    "wof:population":808
},
  "geometry": {"coordinates":[84.54227400000001,26.333355],"type":"Point"}
}