{
  "type": "Feature",
  "properties": {
    "iso:country":"IN",
    "ks:ks_name":"Paisiya Urf Konghusari",
    "ks:ks_pop":839,
    "ks:ks_type":"VILLAGE",
    "ks:ks_uagg_main":0,
    "name:eng_x_preferred":[
        "Paisiya Urf Konghusari"
    ],
    "wof:name":"Paisiya Urf Konghusari",
    "wof:placetype":"neighbourhood",
    "wof:population":839
},
  "geometry": {"coordinates":[83.442166,27.344159],"type":"Point"}
}