{
  "type": "Feature",
  "properties": {
    "gn:admin1_code":"25.0",
    "gn:admin2_code":"620",
    "gn:asciiname":"Ammani Chattram",
    "gn:country_code":"IN",
    "gn:dem":5,
    "gn:feature_class":"P",
    "gn:feature_code":"PPL",
    "gn:name":"Ammani Chattram",
    "gn:population":0,
    "gn:timezone":"Asia/Kolkata",
    "iso:country":"IN",
    "name:und_x_variant":[
        "Ammanitchatram",
        "Ammani Chattram"
    ],
    "wof:name":"Ammani Chattram",
    "wof:placetype":"locality"
},
  "geometry": {"coordinates":[79.25359,10.20777],"type":"Point"}
}