{
  "type": "Feature",
  "properties": {
    "iso:country":"IN",
    "ks:ks_name":"Anjaraba",
    "ks:ks_pop":184,
    "ks:ks_type":"VILLAGE",
    "name:eng_x_preferred":[
        "Anjaraba"
    ],
    "wof:name":"Anjaraba",
    "wof:placetype":"locality",
    "wof:population":184
},
  "geometry": {"coordinates":[84.330347,19.039363],"type":"Point"}
}