{
  "type": "Feature",
  "properties": {
    "iso:country":"IN",
    "ks:ks_name":"Rana Tola",
    "ks:ks_pop":148,
    "ks:ks_type":"HABITATION",
    "name:eng_x_preferred":[
        "Rana Tola"
    ],
    "wof:name":"Rana Tola",
    "wof:placetype":"locality",
    "wof:population":148
},
  "geometry": {"coordinates":[86.23392,24.29338],"type":"Point"}
}