{
  "type": "Feature",
  "properties": {
    "gn:admin1_code":"2.0",
    "gn:admin2_code":"542.0",
    "gn:asciiname":"Rangavalasa",
    "gn:country_code":"IN",
    "gn:dem":911,
    "gn:feature_class":"P",
    "gn:feature_code":"PPL",
    "gn:name":"Rangavalasa",
    "gn:population":0,
    "gn:timezone":"Asia/Kolkata",
    "iso:country":"IN",
    "ks:ks_name":"Rangamvalasa",
    "ks:ks_pop":64,
    "ks:ks_type":"HABITATION",
    "name:eng_x_preferred":[
        "Rangamvalasa"
    ],
    "name:eng_x_variant":[
        "Rangavalasa"
    ],
    "wof:name":"Rangamvalasa",
    "wof:placetype":"locality",
    "wof:population":64
},
  "geometry": {"coordinates":[83.797729,18.818569],"type":"Point"}
}