{
  "type": "Feature",
  "properties": {
    "gn:admin1_code":"2.0",
    "gn:admin2_code":"542.0",
    "gn:asciiname":"Rangavalasa",
    "gn:country_code":"IN",
    "gn:dem":911,
    "gn:feature_class":"P",
    "gn:feature_code":"PPL",
    "gn:name":"Rangavalasa",
    "gn:population":0,
    "gn:timezone":"Asia/Kolkata",
    "iso:country":"IN",
    "wof:name":"Rangavalasa",
    "wof:placetype":"locality"
},
  "geometry": {"coordinates":[83.8027,18.82071],"type":"Point"}
}