{
  "type": "Feature",
  "properties": {
    "gn:admin1_code":"19",
    "gn:admin2_code":"555.0",
    "gn:asciiname":"Mamdapur",
    "gn:country_code":"IN",
    "gn:dem":580,
    "gn:feature_class":"P",
    "gn:feature_code":"PPL",
    "gn:name":"Mamd\u0101pur",
    "gn:population":0,
    "gn:timezone":"Asia/Kolkata",
    "iso:country":"IN",
    "name:und_x_variant":[
        "Mamd\u0101pur",
        "Momd\u0101pur"
    ],
    "wof:name":"Mamdapur",
    "wof:placetype":"locality"
},
  "geometry": {"coordinates":[74.93083,16.11122],"type":"Point"}
}