{
  "type": "Feature",
  "properties": {
    "iso:country":"IN",
    "ks:ks_name":"Paduumpur Khas",
    "ks:ks_pop":761,
    "ks:ks_type":"HABITATION",
    "name:eng_x_preferred":[
        "Paduumpur Khas"
    ],
    "wof:name":"Paduumpur Khas",
    "wof:placetype":"locality",
    "wof:population":761
},
  "geometry": {"coordinates":[82.668316,25.788827],"type":"Point"}
}