{
  "type": "Feature",
  "properties": {
    "iso:country":"IN",
    "ks:ks_name":"Kotarichhapar",
    "ks:ks_pop":121,
    "ks:ks_type":"HABITATION",
    "name:eng_x_preferred":[
        "Kotarichhapar"
    ],
    "wof:name":"Kotarichhapar",
    "wof:placetype":"locality",
    "wof:population":121
},
  "geometry": {"coordinates":[81.01323499999999,21.565334],"type":"Point"}
}