{
  "type": "Feature",
  "properties": {
    "iso:country":"IN",
    "ks:ks_name":"Nangla",
    "ks:ks_pop":26,
    "ks:ks_type":"VILLAGE",
    "name:eng_x_preferred":[
        "Nangla"
    ],
    "wof:name":"Nangla",
    "wof:placetype":"locality",
    "wof:population":26
},
  "geometry": {"coordinates":[86.990583,23.368512],"type":"Point"}
}