{
  "type": "Feature",
  "properties": {
    "gn:admin1_code":"19.0",
    "gn:admin2_code":"581.0",
    "gn:asciiname":"Tulampalli",
    "gn:country_code":"IN",
    "gn:dem":790,
    "gn:feature_class":"P",
    "gn:feature_code":"PPL",
    "gn:name":"Tulampalli",
    "gn:population":0,
    "gn:timezone":"Asia/Kolkata",
    "iso:country":"IN",
    "wof:name":"Tulampalli",
    "wof:placetype":"locality"
},
  "geometry": {"coordinates":[78.23461999999998,12.85658],"type":"Point"}
}