{
  "type": "Feature",
  "properties": {
    "iso:country":"IN",
    "ks:ks_alt_nam":"Chinapuvalasa colony",
    "ks:ks_name":"Chinapuvalasa Colony",
    "ks:ks_pop":55,
    "ks:ks_type":"HABITATION",
    "name:eng_x_preferred":[
        "Chinapuvalasa Colony"
    ],
    "wof:name":"Chinapuvalasa Colony",
    "wof:placetype":"locality",
    "wof:population":55
},
  "geometry": {"coordinates":[83.45823900000001,18.762738],"type":"Point"}
}