{
  "type": "Feature",
  "properties": {
    "iso:country":"IN",
    "ks:ks_name":"Mahtodih",
    "ks:ks_pop":108,
    "ks:ks_type":"VILLAGE",
    "ks:ks_uagg_main":0,
    "name:eng_x_preferred":[
        "Mahtodih"
    ],
    "wof:name":"Mahtodih",
    "wof:placetype":"locality",
    "wof:population":108
},
  "geometry": {"coordinates":[86.341702,24.146767],"type":"Point"}
}