{
  "type": "Feature",
  "properties": {
    "iso:country":"IN",
    "ks:ks_name":"Ubhale",
    "ks:ks_pop":617,
    "ks:ks_type":"VILLAGE",
    "name:eng_x_preferred":[
        "Ubhale"
    ],
    "wof:name":"Ubhale",
    "wof:placetype":"locality",
    "wof:population":617
},
  "geometry": {"coordinates":[73.364356,17.431045],"type":"Point"}
}