{
  "type": "Feature",
  "properties": {
    "iso:country":"IN",
    "ks:ks_name":"Khalachiwadi",
    "ks:ks_pop":105,
    "ks:ks_type":"HABITATION",
    "name:eng_x_preferred":[
        "Khalachiwadi"
    ],
    "wof:name":"Khalachiwadi",
    "wof:placetype":"locality",
    "wof:population":105
},
  "geometry": {"coordinates":[73.51472200000001,17.159444],"type":"Point"}
}