{
  "type": "Feature",
  "properties": {
    "iso:country":"IN",
    "ks:ks_name":"Tola Jharna",
    "ks:ks_pop":243,
    "ks:ks_type":"VILLAGE",
    "name:eng_x_preferred":[
        "Tola Jharna"
    ],
    "wof:name":"Tola Jharna",
    "wof:placetype":"locality",
    "wof:population":243
},
  "geometry": {"coordinates":[86.483909,24.919371],"type":"Point"}
}