{
  "type": "Feature",
  "properties": {
    "iso:country":"IN",
    "ks:ks_alt_nam":"dhanaiya",
    "ks:ks_name":"Dhanaiya",
    "ks:ks_pop":156,
    "ks:ks_type":"HABITATION",
    "ks:ks_uagg_main":0,
    "name:eng_x_preferred":[
        "Dhanaiya"
    ],
    "wof:name":"Dhanaiya",
    "wof:placetype":"neighbourhood",
    "wof:population":156
},
  "geometry": {"coordinates":[80.42789999999999,26.470833],"type":"Point"}
}