{
  "type": "Feature",
  "properties": {
    "iso:country":"IN",
    "ks:ks_name":"Mahdewadand",
    "ks:ks_pop":22,
    "ks:ks_type":"HABITATION",
    "name:eng_x_preferred":[
        "Mahdewadand"
    ],
    "wof:name":"Mahdewadand",
    "wof:placetype":"locality",
    "wof:population":22
},
  "geometry": {"coordinates":[82.63548,24.604808],"type":"Point"}
}