{
  "type": "Feature",
  "properties": {
    "iso:country":"IN",
    "ks:ks_name":"Paravelikuzhy",
    "ks:ks_pop":718,
    "ks:ks_type":"HABITATION",
    "name:eng_x_preferred":[
        "Paravelikuzhy"
    ],
    "wof:name":"Paravelikuzhy",
    "wof:placetype":"locality",
    "wof:population":718
},
  "geometry": {"coordinates":[76.44579400000001,9.920318],"type":"Point"}
}