{
  "type": "Feature",
  "properties": {
    "iso:country":"IN",
    "ks:ks_name":"Damodarpur",
    "ks:ks_pop":213,
    "ks:ks_type":"VILLAGE",
    "name:eng_x_preferred":[
        "Damodarpur"
    ],
    "wof:name":"Damodarpur",
    "wof:placetype":"locality",
    "wof:population":213
},
  "geometry": {"coordinates":[86.82111500000001,22.954876],"type":"Point"}
}