{
  "type": "Feature",
  "properties": {
    "gn:admin1_code":"38.0",
    "gn:admin2_code":"352.0",
    "gn:asciiname":"Gorda",
    "gn:country_code":"IN",
    "gn:dem":87,
    "gn:feature_class":"P",
    "gn:feature_code":"PPL",
    "gn:name":"Gorda",
    "gn:population":0,
    "gn:timezone":"Asia/Kolkata",
    "iso:country":"IN",
    "ks:ks_name":"Gorda",
    "ks:ks_pop":702,
    "ks:ks_type":"VILLAGE",
    "name:eng_x_preferred":[
        "Gorda"
    ],
    "name:spa_x_preferred":[
        "Gorda"
    ],
    "wof:name":"Gorda",
    "wof:placetype":"locality",
    "wof:population":702
},
  "geometry": {"coordinates":[87.634906,25.068722],"type":"Point"}
}