{
  "type": "Feature",
  "properties": {
    "gn:admin1_code":"38.0",
    "gn:admin2_code":"352.0",
    "gn:asciiname":"Gorda",
    "gn:country_code":"IN",
    "gn:dem":87,
    "gn:feature_class":"P",
    "gn:feature_code":"PPL",
    "gn:name":"Gorda",
    "gn:population":0,
    "gn:timezone":"Asia/Kolkata",
    "iso:country":"IN",
    "wof:name":"Gorda",
    "wof:placetype":"locality"
},
  "geometry": {"coordinates":[87.63490999999998,25.06872000000001],"type":"Point"}
}