{
  "type": "Feature",
  "properties": {
    "iso:country":"IN",
    "ks:ks_name":"Dabbakota",
    "ks:ks_pop":286,
    "ks:ks_type":"HABITATION",
    "name:eng_x_preferred":[
        "Dabbakota"
    ],
    "wof:name":"Dabbakota",
    "wof:placetype":"locality",
    "wof:population":286
},
  "geometry": {"coordinates":[82.113159,18.014622],"type":"Point"}
}