{
  "type": "Feature",
  "properties": {
    "iso:country":"IN",
    "ks:ks_name":"Telin Purwa",
    "ks:ks_pop":292,
    "ks:ks_type":"HABITATION",
    "name:eng_x_preferred":[
        "Telin Purwa"
    ],
    "wof:name":"Telin Purwa",
    "wof:placetype":"locality",
    "wof:population":292
},
  "geometry": {"coordinates":[81.868025,27.868767],"type":"Point"}
}