{
  "type": "Feature",
  "properties": {
    "iso:country":"IN",
    "ks:ks_name":"Gadla Gird",
    "ks:ks_pop":857,
    "ks:ks_type":"VILLAGE",
    "name:eng_x_preferred":[
        "Gadla Gird"
    ],
    "wof:name":"Gadla Gird",
    "wof:placetype":"locality",
    "wof:population":857
},
  "geometry": {"coordinates":[77.331648,24.578701],"type":"Point"}
}