{
  "type": "Feature",
  "properties": {
    "iso:country":"IN",
    "ks:ks_alt_nam":"Jhinkib\u0101h\u0101l",
    "ks:ks_name":"Jhinkibahal",
    "ks:ks_type":"VILLAGE",
    "name:eng_x_preferred":[
        "Jhinkibahal"
    ],
    "name:eng_x_variant":[
        "Jhinkib\u0101h\u0101l"
    ],
    "wof:name":"Jhinkibahal",
    "wof:placetype":"locality"
},
  "geometry": {"coordinates":[84.42947599999999,21.023019],"type":"Point"}
}