{
  "type": "Feature",
  "properties": {
    "iso:country":"IN",
    "ks:ks_name":"Bhimaganga",
    "ks:ks_pop":73,
    "ks:ks_type":"HABITATION",
    "name:eng_x_preferred":[
        "Bhimaganga"
    ],
    "wof:name":"Bhimaganga",
    "wof:placetype":"locality",
    "wof:population":73
},
  "geometry": {"coordinates":[84.701362,21.605426],"type":"Point"}
}