{
  "type": "Feature",
  "properties": {
    "iso:country":"IN",
    "ks:ks_name":"Chamruti",
    "ks:ks_pop":598,
    "ks:ks_type":"HABITATION",
    "name:eng_x_preferred":[
        "Chamruti"
    ],
    "wof:name":"Chamruti",
    "wof:placetype":"locality",
    "wof:population":598
},
  "geometry": {"coordinates":[82.13223000000001,25.31448],"type":"Point"}
}