{
  "type": "Feature",
  "properties": {
    "iso:country":"IN",
    "ks:ks_name":"Madrua Patti Awa",
    "ks:ks_pop":255,
    "ks:ks_type":"VILLAGE",
    "name:eng_x_preferred":[
        "Madrua Patti Awa"
    ],
    "wof:name":"Madrua Patti Awa",
    "wof:placetype":"locality",
    "wof:population":255
},
  "geometry": {"coordinates":[79.545174,27.987836],"type":"Point"}
}