{
  "type": "Feature",
  "properties": {
    "iso:country":"IN",
    "ks:ks_name":"Kedibana",
    "ks:ks_pop":165,
    "ks:ks_type":"HABITATION",
    "name:eng_x_preferred":[
        "Kedibana"
    ],
    "wof:name":"Kedibana",
    "wof:placetype":"locality",
    "wof:population":165
},
  "geometry": {"coordinates":[75.55588,12.673934],"type":"Point"}
}