{
  "type": "Feature",
  "properties": {
    "iso:country":"IN",
    "ks:ks_name":"Dharampur Ram Rae",
    "ks:ks_pop":272,
    "ks:ks_type":"VILLAGE",
    "name:eng_x_preferred":[
        "Dharampur Ram Rae"
    ],
    "wof:name":"Dharampur Ram Rae",
    "wof:placetype":"locality",
    "wof:population":272
},
  "geometry": {"coordinates":[85.381428,25.637456],"type":"Point"}
}