{
  "type": "Feature",
  "properties": {
    "gn:admin1_code":"36",
    "gn:admin2_code":"153.0",
    "gn:asciiname":"Sikandarabad",
    "gn:country_code":"IN",
    "gn:dem":158,
    "gn:feature_class":"P",
    "gn:feature_code":"PPL",
    "gn:name":"Sikandar\u0101b\u0101d",
    "gn:population":0,
    "gn:timezone":"Asia/Kolkata",
    "iso:country":"IN",
    "name:und_x_variant":[
        "Sikanderabad",
        "Sikandar\u0101b\u0101d"
    ],
    "wof:name":"Sikandarabad",
    "wof:placetype":"locality"
},
  "geometry": {"coordinates":[80.49521999999997,27.9571],"type":"Point"}
}