{
  "type": "Feature",
  "properties": {
    "iso:country":"IN",
    "ks:ks_name":"Marak Para",
    "ks:ks_pop":382,
    "ks:ks_type":"HABITATION",
    "name:eng_x_preferred":[
        "Marak Para"
    ],
    "wof:name":"Marak Para",
    "wof:placetype":"locality",
    "wof:population":382
},
  "geometry": {"coordinates":[91.464759,23.445304],"type":"Point"}
}