{
  "type": "Feature",
  "properties": {
    "iso:country":"IN",
    "ks:ks_name":"Chaphyachiwadi",
    "ks:ks_pop":205,
    "ks:ks_type":"HABITATION",
    "name:eng_x_preferred":[
        "Chaphyachiwadi"
    ],
    "wof:name":"Chaphyachiwadi",
    "wof:placetype":"locality",
    "wof:population":205
},
  "geometry": {"coordinates":[73.24798,19.113819],"type":"Point"}
}