{
  "type": "Feature",
  "properties": {
    "gn:admin1_code":"35",
    "gn:admin2_code":"462.0",
    "gn:asciiname":"Chamradol",
    "gn:country_code":"IN",
    "gn:dem":328,
    "gn:feature_class":"P",
    "gn:feature_code":"PPL",
    "gn:name":"Chamr\u0101dol",
    "gn:population":0,
    "gn:timezone":"Asia/Kolkata",
    "iso:country":"IN",
    "ks:ks_alt_nam":"Chamr\u0101dol",
    "ks:ks_name":"Chamradol",
    "ks:ks_pop":2354,
    "ks:ks_type":"VILLAGE",
    "name:eng_x_preferred":[
        "Chamradol"
    ],
    "name:eng_x_variant":[
        "Chamr\u0101dol"
    ],
    "wof:name":"Chamradol",
    "wof:placetype":"locality",
    "wof:population":2354
},
  "geometry": {"coordinates":[81.529966,24.123122],"type":"Point"}
}