{
  "type": "Feature",
  "properties": {
    "gn:admin1_code":"36.0",
    "gn:admin2_code":"142.0",
    "gn:asciiname":"Shivnathgarhi",
    "gn:country_code":"IN",
    "gn:dem":208,
    "gn:feature_class":"P",
    "gn:feature_code":"PPL",
    "gn:name":"Shivn\u0101thgarhi",
    "gn:population":0,
    "gn:timezone":"Asia/Kolkata",
    "iso:country":"IN",
    "wof:name":"Shivnathgarhi",
    "wof:placetype":"locality"
},
  "geometry": {"coordinates":[77.70692,28.4749],"type":"Point"}
}