{
  "type": "Feature",
  "properties": {
    "iso:country":"IN",
    "ks:ks_name":"Nirwattikodla",
    "ks:ks_pop":114,
    "ks:ks_type":"HABITATION",
    "name:eng_x_preferred":[
        "Nirwattikodla"
    ],
    "wof:name":"Nirwattikodla",
    "wof:placetype":"locality",
    "wof:population":114
},
  "geometry": {"coordinates":[74.49343399999999,14.296668],"type":"Point"}
}