{
  "type": "Feature",
  "properties": {
    "gn:admin1_code":"12.0",
    "gn:admin2_code":"005",
    "gn:asciiname":"Dhabrot",
    "gn:country_code":"IN",
    "gn:dem":1384,
    "gn:feature_class":"P",
    "gn:feature_code":"PPL",
    "gn:name":"Dhabrot",
    "gn:population":0,
    "gn:timezone":"Asia/Kolkata",
    "iso:country":"IN",
    "wof:name":"Dhabrot",
    "wof:placetype":"locality"
},
  "geometry": {"coordinates":[74.23172,33.5161],"type":"Point"}
}