{
  "type": "Feature",
  "properties": {
    "iso:country":"IN",
    "ks:ks_name":"Nawada",
    "ks:ks_pop":2022,
    "ks:ks_type":"VILLAGE",
    "name:eng_x_preferred":[
        "Nawada"
    ],
    "wof:name":"Nawada",
    "wof:placetype":"locality",
    "wof:population":2022
},
  "geometry": {"coordinates":[85.454832,26.068979],"type":"Point"}
}