{
  "type": "Feature",
  "properties": {
    "gn:admin1_code":"36.0",
    "gn:admin2_code":"153.0",
    "gn:asciiname":"Kalli",
    "gn:country_code":"IN",
    "gn:dem":153,
    "gn:feature_class":"P",
    "gn:feature_code":"PPL",
    "gn:name":"Kalli",
    "gn:population":0,
    "gn:timezone":"Asia/Kolkata",
    "iso:country":"IN",
    "name:ceb_x_preferred":[
        "Kalli"
    ],
    "name:deu_x_preferred":[
        "Kalli"
    ],
    "name:swe_x_preferred":[
        "Kalli"
    ],
    "name:vol_x_preferred":[
        "Kalli"
    ],
    "wof:name":"Kalli",
    "wof:placetype":"neighbourhood"
},
  "geometry": {"coordinates":[80.39196,27.81117],"type":"Point"}
}