{
  "type": "Feature",
  "properties": {
    "iso:country":"IN",
    "ks:ks_name":"Srirampur",
    "ks:ks_pop":15,
    "ks:ks_type":"VILLAGE",
    "name:eng_x_preferred":[
        "Srirampur"
    ],
    "wof:name":"Srirampur",
    "wof:placetype":"locality",
    "wof:population":15
},
  "geometry": {"coordinates":[87.2015,21.818188],"type":"Point"}
}