{
  "type": "Feature",
  "properties": {
    "gn:admin1_code":"38.0",
    "gn:admin2_code":"362.0",
    "gn:asciiname":"Beldanga",
    "gn:country_code":"IN",
    "gn:dem":77,
    "gn:feature_class":"P",
    "gn:feature_code":"PPL",
    "gn:name":"Beld\u0101nga",
    "gn:population":0,
    "gn:timezone":"Asia/Kolkata",
    "iso:country":"IN",
    "name:ben_x_preferred":[
        "\u09ac\u09c7\u09b2\u09a1\u09be\u0999\u09be"
    ],
    "name:bpy_x_preferred":[
        "\u09ac\u09c7\u09b2\u09a1\u09be\u0999\u09be"
    ],
    "name:ceb_x_preferred":[
        "Beld\u0101nga"
    ],
    "name:fra_x_preferred":[
        "Beldanga"
    ],
    "name:ita_x_preferred":[
        "Beldanga"
    ],
    "name:msa_x_preferred":[
        "Beldanga"
    ],
    "name:new_x_preferred":[
        "\u092c\u0947\u0932\u094d\u0926\u0902\u0917\u093e"
    ],
    "name:por_x_preferred":[
        "Beldanga"
    ],
    "name:spa_x_preferred":[
        "Beldanga"
    ],
    "name:swe_x_preferred":[
        "Beld\u0101nga"
    ],
    "name:vie_x_preferred":[
        "Beldanga"
    ],
    "name:zho_x_preferred":[
        "\u8d1d\u5c14\u5f53\u683c\u963f"
    ],
    "wof:name":"Beldanga",
    "wof:placetype":"locality"
},
  "geometry": {"coordinates":[87.54001,24.09747],"type":"Point"}
}