{
  "type": "Feature",
  "properties": {
    "iso:country":"IN",
    "ks:ks_name":"Reddibai",
    "ks:ks_pop":15,
    "ks:ks_type":"HABITATION",
    "name:eng_x_preferred":[
        "Reddibai"
    ],
    "wof:name":"Reddibai",
    "wof:placetype":"locality",
    "wof:population":15
},
  "geometry": {"coordinates":[79.137602,17.398756],"type":"Point"}
}