{
  "type": "Feature",
  "properties": {
    "iso:country":"IN",
    "ks:ks_name":"Kaashidih",
    "ks:ks_pop":113,
    "ks:ks_type":"HABITATION",
    "name:eng_x_preferred":[
        "Kaashidih"
    ],
    "wof:name":"Kaashidih",
    "wof:placetype":"locality",
    "wof:population":113
},
  "geometry": {"coordinates":[86.188354,22.991999],"type":"Point"}
}