{
  "type": "Feature",
  "properties": {
    "iso:country":"IN",
    "ks:ks_name":"Kancherlavaripalli",
    "ks:ks_pop":74,
    "ks:ks_type":"HABITATION",
    "name:eng_x_preferred":[
        "Kancherlavaripalli"
    ],
    "wof:name":"Kancherlavaripalli",
    "wof:placetype":"locality",
    "wof:population":74
},
  "geometry": {"coordinates":[79.45120199999999,15.397505],"type":"Point"}
}