{
  "type": "Feature",
  "properties": {
    "iso:country":"IN",
    "ks:ks_name":"Laxmipur",
    "ks:ks_pop":78,
    "ks:ks_type":"HABITATION",
    "name:eng_x_preferred":[
        "Laxmipur"
    ],
    "wof:name":"Laxmipur",
    "wof:placetype":"locality",
    "wof:population":78
},
  "geometry": {"coordinates":[82.028536,18.078023],"type":"Point"}
}