{
  "type": "Feature",
  "properties": {
    "iso:country":"IN",
    "ks:ks_name":"Tumadikasa",
    "ks:ks_pop":480,
    "ks:ks_type":"VILLAGE",
    "name:eng_x_preferred":[
        "Tumadikasa"
    ],
    "wof:name":"Tumadikasa",
    "wof:placetype":"locality",
    "wof:population":480
},
  "geometry": {"coordinates":[80.512263,20.9125],"type":"Point"}
}