{
  "type": "Feature",
  "properties": {
    "iso:country":"IN",
    "ks:ks_alt_nam":"wangapada",
    "ks:ks_name":"Wangapada",
    "ks:ks_pop":253,
    "ks:ks_type":"HABITATION",
    "name:eng_x_preferred":[
        "Wangapada"
    ],
    "wof:name":"Wangapada",
    "wof:placetype":"locality",
    "wof:population":253
},
  "geometry": {"coordinates":[72.83430199999999,19.845062],"type":"Point"}
}