{
  "type": "Feature",
  "properties": {
    "iso:country":"IN",
    "ks:ks_name":"Diguvavaddepalle",
    "ks:ks_pop":24,
    "ks:ks_type":"HABITATION",
    "ks:ks_uagg_main":0,
    "name:eng_x_preferred":[
        "Diguvavaddepalle"
    ],
    "wof:name":"Diguvavaddepalle",
    "wof:placetype":"neighbourhood",
    "wof:population":24
},
  "geometry": {"coordinates":[78.59541,14.085469],"type":"Point"}
}