{
  "type": "Feature",
  "properties": {
    "iso:country":"IN",
    "ks:ks_name":"Nardiya",
    "ks:ks_pop":157,
    "ks:ks_type":"VILLAGE",
    "name:eng_x_preferred":[
        "Nardiya"
    ],
    "wof:name":"Nardiya",
    "wof:placetype":"locality",
    "wof:population":157
},
  "geometry": {"coordinates":[74.61300799999999,24.568408],"type":"Point"}
}