{
  "type": "Feature",
  "properties": {
    "gn:admin1_code":"36.0",
    "gn:admin2_code":"189.0",
    "gn:asciiname":"Latwa Murlidhar",
    "gn:country_code":"IN",
    "gn:dem":81,
    "gn:feature_class":"P",
    "gn:feature_code":"PPL",
    "gn:name":"Latw\u0101 Murlidhar",
    "gn:population":0,
    "gn:timezone":"Asia/Kolkata",
    "iso:country":"IN",
    "wof:name":"Latwa Murlidhar",
    "wof:placetype":"locality"
},
  "geometry": {"coordinates":[84.22880000000001,26.64316],"type":"Point"}
}