{
  "type": "Feature",
  "properties": {
    "gn:admin1_code":"11.0",
    "gn:admin2_code":"27.0",
    "gn:asciiname":"Sharandi",
    "gn:country_code":"IN",
    "gn:dem":2485,
    "gn:feature_class":"P",
    "gn:feature_code":"PPL",
    "gn:name":"Shar\u0101ndi",
    "gn:population":0,
    "gn:timezone":"Asia/Kolkata",
    "iso:country":"IN",
    "wof:name":"Sharandi",
    "wof:placetype":"locality"
},
  "geometry": {"coordinates":[77.09869,31.53308],"type":"Point"}
}