{
  "type": "Feature",
  "properties": {
    "iso:country":"IN",
    "ks:ks_alt_nam":"SURYAVANSHIWASTI",
    "ks:ks_name":"Suryavanshiwasti",
    "ks:ks_pop":129,
    "ks:ks_type":"HABITATION",
    "name:eng_x_preferred":[
        "Suryavanshiwasti"
    ],
    "wof:name":"Suryavanshiwasti",
    "wof:placetype":"locality",
    "wof:population":129
},
  "geometry": {"coordinates":[74.901979,16.950372],"type":"Point"}
}