{
  "type": "Feature",
  "properties": {
    "gn:admin1_code":"2.0",
    "gn:admin2_code":"549.0",
    "gn:asciiname":"Sulavaripalem",
    "gn:country_code":"IN",
    "gn:dem":7,
    "gn:feature_class":"P",
    "gn:feature_code":"PPL",
    "gn:name":"Sulav\u0101rip\u0101lem",
    "gn:population":0,
    "gn:timezone":"Asia/Kolkata",
    "iso:country":"IN",
    "wof:name":"Sulavaripalem",
    "wof:placetype":"neighbourhood"
},
  "geometry": {"coordinates":[80.33468999999999,15.78023],"type":"Point"}
}