{
  "type": "Feature",
  "properties": {
    "iso:country":"IN",
    "ks:ks_name":"29 PBN",
    "ks:ks_pop":27,
    "ks:ks_type":"VILLAGE",
    "name:eng_x_preferred":[
        "29 PBN"
    ],
    "wof:name":"29 PBN",
    "wof:placetype":"locality",
    "wof:population":27
},
  "geometry": {"coordinates":[73.903492,29.405061],"type":"Point"}
}