{
  "type": "Feature",
  "properties": {
    "gn:admin1_code":"3.0",
    "gn:admin2_code":"300.0",
    "gn:asciiname":"Dawaguri Number Three",
    "gn:country_code":"IN",
    "gn:dem":53,
    "gn:feature_class":"P",
    "gn:feature_code":"PPL",
    "gn:name":"D\u0101w\u0101guri Number Three",
    "gn:population":0,
    "gn:timezone":"Asia/Kolkata",
    "iso:country":"IN",
    "name:und_x_variant":[
        "D\u0101w\u0101guri Number Three",
        "D\u0101w\u0101guri No 3"
    ],
    "wof:name":"Dawaguri Number Three",
    "wof:placetype":"locality"
},
  "geometry": {"coordinates":[89.88844,26.458],"type":"Point"}
}