{
  "type": "Feature",
  "properties": {
    "gn:admin1_code":"37",
    "gn:admin2_code":"410.0",
    "gn:asciiname":"Tundri",
    "gn:country_code":"IN",
    "gn:dem":238,
    "gn:feature_class":"P",
    "gn:feature_code":"PPL",
    "gn:name":"Tundri",
    "gn:population":0,
    "gn:timezone":"Asia/Kolkata",
    "iso:country":"IN",
    "name:hin_x_preferred":[
        "\u091f\u0941\u0923\u094d\u0921\u094d\u0930\u0940"
    ],
    "wof:name":"Tundri",
    "wof:placetype":"locality"
},
  "geometry": {"coordinates":[82.66282,21.68201],"type":"Point"}
}