{
  "type": "Feature",
  "properties": {
    "iso:country":"IN",
    "ks:ks_name":"Hanumanpura",
    "ks:ks_pop":404,
    "ks:ks_type":"HABITATION",
    "name:eng_x_preferred":[
        "Hanumanpura"
    ],
    "wof:name":"Hanumanpura",
    "wof:placetype":"locality",
    "wof:population":404
},
  "geometry": {"coordinates":[71.716819,24.894664],"type":"Point"}
}