{
  "type": "Feature",
  "properties": {
    "iso:country":"IN",
    "ks:ks_name":"Silaudi",
    "ks:ks_pop":501,
    "ks:ks_type":"HABITATION",
    "name:eng_x_preferred":[
        "Silaudi"
    ],
    "wof:name":"Silaudi",
    "wof:placetype":"locality",
    "wof:population":501
},
  "geometry": {"coordinates":[79.436966,30.120634],"type":"Point"}
}