{
  "type": "Feature",
  "properties": {
    "gn:admin1_code":"25",
    "gn:admin2_code":"604.0",
    "gn:asciiname":"Melkanakkampattu",
    "gn:country_code":"IN",
    "gn:dem":15,
    "gn:feature_class":"P",
    "gn:feature_code":"PPL",
    "gn:name":"Melkanakkampattu",
    "gn:population":0,
    "gn:timezone":"Asia/Kolkata",
    "iso:country":"IN",
    "wof:name":"Melkanakkampattu",
    "wof:placetype":"locality"
},
  "geometry": {"coordinates":[80.10469999999999,12.64937],"type":"Point"}
}