{
  "type": "Feature",
  "properties": {
    "iso:country":"IN",
    "ks:ks_name":"Kadamguri",
    "ks:ks_pop":2300,
    "ks:ks_type":"VILLAGE",
    "ks:ks_uagg_main":0,
    "name:eng_x_preferred":[
        "Kadamguri"
    ],
    "wof:name":"Kadamguri",
    "wof:placetype":"neighbourhood",
    "wof:population":2300
},
  "geometry": {"coordinates":[90.97765,26.402981],"type":"Point"}
}