{
  "type": "Feature",
  "properties": {
    "gn:admin1_code":"35.0",
    "gn:admin2_code":"464.0",
    "gn:asciiname":"Ruparel",
    "gn:country_code":"IN",
    "gn:dem":351,
    "gn:feature_class":"P",
    "gn:feature_code":"PPL",
    "gn:name":"Ruparel",
    "gn:population":0,
    "gn:timezone":"Asia/Kolkata",
    "iso:country":"IN",
    "ks:ks_name":"Ruparel",
    "ks:ks_pop":873,
    "ks:ks_type":"VILLAGE",
    "name:eng_x_preferred":[
        "Ruparel"
    ],
    "wof:name":"Ruparel",
    "wof:placetype":"locality",
    "wof:population":873
},
  "geometry": {"coordinates":[74.661597,22.801739],"type":"Point"}
}