{
  "type": "Feature",
  "properties": {
    "iso:country":"IN",
    "ks:ks_name":"Aalwada",
    "ks:ks_pop":37,
    "ks:ks_type":"HABITATION",
    "name:eng_x_preferred":[
        "Aalwada"
    ],
    "wof:name":"Aalwada",
    "wof:placetype":"locality",
    "wof:population":37
},
  "geometry": {"coordinates":[81.129435,19.322968],"type":"Point"}
}