{
  "type": "Feature",
  "properties": {
    "iso:country":"IN",
    "ks:ks_name":"Brundeiposi",
    "ks:ks_pop":170,
    "ks:ks_type":"VILLAGE",
    "name:eng_x_preferred":[
        "Brundeiposi"
    ],
    "wof:name":"Brundeiposi",
    "wof:placetype":"locality",
    "wof:population":170
},
  "geometry": {"coordinates":[86.21019800000001,21.955801],"type":"Point"}
}