{
  "type": "Feature",
  "properties": {
    "gn:admin1_code":"10.0",
    "gn:admin2_code":"069",
    "gn:asciiname":"Gurudwara",
    "gn:country_code":"IN",
    "gn:dem":358,
    "gn:feature_class":"P",
    "gn:feature_code":"PPL",
    "gn:name":"Gur\u016bdw\u0101ra",
    "gn:population":0,
    "gn:timezone":"Asia/Kolkata",
    "iso:country":"IN",
    "name:ara_x_preferred":[
        "\u0645\u0639\u0628\u062f \u063a\u0648\u0631\u062f\u0648\u0627\u0631\u0627"
    ],
    "name:ben_bn_x_preferred":[
        "\u0997\u09c1\u09b0\u09c1\u09a6\u09c1\u09af\u09bc\u09be\u09b0\u09be"
    ],
    "name:ben_in_x_preferred":[
        "\u0997\u09c1\u09b0\u09c1\u09a6\u09c1\u09af\u09bc\u09be\u09b0\u09be"
    ],
    "name:guj_x_preferred":[
        "\u0a97\u0ac1\u0ab0\u0ac1\u0aa6\u0acd\u0ab5\u0abe\u0ab0\u0abe"
    ],
    "name:hin_x_preferred":[
        "\u0917\u0941\u0930\u0941\u0926\u094d\u0935\u093e\u0930\u093e"
    ],
    "name:kan_x_preferred":[
        "\u0c97\u0cc1\u0cb0\u0cc1\u0ca6\u0ccd\u0cb5\u0cbe\u0cb0"
    ],
    "name:mal_x_preferred":[
        "\u0d17\u0d41\u0d30\u0d41\u0d26\u0d4d\u0d35\u0d3e\u0d30"
    ],
    "name:mar_x_preferred":[
        "\u0917\u0941\u0930\u0941\u0926\u094d\u0935\u093e\u0930\u093e"
    ],
    "name:pan_x_preferred":[
        "\u0a17\u0a41\u0a30\u0a42\u0a26\u0a35\u0a3e\u0a30\u0a3e"
    ],
    "name:tam_x_preferred":[
        "\u0b95\u0bc1\u0bb0\u0bc1\u0ba4\u0bcd\u0bb5\u0bbe\u0bb0\u0bbe"
    ],
    "name:tel_x_preferred":[
        "\u0c17\u0c41\u0c30\u0c41\u0c26\u0c4d\u0c35\u0c3e\u0c30\u0c3e"
    ],
    "name:urd_x_preferred":[
        "\u06af\u0631\u0648\u062f\u0648\u0627\u0631\u06c1"
    ],
    "wof:name":"Gurudwara",
    "wof:placetype":"neighbourhood"
},
  "geometry": {"coordinates":[76.84881999999998,30.71876],"type":"Point"}
}