{
  "type": "Feature",
  "properties": {
    "gn:admin1_code":"25.0",
    "gn:admin2_code":"632.0",
    "gn:asciiname":"Pappampatti",
    "gn:country_code":"IN",
    "gn:dem":408,
    "gn:feature_class":"P",
    "gn:feature_code":"PPL",
    "gn:name":"P\u0101ppampatti",
    "gn:population":0,
    "gn:timezone":"Asia/Kolkata",
    "iso:country":"IN",
    "wof:name":"Pappampatti",
    "wof:placetype":"locality"
},
  "geometry": {"coordinates":[77.10178000000001,10.95965],"type":"Point"}
}