{
  "type": "Feature",
  "properties": {
    "gn:admin1_code":"34.0",
    "gn:admin2_code":"222.0",
    "gn:asciiname":"Turkia",
    "gn:country_code":"IN",
    "gn:dem":46,
    "gn:feature_class":"P",
    "gn:feature_code":"PPL",
    "gn:name":"Turkia",
    "gn:population":0,
    "gn:timezone":"Asia/Kolkata",
    "iso:country":"IN",
    "ks:ks_name":"Turkia",
    "ks:ks_pop":312,
    "ks:ks_type":"VILLAGE",
    "name:eng_x_preferred":[
        "Turkia"
    ],
    "wof:name":"Turkia",
    "wof:placetype":"locality",
    "wof:population":312
},
  "geometry": {"coordinates":[86.253411,25.533342],"type":"Point"}
}