{
  "type": "Feature",
  "properties": {
    "iso:country":"IN",
    "ks:ks_name":"Dhadawali",
    "ks:ks_pop":42,
    "ks:ks_type":"VILLAGE",
    "name:eng_x_preferred":[
        "Dhadawali"
    ],
    "wof:name":"Dhadawali",
    "wof:placetype":"locality",
    "wof:population":42
},
  "geometry": {"coordinates":[73.55712200000001,18.377724],"type":"Point"}
}