{
  "type": "Feature",
  "properties": {
    "iso:country":"IN",
    "ks:ks_name":"Rautwadi",
    "ks:ks_pop":87,
    "ks:ks_type":"VILLAGE",
    "name:eng_x_preferred":[
        "Rautwadi"
    ],
    "wof:name":"Rautwadi",
    "wof:placetype":"locality",
    "wof:population":87
},
  "geometry": {"coordinates":[73.414063,16.607139],"type":"Point"}
}