{
  "type": "Feature",
  "properties": {
    "gn:admin1_code":"30",
    "gn:admin2_code":"251.0",
    "gn:asciiname":"Riu",
    "gn:country_code":"IN",
    "gn:dem":1043,
    "gn:feature_class":"P",
    "gn:feature_code":"PPL",
    "gn:name":"Riu",
    "gn:population":0,
    "gn:timezone":"Asia/Kolkata",
    "iso:country":"IN",
    "wof:name":"Riu",
    "wof:placetype":"locality"
},
  "geometry": {"coordinates":[95.05316999999999,28.30692],"type":"Point"}
}