{
  "type": "Feature",
  "properties": {
    "iso:country":"IN",
    "ks:ks_name":"Budigireddigaripalle",
    "ks:ks_pop":159,
    "ks:ks_type":"HABITATION",
    "ks:ks_uagg_main":0,
    "name:eng_x_preferred":[
        "Budigireddigaripalle"
    ],
    "wof:name":"Budigireddigaripalle",
    "wof:placetype":"neighbourhood",
    "wof:population":159
},
  "geometry": {"coordinates":[78.923227,13.645936],"type":"Point"}
}