{
  "type": "Feature",
  "properties": {
    "gn:admin1_code":"37.0",
    "gn:admin2_code":"413.0",
    "gn:asciiname":"Nulegondi",
    "gn:country_code":"IN",
    "gn:dem":441,
    "gn:feature_class":"P",
    "gn:feature_code":"PPL",
    "gn:name":"Nulegondi",
    "gn:population":0,
    "gn:timezone":"Asia/Kolkata",
    "iso:country":"IN",
    "ks:ks_name":"Lulegondi",
    "ks:ks_pop":313,
    "ks:ks_type":"VILLAGE",
    "name:eng_x_preferred":[
        "Lulegondi"
    ],
    "name:eng_x_variant":[
        "Nulegondi"
    ],
    "wof:name":"Lulegondi",
    "wof:placetype":"locality",
    "wof:population":313
},
  "geometry": {"coordinates":[81.49301699999999,20.170383],"type":"Point"}
}