{
  "type": "Feature",
  "properties": {
    "gn:admin1_code":"35.0",
    "gn:admin2_code":"419.0",
    "gn:asciiname":"Gastua ka Pura",
    "gn:country_code":"IN",
    "gn:dem":186,
    "gn:feature_class":"P",
    "gn:feature_code":"PPL",
    "gn:name":"Gastua ka Pura",
    "gn:population":0,
    "gn:timezone":"Asia/Kolkata",
    "iso:country":"IN",
    "wof:name":"Gastua ka Pura",
    "wof:placetype":"locality"
},
  "geometry": {"coordinates":[77.88464999999999,26.32552],"type":"Point"}
}