{
  "type": "Feature",
  "properties": {
    "iso:country":"IN",
    "ks:ks_name":"Nagla Mardan",
    "ks:ks_pop":159,
    "ks:ks_type":"HABITATION",
    "name:eng_x_preferred":[
        "Nagla Mardan"
    ],
    "wof:name":"Nagla Mardan",
    "wof:placetype":"locality",
    "wof:population":159
},
  "geometry": {"coordinates":[78.71283200000001,27.360142],"type":"Point"}
}