{
  "type": "Feature",
  "properties": {
    "iso:country":"IN",
    "ks:ks_name":"Madumar Gross Form",
    "ks:ks_pop":0,
    "ks:ks_type":"VILLAGE",
    "name:eng_x_preferred":[
        "Madumar Gross Form"
    ],
    "wof:name":"Madumar Gross Form",
    "wof:placetype":"locality",
    "wof:population":0
},
  "geometry": {"coordinates":[78.859223,24.693232],"type":"Point"}
}