{
  "type": "Feature",
  "properties": {
    "iso:country":"IN",
    "ks:ks_name":"Barikere",
    "ks:ks_pop":175,
    "ks:ks_type":"HABITATION",
    "name:eng_x_preferred":[
        "Barikere"
    ],
    "wof:name":"Barikere",
    "wof:placetype":"locality",
    "wof:population":175
},
  "geometry": {"coordinates":[75.696037,13.199489],"type":"Point"}
}