{
  "type": "Feature",
  "properties": {
    "gn:admin1_code":"2",
    "gn:admin2_code":"544.0",
    "gn:asciiname":"Kinanguda",
    "gn:country_code":"IN",
    "gn:dem":986,
    "gn:feature_class":"P",
    "gn:feature_code":"PPL",
    "gn:name":"Kinang\u016bda",
    "gn:population":0,
    "gn:timezone":"Asia/Kolkata",
    "iso:country":"IN",
    "wof:name":"Kinanguda",
    "wof:placetype":"locality"
},
  "geometry": {"coordinates":[82.92929000000002,18.26433],"type":"Point"}
}