{
  "type": "Feature",
  "properties": {
    "gn:admin1_code":"2",
    "gn:admin2_code":"544.0",
    "gn:asciiname":"Kinanguda",
    "gn:country_code":"IN",
    "gn:dem":986,
    "gn:feature_class":"P",
    "gn:feature_code":"PPL",
    "gn:name":"Kinang\u016bda",
    "gn:population":0,
    "gn:timezone":"Asia/Kolkata",
    "iso:country":"IN",
    "ks:ks_name":"Kinnamguda",
    "ks:ks_pop":268,
    "ks:ks_type":"HABITATION",
    "name:eng_x_preferred":[
        "Kinnamguda"
    ],
    "name:eng_x_variant":[
        "Kinanguda"
    ],
    "wof:name":"Kinnamguda",
    "wof:placetype":"locality",
    "wof:population":268
},
  "geometry": {"coordinates":[82.92988099999999,18.264122],"type":"Point"}
}