{
  "type": "Feature",
  "properties": {
    "iso:country":"IN",
    "ks:ks_name":"Nischintapur",
    "ks:ks_pop":125,
    "ks:ks_type":"VILLAGE",
    "name:eng_x_preferred":[
        "Nischintapur"
    ],
    "wof:name":"Nischintapur",
    "wof:placetype":"locality",
    "wof:population":125
},
  "geometry": {"coordinates":[87.14068399999999,21.624155],"type":"Point"}
}