{
  "type": "Feature",
  "properties": {
    "gn:admin1_code":"11",
    "gn:admin2_code":"24.0",
    "gn:asciiname":"Arath Jhikli",
    "gn:country_code":"IN",
    "gn:dem":1047,
    "gn:feature_class":"P",
    "gn:feature_code":"PPL",
    "gn:name":"\u0100rath Jhikli",
    "gn:population":0,
    "gn:timezone":"Asia/Kolkata",
    "iso:country":"IN",
    "wof:name":"Arath Jhikli",
    "wof:placetype":"locality"
},
  "geometry": {"coordinates":[76.46723,32.09497],"type":"Point"}
}