{
  "type": "Feature",
  "properties": {
    "gn:admin1_code":"2.0",
    "gn:admin2_code":"553.0",
    "gn:asciiname":"Gitalavandlapalle",
    "gn:country_code":"IN",
    "gn:dem":508,
    "gn:feature_class":"P",
    "gn:feature_code":"PPL",
    "gn:name":"Gitalav\u0101ndlapalle",
    "gn:population":0,
    "gn:timezone":"Asia/Kolkata",
    "iso:country":"IN",
    "wof:name":"Gitalavandlapalle",
    "wof:placetype":"neighbourhood"
},
  "geometry": {"coordinates":[78.28361,13.94831],"type":"Point"}
}