{
  "type": "Feature",
  "properties": {
    "iso:country":"IN",
    "ks:ks_name":"Ibspur",
    "ks:ks_pop":427,
    "ks:ks_type":"HABITATION",
    "name:eng_x_preferred":[
        "Ibspur"
    ],
    "wof:name":"Ibspur",
    "wof:placetype":"locality",
    "wof:population":427
},
  "geometry": {"coordinates":[78.136038,28.628896],"type":"Point"}
}