{
  "type": "Feature",
  "properties": {
    "iso:country":"IN",
    "ks:ks_alt_nam":"MUSHARI NAYABAS",
    "ks:ks_name":"Mushari Nayabas",
    "ks:ks_pop":203,
    "ks:ks_type":"HABITATION",
    "name:eng_x_preferred":[
        "Mushari Nayabas"
    ],
    "wof:name":"Mushari Nayabas",
    "wof:placetype":"locality",
    "wof:population":203
},
  "geometry": {"coordinates":[86.550799,25.551211],"type":"Point"}
}