{
  "type": "Feature",
  "properties": {
    "iso:country":"IN",
    "ks:ks_name":"Tulipadi",
    "ks:ks_pop":263,
    "ks:ks_type":"HABITATION",
    "name:eng_x_preferred":[
        "Tulipadi"
    ],
    "wof:name":"Tulipadi",
    "wof:placetype":"locality",
    "wof:population":263
},
  "geometry": {"coordinates":[86.31354399999999,20.985058],"type":"Point"}
}