{
  "type": "Feature",
  "properties": {
    "iso:country":"IN",
    "ks:ks_name":"Kewal Pur",
    "ks:ks_pop":107,
    "ks:ks_type":"HABITATION",
    "name:eng_x_preferred":[
        "Kewal Pur"
    ],
    "wof:name":"Kewal Pur",
    "wof:placetype":"locality",
    "wof:population":107
},
  "geometry": {"coordinates":[81.844942,26.070573],"type":"Point"}
}