{
  "type": "Feature",
  "properties": {
    "iso:country":"IN",
    "ks:ks_name":"Sannatadukattu",
    "ks:ks_pop":101,
    "ks:ks_type":"HABITATION",
    "name:eng_x_preferred":[
        "Sannatadukattu"
    ],
    "wof:name":"Sannatadukattu",
    "wof:placetype":"locality",
    "wof:population":101
},
  "geometry": {"coordinates":[74.416922,14.452063],"type":"Point"}
}