{
  "type": "Feature",
  "properties": {
    "iso:country":"IN",
    "ks:ks_name":"Sankarapuram",
    "ks:ks_pop":12,
    "ks:ks_type":"HABITATION",
    "name:eng_x_preferred":[
        "Sankarapuram"
    ],
    "wof:name":"Sankarapuram",
    "wof:placetype":"locality",
    "wof:population":12
},
  "geometry": {"coordinates":[78.48252100000001,13.512856],"type":"Point"}
}