{
  "type": "Feature",
  "properties": {
    "iso:country":"IN",
    "ks:ks_name":"Dhepaguda",
    "ks:ks_pop":276,
    "ks:ks_type":"VILLAGE",
    "name:eng_x_preferred":[
        "Dhepaguda"
    ],
    "wof:name":"Dhepaguda",
    "wof:placetype":"locality",
    "wof:population":276
},
  "geometry": {"coordinates":[84.37069,19.716154],"type":"Point"}
}