{
  "type": "Feature",
  "properties": {
    "iso:country":"IN",
    "ks:ks_name":"Fatepur",
    "ks:ks_pop":1866,
    "ks:ks_type":"VILLAGE",
    "name:eng_x_preferred":[
        "Fatepur"
    ],
    "wof:name":"Fatepur",
    "wof:placetype":"locality",
    "wof:population":1866
},
  "geometry": {"coordinates":[86.625579,23.768728],"type":"Point"}
}