{
  "type": "Feature",
  "properties": {
    "iso:country":"IN",
    "ks:ks_name":"Kelwa",
    "ks:ks_pop":443,
    "ks:ks_type":"VILLAGE",
    "name:eng_x_preferred":[
        "Kelwa"
    ],
    "wof:name":"Kelwa",
    "wof:placetype":"locality",
    "wof:population":443
},
  "geometry": {"coordinates":[74.201408,24.309589],"type":"Point"}
}