{
  "type": "Feature",
  "properties": {
    "iso:country":"IN",
    "ks:ks_name":"14 STG",
    "ks:ks_pop":183,
    "ks:ks_type":"VILLAGE",
    "name:eng_x_preferred":[
        "14 STG"
    ],
    "wof:name":"14 STG",
    "wof:placetype":"locality",
    "wof:population":183
},
  "geometry": {"coordinates":[74.18251100000001,29.530672],"type":"Point"}
}