{
  "type": "Feature",
  "properties": {
    "gn:admin1_code":"25.0",
    "gn:admin2_code":"612.0",
    "gn:asciiname":"V.S.K.Valasai (Dindigul-Dist.)",
    "gn:country_code":"IN",
    "gn:dem":372,
    "gn:elevation":"320.0",
    "gn:feature_class":"P",
    "gn:feature_code":"PPL",
    "gn:name":"V.S.K.Valasai (Dindigul-Dist.)",
    "gn:population":17865,
    "gn:timezone":"Asia/Kolkata",
    "iso:country":"IN",
    "name:eng_x_colloquial":[
        "V.S.K.Valasai (Dindigul-Dist.)"
    ],
    "name:eng_x_historical":[
        "V.S.K.Valasai (Dindigul-Dist.)"
    ],
    "name:eng_x_preferred":[
        "V.S.K.Valasai (Dindigul-Dist.)"
    ],
    "name:fra_x_preferred":[
        "V.S.K.Valasai (Dindigul-Dist.)"
    ],
    "name:rus_x_preferred":[
        "\u0412.\u0421.\u041a.\u0412\u0430\u043b\u0430\u0441\u0430\u0438"
    ],
    "name:spa_x_preferred":[
        "V.S.K.Valasai (Dindigul-Dist.)"
    ],
    "wof:name":"V.S.K.Valasai (Dindigul-Dist.)",
    "wof:placetype":"locality",
    "wof:population":17865
},
  "geometry": {"coordinates":[78.15141,10.31549],"type":"Point"}
}