{
  "type": "Feature",
  "properties": {
    "iso:country":"IN",
    "ks:ks_alt_nam":"5 SDS",
    "ks:ks_name":"5 Sds",
    "ks:ks_pop":53,
    "ks:ks_type":"HABITATION",
    "name:eng_x_preferred":[
        "5 Sds"
    ],
    "wof:name":"5 Sds",
    "wof:placetype":"locality",
    "wof:population":53
},
  "geometry": {"coordinates":[74.150419,29.895433],"type":"Point"}
}