{
  "type": "Feature",
  "properties": {
    "gn:admin1_code":"39.0",
    "gn:admin2_code":"64.0",
    "gn:asciiname":"Dina",
    "gn:country_code":"IN",
    "gn:dem":1412,
    "gn:feature_class":"P",
    "gn:feature_code":"PPL",
    "gn:name":"D\u012bna",
    "gn:population":0,
    "gn:timezone":"Asia/Kolkata",
    "iso:country":"IN",
    "ks:ks_alt_nam":"D\u012bna",
    "ks:ks_name":"Dina",
    "ks:ks_type":"VILLAGE",
    "name:als_x_preferred":[
        "Dina"
    ],
    "name:ces_x_preferred":[
        "Dina"
    ],
    "name:dan_x_preferred":[
        "Dina"
    ],
    "name:deu_x_preferred":[
        "Dina"
    ],
    "name:eng_x_preferred":[
        "Dina"
    ],
    "name:eng_x_variant":[
        "D\u012bna"
    ],
    "name:hun_x_preferred":[
        "Dina"
    ],
    "name:ita_x_preferred":[
        "Dina"
    ],
    "name:nno_x_preferred":[
        "Dina"
    ],
    "name:nor_x_preferred":[
        "Dina"
    ],
    "name:pol_x_preferred":[
        "Dina"
    ],
    "name:rus_x_preferred":[
        "\u0414\u0438\u043d\u0430"
    ],
    "name:swe_x_preferred":[
        "Dina"
    ],
    "wof:name":"Dina",
    "wof:placetype":"locality"
},
  "geometry": {"coordinates":[79.496225,29.510475],"type":"Point"}
}