{
  "type": "Feature",
  "properties": {
    "gn:admin1_code":"19.0",
    "gn:admin2_code":"555.0",
    "gn:asciiname":"Govankop",
    "gn:country_code":"IN",
    "gn:dem":614,
    "gn:feature_class":"P",
    "gn:feature_code":"PPL",
    "gn:name":"Govankop",
    "gn:population":0,
    "gn:timezone":"Asia/Kolkata",
    "iso:country":"IN",
    "wof:name":"Govankop",
    "wof:placetype":"locality"
},
  "geometry": {"coordinates":[75.26765999999998,15.86011],"type":"Point"}
}