{
  "type": "Feature",
  "properties": {
    "gn:admin1_code":"34.0",
    "gn:admin2_code":"215.0",
    "gn:asciiname":"Basauli",
    "gn:country_code":"IN",
    "gn:dem":53,
    "gn:feature_class":"P",
    "gn:feature_code":"PPL",
    "gn:name":"Basauli",
    "gn:population":0,
    "gn:timezone":"Asia/Kolkata",
    "iso:country":"IN",
    "ks:ks_name":"Basauli",
    "ks:ks_pop":1461,
    "ks:ks_type":"HABITATION",
    "ks:ks_uagg_main":0,
    "name:eng_x_preferred":[
        "Basauli"
    ],
    "wof:name":"Basauli",
    "wof:placetype":"neighbourhood",
    "wof:population":1461
},
  "geometry": {"coordinates":[86.144289,26.078513],"type":"Point"}
}