{
  "type": "Feature",
  "properties": {
    "gn:admin1_code":"37.0",
    "gn:admin2_code":"403.0",
    "gn:asciiname":"Katharapali",
    "gn:country_code":"IN",
    "gn:dem":226,
    "gn:feature_class":"P",
    "gn:feature_code":"PPL",
    "gn:name":"Katharapali",
    "gn:population":0,
    "gn:timezone":"Asia/Kolkata",
    "iso:country":"IN",
    "wof:name":"Katharapali",
    "wof:placetype":"neighbourhood"
},
  "geometry": {"coordinates":[83.37493000000001,21.92181],"type":"Point"}
}