{
  "type": "Feature",
  "properties": {
    "iso:country":"IN",
    "ks:ks_name":"Tapryachiwadi",
    "ks:ks_pop":110,
    "ks:ks_type":"HABITATION",
    "name:eng_x_preferred":[
        "Tapryachiwadi"
    ],
    "wof:name":"Tapryachiwadi",
    "wof:placetype":"locality",
    "wof:population":110
},
  "geometry": {"coordinates":[73.141262,18.853587],"type":"Point"}
}