{
  "type": "Feature",
  "properties": {
    "iso:country":"IN",
    "ks:ks_alt_nam":"sutarwadi",
    "ks:ks_name":"Sutarwadi",
    "ks:ks_pop":102,
    "ks:ks_type":"HABITATION",
    "name:eng_x_preferred":[
        "Sutarwadi"
    ],
    "wof:name":"Sutarwadi",
    "wof:placetype":"locality",
    "wof:population":102
},
  "geometry": {"coordinates":[73.840081,16.192464],"type":"Point"}
}