{
  "type": "Feature",
  "properties": {
    "iso:country":"IN",
    "ks:ks_name":"Kakra",
    "ks:ks_pop":484,
    "ks:ks_type":"VILLAGE",
    "name:eng_x_preferred":[
        "Kakra"
    ],
    "wof:name":"Kakra",
    "wof:placetype":"locality",
    "wof:population":484
},
  "geometry": {"coordinates":[87.90598199999999,23.886575],"type":"Point"}
}