{
  "type": "Feature",
  "properties": {
    "iso:country":"IN",
    "ks:ks_name":"Umargatta",
    "ks:ks_pop":61,
    "ks:ks_type":"HABITATION",
    "name:eng_x_preferred":[
        "Umargatta"
    ],
    "wof:name":"Umargatta",
    "wof:placetype":"locality",
    "wof:population":61
},
  "geometry": {"coordinates":[80.45909,19.957548],"type":"Point"}
}