{
  "type": "Feature",
  "properties": {
    "iso:country":"IN",
    "ks:ks_name":"Halikai",
    "ks:ks_pop":44,
    "ks:ks_type":"HABITATION",
    "name:eng_x_preferred":[
        "Halikai"
    ],
    "wof:name":"Halikai",
    "wof:placetype":"locality",
    "wof:population":44
},
  "geometry": {"coordinates":[74.794653,14.090109],"type":"Point"}
}