{
  "type": "Feature",
  "properties": {
    "iso:country":"IN",
    "ks:ks_alt_nam":"B.Kothavalasa",
    "ks:ks_name":"B.kothavalasa",
    "ks:ks_pop":75,
    "ks:ks_type":"HABITATION",
    "name:eng_x_preferred":[
        "B.kothavalasa"
    ],
    "wof:name":"B.kothavalasa",
    "wof:placetype":"locality",
    "wof:population":75
},
  "geometry": {"coordinates":[83.10824599999999,18.266402],"type":"Point"}
}