{
  "type": "Feature",
  "properties": {
    "gn:admin1_code":"25.0",
    "gn:admin2_code":"605.0",
    "gn:asciiname":"Konur",
    "gn:country_code":"IN",
    "gn:dem":622,
    "gn:feature_class":"P",
    "gn:feature_code":"PPL",
    "gn:name":"Kon\u016br",
    "gn:population":0,
    "gn:timezone":"Asia/Kolkata",
    "iso:country":"IN",
    "name:ceb_x_preferred":[
        "Konur"
    ],
    "name:swe_x_preferred":[
        "Konur"
    ],
    "wof:name":"Konur",
    "wof:placetype":"locality"
},
  "geometry": {"coordinates":[78.97526999999999,12.73167],"type":"Point"}
}