{
  "type": "Feature",
  "properties": {
    "gn:admin1_code":"21.0",
    "gn:admin2_code":"398.0",
    "gn:asciiname":"Malikudupi",
    "gn:country_code":"IN",
    "gn:dem":926,
    "gn:feature_class":"P",
    "gn:feature_code":"PPL",
    "gn:name":"M\u0101likudupi",
    "gn:population":0,
    "gn:timezone":"Asia/Kolkata",
    "iso:country":"IN",
    "wof:name":"Malikudupi",
    "wof:placetype":"neighbourhood"
},
  "geometry": {"coordinates":[82.91003000000001,18.62399],"type":"Point"}
}