{
  "type": "Feature",
  "properties": {
    "iso:country":"IN",
    "ks:ks_name":"Thebhai",
    "ks:ks_pop":154,
    "ks:ks_type":"VILLAGE",
    "name:eng_x_preferred":[
        "Thebhai"
    ],
    "wof:name":"Thebhai",
    "wof:placetype":"locality",
    "wof:population":154
},
  "geometry": {"coordinates":[86.66092999999999,25.035828],"type":"Point"}
}