{
  "type": "Feature",
  "properties": {
    "gn:admin1_code":"36.0",
    "gn:admin2_code":"179.0",
    "gn:asciiname":"Palia",
    "gn:country_code":"IN",
    "gn:dem":103,
    "gn:feature_class":"P",
    "gn:feature_code":"PPL",
    "gn:name":"Palia",
    "gn:population":0,
    "gn:timezone":"Asia/Kolkata",
    "iso:country":"IN",
    "name:fas_x_preferred":[
        "\u067e\u0627\u0644\u06cc\u0627"
    ],
    "name:urd_x_preferred":[
        "\u067e\u0627\u0644\u06cc\u0627"
    ],
    "wof:name":"Palia",
    "wof:placetype":"locality"
},
  "geometry": {"coordinates":[81.97369999999999,26.24277],"type":"Point"}
}