{
  "type": "Feature",
  "properties": {
    "iso:country":"IN",
    "ks:ks_name":"Barawa Tola",
    "ks:ks_pop":1339,
    "ks:ks_type":"VILLAGE",
    "name:eng_x_preferred":[
        "Barawa Tola"
    ],
    "wof:name":"Barawa Tola",
    "wof:placetype":"locality",
    "wof:population":1339
},
  "geometry": {"coordinates":[82.98137199999999,23.952461],"type":"Point"}
}