{
  "type": "Feature",
  "properties": {
    "iso:country":"IN",
    "ks:ks_name":"Paschim Tola",
    "ks:ks_pop":240,
    "ks:ks_type":"HABITATION",
    "name:eng_x_preferred":[
        "Paschim Tola"
    ],
    "wof:name":"Paschim Tola",
    "wof:placetype":"locality",
    "wof:population":240
},
  "geometry": {"coordinates":[82.672647,26.816776],"type":"Point"}
}