{
  "type": "Feature",
  "properties": {
    "iso:country":"IN",
    "ks:ks_name":"Equmara",
    "ks:ks_pop":176,
    "ks:ks_type":"VILLAGE",
    "name:eng_x_preferred":[
        "Equmara"
    ],
    "wof:name":"Equmara",
    "wof:placetype":"locality",
    "wof:population":176
},
  "geometry": {"coordinates":[84.272812,18.790706],"type":"Point"}
}