{
  "type": "Feature",
  "properties": {
    "iso:country":"IN",
    "ks:ks_name":"Bhatwadi",
    "ks:ks_pop":24,
    "ks:ks_type":"HABITATION",
    "name:eng_x_preferred":[
        "Bhatwadi"
    ],
    "wof:name":"Bhatwadi",
    "wof:placetype":"locality",
    "wof:population":24
},
  "geometry": {"coordinates":[73.890494,15.781241],"type":"Point"}
}