{
  "type": "Feature",
  "properties": {
    "iso:country":"IN",
    "ks:ks_name":"Matijhariya",
    "ks:ks_pop":481,
    "ks:ks_type":"VILLAGE",
    "name:eng_x_preferred":[
        "Matijhariya"
    ],
    "wof:name":"Matijhariya",
    "wof:placetype":"locality",
    "wof:population":481
},
  "geometry": {"coordinates":[82.430302,23.205881],"type":"Point"}
}