{
  "type": "Feature",
  "properties": {
    "iso:country":"IN",
    "ks:ks_name":"Sabaiya",
    "ks:ks_pop":163,
    "ks:ks_type":"VILLAGE",
    "name:eng_x_preferred":[
        "Sabaiya"
    ],
    "wof:name":"Sabaiya",
    "wof:placetype":"locality",
    "wof:population":163
},
  "geometry": {"coordinates":[86.585515,25.031536],"type":"Point"}
}