{
  "type": "Feature",
  "properties": {
    "iso:country":"IN",
    "ks:ks_name":"Ghamirpura",
    "ks:ks_pop":230,
    "ks:ks_type":"HABITATION",
    "name:eng_x_preferred":[
        "Ghamirpura"
    ],
    "wof:name":"Ghamirpura",
    "wof:placetype":"locality",
    "wof:population":230
},
  "geometry": {"coordinates":[72.88727799999999,22.894556],"type":"Point"}
}