{
  "type": "Feature",
  "properties": {
    "iso:country":"IN",
    "ks:ks_name":"Baulapal",
    "ks:ks_pop":1051,
    "ks:ks_type":"HABITATION",
    "name:eng_x_preferred":[
        "Baulapal"
    ],
    "wof:name":"Baulapal",
    "wof:placetype":"locality",
    "wof:population":1051
},
  "geometry": {"coordinates":[85.879817,20.980256],"type":"Point"}
}