{
  "type": "Feature",
  "properties": {
    "iso:country":"IN",
    "ks:ks_name":"Rajpura",
    "ks:ks_pop":149,
    "ks:ks_type":"HABITATION",
    "name:eng_x_preferred":[
        "Rajpura"
    ],
    "wof:name":"Rajpura",
    "wof:placetype":"locality",
    "wof:population":149
},
  "geometry": {"coordinates":[77.00212000000001,26.040869],"type":"Point"}
}