{
  "type": "Feature",
  "properties": {
    "gn:admin1_code":"16",
    "gn:admin2_code":"508.0",
    "gn:asciiname":"Khargi",
    "gn:country_code":"IN",
    "gn:dem":304,
    "gn:feature_class":"P",
    "gn:feature_code":"PPL",
    "gn:name":"Khargi",
    "gn:population":0,
    "gn:timezone":"Asia/Kolkata",
    "iso:country":"IN",
    "name:ara_x_preferred":[
        "\u062e\u0631\u063a\u064a"
    ],
    "name:ceb_x_preferred":[
        "Kharg\u012b"
    ],
    "name:fas_x_preferred":[
        "\u062e\u0631\u06af\u06cc"
    ],
    "name:msa_x_preferred":[
        "Khargi"
    ],
    "name:swe_x_preferred":[
        "Kharg\u012b"
    ],
    "wof:name":"Khargi",
    "wof:placetype":"locality"
},
  "geometry": {"coordinates":[80.46055,20.07478],"type":"Point"}
}