{
  "type": "Feature",
  "properties": {
    "iso:country":"IN",
    "ks:ks_name":"Kothapalli",
    "ks:ks_pop":357,
    "ks:ks_type":"HABITATION",
    "name:eng_x_preferred":[
        "Kothapalli"
    ],
    "wof:name":"Kothapalli",
    "wof:placetype":"locality",
    "wof:population":357
},
  "geometry": {"coordinates":[79.773743,15.507978],"type":"Point"}
}