{
  "type": "Feature",
  "properties": {
    "iso:country":"IN",
    "ks:ks_name":"Karamtoli",
    "ks:ks_pop":177,
    "ks:ks_type":"VILLAGE",
    "ks:ks_uagg_main":0,
    "name:eng_x_preferred":[
        "Karamtoli"
    ],
    "wof:name":"Karamtoli",
    "wof:placetype":"neighbourhood",
    "wof:population":177
},
  "geometry": {"coordinates":[84.524845,23.035141],"type":"Point"}
}