{
  "type": "Feature",
  "properties": {
    "iso:country":"IN",
    "ks:ks_name":"School Para",
    "ks:ks_pop":709,
    "ks:ks_type":"HABITATION",
    "name:eng_x_preferred":[
        "School Para"
    ],
    "wof:name":"School Para",
    "wof:placetype":"locality",
    "wof:population":709
},
  "geometry": {"coordinates":[81.556515,19.361312],"type":"Point"}
}