{
  "type": "Feature",
  "properties": {
    "gn:admin1_code":"34.0",
    "gn:admin2_code":"235.0",
    "gn:asciiname":"Siwabigha",
    "gn:country_code":"IN",
    "gn:dem":144,
    "gn:feature_class":"P",
    "gn:feature_code":"PPL",
    "gn:name":"Siw\u0101bigh\u0101",
    "gn:population":0,
    "gn:timezone":"Asia/Kolkata",
    "iso:country":"IN",
    "ks:ks_alt_nam":"Siw\u0101bigh\u0101",
    "ks:ks_name":"Siwabigha",
    "ks:ks_type":"VILLAGE",
    "ks:ks_uagg_main":0,
    "name:eng_x_preferred":[
        "Siwabigha"
    ],
    "name:eng_x_variant":[
        "Siw\u0101bigh\u0101"
    ],
    "wof:name":"Siwabigha",
    "wof:placetype":"neighbourhood"
},
  "geometry": {"coordinates":[84.134305,24.603287],"type":"Point"}
}