{
  "type": "Feature",
  "properties": {
    "gn:admin1_code":"19.0",
    "gn:admin2_code":"568.0",
    "gn:asciiname":"Kabale",
    "gn:country_code":"IN",
    "gn:dem":597,
    "gn:feature_class":"P",
    "gn:feature_code":"PPL",
    "gn:name":"Kabale",
    "gn:population":0,
    "gn:timezone":"Asia/Kolkata",
    "iso:country":"IN",
    "ks:ks_name":"Kabale",
    "ks:ks_pop":514,
    "ks:ks_type":"VILLAGE",
    "name:azb_x_preferred":[
        "\u06a9\u0627\u0628\u0627\u0644\u0647"
    ],
    "name:ben_x_preferred":[
        "\u0995\u09be\u09ac\u09c7\u09b2"
    ],
    "name:ceb_x_preferred":[
        "Kabale"
    ],
    "name:deu_x_preferred":[
        "Kabale"
    ],
    "name:eng_x_preferred":[
        "Kabale"
    ],
    "name:fas_x_preferred":[
        "\u06a9\u0627\u0628\u0627\u0644\u0647"
    ],
    "name:fra_x_preferred":[
        "Kabale"
    ],
    "name:heb_x_preferred":[
        "\u05e7\u05d1\u05d0\u05dc\u05d4"
    ],
    "name:hin_x_preferred":[
        "\u0915\u092c\u093e\u0932\u0947"
    ],
    "name:hun_x_preferred":[
        "Kabale"
    ],
    "name:ind_x_preferred":[
        "Kabale"
    ],
    "name:ita_x_preferred":[
        "Kabale"
    ],
    "name:kor_x_preferred":[
        "\uce74\ubc1c\ub808"
    ],
    "name:lit_x_preferred":[
        "Kabal\u0117"
    ],
    "name:lug_x_preferred":[
        "Kabale"
    ],
    "name:nld_x_preferred":[
        "Kabale"
    ],
    "name:pol_x_preferred":[
        "Kabale"
    ],
    "name:ron_x_preferred":[
        "Kabale"
    ],
    "name:rus_x_preferred":[
        "\u041a\u0430\u0431\u0430\u043b\u0435"
    ],
    "name:slv_x_preferred":[
        "Kabale"
    ],
    "name:spa_x_preferred":[
        "Kabale"
    ],
    "name:swa_x_preferred":[
        "Kabale"
    ],
    "name:swe_x_preferred":[
        "Kabale"
    ],
    "name:tur_x_preferred":[
        "Kabale"
    ],
    "name:ukr_x_preferred":[
        "\u041a\u0430\u0431\u0430\u043b\u0435"
    ],
    "name:urd_x_preferred":[
        "\u06a9\u0628\u0627\u0644\u06d2"
    ],
    "name:vie_x_preferred":[
        "Kabale"
    ],
    "name:zho_cn_x_preferred":[
        "\u5361\u5df4\u83b1"
    ],
    "name:zho_tw_x_preferred":[
        "\u5361\u5df4\u840a"
    ],
    "wof:name":"Kabale",
    "wof:placetype":"locality",
    "wof:population":514
},
  "geometry": {"coordinates":[75.029144,13.772147],"type":"Point"}
}