{
  "type": "Feature",
  "properties": {
    "iso:country":"IN",
    "ks:ks_name":"Barhawali Dhani",
    "ks:ks_pop":70,
    "ks:ks_type":"HABITATION",
    "name:eng_x_preferred":[
        "Barhawali Dhani"
    ],
    "wof:name":"Barhawali Dhani",
    "wof:placetype":"locality",
    "wof:population":70
},
  "geometry": {"coordinates":[75.669667,27.2372],"type":"Point"}
}