{
  "type": "Feature",
  "properties": {
    "iso:country":"IN",
    "ks:ks_name":"Bahadurpur",
    "ks:ks_pop":489,
    "ks:ks_type":"HABITATION",
    "name:eng_x_preferred":[
        "Bahadurpur"
    ],
    "wof:name":"Bahadurpur",
    "wof:placetype":"locality",
    "wof:population":489
},
  "geometry": {"coordinates":[80.879003,25.807872],"type":"Point"}
}