{
  "type": "Feature",
  "properties": {
    "gn:admin1_code":"12.0",
    "gn:admin2_code":"021",
    "gn:asciiname":"Paladpur",
    "gn:country_code":"IN",
    "gn:dem":269,
    "gn:feature_class":"P",
    "gn:feature_code":"PPL",
    "gn:name":"Pal\u0101dpur",
    "gn:population":0,
    "gn:timezone":"Asia/Kolkata",
    "iso:country":"IN",
    "name:und_x_variant":[
        "Pal\u0101dpur",
        "Pahi\u0101dpur"
    ],
    "wof:name":"Paladpur",
    "wof:placetype":"locality"
},
  "geometry": {"coordinates":[74.76765999999998,32.69751],"type":"Point"}
}