{
  "type": "Feature",
  "properties": {
    "gn:admin1_code":"9.0",
    "gn:admin2_code":"486",
    "gn:asciiname":"Goraj",
    "gn:country_code":"IN",
    "gn:dem":73,
    "gn:feature_class":"P",
    "gn:feature_code":"PPL",
    "gn:name":"Goraj",
    "gn:population":0,
    "gn:timezone":"Asia/Kolkata",
    "iso:country":"IN",
    "name:ceb_x_preferred":[
        "Goraj"
    ],
    "name:deu_x_preferred":[
        "Goraj"
    ],
    "name:fra_x_preferred":[
        "Goraj"
    ],
    "name:nld_x_preferred":[
        "Goraj"
    ],
    "name:pol_x_preferred":[
        "Goraj"
    ],
    "name:ukr_x_preferred":[
        "\u0490\u043e\u0440\u0430\u0439"
    ],
    "wof:name":"Goraj",
    "wof:placetype":"locality"
},
  "geometry": {"coordinates":[73.48285,22.33436],"type":"Point"}
}