{
  "type": "Feature",
  "properties": {
    "iso:country":"IN",
    "ks:ks_name":"Lambadi Thanda Ho Kothapally",
    "ks:ks_pop":187,
    "ks:ks_type":"HABITATION",
    "name:eng_x_preferred":[
        "Lambadi Thanda Ho Kothapally"
    ],
    "wof:name":"Lambadi Thanda Ho Kothapally",
    "wof:placetype":"locality",
    "wof:population":187
},
  "geometry": {"coordinates":[79.220433,17.65672],"type":"Point"}
}