{
  "type": "Feature",
  "properties": {
    "gn:admin1_code":"36",
    "gn:admin2_code":"196.0",
    "gn:asciiname":"Bhatwara Khurd",
    "gn:country_code":"IN",
    "gn:dem":88,
    "gn:feature_class":"P",
    "gn:feature_code":"PPL",
    "gn:name":"Bhatw\u0101ra Khurd",
    "gn:population":0,
    "gn:timezone":"Asia/Kolkata",
    "iso:country":"IN",
    "wof:name":"Bhatwara Khurd",
    "wof:placetype":"locality"
},
  "geometry": {"coordinates":[83.15590999999998,25.07557000000001],"type":"Point"}
}