{
  "type": "Feature",
  "properties": {
    "gn:admin1_code":"11.0",
    "gn:admin2_code":"32.0",
    "gn:asciiname":"Sharh",
    "gn:country_code":"IN",
    "gn:dem":1987,
    "gn:feature_class":"P",
    "gn:feature_code":"PPL",
    "gn:name":"Sh\u0101rh",
    "gn:population":0,
    "gn:timezone":"Asia/Kolkata",
    "iso:country":"IN",
    "name:ind_x_preferred":[
        "Syarh"
    ],
    "wof:name":"Sharh",
    "wof:placetype":"locality"
},
  "geometry": {"coordinates":[77.38564000000002,30.90339],"type":"Point"}
}