{
  "type": "Feature",
  "properties": {
    "gn:admin1_code":"39",
    "gn:admin2_code":"61.0",
    "gn:asciiname":"Chapri",
    "gn:country_code":"IN",
    "gn:dem":1679,
    "gn:feature_class":"P",
    "gn:feature_code":"PPL",
    "gn:name":"Ch\u0101pri",
    "gn:population":0,
    "gn:timezone":"Asia/Kolkata",
    "iso:country":"IN",
    "ks:ks_alt_nam":"Ch\u0101pri",
    "ks:ks_name":"Chapri",
    "ks:ks_type":"VILLAGE",
    "name:eng_x_preferred":[
        "Chapri"
    ],
    "name:eng_x_variant":[
        "Ch\u0101pri"
    ],
    "wof:name":"Chapri",
    "wof:placetype":"locality"
},
  "geometry": {"coordinates":[78.890018,29.888995],"type":"Point"}
}