{
  "type": "Feature",
  "properties": {
    "gn:admin1_code":"11.0",
    "gn:admin2_code":"32.0",
    "gn:asciiname":"Dingari Dona",
    "gn:country_code":"IN",
    "gn:dem":1360,
    "gn:feature_class":"P",
    "gn:feature_code":"PPL",
    "gn:name":"D\u012bngari Dona",
    "gn:population":0,
    "gn:timezone":"Asia/Kolkata",
    "iso:country":"IN",
    "wof:name":"Dingari Dona",
    "wof:placetype":"locality"
},
  "geometry": {"coordinates":[77.19396,30.76695],"type":"Point"}
}