{
  "type": "Feature",
  "properties": {
    "gn:admin1_code":"23.0",
    "gn:admin2_code":"048",
    "gn:asciiname":"Bhambal Khurd",
    "gn:country_code":"IN",
    "gn:dem":246,
    "gn:feature_class":"P",
    "gn:feature_code":"PPL",
    "gn:name":"Bhambal Khurd",
    "gn:population":0,
    "gn:timezone":"Asia/Kolkata",
    "iso:country":"IN",
    "wof:name":"Bhambal Khurd",
    "wof:placetype":"locality"
},
  "geometry": {"coordinates":[76.50869,30.11192],"type":"Point"}
}