{
  "type": "Feature",
  "properties": {
    "iso:country":"IN",
    "ks:ks_name":"Pinjari Summer Singh",
    "ks:ks_pop":1781,
    "ks:ks_type":"VILLAGE",
    "ks:ks_uagg_main":0,
    "name:eng_x_preferred":[
        "Pinjari Summer Singh"
    ],
    "wof:name":"Pinjari Summer Singh",
    "wof:placetype":"neighbourhood",
    "wof:population":1781
},
  "geometry": {"coordinates":[79.034334,27.447004],"type":"Point"}
}