{
  "type": "Feature",
  "properties": {
    "iso:country":"IN",
    "ks:ks_name":"Pandewadi",
    "ks:ks_pop":1401,
    "ks:ks_type":"VILLAGE",
    "name:eng_x_preferred":[
        "Pandewadi"
    ],
    "wof:name":"Pandewadi",
    "wof:placetype":"locality",
    "wof:population":1401
},
  "geometry": {"coordinates":[74.051372,16.401207],"type":"Point"}
}