{
  "type": "Feature",
  "properties": {
    "gn:admin1_code":"16.0",
    "gn:admin2_code":"524.0",
    "gn:asciiname":"Pakhar Sanvi",
    "gn:country_code":"IN",
    "gn:dem":620,
    "gn:feature_class":"P",
    "gn:feature_code":"PPL",
    "gn:name":"Pakhar Sanvi",
    "gn:population":0,
    "gn:timezone":"Asia/Kolkata",
    "iso:country":"IN",
    "wof:name":"Pakhar Sanvi",
    "wof:placetype":"locality"
},
  "geometry": {"coordinates":[76.52084000000001,18.38138],"type":"Point"}
}