{
  "type": "Feature",
  "properties": {
    "iso:country":"IN",
    "ks:ks_name":"Mushri Tola",
    "ks:ks_pop":181,
    "ks:ks_type":"HABITATION",
    "name:eng_x_preferred":[
        "Mushri Tola"
    ],
    "wof:name":"Mushri Tola",
    "wof:placetype":"locality",
    "wof:population":181
},
  "geometry": {"coordinates":[87.370678,26.309707],"type":"Point"}
}