{
  "type": "Feature",
  "properties": {
    "iso:country":"IN",
    "ks:ks_name":"W Daharani",
    "ks:ks_pop":4676,
    "ks:ks_type":"HABITATION",
    "name:eng_x_preferred":[
        "W Daharani"
    ],
    "wof:name":"W Daharani",
    "wof:placetype":"locality",
    "wof:population":4676
},
  "geometry": {"coordinates":[88.71423900000001,22.357772],"type":"Point"}
}