{
  "type": "Feature",
  "properties": {
    "gn:admin1_code":"35.0",
    "gn:admin2_code":"454.0",
    "gn:asciiname":"Chandgaon",
    "gn:country_code":"IN",
    "gn:dem":706,
    "gn:feature_class":"P",
    "gn:feature_code":"PPL",
    "gn:name":"Ch\u0101ndgaon",
    "gn:population":0,
    "gn:timezone":"Asia/Kolkata",
    "iso:country":"IN",
    "name:und_x_variant":[
        "Ch\u0101ndgaon",
        "Chhindpuri"
    ],
    "wof:name":"Chandgaon",
    "wof:placetype":"locality"
},
  "geometry": {"coordinates":[80.93375,22.29023],"type":"Point"}
}