{
  "type": "Feature",
  "properties": {
    "gn:admin1_code":"36",
    "gn:admin2_code":"175.0",
    "gn:asciiname":"Mando",
    "gn:country_code":"IN",
    "gn:dem":122,
    "gn:feature_class":"P",
    "gn:feature_code":"PPL",
    "gn:name":"M\u0101ndo",
    "gn:population":0,
    "gn:timezone":"Asia/Kolkata",
    "iso:country":"IN",
    "name:ceb_x_preferred":[
        "Mando"
    ],
    "name:deu_x_preferred":[
        "Mando"
    ],
    "name:fas_x_preferred":[
        "\u0645\u0627\u0646\u062f\u0648"
    ],
    "name:nld_x_preferred":[
        "Mando"
    ],
    "name:pol_x_preferred":[
        "Mando"
    ],
    "name:por_x_preferred":[
        "Mando"
    ],
    "name:spa_x_preferred":[
        "Mando"
    ],
    "name:swe_x_preferred":[
        "Mando"
    ],
    "wof:name":"Mando",
    "wof:placetype":"locality"
},
  "geometry": {"coordinates":[82.07274,24.92512],"type":"Point"}
}