{
  "type": "Feature",
  "properties": {
    "gn:admin1_code":"36.0",
    "gn:admin2_code":"183.0",
    "gn:asciiname":"Bakhtawar Misr",
    "gn:country_code":"IN",
    "gn:dem":102,
    "gn:feature_class":"P",
    "gn:feature_code":"PPL",
    "gn:name":"Bakht\u0101war Misr",
    "gn:population":0,
    "gn:timezone":"Asia/Kolkata",
    "iso:country":"IN",
    "wof:name":"Bakhtawar Misr",
    "wof:placetype":"locality"
},
  "geometry": {"coordinates":[82.00839999999999,26.97177000000001],"type":"Point"}
}