{
  "type": "Feature",
  "properties": {
    "gn:admin1_code":"36.0",
    "gn:admin2_code":"134.0",
    "gn:asciiname":"Puranpur",
    "gn:country_code":"IN",
    "gn:dem":230,
    "gn:feature_class":"P",
    "gn:feature_code":"PPL",
    "gn:name":"P\u016branpur",
    "gn:population":0,
    "gn:timezone":"Asia/Kolkata",
    "iso:country":"IN",
    "name:und_x_variant":[
        "P\u016branpur",
        "Salempur Mathna"
    ],
    "wof:name":"Puranpur",
    "wof:placetype":"locality"
},
  "geometry": {"coordinates":[78.11935,29.35189],"type":"Point"}
}