{
  "type": "Feature",
  "properties": {
    "iso:country":"IN",
    "ks:ks_name":"Utinda Malla",
    "ks:ks_pop":168,
    "ks:ks_type":"VILLAGE",
    "name:eng_x_preferred":[
        "Utinda Malla"
    ],
    "wof:name":"Utinda Malla",
    "wof:placetype":"locality",
    "wof:population":168
},
  "geometry": {"coordinates":[79.093127,29.723743],"type":"Point"}
}