{
  "type": "Feature",
  "properties": {
    "gn:admin1_code":"24.0",
    "gn:admin2_code":"110.0",
    "gn:asciiname":"Ghasipura",
    "gn:country_code":"IN",
    "gn:dem":329,
    "gn:feature_class":"P",
    "gn:feature_code":"PPL",
    "gn:name":"Gh\u0101s\u012bpura",
    "gn:population":0,
    "gn:timezone":"Asia/Kolkata",
    "iso:country":"IN",
    "name:fas_x_preferred":[
        "\u06af\u0627\u0633\u06cc\u067e\u0648\u0631\u0627"
    ],
    "wof:name":"Ghasipura",
    "wof:placetype":"locality"
},
  "geometry": {"coordinates":[76.08736,26.71741],"type":"Point"}
}