{
  "type": "Feature",
  "properties": {
    "iso:country":"IN",
    "ks:ks_name":"Puranpur Salhapur",
    "ks:ks_pop":2424,
    "ks:ks_type":"VILLAGE",
    "ks:ks_uagg_main":0,
    "name:eng_x_preferred":[
        "Puranpur Salhapur"
    ],
    "wof:name":"Puranpur Salhapur",
    "wof:placetype":"neighbourhood",
    "wof:population":2424
},
  "geometry": {"coordinates":[78.00451200000001,29.958358],"type":"Point"}
}