{
  "type": "Feature",
  "properties": {
    "iso:country":"IN",
    "ks:ks_name":"3 KAM",
    "ks:ks_pop":105,
    "ks:ks_type":"VILLAGE",
    "name:eng_x_preferred":[
        "3 KAM"
    ],
    "wof:name":"3 KAM",
    "wof:placetype":"locality",
    "wof:population":105
},
  "geometry": {"coordinates":[73.35652899999999,29.106871],"type":"Point"}
}