{
  "type": "Feature",
  "properties": {
    "gn:admin1_code":"19.0",
    "gn:admin2_code":"560.0",
    "gn:asciiname":"Budugumpa",
    "gn:country_code":"IN",
    "gn:dem":506,
    "gn:feature_class":"P",
    "gn:feature_code":"PPL",
    "gn:name":"Budugumpa",
    "gn:population":0,
    "gn:timezone":"Asia/Kolkata",
    "iso:country":"IN",
    "name:vie_x_preferred":[
        "Budugumpa"
    ],
    "wof:name":"Budugumpa",
    "wof:placetype":"locality"
},
  "geometry": {"coordinates":[76.31379,15.39333],"type":"Point"}
}