{
  "type": "Feature",
  "properties": {
    "iso:country":"IN",
    "ks:ks_name":"Khuliyapura",
    "ks:ks_pop":189,
    "ks:ks_type":"HABITATION",
    "name:eng_x_preferred":[
        "Khuliyapura"
    ],
    "wof:name":"Khuliyapura",
    "wof:placetype":"locality",
    "wof:population":189
},
  "geometry": {"coordinates":[78.66306,26.798218],"type":"Point"}
}