{
  "type": "Feature",
  "properties": {
    "iso:country":"IN",
    "ks:ks_name":"Labada Faliya",
    "ks:ks_pop":690,
    "ks:ks_type":"HABITATION",
    "name:eng_x_preferred":[
        "Labada Faliya"
    ],
    "wof:name":"Labada Faliya",
    "wof:placetype":"locality",
    "wof:population":690
},
  "geometry": {"coordinates":[73.825667,22.856778],"type":"Point"}
}