{
  "type": "Feature",
  "properties": {
    "gn:admin1_code":"35",
    "gn:admin2_code":"445.0",
    "gn:asciiname":"Pipliya",
    "gn:country_code":"IN",
    "gn:dem":298,
    "gn:feature_class":"P",
    "gn:feature_code":"PPL",
    "gn:name":"P\u012bpliya",
    "gn:population":0,
    "gn:timezone":"Asia/Kolkata",
    "iso:country":"IN",
    "ks:ks_alt_nam":"P\u012bpliya",
    "ks:ks_name":"Pipliya",
    "ks:ks_type":"VILLAGE",
    "name:eng_x_preferred":[
        "Pipliya"
    ],
    "name:eng_x_variant":[
        "P\u012bpliya"
    ],
    "wof:name":"Pipliya",
    "wof:placetype":"locality"
},
  "geometry": {"coordinates":[77.385784,22.693681],"type":"Point"}
}