{
  "type": "Feature",
  "properties": {
    "iso:country":"IN",
    "ks:ks_alt_nam":"jokhan purwa",
    "ks:ks_name":"Jokhan Purwa",
    "ks:ks_pop":38,
    "ks:ks_type":"HABITATION",
    "name:eng_x_preferred":[
        "Jokhan Purwa"
    ],
    "wof:name":"Jokhan Purwa",
    "wof:placetype":"locality",
    "wof:population":38
},
  "geometry": {"coordinates":[81.59064499999999,27.390422],"type":"Point"}
}