{
  "type": "Feature",
  "properties": {
    "gn:admin1_code":"35.0",
    "gn:admin2_code":"454.0",
    "gn:asciiname":"Bharli Lutiachuha",
    "gn:country_code":"IN",
    "gn:dem":660,
    "gn:feature_class":"P",
    "gn:feature_code":"PPL",
    "gn:name":"Bharl\u012b Lutiachuha",
    "gn:population":0,
    "gn:timezone":"Asia/Kolkata",
    "iso:country":"IN",
    "wof:name":"Bharli Lutiachuha",
    "wof:placetype":"neighbourhood"
},
  "geometry": {"coordinates":[80.86512,22.49073],"type":"Point"}
}