{
  "type": "Feature",
  "properties": {
    "iso:country":"IN",
    "ks:ks_name":"Duiringpunchi",
    "ks:ks_pop":100,
    "ks:ks_type":"HABITATION",
    "name:eng_x_preferred":[
        "Duiringpunchi"
    ],
    "wof:name":"Duiringpunchi",
    "wof:placetype":"locality",
    "wof:population":100
},
  "geometry": {"coordinates":[92.99036099999999,25.153477],"type":"Point"}
}