{
  "type": "Feature",
  "properties": {
    "iso:country":"IN",
    "ks:ks_name":"Dadhawa",
    "ks:ks_pop":982,
    "ks:ks_type":"VILLAGE",
    "name:eng_x_preferred":[
        "Dadhawa"
    ],
    "wof:name":"Dadhawa",
    "wof:placetype":"locality",
    "wof:population":982
},
  "geometry": {"coordinates":[81.57481,24.515246],"type":"Point"}
}