{
  "type": "Feature",
  "properties": {
    "iso:country":"IN",
    "ks:ks_name":"Mullugudde Palli",
    "ks:ks_pop":186,
    "ks:ks_type":"HABITATION",
    "name:eng_x_preferred":[
        "Mullugudde Palli"
    ],
    "wof:name":"Mullugudde Palli",
    "wof:placetype":"locality",
    "wof:population":186
},
  "geometry": {"coordinates":[74.869243,13.244211],"type":"Point"}
}