{
  "type": "Feature",
  "properties": {
    "iso:country":"IN",
    "ks:ks_name":"Majhiguda3",
    "ks:ks_pop":314,
    "ks:ks_type":"HABITATION",
    "name:eng_x_preferred":[
        "Majhiguda3"
    ],
    "wof:name":"Majhiguda3",
    "wof:placetype":"locality",
    "wof:population":314
},
  "geometry": {"coordinates":[82.239564,19.586429],"type":"Point"}
}