{
  "type": "Feature",
  "properties": {
    "gn:admin1_code":"16.0",
    "gn:admin2_code":"514.0",
    "gn:asciiname":"Mangrul",
    "gn:country_code":"IN",
    "gn:dem":432,
    "gn:feature_class":"P",
    "gn:feature_code":"PPL",
    "gn:name":"Mangrul",
    "gn:population":0,
    "gn:timezone":"Asia/Kolkata",
    "iso:country":"IN",
    "wof:name":"Mangrul",
    "wof:placetype":"locality"
},
  "geometry": {"coordinates":[76.33814,19.6024],"type":"Point"}
}