{
  "type": "Feature",
  "properties": {
    "iso:country":"IN",
    "ks:ks_name":"Mararpara Jethegaon",
    "ks:ks_pop":426,
    "ks:ks_type":"HABITATION",
    "name:eng_x_preferred":[
        "Mararpara Jethegaon"
    ],
    "wof:name":"Mararpara Jethegaon",
    "wof:placetype":"locality",
    "wof:population":426
},
  "geometry": {"coordinates":[80.99552,20.148799],"type":"Point"}
}