{
  "type": "Feature",
  "properties": {
    "iso:country":"IN",
    "ks:ks_name":"Savriya Pani",
    "ks:ks_pop":2229,
    "ks:ks_type":"HABITATION",
    "name:eng_x_preferred":[
        "Savriya Pani"
    ],
    "wof:name":"Savriya Pani",
    "wof:placetype":"locality",
    "wof:population":2229
},
  "geometry": {"coordinates":[74.709012,21.909657],"type":"Point"}
}