{
  "type": "Feature",
  "properties": {
    "gn:admin1_code":"11",
    "gn:admin2_code":"31.0",
    "gn:asciiname":"Kaundi",
    "gn:country_code":"IN",
    "gn:dem":754,
    "gn:feature_class":"P",
    "gn:feature_code":"PPL",
    "gn:name":"Kaundi",
    "gn:population":0,
    "gn:timezone":"Asia/Kolkata",
    "iso:country":"IN",
    "wof:name":"Kaundi",
    "wof:placetype":"locality"
},
  "geometry": {"coordinates":[76.82984999999999,30.99252000000001],"type":"Point"}
}