{
  "type": "Feature",
  "properties": {
    "gn:admin1_code":"19.0",
    "gn:admin2_code":"565.0",
    "gn:asciiname":"Agasaladibbadahalli",
    "gn:country_code":"IN",
    "gn:dem":663,
    "gn:feature_class":"P",
    "gn:feature_code":"PPL",
    "gn:name":"Agas\u0101ladibbadahalli",
    "gn:population":0,
    "gn:timezone":"Asia/Kolkata",
    "iso:country":"IN",
    "wof:name":"Agasaladibbadahalli",
    "wof:placetype":"locality"
},
  "geometry": {"coordinates":[76.51489000000002,14.84091],"type":"Point"}
}