{
  "type": "Feature",
  "properties": {
    "gn:admin1_code":"35",
    "gn:admin2_code":"436.0",
    "gn:asciiname":"Mawana",
    "gn:country_code":"IN",
    "gn:dem":424,
    "gn:feature_class":"P",
    "gn:feature_code":"PPL",
    "gn:name":"Maw\u0101na",
    "gn:population":0,
    "gn:timezone":"Asia/Kolkata",
    "iso:country":"IN",
    "name:bpy_x_preferred":[
        "\u09ae\u09be\u09f1\u09be\u09a8\u09be"
    ],
    "name:ceb_x_preferred":[
        "Maw\u0101na"
    ],
    "name:hin_x_preferred":[
        "\u092e\u0935\u093e\u0928\u093e"
    ],
    "name:ita_x_preferred":[
        "Mawana"
    ],
    "name:mlg_x_preferred":[
        "Mawana"
    ],
    "name:msa_x_preferred":[
        "Mawana"
    ],
    "name:new_x_preferred":[
        "\u092e\u0935\u0928\u093e"
    ],
    "name:nld_x_preferred":[
        "Mawana"
    ],
    "name:pol_x_preferred":[
        "Mawana"
    ],
    "name:por_x_preferred":[
        "Mawana"
    ],
    "name:swe_x_preferred":[
        "Mawana"
    ],
    "name:und_x_variant":[
        "Mohana"
    ],
    "name:urd_x_preferred":[
        "\u0645\u0648\u0627\u0646\u0627"
    ],
    "name:vie_x_preferred":[
        "Mawana"
    ],
    "name:zho_x_preferred":[
        "\u9a6c\u74e6\u7eb3"
    ],
    "wof:name":"Mawana",
    "wof:placetype":"neighbourhood"
},
  "geometry": {"coordinates":[76.37206999999999,23.69292],"type":"Point"}
}