{
  "type": "Feature",
  "properties": {
    "iso:country":"IN",
    "ks:ks_name":"Berama",
    "ks:ks_pop":323,
    "ks:ks_type":"VILLAGE",
    "name:eng_x_preferred":[
        "Berama"
    ],
    "wof:name":"Berama",
    "wof:placetype":"locality",
    "wof:population":323
},
  "geometry": {"coordinates":[83.89700499999999,19.777803],"type":"Point"}
}