{
  "type": "Feature",
  "properties": {
    "iso:country":"IN",
    "ks:ks_name":"Karauti",
    "ks:ks_pop":379,
    "ks:ks_type":"VILLAGE",
    "name:eng_x_preferred":[
        "Karauti"
    ],
    "wof:name":"Karauti",
    "wof:placetype":"locality",
    "wof:population":379
},
  "geometry": {"coordinates":[82.68278100000001,23.79841],"type":"Point"}
}