{
  "type": "Feature",
  "properties": {
    "iso:country":"IN",
    "ks:ks_alt_nam":"Is\u0101pur Di\u0101ra",
    "ks:ks_name":"Isapur Diara",
    "ks:ks_type":"VILLAGE",
    "name:eng_x_preferred":[
        "Isapur Diara"
    ],
    "name:eng_x_variant":[
        "Is\u0101pur Di\u0101ra"
    ],
    "wof:name":"Isapur Diara",
    "wof:placetype":"locality"
},
  "geometry": {"coordinates":[84.563159,26.443615],"type":"Point"}
}