{
  "type": "Feature",
  "properties": {
    "gn:admin1_code":"19.0",
    "gn:admin2_code":"570.0",
    "gn:asciiname":"Nellibiru",
    "gn:country_code":"IN",
    "gn:dem":812,
    "gn:feature_class":"P",
    "gn:feature_code":"PPL",
    "gn:name":"N\u0113llibiru",
    "gn:population":0,
    "gn:timezone":"Asia/Kolkata",
    "iso:country":"IN",
    "wof:name":"Nellibiru",
    "wof:placetype":"locality"
},
  "geometry": {"coordinates":[75.27775,13.20536],"type":"Point"}
}