{
  "type": "Feature",
  "properties": {
    "iso:country":"IN",
    "ks:ks_alt_nam":"Badr\u012bn\u0101th",
    "ks:ks_name":"Badrinath",
    "ks:ks_pop":1682,
    "ks:ks_type":"VILLAGE",
    "name:eng_x_preferred":[
        "Badrinath"
    ],
    "name:eng_x_variant":[
        "Badr\u012bn\u0101th"
    ],
    "wof:name":"Badrinath",
    "wof:placetype":"locality",
    "wof:population":1682
},
  "geometry": {"coordinates":[79.289517,30.748905],"type":"Point"}
}