{
  "type": "Feature",
  "properties": {
    "iso:country":"IN",
    "ks:ks_name":"Nagaria Falia",
    "ks:ks_pop":130,
    "ks:ks_type":"HABITATION",
    "name:eng_x_preferred":[
        "Nagaria Falia"
    ],
    "wof:name":"Nagaria Falia",
    "wof:placetype":"locality",
    "wof:population":130
},
  "geometry": {"coordinates":[73.651583,23.437167],"type":"Point"}
}