{
  "type": "Feature",
  "properties": {
    "iso:country":"IN",
    "ks:ks_name":"Uttarwari Tola",
    "ks:ks_pop":389,
    "ks:ks_type":"HABITATION",
    "name:eng_x_preferred":[
        "Uttarwari Tola"
    ],
    "wof:name":"Uttarwari Tola",
    "wof:placetype":"locality",
    "wof:population":389
},
  "geometry": {"coordinates":[86.54055700000001,25.297567],"type":"Point"}
}