{
  "type": "Feature",
  "properties": {
    "iso:country":"IN",
    "ks:ks_alt_nam":"Nagadpoi\u0101",
    "ks:ks_name":"Nagadpoia",
    "ks:ks_pop":243,
    "ks:ks_type":"VILLAGE",
    "name:eng_x_preferred":[
        "Nagadpoia"
    ],
    "name:eng_x_variant":[
        "Nagadpoi\u0101"
    ],
    "wof:name":"Nagadpoia",
    "wof:placetype":"locality",
    "wof:population":243
},
  "geometry": {"coordinates":[84.202303,26.529391],"type":"Point"}
}