{
  "type": "Feature",
  "properties": {
    "gn:admin1_code":"25.0",
    "gn:admin2_code":"631.0",
    "gn:asciiname":"Pasamudram",
    "gn:country_code":"IN",
    "gn:dem":827,
    "gn:feature_class":"P",
    "gn:feature_code":"PPL",
    "gn:name":"P\u0101samudram",
    "gn:population":0,
    "gn:timezone":"Asia/Kolkata",
    "iso:country":"IN",
    "wof:name":"Pasamudram",
    "wof:placetype":"locality"
},
  "geometry": {"coordinates":[77.83426999999998,12.62902],"type":"Point"}
}