{
  "type": "Feature",
  "properties": {
    "iso:country":"IN",
    "ks:ks_name":"Sunkarimentu",
    "ks:ks_pop":55,
    "ks:ks_type":"VILLAGE",
    "name:eng_x_preferred":[
        "Sunkarimentu"
    ],
    "wof:name":"Sunkarimentu",
    "wof:placetype":"locality",
    "wof:population":55
},
  "geometry": {"coordinates":[83.408438,19.147892],"type":"Point"}
}