{
  "type": "Feature",
  "properties": {
    "iso:country":"IN",
    "ks:ks_name":"Modsingh Nagar",
    "ks:ks_pop":320,
    "ks:ks_type":"HABITATION",
    "name:eng_x_preferred":[
        "Modsingh Nagar"
    ],
    "wof:name":"Modsingh Nagar",
    "wof:placetype":"locality",
    "wof:population":320
},
  "geometry": {"coordinates":[72.444883,26.650089],"type":"Point"}
}