{
  "type": "Feature",
  "properties": {
    "iso:country":"IN",
    "ks:ks_name":"Karamguda",
    "ks:ks_pop":273,
    "ks:ks_type":"HABITATION",
    "name:eng_x_preferred":[
        "Karamguda"
    ],
    "wof:name":"Karamguda",
    "wof:placetype":"locality",
    "wof:population":273
},
  "geometry": {"coordinates":[81.60484,18.298076],"type":"Point"}
}