{
  "type": "Feature",
  "properties": {
    "gn:admin1_code":"13.0",
    "gn:admin2_code":"593.0",
    "gn:asciiname":"Thadikundu",
    "gn:country_code":"IN",
    "gn:dem":733,
    "gn:feature_class":"P",
    "gn:feature_code":"PPL",
    "gn:name":"Thadikundu",
    "gn:population":0,
    "gn:timezone":"Asia/Kolkata",
    "iso:country":"IN",
    "wof:name":"Thadikundu",
    "wof:placetype":"locality"
},
  "geometry": {"coordinates":[76.52710999999999,11.10404],"type":"Point"}
}