{
  "type": "Feature",
  "properties": {
    "iso:country":"IN",
    "ks:ks_name":"Bhitartampa",
    "ks:ks_pop":5,
    "ks:ks_type":"VILLAGE",
    "name:eng_x_preferred":[
        "Bhitartampa"
    ],
    "wof:name":"Bhitartampa",
    "wof:placetype":"locality",
    "wof:population":5
},
  "geometry": {"coordinates":[84.40157000000001,19.318843],"type":"Point"}
}