{
  "type": "Feature",
  "properties": {
    "gn:admin1_code":"9.0",
    "gn:admin2_code":"469",
    "gn:asciiname":"Dantivada",
    "gn:country_code":"IN",
    "gn:dem":169,
    "gn:feature_class":"P",
    "gn:feature_code":"PPL",
    "gn:name":"D\u0101ntiv\u0101da",
    "gn:population":0,
    "gn:timezone":"Asia/Kolkata",
    "iso:country":"IN",
    "ks:ks_alt_nam":"D\u0101nt\u012bw\u0101da",
    "ks:ks_name":"Dantiwada",
    "ks:ks_pop":4319,
    "ks:ks_type":"VILLAGE",
    "name:eng_x_preferred":[
        "Dantiwada"
    ],
    "name:eng_x_variant":[
        "Dantivada",
        "D\u0101nt\u012bw\u0101da"
    ],
    "name:und_x_variant":[
        "D\u0101nt\u012bw\u0101da",
        "D\u0101ntiv\u0101da"
    ],
    "wof:name":"Dantiwada",
    "wof:placetype":"locality",
    "wof:population":4319
},
  "geometry": {"coordinates":[72.339612,24.343566],"type":"Point"}
}