{
  "type": "Feature",
  "properties": {
    "gn:admin1_code":"9.0",
    "gn:admin2_code":"469",
    "gn:asciiname":"Dantivada",
    "gn:country_code":"IN",
    "gn:dem":169,
    "gn:feature_class":"P",
    "gn:feature_code":"PPL",
    "gn:name":"D\u0101ntiv\u0101da",
    "gn:population":0,
    "gn:timezone":"Asia/Kolkata",
    "iso:country":"IN",
    "name:und_x_variant":[
        "D\u0101nt\u012bw\u0101da",
        "D\u0101ntiv\u0101da"
    ],
    "wof:name":"Dantivada",
    "wof:placetype":"locality"
},
  "geometry": {"coordinates":[72.33960999999999,24.34357],"type":"Point"}
}