{
  "type": "Feature",
  "properties": {
    "gn:admin1_code":"36",
    "gn:admin2_code":"178.0",
    "gn:asciiname":"Madhpur Miranpur",
    "gn:country_code":"IN",
    "gn:dem":97,
    "gn:feature_class":"P",
    "gn:feature_code":"PPL",
    "gn:name":"Madhpur M\u012branpur",
    "gn:population":0,
    "gn:timezone":"Asia/Kolkata",
    "iso:country":"IN",
    "ks:ks_name":"Madhupur Meeranpur",
    "ks:ks_pop":900,
    "ks:ks_type":"VILLAGE",
    "name:eng_x_preferred":[
        "Madhupur Meeranpur"
    ],
    "name:eng_x_variant":[
        "Madhpur Miranpur"
    ],
    "wof:name":"Madhupur Meeranpur",
    "wof:placetype":"locality",
    "wof:population":900
},
  "geometry": {"coordinates":[82.36541800000001,26.525419],"type":"Point"}
}