{
  "type": "Feature",
  "properties": {
    "gn:admin1_code":"40",
    "gn:admin2_code":"541.0",
    "gn:asciiname":"Gurralabayalu",
    "gn:country_code":"IN",
    "gn:dem":68,
    "gn:feature_class":"P",
    "gn:feature_code":"PPL",
    "gn:name":"Gurr\u0101labayalu",
    "gn:population":0,
    "gn:timezone":"Asia/Kolkata",
    "iso:country":"IN",
    "ks:ks_name":"Gurralabayalu",
    "ks:ks_pop":260,
    "ks:ks_type":"VILLAGE",
    "name:eng_x_preferred":[
        "Gurralabayalu"
    ],
    "wof:name":"Gurralabayalu",
    "wof:placetype":"locality",
    "wof:population":260
},
  "geometry": {"coordinates":[80.98712500000001,17.780527],"type":"Point"}
}