{
  "type": "Feature",
  "properties": {
    "iso:country":"IN",
    "ks:ks_name":"Chatuapara",
    "ks:ks_pop":1907,
    "ks:ks_type":"HABITATION",
    "name:eng_x_preferred":[
        "Chatuapara"
    ],
    "wof:name":"Chatuapara",
    "wof:placetype":"locality",
    "wof:population":1907
},
  "geometry": {"coordinates":[88.614493,22.217334],"type":"Point"}
}