{
  "type": "Feature",
  "properties": {
    "iso:country":"IN",
    "ks:ks_name":"Tola Chormara",
    "ks:ks_pop":177,
    "ks:ks_type":"VILLAGE",
    "name:eng_x_preferred":[
        "Tola Chormara"
    ],
    "wof:name":"Tola Chormara",
    "wof:placetype":"locality",
    "wof:population":177
},
  "geometry": {"coordinates":[86.36444,25.106093],"type":"Point"}
}