{
  "type": "Feature",
  "properties": {
    "iso:country":"IN",
    "ks:ks_alt_nam":"thillampatti",
    "ks:ks_name":"Thillampatti",
    "ks:ks_pop":87,
    "ks:ks_type":"HABITATION",
    "name:eng_x_preferred":[
        "Thillampatti"
    ],
    "wof:name":"Thillampatti",
    "wof:placetype":"locality",
    "wof:population":87
},
  "geometry": {"coordinates":[78.490371,10.506025],"type":"Point"}
}