{
  "type": "Feature",
  "properties": {
    "iso:country":"IN",
    "ks:ks_name":"Bholaguri Gaon",
    "ks:ks_pop":1304,
    "ks:ks_type":"VILLAGE",
    "ks:ks_uagg_main":0,
    "name:eng_x_preferred":[
        "Bholaguri Gaon"
    ],
    "wof:name":"Bholaguri Gaon",
    "wof:placetype":"neighbourhood",
    "wof:population":1304
},
  "geometry": {"coordinates":[93.888665,26.517329],"type":"Point"}
}