{
  "type": "Feature",
  "properties": {
    "iso:country":"IN",
    "ks:ks_name":"Kadalichuan",
    "ks:ks_pop":253,
    "ks:ks_type":"HABITATION",
    "name:eng_x_preferred":[
        "Kadalichuan"
    ],
    "wof:name":"Kadalichuan",
    "wof:placetype":"locality",
    "wof:population":253
},
  "geometry": {"coordinates":[82.88833200000001,19.651739],"type":"Point"}
}