{
  "type": "Feature",
  "properties": {
    "gn:admin1_code":"23.0",
    "gn:admin2_code":"42.0",
    "gn:asciiname":"Mandar",
    "gn:country_code":"IN",
    "gn:dem":215,
    "gn:feature_class":"P",
    "gn:feature_code":"PPL",
    "gn:name":"Mandar",
    "gn:population":0,
    "gn:timezone":"Asia/Kolkata",
    "iso:country":"IN",
    "name:ceb_x_preferred":[
        "Mandar"
    ],
    "name:deu_x_preferred":[
        "Mandar"
    ],
    "name:fra_x_preferred":[
        "Mandar"
    ],
    "name:ind_x_preferred":[
        "Mandar"
    ],
    "wof:name":"Mandar",
    "wof:placetype":"locality"
},
  "geometry": {"coordinates":[75.10768,30.9945],"type":"Point"}
}