{
  "type": "Feature",
  "properties": {
    "iso:country":"IN",
    "ks:ks_name":"Nazarpur",
    "ks:ks_pop":109,
    "ks:ks_type":"HABITATION",
    "name:eng_x_preferred":[
        "Nazarpur"
    ],
    "wof:name":"Nazarpur",
    "wof:placetype":"locality",
    "wof:population":109
},
  "geometry": {"coordinates":[88.163595,26.272995],"type":"Point"}
}