{
  "type": "Feature",
  "properties": {
    "iso:country":"IN",
    "ks:ks_name":"Dewasar",
    "ks:ks_pop":30,
    "ks:ks_type":"HABITATION",
    "name:eng_x_preferred":[
        "Dewasar"
    ],
    "wof:name":"Dewasar",
    "wof:placetype":"locality",
    "wof:population":30
},
  "geometry": {"coordinates":[73.510139,27.974858],"type":"Point"}
}