{
  "type": "Feature",
  "properties": {
    "iso:country":"IN",
    "ks:ks_name":"Durgapur Barari",
    "ks:ks_pop":0,
    "ks:ks_type":"VILLAGE",
    "name:eng_x_preferred":[
        "Durgapur Barari"
    ],
    "wof:name":"Durgapur Barari",
    "wof:placetype":"locality",
    "wof:population":0
},
  "geometry": {"coordinates":[86.44433100000001,25.486457],"type":"Point"}
}