{
  "type": "Feature",
  "properties": {
    "iso:country":"IN",
    "ks:ks_name":"Milki",
    "ks:ks_pop":0,
    "ks:ks_type":"VILLAGE",
    "name:eng_x_preferred":[
        "Milki"
    ],
    "wof:name":"Milki",
    "wof:placetype":"locality",
    "wof:population":0
},
  "geometry": {"coordinates":[86.021474,26.227146],"type":"Point"}
}