{
  "type": "Feature",
  "properties": {
    "gn:admin1_code":"36",
    "gn:admin2_code":"191.0",
    "gn:asciiname":"Burhanpur",
    "gn:country_code":"IN",
    "gn:dem":77,
    "gn:feature_class":"P",
    "gn:feature_code":"PPL",
    "gn:name":"Burh\u0101npur",
    "gn:population":0,
    "gn:timezone":"Asia/Kolkata",
    "iso:country":"IN",
    "name:ara_x_preferred":[
        "\u0628\u0631\u0647\u0627\u0646 \u0628\u0648\u0631"
    ],
    "name:ben_x_preferred":[
        "\u09ac\u09c1\u09b0\u09b9\u09be\u09a8\u09aa\u09c1\u09b0"
    ],
    "name:bih_x_preferred":[
        "\u092c\u0941\u0930\u0939\u093e\u0928\u092a\u0941\u0930"
    ],
    "name:bpy_x_preferred":[
        "\u09ac\u09c1\u09b0\u09b9\u09be\u09a8\u09aa\u09c1\u09b0"
    ],
    "name:cat_x_preferred":[
        "Burhanpur"
    ],
    "name:ceb_x_preferred":[
        "Burh\u0101npur"
    ],
    "name:deu_x_preferred":[
        "Burhanpur"
    ],
    "name:fas_x_preferred":[
        "\u0628\u0631\u0647\u0627\u0646\u067e\u0648\u0631"
    ],
    "name:fra_x_preferred":[
        "Burhanpur"
    ],
    "name:glg_x_preferred":[
        "Burhanpur"
    ],
    "name:guj_x_preferred":[
        "\u0aac\u0ac1\u0ab0\u0ab9\u0abe\u0aa8\u0aaa\u0ac1\u0ab0"
    ],
    "name:hin_x_preferred":[
        "\u092c\u0941\u0930\u0939\u093e\u0928\u092a\u0941\u0930"
    ],
    "name:ita_x_preferred":[
        "Burhanpur"
    ],
    "name:jpn_x_preferred":[
        "\u30d6\u30eb\u30cf\u30fc\u30f3\u30d7\u30eb"
    ],
    "name:mar_x_preferred":[
        "\u092c\u0931\u094d\u0939\u093e\u0923\u092a\u0942\u0930"
    ],
    "name:mlg_x_preferred":[
        "Burhanpur"
    ],
    "name:msa_x_preferred":[
        "Burhanpur"
    ],
    "name:nep_x_preferred":[
        "\u092c\u0941\u0930\u0939\u093e\u0928\u092a\u0941\u0930"
    ],
    "name:new_x_preferred":[
        "\u092c\u0941\u0930\u094d\u0939\u0928\u094d\u092a\u0941\u0930"
    ],
    "name:nld_x_preferred":[
        "Burhanpur"
    ],
    "name:pam_x_preferred":[
        "Burhanpur"
    ],
    "name:pol_x_preferred":[
        "Barhanpur"
    ],
    "name:por_x_preferred":[
        "Burhanpur"
    ],
    "name:rus_x_preferred":[
        "\u0411\u0443\u0440\u0445\u0430\u043d\u043f\u0443\u0440"
    ],
    "name:san_x_preferred":[
        "\u092c\u0941\u0930\u0939\u093e\u0928\u092a\u0941\u0930\u092e\u094d"
    ],
    "name:spa_x_preferred":[
        "Burhanpur"
    ],
    "name:srp_x_preferred":[
        "\u0411\u0443\u0440\u0430\u043d\u043f\u0443\u0440"
    ],
    "name:swe_x_preferred":[
        "Burhanpur"
    ],
    "name:tam_x_preferred":[
        "\u0baa\u0bc1\u0bb0\u0bcd\u0bb9\u0bbe\u0ba9\u0bcd\u0baa\u0bc2\u0bb0\u0bcd"
    ],
    "name:tha_x_preferred":[
        "\u0e1e\u0e38\u0e23\u0e2b\u0e32\u0e19\u0e1b\u0e38\u0e23\u0e30"
    ],
    "name:tur_x_preferred":[
        "Burhanpur"
    ],
    "name:ukr_x_preferred":[
        "\u0411\u0443\u0440\u0445\u0430\u043d\u043f\u0443\u0440"
    ],
    "name:urd_x_preferred":[
        "\u0628\u0631\u06c1\u0627\u0646 \u067e\u0648\u0631"
    ],
    "name:vie_x_preferred":[
        "Burhanpur"
    ],
    "name:war_x_preferred":[
        "Burhanpur"
    ],
    "name:zho_x_preferred":[
        "\u5e03\u5c14\u6c49\u666e\u5c14"
    ],
    "wof:name":"Burhanpur",
    "wof:placetype":"locality"
},
  "geometry": {"coordinates":[83.32693,26.30273],"type":"Point"}
}