{
  "type": "Feature",
  "properties": {
    "iso:country":"IN",
    "ks:ks_name":"Bhataulia",
    "ks:ks_pop":0,
    "ks:ks_type":"VILLAGE",
    "name:eng_x_preferred":[
        "Bhataulia"
    ],
    "wof:name":"Bhataulia",
    "wof:placetype":"locality",
    "wof:population":0
},
  "geometry": {"coordinates":[83.57535900000001,25.656361],"type":"Point"}
}