{
  "type": "Feature",
  "properties": {
    "iso:country":"IN",
    "ks:ks_name":"Jhau Danga",
    "ks:ks_pop":669,
    "ks:ks_type":"VILLAGE",
    "ks:ks_uagg_main":0,
    "name:eng_x_preferred":[
        "Jhau Danga"
    ],
    "wof:name":"Jhau Danga",
    "wof:placetype":"neighbourhood",
    "wof:population":669
},
  "geometry": {"coordinates":[88.185288,24.367018],"type":"Point"}
}