{
  "type": "Feature",
  "properties": {
    "iso:country":"IN",
    "ks:ks_name":"Jaddu Jarkala",
    "ks:ks_pop":130,
    "ks:ks_type":"HABITATION",
    "name:eng_x_preferred":[
        "Jaddu Jarkala"
    ],
    "wof:name":"Jaddu Jarkala",
    "wof:placetype":"locality",
    "wof:population":130
},
  "geometry": {"coordinates":[74.929982,13.255049],"type":"Point"}
}