{
  "type": "Feature",
  "properties": {
    "gn:admin1_code":"24.0",
    "gn:admin2_code":"120.0",
    "gn:asciiname":"Pathraj Buzurg",
    "gn:country_code":"IN",
    "gn:dem":346,
    "gn:feature_class":"P",
    "gn:feature_code":"PPL",
    "gn:name":"Pathr\u0101j Buzurg",
    "gn:population":0,
    "gn:timezone":"Asia/Kolkata",
    "iso:country":"IN",
    "wof:name":"Pathraj Buzurg",
    "wof:placetype":"neighbourhood"
},
  "geometry": {"coordinates":[75.38402000000001,26.10797],"type":"Point"}
}