{
  "type": "Feature",
  "properties": {
    "iso:country":"IN",
    "ks:ks_name":"Neemanhalli",
    "ks:ks_pop":202,
    "ks:ks_type":"HABITATION",
    "name:eng_x_preferred":[
        "Neemanhalli"
    ],
    "wof:name":"Neemanhalli",
    "wof:placetype":"locality",
    "wof:population":202
},
  "geometry": {"coordinates":[75.43720500000001,13.310531],"type":"Point"}
}