{
  "type": "Feature",
  "properties": {
    "iso:country":"IN",
    "ks:ks_name":"Gopalapuram",
    "ks:ks_pop":285,
    "ks:ks_type":"HABITATION",
    "ks:ks_uagg_main":0,
    "name:eng_x_preferred":[
        "Gopalapuram"
    ],
    "wof:name":"Gopalapuram",
    "wof:placetype":"neighbourhood",
    "wof:population":285
},
  "geometry": {"coordinates":[81.29333099999999,16.856039],"type":"Point"}
}