{
  "type": "Feature",
  "properties": {
    "gn:admin1_code":"16",
    "gn:admin2_code":"499.0",
    "gn:asciiname":"Dondvada",
    "gn:country_code":"IN",
    "gn:dem":171,
    "gn:feature_class":"P",
    "gn:feature_code":"PPL",
    "gn:name":"Dondv\u0101da",
    "gn:population":0,
    "gn:timezone":"Asia/Kolkata",
    "iso:country":"IN",
    "wof:name":"Dondvada",
    "wof:placetype":"neighbourhood"
},
  "geometry": {"coordinates":[75.20514,21.16979],"type":"Point"}
}