{
  "type": "Feature",
  "properties": {
    "iso:country":"IN",
    "ks:ks_name":"Pujariput",
    "ks:ks_pop":625,
    "ks:ks_type":"HABITATION",
    "name:eng_x_preferred":[
        "Pujariput"
    ],
    "wof:name":"Pujariput",
    "wof:placetype":"locality",
    "wof:population":625
},
  "geometry": {"coordinates":[82.735439,18.367208],"type":"Point"}
}