{
  "type": "Feature",
  "properties": {
    "iso:country":"IN",
    "ks:ks_name":"Jhoksitola",
    "ks:ks_pop":392,
    "ks:ks_type":"HABITATION",
    "name:eng_x_preferred":[
        "Jhoksitola"
    ],
    "wof:name":"Jhoksitola",
    "wof:placetype":"locality",
    "wof:population":392
},
  "geometry": {"coordinates":[87.851316,25.237954],"type":"Point"}
}