{
  "type": "Feature",
  "properties": {
    "iso:country":"IN",
    "ks:ks_name":"Chhota Nalgerya",
    "ks:ks_pop":1603,
    "ks:ks_type":"VILLAGE",
    "name:eng_x_preferred":[
        "Chhota Nalgerya"
    ],
    "wof:name":"Chhota Nalgerya",
    "wof:placetype":"locality",
    "wof:population":1603
},
  "geometry": {"coordinates":[87.59978599999999,21.841803],"type":"Point"}
}