{
  "type": "Feature",
  "properties": {
    "iso:country":"IN",
    "ks:ks_name":"Dhorka",
    "ks:ks_pop":1360,
    "ks:ks_type":"VILLAGE",
    "ks:ks_uagg_main":0,
    "name:eng_x_preferred":[
        "Dhorka"
    ],
    "wof:name":"Dhorka",
    "wof:placetype":"neighbourhood",
    "wof:population":1360
},
  "geometry": {"coordinates":[76.905325,28.406045],"type":"Point"}
}