{
  "type": "Feature",
  "properties": {
    "gn:admin1_code":"25.0",
    "gn:admin2_code":"631.0",
    "gn:asciiname":"Gopanapalli",
    "gn:country_code":"IN",
    "gn:dem":891,
    "gn:feature_class":"P",
    "gn:feature_code":"PPL",
    "gn:name":"Gopanapalli",
    "gn:population":0,
    "gn:timezone":"Asia/Kolkata",
    "iso:country":"IN",
    "name:tam_x_preferred":[
        "\u0b95\u0bcb\u0baa\u0ba9\u0baa\u0bcd\u0baa\u0bb3\u0bcd\u0bb3\u0bbf"
    ],
    "wof:name":"Gopanapalli",
    "wof:placetype":"locality"
},
  "geometry": {"coordinates":[77.79640000000001,12.65127],"type":"Point"}
}