{
  "type": "Feature",
  "properties": {
    "iso:country":"IN",
    "ks:ks_name":"Yanadhicenter",
    "ks:ks_pop":162,
    "ks:ks_type":"HABITATION",
    "name:eng_x_preferred":[
        "Yanadhicenter"
    ],
    "wof:name":"Yanadhicenter",
    "wof:placetype":"locality",
    "wof:population":162
},
  "geometry": {"coordinates":[79.692027,13.890767],"type":"Point"}
}