{
  "type": "Feature",
  "properties": {
    "iso:country":"IN",
    "ks:ks_name":"Sutrakar",
    "ks:ks_pop":6456,
    "ks:ks_type":"VILLAGE",
    "name:eng_x_preferred":[
        "Sutrakar"
    ],
    "wof:name":"Sutrakar",
    "wof:placetype":"locality",
    "wof:population":6456
},
  "geometry": {"coordinates":[72.945246,20.145136],"type":"Point"}
}