{
  "type": "Feature",
  "properties": {
    "iso:country":"IN",
    "ks:ks_name":"Muraripur",
    "ks:ks_pop":777,
    "ks:ks_type":"VILLAGE",
    "ks:ks_uagg_main":0,
    "name:eng_x_preferred":[
        "Muraripur"
    ],
    "wof:name":"Muraripur",
    "wof:placetype":"neighbourhood",
    "wof:population":777
},
  "geometry": {"coordinates":[88.334659,22.105876],"type":"Point"}
}