{
  "type": "Feature",
  "properties": {
    "iso:country":"IN",
    "ks:ks_alt_nam":"It\u0101wa",
    "ks:ks_name":"Itawa",
    "ks:ks_pop":0,
    "ks:ks_type":"VILLAGE",
    "name:eng_x_preferred":[
        "Itawa"
    ],
    "name:eng_x_variant":[
        "It\u0101wa"
    ],
    "wof:name":"Itawa",
    "wof:placetype":"locality",
    "wof:population":0
},
  "geometry": {"coordinates":[83.92569899999999,25.143008],"type":"Point"}
}