{
  "type": "Feature",
  "properties": {
    "gn:admin1_code":"21.0",
    "gn:admin2_code":"390.0",
    "gn:asciiname":"Durikupada",
    "gn:country_code":"IN",
    "gn:dem":787,
    "gn:feature_class":"P",
    "gn:feature_code":"PPL",
    "gn:name":"Durikupada",
    "gn:population":0,
    "gn:timezone":"Asia/Kolkata",
    "iso:country":"IN",
    "ks:ks_name":"Durikupuda",
    "ks:ks_pop":306,
    "ks:ks_type":"VILLAGE",
    "name:eng_x_preferred":[
        "Durikupuda"
    ],
    "name:eng_x_variant":[
        "Durikupada"
    ],
    "wof:name":"Durikupuda",
    "wof:placetype":"locality",
    "wof:population":306
},
  "geometry": {"coordinates":[83.92382000000001,19.828679],"type":"Point"}
}