{
  "type": "Feature",
  "properties": {
    "iso:country":"IN",
    "ks:ks_name":"15 SD",
    "ks:ks_pop":23,
    "ks:ks_type":"VILLAGE",
    "name:eng_x_preferred":[
        "15 SD"
    ],
    "wof:name":"15 SD",
    "wof:placetype":"locality",
    "wof:population":23
},
  "geometry": {"coordinates":[73.654608,29.272],"type":"Point"}
}