{
  "type": "Feature",
  "properties": {
    "iso:country":"IN",
    "ks:ks_name":"Chhayan",
    "ks:ks_pop":805,
    "ks:ks_type":"HABITATION",
    "name:eng_x_preferred":[
        "Chhayan"
    ],
    "wof:name":"Chhayan",
    "wof:placetype":"locality",
    "wof:population":805
},
  "geometry": {"coordinates":[75.07730599999999,22.85222],"type":"Point"}
}