{
  "type": "Feature",
  "properties": {
    "iso:country":"IN",
    "ks:ks_alt_nam":"Naur\u012by\u0101la",
    "ks:ks_name":"Nauriyala",
    "ks:ks_type":"VILLAGE",
    "name:eng_x_preferred":[
        "Nauriyala"
    ],
    "name:eng_x_variant":[
        "Naur\u012by\u0101la"
    ],
    "wof:name":"Nauriyala",
    "wof:placetype":"locality"
},
  "geometry": {"coordinates":[70.344458,26.097589],"type":"Point"}
}