{
  "type": "Feature",
  "properties": {
    "iso:country":"IN",
    "ks:ks_alt_nam":"MANE WASTI",
    "ks:ks_name":"Mane Wasti",
    "ks:ks_pop":115,
    "ks:ks_type":"HABITATION",
    "name:eng_x_preferred":[
        "Mane Wasti"
    ],
    "wof:name":"Mane Wasti",
    "wof:placetype":"locality",
    "wof:population":115
},
  "geometry": {"coordinates":[74.871972,16.950407],"type":"Point"}
}