{
  "type": "Feature",
  "properties": {
    "iso:country":"IN",
    "ks:ks_name":"Tangta",
    "ks:ks_pop":980,
    "ks:ks_type":"HABITATION",
    "name:eng_x_preferred":[
        "Tangta"
    ],
    "wof:name":"Tangta",
    "wof:placetype":"locality",
    "wof:population":980
},
  "geometry": {"coordinates":[88.798652,27.128806],"type":"Point"}
}