{
  "type": "Feature",
  "properties": {
    "iso:country":"IN",
    "ks:ks_alt_nam":"Usar thakurwadi",
    "ks:ks_name":"Usar Thakurwadi",
    "ks:ks_pop":100,
    "ks:ks_type":"HABITATION",
    "name:eng_x_preferred":[
        "Usar Thakurwadi"
    ],
    "wof:name":"Usar Thakurwadi",
    "wof:placetype":"locality",
    "wof:population":100
},
  "geometry": {"coordinates":[73.082554,18.409834],"type":"Point"}
}