{
  "type": "Feature",
  "properties": {
    "gn:admin1_code":"11.0",
    "gn:admin2_code":"26.0",
    "gn:asciiname":"Lohshte",
    "gn:country_code":"IN",
    "gn:dem":1907,
    "gn:feature_class":"P",
    "gn:feature_code":"PPL",
    "gn:name":"Lohshte",
    "gn:population":0,
    "gn:timezone":"Asia/Kolkata",
    "iso:country":"IN",
    "wof:name":"Lohshte",
    "wof:placetype":"locality"
},
  "geometry": {"coordinates":[77.32918000000002,31.48298],"type":"Point"}
}