{
  "type": "Feature",
  "properties": {
    "iso:country":"IN",
    "ks:ks_name":"Mudalkeri",
    "ks:ks_pop":48,
    "ks:ks_type":"HABITATION",
    "name:eng_x_preferred":[
        "Mudalkeri"
    ],
    "wof:name":"Mudalkeri",
    "wof:placetype":"locality",
    "wof:population":48
},
  "geometry": {"coordinates":[74.463915,14.575724],"type":"Point"}
}