{
  "type": "Feature",
  "properties": {
    "gn:country":"IN",
    "gn:fcode":"PPL",
    "gn:pop":26443,
    "iso:country":"IN",
    "name:unk_x_variant":[
        "Alirajpur"
    ],
    "qs:name":"Rajpur",
    "qs:name_adm0":"India",
    "qs:name_adm1":"Gujarat",
    "qs:photos_9r":0,
    "qs:photos_sr":0,
    "qs:placetype":"Town",
    "qs:pop_sr":"7",
    "wd:wordcount":115,
    "wof:name":"Rajpur",
    "wof:placetype":"locality",
    "wof:population":26443
},
  "geometry": {"coordinates":[74.35511,22.30428],"type":"Point"}
}