{
  "type": "Feature",
  "properties": {
    "iso:country":"IN",
    "ks:ks_name":"Haito",
    "ks:ks_pop":326,
    "ks:ks_type":"VILLAGE",
    "ks:ks_uagg_main":0,
    "name:eng_x_preferred":[
        "Haito"
    ],
    "wof:name":"Haito",
    "wof:placetype":"neighbourhood",
    "wof:population":326
},
  "geometry": {"coordinates":[88.249441,25.045109],"type":"Point"}
}