{
  "type": "Feature",
  "properties": {
    "gn:admin1_code":"35",
    "gn:admin2_code":"451.0",
    "gn:asciiname":"Saliwara",
    "gn:country_code":"IN",
    "gn:dem":404,
    "gn:feature_class":"P",
    "gn:feature_code":"PPL",
    "gn:name":"S\u0101l\u012bw\u0101ra",
    "gn:population":0,
    "gn:timezone":"Asia/Kolkata",
    "iso:country":"IN",
    "ks:ks_name":"Saliwada",
    "ks:ks_pop":2718,
    "ks:ks_type":"VILLAGE",
    "name:eng_x_preferred":[
        "Saliwada"
    ],
    "name:eng_x_variant":[
        "Saliwara"
    ],
    "wof:name":"Saliwada",
    "wof:placetype":"locality",
    "wof:population":2718
},
  "geometry": {"coordinates":[79.999413,23.110499],"type":"Point"}
}