{
  "type": "Feature",
  "properties": {
    "gn:admin1_code":"2.0",
    "gn:asciiname":"Mallapur",
    "gn:country_code":"IN",
    "gn:dem":334,
    "gn:feature_class":"P",
    "gn:feature_code":"PPL",
    "gn:name":"Mall\u0101pur",
    "gn:population":0,
    "gn:timezone":"Asia/Kolkata",
    "iso:country":"IN",
    "wof:name":"Mallapur",
    "wof:placetype":"locality"
},
  "geometry": {"coordinates":[78.27212,19.03499],"type":"Point"}
}