{
  "type": "Feature",
  "properties": {
    "gn:admin1_code":"19.0",
    "gn:admin2_code":"568.0",
    "gn:asciiname":"Bennebisa",
    "gn:country_code":"IN",
    "gn:dem":595,
    "gn:feature_class":"P",
    "gn:feature_code":"PPL",
    "gn:name":"Benneb\u012bsa",
    "gn:population":0,
    "gn:timezone":"Asia/Kolkata",
    "iso:country":"IN",
    "wof:name":"Bennebisa",
    "wof:placetype":"locality"
},
  "geometry": {"coordinates":[75.4682,13.75792],"type":"Point"}
}