{
  "type": "Feature",
  "properties": {
    "iso:country":"IN",
    "ks:ks_name":"Khajurinali",
    "ks:ks_pop":3,
    "ks:ks_type":"HABITATION",
    "name:eng_x_preferred":[
        "Khajurinali"
    ],
    "wof:name":"Khajurinali",
    "wof:placetype":"locality",
    "wof:population":3
},
  "geometry": {"coordinates":[84.72694799999999,21.343365],"type":"Point"}
}