{
  "type": "Feature",
  "properties": {
    "gn:admin1_code":"16",
    "gn:admin2_code":"509.0",
    "gn:asciiname":"Padmapur",
    "gn:country_code":"IN",
    "gn:dem":200,
    "gn:feature_class":"P",
    "gn:feature_code":"PPL",
    "gn:name":"Padm\u0101pur",
    "gn:population":0,
    "gn:timezone":"Asia/Kolkata",
    "iso:country":"IN",
    "name:ben_x_preferred":[
        "\u09aa\u09a6\u09cd\u09ae\u09be\u09aa\u09c1\u09b0"
    ],
    "name:bpy_x_preferred":[
        "\u09aa\u09a6\u09cd\u09ae\u09be\u09aa\u09c1\u09b0"
    ],
    "name:ceb_x_preferred":[
        "Padmapur"
    ],
    "name:ita_x_preferred":[
        "Padmapur"
    ],
    "name:msa_x_preferred":[
        "Padmapur"
    ],
    "name:nld_x_preferred":[
        "Padmapur"
    ],
    "name:ori_x_preferred":[
        "\u0b2a\u0b26\u0b4d\u0b2e\u0b2a\u0b41\u0b30"
    ],
    "name:por_x_preferred":[
        "Padmapur"
    ],
    "name:swe_x_preferred":[
        "Padmapur"
    ],
    "name:vie_x_preferred":[
        "Padmapur"
    ],
    "name:zho_x_preferred":[
        "\u5e15\u5fb7\u9a6c\u666e\u5c14"
    ],
    "wof:name":"Padmapur",
    "wof:placetype":"locality"
},
  "geometry": {"coordinates":[79.30707,20.04537],"type":"Point"}
}