{
  "type": "Feature",
  "properties": {
    "iso:country":"IN",
    "ks:ks_name":"Mulgam Falia",
    "ks:ks_pop":559,
    "ks:ks_type":"HABITATION",
    "name:eng_x_preferred":[
        "Mulgam Falia"
    ],
    "wof:name":"Mulgam Falia",
    "wof:placetype":"locality",
    "wof:population":559
},
  "geometry": {"coordinates":[73.043278,20.359889],"type":"Point"}
}