{
  "type": "Feature",
  "properties": {
    "iso:country":"IN",
    "ks:ks_name":"Ningalarahatti",
    "ks:ks_pop":181,
    "ks:ks_type":"HABITATION",
    "name:eng_x_preferred":[
        "Ningalarahatti"
    ],
    "wof:name":"Ningalarahatti",
    "wof:placetype":"locality",
    "wof:population":181
},
  "geometry": {"coordinates":[76.563056,14.324444],"type":"Point"}
}