{
  "type": "Feature",
  "properties": {
    "iso:country":"IN",
    "ks:ks_name":"Langhat Tokbi",
    "ks:ks_pop":341,
    "ks:ks_type":"HABITATION",
    "name:eng_x_preferred":[
        "Langhat Tokbi"
    ],
    "wof:name":"Langhat Tokbi",
    "wof:placetype":"locality",
    "wof:population":341
},
  "geometry": {"coordinates":[93.150167,26.094612],"type":"Point"}
}