{
  "type": "Feature",
  "properties": {
    "iso:country":"IN",
    "ks:ks_name":"Mandirigoundankottai",
    "ks:ks_pop":245,
    "ks:ks_type":"HABITATION",
    "name:eng_x_preferred":[
        "Mandirigoundankottai"
    ],
    "wof:name":"Mandirigoundankottai",
    "wof:placetype":"locality",
    "wof:population":245
},
  "geometry": {"coordinates":[78.033435,12.006866],"type":"Point"}
}