{
  "type": "Feature",
  "properties": {
    "gn:admin1_code":"29",
    "gn:admin2_code":"241.0",
    "gn:asciiname":"Chomnagu",
    "gn:country_code":"IN",
    "gn:dem":3967,
    "gn:feature_class":"P",
    "gn:feature_code":"PPL",
    "gn:name":"Chomnagu",
    "gn:population":0,
    "gn:timezone":"Asia/Kolkata",
    "iso:country":"IN",
    "wof:name":"Chomnagu",
    "wof:placetype":"locality"
},
  "geometry": {"coordinates":[88.78230000000001,27.42472],"type":"Point"}
}