{
  "type": "Feature",
  "properties": {
    "iso:country":"IN",
    "ks:ks_name":"Kurukattur",
    "ks:ks_pop":598,
    "ks:ks_type":"HABITATION",
    "name:eng_x_preferred":[
        "Kurukattur"
    ],
    "wof:name":"Kurukattur",
    "wof:placetype":"locality",
    "wof:population":598
},
  "geometry": {"coordinates":[78.00873799999999,8.607549],"type":"Point"}
}