{
  "type": "Feature",
  "properties": {
    "iso:country":"IN",
    "ks:ks_alt_nam":"Chaudhari faliya",
    "ks:ks_name":"Chaudhari Faliya",
    "ks:ks_pop":89,
    "ks:ks_type":"HABITATION",
    "name:eng_x_preferred":[
        "Chaudhari Faliya"
    ],
    "wof:name":"Chaudhari Faliya",
    "wof:placetype":"locality",
    "wof:population":89
},
  "geometry": {"coordinates":[73.450576,20.486988],"type":"Point"}
}