{
  "type": "Feature",
  "properties": {
    "iso:country":"IN",
    "ks:ks_name":"Pahar Gaon",
    "ks:ks_pop":51,
    "ks:ks_type":"VILLAGE",
    "name:eng_x_preferred":[
        "Pahar Gaon"
    ],
    "wof:name":"Pahar Gaon",
    "wof:placetype":"locality",
    "wof:population":51
},
  "geometry": {"coordinates":[78.769926,29.869114],"type":"Point"}
}