{
  "type": "Feature",
  "properties": {
    "iso:country":"IN",
    "ks:ks_name":"Haleji",
    "ks:ks_pop":238,
    "ks:ks_type":"HABITATION",
    "name:eng_x_preferred":[
        "Haleji"
    ],
    "wof:name":"Haleji",
    "wof:placetype":"locality",
    "wof:population":238
},
  "geometry": {"coordinates":[75.252741,12.896431],"type":"Point"}
}