{
  "type": "Feature",
  "properties": {
    "gn:admin1_code":"16",
    "gn:admin2_code":"508.0",
    "gn:asciiname":"Ambejhari",
    "gn:country_code":"IN",
    "gn:dem":271,
    "gn:feature_class":"P",
    "gn:feature_code":"PPL",
    "gn:name":"Ambejhari",
    "gn:population":0,
    "gn:timezone":"Asia/Kolkata",
    "iso:country":"IN",
    "ks:ks_name":"Ambezari",
    "ks:ks_pop":195,
    "ks:ks_type":"VILLAGE",
    "name:eng_x_preferred":[
        "Ambezari"
    ],
    "name:eng_x_variant":[
        "Ambejhari"
    ],
    "wof:name":"Ambezari",
    "wof:placetype":"locality",
    "wof:population":195
},
  "geometry": {"coordinates":[80.306292,20.549258],"type":"Point"}
}