{
  "type": "Feature",
  "properties": {
    "gn:admin1_code":"16",
    "gn:admin2_code":"508.0",
    "gn:asciiname":"Ambejhari",
    "gn:country_code":"IN",
    "gn:dem":271,
    "gn:feature_class":"P",
    "gn:feature_code":"PPL",
    "gn:name":"Ambejhari",
    "gn:population":0,
    "gn:timezone":"Asia/Kolkata",
    "iso:country":"IN",
    "wof:name":"Ambejhari",
    "wof:placetype":"locality"
},
  "geometry": {"coordinates":[80.30665999999999,20.54847],"type":"Point"}
}