{
  "type": "Feature",
  "properties": {
    "iso:country":"IN",
    "ks:ks_alt_nam":"Daulatpur Chondi",
    "ks:ks_name":"Daulatpur",
    "ks:ks_type":"VILLAGE",
    "ks:ks_uagg_main":0,
    "name:eng_x_preferred":[
        "Daulatpur"
    ],
    "name:eng_x_variant":[
        "Daulatpur Chondi"
    ],
    "wof:name":"Daulatpur",
    "wof:placetype":"neighbourhood"
},
  "geometry": {"coordinates":[85.701655,25.472849],"type":"Point"}
}