{
  "type": "Feature",
  "properties": {
    "iso:country":"IN",
    "ks:ks_alt_nam":"S\u0101gjori",
    "ks:ks_name":"Sagjori",
    "ks:ks_pop":1813,
    "ks:ks_type":"VILLAGE",
    "name:eng_x_preferred":[
        "Sagjori"
    ],
    "name:eng_x_variant":[
        "S\u0101gjori"
    ],
    "wof:name":"Sagjori",
    "wof:placetype":"locality",
    "wof:population":1813
},
  "geometry": {"coordinates":[85.091274,22.274742],"type":"Point"}
}