{
  "type": "Feature",
  "properties": {
    "iso:country":"IN",
    "ks:ks_alt_nam":"dausigami 1",
    "ks:ks_name":"Dausigami 1",
    "ks:ks_pop":942,
    "ks:ks_type":"HABITATION",
    "name:eng_x_preferred":[
        "Dausigami 1"
    ],
    "wof:name":"Dausigami 1",
    "wof:placetype":"locality",
    "wof:population":942
},
  "geometry": {"coordinates":[91.361436,26.575857],"type":"Point"}
}