{
  "type": "Feature",
  "properties": {
    "gn:admin1_code":"19.0",
    "gn:admin2_code":"581.0",
    "gn:asciiname":"Gulipalli",
    "gn:country_code":"IN",
    "gn:dem":785,
    "gn:feature_class":"P",
    "gn:feature_code":"PPL",
    "gn:name":"Gulipalli",
    "gn:population":0,
    "gn:timezone":"Asia/Kolkata",
    "iso:country":"IN",
    "wof:name":"Gulipalli",
    "wof:placetype":"neighbourhood"
},
  "geometry": {"coordinates":[78.11645,12.87391],"type":"Point"}
}