{
  "type": "Feature",
  "properties": {
    "iso:country":"IN",
    "ks:ks_name":"Dukhinaikguda",
    "ks:ks_pop":354,
    "ks:ks_type":"VILLAGE",
    "name:eng_x_preferred":[
        "Dukhinaikguda"
    ],
    "wof:name":"Dukhinaikguda",
    "wof:placetype":"locality",
    "wof:population":354
},
  "geometry": {"coordinates":[83.42697099999999,19.225461],"type":"Point"}
}