{
  "type": "Feature",
  "properties": {
    "iso:country":"IN",
    "ks:ks_name":"Thakur Purwa",
    "ks:ks_pop":175,
    "ks:ks_type":"HABITATION",
    "name:eng_x_preferred":[
        "Thakur Purwa"
    ],
    "wof:name":"Thakur Purwa",
    "wof:placetype":"locality",
    "wof:population":175
},
  "geometry": {"coordinates":[81.19506,26.836076],"type":"Point"}
}