{
  "type": "Feature",
  "properties": {
    "iso:country":"IN",
    "ks:ks_alt_nam":"KADUKANADEWASTI",
    "ks:ks_name":"Kadukanadewasti",
    "ks:ks_pop":1160,
    "ks:ks_type":"HABITATION",
    "name:eng_x_preferred":[
        "Kadukanadewasti"
    ],
    "wof:name":"Kadukanadewasti",
    "wof:placetype":"locality",
    "wof:population":1160
},
  "geometry": {"coordinates":[74.58524199999999,19.834268],"type":"Point"}
}