{
  "type": "Feature",
  "properties": {
    "iso:country":"IN",
    "ks:ks_name":"Mahuladagar",
    "ks:ks_pop":154,
    "ks:ks_type":"HABITATION",
    "name:eng_x_preferred":[
        "Mahuladagar"
    ],
    "wof:name":"Mahuladagar",
    "wof:placetype":"locality",
    "wof:population":154
},
  "geometry": {"coordinates":[85.460616,20.848694],"type":"Point"}
}