{
  "type": "Feature",
  "properties": {
    "iso:country":"IN",
    "ks:ks_name":"S. Pudhukulam",
    "ks:ks_pop":116,
    "ks:ks_type":"HABITATION",
    "name:eng_x_preferred":[
        "S. Pudhukulam"
    ],
    "wof:name":"S. Pudhukulam",
    "wof:placetype":"locality",
    "wof:population":116
},
  "geometry": {"coordinates":[78.602577,9.72902],"type":"Point"}
}