{
  "type": "Feature",
  "properties": {
    "iso:country":"IN",
    "ks:ks_name":"Padagar Dhangarwadi",
    "ks:ks_pop":17,
    "ks:ks_type":"HABITATION",
    "name:eng_x_preferred":[
        "Padagar Dhangarwadi"
    ],
    "wof:name":"Padagar Dhangarwadi",
    "wof:placetype":"locality",
    "wof:population":17
},
  "geometry": {"coordinates":[73.555064,16.385586],"type":"Point"}
}