{
  "type": "Feature",
  "properties": {
    "iso:country":"IN",
    "ks:ks_name":"Banota Walla",
    "ks:ks_pop":41,
    "ks:ks_type":"VILLAGE",
    "name:eng_x_preferred":[
        "Banota Walla"
    ],
    "wof:name":"Banota Walla",
    "wof:placetype":"locality",
    "wof:population":41
},
  "geometry": {"coordinates":[78.23898199999999,30.676508],"type":"Point"}
}