{
  "type": "Feature",
  "properties": {
    "gn:admin1_code":"24.0",
    "gn:admin2_code":"120",
    "gn:asciiname":"Kunwarawas",
    "gn:country_code":"IN",
    "gn:dem":298,
    "gn:feature_class":"P",
    "gn:feature_code":"PPL",
    "gn:name":"Kunwar\u0101w\u0101s",
    "gn:population":0,
    "gn:timezone":"Asia/Kolkata",
    "iso:country":"IN",
    "wof:name":"Kunwarawas",
    "wof:placetype":"locality"
},
  "geometry": {"coordinates":[75.53166,25.92478],"type":"Point"}
}