{
  "type": "Feature",
  "properties": {
    "gn:admin1_code":"11",
    "gn:admin2_code":"23.0",
    "gn:asciiname":"Khajri",
    "gn:country_code":"IN",
    "gn:dem":2272,
    "gn:feature_class":"P",
    "gn:feature_code":"PPL",
    "gn:name":"Khajri",
    "gn:population":0,
    "gn:timezone":"Asia/Kolkata",
    "iso:country":"IN",
    "wof:name":"Khajri",
    "wof:placetype":"locality"
},
  "geometry": {"coordinates":[76.18046,32.71958],"type":"Point"}
}