{
  "type": "Feature",
  "properties": {
    "iso:country":"IN",
    "ks:ks_name":"Burhanpur",
    "ks:ks_pop":941,
    "ks:ks_type":"HABITATION",
    "name:eng_x_preferred":[
        "Burhanpur"
    ],
    "name:hin_x_preferred":[
        "\u092c\u0941\u0930\u0939\u093e\u0928\u092a\u0941\u0930"
    ],
    "wof:name":"Burhanpur",
    "wof:placetype":"locality",
    "wof:population":941
},
  "geometry": {"coordinates":[82.510977,25.931848],"type":"Point"}
}