{
  "type": "Feature",
  "properties": {
    "iso:country":"IN",
    "ks:ks_name":"Mandalpadar",
    "ks:ks_pop":245,
    "ks:ks_type":"VILLAGE",
    "name:eng_x_preferred":[
        "Mandalpadar"
    ],
    "wof:name":"Mandalpadar",
    "wof:placetype":"locality",
    "wof:population":245
},
  "geometry": {"coordinates":[83.662628,20.087331],"type":"Point"}
}