{
  "type": "Feature",
  "properties": {
    "gn:admin1_code":"36",
    "gn:admin2_code":"199.0",
    "gn:asciiname":"Gorkhi",
    "gn:country_code":"IN",
    "gn:dem":81,
    "gn:feature_class":"P",
    "gn:feature_code":"PPL",
    "gn:name":"Gorkhi",
    "gn:population":0,
    "gn:timezone":"Asia/Kolkata",
    "iso:country":"IN",
    "name:nep_x_preferred":[
        "\u0917\u094b\u0930\u094d\u0916\u0940 \u0917\u093e\u0909\u0901"
    ],
    "wof:name":"Gorkhi",
    "wof:placetype":"locality"
},
  "geometry": {"coordinates":[83.16481999999998,25.17169],"type":"Point"}
}