{
  "type": "Feature",
  "properties": {
    "iso:country":"IN",
    "ks:ks_alt_nam":"Jackabpur FV",
    "ks:ks_name":"Jackabpur Fv",
    "ks:ks_pop":3230,
    "ks:ks_type":"HABITATION",
    "name:eng_x_preferred":[
        "Jackabpur Fv"
    ],
    "wof:name":"Jackabpur Fv",
    "wof:placetype":"locality",
    "wof:population":3230
},
  "geometry": {"coordinates":[92.53001399999999,24.265059],"type":"Point"}
}