{
  "type": "Feature",
  "properties": {
    "iso:country":"IN",
    "ks:ks_name":"Besanapath",
    "ks:ks_pop":504,
    "ks:ks_type":"HABITATION",
    "name:eng_x_preferred":[
        "Besanapath"
    ],
    "wof:name":"Besanapath",
    "wof:placetype":"locality",
    "wof:population":504
},
  "geometry": {"coordinates":[84.293578,23.238322],"type":"Point"}
}