{
  "type": "Feature",
  "properties": {
    "iso:country":"IN",
    "ks:ks_name":"Dighaldari West",
    "ks:ks_pop":1025,
    "ks:ks_type":"HABITATION",
    "name:eng_x_preferred":[
        "Dighaldari West"
    ],
    "wof:name":"Dighaldari West",
    "wof:placetype":"locality",
    "wof:population":1025
},
  "geometry": {"coordinates":[92.601597,26.257249],"type":"Point"}
}