{
  "type": "Feature",
  "properties": {
    "iso:country":"IN",
    "ks:ks_name":"Penjikupa",
    "ks:ks_pop":95,
    "ks:ks_type":"VILLAGE",
    "name:eng_x_preferred":[
        "Penjikupa"
    ],
    "wof:name":"Penjikupa",
    "wof:placetype":"locality",
    "wof:population":95
},
  "geometry": {"coordinates":[83.564746,20.280226],"type":"Point"}
}