{
  "type": "Feature",
  "properties": {
    "gn:admin1_code":"25.0",
    "gn:admin2_code":"633.0",
    "gn:asciiname":"Velarasi Vadamalaipalaiyam",
    "gn:country_code":"IN",
    "gn:dem":365,
    "gn:feature_class":"P",
    "gn:feature_code":"PPL",
    "gn:name":"Velar\u0101si Vadamalaip\u0101laiyam",
    "gn:population":0,
    "gn:timezone":"Asia/Kolkata",
    "iso:country":"IN",
    "wof:name":"Velarasi Vadamalaipalaiyam",
    "wof:placetype":"locality"
},
  "geometry": {"coordinates":[77.34838000000001,10.89341],"type":"Point"}
}