{
  "type": "Feature",
  "properties": {
    "iso:country":"IN",
    "ks:ks_name":"Mettupatti",
    "ks:ks_pop":515,
    "ks:ks_type":"HABITATION",
    "name:eng_x_preferred":[
        "Mettupatti"
    ],
    "wof:name":"Mettupatti",
    "wof:placetype":"locality",
    "wof:population":515
},
  "geometry": {"coordinates":[78.925009,10.506086],"type":"Point"}
}