{
  "type": "Feature",
  "properties": {
    "iso:country":"IN",
    "ks:ks_name":"Richchola Mustqil",
    "ks:ks_pop":897,
    "ks:ks_type":"HABITATION",
    "name:eng_x_preferred":[
        "Richchola Mustqil"
    ],
    "wof:name":"Richchola Mustqil",
    "wof:placetype":"locality",
    "wof:population":897
},
  "geometry": {"coordinates":[79.91468399999999,28.619045],"type":"Point"}
}