{
  "type": "Feature",
  "properties": {
    "iso:country":"IN",
    "ks:ks_name":"Parivila",
    "ks:ks_pop":455,
    "ks:ks_type":"VILLAGE",
    "name:eng_x_preferred":[
        "Parivila"
    ],
    "wof:name":"Parivila",
    "wof:placetype":"locality",
    "wof:population":455
},
  "geometry": {"coordinates":[87.01098500000001,21.493864],"type":"Point"}
}