{
  "type": "Feature",
  "properties": {
    "iso:country":"IN",
    "ks:ks_name":"Baharchandberya",
    "ks:ks_pop":1192,
    "ks:ks_type":"VILLAGE",
    "name:eng_x_preferred":[
        "Baharchandberya"
    ],
    "wof:name":"Baharchandberya",
    "wof:placetype":"locality",
    "wof:population":1192
},
  "geometry": {"coordinates":[87.828823,21.894123],"type":"Point"}
}