{
  "type": "Feature",
  "properties": {
    "iso:country":"IN",
    "ks:ks_name":"Valpani",
    "ks:ks_pop":37,
    "ks:ks_type":"HABITATION",
    "name:eng_x_preferred":[
        "Valpani"
    ],
    "wof:name":"Valpani",
    "wof:placetype":"locality",
    "wof:population":37
},
  "geometry": {"coordinates":[74.81877,21.731781],"type":"Point"}
}