{
  "type": "Feature",
  "properties": {
    "gn:admin1_code":"35",
    "gn:admin2_code":"456.0",
    "gn:asciiname":"Khari",
    "gn:country_code":"IN",
    "gn:dem":534,
    "gn:feature_class":"P",
    "gn:feature_code":"PPL",
    "gn:name":"Kh\u0101ri",
    "gn:population":0,
    "gn:timezone":"Asia/Kolkata",
    "iso:country":"IN",
    "ks:ks_alt_nam":"Kh\u0101ri",
    "ks:ks_name":"Khari",
    "ks:ks_pop":1854,
    "ks:ks_type":"VILLAGE",
    "ks:ks_uagg_main":0,
    "name:ceb_x_preferred":[
        "Khari"
    ],
    "name:deu_x_preferred":[
        "Khari"
    ],
    "name:eng_x_preferred":[
        "Khari"
    ],
    "name:eng_x_variant":[
        "Kh\u0101ri"
    ],
    "name:msa_x_preferred":[
        "Khari"
    ],
    "name:new_x_preferred":[
        "\u0916\u0930\u0940"
    ],
    "name:pol_x_preferred":[
        "Khari"
    ],
    "wof:name":"Khari",
    "wof:placetype":"neighbourhood",
    "wof:population":1854
},
  "geometry": {"coordinates":[79.742524,22.068507],"type":"Point"}
}