{
  "type": "Feature",
  "properties": {
    "gn:admin1_code":"2",
    "gn:admin2_code":"545.0",
    "gn:asciiname":"Patapadu",
    "gn:country_code":"IN",
    "gn:dem":243,
    "gn:feature_class":"P",
    "gn:feature_code":"PPL",
    "gn:name":"P\u0101tap\u0101du",
    "gn:population":0,
    "gn:timezone":"Asia/Kolkata",
    "iso:country":"IN",
    "ks:ks_name":"Pathapadu",
    "ks:ks_pop":97,
    "ks:ks_type":"HABITATION",
    "name:eng_x_preferred":[
        "Pathapadu"
    ],
    "name:eng_x_variant":[
        "Patapadu"
    ],
    "wof:name":"Pathapadu",
    "wof:placetype":"locality",
    "wof:population":97
},
  "geometry": {"coordinates":[82.047059,17.494099],"type":"Point"}
}