{
  "type": "Feature",
  "properties": {
    "iso:country":"IN",
    "ks:ks_name":"Vajantriwada",
    "ks:ks_pop":20,
    "ks:ks_type":"HABITATION",
    "name:eng_x_preferred":[
        "Vajantriwada"
    ],
    "wof:name":"Vajantriwada",
    "wof:placetype":"locality",
    "wof:population":20
},
  "geometry": {"coordinates":[74.256017,14.888345],"type":"Point"}
}