{
  "type": "Feature",
  "properties": {
    "gn:admin1_code":"19.0",
    "gn:admin2_code":"567",
    "gn:asciiname":"Bilchodu",
    "gn:cc2":"IN",
    "gn:country_code":"IN",
    "gn:dem":629,
    "gn:feature_class":"P",
    "gn:feature_code":"PPL",
    "gn:name":"Bilchodu",
    "gn:population":0,
    "gn:timezone":"Asia/Kolkata",
    "iso:country":"IN",
    "name:und_x_variant":[
        "Bilchod"
    ],
    "wof:name":"Bilchodu",
    "wof:placetype":"locality"
},
  "geometry": {"coordinates":[76.16246,14.49552],"type":"Point"}
}