{
  "type": "Feature",
  "properties": {
    "iso:country":"IN",
    "ks:ks_name":"Barbaria",
    "ks:ks_pop":1096,
    "ks:ks_type":"VILLAGE",
    "ks:ks_uagg_main":0,
    "name:eng_x_preferred":[
        "Barbaria"
    ],
    "wof:name":"Barbaria",
    "wof:placetype":"locality",
    "wof:population":1096
},
  "geometry": {"coordinates":[87.460589,21.615358],"type":"Point"}
}