{
  "type": "Feature",
  "properties": {
    "iso:country":"IN",
    "ks:ks_name":"Vishnupura",
    "ks:ks_pop":1060,
    "ks:ks_type":"HABITATION",
    "name:eng_x_preferred":[
        "Vishnupura"
    ],
    "wof:name":"Vishnupura",
    "wof:placetype":"locality",
    "wof:population":1060
},
  "geometry": {"coordinates":[72.51298,23.59427],"type":"Point"}
}