{
  "type": "Feature",
  "properties": {
    "iso:country":"IN",
    "ks:ks_name":"Kumetipara",
    "ks:ks_pop":58,
    "ks:ks_type":"HABITATION",
    "name:eng_x_preferred":[
        "Kumetipara"
    ],
    "wof:name":"Kumetipara",
    "wof:placetype":"locality",
    "wof:population":58
},
  "geometry": {"coordinates":[80.635368,20.562689],"type":"Point"}
}