{
  "type": "Feature",
  "properties": {
    "iso:country":"IN",
    "ks:ks_name":"Kalmane",
    "ks:ks_pop":40,
    "ks:ks_type":"HABITATION",
    "name:eng_x_preferred":[
        "Kalmane"
    ],
    "wof:name":"Kalmane",
    "wof:placetype":"locality",
    "wof:population":40
},
  "geometry": {"coordinates":[74.749678,14.595426],"type":"Point"}
}