{
  "type": "Feature",
  "properties": {
    "iso:country":"IN",
    "ks:ks_alt_nam":"Bh\u0101tgarh",
    "ks:ks_alt_nam_2":"Bhatgarh",
    "ks:ks_name":"Bhat",
    "ks:ks_type":"VILLAGE",
    "name:eng_x_preferred":[
        "Bhat"
    ],
    "name:eng_x_variant":[
        "Bh\u0101tgarh",
        "Bhatgarh"
    ],
    "wof:name":"Bhat",
    "wof:placetype":"locality"
},
  "geometry": {"coordinates":[79.920074,29.731778],"type":"Point"}
}