{
  "type": "Feature",
  "properties": {
    "gn:admin1_code":"34.0",
    "gn:admin2_code":"218.0",
    "gn:asciiname":"Laka Tola",
    "gn:country_code":"IN",
    "gn:dem":67,
    "gn:feature_class":"P",
    "gn:feature_code":"PPL",
    "gn:name":"L\u0101ka Tola",
    "gn:population":0,
    "gn:timezone":"Asia/Kolkata",
    "iso:country":"IN",
    "wof:name":"Laka Tola",
    "wof:placetype":"locality"
},
  "geometry": {"coordinates":[84.60655,26.25275],"type":"Point"}
}