{
  "type": "Feature",
  "properties": {
    "gn:admin1_code":"11.0",
    "gn:admin2_code":"31.0",
    "gn:asciiname":"Simi",
    "gn:country_code":"IN",
    "gn:dem":1265,
    "gn:feature_class":"P",
    "gn:feature_code":"PPL",
    "gn:name":"Simi",
    "gn:population":0,
    "gn:timezone":"Asia/Kolkata",
    "iso:country":"IN",
    "name:ceb_x_preferred":[
        "Simi"
    ],
    "name:deu_x_preferred":[
        "Simi"
    ],
    "name:fas_x_preferred":[
        "\u0633\u06cc\u0645\u06cc"
    ],
    "name:fin_x_preferred":[
        "Simi"
    ],
    "name:fra_x_preferred":[
        "Simi"
    ],
    "name:ita_x_preferred":[
        "Simi"
    ],
    "name:nld_x_preferred":[
        "Simi"
    ],
    "name:spa_x_preferred":[
        "Simi"
    ],
    "name:swe_x_preferred":[
        "Simi"
    ],
    "wof:name":"Simi",
    "wof:placetype":"locality"
},
  "geometry": {"coordinates":[77.02070999999999,30.91438],"type":"Point"}
}