{
  "type": "Feature",
  "properties": {
    "gn:admin1_code":"36",
    "gn:admin2_code":"200.0",
    "gn:asciiname":"Harankhuri",
    "gn:country_code":"IN",
    "gn:dem":317,
    "gn:feature_class":"P",
    "gn:feature_code":"PPL",
    "gn:name":"Harankhuri",
    "gn:population":0,
    "gn:timezone":"Asia/Kolkata",
    "iso:country":"IN",
    "ks:ks_name":"Haran Khury",
    "ks:ks_pop":195,
    "ks:ks_type":"VILLAGE",
    "name:eng_x_preferred":[
        "Haran Khury"
    ],
    "name:eng_x_variant":[
        "Harankhuri"
    ],
    "wof:name":"Haran Khury",
    "wof:placetype":"locality",
    "wof:population":195
},
  "geometry": {"coordinates":[83.19893399999999,24.689023],"type":"Point"}
}