{
  "type": "Feature",
  "properties": {
    "iso:country":"IN",
    "ks:ks_name":"Dhrubapahalipur",
    "ks:ks_pop":792,
    "ks:ks_type":"VILLAGE",
    "name:eng_x_preferred":[
        "Dhrubapahalipur"
    ],
    "wof:name":"Dhrubapahalipur",
    "wof:placetype":"locality",
    "wof:population":792
},
  "geometry": {"coordinates":[86.83301899999999,20.777968],"type":"Point"}
}