{
  "type": "Feature",
  "properties": {
    "gn:country":"IN",
    "gn:fcode":"PPL",
    "gn:population":0,
    "iso:country":"IN",
    "name:tat_x_preferred":[
        "\u0414\u0443\u0432\u0430\u0440\u043a\u0430"
    ],
    "qs_pg:aaroncc":"IN",
    "qs_pg:gn_country":"IN",
    "qs_pg:gn_fcode":"PPL",
    "qs_pg:gn_pop":0,
    "qs_pg:name":"Duwarka",
    "qs_pg:name_adm0":"India",
    "qs_pg:name_adm1":"Haryana",
    "qs_pg:photos_9r":0,
    "qs_pg:photos_sr":0,
    "qs_pg:pop_sr":0,
    "qs_pg:qs_pg_placetype":"locality",
    "qs_pg:qs_pg_placetype_gp":"Town",
    "qs_pg:woe_adm0":23424848,
    "woe:adm0_id":23424848,
    "woe:name_adm0":"India",
    "woe:name_adm1":"Haryana",
    "woe:placetype":"Town",
    "wof:name":"Duwarka",
    "wof:placetype":"neighbourhood"
},
  "geometry": {"coordinates":[77.05313,28.59146],"type":"Point"}
}