{
  "type": "Feature",
  "properties": {
    "iso:country":"IN",
    "ks:ks_name":"Jamunpani",
    "ks:ks_pop":102,
    "ks:ks_type":"VILLAGE",
    "name:eng_x_preferred":[
        "Jamunpani"
    ],
    "wof:name":"Jamunpani",
    "wof:placetype":"locality",
    "wof:population":102
},
  "geometry": {"coordinates":[79.595759,23.004077],"type":"Point"}
}