{
  "type": "Feature",
  "properties": {
    "iso:country":"IN",
    "ks:ks_name":"Devipur",
    "ks:ks_pop":0,
    "ks:ks_type":"VILLAGE",
    "name:eng_x_preferred":[
        "Devipur"
    ],
    "wof:name":"Devipur",
    "wof:placetype":"locality",
    "wof:population":0
},
  "geometry": {"coordinates":[83.42341999999999,27.176784],"type":"Point"}
}