{
  "type": "Feature",
  "properties": {
    "iso:country":"IN",
    "ks:ks_name":"Achla",
    "ks:ks_pop":236,
    "ks:ks_type":"VILLAGE",
    "name:eng_x_preferred":[
        "Achla"
    ],
    "wof:name":"Achla",
    "wof:placetype":"locality",
    "wof:population":236
},
  "geometry": {"coordinates":[71.35592699999999,26.706818],"type":"Point"}
}