{
  "type": "Feature",
  "properties": {
    "gn:admin1_code":"19.0",
    "gn:admin2_code":"574.0",
    "gn:asciiname":"Dumgere",
    "gn:country_code":"IN",
    "gn:dem":923,
    "gn:feature_class":"P",
    "gn:feature_code":"PPL",
    "gn:name":"Dumgere",
    "gn:population":0,
    "gn:timezone":"Asia/Kolkata",
    "iso:country":"IN",
    "wof:name":"Dumgere",
    "wof:placetype":"neighbourhood"
},
  "geometry": {"coordinates":[76.19686,12.91342],"type":"Point"}
}