{
  "type": "Feature",
  "properties": {
    "gn:admin1_code":"11.0",
    "gn:admin2_code":"33.0",
    "gn:asciiname":"Jewari",
    "gn:country_code":"IN",
    "gn:dem":1108,
    "gn:feature_class":"P",
    "gn:feature_code":"PPL",
    "gn:name":"Jewari",
    "gn:population":0,
    "gn:timezone":"Asia/Kolkata",
    "iso:country":"IN",
    "wof:name":"Jewari",
    "wof:placetype":"locality"
},
  "geometry": {"coordinates":[77.67371999999997,31.39161],"type":"Point"}
}