{
  "type": "Feature",
  "properties": {
    "iso:country":"IN",
    "ks:ks_name":"Madappady",
    "ks:ks_pop":1009,
    "ks:ks_type":"VILLAGE",
    "name:eng_x_preferred":[
        "Madappady"
    ],
    "wof:name":"Madappady",
    "wof:placetype":"locality",
    "wof:population":1009
},
  "geometry": {"coordinates":[75.53475299999999,12.584129],"type":"Point"}
}