{
  "type": "Feature",
  "properties": {
    "gn:admin1_code":"36",
    "gn:admin2_code":"179.0",
    "gn:asciiname":"Khajuri",
    "gn:country_code":"IN",
    "gn:dem":100,
    "gn:feature_class":"P",
    "gn:feature_code":"PPL",
    "gn:name":"Khaj\u016bri",
    "gn:population":0,
    "gn:timezone":"Asia/Kolkata",
    "iso:country":"IN",
    "ks:ks_name":"Khajuri",
    "ks:ks_pop":795,
    "ks:ks_type":"VILLAGE",
    "name:eng_x_preferred":[
        "Khajuri"
    ],
    "wof:name":"Khajuri",
    "wof:placetype":"locality",
    "wof:population":795
},
  "geometry": {"coordinates":[82.10408099999999,26.079411],"type":"Point"}
}