{
  "type": "Feature",
  "properties": {
    "iso:country":"IN",
    "ks:ks_name":"Dohifodewasti",
    "ks:ks_pop":108,
    "ks:ks_type":"HABITATION",
    "name:eng_x_preferred":[
        "Dohifodewasti"
    ],
    "wof:name":"Dohifodewasti",
    "wof:placetype":"locality",
    "wof:population":108
},
  "geometry": {"coordinates":[75.660642,18.08711],"type":"Point"}
}