{
  "type": "Feature",
  "properties": {
    "iso:country":"IN",
    "ks:ks_name":"Dhakpura",
    "ks:ks_pop":348,
    "ks:ks_type":"HABITATION",
    "name:eng_x_preferred":[
        "Dhakpura"
    ],
    "wof:name":"Dhakpura",
    "wof:placetype":"locality",
    "wof:population":348
},
  "geometry": {"coordinates":[79.183345,27.531323],"type":"Point"}
}