{
  "type": "Feature",
  "properties": {
    "iso:country":"IN",
    "ks:ks_name":"Deshmukh Nagar",
    "ks:ks_pop":1234,
    "ks:ks_type":"HABITATION",
    "name:eng_x_preferred":[
        "Deshmukh Nagar"
    ],
    "wof:name":"Deshmukh Nagar",
    "wof:placetype":"locality",
    "wof:population":1234
},
  "geometry": {"coordinates":[73.44572100000001,20.65346],"type":"Point"}
}