{
  "type": "Feature",
  "properties": {
    "iso:country":"IN",
    "ks:ks_name":"Ludhawani",
    "ks:ks_pop":90,
    "ks:ks_type":"HABITATION",
    "name:eng_x_preferred":[
        "Ludhawani"
    ],
    "wof:name":"Ludhawani",
    "wof:placetype":"locality",
    "wof:population":90
},
  "geometry": {"coordinates":[76.633047,26.173542],"type":"Point"}
}