{
  "type": "Feature",
  "properties": {
    "gn:admin1_code":"36.0",
    "gn:admin2_code":"174",
    "gn:asciiname":"Daranagar",
    "gn:country_code":"IN",
    "gn:dem":113,
    "gn:feature_class":"P",
    "gn:feature_code":"PPL",
    "gn:name":"D\u0101r\u0101nagar",
    "gn:population":0,
    "gn:timezone":"Asia/Kolkata",
    "iso:country":"IN",
    "name:ceb_x_preferred":[
        "D\u0101r\u0101nagar"
    ],
    "name:swe_x_preferred":[
        "D\u0101r\u0101nagar"
    ],
    "name:und_x_variant":[
        "D\u0101r\u0101nagar"
    ],
    "wof:name":"Daranagar",
    "wof:placetype":"locality"
},
  "geometry": {"coordinates":[81.34990000000001,25.68139],"type":"Point"}
}