{
  "type": "Feature",
  "properties": {
    "iso:country":"IN",
    "ks:ks_alt_nam":"Gaddayyana doddi",
    "ks:ks_name":"Gaddayyana Doddi",
    "ks:ks_pop":65,
    "ks:ks_type":"HABITATION",
    "name:eng_x_preferred":[
        "Gaddayyana Doddi"
    ],
    "wof:name":"Gaddayyana Doddi",
    "wof:placetype":"locality",
    "wof:population":65
},
  "geometry": {"coordinates":[76.729676,16.342343],"type":"Point"}
}