{
  "type": "Feature",
  "properties": {
    "iso:country":"IN",
    "ks:ks_name":"Hirenagar",
    "ks:ks_pop":521,
    "ks:ks_type":"VILLAGE",
    "name:eng_x_preferred":[
        "Hirenagar"
    ],
    "wof:name":"Hirenagar",
    "wof:placetype":"locality",
    "wof:population":521
},
  "geometry": {"coordinates":[74.60419,20.320283],"type":"Point"}
}