{
  "type": "Feature",
  "properties": {
    "gn:admin1_code":"36.0",
    "gn:admin2_code":"182.0",
    "gn:asciiname":"Kaili",
    "gn:country_code":"IN",
    "gn:dem":113,
    "gn:feature_class":"P",
    "gn:feature_code":"PPL",
    "gn:name":"Kaili",
    "gn:population":0,
    "gn:timezone":"Asia/Kolkata",
    "iso:country":"IN",
    "name:ceb_x_preferred":[
        "Kaili"
    ],
    "name:deu_x_preferred":[
        "Kaili"
    ],
    "name:ind_x_preferred":[
        "Kaili"
    ],
    "wof:name":"Kaili",
    "wof:placetype":"locality"
},
  "geometry": {"coordinates":[82.27354,27.49104],"type":"Point"}
}