{
  "type": "Feature",
  "properties": {
    "iso:country":"IN",
    "ks:ks_alt_nam":"Timm\u0101puram",
    "ks:ks_name":"Timmapuram",
    "ks:ks_type":"VILLAGE",
    "name:eng_x_preferred":[
        "Timmapuram"
    ],
    "name:eng_x_variant":[
        "Timm\u0101puram"
    ],
    "wof:name":"Timmapuram",
    "wof:placetype":"locality"
},
  "geometry": {"coordinates":[81.050011,18.451452],"type":"Point"}
}