{
  "type": "Feature",
  "properties": {
    "gn:admin1_code":"34.0",
    "gn:admin2_code":"217.0",
    "gn:asciiname":"Barwa Khurd",
    "gn:country_code":"IN",
    "gn:dem":77,
    "gn:feature_class":"P",
    "gn:feature_code":"PPL",
    "gn:name":"Barwa Khurd",
    "gn:population":0,
    "gn:timezone":"Asia/Kolkata",
    "iso:country":"IN",
    "ks:ks_name":"Barwa Khurd",
    "ks:ks_type":"VILLAGE",
    "name:eng_x_preferred":[
        "Barwa Khurd"
    ],
    "wof:name":"Barwa Khurd",
    "wof:placetype":"locality"
},
  "geometry": {"coordinates":[84.30708799999999,26.61469],"type":"Point"}
}