{
  "type": "Feature",
  "properties": {
    "iso:country":"IN",
    "ks:ks_name":"Kelamut Kabbinale",
    "ks:ks_pop":123,
    "ks:ks_type":"HABITATION",
    "name:eng_x_preferred":[
        "Kelamut Kabbinale"
    ],
    "wof:name":"Kelamut Kabbinale",
    "wof:placetype":"locality",
    "wof:population":123
},
  "geometry": {"coordinates":[75.046468,13.409608],"type":"Point"}
}