{
  "type": "Feature",
  "properties": {
    "gn:admin1_code":"34.0",
    "gn:admin2_code":"239.0",
    "gn:asciiname":"Shahbazpur",
    "gn:country_code":"IN",
    "gn:dem":70,
    "gn:feature_class":"P",
    "gn:feature_code":"PPL",
    "gn:name":"Sh\u0101hb\u0101zpur",
    "gn:population":0,
    "gn:timezone":"Asia/Kolkata",
    "iso:country":"IN",
    "wof:name":"Shahbazpur",
    "wof:placetype":"locality"
},
  "geometry": {"coordinates":[85.13186,25.19894],"type":"Point"}
}