{
  "type": "Feature",
  "properties": {
    "iso:country":"IN",
    "ks:ks_name":"Noolpuzha",
    "ks:ks_pop":1821,
    "ks:ks_type":"VILLAGE",
    "name:eng_x_preferred":[
        "Noolpuzha"
    ],
    "wof:name":"Noolpuzha",
    "wof:placetype":"locality",
    "wof:population":1821
},
  "geometry": {"coordinates":[76.344604,11.603227],"type":"Point"}
}