{
  "type": "Feature",
  "properties": {
    "iso:country":"IN",
    "ks:ks_name":"Mangaldaipara",
    "ks:ks_pop":69,
    "ks:ks_type":"VILLAGE",
    "ks:ks_uagg_main":0,
    "name:eng_x_preferred":[
        "Mangaldaipara"
    ],
    "wof:name":"Mangaldaipara",
    "wof:placetype":"neighbourhood",
    "wof:population":69
},
  "geometry": {"coordinates":[94.36313699999999,27.465214],"type":"Point"}
}