{
  "type": "Feature",
  "properties": {
    "iso:country":"IN",
    "ks:ks_name":"Arazi Saikuli",
    "ks:ks_pop":123,
    "ks:ks_type":"VILLAGE",
    "ks:ks_uagg_main":0,
    "name:eng_x_preferred":[
        "Arazi Saikuli"
    ],
    "wof:name":"Arazi Saikuli",
    "wof:placetype":"neighbourhood",
    "wof:population":123
},
  "geometry": {"coordinates":[88.26279100000001,24.170567],"type":"Point"}
}