{
  "type": "Feature",
  "properties": {
    "gn:admin1_code":"19.0",
    "gn:admin2_code":"577.0",
    "gn:asciiname":"Chikkahalli",
    "gn:country_code":"IN",
    "gn:dem":737,
    "gn:feature_class":"P",
    "gn:feature_code":"PPL",
    "gn:name":"Chikkahalli",
    "gn:population":0,
    "gn:timezone":"Asia/Kolkata",
    "iso:country":"IN",
    "wof:name":"Chikkahalli",
    "wof:placetype":"locality"
},
  "geometry": {"coordinates":[76.72955999999998,12.28177],"type":"Point"}
}