{
  "type": "Feature",
  "properties": {
    "iso:country":"IN",
    "ks:ks_name":"Amgadhera",
    "ks:ks_pop":92,
    "ks:ks_type":"HABITATION",
    "name:eng_x_preferred":[
        "Amgadhera"
    ],
    "wof:name":"Amgadhera",
    "wof:placetype":"locality",
    "wof:population":92
},
  "geometry": {"coordinates":[79.168987,29.677967],"type":"Point"}
}