{
  "type": "Feature",
  "properties": {
    "iso:country":"IN",
    "ks:ks_name":"Thogaranahally",
    "ks:ks_pop":540,
    "ks:ks_type":"HABITATION",
    "name:eng_x_preferred":[
        "Thogaranahally"
    ],
    "wof:name":"Thogaranahally",
    "wof:placetype":"locality",
    "wof:population":540
},
  "geometry": {"coordinates":[75.968654,12.97761],"type":"Point"}
}