{
  "type": "Feature",
  "properties": {
    "iso:country":"IN",
    "ks:ks_name":"Rakasirai",
    "ks:ks_pop":90,
    "ks:ks_type":"HABITATION",
    "name:eng_x_preferred":[
        "Rakasirai"
    ],
    "wof:name":"Rakasirai",
    "wof:placetype":"locality",
    "wof:population":90
},
  "geometry": {"coordinates":[82.471977,18.320804],"type":"Point"}
}