{
  "type": "Feature",
  "properties": {
    "gn:admin1_code":"35.0",
    "gn:admin2_code":"457.0",
    "gn:asciiname":"Chilora",
    "gn:country_code":"IN",
    "gn:dem":327,
    "gn:feature_class":"P",
    "gn:feature_code":"PPL",
    "gn:name":"Chilora",
    "gn:population":0,
    "gn:timezone":"Asia/Kolkata",
    "iso:country":"IN",
    "ks:ks_name":"Chillora",
    "ks:ks_pop":456,
    "ks:ks_type":"HABITATION",
    "name:eng_x_preferred":[
        "Chillora"
    ],
    "name:eng_x_variant":[
        "Chilora"
    ],
    "wof:name":"Chillora",
    "wof:placetype":"locality",
    "wof:population":456
},
  "geometry": {"coordinates":[80.597059,21.557387],"type":"Point"}
}