{
  "type": "Feature",
  "properties": {
    "gn:admin1_code":"16.0",
    "gn:admin2_code":"520.0",
    "gn:asciiname":"Nigdi",
    "gn:country_code":"IN",
    "gn:dem":18,
    "gn:feature_class":"P",
    "gn:feature_code":"PPL",
    "gn:name":"Nigdi",
    "gn:population":0,
    "gn:timezone":"Asia/Kolkata",
    "iso:country":"IN",
    "wof:name":"Nigdi",
    "wof:placetype":"locality"
},
  "geometry": {"coordinates":[73.11645,18.48555],"type":"Point"}
}