{
  "type": "Feature",
  "properties": {
    "gn:admin1_code":"16.0",
    "gn:admin2_code":"520.0",
    "gn:asciiname":"Nigdi",
    "gn:country_code":"IN",
    "gn:dem":18,
    "gn:feature_class":"P",
    "gn:feature_code":"PPL",
    "gn:name":"Nigdi",
    "gn:population":0,
    "gn:timezone":"Asia/Kolkata",
    "iso:country":"IN",
    "name:ara_x_preferred":[
        "\u0646\u064a\u063a\u062f\u064a"
    ],
    "name:ben_bn_x_preferred":[
        "\u09a8\u09bf\u0997\u09dc\u09bf"
    ],
    "name:ben_in_x_preferred":[
        "\u09a8\u09bf\u0997\u09dc\u09bf"
    ],
    "name:guj_x_preferred":[
        "\u0aa8\u0abf\u0a97\u0acd\u0aa1\u0ac0"
    ],
    "name:hin_x_preferred":[
        "\u0928\u093f\u0917\u0921\u0940"
    ],
    "name:kan_x_preferred":[
        "\u0ca8\u0cbf\u0c97\u0ca1\u0cbf"
    ],
    "name:mal_x_preferred":[
        "\u0d28\u0d3f\u0d17\u0d4d\u0d21\u0d3f"
    ],
    "name:mar_x_preferred":[
        "\u0928\u093f\u0917\u0921\u0940"
    ],
    "name:pan_x_preferred":[
        "\u0a28\u0a3f\u0a17\u0a5c\u0a40"
    ],
    "name:tam_x_preferred":[
        "\u0ba8\u0bbf\u0b95\u0bcd\u0b9f\u0bbf"
    ],
    "name:tel_x_preferred":[
        "\u0c28\u0c3f\u0c17\u0c4d\u0c21\u0c3f"
    ],
    "name:urd_x_preferred":[
        "\u0646\u06af\u0688\u06cc"
    ],
    "wof:name":"Nigdi",
    "wof:placetype":"locality"
},
  "geometry": {"coordinates":[73.11645,18.48555],"type":"Point"}
}