{
  "type": "Feature",
  "properties": {
    "gn:admin1_code":"36",
    "gn:admin2_code":"176.0",
    "gn:asciiname":"Nawa Purwa Balha",
    "gn:country_code":"IN",
    "gn:dem":115,
    "gn:feature_class":"P",
    "gn:feature_code":"PPL",
    "gn:name":"Nawa Purwa Balha",
    "gn:population":0,
    "gn:timezone":"Asia/Kolkata",
    "iso:country":"IN",
    "wof:name":"Nawa Purwa Balha",
    "wof:placetype":"neighbourhood"
},
  "geometry": {"coordinates":[81.52979999999999,26.82285],"type":"Point"}
}