{
  "type": "Feature",
  "properties": {
    "gn:admin1_code":"25.0",
    "gn:admin2_code":"609.0",
    "gn:asciiname":"Chellappanpalaiyampudur",
    "gn:country_code":"IN",
    "gn:dem":152,
    "gn:feature_class":"P",
    "gn:feature_code":"PPL",
    "gn:name":"Chellappanp\u0101laiyampud\u016br",
    "gn:population":0,
    "gn:timezone":"Asia/Kolkata",
    "iso:country":"IN",
    "wof:name":"Chellappanpalaiyampudur",
    "wof:placetype":"locality"
},
  "geometry": {"coordinates":[77.96488000000002,11.13095],"type":"Point"}
}