{
  "type": "Feature",
  "properties": {
    "gn:admin1_code":"35.0",
    "gn:admin2_code":"457",
    "gn:asciiname":"Bhimlat",
    "gn:country_code":"IN",
    "gn:dem":571,
    "gn:feature_class":"P",
    "gn:feature_code":"PPL",
    "gn:name":"Bh\u012bml\u0101t",
    "gn:population":0,
    "gn:timezone":"Asia/Kolkata",
    "iso:country":"IN",
    "name:und_x_variant":[
        "Bhimlath",
        "Bh\u012bml\u0101t"
    ],
    "wof:name":"Bhimlat",
    "wof:placetype":"locality"
},
  "geometry": {"coordinates":[80.70316,22.12705],"type":"Point"}
}