{
  "type": "Feature",
  "properties": {
    "gn:admin1_code":"35.0",
    "gn:admin2_code":"457",
    "gn:asciiname":"Bhimlat",
    "gn:country_code":"IN",
    "gn:dem":571,
    "gn:feature_class":"P",
    "gn:feature_code":"PPL",
    "gn:name":"Bh\u012bml\u0101t",
    "gn:population":0,
    "gn:timezone":"Asia/Kolkata",
    "iso:country":"IN",
    "ks:ks_alt_nam":"Bh\u012bml\u0101t",
    "ks:ks_name":"Bhimlat",
    "ks:ks_pop":759,
    "ks:ks_type":"VILLAGE",
    "name:eng_x_preferred":[
        "Bhimlat"
    ],
    "name:eng_x_variant":[
        "Bh\u012bml\u0101t"
    ],
    "name:und_x_variant":[
        "Bhimlath",
        "Bh\u012bml\u0101t"
    ],
    "wof:name":"Bhimlat",
    "wof:placetype":"locality",
    "wof:population":759
},
  "geometry": {"coordinates":[80.702094,22.127299],"type":"Point"}
}