{
  "type": "Feature",
  "properties": {
    "iso:country":"IN",
    "ks:ks_name":"Sherbandha",
    "ks:ks_pop":68,
    "ks:ks_type":"HABITATION",
    "name:eng_x_preferred":[
        "Sherbandha"
    ],
    "wof:name":"Sherbandha",
    "wof:placetype":"locality",
    "wof:population":68
},
  "geometry": {"coordinates":[83.06886,19.832496],"type":"Point"}
}