{
  "type": "Feature",
  "properties": {
    "iso:country":"IN",
    "qs:name":"Gole Dak Khana",
    "qs:name_adm0":"India",
    "qs:name_adm1":"Delhi",
    "qs:photos":273,
    "qs:photos_1k":55,
    "qs:photos_9k":1,
    "qs:photos_9r":4,
    "qs:photos_all":273,
    "qs:photos_sr":5,
    "qs:placetype":"Suburb",
    "qs:pop_sr":"0",
    "wof:name":"Gole Dak Khana",
    "wof:placetype":"neighbourhood"
},
  "geometry": {"coordinates":[77.20892600000001,28.626308],"type":"Point"}
}