{
  "type": "Feature",
  "properties": {
    "gn:admin1_code":"16",
    "gn:admin2_code":"503.0",
    "gn:asciiname":"Wadner",
    "gn:country_code":"IN",
    "gn:dem":333,
    "gn:feature_class":"P",
    "gn:feature_code":"PPL",
    "gn:name":"Wadner",
    "gn:population":0,
    "gn:timezone":"Asia/Kolkata",
    "iso:country":"IN",
    "wof:name":"Wadner",
    "wof:placetype":"neighbourhood"
},
  "geometry": {"coordinates":[77.40178,21.13854],"type":"Point"}
}