{
  "type": "Feature",
  "properties": {
    "iso:country":"IN",
    "ks:ks_name":"Bulakipur",
    "ks:ks_pop":0,
    "ks:ks_type":"VILLAGE",
    "name:eng_x_preferred":[
        "Bulakipur"
    ],
    "wof:name":"Bulakipur",
    "wof:placetype":"locality",
    "wof:population":0
},
  "geometry": {"coordinates":[77.939531,29.709106],"type":"Point"}
}