{
  "type": "Feature",
  "properties": {
    "iso:country":"IN",
    "ks:ks_name":"18 MD-B",
    "ks:ks_pop":45,
    "ks:ks_type":"VILLAGE",
    "name:eng_x_preferred":[
        "18 MD-B"
    ],
    "wof:name":"18 MD-B",
    "wof:placetype":"locality",
    "wof:population":45
},
  "geometry": {"coordinates":[73.02517899999999,29.05411],"type":"Point"}
}