{
  "type": "Feature",
  "properties": {
    "iso:country":"IN",
    "ks:ks_name":"Byasati",
    "ks:ks_pop":325,
    "ks:ks_type":"VILLAGE",
    "ks:ks_uagg_main":0,
    "name:eng_x_preferred":[
        "Byasati"
    ],
    "wof:name":"Byasati",
    "wof:placetype":"neighbourhood",
    "wof:population":325
},
  "geometry": {"coordinates":[88.82852,22.989173],"type":"Point"}
}