{
  "type": "Feature",
  "properties": {
    "iso:country":"IN",
    "ks:ks_name":"Sidilukoppa",
    "ks:ks_pop":14,
    "ks:ks_type":"HABITATION",
    "name:eng_x_preferred":[
        "Sidilukoppa"
    ],
    "wof:name":"Sidilukoppa",
    "wof:placetype":"locality",
    "wof:population":14
},
  "geometry": {"coordinates":[75.413319,13.403551],"type":"Point"}
}