{
  "type": "Feature",
  "properties": {
    "iso:country":"IN",
    "ks:ks_name":"Bhadrimau",
    "ks:ks_pop":631,
    "ks:ks_type":"HABITATION",
    "name:eng_x_preferred":[
        "Bhadrimau"
    ],
    "wof:name":"Bhadrimau",
    "wof:placetype":"locality",
    "wof:population":631
},
  "geometry": {"coordinates":[81.95536300000001,18.81564],"type":"Point"}
}