{
  "type": "Feature",
  "properties": {
    "iso:country":"IN",
    "ks:ks_name":"Brahmandihi",
    "ks:ks_pop":639,
    "ks:ks_type":"VILLAGE",
    "name:eng_x_preferred":[
        "Brahmandihi"
    ],
    "wof:name":"Brahmandihi",
    "wof:placetype":"locality",
    "wof:population":639
},
  "geometry": {"coordinates":[87.56660100000001,23.760772],"type":"Point"}
}