{
  "type": "Feature",
  "properties": {
    "gn:country":"IN",
    "gn:fcode":"PPL",
    "gn:pop":14249,
    "iso:country":"IN",
    "name:ceb_x_preferred":[
        "Kankip\u0101du"
    ],
    "name:eng_x_preferred":[
        "Kankipadu"
    ],
    "name:hin_x_preferred":[
        "\u0915\u093e\u0901\u0915\u0940\u092a\u093e\u0921\u0941"
    ],
    "name:new_x_preferred":[
        "\u0915\u0902\u0915\u093f\u092a\u093e\u0921\u0941 \u092e\u0923\u094d\u0921\u0932"
    ],
    "name:nld_x_preferred":[
        "Kankipadu"
    ],
    "name:swe_x_preferred":[
        "Kankip\u0101du"
    ],
    "name:tel_x_preferred":[
        "\u0c15\u0c02\u0c15\u0c3f\u0c2a\u0c3e\u0c21\u0c41"
    ],
    "name:unk_x_variant":[
        "Kankipad"
    ],
    "name:urd_x_preferred":[
        "\u06a9\u0646\u06a9\u06cc \u067e\u0627\u0688\u0648"
    ],
    "name:vie_x_preferred":[
        "Kankipadu"
    ],
    "qs:name":"Kankipadu",
    "qs:name_adm0":"India",
    "qs:name_adm1":"Andhra Pradesh",
    "qs:photos_9r":0,
    "qs:photos_sr":0,
    "qs:placetype":"Town",
    "qs:pop_sr":"6",
    "wd:wordcount":166,
    "wof:name":"Kankipadu",
    "wof:placetype":"locality",
    "wof:population":14249
},
  "geometry": {"coordinates":[80.78333000000001,16.45],"type":"Point"}
}