{
  "type": "Feature",
  "properties": {
    "iso:country":"IN",
    "ks:ks_name":"Tola Domadih",
    "ks:ks_pop":97,
    "ks:ks_type":"VILLAGE",
    "name:eng_x_preferred":[
        "Tola Domadih"
    ],
    "wof:name":"Tola Domadih",
    "wof:placetype":"locality",
    "wof:population":97
},
  "geometry": {"coordinates":[86.892096,24.652503],"type":"Point"}
}