{
  "type": "Feature",
  "properties": {
    "iso:country":"IN",
    "ks:ks_name":"Damaguda",
    "ks:ks_pop":150,
    "ks:ks_type":"HABITATION",
    "name:eng_x_preferred":[
        "Damaguda"
    ],
    "wof:name":"Damaguda",
    "wof:placetype":"locality",
    "wof:population":150
},
  "geometry": {"coordinates":[81.978444,18.346969],"type":"Point"}
}