{
  "type": "Feature",
  "properties": {
    "gn:admin1_code":"11.0",
    "gn:admin2_code":"24.0",
    "gn:asciiname":"Bankaroli",
    "gn:country_code":"IN",
    "gn:dem":534,
    "gn:feature_class":"P",
    "gn:feature_code":"PPL",
    "gn:name":"Bankaroli",
    "gn:population":0,
    "gn:timezone":"Asia/Kolkata",
    "iso:country":"IN",
    "wof:name":"Bankaroli",
    "wof:placetype":"locality"
},
  "geometry": {"coordinates":[75.91355,32.1373],"type":"Point"}
}