{
  "type": "Feature",
  "properties": {
    "iso:country":"IN",
    "ks:ks_name":"Manchannahalli",
    "ks:ks_type":"VILLAGE",
    "name:eng_x_preferred":[
        "Manchannahalli"
    ],
    "wof:name":"Manchannahalli",
    "wof:placetype":"locality"
},
  "geometry": {"coordinates":[76.056961,12.838592],"type":"Point"}
}