{
  "type": "Feature",
  "properties": {
    "gn:admin1_code":"34.0",
    "gn:admin2_code":"229.0",
    "gn:asciiname":"Sahra",
    "gn:country_code":"IN",
    "gn:dem":46,
    "gn:feature_class":"P",
    "gn:feature_code":"PPL",
    "gn:name":"Sahra",
    "gn:population":0,
    "gn:timezone":"Asia/Kolkata",
    "iso:country":"IN",
    "name:ara_x_preferred":[
        "\u0635\u062d\u0631\u0627\u0621"
    ],
    "name:fin_x_preferred":[
        "Sahra"
    ],
    "name:ita_x_preferred":[
        "Sahra"
    ],
    "name:pol_x_preferred":[
        "Sahra"
    ],
    "name:por_x_preferred":[
        "Sahra"
    ],
    "wof:name":"Sahra",
    "wof:placetype":"locality"
},
  "geometry": {"coordinates":[85.89614,25.23068],"type":"Point"}
}