{
  "type": "Feature",
  "properties": {
    "gn:admin1_code":"11.0",
    "gn:admin2_code":"33.0",
    "gn:asciiname":"Jur",
    "gn:country_code":"IN",
    "gn:dem":1317,
    "gn:feature_class":"P",
    "gn:feature_code":"PPL",
    "gn:name":"J\u016br",
    "gn:population":0,
    "gn:timezone":"Asia/Kolkata",
    "iso:country":"IN",
    "name:ceb_x_preferred":[
        "Jur"
    ],
    "name:ces_x_preferred":[
        "Jur"
    ],
    "name:deu_x_preferred":[
        "Jur"
    ],
    "name:slk_x_preferred":[
        "Jur"
    ],
    "name:swe_x_preferred":[
        "Jur"
    ],
    "wof:name":"Jur",
    "wof:placetype":"locality"
},
  "geometry": {"coordinates":[77.37489000000002,31.29467],"type":"Point"}
}