{
  "type": "Feature",
  "properties": {
    "gn:admin1_code":"19.0",
    "gn:admin2_code":"582.0",
    "gn:asciiname":"Bandahalli",
    "gn:country_code":"IN",
    "gn:dem":800,
    "gn:feature_class":"P",
    "gn:feature_code":"PPL",
    "gn:name":"Bandahalli",
    "gn:population":0,
    "gn:timezone":"Asia/Kolkata",
    "iso:country":"IN",
    "name:vie_x_preferred":[
        "Bandahalli"
    ],
    "wof:name":"Bandahalli",
    "wof:placetype":"neighbourhood"
},
  "geometry": {"coordinates":[78.06914,13.50296],"type":"Point"}
}