{
  "type": "Feature",
  "properties": {
    "iso:country":"IN",
    "ks:ks_name":"Mahuliyar",
    "ks:ks_pop":65,
    "ks:ks_type":"HABITATION",
    "name:eng_x_preferred":[
        "Mahuliyar"
    ],
    "wof:name":"Mahuliyar",
    "wof:placetype":"locality",
    "wof:population":65
},
  "geometry": {"coordinates":[81.832583,26.108425],"type":"Point"}
}