{
  "type": "Feature",
  "properties": {
    "gn:admin1_code":"35.0",
    "gn:admin2_code":"428",
    "gn:asciiname":"Batiagarh",
    "gn:country_code":"IN",
    "gn:dem":362,
    "gn:feature_class":"P",
    "gn:feature_code":"PPL",
    "gn:name":"Bati\u0101garh",
    "gn:population":0,
    "gn:timezone":"Asia/Kolkata",
    "iso:country":"IN",
    "wof:name":"Batiagarh",
    "wof:placetype":"locality"
},
  "geometry": {"coordinates":[79.34896999999999,24.11337],"type":"Point"}
}