{
  "type": "Feature",
  "properties": {
    "iso:country":"IN",
    "ks:ks_name":"Kalsar",
    "ks:ks_pop":2026,
    "ks:ks_type":"VILLAGE",
    "name:eng_x_preferred":[
        "Kalsar"
    ],
    "wof:name":"Kalsar",
    "wof:placetype":"locality",
    "wof:population":2026
},
  "geometry": {"coordinates":[72.89067900000001,20.471096],"type":"Point"}
}