{
  "type": "Feature",
  "properties": {
    "iso:country":"IN",
    "ks:ks_alt_nam":"PIPARDOLIA",
    "ks:ks_name":"Pipardolia",
    "ks:ks_pop":377,
    "ks:ks_type":"HABITATION",
    "name:eng_x_preferred":[
        "Pipardolia"
    ],
    "wof:name":"Pipardolia",
    "wof:placetype":"locality",
    "wof:population":377
},
  "geometry": {"coordinates":[83.700602,24.13616],"type":"Point"}
}