{
  "type": "Feature",
  "properties": {
    "iso:country":"IN",
    "ks:ks_name":"7 JRK",
    "ks:ks_pop":140,
    "ks:ks_type":"VILLAGE",
    "name:eng_x_preferred":[
        "7 JRK"
    ],
    "wof:name":"7 JRK",
    "wof:placetype":"locality",
    "wof:population":140
},
  "geometry": {"coordinates":[74.216269,29.625322],"type":"Point"}
}