{
  "type": "Feature",
  "properties": {
    "iso:country":"IN",
    "ks:ks_name":"Sidaguda",
    "ks:ks_pop":198,
    "ks:ks_type":"VILLAGE",
    "name:eng_x_preferred":[
        "Sidaguda"
    ],
    "wof:name":"Sidaguda",
    "wof:placetype":"locality",
    "wof:population":198
},
  "geometry": {"coordinates":[83.821952,19.386772],"type":"Point"}
}