{
  "type": "Feature",
  "properties": {
    "gn:admin1_code":"35",
    "gn:admin2_code":"428.0",
    "gn:asciiname":"Sarsaila",
    "gn:country_code":"IN",
    "gn:dem":379,
    "gn:feature_class":"P",
    "gn:feature_code":"PPL",
    "gn:name":"Sarsaila",
    "gn:population":0,
    "gn:timezone":"Asia/Kolkata",
    "iso:country":"IN",
    "wof:name":"Sarsaila",
    "wof:placetype":"locality"
},
  "geometry": {"coordinates":[79.27611,23.39109],"type":"Point"}
}