{
  "type": "Feature",
  "properties": {
    "iso:country":"IN",
    "ks:ks_alt_nam":"HARIJAN TOLA-2",
    "ks:ks_name":"Harijan Tola-2",
    "ks:ks_pop":328,
    "ks:ks_type":"HABITATION",
    "ks:ks_uagg_main":0,
    "name:eng_x_preferred":[
        "Harijan Tola-2"
    ],
    "wof:name":"Harijan Tola-2",
    "wof:placetype":"neighbourhood",
    "wof:population":328
},
  "geometry": {"coordinates":[86.645785,26.330711],"type":"Point"}
}