{
  "type": "Feature",
  "properties": {
    "iso:country":"IN",
    "ks:ks_name":"Kurkuchya",
    "ks:ks_pop":0,
    "ks:ks_type":"VILLAGE",
    "name:eng_x_preferred":[
        "Kurkuchya"
    ],
    "wof:name":"Kurkuchya",
    "wof:placetype":"locality",
    "wof:population":0
},
  "geometry": {"coordinates":[87.409476,22.033283],"type":"Point"}
}