{
  "type": "Feature",
  "properties": {
    "gn:admin1_code":"11.0",
    "gn:admin2_code":"33.0",
    "gn:asciiname":"Kori",
    "gn:country_code":"IN",
    "gn:dem":1972,
    "gn:feature_class":"P",
    "gn:feature_code":"PPL",
    "gn:name":"Kori",
    "gn:population":0,
    "gn:timezone":"Asia/Kolkata",
    "iso:country":"IN",
    "name:bel_x_preferred":[
        "\u041a\u043e\u0440\u044b"
    ],
    "name:ben_x_preferred":[
        "\u0995\u09a1\u09bc\u09bf"
    ],
    "name:ceb_x_preferred":[
        "Kori"
    ],
    "name:deu_x_preferred":[
        "Kori"
    ],
    "name:ind_x_preferred":[
        "Kori"
    ],
    "name:lav_x_preferred":[
        "Kori"
    ],
    "name:swe_x_preferred":[
        "Kori"
    ],
    "name:ukr_x_preferred":[
        "\u041a\u043e\u0440\u0456"
    ],
    "wof:name":"Kori",
    "wof:placetype":"locality"
},
  "geometry": {"coordinates":[77.58584,31.11718],"type":"Point"}
}