{
  "type": "Feature",
  "properties": {
    "gn:admin1_code":"23.0",
    "gn:admin2_code":"43.0",
    "gn:asciiname":"Rukna Mungla",
    "gn:country_code":"IN",
    "gn:dem":196,
    "gn:feature_class":"P",
    "gn:feature_code":"PPL",
    "gn:name":"Rukna Mungla",
    "gn:population":0,
    "gn:timezone":"Asia/Kolkata",
    "iso:country":"IN",
    "ks:ks_name":"Rukna Mungla",
    "ks:ks_pop":766,
    "ks:ks_type":"VILLAGE",
    "name:eng_x_preferred":[
        "Rukna Mungla"
    ],
    "wof:name":"Rukna Mungla",
    "wof:placetype":"locality",
    "wof:population":766
},
  "geometry": {"coordinates":[74.636689,30.899024],"type":"Point"}
}