{
  "type": "Feature",
  "properties": {
    "gn:admin1_code":"24.0",
    "gn:admin2_code":"110.0",
    "gn:asciiname":"Shrikrishnapura",
    "gn:country_code":"IN",
    "gn:dem":310,
    "gn:feature_class":"P",
    "gn:feature_code":"PPL",
    "gn:name":"Shr\u012bkrishnapura",
    "gn:population":0,
    "gn:timezone":"Asia/Kolkata",
    "iso:country":"IN",
    "ks:ks_name":"Shrikishanpura",
    "ks:ks_pop":449,
    "ks:ks_type":"VILLAGE",
    "name:eng_x_preferred":[
        "Shrikishanpura"
    ],
    "name:eng_x_variant":[
        "Shrikrishnapura"
    ],
    "wof:name":"Shrikishanpura",
    "wof:placetype":"locality",
    "wof:population":449
},
  "geometry": {"coordinates":[76.127275,26.663272],"type":"Point"}
}