{
  "type": "Feature",
  "properties": {
    "gn:admin1_code":"36.0",
    "gn:admin2_code":"155.0",
    "gn:asciiname":"Shiuadi",
    "gn:country_code":"IN",
    "gn:dem":133,
    "gn:feature_class":"P",
    "gn:feature_code":"PPL",
    "gn:name":"Shiu\u0101di",
    "gn:population":0,
    "gn:timezone":"Asia/Kolkata",
    "iso:country":"IN",
    "wof:name":"Shiuadi",
    "wof:placetype":"locality"
},
  "geometry": {"coordinates":[80.75333000000001,27.12757],"type":"Point"}
}