{
  "type": "Feature",
  "properties": {
    "gn:admin1_code":"2.0",
    "gn:admin2_code":"544.0",
    "gn:asciiname":"Sankumedde",
    "gn:country_code":"IN",
    "gn:dem":868,
    "gn:feature_class":"P",
    "gn:feature_code":"PPL",
    "gn:name":"Sankumedde",
    "gn:population":0,
    "gn:timezone":"Asia/Kolkata",
    "iso:country":"IN",
    "wof:name":"Sankumedde",
    "wof:placetype":"locality"
},
  "geometry": {"coordinates":[82.40921999999998,18.05861],"type":"Point"}
}