{
  "type": "Feature",
  "properties": {
    "iso:country":"IN",
    "ks:ks_name":"Dharma Thanda",
    "ks:ks_pop":119,
    "ks:ks_type":"HABITATION",
    "name:eng_x_preferred":[
        "Dharma Thanda"
    ],
    "wof:name":"Dharma Thanda",
    "wof:placetype":"locality",
    "wof:population":119
},
  "geometry": {"coordinates":[78.163003,17.84535],"type":"Point"}
}