{
  "type": "Feature",
  "properties": {
    "iso:country":"IN",
    "ks:ks_alt_nam":"DhuniaGaon Pt I",
    "ks:ks_name":"Dhuniagaon Pt I",
    "ks:ks_pop":489,
    "ks:ks_type":"HABITATION",
    "ks:ks_uagg_main":0,
    "name:eng_x_preferred":[
        "Dhuniagaon Pt I"
    ],
    "wof:name":"Dhuniagaon Pt I",
    "wof:placetype":"neighbourhood",
    "wof:population":489
},
  "geometry": {"coordinates":[94.524276,26.836588],"type":"Point"}
}