{
  "type": "Feature",
  "properties": {
    "gn:admin1_code":"24",
    "gn:admin2_code":"119.0",
    "gn:asciiname":"Lande",
    "gn:country_code":"IN",
    "gn:dem":477,
    "gn:feature_class":"P",
    "gn:feature_code":"PPL",
    "gn:name":"L\u0101nde",
    "gn:population":0,
    "gn:timezone":"Asia/Kolkata",
    "iso:country":"IN",
    "name:bre_x_preferred":[
        "Lande"
    ],
    "name:deu_x_preferred":[
        "Lande"
    ],
    "name:nor_x_preferred":[
        "Lande"
    ],
    "name:rus_x_preferred":[
        "\u041b\u0430\u043d\u0434\u0435"
    ],
    "name:ukr_x_preferred":[
        "\u041b\u0430\u043d\u0434\u0435"
    ],
    "wof:name":"Lande",
    "wof:placetype":"locality"
},
  "geometry": {"coordinates":[74.48568,26.14377],"type":"Point"}
}