{
  "type": "Feature",
  "properties": {
    "gn:admin1_code":"36",
    "gn:admin2_code":"134.0",
    "gn:asciiname":"Maulawala",
    "gn:country_code":"IN",
    "gn:dem":227,
    "gn:feature_class":"P",
    "gn:feature_code":"PPL",
    "gn:name":"Maul\u0101w\u0101la",
    "gn:population":0,
    "gn:timezone":"Asia/Kolkata",
    "iso:country":"IN",
    "name:und_x_variant":[
        "Maul\u0101w\u0101la",
        "Muhammad Tak\u012bpur Gh\u0101si"
    ],
    "wof:name":"Maulawala",
    "wof:placetype":"neighbourhood"
},
  "geometry": {"coordinates":[78.44486000000001,29.16978],"type":"Point"}
}