{
  "type": "Feature",
  "properties": {
    "gn:admin1_code":"11.0",
    "gn:admin2_code":"31.0",
    "gn:asciiname":"Kohari",
    "gn:country_code":"IN",
    "gn:dem":1400,
    "gn:feature_class":"P",
    "gn:feature_code":"PPL",
    "gn:name":"Koh\u0101ri",
    "gn:population":0,
    "gn:timezone":"Asia/Kolkata",
    "iso:country":"IN",
    "wof:name":"Kohari",
    "wof:placetype":"locality"
},
  "geometry": {"coordinates":[77.11568,30.97007],"type":"Point"}
}