{
  "type": "Feature",
  "properties": {
    "iso:country":"IN",
    "ks:ks_alt_nam":"vellamodivilai",
    "ks:ks_name":"Vellamodivilai",
    "ks:ks_pop":205,
    "ks:ks_type":"HABITATION",
    "name:eng_x_preferred":[
        "Vellamodivilai"
    ],
    "wof:name":"Vellamodivilai",
    "wof:placetype":"locality",
    "wof:population":205
},
  "geometry": {"coordinates":[77.39882,8.121906],"type":"Point"}
}