{
  "type": "Feature",
  "properties": {
    "gn:admin1_code":"40.0",
    "gn:admin2_code":"540.0",
    "gn:asciiname":"Darkapeta",
    "gn:country_code":"IN",
    "gn:dem":183,
    "gn:feature_class":"P",
    "gn:feature_code":"PPL",
    "gn:name":"Darkapeta",
    "gn:population":0,
    "gn:timezone":"Asia/Kolkata",
    "iso:country":"IN",
    "wof:name":"Darkapeta",
    "wof:placetype":"locality"
},
  "geometry": {"coordinates":[79.60665999999998,18.42766],"type":"Point"}
}