{
  "type": "Feature",
  "properties": {
    "iso:country":"IN",
    "ks:ks_name":"Madapura",
    "ks:ks_pop":62,
    "ks:ks_type":"HABITATION",
    "name:eng_x_preferred":[
        "Madapura"
    ],
    "wof:name":"Madapura",
    "wof:placetype":"locality",
    "wof:population":62
},
  "geometry": {"coordinates":[75.41943999999999,13.589981],"type":"Point"}
}