{
  "type": "Feature",
  "properties": {
    "iso:country":"IN",
    "ks:ks_name":"Insan Nagar",
    "ks:ks_pop":187,
    "ks:ks_type":"HABITATION",
    "name:eng_x_preferred":[
        "Insan Nagar"
    ],
    "wof:name":"Insan Nagar",
    "wof:placetype":"locality",
    "wof:population":187
},
  "geometry": {"coordinates":[81.579802,27.693528],"type":"Point"}
}