{
  "type": "Feature",
  "properties": {
    "iso:country":"IN",
    "ks:ks_name":"Karmatari",
    "ks:ks_pop":0,
    "ks:ks_type":"VILLAGE",
    "name:eng_x_preferred":[
        "Karmatari"
    ],
    "wof:name":"Karmatari",
    "wof:placetype":"locality",
    "wof:population":0
},
  "geometry": {"coordinates":[85.505529,24.498952],"type":"Point"}
}