{
  "type": "Feature",
  "properties": {
    "gn:admin1_code":"36.0",
    "gn:admin2_code":"143.0",
    "gn:asciiname":"Pachawari",
    "gn:country_code":"IN",
    "gn:dem":193,
    "gn:feature_class":"P",
    "gn:feature_code":"PPL",
    "gn:name":"Pach\u0101wari",
    "gn:population":0,
    "gn:timezone":"Asia/Kolkata",
    "iso:country":"IN",
    "wof:name":"Pachawari",
    "wof:placetype":"locality"
},
  "geometry": {"coordinates":[77.83739,27.80807],"type":"Point"}
}