{
  "type": "Feature",
  "properties": {
    "iso:country":"IN",
    "ks:ks_name":"Sarkar O Dashpara E",
    "ks:ks_pop":786,
    "ks:ks_type":"HABITATION",
    "ks:ks_uagg_main":0,
    "name:eng_x_preferred":[
        "Sarkar O Dashpara E"
    ],
    "wof:name":"Sarkar O Dashpara E",
    "wof:placetype":"locality",
    "wof:population":786
},
  "geometry": {"coordinates":[88.128541,22.598311],"type":"Point"}
}