{
  "type": "Feature",
  "properties": {
    "gn:admin1_code":"19.0",
    "gn:admin2_code":"572",
    "gn:asciiname":"Kormangla 4Th Block",
    "gn:country_code":"IN",
    "gn:dem":887,
    "gn:feature_class":"P",
    "gn:feature_code":"PPL",
    "gn:name":"Kormangla 4Th Block",
    "gn:population":0,
    "gn:timezone":"Asia/Kolkata",
    "iso:country":"IN",
    "wof:name":"Kormangla 4Th Block",
    "wof:placetype":"locality"
},
  "geometry": {"coordinates":[77.62759,12.93288],"type":"Point"}
}