{
  "type": "Feature",
  "properties": {
    "iso:country":"IN",
    "ks:ks_alt_nam":"JHAUWA TOLA",
    "ks:ks_name":"Jhauwa Tola",
    "ks:ks_pop":644,
    "ks:ks_type":"HABITATION",
    "ks:ks_uagg_main":0,
    "name:eng_x_preferred":[
        "Jhauwa Tola"
    ],
    "wof:name":"Jhauwa Tola",
    "wof:placetype":"neighbourhood",
    "wof:population":644
},
  "geometry": {"coordinates":[84.925977,25.756949],"type":"Point"}
}