{
  "type": "Feature",
  "properties": {
    "iso:country":"IN",
    "ks:ks_name":"Karundiya",
    "ks:ks_pop":62,
    "ks:ks_type":"VILLAGE",
    "name:eng_x_preferred":[
        "Karundiya"
    ],
    "wof:name":"Karundiya",
    "wof:placetype":"locality",
    "wof:population":62
},
  "geometry": {"coordinates":[75.066008,24.912219],"type":"Point"}
}