{
  "type": "Feature",
  "properties": {
    "gn:country":"IN",
    "gn:fcode":"PPL",
    "gn:pop":6693,
    "iso:country":"IN",
    "name:ben_x_preferred":[
        "\u0997\u09be\u09b0\u09cd\u09a6\u09bf\u0993\u09af\u09bc\u09be\u09b2\u09be"
    ],
    "name:bpy_x_preferred":[
        "\u0997\u09be\u09b0\u09cd\u09a6\u09bf\u09f1\u09be\u09b2\u09be"
    ],
    "name:ceb_x_preferred":[
        "Garhdiw\u0101la"
    ],
    "name:eng_x_preferred":[
        "Gardhiwala"
    ],
    "name:fra_x_preferred":[
        "Gardhiwala"
    ],
    "name:ita_x_preferred":[
        "Gardhiwala"
    ],
    "name:msa_x_preferred":[
        "Gardhiwala"
    ],
    "name:nan_x_preferred":[
        "Gardhiwala"
    ],
    "name:new_x_preferred":[
        "\u0917\u0930\u094d\u0927\u093f\u0935\u093e\u0932\u093e"
    ],
    "name:nld_x_preferred":[
        "Gardhiwala"
    ],
    "name:por_x_preferred":[
        "Gardhiwala"
    ],
    "name:swe_x_preferred":[
        "Garhdiw\u0101la"
    ],
    "name:unk_x_variant":[
        "Gardh\u012bw\u0101la"
    ],
    "name:vie_x_preferred":[
        "Gardhiwala"
    ],
    "name:zho_x_preferred":[
        "\u52a0\u5c14\u8fea\u74e6\u62c9"
    ],
    "qs:name":"Garhd\u012bw\u0101la",
    "qs:photos_9r":0,
    "qs:photos_sr":0,
    "qs:pop_sr":"5",
    "wof:name":"Garhd\u012bw\u0101la",
    "wof:placetype":"locality",
    "wof:population":6693
},
  "geometry": {"coordinates":[75.75479,31.74069],"type":"Point"}
}