{
  "type": "Feature",
  "properties": {
    "iso:country":"IN",
    "ks:ks_name":"Bhatgawan",
    "ks:ks_pop":181,
    "ks:ks_type":"VILLAGE",
    "name:eng_x_preferred":[
        "Bhatgawan"
    ],
    "wof:name":"Bhatgawan",
    "wof:placetype":"locality",
    "wof:population":181
},
  "geometry": {"coordinates":[81.498199,25.172232],"type":"Point"}
}