{
  "type": "Feature",
  "properties": {
    "gn:admin1_code":"35",
    "gn:admin2_code":"457.0",
    "gn:asciiname":"Chaukhanditola",
    "gn:country_code":"IN",
    "gn:dem":353,
    "gn:feature_class":"P",
    "gn:feature_code":"PPL",
    "gn:name":"Chaukhand\u012btola",
    "gn:population":0,
    "gn:timezone":"Asia/Kolkata",
    "iso:country":"IN",
    "wof:name":"Chaukhanditola",
    "wof:placetype":"locality"
},
  "geometry": {"coordinates":[79.77363000000003,21.72892],"type":"Point"}
}