{
  "type": "Feature",
  "properties": {
    "gn:admin1_code":"37",
    "gn:admin2_code":"408.0",
    "gn:asciiname":"Koliari",
    "gn:country_code":"IN",
    "gn:dem":341,
    "gn:feature_class":"P",
    "gn:feature_code":"PPL",
    "gn:name":"Koli\u0101ri",
    "gn:population":0,
    "gn:timezone":"Asia/Kolkata",
    "iso:country":"IN",
    "wof:name":"Koliari",
    "wof:placetype":"locality"
},
  "geometry": {"coordinates":[80.66259000000002,20.88767],"type":"Point"}
}