{
  "type": "Feature",
  "properties": {
    "gn:admin1_code":"40",
    "gn:admin2_code":"538.0",
    "gn:asciiname":"Parsapur",
    "gn:country_code":"IN",
    "gn:dem":538,
    "gn:feature_class":"P",
    "gn:feature_code":"PPL",
    "gn:name":"Pars\u0101pur",
    "gn:population":0,
    "gn:timezone":"Asia/Kolkata",
    "iso:country":"IN",
    "name:ceb_x_preferred":[
        "Paraspur"
    ],
    "name:mai_x_preferred":[
        "\u092a\u0930\u0938\u094d\u092a\u0941\u0930"
    ],
    "name:msa_x_preferred":[
        "Parsapur"
    ],
    "name:nep_x_preferred":[
        "\u092a\u0930\u0938\u094d\u092a\u0941\u0930"
    ],
    "name:pol_x_preferred":[
        "Paraspur"
    ],
    "wof:name":"Parsapur",
    "wof:placetype":"locality"
},
  "geometry": {"coordinates":[77.6477,17.07289],"type":"Point"}
}