{
  "type": "Feature",
  "properties": {
    "gn:admin1_code":"16",
    "gn:admin2_code":"508.0",
    "gn:asciiname":"Sonpurchak",
    "gn:country_code":"IN",
    "gn:dem":215,
    "gn:feature_class":"P",
    "gn:feature_code":"PPL",
    "gn:name":"Sonpurchak",
    "gn:population":0,
    "gn:timezone":"Asia/Kolkata",
    "iso:country":"IN",
    "ks:ks_name":"Sonpur Chak",
    "ks:ks_pop":113,
    "ks:ks_type":"VILLAGE",
    "ks:ks_uagg_main":0,
    "name:eng_x_preferred":[
        "Sonpur Chak"
    ],
    "wof:name":"Sonpur Chak",
    "wof:placetype":"neighbourhood",
    "wof:population":113
},
  "geometry": {"coordinates":[80.080682,20.408682],"type":"Point"}
}