{
  "type": "Feature",
  "properties": {
    "gn:admin1_code":"36.0",
    "gn:admin2_code":"162.0",
    "gn:asciiname":"Purwa Rawat",
    "gn:country_code":"IN",
    "gn:dem":144,
    "gn:feature_class":"P",
    "gn:feature_code":"PPL",
    "gn:name":"Purwa R\u0101wat",
    "gn:population":0,
    "gn:timezone":"Asia/Kolkata",
    "iso:country":"IN",
    "ks:ks_alt_nam":"Purwa R\u0101wat",
    "ks:ks_name":"Purwa Rawat",
    "ks:ks_type":"VILLAGE",
    "ks:ks_uagg_main":0,
    "name:eng_x_preferred":[
        "Purwa Rawat"
    ],
    "name:eng_x_variant":[
        "Purwa R\u0101wat"
    ],
    "wof:name":"Purwa Rawat",
    "wof:placetype":"neighbourhood"
},
  "geometry": {"coordinates":[79.60086099999999,26.762917],"type":"Point"}
}