{
  "type": "Feature",
  "properties": {
    "iso:country":"IN",
    "ks:ks_alt_nam":"BAGICHAPARA",
    "ks:ks_name":"Bagichapara",
    "ks:ks_pop":213,
    "ks:ks_type":"HABITATION",
    "name:eng_x_preferred":[
        "Bagichapara"
    ],
    "wof:name":"Bagichapara",
    "wof:placetype":"locality",
    "wof:population":213
},
  "geometry": {"coordinates":[81.892332,22.106017],"type":"Point"}
}