{
  "type": "Feature",
  "properties": {
    "gn:admin1_code":"25.0",
    "gn:admin2_code":"620.0",
    "gn:asciiname":"Pavanachcheri",
    "gn:country_code":"IN",
    "gn:dem":27,
    "gn:feature_class":"P",
    "gn:feature_code":"PPL",
    "gn:name":"P\u0101van\u0101chcheri",
    "gn:population":0,
    "gn:timezone":"Asia/Kolkata",
    "iso:country":"IN",
    "ks:ks_name":"Pavanancheri",
    "ks:ks_pop":341,
    "ks:ks_type":"HABITATION",
    "name:eng_x_preferred":[
        "Pavanancheri"
    ],
    "name:eng_x_variant":[
        "Pavanachcheri"
    ],
    "wof:name":"Pavanancheri",
    "wof:placetype":"locality",
    "wof:population":341
},
  "geometry": {"coordinates":[79.384738,11.02664],"type":"Point"}
}