{
  "type": "Feature",
  "properties": {
    "iso:country":"IN",
    "ks:ks_name":"25 NTR",
    "ks:ks_pop":292,
    "ks:ks_type":"VILLAGE",
    "name:eng_x_preferred":[
        "25 NTR"
    ],
    "wof:name":"25 NTR",
    "wof:placetype":"locality",
    "wof:population":292
},
  "geometry": {"coordinates":[74.84553,29.216957],"type":"Point"}
}