{
  "type": "Feature",
  "properties": {
    "iso:country":"IN",
    "ks:ks_name":"Snehapadi Jn",
    "ks:ks_pop":811,
    "ks:ks_type":"HABITATION",
    "name:eng_x_preferred":[
        "Snehapadi Jn"
    ],
    "wof:name":"Snehapadi Jn",
    "wof:placetype":"locality",
    "wof:population":811
},
  "geometry": {"coordinates":[76.327826,11.217641],"type":"Point"}
}