{
  "type": "Feature",
  "properties": {
    "gn:admin1_code":"37.0",
    "gn:admin2_code":"417.0",
    "gn:asciiname":"Orsanporka",
    "gn:country_code":"IN",
    "gn:dem":302,
    "gn:feature_class":"P",
    "gn:feature_code":"PPL",
    "gn:name":"Orsanporka",
    "gn:population":0,
    "gn:timezone":"Asia/Kolkata",
    "iso:country":"IN",
    "ks:ks_name":"Orsanporka",
    "ks:ks_type":"VILLAGE",
    "name:eng_x_preferred":[
        "Orsanporka"
    ],
    "wof:name":"Orsanporka",
    "wof:placetype":"locality"
},
  "geometry": {"coordinates":[80.675438,19.205103],"type":"Point"}
}