{
  "type": "Feature",
  "properties": {
    "iso:country":"IN",
    "ks:ks_name":"Revatiwadi",
    "ks:ks_pop":218,
    "ks:ks_type":"HABITATION",
    "name:eng_x_preferred":[
        "Revatiwadi"
    ],
    "wof:name":"Revatiwadi",
    "wof:placetype":"locality",
    "wof:population":218
},
  "geometry": {"coordinates":[73.685367,15.86951],"type":"Point"}
}