{
  "type": "Feature",
  "properties": {
    "iso:country":"IN",
    "ks:ks_alt_nam":"Ng. Bhawani XXX",
    "ks:ks_name":"Ng. Bhawani Xxx",
    "ks:ks_pop":559,
    "ks:ks_type":"HABITATION",
    "ks:ks_uagg_main":0,
    "name:eng_x_preferred":[
        "Ng. Bhawani Xxx"
    ],
    "wof:name":"Ng. Bhawani Xxx",
    "wof:placetype":"neighbourhood",
    "wof:population":559
},
  "geometry": {"coordinates":[78.80036,27.883873],"type":"Point"}
}