{
  "type": "Feature",
  "properties": {
    "iso:country":"IN",
    "ks:ks_name":"Keamati",
    "ks:ks_pop":13,
    "ks:ks_type":"HABITATION",
    "name:eng_x_preferred":[
        "Keamati"
    ],
    "wof:name":"Keamati",
    "wof:placetype":"locality",
    "wof:population":13
},
  "geometry": {"coordinates":[75.623823,12.550715],"type":"Point"}
}