{
  "type": "Feature",
  "properties": {
    "iso:country":"IN",
    "ks:ks_name":"Atrauliya",
    "ks:ks_pop":0,
    "ks:ks_type":"VILLAGE",
    "name:eng_x_preferred":[
        "Atrauliya"
    ],
    "wof:name":"Atrauliya",
    "wof:placetype":"locality",
    "wof:population":0
},
  "geometry": {"coordinates":[83.514664,25.315977],"type":"Point"}
}