{
  "type": "Feature",
  "properties": {
    "iso:country":"IN",
    "ks:ks_name":"Mahmoodpur",
    "ks:ks_pop":127,
    "ks:ks_type":"HABITATION",
    "name:eng_x_preferred":[
        "Mahmoodpur"
    ],
    "wof:name":"Mahmoodpur",
    "wof:placetype":"locality",
    "wof:population":127
},
  "geometry": {"coordinates":[82.94090799999999,26.218062],"type":"Point"}
}