{
  "type": "Feature",
  "properties": {
    "iso:country":"IN",
    "ks:ks_name":"Gohiradadar",
    "ks:ks_pop":217,
    "ks:ks_type":"VILLAGE",
    "name:eng_x_preferred":[
        "Gohiradadar"
    ],
    "wof:name":"Gohiradadar",
    "wof:placetype":"locality",
    "wof:population":217
},
  "geometry": {"coordinates":[84.116029,21.079617],"type":"Point"}
}