{
  "type": "Feature",
  "properties": {
    "gn:admin1_code":"19.0",
    "gn:admin2_code":"573.0",
    "gn:asciiname":"Kallukamari",
    "gn:country_code":"IN",
    "gn:dem":814,
    "gn:feature_class":"P",
    "gn:feature_code":"PPL",
    "gn:name":"Kallukamari",
    "gn:population":0,
    "gn:timezone":"Asia/Kolkata",
    "iso:country":"IN",
    "ks:ks_name":"Kallukomari",
    "ks:ks_pop":299,
    "ks:ks_type":"VILLAGE",
    "name:eng_x_preferred":[
        "Kallukomari"
    ],
    "name:eng_x_variant":[
        "Kallukamari"
    ],
    "wof:name":"Kallukomari",
    "wof:placetype":"locality",
    "wof:population":299
},
  "geometry": {"coordinates":[76.720111,12.832643],"type":"Point"}
}