{
  "type": "Feature",
  "properties": {
    "iso:country":"IN",
    "ks:ks_name":"Mendi",
    "ks:ks_pop":315,
    "ks:ks_type":"HABITATION",
    "name:eng_x_preferred":[
        "Mendi"
    ],
    "wof:name":"Mendi",
    "wof:placetype":"locality",
    "wof:population":315
},
  "geometry": {"coordinates":[81.460522,16.487348],"type":"Point"}
}