{
  "type": "Feature",
  "properties": {
    "iso:country":"IN",
    "ks:ks_name":"Gurugudem",
    "ks:ks_pop":44,
    "ks:ks_type":"HABITATION",
    "name:eng_x_preferred":[
        "Gurugudem"
    ],
    "wof:name":"Gurugudem",
    "wof:placetype":"locality",
    "wof:population":44
},
  "geometry": {"coordinates":[82.32873499999999,17.893588],"type":"Point"}
}