{
  "type": "Feature",
  "properties": {
    "iso:country":"IN",
    "ks:ks_alt_nam":"Bhagw\u0101npur",
    "ks:ks_name":"Bhagwanpur",
    "ks:ks_type":"VILLAGE",
    "ks:ks_uagg_main":0,
    "name:eng_x_preferred":[
        "Bhagwanpur"
    ],
    "name:eng_x_variant":[
        "Bhagw\u0101npur"
    ],
    "wof:name":"Bhagwanpur",
    "wof:placetype":"neighbourhood"
},
  "geometry": {"coordinates":[83.002635,25.272892],"type":"Point"}
}