{
  "type": "Feature",
  "properties": {
    "iso:country":"IN",
    "ks:ks_alt_nam":"chaman ganj",
    "ks:ks_name":"Chaman Ganj",
    "ks:ks_pop":900,
    "ks:ks_type":"HABITATION",
    "name:eng_x_preferred":[
        "Chaman Ganj"
    ],
    "wof:name":"Chaman Ganj",
    "wof:placetype":"locality",
    "wof:population":900
},
  "geometry": {"coordinates":[81.98603,25.41089],"type":"Point"}
}