{
  "type": "Feature",
  "properties": {
    "gn:admin1_code":"16.0",
    "gn:admin2_code":"507.0",
    "gn:asciiname":"Tedwa",
    "gn:country_code":"IN",
    "gn:dem":287,
    "gn:feature_class":"P",
    "gn:feature_code":"PPL",
    "gn:name":"Tedw\u0101",
    "gn:population":0,
    "gn:timezone":"Asia/Kolkata",
    "iso:country":"IN",
    "wof:name":"Tedwa",
    "wof:placetype":"locality"
},
  "geometry": {"coordinates":[80.16604,21.59726],"type":"Point"}
}