{
  "type": "Feature",
  "properties": {
    "gn:admin1_code":"36",
    "gn:admin2_code":"178.0",
    "gn:asciiname":"Sulempur",
    "gn:country_code":"IN",
    "gn:dem":99,
    "gn:feature_class":"P",
    "gn:feature_code":"PPL",
    "gn:name":"Sulempur",
    "gn:population":0,
    "gn:timezone":"Asia/Kolkata",
    "iso:country":"IN",
    "ks:ks_name":"Sulem Pur",
    "ks:ks_pop":201,
    "ks:ks_type":"HABITATION",
    "name:eng_x_preferred":[
        "Sulem Pur"
    ],
    "name:eng_x_variant":[
        "Sulempur"
    ],
    "wof:name":"Sulem Pur",
    "wof:placetype":"locality",
    "wof:population":201
},
  "geometry": {"coordinates":[82.541659,26.617673],"type":"Point"}
}