{
  "type": "Feature",
  "properties": {
    "gn:admin1_code":"16.0",
    "gn:admin2_code":"504.0",
    "gn:asciiname":"Shirpur",
    "gn:country_code":"IN",
    "gn:dem":319,
    "gn:feature_class":"P",
    "gn:feature_code":"PPL",
    "gn:name":"Shirpur",
    "gn:population":0,
    "gn:timezone":"Asia/Kolkata",
    "iso:country":"IN",
    "name:ceb_x_preferred":[
        "Shirpur"
    ],
    "name:guj_x_preferred":[
        "\u0ab6\u0abf\u0ab0\u0aaa\u0ac1\u0ab0"
    ],
    "name:hin_x_preferred":[
        "\u0936\u093f\u0930\u092a\u0941\u0930"
    ],
    "name:mar_x_preferred":[
        "\u0936\u093f\u0930\u092a\u0942\u0930"
    ],
    "name:swe_x_preferred":[
        "Shirpur"
    ],
    "name:urd_x_preferred":[
        "\u0634\u0631\u067e\u0648\u0631"
    ],
    "wof:name":"Shirpur",
    "wof:placetype":"locality"
},
  "geometry": {"coordinates":[78.1491,21.1773],"type":"Point"}
}