{
  "type": "Feature",
  "properties": {
    "gn:admin1_code":"16.0",
    "gn:admin2_code":"504.0",
    "gn:asciiname":"Shirpur",
    "gn:country_code":"IN",
    "gn:dem":319,
    "gn:feature_class":"P",
    "gn:feature_code":"PPL",
    "gn:name":"Shirpur",
    "gn:population":0,
    "gn:timezone":"Asia/Kolkata",
    "iso:country":"IN",
    "wof:name":"Shirpur",
    "wof:placetype":"locality"
},
  "geometry": {"coordinates":[78.1491,21.1773],"type":"Point"}
}