{
  "type": "Feature",
  "properties": {
    "iso:country":"IN",
    "ks:ks_alt_nam":"Dighewadi katkarwadi",
    "ks:ks_name":"Dighewadi Katkarwadi",
    "ks:ks_pop":147,
    "ks:ks_type":"HABITATION",
    "name:eng_x_preferred":[
        "Dighewadi Katkarwadi"
    ],
    "wof:name":"Dighewadi Katkarwadi",
    "wof:placetype":"locality",
    "wof:population":147
},
  "geometry": {"coordinates":[73.315704,18.481982],"type":"Point"}
}