{
  "type": "Feature",
  "properties": {
    "iso:country":"IN",
    "ks:ks_name":"Kodwa",
    "ks:ks_pop":335,
    "ks:ks_type":"VILLAGE",
    "name:eng_x_preferred":[
        "Kodwa"
    ],
    "wof:name":"Kodwa",
    "wof:placetype":"locality",
    "wof:population":335
},
  "geometry": {"coordinates":[81.369981,27.50949],"type":"Point"}
}