{
  "type": "Feature",
  "properties": {
    "gn:admin1_code":"25.0",
    "gn:admin2_code":"616.0",
    "gn:asciiname":"Nayakkanpalaiyam",
    "gn:country_code":"IN",
    "gn:dem":36,
    "gn:feature_class":"P",
    "gn:feature_code":"PPL",
    "gn:name":"N\u0101yakkanp\u0101laiyam",
    "gn:population":0,
    "gn:timezone":"Asia/Kolkata",
    "iso:country":"IN",
    "wof:name":"Nayakkanpalaiyam",
    "wof:placetype":"locality"
},
  "geometry": {"coordinates":[79.16985,10.9584],"type":"Point"}
}