{
  "type": "Feature",
  "properties": {
    "iso:country":"IN",
    "ks:ks_name":"Kuduma",
    "ks:ks_pop":112,
    "ks:ks_type":"VILLAGE",
    "name:eng_x_preferred":[
        "Kuduma"
    ],
    "wof:name":"Kuduma",
    "wof:placetype":"locality",
    "wof:population":112
},
  "geometry": {"coordinates":[84.235359,19.627116],"type":"Point"}
}