{
  "type": "Feature",
  "properties": {
    "iso:country":"IN",
    "ks:ks_name":"Kosambi Chak",
    "ks:ks_pop":0,
    "ks:ks_type":"VILLAGE",
    "name:eng_x_preferred":[
        "Kosambi Chak"
    ],
    "wof:name":"Kosambi Chak",
    "wof:placetype":"locality",
    "wof:population":0
},
  "geometry": {"coordinates":[79.75823699999999,20.544734],"type":"Point"}
}