{
  "type": "Feature",
  "properties": {
    "gn:admin1_code":"35.0",
    "gn:admin2_code":"450.0",
    "gn:asciiname":"Kaina",
    "gn:country_code":"IN",
    "gn:dem":435,
    "gn:feature_class":"P",
    "gn:feature_code":"PPL",
    "gn:name":"Kaina",
    "gn:population":0,
    "gn:timezone":"Asia/Kolkata",
    "iso:country":"IN",
    "name:ceb_x_preferred":[
        "Kaina"
    ],
    "name:deu_x_preferred":[
        "Kaina"
    ],
    "name:swe_x_preferred":[
        "Kaina"
    ],
    "wof:name":"Kaina",
    "wof:placetype":"locality"
},
  "geometry": {"coordinates":[80.07738000000001,23.87662000000001],"type":"Point"}
}