{
  "type": "Feature",
  "properties": {
    "gn:admin1_code":"11",
    "gn:admin2_code":"33.0",
    "gn:asciiname":"Dhalana",
    "gn:country_code":"IN",
    "gn:dem":1585,
    "gn:feature_class":"P",
    "gn:feature_code":"PPL",
    "gn:name":"Dhal\u0101na",
    "gn:population":0,
    "gn:timezone":"Asia/Kolkata",
    "iso:country":"IN",
    "wof:name":"Dhalana",
    "wof:placetype":"locality"
},
  "geometry": {"coordinates":[77.19372,31.02115],"type":"Point"}
}