{
  "type": "Feature",
  "properties": {
    "iso:country":"IN",
    "ks:ks_name":"Madhopur Urf Patharchali 2",
    "ks:ks_pop":31,
    "ks:ks_type":"HABITATION",
    "name:eng_x_preferred":[
        "Madhopur Urf Patharchali 2"
    ],
    "wof:name":"Madhopur Urf Patharchali 2",
    "wof:placetype":"locality",
    "wof:population":31
},
  "geometry": {"coordinates":[87.75183699999999,24.515314],"type":"Point"}
}