{
  "type": "Feature",
  "properties": {
    "iso:country":"IN",
    "ks:ks_name":"Sumel",
    "ks:ks_pop":306,
    "ks:ks_type":"HABITATION",
    "name:eng_x_preferred":[
        "Sumel"
    ],
    "wof:name":"Sumel",
    "wof:placetype":"locality",
    "wof:population":306
},
  "geometry": {"coordinates":[76.748329,27.043855],"type":"Point"}
}