{
  "type": "Feature",
  "properties": {
    "iso:country":"IN",
    "ks:ks_name":"Hendegir",
    "ks:ks_pop":1182,
    "ks:ks_type":"VILLAGE",
    "name:eng_x_preferred":[
        "Hendegir"
    ],
    "wof:name":"Hendegir",
    "wof:placetype":"locality",
    "wof:population":1182
},
  "geometry": {"coordinates":[85.161906,23.697343],"type":"Point"}
}