{
  "type": "Feature",
  "properties": {
    "iso:country":"IN",
    "ks:ks_name":"South Chaimarua",
    "ks:ks_pop":524,
    "ks:ks_type":"HABITATION",
    "name:eng_x_preferred":[
        "South Chaimarua"
    ],
    "wof:name":"South Chaimarua",
    "wof:placetype":"locality",
    "wof:population":524
},
  "geometry": {"coordinates":[91.527734,23.656803],"type":"Point"}
}