{
  "type": "Feature",
  "properties": {
    "gn:admin1_code":"36.0",
    "gn:admin2_code":"192.0",
    "gn:asciiname":"Punapar",
    "gn:country_code":"IN",
    "gn:dem":78,
    "gn:feature_class":"P",
    "gn:feature_code":"PPL",
    "gn:name":"Pun\u0101p\u0101r",
    "gn:population":0,
    "gn:timezone":"Asia/Kolkata",
    "iso:country":"IN",
    "ks:ks_alt_nam":"Pun\u0101p\u0101r",
    "ks:ks_name":"Punapar",
    "ks:ks_type":"VILLAGE",
    "name:eng_x_preferred":[
        "Punapar"
    ],
    "name:eng_x_variant":[
        "Pun\u0101p\u0101r"
    ],
    "wof:name":"Punapar",
    "wof:placetype":"locality"
},
  "geometry": {"coordinates":[83.61044699999999,26.17003],"type":"Point"}
}