{
  "type": "Feature",
  "properties": {
    "gn:admin1_code":"2",
    "gn:admin2_code":"546.0",
    "gn:asciiname":"Pulla",
    "gn:country_code":"IN",
    "gn:dem":18,
    "gn:feature_class":"P",
    "gn:feature_code":"PPL",
    "gn:name":"P\u016blla",
    "gn:population":0,
    "gn:timezone":"Asia/Kolkata",
    "iso:country":"IN",
    "name:ara_x_preferred":[
        "\u0628\u0648\u0644\u0627"
    ],
    "name:bar_x_preferred":[
        "Pulla"
    ],
    "name:deu_x_preferred":[
        "Pulla"
    ],
    "name:fin_x_preferred":[
        "Pulla"
    ],
    "name:pol_x_preferred":[
        "Pulla"
    ],
    "name:por_x_preferred":[
        "Pulla"
    ],
    "name:spa_x_preferred":[
        "Pulla"
    ],
    "wof:name":"Pulla",
    "wof:placetype":"locality"
},
  "geometry": {"coordinates":[81.32406,16.80595],"type":"Point"}
}