{
  "type": "Feature",
  "properties": {
    "gn:admin1_code":"11.0",
    "gn:admin2_code":"32.0",
    "gn:asciiname":"Nail",
    "gn:country_code":"IN",
    "gn:dem":1338,
    "gn:feature_class":"P",
    "gn:feature_code":"PPL",
    "gn:name":"Nail",
    "gn:population":0,
    "gn:timezone":"Asia/Kolkata",
    "iso:country":"IN",
    "name:ara_x_preferred":[
        "\u0646\u0627\u064a\u0644"
    ],
    "name:ben_bn_x_preferred":[
        "\u09a8\u09c7\u0987\u09b2"
    ],
    "name:ben_in_x_preferred":[
        "\u09a8\u09c7\u0987\u09b2"
    ],
    "name:ben_x_preferred":[
        "\u09a8\u0996"
    ],
    "name:ceb_x_preferred":[
        "Nail"
    ],
    "name:deu_x_preferred":[
        "Nail"
    ],
    "name:guj_x_preferred":[
        "\u0aa8\u0ac8\u0ab2"
    ],
    "name:hin_x_preferred":[
        "\u0928\u0947\u0932"
    ],
    "name:ita_x_preferred":[
        "Nail"
    ],
    "name:jpn_x_preferred":[
        "\u30cd\u30a4\u30eb"
    ],
    "name:kan_x_preferred":[
        "\u0ca8\u0cc7\u0cb2\u0ccd"
    ],
    "name:mal_x_preferred":[
        "\u0d28\u0d48\u0d7d"
    ],
    "name:mar_x_preferred":[
        "\u0928\u0947\u0932"
    ],
    "name:pan_x_preferred":[
        "\u0a28\u0a47\u0a32"
    ],
    "name:por_x_preferred":[
        "Nail"
    ],
    "name:tam_x_preferred":[
        "\u0b86\u0ba3\u0bbf"
    ],
    "name:tel_x_preferred":[
        "\u0c28\u0c46\u0c2f\u0c3f\u0c32\u0c4d"
    ],
    "name:urd_x_preferred":[
        "\u0646\u0627\u0626\u0644"
    ],
    "name:yid_x_preferred":[
        "\u05e0\u05d0\u05d2\u05dc"
    ],
    "wof:name":"Nail",
    "wof:placetype":"locality"
},
  "geometry": {"coordinates":[77.68866,30.70793],"type":"Point"}
}