{
  "type": "Feature",
  "properties": {
    "iso:country":"IN",
    "ks:ks_name":"Tembhi",
    "ks:ks_pop":8,
    "ks:ks_type":"HABITATION",
    "name:eng_x_preferred":[
        "Tembhi"
    ],
    "wof:name":"Tembhi",
    "wof:placetype":"locality",
    "wof:population":8
},
  "geometry": {"coordinates":[77.994981,20.564828],"type":"Point"}
}