{
  "type": "Feature",
  "properties": {
    "iso:country":"IN",
    "ks:ks_name":"Ambajiparu",
    "ks:ks_pop":410,
    "ks:ks_type":"HABITATION",
    "name:eng_x_preferred":[
        "Ambajiparu"
    ],
    "wof:name":"Ambajiparu",
    "wof:placetype":"locality",
    "wof:population":410
},
  "geometry": {"coordinates":[72.421809,23.879225],"type":"Point"}
}