{
  "type": "Feature",
  "properties": {
    "iso:country":"IN",
    "ks:ks_name":"Sujanapeta",
    "ks:ks_pop":465,
    "ks:ks_type":"HABITATION",
    "name:eng_x_preferred":[
        "Sujanapeta"
    ],
    "wof:name":"Sujanapeta",
    "wof:placetype":"locality",
    "wof:population":465
},
  "geometry": {"coordinates":[82.541253,18.384442],"type":"Point"}
}