{
  "type": "Feature",
  "properties": {
    "iso:country":"IN",
    "ks:ks_name":"Vellankulam Colony",
    "ks:ks_pop":410,
    "ks:ks_type":"HABITATION",
    "name:eng_x_preferred":[
        "Vellankulam Colony"
    ],
    "wof:name":"Vellankulam Colony",
    "wof:placetype":"locality",
    "wof:population":410
},
  "geometry": {"coordinates":[79.272325,12.7684],"type":"Point"}
}