{
  "type": "Feature",
  "properties": {
    "gn:admin1_code":"36.0",
    "gn:admin2_code":"140.0",
    "gn:asciiname":"Pachahira",
    "gn:country_code":"IN",
    "gn:dem":212,
    "gn:feature_class":"P",
    "gn:feature_code":"PPL",
    "gn:name":"Pach\u0101hira",
    "gn:population":0,
    "gn:timezone":"Asia/Kolkata",
    "iso:country":"IN",
    "ks:ks_alt_nam":"Pach\u0101hira",
    "ks:ks_name":"Pachahira",
    "ks:ks_pop":1813,
    "ks:ks_type":"VILLAGE",
    "wof:name":"Pachahira",
    "wof:placetype":"neighbourhood"
},
  "geometry": {"coordinates":[77.21841999999999,28.80657],"type":"Point"}
}