{
  "type": "Feature",
  "properties": {
    "gn:admin1_code":"37.0",
    "gn:admin2_code":"412.0",
    "gn:asciiname":"Sirri",
    "gn:country_code":"IN",
    "gn:dem":314,
    "gn:feature_class":"P",
    "gn:feature_code":"PPL",
    "gn:name":"Sirri",
    "gn:population":0,
    "gn:timezone":"Asia/Kolkata",
    "iso:country":"IN",
    "wof:name":"Sirri",
    "wof:placetype":"locality"
},
  "geometry": {"coordinates":[81.73464,20.94265],"type":"Point"}
}