{
  "type": "Feature",
  "properties": {
    "iso:country":"IN",
    "ks:ks_alt_nam":"Tilathi tola",
    "ks:ks_name":"Tilathi Tola",
    "ks:ks_pop":1151,
    "ks:ks_type":"HABITATION",
    "name:eng_x_preferred":[
        "Tilathi Tola"
    ],
    "wof:name":"Tilathi Tola",
    "wof:placetype":"locality",
    "wof:population":1151
},
  "geometry": {"coordinates":[86.547946,25.758775],"type":"Point"}
}