{
  "type": "Feature",
  "properties": {
    "gn:admin1_code":"39.0",
    "gn:admin2_code":"64.0",
    "gn:asciiname":"Mahargaon",
    "gn:country_code":"IN",
    "gn:dem":1392,
    "gn:feature_class":"P",
    "gn:feature_code":"PPL",
    "gn:name":"Mahargaon",
    "gn:population":0,
    "gn:timezone":"Asia/Kolkata",
    "iso:country":"IN",
    "ks:ks_name":"Mahargaon",
    "ks:ks_type":"VILLAGE",
    "name:eng_x_preferred":[
        "Mahargaon"
    ],
    "wof:name":"Mahargaon",
    "wof:placetype":"locality"
},
  "geometry": {"coordinates":[79.20497400000001,29.88925],"type":"Point"}
}