{
  "type": "Feature",
  "properties": {
    "iso:country":"IN",
    "ks:ks_name":"Pipli",
    "ks:ks_pop":1226,
    "ks:ks_type":"VILLAGE",
    "ks:ks_uagg_main":0,
    "name:eng_x_preferred":[
        "Pipli"
    ],
    "wof:name":"Pipli",
    "wof:placetype":"neighbourhood",
    "wof:population":1226
},
  "geometry": {"coordinates":[88.27422199999999,22.647783],"type":"Point"}
}