{
  "type": "Feature",
  "properties": {
    "iso:country":"IN",
    "ks:ks_name":"Umarkhohi",
    "ks:ks_pop":484,
    "ks:ks_type":"VILLAGE",
    "name:eng_x_preferred":[
        "Umarkhohi"
    ],
    "wof:name":"Umarkhohi",
    "wof:placetype":"locality",
    "wof:population":484
},
  "geometry": {"coordinates":[81.499724,23.855774],"type":"Point"}
}