{
  "type": "Feature",
  "properties": {
    "gn:admin1_code":"39",
    "gn:admin2_code":"67.0",
    "gn:asciiname":"Chandpur",
    "gn:country_code":"IN",
    "gn:dem":246,
    "gn:feature_class":"P",
    "gn:feature_code":"PPL",
    "gn:name":"Ch\u0101ndpur",
    "gn:population":0,
    "gn:timezone":"Asia/Kolkata",
    "iso:country":"IN",
    "ks:ks_alt_nam":"Ch\u0101ndpur",
    "ks:ks_name":"Chandpur",
    "ks:ks_pop":857,
    "ks:ks_type":"VILLAGE",
    "name:ben_x_preferred":[
        "\u099a\u09be\u0981\u09a6\u09aa\u09c1\u09b0"
    ],
    "name:ceb_x_preferred":[
        "Chandpur"
    ],
    "name:deu_x_preferred":[
        "Chandpur"
    ],
    "name:eng_x_preferred":[
        "Chandpur"
    ],
    "name:eng_x_variant":[
        "Ch\u0101ndpur"
    ],
    "name:ita_x_preferred":[
        "Chandpur"
    ],
    "name:nld_x_preferred":[
        "Chandpur"
    ],
    "name:pol_x_preferred":[
        "Chandpur"
    ],
    "name:rus_x_preferred":[
        "\u0427\u0430\u043d\u0434\u043f\u0443\u0440"
    ],
    "name:swe_x_preferred":[
        "Chandpur"
    ],
    "wof:name":"Chandpur",
    "wof:placetype":"locality",
    "wof:population":857
},
  "geometry": {"coordinates":[79.005129,29.281614],"type":"Point"}
}