{
  "type": "Feature",
  "properties": {
    "iso:country":"IN",
    "ks:ks_name":"Pandharibhatal",
    "ks:ks_pop":302,
    "ks:ks_type":"VILLAGE",
    "name:eng_x_preferred":[
        "Pandharibhatal"
    ],
    "wof:name":"Pandharibhatal",
    "wof:placetype":"locality",
    "wof:population":302
},
  "geometry": {"coordinates":[80.059271,19.923709],"type":"Point"}
}