{
  "type": "Feature",
  "properties": {
    "iso:country":"IN",
    "ks:ks_name":"Purbamitani",
    "ks:ks_pop":440,
    "ks:ks_type":"HABITATION",
    "name:eng_x_preferred":[
        "Purbamitani"
    ],
    "wof:name":"Purbamitani",
    "wof:placetype":"locality",
    "wof:population":440
},
  "geometry": {"coordinates":[88.19732999999999,23.342123],"type":"Point"}
}