{
  "type": "Feature",
  "properties": {
    "iso:country":"IN",
    "ks:ks_alt_nam":"Londhe Ghorapade wasti",
    "ks:ks_name":"Londhe Ghorapade Wasti",
    "ks:ks_pop":401,
    "ks:ks_type":"HABITATION",
    "name:eng_x_preferred":[
        "Londhe Ghorapade Wasti"
    ],
    "wof:name":"Londhe Ghorapade Wasti",
    "wof:placetype":"locality",
    "wof:population":401
},
  "geometry": {"coordinates":[74.49455,19.470785],"type":"Point"}
}