{
  "type": "Feature",
  "properties": {
    "iso:country":"IN",
    "ks:ks_name":"Aurangpur",
    "ks:ks_type":"VILLAGE",
    "name:eng_x_preferred":[
        "Aurangpur"
    ],
    "wof:name":"Aurangpur",
    "wof:placetype":"locality"
},
  "geometry": {"coordinates":[77.86565299999999,20.381653],"type":"Point"}
}