{
  "type": "Feature",
  "properties": {
    "gn:admin1_code":"35",
    "gn:admin2_code":"434.0",
    "gn:asciiname":"Panth Piploda",
    "gn:country_code":"IN",
    "gn:dem":462,
    "gn:feature_class":"P",
    "gn:feature_code":"PPL",
    "gn:name":"Panth Piploda",
    "gn:population":0,
    "gn:timezone":"Asia/Kolkata",
    "iso:country":"IN",
    "wof:name":"Panth Piploda",
    "wof:placetype":"locality"
},
  "geometry": {"coordinates":[75.41105999999998,23.66043],"type":"Point"}
}