{
  "type": "Feature",
  "properties": {
    "iso:country":"IN",
    "ks:ks_alt_nam":"PARU",
    "ks:ks_name":"Paru",
    "ks:ks_pop":60,
    "ks:ks_type":"HABITATION",
    "name:eng_x_preferred":[
        "Paru"
    ],
    "wof:name":"Paru",
    "wof:placetype":"locality",
    "wof:population":60
},
  "geometry": {"coordinates":[77.96300100000001,22.153034],"type":"Point"}
}