{
  "type": "Feature",
  "properties": {
    "iso:country":"IN",
    "ks:ks_alt_nam":"RAMPUR TA REOTI",
    "ks:ks_name":"Rampur Ta Reoti",
    "ks:ks_pop":3489,
    "ks:ks_type":"HABITATION",
    "name:eng_x_preferred":[
        "Rampur Ta Reoti"
    ],
    "wof:name":"Rampur Ta Reoti",
    "wof:placetype":"locality",
    "wof:population":3489
},
  "geometry": {"coordinates":[84.29843,25.821883],"type":"Point"}
}