{
  "type": "Feature",
  "properties": {
    "iso:country":"IN",
    "ks:ks_name":"Barti",
    "ks:ks_pop":652,
    "ks:ks_type":"VILLAGE",
    "ks:ks_uagg_main":0,
    "name:eng_x_preferred":[
        "Barti"
    ],
    "wof:name":"Barti",
    "wof:placetype":"neighbourhood",
    "wof:population":652
},
  "geometry": {"coordinates":[86.20558699999999,20.348108],"type":"Point"}
}