{
  "type": "Feature",
  "properties": {
    "gn:admin1_code":"36",
    "gn:admin2_code":"193.0",
    "gn:asciiname":"Sawan",
    "gn:country_code":"IN",
    "gn:dem":71,
    "gn:feature_class":"P",
    "gn:feature_code":"PPL",
    "gn:name":"Saw\u0101n",
    "gn:population":0,
    "gn:timezone":"Asia/Kolkata",
    "iso:country":"IN",
    "name:ara_x_preferred":[
        "\u0633\u0627\u0648\u0627\u0646"
    ],
    "name:mal_x_preferred":[
        "\u0d38\u0d3e\u0d35\u0d7b"
    ],
    "name:pan_x_preferred":[
        "\u0a38\u0a3e\u0a35\u0a23"
    ],
    "name:tam_x_preferred":[
        "\u0b9a\u0bbe\u0bb5\u0ba9\u0bcd"
    ],
    "name:und_x_variant":[
        "Saw\u0101n",
        "Sawan"
    ],
    "name:urd_x_preferred":[
        "\u0633\u0627\u0648\u0646"
    ],
    "wof:name":"Sawan",
    "wof:placetype":"locality"
},
  "geometry": {"coordinates":[83.97601,25.90082],"type":"Point"}
}