{
  "type": "Feature",
  "properties": {
    "gn:admin1_code":"36",
    "gn:admin2_code":"193.0",
    "gn:asciiname":"Sawan",
    "gn:country_code":"IN",
    "gn:dem":71,
    "gn:feature_class":"P",
    "gn:feature_code":"PPL",
    "gn:name":"Saw\u0101n",
    "gn:population":0,
    "gn:timezone":"Asia/Kolkata",
    "iso:country":"IN",
    "name:und_x_variant":[
        "Saw\u0101n",
        "Sawan"
    ],
    "wof:name":"Sawan",
    "wof:placetype":"locality"
},
  "geometry": {"coordinates":[83.97601,25.90082],"type":"Point"}
}