{
  "type": "Feature",
  "properties": {
    "iso:country":"IN",
    "ks:ks_name":"Tola Baghakolo",
    "ks:ks_pop":114,
    "ks:ks_type":"VILLAGE",
    "name:eng_x_preferred":[
        "Tola Baghakolo"
    ],
    "wof:name":"Tola Baghakolo",
    "wof:placetype":"locality",
    "wof:population":114
},
  "geometry": {"coordinates":[86.250089,24.630989],"type":"Point"}
}