{
  "type": "Feature",
  "properties": {
    "iso:country":"IN",
    "ks:ks_name":"Pakalagudem",
    "ks:ks_pop":150,
    "ks:ks_type":"HABITATION",
    "name:eng_x_preferred":[
        "Pakalagudem"
    ],
    "wof:name":"Pakalagudem",
    "wof:placetype":"locality",
    "wof:population":150
},
  "geometry": {"coordinates":[81.126751,17.140522],"type":"Point"}
}