{
  "type": "Feature",
  "properties": {
    "iso:country":"IN",
    "ks:ks_name":"Madna",
    "ks:ks_pop":4734,
    "ks:ks_type":"URBAN",
    "ks:ks_uagg_main":0,
    "name:eng_x_preferred":[
        "Madna"
    ],
    "wof:name":"Madna",
    "wof:placetype":"neighbourhood",
    "wof:population":4734
},
  "geometry": {"coordinates":[88.041399,24.570411],"type":"Point"}
}