{
  "type": "Feature",
  "properties": {
    "iso:country":"IN",
    "ks:ks_alt_nam":"Balasaheb nagar",
    "ks:ks_name":"Balasaheb Nagar",
    "ks:ks_pop":468,
    "ks:ks_type":"HABITATION",
    "ks:ks_uagg_main":0,
    "name:eng_x_preferred":[
        "Balasaheb Nagar"
    ],
    "wof:name":"Balasaheb Nagar",
    "wof:placetype":"locality",
    "wof:population":468
},
  "geometry": {"coordinates":[74.348344,16.715019],"type":"Point"}
}