{
  "type": "Feature",
  "properties": {
    "iso:country":"IN",
    "ks:ks_name":"Ikali",
    "ks:ks_pop":311,
    "ks:ks_type":"HABITATION",
    "name:eng_x_preferred":[
        "Ikali"
    ],
    "wof:name":"Ikali",
    "wof:placetype":"locality",
    "wof:population":311
},
  "geometry": {"coordinates":[79.202348,11.160162],"type":"Point"}
}