{
  "type": "Feature",
  "properties": {
    "iso:country":"IN",
    "ks:ks_name":"Venkataswamipalli",
    "ks:ks_pop":11,
    "ks:ks_type":"HABITATION",
    "name:eng_x_preferred":[
        "Venkataswamipalli"
    ],
    "wof:name":"Venkataswamipalli",
    "wof:placetype":"locality",
    "wof:population":11
},
  "geometry": {"coordinates":[77.9516,14.043549],"type":"Point"}
}