{
  "type": "Feature",
  "properties": {
    "iso:country":"IN",
    "ks:ks_alt_nam":"REFUSI TOLA",
    "ks:ks_name":"Refusi Tola",
    "ks:ks_pop":446,
    "ks:ks_type":"HABITATION",
    "ks:ks_uagg_main":0,
    "name:eng_x_preferred":[
        "Refusi Tola"
    ],
    "wof:name":"Refusi Tola",
    "wof:placetype":"neighbourhood",
    "wof:population":446
},
  "geometry": {"coordinates":[87.516541,25.723211],"type":"Point"}
}