{
  "type": "Feature",
  "properties": {
    "iso:country":"IN",
    "ks:ks_name":"Kushbauna",
    "ks:ks_pop":1146,
    "ks:ks_type":"HABITATION",
    "name:eng_x_preferred":[
        "Kushbauna"
    ],
    "wof:name":"Kushbauna",
    "wof:placetype":"locality",
    "wof:population":1146
},
  "geometry": {"coordinates":[83.14720199999999,27.283287],"type":"Point"}
}