{
  "type": "Feature",
  "properties": {
    "iso:country":"IN",
    "ks:ks_name":"Baraia Chak",
    "ks:ks_pop":257,
    "ks:ks_type":"VILLAGE",
    "ks:ks_uagg_main":0,
    "name:eng_x_preferred":[
        "Baraia Chak"
    ],
    "wof:name":"Baraia Chak",
    "wof:placetype":"neighbourhood",
    "wof:population":257
},
  "geometry": {"coordinates":[87.485235,25.166459],"type":"Point"}
}