{
  "type": "Feature",
  "properties": {
    "iso:country":"IN",
    "ks:ks_name":"Mal Falia",
    "ks:ks_pop":236,
    "ks:ks_type":"HABITATION",
    "name:eng_x_preferred":[
        "Mal Falia"
    ],
    "wof:name":"Mal Falia",
    "wof:placetype":"locality",
    "wof:population":236
},
  "geometry": {"coordinates":[74.094083,23.269944],"type":"Point"}
}