{
  "type": "Feature",
  "properties": {
    "iso:country":"IN",
    "ks:ks_name":"Khandikuti",
    "ks:ks_pop":47,
    "ks:ks_type":"VILLAGE",
    "name:eng_x_preferred":[
        "Khandikuti"
    ],
    "wof:name":"Khandikuti",
    "wof:placetype":"locality",
    "wof:population":47
},
  "geometry": {"coordinates":[84.36553499999999,20.572015],"type":"Point"}
}