{
  "type": "Feature",
  "properties": {
    "gn:admin1_code":"16.0",
    "gn:admin2_code":"515",
    "gn:asciiname":"Ajanta",
    "gn:country_code":"IN",
    "gn:dem":580,
    "gn:feature_class":"P",
    "gn:feature_code":"PPL",
    "gn:name":"Ajanta",
    "gn:population":0,
    "gn:timezone":"Asia/Kolkata",
    "iso:country":"IN",
    "name:dan_x_preferred":[
        "Ajanta"
    ],
    "name:fas_x_preferred":[
        "\u0627\u062c\u0627\u0646\u062a\u0627"
    ],
    "name:hrv_x_preferred":[
        "Ajanta"
    ],
    "name:ita_x_preferred":[
        "Ajanta"
    ],
    "name:mar_x_preferred":[
        "\u0905\u091c\u093f\u0902\u0920\u093e"
    ],
    "name:pnb_x_preferred":[
        "\u0627\u062c\u0646\u062a\u0627"
    ],
    "name:tel_x_preferred":[
        "\u0c05\u0c1c\u0c02\u0c24\u0c3e"
    ],
    "wof:name":"Ajanta",
    "wof:placetype":"locality"
},
  "geometry": {"coordinates":[75.74936,20.53194],"type":"Point"}
}