{
  "type": "Feature",
  "properties": {
    "gn:admin1_code":"16.0",
    "gn:admin2_code":"515",
    "gn:asciiname":"Ajanta",
    "gn:country_code":"IN",
    "gn:dem":580,
    "gn:feature_class":"P",
    "gn:feature_code":"PPL",
    "gn:name":"Ajanta",
    "gn:population":0,
    "gn:timezone":"Asia/Kolkata",
    "iso:country":"IN",
    "wof:name":"Ajanta",
    "wof:placetype":"locality"
},
  "geometry": {"coordinates":[75.74936,20.53194],"type":"Point"}
}