{
  "type": "Feature",
  "properties": {
    "iso:country":"IN",
    "ks:ks_name":"Krishnasamyvattam",
    "ks:ks_pop":114,
    "ks:ks_type":"HABITATION",
    "ks:ks_uagg_main":0,
    "name:eng_x_preferred":[
        "Krishnasamyvattam"
    ],
    "wof:name":"Krishnasamyvattam",
    "wof:placetype":"neighbourhood",
    "wof:population":114
},
  "geometry": {"coordinates":[78.492062,12.433454],"type":"Point"}
}