{
  "type": "Feature",
  "properties": {
    "gn:admin1_code":"40",
    "gn:admin2_code":"539.0",
    "gn:asciiname":"Yallapur",
    "gn:country_code":"IN",
    "gn:dem":157,
    "gn:feature_class":"P",
    "gn:feature_code":"PPL",
    "gn:name":"Yall\u0101pur",
    "gn:population":0,
    "gn:timezone":"Asia/Kolkata",
    "iso:country":"IN",
    "name:urd_x_preferred":[
        "\u06cc\u0644\u06c1 \u067e\u0648\u0631"
    ],
    "wof:name":"Yallapur",
    "wof:placetype":"neighbourhood"
},
  "geometry": {"coordinates":[79.3553,16.69366],"type":"Point"}
}