{
  "type": "Feature",
  "properties": {
    "gn:admin1_code":"19.0",
    "gn:admin2_code":"563",
    "gn:asciiname":"Idgundi",
    "gn:country_code":"IN",
    "gn:dem":466,
    "gn:feature_class":"P",
    "gn:feature_code":"PPL",
    "gn:name":"Idgundi",
    "gn:population":0,
    "gn:timezone":"Asia/Kolkata",
    "iso:country":"IN",
    "ks:ks_name":"Idgundi",
    "ks:ks_type":"VILLAGE",
    "name:eng_x_preferred":[
        "Idgundi"
    ],
    "wof:name":"Idgundi",
    "wof:placetype":"locality"
},
  "geometry": {"coordinates":[74.64191,14.911148],"type":"Point"}
}