{
  "type": "Feature",
  "properties": {
    "gn:admin1_code":"12.0",
    "gn:admin2_code":"6.0",
    "gn:asciiname":"Khanial Kot",
    "gn:country_code":"IN",
    "gn:dem":1679,
    "gn:feature_class":"P",
    "gn:feature_code":"PPL",
    "gn:name":"Khani\u0101l K\u014dt",
    "gn:population":0,
    "gn:timezone":"Asia/Kolkata",
    "iso:country":"IN",
    "wof:name":"Khanial Kot",
    "wof:placetype":"locality"
},
  "geometry": {"coordinates":[74.39149,33.53065],"type":"Point"}
}