{
  "type": "Feature",
  "properties": {
    "iso:country":"IN",
    "ks:ks_name":"Paligaon",
    "ks:ks_pop":761,
    "ks:ks_type":"VILLAGE",
    "name:eng_x_preferred":[
        "Paligaon"
    ],
    "wof:name":"Paligaon",
    "wof:placetype":"locality",
    "wof:population":761
},
  "geometry": {"coordinates":[83.976411,20.873916],"type":"Point"}
}