{
  "type": "Feature",
  "properties": {
    "iso:country":"IN",
    "ks:ks_name":"Gangarampur",
    "ks:ks_pop":137,
    "ks:ks_type":"VILLAGE",
    "ks:ks_uagg_main":0,
    "name:ben_x_preferred":[
        "\u0997\u0999\u09cd\u0997\u09be\u09b0\u09be\u09ae\u09aa\u09c1\u09b0"
    ],
    "name:eng_x_preferred":[
        "Gangarampur"
    ],
    "name:hin_x_preferred":[
        "\u0917\u0902\u0917\u093e\u0930\u093e\u092e\u092a\u0941\u0930"
    ],
    "wof:name":"Gangarampur",
    "wof:placetype":"neighbourhood",
    "wof:population":137
},
  "geometry": {"coordinates":[87.876396,24.638134],"type":"Point"}
}