{
  "type": "Feature",
  "properties": {
    "iso:country":"IN",
    "ks:ks_name":"Sawant Nagar",
    "ks:ks_pop":23,
    "ks:ks_type":"HABITATION",
    "name:eng_x_preferred":[
        "Sawant Nagar"
    ],
    "wof:name":"Sawant Nagar",
    "wof:placetype":"locality",
    "wof:population":23
},
  "geometry": {"coordinates":[78.902238,24.677491],"type":"Point"}
}