{
  "type": "Feature",
  "properties": {
    "iso:country":"IN",
    "ks:ks_name":"Sana Orali",
    "ks:ks_pop":282,
    "ks:ks_type":"HABITATION",
    "name:eng_x_preferred":[
        "Sana Orali"
    ],
    "wof:name":"Sana Orali",
    "wof:placetype":"locality",
    "wof:population":282
},
  "geometry": {"coordinates":[86.602743,20.91424],"type":"Point"}
}