{
  "type": "Feature",
  "properties": {
    "iso:country":"IN",
    "ks:ks_alt_nam":"YADAV TOLA",
    "ks:ks_name":"Yadav Tola",
    "ks:ks_pop":400,
    "ks:ks_type":"HABITATION",
    "name:eng_x_preferred":[
        "Yadav Tola"
    ],
    "wof:name":"Yadav Tola",
    "wof:placetype":"locality",
    "wof:population":400
},
  "geometry": {"coordinates":[83.486689,24.848951],"type":"Point"}
}