{
  "type": "Feature",
  "properties": {
    "gn:admin1_code":"19.0",
    "gn:admin2_code":"563.0",
    "gn:asciiname":"Hadgeri",
    "gn:country_code":"IN",
    "gn:dem":14,
    "gn:feature_class":"P",
    "gn:feature_code":"PPL",
    "gn:name":"H\u0101dgeri",
    "gn:population":0,
    "gn:timezone":"Asia/Kolkata",
    "iso:country":"IN",
    "ks:ks_name":"Hadageri",
    "ks:ks_pop":193,
    "ks:ks_type":"HABITATION",
    "name:eng_x_preferred":[
        "Hadageri"
    ],
    "name:eng_x_variant":[
        "Hadgeri"
    ],
    "wof:name":"Hadageri",
    "wof:placetype":"locality",
    "wof:population":193
},
  "geometry": {"coordinates":[74.51978699999999,14.296285],"type":"Point"}
}