{
  "type": "Feature",
  "properties": {
    "iso:country":"IN",
    "ks:ks_name":"Vasan Chauhan",
    "ks:ks_pop":744,
    "ks:ks_type":"VILLAGE",
    "name:eng_x_preferred":[
        "Vasan Chauhan"
    ],
    "wof:name":"Vasan Chauhan",
    "wof:placetype":"locality",
    "wof:population":744
},
  "geometry": {"coordinates":[71.68514999999999,24.726798],"type":"Point"}
}