{
  "type": "Feature",
  "properties": {
    "iso:country":"IN",
    "ks:ks_name":"Sajnapara",
    "ks:ks_pop":2411,
    "ks:ks_type":"VILLAGE",
    "name:eng_x_preferred":[
        "Sajnapara"
    ],
    "wof:name":"Sajnapara",
    "wof:placetype":"locality",
    "wof:population":2411
},
  "geometry": {"coordinates":[89.034288,26.685967],"type":"Point"}
}