{
  "type": "Feature",
  "properties": {
    "iso:country":"IN",
    "ks:ks_name":"Dolaniyon Ki Dhani",
    "ks:ks_pop":100,
    "ks:ks_type":"HABITATION",
    "name:eng_x_preferred":[
        "Dolaniyon Ki Dhani"
    ],
    "wof:name":"Dolaniyon Ki Dhani",
    "wof:placetype":"locality",
    "wof:population":100
},
  "geometry": {"coordinates":[71.342108,25.508292],"type":"Point"}
}