{
  "type": "Feature",
  "properties": {
    "iso:country":"IN",
    "ks:ks_name":"Satbhaiwadi",
    "ks:ks_pop":121,
    "ks:ks_type":"HABITATION",
    "name:eng_x_preferred":[
        "Satbhaiwadi"
    ],
    "wof:name":"Satbhaiwadi",
    "wof:placetype":"locality",
    "wof:population":121
},
  "geometry": {"coordinates":[73.433333,17.305278],"type":"Point"}
}