{
  "type": "Feature",
  "properties": {
    "iso:country":"IN",
    "ks:ks_name":"Dungri Falia",
    "ks:ks_pop":371,
    "ks:ks_type":"HABITATION",
    "name:eng_x_preferred":[
        "Dungri Falia"
    ],
    "wof:name":"Dungri Falia",
    "wof:placetype":"locality",
    "wof:population":371
},
  "geometry": {"coordinates":[73.075056,20.3405],"type":"Point"}
}