{
  "type": "Feature",
  "properties": {
    "iso:country":"IN",
    "ks:ks_name":"Damodra",
    "ks:ks_pop":452,
    "ks:ks_type":"HABITATION",
    "name:eng_x_preferred":[
        "Damodra"
    ],
    "wof:name":"Damodra",
    "wof:placetype":"locality",
    "wof:population":452
},
  "geometry": {"coordinates":[86.80109299999999,24.706206],"type":"Point"}
}