{
  "type": "Feature",
  "properties": {
    "iso:country":"IN",
    "ks:ks_name":"Annara",
    "ks:ks_pop":230,
    "ks:ks_type":"HABITATION",
    "ks:ks_uagg_main":0,
    "name:eng_x_preferred":[
        "Annara"
    ],
    "wof:name":"Annara",
    "wof:placetype":"neighbourhood",
    "wof:population":230
},
  "geometry": {"coordinates":[74.750669,13.182697],"type":"Point"}
}