{
  "type": "Feature",
  "properties": {
    "iso:country":"IN",
    "ks:ks_name":"Koriachak Amanat",
    "ks:ks_pop":0,
    "ks:ks_type":"VILLAGE",
    "name:eng_x_preferred":[
        "Koriachak Amanat"
    ],
    "wof:name":"Koriachak Amanat",
    "wof:placetype":"locality",
    "wof:population":0
},
  "geometry": {"coordinates":[87.459729,25.266066],"type":"Point"}
}