{
  "type": "Feature",
  "properties": {
    "iso:country":"IN",
    "ks:ks_name":"Durgapur",
    "ks:ks_pop":0,
    "ks:ks_type":"VILLAGE",
    "name:eng_x_preferred":[
        "Durgapur"
    ],
    "wof:name":"Durgapur",
    "wof:placetype":"locality",
    "wof:population":0
},
  "geometry": {"coordinates":[84.040733,25.245401],"type":"Point"}
}