{
  "type": "Feature",
  "properties": {
    "iso:country":"IN",
    "ks:ks_name":"Kovinipatti",
    "ks:ks_pop":112,
    "ks:ks_type":"HABITATION",
    "name:eng_x_preferred":[
        "Kovinipatti"
    ],
    "wof:name":"Kovinipatti",
    "wof:placetype":"locality",
    "wof:population":112
},
  "geometry": {"coordinates":[78.60123900000001,9.934781],"type":"Point"}
}