{
  "type": "Feature",
  "properties": {
    "iso:country":"IN",
    "ks:ks_name":"Ahiran Purwa/vijulideeh",
    "ks:ks_pop":122,
    "ks:ks_type":"HABITATION",
    "name:eng_x_preferred":[
        "Ahiran Purwa/vijulideeh"
    ],
    "wof:name":"Ahiran Purwa/vijulideeh",
    "wof:placetype":"locality",
    "wof:population":122
},
  "geometry": {"coordinates":[81.845467,26.589875],"type":"Point"}
}