{
  "type": "Feature",
  "properties": {
    "iso:country":"IN",
    "ks:ks_name":"Paskewada",
    "ks:ks_pop":61,
    "ks:ks_type":"HABITATION",
    "name:eng_x_preferred":[
        "Paskewada"
    ],
    "wof:name":"Paskewada",
    "wof:placetype":"locality",
    "wof:population":61
},
  "geometry": {"coordinates":[74.202332,14.865662],"type":"Point"}
}