{
  "type": "Feature",
  "properties": {
    "gn:admin1_code":"36",
    "gn:admin2_code":"194.0",
    "gn:asciiname":"Adipur",
    "gn:country_code":"IN",
    "gn:dem":92,
    "gn:feature_class":"P",
    "gn:feature_code":"PPL",
    "gn:name":"\u0100d\u012bpur",
    "gn:population":0,
    "gn:timezone":"Asia/Kolkata",
    "iso:country":"IN",
    "ks:ks_alt_nam":"\u0100d\u012bpur",
    "ks:ks_name":"Adipur",
    "ks:ks_pop":560,
    "ks:ks_type":"VILLAGE",
    "ks:ks_uagg_main":0,
    "name:eng_x_preferred":[
        "Adipur"
    ],
    "name:eng_x_variant":[
        "\u0100d\u012bpur"
    ],
    "name:fas_x_preferred":[
        "\u0627\u062f\u06cc\u067e\u0648\u0631"
    ],
    "name:guj_x_preferred":[
        "\u0a86\u0aa6\u0abf\u0aaa\u0ac1\u0ab0"
    ],
    "name:hin_x_preferred":[
        "\u0906\u0926\u093f\u092a\u0941\u0930"
    ],
    "name:pnb_x_preferred":[
        "\u0622\u062f\u06cc\u067e\u0648\u0631"
    ],
    "name:urd_x_preferred":[
        "\u0627\u062f\u06cc\u067e\u0648\u0631"
    ],
    "wof:name":"Adipur",
    "wof:placetype":"neighbourhood",
    "wof:population":560
},
  "geometry": {"coordinates":[82.63582100000001,25.525089],"type":"Point"}
}