{
  "type": "Feature",
  "properties": {
    "iso:country":"IN",
    "ks:ks_name":"Tentulia",
    "ks:ks_pop":463,
    "ks:ks_type":"VILLAGE",
    "name:eng_x_preferred":[
        "Tentulia"
    ],
    "wof:name":"Tentulia",
    "wof:placetype":"locality",
    "wof:population":463
},
  "geometry": {"coordinates":[86.885384,21.378852],"type":"Point"}
}