{
  "type": "Feature",
  "properties": {
    "iso:country":"IN",
    "name:ara_x_preferred":[
        "\u062f\u062a\u0648\u0627\u062f\u064a \u0623\u0643\u0648\u0631\u062f\u064a"
    ],
    "name:ben_bn_x_preferred":[
        "\u09a6\u09c1\u09a4\u09be\u0993\u09af\u09bc\u09be\u09dc\u09bf \u0986\u0995\u09c1\u09b0\u09a1\u09bf"
    ],
    "name:ben_in_x_preferred":[
        "\u09a6\u09c1\u09a4\u09be\u0993\u09af\u09bc\u09be\u09dc\u09bf \u0986\u0995\u09c1\u09b0\u09a1\u09bf"
    ],
    "name:eng_x_preferred":[
        "Dutawadi Akurdi"
    ],
    "name:guj_x_preferred":[
        "\u0aa6\u0ac1\u0aa4\u0abe\u0ab5\u0abe\u0aa1\u0ac0 \u0a85\u0a95\u0ac1\u0ab0\u0acd\u0aa1\u0ac0"
    ],
    "name:hin_x_preferred":[
        "\u0926\u0942\u0924\u093e\u0935\u093e\u095c\u0940 \u0905\u0915\u0941\u0930\u094d\u0926\u0940"
    ],
    "name:kan_x_preferred":[
        "\u0ca6\u0cc1\u0ca4\u0cbe\u0cb5\u0cbe\u0ca6\u0cbf \u0c85\u0c95\u0cc2\u0cb0\u0ccd\u0ca1\u0cbf"
    ],
    "name:mal_x_preferred":[
        "\u0d26\u0d41\u0d24\u0d35\u0d3e\u0d1f\u0d3f \u0d05\u0d15\u0d41\u0d7c\u0d26\u0d3f"
    ],
    "name:mar_x_preferred":[
        "\u0926\u0924\u094d\u0924\u0935\u093e\u0921\u0940 \u0906\u0915\u0941\u0930\u094d\u0921\u0940"
    ],
    "name:pan_x_preferred":[
        "\u0a26\u0a71\u0a24\u0a3e\u0a35\u0a5c\u0a40 \u0a05\u0a15\u0a41\u0a30\u0a21\u0a40"
    ],
    "name:tam_x_preferred":[
        "\u0ba4\u0bc1\u0b9f\u0bbe\u0bb5\u0bbe\u0b9f\u0bbf \u0b85\u0b95\u0bc1\u0bb0\u0bcd\u0ba4\u0bbf"
    ],
    "name:tel_x_preferred":[
        "\u0c26\u0c42\u0c24\u0c35\u0c3e\u0c21\u0c3f \u0c05\u0c15\u0c4d\u0c30\u0c42\u0c21\u0c3f"
    ],
    "name:urd_x_preferred":[
        "\u062f\u062a\u0627\u0648\u0627\u0691\u06cc \u0627\u06a9\u0631\u062f\u06cc"
    ],
    "qs:gn_adm0_cc":"IN",
    "qs:gn_local":7626690,
    "qs:gn_nam_loc":"kherdi",
    "qs:gn_namadm1":"16",
    "qs:local_max":167,
    "qs:local_sum":278,
    "qs:localhoods":6,
    "qs:name":"Dutawadi Akurdi",
    "qs:name_adm0":"India",
    "qs:name_adm1":"Maharashtra",
    "qs:name_adm2":"Pune",
    "qs:name_local":"Pimpri Chinchwad",
    "qs:photo_max":3,
    "qs:photo_sum":3,
    "qs:placetype":"Suburb",
    "qs:quad_count":1,
    "qs:woe_adm0":23424848,
    "qs:woe_adm1":2345750,
    "qs:woe_adm2":12586544,
    "qs:woe_lau":0,
    "qs:woe_local":2275834,
    "qs:woe_ver":"7.10.0",
    "wof:lang":[
        "eng"
    ],
    "wof:name":"Dutawadi Akurdi",
    "wof:placetype":"neighbourhood"
},
  "geometry": {"coordinates":[73.77594000000001,18.654053],"type":"Point"}
}