{
  "type": "Feature",
  "properties": {
    "gn:admin1_code":"34.0",
    "gn:admin2_code":"230.0",
    "gn:asciiname":"Sekandarpur",
    "gn:country_code":"IN",
    "gn:dem":63,
    "gn:feature_class":"P",
    "gn:feature_code":"PPL",
    "gn:name":"Sekandarpur",
    "gn:population":0,
    "gn:timezone":"Asia/Kolkata",
    "iso:country":"IN",
    "ks:ks_name":"Sikandarpur",
    "ks:ks_pop":3010,
    "ks:ks_type":"VILLAGE",
    "ks:ks_uagg_main":0,
    "name:eng_x_preferred":[
        "Sikandarpur"
    ],
    "wof:name":"Sikandarpur",
    "wof:placetype":"neighbourhood",
    "wof:population":3010
},
  "geometry": {"coordinates":[84.848748,25.575131],"type":"Point"}
}