{
  "type": "Feature",
  "properties": {
    "iso:country":"IN",
    "ks:ks_name":"Bholwatal",
    "ks:ks_pop":118,
    "ks:ks_type":"HABITATION",
    "name:eng_x_preferred":[
        "Bholwatal"
    ],
    "wof:name":"Bholwatal",
    "wof:placetype":"locality",
    "wof:population":118
},
  "geometry": {"coordinates":[81.285589,26.044245],"type":"Point"}
}