{
  "type": "Feature",
  "properties": {
    "iso:country":"IN",
    "ks:ks_name":"Damplu",
    "ks:ks_pop":458,
    "ks:ks_type":"VILLAGE",
    "name:eng_x_preferred":[
        "Damplu"
    ],
    "wof:name":"Damplu",
    "wof:placetype":"locality",
    "wof:population":458
},
  "geometry": {"coordinates":[84.158997,19.820342],"type":"Point"}
}