{
  "type": "Feature",
  "properties": {
    "iso:country":"IN",
    "ks:ks_name":"Sargudiyavas",
    "ks:ks_pop":248,
    "ks:ks_type":"HABITATION",
    "name:eng_x_preferred":[
        "Sargudiyavas"
    ],
    "wof:name":"Sargudiyavas",
    "wof:placetype":"locality",
    "wof:population":248
},
  "geometry": {"coordinates":[71.743364,24.127865],"type":"Point"}
}