{
  "type": "Feature",
  "properties": {
    "iso:country":"IN",
    "ks:ks_alt_nam":"Bogal\u016br",
    "ks:ks_name":"Bogalur",
    "ks:ks_pop":2027,
    "ks:ks_type":"VILLAGE",
    "name:eng_x_preferred":[
        "Bogalur"
    ],
    "name:eng_x_variant":[
        "Bogal\u016br"
    ],
    "wof:name":"Bogalur",
    "wof:placetype":"locality",
    "wof:population":2027
},
  "geometry": {"coordinates":[78.707458,9.403243],"type":"Point"}
}