{
  "type": "Feature",
  "properties": {
    "gn:admin1_code":"36.0",
    "gn:admin2_code":"161.0",
    "gn:asciiname":"Bitathi",
    "gn:country_code":"IN",
    "gn:dem":147,
    "gn:feature_class":"P",
    "gn:feature_code":"PPL",
    "gn:name":"Bitathi",
    "gn:population":0,
    "gn:timezone":"Asia/Kolkata",
    "iso:country":"IN",
    "wof:name":"Bitathi",
    "wof:placetype":"neighbourhood"
},
  "geometry": {"coordinates":[79.08785,26.63755],"type":"Point"}
}