{
  "type": "Feature",
  "properties": {
    "gn:admin1_code":"12",
    "gn:admin2_code":"20.0",
    "gn:asciiname":"Jabar",
    "gn:country_code":"IN",
    "gn:dem":2750,
    "gn:feature_class":"P",
    "gn:feature_code":"PPL",
    "gn:name":"Jabar",
    "gn:population":0,
    "gn:timezone":"Asia/Kolkata",
    "iso:country":"IN",
    "wof:name":"Jabar",
    "wof:placetype":"locality"
},
  "geometry": {"coordinates":[74.96041,33.39279000000001],"type":"Point"}
}