{
  "type": "Feature",
  "properties": {
    "iso:country":"IN",
    "ks:ks_name":"Malda Khurd",
    "ks:ks_pop":263,
    "ks:ks_type":"VILLAGE",
    "ks:ks_uagg_main":0,
    "name:eng_x_preferred":[
        "Malda Khurd"
    ],
    "wof:name":"Malda Khurd",
    "wof:placetype":"neighbourhood",
    "wof:population":263
},
  "geometry": {"coordinates":[86.664536,25.068304],"type":"Point"}
}