{
  "type": "Feature",
  "properties": {
    "gn:admin1_code":"34.0",
    "gn:admin2_code":"238.0",
    "gn:asciiname":"Parasi",
    "gn:country_code":"IN",
    "gn:dem":153,
    "gn:feature_class":"P",
    "gn:feature_code":"PPL",
    "gn:name":"Par\u0101si",
    "gn:population":0,
    "gn:timezone":"Asia/Kolkata",
    "iso:country":"IN",
    "name:bpy_x_preferred":[
        "\u09aa\u09be\u09b0\u09be\u09b8\u09bf"
    ],
    "name:ita_x_preferred":[
        "Parasi"
    ],
    "name:msa_x_preferred":[
        "Parasi"
    ],
    "name:nld_x_preferred":[
        "Parasi"
    ],
    "name:ori_x_preferred":[
        "\u0b2a\u0b3e\u0b30\u0b3e\u0b38\u0b3f"
    ],
    "name:pnb_x_preferred":[
        "\u067e\u0627\u0631\u0627\u0633\u06cc"
    ],
    "name:pol_x_preferred":[
        "Parasi"
    ],
    "name:por_x_preferred":[
        "Parasi"
    ],
    "name:urd_x_preferred":[
        "\u067e\u0627\u0631\u0627\u0633\u06cc"
    ],
    "name:vie_x_preferred":[
        "Parasi"
    ],
    "name:zho_x_preferred":[
        "\u5e15\u62c9\u897f"
    ],
    "wof:name":"Parasi",
    "wof:placetype":"locality"
},
  "geometry": {"coordinates":[86.08653000000002,24.79213],"type":"Point"}
}