{
  "type": "Feature",
  "properties": {
    "gn:country":"IN",
    "gn:fcode":"PPL",
    "gn:pop":89289,
    "iso:country":"IN",
    "name:ben_x_preferred":[
        "\u09b6\u09be\u09b9\u09a6\u09cb\u09b2"
    ],
    "name:bpy_x_preferred":[
        "\u09b6\u09be\u09b9\u09a6\u09cb\u09b2"
    ],
    "name:ceb_x_preferred":[
        "Shahdol"
    ],
    "name:deu_x_preferred":[
        "Shahdol"
    ],
    "name:eng_x_preferred":[
        "Shahdol"
    ],
    "name:fra_x_preferred":[
        "Shahdol"
    ],
    "name:guj_x_preferred":[
        "\u0ab6\u0abe\u0ab9\u0aa1\u0acb\u0ab2"
    ],
    "name:hif_x_preferred":[
        "Shahdol"
    ],
    "name:hin_x_preferred":[
        "\u0936\u0939\u0926\u094b\u0932"
    ],
    "name:ind_x_preferred":[
        "Shahdol"
    ],
    "name:ita_x_preferred":[
        "Shahdol"
    ],
    "name:jpn_x_preferred":[
        "\u30b7\u30e3\u30fc\u30c9\u30eb"
    ],
    "name:kan_x_preferred":[
        "\u0cb6\u0cb9\u0ccd\u0ca1\u0cbe\u0cb2\u0ccd"
    ],
    "name:kor_x_preferred":[
        "\uc0e4\ub3c4\uc77c"
    ],
    "name:mar_x_preferred":[
        "\u0936\u093e\u0939\u0921\u094b\u0932"
    ],
    "name:mlg_x_preferred":[
        "Shahdol"
    ],
    "name:msa_x_preferred":[
        "Shahdol"
    ],
    "name:nep_x_preferred":[
        "\u0936\u0939\u0926\u094b\u0932"
    ],
    "name:nld_x_preferred":[
        "Shahdol"
    ],
    "name:ori_x_preferred":[
        "\u0b36\u0b3e\u0b39\u0b21\u0b3c\u0b4b\u0b32"
    ],
    "name:por_x_preferred":[
        "Shahdol"
    ],
    "name:rus_x_preferred":[
        "\u0428\u0430\u0445\u0434\u043e\u043b"
    ],
    "name:san_x_preferred":[
        "\u0936\u0939\u0921\u094b\u0932"
    ],
    "name:spa_x_preferred":[
        "Shahdol"
    ],
    "name:swe_x_preferred":[
        "Shahdol"
    ],
    "name:tam_x_preferred":[
        "\u0bb7\u0b9f\u0bcb\u0bb2\u0bcd"
    ],
    "name:tam_x_variant":[
        "\u0b9a\u0bbe\u0ba4\u0bcb\u0bb2\u0bcd"
    ],
    "name:tel_x_preferred":[
        "\u0c37\u0c39\u0c26\u0c4b\u0c32\u0c4d"
    ],
    "name:unk_x_variant":[
        "Sahdol"
    ],
    "name:urd_x_preferred":[
        "\u0634\u0627\u062d\u062f\u0648\u0644"
    ],
    "name:vie_x_preferred":[
        "Shahdol"
    ],
    "name:zho_x_preferred":[
        "\u65af\u54c8\u8d6b\u591a\u5c14"
    ],
    "qs:name":"Shahdol",
    "qs:name_adm0":"India",
    "qs:name_adm1":"Madhya Pradesh",
    "qs:photos_9k":1,
    "qs:photos_9r":1,
    "qs:photos_all":3,
    "qs:photos_sr":0,
    "qs:placetype":"Town",
    "qs:pop_sr":"8",
    "wd:wordcount":918,
    "wof:name":"Shahdol",
    "wof:placetype":"locality",
    "wof:population":89289
},
  "geometry": {"coordinates":[81.36190000000001,23.29356],"type":"Point"}
}