{
  "type": "Feature",
  "properties": {
    "iso:country":"IN",
    "ks:ks_name":"Gundunia Bhalupani",
    "ks:ks_pop":245,
    "ks:ks_type":"HABITATION",
    "name:eng_x_preferred":[
        "Gundunia Bhalupani"
    ],
    "wof:name":"Gundunia Bhalupani",
    "wof:placetype":"locality",
    "wof:population":245
},
  "geometry": {"coordinates":[85.66672,21.940584],"type":"Point"}
}