{
  "type": "Feature",
  "properties": {
    "gn:admin1_code":"34.0",
    "gn:admin2_code":"231.0",
    "gn:asciiname":"Barar",
    "gn:country_code":"IN",
    "gn:dem":81,
    "gn:feature_class":"P",
    "gn:feature_code":"PPL",
    "gn:name":"Bar\u0101r",
    "gn:population":0,
    "gn:timezone":"Asia/Kolkata",
    "iso:country":"IN",
    "name:ara_x_preferred":[
        "\u0628\u0631\u0627\u0631"
    ],
    "name:fas_x_preferred":[
        "\u0628\u0631\u0627\u0631"
    ],
    "wof:name":"Barar",
    "wof:placetype":"locality"
},
  "geometry": {"coordinates":[84.47198,25.33686],"type":"Point"}
}