{
  "type": "Feature",
  "properties": {
    "gn:admin1_code":"36.0",
    "gn:admin2_code":"183.0",
    "gn:asciiname":"Kharkua",
    "gn:country_code":"IN",
    "gn:dem":105,
    "gn:feature_class":"P",
    "gn:feature_code":"PPL",
    "gn:name":"Kharkua",
    "gn:population":0,
    "gn:timezone":"Asia/Kolkata",
    "iso:country":"IN",
    "wof:name":"Kharkua",
    "wof:placetype":"locality"
},
  "geometry": {"coordinates":[81.71283000000003,27.00277],"type":"Point"}
}