{
  "type": "Feature",
  "properties": {
    "gn:admin1_code":"34.0",
    "gn:admin2_code":"229.0",
    "gn:asciiname":"Tetaria",
    "gn:country_code":"IN",
    "gn:dem":71,
    "gn:feature_class":"P",
    "gn:feature_code":"PPL",
    "gn:name":"Tetaria",
    "gn:population":0,
    "gn:timezone":"Asia/Kolkata",
    "iso:country":"IN",
    "ks:ks_name":"Tetaria",
    "ks:ks_pop":761,
    "ks:ks_type":"VILLAGE",
    "ks:ks_uagg_main":0,
    "name:eng_x_preferred":[
        "Tetaria"
    ],
    "wof:name":"Tetaria",
    "wof:placetype":"neighbourhood",
    "wof:population":761
},
  "geometry": {"coordinates":[85.238568,25.146621],"type":"Point"}
}