{
  "type": "Feature",
  "properties": {
    "gn:admin1_code":"24.0",
    "gn:admin2_code":"114.0",
    "gn:asciiname":"Faqiran Ka Tibba",
    "gn:country_code":"IN",
    "gn:dem":158,
    "gn:feature_class":"P",
    "gn:feature_code":"PPL",
    "gn:name":"Faq\u0131r\u0101n Ka Tibba",
    "gn:population":0,
    "gn:timezone":"Asia/Kolkata",
    "iso:country":"IN",
    "wof:name":"Faqiran Ka Tibba",
    "wof:placetype":"locality"
},
  "geometry": {"coordinates":[71.22795000000001,27.34307],"type":"Point"}
}