{
  "type": "Feature",
  "properties": {
    "gn:admin1_code":"9.0",
    "gn:admin2_code":"469.0",
    "gn:asciiname":"Moria",
    "gn:country_code":"IN",
    "gn:dem":228,
    "gn:feature_class":"P",
    "gn:feature_code":"PPL",
    "gn:name":"Moria",
    "gn:population":0,
    "gn:timezone":"Asia/Kolkata",
    "iso:country":"IN",
    "name:ceb_x_preferred":[
        "Moria"
    ],
    "name:ces_x_preferred":[
        "Moria"
    ],
    "name:deu_x_preferred":[
        "Moria"
    ],
    "name:fra_x_preferred":[
        "Moria"
    ],
    "name:ita_x_preferred":[
        "Moria"
    ],
    "name:jpn_x_preferred":[
        "\u30e2\u30ea\u30a2"
    ],
    "name:kor_x_preferred":[
        "\ubaa8\ub9ac\uc544"
    ],
    "name:nld_x_preferred":[
        "Moria"
    ],
    "name:pol_x_preferred":[
        "Moria"
    ],
    "name:rus_x_preferred":[
        "\u041c\u043e\u0440\u0438\u044f"
    ],
    "name:slk_x_preferred":[
        "Moria"
    ],
    "name:spa_x_preferred":[
        "Moria"
    ],
    "name:swe_x_preferred":[
        "Moria"
    ],
    "name:ukr_x_preferred":[
        "\u041c\u043e\u0440\u0456\u044f"
    ],
    "wof:name":"Moria",
    "wof:placetype":"locality"
},
  "geometry": {"coordinates":[72.66939000000001,24.10635],"type":"Point"}
}