{
  "type": "Feature",
  "properties": {
    "iso:country":"IN",
    "ks:ks_alt_nam":"MIRAJEWASTI",
    "ks:ks_name":"Mirajewasti",
    "ks:ks_pop":141,
    "ks:ks_type":"HABITATION",
    "name:eng_x_preferred":[
        "Mirajewasti"
    ],
    "wof:name":"Mirajewasti",
    "wof:placetype":"locality",
    "wof:population":141
},
  "geometry": {"coordinates":[74.836074,16.949903],"type":"Point"}
}