{
  "type": "Feature",
  "properties": {
    "iso:country":"IN",
    "ks:ks_name":"Tanda Masood Pur",
    "ks:ks_pop":1,
    "ks:ks_type":"VILLAGE",
    "name:eng_x_preferred":[
        "Tanda Masood Pur"
    ],
    "wof:name":"Tanda Masood Pur",
    "wof:placetype":"locality",
    "wof:population":1
},
  "geometry": {"coordinates":[81.26246399999999,27.061168],"type":"Point"}
}