{
  "type": "Feature",
  "properties": {
    "gn:admin1_code":"21.0",
    "gn:admin2_code":"388.0",
    "gn:asciiname":"Tulasipadar",
    "gn:country_code":"IN",
    "gn:dem":46,
    "gn:feature_class":"P",
    "gn:feature_code":"PPL",
    "gn:name":"Tulasipadar",
    "gn:population":0,
    "gn:timezone":"Asia/Kolkata",
    "iso:country":"IN",
    "wof:name":"Tulasipadar",
    "wof:placetype":"locality"
},
  "geometry": {"coordinates":[84.62305000000001,19.42239],"type":"Point"}
}