{
  "type": "Feature",
  "properties": {
    "iso:country":"IN",
    "ks:ks_name":"Atwa Durg",
    "ks:ks_pop":1520,
    "ks:ks_type":"VILLAGE",
    "ks:ks_uagg_main":0,
    "name:eng_x_preferred":[
        "Atwa Durg"
    ],
    "wof:name":"Atwa Durg",
    "wof:placetype":"neighbourhood",
    "wof:population":1520
},
  "geometry": {"coordinates":[84.252668,26.333051],"type":"Point"}
}