{
  "type": "Feature",
  "properties": {
    "iso:country":"IN",
    "ks:ks_alt_nam":"19 No. line supa",
    "ks:ks_name":"19 No. Line Supa",
    "ks:ks_pop":101,
    "ks:ks_type":"HABITATION",
    "ks:ks_uagg_main":0,
    "name:eng_x_preferred":[
        "19 No. Line Supa"
    ],
    "wof:name":"19 No. Line Supa",
    "wof:placetype":"neighbourhood",
    "wof:population":101
},
  "geometry": {"coordinates":[91.661131,26.719964],"type":"Point"}
}