{
  "type": "Feature",
  "properties": {
    "iso:country":"IN",
    "ks:ks_alt_nam":"dipasai",
    "ks:ks_name":"Dipasai",
    "ks:ks_pop":529,
    "ks:ks_type":"HABITATION",
    "name:eng_x_preferred":[
        "Dipasai"
    ],
    "wof:name":"Dipasai",
    "wof:placetype":"locality",
    "wof:population":529
},
  "geometry": {"coordinates":[85.46754300000001,22.622677],"type":"Point"}
}