{
  "type": "Feature",
  "properties": {
    "gn:admin1_code":"38.0",
    "gn:admin2_code":"348.0",
    "gn:asciiname":"Dumardiha",
    "gn:country_code":"IN",
    "gn:dem":379,
    "gn:feature_class":"P",
    "gn:feature_code":"PPL",
    "gn:name":"Dumardiha",
    "gn:population":0,
    "gn:timezone":"Asia/Kolkata",
    "iso:country":"IN",
    "ks:ks_name":"Dumardiha",
    "ks:ks_pop":321,
    "ks:ks_type":"VILLAGE",
    "ks:ks_uagg_main":0,
    "name:eng_x_preferred":[
        "Dumardiha"
    ],
    "wof:name":"Dumardiha",
    "wof:placetype":"neighbourhood",
    "wof:population":321
},
  "geometry": {"coordinates":[85.543189,24.382146],"type":"Point"}
}