{
  "type": "Feature",
  "properties": {
    "iso:country":"IN",
    "ks:ks_name":"Ravindranagar Colony",
    "ks:ks_pop":90,
    "ks:ks_type":"HABITATION",
    "name:eng_x_preferred":[
        "Ravindranagar Colony"
    ],
    "wof:name":"Ravindranagar Colony",
    "wof:placetype":"locality",
    "wof:population":90
},
  "geometry": {"coordinates":[78.880691,13.980098],"type":"Point"}
}