{
  "type": "Feature",
  "properties": {
    "iso:country":"IN",
    "ks:ks_name":"Madhaili Dahiyara",
    "ks:ks_pop":1098,
    "ks:ks_type":"HABITATION",
    "name:eng_x_preferred":[
        "Madhaili Dahiyara"
    ],
    "wof:name":"Madhaili Dahiyara",
    "wof:placetype":"locality",
    "wof:population":1098
},
  "geometry": {"coordinates":[86.932294,25.614727],"type":"Point"}
}