{
  "type": "Feature",
  "properties": {
    "iso:country":"IN",
    "ks:ks_name":"Wadadoga",
    "ks:ks_pop":170,
    "ks:ks_type":"HABITATION",
    "name:eng_x_preferred":[
        "Wadadoga"
    ],
    "wof:name":"Wadadoga",
    "wof:placetype":"locality",
    "wof:population":170
},
  "geometry": {"coordinates":[74.34277400000001,21.875875],"type":"Point"}
}