{
  "type": "Feature",
  "properties": {
    "iso:country":"IN",
    "ks:ks_name":"Goudaguda",
    "ks:ks_pop":22,
    "ks:ks_type":"VILLAGE",
    "name:eng_x_preferred":[
        "Goudaguda"
    ],
    "wof:name":"Goudaguda",
    "wof:placetype":"locality",
    "wof:population":22
},
  "geometry": {"coordinates":[83.49379500000001,19.341221],"type":"Point"}
}