{
  "type": "Feature",
  "properties": {
    "gn:admin1_code":"2.0",
    "gn:admin2_code":"552.0",
    "gn:asciiname":"Alluru",
    "gn:country_code":"IN",
    "gn:dem":289,
    "gn:feature_class":"P",
    "gn:feature_code":"PPL",
    "gn:name":"All\u016bru",
    "gn:population":0,
    "gn:timezone":"Asia/Kolkata",
    "iso:country":"IN",
    "wof:name":"Alluru",
    "wof:placetype":"locality"
},
  "geometry": {"coordinates":[78.21173,15.86653],"type":"Point"}
}