{
  "type": "Feature",
  "properties": {
    "iso:country":"IN",
    "ks:ks_name":"Chamaranpurwa",
    "ks:ks_pop":424,
    "ks:ks_type":"HABITATION",
    "name:eng_x_preferred":[
        "Chamaranpurwa"
    ],
    "wof:name":"Chamaranpurwa",
    "wof:placetype":"locality",
    "wof:population":424
},
  "geometry": {"coordinates":[81.367878,27.845227],"type":"Point"}
}