{
  "type": "Feature",
  "properties": {
    "iso:country":"IN",
    "ks:ks_name":"Amarkutir",
    "ks:ks_pop":502,
    "ks:ks_type":"HABITATION",
    "name:eng_x_preferred":[
        "Amarkutir"
    ],
    "wof:name":"Amarkutir",
    "wof:placetype":"locality",
    "wof:population":502
},
  "geometry": {"coordinates":[87.647586,23.686148],"type":"Point"}
}