{
  "type": "Feature",
  "properties": {
    "gn:admin1_code":"11",
    "gn:admin2_code":"24.0",
    "gn:asciiname":"Jugehr",
    "gn:country_code":"IN",
    "gn:dem":756,
    "gn:feature_class":"P",
    "gn:feature_code":"PPL",
    "gn:name":"Jugehr",
    "gn:population":0,
    "gn:timezone":"Asia/Kolkata",
    "iso:country":"IN",
    "wof:name":"Jugehr",
    "wof:placetype":"locality"
},
  "geometry": {"coordinates":[76.2646,32.16271],"type":"Point"}
}