{
  "type": "Feature",
  "properties": {
    "gn:admin1_code":"36.0",
    "gn:admin2_code":"171.0",
    "gn:asciiname":"Taura",
    "gn:country_code":"IN",
    "gn:dem":116,
    "gn:feature_class":"P",
    "gn:feature_code":"PPL",
    "gn:name":"Taura",
    "gn:population":0,
    "gn:timezone":"Asia/Kolkata",
    "iso:country":"IN",
    "ks:ks_name":"Taura",
    "ks:ks_pop":1067,
    "ks:ks_type":"VILLAGE",
    "ks:ks_uagg_main":0,
    "name:bak_x_preferred":[
        "\u0422\u0430\u0443\u0440\u0430"
    ],
    "name:ceb_x_preferred":[
        "Taura"
    ],
    "name:deu_x_preferred":[
        "Taura"
    ],
    "name:eng_x_preferred":[
        "Taura"
    ],
    "name:epo_x_preferred":[
        "Taura"
    ],
    "name:est_x_preferred":[
        "Taura vald"
    ],
    "name:eus_x_preferred":[
        "Taura"
    ],
    "name:fra_x_preferred":[
        "Taura"
    ],
    "name:hun_x_preferred":[
        "Taura"
    ],
    "name:ita_x_preferred":[
        "Taura"
    ],
    "name:mkd_x_preferred":[
        "\u0422\u0430\u0443\u0440\u0430"
    ],
    "name:msa_x_preferred":[
        "Taura"
    ],
    "name:nld_x_preferred":[
        "Taura"
    ],
    "name:pol_x_preferred":[
        "Taura"
    ],
    "name:ron_x_preferred":[
        "Taura"
    ],
    "name:rus_x_preferred":[
        "\u0422\u0430\u0443\u0440\u0430"
    ],
    "name:spa_x_preferred":[
        "Taura"
    ],
    "name:srp_x_preferred":[
        "\u0422\u0430\u0443\u0440\u0430"
    ],
    "name:ukr_x_preferred":[
        "\u0422\u0430\u0443\u0440\u0430"
    ],
    "name:uzb_x_preferred":[
        "Taura"
    ],
    "name:vie_x_preferred":[
        "Taura"
    ],
    "name:vol_x_preferred":[
        "Taura"
    ],
    "name:war_x_preferred":[
        "Taura"
    ],
    "wof:name":"Taura",
    "wof:placetype":"neighbourhood",
    "wof:population":1067
},
  "geometry": {"coordinates":[81.024503,25.309235],"type":"Point"}
}