{
  "type": "Feature",
  "properties": {
    "gn:admin1_code":"19.0",
    "gn:admin2_code":"567.0",
    "gn:asciiname":"Sagar Petta",
    "gn:country_code":"IN",
    "gn:dem":619,
    "gn:feature_class":"P",
    "gn:feature_code":"PPL",
    "gn:name":"S\u0101gar Petta",
    "gn:population":0,
    "gn:timezone":"Asia/Kolkata",
    "iso:country":"IN",
    "wof:name":"Sagar Petta",
    "wof:placetype":"locality"
},
  "geometry": {"coordinates":[75.8163,14.20723],"type":"Point"}
}