{
  "type": "Feature",
  "properties": {
    "iso:country":"IN",
    "ks:ks_name":"Dongripara",
    "ks:ks_pop":278,
    "ks:ks_type":"HABITATION",
    "name:eng_x_preferred":[
        "Dongripara"
    ],
    "wof:name":"Dongripara",
    "wof:placetype":"locality",
    "wof:population":278
},
  "geometry": {"coordinates":[81.79301599999999,19.760906],"type":"Point"}
}