{
  "type": "Feature",
  "properties": {
    "iso:country":"IN",
    "ks:ks_name":"Thadgam",
    "ks:ks_pop":2004,
    "ks:ks_type":"VILLAGE",
    "name:eng_x_preferred":[
        "Thadgam"
    ],
    "wof:name":"Thadgam",
    "wof:placetype":"locality",
    "wof:population":2004
},
  "geometry": {"coordinates":[73.978708,22.089496],"type":"Point"}
}