{
  "type": "Feature",
  "properties": {
    "gn:admin1_code":"35",
    "gn:admin2_code":"419.0",
    "gn:asciiname":"Kotra",
    "gn:country_code":"IN",
    "gn:dem":189,
    "gn:feature_class":"P",
    "gn:feature_code":"PPL",
    "gn:name":"Kotra",
    "gn:population":0,
    "gn:timezone":"Asia/Kolkata",
    "iso:country":"IN",
    "name:ara_x_preferred":[
        "\u0643\u0648\u062a\u0631\u0627"
    ],
    "name:ben_bn_x_preferred":[
        "\u0995\u09cb\u099f\u09b0\u09be"
    ],
    "name:ben_in_x_preferred":[
        "\u0995\u09cb\u099f\u09b0\u09be"
    ],
    "name:guj_x_preferred":[
        "\u0a95\u0acb\u0a9f\u0ab0\u0abe"
    ],
    "name:hin_x_preferred":[
        "\u0915\u094b\u091f\u0930\u093e"
    ],
    "name:kan_x_preferred":[
        "\u0c95\u0ccb\u0ca4\u0ccd\u0cb0\u0cbe"
    ],
    "name:mal_x_preferred":[
        "\u0d15\u0d4b\u0d24\u0d4d\u0d30"
    ],
    "name:mar_x_preferred":[
        "\u0915\u094b\u091f\u094d\u0930\u093e"
    ],
    "name:pan_x_preferred":[
        "\u0a15\u0a4b\u0a1f\u0a30\u0a3e"
    ],
    "name:tam_x_preferred":[
        "\u0b95\u0bcb\u0b9f\u0bcd\u0bb0\u0bbe"
    ],
    "name:tel_x_preferred":[
        "\u0c15\u0c4a\u0c1f\u0c4d\u0c30\u0c3e"
    ],
    "name:urd_x_preferred":[
        "\u06a9\u0648\u0679\u0631\u0627"
    ],
    "wof:name":"Kotra",
    "wof:placetype":"locality"
},
  "geometry": {"coordinates":[77.62642,26.42566],"type":"Point"}
}