{
  "type": "Feature",
  "properties": {
    "iso:country":"IN",
    "ks:ks_name":"Palonam",
    "ks:ks_pop":345,
    "ks:ks_type":"HABITATION",
    "ks:ks_uagg_main":0,
    "name:eng_x_preferred":[
        "Palonam"
    ],
    "wof:name":"Palonam",
    "wof:placetype":"neighbourhood",
    "wof:population":345
},
  "geometry": {"coordinates":[76.895064,8.876998],"type":"Point"}
}