{
  "type": "Feature",
  "properties": {
    "iso:country":"IN",
    "ks:ks_alt_nam":"hariharpur",
    "ks:ks_name":"Hariharpur",
    "ks:ks_pop":127,
    "ks:ks_type":"HABITATION",
    "name:eng_x_preferred":[
        "Hariharpur"
    ],
    "wof:name":"Hariharpur",
    "wof:placetype":"locality",
    "wof:population":127
},
  "geometry": {"coordinates":[82.696673,25.397217],"type":"Point"}
}