{
  "type": "Feature",
  "properties": {
    "iso:country":"IN",
    "ks:ks_alt_nam":"HIMOTON KI BHAN",
    "ks:ks_name":"Himoton Ki Bhan",
    "ks:ks_pop":89,
    "ks:ks_type":"HABITATION",
    "name:eng_x_preferred":[
        "Himoton Ki Bhan"
    ],
    "wof:name":"Himoton Ki Bhan",
    "wof:placetype":"locality",
    "wof:population":89
},
  "geometry": {"coordinates":[74.684844,23.811474],"type":"Point"}
}