{
  "type": "Feature",
  "properties": {
    "gn:admin1_code":"19.0",
    "gn:admin2_code":"572.0",
    "gn:asciiname":"Lakshmipur",
    "gn:country_code":"IN",
    "gn:dem":888,
    "gn:feature_class":"P",
    "gn:feature_code":"PPL",
    "gn:name":"Lakshmipur",
    "gn:population":0,
    "gn:timezone":"Asia/Kolkata",
    "iso:country":"IN",
    "name:ceb_x_preferred":[
        "Lakshmipur"
    ],
    "name:fra_x_preferred":[
        "Lakshmipur"
    ],
    "name:swe_x_preferred":[
        "Lakshmipur"
    ],
    "wof:name":"Lakshmipur",
    "wof:placetype":"neighbourhood"
},
  "geometry": {"coordinates":[77.52867000000001,13.08592],"type":"Point"}
}