{
  "type": "Feature",
  "properties": {
    "iso:country":"IN",
    "ks:ks_alt_nam":"doddakumeri",
    "ks:ks_name":"Doddakumeri",
    "ks:ks_pop":253,
    "ks:ks_type":"HABITATION",
    "name:eng_x_preferred":[
        "Doddakumeri"
    ],
    "wof:name":"Doddakumeri",
    "wof:placetype":"locality",
    "wof:population":253
},
  "geometry": {"coordinates":[75.47475,12.468454],"type":"Point"}
}