{
  "type": "Feature",
  "properties": {
    "iso:country":"IN",
    "ks:ks_name":"Panathila",
    "ks:ks_pop":394,
    "ks:ks_type":"HABITATION",
    "name:eng_x_preferred":[
        "Panathila"
    ],
    "wof:name":"Panathila",
    "wof:placetype":"locality",
    "wof:population":394
},
  "geometry": {"coordinates":[75.42494000000001,12.569525],"type":"Point"}
}