{
  "type": "Feature",
  "properties": {
    "gn:admin1_code":"12.0",
    "gn:admin2_code":"16.0",
    "gn:asciiname":"Kundi",
    "gn:country_code":"IN",
    "gn:dem":1716,
    "gn:feature_class":"P",
    "gn:feature_code":"PPL",
    "gn:name":"Kund\u012b",
    "gn:population":0,
    "gn:timezone":"Asia/Kolkata",
    "iso:country":"IN",
    "name:ceb_x_preferred":[
        "Kundi"
    ],
    "name:swe_x_preferred":[
        "Kundi"
    ],
    "wof:name":"Kundi",
    "wof:placetype":"locality"
},
  "geometry": {"coordinates":[75.72668,33.08472],"type":"Point"}
}