{
  "type": "Feature",
  "properties": {
    "gn:admin1_code":"36",
    "gn:admin2_code":"173.0",
    "gn:asciiname":"Patihtia Khurd",
    "gn:country_code":"IN",
    "gn:dem":93,
    "gn:feature_class":"P",
    "gn:feature_code":"PPL",
    "gn:name":"Patihtia Khurd",
    "gn:population":0,
    "gn:timezone":"Asia/Kolkata",
    "iso:country":"IN",
    "ks:ks_name":"Patihtia Khurd",
    "ks:ks_pop":972,
    "ks:ks_type":"VILLAGE",
    "name:eng_x_preferred":[
        "Patihtia Khurd"
    ],
    "wof:name":"Patihtia Khurd",
    "wof:placetype":"locality",
    "wof:population":972
},
  "geometry": {"coordinates":[82.139218,25.741095],"type":"Point"}
}