{
  "type": "Feature",
  "properties": {
    "iso:country":"IN",
    "ks:ks_alt_nam":"Ch\u0101ngo Singha",
    "ks:ks_name":"Chango Singha",
    "ks:ks_type":"VILLAGE",
    "ks:ks_uagg_main":0,
    "name:eng_x_preferred":[
        "Chango Singha"
    ],
    "name:eng_x_variant":[
        "Ch\u0101ngo Singha"
    ],
    "wof:name":"Chango Singha",
    "wof:placetype":"neighbourhood"
},
  "geometry": {"coordinates":[85.868049,24.404454],"type":"Point"}
}