{
  "type": "Feature",
  "properties": {
    "gn:admin1_code":"3.0",
    "gn:admin2_code":"317.0",
    "gn:asciiname":"Nayagram",
    "gn:country_code":"IN",
    "gn:dem":20,
    "gn:feature_class":"P",
    "gn:feature_code":"PPL",
    "gn:name":"Nayagram",
    "gn:population":0,
    "gn:timezone":"Asia/Kolkata",
    "iso:country":"IN",
    "ks:ks_name":"Nayagram",
    "ks:ks_pop":878,
    "ks:ks_type":"HABITATION",
    "name:ben_x_preferred":[
        "\u09a8\u09af\u09bc\u09be\u0997\u09cd\u09b0\u09be\u09ae"
    ],
    "name:eng_x_preferred":[
        "Nayagram"
    ],
    "wof:name":"Nayagram",
    "wof:placetype":"locality",
    "wof:population":878
},
  "geometry": {"coordinates":[92.421217,24.568813],"type":"Point"}
}