{
  "type": "Feature",
  "properties": {
    "gn:admin1_code":"3.0",
    "gn:admin2_code":"317.0",
    "gn:asciiname":"Nayagram",
    "gn:country_code":"IN",
    "gn:dem":20,
    "gn:feature_class":"P",
    "gn:feature_code":"PPL",
    "gn:name":"Nayagram",
    "gn:population":0,
    "gn:timezone":"Asia/Kolkata",
    "iso:country":"IN",
    "name:ben_x_preferred":[
        "\u09a8\u09af\u09bc\u09be\u0997\u09cd\u09b0\u09be\u09ae"
    ],
    "wof:name":"Nayagram",
    "wof:placetype":"locality"
},
  "geometry": {"coordinates":[92.42211,24.56874],"type":"Point"}
}