{
  "type": "Feature",
  "properties": {
    "gn:admin1_code":"36.0",
    "gn:admin2_code":"188.0",
    "gn:asciiname":"Bagaha",
    "gn:country_code":"IN",
    "gn:dem":72,
    "gn:feature_class":"P",
    "gn:feature_code":"PPL",
    "gn:name":"Bagaha",
    "gn:population":0,
    "gn:timezone":"Asia/Kolkata",
    "iso:country":"IN",
    "ks:ks_name":"Bagaha",
    "ks:ks_pop":763,
    "ks:ks_type":"HABITATION",
    "name:ben_x_preferred":[
        "\u09ad\u09be\u0999\u09cd\u0997\u09be"
    ],
    "name:bih_x_preferred":[
        "\u092c\u0917\u0939\u093e"
    ],
    "name:bpy_x_preferred":[
        "\u09ad\u09be\u0999\u09cd\u0997\u09be"
    ],
    "name:ceb_x_preferred":[
        "Bagaha"
    ],
    "name:eng_x_preferred":[
        "Bagaha"
    ],
    "name:fas_x_preferred":[
        "\u0628\u0627\u06af\u0627\u0647\u0627"
    ],
    "name:hin_x_preferred":[
        "\u092c\u0917\u0939\u093e"
    ],
    "name:ita_x_preferred":[
        "Bagaha"
    ],
    "name:msa_x_preferred":[
        "Bagaha"
    ],
    "name:nep_x_preferred":[
        "\u092c\u0917\u0939\u093e"
    ],
    "name:new_x_preferred":[
        "\u092c\u0917\u0939\u093e"
    ],
    "name:ori_x_preferred":[
        "\u0b2c\u0b3e\u0b17\u0b3e\u0b39\u0b3e"
    ],
    "name:por_x_preferred":[
        "Bagaha"
    ],
    "name:rus_x_preferred":[
        "\u0411\u0430\u0433\u0430\u0445\u0430"
    ],
    "name:spa_x_preferred":[
        "Bagaha"
    ],
    "name:swe_x_preferred":[
        "Bagaha"
    ],
    "name:urd_x_preferred":[
        "\u0628\u0627\u06af\u0627\u06c1\u0627"
    ],
    "name:vie_x_preferred":[
        "Bagaha"
    ],
    "name:zho_x_preferred":[
        "\u5df4\u52a0\u54c8"
    ],
    "wof:name":"Bagaha",
    "wof:placetype":"locality",
    "wof:population":763
},
  "geometry": {"coordinates":[83.638576,26.28692],"type":"Point"}
}