{
  "type": "Feature",
  "properties": {
    "gn:admin1_code":"35.0",
    "gn:admin2_code":"455.0",
    "gn:asciiname":"Gulsi",
    "gn:country_code":"IN",
    "gn:dem":468,
    "gn:feature_class":"P",
    "gn:feature_code":"PPL",
    "gn:name":"Gulsi",
    "gn:population":0,
    "gn:timezone":"Asia/Kolkata",
    "iso:country":"IN",
    "ks:ks_name":"Gulsi",
    "ks:ks_pop":940,
    "ks:ks_type":"VILLAGE",
    "name:eng_x_preferred":[
        "Gulsi"
    ],
    "wof:name":"Gulsi",
    "wof:placetype":"locality",
    "wof:population":940
},
  "geometry": {"coordinates":[78.961422,21.781329],"type":"Point"}
}