{
  "type": "Feature",
  "properties": {
    "iso:country":"IN",
    "ks:ks_alt_nam":"PATHERGARH",
    "ks:ks_name":"Pathergarh",
    "ks:ks_pop":253,
    "ks:ks_type":"HABITATION",
    "name:eng_x_preferred":[
        "Pathergarh"
    ],
    "wof:name":"Pathergarh",
    "wof:placetype":"locality",
    "wof:population":253
},
  "geometry": {"coordinates":[84.07223,24.68746],"type":"Point"}
}