{
  "type": "Feature",
  "properties": {
    "iso:country":"IN",
    "ks:ks_name":"Bhojpor",
    "ks:ks_pop":651,
    "ks:ks_type":"VILLAGE",
    "name:eng_x_preferred":[
        "Bhojpor"
    ],
    "wof:name":"Bhojpor",
    "wof:placetype":"locality",
    "wof:population":651
},
  "geometry": {"coordinates":[73.232523,21.643967],"type":"Point"}
}