{
  "type": "Feature",
  "properties": {
    "iso:country":"IN",
    "ks:ks_name":"Tamasi Rt.",
    "ks:ks_pop":0,
    "ks:ks_type":"VILLAGE",
    "name:eng_x_preferred":[
        "Tamasi Rt."
    ],
    "wof:name":"Tamasi Rt.",
    "wof:placetype":"locality",
    "wof:population":0
},
  "geometry": {"coordinates":[79.263268,20.278036],"type":"Point"}
}