{
  "type": "Feature",
  "properties": {
    "iso:country":"IN",
    "ks:ks_name":"Burusingi",
    "ks:ks_pop":83,
    "ks:ks_type":"VILLAGE",
    "name:eng_x_preferred":[
        "Burusingi"
    ],
    "wof:name":"Burusingi",
    "wof:placetype":"locality",
    "wof:population":83
},
  "geometry": {"coordinates":[84.256968,18.994167],"type":"Point"}
}