{
  "type": "Feature",
  "properties": {
    "gn:admin1_code":"7.0",
    "gn:admin2_code":"097",
    "gn:asciiname":"Dichaon Kalan",
    "gn:country_code":"IN",
    "gn:dem":221,
    "gn:feature_class":"P",
    "gn:feature_code":"PPL",
    "gn:name":"Dich\u0101on Kal\u0101n",
    "gn:population":0,
    "gn:timezone":"Asia/Kolkata",
    "iso:country":"IN",
    "name:und_x_variant":[
        "Dich\u0101on Kal\u0101n"
    ],
    "wof:name":"Dichaon Kalan",
    "wof:placetype":"locality"
},
  "geometry": {"coordinates":[76.98260999999999,28.63983],"type":"Point"}
}