{
  "type": "Feature",
  "properties": {
    "gn:admin1_code":"35",
    "gn:admin2_code":"453.0",
    "gn:asciiname":"Dewalpur",
    "gn:country_code":"IN",
    "gn:dem":744,
    "gn:feature_class":"P",
    "gn:feature_code":"PPL",
    "gn:name":"Dewalpur",
    "gn:population":0,
    "gn:timezone":"Asia/Kolkata",
    "iso:country":"IN",
    "wof:name":"Dewalpur",
    "wof:placetype":"locality"
},
  "geometry": {"coordinates":[81.09007,22.77011],"type":"Point"}
}