{
  "type": "Feature",
  "properties": {
    "iso:country":"IN",
    "ks:ks_name":"Daulpur",
    "ks:ks_pop":832,
    "ks:ks_type":"HABITATION",
    "ks:ks_uagg_main":0,
    "name:eng_x_preferred":[
        "Daulpur"
    ],
    "wof:name":"Daulpur",
    "wof:placetype":"neighbourhood",
    "wof:population":832
},
  "geometry": {"coordinates":[78.868453,27.466599],"type":"Point"}
}