{
  "type": "Feature",
  "properties": {
    "gn:admin1_code":"34.0",
    "gn:admin2_code":"231.0",
    "gn:asciiname":"Narayanpur",
    "gn:country_code":"IN",
    "gn:dem":67,
    "gn:feature_class":"P",
    "gn:feature_code":"PPL",
    "gn:name":"N\u0101r\u0101yanpur",
    "gn:population":0,
    "gn:timezone":"Asia/Kolkata",
    "iso:country":"IN",
    "name:ceb_x_preferred":[
        "Narayanpur"
    ],
    "name:fra_x_preferred":[
        "Narayanpur"
    ],
    "name:pol_x_preferred":[
        "Narayanpur"
    ],
    "name:swe_x_preferred":[
        "Narayanpur"
    ],
    "name:tel_x_preferred":[
        "\u0c28\u0c3e\u0c30\u0c3e\u0c2f\u0c23\u0c4d\u200c\u0c2a\u0c42\u0c30\u0c4d"
    ],
    "wof:name":"Narayanpur",
    "wof:placetype":"locality"
},
  "geometry": {"coordinates":[84.7514,25.46073],"type":"Point"}
}