{
  "type": "Feature",
  "properties": {
    "gn:admin1_code":"12.0",
    "gn:asciiname":"Muri",
    "gn:country_code":"IN",
    "gn:dem":2043,
    "gn:feature_class":"P",
    "gn:feature_code":"PPL",
    "gn:name":"Muri",
    "gn:population":0,
    "gn:timezone":"Asia/Kolkata",
    "iso:country":"IN",
    "name:als_x_preferred":[
        "Muri"
    ],
    "name:ceb_x_preferred":[
        "Muri"
    ],
    "name:ces_x_preferred":[
        "Muri"
    ],
    "name:deu_x_preferred":[
        "Muri"
    ],
    "name:epo_x_preferred":[
        "Muri"
    ],
    "name:est_x_preferred":[
        "Muri"
    ],
    "name:eus_x_preferred":[
        "Muri"
    ],
    "name:fra_x_preferred":[
        "Muri"
    ],
    "name:ita_x_preferred":[
        "Muri"
    ],
    "name:lat_x_preferred":[
        "Muri"
    ],
    "name:nld_x_preferred":[
        "Muri"
    ],
    "name:swe_x_preferred":[
        "Muri"
    ],
    "name:und_x_variant":[
        "Muhri"
    ],
    "name:vol_x_preferred":[
        "Muri"
    ],
    "wof:name":"Muri",
    "wof:placetype":"locality"
},
  "geometry": {"coordinates":[73.92969000000002,34.06943],"type":"Point"}
}