{
  "type": "Feature",
  "properties": {
    "gn:admin1_code":"19.0",
    "gn:admin2_code":"574.0",
    "gn:asciiname":"Kasturavalli",
    "gn:country_code":"IN",
    "gn:dem":939,
    "gn:feature_class":"P",
    "gn:feature_code":"PPL",
    "gn:name":"Kast\u016bravalli",
    "gn:population":0,
    "gn:timezone":"Asia/Kolkata",
    "iso:country":"IN",
    "wof:name":"Kasturavalli",
    "wof:placetype":"locality"
},
  "geometry": {"coordinates":[76.14455,12.99777],"type":"Point"}
}