{
  "type": "Feature",
  "properties": {
    "gn:admin1_code":"36.0",
    "gn:admin2_code":"135.0",
    "gn:asciiname":"Kadirpur",
    "gn:country_code":"IN",
    "gn:dem":194,
    "gn:feature_class":"P",
    "gn:feature_code":"PPL",
    "gn:name":"K\u0101dirpur",
    "gn:population":0,
    "gn:timezone":"Asia/Kolkata",
    "iso:country":"IN",
    "ks:ks_name":"Kadarpur",
    "ks:ks_pop":1002,
    "ks:ks_type":"VILLAGE",
    "ks:ks_uagg_main":0,
    "name:eng_x_preferred":[
        "Kadarpur"
    ],
    "wof:name":"Kadarpur",
    "wof:placetype":"neighbourhood",
    "wof:population":1002
},
  "geometry": {"coordinates":[78.65415400000001,28.488699],"type":"Point"}
}