{
  "type": "Feature",
  "properties": {
    "iso:country":"IN",
    "ks:ks_name":"Azadpur",
    "ks:ks_pop":1392,
    "ks:ks_type":"VILLAGE",
    "ks:ks_uagg_main":0,
    "name:eng_x_preferred":[
        "Azadpur"
    ],
    "wof:name":"Azadpur",
    "wof:placetype":"neighbourhood",
    "wof:population":1392
},
  "geometry": {"coordinates":[88.70826099999999,25.455437],"type":"Point"}
}