{
  "type": "Feature",
  "properties": {
    "iso:country":"IN",
    "ks:ks_name":"Bikrampur",
    "ks:ks_pop":556,
    "ks:ks_type":"VILLAGE",
    "ks:ks_uagg_main":0,
    "name:eng_x_preferred":[
        "Bikrampur"
    ],
    "wof:name":"Bikrampur",
    "wof:placetype":"locality",
    "wof:population":556
},
  "geometry": {"coordinates":[84.496853,26.475971],"type":"Point"}
}