{
  "type": "Feature",
  "properties": {
    "iso:country":"IN",
    "ks:ks_name":"Mayapurwa",
    "ks:ks_pop":159,
    "ks:ks_type":"HABITATION",
    "name:eng_x_preferred":[
        "Mayapurwa"
    ],
    "wof:name":"Mayapurwa",
    "wof:placetype":"locality",
    "wof:population":159
},
  "geometry": {"coordinates":[81.25335,27.505115],"type":"Point"}
}