{
  "type": "Feature",
  "properties": {
    "gn:admin1_code":"39.0",
    "gn:admin2_code":"64.0",
    "gn:asciiname":"Chauna",
    "gn:country_code":"IN",
    "gn:dem":1408,
    "gn:feature_class":"P",
    "gn:feature_code":"PPL",
    "gn:name":"Chauna",
    "gn:population":0,
    "gn:timezone":"Asia/Kolkata",
    "iso:country":"IN",
    "ks:ks_name":"Chauna",
    "ks:ks_pop":912,
    "ks:ks_type":"VILLAGE",
    "name:bre_x_preferred":[
        "Chauna"
    ],
    "name:cat_x_preferred":[
        "Chauna"
    ],
    "name:ceb_x_preferred":[
        "Chauna"
    ],
    "name:eng_x_preferred":[
        "Chauna"
    ],
    "name:epo_x_preferred":[
        "\u0108a\u016dnoj"
    ],
    "name:fas_x_preferred":[
        "\u0641\u0631\u06cc\u0627\u062f\u06a9\u0634\u200c\u0647\u0627\u06cc \u0628\u0632\u0631\u06af"
    ],
    "name:fin_x_preferred":[
        "T\u00f6yht\u00f6romiskot"
    ],
    "name:fra_x_preferred":[
        "Chauna"
    ],
    "name:heb_x_preferred":[
        "\u05e7\u05de\u05d9\u05e7\u05d9"
    ],
    "name:ita_x_preferred":[
        "Chauna"
    ],
    "name:nld_x_preferred":[
        "Chauna"
    ],
    "name:nor_x_preferred":[
        "Chauna"
    ],
    "name:pol_x_preferred":[
        "Chauna"
    ],
    "name:spa_x_preferred":[
        "Chauna"
    ],
    "name:srp_x_preferred":[
        "Chauna"
    ],
    "name:swe_x_preferred":[
        "Chauna"
    ],
    "name:ukr_x_preferred":[
        "\u0427\u0430\u0439\u044f"
    ],
    "name:vie_x_preferred":[
        "Chauna"
    ],
    "name:war_x_preferred":[
        "Chauna"
    ],
    "wof:name":"Chauna",
    "wof:placetype":"locality",
    "wof:population":912
},
  "geometry": {"coordinates":[79.588746,29.671595],"type":"Point"}
}