{
  "type": "Feature",
  "properties": {
    "iso:country":"IN",
    "ks:ks_name":"Farakpur",
    "ks:ks_type":"VILLAGE",
    "ks:ks_uagg_main":0,
    "name:eng_x_preferred":[
        "Farakpur"
    ],
    "wof:name":"Farakpur",
    "wof:placetype":"neighbourhood"
},
  "geometry": {"coordinates":[77.240882,30.136031],"type":"Point"}
}