{
  "type": "Feature",
  "properties": {
    "iso:country":"IN",
    "ks:ks_name":"Sanjha Ghat",
    "ks:ks_pop":1684,
    "ks:ks_type":"HABITATION",
    "name:eng_x_preferred":[
        "Sanjha Ghat"
    ],
    "wof:name":"Sanjha Ghat",
    "wof:placetype":"locality",
    "wof:population":1684
},
  "geometry": {"coordinates":[87.23278000000001,25.783937],"type":"Point"}
}