{
  "type": "Feature",
  "properties": {
    "iso:country":"IN",
    "ks:ks_name":"Kanbua",
    "ks:ks_pop":364,
    "ks:ks_type":"VILLAGE",
    "name:eng_x_preferred":[
        "Kanbua"
    ],
    "wof:name":"Kanbua",
    "wof:placetype":"locality",
    "wof:population":364
},
  "geometry": {"coordinates":[77.86492800000001,30.604184],"type":"Point"}
}