{
  "type": "Feature",
  "properties": {
    "gn:admin1_code":"2.0",
    "gn:admin2_code":"546.0",
    "gn:asciiname":"Chintapalle",
    "gn:country_code":"IN",
    "gn:dem":308,
    "gn:feature_class":"P",
    "gn:feature_code":"PPL",
    "gn:name":"Chintapalle",
    "gn:population":0,
    "gn:timezone":"Asia/Kolkata",
    "iso:country":"IN",
    "ks:ks_name":"Chintapalli",
    "ks:ks_pop":229,
    "ks:ks_type":"HABITATION",
    "name:eng_x_preferred":[
        "Chintapalli"
    ],
    "name:eng_x_variant":[
        "Chintapalle"
    ],
    "name:tel_x_preferred":[
        "\u0c1a\u0c3f\u0c02\u0c24\u0c2a\u0c32\u0c4d\u0c32\u0c3f"
    ],
    "name:vie_x_preferred":[
        "Chintapalle"
    ],
    "wof:name":"Chintapalli",
    "wof:placetype":"locality",
    "wof:population":229
},
  "geometry": {"coordinates":[81.465632,17.314454],"type":"Point"}
}