{
  "type": "Feature",
  "properties": {
    "gn:admin1_code":"2.0",
    "gn:admin2_code":"546.0",
    "gn:asciiname":"Chintapalle",
    "gn:country_code":"IN",
    "gn:dem":308,
    "gn:feature_class":"P",
    "gn:feature_code":"PPL",
    "gn:name":"Chintapalle",
    "gn:population":0,
    "gn:timezone":"Asia/Kolkata",
    "iso:country":"IN",
    "name:tel_x_preferred":[
        "\u0c1a\u0c3f\u0c02\u0c24\u0c2a\u0c32\u0c4d\u0c32\u0c3f"
    ],
    "name:vie_x_preferred":[
        "Chintapalle"
    ],
    "wof:name":"Chintapalle",
    "wof:placetype":"locality"
},
  "geometry": {"coordinates":[81.4635,17.31162999999999],"type":"Point"}
}