{
  "type": "Feature",
  "properties": {
    "gn:admin1_code":"35",
    "gn:admin2_code":"443.0",
    "gn:asciiname":"Zamindar Pipariya",
    "gn:country_code":"IN",
    "gn:dem":429,
    "gn:feature_class":"P",
    "gn:feature_code":"PPL",
    "gn:name":"Zam\u012bnd\u0101r Pipariya",
    "gn:population":0,
    "gn:timezone":"Asia/Kolkata",
    "iso:country":"IN",
    "wof:name":"Zamindar Pipariya",
    "wof:placetype":"locality"
},
  "geometry": {"coordinates":[78.12013,23.75099],"type":"Point"}
}