{
  "type": "Feature",
  "properties": {
    "gn:admin1_code":"35.0",
    "gn:admin2_code":"447.0",
    "gn:asciiname":"Kathi",
    "gn:country_code":"IN",
    "gn:dem":709,
    "gn:feature_class":"P",
    "gn:feature_code":"PPL",
    "gn:name":"K\u0101thi",
    "gn:population":0,
    "gn:timezone":"Asia/Kolkata",
    "iso:country":"IN",
    "name:ceb_x_preferred":[
        "Kathi"
    ],
    "name:deu_x_preferred":[
        "Kathi"
    ],
    "name:swe_x_preferred":[
        "Kathi"
    ],
    "wof:name":"Kathi",
    "wof:placetype":"locality"
},
  "geometry": {"coordinates":[78.49238000000003,21.89551],"type":"Point"}
}