{
  "type": "Feature",
  "properties": {
    "iso:country":"IN",
    "ks:ks_name":"Sogna",
    "ks:ks_pop":258,
    "ks:ks_type":"VILLAGE",
    "name:eng_x_preferred":[
        "Sogna"
    ],
    "wof:name":"Sogna",
    "wof:placetype":"locality",
    "wof:population":258
},
  "geometry": {"coordinates":[79.02464000000001,30.419101],"type":"Point"}
}