{
  "type": "Feature",
  "properties": {
    "iso:country":"IN",
    "ks:ks_name":"Jangritual",
    "ks:ks_pop":239,
    "ks:ks_type":"HABITATION",
    "name:eng_x_preferred":[
        "Jangritual"
    ],
    "wof:name":"Jangritual",
    "wof:placetype":"locality",
    "wof:population":239
},
  "geometry": {"coordinates":[84.00339099999999,19.033086],"type":"Point"}
}