{
  "type": "Feature",
  "properties": {
    "iso:country":"IN",
    "ks:ks_alt_nam":"dahi",
    "ks:ks_name":"Dahi",
    "ks:ks_pop":400,
    "ks:ks_type":"HABITATION",
    "name:eng_x_preferred":[
        "Dahi"
    ],
    "wof:name":"Dahi",
    "wof:placetype":"locality",
    "wof:population":400
},
  "geometry": {"coordinates":[82.082863,25.189484],"type":"Point"}
}