{
  "type": "Feature",
  "properties": {
    "iso:country":"IN",
    "ks:ks_name":"Daulatabad",
    "ks:ks_pop":530,
    "ks:ks_type":"HABITATION",
    "name:eng_x_preferred":[
        "Daulatabad"
    ],
    "wof:name":"Daulatabad",
    "wof:placetype":"locality",
    "wof:population":530
},
  "geometry": {"coordinates":[75.80656399999999,18.642628],"type":"Point"}
}