{
  "type": "Feature",
  "properties": {
    "iso:country":"IN",
    "ks:ks_name":"Makhauli",
    "ks:ks_pop":19,
    "ks:ks_type":"HABITATION",
    "name:eng_x_preferred":[
        "Makhauli"
    ],
    "wof:name":"Makhauli",
    "wof:placetype":"locality",
    "wof:population":19
},
  "geometry": {"coordinates":[80.022991,29.879548],"type":"Point"}
}