{
  "type": "Feature",
  "properties": {
    "iso:country":"IN",
    "qs:name":"Jarolpokpi",
    "qs:name_adm0":"India",
    "qs:name_adm1":"Manipur",
    "qs:photos":3,
    "qs:photos_1k":1,
    "qs:photos_9k":1,
    "qs:photos_9r":1,
    "qs:photos_all":3,
    "qs:photos_sr":1,
    "qs:placetype":"Town",
    "qs:pop_sr":"0",
    "wof:name":"Jarolpokpi",
    "wof:placetype":"locality"
},
  "geometry": {"coordinates":[93.202955,24.785133],"type":"Point"}
}