{
  "type": "Feature",
  "properties": {
    "gn:admin1_code":"37",
    "gn:admin2_code":"407.0",
    "gn:asciiname":"Dongaria",
    "gn:country_code":"IN",
    "gn:dem":318,
    "gn:feature_class":"P",
    "gn:feature_code":"PPL",
    "gn:name":"Dongaria",
    "gn:population":0,
    "gn:timezone":"Asia/Kolkata",
    "iso:country":"IN",
    "wof:name":"Dongaria",
    "wof:placetype":"locality"
},
  "geometry": {"coordinates":[81.22688000000002,21.77346],"type":"Point"}
}