{
  "type": "Feature",
  "properties": {
    "iso:country":"IN",
    "ks:ks_name":"Bhomjai",
    "ks:ks_pop":138,
    "ks:ks_type":"VILLAGE",
    "name:eng_x_preferred":[
        "Bhomjai"
    ],
    "wof:name":"Bhomjai",
    "wof:placetype":"locality",
    "wof:population":138
},
  "geometry": {"coordinates":[73.38303399999999,17.992818],"type":"Point"}
}