{
  "type": "Feature",
  "properties": {
    "iso:country":"IN",
    "ks:ks_name":"Kusumguda",
    "ks:ks_pop":18,
    "ks:ks_type":"HABITATION",
    "name:eng_x_preferred":[
        "Kusumguda"
    ],
    "wof:name":"Kusumguda",
    "wof:placetype":"locality",
    "wof:population":18
},
  "geometry": {"coordinates":[82.141706,18.36376],"type":"Point"}
}