{
  "type": "Feature",
  "properties": {
    "iso:country":"IN",
    "ks:ks_name":"Bandariya Ryt",
    "ks:ks_pop":960,
    "ks:ks_type":"VILLAGE",
    "name:eng_x_preferred":[
        "Bandariya Ryt"
    ],
    "wof:name":"Bandariya Ryt",
    "wof:placetype":"locality",
    "wof:population":960
},
  "geometry": {"coordinates":[76.810875,22.094371],"type":"Point"}
}