{
  "type": "Feature",
  "properties": {
    "iso:country":"IN",
    "ks:ks_name":"Koinaha Bazar",
    "ks:ks_pop":383,
    "ks:ks_type":"HABITATION",
    "ks:ks_uagg_main":0,
    "name:eng_x_preferred":[
        "Koinaha Bazar"
    ],
    "wof:name":"Koinaha Bazar",
    "wof:placetype":"neighbourhood",
    "wof:population":383
},
  "geometry": {"coordinates":[83.04033800000001,26.169873],"type":"Point"}
}