{
  "type": "Feature",
  "properties": {
    "gn:admin1_code":"11.0",
    "gn:admin2_code":"27.0",
    "gn:asciiname":"Dharawat",
    "gn:country_code":"IN",
    "gn:dem":2687,
    "gn:feature_class":"P",
    "gn:feature_code":"PPL",
    "gn:name":"Dhar\u0101wat",
    "gn:population":0,
    "gn:timezone":"Asia/Kolkata",
    "iso:country":"IN",
    "wof:name":"Dharawat",
    "wof:placetype":"locality"
},
  "geometry": {"coordinates":[77.13704,31.50685],"type":"Point"}
}