{
  "type": "Feature",
  "properties": {
    "gn:admin1_code":"40.0",
    "gn:admin2_code":"536.0",
    "gn:asciiname":"Zamistapur",
    "gn:country_code":"IN",
    "gn:dem":517,
    "gn:feature_class":"P",
    "gn:feature_code":"PPL",
    "gn:name":"Zamist\u0101pur",
    "gn:population":0,
    "gn:timezone":"Asia/Kolkata",
    "iso:country":"IN",
    "wof:name":"Zamistapur",
    "wof:placetype":"neighbourhood"
},
  "geometry": {"coordinates":[78.50327,17.41441],"type":"Point"}
}