{
  "type": "Feature",
  "properties": {
    "gn:admin1_code":"10",
    "gn:admin2_code":"86.0",
    "gn:asciiname":"Mahchana",
    "gn:country_code":"IN",
    "gn:dem":225,
    "gn:feature_class":"P",
    "gn:feature_code":"PPL",
    "gn:name":"Mahch\u0101na",
    "gn:population":0,
    "gn:timezone":"Asia/Kolkata",
    "iso:country":"IN",
    "wof:name":"Mahchana",
    "wof:placetype":"locality"
},
  "geometry": {"coordinates":[76.74694000000002,28.39191],"type":"Point"}
}