{
  "type": "Feature",
  "properties": {
    "gn:admin1_code":"36",
    "gn:admin2_code":"138.0",
    "gn:asciiname":"Lawar Janali",
    "gn:country_code":"IN",
    "gn:dem":232,
    "gn:feature_class":"P",
    "gn:feature_code":"PPL",
    "gn:name":"L\u0101war J\u0101nali",
    "gn:population":0,
    "gn:timezone":"Asia/Kolkata",
    "iso:country":"IN",
    "ks:ks_alt_nam":"L\u0101war J\u0101nali",
    "ks:ks_name":"Lawar Janali",
    "ks:ks_type":"VILLAGE",
    "name:eng_x_preferred":[
        "Lawar Janali"
    ],
    "name:eng_x_variant":[
        "L\u0101war J\u0101nali"
    ],
    "wof:name":"Lawar Janali",
    "wof:placetype":"locality"
},
  "geometry": {"coordinates":[77.777033,29.123288],"type":"Point"}
}