{
  "type": "Feature",
  "properties": {
    "gn:admin1_code":"35",
    "gn:admin2_code":"466.0",
    "gn:asciiname":"Salia",
    "gn:country_code":"IN",
    "gn:dem":290,
    "gn:feature_class":"P",
    "gn:feature_code":"PPL",
    "gn:name":"S\u0101lia",
    "gn:population":0,
    "gn:timezone":"Asia/Kolkata",
    "iso:country":"IN",
    "name:ceb_x_preferred":[
        "Salia"
    ],
    "name:deu_x_preferred":[
        "Salia"
    ],
    "wof:name":"Salia",
    "wof:placetype":"neighbourhood"
},
  "geometry": {"coordinates":[76.63809999999999,21.86129],"type":"Point"}
}