{
  "type": "Feature",
  "properties": {
    "iso:country":"IN",
    "ks:ks_name":"Semboor",
    "ks:ks_pop":250,
    "ks:ks_type":"VILLAGE",
    "name:eng_x_preferred":[
        "Semboor"
    ],
    "wof:name":"Semboor",
    "wof:placetype":"locality",
    "wof:population":250
},
  "geometry": {"coordinates":[78.342249,9.852352],"type":"Point"}
}