{
  "type": "Feature",
  "properties": {
    "gn:admin1_code":"11",
    "gn:admin2_code":"23.0",
    "gn:asciiname":"Purgola Uparla",
    "gn:country_code":"IN",
    "gn:dem":1886,
    "gn:feature_class":"P",
    "gn:feature_code":"PPL",
    "gn:name":"Purgola Uparla",
    "gn:population":0,
    "gn:timezone":"Asia/Kolkata",
    "iso:country":"IN",
    "wof:name":"Purgola Uparla",
    "wof:placetype":"locality"
},
  "geometry": {"coordinates":[76.18675,32.49774],"type":"Point"}
}