{
  "type": "Feature",
  "properties": {
    "gn:admin1_code":"39",
    "gn:admin2_code":"60.0",
    "gn:asciiname":"Dalara",
    "gn:country_code":"IN",
    "gn:dem":1828,
    "gn:feature_class":"P",
    "gn:feature_code":"PPL",
    "gn:name":"Dal\u0101ra",
    "gn:population":0,
    "gn:timezone":"Asia/Kolkata",
    "iso:country":"IN",
    "name:deu_x_preferred":[
        "Dalara"
    ],
    "name:rus_x_preferred":[
        "Dalara"
    ],
    "wof:name":"Dalara",
    "wof:placetype":"locality"
},
  "geometry": {"coordinates":[77.87866,30.9084],"type":"Point"}
}