{
  "type": "Feature",
  "properties": {
    "iso:country":"IN",
    "ks:ks_name":"Kitajhore",
    "ks:ks_pop":115,
    "ks:ks_type":"HABITATION",
    "name:eng_x_preferred":[
        "Kitajhore"
    ],
    "wof:name":"Kitajhore",
    "wof:placetype":"locality",
    "wof:population":115
},
  "geometry": {"coordinates":[87.55121200000001,25.09461],"type":"Point"}
}