{
  "type": "Feature",
  "properties": {
    "iso:country":"IN",
    "ks:ks_alt_nam":"salakkadu",
    "ks:ks_name":"Salakkadu",
    "ks:ks_pop":145,
    "ks:ks_type":"HABITATION",
    "name:eng_x_preferred":[
        "Salakkadu"
    ],
    "wof:name":"Salakkadu",
    "wof:placetype":"locality",
    "wof:population":145
},
  "geometry": {"coordinates":[78.45743,11.160243],"type":"Point"}
}