{
  "type": "Feature",
  "properties": {
    "iso:country":"IN",
    "ks:ks_name":"Dongipada",
    "ks:ks_pop":224,
    "ks:ks_type":"HABITATION",
    "name:eng_x_preferred":[
        "Dongipada"
    ],
    "wof:name":"Dongipada",
    "wof:placetype":"locality",
    "wof:population":224
},
  "geometry": {"coordinates":[73.10266799999999,20.040916],"type":"Point"}
}