{
  "type": "Feature",
  "properties": {
    "gn:admin1_code":"37.0",
    "gn:admin2_code":"409",
    "gn:asciiname":"Bortara",
    "gn:country_code":"IN",
    "gn:dem":296,
    "gn:feature_class":"P",
    "gn:feature_code":"PPL",
    "gn:name":"Bortara",
    "gn:population":0,
    "gn:timezone":"Asia/Kolkata",
    "iso:country":"IN",
    "name:eng_x_preferred":[
        "Bortara"
    ],
    "wof:name":"Bortara",
    "wof:placetype":"locality"
},
  "geometry": {"coordinates":[81.22075,21.64409],"type":"Point"}
}