{
  "type": "Feature",
  "properties": {
    "iso:country":"IN",
    "ks:ks_alt_nam":"BHARO KHERA",
    "ks:ks_name":"Bharo Khera",
    "ks:ks_pop":90,
    "ks:ks_type":"HABITATION",
    "name:eng_x_preferred":[
        "Bharo Khera"
    ],
    "wof:name":"Bharo Khera",
    "wof:placetype":"locality",
    "wof:population":90
},
  "geometry": {"coordinates":[80.783568,26.281319],"type":"Point"}
}