{
  "type": "Feature",
  "properties": {
    "gn:admin1_code":"19.0",
    "gn:admin2_code":"572.0",
    "gn:asciiname":"Kolapur",
    "gn:country_code":"IN",
    "gn:dem":888,
    "gn:feature_class":"P",
    "gn:feature_code":"PPL",
    "gn:name":"Kolapur",
    "gn:population":0,
    "gn:timezone":"Asia/Kolkata",
    "iso:country":"IN",
    "wof:name":"Kolapur",
    "wof:placetype":"locality"
},
  "geometry": {"coordinates":[77.49188000000002,13.20681],"type":"Point"}
}