{
  "type": "Feature",
  "properties": {
    "iso:country":"IN",
    "ks:ks_name":"Malebettu",
    "ks:ks_pop":210,
    "ks:ks_type":"HABITATION",
    "name:eng_x_preferred":[
        "Malebettu"
    ],
    "wof:name":"Malebettu",
    "wof:placetype":"locality",
    "wof:population":210
},
  "geometry": {"coordinates":[75.115396,12.994316],"type":"Point"}
}