{
  "type": "Feature",
  "properties": {
    "gn:admin1_code":"2.0",
    "gn:admin2_code":"554.0",
    "gn:asciiname":"Mukkuvandlapalli",
    "gn:country_code":"IN",
    "gn:dem":581,
    "gn:feature_class":"P",
    "gn:feature_code":"PPL",
    "gn:name":"Mukkuv\u0101ndlapalli",
    "gn:population":0,
    "gn:timezone":"Asia/Kolkata",
    "iso:country":"IN",
    "ks:ks_alt_nam":"Mukkavandlapalli H/W",
    "ks:ks_name":"Mukkavandlapalli H/w",
    "ks:ks_pop":107,
    "ks:ks_type":"HABITATION",
    "name:eng_x_preferred":[
        "Mukkavandlapalli H/w"
    ],
    "name:eng_x_variant":[
        "Mukkuvandlapalli"
    ],
    "wof:name":"Mukkavandlapalli H/w",
    "wof:placetype":"locality",
    "wof:population":107
},
  "geometry": {"coordinates":[79.132347,13.636638],"type":"Point"}
}