{
  "type": "Feature",
  "properties": {
    "iso:country":"IN",
    "ks:ks_name":"N. Manakudi",
    "ks:ks_pop":180,
    "ks:ks_type":"HABITATION",
    "name:eng_x_preferred":[
        "N. Manakudi"
    ],
    "wof:name":"N. Manakudi",
    "wof:placetype":"locality",
    "wof:population":180
},
  "geometry": {"coordinates":[78.63547699999999,9.749798],"type":"Point"}
}