{
  "type": "Feature",
  "properties": {
    "iso:country":"IN",
    "ks:ks_name":"Gomra Colony",
    "ks:ks_pop":93,
    "ks:ks_type":"HABITATION",
    "name:eng_x_preferred":[
        "Gomra Colony"
    ],
    "wof:name":"Gomra Colony",
    "wof:placetype":"locality",
    "wof:population":93
},
  "geometry": {"coordinates":[91.688086,23.192067],"type":"Point"}
}