{
  "type": "Feature",
  "properties": {
    "iso:country":"IN",
    "ks:ks_name":"Karuppur",
    "ks:ks_pop":320,
    "ks:ks_type":"HABITATION",
    "ks:ks_uagg_main":0,
    "name:eng_x_preferred":[
        "Karuppur"
    ],
    "wof:name":"Karuppur",
    "wof:placetype":"neighbourhood",
    "wof:population":320
},
  "geometry": {"coordinates":[79.053437,10.054113],"type":"Point"}
}