{
  "type": "Feature",
  "properties": {
    "iso:country":"IN",
    "ks:ks_name":"Bamansemaliya",
    "ks:ks_pop":1689,
    "ks:ks_type":"HABITATION",
    "name:eng_x_preferred":[
        "Bamansemaliya"
    ],
    "wof:name":"Bamansemaliya",
    "wof:placetype":"locality",
    "wof:population":1689
},
  "geometry": {"coordinates":[74.61993099999999,22.73125],"type":"Point"}
}