{
  "type": "Feature",
  "properties": {
    "iso:country":"IN",
    "ks:ks_name":"Pama Khera",
    "ks:ks_pop":502,
    "ks:ks_type":"VILLAGE",
    "ks:ks_uagg_main":0,
    "name:eng_x_preferred":[
        "Pama Khera"
    ],
    "wof:name":"Pama Khera",
    "wof:placetype":"neighbourhood",
    "wof:population":502
},
  "geometry": {"coordinates":[80.503187,26.709774],"type":"Point"}
}