{
  "type": "Feature",
  "properties": {
    "iso:country":"IN",
    "ks:ks_name":"Vlavetti",
    "ks:ks_pop":1250,
    "ks:ks_type":"HABITATION",
    "name:eng_x_preferred":[
        "Vlavetti"
    ],
    "wof:name":"Vlavetti",
    "wof:placetype":"locality",
    "wof:population":1250
},
  "geometry": {"coordinates":[77.13119500000001,8.560416],"type":"Point"}
}