{
  "type": "Feature",
  "properties": {
    "iso:country":"IN",
    "ks:ks_alt_nam":"PURE RAM DAYAL",
    "ks:ks_name":"Pure Ram Dayal",
    "ks:ks_pop":93,
    "ks:ks_type":"HABITATION",
    "ks:ks_uagg_main":0,
    "name:eng_x_preferred":[
        "Pure Ram Dayal"
    ],
    "wof:name":"Pure Ram Dayal",
    "wof:placetype":"neighbourhood",
    "wof:population":93
},
  "geometry": {"coordinates":[81.669417,26.389044],"type":"Point"}
}