{
  "type": "Feature",
  "properties": {
    "iso:country":"IN",
    "ks:ks_name":"Puran Narang Bari Para",
    "ks:ks_pop":366,
    "ks:ks_type":"HABITATION",
    "name:eng_x_preferred":[
        "Puran Narang Bari Para"
    ],
    "wof:name":"Puran Narang Bari Para",
    "wof:placetype":"locality",
    "wof:population":366
},
  "geometry": {"coordinates":[91.555082,23.79089],"type":"Point"}
}