{
  "type": "Feature",
  "properties": {
    "gn:admin1_code":"19.0",
    "gn:admin2_code":"574.0",
    "gn:asciiname":"Devagondanahalli",
    "gn:country_code":"IN",
    "gn:dem":984,
    "gn:feature_class":"P",
    "gn:feature_code":"PPL",
    "gn:name":"Devagondanahalli",
    "gn:population":0,
    "gn:timezone":"Asia/Kolkata",
    "iso:country":"IN",
    "wof:name":"Devagondanahalli",
    "wof:placetype":"locality"
},
  "geometry": {"coordinates":[76.04048,13.06432],"type":"Point"}
}