{
  "type": "Feature",
  "properties": {
    "gn:admin1_code":"35.0",
    "gn:admin2_code":"454.0",
    "gn:asciiname":"Keolari",
    "gn:country_code":"IN",
    "gn:dem":588,
    "gn:feature_class":"P",
    "gn:feature_code":"PPL",
    "gn:name":"Keol\u0101r\u012b",
    "gn:population":0,
    "gn:timezone":"Asia/Kolkata",
    "iso:country":"IN",
    "ks:ks_alt_nam":"Keol\u0101r\u012b",
    "ks:ks_name":"Keolari",
    "ks:ks_type":"VILLAGE",
    "name:eng_x_preferred":[
        "Keolari"
    ],
    "name:eng_x_variant":[
        "Keol\u0101r\u012b"
    ],
    "name:ori_x_preferred":[
        "\u0b15\u0b47\u0b13\u0b32\u0b3e\u0b30\u0b3f"
    ],
    "wof:name":"Keolari",
    "wof:placetype":"locality"
},
  "geometry": {"coordinates":[80.94719600000001,22.514723],"type":"Point"}
}