{
  "type": "Feature",
  "properties": {
    "iso:country":"IN",
    "ks:ks_name":"7 PTP",
    "ks:ks_pop":55,
    "ks:ks_type":"VILLAGE",
    "name:eng_x_preferred":[
        "7 PTP"
    ],
    "wof:name":"7 PTP",
    "wof:placetype":"locality",
    "wof:population":55
},
  "geometry": {"coordinates":[74.320499,29.902711],"type":"Point"}
}