{
  "type": "Feature",
  "properties": {
    "iso:country":"IN",
    "ks:ks_name":"Poilur",
    "ks:ks_pop":2178,
    "ks:ks_type":"HABITATION",
    "name:eng_x_preferred":[
        "Poilur"
    ],
    "wof:name":"Poilur",
    "wof:placetype":"locality",
    "wof:population":2178
},
  "geometry": {"coordinates":[76.24573599999999,10.807272],"type":"Point"}
}