{
  "type": "Feature",
  "properties": {
    "iso:country":"IN",
    "ks:ks_name":"Peetnaickanaptty",
    "ks:ks_pop":112,
    "ks:ks_type":"HABITATION",
    "ks:ks_uagg_main":0,
    "name:eng_x_preferred":[
        "Peetnaickanaptty"
    ],
    "wof:name":"Peetnaickanaptty",
    "wof:placetype":"neighbourhood",
    "wof:population":112
},
  "geometry": {"coordinates":[77.63551099999999,10.018899],"type":"Point"}
}