{
  "type": "Feature",
  "properties": {
    "iso:country":"IN",
    "ks:ks_name":"Itba",
    "ks:ks_pop":725,
    "ks:ks_type":"HABITATION",
    "name:eng_x_preferred":[
        "Itba"
    ],
    "wof:name":"Itba",
    "wof:placetype":"locality",
    "wof:population":725
},
  "geometry": {"coordinates":[86.705078,25.018578],"type":"Point"}
}