{
  "type": "Feature",
  "properties": {
    "iso:country":"IN",
    "ks:ks_name":"Radhasaranpur",
    "ks:ks_pop":168,
    "ks:ks_type":"VILLAGE",
    "name:eng_x_preferred":[
        "Radhasaranpur"
    ],
    "wof:name":"Radhasaranpur",
    "wof:placetype":"locality",
    "wof:population":168
},
  "geometry": {"coordinates":[85.68787399999999,20.556179],"type":"Point"}
}