{
  "type": "Feature",
  "properties": {
    "iso:country":"IN",
    "ks:ks_name":"Haridas",
    "ks:ks_pop":891,
    "ks:ks_type":"VILLAGE",
    "ks:ks_uagg_main":0,
    "name:eng_x_preferred":[
        "Haridas"
    ],
    "wof:name":"Haridas",
    "wof:placetype":"neighbourhood",
    "wof:population":891
},
  "geometry": {"coordinates":[88.17980300000001,25.22324],"type":"Point"}
}