{
  "type": "Feature",
  "properties": {
    "iso:country":"IN",
    "ks:ks_name":"Suratraidi Alias Lakragora",
    "ks:ks_pop":56,
    "ks:ks_type":"VILLAGE",
    "name:eng_x_preferred":[
        "Suratraidi Alias Lakragora"
    ],
    "wof:name":"Suratraidi Alias Lakragora",
    "wof:placetype":"locality",
    "wof:population":56
},
  "geometry": {"coordinates":[86.281064,22.586443],"type":"Point"}
}