{
  "type": "Feature",
  "properties": {
    "gn:admin1_code":"23.0",
    "gn:admin2_code":"43.0",
    "gn:asciiname":"Bareke",
    "gn:country_code":"IN",
    "gn:dem":197,
    "gn:feature_class":"P",
    "gn:feature_code":"PPL",
    "gn:name":"B\u0101reke",
    "gn:population":0,
    "gn:timezone":"Asia/Kolkata",
    "iso:country":"IN",
    "wof:name":"Bareke",
    "wof:placetype":"locality"
},
  "geometry": {"coordinates":[74.55884,30.97154],"type":"Point"}
}