{
  "type": "Feature",
  "properties": {
    "iso:country":"IN",
    "ks:ks_name":"Bhola Batabari",
    "ks:ks_pop":255,
    "ks:ks_type":"VILLAGE",
    "name:eng_x_preferred":[
        "Bhola Batabari"
    ],
    "wof:name":"Bhola Batabari",
    "wof:placetype":"locality",
    "wof:population":255
},
  "geometry": {"coordinates":[91.732771,26.703249],"type":"Point"}
}