{
  "type": "Feature",
  "properties": {
    "iso:country":"IN",
    "ks:ks_name":"Sshebganj Bassbagan",
    "ks:ks_pop":1138,
    "ks:ks_type":"HABITATION",
    "name:eng_x_preferred":[
        "Sshebganj Bassbagan"
    ],
    "wof:name":"Sshebganj Bassbagan",
    "wof:placetype":"locality",
    "wof:population":1138
},
  "geometry": {"coordinates":[89.602827,26.115352],"type":"Point"}
}