{
  "type": "Feature",
  "properties": {
    "iso:country":"IN",
    "ks:ks_name":"Maindipur",
    "ks:ks_pop":120,
    "ks:ks_type":"VILLAGE",
    "ks:ks_uagg_main":0,
    "name:eng_x_preferred":[
        "Maindipur"
    ],
    "wof:name":"Maindipur",
    "wof:placetype":"neighbourhood",
    "wof:population":120
},
  "geometry": {"coordinates":[83.123204,25.683316],"type":"Point"}
}