{
  "type": "Feature",
  "properties": {
    "iso:country":"IN",
    "ks:ks_alt_nam":"Ram chandra ka pura",
    "ks:ks_name":"Ram Chandra Ka Pura",
    "ks:ks_pop":115,
    "ks:ks_type":"HABITATION",
    "name:eng_x_preferred":[
        "Ram Chandra Ka Pura"
    ],
    "wof:name":"Ram Chandra Ka Pura",
    "wof:placetype":"locality",
    "wof:population":115
},
  "geometry": {"coordinates":[78.097644,26.83905],"type":"Point"}
}