{
  "type": "Feature",
  "properties": {
    "iso:country":"IN",
    "ks:ks_alt_nam":"BAHARULI KHAS",
    "ks:ks_name":"Baharuli Khas",
    "ks:ks_pop":2500,
    "ks:ks_type":"HABITATION",
    "name:eng_x_preferred":[
        "Baharuli Khas"
    ],
    "wof:name":"Baharuli Khas",
    "wof:placetype":"locality",
    "wof:population":2500
},
  "geometry": {"coordinates":[84.776842,26.132144],"type":"Point"}
}