{
  "type": "Feature",
  "properties": {
    "iso:country":"IN",
    "ks:ks_name":"Lambaruguda",
    "ks:ks_pop":137,
    "ks:ks_type":"VILLAGE",
    "name:eng_x_preferred":[
        "Lambaruguda"
    ],
    "wof:name":"Lambaruguda",
    "wof:placetype":"locality",
    "wof:population":137
},
  "geometry": {"coordinates":[83.93391800000001,19.479936],"type":"Point"}
}