{
  "type": "Feature",
  "properties": {
    "gn:admin1_code":"37",
    "gn:admin2_code":"409.0",
    "gn:asciiname":"Sengaon",
    "gn:country_code":"IN",
    "gn:dem":261,
    "gn:feature_class":"P",
    "gn:feature_code":"PPL",
    "gn:name":"Sengaon",
    "gn:population":0,
    "gn:timezone":"Asia/Kolkata",
    "iso:country":"IN",
    "ks:ks_name":"Sengaon",
    "ks:ks_pop":43,
    "ks:ks_type":"HABITATION",
    "name:eng_x_preferred":[
        "Sengaon"
    ],
    "name:hin_x_preferred":[
        "\u0938\u0947\u0928\u0917\u093e\u0901\u0935"
    ],
    "wof:name":"Sengaon",
    "wof:placetype":"locality",
    "wof:population":43
},
  "geometry": {"coordinates":[81.700625,21.814842],"type":"Point"}
}