{
  "type": "Feature",
  "properties": {
    "iso:country":"IN",
    "ks:ks_name":"Dhola",
    "ks:ks_pop":14,
    "ks:ks_type":"HABITATION",
    "name:eng_x_preferred":[
        "Dhola"
    ],
    "wof:name":"Dhola",
    "wof:placetype":"locality",
    "wof:population":14
},
  "geometry": {"coordinates":[75.42873400000001,12.717502],"type":"Point"}
}