{
  "type": "Feature",
  "properties": {
    "iso:country":"IN",
    "ks:ks_name":"Sanadar",
    "ks:ks_pop":780,
    "ks:ks_type":"VILLAGE",
    "name:eng_x_preferred":[
        "Sanadar"
    ],
    "wof:name":"Sanadar",
    "wof:placetype":"locality",
    "wof:population":780
},
  "geometry": {"coordinates":[71.797264,24.107008],"type":"Point"}
}