{
  "type": "Feature",
  "properties": {
    "iso:country":"IN",
    "ks:ks_name":"Antojiwadi",
    "ks:ks_pop":77,
    "ks:ks_type":"HABITATION",
    "name:eng_x_preferred":[
        "Antojiwadi"
    ],
    "wof:name":"Antojiwadi",
    "wof:placetype":"locality",
    "wof:population":77
},
  "geometry": {"coordinates":[73.70519400000001,16.773611],"type":"Point"}
}