{
  "type": "Feature",
  "properties": {
    "iso:country":"IN",
    "ks:ks_name":"Gungasar",
    "ks:ks_pop":5,
    "ks:ks_type":"HABITATION",
    "name:eng_x_preferred":[
        "Gungasar"
    ],
    "wof:name":"Gungasar",
    "wof:placetype":"locality",
    "wof:population":5
},
  "geometry": {"coordinates":[75.012691,14.736454],"type":"Point"}
}