{
  "type": "Feature",
  "properties": {
    "iso:country":"IN",
    "ks:ks_alt_nam":"Guna Ch.Uchoi Para",
    "ks:ks_name":"Guna Ch.uchoi Para",
    "ks:ks_pop":30,
    "ks:ks_type":"HABITATION",
    "name:eng_x_preferred":[
        "Guna Ch.uchoi Para"
    ],
    "wof:name":"Guna Ch.uchoi Para",
    "wof:placetype":"locality",
    "wof:population":30
},
  "geometry": {"coordinates":[91.748841,23.380651],"type":"Point"}
}