{
  "type": "Feature",
  "properties": {
    "gn:admin1_code":"36",
    "gn:admin2_code":"178.0",
    "gn:asciiname":"Makhdumnagar",
    "gn:country_code":"IN",
    "gn:dem":94,
    "gn:feature_class":"P",
    "gn:feature_code":"PPL",
    "gn:name":"Makhd\u016bmnagar",
    "gn:population":0,
    "gn:timezone":"Asia/Kolkata",
    "iso:country":"IN",
    "ks:ks_alt_nam":"Makhd\u016bmnagar",
    "ks:ks_name":"Makhdumnagar",
    "ks:ks_type":"VILLAGE",
    "ks:ks_uagg_main":0,
    "name:eng_x_preferred":[
        "Makhdumnagar"
    ],
    "name:eng_x_variant":[
        "Makhd\u016bmnagar"
    ],
    "wof:name":"Makhdumnagar",
    "wof:placetype":"locality"
},
  "geometry": {"coordinates":[82.600784,26.580891],"type":"Point"}
}