{
  "type": "Feature",
  "properties": {
    "iso:country":"IN",
    "ks:ks_name":"Ahmadkot",
    "ks:ks_pop":398,
    "ks:ks_type":"VILLAGE",
    "name:eng_x_preferred":[
        "Ahmadkot"
    ],
    "wof:name":"Ahmadkot",
    "wof:placetype":"locality",
    "wof:population":398
},
  "geometry": {"coordinates":[71.368022,24.768824],"type":"Point"}
}