{
  "type": "Feature",
  "properties": {
    "gn:admin1_code":"11",
    "gn:admin2_code":"23.0",
    "gn:asciiname":"Paredu",
    "gn:country_code":"IN",
    "gn:dem":1345,
    "gn:feature_class":"P",
    "gn:feature_code":"PPL",
    "gn:name":"Paredu",
    "gn:population":0,
    "gn:timezone":"Asia/Kolkata",
    "iso:country":"IN",
    "wof:name":"Paredu",
    "wof:placetype":"locality"
},
  "geometry": {"coordinates":[76.15045000000001,32.5636],"type":"Point"}
}