{
  "type": "Feature",
  "properties": {
    "gn:admin1_code":"21.0",
    "gn:admin2_code":"393.0",
    "gn:asciiname":"Muribahal",
    "gn:country_code":"IN",
    "gn:dem":268,
    "gn:feature_class":"P",
    "gn:feature_code":"PPL",
    "gn:name":"Muribahal",
    "gn:population":0,
    "gn:timezone":"Asia/Kolkata",
    "iso:country":"IN",
    "wof:name":"Muribahal",
    "wof:placetype":"locality"
},
  "geometry": {"coordinates":[83.01311,20.38666],"type":"Point"}
}