{
  "type": "Feature",
  "properties": {
    "gn:admin1_code":"37",
    "gn:admin2_code":"411.0",
    "gn:asciiname":"Kharora",
    "gn:country_code":"IN",
    "gn:dem":291,
    "gn:feature_class":"P",
    "gn:feature_code":"PPL",
    "gn:name":"Kharora",
    "gn:population":0,
    "gn:timezone":"Asia/Kolkata",
    "iso:country":"IN",
    "ks:ks_name":"Kharora",
    "ks:ks_pop":1855,
    "ks:ks_type":"VILLAGE",
    "ks:ks_uagg_main":0,
    "wof:name":"Kharora",
    "wof:placetype":"neighbourhood"
},
  "geometry": {"coordinates":[82.07436,21.12431],"type":"Point"}
}