{
  "type": "Feature",
  "properties": {
    "iso:country":"IN",
    "ks:ks_name":"Gogadeo Garh",
    "ks:ks_pop":491,
    "ks:ks_type":"HABITATION",
    "name:eng_x_preferred":[
        "Gogadeo Garh"
    ],
    "wof:name":"Gogadeo Garh",
    "wof:placetype":"locality",
    "wof:population":491
},
  "geometry": {"coordinates":[72.39943599999999,26.589497],"type":"Point"}
}