{
  "type": "Feature",
  "properties": {
    "iso:country":"IN",
    "ks:ks_name":"Khejra Gopi",
    "ks:ks_pop":592,
    "ks:ks_type":"VILLAGE",
    "name:eng_x_preferred":[
        "Khejra Gopi"
    ],
    "wof:name":"Khejra Gopi",
    "wof:placetype":"locality",
    "wof:population":592
},
  "geometry": {"coordinates":[77.36215,23.630293],"type":"Point"}
}