{
  "type": "Feature",
  "properties": {
    "iso:country":"IN",
    "ks:ks_name":"Sankarpur Gandhwar",
    "ks:ks_pop":448,
    "ks:ks_type":"VILLAGE",
    "name:eng_x_preferred":[
        "Sankarpur Gandhwar"
    ],
    "wof:name":"Sankarpur Gandhwar",
    "wof:placetype":"locality",
    "wof:population":448
},
  "geometry": {"coordinates":[86.00304199999999,26.264682],"type":"Point"}
}