{
  "type": "Feature",
  "properties": {
    "iso:country":"IN",
    "ks:ks_name":"Bsudevpur",
    "ks:ks_pop":287,
    "ks:ks_type":"HABITATION",
    "ks:ks_uagg_main":0,
    "name:eng_x_preferred":[
        "Bsudevpur"
    ],
    "wof:name":"Bsudevpur",
    "wof:placetype":"neighbourhood",
    "wof:population":287
},
  "geometry": {"coordinates":[83.734729,26.501519],"type":"Point"}
}