{
  "type": "Feature",
  "properties": {
    "iso:country":"IN",
    "ks:ks_name":"Banaha",
    "ks:ks_pop":218,
    "ks:ks_type":"HABITATION",
    "ks:ks_uagg_main":0,
    "name:eng_x_preferred":[
        "Banaha"
    ],
    "wof:name":"Banaha",
    "wof:placetype":"neighbourhood",
    "wof:population":218
},
  "geometry": {"coordinates":[84.493866,24.327935],"type":"Point"}
}