{
  "type": "Feature",
  "properties": {
    "iso:country":"IN",
    "ks:ks_name":"Adivilomadigapalle",
    "ks:ks_pop":79,
    "ks:ks_type":"HABITATION",
    "name:eng_x_preferred":[
        "Adivilomadigapalle"
    ],
    "wof:name":"Adivilomadigapalle",
    "wof:placetype":"locality",
    "wof:population":79
},
  "geometry": {"coordinates":[78.68570200000001,13.852107],"type":"Point"}
}