{
  "type": "Feature",
  "properties": {
    "gn:admin1_code":"34",
    "gn:admin2_code":"203.0",
    "gn:asciiname":"Madhubani",
    "gn:country_code":"IN",
    "gn:dem":91,
    "gn:feature_class":"P",
    "gn:feature_code":"PPL",
    "gn:name":"Madhubani",
    "gn:population":0,
    "gn:timezone":"Asia/Kolkata",
    "iso:country":"IN",
    "name:ara_x_preferred":[
        "\u0645\u0627\u062f\u0647\u0648\u0628\u0627\u0646\u0649"
    ],
    "name:ceb_x_preferred":[
        "Madhubani"
    ],
    "name:deu_x_preferred":[
        "Madhubani"
    ],
    "name:nld_x_preferred":[
        "Madhubani"
    ],
    "name:swe_x_preferred":[
        "Madhubani"
    ],
    "wof:name":"Madhubani",
    "wof:placetype":"locality"
},
  "geometry": {"coordinates":[84.10396,27.00013],"type":"Point"}
}