{
  "type": "Feature",
  "properties": {
    "gn:admin1_code":"35.0",
    "gn:admin2_code":"457.0",
    "gn:asciiname":"Majhdhar",
    "gn:country_code":"IN",
    "gn:dem":548,
    "gn:feature_class":"P",
    "gn:feature_code":"PPL",
    "gn:name":"Majhdh\u0101r",
    "gn:population":0,
    "gn:timezone":"Asia/Kolkata",
    "iso:country":"IN",
    "ks:ks_name":"Majdhar",
    "ks:ks_pop":83,
    "ks:ks_type":"VILLAGE",
    "name:eng_x_preferred":[
        "Majdhar"
    ],
    "name:eng_x_variant":[
        "Majhdhar"
    ],
    "wof:name":"Majdhar",
    "wof:placetype":"locality",
    "wof:population":83
},
  "geometry": {"coordinates":[80.54513900000001,21.79932],"type":"Point"}
}