{
  "type": "Feature",
  "properties": {
    "iso:country":"IN",
    "ks:ks_name":"Poomarathu Kollai",
    "ks:ks_pop":145,
    "ks:ks_type":"HABITATION",
    "name:eng_x_preferred":[
        "Poomarathu Kollai"
    ],
    "wof:name":"Poomarathu Kollai",
    "wof:placetype":"locality",
    "wof:population":145
},
  "geometry": {"coordinates":[78.785028,12.763131],"type":"Point"}
}