{
  "type": "Feature",
  "properties": {
    "gn:admin1_code":"37",
    "gn:admin2_code":"410.0",
    "gn:asciiname":"Nagrar",
    "gn:country_code":"IN",
    "gn:dem":674,
    "gn:feature_class":"P",
    "gn:feature_code":"PPL",
    "gn:name":"Nagr\u0101r",
    "gn:population":0,
    "gn:timezone":"Asia/Kolkata",
    "iso:country":"IN",
    "ks:ks_alt_nam":"Nagr\u0101r",
    "ks:ks_name":"Nagrar",
    "ks:ks_type":"VILLAGE",
    "name:eng_x_preferred":[
        "Nagrar"
    ],
    "name:eng_x_variant":[
        "Nagr\u0101r"
    ],
    "wof:name":"Nagrar",
    "wof:placetype":"locality"
},
  "geometry": {"coordinates":[82.38225799999999,20.484661],"type":"Point"}
}