{
  "type": "Feature",
  "properties": {
    "iso:country":"IN",
    "ks:ks_name":"Panch Berya",
    "ks:ks_pop":712,
    "ks:ks_type":"VILLAGE",
    "name:eng_x_preferred":[
        "Panch Berya"
    ],
    "wof:name":"Panch Berya",
    "wof:placetype":"locality",
    "wof:population":712
},
  "geometry": {"coordinates":[87.830215,22.255773],"type":"Point"}
}