{
  "type": "Feature",
  "properties": {
    "iso:country":"IN",
    "ks:ks_name":"Ajeru",
    "ks:ks_pop":175,
    "ks:ks_type":"HABITATION",
    "name:eng_x_preferred":[
        "Ajeru"
    ],
    "wof:name":"Ajeru",
    "wof:placetype":"locality",
    "wof:population":175
},
  "geometry": {"coordinates":[75.15745099999999,12.696108],"type":"Point"}
}