{
  "type": "Feature",
  "properties": {
    "iso:country":"IN",
    "ks:ks_name":"Sarpada",
    "ks:ks_pop":256,
    "ks:ks_type":"HABITATION",
    "name:eng_x_preferred":[
        "Sarpada"
    ],
    "wof:name":"Sarpada",
    "wof:placetype":"locality",
    "wof:population":256
},
  "geometry": {"coordinates":[72.798653,20.042671],"type":"Point"}
}