{
  "type": "Feature",
  "properties": {
    "gn:admin1_code":"36.0",
    "gn:admin2_code":"151.0",
    "gn:asciiname":"Balpur",
    "gn:country_code":"IN",
    "gn:dem":190,
    "gn:feature_class":"P",
    "gn:feature_code":"PPL",
    "gn:name":"B\u0101lpur",
    "gn:population":0,
    "gn:timezone":"Asia/Kolkata",
    "iso:country":"IN",
    "ks:ks_alt_nam":"B\u0101lpur",
    "ks:ks_name":"Balpur",
    "ks:ks_pop":1242,
    "ks:ks_type":"VILLAGE",
    "ks:ks_uagg_main":0,
    "name:eng_x_preferred":[
        "Balpur"
    ],
    "name:eng_x_variant":[
        "B\u0101lpur"
    ],
    "wof:name":"Balpur",
    "wof:placetype":"neighbourhood",
    "wof:population":1242
},
  "geometry": {"coordinates":[79.619297,28.660496],"type":"Point"}
}