{
  "type": "Feature",
  "properties": {
    "iso:country":"IN",
    "ks:ks_name":"Kuargaon",
    "ks:ks_pop":173,
    "ks:ks_type":"VILLAGE",
    "name:eng_x_preferred":[
        "Kuargaon"
    ],
    "wof:name":"Kuargaon",
    "wof:placetype":"locality",
    "wof:population":173
},
  "geometry": {"coordinates":[88.30787599999999,26.288108],"type":"Point"}
}