{
  "type": "Feature",
  "properties": {
    "gn:admin1_code":"2",
    "gn:admin2_code":"544.0",
    "gn:asciiname":"Peddalochili",
    "gn:country_code":"IN",
    "gn:dem":1213,
    "gn:feature_class":"P",
    "gn:feature_code":"PPL",
    "gn:name":"Peddalochili",
    "gn:population":0,
    "gn:timezone":"Asia/Kolkata",
    "iso:country":"IN",
    "wof:name":"Peddalochili",
    "wof:placetype":"locality"
},
  "geometry": {"coordinates":[82.60063000000002,17.98611],"type":"Point"}
}