{
  "type": "Feature",
  "properties": {
    "gn:admin1_code":"2",
    "gn:admin2_code":"544.0",
    "gn:asciiname":"Peddalochili",
    "gn:country_code":"IN",
    "gn:dem":1213,
    "gn:feature_class":"P",
    "gn:feature_code":"PPL",
    "gn:name":"Peddalochili",
    "gn:population":0,
    "gn:timezone":"Asia/Kolkata",
    "iso:country":"IN",
    "ks:ks_name":"Peddalochale",
    "ks:ks_pop":570,
    "ks:ks_type":"HABITATION",
    "name:eng_x_preferred":[
        "Peddalochale"
    ],
    "name:eng_x_variant":[
        "Peddalochili"
    ],
    "wof:name":"Peddalochale",
    "wof:placetype":"locality",
    "wof:population":570
},
  "geometry": {"coordinates":[82.60317999999999,17.985157],"type":"Point"}
}