{
  "type": "Feature",
  "properties": {
    "iso:country":"IN",
    "ks:ks_name":"Pub Lumding Part-2",
    "ks:ks_pop":1865,
    "ks:ks_type":"VILLAGE",
    "name:eng_x_preferred":[
        "Pub Lumding Part-2"
    ],
    "wof:name":"Pub Lumding Part-2",
    "wof:placetype":"locality",
    "wof:population":1865
},
  "geometry": {"coordinates":[93.21694599999999,25.73075],"type":"Point"}
}