{
  "type": "Feature",
  "properties": {
    "gn:admin1_code":"2.0",
    "gn:admin2_code":"543.0",
    "gn:asciiname":"Kondataduru",
    "gn:country_code":"IN",
    "gn:dem":215,
    "gn:feature_class":"P",
    "gn:feature_code":"PPL",
    "gn:name":"Kondat\u0101d\u016bru",
    "gn:population":0,
    "gn:timezone":"Asia/Kolkata",
    "iso:country":"IN",
    "ks:ks_alt_nam":"Kondat\u0101d\u016bru",
    "ks:ks_name":"Kondataduru",
    "ks:ks_type":"VILLAGE",
    "name:eng_x_preferred":[
        "Kondataduru"
    ],
    "name:eng_x_variant":[
        "Kondat\u0101d\u016bru"
    ],
    "wof:name":"Kondataduru",
    "wof:placetype":"locality"
},
  "geometry": {"coordinates":[83.145956,18.437329],"type":"Point"}
}