{
  "type": "Feature",
  "properties": {
    "gn:admin1_code":"19.0",
    "gn:admin2_code":"568.0",
    "gn:asciiname":"Kanchikeri",
    "gn:country_code":"IN",
    "gn:dem":612,
    "gn:feature_class":"P",
    "gn:feature_code":"PPL",
    "gn:name":"Kanchikeri",
    "gn:population":0,
    "gn:timezone":"Asia/Kolkata",
    "iso:country":"IN",
    "ks:ks_name":"Kanchikere",
    "ks:ks_pop":75,
    "ks:ks_type":"HABITATION",
    "name:eng_x_preferred":[
        "Kanchikere"
    ],
    "name:eng_x_variant":[
        "Kanchikeri"
    ],
    "wof:name":"Kanchikere",
    "wof:placetype":"locality",
    "wof:population":75
},
  "geometry": {"coordinates":[74.834017,13.909762],"type":"Point"}
}