{
  "type": "Feature",
  "properties": {
    "iso:country":"IN",
    "ks:ks_name":"Chiwad Kalan",
    "ks:ks_pop":1020,
    "ks:ks_type":"HABITATION",
    "name:eng_x_preferred":[
        "Chiwad Kalan"
    ],
    "wof:name":"Chiwad Kalan",
    "wof:placetype":"locality",
    "wof:population":1020
},
  "geometry": {"coordinates":[76.49065,24.135866],"type":"Point"}
}