{
  "type": "Feature",
  "properties": {
    "gn:admin1_code":"34",
    "gn:admin2_code":"218.0",
    "gn:asciiname":"Majahida",
    "gn:country_code":"IN",
    "gn:dem":69,
    "gn:feature_class":"P",
    "gn:feature_code":"PPL",
    "gn:name":"Majahida",
    "gn:population":0,
    "gn:timezone":"Asia/Kolkata",
    "iso:country":"IN",
    "name:und_x_variant":[
        "Majahidpur"
    ],
    "wof:name":"Majahida",
    "wof:placetype":"locality"
},
  "geometry": {"coordinates":[84.29178,26.2422],"type":"Point"}
}