{
  "type": "Feature",
  "properties": {
    "iso:country":"IN",
    "ks:ks_name":"Sirmandih",
    "ks:ks_pop":458,
    "ks:ks_type":"VILLAGE",
    "ks:ks_uagg_main":0,
    "name:eng_x_preferred":[
        "Sirmandih"
    ],
    "wof:name":"Sirmandih",
    "wof:placetype":"neighbourhood",
    "wof:population":458
},
  "geometry": {"coordinates":[85.96099,24.446356],"type":"Point"}
}