{
  "type": "Feature",
  "properties": {
    "gn:admin1_code":"36",
    "gn:admin2_code":"180.0",
    "gn:asciiname":"Lakhwapur Bahraicha",
    "gn:country_code":"IN",
    "gn:dem":109,
    "gn:feature_class":"P",
    "gn:feature_code":"PPL",
    "gn:name":"Lakhw\u0101pur Bahraicha",
    "gn:population":0,
    "gn:timezone":"Asia/Kolkata",
    "iso:country":"IN",
    "wof:name":"Lakhwapur Bahraicha",
    "wof:placetype":"locality"
},
  "geometry": {"coordinates":[81.63284,27.26531],"type":"Point"}
}