{
  "type": "Feature",
  "properties": {
    "iso:country":"IN",
    "ks:ks_name":"Parasari",
    "ks:ks_pop":30,
    "ks:ks_type":"VILLAGE",
    "name:eng_x_preferred":[
        "Parasari"
    ],
    "wof:name":"Parasari",
    "wof:placetype":"locality",
    "wof:population":30
},
  "geometry": {"coordinates":[79.297533,23.76208],"type":"Point"}
}