{
  "type": "Feature",
  "properties": {
    "gn:admin1_code":"35.0",
    "gn:admin2_code":"449.0",
    "gn:asciiname":"Birjikhapa",
    "gn:country_code":"IN",
    "gn:dem":392,
    "gn:feature_class":"P",
    "gn:feature_code":"PPL",
    "gn:name":"Birj\u012bkh\u0101pa",
    "gn:population":0,
    "gn:timezone":"Asia/Kolkata",
    "iso:country":"IN",
    "ks:ks_alt_nam":"Birj\u012bkh\u0101pa",
    "ks:ks_name":"Birjikhapa",
    "ks:ks_pop":177,
    "ks:ks_type":"VILLAGE",
    "name:eng_x_preferred":[
        "Birjikhapa"
    ],
    "name:eng_x_variant":[
        "Birj\u012bkh\u0101pa"
    ],
    "wof:name":"Birjikhapa",
    "wof:placetype":"locality",
    "wof:population":177
},
  "geometry": {"coordinates":[78.350685,22.591838],"type":"Point"}
}