{
  "type": "Feature",
  "properties": {
    "iso:country":"IN",
    "ks:ks_name":"Thomathuram",
    "ks:ks_pop":2815,
    "ks:ks_type":"HABITATION",
    "name:eng_x_preferred":[
        "Thomathuram"
    ],
    "wof:name":"Thomathuram",
    "wof:placetype":"locality",
    "wof:population":2815
},
  "geometry": {"coordinates":[76.372061,9.499024],"type":"Point"}
}