{
  "type": "Feature",
  "properties": {
    "iso:country":"IN",
    "ks:ks_name":"Nheru",
    "ks:ks_pop":1852,
    "ks:ks_type":"HABITATION",
    "name:eng_x_preferred":[
        "Nheru"
    ],
    "wof:name":"Nheru",
    "wof:placetype":"locality",
    "wof:population":1852
},
  "geometry": {"coordinates":[75.214079,12.481789],"type":"Point"}
}