{
  "type": "Feature",
  "properties": {
    "gn:admin1_code":"36.0",
    "gn:admin2_code":"182.0",
    "gn:asciiname":"Aghirwa",
    "gn:country_code":"IN",
    "gn:dem":110,
    "gn:feature_class":"P",
    "gn:feature_code":"PPL",
    "gn:name":"Aghirwa",
    "gn:population":0,
    "gn:timezone":"Asia/Kolkata",
    "iso:country":"IN",
    "ks:ks_name":"Agharwa",
    "ks:ks_pop":526,
    "ks:ks_type":"HABITATION",
    "ks:ks_uagg_main":0,
    "name:eng_x_preferred":[
        "Agharwa"
    ],
    "wof:name":"Agharwa",
    "wof:placetype":"neighbourhood",
    "wof:population":526
},
  "geometry": {"coordinates":[82.178634,27.386021],"type":"Point"}
}