{
  "type": "Feature",
  "properties": {
    "iso:country":"IN",
    "ks:ks_name":"Khirgidas Pur",
    "ks:ks_pop":150,
    "ks:ks_type":"HABITATION",
    "name:eng_x_preferred":[
        "Khirgidas Pur"
    ],
    "wof:name":"Khirgidas Pur",
    "wof:placetype":"locality",
    "wof:population":150
},
  "geometry": {"coordinates":[81.180361,27.419131],"type":"Point"}
}