{
  "type": "Feature",
  "properties": {
    "gn:admin1_code":"25.0",
    "gn:admin2_code":"631.0",
    "gn:asciiname":"Sintagumpalli",
    "gn:country_code":"IN",
    "gn:dem":560,
    "gn:feature_class":"P",
    "gn:feature_code":"PPL",
    "gn:name":"Sintagumpalli",
    "gn:population":0,
    "gn:timezone":"Asia/Kolkata",
    "iso:country":"IN",
    "wof:name":"Sintagumpalli",
    "wof:placetype":"neighbourhood"
},
  "geometry": {"coordinates":[78.13737999999999,12.69852],"type":"Point"}
}