{
  "type": "Feature",
  "properties": {
    "iso:country":"IN",
    "ks:ks_name":"Kusiyarbarcha",
    "ks:ks_pop":180,
    "ks:ks_type":"VILLAGE",
    "name:eng_x_preferred":[
        "Kusiyarbarcha"
    ],
    "wof:name":"Kusiyarbarcha",
    "wof:placetype":"locality",
    "wof:population":180
},
  "geometry": {"coordinates":[82.15599899999999,20.148131],"type":"Point"}
}