{
  "type": "Feature",
  "properties": {
    "iso:country":"IN",
    "ks:ks_name":"Safiabad",
    "ks:ks_pop":1212,
    "ks:ks_type":"VILLAGE",
    "name:eng_x_preferred":[
        "Safiabad"
    ],
    "wof:name":"Safiabad",
    "wof:placetype":"locality",
    "wof:population":1212
},
  "geometry": {"coordinates":[87.33660399999999,22.393814],"type":"Point"}
}