{
  "type": "Feature",
  "properties": {
    "iso:country":"IN",
    "ks:ks_name":"Keelakorapalayam",
    "ks:ks_pop":466,
    "ks:ks_type":"HABITATION",
    "ks:ks_uagg_main":0,
    "name:eng_x_preferred":[
        "Keelakorapalayam"
    ],
    "wof:name":"Keelakorapalayam",
    "wof:placetype":"neighbourhood",
    "wof:population":466
},
  "geometry": {"coordinates":[78.392195,10.95081],"type":"Point"}
}