{
  "type": "Feature",
  "properties": {
    "gn:admin1_code":"12.0",
    "gn:admin2_code":"1.0",
    "gn:asciiname":"Bara Baihk",
    "gn:country_code":"IN",
    "gn:dem":2615,
    "gn:feature_class":"P",
    "gn:feature_code":"PPL",
    "gn:name":"B\u0101ra Baihk",
    "gn:population":0,
    "gn:timezone":"Asia/Kolkata",
    "iso:country":"IN",
    "wof:name":"Bara Baihk",
    "wof:placetype":"locality"
},
  "geometry": {"coordinates":[74.02112,34.53793],"type":"Point"}
}