{
  "type": "Feature",
  "properties": {
    "iso:country":"IN",
    "ks:ks_name":"Kattubanda",
    "ks:ks_pop":90,
    "ks:ks_type":"HABITATION",
    "name:eng_x_preferred":[
        "Kattubanda"
    ],
    "wof:name":"Kattubanda",
    "wof:placetype":"locality",
    "wof:population":90
},
  "geometry": {"coordinates":[82.43553300000001,17.985066],"type":"Point"}
}