{
  "type": "Feature",
  "properties": {
    "iso:country":"IN",
    "ks:ks_alt_nam":"dhanaki",
    "ks:ks_name":"Dhanaki",
    "ks:ks_pop":64,
    "ks:ks_type":"HABITATION",
    "name:eng_x_preferred":[
        "Dhanaki"
    ],
    "wof:name":"Dhanaki",
    "wof:placetype":"locality",
    "wof:population":64
},
  "geometry": {"coordinates":[73.493515,19.132193],"type":"Point"}
}