{
  "type": "Feature",
  "properties": {
    "iso:country":"IN",
    "ks:ks_alt_nam":"KatKaripada 1",
    "ks:ks_name":"Katkaripada 1",
    "ks:ks_pop":32,
    "ks:ks_type":"HABITATION",
    "name:eng_x_preferred":[
        "Katkaripada 1"
    ],
    "wof:name":"Katkaripada 1",
    "wof:placetype":"locality",
    "wof:population":32
},
  "geometry": {"coordinates":[72.86549100000001,19.748205],"type":"Point"}
}