{
  "type": "Feature",
  "properties": {
    "gn:admin1_code":"24.0",
    "gn:admin2_code":"104.0",
    "gn:asciiname":"Mahtawas",
    "gn:country_code":"IN",
    "gn:dem":279,
    "gn:feature_class":"P",
    "gn:feature_code":"PPL",
    "gn:name":"Maht\u0101w\u0101s",
    "gn:population":0,
    "gn:timezone":"Asia/Kolkata",
    "iso:country":"IN",
    "name:und_x_variant":[
        "Maht\u0101w\u0101s"
    ],
    "wof:name":"Mahtawas",
    "wof:placetype":"locality"
},
  "geometry": {"coordinates":[76.41526,28.12969],"type":"Point"}
}