{
  "type": "Feature",
  "properties": {
    "iso:country":"IN",
    "ks:ks_name":"Kundara Kala",
    "ks:ks_pop":406,
    "ks:ks_type":"VILLAGE",
    "ks:ks_uagg_main":0,
    "name:eng_x_preferred":[
        "Kundara Kala"
    ],
    "wof:name":"Kundara Kala",
    "wof:placetype":"neighbourhood",
    "wof:population":406
},
  "geometry": {"coordinates":[80.69144300000001,26.913749],"type":"Point"}
}