{
  "type": "Feature",
  "properties": {
    "gn:admin1_code":"11",
    "gn:admin2_code":"24.0",
    "gn:asciiname":"Bah",
    "gn:country_code":"IN",
    "gn:dem":826,
    "gn:feature_class":"P",
    "gn:feature_code":"PPL",
    "gn:name":"B\u0101h",
    "gn:population":0,
    "gn:timezone":"Asia/Kolkata",
    "iso:country":"IN",
    "name:bih_x_preferred":[
        "\u092c\u093e\u0939"
    ],
    "name:bpy_x_preferred":[
        "\u09ac\u09be\u09b9"
    ],
    "name:ceb_x_preferred":[
        "B\u0101h"
    ],
    "name:deu_x_preferred":[
        "Bah"
    ],
    "name:hin_x_preferred":[
        "\u092c\u093e\u0939"
    ],
    "name:ita_x_preferred":[
        "Bah"
    ],
    "name:msa_x_preferred":[
        "Bah"
    ],
    "name:new_x_preferred":[
        "\u092c\u093e\u0939"
    ],
    "name:nld_x_preferred":[
        "Bah"
    ],
    "name:pol_x_preferred":[
        "Bah"
    ],
    "name:por_x_preferred":[
        "Bah"
    ],
    "name:swe_x_preferred":[
        "B\u0101h"
    ],
    "name:urd_x_preferred":[
        "\u0628\u0627\u06c1"
    ],
    "name:vie_x_preferred":[
        "Bah"
    ],
    "name:zho_x_preferred":[
        "\u5df4\u9547"
    ],
    "wof:name":"Bah",
    "wof:placetype":"locality"
},
  "geometry": {"coordinates":[76.39556999999998,31.87122],"type":"Point"}
}