{
  "type": "Feature",
  "properties": {
    "iso:country":"IN",
    "ks:ks_name":"Kondari",
    "ks:ks_pop":200,
    "ks:ks_type":"HABITATION",
    "ks:ks_uagg_main":0,
    "name:eng_x_preferred":[
        "Kondari"
    ],
    "wof:name":"Kondari",
    "wof:placetype":"neighbourhood",
    "wof:population":200
},
  "geometry": {"coordinates":[81.816638,27.069206],"type":"Point"}
}