{
  "type": "Feature",
  "properties": {
    "iso:country":"IN",
    "ks:ks_name":"J H C",
    "ks:ks_pop":323,
    "ks:ks_type":"HABITATION",
    "name:eng_x_preferred":[
        "J H C"
    ],
    "wof:name":"J H C",
    "wof:placetype":"locality",
    "wof:population":323
},
  "geometry": {"coordinates":[74.925978,13.515309],"type":"Point"}
}