{
  "type": "Feature",
  "properties": {
    "iso:country":"IN",
    "ks:ks_name":"Viruthanvayal",
    "ks:ks_pop":121,
    "ks:ks_type":"HABITATION",
    "name:eng_x_preferred":[
        "Viruthanvayal"
    ],
    "wof:name":"Viruthanvayal",
    "wof:placetype":"locality",
    "wof:population":121
},
  "geometry": {"coordinates":[78.740651,9.75109],"type":"Point"}
}