{
  "type": "Feature",
  "properties": {
    "iso:country":"IN",
    "ks:ks_name":"Baramara",
    "ks:ks_pop":2033,
    "ks:ks_type":"VILLAGE",
    "name:eng_x_preferred":[
        "Baramara"
    ],
    "wof:name":"Baramara",
    "wof:placetype":"locality",
    "wof:population":2033
},
  "geometry": {"coordinates":[87.332525,22.952861],"type":"Point"}
}