{
  "type": "Feature",
  "properties": {
    "gn:admin1_code":"36",
    "gn:admin2_code":"196.0",
    "gn:asciiname":"Mahabalpur",
    "gn:country_code":"IN",
    "gn:dem":80,
    "gn:feature_class":"P",
    "gn:feature_code":"PPL",
    "gn:name":"Mah\u0101balpur",
    "gn:population":0,
    "gn:timezone":"Asia/Kolkata",
    "iso:country":"IN",
    "ks:ks_name":"Mahawalpur",
    "ks:ks_pop":2735,
    "ks:ks_type":"VILLAGE",
    "name:eng_x_preferred":[
        "Mahawalpur"
    ],
    "name:eng_x_variant":[
        "Mahabalpur"
    ],
    "wof:name":"Mahawalpur",
    "wof:placetype":"locality",
    "wof:population":2735
},
  "geometry": {"coordinates":[83.08922,25.292953],"type":"Point"}
}