{
  "type": "Feature",
  "properties": {
    "gn:admin1_code":"10",
    "gn:admin2_code":"85.0",
    "gn:asciiname":"Haluhera",
    "gn:country_code":"IN",
    "gn:dem":239,
    "gn:feature_class":"P",
    "gn:feature_code":"PPL",
    "gn:name":"H\u0101luhera",
    "gn:population":0,
    "gn:timezone":"Asia/Kolkata",
    "iso:country":"IN",
    "wof:name":"Haluhera",
    "wof:placetype":"locality"
},
  "geometry": {"coordinates":[76.5318,28.29201],"type":"Point"}
}