{
  "type": "Feature",
  "properties": {
    "iso:country":"IN",
    "ks:ks_name":"Zotingdara",
    "ks:ks_pop":65,
    "ks:ks_type":"HABITATION",
    "name:eng_x_preferred":[
        "Zotingdara"
    ],
    "wof:name":"Zotingdara",
    "wof:placetype":"locality",
    "wof:population":65
},
  "geometry": {"coordinates":[78.48647200000001,20.250537],"type":"Point"}
}