{
  "type": "Feature",
  "properties": {
    "iso:country":"IN",
    "ks:ks_name":"Reddigudem",
    "ks:ks_pop":78,
    "ks:ks_type":"HABITATION",
    "name:eng_x_preferred":[
        "Reddigudem"
    ],
    "wof:name":"Reddigudem",
    "wof:placetype":"locality",
    "wof:population":78
},
  "geometry": {"coordinates":[81.251887,17.320192],"type":"Point"}
}