{
  "type": "Feature",
  "properties": {
    "iso:country":"IN",
    "ks:ks_name":"Vanniyampatti",
    "ks:ks_pop":175,
    "ks:ks_type":"HABITATION",
    "name:eng_x_preferred":[
        "Vanniyampatti"
    ],
    "wof:name":"Vanniyampatti",
    "wof:placetype":"locality",
    "wof:population":175
},
  "geometry": {"coordinates":[78.969847,10.692555],"type":"Point"}
}