{
  "type": "Feature",
  "properties": {
    "iso:country":"IN",
    "ks:ks_name":"Kantivana",
    "ks:ks_pop":254,
    "ks:ks_type":"HABITATION",
    "name:eng_x_preferred":[
        "Kantivana"
    ],
    "wof:name":"Kantivana",
    "wof:placetype":"locality",
    "wof:population":254
},
  "geometry": {"coordinates":[74.78321,14.335948],"type":"Point"}
}