{
  "type": "Feature",
  "properties": {
    "iso:country":"IN",
    "ks:ks_name":"Batadula Madhyapara",
    "ks:ks_pop":372,
    "ks:ks_type":"HABITATION",
    "ks:ks_uagg_main":0,
    "name:eng_x_preferred":[
        "Batadula Madhyapara"
    ],
    "wof:name":"Batadula Madhyapara",
    "wof:placetype":"neighbourhood",
    "wof:population":372
},
  "geometry": {"coordinates":[91.221425,23.537212],"type":"Point"}
}