{
  "type": "Feature",
  "properties": {
    "gn:admin1_code":"35",
    "gn:admin2_code":"456.0",
    "gn:asciiname":"Keolari",
    "gn:country_code":"IN",
    "gn:dem":549,
    "gn:feature_class":"P",
    "gn:feature_code":"PPL",
    "gn:name":"Keol\u0101ri",
    "gn:population":0,
    "gn:timezone":"Asia/Kolkata",
    "iso:country":"IN",
    "name:ori_x_preferred":[
        "\u0b15\u0b47\u0b13\u0b32\u0b3e\u0b30\u0b3f"
    ],
    "wof:name":"Keolari",
    "wof:placetype":"locality"
},
  "geometry": {"coordinates":[79.96655,22.6643],"type":"Point"}
}