{
  "type": "Feature",
  "properties": {
    "iso:country":"IN",
    "ks:ks_name":"Kediyakatchh",
    "ks:ks_pop":850,
    "ks:ks_type":"HABITATION",
    "name:eng_x_preferred":[
        "Kediyakatchh"
    ],
    "wof:name":"Kediyakatchh",
    "wof:placetype":"locality",
    "wof:population":850
},
  "geometry": {"coordinates":[73.03269400000001,20.411361],"type":"Point"}
}