{
  "type": "Feature",
  "properties": {
    "iso:country":"IN",
    "ks:ks_name":"Ghorlata",
    "ks:ks_pop":81,
    "ks:ks_type":"HABITATION",
    "name:eng_x_preferred":[
        "Ghorlata"
    ],
    "wof:name":"Ghorlata",
    "wof:placetype":"locality",
    "wof:population":81
},
  "geometry": {"coordinates":[85.51722700000001,23.375249],"type":"Point"}
}