{
  "type": "Feature",
  "properties": {
    "gn:admin1_code":"35",
    "gn:admin2_code":"455.0",
    "gn:asciiname":"Mohgaon Kalan",
    "gn:country_code":"IN",
    "gn:dem":626,
    "gn:feature_class":"P",
    "gn:feature_code":"PPL",
    "gn:name":"Mohgaon Kal\u0101n",
    "gn:population":0,
    "gn:timezone":"Asia/Kolkata",
    "iso:country":"IN",
    "wof:name":"Mohgaon Kalan",
    "wof:placetype":"locality"
},
  "geometry": {"coordinates":[79.12704000000002,21.80416],"type":"Point"}
}