{
  "type": "Feature",
  "properties": {
    "iso:country":"IN",
    "ks:ks_name":"Gadilkarwasti",
    "ks:ks_pop":118,
    "ks:ks_type":"HABITATION",
    "name:eng_x_preferred":[
        "Gadilkarwasti"
    ],
    "wof:name":"Gadilkarwasti",
    "wof:placetype":"locality",
    "wof:population":118
},
  "geometry": {"coordinates":[74.377454,18.8666],"type":"Point"}
}