{
  "type": "Feature",
  "properties": {
    "iso:country":"IN",
    "ks:ks_name":"Gardanepada",
    "ks:ks_pop":83,
    "ks:ks_type":"HABITATION",
    "name:eng_x_preferred":[
        "Gardanepada"
    ],
    "wof:name":"Gardanepada",
    "wof:placetype":"locality",
    "wof:population":83
},
  "geometry": {"coordinates":[73.15098,19.533225],"type":"Point"}
}