{
  "type": "Feature",
  "properties": {
    "gn:admin1_code":"19",
    "gn:admin2_code":"575.0",
    "gn:asciiname":"Hatti Kudru",
    "gn:country_code":"IN",
    "gn:dem":8,
    "gn:feature_class":"P",
    "gn:feature_code":"PPL",
    "gn:name":"Hatti Kudru",
    "gn:population":0,
    "gn:timezone":"Asia/Kolkata",
    "iso:country":"IN",
    "wof:name":"Hatti Kudru",
    "wof:placetype":"locality"
},
  "geometry": {"coordinates":[74.73254,13.64043],"type":"Point"}
}