{
  "type": "Feature",
  "properties": {
    "gn:admin1_code":"19",
    "gn:admin2_code":"575.0",
    "gn:asciiname":"Hatti Kudru",
    "gn:country_code":"IN",
    "gn:dem":8,
    "gn:feature_class":"P",
    "gn:feature_code":"PPL",
    "gn:name":"Hatti Kudru",
    "gn:population":0,
    "gn:timezone":"Asia/Kolkata",
    "iso:country":"IN",
    "ks:ks_name":"Hattikudru",
    "ks:ks_pop":475,
    "ks:ks_type":"HABITATION",
    "name:eng_x_preferred":[
        "Hattikudru"
    ],
    "name:eng_x_variant":[
        "Hatti Kudru"
    ],
    "wof:name":"Hattikudru",
    "wof:placetype":"locality",
    "wof:population":475
},
  "geometry": {"coordinates":[74.734059,13.641082],"type":"Point"}
}