{
  "type": "Feature",
  "properties": {
    "iso:country":"IN",
    "ks:ks_name":"Nandipuram",
    "ks:ks_pop":258,
    "ks:ks_type":"HABITATION",
    "name:eng_x_preferred":[
        "Nandipuram"
    ],
    "wof:name":"Nandipuram",
    "wof:placetype":"locality",
    "wof:population":258
},
  "geometry": {"coordinates":[77.55450999999999,12.273489],"type":"Point"}
}