{
  "type": "Feature",
  "properties": {
    "iso:country":"IN",
    "ks:ks_name":"Dhalibil Pt I",
    "ks:ks_pop":1188,
    "ks:ks_type":"VILLAGE",
    "name:eng_x_preferred":[
        "Dhalibil Pt I"
    ],
    "wof:name":"Dhalibil Pt I",
    "wof:placetype":"locality",
    "wof:population":1188
},
  "geometry": {"coordinates":[92.44261299999999,24.577029],"type":"Point"}
}