{
  "type": "Feature",
  "properties": {
    "gn:admin1_code":"36",
    "gn:admin2_code":"175.0",
    "gn:asciiname":"Newaria Bayalis",
    "gn:country_code":"IN",
    "gn:dem":136,
    "gn:feature_class":"P",
    "gn:feature_code":"PPL",
    "gn:name":"Newaria Bay\u0101lis",
    "gn:population":0,
    "gn:timezone":"Asia/Kolkata",
    "iso:country":"IN",
    "wof:name":"Newaria Bayalis",
    "wof:placetype":"locality"
},
  "geometry": {"coordinates":[82.16211,24.97527],"type":"Point"}
}