{
  "type": "Feature",
  "properties": {
    "gn:admin1_code":"37.0",
    "gn:admin2_code":"416.0",
    "gn:asciiname":"Voyaras",
    "gn:country_code":"IN",
    "gn:dem":315,
    "gn:feature_class":"P",
    "gn:feature_code":"PPL",
    "gn:name":"Voyar\u0101s",
    "gn:population":0,
    "gn:timezone":"Asia/Kolkata",
    "iso:country":"IN",
    "name:und_x_variant":[
        "Voyar\u0101s",
        "Dandig\u016bda"
    ],
    "wof:name":"Voyaras",
    "wof:placetype":"locality"
},
  "geometry": {"coordinates":[81.55213000000001,18.52709],"type":"Point"}
}