{
  "type": "Feature",
  "properties": {
    "iso:country":"IN",
    "ks:ks_name":"Solaoorani",
    "ks:ks_pop":161,
    "ks:ks_type":"HABITATION",
    "name:eng_x_preferred":[
        "Solaoorani"
    ],
    "wof:name":"Solaoorani",
    "wof:placetype":"locality",
    "wof:population":161
},
  "geometry": {"coordinates":[78.69319,9.660469],"type":"Point"}
}