{
  "type": "Feature",
  "properties": {
    "gn:admin1_code":"36",
    "gn:admin2_code":"196.0",
    "gn:asciiname":"Tiwaripur",
    "gn:country_code":"IN",
    "gn:dem":79,
    "gn:feature_class":"P",
    "gn:feature_code":"PPL",
    "gn:name":"Tiw\u0101r\u012bpur",
    "gn:population":0,
    "gn:timezone":"Asia/Kolkata",
    "iso:country":"IN",
    "ks:ks_alt_nam":"Tiw\u0101r\u012bpur",
    "ks:ks_name":"Tiwaripur",
    "ks:ks_pop":146,
    "ks:ks_type":"VILLAGE",
    "name:eng_x_preferred":[
        "Tiwaripur"
    ],
    "name:eng_x_variant":[
        "Tiw\u0101r\u012bpur"
    ],
    "wof:name":"Tiwaripur",
    "wof:placetype":"locality",
    "wof:population":146
},
  "geometry": {"coordinates":[83.212273,25.389551],"type":"Point"}
}