{
  "type": "Feature",
  "properties": {
    "gn:admin1_code":"16.0",
    "gn:admin2_code":"528",
    "gn:asciiname":"Dhamnand",
    "gn:country_code":"IN",
    "gn:dem":95,
    "gn:feature_class":"P",
    "gn:feature_code":"PPL",
    "gn:name":"Dh\u0101mnand",
    "gn:population":0,
    "gn:timezone":"Asia/Kolkata",
    "iso:country":"IN",
    "name:und_x_variant":[
        "Dhamnad",
        "Dh\u0101mnand"
    ],
    "wof:name":"Dhamnand",
    "wof:placetype":"locality"
},
  "geometry": {"coordinates":[73.60394000000002,17.60661],"type":"Point"}
}