{
  "type": "Feature",
  "properties": {
    "iso:country":"IN",
    "ks:ks_name":"Katikbhita",
    "ks:ks_pop":164,
    "ks:ks_type":"VILLAGE",
    "name:eng_x_preferred":[
        "Katikbhita"
    ],
    "wof:name":"Katikbhita",
    "wof:placetype":"locality",
    "wof:population":164
},
  "geometry": {"coordinates":[87.428516,24.891249],"type":"Point"}
}