{
  "type": "Feature",
  "properties": {
    "iso:country":"IN",
    "ks:ks_alt_nam":"PURE NURPUR",
    "ks:ks_name":"Pure Nurpur",
    "ks:ks_pop":67,
    "ks:ks_type":"HABITATION",
    "name:eng_x_preferred":[
        "Pure Nurpur"
    ],
    "wof:name":"Pure Nurpur",
    "wof:placetype":"locality",
    "wof:population":67
},
  "geometry": {"coordinates":[81.44459999999999,26.542],"type":"Point"}
}