{
  "type": "Feature",
  "properties": {
    "iso:country":"IN",
    "ks:ks_alt_nam":"Basveshwara camp",
    "ks:ks_name":"Basveshwara Camp",
    "ks:ks_pop":883,
    "ks:ks_type":"HABITATION",
    "name:eng_x_preferred":[
        "Basveshwara Camp"
    ],
    "wof:name":"Basveshwara Camp",
    "wof:placetype":"locality",
    "wof:population":883
},
  "geometry": {"coordinates":[77.003191,15.055184],"type":"Point"}
}