{
  "type": "Feature",
  "properties": {
    "iso:country":"IN",
    "ks:ks_name":"Kharani Jan",
    "ks:ks_pop":833,
    "ks:ks_type":"VILLAGE",
    "name:eng_x_preferred":[
        "Kharani Jan"
    ],
    "wof:name":"Kharani Jan",
    "wof:placetype":"locality",
    "wof:population":833
},
  "geometry": {"coordinates":[93.671556,26.893673],"type":"Point"}
}