{
  "type": "Feature",
  "properties": {
    "iso:country":"IN",
    "ks:ks_name":"Nayapally",
    "ks:ks_pop":150,
    "ks:ks_type":"VILLAGE",
    "name:eng_x_preferred":[
        "Nayapally"
    ],
    "wof:name":"Nayapally",
    "wof:placetype":"locality",
    "wof:population":150
},
  "geometry": {"coordinates":[85.403189,20.158871],"type":"Point"}
}