{
  "type": "Feature",
  "properties": {
    "iso:country":"IN",
    "ks:ks_alt_nam":"Marhi Kachhar ryt",
    "ks:ks_name":"Marhi Kachhar Ryt",
    "ks:ks_pop":63,
    "ks:ks_type":"HABITATION",
    "name:eng_x_preferred":[
        "Marhi Kachhar Ryt"
    ],
    "wof:name":"Marhi Kachhar Ryt",
    "wof:placetype":"locality",
    "wof:population":63
},
  "geometry": {"coordinates":[80.62538499999999,22.958236],"type":"Point"}
}