{
  "type": "Feature",
  "properties": {
    "gn:admin1_code":"36.0",
    "gn:admin2_code":"189.0",
    "gn:asciiname":"Deoria",
    "gn:country_code":"IN",
    "gn:dem":79,
    "gn:feature_class":"P",
    "gn:feature_code":"PPL",
    "gn:name":"Deori\u0101",
    "gn:population":0,
    "gn:timezone":"Asia/Kolkata",
    "iso:country":"IN",
    "name:ceb_x_preferred":[
        "Deoria"
    ],
    "name:nld_x_preferred":[
        "Deoria"
    ],
    "name:pol_x_preferred":[
        "Deoria"
    ],
    "name:swe_x_preferred":[
        "Deoria"
    ],
    "wof:name":"Deoria",
    "wof:placetype":"locality"
},
  "geometry": {"coordinates":[84.05618,26.65153],"type":"Point"}
}