{
  "type": "Feature",
  "properties": {
    "iso:country":"IN",
    "ks:ks_name":"Dahisahi",
    "ks:ks_pop":113,
    "ks:ks_type":"VILLAGE",
    "name:eng_x_preferred":[
        "Dahisahi"
    ],
    "wof:name":"Dahisahi",
    "wof:placetype":"locality",
    "wof:population":113
},
  "geometry": {"coordinates":[86.581692,22.146132],"type":"Point"}
}