{
  "type": "Feature",
  "properties": {
    "iso:country":"IN",
    "ks:ks_name":"H C Pejamangur",
    "ks:ks_pop":110,
    "ks:ks_type":"HABITATION",
    "name:eng_x_preferred":[
        "H C Pejamangur"
    ],
    "wof:name":"H C Pejamangur",
    "wof:placetype":"locality",
    "wof:population":110
},
  "geometry": {"coordinates":[74.84388199999999,13.454639],"type":"Point"}
}