{
  "type": "Feature",
  "properties": {
    "gn:admin1_code":"37.0",
    "gn:admin2_code":"403.0",
    "gn:asciiname":"Kapu",
    "gn:country_code":"IN",
    "gn:dem":567,
    "gn:feature_class":"P",
    "gn:feature_code":"PPL",
    "gn:name":"Kapu",
    "gn:population":0,
    "gn:timezone":"Asia/Kolkata",
    "iso:country":"IN",
    "name:ara_x_preferred":[
        "\u0643\u0627\u0628\u0648"
    ],
    "name:deu_x_preferred":[
        "Tapu"
    ],
    "name:eus_x_preferred":[
        "Kapu"
    ],
    "name:ind_x_preferred":[
        "Kapu"
    ],
    "name:nld_x_preferred":[
        "Kapu"
    ],
    "name:spa_x_preferred":[
        "Kapu"
    ],
    "name:swe_x_preferred":[
        "Kapu"
    ],
    "wof:name":"Kapu",
    "wof:placetype":"locality"
},
  "geometry": {"coordinates":[83.33898000000001,22.66956],"type":"Point"}
}