{
  "type": "Feature",
  "properties": {
    "iso:country":"IN",
    "ks:ks_name":"Harishankarpur",
    "ks:ks_pop":246,
    "ks:ks_type":"VILLAGE",
    "name:eng_x_preferred":[
        "Harishankarpur"
    ],
    "wof:name":"Harishankarpur",
    "wof:placetype":"locality",
    "wof:population":246
},
  "geometry": {"coordinates":[85.10180099999999,26.080312],"type":"Point"}
}