{
  "type": "Feature",
  "properties": {
    "iso:country":"IN",
    "ks:ks_name":"Dob",
    "ks:ks_pop":1935,
    "ks:ks_type":"VILLAGE",
    "name:eng_x_preferred":[
        "Dob"
    ],
    "wof:name":"Dob",
    "wof:placetype":"locality",
    "wof:population":1935
},
  "geometry": {"coordinates":[77.747212,22.971617],"type":"Point"}
}