{
  "type": "Feature",
  "properties": {
    "gn:admin1_code":"28.0",
    "gn:admin2_code":"343",
    "gn:asciiname":"Dhamnagar",
    "gn:country_code":"IN",
    "gn:dem":9,
    "gn:feature_class":"P",
    "gn:feature_code":"PPL",
    "gn:name":"Dh\u0101mnagar",
    "gn:population":0,
    "gn:timezone":"Asia/Kolkata",
    "iso:country":"IN",
    "name:ori_x_preferred":[
        "\u0b27\u0b3e\u0b2e\u0b28\u0b17\u0b30"
    ],
    "wof:name":"Dhamnagar",
    "wof:placetype":"locality"
},
  "geometry": {"coordinates":[88.41059,22.36799],"type":"Point"}
}