{
  "type": "Feature",
  "properties": {
    "iso:country":"IN",
    "ks:ks_name":"Jharna Tola",
    "ks:ks_pop":199,
    "ks:ks_type":"HABITATION",
    "name:eng_x_preferred":[
        "Jharna Tola"
    ],
    "wof:name":"Jharna Tola",
    "wof:placetype":"locality",
    "wof:population":199
},
  "geometry": {"coordinates":[86.54369699999999,24.955699],"type":"Point"}
}