{
  "type": "Feature",
  "properties": {
    "iso:country":"IN",
    "ks:ks_name":"Umsharkow",
    "ks:ks_pop":92,
    "ks:ks_type":"HABITATION",
    "name:eng_x_preferred":[
        "Umsharkow"
    ],
    "wof:name":"Umsharkow",
    "wof:placetype":"locality",
    "wof:population":92
},
  "geometry": {"coordinates":[91.634562,25.934147],"type":"Point"}
}