{
  "type": "Feature",
  "properties": {
    "iso:country":"IN",
    "ks:ks_name":"Dariyapur",
    "ks:ks_pop":145,
    "ks:ks_type":"VILLAGE",
    "name:eng_x_preferred":[
        "Dariyapur"
    ],
    "wof:name":"Dariyapur",
    "wof:placetype":"locality",
    "wof:population":145
},
  "geometry": {"coordinates":[77.358801,23.747742],"type":"Point"}
}