{
  "type": "Feature",
  "properties": {
    "iso:country":"IN",
    "ks:ks_name":"Ragunathpura",
    "ks:ks_pop":451,
    "ks:ks_type":"HABITATION",
    "name:eng_x_preferred":[
        "Ragunathpura"
    ],
    "wof:name":"Ragunathpura",
    "wof:placetype":"locality",
    "wof:population":451
},
  "geometry": {"coordinates":[72.384275,26.246917],"type":"Point"}
}