{
  "type": "Feature",
  "properties": {
    "gn:admin1_code":"37",
    "gn:admin2_code":"413.0",
    "gn:asciiname":"Rawas",
    "gn:country_code":"IN",
    "gn:dem":650,
    "gn:feature_class":"P",
    "gn:feature_code":"PPL",
    "gn:name":"R\u0101was",
    "gn:population":0,
    "gn:timezone":"Asia/Kolkata",
    "iso:country":"IN",
    "ks:ks_alt_nam":"R\u0101was",
    "ks:ks_name":"Rawas",
    "ks:ks_pop":542,
    "ks:ks_type":"VILLAGE",
    "name:eng_x_preferred":[
        "Rawas"
    ],
    "name:eng_x_variant":[
        "R\u0101was"
    ],
    "wof:name":"Rawas",
    "wof:placetype":"locality",
    "wof:population":542
},
  "geometry": {"coordinates":[81.676967,20.134557],"type":"Point"}
}