{
  "type": "Feature",
  "properties": {
    "iso:country":"IN",
    "ks:ks_name":"Valotha",
    "ks:ks_pop":234,
    "ks:ks_type":"VILLAGE",
    "name:eng_x_preferred":[
        "Valotha"
    ],
    "wof:name":"Valotha",
    "wof:placetype":"locality",
    "wof:population":234
},
  "geometry": {"coordinates":[73.49119399999999,20.995389],"type":"Point"}
}