{
  "type": "Feature",
  "properties": {
    "gn:admin1_code":"36",
    "gn:admin2_code":"201.0",
    "gn:asciiname":"Hari Singhpur",
    "gn:country_code":"IN",
    "gn:dem":172,
    "gn:feature_class":"P",
    "gn:feature_code":"PPL",
    "gn:name":"Hari Singhpur",
    "gn:population":0,
    "gn:timezone":"Asia/Kolkata",
    "iso:country":"IN",
    "ks:ks_name":"Harsinghpur",
    "ks:ks_pop":188,
    "ks:ks_type":"HABITATION",
    "name:eng_x_preferred":[
        "Harsinghpur"
    ],
    "name:eng_x_variant":[
        "Hari Singhpur"
    ],
    "wof:name":"Harsinghpur",
    "wof:placetype":"locality",
    "wof:population":188
},
  "geometry": {"coordinates":[78.613179,27.532341],"type":"Point"}
}