{
  "type": "Feature",
  "properties": {
    "iso:country":"IN",
    "ks:ks_name":"Pholriwal",
    "ks:ks_pop":3129,
    "ks:ks_type":"VILLAGE",
    "ks:ks_uagg_main":0,
    "name:eng_x_preferred":[
        "Pholriwal"
    ],
    "wof:name":"Pholriwal",
    "wof:placetype":"locality",
    "wof:population":3129
},
  "geometry": {"coordinates":[75.592721,31.265552],"type":"Point"}
}