{
  "type": "Feature",
  "properties": {
    "iso:country":"IN",
    "ks:ks_alt_nam":"BUIYABASA",
    "ks:ks_name":"Buiyabasa",
    "ks:ks_pop":345,
    "ks:ks_type":"HABITATION",
    "name:eng_x_preferred":[
        "Buiyabasa"
    ],
    "wof:name":"Buiyabasa",
    "wof:placetype":"locality",
    "wof:population":345
},
  "geometry": {"coordinates":[85.73987,22.540313],"type":"Point"}
}