{
  "type": "Feature",
  "properties": {
    "gn:admin1_code":"34.0",
    "gn:admin2_code":"217.0",
    "gn:asciiname":"Sakla",
    "gn:country_code":"IN",
    "gn:dem":66,
    "gn:feature_class":"P",
    "gn:feature_code":"PPL",
    "gn:name":"Sakla",
    "gn:population":0,
    "gn:timezone":"Asia/Kolkata",
    "iso:country":"IN",
    "name:deu_x_preferred":[
        "Sakla"
    ],
    "name:est_x_preferred":[
        "Sakla"
    ],
    "name:vol_x_preferred":[
        "Sakla"
    ],
    "wof:name":"Sakla",
    "wof:placetype":"locality"
},
  "geometry": {"coordinates":[84.65468,26.31403],"type":"Point"}
}