{
  "type": "Feature",
  "properties": {
    "iso:country":"IN",
    "ks:ks_name":"Shyam Pur",
    "ks:ks_pop":171,
    "ks:ks_type":"VILLAGE",
    "name:eng_x_preferred":[
        "Shyam Pur"
    ],
    "wof:name":"Shyam Pur",
    "wof:placetype":"locality",
    "wof:population":171
},
  "geometry": {"coordinates":[87.181639,22.933433],"type":"Point"}
}