{
  "type": "Feature",
  "properties": {
    "iso:country":"IN",
    "ks:ks_name":"Bikrampur",
    "ks:ks_pop":1464,
    "ks:ks_type":"VILLAGE",
    "name:eng_x_preferred":[
        "Bikrampur"
    ],
    "wof:name":"Bikrampur",
    "wof:placetype":"locality",
    "wof:population":1464
},
  "geometry": {"coordinates":[87.15010599999999,23.169381],"type":"Point"}
}