{
  "type": "Feature",
  "properties": {
    "iso:country":"IN",
    "ks:ks_name":"Jamuguda",
    "ks:ks_pop":659,
    "ks:ks_type":"VILLAGE",
    "name:eng_x_preferred":[
        "Jamuguda"
    ],
    "wof:name":"Jamuguda",
    "wof:placetype":"locality",
    "wof:population":659
},
  "geometry": {"coordinates":[83.880431,19.082153],"type":"Point"}
}