{
  "type": "Feature",
  "properties": {
    "iso:country":"IN",
    "ks:ks_name":"Kaveripalya",
    "ks:ks_pop":172,
    "ks:ks_type":"HABITATION",
    "name:eng_x_preferred":[
        "Kaveripalya"
    ],
    "wof:name":"Kaveripalya",
    "wof:placetype":"locality",
    "wof:population":172
},
  "geometry": {"coordinates":[77.082458,13.111995],"type":"Point"}
}