{
  "type": "Feature",
  "properties": {
    "gn:admin1_code":"24.0",
    "gn:admin2_code":"119.0",
    "gn:asciiname":"Hanwantia",
    "gn:country_code":"IN",
    "gn:dem":391,
    "gn:feature_class":"P",
    "gn:feature_code":"PPL",
    "gn:name":"Hanwantia",
    "gn:population":0,
    "gn:timezone":"Asia/Kolkata",
    "iso:country":"IN",
    "wof:name":"Hanwantia",
    "wof:placetype":"locality"
},
  "geometry": {"coordinates":[74.80726999999997,26.20081],"type":"Point"}
}