{
  "type": "Feature",
  "properties": {
    "gn:admin1_code":"35.0",
    "gn:admin2_code":"451.0",
    "gn:asciiname":"Deori",
    "gn:country_code":"IN",
    "gn:dem":388,
    "gn:feature_class":"P",
    "gn:feature_code":"PPL",
    "gn:name":"Deor\u012b",
    "gn:population":0,
    "gn:timezone":"Asia/Kolkata",
    "iso:country":"IN",
    "name:cat_x_preferred":[
        "Deori"
    ],
    "name:ceb_x_preferred":[
        "Deori"
    ],
    "name:por_x_preferred":[
        "Deori"
    ],
    "name:swe_x_preferred":[
        "Deori"
    ],
    "wof:name":"Deori",
    "wof:placetype":"neighbourhood"
},
  "geometry": {"coordinates":[80.00442,23.29763],"type":"Point"}
}