{
  "type": "Feature",
  "properties": {
    "iso:country":"IN",
    "ks:ks_name":"Muthuramalingapuram",
    "ks:ks_pop":120,
    "ks:ks_type":"HABITATION",
    "name:eng_x_preferred":[
        "Muthuramalingapuram"
    ],
    "wof:name":"Muthuramalingapuram",
    "wof:placetype":"locality",
    "wof:population":120
},
  "geometry": {"coordinates":[78.337637,9.143044],"type":"Point"}
}