{
  "type": "Feature",
  "properties": {
    "iso:country":"IN",
    "ks:ks_alt_nam":"KEKARDIPA",
    "ks:ks_name":"Kekardipa",
    "ks:ks_pop":193,
    "ks:ks_type":"HABITATION",
    "name:eng_x_preferred":[
        "Kekardipa"
    ],
    "wof:name":"Kekardipa",
    "wof:placetype":"locality",
    "wof:population":193
},
  "geometry": {"coordinates":[83.62514299999999,22.973498],"type":"Point"}
}