{
  "type": "Feature",
  "properties": {
    "iso:country":"IN",
    "ks:ks_name":"Surabhi Vaddepalli",
    "ks:ks_pop":173,
    "ks:ks_type":"HABITATION",
    "name:eng_x_preferred":[
        "Surabhi Vaddepalli"
    ],
    "wof:name":"Surabhi Vaddepalli",
    "wof:placetype":"locality",
    "wof:population":173
},
  "geometry": {"coordinates":[78.595133,14.213286],"type":"Point"}
}