{
  "type": "Feature",
  "properties": {
    "iso:country":"IN",
    "ks:ks_name":"Ajroli Daulji",
    "ks:ks_pop":129,
    "ks:ks_type":"HABITATION",
    "name:eng_x_preferred":[
        "Ajroli Daulji"
    ],
    "wof:name":"Ajroli Daulji",
    "wof:placetype":"locality",
    "wof:population":129
},
  "geometry": {"coordinates":[73.308285,24.287076],"type":"Point"}
}