{
  "type": "Feature",
  "properties": {
    "gn:admin1_code":"35.0",
    "gn:admin2_code":"455.0",
    "gn:asciiname":"Chaurai",
    "gn:country_code":"IN",
    "gn:dem":700,
    "gn:feature_class":"P",
    "gn:feature_code":"PPL",
    "gn:name":"Chaurai",
    "gn:population":0,
    "gn:timezone":"Asia/Kolkata",
    "iso:country":"IN",
    "ks:ks_name":"Chourai",
    "ks:ks_pop":831,
    "ks:ks_type":"VILLAGE",
    "name:eng_x_preferred":[
        "Chourai"
    ],
    "name:eng_x_variant":[
        "Chaurai"
    ],
    "wof:name":"Chourai",
    "wof:placetype":"locality",
    "wof:population":831
},
  "geometry": {"coordinates":[78.533691,21.964526],"type":"Point"}
}