{
  "type": "Feature",
  "properties": {
    "iso:country":"IN",
    "ks:ks_name":"Manjuriguda",
    "ks:ks_pop":154,
    "ks:ks_type":"HABITATION",
    "name:eng_x_preferred":[
        "Manjuriguda"
    ],
    "wof:name":"Manjuriguda",
    "wof:placetype":"locality",
    "wof:population":154
},
  "geometry": {"coordinates":[82.086438,18.578071],"type":"Point"}
}