{
  "type": "Feature",
  "properties": {
    "iso:country":"IN",
    "ks:ks_name":"Bhaloo Udainagar",
    "ks:ks_pop":711,
    "ks:ks_type":"VILLAGE",
    "name:eng_x_preferred":[
        "Bhaloo Udainagar"
    ],
    "wof:name":"Bhaloo Udainagar",
    "wof:placetype":"locality",
    "wof:population":711
},
  "geometry": {"coordinates":[72.48377499999999,26.545008],"type":"Point"}
}