{
  "type": "Feature",
  "properties": {
    "iso:country":"IN",
    "ks:ks_name":"Puania",
    "ks:ks_pop":643,
    "ks:ks_type":"VILLAGE",
    "ks:ks_uagg_main":0,
    "name:eng_x_preferred":[
        "Puania"
    ],
    "wof:name":"Puania",
    "wof:placetype":"neighbourhood",
    "wof:population":643
},
  "geometry": {"coordinates":[85.377358,20.202102],"type":"Point"}
}