{
  "type": "Feature",
  "properties": {
    "iso:country":"IN",
    "ks:ks_name":"Bachhera Khera",
    "ks:ks_pop":537,
    "ks:ks_type":"VILLAGE",
    "name:eng_x_preferred":[
        "Bachhera Khera"
    ],
    "wof:name":"Bachhera Khera",
    "wof:placetype":"locality",
    "wof:population":537
},
  "geometry": {"coordinates":[80.423396,25.185956],"type":"Point"}
}