{
  "type": "Feature",
  "properties": {
    "iso:country":"IN",
    "ks:ks_alt_nam":"JHAGARPUR",
    "ks:ks_name":"Jhagarpur",
    "ks:ks_pop":158,
    "ks:ks_type":"HABITATION",
    "name:eng_x_preferred":[
        "Jhagarpur"
    ],
    "wof:name":"Jhagarpur",
    "wof:placetype":"locality",
    "wof:population":158
},
  "geometry": {"coordinates":[83.948531,22.653117],"type":"Point"}
}