{
  "type": "Feature",
  "properties": {
    "iso:country":"IN",
    "ks:ks_name":"Khurdan",
    "ks:ks_pop":464,
    "ks:ks_type":"VILLAGE",
    "ks:ks_uagg_main":0,
    "name:eng_x_preferred":[
        "Khurdan"
    ],
    "wof:name":"Khurdan",
    "wof:placetype":"neighbourhood",
    "wof:population":464
},
  "geometry": {"coordinates":[76.298265,31.146057],"type":"Point"}
}