{
  "type": "Feature",
  "properties": {
    "iso:country":"IN",
    "ks:ks_name":"Ucalapani",
    "ks:ks_pop":405,
    "ks:ks_type":"HABITATION",
    "name:eng_x_preferred":[
        "Ucalapani"
    ],
    "wof:name":"Ucalapani",
    "wof:placetype":"locality",
    "wof:population":405
},
  "geometry": {"coordinates":[73.817932,21.039889],"type":"Point"}
}