{
  "type": "Feature",
  "properties": {
    "iso:country":"IN",
    "ks:ks_name":"Gadkhet",
    "ks:ks_pop":11,
    "ks:ks_type":"HABITATION",
    "name:eng_x_preferred":[
        "Gadkhet"
    ],
    "wof:name":"Gadkhet",
    "wof:placetype":"locality",
    "wof:population":11
},
  "geometry": {"coordinates":[79.10016,29.919751],"type":"Point"}
}