{
  "type": "Feature",
  "properties": {
    "iso:country":"IN",
    "ks:ks_name":"Gopalpur Ramkishun",
    "ks:ks_pop":1603,
    "ks:ks_type":"VILLAGE",
    "name:eng_x_preferred":[
        "Gopalpur Ramkishun"
    ],
    "wof:name":"Gopalpur Ramkishun",
    "wof:placetype":"locality",
    "wof:population":1603
},
  "geometry": {"coordinates":[85.74292800000001,25.759969],"type":"Point"}
}