{
  "type": "Feature",
  "properties": {
    "iso:country":"IN",
    "ks:ks_name":"Shahpur Buzurg",
    "ks:ks_pop":279,
    "ks:ks_type":"VILLAGE",
    "ks:ks_uagg_main":0,
    "name:eng_x_preferred":[
        "Shahpur Buzurg"
    ],
    "wof:name":"Shahpur Buzurg",
    "wof:placetype":"neighbourhood",
    "wof:population":279
},
  "geometry": {"coordinates":[79.160903,25.782554],"type":"Point"}
}