{
  "type": "Feature",
  "properties": {
    "iso:country":"IN",
    "ks:ks_alt_nam":"JOGI DIH",
    "ks:ks_name":"Jogi Dih",
    "ks:ks_pop":1336,
    "ks:ks_type":"HABITATION",
    "ks:ks_uagg_main":0,
    "name:eng_x_preferred":[
        "Jogi Dih"
    ],
    "wof:name":"Jogi Dih",
    "wof:placetype":"neighbourhood",
    "wof:population":1336
},
  "geometry": {"coordinates":[86.051438,25.709129],"type":"Point"}
}