{
  "type": "Feature",
  "properties": {
    "iso:country":"IN",
    "ks:ks_name":"Vanewadi",
    "ks:ks_pop":92,
    "ks:ks_type":"HABITATION",
    "name:eng_x_preferred":[
        "Vanewadi"
    ],
    "wof:name":"Vanewadi",
    "wof:placetype":"locality",
    "wof:population":92
},
  "geometry": {"coordinates":[73.242778,17.350556],"type":"Point"}
}