{
  "type": "Feature",
  "properties": {
    "iso:country":"IN",
    "ks:ks_name":"Bar Kaunri Chak",
    "ks:ks_pop":55,
    "ks:ks_type":"VILLAGE",
    "name:eng_x_preferred":[
        "Bar Kaunri Chak"
    ],
    "wof:name":"Bar Kaunri Chak",
    "wof:placetype":"locality",
    "wof:population":55
},
  "geometry": {"coordinates":[87.489149,22.630542],"type":"Point"}
}