{
  "type": "Feature",
  "properties": {
    "iso:country":"IN",
    "ks:ks_name":"Murkal",
    "ks:ks_pop":11,
    "ks:ks_type":"HABITATION",
    "name:eng_x_preferred":[
        "Murkal"
    ],
    "wof:name":"Murkal",
    "wof:placetype":"locality",
    "wof:population":11
},
  "geometry": {"coordinates":[76.06999999999999,12.116944],"type":"Point"}
}