{
  "type": "Feature",
  "properties": {
    "iso:country":"IN",
    "ks:ks_name":"Malyan",
    "ks:ks_pop":157,
    "ks:ks_type":"VILLAGE",
    "name:eng_x_preferred":[
        "Malyan"
    ],
    "wof:name":"Malyan",
    "wof:placetype":"locality",
    "wof:population":157
},
  "geometry": {"coordinates":[87.530666,22.465822],"type":"Point"}
}