{
  "type": "Feature",
  "properties": {
    "gn:admin1_code":"16.0",
    "gn:admin2_code":"504.0",
    "gn:asciiname":"Malegaon",
    "gn:country_code":"IN",
    "gn:dem":482,
    "gn:feature_class":"P",
    "gn:feature_code":"PPL",
    "gn:name":"M\u0101legaon",
    "gn:population":0,
    "gn:timezone":"Asia/Kolkata",
    "iso:country":"IN",
    "name:ara_x_preferred":[
        "\u0645\u0627\u0644\u064a\u063a\u0627\u0624\u0646"
    ],
    "name:azb_x_preferred":[
        "\u0645\u0627\u0644\u0647\u0642\u0648\u0627\u0646"
    ],
    "name:ben_x_preferred":[
        "\u09ae\u09be\u09b2\u09c7\u0997\u09be\u0981\u0993"
    ],
    "name:bih_x_preferred":[
        "\u092e\u093e\u0932\u0947\u0917\u093e\u0901\u0935"
    ],
    "name:bpy_x_preferred":[
        "\u09ae\u09be\u09b2\u09c7\u0997\u09be\u0981\u0993"
    ],
    "name:cat_x_preferred":[
        "Malegaon"
    ],
    "name:ceb_x_preferred":[
        "M\u0101legaon"
    ],
    "name:deu_x_preferred":[
        "Malegaon"
    ],
    "name:fas_x_preferred":[
        "\u0645\u0627\u0644\u0647\u200c\u06af\u0648\u0627\u0646"
    ],
    "name:fra_x_preferred":[
        "Malegaon"
    ],
    "name:guj_x_preferred":[
        "\u0aae\u0abe\u0ab2\u0ac7\u0a97\u0abe\u0a82\u0ab5"
    ],
    "name:hif_x_preferred":[
        "Malegaon"
    ],
    "name:hin_x_preferred":[
        "\u092e\u093e\u0932\u0947\u0917\u093e\u0902\u0935"
    ],
    "name:ita_x_preferred":[
        "Malegaon"
    ],
    "name:jpn_x_preferred":[
        "\u30de\u30fc\u30ec\u30fc\u30ac\u30fc\u30aa\u30f3"
    ],
    "name:mal_x_preferred":[
        "\u0d2e\u0d3e\u0d32\u0d47\u0d17\u0d3e\u0d35\u0d4d"
    ],
    "name:mar_x_preferred":[
        "\u092e\u093e\u0932\u0947\u0917\u093e\u0935"
    ],
    "name:mlg_x_preferred":[
        "Malegaon"
    ],
    "name:msa_x_preferred":[
        "Malegaon"
    ],
    "name:nep_x_preferred":[
        "\u092e\u093e\u0932\u0947\u0917\u093e\u0902\u0935"
    ],
    "name:new_x_preferred":[
        "\u092e\u093e\u0932\u0947\u0917\u093e\u0902\u0935"
    ],
    "name:nld_x_preferred":[
        "Malegaon"
    ],
    "name:nor_x_preferred":[
        "Malegaon"
    ],
    "name:ori_x_preferred":[
        "\u0b2e\u0b3e\u0b32\u0b47\u0b17\u0b3e\u0b13\u0b01"
    ],
    "name:pnb_x_preferred":[
        "\u0645\u0627\u0644\u06cc\u06af\u0627\u0624\u06ba"
    ],
    "name:pol_x_preferred":[
        "Malegaon"
    ],
    "name:por_x_preferred":[
        "Malegaon"
    ],
    "name:pus_x_preferred":[
        "\u0645\u0627\u0644\u064a\u06af\u0627\u0648"
    ],
    "name:srp_x_preferred":[
        "\u041c\u0430\u043b\u0435\u0433\u0430\u043e\u043d"
    ],
    "name:swe_x_preferred":[
        "Malegaon"
    ],
    "name:tam_x_preferred":[
        "\u0bae\u0bbe\u0bb2\u0bc7\u0b95\u0bbe\u0ba9\u0bcd"
    ],
    "name:urd_x_preferred":[
        "\u0645\u0627\u0644\u06cc\u06af\u0627\u0624\u06ba"
    ],
    "name:vie_x_preferred":[
        "Malegaon"
    ],
    "name:war_x_preferred":[
        "Malegaon"
    ],
    "name:zho_x_preferred":[
        "\u99ac\u840a\u5ca1"
    ],
    "wof:name":"Malegaon",
    "wof:placetype":"locality"
},
  "geometry": {"coordinates":[78.29000000000001,21.1035],"type":"Point"}
}