{
  "type": "Feature",
  "properties": {
    "gn:admin1_code":"16.0",
    "gn:admin2_code":"504.0",
    "gn:asciiname":"Malegaon",
    "gn:country_code":"IN",
    "gn:dem":482,
    "gn:feature_class":"P",
    "gn:feature_code":"PPL",
    "gn:name":"M\u0101legaon",
    "gn:population":0,
    "gn:timezone":"Asia/Kolkata",
    "iso:country":"IN",
    "wof:name":"Malegaon",
    "wof:placetype":"locality"
},
  "geometry": {"coordinates":[78.29000000000001,21.1035],"type":"Point"}
}