{
  "type": "Feature",
  "properties": {
    "iso:country":"IN",
    "ks:ks_name":"Nirappam",
    "ks:ks_pop":485,
    "ks:ks_type":"HABITATION",
    "ks:ks_uagg_main":0,
    "name:eng_x_preferred":[
        "Nirappam"
    ],
    "wof:name":"Nirappam",
    "wof:placetype":"neighbourhood",
    "wof:population":485
},
  "geometry": {"coordinates":[76.31712400000001,11.665342],"type":"Point"}
}