{
  "type": "Feature",
  "properties": {
    "gn:admin1_code":"35",
    "gn:admin2_code":"419.0",
    "gn:asciiname":"Devkhori",
    "gn:country_code":"IN",
    "gn:dem":208,
    "gn:feature_class":"P",
    "gn:feature_code":"PPL",
    "gn:name":"Devkhori",
    "gn:population":0,
    "gn:timezone":"Asia/Kolkata",
    "iso:country":"IN",
    "ks:ks_name":"Devkhori",
    "ks:ks_type":"VILLAGE",
    "name:eng_x_preferred":[
        "Devkhori"
    ],
    "wof:name":"Devkhori",
    "wof:placetype":"locality"
},
  "geometry": {"coordinates":[77.56589700000001,26.167432],"type":"Point"}
}