{
  "type": "Feature",
  "properties": {
    "iso:country":"IN",
    "ks:ks_name":"Paradhwadi",
    "ks:ks_pop":123,
    "ks:ks_type":"HABITATION",
    "name:eng_x_preferred":[
        "Paradhwadi"
    ],
    "wof:name":"Paradhwadi",
    "wof:placetype":"locality",
    "wof:population":123
},
  "geometry": {"coordinates":[73.495411,19.663868],"type":"Point"}
}