{
  "type": "Feature",
  "properties": {
    "gn:admin1_code":"24.0",
    "gn:admin2_code":"99.0",
    "gn:asciiname":"Khat",
    "gn:country_code":"IN",
    "gn:dem":181,
    "gn:feature_class":"P",
    "gn:feature_code":"PPL",
    "gn:name":"Kh\u0101t",
    "gn:population":0,
    "gn:timezone":"Asia/Kolkata",
    "iso:country":"IN",
    "wof:name":"Khat",
    "wof:placetype":"locality"
},
  "geometry": {"coordinates":[74.12448000000001,29.87512000000001],"type":"Point"}
}