{
  "type": "Feature",
  "properties": {
    "gn:admin1_code":"23.0",
    "gn:admin2_code":"46.0",
    "gn:asciiname":"Kot Guru",
    "gn:country_code":"IN",
    "gn:dem":201,
    "gn:feature_class":"P",
    "gn:feature_code":"PPL",
    "gn:name":"Kot Gur\u016b",
    "gn:population":0,
    "gn:timezone":"Asia/Kolkata",
    "iso:country":"IN",
    "name:und_x_variant":[
        "Kot Gur\u016b",
        "Gur\u016bke"
    ],
    "wof:name":"Kot Guru",
    "wof:placetype":"locality"
},
  "geometry": {"coordinates":[74.81395999999999,30.09707],"type":"Point"}
}