{
  "type": "Feature",
  "properties": {
    "iso:country":"IN",
    "ks:ks_name":"Thakrewasti",
    "ks:ks_pop":156,
    "ks:ks_type":"HABITATION",
    "name:eng_x_preferred":[
        "Thakrewasti"
    ],
    "wof:name":"Thakrewasti",
    "wof:placetype":"locality",
    "wof:population":156
},
  "geometry": {"coordinates":[74.123643,18.374958],"type":"Point"}
}