{
  "type": "Feature",
  "properties": {
    "gn:admin1_code":"36.0",
    "gn:admin2_code":"168.0",
    "gn:asciiname":"Bhilawan",
    "gn:country_code":"IN",
    "gn:dem":110,
    "gn:feature_class":"P",
    "gn:feature_code":"PPL",
    "gn:name":"Bhil\u0101w\u0101n",
    "gn:population":0,
    "gn:timezone":"Asia/Kolkata",
    "iso:country":"IN",
    "wof:name":"Bhilawan",
    "wof:placetype":"locality"
},
  "geometry": {"coordinates":[80.16011999999998,25.95468],"type":"Point"}
}