{
  "type": "Feature",
  "properties": {
    "gn:admin1_code":"36",
    "gn:admin2_code":"191.0",
    "gn:asciiname":"Tondarpur",
    "gn:country_code":"IN",
    "gn:dem":78,
    "gn:feature_class":"P",
    "gn:feature_code":"PPL",
    "gn:name":"Tondarpur",
    "gn:population":0,
    "gn:timezone":"Asia/Kolkata",
    "iso:country":"IN",
    "ks:ks_name":"Tondarpur",
    "ks:ks_type":"VILLAGE",
    "name:eng_x_preferred":[
        "Tondarpur"
    ],
    "wof:name":"Tondarpur",
    "wof:placetype":"locality"
},
  "geometry": {"coordinates":[83.17807999999999,25.818252],"type":"Point"}
}