{
  "type": "Feature",
  "properties": {
    "gn:admin1_code":"34.0",
    "gn:admin2_code":"236.0",
    "gn:asciiname":"Karai",
    "gn:country_code":"IN",
    "gn:dem":100,
    "gn:feature_class":"P",
    "gn:feature_code":"PPL",
    "gn:name":"Karai",
    "gn:population":0,
    "gn:timezone":"Asia/Kolkata",
    "iso:country":"IN",
    "name:ceb_x_preferred":[
        "Karai"
    ],
    "name:deu_x_preferred":[
        "Karai"
    ],
    "name:fra_x_preferred":[
        "Karai"
    ],
    "wof:name":"Karai",
    "wof:placetype":"locality"
},
  "geometry": {"coordinates":[84.72063,24.90958],"type":"Point"}
}