{
  "type": "Feature",
  "properties": {
    "gn:admin1_code":"16",
    "gn:admin2_code":"510.0",
    "gn:asciiname":"Digdoh",
    "gn:country_code":"IN",
    "gn:dem":240,
    "gn:feature_class":"P",
    "gn:feature_code":"PPL",
    "gn:name":"Digdoh",
    "gn:population":0,
    "gn:timezone":"Asia/Kolkata",
    "iso:country":"IN",
    "name:ben_x_preferred":[
        "\u09a6\u09bf\u0997\u09a6\u09cb\u09b9"
    ],
    "name:bpy_x_preferred":[
        "\u09a6\u09bf\u0997\u09a6\u09cb\u09b9"
    ],
    "name:ind_x_preferred":[
        "Digdoh"
    ],
    "name:ita_x_preferred":[
        "Digdoh"
    ],
    "name:msa_x_preferred":[
        "Digdoh"
    ],
    "name:new_x_preferred":[
        "\u0926\u093f\u0917\u094d\u0926\u094b\u0939"
    ],
    "name:nld_x_preferred":[
        "Digdoh"
    ],
    "name:por_x_preferred":[
        "Digdoh"
    ],
    "name:urd_x_preferred":[
        "\u062f\u06af\u062f\u0648\u06c1"
    ],
    "name:vie_x_preferred":[
        "Digdoh"
    ],
    "name:zho_x_preferred":[
        "\u8fea\u683c\u591a"
    ],
    "wof:name":"Digdoh",
    "wof:placetype":"locality"
},
  "geometry": {"coordinates":[78.71436,20.22281],"type":"Point"}
}