{
  "type": "Feature",
  "properties": {
    "iso:country":"IN",
    "ks:ks_alt_nam":"Marp\u0101",
    "ks:ks_name":"Marpa",
    "ks:ks_pop":297,
    "ks:ks_type":"VILLAGE",
    "name:eng_x_preferred":[
        "Marpa"
    ],
    "name:eng_x_variant":[
        "Marp\u0101"
    ],
    "wof:name":"Marpa",
    "wof:placetype":"locality",
    "wof:population":297
},
  "geometry": {"coordinates":[85.51099499999999,24.132497],"type":"Point"}
}