{
  "type": "Feature",
  "properties": {
    "iso:country":"IN",
    "ks:ks_name":"Markuta",
    "ks:ks_pop":264,
    "ks:ks_type":"HABITATION",
    "ks:ks_uagg_main":0,
    "name:eng_x_preferred":[
        "Markuta"
    ],
    "wof:name":"Markuta",
    "wof:placetype":"neighbourhood",
    "wof:population":264
},
  "geometry": {"coordinates":[81.048558,27.753377],"type":"Point"}
}