{
  "type": "Feature",
  "properties": {
    "gn:admin1_code":"34.0",
    "gn:admin2_code":"216.0",
    "gn:asciiname":"Muhammadpur Bhopat",
    "gn:country_code":"IN",
    "gn:dem":54,
    "gn:feature_class":"P",
    "gn:feature_code":"PPL",
    "gn:name":"Muhammadpur Bhopat",
    "gn:population":0,
    "gn:timezone":"Asia/Kolkata",
    "iso:country":"IN",
    "ks:ks_name":"Mahhamadpur Bhopat",
    "ks:ks_pop":2165,
    "ks:ks_type":"VILLAGE",
    "name:eng_x_preferred":[
        "Mahhamadpur Bhopat"
    ],
    "name:eng_x_variant":[
        "Muhammadpur Bhopat"
    ],
    "wof:name":"Mahhamadpur Bhopat",
    "wof:placetype":"locality",
    "wof:population":2165
},
  "geometry": {"coordinates":[85.491203,25.951271],"type":"Point"}
}