{
  "type": "Feature",
  "properties": {
    "iso:country":"IN",
    "ks:ks_name":"Ambatoli",
    "ks:ks_pop":598,
    "ks:ks_type":"HABITATION",
    "name:eng_x_preferred":[
        "Ambatoli"
    ],
    "wof:name":"Ambatoli",
    "wof:placetype":"locality",
    "wof:population":598
},
  "geometry": {"coordinates":[84.245881,22.793551],"type":"Point"}
}