{
  "type": "Feature",
  "properties": {
    "iso:country":"IN",
    "ks:ks_alt_nam":"Ram nagar",
    "ks:ks_name":"Ram Nagar",
    "ks:ks_pop":765,
    "ks:ks_type":"HABITATION",
    "name:eng_x_preferred":[
        "Ram Nagar"
    ],
    "wof:name":"Ram Nagar",
    "wof:placetype":"locality",
    "wof:population":765
},
  "geometry": {"coordinates":[72.773764,27.094167],"type":"Point"}
}