{
  "type": "Feature",
  "properties": {
    "iso:country":"IN",
    "ks:ks_name":"Jalalpur Basahiya",
    "ks:ks_pop":201,
    "ks:ks_type":"VILLAGE",
    "name:eng_x_preferred":[
        "Jalalpur Basahiya"
    ],
    "wof:name":"Jalalpur Basahiya",
    "wof:placetype":"locality",
    "wof:population":201
},
  "geometry": {"coordinates":[81.590988,27.260176],"type":"Point"}
}