{
  "type": "Feature",
  "properties": {
    "iso:country":"IN",
    "ks:ks_name":"Estate Labour Colony",
    "ks:ks_pop":400,
    "ks:ks_type":"HABITATION",
    "name:eng_x_preferred":[
        "Estate Labour Colony"
    ],
    "wof:name":"Estate Labour Colony",
    "wof:placetype":"locality",
    "wof:population":400
},
  "geometry": {"coordinates":[76.912735,9.167429],"type":"Point"}
}