{
  "type": "Feature",
  "properties": {
    "gn:admin1_code":"37",
    "gn:admin2_code":"407.0",
    "gn:asciiname":"Ladua",
    "gn:country_code":"IN",
    "gn:dem":358,
    "gn:feature_class":"P",
    "gn:feature_code":"PPL",
    "gn:name":"Ladua",
    "gn:population":0,
    "gn:timezone":"Asia/Kolkata",
    "iso:country":"IN",
    "wof:name":"Ladua",
    "wof:placetype":"locality"
},
  "geometry": {"coordinates":[81.36745000000001,22.22351],"type":"Point"}
}