{
  "type": "Feature",
  "properties": {
    "gn:admin1_code":"19.0",
    "gn:admin2_code":"574.0",
    "gn:asciiname":"Naganahalli",
    "gn:country_code":"IN",
    "gn:dem":922,
    "gn:feature_class":"P",
    "gn:feature_code":"PPL",
    "gn:name":"N\u0101ganahalli",
    "gn:population":0,
    "gn:timezone":"Asia/Kolkata",
    "iso:country":"IN",
    "ks:ks_name":"Naganahally",
    "ks:ks_pop":100,
    "ks:ks_type":"HABITATION",
    "name:eng_x_preferred":[
        "Naganahally"
    ],
    "name:eng_x_variant":[
        "Naganahalli"
    ],
    "wof:name":"Naganahally",
    "wof:placetype":"locality",
    "wof:population":100
},
  "geometry": {"coordinates":[76.555263,12.87321],"type":"Point"}
}