{
  "type": "Feature",
  "properties": {
    "iso:country":"IN",
    "ks:ks_name":"Pazhaya Lakkidi",
    "ks:ks_pop":1519,
    "ks:ks_type":"HABITATION",
    "ks:ks_uagg_main":0,
    "name:eng_x_preferred":[
        "Pazhaya Lakkidi"
    ],
    "wof:name":"Pazhaya Lakkidi",
    "wof:placetype":"locality",
    "wof:population":1519
},
  "geometry": {"coordinates":[76.451369,10.776105],"type":"Point"}
}