{
  "type": "Feature",
  "properties": {
    "gn:admin1_code":"35",
    "gn:admin2_code":"426.0",
    "gn:asciiname":"Nayegaon",
    "gn:country_code":"IN",
    "gn:dem":495,
    "gn:feature_class":"P",
    "gn:feature_code":"PPL",
    "gn:name":"Nayegaon",
    "gn:population":0,
    "gn:timezone":"Asia/Kolkata",
    "iso:country":"IN",
    "ks:ks_name":"Nayagaon",
    "ks:ks_pop":312,
    "ks:ks_type":"VILLAGE",
    "name:eng_x_preferred":[
        "Nayagaon"
    ],
    "name:eng_x_variant":[
        "Nayegaon"
    ],
    "wof:name":"Nayagaon",
    "wof:placetype":"locality",
    "wof:population":312
},
  "geometry": {"coordinates":[80.50290099999999,24.229839],"type":"Point"}
}