{
  "type": "Feature",
  "properties": {
    "iso:country":"IN",
    "ks:ks_name":"Babupur",
    "ks:ks_pop":216,
    "ks:ks_type":"VILLAGE",
    "name:eng_x_preferred":[
        "Babupur"
    ],
    "wof:name":"Babupur",
    "wof:placetype":"locality",
    "wof:population":216
},
  "geometry": {"coordinates":[86.91325500000001,24.519012],"type":"Point"}
}