{
  "type": "Feature",
  "properties": {
    "iso:country":"IN",
    "ks:ks_name":"Kodiamma",
    "ks:ks_pop":4032,
    "ks:ks_type":"HABITATION",
    "name:eng_x_preferred":[
        "Kodiamma"
    ],
    "wof:name":"Kodiamma",
    "wof:placetype":"locality",
    "wof:population":4032
},
  "geometry": {"coordinates":[74.971555,12.613641],"type":"Point"}
}