{
  "type": "Feature",
  "properties": {
    "iso:country":"IN",
    "ks:ks_name":"Majhigam",
    "ks:ks_pop":67,
    "ks:ks_type":"VILLAGE",
    "name:eng_x_preferred":[
        "Majhigam"
    ],
    "wof:name":"Majhigam",
    "wof:placetype":"locality",
    "wof:population":67
},
  "geometry": {"coordinates":[84.282838,19.758714],"type":"Point"}
}