{
  "type": "Feature",
  "properties": {
    "gn:admin1_code":"40",
    "gn:admin2_code":"538.0",
    "gn:asciiname":"Nilgiri",
    "gn:country_code":"IN",
    "gn:dem":870,
    "gn:feature_class":"P",
    "gn:feature_code":"PPL",
    "gn:name":"N\u012blgiri",
    "gn:population":0,
    "gn:timezone":"Asia/Kolkata",
    "iso:country":"IN",
    "name:ceb_x_preferred":[
        "Nilgiri"
    ],
    "name:deu_x_preferred":[
        "Nilgiri"
    ],
    "name:fra_x_preferred":[
        "Nilgiri"
    ],
    "name:hin_x_preferred":[
        "\u0928\u0940\u0932\u0917\u093f\u0930\u093f"
    ],
    "name:nld_x_preferred":[
        "Nilgiri"
    ],
    "name:pol_x_preferred":[
        "Nilgiri"
    ],
    "name:por_x_preferred":[
        "Nilgiri"
    ],
    "name:rus_x_preferred":[
        "\u041d\u0438\u043b\u0433\u0438\u0440\u0438"
    ],
    "name:swe_x_preferred":[
        "Nilgiri"
    ],
    "name:ukr_x_preferred":[
        "\u041d\u0456\u043b\u0491\u0456\u0440\u0456"
    ],
    "wof:name":"Nilgiri",
    "wof:placetype":"locality"
},
  "geometry": {"coordinates":[78.67174,16.25597],"type":"Point"}
}