{
  "type": "Feature",
  "properties": {
    "iso:country":"IN",
    "ks:ks_name":"Karungulipallam",
    "ks:ks_type":"VILLAGE",
    "name:eng_x_preferred":[
        "Karungulipallam"
    ],
    "wof:name":"Karungulipallam",
    "wof:placetype":"locality"
},
  "geometry": {"coordinates":[80.186652,12.67386],"type":"Point"}
}