{
  "type": "Feature",
  "properties": {
    "gn:admin1_code":"2.0",
    "gn:admin2_code":"544.0",
    "gn:asciiname":"Ambiri",
    "gn:country_code":"IN",
    "gn:dem":788,
    "gn:feature_class":"P",
    "gn:feature_code":"PPL",
    "gn:name":"Ambiri",
    "gn:population":0,
    "gn:timezone":"Asia/Kolkata",
    "iso:country":"IN",
    "wof:name":"Ambiri",
    "wof:placetype":"locality"
},
  "geometry": {"coordinates":[82.37665,18.18687000000001],"type":"Point"}
}