{
  "type": "Feature",
  "properties": {
    "iso:country":"IN",
    "ks:ks_name":"Bilpar",
    "ks:ks_pop":1120,
    "ks:ks_type":"VILLAGE",
    "ks:ks_uagg_main":0,
    "name:eng_x_preferred":[
        "Bilpar"
    ],
    "wof:name":"Bilpar",
    "wof:placetype":"neighbourhood",
    "wof:population":1120
},
  "geometry": {"coordinates":[91.54859999999999,26.597837],"type":"Point"}
}