{
  "type": "Feature",
  "properties": {
    "iso:country":"IN",
    "ks:ks_name":"Barachandabila",
    "ks:ks_pop":715,
    "ks:ks_type":"VILLAGE",
    "ks:ks_uagg_main":0,
    "name:eng_x_preferred":[
        "Barachandabila"
    ],
    "wof:name":"Barachandabila",
    "wof:placetype":"neighbourhood",
    "wof:population":715
},
  "geometry": {"coordinates":[87.242069,22.694008],"type":"Point"}
}