{
  "type": "Feature",
  "properties": {
    "iso:country":"IN",
    "ks:ks_name":"Magdaur",
    "ks:ks_pop":961,
    "ks:ks_type":"VILLAGE",
    "name:eng_x_preferred":[
        "Magdaur"
    ],
    "wof:name":"Magdaur",
    "wof:placetype":"locality",
    "wof:population":961
},
  "geometry": {"coordinates":[81.365971,25.140267],"type":"Point"}
}