{
  "type": "Feature",
  "properties": {
    "gn:admin1_code":"35.0",
    "gn:admin2_code":"466.0",
    "gn:asciiname":"Utri",
    "gn:country_code":"IN",
    "gn:dem":248,
    "gn:feature_class":"P",
    "gn:feature_code":"PPL",
    "gn:name":"Utri",
    "gn:population":0,
    "gn:timezone":"Asia/Kolkata",
    "iso:country":"IN",
    "wof:name":"Utri",
    "wof:placetype":"neighbourhood"
},
  "geometry": {"coordinates":[76.39163000000001,22.12914],"type":"Point"}
}