{
  "type": "Feature",
  "properties": {
    "gn:admin1_code":"21",
    "gn:admin2_code":"371.0",
    "gn:asciiname":"Machida",
    "gn:country_code":"IN",
    "gn:dem":229,
    "gn:feature_class":"P",
    "gn:feature_code":"PPL",
    "gn:name":"Machida",
    "gn:population":0,
    "gn:timezone":"Asia/Kolkata",
    "iso:country":"IN",
    "name:ceb_x_preferred":[
        "Machida"
    ],
    "name:deu_x_preferred":[
        "Machida"
    ],
    "name:mlg_x_preferred":[
        "Machida"
    ],
    "wof:name":"Machida",
    "wof:placetype":"locality"
},
  "geometry": {"coordinates":[83.60654,21.81715],"type":"Point"}
}