{
  "type": "Feature",
  "properties": {
    "gn:admin1_code":"33.0",
    "gn:admin2_code":"586",
    "gn:asciiname":"Boma",
    "gn:country_code":"IN",
    "gn:dem":304,
    "gn:feature_class":"P",
    "gn:feature_code":"PPL",
    "gn:name":"Boma",
    "gn:population":0,
    "gn:timezone":"Asia/Kolkata",
    "iso:country":"IN",
    "ks:ks_name":"Boma",
    "ks:ks_pop":0,
    "ks:ks_type":"VILLAGE",
    "name:ceb_x_preferred":[
        "Boma"
    ],
    "name:deu_x_preferred":[
        "Boma"
    ],
    "name:eng_x_preferred":[
        "Boma"
    ],
    "name:fra_x_preferred":[
        "Boma"
    ],
    "name:ita_x_preferred":[
        "Boma"
    ],
    "name:lin_x_preferred":[
        "Boma"
    ],
    "name:nld_x_preferred":[
        "Boma"
    ],
    "name:pol_x_preferred":[
        "Boma"
    ],
    "name:por_x_preferred":[
        "Boma"
    ],
    "name:rus_x_preferred":[
        "\u0411\u043e\u043c\u0430"
    ],
    "name:srp_x_preferred":[
        "\u0411\u043e\u043c\u0430"
    ],
    "name:swe_x_preferred":[
        "Boma"
    ],
    "wof:name":"Boma",
    "wof:placetype":"locality",
    "wof:population":0
},
  "geometry": {"coordinates":[74.275277,15.293597],"type":"Point"}
}