{
  "type": "Feature",
  "properties": {
    "iso:country":"IN",
    "ks:ks_name":"Lakhipur",
    "ks:ks_pop":69,
    "ks:ks_type":"HABITATION",
    "name:eng_x_preferred":[
        "Lakhipur"
    ],
    "wof:name":"Lakhipur",
    "wof:placetype":"locality",
    "wof:population":69
},
  "geometry": {"coordinates":[93.598848,26.919399],"type":"Point"}
}