{
  "type": "Feature",
  "properties": {
    "iso:country":"IN",
    "ks:ks_name":"Phulwar",
    "ks:ks_pop":1736,
    "ks:ks_type":"VILLAGE",
    "ks:ks_uagg_main":0,
    "name:eng_x_preferred":[
        "Phulwar"
    ],
    "wof:name":"Phulwar",
    "wof:placetype":"locality",
    "wof:population":1736
},
  "geometry": {"coordinates":[86.281347,23.832194],"type":"Point"}
}