{
  "type": "Feature",
  "properties": {
    "gn:admin1_code":"10.0",
    "gn:admin2_code":"85.0",
    "gn:asciiname":"Srinagor",
    "gn:country_code":"IN",
    "gn:dem":275,
    "gn:feature_class":"P",
    "gn:feature_code":"PPL",
    "gn:name":"Sr\u012bnagor",
    "gn:population":0,
    "gn:timezone":"Asia/Kolkata",
    "iso:country":"IN",
    "ks:ks_name":"Srinagar",
    "ks:ks_pop":252,
    "ks:ks_type":"VILLAGE",
    "name:eng_x_preferred":[
        "Srinagar"
    ],
    "name:eng_x_variant":[
        "Srinagor"
    ],
    "wof:name":"Srinagar",
    "wof:placetype":"locality",
    "wof:population":252
},
  "geometry": {"coordinates":[76.348949,28.229671],"type":"Point"}
}