{
  "type": "Feature",
  "properties": {
    "gn:admin1_code":"38.0",
    "gn:admin2_code":"360.0",
    "gn:asciiname":"Lupung",
    "gn:country_code":"IN",
    "gn:dem":610,
    "gn:feature_class":"P",
    "gn:feature_code":"PPL",
    "gn:name":"Lupung",
    "gn:population":0,
    "gn:timezone":"Asia/Kolkata",
    "iso:country":"IN",
    "wof:name":"Lupung",
    "wof:placetype":"locality"
},
  "geometry": {"coordinates":[85.3028,24.06201],"type":"Point"}
}