{
  "type": "Feature",
  "properties": {
    "iso:country":"IN",
    "ks:ks_alt_nam":"NAGLA  BAGHEL",
    "ks:ks_name":"Nagla Baghel",
    "ks:ks_pop":320,
    "ks:ks_type":"HABITATION",
    "name:eng_x_preferred":[
        "Nagla Baghel"
    ],
    "name:eng_x_variant":[
        "NAGLA  BAGHEL"
    ],
    "wof:name":"Nagla Baghel",
    "wof:placetype":"locality",
    "wof:population":320
},
  "geometry": {"coordinates":[78.113986,27.440302],"type":"Point"}
}