{
  "type": "Feature",
  "properties": {
    "gn:admin1_code":"2.0",
    "gn:admin2_code":"543.0",
    "gn:asciiname":"Gorada",
    "gn:country_code":"IN",
    "gn:dem":306,
    "gn:feature_class":"P",
    "gn:feature_code":"PPL",
    "gn:name":"Gorada",
    "gn:population":0,
    "gn:timezone":"Asia/Kolkata",
    "iso:country":"IN",
    "ks:ks_name":"Gorada",
    "ks:ks_pop":517,
    "ks:ks_type":"HABITATION",
    "name:eng_x_preferred":[
        "Gorada"
    ],
    "wof:name":"Gorada",
    "wof:placetype":"locality",
    "wof:population":517
},
  "geometry": {"coordinates":[83.581176,18.996404],"type":"Point"}
}