{
  "type": "Feature",
  "properties": {
    "gn:admin1_code":"10",
    "gn:admin2_code":"70.0",
    "gn:asciiname":"Salaiehri",
    "gn:country_code":"IN",
    "gn:dem":277,
    "gn:feature_class":"P",
    "gn:feature_code":"PPL",
    "gn:name":"Sal\u0101iehri",
    "gn:population":0,
    "gn:timezone":"Asia/Kolkata",
    "iso:country":"IN",
    "wof:name":"Salaiehri",
    "wof:placetype":"locality"
},
  "geometry": {"coordinates":[76.88797,30.32175],"type":"Point"}
}