{
  "type": "Feature",
  "properties": {
    "gn:country":"IN",
    "gn:fcode":"PPL",
    "gn:pop":2780,
    "iso:country":"IN",
    "name:bpy_x_preferred":[
        "\u09a6\u09cb\u0997\u09be\u09a6\u09cd\u09a6\u09be"
    ],
    "name:bul_x_preferred":[
        "\u0414\u043e\u0433\u0430\u0434\u0430"
    ],
    "name:chi_x_preferred":[
        "\u591a\u52a0\u8fbe"
    ],
    "name:dut_x_preferred":[
        "Dogadda"
    ],
    "name:eng_x_preferred":[
        "Dogadda"
    ],
    "name:ita_x_preferred":[
        "Dogadda"
    ],
    "name:may_x_preferred":[
        "Dogadda"
    ],
    "name:mlg_x_preferred":[
        "Dogadda"
    ],
    "name:nan_x_preferred":[
        "Dogadda"
    ],
    "name:new_x_preferred":[
        "\u0926\u094b\u0917\u0921\u094d\u0921\u093e"
    ],
    "name:pol_x_preferred":[
        "Dogadda"
    ],
    "name:por_x_preferred":[
        "Dogadda"
    ],
    "name:swe_x_preferred":[
        "Dogadda"
    ],
    "name:unk_x_variant":[
        "Garhwal"
    ],
    "name:vie_x_preferred":[
        "Dogadda"
    ],
    "qs:name":"Dogadda",
    "qs:name_adm0":"India",
    "qs:name_adm1":"Uttarakhand",
    "qs:photos_9k":1,
    "qs:photos_9r":1,
    "qs:photos_all":22,
    "qs:photos_sr":0,
    "qs:placetype":"Town",
    "qs:pop_sr":"4",
    "wd:wordcount":289,
    "wof:name":"Dogadda",
    "wof:placetype":"locality",
    "wof:population":2780
},
  "geometry": {"coordinates":[78.60813,29.80677],"type":"Point"}
}