{
  "type": "Feature",
  "properties": {
    "iso:country":"IN",
    "ks:ks_name":"Imliyahwa",
    "ks:ks_pop":560,
    "ks:ks_type":"HABITATION",
    "ks:ks_uagg_main":0,
    "name:eng_x_preferred":[
        "Imliyahwa"
    ],
    "wof:name":"Imliyahwa",
    "wof:placetype":"neighbourhood",
    "wof:population":560
},
  "geometry": {"coordinates":[82.85368,26.482025],"type":"Point"}
}