{
  "type": "Feature",
  "properties": {
    "iso:country":"IN",
    "ks:ks_name":"Kadubhita",
    "ks:ks_pop":446,
    "ks:ks_type":"VILLAGE",
    "name:eng_x_preferred":[
        "Kadubhita"
    ],
    "wof:name":"Kadubhita",
    "wof:placetype":"locality",
    "wof:population":446
},
  "geometry": {"coordinates":[88.240871,26.581164],"type":"Point"}
}