{
  "type": "Feature",
  "properties": {
    "iso:country":"IN",
    "ks:ks_name":"Geddalhalli",
    "ks:ks_pop":1485,
    "ks:ks_type":"VILLAGE",
    "ks:ks_uagg_main":0,
    "name:eng_x_preferred":[
        "Geddalhalli"
    ],
    "wof:name":"Geddalhalli",
    "wof:placetype":"neighbourhood",
    "wof:population":1485
},
  "geometry": {"coordinates":[77.644728,13.048611],"type":"Point"}
}