{
  "type": "Feature",
  "properties": {
    "gn:admin1_code":"36.0",
    "gn:admin2_code":"184.0",
    "gn:asciiname":"Khamaria",
    "gn:country_code":"IN",
    "gn:dem":97,
    "gn:feature_class":"P",
    "gn:feature_code":"PPL",
    "gn:name":"Khamaria",
    "gn:population":0,
    "gn:timezone":"Asia/Kolkata",
    "iso:country":"IN",
    "ks:ks_name":"Khamhariya",
    "ks:ks_pop":1350,
    "ks:ks_type":"VILLAGE",
    "name:bpy_x_preferred":[
        "\u0996\u09be\u09ae\u09be\u09b0\u09bf\u09af\u09bc\u09be"
    ],
    "name:eng_x_preferred":[
        "Khamhariya"
    ],
    "name:eng_x_variant":[
        "Khamaria"
    ],
    "name:hin_x_preferred":[
        "\u0916\u092e\u0930\u093f\u092f\u093e"
    ],
    "name:ita_x_preferred":[
        "Khamaria"
    ],
    "name:msa_x_preferred":[
        "Khamaria"
    ],
    "name:new_x_preferred":[
        "\u0916\u092e\u0930\u093f\u092f\u093e"
    ],
    "name:nld_x_preferred":[
        "Khamaria"
    ],
    "name:pol_x_preferred":[
        "Khamaria"
    ],
    "name:por_x_preferred":[
        "Khamaria"
    ],
    "name:urd_x_preferred":[
        "\u06a9\u06be\u0645\u0627\u0631\u06cc\u0627"
    ],
    "name:vie_x_preferred":[
        "Khamaria"
    ],
    "name:zho_x_preferred":[
        "\u5361\u9a6c\u91cc\u4e9a"
    ],
    "wof:name":"Khamhariya",
    "wof:placetype":"locality",
    "wof:population":1350
},
  "geometry": {"coordinates":[82.751971,27.376414],"type":"Point"}
}