{
  "type": "Feature",
  "properties": {
    "iso:country":"IN",
    "ks:ks_name":"Bajua",
    "ks:ks_pop":2700,
    "ks:ks_type":"VILLAGE",
    "name:eng_x_preferred":[
        "Bajua"
    ],
    "wof:name":"Bajua",
    "wof:placetype":"locality",
    "wof:population":2700
},
  "geometry": {"coordinates":[87.727954,22.945104],"type":"Point"}
}