{
  "type": "Feature",
  "properties": {
    "gn:admin1_code":"35.0",
    "gn:admin2_code":"460",
    "gn:asciiname":"Barutara",
    "gn:country_code":"IN",
    "gn:dem":493,
    "gn:feature_class":"P",
    "gn:feature_code":"PPL",
    "gn:name":"Barutara",
    "gn:population":0,
    "gn:timezone":"Asia/Kolkata",
    "iso:country":"IN",
    "ks:ks_name":"Barutara",
    "ks:ks_pop":479,
    "ks:ks_type":"HABITATION",
    "name:eng_x_preferred":[
        "Barutara"
    ],
    "wof:name":"Barutara",
    "wof:placetype":"locality",
    "wof:population":479
},
  "geometry": {"coordinates":[81.60682199999999,23.50118],"type":"Point"}
}