{
  "type": "Feature",
  "properties": {
    "gn:admin1_code":"35.0",
    "gn:admin2_code":"460",
    "gn:asciiname":"Barutara",
    "gn:country_code":"IN",
    "gn:dem":493,
    "gn:feature_class":"P",
    "gn:feature_code":"PPL",
    "gn:name":"Barutara",
    "gn:population":0,
    "gn:timezone":"Asia/Kolkata",
    "iso:country":"IN",
    "wof:name":"Barutara",
    "wof:placetype":"locality"
},
  "geometry": {"coordinates":[81.60744,23.50086],"type":"Point"}
}