{
  "type": "Feature",
  "properties": {
    "iso:country":"IN",
    "ks:ks_name":"Hetyasol",
    "ks:ks_pop":15,
    "ks:ks_type":"HABITATION",
    "name:eng_x_preferred":[
        "Hetyasol"
    ],
    "wof:name":"Hetyasol",
    "wof:placetype":"locality",
    "wof:population":15
},
  "geometry": {"coordinates":[86.79714199999999,22.579369],"type":"Point"}
}