{
  "type": "Feature",
  "properties": {
    "gn:admin1_code":"2",
    "gn:admin2_code":"544.0",
    "gn:asciiname":"Bilaiput",
    "gn:country_code":"IN",
    "gn:dem":919,
    "gn:feature_class":"P",
    "gn:feature_code":"PPL",
    "gn:name":"Bilaiput",
    "gn:population":0,
    "gn:timezone":"Asia/Kolkata",
    "iso:country":"IN",
    "wof:name":"Bilaiput",
    "wof:placetype":"locality"
},
  "geometry": {"coordinates":[82.76226,18.17764],"type":"Point"}
}