{
  "type": "Feature",
  "properties": {
    "iso:country":"IN",
    "ks:ks_name":"Chatarpura",
    "ks:ks_pop":858,
    "ks:ks_type":"VILLAGE",
    "name:eng_x_preferred":[
        "Chatarpura"
    ],
    "wof:name":"Chatarpura",
    "wof:placetype":"locality",
    "wof:population":858
},
  "geometry": {"coordinates":[72.124903,26.437378],"type":"Point"}
}