{
  "type": "Feature",
  "properties": {
    "gn:admin1_code":"34.0",
    "gn:admin2_code":"222.0",
    "gn:asciiname":"Manka Salimpur",
    "gn:country_code":"IN",
    "gn:dem":48,
    "gn:feature_class":"P",
    "gn:feature_code":"PPL",
    "gn:name":"Manka Sal\u012bmpur",
    "gn:population":0,
    "gn:timezone":"Asia/Kolkata",
    "iso:country":"IN",
    "ks:ks_name":"Manka Salempur",
    "ks:ks_pop":811,
    "ks:ks_type":"VILLAGE",
    "ks:ks_uagg_main":0,
    "name:eng_x_preferred":[
        "Manka Salempur"
    ],
    "wof:name":"Manka Salempur",
    "wof:placetype":"neighbourhood",
    "wof:population":811
},
  "geometry": {"coordinates":[86.23117499999999,25.402743],"type":"Point"}
}