{
  "type": "Feature",
  "properties": {
    "iso:country":"IN",
    "ks:ks_name":"Baraik Basti",
    "ks:ks_pop":220,
    "ks:ks_type":"HABITATION",
    "name:eng_x_preferred":[
        "Baraik Basti"
    ],
    "wof:name":"Baraik Basti",
    "wof:placetype":"locality",
    "wof:population":220
},
  "geometry": {"coordinates":[94.897227,26.972829],"type":"Point"}
}