{
  "type": "Feature",
  "properties": {
    "iso:country":"IN",
    "ks:ks_name":"Buduka Boulajholi",
    "ks:ks_pop":20,
    "ks:ks_type":"HABITATION",
    "name:eng_x_preferred":[
        "Buduka Boulajholi"
    ],
    "wof:name":"Buduka Boulajholi",
    "wof:placetype":"locality",
    "wof:population":20
},
  "geometry": {"coordinates":[84.716121,19.403612],"type":"Point"}
}