{
  "type": "Feature",
  "properties": {
    "gn:admin1_code":"36",
    "gn:admin2_code":"180.0",
    "gn:asciiname":"Kamali",
    "gn:country_code":"IN",
    "gn:dem":118,
    "gn:feature_class":"P",
    "gn:feature_code":"PPL",
    "gn:name":"Kam\u0101li",
    "gn:population":0,
    "gn:timezone":"Asia/Kolkata",
    "iso:country":"IN",
    "ks:ks_alt_nam":"Kam\u0101li",
    "ks:ks_name":"Kamali",
    "ks:ks_type":"VILLAGE",
    "name:ceb_x_preferred":[
        "Kamali"
    ],
    "name:deu_x_preferred":[
        "Kamali"
    ],
    "name:eng_x_preferred":[
        "Kamali"
    ],
    "name:eng_x_variant":[
        "Kam\u0101li"
    ],
    "name:fas_x_preferred":[
        "\u06a9\u0645\u0627\u0644\u06cc"
    ],
    "wof:name":"Kamali",
    "wof:placetype":"locality"
},
  "geometry": {"coordinates":[81.58845100000001,27.638074],"type":"Point"}
}