{
  "type": "Feature",
  "properties": {
    "gn:admin1_code":"35.0",
    "gn:admin2_code":"458.0",
    "gn:asciiname":"Gangotri",
    "gn:country_code":"IN",
    "gn:dem":317,
    "gn:feature_class":"P",
    "gn:feature_code":"PPL",
    "gn:name":"Gangotri",
    "gn:population":0,
    "gn:timezone":"Asia/Kolkata",
    "iso:country":"IN",
    "name:ben_x_preferred":[
        "\u0997\u0999\u09cd\u0997\u09cb\u09a4\u09cd\u09b0\u09c0"
    ],
    "name:bih_x_preferred":[
        "\u0917\u0902\u0917\u094b\u0924\u094d\u0930\u0940"
    ],
    "name:bpy_x_preferred":[
        "\u0997\u0999\u09cd\u0997\u09cb\u09a4\u09cd\u09a4\u09b0\u09bf"
    ],
    "name:ceb_x_preferred":[
        "Gangotri"
    ],
    "name:deu_x_preferred":[
        "Gangotri"
    ],
    "name:fra_x_preferred":[
        "Gangotr\u00ee"
    ],
    "name:guj_x_preferred":[
        "\u0a97\u0a82\u0a97\u0acb\u0aa4\u0acd\u0ab0\u0ac0"
    ],
    "name:hin_x_preferred":[
        "\u0917\u0902\u0917\u094b\u0924\u094d\u0930\u0940"
    ],
    "name:ita_x_preferred":[
        "Gangotri"
    ],
    "name:kan_x_preferred":[
        "\u0c97\u0c82\u0c97\u0ccb\u0ca4\u0ccd\u0cb0\u0cbf"
    ],
    "name:mai_x_preferred":[
        "\u0917\u0919\u094d\u0917\u094b\u0924\u094d\u0930\u0940"
    ],
    "name:mal_x_preferred":[
        "\u0d17\u0d02\u0d17\u0d4b\u0d24\u0d4d\u0d30\u0d3f"
    ],
    "name:mar_x_preferred":[
        "\u0917\u0902\u0917\u094b\u0924\u094d\u0930\u0940"
    ],
    "name:mlg_x_preferred":[
        "Gangotri"
    ],
    "name:msa_x_preferred":[
        "Gangotri"
    ],
    "name:nep_x_preferred":[
        "\u0917\u0919\u094d\u0917\u094b\u0924\u094d\u0930\u0940"
    ],
    "name:new_x_preferred":[
        "\u0917\u0902\u0917\u094b\u0924\u094d\u0930\u0940"
    ],
    "name:nno_x_preferred":[
        "Gangotri"
    ],
    "name:pan_x_preferred":[
        "\u0a17\u0a70\u0a17\u0a4b\u0a24\u0a30\u0a40"
    ],
    "name:pnb_x_preferred":[
        "\u06af\u0646\u06af\u0648\u062a\u0631\u06cc"
    ],
    "name:pol_x_preferred":[
        "Gangotri"
    ],
    "name:rus_x_preferred":[
        "\u0413\u0430\u043d\u0433\u043e\u0442\u0440\u0438"
    ],
    "name:san_x_preferred":[
        "\u0917\u0919\u094d\u0917\u094b\u0924\u094d\u0930\u0940"
    ],
    "name:spa_x_preferred":[
        "Gangotri"
    ],
    "name:swe_x_preferred":[
        "Gangotri"
    ],
    "name:tam_x_preferred":[
        "\u0b95\u0b99\u0bcd\u0b95\u0bcb\u0ba4\u0bcd\u0bb0\u0bbf"
    ],
    "name:tel_x_preferred":[
        "\u0c17\u0c02\u0c17\u0c4b\u0c24\u0c4d\u0c30\u0c3f"
    ],
    "name:ukr_x_preferred":[
        "\u0490\u0430\u043d\u0491\u043e\u0442\u0440\u0456"
    ],
    "name:urd_x_preferred":[
        "\u06af\u0646\u06af\u0648\u062a\u0631\u06cc"
    ],
    "name:vie_x_preferred":[
        "Gangotri"
    ],
    "name:zho_x_preferred":[
        "\u6839\u6208\u5fb7\u91cc"
    ],
    "wof:name":"Gangotri",
    "wof:placetype":"locality"
},
  "geometry": {"coordinates":[76.83863000000002,24.79472],"type":"Point"}
}