{
  "type": "Feature",
  "properties": {
    "gn:admin1_code":"35.0",
    "gn:admin2_code":"458.0",
    "gn:asciiname":"Gangotri",
    "gn:country_code":"IN",
    "gn:dem":317,
    "gn:feature_class":"P",
    "gn:feature_code":"PPL",
    "gn:name":"Gangotri",
    "gn:population":0,
    "gn:timezone":"Asia/Kolkata",
    "iso:country":"IN",
    "wof:name":"Gangotri",
    "wof:placetype":"locality"
},
  "geometry": {"coordinates":[76.83863000000002,24.79472],"type":"Point"}
}