{
  "type": "Feature",
  "properties": {
    "iso:country":"IN",
    "ks:ks_name":"Karim Dadwa",
    "ks:ks_pop":564,
    "ks:ks_type":"HABITATION",
    "ks:ks_uagg_main":0,
    "name:eng_x_preferred":[
        "Karim Dadwa"
    ],
    "wof:name":"Karim Dadwa",
    "wof:placetype":"neighbourhood",
    "wof:population":564
},
  "geometry": {"coordinates":[82.749506,26.380817],"type":"Point"}
}