{
  "type": "Feature",
  "properties": {
    "iso:country":"IN",
    "ks:ks_name":"Nandanpur",
    "ks:ks_pop":142,
    "ks:ks_type":"HABITATION",
    "name:eng_x_preferred":[
        "Nandanpur"
    ],
    "wof:name":"Nandanpur",
    "wof:placetype":"locality",
    "wof:population":142
},
  "geometry": {"coordinates":[78.119773,27.191438],"type":"Point"}
}