{
  "type": "Feature",
  "properties": {
    "iso:country":"IN",
    "ks:ks_name":"Bagaiha",
    "ks:ks_pop":1228,
    "ks:ks_type":"VILLAGE",
    "name:eng_x_preferred":[
        "Bagaiha"
    ],
    "wof:name":"Bagaiha",
    "wof:placetype":"locality",
    "wof:population":1228
},
  "geometry": {"coordinates":[81.62143,24.088772],"type":"Point"}
}