{
  "type": "Feature",
  "properties": {
    "iso:country":"IN",
    "ks:ks_name":"Bhangadaha",
    "ks:ks_pop":864,
    "ks:ks_type":"VILLAGE",
    "name:eng_x_preferred":[
        "Bhangadaha"
    ],
    "wof:name":"Bhangadaha",
    "wof:placetype":"locality",
    "wof:population":864
},
  "geometry": {"coordinates":[87.694356,22.619332],"type":"Point"}
}