{
  "type": "Feature",
  "properties": {
    "iso:country":"IN",
    "ks:ks_name":"Darowanpara",
    "ks:ks_pop":725,
    "ks:ks_type":"HABITATION",
    "ks:ks_uagg_main":0,
    "name:eng_x_preferred":[
        "Darowanpara"
    ],
    "wof:name":"Darowanpara",
    "wof:placetype":"locality",
    "wof:population":725
},
  "geometry": {"coordinates":[88.200587,22.517324],"type":"Point"}
}