{
  "type": "Feature",
  "properties": {
    "iso:country":"IN",
    "ks:ks_name":"Kolai Pandey Ka Purva",
    "ks:ks_pop":104,
    "ks:ks_type":"HABITATION",
    "name:eng_x_preferred":[
        "Kolai Pandey Ka Purva"
    ],
    "wof:name":"Kolai Pandey Ka Purva",
    "wof:placetype":"locality",
    "wof:population":104
},
  "geometry": {"coordinates":[82.23533399999999,26.71315],"type":"Point"}
}