{
  "type": "Feature",
  "properties": {
    "iso:country":"IN",
    "ks:ks_alt_nam":"Kamod bk",
    "ks:ks_name":"Kamod Bk",
    "ks:ks_pop":608,
    "ks:ks_type":"HABITATION",
    "name:eng_x_preferred":[
        "Kamod Bk"
    ],
    "wof:name":"Kamod Bk",
    "wof:placetype":"locality",
    "wof:population":608
},
  "geometry": {"coordinates":[74.268455,21.874292],"type":"Point"}
}