{
  "type": "Feature",
  "properties": {
    "gn:admin1_code":"35",
    "gn:admin2_code":"448.0",
    "gn:asciiname":"Nazarpura",
    "gn:country_code":"IN",
    "gn:dem":323,
    "gn:feature_class":"P",
    "gn:feature_code":"PPL",
    "gn:name":"Nazarpura",
    "gn:population":0,
    "gn:timezone":"Asia/Kolkata",
    "iso:country":"IN",
    "wof:name":"Nazarpura",
    "wof:placetype":"locality"
},
  "geometry": {"coordinates":[77.2317,22.2483],"type":"Point"}
}