{
  "type": "Feature",
  "properties": {
    "gn:admin1_code":"25.0",
    "gn:admin2_code":"611.0",
    "gn:asciiname":"Jakkathonimund",
    "gn:country_code":"IN",
    "gn:dem":2010,
    "gn:feature_class":"P",
    "gn:feature_code":"PPL",
    "gn:name":"Jakkathonimund",
    "gn:population":0,
    "gn:timezone":"Asia/Kolkata",
    "iso:country":"IN",
    "wof:name":"Jakkathonimund",
    "wof:placetype":"locality"
},
  "geometry": {"coordinates":[76.79640000000001,11.47759],"type":"Point"}
}