{
  "type": "Feature",
  "properties": {
    "gn:admin1_code":"12.0",
    "gn:admin2_code":"008",
    "gn:asciiname":"Markut",
    "gn:country_code":"IN",
    "gn:dem":2192,
    "gn:feature_class":"P",
    "gn:feature_code":"PPL",
    "gn:name":"Mark\u016bt",
    "gn:population":0,
    "gn:timezone":"Asia/Kolkata",
    "iso:country":"IN",
    "wof:name":"Markut",
    "wof:placetype":"locality"
},
  "geometry": {"coordinates":[74.19444,34.28098],"type":"Point"}
}