{
  "type": "Feature",
  "properties": {
    "iso:country":"IN",
    "ks:ks_name":"Karaundi Mal.Bargoan",
    "ks:ks_pop":1478,
    "ks:ks_type":"VILLAGE",
    "name:eng_x_preferred":[
        "Karaundi Mal.Bargoan"
    ],
    "wof:name":"Karaundi Mal.Bargoan",
    "wof:placetype":"locality",
    "wof:population":1478
},
  "geometry": {"coordinates":[80.74488700000001,23.148345],"type":"Point"}
}