{
  "type": "Feature",
  "properties": {
    "iso:country":"IN",
    "ks:ks_alt_nam":"Tilgawan kala",
    "ks:ks_name":"Tilgawan Kala",
    "ks:ks_pop":332,
    "ks:ks_type":"HABITATION",
    "name:eng_x_preferred":[
        "Tilgawan Kala"
    ],
    "wof:name":"Tilgawan Kala",
    "wof:placetype":"locality",
    "wof:population":332
},
  "geometry": {"coordinates":[80.496872,24.522438],"type":"Point"}
}