{
  "type": "Feature",
  "properties": {
    "iso:country":"IN",
    "ks:ks_name":"Sampathila",
    "ks:ks_pop":65,
    "ks:ks_type":"HABITATION",
    "name:eng_x_preferred":[
        "Sampathila"
    ],
    "wof:name":"Sampathila",
    "wof:placetype":"locality",
    "wof:population":65
},
  "geometry": {"coordinates":[75.341514,12.585025],"type":"Point"}
}