{
  "type": "Feature",
  "properties": {
    "gn:admin1_code":"36.0",
    "gn:admin2_code":"153.0",
    "gn:asciiname":"Lalwapur",
    "gn:country_code":"IN",
    "gn:dem":158,
    "gn:feature_class":"P",
    "gn:feature_code":"PPL",
    "gn:name":"Lalw\u0101pur",
    "gn:population":0,
    "gn:timezone":"Asia/Kolkata",
    "iso:country":"IN",
    "wof:name":"Lalwapur",
    "wof:placetype":"locality"
},
  "geometry": {"coordinates":[80.35648,27.9134],"type":"Point"}
}