{
  "type": "Feature",
  "properties": {
    "iso:country":"IN",
    "ks:ks_name":"Telbhitha",
    "ks:ks_pop":644,
    "ks:ks_type":"HABITATION",
    "name:eng_x_preferred":[
        "Telbhitha"
    ],
    "wof:name":"Telbhitha",
    "wof:placetype":"locality",
    "wof:population":644
},
  "geometry": {"coordinates":[87.442457,24.82654],"type":"Point"}
}