{
  "type": "Feature",
  "properties": {
    "gn:admin1_code":"34.0",
    "gn:admin2_code":"235.0",
    "gn:asciiname":"Khairi Ram",
    "gn:country_code":"IN",
    "gn:dem":162,
    "gn:feature_class":"P",
    "gn:feature_code":"PPL",
    "gn:name":"Khair\u012b R\u0101m",
    "gn:population":0,
    "gn:timezone":"Asia/Kolkata",
    "iso:country":"IN",
    "ks:ks_alt_nam":"Khair\u012b R\u0101m",
    "ks:ks_name":"Khairi Ram",
    "ks:ks_pop":106,
    "ks:ks_type":"VILLAGE",
    "name:eng_x_preferred":[
        "Khairi Ram"
    ],
    "name:eng_x_variant":[
        "Khair\u012b R\u0101m"
    ],
    "wof:name":"Khairi Ram",
    "wof:placetype":"locality",
    "wof:population":106
},
  "geometry": {"coordinates":[84.15374799999999,24.550717],"type":"Point"}
}