{
  "type": "Feature",
  "properties": {
    "iso:country":"IN",
    "ks:ks_name":"Nethrabailu",
    "ks:ks_pop":190,
    "ks:ks_type":"HABITATION",
    "name:eng_x_preferred":[
        "Nethrabailu"
    ],
    "wof:name":"Nethrabailu",
    "wof:placetype":"locality",
    "wof:population":190
},
  "geometry": {"coordinates":[75.233525,13.037524],"type":"Point"}
}