{
  "type": "Feature",
  "properties": {
    "gn:admin1_code":"19.0",
    "gn:admin2_code":"570.0",
    "gn:asciiname":"Melaholagadde",
    "gn:country_code":"IN",
    "gn:dem":1143,
    "gn:feature_class":"P",
    "gn:feature_code":"PPL",
    "gn:name":"Melaholagadde",
    "gn:population":0,
    "gn:timezone":"Asia/Kolkata",
    "iso:country":"IN",
    "wof:name":"Melaholagadde",
    "wof:placetype":"locality"
},
  "geometry": {"coordinates":[75.65514,13.39006],"type":"Point"}
}