{
  "type": "Feature",
  "properties": {
    "iso:country":"IN",
    "ks:ks_name":"Rajaura",
    "ks:ks_pop":393,
    "ks:ks_type":"VILLAGE",
    "ks:ks_uagg_main":0,
    "name:eng_x_preferred":[
        "Rajaura"
    ],
    "wof:name":"Rajaura",
    "wof:placetype":"neighbourhood",
    "wof:population":393
},
  "geometry": {"coordinates":[76.55440299999999,25.535558],"type":"Point"}
}