{
  "type": "Feature",
  "properties": {
    "gn:admin1_code":"34.0",
    "gn:admin2_code":"234.0",
    "gn:asciiname":"Rutawan",
    "gn:country_code":"IN",
    "gn:dem":104,
    "gn:feature_class":"P",
    "gn:feature_code":"PPL",
    "gn:name":"Rut\u0101w\u0101n",
    "gn:population":0,
    "gn:timezone":"Asia/Kolkata",
    "iso:country":"IN",
    "ks:ks_name":"Rutawan",
    "ks:ks_pop":2187,
    "ks:ks_type":"VILLAGE",
    "name:eng_x_preferred":[
        "Rutawan"
    ],
    "wof:name":"Rutawan",
    "wof:placetype":"locality",
    "wof:population":2187
},
  "geometry": {"coordinates":[84.17587399999999,25.034492],"type":"Point"}
}