{
  "type": "Feature",
  "properties": {
    "iso:country":"IN",
    "ks:ks_name":"Ganapathiyapuram",
    "ks:ks_pop":460,
    "ks:ks_type":"HABITATION",
    "ks:ks_uagg_main":0,
    "name:eng_x_preferred":[
        "Ganapathiyapuram"
    ],
    "wof:name":"Ganapathiyapuram",
    "wof:placetype":"neighbourhood",
    "wof:population":460
},
  "geometry": {"coordinates":[77.584705,8.281371],"type":"Point"}
}