{
  "type": "Feature",
  "properties": {
    "iso:country":"IN",
    "ks:ks_name":"Katajar",
    "ks:ks_pop":933,
    "ks:ks_type":"HABITATION",
    "name:eng_x_preferred":[
        "Katajar"
    ],
    "wof:name":"Katajar",
    "wof:placetype":"locality",
    "wof:population":933
},
  "geometry": {"coordinates":[80.400784,22.460999],"type":"Point"}
}