{
  "type": "Feature",
  "properties": {
    "iso:country":"IN",
    "ks:ks_name":"Tukuda",
    "ks:ks_pop":95,
    "ks:ks_type":"VILLAGE",
    "name:eng_x_preferred":[
        "Tukuda"
    ],
    "wof:name":"Tukuda",
    "wof:placetype":"locality",
    "wof:population":95
},
  "geometry": {"coordinates":[84.877854,20.252655],"type":"Point"}
}