{
  "type": "Feature",
  "properties": {
    "iso:country":"IN",
    "ks:ks_name":"Sanahantuad",
    "ks:ks_pop":1159,
    "ks:ks_type":"VILLAGE",
    "ks:ks_uagg_main":0,
    "name:eng_x_preferred":[
        "Sanahantuad"
    ],
    "wof:name":"Sanahantuad",
    "wof:placetype":"neighbourhood",
    "wof:population":1159
},
  "geometry": {"coordinates":[85.181321,19.80063],"type":"Point"}
}