{
  "type": "Feature",
  "properties": {
    "iso:country":"IN",
    "ks:ks_name":"Humbarvane",
    "ks:ks_pop":120,
    "ks:ks_type":"HABITATION",
    "name:eng_x_preferred":[
        "Humbarvane"
    ],
    "wof:name":"Humbarvane",
    "wof:placetype":"locality",
    "wof:population":120
},
  "geometry": {"coordinates":[73.34992800000001,17.253992],"type":"Point"}
}