{
  "type": "Feature",
  "properties": {
    "iso:country":"IN",
    "ks:ks_name":"Ganesapuram",
    "ks:ks_pop":305,
    "ks:ks_type":"HABITATION",
    "name:eng_x_preferred":[
        "Ganesapuram"
    ],
    "wof:name":"Ganesapuram",
    "wof:placetype":"locality",
    "wof:population":305
},
  "geometry": {"coordinates":[77.93192000000001,10.062683],"type":"Point"}
}