{
  "type": "Feature",
  "properties": {
    "iso:country":"IN",
    "ks:ks_name":"Shaldi Ka Pura",
    "ks:ks_pop":130,
    "ks:ks_type":"HABITATION",
    "name:eng_x_preferred":[
        "Shaldi Ka Pura"
    ],
    "wof:name":"Shaldi Ka Pura",
    "wof:placetype":"locality",
    "wof:population":130
},
  "geometry": {"coordinates":[81.93848,25.29284],"type":"Point"}
}