{
  "type": "Feature",
  "properties": {
    "iso:country":"IN",
    "ks:ks_name":"Govele Kond",
    "ks:ks_pop":336,
    "ks:ks_type":"HABITATION",
    "name:eng_x_preferred":[
        "Govele Kond"
    ],
    "wof:name":"Govele Kond",
    "wof:placetype":"locality",
    "wof:population":336
},
  "geometry": {"coordinates":[73.226902,18.148628],"type":"Point"}
}