{
  "type": "Feature",
  "properties": {
    "gn:admin1_code":"11",
    "gn:admin2_code":"28.0",
    "gn:asciiname":"Barin",
    "gn:country_code":"IN",
    "gn:dem":614,
    "gn:feature_class":"P",
    "gn:feature_code":"PPL",
    "gn:name":"Barin",
    "gn:population":0,
    "gn:timezone":"Asia/Kolkata",
    "iso:country":"IN",
    "name:deu_x_preferred":[
        "Barin"
    ],
    "name:fra_x_preferred":[
        "Barin"
    ],
    "name:rus_x_preferred":[
        "\u0411\u0430\u0440\u0438\u043d"
    ],
    "wof:name":"Barin",
    "wof:placetype":"locality"
},
  "geometry": {"coordinates":[76.47663,31.80042000000001],"type":"Point"}
}