{
  "type": "Feature",
  "properties": {
    "iso:country":"IN",
    "ks:ks_name":"Pandiannagar",
    "ks:ks_pop":155,
    "ks:ks_type":"HABITATION",
    "name:eng_x_preferred":[
        "Pandiannagar"
    ],
    "wof:name":"Pandiannagar",
    "wof:placetype":"locality",
    "wof:population":155
},
  "geometry": {"coordinates":[78.272521,10.237468],"type":"Point"}
}