{
  "type": "Feature",
  "properties": {
    "gn:admin1_code":"25.0",
    "gn:admin2_code":"630",
    "gn:asciiname":"Karagur",
    "gn:country_code":"IN",
    "gn:dem":547,
    "gn:feature_class":"P",
    "gn:feature_code":"PPL",
    "gn:name":"Karag\u016br",
    "gn:population":0,
    "gn:timezone":"Asia/Kolkata",
    "iso:country":"IN",
    "name:und_x_variant":[
        "Karag\u016br",
        "Karay\u016br"
    ],
    "wof:name":"Karagur",
    "wof:placetype":"neighbourhood"
},
  "geometry": {"coordinates":[77.98363000000001,12.3015],"type":"Point"}
}