{
  "type": "Feature",
  "properties": {
    "iso:country":"IN",
    "ks:ks_name":"Dina Khera",
    "ks:ks_pop":140,
    "ks:ks_type":"HABITATION",
    "name:eng_x_preferred":[
        "Dina Khera"
    ],
    "wof:name":"Dina Khera",
    "wof:placetype":"locality",
    "wof:population":140
},
  "geometry": {"coordinates":[80.45112399999999,27.113532],"type":"Point"}
}