{
  "type": "Feature",
  "properties": {
    "iso:country":"IN",
    "ks:ks_name":"Midte",
    "ks:ks_pop":349,
    "ks:ks_type":"HABITATION",
    "name:eng_x_preferred":[
        "Midte"
    ],
    "wof:name":"Midte",
    "wof:placetype":"locality",
    "wof:population":349
},
  "geometry": {"coordinates":[80.801106,18.896101],"type":"Point"}
}