{
  "type": "Feature",
  "properties": {
    "iso:country":"IN",
    "ks:ks_name":"Chityalathanda",
    "ks:ks_pop":1149,
    "ks:ks_type":"HABITATION",
    "name:eng_x_preferred":[
        "Chityalathanda"
    ],
    "wof:name":"Chityalathanda",
    "wof:placetype":"locality",
    "wof:population":1149
},
  "geometry": {"coordinates":[79.988148,16.655487],"type":"Point"}
}