{
  "type": "Feature",
  "properties": {
    "gn:admin1_code":"35",
    "gn:admin2_code":"466.0",
    "gn:asciiname":"Didamda",
    "gn:country_code":"IN",
    "gn:dem":345,
    "gn:feature_class":"P",
    "gn:feature_code":"PPL",
    "gn:name":"Didamda",
    "gn:population":0,
    "gn:timezone":"Asia/Kolkata",
    "iso:country":"IN",
    "ks:ks_name":"Didimda",
    "ks:ks_pop":950,
    "ks:ks_type":"HABITATION",
    "name:eng_x_preferred":[
        "Didimda"
    ],
    "name:eng_x_variant":[
        "Didamda"
    ],
    "wof:name":"Didimda",
    "wof:placetype":"locality",
    "wof:population":950
},
  "geometry": {"coordinates":[77.06160300000001,21.746576],"type":"Point"}
}