{
  "type": "Feature",
  "properties": {
    "iso:country":"IN",
    "ks:ks_name":"Hegde Hittal",
    "ks:ks_pop":168,
    "ks:ks_type":"HABITATION",
    "name:eng_x_preferred":[
        "Hegde Hittal"
    ],
    "wof:name":"Hegde Hittal",
    "wof:placetype":"locality",
    "wof:population":168
},
  "geometry": {"coordinates":[74.42712299999999,14.308214],"type":"Point"}
}