{
  "type": "Feature",
  "properties": {
    "iso:country":"IN",
    "ks:ks_name":"Kanjirapara",
    "ks:ks_pop":200,
    "ks:ks_type":"HABITATION",
    "name:eng_x_preferred":[
        "Kanjirapara"
    ],
    "wof:name":"Kanjirapara",
    "wof:placetype":"locality",
    "wof:population":200
},
  "geometry": {"coordinates":[76.01873000000001,11.416284],"type":"Point"}
}