{
  "type": "Feature",
  "properties": {
    "iso:country":"IN",
    "ks:ks_name":"Pipra",
    "ks:ks_pop":69,
    "ks:ks_type":"HABITATION",
    "name:eng_x_preferred":[
        "Pipra"
    ],
    "wof:name":"Pipra",
    "wof:placetype":"locality",
    "wof:population":69
},
  "geometry": {"coordinates":[86.754704,24.68152],"type":"Point"}
}