{
  "type": "Feature",
  "properties": {
    "iso:country":"IN",
    "ks:ks_name":"Kaplitikra",
    "ks:ks_pop":47,
    "ks:ks_type":"HABITATION",
    "name:eng_x_preferred":[
        "Kaplitikra"
    ],
    "wof:name":"Kaplitikra",
    "wof:placetype":"locality",
    "wof:population":47
},
  "geometry": {"coordinates":[82.487689,22.735087],"type":"Point"}
}