{
  "type": "Feature",
  "properties": {
    "gn:admin1_code":"19.0",
    "gn:admin2_code":"572.0",
    "gn:asciiname":"Puradpalya",
    "gn:country_code":"IN",
    "gn:dem":863,
    "gn:feature_class":"P",
    "gn:feature_code":"PPL",
    "gn:name":"Puradp\u0101lya",
    "gn:population":0,
    "gn:timezone":"Asia/Kolkata",
    "iso:country":"IN",
    "wof:name":"Puradpalya",
    "wof:placetype":"locality"
},
  "geometry": {"coordinates":[77.37566,12.94696],"type":"Point"}
}