{
  "type": "Feature",
  "properties": {
    "iso:country":"IN",
    "ks:ks_name":"Cheto Poka",
    "ks:ks_pop":131,
    "ks:ks_type":"HABITATION",
    "name:eng_x_preferred":[
        "Cheto Poka"
    ],
    "wof:name":"Cheto Poka",
    "wof:placetype":"locality",
    "wof:population":131
},
  "geometry": {"coordinates":[87.37184499999999,24.481369],"type":"Point"}
}