{
  "type": "Feature",
  "properties": {
    "iso:country":"IN",
    "ks:ks_name":"Balasamuthiram",
    "ks:ks_pop":40,
    "ks:ks_type":"HABITATION",
    "name:eng_x_preferred":[
        "Balasamuthiram"
    ],
    "wof:name":"Balasamuthiram",
    "wof:placetype":"locality",
    "wof:population":40
},
  "geometry": {"coordinates":[78.001272,10.75961],"type":"Point"}
}