{
  "type": "Feature",
  "properties": {
    "iso:country":"IN",
    "ks:ks_name":"Pasiya Deeh",
    "ks:ks_pop":263,
    "ks:ks_type":"HABITATION",
    "name:eng_x_preferred":[
        "Pasiya Deeh"
    ],
    "wof:name":"Pasiya Deeh",
    "wof:placetype":"locality",
    "wof:population":263
},
  "geometry": {"coordinates":[83.043779,27.326559],"type":"Point"}
}