{
  "type": "Feature",
  "properties": {
    "iso:country":"IN",
    "ks:ks_name":"Kherkherigata",
    "ks:ks_pop":214,
    "ks:ks_type":"VILLAGE",
    "name:eng_x_preferred":[
        "Kherkherigata"
    ],
    "wof:name":"Kherkherigata",
    "wof:placetype":"locality",
    "wof:population":214
},
  "geometry": {"coordinates":[76.818611,24.177778],"type":"Point"}
}