{
  "type": "Feature",
  "properties": {
    "gn:admin1_code":"36",
    "gn:admin2_code":"152.0",
    "gn:asciiname":"Shamshipur",
    "gn:country_code":"IN",
    "gn:dem":149,
    "gn:feature_class":"P",
    "gn:feature_code":"PPL",
    "gn:name":"Shamshipur",
    "gn:population":0,
    "gn:timezone":"Asia/Kolkata",
    "iso:country":"IN",
    "ks:ks_name":"Shamshipur",
    "ks:ks_type":"VILLAGE",
    "name:eng_x_preferred":[
        "Shamshipur"
    ],
    "wof:name":"Shamshipur",
    "wof:placetype":"locality"
},
  "geometry": {"coordinates":[79.52251800000001,27.824598],"type":"Point"}
}