{
  "type": "Feature",
  "properties": {
    "iso:country":"IN",
    "ks:ks_name":"Badibarasi",
    "ks:ks_pop":742,
    "ks:ks_type":"VILLAGE",
    "name:eng_x_preferred":[
        "Badibarasi"
    ],
    "wof:name":"Badibarasi",
    "wof:placetype":"locality",
    "wof:population":742
},
  "geometry": {"coordinates":[88.416239,22.116823],"type":"Point"}
}