{
  "type": "Feature",
  "properties": {
    "iso:country":"IN",
    "ks:ks_name":"Belabad",
    "ks:ks_pop":75,
    "ks:ks_type":"VILLAGE",
    "name:eng_x_preferred":[
        "Belabad"
    ],
    "wof:name":"Belabad",
    "wof:placetype":"locality",
    "wof:population":75
},
  "geometry": {"coordinates":[86.83744799999999,24.248612],"type":"Point"}
}