{
  "type": "Feature",
  "properties": {
    "iso:country":"IN",
    "ks:ks_name":"Sardarnagar",
    "ks:ks_pop":227,
    "ks:ks_type":"HABITATION",
    "name:eng_x_preferred":[
        "Sardarnagar"
    ],
    "wof:name":"Sardarnagar",
    "wof:placetype":"locality",
    "wof:population":227
},
  "geometry": {"coordinates":[72.94525,22.70775],"type":"Point"}
}