{
  "type": "Feature",
  "properties": {
    "iso:country":"IN",
    "ks:ks_name":"Jamnagar",
    "ks:ks_pop":12264,
    "ks:ks_type":"VILLAGE",
    "ks:ks_uagg_main":0,
    "name:eng_x_preferred":[
        "Jamnagar"
    ],
    "wof:name":"Jamnagar",
    "wof:placetype":"neighbourhood",
    "wof:population":12264
},
  "geometry": {"coordinates":[87.84331400000001,24.998036],"type":"Point"}
}