{
  "type": "Feature",
  "properties": {
    "iso:country":"IN",
    "ks:ks_name":"Khamargachhi",
    "ks:ks_pop":630,
    "ks:ks_type":"VILLAGE",
    "ks:ks_uagg_main":0,
    "name:eng_x_preferred":[
        "Khamargachhi"
    ],
    "wof:name":"Khamargachhi",
    "wof:placetype":"locality",
    "wof:population":630
},
  "geometry": {"coordinates":[88.445584,23.061802],"type":"Point"}
}