{
  "type": "Feature",
  "properties": {
    "iso:country":"IN",
    "ks:ks_name":"12 KJD",
    "ks:ks_pop":1225,
    "ks:ks_type":"VILLAGE",
    "name:eng_x_preferred":[
        "12 KJD"
    ],
    "wof:name":"12 KJD",
    "wof:placetype":"locality",
    "wof:population":1225
},
  "geometry": {"coordinates":[72.68499799999999,28.671503],"type":"Point"}
}