{
  "type": "Feature",
  "properties": {
    "iso:country":"IN",
    "ks:ks_alt_nam":"MHASKEWASTI",
    "ks:ks_name":"Mhaskewasti",
    "ks:ks_pop":125,
    "ks:ks_type":"HABITATION",
    "name:eng_x_preferred":[
        "Mhaskewasti"
    ],
    "wof:name":"Mhaskewasti",
    "wof:placetype":"locality",
    "wof:population":125
},
  "geometry": {"coordinates":[74.653587,17.100194],"type":"Point"}
}