{
  "type": "Feature",
  "properties": {
    "gn:admin1_code":"9.0",
    "gn:admin2_code":"472.0",
    "gn:asciiname":"Kelo",
    "gn:country_code":"IN",
    "gn:dem":257,
    "gn:feature_class":"P",
    "gn:feature_code":"PPL",
    "gn:name":"Kelo",
    "gn:population":0,
    "gn:timezone":"Asia/Kolkata",
    "iso:country":"IN",
    "name:ben_x_preferred":[
        "\u0995\u09c7\u09b2\u09cb"
    ],
    "name:ceb_x_preferred":[
        "Kelo"
    ],
    "name:ell_x_preferred":[
        "\u039a\u03ad\u03bb\u03bf"
    ],
    "name:fin_x_preferred":[
        "Kelo"
    ],
    "name:heb_x_preferred":[
        "\u05e7\u05dc\u05d5"
    ],
    "name:hin_x_preferred":[
        "\u0915\u0947\u0932\u094b"
    ],
    "name:hun_x_preferred":[
        "Kelo"
    ],
    "name:ita_x_preferred":[
        "Kelo"
    ],
    "name:kor_x_preferred":[
        "\ucf08\ub85c"
    ],
    "name:nld_x_preferred":[
        "Kelo"
    ],
    "name:por_x_preferred":[
        "Kelo"
    ],
    "name:slk_x_preferred":[
        "Kelo"
    ],
    "name:swe_x_preferred":[
        "Kelo"
    ],
    "name:tur_x_preferred":[
        "Kelo"
    ],
    "name:ukr_x_preferred":[
        "\u041a\u0435\u043b\u043e"
    ],
    "name:vie_x_preferred":[
        "Kelo"
    ],
    "wof:name":"Kelo",
    "wof:placetype":"locality"
},
  "geometry": {"coordinates":[73.18527,24.00355],"type":"Point"}
}