{
  "type": "Feature",
  "properties": {
    "gn:admin1_code":"9.0",
    "gn:admin2_code":"472.0",
    "gn:asciiname":"Kelo",
    "gn:country_code":"IN",
    "gn:dem":257,
    "gn:feature_class":"P",
    "gn:feature_code":"PPL",
    "gn:name":"Kelo",
    "gn:population":0,
    "gn:timezone":"Asia/Kolkata",
    "iso:country":"IN",
    "name:ceb_x_preferred":[
        "Kelo"
    ],
    "name:fin_x_preferred":[
        "Kelo"
    ],
    "name:ita_x_preferred":[
        "Kelo"
    ],
    "name:nld_x_preferred":[
        "Kelo"
    ],
    "name:slk_x_preferred":[
        "Kelo"
    ],
    "name:swe_x_preferred":[
        "Kelo"
    ],
    "wof:name":"Kelo",
    "wof:placetype":"locality"
},
  "geometry": {"coordinates":[73.18526999999997,24.00355],"type":"Point"}
}