{
  "type": "Feature",
  "properties": {
    "iso:country":"IN",
    "ks:ks_name":"Goylon Ki Dhani",
    "ks:ks_pop":200,
    "ks:ks_type":"HABITATION",
    "name:eng_x_preferred":[
        "Goylon Ki Dhani"
    ],
    "wof:name":"Goylon Ki Dhani",
    "wof:placetype":"locality",
    "wof:population":200
},
  "geometry": {"coordinates":[71.43898299999999,25.692153],"type":"Point"}
}