{
  "type": "Feature",
  "properties": {
    "iso:country":"IN",
    "ks:ks_alt_nam":"MAHUWATOLI",
    "ks:ks_name":"Mahuwatoli",
    "ks:ks_pop":422,
    "ks:ks_type":"HABITATION",
    "name:eng_x_preferred":[
        "Mahuwatoli"
    ],
    "wof:name":"Mahuwatoli",
    "wof:placetype":"locality",
    "wof:population":422
},
  "geometry": {"coordinates":[83.86915,22.821364],"type":"Point"}
}