{
  "type": "Feature",
  "properties": {
    "iso:country":"IN",
    "ks:ks_name":"Raipura Brahman",
    "ks:ks_pop":1660,
    "ks:ks_type":"VILLAGE",
    "ks:ks_uagg_main":0,
    "name:eng_x_preferred":[
        "Raipura Brahman"
    ],
    "wof:name":"Raipura Brahman",
    "wof:placetype":"neighbourhood",
    "wof:population":1660
},
  "geometry": {"coordinates":[76.61792199999999,26.949641],"type":"Point"}
}