{
  "type": "Feature",
  "properties": {
    "iso:country":"IN",
    "ks:ks_name":"Kherli",
    "ks:ks_pop":593,
    "ks:ks_type":"VILLAGE",
    "ks:ks_uagg_main":0,
    "name:eng_x_preferred":[
        "Kherli"
    ],
    "wof:name":"Kherli",
    "wof:placetype":"locality",
    "wof:population":593
},
  "geometry": {"coordinates":[76.40022500000001,26.902983],"type":"Point"}
}