{
  "type": "Feature",
  "properties": {
    "gn:admin1_code":"25.0",
    "gn:admin2_code":"615.0",
    "gn:asciiname":"Perali",
    "gn:country_code":"IN",
    "gn:dem":118,
    "gn:feature_class":"P",
    "gn:feature_code":"PPL",
    "gn:name":"Perali",
    "gn:population":0,
    "gn:timezone":"Asia/Kolkata",
    "iso:country":"IN",
    "wof:name":"Perali",
    "wof:placetype":"locality"
},
  "geometry": {"coordinates":[78.95180999999999,11.23134],"type":"Point"}
}