{
  "type": "Feature",
  "properties": {
    "iso:country":"IN",
    "ks:ks_name":"Kumbargudde",
    "ks:ks_pop":239,
    "ks:ks_type":"HABITATION",
    "ks:ks_uagg_main":0,
    "name:eng_x_preferred":[
        "Kumbargudde"
    ],
    "wof:name":"Kumbargudde",
    "wof:placetype":"neighbourhood",
    "wof:population":239
},
  "geometry": {"coordinates":[74.751177,13.228523],"type":"Point"}
}