{
  "type": "Feature",
  "properties": {
    "iso:country":"IN",
    "ks:ks_alt_nam":"keelapasalai",
    "ks:ks_name":"Keelapasalai",
    "ks:ks_pop":2457,
    "ks:ks_type":"HABITATION",
    "ks:ks_uagg_main":1,
    "name:eng_x_preferred":[
        "Keelapasalai"
    ],
    "wof:name":"Keelapasalai",
    "wof:placetype":"neighbourhood",
    "wof:population":2457
},
  "geometry": {"coordinates":[78.45330199999999,9.685824],"type":"Point"}
}