{
  "type": "Feature",
  "properties": {
    "gn:admin1_code":"35",
    "gn:admin2_code":"422.0",
    "gn:asciiname":"Phattaghat",
    "gn:country_code":"IN",
    "gn:dem":249,
    "gn:feature_class":"P",
    "gn:feature_code":"PPL",
    "gn:name":"Phatt\u0101gh\u0101t",
    "gn:population":0,
    "gn:timezone":"Asia/Kolkata",
    "iso:country":"IN",
    "wof:name":"Phattaghat",
    "wof:placetype":"locality"
},
  "geometry": {"coordinates":[78.44404,25.60968],"type":"Point"}
}