{
  "type": "Feature",
  "properties": {
    "iso:country":"IN",
    "ks:ks_name":"Mushahri",
    "ks:ks_pop":514,
    "ks:ks_type":"HABITATION",
    "name:eng_x_preferred":[
        "Mushahri"
    ],
    "wof:name":"Mushahri",
    "wof:placetype":"locality",
    "wof:population":514
},
  "geometry": {"coordinates":[86.398467,25.231345],"type":"Point"}
}