{
  "type": "Feature",
  "properties": {
    "gn:admin1_code":"36",
    "gn:admin2_code":"148.0",
    "gn:asciiname":"Nagla Gadaria",
    "gn:country_code":"IN",
    "gn:dem":159,
    "gn:feature_class":"P",
    "gn:feature_code":"PPL",
    "gn:name":"Nagla Gadari\u0101",
    "gn:population":0,
    "gn:timezone":"Asia/Kolkata",
    "iso:country":"IN",
    "wof:name":"Nagla Gadaria",
    "wof:placetype":"neighbourhood"
},
  "geometry": {"coordinates":[79.05983999999999,27.30627],"type":"Point"}
}