{
  "type": "Feature",
  "properties": {
    "gn:admin1_code":"09",
    "gn:admin2_code":"480.0",
    "gn:asciiname":"Randhia",
    "gn:country_code":"IN",
    "gn:dem":169,
    "gn:feature_class":"P",
    "gn:feature_code":"PPL",
    "gn:name":"R\u0101ndhia",
    "gn:population":0,
    "gn:timezone":"Asia/Kolkata",
    "iso:country":"IN",
    "name:guj_x_preferred":[
        "\u0ab0\u0abe\u0a82\u0aa2\u0ac0\u0aaf\u0abe"
    ],
    "name:hin_x_preferred":[
        "\u0930\u093e\u0901\u0922\u0940\u092f\u093e"
    ],
    "wof:name":"Randhia",
    "wof:placetype":"locality"
},
  "geometry": {"coordinates":[71.14928,21.70598],"type":"Point"}
}