{
  "type": "Feature",
  "properties": {
    "gn:admin1_code":"34.0",
    "gn:admin2_code":"236.0",
    "gn:asciiname":"Sakhanwan",
    "gn:country_code":"IN",
    "gn:dem":139,
    "gn:feature_class":"P",
    "gn:feature_code":"PPL",
    "gn:name":"Sakhanw\u0101n",
    "gn:population":0,
    "gn:timezone":"Asia/Kolkata",
    "iso:country":"IN",
    "ks:ks_alt_nam":"Sakhanw\u0101n",
    "ks:ks_name":"Sakhanwan",
    "ks:ks_type":"VILLAGE",
    "name:eng_x_preferred":[
        "Sakhanwan"
    ],
    "name:eng_x_variant":[
        "Sakhanw\u0101n"
    ],
    "wof:name":"Sakhanwan",
    "wof:placetype":"locality"
},
  "geometry": {"coordinates":[84.965321,24.563709],"type":"Point"}
}