{
  "type": "Feature",
  "properties": {
    "gn:admin1_code":"36.0",
    "gn:admin2_code":"158.0",
    "gn:asciiname":"Pura Shamsher Bahadur",
    "gn:country_code":"IN",
    "gn:dem":118,
    "gn:feature_class":"P",
    "gn:feature_code":"PPL",
    "gn:name":"Pura Shamsher Bah\u0101dur",
    "gn:population":0,
    "gn:timezone":"Asia/Kolkata",
    "iso:country":"IN",
    "wof:name":"Pura Shamsher Bahadur",
    "wof:placetype":"locality"
},
  "geometry": {"coordinates":[81.22718,26.02999],"type":"Point"}
}