{
  "type": "Feature",
  "properties": {
    "iso:country":"IN",
    "ks:ks_name":"Seduthankuppam",
    "ks:ks_pop":522,
    "ks:ks_type":"HABITATION",
    "ks:ks_uagg_main":0,
    "name:eng_x_preferred":[
        "Seduthankuppam"
    ],
    "wof:name":"Seduthankuppam",
    "wof:placetype":"neighbourhood",
    "wof:population":522
},
  "geometry": {"coordinates":[79.47456,11.625409],"type":"Point"}
}