{
  "type": "Feature",
  "properties": {
    "iso:country":"IN",
    "ks:ks_name":"Nankuri",
    "ks:ks_pop":253,
    "ks:ks_type":"VILLAGE",
    "name:eng_x_preferred":[
        "Nankuri"
    ],
    "wof:name":"Nankuri",
    "wof:placetype":"locality",
    "wof:population":253
},
  "geometry": {"coordinates":[80.253015,29.755922],"type":"Point"}
}