{
  "type": "Feature",
  "properties": {
    "gn:admin1_code":"25",
    "gn:admin2_code":"620.0",
    "gn:asciiname":"Surakkottai",
    "gn:country_code":"IN",
    "gn:dem":56,
    "gn:feature_class":"P",
    "gn:feature_code":"PPL",
    "gn:name":"S\u016brakkottai",
    "gn:population":0,
    "gn:timezone":"Asia/Kolkata",
    "iso:country":"IN",
    "wof:name":"Surakkottai",
    "wof:placetype":"locality"
},
  "geometry": {"coordinates":[79.19001,10.7355],"type":"Point"}
}