{
  "type": "Feature",
  "properties": {
    "iso:country":"IN",
    "ks:ks_name":"Pratappur",
    "ks:ks_pop":0,
    "ks:ks_type":"VILLAGE",
    "name:eng_x_preferred":[
        "Pratappur"
    ],
    "wof:name":"Pratappur",
    "wof:placetype":"locality",
    "wof:population":0
},
  "geometry": {"coordinates":[85.006513,21.908789],"type":"Point"}
}