{
  "type": "Feature",
  "properties": {
    "iso:country":"IN",
    "ks:ks_alt_nam":"Eieven SMD Mammuwala",
    "ks:ks_name":"Eieven Smd Mammuwala",
    "ks:ks_pop":350,
    "ks:ks_type":"HABITATION",
    "name:eng_x_preferred":[
        "Eieven Smd Mammuwala"
    ],
    "wof:name":"Eieven Smd Mammuwala",
    "wof:placetype":"locality",
    "wof:population":350
},
  "geometry": {"coordinates":[72.512164,28.333911],"type":"Point"}
}