{
  "type": "Feature",
  "properties": {
    "iso:country":"IN",
    "ks:ks_name":"Bagaribari B",
    "ks:ks_pop":398,
    "ks:ks_type":"HABITATION",
    "name:eng_x_preferred":[
        "Bagaribari B"
    ],
    "wof:name":"Bagaribari B",
    "wof:placetype":"locality",
    "wof:population":398
},
  "geometry": {"coordinates":[92.303606,26.679465],"type":"Point"}
}