{
  "type": "Feature",
  "properties": {
    "gn:admin1_code":"36",
    "gn:admin2_code":"159.0",
    "gn:asciiname":"Sadhu Sarai",
    "gn:country_code":"IN",
    "gn:dem":146,
    "gn:feature_class":"P",
    "gn:feature_code":"PPL",
    "gn:name":"S\u0101dhu Sar\u0101i",
    "gn:population":0,
    "gn:timezone":"Asia/Kolkata",
    "iso:country":"IN",
    "ks:ks_name":"Sado Sarai",
    "ks:ks_pop":310,
    "ks:ks_type":"HABITATION",
    "name:eng_x_preferred":[
        "Sado Sarai"
    ],
    "name:eng_x_variant":[
        "Sadhu Sarai"
    ],
    "wof:name":"Sado Sarai",
    "wof:placetype":"locality",
    "wof:population":310
},
  "geometry": {"coordinates":[79.465019,27.561382],"type":"Point"}
}