{
  "type": "Feature",
  "properties": {
    "gn:admin1_code":"11.0",
    "gn:admin2_code":"25.0",
    "gn:asciiname":"Ruhling",
    "gn:country_code":"IN",
    "gn:dem":3093,
    "gn:feature_class":"P",
    "gn:feature_code":"PPL",
    "gn:name":"Ruhling",
    "gn:population":0,
    "gn:timezone":"Asia/Kolkata",
    "iso:country":"IN",
    "wof:name":"Ruhling",
    "wof:placetype":"locality"
},
  "geometry": {"coordinates":[76.76306,32.84093],"type":"Point"}
}