{
  "type": "Feature",
  "properties": {
    "iso:country":"IN",
    "ks:ks_name":"Paimagham",
    "ks:ks_pop":1361,
    "ks:ks_type":"VILLAGE",
    "ks:ks_uagg_main":0,
    "name:eng_x_preferred":[
        "Paimagham"
    ],
    "wof:name":"Paimagham",
    "wof:placetype":"neighbourhood",
    "wof:population":1361
},
  "geometry": {"coordinates":[78.958268,13.280172],"type":"Point"}
}