{
  "type": "Feature",
  "properties": {
    "iso:country":"IN",
    "ks:ks_name":"Nolepurwa",
    "ks:ks_pop":270,
    "ks:ks_type":"HABITATION",
    "name:eng_x_preferred":[
        "Nolepurwa"
    ],
    "wof:name":"Nolepurwa",
    "wof:placetype":"locality",
    "wof:population":270
},
  "geometry": {"coordinates":[79.971479,26.891723],"type":"Point"}
}