{
  "type": "Feature",
  "properties": {
    "gn:admin1_code":"36",
    "gn:admin2_code":"187.0",
    "gn:asciiname":"Pachrukhia",
    "gn:country_code":"IN",
    "gn:dem":96,
    "gn:feature_class":"P",
    "gn:feature_code":"PPL",
    "gn:name":"Pachrukhia",
    "gn:population":0,
    "gn:timezone":"Asia/Kolkata",
    "iso:country":"IN",
    "name:und_x_variant":[
        "Pipraich"
    ],
    "wof:name":"Pachrukhia",
    "wof:placetype":"neighbourhood"
},
  "geometry": {"coordinates":[83.65552,27.06466],"type":"Point"}
}