{
  "type": "Feature",
  "properties": {
    "iso:country":"IN",
    "ks:ks_name":"Vidhate Wasti",
    "ks:ks_pop":97,
    "ks:ks_type":"HABITATION",
    "name:eng_x_preferred":[
        "Vidhate Wasti"
    ],
    "wof:name":"Vidhate Wasti",
    "wof:placetype":"locality",
    "wof:population":97
},
  "geometry": {"coordinates":[76.068911,17.537143],"type":"Point"}
}