{
  "type": "Feature",
  "properties": {
    "iso:country":"IN",
    "ks:ks_name":"Mugalpur",
    "ks:ks_pop":445,
    "ks:ks_type":"VILLAGE",
    "name:eng_x_preferred":[
        "Mugalpur"
    ],
    "wof:name":"Mugalpur",
    "wof:placetype":"locality",
    "wof:population":445
},
  "geometry": {"coordinates":[95.747393,27.875553],"type":"Point"}
}