{
  "type": "Feature",
  "properties": {
    "iso:country":"IN",
    "ks:ks_name":"Gaurhi",
    "ks:ks_pop":159,
    "ks:ks_type":"HABITATION",
    "name:eng_x_preferred":[
        "Gaurhi"
    ],
    "wof:name":"Gaurhi",
    "wof:placetype":"locality",
    "wof:population":159
},
  "geometry": {"coordinates":[81.68005700000001,27.422477],"type":"Point"}
}