{
  "type": "Feature",
  "properties": {
    "iso:country":"IN",
    "ks:ks_name":"Sangana",
    "ks:ks_pop":161,
    "ks:ks_type":"VILLAGE",
    "name:eng_x_preferred":[
        "Sangana"
    ],
    "wof:name":"Sangana",
    "wof:placetype":"locality",
    "wof:population":161
},
  "geometry": {"coordinates":[71.123681,26.790422],"type":"Point"}
}