{
  "type": "Feature",
  "properties": {
    "iso:country":"IN",
    "ks:ks_name":"Jaypur",
    "ks:ks_pop":665,
    "ks:ks_type":"VILLAGE",
    "name:eng_x_preferred":[
        "Jaypur"
    ],
    "wof:name":"Jaypur",
    "wof:placetype":"locality",
    "wof:population":665
},
  "geometry": {"coordinates":[86.247708,20.827366],"type":"Point"}
}