{
  "type": "Feature",
  "properties": {
    "gn:admin1_code":"34.0",
    "gn:admin2_code":"234.0",
    "gn:asciiname":"Chorpokhar Inglis",
    "gn:country_code":"IN",
    "gn:dem":80,
    "gn:feature_class":"P",
    "gn:feature_code":"PPL",
    "gn:name":"Chorpokhar Inglis",
    "gn:population":0,
    "gn:timezone":"Asia/Kolkata",
    "iso:country":"IN",
    "wof:name":"Chorpokhar Inglis",
    "wof:placetype":"locality"
},
  "geometry": {"coordinates":[84.12508000000003,25.34728],"type":"Point"}
}