{
  "type": "Feature",
  "properties": {
    "gn:admin1_code":"12.0",
    "gn:admin2_code":"021",
    "gn:asciiname":"Keri",
    "gn:country_code":"IN",
    "gn:dem":571,
    "gn:feature_class":"P",
    "gn:feature_code":"PPL",
    "gn:name":"Keri",
    "gn:population":0,
    "gn:timezone":"Asia/Kolkata",
    "iso:country":"IN",
    "name:heb_x_preferred":[
        "\u05d1\u05e2\u05dc \u05e7\u05e8\u05d9"
    ],
    "wof:name":"Keri",
    "wof:placetype":"locality"
},
  "geometry": {"coordinates":[74.6082,32.93471],"type":"Point"}
}