{
  "type": "Feature",
  "properties": {
    "iso:country":"IN",
    "ks:ks_name":"Kokerama",
    "ks:ks_pop":75,
    "ks:ks_type":"HABITATION",
    "ks:ks_uagg_main":0,
    "name:eng_x_preferred":[
        "Kokerama"
    ],
    "wof:name":"Kokerama",
    "wof:placetype":"neighbourhood",
    "wof:population":75
},
  "geometry": {"coordinates":[84.311038,22.28286],"type":"Point"}
}