{
  "type": "Feature",
  "properties": {
    "iso:country":"IN",
    "ks:ks_name":"Dhos Doddi",
    "ks:ks_pop":54,
    "ks:ks_type":"HABITATION",
    "name:eng_x_preferred":[
        "Dhos Doddi"
    ],
    "wof:name":"Dhos Doddi",
    "wof:placetype":"locality",
    "wof:population":54
},
  "geometry": {"coordinates":[74.53850199999999,14.389269],"type":"Point"}
}