{
  "type": "Feature",
  "properties": {
    "iso:country":"IN",
    "ks:ks_name":"Khadari",
    "ks:ks_pop":38,
    "ks:ks_type":"HABITATION",
    "name:eng_x_preferred":[
        "Khadari"
    ],
    "wof:name":"Khadari",
    "wof:placetype":"locality",
    "wof:population":38
},
  "geometry": {"coordinates":[79.068269,23.79139],"type":"Point"}
}