{
  "type": "Feature",
  "properties": {
    "iso:country":"IN",
    "ks:ks_name":"Geduri Ganj",
    "ks:ks_pop":195,
    "ks:ks_type":"HABITATION",
    "name:eng_x_preferred":[
        "Geduri Ganj"
    ],
    "wof:name":"Geduri Ganj",
    "wof:placetype":"locality",
    "wof:population":195
},
  "geometry": {"coordinates":[82.796662,26.331621],"type":"Point"}
}