{
  "type": "Feature",
  "properties": {
    "iso:country":"IN",
    "ks:ks_name":"Bannigiridoddi",
    "ks:ks_pop":190,
    "ks:ks_type":"HABITATION",
    "name:eng_x_preferred":[
        "Bannigiridoddi"
    ],
    "wof:name":"Bannigiridoddi",
    "wof:placetype":"locality",
    "wof:population":190
},
  "geometry": {"coordinates":[77.59551500000001,12.503389],"type":"Point"}
}