{
  "type": "Feature",
  "properties": {
    "gn:admin1_code":"37",
    "gn:admin2_code":"406.0",
    "gn:asciiname":"Pondi",
    "gn:country_code":"IN",
    "gn:dem":289,
    "gn:feature_class":"P",
    "gn:feature_code":"PPL",
    "gn:name":"Pond\u012b",
    "gn:population":0,
    "gn:timezone":"Asia/Kolkata",
    "iso:country":"IN",
    "name:ceb_x_preferred":[
        "Pondi"
    ],
    "name:swe_x_preferred":[
        "Pondi"
    ],
    "wof:name":"Pondi",
    "wof:placetype":"locality"
},
  "geometry": {"coordinates":[82.06228,22.16242],"type":"Point"}
}