{
  "type": "Feature",
  "properties": {
    "gn:admin1_code":"11",
    "gn:admin2_code":"23.0",
    "gn:asciiname":"Singra Adwar",
    "gn:country_code":"IN",
    "gn:dem":2685,
    "gn:feature_class":"P",
    "gn:feature_code":"PPL",
    "gn:name":"Singra Adw\u0101r",
    "gn:population":0,
    "gn:timezone":"Asia/Kolkata",
    "iso:country":"IN",
    "wof:name":"Singra Adwar",
    "wof:placetype":"locality"
},
  "geometry": {"coordinates":[76.15304999999999,32.97168],"type":"Point"}
}