{
  "type": "Feature",
  "properties": {
    "iso:country":"IN",
    "ks:ks_name":"Samaypara",
    "ks:ks_pop":0,
    "ks:ks_type":"VILLAGE",
    "name:eng_x_preferred":[
        "Samaypara"
    ],
    "wof:name":"Samaypara",
    "wof:placetype":"locality",
    "wof:population":0
},
  "geometry": {"coordinates":[87.232462,22.864607],"type":"Point"}
}