{
  "type": "Feature",
  "properties": {
    "iso:country":"IN",
    "ks:ks_name":"Pawarwasti I",
    "ks:ks_pop":225,
    "ks:ks_type":"HABITATION",
    "name:eng_x_preferred":[
        "Pawarwasti I"
    ],
    "wof:name":"Pawarwasti I",
    "wof:placetype":"locality",
    "wof:population":225
},
  "geometry": {"coordinates":[74.83866399999999,18.635488],"type":"Point"}
}