{
  "type": "Feature",
  "properties": {
    "iso:country":"IN",
    "ks:ks_name":"Sevrimal",
    "ks:ks_pop":988,
    "ks:ks_type":"VILLAGE",
    "name:eng_x_preferred":[
        "Sevrimal"
    ],
    "wof:name":"Sevrimal",
    "wof:placetype":"locality",
    "wof:population":988
},
  "geometry": {"coordinates":[75.461197,22.394026],"type":"Point"}
}