{
  "type": "Feature",
  "properties": {
    "iso:country":"IN",
    "ks:ks_name":"Sakal Mathgaon",
    "ks:ks_pop":41,
    "ks:ks_type":"HABITATION",
    "name:eng_x_preferred":[
        "Sakal Mathgaon"
    ],
    "wof:name":"Sakal Mathgaon",
    "wof:placetype":"locality",
    "wof:population":41
},
  "geometry": {"coordinates":[74.39479300000001,14.987705],"type":"Point"}
}