{
  "type": "Feature",
  "properties": {
    "gn:admin1_code":"31",
    "gn:admin2_code":"287.0",
    "gn:asciiname":"Lawngtlai",
    "gn:country_code":"IN",
    "gn:dem":816,
    "gn:feature_class":"P",
    "gn:feature_code":"PPL",
    "gn:name":"Lawngtlai",
    "gn:population":0,
    "gn:timezone":"Asia/Kolkata",
    "iso:country":"IN",
    "name:ceb_x_preferred":[
        "Lawngtlai"
    ],
    "name:guj_x_preferred":[
        "\u0ab2\u0acb\u0aa8\u0acd\u0a97\u0aa4\u0ab2\u0abe\u0a87"
    ],
    "name:hin_x_preferred":[
        "\u0932\u094c\u0902\u0917\u0924\u094d\u0932\u093e\u0907"
    ],
    "name:ita_x_preferred":[
        "Lawngtlai"
    ],
    "name:mlg_x_preferred":[
        "Lawngtlai"
    ],
    "name:san_x_preferred":[
        "\u0932\u094c\u0919\u094d\u0917\u0924\u094d\u0932\u093e\u092f"
    ],
    "name:swe_x_preferred":[
        "Lawngtlai"
    ],
    "name:tam_x_preferred":[
        "\u0bb2\u0bbe\u0b99\u0bcd\u0ba4\u0bb2\u0bbe\u0baf\u0bcd"
    ],
    "name:urd_x_preferred":[
        "\u0644\u0627\u0648\u0646\u06af\u062a\u0644\u0627\u0626\u06cc"
    ],
    "wof:name":"Lawngtlai",
    "wof:placetype":"locality"
},
  "geometry": {"coordinates":[92.89901999999999,22.53254],"type":"Point"}
}