{
  "type": "Feature",
  "properties": {
    "gn:admin1_code":"31",
    "gn:admin2_code":"287.0",
    "gn:asciiname":"Lawngtlai",
    "gn:country_code":"IN",
    "gn:dem":816,
    "gn:feature_class":"P",
    "gn:feature_code":"PPL",
    "gn:name":"Lawngtlai",
    "gn:population":0,
    "gn:timezone":"Asia/Kolkata",
    "iso:country":"IN",
    "wof:name":"Lawngtlai",
    "wof:placetype":"locality"
},
  "geometry": {"coordinates":[92.89901999999999,22.53254],"type":"Point"}
}