{
  "type": "Feature",
  "properties": {
    "iso:country":"IN",
    "ks:ks_name":"Manirahi Tola",
    "ks:ks_pop":515,
    "ks:ks_type":"HABITATION",
    "name:eng_x_preferred":[
        "Manirahi Tola"
    ],
    "wof:name":"Manirahi Tola",
    "wof:placetype":"locality",
    "wof:population":515
},
  "geometry": {"coordinates":[86.90834599999999,25.940967],"type":"Point"}
}