{
  "type": "Feature",
  "properties": {
    "iso:country":"IN",
    "ks:ks_name":"Ramgondanahalli",
    "ks:ks_pop":1208,
    "ks:ks_type":"VILLAGE",
    "ks:ks_uagg_main":0,
    "name:eng_x_preferred":[
        "Ramgondanahalli"
    ],
    "wof:name":"Ramgondanahalli",
    "wof:placetype":"neighbourhood",
    "wof:population":1208
},
  "geometry": {"coordinates":[75.48052300000001,14.666119],"type":"Point"}
}