{
  "type": "Feature",
  "properties": {
    "iso:country":"IN",
    "ks:ks_name":"Morangaon",
    "ks:ks_pop":1121,
    "ks:ks_type":"VILLAGE",
    "name:eng_x_preferred":[
        "Morangaon"
    ],
    "wof:name":"Morangaon",
    "wof:placetype":"locality",
    "wof:population":1121
},
  "geometry": {"coordinates":[93.896794,26.242793],"type":"Point"}
}