{
  "type": "Feature",
  "properties": {
    "iso:country":"IN",
    "ks:ks_name":"Darlong Para",
    "ks:ks_pop":157,
    "ks:ks_type":"HABITATION",
    "name:eng_x_preferred":[
        "Darlong Para"
    ],
    "wof:name":"Darlong Para",
    "wof:placetype":"locality",
    "wof:population":157
},
  "geometry": {"coordinates":[92.260634,24.221656],"type":"Point"}
}