{
  "type": "Feature",
  "properties": {
    "gn:admin1_code":"35",
    "gn:admin2_code":"451.0",
    "gn:asciiname":"Rampuri",
    "gn:country_code":"IN",
    "gn:dem":395,
    "gn:feature_class":"P",
    "gn:feature_code":"PPL",
    "gn:name":"R\u0101mpuri",
    "gn:population":0,
    "gn:timezone":"Asia/Kolkata",
    "iso:country":"IN",
    "name:tam_x_preferred":[
        "\u0bb0\u0bbe\u0bae\u0bcd\u0baa\u0bc1\u0bb0\u0bbf"
    ],
    "wof:name":"Rampuri",
    "wof:placetype":"neighbourhood"
},
  "geometry": {"coordinates":[79.98231,23.07013],"type":"Point"}
}