{
  "type": "Feature",
  "properties": {
    "iso:country":"IN",
    "ks:ks_name":"Hatiaganda",
    "ks:ks_pop":1340,
    "ks:ks_type":"VILLAGE",
    "name:eng_x_preferred":[
        "Hatiaganda"
    ],
    "wof:name":"Hatiaganda",
    "wof:placetype":"locality",
    "wof:population":1340
},
  "geometry": {"coordinates":[86.83352600000001,21.494585],"type":"Point"}
}