{
  "type": "Feature",
  "properties": {
    "iso:country":"IN",
    "ks:ks_name":"Merengagudi",
    "ks:ks_pop":78,
    "ks:ks_type":"HABITATION",
    "name:eng_x_preferred":[
        "Merengagudi"
    ],
    "wof:name":"Merengagudi",
    "wof:placetype":"locality",
    "wof:population":78
},
  "geometry": {"coordinates":[83.82468,19.451481],"type":"Point"}
}