{
  "type": "Feature",
  "properties": {
    "iso:country":"IN",
    "ks:ks_name":"Mahal Badowal",
    "ks:ks_pop":50,
    "ks:ks_type":"VILLAGE",
    "name:eng_x_preferred":[
        "Mahal Badowal"
    ],
    "wof:name":"Mahal Badowal",
    "wof:placetype":"locality",
    "wof:population":50
},
  "geometry": {"coordinates":[75.93714199999999,31.066059],"type":"Point"}
}