{
  "type": "Feature",
  "properties": {
    "gn:admin1_code":"13.0",
    "gn:admin2_code":"595.0",
    "gn:asciiname":"Athani",
    "gn:country_code":"IN",
    "gn:dem":11,
    "gn:feature_class":"P",
    "gn:feature_code":"PPL",
    "gn:name":"Athani",
    "gn:population":0,
    "gn:timezone":"Asia/Kolkata",
    "iso:country":"IN",
    "name:tam_x_preferred":[
        "\u0b85\u0ba4\u0bcd\u0ba4\u0bbe\u0ba3\u0bbf"
    ],
    "name:vie_x_preferred":[
        "Athani"
    ],
    "wof:name":"Athani",
    "wof:placetype":"neighbourhood"
},
  "geometry": {"coordinates":[76.35523999999999,10.15397],"type":"Point"}
}