{
  "type": "Feature",
  "properties": {
    "gn:admin1_code":"2",
    "gn:admin2_code":"544.0",
    "gn:asciiname":"Kottapalem",
    "gn:country_code":"IN",
    "gn:dem":300,
    "gn:feature_class":"P",
    "gn:feature_code":"PPL",
    "gn:name":"Kottap\u0101lem",
    "gn:population":0,
    "gn:timezone":"Asia/Kolkata",
    "iso:country":"IN",
    "ks:ks_name":"Kothapalem",
    "ks:ks_pop":62,
    "ks:ks_type":"VILLAGE",
    "name:eng_x_preferred":[
        "Kothapalem"
    ],
    "name:eng_x_variant":[
        "Kottapalem"
    ],
    "wof:name":"Kothapalem",
    "wof:placetype":"locality",
    "wof:population":62
},
  "geometry": {"coordinates":[82.394739,17.758757],"type":"Point"}
}