{
  "type": "Feature",
  "properties": {
    "iso:country":"IN",
    "ks:ks_name":"Chengeli Gaon",
    "ks:ks_pop":280,
    "ks:ks_type":"HABITATION",
    "name:eng_x_preferred":[
        "Chengeli Gaon"
    ],
    "wof:name":"Chengeli Gaon",
    "wof:placetype":"locality",
    "wof:population":280
},
  "geometry": {"coordinates":[95.699442,27.669375],"type":"Point"}
}