{
  "type": "Feature",
  "properties": {
    "gn:admin1_code":"34.0",
    "gn:admin2_code":"215",
    "gn:asciiname":"Jogiara",
    "gn:country_code":"IN",
    "gn:dem":62,
    "gn:feature_class":"P",
    "gn:feature_code":"PPL",
    "gn:name":"Jogi\u0101ra",
    "gn:population":0,
    "gn:timezone":"Asia/Kolkata",
    "iso:country":"IN",
    "name:und_x_variant":[
        "Jogi\u0101ra"
    ],
    "wof:name":"Jogiara",
    "wof:placetype":"locality"
},
  "geometry": {"coordinates":[85.75041,26.4092],"type":"Point"}
}