{
  "type": "Feature",
  "properties": {
    "gn:admin1_code":"28.0",
    "gn:admin2_code":"327.0",
    "gn:asciiname":"Kamjer",
    "gn:country_code":"IN",
    "gn:dem":993,
    "gn:feature_class":"P",
    "gn:feature_code":"PPL",
    "gn:name":"Kamjer",
    "gn:population":0,
    "gn:timezone":"Asia/Kolkata",
    "iso:country":"IN",
    "wof:name":"Kamjer",
    "wof:placetype":"locality"
},
  "geometry": {"coordinates":[88.54876999999998,27.05328],"type":"Point"}
}