{
  "type": "Feature",
  "properties": {
    "iso:country":"IN",
    "ks:ks_name":"Upperpara",
    "ks:ks_pop":313,
    "ks:ks_type":"HABITATION",
    "name:eng_x_preferred":[
        "Upperpara"
    ],
    "wof:name":"Upperpara",
    "wof:placetype":"locality",
    "wof:population":313
},
  "geometry": {"coordinates":[82.351337,22.495052],"type":"Point"}
}