{
  "type": "Feature",
  "properties": {
    "gn:admin1_code":"36.0",
    "gn:admin2_code":"173.0",
    "gn:asciiname":"Purwa Hanuman",
    "gn:country_code":"IN",
    "gn:dem":104,
    "gn:feature_class":"P",
    "gn:feature_code":"PPL",
    "gn:name":"Purwa Han\u016bm\u0101n",
    "gn:population":0,
    "gn:timezone":"Asia/Kolkata",
    "iso:country":"IN",
    "ks:ks_alt_nam":"PURE AHIRAN",
    "ks:ks_name":"Pure Ahiran",
    "ks:ks_pop":68,
    "ks:ks_type":"HABITATION",
    "name:eng_x_preferred":[
        "Pure Ahiran"
    ],
    "name:eng_x_variant":[
        "Purwa Hanuman"
    ],
    "wof:name":"Pure Ahiran",
    "wof:placetype":"locality",
    "wof:population":68
},
  "geometry": {"coordinates":[81.84975799999999,26.049056],"type":"Point"}
}