{
  "type": "Feature",
  "properties": {
    "iso:country":"IN",
    "ks:ks_name":"Durekarwadi",
    "ks:ks_pop":141,
    "ks:ks_type":"HABITATION",
    "name:eng_x_preferred":[
        "Durekarwadi"
    ],
    "wof:name":"Durekarwadi",
    "wof:placetype":"locality",
    "wof:population":141
},
  "geometry": {"coordinates":[73.730352,15.895495],"type":"Point"}
}