{
  "type": "Feature",
  "properties": {
    "gn:admin1_code":"35",
    "gn:admin2_code":"422.0",
    "gn:asciiname":"Khiria",
    "gn:country_code":"IN",
    "gn:dem":218,
    "gn:feature_class":"P",
    "gn:feature_code":"PPL",
    "gn:name":"Khiria",
    "gn:population":0,
    "gn:timezone":"Asia/Kolkata",
    "iso:country":"IN",
    "name:tam_x_preferred":[
        "\u0b95\u0bc0\u0bb0\u0bbf\u0baf\u0bbe"
    ],
    "wof:name":"Khiria",
    "wof:placetype":"locality"
},
  "geometry": {"coordinates":[78.30126,25.71336],"type":"Point"}
}