{
  "type": "Feature",
  "properties": {
    "iso:country":"IN",
    "ks:ks_alt_nam":"Longle ethan",
    "ks:ks_name":"Longle Ethan",
    "ks:ks_pop":466,
    "ks:ks_type":"HABITATION",
    "name:eng_x_preferred":[
        "Longle Ethan"
    ],
    "wof:name":"Longle Ethan",
    "wof:placetype":"locality",
    "wof:population":466
},
  "geometry": {"coordinates":[92.556383,25.764085],"type":"Point"}
}