{
  "type": "Feature",
  "properties": {
    "iso:country":"IN",
    "ks:ks_name":"Lukuiya",
    "ks:ks_pop":0,
    "ks:ks_type":"VILLAGE",
    "name:eng_x_preferred":[
        "Lukuiya"
    ],
    "wof:name":"Lukuiya",
    "wof:placetype":"locality",
    "wof:population":0
},
  "geometry": {"coordinates":[85.34710200000001,23.744633],"type":"Point"}
}