{
  "type": "Feature",
  "properties": {
    "iso:country":"IN",
    "name:eng_x_preferred":[
        "Pali"
    ],
    "name:unk_x_variant":[
        "Pali"
    ],
    "qs:gn_adm0_cc":"IN",
    "qs:gn_local":1277882,
    "qs:gn_nam_loc":"Baghpat, Baghpat, Uttar Pradesh, IN",
    "qs:gn_namadm1":"36",
    "qs:local_max":5,
    "qs:local_sum":5,
    "qs:localhoods":1,
    "qs:name":"Pali",
    "qs:name_adm0":"India",
    "qs:name_adm1":"Uttar Pradesh",
    "qs:name_adm2":"Baghpat",
    "qs:name_local":"Baghpat",
    "qs:photo_max":3,
    "qs:photo_sum":5,
    "qs:placetype":"Suburb",
    "qs:quad_count":2,
    "qs:woe_adm0":23424848,
    "qs:woe_adm1":2345760,
    "qs:woe_adm2":12586721,
    "qs:woe_lau":0,
    "qs:woe_local":2291163,
    "qs:woe_ver":"7.10.0",
    "wof:lang":[
        "eng"
    ],
    "wof:name":"Pali",
    "wof:placetype":"neighbourhood"
},
  "geometry": {"coordinates":[77.27179,28.952879],"type":"Point"}
}