{
  "type": "Feature",
  "properties": {
    "iso:country":"IN",
    "ks:ks_name":"Ramnagar",
    "ks:ks_pop":316,
    "ks:ks_type":"VILLAGE",
    "name:eng_x_preferred":[
        "Ramnagar"
    ],
    "wof:name":"Ramnagar",
    "wof:placetype":"locality",
    "wof:population":316
},
  "geometry": {"coordinates":[72.71361899999999,26.446481],"type":"Point"}
}