{
  "type": "Feature",
  "properties": {
    "iso:country":"IN",
    "ks:ks_name":"Jotpura",
    "ks:ks_pop":153,
    "ks:ks_type":"VILLAGE",
    "name:eng_x_preferred":[
        "Jotpura"
    ],
    "wof:name":"Jotpura",
    "wof:placetype":"locality",
    "wof:population":153
},
  "geometry": {"coordinates":[75.431741,21.982164],"type":"Point"}
}