{
  "type": "Feature",
  "properties": {
    "iso:country":"IN",
    "ks:ks_name":"Chakapaju",
    "ks:ks_pop":71,
    "ks:ks_type":"VILLAGE",
    "name:eng_x_preferred":[
        "Chakapaju"
    ],
    "wof:name":"Chakapaju",
    "wof:placetype":"locality",
    "wof:population":71
},
  "geometry": {"coordinates":[84.633534,20.214064],"type":"Point"}
}