{
  "type": "Feature",
  "properties": {
    "iso:country":"IN",
    "ks:ks_alt_nam":"FAKEERE PURAWA",
    "ks:ks_name":"Fakeere Purawa",
    "ks:ks_pop":15,
    "ks:ks_type":"HABITATION",
    "ks:ks_uagg_main":0,
    "name:eng_x_preferred":[
        "Fakeere Purawa"
    ],
    "wof:name":"Fakeere Purawa",
    "wof:placetype":"neighbourhood",
    "wof:population":15
},
  "geometry": {"coordinates":[80.35184,26.713248],"type":"Point"}
}