{
  "type": "Feature",
  "properties": {
    "iso:country":"IN",
    "ks:ks_name":"Dhamanapadar",
    "ks:ks_pop":212,
    "ks:ks_type":"VILLAGE",
    "name:eng_x_preferred":[
        "Dhamanapadar"
    ],
    "wof:name":"Dhamanapadar",
    "wof:placetype":"locality",
    "wof:population":212
},
  "geometry": {"coordinates":[84.60958599999999,19.277492],"type":"Point"}
}