{
  "type": "Feature",
  "properties": {
    "gn:admin1_code":"12",
    "gn:admin2_code":"14.0",
    "gn:asciiname":"Dudal",
    "gn:country_code":"IN",
    "gn:dem":3430,
    "gn:feature_class":"P",
    "gn:feature_code":"PPL",
    "gn:name":"Dudal",
    "gn:population":0,
    "gn:timezone":"Asia/Kolkata",
    "iso:country":"IN",
    "wof:name":"Dudal",
    "wof:placetype":"locality"
},
  "geometry": {"coordinates":[75.42053,34.05904],"type":"Point"}
}