{
  "type": "Feature",
  "properties": {
    "iso:country":"IN",
    "ks:ks_name":"Kapdisar",
    "ks:ks_pop":718,
    "ks:ks_type":"HABITATION",
    "name:eng_x_preferred":[
        "Kapdisar"
    ],
    "wof:name":"Kapdisar",
    "wof:placetype":"locality",
    "wof:population":718
},
  "geometry": {"coordinates":[72.177542,27.142783],"type":"Point"}
}