{
  "type": "Feature",
  "properties": {
    "gn:admin1_code":"23",
    "gn:admin2_code":"38.0",
    "gn:asciiname":"Bhagian",
    "gn:country_code":"IN",
    "gn:dem":258,
    "gn:feature_class":"P",
    "gn:feature_code":"PPL",
    "gn:name":"Bhagi\u0101n",
    "gn:population":0,
    "gn:timezone":"Asia/Kolkata",
    "iso:country":"IN",
    "wof:name":"Bhagian",
    "wof:placetype":"neighbourhood"
},
  "geometry": {"coordinates":[75.71177,31.6231],"type":"Point"}
}