{
  "type": "Feature",
  "properties": {
    "gn:admin1_code":"35",
    "gn:admin2_code":"424.0",
    "gn:asciiname":"Bhaunrkhali",
    "gn:country_code":"IN",
    "gn:dem":325,
    "gn:feature_class":"P",
    "gn:feature_code":"PPL",
    "gn:name":"Bhaunrkhali",
    "gn:population":0,
    "gn:timezone":"Asia/Kolkata",
    "iso:country":"IN",
    "wof:name":"Bhaunrkhali",
    "wof:placetype":"locality"
},
  "geometry": {"coordinates":[78.6979,24.9188],"type":"Point"}
}