{
  "type": "Feature",
  "properties": {
    "iso:country":"IN",
    "ks:ks_name":"Deora Raja",
    "ks:ks_pop":196,
    "ks:ks_type":"HABITATION",
    "name:eng_x_preferred":[
        "Deora Raja"
    ],
    "wof:name":"Deora Raja",
    "wof:placetype":"locality",
    "wof:population":196
},
  "geometry": {"coordinates":[83.15213300000001,24.674642],"type":"Point"}
}