{
  "type": "Feature",
  "properties": {
    "gn:admin1_code":"36.0",
    "gn:admin2_code":"175.0",
    "gn:asciiname":"Bishanpur",
    "gn:country_code":"IN",
    "gn:dem":104,
    "gn:feature_class":"P",
    "gn:feature_code":"PPL",
    "gn:name":"Bishanpur",
    "gn:population":0,
    "gn:timezone":"Asia/Kolkata",
    "iso:country":"IN",
    "name:und_x_variant":[
        "Sar\u0101i Bh\u0101rat"
    ],
    "wof:name":"Bishanpur",
    "wof:placetype":"locality"
},
  "geometry": {"coordinates":[81.79266,25.62811],"type":"Point"}
}