{
  "type": "Feature",
  "properties": {
    "gn:admin1_code":"31.0",
    "gn:admin2_code":"282.0",
    "gn:asciiname":"Kawnpur",
    "gn:country_code":"IN",
    "gn:dem":736,
    "gn:feature_class":"P",
    "gn:feature_code":"PPL",
    "gn:name":"Kawnpur",
    "gn:population":0,
    "gn:timezone":"Asia/Kolkata",
    "iso:country":"IN",
    "wof:name":"Kawnpur",
    "wof:placetype":"locality"
},
  "geometry": {"coordinates":[92.6756,24.04758],"type":"Point"}
}