{
  "type": "Feature",
  "properties": {
    "gn:admin1_code":"38.0",
    "gn:admin2_code":"349",
    "gn:asciiname":"Koiridih",
    "gn:country_code":"IN",
    "gn:dem":313,
    "gn:feature_class":"P",
    "gn:feature_code":"PPL",
    "gn:name":"Koiridih",
    "gn:population":0,
    "gn:timezone":"Asia/Kolkata",
    "iso:country":"IN",
    "wof:name":"Koiridih",
    "wof:placetype":"locality"
},
  "geometry": {"coordinates":[86.00579,24.1457],"type":"Point"}
}