{
  "type": "Feature",
  "properties": {
    "iso:country":"IN",
    "ks:ks_name":"Gaya Deen Deeh",
    "ks:ks_pop":110,
    "ks:ks_type":"HABITATION",
    "name:eng_x_preferred":[
        "Gaya Deen Deeh"
    ],
    "wof:name":"Gaya Deen Deeh",
    "wof:placetype":"locality",
    "wof:population":110
},
  "geometry": {"coordinates":[82.31482,27.208012],"type":"Point"}
}