{
  "type": "Feature",
  "properties": {
    "iso:country":"IN",
    "ks:ks_name":"Duliamau",
    "ks:ks_pop":0,
    "ks:ks_type":"VILLAGE",
    "name:eng_x_preferred":[
        "Duliamau"
    ],
    "wof:name":"Duliamau",
    "wof:placetype":"locality",
    "wof:population":0
},
  "geometry": {"coordinates":[83.098465,25.691174],"type":"Point"}
}