{
  "type": "Feature",
  "properties": {
    "gn:admin1_code":"12.0",
    "gn:admin2_code":"006",
    "gn:asciiname":"Thanda Dab",
    "gn:country_code":"IN",
    "gn:dem":1164,
    "gn:feature_class":"P",
    "gn:feature_code":"PPL",
    "gn:name":"Thanda Dab",
    "gn:population":0,
    "gn:timezone":"Asia/Kolkata",
    "iso:country":"IN",
    "wof:name":"Thanda Dab",
    "wof:placetype":"locality"
},
  "geometry": {"coordinates":[74.22988000000002,33.23792],"type":"Point"}
}