{
  "type": "Feature",
  "properties": {
    "iso:country":"IN",
    "ks:ks_name":"Deguvapalli",
    "ks:ks_pop":74,
    "ks:ks_type":"HABITATION",
    "name:eng_x_preferred":[
        "Deguvapalli"
    ],
    "wof:name":"Deguvapalli",
    "wof:placetype":"locality",
    "wof:population":74
},
  "geometry": {"coordinates":[78.342448,14.193699],"type":"Point"}
}