{
  "type": "Feature",
  "properties": {
    "iso:country":"IN",
    "ks:ks_name":"Singilikuppam",
    "ks:ks_pop":310,
    "ks:ks_type":"VILLAGE",
    "ks:ks_uagg_main":0,
    "name:eng_x_preferred":[
        "Singilikuppam"
    ],
    "wof:name":"Singilikuppam",
    "wof:placetype":"locality",
    "wof:population":310
},
  "geometry": {"coordinates":[80.098814,13.216831],"type":"Point"}
}