{
  "type": "Feature",
  "properties": {
    "gn:admin1_code":"21.0",
    "gn:admin2_code":"398.0",
    "gn:asciiname":"Dengaguda",
    "gn:country_code":"IN",
    "gn:dem":809,
    "gn:feature_class":"P",
    "gn:feature_code":"PPL",
    "gn:name":"Dengaguda",
    "gn:population":0,
    "gn:timezone":"Asia/Kolkata",
    "iso:country":"IN",
    "wof:name":"Dengaguda",
    "wof:placetype":"locality"
},
  "geometry": {"coordinates":[82.74642,18.82037],"type":"Point"}
}