{
  "type": "Feature",
  "properties": {
    "gn:admin1_code":"25.0",
    "gn:admin2_code":"602",
    "gn:asciiname":"Mettupalaiyam",
    "gn:country_code":"IN",
    "gn:dem":7,
    "gn:feature_class":"P",
    "gn:feature_code":"PPL",
    "gn:name":"Mettupalaiyam",
    "gn:population":0,
    "gn:timezone":"Asia/Kolkata",
    "iso:country":"IN",
    "wof:name":"Mettupalaiyam",
    "wof:placetype":"neighbourhood"
},
  "geometry": {"coordinates":[80.29778,13.14639],"type":"Point"}
}