{
  "type": "Feature",
  "properties": {
    "iso:country":"IN",
    "ks:ks_name":"Lokkere",
    "ks:ks_pop":102,
    "ks:ks_type":"VILLAGE",
    "name:eng_x_preferred":[
        "Lokkere"
    ],
    "wof:name":"Lokkere",
    "wof:placetype":"locality",
    "wof:population":102
},
  "geometry": {"coordinates":[76.703506,11.663235],"type":"Point"}
}