{
  "type": "Feature",
  "properties": {
    "iso:country":"IN",
    "ks:ks_name":"Nabinbari",
    "ks:ks_pop":443,
    "ks:ks_type":"HABITATION",
    "ks:ks_uagg_main":0,
    "name:eng_x_preferred":[
        "Nabinbari"
    ],
    "wof:name":"Nabinbari",
    "wof:placetype":"neighbourhood",
    "wof:population":443
},
  "geometry": {"coordinates":[91.79525099999999,24.147707],"type":"Point"}
}