{
  "type": "Feature",
  "properties": {
    "iso:country":"IN",
    "ks:ks_name":"Bawdichapa",
    "ks:ks_pop":1172,
    "ks:ks_type":"HABITATION",
    "name:eng_x_preferred":[
        "Bawdichapa"
    ],
    "wof:name":"Bawdichapa",
    "wof:placetype":"locality",
    "wof:population":1172
},
  "geometry": {"coordinates":[76.71135,25.499189],"type":"Point"}
}