{
  "type": "Feature",
  "properties": {
    "iso:country":"IN",
    "ks:ks_alt_nam":"Kahar tola",
    "ks:ks_name":"Kahar Tola",
    "ks:ks_pop":48,
    "ks:ks_type":"HABITATION",
    "ks:ks_uagg_main":0,
    "name:eng_x_preferred":[
        "Kahar Tola"
    ],
    "wof:name":"Kahar Tola",
    "wof:placetype":"neighbourhood",
    "wof:population":48
},
  "geometry": {"coordinates":[87.34410800000001,26.25875],"type":"Point"}
}