{
  "type": "Feature",
  "properties": {
    "gn:admin1_code":"21",
    "gn:admin2_code":"395.0",
    "gn:asciiname":"Khaing",
    "gn:country_code":"IN",
    "gn:dem":308,
    "gn:feature_class":"P",
    "gn:feature_code":"PPL",
    "gn:name":"Khaing",
    "gn:population":0,
    "gn:timezone":"Asia/Kolkata",
    "iso:country":"IN",
    "ks:ks_name":"Khaing",
    "ks:ks_type":"VILLAGE",
    "name:eng_x_preferred":[
        "Khaing"
    ],
    "wof:name":"Khaing",
    "wof:placetype":"locality"
},
  "geometry": {"coordinates":[83.19471,19.873196],"type":"Point"}
}