{
  "type": "Feature",
  "properties": {
    "gn:admin1_code":"35",
    "gn:admin2_code":"455.0",
    "gn:asciiname":"Richhera",
    "gn:country_code":"IN",
    "gn:dem":832,
    "gn:feature_class":"P",
    "gn:feature_code":"PPL",
    "gn:name":"Richhera",
    "gn:population":0,
    "gn:timezone":"Asia/Kolkata",
    "iso:country":"IN",
    "wof:name":"Richhera",
    "wof:placetype":"neighbourhood"
},
  "geometry": {"coordinates":[79.1054,22.36833],"type":"Point"}
}