{
  "type": "Feature",
  "properties": {
    "iso:country":"IN",
    "ks:ks_name":"Jilinggora",
    "ks:ks_pop":242,
    "ks:ks_type":"VILLAGE",
    "name:eng_x_preferred":[
        "Jilinggora"
    ],
    "wof:name":"Jilinggora",
    "wof:placetype":"locality",
    "wof:population":242
},
  "geometry": {"coordinates":[86.275267,22.570288],"type":"Point"}
}