{
  "type": "Feature",
  "properties": {
    "gn:admin1_code":"40",
    "gn:admin2_code":"540.0",
    "gn:asciiname":"Singaram",
    "gn:country_code":"IN",
    "gn:dem":293,
    "gn:feature_class":"P",
    "gn:feature_code":"PPL",
    "gn:name":"Singaram",
    "gn:population":0,
    "gn:timezone":"Asia/Kolkata",
    "iso:country":"IN",
    "wof:name":"Singaram",
    "wof:placetype":"locality"
},
  "geometry": {"coordinates":[79.57035,17.89607999999999],"type":"Point"}
}