{
  "type": "Feature",
  "properties": {
    "gn:admin1_code":"29.0",
    "gn:admin2_code":"244.0",
    "gn:asciiname":"Sajong",
    "gn:country_code":"IN",
    "gn:dem":960,
    "gn:feature_class":"P",
    "gn:feature_code":"PPL",
    "gn:name":"S\u0101jong",
    "gn:population":0,
    "gn:timezone":"Asia/Kolkata",
    "iso:country":"IN",
    "wof:name":"Sajong",
    "wof:placetype":"locality"
},
  "geometry": {"coordinates":[88.55006,27.20461],"type":"Point"}
}