{
  "type": "Feature",
  "properties": {
    "iso:country":"IN",
    "ks:ks_name":"Sastavu",
    "ks:ks_pop":231,
    "ks:ks_type":"HABITATION",
    "name:eng_x_preferred":[
        "Sastavu"
    ],
    "wof:name":"Sastavu",
    "wof:placetype":"locality",
    "wof:population":231
},
  "geometry": {"coordinates":[74.839973,13.447296],"type":"Point"}
}