{
  "type": "Feature",
  "properties": {
    "iso:country":"IN",
    "ks:ks_name":"Majra Nekpur",
    "ks:ks_pop":1393,
    "ks:ks_type":"HABITATION",
    "name:eng_x_preferred":[
        "Majra Nekpur"
    ],
    "wof:name":"Majra Nekpur",
    "wof:placetype":"locality",
    "wof:population":1393
},
  "geometry": {"coordinates":[78.448779,28.754179],"type":"Point"}
}