{
  "type": "Feature",
  "properties": {
    "gn:admin1_code":"36.0",
    "gn:admin2_code":"179.0",
    "gn:asciiname":"Purwa Gadaria",
    "gn:country_code":"IN",
    "gn:dem":103,
    "gn:feature_class":"P",
    "gn:feature_code":"PPL",
    "gn:name":"Purwa Gadaria",
    "gn:population":0,
    "gn:timezone":"Asia/Kolkata",
    "iso:country":"IN",
    "wof:name":"Purwa Gadaria",
    "wof:placetype":"locality"
},
  "geometry": {"coordinates":[81.83725,26.11115],"type":"Point"}
}