{
  "type": "Feature",
  "properties": {
    "gn:admin1_code":"34.0",
    "gn:admin2_code":"223.0",
    "gn:asciiname":"Goar",
    "gn:country_code":"IN",
    "gn:dem":40,
    "gn:feature_class":"P",
    "gn:feature_code":"PPL",
    "gn:name":"Go\u0101r",
    "gn:population":0,
    "gn:timezone":"Asia/Kolkata",
    "iso:country":"IN",
    "name:azb_x_preferred":[
        "\u0642\u0648\u0631"
    ],
    "name:deu_x_preferred":[
        "Goar"
    ],
    "name:fas_x_preferred":[
        "\u06af\u0648\u0631"
    ],
    "name:fra_x_preferred":[
        "Goar"
    ],
    "name:ind_x_preferred":[
        "Goar"
    ],
    "name:ita_x_preferred":[
        "Goar"
    ],
    "name:nld_x_preferred":[
        "Goar"
    ],
    "name:rus_x_preferred":[
        "\u0413\u043e\u0430\u0440"
    ],
    "name:slk_x_preferred":[
        "Goar"
    ],
    "name:ukr_x_preferred":[
        "\u0413\u043e\u0430\u0440"
    ],
    "name:vie_x_preferred":[
        "Goar"
    ],
    "wof:name":"Goar",
    "wof:placetype":"neighbourhood"
},
  "geometry": {"coordinates":[86.62832,25.60137],"type":"Point"}
}