{
  "type": "Feature",
  "properties": {
    "gn:admin1_code":"40",
    "gn:admin2_code":"540.0",
    "gn:asciiname":"Uggampalli",
    "gn:country_code":"IN",
    "gn:dem":181,
    "gn:feature_class":"P",
    "gn:feature_code":"PPL",
    "gn:name":"Uggampalli",
    "gn:population":0,
    "gn:timezone":"Asia/Kolkata",
    "iso:country":"IN",
    "name:eng_x_preferred":[
        "Uggampalli"
    ],
    "wof:name":"Uggampalli",
    "wof:placetype":"locality"
},
  "geometry": {"coordinates":[79.86806999999997,17.49445],"type":"Point"}
}