{
  "type": "Feature",
  "properties": {
    "iso:country":"IN",
    "ks:ks_name":"Devtidand",
    "ks:ks_pop":199,
    "ks:ks_type":"VILLAGE",
    "name:eng_x_preferred":[
        "Devtidand"
    ],
    "wof:name":"Devtidand",
    "wof:placetype":"locality",
    "wof:population":199
},
  "geometry": {"coordinates":[82.33938999999999,23.556823],"type":"Point"}
}