{
  "type": "Feature",
  "properties": {
    "gn:admin1_code":"37.0",
    "gn:admin2_code":"417.0",
    "gn:asciiname":"Vardeli",
    "gn:country_code":"IN",
    "gn:dem":119,
    "gn:feature_class":"P",
    "gn:feature_code":"PPL",
    "gn:name":"Vardeli",
    "gn:population":0,
    "gn:timezone":"Asia/Kolkata",
    "iso:country":"IN",
    "ks:ks_name":"Vardeli",
    "ks:ks_type":"VILLAGE",
    "name:eng_x_preferred":[
        "Vardeli"
    ],
    "wof:name":"Vardeli",
    "wof:placetype":"locality"
},
  "geometry": {"coordinates":[80.32579699999999,18.912179],"type":"Point"}
}