{
  "type": "Feature",
  "properties": {
    "iso:country":"IN",
    "ks:ks_name":"Madarpur Rosanjamakhan",
    "ks:ks_pop":239,
    "ks:ks_type":"VILLAGE",
    "ks:ks_uagg_main":0,
    "name:eng_x_preferred":[
        "Madarpur Rosanjamakhan"
    ],
    "wof:name":"Madarpur Rosanjamakhan",
    "wof:placetype":"neighbourhood",
    "wof:population":239
},
  "geometry": {"coordinates":[81.31241799999999,26.744912],"type":"Point"}
}