{
  "type": "Feature",
  "properties": {
    "iso:country":"IN",
    "ks:ks_name":"Kantapada",
    "ks:ks_pop":15,
    "ks:ks_type":"VILLAGE",
    "name:eng_x_preferred":[
        "Kantapada"
    ],
    "wof:name":"Kantapada",
    "wof:placetype":"locality",
    "wof:population":15
},
  "geometry": {"coordinates":[84.179885,20.34035],"type":"Point"}
}