{
  "type": "Feature",
  "properties": {
    "iso:country":"IN",
    "ks:ks_name":"Ramosewadi P",
    "ks:ks_pop":90,
    "ks:ks_type":"HABITATION",
    "name:eng_x_preferred":[
        "Ramosewadi P"
    ],
    "wof:name":"Ramosewadi P",
    "wof:placetype":"locality",
    "wof:population":90
},
  "geometry": {"coordinates":[73.99769999999999,19.699],"type":"Point"}
}