{
  "type": "Feature",
  "properties": {
    "iso:country":"IN",
    "ks:ks_name":"Zaroha",
    "ks:ks_pop":100,
    "ks:ks_type":"HABITATION",
    "name:eng_x_preferred":[
        "Zaroha"
    ],
    "wof:name":"Zaroha",
    "wof:placetype":"locality",
    "wof:population":100
},
  "geometry": {"coordinates":[81.492305,25.614387],"type":"Point"}
}