{
  "type": "Feature",
  "properties": {
    "iso:country":"IN",
    "ks:ks_name":"Nayakvas",
    "ks:ks_pop":113,
    "ks:ks_type":"HABITATION",
    "name:eng_x_preferred":[
        "Nayakvas"
    ],
    "wof:name":"Nayakvas",
    "wof:placetype":"locality",
    "wof:population":113
},
  "geometry": {"coordinates":[73.5346,22.7139],"type":"Point"}
}