{
  "type": "Feature",
  "properties": {
    "iso:country":"IN",
    "ks:ks_name":"Puttalingipalya",
    "ks:ks_pop":475,
    "ks:ks_type":"HABITATION",
    "name:eng_x_preferred":[
        "Puttalingipalya"
    ],
    "wof:name":"Puttalingipalya",
    "wof:placetype":"locality",
    "wof:population":475
},
  "geometry": {"coordinates":[77.09445599999999,13.009734],"type":"Point"}
}