{
  "type": "Feature",
  "properties": {
    "iso:country":"IN",
    "ks:ks_name":"Jalahanda",
    "ks:ks_pop":254,
    "ks:ks_type":"VILLAGE",
    "name:eng_x_preferred":[
        "Jalahanda"
    ],
    "wof:name":"Jalahanda",
    "wof:placetype":"locality",
    "wof:population":254
},
  "geometry": {"coordinates":[87.03994,21.735163],"type":"Point"}
}