{
  "type": "Feature",
  "properties": {
    "iso:country":"IN",
    "ks:ks_alt_nam":"DUMUHAN",
    "ks:ks_name":"Dumuhan",
    "ks:ks_pop":452,
    "ks:ks_type":"HABITATION",
    "name:eng_x_preferred":[
        "Dumuhan"
    ],
    "wof:name":"Dumuhan",
    "wof:placetype":"locality",
    "wof:population":452
},
  "geometry": {"coordinates":[85.8325,23.9065],"type":"Point"}
}