{
  "type": "Feature",
  "properties": {
    "iso:country":"IN",
    "ks:ks_name":"Gumpagadabavalasa",
    "ks:ks_pop":108,
    "ks:ks_type":"HABITATION",
    "name:eng_x_preferred":[
        "Gumpagadabavalasa"
    ],
    "wof:name":"Gumpagadabavalasa",
    "wof:placetype":"locality",
    "wof:population":108
},
  "geometry": {"coordinates":[83.47061100000001,18.860594],"type":"Point"}
}