{
  "type": "Feature",
  "properties": {
    "gn:admin1_code":"21",
    "gn:admin2_code":"382.0",
    "gn:asciiname":"Sukinda",
    "gn:country_code":"IN",
    "gn:dem":69,
    "gn:feature_class":"P",
    "gn:feature_code":"PPL",
    "gn:name":"Sukinda",
    "gn:population":0,
    "gn:timezone":"Asia/Kolkata",
    "iso:country":"IN",
    "name:epo_x_preferred":[
        "Sukinda"
    ],
    "name:nld_x_preferred":[
        "Sukinda"
    ],
    "name:ori_x_preferred":[
        "\u0b38\u0b41\u0b15\u0b3f\u0b28\u0b4d\u0b26\u0b3e"
    ],
    "name:und_x_variant":[
        "Sukinda Kh\u0101s",
        "Sukinda"
    ],
    "wof:name":"Sukinda",
    "wof:placetype":"locality"
},
  "geometry": {"coordinates":[85.91249000000001,20.9719],"type":"Point"}
}