{
  "type": "Feature",
  "properties": {
    "gn:admin1_code":"16.0",
    "gn:asciiname":"Daddi",
    "gn:country_code":"IN",
    "gn:dem":699,
    "gn:feature_class":"P",
    "gn:feature_code":"PPL",
    "gn:name":"Daddi",
    "gn:population":0,
    "gn:timezone":"Asia/Kolkata",
    "iso:country":"IN",
    "name:und_x_variant":[
        "Dadi"
    ],
    "name:vie_x_preferred":[
        "Daddi"
    ],
    "wof:name":"Daddi",
    "wof:placetype":"locality"
},
  "geometry": {"coordinates":[74.43796999999998,16.06402000000001],"type":"Point"}
}