{
  "type": "Feature",
  "properties": {
    "iso:country":"IN",
    "ks:ks_name":"Gunjampara",
    "ks:ks_pop":383,
    "ks:ks_type":"HABITATION",
    "name:eng_x_preferred":[
        "Gunjampara"
    ],
    "wof:name":"Gunjampara",
    "wof:placetype":"locality",
    "wof:population":383
},
  "geometry": {"coordinates":[81.544397,18.803059],"type":"Point"}
}