{
  "type": "Feature",
  "properties": {
    "iso:country":"IN",
    "ks:ks_name":"Kadipur",
    "ks:ks_pop":1123,
    "ks:ks_type":"HABITATION",
    "name:eng_x_preferred":[
        "Kadipur"
    ],
    "wof:name":"Kadipur",
    "wof:placetype":"locality",
    "wof:population":1123
},
  "geometry": {"coordinates":[83.085995,25.450829],"type":"Point"}
}