{
  "type": "Feature",
  "properties": {
    "iso:country":"IN",
    "ks:ks_alt_nam":"Banna kheda",
    "ks:ks_name":"Banna Kheda",
    "ks:ks_pop":939,
    "ks:ks_type":"HABITATION",
    "name:eng_x_preferred":[
        "Banna Kheda"
    ],
    "wof:name":"Banna Kheda",
    "wof:placetype":"locality",
    "wof:population":939
},
  "geometry": {"coordinates":[77.273804,24.798493],"type":"Point"}
}