{
  "type": "Feature",
  "properties": {
    "gn:admin1_code":"19",
    "gn:admin2_code":"563.0",
    "gn:asciiname":"Ullal",
    "gn:country_code":"IN",
    "gn:dem":637,
    "gn:feature_class":"P",
    "gn:feature_code":"PPL",
    "gn:name":"Ullal",
    "gn:population":0,
    "gn:timezone":"Asia/Kolkata",
    "iso:country":"IN",
    "name:ben_x_preferred":[
        "\u0989\u09b2\u09cd\u09b2\u09be\u09b2"
    ],
    "name:bpy_x_preferred":[
        "\u0989\u09b2\u09cd\u09b2\u09be\u09b2"
    ],
    "name:ceb_x_preferred":[
        "Ullal"
    ],
    "name:fra_x_preferred":[
        "Ullal"
    ],
    "name:hin_x_preferred":[
        "\u0909\u0932\u094d\u0932\u093e\u0932"
    ],
    "name:ind_x_preferred":[
        "Ullal"
    ],
    "name:ita_x_preferred":[
        "Ullal"
    ],
    "name:kan_x_preferred":[
        "\u0c89\u0cb3\u0ccd\u0cb3\u0cbe\u0cb2"
    ],
    "name:mlg_x_preferred":[
        "Ullal"
    ],
    "name:msa_x_preferred":[
        "Ullal"
    ],
    "name:nld_x_preferred":[
        "Ullal"
    ],
    "name:spa_x_preferred":[
        "Ullal"
    ],
    "name:swe_x_preferred":[
        "Ullal"
    ],
    "name:tam_x_preferred":[
        "\u0b89\u0bb3\u0bcd\u0bb3\u0bbe\u0bb2\u0bcd"
    ],
    "name:tcy_x_preferred":[
        "\u0c89\u0cb3\u0ccd\u0cb3\u0cbe\u0cb2"
    ],
    "name:vie_x_preferred":[
        "Ullal"
    ],
    "name:zho_x_preferred":[
        "\u4e4c\u5c14\u62c9\u5c14"
    ],
    "wof:name":"Ullal",
    "wof:placetype":"locality"
},
  "geometry": {"coordinates":[74.92144999999999,14.73429],"type":"Point"}
}