{
  "type": "Feature",
  "properties": {
    "gn:admin1_code":"25.0",
    "gn:admin2_code":"620.0",
    "gn:asciiname":"Kulichapattu",
    "gn:country_code":"IN",
    "gn:dem":47,
    "gn:feature_class":"P",
    "gn:feature_code":"PPL",
    "gn:name":"Kulichapattu",
    "gn:population":0,
    "gn:timezone":"Asia/Kolkata",
    "iso:country":"IN",
    "name:tam_x_preferred":[
        "\u0b95\u0bc1\u0bb3\u0bbf\u0b9a\u0bcd\u0b9a\u0baa\u0bcd\u0baa\u0b9f\u0bcd\u0b9f\u0bc1"
    ],
    "wof:name":"Kulichapattu",
    "wof:placetype":"locality"
},
  "geometry": {"coordinates":[79.20104000000001,10.75809],"type":"Point"}
}