{
  "type": "Feature",
  "properties": {
    "gn:admin1_code":"16.0",
    "gn:admin2_code":"522.0",
    "gn:asciiname":"Shrirampur",
    "gn:country_code":"IN",
    "gn:dem":537,
    "gn:feature_class":"P",
    "gn:feature_code":"PPL",
    "gn:name":"Shrirampur",
    "gn:population":0,
    "gn:timezone":"Asia/Kolkata",
    "iso:country":"IN",
    "wof:name":"Shrirampur",
    "wof:placetype":"locality"
},
  "geometry": {"coordinates":[74.65699000000002,19.62201],"type":"Point"}
}