{
  "type": "Feature",
  "properties": {
    "iso:country":"IN",
    "ks:ks_alt_nam":"LAXMAN CHANDRA PARA",
    "ks:ks_name":"Laxman Chandra Para",
    "ks:ks_pop":307,
    "ks:ks_type":"HABITATION",
    "ks:ks_uagg_main":0,
    "name:eng_x_preferred":[
        "Laxman Chandra Para"
    ],
    "wof:name":"Laxman Chandra Para",
    "wof:placetype":"neighbourhood",
    "wof:population":307
},
  "geometry": {"coordinates":[91.651195,23.941609],"type":"Point"}
}