{
  "type": "Feature",
  "properties": {
    "iso:country":"IN",
    "ks:ks_name":"Maskepu",
    "ks:ks_pop":146,
    "ks:ks_type":"VILLAGE",
    "name:eng_x_preferred":[
        "Maskepu"
    ],
    "wof:name":"Maskepu",
    "wof:placetype":"locality",
    "wof:population":146
},
  "geometry": {"coordinates":[87.597588,24.798798],"type":"Point"}
}