{
  "type": "Feature",
  "properties": {
    "gn:admin1_code":"36",
    "gn:admin2_code":"176.0",
    "gn:asciiname":"Habwanipur",
    "gn:country_code":"IN",
    "gn:dem":126,
    "gn:feature_class":"P",
    "gn:feature_code":"PPL",
    "gn:name":"Habw\u0101nipur",
    "gn:population":0,
    "gn:timezone":"Asia/Kolkata",
    "iso:country":"IN",
    "wof:name":"Habwanipur",
    "wof:placetype":"locality"
},
  "geometry": {"coordinates":[81.06971999999998,26.99636],"type":"Point"}
}