{
  "type": "Feature",
  "properties": {
    "gn:admin1_code":"36",
    "gn:admin2_code":"175.0",
    "gn:asciiname":"Kunchi",
    "gn:country_code":"IN",
    "gn:dem":97,
    "gn:feature_class":"P",
    "gn:feature_code":"PPL",
    "gn:name":"K\u016bnchi",
    "gn:population":0,
    "gn:timezone":"Asia/Kolkata",
    "iso:country":"IN",
    "name:ceb_x_preferred":[
        "Kunchi"
    ],
    "name:fra_x_preferred":[
        "Kunchi"
    ],
    "name:spa_x_preferred":[
        "Kunchi"
    ],
    "name:swe_x_preferred":[
        "Kunchi"
    ],
    "wof:name":"Kunchi",
    "wof:placetype":"locality"
},
  "geometry": {"coordinates":[82.14636999999998,25.15214],"type":"Point"}
}