{
  "type": "Feature",
  "properties": {
    "iso:country":"IN",
    "ks:ks_name":"Bamni",
    "ks:ks_pop":30,
    "ks:ks_type":"HABITATION",
    "name:eng_x_preferred":[
        "Bamni"
    ],
    "wof:name":"Bamni",
    "wof:placetype":"locality",
    "wof:population":30
},
  "geometry": {"coordinates":[86.72378,22.66215],"type":"Point"}
}