{
  "type": "Feature",
  "properties": {
    "iso:country":"IN",
    "ks:ks_name":"Modapalli",
    "ks:ks_pop":234,
    "ks:ks_type":"HABITATION",
    "name:eng_x_preferred":[
        "Modapalli"
    ],
    "wof:name":"Modapalli",
    "wof:placetype":"locality",
    "wof:population":234
},
  "geometry": {"coordinates":[82.714719,18.021609],"type":"Point"}
}