{
  "type": "Feature",
  "properties": {
    "gn:admin1_code":"19.0",
    "gn:admin2_code":"577.0",
    "gn:asciiname":"Hunsur",
    "gn:country_code":"IN",
    "gn:dem":748,
    "gn:feature_class":"P",
    "gn:feature_code":"PPL",
    "gn:name":"Hunsur",
    "gn:population":0,
    "gn:timezone":"Asia/Kolkata",
    "iso:country":"IN",
    "wof:name":"Hunsur",
    "wof:placetype":"locality"
},
  "geometry": {"coordinates":[76.42128000000002,11.87347],"type":"Point"}
}