{
  "type": "Feature",
  "properties": {
    "iso:country":"IN",
    "ks:ks_name":"Singhnia",
    "ks:ks_pop":121,
    "ks:ks_type":"VILLAGE",
    "name:eng_x_preferred":[
        "Singhnia"
    ],
    "wof:name":"Singhnia",
    "wof:placetype":"locality",
    "wof:population":121
},
  "geometry": {"coordinates":[86.972514,24.589903],"type":"Point"}
}