{
  "type": "Feature",
  "properties": {
    "iso:country":"IN",
    "ks:ks_alt_nam":"Khal faliya",
    "ks:ks_name":"Khal Faliya",
    "ks:ks_pop":280,
    "ks:ks_type":"HABITATION",
    "name:eng_x_preferred":[
        "Khal Faliya"
    ],
    "wof:name":"Khal Faliya",
    "wof:placetype":"locality",
    "wof:population":280
},
  "geometry": {"coordinates":[74.026194,21.99625],"type":"Point"}
}