{
  "type": "Feature",
  "properties": {
    "iso:country":"IN",
    "ks:ks_name":"Miabagicha",
    "ks:ks_pop":0,
    "ks:ks_type":"VILLAGE",
    "name:eng_x_preferred":[
        "Miabagicha"
    ],
    "wof:name":"Miabagicha",
    "wof:placetype":"locality",
    "wof:population":0
},
  "geometry": {"coordinates":[86.708434,25.240389],"type":"Point"}
}