{
  "type": "Feature",
  "properties": {
    "gn:admin1_code":"35.0",
    "gn:admin2_code":"427",
    "gn:asciiname":"Ghoreta",
    "gn:country_code":"IN",
    "gn:dem":465,
    "gn:feature_class":"P",
    "gn:feature_code":"PPL",
    "gn:name":"Ghoreta",
    "gn:population":0,
    "gn:timezone":"Asia/Kolkata",
    "iso:country":"IN",
    "name:fra_x_preferred":[
        "Ghoreta"
    ],
    "name:mai_x_preferred":[
        "\u0918\u094b\u0930\u0947\u091f\u093e"
    ],
    "name:msa_x_preferred":[
        "Ghoreta"
    ],
    "name:nep_x_preferred":[
        "\u0918\u094b\u0930\u0947\u091f\u093e"
    ],
    "name:new_x_preferred":[
        "\u0918\u094b\u0930\u0947\u091f\u093e"
    ],
    "name:pol_x_preferred":[
        "Ghoreta"
    ],
    "wof:name":"Ghoreta",
    "wof:placetype":"locality"
},
  "geometry": {"coordinates":[78.75939,24.23795],"type":"Point"}
}