{
  "type": "Feature",
  "properties": {
    "gn:admin1_code":"35.0",
    "gn:admin2_code":"449",
    "gn:asciiname":"Dhain",
    "gn:country_code":"IN",
    "gn:dem":410,
    "gn:feature_class":"P",
    "gn:feature_code":"PPL",
    "gn:name":"Dh\u0101in",
    "gn:population":0,
    "gn:timezone":"Asia/Kolkata",
    "iso:country":"IN",
    "ks:ks_alt_nam":"Dh\u0101in",
    "ks:ks_name":"Dhain",
    "ks:ks_pop":274,
    "ks:ks_type":"VILLAGE",
    "name:eng_x_preferred":[
        "Dhain"
    ],
    "name:eng_x_variant":[
        "Dh\u0101in"
    ],
    "wof:name":"Dhain",
    "wof:placetype":"locality",
    "wof:population":274
},
  "geometry": {"coordinates":[78.171718,22.439476],"type":"Point"}
}