{
  "type": "Feature",
  "properties": {
    "iso:country":"IN",
    "ks:ks_name":"Jeeyarkulam",
    "ks:ks_pop":56,
    "ks:ks_type":"HABITATION",
    "name:eng_x_preferred":[
        "Jeeyarkulam"
    ],
    "wof:name":"Jeeyarkulam",
    "wof:placetype":"locality",
    "wof:population":56
},
  "geometry": {"coordinates":[77.638465,8.488684],"type":"Point"}
}