{
  "type": "Feature",
  "properties": {
    "iso:country":"IN",
    "ks:ks_name":"Sar Bani",
    "ks:ks_pop":330,
    "ks:ks_type":"HABITATION",
    "name:eng_x_preferred":[
        "Sar Bani"
    ],
    "wof:name":"Sar Bani",
    "wof:placetype":"locality",
    "wof:population":330
},
  "geometry": {"coordinates":[86.76430999999999,22.183513],"type":"Point"}
}