{
  "type": "Feature",
  "properties": {
    "iso:country":"IN",
    "ks:ks_name":"Jodi Mallapanahalli",
    "ks:ks_pop":123,
    "ks:ks_type":"HABITATION",
    "name:eng_x_preferred":[
        "Jodi Mallapanahalli"
    ],
    "wof:name":"Jodi Mallapanahalli",
    "wof:placetype":"locality",
    "wof:population":123
},
  "geometry": {"coordinates":[76.101467,12.847152],"type":"Point"}
}