{
  "type": "Feature",
  "properties": {
    "iso:country":"IN",
    "name:ara_x_preferred":[
        "\u0643\u0627\u0643\u0631\u0648\u0644\u0627"
    ],
    "name:ben_bn_x_preferred":[
        "\u0995\u09be\u0995\u09b0\u09be\u0989\u09b2\u09be"
    ],
    "name:ben_in_x_preferred":[
        "\u0995\u09be\u0995\u09b0\u09be\u0989\u09b2\u09be"
    ],
    "name:guj_x_preferred":[
        "\u0a95\u0abe\u0a95\u0acd\u0ab0\u0acc\u0ab2\u0abe"
    ],
    "name:hin_x_preferred":[
        "\u0915\u0915\u0930\u094c\u0932\u093e"
    ],
    "name:kan_x_preferred":[
        "\u0c95\u0c95\u0ccd\u0cb0\u0ccc\u0cb2\u0cbe"
    ],
    "name:mal_x_preferred":[
        "\u0d15\u0d15\u0d4d\u0d30\u0d57\u0d33"
    ],
    "name:mar_x_preferred":[
        "\u0915\u093e\u0915\u0930\u094c\u0932\u093e"
    ],
    "name:pan_x_preferred":[
        "\u0a15\u0a15\u0a30\u0a4c\u0a32\u0a3e"
    ],
    "name:tam_x_preferred":[
        "\u0b95\u0b95\u0bcd\u0bb0\u0bcc\u0bb2\u0bbe"
    ],
    "name:tel_x_preferred":[
        "\u0c15\u0c3e\u0c15\u0c4d\u0c30\u0c4c\u0c32\u0c3e"
    ],
    "name:urd_x_preferred":[
        "\u06a9\u06a9\u0631\u0648\u0644\u06c1"
    ],
    "qs:name":"Kakraula",
    "qs:name_adm0":"India",
    "qs:name_adm1":"Delhi",
    "qs:photos":2,
    "qs:photos_1k":1,
    "qs:photos_9k":1,
    "qs:photos_9r":1,
    "qs:photos_all":2,
    "qs:photos_sr":1,
    "qs:placetype":"Suburb",
    "qs:pop_sr":"0",
    "wd:wordcount":71,
    "wof:name":"Kakraula",
    "wof:placetype":"neighbourhood"
},
  "geometry": {"coordinates":[77.38983,29.35867],"type":"Point"}
}