{
  "type": "Feature",
  "properties": {
    "iso:country":"IN",
    "qs:name":"Kakraula",
    "qs:name_adm0":"India",
    "qs:name_adm1":"Delhi",
    "qs:photos":2,
    "qs:photos_1k":1,
    "qs:photos_9k":1,
    "qs:photos_9r":1,
    "qs:photos_all":2,
    "qs:photos_sr":1,
    "qs:placetype":"Suburb",
    "qs:pop_sr":"0",
    "wd:wordcount":71,
    "wof:name":"Kakraula",
    "wof:placetype":"neighbourhood"
},
  "geometry": {"coordinates":[77.38983,29.35867],"type":"Point"}
}