{
  "type": "Feature",
  "properties": {
    "iso:country":"IN",
    "ks:ks_name":"Matkamjharan",
    "ks:ks_pop":264,
    "ks:ks_type":"VILLAGE",
    "name:eng_x_preferred":[
        "Matkamjharan"
    ],
    "wof:name":"Matkamjharan",
    "wof:placetype":"locality",
    "wof:population":264
},
  "geometry": {"coordinates":[84.996239,22.147903],"type":"Point"}
}