{
  "type": "Feature",
  "properties": {
    "iso:country":"IN",
    "ks:ks_name":"Khalachi Boudhwadi",
    "ks:ks_pop":69,
    "ks:ks_type":"HABITATION",
    "name:eng_x_preferred":[
        "Khalachi Boudhwadi"
    ],
    "wof:name":"Khalachi Boudhwadi",
    "wof:placetype":"locality",
    "wof:population":69
},
  "geometry": {"coordinates":[73.65416,17.007014],"type":"Point"}
}