{
  "type": "Feature",
  "properties": {
    "iso:country":"IN",
    "ks:ks_name":"Mayurnathapuram",
    "ks:ks_pop":1031,
    "ks:ks_type":"HABITATION",
    "name:eng_x_preferred":[
        "Mayurnathapuram"
    ],
    "wof:name":"Mayurnathapuram",
    "wof:placetype":"locality",
    "wof:population":1031
},
  "geometry": {"coordinates":[78.012592,9.318174],"type":"Point"}
}