{
  "type": "Feature",
  "properties": {
    "iso:country":"IN",
    "ks:ks_name":"Raipalem",
    "ks:ks_pop":48,
    "ks:ks_type":"HABITATION",
    "name:eng_x_preferred":[
        "Raipalem"
    ],
    "wof:name":"Raipalem",
    "wof:placetype":"locality",
    "wof:population":48
},
  "geometry": {"coordinates":[82.51514299999999,17.839637],"type":"Point"}
}