{
  "type": "Feature",
  "properties": {
    "iso:country":"IN",
    "ks:ks_alt_nam":"Nelhal camp",
    "ks:ks_name":"Nelhal Camp",
    "ks:ks_pop":111,
    "ks:ks_type":"HABITATION",
    "name:eng_x_preferred":[
        "Nelhal Camp"
    ],
    "wof:name":"Nelhal Camp",
    "wof:placetype":"locality",
    "wof:population":111
},
  "geometry": {"coordinates":[77.29529700000001,16.152645],"type":"Point"}
}