{
  "type": "Feature",
  "properties": {
    "iso:country":"IN",
    "ks:ks_name":"Kapisargiguda",
    "ks:ks_pop":104,
    "ks:ks_type":"HABITATION",
    "name:eng_x_preferred":[
        "Kapisargiguda"
    ],
    "wof:name":"Kapisargiguda",
    "wof:placetype":"locality",
    "wof:population":104
},
  "geometry": {"coordinates":[82.10760500000001,18.514922],"type":"Point"}
}