{
  "type": "Feature",
  "properties": {
    "gn:admin1_code":"36.0",
    "gn:admin2_code":"183.0",
    "gn:asciiname":"Pura Fateh Singh",
    "gn:country_code":"IN",
    "gn:dem":104,
    "gn:feature_class":"P",
    "gn:feature_code":"PPL",
    "gn:name":"Pura Fateh Singh",
    "gn:population":0,
    "gn:timezone":"Asia/Kolkata",
    "iso:country":"IN",
    "name:und_x_variant":[
        "Asogpur"
    ],
    "wof:name":"Pura Fateh Singh",
    "wof:placetype":"locality"
},
  "geometry": {"coordinates":[82.11188,27.00333],"type":"Point"}
}