{
  "type": "Feature",
  "properties": {
    "iso:country":"IN",
    "ks:ks_name":"Madanmohanpur",
    "ks:ks_pop":0,
    "ks:ks_type":"VILLAGE",
    "name:eng_x_preferred":[
        "Madanmohanpur"
    ],
    "wof:name":"Madanmohanpur",
    "wof:placetype":"locality",
    "wof:population":0
},
  "geometry": {"coordinates":[87.645225,23.474113],"type":"Point"}
}