{
  "type": "Feature",
  "properties": {
    "iso:country":"IN",
    "ks:ks_alt_nam":"KALAMADI BAGLKOT WASTI",
    "ks:ks_name":"Kalamadi Baglkot Wasti",
    "ks:ks_pop":117,
    "ks:ks_type":"HABITATION",
    "name:eng_x_preferred":[
        "Kalamadi Baglkot Wasti"
    ],
    "wof:name":"Kalamadi Baglkot Wasti",
    "wof:placetype":"locality",
    "wof:population":117
},
  "geometry": {"coordinates":[75.420411,17.224717],"type":"Point"}
}