{
  "type": "Feature",
  "properties": {
    "iso:country":"IN",
    "ks:ks_name":"Luhar Falia",
    "ks:ks_pop":1081,
    "ks:ks_type":"HABITATION",
    "name:eng_x_preferred":[
        "Luhar Falia"
    ],
    "wof:name":"Luhar Falia",
    "wof:placetype":"locality",
    "wof:population":1081
},
  "geometry": {"coordinates":[73.935389,22.866472],"type":"Point"}
}