{
  "type": "Feature",
  "properties": {
    "iso:country":"IN",
    "ks:ks_name":"Majgawa",
    "ks:ks_pop":508,
    "ks:ks_type":"VILLAGE",
    "ks:ks_uagg_main":0,
    "name:eng_x_preferred":[
        "Majgawa"
    ],
    "wof:name":"Majgawa",
    "wof:placetype":"neighbourhood",
    "wof:population":508
},
  "geometry": {"coordinates":[81.428742,28.128273],"type":"Point"}
}