{
  "type": "Feature",
  "properties": {
    "iso:country":"IN",
    "ks:ks_name":"Pandri Khurd",
    "ks:ks_pop":195,
    "ks:ks_type":"VILLAGE",
    "name:eng_x_preferred":[
        "Pandri Khurd"
    ],
    "wof:name":"Pandri Khurd",
    "wof:placetype":"locality",
    "wof:population":195
},
  "geometry": {"coordinates":[84.865172,24.451729],"type":"Point"}
}