{
  "type": "Feature",
  "properties": {
    "iso:country":"IN",
    "ks:ks_name":"Kalaif",
    "ks:ks_pop":302,
    "ks:ks_type":"VILLAGE",
    "name:eng_x_preferred":[
        "Kalaif"
    ],
    "wof:name":"Kalaif",
    "wof:placetype":"locality",
    "wof:population":302
},
  "geometry": {"coordinates":[78.39977,30.435649],"type":"Point"}
}