{
  "type": "Feature",
  "properties": {
    "gn:admin1_code":"39.0",
    "gn:admin2_code":"66.0",
    "gn:asciiname":"Awe",
    "gn:country_code":"IN",
    "gn:dem":762,
    "gn:feature_class":"P",
    "gn:feature_code":"PPL",
    "gn:name":"\u0100we",
    "gn:population":0,
    "gn:timezone":"Asia/Kolkata",
    "iso:country":"IN",
    "name:lit_x_preferred":[
        "Pagarbi baim\u0117"
    ],
    "wof:name":"Awe",
    "wof:placetype":"locality"
},
  "geometry": {"coordinates":[79.30001999999998,29.42249],"type":"Point"}
}