{
  "type": "Feature",
  "properties": {
    "iso:country":"IN",
    "ks:ks_name":"Mundki",
    "ks:ks_pop":110,
    "ks:ks_type":"HABITATION",
    "name:eng_x_preferred":[
        "Mundki"
    ],
    "wof:name":"Mundki",
    "wof:placetype":"locality",
    "wof:population":110
},
  "geometry": {"coordinates":[74.543064,14.174379],"type":"Point"}
}