{
  "type": "Feature",
  "properties": {
    "gn:admin1_code":"23",
    "gn:admin2_code":"52.0",
    "gn:asciiname":"Daun",
    "gn:country_code":"IN",
    "gn:dem":318,
    "gn:feature_class":"P",
    "gn:feature_code":"PPL",
    "gn:name":"D\u0101\u016bn",
    "gn:population":0,
    "gn:timezone":"Asia/Kolkata",
    "iso:country":"IN",
    "name:ara_x_preferred":[
        "\u062f\u0627\u0648\u0646"
    ],
    "name:ben_bn_x_preferred":[
        "\u09a6\u09be\u0989\u09a8"
    ],
    "name:ben_in_x_preferred":[
        "\u09a6\u09be\u0989\u09a8"
    ],
    "name:guj_x_preferred":[
        "\u0aa6\u0abe\u0a89\u0aa8"
    ],
    "name:hin_x_preferred":[
        "\u0926\u094c\u0928"
    ],
    "name:kan_x_preferred":[
        "\u0ca6\u0ccc\u0ca8\u0ccd"
    ],
    "name:mal_x_preferred":[
        "\u0d21\u0d4b\u0d7a"
    ],
    "name:mar_x_preferred":[
        "\u0921\u093e\u0909\u0928"
    ],
    "name:pan_x_preferred":[
        "\u0a26\u0a3e\u0a0a\u0a02"
    ],
    "name:tam_x_preferred":[
        "\u0ba4\u0bcc\u0ba9\u0bcd"
    ],
    "name:tel_x_preferred":[
        "\u0c21\u0c3e\u0c35\u0c41\u0c28\u0c4d"
    ],
    "name:urd_x_preferred":[
        "\u062f\u0627\u0624\u0646"
    ],
    "wof:name":"Daun",
    "wof:placetype":"neighbourhood"
},
  "geometry": {"coordinates":[76.68333,30.74176],"type":"Point"}
}