{
  "type": "Feature",
  "properties": {
    "iso:country":"IN",
    "ks:ks_alt_nam":"Bhat ka Tor",
    "ks:ks_name":"Bhat Ka Tor",
    "ks:ks_pop":1,
    "ks:ks_type":"HABITATION",
    "name:eng_x_preferred":[
        "Bhat Ka Tor"
    ],
    "wof:name":"Bhat Ka Tor",
    "wof:placetype":"locality",
    "wof:population":1
},
  "geometry": {"coordinates":[77.433616,26.309761],"type":"Point"}
}