{
  "type": "Feature",
  "properties": {
    "iso:country":"IN",
    "ks:ks_alt_nam":"Vazhiyila para",
    "ks:ks_name":"Vazhiyila Para",
    "ks:ks_pop":1440,
    "ks:ks_type":"HABITATION",
    "name:eng_x_preferred":[
        "Vazhiyila Para"
    ],
    "wof:name":"Vazhiyila Para",
    "wof:placetype":"locality",
    "wof:population":1440
},
  "geometry": {"coordinates":[76.27419399999999,11.02903],"type":"Point"}
}