{
  "type": "Feature",
  "properties": {
    "iso:country":"IN",
    "ks:ks_name":"Purna Daichapara",
    "ks:ks_pop":525,
    "ks:ks_type":"VILLAGE",
    "ks:ks_uagg_main":0,
    "name:eng_x_preferred":[
        "Purna Daichapara"
    ],
    "wof:name":"Purna Daichapara",
    "wof:placetype":"neighbourhood",
    "wof:population":525
},
  "geometry": {"coordinates":[91.519205,26.363061],"type":"Point"}
}