{
  "type": "Feature",
  "properties": {
    "iso:country":"IN",
    "ks:ks_name":"Kamutipanga",
    "ks:ks_pop":84,
    "ks:ks_type":"VILLAGE",
    "name:eng_x_preferred":[
        "Kamutipanga"
    ],
    "wof:name":"Kamutipanga",
    "wof:placetype":"locality",
    "wof:population":84
},
  "geometry": {"coordinates":[84.57766100000001,20.411481],"type":"Point"}
}