{
  "type": "Feature",
  "properties": {
    "gn:country":"IN",
    "gn:fcode":"PPL",
    "gn:pop":0,
    "iso:country":"IN",
    "name:eng_x_preferred":[
        "Ghansoli"
    ],
    "name:hin_x_preferred":[
        "\u0918\u0923\u0938\u094b\u0932\u0940"
    ],
    "name:kan_x_preferred":[
        "\u0c98\u0ca8\u0ccd \u0cb8\u0ccb\u0cb2\u0cbf"
    ],
    "name:mar_x_preferred":[
        "\u0918\u0923\u0938\u094b\u0932\u0940"
    ],
    "name:unk_x_variant":[
        "Ghansoli Necol"
    ],
    "qs:name":"Ghansoli",
    "qs:name_adm0":"India",
    "qs:name_adm1":"Maharashtra",
    "qs:photos":12,
    "qs:photos_1k":2,
    "qs:photos_9k":1,
    "qs:photos_9r":1,
    "qs:photos_all":12,
    "qs:photos_sr":1,
    "qs:placetype":"Suburb",
    "qs:pop_sr":"0",
    "wd:wordcount":276,
    "wof:name":"Ghansoli",
    "wof:placetype":"neighbourhood",
    "wof:population":0
},
  "geometry": {"coordinates":[72.98333,19.11667],"type":"Point"}
}