{
  "type": "Feature",
  "properties": {
    "gn:country":"IN",
    "gn:fcode":"PPL",
    "gn:population":0,
    "iso:country":"IN",
    "name:ara_x_preferred":[
        "\u063a\u0627\u0646\u0632\u0648\u0644\u064a"
    ],
    "name:ben_bn_x_preferred":[
        "\u0998\u09a8\u09b8\u09cb\u09b2\u09bf"
    ],
    "name:ben_in_x_preferred":[
        "\u0998\u09a8\u09b8\u09cb\u09b2\u09bf"
    ],
    "name:eng_x_preferred":[
        "Ghansoli"
    ],
    "name:guj_x_preferred":[
        "\u0a98\u0aa8\u0ab8\u0acb\u0ab2\u0ac0"
    ],
    "name:hin_x_preferred":[
        "\u0918\u0928\u0938\u094b\u0932\u0940"
    ],
    "name:hin_x_variant":[
        "\u0918\u0923\u0938\u094b\u0932\u0940"
    ],
    "name:kan_x_preferred":[
        "\u0c98\u0ca8\u0ccd\u0cb8\u0ccb\u0cb2\u0cbf"
    ],
    "name:kan_x_variant":[
        "\u0c98\u0ca8\u0ccd \u0cb8\u0ccb\u0cb2\u0cbf"
    ],
    "name:mal_x_preferred":[
        "\u0d17\u0d3e\u0d7b\u0d38\u0d4b\u0d33\u0d3f"
    ],
    "name:mar_x_preferred":[
        "\u0918\u0923\u0938\u094b\u0932\u0940"
    ],
    "name:pan_x_preferred":[
        "\u0a18\u0a23\u0a38\u0a4c\u0a32\u0a40"
    ],
    "name:tam_x_preferred":[
        "\u0b95\u0bbe\u0ba9\u0bcd\u0b9a\u0bcb\u0bb2\u0bbf"
    ],
    "name:tel_x_preferred":[
        "\u0c18\u0c28\u0c4d"
    ],
    "name:und_x_variant":[
        "Ghansoli Necol"
    ],
    "name:urd_x_preferred":[
        "\u06af\u06be\u0646\u0633\u0648\u0644\u06cc"
    ],
    "qs:name":"Ghansoli",
    "qs:name_adm0":"India",
    "qs:name_adm1":"Maharashtra",
    "qs:photos":12,
    "qs:photos_1k":2,
    "qs:photos_9k":1,
    "qs:photos_9r":1,
    "qs:photos_all":12,
    "qs:photos_sr":1,
    "qs:placetype":"Suburb",
    "qs:pop_sr":"0",
    "wd:wordcount":276,
    "wof:name":"Ghansoli",
    "wof:placetype":"neighbourhood",
    "wof:population":0
},
  "geometry": {"coordinates":[72.98333,19.11667],"type":"Point"}
}