{
  "type": "Feature",
  "properties": {
    "iso:country":"IN",
    "ks:ks_name":"Gudipara",
    "ks:ks_pop":390,
    "ks:ks_type":"HABITATION",
    "name:eng_x_preferred":[
        "Gudipara"
    ],
    "wof:name":"Gudipara",
    "wof:placetype":"locality",
    "wof:population":390
},
  "geometry": {"coordinates":[81.64095399999999,19.224292],"type":"Point"}
}