{
  "type": "Feature",
  "properties": {
    "iso:country":"IN",
    "ks:ks_name":"Meltadi",
    "ks:ks_pop":71,
    "ks:ks_type":"HABITATION",
    "name:eng_x_preferred":[
        "Meltadi"
    ],
    "wof:name":"Meltadi",
    "wof:placetype":"locality",
    "wof:population":71
},
  "geometry": {"coordinates":[74.478037,14.299654],"type":"Point"}
}