{
  "type": "Feature",
  "properties": {
    "iso:country":"IN",
    "ks:ks_alt_nam":"naveena area",
    "ks:ks_name":"Naveena Area",
    "ks:ks_pop":2682,
    "ks:ks_type":"HABITATION",
    "name:eng_x_preferred":[
        "Naveena Area"
    ],
    "wof:name":"Naveena Area",
    "wof:placetype":"locality",
    "wof:population":2682
},
  "geometry": {"coordinates":[75.705314,11.480875],"type":"Point"}
}