{
  "type": "Feature",
  "properties": {
    "gn:admin1_code":"11",
    "gn:admin2_code":"23.0",
    "gn:asciiname":"Kala",
    "gn:country_code":"IN",
    "gn:dem":2045,
    "gn:feature_class":"P",
    "gn:feature_code":"PPL",
    "gn:name":"Kala",
    "gn:population":0,
    "gn:timezone":"Asia/Kolkata",
    "iso:country":"IN",
    "name:aze_x_preferred":[
        "Kala"
    ],
    "name:ben_x_preferred":[
        "\u0995\u09b2\u09be"
    ],
    "name:ceb_x_preferred":[
        "Kala"
    ],
    "name:ces_x_preferred":[
        "Kala"
    ],
    "name:deu_x_preferred":[
        "Kala"
    ],
    "name:est_x_preferred":[
        "Kala"
    ],
    "name:eus_x_preferred":[
        "Kala"
    ],
    "name:fas_x_preferred":[
        "\u06a9\u0627\u0644\u0627"
    ],
    "name:fin_x_preferred":[
        "Kala"
    ],
    "name:fra_x_preferred":[
        "Kala"
    ],
    "name:ind_x_preferred":[
        "Kala"
    ],
    "name:ita_x_preferred":[
        "Kala"
    ],
    "name:lit_x_preferred":[
        "Kala"
    ],
    "name:nld_x_preferred":[
        "Kala"
    ],
    "name:pol_x_preferred":[
        "Kala"
    ],
    "name:por_x_preferred":[
        "Kala"
    ],
    "name:slv_x_preferred":[
        "Kala"
    ],
    "name:spa_x_preferred":[
        "Kala"
    ],
    "name:swe_x_preferred":[
        "Kala"
    ],
    "wof:name":"Kala",
    "wof:placetype":"locality"
},
  "geometry": {"coordinates":[76.12841999999998,32.84864],"type":"Point"}
}