{
  "type": "Feature",
  "properties": {
    "iso:country":"IN",
    "ks:ks_alt_nam":"awatemala",
    "ks:ks_name":"Awatemala",
    "ks:ks_pop":160,
    "ks:ks_type":"HABITATION",
    "name:eng_x_preferred":[
        "Awatemala"
    ],
    "wof:name":"Awatemala",
    "wof:placetype":"locality",
    "wof:population":160
},
  "geometry": {"coordinates":[73.800585,19.111798],"type":"Point"}
}