{
  "type": "Feature",
  "properties": {
    "gn:admin1_code":"24.0",
    "gn:admin2_code":"112.0",
    "gn:asciiname":"Khokharia",
    "gn:country_code":"IN",
    "gn:dem":462,
    "gn:feature_class":"P",
    "gn:feature_code":"PPL",
    "gn:name":"Khokhari\u0101",
    "gn:population":0,
    "gn:timezone":"Asia/Kolkata",
    "iso:country":"IN",
    "wof:name":"Khokharia",
    "wof:placetype":"locality"
},
  "geometry": {"coordinates":[74.58752,26.68097],"type":"Point"}
}