{
  "type": "Feature",
  "properties": {
    "iso:country":"IN",
    "name:eng_x_preferred":[
        "Dadar West"
    ],
    "name:unk_x_variant":[
        "Dadar West"
    ],
    "qs:gn_adm0_cc":"IN",
    "qs:gn_fcode":"PPL",
    "qs:gn_local":1275339,
    "qs:gn_namadm1":"16",
    "qs:gn_name":"Dadar West",
    "qs:local_max":3819,
    "qs:local_sum":50908,
    "qs:localhoods":70,
    "qs:name":"Dadar West",
    "qs:name_adm0":"India",
    "qs:name_adm1":"Maharashtra",
    "qs:name_adm2":"Mumbai",
    "qs:name_local":"Mumbai",
    "qs:photo_max":79,
    "qs:photo_sum":451,
    "qs:placetype":"Suburb",
    "qs:quad_count":25,
    "qs:woe_adm0":23424848,
    "qs:woe_adm1":2345750,
    "qs:woe_adm2":12586539,
    "qs:woe_lau":0,
    "qs:woe_local":2295411,
    "qs:woe_ver":"7.10.0",
    "wof:lang":[
        "eng"
    ],
    "wof:name":"Dadar West",
    "wof:placetype":"neighbourhood"
},
  "geometry": {"coordinates":[72.838386,19.022837],"type":"Point"}
}