{
  "type": "Feature",
  "properties": {
    "gn:admin1_code":"11.0",
    "gn:admin2_code":"27.0",
    "gn:asciiname":"Chyuni",
    "gn:country_code":"IN",
    "gn:dem":2521,
    "gn:feature_class":"P",
    "gn:feature_code":"PPL",
    "gn:name":"Chy\u016bni",
    "gn:population":0,
    "gn:timezone":"Asia/Kolkata",
    "iso:country":"IN",
    "wof:name":"Chyuni",
    "wof:placetype":"locality"
},
  "geometry": {"coordinates":[77.23869999999999,31.58369],"type":"Point"}
}