{
  "type": "Feature",
  "properties": {
    "gn:admin1_code":"11.0",
    "gn:admin2_code":"26.0",
    "gn:asciiname":"Olinal",
    "gn:country_code":"IN",
    "gn:dem":1407,
    "gn:feature_class":"P",
    "gn:feature_code":"PPL",
    "gn:name":"Olinal",
    "gn:population":0,
    "gn:timezone":"Asia/Kolkata",
    "iso:country":"IN",
    "wof:name":"Olinal",
    "wof:placetype":"locality"
},
  "geometry": {"coordinates":[77.56428000000002,31.4565],"type":"Point"}
}