{
  "type": "Feature",
  "properties": {
    "iso:country":"IN",
    "ks:ks_name":"Bhandarigadia",
    "ks:ks_pop":0,
    "ks:ks_type":"VILLAGE",
    "name:eng_x_preferred":[
        "Bhandarigadia"
    ],
    "wof:name":"Bhandarigadia",
    "wof:placetype":"locality",
    "wof:population":0
},
  "geometry": {"coordinates":[85.492434,19.947201],"type":"Point"}
}