{
  "type": "Feature",
  "properties": {
    "iso:country":"IN",
    "ks:ks_name":"Matariya Vejma",
    "ks:ks_pop":4054,
    "ks:ks_type":"VILLAGE",
    "name:eng_x_preferred":[
        "Matariya Vejma"
    ],
    "wof:name":"Matariya Vejma",
    "wof:placetype":"locality",
    "wof:population":4054
},
  "geometry": {"coordinates":[73.857885,22.890837],"type":"Point"}
}