{
  "type": "Feature",
  "properties": {
    "iso:country":"IN",
    "ks:ks_name":"Manakkalpadi",
    "ks:ks_pop":2055,
    "ks:ks_type":"HABITATION",
    "name:eng_x_preferred":[
        "Manakkalpadi"
    ],
    "wof:name":"Manakkalpadi",
    "wof:placetype":"locality",
    "wof:population":2055
},
  "geometry": {"coordinates":[76.235353,10.815738],"type":"Point"}
}