{
  "type": "Feature",
  "properties": {
    "iso:country":"IN",
    "ks:ks_name":"Joshiwadi",
    "ks:ks_pop":112,
    "ks:ks_type":"HABITATION",
    "name:eng_x_preferred":[
        "Joshiwadi"
    ],
    "wof:name":"Joshiwadi",
    "wof:placetype":"locality",
    "wof:population":112
},
  "geometry": {"coordinates":[73.733875,15.867335],"type":"Point"}
}