{
  "type": "Feature",
  "properties": {
    "iso:country":"IN",
    "ks:ks_alt_nam":"Long Terang gaon",
    "ks:ks_name":"Long Terang Gaon",
    "ks:ks_pop":353,
    "ks:ks_type":"HABITATION",
    "name:eng_x_preferred":[
        "Long Terang Gaon"
    ],
    "wof:name":"Long Terang Gaon",
    "wof:placetype":"locality",
    "wof:population":353
},
  "geometry": {"coordinates":[93.11731,26.151337],"type":"Point"}
}