{
  "type": "Feature",
  "properties": {
    "iso:country":"IN",
    "ks:ks_alt_nam":"majhigavan",
    "ks:ks_name":"Majhigavan",
    "ks:ks_pop":275,
    "ks:ks_type":"HABITATION",
    "name:eng_x_preferred":[
        "Majhigavan"
    ],
    "wof:name":"Majhigavan",
    "wof:placetype":"locality",
    "wof:population":275
},
  "geometry": {"coordinates":[80.722686,26.176798],"type":"Point"}
}