{
  "type": "Feature",
  "properties": {
    "gn:admin1_code":"35.0",
    "gn:admin2_code":"455.0",
    "gn:asciiname":"Khamra",
    "gn:country_code":"IN",
    "gn:dem":788,
    "gn:feature_class":"P",
    "gn:feature_code":"PPL",
    "gn:name":"Khamra",
    "gn:population":0,
    "gn:timezone":"Asia/Kolkata",
    "iso:country":"IN",
    "name:che_x_preferred":[
        "\u0425\u0430\u043c\u0440\u0430"
    ],
    "wof:name":"Khamra",
    "wof:placetype":"neighbourhood"
},
  "geometry": {"coordinates":[78.75933999999999,22.16968],"type":"Point"}
}