{
  "type": "Feature",
  "properties": {
    "iso:country":"IN",
    "ks:ks_name":"Pure Tiwari",
    "ks:ks_pop":125,
    "ks:ks_type":"HABITATION",
    "name:eng_x_preferred":[
        "Pure Tiwari"
    ],
    "wof:name":"Pure Tiwari",
    "wof:placetype":"locality",
    "wof:population":125
},
  "geometry": {"coordinates":[81.968367,26.555726],"type":"Point"}
}