{
  "type": "Feature",
  "properties": {
    "gn:admin1_code":"36.0",
    "gn:admin2_code":"140.0",
    "gn:asciiname":"Deoli",
    "gn:country_code":"IN",
    "gn:dem":220,
    "gn:feature_class":"P",
    "gn:feature_code":"PPL",
    "gn:name":"Deoli",
    "gn:population":0,
    "gn:timezone":"Asia/Kolkata",
    "iso:country":"IN",
    "ks:ks_name":"Deoli",
    "ks:ks_pop":2676,
    "ks:ks_type":"VILLAGE",
    "ks:ks_uagg_main":0,
    "name:ben_x_preferred":[
        "\u09a6\u09c7\u0993\u09b2\u09bf"
    ],
    "name:bih_x_preferred":[
        "\u0926\u0947\u0935\u0932\u0940"
    ],
    "name:ceb_x_preferred":[
        "Deoli"
    ],
    "name:eng_x_preferred":[
        "Deoli"
    ],
    "name:nld_x_preferred":[
        "Deoli"
    ],
    "name:swe_x_preferred":[
        "Deoli"
    ],
    "wof:name":"Deoli",
    "wof:placetype":"neighbourhood",
    "wof:population":2676
},
  "geometry": {"coordinates":[77.986656,28.823524],"type":"Point"}
}