{
  "type": "Feature",
  "properties": {
    "gn:admin1_code":"35.0",
    "gn:admin2_code":"421.0",
    "gn:asciiname":"Jaggupura",
    "gn:country_code":"IN",
    "gn:dem":177,
    "gn:feature_class":"P",
    "gn:feature_code":"PPL",
    "gn:name":"Jagg\u016bpura",
    "gn:population":0,
    "gn:timezone":"Asia/Kolkata",
    "iso:country":"IN",
    "name:eng_x_preferred":[
        "Jagg\u016bpura"
    ],
    "wof:name":"Jaggupura",
    "wof:placetype":"locality"
},
  "geometry": {"coordinates":[78.33145,26.28241],"type":"Point"}
}