{
  "type": "Feature",
  "properties": {
    "iso:country":"IN",
    "ks:ks_name":"Niz Katigorah Pt III",
    "ks:ks_pop":4727,
    "ks:ks_type":"URBAN",
    "name:eng_x_preferred":[
        "Niz Katigorah Pt III"
    ],
    "wof:name":"Niz Katigorah Pt III",
    "wof:placetype":"locality",
    "wof:population":4727
},
  "geometry": {"coordinates":[92.56152299999999,24.875474],"type":"Point"}
}