{
  "type": "Feature",
  "properties": {
    "iso:country":"IN",
    "ks:ks_name":"Barbari",
    "ks:ks_pop":333,
    "ks:ks_type":"VILLAGE",
    "name:eng_x_preferred":[
        "Barbari"
    ],
    "wof:name":"Barbari",
    "wof:placetype":"locality",
    "wof:population":333
},
  "geometry": {"coordinates":[91.39609400000001,26.655883],"type":"Point"}
}