{
  "type": "Feature",
  "properties": {
    "iso:country":"IN",
    "ks:ks_alt_nam":"PHTANAU MUHALLH",
    "ks:ks_name":"Phtanau Muhallh",
    "ks:ks_pop":186,
    "ks:ks_type":"HABITATION",
    "name:eng_x_preferred":[
        "Phtanau Muhallh"
    ],
    "wof:name":"Phtanau Muhallh",
    "wof:placetype":"locality",
    "wof:population":186
},
  "geometry": {"coordinates":[81.803731,26.491831],"type":"Point"}
}