{
  "type": "Feature",
  "properties": {
    "gn:admin1_code":"2.0",
    "gn:admin2_code":"550",
    "gn:asciiname":"Chennur",
    "gn:country_code":"IN",
    "gn:dem":23,
    "gn:feature_class":"P",
    "gn:feature_code":"PPL",
    "gn:name":"Chenn\u016br",
    "gn:population":0,
    "gn:timezone":"Asia/Kolkata",
    "iso:country":"IN",
    "name:und_x_variant":[
        "Chenn\u016br",
        "Chenn\u016bru"
    ],
    "wof:name":"Chennur",
    "wof:placetype":"locality"
},
  "geometry": {"coordinates":[79.79859999999999,14.15587],"type":"Point"}
}