{
  "type": "Feature",
  "properties": {
    "iso:country":"IN",
    "name:ara_x_preferred":[
        "\u0633\u0627\u0632\u064a\u0627\u0645\u0631\u062b\u064a \u0646\u0627\u062c\u0627\u0631"
    ],
    "name:ben_bn_x_preferred":[
        "\u09b8\u09a4\u09cd\u09af\u09ae\u09c2\u09b0\u09cd\u09a4\u09bf \u09a8\u0997\u09b0"
    ],
    "name:ben_in_x_preferred":[
        "\u09b8\u09a4\u09cd\u09af\u09ae\u09c2\u09b0\u09cd\u09a4\u09bf \u09a8\u0997\u09b0"
    ],
    "name:eng_x_preferred":[
        "Sathyamurthi Nagar"
    ],
    "name:guj_x_preferred":[
        "\u0ab8\u0aa4\u0acd\u0aaf\u0aae\u0ac1\u0ab0\u0acd\u0aa4\u0ac0 \u0aa8\u0a97\u0ab0"
    ],
    "name:hin_x_preferred":[
        "\u0938\u0924\u094d\u092f\u092e\u0942\u0930\u094d\u0924\u0940 \u0928\u0917\u0930"
    ],
    "name:kan_x_preferred":[
        "\u0cb8\u0ca4\u0ccd\u0caf\u0cae\u0cc2\u0cb0\u0ccd\u0ca4\u0cbf \u0ca8\u0c97\u0cb0"
    ],
    "name:mal_x_preferred":[
        "\u0d38\u0d24\u0d4d\u0d2f\u0d2e\u0d42\u0d7c\u0d24\u0d4d\u0d24\u0d3f \u0d28\u0d17\u0d7c"
    ],
    "name:mar_x_preferred":[
        "\u0938\u0924\u094d\u092f\u092e\u0942\u0930\u094d\u0924\u0940 \u0928\u0917\u0930"
    ],
    "name:pan_x_preferred":[
        "\u0a38\u0a24\u0a3f\u0a06\u0a2e\u0a42\u0a30\u0a24\u0a40 \u0a28\u0a17\u0a30"
    ],
    "name:tam_x_preferred":[
        "\u0b9a\u0ba4\u0bcd\u0ba4\u0bbf\u0baf\u0bae\u0bc2\u0bb0\u0bcd\u0ba4\u0bcd\u0ba4\u0bbf \u0ba8\u0b95\u0bb0\u0bcd"
    ],
    "name:tel_x_preferred":[
        "\u0c38\u0c24\u0c4d\u0c2f\u0c2e\u0c42\u0c30\u0c4d\u0c24\u0c3f \u0c28\u0c17\u0c30\u0c4d"
    ],
    "name:urd_x_preferred":[
        "\u0633\u062a\u06cc\u06c1 \u0645\u0648\u0631\u062a\u06cc \u0646\u06af\u0631"
    ],
    "qs:gn_adm0_cc":"IN",
    "qs:gn_fcode":"PPLX",
    "qs:gn_local":1254331,
    "qs:gn_nam_loc":"tiruvallur",
    "qs:gn_namadm1":"25",
    "qs:gn_name":"Satyamurti Nagar",
    "qs:local_max":148,
    "qs:local_sum":450,
    "qs:localhoods":11,
    "qs:name":"Sathyamurthi Nagar",
    "qs:name_adm0":"India",
    "qs:name_adm1":"Tamil Nadu",
    "qs:name_adm2":"Thiruvallur",
    "qs:name_local":"Tiruvallur",
    "qs:photo_max":5,
    "qs:photo_sum":6,
    "qs:placetype":"Suburb",
    "qs:quad_count":2,
    "qs:woe_adm0":23424848,
    "qs:woe_adm1":2345758,
    "qs:woe_adm2":12586703,
    "qs:woe_lau":0,
    "qs:woe_local":2287533,
    "qs:woe_ver":"7.10.0",
    "wof:lang":[
        "eng"
    ],
    "wof:name":"Sathyamurthi Nagar",
    "wof:placetype":"neighbourhood"
},
  "geometry": {"coordinates":[80.131531,13.134762],"type":"Point"}
}