{
  "type": "Feature",
  "properties": {
    "iso:country":"IN",
    "name:eng_x_preferred":[
        "Sathyamurthi Nagar"
    ],
    "name:unk_x_variant":[
        "Sathyamurthi Nagar"
    ],
    "qs:gn_adm0_cc":"IN",
    "qs:gn_fcode":"PPLX",
    "qs:gn_local":1254331,
    "qs:gn_nam_loc":"tiruvallur",
    "qs:gn_namadm1":"25",
    "qs:gn_name":"Satyamurti Nagar",
    "qs:local_max":148,
    "qs:local_sum":450,
    "qs:localhoods":11,
    "qs:name":"Sathyamurthi Nagar",
    "qs:name_adm0":"India",
    "qs:name_adm1":"Tamil Nadu",
    "qs:name_adm2":"Thiruvallur",
    "qs:name_local":"Tiruvallur",
    "qs:photo_max":5,
    "qs:photo_sum":6,
    "qs:placetype":"Suburb",
    "qs:quad_count":2,
    "qs:woe_adm0":23424848,
    "qs:woe_adm1":2345758,
    "qs:woe_adm2":12586703,
    "qs:woe_lau":0,
    "qs:woe_local":2287533,
    "qs:woe_ver":"7.10.0",
    "wof:lang":[
        "eng"
    ],
    "wof:name":"Sathyamurthi Nagar",
    "wof:placetype":"neighbourhood"
},
  "geometry": {"coordinates":[80.131531,13.134762],"type":"Point"}
}