{
  "type": "Feature",
  "properties": {
    "gn:admin1_code":"25.0",
    "gn:admin2_code":"616.0",
    "gn:asciiname":"Tandavarayankudikkadu",
    "gn:country_code":"IN",
    "gn:dem":22,
    "gn:feature_class":"P",
    "gn:feature_code":"PPL",
    "gn:name":"T\u0101ndavaray\u0101nkudikk\u0101du",
    "gn:population":0,
    "gn:timezone":"Asia/Kolkata",
    "iso:country":"IN",
    "wof:name":"Tandavarayankudikkadu",
    "wof:placetype":"locality"
},
  "geometry": {"coordinates":[79.43867,11.14005],"type":"Point"}
}