{
  "type": "Feature",
  "properties": {
    "gn:admin1_code":"40",
    "gn:admin2_code":"537.0",
    "gn:asciiname":"Ponagutta Tanda",
    "gn:country_code":"IN",
    "gn:dem":589,
    "gn:feature_class":"P",
    "gn:feature_code":"PPL",
    "gn:name":"Ponagutta T\u0101nda",
    "gn:population":0,
    "gn:timezone":"Asia/Kolkata",
    "iso:country":"IN",
    "wof:name":"Ponagutta Tanda",
    "wof:placetype":"locality"
},
  "geometry": {"coordinates":[78.22010999999998,17.43627],"type":"Point"}
}