{
  "type": "Feature",
  "properties": {
    "iso:country":"IN",
    "ks:ks_name":"Kattinaickenpatty",
    "ks:ks_pop":791,
    "ks:ks_type":"HABITATION",
    "ks:ks_uagg_main":0,
    "name:eng_x_preferred":[
        "Kattinaickenpatty"
    ],
    "wof:name":"Kattinaickenpatty",
    "wof:placetype":"neighbourhood",
    "wof:population":791
},
  "geometry": {"coordinates":[77.873786,11.686381],"type":"Point"}
}