{
  "type": "Feature",
  "properties": {
    "iso:country":"IN",
    "ks:ks_name":"Ghivdoda",
    "ks:ks_pop":22,
    "ks:ks_type":"VILLAGE",
    "name:eng_x_preferred":[
        "Ghivdoda"
    ],
    "wof:name":"Ghivdoda",
    "wof:placetype":"locality",
    "wof:population":22
},
  "geometry": {"coordinates":[81.596251,25.237417],"type":"Point"}
}