{
  "type": "Feature",
  "properties": {
    "iso:country":"IN",
    "ks:ks_name":"Padariya Bareli",
    "ks:ks_pop":17,
    "ks:ks_type":"HABITATION",
    "name:eng_x_preferred":[
        "Padariya Bareli"
    ],
    "wof:name":"Padariya Bareli",
    "wof:placetype":"locality",
    "wof:population":17
},
  "geometry": {"coordinates":[80.38773999999999,23.489076],"type":"Point"}
}