{
  "type": "Feature",
  "properties": {
    "iso:country":"IN",
    "ks:ks_name":"Chivatewasti",
    "ks:ks_pop":94,
    "ks:ks_type":"HABITATION",
    "name:eng_x_preferred":[
        "Chivatewasti"
    ],
    "wof:name":"Chivatewasti",
    "wof:placetype":"locality",
    "wof:population":94
},
  "geometry": {"coordinates":[75.66922,18.32605],"type":"Point"}
}