{
  "type": "Feature",
  "properties": {
    "iso:country":"IN",
    "ks:ks_alt_nam":"Tasatw\u0101r",
    "ks:ks_name":"Tasatwar",
    "ks:ks_pop":138,
    "ks:ks_type":"VILLAGE",
    "name:eng_x_preferred":[
        "Tasatwar"
    ],
    "name:eng_x_variant":[
        "Tasatw\u0101r"
    ],
    "wof:name":"Tasatwar",
    "wof:placetype":"locality",
    "wof:population":138
},
  "geometry": {"coordinates":[84.809676,23.831887],"type":"Point"}
}