{
  "type": "Feature",
  "properties": {
    "iso:country":"IN",
    "ks:ks_name":"Madigapalle",
    "ks:ks_pop":211,
    "ks:ks_type":"HABITATION",
    "ks:ks_uagg_main":0,
    "name:eng_x_preferred":[
        "Madigapalle"
    ],
    "wof:name":"Madigapalle",
    "wof:placetype":"neighbourhood",
    "wof:population":211
},
  "geometry": {"coordinates":[78.647914,13.559565],"type":"Point"}
}