{
  "type": "Feature",
  "properties": {
    "iso:country":"IN",
    "ks:ks_name":"Pappana Thanda",
    "ks:ks_pop":119,
    "ks:ks_type":"HABITATION",
    "name:eng_x_preferred":[
        "Pappana Thanda"
    ],
    "wof:name":"Pappana Thanda",
    "wof:placetype":"locality",
    "wof:population":119
},
  "geometry": {"coordinates":[77.851006,13.832005],"type":"Point"}
}