{
  "type": "Feature",
  "properties": {
    "iso:country":"IN",
    "ks:ks_name":"Raghunadhapalem",
    "ks:ks_pop":597,
    "ks:ks_type":"HABITATION",
    "name:eng_x_preferred":[
        "Raghunadhapalem"
    ],
    "wof:name":"Raghunadhapalem",
    "wof:placetype":"locality",
    "wof:population":597
},
  "geometry": {"coordinates":[80.527444,18.053874],"type":"Point"}
}