{
  "type": "Feature",
  "properties": {
    "iso:country":"IN",
    "ks:ks_name":"Chalanguda",
    "ks:ks_pop":263,
    "ks:ks_type":"HABITATION",
    "name:eng_x_preferred":[
        "Chalanguda"
    ],
    "wof:name":"Chalanguda",
    "wof:placetype":"locality",
    "wof:population":263
},
  "geometry": {"coordinates":[82.204958,19.727522],"type":"Point"}
}