{
  "type": "Feature",
  "properties": {
    "iso:country":"IN",
    "ks:ks_name":"Bettu Qadim",
    "ks:ks_pop":242,
    "ks:ks_type":"HABITATION",
    "name:eng_x_preferred":[
        "Bettu Qadim"
    ],
    "wof:name":"Bettu Qadim",
    "wof:placetype":"locality",
    "wof:population":242
},
  "geometry": {"coordinates":[74.419343,30.810723],"type":"Point"}
}