{
  "type": "Feature",
  "properties": {
    "gn:admin1_code":"35",
    "gn:admin2_code":"422.0",
    "gn:asciiname":"Imlia",
    "gn:country_code":"IN",
    "gn:dem":222,
    "gn:feature_class":"P",
    "gn:feature_code":"PPL",
    "gn:name":"Imlia",
    "gn:population":0,
    "gn:timezone":"Asia/Kolkata",
    "iso:country":"IN",
    "wof:name":"Imlia",
    "wof:placetype":"neighbourhood"
},
  "geometry": {"coordinates":[78.58132000000001,25.69292],"type":"Point"}
}