{
  "type": "Feature",
  "properties": {
    "gn:admin1_code":"37",
    "gn:admin2_code":"405.0",
    "gn:asciiname":"Sulauni",
    "gn:country_code":"IN",
    "gn:dem":229,
    "gn:feature_class":"P",
    "gn:feature_code":"PPL",
    "gn:name":"Sulauni",
    "gn:population":0,
    "gn:timezone":"Asia/Kolkata",
    "iso:country":"IN",
    "ks:ks_name":"Sulauni",
    "ks:ks_pop":936,
    "ks:ks_type":"VILLAGE",
    "ks:ks_uagg_main":0,
    "name:eng_x_preferred":[
        "Sulauni"
    ],
    "wof:name":"Sulauni",
    "wof:placetype":"neighbourhood",
    "wof:population":936
},
  "geometry": {"coordinates":[82.940129,21.925203],"type":"Point"}
}