{
  "type": "Feature",
  "properties": {
    "iso:country":"IN",
    "ks:ks_name":"Nutan Para",
    "ks:ks_pop":231,
    "ks:ks_type":"HABITATION",
    "name:eng_x_preferred":[
        "Nutan Para"
    ],
    "wof:name":"Nutan Para",
    "wof:placetype":"locality",
    "wof:population":231
},
  "geometry": {"coordinates":[92.260952,24.184693],"type":"Point"}
}