{
  "type": "Feature",
  "properties": {
    "iso:country":"IN",
    "ks:ks_name":"Byadarahosahalli",
    "ks:ks_pop":52,
    "ks:ks_type":"VILLAGE",
    "name:eng_x_preferred":[
        "Byadarahosahalli"
    ],
    "wof:name":"Byadarahosahalli",
    "wof:placetype":"locality",
    "wof:population":52
},
  "geometry": {"coordinates":[76.814324,13.009726],"type":"Point"}
}