{
  "type": "Feature",
  "properties": {
    "iso:country":"IN",
    "ks:ks_name":"Jhinjhana",
    "ks:ks_pop":452,
    "ks:ks_type":"VILLAGE",
    "name:eng_x_preferred":[
        "Jhinjhana"
    ],
    "wof:name":"Jhinjhana",
    "wof:placetype":"locality",
    "wof:population":452
},
  "geometry": {"coordinates":[74.154707,22.319369],"type":"Point"}
}