{
  "type": "Feature",
  "properties": {
    "gn:admin1_code":"40",
    "gn:admin2_code":"532.0",
    "gn:asciiname":"Mudhol",
    "gn:country_code":"IN",
    "gn:dem":374,
    "gn:feature_class":"P",
    "gn:feature_code":"PPL",
    "gn:name":"Mudhol",
    "gn:population":0,
    "gn:timezone":"Asia/Kolkata",
    "iso:country":"IN",
    "name:bar_x_preferred":[
        "Mudhol"
    ],
    "name:ben_x_preferred":[
        "\u09ae\u09c1\u09a7\u09cb\u09b2"
    ],
    "name:bpy_x_preferred":[
        "\u09ae\u09c1\u09a6\u09b9\u09b2"
    ],
    "name:ceb_x_preferred":[
        "Mudhol"
    ],
    "name:deu_x_preferred":[
        "Mudhol"
    ],
    "name:ita_x_preferred":[
        "Mudhol"
    ],
    "name:jpn_x_preferred":[
        "\u30e0\u30c9\u30fc\u30eb"
    ],
    "name:kan_x_preferred":[
        "\u0cae\u0cc1\u0ca7\u0ccb\u0cb3"
    ],
    "name:mlg_x_preferred":[
        "Mudhol"
    ],
    "name:msa_x_preferred":[
        "Mudhol"
    ],
    "name:new_x_preferred":[
        "\u092e\u0941\u0927\u094b\u0932"
    ],
    "name:nld_x_preferred":[
        "Mudhol"
    ],
    "name:ori_x_preferred":[
        "\u0b2e\u0b41\u0b27\u0b4b\u0b32\u0b4d"
    ],
    "name:spa_x_preferred":[
        "Mudhol"
    ],
    "name:urd_x_preferred":[
        "\u0645\u0648\u062f\u06be\u0648\u0644"
    ],
    "name:vie_x_preferred":[
        "Mudhol"
    ],
    "name:zho_x_preferred":[
        "\u7a46\u591a\u5c14"
    ],
    "wof:name":"Mudhol",
    "wof:placetype":"locality"
},
  "geometry": {"coordinates":[77.91070999999999,18.97479],"type":"Point"}
}