{
  "type": "Feature",
  "properties": {
    "gn:admin1_code":"40",
    "gn:admin2_code":"532.0",
    "gn:asciiname":"Mudhol",
    "gn:country_code":"IN",
    "gn:dem":374,
    "gn:feature_class":"P",
    "gn:feature_code":"PPL",
    "gn:name":"Mudhol",
    "gn:population":0,
    "gn:timezone":"Asia/Kolkata",
    "iso:country":"IN",
    "wof:name":"Mudhol",
    "wof:placetype":"locality"
},
  "geometry": {"coordinates":[77.91070999999999,18.97479],"type":"Point"}
}