{
  "type": "Feature",
  "properties": {
    "gn:admin1_code":"36.0",
    "gn:admin2_code":"184.0",
    "gn:asciiname":"Sakhui Khurd",
    "gn:country_code":"IN",
    "gn:dem":95,
    "gn:feature_class":"P",
    "gn:feature_code":"PPL",
    "gn:name":"Sakhui Khurd",
    "gn:population":0,
    "gn:timezone":"Asia/Kolkata",
    "iso:country":"IN",
    "wof:name":"Sakhui Khurd",
    "wof:placetype":"neighbourhood"
},
  "geometry": {"coordinates":[82.72995,27.27597],"type":"Point"}
}