{
  "type": "Feature",
  "properties": {
    "iso:country":"IN",
    "ks:ks_name":"Rajganga",
    "ks:ks_pop":952,
    "ks:ks_type":"VILLAGE",
    "ks:ks_uagg_main":0,
    "name:eng_x_preferred":[
        "Rajganga"
    ],
    "wof:name":"Rajganga",
    "wof:placetype":"neighbourhood",
    "wof:population":952
},
  "geometry": {"coordinates":[87.564222,22.668332],"type":"Point"}
}