{
  "type": "Feature",
  "properties": {
    "iso:country":"IN",
    "ks:ks_name":"Jhatiapalli",
    "ks:ks_pop":216,
    "ks:ks_type":"VILLAGE",
    "name:eng_x_preferred":[
        "Jhatiapalli"
    ],
    "wof:name":"Jhatiapalli",
    "wof:placetype":"locality",
    "wof:population":216
},
  "geometry": {"coordinates":[85.308522,20.317451],"type":"Point"}
}