{
  "type": "Feature",
  "properties": {
    "gn:admin1_code":"36",
    "gn:admin2_code":"174.0",
    "gn:asciiname":"Sukhdharanpur Kithuan",
    "gn:country_code":"IN",
    "gn:dem":110,
    "gn:feature_class":"P",
    "gn:feature_code":"PPL",
    "gn:name":"Sukhdh\u0101ranpur Kithu\u0101n",
    "gn:population":0,
    "gn:timezone":"Asia/Kolkata",
    "iso:country":"IN",
    "ks:ks_name":"Shukhdharanpur Kithawan",
    "ks:ks_pop":455,
    "ks:ks_type":"VILLAGE",
    "name:eng_x_preferred":[
        "Shukhdharanpur Kithawan"
    ],
    "name:eng_x_variant":[
        "Sukhdharanpur Kithuan"
    ],
    "wof:name":"Shukhdharanpur Kithawan",
    "wof:placetype":"locality",
    "wof:population":455
},
  "geometry": {"coordinates":[81.33626099999999,25.677177],"type":"Point"}
}