{
  "type": "Feature",
  "properties": {
    "gn:admin1_code":"36",
    "gn:admin2_code":"174.0",
    "gn:asciiname":"Sukhdharanpur Kithuan",
    "gn:country_code":"IN",
    "gn:dem":110,
    "gn:feature_class":"P",
    "gn:feature_code":"PPL",
    "gn:name":"Sukhdh\u0101ranpur Kithu\u0101n",
    "gn:population":0,
    "gn:timezone":"Asia/Kolkata",
    "iso:country":"IN",
    "wof:name":"Sukhdharanpur Kithuan",
    "wof:placetype":"locality"
},
  "geometry": {"coordinates":[81.34023000000001,25.67679],"type":"Point"}
}