{
  "type": "Feature",
  "properties": {
    "gn:admin1_code":"36.0",
    "gn:admin2_code":"136.0",
    "gn:asciiname":"Gajraula",
    "gn:country_code":"IN",
    "gn:dem":209,
    "gn:feature_class":"P",
    "gn:feature_code":"PPL",
    "gn:name":"Gajraula",
    "gn:population":0,
    "gn:timezone":"Asia/Kolkata",
    "iso:country":"IN",
    "ks:ks_name":"Gajraula",
    "ks:ks_pop":421,
    "ks:ks_type":"VILLAGE",
    "ks:ks_uagg_main":0,
    "name:bpy_x_preferred":[
        "\u0997\u099c\u09b0\u09be\u09f1\u09c1\u09b2\u09be"
    ],
    "name:ceb_x_preferred":[
        "Gajraula"
    ],
    "name:eng_x_preferred":[
        "Gajraula"
    ],
    "name:hin_x_preferred":[
        "\u0917\u091c\u0930\u094c\u0932\u093e"
    ],
    "name:ita_x_preferred":[
        "Gajraula"
    ],
    "name:mlg_x_preferred":[
        "Gajraula"
    ],
    "name:msa_x_preferred":[
        "Gajraula"
    ],
    "name:new_x_preferred":[
        "\u0917\u091c\u094d\u0930\u094c\u0932\u093e"
    ],
    "name:nld_x_preferred":[
        "Gajraula"
    ],
    "name:pol_x_preferred":[
        "Gajraula"
    ],
    "name:por_x_preferred":[
        "Gajraula"
    ],
    "name:swe_x_preferred":[
        "Gajraula"
    ],
    "name:urd_x_preferred":[
        "\u06af\u062c\u0631\u0648\u0644\u06c1"
    ],
    "name:vie_x_preferred":[
        "Gajraula"
    ],
    "name:zho_x_preferred":[
        "\u52a0\u6770\u52b3\u62c9"
    ],
    "wof:name":"Gajraula",
    "wof:placetype":"neighbourhood",
    "wof:population":421
},
  "geometry": {"coordinates":[78.965371,29.010364],"type":"Point"}
}