{
  "type": "Feature",
  "properties": {
    "iso:country":"IN",
    "ks:ks_name":"Siddirajukandrika",
    "ks:ks_pop":427,
    "ks:ks_type":"HABITATION",
    "name:eng_x_preferred":[
        "Siddirajukandrika"
    ],
    "wof:name":"Siddirajukandrika",
    "wof:placetype":"locality",
    "wof:population":427
},
  "geometry": {"coordinates":[79.33896799999999,13.930384],"type":"Point"}
}