{
  "type": "Feature",
  "properties": {
    "iso:country":"IN",
    "ks:ks_name":"Sipah Maheri",
    "ks:ks_pop":660,
    "ks:ks_type":"VILLAGE",
    "name:eng_x_preferred":[
        "Sipah Maheri"
    ],
    "wof:name":"Sipah Maheri",
    "wof:placetype":"locality",
    "wof:population":660
},
  "geometry": {"coordinates":[81.98798600000001,25.835672],"type":"Point"}
}