{
  "type": "Feature",
  "properties": {
    "iso:country":"IN",
    "ks:ks_name":"Kodasinge",
    "ks:ks_pop":44,
    "ks:ks_type":"HABITATION",
    "name:eng_x_preferred":[
        "Kodasinge"
    ],
    "wof:name":"Kodasinge",
    "wof:placetype":"locality",
    "wof:population":44
},
  "geometry": {"coordinates":[74.81731000000001,14.516475],"type":"Point"}
}