{
  "type": "Feature",
  "properties": {
    "gn:admin1_code":"36.0",
    "gn:admin2_code":"143.0",
    "gn:asciiname":"Mohkampur",
    "gn:country_code":"IN",
    "gn:dem":178,
    "gn:feature_class":"P",
    "gn:feature_code":"PPL",
    "gn:name":"Mohkampur",
    "gn:population":0,
    "gn:timezone":"Asia/Kolkata",
    "iso:country":"IN",
    "ks:ks_name":"Mohkampur",
    "ks:ks_pop":662,
    "ks:ks_type":"HABITATION",
    "name:eng_x_preferred":[
        "Mohkampur"
    ],
    "wof:name":"Mohkampur",
    "wof:placetype":"locality",
    "wof:population":662
},
  "geometry": {"coordinates":[78.53565999999999,28.021595],"type":"Point"}
}