{
  "type": "Feature",
  "properties": {
    "iso:country":"IN",
    "ks:ks_name":"Dhumatsasan",
    "ks:ks_pop":2051,
    "ks:ks_type":"VILLAGE",
    "ks:ks_uagg_main":0,
    "name:eng_x_preferred":[
        "Dhumatsasan"
    ],
    "wof:name":"Dhumatsasan",
    "wof:placetype":"neighbourhood",
    "wof:population":2051
},
  "geometry": {"coordinates":[86.405244,20.610442],"type":"Point"}
}