{
  "type": "Feature",
  "properties": {
    "gn:admin1_code":"34.0",
    "gn:admin2_code":"220.0",
    "gn:asciiname":"Amer",
    "gn:country_code":"IN",
    "gn:dem":56,
    "gn:feature_class":"P",
    "gn:feature_code":"PPL",
    "gn:name":"Amer",
    "gn:population":0,
    "gn:timezone":"Asia/Kolkata",
    "iso:country":"IN",
    "name:ceb_x_preferred":[
        "Amer"
    ],
    "name:deu_x_preferred":[
        "Amer"
    ],
    "name:fra_x_preferred":[
        "Amer"
    ],
    "name:ita_x_preferred":[
        "Amer"
    ],
    "name:nld_x_preferred":[
        "Amer"
    ],
    "name:swe_x_preferred":[
        "Amer"
    ],
    "wof:name":"Amer",
    "wof:placetype":"locality"
},
  "geometry": {"coordinates":[85.33099,25.63339],"type":"Point"}
}