{
  "type": "Feature",
  "properties": {
    "iso:country":"IN",
    "ks:ks_alt_nam":"NARAYAN PUR",
    "ks:ks_name":"Narayan Pur",
    "ks:ks_pop":1050,
    "ks:ks_type":"HABITATION",
    "name:eng_x_preferred":[
        "Narayan Pur"
    ],
    "wof:name":"Narayan Pur",
    "wof:placetype":"locality",
    "wof:population":1050
},
  "geometry": {"coordinates":[84.76691,25.944298],"type":"Point"}
}