{
  "type": "Feature",
  "properties": {
    "gn:admin1_code":"03",
    "gn:admin2_code":"314.0",
    "gn:asciiname":"Umswai",
    "gn:country_code":"IN",
    "gn:dem":632,
    "gn:feature_class":"P",
    "gn:feature_code":"PPL",
    "gn:name":"Umswai",
    "gn:population":0,
    "gn:timezone":"Asia/Kolkata",
    "iso:country":"IN",
    "wof:name":"Umswai",
    "wof:placetype":"locality"
},
  "geometry": {"coordinates":[92.23865000000001,25.94002],"type":"Point"}
}