{
  "type": "Feature",
  "properties": {
    "iso:country":"IN",
    "ks:ks_name":"Tarpura",
    "ks:ks_pop":432,
    "ks:ks_type":"HABITATION",
    "name:eng_x_preferred":[
        "Tarpura"
    ],
    "wof:name":"Tarpura",
    "wof:placetype":"locality",
    "wof:population":432
},
  "geometry": {"coordinates":[71.966459,27.837384],"type":"Point"}
}