{
  "type": "Feature",
  "properties": {
    "gn:admin1_code":"36",
    "gn:admin2_code":"179.0",
    "gn:asciiname":"Purwa Udhiare",
    "gn:country_code":"IN",
    "gn:dem":100,
    "gn:feature_class":"P",
    "gn:feature_code":"PPL",
    "gn:name":"Purwa Udhi\u0101re",
    "gn:population":0,
    "gn:timezone":"Asia/Kolkata",
    "iso:country":"IN",
    "wof:name":"Purwa Udhiare",
    "wof:placetype":"neighbourhood"
},
  "geometry": {"coordinates":[82.17367,26.24617],"type":"Point"}
}