{
  "type": "Feature",
  "properties": {
    "gn:admin1_code":"34.0",
    "gn:admin2_code":"236.0",
    "gn:asciiname":"Baheliya Bigha",
    "gn:country_code":"IN",
    "gn:dem":141,
    "gn:feature_class":"P",
    "gn:feature_code":"PPL",
    "gn:name":"Baheliya Bigha",
    "gn:population":0,
    "gn:timezone":"Asia/Kolkata",
    "iso:country":"IN",
    "ks:ks_alt_nam":"BAHALIYA BIGHA",
    "ks:ks_name":"Bahaliya Bigha",
    "ks:ks_pop":226,
    "ks:ks_type":"HABITATION",
    "name:eng_x_preferred":[
        "Bahaliya Bigha"
    ],
    "name:eng_x_variant":[
        "Baheliya Bigha"
    ],
    "wof:name":"Bahaliya Bigha",
    "wof:placetype":"locality",
    "wof:population":226
},
  "geometry": {"coordinates":[84.836589,24.606639],"type":"Point"}
}