{
  "type": "Feature",
  "properties": {
    "iso:country":"IN",
    "ks:ks_name":"Moonumuri",
    "ks:ks_pop":354,
    "ks:ks_type":"HABITATION",
    "name:eng_x_preferred":[
        "Moonumuri"
    ],
    "wof:name":"Moonumuri",
    "wof:placetype":"locality",
    "wof:population":354
},
  "geometry": {"coordinates":[76.307213,10.20878],"type":"Point"}
}