{
  "type": "Feature",
  "properties": {
    "gn:admin1_code":"24.0",
    "gn:admin2_code":"122.0",
    "gn:asciiname":"Dhaniya",
    "gn:country_code":"IN",
    "gn:dem":513,
    "gn:feature_class":"P",
    "gn:feature_code":"PPL",
    "gn:name":"Dh\u0101niya",
    "gn:population":0,
    "gn:timezone":"Asia/Kolkata",
    "iso:country":"IN",
    "name:und_x_variant":[
        "Dh\u0101niya",
        "D\u0101niya Som\u0101niya"
    ],
    "wof:name":"Dhaniya",
    "wof:placetype":"locality"
},
  "geometry": {"coordinates":[74.24861,25.47427],"type":"Point"}
}