{
  "type": "Feature",
  "properties": {
    "gn:admin1_code":"2.0",
    "gn:admin2_code":"553.0",
    "gn:asciiname":"Kammavaripalle",
    "gn:country_code":"IN",
    "gn:dem":336,
    "gn:feature_class":"P",
    "gn:feature_code":"PPL",
    "gn:name":"Kammav\u0101ripalle",
    "gn:population":0,
    "gn:timezone":"Asia/Kolkata",
    "iso:country":"IN",
    "ks:ks_name":"Kammavaripalli",
    "ks:ks_pop":272,
    "ks:ks_type":"HABITATION",
    "name:eng_x_preferred":[
        "Kammavaripalli"
    ],
    "name:eng_x_variant":[
        "Kammavaripalle"
    ],
    "wof:name":"Kammavaripalli",
    "wof:placetype":"locality",
    "wof:population":272
},
  "geometry": {"coordinates":[77.944607,14.421894],"type":"Point"}
}