{
  "type": "Feature",
  "properties": {
    "iso:country":"IN",
    "ks:ks_alt_nam":"Budh\u0101b\u0101ri",
    "ks:ks_name":"Budhabari",
    "ks:ks_pop":137,
    "ks:ks_type":"VILLAGE",
    "name:eng_x_preferred":[
        "Budhabari"
    ],
    "name:eng_x_variant":[
        "Budh\u0101b\u0101ri"
    ],
    "wof:name":"Budhabari",
    "wof:placetype":"locality",
    "wof:population":137
},
  "geometry": {"coordinates":[84.93979400000001,20.237828],"type":"Point"}
}