{
  "type": "Feature",
  "properties": {
    "iso:country":"IN",
    "ks:ks_name":"Bir Majal",
    "ks:ks_pop":0,
    "ks:ks_type":"VILLAGE",
    "name:eng_x_preferred":[
        "Bir Majal"
    ],
    "wof:name":"Bir Majal",
    "wof:placetype":"locality",
    "wof:population":0
},
  "geometry": {"coordinates":[76.412976,30.210695],"type":"Point"}
}