{
  "type": "Feature",
  "properties": {
    "gn:admin1_code":"37",
    "gn:admin2_code":"407.0",
    "gn:asciiname":"Limo",
    "gn:country_code":"IN",
    "gn:dem":341,
    "gn:feature_class":"P",
    "gn:feature_code":"PPL",
    "gn:name":"L\u012bmo",
    "gn:population":0,
    "gn:timezone":"Asia/Kolkata",
    "iso:country":"IN",
    "name:arg_x_preferred":[
        "Limo"
    ],
    "name:ceb_x_preferred":[
        "Limo"
    ],
    "name:deu_x_preferred":[
        "Limo"
    ],
    "name:epo_x_preferred":[
        "Limo"
    ],
    "name:fin_x_preferred":[
        "Limo"
    ],
    "name:fra_x_preferred":[
        "Limo"
    ],
    "name:ita_x_preferred":[
        "Limo"
    ],
    "name:nld_x_preferred":[
        "Limo"
    ],
    "name:pol_x_preferred":[
        "Limo"
    ],
    "name:swe_x_preferred":[
        "Limo"
    ],
    "wof:name":"Limo",
    "wof:placetype":"locality"
},
  "geometry": {"coordinates":[81.25084,21.97435],"type":"Point"}
}