{
  "type": "Feature",
  "properties": {
    "iso:country":"IN",
    "ks:ks_name":"Basra",
    "ks:ks_pop":292,
    "ks:ks_type":"HABITATION",
    "name:eng_x_preferred":[
        "Basra"
    ],
    "wof:name":"Basra",
    "wof:placetype":"locality",
    "wof:population":292
},
  "geometry": {"coordinates":[70.81554199999999,26.357392],"type":"Point"}
}