{
  "type": "Feature",
  "properties": {
    "iso:country":"IN",
    "ks:ks_name":"Alangar",
    "ks:ks_pop":725,
    "ks:ks_type":"HABITATION",
    "name:eng_x_preferred":[
        "Alangar"
    ],
    "wof:name":"Alangar",
    "wof:placetype":"locality",
    "wof:population":725
},
  "geometry": {"coordinates":[75.112482,12.745867],"type":"Point"}
}