{
  "type": "Feature",
  "properties": {
    "gn:admin1_code":"39",
    "gn:admin2_code":"61.0",
    "gn:asciiname":"Khingsari",
    "gn:country_code":"IN",
    "gn:dem":1569,
    "gn:feature_class":"P",
    "gn:feature_code":"PPL",
    "gn:name":"Khings\u0101ri",
    "gn:population":0,
    "gn:timezone":"Asia/Kolkata",
    "iso:country":"IN",
    "wof:name":"Khingsari",
    "wof:placetype":"locality"
},
  "geometry": {"coordinates":[78.91306999999998,30.20508],"type":"Point"}
}