{
  "type": "Feature",
  "properties": {
    "iso:country":"IN",
    "ks:ks_name":"Chauri Kalan",
    "ks:ks_pop":0,
    "ks:ks_type":"VILLAGE",
    "name:eng_x_preferred":[
        "Chauri Kalan"
    ],
    "wof:name":"Chauri Kalan",
    "wof:placetype":"locality",
    "wof:population":0
},
  "geometry": {"coordinates":[84.311193,25.991139],"type":"Point"}
}