{
  "type": "Feature",
  "properties": {
    "gn:admin1_code":"36",
    "gn:admin2_code":"134.0",
    "gn:asciiname":"Khatapur",
    "gn:country_code":"IN",
    "gn:dem":240,
    "gn:feature_class":"P",
    "gn:feature_code":"PPL",
    "gn:name":"Khat\u0101pur",
    "gn:population":0,
    "gn:timezone":"Asia/Kolkata",
    "iso:country":"IN",
    "name:und_x_variant":[
        "Khat\u0101pur",
        "At\u0101pur"
    ],
    "wof:name":"Khatapur",
    "wof:placetype":"locality"
},
  "geometry": {"coordinates":[78.25466,29.27473],"type":"Point"}
}