{
  "type": "Feature",
  "properties": {
    "iso:country":"IN",
    "ks:ks_name":"Khadakwadi",
    "ks:ks_pop":136,
    "ks:ks_type":"HABITATION",
    "name:eng_x_preferred":[
        "Khadakwadi"
    ],
    "wof:name":"Khadakwadi",
    "wof:placetype":"locality",
    "wof:population":136
},
  "geometry": {"coordinates":[73.68632700000001,16.772953],"type":"Point"}
}