{
  "type": "Feature",
  "properties": {
    "iso:country":"IN",
    "ks:ks_name":"Shahpur",
    "ks:ks_pop":532,
    "ks:ks_type":"HABITATION",
    "name:eng_x_preferred":[
        "Shahpur"
    ],
    "wof:name":"Shahpur",
    "wof:placetype":"locality",
    "wof:population":532
},
  "geometry": {"coordinates":[85.90814,24.985409],"type":"Point"}
}