{
  "type": "Feature",
  "properties": {
    "iso:country":"IN",
    "ks:ks_name":"Chauthaiwadi",
    "ks:ks_pop":122,
    "ks:ks_type":"HABITATION",
    "name:eng_x_preferred":[
        "Chauthaiwadi"
    ],
    "wof:name":"Chauthaiwadi",
    "wof:placetype":"locality",
    "wof:population":122
},
  "geometry": {"coordinates":[73.406836,17.207695],"type":"Point"}
}