{
  "type": "Feature",
  "properties": {
    "iso:country":"IN",
    "ks:ks_name":"Nilaj",
    "ks:ks_pop":583,
    "ks:ks_type":"HABITATION",
    "name:eng_x_preferred":[
        "Nilaj"
    ],
    "wof:name":"Nilaj",
    "wof:placetype":"locality",
    "wof:population":583
},
  "geometry": {"coordinates":[75.24448,18.437446],"type":"Point"}
}