{
  "type": "Feature",
  "properties": {
    "iso:country":"IN",
    "ks:ks_name":"Gamharia Khurd",
    "ks:ks_pop":0,
    "ks:ks_type":"VILLAGE",
    "name:eng_x_preferred":[
        "Gamharia Khurd"
    ],
    "wof:name":"Gamharia Khurd",
    "wof:placetype":"locality",
    "wof:population":0
},
  "geometry": {"coordinates":[83.52140199999999,24.686682],"type":"Point"}
}