{
  "type": "Feature",
  "properties": {
    "iso:country":"IN",
    "ks:ks_name":"Deogaon",
    "ks:ks_pop":23,
    "ks:ks_type":"HABITATION",
    "name:eng_x_preferred":[
        "Deogaon"
    ],
    "wof:name":"Deogaon",
    "wof:placetype":"locality",
    "wof:population":23
},
  "geometry": {"coordinates":[78.180182,21.136289],"type":"Point"}
}