{
  "type": "Feature",
  "properties": {
    "iso:country":"IN",
    "ks:ks_name":"Pherupur Kathiya",
    "ks:ks_pop":83,
    "ks:ks_type":"VILLAGE",
    "ks:ks_uagg_main":0,
    "name:eng_x_preferred":[
        "Pherupur Kathiya"
    ],
    "wof:name":"Pherupur Kathiya",
    "wof:placetype":"neighbourhood",
    "wof:population":83
},
  "geometry": {"coordinates":[78.116607,29.861349],"type":"Point"}
}