{
  "type": "Feature",
  "properties": {
    "iso:country":"IN",
    "ks:ks_name":"Adarsh Kekad",
    "ks:ks_pop":1013,
    "ks:ks_type":"HABITATION",
    "name:eng_x_preferred":[
        "Adarsh Kekad"
    ],
    "wof:name":"Adarsh Kekad",
    "wof:placetype":"locality",
    "wof:population":1013
},
  "geometry": {"coordinates":[71.327764,25.094022],"type":"Point"}
}