{
  "type": "Feature",
  "properties": {
    "gn:admin1_code":"35.0",
    "gn:admin2_code":"453.0",
    "gn:asciiname":"Gutli",
    "gn:country_code":"IN",
    "gn:dem":706,
    "gn:feature_class":"P",
    "gn:feature_code":"PPL",
    "gn:name":"Gutli",
    "gn:population":0,
    "gn:timezone":"Asia/Kolkata",
    "iso:country":"IN",
    "wof:name":"Gutli",
    "wof:placetype":"locality"
},
  "geometry": {"coordinates":[80.67468000000002,23.12461],"type":"Point"}
}