{
  "type": "Feature",
  "properties": {
    "gn:admin1_code":"11.0",
    "gn:admin2_code":"33.0",
    "gn:asciiname":"Balog",
    "gn:country_code":"IN",
    "gn:dem":1429,
    "gn:feature_class":"P",
    "gn:feature_code":"PPL",
    "gn:name":"Balog",
    "gn:population":0,
    "gn:timezone":"Asia/Kolkata",
    "iso:country":"IN",
    "name:hun_x_preferred":[
        "Balog"
    ],
    "wof:name":"Balog",
    "wof:placetype":"locality"
},
  "geometry": {"coordinates":[77.25569,30.97197],"type":"Point"}
}