{
  "type": "Feature",
  "properties": {
    "iso:country":"IN",
    "ks:ks_name":"Siraje",
    "ks:ks_pop":36,
    "ks:ks_type":"HABITATION",
    "name:eng_x_preferred":[
        "Siraje"
    ],
    "wof:name":"Siraje",
    "wof:placetype":"locality",
    "wof:population":36
},
  "geometry": {"coordinates":[75.34611599999999,12.557453],"type":"Point"}
}