{
  "type": "Feature",
  "properties": {
    "gn:admin1_code":"2.0",
    "gn:admin2_code":"551.0",
    "gn:asciiname":"Budidiguntapalle",
    "gn:country_code":"IN",
    "gn:dem":386,
    "gn:feature_class":"P",
    "gn:feature_code":"PPL",
    "gn:name":"B\u016bdidiguntapalle",
    "gn:population":0,
    "gn:timezone":"Asia/Kolkata",
    "iso:country":"IN",
    "wof:name":"Budidiguntapalle",
    "wof:placetype":"neighbourhood"
},
  "geometry": {"coordinates":[78.67574999999999,14.1718],"type":"Point"}
}