{
  "type": "Feature",
  "properties": {
    "iso:country":"IN",
    "ks:ks_name":"Sharkaj Nahar Baliwala",
    "ks:ks_pop":44,
    "ks:ks_type":"VILLAGE",
    "name:eng_x_preferred":[
        "Sharkaj Nahar Baliwala"
    ],
    "wof:name":"Sharkaj Nahar Baliwala",
    "wof:placetype":"locality",
    "wof:population":44
},
  "geometry": {"coordinates":[73.946789,30.095548],"type":"Point"}
}