{
  "type": "Feature",
  "properties": {
    "gn:admin1_code":"36",
    "gn:admin2_code":"159.0",
    "gn:asciiname":"Rupnagar",
    "gn:country_code":"IN",
    "gn:dem":153,
    "gn:feature_class":"P",
    "gn:feature_code":"PPL",
    "gn:name":"R\u016bpnagar",
    "gn:population":0,
    "gn:timezone":"Asia/Kolkata",
    "iso:country":"IN",
    "name:ben_x_preferred":[
        "\u09b0\u09c2\u09aa\u09a8\u0997\u09b0"
    ],
    "name:bpy_x_preferred":[
        "\u09b0\u09c2\u09aa\u09a8\u0997\u09b0"
    ],
    "name:cat_x_preferred":[
        "Rupnagar"
    ],
    "name:ceb_x_preferred":[
        "Rupnagar"
    ],
    "name:deu_x_preferred":[
        "Rupnagar"
    ],
    "name:fra_x_preferred":[
        "Rupnagar"
    ],
    "name:guj_x_preferred":[
        "\u0ab0\u0ac1\u0aaa\u0aa8\u0a97\u0ab0"
    ],
    "name:hin_x_preferred":[
        "\u0930\u0942\u092a\u0928\u0917\u0930"
    ],
    "name:ita_x_preferred":[
        "Rupnagar"
    ],
    "name:mar_x_preferred":[
        "\u0930\u094b\u092a\u0921"
    ],
    "name:mlg_x_preferred":[
        "Rupnagar"
    ],
    "name:msa_x_preferred":[
        "Rupnagar"
    ],
    "name:new_x_preferred":[
        "\u0930\u0941\u092a\u0928\u0917\u0930"
    ],
    "name:nld_x_preferred":[
        "Rupnagar"
    ],
    "name:ori_x_preferred":[
        "\u0b30\u0b42\u0b2a\u0b28\u0b17\u0b30"
    ],
    "name:rus_x_preferred":[
        "\u0420\u0443\u043f\u0430\u0440"
    ],
    "name:san_x_preferred":[
        "\u0930\u0942\u092a\u0928\u0917\u0930\u092e\u094d"
    ],
    "name:spa_x_preferred":[
        "Rupnagar"
    ],
    "name:swe_x_preferred":[
        "Rupnagar"
    ],
    "name:tam_x_preferred":[
        "\u0bb0\u0bc2\u0baa\u0bcd\u0ba8\u0b95\u0bb0\u0bcd"
    ],
    "name:urd_x_preferred":[
        "\u0631\u0648\u067e\u0646\u06af\u0631"
    ],
    "name:vie_x_preferred":[
        "Rupnagar"
    ],
    "name:zho_x_preferred":[
        "\u9c81\u666e\u7eb3\u52a0\u5c14"
    ],
    "wof:name":"Rupnagar",
    "wof:placetype":"locality"
},
  "geometry": {"coordinates":[79.29576999999998,27.2873],"type":"Point"}
}