{
  "type": "Feature",
  "properties": {
    "iso:country":"IN",
    "ks:ks_name":"Kathotan Purwa",
    "ks:ks_pop":130,
    "ks:ks_type":"HABITATION",
    "ks:ks_uagg_main":0,
    "name:eng_x_preferred":[
        "Kathotan Purwa"
    ],
    "wof:name":"Kathotan Purwa",
    "wof:placetype":"neighbourhood",
    "wof:population":130
},
  "geometry": {"coordinates":[81.49180200000001,27.244093],"type":"Point"}
}