{
  "type": "Feature",
  "properties": {
    "iso:country":"IN",
    "ks:ks_name":"Pipara E. Tola",
    "ks:ks_pop":420,
    "ks:ks_type":"HABITATION",
    "name:eng_x_preferred":[
        "Pipara E. Tola"
    ],
    "wof:name":"Pipara E. Tola",
    "wof:placetype":"locality",
    "wof:population":420
},
  "geometry": {"coordinates":[85.26727099999999,24.801664],"type":"Point"}
}