{
  "type": "Feature",
  "properties": {
    "iso:country":"IN",
    "ks:ks_name":"Villiyar Colony",
    "ks:ks_pop":680,
    "ks:ks_type":"HABITATION",
    "name:eng_x_preferred":[
        "Villiyar Colony"
    ],
    "wof:name":"Villiyar Colony",
    "wof:placetype":"locality",
    "wof:population":680
},
  "geometry": {"coordinates":[79.92770899999999,13.348706],"type":"Point"}
}