{
  "type": "Feature",
  "properties": {
    "iso:country":"IN",
    "ks:ks_name":"Kokkathodu",
    "ks:ks_pop":1346,
    "ks:ks_type":"HABITATION",
    "name:eng_x_preferred":[
        "Kokkathodu"
    ],
    "wof:name":"Kokkathodu",
    "wof:placetype":"locality",
    "wof:population":1346
},
  "geometry": {"coordinates":[76.977462,9.199697],"type":"Point"}
}