{
  "type": "Feature",
  "properties": {
    "iso:country":"IN",
    "ks:ks_alt_nam":"RAGHURAJ SINGH PUR",
    "ks:ks_name":"Raghuraj Singh Pur",
    "ks:ks_pop":222,
    "ks:ks_type":"HABITATION",
    "ks:ks_uagg_main":0,
    "name:eng_x_preferred":[
        "Raghuraj Singh Pur"
    ],
    "wof:name":"Raghuraj Singh Pur",
    "wof:placetype":"neighbourhood",
    "wof:population":222
},
  "geometry": {"coordinates":[81.48108000000001,27.25075],"type":"Point"}
}