{
  "type": "Feature",
  "properties": {
    "iso:country":"IN",
    "ks:ks_name":"Nilakanthapur",
    "ks:ks_pop":1585,
    "ks:ks_type":"VILLAGE",
    "ks:ks_uagg_main":0,
    "name:eng_x_preferred":[
        "Nilakanthapur"
    ],
    "wof:name":"Nilakanthapur",
    "wof:placetype":"neighbourhood",
    "wof:population":1585
},
  "geometry": {"coordinates":[86.196968,20.757557],"type":"Point"}
}