{
  "type": "Feature",
  "properties": {
    "iso:country":"IN",
    "ks:ks_name":"Raja Bala",
    "ks:ks_pop":772,
    "ks:ks_type":"VILLAGE",
    "ks:ks_uagg_main":0,
    "name:eng_x_preferred":[
        "Raja Bala"
    ],
    "wof:name":"Raja Bala",
    "wof:placetype":"neighbourhood",
    "wof:population":772
},
  "geometry": {"coordinates":[89.98481700000001,25.844096],"type":"Point"}
}