{
  "type": "Feature",
  "properties": {
    "iso:country":"IN",
    "ks:ks_name":"Mugerodi",
    "ks:ks_pop":289,
    "ks:ks_type":"HABITATION",
    "name:eng_x_preferred":[
        "Mugerodi"
    ],
    "wof:name":"Mugerodi",
    "wof:placetype":"locality",
    "wof:population":289
},
  "geometry": {"coordinates":[75.181856,12.931515],"type":"Point"}
}