{
  "type": "Feature",
  "properties": {
    "gn:admin1_code":"21.0",
    "gn:admin2_code":"398.0",
    "gn:asciiname":"Leja",
    "gn:country_code":"IN",
    "gn:dem":788,
    "gn:feature_class":"P",
    "gn:feature_code":"PPL",
    "gn:name":"Leja",
    "gn:population":0,
    "gn:timezone":"Asia/Kolkata",
    "iso:country":"IN",
    "wof:name":"Leja",
    "wof:placetype":"neighbourhood"
},
  "geometry": {"coordinates":[82.52912000000001,18.71107],"type":"Point"}
}