{
  "type": "Feature",
  "properties": {
    "iso:country":"IN",
    "ks:ks_name":"Dori",
    "ks:ks_pop":137,
    "ks:ks_type":"VILLAGE",
    "name:eng_x_preferred":[
        "Dori"
    ],
    "wof:name":"Dori",
    "wof:placetype":"locality",
    "wof:population":137
},
  "geometry": {"coordinates":[84.529781,23.918539],"type":"Point"}
}