{
  "type": "Feature",
  "properties": {
    "iso:country":"IN",
    "ks:ks_alt_nam":"gangapur",
    "ks:ks_name":"Gangapur",
    "ks:ks_pop":1354,
    "ks:ks_type":"HABITATION",
    "ks:ks_uagg_main":0,
    "name:eng_x_preferred":[
        "Gangapur"
    ],
    "name:hin_x_preferred":[
        "\u0917\u0902\u0917\u093e\u092a\u0941\u0930"
    ],
    "wof:name":"Gangapur",
    "wof:placetype":"neighbourhood",
    "wof:population":1354
},
  "geometry": {"coordinates":[81.767594,27.871191],"type":"Point"}
}