{
  "type": "Feature",
  "properties": {
    "iso:country":"IN",
    "ks:ks_name":"Kaguvalasa",
    "ks:ks_pop":39,
    "ks:ks_type":"VILLAGE",
    "name:eng_x_preferred":[
        "Kaguvalasa"
    ],
    "wof:name":"Kaguvalasa",
    "wof:placetype":"locality",
    "wof:population":39
},
  "geometry": {"coordinates":[83.01805400000001,18.337092],"type":"Point"}
}