{
  "type": "Feature",
  "properties": {
    "gn:admin1_code":"36.0",
    "gn:admin2_code":"142.0",
    "gn:asciiname":"Azadnagar",
    "gn:country_code":"IN",
    "gn:dem":211,
    "gn:feature_class":"P",
    "gn:feature_code":"PPL",
    "gn:name":"\u0100z\u0101dnagar",
    "gn:population":0,
    "gn:timezone":"Asia/Kolkata",
    "iso:country":"IN",
    "wof:name":"Azadnagar",
    "wof:placetype":"locality"
},
  "geometry": {"coordinates":[77.76241,28.55223],"type":"Point"}
}