{
  "type": "Feature",
  "properties": {
    "gn:admin1_code":"25.0",
    "gn:admin2_code":"610.0",
    "gn:asciiname":"Unangattuvalsu",
    "gn:country_code":"IN",
    "gn:dem":224,
    "gn:feature_class":"P",
    "gn:feature_code":"PPL",
    "gn:name":"\u016anang\u0101ttuvalsu",
    "gn:population":0,
    "gn:timezone":"Asia/Kolkata",
    "iso:country":"IN",
    "wof:name":"Unangattuvalsu",
    "wof:placetype":"locality"
},
  "geometry": {"coordinates":[77.61631,11.38499],"type":"Point"}
}