{
  "type": "Feature",
  "properties": {
    "iso:country":"IN",
    "name:ara_x_preferred":[
        "\u0644\u064a\u0646\u063a\u0627\u0631\u062c \u0628\u0648\u0631\u0627"
    ],
    "name:ben_bn_x_preferred":[
        "\u09b2\u09bf\u0999\u09cd\u0997\u09b0\u09be\u099c\u09aa\u09c1\u09b0\u09be"
    ],
    "name:ben_in_x_preferred":[
        "\u09b2\u09bf\u0999\u09cd\u0997\u09b0\u09be\u099c\u09aa\u09c1\u09b0\u09be"
    ],
    "name:guj_x_preferred":[
        "\u0ab2\u0abf\u0a82\u0a97\u0ab0\u0abe\u0a9c\u0aaa\u0ac1\u0ab0\u0abe"
    ],
    "name:hin_x_preferred":[
        "\u0932\u093f\u0902\u0917\u0930\u093e\u091c\u092a\u0941\u0930\u093e"
    ],
    "name:kan_x_preferred":[
        "\u0cb2\u0cbf\u0c82\u0c97\u0cb0\u0cbe\u0c9c\u0caa\u0cc1\u0cb0"
    ],
    "name:mal_x_preferred":[
        "\u0d32\u0d3f\u0d02\u0d17\u0d30\u0d3e\u0d1c\u0d2a\u0d41\u0d30"
    ],
    "name:mar_x_preferred":[
        "\u0932\u093f\u0902\u0917\u0930\u093e\u091c\u092a\u0941\u0930\u093e"
    ],
    "name:pan_x_preferred":[
        "\u0a32\u0a3f\u0a70\u0a17\u0a3e\u0a30\u0a3e\u0a1c\u0a3e\u0a2a\u0a41\u0a30\u0a3e"
    ],
    "name:tam_x_preferred":[
        "\u0bb2\u0bbf\u0b99\u0bcd\u0b95\u0bb0\u0bbe\u0b9c\u0baa\u0bc1\u0bb0\u0bae\u0bcd"
    ],
    "name:tel_x_preferred":[
        "\u0c32\u0c3f\u0c02\u0c17\u0c30\u0c3e\u0c1c\u0c2a\u0c41\u0c30\u0c3e"
    ],
    "name:urd_x_preferred":[
        "\u0644\u0646\u06af\u0627 \u0631\u0627\u062c\u0627 \u067e\u0648\u0631\u06c1"
    ],
    "qs:name":"Lingarajapura",
    "qs:name_adm0":"India",
    "qs:name_adm1":"Karnataka",
    "qs:photos":184,
    "qs:photos_1k":37,
    "qs:photos_9k":1,
    "qs:photos_9r":4,
    "qs:photos_all":184,
    "qs:photos_sr":4,
    "qs:placetype":"Suburb",
    "qs:pop_sr":"0",
    "wof:name":"Lingarajapura",
    "wof:placetype":"neighbourhood"
},
  "geometry": {"coordinates":[77.604675,12.971187],"type":"Point"}
}