{
  "type": "Feature",
  "properties": {
    "iso:country":"IN",
    "qs:name":"Lingarajapura",
    "qs:name_adm0":"India",
    "qs:name_adm1":"Karnataka",
    "qs:photos":184,
    "qs:photos_1k":37,
    "qs:photos_9k":1,
    "qs:photos_9r":4,
    "qs:photos_all":184,
    "qs:photos_sr":4,
    "qs:placetype":"Suburb",
    "qs:pop_sr":"0",
    "wof:name":"Lingarajapura",
    "wof:placetype":"neighbourhood"
},
  "geometry": {"coordinates":[77.604675,12.971187],"type":"Point"}
}