{
  "type": "Feature",
  "properties": {
    "iso:country":"IN",
    "ks:ks_name":"Bongali Gaon",
    "ks:ks_pop":1425,
    "ks:ks_type":"VILLAGE",
    "ks:ks_uagg_main":0,
    "name:eng_x_preferred":[
        "Bongali Gaon"
    ],
    "wof:name":"Bongali Gaon",
    "wof:placetype":"neighbourhood",
    "wof:population":1425
},
  "geometry": {"coordinates":[93.551312,26.632554],"type":"Point"}
}