{
  "type": "Feature",
  "properties": {
    "iso:country":"IN",
    "ks:ks_name":"Gaonthanwadi",
    "ks:ks_pop":189,
    "ks:ks_type":"HABITATION",
    "name:eng_x_preferred":[
        "Gaonthanwadi"
    ],
    "wof:name":"Gaonthanwadi",
    "wof:placetype":"locality",
    "wof:population":189
},
  "geometry": {"coordinates":[73.709459,16.368459],"type":"Point"}
}