{
  "type": "Feature",
  "properties": {
    "iso:country":"IN",
    "ks:ks_name":"Godabhanga",
    "ks:ks_pop":302,
    "ks:ks_type":"VILLAGE",
    "name:eng_x_preferred":[
        "Godabhanga"
    ],
    "wof:name":"Godabhanga",
    "wof:placetype":"locality",
    "wof:population":302
},
  "geometry": {"coordinates":[85.017681,21.530106],"type":"Point"}
}