{
  "type": "Feature",
  "properties": {
    "iso:country":"IN",
    "ks:ks_name":"Korangkel",
    "ks:ks_pop":324,
    "ks:ks_type":"VILLAGE",
    "name:eng_x_preferred":[
        "Korangkel"
    ],
    "wof:name":"Korangkel",
    "wof:placetype":"locality",
    "wof:population":324
},
  "geometry": {"coordinates":[85.30243900000001,22.8528],"type":"Point"}
}