{
  "type": "Feature",
  "properties": {
    "iso:country":"IN",
    "ks:ks_name":"Sawantwada",
    "ks:ks_pop":420,
    "ks:ks_type":"HABITATION",
    "name:eng_x_preferred":[
        "Sawantwada"
    ],
    "wof:name":"Sawantwada",
    "wof:placetype":"locality",
    "wof:population":420
},
  "geometry": {"coordinates":[73.782881,16.072037],"type":"Point"}
}