{
  "type": "Feature",
  "properties": {
    "iso:country":"IN",
    "ks:ks_name":"Kothamuramalla",
    "ks:ks_pop":1093,
    "ks:ks_type":"HABITATION",
    "name:eng_x_preferred":[
        "Kothamuramalla"
    ],
    "wof:name":"Kothamuramalla",
    "wof:placetype":"locality",
    "wof:population":1093
},
  "geometry": {"coordinates":[82.173261,16.665881],"type":"Point"}
}