{
  "type": "Feature",
  "properties": {
    "iso:country":"IN",
    "ks:ks_name":"Jharbeda",
    "ks:ks_pop":1024,
    "ks:ks_type":"VILLAGE",
    "name:eng_x_preferred":[
        "Jharbeda"
    ],
    "wof:name":"Jharbeda",
    "wof:placetype":"locality",
    "wof:population":1024
},
  "geometry": {"coordinates":[85.054694,22.244564],"type":"Point"}
}