{
  "type": "Feature",
  "properties": {
    "iso:country":"IN",
    "ks:ks_name":"Melkuppusur",
    "ks:ks_pop":102,
    "ks:ks_type":"HABITATION",
    "name:eng_x_preferred":[
        "Melkuppusur"
    ],
    "wof:name":"Melkuppusur",
    "wof:placetype":"locality",
    "wof:population":102
},
  "geometry": {"coordinates":[78.954836,12.72351],"type":"Point"}
}