{
  "type": "Feature",
  "properties": {
    "iso:country":"IN",
    "ks:ks_name":"Basautha Mohatua Tola",
    "ks:ks_pop":312,
    "ks:ks_type":"HABITATION",
    "ks:ks_uagg_main":0,
    "name:eng_x_preferred":[
        "Basautha Mohatua Tola"
    ],
    "wof:name":"Basautha Mohatua Tola",
    "wof:placetype":"neighbourhood",
    "wof:population":312
},
  "geometry": {"coordinates":[87.04541999999999,25.530036],"type":"Point"}
}