{
  "type": "Feature",
  "properties": {
    "iso:country":"IN",
    "ks:ks_alt_nam":"Patil pada",
    "ks:ks_name":"Patil Pada",
    "ks:ks_pop":96,
    "ks:ks_type":"HABITATION",
    "ks:ks_uagg_main":0,
    "name:eng_x_preferred":[
        "Patil Pada"
    ],
    "wof:name":"Patil Pada",
    "wof:placetype":"neighbourhood",
    "wof:population":96
},
  "geometry": {"coordinates":[72.99540399999999,19.812716],"type":"Point"}
}