{
  "type": "Feature",
  "properties": {
    "gn:admin1_code":"2.0",
    "gn:admin2_code":"547.0",
    "gn:asciiname":"Gudapadu",
    "gn:country_code":"IN",
    "gn:dem":117,
    "gn:feature_class":"P",
    "gn:feature_code":"PPL",
    "gn:name":"G\u016bdap\u0101du",
    "gn:population":0,
    "gn:timezone":"Asia/Kolkata",
    "iso:country":"IN",
    "name:tat_x_preferred":[
        "\u0413\u0443\u0434\u0430\u043f\u0430\u0434\u0443"
    ],
    "name:tel_x_preferred":[
        "\u0c17\u0c42\u0c21\u0c2a\u0c3e\u0c21\u0c41"
    ],
    "wof:name":"Gudapadu",
    "wof:placetype":"locality"
},
  "geometry": {"coordinates":[80.84458000000002,16.82623],"type":"Point"}
}