{
  "type": "Feature",
  "properties": {
    "iso:country":"IN",
    "ks:ks_alt_nam":"SALAGARVASTI",
    "ks:ks_name":"Salagarvasti",
    "ks:ks_pop":75,
    "ks:ks_type":"HABITATION",
    "ks:ks_uagg_main":0,
    "name:eng_x_preferred":[
        "Salagarvasti"
    ],
    "wof:name":"Salagarvasti",
    "wof:placetype":"neighbourhood",
    "wof:population":75
},
  "geometry": {"coordinates":[74.289075,17.118733],"type":"Point"}
}