{
  "type": "Feature",
  "properties": {
    "gn:country":"IN",
    "gn:fcode":"PPL",
    "gn:pop":17270,
    "iso:country":"IN",
    "name:ben_x_preferred":[
        "\u09b8\u09be\u09b0\u09cd\u09a6\u09c1\u09b2\u0997\u09a1\u09bc"
    ],
    "name:bpy_x_preferred":[
        "\u09b8\u09be\u09b0\u09cd\u09a6\u09c1\u09b2\u0997\u09a1\u09bc"
    ],
    "name:bul_x_preferred":[
        "\u0421\u0430\u0440\u0434\u0443\u043b\u0433\u0430\u0440\u0445"
    ],
    "name:chi_x_preferred":[
        "\u8428\u5c14\u675c\u5c14\u52a0\u5c14"
    ],
    "name:dut_x_preferred":[
        "Sardulgarh"
    ],
    "name:eng_x_preferred":[
        "Sardulgarh"
    ],
    "name:fre_x_preferred":[
        "Sardulgarh"
    ],
    "name:ita_x_preferred":[
        "Sardulgarh"
    ],
    "name:may_x_preferred":[
        "Sardulgarh"
    ],
    "name:nan_x_preferred":[
        "Sardulgarh"
    ],
    "name:por_x_preferred":[
        "Sardulgarh"
    ],
    "name:spa_x_preferred":[
        "Sardulgarh"
    ],
    "name:swe_x_preferred":[
        "Sardulgarh"
    ],
    "name:unk_x_variant":[
        "Sardulgarh"
    ],
    "name:vie_x_preferred":[
        "Sardulgarh"
    ],
    "qs:name":"Sardargarh",
    "qs:name_adm0":"India",
    "qs:name_adm1":"Punjab",
    "qs:photos_9r":0,
    "qs:photos_sr":0,
    "qs:placetype":"Town",
    "qs:pop_sr":"6",
    "wd:wordcount":139,
    "wof:name":"Sardargarh",
    "wof:placetype":"locality",
    "wof:population":17270
},
  "geometry": {"coordinates":[75.23608,29.69224],"type":"Point"}
}