{
  "type": "Feature",
  "properties": {
    "gn:admin1_code":"38.0",
    "gn:admin2_code":"362.0",
    "gn:asciiname":"Gumapahari",
    "gn:country_code":"IN",
    "gn:dem":94,
    "gn:feature_class":"P",
    "gn:feature_code":"PPL",
    "gn:name":"Gum\u0101pah\u0101ri",
    "gn:population":0,
    "gn:timezone":"Asia/Kolkata",
    "iso:country":"IN",
    "ks:ks_alt_nam":"Gum\u0101pah\u0101ri",
    "ks:ks_name":"Gumapahari",
    "ks:ks_pop":540,
    "ks:ks_type":"VILLAGE",
    "name:eng_x_preferred":[
        "Gumapahari"
    ],
    "name:eng_x_variant":[
        "Gum\u0101pah\u0101ri"
    ],
    "wof:name":"Gumapahari",
    "wof:placetype":"locality",
    "wof:population":540
},
  "geometry": {"coordinates":[87.56883500000001,24.506202],"type":"Point"}
}