{
  "type": "Feature",
  "properties": {
    "iso:country":"IN",
    "ks:ks_name":"Jhapad",
    "ks:ks_pop":545,
    "ks:ks_type":"VILLAGE",
    "name:eng_x_preferred":[
        "Jhapad"
    ],
    "wof:name":"Jhapad",
    "wof:placetype":"locality",
    "wof:population":545
},
  "geometry": {"coordinates":[82.839502,23.919682],"type":"Point"}
}