{
  "type": "Feature",
  "properties": {
    "gn:admin1_code":"25.0",
    "gn:admin2_code":"602.0",
    "gn:asciiname":"Amidanallur",
    "gn:country_code":"IN",
    "gn:dem":20,
    "gn:feature_class":"P",
    "gn:feature_code":"PPL",
    "gn:name":"Amid\u0101nall\u016br",
    "gn:population":0,
    "gn:timezone":"Asia/Kolkata",
    "iso:country":"IN",
    "ks:ks_name":"Amindanallur",
    "ks:ks_pop":1058,
    "ks:ks_type":"VILLAGE",
    "name:eng_x_preferred":[
        "Amindanallur"
    ],
    "name:eng_x_variant":[
        "Amidanallur"
    ],
    "wof:name":"Amindanallur",
    "wof:placetype":"locality",
    "wof:population":1058
},
  "geometry": {"coordinates":[80.12067500000001,13.297727],"type":"Point"}
}