{
  "type": "Feature",
  "properties": {
    "gn:admin1_code":"39.0",
    "gn:admin2_code":"65.0",
    "gn:asciiname":"Amoli",
    "gn:country_code":"IN",
    "gn:dem":1427,
    "gn:feature_class":"P",
    "gn:feature_code":"PPL",
    "gn:name":"Amoli",
    "gn:population":0,
    "gn:timezone":"Asia/Kolkata",
    "iso:country":"IN",
    "ks:ks_name":"Amoli",
    "ks:ks_type":"VILLAGE",
    "name:eng_x_preferred":[
        "Amoli"
    ],
    "wof:name":"Amoli",
    "wof:placetype":"locality"
},
  "geometry": {"coordinates":[79.932483,29.437008],"type":"Point"}
}