{
  "type": "Feature",
  "properties": {
    "gn:country":"IN",
    "gn:fcode":"PPL",
    "gn:pop":32549,
    "iso:country":"IN",
    "name:ben_x_preferred":[
        "\u099a\u09be\u09a8\u09cd\u09a6\u09c7\u09b0\u09c0"
    ],
    "name:bpy_x_preferred":[
        "\u099a\u09be\u09a8\u09cd\u09a6\u09c7\u09b0\u09c0"
    ],
    "name:cat_x_preferred":[
        "Chanderi"
    ],
    "name:chi_x_preferred":[
        "\u94b1\u5fb7\u91cc"
    ],
    "name:dut_x_preferred":[
        "Chanderi"
    ],
    "name:eng_x_preferred":[
        "Chanderi"
    ],
    "name:fre_x_preferred":[
        "Chanderi"
    ],
    "name:ger_x_preferred":[
        "Chanderi"
    ],
    "name:guj_x_preferred":[
        "\u0a9a\u0a82\u0aa6\u0ac7\u0ab0\u0ac0"
    ],
    "name:hin_x_preferred":[
        "\u091a\u0902\u0926\u0947\u0930\u0940"
    ],
    "name:ita_x_preferred":[
        "Chanderi"
    ],
    "name:jpn_x_preferred":[
        "\u30c1\u30e3\u30f3\u30c7\u30fc\u30ea\u30fc"
    ],
    "name:kan_x_preferred":[
        "\u0c9a\u0cbe\u0c82\u0ca6\u0cc7\u0cb0\u0cbf"
    ],
    "name:kor_x_preferred":[
        "\ucc2c\ub370\ub9ac"
    ],
    "name:may_x_preferred":[
        "Chanderi"
    ],
    "name:mlg_x_preferred":[
        "Chanderi"
    ],
    "name:new_x_preferred":[
        "\u091a\u0928\u094d\u0926\u0947\u0930\u0940"
    ],
    "name:pan_x_preferred":[
        "\u0a1a\u0a70\u0a26\u0a47\u0a30\u0a40"
    ],
    "name:por_x_preferred":[
        "Chanderi"
    ],
    "name:rus_x_preferred":[
        "\u0427\u0430\u043d\u0434\u0435\u0440\u0438"
    ],
    "name:san_x_preferred":[
        "\u091a\u0928\u094d\u0926\u0947\u0930\u0940"
    ],
    "name:spa_x_preferred":[
        "Chanderi"
    ],
    "name:swe_x_preferred":[
        "Chanderi"
    ],
    "name:tam_x_preferred":[
        "\u0b9a\u0ba8\u0bcd\u0ba4\u0bc7\u0bb0\u0bbf"
    ],
    "name:tel_x_preferred":[
        "\u0c1a\u0c02\u0c26\u0c47\u0c30\u0c3f"
    ],
    "name:urd_x_preferred":[
        "\u0686\u0627\u0646\u062f\u06cc\u0631\u06cc"
    ],
    "name:vie_x_preferred":[
        "Chanderi"
    ],
    "name:zho_x_preferred":[
        "\u94b1\u5fb7\u91cc"
    ],
    "qs:name":"Chanderi",
    "qs:name_adm0":"India",
    "qs:name_adm1":"Madhya Pradesh",
    "qs:photos":247,
    "qs:photos_1k":50,
    "qs:photos_9k":1,
    "qs:photos_9r":4,
    "qs:photos_all":247,
    "qs:photos_sr":4,
    "qs:placetype":"Town",
    "qs:pop_sr":"7",
    "wd:wordcount":1255,
    "wof:name":"Chanderi",
    "wof:placetype":"locality",
    "wof:population":32549
},
  "geometry": {"coordinates":[78.13760000000001,24.71514],"type":"Point"}
}