{
  "type": "Feature",
  "properties": {
    "iso:country":"IN",
    "ks:ks_alt_nam":"kannadi juncton",
    "ks:ks_name":"Kannadi Juncton",
    "ks:ks_pop":1598,
    "ks:ks_type":"HABITATION",
    "name:eng_x_preferred":[
        "Kannadi Juncton"
    ],
    "wof:name":"Kannadi Juncton",
    "wof:placetype":"locality",
    "wof:population":1598
},
  "geometry": {"coordinates":[76.355026,9.60697],"type":"Point"}
}