{
  "type": "Feature",
  "properties": {
    "iso:country":"IN",
    "ks:ks_name":"Madomasi",
    "ks:ks_pop":102,
    "ks:ks_type":"VILLAGE",
    "name:eng_x_preferred":[
        "Madomasi"
    ],
    "wof:name":"Madomasi",
    "wof:placetype":"locality",
    "wof:population":102
},
  "geometry": {"coordinates":[87.42828299999999,24.905225],"type":"Point"}
}