{
  "type": "Feature",
  "properties": {
    "gn:admin1_code":"19.0",
    "gn:admin2_code":"562.0",
    "gn:asciiname":"Sotakanhal",
    "gn:country_code":"IN",
    "gn:dem":569,
    "gn:feature_class":"P",
    "gn:feature_code":"PPL",
    "gn:name":"Sotakanh\u0101l",
    "gn:population":0,
    "gn:timezone":"Asia/Kolkata",
    "iso:country":"IN",
    "wof:name":"Sotakanhal",
    "wof:placetype":"locality"
},
  "geometry": {"coordinates":[75.40399000000002,15.63051],"type":"Point"}
}