{
  "type": "Feature",
  "properties": {
    "iso:country":"IN",
    "ks:ks_alt_nam":"Gavti pada",
    "ks:ks_name":"Gavti Pada",
    "ks:ks_pop":121,
    "ks:ks_type":"HABITATION",
    "name:eng_x_preferred":[
        "Gavti Pada"
    ],
    "wof:name":"Gavti Pada",
    "wof:placetype":"locality",
    "wof:population":121
},
  "geometry": {"coordinates":[72.993398,19.790732],"type":"Point"}
}