{
  "type": "Feature",
  "properties": {
    "iso:country":"IN",
    "ks:ks_name":"Malali",
    "ks:ks_pop":98,
    "ks:ks_type":"HABITATION",
    "name:eng_x_preferred":[
        "Malali"
    ],
    "wof:name":"Malali",
    "wof:placetype":"locality",
    "wof:population":98
},
  "geometry": {"coordinates":[75.04902,13.885595],"type":"Point"}
}