{
  "type": "Feature",
  "properties": {
    "iso:country":"IN",
    "ks:ks_name":"Ramapuram",
    "ks:ks_pop":130,
    "ks:ks_type":"HABITATION",
    "name:eng_x_preferred":[
        "Ramapuram"
    ],
    "wof:name":"Ramapuram",
    "wof:placetype":"locality",
    "wof:population":130
},
  "geometry": {"coordinates":[79.388041,16.813911],"type":"Point"}
}