{
  "type": "Feature",
  "properties": {
    "iso:country":"IN",
    "ks:ks_name":"Bedi",
    "ks:ks_type":"VILLAGE",
    "ks:ks_uagg_main":0,
    "name:eng_x_preferred":[
        "Bedi"
    ],
    "wof:name":"Bedi",
    "wof:placetype":"neighbourhood"
},
  "geometry": {"coordinates":[70.043629,22.50143],"type":"Point"}
}