{
  "type": "Feature",
  "properties": {
    "iso:country":"IN",
    "ks:ks_alt_nam":"PURE RAMDEEN",
    "ks:ks_name":"Pure Ramdeen",
    "ks:ks_pop":48,
    "ks:ks_type":"HABITATION",
    "ks:ks_uagg_main":0,
    "name:eng_x_preferred":[
        "Pure Ramdeen"
    ],
    "wof:name":"Pure Ramdeen",
    "wof:placetype":"neighbourhood",
    "wof:population":48
},
  "geometry": {"coordinates":[81.909502,26.479854],"type":"Point"}
}