{
  "type": "Feature",
  "properties": {
    "iso:country":"IN",
    "ks:ks_name":"Kutipara",
    "ks:ks_pop":727,
    "ks:ks_type":"HABITATION",
    "name:eng_x_preferred":[
        "Kutipara"
    ],
    "wof:name":"Kutipara",
    "wof:placetype":"locality",
    "wof:population":727
},
  "geometry": {"coordinates":[89.471104,26.365382],"type":"Point"}
}