{
  "type": "Feature",
  "properties": {
    "iso:country":"IN",
    "ks:ks_name":"Homasita",
    "ks:ks_pop":4,
    "ks:ks_type":"VILLAGE",
    "name:eng_x_preferred":[
        "Homasita"
    ],
    "wof:name":"Homasita",
    "wof:placetype":"locality",
    "wof:population":4
},
  "geometry": {"coordinates":[85.681821,23.501084],"type":"Point"}
}