{
  "type": "Feature",
  "properties": {
    "gn:admin1_code":"23.0",
    "gn:admin2_code":"44.0",
    "gn:asciiname":"Patti Karam",
    "gn:country_code":"IN",
    "gn:dem":192,
    "gn:feature_class":"P",
    "gn:feature_code":"PPL",
    "gn:name":"Patti K\u0101ram",
    "gn:population":0,
    "gn:timezone":"Asia/Kolkata",
    "iso:country":"IN",
    "name:und_x_variant":[
        "Patti K\u0101ram",
        "Dabw\u0101la Khurd"
    ],
    "wof:name":"Patti Karam",
    "wof:placetype":"locality"
},
  "geometry": {"coordinates":[74.31085,30.24807],"type":"Point"}
}