{
  "type": "Feature",
  "properties": {
    "gn:admin1_code":"12.0",
    "gn:admin2_code":"13.0",
    "gn:asciiname":"Bandapoh",
    "gn:country_code":"IN",
    "gn:dem":1735,
    "gn:feature_class":"P",
    "gn:feature_code":"PPL",
    "gn:name":"Bandapoh",
    "gn:population":0,
    "gn:timezone":"Asia/Kolkata",
    "iso:country":"IN",
    "wof:name":"Bandapoh",
    "wof:placetype":"locality"
},
  "geometry": {"coordinates":[74.96347,33.7527],"type":"Point"}
}