{
  "type": "Feature",
  "properties": {
    "gn:admin1_code":"21",
    "gn:admin2_code":"395.0",
    "gn:asciiname":"Partapur",
    "gn:country_code":"IN",
    "gn:dem":424,
    "gn:feature_class":"P",
    "gn:feature_code":"PPL",
    "gn:name":"Partapur",
    "gn:population":0,
    "gn:timezone":"Asia/Kolkata",
    "iso:country":"IN",
    "wof:name":"Partapur",
    "wof:placetype":"locality"
},
  "geometry": {"coordinates":[83.40205,19.7675],"type":"Point"}
}