{
  "type": "Feature",
  "properties": {
    "iso:country":"IN",
    "ks:ks_name":"Vaddigudem",
    "ks:ks_pop":543,
    "ks:ks_type":"HABITATION",
    "name:eng_x_preferred":[
        "Vaddigudem"
    ],
    "wof:name":"Vaddigudem",
    "wof:placetype":"locality",
    "wof:population":543
},
  "geometry": {"coordinates":[82.10791399999999,16.657702],"type":"Point"}
}