{
  "type": "Feature",
  "properties": {
    "iso:country":"IN",
    "ks:ks_name":"Jhiktia",
    "ks:ks_pop":1165,
    "ks:ks_type":"VILLAGE",
    "ks:ks_uagg_main":0,
    "name:eng_x_preferred":[
        "Jhiktia"
    ],
    "wof:name":"Jhiktia",
    "wof:placetype":"neighbourhood",
    "wof:population":1165
},
  "geometry": {"coordinates":[86.890096,25.138826],"type":"Point"}
}