{
  "type": "Feature",
  "properties": {
    "iso:country":"IN",
    "ks:ks_name":"Balipadar",
    "ks:ks_pop":62,
    "ks:ks_type":"HABITATION",
    "name:eng_x_preferred":[
        "Balipadar"
    ],
    "wof:name":"Balipadar",
    "wof:placetype":"locality",
    "wof:population":62
},
  "geometry": {"coordinates":[83.923604,19.25553],"type":"Point"}
}