{
  "type": "Feature",
  "properties": {
    "gn:admin1_code":"24",
    "gn:admin2_code":"112.0",
    "gn:asciiname":"Lampolai",
    "gn:country_code":"IN",
    "gn:dem":335,
    "gn:feature_class":"P",
    "gn:feature_code":"PPL",
    "gn:name":"L\u0101mpolai",
    "gn:population":0,
    "gn:timezone":"Asia/Kolkata",
    "iso:country":"IN",
    "name:und_x_variant":[
        "L\u0101mpolai"
    ],
    "wof:name":"Lampolai",
    "wof:placetype":"locality"
},
  "geometry": {"coordinates":[74.18975,26.64154000000001],"type":"Point"}
}