{
  "type": "Feature",
  "properties": {
    "iso:country":"IN",
    "ks:ks_name":"Ubon Gaon",
    "ks:ks_pop":79,
    "ks:ks_type":"VILLAGE",
    "name:eng_x_preferred":[
        "Ubon Gaon"
    ],
    "wof:name":"Ubon Gaon",
    "wof:placetype":"locality",
    "wof:population":79
},
  "geometry": {"coordinates":[95.74792100000001,27.373753],"type":"Point"}
}