{
  "type": "Feature",
  "properties": {
    "iso:country":"IN",
    "ks:ks_name":"Ram Nagar",
    "ks:ks_pop":304,
    "ks:ks_type":"HABITATION",
    "name:eng_x_preferred":[
        "Ram Nagar"
    ],
    "wof:name":"Ram Nagar",
    "wof:placetype":"locality",
    "wof:population":304
},
  "geometry": {"coordinates":[85.923906,25.815024],"type":"Point"}
}