{
  "type": "Feature",
  "properties": {
    "iso:country":"IN",
    "name:eng_x_preferred":[
        "Bhatiyani Chauhta"
    ],
    "name:unk_x_variant":[
        "Bhatiyani Chauhta"
    ],
    "qs:gn_adm0_cc":"IN",
    "qs:gn_local":1253986,
    "qs:gn_nam_loc":"Udaipur, Udaipur, Rajasthan, IN",
    "qs:gn_namadm1":"24",
    "qs:local_max":4409,
    "qs:local_sum":9770,
    "qs:localhoods":18,
    "qs:name":"Bhatiyani Chauhta",
    "qs:name_adm0":"India",
    "qs:name_adm1":"Rajasthan",
    "qs:name_adm2":"Udaipur",
    "qs:name_local":"Udaipur",
    "qs:photo_max":40,
    "qs:photo_sum":49,
    "qs:placetype":"Suburb",
    "qs:quad_count":2,
    "qs:woe_adm0":23424848,
    "qs:woe_adm1":2345757,
    "qs:woe_adm2":12586676,
    "qs:woe_lau":0,
    "qs:woe_local":2295108,
    "qs:woe_ver":"7.10.0",
    "wof:lang":[
        "eng"
    ],
    "wof:name":"Bhatiyani Chauhta",
    "wof:placetype":"neighbourhood"
},
  "geometry": {"coordinates":[73.68621,24.577724],"type":"Point"}
}