{
  "type": "Feature",
  "properties": {
    "iso:country":"IN",
    "name:ara_x_preferred":[
        "\u0628\u0647\u0627\u062a\u064a\u0627\u0646\u064a \u062a\u0634\u0648\u0647\u0627\u062a\u0627"
    ],
    "name:ben_bn_x_preferred":[
        "\u09ad\u09be\u099f\u09bf\u09af\u09bc\u09be\u09a8\u09bf \u099a\u09cc\u09a4\u09be"
    ],
    "name:ben_in_x_preferred":[
        "\u09ad\u09be\u099f\u09bf\u09af\u09bc\u09be\u09a8\u09bf \u099a\u09cc\u09a4\u09be"
    ],
    "name:eng_x_preferred":[
        "Bhatiyani Chauhta"
    ],
    "name:guj_x_preferred":[
        "\u0aad\u0a9f\u0abf\u0aaf\u0abe\u0aa3\u0ac0 \u0a9a\u0acc\u0ab9\u0aa4\u0abe"
    ],
    "name:hin_x_preferred":[
        "\u092d\u091f\u093f\u092f\u093e\u0928\u0940 \u091a\u094c\u0939\u093e\u091f\u093e"
    ],
    "name:kan_x_preferred":[
        "\u0cad\u0ca4\u0cbf\u0caf\u0cbe\u0ca8\u0cbf \u0c9a\u0ccc\u0ca4\u0cbe"
    ],
    "name:mal_x_preferred":[
        "\u0d2d\u0d3e\u0d1f\u0d4d\u0d1f\u0d3f\u0d2f\u0d3e\u0d28\u0d3f \u0d1a\u0d57\u0d24"
    ],
    "name:mar_x_preferred":[
        "\u092d\u091f\u093f\u092f\u093e\u0923\u0940 \u091a\u094c\u0939\u091f\u093e"
    ],
    "name:pan_x_preferred":[
        "\u0a2d\u0a1f\u0a40\u0a06\u0a23\u0a40 \u0a1a\u0a4c\u0a39\u0a1f\u0a3e"
    ],
    "name:tam_x_preferred":[
        "\u0baa\u0b9f\u0bbf\u0baf\u0bbe\u0ba9\u0bbf \u0b9a\u0bcc\u0bb9\u0bcd\u0b9f\u0bbe"
    ],
    "name:tel_x_preferred":[
        "\u0c2c\u0c24\u0c3f\u0c2f\u0c3e\u0c28\u0c3f \u0c1a\u0c4c\u0c24\u0c3e"
    ],
    "name:urd_x_preferred":[
        "\u0628\u06be\u062a\u06cc\u0627\u0646\u06cc \u0686\u0648\u062a\u0631\u06c1"
    ],
    "qs:gn_adm0_cc":"IN",
    "qs:gn_local":1253986,
    "qs:gn_nam_loc":"Udaipur, Udaipur, Rajasthan, IN",
    "qs:gn_namadm1":"24",
    "qs:local_max":4409,
    "qs:local_sum":9770,
    "qs:localhoods":18,
    "qs:name":"Bhatiyani Chauhta",
    "qs:name_adm0":"India",
    "qs:name_adm1":"Rajasthan",
    "qs:name_adm2":"Udaipur",
    "qs:name_local":"Udaipur",
    "qs:photo_max":40,
    "qs:photo_sum":49,
    "qs:placetype":"Suburb",
    "qs:quad_count":2,
    "qs:woe_adm0":23424848,
    "qs:woe_adm1":2345757,
    "qs:woe_adm2":12586676,
    "qs:woe_lau":0,
    "qs:woe_local":2295108,
    "qs:woe_ver":"7.10.0",
    "wof:lang":[
        "eng"
    ],
    "wof:name":"Bhatiyani Chauhta",
    "wof:placetype":"neighbourhood"
},
  "geometry": {"coordinates":[73.68621,24.577724],"type":"Point"}
}