{
  "type": "Feature",
  "properties": {
    "iso:country":"IN",
    "ks:ks_name":"Nagdi",
    "ks:ks_pop":111,
    "ks:ks_type":"VILLAGE",
    "name:eng_x_preferred":[
        "Nagdi"
    ],
    "wof:name":"Nagdi",
    "wof:placetype":"locality",
    "wof:population":111
},
  "geometry": {"coordinates":[86.810626,22.507364],"type":"Point"}
}