{
  "type": "Feature",
  "properties": {
    "iso:country":"IN",
    "ks:ks_alt_nam":"AKELWATAR",
    "ks:ks_name":"Akelwatar",
    "ks:ks_pop":150,
    "ks:ks_type":"HABITATION",
    "name:eng_x_preferred":[
        "Akelwatar"
    ],
    "wof:name":"Akelwatar",
    "wof:placetype":"locality",
    "wof:population":150
},
  "geometry": {"coordinates":[85.652486,24.634632],"type":"Point"}
}