{
  "type": "Feature",
  "properties": {
    "gn:admin1_code":"37.0",
    "gn:admin2_code":"408.0",
    "gn:asciiname":"Jiratola",
    "gn:country_code":"IN",
    "gn:dem":344,
    "gn:feature_class":"P",
    "gn:feature_code":"PPL",
    "gn:name":"J\u012br\u0101tola",
    "gn:population":0,
    "gn:timezone":"Asia/Kolkata",
    "iso:country":"IN",
    "name:eng_x_preferred":[
        "J\u012br\u0101tola"
    ],
    "wof:name":"Jiratola",
    "wof:placetype":"locality"
},
  "geometry": {"coordinates":[81.03549,21.62867],"type":"Point"}
}