{
  "type": "Feature",
  "properties": {
    "gn:admin1_code":"10.0",
    "gn:admin2_code":"85.0",
    "gn:asciiname":"Lakhnaur",
    "gn:country_code":"IN",
    "gn:dem":244,
    "gn:feature_class":"P",
    "gn:feature_code":"PPL",
    "gn:name":"L\u0101khnaur",
    "gn:population":0,
    "gn:timezone":"Asia/Kolkata",
    "iso:country":"IN",
    "ks:ks_alt_nam":"L\u0101khnaur",
    "ks:ks_name":"Lakhnaur",
    "ks:ks_pop":868,
    "ks:ks_type":"VILLAGE",
    "ks:ks_uagg_main":0,
    "name:eng_x_preferred":[
        "Lakhnaur"
    ],
    "name:eng_x_variant":[
        "L\u0101khnaur"
    ],
    "wof:name":"Lakhnaur",
    "wof:placetype":"neighbourhood",
    "wof:population":868
},
  "geometry": {"coordinates":[76.571022,28.231606],"type":"Point"}
}