{
  "type": "Feature",
  "properties": {
    "iso:country":"IN",
    "ks:ks_name":"Bolayan Nagar",
    "ks:ks_pop":166,
    "ks:ks_type":"HABITATION",
    "name:eng_x_preferred":[
        "Bolayan Nagar"
    ],
    "wof:name":"Bolayan Nagar",
    "wof:placetype":"locality",
    "wof:population":166
},
  "geometry": {"coordinates":[78.909479,9.327645],"type":"Point"}
}