{
  "type": "Feature",
  "properties": {
    "gn:admin1_code":"35.0",
    "gn:admin2_code":"455.0",
    "gn:asciiname":"Pindraj",
    "gn:country_code":"IN",
    "gn:dem":629,
    "gn:feature_class":"P",
    "gn:feature_code":"PPL",
    "gn:name":"Pindraj",
    "gn:population":0,
    "gn:timezone":"Asia/Kolkata",
    "iso:country":"IN",
    "wof:name":"Pindraj",
    "wof:placetype":"neighbourhood"
},
  "geometry": {"coordinates":[78.96829,21.88551],"type":"Point"}
}