{
  "type": "Feature",
  "properties": {
    "iso:country":"IN",
    "ks:ks_name":"Lakharipeta",
    "ks:ks_pop":383,
    "ks:ks_type":"VILLAGE",
    "name:eng_x_preferred":[
        "Lakharipeta"
    ],
    "wof:name":"Lakharipeta",
    "wof:placetype":"locality",
    "wof:population":383
},
  "geometry": {"coordinates":[84.200675,19.443063],"type":"Point"}
}