{
  "type": "Feature",
  "properties": {
    "gn:admin1_code":"21.0",
    "gn:admin2_code":"398.0",
    "gn:asciiname":"Kottaguda",
    "gn:country_code":"IN",
    "gn:dem":825,
    "gn:feature_class":"P",
    "gn:feature_code":"PPL",
    "gn:name":"Kottaguda",
    "gn:population":0,
    "gn:timezone":"Asia/Kolkata",
    "iso:country":"IN",
    "wof:name":"Kottaguda",
    "wof:placetype":"neighbourhood"
},
  "geometry": {"coordinates":[82.71988,18.83714],"type":"Point"}
}