{
  "type": "Feature",
  "properties": {
    "iso:country":"IN",
    "ks:ks_name":"Bajekudlu",
    "ks:ks_pop":2090,
    "ks:ks_type":"HABITATION",
    "name:eng_x_preferred":[
        "Bajekudlu"
    ],
    "wof:name":"Bajekudlu",
    "wof:placetype":"locality",
    "wof:population":2090
},
  "geometry": {"coordinates":[75.088859,12.673377],"type":"Point"}
}