{
  "type": "Feature",
  "properties": {
    "gn:admin1_code":"35.0",
    "gn:admin2_code":"419.0",
    "gn:asciiname":"Nareshwar",
    "gn:country_code":"IN",
    "gn:dem":191,
    "gn:feature_class":"P",
    "gn:feature_code":"PPL",
    "gn:name":"Nareshwar",
    "gn:population":0,
    "gn:timezone":"Asia/Kolkata",
    "iso:country":"IN",
    "name:ceb_x_preferred":[
        "Nareshwor"
    ],
    "name:mai_x_preferred":[
        "\u0928\u0930\u0947\u0936\u094d\u0935\u0930"
    ],
    "name:msa_x_preferred":[
        "Nareshwor"
    ],
    "name:nep_x_preferred":[
        "\u0928\u0930\u0947\u0936\u094d\u0935\u0930"
    ],
    "name:new_x_preferred":[
        "\u0928\u0930\u0947\u0936\u094d\u0935\u0930"
    ],
    "name:pol_x_preferred":[
        "Natreswor"
    ],
    "wof:name":"Nareshwar",
    "wof:placetype":"locality"
},
  "geometry": {"coordinates":[78.25261999999999,26.32897],"type":"Point"}
}