{
  "type": "Feature",
  "properties": {
    "iso:country":"IN",
    "ks:ks_name":"Joginahithlu",
    "ks:ks_pop":82,
    "ks:ks_type":"HABITATION",
    "name:eng_x_preferred":[
        "Joginahithlu"
    ],
    "wof:name":"Joginahithlu",
    "wof:placetype":"locality",
    "wof:population":82
},
  "geometry": {"coordinates":[75.321138,13.460703],"type":"Point"}
}