{
  "type": "Feature",
  "properties": {
    "iso:country":"IN",
    "ks:ks_name":"Chauthmal",
    "ks:ks_pop":909,
    "ks:ks_type":"VILLAGE",
    "name:eng_x_preferred":[
        "Chauthmal"
    ],
    "wof:name":"Chauthmal",
    "wof:placetype":"locality",
    "wof:population":909
},
  "geometry": {"coordinates":[74.118694,23.427839],"type":"Point"}
}