{
  "type": "Feature",
  "properties": {
    "gn:admin1_code":"11",
    "gn:admin2_code":"23.0",
    "gn:asciiname":"Bintru Dhar",
    "gn:country_code":"IN",
    "gn:dem":2097,
    "gn:feature_class":"P",
    "gn:feature_code":"PPL",
    "gn:name":"Bintru Dh\u0101r",
    "gn:population":0,
    "gn:timezone":"Asia/Kolkata",
    "iso:country":"IN",
    "wof:name":"Bintru Dhar",
    "wof:placetype":"locality"
},
  "geometry": {"coordinates":[76.06165,32.41972],"type":"Point"}
}