{
  "type": "Feature",
  "properties": {
    "iso:country":"IN",
    "ks:ks_name":"Padathkadavu",
    "ks:ks_pop":615,
    "ks:ks_type":"HABITATION",
    "name:eng_x_preferred":[
        "Padathkadavu"
    ],
    "wof:name":"Padathkadavu",
    "wof:placetype":"locality",
    "wof:population":615
},
  "geometry": {"coordinates":[75.791972,11.623004],"type":"Point"}
}