{
  "type": "Feature",
  "properties": {
    "gn:admin1_code":"36",
    "gn:admin2_code":"135.0",
    "gn:asciiname":"Sherpur Patti Ehtamali",
    "gn:country_code":"IN",
    "gn:dem":213,
    "gn:feature_class":"P",
    "gn:feature_code":"PPL",
    "gn:name":"Sherpur Patti Ehtam\u0101li",
    "gn:population":0,
    "gn:timezone":"Asia/Kolkata",
    "iso:country":"IN",
    "ks:ks_alt_nam":"Sherpur Patti Ehtam\u0101li",
    "ks:ks_name":"Sherpur Patti Ehtamali",
    "ks:ks_type":"VILLAGE",
    "ks:ks_uagg_main":0,
    "name:eng_x_preferred":[
        "Sherpur Patti Ehtamali"
    ],
    "name:eng_x_variant":[
        "Sherpur Patti Ehtam\u0101li"
    ],
    "wof:name":"Sherpur Patti Ehtamali",
    "wof:placetype":"neighbourhood"
},
  "geometry": {"coordinates":[78.69835500000001,29.165962],"type":"Point"}
}