{
  "type": "Feature",
  "properties": {
    "iso:country":"IN",
    "ks:ks_name":"Kambarkia",
    "ks:ks_pop":594,
    "ks:ks_type":"VILLAGE",
    "name:eng_x_preferred":[
        "Kambarkia"
    ],
    "wof:name":"Kambarkia",
    "wof:placetype":"locality",
    "wof:population":594
},
  "geometry": {"coordinates":[83.782436,20.298774],"type":"Point"}
}