{
  "type": "Feature",
  "properties": {
    "gn:admin1_code":"35",
    "gn:admin2_code":"449.0",
    "gn:asciiname":"Bareli",
    "gn:country_code":"IN",
    "gn:dem":327,
    "gn:feature_class":"P",
    "gn:feature_code":"PPL",
    "gn:name":"Bareli",
    "gn:population":0,
    "gn:timezone":"Asia/Kolkata",
    "iso:country":"IN",
    "name:ceb_x_preferred":[
        "Bareli"
    ],
    "name:fin_x_preferred":[
        "Bareli"
    ],
    "name:swe_x_preferred":[
        "Bareli"
    ],
    "wof:name":"Bareli",
    "wof:placetype":"locality"
},
  "geometry": {"coordinates":[78.27314,22.79235],"type":"Point"}
}