{
  "type": "Feature",
  "properties": {
    "gn:admin1_code":"35.0",
    "gn:admin2_code":"424",
    "gn:asciiname":"Shivpura",
    "gn:country_code":"IN",
    "gn:dem":276,
    "gn:feature_class":"P",
    "gn:feature_code":"PPL",
    "gn:name":"Shivpura",
    "gn:population":0,
    "gn:timezone":"Asia/Kolkata",
    "iso:country":"IN",
    "ks:ks_name":"Shivpura",
    "ks:ks_pop":670,
    "ks:ks_type":"VILLAGE",
    "name:eng_x_preferred":[
        "Shivpura"
    ],
    "wof:name":"Shivpura",
    "wof:placetype":"locality",
    "wof:population":670
},
  "geometry": {"coordinates":[78.985449,24.919374],"type":"Point"}
}