{
  "type": "Feature",
  "properties": {
    "iso:country":"IN",
    "ks:ks_name":"Saldigedda",
    "ks:ks_pop":36,
    "ks:ks_type":"HABITATION",
    "name:eng_x_preferred":[
        "Saldigedda"
    ],
    "wof:name":"Saldigedda",
    "wof:placetype":"locality",
    "wof:population":36
},
  "geometry": {"coordinates":[82.72805,18.039156],"type":"Point"}
}