{
  "type": "Feature",
  "properties": {
    "iso:country":"IN",
    "ks:ks_name":"Nirdesh Khali",
    "ks:ks_pop":2200,
    "ks:ks_type":"HABITATION",
    "name:eng_x_preferred":[
        "Nirdesh Khali"
    ],
    "wof:name":"Nirdesh Khali",
    "wof:placetype":"locality",
    "wof:population":2200
},
  "geometry": {"coordinates":[88.722488,22.294308],"type":"Point"}
}