{
  "type": "Feature",
  "properties": {
    "iso:country":"IN",
    "ks:ks_name":"Sutarwadi",
    "ks:ks_pop":261,
    "ks:ks_type":"HABITATION",
    "name:eng_x_preferred":[
        "Sutarwadi"
    ],
    "wof:name":"Sutarwadi",
    "wof:placetype":"locality",
    "wof:population":261
},
  "geometry": {"coordinates":[73.64031900000001,16.915754],"type":"Point"}
}