{
  "type": "Feature",
  "properties": {
    "iso:country":"IN",
    "ks:ks_alt_nam":"BELTOLI",
    "ks:ks_name":"Beltoli",
    "ks:ks_pop":120,
    "ks:ks_type":"HABITATION",
    "name:eng_x_preferred":[
        "Beltoli"
    ],
    "wof:name":"Beltoli",
    "wof:placetype":"locality",
    "wof:population":120
},
  "geometry": {"coordinates":[83.79942200000001,22.999564],"type":"Point"}
}