{
  "type": "Feature",
  "properties": {
    "gn:admin1_code":"2",
    "gn:admin2_code":"544.0",
    "gn:asciiname":"Gondipalle",
    "gn:country_code":"IN",
    "gn:dem":867,
    "gn:feature_class":"P",
    "gn:feature_code":"PPL",
    "gn:name":"Gondipalle",
    "gn:population":0,
    "gn:timezone":"Asia/Kolkata",
    "iso:country":"IN",
    "ks:ks_name":"Gondipalle",
    "ks:ks_type":"VILLAGE",
    "name:eng_x_preferred":[
        "Gondipalle"
    ],
    "wof:name":"Gondipalle",
    "wof:placetype":"locality"
},
  "geometry": {"coordinates":[82.20617300000001,17.89437],"type":"Point"}
}