{
  "type": "Feature",
  "properties": {
    "iso:country":"IN",
    "ks:ks_name":"Upperpodapadar",
    "ks:ks_pop":114,
    "ks:ks_type":"HABITATION",
    "name:eng_x_preferred":[
        "Upperpodapadar"
    ],
    "wof:name":"Upperpodapadar",
    "wof:placetype":"locality",
    "wof:population":114
},
  "geometry": {"coordinates":[83.00277800000001,18.931401],"type":"Point"}
}