{
  "type": "Feature",
  "properties": {
    "iso:country":"IN",
    "ks:ks_name":"Devaraduka",
    "ks:ks_pop":1543,
    "ks:ks_type":"HABITATION",
    "name:eng_x_preferred":[
        "Devaraduka"
    ],
    "wof:name":"Devaraduka",
    "wof:placetype":"locality",
    "wof:population":1543
},
  "geometry": {"coordinates":[75.267208,12.562862],"type":"Point"}
}