{
  "type": "Feature",
  "properties": {
    "iso:country":"IN",
    "ks:ks_name":"Borgaon",
    "ks:ks_pop":865,
    "ks:ks_type":"VILLAGE",
    "ks:ks_uagg_main":0,
    "name:eng_x_preferred":[
        "Borgaon"
    ],
    "wof:name":"Borgaon",
    "wof:placetype":"neighbourhood",
    "wof:population":865
},
  "geometry": {"coordinates":[94.556719,27.501303],"type":"Point"}
}