{
  "type": "Feature",
  "properties": {
    "iso:country":"IN",
    "ks:ks_name":"Gunjarabadi",
    "ks:ks_pop":178,
    "ks:ks_type":"HABITATION",
    "name:eng_x_preferred":[
        "Gunjarabadi"
    ],
    "wof:name":"Gunjarabadi",
    "wof:placetype":"locality",
    "wof:population":178
},
  "geometry": {"coordinates":[83.489118,19.168424],"type":"Point"}
}