{
  "type": "Feature",
  "properties": {
    "iso:country":"IN",
    "ks:ks_alt_nam":"Sah\u0101datpura",
    "ks:ks_name":"Sahadatpura",
    "ks:ks_type":"VILLAGE",
    "ks:ks_uagg_main":0,
    "name:eng_x_preferred":[
        "Sahadatpura"
    ],
    "name:eng_x_variant":[
        "Sah\u0101datpura"
    ],
    "wof:name":"Sahadatpura",
    "wof:placetype":"neighbourhood"
},
  "geometry": {"coordinates":[83.567421,25.930206],"type":"Point"}
}