{
  "type": "Feature",
  "properties": {
    "iso:country":"IN",
    "ks:ks_name":"Aruhabarti No-1",
    "ks:ks_pop":2293,
    "ks:ks_type":"VILLAGE",
    "name:eng_x_preferred":[
        "Aruhabarti No-1"
    ],
    "wof:name":"Aruhabarti No-1",
    "wof:placetype":"locality",
    "wof:population":2293
},
  "geometry": {"coordinates":[87.327769,21.673173],"type":"Point"}
}