{
  "type": "Feature",
  "properties": {
    "iso:country":"IN",
    "ks:ks_name":"Purnachandrapur-II",
    "ks:ks_pop":221,
    "ks:ks_type":"VILLAGE",
    "name:eng_x_preferred":[
        "Purnachandrapur-II"
    ],
    "wof:name":"Purnachandrapur-II",
    "wof:placetype":"locality",
    "wof:population":221
},
  "geometry": {"coordinates":[86.912195,21.765754],"type":"Point"}
}