{
  "type": "Feature",
  "properties": {
    "iso:country":"IN",
    "ks:ks_name":"Motaiwadi",
    "ks:ks_pop":238,
    "ks:ks_type":"HABITATION",
    "name:eng_x_preferred":[
        "Motaiwadi"
    ],
    "wof:name":"Motaiwadi",
    "wof:placetype":"locality",
    "wof:population":238
},
  "geometry": {"coordinates":[73.985778,16.75055],"type":"Point"}
}