{
  "type": "Feature",
  "properties": {
    "gn:admin1_code":"19.0",
    "gn:admin2_code":"572.0",
    "gn:asciiname":"Shigihalli",
    "gn:country_code":"IN",
    "gn:dem":850,
    "gn:feature_class":"P",
    "gn:feature_code":"PPL",
    "gn:name":"Shigihalli",
    "gn:population":0,
    "gn:timezone":"Asia/Kolkata",
    "iso:country":"IN",
    "wof:name":"Shigihalli",
    "wof:placetype":"locality"
},
  "geometry": {"coordinates":[77.44901999999998,12.97313],"type":"Point"}
}