{
  "type": "Feature",
  "properties": {
    "iso:country":"IN",
    "ks:ks_name":"Navalkollaipatti",
    "ks:ks_pop":150,
    "ks:ks_type":"HABITATION",
    "name:eng_x_preferred":[
        "Navalkollaipatti"
    ],
    "wof:name":"Navalkollaipatti",
    "wof:placetype":"locality",
    "wof:population":150
},
  "geometry": {"coordinates":[79.08931800000001,10.555296],"type":"Point"}
}