{
  "type": "Feature",
  "properties": {
    "gn:admin1_code":"25.0",
    "gn:admin2_code":"604.0",
    "gn:asciiname":"Mambattu",
    "gn:country_code":"IN",
    "gn:dem":34,
    "gn:feature_class":"P",
    "gn:feature_code":"PPL",
    "gn:name":"M\u0101mbattu",
    "gn:population":0,
    "gn:timezone":"Asia/Kolkata",
    "iso:country":"IN",
    "ks:ks_name":"Mambattu",
    "ks:ks_pop":500,
    "ks:ks_type":"VILLAGE",
    "name:eng_x_preferred":[
        "Mambattu"
    ],
    "wof:name":"Mambattu",
    "wof:placetype":"locality",
    "wof:population":500
},
  "geometry": {"coordinates":[79.895938,12.604674],"type":"Point"}
}