{
  "type": "Feature",
  "properties": {
    "gn:admin1_code":"16",
    "gn:admin2_code":"512.0",
    "gn:asciiname":"Pipla",
    "gn:country_code":"IN",
    "gn:dem":389,
    "gn:feature_class":"P",
    "gn:feature_code":"PPL",
    "gn:name":"Pipla",
    "gn:population":0,
    "gn:timezone":"Asia/Kolkata",
    "iso:country":"IN",
    "wof:name":"Pipla",
    "wof:placetype":"locality"
},
  "geometry": {"coordinates":[77.1707,19.17492],"type":"Point"}
}