{
  "type": "Feature",
  "properties": {
    "iso:country":"IN",
    "ks:ks_name":"Nauli Chack",
    "ks:ks_pop":45,
    "ks:ks_type":"VILLAGE",
    "ks:ks_uagg_main":0,
    "name:eng_x_preferred":[
        "Nauli Chack"
    ],
    "wof:name":"Nauli Chack",
    "wof:placetype":"neighbourhood",
    "wof:population":45
},
  "geometry": {"coordinates":[78.67084800000001,30.557504],"type":"Point"}
}