{
  "type": "Feature",
  "properties": {
    "iso:country":"IN",
    "ks:ks_name":"Bazarwadi.",
    "ks:ks_pop":43,
    "ks:ks_type":"HABITATION",
    "name:eng_x_preferred":[
        "Bazarwadi."
    ],
    "wof:name":"Bazarwadi.",
    "wof:placetype":"locality",
    "wof:population":43
},
  "geometry": {"coordinates":[73.513875,16.187981],"type":"Point"}
}