{
  "type": "Feature",
  "properties": {
    "gn:admin1_code":"34.0",
    "gn:admin2_code":"214.0",
    "gn:asciiname":"Motibari",
    "gn:country_code":"IN",
    "gn:dem":43,
    "gn:feature_class":"P",
    "gn:feature_code":"PPL",
    "gn:name":"Motib\u0101ri",
    "gn:population":0,
    "gn:timezone":"Asia/Kolkata",
    "iso:country":"IN",
    "wof:name":"Motibari",
    "wof:placetype":"locality"
},
  "geometry": {"coordinates":[86.84229999999999,25.72714],"type":"Point"}
}