{
  "type": "Feature",
  "properties": {
    "gn:admin1_code":"2.0",
    "gn:admin2_code":"544.0",
    "gn:asciiname":"Chittampadu",
    "gn:country_code":"IN",
    "gn:dem":574,
    "gn:feature_class":"P",
    "gn:feature_code":"PPL",
    "gn:name":"Chittamp\u0101du",
    "gn:population":0,
    "gn:timezone":"Asia/Kolkata",
    "iso:country":"IN",
    "ks:ks_name":"Chittampadu",
    "ks:ks_pop":41,
    "ks:ks_type":"HABITATION",
    "name:eng_x_preferred":[
        "Chittampadu"
    ],
    "wof:name":"Chittampadu",
    "wof:placetype":"locality",
    "wof:population":41
},
  "geometry": {"coordinates":[83.033579,18.180782],"type":"Point"}
}