{
  "type": "Feature",
  "properties": {
    "iso:country":"IN",
    "ks:ks_name":"Battubathan",
    "ks:ks_pop":42,
    "ks:ks_type":"VILLAGE",
    "name:eng_x_preferred":[
        "Battubathan"
    ],
    "wof:name":"Battubathan",
    "wof:placetype":"locality",
    "wof:population":42
},
  "geometry": {"coordinates":[86.992133,24.155703],"type":"Point"}
}