{
  "type": "Feature",
  "properties": {
    "iso:country":"IN",
    "ks:ks_name":"Banathapalke",
    "ks:ks_pop":90,
    "ks:ks_type":"HABITATION",
    "name:eng_x_preferred":[
        "Banathapalke"
    ],
    "wof:name":"Banathapalke",
    "wof:placetype":"locality",
    "wof:population":90
},
  "geometry": {"coordinates":[75.069665,13.237675],"type":"Point"}
}