{
  "type": "Feature",
  "properties": {
    "gn:admin1_code":"34.0",
    "gn:admin2_code":"236.0",
    "gn:asciiname":"Guraru",
    "gn:country_code":"IN",
    "gn:dem":143,
    "gn:feature_class":"P",
    "gn:feature_code":"PPL",
    "gn:name":"Gur\u0101ru",
    "gn:population":0,
    "gn:timezone":"Asia/Kolkata",
    "iso:country":"IN",
    "name:und_x_variant":[
        "Gur\u0101ru",
        "Gudru"
    ],
    "wof:name":"Guraru",
    "wof:placetype":"locality"
},
  "geometry": {"coordinates":[84.73229000000001,24.62956],"type":"Point"}
}