{
  "type": "Feature",
  "properties": {
    "gn:admin1_code":"40",
    "gn:admin2_code":"539.0",
    "gn:asciiname":"Veldanda",
    "gn:country_code":"IN",
    "gn:dem":144,
    "gn:feature_class":"P",
    "gn:feature_code":"PPL",
    "gn:name":"Veldanda",
    "gn:population":0,
    "gn:timezone":"Asia/Kolkata",
    "iso:country":"IN",
    "name:new_x_preferred":[
        "\u0935\u0947\u0932\u094d\u0926\u0902\u0921 \u092e\u0923\u094d\u0921\u0932"
    ],
    "name:tel_x_preferred":[
        "\u0c35\u0c46\u0c32\u0c4d\u0c26\u0c02\u0c21"
    ],
    "wof:name":"Veldanda",
    "wof:placetype":"locality"
},
  "geometry": {"coordinates":[79.78231,16.97101],"type":"Point"}
}