{
  "type": "Feature",
  "properties": {
    "gn:admin1_code":"36",
    "gn:admin2_code":"180.0",
    "gn:asciiname":"Bamhiari",
    "gn:country_code":"IN",
    "gn:dem":118,
    "gn:feature_class":"P",
    "gn:feature_code":"PPL",
    "gn:name":"Bamhi\u0101ri",
    "gn:population":0,
    "gn:timezone":"Asia/Kolkata",
    "iso:country":"IN",
    "wof:name":"Bamhiari",
    "wof:placetype":"locality"
},
  "geometry": {"coordinates":[81.47159000000001,27.41055],"type":"Point"}
}