{
  "type": "Feature",
  "properties": {
    "iso:country":"IN",
    "ks:ks_name":"Majherhat East",
    "ks:ks_pop":1585,
    "ks:ks_type":"HABITATION",
    "name:eng_x_preferred":[
        "Majherhat East"
    ],
    "wof:name":"Majherhat East",
    "wof:placetype":"locality",
    "wof:population":1585
},
  "geometry": {"coordinates":[88.54551600000001,22.330811],"type":"Point"}
}