{
  "type": "Feature",
  "properties": {
    "iso:country":"IN",
    "ks:ks_name":"Bennamakki",
    "ks:ks_pop":138,
    "ks:ks_type":"HABITATION",
    "name:eng_x_preferred":[
        "Bennamakki"
    ],
    "wof:name":"Bennamakki",
    "wof:placetype":"locality",
    "wof:population":138
},
  "geometry": {"coordinates":[74.77167,13.706695],"type":"Point"}
}