{
  "type": "Feature",
  "properties": {
    "gn:admin1_code":"2.0",
    "gn:admin2_code":"554.0",
    "gn:asciiname":"Ambaramaharajupuram",
    "gn:country_code":"IN",
    "gn:dem":207,
    "gn:feature_class":"P",
    "gn:feature_code":"PPL",
    "gn:name":"Ambaramah\u0101r\u0101jupuram",
    "gn:population":0,
    "gn:timezone":"Asia/Kolkata",
    "iso:country":"IN",
    "wof:name":"Ambaramaharajupuram",
    "wof:placetype":"locality"
},
  "geometry": {"coordinates":[79.34501,13.28219],"type":"Point"}
}