{
  "type": "Feature",
  "properties": {
    "gn:admin1_code":"2.0",
    "gn:admin2_code":"554.0",
    "gn:asciiname":"Ambaramaharajupuram",
    "gn:country_code":"IN",
    "gn:dem":207,
    "gn:feature_class":"P",
    "gn:feature_code":"PPL",
    "gn:name":"Ambaramah\u0101r\u0101jupuram",
    "gn:population":0,
    "gn:timezone":"Asia/Kolkata",
    "iso:country":"IN",
    "ks:ks_alt_nam":"AMBARAMAHARAJA PURAM",
    "ks:ks_name":"Ambaramaharaja Puram",
    "ks:ks_pop":87,
    "ks:ks_type":"HABITATION",
    "name:eng_x_preferred":[
        "Ambaramaharaja Puram"
    ],
    "name:eng_x_variant":[
        "Ambaramaharajupuram"
    ],
    "wof:name":"Ambaramaharaja Puram",
    "wof:placetype":"locality",
    "wof:population":87
},
  "geometry": {"coordinates":[79.346422,13.280956],"type":"Point"}
}