{
  "type": "Feature",
  "properties": {
    "iso:country":"IN",
    "ks:ks_name":"Khemwadi",
    "ks:ks_pop":150,
    "ks:ks_type":"HABITATION",
    "name:eng_x_preferred":[
        "Khemwadi"
    ],
    "wof:name":"Khemwadi",
    "wof:placetype":"locality",
    "wof:population":150
},
  "geometry": {"coordinates":[73.19041900000001,18.615613],"type":"Point"}
}