{
  "type": "Feature",
  "properties": {
    "iso:country":"IN",
    "ks:ks_alt_nam":"N\u0101ngloi J\u0101t",
    "ks:ks_name":"Nangloi Jat",
    "ks:ks_type":"VILLAGE",
    "ks:ks_uagg_main":0,
    "name:eng_x_preferred":[
        "Nangloi Jat"
    ],
    "name:eng_x_variant":[
        "N\u0101ngloi J\u0101t"
    ],
    "wof:name":"Nangloi Jat",
    "wof:placetype":"neighbourhood"
},
  "geometry": {"coordinates":[77.067994,28.679568],"type":"Point"}
}