{
  "type": "Feature",
  "properties": {
    "gn:admin1_code":"36",
    "gn:admin2_code":"165.0",
    "gn:asciiname":"Rewa",
    "gn:country_code":"IN",
    "gn:dem":139,
    "gn:feature_class":"P",
    "gn:feature_code":"PPL",
    "gn:name":"Rewa",
    "gn:population":0,
    "gn:timezone":"Asia/Kolkata",
    "iso:country":"IN",
    "name:ben_x_preferred":[
        "\u09b0\u09c7\u0993\u09af\u09bc\u09be"
    ],
    "name:bih_x_preferred":[
        "\u0930\u0940\u0935\u093e"
    ],
    "name:bpy_x_preferred":[
        "\u09b0\u09c7\u09f1\u09be"
    ],
    "name:ceb_x_preferred":[
        "Rewa"
    ],
    "name:deu_x_preferred":[
        "Rewa"
    ],
    "name:fin_x_preferred":[
        "Rewa"
    ],
    "name:fra_x_preferred":[
        "Rewa"
    ],
    "name:ita_x_preferred":[
        "Rewa"
    ],
    "name:msa_x_preferred":[
        "Rewa"
    ],
    "name:nld_x_preferred":[
        "Rewa"
    ],
    "name:pol_x_preferred":[
        "Rewa"
    ],
    "name:por_x_preferred":[
        "Rewa"
    ],
    "name:spa_x_preferred":[
        "Rewa"
    ],
    "name:swe_x_preferred":[
        "Rewa"
    ],
    "wof:name":"Rewa",
    "wof:placetype":"locality"
},
  "geometry": {"coordinates":[79.50508000000001,26.02224],"type":"Point"}
}