{
  "type": "Feature",
  "properties": {
    "gn:admin1_code":"34.0",
    "gn:admin2_code":"219.0",
    "gn:asciiname":"Chetan Parsa",
    "gn:country_code":"IN",
    "gn:dem":57,
    "gn:feature_class":"P",
    "gn:feature_code":"PPL",
    "gn:name":"Chetan Parsa",
    "gn:population":0,
    "gn:timezone":"Asia/Kolkata",
    "iso:country":"IN",
    "ks:ks_name":"Chetan Parsa",
    "ks:ks_pop":1104,
    "ks:ks_type":"VILLAGE",
    "name:eng_x_preferred":[
        "Chetan Parsa"
    ],
    "wof:name":"Chetan Parsa",
    "wof:placetype":"locality",
    "wof:population":1104
},
  "geometry": {"coordinates":[85.026644,25.892532],"type":"Point"}
}