{
  "type": "Feature",
  "properties": {
    "gn:admin1_code":"24.0",
    "gn:admin2_code":"130.0",
    "gn:asciiname":"Khotawara",
    "gn:country_code":"IN",
    "gn:dem":406,
    "gn:feature_class":"P",
    "gn:feature_code":"PPL",
    "gn:name":"Khot\u0101w\u0101ra",
    "gn:population":0,
    "gn:timezone":"Asia/Kolkata",
    "iso:country":"IN",
    "ks:ks_name":"Khutwara",
    "ks:ks_pop":391,
    "ks:ks_type":"VILLAGE",
    "name:eng_x_preferred":[
        "Khutwara"
    ],
    "name:eng_x_variant":[
        "Khotawara"
    ],
    "wof:name":"Khutwara",
    "wof:placetype":"locality",
    "wof:population":391
},
  "geometry": {"coordinates":[73.506743,23.992881],"type":"Point"}
}