{
  "type": "Feature",
  "properties": {
    "iso:country":"IN",
    "ks:ks_name":"Bisunpur Nagwan",
    "ks:ks_pop":853,
    "ks:ks_type":"VILLAGE",
    "ks:ks_uagg_main":0,
    "name:eng_x_preferred":[
        "Bisunpur Nagwan"
    ],
    "wof:name":"Bisunpur Nagwan",
    "wof:placetype":"locality",
    "wof:population":853
},
  "geometry": {"coordinates":[85.51500799999999,26.513131],"type":"Point"}
}