{
  "type": "Feature",
  "properties": {
    "iso:country":"IN",
    "ks:ks_alt_nam":"Vasuram Thanda at Desya Thanda",
    "ks:ks_name":"Vasuram Thanda At Desya Thanda",
    "ks:ks_pop":66,
    "ks:ks_type":"HABITATION",
    "name:eng_x_preferred":[
        "Vasuram Thanda At Desya Thanda"
    ],
    "wof:name":"Vasuram Thanda At Desya Thanda",
    "wof:placetype":"locality",
    "wof:population":66
},
  "geometry": {"coordinates":[78.22872700000001,17.947923],"type":"Point"}
}