{
  "type": "Feature",
  "properties": {
    "iso:country":"IN",
    "ks:ks_alt_nam":"MUSHAHAR TOLA",
    "ks:ks_name":"Mushahar Tola",
    "ks:ks_pop":499,
    "ks:ks_type":"HABITATION",
    "name:eng_x_preferred":[
        "Mushahar Tola"
    ],
    "wof:name":"Mushahar Tola",
    "wof:placetype":"locality",
    "wof:population":499
},
  "geometry": {"coordinates":[84.58069,26.42493],"type":"Point"}
}