{
  "type": "Feature",
  "properties": {
    "gn:admin1_code":"36",
    "gn:admin2_code":"158.0",
    "gn:asciiname":"Jatua Tappa Bijhaun",
    "gn:country_code":"IN",
    "gn:dem":116,
    "gn:feature_class":"P",
    "gn:feature_code":"PPL",
    "gn:name":"Jatua Tappa Bijhaun",
    "gn:population":0,
    "gn:timezone":"Asia/Kolkata",
    "iso:country":"IN",
    "wof:name":"Jatua Tappa Bijhaun",
    "wof:placetype":"locality"
},
  "geometry": {"coordinates":[81.29701999999997,26.31602],"type":"Point"}
}