{
  "type": "Feature",
  "properties": {
    "iso:country":"IN",
    "ks:ks_name":"Kaisali",
    "ks:ks_pop":105,
    "ks:ks_type":"VILLAGE",
    "name:eng_x_preferred":[
        "Kaisali"
    ],
    "wof:name":"Kaisali",
    "wof:placetype":"locality",
    "wof:population":105
},
  "geometry": {"coordinates":[80.322495,29.699674],"type":"Point"}
}