{
  "type": "Feature",
  "properties": {
    "iso:country":"IN",
    "ks:ks_name":"Dharpur",
    "ks:ks_pop":92,
    "ks:ks_type":"VILLAGE",
    "name:eng_x_preferred":[
        "Dharpur"
    ],
    "wof:name":"Dharpur",
    "wof:placetype":"locality",
    "wof:population":92
},
  "geometry": {"coordinates":[73.622103,24.018308],"type":"Point"}
}