{
  "type": "Feature",
  "properties": {
    "gn:admin1_code":"38.0",
    "gn:admin2_code":"347.0",
    "gn:asciiname":"Chaurtanrtoli",
    "gn:country_code":"IN",
    "gn:dem":413,
    "gn:feature_class":"P",
    "gn:feature_code":"PPL",
    "gn:name":"Chaurt\u0101nrtoli",
    "gn:population":0,
    "gn:timezone":"Asia/Kolkata",
    "iso:country":"IN",
    "wof:name":"Chaurtanrtoli",
    "wof:placetype":"locality"
},
  "geometry": {"coordinates":[85.02228000000002,24.34223],"type":"Point"}
}