{
  "type": "Feature",
  "properties": {
    "gn:admin1_code":"19",
    "gn:admin2_code":"563.0",
    "gn:asciiname":"Kotalli",
    "gn:country_code":"IN",
    "gn:dem":520,
    "gn:feature_class":"P",
    "gn:feature_code":"PPL",
    "gn:name":"Kotalli",
    "gn:population":0,
    "gn:timezone":"Asia/Kolkata",
    "iso:country":"IN",
    "name:ceb_x_preferred":[
        "Kotall\u012b"
    ],
    "name:fas_x_preferred":[
        "\u06a9\u062a\u0644\u06cc"
    ],
    "name:swe_x_preferred":[
        "Kotall\u012b"
    ],
    "wof:name":"Kotalli",
    "wof:placetype":"locality"
},
  "geometry": {"coordinates":[74.76706,14.38533],"type":"Point"}
}