{
  "type": "Feature",
  "properties": {
    "gn:admin1_code":"39.0",
    "gn:admin2_code":"57.0",
    "gn:asciiname":"Kaling Simar",
    "gn:country_code":"IN",
    "gn:dem":1656,
    "gn:feature_class":"P",
    "gn:feature_code":"PPL",
    "gn:name":"K\u0101ling Sim\u0101r",
    "gn:population":0,
    "gn:timezone":"Asia/Kolkata",
    "iso:country":"IN",
    "wof:name":"Kaling Simar",
    "wof:placetype":"locality"
},
  "geometry": {"coordinates":[79.27288,29.99405],"type":"Point"}
}