{
  "type": "Feature",
  "properties": {
    "gn:country":"IN",
    "gn:fcode":"PPL",
    "gn:population":47774,
    "iso:country":"IN",
    "name:ceb_x_preferred":[
        "Chur\u0101ch\u0101ndpur"
    ],
    "name:eng_x_preferred":[
        "Churachandpur"
    ],
    "name:fra_x_preferred":[
        "Churachandpur"
    ],
    "name:guj_x_preferred":[
        "\u0a9a\u0ac1\u0ab0\u0abe\u0a9a\u0abe\u0a82\u0aa6\u0aaa\u0ac1\u0ab0"
    ],
    "name:hin_x_preferred":[
        "\u091a\u0941\u0930\u093e\u091a\u093e\u0902\u0926\u092a\u0941\u0930"
    ],
    "name:ita_x_preferred":[
        "Churachandpur"
    ],
    "name:mar_x_preferred":[
        "\u091a\u0941\u0930\u093e\u091a\u093e\u0902\u0926\u092a\u0942\u0930"
    ],
    "name:mni_x_preferred":[
        "\uabc6\uabe8\uabd4\uabc6\uabe5\uabdf\uabc4\uabe7\uabd4"
    ],
    "name:nld_x_preferred":[
        "Churachandpur"
    ],
    "name:spa_x_preferred":[
        "Churachandpur"
    ],
    "name:swe_x_preferred":[
        "Chur\u0101ch\u0101ndpur"
    ],
    "name:tam_x_preferred":[
        "\u0b9a\u0bc1\u0bb0\u0bbe\u0b9a\u0ba8\u0bcd\u0ba4\u0bcd\u0baa\u0bc2\u0bb0\u0bcd"
    ],
    "name:tel_x_preferred":[
        "\u0c1a\u0c41\u0c30\u0c1a\u0c02\u0c26\u0c4d\u200c\u0c2a\u0c42\u0c30\u0c4d"
    ],
    "name:ukr_x_preferred":[
        "\u0427\u0443\u0440\u0430\u0447\u0430\u043d\u0434\u043f\u0443\u0440"
    ],
    "qs:name":"Chur\u0101ch\u0101ndpur",
    "qs:photos_9r":0,
    "qs:photos_sr":0,
    "qs:pop_sr":"7",
    "wd:wordcount":613,
    "wof:name":"Chur\u0101ch\u0101ndpur",
    "wof:placetype":"locality",
    "wof:population":47774
},
  "geometry": {"coordinates":[93.66999,24.33353],"type":"Point"}
}