{
  "type": "Feature",
  "properties": {
    "gn:country":"IN",
    "gn:fcode":"PPL",
    "gn:population":47774,
    "iso:country":"IN",
    "name:eng_x_preferred":[
        "Churachandpur"
    ],
    "name:fra_x_preferred":[
        "Churachandpur"
    ],
    "name:guj_x_preferred":[
        "\u0a9a\u0ac1\u0ab0\u0abe\u0a9a\u0abe\u0a82\u0aa6\u0aaa\u0ac1\u0ab0"
    ],
    "name:ita_x_preferred":[
        "Churachandpur"
    ],
    "name:nld_x_preferred":[
        "Churachandpur"
    ],
    "name:spa_x_preferred":[
        "Churachandpur"
    ],
    "qs:name":"Chur\u0101ch\u0101ndpur",
    "qs:photos_9r":0,
    "qs:photos_sr":0,
    "qs:pop_sr":"7",
    "wd:wordcount":613,
    "wof:name":"Chur\u0101ch\u0101ndpur",
    "wof:placetype":"locality",
    "wof:population":47774
},
  "geometry": {"coordinates":[93.66999,24.33353],"type":"Point"}
}