{
  "type": "Feature",
  "properties": {
    "gn:admin1_code":"25.0",
    "gn:admin2_code":"607.0",
    "gn:asciiname":"Kallandal",
    "gn:country_code":"IN",
    "gn:dem":130,
    "gn:feature_class":"P",
    "gn:feature_code":"PPL",
    "gn:name":"Kallandal",
    "gn:population":0,
    "gn:timezone":"Asia/Kolkata",
    "iso:country":"IN",
    "wof:name":"Kallandal",
    "wof:placetype":"locality"
},
  "geometry": {"coordinates":[79.23676999999998,12.03933],"type":"Point"}
}