{
  "type": "Feature",
  "properties": {
    "gn:admin1_code":"16",
    "gn:admin2_code":"501.0",
    "gn:asciiname":"Ukli",
    "gn:country_code":"IN",
    "gn:dem":313,
    "gn:feature_class":"P",
    "gn:feature_code":"PPL",
    "gn:name":"Ukli",
    "gn:population":0,
    "gn:timezone":"Asia/Kolkata",
    "iso:country":"IN",
    "ks:ks_name":"Ukli",
    "ks:ks_type":"VILLAGE",
    "name:eng_x_preferred":[
        "Ukli"
    ],
    "wof:name":"Ukli",
    "wof:placetype":"locality"
},
  "geometry": {"coordinates":[77.17362300000001,20.649873],"type":"Point"}
}