{
  "type": "Feature",
  "properties": {
    "iso:country":"IN",
    "ks:ks_name":"Bandipur",
    "ks:ks_pop":2707,
    "ks:ks_type":"VILLAGE",
    "name:eng_x_preferred":[
        "Bandipur"
    ],
    "wof:name":"Bandipur",
    "wof:placetype":"locality",
    "wof:population":2707
},
  "geometry": {"coordinates":[87.755348,22.735476],"type":"Point"}
}