{
  "type": "Feature",
  "properties": {
    "iso:country":"IN",
    "ks:ks_name":"Mahadev Padava",
    "ks:ks_pop":258,
    "ks:ks_type":"HABITATION",
    "name:eng_x_preferred":[
        "Mahadev Padava"
    ],
    "wof:name":"Mahadev Padava",
    "wof:placetype":"locality",
    "wof:population":258
},
  "geometry": {"coordinates":[75.38200999999999,21.691959],"type":"Point"}
}