{
  "type": "Feature",
  "properties": {
    "iso:country":"IN",
    "name:eng_x_preferred":[
        "Barwara House Colony"
    ],
    "qs:gn_adm0_cc":"IN",
    "qs:gn_local":1269515,
    "qs:gn_nam_loc":"Jaipur, Jaipur, Rajasthan, IN",
    "qs:gn_namadm1":"24",
    "qs:local_max":5228,
    "qs:local_sum":21837,
    "qs:localhoods":33,
    "qs:name":"Barwara House Colony",
    "qs:name_adm0":"India",
    "qs:name_adm1":"Rajasthan",
    "qs:name_adm2":"Jaipur",
    "qs:name_local":"Jaipur",
    "qs:photo_max":29,
    "qs:photo_sum":47,
    "qs:placetype":"Suburb",
    "qs:quad_count":3,
    "qs:woe_adm0":23424848,
    "qs:woe_adm1":2345757,
    "qs:woe_adm2":12586662,
    "qs:woe_lau":0,
    "qs:woe_local":2295401,
    "qs:woe_ver":"7.10.0",
    "wof:lang":[
        "eng"
    ],
    "wof:name":"Barwara House Colony",
    "wof:placetype":"neighbourhood"
},
  "geometry": {"coordinates":[75.785854,26.912795],"type":"Point"}
}