{
  "type": "Feature",
  "properties": {
    "iso:country":"IN",
    "ks:ks_name":"Shonpur",
    "ks:ks_pop":1296,
    "ks:ks_type":"VILLAGE",
    "name:eng_x_preferred":[
        "Shonpur"
    ],
    "wof:name":"Shonpur",
    "wof:placetype":"locality",
    "wof:population":1296
},
  "geometry": {"coordinates":[87.487818,21.656246],"type":"Point"}
}