{
  "type": "Feature",
  "properties": {
    "iso:country":"IN",
    "ks:ks_name":"Telugucampu",
    "ks:ks_pop":145,
    "ks:ks_type":"HABITATION",
    "name:eng_x_preferred":[
        "Telugucampu"
    ],
    "wof:name":"Telugucampu",
    "wof:placetype":"locality",
    "wof:population":145
},
  "geometry": {"coordinates":[81.91291099999999,17.973126],"type":"Point"}
}