{
  "type": "Feature",
  "properties": {
    "iso:country":"IN",
    "ks:ks_alt_nam":"SANLISIA",
    "ks:ks_name":"Sanlisia",
    "ks:ks_pop":435,
    "ks:ks_type":"HABITATION",
    "name:eng_x_preferred":[
        "Sanlisia"
    ],
    "wof:name":"Sanlisia",
    "wof:placetype":"locality",
    "wof:population":435
},
  "geometry": {"coordinates":[85.739538,22.384309],"type":"Point"}
}