{
  "type": "Feature",
  "properties": {
    "iso:country":"IN",
    "ks:ks_name":"Rengappagoundenpudur",
    "ks:ks_pop":282,
    "ks:ks_type":"HABITATION",
    "name:eng_x_preferred":[
        "Rengappagoundenpudur"
    ],
    "wof:name":"Rengappagoundenpudur",
    "wof:placetype":"locality",
    "wof:population":282
},
  "geometry": {"coordinates":[77.03425799999999,11.2383],"type":"Point"}
}