{
  "type": "Feature",
  "properties": {
    "iso:country":"IN",
    "ks:ks_name":"Kumbharmuli",
    "ks:ks_pop":2175,
    "ks:ks_type":"HABITATION",
    "name:eng_x_preferred":[
        "Kumbharmuli"
    ],
    "wof:name":"Kumbharmuli",
    "wof:placetype":"locality",
    "wof:population":2175
},
  "geometry": {"coordinates":[87.427627,21.656956],"type":"Point"}
}