{
  "type": "Feature",
  "properties": {
    "gn:admin1_code":"19.0",
    "gn:admin2_code":"563.0",
    "gn:asciiname":"Tannirmadi",
    "gn:country_code":"IN",
    "gn:dem":15,
    "gn:feature_class":"P",
    "gn:feature_code":"PPL",
    "gn:name":"Tannirmadi",
    "gn:population":0,
    "gn:timezone":"Asia/Kolkata",
    "iso:country":"IN",
    "ks:ks_alt_nam":"tanniramadi",
    "ks:ks_name":"Tanniramadi",
    "ks:ks_pop":230,
    "ks:ks_type":"HABITATION",
    "name:eng_x_preferred":[
        "Tanniramadi"
    ],
    "name:eng_x_variant":[
        "Tannirmadi"
    ],
    "wof:name":"Tanniramadi",
    "wof:placetype":"locality",
    "wof:population":230
},
  "geometry": {"coordinates":[74.53809699999999,13.966275],"type":"Point"}
}