{
  "type": "Feature",
  "properties": {
    "gn:admin1_code":"16",
    "gn:admin2_code":"505.0",
    "gn:asciiname":"Kitari",
    "gn:country_code":"IN",
    "gn:dem":248,
    "gn:feature_class":"P",
    "gn:feature_code":"PPL",
    "gn:name":"Kit\u0101ri",
    "gn:population":0,
    "gn:timezone":"Asia/Kolkata",
    "iso:country":"IN",
    "ks:ks_alt_nam":"Kit\u0101ri",
    "ks:ks_name":"Kitari",
    "ks:ks_pop":140,
    "ks:ks_type":"VILLAGE",
    "name:eng_x_preferred":[
        "Kitari"
    ],
    "name:eng_x_variant":[
        "Kit\u0101ri"
    ],
    "wof:name":"Kitari",
    "wof:placetype":"locality",
    "wof:population":140
},
  "geometry": {"coordinates":[79.52046900000001,20.858565],"type":"Point"}
}