{
  "type": "Feature",
  "properties": {
    "gn:admin1_code":"35",
    "gn:admin2_code":"426.0",
    "gn:asciiname":"Ghutehi",
    "gn:country_code":"IN",
    "gn:dem":462,
    "gn:feature_class":"P",
    "gn:feature_code":"PPL",
    "gn:name":"Ghutehi",
    "gn:population":0,
    "gn:timezone":"Asia/Kolkata",
    "iso:country":"IN",
    "ks:ks_name":"Ghutehi",
    "ks:ks_pop":271,
    "ks:ks_type":"VILLAGE",
    "name:eng_x_preferred":[
        "Ghutehi"
    ],
    "wof:name":"Ghutehi",
    "wof:placetype":"locality",
    "wof:population":271
},
  "geometry": {"coordinates":[79.92042600000001,24.013227],"type":"Point"}
}