{
  "type": "Feature",
  "properties": {
    "iso:country":"IN",
    "ks:ks_name":"Gohnia",
    "ks:ks_pop":240,
    "ks:ks_type":"HABITATION",
    "name:eng_x_preferred":[
        "Gohnia"
    ],
    "wof:name":"Gohnia",
    "wof:placetype":"locality",
    "wof:population":240
},
  "geometry": {"coordinates":[80.97207400000001,27.873081],"type":"Point"}
}