{
  "type": "Feature",
  "properties": {
    "gn:admin1_code":"11.0",
    "gn:admin2_code":"26.0",
    "gn:asciiname":"Mathui",
    "gn:country_code":"IN",
    "gn:dem":1821,
    "gn:feature_class":"P",
    "gn:feature_code":"PPL",
    "gn:name":"Mathui",
    "gn:population":0,
    "gn:timezone":"Asia/Kolkata",
    "iso:country":"IN",
    "wof:name":"Mathui",
    "wof:placetype":"locality"
},
  "geometry": {"coordinates":[77.36736999999999,31.48115],"type":"Point"}
}