{
  "type": "Feature",
  "properties": {
    "iso:country":"IN",
    "ks:ks_name":"Tirugatirallu",
    "ks:ks_pop":152,
    "ks:ks_type":"HABITATION",
    "name:eng_x_preferred":[
        "Tirugatirallu"
    ],
    "wof:name":"Tirugatirallu",
    "wof:placetype":"locality",
    "wof:population":152
},
  "geometry": {"coordinates":[81.655394,17.478139],"type":"Point"}
}