{
  "type": "Feature",
  "properties": {
    "gn:admin1_code":"12.0",
    "gn:asciiname":"Sambah",
    "gn:country_code":"IN",
    "gn:dem":488,
    "gn:feature_class":"P",
    "gn:feature_code":"PPL",
    "gn:name":"Samb\u0101h",
    "gn:population":0,
    "gn:timezone":"Asia/Kolkata",
    "iso:country":"IN",
    "wof:name":"Sambah",
    "wof:placetype":"locality"
},
  "geometry": {"coordinates":[74.33333,33.06111],"type":"Point"}
}