{
  "type": "Feature",
  "properties": {
    "iso:country":"IN",
    "ks:ks_name":"Chakdehi",
    "ks:ks_pop":630,
    "ks:ks_type":"VILLAGE",
    "name:eng_x_preferred":[
        "Chakdehi"
    ],
    "wof:name":"Chakdehi",
    "wof:placetype":"locality",
    "wof:population":630
},
  "geometry": {"coordinates":[82.794432,23.835513],"type":"Point"}
}