{
  "type": "Feature",
  "properties": {
    "iso:country":"IN",
    "ks:ks_name":"Kakkad S",
    "ks:ks_pop":1012,
    "ks:ks_type":"HABITATION",
    "name:eng_x_preferred":[
        "Kakkad S"
    ],
    "wof:name":"Kakkad S",
    "wof:placetype":"locality",
    "wof:population":1012
},
  "geometry": {"coordinates":[75.962091,11.494584],"type":"Point"}
}