{
  "type": "Feature",
  "properties": {
    "iso:country":"IN",
    "ks:ks_name":"Jorapokhar",
    "ks:ks_pop":378,
    "ks:ks_type":"VILLAGE",
    "ks:ks_uagg_main":0,
    "name:eng_x_preferred":[
        "Jorapokhar"
    ],
    "name:hin_x_preferred":[
        "\u091c\u094b\u0930\u093e\u092a\u094b\u0916\u0930"
    ],
    "wof:name":"Jorapokhar",
    "wof:placetype":"neighbourhood",
    "wof:population":378
},
  "geometry": {"coordinates":[85.46008,22.587032],"type":"Point"}
}