{
  "type": "Feature",
  "properties": {
    "iso:country":"IN",
    "ks:ks_name":"Fularakot",
    "ks:ks_pop":333,
    "ks:ks_type":"HABITATION",
    "name:eng_x_preferred":[
        "Fularakot"
    ],
    "wof:name":"Fularakot",
    "wof:placetype":"locality",
    "wof:population":333
},
  "geometry": {"coordinates":[79.882631,29.451918],"type":"Point"}
}