{
  "type": "Feature",
  "properties": {
    "iso:country":"IN",
    "ks:ks_name":"Padiyane Yemmemadu Masque",
    "ks:ks_pop":100,
    "ks:ks_type":"HABITATION",
    "name:eng_x_preferred":[
        "Padiyane Yemmemadu Masque"
    ],
    "wof:name":"Padiyane Yemmemadu Masque",
    "wof:placetype":"locality",
    "wof:population":100
},
  "geometry": {"coordinates":[75.647778,12.328889],"type":"Point"}
}