{
  "type": "Feature",
  "properties": {
    "iso:country":"IN",
    "ks:ks_name":"Berhampur",
    "ks:ks_pop":790,
    "ks:ks_type":"VILLAGE",
    "ks:ks_uagg_main":0,
    "name:eng_x_preferred":[
        "Berhampur"
    ],
    "wof:name":"Berhampur",
    "wof:placetype":"neighbourhood",
    "wof:population":790
},
  "geometry": {"coordinates":[86.38334999999999,21.207877],"type":"Point"}
}