{
  "type": "Feature",
  "properties": {
    "iso:country":"IN",
    "ks:ks_name":"Gorasara Panditan",
    "ks:ks_pop":65,
    "ks:ks_type":"HABITATION",
    "name:eng_x_preferred":[
        "Gorasara Panditan"
    ],
    "wof:name":"Gorasara Panditan",
    "wof:placetype":"locality",
    "wof:population":65
},
  "geometry": {"coordinates":[83.641175,26.057397],"type":"Point"}
}