{
  "type": "Feature",
  "properties": {
    "gn:admin1_code":"35.0",
    "gn:admin2_code":"466.0",
    "gn:asciiname":"Kesun",
    "gn:country_code":"IN",
    "gn:dem":263,
    "gn:feature_class":"P",
    "gn:feature_code":"PPL",
    "gn:name":"Kes\u016bn",
    "gn:population":0,
    "gn:timezone":"Asia/Kolkata",
    "iso:country":"IN",
    "name:hye_x_preferred":[
        "\u0554\u0565\u057d\u0578\u0582\u0576"
    ],
    "wof:name":"Kesun",
    "wof:placetype":"neighbourhood"
},
  "geometry": {"coordinates":[76.32093999999999,22.00033],"type":"Point"}
}