{
  "type": "Feature",
  "properties": {
    "iso:country":"IN",
    "ks:ks_name":"Mahaldar Tola",
    "ks:ks_pop":144,
    "ks:ks_type":"HABITATION",
    "ks:ks_uagg_main":0,
    "name:eng_x_preferred":[
        "Mahaldar Tola"
    ],
    "wof:name":"Mahaldar Tola",
    "wof:placetype":"neighbourhood",
    "wof:population":144
},
  "geometry": {"coordinates":[87.655821,26.013452],"type":"Point"}
}