{
  "type": "Feature",
  "properties": {
    "gn:admin1_code":"37",
    "gn:admin2_code":"406.0",
    "gn:asciiname":"Rigwar",
    "gn:country_code":"IN",
    "gn:dem":361,
    "gn:feature_class":"P",
    "gn:feature_code":"PPL",
    "gn:name":"Rigw\u0101r",
    "gn:population":0,
    "gn:timezone":"Asia/Kolkata",
    "iso:country":"IN",
    "ks:ks_alt_nam":"Rigw\u0101r",
    "ks:ks_name":"Rigwar",
    "ks:ks_type":"VILLAGE",
    "ks:ks_uagg_main":0,
    "name:eng_x_preferred":[
        "Rigwar"
    ],
    "name:eng_x_variant":[
        "Rigw\u0101r"
    ],
    "wof:name":"Rigwar",
    "wof:placetype":"neighbourhood"
},
  "geometry": {"coordinates":[82.13079999999999,22.425277],"type":"Point"}
}