{
  "type": "Feature",
  "properties": {
    "gn:admin1_code":"19.0",
    "gn:admin2_code":"584.0",
    "gn:asciiname":"Balgondanhalli",
    "gn:country_code":"IN",
    "gn:dem":651,
    "gn:feature_class":"P",
    "gn:feature_code":"PPL",
    "gn:name":"Balgondanhalli",
    "gn:population":0,
    "gn:timezone":"Asia/Kolkata",
    "iso:country":"IN",
    "ks:ks_name":"Balagondanahalli",
    "ks:ks_pop":101,
    "ks:ks_type":"VILLAGE",
    "name:eng_x_preferred":[
        "Balagondanahalli"
    ],
    "name:eng_x_variant":[
        "Balgondanhalli"
    ],
    "wof:name":"Balagondanahalli",
    "wof:placetype":"locality",
    "wof:population":101
},
  "geometry": {"coordinates":[77.586573,12.367576],"type":"Point"}
}