{
  "type": "Feature",
  "properties": {
    "iso:country":"IN",
    "ks:ks_name":"Neguwan",
    "ks:ks_pop":685,
    "ks:ks_type":"VILLAGE",
    "ks:ks_uagg_main":0,
    "name:eng_x_preferred":[
        "Neguwan"
    ],
    "wof:name":"Neguwan",
    "wof:placetype":"neighbourhood",
    "wof:population":685
},
  "geometry": {"coordinates":[78.760744,25.382989],"type":"Point"}
}