{
  "type": "Feature",
  "properties": {
    "iso:country":"IN",
    "ks:ks_alt_nam":"kullamullakandy mukku",
    "ks:ks_name":"Kullamullakandy Mukku",
    "ks:ks_pop":345,
    "ks:ks_type":"HABITATION",
    "name:eng_x_preferred":[
        "Kullamullakandy Mukku"
    ],
    "wof:name":"Kullamullakandy Mukku",
    "wof:placetype":"locality",
    "wof:population":345
},
  "geometry": {"coordinates":[75.754215,11.607628],"type":"Point"}
}