{
  "type": "Feature",
  "properties": {
    "iso:country":"IN",
    "ks:ks_name":"Kamiladaspur",
    "ks:ks_pop":194,
    "ks:ks_type":"VILLAGE",
    "ks:ks_uagg_main":0,
    "name:eng_x_preferred":[
        "Kamiladaspur"
    ],
    "wof:name":"Kamiladaspur",
    "wof:placetype":"neighbourhood",
    "wof:population":194
},
  "geometry": {"coordinates":[86.33186000000001,20.498113],"type":"Point"}
}