{
  "type": "Feature",
  "properties": {
    "gn:admin1_code":"38",
    "gn:admin2_code":"358.0",
    "gn:asciiname":"Nakhila",
    "gn:country_code":"IN",
    "gn:dem":167,
    "gn:feature_class":"P",
    "gn:feature_code":"PPL",
    "gn:name":"Nakhila",
    "gn:population":0,
    "gn:timezone":"Asia/Kolkata",
    "iso:country":"IN",
    "ks:ks_name":"Nokhila",
    "ks:ks_pop":1042,
    "ks:ks_type":"VILLAGE",
    "name:eng_x_preferred":[
        "Nokhila"
    ],
    "name:eng_x_variant":[
        "Nakhila"
    ],
    "wof:name":"Nokhila",
    "wof:placetype":"locality",
    "wof:population":1042
},
  "geometry": {"coordinates":[83.93206600000001,24.459325],"type":"Point"}
}