{
  "type": "Feature",
  "properties": {
    "gn:admin1_code":"19.0",
    "gn:admin2_code":"574.0",
    "gn:asciiname":"Mellahalli",
    "gn:country_code":"IN",
    "gn:dem":918,
    "gn:feature_class":"P",
    "gn:feature_code":"PPL",
    "gn:name":"Mellahalli",
    "gn:population":0,
    "gn:timezone":"Asia/Kolkata",
    "iso:country":"IN",
    "name:vie_x_preferred":[
        "Mellahalli"
    ],
    "wof:name":"Mellahalli",
    "wof:placetype":"locality"
},
  "geometry": {"coordinates":[76.24248,12.93933],"type":"Point"}
}