{
  "type": "Feature",
  "properties": {
    "iso:country":"IN",
    "ks:ks_name":"Anara",
    "ks:ks_pop":743,
    "ks:ks_type":"VILLAGE",
    "ks:ks_uagg_main":0,
    "name:eng_x_preferred":[
        "Anara"
    ],
    "wof:name":"Anara",
    "wof:placetype":"neighbourhood",
    "wof:population":743
},
  "geometry": {"coordinates":[86.951142,22.77154],"type":"Point"}
}