{
  "type": "Feature",
  "properties": {
    "iso:country":"IN",
    "ks:ks_alt_nam":"tankkunnu",
    "ks:ks_name":"Tankkunnu",
    "ks:ks_pop":260,
    "ks:ks_type":"HABITATION",
    "name:eng_x_preferred":[
        "Tankkunnu"
    ],
    "wof:name":"Tankkunnu",
    "wof:placetype":"locality",
    "wof:population":260
},
  "geometry": {"coordinates":[77.058511,9.923991],"type":"Point"}
}