{
  "type": "Feature",
  "properties": {
    "gn:admin1_code":"34.0",
    "gn:admin2_code":"218.0",
    "gn:asciiname":"Gahilapur",
    "gn:country_code":"IN",
    "gn:dem":67,
    "gn:feature_class":"P",
    "gn:feature_code":"PPL",
    "gn:name":"Gahil\u0101pur",
    "gn:population":0,
    "gn:timezone":"Asia/Kolkata",
    "iso:country":"IN",
    "ks:ks_alt_nam":"Gahil\u0101pur",
    "ks:ks_name":"Gahilapur",
    "ks:ks_pop":351,
    "ks:ks_type":"VILLAGE",
    "ks:ks_uagg_main":0,
    "name:eng_x_preferred":[
        "Gahilapur"
    ],
    "name:eng_x_variant":[
        "Gahil\u0101pur"
    ],
    "wof:name":"Gahilapur",
    "wof:placetype":"neighbourhood",
    "wof:population":351
},
  "geometry": {"coordinates":[84.19968,26.095969],"type":"Point"}
}