{
  "type": "Feature",
  "properties": {
    "iso:country":"IN",
    "ks:ks_alt_nam":"Barkurwa dharkar tola",
    "ks:ks_name":"Barkurwa Dharkar Tola",
    "ks:ks_pop":417,
    "ks:ks_type":"HABITATION",
    "ks:ks_uagg_main":0,
    "name:eng_x_preferred":[
        "Barkurwa Dharkar Tola"
    ],
    "wof:name":"Barkurwa Dharkar Tola",
    "wof:placetype":"neighbourhood",
    "wof:population":417
},
  "geometry": {"coordinates":[87.40210500000001,26.275778],"type":"Point"}
}