{
  "type": "Feature",
  "properties": {
    "iso:country":"IN",
    "ks:ks_name":"Yerrayyapeta",
    "ks:ks_pop":1077,
    "ks:ks_type":"HABITATION",
    "name:eng_x_preferred":[
        "Yerrayyapeta"
    ],
    "wof:name":"Yerrayyapeta",
    "wof:placetype":"locality",
    "wof:population":1077
},
  "geometry": {"coordinates":[82.51626400000001,17.24049],"type":"Point"}
}