{
  "type": "Feature",
  "properties": {
    "gn:admin1_code":"25.0",
    "gn:admin2_code":"633",
    "gn:asciiname":"Avanashipalaiyam",
    "gn:country_code":"IN",
    "gn:dem":334,
    "gn:feature_class":"P",
    "gn:feature_code":"PPL",
    "gn:name":"Avan\u0101ship\u0101laiyam",
    "gn:population":0,
    "gn:timezone":"Asia/Kolkata",
    "iso:country":"IN",
    "wof:name":"Avanashipalaiyam",
    "wof:placetype":"locality"
},
  "geometry": {"coordinates":[77.43523,10.96957],"type":"Point"}
}