{
  "type": "Feature",
  "properties": {
    "gn:admin1_code":"24.0",
    "gn:admin2_code":"130.0",
    "gn:asciiname":"Rajo",
    "gn:country_code":"IN",
    "gn:dem":294,
    "gn:feature_class":"P",
    "gn:feature_code":"PPL",
    "gn:name":"Rajo",
    "gn:population":0,
    "gn:timezone":"Asia/Kolkata",
    "iso:country":"IN",
    "name:fra_x_preferred":[
        "Rajo"
    ],
    "name:srp_x_preferred":[
        "\u0420\u0430\u0458\u043e"
    ],
    "wof:name":"Rajo",
    "wof:placetype":"locality"
},
  "geometry": {"coordinates":[73.7809,24.00436],"type":"Point"}
}