{
  "type": "Feature",
  "properties": {
    "iso:country":"IN",
    "ks:ks_name":"Channamalam",
    "ks:ks_pop":684,
    "ks:ks_type":"HABITATION",
    "name:eng_x_preferred":[
        "Channamalam"
    ],
    "wof:name":"Channamalam",
    "wof:placetype":"locality",
    "wof:population":684
},
  "geometry": {"coordinates":[77.59775999999999,12.487901],"type":"Point"}
}