{
  "type": "Feature",
  "properties": {
    "iso:country":"IN",
    "ks:ks_name":"Veerichettipatti",
    "ks:ks_pop":360,
    "ks:ks_type":"HABITATION",
    "name:eng_x_preferred":[
        "Veerichettipatti"
    ],
    "wof:name":"Veerichettipatti",
    "wof:placetype":"locality",
    "wof:population":360
},
  "geometry": {"coordinates":[78.15914600000001,12.075206],"type":"Point"}
}