{
  "type": "Feature",
  "properties": {
    "iso:country":"IN",
    "ks:ks_name":"Rasaniya",
    "ks:ks_pop":177,
    "ks:ks_type":"HABITATION",
    "name:eng_x_preferred":[
        "Rasaniya"
    ],
    "wof:name":"Rasaniya",
    "wof:placetype":"locality",
    "wof:population":177
},
  "geometry": {"coordinates":[75.01314000000001,22.972882],"type":"Point"}
}