{
  "type": "Feature",
  "properties": {
    "iso:country":"IN",
    "ks:ks_name":"Nirmalacheri",
    "ks:ks_pop":45,
    "ks:ks_type":"HABITATION",
    "name:eng_x_preferred":[
        "Nirmalacheri"
    ],
    "wof:name":"Nirmalacheri",
    "wof:placetype":"locality",
    "wof:population":45
},
  "geometry": {"coordinates":[79.565692,10.722473],"type":"Point"}
}