{
  "type": "Feature",
  "properties": {
    "iso:country":"IN",
    "ks:ks_name":"Nalapeepla",
    "ks:ks_pop":562,
    "ks:ks_type":"VILLAGE",
    "name:eng_x_preferred":[
        "Nalapeepla"
    ],
    "wof:name":"Nalapeepla",
    "wof:placetype":"locality",
    "wof:population":562
},
  "geometry": {"coordinates":[73.527,24.13195],"type":"Point"}
}