{
  "type": "Feature",
  "properties": {
    "gn:admin1_code":"23.0",
    "gn:admin2_code":"041",
    "gn:asciiname":"Karaudian",
    "gn:country_code":"IN",
    "gn:dem":255,
    "gn:feature_class":"P",
    "gn:feature_code":"PPL",
    "gn:name":"Karaudi\u0101n",
    "gn:population":0,
    "gn:timezone":"Asia/Kolkata",
    "iso:country":"IN",
    "ks:ks_alt_nam":"Karaudi\u0101n",
    "ks:ks_name":"Karaudian",
    "ks:ks_type":"VILLAGE",
    "ks:ks_uagg_main":0,
    "name:eng_x_preferred":[
        "Karaudian"
    ],
    "name:eng_x_variant":[
        "Karaudi\u0101n"
    ],
    "name:und_x_variant":[
        "Karaundia",
        "Karaudi\u0101n"
    ],
    "wof:name":"Karaudian",
    "wof:placetype":"neighbourhood"
},
  "geometry": {"coordinates":[76.080173,30.682195],"type":"Point"}
}