{
  "type": "Feature",
  "properties": {
    "iso:country":"IN",
    "ks:ks_name":"Teerajpur",
    "ks:ks_pop":252,
    "ks:ks_type":"VILLAGE",
    "name:eng_x_preferred":[
        "Teerajpur"
    ],
    "wof:name":"Teerajpur",
    "wof:placetype":"locality",
    "wof:population":252
},
  "geometry": {"coordinates":[78.101249,26.895885],"type":"Point"}
}