{
  "type": "Feature",
  "properties": {
    "iso:country":"IN",
    "ks:ks_name":"Keshai Dighi",
    "ks:ks_pop":803,
    "ks:ks_type":"VILLAGE",
    "ks:ks_uagg_main":0,
    "name:eng_x_preferred":[
        "Keshai Dighi"
    ],
    "wof:name":"Keshai Dighi",
    "wof:placetype":"neighbourhood",
    "wof:population":803
},
  "geometry": {"coordinates":[87.724495,22.005404],"type":"Point"}
}