{
  "type": "Feature",
  "properties": {
    "gn:admin1_code":"9.0",
    "gn:admin2_code":"490",
    "gn:asciiname":"Delwara",
    "gn:country_code":"IN",
    "gn:dem":8,
    "gn:feature_class":"P",
    "gn:feature_code":"PPL",
    "gn:name":"Delwara",
    "gn:population":0,
    "gn:timezone":"Asia/Kolkata",
    "iso:country":"IN",
    "wof:name":"Delwara",
    "wof:placetype":"locality"
},
  "geometry": {"coordinates":[72.83598000000001,20.97964],"type":"Point"}
}