{
  "type": "Feature",
  "properties": {
    "iso:country":"IN",
    "ks:ks_name":"Tamtiya",
    "ks:ks_pop":388,
    "ks:ks_type":"VILLAGE",
    "name:eng_x_preferred":[
        "Tamtiya"
    ],
    "wof:name":"Tamtiya",
    "wof:placetype":"locality",
    "wof:population":388
},
  "geometry": {"coordinates":[74.71878100000001,23.531381],"type":"Point"}
}