{
  "type": "Feature",
  "properties": {
    "iso:country":"IN",
    "ks:ks_name":"Banyan Purwa",
    "ks:ks_pop":130,
    "ks:ks_type":"HABITATION",
    "name:eng_x_preferred":[
        "Banyan Purwa"
    ],
    "wof:name":"Banyan Purwa",
    "wof:placetype":"locality",
    "wof:population":130
},
  "geometry": {"coordinates":[81.725525,27.314988],"type":"Point"}
}