{
  "type": "Feature",
  "properties": {
    "iso:country":"IN",
    "ks:ks_name":"Girwarganj",
    "ks:ks_pop":1006,
    "ks:ks_type":"VILLAGE",
    "name:eng_x_preferred":[
        "Girwarganj"
    ],
    "wof:name":"Girwarganj",
    "wof:placetype":"locality",
    "wof:population":1006
},
  "geometry": {"coordinates":[83.45584599999999,23.640079],"type":"Point"}
}