{
  "type": "Feature",
  "properties": {
    "iso:country":"IN",
    "ks:ks_name":"Nagapur",
    "ks:ks_pop":1597,
    "ks:ks_type":"HABITATION",
    "name:eng_x_preferred":[
        "Nagapur"
    ],
    "wof:name":"Nagapur",
    "wof:placetype":"locality",
    "wof:population":1597
},
  "geometry": {"coordinates":[80.54083300000001,26.285556],"type":"Point"}
}