{
  "type": "Feature",
  "properties": {
    "gn:admin1_code":"19.0",
    "gn:admin2_code":"574.0",
    "gn:asciiname":"Kunarhalli",
    "gn:country_code":"IN",
    "gn:dem":925,
    "gn:feature_class":"P",
    "gn:feature_code":"PPL",
    "gn:name":"Kunarhalli",
    "gn:population":0,
    "gn:timezone":"Asia/Kolkata",
    "iso:country":"IN",
    "wof:name":"Kunarhalli",
    "wof:placetype":"locality"
},
  "geometry": {"coordinates":[75.90170000000001,12.84322],"type":"Point"}
}