{
  "type": "Feature",
  "properties": {
    "gn:admin1_code":"40.0",
    "gn:admin2_code":"537.0",
    "gn:asciiname":"Mandapalli",
    "gn:country_code":"IN",
    "gn:dem":595,
    "gn:feature_class":"P",
    "gn:feature_code":"PPL",
    "gn:name":"Mandapalli",
    "gn:population":0,
    "gn:timezone":"Asia/Kolkata",
    "iso:country":"IN",
    "wof:name":"Mandapalli",
    "wof:placetype":"locality"
},
  "geometry": {"coordinates":[78.53844000000002,17.5664],"type":"Point"}
}