{
  "type": "Feature",
  "properties": {
    "iso:country":"IN",
    "ks:ks_name":"Thachampilli",
    "ks:ks_pop":554,
    "ks:ks_type":"HABITATION",
    "ks:ks_uagg_main":0,
    "name:eng_x_preferred":[
        "Thachampilli"
    ],
    "wof:name":"Thachampilli",
    "wof:placetype":"neighbourhood",
    "wof:population":554
},
  "geometry": {"coordinates":[76.165783,10.492993],"type":"Point"}
}