{
  "type": "Feature",
  "properties": {
    "gn:admin1_code":"21.0",
    "gn:admin2_code":"398.0",
    "gn:asciiname":"Morichimalo",
    "gn:country_code":"IN",
    "gn:dem":961,
    "gn:feature_class":"P",
    "gn:feature_code":"PPL",
    "gn:name":"Morichim\u0101lo",
    "gn:population":0,
    "gn:timezone":"Asia/Kolkata",
    "iso:country":"IN",
    "wof:name":"Morichimalo",
    "wof:placetype":"locality"
},
  "geometry": {"coordinates":[82.98862,18.83721],"type":"Point"}
}