{
  "type": "Feature",
  "properties": {
    "gn:admin1_code":"12.0",
    "gn:admin2_code":"18.0",
    "gn:asciiname":"Hadar",
    "gn:country_code":"IN",
    "gn:dem":2552,
    "gn:feature_class":"P",
    "gn:feature_code":"PPL",
    "gn:name":"Had\u0101r",
    "gn:population":0,
    "gn:timezone":"Asia/Kolkata",
    "iso:country":"IN",
    "name:fra_x_preferred":[
        "Hadar"
    ],
    "name:heb_x_preferred":[
        "\u05d4\u05d3\u05e8"
    ],
    "name:ita_x_preferred":[
        "Hadar"
    ],
    "name:nld_x_preferred":[
        "Hadar"
    ],
    "name:pol_x_preferred":[
        "Hadar"
    ],
    "name:por_x_preferred":[
        "Hadar"
    ],
    "name:slk_x_preferred":[
        "Hadar"
    ],
    "name:slv_x_preferred":[
        "Hadar"
    ],
    "name:spa_x_preferred":[
        "Hadar"
    ],
    "name:swe_x_preferred":[
        "Hadar"
    ],
    "wof:name":"Hadar",
    "wof:placetype":"locality"
},
  "geometry": {"coordinates":[75.7287,33.26458],"type":"Point"}
}