{
  "type": "Feature",
  "properties": {
    "iso:country":"IN",
    "ks:ks_name":"Ramdohar",
    "ks:ks_pop":244,
    "ks:ks_type":"HABITATION",
    "name:eng_x_preferred":[
        "Ramdohar"
    ],
    "wof:name":"Ramdohar",
    "wof:placetype":"locality",
    "wof:population":244
},
  "geometry": {"coordinates":[84.537257,24.754773],"type":"Point"}
}