{
  "type": "Feature",
  "properties": {
    "gn:admin1_code":"12.0",
    "gn:admin2_code":"1.0",
    "gn:asciiname":"Mushnar",
    "gn:country_code":"IN",
    "gn:dem":2843,
    "gn:feature_class":"P",
    "gn:feature_code":"PPL",
    "gn:name":"Mushn\u0101r",
    "gn:population":0,
    "gn:timezone":"Asia/Kolkata",
    "iso:country":"IN",
    "wof:name":"Mushnar",
    "wof:placetype":"locality"
},
  "geometry": {"coordinates":[74.43814999999999,34.57818],"type":"Point"}
}