{
  "type": "Feature",
  "properties": {
    "iso:country":"IN",
    "ks:ks_name":"Ahiyapur",
    "ks:ks_pop":101,
    "ks:ks_type":"VILLAGE",
    "name:eng_x_preferred":[
        "Ahiyapur"
    ],
    "wof:name":"Ahiyapur",
    "wof:placetype":"locality",
    "wof:population":101
},
  "geometry": {"coordinates":[82.400493,25.651168],"type":"Point"}
}