{
  "type": "Feature",
  "properties": {
    "iso:country":"IN",
    "ks:ks_alt_nam":"Naharpura giri",
    "ks:ks_name":"Naharpura Giri",
    "ks:ks_pop":1706,
    "ks:ks_type":"HABITATION",
    "name:eng_x_preferred":[
        "Naharpura Giri"
    ],
    "wof:name":"Naharpura Giri",
    "wof:placetype":"locality",
    "wof:population":1706
},
  "geometry": {"coordinates":[74.17998299999999,26.190492],"type":"Point"}
}