{
  "type": "Feature",
  "properties": {
    "iso:country":"IN",
    "ks:ks_alt_nam":"SAVARO Chauraha",
    "ks:ks_name":"Savaro Chauraha",
    "ks:ks_pop":90,
    "ks:ks_type":"HABITATION",
    "ks:ks_uagg_main":0,
    "name:eng_x_preferred":[
        "Savaro Chauraha"
    ],
    "wof:name":"Savaro Chauraha",
    "wof:placetype":"neighbourhood",
    "wof:population":90
},
  "geometry": {"coordinates":[81.381113,25.525202],"type":"Point"}
}