{
  "type": "Feature",
  "properties": {
    "iso:country":"IN",
    "ks:ks_name":"Chudanga",
    "ks:ks_pop":471,
    "ks:ks_type":"VILLAGE",
    "name:eng_x_preferred":[
        "Chudanga"
    ],
    "wof:name":"Chudanga",
    "wof:placetype":"locality",
    "wof:population":471
},
  "geometry": {"coordinates":[85.81614999999999,20.421708],"type":"Point"}
}