{
  "type": "Feature",
  "properties": {
    "iso:country":"IN",
    "ks:ks_name":"Tanajwa",
    "ks:ks_pop":330,
    "ks:ks_type":"HABITATION",
    "name:eng_x_preferred":[
        "Tanajwa"
    ],
    "wof:name":"Tanajwa",
    "wof:placetype":"locality",
    "wof:population":330
},
  "geometry": {"coordinates":[82.992102,27.241069],"type":"Point"}
}