{
  "type": "Feature",
  "properties": {
    "iso:country":"IN",
    "ks:ks_name":"Anantapur",
    "ks:ks_pop":702,
    "ks:ks_type":"VILLAGE",
    "name:eng_x_preferred":[
        "Anantapur"
    ],
    "wof:name":"Anantapur",
    "wof:placetype":"locality",
    "wof:population":702
},
  "geometry": {"coordinates":[86.78308,20.719196],"type":"Point"}
}