{
  "type": "Feature",
  "properties": {
    "iso:country":"IN",
    "ks:ks_name":"Mochi Tola",
    "ks:ks_pop":123,
    "ks:ks_type":"HABITATION",
    "ks:ks_uagg_main":0,
    "name:eng_x_preferred":[
        "Mochi Tola"
    ],
    "wof:name":"Mochi Tola",
    "wof:placetype":"neighbourhood",
    "wof:population":123
},
  "geometry": {"coordinates":[86.967192,25.591358],"type":"Point"}
}