{
  "type": "Feature",
  "properties": {
    "gn:admin1_code":"36",
    "gn:admin2_code":"138.0",
    "gn:asciiname":"Gajrauli",
    "gn:country_code":"IN",
    "gn:dem":215,
    "gn:feature_class":"P",
    "gn:feature_code":"PPL",
    "gn:name":"Gajrauli",
    "gn:population":0,
    "gn:timezone":"Asia/Kolkata",
    "iso:country":"IN",
    "ks:ks_name":"Gajrauli",
    "ks:ks_pop":523,
    "ks:ks_type":"VILLAGE",
    "ks:ks_uagg_main":0,
    "name:eng_x_preferred":[
        "Gajrauli"
    ],
    "wof:name":"Gajrauli",
    "wof:placetype":"neighbourhood",
    "wof:population":523
},
  "geometry": {"coordinates":[78.033801,29.203897],"type":"Point"}
}