{
  "type": "Feature",
  "properties": {
    "iso:country":"IN",
    "ks:ks_name":"Nagla Madiya",
    "ks:ks_pop":200,
    "ks:ks_type":"HABITATION",
    "name:eng_x_preferred":[
        "Nagla Madiya"
    ],
    "wof:name":"Nagla Madiya",
    "wof:placetype":"locality",
    "wof:population":200
},
  "geometry": {"coordinates":[77.777531,28.067415],"type":"Point"}
}