{
  "type": "Feature",
  "properties": {
    "iso:country":"IN",
    "ks:ks_name":"Khatibkhar",
    "ks:ks_pop":1175,
    "ks:ks_type":"HABITATION",
    "name:eng_x_preferred":[
        "Khatibkhar"
    ],
    "wof:name":"Khatibkhar",
    "wof:placetype":"locality",
    "wof:population":1175
},
  "geometry": {"coordinates":[72.976904,18.320616],"type":"Point"}
}