{
  "type": "Feature",
  "properties": {
    "iso:country":"IN",
    "ks:ks_name":"Bahora Urf Mahammadpur Chak",
    "ks:ks_pop":495,
    "ks:ks_type":"VILLAGE",
    "name:eng_x_preferred":[
        "Bahora Urf Mahammadpur Chak"
    ],
    "wof:name":"Bahora Urf Mahammadpur Chak",
    "wof:placetype":"locality",
    "wof:population":495
},
  "geometry": {"coordinates":[85.31702199999999,26.120632],"type":"Point"}
}