{
  "type": "Feature",
  "properties": {
    "iso:country":"IN",
    "ks:ks_name":"Wasim Pur",
    "ks:ks_pop":618,
    "ks:ks_type":"HABITATION",
    "ks:ks_uagg_main":0,
    "name:eng_x_preferred":[
        "Wasim Pur"
    ],
    "wof:name":"Wasim Pur",
    "wof:placetype":"neighbourhood",
    "wof:population":618
},
  "geometry": {"coordinates":[79.71853900000001,26.896242],"type":"Point"}
}