{
  "type": "Feature",
  "properties": {
    "gn:admin1_code":"36",
    "gn:admin2_code":"154.0",
    "gn:asciiname":"Supauli",
    "gn:country_code":"IN",
    "gn:dem":131,
    "gn:feature_class":"P",
    "gn:feature_code":"PPL",
    "gn:name":"Supauli",
    "gn:population":0,
    "gn:timezone":"Asia/Kolkata",
    "iso:country":"IN",
    "name:fra_x_preferred":[
        "Supauli"
    ],
    "name:mai_x_preferred":[
        "\u0938\u0941\u092a\u094c\u0932\u0940"
    ],
    "name:nep_x_preferred":[
        "\u0938\u0941\u092a\u094c\u0932\u0940"
    ],
    "name:pol_x_preferred":[
        "Supauli"
    ],
    "wof:name":"Supauli",
    "wof:placetype":"locality"
},
  "geometry": {"coordinates":[81.07075,27.74687],"type":"Point"}
}