{
  "type": "Feature",
  "properties": {
    "iso:country":"IN",
    "ks:ks_name":"Jharmunda",
    "ks:ks_pop":228,
    "ks:ks_type":"HABITATION",
    "name:eng_x_preferred":[
        "Jharmunda"
    ],
    "wof:name":"Jharmunda",
    "wof:placetype":"locality",
    "wof:population":228
},
  "geometry": {"coordinates":[84.031834,22.566654],"type":"Point"}
}