{
  "type": "Feature",
  "properties": {
    "iso:country":"IN",
    "ks:ks_name":"Pillaiyarpatti",
    "ks:ks_pop":297,
    "ks:ks_type":"HABITATION",
    "name:eng_x_preferred":[
        "Pillaiyarpatti"
    ],
    "wof:name":"Pillaiyarpatti",
    "wof:placetype":"locality",
    "wof:population":297
},
  "geometry": {"coordinates":[78.39616700000001,10.246428],"type":"Point"}
}