{
  "type": "Feature",
  "properties": {
    "iso:country":"IN",
    "ks:ks_name":"Aanwari",
    "ks:ks_pop":1439,
    "ks:ks_type":"VILLAGE",
    "name:eng_x_preferred":[
        "Aanwari"
    ],
    "wof:name":"Aanwari",
    "wof:placetype":"locality",
    "wof:population":1439
},
  "geometry": {"coordinates":[81.554518,20.004125],"type":"Point"}
}