{
  "type": "Feature",
  "properties": {
    "iso:country":"IN",
    "ks:ks_name":"Kothapeta",
    "ks:ks_pop":1534,
    "ks:ks_type":"VILLAGE",
    "ks:ks_uagg_main":0,
    "name:eng_x_preferred":[
        "Kothapeta"
    ],
    "wof:name":"Kothapeta",
    "wof:placetype":"neighbourhood",
    "wof:population":1534
},
  "geometry": {"coordinates":[84.150762,18.518507],"type":"Point"}
}