{
  "type": "Feature",
  "properties": {
    "gn:admin1_code":"12.0",
    "gn:admin2_code":"19.0",
    "gn:asciiname":"Adu Banj",
    "gn:country_code":"IN",
    "gn:dem":1536,
    "gn:feature_class":"P",
    "gn:feature_code":"PPL",
    "gn:name":"\u0100du Banj",
    "gn:population":0,
    "gn:timezone":"Asia/Kolkata",
    "iso:country":"IN",
    "wof:name":"Adu Banj",
    "wof:placetype":"locality"
},
  "geometry": {"coordinates":[75.1087,33.04061],"type":"Point"}
}