{
  "type": "Feature",
  "properties": {
    "iso:country":"IN",
    "ks:ks_name":"Kanekarwadi",
    "ks:ks_pop":481,
    "ks:ks_type":"HABITATION",
    "name:eng_x_preferred":[
        "Kanekarwadi"
    ],
    "wof:name":"Kanekarwadi",
    "wof:placetype":"locality",
    "wof:population":481
},
  "geometry": {"coordinates":[73.36138099999999,16.653456],"type":"Point"}
}