{
  "type": "Feature",
  "properties": {
    "iso:country":"IN",
    "ks:ks_name":"Ramtobahan Urf Bishunpurmohan",
    "ks:ks_pop":401,
    "ks:ks_type":"VILLAGE",
    "name:eng_x_preferred":[
        "Ramtobahan Urf Bishunpurmohan"
    ],
    "wof:name":"Ramtobahan Urf Bishunpurmohan",
    "wof:placetype":"locality",
    "wof:population":401
},
  "geometry": {"coordinates":[85.275606,26.247243],"type":"Point"}
}