{
  "type": "Feature",
  "properties": {
    "iso:country":"IN",
    "ks:ks_name":"Gobindapur",
    "ks:ks_pop":2743,
    "ks:ks_type":"VILLAGE",
    "ks:ks_uagg_main":0,
    "name:eng_x_preferred":[
        "Gobindapur"
    ],
    "wof:name":"Gobindapur",
    "wof:placetype":"neighbourhood",
    "wof:population":2743
},
  "geometry": {"coordinates":[86.55540499999999,20.228282],"type":"Point"}
}