{
  "type": "Feature",
  "properties": {
    "gn:admin1_code":"11",
    "gn:admin2_code":"23.0",
    "gn:asciiname":"Saunthari",
    "gn:country_code":"IN",
    "gn:dem":2064,
    "gn:feature_class":"P",
    "gn:feature_code":"PPL",
    "gn:name":"Saunthari",
    "gn:population":0,
    "gn:timezone":"Asia/Kolkata",
    "iso:country":"IN",
    "wof:name":"Saunthari",
    "wof:placetype":"locality"
},
  "geometry": {"coordinates":[76.19481999999998,32.61444],"type":"Point"}
}