{
  "type": "Feature",
  "properties": {
    "iso:country":"IN",
    "ks:ks_name":"Jainagar Piprajoria",
    "ks:ks_pop":976,
    "ks:ks_type":"VILLAGE",
    "name:eng_x_preferred":[
        "Jainagar Piprajoria"
    ],
    "wof:name":"Jainagar Piprajoria",
    "wof:placetype":"locality",
    "wof:population":976
},
  "geometry": {"coordinates":[87.29192,24.708422],"type":"Point"}
}