{
  "type": "Feature",
  "properties": {
    "iso:country":"IN",
    "ks:ks_name":"Dulung",
    "ks:ks_pop":46,
    "ks:ks_type":"HABITATION",
    "name:eng_x_preferred":[
        "Dulung"
    ],
    "wof:name":"Dulung",
    "wof:placetype":"locality",
    "wof:population":46
},
  "geometry": {"coordinates":[93.372848,26.928244],"type":"Point"}
}