{
  "type": "Feature",
  "properties": {
    "gn:admin1_code":"21.0",
    "gn:admin2_code":"396.0",
    "gn:asciiname":"Narangabadi",
    "gn:country_code":"IN",
    "gn:dem":424,
    "gn:feature_class":"P",
    "gn:feature_code":"PPL",
    "gn:name":"Narangab\u0101di",
    "gn:population":0,
    "gn:timezone":"Asia/Kolkata",
    "iso:country":"IN",
    "ks:ks_alt_nam":"Narangab\u0101di",
    "ks:ks_name":"Narangabadi",
    "ks:ks_type":"VILLAGE",
    "name:eng_x_preferred":[
        "Narangabadi"
    ],
    "name:eng_x_variant":[
        "Narangab\u0101di"
    ],
    "wof:name":"Narangabadi",
    "wof:placetype":"locality"
},
  "geometry": {"coordinates":[83.254048,19.381497],"type":"Point"}
}