{
  "type": "Feature",
  "properties": {
    "iso:country":"IN",
    "ks:ks_name":"Chhanaghara",
    "ks:ks_pop":1816,
    "ks:ks_type":"VILLAGE",
    "ks:ks_uagg_main":0,
    "name:eng_x_preferred":[
        "Chhanaghara"
    ],
    "wof:name":"Chhanaghara",
    "wof:placetype":"neighbourhood",
    "wof:population":1816
},
  "geometry": {"coordinates":[85.72512,20.18511],"type":"Point"}
}