{
  "type": "Feature",
  "properties": {
    "iso:country":"IN",
    "ks:ks_name":"Prakarai Para",
    "ks:ks_pop":175,
    "ks:ks_type":"HABITATION",
    "name:eng_x_preferred":[
        "Prakarai Para"
    ],
    "wof:name":"Prakarai Para",
    "wof:placetype":"locality",
    "wof:population":175
},
  "geometry": {"coordinates":[91.897313,23.882281],"type":"Point"}
}