{
  "type": "Feature",
  "properties": {
    "gn:admin1_code":"34.0",
    "gn:admin2_code":"204.0",
    "gn:asciiname":"Madhurapur",
    "gn:country_code":"IN",
    "gn:dem":66,
    "gn:feature_class":"P",
    "gn:feature_code":"PPL",
    "gn:name":"Madhur\u0101pur",
    "gn:population":0,
    "gn:timezone":"Asia/Kolkata",
    "iso:country":"IN",
    "ks:ks_name":"Madhurapur",
    "ks:ks_pop":2994,
    "ks:ks_type":"VILLAGE",
    "ks:ks_uagg_main":0,
    "name:eng_x_preferred":[
        "Madhurapur"
    ],
    "wof:name":"Madhurapur",
    "wof:placetype":"neighbourhood",
    "wof:population":2994
},
  "geometry": {"coordinates":[84.96260100000001,26.441876],"type":"Point"}
}