{
  "type": "Feature",
  "properties": {
    "gn:admin1_code":"35",
    "gn:admin2_code":"425.0",
    "gn:asciiname":"Karri",
    "gn:country_code":"IN",
    "gn:dem":493,
    "gn:feature_class":"P",
    "gn:feature_code":"PPL",
    "gn:name":"Karri",
    "gn:population":0,
    "gn:timezone":"Asia/Kolkata",
    "iso:country":"IN",
    "ks:ks_name":"Karri",
    "ks:ks_pop":297,
    "ks:ks_type":"VILLAGE",
    "name:eng_x_preferred":[
        "Karri"
    ],
    "wof:name":"Karri",
    "wof:placetype":"locality",
    "wof:population":297
},
  "geometry": {"coordinates":[79.273651,24.159884],"type":"Point"}
}