{
  "type": "Feature",
  "properties": {
    "iso:country":"IN",
    "ks:ks_name":"Koothanur",
    "ks:ks_pop":555,
    "ks:ks_type":"HABITATION",
    "name:eng_x_preferred":[
        "Koothanur"
    ],
    "wof:name":"Koothanur",
    "wof:placetype":"locality",
    "wof:population":555
},
  "geometry": {"coordinates":[79.674739,11.007453],"type":"Point"}
}