{
  "type": "Feature",
  "properties": {
    "iso:country":"IN",
    "ks:ks_name":"Hargadi",
    "ks:ks_pop":60,
    "ks:ks_type":"HABITATION",
    "name:eng_x_preferred":[
        "Hargadi"
    ],
    "wof:name":"Hargadi",
    "wof:placetype":"locality",
    "wof:population":60
},
  "geometry": {"coordinates":[81.74172299999999,24.598921],"type":"Point"}
}