{
  "type": "Feature",
  "properties": {
    "gn:admin1_code":"36",
    "gn:admin2_code":"200.0",
    "gn:asciiname":"Randahor",
    "gn:country_code":"IN",
    "gn:dem":351,
    "gn:feature_class":"P",
    "gn:feature_code":"PPL",
    "gn:name":"Randahor",
    "gn:population":0,
    "gn:timezone":"Asia/Kolkata",
    "iso:country":"IN",
    "ks:ks_name":"Ranahor",
    "ks:ks_pop":2429,
    "ks:ks_type":"VILLAGE",
    "name:eng_x_preferred":[
        "Ranahor"
    ],
    "name:eng_x_variant":[
        "Randahor"
    ],
    "wof:name":"Ranahor",
    "wof:placetype":"locality",
    "wof:population":2429
},
  "geometry": {"coordinates":[82.77245499999999,24.263252],"type":"Point"}
}