{
  "type": "Feature",
  "properties": {
    "iso:country":"IN",
    "ks:ks_name":"Bhetua",
    "ks:ks_pop":732,
    "ks:ks_type":"HABITATION",
    "name:eng_x_preferred":[
        "Bhetua"
    ],
    "wof:name":"Bhetua",
    "wof:placetype":"locality",
    "wof:population":732
},
  "geometry": {"coordinates":[81.873931,26.15758],"type":"Point"}
}