{
  "type": "Feature",
  "properties": {
    "gn:admin1_code":"16.0",
    "gn:admin2_code":"530.0",
    "gn:asciiname":"Malvi",
    "gn:country_code":"IN",
    "gn:dem":762,
    "gn:feature_class":"P",
    "gn:feature_code":"PPL",
    "gn:name":"Malvi",
    "gn:population":0,
    "gn:timezone":"Asia/Kolkata",
    "iso:country":"IN",
    "name:fra_x_preferred":[
        "Malvi"
    ],
    "name:kan_x_preferred":[
        "\u0cae\u0cbe\u0cb3\u0ccd\u0cb5\u0cbf"
    ],
    "name:tam_x_preferred":[
        "\u0bae\u0bbe\u0bb2\u0bcd\u0bb5\u0bbf \u0bae\u0bbe\u0b9f\u0bc1"
    ],
    "wof:name":"Malvi",
    "wof:placetype":"locality"
},
  "geometry": {"coordinates":[74.35941,15.78572],"type":"Point"}
}