{
  "type": "Feature",
  "properties": {
    "iso:country":"IN",
    "ks:ks_name":"Nolasahi",
    "ks:ks_pop":565,
    "ks:ks_type":"VILLAGE",
    "name:eng_x_preferred":[
        "Nolasahi"
    ],
    "wof:name":"Nolasahi",
    "wof:placetype":"locality",
    "wof:population":565
},
  "geometry": {"coordinates":[86.342482,20.579137],"type":"Point"}
}