{
  "type": "Feature",
  "properties": {
    "gn:admin1_code":"24",
    "gn:admin2_code":"129.0",
    "gn:asciiname":"Bherupura",
    "gn:country_code":"IN",
    "gn:dem":289,
    "gn:feature_class":"P",
    "gn:feature_code":"PPL",
    "gn:name":"Bher\u016bpura",
    "gn:population":0,
    "gn:timezone":"Asia/Kolkata",
    "iso:country":"IN",
    "wof:name":"Bherupura",
    "wof:placetype":"locality"
},
  "geometry": {"coordinates":[76.41389000000002,24.83162],"type":"Point"}
}