{
  "type": "Feature",
  "properties": {
    "iso:country":"IN",
    "ks:ks_name":"Modumadgu",
    "ks:ks_pop":92,
    "ks:ks_type":"HABITATION",
    "name:eng_x_preferred":[
        "Modumadgu"
    ],
    "wof:name":"Modumadgu",
    "wof:placetype":"locality",
    "wof:population":92
},
  "geometry": {"coordinates":[80.143444,19.191276],"type":"Point"}
}