{
  "type": "Feature",
  "properties": {
    "gn:admin1_code":"7.0",
    "gn:admin2_code":"97.0",
    "gn:asciiname":"Kapas Herd",
    "gn:country_code":"IN",
    "gn:dem":232,
    "gn:feature_class":"P",
    "gn:feature_code":"PPL",
    "gn:name":"K\u0101pas Herd",
    "gn:population":0,
    "gn:timezone":"Asia/Kolkata",
    "iso:country":"IN",
    "wof:name":"Kapas Herd",
    "wof:placetype":"neighbourhood"
},
  "geometry": {"coordinates":[77.08396,28.52614],"type":"Point"}
}