{
  "type": "Feature",
  "properties": {
    "iso:country":"IN",
    "ks:ks_name":"Thimmaganahalli",
    "ks:ks_pop":55,
    "ks:ks_type":"VILLAGE",
    "name:eng_x_preferred":[
        "Thimmaganahalli"
    ],
    "wof:name":"Thimmaganahalli",
    "wof:placetype":"locality",
    "wof:population":55
},
  "geometry": {"coordinates":[77.57086099999999,13.684597],"type":"Point"}
}