{
  "type": "Feature",
  "properties": {
    "iso:country":"IN",
    "ks:ks_name":"Chak Shri Kishanpura No.2",
    "ks:ks_pop":34,
    "ks:ks_type":"VILLAGE",
    "ks:ks_uagg_main":0,
    "name:eng_x_preferred":[
        "Chak Shri Kishanpura No.2"
    ],
    "wof:name":"Chak Shri Kishanpura No.2",
    "wof:placetype":"neighbourhood",
    "wof:population":34
},
  "geometry": {"coordinates":[75.874966,26.661861],"type":"Point"}
}