{
  "type": "Feature",
  "properties": {
    "iso:country":"IN",
    "ks:ks_alt_nam":"PURE ALPI AIWARI",
    "ks:ks_name":"Pure Alpi Aiwari",
    "ks:ks_pop":87,
    "ks:ks_type":"HABITATION",
    "name:eng_x_preferred":[
        "Pure Alpi Aiwari"
    ],
    "wof:name":"Pure Alpi Aiwari",
    "wof:placetype":"locality",
    "wof:population":87
},
  "geometry": {"coordinates":[81.674342,26.393448],"type":"Point"}
}