{
  "type": "Feature",
  "properties": {
    "gn:admin1_code":"19.0",
    "gn:admin2_code":"582.0",
    "gn:asciiname":"Tekahalli",
    "gn:country_code":"IN",
    "gn:dem":866,
    "gn:feature_class":"P",
    "gn:feature_code":"PPL",
    "gn:name":"Tekahalli",
    "gn:population":0,
    "gn:timezone":"Asia/Kolkata",
    "iso:country":"IN",
    "wof:name":"Tekahalli",
    "wof:placetype":"locality"
},
  "geometry": {"coordinates":[77.87398,13.5044],"type":"Point"}
}