{
  "type": "Feature",
  "properties": {
    "iso:country":"IN",
    "ks:ks_name":"Guravwadi",
    "ks:ks_pop":70,
    "ks:ks_type":"HABITATION",
    "name:eng_x_preferred":[
        "Guravwadi"
    ],
    "wof:name":"Guravwadi",
    "wof:placetype":"locality",
    "wof:population":70
},
  "geometry": {"coordinates":[73.488333,17.276389],"type":"Point"}
}