{
  "type": "Feature",
  "properties": {
    "iso:country":"IN",
    "ks:ks_name":"Mahendra",
    "ks:ks_pop":2892,
    "ks:ks_type":"VILLAGE",
    "name:eng_x_preferred":[
        "Mahendra"
    ],
    "wof:name":"Mahendra",
    "wof:placetype":"locality",
    "wof:population":2892
},
  "geometry": {"coordinates":[74.237798,22.574904],"type":"Point"}
}