{
  "type": "Feature",
  "properties": {
    "iso:country":"IN",
    "ks:ks_name":"Barband",
    "ks:ks_pop":626,
    "ks:ks_type":"VILLAGE",
    "name:eng_x_preferred":[
        "Barband"
    ],
    "wof:name":"Barband",
    "wof:placetype":"locality",
    "wof:population":626
},
  "geometry": {"coordinates":[80.406958,25.165555],"type":"Point"}
}