{
  "type": "Feature",
  "properties": {
    "iso:country":"IN",
    "ks:ks_name":"Dahalauda",
    "ks:ks_pop":636,
    "ks:ks_type":"VILLAGE",
    "ks:ks_uagg_main":0,
    "name:eng_x_preferred":[
        "Dahalauda"
    ],
    "wof:name":"Dahalauda",
    "wof:placetype":"neighbourhood",
    "wof:population":636
},
  "geometry": {"coordinates":[87.726945,21.849845],"type":"Point"}
}