{
  "type": "Feature",
  "properties": {
    "iso:country":"IN",
    "ks:ks_name":"Gorada",
    "ks:ks_pop":0,
    "ks:ks_type":"VILLAGE",
    "name:eng_x_preferred":[
        "Gorada"
    ],
    "wof:name":"Gorada",
    "wof:placetype":"locality",
    "wof:population":0
},
  "geometry": {"coordinates":[86.176529,20.129832],"type":"Point"}
}