{
  "type": "Feature",
  "properties": {
    "iso:country":"IN",
    "ks:ks_name":"Sevakalapatti",
    "ks:ks_pop":110,
    "ks:ks_type":"HABITATION",
    "ks:ks_uagg_main":0,
    "name:eng_x_preferred":[
        "Sevakalapatti"
    ],
    "wof:name":"Sevakalapatti",
    "wof:placetype":"neighbourhood",
    "wof:population":110
},
  "geometry": {"coordinates":[78.501833,10.554303],"type":"Point"}
}