{
  "type": "Feature",
  "properties": {
    "iso:country":"IN",
    "ks:ks_name":"Yadavarkudieruppu",
    "ks:ks_pop":907,
    "ks:ks_type":"HABITATION",
    "name:eng_x_preferred":[
        "Yadavarkudieruppu"
    ],
    "wof:name":"Yadavarkudieruppu",
    "wof:placetype":"locality",
    "wof:population":907
},
  "geometry": {"coordinates":[79.602878,12.844218],"type":"Point"}
}