{
  "type": "Feature",
  "properties": {
    "iso:country":"IN",
    "ks:ks_name":"Tengrha Cahk No.4",
    "ks:ks_pop":830,
    "ks:ks_type":"HABITATION",
    "ks:ks_uagg_main":0,
    "name:eng_x_preferred":[
        "Tengrha Cahk No.4"
    ],
    "wof:name":"Tengrha Cahk No.4",
    "wof:placetype":"neighbourhood",
    "wof:population":830
},
  "geometry": {"coordinates":[83.94910900000001,27.148407],"type":"Point"}
}