{
  "type": "Feature",
  "properties": {
    "iso:country":"IN",
    "ks:ks_alt_nam":"Malk\u0101pur",
    "ks:ks_name":"Malkapur",
    "ks:ks_type":"VILLAGE",
    "name:eng_x_preferred":[
        "Malkapur"
    ],
    "name:eng_x_variant":[
        "Malk\u0101pur"
    ],
    "wof:name":"Malkapur",
    "wof:placetype":"locality"
},
  "geometry": {"coordinates":[76.238179,16.35042],"type":"Point"}
}