{
  "type": "Feature",
  "properties": {
    "iso:country":"IN",
    "ks:ks_name":"Galipura Kaval",
    "ks:ks_pop":74,
    "ks:ks_type":"VILLAGE",
    "name:eng_x_preferred":[
        "Galipura Kaval"
    ],
    "wof:name":"Galipura Kaval",
    "wof:placetype":"locality",
    "wof:population":74
},
  "geometry": {"coordinates":[76.199484,12.717233],"type":"Point"}
}