{
  "type": "Feature",
  "properties": {
    "iso:country":"IN",
    "ks:ks_name":"Chilkaguda",
    "ks:ks_pop":840,
    "ks:ks_type":"VILLAGE",
    "name:eng_x_preferred":[
        "Chilkaguda"
    ],
    "wof:name":"Chilkaguda",
    "wof:placetype":"locality",
    "wof:population":840
},
  "geometry": {"coordinates":[83.463311,22.344881],"type":"Point"}
}