{
  "type": "Feature",
  "properties": {
    "iso:country":"IN",
    "ks:ks_name":"Naya Ksai Alias Swargachhinr",
    "ks:ks_pop":193,
    "ks:ks_type":"VILLAGE",
    "name:eng_x_preferred":[
        "Naya Ksai Alias Swargachhinr"
    ],
    "wof:name":"Naya Ksai Alias Swargachhinr",
    "wof:placetype":"locality",
    "wof:population":193
},
  "geometry": {"coordinates":[86.165791,22.587456],"type":"Point"}
}