{
  "type": "Feature",
  "properties": {
    "gn:admin1_code":"10.0",
    "gn:admin2_code":"69.0",
    "gn:asciiname":"Dharara",
    "gn:country_code":"IN",
    "gn:dem":1016,
    "gn:feature_class":"P",
    "gn:feature_code":"PPL",
    "gn:name":"Dh\u0101rara",
    "gn:population":0,
    "gn:timezone":"Asia/Kolkata",
    "iso:country":"IN",
    "ks:ks_alt_nam":"Dh\u0101rara",
    "ks:ks_name":"Dharara",
    "ks:ks_pop":253,
    "ks:ks_type":"VILLAGE",
    "name:eng_x_preferred":[
        "Dharara"
    ],
    "name:eng_x_variant":[
        "Dh\u0101rara"
    ],
    "wof:name":"Dharara",
    "wof:placetype":"locality",
    "wof:population":253
},
  "geometry": {"coordinates":[77.079009,30.724105],"type":"Point"}
}