{
  "type": "Feature",
  "properties": {
    "gn:admin1_code":"2.0",
    "gn:admin2_code":"554.0",
    "gn:asciiname":"Chinnabodanattam",
    "gn:country_code":"IN",
    "gn:dem":253,
    "gn:feature_class":"P",
    "gn:feature_code":"PPL",
    "gn:name":"Chinnabodanattam",
    "gn:population":0,
    "gn:timezone":"Asia/Kolkata",
    "iso:country":"IN",
    "ks:ks_name":"Cinnabodanatham",
    "ks:ks_pop":94,
    "ks:ks_type":"HABITATION",
    "name:eng_x_preferred":[
        "Cinnabodanatham"
    ],
    "name:eng_x_variant":[
        "Chinnabodanattam"
    ],
    "wof:name":"Cinnabodanatham",
    "wof:placetype":"locality",
    "wof:population":94
},
  "geometry": {"coordinates":[79.295185,13.263018],"type":"Point"}
}