{
  "type": "Feature",
  "properties": {
    "iso:country":"IN",
    "ks:ks_name":"Hosabelavanur",
    "ks:ks_pop":528,
    "ks:ks_type":"HABITATION",
    "name:eng_x_preferred":[
        "Hosabelavanur"
    ],
    "wof:name":"Hosabelavanur",
    "wof:placetype":"locality",
    "wof:population":528
},
  "geometry": {"coordinates":[75.933352,14.407869],"type":"Point"}
}