{
  "type": "Feature",
  "properties": {
    "iso:country":"IN",
    "ks:ks_name":"Karaudhai",
    "ks:ks_pop":0,
    "ks:ks_type":"VILLAGE",
    "name:eng_x_preferred":[
        "Karaudhai"
    ],
    "wof:name":"Karaudhai",
    "wof:placetype":"locality",
    "wof:population":0
},
  "geometry": {"coordinates":[81.940056,25.99542],"type":"Point"}
}