{
  "type": "Feature",
  "properties": {
    "iso:country":"IN",
    "ks:ks_name":"Barhi R",
    "ks:ks_pop":943,
    "ks:ks_type":"HABITATION",
    "name:eng_x_preferred":[
        "Barhi R"
    ],
    "wof:name":"Barhi R",
    "wof:placetype":"locality",
    "wof:population":943
},
  "geometry": {"coordinates":[79.97524199999999,23.632504],"type":"Point"}
}