{
  "type": "Feature",
  "properties": {
    "gn:admin1_code":"36.0",
    "gn:admin2_code":"152",
    "gn:asciiname":"Pihani",
    "gn:country_code":"IN",
    "gn:dem":149,
    "gn:feature_class":"P",
    "gn:feature_code":"PPL",
    "gn:name":"Pih\u0101ni",
    "gn:population":0,
    "gn:timezone":"Asia/Kolkata",
    "iso:country":"IN",
    "name:bpy_x_preferred":[
        "\u09aa\u09bf\u09b9\u09be\u09a8\u09bf"
    ],
    "name:ceb_x_preferred":[
        "Pih\u0101ni"
    ],
    "name:hif_x_preferred":[
        "Pihani"
    ],
    "name:hin_x_preferred":[
        "\u092a\u093f\u0939\u093e\u0928\u0940"
    ],
    "name:ita_x_preferred":[
        "Pihani"
    ],
    "name:mlg_x_preferred":[
        "Pihani"
    ],
    "name:msa_x_preferred":[
        "Pihani"
    ],
    "name:nld_x_preferred":[
        "Pihani"
    ],
    "name:ori_x_preferred":[
        "\u0b2a\u0b3f\u0b39\u0b3e\u0b28\u0b3f"
    ],
    "name:pnb_x_preferred":[
        "\u067e\u06c1\u0627\u0646\u06cc"
    ],
    "name:pol_x_preferred":[
        "Pihani"
    ],
    "name:por_x_preferred":[
        "Pihani"
    ],
    "name:swe_x_preferred":[
        "Pih\u0101ni"
    ],
    "name:urd_x_preferred":[
        "\u067e\u06c1\u0627\u0646\u06cc"
    ],
    "name:vie_x_preferred":[
        "Pihani"
    ],
    "name:zho_x_preferred":[
        "\u76ae\u54c8\u5c3c"
    ],
    "wof:name":"Pihani",
    "wof:placetype":"locality"
},
  "geometry": {"coordinates":[79.5611,27.64017],"type":"Point"}
}