{
  "type": "Feature",
  "properties": {
    "gn:admin1_code":"34.0",
    "gn:admin2_code":"232.0",
    "gn:asciiname":"Hansrajpur",
    "gn:country_code":"IN",
    "gn:dem":75,
    "gn:feature_class":"P",
    "gn:feature_code":"PPL",
    "gn:name":"Hansr\u0101jpur",
    "gn:population":0,
    "gn:timezone":"Asia/Kolkata",
    "iso:country":"IN",
    "wof:name":"Hansrajpur",
    "wof:placetype":"locality"
},
  "geometry": {"coordinates":[84.07677,25.37879],"type":"Point"}
}