{
  "type": "Feature",
  "properties": {
    "gn:admin1_code":"34.0",
    "gn:admin2_code":"204.0",
    "gn:asciiname":"Patkhaulia",
    "gn:country_code":"IN",
    "gn:dem":69,
    "gn:feature_class":"P",
    "gn:feature_code":"PPL",
    "gn:name":"Patkhaulia",
    "gn:population":0,
    "gn:timezone":"Asia/Kolkata",
    "iso:country":"IN",
    "ks:ks_name":"Patkhaulia",
    "ks:ks_pop":1226,
    "ks:ks_type":"VILLAGE",
    "name:eng_x_preferred":[
        "Patkhaulia"
    ],
    "wof:name":"Patkhaulia",
    "wof:placetype":"locality",
    "wof:population":1226
},
  "geometry": {"coordinates":[84.835554,26.707157],"type":"Point"}
}