{
  "type": "Feature",
  "properties": {
    "iso:country":"IN",
    "ks:ks_name":"Sukurhuttu",
    "ks:ks_pop":932,
    "ks:ks_type":"VILLAGE",
    "name:eng_x_preferred":[
        "Sukurhuttu"
    ],
    "wof:name":"Sukurhuttu",
    "wof:placetype":"locality",
    "wof:population":932
},
  "geometry": {"coordinates":[85.286772,23.246216],"type":"Point"}
}