{
  "type": "Feature",
  "properties": {
    "iso:country":"IN",
    "ks:ks_alt_nam":"BANSJHAR",
    "ks:ks_name":"Bansjhar",
    "ks:ks_pop":244,
    "ks:ks_type":"HABITATION",
    "name:eng_x_preferred":[
        "Bansjhar"
    ],
    "wof:name":"Bansjhar",
    "wof:placetype":"locality",
    "wof:population":244
},
  "geometry": {"coordinates":[83.779859,22.921826],"type":"Point"}
}