{
  "type": "Feature",
  "properties": {
    "gn:admin1_code":"19.0",
    "gn:admin2_code":"574.0",
    "gn:asciiname":"Godhalli",
    "gn:country_code":"IN",
    "gn:dem":922,
    "gn:feature_class":"P",
    "gn:feature_code":"PPL",
    "gn:name":"Godhalli",
    "gn:population":0,
    "gn:timezone":"Asia/Kolkata",
    "iso:country":"IN",
    "wof:name":"Godhalli",
    "wof:placetype":"locality"
},
  "geometry": {"coordinates":[75.74720000000001,12.70607],"type":"Point"}
}