{
  "type": "Feature",
  "properties": {
    "iso:country":"IN",
    "ks:ks_name":"Muriyad Start Jn4",
    "ks:ks_pop":558,
    "ks:ks_type":"HABITATION",
    "name:eng_x_preferred":[
        "Muriyad Start Jn4"
    ],
    "wof:name":"Muriyad Start Jn4",
    "wof:placetype":"locality",
    "wof:population":558
},
  "geometry": {"coordinates":[76.26514400000001,10.373808],"type":"Point"}
}