{
  "type": "Feature",
  "properties": {
    "iso:country":"IN",
    "ks:ks_name":"Hari Mari",
    "ks:ks_pop":138,
    "ks:ks_type":"VILLAGE",
    "name:eng_x_preferred":[
        "Hari Mari"
    ],
    "wof:name":"Hari Mari",
    "wof:placetype":"locality",
    "wof:population":138
},
  "geometry": {"coordinates":[87.132417,22.056471],"type":"Point"}
}