{
  "type": "Feature",
  "properties": {
    "iso:country":"IN",
    "ks:ks_name":"Vategadde",
    "ks:ks_pop":142,
    "ks:ks_type":"HABITATION",
    "name:eng_x_preferred":[
        "Vategadde"
    ],
    "wof:name":"Vategadde",
    "wof:placetype":"locality",
    "wof:population":142
},
  "geometry": {"coordinates":[74.57377,14.240082],"type":"Point"}
}