{
  "type": "Feature",
  "properties": {
    "iso:country":"IN",
    "ks:ks_name":"Bheemuguda",
    "ks:ks_pop":18,
    "ks:ks_type":"HABITATION",
    "name:eng_x_preferred":[
        "Bheemuguda"
    ],
    "wof:name":"Bheemuguda",
    "wof:placetype":"locality",
    "wof:population":18
},
  "geometry": {"coordinates":[78.90566099999999,19.361878],"type":"Point"}
}