{
  "type": "Feature",
  "properties": {
    "gn:admin1_code":"28.0",
    "gn:admin2_code":"337",
    "gn:asciiname":"Bena",
    "gn:country_code":"IN",
    "gn:dem":8,
    "gn:feature_class":"P",
    "gn:feature_code":"PPL",
    "gn:name":"Bena",
    "gn:population":0,
    "gn:timezone":"Asia/Kolkata",
    "iso:country":"IN",
    "name:cat_x_preferred":[
        "Bena"
    ],
    "name:ceb_x_preferred":[
        "Bena"
    ],
    "name:deu_x_preferred":[
        "Bena"
    ],
    "name:fra_x_preferred":[
        "Bena"
    ],
    "name:hun_x_preferred":[
        "Bena"
    ],
    "name:nld_x_preferred":[
        "Bena"
    ],
    "name:pol_x_preferred":[
        "Bena"
    ],
    "name:por_x_preferred":[
        "Bena"
    ],
    "name:rus_x_preferred":[
        "\u0411\u0438\u043d\u0430"
    ],
    "name:swe_x_preferred":[
        "Bena"
    ],
    "wof:name":"Bena",
    "wof:placetype":"locality"
},
  "geometry": {"coordinates":[88.93611,22.51028],"type":"Point"}
}