{
  "type": "Feature",
  "properties": {
    "gn:admin1_code":"35",
    "gn:admin2_code":"419.0",
    "gn:asciiname":"Pura Gujran",
    "gn:country_code":"IN",
    "gn:dem":165,
    "gn:feature_class":"P",
    "gn:feature_code":"PPL",
    "gn:name":"Pura Gujran",
    "gn:population":0,
    "gn:timezone":"Asia/Kolkata",
    "iso:country":"IN",
    "name:und_x_variant":[
        "Ky\u0101ri ka Pura"
    ],
    "wof:name":"Pura Gujran",
    "wof:placetype":"locality"
},
  "geometry": {"coordinates":[78.2567,26.75397],"type":"Point"}
}