{
  "type": "Feature",
  "properties": {
    "gn:admin1_code":"35.0",
    "gn:admin2_code":"455.0",
    "gn:asciiname":"Sohagpur",
    "gn:country_code":"IN",
    "gn:dem":700,
    "gn:feature_class":"P",
    "gn:feature_code":"PPL",
    "gn:name":"Soh\u0101gpur",
    "gn:population":0,
    "gn:timezone":"Asia/Kolkata",
    "iso:country":"IN",
    "name:ben_x_preferred":[
        "\u09b8\u09cb\u09b9\u09be\u0997\u09aa\u09c1\u09b0"
    ],
    "name:bpy_x_preferred":[
        "\u09b8\u09cb\u09b9\u09be\u0997\u09aa\u09c1\u09b0"
    ],
    "name:ceb_x_preferred":[
        "Soh\u0101gpur"
    ],
    "name:hif_x_preferred":[
        "Sohagpur"
    ],
    "name:hin_x_preferred":[
        "\u0938\u094b\u0939\u093e\u0917\u092a\u0941\u0930"
    ],
    "name:ita_x_preferred":[
        "Sohagpur"
    ],
    "name:mlg_x_preferred":[
        "Sohagpur"
    ],
    "name:msa_x_preferred":[
        "Sohagpur"
    ],
    "name:nld_x_preferred":[
        "Sohagpur"
    ],
    "name:ori_x_preferred":[
        "\u0b38\u0b41\u0b39\u0b3e\u0b17\u0b2a\u0b41\u0b30"
    ],
    "name:por_x_preferred":[
        "Sohagpur"
    ],
    "name:spa_x_preferred":[
        "Sohagpur"
    ],
    "name:swe_x_preferred":[
        "Soh\u0101gpur"
    ],
    "name:vie_x_preferred":[
        "Sohagpur"
    ],
    "name:zho_x_preferred":[
        "\u7d22\u54c8\u683c\u666e\u5c14"
    ],
    "wof:name":"Sohagpur",
    "wof:placetype":"locality"
},
  "geometry": {"coordinates":[78.80154,21.92735],"type":"Point"}
}