{
  "type": "Feature",
  "properties": {
    "iso:country":"IN",
    "ks:ks_name":"Baraebir",
    "ks:ks_pop":1483,
    "ks:ks_type":"VILLAGE",
    "name:eng_x_preferred":[
        "Baraebir"
    ],
    "wof:name":"Baraebir",
    "wof:placetype":"locality",
    "wof:population":1483
},
  "geometry": {"coordinates":[85.49208400000001,22.556656],"type":"Point"}
}