{
  "type": "Feature",
  "properties": {
    "gn:admin1_code":"2.0",
    "gn:admin2_code":"553.0",
    "gn:asciiname":"Reddipalle",
    "gn:country_code":"IN",
    "gn:dem":492,
    "gn:feature_class":"P",
    "gn:feature_code":"PPL",
    "gn:name":"Reddipalle",
    "gn:population":0,
    "gn:timezone":"Asia/Kolkata",
    "iso:country":"IN",
    "name:und_x_variant":[
        "Reddipale"
    ],
    "wof:name":"Reddipalle",
    "wof:placetype":"locality"
},
  "geometry": {"coordinates":[78.01018000000001,14.19933],"type":"Point"}
}