{
  "type": "Feature",
  "properties": {
    "gn:admin1_code":"16.0",
    "gn:admin2_code":"497.0",
    "gn:asciiname":"Chitar",
    "gn:country_code":"IN",
    "gn:dem":484,
    "gn:feature_class":"P",
    "gn:feature_code":"PPL",
    "gn:name":"Chit\u0101r",
    "gn:population":0,
    "gn:timezone":"Asia/Kolkata",
    "iso:country":"IN",
    "ks:ks_name":"Chittar",
    "ks:ks_pop":234,
    "ks:ks_type":"VILLAGE",
    "name:eng_x_preferred":[
        "Chittar"
    ],
    "name:eng_x_variant":[
        "Chitar"
    ],
    "wof:name":"Chittar",
    "wof:placetype":"locality",
    "wof:population":234
},
  "geometry": {"coordinates":[74.181483,21.729944],"type":"Point"}
}