{
  "type": "Feature",
  "properties": {
    "gn:admin1_code":"23.0",
    "gn:admin2_code":"43.0",
    "gn:asciiname":"Husain Shahwala",
    "gn:country_code":"IN",
    "gn:dem":194,
    "gn:feature_class":"P",
    "gn:feature_code":"PPL",
    "gn:name":"Husain Sh\u0101hw\u0101la",
    "gn:population":0,
    "gn:timezone":"Asia/Kolkata",
    "iso:country":"IN",
    "ks:ks_alt_nam":"Husain Sh\u0101hw\u0101la",
    "ks:ks_name":"Husain Shahwala",
    "ks:ks_type":"VILLAGE",
    "name:eng_x_preferred":[
        "Husain Shahwala"
    ],
    "name:eng_x_variant":[
        "Husain Sh\u0101hw\u0101la"
    ],
    "wof:name":"Husain Shahwala",
    "wof:placetype":"locality"
},
  "geometry": {"coordinates":[74.501239,30.87829],"type":"Point"}
}