{
  "type": "Feature",
  "properties": {
    "iso:country":"IN",
    "ks:ks_name":"Ulavalabanda",
    "ks:ks_pop":47,
    "ks:ks_type":"HABITATION",
    "name:eng_x_preferred":[
        "Ulavalabanda"
    ],
    "wof:name":"Ulavalabanda",
    "wof:placetype":"locality",
    "wof:population":47
},
  "geometry": {"coordinates":[78.578137,13.523671],"type":"Point"}
}