{
  "type": "Feature",
  "properties": {
    "iso:country":"IN",
    "ks:ks_name":"Cinema Hall Jn.",
    "ks:ks_pop":845,
    "ks:ks_type":"HABITATION",
    "ks:ks_uagg_main":0,
    "name:eng_x_preferred":[
        "Cinema Hall Jn."
    ],
    "wof:name":"Cinema Hall Jn.",
    "wof:placetype":"neighbourhood",
    "wof:population":845
},
  "geometry": {"coordinates":[76.292061,11.114189],"type":"Point"}
}