{
  "type": "Feature",
  "properties": {
    "iso:country":"IN",
    "ks:ks_name":"Itchikattur",
    "ks:ks_pop":100,
    "ks:ks_type":"HABITATION",
    "ks:ks_uagg_main":0,
    "name:eng_x_preferred":[
        "Itchikattur"
    ],
    "wof:name":"Itchikattur",
    "wof:placetype":"neighbourhood",
    "wof:population":100
},
  "geometry": {"coordinates":[77.535381,11.252104],"type":"Point"}
}