{
  "type": "Feature",
  "properties": {
    "iso:country":"IN",
    "ks:ks_name":"Tiniamba",
    "ks:ks_pop":64,
    "ks:ks_type":"VILLAGE",
    "name:eng_x_preferred":[
        "Tiniamba"
    ],
    "wof:name":"Tiniamba",
    "wof:placetype":"locality",
    "wof:population":64
},
  "geometry": {"coordinates":[84.35508,19.373195],"type":"Point"}
}