{
  "type": "Feature",
  "properties": {
    "iso:country":"IN",
    "ks:ks_name":"Chakdoh",
    "ks:ks_pop":267,
    "ks:ks_type":"VILLAGE",
    "name:eng_x_preferred":[
        "Chakdoh"
    ],
    "wof:name":"Chakdoh",
    "wof:placetype":"locality",
    "wof:population":267
},
  "geometry": {"coordinates":[78.75143799999999,21.285119],"type":"Point"}
}