{
  "type": "Feature",
  "properties": {
    "gn:admin1_code":"16",
    "gn:admin2_code":"505.0",
    "gn:asciiname":"Sasegaon",
    "gn:country_code":"IN",
    "gn:dem":279,
    "gn:feature_class":"P",
    "gn:feature_code":"PPL",
    "gn:name":"Sasegaon",
    "gn:population":0,
    "gn:timezone":"Asia/Kolkata",
    "iso:country":"IN",
    "wof:name":"Sasegaon",
    "wof:placetype":"locality"
},
  "geometry": {"coordinates":[79.28565999999999,21.00683],"type":"Point"}
}