{
  "type": "Feature",
  "properties": {
    "iso:country":"IN",
    "ks:ks_name":"Nadaje",
    "ks:ks_pop":670,
    "ks:ks_type":"HABITATION",
    "name:eng_x_preferred":[
        "Nadaje"
    ],
    "wof:name":"Nadaje",
    "wof:placetype":"locality",
    "wof:population":670
},
  "geometry": {"coordinates":[75.064678,12.810693],"type":"Point"}
}