{
  "type": "Feature",
  "properties": {
    "gn:admin1_code":"35",
    "gn:admin2_code":"430.0",
    "gn:asciiname":"Kullu",
    "gn:country_code":"IN",
    "gn:dem":313,
    "gn:feature_class":"P",
    "gn:feature_code":"PPL",
    "gn:name":"Kullu",
    "gn:population":0,
    "gn:timezone":"Asia/Kolkata",
    "iso:country":"IN",
    "name:ara_x_preferred":[
        "\u0643\u0627\u0644\u0648"
    ],
    "name:ara_x_variant":[
        "\u0643\u0648\u0644\u0648"
    ],
    "name:ben_bn_x_preferred":[
        "\u0995\u09c1\u09b2\u09c1"
    ],
    "name:ben_in_x_preferred":[
        "\u0995\u09c1\u09b2\u09c1"
    ],
    "name:ben_x_preferred":[
        "\u0995\u09c1\u09b2\u09c1"
    ],
    "name:bpy_x_preferred":[
        "\u0995\u09c1\u09b2\u09cd\u09b2\u09c1"
    ],
    "name:cat_x_preferred":[
        "Kulu"
    ],
    "name:deu_x_preferred":[
        "Kullu"
    ],
    "name:fra_x_preferred":[
        "Kullu"
    ],
    "name:guj_x_preferred":[
        "\u0a95\u0ac1\u0ab2\u0acd\u0ab2\u0ac1"
    ],
    "name:guj_x_variant":[
        "\u0a95\u0ac1\u0ab2\u0acd\u0ab2\u0ac2"
    ],
    "name:hin_x_preferred":[
        "\u0915\u0941\u0932\u094d\u0932\u0942"
    ],
    "name:hun_x_preferred":[
        "Kullu"
    ],
    "name:ita_x_preferred":[
        "Kullu"
    ],
    "name:kan_x_preferred":[
        "\u0c95\u0cc1\u0cb2\u0ccd\u0cb2\u0cc1"
    ],
    "name:mal_x_preferred":[
        "\u0d15\u0d41\u0d33\u0d41"
    ],
    "name:mar_x_preferred":[
        "\u0915\u0941\u0932\u094d\u0932\u0942"
    ],
    "name:mar_x_variant":[
        "\u0915\u0941\u0932\u0941"
    ],
    "name:mlg_x_preferred":[
        "Kullu"
    ],
    "name:msa_x_preferred":[
        "Kullu"
    ],
    "name:nep_x_preferred":[
        "\u0915\u0941\u0932\u094d\u0932\u0942"
    ],
    "name:new_x_preferred":[
        "\u0915\u0941\u0932\u094d\u0932\u0941"
    ],
    "name:nld_x_preferred":[
        "Kullu"
    ],
    "name:pan_x_preferred":[
        "\u0a15\u0a41\u0a71\u0a32\u0a42"
    ],
    "name:pol_x_preferred":[
        "Kullu"
    ],
    "name:por_x_preferred":[
        "Kulu"
    ],
    "name:rus_x_preferred":[
        "\u041a\u0443\u043b\u043b\u0443"
    ],
    "name:san_x_preferred":[
        "\u0915\u0941\u0932\u094d\u0932\u0942"
    ],
    "name:swe_x_preferred":[
        "Kullu"
    ],
    "name:tam_x_preferred":[
        "\u0b95\u0bc1\u0bb2\u0bcd\u0bb2\u0bc1"
    ],
    "name:tam_x_variant":[
        "\u0b95\u0bc1\u0bb2\u0bc1"
    ],
    "name:tel_x_preferred":[
        "\u0c15\u0c41\u0c32\u0c4d\u0c32\u0c41"
    ],
    "name:urd_x_preferred":[
        "\u06a9\u0644\u0651\u0648"
    ],
    "name:urd_x_variant":[
        "\u06a9\u0644\u0644\u0648"
    ],
    "name:vie_x_preferred":[
        "Kullu"
    ],
    "name:zho_x_preferred":[
        "\u5e93\u5c14\u5362"
    ],
    "wof:name":"Kullu",
    "wof:placetype":"locality"
},
  "geometry": {"coordinates":[81.23165,24.58219],"type":"Point"}
}