{
  "type": "Feature",
  "properties": {
    "iso:country":"IN",
    "ks:ks_name":"Cherabari",
    "ks:ks_pop":324,
    "ks:ks_type":"VILLAGE",
    "ks:ks_uagg_main":0,
    "name:eng_x_preferred":[
        "Cherabari"
    ],
    "wof:name":"Cherabari",
    "wof:placetype":"neighbourhood",
    "wof:population":324
},
  "geometry": {"coordinates":[91.403488,26.351233],"type":"Point"}
}