{
  "type": "Feature",
  "properties": {
    "gn:country":"IN",
    "gn:fcode":"PPL",
    "gn:population":0,
    "iso:country":"IN",
    "ks:ks_name":"Assagao",
    "ks:ks_pop":4203,
    "ks:ks_type":"VILLAGE",
    "ks:ks_uagg_main":0,
    "name:ast_x_preferred":[
        "Assagao"
    ],
    "name:eng_x_preferred":[
        "Assagao"
    ],
    "name:gom_x_preferred":[
        "\u0906\u0938\u0917\u093e\u0902\u0935"
    ],
    "name:jpn_x_preferred":[
        "\u30a2\u30c3\u30b5\u30ac\u30aa"
    ],
    "name:nld_x_preferred":[
        "Assagao"
    ],
    "name:por_x_preferred":[
        "Assag\u00e3o"
    ],
    "qs:name":"Assagao",
    "qs:name_adm0":"India",
    "qs:name_adm1":"Goa",
    "qs:photos":59,
    "qs:photos_1k":12,
    "qs:photos_9k":1,
    "qs:photos_9r":2,
    "qs:photos_all":59,
    "qs:photos_sr":2,
    "qs:placetype":"Town",
    "qs:pop_sr":"0",
    "wof:name":"Assagao",
    "wof:placetype":"locality",
    "wof:population":4203
},
  "geometry": {"coordinates":[73.759488,15.602868],"type":"Point"}
}