{
  "type": "Feature",
  "properties": {
    "iso:country":"IN",
    "ks:ks_name":"Garighat",
    "ks:ks_pop":755,
    "ks:ks_type":"VILLAGE",
    "name:eng_x_preferred":[
        "Garighat"
    ],
    "wof:name":"Garighat",
    "wof:placetype":"locality",
    "wof:population":755
},
  "geometry": {"coordinates":[83.90748600000001,22.456347],"type":"Point"}
}