{
  "type": "Feature",
  "properties": {
    "iso:country":"IN",
    "ks:ks_name":"Taseng Apam",
    "ks:ks_pop":132,
    "ks:ks_type":"HABITATION",
    "name:eng_x_preferred":[
        "Taseng Apam"
    ],
    "wof:name":"Taseng Apam",
    "wof:placetype":"locality",
    "wof:population":132
},
  "geometry": {"coordinates":[92.754985,25.751492],"type":"Point"}
}