{
  "type": "Feature",
  "properties": {
    "gn:admin1_code":"36",
    "gn:admin2_code":"172.0",
    "gn:asciiname":"Mithanpur Kirtu",
    "gn:country_code":"IN",
    "gn:dem":121,
    "gn:feature_class":"P",
    "gn:feature_code":"PPL",
    "gn:name":"Mithanpur Kirtu",
    "gn:population":0,
    "gn:timezone":"Asia/Kolkata",
    "iso:country":"IN",
    "ks:ks_name":"Mithanpur Kirtu",
    "ks:ks_type":"VILLAGE",
    "ks:ks_uagg_main":0,
    "name:eng_x_preferred":[
        "Mithanpur Kirtu"
    ],
    "wof:name":"Mithanpur Kirtu",
    "wof:placetype":"neighbourhood"
},
  "geometry": {"coordinates":[80.858107,26.020039],"type":"Point"}
}