{
  "type": "Feature",
  "properties": {
    "iso:country":"IN",
    "ks:ks_name":"Samarwan Purwa",
    "ks:ks_pop":205,
    "ks:ks_type":"HABITATION",
    "name:eng_x_preferred":[
        "Samarwan Purwa"
    ],
    "wof:name":"Samarwan Purwa",
    "wof:placetype":"locality",
    "wof:population":205
},
  "geometry": {"coordinates":[82.173214,27.401255],"type":"Point"}
}