{
  "type": "Feature",
  "properties": {
    "iso:country":"IN",
    "ks:ks_alt_nam":"THALA FALI",
    "ks:ks_name":"Thala Fali",
    "ks:ks_pop":75,
    "ks:ks_type":"HABITATION",
    "name:eng_x_preferred":[
        "Thala Fali"
    ],
    "wof:name":"Thala Fali",
    "wof:placetype":"locality",
    "wof:population":75
},
  "geometry": {"coordinates":[72.965789,24.428897],"type":"Point"}
}