{
  "type": "Feature",
  "properties": {
    "iso:country":"IN",
    "ks:ks_name":"Jite",
    "ks:ks_pop":920,
    "ks:ks_type":"VILLAGE",
    "ks:ks_uagg_main":0,
    "name:eng_x_preferred":[
        "Jite"
    ],
    "wof:name":"Jite",
    "wof:placetype":"neighbourhood",
    "wof:population":920
},
  "geometry": {"coordinates":[73.48825100000001,18.118071],"type":"Point"}
}