{
  "type": "Feature",
  "properties": {
    "iso:country":"IN",
    "ks:ks_name":"Basthimadanahalli",
    "ks:ks_pop":22,
    "ks:ks_type":"VILLAGE",
    "name:eng_x_preferred":[
        "Basthimadanahalli"
    ],
    "wof:name":"Basthimadanahalli",
    "wof:placetype":"locality",
    "wof:population":22
},
  "geometry": {"coordinates":[76.385244,12.225624],"type":"Point"}
}