{
  "type": "Feature",
  "properties": {
    "iso:country":"IN",
    "ks:ks_alt_nam":"J.Hosahalli colony",
    "ks:ks_name":"J.hosahalli Colony",
    "ks:ks_pop":167,
    "ks:ks_type":"HABITATION",
    "name:eng_x_preferred":[
        "J.hosahalli Colony"
    ],
    "wof:name":"J.hosahalli Colony",
    "wof:placetype":"locality",
    "wof:population":167
},
  "geometry": {"coordinates":[76.026759,12.701856],"type":"Point"}
}