{
  "type": "Feature",
  "properties": {
    "iso:country":"IN",
    "ks:ks_name":"Phooldesar Singas",
    "ks:ks_pop":714,
    "ks:ks_type":"VILLAGE",
    "name:eng_x_preferred":[
        "Phooldesar Singas"
    ],
    "wof:name":"Phooldesar Singas",
    "wof:placetype":"locality",
    "wof:population":714
},
  "geometry": {"coordinates":[73.660464,28.513996],"type":"Point"}
}