{
  "type": "Feature",
  "properties": {
    "iso:country":"IN",
    "qs:name":"Gaikwadni Haveli",
    "qs:name_adm0":"India",
    "qs:name_adm1":"Gujarat",
    "qs:photos":24,
    "qs:photos_1k":5,
    "qs:photos_9k":1,
    "qs:photos_9r":1,
    "qs:photos_all":24,
    "qs:photos_sr":1,
    "qs:placetype":"Suburb",
    "qs:pop_sr":"0",
    "wof:name":"Gaikwadni Haveli",
    "wof:placetype":"neighbourhood"
},
  "geometry": {"coordinates":[72.57851599999999,23.011363],"type":"Point"}
}