{
  "type": "Feature",
  "properties": {
    "gn:admin1_code":"12.0",
    "gn:asciiname":"Pahariwala",
    "gn:country_code":"IN",
    "gn:dem":281,
    "gn:feature_class":"P",
    "gn:feature_code":"PPL",
    "gn:name":"Pah\u0101riw\u0101la",
    "gn:population":0,
    "gn:timezone":"Asia/Kolkata",
    "iso:country":"IN",
    "name:und_x_variant":[
        "Pah\u0101riw\u0101la",
        "Pahariw\u0101la"
    ],
    "wof:name":"Pahariwala",
    "wof:placetype":"locality"
},
  "geometry": {"coordinates":[74.49175,32.84538],"type":"Point"}
}