{
  "type": "Feature",
  "properties": {
    "gn:admin1_code":"37",
    "gn:admin2_code":"413.0",
    "gn:asciiname":"Kektipara",
    "gn:country_code":"IN",
    "gn:dem":387,
    "gn:feature_class":"P",
    "gn:feature_code":"PPL",
    "gn:name":"Kektip\u0101ra",
    "gn:population":0,
    "gn:timezone":"Asia/Kolkata",
    "iso:country":"IN",
    "wof:name":"Kektipara",
    "wof:placetype":"locality"
},
  "geometry": {"coordinates":[81.03766999999998,20.19202],"type":"Point"}
}