{
  "type": "Feature",
  "properties": {
    "iso:country":"IN",
    "ks:ks_name":"Dakra",
    "ks:ks_pop":5268,
    "ks:ks_type":"VILLAGE",
    "ks:ks_uagg_main":1,
    "name:eng_x_preferred":[
        "Dakra"
    ],
    "wof:name":"Dakra",
    "wof:placetype":"neighbourhood",
    "wof:population":5268
},
  "geometry": {"coordinates":[88.765906,25.227351],"type":"Point"}
}