{
  "type": "Feature",
  "properties": {
    "iso:country":"IN",
    "ks:ks_name":"Satiyari",
    "ks:ks_pop":105,
    "ks:ks_type":"HABITATION",
    "name:eng_x_preferred":[
        "Satiyari"
    ],
    "wof:name":"Satiyari",
    "wof:placetype":"locality",
    "wof:population":105
},
  "geometry": {"coordinates":[83.475146,24.098696],"type":"Point"}
}