{
  "type": "Feature",
  "properties": {
    "iso:country":"IN",
    "ks:ks_name":"Shikli",
    "ks:ks_pop":249,
    "ks:ks_type":"VILLAGE",
    "ks:ks_uagg_main":0,
    "name:eng_x_preferred":[
        "Shikli"
    ],
    "wof:name":"Shikli",
    "wof:placetype":"neighbourhood",
    "wof:population":249
},
  "geometry": {"coordinates":[86.06077999999999,22.951929],"type":"Point"}
}