{
  "type": "Feature",
  "properties": {
    "iso:country":"IN",
    "ks:ks_name":"N.bika",
    "ks:ks_pop":240,
    "ks:ks_type":"HABITATION",
    "name:eng_x_preferred":[
        "N.bika"
    ],
    "wof:name":"N.bika",
    "wof:placetype":"locality",
    "wof:population":240
},
  "geometry": {"coordinates":[79.133825,27.002839],"type":"Point"}
}