{
  "type": "Feature",
  "properties": {
    "gn:admin1_code":"19.0",
    "gn:admin2_code":"566.0",
    "gn:asciiname":"Santenahalli",
    "gn:country_code":"IN",
    "gn:dem":728,
    "gn:feature_class":"P",
    "gn:feature_code":"PPL",
    "gn:name":"S\u0101ntenahalli",
    "gn:population":0,
    "gn:timezone":"Asia/Kolkata",
    "iso:country":"IN",
    "wof:name":"Santenahalli",
    "wof:placetype":"locality"
},
  "geometry": {"coordinates":[76.21483000000001,13.96848],"type":"Point"}
}