{
  "type": "Feature",
  "properties": {
    "iso:country":"IN",
    "ks:ks_name":"Panasaladoddi",
    "ks:ks_pop":88,
    "ks:ks_type":"HABITATION",
    "name:eng_x_preferred":[
        "Panasaladoddi"
    ],
    "wof:name":"Panasaladoddi",
    "wof:placetype":"locality",
    "wof:population":88
},
  "geometry": {"coordinates":[82.269319,17.867404],"type":"Point"}
}