{
  "type": "Feature",
  "properties": {
    "iso:country":"IN",
    "ks:ks_alt_nam":"Mudukutti azhiyatta kandam chunda road",
    "ks:ks_name":"Mudukutti Azhiyatta Kandam Chunda Road",
    "ks:ks_pop":416,
    "ks:ks_type":"HABITATION",
    "name:eng_x_preferred":[
        "Mudukutti Azhiyatta Kandam Chunda Road"
    ],
    "wof:name":"Mudukutti Azhiyatta Kandam Chunda Road",
    "wof:placetype":"locality",
    "wof:population":416
},
  "geometry": {"coordinates":[75.702499,11.756063],"type":"Point"}
}