{
  "type": "Feature",
  "properties": {
    "gn:admin1_code":"35",
    "gn:admin2_code":"426.0",
    "gn:asciiname":"Dharampura",
    "gn:country_code":"IN",
    "gn:dem":323,
    "gn:feature_class":"P",
    "gn:feature_code":"PPL",
    "gn:name":"Dharampura",
    "gn:population":0,
    "gn:timezone":"Asia/Kolkata",
    "iso:country":"IN",
    "name:fas_x_preferred":[
        "\u062f\u0647\u0631\u0645\u200c\u067e\u0648\u0631\u0647"
    ],
    "name:urd_x_preferred":[
        "\u062f\u06be\u0631\u0645 \u067e\u0648\u0631\u06c1"
    ],
    "wof:name":"Dharampura",
    "wof:placetype":"locality"
},
  "geometry": {"coordinates":[80.1537,24.45553],"type":"Point"}
}