{
  "type": "Feature",
  "properties": {
    "gn:admin1_code":"39.0",
    "gn:admin2_code":"60.0",
    "gn:asciiname":"Sondana",
    "gn:country_code":"IN",
    "gn:dem":989,
    "gn:feature_class":"P",
    "gn:feature_code":"PPL",
    "gn:name":"Sondana",
    "gn:population":0,
    "gn:timezone":"Asia/Kolkata",
    "iso:country":"IN",
    "wof:name":"Sondana",
    "wof:placetype":"locality"
},
  "geometry": {"coordinates":[78.18590999999998,30.30367],"type":"Point"}
}