{
  "type": "Feature",
  "properties": {
    "iso:country":"IN",
    "ks:ks_name":"Tilapara No.1",
    "ks:ks_pop":131,
    "ks:ks_type":"HABITATION",
    "ks:ks_uagg_main":0,
    "name:eng_x_preferred":[
        "Tilapara No.1"
    ],
    "wof:name":"Tilapara No.1",
    "wof:placetype":"neighbourhood",
    "wof:population":131
},
  "geometry": {"coordinates":[93.154286,26.25432],"type":"Point"}
}