{
  "type": "Feature",
  "properties": {
    "iso:country":"IN",
    "ks:ks_name":"Baraula Jafrabad",
    "ks:ks_pop":3797,
    "ks:ks_type":"VILLAGE",
    "ks:ks_uagg_main":0,
    "name:eng_x_preferred":[
        "Baraula Jafrabad"
    ],
    "wof:name":"Baraula Jafrabad",
    "wof:placetype":"neighbourhood",
    "wof:population":3797
},
  "geometry": {"coordinates":[78.052392,27.919897],"type":"Point"}
}