{
  "type": "Feature",
  "properties": {
    "iso:country":"IN",
    "ks:ks_name":"Shahjahanpura",
    "ks:ks_pop":0,
    "ks:ks_type":"VILLAGE",
    "name:eng_x_preferred":[
        "Shahjahanpura"
    ],
    "wof:name":"Shahjahanpura",
    "wof:placetype":"locality",
    "wof:population":0
},
  "geometry": {"coordinates":[76.624798,22.854465],"type":"Point"}
}