{
  "type": "Feature",
  "properties": {
    "iso:country":"IN",
    "ks:ks_name":"Nallagutta Madigapalle",
    "ks:ks_pop":155,
    "ks:ks_type":"HABITATION",
    "name:eng_x_preferred":[
        "Nallagutta Madigapalle"
    ],
    "wof:name":"Nallagutta Madigapalle",
    "wof:placetype":"locality",
    "wof:population":155
},
  "geometry": {"coordinates":[78.44860799999999,13.761717],"type":"Point"}
}