{
  "type": "Feature",
  "properties": {
    "iso:country":"IN",
    "ks:ks_alt_nam":"PURE BIBIYAPUR",
    "ks:ks_name":"Pure Bibiyapur",
    "ks:ks_pop":1039,
    "ks:ks_type":"HABITATION",
    "name:eng_x_preferred":[
        "Pure Bibiyapur"
    ],
    "wof:name":"Pure Bibiyapur",
    "wof:placetype":"locality",
    "wof:population":1039
},
  "geometry": {"coordinates":[81.4327,26.3015],"type":"Point"}
}