{
  "type": "Feature",
  "properties": {
    "gn:admin1_code":"10.0",
    "gn:admin2_code":"076",
    "gn:asciiname":"Rohat",
    "gn:country_code":"IN",
    "gn:dem":227,
    "gn:feature_class":"P",
    "gn:feature_code":"PPL",
    "gn:name":"Roh\u0101t",
    "gn:population":0,
    "gn:timezone":"Asia/Kolkata",
    "iso:country":"IN",
    "name:ceb_x_preferred":[
        "Rohat"
    ],
    "name:swe_x_preferred":[
        "Rohat"
    ],
    "wof:name":"Rohat",
    "wof:placetype":"locality"
},
  "geometry": {"coordinates":[76.97469,28.93414000000001],"type":"Point"}
}