{
  "type": "Feature",
  "properties": {
    "iso:country":"IN",
    "ks:ks_name":"Mandav Fatarwadi",
    "ks:ks_pop":628,
    "ks:ks_type":"HABITATION",
    "name:eng_x_preferred":[
        "Mandav Fatarwadi"
    ],
    "wof:name":"Mandav Fatarwadi",
    "wof:placetype":"locality",
    "wof:population":628
},
  "geometry": {"coordinates":[73.862432,15.882734],"type":"Point"}
}