{
  "type": "Feature",
  "properties": {
    "iso:country":"IN",
    "ks:ks_alt_nam":"JAGJEEVAN NAGAR",
    "ks:ks_name":"Jagjeevan Nagar",
    "ks:ks_pop":214,
    "ks:ks_type":"HABITATION",
    "ks:ks_uagg_main":0,
    "name:eng_x_preferred":[
        "Jagjeevan Nagar"
    ],
    "wof:name":"Jagjeevan Nagar",
    "wof:placetype":"neighbourhood",
    "wof:population":214
},
  "geometry": {"coordinates":[85.760186,26.305009],"type":"Point"}
}