{
  "type": "Feature",
  "properties": {
    "gn:admin1_code":"39.0",
    "gn:admin2_code":"061",
    "gn:asciiname":"Chhota Manjhola",
    "gn:country_code":"IN",
    "gn:dem":818,
    "gn:feature_class":"P",
    "gn:feature_code":"PPL",
    "gn:name":"Chhota Manjhola",
    "gn:population":0,
    "gn:timezone":"Asia/Kolkata",
    "iso:country":"IN",
    "wof:name":"Chhota Manjhola",
    "wof:placetype":"locality"
},
  "geometry": {"coordinates":[78.67979,29.80139],"type":"Point"}
}