{
  "type": "Feature",
  "properties": {
    "gn:admin1_code":"25.0",
    "gn:admin2_code":"619.0",
    "gn:asciiname":"Karuppur",
    "gn:country_code":"IN",
    "gn:dem":11,
    "gn:feature_class":"P",
    "gn:feature_code":"PPL",
    "gn:name":"Karupp\u016br",
    "gn:population":0,
    "gn:timezone":"Asia/Kolkata",
    "iso:country":"IN",
    "ks:ks_name":"Karuppur",
    "ks:ks_pop":1026,
    "ks:ks_type":"HABITATION",
    "name:eng_x_preferred":[
        "Karuppur"
    ],
    "wof:name":"Karuppur",
    "wof:placetype":"locality",
    "wof:population":1026
},
  "geometry": {"coordinates":[79.68098500000001,10.748377],"type":"Point"}
}