{
  "type": "Feature",
  "properties": {
    "gn:admin1_code":"34.0",
    "gn:admin2_code":"235.0",
    "gn:asciiname":"Banka",
    "gn:country_code":"IN",
    "gn:dem":89,
    "gn:feature_class":"P",
    "gn:feature_code":"PPL",
    "gn:name":"B\u0101nka",
    "gn:population":0,
    "gn:timezone":"Asia/Kolkata",
    "iso:country":"IN",
    "name:bre_x_preferred":[
        "Banka"
    ],
    "name:cat_x_preferred":[
        "Banka"
    ],
    "name:ceb_x_preferred":[
        "Banka"
    ],
    "name:deu_x_preferred":[
        "Banka"
    ],
    "name:epo_x_preferred":[
        "Banka"
    ],
    "name:eus_x_preferred":[
        "Banka"
    ],
    "name:fra_x_preferred":[
        "Banka"
    ],
    "name:fry_x_preferred":[
        "Banka"
    ],
    "name:nld_x_preferred":[
        "Banka"
    ],
    "name:rus_x_preferred":[
        "\u0411\u0430\u043d\u043a\u0430"
    ],
    "name:san_x_preferred":[
        "\u092c\u093e\u0919\u094d\u0915\u093e"
    ],
    "name:slk_x_preferred":[
        "Banka"
    ],
    "name:srp_x_preferred":[
        "\u0411\u0430\u043d\u043a\u0430"
    ],
    "name:swe_x_preferred":[
        "Banka"
    ],
    "name:ukr_x_preferred":[
        "\u0411\u0430\u043d\u043a\u0430"
    ],
    "wof:name":"Banka",
    "wof:placetype":"locality"
},
  "geometry": {"coordinates":[84.52976,24.91005],"type":"Point"}
}