{
  "type": "Feature",
  "properties": {
    "gn:admin1_code":"34.0",
    "gn:admin2_code":"235.0",
    "gn:asciiname":"Banka",
    "gn:country_code":"IN",
    "gn:dem":89,
    "gn:feature_class":"P",
    "gn:feature_code":"PPL",
    "gn:name":"B\u0101nka",
    "gn:population":0,
    "gn:timezone":"Asia/Kolkata",
    "iso:country":"IN",
    "name:ara_x_preferred":[
        "\u0628\u0627\u0646\u0643\u0627"
    ],
    "name:ben_bn_x_preferred":[
        "\u09ac\u09be\u0999\u09cd\u0995\u09be"
    ],
    "name:ben_in_x_preferred":[
        "\u09ac\u09be\u0999\u09cd\u0995\u09be"
    ],
    "name:bre_x_preferred":[
        "Banka"
    ],
    "name:cat_x_preferred":[
        "Banka"
    ],
    "name:ceb_x_preferred":[
        "Banka"
    ],
    "name:deu_x_preferred":[
        "Banka"
    ],
    "name:epo_x_preferred":[
        "Banka"
    ],
    "name:eus_x_preferred":[
        "Banka"
    ],
    "name:fra_x_preferred":[
        "Banka"
    ],
    "name:fry_x_preferred":[
        "Banka"
    ],
    "name:guj_x_preferred":[
        "\u0aac\u0a82\u0a95\u0abe"
    ],
    "name:hin_x_preferred":[
        "\u092c\u093e\u0902\u0915\u093e"
    ],
    "name:kan_x_preferred":[
        "\u0cac\u0c82\u0c95\u0cbe"
    ],
    "name:mal_x_preferred":[
        "\u0d2c\u0d19\u0d4d\u0d15"
    ],
    "name:mar_x_preferred":[
        "\u092c\u093e\u0902\u0915\u093e"
    ],
    "name:nld_x_preferred":[
        "Banka"
    ],
    "name:pan_x_preferred":[
        "\u0a2c\u0a70\u0a15\u0a3e"
    ],
    "name:rus_x_preferred":[
        "\u0411\u0430\u043d\u043a\u0430"
    ],
    "name:san_x_preferred":[
        "\u092c\u093e\u0919\u094d\u0915\u093e"
    ],
    "name:slk_x_preferred":[
        "Banka"
    ],
    "name:srp_x_preferred":[
        "\u0411\u0430\u043d\u043a\u0430"
    ],
    "name:swe_x_preferred":[
        "Banka"
    ],
    "name:tam_x_preferred":[
        "\u0baa\u0ba9\u0bcd\u0b95\u0bbe"
    ],
    "name:tel_x_preferred":[
        "\u0c2c\u0c02\u0c15\u0c3e"
    ],
    "name:ukr_x_preferred":[
        "\u0411\u0430\u043d\u043a\u0430"
    ],
    "name:urd_x_preferred":[
        "\u0628\u0627\u0646\u06a9\u0627"
    ],
    "wof:name":"Banka",
    "wof:placetype":"locality"
},
  "geometry": {"coordinates":[84.52976,24.91005],"type":"Point"}
}