{
  "type": "Feature",
  "properties": {
    "iso:country":"IN",
    "ks:ks_name":"Agai",
    "ks:ks_pop":304,
    "ks:ks_type":"VILLAGE",
    "ks:ks_uagg_main":0,
    "name:eng_x_preferred":[
        "Agai"
    ],
    "wof:name":"Agai",
    "wof:placetype":"neighbourhood",
    "wof:population":304
},
  "geometry": {"coordinates":[85.775553,26.405853],"type":"Point"}
}