{
  "type": "Feature",
  "properties": {
    "iso:country":"IN",
    "ks:ks_name":"Ambaguda",
    "ks:ks_pop":75,
    "ks:ks_type":"HABITATION",
    "name:eng_x_preferred":[
        "Ambaguda"
    ],
    "wof:name":"Ambaguda",
    "wof:placetype":"locality",
    "wof:population":75
},
  "geometry": {"coordinates":[83.40432,19.561711],"type":"Point"}
}