{
  "type": "Feature",
  "properties": {
    "iso:country":"IN",
    "ks:ks_alt_nam":"M\u0101sakkallu Reserved Forest",
    "ks:ks_name":"Masakkallu Reserved Forest",
    "ks:ks_type":"VILLAGE",
    "name:eng_x_preferred":[
        "Masakkallu Reserved Forest"
    ],
    "name:eng_x_variant":[
        "M\u0101sakkallu Reserved Forest"
    ],
    "wof:name":"Masakkallu Reserved Forest",
    "wof:placetype":"locality"
},
  "geometry": {"coordinates":[77.866377,12.054045],"type":"Point"}
}