{
  "type": "Feature",
  "properties": {
    "gn:admin1_code":"16.0",
    "gn:admin2_code":"505.0",
    "gn:asciiname":"Ganeshpur",
    "gn:country_code":"IN",
    "gn:dem":490,
    "gn:feature_class":"P",
    "gn:feature_code":"PPL",
    "gn:name":"Ganeshpur",
    "gn:population":0,
    "gn:timezone":"Asia/Kolkata",
    "iso:country":"IN",
    "name:ceb_x_preferred":[
        "Ganeshpur"
    ],
    "name:nep_x_preferred":[
        "\u0917\u0923\u0947\u0936\u092a\u0941\u0930"
    ],
    "name:pol_x_preferred":[
        "Ganeshpur"
    ],
    "wof:name":"Ganeshpur",
    "wof:placetype":"locality"
},
  "geometry": {"coordinates":[78.6722,21.17254],"type":"Point"}
}