{
  "type": "Feature",
  "properties": {
    "gn:admin1_code":"19.0",
    "gn:admin2_code":"583.0",
    "gn:asciiname":"Linganhalli",
    "gn:country_code":"IN",
    "gn:dem":924,
    "gn:feature_class":"P",
    "gn:feature_code":"PPL",
    "gn:name":"Linganhalli",
    "gn:population":0,
    "gn:timezone":"Asia/Kolkata",
    "iso:country":"IN",
    "wof:name":"Linganhalli",
    "wof:placetype":"locality"
},
  "geometry": {"coordinates":[77.61790000000001,13.32005],"type":"Point"}
}