{
  "type": "Feature",
  "properties": {
    "iso:country":"IN",
    "ks:ks_name":"Fareed Pur Ahatamali",
    "ks:ks_pop":718,
    "ks:ks_type":"HABITATION",
    "name:eng_x_preferred":[
        "Fareed Pur Ahatamali"
    ],
    "wof:name":"Fareed Pur Ahatamali",
    "wof:placetype":"locality",
    "wof:population":718
},
  "geometry": {"coordinates":[78.13217,28.829301],"type":"Point"}
}