{
  "type": "Feature",
  "properties": {
    "iso:country":"IN",
    "ks:ks_name":"Syamaghanpur",
    "ks:ks_pop":50,
    "ks:ks_type":"HABITATION",
    "name:eng_x_preferred":[
        "Syamaghanpur"
    ],
    "wof:name":"Syamaghanpur",
    "wof:placetype":"locality",
    "wof:population":50
},
  "geometry": {"coordinates":[85.358198,20.051907],"type":"Point"}
}