{
  "type": "Feature",
  "properties": {
    "iso:country":"IN",
    "ks:ks_name":"Pahadeshwar",
    "ks:ks_pop":295,
    "ks:ks_type":"HABITATION",
    "name:eng_x_preferred":[
        "Pahadeshwar"
    ],
    "wof:name":"Pahadeshwar",
    "wof:placetype":"locality",
    "wof:population":295
},
  "geometry": {"coordinates":[74.2894,20.5919],"type":"Point"}
}