{
  "type": "Feature",
  "properties": {
    "gn:admin1_code":"2",
    "gn:admin2_code":"544.0",
    "gn:asciiname":"Jirakonda",
    "gn:country_code":"IN",
    "gn:dem":933,
    "gn:feature_class":"P",
    "gn:feature_code":"PPL",
    "gn:name":"J\u012brakonda",
    "gn:population":0,
    "gn:timezone":"Asia/Kolkata",
    "iso:country":"IN",
    "ks:ks_name":"Jarrakonda",
    "ks:ks_pop":86,
    "ks:ks_type":"VILLAGE",
    "name:eng_x_preferred":[
        "Jarrakonda"
    ],
    "name:eng_x_variant":[
        "Jirakonda"
    ],
    "wof:name":"Jarrakonda",
    "wof:placetype":"locality",
    "wof:population":86
},
  "geometry": {"coordinates":[82.847435,18.032943],"type":"Point"}
}