{
  "type": "Feature",
  "properties": {
    "iso:country":"IN",
    "ks:ks_name":"Siraji",
    "ks:ks_pop":590,
    "ks:ks_type":"VILLAGE",
    "name:eng_x_preferred":[
        "Siraji"
    ],
    "wof:name":"Siraji",
    "wof:placetype":"locality",
    "wof:population":590
},
  "geometry": {"coordinates":[85.165453,24.764742],"type":"Point"}
}