{
  "type": "Feature",
  "properties": {
    "iso:country":"IN",
    "ks:ks_name":"Parsora",
    "ks:ks_pop":129,
    "ks:ks_type":"HABITATION",
    "name:eng_x_preferred":[
        "Parsora"
    ],
    "wof:name":"Parsora",
    "wof:placetype":"locality",
    "wof:population":129
},
  "geometry": {"coordinates":[78.224583,23.622735],"type":"Point"}
}