{
  "type": "Feature",
  "properties": {
    "iso:country":"IN",
    "ks:ks_alt_nam":"E vattoli",
    "ks:ks_name":"E Vattoli",
    "ks:ks_pop":1019,
    "ks:ks_type":"HABITATION",
    "name:eng_x_preferred":[
        "E Vattoli"
    ],
    "wof:name":"E Vattoli",
    "wof:placetype":"locality",
    "wof:population":1019
},
  "geometry": {"coordinates":[75.88922100000001,11.412016],"type":"Point"}
}