{
  "type": "Feature",
  "properties": {
    "gn:admin1_code":"35.0",
    "gn:admin2_code":"427.0",
    "gn:asciiname":"Bichuwa",
    "gn:country_code":"IN",
    "gn:dem":549,
    "gn:feature_class":"P",
    "gn:feature_code":"PPL",
    "gn:name":"Bichuwa",
    "gn:population":0,
    "gn:timezone":"Asia/Kolkata",
    "iso:country":"IN",
    "name:deu_x_preferred":[
        "Bichwa"
    ],
    "name:lit_x_preferred":[
        "Bi\u010dva"
    ],
    "name:pol_x_preferred":[
        "Bi\u0107wa"
    ],
    "name:tam_x_preferred":[
        "\u0baa\u0bbf\u0b9a\u0bcd\u0b9a\u0bc1\u0bb5\u0bbe"
    ],
    "wof:name":"Bichuwa",
    "wof:placetype":"locality"
},
  "geometry": {"coordinates":[78.63008000000001,23.6528],"type":"Point"}
}