{
  "type": "Feature",
  "properties": {
    "iso:country":"IN",
    "ks:ks_alt_nam":"Bamana ka purwa",
    "ks:ks_name":"Bamana Ka Purwa",
    "ks:ks_pop":214,
    "ks:ks_type":"HABITATION",
    "name:eng_x_preferred":[
        "Bamana Ka Purwa"
    ],
    "wof:name":"Bamana Ka Purwa",
    "wof:placetype":"locality",
    "wof:population":214
},
  "geometry": {"coordinates":[80.68646200000001,25.48444],"type":"Point"}
}