{
  "type": "Feature",
  "properties": {
    "iso:country":"IN",
    "ks:ks_name":"Kewtan Purwa",
    "ks:ks_pop":422,
    "ks:ks_type":"HABITATION",
    "name:eng_x_preferred":[
        "Kewtan Purwa"
    ],
    "wof:name":"Kewtan Purwa",
    "wof:placetype":"locality",
    "wof:population":422
},
  "geometry": {"coordinates":[81.710578,27.783422],"type":"Point"}
}