{
  "type": "Feature",
  "properties": {
    "iso:country":"IN",
    "ks:ks_name":"Kali Rana Nagar",
    "ks:ks_pop":1214,
    "ks:ks_type":"HABITATION",
    "name:eng_x_preferred":[
        "Kali Rana Nagar"
    ],
    "wof:name":"Kali Rana Nagar",
    "wof:placetype":"locality",
    "wof:population":1214
},
  "geometry": {"coordinates":[72.83389699999999,27.229058],"type":"Point"}
}