{
  "type": "Feature",
  "properties": {
    "iso:country":"IN",
    "ks:ks_alt_nam":"WARKAR WASTI",
    "ks:ks_name":"Warkar Wasti",
    "ks:ks_pop":103,
    "ks:ks_type":"HABITATION",
    "name:eng_x_preferred":[
        "Warkar Wasti"
    ],
    "wof:name":"Warkar Wasti",
    "wof:placetype":"locality",
    "wof:population":103
},
  "geometry": {"coordinates":[74.655993,19.847734],"type":"Point"}
}