{
  "type": "Feature",
  "properties": {
    "iso:country":"IN",
    "ks:ks_name":"Dariapur",
    "ks:ks_pop":0,
    "ks:ks_type":"VILLAGE",
    "name:eng_x_preferred":[
        "Dariapur"
    ],
    "wof:name":"Dariapur",
    "wof:placetype":"locality",
    "wof:population":0
},
  "geometry": {"coordinates":[86.43231299999999,25.654507],"type":"Point"}
}