{
  "type": "Feature",
  "properties": {
    "gn:admin1_code":"21",
    "gn:admin2_code":"390.0",
    "gn:asciiname":"Targabali",
    "gn:country_code":"IN",
    "gn:dem":722,
    "gn:feature_class":"P",
    "gn:feature_code":"PPL",
    "gn:name":"Targab\u0101li",
    "gn:population":0,
    "gn:timezone":"Asia/Kolkata",
    "iso:country":"IN",
    "ks:ks_alt_nam":"Targab\u0101li",
    "ks:ks_name":"Targabali",
    "ks:ks_type":"VILLAGE",
    "name:eng_x_preferred":[
        "Targabali"
    ],
    "name:eng_x_variant":[
        "Targab\u0101li"
    ],
    "wof:name":"Targabali",
    "wof:placetype":"locality"
},
  "geometry": {"coordinates":[83.574865,19.989334],"type":"Point"}
}