{
  "type": "Feature",
  "properties": {
    "gn:admin1_code":"24.0",
    "gn:admin2_code":"130.0",
    "gn:asciiname":"Godawara",
    "gn:country_code":"IN",
    "gn:dem":596,
    "gn:feature_class":"P",
    "gn:feature_code":"PPL",
    "gn:name":"Godaw\u0101ra",
    "gn:population":0,
    "gn:timezone":"Asia/Kolkata",
    "iso:country":"IN",
    "ks:ks_alt_nam":"Godaw\u0101ra",
    "ks:ks_name":"Godawara",
    "ks:ks_type":"VILLAGE",
    "name:eng_x_preferred":[
        "Godawara"
    ],
    "name:eng_x_variant":[
        "Godaw\u0101ra"
    ],
    "wof:name":"Godawara",
    "wof:placetype":"locality"
},
  "geometry": {"coordinates":[73.434296,24.305971],"type":"Point"}
}