{
  "type": "Feature",
  "properties": {
    "iso:country":"IN",
    "ks:ks_name":"Sahjana Hamjpur",
    "ks:ks_pop":1532,
    "ks:ks_type":"HABITATION",
    "name:eng_x_preferred":[
        "Sahjana Hamjpur"
    ],
    "wof:name":"Sahjana Hamjpur",
    "wof:placetype":"locality",
    "wof:population":1532
},
  "geometry": {"coordinates":[82.86135400000001,26.456511],"type":"Point"}
}