{
  "type": "Feature",
  "properties": {
    "iso:country":"IN",
    "ks:ks_name":"Kalal Majra",
    "ks:ks_pop":1018,
    "ks:ks_type":"HABITATION",
    "name:eng_x_preferred":[
        "Kalal Majra"
    ],
    "wof:name":"Kalal Majra",
    "wof:placetype":"locality",
    "wof:population":1018
},
  "geometry": {"coordinates":[76.958277,30.378171],"type":"Point"}
}