{
  "type": "Feature",
  "properties": {
    "gn:admin1_code":"38.0",
    "gn:admin2_code":"369",
    "gn:asciiname":"Gamharia",
    "gn:country_code":"IN",
    "gn:dem":178,
    "gn:feature_class":"P",
    "gn:feature_code":"PPL",
    "gn:name":"Gamh\u0101ria",
    "gn:population":0,
    "gn:timezone":"Asia/Kolkata",
    "iso:country":"IN",
    "name:hif_x_preferred":[
        "Gamhari"
    ],
    "name:hin_x_preferred":[
        "\u0917\u092e\u094d\u0939\u0930\u093f\u092f\u093e"
    ],
    "name:und_x_variant":[
        "Bara Gamh\u0101ria",
        "Gamaria",
        "Gamh\u0101ria"
    ],
    "wof:name":"Gamharia",
    "wof:placetype":"locality"
},
  "geometry": {"coordinates":[86.10337,22.80943],"type":"Point"}
}