{
  "type": "Feature",
  "properties": {
    "iso:country":"IN",
    "ks:ks_name":"Jaunlibandha",
    "ks:ks_pop":223,
    "ks:ks_type":"VILLAGE",
    "name:eng_x_preferred":[
        "Jaunlibandha"
    ],
    "wof:name":"Jaunlibandha",
    "wof:placetype":"locality",
    "wof:population":223
},
  "geometry": {"coordinates":[85.319647,21.184766],"type":"Point"}
}