{
  "type": "Feature",
  "properties": {
    "iso:country":"IN",
    "ks:ks_name":"Rajmahal",
    "ks:ks_pop":182,
    "ks:ks_type":"VILLAGE",
    "name:eng_x_preferred":[
        "Rajmahal"
    ],
    "wof:name":"Rajmahal",
    "wof:placetype":"locality",
    "wof:population":182
},
  "geometry": {"coordinates":[87.258017,24.158959],"type":"Point"}
}