{
  "type": "Feature",
  "properties": {
    "iso:country":"IN",
    "ks:ks_name":"Chiro",
    "ks:ks_pop":1663,
    "ks:ks_type":"VILLAGE",
    "name:eng_x_preferred":[
        "Chiro"
    ],
    "wof:name":"Chiro",
    "wof:placetype":"locality",
    "wof:population":1663
},
  "geometry": {"coordinates":[84.003304,23.45253],"type":"Point"}
}