{
  "type": "Feature",
  "properties": {
    "gn:admin1_code":"23.0",
    "gn:admin2_code":"035",
    "gn:asciiname":"Jhako Lahri",
    "gn:country_code":"IN",
    "gn:dem":280,
    "gn:feature_class":"P",
    "gn:feature_code":"PPL",
    "gn:name":"Jhako Lahri",
    "gn:population":0,
    "gn:timezone":"Asia/Kolkata",
    "iso:country":"IN",
    "name:und_x_variant":[
        "Jhakholahri",
        "Jhako Lahri"
    ],
    "wof:name":"Jhako Lahri",
    "wof:placetype":"locality"
},
  "geometry": {"coordinates":[75.54179000000001,32.20684],"type":"Point"}
}