{
  "type": "Feature",
  "properties": {
    "iso:country":"IN",
    "ks:ks_name":"Kodri",
    "ks:ks_pop":692,
    "ks:ks_type":"HABITATION",
    "ks:ks_uagg_main":0,
    "name:eng_x_preferred":[
        "Kodri"
    ],
    "wof:name":"Kodri",
    "wof:placetype":"neighbourhood",
    "wof:population":692
},
  "geometry": {"coordinates":[80.404498,27.142628],"type":"Point"}
}