{
  "type": "Feature",
  "properties": {
    "iso:country":"IN",
    "ks:ks_alt_nam":"sukivalewadi",
    "ks:ks_name":"Sukivalewadi",
    "ks:ks_pop":155,
    "ks:ks_type":"HABITATION",
    "name:eng_x_preferred":[
        "Sukivalewadi"
    ],
    "wof:name":"Sukivalewadi",
    "wof:placetype":"locality",
    "wof:population":155
},
  "geometry": {"coordinates":[73.677953,17.518933],"type":"Point"}
}