{
  "type": "Feature",
  "properties": {
    "gn:admin1_code":"35",
    "gn:admin2_code":"456.0",
    "gn:asciiname":"Hamirgarh",
    "gn:country_code":"IN",
    "gn:dem":594,
    "gn:feature_class":"P",
    "gn:feature_code":"PPL",
    "gn:name":"Ham\u012brgarh",
    "gn:population":0,
    "gn:timezone":"Asia/Kolkata",
    "iso:country":"IN",
    "name:cat_x_preferred":[
        "Hamirgarh"
    ],
    "name:hin_x_preferred":[
        "\u0939\u092e\u0940\u0930\u0917\u0922\u093c"
    ],
    "wof:name":"Hamirgarh",
    "wof:placetype":"locality"
},
  "geometry": {"coordinates":[79.46259000000001,22.6466],"type":"Point"}
}