{
  "type": "Feature",
  "properties": {
    "iso:country":"IN",
    "ks:ks_name":"Jaltha Kot",
    "ks:ks_pop":241,
    "ks:ks_type":"VILLAGE",
    "name:eng_x_preferred":[
        "Jaltha Kot"
    ],
    "wof:name":"Jaltha Kot",
    "wof:placetype":"locality",
    "wof:population":241
},
  "geometry": {"coordinates":[79.857175,29.818841],"type":"Point"}
}