{
  "type": "Feature",
  "properties": {
    "gn:admin1_code":"37",
    "gn:admin2_code":"401.0",
    "gn:asciiname":"Daldhoa",
    "gn:country_code":"IN",
    "gn:dem":547,
    "gn:feature_class":"P",
    "gn:feature_code":"PPL",
    "gn:name":"Daldho\u0101",
    "gn:population":0,
    "gn:timezone":"Asia/Kolkata",
    "iso:country":"IN",
    "ks:ks_alt_nam":"Daldho\u0101",
    "ks:ks_name":"Daldhoa",
    "ks:ks_pop":883,
    "ks:ks_type":"VILLAGE",
    "name:eng_x_preferred":[
        "Daldhoa"
    ],
    "name:eng_x_variant":[
        "Daldho\u0101"
    ],
    "wof:name":"Daldhoa",
    "wof:placetype":"locality",
    "wof:population":883
},
  "geometry": {"coordinates":[83.558312,23.588176],"type":"Point"}
}