{
  "type": "Feature",
  "properties": {
    "iso:country":"IN",
    "ks:ks_name":"Subramaniapuram",
    "ks:ks_pop":245,
    "ks:ks_type":"HABITATION",
    "ks:ks_uagg_main":0,
    "name:eng_x_preferred":[
        "Subramaniapuram"
    ],
    "wof:name":"Subramaniapuram",
    "wof:placetype":"neighbourhood",
    "wof:population":245
},
  "geometry": {"coordinates":[77.82008500000001,8.574319],"type":"Point"}
}