{
  "type": "Feature",
  "properties": {
    "gn:admin1_code":"36",
    "gn:admin2_code":"181.0",
    "gn:asciiname":"Khajuria",
    "gn:country_code":"IN",
    "gn:dem":121,
    "gn:feature_class":"P",
    "gn:feature_code":"PPL",
    "gn:name":"Khajuria",
    "gn:population":0,
    "gn:timezone":"Asia/Kolkata",
    "iso:country":"IN",
    "ks:ks_name":"Khajuri",
    "ks:ks_pop":69,
    "ks:ks_type":"HABITATION",
    "name:eng_x_preferred":[
        "Khajuri"
    ],
    "name:eng_x_variant":[
        "Khajuria"
    ],
    "wof:name":"Khajuri",
    "wof:placetype":"locality",
    "wof:population":69
},
  "geometry": {"coordinates":[81.814547,27.521587],"type":"Point"}
}