{
  "type": "Feature",
  "properties": {
    "gn:admin1_code":"2.0",
    "gn:admin2_code":"542.0",
    "gn:asciiname":"Hadobhangi",
    "gn:country_code":"IN",
    "gn:dem":152,
    "gn:feature_class":"P",
    "gn:feature_code":"PPL",
    "gn:name":"Hadobhangi",
    "gn:population":0,
    "gn:timezone":"Asia/Kolkata",
    "iso:country":"IN",
    "ks:ks_name":"Haddubhangi",
    "ks:ks_pop":1703,
    "ks:ks_type":"VILLAGE",
    "name:eng_x_preferred":[
        "Haddubhangi"
    ],
    "name:eng_x_variant":[
        "Hadobhangi"
    ],
    "wof:name":"Haddubhangi",
    "wof:placetype":"locality",
    "wof:population":1703
},
  "geometry": {"coordinates":[83.832092,18.725314],"type":"Point"}
}