{
  "type": "Feature",
  "properties": {
    "iso:country":"IN",
    "ks:ks_name":"Charka",
    "ks:ks_pop":5879,
    "ks:ks_type":"VILLAGE",
    "ks:ks_uagg_main":0,
    "name:eng_x_preferred":[
        "Charka"
    ],
    "wof:name":"Charka",
    "wof:placetype":"neighbourhood",
    "wof:population":5879
},
  "geometry": {"coordinates":[88.078987,24.448481],"type":"Point"}
}