{
  "type": "Feature",
  "properties": {
    "iso:country":"IN",
    "ks:ks_name":"Rampur S",
    "ks:ks_pop":437,
    "ks:ks_type":"VILLAGE",
    "name:eng_x_preferred":[
        "Rampur S"
    ],
    "wof:name":"Rampur S",
    "wof:placetype":"locality",
    "wof:population":437
},
  "geometry": {"coordinates":[79.98547499999999,19.438647],"type":"Point"}
}