{
  "type": "Feature",
  "properties": {
    "iso:country":"IN",
    "ks:ks_name":"Sahijana",
    "ks:ks_pop":404,
    "ks:ks_type":"HABITATION",
    "name:eng_x_preferred":[
        "Sahijana"
    ],
    "wof:name":"Sahijana",
    "wof:placetype":"locality",
    "wof:population":404
},
  "geometry": {"coordinates":[80.040307,27.218839],"type":"Point"}
}