{
  "type": "Feature",
  "properties": {
    "gn:admin1_code":"10",
    "gn:admin2_code":"77.0",
    "gn:asciiname":"Karsola",
    "gn:country_code":"IN",
    "gn:dem":232,
    "gn:feature_class":"P",
    "gn:feature_code":"PPL",
    "gn:name":"Karsola",
    "gn:population":0,
    "gn:timezone":"Asia/Kolkata",
    "iso:country":"IN",
    "wof:name":"Karsola",
    "wof:placetype":"locality"
},
  "geometry": {"coordinates":[76.41395,29.15595],"type":"Point"}
}