{
  "type": "Feature",
  "properties": {
    "gn:admin1_code":"12.0",
    "gn:admin2_code":"008",
    "gn:asciiname":"Punzayar",
    "gn:country_code":"IN",
    "gn:dem":1859,
    "gn:feature_class":"P",
    "gn:feature_code":"PPL",
    "gn:name":"Punzayar",
    "gn:population":0,
    "gn:timezone":"Asia/Kolkata",
    "iso:country":"IN",
    "wof:name":"Punzayar",
    "wof:placetype":"locality"
},
  "geometry": {"coordinates":[74.53662,34.02373],"type":"Point"}
}