{
  "type": "Feature",
  "properties": {
    "gn:admin1_code":"35.0",
    "gn:admin2_code":"457.0",
    "gn:asciiname":"Netra",
    "gn:country_code":"IN",
    "gn:dem":303,
    "gn:feature_class":"P",
    "gn:feature_code":"PPL",
    "gn:name":"Netr\u0101",
    "gn:population":0,
    "gn:timezone":"Asia/Kolkata",
    "iso:country":"IN",
    "name:deu_x_preferred":[
        "Norddeutsche Erdgas-Transversale"
    ],
    "name:ukr_x_preferred":[
        "Netra"
    ],
    "wof:name":"Netra",
    "wof:placetype":"neighbourhood"
},
  "geometry": {"coordinates":[80.22252,21.77948],"type":"Point"}
}