{
  "type": "Feature",
  "properties": {
    "iso:country":"IN",
    "ks:ks_name":"Ambalivas",
    "ks:ks_pop":500,
    "ks:ks_type":"HABITATION",
    "name:eng_x_preferred":[
        "Ambalivas"
    ],
    "wof:name":"Ambalivas",
    "wof:placetype":"locality",
    "wof:population":500
},
  "geometry": {"coordinates":[71.83599100000001,23.948515],"type":"Point"}
}