{
  "type": "Feature",
  "properties": {
    "gn:admin1_code":"11",
    "gn:admin2_code":"23.0",
    "gn:asciiname":"Sobranjia",
    "gn:country_code":"IN",
    "gn:dem":1938,
    "gn:feature_class":"P",
    "gn:feature_code":"PPL",
    "gn:name":"Sobr\u0101njia",
    "gn:population":0,
    "gn:timezone":"Asia/Kolkata",
    "iso:country":"IN",
    "wof:name":"Sobranjia",
    "wof:placetype":"locality"
},
  "geometry": {"coordinates":[76.23076999999998,32.89456],"type":"Point"}
}