{
  "type": "Feature",
  "properties": {
    "iso:country":"IN",
    "ks:ks_name":"Amalchuni",
    "ks:ks_pop":120,
    "ks:ks_type":"VILLAGE",
    "name:eng_x_preferred":[
        "Amalchuni"
    ],
    "wof:name":"Amalchuni",
    "wof:placetype":"locality",
    "wof:population":120
},
  "geometry": {"coordinates":[73.411917,21.30425],"type":"Point"}
}