{
  "type": "Feature",
  "properties": {
    "gn:admin1_code":"31.0",
    "gn:admin2_code":"286.0",
    "gn:asciiname":"Thudmpui",
    "gn:country_code":"IN",
    "gn:dem":579,
    "gn:feature_class":"P",
    "gn:feature_code":"PPL",
    "gn:name":"Thudmpui",
    "gn:population":0,
    "gn:timezone":"Asia/Kolkata",
    "iso:country":"IN",
    "wof:name":"Thudmpui",
    "wof:placetype":"locality"
},
  "geometry": {"coordinates":[92.70983,22.97594],"type":"Point"}
}