{
  "type": "Feature",
  "properties": {
    "iso:country":"IN",
    "ks:ks_name":"Naimpur Govardhan",
    "ks:ks_pop":486,
    "ks:ks_type":"VILLAGE",
    "name:eng_x_preferred":[
        "Naimpur Govardhan"
    ],
    "wof:name":"Naimpur Govardhan",
    "wof:placetype":"locality",
    "wof:population":486
},
  "geometry": {"coordinates":[78.444582,29.471078],"type":"Point"}
}