{
  "type": "Feature",
  "properties": {
    "gn:admin1_code":"10.0",
    "gn:admin2_code":"82.0",
    "gn:asciiname":"Masudpur",
    "gn:country_code":"IN",
    "gn:dem":218,
    "gn:feature_class":"P",
    "gn:feature_code":"PPL",
    "gn:name":"Mas\u016bdpur",
    "gn:population":0,
    "gn:timezone":"Asia/Kolkata",
    "iso:country":"IN",
    "name:und_x_variant":[
        "Mas\u016bdpur"
    ],
    "wof:name":"Masudpur",
    "wof:placetype":"locality"
},
  "geometry": {"coordinates":[76.51351,28.75226],"type":"Point"}
}