{
  "type": "Feature",
  "properties": {
    "iso:country":"IN",
    "name:eng_x_preferred":[
        "More Wasti"
    ],
    "wof:name":"More Wasti",
    "wof:placetype":"neighbourhood"
},
  "geometry": {"coordinates":[73.7969584061961,18.67078812751187],"type":"Point"}
}