{
  "type": "Feature",
  "properties": {
    "iso:country":"IN",
    "name:ara_x_preferred":[
        "\u0645\u0648\u0631\u064a \u0648\u0627\u0633\u062a\u064a"
    ],
    "name:ben_bn_x_preferred":[
        "\u09ae\u09cb\u09b0\u09c7 \u0993\u09df\u09be\u09b8\u09cd\u09a4\u09bf"
    ],
    "name:ben_in_x_preferred":[
        "\u09ae\u09cb\u09b0\u09c7 \u0993\u09df\u09be\u09b8\u09cd\u09a4\u09bf"
    ],
    "name:eng_x_preferred":[
        "More Wasti"
    ],
    "name:guj_x_preferred":[
        "\u0aae\u0acb\u0ab0\u0ac7 \u0ab5\u0ab8\u0acd\u0aa4\u0ac0"
    ],
    "name:hin_x_preferred":[
        "\u092e\u094b\u0930\u0947 \u0935\u0938\u094d\u0924\u0940"
    ],
    "name:kan_x_preferred":[
        "\u0cae\u0ccb\u0cb0\u0cc6 \u0cb5\u0cb8\u0ccd\u0ca4\u0cbf"
    ],
    "name:mal_x_preferred":[
        "\u0d2e\u0d4b\u0d7c \u0d35\u0d3e\u0d38\u0d4d\u0d24\u0d3f"
    ],
    "name:mar_x_preferred":[
        "\u092e\u094b\u0930\u0947 \u0935\u0938\u094d\u0924\u0940"
    ],
    "name:pan_x_preferred":[
        "\u0a2e\u0a4b\u0a30\u0a47 \u0a35\u0a38\u0a24\u0a40"
    ],
    "name:tam_x_preferred":[
        "\u0bae\u0bc7\u0bb2\u0bc1\u0bae\u0bcd \u0bb5\u0bb8\u0bcd\u0ba4\u0bbf"
    ],
    "name:tel_x_preferred":[
        "\u0c2e\u0c4b\u0c30\u0c46 \u0c35\u0c3e\u0c38\u0c4d\u0c24\u0c3f"
    ],
    "name:urd_x_preferred":[
        "\u0645\u0648\u0631\u06cc \u0648\u0633\u062a\u06cc"
    ],
    "wof:name":"More Wasti",
    "wof:placetype":"neighbourhood"
},
  "geometry": {"coordinates":[73.7969584061961,18.67078812751187],"type":"Point"}
}