{
  "type": "Feature",
  "properties": {
    "iso:country":"IN",
    "ks:ks_name":"Survewadi",
    "ks:ks_pop":250,
    "ks:ks_type":"HABITATION",
    "name:eng_x_preferred":[
        "Survewadi"
    ],
    "wof:name":"Survewadi",
    "wof:placetype":"locality",
    "wof:population":250
},
  "geometry": {"coordinates":[73.412222,17.223611],"type":"Point"}
}