{
  "type": "Feature",
  "properties": {
    "iso:country":"IN",
    "ks:ks_name":"Kaligaon Talla",
    "ks:ks_pop":109,
    "ks:ks_type":"HABITATION",
    "name:eng_x_preferred":[
        "Kaligaon Talla"
    ],
    "wof:name":"Kaligaon Talla",
    "wof:placetype":"locality",
    "wof:population":109
},
  "geometry": {"coordinates":[78.846377,29.826398],"type":"Point"}
}