{
  "type": "Feature",
  "properties": {
    "iso:country":"IN",
    "ks:ks_name":"Md. Toli",
    "ks:ks_pop":90,
    "ks:ks_type":"HABITATION",
    "ks:ks_uagg_main":0,
    "name:eng_x_preferred":[
        "Md. Toli"
    ],
    "wof:name":"Md. Toli",
    "wof:placetype":"neighbourhood",
    "wof:population":90
},
  "geometry": {"coordinates":[84.397969,27.095004],"type":"Point"}
}