{
  "type": "Feature",
  "properties": {
    "iso:country":"IN",
    "ks:ks_name":"Chotolawgaon No.2",
    "ks:ks_pop":366,
    "ks:ks_type":"VILLAGE",
    "name:eng_x_preferred":[
        "Chotolawgaon No.2"
    ],
    "wof:name":"Chotolawgaon No.2",
    "wof:placetype":"locality",
    "wof:population":366
},
  "geometry": {"coordinates":[90.713548,26.525091],"type":"Point"}
}