{
  "type": "Feature",
  "properties": {
    "gn:admin1_code":"19.0",
    "gn:admin2_code":"571.0",
    "gn:asciiname":"Buddenahalli",
    "gn:country_code":"IN",
    "gn:dem":731,
    "gn:feature_class":"P",
    "gn:feature_code":"PPL",
    "gn:name":"Buddenahalli",
    "gn:population":0,
    "gn:timezone":"Asia/Kolkata",
    "iso:country":"IN",
    "wof:name":"Buddenahalli",
    "wof:placetype":"locality"
},
  "geometry": {"coordinates":[77.33533,13.56248],"type":"Point"}
}