{
  "type": "Feature",
  "properties": {
    "gn:admin1_code":"36.0",
    "gn:admin2_code":"149.0",
    "gn:asciiname":"Imadpur",
    "gn:country_code":"IN",
    "gn:dem":180,
    "gn:feature_class":"P",
    "gn:feature_code":"PPL",
    "gn:name":"Im\u0101dpur",
    "gn:population":0,
    "gn:timezone":"Asia/Kolkata",
    "iso:country":"IN",
    "ks:ks_alt_nam":"Im\u0101dpur",
    "ks:ks_name":"Imadpur",
    "ks:ks_pop":0,
    "ks:ks_type":"VILLAGE",
    "name:eng_x_preferred":[
        "Imadpur"
    ],
    "name:eng_x_variant":[
        "Im\u0101dpur"
    ],
    "wof:name":"Imadpur",
    "wof:placetype":"locality",
    "wof:population":0
},
  "geometry": {"coordinates":[78.78171500000001,28.107214],"type":"Point"}
}