{
  "type": "Feature",
  "properties": {
    "gn:admin1_code":"28.0",
    "gn:admin2_code":"341",
    "gn:asciiname":"Baragachi",
    "gn:country_code":"IN",
    "gn:dem":8,
    "gn:feature_class":"P",
    "gn:feature_code":"PPL",
    "gn:name":"Bar\u0101g\u0101chi",
    "gn:population":0,
    "gn:timezone":"Asia/Kolkata",
    "iso:country":"IN",
    "wof:name":"Baragachi",
    "wof:placetype":"locality"
},
  "geometry": {"coordinates":[88.08778000000002,22.31917],"type":"Point"}
}