{
  "type": "Feature",
  "properties": {
    "iso:country":"IN",
    "ks:ks_name":"Thennamari South",
    "ks:ks_pop":274,
    "ks:ks_type":"HABITATION",
    "name:eng_x_preferred":[
        "Thennamari South"
    ],
    "wof:name":"Thennamari South",
    "wof:placetype":"locality",
    "wof:population":274
},
  "geometry": {"coordinates":[79.05622099999999,9.899098],"type":"Point"}
}