{
  "type": "Feature",
  "properties": {
    "iso:country":"IN",
    "ks:ks_name":"Paliya Shahzadi",
    "ks:ks_pop":3312,
    "ks:ks_type":"VILLAGE",
    "ks:ks_uagg_main":0,
    "name:eng_x_preferred":[
        "Paliya Shahzadi"
    ],
    "wof:name":"Paliya Shahzadi",
    "wof:placetype":"locality",
    "wof:population":3312
},
  "geometry": {"coordinates":[82.116056,26.743739],"type":"Point"}
}