{
  "type": "Feature",
  "properties": {
    "iso:country":"IN",
    "ks:ks_name":"Tulshi Bigha",
    "ks:ks_pop":410,
    "ks:ks_type":"HABITATION",
    "name:eng_x_preferred":[
        "Tulshi Bigha"
    ],
    "wof:name":"Tulshi Bigha",
    "wof:placetype":"locality",
    "wof:population":410
},
  "geometry": {"coordinates":[85.26146900000001,24.804823],"type":"Point"}
}