{
  "type": "Feature",
  "properties": {
    "iso:country":"IN",
    "ks:ks_name":"Pullakoundampatty",
    "ks:ks_pop":616,
    "ks:ks_type":"HABITATION",
    "name:eng_x_preferred":[
        "Pullakoundampatty"
    ],
    "wof:name":"Pullakoundampatty",
    "wof:placetype":"locality",
    "wof:population":616
},
  "geometry": {"coordinates":[77.813942,9.306577],"type":"Point"}
}