{
  "type": "Feature",
  "properties": {
    "gn:admin1_code":"36",
    "gn:admin2_code":"173.0",
    "gn:asciiname":"Kampa",
    "gn:country_code":"IN",
    "gn:dem":98,
    "gn:feature_class":"P",
    "gn:feature_code":"PPL",
    "gn:name":"K\u0101mpa",
    "gn:population":0,
    "gn:timezone":"Asia/Kolkata",
    "iso:country":"IN",
    "ks:ks_alt_nam":"K\u0101mpa",
    "ks:ks_name":"Kampa",
    "ks:ks_pop":506,
    "ks:ks_type":"VILLAGE",
    "ks:ks_uagg_main":0,
    "name:deu_x_preferred":[
        "Kampa"
    ],
    "name:eng_x_preferred":[
        "Kampa"
    ],
    "name:eng_x_variant":[
        "K\u0101mpa"
    ],
    "name:ita_x_preferred":[
        "Kampa"
    ],
    "name:nld_x_preferred":[
        "Kampa"
    ],
    "name:que_x_preferred":[
        "Kampa"
    ],
    "wof:name":"Kampa",
    "wof:placetype":"neighbourhood",
    "wof:population":506
},
  "geometry": {"coordinates":[82.120352,25.936909],"type":"Point"}
}