{
  "type": "Feature",
  "properties": {
    "iso:country":"IN",
    "ks:ks_name":"Koiritola Niche",
    "ks:ks_pop":179,
    "ks:ks_type":"HABITATION",
    "name:eng_x_preferred":[
        "Koiritola Niche"
    ],
    "wof:name":"Koiritola Niche",
    "wof:placetype":"locality",
    "wof:population":179
},
  "geometry": {"coordinates":[86.069301,24.316383],"type":"Point"}
}