{
  "type": "Feature",
  "properties": {
    "gn:admin1_code":"28.0",
    "gn:admin2_code":"343",
    "gn:asciiname":"Collectorganj",
    "gn:country_code":"IN",
    "gn:dem":5,
    "gn:feature_class":"P",
    "gn:feature_code":"PPL",
    "gn:name":"Collectorganj",
    "gn:population":0,
    "gn:timezone":"Asia/Kolkata",
    "iso:country":"IN",
    "name:und_x_variant":[
        "S\u0101gar Collectorganj"
    ],
    "wof:name":"Collectorganj",
    "wof:placetype":"locality"
},
  "geometry": {"coordinates":[88.16736,21.81576],"type":"Point"}
}