{
  "type": "Feature",
  "properties": {
    "iso:country":"IN",
    "ks:ks_name":"Lakarbindha",
    "ks:ks_pop":96,
    "ks:ks_type":"HABITATION",
    "name:eng_x_preferred":[
        "Lakarbindha"
    ],
    "wof:name":"Lakarbindha",
    "wof:placetype":"locality",
    "wof:population":96
},
  "geometry": {"coordinates":[86.70478,24.377829],"type":"Point"}
}