{
  "type": "Feature",
  "properties": {
    "gn:admin1_code":"3.0",
    "gn:admin2_code":"319.0",
    "gn:asciiname":"Piradhara",
    "gn:country_code":"IN",
    "gn:dem":38,
    "gn:feature_class":"P",
    "gn:feature_code":"PPL",
    "gn:name":"Piradhara",
    "gn:population":0,
    "gn:timezone":"Asia/Kolkata",
    "iso:country":"IN",
    "wof:name":"Piradhara",
    "wof:placetype":"locality"
},
  "geometry": {"coordinates":[90.69273,26.29819],"type":"Point"}
}