{
  "type": "Feature",
  "properties": {
    "iso:country":"IN",
    "ks:ks_name":"Chikkahole Dam",
    "ks:ks_pop":221,
    "ks:ks_type":"HABITATION",
    "name:eng_x_preferred":[
        "Chikkahole Dam"
    ],
    "wof:name":"Chikkahole Dam",
    "wof:placetype":"locality",
    "wof:population":221
},
  "geometry": {"coordinates":[75.875,12.399444],"type":"Point"}
}