{
  "type": "Feature",
  "properties": {
    "iso:country":"IN",
    "ks:ks_alt_nam":"Khirodarpatti",
    "ks:ks_name":"Khirodharpatti",
    "ks:ks_pop":0,
    "ks:ks_type":"VILLAGE",
    "name:eng_x_preferred":[
        "Khirodharpatti"
    ],
    "name:eng_x_variant":[
        "Khirodarpatti"
    ],
    "wof:name":"Khirodharpatti",
    "wof:placetype":"locality",
    "wof:population":0
},
  "geometry": {"coordinates":[84.87042,26.240541],"type":"Point"}
}