{
  "type": "Feature",
  "properties": {
    "gn:admin1_code":"36.0",
    "gn:admin2_code":"182.0",
    "gn:asciiname":"Jamali Jot",
    "gn:country_code":"IN",
    "gn:dem":113,
    "gn:feature_class":"P",
    "gn:feature_code":"PPL",
    "gn:name":"Jam\u0101li Jot",
    "gn:population":0,
    "gn:timezone":"Asia/Kolkata",
    "iso:country":"IN",
    "ks:ks_name":"Jamuni Jot",
    "ks:ks_pop":213,
    "ks:ks_type":"HABITATION",
    "name:eng_x_preferred":[
        "Jamuni Jot"
    ],
    "name:eng_x_variant":[
        "Jamali Jot"
    ],
    "wof:name":"Jamuni Jot",
    "wof:placetype":"locality",
    "wof:population":213
},
  "geometry": {"coordinates":[82.151276,27.486935],"type":"Point"}
}