{
  "type": "Feature",
  "properties": {
    "gn:admin1_code":"36.0",
    "gn:admin2_code":"191.0",
    "gn:asciiname":"Jamilpur",
    "gn:country_code":"IN",
    "gn:dem":84,
    "gn:feature_class":"P",
    "gn:feature_code":"PPL",
    "gn:name":"Jam\u012blpur",
    "gn:population":0,
    "gn:timezone":"Asia/Kolkata",
    "iso:country":"IN",
    "name:und_x_variant":[
        "Jam\u012blpur",
        "Jamilpur"
    ],
    "wof:name":"Jamilpur",
    "wof:placetype":"locality"
},
  "geometry": {"coordinates":[83.16423,26.22435],"type":"Point"}
}