{
  "type": "Feature",
  "properties": {
    "gn:admin1_code":"39",
    "gn:admin2_code":"61.0",
    "gn:asciiname":"Toliyon",
    "gn:country_code":"IN",
    "gn:dem":1513,
    "gn:feature_class":"P",
    "gn:feature_code":"PPL",
    "gn:name":"Toliyon",
    "gn:population":0,
    "gn:timezone":"Asia/Kolkata",
    "iso:country":"IN",
    "wof:name":"Toliyon",
    "wof:placetype":"locality"
},
  "geometry": {"coordinates":[78.93141999999997,29.67312],"type":"Point"}
}