{
  "type": "Feature",
  "properties": {
    "gn:admin1_code":"35.0",
    "gn:admin2_code":"442",
    "gn:asciiname":"Hazaripura",
    "gn:country_code":"IN",
    "gn:dem":418,
    "gn:feature_class":"P",
    "gn:feature_code":"PPL",
    "gn:name":"Haz\u0101r\u012bpura",
    "gn:population":0,
    "gn:timezone":"Asia/Kolkata",
    "iso:country":"IN",
    "name:und_x_variant":[
        "Haz\u0101r\u012bpura",
        "Haz\u0101ripura"
    ],
    "wof:name":"Hazaripura",
    "wof:placetype":"locality"
},
  "geometry": {"coordinates":[76.7544,23.92247],"type":"Point"}
}