{
  "type": "Feature",
  "properties": {
    "iso:country":"IN",
    "ks:ks_name":"M L Tandya",
    "ks:ks_pop":214,
    "ks:ks_type":"HABITATION",
    "name:eng_x_preferred":[
        "M L Tandya"
    ],
    "wof:name":"M L Tandya",
    "wof:placetype":"locality",
    "wof:population":214
},
  "geometry": {"coordinates":[76.269311,13.522952],"type":"Point"}
}