{
  "type": "Feature",
  "properties": {
    "iso:country":"IN",
    "ks:ks_name":"Kathriguppe",
    "ks:ks_pop":613,
    "ks:ks_type":"VILLAGE",
    "ks:ks_uagg_main":0,
    "name:eng_x_preferred":[
        "Kathriguppe"
    ],
    "wof:name":"Kathriguppe",
    "wof:placetype":"neighbourhood",
    "wof:population":613
},
  "geometry": {"coordinates":[77.767156,12.915264],"type":"Point"}
}