{
  "type": "Feature",
  "properties": {
    "iso:country":"IN",
    "ks:ks_name":"Banarhi",
    "ks:ks_pop":175,
    "ks:ks_type":"HABITATION",
    "name:eng_x_preferred":[
        "Banarhi"
    ],
    "wof:name":"Banarhi",
    "wof:placetype":"locality",
    "wof:population":175
},
  "geometry": {"coordinates":[82.983332,27.301284],"type":"Point"}
}