{
  "type": "Feature",
  "properties": {
    "gn:admin1_code":"36.0",
    "gn:admin2_code":"161",
    "gn:asciiname":"Chandarpura",
    "gn:country_code":"IN",
    "gn:dem":154,
    "gn:feature_class":"P",
    "gn:feature_code":"PPL",
    "gn:name":"Chandarpura",
    "gn:population":0,
    "gn:timezone":"Asia/Kolkata",
    "iso:country":"IN",
    "name:und_x_variant":[
        "Chandrapura"
    ],
    "wof:name":"Chandarpura",
    "wof:placetype":"locality"
},
  "geometry": {"coordinates":[79.22223000000002,26.96671],"type":"Point"}
}