{
  "type": "Feature",
  "properties": {
    "iso:country":"IN",
    "ks:ks_alt_nam":"kurauli rajbhar basti",
    "ks:ks_name":"Kurauli Rajbhar Basti",
    "ks:ks_pop":124,
    "ks:ks_type":"HABITATION",
    "name:eng_x_preferred":[
        "Kurauli Rajbhar Basti"
    ],
    "wof:name":"Kurauli Rajbhar Basti",
    "wof:placetype":"locality",
    "wof:population":124
},
  "geometry": {"coordinates":[82.925382,25.397881],"type":"Point"}
}