{
  "type": "Feature",
  "properties": {
    "gn:admin1_code":"21.0",
    "gn:admin2_code":"389.0",
    "gn:asciiname":"Mavel",
    "gn:country_code":"IN",
    "gn:dem":638,
    "gn:feature_class":"P",
    "gn:feature_code":"PPL",
    "gn:name":"Mavel",
    "gn:population":0,
    "gn:timezone":"Asia/Kolkata",
    "iso:country":"IN",
    "ks:ks_name":"Movel",
    "ks:ks_pop":569,
    "ks:ks_type":"VILLAGE",
    "name:eng_x_preferred":[
        "Movel"
    ],
    "name:eng_x_variant":[
        "Mavel"
    ],
    "wof:name":"Movel",
    "wof:placetype":"locality",
    "wof:population":569
},
  "geometry": {"coordinates":[83.969269,19.617484],"type":"Point"}
}