{
  "type": "Feature",
  "properties": {
    "gn:admin1_code":"34.0",
    "gn:admin2_code":"211.0",
    "gn:asciiname":"Bahadurpur Rangpura",
    "gn:country_code":"IN",
    "gn:dem":43,
    "gn:feature_class":"P",
    "gn:feature_code":"PPL",
    "gn:name":"Bah\u0101durpur Rangpura",
    "gn:population":0,
    "gn:timezone":"Asia/Kolkata",
    "iso:country":"IN",
    "wof:name":"Bahadurpur Rangpura",
    "wof:placetype":"locality"
},
  "geometry": {"coordinates":[87.31171999999999,25.72975],"type":"Point"}
}