{
  "type": "Feature",
  "properties": {
    "iso:country":"IN",
    "ks:ks_name":"Allowal",
    "ks:ks_pop":752,
    "ks:ks_type":"HABITATION",
    "name:eng_x_preferred":[
        "Allowal"
    ],
    "wof:name":"Allowal",
    "wof:placetype":"locality",
    "wof:population":752
},
  "geometry": {"coordinates":[75.742265,31.013959],"type":"Point"}
}