{
  "type": "Feature",
  "properties": {
    "iso:country":"IN",
    "ks:ks_name":"Ramdhan Tola",
    "ks:ks_pop":164,
    "ks:ks_type":"HABITATION",
    "ks:ks_uagg_main":0,
    "name:eng_x_preferred":[
        "Ramdhan Tola"
    ],
    "wof:name":"Ramdhan Tola",
    "wof:placetype":"neighbourhood",
    "wof:population":164
},
  "geometry": {"coordinates":[83.29486,27.155708],"type":"Point"}
}