{
  "type": "Feature",
  "properties": {
    "iso:country":"IN",
    "ks:ks_name":"Sadaru Mamidi",
    "ks:ks_pop":75,
    "ks:ks_type":"HABITATION",
    "name:eng_x_preferred":[
        "Sadaru Mamidi"
    ],
    "wof:name":"Sadaru Mamidi",
    "wof:placetype":"locality",
    "wof:population":75
},
  "geometry": {"coordinates":[82.451007,18.145062],"type":"Point"}
}