{
  "type": "Feature",
  "properties": {
    "iso:country":"IN",
    "ks:ks_name":"Naudhiya",
    "ks:ks_pop":3106,
    "ks:ks_type":"VILLAGE",
    "ks:ks_uagg_main":0,
    "name:eng_x_preferred":[
        "Naudhiya"
    ],
    "wof:name":"Naudhiya",
    "wof:placetype":"locality",
    "wof:population":3106
},
  "geometry": {"coordinates":[81.873242,24.427249],"type":"Point"}
}