{
  "type": "Feature",
  "properties": {
    "iso:country":"IN",
    "ks:ks_alt_nam":"PURE CHILAIHYA",
    "ks:ks_name":"Pure Chilaihya",
    "ks:ks_pop":86,
    "ks:ks_type":"HABITATION",
    "ks:ks_uagg_main":0,
    "name:eng_x_preferred":[
        "Pure Chilaihya"
    ],
    "wof:name":"Pure Chilaihya",
    "wof:placetype":"neighbourhood",
    "wof:population":86
},
  "geometry": {"coordinates":[81.4349,26.4444],"type":"Point"}
}