{
  "type": "Feature",
  "properties": {
    "gn:admin1_code":"19.0",
    "gn:admin2_code":"581.0",
    "gn:asciiname":"Karahalli",
    "gn:country_code":"IN",
    "gn:dem":823,
    "gn:feature_class":"P",
    "gn:feature_code":"PPL",
    "gn:name":"K\u0101rahalli",
    "gn:population":0,
    "gn:timezone":"Asia/Kolkata",
    "iso:country":"IN",
    "name:und_x_variant":[
        "K\u0101rahalli",
        "Kesarhalli"
    ],
    "wof:name":"Karahalli",
    "wof:placetype":"locality"
},
  "geometry": {"coordinates":[78.18433,13.00194],"type":"Point"}
}