{
  "type": "Feature",
  "properties": {
    "iso:country":"IN",
    "ks:ks_name":"Mavlatwadi",
    "ks:ks_pop":252,
    "ks:ks_type":"HABITATION",
    "name:eng_x_preferred":[
        "Mavlatwadi"
    ],
    "wof:name":"Mavlatwadi",
    "wof:placetype":"locality",
    "wof:population":252
},
  "geometry": {"coordinates":[73.45611100000001,17.515556],"type":"Point"}
}