{
  "type": "Feature",
  "properties": {
    "gn:admin1_code":"24",
    "gn:admin2_code":"102.0",
    "gn:asciiname":"Tahindesar",
    "gn:country_code":"IN",
    "gn:dem":312,
    "gn:feature_class":"P",
    "gn:feature_code":"PPL",
    "gn:name":"Tahindesar",
    "gn:population":0,
    "gn:timezone":"Asia/Kolkata",
    "iso:country":"IN",
    "wof:name":"Tahindesar",
    "wof:placetype":"neighbourhood"
},
  "geometry": {"coordinates":[73.97020000000001,27.70022],"type":"Point"}
}