{
  "type": "Feature",
  "properties": {
    "iso:country":"IN",
    "ks:ks_alt_nam":"survewadi",
    "ks:ks_name":"Survewadi",
    "ks:ks_pop":101,
    "ks:ks_type":"HABITATION",
    "name:eng_x_preferred":[
        "Survewadi"
    ],
    "wof:name":"Survewadi",
    "wof:placetype":"locality",
    "wof:population":101
},
  "geometry": {"coordinates":[73.716375,16.628458],"type":"Point"}
}