{
  "type": "Feature",
  "properties": {
    "gn:admin1_code":"30",
    "gn:admin2_code":"260.0",
    "gn:asciiname":"Minutang",
    "gn:country_code":"IN",
    "gn:dem":1084,
    "gn:feature_class":"P",
    "gn:feature_code":"PPL",
    "gn:name":"Minutang",
    "gn:population":0,
    "gn:timezone":"Asia/Kolkata",
    "iso:country":"IN",
    "wof:name":"Minutang",
    "wof:placetype":"locality"
},
  "geometry": {"coordinates":[96.53157,28.19838],"type":"Point"}
}