{
  "type": "Feature",
  "properties": {
    "gn:admin1_code":"36.0",
    "gn:admin2_code":"151.0",
    "gn:asciiname":"Banjaria Kallu",
    "gn:country_code":"IN",
    "gn:dem":190,
    "gn:feature_class":"P",
    "gn:feature_code":"PPL",
    "gn:name":"Banjaria Kallu",
    "gn:population":0,
    "gn:timezone":"Asia/Kolkata",
    "iso:country":"IN",
    "ks:ks_name":"Banjaria Kallu",
    "ks:ks_pop":38,
    "ks:ks_type":"VILLAGE",
    "name:eng_x_preferred":[
        "Banjaria Kallu"
    ],
    "wof:name":"Banjaria Kallu",
    "wof:placetype":"locality",
    "wof:population":38
},
  "geometry": {"coordinates":[79.802578,28.73263],"type":"Point"}
}