{
  "type": "Feature",
  "properties": {
    "gn:admin1_code":"36.0",
    "gn:admin2_code":"172.0",
    "gn:asciiname":"Daryapur",
    "gn:country_code":"IN",
    "gn:dem":113,
    "gn:feature_class":"P",
    "gn:feature_code":"PPL",
    "gn:name":"Dary\u0101pur",
    "gn:population":0,
    "gn:timezone":"Asia/Kolkata",
    "iso:country":"IN",
    "name:ben_x_preferred":[
        "\u09a6\u09be\u09b0\u09bf\u09af\u09bc\u09be\u09aa\u09c1\u09b0 \u09ac\u09be\u09a8\u09cb\u09b8\u09be"
    ],
    "name:bpy_x_preferred":[
        "\u09a6\u09be\u09b0\u09bf\u09af\u09bc\u09be\u09aa\u09c1\u09b0 \u09ac\u09be\u09a8\u09cb\u09b8\u09be"
    ],
    "name:ceb_x_preferred":[
        "Dary\u0101pur"
    ],
    "name:ind_x_preferred":[
        "Daryapur Banosa"
    ],
    "name:ita_x_preferred":[
        "Daryapur Banosa"
    ],
    "name:msa_x_preferred":[
        "Daryapur Banosa"
    ],
    "name:new_x_preferred":[
        "\u0926\u0930\u093f\u092f\u093e\u092a\u0941\u0930 \u092c\u0928\u094b\u0938\u093e"
    ],
    "name:nld_x_preferred":[
        "Daryapur Banosa"
    ],
    "name:swe_x_preferred":[
        "Dary\u0101pur"
    ],
    "name:urd_x_preferred":[
        "\u062f\u0631\u06cc\u0627\u067e\u0648\u0631"
    ],
    "name:vie_x_preferred":[
        "Daryapur Banosa"
    ],
    "name:zho_x_preferred":[
        "\u8fbe\u91cc\u4e9a\u666e\u5c14\u5df4\u8bfa\u8428"
    ],
    "wof:name":"Daryapur",
    "wof:placetype":"neighbourhood"
},
  "geometry": {"coordinates":[81.22975,25.84048],"type":"Point"}
}