{
  "type": "Feature",
  "properties": {
    "iso:country":"IN",
    "ks:ks_alt_nam":"KOREWASTI",
    "ks:ks_name":"Korewasti",
    "ks:ks_pop":79,
    "ks:ks_type":"HABITATION",
    "name:eng_x_preferred":[
        "Korewasti"
    ],
    "wof:name":"Korewasti",
    "wof:placetype":"locality",
    "wof:population":79
},
  "geometry": {"coordinates":[74.700928,17.052312],"type":"Point"}
}