{
  "type": "Feature",
  "properties": {
    "gn:admin1_code":"39.0",
    "gn:admin2_code":"65.0",
    "gn:asciiname":"Luitokra",
    "gn:country_code":"IN",
    "gn:dem":1589,
    "gn:feature_class":"P",
    "gn:feature_code":"PPL",
    "gn:name":"Luitokra",
    "gn:population":0,
    "gn:timezone":"Asia/Kolkata",
    "iso:country":"IN",
    "wof:name":"Luitokra",
    "wof:placetype":"locality"
},
  "geometry": {"coordinates":[79.94450000000001,29.38056],"type":"Point"}
}