{
  "type": "Feature",
  "properties": {
    "iso:country":"IN",
    "ks:ks_alt_nam":"Korukondavari HPeta",
    "ks:ks_name":"Korukondavari Hpeta",
    "ks:ks_pop":748,
    "ks:ks_type":"HABITATION",
    "name:eng_x_preferred":[
        "Korukondavari Hpeta"
    ],
    "wof:name":"Korukondavari Hpeta",
    "wof:placetype":"locality",
    "wof:population":748
},
  "geometry": {"coordinates":[81.905069,16.602097],"type":"Point"}
}