{
  "type": "Feature",
  "properties": {
    "gn:admin1_code":"39.0",
    "gn:admin2_code":"057",
    "gn:asciiname":"Karnaprayag",
    "gn:country_code":"IN",
    "gn:dem":810,
    "gn:feature_class":"P",
    "gn:feature_code":"PPL",
    "gn:name":"Karnapray\u0101g",
    "gn:population":0,
    "gn:timezone":"Asia/Kolkata",
    "iso:country":"IN",
    "name:und_x_variant":[
        "Karnprayag",
        "Karnapray\u0101g"
    ],
    "wof:name":"Karnaprayag",
    "wof:placetype":"locality"
},
  "geometry": {"coordinates":[79.22028,30.25942],"type":"Point"}
}