{
  "type": "Feature",
  "properties": {
    "gn:admin1_code":"39.0",
    "gn:admin2_code":"057",
    "gn:asciiname":"Karnaprayag",
    "gn:country_code":"IN",
    "gn:dem":810,
    "gn:feature_class":"P",
    "gn:feature_code":"PPL",
    "gn:name":"Karnapray\u0101g",
    "gn:population":0,
    "gn:timezone":"Asia/Kolkata",
    "iso:country":"IN",
    "ks:ks_alt_nam":"Karnapray\u0101g",
    "ks:ks_name":"Karnaprayag",
    "ks:ks_type":"URBAN",
    "name:bih_x_preferred":[
        "\u0915\u0930\u094d\u0923\u092a\u094d\u0930\u092f\u093e\u0917"
    ],
    "name:bpy_x_preferred":[
        "\u0995\u09b0\u09a8 \u09aa\u09cd\u09b0\u09af\u09bc\u09be\u0997"
    ],
    "name:cat_x_preferred":[
        "Karnaprayag"
    ],
    "name:ceb_x_preferred":[
        "Karnapray\u0101g"
    ],
    "name:eng_x_preferred":[
        "Karnaprayag"
    ],
    "name:eng_x_variant":[
        "Karnapray\u0101g"
    ],
    "name:guj_x_preferred":[
        "\u0a95\u0ab0\u0acd\u0aa3 \u0aaa\u0acd\u0ab0\u0aaf\u0abe\u0a97"
    ],
    "name:hin_x_preferred":[
        "\u0915\u0930\u094d\u0923\u092a\u094d\u0930\u092f\u093e\u0917"
    ],
    "name:ita_x_preferred":[
        "Karnaprayag"
    ],
    "name:kan_x_preferred":[
        "\u0c95\u0cb0\u0ccd\u0ca3\u0caa\u0ccd\u0cb0\u0caf\u0cbe\u0c97"
    ],
    "name:mlg_x_preferred":[
        "Karnaprayag"
    ],
    "name:msa_x_preferred":[
        "Karn Prayag"
    ],
    "name:nep_x_preferred":[
        "\u0915\u0930\u094d\u0923\u092a\u094d\u0930\u092f\u093e\u0917"
    ],
    "name:new_x_preferred":[
        "\u0915\u0930\u094d\u0928 \u092a\u094d\u0930\u092f\u093e\u0917"
    ],
    "name:nld_x_preferred":[
        "Karn Prayag"
    ],
    "name:ori_x_preferred":[
        "\u0b15\u0b30\u0b4d\u0b23\u0b2a\u0b4d\u0b30\u0b5f\u0b3e\u0b17"
    ],
    "name:pan_x_preferred":[
        "\u0a15\u0a30\u0a23 \u0a2a\u0a30\u0a3f\u0a06\u0a17"
    ],
    "name:pol_x_preferred":[
        "Karnaprayag"
    ],
    "name:por_x_preferred":[
        "Karn Prayag"
    ],
    "name:swe_x_preferred":[
        "Karnapray\u0101g"
    ],
    "name:und_x_variant":[
        "Karnprayag"
    ],
    "name:vie_x_preferred":[
        "Karn Prayag"
    ],
    "name:zho_x_preferred":[
        "\u5361\u5c14\u6069\u666e\u62c9\u8036\u683c"
    ],
    "wof:name":"Karnaprayag",
    "wof:placetype":"locality"
},
  "geometry": {"coordinates":[79.220279,30.259418],"type":"Point"}
}