{
  "type": "Feature",
  "properties": {
    "iso:country":"IN",
    "ks:ks_name":"Sankola",
    "ks:ks_pop":756,
    "ks:ks_type":"VILLAGE",
    "ks:ks_uagg_main":0,
    "name:eng_x_preferred":[
        "Sankola"
    ],
    "wof:name":"Sankola",
    "wof:placetype":"neighbourhood",
    "wof:population":756
},
  "geometry": {"coordinates":[87.943759,25.560918],"type":"Point"}
}