{
  "type": "Feature",
  "properties": {
    "iso:country":"IN",
    "ks:ks_name":"Khadikapada",
    "ks:ks_pop":657,
    "ks:ks_type":"HABITATION",
    "name:eng_x_preferred":[
        "Khadikapada"
    ],
    "wof:name":"Khadikapada",
    "wof:placetype":"locality",
    "wof:population":657
},
  "geometry": {"coordinates":[86.734759,21.647589],"type":"Point"}
}