{
  "type": "Feature",
  "properties": {
    "iso:country":"IN",
    "ks:ks_name":"Mlleshpet",
    "ks:ks_pop":76,
    "ks:ks_type":"HABITATION",
    "name:eng_x_preferred":[
        "Mlleshpet"
    ],
    "wof:name":"Mlleshpet",
    "wof:placetype":"locality",
    "wof:population":76
},
  "geometry": {"coordinates":[78.55185299999999,19.31458],"type":"Point"}
}