{
  "type": "Feature",
  "properties": {
    "iso:country":"IN",
    "ks:ks_name":"Laxmipura",
    "ks:ks_pop":1456,
    "ks:ks_type":"VILLAGE",
    "ks:ks_uagg_main":0,
    "name:eng_x_preferred":[
        "Laxmipura"
    ],
    "wof:name":"Laxmipura",
    "wof:placetype":"locality",
    "wof:population":1456
},
  "geometry": {"coordinates":[77.59127700000001,12.822084],"type":"Point"}
}