{
  "type": "Feature",
  "properties": {
    "gn:admin1_code":"36.0",
    "gn:admin2_code":"137.0",
    "gn:asciiname":"Fazilpur",
    "gn:country_code":"IN",
    "gn:dem":217,
    "gn:feature_class":"P",
    "gn:feature_code":"PPL",
    "gn:name":"F\u0101zilpur",
    "gn:population":0,
    "gn:timezone":"Asia/Kolkata",
    "iso:country":"IN",
    "name:pol_x_preferred":[
        "Fazilpur"
    ],
    "name:urd_x_preferred":[
        "\u0641\u0627\u0636\u0644 \u067e\u0648\u0631"
    ],
    "wof:name":"Fazilpur",
    "wof:placetype":"locality"
},
  "geometry": {"coordinates":[78.44069,28.90169],"type":"Point"}
}