{
  "type": "Feature",
  "properties": {
    "gn:admin1_code":"35",
    "gn:admin2_code":"426.0",
    "gn:asciiname":"Mahra",
    "gn:country_code":"IN",
    "gn:dem":337,
    "gn:feature_class":"P",
    "gn:feature_code":"PPL",
    "gn:name":"M\u0101hra",
    "gn:population":0,
    "gn:timezone":"Asia/Kolkata",
    "iso:country":"IN",
    "name:cat_x_preferred":[
        "Mahra"
    ],
    "name:ceb_x_preferred":[
        "Mahra"
    ],
    "wof:name":"Mahra",
    "wof:placetype":"locality"
},
  "geometry": {"coordinates":[80.29571999999997,24.56391],"type":"Point"}
}