{
  "type": "Feature",
  "properties": {
    "gn:admin1_code":"38.0",
    "gn:admin2_code":"347.0",
    "gn:asciiname":"Dokwa",
    "gn:country_code":"IN",
    "gn:dem":411,
    "gn:feature_class":"P",
    "gn:feature_code":"PPL",
    "gn:name":"Dokw\u0101",
    "gn:population":0,
    "gn:timezone":"Asia/Kolkata",
    "iso:country":"IN",
    "ks:ks_alt_nam":"Dokw\u0101",
    "ks:ks_name":"Dokwa",
    "ks:ks_pop":127,
    "ks:ks_type":"VILLAGE",
    "name:eng_x_preferred":[
        "Dokwa"
    ],
    "name:eng_x_variant":[
        "Dokw\u0101"
    ],
    "wof:name":"Dokwa",
    "wof:placetype":"locality",
    "wof:population":127
},
  "geometry": {"coordinates":[84.68056,24.228737],"type":"Point"}
}