{
  "type": "Feature",
  "properties": {
    "iso:country":"IN",
    "ks:ks_name":"Saraiya",
    "ks:ks_pop":331,
    "ks:ks_type":"HABITATION",
    "name:eng_x_preferred":[
        "Saraiya"
    ],
    "wof:name":"Saraiya",
    "wof:placetype":"locality",
    "wof:population":331
},
  "geometry": {"coordinates":[79.569502,26.780314],"type":"Point"}
}