{
  "type": "Feature",
  "properties": {
    "iso:country":"IN",
    "ks:ks_name":"Upper Dasda",
    "ks:ks_pop":62,
    "ks:ks_type":"HABITATION",
    "ks:ks_uagg_main":0,
    "name:eng_x_preferred":[
        "Upper Dasda"
    ],
    "wof:name":"Upper Dasda",
    "wof:placetype":"neighbourhood",
    "wof:population":62
},
  "geometry": {"coordinates":[92.20322400000001,23.950638],"type":"Point"}
}