{
  "type": "Feature",
  "properties": {
    "iso:country":"IN",
    "ks:ks_name":"Hotmouha",
    "ks:ks_pop":74,
    "ks:ks_type":"HABITATION",
    "name:eng_x_preferred":[
        "Hotmouha"
    ],
    "wof:name":"Hotmouha",
    "wof:placetype":"locality",
    "wof:population":74
},
  "geometry": {"coordinates":[82.264455,20.626037],"type":"Point"}
}