{
  "type": "Feature",
  "properties": {
    "gn:admin1_code":"36",
    "gn:admin2_code":"188.0",
    "gn:asciiname":"Kalyanpur",
    "gn:country_code":"IN",
    "gn:dem":81,
    "gn:feature_class":"P",
    "gn:feature_code":"PPL",
    "gn:name":"Kaly\u0101npur",
    "gn:population":0,
    "gn:timezone":"Asia/Kolkata",
    "iso:country":"IN",
    "ks:ks_alt_nam":"Kaly\u0101npur",
    "ks:ks_name":"Kalyanpur",
    "ks:ks_pop":627,
    "ks:ks_type":"VILLAGE",
    "ks:ks_uagg_main":0,
    "name:ceb_x_preferred":[
        "Kalyanpur"
    ],
    "name:eng_x_preferred":[
        "Kalyanpur"
    ],
    "name:eng_x_variant":[
        "Kaly\u0101npur"
    ],
    "name:fra_x_preferred":[
        "Kalyanpur"
    ],
    "name:new_x_preferred":[
        "\u0915\u0932\u094d\u092f\u093e\u0923\u092a\u0941\u0930 \u0917\u093e\u0935\u093f\u0938"
    ],
    "name:pol_x_preferred":[
        "Kalyanpur"
    ],
    "name:swe_x_preferred":[
        "Kalyanpur"
    ],
    "wof:name":"Kalyanpur",
    "wof:placetype":"neighbourhood",
    "wof:population":627
},
  "geometry": {"coordinates":[83.335505,26.571476],"type":"Point"}
}