{
  "type": "Feature",
  "properties": {
    "iso:country":"IN",
    "ks:ks_name":"Samathuvapuram",
    "ks:ks_pop":54,
    "ks:ks_type":"HABITATION",
    "ks:ks_uagg_main":0,
    "name:eng_x_preferred":[
        "Samathuvapuram"
    ],
    "wof:name":"Samathuvapuram",
    "wof:placetype":"neighbourhood",
    "wof:population":54
},
  "geometry": {"coordinates":[78.88243900000001,12.280428],"type":"Point"}
}