{
  "type": "Feature",
  "properties": {
    "gn:admin1_code":"19.0",
    "gn:admin2_code":"569",
    "gn:asciiname":"Barkur",
    "gn:country_code":"IN",
    "gn:dem":20,
    "gn:feature_class":"P",
    "gn:feature_code":"PPL",
    "gn:name":"B\u0101rk\u016br",
    "gn:population":0,
    "gn:timezone":"Asia/Kolkata",
    "iso:country":"IN",
    "name:cat_x_preferred":[
        "Barkur"
    ],
    "name:ind_x_preferred":[
        "Barkur"
    ],
    "name:ita_x_preferred":[
        "Barkur"
    ],
    "name:kan_x_preferred":[
        "\u0cac\u0cbe\u0cb0\u0ccd\u0c95\u0cc2\u0cb0\u0cc1"
    ],
    "name:tcy_x_preferred":[
        "\u0cac\u0cbe\u0cb0\u0ccd\u0c95\u0cc2\u0cb0\u0cc1"
    ],
    "name:und_x_variant":[
        "B\u0101rk\u016bru",
        "B\u0101rk\u016br"
    ],
    "wof:name":"Barkur",
    "wof:placetype":"locality"
},
  "geometry": {"coordinates":[74.74639000000001,13.46556],"type":"Point"}
}