{
  "type": "Feature",
  "properties": {
    "iso:country":"IN",
    "ks:ks_alt_nam":"Jiban sardar para",
    "ks:ks_name":"Jiban Sardar Para",
    "ks:ks_pop":121,
    "ks:ks_type":"HABITATION",
    "name:eng_x_preferred":[
        "Jiban Sardar Para"
    ],
    "wof:name":"Jiban Sardar Para",
    "wof:placetype":"locality",
    "wof:population":121
},
  "geometry": {"coordinates":[91.737166,23.296264],"type":"Point"}
}