{
  "type": "Feature",
  "properties": {
    "iso:country":"IN",
    "ks:ks_name":"Sandiya",
    "ks:ks_pop":326,
    "ks:ks_type":"HABITATION",
    "name:eng_x_preferred":[
        "Sandiya"
    ],
    "wof:name":"Sandiya",
    "wof:placetype":"locality",
    "wof:population":326
},
  "geometry": {"coordinates":[82.725942,27.389053],"type":"Point"}
}