{
  "type": "Feature",
  "properties": {
    "gn:admin1_code":"19.0",
    "gn:admin2_code":"579",
    "gn:asciiname":"Jiwangi",
    "gn:country_code":"IN",
    "gn:dem":471,
    "gn:feature_class":"P",
    "gn:feature_code":"PPL",
    "gn:name":"J\u012bwangi",
    "gn:population":0,
    "gn:timezone":"Asia/Kolkata",
    "iso:country":"IN",
    "name:und_x_variant":[
        "J\u0101wangi",
        "J\u012bwangi"
    ],
    "wof:name":"Jiwangi",
    "wof:placetype":"neighbourhood"
},
  "geometry": {"coordinates":[77.02946,17.52732],"type":"Point"}
}