{
  "type": "Feature",
  "properties": {
    "iso:country":"IN",
    "ks:ks_name":"Ramavaram",
    "ks:ks_pop":82,
    "ks:ks_type":"VILLAGE",
    "name:eng_x_preferred":[
        "Ramavaram"
    ],
    "wof:name":"Ramavaram",
    "wof:placetype":"locality",
    "wof:population":82
},
  "geometry": {"coordinates":[80.251386,18.008009],"type":"Point"}
}