{
  "type": "Feature",
  "properties": {
    "gn:admin1_code":"34.0",
    "gn:admin2_code":"240.0",
    "gn:asciiname":"Rustam Chak",
    "gn:country_code":"IN",
    "gn:dem":79,
    "gn:feature_class":"P",
    "gn:feature_code":"PPL",
    "gn:name":"Rustam Chak",
    "gn:population":0,
    "gn:timezone":"Asia/Kolkata",
    "iso:country":"IN",
    "ks:ks_name":"Rustan Chak",
    "ks:ks_pop":867,
    "ks:ks_type":"VILLAGE",
    "name:eng_x_preferred":[
        "Rustan Chak"
    ],
    "name:eng_x_variant":[
        "Rustam Chak"
    ],
    "wof:name":"Rustan Chak",
    "wof:placetype":"locality",
    "wof:population":867
},
  "geometry": {"coordinates":[84.877073,25.085461],"type":"Point"}
}