{
  "type": "Feature",
  "properties": {
    "iso:country":"IN",
    "ks:ks_name":"Neraduputtu",
    "ks:ks_pop":18,
    "ks:ks_type":"HABITATION",
    "name:eng_x_preferred":[
        "Neraduputtu"
    ],
    "wof:name":"Neraduputtu",
    "wof:placetype":"locality",
    "wof:population":18
},
  "geometry": {"coordinates":[82.37720299999999,18.241505],"type":"Point"}
}