{
  "type": "Feature",
  "properties": {
    "iso:country":"IN",
    "ks:ks_name":"No.1 Garubandha",
    "ks:ks_pop":209,
    "ks:ks_type":"VILLAGE",
    "name:eng_x_preferred":[
        "No.1 Garubandha"
    ],
    "wof:name":"No.1 Garubandha",
    "wof:placetype":"locality",
    "wof:population":209
},
  "geometry": {"coordinates":[93.79641100000001,27.045338],"type":"Point"}
}