{
  "type": "Feature",
  "properties": {
    "iso:country":"IN",
    "ks:ks_alt_nam":"Badhauli Fateh Kh\u0101n",
    "ks:ks_name":"Badhauli Fateh Khan",
    "ks:ks_type":"VILLAGE",
    "name:eng_x_preferred":[
        "Badhauli Fateh Khan"
    ],
    "name:eng_x_variant":[
        "Badhauli Fateh Kh\u0101n"
    ],
    "wof:name":"Badhauli Fateh Khan",
    "wof:placetype":"neighbourhood"
},
  "geometry": {"coordinates":[78.071771,27.833543],"type":"Point"}
}