{
  "type": "Feature",
  "properties": {
    "iso:country":"IN",
    "ks:ks_name":"Gosainpur",
    "ks:ks_pop":675,
    "ks:ks_type":"VILLAGE",
    "ks:ks_uagg_main":0,
    "name:eng_x_preferred":[
        "Gosainpur"
    ],
    "wof:name":"Gosainpur",
    "wof:placetype":"neighbourhood",
    "wof:population":675
},
  "geometry": {"coordinates":[85.54373699999999,26.549228],"type":"Point"}
}