{
  "type": "Feature",
  "properties": {
    "iso:country":"IN",
    "ks:ks_name":"Zarnawadi",
    "ks:ks_pop":1449,
    "ks:ks_type":"VILLAGE",
    "ks:ks_uagg_main":0,
    "name:eng_x_preferred":[
        "Zarnawadi"
    ],
    "wof:name":"Zarnawadi",
    "wof:placetype":"neighbourhood",
    "wof:population":1449
},
  "geometry": {"coordinates":[73.558767,21.614776],"type":"Point"}
}