{
  "type": "Feature",
  "properties": {
    "iso:country":"IN",
    "ks:ks_name":"Vastrapur",
    "ks:ks_pop":24656,
    "ks:ks_type":"VILLAGE",
    "ks:ks_uagg_main":0,
    "name:eng_x_preferred":[
        "Vastrapur"
    ],
    "wof:name":"Vastrapur",
    "wof:placetype":"neighbourhood",
    "wof:population":24656
},
  "geometry": {"coordinates":[72.529245,23.034844],"type":"Point"}
}