{
  "type": "Feature",
  "properties": {
    "iso:country":"IN",
    "ks:ks_name":"Uladpur",
    "ks:ks_pop":61,
    "ks:ks_type":"VILLAGE",
    "name:eng_x_preferred":[
        "Uladpur"
    ],
    "wof:name":"Uladpur",
    "wof:placetype":"locality",
    "wof:population":61
},
  "geometry": {"coordinates":[87.575473,21.872504],"type":"Point"}
}