{
  "type": "Feature",
  "properties": {
    "iso:country":"IN",
    "ks:ks_alt_nam":"Balw\u0101ra",
    "ks:ks_name":"Balwara",
    "ks:ks_type":"VILLAGE",
    "name:eng_x_preferred":[
        "Balwara"
    ],
    "name:eng_x_variant":[
        "Balw\u0101ra"
    ],
    "wof:name":"Balwara",
    "wof:placetype":"locality"
},
  "geometry": {"coordinates":[76.45249800000001,21.855736],"type":"Point"}
}