{
  "type": "Feature",
  "properties": {
    "iso:country":"IN",
    "ks:ks_name":"Kartikona",
    "ks:ks_pop":179,
    "ks:ks_type":"VILLAGE",
    "name:eng_x_preferred":[
        "Kartikona"
    ],
    "wof:name":"Kartikona",
    "wof:placetype":"locality",
    "wof:population":179
},
  "geometry": {"coordinates":[83.56384300000001,19.138978],"type":"Point"}
}