{
  "type": "Feature",
  "properties": {
    "iso:country":"IN",
    "ks:ks_name":"Mallu Majra",
    "ks:ks_pop":566,
    "ks:ks_type":"VILLAGE",
    "name:eng_x_preferred":[
        "Mallu Majra"
    ],
    "wof:name":"Mallu Majra",
    "wof:placetype":"locality",
    "wof:population":566
},
  "geometry": {"coordinates":[75.829176,30.40641],"type":"Point"}
}