{
  "type": "Feature",
  "properties": {
    "iso:country":"IN",
    "ks:ks_name":"Rasagoundampalayam",
    "ks:ks_pop":490,
    "ks:ks_type":"HABITATION",
    "ks:ks_uagg_main":0,
    "name:eng_x_preferred":[
        "Rasagoundampalayam"
    ],
    "wof:name":"Rasagoundampalayam",
    "wof:placetype":"neighbourhood",
    "wof:population":490
},
  "geometry": {"coordinates":[77.27273599999999,11.019268],"type":"Point"}
}