{
  "type": "Feature",
  "properties": {
    "gn:admin1_code":"11",
    "gn:admin2_code":"27.0",
    "gn:asciiname":"Chauk",
    "gn:country_code":"IN",
    "gn:dem":1089,
    "gn:feature_class":"P",
    "gn:feature_code":"PPL",
    "gn:name":"Chauk",
    "gn:population":0,
    "gn:timezone":"Asia/Kolkata",
    "iso:country":"IN",
    "name:ceb_x_preferred":[
        "Chauk"
    ],
    "name:fra_x_preferred":[
        "Chauk"
    ],
    "name:ind_x_preferred":[
        "Chauk"
    ],
    "name:lit_x_preferred":[
        "\u010cokas"
    ],
    "name:mya_x_preferred":[
        "\u1001\u103b\u1031\u102c\u1000\u103a\u1019\u103c\u102d\u102f\u1037"
    ],
    "name:pol_x_preferred":[
        "Czauk"
    ],
    "name:rus_x_preferred":[
        "\u0427\u0430\u0443"
    ],
    "name:shn_x_preferred":[
        "\u1076\u103b\u103d\u1075\u103a\u1089\u104a \u101d\u1035\u1004\u103a\u1038"
    ],
    "name:swe_x_preferred":[
        "Chauk"
    ],
    "name:tha_x_preferred":[
        "\u0e40\u0e0a\u0e32\u0e30"
    ],
    "wof:name":"Chauk",
    "wof:placetype":"locality"
},
  "geometry": {"coordinates":[76.80521999999998,31.57472000000001],"type":"Point"}
}