{
  "type": "Feature",
  "properties": {
    "gn:admin1_code":"11",
    "gn:admin2_code":"27.0",
    "gn:asciiname":"Chauk",
    "gn:country_code":"IN",
    "gn:dem":1089,
    "gn:feature_class":"P",
    "gn:feature_code":"PPL",
    "gn:name":"Chauk",
    "gn:population":0,
    "gn:timezone":"Asia/Kolkata",
    "iso:country":"IN",
    "name:ara_x_preferred":[
        "\u0634\u0648\u0643"
    ],
    "name:ben_x_preferred":[
        "\u099a\u09be\u0989\u0995"
    ],
    "name:ceb_x_preferred":[
        "Chauk"
    ],
    "name:deu_x_preferred":[
        "Chauk"
    ],
    "name:ell_x_preferred":[
        "\u03a4\u03c3\u03ac\u03bf\u03c5\u03ba"
    ],
    "name:fas_x_preferred":[
        "\u0686\u0627\u0626\u0648\u06a9"
    ],
    "name:fra_x_preferred":[
        "Chauk"
    ],
    "name:heb_x_preferred":[
        "\u05e6'\u05d0\u05d5\u05e7"
    ],
    "name:hin_x_preferred":[
        "\u091a\u093e\u0909\u0915"
    ],
    "name:hun_x_preferred":[
        "Chauk"
    ],
    "name:ind_x_preferred":[
        "Chauk"
    ],
    "name:ita_x_preferred":[
        "Chauk"
    ],
    "name:kor_x_preferred":[
        "\ucc28\uc6b1"
    ],
    "name:lit_x_preferred":[
        "\u010cokas"
    ],
    "name:mya_x_preferred":[
        "\u1001\u103b\u1031\u102c\u1000\u103a\u1019\u103c\u102d\u102f\u1037"
    ],
    "name:pol_x_preferred":[
        "Czauk"
    ],
    "name:por_x_preferred":[
        "Chauk"
    ],
    "name:rus_x_preferred":[
        "\u0427\u0430\u0443"
    ],
    "name:shn_x_preferred":[
        "\u1076\u103b\u103d\u1075\u103a\u1089\u104a \u101d\u1035\u1004\u103a\u1038"
    ],
    "name:spa_x_preferred":[
        "Chauk"
    ],
    "name:swe_x_preferred":[
        "Chauk"
    ],
    "name:tha_x_preferred":[
        "\u0e40\u0e0a\u0e32\u0e30"
    ],
    "name:tur_x_preferred":[
        "Chauk"
    ],
    "name:ukr_x_preferred":[
        "\u0427\u0430\u0443"
    ],
    "name:urd_x_preferred":[
        "\u0686\u0627\u0624\u06a9"
    ],
    "name:vie_x_preferred":[
        "Chauk"
    ],
    "name:zho_cn_x_preferred":[
        "\u7a0d\u57e0"
    ],
    "name:zho_tw_x_preferred":[
        "\u55ac\u514b"
    ],
    "wof:name":"Chauk",
    "wof:placetype":"locality"
},
  "geometry": {"coordinates":[76.80522000000001,31.57472],"type":"Point"}
}