{
  "type": "Feature",
  "properties": {
    "iso:country":"IN",
    "ks:ks_name":"Savkarbhatrakeri",
    "ks:ks_pop":25,
    "ks:ks_type":"HABITATION",
    "name:eng_x_preferred":[
        "Savkarbhatrakeri"
    ],
    "wof:name":"Savkarbhatrakeri",
    "wof:placetype":"locality",
    "wof:population":25
},
  "geometry": {"coordinates":[74.809882,14.574869],"type":"Point"}
}