{
  "type": "Feature",
  "properties": {
    "iso:country":"IN",
    "ks:ks_name":"Purba Kurshamari",
    "ks:ks_pop":1240,
    "ks:ks_type":"HABITATION",
    "name:eng_x_preferred":[
        "Purba Kurshamari"
    ],
    "wof:name":"Purba Kurshamari",
    "wof:placetype":"locality",
    "wof:population":1240
},
  "geometry": {"coordinates":[89.26727200000001,26.247859],"type":"Point"}
}