{
  "type": "Feature",
  "properties": {
    "iso:country":"IN",
    "ks:ks_name":"Sitoli",
    "ks:ks_pop":22,
    "ks:ks_type":"VILLAGE",
    "name:eng_x_preferred":[
        "Sitoli"
    ],
    "wof:name":"Sitoli",
    "wof:placetype":"locality",
    "wof:population":22
},
  "geometry": {"coordinates":[79.05105,29.925636],"type":"Point"}
}