{
  "type": "Feature",
  "properties": {
    "iso:country":"IN",
    "ks:ks_name":"Baramelu",
    "ks:ks_pop":113,
    "ks:ks_type":"HABITATION",
    "name:eng_x_preferred":[
        "Baramelu"
    ],
    "wof:name":"Baramelu",
    "wof:placetype":"locality",
    "wof:population":113
},
  "geometry": {"coordinates":[75.260126,12.886987],"type":"Point"}
}