{
  "type": "Feature",
  "properties": {
    "gn:admin1_code":"35.0",
    "gn:admin2_code":"421",
    "gn:asciiname":"Dhoha",
    "gn:country_code":"IN",
    "gn:dem":324,
    "gn:feature_class":"P",
    "gn:feature_code":"PPL",
    "gn:name":"Dhoha",
    "gn:population":0,
    "gn:timezone":"Asia/Kolkata",
    "iso:country":"IN",
    "name:und_x_variant":[
        "Dhoh\u0101"
    ],
    "wof:name":"Dhoha",
    "wof:placetype":"locality"
},
  "geometry": {"coordinates":[77.90821,26.06392],"type":"Point"}
}