{
  "type": "Feature",
  "properties": {
    "gn:admin1_code":"11.0",
    "gn:admin2_code":"26.0",
    "gn:asciiname":"Shagan",
    "gn:country_code":"IN",
    "gn:dem":2218,
    "gn:feature_class":"P",
    "gn:feature_code":"PPL",
    "gn:name":"Sh\u0101g\u0101n",
    "gn:population":0,
    "gn:timezone":"Asia/Kolkata",
    "iso:country":"IN",
    "name:ceb_x_preferred":[
        "Shagan"
    ],
    "name:swe_x_preferred":[
        "Shagan"
    ],
    "wof:name":"Shagan",
    "wof:placetype":"locality"
},
  "geometry": {"coordinates":[77.45224,31.44514],"type":"Point"}
}