{
  "type": "Feature",
  "properties": {
    "gn:admin1_code":"36",
    "gn:admin2_code":"172.0",
    "gn:asciiname":"Astha",
    "gn:country_code":"IN",
    "gn:dem":122,
    "gn:feature_class":"P",
    "gn:feature_code":"PPL",
    "gn:name":"Astha",
    "gn:population":0,
    "gn:timezone":"Asia/Kolkata",
    "iso:country":"IN",
    "name:vie_x_preferred":[
        "Astha"
    ],
    "wof:name":"Astha",
    "wof:placetype":"locality"
},
  "geometry": {"coordinates":[80.70555999999998,25.96857],"type":"Point"}
}