{
  "type": "Feature",
  "properties": {
    "iso:country":"IN",
    "ks:ks_name":"Ram Sala",
    "ks:ks_pop":165,
    "ks:ks_type":"HABITATION",
    "ks:ks_uagg_main":0,
    "name:eng_x_preferred":[
        "Ram Sala"
    ],
    "wof:name":"Ram Sala",
    "wof:placetype":"neighbourhood",
    "wof:population":165
},
  "geometry": {"coordinates":[81.5331,26.4057],"type":"Point"}
}