{
  "type": "Feature",
  "properties": {
    "iso:country":"IN",
    "ks:ks_name":"Mushahari Tola",
    "ks:ks_pop":446,
    "ks:ks_type":"HABITATION",
    "ks:ks_uagg_main":0,
    "name:eng_x_preferred":[
        "Mushahari Tola"
    ],
    "wof:name":"Mushahari Tola",
    "wof:placetype":"neighbourhood",
    "wof:population":446
},
  "geometry": {"coordinates":[86.82953500000001,26.049605],"type":"Point"}
}