{
  "type": "Feature",
  "properties": {
    "iso:country":"IN",
    "ks:ks_name":"Abhrun F",
    "ks:ks_pop":553,
    "ks:ks_type":"HABITATION",
    "ks:ks_uagg_main":0,
    "name:eng_x_preferred":[
        "Abhrun F"
    ],
    "wof:name":"Abhrun F",
    "wof:placetype":"neighbourhood",
    "wof:population":553
},
  "geometry": {"coordinates":[73.228194,20.775389],"type":"Point"}
}