{
  "type": "Feature",
  "properties": {
    "gn:admin1_code":"2.0",
    "gn:admin2_code":"543.0",
    "gn:asciiname":"Chintada",
    "gn:country_code":"IN",
    "gn:dem":98,
    "gn:feature_class":"P",
    "gn:feature_code":"PPL",
    "gn:name":"Chint\u0101da",
    "gn:population":0,
    "gn:timezone":"Asia/Kolkata",
    "iso:country":"IN",
    "name:tel_x_preferred":[
        "\u0c1a\u0c3f\u0c02\u0c24\u0c3e\u0c21"
    ],
    "wof:name":"Chintada",
    "wof:placetype":"locality"
},
  "geometry": {"coordinates":[83.44965000000001,18.6109],"type":"Point"}
}