{
  "type": "Feature",
  "properties": {
    "gn:admin1_code":"11",
    "gn:admin2_code":"27.0",
    "gn:asciiname":"Kua Gahra",
    "gn:country_code":"IN",
    "gn:dem":1274,
    "gn:feature_class":"P",
    "gn:feature_code":"PPL",
    "gn:name":"Kua Gahra",
    "gn:population":0,
    "gn:timezone":"Asia/Kolkata",
    "iso:country":"IN",
    "wof:name":"Kua Gahra",
    "wof:placetype":"locality"
},
  "geometry": {"coordinates":[76.97507,31.49967],"type":"Point"}
}