{
  "type": "Feature",
  "properties": {
    "iso:country":"IN",
    "ks:ks_name":"Jubra",
    "ks:ks_pop":43,
    "ks:ks_type":"HABITATION",
    "name:eng_x_preferred":[
        "Jubra"
    ],
    "wof:name":"Jubra",
    "wof:placetype":"locality",
    "wof:population":43
},
  "geometry": {"coordinates":[80.221918,29.748264],"type":"Point"}
}