{
  "type": "Feature",
  "properties": {
    "gn:admin1_code":"21.0",
    "gn:admin2_code":"398.0",
    "gn:asciiname":"Damonojodi",
    "gn:country_code":"IN",
    "gn:dem":910,
    "gn:feature_class":"P",
    "gn:feature_code":"PPL",
    "gn:name":"Damonojodi",
    "gn:population":0,
    "gn:timezone":"Asia/Kolkata",
    "iso:country":"IN",
    "wof:name":"Damonojodi",
    "wof:placetype":"locality"
},
  "geometry": {"coordinates":[82.91936,18.76323],"type":"Point"}
}