{
  "type": "Feature",
  "properties": {
    "gn:admin1_code":"37",
    "gn:admin2_code":"403.0",
    "gn:asciiname":"Kadurpali",
    "gn:country_code":"IN",
    "gn:dem":218,
    "gn:feature_class":"P",
    "gn:feature_code":"PPL",
    "gn:name":"K\u0101durp\u0101li",
    "gn:population":0,
    "gn:timezone":"Asia/Kolkata",
    "iso:country":"IN",
    "ks:ks_name":"Kandurpali",
    "ks:ks_pop":556,
    "ks:ks_type":"VILLAGE",
    "name:eng_x_preferred":[
        "Kandurpali"
    ],
    "name:eng_x_variant":[
        "Kadurpali"
    ],
    "wof:name":"Kandurpali",
    "wof:placetype":"locality",
    "wof:population":556
},
  "geometry": {"coordinates":[83.356431,21.631399],"type":"Point"}
}