{
  "type": "Feature",
  "properties": {
    "iso:country":"IN",
    "ks:ks_name":"Chapran",
    "ks:ks_pop":155,
    "ks:ks_type":"HABITATION",
    "name:eng_x_preferred":[
        "Chapran"
    ],
    "wof:name":"Chapran",
    "wof:placetype":"locality",
    "wof:population":155
},
  "geometry": {"coordinates":[82.78474300000001,18.571143],"type":"Point"}
}