{
  "type": "Feature",
  "properties": {
    "iso:country":"IN",
    "ks:ks_name":"Bodala",
    "ks:ks_pop":1328,
    "ks:ks_type":"HABITATION",
    "name:eng_x_preferred":[
        "Bodala"
    ],
    "wof:name":"Bodala",
    "wof:placetype":"locality",
    "wof:population":1328
},
  "geometry": {"coordinates":[74.25500599999999,21.768667],"type":"Point"}
}