{
  "type": "Feature",
  "properties": {
    "gn:admin1_code":"36",
    "gn:admin2_code":"201.0",
    "gn:asciiname":"Nagla Karolia",
    "gn:country_code":"IN",
    "gn:dem":164,
    "gn:feature_class":"P",
    "gn:feature_code":"PPL",
    "gn:name":"Nagla Karoli\u0101",
    "gn:population":0,
    "gn:timezone":"Asia/Kolkata",
    "iso:country":"IN",
    "wof:name":"Nagla Karolia",
    "wof:placetype":"neighbourhood"
},
  "geometry": {"coordinates":[79.08848999999999,27.49346],"type":"Point"}
}