{
  "type": "Feature",
  "properties": {
    "iso:country":"IN",
    "ks:ks_name":"Bharti Nagar",
    "ks:ks_pop":224,
    "ks:ks_type":"VILLAGE",
    "name:eng_x_preferred":[
        "Bharti Nagar"
    ],
    "wof:name":"Bharti Nagar",
    "wof:placetype":"locality",
    "wof:population":224
},
  "geometry": {"coordinates":[78.838356,24.109614],"type":"Point"}
}