{
  "type": "Feature",
  "properties": {
    "gn:admin1_code":"12.0",
    "gn:asciiname":"Lowemast",
    "gn:country_code":"IN",
    "gn:dem":2952,
    "gn:feature_class":"P",
    "gn:feature_code":"PPL",
    "gn:name":"Lowemast",
    "gn:population":0,
    "gn:timezone":"Asia/Kolkata",
    "iso:country":"IN",
    "wof:name":"Lowemast",
    "wof:placetype":"locality"
},
  "geometry": {"coordinates":[73.92156999999997,34.41549000000001],"type":"Point"}
}