{
  "type": "Feature",
  "properties": {
    "gn:admin1_code":"12",
    "gn:admin2_code":"6.0",
    "gn:asciiname":"Sial Sui",
    "gn:country_code":"IN",
    "gn:dem":820,
    "gn:feature_class":"P",
    "gn:feature_code":"PPL",
    "gn:name":"Si\u0101l S\u016bi",
    "gn:population":0,
    "gn:timezone":"Asia/Kolkata",
    "iso:country":"IN",
    "wof:name":"Sial Sui",
    "wof:placetype":"locality"
},
  "geometry": {"coordinates":[74.36263000000002,33.22765],"type":"Point"}
}