{
  "type": "Feature",
  "properties": {
    "iso:country":"IN",
    "ks:ks_alt_nam":"RAGHUVANTHPUR HERDUWA",
    "ks:ks_name":"Raghuvanthpur Herduwa",
    "ks:ks_pop":516,
    "ks:ks_type":"HABITATION",
    "name:eng_x_preferred":[
        "Raghuvanthpur Herduwa"
    ],
    "wof:name":"Raghuvanthpur Herduwa",
    "wof:placetype":"locality",
    "wof:population":516
},
  "geometry": {"coordinates":[81.884057,25.635688],"type":"Point"}
}