{
  "type": "Feature",
  "properties": {
    "iso:country":"IN",
    "ks:ks_name":"Pulipara",
    "ks:ks_pop":599,
    "ks:ks_type":"HABITATION",
    "name:eng_x_preferred":[
        "Pulipara"
    ],
    "wof:name":"Pulipara",
    "wof:placetype":"locality",
    "wof:population":599
},
  "geometry": {"coordinates":[76.93195,8.839229],"type":"Point"}
}