{
  "type": "Feature",
  "properties": {
    "gn:admin1_code":"13.0",
    "gn:admin2_code":"588.0",
    "gn:asciiname":"Paivalike",
    "gn:country_code":"IN",
    "gn:dem":68,
    "gn:feature_class":"P",
    "gn:feature_code":"PPLL",
    "gn:name":"Paivalike",
    "gn:population":0,
    "gn:timezone":"Asia/Kolkata",
    "iso:country":"IN",
    "name:mal_x_preferred":[
        "\u0d2a\u0d48\u0d35\u0d46\u0d33\u0d3f\u0d17\u0d46"
    ],
    "wof:name":"Paivalike",
    "wof:placetype":"locality"
},
  "geometry": {"coordinates":[74.99821999999998,12.72553],"type":"Point"}
}