{
  "type": "Feature",
  "properties": {
    "gn:admin1_code":"2",
    "gn:admin2_code":"546.0",
    "gn:asciiname":"Bommidi",
    "gn:country_code":"IN",
    "gn:dem":16,
    "gn:feature_class":"P",
    "gn:feature_code":"PPL",
    "gn:name":"Bommidi",
    "gn:population":0,
    "gn:timezone":"Asia/Kolkata",
    "iso:country":"IN",
    "name:bpy_x_preferred":[
        "\u09ac\u09bf. \u09ae\u09be\u09b2\u09cd\u09b2\u09be\u09aa\u09c1\u09b0\u09ae"
    ],
    "name:ita_x_preferred":[
        "B. Mallapuram"
    ],
    "name:msa_x_preferred":[
        "B. Mallapuram"
    ],
    "name:new_x_preferred":[
        "\u092c\u0940. \u092e\u093e\u0932\u092a\u0941\u0930\u092e"
    ],
    "name:nld_x_preferred":[
        "B. Mallapuram"
    ],
    "name:por_x_preferred":[
        "B. Mallapuram"
    ],
    "name:tam_x_preferred":[
        "\u0baa\u0bbf. \u0bae\u0bb2\u0bcd\u0bb2\u0bbe\u0baa\u0bc1\u0bb0\u0bae\u0bcd"
    ],
    "name:vie_x_preferred":[
        "B. Mallapuram"
    ],
    "wof:name":"Bommidi",
    "wof:placetype":"locality"
},
  "geometry": {"coordinates":[81.47039000000002,16.80114],"type":"Point"}
}