{
  "type": "Feature",
  "properties": {
    "iso:country":"IN",
    "ks:ks_name":"Sutarwadi",
    "ks:ks_pop":81,
    "ks:ks_type":"HABITATION",
    "name:eng_x_preferred":[
        "Sutarwadi"
    ],
    "wof:name":"Sutarwadi",
    "wof:placetype":"locality",
    "wof:population":81
},
  "geometry": {"coordinates":[73.38821299999999,16.478255],"type":"Point"}
}