{
  "type": "Feature",
  "properties": {
    "iso:country":"IN",
    "ks:ks_name":"Sijua",
    "ks:ks_pop":1418,
    "ks:ks_type":"VILLAGE",
    "ks:ks_uagg_main":0,
    "name:eng_x_preferred":[
        "Sijua"
    ],
    "wof:name":"Sijua",
    "wof:placetype":"locality",
    "wof:population":1418
},
  "geometry": {"coordinates":[85.77263499999999,20.22825],"type":"Point"}
}