{
  "type": "Feature",
  "properties": {
    "iso:country":"IN",
    "ks:ks_name":"Kheechiyasar",
    "ks:ks_pop":146,
    "ks:ks_type":"VILLAGE",
    "name:eng_x_preferred":[
        "Kheechiyasar"
    ],
    "wof:name":"Kheechiyasar",
    "wof:placetype":"locality",
    "wof:population":146
},
  "geometry": {"coordinates":[73.630608,27.5814],"type":"Point"}
}