{
  "type": "Feature",
  "properties": {
    "gn:admin1_code":"36.0",
    "gn:admin2_code":"132.0",
    "gn:asciiname":"Gurgajpur",
    "gn:country_code":"IN",
    "gn:dem":258,
    "gn:feature_class":"P",
    "gn:feature_code":"PPL",
    "gn:name":"Gurgajpur",
    "gn:population":0,
    "gn:timezone":"Asia/Kolkata",
    "iso:country":"IN",
    "name:und_x_variant":[
        "Gangd\u0101spur"
    ],
    "wof:name":"Gurgajpur",
    "wof:placetype":"neighbourhood"
},
  "geometry": {"coordinates":[77.75734,29.73191],"type":"Point"}
}