{
  "type": "Feature",
  "properties": {
    "gn:admin1_code":"19",
    "gn:admin2_code":"579.0",
    "gn:asciiname":"Nimbarga",
    "gn:country_code":"IN",
    "gn:dem":448,
    "gn:feature_class":"P",
    "gn:feature_code":"PPL",
    "gn:name":"Nimbarga",
    "gn:population":0,
    "gn:timezone":"Asia/Kolkata",
    "iso:country":"IN",
    "name:ceb_x_preferred":[
        "Nimbarga"
    ],
    "name:swe_x_preferred":[
        "Nimbarga"
    ],
    "name:und_x_variant":[
        "Nimberga",
        "Nimbarga"
    ],
    "wof:name":"Nimbarga",
    "wof:placetype":"locality"
},
  "geometry": {"coordinates":[76.58580000000001,17.38612],"type":"Point"}
}