{
  "type": "Feature",
  "properties": {
    "gn:admin1_code":"10.0",
    "gn:admin2_code":"81.0",
    "gn:asciiname":"Makrana",
    "gn:country_code":"IN",
    "gn:dem":227,
    "gn:feature_class":"P",
    "gn:feature_code":"PPL",
    "gn:name":"Makr\u0101na",
    "gn:population":0,
    "gn:timezone":"Asia/Kolkata",
    "iso:country":"IN",
    "name:ben_x_preferred":[
        "\u09ae\u09be\u0995\u09b0\u09be\u09a8\u09be"
    ],
    "name:bpy_x_preferred":[
        "\u09ae\u09be\u0995\u09b0\u09be\u09a8\u09be"
    ],
    "name:ceb_x_preferred":[
        "Makr\u0101na"
    ],
    "name:hin_x_preferred":[
        "\u092e\u0915\u0930\u093e\u0928\u093e"
    ],
    "name:ita_x_preferred":[
        "Makrana"
    ],
    "name:mlg_x_preferred":[
        "Makrana"
    ],
    "name:msa_x_preferred":[
        "Makrana"
    ],
    "name:new_x_preferred":[
        "\u092e\u0915\u094d\u0930\u0928\u093e"
    ],
    "name:ori_x_preferred":[
        "\u0b2e\u0b3e\u0b15\u0b4d\u0b30\u0b3e\u0b28\u0b3e"
    ],
    "name:rus_x_preferred":[
        "\u041c\u0430\u043a\u0440\u0430\u043d\u0430"
    ],
    "name:swe_x_preferred":[
        "Makrana"
    ],
    "name:urd_x_preferred":[
        "\u0645\u06a9\u0631\u0627\u0646\u0627"
    ],
    "name:vie_x_preferred":[
        "Makrana"
    ],
    "name:xmf_x_preferred":[
        "\u10db\u10d0\u10d9\u10e0\u10d0\u10dc\u10d0"
    ],
    "name:zho_x_preferred":[
        "\u9a6c\u514b\u62c9\u7eb3"
    ],
    "wof:name":"Makrana",
    "wof:placetype":"locality"
},
  "geometry": {"coordinates":[76.27056,28.49478],"type":"Point"}
}