{
  "type": "Feature",
  "properties": {
    "iso:country":"IN",
    "ks:ks_alt_nam":"PHC Rd junction",
    "ks:ks_name":"Phc Rd Junction",
    "ks:ks_pop":1229,
    "ks:ks_type":"HABITATION",
    "name:eng_x_preferred":[
        "Phc Rd Junction"
    ],
    "wof:name":"Phc Rd Junction",
    "wof:placetype":"locality",
    "wof:population":1229
},
  "geometry": {"coordinates":[75.90534,10.875061],"type":"Point"}
}