{
  "type": "Feature",
  "properties": {
    "iso:country":"IN",
    "ks:ks_name":"Karemane",
    "ks:ks_pop":38,
    "ks:ks_type":"HABITATION",
    "name:eng_x_preferred":[
        "Karemane"
    ],
    "wof:name":"Karemane",
    "wof:placetype":"locality",
    "wof:population":38
},
  "geometry": {"coordinates":[74.661959,14.610949],"type":"Point"}
}