{
  "type": "Feature",
  "properties": {
    "gn:admin1_code":"12.0",
    "gn:admin2_code":"006",
    "gn:asciiname":"Bhar Gala",
    "gn:country_code":"IN",
    "gn:dem":1048,
    "gn:feature_class":"P",
    "gn:feature_code":"PPL",
    "gn:name":"Bhar G\u0101la",
    "gn:population":0,
    "gn:timezone":"Asia/Kolkata",
    "iso:country":"IN",
    "wof:name":"Bhar Gala",
    "wof:placetype":"locality"
},
  "geometry": {"coordinates":[74.45454000000002,33.23186],"type":"Point"}
}