{
  "type": "Feature",
  "properties": {
    "iso:country":"IN",
    "ks:ks_name":"Okra",
    "ks:ks_pop":1131,
    "ks:ks_type":"VILLAGE",
    "name:eng_x_preferred":[
        "Okra"
    ],
    "wof:name":"Okra",
    "wof:placetype":"locality",
    "wof:population":1131
},
  "geometry": {"coordinates":[83.40164799999999,23.301401],"type":"Point"}
}