{
  "type": "Feature",
  "properties": {
    "iso:country":"IN",
    "ks:ks_name":"Dibbagudem",
    "ks:ks_pop":171,
    "ks:ks_type":"HABITATION",
    "name:eng_x_preferred":[
        "Dibbagudem"
    ],
    "wof:name":"Dibbagudem",
    "wof:placetype":"locality",
    "wof:population":171
},
  "geometry": {"coordinates":[81.045627,17.279143],"type":"Point"}
}