{
  "type": "Feature",
  "properties": {
    "iso:country":"IN",
    "ks:ks_name":"Berinari",
    "ks:ks_pop":2162,
    "ks:ks_type":"HABITATION",
    "name:eng_x_preferred":[
        "Berinari"
    ],
    "wof:name":"Berinari",
    "wof:placetype":"locality",
    "wof:population":2162
},
  "geometry": {"coordinates":[72.268328,25.507719],"type":"Point"}
}