{
  "type": "Feature",
  "properties": {
    "iso:country":"IN",
    "ks:ks_alt_nam":"Bhandar toli",
    "ks:ks_name":"Bhandar Toli",
    "ks:ks_pop":47,
    "ks:ks_type":"HABITATION",
    "name:eng_x_preferred":[
        "Bhandar Toli"
    ],
    "wof:name":"Bhandar Toli",
    "wof:placetype":"locality",
    "wof:population":47
},
  "geometry": {"coordinates":[84.46259000000001,22.421213],"type":"Point"}
}