{
  "type": "Feature",
  "properties": {
    "gn:admin1_code":"10",
    "gn:admin2_code":"88.0",
    "gn:asciiname":"Asaoti",
    "gn:country_code":"IN",
    "gn:dem":199,
    "gn:feature_class":"P",
    "gn:feature_code":"PPL",
    "gn:name":"As\u0101oti",
    "gn:population":0,
    "gn:timezone":"Asia/Kolkata",
    "iso:country":"IN",
    "wof:name":"Asaoti",
    "wof:placetype":"neighbourhood"
},
  "geometry": {"coordinates":[77.31903,28.2489],"type":"Point"}
}