{
  "type": "Feature",
  "properties": {
    "gn:admin1_code":"36",
    "gn:admin2_code":"164.0",
    "gn:asciiname":"Purwa Dalelpur",
    "gn:country_code":"IN",
    "gn:dem":142,
    "gn:feature_class":"P",
    "gn:feature_code":"PPL",
    "gn:name":"Purwa Dalelpur",
    "gn:population":0,
    "gn:timezone":"Asia/Kolkata",
    "iso:country":"IN",
    "wof:name":"Purwa Dalelpur",
    "wof:placetype":"neighbourhood"
},
  "geometry": {"coordinates":[79.9666,26.83823],"type":"Point"}
}