{
  "type": "Feature",
  "properties": {
    "iso:country":"IN",
    "ks:ks_name":"Deuli",
    "ks:ks_pop":274,
    "ks:ks_type":"VILLAGE",
    "ks:ks_uagg_main":0,
    "name:eng_x_preferred":[
        "Deuli"
    ],
    "wof:name":"Deuli",
    "wof:placetype":"neighbourhood",
    "wof:population":274
},
  "geometry": {"coordinates":[86.563408,21.296219],"type":"Point"}
}