{
  "type": "Feature",
  "properties": {
    "iso:country":"IN",
    "ks:ks_name":"Vanchuadurgam",
    "ks:ks_pop":52,
    "ks:ks_type":"HABITATION",
    "name:eng_x_preferred":[
        "Vanchuadurgam"
    ],
    "wof:name":"Vanchuadurgam",
    "wof:placetype":"locality",
    "wof:population":52
},
  "geometry": {"coordinates":[82.433824,18.039462],"type":"Point"}
}