{
  "type": "Feature",
  "properties": {
    "iso:country":"IN",
    "ks:ks_name":"Fatrutoli",
    "ks:ks_pop":145,
    "ks:ks_type":"HABITATION",
    "name:eng_x_preferred":[
        "Fatrutoli"
    ],
    "wof:name":"Fatrutoli",
    "wof:placetype":"locality",
    "wof:population":145
},
  "geometry": {"coordinates":[85.431262,23.348355],"type":"Point"}
}