{
  "type": "Feature",
  "properties": {
    "gn:admin1_code":"36",
    "gn:admin2_code":"193.0",
    "gn:asciiname":"Bharauli",
    "gn:country_code":"IN",
    "gn:dem":71,
    "gn:feature_class":"P",
    "gn:feature_code":"PPL",
    "gn:name":"Bharaul\u012b",
    "gn:population":0,
    "gn:timezone":"Asia/Kolkata",
    "iso:country":"IN",
    "wof:name":"Bharauli",
    "wof:placetype":"locality"
},
  "geometry": {"coordinates":[83.81494000000001,25.81679],"type":"Point"}
}