{
  "type": "Feature",
  "properties": {
    "iso:country":"IN",
    "ks:ks_name":"Raidiha",
    "ks:ks_pop":357,
    "ks:ks_type":"HABITATION",
    "name:eng_x_preferred":[
        "Raidiha"
    ],
    "wof:name":"Raidiha",
    "wof:placetype":"locality",
    "wof:population":357
},
  "geometry": {"coordinates":[86.480531,21.433739],"type":"Point"}
}