{
  "type": "Feature",
  "properties": {
    "iso:country":"IN",
    "ks:ks_name":"Ranvahi",
    "ks:ks_pop":95,
    "ks:ks_type":"HABITATION",
    "name:eng_x_preferred":[
        "Ranvahi"
    ],
    "wof:name":"Ranvahi",
    "wof:placetype":"locality",
    "wof:population":95
},
  "geometry": {"coordinates":[80.656015,20.298505],"type":"Point"}
}