{
  "type": "Feature",
  "properties": {
    "gn:admin1_code":"34.0",
    "gn:admin2_code":"229.0",
    "gn:asciiname":"Isua",
    "gn:country_code":"IN",
    "gn:dem":70,
    "gn:feature_class":"P",
    "gn:feature_code":"PPL",
    "gn:name":"Isua",
    "gn:population":0,
    "gn:timezone":"Asia/Kolkata",
    "iso:country":"IN",
    "name:ceb_x_preferred":[
        "Isua"
    ],
    "name:swe_x_preferred":[
        "Isua"
    ],
    "wof:name":"Isua",
    "wof:placetype":"locality"
},
  "geometry": {"coordinates":[85.55011999999998,25.07088],"type":"Point"}
}