{
  "type": "Feature",
  "properties": {
    "gn:admin1_code":"40",
    "gn:admin2_code":"537.0",
    "gn:asciiname":"Machanpalli",
    "gn:country_code":"IN",
    "gn:dem":597,
    "gn:feature_class":"P",
    "gn:feature_code":"PPL",
    "gn:name":"M\u0101chanpalli",
    "gn:population":0,
    "gn:timezone":"Asia/Kolkata",
    "iso:country":"IN",
    "wof:name":"Machanpalli",
    "wof:placetype":"locality"
},
  "geometry": {"coordinates":[78.16721,17.20481],"type":"Point"}
}