{
  "type": "Feature",
  "properties": {
    "iso:country":"IN",
    "ks:ks_name":"Ranewadi",
    "ks:ks_pop":125,
    "ks:ks_type":"HABITATION",
    "name:eng_x_preferred":[
        "Ranewadi"
    ],
    "wof:name":"Ranewadi",
    "wof:placetype":"locality",
    "wof:population":125
},
  "geometry": {"coordinates":[73.48168699999999,16.500868],"type":"Point"}
}