{
  "type": "Feature",
  "properties": {
    "iso:country":"IN",
    "ks:ks_name":"Bhadni Uperhar",
    "ks:ks_pop":327,
    "ks:ks_type":"VILLAGE",
    "ks:ks_uagg_main":0,
    "name:eng_x_preferred":[
        "Bhadni Uperhar"
    ],
    "wof:name":"Bhadni Uperhar",
    "wof:placetype":"neighbourhood",
    "wof:population":327
},
  "geometry": {"coordinates":[81.94691,25.385232],"type":"Point"}
}