{
  "type": "Feature",
  "properties": {
    "iso:country":"IN",
    "ks:ks_name":"Sankafal",
    "ks:ks_pop":82,
    "ks:ks_type":"HABITATION",
    "name:eng_x_preferred":[
        "Sankafal"
    ],
    "wof:name":"Sankafal",
    "wof:placetype":"locality",
    "wof:population":82
},
  "geometry": {"coordinates":[80.23618399999999,29.420719],"type":"Point"}
}