{
  "type": "Feature",
  "properties": {
    "iso:country":"IN",
    "ks:ks_name":"Panara",
    "ks:ks_pop":125,
    "ks:ks_type":"VILLAGE",
    "name:eng_x_preferred":[
        "Panara"
    ],
    "wof:name":"Panara",
    "wof:placetype":"locality",
    "wof:population":125
},
  "geometry": {"coordinates":[91.205174,26.441648],"type":"Point"}
}