{
  "type": "Feature",
  "properties": {
    "iso:country":"IN",
    "ks:ks_name":"Baori Ninama",
    "ks:ks_pop":822,
    "ks:ks_type":"VILLAGE",
    "name:eng_x_preferred":[
        "Baori Ninama"
    ],
    "wof:name":"Baori Ninama",
    "wof:placetype":"locality",
    "wof:population":822
},
  "geometry": {"coordinates":[74.548861,23.212514],"type":"Point"}
}