{
  "type": "Feature",
  "properties": {
    "iso:country":"IN",
    "ks:ks_name":"Harizon Tola",
    "ks:ks_pop":1334,
    "ks:ks_type":"HABITATION",
    "name:eng_x_preferred":[
        "Harizon Tola"
    ],
    "wof:name":"Harizon Tola",
    "wof:placetype":"locality",
    "wof:population":1334
},
  "geometry": {"coordinates":[86.06886,25.564721],"type":"Point"}
}