{
  "type": "Feature",
  "properties": {
    "gn:admin1_code":"36.0",
    "gn:admin2_code":"190.0",
    "gn:asciiname":"Rampurwa",
    "gn:country_code":"IN",
    "gn:dem":77,
    "gn:feature_class":"P",
    "gn:feature_code":"PPL",
    "gn:name":"Rampurwa",
    "gn:population":0,
    "gn:timezone":"Asia/Kolkata",
    "iso:country":"IN",
    "ks:ks_name":"Ram Purwa",
    "ks:ks_pop":941,
    "ks:ks_type":"VILLAGE",
    "name:eng_x_preferred":[
        "Ram Purwa"
    ],
    "name:eng_x_variant":[
        "Rampurwa"
    ],
    "wof:name":"Ram Purwa",
    "wof:placetype":"locality",
    "wof:population":941
},
  "geometry": {"coordinates":[83.537874,26.446372],"type":"Point"}
}