{
  "type": "Feature",
  "properties": {
    "gn:admin1_code":"25.0",
    "gn:admin2_code":"619.0",
    "gn:asciiname":"Ovarikkudi",
    "gn:country_code":"IN",
    "gn:dem":2,
    "gn:feature_class":"P",
    "gn:feature_code":"PPL",
    "gn:name":"Ovarikkudi",
    "gn:population":0,
    "gn:timezone":"Asia/Kolkata",
    "iso:country":"IN",
    "ks:ks_name":"Ovarkudi",
    "ks:ks_pop":517,
    "ks:ks_type":"HABITATION",
    "name:eng_x_preferred":[
        "Ovarkudi"
    ],
    "name:eng_x_variant":[
        "Ovarikkudi"
    ],
    "wof:name":"Ovarkudi",
    "wof:placetype":"locality",
    "wof:population":517
},
  "geometry": {"coordinates":[79.614358,10.503172],"type":"Point"}
}