{
  "type": "Feature",
  "properties": {
    "gn:admin1_code":"25.0",
    "gn:admin2_code":"619.0",
    "gn:asciiname":"Ovarikkudi",
    "gn:country_code":"IN",
    "gn:dem":2,
    "gn:feature_class":"P",
    "gn:feature_code":"PPL",
    "gn:name":"Ovarikkudi",
    "gn:population":0,
    "gn:timezone":"Asia/Kolkata",
    "iso:country":"IN",
    "wof:name":"Ovarikkudi",
    "wof:placetype":"locality"
},
  "geometry": {"coordinates":[79.61407,10.50939],"type":"Point"}
}