{
  "type": "Feature",
  "properties": {
    "iso:country":"IN",
    "ks:ks_name":"Bakka Ulithalu",
    "ks:ks_pop":202,
    "ks:ks_type":"HABITATION",
    "name:eng_x_preferred":[
        "Bakka Ulithalu"
    ],
    "wof:name":"Bakka Ulithalu",
    "wof:placetype":"locality",
    "wof:population":202
},
  "geometry": {"coordinates":[75.768056,12.363611],"type":"Point"}
}