{
  "type": "Feature",
  "properties": {
    "iso:country":"IN",
    "ks:ks_name":"Devuguda",
    "ks:ks_pop":102,
    "ks:ks_type":"HABITATION",
    "name:eng_x_preferred":[
        "Devuguda"
    ],
    "wof:name":"Devuguda",
    "wof:placetype":"locality",
    "wof:population":102
},
  "geometry": {"coordinates":[78.93714,19.295492],"type":"Point"}
}