{
  "type": "Feature",
  "properties": {
    "gn:admin1_code":"25.0",
    "gn:admin2_code":"616.0",
    "gn:asciiname":"Arangottai",
    "gn:country_code":"IN",
    "gn:dem":32,
    "gn:feature_class":"P",
    "gn:feature_code":"PPL",
    "gn:name":"Arangottai",
    "gn:population":0,
    "gn:timezone":"Asia/Kolkata",
    "iso:country":"IN",
    "ks:ks_name":"Arankottai",
    "ks:ks_pop":929,
    "ks:ks_type":"HABITATION",
    "name:eng_x_preferred":[
        "Arankottai"
    ],
    "name:eng_x_variant":[
        "Arangottai"
    ],
    "wof:name":"Arankottai",
    "wof:placetype":"locality",
    "wof:population":929
},
  "geometry": {"coordinates":[79.31464800000001,11.036927],"type":"Point"}
}