{
  "type": "Feature",
  "properties": {
    "gn:country":"IN",
    "gn:fcode":"PPL",
    "gn:population":0,
    "iso:country":"IN",
    "name:ben_x_preferred":[
        "\u09aa\u09be\u09b2\u09be\u09af\u09bc\u09ae\u0995\u09cb\u099f\u09cd\u099f\u09be\u0987"
    ],
    "name:cat_x_preferred":[
        "Palayamkottai"
    ],
    "name:deu_x_preferred":[
        "Palayamkottai"
    ],
    "name:eng_x_preferred":[
        "Palayamkottai"
    ],
    "name:fra_x_preferred":[
        "Palayamkottai"
    ],
    "name:guj_x_preferred":[
        "\u0aaa\u0ab2\u0abe\u0aaf\u0aae\u0a95\u0acb\u0a9f\u0acd\u0a9f\u0abe\u0a88"
    ],
    "name:hin_x_preferred":[
        "\u092a\u093e\u0932\u092f\u092e\u0915\u094b\u091f\u094d\u091f\u0947"
    ],
    "name:ita_x_preferred":[
        "Palayamkottai"
    ],
    "name:jpn_x_preferred":[
        "\u30d1\u30e9\u30e4\u30e0\u30b3\u30c3\u30bf\u30a4"
    ],
    "name:kan_x_preferred":[
        "\u0caa\u0cbe\u0cb2\u0caf\u0c82\u0c95\u0cca\u0c9f\u0ccd\u0c9f\u0cc8"
    ],
    "name:kor_x_preferred":[
        "\ud314\ub77c\uc58c\ucf54\ud0c0\uc774"
    ],
    "name:nld_x_preferred":[
        "Palayamkottai"
    ],
    "name:por_x_preferred":[
        "Palayamkottai"
    ],
    "name:rus_x_preferred":[
        "\u041f\u0430\u043b\u0430\u044f\u043c\u043a\u043e\u0442\u0442\u0430\u0438"
    ],
    "name:spa_x_preferred":[
        "Palayamkottai"
    ],
    "name:swe_x_preferred":[
        "Palayamkottai"
    ],
    "name:tam_x_preferred":[
        "\u0baa\u0bbe\u0bb3\u0bc8\u0baf\u0b99\u0bcd\u0b95\u0bcb\u0b9f\u0bcd\u0b9f\u0bc8"
    ],
    "name:tel_x_preferred":[
        "\u0c2a\u0c3e\u0c32\u0c2f\u0c02\u0c15\u0c4a\u0c1f\u0c4d\u0c1f\u0c3e\u0c2f\u0c4d"
    ],
    "name:und_x_variant":[
        "P\u0101laiyamkottai"
    ],
    "name:urd_x_preferred":[
        "\u067e\u0627\u0644\u0627\u06cc\u0627\u0645\u06a9\u0648\u062a\u062a\u0627\u06cc"
    ],
    "qs:name":"Palankottai",
    "qs:name_adm0":"India",
    "qs:name_adm1":"Tamil Nadu",
    "qs:photos_9r":0,
    "qs:photos_sr":0,
    "qs:placetype":"Town",
    "qs:pop_sr":"6",
    "wof:name":"Palankottai",
    "wof:placetype":"locality",
    "wof:population":0
},
  "geometry": {"coordinates":[77.73586,8.72361],"type":"Point"}
}