{
  "type": "Feature",
  "properties": {
    "iso:country":"IN",
    "ks:ks_name":"Bhalu Para",
    "ks:ks_pop":165,
    "ks:ks_type":"HABITATION",
    "name:eng_x_preferred":[
        "Bhalu Para"
    ],
    "wof:name":"Bhalu Para",
    "wof:placetype":"locality",
    "wof:population":165
},
  "geometry": {"coordinates":[81.932686,19.267915],"type":"Point"}
}