{
  "type": "Feature",
  "properties": {
    "iso:country":"IN",
    "ks:ks_name":"Raghu Nathpur",
    "ks:ks_pop":0,
    "ks:ks_type":"VILLAGE",
    "name:eng_x_preferred":[
        "Raghu Nathpur"
    ],
    "wof:name":"Raghu Nathpur",
    "wof:placetype":"locality",
    "wof:population":0
},
  "geometry": {"coordinates":[78.577384,29.4112],"type":"Point"}
}