{
  "type": "Feature",
  "properties": {
    "gn:admin1_code":"24",
    "gn:admin2_code":"119.0",
    "gn:asciiname":"Gorana",
    "gn:country_code":"IN",
    "gn:dem":483,
    "gn:feature_class":"P",
    "gn:feature_code":"PPL",
    "gn:name":"Gor\u0101na",
    "gn:population":0,
    "gn:timezone":"Asia/Kolkata",
    "iso:country":"IN",
    "name:ceb_x_preferred":[
        "Gorana"
    ],
    "name:swe_x_preferred":[
        "Gorana"
    ],
    "wof:name":"Gorana",
    "wof:placetype":"locality"
},
  "geometry": {"coordinates":[74.42435999999999,26.05437],"type":"Point"}
}