{
  "type": "Feature",
  "properties": {
    "iso:country":"IN",
    "ks:ks_name":"Debipur",
    "ks:ks_pop":4891,
    "ks:ks_type":"VILLAGE",
    "ks:ks_uagg_main":0,
    "name:eng_x_preferred":[
        "Debipur"
    ],
    "wof:name":"Debipur",
    "wof:placetype":"neighbourhood",
    "wof:population":4891
},
  "geometry": {"coordinates":[88.022046,24.622116],"type":"Point"}
}