{
  "type": "Feature",
  "properties": {
    "iso:country":"IN",
    "ks:ks_name":"Ambavali Kh.",
    "ks:ks_pop":340,
    "ks:ks_type":"VILLAGE",
    "name:eng_x_preferred":[
        "Ambavali Kh."
    ],
    "wof:name":"Ambavali Kh.",
    "wof:placetype":"locality",
    "wof:population":340
},
  "geometry": {"coordinates":[73.392803,18.033115],"type":"Point"}
}