{
  "type": "Feature",
  "properties": {
    "iso:country":"IN",
    "ks:ks_alt_nam":"BHAGADESHWEAR MANDIR",
    "ks:ks_name":"Bhagadeshwear Mandir",
    "ks:ks_pop":128,
    "ks:ks_type":"HABITATION",
    "name:eng_x_preferred":[
        "Bhagadeshwear Mandir"
    ],
    "wof:name":"Bhagadeshwear Mandir",
    "wof:placetype":"locality",
    "wof:population":128
},
  "geometry": {"coordinates":[74.090374,19.047966],"type":"Point"}
}