{
  "type": "Feature",
  "properties": {
    "iso:country":"IN",
    "ks:ks_name":"Pattanamkundu",
    "ks:ks_pop":933,
    "ks:ks_type":"HABITATION",
    "name:eng_x_preferred":[
        "Pattanamkundu"
    ],
    "wof:name":"Pattanamkundu",
    "wof:placetype":"locality",
    "wof:population":933
},
  "geometry": {"coordinates":[76.21822899999999,11.137574],"type":"Point"}
}