{
  "type": "Feature",
  "properties": {
    "gn:admin1_code":"38.0",
    "gn:admin2_code":"358.0",
    "gn:asciiname":"Saidabad",
    "gn:country_code":"IN",
    "gn:dem":150,
    "gn:feature_class":"P",
    "gn:feature_code":"PPL",
    "gn:name":"Said\u0101b\u0101d",
    "gn:population":0,
    "gn:timezone":"Asia/Kolkata",
    "iso:country":"IN",
    "name:fas_x_preferred":[
        "\u0633\u0639\u06cc\u062f\u0622\u0628\u0627\u062f"
    ],
    "name:urd_x_preferred":[
        "\u0633\u0639\u06cc\u062f \u0622\u0628\u0627\u062f"
    ],
    "wof:name":"Saidabad",
    "wof:placetype":"locality"
},
  "geometry": {"coordinates":[84.00788,24.54092],"type":"Point"}
}