{
  "type": "Feature",
  "properties": {
    "gn:admin1_code":"34.0",
    "gn:admin2_code":"220.0",
    "gn:asciiname":"Bardiha",
    "gn:country_code":"IN",
    "gn:dem":52,
    "gn:feature_class":"P",
    "gn:feature_code":"PPL",
    "gn:name":"Bard\u012bha",
    "gn:population":0,
    "gn:timezone":"Asia/Kolkata",
    "iso:country":"IN",
    "wof:name":"Bardiha",
    "wof:placetype":"locality"
},
  "geometry": {"coordinates":[85.52679999999999,25.83567],"type":"Point"}
}