{
  "type": "Feature",
  "properties": {
    "gn:admin1_code":"23",
    "gn:admin2_code":"36.0",
    "gn:asciiname":"Bhagwanpur",
    "gn:country_code":"IN",
    "gn:dem":230,
    "gn:feature_class":"P",
    "gn:feature_code":"PPL",
    "gn:name":"Bh\u0101gw\u0101npur",
    "gn:population":0,
    "gn:timezone":"Asia/Kolkata",
    "iso:country":"IN",
    "name:fra_x_preferred":[
        "Bhagwanpur"
    ],
    "name:pol_x_preferred":[
        "Bhagwanpur"
    ],
    "wof:name":"Bhagwanpur",
    "wof:placetype":"locality"
},
  "geometry": {"coordinates":[75.51654000000001,31.52829],"type":"Point"}
}