{
  "type": "Feature",
  "properties": {
    "iso:country":"IN",
    "ks:ks_name":"Talakabari Pather",
    "ks:ks_pop":813,
    "ks:ks_type":"VILLAGE",
    "ks:ks_uagg_main":0,
    "name:eng_x_preferred":[
        "Talakabari Pather"
    ],
    "wof:name":"Talakabari Pather",
    "wof:placetype":"neighbourhood",
    "wof:population":813
},
  "geometry": {"coordinates":[92.97165,26.714882],"type":"Point"}
}