{
  "type": "Feature",
  "properties": {
    "iso:country":"IN",
    "ks:ks_alt_nam":"Pendhari modakwadi",
    "ks:ks_name":"Pendhari Modakwadi",
    "ks:ks_pop":98,
    "ks:ks_type":"HABITATION",
    "name:eng_x_preferred":[
        "Pendhari Modakwadi"
    ],
    "wof:name":"Pendhari Modakwadi",
    "wof:placetype":"locality",
    "wof:population":98
},
  "geometry": {"coordinates":[73.712051,16.183405],"type":"Point"}
}