{
  "type": "Feature",
  "properties": {
    "iso:country":"IN",
    "ks:ks_name":"Paidaishapur",
    "ks:ks_pop":122,
    "ks:ks_type":"VILLAGE",
    "ks:ks_uagg_main":0,
    "name:eng_x_preferred":[
        "Paidaishapur"
    ],
    "wof:name":"Paidaishapur",
    "wof:placetype":"neighbourhood",
    "wof:population":122
},
  "geometry": {"coordinates":[83.787845,26.124483],"type":"Point"}
}