{
  "type": "Feature",
  "properties": {
    "gn:admin1_code":"2.0",
    "gn:admin2_code":"542.0",
    "gn:asciiname":"Chinna Kotipalle",
    "gn:country_code":"IN",
    "gn:dem":76,
    "gn:feature_class":"P",
    "gn:feature_code":"PPL",
    "gn:name":"Chinna Kotipalle",
    "gn:population":0,
    "gn:timezone":"Asia/Kolkata",
    "iso:country":"IN",
    "ks:ks_name":"Chinakotipalle",
    "ks:ks_pop":79,
    "ks:ks_type":"VILLAGE",
    "name:eng_x_preferred":[
        "Chinakotipalle"
    ],
    "name:eng_x_variant":[
        "Chinna Kotipalle"
    ],
    "wof:name":"Chinakotipalle",
    "wof:placetype":"locality",
    "wof:population":79
},
  "geometry": {"coordinates":[83.747137,18.646593],"type":"Point"}
}