{
  "type": "Feature",
  "properties": {
    "iso:country":"IN",
    "ks:ks_name":"Guddeangadi",
    "ks:ks_pop":204,
    "ks:ks_type":"HABITATION",
    "name:eng_x_preferred":[
        "Guddeangadi"
    ],
    "wof:name":"Guddeangadi",
    "wof:placetype":"locality",
    "wof:population":204
},
  "geometry": {"coordinates":[74.68648899999999,13.741484],"type":"Point"}
}