{
  "type": "Feature",
  "properties": {
    "iso:country":"IN",
    "ks:ks_name":"Khalia",
    "ks:ks_pop":565,
    "ks:ks_type":"VILLAGE",
    "ks:ks_uagg_main":0,
    "name:eng_x_preferred":[
        "Khalia"
    ],
    "wof:name":"Khalia",
    "wof:placetype":"neighbourhood",
    "wof:population":565
},
  "geometry": {"coordinates":[87.673878,21.931804],"type":"Point"}
}