{
  "type": "Feature",
  "properties": {
    "iso:country":"IN",
    "ks:ks_name":"Uppardoddi",
    "ks:ks_pop":220,
    "ks:ks_type":"HABITATION",
    "name:eng_x_preferred":[
        "Uppardoddi"
    ],
    "wof:name":"Uppardoddi",
    "wof:placetype":"locality",
    "wof:population":220
},
  "geometry": {"coordinates":[76.575275,16.259564],"type":"Point"}
}