{
  "type": "Feature",
  "properties": {
    "gn:admin1_code":"25.0",
    "gn:admin2_code":"632.0",
    "gn:asciiname":"Velappanayakkanpalaiyam",
    "gn:country_code":"IN",
    "gn:dem":402,
    "gn:feature_class":"P",
    "gn:feature_code":"PPL",
    "gn:name":"Velappan\u0101yakkanp\u0101laiyam",
    "gn:population":0,
    "gn:timezone":"Asia/Kolkata",
    "iso:country":"IN",
    "wof:name":"Velappanayakkanpalaiyam",
    "wof:placetype":"locality"
},
  "geometry": {"coordinates":[77.15878000000002,10.88998],"type":"Point"}
}