{
  "type": "Feature",
  "properties": {
    "iso:country":"IN",
    "ks:ks_name":"Kandireddyguda",
    "ks:ks_pop":74,
    "ks:ks_type":"HABITATION",
    "name:eng_x_preferred":[
        "Kandireddyguda"
    ],
    "wof:name":"Kandireddyguda",
    "wof:placetype":"locality",
    "wof:population":74
},
  "geometry": {"coordinates":[78.883371,17.749765],"type":"Point"}
}