{
  "type": "Feature",
  "properties": {
    "iso:country":"IN",
    "ks:ks_alt_nam":"DHOBAWASTI",
    "ks:ks_name":"Dhobawasti",
    "ks:ks_pop":150,
    "ks:ks_type":"HABITATION",
    "name:eng_x_preferred":[
        "Dhobawasti"
    ],
    "wof:name":"Dhobawasti",
    "wof:placetype":"locality",
    "wof:population":150
},
  "geometry": {"coordinates":[74.313057,17.414924],"type":"Point"}
}