{
  "type": "Feature",
  "properties": {
    "iso:country":"IN",
    "ks:ks_name":"10 GGR",
    "ks:ks_pop":387,
    "ks:ks_type":"VILLAGE",
    "name:eng_x_preferred":[
        "10 GGR"
    ],
    "wof:name":"10 GGR",
    "wof:placetype":"locality",
    "wof:population":387
},
  "geometry": {"coordinates":[74.49033799999999,29.542548],"type":"Point"}
}