{
  "type": "Feature",
  "properties": {
    "iso:country":"IN",
    "ks:ks_name":"Bhattarpal",
    "ks:ks_pop":21,
    "ks:ks_type":"HABITATION",
    "name:eng_x_preferred":[
        "Bhattarpal"
    ],
    "wof:name":"Bhattarpal",
    "wof:placetype":"locality",
    "wof:population":21
},
  "geometry": {"coordinates":[74.598527,14.83333],"type":"Point"}
}