{
  "type": "Feature",
  "properties": {
    "iso:country":"IN",
    "ks:ks_name":"Gundlamadugu",
    "ks:ks_pop":74,
    "ks:ks_type":"HABITATION",
    "name:eng_x_preferred":[
        "Gundlamadugu"
    ],
    "wof:name":"Gundlamadugu",
    "wof:placetype":"locality",
    "wof:population":74
},
  "geometry": {"coordinates":[80.670106,17.780557],"type":"Point"}
}