{
  "type": "Feature",
  "properties": {
    "gn:admin1_code":"35.0",
    "gn:admin2_code":"437.0",
    "gn:asciiname":"Gajnod Khera",
    "gn:country_code":"IN",
    "gn:dem":542,
    "gn:feature_class":"P",
    "gn:feature_code":"PPL",
    "gn:name":"G\u0101jnod Khera",
    "gn:population":0,
    "gn:timezone":"Asia/Kolkata",
    "iso:country":"IN",
    "wof:name":"Gajnod Khera",
    "wof:placetype":"locality"
},
  "geometry": {"coordinates":[76.10854999999999,22.71823],"type":"Point"}
}