{
  "type": "Feature",
  "properties": {
    "gn:admin1_code":"38.0",
    "gn:admin2_code":"347.0",
    "gn:asciiname":"Barhe",
    "gn:country_code":"IN",
    "gn:dem":406,
    "gn:feature_class":"P",
    "gn:feature_code":"PPL",
    "gn:name":"Barhe",
    "gn:population":0,
    "gn:timezone":"Asia/Kolkata",
    "iso:country":"IN",
    "ks:ks_alt_nam":"BARHE",
    "ks:ks_name":"Barhe",
    "ks:ks_pop":240,
    "ks:ks_type":"HABITATION",
    "name:eng_x_preferred":[
        "Barhe"
    ],
    "wof:name":"Barhe",
    "wof:placetype":"locality",
    "wof:population":240
},
  "geometry": {"coordinates":[84.67949299999999,24.243862],"type":"Point"}
}