{
  "type": "Feature",
  "properties": {
    "gn:admin1_code":"16",
    "gn:admin2_code":"511.0",
    "gn:asciiname":"Penur Buzurg",
    "gn:country_code":"IN",
    "gn:dem":374,
    "gn:feature_class":"P",
    "gn:feature_code":"PPL",
    "gn:name":"Penur Buzurg",
    "gn:population":0,
    "gn:timezone":"Asia/Kolkata",
    "iso:country":"IN",
    "name:und_x_variant":[
        "Penur"
    ],
    "wof:name":"Penur Buzurg",
    "wof:placetype":"locality"
},
  "geometry": {"coordinates":[77.09187,19.06381],"type":"Point"}
}