{
  "type": "Feature",
  "properties": {
    "gn:admin1_code":"25.0",
    "gn:admin2_code":"605.0",
    "gn:asciiname":"Ammananthanga",
    "gn:country_code":"IN",
    "gn:dem":154,
    "gn:feature_class":"P",
    "gn:feature_code":"PPL",
    "gn:name":"\u0100mmananth\u0101nga",
    "gn:population":0,
    "gn:timezone":"Asia/Kolkata",
    "iso:country":"IN",
    "ks:ks_name":"Ammananthangal",
    "ks:ks_pop":455,
    "ks:ks_type":"VILLAGE",
    "ks:ks_uagg_main":0,
    "name:eng_x_preferred":[
        "Ammananthangal"
    ],
    "wof:name":"Ammananthangal",
    "wof:placetype":"neighbourhood",
    "wof:population":455
},
  "geometry": {"coordinates":[79.38127799999999,12.918024],"type":"Point"}
}