{
  "type": "Feature",
  "properties": {
    "iso:country":"IN",
    "ks:ks_name":"Muturigad",
    "ks:ks_pop":451,
    "ks:ks_type":"HABITATION",
    "name:eng_x_preferred":[
        "Muturigad"
    ],
    "wof:name":"Muturigad",
    "wof:placetype":"locality",
    "wof:population":451
},
  "geometry": {"coordinates":[86.650158,20.88583],"type":"Point"}
}