{
  "type": "Feature",
  "properties": {
    "iso:country":"IN",
    "ks:ks_alt_nam":"Semmankuttai vattam",
    "ks:ks_name":"Semmankuttai Vattam",
    "ks:ks_pop":200,
    "ks:ks_type":"HABITATION",
    "name:eng_x_preferred":[
        "Semmankuttai Vattam"
    ],
    "wof:name":"Semmankuttai Vattam",
    "wof:placetype":"locality",
    "wof:population":200
},
  "geometry": {"coordinates":[78.769423,12.605787],"type":"Point"}
}