{
  "type": "Feature",
  "properties": {
    "iso:country":"IN",
    "ks:ks_alt_nam":"ATE",
    "ks:ks_name":"Ate",
    "ks:ks_pop":628,
    "ks:ks_type":"HABITATION",
    "name:eng_x_preferred":[
        "Ate"
    ],
    "wof:name":"Ate",
    "wof:placetype":"locality",
    "wof:population":628
},
  "geometry": {"coordinates":[84.658427,23.722773],"type":"Point"}
}