{
  "type": "Feature",
  "properties": {
    "iso:country":"IN",
    "ks:ks_name":"Hochar",
    "ks:ks_pop":3818,
    "ks:ks_type":"VILLAGE",
    "ks:ks_uagg_main":1,
    "name:eng_x_preferred":[
        "Hochar"
    ],
    "wof:name":"Hochar",
    "wof:placetype":"neighbourhood",
    "wof:population":3818
},
  "geometry": {"coordinates":[85.33161,23.46354],"type":"Point"}
}