{
  "type": "Feature",
  "properties": {
    "gn:admin1_code":"36.0",
    "gn:admin2_code":"161.0",
    "gn:asciiname":"Dalipnagar",
    "gn:country_code":"IN",
    "gn:dem":130,
    "gn:feature_class":"P",
    "gn:feature_code":"PPL",
    "gn:name":"Dalipnagar",
    "gn:population":0,
    "gn:timezone":"Asia/Kolkata",
    "iso:country":"IN",
    "wof:name":"Dalipnagar",
    "wof:placetype":"locality"
},
  "geometry": {"coordinates":[79.17747,26.59428],"type":"Point"}
}