{
  "type": "Feature",
  "properties": {
    "iso:country":"IN",
    "ks:ks_name":"Kantaberia",
    "ks:ks_pop":9248,
    "ks:ks_type":"URBAN",
    "name:eng_x_preferred":[
        "Kantaberia"
    ],
    "wof:name":"Kantaberia",
    "wof:placetype":"locality",
    "wof:population":9248
},
  "geometry": {"coordinates":[88.08607499999999,22.522394],"type":"Point"}
}