{
  "type": "Feature",
  "properties": {
    "iso:country":"IN",
    "ks:ks_alt_nam":"Karali bari",
    "ks:ks_name":"Karali Bari",
    "ks:ks_pop":276,
    "ks:ks_type":"HABITATION",
    "name:eng_x_preferred":[
        "Karali Bari"
    ],
    "wof:name":"Karali Bari",
    "wof:placetype":"locality",
    "wof:population":276
},
  "geometry": {"coordinates":[91.517286,23.177616],"type":"Point"}
}