{
  "type": "Feature",
  "properties": {
    "iso:country":"IN",
    "ks:ks_name":"Perumbalam",
    "ks:ks_pop":9678,
    "ks:ks_type":"VILLAGE",
    "name:eng_x_preferred":[
        "Perumbalam"
    ],
    "wof:name":"Perumbalam",
    "wof:placetype":"locality",
    "wof:population":9678
},
  "geometry": {"coordinates":[76.36666700000001,9.85],"type":"Point"}
}