{
  "type": "Feature",
  "properties": {
    "iso:country":"IN",
    "ks:ks_name":"Kathepada",
    "ks:ks_pop":356,
    "ks:ks_type":"HABITATION",
    "name:eng_x_preferred":[
        "Kathepada"
    ],
    "wof:name":"Kathepada",
    "wof:placetype":"locality",
    "wof:population":356
},
  "geometry": {"coordinates":[72.84083200000001,19.940852],"type":"Point"}
}