{
  "type": "Feature",
  "properties": {
    "gn:admin1_code":"36",
    "gn:admin2_code":"195.0",
    "gn:asciiname":"Naupura",
    "gn:country_code":"IN",
    "gn:dem":74,
    "gn:feature_class":"P",
    "gn:feature_code":"PPL",
    "gn:name":"Naupura",
    "gn:population":0,
    "gn:timezone":"Asia/Kolkata",
    "iso:country":"IN",
    "wof:name":"Naupura",
    "wof:placetype":"neighbourhood"
},
  "geometry": {"coordinates":[83.53744,25.78563],"type":"Point"}
}