{
  "type": "Feature",
  "properties": {
    "iso:country":"IN",
    "ks:ks_name":"Khuntapara",
    "ks:ks_pop":592,
    "ks:ks_type":"HABITATION",
    "name:eng_x_preferred":[
        "Khuntapara"
    ],
    "wof:name":"Khuntapara",
    "wof:placetype":"locality",
    "wof:population":592
},
  "geometry": {"coordinates":[81.68991,18.895344],"type":"Point"}
}