{
  "type": "Feature",
  "properties": {
    "gn:admin1_code":"19.0",
    "gn:admin2_code":"568.0",
    "gn:asciiname":"Bhogi",
    "gn:country_code":"IN",
    "gn:dem":616,
    "gn:feature_class":"P",
    "gn:feature_code":"PPL",
    "gn:name":"Bhogi",
    "gn:population":0,
    "gn:timezone":"Asia/Kolkata",
    "iso:country":"IN",
    "name:tam_x_preferred":[
        "\u0baa\u0bcb\u0b95\u0bbf"
    ],
    "name:tel_x_preferred":[
        "\u0c2d\u0c4b\u0c17\u0c3f"
    ],
    "wof:name":"Bhogi",
    "wof:placetype":"locality"
},
  "geometry": {"coordinates":[75.31271,14.34076],"type":"Point"}
}