{
  "type": "Feature",
  "properties": {
    "gn:admin1_code":"36.0",
    "gn:admin2_code":"175.0",
    "gn:asciiname":"Kauhat",
    "gn:country_code":"IN",
    "gn:dem":100,
    "gn:feature_class":"P",
    "gn:feature_code":"PPL",
    "gn:name":"Kauhat",
    "gn:population":0,
    "gn:timezone":"Asia/Kolkata",
    "iso:country":"IN",
    "ks:ks_name":"Kauhat",
    "ks:ks_type":"VILLAGE",
    "name:eng_x_preferred":[
        "Kauhat"
    ],
    "wof:name":"Kauhat",
    "wof:placetype":"locality"
},
  "geometry": {"coordinates":[81.82084500000001,25.087713],"type":"Point"}
}