{
  "type": "Feature",
  "properties": {
    "iso:country":"IN",
    "ks:ks_name":"Meoakhana",
    "ks:ks_pop":1580,
    "ks:ks_type":"VILLAGE",
    "ks:ks_uagg_main":0,
    "name:eng_x_preferred":[
        "Meoakhana"
    ],
    "wof:name":"Meoakhana",
    "wof:placetype":"neighbourhood",
    "wof:population":1580
},
  "geometry": {"coordinates":[88.29516700000001,24.357659],"type":"Point"}
}