{
  "type": "Feature",
  "properties": {
    "iso:country":"IN",
    "ks:ks_name":"Nimbalkarwasti",
    "ks:ks_pop":136,
    "ks:ks_type":"HABITATION",
    "name:eng_x_preferred":[
        "Nimbalkarwasti"
    ],
    "wof:name":"Nimbalkarwasti",
    "wof:placetype":"locality",
    "wof:population":136
},
  "geometry": {"coordinates":[74.386217,17.976531],"type":"Point"}
}