{
  "type": "Feature",
  "properties": {
    "gn:admin1_code":"40.0",
    "gn:admin2_code":"539.0",
    "gn:asciiname":"Basantapur",
    "gn:country_code":"IN",
    "gn:dem":434,
    "gn:feature_class":"P",
    "gn:feature_code":"PPL",
    "gn:name":"Basant\u0101pur",
    "gn:population":0,
    "gn:timezone":"Asia/Kolkata",
    "iso:country":"IN",
    "name:fra_x_preferred":[
        "Basantapur"
    ],
    "name:pol_x_preferred":[
        "Basantapur"
    ],
    "wof:name":"Basantapur",
    "wof:placetype":"locality"
},
  "geometry": {"coordinates":[78.94082,17.70332],"type":"Point"}
}