{
  "type": "Feature",
  "properties": {
    "gn:admin1_code":"12.0",
    "gn:asciiname":"Dat",
    "gn:country_code":"IN",
    "gn:dem":3185,
    "gn:feature_class":"P",
    "gn:feature_code":"PPL",
    "gn:name":"Dat",
    "gn:population":0,
    "gn:timezone":"Asia/Kolkata",
    "iso:country":"IN",
    "wof:name":"Dat",
    "wof:placetype":"locality"
},
  "geometry": {"coordinates":[74.24285999999999,34.68953],"type":"Point"}
}