{
  "type": "Feature",
  "properties": {
    "iso:country":"IN",
    "ks:ks_name":"Rakha Tola",
    "ks:ks_pop":321,
    "ks:ks_type":"HABITATION",
    "name:eng_x_preferred":[
        "Rakha Tola"
    ],
    "wof:name":"Rakha Tola",
    "wof:placetype":"locality",
    "wof:population":321
},
  "geometry": {"coordinates":[87.43491400000001,25.289096],"type":"Point"}
}