{
  "type": "Feature",
  "properties": {
    "iso:country":"IN",
    "ks:ks_name":"Megh Rajpur",
    "ks:ks_pop":762,
    "ks:ks_type":"VILLAGE",
    "ks:ks_uagg_main":0,
    "name:eng_x_preferred":[
        "Megh Rajpur"
    ],
    "wof:name":"Megh Rajpur",
    "wof:placetype":"neighbourhood",
    "wof:population":762
},
  "geometry": {"coordinates":[77.65445200000001,29.721944],"type":"Point"}
}