{
  "type": "Feature",
  "properties": {
    "iso:country":"IN",
    "ks:ks_name":"Madhya Chauraguri",
    "ks:ks_pop":222,
    "ks:ks_type":"HABITATION",
    "name:eng_x_preferred":[
        "Madhya Chauraguri"
    ],
    "wof:name":"Madhya Chauraguri",
    "wof:placetype":"locality",
    "wof:population":222
},
  "geometry": {"coordinates":[90.989676,26.614192],"type":"Point"}
}