{
  "type": "Feature",
  "properties": {
    "iso:country":"IN",
    "ks:ks_name":"Katkaripada",
    "ks:ks_pop":93,
    "ks:ks_type":"HABITATION",
    "name:eng_x_preferred":[
        "Katkaripada"
    ],
    "wof:name":"Katkaripada",
    "wof:placetype":"locality",
    "wof:population":93
},
  "geometry": {"coordinates":[73.02188,19.60093],"type":"Point"}
}