{
  "type": "Feature",
  "properties": {
    "iso:country":"IN",
    "ks:ks_name":"Pakaria",
    "ks:ks_pop":114,
    "ks:ks_type":"VILLAGE",
    "name:eng_x_preferred":[
        "Pakaria"
    ],
    "wof:name":"Pakaria",
    "wof:placetype":"locality",
    "wof:population":114
},
  "geometry": {"coordinates":[85.276616,24.329536],"type":"Point"}
}