{
  "type": "Feature",
  "properties": {
    "gn:admin1_code":"9.0",
    "gn:admin2_code":"472.0",
    "gn:asciiname":"Birpur",
    "gn:country_code":"IN",
    "gn:dem":238,
    "gn:feature_class":"P",
    "gn:feature_code":"PPL",
    "gn:name":"Birpur",
    "gn:population":0,
    "gn:timezone":"Asia/Kolkata",
    "iso:country":"IN",
    "wof:name":"Birpur",
    "wof:placetype":"locality"
},
  "geometry": {"coordinates":[73.07106999999998,24.14333],"type":"Point"}
}