{
  "type": "Feature",
  "properties": {
    "iso:country":"IN",
    "ks:ks_name":"Digi",
    "ks:ks_pop":0,
    "ks:ks_type":"VILLAGE",
    "name:eng_x_preferred":[
        "Digi"
    ],
    "wof:name":"Digi",
    "wof:placetype":"locality",
    "wof:population":0
},
  "geometry": {"coordinates":[84.06272800000001,20.762801],"type":"Point"}
}