{
  "type": "Feature",
  "properties": {
    "iso:country":"IN",
    "ks:ks_name":"That Natthuram",
    "ks:ks_pop":590,
    "ks:ks_type":"HABITATION",
    "name:eng_x_preferred":[
        "That Natthuram"
    ],
    "wof:name":"That Natthuram",
    "wof:placetype":"locality",
    "wof:population":590
},
  "geometry": {"coordinates":[78.505988,26.997843],"type":"Point"}
}