{
  "type": "Feature",
  "properties": {
    "gn:admin1_code":"36.0",
    "gn:admin2_code":"150.0",
    "gn:asciiname":"Muhammadpur Pathra",
    "gn:country_code":"IN",
    "gn:dem":164,
    "gn:feature_class":"P",
    "gn:feature_code":"PPL",
    "gn:name":"Muhammadpur Pathra",
    "gn:population":0,
    "gn:timezone":"Asia/Kolkata",
    "iso:country":"IN",
    "ks:ks_name":"Muhammadpur Pathra",
    "ks:ks_type":"VILLAGE",
    "name:eng_x_preferred":[
        "Muhammadpur Pathra"
    ],
    "wof:name":"Muhammadpur Pathra",
    "wof:placetype":"locality"
},
  "geometry": {"coordinates":[79.22513600000001,28.244536],"type":"Point"}
}