{
  "type": "Feature",
  "properties": {
    "iso:country":"IN",
    "ks:ks_name":"Yetewahi",
    "ks:ks_pop":279,
    "ks:ks_type":"VILLAGE",
    "name:eng_x_preferred":[
        "Yetewahi"
    ],
    "wof:name":"Yetewahi",
    "wof:placetype":"locality",
    "wof:population":279
},
  "geometry": {"coordinates":[79.744398,21.008703],"type":"Point"}
}