{
  "type": "Feature",
  "properties": {
    "gn:admin1_code":"24.0",
    "gn:admin2_code":"103",
    "gn:asciiname":"Chinchroli",
    "gn:country_code":"IN",
    "gn:dem":343,
    "gn:feature_class":"P",
    "gn:feature_code":"PPL",
    "gn:name":"Chinchroli",
    "gn:population":0,
    "gn:timezone":"Asia/Kolkata",
    "iso:country":"IN",
    "name:und_x_variant":[
        "Ch\u012bnchroli"
    ],
    "wof:name":"Chinchroli",
    "wof:placetype":"locality"
},
  "geometry": {"coordinates":[75.53461999999998,28.1161],"type":"Point"}
}