{
  "type": "Feature",
  "properties": {
    "gn:admin1_code":"37",
    "gn:admin2_code":"404.0",
    "gn:asciiname":"Sasin",
    "gn:country_code":"IN",
    "gn:dem":434,
    "gn:feature_class":"P",
    "gn:feature_code":"PPL",
    "gn:name":"S\u0101sin",
    "gn:population":0,
    "gn:timezone":"Asia/Kolkata",
    "iso:country":"IN",
    "ks:ks_alt_nam":"S\u0101sin",
    "ks:ks_name":"Sasin",
    "ks:ks_pop":595,
    "ks:ks_type":"VILLAGE",
    "name:eng_x_preferred":[
        "Sasin"
    ],
    "name:eng_x_variant":[
        "S\u0101sin"
    ],
    "wof:name":"Sasin",
    "wof:placetype":"locality",
    "wof:population":595
},
  "geometry": {"coordinates":[82.367035,22.78001],"type":"Point"}
}