{
  "type": "Feature",
  "properties": {
    "gn:admin1_code":"2.0",
    "gn:admin2_code":"544.0",
    "gn:asciiname":"Tangulaguda",
    "gn:country_code":"IN",
    "gn:dem":978,
    "gn:feature_class":"P",
    "gn:feature_code":"PPL",
    "gn:name":"Tangulag\u016bda",
    "gn:population":0,
    "gn:timezone":"Asia/Kolkata",
    "iso:country":"IN",
    "ks:ks_alt_nam":"Tangulag\u016bda",
    "ks:ks_name":"Tangulaguda",
    "ks:ks_type":"VILLAGE",
    "name:eng_x_preferred":[
        "Tangulaguda"
    ],
    "name:eng_x_variant":[
        "Tangulag\u016bda"
    ],
    "wof:name":"Tangulaguda",
    "wof:placetype":"locality"
},
  "geometry": {"coordinates":[83.063678,18.35461],"type":"Point"}
}