{
  "type": "Feature",
  "properties": {
    "gn:admin1_code":"2.0",
    "gn:admin2_code":"544.0",
    "gn:asciiname":"Tangulaguda",
    "gn:country_code":"IN",
    "gn:dem":978,
    "gn:feature_class":"P",
    "gn:feature_code":"PPL",
    "gn:name":"Tangulag\u016bda",
    "gn:population":0,
    "gn:timezone":"Asia/Kolkata",
    "iso:country":"IN",
    "wof:name":"Tangulaguda",
    "wof:placetype":"locality"
},
  "geometry": {"coordinates":[83.07203,18.34944],"type":"Point"}
}