{
  "type": "Feature",
  "properties": {
    "iso:country":"IN",
    "ks:ks_name":"Jogidih",
    "ks:ks_pop":306,
    "ks:ks_type":"VILLAGE",
    "name:eng_x_preferred":[
        "Jogidih"
    ],
    "wof:name":"Jogidih",
    "wof:placetype":"locality",
    "wof:population":306
},
  "geometry": {"coordinates":[86.97409399999999,24.130299],"type":"Point"}
}