{
  "type": "Feature",
  "properties": {
    "iso:country":"IN",
    "ks:ks_alt_nam":"Podugutta thanda",
    "ks:ks_name":"Podugutta Thanda",
    "ks:ks_pop":125,
    "ks:ks_type":"HABITATION",
    "name:eng_x_preferred":[
        "Podugutta Thanda"
    ],
    "wof:name":"Podugutta Thanda",
    "wof:placetype":"locality",
    "wof:population":125
},
  "geometry": {"coordinates":[77.69401999999999,16.714676],"type":"Point"}
}