{
  "type": "Feature",
  "properties": {
    "iso:country":"IN",
    "name:ben_x_preferred":[
        "\u0993\u09b2\u09ac\u09a8\u09cd\u09a8"
    ],
    "name:bpy_x_preferred":[
        "\u0993\u09b2\u09f1\u09a8\u09cd\u09a8"
    ],
    "name:eng_x_preferred":[
        "Olavanna"
    ],
    "name:fra_x_preferred":[
        "Olavanna"
    ],
    "name:ita_x_preferred":[
        "Olavanna"
    ],
    "name:msa_x_preferred":[
        "Olavanna"
    ],
    "name:nan_x_preferred":[
        "Olavanna"
    ],
    "name:nld_x_preferred":[
        "Olavanna"
    ],
    "name:por_x_preferred":[
        "Olavanna"
    ],
    "name:vie_x_preferred":[
        "Olavanna"
    ],
    "name:zho_x_preferred":[
        "\u5965\u62c9\u74e6\u6069\u7eb3"
    ],
    "qs:name":"Olavanna",
    "qs:name_adm0":"India",
    "qs:name_adm1":"Kerala",
    "qs:photos":318,
    "qs:photos_1k":64,
    "qs:photos_9k":1,
    "qs:photos_9r":5,
    "qs:photos_all":318,
    "qs:photos_sr":5,
    "qs:placetype":"Town",
    "qs:pop_sr":"0",
    "wd:wordcount":145,
    "wof:name":"Olavanna",
    "wof:placetype":"locality"
},
  "geometry": {"coordinates":[75.860767,11.307371],"type":"Point"}
}