{
  "type": "Feature",
  "properties": {
    "iso:country":"IN",
    "ks:ks_alt_nam":"N\u0101yikop",
    "ks:ks_name":"Nayikop",
    "ks:ks_type":"VILLAGE",
    "name:eng_x_preferred":[
        "Nayikop"
    ],
    "name:eng_x_variant":[
        "N\u0101yikop"
    ],
    "wof:name":"Nayikop",
    "wof:placetype":"locality"
},
  "geometry": {"coordinates":[75.189235,14.974576],"type":"Point"}
}