{
  "type": "Feature",
  "properties": {
    "iso:country":"IN",
    "ks:ks_name":"Ratanpur",
    "ks:ks_pop":719,
    "ks:ks_type":"VILLAGE",
    "name:eng_x_preferred":[
        "Ratanpur"
    ],
    "wof:name":"Ratanpur",
    "wof:placetype":"locality",
    "wof:population":719
},
  "geometry": {"coordinates":[85.71210000000001,26.006554],"type":"Point"}
}