{
  "type": "Feature",
  "properties": {
    "iso:country":"IN",
    "ks:ks_alt_nam":"CHakpurwa",
    "ks:ks_name":"Chakpurwa",
    "ks:ks_pop":230,
    "ks:ks_type":"HABITATION",
    "name:eng_x_preferred":[
        "Chakpurwa"
    ],
    "wof:name":"Chakpurwa",
    "wof:placetype":"locality",
    "wof:population":230
},
  "geometry": {"coordinates":[80.94192200000001,27.617659],"type":"Point"}
}