{
  "type": "Feature",
  "properties": {
    "gn:admin1_code":"38.0",
    "gn:admin2_code":"362.0",
    "gn:asciiname":"Khairbani",
    "gn:country_code":"IN",
    "gn:dem":119,
    "gn:feature_class":"P",
    "gn:feature_code":"PPL",
    "gn:name":"Khairb\u0101ni",
    "gn:population":0,
    "gn:timezone":"Asia/Kolkata",
    "iso:country":"IN",
    "ks:ks_alt_nam":"Khairb\u0101ni",
    "ks:ks_name":"Khairbani",
    "ks:ks_pop":435,
    "ks:ks_type":"VILLAGE",
    "name:eng_x_preferred":[
        "Khairbani"
    ],
    "name:eng_x_variant":[
        "Khairb\u0101ni"
    ],
    "wof:name":"Khairbani",
    "wof:placetype":"locality",
    "wof:population":435
},
  "geometry": {"coordinates":[87.52782000000001,24.357912],"type":"Point"}
}