{
  "type": "Feature",
  "properties": {
    "gn:admin1_code":"10",
    "gn:admin2_code":"89.0",
    "gn:asciiname":"Dostpur",
    "gn:country_code":"IN",
    "gn:dem":188,
    "gn:feature_class":"P",
    "gn:feature_code":"PPL",
    "gn:name":"Dostpur",
    "gn:population":0,
    "gn:timezone":"Asia/Kolkata",
    "iso:country":"IN",
    "name:bpy_x_preferred":[
        "\u09a6\u09cb\u09b8\u09cd\u09a4\u09aa\u09c1\u09b0"
    ],
    "name:ceb_x_preferred":[
        "Dostpur"
    ],
    "name:fas_x_preferred":[
        "\u062f\u0648\u0633\u062a\u200c\u067e\u0648\u0631"
    ],
    "name:ita_x_preferred":[
        "Dostpur"
    ],
    "name:mlg_x_preferred":[
        "Dostpur"
    ],
    "name:msa_x_preferred":[
        "Dostpur"
    ],
    "name:new_x_preferred":[
        "\u0926\u094b\u0938\u094d\u0924\u092a\u0941\u0930"
    ],
    "name:nld_x_preferred":[
        "Dostpur"
    ],
    "name:pol_x_preferred":[
        "Dostpur"
    ],
    "name:por_x_preferred":[
        "Dostpur"
    ],
    "name:swe_x_preferred":[
        "Dostpur"
    ],
    "name:urd_x_preferred":[
        "\u062f\u0648\u0633\u062a \u067e\u0648\u0631"
    ],
    "name:vie_x_preferred":[
        "Dostpur"
    ],
    "name:zho_x_preferred":[
        "\u591a\u65af\u7279\u666e\u5c14"
    ],
    "wof:name":"Dostpur",
    "wof:placetype":"locality"
},
  "geometry": {"coordinates":[77.49185,28.16086],"type":"Point"}
}