{
  "type": "Feature",
  "properties": {
    "gn:admin1_code":"38",
    "gn:admin2_code":"355.0",
    "gn:asciiname":"Kura",
    "gn:country_code":"IN",
    "gn:dem":226,
    "gn:feature_class":"P",
    "gn:feature_code":"PPL",
    "gn:name":"Kura",
    "gn:population":0,
    "gn:timezone":"Asia/Kolkata",
    "iso:country":"IN",
    "wof:name":"Kura",
    "wof:placetype":"locality"
},
  "geometry": {"coordinates":[86.21318000000002,23.57217],"type":"Point"}
}