{
  "type": "Feature",
  "properties": {
    "gn:admin1_code":"38",
    "gn:admin2_code":"355.0",
    "gn:asciiname":"Kura",
    "gn:country_code":"IN",
    "gn:dem":226,
    "gn:feature_class":"P",
    "gn:feature_code":"PPL",
    "gn:name":"Kura",
    "gn:population":0,
    "gn:timezone":"Asia/Kolkata",
    "iso:country":"IN",
    "name:aze_x_preferred":[
        "K\u00fcr"
    ],
    "name:cat_x_preferred":[
        "Kura"
    ],
    "name:ceb_x_preferred":[
        "Kura"
    ],
    "name:deu_x_preferred":[
        "Kura"
    ],
    "name:est_x_preferred":[
        "Kura"
    ],
    "name:fas_x_preferred":[
        "\u06a9\u0648\u0631\u0627"
    ],
    "name:fra_x_preferred":[
        "Kura"
    ],
    "name:ita_x_preferred":[
        "Kura"
    ],
    "name:lav_x_preferred":[
        "K\u016bra"
    ],
    "name:nld_x_preferred":[
        "Kura"
    ],
    "name:pol_x_preferred":[
        "Kura"
    ],
    "name:slk_x_preferred":[
        "Kura"
    ],
    "name:slv_x_preferred":[
        "Kura"
    ],
    "name:swe_x_preferred":[
        "Kura"
    ],
    "wof:name":"Kura",
    "wof:placetype":"locality"
},
  "geometry": {"coordinates":[86.21318000000002,23.57217],"type":"Point"}
}