{
  "type": "Feature",
  "properties": {
    "iso:country":"IN",
    "ks:ks_name":"Mon Sing Senar Hijunglangso",
    "ks:ks_pop":109,
    "ks:ks_type":"HABITATION",
    "ks:ks_uagg_main":0,
    "name:eng_x_preferred":[
        "Mon Sing Senar Hijunglangso"
    ],
    "wof:name":"Mon Sing Senar Hijunglangso",
    "wof:placetype":"neighbourhood",
    "wof:population":109
},
  "geometry": {"coordinates":[93.769941,26.155918],"type":"Point"}
}