{
  "type": "Feature",
  "properties": {
    "iso:country":"IN",
    "ks:ks_name":"Balejaddi",
    "ks:ks_pop":10,
    "ks:ks_type":"HABITATION",
    "name:eng_x_preferred":[
        "Balejaddi"
    ],
    "wof:name":"Balejaddi",
    "wof:placetype":"locality",
    "wof:population":10
},
  "geometry": {"coordinates":[74.76546399999999,14.358979],"type":"Point"}
}