{
  "type": "Feature",
  "properties": {
    "iso:country":"IN",
    "ks:ks_name":"Ranipuram",
    "ks:ks_pop":2011,
    "ks:ks_type":"HABITATION",
    "name:eng_x_preferred":[
        "Ranipuram"
    ],
    "wof:name":"Ranipuram",
    "wof:placetype":"locality",
    "wof:population":2011
},
  "geometry": {"coordinates":[75.35103100000001,12.419255],"type":"Point"}
}