{
  "type": "Feature",
  "properties": {
    "iso:country":"IN",
    "ks:ks_name":"Lomboi",
    "ks:ks_pop":6235,
    "ks:ks_type":"VILLAGE",
    "name:eng_x_preferred":[
        "Lomboi"
    ],
    "wof:name":"Lomboi",
    "wof:placetype":"locality",
    "wof:population":6235
},
  "geometry": {"coordinates":[84.68106400000001,22.559816],"type":"Point"}
}