{
  "type": "Feature",
  "properties": {
    "gn:admin1_code":"21",
    "gn:admin2_code":"395.0",
    "gn:asciiname":"Tiganguda",
    "gn:country_code":"IN",
    "gn:dem":602,
    "gn:feature_class":"P",
    "gn:feature_code":"PPL",
    "gn:name":"Tiganguda",
    "gn:population":0,
    "gn:timezone":"Asia/Kolkata",
    "iso:country":"IN",
    "wof:name":"Tiganguda",
    "wof:placetype":"locality"
},
  "geometry": {"coordinates":[83.39549,19.80614],"type":"Point"}
}