{
  "type": "Feature",
  "properties": {
    "iso:country":"IN",
    "ks:ks_name":"Lordi Doliya",
    "ks:ks_pop":598,
    "ks:ks_type":"VILLAGE",
    "name:eng_x_preferred":[
        "Lordi Doliya"
    ],
    "wof:name":"Lordi Doliya",
    "wof:placetype":"locality",
    "wof:population":598
},
  "geometry": {"coordinates":[72.837817,26.316414],"type":"Point"}
}