{
  "type": "Feature",
  "properties": {
    "iso:country":"IN",
    "ks:ks_alt_nam":"Bamundanga Pt II",
    "ks:ks_name":"Bamundanga Pt Ii",
    "ks:ks_pop":1938,
    "ks:ks_type":"HABITATION",
    "name:eng_x_preferred":[
        "Bamundanga Pt Ii"
    ],
    "wof:name":"Bamundanga Pt Ii",
    "wof:placetype":"locality",
    "wof:population":1938
},
  "geometry": {"coordinates":[90.447232,26.076639],"type":"Point"}
}