{
  "type": "Feature",
  "properties": {
    "iso:country":"IN",
    "ks:ks_name":"Fareedpua Sawnro",
    "ks:ks_pop":959,
    "ks:ks_type":"HABITATION",
    "name:eng_x_preferred":[
        "Fareedpua Sawnro"
    ],
    "wof:name":"Fareedpua Sawnro",
    "wof:placetype":"locality",
    "wof:population":959
},
  "geometry": {"coordinates":[81.430291,25.44088],"type":"Point"}
}