{
  "type": "Feature",
  "properties": {
    "gn:admin1_code":"34.0",
    "gn:admin2_code":"212.0",
    "gn:asciiname":"Tahirpur",
    "gn:country_code":"IN",
    "gn:dem":40,
    "gn:feature_class":"P",
    "gn:feature_code":"PPL",
    "gn:name":"T\u0101hirpur",
    "gn:population":0,
    "gn:timezone":"Asia/Kolkata",
    "iso:country":"IN",
    "ks:ks_name":"Tahirpur",
    "ks:ks_pop":956,
    "ks:ks_type":"VILLAGE",
    "ks:ks_uagg_main":0,
    "name:eng_x_preferred":[
        "Tahirpur"
    ],
    "wof:name":"Tahirpur",
    "wof:placetype":"neighbourhood",
    "wof:population":956
},
  "geometry": {"coordinates":[87.838812,25.616266],"type":"Point"}
}