{
  "type": "Feature",
  "properties": {
    "iso:country":"IN",
    "ks:ks_name":"Bar Mirjapur",
    "ks:ks_pop":757,
    "ks:ks_type":"VILLAGE",
    "name:eng_x_preferred":[
        "Bar Mirjapur"
    ],
    "wof:name":"Bar Mirjapur",
    "wof:placetype":"locality",
    "wof:population":757
},
  "geometry": {"coordinates":[87.864429,22.262016],"type":"Point"}
}