{
  "type": "Feature",
  "properties": {
    "iso:country":"IN",
    "ks:ks_name":"Chembakulambu",
    "ks:ks_pop":355,
    "ks:ks_type":"HABITATION",
    "name:eng_x_preferred":[
        "Chembakulambu"
    ],
    "wof:name":"Chembakulambu",
    "wof:placetype":"locality",
    "wof:population":355
},
  "geometry": {"coordinates":[76.38284,10.660609],"type":"Point"}
}