{
  "type": "Feature",
  "properties": {
    "gn:admin1_code":"34.0",
    "gn:admin2_code":"218.0",
    "gn:asciiname":"Sumeri Chhapra",
    "gn:country_code":"IN",
    "gn:dem":68,
    "gn:feature_class":"P",
    "gn:feature_code":"PPL",
    "gn:name":"Sumeri Chh\u0101pra",
    "gn:population":0,
    "gn:timezone":"Asia/Kolkata",
    "iso:country":"IN",
    "ks:ks_alt_nam":"Sumeri Chh\u0101pra",
    "ks:ks_name":"Sumeri Chhapra",
    "ks:ks_pop":143,
    "ks:ks_type":"VILLAGE",
    "ks:ks_uagg_main":0,
    "name:eng_x_preferred":[
        "Sumeri Chhapra"
    ],
    "name:eng_x_variant":[
        "Sumeri Chh\u0101pra"
    ],
    "wof:name":"Sumeri Chhapra",
    "wof:placetype":"neighbourhood",
    "wof:population":143
},
  "geometry": {"coordinates":[84.179731,26.205036],"type":"Point"}
}