{
  "type": "Feature",
  "properties": {
    "gn:admin1_code":"19.0",
    "gn:admin2_code":"570.0",
    "gn:asciiname":"Balekoppa",
    "gn:country_code":"IN",
    "gn:dem":897,
    "gn:feature_class":"P",
    "gn:feature_code":"PPL",
    "gn:name":"B\u0101lekoppa",
    "gn:population":0,
    "gn:timezone":"Asia/Kolkata",
    "iso:country":"IN",
    "ks:ks_name":"Balekoppa",
    "ks:ks_pop":121,
    "ks:ks_type":"HABITATION",
    "name:eng_x_preferred":[
        "Balekoppa"
    ],
    "wof:name":"Balekoppa",
    "wof:placetype":"locality",
    "wof:population":121
},
  "geometry": {"coordinates":[75.54525599999999,13.419623],"type":"Point"}
}