{
  "type": "Feature",
  "properties": {
    "iso:country":"IN",
    "ks:ks_name":"Bartihpara",
    "ks:ks_pop":155,
    "ks:ks_type":"HABITATION",
    "name:eng_x_preferred":[
        "Bartihpara"
    ],
    "wof:name":"Bartihpara",
    "wof:placetype":"locality",
    "wof:population":155
},
  "geometry": {"coordinates":[83.16933,22.615795],"type":"Point"}
}