{
  "type": "Feature",
  "properties": {
    "iso:country":"IN",
    "ks:ks_alt_nam":"PASIGUNTA",
    "ks:ks_name":"Pasigunta",
    "ks:ks_pop":83,
    "ks:ks_type":"HABITATION",
    "name:eng_x_preferred":[
        "Pasigunta"
    ],
    "wof:name":"Pasigunta",
    "wof:placetype":"locality",
    "wof:population":83
},
  "geometry": {"coordinates":[79.450892,13.436009],"type":"Point"}
}