{
  "type": "Feature",
  "properties": {
    "gn:admin1_code":"39.0",
    "gn:admin2_code":"67.0",
    "gn:asciiname":"Bajawala",
    "gn:country_code":"IN",
    "gn:dem":215,
    "gn:feature_class":"P",
    "gn:feature_code":"PPL",
    "gn:name":"B\u0101j\u0101w\u0101la",
    "gn:population":0,
    "gn:timezone":"Asia/Kolkata",
    "iso:country":"IN",
    "wof:name":"Bajawala",
    "wof:placetype":"locality"
},
  "geometry": {"coordinates":[79.16143000000002,29.06857],"type":"Point"}
}