{
  "type": "Feature",
  "properties": {
    "iso:country":"IN",
    "ks:ks_name":"Chandalashung N",
    "ks:ks_pop":713,
    "ks:ks_type":"HABITATION",
    "ks:ks_uagg_main":0,
    "name:eng_x_preferred":[
        "Chandalashung N"
    ],
    "wof:name":"Chandalashung N",
    "wof:placetype":"neighbourhood",
    "wof:population":713
},
  "geometry": {"coordinates":[93.95665,26.043265],"type":"Point"}
}