{
  "type": "Feature",
  "properties": {
    "gn:admin1_code":"34.0",
    "gn:admin2_code":"206.0",
    "gn:asciiname":"Bhalwahi",
    "gn:country_code":"IN",
    "gn:dem":67,
    "gn:feature_class":"P",
    "gn:feature_code":"PPL",
    "gn:name":"Bhalw\u0101hi",
    "gn:population":0,
    "gn:timezone":"Asia/Kolkata",
    "iso:country":"IN",
    "wof:name":"Bhalwahi",
    "wof:placetype":"locality"
},
  "geometry": {"coordinates":[85.79614000000002,26.58513],"type":"Point"}
}