{
  "type": "Feature",
  "properties": {
    "iso:country":"IN",
    "ks:ks_name":"Thundiapara",
    "ks:ks_pop":672,
    "ks:ks_type":"HABITATION",
    "name:eng_x_preferred":[
        "Thundiapara"
    ],
    "wof:name":"Thundiapara",
    "wof:placetype":"locality",
    "wof:population":672
},
  "geometry": {"coordinates":[76.730707,9.457991],"type":"Point"}
}