{
  "type": "Feature",
  "properties": {
    "iso:country":"IN",
    "ks:ks_name":"Barapahar",
    "ks:ks_pop":156,
    "ks:ks_type":"VILLAGE",
    "name:eng_x_preferred":[
        "Barapahar"
    ],
    "wof:name":"Barapahar",
    "wof:placetype":"locality",
    "wof:population":156
},
  "geometry": {"coordinates":[86.381626,22.642057],"type":"Point"}
}