{
  "type": "Feature",
  "properties": {
    "iso:country":"IN",
    "ks:ks_name":"Simiahi",
    "ks:ks_pop":2998,
    "ks:ks_type":"VILLAGE",
    "ks:ks_uagg_main":0,
    "name:eng_x_preferred":[
        "Simiahi"
    ],
    "wof:name":"Simiahi",
    "wof:placetype":"neighbourhood",
    "wof:population":2998
},
  "geometry": {"coordinates":[85.720825,26.468943],"type":"Point"}
}