{
  "type": "Feature",
  "properties": {
    "gn:admin1_code":"34.0",
    "gn:admin2_code":"221.0",
    "gn:asciiname":"Gangauli",
    "gn:country_code":"IN",
    "gn:dem":46,
    "gn:feature_class":"P",
    "gn:feature_code":"PPL",
    "gn:name":"Gangauli",
    "gn:population":0,
    "gn:timezone":"Asia/Kolkata",
    "iso:country":"IN",
    "ks:ks_name":"Gangauli",
    "ks:ks_pop":3719,
    "ks:ks_type":"VILLAGE",
    "name:eng_x_preferred":[
        "Gangauli"
    ],
    "wof:name":"Gangauli",
    "wof:placetype":"locality",
    "wof:population":3719
},
  "geometry": {"coordinates":[85.973609,25.654534],"type":"Point"}
}