{
  "type": "Feature",
  "properties": {
    "iso:country":"IN",
    "ks:ks_name":"Birwatarh",
    "ks:ks_pop":167,
    "ks:ks_type":"HABITATION",
    "name:eng_x_preferred":[
        "Birwatarh"
    ],
    "wof:name":"Birwatarh",
    "wof:placetype":"locality",
    "wof:population":167
},
  "geometry": {"coordinates":[84.575639,22.83858],"type":"Point"}
}