{
  "type": "Feature",
  "properties": {
    "iso:country":"IN",
    "ks:ks_name":"Nichebadga",
    "ks:ks_pop":151,
    "ks:ks_type":"HABITATION",
    "name:eng_x_preferred":[
        "Nichebadga"
    ],
    "wof:name":"Nichebadga",
    "wof:placetype":"locality",
    "wof:population":151
},
  "geometry": {"coordinates":[85.224132,23.549642],"type":"Point"}
}