{
  "type": "Feature",
  "properties": {
    "iso:country":"IN",
    "ks:ks_name":"Naulo",
    "ks:ks_pop":471,
    "ks:ks_type":"VILLAGE",
    "name:eng_x_preferred":[
        "Naulo"
    ],
    "wof:name":"Naulo",
    "wof:placetype":"locality",
    "wof:population":471
},
  "geometry": {"coordinates":[86.32977200000001,20.205023],"type":"Point"}
}