{
  "type": "Feature",
  "properties": {
    "gn:admin1_code":"9.0",
    "gn:admin2_code":"484.0",
    "gn:asciiname":"Babrol",
    "gn:country_code":"IN",
    "gn:dem":162,
    "gn:feature_class":"P",
    "gn:feature_code":"PPL",
    "gn:name":"B\u0101brol",
    "gn:population":0,
    "gn:timezone":"Asia/Kolkata",
    "iso:country":"IN",
    "ks:ks_name":"Babrol",
    "ks:ks_pop":3955,
    "ks:ks_type":"VILLAGE",
    "name:eng_x_preferred":[
        "Babrol"
    ],
    "wof:name":"Babrol",
    "wof:placetype":"locality",
    "wof:population":3955
},
  "geometry": {"coordinates":[73.96128400000001,23.206346],"type":"Point"}
}