{
  "type": "Feature",
  "properties": {
    "gn:admin1_code":"37",
    "gn:admin2_code":"406.0",
    "gn:asciiname":"Tuluf",
    "gn:country_code":"IN",
    "gn:dem":375,
    "gn:feature_class":"P",
    "gn:feature_code":"PPL",
    "gn:name":"Tuluf",
    "gn:population":0,
    "gn:timezone":"Asia/Kolkata",
    "iso:country":"IN",
    "ks:ks_name":"Tuluf",
    "ks:ks_type":"VILLAGE",
    "name:eng_x_preferred":[
        "Tuluf"
    ],
    "wof:name":"Tuluf",
    "wof:placetype":"locality"
},
  "geometry": {"coordinates":[81.961941,22.542937],"type":"Point"}
}