{
  "type": "Feature",
  "properties": {
    "gn:admin1_code":"16",
    "gn:admin2_code":"505.0",
    "gn:asciiname":"Undri",
    "gn:country_code":"IN",
    "gn:dem":294,
    "gn:feature_class":"P",
    "gn:feature_code":"PPL",
    "gn:name":"Undr\u012b",
    "gn:population":0,
    "gn:timezone":"Asia/Kolkata",
    "iso:country":"IN",
    "ks:ks_alt_nam":"Undr\u012b",
    "ks:ks_name":"Undri",
    "ks:ks_type":"VILLAGE",
    "name:eng_x_preferred":[
        "Undri"
    ],
    "name:eng_x_variant":[
        "Undr\u012b"
    ],
    "wof:name":"Undri",
    "wof:placetype":"locality"
},
  "geometry": {"coordinates":[79.207835,20.999784],"type":"Point"}
}