{
  "type": "Feature",
  "properties": {
    "iso:country":"IN",
    "ks:ks_alt_nam":"CHAVAN WASTI",
    "ks:ks_name":"Chavan Wasti",
    "ks:ks_pop":140,
    "ks:ks_type":"HABITATION",
    "name:eng_x_preferred":[
        "Chavan Wasti"
    ],
    "wof:name":"Chavan Wasti",
    "wof:placetype":"locality",
    "wof:population":140
},
  "geometry": {"coordinates":[75.591497,17.056184],"type":"Point"}
}