{
  "type": "Feature",
  "properties": {
    "iso:country":"IN",
    "ks:ks_name":"Palla",
    "ks:ks_type":"VILLAGE",
    "ks:ks_uagg_main":1,
    "name:eng_x_preferred":[
        "Palla"
    ],
    "wof:name":"Palla",
    "wof:placetype":"neighbourhood"
},
  "geometry": {"coordinates":[77.185169,28.842412],"type":"Point"}
}