{
  "type": "Feature",
  "properties": {
    "gn:admin1_code":"25.0",
    "gn:admin2_code":"605.0",
    "gn:asciiname":"Talamadugu",
    "gn:country_code":"IN",
    "gn:dem":374,
    "gn:feature_class":"P",
    "gn:feature_code":"PPL",
    "gn:name":"Talamadugu",
    "gn:population":0,
    "gn:timezone":"Asia/Kolkata",
    "iso:country":"IN",
    "name:tel_x_preferred":[
        "\u0c24\u0c32\u0c2e\u0c21\u0c41\u0c17\u0c41"
    ],
    "wof:name":"Talamadugu",
    "wof:placetype":"locality"
},
  "geometry": {"coordinates":[78.87819,12.70166],"type":"Point"}
}