{
  "type": "Feature",
  "properties": {
    "gn:admin1_code":"11.0",
    "gn:admin2_code":"32.0",
    "gn:asciiname":"Bandol",
    "gn:country_code":"IN",
    "gn:dem":1072,
    "gn:feature_class":"P",
    "gn:feature_code":"PPL",
    "gn:name":"Bandol",
    "gn:population":0,
    "gn:timezone":"Asia/Kolkata",
    "iso:country":"IN",
    "name:bul_x_preferred":[
        "\u0411\u0430\u043d\u0434\u043e\u043b"
    ],
    "name:cat_x_preferred":[
        "Band\u00f2u"
    ],
    "name:ceb_x_preferred":[
        "Bandol"
    ],
    "name:deu_x_preferred":[
        "Bandol"
    ],
    "name:eus_x_preferred":[
        "Band\u00f2u"
    ],
    "name:fra_x_preferred":[
        "Bandol"
    ],
    "name:hun_x_preferred":[
        "Bandol"
    ],
    "name:hye_x_preferred":[
        "\u0532\u0561\u0576\u0564\u0578\u056c"
    ],
    "name:ita_x_preferred":[
        "Bandol"
    ],
    "name:jpn_x_preferred":[
        "\u30d0\u30f3\u30c9\u30fc\u30eb"
    ],
    "name:lmo_x_preferred":[
        "Bandol"
    ],
    "name:mlg_x_preferred":[
        "Bandol"
    ],
    "name:msa_x_preferred":[
        "Bandol"
    ],
    "name:nld_x_preferred":[
        "Bandol"
    ],
    "name:nor_x_preferred":[
        "Bandol"
    ],
    "name:oci_x_preferred":[
        "Band\u00f2u"
    ],
    "name:pms_x_preferred":[
        "Bandol"
    ],
    "name:pol_x_preferred":[
        "Bandol"
    ],
    "name:por_x_preferred":[
        "Bandol"
    ],
    "name:ron_x_preferred":[
        "Bandol"
    ],
    "name:rus_x_preferred":[
        "\u0411\u0430\u043d\u0434\u043e\u043b\u044c"
    ],
    "name:slk_x_preferred":[
        "Bandol"
    ],
    "name:spa_x_preferred":[
        "Bandol"
    ],
    "name:sqi_x_preferred":[
        "Bandol"
    ],
    "name:srp_x_preferred":[
        "\u0411\u0430\u043d\u0434\u043e\u043b"
    ],
    "name:swe_x_preferred":[
        "Bandol"
    ],
    "name:ukr_x_preferred":[
        "\u0411\u0430\u043d\u0434\u043e\u043b\u044c"
    ],
    "name:vie_x_preferred":[
        "Bandol"
    ],
    "name:vol_x_preferred":[
        "Bandol"
    ],
    "name:war_x_preferred":[
        "Bandol"
    ],
    "name:zho_x_preferred":[
        "\u90a6\u591a\u52d2"
    ],
    "wof:name":"Bandol",
    "wof:placetype":"locality"
},
  "geometry": {"coordinates":[77.1661,30.68269],"type":"Point"}
}