{
  "type": "Feature",
  "properties": {
    "gn:admin1_code":"19.0",
    "gn:admin2_code":"570.0",
    "gn:asciiname":"Totadahalli",
    "gn:country_code":"IN",
    "gn:dem":1202,
    "gn:feature_class":"P",
    "gn:feature_code":"PPL",
    "gn:name":"Totadahalli",
    "gn:population":0,
    "gn:timezone":"Asia/Kolkata",
    "iso:country":"IN",
    "wof:name":"Totadahalli",
    "wof:placetype":"locality"
},
  "geometry": {"coordinates":[75.74114,13.38052],"type":"Point"}
}