{
  "type": "Feature",
  "properties": {
    "gn:admin1_code":"2.0",
    "gn:admin2_code":"551.0",
    "gn:asciiname":"Visyanadhapuram",
    "gn:country_code":"IN",
    "gn:dem":99,
    "gn:feature_class":"P",
    "gn:feature_code":"PPL",
    "gn:name":"Visy\u0101nadhapuram",
    "gn:population":0,
    "gn:timezone":"Asia/Kolkata",
    "iso:country":"IN",
    "ks:ks_alt_nam":"Visy\u0101nadhapuram",
    "ks:ks_alt_nam_2":"Visyanadhapuram",
    "ks:ks_name":"Viswanathapuram",
    "ks:ks_pop":56,
    "ks:ks_type":"VILLAGE",
    "name:eng_x_preferred":[
        "Viswanathapuram"
    ],
    "name:eng_x_variant":[
        "Visyanadhapuram",
        "Visy\u0101nadhapuram"
    ],
    "wof:name":"Viswanathapuram",
    "wof:placetype":"locality",
    "wof:population":56
},
  "geometry": {"coordinates":[79.186519,14.552687],"type":"Point"}
}