{
  "type": "Feature",
  "properties": {
    "iso:country":"IN",
    "ks:ks_name":"Giddi",
    "ks:ks_pop":132,
    "ks:ks_type":"VILLAGE",
    "name:eng_x_preferred":[
        "Giddi"
    ],
    "wof:name":"Giddi",
    "wof:placetype":"locality",
    "wof:population":132
},
  "geometry": {"coordinates":[84.998377,23.966406],"type":"Point"}
}