{
  "type": "Feature",
  "properties": {
    "iso:country":"IN",
    "ks:ks_alt_nam":"bangalwadi",
    "ks:ks_name":"Bangalwadi",
    "ks:ks_pop":110,
    "ks:ks_type":"HABITATION",
    "name:eng_x_preferred":[
        "Bangalwadi"
    ],
    "wof:name":"Bangalwadi",
    "wof:placetype":"locality",
    "wof:population":110
},
  "geometry": {"coordinates":[73.122801,18.693789],"type":"Point"}
}