{
  "type": "Feature",
  "properties": {
    "iso:country":"IN",
    "ks:ks_name":"Tolyunba Khal",
    "ks:ks_pop":228,
    "ks:ks_type":"VILLAGE",
    "name:eng_x_preferred":[
        "Tolyunba Khal"
    ],
    "wof:name":"Tolyunba Khal",
    "wof:placetype":"locality",
    "wof:population":228
},
  "geometry": {"coordinates":[78.939849,29.725005],"type":"Point"}
}