{
  "type": "Feature",
  "properties": {
    "iso:country":"IN",
    "ks:ks_alt_nam":"Swami ki dhani",
    "ks:ks_name":"Swami Ki Dhani",
    "ks:ks_pop":341,
    "ks:ks_type":"HABITATION",
    "name:eng_x_preferred":[
        "Swami Ki Dhani"
    ],
    "wof:name":"Swami Ki Dhani",
    "wof:placetype":"locality",
    "wof:population":341
},
  "geometry": {"coordinates":[75.339506,28.044355],"type":"Point"}
}