{
  "type": "Feature",
  "properties": {
    "iso:country":"IN",
    "ks:ks_name":"Pechatilla",
    "ks:ks_pop":589,
    "ks:ks_type":"HABITATION",
    "ks:ks_uagg_main":0,
    "name:eng_x_preferred":[
        "Pechatilla"
    ],
    "wof:name":"Pechatilla",
    "wof:placetype":"neighbourhood",
    "wof:population":589
},
  "geometry": {"coordinates":[92.183239,24.26263],"type":"Point"}
}