{
  "type": "Feature",
  "properties": {
    "gn:admin1_code":"36",
    "gn:admin2_code":"188.0",
    "gn:asciiname":"Parahi",
    "gn:country_code":"IN",
    "gn:dem":88,
    "gn:feature_class":"P",
    "gn:feature_code":"PPL",
    "gn:name":"Parahi",
    "gn:population":0,
    "gn:timezone":"Asia/Kolkata",
    "iso:country":"IN",
    "name:und_x_variant":[
        "Pipra Chur\u0101man"
    ],
    "wof:name":"Parahi",
    "wof:placetype":"neighbourhood"
},
  "geometry": {"coordinates":[83.45021,26.87657],"type":"Point"}
}