{
  "type": "Feature",
  "properties": {
    "gn:admin1_code":"36.0",
    "gn:admin2_code":"182.0",
    "gn:asciiname":"Chiti",
    "gn:country_code":"IN",
    "gn:dem":103,
    "gn:feature_class":"P",
    "gn:feature_code":"PPL",
    "gn:name":"Ch\u012bti",
    "gn:population":0,
    "gn:timezone":"Asia/Kolkata",
    "iso:country":"IN",
    "name:ceb_x_preferred":[
        "Chiti"
    ],
    "name:fra_x_preferred":[
        "Chiti"
    ],
    "name:mai_x_preferred":[
        "\u091a\u093f\u0924\u0940"
    ],
    "name:msa_x_preferred":[
        "Chiti"
    ],
    "name:nep_x_preferred":[
        "\u091a\u093f\u0924\u0940"
    ],
    "name:new_x_preferred":[
        "\u091a\u093f\u0924\u0940"
    ],
    "name:pol_x_preferred":[
        "Chiti"
    ],
    "wof:name":"Chiti",
    "wof:placetype":"locality"
},
  "geometry": {"coordinates":[82.37583000000002,27.29796],"type":"Point"}
}