{
  "type": "Feature",
  "properties": {
    "iso:country":"IN",
    "ks:ks_name":"Podi",
    "ks:ks_pop":365,
    "ks:ks_type":"HABITATION",
    "name:eng_x_preferred":[
        "Podi"
    ],
    "wof:name":"Podi",
    "wof:placetype":"locality",
    "wof:population":365
},
  "geometry": {"coordinates":[81.815455,24.132552],"type":"Point"}
}