{
  "type": "Feature",
  "properties": {
    "iso:country":"IN",
    "ks:ks_name":"Bheta",
    "ks:ks_pop":93,
    "ks:ks_type":"VILLAGE",
    "name:eng_x_preferred":[
        "Bheta"
    ],
    "wof:name":"Bheta",
    "wof:placetype":"locality",
    "wof:population":93
},
  "geometry": {"coordinates":[78.94404400000001,29.811009],"type":"Point"}
}