{
  "type": "Feature",
  "properties": {
    "iso:country":"IN",
    "ks:ks_name":"Muktama",
    "ks:ks_pop":1191,
    "ks:ks_type":"VILLAGE",
    "name:eng_x_preferred":[
        "Muktama"
    ],
    "wof:name":"Muktama",
    "wof:placetype":"locality",
    "wof:population":1191
},
  "geometry": {"coordinates":[85.498209,24.047879],"type":"Point"}
}