{
  "type": "Feature",
  "properties": {
    "gn:admin1_code":"28.0",
    "gn:admin2_code":"327.0",
    "gn:asciiname":"Chaibhir",
    "gn:country_code":"IN",
    "gn:dem":2173,
    "gn:feature_class":"P",
    "gn:feature_code":"PPL",
    "gn:name":"Cha\u012bbh\u012br",
    "gn:population":0,
    "gn:timezone":"Asia/Kolkata",
    "iso:country":"IN",
    "wof:name":"Chaibhir",
    "wof:placetype":"locality"
},
  "geometry": {"coordinates":[88.10178000000001,27.01313],"type":"Point"}
}