{
  "type": "Feature",
  "properties": {
    "iso:country":"IN",
    "ks:ks_name":"Ashimpi",
    "ks:ks_pop":205,
    "ks:ks_type":"VILLAGE",
    "name:eng_x_preferred":[
        "Ashimpi"
    ],
    "wof:name":"Ashimpi",
    "wof:placetype":"locality",
    "wof:population":205
},
  "geometry": {"coordinates":[73.624788,18.114434],"type":"Point"}
}