{
  "type": "Feature",
  "properties": {
    "iso:country":"IN",
    "ks:ks_name":"Badshahpur Talab",
    "ks:ks_pop":1070,
    "ks:ks_type":"HABITATION",
    "name:eng_x_preferred":[
        "Badshahpur Talab"
    ],
    "wof:name":"Badshahpur Talab",
    "wof:placetype":"locality",
    "wof:population":1070
},
  "geometry": {"coordinates":[78.006865,28.46117],"type":"Point"}
}