{
  "type": "Feature",
  "properties": {
    "iso:country":"IN",
    "ks:ks_name":"Lupungpiri",
    "ks:ks_pop":125,
    "ks:ks_type":"HABITATION",
    "name:eng_x_preferred":[
        "Lupungpiri"
    ],
    "wof:name":"Lupungpiri",
    "wof:placetype":"locality",
    "wof:population":125
},
  "geometry": {"coordinates":[85.667565,23.000812],"type":"Point"}
}