{
  "type": "Feature",
  "properties": {
    "iso:country":"IN",
    "ks:ks_name":"Shirishbani",
    "ks:ks_pop":42,
    "ks:ks_type":"VILLAGE",
    "name:eng_x_preferred":[
        "Shirishbani"
    ],
    "wof:name":"Shirishbani",
    "wof:placetype":"locality",
    "wof:population":42
},
  "geometry": {"coordinates":[86.54246500000001,22.496385],"type":"Point"}
}