{
  "type": "Feature",
  "properties": {
    "iso:country":"IN",
    "ks:ks_name":"Hunsekatte G.hatty",
    "ks:ks_pop":249,
    "ks:ks_type":"HABITATION",
    "name:eng_x_preferred":[
        "Hunsekatte G.hatty"
    ],
    "wof:name":"Hunsekatte G.hatty",
    "wof:placetype":"locality",
    "wof:population":249
},
  "geometry": {"coordinates":[76.26989399999999,14.242449],"type":"Point"}
}