{
  "type": "Feature",
  "properties": {
    "gn:admin1_code":"11.0",
    "gn:admin2_code":"32.0",
    "gn:asciiname":"Talon",
    "gn:country_code":"IN",
    "gn:dem":784,
    "gn:feature_class":"P",
    "gn:feature_code":"PPL",
    "gn:name":"T\u0101lon",
    "gn:population":0,
    "gn:timezone":"Asia/Kolkata",
    "iso:country":"IN",
    "wof:name":"Talon",
    "wof:placetype":"locality"
},
  "geometry": {"coordinates":[77.31846999999998,30.5733],"type":"Point"}
}