{
  "type": "Feature",
  "properties": {
    "iso:country":"IN",
    "ks:ks_name":"Dera Sukhniya",
    "ks:ks_pop":236,
    "ks:ks_type":"HABITATION",
    "name:eng_x_preferred":[
        "Dera Sukhniya"
    ],
    "wof:name":"Dera Sukhniya",
    "wof:placetype":"locality",
    "wof:population":236
},
  "geometry": {"coordinates":[78.45598200000001,27.970044],"type":"Point"}
}