{
  "type": "Feature",
  "properties": {
    "iso:country":"IN",
    "ks:ks_name":"Palekarwadi",
    "ks:ks_pop":221,
    "ks:ks_type":"VILLAGE",
    "name:eng_x_preferred":[
        "Palekarwadi"
    ],
    "wof:name":"Palekarwadi",
    "wof:placetype":"locality",
    "wof:population":221
},
  "geometry": {"coordinates":[73.46247700000001,16.552584],"type":"Point"}
}