{
  "type": "Feature",
  "properties": {
    "iso:country":"IN",
    "ks:ks_name":"Bir Sarkar",
    "ks:ks_pop":27,
    "ks:ks_type":"VILLAGE",
    "name:eng_x_preferred":[
        "Bir Sarkar"
    ],
    "wof:name":"Bir Sarkar",
    "wof:placetype":"locality",
    "wof:population":27
},
  "geometry": {"coordinates":[75.02147100000001,31.113892],"type":"Point"}
}