{
  "type": "Feature",
  "properties": {
    "iso:country":"IN",
    "ks:ks_name":"Soyagaon",
    "ks:ks_pop":41209,
    "ks:ks_type":"VILLAGE",
    "ks:ks_uagg_main":0,
    "name:eng_x_preferred":[
        "Soyagaon"
    ],
    "wof:name":"Soyagaon",
    "wof:placetype":"neighbourhood",
    "wof:population":41209
},
  "geometry": {"coordinates":[74.50567100000001,20.551761],"type":"Point"}
}