{
  "type": "Feature",
  "properties": {
    "gn:admin1_code":"40.0",
    "gn:admin2_code":"535",
    "gn:asciiname":"Seripalli",
    "gn:country_code":"IN",
    "gn:dem":583,
    "gn:feature_class":"P",
    "gn:feature_code":"PPL",
    "gn:name":"Seripalli",
    "gn:population":0,
    "gn:timezone":"Asia/Kolkata",
    "iso:country":"IN",
    "wof:name":"Seripalli",
    "wof:placetype":"locality"
},
  "geometry": {"coordinates":[78.6187,17.78901],"type":"Point"}
}