{
  "type": "Feature",
  "properties": {
    "gn:admin1_code":"25.0",
    "gn:admin2_code":"605.0",
    "gn:asciiname":"Kuppakalmedu",
    "gn:country_code":"IN",
    "gn:dem":117,
    "gn:feature_class":"P",
    "gn:feature_code":"PPL",
    "gn:name":"Kuppakalmedu",
    "gn:population":0,
    "gn:timezone":"Asia/Kolkata",
    "iso:country":"IN",
    "ks:ks_name":"Kuppukalmedu",
    "ks:ks_pop":926,
    "ks:ks_type":"HABITATION",
    "name:eng_x_preferred":[
        "Kuppukalmedu"
    ],
    "name:eng_x_variant":[
        "Kuppakalmedu"
    ],
    "wof:name":"Kuppukalmedu",
    "wof:placetype":"locality",
    "wof:population":926
},
  "geometry": {"coordinates":[79.52553,13.006055],"type":"Point"}
}