{
  "type": "Feature",
  "properties": {
    "iso:country":"IN",
    "ks:ks_name":"Dhari No. 1",
    "ks:ks_pop":1116,
    "ks:ks_type":"HABITATION",
    "name:eng_x_preferred":[
        "Dhari No. 1"
    ],
    "wof:name":"Dhari No. 1",
    "wof:placetype":"locality",
    "wof:population":1116
},
  "geometry": {"coordinates":[81.414877,24.199064],"type":"Point"}
}