{
  "type": "Feature",
  "properties": {
    "iso:country":"IN",
    "ks:ks_alt_nam":"CHURKA DHURA",
    "ks:ks_name":"Churka Dhura",
    "ks:ks_pop":552,
    "ks:ks_type":"HABITATION",
    "name:eng_x_preferred":[
        "Churka Dhura"
    ],
    "wof:name":"Churka Dhura",
    "wof:placetype":"locality",
    "wof:population":552
},
  "geometry": {"coordinates":[88.762032,26.8321],"type":"Point"}
}