{
  "type": "Feature",
  "properties": {
    "iso:country":"IN",
    "ks:ks_alt_nam":"Sheku tanda",
    "ks:ks_name":"Sheku Tanda",
    "ks:ks_pop":157,
    "ks:ks_type":"HABITATION",
    "name:eng_x_preferred":[
        "Sheku Tanda"
    ],
    "wof:name":"Sheku Tanda",
    "wof:placetype":"locality",
    "wof:population":157
},
  "geometry": {"coordinates":[76.962706,17.671322],"type":"Point"}
}