{
  "type": "Feature",
  "properties": {
    "gn:admin1_code":"39",
    "gn:admin2_code":"61.0",
    "gn:asciiname":"Birwa ki Bari",
    "gn:country_code":"IN",
    "gn:dem":843,
    "gn:feature_class":"P",
    "gn:feature_code":"PPL",
    "gn:name":"Birwa ki B\u0101ri",
    "gn:population":0,
    "gn:timezone":"Asia/Kolkata",
    "iso:country":"IN",
    "wof:name":"Birwa ki Bari",
    "wof:placetype":"locality"
},
  "geometry": {"coordinates":[78.85809999999999,29.68315],"type":"Point"}
}