{
  "type": "Feature",
  "properties": {
    "gn:country":"IN",
    "gn:fcode":"PPL",
    "gn:population":10133,
    "iso:country":"IN",
    "qs:name":"K\u012bran\u016br",
    "qs:photos_9r":0,
    "qs:photos_sr":0,
    "qs:pop_sr":"6",
    "wof:name":"K\u012bran\u016br",
    "wof:placetype":"locality",
    "wof:population":10133
},
  "geometry": {"coordinates":[78.78682000000001,10.56988],"type":"Point"}
}