{
  "type": "Feature",
  "properties": {
    "gn:admin1_code":"36",
    "gn:admin2_code":"195.0",
    "gn:asciiname":"Arazi Inglish",
    "gn:country_code":"IN",
    "gn:dem":76,
    "gn:feature_class":"P",
    "gn:feature_code":"PPL",
    "gn:name":"Ar\u0101zi Inglish",
    "gn:population":0,
    "gn:timezone":"Asia/Kolkata",
    "iso:country":"IN",
    "ks:ks_alt_nam":"Ar\u0101zi Inglish",
    "ks:ks_name":"Arazi Inglish",
    "ks:ks_type":"VILLAGE",
    "ks:ks_uagg_main":0,
    "name:eng_x_preferred":[
        "Arazi Inglish"
    ],
    "name:eng_x_variant":[
        "Ar\u0101zi Inglish"
    ],
    "wof:name":"Arazi Inglish",
    "wof:placetype":"neighbourhood"
},
  "geometry": {"coordinates":[83.47986299999999,25.671072],"type":"Point"}
}