{
  "type": "Feature",
  "properties": {
    "gn:admin1_code":"39.0",
    "gn:admin2_code":"64.0",
    "gn:asciiname":"Maundali",
    "gn:country_code":"IN",
    "gn:dem":928,
    "gn:feature_class":"P",
    "gn:feature_code":"PPL",
    "gn:name":"Maund\u0101li",
    "gn:population":0,
    "gn:timezone":"Asia/Kolkata",
    "iso:country":"IN",
    "ks:ks_name":"Maudali",
    "ks:ks_pop":19,
    "ks:ks_type":"HABITATION",
    "name:eng_x_preferred":[
        "Maudali"
    ],
    "name:eng_x_variant":[
        "Maundali"
    ],
    "wof:name":"Maudali",
    "wof:placetype":"locality",
    "wof:population":19
},
  "geometry": {"coordinates":[79.19922099999999,29.65935],"type":"Point"}
}