{
  "type": "Feature",
  "properties": {
    "iso:country":"IN",
    "ks:ks_name":"Nowakatha",
    "ks:ks_pop":290,
    "ks:ks_type":"HABITATION",
    "name:eng_x_preferred":[
        "Nowakatha"
    ],
    "wof:name":"Nowakatha",
    "wof:placetype":"locality",
    "wof:population":290
},
  "geometry": {"coordinates":[91.47399799999999,26.032033],"type":"Point"}
}