{
  "type": "Feature",
  "properties": {
    "iso:country":"IN",
    "ks:ks_name":"Kokkur",
    "ks:ks_pop":1000,
    "ks:ks_type":"HABITATION",
    "name:eng_x_preferred":[
        "Kokkur"
    ],
    "wof:name":"Kokkur",
    "wof:placetype":"locality",
    "wof:population":1000
},
  "geometry": {"coordinates":[79.565067,11.02033],"type":"Point"}
}