{
  "type": "Feature",
  "properties": {
    "iso:country":"IN",
    "ks:ks_name":"Chargaon",
    "ks:ks_pop":319,
    "ks:ks_type":"HABITATION",
    "name:eng_x_preferred":[
        "Chargaon"
    ],
    "wof:name":"Chargaon",
    "wof:placetype":"locality",
    "wof:population":319
},
  "geometry": {"coordinates":[81.621813,19.569212],"type":"Point"}
}