{
  "type": "Feature",
  "properties": {
    "gn:admin1_code":"34",
    "gn:admin2_code":"232.0",
    "gn:asciiname":"Rauni",
    "gn:country_code":"IN",
    "gn:dem":77,
    "gn:feature_class":"P",
    "gn:feature_code":"PPL",
    "gn:name":"Rauni",
    "gn:population":0,
    "gn:timezone":"Asia/Kolkata",
    "iso:country":"IN",
    "name:fra_x_preferred":[
        "Rauni"
    ],
    "wof:name":"Rauni",
    "wof:placetype":"locality"
},
  "geometry": {"coordinates":[83.88091999999997,25.3795],"type":"Point"}
}