{
  "type": "Feature",
  "properties": {
    "iso:country":"IN",
    "ks:ks_alt_nam":"RAHIKA TOLA",
    "ks:ks_name":"Rahika Tola",
    "ks:ks_pop":255,
    "ks:ks_type":"HABITATION",
    "name:eng_x_preferred":[
        "Rahika Tola"
    ],
    "wof:name":"Rahika Tola",
    "wof:placetype":"locality",
    "wof:population":255
},
  "geometry": {"coordinates":[87.72817999999999,26.027868],"type":"Point"}
}