{
  "type": "Feature",
  "properties": {
    "iso:country":"IN",
    "ks:ks_name":"Peringottukurissi Rd Junc",
    "ks:ks_pop":486,
    "ks:ks_type":"HABITATION",
    "name:eng_x_preferred":[
        "Peringottukurissi Rd Junc"
    ],
    "wof:name":"Peringottukurissi Rd Junc",
    "wof:placetype":"locality",
    "wof:population":486
},
  "geometry": {"coordinates":[76.44481,10.713192],"type":"Point"}
}