{
  "type": "Feature",
  "properties": {
    "iso:country":"IN",
    "ks:ks_name":"Shimultari",
    "ks:ks_pop":0,
    "ks:ks_type":"VILLAGE",
    "name:eng_x_preferred":[
        "Shimultari"
    ],
    "wof:name":"Shimultari",
    "wof:placetype":"locality",
    "wof:population":0
},
  "geometry": {"coordinates":[87.40333,23.862608],"type":"Point"}
}