{
  "type": "Feature",
  "properties": {
    "iso:country":"IN",
    "ks:ks_name":"Halpur",
    "ks:ks_pop":10,
    "ks:ks_type":"VILLAGE",
    "ks:ks_uagg_main":0,
    "name:eng_x_preferred":[
        "Halpur"
    ],
    "wof:name":"Halpur",
    "wof:placetype":"neighbourhood",
    "wof:population":10
},
  "geometry": {"coordinates":[79.688957,27.843385],"type":"Point"}
}