{
  "type": "Feature",
  "properties": {
    "iso:country":"IN",
    "ks:ks_name":"Ramadha",
    "ks:ks_pop":1042,
    "ks:ks_type":"VILLAGE",
    "name:eng_x_preferred":[
        "Ramadha"
    ],
    "wof:name":"Ramadha",
    "wof:placetype":"locality",
    "wof:population":1042
},
  "geometry": {"coordinates":[86.791758,21.237909],"type":"Point"}
}