{
  "type": "Feature",
  "properties": {
    "iso:country":"IN",
    "ks:ks_alt_nam":"DHELEMALA",
    "ks:ks_name":"Dhelemala",
    "ks:ks_pop":150,
    "ks:ks_type":"HABITATION",
    "name:eng_x_preferred":[
        "Dhelemala"
    ],
    "wof:name":"Dhelemala",
    "wof:placetype":"locality",
    "wof:population":150
},
  "geometry": {"coordinates":[74.24811200000001,17.149139],"type":"Point"}
}