{
  "type": "Feature",
  "properties": {
    "gn:admin1_code":"23",
    "gn:admin2_code":"52.0",
    "gn:asciiname":"Tipari",
    "gn:country_code":"IN",
    "gn:dem":301,
    "gn:feature_class":"P",
    "gn:feature_code":"PPL",
    "gn:name":"T\u012bpari",
    "gn:population":0,
    "gn:timezone":"Asia/Kolkata",
    "iso:country":"IN",
    "wof:name":"Tipari",
    "wof:placetype":"locality"
},
  "geometry": {"coordinates":[76.62827,30.71468],"type":"Point"}
}