{
  "type": "Feature",
  "properties": {
    "iso:country":"IN",
    "ks:ks_name":"Patwadi",
    "ks:ks_pop":83,
    "ks:ks_type":"HABITATION",
    "name:eng_x_preferred":[
        "Patwadi"
    ],
    "wof:name":"Patwadi",
    "wof:placetype":"locality",
    "wof:population":83
},
  "geometry": {"coordinates":[73.75777100000001,16.611273],"type":"Point"}
}