{
  "type": "Feature",
  "properties": {
    "iso:country":"IN",
    "ks:ks_name":"Chak Wasia",
    "ks:ks_pop":0,
    "ks:ks_type":"VILLAGE",
    "name:eng_x_preferred":[
        "Chak Wasia"
    ],
    "wof:name":"Chak Wasia",
    "wof:placetype":"locality",
    "wof:population":0
},
  "geometry": {"coordinates":[85.781741,25.130814],"type":"Point"}
}