{
  "type": "Feature",
  "properties": {
    "iso:country":"IN",
    "ks:ks_alt_nam":"Ambharan pada",
    "ks:ks_name":"Ambharan Pada",
    "ks:ks_pop":145,
    "ks:ks_type":"HABITATION",
    "name:eng_x_preferred":[
        "Ambharan Pada"
    ],
    "wof:name":"Ambharan Pada",
    "wof:placetype":"locality",
    "wof:population":145
},
  "geometry": {"coordinates":[72.88883,19.591772],"type":"Point"}
}