{
  "type": "Feature",
  "properties": {
    "iso:country":"IN",
    "ks:ks_name":"Nichetola",
    "ks:ks_pop":94,
    "ks:ks_type":"HABITATION",
    "name:eng_x_preferred":[
        "Nichetola"
    ],
    "wof:name":"Nichetola",
    "wof:placetype":"locality",
    "wof:population":94
},
  "geometry": {"coordinates":[85.898257,22.218304],"type":"Point"}
}