{
  "type": "Feature",
  "properties": {
    "iso:country":"IN",
    "ks:ks_name":"Anduguda",
    "ks:ks_pop":70,
    "ks:ks_type":"HABITATION",
    "name:eng_x_preferred":[
        "Anduguda"
    ],
    "wof:name":"Anduguda",
    "wof:placetype":"locality",
    "wof:population":70
},
  "geometry": {"coordinates":[78.83055299999999,19.62422],"type":"Point"}
}