{
  "type": "Feature",
  "properties": {
    "gn:admin1_code":"36",
    "gn:admin2_code":"200.0",
    "gn:asciiname":"Gajana",
    "gn:country_code":"IN",
    "gn:dem":301,
    "gn:feature_class":"P",
    "gn:feature_code":"PPL",
    "gn:name":"Gajana",
    "gn:population":0,
    "gn:timezone":"Asia/Kolkata",
    "iso:country":"IN",
    "ks:ks_name":"Gajana",
    "ks:ks_pop":50,
    "ks:ks_type":"VILLAGE",
    "name:eng_x_preferred":[
        "Gajana"
    ],
    "name:guj_x_preferred":[
        "\u0a97\u0a9c\u0aa3\u0abe"
    ],
    "wof:name":"Gajana",
    "wof:placetype":"locality",
    "wof:population":50
},
  "geometry": {"coordinates":[82.983632,24.759143],"type":"Point"}
}