{
  "type": "Feature",
  "properties": {
    "gn:admin1_code":"12.0",
    "gn:admin2_code":"008",
    "gn:asciiname":"Sonim",
    "gn:country_code":"IN",
    "gn:dem":1650,
    "gn:feature_class":"P",
    "gn:feature_code":"PPL",
    "gn:name":"Sonim",
    "gn:population":0,
    "gn:timezone":"Asia/Kolkata",
    "iso:country":"IN",
    "name:deu_x_preferred":[
        "Sonim Son"
    ],
    "name:fra_x_preferred":[
        "Sonim"
    ],
    "name:ita_x_preferred":[
        "Sonim"
    ],
    "name:jpn_x_preferred":[
        "\u30bd\u30cb\u30f3"
    ],
    "name:kor_x_preferred":[
        "\uc131\uc120\uc784"
    ],
    "name:tgl_x_preferred":[
        "Sonim"
    ],
    "wof:name":"Sonim",
    "wof:placetype":"locality"
},
  "geometry": {"coordinates":[74.52923,34.12373],"type":"Point"}
}