{
  "type": "Feature",
  "properties": {
    "iso:country":"IN",
    "ks:ks_name":"Limda",
    "ks:ks_pop":2671,
    "ks:ks_type":"VILLAGE",
    "ks:ks_uagg_main":0,
    "name:eng_x_preferred":[
        "Limda"
    ],
    "wof:name":"Limda",
    "wof:placetype":"neighbourhood",
    "wof:population":2671
},
  "geometry": {"coordinates":[73.332528,23.934278],"type":"Point"}
}