{
  "type": "Feature",
  "properties": {
    "iso:country":"IN",
    "ks:ks_name":"Bachanahalli",
    "ks:ks_pop":161,
    "ks:ks_type":"HABITATION",
    "name:eng_x_preferred":[
        "Bachanahalli"
    ],
    "wof:name":"Bachanahalli",
    "wof:placetype":"locality",
    "wof:population":161
},
  "geometry": {"coordinates":[75.68212699999999,13.014858],"type":"Point"}
}