{
  "type": "Feature",
  "properties": {
    "gn:admin1_code":"11.0",
    "gn:admin2_code":"033",
    "gn:asciiname":"Jur",
    "gn:country_code":"IN",
    "gn:dem":1521,
    "gn:feature_class":"P",
    "gn:feature_code":"PPL",
    "gn:name":"Jur",
    "gn:population":0,
    "gn:timezone":"Asia/Kolkata",
    "iso:country":"IN",
    "name:ceb_x_preferred":[
        "Jur"
    ],
    "name:ces_x_preferred":[
        "Jur"
    ],
    "name:deu_x_preferred":[
        "Jur"
    ],
    "name:slk_x_preferred":[
        "Jur"
    ],
    "name:swe_x_preferred":[
        "Jur"
    ],
    "name:und_x_variant":[
        "J\u016bd"
    ],
    "wof:name":"Jur",
    "wof:placetype":"locality"
},
  "geometry": {"coordinates":[77.01297,31.24905],"type":"Point"}
}