{
  "type": "Feature",
  "properties": {
    "gn:admin1_code":"34.0",
    "gn:admin2_code":"225.0",
    "gn:asciiname":"Kadar Chak",
    "gn:country_code":"IN",
    "gn:dem":59,
    "gn:feature_class":"P",
    "gn:feature_code":"PPL",
    "gn:name":"Kadar Chak",
    "gn:population":0,
    "gn:timezone":"Asia/Kolkata",
    "iso:country":"IN",
    "wof:name":"Kadar Chak",
    "wof:placetype":"locality"
},
  "geometry": {"coordinates":[86.71958000000002,25.04631],"type":"Point"}
}