{
  "type": "Feature",
  "properties": {
    "iso:country":"IN",
    "ks:ks_name":"Saganpara 1",
    "ks:ks_pop":15,
    "ks:ks_type":"HABITATION",
    "ks:ks_uagg_main":0,
    "name:eng_x_preferred":[
        "Saganpara 1"
    ],
    "wof:name":"Saganpara 1",
    "wof:placetype":"locality",
    "wof:population":15
},
  "geometry": {"coordinates":[91.487424,26.042479],"type":"Point"}
}