{
  "type": "Feature",
  "properties": {
    "gn:country":"IN",
    "gn:fcode":"PPL",
    "gn:pop":13506,
    "iso:country":"IN",
    "name:ben_x_preferred":[
        "\u0996\u09a1\u09bc\u0997\u09aa\u09c1\u09b0"
    ],
    "name:bpy_x_preferred":[
        "\u0996\u09a1\u09bc\u0997\u09aa\u09c1\u09b0"
    ],
    "name:ceb_x_preferred":[
        "Kharg\u0101pur"
    ],
    "name:eng_x_preferred":[
        "Khargapur"
    ],
    "name:ita_x_preferred":[
        "Khargapur"
    ],
    "name:msa_x_preferred":[
        "Khargapur"
    ],
    "name:nan_x_preferred":[
        "Khargapur"
    ],
    "name:new_x_preferred":[
        "\u0916\u0930\u094d\u0917\u092a\u0941\u0930"
    ],
    "name:nld_x_preferred":[
        "Khargapur"
    ],
    "name:por_x_preferred":[
        "Khargapur"
    ],
    "name:swe_x_preferred":[
        "Kharg\u0101pur"
    ],
    "name:unk_x_variant":[
        "Kharg\u0101pur"
    ],
    "name:vie_x_preferred":[
        "Khargapur"
    ],
    "name:zho_x_preferred":[
        "\u5361\u5c14\u52a0\u666e\u5c14"
    ],
    "qs:name":"Khargapur",
    "qs:name_adm0":"India",
    "qs:name_adm1":"Madhya Pradesh",
    "qs:photos_9r":0,
    "qs:photos_sr":0,
    "qs:placetype":"Town",
    "qs:pop_sr":"6",
    "wd:wordcount":385,
    "wof:name":"Khargapur",
    "wof:placetype":"locality",
    "wof:population":13506
},
  "geometry": {"coordinates":[79.14400000000001,24.823],"type":"Point"}
}