{
  "type": "Feature",
  "properties": {
    "iso:country":"IN",
    "ks:ks_name":"Gordhanpar",
    "ks:ks_pop":945,
    "ks:ks_type":"VILLAGE",
    "name:eng_x_preferred":[
        "Gordhanpar"
    ],
    "wof:name":"Gordhanpar",
    "wof:placetype":"neighbourhood",
    "wof:population":945
},
  "geometry": {"coordinates":[70.000193,22.450536],"type":"Point"}
}