{
  "type": "Feature",
  "properties": {
    "iso:country":"IN",
    "ks:ks_name":"Devsingh Thanda",
    "ks:ks_pop":20,
    "ks:ks_type":"HABITATION",
    "name:eng_x_preferred":[
        "Devsingh Thanda"
    ],
    "wof:name":"Devsingh Thanda",
    "wof:placetype":"locality",
    "wof:population":20
},
  "geometry": {"coordinates":[77.75202899999999,18.110175],"type":"Point"}
}