{
  "type": "Feature",
  "properties": {
    "gn:admin1_code":"10.0",
    "gn:admin2_code":"075",
    "gn:asciiname":"Simla Maulana",
    "gn:country_code":"IN",
    "gn:dem":238,
    "gn:feature_class":"P",
    "gn:feature_code":"PPL",
    "gn:name":"Simla Maul\u0101na",
    "gn:population":0,
    "gn:timezone":"Asia/Kolkata",
    "iso:country":"IN",
    "wof:name":"Simla Maulana",
    "wof:placetype":"locality"
},
  "geometry": {"coordinates":[76.98369,29.45416],"type":"Point"}
}