{
  "type": "Feature",
  "properties": {
    "gn:admin1_code":"10.0",
    "gn:admin2_code":"71.0",
    "gn:asciiname":"Teli Majra",
    "gn:country_code":"IN",
    "gn:dem":285,
    "gn:feature_class":"P",
    "gn:feature_code":"PPL",
    "gn:name":"Teli M\u0101jra",
    "gn:population":0,
    "gn:timezone":"Asia/Kolkata",
    "iso:country":"IN",
    "ks:ks_alt_nam":"Teli M\u0101jra",
    "ks:ks_name":"Teli Majra",
    "ks:ks_type":"VILLAGE",
    "ks:ks_uagg_main":0,
    "name:eng_x_preferred":[
        "Teli Majra"
    ],
    "name:eng_x_variant":[
        "Teli M\u0101jra"
    ],
    "wof:name":"Teli Majra",
    "wof:placetype":"locality"
},
  "geometry": {"coordinates":[77.285343,30.168834],"type":"Point"}
}