{
  "type": "Feature",
  "properties": {
    "iso:country":"IN",
    "ks:ks_name":"Banukudru",
    "ks:ks_pop":169,
    "ks:ks_type":"HABITATION",
    "name:eng_x_preferred":[
        "Banukudru"
    ],
    "wof:name":"Banukudru",
    "wof:placetype":"locality",
    "wof:population":169
},
  "geometry": {"coordinates":[74.691744,13.647642],"type":"Point"}
}