{
  "type": "Feature",
  "properties": {
    "iso:country":"IN",
    "ks:ks_name":"Chorara",
    "ks:ks_pop":148,
    "ks:ks_type":"VILLAGE",
    "name:eng_x_preferred":[
        "Chorara"
    ],
    "wof:name":"Chorara",
    "wof:placetype":"locality",
    "wof:population":148
},
  "geometry": {"coordinates":[79.112177,30.24604],"type":"Point"}
}