{
  "type": "Feature",
  "properties": {
    "gn:admin1_code":"10.0",
    "gn:admin2_code":"72.0",
    "gn:asciiname":"Shekhpur",
    "gn:country_code":"IN",
    "gn:dem":261,
    "gn:feature_class":"P",
    "gn:feature_code":"PPL",
    "gn:name":"Shekhpur",
    "gn:population":0,
    "gn:timezone":"Asia/Kolkata",
    "iso:country":"IN",
    "wof:name":"Shekhpur",
    "wof:placetype":"neighbourhood"
},
  "geometry": {"coordinates":[76.92534999999999,29.99032],"type":"Point"}
}