{
  "type": "Feature",
  "properties": {
    "iso:country":"IN",
    "ks:ks_name":"Halekhan Estate",
    "ks:ks_pop":183,
    "ks:ks_type":"HABITATION",
    "name:eng_x_preferred":[
        "Halekhan Estate"
    ],
    "wof:name":"Halekhan Estate",
    "wof:placetype":"locality",
    "wof:population":183
},
  "geometry": {"coordinates":[75.48988300000001,13.126569],"type":"Point"}
}