{
  "type": "Feature",
  "properties": {
    "iso:country":"IN",
    "ks:ks_name":"Mohandih",
    "ks:ks_pop":0,
    "ks:ks_type":"VILLAGE",
    "name:eng_x_preferred":[
        "Mohandih"
    ],
    "wof:name":"Mohandih",
    "wof:placetype":"locality",
    "wof:population":0
},
  "geometry": {"coordinates":[86.666021,24.443211],"type":"Point"}
}