{
  "type": "Feature",
  "properties": {
    "iso:country":"IN",
    "ks:ks_name":"Marutipada",
    "ks:ks_pop":90,
    "ks:ks_type":"HABITATION",
    "name:eng_x_preferred":[
        "Marutipada"
    ],
    "wof:name":"Marutipada",
    "wof:placetype":"locality",
    "wof:population":90
},
  "geometry": {"coordinates":[74.900678,21.569336],"type":"Point"}
}