{
  "type": "Feature",
  "properties": {
    "gn:admin1_code":"19.0",
    "gn:admin2_code":"574.0",
    "gn:asciiname":"Mugli",
    "gn:country_code":"IN",
    "gn:dem":991,
    "gn:feature_class":"P",
    "gn:feature_code":"PPL",
    "gn:name":"Mugli",
    "gn:population":0,
    "gn:timezone":"Asia/Kolkata",
    "iso:country":"IN",
    "wof:name":"Mugli",
    "wof:placetype":"neighbourhood"
},
  "geometry": {"coordinates":[75.86696000000001,12.9976],"type":"Point"}
}