{
  "type": "Feature",
  "properties": {
    "iso:country":"IN",
    "ks:ks_alt_nam":"nagaiya ka pura",
    "ks:ks_name":"Nagaiya Ka Pura",
    "ks:ks_pop":310,
    "ks:ks_type":"HABITATION",
    "name:eng_x_preferred":[
        "Nagaiya Ka Pura"
    ],
    "wof:name":"Nagaiya Ka Pura",
    "wof:placetype":"locality",
    "wof:population":310
},
  "geometry": {"coordinates":[81.776583,25.592951],"type":"Point"}
}