{
  "type": "Feature",
  "properties": {
    "iso:country":"IN",
    "ks:ks_name":"Bhuiya Tola",
    "ks:ks_pop":133,
    "ks:ks_type":"HABITATION",
    "name:eng_x_preferred":[
        "Bhuiya Tola"
    ],
    "wof:name":"Bhuiya Tola",
    "wof:placetype":"locality",
    "wof:population":133
},
  "geometry": {"coordinates":[83.467055,24.345593],"type":"Point"}
}