{
  "type": "Feature",
  "properties": {
    "iso:country":"IN",
    "ks:ks_name":"Jaraguri No.3",
    "ks:ks_pop":762,
    "ks:ks_type":"VILLAGE",
    "name:eng_x_preferred":[
        "Jaraguri No.3"
    ],
    "wof:name":"Jaraguri No.3",
    "wof:placetype":"locality",
    "wof:population":762
},
  "geometry": {"coordinates":[90.68176699999999,26.439975],"type":"Point"}
}