{
  "type": "Feature",
  "properties": {
    "iso:country":"IN",
    "ks:ks_name":"Dashea Purwa",
    "ks:ks_pop":178,
    "ks:ks_type":"HABITATION",
    "name:eng_x_preferred":[
        "Dashea Purwa"
    ],
    "wof:name":"Dashea Purwa",
    "wof:placetype":"locality",
    "wof:population":178
},
  "geometry": {"coordinates":[81.47243,27.401432],"type":"Point"}
}