{
  "type": "Feature",
  "properties": {
    "gn:admin1_code":"36",
    "gn:admin2_code":"160.0",
    "gn:asciiname":"Anantpur",
    "gn:country_code":"IN",
    "gn:dem":143,
    "gn:feature_class":"P",
    "gn:feature_code":"PPL",
    "gn:name":"Anantpur",
    "gn:population":0,
    "gn:timezone":"Asia/Kolkata",
    "iso:country":"IN",
    "ks:ks_name":"Anant Pur",
    "ks:ks_pop":191,
    "ks:ks_type":"HABITATION",
    "name:eng_x_preferred":[
        "Anant Pur"
    ],
    "name:eng_x_variant":[
        "Anantpur"
    ],
    "name:urd_x_preferred":[
        "\u0627\u0646\u0646\u062a \u067e\u0648\u0631"
    ],
    "wof:name":"Anant Pur",
    "wof:placetype":"locality",
    "wof:population":191
},
  "geometry": {"coordinates":[79.846045,26.960172],"type":"Point"}
}