{
  "type": "Feature",
  "properties": {
    "iso:country":"IN",
    "ks:ks_name":"Dhamri",
    "ks:ks_pop":420,
    "ks:ks_type":"HABITATION",
    "name:eng_x_preferred":[
        "Dhamri"
    ],
    "wof:name":"Dhamri",
    "wof:placetype":"locality",
    "wof:population":420
},
  "geometry": {"coordinates":[87.893394,24.284993],"type":"Point"}
}