{
  "type": "Feature",
  "properties": {
    "iso:country":"IN",
    "ks:ks_name":"Karaibari",
    "ks:ks_pop":1686,
    "ks:ks_type":"VILLAGE",
    "name:eng_x_preferred":[
        "Karaibari"
    ],
    "wof:name":"Karaibari",
    "wof:placetype":"locality",
    "wof:population":1686
},
  "geometry": {"coordinates":[89.184348,26.65983],"type":"Point"}
}