{
  "type": "Feature",
  "properties": {
    "iso:country":"IN",
    "ks:ks_name":"Mara",
    "ks:ks_pop":10,
    "ks:ks_type":"HABITATION",
    "name:eng_x_preferred":[
        "Mara"
    ],
    "wof:name":"Mara",
    "wof:placetype":"locality",
    "wof:population":10
},
  "geometry": {"coordinates":[80.617898,24.564754],"type":"Point"}
}