{
  "type": "Feature",
  "properties": {
    "gn:admin1_code":"2.0",
    "gn:admin2_code":"547.0",
    "gn:asciiname":"Kotturu",
    "gn:country_code":"IN",
    "gn:dem":81,
    "gn:feature_class":"P",
    "gn:feature_code":"PPL",
    "gn:name":"Kotturu",
    "gn:population":0,
    "gn:timezone":"Asia/Kolkata",
    "iso:country":"IN",
    "wof:name":"Kotturu",
    "wof:placetype":"locality"
},
  "geometry": {"coordinates":[80.52361999999999,16.76935],"type":"Point"}
}