{
  "type": "Feature",
  "properties": {
    "gn:admin1_code":"21.0",
    "gn:admin2_code":"376.0",
    "gn:asciiname":"Purnachandrapur",
    "gn:country_code":"IN",
    "gn:dem":24,
    "gn:feature_class":"P",
    "gn:feature_code":"PPL",
    "gn:name":"Purnachandrapur",
    "gn:population":0,
    "gn:timezone":"Asia/Kolkata",
    "iso:country":"IN",
    "wof:name":"Purnachandrapur",
    "wof:placetype":"locality"
},
  "geometry": {"coordinates":[87.13481,21.8053],"type":"Point"}
}