{
  "type": "Feature",
  "properties": {
    "iso:country":"IN",
    "ks:ks_name":"Dihtola",
    "ks:ks_pop":464,
    "ks:ks_type":"HABITATION",
    "name:eng_x_preferred":[
        "Dihtola"
    ],
    "wof:name":"Dihtola",
    "wof:placetype":"locality",
    "wof:population":464
},
  "geometry": {"coordinates":[83.782695,26.44939],"type":"Point"}
}