{
  "type": "Feature",
  "properties": {
    "iso:country":"IN",
    "ks:ks_name":"Indukya Kr. Para",
    "ks:ks_pop":59,
    "ks:ks_type":"HABITATION",
    "name:eng_x_preferred":[
        "Indukya Kr. Para"
    ],
    "wof:name":"Indukya Kr. Para",
    "wof:placetype":"locality",
    "wof:population":59
},
  "geometry": {"coordinates":[92.032382,23.775399],"type":"Point"}
}