{
  "type": "Feature",
  "properties": {
    "iso:country":"IN",
    "ks:ks_name":"Kundli",
    "ks:ks_pop":305,
    "ks:ks_type":"VILLAGE",
    "name:eng_x_preferred":[
        "Kundli"
    ],
    "wof:name":"Kundli",
    "wof:placetype":"locality",
    "wof:population":305
},
  "geometry": {"coordinates":[76.252335,27.584828],"type":"Point"}
}