{
  "type": "Feature",
  "properties": {
    "iso:country":"IN",
    "ks:ks_alt_nam":"jadhavpada",
    "ks:ks_name":"Jadhavpada",
    "ks:ks_pop":417,
    "ks:ks_type":"HABITATION",
    "name:eng_x_preferred":[
        "Jadhavpada"
    ],
    "wof:name":"Jadhavpada",
    "wof:placetype":"locality",
    "wof:population":417
},
  "geometry": {"coordinates":[72.93218299999999,19.847909],"type":"Point"}
}