{
  "type": "Feature",
  "properties": {
    "iso:country":"IN",
    "ks:ks_name":"Sagunmari Pt.I",
    "ks:ks_pop":523,
    "ks:ks_type":"VILLAGE",
    "ks:ks_uagg_main":0,
    "name:eng_x_preferred":[
        "Sagunmari Pt.I"
    ],
    "wof:name":"Sagunmari Pt.I",
    "wof:placetype":"neighbourhood",
    "wof:population":523
},
  "geometry": {"coordinates":[90.192555,26.23091],"type":"Point"}
}