{
  "type": "Feature",
  "properties": {
    "iso:country":"IN",
    "ks:ks_name":"P Gulab",
    "ks:ks_pop":600,
    "ks:ks_type":"HABITATION",
    "ks:ks_uagg_main":0,
    "name:eng_x_preferred":[
        "P Gulab"
    ],
    "wof:name":"P Gulab",
    "wof:placetype":"neighbourhood",
    "wof:population":600
},
  "geometry": {"coordinates":[81.2561,25.900408],"type":"Point"}
}