{
  "type": "Feature",
  "properties": {
    "iso:country":"IN",
    "ks:ks_alt_nam":"D\u0101b",
    "ks:ks_name":"Dab",
    "ks:ks_type":"VILLAGE",
    "name:eng_x_preferred":[
        "Dab"
    ],
    "name:eng_x_variant":[
        "D\u0101b"
    ],
    "wof:name":"Dab",
    "wof:placetype":"locality"
},
  "geometry": {"coordinates":[73.977446,21.692722],"type":"Point"}
}