{
  "type": "Feature",
  "properties": {
    "iso:country":"IN",
    "ks:ks_name":"Karamgoda",
    "ks:ks_pop":0,
    "ks:ks_type":"VILLAGE",
    "name:eng_x_preferred":[
        "Karamgoda"
    ],
    "wof:name":"Karamgoda",
    "wof:placetype":"locality",
    "wof:population":0
},
  "geometry": {"coordinates":[87.52922100000001,25.010223],"type":"Point"}
}