{
  "type": "Feature",
  "properties": {
    "iso:country":"IN",
    "name:eng_x_preferred":[
        "Lady Hardinge Medical College"
    ],
    "name:hin_x_preferred":[
        "\u0932\u0947\u0921\u0940 \u0939\u093e\u0930\u094d\u0921\u093f\u0902\u0917 \u092e\u0947\u0921\u093f\u0915\u0932 \u0915\u0949\u0932\u0947\u091c"
    ],
    "name:mal_x_preferred":[
        "\u0d32\u0d47\u0d21\u0d3f \u0d39\u0d3e\u0d7c\u0d21\u0d3f\u0d02\u0d17\u0d4d \u0d2e\u0d46\u0d21\u0d3f\u0d15\u0d4d\u0d15\u0d7d \u0d15\u0d4b\u0d33\u0d47\u0d1c\u0d4d"
    ],
    "name:pan_x_preferred":[
        "\u0a32\u0a47\u0a21\u0a40 \u0a39\u0a3e\u0a30\u0a21\u0a3f\u0a70\u0a17 \u0a2e\u0a48\u0a21\u0a40\u0a15\u0a32 \u0a15\u0a3e\u0a32\u0a1c"
    ],
    "name:tel_x_preferred":[
        "\u0c32\u0c47\u0c21\u0c40 \u0c39\u0c3e\u0c30\u0c4d\u0c21\u0c3f\u0c02\u0c17\u0c4d \u0c35\u0c48\u0c26\u0c4d\u0c2f \u0c15\u0c33\u0c3e\u0c36\u0c3e\u0c32"
    ],
    "name:ukr_x_preferred":[
        "\u041c\u0435\u0434\u0438\u0447\u043d\u0438\u0439 \u043a\u043e\u043b\u0435\u0434\u0436 \u043b\u0435\u0434\u0456 \u0413\u0430\u0440\u0434\u0456\u043d\u0434\u0436"
    ],
    "qs:name":"Lady Hardinge Medical College",
    "qs:name_adm0":"India",
    "qs:name_adm1":"Delhi",
    "qs:photos":342,
    "qs:photos_1k":69,
    "qs:photos_9k":2,
    "qs:photos_9r":5,
    "qs:photos_all":342,
    "qs:photos_sr":5,
    "qs:placetype":"Suburb",
    "qs:pop_sr":"0",
    "wd:wordcount":999,
    "wof:name":"Lady Hardinge Medical College",
    "wof:placetype":"neighbourhood"
},
  "geometry": {"coordinates":[77.217511,28.635344],"type":"Point"}
}