{
  "type": "Feature",
  "properties": {
    "iso:country":"IN",
    "name:eng_x_preferred":[
        "Lady Hardinge Medical College"
    ],
    "name:ukr_x_preferred":[
        "\u041c\u0435\u0434\u0438\u0447\u043d\u0438\u0439 \u043a\u043e\u043b\u0435\u0434\u0436 \u043b\u0435\u0434\u0456 \u0413\u0430\u0440\u0434\u0456\u043d\u0434\u0436"
    ],
    "qs:name":"Lady Hardinge Medical College",
    "qs:name_adm0":"India",
    "qs:name_adm1":"Delhi",
    "qs:photos":342,
    "qs:photos_1k":69,
    "qs:photos_9k":2,
    "qs:photos_9r":5,
    "qs:photos_all":342,
    "qs:photos_sr":5,
    "qs:placetype":"Suburb",
    "qs:pop_sr":"0",
    "wd:wordcount":999,
    "wof:name":"Lady Hardinge Medical College",
    "wof:placetype":"neighbourhood"
},
  "geometry": {"coordinates":[77.217511,28.635344],"type":"Point"}
}