{
  "type": "Feature",
  "properties": {
    "iso:country":"IN",
    "ks:ks_alt_nam":"Hes\u0101hatu",
    "ks:ks_name":"Hesahatu",
    "ks:ks_pop":524,
    "ks:ks_type":"VILLAGE",
    "name:eng_x_preferred":[
        "Hesahatu"
    ],
    "name:eng_x_variant":[
        "Hes\u0101hatu"
    ],
    "wof:name":"Hesahatu",
    "wof:placetype":"locality",
    "wof:population":524
},
  "geometry": {"coordinates":[85.333775,23.126371],"type":"Point"}
}