{
  "type": "Feature",
  "properties": {
    "gn:country":"IN",
    "gn:fcode":"PPL",
    "gn:pop":0,
    "iso:country":"IN",
    "name:ben_x_preferred":[
        "\u099a\u09bf\u0996\u09be\u09b2\u09a6\u09be\u09b0\u09be"
    ],
    "name:bpy_x_preferred":[
        "\u099a\u09bf\u0996\u09be\u09b2\u09a6\u09be\u09b0\u09be"
    ],
    "name:deu_x_preferred":[
        "Chikhaldara"
    ],
    "name:eng_x_preferred":[
        "Chikhaldara"
    ],
    "name:fra_x_preferred":[
        "Chikhaldara"
    ],
    "name:guj_x_preferred":[
        "\u0a9a\u0abf\u0a96\u0ab2\u0aa6\u0abe\u0ab0\u0abe"
    ],
    "name:ind_x_preferred":[
        "Chikhaldara"
    ],
    "name:ita_x_preferred":[
        "Chikhaldara"
    ],
    "name:jpn_x_preferred":[
        "\u30c1\u30ab\u30eb\u30c0\u30e9"
    ],
    "name:kan_x_preferred":[
        "\u0c9a\u0cbf\u0c95\u0cb2\u0ccd\u0ca6\u0cbe\u0cb0\u0cbe"
    ],
    "name:kor_x_preferred":[
        "\uce58\uce7c\ub2e4\ub77c"
    ],
    "name:mar_x_preferred":[
        "\u091a\u093f\u0916\u0932\u0926\u0930\u093e"
    ],
    "name:mlg_x_preferred":[
        "Chikhaldara"
    ],
    "name:msa_x_preferred":[
        "Chikhaldara"
    ],
    "name:nan_x_preferred":[
        "Chikhaldara"
    ],
    "name:new_x_preferred":[
        "\u091a\u093f\u0916\u0932\u094d\u0926\u0930\u093e"
    ],
    "name:nld_x_preferred":[
        "Chikhaldara"
    ],
    "name:por_x_preferred":[
        "Chikhaldara"
    ],
    "name:rus_x_preferred":[
        "\u0427\u0438\u043a\u0445\u0430\u043b\u0434\u0430\u0440\u0430"
    ],
    "name:san_x_preferred":[
        "\u091a\u093f\u0915\u0932\u094d\u0927\u093e\u0930\u093e"
    ],
    "name:spa_x_preferred":[
        "Chikhaldara"
    ],
    "name:tam_x_preferred":[
        "\u0b9a\u0bc0\u0b95\u0bbe\u0bb2\u0bcd\u0b9f\u0bb0\u0bbe"
    ],
    "name:tel_x_preferred":[
        "\u0c1a\u0c3f\u0c16\u0c32\u0c4d\u0c27\u0c3e\u0c30"
    ],
    "name:unk_x_variant":[
        "Chikalda"
    ],
    "name:urd_x_preferred":[
        "\u0686\u06a9\u0644\u062f\u0631\u0627"
    ],
    "name:vie_x_preferred":[
        "Chikhaldara"
    ],
    "name:zho_x_preferred":[
        "\u5947\u5361\u5c14\u8fbe\u62c9"
    ],
    "qs:name":"Chikhaldara",
    "qs:name_adm0":"India",
    "qs:name_adm1":"Maharashtra",
    "qs:photos":11,
    "qs:photos_1k":2,
    "qs:photos_9k":1,
    "qs:photos_9r":1,
    "qs:photos_all":11,
    "qs:photos_sr":1,
    "qs:placetype":"Town",
    "qs:pop_sr":"0",
    "wd:wordcount":490,
    "wof:name":"Chikhaldara",
    "wof:placetype":"locality",
    "wof:population":0
},
  "geometry": {"coordinates":[77.31694,21.40194],"type":"Point"}
}