{
  "type": "Feature",
  "properties": {
    "iso:country":"IN",
    "ks:ks_name":"Shankar Dih",
    "ks:ks_pop":2266,
    "ks:ks_type":"VILLAGE",
    "ks:ks_uagg_main":0,
    "name:eng_x_preferred":[
        "Shankar Dih"
    ],
    "wof:name":"Shankar Dih",
    "wof:placetype":"neighbourhood",
    "wof:population":2266
},
  "geometry": {"coordinates":[85.027782,25.886178],"type":"Point"}
}