{
  "type": "Feature",
  "properties": {
    "iso:country":"IN",
    "ks:ks_name":"Kudriya",
    "ks:ks_pop":285,
    "ks:ks_type":"VILLAGE",
    "name:eng_x_preferred":[
        "Kudriya"
    ],
    "wof:name":"Kudriya",
    "wof:placetype":"locality",
    "wof:population":285
},
  "geometry": {"coordinates":[76.92925200000001,24.145728],"type":"Point"}
}