{
  "type": "Feature",
  "properties": {
    "gn:admin1_code":"36",
    "gn:admin2_code":"183.0",
    "gn:asciiname":"Balo",
    "gn:country_code":"IN",
    "gn:dem":109,
    "gn:feature_class":"P",
    "gn:feature_code":"PPL",
    "gn:name":"B\u0101lo",
    "gn:population":0,
    "gn:timezone":"Asia/Kolkata",
    "iso:country":"IN",
    "name:ceb_x_preferred":[
        "Balo"
    ],
    "name:fra_x_preferred":[
        "Balo"
    ],
    "name:swe_x_preferred":[
        "Balo"
    ],
    "wof:name":"Balo",
    "wof:placetype":"locality"
},
  "geometry": {"coordinates":[81.82733,27.22796],"type":"Point"}
}