{
  "type": "Feature",
  "properties": {
    "iso:country":"IN",
    "ks:ks_name":"Muthlaje",
    "ks:ks_pop":200,
    "ks:ks_type":"HABITATION",
    "name:eng_x_preferred":[
        "Muthlaje"
    ],
    "wof:name":"Muthlaje",
    "wof:placetype":"locality",
    "wof:population":200
},
  "geometry": {"coordinates":[75.568501,12.675689],"type":"Point"}
}