{
  "type": "Feature",
  "properties": {
    "iso:country":"IN",
    "ks:ks_name":"Amwala Manjhala",
    "ks:ks_pop":296,
    "ks:ks_type":"VILLAGE",
    "ks:ks_uagg_main":0,
    "name:eng_x_preferred":[
        "Amwala Manjhala"
    ],
    "wof:name":"Amwala Manjhala",
    "wof:placetype":"neighbourhood",
    "wof:population":296
},
  "geometry": {"coordinates":[78.087289,30.337764],"type":"Point"}
}