{
  "type": "Feature",
  "properties": {
    "iso:country":"IN",
    "ks:ks_name":"Mulagalaveddhi",
    "ks:ks_pop":24,
    "ks:ks_type":"HABITATION",
    "name:eng_x_preferred":[
        "Mulagalaveddhi"
    ],
    "wof:name":"Mulagalaveddhi",
    "wof:placetype":"locality",
    "wof:population":24
},
  "geometry": {"coordinates":[82.346711,18.04042],"type":"Point"}
}