{
  "type": "Feature",
  "properties": {
    "iso:country":"IN",
    "ks:ks_name":"Jalkar Patuli",
    "ks:ks_pop":1869,
    "ks:ks_type":"VILLAGE",
    "ks:ks_uagg_main":0,
    "name:eng_x_preferred":[
        "Jalkar Patuli"
    ],
    "wof:name":"Jalkar Patuli",
    "wof:placetype":"locality",
    "wof:population":1869
},
  "geometry": {"coordinates":[88.507896,23.3013],"type":"Point"}
}