{
  "type": "Feature",
  "properties": {
    "iso:country":"IN",
    "ks:ks_name":"Mundapadar",
    "ks:ks_pop":84,
    "ks:ks_type":"HABITATION",
    "name:eng_x_preferred":[
        "Mundapadar"
    ],
    "wof:name":"Mundapadar",
    "wof:placetype":"locality",
    "wof:population":84
},
  "geometry": {"coordinates":[84.143328,19.612015],"type":"Point"}
}