{
  "type": "Feature",
  "properties": {
    "iso:country":"IN",
    "ks:ks_name":"Chhatwara Rae Bhan",
    "ks:ks_pop":1523,
    "ks:ks_type":"VILLAGE",
    "name:eng_x_preferred":[
        "Chhatwara Rae Bhan"
    ],
    "wof:name":"Chhatwara Rae Bhan",
    "wof:placetype":"locality",
    "wof:population":1523
},
  "geometry": {"coordinates":[85.421182,25.806136],"type":"Point"}
}