{
  "type": "Feature",
  "properties": {
    "iso:country":"IN",
    "ks:ks_alt_nam":"Bar\u0101p\u0101li",
    "ks:ks_name":"Barapali",
    "ks:ks_pop":369,
    "ks:ks_type":"VILLAGE",
    "name:eng_x_preferred":[
        "Barapali"
    ],
    "name:eng_x_variant":[
        "Bar\u0101p\u0101li"
    ],
    "wof:name":"Barapali",
    "wof:placetype":"locality",
    "wof:population":369
},
  "geometry": {"coordinates":[84.66152,20.864328],"type":"Point"}
}