{
  "type": "Feature",
  "properties": {
    "iso:country":"IN",
    "ks:ks_name":"Manaveli",
    "ks:ks_pop":538,
    "ks:ks_type":"HABITATION",
    "name:eng_x_preferred":[
        "Manaveli"
    ],
    "wof:name":"Manaveli",
    "wof:placetype":"locality",
    "wof:population":538
},
  "geometry": {"coordinates":[79.708489,11.868212],"type":"Point"}
}