{
  "type": "Feature",
  "properties": {
    "iso:country":"IN",
    "ks:ks_name":"Gajrajpur",
    "ks:ks_pop":301,
    "ks:ks_type":"HABITATION",
    "name:eng_x_preferred":[
        "Gajrajpur"
    ],
    "wof:name":"Gajrajpur",
    "wof:placetype":"locality",
    "wof:population":301
},
  "geometry": {"coordinates":[86.56256999999999,24.398858],"type":"Point"}
}