{
  "type": "Feature",
  "properties": {
    "gn:admin1_code":"34.0",
    "gn:admin2_code":"221.0",
    "gn:asciiname":"Gothra",
    "gn:country_code":"IN",
    "gn:dem":49,
    "gn:feature_class":"P",
    "gn:feature_code":"PPL",
    "gn:name":"Gothra",
    "gn:population":0,
    "gn:timezone":"Asia/Kolkata",
    "iso:country":"IN",
    "wof:name":"Gothra",
    "wof:placetype":"locality"
},
  "geometry": {"coordinates":[86.01529000000002,25.77523],"type":"Point"}
}