{
  "type": "Feature",
  "properties": {
    "iso:country":"IN",
    "ks:ks_name":"Bhadkha Purohitan",
    "ks:ks_pop":682,
    "ks:ks_type":"HABITATION",
    "name:eng_x_preferred":[
        "Bhadkha Purohitan"
    ],
    "wof:name":"Bhadkha Purohitan",
    "wof:placetype":"locality",
    "wof:population":682
},
  "geometry": {"coordinates":[71.422183,26.057733],"type":"Point"}
}