{
  "type": "Feature",
  "properties": {
    "iso:country":"IN",
    "ks:ks_name":"No. 2 Chirakhowa",
    "ks:ks_pop":778,
    "ks:ks_type":"HABITATION",
    "name:eng_x_preferred":[
        "No. 2 Chirakhowa"
    ],
    "wof:name":"No. 2 Chirakhowa",
    "wof:placetype":"locality",
    "wof:population":778
},
  "geometry": {"coordinates":[93.65967000000001,26.821947],"type":"Point"}
}