{
  "type": "Feature",
  "properties": {
    "iso:country":"IN",
    "ks:ks_name":"Jhalahi",
    "ks:ks_pop":141,
    "ks:ks_type":"HABITATION",
    "ks:ks_uagg_main":0,
    "name:eng_x_preferred":[
        "Jhalahi"
    ],
    "wof:name":"Jhalahi",
    "wof:placetype":"neighbourhood",
    "wof:population":141
},
  "geometry": {"coordinates":[82.061785,27.023027],"type":"Point"}
}