{
  "type": "Feature",
  "properties": {
    "gn:admin1_code":"36.0",
    "gn:admin2_code":"149",
    "gn:asciiname":"Patti",
    "gn:country_code":"IN",
    "gn:dem":155,
    "gn:feature_class":"P",
    "gn:feature_code":"PPL",
    "gn:name":"Patti",
    "gn:population":0,
    "gn:timezone":"Asia/Kolkata",
    "iso:country":"IN",
    "name:ceb_x_preferred":[
        "Patti"
    ],
    "name:deu_x_preferred":[
        "Patti"
    ],
    "name:fra_x_preferred":[
        "Patti"
    ],
    "name:ita_x_preferred":[
        "Patti"
    ],
    "name:jpn_x_preferred":[
        "\u30d1\u30c3\u30c6\u30a3"
    ],
    "name:nds_x_preferred":[
        "Patti"
    ],
    "name:nld_x_preferred":[
        "Patti"
    ],
    "name:pol_x_preferred":[
        "Patti"
    ],
    "name:rus_x_preferred":[
        "\u041f\u0430\u0442\u0442\u0438"
    ],
    "name:spa_x_preferred":[
        "Patti"
    ],
    "name:swe_x_preferred":[
        "Patti"
    ],
    "wof:name":"Patti",
    "wof:placetype":"locality"
},
  "geometry": {"coordinates":[79.39991999999999,27.95069],"type":"Point"}
}