{
  "type": "Feature",
  "properties": {
    "gn:admin1_code":"16",
    "gn:admin2_code":"505.0",
    "gn:asciiname":"Khasara",
    "gn:country_code":"IN",
    "gn:dem":299,
    "gn:feature_class":"P",
    "gn:feature_code":"PPL",
    "gn:name":"Khas\u0101ra",
    "gn:population":0,
    "gn:timezone":"Asia/Kolkata",
    "iso:country":"IN",
    "ks:ks_alt_nam":"Khas\u0101ra",
    "ks:ks_name":"Khasara",
    "ks:ks_type":"VILLAGE",
    "name:eng_x_preferred":[
        "Khasara"
    ],
    "name:eng_x_variant":[
        "Khas\u0101ra"
    ],
    "wof:name":"Khasara",
    "wof:placetype":"locality"
},
  "geometry": {"coordinates":[79.120278,21.220969],"type":"Point"}
}