{
  "type": "Feature",
  "properties": {
    "iso:country":"IN",
    "ks:ks_name":"Neelakanta Rajapuram",
    "ks:ks_pop":67,
    "ks:ks_type":"VILLAGE",
    "ks:ks_uagg_main":0,
    "name:eng_x_preferred":[
        "Neelakanta Rajapuram"
    ],
    "wof:name":"Neelakanta Rajapuram",
    "wof:placetype":"neighbourhood",
    "wof:population":67
},
  "geometry": {"coordinates":[83.39697700000001,18.422416],"type":"Point"}
}