{
  "type": "Feature",
  "properties": {
    "iso:country":"IN",
    "ks:ks_name":"Chinasomavaram",
    "ks:ks_pop":55,
    "ks:ks_type":"HABITATION",
    "name:eng_x_preferred":[
        "Chinasomavaram"
    ],
    "wof:name":"Chinasomavaram",
    "wof:placetype":"locality",
    "wof:population":55
},
  "geometry": {"coordinates":[82.41183599999999,17.994299],"type":"Point"}
}