{
  "type": "Feature",
  "properties": {
    "iso:country":"IN",
    "ks:ks_name":"Chihimar Deeh",
    "ks:ks_pop":185,
    "ks:ks_type":"HABITATION",
    "name:eng_x_preferred":[
        "Chihimar Deeh"
    ],
    "wof:name":"Chihimar Deeh",
    "wof:placetype":"locality",
    "wof:population":185
},
  "geometry": {"coordinates":[82.948797,27.312601],"type":"Point"}
}