{
  "type": "Feature",
  "properties": {
    "gn:admin1_code":"16",
    "gn:admin2_code":"499.0",
    "gn:asciiname":"Hivarkheda Budrukh",
    "gn:country_code":"IN",
    "gn:dem":211,
    "gn:feature_class":"P",
    "gn:feature_code":"PPL",
    "gn:name":"Hivarkheda Budrukh",
    "gn:population":0,
    "gn:timezone":"Asia/Kolkata",
    "iso:country":"IN",
    "wof:name":"Hivarkheda Budrukh",
    "wof:placetype":"neighbourhood"
},
  "geometry": {"coordinates":[75.05871999999999,20.93598],"type":"Point"}
}