{
  "type": "Feature",
  "properties": {
    "iso:country":"IN",
    "ks:ks_name":"Indarkhapur",
    "ks:ks_pop":838,
    "ks:ks_type":"HABITATION",
    "name:eng_x_preferred":[
        "Indarkhapur"
    ],
    "wof:name":"Indarkhapur",
    "wof:placetype":"locality",
    "wof:population":838
},
  "geometry": {"coordinates":[82.854648,25.402684],"type":"Point"}
}