{
  "type": "Feature",
  "properties": {
    "iso:country":"IN",
    "ks:ks_name":"Rataribar",
    "ks:ks_pop":230,
    "ks:ks_type":"VILLAGE",
    "name:eng_x_preferred":[
        "Rataribar"
    ],
    "wof:name":"Rataribar",
    "wof:placetype":"locality",
    "wof:population":230
},
  "geometry": {"coordinates":[87.43778,22.474085],"type":"Point"}
}