{
  "type": "Feature",
  "properties": {
    "iso:country":"IN",
    "ks:ks_name":"Jikilatta",
    "ks:ks_pop":76,
    "ks:ks_type":"HABITATION",
    "name:eng_x_preferred":[
        "Jikilatta"
    ],
    "wof:name":"Jikilatta",
    "wof:placetype":"locality",
    "wof:population":76
},
  "geometry": {"coordinates":[84.557847,22.516831],"type":"Point"}
}