{
  "type": "Feature",
  "properties": {
    "gn:admin1_code":"28.0",
    "gn:admin2_code":"327.0",
    "gn:asciiname":"Murmidang",
    "gn:country_code":"IN",
    "gn:dem":813,
    "gn:feature_class":"P",
    "gn:feature_code":"PPL",
    "gn:name":"Murm\u012bd\u0101ng",
    "gn:population":0,
    "gn:timezone":"Asia/Kolkata",
    "iso:country":"IN",
    "ks:ks_name":"Murmidong",
    "ks:ks_pop":1763,
    "ks:ks_type":"VILLAGE",
    "name:eng_x_preferred":[
        "Murmidong"
    ],
    "name:eng_x_variant":[
        "Murmidang"
    ],
    "wof:name":"Murmidong",
    "wof:placetype":"locality",
    "wof:population":1763
},
  "geometry": {"coordinates":[88.182883,27.122466],"type":"Point"}
}