{
  "type": "Feature",
  "properties": {
    "gn:admin1_code":"35",
    "gn:admin2_code":"463.0",
    "gn:asciiname":"Khairkhunt",
    "gn:country_code":"IN",
    "gn:dem":383,
    "gn:feature_class":"P",
    "gn:feature_code":"PPL",
    "gn:name":"Khairkhunt",
    "gn:population":0,
    "gn:timezone":"Asia/Kolkata",
    "iso:country":"IN",
    "ks:ks_name":"Khairkhunt",
    "ks:ks_type":"VILLAGE",
    "name:eng_x_preferred":[
        "Khairkhunt"
    ],
    "wof:name":"Khairkhunt",
    "wof:placetype":"locality"
},
  "geometry": {"coordinates":[82.17534999999999,24.31397],"type":"Point"}
}