{
  "type": "Feature",
  "properties": {
    "iso:country":"IN",
    "ks:ks_name":"Napara",
    "ks:ks_pop":0,
    "ks:ks_type":"VILLAGE",
    "name:eng_x_preferred":[
        "Napara"
    ],
    "wof:name":"Napara",
    "wof:placetype":"locality",
    "wof:population":0
},
  "geometry": {"coordinates":[87.778499,23.89476],"type":"Point"}
}