{
  "type": "Feature",
  "properties": {
    "iso:country":"IN",
    "ks:ks_name":"Parmanikdih",
    "ks:ks_pop":948,
    "ks:ks_type":"VILLAGE",
    "ks:ks_uagg_main":0,
    "name:eng_x_preferred":[
        "Parmanikdih"
    ],
    "wof:name":"Parmanikdih",
    "wof:placetype":"neighbourhood",
    "wof:population":948
},
  "geometry": {"coordinates":[86.134806,24.352488],"type":"Point"}
}