{
  "type": "Feature",
  "properties": {
    "gn:admin1_code":"19.0",
    "gn:admin2_code":"564.0",
    "gn:asciiname":"Kiravadi",
    "gn:country_code":"IN",
    "gn:dem":567,
    "gn:feature_class":"P",
    "gn:feature_code":"PPL",
    "gn:name":"Kirav\u0101di",
    "gn:population":0,
    "gn:timezone":"Asia/Kolkata",
    "iso:country":"IN",
    "ks:ks_name":"Kirwadi",
    "ks:ks_pop":1419,
    "ks:ks_type":"VILLAGE",
    "name:eng_x_preferred":[
        "Kirwadi"
    ],
    "name:eng_x_variant":[
        "Kiravadi"
    ],
    "wof:name":"Kirwadi",
    "wof:placetype":"locality",
    "wof:population":1419
},
  "geometry": {"coordinates":[75.21377200000001,14.610447],"type":"Point"}
}