{
  "type": "Feature",
  "properties": {
    "iso:country":"IN",
    "ks:ks_alt_nam":"AHIR TOLA",
    "ks:ks_name":"Ahir Tola",
    "ks:ks_pop":125,
    "ks:ks_type":"HABITATION",
    "name:eng_x_preferred":[
        "Ahir Tola"
    ],
    "wof:name":"Ahir Tola",
    "wof:placetype":"locality",
    "wof:population":125
},
  "geometry": {"coordinates":[83.852915,25.407591],"type":"Point"}
}