{
  "type": "Feature",
  "properties": {
    "iso:country":"IN",
    "ks:ks_name":"Panguda",
    "ks:ks_pop":581,
    "ks:ks_type":"HABITATION",
    "name:eng_x_preferred":[
        "Panguda"
    ],
    "wof:name":"Panguda",
    "wof:placetype":"locality",
    "wof:population":581
},
  "geometry": {"coordinates":[74.302308,22.468356],"type":"Point"}
}