{
  "type": "Feature",
  "properties": {
    "iso:country":"IN",
    "ks:ks_name":"Kauthemala",
    "ks:ks_pop":382,
    "ks:ks_type":"HABITATION",
    "name:eng_x_preferred":[
        "Kauthemala"
    ],
    "wof:name":"Kauthemala",
    "wof:placetype":"locality",
    "wof:population":382
},
  "geometry": {"coordinates":[74.18404700000001,19.480936],"type":"Point"}
}