{
  "type": "Feature",
  "properties": {
    "iso:country":"IN",
    "ks:ks_name":"Bhunka Walla",
    "ks:ks_pop":184,
    "ks:ks_type":"VILLAGE",
    "name:eng_x_preferred":[
        "Bhunka Walla"
    ],
    "wof:name":"Bhunka Walla",
    "wof:placetype":"locality",
    "wof:population":184
},
  "geometry": {"coordinates":[79.04045000000001,30.267719],"type":"Point"}
}