{
  "type": "Feature",
  "properties": {
    "iso:country":"IN",
    "ks:ks_name":"Kalomara",
    "ks:ks_pop":134,
    "ks:ks_type":"HABITATION",
    "name:eng_x_preferred":[
        "Kalomara"
    ],
    "wof:name":"Kalomara",
    "wof:placetype":"locality",
    "wof:population":134
},
  "geometry": {"coordinates":[84.182463,22.270762],"type":"Point"}
}