{
  "type": "Feature",
  "properties": {
    "iso:country":"IN",
    "ks:ks_name":"Bori",
    "ks:ks_pop":934,
    "ks:ks_type":"VILLAGE",
    "name:eng_x_preferred":[
        "Bori"
    ],
    "wof:name":"Bori",
    "wof:placetype":"locality",
    "wof:population":934
},
  "geometry": {"coordinates":[75.264329,22.460813],"type":"Point"}
}