{
  "type": "Feature",
  "properties": {
    "gn:admin1_code":"35",
    "gn:admin2_code":"466.0",
    "gn:asciiname":"Bhogawar",
    "gn:country_code":"IN",
    "gn:dem":288,
    "gn:feature_class":"P",
    "gn:feature_code":"PPL",
    "gn:name":"Bhog\u0101w\u0101r",
    "gn:population":0,
    "gn:timezone":"Asia/Kolkata",
    "iso:country":"IN",
    "wof:name":"Bhogawar",
    "wof:placetype":"neighbourhood"
},
  "geometry": {"coordinates":[76.66253,21.86136],"type":"Point"}
}