{
  "type": "Feature",
  "properties": {
    "iso:country":"IN",
    "ks:ks_name":"Acheli",
    "ks:ks_pop":26,
    "ks:ks_type":"HABITATION",
    "name:eng_x_preferred":[
        "Acheli"
    ],
    "wof:name":"Acheli",
    "wof:placetype":"locality",
    "wof:population":26
},
  "geometry": {"coordinates":[81.081901,19.277971],"type":"Point"}
}