{
  "type": "Feature",
  "properties": {
    "iso:country":"IN",
    "ks:ks_name":"Kailwada",
    "ks:ks_pop":132,
    "ks:ks_type":"HABITATION",
    "name:eng_x_preferred":[
        "Kailwada"
    ],
    "wof:name":"Kailwada",
    "wof:placetype":"locality",
    "wof:population":132
},
  "geometry": {"coordinates":[74.39075800000001,15.463086],"type":"Point"}
}