{
  "type": "Feature",
  "properties": {
    "iso:country":"IN",
    "ks:ks_name":"Khirkhira",
    "ks:ks_pop":1975,
    "ks:ks_type":"HABITATION",
    "name:eng_x_preferred":[
        "Khirkhira"
    ],
    "wof:name":"Khirkhira",
    "wof:placetype":"locality",
    "wof:population":1975
},
  "geometry": {"coordinates":[76.750412,26.288722],"type":"Point"}
}