{
  "type": "Feature",
  "properties": {
    "iso:country":"IN",
    "ks:ks_name":"Chak Chamrul",
    "ks:ks_pop":0,
    "ks:ks_type":"VILLAGE",
    "name:eng_x_preferred":[
        "Chak Chamrul"
    ],
    "wof:name":"Chak Chamrul",
    "wof:placetype":"locality",
    "wof:population":0
},
  "geometry": {"coordinates":[87.81250199999999,22.903864],"type":"Point"}
}