{
  "type": "Feature",
  "properties": {
    "iso:country":"IN",
    "ks:ks_alt_nam":"patharevasti",
    "ks:ks_name":"Patharevasti",
    "ks:ks_pop":197,
    "ks:ks_type":"HABITATION",
    "ks:ks_uagg_main":0,
    "name:eng_x_preferred":[
        "Patharevasti"
    ],
    "wof:name":"Patharevasti",
    "wof:placetype":"neighbourhood",
    "wof:population":197
},
  "geometry": {"coordinates":[74.3595,18.2859],"type":"Point"}
}