{
  "type": "Feature",
  "properties": {
    "iso:country":"IN",
    "ks:ks_name":"Thanichiyam",
    "ks:ks_pop":670,
    "ks:ks_type":"VILLAGE",
    "name:eng_x_preferred":[
        "Thanichiyam"
    ],
    "wof:name":"Thanichiyam",
    "wof:placetype":"locality",
    "wof:population":670
},
  "geometry": {"coordinates":[78.623125,9.200587],"type":"Point"}
}