{
  "type": "Feature",
  "properties": {
    "gn:admin1_code":"3.0",
    "gn:admin2_code":"306",
    "gn:asciiname":"Jamuguri",
    "gn:country_code":"IN",
    "gn:dem":77,
    "gn:feature_class":"P",
    "gn:feature_code":"PPL",
    "gn:name":"J\u0101muguri",
    "gn:population":0,
    "gn:timezone":"Asia/Kolkata",
    "iso:country":"IN",
    "name:und_x_variant":[
        "Januguri",
        "J\u0101muguri"
    ],
    "wof:name":"Jamuguri",
    "wof:placetype":"neighbourhood"
},
  "geometry": {"coordinates":[92.93113,26.72171],"type":"Point"}
}