{
  "type": "Feature",
  "properties": {
    "iso:country":"IN",
    "ks:ks_name":"Halamakki",
    "ks:ks_pop":140,
    "ks:ks_type":"HABITATION",
    "name:eng_x_preferred":[
        "Halamakki"
    ],
    "wof:name":"Halamakki",
    "wof:placetype":"locality",
    "wof:population":140
},
  "geometry": {"coordinates":[75.648505,13.195937],"type":"Point"}
}