{
  "type": "Feature",
  "properties": {
    "gn:admin1_code":"16",
    "gn:admin2_code":"530.0",
    "gn:asciiname":"Padsali",
    "gn:country_code":"IN",
    "gn:dem":606,
    "gn:feature_class":"P",
    "gn:feature_code":"PPL",
    "gn:name":"Pads\u0101li",
    "gn:population":0,
    "gn:timezone":"Asia/Kolkata",
    "iso:country":"IN",
    "wof:name":"Padsali",
    "wof:placetype":"locality"
},
  "geometry": {"coordinates":[73.85009000000002,16.69925],"type":"Point"}
}