{
  "type": "Feature",
  "properties": {
    "gn:gn_country":"IN",
    "gn:gn_fcode":"PPL",
    "gn:gn_pop":23496,
    "gn:population":23496,
    "iso:country":"IN",
    "name:unk_x_variant":[
        "Malpe"
    ],
    "qs_pg:aaroncc":"IN",
    "qs_pg:gn_country":"IN",
    "qs_pg:gn_fcode":"PPL",
    "qs_pg:gn_pop":23496,
    "qs_pg:name":"Alape",
    "qs_pg:name_adm0":"India",
    "qs_pg:name_adm1":"Karnataka",
    "qs_pg:photos_9r":0,
    "qs_pg:photos_sr":0,
    "qs_pg:pop_sr":7,
    "qs_pg:qs_pg_placetype":"neighbourhood",
    "qs_pg:qs_pg_placetype_gp":"Suburb",
    "qs_pg:woe_adm0":23424848,
    "woe:adm0_id":23424848,
    "woe:name_adm0":"India",
    "woe:name_adm1":"Karnataka",
    "woe:placetype":"Suburb",
    "wof:name":"Alape",
    "wof:placetype":"neighbourhood",
    "wof:population":23496
},
  "geometry": {"coordinates":[74.70833,13.35284],"type":"Point"}
}