{
  "type": "Feature",
  "properties": {
    "iso:country":"IN",
    "ks:ks_alt_nam":"KHAIRI PURUWA",
    "ks:ks_name":"Khairi Puruwa",
    "ks:ks_pop":78,
    "ks:ks_type":"HABITATION",
    "ks:ks_uagg_main":0,
    "name:eng_x_preferred":[
        "Khairi Puruwa"
    ],
    "wof:name":"Khairi Puruwa",
    "wof:placetype":"neighbourhood",
    "wof:population":78
},
  "geometry": {"coordinates":[81.317803,27.990453],"type":"Point"}
}