{
  "type": "Feature",
  "properties": {
    "iso:country":"IN",
    "ks:ks_alt_nam":"CHOUGULE WASTI 2",
    "ks:ks_name":"Chougule Wasti 2",
    "ks:ks_pop":79,
    "ks:ks_type":"HABITATION",
    "name:eng_x_preferred":[
        "Chougule Wasti 2"
    ],
    "wof:name":"Chougule Wasti 2",
    "wof:placetype":"locality",
    "wof:population":79
},
  "geometry": {"coordinates":[75.114942,17.112198],"type":"Point"}
}