{
  "type": "Feature",
  "properties": {
    "iso:country":"IN",
    "ks:ks_name":"Seetharamapattinam",
    "ks:ks_pop":244,
    "ks:ks_type":"HABITATION",
    "name:eng_x_preferred":[
        "Seetharamapattinam"
    ],
    "wof:name":"Seetharamapattinam",
    "wof:placetype":"locality",
    "wof:population":244
},
  "geometry": {"coordinates":[79.228618,10.070978],"type":"Point"}
}