{
  "type": "Feature",
  "properties": {
    "gn:admin1_code":"12.0",
    "gn:admin2_code":"3.0",
    "gn:asciiname":"Machakka",
    "gn:country_code":"IN",
    "gn:dem":3201,
    "gn:feature_class":"P",
    "gn:feature_code":"PPL",
    "gn:name":"Machakka",
    "gn:population":0,
    "gn:timezone":"Asia/Kolkata",
    "iso:country":"IN",
    "wof:name":"Machakka",
    "wof:placetype":"locality"
},
  "geometry": {"coordinates":[77.29493000000002,34.21693],"type":"Point"}
}