{
  "type": "Feature",
  "properties": {
    "gn:admin1_code":"11",
    "gn:admin2_code":"27.0",
    "gn:asciiname":"Kherendi",
    "gn:country_code":"IN",
    "gn:dem":1748,
    "gn:feature_class":"P",
    "gn:feature_code":"PPL",
    "gn:name":"Kherendi",
    "gn:population":0,
    "gn:timezone":"Asia/Kolkata",
    "iso:country":"IN",
    "wof:name":"Kherendi",
    "wof:placetype":"locality"
},
  "geometry": {"coordinates":[76.98855,31.47973],"type":"Point"}
}