{
  "type": "Feature",
  "properties": {
    "iso:country":"IN",
    "ks:ks_name":"Abdaguri No.2",
    "ks:ks_pop":611,
    "ks:ks_type":"VILLAGE",
    "ks:ks_uagg_main":0,
    "name:eng_x_preferred":[
        "Abdaguri No.2"
    ],
    "wof:name":"Abdaguri No.2",
    "wof:placetype":"neighbourhood",
    "wof:population":611
},
  "geometry": {"coordinates":[90.849868,26.588371],"type":"Point"}
}