{
  "type": "Feature",
  "properties": {
    "gn:admin1_code":"19.0",
    "gn:admin2_code":"569.0",
    "gn:asciiname":"Benkanaberu",
    "gn:country_code":"IN",
    "gn:dem":57,
    "gn:feature_class":"P",
    "gn:feature_code":"PPL",
    "gn:name":"B\u0113nkanaberu",
    "gn:population":0,
    "gn:timezone":"Asia/Kolkata",
    "iso:country":"IN",
    "ks:ks_name":"Bankanaberu",
    "ks:ks_pop":167,
    "ks:ks_type":"HABITATION",
    "name:eng_x_preferred":[
        "Bankanaberu"
    ],
    "name:eng_x_variant":[
        "Benkanaberu"
    ],
    "wof:name":"Bankanaberu",
    "wof:placetype":"locality",
    "wof:population":167
},
  "geometry": {"coordinates":[74.747592,13.819379],"type":"Point"}
}