{
  "type": "Feature",
  "properties": {
    "iso:country":"IN",
    "ks:ks_name":"Kajiwadi",
    "ks:ks_pop":48,
    "ks:ks_type":"HABITATION",
    "name:eng_x_preferred":[
        "Kajiwadi"
    ],
    "wof:name":"Kajiwadi",
    "wof:placetype":"locality",
    "wof:population":48
},
  "geometry": {"coordinates":[73.59818799999999,16.585341],"type":"Point"}
}