{
  "type": "Feature",
  "properties": {
    "gn:admin1_code":"39.0",
    "gn:admin2_code":"59.0",
    "gn:asciiname":"Syalsi Upli",
    "gn:country_code":"IN",
    "gn:dem":1475,
    "gn:feature_class":"P",
    "gn:feature_code":"PPL",
    "gn:name":"Sy\u0101lsi Upli",
    "gn:population":0,
    "gn:timezone":"Asia/Kolkata",
    "iso:country":"IN",
    "wof:name":"Syalsi Upli",
    "wof:placetype":"locality"
},
  "geometry": {"coordinates":[78.21951,30.47598],"type":"Point"}
}