{
  "type": "Feature",
  "properties": {
    "iso:country":"IN",
    "ks:ks_name":"Hadlugadde",
    "ks:ks_pop":21,
    "ks:ks_type":"HABITATION",
    "name:eng_x_preferred":[
        "Hadlugadde"
    ],
    "wof:name":"Hadlugadde",
    "wof:placetype":"locality",
    "wof:population":21
},
  "geometry": {"coordinates":[75.423339,13.394975],"type":"Point"}
}