{
  "type": "Feature",
  "properties": {
    "gn:admin1_code":"19.0",
    "gn:admin2_code":"570.0",
    "gn:asciiname":"Haralahalli",
    "gn:country_code":"IN",
    "gn:dem":821,
    "gn:feature_class":"P",
    "gn:feature_code":"PPL",
    "gn:name":"Haralahalli",
    "gn:population":0,
    "gn:timezone":"Asia/Kolkata",
    "iso:country":"IN",
    "wof:name":"Haralahalli",
    "wof:placetype":"locality"
},
  "geometry": {"coordinates":[76.03194999999999,13.87523],"type":"Point"}
}