{
  "type": "Feature",
  "properties": {
    "iso:country":"IN",
    "ks:ks_alt_nam":"HARIYANTALA",
    "ks:ks_name":"Hariyantala",
    "ks:ks_pop":250,
    "ks:ks_type":"HABITATION",
    "name:eng_x_preferred":[
        "Hariyantala"
    ],
    "wof:name":"Hariyantala",
    "wof:placetype":"locality",
    "wof:population":250
},
  "geometry": {"coordinates":[84.851726,24.197959],"type":"Point"}
}