{
  "type": "Feature",
  "properties": {
    "iso:country":"IN",
    "ks:ks_name":"Kunman",
    "ks:ks_pop":0,
    "ks:ks_type":"VILLAGE",
    "name:eng_x_preferred":[
        "Kunman"
    ],
    "wof:name":"Kunman",
    "wof:placetype":"locality",
    "wof:population":0
},
  "geometry": {"coordinates":[87.651309,24.964231],"type":"Point"}
}