{
  "type": "Feature",
  "properties": {
    "gn:admin1_code":"36",
    "gn:admin2_code":"149.0",
    "gn:asciiname":"Mathla",
    "gn:country_code":"IN",
    "gn:dem":151,
    "gn:feature_class":"P",
    "gn:feature_code":"PPL",
    "gn:name":"Mathla",
    "gn:population":0,
    "gn:timezone":"Asia/Kolkata",
    "iso:country":"IN",
    "wof:name":"Mathla",
    "wof:placetype":"locality"
},
  "geometry": {"coordinates":[79.29123,27.72171],"type":"Point"}
}