{
  "type": "Feature",
  "properties": {
    "iso:country":"IN",
    "ks:ks_name":"Alalthi Kadavu",
    "ks:ks_pop":450,
    "ks:ks_type":"HABITATION",
    "name:eng_x_preferred":[
        "Alalthi Kadavu"
    ],
    "wof:name":"Alalthi Kadavu",
    "wof:placetype":"locality",
    "wof:population":450
},
  "geometry": {"coordinates":[75.41001199999999,12.454061],"type":"Point"}
}