{
  "type": "Feature",
  "properties": {
    "gn:admin1_code":"19.0",
    "gn:admin2_code":"583.0",
    "gn:asciiname":"Bhimapur",
    "gn:country_code":"IN",
    "gn:dem":899,
    "gn:feature_class":"P",
    "gn:feature_code":"PPL",
    "gn:name":"Bhim\u0101pur",
    "gn:population":0,
    "gn:timezone":"Asia/Kolkata",
    "iso:country":"IN",
    "name:ceb_x_preferred":[
        "Bhimapur"
    ],
    "name:fra_x_preferred":[
        "Bhimapur"
    ],
    "name:msa_x_preferred":[
        "Bhimapur"
    ],
    "name:nep_x_preferred":[
        "\u092d\u093f\u092e\u094d\u092e\u093e\u092a\u0941\u0930"
    ],
    "name:pol_x_preferred":[
        "Bhimapur"
    ],
    "wof:name":"Bhimapur",
    "wof:placetype":"locality"
},
  "geometry": {"coordinates":[77.90741,13.1438],"type":"Point"}
}