{
  "type": "Feature",
  "properties": {
    "iso:country":"IN",
    "ks:ks_name":"Mannathithura",
    "ks:ks_pop":837,
    "ks:ks_type":"HABITATION",
    "name:eng_x_preferred":[
        "Mannathithura"
    ],
    "wof:name":"Mannathithura",
    "wof:placetype":"locality",
    "wof:population":837
},
  "geometry": {"coordinates":[76.076103,11.228976],"type":"Point"}
}