{
  "type": "Feature",
  "properties": {
    "iso:country":"IN",
    "ks:ks_name":"Ratanpura",
    "ks:ks_pop":710,
    "ks:ks_type":"HABITATION",
    "name:eng_x_preferred":[
        "Ratanpura"
    ],
    "wof:name":"Ratanpura",
    "wof:placetype":"locality",
    "wof:population":710
},
  "geometry": {"coordinates":[71.772722,25.203253],"type":"Point"}
}