{
  "type": "Feature",
  "properties": {
    "iso:country":"IN",
    "ks:ks_name":"Baraua Nurabad",
    "ks:ks_pop":2743,
    "ks:ks_type":"VILLAGE",
    "name:eng_x_preferred":[
        "Baraua Nurabad"
    ],
    "wof:name":"Baraua Nurabad",
    "wof:placetype":"neighbourhood",
    "wof:population":2743
},
  "geometry": {"coordinates":[78.13106500000001,26.314207],"type":"Point"}
}