{
  "type": "Feature",
  "properties": {
    "iso:country":"IN",
    "ks:ks_name":"Kevthiya",
    "ks:ks_pop":86,
    "ks:ks_type":"HABITATION",
    "name:eng_x_preferred":[
        "Kevthiya"
    ],
    "wof:name":"Kevthiya",
    "wof:placetype":"locality",
    "wof:population":86
},
  "geometry": {"coordinates":[82.223625,26.53903],"type":"Point"}
}