{
  "type": "Feature",
  "properties": {
    "iso:country":"IN",
    "ks:ks_name":"Ekrampur",
    "ks:ks_pop":879,
    "ks:ks_type":"VILLAGE",
    "ks:ks_uagg_main":0,
    "name:eng_x_preferred":[
        "Ekrampur"
    ],
    "wof:name":"Ekrampur",
    "wof:placetype":"neighbourhood",
    "wof:population":879
},
  "geometry": {"coordinates":[79.774261,26.507055],"type":"Point"}
}