{
  "type": "Feature",
  "properties": {
    "iso:country":"IN",
    "ks:ks_name":"Tadewasti",
    "ks:ks_pop":109,
    "ks:ks_type":"HABITATION",
    "name:eng_x_preferred":[
        "Tadewasti"
    ],
    "wof:name":"Tadewasti",
    "wof:placetype":"locality",
    "wof:population":109
},
  "geometry": {"coordinates":[75.720224,18.113101],"type":"Point"}
}