{
  "type": "Feature",
  "properties": {
    "iso:country":"IN",
    "ks:ks_name":"Kalahbhanga",
    "ks:ks_pop":4024,
    "ks:ks_type":"VILLAGE",
    "ks:ks_uagg_main":0,
    "name:eng_x_preferred":[
        "Kalahbhanga"
    ],
    "wof:name":"Kalahbhanga",
    "wof:placetype":"neighbourhood",
    "wof:population":4024
},
  "geometry": {"coordinates":[90.95097699999999,26.498681],"type":"Point"}
}