{
  "type": "Feature",
  "properties": {
    "iso:country":"IN",
    "ks:ks_name":"Karkashi",
    "ks:ks_pop":919,
    "ks:ks_type":"HABITATION",
    "name:eng_x_preferred":[
        "Karkashi"
    ],
    "wof:name":"Karkashi",
    "wof:placetype":"locality",
    "wof:population":919
},
  "geometry": {"coordinates":[90.740284,26.069097],"type":"Point"}
}