{
  "type": "Feature",
  "properties": {
    "iso:country":"IN",
    "ks:ks_name":"Ris",
    "ks:ks_pop":639,
    "ks:ks_type":"VILLAGE",
    "ks:ks_uagg_main":0,
    "name:eng_x_preferred":[
        "Ris"
    ],
    "wof:name":"Ris",
    "wof:placetype":"neighbourhood",
    "wof:population":639
},
  "geometry": {"coordinates":[86.28326199999999,25.27738],"type":"Point"}
}