{
  "type": "Feature",
  "properties": {
    "gn:admin1_code":"35.0",
    "gn:admin2_code":"457.0",
    "gn:asciiname":"Saori",
    "gn:country_code":"IN",
    "gn:dem":284,
    "gn:feature_class":"P",
    "gn:feature_code":"PPL",
    "gn:name":"Saor\u012b",
    "gn:population":0,
    "gn:timezone":"Asia/Kolkata",
    "iso:country":"IN",
    "name:jpn_x_preferred":[
        "\u3055\u304a\u308a"
    ],
    "name:kor_x_preferred":[
        "\uc0ac\uc624\ub9ac"
    ],
    "wof:name":"Saori",
    "wof:placetype":"neighbourhood"
},
  "geometry": {"coordinates":[80.00817000000001,21.56069],"type":"Point"}
}