{
  "type": "Feature",
  "properties": {
    "iso:country":"IN",
    "ks:ks_name":"Miyar Dendabettu",
    "ks:ks_pop":350,
    "ks:ks_type":"HABITATION",
    "name:eng_x_preferred":[
        "Miyar Dendabettu"
    ],
    "wof:name":"Miyar Dendabettu",
    "wof:placetype":"locality",
    "wof:population":350
},
  "geometry": {"coordinates":[75.03686999999999,13.201199],"type":"Point"}
}