{
  "type": "Feature",
  "properties": {
    "iso:country":"IN",
    "ks:ks_name":"Lalguwadi",
    "ks:ks_pop":1848,
    "ks:ks_type":"VILLAGE",
    "name:eng_x_preferred":[
        "Lalguwadi"
    ],
    "wof:name":"Lalguwadi",
    "wof:placetype":"locality",
    "wof:population":1848
},
  "geometry": {"coordinates":[74.942162,23.21068],"type":"Point"}
}