{
  "type": "Feature",
  "properties": {
    "gn:admin1_code":"10.0",
    "gn:admin2_code":"71.0",
    "gn:asciiname":"Shekhupura",
    "gn:country_code":"IN",
    "gn:dem":292,
    "gn:feature_class":"P",
    "gn:feature_code":"PPL",
    "gn:name":"Shekh\u016bpura",
    "gn:population":0,
    "gn:timezone":"Asia/Kolkata",
    "iso:country":"IN",
    "ks:ks_name":"Shekhupura",
    "ks:ks_type":"VILLAGE",
    "name:eng_x_preferred":[
        "Shekhupura"
    ],
    "wof:name":"Shekhupura",
    "wof:placetype":"locality"
},
  "geometry": {"coordinates":[77.232589,30.285],"type":"Point"}
}