{
  "type": "Feature",
  "properties": {
    "iso:country":"IN",
    "ks:ks_name":"Anthur",
    "ks:ks_pop":249,
    "ks:ks_type":"HABITATION",
    "name:eng_x_preferred":[
        "Anthur"
    ],
    "wof:name":"Anthur",
    "wof:placetype":"locality",
    "wof:population":249
},
  "geometry": {"coordinates":[74.865312,13.646793],"type":"Point"}
}