{
  "type": "Feature",
  "properties": {
    "gn:admin1_code":"12",
    "gn:admin2_code":"12.0",
    "gn:asciiname":"Agahanzpur",
    "gn:country_code":"IN",
    "gn:dem":1595,
    "gn:feature_class":"P",
    "gn:feature_code":"PPL",
    "gn:name":"Agah\u0101nzpur",
    "gn:population":0,
    "gn:timezone":"Asia/Kolkata",
    "iso:country":"IN",
    "wof:name":"Agahanzpur",
    "wof:placetype":"locality"
},
  "geometry": {"coordinates":[75.00904,33.92377],"type":"Point"}
}