{
  "type": "Feature",
  "properties": {
    "iso:country":"IN",
    "ks:ks_name":"Keelaeruthigoundanpatti",
    "ks:ks_pop":498,
    "ks:ks_type":"HABITATION",
    "name:eng_x_preferred":[
        "Keelaeruthigoundanpatti"
    ],
    "wof:name":"Keelaeruthigoundanpatti",
    "wof:placetype":"locality",
    "wof:population":498
},
  "geometry": {"coordinates":[78.42082499999999,10.579073],"type":"Point"}
}