{
  "type": "Feature",
  "properties": {
    "iso:country":"IN",
    "ks:ks_name":"Bhadwal",
    "ks:ks_pop":809,
    "ks:ks_type":"HABITATION",
    "name:eng_x_preferred":[
        "Bhadwal"
    ],
    "wof:name":"Bhadwal",
    "wof:placetype":"locality",
    "wof:population":809
},
  "geometry": {"coordinates":[83.09123200000001,27.335649],"type":"Point"}
}