{
  "type": "Feature",
  "properties": {
    "gn:admin1_code":"35",
    "gn:admin2_code":"423.0",
    "gn:asciiname":"Surwaya",
    "gn:country_code":"IN",
    "gn:dem":409,
    "gn:feature_class":"P",
    "gn:feature_code":"PPL",
    "gn:name":"Surw\u0101y\u0101",
    "gn:population":0,
    "gn:timezone":"Asia/Kolkata",
    "iso:country":"IN",
    "ks:ks_alt_nam":"Surw\u0101y\u0101",
    "ks:ks_name":"Surwaya",
    "ks:ks_pop":1096,
    "ks:ks_type":"VILLAGE",
    "name:eng_x_preferred":[
        "Surwaya"
    ],
    "name:eng_x_variant":[
        "Surw\u0101y\u0101"
    ],
    "wof:name":"Surwaya",
    "wof:placetype":"locality",
    "wof:population":1096
},
  "geometry": {"coordinates":[77.83151599999999,25.415534],"type":"Point"}
}