{
  "type": "Feature",
  "properties": {
    "gn:admin1_code":"35",
    "gn:admin2_code":"423.0",
    "gn:asciiname":"Surwaya",
    "gn:country_code":"IN",
    "gn:dem":409,
    "gn:feature_class":"P",
    "gn:feature_code":"PPL",
    "gn:name":"Surw\u0101y\u0101",
    "gn:population":0,
    "gn:timezone":"Asia/Kolkata",
    "iso:country":"IN",
    "wof:name":"Surwaya",
    "wof:placetype":"locality"
},
  "geometry": {"coordinates":[77.83213000000001,25.41806],"type":"Point"}
}