{
  "type": "Feature",
  "properties": {
    "iso:country":"IN",
    "ks:ks_name":"Kolwara",
    "ks:ks_pop":735,
    "ks:ks_type":"VILLAGE",
    "name:eng_x_preferred":[
        "Kolwara"
    ],
    "wof:name":"Kolwara",
    "wof:placetype":"locality",
    "wof:population":735
},
  "geometry": {"coordinates":[73.28046000000001,24.961982],"type":"Point"}
}