{
  "type": "Feature",
  "properties": {
    "iso:country":"IN",
    "ks:ks_name":"Busiputtu",
    "ks:ks_pop":56,
    "ks:ks_type":"HABITATION",
    "name:eng_x_preferred":[
        "Busiputtu"
    ],
    "wof:name":"Busiputtu",
    "wof:placetype":"locality",
    "wof:population":56
},
  "geometry": {"coordinates":[82.665678,18.283168],"type":"Point"}
}