{
  "type": "Feature",
  "properties": {
    "iso:country":"IN",
    "ks:ks_alt_nam":"Kerkarwadi aronda road",
    "ks:ks_name":"Kerkarwadi Aronda Road",
    "ks:ks_pop":102,
    "ks:ks_type":"HABITATION",
    "name:eng_x_preferred":[
        "Kerkarwadi Aronda Road"
    ],
    "wof:name":"Kerkarwadi Aronda Road",
    "wof:placetype":"locality",
    "wof:population":102
},
  "geometry": {"coordinates":[73.73863,15.779714],"type":"Point"}
}