{
  "type": "Feature",
  "properties": {
    "iso:country":"IN",
    "ks:ks_name":"Purwari Lagunaha",
    "ks:ks_pop":1397,
    "ks:ks_type":"VILLAGE",
    "ks:ks_uagg_main":0,
    "name:eng_x_preferred":[
        "Purwari Lagunaha"
    ],
    "wof:name":"Purwari Lagunaha",
    "wof:placetype":"neighbourhood",
    "wof:population":1397
},
  "geometry": {"coordinates":[84.25185999999999,27.015447],"type":"Point"}
}