{
  "type": "Feature",
  "properties": {
    "iso:country":"IN",
    "ks:ks_name":"Tingirijhola",
    "ks:ks_pop":55,
    "ks:ks_type":"VILLAGE",
    "name:eng_x_preferred":[
        "Tingirijhola"
    ],
    "wof:name":"Tingirijhola",
    "wof:placetype":"locality",
    "wof:population":55
},
  "geometry": {"coordinates":[83.552098,19.134923],"type":"Point"}
}