{
  "type": "Feature",
  "properties": {
    "gn:admin1_code":"11",
    "gn:admin2_code":"23.0",
    "gn:asciiname":"Chala",
    "gn:country_code":"IN",
    "gn:dem":1244,
    "gn:feature_class":"P",
    "gn:feature_code":"PPL",
    "gn:name":"Chala",
    "gn:population":0,
    "gn:timezone":"Asia/Kolkata",
    "iso:country":"IN",
    "name:aym_x_preferred":[
        "Ch'alla"
    ],
    "name:ces_x_preferred":[
        "Chala"
    ],
    "name:deu_x_preferred":[
        "Chala"
    ],
    "name:lit_x_preferred":[
        "\u010cala"
    ],
    "name:que_x_preferred":[
        "Chala"
    ],
    "name:ukr_x_preferred":[
        "\u0427\u0430\u043b\u0430"
    ],
    "wof:name":"Chala",
    "wof:placetype":"locality"
},
  "geometry": {"coordinates":[76.14471,32.77939],"type":"Point"}
}