{
  "type": "Feature",
  "properties": {
    "iso:country":"IN",
    "ks:ks_name":"Dhinakarankulam",
    "ks:ks_pop":452,
    "ks:ks_type":"HABITATION",
    "name:eng_x_preferred":[
        "Dhinakarankulam"
    ],
    "wof:name":"Dhinakarankulam",
    "wof:placetype":"locality",
    "wof:population":452
},
  "geometry": {"coordinates":[77.83005300000001,8.320052],"type":"Point"}
}