{
  "type": "Feature",
  "properties": {
    "iso:country":"IN",
    "ks:ks_alt_nam":"MPV 44",
    "ks:ks_name":"Mpv 44",
    "ks:ks_pop":361,
    "ks:ks_type":"HABITATION",
    "name:eng_x_preferred":[
        "Mpv 44"
    ],
    "wof:name":"Mpv 44",
    "wof:placetype":"locality",
    "wof:population":361
},
  "geometry": {"coordinates":[81.507716,18.074026],"type":"Point"}
}