{
  "type": "Feature",
  "properties": {
    "iso:country":"IN",
    "ks:ks_name":"Mahamadpur",
    "ks:ks_pop":161,
    "ks:ks_type":"VILLAGE",
    "name:eng_x_preferred":[
        "Mahamadpur"
    ],
    "wof:name":"Mahamadpur",
    "wof:placetype":"locality",
    "wof:population":161
},
  "geometry": {"coordinates":[86.092561,26.071856],"type":"Point"}
}