{
  "type": "Feature",
  "properties": {
    "gn:admin1_code":"11.0",
    "gn:admin2_code":"27.0",
    "gn:asciiname":"Kachhni",
    "gn:country_code":"IN",
    "gn:dem":1376,
    "gn:feature_class":"P",
    "gn:feature_code":"PPL",
    "gn:name":"Kachhni",
    "gn:population":0,
    "gn:timezone":"Asia/Kolkata",
    "iso:country":"IN",
    "wof:name":"Kachhni",
    "wof:placetype":"locality"
},
  "geometry": {"coordinates":[77.10075999999999,31.70559],"type":"Point"}
}