{
  "type": "Feature",
  "properties": {
    "gn:admin1_code":"19.0",
    "gn:admin2_code":"571.0",
    "gn:asciiname":"Kotipura",
    "gn:country_code":"IN",
    "gn:dem":768,
    "gn:feature_class":"P",
    "gn:feature_code":"PPL",
    "gn:name":"Kotipura",
    "gn:population":0,
    "gn:timezone":"Asia/Kolkata",
    "iso:country":"IN",
    "ks:ks_name":"Kothipura",
    "ks:ks_pop":669,
    "ks:ks_type":"VILLAGE",
    "name:eng_x_preferred":[
        "Kothipura"
    ],
    "name:eng_x_variant":[
        "Kotipura"
    ],
    "wof:name":"Kothipura",
    "wof:placetype":"locality",
    "wof:population":669
},
  "geometry": {"coordinates":[77.02438600000001,13.006187],"type":"Point"}
}