{
  "type": "Feature",
  "properties": {
    "iso:country":"IN",
    "ks:ks_name":"Bindaban.",
    "ks:ks_pop":445,
    "ks:ks_type":"HABITATION",
    "name:eng_x_preferred":[
        "Bindaban."
    ],
    "wof:name":"Bindaban.",
    "wof:placetype":"locality",
    "wof:population":445
},
  "geometry": {"coordinates":[86.802683,25.680645],"type":"Point"}
}