{
  "type": "Feature",
  "properties": {
    "iso:country":"IN",
    "ks:ks_name":"Sennimalaipalayam",
    "ks:ks_pop":151,
    "ks:ks_type":"HABITATION",
    "name:eng_x_preferred":[
        "Sennimalaipalayam"
    ],
    "wof:name":"Sennimalaipalayam",
    "wof:placetype":"locality",
    "wof:population":151
},
  "geometry": {"coordinates":[77.492813,10.81151],"type":"Point"}
}