{
  "type": "Feature",
  "properties": {
    "gn:admin1_code":"23.0",
    "gn:admin2_code":"35.0",
    "gn:asciiname":"Naushehra Nalbandah",
    "gn:country_code":"IN",
    "gn:dem":293,
    "gn:feature_class":"P",
    "gn:feature_code":"PPL",
    "gn:name":"Naushehra N\u0101lbandah",
    "gn:population":0,
    "gn:timezone":"Asia/Kolkata",
    "iso:country":"IN",
    "wof:name":"Naushehra Nalbandah",
    "wof:placetype":"locality"
},
  "geometry": {"coordinates":[75.6177,32.20489],"type":"Point"}
}