{
  "type": "Feature",
  "properties": {
    "gn:admin1_code":"35",
    "gn:admin2_code":"430.0",
    "gn:asciiname":"Hariya",
    "gn:country_code":"IN",
    "gn:dem":338,
    "gn:feature_class":"P",
    "gn:feature_code":"PPL",
    "gn:name":"Hariya",
    "gn:population":0,
    "gn:timezone":"Asia/Kolkata",
    "iso:country":"IN",
    "ks:ks_name":"Hadiya",
    "ks:ks_pop":1330,
    "ks:ks_type":"HABITATION",
    "name:eng_x_preferred":[
        "Hadiya"
    ],
    "name:eng_x_variant":[
        "Hariya"
    ],
    "wof:name":"Hadiya",
    "wof:placetype":"locality",
    "wof:population":1330
},
  "geometry": {"coordinates":[81.691261,24.742791],"type":"Point"}
}