{
  "type": "Feature",
  "properties": {
    "gn:admin1_code":"23.0",
    "gn:admin2_code":"49.0",
    "gn:asciiname":"Bhagwanpura",
    "gn:country_code":"IN",
    "gn:dem":228,
    "gn:feature_class":"P",
    "gn:feature_code":"PPL",
    "gn:name":"Bhagw\u0101npura",
    "gn:population":0,
    "gn:timezone":"Asia/Kolkata",
    "iso:country":"IN",
    "wof:name":"Bhagwanpura",
    "wof:placetype":"locality"
},
  "geometry": {"coordinates":[74.88136999999998,31.9739],"type":"Point"}
}