{
  "type": "Feature",
  "properties": {
    "gn:admin1_code":"35.0",
    "gn:admin2_code":"455.0",
    "gn:asciiname":"Moyakhedi",
    "gn:country_code":"IN",
    "gn:dem":459,
    "gn:feature_class":"P",
    "gn:feature_code":"PPL",
    "gn:name":"Moy\u0101khedi",
    "gn:population":0,
    "gn:timezone":"Asia/Kolkata",
    "iso:country":"IN",
    "ks:ks_name":"Mohkhedi",
    "ks:ks_pop":150,
    "ks:ks_type":"VILLAGE",
    "name:eng_x_preferred":[
        "Mohkhedi"
    ],
    "name:eng_x_variant":[
        "Moyakhedi"
    ],
    "wof:name":"Mohkhedi",
    "wof:placetype":"locality",
    "wof:population":150
},
  "geometry": {"coordinates":[78.458652,21.536583],"type":"Point"}
}