{
  "type": "Feature",
  "properties": {
    "gn:admin1_code":"34.0",
    "gn:admin2_code":"216.0",
    "gn:asciiname":"Parsa Sadhan",
    "gn:country_code":"IN",
    "gn:dem":62,
    "gn:feature_class":"P",
    "gn:feature_code":"PPL",
    "gn:name":"P\u0101rsa S\u0101dhan",
    "gn:population":0,
    "gn:timezone":"Asia/Kolkata",
    "iso:country":"IN",
    "wof:name":"Parsa Sadhan",
    "wof:placetype":"locality"
},
  "geometry": {"coordinates":[84.98180000000001,26.25614],"type":"Point"}
}