{
  "type": "Feature",
  "properties": {
    "iso:country":"IN",
    "ks:ks_name":"Umarsandi",
    "ks:ks_pop":580,
    "ks:ks_type":"HABITATION",
    "name:eng_x_preferred":[
        "Umarsandi"
    ],
    "wof:name":"Umarsandi",
    "wof:placetype":"locality",
    "wof:population":580
},
  "geometry": {"coordinates":[79.58857399999999,27.879155],"type":"Point"}
}