{
  "type": "Feature",
  "properties": {
    "iso:country":"IN",
    "ks:ks_name":"Sardoli",
    "ks:ks_pop":78,
    "ks:ks_type":"VILLAGE",
    "name:eng_x_preferred":[
        "Sardoli"
    ],
    "wof:name":"Sardoli",
    "wof:placetype":"locality",
    "wof:population":78
},
  "geometry": {"coordinates":[83.858895,20.347147],"type":"Point"}
}