{
  "type": "Feature",
  "properties": {
    "gn:admin1_code":"19.0",
    "gn:admin2_code":"570.0",
    "gn:asciiname":"Karli",
    "gn:country_code":"IN",
    "gn:dem":852,
    "gn:feature_class":"P",
    "gn:feature_code":"PPL",
    "gn:name":"K\u0101rli",
    "gn:population":0,
    "gn:timezone":"Asia/Kolkata",
    "iso:country":"IN",
    "name:deu_x_preferred":[
        "Karli"
    ],
    "name:isl_x_preferred":[
        "Karli"
    ],
    "name:pol_x_preferred":[
        "Karli"
    ],
    "name:slv_x_preferred":[
        "Karli"
    ],
    "wof:name":"Karli",
    "wof:placetype":"locality"
},
  "geometry": {"coordinates":[75.28385,13.24879],"type":"Point"}
}