{
  "type": "Feature",
  "properties": {
    "iso:country":"IN",
    "ks:ks_name":"Kajal Basti",
    "ks:ks_pop":960,
    "ks:ks_type":"HABITATION",
    "name:eng_x_preferred":[
        "Kajal Basti"
    ],
    "wof:name":"Kajal Basti",
    "wof:placetype":"locality",
    "wof:population":960
},
  "geometry": {"coordinates":[87.87752399999999,26.448591],"type":"Point"}
}