{
  "type": "Feature",
  "properties": {
    "iso:country":"IN",
    "ks:ks_name":"Bharudpura",
    "ks:ks_pop":425,
    "ks:ks_type":"HABITATION",
    "name:eng_x_preferred":[
        "Bharudpura"
    ],
    "wof:name":"Bharudpura",
    "wof:placetype":"locality",
    "wof:population":425
},
  "geometry": {"coordinates":[75.474743,22.371383],"type":"Point"}
}