{
  "type": "Feature",
  "properties": {
    "iso:country":"IN",
    "ks:ks_alt_nam":"Jamuniya kala",
    "ks:ks_name":"Jamuniya Kala",
    "ks:ks_pop":189,
    "ks:ks_type":"HABITATION",
    "name:eng_x_preferred":[
        "Jamuniya Kala"
    ],
    "wof:name":"Jamuniya Kala",
    "wof:placetype":"locality",
    "wof:population":189
},
  "geometry": {"coordinates":[80.55302,24.402425],"type":"Point"}
}