{
  "type": "Feature",
  "properties": {
    "gn:admin1_code":"36.0",
    "gn:admin2_code":"193.0",
    "gn:asciiname":"Mubarakpur",
    "gn:country_code":"IN",
    "gn:dem":70,
    "gn:feature_class":"P",
    "gn:feature_code":"PPL",
    "gn:name":"Mub\u0101rakpur",
    "gn:population":0,
    "gn:timezone":"Asia/Kolkata",
    "iso:country":"IN",
    "name:ara_x_preferred":[
        "\u0645\u0628\u0627\u0631\u0643 \u0628\u0648\u0631"
    ],
    "name:ara_x_variant":[
        "\u0645\u0628\u0627\u0631\u0643\u0641\u0648\u0631"
    ],
    "name:ben_bn_x_preferred":[
        "\u09ae\u09c1\u09ac\u09be\u09b0\u0995\u09aa\u09c1\u09b0"
    ],
    "name:ben_in_x_preferred":[
        "\u09ae\u09c1\u09ac\u09be\u09b0\u0995\u09aa\u09c1\u09b0"
    ],
    "name:bih_x_preferred":[
        "\u092e\u0941\u092c\u093e\u0930\u0915\u092a\u0941\u0930"
    ],
    "name:bpy_x_preferred":[
        "\u09ae\u09c1\u09ac\u09be\u09b0\u0995\u09aa\u09c1\u09b0"
    ],
    "name:ceb_x_preferred":[
        "Mub\u0101rakpur"
    ],
    "name:fas_x_preferred":[
        "\u0645\u0628\u0627\u0631\u06a9\u200c\u067e\u0648\u0631"
    ],
    "name:guj_x_preferred":[
        "\u0aae\u0ac1\u0aac\u0abe\u0ab0\u0a95\u0aaa\u0ac1\u0ab0"
    ],
    "name:hin_x_preferred":[
        "\u092e\u0941\u092c\u093e\u0930\u0915\u092a\u0941\u0930"
    ],
    "name:ita_x_preferred":[
        "Mubarakpur"
    ],
    "name:jpn_x_preferred":[
        "\u30e0\u30d0\u30fc\u30e9\u30af\u30d7\u30eb"
    ],
    "name:kan_x_preferred":[
        "\u0cae\u0cc1\u0cac\u0cbe\u0cb0\u0c95\u0ccd"
    ],
    "name:mal_x_preferred":[
        "\u0d2e\u0d41\u0d2c\u0d3e\u0d31\u0d15\u0d4d\u0d2a\u0d42\u0d7c"
    ],
    "name:mar_x_preferred":[
        "\u092e\u0941\u092c\u093e\u0930\u0915\u092a\u0942\u0930"
    ],
    "name:mlg_x_preferred":[
        "Mubarakpur"
    ],
    "name:msa_x_preferred":[
        "Mubarakpur"
    ],
    "name:new_x_preferred":[
        "\u092e\u0941\u092c\u093e\u0930\u0915\u092a\u0941\u0930"
    ],
    "name:nld_x_preferred":[
        "Mubarakpur"
    ],
    "name:pan_x_preferred":[
        "\u0a2e\u0a41\u0a2c\u0a3e\u0a30\u0a15\u0a2a\u0a41\u0a30"
    ],
    "name:pol_x_preferred":[
        "Mubarakpur"
    ],
    "name:swe_x_preferred":[
        "Mubarakpur"
    ],
    "name:tam_x_preferred":[
        "\u0bae\u0bc1\u0baa\u0bbe\u0bb0\u0b95\u0bcd\u0baa\u0bc2\u0bb0\u0bcd"
    ],
    "name:tel_x_preferred":[
        "\u0c2e\u0c41\u0c2c\u0c3e\u0c30\u0c15\u0c4d"
    ],
    "name:urd_x_preferred":[
        "\u0645\u0628\u0627\u0631\u06a9 \u067e\u0648\u0631"
    ],
    "name:urd_x_variant":[
        "\u0645\u0628\u0627\u0631\u06a9\u067e\u0648\u0631"
    ],
    "name:vie_x_preferred":[
        "Mubarakpur"
    ],
    "name:zho_x_preferred":[
        "\u7a46\u5df4\u62c9\u514b\u666e\u5c14"
    ],
    "wof:name":"Mubarakpur",
    "wof:placetype":"locality"
},
  "geometry": {"coordinates":[83.85034,26.14466],"type":"Point"}
}