{
  "type": "Feature",
  "properties": {
    "iso:country":"IN",
    "ks:ks_name":"Gangwara Tola Kharpati",
    "ks:ks_pop":1527,
    "ks:ks_type":"HABITATION",
    "name:eng_x_preferred":[
        "Gangwara Tola Kharpati"
    ],
    "wof:name":"Gangwara Tola Kharpati",
    "wof:placetype":"locality",
    "wof:population":1527
},
  "geometry": {"coordinates":[85.54409699999999,26.396836],"type":"Point"}
}