{
  "type": "Feature",
  "properties": {
    "gn:admin1_code":"25.0",
    "gn:admin2_code":"628",
    "gn:asciiname":"Idindakarai",
    "gn:country_code":"IN",
    "gn:dem":12,
    "gn:feature_class":"P",
    "gn:feature_code":"PPL",
    "gn:name":"Idindakarai",
    "gn:population":0,
    "gn:timezone":"Asia/Kolkata",
    "iso:country":"IN",
    "name:und_x_variant":[
        "Idingikari",
        "Idindakarai"
    ],
    "wof:name":"Idindakarai",
    "wof:placetype":"locality"
},
  "geometry": {"coordinates":[77.74311999999998,8.17717],"type":"Point"}
}