{
  "type": "Feature",
  "properties": {
    "iso:country":"IN",
    "ks:ks_name":"Narsaigudem",
    "ks:ks_pop":318,
    "ks:ks_type":"HABITATION",
    "name:eng_x_preferred":[
        "Narsaigudem"
    ],
    "wof:name":"Narsaigudem",
    "wof:placetype":"locality",
    "wof:population":318
},
  "geometry": {"coordinates":[80.494097,18.184787],"type":"Point"}
}