{
  "type": "Feature",
  "properties": {
    "gn:admin1_code":"2.0",
    "gn:admin2_code":"542.0",
    "gn:asciiname":"Ahobalacharyulupeta",
    "gn:country_code":"IN",
    "gn:dem":42,
    "gn:feature_class":"P",
    "gn:feature_code":"PPL",
    "gn:name":"Ahobal\u0101ch\u0101ryulupeta",
    "gn:population":0,
    "gn:timezone":"Asia/Kolkata",
    "iso:country":"IN",
    "wof:name":"Ahobalacharyulupeta",
    "wof:placetype":"locality"
},
  "geometry": {"coordinates":[83.85704,18.48459],"type":"Point"}
}