{
  "type": "Feature",
  "properties": {
    "iso:country":"IN",
    "ks:ks_alt_nam":"MHARAJPUR",
    "ks:ks_name":"Mharajpur",
    "ks:ks_pop":250,
    "ks:ks_type":"HABITATION",
    "name:eng_x_preferred":[
        "Mharajpur"
    ],
    "wof:name":"Mharajpur",
    "wof:placetype":"locality",
    "wof:population":250
},
  "geometry": {"coordinates":[79.169076,26.480076],"type":"Point"}
}