{
  "type": "Feature",
  "properties": {
    "iso:country":"IN",
    "ks:ks_name":"Chandiagaon",
    "ks:ks_pop":2435,
    "ks:ks_type":"HABITATION",
    "name:eng_x_preferred":[
        "Chandiagaon"
    ],
    "wof:name":"Chandiagaon",
    "wof:placetype":"locality",
    "wof:population":2435
},
  "geometry": {"coordinates":[90.358733,26.455095],"type":"Point"}
}