{
  "type": "Feature",
  "properties": {
    "gn:admin1_code":"23.0",
    "gn:admin2_code":"43.0",
    "gn:asciiname":"Jiwa Bhedi",
    "gn:country_code":"IN",
    "gn:dem":201,
    "gn:feature_class":"P",
    "gn:feature_code":"PPL",
    "gn:name":"J\u012bwa Bhedi",
    "gn:population":0,
    "gn:timezone":"Asia/Kolkata",
    "iso:country":"IN",
    "ks:ks_alt_nam":"J\u012bwa Bhedi",
    "ks:ks_name":"Jiwa Bhedi",
    "ks:ks_pop":231,
    "ks:ks_type":"VILLAGE",
    "name:eng_x_preferred":[
        "Jiwa Bhedi"
    ],
    "name:eng_x_variant":[
        "J\u012bwa Bhedi"
    ],
    "wof:name":"Jiwa Bhedi",
    "wof:placetype":"locality",
    "wof:population":231
},
  "geometry": {"coordinates":[74.705358,31.017914],"type":"Point"}
}