{
  "type": "Feature",
  "properties": {
    "iso:country":"IN",
    "ks:ks_alt_nam":"South yadav toli",
    "ks:ks_name":"South Yadav Toli",
    "ks:ks_pop":108,
    "ks:ks_type":"HABITATION",
    "name:eng_x_preferred":[
        "South Yadav Toli"
    ],
    "wof:name":"South Yadav Toli",
    "wof:placetype":"locality",
    "wof:population":108
},
  "geometry": {"coordinates":[85.307017,24.833513],"type":"Point"}
}