{
  "type": "Feature",
  "properties": {
    "gn:admin1_code":"36",
    "gn:admin2_code":"152.0",
    "gn:asciiname":"Nanakpur",
    "gn:country_code":"IN",
    "gn:dem":153,
    "gn:feature_class":"P",
    "gn:feature_code":"PPL",
    "gn:name":"N\u0101nakpur",
    "gn:population":0,
    "gn:timezone":"Asia/Kolkata",
    "iso:country":"IN",
    "ks:ks_alt_nam":"N\u0101nakpur",
    "ks:ks_name":"Nanakpur",
    "ks:ks_pop":428,
    "ks:ks_type":"VILLAGE",
    "ks:ks_uagg_main":0,
    "name:eng_x_preferred":[
        "Nanakpur"
    ],
    "name:eng_x_variant":[
        "N\u0101nakpur"
    ],
    "wof:name":"Nanakpur",
    "wof:placetype":"neighbourhood",
    "wof:population":428
},
  "geometry": {"coordinates":[79.817785,27.787321],"type":"Point"}
}