{
  "type": "Feature",
  "properties": {
    "iso:country":"IN",
    "ks:ks_name":"Hidi Badi",
    "ks:ks_pop":993,
    "ks:ks_type":"VILLAGE",
    "name:eng_x_preferred":[
        "Hidi Badi"
    ],
    "wof:name":"Hidi Badi",
    "wof:placetype":"locality",
    "wof:population":993
},
  "geometry": {"coordinates":[74.71551700000001,22.689209],"type":"Point"}
}