{
  "type": "Feature",
  "properties": {
    "iso:country":"IN",
    "ks:ks_name":"Sonar Chak",
    "ks:ks_pop":151,
    "ks:ks_type":"VILLAGE",
    "name:eng_x_preferred":[
        "Sonar Chak"
    ],
    "wof:name":"Sonar Chak",
    "wof:placetype":"locality",
    "wof:population":151
},
  "geometry": {"coordinates":[87.76181,25.031428],"type":"Point"}
}