{
  "type": "Feature",
  "properties": {
    "iso:country":"IN",
    "ks:ks_name":"Kusumaput",
    "ks:ks_pop":59,
    "ks:ks_type":"VILLAGE",
    "name:eng_x_preferred":[
        "Kusumaput"
    ],
    "wof:name":"Kusumaput",
    "wof:placetype":"locality",
    "wof:population":59
},
  "geometry": {"coordinates":[82.389551,18.325607],"type":"Point"}
}