{
  "type": "Feature",
  "properties": {
    "gn:admin1_code":"16",
    "gn:admin2_code":"511.0",
    "gn:asciiname":"Totamba",
    "gn:country_code":"IN",
    "gn:dem":472,
    "gn:feature_class":"P",
    "gn:feature_code":"PPL",
    "gn:name":"Totamba",
    "gn:population":0,
    "gn:timezone":"Asia/Kolkata",
    "iso:country":"IN",
    "wof:name":"Totamba",
    "wof:placetype":"locality"
},
  "geometry": {"coordinates":[78.00251,19.3145],"type":"Point"}
}