{
  "type": "Feature",
  "properties": {
    "iso:country":"IN",
    "ks:ks_name":"Talasasimaha",
    "ks:ks_pop":47,
    "ks:ks_type":"VILLAGE",
    "name:eng_x_preferred":[
        "Talasasimaha"
    ],
    "wof:name":"Talasasimaha",
    "wof:placetype":"locality",
    "wof:population":47
},
  "geometry": {"coordinates":[84.141696,20.174486],"type":"Point"}
}