{
  "type": "Feature",
  "properties": {
    "gn:admin1_code":"34.0",
    "gn:admin2_code":"220.0",
    "gn:asciiname":"Bahlolpur",
    "gn:country_code":"IN",
    "gn:dem":56,
    "gn:feature_class":"P",
    "gn:feature_code":"PPL",
    "gn:name":"Bahlolpur",
    "gn:population":0,
    "gn:timezone":"Asia/Kolkata",
    "iso:country":"IN",
    "ks:ks_name":"Bahlolpur",
    "ks:ks_pop":970,
    "ks:ks_type":"VILLAGE",
    "name:eng_x_preferred":[
        "Bahlolpur"
    ],
    "wof:name":"Bahlolpur",
    "wof:placetype":"locality",
    "wof:population":970
},
  "geometry": {"coordinates":[85.305352,25.8529],"type":"Point"}
}