{
  "type": "Feature",
  "properties": {
    "gn:admin1_code":"36.0",
    "gn:admin2_code":"161",
    "gn:asciiname":"Nagla Rampura",
    "gn:country_code":"IN",
    "gn:dem":149,
    "gn:feature_class":"P",
    "gn:feature_code":"PPL",
    "gn:name":"Nagla R\u0101mpura",
    "gn:population":0,
    "gn:timezone":"Asia/Kolkata",
    "iso:country":"IN",
    "name:und_x_variant":[
        "Nagla R\u0101mpura",
        "Rampura"
    ],
    "wof:name":"Nagla Rampura",
    "wof:placetype":"neighbourhood"
},
  "geometry": {"coordinates":[79.23723,26.83025],"type":"Point"}
}