{
  "type": "Feature",
  "properties": {
    "iso:country":"IN",
    "ks:ks_name":"Molding",
    "ks:ks_pop":85,
    "ks:ks_type":"HABITATION",
    "name:eng_x_preferred":[
        "Molding"
    ],
    "wof:name":"Molding",
    "wof:placetype":"locality",
    "wof:population":85
},
  "geometry": {"coordinates":[93.61429699999999,26.071111],"type":"Point"}
}