{
  "type": "Feature",
  "properties": {
    "iso:country":"IN",
    "ks:ks_name":"3 B",
    "ks:ks_pop":556,
    "ks:ks_type":"HABITATION",
    "name:eng_x_preferred":[
        "3 B"
    ],
    "wof:name":"3 B",
    "wof:placetype":"locality",
    "wof:population":556
},
  "geometry": {"coordinates":[73.844847,29.941997],"type":"Point"}
}