{
  "type": "Feature",
  "properties": {
    "gn:admin1_code":"21.0",
    "gn:admin2_code":"398.0",
    "gn:asciiname":"Vasapaka",
    "gn:country_code":"IN",
    "gn:dem":831,
    "gn:feature_class":"P",
    "gn:feature_code":"PPL",
    "gn:name":"Vasap\u0101ka",
    "gn:population":0,
    "gn:timezone":"Asia/Kolkata",
    "iso:country":"IN",
    "wof:name":"Vasapaka",
    "wof:placetype":"locality"
},
  "geometry": {"coordinates":[83.01357,18.79335],"type":"Point"}
}