{
  "type": "Feature",
  "properties": {
    "gn:admin1_code":"34.0",
    "gn:admin2_code":"203.0",
    "gn:asciiname":"Siswa Tola Jai Rai",
    "gn:country_code":"IN",
    "gn:dem":83,
    "gn:feature_class":"P",
    "gn:feature_code":"PPL",
    "gn:name":"Siswa Tola Jai R\u0101i",
    "gn:population":0,
    "gn:timezone":"Asia/Kolkata",
    "iso:country":"IN",
    "ks:ks_name":"Ssiswa Tola Jai Ray",
    "ks:ks_pop":302,
    "ks:ks_type":"VILLAGE",
    "name:eng_x_preferred":[
        "Ssiswa Tola Jai Ray"
    ],
    "name:eng_x_variant":[
        "Siswa Tola Jai Rai"
    ],
    "wof:name":"Ssiswa Tola Jai Ray",
    "wof:placetype":"locality",
    "wof:population":302
},
  "geometry": {"coordinates":[84.299356,26.969439],"type":"Point"}
}