{
  "type": "Feature",
  "properties": {
    "gn:admin1_code":"34.0",
    "gn:admin2_code":"203.0",
    "gn:asciiname":"Siswa Tola Jai Rai",
    "gn:country_code":"IN",
    "gn:dem":83,
    "gn:feature_class":"P",
    "gn:feature_code":"PPL",
    "gn:name":"Siswa Tola Jai R\u0101i",
    "gn:population":0,
    "gn:timezone":"Asia/Kolkata",
    "iso:country":"IN",
    "wof:name":"Siswa Tola Jai Rai",
    "wof:placetype":"locality"
},
  "geometry": {"coordinates":[84.30011999999998,26.9766],"type":"Point"}
}