{
  "type": "Feature",
  "properties": {
    "iso:country":"IN",
    "ks:ks_name":"Budhimal",
    "ks:ks_pop":20,
    "ks:ks_type":"VILLAGE",
    "name:eng_x_preferred":[
        "Budhimal"
    ],
    "wof:name":"Budhimal",
    "wof:placetype":"locality",
    "wof:population":20
},
  "geometry": {"coordinates":[83.788248,20.590885],"type":"Point"}
}