{
  "type": "Feature",
  "properties": {
    "gn:admin1_code":"36.0",
    "gn:admin2_code":"171.0",
    "gn:asciiname":"Magarhai",
    "gn:country_code":"IN",
    "gn:dem":118,
    "gn:feature_class":"P",
    "gn:feature_code":"PPL",
    "gn:name":"Magarh\u0101i",
    "gn:population":0,
    "gn:timezone":"Asia/Kolkata",
    "iso:country":"IN",
    "ks:ks_name":"Magarhai",
    "ks:ks_pop":567,
    "ks:ks_type":"VILLAGE",
    "ks:ks_uagg_main":0,
    "name:eng_x_preferred":[
        "Magarhai"
    ],
    "wof:name":"Magarhai",
    "wof:placetype":"neighbourhood",
    "wof:population":567
},
  "geometry": {"coordinates":[81.127363,25.278781],"type":"Point"}
}