{
  "type": "Feature",
  "properties": {
    "iso:country":"IN",
    "ks:ks_name":"Vallamvalappu",
    "ks:ks_pop":450,
    "ks:ks_type":"HABITATION",
    "name:eng_x_preferred":[
        "Vallamvalappu"
    ],
    "wof:name":"Vallamvalappu",
    "wof:placetype":"locality",
    "wof:population":450
},
  "geometry": {"coordinates":[76.470275,10.55064],"type":"Point"}
}