{
  "type": "Feature",
  "properties": {
    "gn:admin1_code":"39.0",
    "gn:admin2_code":"64.0",
    "gn:asciiname":"Dugoli",
    "gn:country_code":"IN",
    "gn:dem":792,
    "gn:feature_class":"P",
    "gn:feature_code":"PPL",
    "gn:name":"Dugoli",
    "gn:population":0,
    "gn:timezone":"Asia/Kolkata",
    "iso:country":"IN",
    "ks:ks_name":"Dugoli",
    "ks:ks_pop":194,
    "ks:ks_type":"VILLAGE",
    "name:eng_x_preferred":[
        "Dugoli"
    ],
    "wof:name":"Dugoli",
    "wof:placetype":"locality",
    "wof:population":194
},
  "geometry": {"coordinates":[79.24704699999999,29.679898],"type":"Point"}
}