{
  "type": "Feature",
  "properties": {
    "gn:admin1_code":"24.0",
    "gn:admin2_code":"122.0",
    "gn:asciiname":"Bara Bariya",
    "gn:country_code":"IN",
    "gn:dem":505,
    "gn:feature_class":"P",
    "gn:feature_code":"PPL",
    "gn:name":"Bara B\u0101riya",
    "gn:population":0,
    "gn:timezone":"Asia/Kolkata",
    "iso:country":"IN",
    "wof:name":"Bara Bariya",
    "wof:placetype":"locality"
},
  "geometry": {"coordinates":[74.24994000000002,25.34757],"type":"Point"}
}