{
  "type": "Feature",
  "properties": {
    "iso:country":"IN",
    "ks:ks_name":"Kanmane",
    "ks:ks_pop":9,
    "ks:ks_type":"HABITATION",
    "name:eng_x_preferred":[
        "Kanmane"
    ],
    "wof:name":"Kanmane",
    "wof:placetype":"locality",
    "wof:population":9
},
  "geometry": {"coordinates":[74.684465,14.33488],"type":"Point"}
}