{
  "type": "Feature",
  "properties": {
    "gn:admin1_code":"19.0",
    "gn:admin2_code":"581.0",
    "gn:asciiname":"Hijavanahalli",
    "gn:country_code":"IN",
    "gn:dem":897,
    "gn:feature_class":"P",
    "gn:feature_code":"PPL",
    "gn:name":"Hijavanahalli",
    "gn:population":0,
    "gn:timezone":"Asia/Kolkata",
    "iso:country":"IN",
    "wof:name":"Hijavanahalli",
    "wof:placetype":"locality"
},
  "geometry": {"coordinates":[78.03747,13.03817],"type":"Point"}
}