{
  "type": "Feature",
  "properties": {
    "gn:admin1_code":"19",
    "gn:admin2_code":"580.0",
    "gn:asciiname":"Nagarahal",
    "gn:country_code":"IN",
    "gn:dem":377,
    "gn:feature_class":"P",
    "gn:feature_code":"PPL",
    "gn:name":"N\u0101garah\u0101l",
    "gn:population":0,
    "gn:timezone":"Asia/Kolkata",
    "iso:country":"IN",
    "wof:name":"Nagarahal",
    "wof:placetype":"locality"
},
  "geometry": {"coordinates":[76.70000999999998,16.45435],"type":"Point"}
}