{
  "type": "Feature",
  "properties": {
    "gn:admin1_code":"21",
    "gn:admin2_code":"394.0",
    "gn:asciiname":"Baloda",
    "gn:country_code":"IN",
    "gn:dem":318,
    "gn:feature_class":"P",
    "gn:feature_code":"PPL",
    "gn:name":"Baloda",
    "gn:population":0,
    "gn:timezone":"Asia/Kolkata",
    "iso:country":"IN",
    "name:ben_x_preferred":[
        "\u09ac\u09be\u09b2\u09cb\u09a6\u09be"
    ],
    "name:bpy_x_preferred":[
        "\u09ac\u09be\u09b2\u09cb\u09a6\u09be"
    ],
    "name:ceb_x_preferred":[
        "Baloda"
    ],
    "name:ita_x_preferred":[
        "Baloda"
    ],
    "name:msa_x_preferred":[
        "Baloda"
    ],
    "name:new_x_preferred":[
        "\u092c\u0932\u094b\u0921\u093e"
    ],
    "name:nld_x_preferred":[
        "Baloda"
    ],
    "name:por_x_preferred":[
        "Baloda"
    ],
    "name:spa_x_preferred":[
        "Baloda"
    ],
    "name:swe_x_preferred":[
        "Baloda"
    ],
    "name:tgl_x_preferred":[
        "Baloda"
    ],
    "name:urd_x_preferred":[
        "\u0628\u0644\u0648\u062f\u0627"
    ],
    "name:vie_x_preferred":[
        "Baloda"
    ],
    "name:zho_x_preferred":[
        "\u5df4\u6d1b\u8fbe"
    ],
    "wof:name":"Baloda",
    "wof:placetype":"locality"
},
  "geometry": {"coordinates":[82.56255,20.91526],"type":"Point"}
}