{
  "type": "Feature",
  "properties": {
    "gn:admin1_code":"36.0",
    "gn:admin2_code":"179.0",
    "gn:asciiname":"Zilla",
    "gn:country_code":"IN",
    "gn:dem":98,
    "gn:feature_class":"P",
    "gn:feature_code":"PPL",
    "gn:name":"Zilla",
    "gn:population":0,
    "gn:timezone":"Asia/Kolkata",
    "iso:country":"IN",
    "name:deu_x_preferred":[
        "Zilla"
    ],
    "name:fra_x_preferred":[
        "Zilla"
    ],
    "name:ita_x_preferred":[
        "Zilla"
    ],
    "name:nds_x_preferred":[
        "Zilla"
    ],
    "name:nld_x_preferred":[
        "Zilla"
    ],
    "name:pol_x_preferred":[
        "Zilla"
    ],
    "name:por_x_preferred":[
        "Zilla"
    ],
    "name:spa_x_preferred":[
        "Zilla"
    ],
    "name:vie_x_preferred":[
        "Zilla"
    ],
    "wof:name":"Zilla",
    "wof:placetype":"locality"
},
  "geometry": {"coordinates":[81.95563,26.07473],"type":"Point"}
}