{
  "type": "Feature",
  "properties": {
    "iso:country":"IN",
    "ks:ks_name":"Kalloli",
    "ks:ks_pop":1524,
    "ks:ks_type":"VILLAGE",
    "ks:ks_uagg_main":0,
    "name:eng_x_preferred":[
        "Kalloli"
    ],
    "wof:name":"Kalloli",
    "wof:placetype":"neighbourhood",
    "wof:population":1524
},
  "geometry": {"coordinates":[86.68593300000001,23.439369],"type":"Point"}
}