{
  "type": "Feature",
  "properties": {
    "gn:admin1_code":"39",
    "gn:admin2_code":"61.0",
    "gn:asciiname":"Bangargaon",
    "gn:country_code":"IN",
    "gn:dem":1543,
    "gn:feature_class":"P",
    "gn:feature_code":"PPL",
    "gn:name":"Bangargaon",
    "gn:population":0,
    "gn:timezone":"Asia/Kolkata",
    "iso:country":"IN",
    "wof:name":"Bangargaon",
    "wof:placetype":"locality"
},
  "geometry": {"coordinates":[78.77004000000002,30.10769],"type":"Point"}
}