{
  "type": "Feature",
  "properties": {
    "iso:country":"IN",
    "ks:ks_name":"Dhian Singhpura",
    "ks:ks_pop":0,
    "ks:ks_type":"VILLAGE",
    "name:eng_x_preferred":[
        "Dhian Singhpura"
    ],
    "wof:name":"Dhian Singhpura",
    "wof:placetype":"locality",
    "wof:population":0
},
  "geometry": {"coordinates":[74.725618,31.932794],"type":"Point"}
}