{
  "type": "Feature",
  "properties": {
    "gn:admin1_code":"36.0",
    "gn:admin2_code":"167",
    "gn:asciiname":"Jataua",
    "gn:country_code":"IN",
    "gn:dem":385,
    "gn:feature_class":"P",
    "gn:feature_code":"PPL",
    "gn:name":"Jata\u016ba",
    "gn:population":0,
    "gn:timezone":"Asia/Kolkata",
    "iso:country":"IN",
    "ks:ks_name":"Jatauya",
    "ks:ks_pop":495,
    "ks:ks_type":"HABITATION",
    "name:eng_x_preferred":[
        "Jatauya"
    ],
    "name:eng_x_variant":[
        "Jataua"
    ],
    "wof:name":"Jatauya",
    "wof:placetype":"locality",
    "wof:population":495
},
  "geometry": {"coordinates":[78.886021,24.543145],"type":"Point"}
}