{
  "type": "Feature",
  "properties": {
    "iso:country":"IN",
    "ks:ks_name":"Semiliatalo",
    "ks:ks_pop":466,
    "ks:ks_type":"HABITATION",
    "name:eng_x_preferred":[
        "Semiliatalo"
    ],
    "wof:name":"Semiliatalo",
    "wof:placetype":"locality",
    "wof:population":466
},
  "geometry": {"coordinates":[82.218047,18.804499],"type":"Point"}
}