{
  "type": "Feature",
  "properties": {
    "iso:country":"IN",
    "ks:ks_name":"Nayapurwa",
    "ks:ks_pop":567,
    "ks:ks_type":"HABITATION",
    "name:eng_x_preferred":[
        "Nayapurwa"
    ],
    "wof:name":"Nayapurwa",
    "wof:placetype":"locality",
    "wof:population":567
},
  "geometry": {"coordinates":[81.307507,27.73065],"type":"Point"}
}