{
  "type": "Feature",
  "properties": {
    "iso:country":"IN",
    "ks:ks_alt_nam":"Mannicheni jn",
    "ks:ks_name":"Mannicheni Jn",
    "ks:ks_pop":687,
    "ks:ks_type":"HABITATION",
    "name:eng_x_preferred":[
        "Mannicheni Jn"
    ],
    "wof:name":"Mannicheni Jn",
    "wof:placetype":"locality",
    "wof:population":687
},
  "geometry": {"coordinates":[76.333495,11.436921],"type":"Point"}
}