{
  "type": "Feature",
  "properties": {
    "gn:admin1_code":"19.0",
    "gn:admin2_code":"559.0",
    "gn:asciiname":"Chintamandoddi",
    "gn:country_code":"IN",
    "gn:dem":352,
    "gn:feature_class":"P",
    "gn:feature_code":"PPL",
    "gn:name":"Chintamandoddi",
    "gn:population":0,
    "gn:timezone":"Asia/Kolkata",
    "iso:country":"IN",
    "wof:name":"Chintamandoddi",
    "wof:placetype":"locality"
},
  "geometry": {"coordinates":[77.00994,15.82847],"type":"Point"}
}