{
  "type": "Feature",
  "properties": {
    "iso:country":"IN",
    "ks:ks_alt_nam":"Ingn\u0101l",
    "ks:ks_name":"Ingnal",
    "ks:ks_type":"VILLAGE",
    "name:eng_x_preferred":[
        "Ingnal"
    ],
    "name:eng_x_variant":[
        "Ingn\u0101l"
    ],
    "wof:name":"Ingnal",
    "wof:placetype":"locality"
},
  "geometry": {"coordinates":[76.708963,16.764221],"type":"Point"}
}