{
  "type": "Feature",
  "properties": {
    "gn:admin1_code":"28.0",
    "gn:admin2_code":"334.0",
    "gn:asciiname":"Mallikpur",
    "gn:country_code":"IN",
    "gn:dem":49,
    "gn:feature_class":"P",
    "gn:feature_code":"PPL",
    "gn:name":"Mallikpur",
    "gn:population":0,
    "gn:timezone":"Asia/Kolkata",
    "iso:country":"IN",
    "ks:ks_name":"Mallikpur",
    "ks:ks_pop":646,
    "ks:ks_type":"VILLAGE",
    "ks:ks_uagg_main":0,
    "name:eng_x_preferred":[
        "Mallikpur"
    ],
    "wof:name":"Mallikpur",
    "wof:placetype":"neighbourhood",
    "wof:population":646
},
  "geometry": {"coordinates":[87.77728500000001,24.209564],"type":"Point"}
}