{
  "type": "Feature",
  "properties": {
    "iso:country":"IN",
    "ks:ks_name":"Bakot",
    "ks:ks_pop":274,
    "ks:ks_type":"HABITATION",
    "name:eng_x_preferred":[
        "Bakot"
    ],
    "wof:name":"Bakot",
    "wof:placetype":"locality",
    "wof:population":274
},
  "geometry": {"coordinates":[80.61933999999999,25.056234],"type":"Point"}
}