{
  "type": "Feature",
  "properties": {
    "iso:country":"IN",
    "ks:ks_name":"Mahdauli",
    "ks:ks_pop":771,
    "ks:ks_type":"VILLAGE",
    "name:eng_x_preferred":[
        "Mahdauli"
    ],
    "wof:name":"Mahdauli",
    "wof:placetype":"locality",
    "wof:population":771
},
  "geometry": {"coordinates":[81.65200400000001,23.860808],"type":"Point"}
}