{
  "type": "Feature",
  "properties": {
    "iso:country":"IN",
    "qs:name":"Bhilarewadi",
    "qs:name_adm0":"India",
    "qs:name_adm1":"Maharashtra",
    "qs:photos":43,
    "qs:photos_1k":9,
    "qs:photos_9k":1,
    "qs:photos_9r":2,
    "qs:photos_all":43,
    "qs:photos_sr":2,
    "qs:placetype":"Town",
    "qs:pop_sr":"0",
    "wof:name":"Bhilarewadi",
    "wof:placetype":"locality"
},
  "geometry": {"coordinates":[73.856987,18.416244],"type":"Point"}
}