{
  "type": "Feature",
  "properties": {
    "iso:country":"IN",
    "ks:ks_name":"Bhilarewadi",
    "ks:ks_pop":1635,
    "ks:ks_type":"VILLAGE",
    "name:eng_x_preferred":[
        "Bhilarewadi"
    ],
    "qs:name":"Bhilarewadi",
    "qs:name_adm0":"India",
    "qs:name_adm1":"Maharashtra",
    "qs:photos":43,
    "qs:photos_1k":9,
    "qs:photos_9k":1,
    "qs:photos_9r":2,
    "qs:photos_all":43,
    "qs:photos_sr":2,
    "qs:placetype":"Town",
    "qs:pop_sr":"0",
    "wof:name":"Bhilarewadi",
    "wof:placetype":"locality",
    "wof:population":1635
},
  "geometry": {"coordinates":[73.86595,18.409941],"type":"Point"}
}