{
  "type": "Feature",
  "properties": {
    "iso:country":"IN",
    "ks:ks_name":"Srirampur",
    "ks:ks_pop":158,
    "ks:ks_type":"VILLAGE",
    "name:eng_x_preferred":[
        "Srirampur"
    ],
    "wof:name":"Srirampur",
    "wof:placetype":"locality",
    "wof:population":158
},
  "geometry": {"coordinates":[87.496444,22.379],"type":"Point"}
}