{
  "type": "Feature",
  "properties": {
    "iso:country":"IN",
    "ks:ks_name":"Toulyon",
    "ks:ks_pop":88,
    "ks:ks_type":"VILLAGE",
    "name:eng_x_preferred":[
        "Toulyon"
    ],
    "wof:name":"Toulyon",
    "wof:placetype":"locality",
    "wof:population":88
},
  "geometry": {"coordinates":[79.169996,29.997746],"type":"Point"}
}