{
  "type": "Feature",
  "properties": {
    "gn:country":"IN",
    "gn:fcode":"PPL",
    "gn:pop":17796,
    "iso:country":"IN",
    "name:bpy_x_preferred":[
        "\u09b8\u09bf\u0982\u09b9\u09b0\u09be\u09af\u09bc\u0995\u09c1\u09a8\u09cd\u09a1\u09be"
    ],
    "name:ceb_x_preferred":[
        "Singar\u0101yakonda"
    ],
    "name:eng_x_preferred":[
        "Singarayakonda"
    ],
    "name:fra_x_preferred":[
        "Singarayakonda"
    ],
    "name:ita_x_preferred":[
        "Singarayakonda"
    ],
    "name:msa_x_preferred":[
        "Singarayakonda"
    ],
    "name:nan_x_preferred":[
        "Singarayakonda"
    ],
    "name:new_x_preferred":[
        "\u0938\u093f\u0902\u0917\u0930\u093e\u092f\u0915\u094b\u0923\u094d\u0921 \u092e\u0923\u094d\u0921\u0932"
    ],
    "name:nld_x_preferred":[
        "Singarayakonda"
    ],
    "name:por_x_preferred":[
        "Singarayakonda"
    ],
    "name:swe_x_preferred":[
        "Singar\u0101yakonda"
    ],
    "name:tel_x_preferred":[
        "\u0c38\u0c3f\u0c02\u0c17\u0c30\u0c3e\u0c2f\u0c15\u0c4a\u0c02\u0c21"
    ],
    "name:unk_x_variant":[
        "Singaraya Konda Pagoda"
    ],
    "name:urd_x_preferred":[
        "\u0633\u0646\u06af\u0627\u0631\u0627\u06cc\u0627\u06a9\u0648\u0646\u0688\u06c1"
    ],
    "name:vie_x_preferred":[
        "Singarayakonda"
    ],
    "name:zho_x_preferred":[
        "\u8f9b\u683c\u62c9\u8036\u5b54\u8fbe"
    ],
    "qs:name":"Singarayakonda",
    "qs:name_adm0":"India",
    "qs:name_adm1":"Andhra Pradesh",
    "qs:photos_9k":1,
    "qs:photos_9r":1,
    "qs:photos_all":4,
    "qs:photos_sr":0,
    "qs:placetype":"Town",
    "qs:pop_sr":"6",
    "wd:wordcount":235,
    "wof:name":"Singarayakonda",
    "wof:placetype":"locality",
    "wof:population":17796
},
  "geometry": {"coordinates":[80.02802,15.23094],"type":"Point"}
}