{
  "type": "Feature",
  "properties": {
    "iso:country":"IN",
    "ks:ks_name":"Thuapadi",
    "ks:ks_pop":204,
    "ks:ks_type":"VILLAGE",
    "name:eng_x_preferred":[
        "Thuapadi"
    ],
    "wof:name":"Thuapadi",
    "wof:placetype":"locality",
    "wof:population":204
},
  "geometry": {"coordinates":[83.59732200000001,19.791132],"type":"Point"}
}