{
  "type": "Feature",
  "properties": {
    "gn:admin1_code":"25.0",
    "gn:admin2_code":"610.0",
    "gn:asciiname":"Pandipalaiyam",
    "gn:country_code":"IN",
    "gn:dem":180,
    "gn:feature_class":"P",
    "gn:feature_code":"PPL",
    "gn:name":"P\u0101ndip\u0101laiyam",
    "gn:population":0,
    "gn:timezone":"Asia/Kolkata",
    "iso:country":"IN",
    "ks:ks_name":"Pondypalayam",
    "ks:ks_pop":93,
    "ks:ks_type":"HABITATION",
    "ks:ks_uagg_main":0,
    "name:eng_x_preferred":[
        "Pondypalayam"
    ],
    "wof:name":"Pondypalayam",
    "wof:placetype":"neighbourhood",
    "wof:population":93
},
  "geometry": {"coordinates":[77.793307,11.186877],"type":"Point"}
}