{
  "type": "Feature",
  "properties": {
    "gn:admin1_code":"11.0",
    "gn:admin2_code":"31.0",
    "gn:asciiname":"Shogi",
    "gn:country_code":"IN",
    "gn:dem":1386,
    "gn:feature_class":"P",
    "gn:feature_code":"PPL",
    "gn:name":"Shogi",
    "gn:population":0,
    "gn:timezone":"Asia/Kolkata",
    "iso:country":"IN",
    "name:afr_x_preferred":[
        "Shogi"
    ],
    "name:als_x_preferred":[
        "Sh\u014dgi"
    ],
    "name:ara_x_preferred":[
        "\u0634\u0648\u063a\u064a"
    ],
    "name:bar_x_preferred":[
        "Shogi"
    ],
    "name:cat_x_preferred":[
        "Sh\u014dgi"
    ],
    "name:ces_x_preferred":[
        "\u0160\u00f3gi"
    ],
    "name:dan_x_preferred":[
        "Shogi"
    ],
    "name:deu_x_preferred":[
        "Sh\u014dgi"
    ],
    "name:ell_x_preferred":[
        "\u03a3\u03cc\u03b3\u03ba\u03b9"
    ],
    "name:epo_x_preferred":[
        "\u015cogio"
    ],
    "name:est_x_preferred":[
        "Sh\u014dgi"
    ],
    "name:fas_x_preferred":[
        "\u0634\u0648\u06af\u06cc"
    ],
    "name:fin_x_preferred":[
        "Sh\u014dgi"
    ],
    "name:fra_x_preferred":[
        "Sh\u014dgi"
    ],
    "name:heb_x_preferred":[
        "\u05e9\u05d5\u05d2\u05d9"
    ],
    "name:hun_x_preferred":[
        "S\u00f3gi"
    ],
    "name:ido_x_preferred":[
        "Shogio"
    ],
    "name:ind_x_preferred":[
        "Sogi"
    ],
    "name:isl_x_preferred":[
        "Sh\u014dgi"
    ],
    "name:ita_x_preferred":[
        "Sh\u014dgi"
    ],
    "name:lit_x_preferred":[
        "\u0160ogis"
    ],
    "name:msa_x_preferred":[
        "Shogi"
    ],
    "name:nld_x_preferred":[
        "Shogi"
    ],
    "name:nor_x_preferred":[
        "Shogi"
    ],
    "name:pol_x_preferred":[
        "Sh\u014dgi"
    ],
    "name:por_x_preferred":[
        "Shogi"
    ],
    "name:ron_x_preferred":[
        "Shogi"
    ],
    "name:rus_x_preferred":[
        "\u0421\u0451\u0433\u0438"
    ],
    "name:sco_x_preferred":[
        "Shogi"
    ],
    "name:slk_x_preferred":[
        "\u0160\u00f3gi"
    ],
    "name:spa_x_preferred":[
        "Sh\u014dgi"
    ],
    "name:swe_x_preferred":[
        "Shogi"
    ],
    "name:tgl_x_preferred":[
        "Shogi"
    ],
    "name:tha_x_preferred":[
        "\u0e2b\u0e21\u0e32\u0e01\u0e23\u0e38\u0e01\u0e0d\u0e35\u0e48\u0e1b\u0e38\u0e48\u0e19"
    ],
    "name:tur_x_preferred":[
        "\u015eogi"
    ],
    "name:ukr_x_preferred":[
        "\u0421\u044c\u043e\u0491\u0456"
    ],
    "name:vie_x_preferred":[
        "Sh\u014dgi"
    ],
    "name:zho_x_preferred":[
        "\u5c06\u68cb"
    ],
    "wof:name":"Shogi",
    "wof:placetype":"locality"
},
  "geometry": {"coordinates":[77.01607,30.82284000000001],"type":"Point"}
}