{
  "type": "Feature",
  "properties": {
    "gn:admin1_code":"19.0",
    "gn:admin2_code":"555.0",
    "gn:asciiname":"Khadervadi",
    "gn:country_code":"IN",
    "gn:dem":767,
    "gn:feature_class":"P",
    "gn:feature_code":"PPL",
    "gn:name":"Khaderv\u0101di",
    "gn:population":0,
    "gn:timezone":"Asia/Kolkata",
    "iso:country":"IN",
    "wof:name":"Khadervadi",
    "wof:placetype":"neighbourhood"
},
  "geometry": {"coordinates":[74.47568,15.81057],"type":"Point"}
}