{
  "type": "Feature",
  "properties": {
    "iso:country":"IN",
    "ks:ks_name":"Barasara",
    "ks:ks_pop":660,
    "ks:ks_type":"HABITATION",
    "ks:ks_uagg_main":0,
    "name:eng_x_preferred":[
        "Barasara"
    ],
    "wof:name":"Barasara",
    "wof:placetype":"locality",
    "wof:population":660
},
  "geometry": {"coordinates":[83.09683800000001,25.445727],"type":"Point"}
}