{
  "type": "Feature",
  "properties": {
    "iso:country":"IN",
    "ks:ks_name":"Parwani",
    "ks:ks_pop":52,
    "ks:ks_type":"VILLAGE",
    "name:eng_x_preferred":[
        "Parwani"
    ],
    "wof:name":"Parwani",
    "wof:placetype":"locality",
    "wof:population":52
},
  "geometry": {"coordinates":[85.132419,24.325395],"type":"Point"}
}