{
  "type": "Feature",
  "properties": {
    "gn:admin1_code":"36",
    "gn:admin2_code":"165.0",
    "gn:asciiname":"Kashirampur",
    "gn:country_code":"IN",
    "gn:dem":139,
    "gn:feature_class":"P",
    "gn:feature_code":"PPL",
    "gn:name":"K\u0101sh\u012br\u0101mpur",
    "gn:population":0,
    "gn:timezone":"Asia/Kolkata",
    "iso:country":"IN",
    "name:bpy_x_preferred":[
        "\u0995\u09be\u09b6\u09bf\u09b0\u09be\u09ae\u09aa\u09c1\u09b0"
    ],
    "name:ita_x_preferred":[
        "Kashirampur"
    ],
    "name:mlg_x_preferred":[
        "Kashirampur"
    ],
    "name:msa_x_preferred":[
        "Kashirampur"
    ],
    "name:new_x_preferred":[
        "\u0915\u093e\u0936\u093f\u0930\u093e\u092e\u092a\u0941\u0930"
    ],
    "name:nld_x_preferred":[
        "Kashirampur"
    ],
    "name:pol_x_preferred":[
        "Kashirampur"
    ],
    "name:por_x_preferred":[
        "Kashirampur"
    ],
    "name:vie_x_preferred":[
        "Kashirampur"
    ],
    "name:zho_x_preferred":[
        "\u5361\u65af\u5e0c\u62c9\u59c6\u666e\u5c14"
    ],
    "wof:name":"Kashirampur",
    "wof:placetype":"locality"
},
  "geometry": {"coordinates":[79.72072,26.0781],"type":"Point"}
}