{
  "type": "Feature",
  "properties": {
    "gn:admin1_code":"39.0",
    "gn:admin2_code":"64.0",
    "gn:asciiname":"Sirar",
    "gn:country_code":"IN",
    "gn:dem":1460,
    "gn:feature_class":"P",
    "gn:feature_code":"PPL",
    "gn:name":"Sir\u0101r",
    "gn:population":0,
    "gn:timezone":"Asia/Kolkata",
    "iso:country":"IN",
    "wof:name":"Sirar",
    "wof:placetype":"locality"
},
  "geometry": {"coordinates":[79.71333,29.613],"type":"Point"}
}