{
  "type": "Feature",
  "properties": {
    "gn:admin1_code":"39.0",
    "gn:admin2_code":"64.0",
    "gn:asciiname":"Sirar",
    "gn:country_code":"IN",
    "gn:dem":1460,
    "gn:feature_class":"P",
    "gn:feature_code":"PPL",
    "gn:name":"Sir\u0101r",
    "gn:population":0,
    "gn:timezone":"Asia/Kolkata",
    "iso:country":"IN",
    "ks:ks_alt_nam":"Sir\u0101r",
    "ks:ks_name":"Sirar",
    "ks:ks_pop":370,
    "ks:ks_type":"VILLAGE",
    "name:eng_x_preferred":[
        "Sirar"
    ],
    "name:eng_x_variant":[
        "Sir\u0101r"
    ],
    "wof:name":"Sirar",
    "wof:placetype":"locality",
    "wof:population":370
},
  "geometry": {"coordinates":[79.710448,29.610056],"type":"Point"}
}