{
  "type": "Feature",
  "properties": {
    "gn:admin1_code":"35.0",
    "gn:admin2_code":"441.0",
    "gn:asciiname":"Amliapani",
    "gn:country_code":"IN",
    "gn:dem":412,
    "gn:feature_class":"P",
    "gn:feature_code":"PPL",
    "gn:name":"Amliap\u0101ni",
    "gn:population":0,
    "gn:timezone":"Asia/Kolkata",
    "iso:country":"IN",
    "ks:ks_name":"Amalya Pani",
    "ks:ks_pop":646,
    "ks:ks_type":"HABITATION",
    "name:eng_x_preferred":[
        "Amalya Pani"
    ],
    "name:eng_x_variant":[
        "Amliapani"
    ],
    "wof:name":"Amalya Pani",
    "wof:placetype":"locality",
    "wof:population":646
},
  "geometry": {"coordinates":[74.909161,21.961889],"type":"Point"}
}