{
  "type": "Feature",
  "properties": {
    "iso:country":"IN",
    "ks:ks_name":"Kukribehra",
    "ks:ks_pop":686,
    "ks:ks_type":"VILLAGE",
    "name:eng_x_preferred":[
        "Kukribehra"
    ],
    "wof:name":"Kukribehra",
    "wof:placetype":"locality",
    "wof:population":686
},
  "geometry": {"coordinates":[82.287983,22.772669],"type":"Point"}
}