{
  "type": "Feature",
  "properties": {
    "iso:country":"IN",
    "ks:ks_alt_nam":"HARIRAI PARA",
    "ks:ks_name":"Harirai Para",
    "ks:ks_pop":912,
    "ks:ks_type":"HABITATION",
    "name:eng_x_preferred":[
        "Harirai Para"
    ],
    "wof:name":"Harirai Para",
    "wof:placetype":"locality",
    "wof:population":912
},
  "geometry": {"coordinates":[91.33443,23.762852],"type":"Point"}
}