{
  "type": "Feature",
  "properties": {
    "iso:country":"IN",
    "ks:ks_name":"Lahia",
    "ks:ks_pop":0,
    "ks:ks_type":"VILLAGE",
    "name:eng_x_preferred":[
        "Lahia"
    ],
    "wof:name":"Lahia",
    "wof:placetype":"locality",
    "wof:population":0
},
  "geometry": {"coordinates":[80.16852900000001,28.305026],"type":"Point"}
}