{
  "type": "Feature",
  "properties": {
    "gn:admin1_code":"34.0",
    "gn:admin2_code":"219.0",
    "gn:asciiname":"Nathua",
    "gn:country_code":"IN",
    "gn:dem":58,
    "gn:feature_class":"P",
    "gn:feature_code":"PPL",
    "gn:name":"Nathua",
    "gn:population":0,
    "gn:timezone":"Asia/Kolkata",
    "iso:country":"IN",
    "ks:ks_name":"Nathua",
    "ks:ks_pop":2199,
    "ks:ks_type":"VILLAGE",
    "ks:ks_uagg_main":0,
    "name:eng_x_preferred":[
        "Nathua"
    ],
    "wof:name":"Nathua",
    "wof:placetype":"neighbourhood",
    "wof:population":2199
},
  "geometry": {"coordinates":[84.815832,25.967566],"type":"Point"}
}