{
  "type": "Feature",
  "properties": {
    "gn:admin1_code":"11.0",
    "gn:admin2_code":"32.0",
    "gn:asciiname":"Banalag",
    "gn:country_code":"IN",
    "gn:dem":968,
    "gn:feature_class":"P",
    "gn:feature_code":"PPL",
    "gn:name":"Ban\u0101lag",
    "gn:population":0,
    "gn:timezone":"Asia/Kolkata",
    "iso:country":"IN",
    "wof:name":"Banalag",
    "wof:placetype":"locality"
},
  "geometry": {"coordinates":[77.12793000000001,30.73215],"type":"Point"}
}