{
  "type": "Feature",
  "properties": {
    "iso:country":"IN",
    "ks:ks_name":"Narayanapuram",
    "ks:ks_pop":454,
    "ks:ks_type":"HABITATION",
    "name:eng_x_preferred":[
        "Narayanapuram"
    ],
    "wof:name":"Narayanapuram",
    "wof:placetype":"locality",
    "wof:population":454
},
  "geometry": {"coordinates":[77.959985,10.005853],"type":"Point"}
}