{
  "type": "Feature",
  "properties": {
    "gn:admin1_code":"3.0",
    "gn:admin2_code":"305",
    "gn:asciiname":"Amguri",
    "gn:country_code":"IN",
    "gn:dem":77,
    "gn:feature_class":"P",
    "gn:feature_code":"PPL",
    "gn:name":"Amguri",
    "gn:population":0,
    "gn:timezone":"Asia/Kolkata",
    "iso:country":"IN",
    "name:asm_x_preferred":[
        "\u0986\u09ae\u0997\u09c1\u09f0\u09bf"
    ],
    "name:ben_x_preferred":[
        "\u0986\u09ae\u0997\u09c1\u09a1\u09bc\u09bf"
    ],
    "name:bpy_x_preferred":[
        "\u0986\u09ae\u0997\u09c1\u09a1\u09bc\u09bf"
    ],
    "name:ceb_x_preferred":[
        "Amguri"
    ],
    "name:fas_x_preferred":[
        "\u0627\u0645\u06af\u0648\u0631\u06cc"
    ],
    "name:ita_x_preferred":[
        "Amguri"
    ],
    "name:min_x_preferred":[
        "Amguri"
    ],
    "name:msa_x_preferred":[
        "Amguri"
    ],
    "name:new_x_preferred":[
        "\u0905\u0917\u0941\u0930\u0940"
    ],
    "name:nld_x_preferred":[
        "Amguri"
    ],
    "name:por_x_preferred":[
        "Amguri"
    ],
    "name:spa_x_preferred":[
        "Amguri"
    ],
    "name:swe_x_preferred":[
        "Amguri"
    ],
    "name:vie_x_preferred":[
        "Amguri"
    ],
    "name:zho_x_preferred":[
        "\u963f\u59c6\u53e4\u91cc"
    ],
    "wof:name":"Amguri",
    "wof:placetype":"locality"
},
  "geometry": {"coordinates":[93.05110999999999,26.57122],"type":"Point"}
}