{
  "type": "Feature",
  "properties": {
    "gn:admin1_code":"3.0",
    "gn:admin2_code":"305",
    "gn:asciiname":"Amguri",
    "gn:country_code":"IN",
    "gn:dem":77,
    "gn:feature_class":"P",
    "gn:feature_code":"PPL",
    "gn:name":"Amguri",
    "gn:population":0,
    "gn:timezone":"Asia/Kolkata",
    "iso:country":"IN",
    "wof:name":"Amguri",
    "wof:placetype":"locality"
},
  "geometry": {"coordinates":[93.05110999999999,26.57122],"type":"Point"}
}