{
  "type": "Feature",
  "properties": {
    "gn:admin1_code":"36.0",
    "gn:admin2_code":"158.0",
    "gn:asciiname":"Pura Moti",
    "gn:country_code":"IN",
    "gn:dem":114,
    "gn:feature_class":"P",
    "gn:feature_code":"PPL",
    "gn:name":"Pura Moti",
    "gn:population":0,
    "gn:timezone":"Asia/Kolkata",
    "iso:country":"IN",
    "ks:ks_name":"Pure Moti",
    "ks:ks_pop":119,
    "ks:ks_type":"HABITATION",
    "name:eng_x_preferred":[
        "Pure Moti"
    ],
    "name:eng_x_variant":[
        "Pura Moti"
    ],
    "wof:name":"Pure Moti",
    "wof:placetype":"locality",
    "wof:population":119
},
  "geometry": {"coordinates":[81.41200000000001,26.426],"type":"Point"}
}