{
  "type": "Feature",
  "properties": {
    "iso:country":"IN",
    "ks:ks_name":"Bhimanakere",
    "ks:ks_pop":63,
    "ks:ks_type":"HABITATION",
    "name:eng_x_preferred":[
        "Bhimanakere"
    ],
    "wof:name":"Bhimanakere",
    "wof:placetype":"locality",
    "wof:population":63
},
  "geometry": {"coordinates":[75.041017,13.973789],"type":"Point"}
}