{
  "type": "Feature",
  "properties": {
    "iso:country":"IN",
    "ks:ks_name":"Saramanda",
    "ks:ks_type":"VILLAGE",
    "name:eng_x_preferred":[
        "Saramanda"
    ],
    "wof:name":"Saramanda",
    "wof:placetype":"locality"
},
  "geometry": {"coordinates":[82.379817,17.808627],"type":"Point"}
}