{
  "type": "Feature",
  "properties": {
    "iso:country":"IN",
    "ks:ks_name":"Muthikaguda",
    "ks:ks_pop":41,
    "ks:ks_type":"HABITATION",
    "name:eng_x_preferred":[
        "Muthikaguda"
    ],
    "wof:name":"Muthikaguda",
    "wof:placetype":"locality",
    "wof:population":41
},
  "geometry": {"coordinates":[83.85129999999999,18.834458],"type":"Point"}
}