{
  "type": "Feature",
  "properties": {
    "gn:admin1_code":"25.0",
    "gn:admin2_code":"610.0",
    "gn:asciiname":"Palanikkayundanpalaiyam",
    "gn:country_code":"IN",
    "gn:dem":239,
    "gn:feature_class":"P",
    "gn:feature_code":"PPL",
    "gn:name":"Palanikkayundanp\u0101laiyam",
    "gn:population":0,
    "gn:timezone":"Asia/Kolkata",
    "iso:country":"IN",
    "wof:name":"Palanikkayundanpalaiyam",
    "wof:placetype":"locality"
},
  "geometry": {"coordinates":[77.35998000000002,11.4283],"type":"Point"}
}