{
  "type": "Feature",
  "properties": {
    "gn:admin1_code":"25.0",
    "gn:admin2_code":"631.0",
    "gn:asciiname":"Simakalpalli",
    "gn:country_code":"IN",
    "gn:dem":506,
    "gn:feature_class":"P",
    "gn:feature_code":"PPL",
    "gn:name":"Simakalpalli",
    "gn:population":0,
    "gn:timezone":"Asia/Kolkata",
    "iso:country":"IN",
    "wof:name":"Simakalpalli",
    "wof:placetype":"neighbourhood"
},
  "geometry": {"coordinates":[78.13355,12.55677],"type":"Point"}
}