{
  "type": "Feature",
  "properties": {
    "iso:country":"IN",
    "ks:ks_name":"Surjan Ka Purwa",
    "ks:ks_pop":242,
    "ks:ks_type":"HABITATION",
    "ks:ks_uagg_main":0,
    "name:eng_x_preferred":[
        "Surjan Ka Purwa"
    ],
    "wof:name":"Surjan Ka Purwa",
    "wof:placetype":"neighbourhood",
    "wof:population":242
},
  "geometry": {"coordinates":[80.45768700000001,25.279629],"type":"Point"}
}