{
  "type": "Feature",
  "properties": {
    "gn:admin1_code":"2.0",
    "gn:admin2_code":"544.0",
    "gn:asciiname":"Mandipalle",
    "gn:country_code":"IN",
    "gn:dem":695,
    "gn:feature_class":"P",
    "gn:feature_code":"PPL",
    "gn:name":"Mandipalle",
    "gn:population":0,
    "gn:timezone":"Asia/Kolkata",
    "iso:country":"IN",
    "wof:name":"Mandipalle",
    "wof:placetype":"locality"
},
  "geometry": {"coordinates":[82.36564,18.02557],"type":"Point"}
}