{
  "type": "Feature",
  "properties": {
    "iso:country":"IN",
    "ks:ks_alt_nam":"ZOLHA TARA",
    "ks:ks_name":"Zolha Tara",
    "ks:ks_pop":523,
    "ks:ks_type":"HABITATION",
    "ks:ks_uagg_main":0,
    "name:eng_x_preferred":[
        "Zolha Tara"
    ],
    "wof:name":"Zolha Tara",
    "wof:placetype":"neighbourhood",
    "wof:population":523
},
  "geometry": {"coordinates":[82.311477,26.19226],"type":"Point"}
}