{
  "type": "Feature",
  "properties": {
    "iso:country":"IN",
    "ks:ks_name":"Chhanga Tanda",
    "ks:ks_pop":289,
    "ks:ks_type":"HABITATION",
    "name:eng_x_preferred":[
        "Chhanga Tanda"
    ],
    "wof:name":"Chhanga Tanda",
    "wof:placetype":"locality",
    "wof:population":289
},
  "geometry": {"coordinates":[80.571572,28.344159],"type":"Point"}
}