{
  "type": "Feature",
  "properties": {
    "iso:country":"IN",
    "ks:ks_alt_nam":"ATHVALEWASTI",
    "ks:ks_name":"Athvalewasti",
    "ks:ks_pop":75,
    "ks:ks_type":"HABITATION",
    "name:eng_x_preferred":[
        "Athvalewasti"
    ],
    "wof:name":"Athvalewasti",
    "wof:placetype":"locality",
    "wof:population":75
},
  "geometry": {"coordinates":[74.958724,17.084175],"type":"Point"}
}