{
  "type": "Feature",
  "properties": {
    "iso:country":"IN",
    "ks:ks_name":"Aratikayalanka",
    "ks:ks_pop":1740,
    "ks:ks_type":"HABITATION",
    "name:eng_x_preferred":[
        "Aratikayalanka"
    ],
    "wof:name":"Aratikayalanka",
    "wof:placetype":"locality",
    "wof:population":1740
},
  "geometry": {"coordinates":[82.18451899999999,16.731481],"type":"Point"}
}