{
  "type": "Feature",
  "properties": {
    "iso:country":"IN",
    "ks:ks_alt_nam":"Gos\u0101indih",
    "ks:ks_name":"Gosaindih",
    "ks:ks_pop":348,
    "ks:ks_type":"VILLAGE",
    "ks:ks_uagg_main":0,
    "name:eng_x_preferred":[
        "Gosaindih"
    ],
    "name:eng_x_variant":[
        "Gos\u0101indih"
    ],
    "wof:name":"Gosaindih",
    "wof:placetype":"neighbourhood",
    "wof:population":348
},
  "geometry": {"coordinates":[86.276785,24.413021],"type":"Point"}
}