{
  "type": "Feature",
  "properties": {
    "iso:country":"IN",
    "ks:ks_name":"Katharpada",
    "ks:ks_pop":359,
    "ks:ks_type":"HABITATION",
    "name:eng_x_preferred":[
        "Katharpada"
    ],
    "wof:name":"Katharpada",
    "wof:placetype":"locality",
    "wof:population":359
},
  "geometry": {"coordinates":[84.716528,22.240401],"type":"Point"}
}