{
  "type": "Feature",
  "properties": {
    "iso:country":"IN",
    "ks:ks_name":"Damasaravi",
    "ks:ks_pop":21,
    "ks:ks_type":"HABITATION",
    "name:eng_x_preferred":[
        "Damasaravi"
    ],
    "wof:name":"Damasaravi",
    "wof:placetype":"locality",
    "wof:population":21
},
  "geometry": {"coordinates":[83.042433,18.549563],"type":"Point"}
}