{
  "type": "Feature",
  "properties": {
    "iso:country":"IN",
    "ks:ks_name":"Kanakodige",
    "ks:ks_pop":53,
    "ks:ks_type":"HABITATION",
    "name:eng_x_preferred":[
        "Kanakodige"
    ],
    "wof:name":"Kanakodige",
    "wof:placetype":"locality",
    "wof:population":53
},
  "geometry": {"coordinates":[75.403971,13.427382],"type":"Point"}
}