{
  "type": "Feature",
  "properties": {
    "iso:country":"IN",
    "ks:ks_name":"Baligari",
    "ks:ks_pop":2857,
    "ks:ks_type":"VILLAGE",
    "ks:ks_uagg_main":0,
    "name:eng_x_preferred":[
        "Baligari"
    ],
    "wof:name":"Baligari",
    "wof:placetype":"locality",
    "wof:population":2857
},
  "geometry": {"coordinates":[88.486199,22.571536],"type":"Point"}
}