{
  "type": "Feature",
  "properties": {
    "iso:country":"IN",
    "ks:ks_name":"Thazhekode",
    "ks:ks_pop":21764,
    "ks:ks_type":"VILLAGE",
    "name:eng_x_preferred":[
        "Thazhekode"
    ],
    "wof:name":"Thazhekode",
    "wof:placetype":"locality",
    "wof:population":21764
},
  "geometry": {"coordinates":[76.287243,10.962783],"type":"Point"}
}