{
  "type": "Feature",
  "properties": {
    "gn:admin1_code":"34",
    "gn:admin2_code":"218.0",
    "gn:asciiname":"Sonbarsa",
    "gn:country_code":"IN",
    "gn:dem":67,
    "gn:feature_class":"P",
    "gn:feature_code":"PPL",
    "gn:name":"Sonb\u0101rsa",
    "gn:population":0,
    "gn:timezone":"Asia/Kolkata",
    "iso:country":"IN",
    "ks:ks_name":"Sonbarsa",
    "ks:ks_pop":511,
    "ks:ks_type":"VILLAGE",
    "name:ceb_x_preferred":[
        "Sonbarsa"
    ],
    "name:eng_x_preferred":[
        "Sonbarsa"
    ],
    "name:mai_x_preferred":[
        "\u0938\u094b\u0928\u092c\u0930\u094d\u0937\u093e"
    ],
    "name:msa_x_preferred":[
        "Sonbarsa"
    ],
    "name:nep_x_preferred":[
        "\u0938\u094b\u0928\u092c\u0930\u094d\u0937\u093e"
    ],
    "name:new_x_preferred":[
        "\u0938\u094b\u0928\u0935\u0930\u094d\u0937"
    ],
    "name:pol_x_preferred":[
        "Sonbarsa"
    ],
    "wof:name":"Sonbarsa",
    "wof:placetype":"locality",
    "wof:population":511
},
  "geometry": {"coordinates":[84.305364,26.078156],"type":"Point"}
}