{
  "type": "Feature",
  "properties": {
    "iso:country":"IN",
    "ks:ks_name":"Sajanpura",
    "ks:ks_pop":1231,
    "ks:ks_type":"HABITATION",
    "name:eng_x_preferred":[
        "Sajanpura"
    ],
    "wof:name":"Sajanpura",
    "wof:placetype":"locality",
    "wof:population":1231
},
  "geometry": {"coordinates":[72.10175599999999,25.425781],"type":"Point"}
}