{
  "type": "Feature",
  "properties": {
    "iso:country":"IN",
    "ks:ks_name":"Mohanchak",
    "ks:ks_pop":8,
    "ks:ks_type":"VILLAGE",
    "name:eng_x_preferred":[
        "Mohanchak"
    ],
    "wof:name":"Mohanchak",
    "wof:placetype":"locality",
    "wof:population":8
},
  "geometry": {"coordinates":[87.402584,22.074028],"type":"Point"}
}