{
  "type": "Feature",
  "properties": {
    "iso:country":"IN",
    "ks:ks_name":"Thakur Suba",
    "ks:ks_pop":108,
    "ks:ks_type":"HABITATION",
    "name:eng_x_preferred":[
        "Thakur Suba"
    ],
    "wof:name":"Thakur Suba",
    "wof:placetype":"locality",
    "wof:population":108
},
  "geometry": {"coordinates":[91.724062,26.431059],"type":"Point"}
}