{
  "type": "Feature",
  "properties": {
    "iso:country":"IN",
    "ks:ks_alt_nam":"Ambegaon kh",
    "ks:ks_name":"Ambegaon Kh",
    "ks:ks_pop":173,
    "ks:ks_type":"HABITATION",
    "name:eng_x_preferred":[
        "Ambegaon Kh"
    ],
    "wof:name":"Ambegaon Kh",
    "wof:placetype":"locality",
    "wof:population":173
},
  "geometry": {"coordinates":[73.601755,18.381159],"type":"Point"}
}