{
  "type": "Feature",
  "properties": {
    "iso:country":"IN",
    "ks:ks_name":"Sanapwasti",
    "ks:ks_pop":152,
    "ks:ks_type":"HABITATION",
    "name:eng_x_preferred":[
        "Sanapwasti"
    ],
    "wof:name":"Sanapwasti",
    "wof:placetype":"locality",
    "wof:population":152
},
  "geometry": {"coordinates":[74.22721900000001,19.654052],"type":"Point"}
}