{
  "type": "Feature",
  "properties": {
    "iso:country":"IN",
    "ks:ks_name":"Chinta Purwa",
    "ks:ks_pop":155,
    "ks:ks_type":"HABITATION",
    "ks:ks_uagg_main":0,
    "name:eng_x_preferred":[
        "Chinta Purwa"
    ],
    "wof:name":"Chinta Purwa",
    "wof:placetype":"neighbourhood",
    "wof:population":155
},
  "geometry": {"coordinates":[80.280739,27.391243],"type":"Point"}
}