{
  "type": "Feature",
  "properties": {
    "gn:admin1_code":"25.0",
    "gn:admin2_code":"633.0",
    "gn:asciiname":"Kolinji Kattuppudur",
    "gn:country_code":"IN",
    "gn:dem":279,
    "gn:feature_class":"P",
    "gn:feature_code":"PPL",
    "gn:name":"Kolinji K\u0101ttuppud\u016br",
    "gn:population":0,
    "gn:timezone":"Asia/Kolkata",
    "iso:country":"IN",
    "wof:name":"Kolinji Kattuppudur",
    "wof:placetype":"locality"
},
  "geometry": {"coordinates":[77.43219000000001,10.79398],"type":"Point"}
}