{
  "type": "Feature",
  "properties": {
    "iso:country":"IN",
    "ks:ks_alt_nam":"Sugouri ka Purwa",
    "ks:ks_name":"Sugouri Ka Purwa",
    "ks:ks_pop":132,
    "ks:ks_type":"HABITATION",
    "ks:ks_uagg_main":0,
    "name:eng_x_preferred":[
        "Sugouri Ka Purwa"
    ],
    "wof:name":"Sugouri Ka Purwa",
    "wof:placetype":"neighbourhood",
    "wof:population":132
},
  "geometry": {"coordinates":[81.951643,26.423597],"type":"Point"}
}