{
  "type": "Feature",
  "properties": {
    "iso:country":"IN",
    "ks:ks_name":"Tukutoli",
    "ks:ks_pop":131,
    "ks:ks_type":"HABITATION",
    "name:eng_x_preferred":[
        "Tukutoli"
    ],
    "wof:name":"Tukutoli",
    "wof:placetype":"locality",
    "wof:population":131
},
  "geometry": {"coordinates":[84.134745,22.701409],"type":"Point"}
}