{
  "type": "Feature",
  "properties": {
    "iso:country":"IN",
    "ks:ks_name":"Talab",
    "ks:ks_pop":103,
    "ks:ks_type":"VILLAGE",
    "name:eng_x_preferred":[
        "Talab"
    ],
    "wof:name":"Talab",
    "wof:placetype":"locality",
    "wof:population":103
},
  "geometry": {"coordinates":[74.582908,24.246842],"type":"Point"}
}