{
  "type": "Feature",
  "properties": {
    "iso:country":"IN",
    "ks:ks_name":"Kamrora",
    "ks:ks_pop":650,
    "ks:ks_type":"HABITATION",
    "name:eng_x_preferred":[
        "Kamrora"
    ],
    "wof:name":"Kamrora",
    "wof:placetype":"locality",
    "wof:population":650
},
  "geometry": {"coordinates":[85.327134,22.695917],"type":"Point"}
}