{
  "type": "Feature",
  "properties": {
    "iso:country":"IN",
    "ks:ks_name":"Futkaltoli",
    "ks:ks_pop":186,
    "ks:ks_type":"HABITATION",
    "name:eng_x_preferred":[
        "Futkaltoli"
    ],
    "wof:name":"Futkaltoli",
    "wof:placetype":"locality",
    "wof:population":186
},
  "geometry": {"coordinates":[85.23926899999999,23.21408],"type":"Point"}
}