{
  "type": "Feature",
  "properties": {
    "iso:country":"IN",
    "ks:ks_name":"Amara Pathar",
    "ks:ks_pop":701,
    "ks:ks_type":"HABITATION",
    "name:eng_x_preferred":[
        "Amara Pathar"
    ],
    "wof:name":"Amara Pathar",
    "wof:placetype":"locality",
    "wof:population":701
},
  "geometry": {"coordinates":[91.99758300000001,26.176983],"type":"Point"}
}