{
  "type": "Feature",
  "properties": {
    "gn:admin1_code":"34.0",
    "gn:admin2_code":"221.0",
    "gn:asciiname":"Bhuswardih",
    "gn:country_code":"IN",
    "gn:dem":50,
    "gn:feature_class":"P",
    "gn:feature_code":"PPL",
    "gn:name":"Bhuswardih",
    "gn:population":0,
    "gn:timezone":"Asia/Kolkata",
    "iso:country":"IN",
    "ks:ks_alt_nam":"bhushwardih",
    "ks:ks_name":"Bhushwardih",
    "ks:ks_pop":764,
    "ks:ks_type":"HABITATION",
    "name:eng_x_preferred":[
        "Bhushwardih"
    ],
    "name:eng_x_variant":[
        "Bhuswardih"
    ],
    "wof:name":"Bhushwardih",
    "wof:placetype":"locality",
    "wof:population":764
},
  "geometry": {"coordinates":[85.987021,25.662983],"type":"Point"}
}