{
  "type": "Feature",
  "properties": {
    "gn:admin1_code":"34.0",
    "gn:admin2_code":"217.0",
    "gn:asciiname":"Kuaridih",
    "gn:country_code":"IN",
    "gn:dem":77,
    "gn:feature_class":"P",
    "gn:feature_code":"PPL",
    "gn:name":"Ku\u0101rid\u012bh",
    "gn:population":0,
    "gn:timezone":"Asia/Kolkata",
    "iso:country":"IN",
    "ks:ks_alt_nam":"Ku\u0101rid\u012bh",
    "ks:ks_name":"Kuaridih",
    "ks:ks_pop":638,
    "ks:ks_type":"VILLAGE",
    "ks:ks_uagg_main":0,
    "name:eng_x_preferred":[
        "Kuaridih"
    ],
    "name:eng_x_variant":[
        "Ku\u0101rid\u012bh"
    ],
    "wof:name":"Kuaridih",
    "wof:placetype":"neighbourhood",
    "wof:population":638
},
  "geometry": {"coordinates":[84.166229,26.433951],"type":"Point"}
}