{
  "type": "Feature",
  "properties": {
    "gn:admin1_code":"34.0",
    "gn:admin2_code":"239.0",
    "gn:asciiname":"Narain Bigha",
    "gn:country_code":"IN",
    "gn:dem":73,
    "gn:feature_class":"P",
    "gn:feature_code":"PPL",
    "gn:name":"Nar\u0101in Bigha",
    "gn:population":0,
    "gn:timezone":"Asia/Kolkata",
    "iso:country":"IN",
    "ks:ks_name":"Narayan Bigha",
    "ks:ks_pop":67,
    "ks:ks_type":"HABITATION",
    "name:eng_x_preferred":[
        "Narayan Bigha"
    ],
    "name:eng_x_variant":[
        "Narain Bigha"
    ],
    "wof:name":"Narayan Bigha",
    "wof:placetype":"locality",
    "wof:population":67
},
  "geometry": {"coordinates":[85.099695,25.162482],"type":"Point"}
}