{
  "type": "Feature",
  "properties": {
    "iso:country":"IN",
    "ks:ks_name":"Gol Tilla",
    "ks:ks_pop":621,
    "ks:ks_type":"HABITATION",
    "ks:ks_uagg_main":0,
    "name:eng_x_preferred":[
        "Gol Tilla"
    ],
    "wof:name":"Gol Tilla",
    "wof:placetype":"neighbourhood",
    "wof:population":621
},
  "geometry": {"coordinates":[91.467197,23.545097],"type":"Point"}
}