{
  "type": "Feature",
  "properties": {
    "iso:country":"IN",
    "ks:ks_name":"Somnalli",
    "ks:ks_pop":89,
    "ks:ks_type":"HABITATION",
    "name:eng_x_preferred":[
        "Somnalli"
    ],
    "wof:name":"Somnalli",
    "wof:placetype":"locality",
    "wof:population":89
},
  "geometry": {"coordinates":[74.85159299999999,14.656842],"type":"Point"}
}