{
  "type": "Feature",
  "properties": {
    "iso:country":"IN",
    "ks:ks_alt_nam":"Tur\u012b",
    "ks:ks_name":"Turi",
    "ks:ks_pop":280,
    "ks:ks_type":"VILLAGE",
    "name:eng_x_preferred":[
        "Turi"
    ],
    "name:eng_x_variant":[
        "Tur\u012b"
    ],
    "wof:name":"Turi",
    "wof:placetype":"locality",
    "wof:population":280
},
  "geometry": {"coordinates":[84.959861,24.117937],"type":"Point"}
}