{
  "type": "Feature",
  "properties": {
    "iso:country":"IN",
    "ks:ks_name":"Bhuiya Para",
    "ks:ks_pop":1232,
    "ks:ks_type":"HABITATION",
    "name:eng_x_preferred":[
        "Bhuiya Para"
    ],
    "wof:name":"Bhuiya Para",
    "wof:placetype":"locality",
    "wof:population":1232
},
  "geometry": {"coordinates":[88.77496499999999,22.325971],"type":"Point"}
}