{
  "type": "Feature",
  "properties": {
    "gn:admin1_code":"25",
    "gn:admin2_code":"609.0",
    "gn:asciiname":"Sendamangalam",
    "gn:country_code":"IN",
    "gn:dem":190,
    "gn:feature_class":"P",
    "gn:feature_code":"PPL",
    "gn:name":"Sendamangalam",
    "gn:population":0,
    "gn:timezone":"Asia/Kolkata",
    "iso:country":"IN",
    "name:ceb_x_preferred":[
        "Sendamangalam"
    ],
    "name:swe_x_preferred":[
        "Sendamangalam"
    ],
    "wof:name":"Sendamangalam",
    "wof:placetype":"locality"
},
  "geometry": {"coordinates":[78.23416,11.28111],"type":"Point"}
}