{
  "type": "Feature",
  "properties": {
    "iso:country":"IN",
    "ks:ks_name":"Gosaviwadi",
    "ks:ks_pop":88,
    "ks:ks_type":"HABITATION",
    "name:eng_x_preferred":[
        "Gosaviwadi"
    ],
    "wof:name":"Gosaviwadi",
    "wof:placetype":"locality",
    "wof:population":88
},
  "geometry": {"coordinates":[73.840585,16.259483],"type":"Point"}
}