{
  "type": "Feature",
  "properties": {
    "gn:admin1_code":"11.0",
    "gn:admin2_code":"24.0",
    "gn:asciiname":"Gheta",
    "gn:country_code":"IN",
    "gn:dem":561,
    "gn:feature_class":"P",
    "gn:feature_code":"PPL",
    "gn:name":"Gheta",
    "gn:population":0,
    "gn:timezone":"Asia/Kolkata",
    "iso:country":"IN",
    "wof:name":"Gheta",
    "wof:placetype":"locality"
},
  "geometry": {"coordinates":[75.86209000000002,32.19144],"type":"Point"}
}