{
  "type": "Feature",
  "properties": {
    "gn:admin1_code":"2",
    "gn:admin2_code":"544.0",
    "gn:asciiname":"Ennagundi",
    "gn:country_code":"IN",
    "gn:dem":842,
    "gn:feature_class":"P",
    "gn:feature_code":"PPL",
    "gn:name":"Ennagundi",
    "gn:population":0,
    "gn:timezone":"Asia/Kolkata",
    "iso:country":"IN",
    "wof:name":"Ennagundi",
    "wof:placetype":"locality"
},
  "geometry": {"coordinates":[82.1865,17.9825],"type":"Point"}
}