{
  "type": "Feature",
  "properties": {
    "gn:admin1_code":"10.0",
    "gn:admin2_code":"73.0",
    "gn:asciiname":"Dadwana",
    "gn:country_code":"IN",
    "gn:dem":250,
    "gn:feature_class":"P",
    "gn:feature_code":"PPL",
    "gn:name":"Dadw\u0101na",
    "gn:population":0,
    "gn:timezone":"Asia/Kolkata",
    "iso:country":"IN",
    "wof:name":"Dadwana",
    "wof:placetype":"locality"
},
  "geometry": {"coordinates":[76.63475,29.89136],"type":"Point"}
}