{
  "type": "Feature",
  "properties": {
    "iso:country":"IN",
    "ks:ks_name":"Amba",
    "ks:ks_pop":860,
    "ks:ks_type":"HABITATION",
    "name:eng_x_preferred":[
        "Amba"
    ],
    "wof:name":"Amba",
    "wof:placetype":"locality",
    "wof:population":860
},
  "geometry": {"coordinates":[75.97798,11.557138],"type":"Point"}
}