{
  "type": "Feature",
  "properties": {
    "iso:country":"IN",
    "ks:ks_name":"Chithrabail",
    "ks:ks_pop":188,
    "ks:ks_type":"HABITATION",
    "name:eng_x_preferred":[
        "Chithrabail"
    ],
    "wof:name":"Chithrabail",
    "wof:placetype":"locality",
    "wof:population":188
},
  "geometry": {"coordinates":[74.864783,13.271842],"type":"Point"}
}