{
  "type": "Feature",
  "properties": {
    "iso:country":"IN",
    "ks:ks_name":"Rensing Lekthe",
    "ks:ks_pop":93,
    "ks:ks_type":"HABITATION",
    "ks:ks_uagg_main":0,
    "name:eng_x_preferred":[
        "Rensing Lekthe"
    ],
    "wof:name":"Rensing Lekthe",
    "wof:placetype":"neighbourhood",
    "wof:population":93
},
  "geometry": {"coordinates":[93.769555,26.233974],"type":"Point"}
}