{
  "type": "Feature",
  "properties": {
    "iso:country":"IN",
    "ks:ks_name":"Rambili",
    "ks:ks_pop":134,
    "ks:ks_type":"VILLAGE",
    "name:eng_x_preferred":[
        "Rambili"
    ],
    "wof:name":"Rambili",
    "wof:placetype":"locality",
    "wof:population":134
},
  "geometry": {"coordinates":[84.20735500000001,19.602118],"type":"Point"}
}