{
  "type": "Feature",
  "properties": {
    "iso:country":"IN",
    "ks:ks_name":"Barunakandha",
    "ks:ks_pop":186,
    "ks:ks_type":"VILLAGE",
    "ks:ks_uagg_main":0,
    "name:eng_x_preferred":[
        "Barunakandha"
    ],
    "wof:name":"Barunakandha",
    "wof:placetype":"neighbourhood",
    "wof:population":186
},
  "geometry": {"coordinates":[86.54597200000001,20.289417],"type":"Point"}
}