{
  "type": "Feature",
  "properties": {
    "gn:admin1_code":"38.0",
    "gn:admin2_code":"352.0",
    "gn:asciiname":"Phuljhari",
    "gn:country_code":"IN",
    "gn:dem":223,
    "gn:feature_class":"P",
    "gn:feature_code":"PPL",
    "gn:name":"Phuljh\u0101ri",
    "gn:population":0,
    "gn:timezone":"Asia/Kolkata",
    "iso:country":"IN",
    "ks:ks_alt_nam":"Phuljh\u0101ri",
    "ks:ks_name":"Phuljhari",
    "ks:ks_pop":48,
    "ks:ks_type":"VILLAGE",
    "name:eng_x_preferred":[
        "Phuljhari"
    ],
    "name:eng_x_variant":[
        "Phuljh\u0101ri"
    ],
    "wof:name":"Phuljhari",
    "wof:placetype":"locality",
    "wof:population":48
},
  "geometry": {"coordinates":[87.705102,25.210918],"type":"Point"}
}