{
  "type": "Feature",
  "properties": {
    "iso:country":"IN",
    "ks:ks_name":"Gollabanda",
    "ks:ks_pop":51,
    "ks:ks_type":"HABITATION",
    "name:eng_x_preferred":[
        "Gollabanda"
    ],
    "wof:name":"Gollabanda",
    "wof:placetype":"locality",
    "wof:population":51
},
  "geometry": {"coordinates":[82.03342499999999,17.726063],"type":"Point"}
}