{
  "type": "Feature",
  "properties": {
    "iso:country":"IN",
    "ks:ks_name":"Ram Sanehi Pur",
    "ks:ks_pop":129,
    "ks:ks_type":"HABITATION",
    "name:eng_x_preferred":[
        "Ram Sanehi Pur"
    ],
    "wof:name":"Ram Sanehi Pur",
    "wof:placetype":"locality",
    "wof:population":129
},
  "geometry": {"coordinates":[81.899063,27.527467],"type":"Point"}
}