{
  "type": "Feature",
  "properties": {
    "iso:country":"IN",
    "qs:name":"Harsh Vihar",
    "qs:name_adm0":"India",
    "qs:name_adm1":"Delhi",
    "qs:photos":7,
    "qs:photos_1k":1,
    "qs:photos_9k":1,
    "qs:photos_9r":1,
    "qs:photos_all":7,
    "qs:photos_sr":1,
    "qs:placetype":"Suburb",
    "qs:pop_sr":"0",
    "wof:name":"Harsh Vihar",
    "wof:placetype":"neighbourhood"
},
  "geometry": {"coordinates":[77.133701,28.694153],"type":"Point"}
}