{
  "type": "Feature",
  "properties": {
    "iso:country":"IN",
    "ks:ks_name":"Banapura",
    "ks:ks_pop":917,
    "ks:ks_type":"VILLAGE",
    "ks:ks_uagg_main":0,
    "name:eng_x_preferred":[
        "Banapura"
    ],
    "wof:name":"Banapura",
    "wof:placetype":"neighbourhood",
    "wof:population":917
},
  "geometry": {"coordinates":[86.153014,20.629027],"type":"Point"}
}