{
  "type": "Feature",
  "properties": {
    "iso:country":"IN",
    "ks:ks_name":"Surve Wasti",
    "ks:ks_pop":629,
    "ks:ks_type":"HABITATION",
    "name:eng_x_preferred":[
        "Surve Wasti"
    ],
    "wof:name":"Surve Wasti",
    "wof:placetype":"locality",
    "wof:population":629
},
  "geometry": {"coordinates":[75.405779,17.896681],"type":"Point"}
}