{
  "type": "Feature",
  "properties": {
    "iso:country":"IN",
    "ks:ks_name":"Gangadasbati",
    "ks:ks_pop":0,
    "ks:ks_type":"VILLAGE",
    "name:eng_x_preferred":[
        "Gangadasbati"
    ],
    "wof:name":"Gangadasbati",
    "wof:placetype":"locality",
    "wof:population":0
},
  "geometry": {"coordinates":[87.89279999999999,23.750355],"type":"Point"}
}