{
  "type": "Feature",
  "properties": {
    "iso:country":"IN",
    "ks:ks_name":"Samagota",
    "ks:ks_pop":57,
    "ks:ks_type":"VILLAGE",
    "name:eng_x_preferred":[
        "Samagota"
    ],
    "wof:name":"Samagota",
    "wof:placetype":"locality",
    "wof:population":57
},
  "geometry": {"coordinates":[84.160861,20.003022],"type":"Point"}
}