{
  "type": "Feature",
  "properties": {
    "iso:country":"IN",
    "ks:ks_name":"Pat Pukur",
    "ks:ks_pop":4157,
    "ks:ks_type":"VILLAGE",
    "ks:ks_uagg_main":0,
    "name:eng_x_preferred":[
        "Pat Pukur"
    ],
    "wof:name":"Pat Pukur",
    "wof:placetype":"neighbourhood",
    "wof:population":4157
},
  "geometry": {"coordinates":[88.49437,22.133041],"type":"Point"}
}