{
  "type": "Feature",
  "properties": {
    "iso:country":"IN",
    "ks:ks_name":"Phuljodi",
    "ks:ks_pop":306,
    "ks:ks_type":"HABITATION",
    "name:eng_x_preferred":[
        "Phuljodi"
    ],
    "wof:name":"Phuljodi",
    "wof:placetype":"locality",
    "wof:population":306
},
  "geometry": {"coordinates":[82.065834,19.769892],"type":"Point"}
}