{
  "type": "Feature",
  "properties": {
    "iso:country":"IN",
    "ks:ks_name":"Kondameeda Thanda",
    "ks:ks_pop":119,
    "ks:ks_type":"HABITATION",
    "name:eng_x_preferred":[
        "Kondameeda Thanda"
    ],
    "wof:name":"Kondameeda Thanda",
    "wof:placetype":"locality",
    "wof:population":119
},
  "geometry": {"coordinates":[78.45342599999999,13.522483],"type":"Point"}
}