{
  "type": "Feature",
  "properties": {
    "iso:country":"IN",
    "ks:ks_name":"Kachari Para",
    "ks:ks_pop":1363,
    "ks:ks_type":"HABITATION",
    "name:eng_x_preferred":[
        "Kachari Para"
    ],
    "wof:name":"Kachari Para",
    "wof:placetype":"locality",
    "wof:population":1363
},
  "geometry": {"coordinates":[88.810868,22.194248],"type":"Point"}
}