{
  "type": "Feature",
  "properties": {
    "iso:country":"IN",
    "ks:ks_name":"Usaniyadeeh",
    "ks:ks_pop":100,
    "ks:ks_type":"HABITATION",
    "name:eng_x_preferred":[
        "Usaniyadeeh"
    ],
    "wof:name":"Usaniyadeeh",
    "wof:placetype":"locality",
    "wof:population":100
},
  "geometry": {"coordinates":[80.823599,27.387054],"type":"Point"}
}