{
  "type": "Feature",
  "properties": {
    "iso:country":"IN",
    "ks:ks_alt_nam":"Pawar wasti",
    "ks:ks_name":"Pawar Wasti",
    "ks:ks_pop":36,
    "ks:ks_type":"HABITATION",
    "name:eng_x_preferred":[
        "Pawar Wasti"
    ],
    "wof:name":"Pawar Wasti",
    "wof:placetype":"locality",
    "wof:population":36
},
  "geometry": {"coordinates":[75.677812,18.668793],"type":"Point"}
}