{
  "type": "Feature",
  "properties": {
    "gn:admin1_code":"35.0",
    "gn:admin2_code":"455.0",
    "gn:asciiname":"Rewaldehi",
    "gn:country_code":"IN",
    "gn:dem":695,
    "gn:feature_class":"P",
    "gn:feature_code":"PPL",
    "gn:name":"Rewaldehi",
    "gn:population":0,
    "gn:timezone":"Asia/Kolkata",
    "iso:country":"IN",
    "wof:name":"Rewaldehi",
    "wof:placetype":"locality"
},
  "geometry": {"coordinates":[78.41063,21.99628],"type":"Point"}
}