{
  "type": "Feature",
  "properties": {
    "gn:admin1_code":"21",
    "gn:admin2_code":"375.0",
    "gn:asciiname":"Palaspal",
    "gn:country_code":"IN",
    "gn:dem":354,
    "gn:feature_class":"P",
    "gn:feature_code":"PPL",
    "gn:name":"Pal\u0101sp\u0101l",
    "gn:population":0,
    "gn:timezone":"Asia/Kolkata",
    "iso:country":"IN",
    "wof:name":"Palaspal",
    "wof:placetype":"locality"
},
  "geometry": {"coordinates":[85.76994000000001,21.21896],"type":"Point"}
}