{
  "type": "Feature",
  "properties": {
    "iso:country":"IN",
    "ks:ks_name":"Karandadi",
    "ks:ks_pop":210,
    "ks:ks_type":"HABITATION",
    "name:eng_x_preferred":[
        "Karandadi"
    ],
    "wof:name":"Karandadi",
    "wof:placetype":"locality",
    "wof:population":210
},
  "geometry": {"coordinates":[74.775115,13.22719],"type":"Point"}
}