{
  "type": "Feature",
  "properties": {
    "iso:country":"IN",
    "ks:ks_alt_nam":"Pasi tola",
    "ks:ks_name":"Pasi Tola",
    "ks:ks_pop":238,
    "ks:ks_type":"HABITATION",
    "name:eng_x_preferred":[
        "Pasi Tola"
    ],
    "wof:name":"Pasi Tola",
    "wof:placetype":"locality",
    "wof:population":238
},
  "geometry": {"coordinates":[83.757532,25.095694],"type":"Point"}
}