{
  "type": "Feature",
  "properties": {
    "iso:country":"IN",
    "ks:ks_name":"Khaneta Bichala",
    "ks:ks_pop":18,
    "ks:ks_type":"HABITATION",
    "name:eng_x_preferred":[
        "Khaneta Bichala"
    ],
    "wof:name":"Khaneta Bichala",
    "wof:placetype":"locality",
    "wof:population":18
},
  "geometry": {"coordinates":[78.823522,29.827966],"type":"Point"}
}