{
  "type": "Feature",
  "properties": {
    "iso:country":"IN",
    "ks:ks_name":"Lohar Tola",
    "ks:ks_pop":30,
    "ks:ks_type":"HABITATION",
    "name:eng_x_preferred":[
        "Lohar Tola"
    ],
    "wof:name":"Lohar Tola",
    "wof:placetype":"locality",
    "wof:population":30
},
  "geometry": {"coordinates":[83.248698,26.680195],"type":"Point"}
}