{
  "type": "Feature",
  "properties": {
    "iso:country":"IN",
    "ks:ks_name":"Khatkhati",
    "ks:ks_pop":147,
    "ks:ks_type":"HABITATION",
    "name:eng_x_preferred":[
        "Khatkhati"
    ],
    "wof:name":"Khatkhati",
    "wof:placetype":"locality",
    "wof:population":147
},
  "geometry": {"coordinates":[91.223573,25.898977],"type":"Point"}
}