{
  "type": "Feature",
  "properties": {
    "iso:country":"IN",
    "ks:ks_name":"Bikkatty",
    "ks:ks_pop":250,
    "ks:ks_type":"HABITATION",
    "ks:ks_uagg_main":0,
    "name:eng_x_preferred":[
        "Bikkatty"
    ],
    "wof:name":"Bikkatty",
    "wof:placetype":"neighbourhood",
    "wof:population":250
},
  "geometry": {"coordinates":[76.666037,11.220466],"type":"Point"}
}