{
  "type": "Feature",
  "properties": {
    "iso:country":"IN",
    "ks:ks_name":"Siddanakatta",
    "ks:ks_pop":5,
    "ks:ks_type":"HABITATION",
    "name:eng_x_preferred":[
        "Siddanakatta"
    ],
    "wof:name":"Siddanakatta",
    "wof:placetype":"locality",
    "wof:population":5
},
  "geometry": {"coordinates":[75.037694,14.913418],"type":"Point"}
}