{
  "type": "Feature",
  "properties": {
    "iso:country":"IN",
    "ks:ks_name":"Lalpur",
    "ks:ks_pop":272,
    "ks:ks_type":"VILLAGE",
    "name:eng_x_preferred":[
        "Lalpur"
    ],
    "wof:name":"Lalpur",
    "wof:placetype":"locality",
    "wof:population":272
},
  "geometry": {"coordinates":[88.409339,25.229422],"type":"Point"}
}