{
  "type": "Feature",
  "properties": {
    "gn:admin1_code":"28.0",
    "gn:admin2_code":"333.0",
    "gn:asciiname":"Punye",
    "gn:country_code":"IN",
    "gn:dem":31,
    "gn:feature_class":"P",
    "gn:feature_code":"PPL",
    "gn:name":"Punye",
    "gn:population":0,
    "gn:timezone":"Asia/Kolkata",
    "iso:country":"IN",
    "wof:name":"Punye",
    "wof:placetype":"neighbourhood"
},
  "geometry": {"coordinates":[87.94110999999999,24.09072],"type":"Point"}
}