{
  "type": "Feature",
  "properties": {
    "iso:country":"IN",
    "ks:ks_name":"Dmbarpur Urf Jatamalpur",
    "ks:ks_pop":29,
    "ks:ks_type":"VILLAGE",
    "name:eng_x_preferred":[
        "Dmbarpur Urf Jatamalpur"
    ],
    "wof:name":"Dmbarpur Urf Jatamalpur",
    "wof:placetype":"locality",
    "wof:population":29
},
  "geometry": {"coordinates":[83.81427499999999,26.510676],"type":"Point"}
}