{
  "type": "Feature",
  "properties": {
    "iso:country":"IN",
    "ks:ks_name":"Kolenilam",
    "ks:ks_pop":524,
    "ks:ks_type":"HABITATION",
    "name:eng_x_preferred":[
        "Kolenilam"
    ],
    "wof:name":"Kolenilam",
    "wof:placetype":"locality",
    "wof:population":524
},
  "geometry": {"coordinates":[76.147577,10.444289],"type":"Point"}
}