{
  "type": "Feature",
  "properties": {
    "gn:admin1_code":"35",
    "gn:admin2_code":"452.0",
    "gn:asciiname":"Thuhari Khurd",
    "gn:country_code":"IN",
    "gn:dem":465,
    "gn:feature_class":"P",
    "gn:feature_code":"PPL",
    "gn:name":"Thuh\u0101ri Khurd",
    "gn:population":0,
    "gn:timezone":"Asia/Kolkata",
    "iso:country":"IN",
    "ks:ks_name":"Thuwarikhurd",
    "ks:ks_pop":197,
    "ks:ks_type":"HABITATION",
    "name:eng_x_preferred":[
        "Thuwarikhurd"
    ],
    "name:eng_x_variant":[
        "Thuhari Khurd"
    ],
    "wof:name":"Thuwarikhurd",
    "wof:placetype":"locality",
    "wof:population":197
},
  "geometry": {"coordinates":[79.37353899999999,22.773666],"type":"Point"}
}