{
  "type": "Feature",
  "properties": {
    "gn:admin1_code":"9",
    "gn:admin2_code":"485.0",
    "gn:asciiname":"Kocher",
    "gn:country_code":"IN",
    "gn:dem":331,
    "gn:feature_class":"P",
    "gn:feature_code":"PPL",
    "gn:name":"Kocher",
    "gn:population":0,
    "gn:timezone":"Asia/Kolkata",
    "iso:country":"IN",
    "name:bul_x_preferred":[
        "\u041a\u043e\u0445\u0435\u0440"
    ],
    "name:ceb_x_preferred":[
        "Kocher"
    ],
    "name:chv_x_preferred":[
        "\u041a\u043e\u0445\u0435\u0440"
    ],
    "name:dan_x_preferred":[
        "Kocher"
    ],
    "name:deu_x_preferred":[
        "Kocher"
    ],
    "name:epo_x_preferred":[
        "Kocher"
    ],
    "name:fin_x_preferred":[
        "Kocher"
    ],
    "name:fra_x_preferred":[
        "Kocher"
    ],
    "name:jpn_x_preferred":[
        "\u30b3\u30c3\u30cf\u30fc\u5ddd"
    ],
    "name:lat_x_preferred":[
        "Cochera"
    ],
    "name:lit_x_preferred":[
        "Kocheris"
    ],
    "name:mkd_x_preferred":[
        "\u041a\u043e\u0445\u0435\u0440"
    ],
    "name:nld_x_preferred":[
        "Kocher"
    ],
    "name:nno_x_preferred":[
        "Kocher"
    ],
    "name:pol_x_preferred":[
        "Kocher"
    ],
    "name:ron_x_preferred":[
        "Kocher"
    ],
    "name:rus_x_preferred":[
        "\u041a\u043e\u0445\u0435\u0440"
    ],
    "name:srp_x_preferred":[
        "\u041a\u043e\u0445\u0435\u0440"
    ],
    "name:swe_x_preferred":[
        "Kocher"
    ],
    "name:ukr_x_preferred":[
        "\u041a\u043e\u0445\u0435\u0440"
    ],
    "name:zho_x_preferred":[
        "\u79d1\u8d6b\u723e\u6cb3"
    ],
    "wof:name":"Kocher",
    "wof:placetype":"locality"
},
  "geometry": {"coordinates":[74.06005999999999,23.04584],"type":"Point"}
}