{
  "type": "Feature",
  "properties": {
    "iso:country":"IN",
    "ks:ks_name":"Gazipur Patna",
    "ks:ks_pop":1796,
    "ks:ks_type":"VILLAGE",
    "name:eng_x_preferred":[
        "Gazipur Patna"
    ],
    "wof:name":"Gazipur Patna",
    "wof:placetype":"locality",
    "wof:population":1796
},
  "geometry": {"coordinates":[87.32406400000001,21.913536],"type":"Point"}
}