{
  "type": "Feature",
  "properties": {
    "iso:country":"IN",
    "ks:ks_name":"Kendmal",
    "ks:ks_pop":200,
    "ks:ks_type":"HABITATION",
    "name:eng_x_preferred":[
        "Kendmal"
    ],
    "wof:name":"Kendmal",
    "wof:placetype":"locality",
    "wof:population":200
},
  "geometry": {"coordinates":[84.11333500000001,21.778209],"type":"Point"}
}