{
  "type": "Feature",
  "properties": {
    "iso:country":"IN",
    "ks:ks_name":"Ahiran Purwa",
    "ks:ks_pop":510,
    "ks:ks_type":"HABITATION",
    "name:eng_x_preferred":[
        "Ahiran Purwa"
    ],
    "wof:name":"Ahiran Purwa",
    "wof:placetype":"locality",
    "wof:population":510
},
  "geometry": {"coordinates":[80.972657,25.275688],"type":"Point"}
}