{
  "type": "Feature",
  "properties": {
    "iso:country":"IN",
    "ks:ks_name":"Tengahra",
    "ks:ks_pop":2912,
    "ks:ks_type":"VILLAGE",
    "ks:ks_uagg_main":0,
    "name:eng_x_preferred":[
        "Tengahra"
    ],
    "wof:name":"Tengahra",
    "wof:placetype":"neighbourhood",
    "wof:population":2912
},
  "geometry": {"coordinates":[86.403192,25.00048],"type":"Point"}
}