{
  "type": "Feature",
  "properties": {
    "iso:country":"IN",
    "ks:ks_name":"Pure Chandrapal",
    "ks:ks_pop":146,
    "ks:ks_type":"HABITATION",
    "name:eng_x_preferred":[
        "Pure Chandrapal"
    ],
    "wof:name":"Pure Chandrapal",
    "wof:placetype":"locality",
    "wof:population":146
},
  "geometry": {"coordinates":[81.005545,26.26358],"type":"Point"}
}