{
  "type": "Feature",
  "properties": {
    "iso:country":"IN",
    "ks:ks_name":"Chak Dalar",
    "ks:ks_pop":346,
    "ks:ks_type":"VILLAGE",
    "name:eng_x_preferred":[
        "Chak Dalar"
    ],
    "wof:name":"Chak Dalar",
    "wof:placetype":"locality",
    "wof:population":346
},
  "geometry": {"coordinates":[79.754227,29.37904],"type":"Point"}
}