{
  "type": "Feature",
  "properties": {
    "gn:admin1_code":"09",
    "gn:admin2_code":"481.0",
    "gn:asciiname":"Samadhiala",
    "gn:country_code":"IN",
    "gn:dem":60,
    "gn:feature_class":"P",
    "gn:feature_code":"PPL",
    "gn:name":"Sam\u0101dhi\u0101la",
    "gn:population":0,
    "gn:timezone":"Asia/Kolkata",
    "iso:country":"IN",
    "wof:name":"Samadhiala",
    "wof:placetype":"locality"
},
  "geometry": {"coordinates":[71.89317,21.291],"type":"Point"}
}