{
  "type": "Feature",
  "properties": {
    "gn:admin1_code":"16.0",
    "gn:admin2_code":"504.0",
    "gn:asciiname":"Choti Dhawdi",
    "gn:country_code":"IN",
    "gn:dem":457,
    "gn:feature_class":"P",
    "gn:feature_code":"PPL",
    "gn:name":"Choti Dh\u0101wdi",
    "gn:population":0,
    "gn:timezone":"Asia/Kolkata",
    "iso:country":"IN",
    "wof:name":"Choti Dhawdi",
    "wof:placetype":"neighbourhood"
},
  "geometry": {"coordinates":[78.41254000000001,21.12767],"type":"Point"}
}