{
  "type": "Feature",
  "properties": {
    "iso:country":"IN",
    "ks:ks_name":"Tawa",
    "ks:ks_pop":1649,
    "ks:ks_type":"VILLAGE",
    "name:eng_x_preferred":[
        "Tawa"
    ],
    "wof:name":"Tawa",
    "wof:placetype":"locality",
    "wof:population":1649
},
  "geometry": {"coordinates":[72.95236300000001,19.868884],"type":"Point"}
}