{
  "type": "Feature",
  "properties": {
    "iso:country":"IN",
    "ks:ks_alt_nam":"BADAL GOVIND",
    "ks:ks_name":"Badal Govind",
    "ks:ks_pop":16,
    "ks:ks_type":"HABITATION",
    "ks:ks_uagg_main":0,
    "name:eng_x_preferred":[
        "Badal Govind"
    ],
    "wof:name":"Badal Govind",
    "wof:placetype":"neighbourhood",
    "wof:population":16
},
  "geometry": {"coordinates":[81.614645,26.300607],"type":"Point"}
}