{
  "type": "Feature",
  "properties": {
    "gn:admin1_code":"35.0",
    "gn:admin2_code":"449.0",
    "gn:asciiname":"Renjakhera",
    "gn:country_code":"IN",
    "gn:dem":344,
    "gn:feature_class":"P",
    "gn:feature_code":"PPL",
    "gn:name":"Renj\u0101khera",
    "gn:population":0,
    "gn:timezone":"Asia/Kolkata",
    "iso:country":"IN",
    "ks:ks_alt_nam":"Renj\u0101khera",
    "ks:ks_name":"Renjakhera",
    "ks:ks_type":"VILLAGE",
    "name:eng_x_preferred":[
        "Renjakhera"
    ],
    "name:eng_x_variant":[
        "Renj\u0101khera"
    ],
    "wof:name":"Renjakhera",
    "wof:placetype":"locality"
},
  "geometry": {"coordinates":[78.210683,22.667844],"type":"Point"}
}