{
  "type": "Feature",
  "properties": {
    "iso:country":"IN",
    "ks:ks_name":"Addagutta",
    "ks:ks_pop":160,
    "ks:ks_type":"HABITATION",
    "name:eng_x_preferred":[
        "Addagutta"
    ],
    "wof:name":"Addagutta",
    "wof:placetype":"locality",
    "wof:population":160
},
  "geometry": {"coordinates":[78.64669499999999,19.644467],"type":"Point"}
}