{
  "type": "Feature",
  "properties": {
    "iso:country":"IN",
    "ks:ks_name":"Lundru",
    "ks:ks_pop":105,
    "ks:ks_type":"VILLAGE",
    "name:eng_x_preferred":[
        "Lundru"
    ],
    "wof:name":"Lundru",
    "wof:placetype":"locality",
    "wof:population":105
},
  "geometry": {"coordinates":[83.785212,20.462708],"type":"Point"}
}