{
  "type": "Feature",
  "properties": {
    "iso:country":"IN",
    "ks:ks_name":"Hori Purwa",
    "ks:ks_pop":187,
    "ks:ks_type":"HABITATION",
    "ks:ks_uagg_main":0,
    "name:eng_x_preferred":[
        "Hori Purwa"
    ],
    "wof:name":"Hori Purwa",
    "wof:placetype":"neighbourhood",
    "wof:population":187
},
  "geometry": {"coordinates":[80.747317,27.148034],"type":"Point"}
}