{
  "type": "Feature",
  "properties": {
    "iso:country":"IN",
    "ks:ks_alt_nam":"Barahman tola",
    "ks:ks_name":"Barahman Tola",
    "ks:ks_pop":400,
    "ks:ks_type":"HABITATION",
    "name:eng_x_preferred":[
        "Barahman Tola"
    ],
    "wof:name":"Barahman Tola",
    "wof:placetype":"locality",
    "wof:population":400
},
  "geometry": {"coordinates":[83.825433,25.333233],"type":"Point"}
}