{
  "type": "Feature",
  "properties": {
    "gn:admin1_code":"23.0",
    "gn:admin2_code":"50.0",
    "gn:asciiname":"Sito Ma Jhuggian",
    "gn:country_code":"IN",
    "gn:dem":205,
    "gn:feature_class":"P",
    "gn:feature_code":"PPL",
    "gn:name":"S\u012bto Ma Jhuggi\u0101n",
    "gn:population":0,
    "gn:timezone":"Asia/Kolkata",
    "iso:country":"IN",
    "wof:name":"Sito Ma Jhuggian",
    "wof:placetype":"locality"
},
  "geometry": {"coordinates":[74.79559,31.16073],"type":"Point"}
}