{
  "type": "Feature",
  "properties": {
    "gn:admin1_code":"38",
    "gn:admin2_code":"346.0",
    "gn:asciiname":"Patsi",
    "gn:country_code":"IN",
    "gn:dem":184,
    "gn:feature_class":"P",
    "gn:feature_code":"PPL",
    "gn:name":"P\u0101tsi",
    "gn:population":0,
    "gn:timezone":"Asia/Kolkata",
    "iso:country":"IN",
    "ks:ks_name":"Patsi",
    "ks:ks_pop":170,
    "ks:ks_type":"VILLAGE",
    "ks:ks_uagg_main":0,
    "name:eng_x_preferred":[
        "Patsi"
    ],
    "wof:name":"Patsi",
    "wof:placetype":"neighbourhood",
    "wof:population":170
},
  "geometry": {"coordinates":[83.848249,24.235909],"type":"Point"}
}