{
  "type": "Feature",
  "properties": {
    "iso:country":"IN",
    "ks:ks_name":"Kadasseri",
    "ks:ks_pop":973,
    "ks:ks_type":"HABITATION",
    "name:eng_x_preferred":[
        "Kadasseri"
    ],
    "wof:name":"Kadasseri",
    "wof:placetype":"locality",
    "wof:population":973
},
  "geometry": {"coordinates":[76.214276,11.524294],"type":"Point"}
}