{
  "type": "Feature",
  "properties": {
    "iso:country":"IN",
    "ks:ks_name":"Bandega",
    "ks:ks_pop":281,
    "ks:ks_type":"VILLAGE",
    "name:eng_x_preferred":[
        "Bandega"
    ],
    "wof:name":"Bandega",
    "wof:placetype":"locality",
    "wof:population":281
},
  "geometry": {"coordinates":[83.63772299999999,22.138479],"type":"Point"}
}