{
  "type": "Feature",
  "properties": {
    "iso:country":"IN",
    "ks:ks_name":"Kananpara",
    "ks:ks_pop":1446,
    "ks:ks_type":"HABITATION",
    "ks:ks_uagg_main":0,
    "name:eng_x_preferred":[
        "Kananpara"
    ],
    "wof:name":"Kananpara",
    "wof:placetype":"neighbourhood",
    "wof:population":1446
},
  "geometry": {"coordinates":[87.890827,25.367056],"type":"Point"}
}