{
  "type": "Feature",
  "properties": {
    "iso:country":"IN",
    "ks:ks_name":"Rukumuddinpur",
    "ks:ks_pop":272,
    "ks:ks_type":"HABITATION",
    "name:eng_x_preferred":[
        "Rukumuddinpur"
    ],
    "wof:name":"Rukumuddinpur",
    "wof:placetype":"locality",
    "wof:population":272
},
  "geometry": {"coordinates":[83.186466,26.225997],"type":"Point"}
}