{
  "type": "Feature",
  "properties": {
    "iso:country":"IN",
    "ks:ks_name":"Ellankiraipatty",
    "ks:ks_pop":265,
    "ks:ks_type":"HABITATION",
    "name:eng_x_preferred":[
        "Ellankiraipatty"
    ],
    "wof:name":"Ellankiraipatty",
    "wof:placetype":"locality",
    "wof:population":265
},
  "geometry": {"coordinates":[78.349289,11.250346],"type":"Point"}
}