{
  "type": "Feature",
  "properties": {
    "iso:country":"IN",
    "ks:ks_name":"Peyadikottai",
    "ks:ks_pop":160,
    "ks:ks_type":"HABITATION",
    "name:eng_x_preferred":[
        "Peyadikottai"
    ],
    "wof:name":"Peyadikottai",
    "wof:placetype":"locality",
    "wof:population":160
},
  "geometry": {"coordinates":[79.032196,9.895394],"type":"Point"}
}