{
  "type": "Feature",
  "properties": {
    "gn:admin1_code":"19",
    "gn:admin2_code":"559.0",
    "gn:asciiname":"Kasamdoddi",
    "gn:country_code":"IN",
    "gn:dem":509,
    "gn:feature_class":"P",
    "gn:feature_code":"PPL",
    "gn:name":"K\u0101samdoddi",
    "gn:population":0,
    "gn:timezone":"Asia/Kolkata",
    "iso:country":"IN",
    "ks:ks_name":"Kasan Doddi",
    "ks:ks_pop":1387,
    "ks:ks_type":"VILLAGE",
    "name:eng_x_preferred":[
        "Kasan Doddi"
    ],
    "name:eng_x_variant":[
        "Kasamdoddi"
    ],
    "wof:name":"Kasan Doddi",
    "wof:placetype":"locality",
    "wof:population":1387
},
  "geometry": {"coordinates":[76.856075,16.190421],"type":"Point"}
}