{
  "type": "Feature",
  "properties": {
    "gn:admin1_code":"10.0",
    "gn:admin2_code":"86.0",
    "gn:asciiname":"Langra",
    "gn:country_code":"IN",
    "gn:dem":253,
    "gn:feature_class":"P",
    "gn:feature_code":"PPL",
    "gn:name":"Langra",
    "gn:population":0,
    "gn:timezone":"Asia/Kolkata",
    "iso:country":"IN",
    "wof:name":"Langra",
    "wof:placetype":"locality"
},
  "geometry": {"coordinates":[76.90089999999999,28.28309],"type":"Point"}
}