{
  "type": "Feature",
  "properties": {
    "iso:country":"IN",
    "ks:ks_name":"2 Mile",
    "ks:ks_pop":488,
    "ks:ks_type":"HABITATION",
    "name:eng_x_preferred":[
        "2 Mile"
    ],
    "wof:name":"2 Mile",
    "wof:placetype":"locality",
    "wof:population":488
},
  "geometry": {"coordinates":[93.781435,26.046995],"type":"Point"}
}