{
  "type": "Feature",
  "properties": {
    "iso:country":"IN",
    "ks:ks_name":"Jerpai No 2",
    "ks:ks_pop":330,
    "ks:ks_type":"HABITATION",
    "name:eng_x_preferred":[
        "Jerpai No 2"
    ],
    "wof:name":"Jerpai No 2",
    "wof:placetype":"locality",
    "wof:population":330
},
  "geometry": {"coordinates":[94.061171,26.429394],"type":"Point"}
}