{
  "type": "Feature",
  "properties": {
    "gn:admin1_code":"40.0",
    "gn:admin2_code":"534.0",
    "gn:asciiname":"Kottapalli",
    "gn:country_code":"IN",
    "gn:dem":140,
    "gn:feature_class":"P",
    "gn:feature_code":"PPL",
    "gn:name":"Kottapalli",
    "gn:population":0,
    "gn:timezone":"Asia/Kolkata",
    "iso:country":"IN",
    "ks:ks_name":"Kothapalle",
    "ks:ks_pop":317,
    "ks:ks_type":"VILLAGE",
    "ks:ks_uagg_main":0,
    "name:eng_x_preferred":[
        "Kothapalle"
    ],
    "wof:name":"Kothapalle",
    "wof:placetype":"locality",
    "wof:population":317
},
  "geometry": {"coordinates":[79.405463,18.873062],"type":"Point"}
}