{
  "type": "Feature",
  "properties": {
    "iso:country":"IN",
    "ks:ks_name":"Jamirdiha",
    "ks:ks_pop":239,
    "ks:ks_type":"VILLAGE",
    "name:eng_x_preferred":[
        "Jamirdiha"
    ],
    "wof:name":"Jamirdiha",
    "wof:placetype":"locality",
    "wof:population":239
},
  "geometry": {"coordinates":[86.751383,22.300836],"type":"Point"}
}