{
  "type": "Feature",
  "properties": {
    "gn:admin1_code":"23.0",
    "gn:admin2_code":"54.0",
    "gn:asciiname":"Bhaddalwadh",
    "gn:country_code":"IN",
    "gn:dem":233,
    "gn:feature_class":"P",
    "gn:feature_code":"PPL",
    "gn:name":"Bhaddalwadh",
    "gn:population":0,
    "gn:timezone":"Asia/Kolkata",
    "iso:country":"IN",
    "wof:name":"Bhaddalwadh",
    "wof:placetype":"locality"
},
  "geometry": {"coordinates":[75.56905,30.42496],"type":"Point"}
}