{
  "type": "Feature",
  "properties": {
    "iso:country":"IN",
    "ks:ks_name":"Guttakindavenkatapuram",
    "ks:ks_pop":91,
    "ks:ks_type":"HABITATION",
    "name:eng_x_preferred":[
        "Guttakindavenkatapuram"
    ],
    "wof:name":"Guttakindavenkatapuram",
    "wof:placetype":"locality",
    "wof:population":91
},
  "geometry": {"coordinates":[79.22756099999999,13.198588],"type":"Point"}
}