{
  "type": "Feature",
  "properties": {
    "iso:country":"IN",
    "ks:ks_name":"Undi",
    "ks:ks_pop":317,
    "ks:ks_type":"VILLAGE",
    "name:eng_x_preferred":[
        "Undi"
    ],
    "wof:name":"Undi",
    "wof:placetype":"locality",
    "wof:population":317
},
  "geometry": {"coordinates":[73.24175,17.235616],"type":"Point"}
}