{
  "type": "Feature",
  "properties": {
    "iso:country":"IN",
    "ks:ks_name":"Data",
    "ks:ks_pop":304,
    "ks:ks_type":"VILLAGE",
    "name:eng_x_preferred":[
        "Data"
    ],
    "wof:name":"Data",
    "wof:placetype":"locality",
    "wof:population":304
},
  "geometry": {"coordinates":[75.711035,31.755431],"type":"Point"}
}