{
  "type": "Feature",
  "properties": {
    "iso:country":"IN",
    "ks:ks_alt_nam":"Jabl\u0101",
    "ks:ks_name":"Jabla",
    "ks:ks_pop":418,
    "ks:ks_type":"VILLAGE",
    "name:eng_x_preferred":[
        "Jabla"
    ],
    "name:eng_x_variant":[
        "Jabl\u0101"
    ],
    "wof:name":"Jabla",
    "wof:placetype":"locality",
    "wof:population":418
},
  "geometry": {"coordinates":[85.85681200000001,23.352233],"type":"Point"}
}