{
  "type": "Feature",
  "properties": {
    "iso:country":"IN",
    "ks:ks_name":"Anthili",
    "ks:ks_pop":673,
    "ks:ks_type":"VILLAGE",
    "name:eng_x_preferred":[
        "Anthili"
    ],
    "wof:name":"Anthili",
    "wof:placetype":"locality",
    "wof:population":673
},
  "geometry": {"coordinates":[83.895915,18.64526],"type":"Point"}
}