{
  "type": "Feature",
  "properties": {
    "iso:country":"IN",
    "ks:ks_alt_nam":"Duka saud",
    "ks:ks_name":"Duka Saud",
    "ks:ks_pop":8,
    "ks:ks_type":"HABITATION",
    "name:eng_x_preferred":[
        "Duka Saud"
    ],
    "wof:name":"Duka Saud",
    "wof:placetype":"locality",
    "wof:population":8
},
  "geometry": {"coordinates":[79.14648,30.33471],"type":"Point"}
}