{
  "type": "Feature",
  "properties": {
    "gn:admin1_code":"34.0",
    "gn:admin2_code":"237.0",
    "gn:asciiname":"Murehta Chak",
    "gn:country_code":"IN",
    "gn:dem":111,
    "gn:feature_class":"P",
    "gn:feature_code":"PPL",
    "gn:name":"Murehta Chak",
    "gn:population":0,
    "gn:timezone":"Asia/Kolkata",
    "iso:country":"IN",
    "ks:ks_name":"Murehta Chak",
    "ks:ks_type":"VILLAGE",
    "name:eng_x_preferred":[
        "Murehta Chak"
    ],
    "wof:name":"Murehta Chak",
    "wof:placetype":"locality"
},
  "geometry": {"coordinates":[85.351623,24.787793],"type":"Point"}
}