{
  "type": "Feature",
  "properties": {
    "gn:admin1_code":"9.0",
    "gn:admin2_code":"486.0",
    "gn:asciiname":"Rendi",
    "gn:country_code":"IN",
    "gn:dem":256,
    "gn:feature_class":"P",
    "gn:feature_code":"PPL",
    "gn:name":"Rendi",
    "gn:population":0,
    "gn:timezone":"Asia/Kolkata",
    "iso:country":"IN",
    "wof:name":"Rendi",
    "wof:placetype":"locality"
},
  "geometry": {"coordinates":[74.09214,22.0505],"type":"Point"}
}