{
  "type": "Feature",
  "properties": {
    "iso:country":"IN",
    "ks:ks_name":"Karma",
    "ks:ks_pop":520,
    "ks:ks_type":"HABITATION",
    "name:eng_x_preferred":[
        "Karma"
    ],
    "wof:name":"Karma",
    "wof:placetype":"locality",
    "wof:population":520
},
  "geometry": {"coordinates":[85.729179,23.886455],"type":"Point"}
}