{
  "type": "Feature",
  "properties": {
    "gn:admin1_code":"35",
    "gn:admin2_code":"461.0",
    "gn:asciiname":"Patheti",
    "gn:country_code":"IN",
    "gn:dem":911,
    "gn:feature_class":"P",
    "gn:feature_code":"PPL",
    "gn:name":"Patheti",
    "gn:population":0,
    "gn:timezone":"Asia/Kolkata",
    "iso:country":"IN",
    "wof:name":"Patheti",
    "wof:placetype":"locality"
},
  "geometry": {"coordinates":[81.63464999999999,22.85817],"type":"Point"}
}