{
  "type": "Feature",
  "properties": {
    "iso:country":"IN",
    "ks:ks_name":"Hunasekatte",
    "ks:ks_pop":32,
    "ks:ks_type":"HABITATION",
    "name:eng_x_preferred":[
        "Hunasekatte"
    ],
    "wof:name":"Hunasekatte",
    "wof:placetype":"locality",
    "wof:population":32
},
  "geometry": {"coordinates":[75.980278,12.551111],"type":"Point"}
}