{
  "type": "Feature",
  "properties": {
    "iso:country":"IN",
    "ks:ks_name":"Kolhua",
    "ks:ks_pop":557,
    "ks:ks_type":"VILLAGE",
    "name:eng_x_preferred":[
        "Kolhua"
    ],
    "wof:name":"Kolhua",
    "wof:placetype":"locality",
    "wof:population":557
},
  "geometry": {"coordinates":[82.641752,23.825041],"type":"Point"}
}