{
  "type": "Feature",
  "properties": {
    "iso:country":"IN",
    "ks:ks_name":"Dani Chak",
    "ks:ks_pop":0,
    "ks:ks_type":"VILLAGE",
    "name:eng_x_preferred":[
        "Dani Chak"
    ],
    "wof:name":"Dani Chak",
    "wof:placetype":"locality",
    "wof:population":0
},
  "geometry": {"coordinates":[85.659462,25.011849],"type":"Point"}
}