{
  "type": "Feature",
  "properties": {
    "iso:country":"IN",
    "ks:ks_name":"Hayatpur",
    "ks:ks_pop":36,
    "ks:ks_type":"VILLAGE",
    "name:eng_x_preferred":[
        "Hayatpur"
    ],
    "wof:name":"Hayatpur",
    "wof:placetype":"locality",
    "wof:population":36
},
  "geometry": {"coordinates":[86.346615,20.359131],"type":"Point"}
}