{
  "type": "Feature",
  "properties": {
    "iso:country":"IN",
    "ks:ks_name":"Surkhand",
    "ks:ks_pop":491,
    "ks:ks_type":"VILLAGE",
    "name:eng_x_preferred":[
        "Surkhand"
    ],
    "wof:name":"Surkhand",
    "wof:placetype":"locality",
    "wof:population":491
},
  "geometry": {"coordinates":[74.235361,24.408042],"type":"Point"}
}