{
  "type": "Feature",
  "properties": {
    "iso:country":"IN",
    "ks:ks_name":"Jiankata",
    "ks:ks_pop":206,
    "ks:ks_type":"VILLAGE",
    "ks:ks_uagg_main":0,
    "name:eng_x_preferred":[
        "Jiankata"
    ],
    "wof:name":"Jiankata",
    "wof:placetype":"neighbourhood",
    "wof:population":206
},
  "geometry": {"coordinates":[84.422966,20.623394],"type":"Point"}
}