{
  "type": "Feature",
  "properties": {
    "iso:country":"IN",
    "ks:ks_name":"Anjaneyapura",
    "ks:ks_pop":668,
    "ks:ks_type":"HABITATION",
    "name:eng_x_preferred":[
        "Anjaneyapura"
    ],
    "wof:name":"Anjaneyapura",
    "wof:placetype":"locality",
    "wof:population":668
},
  "geometry": {"coordinates":[75.711,14.23],"type":"Point"}
}