{
  "type": "Feature",
  "properties": {
    "iso:country":"IN",
    "ks:ks_alt_nam":"U.Kuruba nal",
    "ks:ks_name":"U.kuruba Nal",
    "ks:ks_pop":816,
    "ks:ks_type":"HABITATION",
    "name:eng_x_preferred":[
        "U.kuruba Nal"
    ],
    "wof:name":"U.kuruba Nal",
    "wof:placetype":"locality",
    "wof:population":816
},
  "geometry": {"coordinates":[76.193566,15.705934],"type":"Point"}
}