{
  "type": "Feature",
  "properties": {
    "gn:admin1_code":"11",
    "gn:admin2_code":"24.0",
    "gn:asciiname":"Kupar Lahr",
    "gn:country_code":"IN",
    "gn:dem":637,
    "gn:feature_class":"P",
    "gn:feature_code":"PPL",
    "gn:name":"Kupar L\u0101hr",
    "gn:population":0,
    "gn:timezone":"Asia/Kolkata",
    "iso:country":"IN",
    "wof:name":"Kupar Lahr",
    "wof:placetype":"locality"
},
  "geometry": {"coordinates":[76.25078000000001,32.04767],"type":"Point"}
}