{
  "type": "Feature",
  "properties": {
    "iso:country":"IN",
    "ks:ks_name":"Sadewadi",
    "ks:ks_pop":58,
    "ks:ks_type":"HABITATION",
    "name:eng_x_preferred":[
        "Sadewadi"
    ],
    "wof:name":"Sadewadi",
    "wof:placetype":"locality",
    "wof:population":58
},
  "geometry": {"coordinates":[73.402906,17.554208],"type":"Point"}
}