{
  "type": "Feature",
  "properties": {
    "iso:country":"IN",
    "ks:ks_name":"Marathewadi",
    "ks:ks_pop":32,
    "ks:ks_type":"HABITATION",
    "name:eng_x_preferred":[
        "Marathewadi"
    ],
    "wof:name":"Marathewadi",
    "wof:placetype":"locality",
    "wof:population":32
},
  "geometry": {"coordinates":[73.637925,16.574844],"type":"Point"}
}