{
  "type": "Feature",
  "properties": {
    "iso:country":"IN",
    "ks:ks_name":"Saraighata",
    "ks:ks_pop":788,
    "ks:ks_type":"VILLAGE",
    "name:eng_x_preferred":[
        "Saraighata"
    ],
    "wof:name":"Saraighata",
    "wof:placetype":"locality",
    "wof:population":788
},
  "geometry": {"coordinates":[87.72770300000001,22.35884],"type":"Point"}
}