{
  "type": "Feature",
  "properties": {
    "iso:country":"IN",
    "ks:ks_name":"Godigaon",
    "ks:ks_pop":556,
    "ks:ks_type":"VILLAGE",
    "ks:ks_uagg_main":0,
    "name:eng_x_preferred":[
        "Godigaon"
    ],
    "wof:name":"Godigaon",
    "wof:placetype":"neighbourhood",
    "wof:population":556
},
  "geometry": {"coordinates":[82.20712,24.589045],"type":"Point"}
}