{
  "type": "Feature",
  "properties": {
    "iso:country":"IN",
    "ks:ks_name":"Vishnoiyon Ki Dhani",
    "ks:ks_pop":630,
    "ks:ks_type":"VILLAGE",
    "name:eng_x_preferred":[
        "Vishnoiyon Ki Dhani"
    ],
    "wof:name":"Vishnoiyon Ki Dhani",
    "wof:placetype":"locality",
    "wof:population":630
},
  "geometry": {"coordinates":[73.186283,26.317875],"type":"Point"}
}