{
  "type": "Feature",
  "properties": {
    "iso:country":"IN",
    "ks:ks_alt_nam":"DHANGAR DIH",
    "ks:ks_name":"Dhangar Dih",
    "ks:ks_pop":279,
    "ks:ks_type":"HABITATION",
    "name:eng_x_preferred":[
        "Dhangar Dih"
    ],
    "wof:name":"Dhangar Dih",
    "wof:placetype":"locality",
    "wof:population":279
},
  "geometry": {"coordinates":[83.654557,24.717825],"type":"Point"}
}