{
  "type": "Feature",
  "properties": {
    "gn:admin1_code":"40",
    "gn:admin2_code":"540.0",
    "gn:asciiname":"Chingapur",
    "gn:country_code":"IN",
    "gn:dem":210,
    "gn:feature_class":"P",
    "gn:feature_code":"PPL",
    "gn:name":"Ching\u0101pur",
    "gn:population":0,
    "gn:timezone":"Asia/Kolkata",
    "iso:country":"IN",
    "wof:name":"Chingapur",
    "wof:placetype":"locality"
},
  "geometry": {"coordinates":[79.96297,17.59045],"type":"Point"}
}