{
  "type": "Feature",
  "properties": {
    "iso:country":"IN",
    "ks:ks_name":"Atwa",
    "ks:ks_pop":157,
    "ks:ks_type":"HABITATION",
    "ks:ks_uagg_main":0,
    "name:eng_x_preferred":[
        "Atwa"
    ],
    "wof:name":"Atwa",
    "wof:placetype":"neighbourhood",
    "wof:population":157
},
  "geometry": {"coordinates":[81.28021099999999,26.907787],"type":"Point"}
}