{
  "type": "Feature",
  "properties": {
    "iso:country":"IN",
    "ks:ks_name":"Mandi Samiti",
    "ks:ks_pop":265,
    "ks:ks_type":"HABITATION",
    "ks:ks_uagg_main":0,
    "name:eng_x_preferred":[
        "Mandi Samiti"
    ],
    "wof:name":"Mandi Samiti",
    "wof:placetype":"neighbourhood",
    "wof:population":265
},
  "geometry": {"coordinates":[83.572479,26.750002],"type":"Point"}
}