{
  "type": "Feature",
  "properties": {
    "iso:country":"IN",
    "ks:ks_name":"Seenankudi",
    "ks:ks_pop":527,
    "ks:ks_type":"HABITATION",
    "name:eng_x_preferred":[
        "Seenankudi"
    ],
    "wof:name":"Seenankudi",
    "wof:placetype":"locality",
    "wof:population":527
},
  "geometry": {"coordinates":[78.79895,9.662073],"type":"Point"}
}