{
  "type": "Feature",
  "properties": {
    "gn:admin1_code":"21.0",
    "gn:admin2_code":"399.0",
    "gn:asciiname":"Lomtaput",
    "gn:country_code":"IN",
    "gn:dem":273,
    "gn:feature_class":"P",
    "gn:feature_code":"PPL",
    "gn:name":"Lomt\u0101put",
    "gn:population":0,
    "gn:timezone":"Asia/Kolkata",
    "iso:country":"IN",
    "ks:ks_name":"Lamataput",
    "ks:ks_pop":530,
    "ks:ks_type":"VILLAGE",
    "name:eng_x_preferred":[
        "Lamataput"
    ],
    "name:eng_x_variant":[
        "Lomtaput"
    ],
    "wof:name":"Lamataput",
    "wof:placetype":"locality",
    "wof:population":530
},
  "geometry": {"coordinates":[82.245167,18.501894],"type":"Point"}
}