{
  "type": "Feature",
  "properties": {
    "iso:country":"IN",
    "ks:ks_name":"Kodiyar Gaon",
    "ks:ks_pop":10,
    "ks:ks_type":"HABITATION",
    "name:eng_x_preferred":[
        "Kodiyar Gaon"
    ],
    "wof:name":"Kodiyar Gaon",
    "wof:placetype":"locality",
    "wof:population":10
},
  "geometry": {"coordinates":[78.76993899999999,30.021772],"type":"Point"}
}