{
  "type": "Feature",
  "properties": {
    "iso:country":"IN",
    "ks:ks_name":"Kol Basti",
    "ks:ks_pop":358,
    "ks:ks_type":"HABITATION",
    "ks:ks_uagg_main":0,
    "name:eng_x_preferred":[
        "Kol Basti"
    ],
    "wof:name":"Kol Basti",
    "wof:placetype":"neighbourhood",
    "wof:population":358
},
  "geometry": {"coordinates":[82.94086799999999,24.870813],"type":"Point"}
}