{
  "type": "Feature",
  "properties": {
    "iso:country":"IN",
    "qs:name":"Katra Lal Ganj",
    "qs:name_adm0":"India",
    "qs:name_adm1":"Uttar Pradesh",
    "qs:photos":6,
    "qs:photos_1k":1,
    "qs:photos_9k":1,
    "qs:photos_9r":1,
    "qs:photos_all":6,
    "qs:photos_sr":1,
    "qs:placetype":"Town",
    "qs:pop_sr":"0",
    "wof:name":"Katra Lal Ganj",
    "wof:placetype":"locality"
},
  "geometry": {"coordinates":[81.692826,26.207894],"type":"Point"}
}