{
  "type": "Feature",
  "properties": {
    "iso:country":"IN",
    "ks:ks_name":"Thelappuzhakadavu",
    "ks:ks_pop":820,
    "ks:ks_type":"HABITATION",
    "name:eng_x_preferred":[
        "Thelappuzhakadavu"
    ],
    "wof:name":"Thelappuzhakadavu",
    "wof:placetype":"locality",
    "wof:population":820
},
  "geometry": {"coordinates":[76.699742,9.453322],"type":"Point"}
}