{
  "type": "Feature",
  "properties": {
    "iso:country":"IN",
    "ks:ks_name":"Jokalundi",
    "ks:ks_pop":130,
    "ks:ks_type":"VILLAGE",
    "name:eng_x_preferred":[
        "Jokalundi"
    ],
    "wof:name":"Jokalundi",
    "wof:placetype":"locality",
    "wof:population":130
},
  "geometry": {"coordinates":[84.90623600000001,19.707858],"type":"Point"}
}