{
  "type": "Feature",
  "properties": {
    "iso:country":"IN",
    "ks:ks_name":"Madanapallivari Indlu",
    "ks:ks_pop":52,
    "ks:ks_type":"HABITATION",
    "ks:ks_uagg_main":0,
    "name:eng_x_preferred":[
        "Madanapallivari Indlu"
    ],
    "wof:name":"Madanapallivari Indlu",
    "wof:placetype":"neighbourhood",
    "wof:population":52
},
  "geometry": {"coordinates":[78.820864,13.919163],"type":"Point"}
}