{
  "type": "Feature",
  "properties": {
    "gn:admin1_code":"11.0",
    "gn:admin2_code":"32.0",
    "gn:asciiname":"Kuphar",
    "gn:country_code":"IN",
    "gn:dem":1969,
    "gn:feature_class":"P",
    "gn:feature_code":"PPL",
    "gn:name":"Kuphar",
    "gn:population":0,
    "gn:timezone":"Asia/Kolkata",
    "iso:country":"IN",
    "name:ara_x_preferred":[
        "\u0642\u0641\u0629"
    ],
    "name:deu_x_preferred":[
        "Guffa"
    ],
    "name:fas_x_preferred":[
        "\u0642\u0627\u06cc\u0642 \u0632\u0646\u0628\u06cc\u0644\u06cc"
    ],
    "name:fra_x_preferred":[
        "Kuffa"
    ],
    "name:rus_x_preferred":[
        "\u0413\u0443\u0444\u0444\u0430"
    ],
    "wof:name":"Kuphar",
    "wof:placetype":"locality"
},
  "geometry": {"coordinates":[77.57290999999999,30.71018],"type":"Point"}
}