{
  "type": "Feature",
  "properties": {
    "iso:country":"IN",
    "ks:ks_alt_nam":"ghanvat hagare vasti",
    "ks:ks_name":"Ghanvat Hagare Vasti",
    "ks:ks_pop":365,
    "ks:ks_type":"HABITATION",
    "ks:ks_uagg_main":0,
    "name:eng_x_preferred":[
        "Ghanvat Hagare Vasti"
    ],
    "wof:name":"Ghanvat Hagare Vasti",
    "wof:placetype":"neighbourhood",
    "wof:population":365
},
  "geometry": {"coordinates":[74.50490000000001,18.0687],"type":"Point"}
}