{
  "type": "Feature",
  "properties": {
    "gn:admin1_code":"19.0",
    "gn:admin2_code":"581.0",
    "gn:asciiname":"Chintgomanhalli",
    "gn:country_code":"IN",
    "gn:dem":809,
    "gn:feature_class":"P",
    "gn:feature_code":"PPL",
    "gn:name":"Chintg\u014dmanhalli",
    "gn:population":0,
    "gn:timezone":"Asia/Kolkata",
    "iso:country":"IN",
    "wof:name":"Chintgomanhalli",
    "wof:placetype":"locality"
},
  "geometry": {"coordinates":[78.21684999999999,12.91041],"type":"Point"}
}