{
  "type": "Feature",
  "properties": {
    "gn:admin1_code":"12.0",
    "gn:admin2_code":"021",
    "gn:asciiname":"Doara",
    "gn:country_code":"IN",
    "gn:dem":385,
    "gn:feature_class":"P",
    "gn:feature_code":"PPL",
    "gn:name":"Do\u0101ra",
    "gn:population":0,
    "gn:timezone":"Asia/Kolkata",
    "iso:country":"IN",
    "name:und_x_variant":[
        "Do\u0101ra",
        "Dow\u0101ran"
    ],
    "wof:name":"Doara",
    "wof:placetype":"locality"
},
  "geometry": {"coordinates":[74.89621,32.7379],"type":"Point"}
}