{
  "type": "Feature",
  "properties": {
    "gn:admin1_code":"12.0",
    "gn:admin2_code":"16.0",
    "gn:asciiname":"Hamirpur",
    "gn:country_code":"IN",
    "gn:dem":1281,
    "gn:feature_class":"P",
    "gn:feature_code":"PPL",
    "gn:name":"Hamirpur",
    "gn:population":0,
    "gn:timezone":"Asia/Kolkata",
    "iso:country":"IN",
    "name:cat_x_preferred":[
        "Hamirpur"
    ],
    "name:deu_x_preferred":[
        "Hamirpur"
    ],
    "name:fra_x_preferred":[
        "Hamirpur"
    ],
    "name:hin_x_preferred":[
        "\u0939\u092e\u0940\u0930\u092a\u0941\u0930"
    ],
    "name:ita_x_preferred":[
        "Hamirpur"
    ],
    "name:nld_x_preferred":[
        "Hamirpur"
    ],
    "name:pnb_x_preferred":[
        "\u06be\u0645\u06cc\u0631 \u067e\u0648\u0631"
    ],
    "name:pol_x_preferred":[
        "Hamirpur"
    ],
    "name:rus_x_preferred":[
        "\u0425\u0430\u043c\u0438\u0440\u043f\u0443\u0440"
    ],
    "name:swe_x_preferred":[
        "Hamirpur"
    ],
    "wof:name":"Hamirpur",
    "wof:placetype":"locality"
},
  "geometry": {"coordinates":[75.59418000000002,33.13042],"type":"Point"}
}