{
  "type": "Feature",
  "properties": {
    "iso:country":"IN",
    "ks:ks_name":"Khardokule",
    "ks:ks_pop":766,
    "ks:ks_type":"HABITATION",
    "name:eng_x_preferred":[
        "Khardokule"
    ],
    "wof:name":"Khardokule",
    "wof:placetype":"locality",
    "wof:population":766
},
  "geometry": {"coordinates":[72.938433,18.38206],"type":"Point"}
}