{
  "type": "Feature",
  "properties": {
    "gn:country":"IN",
    "gn:fcode":"PPL",
    "gn:pop":0,
    "iso:country":"IN",
    "name:bel_x_preferred":[
        "\u041f\u0430\u043d\u043a\u0456"
    ],
    "name:ceb_x_preferred":[
        "Panki"
    ],
    "name:rus_x_preferred":[
        "\u041f\u0430\u043d\u043a\u0438"
    ],
    "name:swe_x_preferred":[
        "Panki"
    ],
    "qs:name":"Panki",
    "qs:name_adm0":"India",
    "qs:name_adm1":"Jharkhand",
    "qs:photos_9r":0,
    "qs:photos_sr":0,
    "qs:placetype":"Town",
    "qs:pop_sr":"0",
    "wd:wordcount":43,
    "wof:name":"Panki",
    "wof:placetype":"locality",
    "wof:population":0
},
  "geometry": {"coordinates":[84.47727,24.03541],"type":"Point"}
}