{
  "type": "Feature",
  "properties": {
    "iso:country":"IN",
    "ks:ks_alt_nam":"Irinjalakuda- Katttoor Rd jun",
    "ks:ks_name":"Irinjalakuda- Katttoor Rd Jun",
    "ks:ks_pop":348,
    "ks:ks_type":"HABITATION",
    "name:eng_x_preferred":[
        "Irinjalakuda- Katttoor Rd Jun"
    ],
    "wof:name":"Irinjalakuda- Katttoor Rd Jun",
    "wof:placetype":"locality",
    "wof:population":348
},
  "geometry": {"coordinates":[76.157051,10.371115],"type":"Point"}
}