{
  "type": "Feature",
  "properties": {
    "iso:country":"IN",
    "ks:ks_name":"Paranpur",
    "ks:ks_pop":8867,
    "ks:ks_type":"VILLAGE",
    "name:eng_x_preferred":[
        "Paranpur"
    ],
    "wof:name":"Paranpur",
    "wof:placetype":"locality",
    "wof:population":8867
},
  "geometry": {"coordinates":[87.93679899999999,24.893769],"type":"Point"}
}