{
  "type": "Feature",
  "properties": {
    "gn:admin1_code":"36",
    "gn:admin2_code":"142.0",
    "gn:asciiname":"Tanian",
    "gn:country_code":"IN",
    "gn:dem":194,
    "gn:feature_class":"P",
    "gn:feature_code":"PPL",
    "gn:name":"Tani\u0101n",
    "gn:population":0,
    "gn:timezone":"Asia/Kolkata",
    "iso:country":"IN",
    "name:fas_x_preferred":[
        "\u062a\u0646\u06cc\u0627\u0646"
    ],
    "name:msa_x_preferred":[
        "Tanian"
    ],
    "name:ukr_x_preferred":[
        "\u0422\u0430\u043d\u0456\u044f\u043d"
    ],
    "wof:name":"Tanian",
    "wof:placetype":"locality"
},
  "geometry": {"coordinates":[77.78394,28.17531],"type":"Point"}
}