{
  "type": "Feature",
  "properties": {
    "iso:country":"IN",
    "ks:ks_name":"Khetbharar",
    "ks:ks_pop":216,
    "ks:ks_type":"VILLAGE",
    "name:eng_x_preferred":[
        "Khetbharar"
    ],
    "wof:name":"Khetbharar",
    "wof:placetype":"locality",
    "wof:population":216
},
  "geometry": {"coordinates":[80.23147299999999,29.926218],"type":"Point"}
}