{
  "type": "Feature",
  "properties": {
    "iso:country":"IN",
    "ks:ks_name":"Nasherkuli",
    "ks:ks_pop":3075,
    "ks:ks_type":"VILLAGE",
    "ks:ks_uagg_main":0,
    "name:eng_x_preferred":[
        "Nasherkuli"
    ],
    "wof:name":"Nasherkuli",
    "wof:placetype":"locality",
    "wof:population":3075
},
  "geometry": {"coordinates":[88.60038400000001,23.135965],"type":"Point"}
}