{
  "type": "Feature",
  "properties": {
    "gn:admin1_code":"25.0",
    "gn:admin2_code":"632.0",
    "gn:asciiname":"Kangayampalaiyam",
    "gn:country_code":"IN",
    "gn:dem":375,
    "gn:feature_class":"P",
    "gn:feature_code":"PPL",
    "gn:name":"K\u0101ngayamp\u0101laiyam",
    "gn:population":0,
    "gn:timezone":"Asia/Kolkata",
    "iso:country":"IN",
    "ks:ks_name":"Kangayampalayam",
    "ks:ks_pop":2981,
    "ks:ks_type":"VILLAGE",
    "ks:ks_uagg_main":0,
    "name:eng_x_preferred":[
        "Kangayampalayam"
    ],
    "wof:name":"Kangayampalayam",
    "wof:placetype":"locality",
    "wof:population":2981
},
  "geometry": {"coordinates":[77.143998,11.023592],"type":"Point"}
}