{
  "type": "Feature",
  "properties": {
    "iso:country":"IN",
    "ks:ks_name":"Malagudatanda",
    "ks:ks_pop":50,
    "ks:ks_type":"HABITATION",
    "name:eng_x_preferred":[
        "Malagudatanda"
    ],
    "wof:name":"Malagudatanda",
    "wof:placetype":"locality",
    "wof:population":50
},
  "geometry": {"coordinates":[78.30651899999999,17.054143],"type":"Point"}
}