{
  "type": "Feature",
  "properties": {
    "gn:admin1_code":"24.0",
    "gn:admin2_code":"119.0",
    "gn:asciiname":"Sadapur",
    "gn:country_code":"IN",
    "gn:dem":366,
    "gn:feature_class":"P",
    "gn:feature_code":"PPL",
    "gn:name":"Sad\u0101pur",
    "gn:population":0,
    "gn:timezone":"Asia/Kolkata",
    "iso:country":"IN",
    "name:aze_x_preferred":[
        "Sadapur"
    ],
    "wof:name":"Sadapur",
    "wof:placetype":"locality"
},
  "geometry": {"coordinates":[75.09268,26.18598],"type":"Point"}
}