{
  "type": "Feature",
  "properties": {
    "iso:country":"IN",
    "ks:ks_alt_nam":"NOABARI",
    "ks:ks_name":"Noabari",
    "ks:ks_pop":545,
    "ks:ks_type":"HABITATION",
    "name:eng_x_preferred":[
        "Noabari"
    ],
    "wof:name":"Noabari",
    "wof:placetype":"locality",
    "wof:population":545
},
  "geometry": {"coordinates":[91.37304399999999,23.466515],"type":"Point"}
}