{
  "type": "Feature",
  "properties": {
    "gn:admin1_code":"35.0",
    "gn:admin2_code":"455.0",
    "gn:asciiname":"Kokat",
    "gn:country_code":"IN",
    "gn:dem":769,
    "gn:feature_class":"P",
    "gn:feature_code":"PPL",
    "gn:name":"Kokat",
    "gn:population":0,
    "gn:timezone":"Asia/Kolkata",
    "iso:country":"IN",
    "ks:ks_name":"Kokat",
    "ks:ks_type":"VILLAGE",
    "name:eng_x_preferred":[
        "Kokat"
    ],
    "wof:name":"Kokat",
    "wof:placetype":"locality"
},
  "geometry": {"coordinates":[78.645753,22.123479],"type":"Point"}
}