{
  "type": "Feature",
  "properties": {
    "gn:admin1_code":"35.0",
    "gn:admin2_code":"455.0",
    "gn:asciiname":"Kokat",
    "gn:country_code":"IN",
    "gn:dem":769,
    "gn:feature_class":"P",
    "gn:feature_code":"PPL",
    "gn:name":"Kokat",
    "gn:population":0,
    "gn:timezone":"Asia/Kolkata",
    "iso:country":"IN",
    "wof:name":"Kokat",
    "wof:placetype":"locality"
},
  "geometry": {"coordinates":[78.65659000000002,22.11502],"type":"Point"}
}