{
  "type": "Feature",
  "properties": {
    "iso:country":"IN",
    "ks:ks_name":"Naugawan",
    "ks:ks_pop":552,
    "ks:ks_type":"VILLAGE",
    "name:eng_x_preferred":[
        "Naugawan"
    ],
    "wof:name":"Naugawan",
    "wof:placetype":"locality",
    "wof:population":552
},
  "geometry": {"coordinates":[81.616124,23.396033],"type":"Point"}
}