{
  "type": "Feature",
  "properties": {
    "gn:admin1_code":"37",
    "gn:admin2_code":"406.0",
    "gn:asciiname":"Chuapara",
    "gn:country_code":"IN",
    "gn:dem":267,
    "gn:feature_class":"P",
    "gn:feature_code":"PPL",
    "gn:name":"Chuap\u0101ra",
    "gn:population":0,
    "gn:timezone":"Asia/Kolkata",
    "iso:country":"IN",
    "wof:name":"Chuapara",
    "wof:placetype":"locality"
},
  "geometry": {"coordinates":[82.15248000000003,21.99283],"type":"Point"}
}