{
  "type": "Feature",
  "properties": {
    "iso:country":"IN",
    "ks:ks_alt_nam":"akorda",
    "ks:ks_name":"Akorda",
    "ks:ks_pop":227,
    "ks:ks_type":"HABITATION",
    "name:eng_x_preferred":[
        "Akorda"
    ],
    "wof:name":"Akorda",
    "wof:placetype":"locality",
    "wof:population":227
},
  "geometry": {"coordinates":[74.565787,15.230929],"type":"Point"}
}