{
  "type": "Feature",
  "properties": {
    "gn:admin1_code":"19.0",
    "gn:admin2_code":"572",
    "gn:asciiname":"K .P .C Layout",
    "gn:country_code":"IN",
    "gn:dem":897,
    "gn:feature_class":"P",
    "gn:feature_code":"PPL",
    "gn:name":"K .P .C Layout",
    "gn:population":0,
    "gn:timezone":"Asia/Kolkata",
    "iso:country":"IN",
    "wof:name":"K .P .C Layout",
    "wof:placetype":"neighbourhood"
},
  "geometry": {"coordinates":[77.67815,12.90517],"type":"Point"}
}