{
  "type": "Feature",
  "properties": {
    "iso:country":"IN",
    "ks:ks_name":"Handipoda",
    "ks:ks_pop":504,
    "ks:ks_type":"VILLAGE",
    "name:eng_x_preferred":[
        "Handipoda"
    ],
    "wof:name":"Handipoda",
    "wof:placetype":"locality",
    "wof:population":504
},
  "geometry": {"coordinates":[87.431302,21.662182],"type":"Point"}
}