{
  "type": "Feature",
  "properties": {
    "iso:country":"IN",
    "ks:ks_name":"Ahir Tola",
    "ks:ks_pop":100,
    "ks:ks_type":"HABITATION",
    "name:eng_x_preferred":[
        "Ahir Tola"
    ],
    "wof:name":"Ahir Tola",
    "wof:placetype":"locality",
    "wof:population":100
},
  "geometry": {"coordinates":[83.78572,26.096979],"type":"Point"}
}