{
  "type": "Feature",
  "properties": {
    "gn:admin1_code":"36",
    "gn:admin2_code":"144.0",
    "gn:asciiname":"Nagla Umed",
    "gn:country_code":"IN",
    "gn:dem":183,
    "gn:feature_class":"P",
    "gn:feature_code":"PPL",
    "gn:name":"Nagla Umed",
    "gn:population":0,
    "gn:timezone":"Asia/Kolkata",
    "iso:country":"IN",
    "wof:name":"Nagla Umed",
    "wof:placetype":"locality"
},
  "geometry": {"coordinates":[78.05682,27.63639],"type":"Point"}
}