{
  "type": "Feature",
  "properties": {
    "iso:country":"IN",
    "ks:ks_name":"Jadiyana",
    "ks:ks_pop":89,
    "ks:ks_type":"VILLAGE",
    "name:eng_x_preferred":[
        "Jadiyana"
    ],
    "wof:name":"Jadiyana",
    "wof:placetype":"locality",
    "wof:population":89
},
  "geometry": {"coordinates":[78.70159200000001,29.824868],"type":"Point"}
}