{
  "type": "Feature",
  "properties": {
    "gn:admin1_code":"28.0",
    "gn:admin2_code":"330.0",
    "gn:asciiname":"Jairampur",
    "gn:country_code":"IN",
    "gn:dem":44,
    "gn:feature_class":"P",
    "gn:feature_code":"PPL",
    "gn:name":"Jair\u0101mpur",
    "gn:population":0,
    "gn:timezone":"Asia/Kolkata",
    "iso:country":"IN",
    "name:ben_x_preferred":[
        "\u099c\u09af\u09bc\u09b0\u09be\u09ae\u09aa\u09c1\u09b0"
    ],
    "name:bpy_x_preferred":[
        "\u099c\u09af\u09bc\u09b0\u09be\u09ae\u09aa\u09c1\u09b0"
    ],
    "name:ita_x_preferred":[
        "Jairampur"
    ],
    "name:msa_x_preferred":[
        "Jairampur"
    ],
    "name:new_x_preferred":[
        "\u091c\u092f\u0930\u093e\u092e\u092a\u0941\u0930"
    ],
    "name:nld_x_preferred":[
        "Jairampur"
    ],
    "name:por_x_preferred":[
        "Jairampur"
    ],
    "name:tgl_x_preferred":[
        "Jairampur"
    ],
    "name:urd_x_preferred":[
        "\u062c\u06cc\u0631\u0627\u0645\u067e\u0648\u0631"
    ],
    "name:vie_x_preferred":[
        "Jairampur"
    ],
    "wof:name":"Jairampur",
    "wof:placetype":"locality"
},
  "geometry": {"coordinates":[87.87505,25.91626],"type":"Point"}
}