{
  "type": "Feature",
  "properties": {
    "iso:country":"IN",
    "ks:ks_name":"Boddaputtu",
    "ks:ks_pop":116,
    "ks:ks_type":"VILLAGE",
    "name:eng_x_preferred":[
        "Boddaputtu"
    ],
    "wof:name":"Boddaputtu",
    "wof:placetype":"locality",
    "wof:population":116
},
  "geometry": {"coordinates":[82.803888,18.16896],"type":"Point"}
}