{
  "type": "Feature",
  "properties": {
    "iso:country":"IN",
    "ks:ks_name":"Ahiran Purwa",
    "ks:ks_pop":227,
    "ks:ks_type":"HABITATION",
    "name:eng_x_preferred":[
        "Ahiran Purwa"
    ],
    "wof:name":"Ahiran Purwa",
    "wof:placetype":"locality",
    "wof:population":227
},
  "geometry": {"coordinates":[81.89258700000001,27.535941],"type":"Point"}
}