{
  "type": "Feature",
  "properties": {
    "iso:country":"IN",
    "ks:ks_name":"Kanarsuan",
    "ks:ks_pop":411,
    "ks:ks_type":"VILLAGE",
    "name:eng_x_preferred":[
        "Kanarsuan"
    ],
    "wof:name":"Kanarsuan",
    "wof:placetype":"locality",
    "wof:population":411
},
  "geometry": {"coordinates":[84.907606,22.154928],"type":"Point"}
}