{
  "type": "Feature",
  "properties": {
    "gn:admin1_code":"35.0",
    "gn:admin2_code":"457.0",
    "gn:asciiname":"Khapakhera",
    "gn:country_code":"IN",
    "gn:dem":558,
    "gn:feature_class":"P",
    "gn:feature_code":"PPL",
    "gn:name":"Kh\u0101pakher\u0101",
    "gn:population":0,
    "gn:timezone":"Asia/Kolkata",
    "iso:country":"IN",
    "ks:ks_name":"Khapakheda",
    "ks:ks_pop":302,
    "ks:ks_type":"VILLAGE",
    "name:eng_x_preferred":[
        "Khapakheda"
    ],
    "name:eng_x_variant":[
        "Khapakhera"
    ],
    "wof:name":"Khapakheda",
    "wof:placetype":"locality",
    "wof:population":302
},
  "geometry": {"coordinates":[80.317336,22.258409],"type":"Point"}
}