{
  "type": "Feature",
  "properties": {
    "gn:admin1_code":"25.0",
    "gn:admin2_code":"605.0",
    "gn:asciiname":"Jolagoundanuru",
    "gn:country_code":"IN",
    "gn:dem":424,
    "gn:feature_class":"P",
    "gn:feature_code":"PPL",
    "gn:name":"Jolagoundan\u016bru",
    "gn:population":0,
    "gn:timezone":"Asia/Kolkata",
    "iso:country":"IN",
    "wof:name":"Jolagoundanuru",
    "wof:placetype":"locality"
},
  "geometry": {"coordinates":[78.67669000000002,12.51595],"type":"Point"}
}