{
  "type": "Feature",
  "properties": {
    "iso:country":"IN",
    "ks:ks_alt_nam":"Nainoli G\u0101d",
    "ks:ks_alt_nam_2":"Nainoli Gad",
    "ks:ks_name":"Nainoli",
    "ks:ks_type":"VILLAGE",
    "name:eng_x_preferred":[
        "Nainoli"
    ],
    "name:eng_x_variant":[
        "Nainoli G\u0101d",
        "Nainoli Gad"
    ],
    "wof:name":"Nainoli",
    "wof:placetype":"locality"
},
  "geometry": {"coordinates":[79.983632,29.62419],"type":"Point"}
}