{
  "type": "Feature",
  "properties": {
    "iso:country":"IN",
    "ks:ks_alt_nam":"KAIMATOLA",
    "ks:ks_name":"Kaimatola",
    "ks:ks_pop":105,
    "ks:ks_type":"HABITATION",
    "name:eng_x_preferred":[
        "Kaimatola"
    ],
    "wof:name":"Kaimatola",
    "wof:placetype":"locality",
    "wof:population":105
},
  "geometry": {"coordinates":[82.850931,23.856808],"type":"Point"}
}