{
  "type": "Feature",
  "properties": {
    "gn:admin1_code":"36",
    "gn:admin2_code":"173.0",
    "gn:asciiname":"Pura Lannanchirai",
    "gn:country_code":"IN",
    "gn:dem":101,
    "gn:feature_class":"P",
    "gn:feature_code":"PPL",
    "gn:name":"Pura L\u0101nnanchirai",
    "gn:population":0,
    "gn:timezone":"Asia/Kolkata",
    "iso:country":"IN",
    "ks:ks_alt_nam":"Pura L\u0101nnanchirai",
    "ks:ks_name":"Pura Lannanchirai",
    "ks:ks_type":"VILLAGE",
    "name:eng_x_preferred":[
        "Pura Lannanchirai"
    ],
    "name:eng_x_variant":[
        "Pura L\u0101nnanchirai"
    ],
    "wof:name":"Pura Lannanchirai",
    "wof:placetype":"locality"
},
  "geometry": {"coordinates":[81.681077,25.844249],"type":"Point"}
}