{
  "type": "Feature",
  "properties": {
    "gn:admin1_code":"16",
    "gn:admin2_code":"528.0",
    "gn:asciiname":"Tonda",
    "gn:country_code":"IN",
    "gn:dem":53,
    "gn:feature_class":"P",
    "gn:feature_code":"PPL",
    "gn:name":"Tonda",
    "gn:population":0,
    "gn:timezone":"Asia/Kolkata",
    "iso:country":"IN",
    "name:arg_x_preferred":[
        "Tonda"
    ],
    "name:ceb_x_preferred":[
        "Tonda"
    ],
    "name:deu_x_preferred":[
        "Tonda"
    ],
    "name:nld_x_preferred":[
        "Tonda"
    ],
    "name:swe_x_preferred":[
        "Tonda"
    ],
    "wof:name":"Tonda",
    "wof:placetype":"locality"
},
  "geometry": {"coordinates":[73.37699000000001,16.93463],"type":"Point"}
}