{
  "type": "Feature",
  "properties": {
    "gn:admin1_code":"36",
    "gn:admin2_code":"154.0",
    "gn:asciiname":"Chandnapur",
    "gn:country_code":"IN",
    "gn:dem":134,
    "gn:feature_class":"P",
    "gn:feature_code":"PPL",
    "gn:name":"Chandn\u0101pur",
    "gn:population":0,
    "gn:timezone":"Asia/Kolkata",
    "iso:country":"IN",
    "wof:name":"Chandnapur",
    "wof:placetype":"locality"
},
  "geometry": {"coordinates":[81.04414,27.34884000000001],"type":"Point"}
}