{
  "type": "Feature",
  "properties": {
    "iso:country":"IN",
    "ks:ks_alt_nam":"cherandathoor",
    "ks:ks_name":"Cherandathoor",
    "ks:ks_pop":4253,
    "ks:ks_type":"HABITATION",
    "name:eng_x_preferred":[
        "Cherandathoor"
    ],
    "wof:name":"Cherandathoor",
    "wof:placetype":"locality",
    "wof:population":4253
},
  "geometry": {"coordinates":[75.676096,11.552115],"type":"Point"}
}