{
  "type": "Feature",
  "properties": {
    "gn:admin1_code":"34",
    "gn:admin2_code":"232.0",
    "gn:asciiname":"Karhansi",
    "gn:country_code":"IN",
    "gn:dem":68,
    "gn:feature_class":"P",
    "gn:feature_code":"PPL",
    "gn:name":"Karh\u0101nsi",
    "gn:population":0,
    "gn:timezone":"Asia/Kolkata",
    "iso:country":"IN",
    "name:und_x_variant":[
        "Karh\u0101nsi",
        "R\u0101mnagai"
    ],
    "wof:name":"Karhansi",
    "wof:placetype":"locality"
},
  "geometry": {"coordinates":[83.95820999999999,25.49635],"type":"Point"}
}