{
  "type": "Feature",
  "properties": {
    "gn:admin1_code":"36.0",
    "gn:admin2_code":"135.0",
    "gn:asciiname":"Lala Tikar",
    "gn:country_code":"IN",
    "gn:dem":188,
    "gn:feature_class":"P",
    "gn:feature_code":"PPL",
    "gn:name":"L\u0101la T\u012bkar",
    "gn:population":0,
    "gn:timezone":"Asia/Kolkata",
    "iso:country":"IN",
    "name:und_x_variant":[
        "L\u0101la T\u012bkar",
        "Mahesh Nagli"
    ],
    "wof:name":"Lala Tikar",
    "wof:placetype":"locality"
},
  "geometry": {"coordinates":[78.89757,28.7163],"type":"Point"}
}