{
  "type": "Feature",
  "properties": {
    "gn:admin1_code":"36.0",
    "gn:admin2_code":"135.0",
    "gn:asciiname":"Umri",
    "gn:country_code":"IN",
    "gn:dem":197,
    "gn:feature_class":"P",
    "gn:feature_code":"PPL",
    "gn:name":"Umri",
    "gn:population":0,
    "gn:timezone":"Asia/Kolkata",
    "iso:country":"IN",
    "ks:ks_name":"Umari",
    "ks:ks_pop":2374,
    "ks:ks_type":"VILLAGE",
    "ks:ks_uagg_main":0,
    "name:ceb_x_preferred":[
        "Umri"
    ],
    "name:eng_x_preferred":[
        "Umari"
    ],
    "name:pol_x_preferred":[
        "Umri"
    ],
    "name:swe_x_preferred":[
        "Umri"
    ],
    "wof:name":"Umari",
    "wof:placetype":"neighbourhood",
    "wof:population":2374
},
  "geometry": {"coordinates":[78.730887,28.795956],"type":"Point"}
}