{
  "type": "Feature",
  "properties": {
    "gn:admin1_code":"09",
    "gn:admin2_code":"484.0",
    "gn:asciiname":"Sant",
    "gn:country_code":"IN",
    "gn:dem":144,
    "gn:feature_class":"P",
    "gn:feature_code":"PPL",
    "gn:name":"Sant",
    "gn:population":0,
    "gn:timezone":"Asia/Kolkata",
    "iso:country":"IN",
    "name:ceb_x_preferred":[
        "Sant"
    ],
    "name:fra_x_preferred":[
        "Sant"
    ],
    "name:hat_x_preferred":[
        "Sant"
    ],
    "name:mon_x_preferred":[
        "\u0421\u0430\u043d\u0442 \u0441\u0443\u043c"
    ],
    "name:por_x_preferred":[
        "Sant"
    ],
    "name:swe_x_preferred":[
        "Sant"
    ],
    "name:urd_x_preferred":[
        "\u0633\u0646\u062a"
    ],
    "wof:name":"Sant",
    "wof:placetype":"locality"
},
  "geometry": {"coordinates":[73.8817,23.19752],"type":"Point"}
}