{
  "type": "Feature",
  "properties": {
    "gn:admin1_code":"09",
    "gn:admin2_code":"484.0",
    "gn:asciiname":"Sant",
    "gn:country_code":"IN",
    "gn:dem":144,
    "gn:feature_class":"P",
    "gn:feature_code":"PPL",
    "gn:name":"Sant",
    "gn:population":0,
    "gn:timezone":"Asia/Kolkata",
    "iso:country":"IN",
    "wof:name":"Sant",
    "wof:placetype":"locality"
},
  "geometry": {"coordinates":[73.8817,23.19752],"type":"Point"}
}