{
  "type": "Feature",
  "properties": {
    "iso:country":"IN",
    "ks:ks_name":"Rasulpur Misra",
    "ks:ks_pop":11,
    "ks:ks_type":"VILLAGE",
    "name:eng_x_preferred":[
        "Rasulpur Misra"
    ],
    "wof:name":"Rasulpur Misra",
    "wof:placetype":"locality",
    "wof:population":11
},
  "geometry": {"coordinates":[83.146293,26.397711],"type":"Point"}
}