{
  "type": "Feature",
  "properties": {
    "iso:country":"IN",
    "ks:ks_name":"Hariya",
    "ks:ks_pop":581,
    "ks:ks_type":"HABITATION",
    "name:eng_x_preferred":[
        "Hariya"
    ],
    "wof:name":"Hariya",
    "wof:placetype":"locality",
    "wof:population":581
},
  "geometry": {"coordinates":[82.67039200000001,27.365854],"type":"Point"}
}