{
  "type": "Feature",
  "properties": {
    "iso:country":"IN",
    "ks:ks_name":"Saghanpur",
    "ks:ks_pop":366,
    "ks:ks_type":"HABITATION",
    "name:eng_x_preferred":[
        "Saghanpur"
    ],
    "wof:name":"Saghanpur",
    "wof:placetype":"locality",
    "wof:population":366
},
  "geometry": {"coordinates":[82.709312,26.156327],"type":"Point"}
}