{
  "type": "Feature",
  "properties": {
    "gn:admin1_code":"24.0",
    "gn:admin2_code":"102",
    "gn:asciiname":"Hariyasar",
    "gn:country_code":"IN",
    "gn:dem":260,
    "gn:feature_class":"P",
    "gn:feature_code":"PPL",
    "gn:name":"Hariy\u0101s\u0101r",
    "gn:population":0,
    "gn:timezone":"Asia/Kolkata",
    "iso:country":"IN",
    "name:und_x_variant":[
        "Hari\u0101sar",
        "Hariy\u0101sar",
        "Hariy\u0101s\u0101r"
    ],
    "wof:name":"Hariyasar",
    "wof:placetype":"locality"
},
  "geometry": {"coordinates":[74.65264999999999,28.43095],"type":"Point"}
}