{
  "type": "Feature",
  "properties": {
    "iso:country":"IN",
    "ks:ks_name":"Malia Falia",
    "ks:ks_pop":298,
    "ks:ks_type":"HABITATION",
    "name:eng_x_preferred":[
        "Malia Falia"
    ],
    "wof:name":"Malia Falia",
    "wof:placetype":"locality",
    "wof:population":298
},
  "geometry": {"coordinates":[73.844528,23.364861],"type":"Point"}
}