{
  "type": "Feature",
  "properties": {
    "gn:admin1_code":"23.0",
    "gn:admin2_code":"54.0",
    "gn:asciiname":"Dhraj",
    "gn:country_code":"IN",
    "gn:dem":221,
    "gn:feature_class":"P",
    "gn:feature_code":"PPL",
    "gn:name":"Dhr\u0101j",
    "gn:population":0,
    "gn:timezone":"Asia/Kolkata",
    "iso:country":"IN",
    "wof:name":"Dhraj",
    "wof:placetype":"locality"
},
  "geometry": {"coordinates":[75.34536999999997,30.30987],"type":"Point"}
}