{
  "type": "Feature",
  "properties": {
    "gn:admin1_code":"16.0",
    "gn:admin2_code":"497.0",
    "gn:asciiname":"Bhujgaon",
    "gn:country_code":"IN",
    "gn:dem":402,
    "gn:feature_class":"P",
    "gn:feature_code":"PPL",
    "gn:name":"Bhujgaon",
    "gn:population":0,
    "gn:timezone":"Asia/Kolkata",
    "iso:country":"IN",
    "ks:ks_name":"Bhujgaon",
    "ks:ks_pop":932,
    "ks:ks_type":"VILLAGE",
    "name:eng_x_preferred":[
        "Bhujgaon"
    ],
    "wof:name":"Bhujgaon",
    "wof:placetype":"locality",
    "wof:population":932
},
  "geometry": {"coordinates":[74.18966500000001,21.822971],"type":"Point"}
}