{
  "type": "Feature",
  "properties": {
    "iso:country":"IN",
    "ks:ks_name":"Sahabpur Y.b.",
    "ks:ks_pop":46,
    "ks:ks_type":"HABITATION",
    "name:eng_x_preferred":[
        "Sahabpur Y.b."
    ],
    "wof:name":"Sahabpur Y.b.",
    "wof:placetype":"locality",
    "wof:population":46
},
  "geometry": {"coordinates":[83.388874,25.90628],"type":"Point"}
}