{
  "type": "Feature",
  "properties": {
    "iso:country":"IN",
    "ks:ks_alt_nam":"R Kondaiah camp",
    "ks:ks_name":"R Kondaiah Camp",
    "ks:ks_pop":505,
    "ks:ks_type":"HABITATION",
    "name:eng_x_preferred":[
        "R Kondaiah Camp"
    ],
    "wof:name":"R Kondaiah Camp",
    "wof:placetype":"locality",
    "wof:population":505
},
  "geometry": {"coordinates":[76.67185499999999,15.418993],"type":"Point"}
}