{
  "type": "Feature",
  "properties": {
    "iso:country":"IN",
    "ks:ks_name":"Chavdiwadi",
    "ks:ks_pop":207,
    "ks:ks_type":"HABITATION",
    "name:eng_x_preferred":[
        "Chavdiwadi"
    ],
    "wof:name":"Chavdiwadi",
    "wof:placetype":"locality",
    "wof:population":207
},
  "geometry": {"coordinates":[73.841718,15.971288],"type":"Point"}
}