{
  "type": "Feature",
  "properties": {
    "gn:admin1_code":"36.0",
    "gn:admin2_code":"150.0",
    "gn:asciiname":"Bhatpura",
    "gn:country_code":"IN",
    "gn:dem":175,
    "gn:feature_class":"P",
    "gn:feature_code":"PPL",
    "gn:name":"Bhatpura",
    "gn:population":0,
    "gn:timezone":"Asia/Kolkata",
    "iso:country":"IN",
    "ks:ks_name":"Bhatpura",
    "ks:ks_type":"VILLAGE",
    "name:eng_x_preferred":[
        "Bhatpura"
    ],
    "wof:name":"Bhatpura",
    "wof:placetype":"locality"
},
  "geometry": {"coordinates":[79.53684199999999,28.466333],"type":"Point"}
}