{
  "type": "Feature",
  "properties": {
    "iso:country":"IN",
    "ks:ks_name":"Jidu",
    "ks:ks_pop":424,
    "ks:ks_type":"VILLAGE",
    "ks:ks_uagg_main":0,
    "name:eng_x_preferred":[
        "Jidu"
    ],
    "wof:name":"Jidu",
    "wof:placetype":"neighbourhood",
    "wof:population":424
},
  "geometry": {"coordinates":[85.257576,23.511935],"type":"Point"}
}