{
  "type": "Feature",
  "properties": {
    "iso:country":"IN",
    "ks:ks_name":"Edakkattuparambu",
    "ks:ks_pop":561,
    "ks:ks_type":"HABITATION",
    "name:eng_x_preferred":[
        "Edakkattuparambu"
    ],
    "wof:name":"Edakkattuparambu",
    "wof:placetype":"locality",
    "wof:population":561
},
  "geometry": {"coordinates":[76.070711,11.273641],"type":"Point"}
}