{
  "type": "Feature",
  "properties": {
    "iso:country":"IN",
    "ks:ks_name":"Tantipara",
    "ks:ks_pop":1070,
    "ks:ks_type":"HABITATION",
    "ks:ks_uagg_main":0,
    "name:eng_x_preferred":[
        "Tantipara"
    ],
    "wof:name":"Tantipara",
    "wof:placetype":"neighbourhood",
    "wof:population":1070
},
  "geometry": {"coordinates":[88.053217,22.708373],"type":"Point"}
}