{
  "type": "Feature",
  "properties": {
    "gn:admin1_code":"2.0",
    "gn:admin2_code":"552.0",
    "gn:asciiname":"Zaftijagirpendekallu",
    "gn:country_code":"IN",
    "gn:dem":428,
    "gn:feature_class":"P",
    "gn:feature_code":"PPL",
    "gn:name":"Zaftij\u0101g\u012brpendekallu",
    "gn:population":0,
    "gn:timezone":"Asia/Kolkata",
    "iso:country":"IN",
    "wof:name":"Zaftijagirpendekallu",
    "wof:placetype":"locality"
},
  "geometry": {"coordinates":[77.39913,15.63936],"type":"Point"}
}