{
  "type": "Feature",
  "properties": {
    "iso:country":"IN",
    "ks:ks_alt_nam":"KATIHORI",
    "ks:ks_name":"Katihori",
    "ks:ks_pop":321,
    "ks:ks_type":"HABITATION",
    "name:eng_x_preferred":[
        "Katihori"
    ],
    "wof:name":"Katihori",
    "wof:placetype":"locality",
    "wof:population":321
},
  "geometry": {"coordinates":[85.539778,22.187444],"type":"Point"}
}