{
  "type": "Feature",
  "properties": {
    "gn:admin1_code":"36.0",
    "gn:admin2_code":"173.0",
    "gn:asciiname":"Sandwa",
    "gn:country_code":"IN",
    "gn:dem":110,
    "gn:feature_class":"P",
    "gn:feature_code":"PPL",
    "gn:name":"Sandwa",
    "gn:population":0,
    "gn:timezone":"Asia/Kolkata",
    "iso:country":"IN",
    "name:ceb_x_preferred":[
        "S\u0101ndwa"
    ],
    "name:hin_x_preferred":[
        "\u0938\u093e\u0902\u0921\u0935\u093e"
    ],
    "name:swe_x_preferred":[
        "S\u0101ndwa"
    ],
    "wof:name":"Sandwa",
    "wof:placetype":"locality"
},
  "geometry": {"coordinates":[81.76238000000002,26.06024],"type":"Point"}
}