{
  "type": "Feature",
  "properties": {
    "gn:admin1_code":"19",
    "gn:admin2_code":"563.0",
    "gn:asciiname":"Mattimane",
    "gn:country_code":"IN",
    "gn:dem":512,
    "gn:feature_class":"P",
    "gn:feature_code":"PPL",
    "gn:name":"Mattimane",
    "gn:population":0,
    "gn:timezone":"Asia/Kolkata",
    "iso:country":"IN",
    "ks:ks_name":"Mattemane",
    "ks:ks_pop":45,
    "ks:ks_type":"HABITATION",
    "name:eng_x_preferred":[
        "Mattemane"
    ],
    "name:eng_x_variant":[
        "Mattimane"
    ],
    "wof:name":"Mattemane",
    "wof:placetype":"locality",
    "wof:population":45
},
  "geometry": {"coordinates":[74.79151,14.44574],"type":"Point"}
}