{
  "type": "Feature",
  "properties": {
    "gn:admin1_code":"33",
    "gn:admin2_code":"585.0",
    "gn:asciiname":"Talaulim",
    "gn:country_code":"IN",
    "gn:dem":46,
    "gn:feature_class":"P",
    "gn:feature_code":"PPL",
    "gn:name":"Talaulim",
    "gn:population":0,
    "gn:timezone":"Asia/Kolkata",
    "iso:country":"IN",
    "wof:name":"Talaulim",
    "wof:placetype":"locality"
},
  "geometry": {"coordinates":[73.98333000000002,15.38333],"type":"Point"}
}