{
  "type": "Feature",
  "properties": {
    "gn:admin1_code":"23.0",
    "gn:admin2_code":"49.0",
    "gn:asciiname":"Sadhar",
    "gn:country_code":"IN",
    "gn:dem":239,
    "gn:feature_class":"P",
    "gn:feature_code":"PPL",
    "gn:name":"Sadhar",
    "gn:population":0,
    "gn:timezone":"Asia/Kolkata",
    "iso:country":"IN",
    "name:fas_x_preferred":[
        "\u0633\u062f\u0647\u0627\u0631"
    ],
    "name:urd_x_preferred":[
        "\u0633\u062f\u06be\u0627\u0631"
    ],
    "wof:name":"Sadhar",
    "wof:placetype":"locality"
},
  "geometry": {"coordinates":[75.20855,31.58944],"type":"Point"}
}