{
  "type": "Feature",
  "properties": {
    "iso:country":"IN",
    "ks:ks_name":"Musalman Tola",
    "ks:ks_pop":754,
    "ks:ks_type":"HABITATION",
    "ks:ks_uagg_main":0,
    "name:eng_x_preferred":[
        "Musalman Tola"
    ],
    "wof:name":"Musalman Tola",
    "wof:placetype":"neighbourhood",
    "wof:population":754
},
  "geometry": {"coordinates":[87.05112200000001,26.424679],"type":"Point"}
}