{
  "type": "Feature",
  "properties": {
    "gn:admin1_code":"10.0",
    "gn:admin2_code":"71.0",
    "gn:asciiname":"Sisauli",
    "gn:country_code":"IN",
    "gn:dem":280,
    "gn:feature_class":"P",
    "gn:feature_code":"PPL",
    "gn:name":"Sisauli",
    "gn:population":0,
    "gn:timezone":"Asia/Kolkata",
    "iso:country":"IN",
    "name:bpy_x_preferred":[
        "\u09b8\u09bf\u09b8\u09be\u0989\u09b2\u09bf"
    ],
    "name:ceb_x_preferred":[
        "Sisauli"
    ],
    "name:ita_x_preferred":[
        "Sisauli"
    ],
    "name:mlg_x_preferred":[
        "Sisauli"
    ],
    "name:msa_x_preferred":[
        "Sisauli"
    ],
    "name:nld_x_preferred":[
        "Sisauli"
    ],
    "name:pol_x_preferred":[
        "Sisauli"
    ],
    "name:por_x_preferred":[
        "Sisauli"
    ],
    "name:swe_x_preferred":[
        "Sisauli"
    ],
    "name:urd_x_preferred":[
        "\u0633\u06cc\u0633\u0648\u0644\u06cc"
    ],
    "name:vie_x_preferred":[
        "Sisauli"
    ],
    "name:zho_x_preferred":[
        "\u897f\u7ecd\u5229"
    ],
    "wof:name":"Sisauli",
    "wof:placetype":"neighbourhood"
},
  "geometry": {"coordinates":[77.25959,30.14297],"type":"Point"}
}