{
  "type": "Feature",
  "properties": {
    "gn:admin1_code":"36",
    "gn:admin2_code":"180.0",
    "gn:asciiname":"Harha Purwa",
    "gn:country_code":"IN",
    "gn:dem":123,
    "gn:feature_class":"P",
    "gn:feature_code":"PPL",
    "gn:name":"Harha Purwa",
    "gn:population":0,
    "gn:timezone":"Asia/Kolkata",
    "iso:country":"IN",
    "ks:ks_alt_nam":"HADAHA PURWA",
    "ks:ks_name":"Hadaha Purwa",
    "ks:ks_pop":131,
    "ks:ks_type":"HABITATION",
    "name:eng_x_preferred":[
        "Hadaha Purwa"
    ],
    "name:eng_x_variant":[
        "Harha Purwa"
    ],
    "wof:name":"Hadaha Purwa",
    "wof:placetype":"locality",
    "wof:population":131
},
  "geometry": {"coordinates":[81.68164299999999,27.525662],"type":"Point"}
}