{
  "type": "Feature",
  "properties": {
    "iso:country":"IN",
    "ks:ks_alt_nam":"Vaoigadda tanda",
    "ks:ks_name":"Vaoigadda Tanda",
    "ks:ks_pop":99,
    "ks:ks_type":"HABITATION",
    "name:eng_x_preferred":[
        "Vaoigadda Tanda"
    ],
    "wof:name":"Vaoigadda Tanda",
    "wof:placetype":"locality",
    "wof:population":99
},
  "geometry": {"coordinates":[78.291912,16.871202],"type":"Point"}
}