{
  "type": "Feature",
  "properties": {
    "iso:country":"IN",
    "ks:ks_name":"Kalapathar",
    "ks:ks_pop":370,
    "ks:ks_type":"HABITATION",
    "name:eng_x_preferred":[
        "Kalapathar"
    ],
    "wof:name":"Kalapathar",
    "wof:placetype":"locality",
    "wof:population":370
},
  "geometry": {"coordinates":[86.755292,22.661959],"type":"Point"}
}