{
  "type": "Feature",
  "properties": {
    "iso:country":"IN",
    "ks:ks_name":"Bhagnahir",
    "ks:ks_pop":0,
    "ks:ks_type":"VILLAGE",
    "name:eng_x_preferred":[
        "Bhagnahir"
    ],
    "wof:name":"Bhagnahir",
    "wof:placetype":"locality",
    "wof:population":0
},
  "geometry": {"coordinates":[86.460465,23.981298],"type":"Point"}
}