{
  "type": "Feature",
  "properties": {
    "gn:admin1_code":"11",
    "gn:admin2_code":"23.0",
    "gn:asciiname":"Matola",
    "gn:country_code":"IN",
    "gn:dem":1651,
    "gn:feature_class":"P",
    "gn:feature_code":"PPL",
    "gn:name":"Matola",
    "gn:population":0,
    "gn:timezone":"Asia/Kolkata",
    "iso:country":"IN",
    "wof:name":"Matola",
    "wof:placetype":"locality"
},
  "geometry": {"coordinates":[76.01016,32.56339000000001],"type":"Point"}
}