{
  "type": "Feature",
  "properties": {
    "gn:admin1_code":"34.0",
    "gn:admin2_code":"229",
    "gn:asciiname":"Giriak",
    "gn:country_code":"IN",
    "gn:dem":75,
    "gn:feature_class":"P",
    "gn:feature_code":"PPL",
    "gn:name":"Giriak",
    "gn:population":0,
    "gn:timezone":"Asia/Kolkata",
    "iso:country":"IN",
    "wof:name":"Giriak",
    "wof:placetype":"locality"
},
  "geometry": {"coordinates":[85.52873000000002,25.02771],"type":"Point"}
}