{
  "type": "Feature",
  "properties": {
    "gn:admin1_code":"35",
    "gn:admin2_code":"467.0",
    "gn:asciiname":"Amba",
    "gn:country_code":"IN",
    "gn:dem":624,
    "gn:feature_class":"P",
    "gn:feature_code":"PPL",
    "gn:name":"Amba",
    "gn:population":0,
    "gn:timezone":"Asia/Kolkata",
    "iso:country":"IN",
    "wof:name":"Amba",
    "wof:placetype":"locality"
},
  "geometry": {"coordinates":[76.00988000000002,21.5338],"type":"Point"}
}