{
  "type": "Feature",
  "properties": {
    "iso:country":"IN",
    "ks:ks_alt_nam":"tutiha",
    "ks:ks_name":"Tutiha",
    "ks:ks_pop":154,
    "ks:ks_type":"HABITATION",
    "ks:ks_uagg_main":0,
    "name:eng_x_preferred":[
        "Tutiha"
    ],
    "wof:name":"Tutiha",
    "wof:placetype":"neighbourhood",
    "wof:population":154
},
  "geometry": {"coordinates":[81.90300499999999,27.487337],"type":"Point"}
}