{
  "type": "Feature",
  "properties": {
    "iso:country":"IN",
    "ks:ks_name":"Baj Guda Para",
    "ks:ks_pop":186,
    "ks:ks_type":"HABITATION",
    "name:eng_x_preferred":[
        "Baj Guda Para"
    ],
    "wof:name":"Baj Guda Para",
    "wof:placetype":"locality",
    "wof:population":186
},
  "geometry": {"coordinates":[82.055894,19.336949],"type":"Point"}
}