{
  "type": "Feature",
  "properties": {
    "iso:country":"IN",
    "ks:ks_name":"Rampuriya",
    "ks:ks_pop":4,
    "ks:ks_type":"VILLAGE",
    "name:eng_x_preferred":[
        "Rampuriya"
    ],
    "wof:name":"Rampuriya",
    "wof:placetype":"locality",
    "wof:population":4
},
  "geometry": {"coordinates":[75.331276,25.209646],"type":"Point"}
}