{
  "type": "Feature",
  "properties": {
    "iso:country":"IN",
    "ks:ks_name":"Khetauli",
    "ks:ks_pop":853,
    "ks:ks_type":"VILLAGE",
    "name:eng_x_preferred":[
        "Khetauli"
    ],
    "wof:name":"Khetauli",
    "wof:placetype":"locality",
    "wof:population":853
},
  "geometry": {"coordinates":[81.476011,23.351712],"type":"Point"}
}