{
  "type": "Feature",
  "properties": {
    "gn:admin1_code":"36",
    "gn:admin2_code":"180.0",
    "gn:asciiname":"Sohna",
    "gn:country_code":"IN",
    "gn:dem":123,
    "gn:feature_class":"P",
    "gn:feature_code":"PPL",
    "gn:name":"Sohna",
    "gn:population":0,
    "gn:timezone":"Asia/Kolkata",
    "iso:country":"IN",
    "name:ben_x_preferred":[
        "\u09b8\u09cb\u09b9\u09a8\u09be"
    ],
    "name:bpy_x_preferred":[
        "\u09b8\u09cb\u09b9\u09a8\u09be"
    ],
    "name:ceb_x_preferred":[
        "Sohna"
    ],
    "name:deu_x_preferred":[
        "Sohna"
    ],
    "name:hin_x_preferred":[
        "\u0938\u094b\u0939\u0928\u093e"
    ],
    "name:ita_x_preferred":[
        "Sohna"
    ],
    "name:msa_x_preferred":[
        "Sohna"
    ],
    "name:ori_x_preferred":[
        "\u0b38\u0b4b\u0b39\u0b28\u0b3e"
    ],
    "name:por_x_preferred":[
        "Sohna"
    ],
    "name:spa_x_preferred":[
        "Sohna"
    ],
    "name:swe_x_preferred":[
        "Sohna"
    ],
    "name:vie_x_preferred":[
        "Sohna"
    ],
    "name:zho_x_preferred":[
        "\u7d22\u8d6b\u7eb3"
    ],
    "wof:name":"Sohna",
    "wof:placetype":"locality"
},
  "geometry": {"coordinates":[81.52625999999999,27.59521],"type":"Point"}
}