{
  "type": "Feature",
  "properties": {
    "gn:admin1_code":"25.0",
    "gn:admin2_code":"633.0",
    "gn:asciiname":"Ayyampalaiyam",
    "gn:country_code":"IN",
    "gn:dem":311,
    "gn:feature_class":"P",
    "gn:feature_code":"PPL",
    "gn:name":"Ayyamp\u0101laiyam",
    "gn:population":0,
    "gn:timezone":"Asia/Kolkata",
    "iso:country":"IN",
    "ks:ks_name":"Ayyampalayam",
    "ks:ks_pop":129,
    "ks:ks_type":"HABITATION",
    "name:eng_x_preferred":[
        "Ayyampalayam"
    ],
    "name:eng_x_variant":[
        "Ayyampalaiyam"
    ],
    "wof:name":"Ayyampalayam",
    "wof:placetype":"locality",
    "wof:population":129
},
  "geometry": {"coordinates":[77.469931,10.947538],"type":"Point"}
}