{
  "type": "Feature",
  "properties": {
    "gn:admin1_code":"36",
    "gn:admin2_code":"134.0",
    "gn:asciiname":"Laluwala",
    "gn:country_code":"IN",
    "gn:dem":266,
    "gn:feature_class":"P",
    "gn:feature_code":"PPL",
    "gn:name":"L\u0101l\u016bw\u0101la",
    "gn:population":0,
    "gn:timezone":"Asia/Kolkata",
    "iso:country":"IN",
    "name:und_x_variant":[
        "L\u0101l\u016bw\u0101la",
        "Tat\u0101rpur L\u0101lu"
    ],
    "wof:name":"Laluwala",
    "wof:placetype":"locality"
},
  "geometry": {"coordinates":[78.336,29.5983],"type":"Point"}
}