{
  "type": "Feature",
  "properties": {
    "iso:country":"IN",
    "ks:ks_name":"Koppulakota",
    "ks:ks_pop":211,
    "ks:ks_type":"HABITATION",
    "name:eng_x_preferred":[
        "Koppulakota"
    ],
    "wof:name":"Koppulakota",
    "wof:placetype":"locality",
    "wof:population":211
},
  "geometry": {"coordinates":[81.993976,17.904319],"type":"Point"}
}