{
  "type": "Feature",
  "properties": {
    "iso:country":"IN",
    "ks:ks_name":"Jampal",
    "ks:ks_pop":66,
    "ks:ks_type":"HABITATION",
    "name:eng_x_preferred":[
        "Jampal"
    ],
    "wof:name":"Jampal",
    "wof:placetype":"locality",
    "wof:population":66
},
  "geometry": {"coordinates":[84.592456,21.32958],"type":"Point"}
}