{
  "type": "Feature",
  "properties": {
    "gn:admin1_code":"19.0",
    "gn:admin2_code":"568.0",
    "gn:asciiname":"Mandali",
    "gn:country_code":"IN",
    "gn:dem":576,
    "gn:feature_class":"P",
    "gn:feature_code":"PPL",
    "gn:name":"Mandali",
    "gn:population":0,
    "gn:timezone":"Asia/Kolkata",
    "iso:country":"IN",
    "name:ara_x_preferred":[
        "\u0645\u0646\u062f\u0644\u064a"
    ],
    "name:ben_x_preferred":[
        "\u09ae\u09be\u09a8\u09cd\u09a6\u09be\u09b2\u09bf"
    ],
    "name:ell_x_preferred":[
        "\u039c\u03ac\u03bd\u03c4\u03b1\u03bb\u03b9"
    ],
    "name:fra_x_preferred":[
        "Mandali"
    ],
    "name:heb_x_preferred":[
        "\u05de\u05e0\u05d3\u05dc\u05d9"
    ],
    "name:hin_x_preferred":[
        "\u092e\u0902\u0921\u093e\u0932\u0940"
    ],
    "name:hun_x_preferred":[
        "Mandali"
    ],
    "name:ind_x_preferred":[
        "Mandali"
    ],
    "name:ita_x_preferred":[
        "Mandali"
    ],
    "name:jpn_x_preferred":[
        "\u30de\u30f3\u30c0\u30ea"
    ],
    "name:kor_x_preferred":[
        "\ub9cc\ub2ec\ub9ac"
    ],
    "name:pol_x_preferred":[
        "Mandali"
    ],
    "name:spa_x_preferred":[
        "Mandali"
    ],
    "name:tur_x_preferred":[
        "Mandali"
    ],
    "name:ukr_x_preferred":[
        "\u041c\u0430\u043d\u0434\u0430\u043b\u0456"
    ],
    "name:vie_x_preferred":[
        "Mandali"
    ],
    "wof:name":"Mandali",
    "wof:placetype":"locality"
},
  "geometry": {"coordinates":[75.5624,13.91112],"type":"Point"}
}