{
  "type": "Feature",
  "properties": {
    "gn:admin1_code":"19.0",
    "gn:admin2_code":"568.0",
    "gn:asciiname":"Mandali",
    "gn:country_code":"IN",
    "gn:dem":576,
    "gn:feature_class":"P",
    "gn:feature_code":"PPL",
    "gn:name":"Mandali",
    "gn:population":0,
    "gn:timezone":"Asia/Kolkata",
    "iso:country":"IN",
    "name:ara_x_preferred":[
        "\u0645\u0646\u062f\u0644\u064a"
    ],
    "name:fra_x_preferred":[
        "Mandali"
    ],
    "wof:name":"Mandali",
    "wof:placetype":"locality"
},
  "geometry": {"coordinates":[75.5624,13.91112],"type":"Point"}
}