{
  "type": "Feature",
  "properties": {
    "gn:admin1_code":"12.0",
    "gn:admin2_code":"17.0",
    "gn:asciiname":"Makrota",
    "gn:country_code":"IN",
    "gn:dem":1502,
    "gn:feature_class":"P",
    "gn:feature_code":"PPL",
    "gn:name":"Makrota",
    "gn:population":0,
    "gn:timezone":"Asia/Kolkata",
    "iso:country":"IN",
    "wof:name":"Makrota",
    "wof:placetype":"locality"
},
  "geometry": {"coordinates":[75.18214999999999,33.36487],"type":"Point"}
}