{
  "type": "Feature",
  "properties": {
    "gn:admin1_code":"36.0",
    "gn:admin2_code":"176.0",
    "gn:asciiname":"Siddhaur",
    "gn:country_code":"IN",
    "gn:dem":120,
    "gn:feature_class":"P",
    "gn:feature_code":"PPL",
    "gn:name":"Siddhaur",
    "gn:population":0,
    "gn:timezone":"Asia/Kolkata",
    "iso:country":"IN",
    "name:bpy_x_preferred":[
        "\u09b8\u09bf\u09a6\u09cd\u09a7\u09cc\u09b0"
    ],
    "name:ceb_x_preferred":[
        "Siddhaur"
    ],
    "name:ita_x_preferred":[
        "Siddhaur"
    ],
    "name:msa_x_preferred":[
        "Siddhaur"
    ],
    "name:nld_x_preferred":[
        "Siddhaur"
    ],
    "name:pol_x_preferred":[
        "Siddhaur"
    ],
    "name:por_x_preferred":[
        "Siddhaur"
    ],
    "name:swe_x_preferred":[
        "Siddhaur"
    ],
    "name:urd_x_preferred":[
        "\u0633\u062f\u06be\u0648\u0631"
    ],
    "name:vie_x_preferred":[
        "Siddhaur"
    ],
    "name:zho_x_preferred":[
        "\u897f\u9053\u5c14"
    ],
    "wof:name":"Siddhaur",
    "wof:placetype":"locality"
},
  "geometry": {"coordinates":[81.40271,26.76988],"type":"Point"}
}