{
  "type": "Feature",
  "properties": {
    "gn:admin1_code":"36.0",
    "gn:admin2_code":"174.0",
    "gn:asciiname":"Amina",
    "gn:country_code":"IN",
    "gn:dem":107,
    "gn:feature_class":"P",
    "gn:feature_code":"PPL",
    "gn:name":"Am\u012bna",
    "gn:population":0,
    "gn:timezone":"Asia/Kolkata",
    "iso:country":"IN",
    "ks:ks_alt_nam":"Am\u012bna",
    "ks:ks_name":"Amina",
    "ks:ks_pop":1237,
    "ks:ks_type":"VILLAGE",
    "ks:ks_uagg_main":0,
    "name:ara_x_preferred":[
        "\u0627\u0644\u0645\u0644\u0643\u0629 \u0623\u0645\u064a\u0646\u0629"
    ],
    "name:eng_x_preferred":[
        "Amina"
    ],
    "name:eng_x_variant":[
        "Am\u012bna"
    ],
    "name:hau_x_preferred":[
        "Sarauniya Amina"
    ],
    "name:hin_x_preferred":[
        "\u0905\u092e\u0940\u0928\u093e"
    ],
    "name:mal_x_preferred":[
        "\u0d05\u0d2e\u0d3f\u0d28"
    ],
    "wof:name":"Amina",
    "wof:placetype":"neighbourhood",
    "wof:population":1237
},
  "geometry": {"coordinates":[81.326322,25.377768],"type":"Point"}
}