{
  "type": "Feature",
  "properties": {
    "iso:country":"IN",
    "ks:ks_name":"Bhagorawas",
    "ks:ks_pop":413,
    "ks:ks_type":"HABITATION",
    "name:eng_x_preferred":[
        "Bhagorawas"
    ],
    "wof:name":"Bhagorawas",
    "wof:placetype":"locality",
    "wof:population":413
},
  "geometry": {"coordinates":[73.32525,24.30085],"type":"Point"}
}