{
  "type": "Feature",
  "properties": {
    "iso:country":"IN",
    "ks:ks_name":"Bandarlapalle",
    "ks:ks_pop":42,
    "ks:ks_type":"HABITATION",
    "name:eng_x_preferred":[
        "Bandarlapalle"
    ],
    "wof:name":"Bandarlapalle",
    "wof:placetype":"locality",
    "wof:population":42
},
  "geometry": {"coordinates":[77.426214,13.820365],"type":"Point"}
}