{
  "type": "Feature",
  "properties": {
    "iso:country":"IN",
    "ks:ks_name":"Gania Sadhu Para",
    "ks:ks_pop":60,
    "ks:ks_type":"HABITATION",
    "name:eng_x_preferred":[
        "Gania Sadhu Para"
    ],
    "wof:name":"Gania Sadhu Para",
    "wof:placetype":"locality",
    "wof:population":60
},
  "geometry": {"coordinates":[91.47488199999999,23.924608],"type":"Point"}
}