{
  "type": "Feature",
  "properties": {
    "iso:country":"IN",
    "ks:ks_name":"Bela Gopi",
    "ks:ks_pop":903,
    "ks:ks_type":"VILLAGE",
    "name:eng_x_preferred":[
        "Bela Gopi"
    ],
    "wof:name":"Bela Gopi",
    "wof:placetype":"locality",
    "wof:population":903
},
  "geometry": {"coordinates":[85.575553,26.106513],"type":"Point"}
}