{
  "type": "Feature",
  "properties": {
    "iso:country":"IN",
    "ks:ks_name":"Killupalli",
    "ks:ks_pop":25,
    "ks:ks_type":"HABITATION",
    "name:eng_x_preferred":[
        "Killupalli"
    ],
    "wof:name":"Killupalli",
    "wof:placetype":"locality",
    "wof:population":25
},
  "geometry": {"coordinates":[82.34099399999999,18.04612],"type":"Point"}
}