{
  "type": "Feature",
  "properties": {
    "iso:country":"IN",
    "ks:ks_name":"Chak Haji Urf Shekhpur",
    "ks:ks_pop":700,
    "ks:ks_type":"VILLAGE",
    "name:eng_x_preferred":[
        "Chak Haji Urf Shekhpur"
    ],
    "wof:name":"Chak Haji Urf Shekhpur",
    "wof:placetype":"locality",
    "wof:population":700
},
  "geometry": {"coordinates":[84.10599000000001,26.043136],"type":"Point"}
}