{
  "type": "Feature",
  "properties": {
    "iso:country":"IN",
    "ks:ks_name":"Sungamuhan-I",
    "ks:ks_pop":346,
    "ks:ks_type":"VILLAGE",
    "name:eng_x_preferred":[
        "Sungamuhan-I"
    ],
    "wof:name":"Sungamuhan-I",
    "wof:placetype":"locality",
    "wof:population":346
},
  "geometry": {"coordinates":[87.30271,21.652527],"type":"Point"}
}