{
  "type": "Feature",
  "properties": {
    "iso:country":"IN",
    "ks:ks_name":"Kaikatoli",
    "ks:ks_pop":97,
    "ks:ks_type":"HABITATION",
    "name:eng_x_preferred":[
        "Kaikatoli"
    ],
    "wof:name":"Kaikatoli",
    "wof:placetype":"locality",
    "wof:population":97
},
  "geometry": {"coordinates":[85.30699799999999,22.829377],"type":"Point"}
}