{
  "type": "Feature",
  "properties": {
    "iso:country":"IN",
    "name:ara_x_preferred":[
        "\u0643\u0627\u0644\u064a\u0645\u0628\u0648\u0646\u062c"
    ],
    "name:ben_x_preferred":[
        "\u0995\u09be\u09b2\u09bf\u09ae\u09cd\u09aa\u0982"
    ],
    "name:bpy_x_preferred":[
        "\u0995\u09be\u09b2\u09bf\u09ae\u09cd\u09aa\u0982"
    ],
    "name:cat_x_preferred":[
        "Kalimpong"
    ],
    "name:ceb_x_preferred":[
        "K\u0101limpang"
    ],
    "name:cym_x_preferred":[
        "Kalimpong"
    ],
    "name:deu_x_preferred":[
        "Kalimpong"
    ],
    "name:eng_x_preferred":[
        "Kalimpong"
    ],
    "name:fra_x_preferred":[
        "Kalimpong"
    ],
    "name:guj_x_preferred":[
        "\u0a95\u0abe\u0ab2\u0abf\u0aae\u0aaa\u0acb\u0a82\u0a97"
    ],
    "name:hif_x_preferred":[
        "Kalimpong"
    ],
    "name:hin_x_preferred":[
        "\u0915\u093e\u0932\u093f\u0902\u092a\u094b\u0902\u0917"
    ],
    "name:hye_x_preferred":[
        "\u053f\u0561\u056c\u056b\u0574\u057a\u0578\u0576\u0563"
    ],
    "name:ind_x_preferred":[
        "Kalimpong"
    ],
    "name:ita_x_preferred":[
        "Kalimpong"
    ],
    "name:jpn_x_preferred":[
        "\u30ab\u30ea\u30f3\u30dd\u30f3"
    ],
    "name:kan_x_preferred":[
        "\u0c95\u0cbe\u0cb2\u0cbf\u0c82\u0caa\u0cbe\u0c82\u0c97\u0ccd"
    ],
    "name:kor_x_preferred":[
        "\uce7c\ub9bc\ud401"
    ],
    "name:mai_x_preferred":[
        "\u0915\u093e\u0932\u093f\u092e\u094d\u092a\u094b\u0919"
    ],
    "name:mar_x_preferred":[
        "\u0915\u093e\u0932\u093f\u0902\u092a\u094b\u0902\u0917"
    ],
    "name:mlg_x_preferred":[
        "Kalimpong"
    ],
    "name:msa_x_preferred":[
        "Kalimpong"
    ],
    "name:nan_x_preferred":[
        "Kalimpong"
    ],
    "name:nep_x_preferred":[
        "\u0915\u093e\u0932\u093f\u092e\u094d\u092a\u094b\u0919"
    ],
    "name:new_x_preferred":[
        "\u0915\u093e\u0932\u093f\u092e\u094d\u092a\u094b\u0919"
    ],
    "name:nld_x_preferred":[
        "Kalimpong"
    ],
    "name:ori_x_preferred":[
        "Kalimpong"
    ],
    "name:pam_x_preferred":[
        "Kalimpong"
    ],
    "name:pan_x_preferred":[
        "\u0a15\u0a3e\u0a32\u0a3f\u0a70\u0a2a\u0a4b\u0a70\u0a17"
    ],
    "name:pol_x_preferred":[
        "Kalimpong"
    ],
    "name:por_x_preferred":[
        "Kalimpong"
    ],
    "name:rus_x_preferred":[
        "\u041a\u0430\u043b\u0438\u043c\u043f\u043e\u043d\u0433"
    ],
    "name:slk_x_preferred":[
        "Kalimpong"
    ],
    "name:spa_x_preferred":[
        "Kalimpong"
    ],
    "name:swe_x_preferred":[
        "Kalimpong"
    ],
    "name:tam_x_preferred":[
        "\u0b95\u0bbe\u0bb2\u0bbf\u0bae\u0bcd\u0baa\u0bcb\u0b99\u0bcd"
    ],
    "name:tel_x_preferred":[
        "\u0c15\u0c3e\u0c32\u0c3f\u0c02\u0c2a\u0c3e\u0c02\u0c17\u0c4d"
    ],
    "name:ukr_x_preferred":[
        "\u041a\u0430\u043b\u0456\u043c\u043f\u043e\u043d\u0491"
    ],
    "name:urd_x_preferred":[
        "\u06a9\u0627\u0644\u06cc\u0645\u067e\u0648\u0646\u062c"
    ],
    "name:vie_x_preferred":[
        "Kalimpong"
    ],
    "name:zho_x_preferred":[
        "\u5676\u502b\u5821"
    ],
    "qs:name":"Kalimpong",
    "qs:name_adm0":"India",
    "qs:name_adm1":"West Bengal",
    "qs:photos":884,
    "qs:photos_1k":179,
    "qs:photos_9k":4,
    "qs:photos_9r":6,
    "qs:photos_all":884,
    "qs:photos_sr":10,
    "qs:placetype":"Town",
    "qs:pop_sr":"0",
    "wd:wordcount":5306,
    "wof:name":"Kalimpong",
    "wof:placetype":"locality"
},
  "geometry": {"coordinates":[88.4729,27.058208],"type":"Point"}
}