{
  "type": "Feature",
  "properties": {
    "iso:country":"IN",
    "ks:ks_name":"Ratanpur",
    "ks:ks_pop":1509,
    "ks:ks_type":"VILLAGE",
    "ks:ks_uagg_main":0,
    "name:eng_x_preferred":[
        "Ratanpur"
    ],
    "wof:name":"Ratanpur",
    "wof:placetype":"neighbourhood",
    "wof:population":1509
},
  "geometry": {"coordinates":[85.593535,26.275893],"type":"Point"}
}