{
  "type": "Feature",
  "properties": {
    "iso:country":"IN",
    "ks:ks_name":"Dakshin Marichbari",
    "ks:ks_pop":0,
    "ks:ks_type":"VILLAGE",
    "name:eng_x_preferred":[
        "Dakshin Marichbari"
    ],
    "wof:name":"Dakshin Marichbari",
    "wof:placetype":"locality",
    "wof:population":0
},
  "geometry": {"coordinates":[88.76471600000001,26.547677],"type":"Point"}
}