{
  "type": "Feature",
  "properties": {
    "gn:admin1_code":"35.0",
    "gn:admin2_code":"467",
    "gn:asciiname":"Khaknar",
    "gn:country_code":"IN",
    "gn:dem":302,
    "gn:feature_class":"P",
    "gn:feature_code":"PPL",
    "gn:name":"Khakn\u0101r",
    "gn:population":0,
    "gn:timezone":"Asia/Kolkata",
    "iso:country":"IN",
    "wof:name":"Khaknar",
    "wof:placetype":"neighbourhood"
},
  "geometry": {"coordinates":[76.56926,21.36738],"type":"Point"}
}