{
  "type": "Feature",
  "properties": {
    "iso:country":"IN",
    "ks:ks_alt_nam":"BASANTPUR",
    "ks:ks_name":"Basantpur",
    "ks:ks_pop":128,
    "ks:ks_type":"HABITATION",
    "name:eng_x_preferred":[
        "Basantpur"
    ],
    "wof:name":"Basantpur",
    "wof:placetype":"locality",
    "wof:population":128
},
  "geometry": {"coordinates":[84.24589899999999,24.258979],"type":"Point"}
}