{
  "type": "Feature",
  "properties": {
    "iso:country":"IN",
    "ks:ks_name":"Kahandolsa",
    "ks:ks_pop":791,
    "ks:ks_type":"HABITATION",
    "name:eng_x_preferred":[
        "Kahandolsa"
    ],
    "wof:name":"Kahandolsa",
    "wof:placetype":"locality",
    "wof:population":791
},
  "geometry": {"coordinates":[73.518281,20.482933],"type":"Point"}
}