{
  "type": "Feature",
  "properties": {
    "iso:country":"IN",
    "ks:ks_name":"Dongariguda",
    "ks:ks_pop":745,
    "ks:ks_type":"HABITATION",
    "name:eng_x_preferred":[
        "Dongariguda"
    ],
    "wof:name":"Dongariguda",
    "wof:placetype":"locality",
    "wof:population":745
},
  "geometry": {"coordinates":[81.803603,19.159698],"type":"Point"}
}