{
  "type": "Feature",
  "properties": {
    "iso:country":"IN",
    "ks:ks_alt_nam":"satyanagarpahi",
    "ks:ks_name":"Satyanagarpahi",
    "ks:ks_pop":528,
    "ks:ks_type":"HABITATION",
    "name:eng_x_preferred":[
        "Satyanagarpahi"
    ],
    "wof:name":"Satyanagarpahi",
    "wof:placetype":"locality",
    "wof:population":528
},
  "geometry": {"coordinates":[86.95776499999999,21.408056],"type":"Point"}
}