{
  "type": "Feature",
  "properties": {
    "gn:admin1_code":"36",
    "gn:admin2_code":"188.0",
    "gn:asciiname":"Khalsa",
    "gn:country_code":"IN",
    "gn:dem":84,
    "gn:feature_class":"P",
    "gn:feature_code":"PPL",
    "gn:name":"Kh\u0101lsa",
    "gn:population":0,
    "gn:timezone":"Asia/Kolkata",
    "iso:country":"IN",
    "name:cat_x_preferred":[
        "Khalsa"
    ],
    "name:fas_x_preferred":[
        "\u062e\u0627\u0644\u0635\u0647"
    ],
    "name:fra_x_preferred":[
        "Khalsa"
    ],
    "name:guj_x_preferred":[
        "\u0a96\u0abe\u0ab2\u0ab8\u0abe"
    ],
    "name:heb_x_preferred":[
        "\u05e7\u05d4\u05dc\u05e1\u05d4"
    ],
    "name:hin_x_preferred":[
        "\u0916\u093c\u093e\u0932\u0938\u093e"
    ],
    "name:ind_x_preferred":[
        "Khalsa"
    ],
    "name:ita_x_preferred":[
        "Kh\u0101ls\u0101"
    ],
    "name:jpn_x_preferred":[
        "\u30ab\u30fc\u30eb\u30b5\u30fc"
    ],
    "name:mar_x_preferred":[
        "\u0916\u093e\u0932\u0938\u093e \u092a\u0902\u0925"
    ],
    "name:pan_x_preferred":[
        "\u0a16\u0a3c\u0a3e\u0a32\u0a38\u0a3e"
    ],
    "name:pnb_x_preferred":[
        "\u062e\u0627\u0644\u0635\u06c1"
    ],
    "name:pol_x_preferred":[
        "Khalsa"
    ],
    "name:por_x_preferred":[
        "Khalsa"
    ],
    "name:swe_x_preferred":[
        "Khalsa"
    ],
    "name:tam_x_preferred":[
        "\u0b95\u0bbe\u0bb2\u0bcd\u0b9a\u0bbe"
    ],
    "name:tel_x_preferred":[
        "\u0c16\u0c32\u0c4d\u0c38\u0c3e"
    ],
    "name:tha_x_preferred":[
        "\u0e02\u0e32\u0e25\u0e2a\u0e32"
    ],
    "name:urd_x_preferred":[
        "\u062e\u0627\u0644\u0635\u06c1"
    ],
    "wof:name":"Khalsa",
    "wof:placetype":"locality"
},
  "geometry": {"coordinates":[83.24803,26.56217],"type":"Point"}
}