{
  "type": "Feature",
  "properties": {
    "iso:country":"IN",
    "ks:ks_name":"Dhansai Para",
    "ks:ks_pop":197,
    "ks:ks_type":"HABITATION",
    "name:eng_x_preferred":[
        "Dhansai Para"
    ],
    "wof:name":"Dhansai Para",
    "wof:placetype":"locality",
    "wof:population":197
},
  "geometry": {"coordinates":[91.765925,23.602668],"type":"Point"}
}