{
  "type": "Feature",
  "properties": {
    "gn:admin1_code":"19.0",
    "gn:admin2_code":"568.0",
    "gn:asciiname":"Kirgulige",
    "gn:country_code":"IN",
    "gn:dem":603,
    "gn:feature_class":"P",
    "gn:feature_code":"PPL",
    "gn:name":"K\u012brgulige",
    "gn:population":0,
    "gn:timezone":"Asia/Kolkata",
    "iso:country":"IN",
    "wof:name":"Kirgulige",
    "wof:placetype":"locality"
},
  "geometry": {"coordinates":[75.01363000000001,13.86222],"type":"Point"}
}