{
  "type": "Feature",
  "properties": {
    "iso:country":"IN",
    "ks:ks_name":"Barakuskuta",
    "ks:ks_pop":148,
    "ks:ks_type":"VILLAGE",
    "name:eng_x_preferred":[
        "Barakuskuta"
    ],
    "wof:name":"Barakuskuta",
    "wof:placetype":"locality",
    "wof:population":148
},
  "geometry": {"coordinates":[87.462132,24.5993],"type":"Point"}
}