{
  "type": "Feature",
  "properties": {
    "iso:country":"IN",
    "ks:ks_alt_nam":"Pakri B\u0101ng\u0101li",
    "ks:ks_name":"Pakri Bangali",
    "ks:ks_pop":2115,
    "ks:ks_type":"VILLAGE",
    "ks:ks_uagg_main":0,
    "name:eng_x_preferred":[
        "Pakri Bangali"
    ],
    "name:eng_x_variant":[
        "Pakri B\u0101ng\u0101li"
    ],
    "wof:name":"Pakri Bangali",
    "wof:placetype":"neighbourhood",
    "wof:population":2115
},
  "geometry": {"coordinates":[84.366626,26.227969],"type":"Point"}
}