{
  "type": "Feature",
  "properties": {
    "iso:country":"IN",
    "ks:ks_name":"Palem",
    "ks:ks_pop":45,
    "ks:ks_type":"VILLAGE",
    "name:eng_x_preferred":[
        "Palem"
    ],
    "wof:name":"Palem",
    "wof:placetype":"locality",
    "wof:population":45
},
  "geometry": {"coordinates":[87.37596499999999,24.785594],"type":"Point"}
}