{
  "type": "Feature",
  "properties": {
    "iso:country":"IN",
    "ks:ks_alt_nam":"ANANDNAGAR",
    "ks:ks_name":"Anandnagar",
    "ks:ks_pop":352,
    "ks:ks_type":"HABITATION",
    "name:eng_x_preferred":[
        "Anandnagar"
    ],
    "wof:name":"Anandnagar",
    "wof:placetype":"locality",
    "wof:population":352
},
  "geometry": {"coordinates":[75.40012400000001,17.125627],"type":"Point"}
}