{
  "type": "Feature",
  "properties": {
    "iso:country":"IN",
    "ks:ks_alt_nam":"Nagla B\u0101han",
    "ks:ks_name":"Nagla Bahan",
    "ks:ks_type":"VILLAGE",
    "name:eng_x_preferred":[
        "Nagla Bahan"
    ],
    "name:eng_x_variant":[
        "Nagla B\u0101han"
    ],
    "wof:name":"Nagla Bahan",
    "wof:placetype":"locality"
},
  "geometry": {"coordinates":[77.36093700000001,28.831597],"type":"Point"}
}