{
  "type": "Feature",
  "properties": {
    "iso:country":"IN",
    "ks:ks_name":"Puraori",
    "ks:ks_pop":22,
    "ks:ks_type":"VILLAGE",
    "name:eng_x_preferred":[
        "Puraori"
    ],
    "wof:name":"Puraori",
    "wof:placetype":"locality",
    "wof:population":22
},
  "geometry": {"coordinates":[83.245841,26.337903],"type":"Point"}
}