{
  "type": "Feature",
  "properties": {
    "gn:admin1_code":"40",
    "gn:admin2_code":"540.0",
    "gn:asciiname":"Ubalkeshavapuram",
    "gn:country_code":"IN",
    "gn:dem":429,
    "gn:feature_class":"P",
    "gn:feature_code":"PPL",
    "gn:name":"\u016abalkeshavapuram",
    "gn:population":0,
    "gn:timezone":"Asia/Kolkata",
    "iso:country":"IN",
    "wof:name":"Ubalkeshavapuram",
    "wof:placetype":"locality"
},
  "geometry": {"coordinates":[79.07598,17.75162000000001],"type":"Point"}
}