{
  "type": "Feature",
  "properties": {
    "iso:country":"IN",
    "ks:ks_alt_nam":"TAKJHIRI FV",
    "ks:ks_name":"Takjhiri Fv",
    "ks:ks_pop":496,
    "ks:ks_type":"HABITATION",
    "name:eng_x_preferred":[
        "Takjhiri Fv"
    ],
    "wof:name":"Takjhiri Fv",
    "wof:placetype":"locality",
    "wof:population":496
},
  "geometry": {"coordinates":[77.411495,21.815624],"type":"Point"}
}