{
  "type": "Feature",
  "properties": {
    "iso:country":"IN",
    "ks:ks_name":"Dunda Ankara",
    "ks:ks_pop":71,
    "ks:ks_type":"HABITATION",
    "name:eng_x_preferred":[
        "Dunda Ankara"
    ],
    "wof:name":"Dunda Ankara",
    "wof:placetype":"locality",
    "wof:population":71
},
  "geometry": {"coordinates":[78.458001,29.96395],"type":"Point"}
}