{
  "type": "Feature",
  "properties": {
    "iso:country":"IN",
    "ks:ks_name":"Ganjana",
    "ks:ks_pop":53,
    "ks:ks_type":"VILLAGE",
    "name:eng_x_preferred":[
        "Ganjana"
    ],
    "wof:name":"Ganjana",
    "wof:placetype":"locality",
    "wof:population":53
},
  "geometry": {"coordinates":[84.364132,19.819606],"type":"Point"}
}