{
  "type": "Feature",
  "properties": {
    "iso:country":"IN",
    "ks:ks_alt_nam":"KOMLIBATHAN",
    "ks:ks_name":"Komlibathan",
    "ks:ks_pop":212,
    "ks:ks_type":"HABITATION",
    "name:eng_x_preferred":[
        "Komlibathan"
    ],
    "wof:name":"Komlibathan",
    "wof:placetype":"locality",
    "wof:population":212
},
  "geometry": {"coordinates":[83.878698,23.076344],"type":"Point"}
}