{
  "type": "Feature",
  "properties": {
    "gn:admin1_code":"37.0",
    "gn:admin2_code":"406.0",
    "gn:asciiname":"Khondhara",
    "gn:country_code":"IN",
    "gn:dem":359,
    "gn:feature_class":"P",
    "gn:feature_code":"PPL",
    "gn:name":"Khondhara",
    "gn:population":0,
    "gn:timezone":"Asia/Kolkata",
    "iso:country":"IN",
    "wof:name":"Khondhara",
    "wof:placetype":"locality"
},
  "geometry": {"coordinates":[82.37366999999998,22.27535],"type":"Point"}
}