{
  "type": "Feature",
  "properties": {
    "iso:country":"IN",
    "ks:ks_alt_nam":"balanadu",
    "ks:ks_name":"Balanadu",
    "ks:ks_pop":825,
    "ks:ks_type":"HABITATION",
    "name:eng_x_preferred":[
        "Balanadu"
    ],
    "wof:name":"Balanadu",
    "wof:placetype":"locality",
    "wof:population":825
},
  "geometry": {"coordinates":[76.846557,9.983051],"type":"Point"}
}