{
  "type": "Feature",
  "properties": {
    "iso:country":"IN",
    "ks:ks_name":"Papara",
    "ks:ks_pop":227,
    "ks:ks_type":"VILLAGE",
    "name:eng_x_preferred":[
        "Papara"
    ],
    "wof:name":"Papara",
    "wof:placetype":"locality",
    "wof:population":227
},
  "geometry": {"coordinates":[82.453264,25.003659],"type":"Point"}
}