{
  "type": "Feature",
  "properties": {
    "iso:country":"IN",
    "ks:ks_name":"Kumaramangalam",
    "ks:ks_pop":100,
    "ks:ks_type":"HABITATION",
    "name:eng_x_preferred":[
        "Kumaramangalam"
    ],
    "wof:name":"Kumaramangalam",
    "wof:placetype":"locality",
    "wof:population":100
},
  "geometry": {"coordinates":[79.619804,10.692326],"type":"Point"}
}