{
  "type": "Feature",
  "properties": {
    "gn:admin1_code":"38.0",
    "gn:admin2_code":"352.0",
    "gn:asciiname":"Gidakol",
    "gn:country_code":"IN",
    "gn:dem":134,
    "gn:feature_class":"P",
    "gn:feature_code":"PPL",
    "gn:name":"Gid\u0101kol",
    "gn:population":0,
    "gn:timezone":"Asia/Kolkata",
    "iso:country":"IN",
    "ks:ks_alt_nam":"Gid\u0101kol",
    "ks:ks_alt_nam_2":"Gidakol",
    "ks:ks_name":"Gidakole",
    "ks:ks_pop":14,
    "ks:ks_type":"VILLAGE",
    "name:eng_x_preferred":[
        "Gidakole"
    ],
    "name:eng_x_variant":[
        "Gidakol",
        "Gid\u0101kol"
    ],
    "wof:name":"Gidakole",
    "wof:placetype":"locality",
    "wof:population":14
},
  "geometry": {"coordinates":[87.56260899999999,25.067504],"type":"Point"}
}