{
  "type": "Feature",
  "properties": {
    "iso:country":"IN",
    "ks:ks_name":"Adiwadi",
    "ks:ks_pop":167,
    "ks:ks_type":"HABITATION",
    "name:eng_x_preferred":[
        "Adiwadi"
    ],
    "wof:name":"Adiwadi",
    "wof:placetype":"locality",
    "wof:population":167
},
  "geometry": {"coordinates":[73.166478,17.645003],"type":"Point"}
}