{
  "type": "Feature",
  "properties": {
    "gn:admin1_code":"2.0",
    "gn:admin2_code":"542.0",
    "gn:asciiname":"Akkarajupeta",
    "gn:country_code":"IN",
    "gn:dem":112,
    "gn:feature_class":"P",
    "gn:feature_code":"PPL",
    "gn:name":"Akkar\u0101jupeta",
    "gn:population":0,
    "gn:timezone":"Asia/Kolkata",
    "iso:country":"IN",
    "ks:ks_name":"Akkirajupeta",
    "ks:ks_pop":108,
    "ks:ks_type":"HABITATION",
    "name:eng_x_preferred":[
        "Akkirajupeta"
    ],
    "name:eng_x_variant":[
        "Akkarajupeta"
    ],
    "wof:name":"Akkirajupeta",
    "wof:placetype":"locality",
    "wof:population":108
},
  "geometry": {"coordinates":[83.727481,18.671361],"type":"Point"}
}