{
  "type": "Feature",
  "properties": {
    "iso:country":"IN",
    "ks:ks_name":"Ubuda",
    "ks:ks_pop":1226,
    "ks:ks_type":"VILLAGE",
    "name:eng_x_preferred":[
        "Ubuda"
    ],
    "wof:name":"Ubuda",
    "wof:placetype":"locality",
    "wof:population":1226
},
  "geometry": {"coordinates":[83.83575,21.747991],"type":"Point"}
}