{
  "type": "Feature",
  "properties": {
    "iso:country":"IN",
    "ks:ks_name":"Kundal",
    "ks:ks_pop":481,
    "ks:ks_type":"VILLAGE",
    "name:eng_x_preferred":[
        "Kundal"
    ],
    "wof:name":"Kundal",
    "wof:placetype":"locality",
    "wof:population":481
},
  "geometry": {"coordinates":[73.33610899999999,24.508159],"type":"Point"}
}