{
  "type": "Feature",
  "properties": {
    "gn:admin1_code":"25.0",
    "gn:admin2_code":"632.0",
    "gn:asciiname":"Kaliyapuram",
    "gn:country_code":"IN",
    "gn:dem":230,
    "gn:feature_class":"P",
    "gn:feature_code":"PPL",
    "gn:name":"K\u0101liy\u0101puram",
    "gn:population":0,
    "gn:timezone":"Asia/Kolkata",
    "iso:country":"IN",
    "wof:name":"Kaliyapuram",
    "wof:placetype":"locality"
},
  "geometry": {"coordinates":[76.92511999999998,10.76505],"type":"Point"}
}