{
  "type": "Feature",
  "properties": {
    "iso:country":"IN",
    "ks:ks_name":"Bariola",
    "ks:ks_pop":210,
    "ks:ks_type":"VILLAGE",
    "name:eng_x_preferred":[
        "Bariola"
    ],
    "wof:name":"Bariola",
    "wof:placetype":"locality",
    "wof:population":210
},
  "geometry": {"coordinates":[84.089778,19.035505],"type":"Point"}
}