{
  "type": "Feature",
  "properties": {
    "iso:country":"IN",
    "ks:ks_alt_nam":"FURSATGANJ",
    "ks:ks_name":"Fursatganj",
    "ks:ks_pop":64,
    "ks:ks_type":"HABITATION",
    "name:eng_x_preferred":[
        "Fursatganj"
    ],
    "wof:name":"Fursatganj",
    "wof:placetype":"locality",
    "wof:population":64
},
  "geometry": {"coordinates":[82.214185,26.209826],"type":"Point"}
}