{
  "type": "Feature",
  "properties": {
    "iso:country":"IN",
    "ks:ks_name":"Tikonemala",
    "ks:ks_pop":258,
    "ks:ks_type":"HABITATION",
    "name:eng_x_preferred":[
        "Tikonemala"
    ],
    "wof:name":"Tikonemala",
    "wof:placetype":"locality",
    "wof:population":258
},
  "geometry": {"coordinates":[74.191582,19.101918],"type":"Point"}
}