{
  "type": "Feature",
  "properties": {
    "iso:country":"IN",
    "ks:ks_alt_nam":"Santhosh nagar",
    "ks:ks_name":"Santhosh Nagar",
    "ks:ks_pop":189,
    "ks:ks_type":"HABITATION",
    "name:eng_x_preferred":[
        "Santhosh Nagar"
    ],
    "wof:name":"Santhosh Nagar",
    "wof:placetype":"locality",
    "wof:population":189
},
  "geometry": {"coordinates":[84.513599,18.779675],"type":"Point"}
}