{
  "type": "Feature",
  "properties": {
    "iso:country":"IN",
    "ks:ks_name":"Manihinaya School Para",
    "ks:ks_pop":1257,
    "ks:ks_type":"HABITATION",
    "name:eng_x_preferred":[
        "Manihinaya School Para"
    ],
    "wof:name":"Manihinaya School Para",
    "wof:placetype":"locality",
    "wof:population":1257
},
  "geometry": {"coordinates":[81.365246,19.538342],"type":"Point"}
}