{
  "type": "Feature",
  "properties": {
    "gn:admin1_code":"24.0",
    "gn:admin2_code":"102",
    "gn:asciiname":"Kalusar",
    "gn:country_code":"IN",
    "gn:dem":260,
    "gn:feature_class":"P",
    "gn:feature_code":"PPL",
    "gn:name":"K\u0101l\u016bsar",
    "gn:population":0,
    "gn:timezone":"Asia/Kolkata",
    "iso:country":"IN",
    "name:und_x_variant":[
        "K\u0101l\u016bsar",
        "K\u0101lusar"
    ],
    "wof:name":"Kalusar",
    "wof:placetype":"locality"
},
  "geometry": {"coordinates":[74.60065999999998,28.42413],"type":"Point"}
}