{
  "type": "Feature",
  "properties": {
    "iso:country":"IN",
    "ks:ks_name":"Chawrauti",
    "ks:ks_pop":66,
    "ks:ks_type":"HABITATION",
    "name:eng_x_preferred":[
        "Chawrauti"
    ],
    "wof:name":"Chawrauti",
    "wof:placetype":"locality",
    "wof:population":66
},
  "geometry": {"coordinates":[83.956828,26.619682],"type":"Point"}
}