{
  "type": "Feature",
  "properties": {
    "iso:country":"IN",
    "ks:ks_name":"Akyawar",
    "ks:ks_pop":146,
    "ks:ks_type":"HABITATION",
    "name:eng_x_preferred":[
        "Akyawar"
    ],
    "wof:name":"Akyawar",
    "wof:placetype":"locality",
    "wof:population":146
},
  "geometry": {"coordinates":[73.409181,24.767669],"type":"Point"}
}