{
  "type": "Feature",
  "properties": {
    "iso:country":"IN",
    "ks:ks_alt_nam":"Bhutupunji Dowka section",
    "ks:ks_name":"Bhutupunji Dowka Section",
    "ks:ks_pop":1381,
    "ks:ks_type":"HABITATION",
    "name:eng_x_preferred":[
        "Bhutupunji Dowka Section"
    ],
    "wof:name":"Bhutupunji Dowka Section",
    "wof:placetype":"locality",
    "wof:population":1381
},
  "geometry": {"coordinates":[92.38665399999999,24.326037],"type":"Point"}
}