{
  "type": "Feature",
  "properties": {
    "iso:country":"IN",
    "ks:ks_name":"Parakkapadavu",
    "ks:ks_pop":269,
    "ks:ks_type":"HABITATION",
    "name:eng_x_preferred":[
        "Parakkapadavu"
    ],
    "wof:name":"Parakkapadavu",
    "wof:placetype":"locality",
    "wof:population":269
},
  "geometry": {"coordinates":[76.392636,10.338986],"type":"Point"}
}