{
  "type": "Feature",
  "properties": {
    "iso:country":"IN",
    "ks:ks_name":"Chippne",
    "ks:ks_pop":24,
    "ks:ks_type":"HABITATION",
    "name:eng_x_preferred":[
        "Chippne"
    ],
    "wof:name":"Chippne",
    "wof:placetype":"locality",
    "wof:population":24
},
  "geometry": {"coordinates":[75.23339300000001,13.609127],"type":"Point"}
}