{
  "type": "Feature",
  "properties": {
    "gn:admin1_code":"36",
    "gn:admin2_code":"196.0",
    "gn:asciiname":"Hardahwa",
    "gn:country_code":"IN",
    "gn:dem":310,
    "gn:feature_class":"P",
    "gn:feature_code":"PPL",
    "gn:name":"Hardahwa",
    "gn:population":0,
    "gn:timezone":"Asia/Kolkata",
    "iso:country":"IN",
    "wof:name":"Hardahwa",
    "wof:placetype":"locality"
},
  "geometry": {"coordinates":[83.18056,24.73185],"type":"Point"}
}