{
  "type": "Feature",
  "properties": {
    "iso:country":"IN",
    "ks:ks_name":"Khakhara",
    "ks:ks_pop":239,
    "ks:ks_type":"HABITATION",
    "name:eng_x_preferred":[
        "Khakhara"
    ],
    "wof:name":"Khakhara",
    "wof:placetype":"locality",
    "wof:population":239
},
  "geometry": {"coordinates":[73.917328,25.815739],"type":"Point"}
}