{
  "type": "Feature",
  "properties": {
    "iso:country":"IN",
    "ks:ks_name":"6 PSD-C",
    "ks:ks_pop":562,
    "ks:ks_type":"VILLAGE",
    "ks:ks_uagg_main":0,
    "name:eng_x_preferred":[
        "6 PSD-C"
    ],
    "wof:name":"6 PSD-C",
    "wof:placetype":"neighbourhood",
    "wof:population":562
},
  "geometry": {"coordinates":[72.89021,28.848958],"type":"Point"}
}