{
  "type": "Feature",
  "properties": {
    "iso:country":"IN",
    "ks:ks_name":"Doroho",
    "ks:ks_pop":8,
    "ks:ks_type":"HABITATION",
    "name:eng_x_preferred":[
        "Doroho"
    ],
    "wof:name":"Doroho",
    "wof:placetype":"locality",
    "wof:population":8
},
  "geometry": {"coordinates":[92.86541699999999,25.36672],"type":"Point"}
}