{
  "type": "Feature",
  "properties": {
    "iso:country":"IN",
    "ks:ks_name":"Anandakhal",
    "ks:ks_pop":1077,
    "ks:ks_type":"VILLAGE",
    "name:eng_x_preferred":[
        "Anandakhal"
    ],
    "wof:name":"Anandakhal",
    "wof:placetype":"locality",
    "wof:population":1077
},
  "geometry": {"coordinates":[92.931173,24.550175],"type":"Point"}
}