{
  "type": "Feature",
  "properties": {
    "iso:country":"IN",
    "ks:ks_name":"Kishanniwas",
    "ks:ks_pop":232,
    "ks:ks_type":"VILLAGE",
    "ks:ks_uagg_main":0,
    "name:eng_x_preferred":[
        "Kishanniwas"
    ],
    "wof:name":"Kishanniwas",
    "wof:placetype":"neighbourhood",
    "wof:population":232
},
  "geometry": {"coordinates":[75.34963,25.1478],"type":"Point"}
}