{
  "type": "Feature",
  "properties": {
    "iso:country":"IN",
    "ks:ks_name":"Gadi",
    "ks:ks_pop":25,
    "ks:ks_type":"VILLAGE",
    "name:eng_x_preferred":[
        "Gadi"
    ],
    "wof:name":"Gadi",
    "wof:placetype":"locality",
    "wof:population":25
},
  "geometry": {"coordinates":[86.196763,24.258207],"type":"Point"}
}