{
  "type": "Feature",
  "properties": {
    "gn:admin1_code":"24.0",
    "gn:admin2_code":"125.0",
    "gn:asciiname":"Gamania Moti",
    "gn:country_code":"IN",
    "gn:dem":228,
    "gn:feature_class":"P",
    "gn:feature_code":"PPL",
    "gn:name":"Gam\u0101nia Moti",
    "gn:population":0,
    "gn:timezone":"Asia/Kolkata",
    "iso:country":"IN",
    "ks:ks_name":"Gamaniya Moti",
    "ks:ks_pop":824,
    "ks:ks_type":"VILLAGE",
    "name:eng_x_preferred":[
        "Gamaniya Moti"
    ],
    "name:eng_x_variant":[
        "Gamania Moti"
    ],
    "wof:name":"Gamaniya Moti",
    "wof:placetype":"locality",
    "wof:population":824
},
  "geometry": {"coordinates":[74.187433,23.268264],"type":"Point"}
}