{
  "type": "Feature",
  "properties": {
    "gn:admin1_code":"19",
    "gn:admin2_code":"564.0",
    "gn:asciiname":"Tilvalli",
    "gn:country_code":"IN",
    "gn:dem":558,
    "gn:feature_class":"P",
    "gn:feature_code":"PPL",
    "gn:name":"Tilvalli",
    "gn:population":0,
    "gn:timezone":"Asia/Kolkata",
    "iso:country":"IN",
    "wof:name":"Tilvalli",
    "wof:placetype":"locality"
},
  "geometry": {"coordinates":[75.23096,14.62676],"type":"Point"}
}