{
  "type": "Feature",
  "properties": {
    "iso:country":"IN",
    "ks:ks_name":"Chotya Bayadee",
    "ks:ks_pop":203,
    "ks:ks_type":"VILLAGE",
    "name:eng_x_preferred":[
        "Chotya Bayadee"
    ],
    "wof:name":"Chotya Bayadee",
    "wof:placetype":"locality",
    "wof:population":203
},
  "geometry": {"coordinates":[74.720169,22.576759],"type":"Point"}
}