{
  "type": "Feature",
  "properties": {
    "gn:admin1_code":"39",
    "gn:admin2_code":"61.0",
    "gn:asciiname":"Gawana Talla",
    "gn:country_code":"IN",
    "gn:dem":942,
    "gn:feature_class":"P",
    "gn:feature_code":"PPL",
    "gn:name":"Gaw\u0101na Talla",
    "gn:population":0,
    "gn:timezone":"Asia/Kolkata",
    "iso:country":"IN",
    "wof:name":"Gawana Talla",
    "wof:placetype":"locality"
},
  "geometry": {"coordinates":[78.83848,29.87229],"type":"Point"}
}