{
  "type": "Feature",
  "properties": {
    "iso:country":"IN",
    "ks:ks_name":"Nadusoorangudi",
    "ks:ks_pop":620,
    "ks:ks_type":"HABITATION",
    "name:eng_x_preferred":[
        "Nadusoorangudi"
    ],
    "wof:name":"Nadusoorangudi",
    "wof:placetype":"locality",
    "wof:population":620
},
  "geometry": {"coordinates":[77.870392,9.325024],"type":"Point"}
}