{
  "type": "Feature",
  "properties": {
    "gn:country":"IN",
    "gn:fcode":"PPL",
    "gn:pop":9902,
    "iso:country":"IN",
    "name:bpy_x_preferred":[
        "\u09a8\u09be\u0999\u09cd\u0997\u09be\u09ac\u09be\u09b2\u09cd\u09b2\u09bf"
    ],
    "name:bul_x_preferred":[
        "\u041d\u0430\u043d\u0433\u0430\u0432\u0430\u043b\u0438"
    ],
    "name:chi_x_preferred":[
        "\u5357\u683c\u963f\u74e6\u5229"
    ],
    "name:dut_x_preferred":[
        "Nangavalli"
    ],
    "name:eng_x_preferred":[
        "Nangavalli"
    ],
    "name:ita_x_preferred":[
        "Nangavalli"
    ],
    "name:may_x_preferred":[
        "Nangavalli"
    ],
    "name:nan_x_preferred":[
        "Nangavalli"
    ],
    "name:new_x_preferred":[
        "\u0928\u0928\u094d\u0917\u0935\u0932\u094d\u0932\u0940"
    ],
    "name:por_x_preferred":[
        "Nangavalli"
    ],
    "name:swe_x_preferred":[
        "Nangavalli"
    ],
    "name:tam_x_preferred":[
        "\u0ba8\u0b99\u0bcd\u0b95\u0bb5\u0bb3\u0bcd\u0bb3\u0bbf"
    ],
    "name:unk_x_variant":[
        "Nangavelli"
    ],
    "name:vie_x_preferred":[
        "Nangavalli"
    ],
    "qs:name":"Nagamballi",
    "qs:name_adm0":"India",
    "qs:name_adm1":"Tamil Nadu",
    "qs:photos_9r":0,
    "qs:photos_sr":0,
    "qs:placetype":"Town",
    "qs:pop_sr":"5",
    "wof:name":"Nagamballi",
    "wof:placetype":"locality",
    "wof:population":9902
},
  "geometry": {"coordinates":[77.89138,11.76108],"type":"Point"}
}