{
  "type": "Feature",
  "properties": {
    "gn:admin1_code":"31",
    "gn:admin2_code":"288.0",
    "gn:asciiname":"Serkawr",
    "gn:country_code":"IN",
    "gn:dem":928,
    "gn:feature_class":"P",
    "gn:feature_code":"PPL",
    "gn:name":"Serkawr",
    "gn:population":0,
    "gn:timezone":"Asia/Kolkata",
    "iso:country":"IN",
    "wof:name":"Serkawr",
    "wof:placetype":"locality"
},
  "geometry": {"coordinates":[92.98005000000001,22.36218],"type":"Point"}
}