{
  "type": "Feature",
  "properties": {
    "gn:admin1_code":"02",
    "gn:admin2_code":"545.0",
    "gn:asciiname":"Uppada",
    "gn:country_code":"IN",
    "gn:dem":7,
    "gn:feature_class":"P",
    "gn:feature_code":"PPL",
    "gn:name":"Upp\u0101da",
    "gn:population":0,
    "gn:timezone":"Asia/Kolkata",
    "iso:country":"IN",
    "name:tel_x_preferred":[
        "\u0c09\u0c2a\u0c4d\u0c2a\u0c3e\u0c21"
    ],
    "name:und_x_variant":[
        "Upp\u0101da"
    ],
    "wof:name":"Uppada",
    "wof:placetype":"locality"
},
  "geometry": {"coordinates":[82.33333,17.08333],"type":"Point"}
}