{
  "type": "Feature",
  "properties": {
    "gn:admin1_code":"36.0",
    "gn:admin2_code":"149",
    "gn:asciiname":"Urena",
    "gn:country_code":"IN",
    "gn:dem":158,
    "gn:feature_class":"P",
    "gn:feature_code":"PPL",
    "gn:name":"Urena",
    "gn:population":0,
    "gn:timezone":"Asia/Kolkata",
    "iso:country":"IN",
    "name:ceb_x_preferred":[
        "Urena"
    ],
    "name:ces_x_preferred":[
        "Urena"
    ],
    "name:nld_x_preferred":[
        "Urena"
    ],
    "name:por_x_preferred":[
        "Urena"
    ],
    "name:spa_x_preferred":[
        "Urena"
    ],
    "name:swe_x_preferred":[
        "Urena"
    ],
    "name:vie_x_preferred":[
        "Chi K\u00e9"
    ],
    "name:war_x_preferred":[
        "Urena"
    ],
    "name:zho_x_preferred":[
        "\u68b5\u5929\u82b1\u5c5e"
    ],
    "wof:name":"Urena",
    "wof:placetype":"locality"
},
  "geometry": {"coordinates":[79.45774,27.99795],"type":"Point"}
}