{
  "type": "Feature",
  "properties": {
    "iso:country":"IN",
    "ks:ks_name":"Karakalavalasa",
    "ks:ks_pop":260,
    "ks:ks_type":"HABITATION",
    "name:eng_x_preferred":[
        "Karakalavalasa"
    ],
    "wof:name":"Karakalavalasa",
    "wof:placetype":"locality",
    "wof:population":260
},
  "geometry": {"coordinates":[82.845187,18.181749],"type":"Point"}
}