{
  "type": "Feature",
  "properties": {
    "gn:admin1_code":"19.0",
    "gn:admin2_code":"570.0",
    "gn:asciiname":"Bilankodigi",
    "gn:country_code":"IN",
    "gn:dem":656,
    "gn:feature_class":"P",
    "gn:feature_code":"PPL",
    "gn:name":"Bilankodigi",
    "gn:population":0,
    "gn:timezone":"Asia/Kolkata",
    "iso:country":"IN",
    "wof:name":"Bilankodigi",
    "wof:placetype":"locality"
},
  "geometry": {"coordinates":[75.21666,13.51235],"type":"Point"}
}