{
  "type": "Feature",
  "properties": {
    "iso:country":"IN",
    "ks:ks_name":"Traibeda",
    "ks:ks_pop":418,
    "ks:ks_type":"HABITATION",
    "name:eng_x_preferred":[
        "Traibeda"
    ],
    "wof:name":"Traibeda",
    "wof:placetype":"locality",
    "wof:population":418
},
  "geometry": {"coordinates":[83.34366,19.78419],"type":"Point"}
}