{
  "type": "Feature",
  "properties": {
    "gn:admin1_code":"19.0",
    "gn:admin2_code":"565.0",
    "gn:asciiname":"Rameswarabandi",
    "gn:country_code":"IN",
    "gn:dem":492,
    "gn:feature_class":"P",
    "gn:feature_code":"PPL",
    "gn:name":"R\u0101meswarabandi",
    "gn:population":0,
    "gn:timezone":"Asia/Kolkata",
    "iso:country":"IN",
    "ks:ks_name":"Rameswara Bandi",
    "ks:ks_pop":1188,
    "ks:ks_type":"VILLAGE",
    "name:eng_x_preferred":[
        "Rameswara Bandi"
    ],
    "name:eng_x_variant":[
        "Rameswarabandi"
    ],
    "wof:name":"Rameswara Bandi",
    "wof:placetype":"locality",
    "wof:population":1188
},
  "geometry": {"coordinates":[76.17544700000001,15.192443],"type":"Point"}
}