{
  "type": "Feature",
  "properties": {
    "gn:admin1_code":"16.0",
    "gn:admin2_code":"522",
    "gn:asciiname":"Dhandharphal",
    "gn:country_code":"IN",
    "gn:dem":571,
    "gn:feature_class":"P",
    "gn:feature_code":"PPL",
    "gn:name":"Dh\u0101ndharphal",
    "gn:population":0,
    "gn:timezone":"Asia/Kolkata",
    "iso:country":"IN",
    "name:und_x_variant":[
        "Dhandarphal",
        "Dh\u0101ndharphal"
    ],
    "wof:name":"Dhandharphal",
    "wof:placetype":"locality"
},
  "geometry": {"coordinates":[74.11896999999998,19.53254],"type":"Point"}
}