{
  "type": "Feature",
  "properties": {
    "gn:admin1_code":"10.0",
    "gn:admin2_code":"72.0",
    "gn:asciiname":"Ramsaran Majra",
    "gn:country_code":"IN",
    "gn:dem":264,
    "gn:feature_class":"P",
    "gn:feature_code":"PPL",
    "gn:name":"R\u0101msaran Majra",
    "gn:population":0,
    "gn:timezone":"Asia/Kolkata",
    "iso:country":"IN",
    "wof:name":"Ramsaran Majra",
    "wof:placetype":"locality"
},
  "geometry": {"coordinates":[77.00202,30.07841],"type":"Point"}
}