{
  "type": "Feature",
  "properties": {
    "gn:admin1_code":"2.0",
    "gn:admin2_code":"554.0",
    "gn:asciiname":"Pichaguttapalle",
    "gn:country_code":"IN",
    "gn:dem":739,
    "gn:feature_class":"P",
    "gn:feature_code":"PPL",
    "gn:name":"Pichaguttapalle",
    "gn:population":0,
    "gn:timezone":"Asia/Kolkata",
    "iso:country":"IN",
    "wof:name":"Pichaguttapalle",
    "wof:placetype":"neighbourhood"
},
  "geometry": {"coordinates":[78.62551000000001,13.12755],"type":"Point"}
}