{
  "type": "Feature",
  "properties": {
    "iso:country":"IN",
    "ks:ks_name":"Chopadekarwadi",
    "ks:ks_pop":94,
    "ks:ks_type":"HABITATION",
    "name:eng_x_preferred":[
        "Chopadekarwadi"
    ],
    "wof:name":"Chopadekarwadi",
    "wof:placetype":"locality",
    "wof:population":94
},
  "geometry": {"coordinates":[73.498008,15.975878],"type":"Point"}
}