{
  "type": "Feature",
  "properties": {
    "gn:admin1_code":"16",
    "gn:admin2_code":"522.0",
    "gn:asciiname":"Vaghunde Budrukh",
    "gn:country_code":"IN",
    "gn:dem":696,
    "gn:feature_class":"P",
    "gn:feature_code":"PPL",
    "gn:name":"Vaghunde Budrukh",
    "gn:population":0,
    "gn:timezone":"Asia/Kolkata",
    "iso:country":"IN",
    "name:und_x_variant":[
        "Vaghunde",
        "Vanghunde Budrukh",
        "Vaghunde Budrukh"
    ],
    "wof:name":"Vaghunde Budrukh",
    "wof:placetype":"neighbourhood"
},
  "geometry": {"coordinates":[74.50801,18.93492],"type":"Point"}
}