{
  "type": "Feature",
  "properties": {
    "gn:admin1_code":"35.0",
    "gn:admin2_code":"454.0",
    "gn:asciiname":"Boria",
    "gn:country_code":"IN",
    "gn:dem":463,
    "gn:feature_class":"P",
    "gn:feature_code":"PPL",
    "gn:name":"Bori\u0101",
    "gn:population":0,
    "gn:timezone":"Asia/Kolkata",
    "iso:country":"IN",
    "name:ceb_x_preferred":[
        "Boria"
    ],
    "name:swe_x_preferred":[
        "Boria"
    ],
    "wof:name":"Boria",
    "wof:placetype":"locality"
},
  "geometry": {"coordinates":[80.21351,22.84974],"type":"Point"}
}