{
  "type": "Feature",
  "properties": {
    "gn:admin1_code":"19.0",
    "gn:admin2_code":"582.0",
    "gn:asciiname":"Angarekhanhalli",
    "gn:country_code":"IN",
    "gn:dem":902,
    "gn:feature_class":"P",
    "gn:feature_code":"PPL",
    "gn:name":"Angarekh\u0101nhalli",
    "gn:population":0,
    "gn:timezone":"Asia/Kolkata",
    "iso:country":"IN",
    "wof:name":"Angarekhanhalli",
    "wof:placetype":"locality"
},
  "geometry": {"coordinates":[77.82119,13.44694],"type":"Point"}
}