{
  "type": "Feature",
  "properties": {
    "gn:admin1_code":"11",
    "gn:admin2_code":"23.0",
    "gn:asciiname":"Ladhena",
    "gn:country_code":"IN",
    "gn:dem":1268,
    "gn:feature_class":"P",
    "gn:feature_code":"PPL",
    "gn:name":"Ladhena",
    "gn:population":0,
    "gn:timezone":"Asia/Kolkata",
    "iso:country":"IN",
    "wof:name":"Ladhena",
    "wof:placetype":"locality"
},
  "geometry": {"coordinates":[76.01437,32.44143],"type":"Point"}
}