{
  "type": "Feature",
  "properties": {
    "iso:country":"IN",
    "ks:ks_name":"Badlipara Wadlipara",
    "ks:ks_pop":300,
    "ks:ks_type":"HABITATION",
    "name:eng_x_preferred":[
        "Badlipara Wadlipara"
    ],
    "wof:name":"Badlipara Wadlipara",
    "wof:placetype":"locality",
    "wof:population":300
},
  "geometry": {"coordinates":[74.55480300000001,23.195736],"type":"Point"}
}