{
  "type": "Feature",
  "properties": {
    "iso:country":"IN",
    "ks:ks_name":"River End2",
    "ks:ks_pop":576,
    "ks:ks_type":"HABITATION",
    "name:eng_x_preferred":[
        "River End2"
    ],
    "wof:name":"River End2",
    "wof:placetype":"locality",
    "wof:population":576
},
  "geometry": {"coordinates":[76.256306,10.351793],"type":"Point"}
}