{
  "type": "Feature",
  "properties": {
    "iso:country":"IN",
    "ks:ks_name":"No 1 Assamia Gaon",
    "ks:ks_pop":3588,
    "ks:ks_type":"VILLAGE",
    "name:eng_x_preferred":[
        "No 1 Assamia Gaon"
    ],
    "wof:name":"No 1 Assamia Gaon",
    "wof:placetype":"locality",
    "wof:population":3588
},
  "geometry": {"coordinates":[95.584289,27.478128],"type":"Point"}
}