{
  "type": "Feature",
  "properties": {
    "iso:country":"IN",
    "ks:ks_name":"Thalkarwadi",
    "ks:ks_pop":98,
    "ks:ks_type":"HABITATION",
    "name:eng_x_preferred":[
        "Thalkarwadi"
    ],
    "wof:name":"Thalkarwadi",
    "wof:placetype":"locality",
    "wof:population":98
},
  "geometry": {"coordinates":[73.486125,16.165282],"type":"Point"}
}