{
  "type": "Feature",
  "properties": {
    "iso:country":"IN",
    "ks:ks_name":"Sirampur",
    "ks:ks_pop":215,
    "ks:ks_type":"VILLAGE",
    "name:eng_x_preferred":[
        "Sirampur"
    ],
    "wof:name":"Sirampur",
    "wof:placetype":"locality",
    "wof:population":215
},
  "geometry": {"coordinates":[87.231201,24.322296],"type":"Point"}
}