{
  "type": "Feature",
  "properties": {
    "iso:country":"IN",
    "ks:ks_name":"Kidramala",
    "ks:ks_pop":190,
    "ks:ks_type":"VILLAGE",
    "name:eng_x_preferred":[
        "Kidramala"
    ],
    "wof:name":"Kidramala",
    "wof:placetype":"locality",
    "wof:population":190
},
  "geometry": {"coordinates":[84.04707500000001,19.923498],"type":"Point"}
}