{
  "type": "Feature",
  "properties": {
    "gn:admin1_code":"36",
    "gn:admin2_code":"185.0",
    "gn:asciiname":"Dhuswa",
    "gn:country_code":"IN",
    "gn:dem":90,
    "gn:feature_class":"P",
    "gn:feature_code":"PPL",
    "gn:name":"Dhuswa",
    "gn:population":0,
    "gn:timezone":"Asia/Kolkata",
    "iso:country":"IN",
    "ks:ks_name":"Dhuswa",
    "ks:ks_type":"VILLAGE",
    "name:eng_x_preferred":[
        "Dhuswa"
    ],
    "wof:name":"Dhuswa",
    "wof:placetype":"locality"
},
  "geometry": {"coordinates":[82.392675,26.702308],"type":"Point"}
}