{
  "type": "Feature",
  "properties": {
    "iso:country":"IN",
    "ks:ks_name":"Ramapura",
    "ks:ks_pop":180,
    "ks:ks_type":"HABITATION",
    "name:eng_x_preferred":[
        "Ramapura"
    ],
    "wof:name":"Ramapura",
    "wof:placetype":"locality",
    "wof:population":180
},
  "geometry": {"coordinates":[77.083753,12.106478],"type":"Point"}
}