{
  "type": "Feature",
  "properties": {
    "iso:country":"IN",
    "ks:ks_name":"Dewawala",
    "ks:ks_pop":250,
    "ks:ks_type":"HABITATION",
    "name:eng_x_preferred":[
        "Dewawala"
    ],
    "wof:name":"Dewawala",
    "wof:placetype":"locality",
    "wof:population":250
},
  "geometry": {"coordinates":[71.84146200000001,27.831686],"type":"Point"}
}