{
  "type": "Feature",
  "properties": {
    "iso:country":"IN",
    "ks:ks_name":"Tola Burhnair",
    "ks:ks_pop":588,
    "ks:ks_type":"VILLAGE",
    "ks:ks_uagg_main":0,
    "name:eng_x_preferred":[
        "Tola Burhnair"
    ],
    "wof:name":"Tola Burhnair",
    "wof:placetype":"neighbourhood",
    "wof:population":588
},
  "geometry": {"coordinates":[86.40671500000001,24.751538],"type":"Point"}
}