{
  "type": "Feature",
  "properties": {
    "gn:admin1_code":"40.0",
    "gn:admin2_code":"539.0",
    "gn:asciiname":"Kannareddipalli",
    "gn:country_code":"IN",
    "gn:dem":504,
    "gn:feature_class":"P",
    "gn:feature_code":"PPL",
    "gn:name":"Kannareddipalli",
    "gn:population":0,
    "gn:timezone":"Asia/Kolkata",
    "iso:country":"IN",
    "wof:name":"Kannareddipalli",
    "wof:placetype":"locality"
},
  "geometry": {"coordinates":[78.88219000000002,17.74889],"type":"Point"}
}