{
  "type": "Feature",
  "properties": {
    "iso:country":"IN",
    "ks:ks_name":"Harekal Talmalappa Temple",
    "ks:ks_pop":150,
    "ks:ks_type":"HABITATION",
    "name:eng_x_preferred":[
        "Harekal Talmalappa Temple"
    ],
    "wof:name":"Harekal Talmalappa Temple",
    "wof:placetype":"locality",
    "wof:population":150
},
  "geometry": {"coordinates":[76.267814,13.126046],"type":"Point"}
}