{
  "type": "Feature",
  "properties": {
    "gn:admin1_code":"9.0",
    "gn:admin2_code":"476.0",
    "gn:asciiname":"Atkot",
    "gn:country_code":"IN",
    "gn:dem":176,
    "gn:feature_class":"P",
    "gn:feature_code":"PPL",
    "gn:name":"Atkot",
    "gn:population":0,
    "gn:timezone":"Asia/Kolkata",
    "iso:country":"IN",
    "name:guj_x_preferred":[
        "\u0a86\u0a9f\u0a95\u0acb\u0a9f"
    ],
    "name:hin_x_preferred":[
        "\u0906\u091f\u0915\u094b\u091f"
    ],
    "wof:name":"Atkot",
    "wof:placetype":"locality"
},
  "geometry": {"coordinates":[71.15019000000002,22.00897],"type":"Point"}
}