{
  "type": "Feature",
  "properties": {
    "gn:admin1_code":"9.0",
    "gn:admin2_code":"476.0",
    "gn:asciiname":"Atkot",
    "gn:country_code":"IN",
    "gn:dem":176,
    "gn:feature_class":"P",
    "gn:feature_code":"PPL",
    "gn:name":"Atkot",
    "gn:population":0,
    "gn:timezone":"Asia/Kolkata",
    "iso:country":"IN",
    "wof:name":"Atkot",
    "wof:placetype":"locality"
},
  "geometry": {"coordinates":[71.15019000000002,22.00897],"type":"Point"}
}