{
  "type": "Feature",
  "properties": {
    "iso:country":"IN",
    "ks:ks_name":"Mohan Purwa",
    "ks:ks_pop":331,
    "ks:ks_type":"HABITATION",
    "ks:ks_uagg_main":0,
    "name:eng_x_preferred":[
        "Mohan Purwa"
    ],
    "wof:name":"Mohan Purwa",
    "wof:placetype":"neighbourhood",
    "wof:population":331
},
  "geometry": {"coordinates":[81.82216099999999,27.663546],"type":"Point"}
}