{
  "type": "Feature",
  "properties": {
    "gn:admin1_code":"11.0",
    "gn:admin2_code":"33.0",
    "gn:asciiname":"Sanain",
    "gn:country_code":"IN",
    "gn:dem":2245,
    "gn:feature_class":"P",
    "gn:feature_code":"PPL",
    "gn:name":"Sanain",
    "gn:population":0,
    "gn:timezone":"Asia/Kolkata",
    "iso:country":"IN",
    "name:fas_x_preferred":[
        "\u0633\u0627\u0646\u0627\u06cc\u0646"
    ],
    "wof:name":"Sanain",
    "wof:placetype":"locality"
},
  "geometry": {"coordinates":[77.3257,31.12968],"type":"Point"}
}