{
  "type": "Feature",
  "properties": {
    "iso:country":"IN",
    "ks:ks_name":"Khala Damar",
    "ks:ks_pop":471,
    "ks:ks_type":"HABITATION",
    "name:eng_x_preferred":[
        "Khala Damar"
    ],
    "wof:name":"Khala Damar",
    "wof:placetype":"locality",
    "wof:population":471
},
  "geometry": {"coordinates":[83.517206,24.132521],"type":"Point"}
}