{
  "type": "Feature",
  "properties": {
    "iso:country":"IN",
    "ks:ks_name":"Ambalakkalli",
    "ks:ks_pop":428,
    "ks:ks_type":"HABITATION",
    "name:eng_x_preferred":[
        "Ambalakkalli"
    ],
    "wof:name":"Ambalakkalli",
    "wof:placetype":"locality",
    "wof:population":428
},
  "geometry": {"coordinates":[76.25472000000001,11.123358],"type":"Point"}
}