{
  "type": "Feature",
  "properties": {
    "iso:country":"IN",
    "ks:ks_name":"Narbada",
    "ks:ks_pop":282,
    "ks:ks_type":"VILLAGE",
    "name:eng_x_preferred":[
        "Narbada"
    ],
    "wof:name":"Narbada",
    "wof:placetype":"locality",
    "wof:population":282
},
  "geometry": {"coordinates":[82.69153300000001,22.48953],"type":"Point"}
}