{
  "type": "Feature",
  "properties": {
    "gn:admin1_code":"38.0",
    "gn:admin2_code":"353.0",
    "gn:asciiname":"Ranbahiar",
    "gn:country_code":"IN",
    "gn:dem":115,
    "gn:feature_class":"P",
    "gn:feature_code":"PPL",
    "gn:name":"Ranbahi\u0101r",
    "gn:population":0,
    "gn:timezone":"Asia/Kolkata",
    "iso:country":"IN",
    "name:und_x_variant":[
        "Ranbahi\u0101r",
        "Keskeso"
    ],
    "wof:name":"Ranbahiar",
    "wof:placetype":"locality"
},
  "geometry": {"coordinates":[87.59189000000001,24.68797],"type":"Point"}
}