{
  "type": "Feature",
  "properties": {
    "gn:admin1_code":"38.0",
    "gn:admin2_code":"353.0",
    "gn:asciiname":"Ranbahiar",
    "gn:country_code":"IN",
    "gn:dem":115,
    "gn:feature_class":"P",
    "gn:feature_code":"PPL",
    "gn:name":"Ranbahi\u0101r",
    "gn:population":0,
    "gn:timezone":"Asia/Kolkata",
    "iso:country":"IN",
    "ks:ks_alt_nam":"Ranbahi\u0101r",
    "ks:ks_name":"Ranbahiar",
    "ks:ks_pop":363,
    "ks:ks_type":"VILLAGE",
    "name:eng_x_preferred":[
        "Ranbahiar"
    ],
    "name:eng_x_variant":[
        "Ranbahi\u0101r"
    ],
    "name:und_x_variant":[
        "Ranbahi\u0101r",
        "Keskeso"
    ],
    "wof:name":"Ranbahiar",
    "wof:placetype":"locality",
    "wof:population":363
},
  "geometry": {"coordinates":[87.59189499999999,24.687968],"type":"Point"}
}