{
  "type": "Feature",
  "properties": {
    "gn:admin1_code":"37.0",
    "gn:admin2_code":"409.0",
    "gn:asciiname":"Bodal",
    "gn:country_code":"IN",
    "gn:dem":322,
    "gn:feature_class":"P",
    "gn:feature_code":"PPL",
    "gn:name":"Bodal",
    "gn:population":0,
    "gn:timezone":"Asia/Kolkata",
    "iso:country":"IN",
    "ks:ks_name":"Bodal",
    "ks:ks_pop":1085,
    "ks:ks_type":"VILLAGE",
    "name:eng_x_preferred":[
        "Bodal"
    ],
    "wof:name":"Bodal",
    "wof:placetype":"locality",
    "wof:population":1085
},
  "geometry": {"coordinates":[81.39452900000001,20.89101],"type":"Point"}
}