{
  "type": "Feature",
  "properties": {
    "iso:country":"IN",
    "ks:ks_name":"Bela",
    "ks:ks_pop":1809,
    "ks:ks_type":"VILLAGE",
    "name:eng_x_preferred":[
        "Bela"
    ],
    "wof:name":"Bela",
    "wof:placetype":"locality",
    "wof:population":1809
},
  "geometry": {"coordinates":[85.03353,25.078509],"type":"Point"}
}