{
  "type": "Feature",
  "properties": {
    "iso:country":"IN",
    "qs:name":"Gomat",
    "qs:name_adm0":"India",
    "qs:name_adm1":"Rajasthan",
    "qs:photos":57,
    "qs:photos_1k":12,
    "qs:photos_9k":1,
    "qs:photos_9r":2,
    "qs:photos_all":57,
    "qs:photos_sr":2,
    "qs:placetype":"Town",
    "qs:pop_sr":"0",
    "wof:name":"Gomat",
    "wof:placetype":"locality"
},
  "geometry": {"coordinates":[71.883201,26.934313],"type":"Point"}
}