{
  "type": "Feature",
  "properties": {
    "gn:admin1_code":"13.0",
    "gn:admin2_code":"592.0",
    "gn:asciiname":"Pariyapuram",
    "gn:country_code":"IN",
    "gn:dem":18,
    "gn:feature_class":"P",
    "gn:feature_code":"PPL",
    "gn:name":"Pariy\u0101puram",
    "gn:population":0,
    "gn:timezone":"Asia/Kolkata",
    "iso:country":"IN",
    "name:ceb_x_preferred":[
        "Pariy\u0101puram"
    ],
    "name:swe_x_preferred":[
        "Pariy\u0101puram"
    ],
    "wof:name":"Pariyapuram",
    "wof:placetype":"neighbourhood"
},
  "geometry": {"coordinates":[75.90803,10.89114],"type":"Point"}
}