{
  "type": "Feature",
  "properties": {
    "gn:admin1_code":"36.0",
    "gn:admin2_code":"182.0",
    "gn:asciiname":"Chak Arazi Gajupur",
    "gn:country_code":"IN",
    "gn:dem":97,
    "gn:feature_class":"P",
    "gn:feature_code":"PPL",
    "gn:name":"Chak Ar\u0101zi G\u0101jupur",
    "gn:population":0,
    "gn:timezone":"Asia/Kolkata",
    "iso:country":"IN",
    "wof:name":"Chak Arazi Gajupur",
    "wof:placetype":"neighbourhood"
},
  "geometry": {"coordinates":[82.43368,27.1728],"type":"Point"}
}