{
  "type": "Feature",
  "properties": {
    "iso:country":"IN",
    "ks:ks_name":"Kalvapara",
    "ks:ks_pop":280,
    "ks:ks_type":"VILLAGE",
    "name:eng_x_preferred":[
        "Kalvapara"
    ],
    "wof:name":"Kalvapara",
    "wof:placetype":"locality",
    "wof:population":280
},
  "geometry": {"coordinates":[87.829671,24.920704],"type":"Point"}
}