{
  "type": "Feature",
  "properties": {
    "iso:country":"IN",
    "ks:ks_name":"Rohar",
    "ks:ks_pop":698,
    "ks:ks_type":"HABITATION",
    "name:eng_x_preferred":[
        "Rohar"
    ],
    "wof:name":"Rohar",
    "wof:placetype":"locality",
    "wof:population":698
},
  "geometry": {"coordinates":[77.212425,26.639078],"type":"Point"}
}