{
  "type": "Feature",
  "properties": {
    "iso:country":"IN",
    "ks:ks_name":"Kamaicha",
    "ks:ks_pop":186,
    "ks:ks_type":"HABITATION",
    "name:eng_x_preferred":[
        "Kamaicha"
    ],
    "wof:name":"Kamaicha",
    "wof:placetype":"locality",
    "wof:population":186
},
  "geometry": {"coordinates":[80.693557,27.390098],"type":"Point"}
}