{
  "type": "Feature",
  "properties": {
    "iso:country":"IN",
    "ks:ks_name":"Jhilki Bosti",
    "ks:ks_pop":154,
    "ks:ks_type":"HABITATION",
    "name:eng_x_preferred":[
        "Jhilki Bosti"
    ],
    "wof:name":"Jhilki Bosti",
    "wof:placetype":"locality",
    "wof:population":154
},
  "geometry": {"coordinates":[93.603182,26.01113],"type":"Point"}
}