{
  "type": "Feature",
  "properties": {
    "iso:country":"IN",
    "ks:ks_name":"Nagla Kothi",
    "ks:ks_pop":416,
    "ks:ks_type":"HABITATION",
    "name:eng_x_preferred":[
        "Nagla Kothi"
    ],
    "wof:name":"Nagla Kothi",
    "wof:placetype":"locality",
    "wof:population":416
},
  "geometry": {"coordinates":[78.678781,27.041619],"type":"Point"}
}