{
  "type": "Feature",
  "properties": {
    "iso:country":"IN",
    "ks:ks_alt_nam":"Bh\u0101nd\u0101rib\u0101ri",
    "ks:ks_name":"Bhandaribari",
    "ks:ks_pop":75,
    "ks:ks_type":"VILLAGE",
    "name:eng_x_preferred":[
        "Bhandaribari"
    ],
    "name:eng_x_variant":[
        "Bh\u0101nd\u0101rib\u0101ri"
    ],
    "wof:name":"Bhandaribari",
    "wof:placetype":"locality",
    "wof:population":75
},
  "geometry": {"coordinates":[84.84115300000001,20.120218],"type":"Point"}
}