{
  "type": "Feature",
  "properties": {
    "iso:country":"IN",
    "ks:ks_name":"Badageeranahatti",
    "ks:ks_pop":74,
    "ks:ks_type":"HABITATION",
    "name:eng_x_preferred":[
        "Badageeranahatti"
    ],
    "wof:name":"Badageeranahatti",
    "wof:placetype":"locality",
    "wof:population":74
},
  "geometry": {"coordinates":[76.881078,13.126434],"type":"Point"}
}