{
  "type": "Feature",
  "properties": {
    "iso:country":"IN",
    "ks:ks_name":"Nagla Kumara",
    "ks:ks_pop":380,
    "ks:ks_type":"HABITATION",
    "name:eng_x_preferred":[
        "Nagla Kumara"
    ],
    "wof:name":"Nagla Kumara",
    "wof:placetype":"locality",
    "wof:population":380
},
  "geometry": {"coordinates":[77.981205,27.064576],"type":"Point"}
}