{
  "type": "Feature",
  "properties": {
    "iso:country":"IN",
    "ks:ks_name":"Chootoo",
    "ks:ks_pop":775,
    "ks:ks_type":"HABITATION",
    "name:eng_x_preferred":[
        "Chootoo"
    ],
    "wof:name":"Chootoo",
    "wof:placetype":"locality",
    "wof:population":775
},
  "geometry": {"coordinates":[71.654494,25.389339],"type":"Point"}
}