{
  "type": "Feature",
  "properties": {
    "iso:country":"IN",
    "ks:ks_name":"Bouddhwadi",
    "ks:ks_pop":60,
    "ks:ks_type":"HABITATION",
    "ks:ks_uagg_main":0,
    "name:eng_x_preferred":[
        "Bouddhwadi"
    ],
    "wof:name":"Bouddhwadi",
    "wof:placetype":"neighbourhood",
    "wof:population":60
},
  "geometry": {"coordinates":[73.611639,16.234139],"type":"Point"}
}