{
  "type": "Feature",
  "properties": {
    "iso:country":"IN",
    "ks:ks_name":"Puran Bairagi Para",
    "ks:ks_pop":164,
    "ks:ks_type":"HABITATION",
    "ks:ks_uagg_main":0,
    "name:eng_x_preferred":[
        "Puran Bairagi Para"
    ],
    "wof:name":"Puran Bairagi Para",
    "wof:placetype":"neighbourhood",
    "wof:population":164
},
  "geometry": {"coordinates":[91.480199,23.933031],"type":"Point"}
}