{
  "type": "Feature",
  "properties": {
    "iso:country":"IN",
    "ks:ks_name":"Mahmudpur T. Baruin",
    "ks:ks_pop":0,
    "ks:ks_type":"VILLAGE",
    "name:eng_x_preferred":[
        "Mahmudpur T. Baruin"
    ],
    "wof:name":"Mahmudpur T. Baruin",
    "wof:placetype":"locality",
    "wof:population":0
},
  "geometry": {"coordinates":[83.52906400000001,25.377907],"type":"Point"}
}