{
  "type": "Feature",
  "properties": {
    "gn:admin1_code":"12",
    "gn:admin2_code":"14.0",
    "gn:asciiname":"Brent",
    "gn:country_code":"IN",
    "gn:dem":1639,
    "gn:feature_class":"P",
    "gn:feature_code":"PPL",
    "gn:name":"Brent",
    "gn:population":0,
    "gn:timezone":"Asia/Kolkata",
    "iso:country":"IN",
    "name:ara_x_preferred":[
        "\u0628\u0631\u064a\u0646\u062a"
    ],
    "name:ell_x_preferred":[
        "\u039c\u03c0\u03c1\u03b5\u03bd\u03c4"
    ],
    "name:ind_x_preferred":[
        "Brent"
    ],
    "wof:name":"Brent",
    "wof:placetype":"locality"
},
  "geometry": {"coordinates":[75.18001,33.6821],"type":"Point"}
}