{
  "type": "Feature",
  "properties": {
    "iso:country":"IN",
    "ks:ks_name":"Tadhivedi",
    "ks:ks_pop":2177,
    "ks:ks_type":"VILLAGE",
    "name:eng_x_preferred":[
        "Tadhivedi"
    ],
    "wof:name":"Tadhivedi",
    "wof:placetype":"locality",
    "wof:population":2177
},
  "geometry": {"coordinates":[73.169417,24.3345],"type":"Point"}
}