{
  "type": "Feature",
  "properties": {
    "iso:country":"IN",
    "ks:ks_name":"Palbasti",
    "ks:ks_pop":309,
    "ks:ks_type":"HABITATION",
    "name:eng_x_preferred":[
        "Palbasti"
    ],
    "wof:name":"Palbasti",
    "wof:placetype":"locality",
    "wof:population":309
},
  "geometry": {"coordinates":[82.785005,25.363921],"type":"Point"}
}