{
  "type": "Feature",
  "properties": {
    "iso:country":"IN",
    "ks:ks_name":"Makanatte",
    "ks:ks_pop":14,
    "ks:ks_type":"HABITATION",
    "name:eng_x_preferred":[
        "Makanatte"
    ],
    "wof:name":"Makanatte",
    "wof:placetype":"locality",
    "wof:population":14
},
  "geometry": {"coordinates":[75.12512099999999,14.036549],"type":"Point"}
}