{
  "type": "Feature",
  "properties": {
    "iso:country":"IN",
    "ks:ks_alt_nam":"Peppeganj Railroad Station",
    "ks:ks_name":"Peppeganj",
    "ks:ks_type":"VILLAGE",
    "ks:ks_uagg_main":0,
    "name:eng_x_preferred":[
        "Peppeganj"
    ],
    "name:eng_x_variant":[
        "Peppeganj Railroad Station"
    ],
    "wof:name":"Peppeganj",
    "wof:placetype":"neighbourhood"
},
  "geometry": {"coordinates":[83.295079,26.930855],"type":"Point"}
}