{
  "type": "Feature",
  "properties": {
    "iso:country":"IN",
    "ks:ks_name":"Paraji",
    "ks:ks_pop":175,
    "ks:ks_type":"VILLAGE",
    "name:eng_x_preferred":[
        "Paraji"
    ],
    "wof:name":"Paraji",
    "wof:placetype":"locality",
    "wof:population":175
},
  "geometry": {"coordinates":[84.17868300000001,19.057298],"type":"Point"}
}