{
  "type": "Feature",
  "properties": {
    "iso:country":"IN",
    "ks:ks_name":"Nalmuri",
    "ks:ks_pop":2298,
    "ks:ks_type":"VILLAGE",
    "ks:ks_uagg_main":0,
    "name:eng_x_preferred":[
        "Nalmuri"
    ],
    "wof:name":"Nalmuri",
    "wof:placetype":"neighbourhood",
    "wof:population":2298
},
  "geometry": {"coordinates":[88.59735499999999,22.493501],"type":"Point"}
}