{
  "type": "Feature",
  "properties": {
    "iso:country":"IN",
    "ks:ks_name":"Balijan",
    "ks:ks_pop":932,
    "ks:ks_type":"VILLAGE",
    "ks:ks_uagg_main":0,
    "name:eng_x_preferred":[
        "Balijan"
    ],
    "wof:name":"Balijan",
    "wof:placetype":"locality",
    "wof:population":932
},
  "geometry": {"coordinates":[93.55935100000001,26.848024],"type":"Point"}
}