{
  "type": "Feature",
  "properties": {
    "iso:country":"IN",
    "ks:ks_name":"Janiyon Ki Beri",
    "ks:ks_pop":990,
    "ks:ks_type":"HABITATION",
    "name:eng_x_preferred":[
        "Janiyon Ki Beri"
    ],
    "wof:name":"Janiyon Ki Beri",
    "wof:placetype":"locality",
    "wof:population":990
},
  "geometry": {"coordinates":[71.265083,25.160658],"type":"Point"}
}