{
  "type": "Feature",
  "properties": {
    "iso:country":"IN",
    "ks:ks_name":"Ragumanpettai",
    "ks:ks_pop":439,
    "ks:ks_type":"HABITATION",
    "ks:ks_uagg_main":0,
    "name:eng_x_preferred":[
        "Ragumanpettai"
    ],
    "wof:name":"Ragumanpettai",
    "wof:placetype":"neighbourhood",
    "wof:population":439
},
  "geometry": {"coordinates":[79.144448,12.750989],"type":"Point"}
}