{
  "type": "Feature",
  "properties": {
    "iso:country":"IN",
    "ks:ks_name":"Madraha",
    "ks:ks_type":"VILLAGE",
    "name:eng_x_preferred":[
        "Madraha"
    ],
    "wof:name":"Madraha",
    "wof:placetype":"locality"
},
  "geometry": {"coordinates":[83.221345,26.83742],"type":"Point"}
}