{
  "type": "Feature",
  "properties": {
    "iso:country":"IN",
    "ks:ks_name":"Mudoor Junction",
    "ks:ks_pop":120,
    "ks:ks_type":"HABITATION",
    "name:eng_x_preferred":[
        "Mudoor Junction"
    ],
    "wof:name":"Mudoor Junction",
    "wof:placetype":"locality",
    "wof:population":120
},
  "geometry": {"coordinates":[74.87042099999999,13.807215],"type":"Point"}
}