{
  "type": "Feature",
  "properties": {
    "gn:admin1_code":"34.0",
    "gn:admin2_code":"203.0",
    "gn:asciiname":"Hamira",
    "gn:country_code":"IN",
    "gn:dem":90,
    "gn:feature_class":"P",
    "gn:feature_code":"PPL",
    "gn:name":"Hamira",
    "gn:population":0,
    "gn:timezone":"Asia/Kolkata",
    "iso:country":"IN",
    "name:pan_x_preferred":[
        "\u0a39\u0a2e\u0a40\u0a30\u0a3e"
    ],
    "wof:name":"Hamira",
    "wof:placetype":"locality"
},
  "geometry": {"coordinates":[84.29566,27.02455],"type":"Point"}
}