{
  "type": "Feature",
  "properties": {
    "iso:country":"IN",
    "ks:ks_alt_nam":"lala pur",
    "ks:ks_name":"Lala Pur",
    "ks:ks_pop":258,
    "ks:ks_type":"HABITATION",
    "name:eng_x_preferred":[
        "Lala Pur"
    ],
    "wof:name":"Lala Pur",
    "wof:placetype":"locality",
    "wof:population":258
},
  "geometry": {"coordinates":[82.21465600000001,25.3998],"type":"Point"}
}