{
  "type": "Feature",
  "properties": {
    "gn:admin1_code":"9.0",
    "gn:admin2_code":"490",
    "gn:asciiname":"Gandeva",
    "gn:country_code":"IN",
    "gn:dem":27,
    "gn:feature_class":"P",
    "gn:feature_code":"PPL",
    "gn:name":"Gandeva",
    "gn:population":0,
    "gn:timezone":"Asia/Kolkata",
    "iso:country":"IN",
    "wof:name":"Gandeva",
    "wof:placetype":"locality"
},
  "geometry": {"coordinates":[73.07831999999998,20.86376],"type":"Point"}
}