{
  "type": "Feature",
  "properties": {
    "iso:country":"IN",
    "ks:ks_alt_nam":"Nadumuslim street",
    "ks:ks_name":"Nadumuslim Street",
    "ks:ks_pop":222,
    "ks:ks_type":"HABITATION",
    "ks:ks_uagg_main":0,
    "name:eng_x_preferred":[
        "Nadumuslim Street"
    ],
    "wof:name":"Nadumuslim Street",
    "wof:placetype":"neighbourhood",
    "wof:population":222
},
  "geometry": {"coordinates":[78.56838399999999,12.587404],"type":"Point"}
}