{
  "type": "Feature",
  "properties": {
    "gn:admin1_code":"13.0",
    "gn:admin2_code":"590.0",
    "gn:asciiname":"Pannipari",
    "gn:country_code":"IN",
    "gn:dem":885,
    "gn:feature_class":"P",
    "gn:feature_code":"PPL",
    "gn:name":"Pannipari",
    "gn:population":0,
    "gn:timezone":"Asia/Kolkata",
    "iso:country":"IN",
    "wof:name":"Pannipari",
    "wof:placetype":"neighbourhood"
},
  "geometry": {"coordinates":[76.26152999999999,11.65843],"type":"Point"}
}