{
  "type": "Feature",
  "properties": {
    "iso:country":"IN",
    "ks:ks_name":"Purba Bibipur",
    "ks:ks_pop":361,
    "ks:ks_type":"HABITATION",
    "name:eng_x_preferred":[
        "Purba Bibipur"
    ],
    "wof:name":"Purba Bibipur",
    "wof:placetype":"locality",
    "wof:population":361
},
  "geometry": {"coordinates":[88.832466,22.692941],"type":"Point"}
}