{
  "type": "Feature",
  "properties": {
    "iso:country":"IN",
    "ks:ks_name":"Police Line Para",
    "ks:ks_pop":849,
    "ks:ks_type":"HABITATION",
    "ks:ks_uagg_main":0,
    "name:eng_x_preferred":[
        "Police Line Para"
    ],
    "wof:name":"Police Line Para",
    "wof:placetype":"neighbourhood",
    "wof:population":849
},
  "geometry": {"coordinates":[91.463323,23.551563],"type":"Point"}
}