{
  "type": "Feature",
  "properties": {
    "iso:country":"IN",
    "ks:ks_name":"3 RK",
    "ks:ks_pop":231,
    "ks:ks_type":"VILLAGE",
    "name:eng_x_preferred":[
        "3 RK"
    ],
    "wof:name":"3 RK",
    "wof:placetype":"locality",
    "wof:population":231
},
  "geometry": {"coordinates":[74.54199800000001,29.55682],"type":"Point"}
}