{
  "type": "Feature",
  "properties": {
    "iso:country":"IN",
    "ks:ks_name":"Patil Basti",
    "ks:ks_pop":526,
    "ks:ks_type":"HABITATION",
    "name:eng_x_preferred":[
        "Patil Basti"
    ],
    "wof:name":"Patil Basti",
    "wof:placetype":"locality",
    "wof:population":526
},
  "geometry": {"coordinates":[82.291466,25.767775],"type":"Point"}
}