{
  "type": "Feature",
  "properties": {
    "iso:country":"IN",
    "ks:ks_name":"Kadaisypodu",
    "ks:ks_pop":187,
    "ks:ks_type":"HABITATION",
    "name:eng_x_preferred":[
        "Kadaisypodu"
    ],
    "wof:name":"Kadaisypodu",
    "wof:placetype":"locality",
    "wof:population":187
},
  "geometry": {"coordinates":[77.902191,12.361057],"type":"Point"}
}