{
  "type": "Feature",
  "properties": {
    "gn:country":"IN",
    "gn:fcode":"PPL",
    "gn:pop":8494,
    "iso:country":"IN",
    "name:asm_x_preferred":[
        "\u0986\u09ae\u0997\u09c1\u09f0\u09bf"
    ],
    "name:ben_x_preferred":[
        "\u0986\u09ae\u0997\u09c1\u09a1\u09bc\u09bf"
    ],
    "name:bpy_x_preferred":[
        "\u0986\u09ae\u0997\u09c1\u09a1\u09bc\u09bf"
    ],
    "name:bul_x_preferred":[
        "\u0410\u043c\u0433\u0443\u0440\u0438"
    ],
    "name:ceb_x_preferred":[
        "Amguri"
    ],
    "name:eng_x_preferred":[
        "Amguri"
    ],
    "name:fas_x_preferred":[
        "\u0627\u0645\u06af\u0648\u0631\u06cc"
    ],
    "name:fra_x_preferred":[
        "Amguri"
    ],
    "name:ita_x_preferred":[
        "Amguri"
    ],
    "name:min_x_preferred":[
        "Amguri"
    ],
    "name:msa_x_preferred":[
        "Amguri"
    ],
    "name:nan_x_preferred":[
        "Amguri"
    ],
    "name:new_x_preferred":[
        "\u0905\u0917\u0941\u0930\u0940"
    ],
    "name:nld_x_preferred":[
        "Amguri"
    ],
    "name:por_x_preferred":[
        "Amguri"
    ],
    "name:spa_x_preferred":[
        "Amguri"
    ],
    "name:swe_x_preferred":[
        "Amguri"
    ],
    "name:vie_x_preferred":[
        "Amguri"
    ],
    "name:zho_x_preferred":[
        "\u963f\u59c6\u53e4\u91cc"
    ],
    "qs:name":"Amguri",
    "qs:name_adm0":"India",
    "qs:name_adm1":"Assam",
    "qs:photos_9r":0,
    "qs:photos_sr":0,
    "qs:placetype":"Town",
    "qs:pop_sr":"5",
    "wd:wordcount":463,
    "wof:name":"Amguri",
    "wof:placetype":"locality",
    "wof:population":8494
},
  "geometry": {"coordinates":[94.52614,26.81482],"type":"Point"}
}