{
  "type": "Feature",
  "properties": {
    "gn:admin1_code":"36.0",
    "gn:admin2_code":"182.0",
    "gn:asciiname":"Akbarpur",
    "gn:country_code":"IN",
    "gn:dem":115,
    "gn:feature_class":"P",
    "gn:feature_code":"PPL",
    "gn:name":"Akbarpur",
    "gn:population":0,
    "gn:timezone":"Asia/Kolkata",
    "iso:country":"IN",
    "name:bih_x_preferred":[
        "\u0905\u0915\u092c\u0930\u092a\u0941\u0930"
    ],
    "name:ceb_x_preferred":[
        "Akbarpur"
    ],
    "name:deu_x_preferred":[
        "Akbarpur"
    ],
    "name:ita_x_preferred":[
        "Akbarpur"
    ],
    "name:msa_x_preferred":[
        "Akbarpur"
    ],
    "name:new_x_preferred":[
        "\u0905\u0916\u092c\u0930\u092a\u0941\u0930"
    ],
    "name:nld_x_preferred":[
        "Akbarpur"
    ],
    "name:pol_x_preferred":[
        "Akbarpur"
    ],
    "name:rus_x_preferred":[
        "\u0410\u043a\u0431\u0430\u0440\u043f\u0443\u0440"
    ],
    "name:swe_x_preferred":[
        "Akbarpur"
    ],
    "name:vie_x_preferred":[
        "Akbarpur"
    ],
    "wof:name":"Akbarpur",
    "wof:placetype":"neighbourhood"
},
  "geometry": {"coordinates":[82.09456,27.57155],"type":"Point"}
}