{
  "type": "Feature",
  "properties": {
    "iso:country":"IN",
    "ks:ks_name":"Kesharipura",
    "ks:ks_pop":326,
    "ks:ks_type":"VILLAGE",
    "name:eng_x_preferred":[
        "Kesharipura"
    ],
    "wof:name":"Kesharipura",
    "wof:placetype":"locality",
    "wof:population":326
},
  "geometry": {"coordinates":[79.987899,25.092355],"type":"Point"}
}