{
  "type": "Feature",
  "properties": {
    "gn:admin1_code":"24.0",
    "gn:admin2_code":"110",
    "gn:asciiname":"Sabrampura",
    "gn:country_code":"IN",
    "gn:dem":418,
    "gn:feature_class":"P",
    "gn:feature_code":"PPL",
    "gn:name":"Sabr\u0101mpura",
    "gn:population":0,
    "gn:timezone":"Asia/Kolkata",
    "iso:country":"IN",
    "ks:ks_name":"Sabrampura",
    "ks:ks_pop":1104,
    "ks:ks_type":"HABITATION",
    "name:eng_x_preferred":[
        "Sabrampura"
    ],
    "wof:name":"Sabrampura",
    "wof:placetype":"locality",
    "wof:population":1104
},
  "geometry": {"coordinates":[75.64268300000001,26.959247],"type":"Point"}
}