{
  "type": "Feature",
  "properties": {
    "iso:country":"IN",
    "ks:ks_name":"Ambasal",
    "ks:ks_pop":1603,
    "ks:ks_type":"VILLAGE",
    "name:eng_x_preferred":[
        "Ambasal"
    ],
    "wof:name":"Ambasal",
    "wof:placetype":"locality",
    "wof:population":1603
},
  "geometry": {"coordinates":[86.28260299999999,20.103665],"type":"Point"}
}