{
  "type": "Feature",
  "properties": {
    "iso:country":"IN",
    "ks:ks_name":"Sorafali",
    "ks:ks_pop":0,
    "ks:ks_type":"VILLAGE",
    "name:eng_x_preferred":[
        "Sorafali"
    ],
    "wof:name":"Sorafali",
    "wof:placetype":"locality",
    "wof:population":0
},
  "geometry": {"coordinates":[73.684088,21.49199],"type":"Point"}
}