{
  "type": "Feature",
  "properties": {
    "gn:admin1_code":"36",
    "gn:admin2_code":"142.0",
    "gn:asciiname":"Bhatwara",
    "gn:country_code":"IN",
    "gn:dem":201,
    "gn:feature_class":"P",
    "gn:feature_code":"PPL",
    "gn:name":"Bhatw\u0101ra",
    "gn:population":0,
    "gn:timezone":"Asia/Kolkata",
    "iso:country":"IN",
    "name:und_x_variant":[
        "Bhatw\u0101ra",
        "Murtaz\u0101b\u0101d"
    ],
    "wof:name":"Bhatwara",
    "wof:placetype":"locality"
},
  "geometry": {"coordinates":[77.91457,28.29256],"type":"Point"}
}