{
  "type": "Feature",
  "properties": {
    "gn:admin1_code":"39.0",
    "gn:admin2_code":"061",
    "gn:asciiname":"Kaldhunga",
    "gn:country_code":"IN",
    "gn:dem":1192,
    "gn:feature_class":"P",
    "gn:feature_code":"PPL",
    "gn:name":"Kaldhunga",
    "gn:population":0,
    "gn:timezone":"Asia/Kolkata",
    "iso:country":"IN",
    "ks:ks_alt_nam":"kaldunga",
    "ks:ks_name":"Kaldunga",
    "ks:ks_pop":140,
    "ks:ks_type":"HABITATION",
    "name:eng_x_preferred":[
        "Kaldunga"
    ],
    "name:eng_x_variant":[
        "Kaldhunga"
    ],
    "wof:name":"Kaldunga",
    "wof:placetype":"locality",
    "wof:population":140
},
  "geometry": {"coordinates":[78.668824,29.828356],"type":"Point"}
}