{
  "type": "Feature",
  "properties": {
    "gn:admin1_code":"35",
    "gn:admin2_code":"456.0",
    "gn:asciiname":"Khursipar Khurd",
    "gn:country_code":"IN",
    "gn:dem":573,
    "gn:feature_class":"P",
    "gn:feature_code":"PPL",
    "gn:name":"Khurs\u012bp\u0101r Khurd",
    "gn:population":0,
    "gn:timezone":"Asia/Kolkata",
    "iso:country":"IN",
    "wof:name":"Khursipar Khurd",
    "wof:placetype":"locality"
},
  "geometry": {"coordinates":[79.65120999999998,22.03625],"type":"Point"}
}