{
  "type": "Feature",
  "properties": {
    "iso:country":"IN",
    "ks:ks_alt_nam":"BORDMAN NAGAR",
    "ks:ks_name":"Bordman Nagar",
    "ks:ks_pop":399,
    "ks:ks_type":"HABITATION",
    "ks:ks_uagg_main":0,
    "name:eng_x_preferred":[
        "Bordman Nagar"
    ],
    "wof:name":"Bordman Nagar",
    "wof:placetype":"neighbourhood",
    "wof:population":399
},
  "geometry": {"coordinates":[85.801211,24.915049],"type":"Point"}
}