{
  "type": "Feature",
  "properties": {
    "iso:country":"IN",
    "ks:ks_alt_nam":"Naxa tilla FV",
    "ks:ks_name":"Naxa Tilla Fv",
    "ks:ks_pop":981,
    "ks:ks_type":"HABITATION",
    "name:eng_x_preferred":[
        "Naxa Tilla Fv"
    ],
    "wof:name":"Naxa Tilla Fv",
    "wof:placetype":"locality",
    "wof:population":981
},
  "geometry": {"coordinates":[92.738804,24.559043],"type":"Point"}
}