{
  "type": "Feature",
  "properties": {
    "iso:country":"IN",
    "ks:ks_name":"Kusumajodi",
    "ks:ks_pop":2257,
    "ks:ks_type":"VILLAGE",
    "name:eng_x_preferred":[
        "Kusumajodi"
    ],
    "wof:name":"Kusumajodi",
    "wof:placetype":"locality",
    "wof:population":2257
},
  "geometry": {"coordinates":[85.528695,20.8201],"type":"Point"}
}