{
  "type": "Feature",
  "properties": {
    "iso:country":"IN",
    "ks:ks_name":"Dalak Jamatia Para",
    "ks:ks_pop":227,
    "ks:ks_type":"HABITATION",
    "name:eng_x_preferred":[
        "Dalak Jamatia Para"
    ],
    "wof:name":"Dalak Jamatia Para",
    "wof:placetype":"locality",
    "wof:population":227
},
  "geometry": {"coordinates":[91.680082,23.500408],"type":"Point"}
}