{
  "type": "Feature",
  "properties": {
    "iso:country":"IN",
    "ks:ks_name":"Jakharia Chuk",
    "ks:ks_pop":1433,
    "ks:ks_type":"HABITATION",
    "name:eng_x_preferred":[
        "Jakharia Chuk"
    ],
    "wof:name":"Jakharia Chuk",
    "wof:placetype":"locality",
    "wof:population":1433
},
  "geometry": {"coordinates":[94.409128,26.841502],"type":"Point"}
}