{
  "type": "Feature",
  "properties": {
    "iso:country":"IN",
    "ks:ks_name":"Garhi",
    "ks:ks_pop":101,
    "ks:ks_type":"HABITATION",
    "name:eng_x_preferred":[
        "Garhi"
    ],
    "wof:name":"Garhi",
    "wof:placetype":"locality",
    "wof:population":101
},
  "geometry": {"coordinates":[78.63229,27.83092],"type":"Point"}
}