{
  "type": "Feature",
  "properties": {
    "gn:admin1_code":"38.0",
    "gn:admin2_code":"347.0",
    "gn:asciiname":"Sildag",
    "gn:country_code":"IN",
    "gn:dem":374,
    "gn:feature_class":"P",
    "gn:feature_code":"PPL",
    "gn:name":"Sild\u0101g",
    "gn:population":0,
    "gn:timezone":"Asia/Kolkata",
    "iso:country":"IN",
    "ks:ks_alt_nam":"Sild\u0101g",
    "ks:ks_name":"Sildag",
    "ks:ks_pop":1648,
    "ks:ks_type":"VILLAGE",
    "name:eng_x_preferred":[
        "Sildag"
    ],
    "name:eng_x_variant":[
        "Sild\u0101g"
    ],
    "wof:name":"Sildag",
    "wof:placetype":"locality",
    "wof:population":1648
},
  "geometry": {"coordinates":[84.66516900000001,24.094265],"type":"Point"}
}