{
  "type": "Feature",
  "properties": {
    "gn:admin1_code":"40",
    "gn:admin2_code":"537.0",
    "gn:asciiname":"Shankarpalli",
    "gn:country_code":"IN",
    "gn:dem":581,
    "gn:feature_class":"P",
    "gn:feature_code":"PPL",
    "gn:name":"Shankarpalli",
    "gn:population":0,
    "gn:timezone":"Asia/Kolkata",
    "iso:country":"IN",
    "name:new_x_preferred":[
        "\u0936\u0902\u0915\u0930\u092a\u0932\u094d\u0932\u093f \u092e\u0923\u094d\u0921\u0932"
    ],
    "name:tel_x_preferred":[
        "\u0c36\u0c02\u0c15\u0c30\u0c4d\u200c\u0c2a\u0c32\u0c4d\u0c32\u0c3f"
    ],
    "name:und_x_variant":[
        "Shankerpalli",
        "Shankarpalli"
    ],
    "wof:name":"Shankarpalli",
    "wof:placetype":"locality"
},
  "geometry": {"coordinates":[78.131,17.45229],"type":"Point"}
}