{
  "type": "Feature",
  "properties": {
    "gn:admin1_code":"34.0",
    "gn:admin2_code":"207.0",
    "gn:asciiname":"Kaithahi",
    "gn:country_code":"IN",
    "gn:dem":62,
    "gn:feature_class":"P",
    "gn:feature_code":"PPL",
    "gn:name":"Kaith\u0101hi",
    "gn:population":0,
    "gn:timezone":"Asia/Kolkata",
    "iso:country":"IN",
    "ks:ks_alt_nam":"Kaith\u0101hi",
    "ks:ks_name":"Kaithahi",
    "ks:ks_pop":4860,
    "ks:ks_type":"VILLAGE",
    "ks:ks_uagg_main":0,
    "name:eng_x_preferred":[
        "Kaithahi"
    ],
    "name:eng_x_variant":[
        "Kaith\u0101hi"
    ],
    "wof:name":"Kaithahi",
    "wof:placetype":"neighbourhood",
    "wof:population":4860
},
  "geometry": {"coordinates":[86.153446,26.34724],"type":"Point"}
}