{
  "type": "Feature",
  "properties": {
    "gn:admin1_code":"36.0",
    "gn:admin2_code":"174.0",
    "gn:asciiname":"Malaka",
    "gn:country_code":"IN",
    "gn:dem":111,
    "gn:feature_class":"P",
    "gn:feature_code":"PPL",
    "gn:name":"Mal\u0101ka",
    "gn:population":0,
    "gn:timezone":"Asia/Kolkata",
    "iso:country":"IN",
    "name:ceb_x_preferred":[
        "Malaka"
    ],
    "name:ces_x_preferred":[
        "Malaka"
    ],
    "name:deu_x_preferred":[
        "Malaka"
    ],
    "name:fra_x_preferred":[
        "Malaka"
    ],
    "name:nld_x_preferred":[
        "Malaka"
    ],
    "name:slk_x_preferred":[
        "Malaka"
    ],
    "name:swe_x_preferred":[
        "Malaka"
    ],
    "wof:name":"Malaka",
    "wof:placetype":"locality"
},
  "geometry": {"coordinates":[81.27282,25.75345],"type":"Point"}
}