{
  "type": "Feature",
  "properties": {
    "iso:country":"IN",
    "ks:ks_name":"Nazar Ali Milik",
    "ks:ks_pop":994,
    "ks:ks_type":"VILLAGE",
    "name:eng_x_preferred":[
        "Nazar Ali Milik"
    ],
    "wof:name":"Nazar Ali Milik",
    "wof:placetype":"locality",
    "wof:population":994
},
  "geometry": {"coordinates":[87.004578,25.613104],"type":"Point"}
}