{
  "type": "Feature",
  "properties": {
    "iso:country":"IN",
    "ks:ks_name":"Killa Mura",
    "ks:ks_pop":326,
    "ks:ks_type":"HABITATION",
    "name:eng_x_preferred":[
        "Killa Mura"
    ],
    "wof:name":"Killa Mura",
    "wof:placetype":"locality",
    "wof:population":326
},
  "geometry": {"coordinates":[91.490982,23.244065],"type":"Point"}
}