{
  "type": "Feature",
  "properties": {
    "iso:country":"IN",
    "ks:ks_name":"Babari",
    "ks:ks_pop":79,
    "ks:ks_type":"VILLAGE",
    "name:eng_x_preferred":[
        "Babari"
    ],
    "wof:name":"Babari",
    "wof:placetype":"locality",
    "wof:population":79
},
  "geometry": {"coordinates":[79.626988,29.747973],"type":"Point"}
}