{
  "type": "Feature",
  "properties": {
    "gn:admin1_code":"16",
    "gn:admin2_code":"523.0",
    "gn:asciiname":"Nandgaul",
    "gn:country_code":"IN",
    "gn:dem":591,
    "gn:feature_class":"P",
    "gn:feature_code":"PPL",
    "gn:name":"Nandgaul",
    "gn:population":0,
    "gn:timezone":"Asia/Kolkata",
    "iso:country":"IN",
    "wof:name":"Nandgaul",
    "wof:placetype":"locality"
},
  "geometry": {"coordinates":[76.51776,18.7728],"type":"Point"}
}