{
  "type": "Feature",
  "properties": {
    "gn:admin1_code":"36",
    "gn:admin2_code":"143.0",
    "gn:asciiname":"Ghangauli",
    "gn:country_code":"IN",
    "gn:dem":192,
    "gn:feature_class":"P",
    "gn:feature_code":"PPL",
    "gn:name":"Gh\u0101ngauli",
    "gn:population":0,
    "gn:timezone":"Asia/Kolkata",
    "iso:country":"IN",
    "wof:name":"Ghangauli",
    "wof:placetype":"locality"
},
  "geometry": {"coordinates":[77.61667,27.94058],"type":"Point"}
}