{
  "type": "Feature",
  "properties": {
    "iso:country":"IN",
    "ks:ks_name":"Lakhanpur",
    "ks:ks_pop":294,
    "ks:ks_type":"VILLAGE",
    "name:eng_x_preferred":[
        "Lakhanpur"
    ],
    "wof:name":"Lakhanpur",
    "wof:placetype":"locality",
    "wof:population":294
},
  "geometry": {"coordinates":[87.38007500000001,24.318124],"type":"Point"}
}