{
  "type": "Feature",
  "properties": {
    "iso:country":"IN",
    "ks:ks_name":"Kali Purwa",
    "ks:ks_pop":102,
    "ks:ks_type":"HABITATION",
    "name:eng_x_preferred":[
        "Kali Purwa"
    ],
    "wof:name":"Kali Purwa",
    "wof:placetype":"locality",
    "wof:population":102
},
  "geometry": {"coordinates":[81.829908,27.646896],"type":"Point"}
}