{
  "type": "Feature",
  "properties": {
    "gn:admin1_code":"23.0",
    "gn:admin2_code":"35.0",
    "gn:asciiname":"Bains",
    "gn:country_code":"IN",
    "gn:dem":253,
    "gn:feature_class":"P",
    "gn:feature_code":"PPL",
    "gn:name":"Bains",
    "gn:population":0,
    "gn:timezone":"Asia/Kolkata",
    "iso:country":"IN",
    "name:bre_x_preferred":[
        "Bains"
    ],
    "name:ceb_x_preferred":[
        "Bains"
    ],
    "name:deu_x_preferred":[
        "Bains"
    ],
    "name:fra_x_preferred":[
        "Bains"
    ],
    "name:nld_x_preferred":[
        "Bains"
    ],
    "name:spa_x_preferred":[
        "Bains"
    ],
    "name:swe_x_preferred":[
        "Bains"
    ],
    "wof:name":"Bains",
    "wof:placetype":"locality"
},
  "geometry": {"coordinates":[75.33034000000001,32.10649],"type":"Point"}
}