{
  "type": "Feature",
  "properties": {
    "iso:country":"IN",
    "ks:ks_name":"Kusum",
    "ks:ks_pop":413,
    "ks:ks_type":"VILLAGE",
    "name:eng_x_preferred":[
        "Kusum"
    ],
    "wof:name":"Kusum",
    "wof:placetype":"locality",
    "wof:population":413
},
  "geometry": {"coordinates":[84.947193,22.618913],"type":"Point"}
}