{
  "type": "Feature",
  "properties": {
    "iso:country":"IN",
    "ks:ks_name":"Nallur",
    "ks:ks_pop":293,
    "ks:ks_type":"VILLAGE",
    "name:eng_x_preferred":[
        "Nallur"
    ],
    "wof:name":"Nallur",
    "wof:placetype":"locality",
    "wof:population":293
},
  "geometry": {"coordinates":[76.38677800000001,11.962131],"type":"Point"}
}