{
  "type": "Feature",
  "properties": {
    "gn:admin1_code":"25.0",
    "gn:admin2_code":"606.0",
    "gn:asciiname":"Tondamanur",
    "gn:country_code":"IN",
    "gn:dem":157,
    "gn:feature_class":"P",
    "gn:feature_code":"PPL",
    "gn:name":"Tondam\u0101n\u016br",
    "gn:population":0,
    "gn:timezone":"Asia/Kolkata",
    "iso:country":"IN",
    "ks:ks_name":"Thondamanur",
    "ks:ks_pop":1112,
    "ks:ks_type":"VILLAGE",
    "name:eng_x_preferred":[
        "Thondamanur"
    ],
    "name:eng_x_variant":[
        "Tondamanur"
    ],
    "wof:name":"Thondamanur",
    "wof:placetype":"locality",
    "wof:population":1112
},
  "geometry": {"coordinates":[78.952657,12.087825],"type":"Point"}
}