{
  "type": "Feature",
  "properties": {
    "iso:country":"IN",
    "ks:ks_name":"Adivasi Para",
    "ks:ks_pop":850,
    "ks:ks_type":"HABITATION",
    "name:eng_x_preferred":[
        "Adivasi Para"
    ],
    "wof:name":"Adivasi Para",
    "wof:placetype":"locality",
    "wof:population":850
},
  "geometry": {"coordinates":[88.68163699999999,22.234558],"type":"Point"}
}