{
  "type": "Feature",
  "properties": {
    "gn:admin1_code":"40.0",
    "gn:admin2_code":"534.0",
    "gn:asciiname":"Gollapalli",
    "gn:country_code":"IN",
    "gn:dem":244,
    "gn:feature_class":"P",
    "gn:feature_code":"PPL",
    "gn:name":"Gollapalli",
    "gn:population":0,
    "gn:timezone":"Asia/Kolkata",
    "iso:country":"IN",
    "ks:ks_name":"Gollapalli",
    "ks:ks_type":"VILLAGE",
    "name:eng_x_preferred":[
        "Gollapalli"
    ],
    "wof:name":"Gollapalli",
    "wof:placetype":"locality"
},
  "geometry": {"coordinates":[79.24404800000001,18.45654],"type":"Point"}
}