{
  "type": "Feature",
  "properties": {
    "iso:country":"IN",
    "ks:ks_name":"Panankadu",
    "ks:ks_pop":101,
    "ks:ks_type":"HABITATION",
    "name:eng_x_preferred":[
        "Panankadu"
    ],
    "wof:name":"Panankadu",
    "wof:placetype":"locality",
    "wof:population":101
},
  "geometry": {"coordinates":[79.08395,10.178087],"type":"Point"}
}