{
  "type": "Feature",
  "properties": {
    "gn:admin1_code":"12.0",
    "gn:admin2_code":"002",
    "gn:asciiname":"Asthanpur",
    "gn:country_code":"IN",
    "gn:dem":1596,
    "gn:feature_class":"P",
    "gn:feature_code":"PPL",
    "gn:name":"Asthanpur",
    "gn:population":0,
    "gn:timezone":"Asia/Kolkata",
    "iso:country":"IN",
    "wof:name":"Asthanpur",
    "wof:placetype":"locality"
},
  "geometry": {"coordinates":[74.80407,34.0196],"type":"Point"}
}