{
  "type": "Feature",
  "properties": {
    "iso:country":"IN",
    "ks:ks_alt_nam":"GORIARI",
    "ks:ks_name":"Goriari",
    "ks:ks_pop":822,
    "ks:ks_type":"HABITATION",
    "name:eng_x_preferred":[
        "Goriari"
    ],
    "wof:name":"Goriari",
    "wof:placetype":"locality",
    "wof:population":822
},
  "geometry": {"coordinates":[87.417824,25.505021],"type":"Point"}
}