{
  "type": "Feature",
  "properties": {
    "iso:country":"IN",
    "ks:ks_name":"Panwar Purwa",
    "ks:ks_pop":250,
    "ks:ks_type":"HABITATION",
    "name:eng_x_preferred":[
        "Panwar Purwa"
    ],
    "wof:name":"Panwar Purwa",
    "wof:placetype":"locality",
    "wof:population":250
},
  "geometry": {"coordinates":[81.414135,26.55758],"type":"Point"}
}