{
  "type": "Feature",
  "properties": {
    "iso:country":"IN",
    "ks:ks_alt_nam":"DESAIWASTI",
    "ks:ks_name":"Desaiwasti",
    "ks:ks_pop":77,
    "ks:ks_type":"HABITATION",
    "name:eng_x_preferred":[
        "Desaiwasti"
    ],
    "wof:name":"Desaiwasti",
    "wof:placetype":"locality",
    "wof:population":77
},
  "geometry": {"coordinates":[74.273218,17.13032],"type":"Point"}
}