{
  "type": "Feature",
  "properties": {
    "iso:country":"IN",
    "ks:ks_name":"Ebrahimpur Murar Singh",
    "ks:ks_pop":0,
    "ks:ks_type":"VILLAGE",
    "name:eng_x_preferred":[
        "Ebrahimpur Murar Singh"
    ],
    "wof:name":"Ebrahimpur Murar Singh",
    "wof:placetype":"locality",
    "wof:population":0
},
  "geometry": {"coordinates":[83.77891200000001,25.773073],"type":"Point"}
}