{
  "type": "Feature",
  "properties": {
    "iso:country":"IN",
    "ks:ks_name":"Chandipur",
    "ks:ks_pop":2225,
    "ks:ks_type":"VILLAGE",
    "name:eng_x_preferred":[
        "Chandipur"
    ],
    "wof:name":"Chandipur",
    "wof:placetype":"locality",
    "wof:population":2225
},
  "geometry": {"coordinates":[88.051244,21.700117],"type":"Point"}
}