{
  "type": "Feature",
  "properties": {
    "iso:country":"IN",
    "ks:ks_name":"Badewasti",
    "ks:ks_pop":203,
    "ks:ks_type":"HABITATION",
    "name:eng_x_preferred":[
        "Badewasti"
    ],
    "wof:name":"Badewasti",
    "wof:placetype":"locality",
    "wof:population":203
},
  "geometry": {"coordinates":[75.08208999999999,19.341584],"type":"Point"}
}