{
  "type": "Feature",
  "properties": {
    "iso:country":"IN",
    "ks:ks_name":"Loni",
    "ks:ks_pop":82,
    "ks:ks_type":"VILLAGE",
    "name:eng_x_preferred":[
        "Loni"
    ],
    "wof:name":"Loni",
    "wof:placetype":"locality",
    "wof:population":82
},
  "geometry": {"coordinates":[81.319625,25.046208],"type":"Point"}
}