{
  "type": "Feature",
  "properties": {
    "gn:admin1_code":"19",
    "gn:admin2_code":"556.0",
    "gn:asciiname":"Harnapur",
    "gn:country_code":"IN",
    "gn:dem":538,
    "gn:feature_class":"P",
    "gn:feature_code":"PPL",
    "gn:name":"Harn\u0101pur",
    "gn:population":0,
    "gn:timezone":"Asia/Kolkata",
    "iso:country":"IN",
    "wof:name":"Harnapur",
    "wof:placetype":"locality"
},
  "geometry": {"coordinates":[76.28564,16.02548],"type":"Point"}
}