{
  "type": "Feature",
  "properties": {
    "gn:admin1_code":"24.0",
    "gn:admin2_code":"100",
    "gn:asciiname":"Kanau",
    "gn:country_code":"IN",
    "gn:dem":209,
    "gn:feature_class":"P",
    "gn:feature_code":"PPL",
    "gn:name":"Kan\u0101u",
    "gn:population":0,
    "gn:timezone":"Asia/Kolkata",
    "iso:country":"IN",
    "name:und_x_variant":[
        "Kan\u0101u",
        "Kanau"
    ],
    "wof:name":"Kanau",
    "wof:placetype":"locality"
},
  "geometry": {"coordinates":[74.90954000000001,28.99188],"type":"Point"}
}