{
  "type": "Feature",
  "properties": {
    "iso:country":"IN",
    "ks:ks_name":"Sikandarpur",
    "ks:ks_type":"VILLAGE",
    "ks:ks_uagg_main":0,
    "name:eng_x_preferred":[
        "Sikandarpur"
    ],
    "wof:name":"Sikandarpur",
    "wof:placetype":"neighbourhood"
},
  "geometry": {"coordinates":[77.347185,28.703806],"type":"Point"}
}