{
  "type": "Feature",
  "properties": {
    "iso:country":"IN",
    "ks:ks_name":"Barbalia",
    "ks:ks_pop":599,
    "ks:ks_type":"VILLAGE",
    "name:eng_x_preferred":[
        "Barbalia"
    ],
    "wof:name":"Barbalia",
    "wof:placetype":"locality",
    "wof:population":599
},
  "geometry": {"coordinates":[87.335401,22.050703],"type":"Point"}
}