{
  "type": "Feature",
  "properties": {
    "gn:admin1_code":"36.0",
    "gn:admin2_code":"193.0",
    "gn:asciiname":"Karmanpur",
    "gn:country_code":"IN",
    "gn:dem":62,
    "gn:feature_class":"P",
    "gn:feature_code":"PPL",
    "gn:name":"Karmanpur",
    "gn:population":0,
    "gn:timezone":"Asia/Kolkata",
    "iso:country":"IN",
    "ks:ks_name":"Karmanpur",
    "ks:ks_pop":2655,
    "ks:ks_type":"HABITATION",
    "ks:ks_uagg_main":0,
    "name:eng_x_preferred":[
        "Karmanpur"
    ],
    "wof:name":"Karmanpur",
    "wof:placetype":"neighbourhood",
    "wof:population":2655
},
  "geometry": {"coordinates":[84.459862,25.805041],"type":"Point"}
}