{
  "type": "Feature",
  "properties": {
    "gn:admin1_code":"36",
    "gn:admin2_code":"185.0",
    "gn:asciiname":"Pakri",
    "gn:country_code":"IN",
    "gn:dem":95,
    "gn:feature_class":"P",
    "gn:feature_code":"PPL",
    "gn:name":"Pakri",
    "gn:population":0,
    "gn:timezone":"Asia/Kolkata",
    "iso:country":"IN",
    "ks:ks_name":"Pakri",
    "ks:ks_type":"VILLAGE",
    "name:eng_x_preferred":[
        "Pakri"
    ],
    "name:est_x_preferred":[
        "Pakri"
    ],
    "name:lav_x_preferred":[
        "Pakri"
    ],
    "wof:name":"Pakri",
    "wof:placetype":"locality"
},
  "geometry": {"coordinates":[82.837524,26.956927],"type":"Point"}
}