{
  "type": "Feature",
  "properties": {
    "iso:country":"IN",
    "ks:ks_name":"Machhnan",
    "ks:ks_pop":1053,
    "ks:ks_type":"VILLAGE",
    "ks:ks_uagg_main":0,
    "name:eng_x_preferred":[
        "Machhnan"
    ],
    "wof:name":"Machhnan",
    "wof:placetype":"neighbourhood",
    "wof:population":1053
},
  "geometry": {"coordinates":[87.72918799999999,22.038587],"type":"Point"}
}