{
  "type": "Feature",
  "properties": {
    "gn:admin1_code":"2.0",
    "gn:admin2_code":"542.0",
    "gn:asciiname":"Buradapeta",
    "gn:country_code":"IN",
    "gn:dem":28,
    "gn:feature_class":"P",
    "gn:feature_code":"PPL",
    "gn:name":"B\u016br\u0101dapeta",
    "gn:population":0,
    "gn:timezone":"Asia/Kolkata",
    "iso:country":"IN",
    "wof:name":"Buradapeta",
    "wof:placetype":"locality"
},
  "geometry": {"coordinates":[83.81461999999998,18.45684],"type":"Point"}
}