{
  "type": "Feature",
  "properties": {
    "iso:country":"IN",
    "ks:ks_name":"Jalanalli",
    "ks:ks_pop":16,
    "ks:ks_type":"HABITATION",
    "name:eng_x_preferred":[
        "Jalanalli"
    ],
    "wof:name":"Jalanalli",
    "wof:placetype":"locality",
    "wof:population":16
},
  "geometry": {"coordinates":[74.600326,14.521022],"type":"Point"}
}