{
  "type": "Feature",
  "properties": {
    "iso:country":"IN",
    "ks:ks_alt_nam":"KAMAT HARIZON TOLA",
    "ks:ks_name":"Kamat Harizon Tola",
    "ks:ks_pop":61,
    "ks:ks_type":"HABITATION",
    "ks:ks_uagg_main":0,
    "name:eng_x_preferred":[
        "Kamat Harizon Tola"
    ],
    "wof:name":"Kamat Harizon Tola",
    "wof:placetype":"neighbourhood",
    "wof:population":61
},
  "geometry": {"coordinates":[87.990999,26.166434],"type":"Point"}
}