{
  "type": "Feature",
  "properties": {
    "iso:country":"IN",
    "ks:ks_name":"Mukundapur",
    "ks:ks_pop":914,
    "ks:ks_type":"VILLAGE",
    "ks:ks_uagg_main":0,
    "name:eng_x_preferred":[
        "Mukundapur"
    ],
    "wof:name":"Mukundapur",
    "wof:placetype":"neighbourhood",
    "wof:population":914
},
  "geometry": {"coordinates":[88.719052,23.483985],"type":"Point"}
}