{
  "type": "Feature",
  "properties": {
    "iso:country":"IN",
    "ks:ks_name":"Sithargalnatham",
    "ks:ks_pop":520,
    "ks:ks_type":"HABITATION",
    "ks:ks_uagg_main":0,
    "name:eng_x_preferred":[
        "Sithargalnatham"
    ],
    "wof:name":"Sithargalnatham",
    "wof:placetype":"neighbourhood",
    "wof:population":520
},
  "geometry": {"coordinates":[77.842482,10.087331],"type":"Point"}
}