{
  "type": "Feature",
  "properties": {
    "iso:country":"IN",
    "ks:ks_alt_nam":"Garbhanga F.V. 1",
    "ks:ks_name":"Garbhanga F.v. 1",
    "ks:ks_pop":95,
    "ks:ks_type":"HABITATION",
    "name:eng_x_preferred":[
        "Garbhanga F.v. 1"
    ],
    "wof:name":"Garbhanga F.v. 1",
    "wof:placetype":"locality",
    "wof:population":95
},
  "geometry": {"coordinates":[91.68067600000001,25.998921],"type":"Point"}
}