{
  "type": "Feature",
  "properties": {
    "iso:country":"IN",
    "ks:ks_name":"Navezari",
    "ks:ks_pop":252,
    "ks:ks_type":"VILLAGE",
    "name:eng_x_preferred":[
        "Navezari"
    ],
    "wof:name":"Navezari",
    "wof:placetype":"locality",
    "wof:population":252
},
  "geometry": {"coordinates":[80.38686300000001,20.753378],"type":"Point"}
}