{
  "type": "Feature",
  "properties": {
    "gn:admin1_code":"19.0",
    "gn:admin2_code":"584.0",
    "gn:asciiname":"Vajarhalli",
    "gn:country_code":"IN",
    "gn:dem":763,
    "gn:feature_class":"P",
    "gn:feature_code":"PPL",
    "gn:name":"V\u0101jarhalli",
    "gn:population":0,
    "gn:timezone":"Asia/Kolkata",
    "iso:country":"IN",
    "wof:name":"Vajarhalli",
    "wof:placetype":"neighbourhood"
},
  "geometry": {"coordinates":[77.39158,12.82378],"type":"Point"}
}