{
  "type": "Feature",
  "properties": {
    "iso:country":"IN",
    "ks:ks_name":"Thatia Garh Goriari",
    "ks:ks_pop":3087,
    "ks:ks_type":"VILLAGE",
    "name:eng_x_preferred":[
        "Thatia Garh Goriari"
    ],
    "wof:name":"Thatia Garh Goriari",
    "wof:placetype":"locality",
    "wof:population":3087
},
  "geometry": {"coordinates":[85.29386100000001,26.019789],"type":"Point"}
}