{
  "type": "Feature",
  "properties": {
    "gn:admin1_code":"19.0",
    "gn:admin2_code":"577.0",
    "gn:asciiname":"Dwarekere",
    "gn:country_code":"IN",
    "gn:dem":885,
    "gn:feature_class":"P",
    "gn:feature_code":"PPL",
    "gn:name":"Dwarekere",
    "gn:population":0,
    "gn:timezone":"Asia/Kolkata",
    "iso:country":"IN",
    "wof:name":"Dwarekere",
    "wof:placetype":"locality"
},
  "geometry": {"coordinates":[76.1644,12.41339],"type":"Point"}
}