{
  "type": "Feature",
  "properties": {
    "gn:admin1_code":"35.0",
    "gn:admin2_code":"447.0",
    "gn:asciiname":"Kharparakheri",
    "gn:country_code":"IN",
    "gn:dem":725,
    "gn:feature_class":"P",
    "gn:feature_code":"PPL",
    "gn:name":"Kharpar\u0101kheri",
    "gn:population":0,
    "gn:timezone":"Asia/Kolkata",
    "iso:country":"IN",
    "wof:name":"Kharparakheri",
    "wof:placetype":"locality"
},
  "geometry": {"coordinates":[78.25032,21.89782],"type":"Point"}
}