{
  "type": "Feature",
  "properties": {
    "iso:country":"IN",
    "ks:ks_alt_nam":"WAGHAMAREWASTI",
    "ks:ks_name":"Waghamarewasti",
    "ks:ks_pop":77,
    "ks:ks_type":"HABITATION",
    "name:eng_x_preferred":[
        "Waghamarewasti"
    ],
    "wof:name":"Waghamarewasti",
    "wof:placetype":"locality",
    "wof:population":77
},
  "geometry": {"coordinates":[74.703883,17.199682],"type":"Point"}
}