{
  "type": "Feature",
  "properties": {
    "iso:country":"IN",
    "ks:ks_name":"Gitikapadar",
    "ks:ks_pop":318,
    "ks:ks_type":"HABITATION",
    "name:eng_x_preferred":[
        "Gitikapadar"
    ],
    "wof:name":"Gitikapadar",
    "wof:placetype":"locality",
    "wof:population":318
},
  "geometry": {"coordinates":[82.738438,19.730756],"type":"Point"}
}