{
  "type": "Feature",
  "properties": {
    "gn:admin1_code":"11.0",
    "gn:admin2_code":"32.0",
    "gn:asciiname":"Tapra",
    "gn:country_code":"IN",
    "gn:dem":971,
    "gn:feature_class":"P",
    "gn:feature_code":"PPL",
    "gn:name":"Tapra",
    "gn:population":0,
    "gn:timezone":"Asia/Kolkata",
    "iso:country":"IN",
    "wof:name":"Tapra",
    "wof:placetype":"locality"
},
  "geometry": {"coordinates":[77.70896,30.72497000000001],"type":"Point"}
}