{
  "type": "Feature",
  "properties": {
    "gn:admin1_code":"19.0",
    "gn:admin2_code":"573.0",
    "gn:asciiname":"Honaganagalli",
    "gn:country_code":"IN",
    "gn:dem":810,
    "gn:feature_class":"P",
    "gn:feature_code":"PPL",
    "gn:name":"Honag\u0101nagalli",
    "gn:population":0,
    "gn:timezone":"Asia/Kolkata",
    "iso:country":"IN",
    "wof:name":"Honaganagalli",
    "wof:placetype":"locality"
},
  "geometry": {"coordinates":[76.5979,12.52586],"type":"Point"}
}