{
  "type": "Feature",
  "properties": {
    "iso:country":"IN",
    "ks:ks_name":"Misraulia",
    "ks:ks_pop":605,
    "ks:ks_type":"VILLAGE",
    "ks:ks_uagg_main":0,
    "name:eng_x_preferred":[
        "Misraulia"
    ],
    "wof:name":"Misraulia",
    "wof:placetype":"locality",
    "wof:population":605
},
  "geometry": {"coordinates":[83.983986,25.557377],"type":"Point"}
}