{
  "type": "Feature",
  "properties": {
    "iso:country":"IN",
    "ks:ks_name":"Marilingegowdanakoppalu",
    "ks:ks_pop":191,
    "ks:ks_type":"HABITATION",
    "name:eng_x_preferred":[
        "Marilingegowdanakoppalu"
    ],
    "wof:name":"Marilingegowdanakoppalu",
    "wof:placetype":"locality",
    "wof:population":191
},
  "geometry": {"coordinates":[76.25346500000001,12.646789],"type":"Point"}
}