{
  "type": "Feature",
  "properties": {
    "iso:country":"IN",
    "ks:ks_name":"Kanta",
    "ks:ks_pop":99,
    "ks:ks_type":"HABITATION",
    "name:eng_x_preferred":[
        "Kanta"
    ],
    "wof:name":"Kanta",
    "wof:placetype":"locality",
    "wof:population":99
},
  "geometry": {"coordinates":[82.60765600000001,18.390636],"type":"Point"}
}