{
  "type": "Feature",
  "properties": {
    "gn:admin1_code":"2.0",
    "gn:admin2_code":"550.0",
    "gn:asciiname":"Zangamvani Doruvu",
    "gn:country_code":"IN",
    "gn:dem":10,
    "gn:feature_class":"P",
    "gn:feature_code":"PPL",
    "gn:name":"Zangamv\u0101ni Doruvu",
    "gn:population":0,
    "gn:timezone":"Asia/Kolkata",
    "iso:country":"IN",
    "wof:name":"Zangamvani Doruvu",
    "wof:placetype":"locality"
},
  "geometry": {"coordinates":[80.13531,14.47095],"type":"Point"}
}