{
  "type": "Feature",
  "properties": {
    "iso:country":"IN",
    "ks:ks_name":"Paikpara",
    "ks:ks_pop":315,
    "ks:ks_type":"VILLAGE",
    "ks:ks_uagg_main":0,
    "name:eng_x_preferred":[
        "Paikpara"
    ],
    "wof:name":"Paikpara",
    "wof:placetype":"neighbourhood",
    "wof:population":315
},
  "geometry": {"coordinates":[87.69515800000001,23.853807],"type":"Point"}
}