{
  "type": "Feature",
  "properties": {
    "iso:country":"IN",
    "ks:ks_name":"Vadakkipatti",
    "ks:ks_pop":390,
    "ks:ks_type":"HABITATION",
    "name:eng_x_preferred":[
        "Vadakkipatti"
    ],
    "wof:name":"Vadakkipatti",
    "wof:placetype":"locality",
    "wof:population":390
},
  "geometry": {"coordinates":[78.333972,10.497139],"type":"Point"}
}