{
  "type": "Feature",
  "properties": {
    "iso:country":"IN",
    "ks:ks_name":"Banki",
    "ks:ks_pop":548,
    "ks:ks_type":"VILLAGE",
    "name:eng_x_preferred":[
        "Banki"
    ],
    "wof:name":"Banki",
    "wof:placetype":"locality",
    "wof:population":548
},
  "geometry": {"coordinates":[86.931358,24.937887],"type":"Point"}
}