{
  "type": "Feature",
  "properties": {
    "iso:country":"IN",
    "ks:ks_alt_nam":"KHALCHI GURAVWADI",
    "ks:ks_name":"Khalchi Guravwadi",
    "ks:ks_pop":75,
    "ks:ks_type":"HABITATION",
    "name:eng_x_preferred":[
        "Khalchi Guravwadi"
    ],
    "wof:name":"Khalchi Guravwadi",
    "wof:placetype":"neighbourhood",
    "wof:population":75
},
  "geometry": {"coordinates":[73.52620899999999,16.664744],"type":"Point"}
}