{
  "type": "Feature",
  "properties": {
    "gn:admin1_code":"39",
    "gn:admin2_code":"67.0",
    "gn:asciiname":"Sheorajpur Mazra",
    "gn:country_code":"IN",
    "gn:dem":237,
    "gn:feature_class":"P",
    "gn:feature_code":"PPL",
    "gn:name":"Sheor\u0101jpur Mazra",
    "gn:population":0,
    "gn:timezone":"Asia/Kolkata",
    "iso:country":"IN",
    "wof:name":"Sheorajpur Mazra",
    "wof:placetype":"locality"
},
  "geometry": {"coordinates":[78.89466999999998,29.25668],"type":"Point"}
}