{
  "type": "Feature",
  "properties": {
    "gn:admin1_code":"35",
    "gn:admin2_code":"420.0",
    "gn:asciiname":"Yemanpura",
    "gn:country_code":"IN",
    "gn:dem":161,
    "gn:feature_class":"P",
    "gn:feature_code":"PPL",
    "gn:name":"Yemanpura",
    "gn:population":0,
    "gn:timezone":"Asia/Kolkata",
    "iso:country":"IN",
    "wof:name":"Yemanpura",
    "wof:placetype":"locality"
},
  "geometry": {"coordinates":[78.43928000000002,26.53599],"type":"Point"}
}