{
  "type": "Feature",
  "properties": {
    "iso:country":"IN",
    "ks:ks_name":"Matasula",
    "ks:ks_pop":1793,
    "ks:ks_type":"VILLAGE",
    "name:eng_x_preferred":[
        "Matasula"
    ],
    "wof:name":"Matasula",
    "wof:placetype":"locality",
    "wof:population":1793
},
  "geometry": {"coordinates":[74.506996,22.664312],"type":"Point"}
}