{
  "type": "Feature",
  "properties": {
    "iso:country":"IN",
    "ks:ks_name":"Bandhudih",
    "ks:ks_pop":101,
    "ks:ks_type":"HABITATION",
    "name:eng_x_preferred":[
        "Bandhudih"
    ],
    "wof:name":"Bandhudih",
    "wof:placetype":"locality",
    "wof:population":101
},
  "geometry": {"coordinates":[85.82396799999999,22.928211],"type":"Point"}
}