{
  "type": "Feature",
  "properties": {
    "iso:country":"IN",
    "ks:ks_name":"Khedarpur",
    "ks:ks_pop":954,
    "ks:ks_type":"VILLAGE",
    "ks:ks_uagg_main":0,
    "name:eng_x_preferred":[
        "Khedarpur"
    ],
    "wof:name":"Khedarpur",
    "wof:placetype":"neighbourhood",
    "wof:population":954
},
  "geometry": {"coordinates":[86.71680499999999,20.951189],"type":"Point"}
}