{
  "type": "Feature",
  "properties": {
    "iso:country":"IN",
    "ks:ks_name":"Sirsia Tola Shiwnagar Urf Dich",
    "ks:ks_pop":3,
    "ks:ks_type":"VILLAGE",
    "name:eng_x_preferred":[
        "Sirsia Tola Shiwnagar Urf Dich"
    ],
    "wof:name":"Sirsia Tola Shiwnagar Urf Dich",
    "wof:placetype":"locality",
    "wof:population":3
},
  "geometry": {"coordinates":[84.97098800000001,26.616674],"type":"Point"}
}