{
  "type": "Feature",
  "properties": {
    "gn:country":"IN",
    "gn:fcode":"PPL",
    "gn:pop":18820,
    "iso:country":"IN",
    "name:bpy_x_preferred":[
        "\u09ae\u09b2\u09cd\u09b2\u09b8\u09ae\u09c1\u09a6\u09cd\u09b0\u09ae"
    ],
    "name:bul_x_preferred":[
        "\u041c\u0430\u043b\u0430\u0441\u0430\u043c\u0443\u0434\u0440\u0430\u043c"
    ],
    "name:chi_x_preferred":[
        "\u9a6c\u62c9\u8428\u7a46\u5fb7\u62c9\u59c6"
    ],
    "name:dut_x_preferred":[
        "Mallasamudram"
    ],
    "name:eng_x_preferred":[
        "Mallasamudram"
    ],
    "name:fre_x_preferred":[
        "Mallasamudram"
    ],
    "name:ita_x_preferred":[
        "Mallasamudram"
    ],
    "name:may_x_preferred":[
        "Mallasamudram"
    ],
    "name:nan_x_preferred":[
        "Mallasamudram"
    ],
    "name:new_x_preferred":[
        "\u092e\u0932\u094d\u0932\u0938\u092e\u0941\u0926\u094d\u0930\u092e"
    ],
    "name:por_x_preferred":[
        "Mallasamudram"
    ],
    "name:swe_x_preferred":[
        "Mallasamudram"
    ],
    "name:tam_x_preferred":[
        "\u0bae\u0bb2\u0bcd\u0bb2\u0b9a\u0bae\u0bc1\u0ba4\u0bcd\u0ba4\u0bbf\u0bb0\u0bae\u0bcd"
    ],
    "name:vie_x_preferred":[
        "Mallasamudram"
    ],
    "qs:name":"Mallasamudram",
    "qs:name_adm0":"India",
    "qs:name_adm1":"Tamil Nadu",
    "qs:photos_9r":0,
    "qs:photos_sr":0,
    "qs:placetype":"Town",
    "qs:pop_sr":"6",
    "wd:wordcount":228,
    "wof:name":"Mallasamudram",
    "wof:placetype":"locality",
    "wof:population":18820
},
  "geometry": {"coordinates":[78.03277,11.4892],"type":"Point"}
}