{
  "type": "Feature",
  "properties": {
    "iso:country":"IN",
    "ks:ks_name":"Shalpukur",
    "ks:ks_pop":579,
    "ks:ks_type":"HABITATION",
    "ks:ks_uagg_main":0,
    "name:eng_x_preferred":[
        "Shalpukur"
    ],
    "wof:name":"Shalpukur",
    "wof:placetype":"neighbourhood",
    "wof:population":579
},
  "geometry": {"coordinates":[91.28612,23.384636],"type":"Point"}
}