{
  "type": "Feature",
  "properties": {
    "gn:admin1_code":"16",
    "gn:admin2_code":"521.0",
    "gn:asciiname":"Ranjangaon Ganpati",
    "gn:country_code":"IN",
    "gn:dem":626,
    "gn:feature_class":"P",
    "gn:feature_code":"PPL",
    "gn:name":"Ranjangaon Ganpati",
    "gn:population":0,
    "gn:timezone":"Asia/Kolkata",
    "iso:country":"IN",
    "name:tam_x_preferred":[
        "\u0bb0\u0b9e\u0bcd\u0b9a\u0ba9\u0bcd\u0b95\u0bcb\u0ba3\u0bcd \u0b95\u0ba3\u0baa\u0ba4\u0bbf"
    ],
    "name:und_x_variant":[
        "Ranjangaon Ganpat",
        "Ranjangaon Ganpati"
    ],
    "wof:name":"Ranjangaon Ganpati",
    "wof:placetype":"locality"
},
  "geometry": {"coordinates":[74.2443,18.75365],"type":"Point"}
}