{
  "type": "Feature",
  "properties": {
    "iso:country":"IN",
    "ks:ks_name":"Dumaria",
    "ks:ks_pop":344,
    "ks:ks_type":"VILLAGE",
    "name:eng_x_preferred":[
        "Dumaria"
    ],
    "wof:name":"Dumaria",
    "wof:placetype":"locality",
    "wof:population":344
},
  "geometry": {"coordinates":[87.000472,24.37064],"type":"Point"}
}