{
  "type": "Feature",
  "properties": {
    "iso:country":"IN",
    "ks:ks_alt_nam":"MAJHAPARA",
    "ks:ks_name":"Majhapara",
    "ks:ks_pop":907,
    "ks:ks_type":"HABITATION",
    "name:eng_x_preferred":[
        "Majhapara"
    ],
    "wof:name":"Majhapara",
    "wof:placetype":"locality",
    "wof:population":907
},
  "geometry": {"coordinates":[83.414714,23.048768],"type":"Point"}
}