{
  "type": "Feature",
  "properties": {
    "gn:admin1_code":"36",
    "gn:admin2_code":"170.0",
    "gn:asciiname":"Jamalpur",
    "gn:country_code":"IN",
    "gn:dem":131,
    "gn:feature_class":"P",
    "gn:feature_code":"PPL",
    "gn:name":"Jam\u0101lpur",
    "gn:population":0,
    "gn:timezone":"Asia/Kolkata",
    "iso:country":"IN",
    "name:ara_x_preferred":[
        "\u062c\u0645\u0627\u0644\u0628\u0648\u0631"
    ],
    "name:ben_x_preferred":[
        "\u099c\u09be\u09ae\u09be\u09b2\u09aa\u09c1\u09b0"
    ],
    "name:bih_x_preferred":[
        "\u091c\u092e\u093e\u0932\u092a\u0941\u0930"
    ],
    "name:bpy_x_preferred":[
        "\u099c\u09be\u09ae\u09be\u09b2\u09aa\u09c1\u09b0"
    ],
    "name:ceb_x_preferred":[
        "Jamalpur"
    ],
    "name:deu_x_preferred":[
        "Jamalpur"
    ],
    "name:fra_x_preferred":[
        "Jamalpur"
    ],
    "name:heb_x_preferred":[
        "\u05d2'\u05de\u05dc\u05e4\u05d5\u05e8"
    ],
    "name:hun_x_preferred":[
        "Jamalpur"
    ],
    "name:ind_x_preferred":[
        "Jamalpur"
    ],
    "name:kor_x_preferred":[
        "\uc790\ub9d0\ud478\ub974"
    ],
    "name:lit_x_preferred":[
        "D\u017eamalpuras"
    ],
    "name:new_x_preferred":[
        "\u091c\u092e\u0932\u092a\u0941\u0930"
    ],
    "name:nld_x_preferred":[
        "Jamalpur"
    ],
    "name:pol_x_preferred":[
        "Jamalpur"
    ],
    "name:por_x_preferred":[
        "Jamalpur"
    ],
    "name:swe_x_preferred":[
        "Jamalpur"
    ],
    "name:tur_x_preferred":[
        "Jamalpur"
    ],
    "name:ukr_x_preferred":[
        "\u0414\u0436\u0430\u043c\u0430\u043b\u043f\u0443\u0440"
    ],
    "wof:name":"Jamalpur",
    "wof:placetype":"locality"
},
  "geometry": {"coordinates":[80.38111000000001,25.55025],"type":"Point"}
}