{
  "type": "Feature",
  "properties": {
    "gn:admin1_code":"36",
    "gn:admin2_code":"198.0",
    "gn:asciiname":"Chak Serwa",
    "gn:country_code":"IN",
    "gn:dem":90,
    "gn:feature_class":"P",
    "gn:feature_code":"PPL",
    "gn:name":"Chak Serwa",
    "gn:population":0,
    "gn:timezone":"Asia/Kolkata",
    "iso:country":"IN",
    "ks:ks_name":"Chak Serwan",
    "ks:ks_pop":223,
    "ks:ks_type":"VILLAGE",
    "name:eng_x_preferred":[
        "Chak Serwan"
    ],
    "name:eng_x_variant":[
        "Chak Serwa"
    ],
    "wof:name":"Chak Serwan",
    "wof:placetype":"locality",
    "wof:population":223
},
  "geometry": {"coordinates":[82.58816299999999,25.436921],"type":"Point"}
}