{
  "type": "Feature",
  "properties": {
    "gn:admin1_code":"21",
    "gn:admin2_code":"390.0",
    "gn:asciiname":"Neddiguda",
    "gn:country_code":"IN",
    "gn:dem":166,
    "gn:feature_class":"P",
    "gn:feature_code":"PPL",
    "gn:name":"Neddiguda",
    "gn:population":0,
    "gn:timezone":"Asia/Kolkata",
    "iso:country":"IN",
    "ks:ks_name":"Nediguda",
    "ks:ks_pop":228,
    "ks:ks_type":"VILLAGE",
    "name:eng_x_preferred":[
        "Nediguda"
    ],
    "name:eng_x_variant":[
        "Neddiguda"
    ],
    "name:und_x_variant":[
        "Neddigurha"
    ],
    "wof:name":"Nediguda",
    "wof:placetype":"locality",
    "wof:population":228
},
  "geometry": {"coordinates":[84.581075,20.193253],"type":"Point"}
}