{
  "type": "Feature",
  "properties": {
    "gn:admin1_code":"21",
    "gn:admin2_code":"390.0",
    "gn:asciiname":"Neddiguda",
    "gn:country_code":"IN",
    "gn:dem":166,
    "gn:feature_class":"P",
    "gn:feature_code":"PPL",
    "gn:name":"Neddiguda",
    "gn:population":0,
    "gn:timezone":"Asia/Kolkata",
    "iso:country":"IN",
    "name:und_x_variant":[
        "Neddigurha"
    ],
    "wof:name":"Neddiguda",
    "wof:placetype":"locality"
},
  "geometry": {"coordinates":[84.56815999999998,20.19077],"type":"Point"}
}