{
  "type": "Feature",
  "properties": {
    "iso:country":"IN",
    "ks:ks_name":"Goapalapuram",
    "ks:ks_pop":31,
    "ks:ks_type":"HABITATION",
    "name:eng_x_preferred":[
        "Goapalapuram"
    ],
    "wof:name":"Goapalapuram",
    "wof:placetype":"locality",
    "wof:population":31
},
  "geometry": {"coordinates":[82.646688,18.11522],"type":"Point"}
}