{
  "type": "Feature",
  "properties": {
    "gn:admin1_code":"34",
    "gn:admin2_code":"232.0",
    "gn:asciiname":"Silkantpur",
    "gn:country_code":"IN",
    "gn:dem":76,
    "gn:feature_class":"P",
    "gn:feature_code":"PPL",
    "gn:name":"Silkantpur",
    "gn:population":0,
    "gn:timezone":"Asia/Kolkata",
    "iso:country":"IN",
    "ks:ks_name":"Siri Kantpur",
    "ks:ks_pop":511,
    "ks:ks_type":"VILLAGE",
    "ks:ks_uagg_main":0,
    "name:eng_x_preferred":[
        "Siri Kantpur"
    ],
    "wof:name":"Siri Kantpur",
    "wof:placetype":"neighbourhood",
    "wof:population":511
},
  "geometry": {"coordinates":[83.898358,25.31905],"type":"Point"}
}