{
  "type": "Feature",
  "properties": {
    "gn:admin1_code":"36.0",
    "gn:admin2_code":"151.0",
    "gn:asciiname":"Simaria Tarachand",
    "gn:country_code":"IN",
    "gn:dem":180,
    "gn:feature_class":"P",
    "gn:feature_code":"PPL",
    "gn:name":"Simaria T\u0101r\u0101chand",
    "gn:population":0,
    "gn:timezone":"Asia/Kolkata",
    "iso:country":"IN",
    "name:und_x_variant":[
        "Simaria T\u0101r\u0101chand",
        "Simaria"
    ],
    "wof:name":"Simaria Tarachand",
    "wof:placetype":"locality"
},
  "geometry": {"coordinates":[79.80605,28.50045],"type":"Point"}
}