{
  "type": "Feature",
  "properties": {
    "iso:country":"IN",
    "ks:ks_name":"Nahanga",
    "ks:ks_pop":1512,
    "ks:ks_type":"VILLAGE",
    "ks:ks_uagg_main":0,
    "name:eng_x_preferred":[
        "Nahanga"
    ],
    "wof:name":"Nahanga",
    "wof:placetype":"neighbourhood",
    "wof:population":1512
},
  "geometry": {"coordinates":[86.179179,20.527388],"type":"Point"}
}