{
  "type": "Feature",
  "properties": {
    "gn:admin1_code":"10.0",
    "gn:admin2_code":"85.0",
    "gn:asciiname":"Zainabad",
    "gn:country_code":"IN",
    "gn:dem":260,
    "gn:feature_class":"P",
    "gn:feature_code":"PPL",
    "gn:name":"Zain\u0101b\u0101d",
    "gn:population":0,
    "gn:timezone":"Asia/Kolkata",
    "iso:country":"IN",
    "name:hin_x_preferred":[
        "\u091c\u0948\u0928\u093e\u092c\u093e\u0926"
    ],
    "wof:name":"Zainabad",
    "wof:placetype":"locality"
},
  "geometry": {"coordinates":[76.38231,28.28813],"type":"Point"}
}