{
  "type": "Feature",
  "properties": {
    "iso:country":"IN",
    "ks:ks_name":"Auhawa Khader",
    "ks:ks_pop":0,
    "ks:ks_type":"VILLAGE",
    "name:eng_x_preferred":[
        "Auhawa Khader"
    ],
    "wof:name":"Auhawa Khader",
    "wof:placetype":"locality",
    "wof:population":0
},
  "geometry": {"coordinates":[77.681703,27.75131],"type":"Point"}
}