{
  "type": "Feature",
  "properties": {
    "iso:country":"IN",
    "ks:ks_alt_nam":"TALABI",
    "ks:ks_name":"Talabi",
    "ks:ks_pop":123,
    "ks:ks_type":"HABITATION",
    "name:eng_x_preferred":[
        "Talabi"
    ],
    "wof:name":"Talabi",
    "wof:placetype":"locality",
    "wof:population":123
},
  "geometry": {"coordinates":[75.226353,13.662854],"type":"Point"}
}