{
  "type": "Feature",
  "properties": {
    "gn:admin1_code":"24.0",
    "gn:admin2_code":"107.0",
    "gn:asciiname":"Kemri",
    "gn:country_code":"IN",
    "gn:dem":243,
    "gn:feature_class":"P",
    "gn:feature_code":"PPL",
    "gn:name":"Kemri",
    "gn:population":0,
    "gn:timezone":"Asia/Kolkata",
    "iso:country":"IN",
    "name:bpy_x_preferred":[
        "\u0995\u09c7\u09ae\u09b0\u09bf"
    ],
    "name:ceb_x_preferred":[
        "Kemr\u012b"
    ],
    "name:ita_x_preferred":[
        "Kemri"
    ],
    "name:mlg_x_preferred":[
        "Kemri"
    ],
    "name:msa_x_preferred":[
        "Kemri"
    ],
    "name:new_x_preferred":[
        "\u0915\u0947\u092e\u094d\u0930\u0940"
    ],
    "name:nld_x_preferred":[
        "Kemri"
    ],
    "name:pol_x_preferred":[
        "Kemri"
    ],
    "name:swe_x_preferred":[
        "Kemr\u012b"
    ],
    "name:urd_x_preferred":[
        "\u06a9\u06cc\u0645\u0631\u06cc"
    ],
    "name:vie_x_preferred":[
        "Kemri"
    ],
    "name:zho_x_preferred":[
        "\u51ef\u59c6\u91cc"
    ],
    "wof:name":"Kemri",
    "wof:placetype":"locality"
},
  "geometry": {"coordinates":[76.75384,26.71145],"type":"Point"}
}