{
  "type": "Feature",
  "properties": {
    "iso:country":"IN",
    "ks:ks_alt_nam":"Varchi banachiwadi",
    "ks:ks_name":"Varchi Banachiwadi",
    "ks:ks_pop":225,
    "ks:ks_type":"HABITATION",
    "name:eng_x_preferred":[
        "Varchi Banachiwadi"
    ],
    "wof:name":"Varchi Banachiwadi",
    "wof:placetype":"locality",
    "wof:population":225
},
  "geometry": {"coordinates":[73.438216,17.108283],"type":"Point"}
}