{
  "type": "Feature",
  "properties": {
    "iso:country":"IN",
    "ks:ks_name":"Parwan South Tola",
    "ks:ks_pop":150,
    "ks:ks_type":"HABITATION",
    "name:eng_x_preferred":[
        "Parwan South Tola"
    ],
    "wof:name":"Parwan South Tola",
    "wof:placetype":"locality",
    "wof:population":150
},
  "geometry": {"coordinates":[87.77843799999999,26.165354],"type":"Point"}
}