{
  "type": "Feature",
  "properties": {
    "iso:country":"IN",
    "ks:ks_name":"Katgaon",
    "ks:ks_pop":251,
    "ks:ks_type":"VILLAGE",
    "name:eng_x_preferred":[
        "Katgaon"
    ],
    "wof:name":"Katgaon",
    "wof:placetype":"locality",
    "wof:population":251
},
  "geometry": {"coordinates":[80.845702,19.987555],"type":"Point"}
}