{
  "type": "Feature",
  "properties": {
    "iso:country":"IN",
    "ks:ks_name":"Kalkardi",
    "ks:ks_pop":298,
    "ks:ks_type":"HABITATION",
    "name:eng_x_preferred":[
        "Kalkardi"
    ],
    "wof:name":"Kalkardi",
    "wof:placetype":"locality",
    "wof:population":298
},
  "geometry": {"coordinates":[74.637535,14.53962],"type":"Point"}
}