{
  "type": "Feature",
  "properties": {
    "gn:admin1_code":"25.0",
    "gn:admin2_code":"633.0",
    "gn:asciiname":"Ravanapuram",
    "gn:country_code":"IN",
    "gn:dem":341,
    "gn:feature_class":"P",
    "gn:feature_code":"PPL",
    "gn:name":"R\u0101van\u0101puram",
    "gn:population":0,
    "gn:timezone":"Asia/Kolkata",
    "iso:country":"IN",
    "wof:name":"Ravanapuram",
    "wof:placetype":"locality"
},
  "geometry": {"coordinates":[77.09681999999999,10.53373],"type":"Point"}
}