{
  "type": "Feature",
  "properties": {
    "gn:admin1_code":"11",
    "gn:admin2_code":"27.0",
    "gn:asciiname":"Bherka",
    "gn:country_code":"IN",
    "gn:dem":1314,
    "gn:feature_class":"P",
    "gn:feature_code":"PPL",
    "gn:name":"Bherka",
    "gn:population":0,
    "gn:timezone":"Asia/Kolkata",
    "iso:country":"IN",
    "wof:name":"Bherka",
    "wof:placetype":"locality"
},
  "geometry": {"coordinates":[76.85065999999998,31.66659000000001],"type":"Point"}
}