{
  "type": "Feature",
  "properties": {
    "gn:admin1_code":"21.0",
    "gn:admin2_code":"390.0",
    "gn:asciiname":"Sarukinga",
    "gn:country_code":"IN",
    "gn:dem":593,
    "gn:feature_class":"P",
    "gn:feature_code":"PPL",
    "gn:name":"Sarukinga",
    "gn:population":0,
    "gn:timezone":"Asia/Kolkata",
    "iso:country":"IN",
    "ks:ks_name":"Sarkingia",
    "ks:ks_pop":190,
    "ks:ks_type":"VILLAGE",
    "name:eng_x_preferred":[
        "Sarkingia"
    ],
    "name:eng_x_variant":[
        "Sarukinga"
    ],
    "wof:name":"Sarkingia",
    "wof:placetype":"locality",
    "wof:population":190
},
  "geometry": {"coordinates":[83.84766999999999,19.971827],"type":"Point"}
}