{
  "type": "Feature",
  "properties": {
    "gn:admin1_code":"12.0",
    "gn:admin2_code":"003",
    "gn:asciiname":"Khor",
    "gn:country_code":"IN",
    "gn:dem":3672,
    "gn:feature_class":"P",
    "gn:feature_code":"PPL",
    "gn:name":"Khor",
    "gn:population":0,
    "gn:timezone":"Asia/Kolkata",
    "iso:country":"IN",
    "wof:name":"Khor",
    "wof:placetype":"locality"
},
  "geometry": {"coordinates":[77.04928000000002,34.85426],"type":"Point"}
}