{
  "type": "Feature",
  "properties": {
    "iso:country":"IN",
    "ks:ks_name":"Kurapada",
    "ks:ks_pop":111,
    "ks:ks_type":"HABITATION",
    "name:eng_x_preferred":[
        "Kurapada"
    ],
    "wof:name":"Kurapada",
    "wof:placetype":"locality",
    "wof:population":111
},
  "geometry": {"coordinates":[84.43132300000001,19.098247],"type":"Point"}
}