{
  "type": "Feature",
  "properties": {
    "iso:country":"IN",
    "ks:ks_name":"River Block No 12 N.C",
    "ks:ks_pop":0,
    "ks:ks_type":"VILLAGE",
    "name:eng_x_preferred":[
        "River Block No 12 N.C"
    ],
    "wof:name":"River Block No 12 N.C",
    "wof:placetype":"locality",
    "wof:population":0
},
  "geometry": {"coordinates":[89.95092099999999,25.854663],"type":"Point"}
}