{
  "type": "Feature",
  "properties": {
    "iso:country":"IN",
    "ks:ks_name":"Nurpur",
    "ks:ks_pop":994,
    "ks:ks_type":"VILLAGE",
    "ks:ks_uagg_main":0,
    "name:eng_x_preferred":[
        "Nurpur"
    ],
    "wof:name":"Nurpur",
    "wof:placetype":"neighbourhood",
    "wof:population":994
},
  "geometry": {"coordinates":[85.10554500000001,25.226834],"type":"Point"}
}