{
  "type": "Feature",
  "properties": {
    "iso:country":"IN",
    "name:dut_x_preferred":[
        "Auli"
    ],
    "name:eng_x_preferred":[
        "Auli"
    ],
    "name:hin_x_preferred":[
        "\u0914\u0932\u0940"
    ],
    "name:mal_x_preferred":[
        "\u0d13\u0d32\u0d3f"
    ],
    "name:pol_x_preferred":[
        "Auli"
    ],
    "name:urd_x_preferred":[
        "\u0627\u0648\u0644\u06cc"
    ],
    "qs:name":"Auli",
    "qs:name_adm0":"India",
    "qs:name_adm1":"Uttarakhand",
    "qs:photos":481,
    "qs:photos_1k":97,
    "qs:photos_9k":2,
    "qs:photos_9r":5,
    "qs:photos_all":481,
    "qs:photos_sr":7,
    "qs:placetype":"Town",
    "qs:pop_sr":"0",
    "wd:wordcount":2174,
    "wof:name":"Auli",
    "wof:placetype":"locality"
},
  "geometry": {"coordinates":[79.59217,30.468057],"type":"Point"}
}