{
  "type": "Feature",
  "properties": {
    "iso:country":"IN",
    "ks:ks_name":"Varanavasipalayam",
    "ks:ks_pop":180,
    "ks:ks_type":"HABITATION",
    "ks:ks_uagg_main":0,
    "name:eng_x_preferred":[
        "Varanavasipalayam"
    ],
    "wof:name":"Varanavasipalayam",
    "wof:placetype":"neighbourhood",
    "wof:population":180
},
  "geometry": {"coordinates":[77.33983499999999,11.24251],"type":"Point"}
}