{
  "type": "Feature",
  "properties": {
    "gn:admin1_code":"39.0",
    "gn:admin2_code":"64.0",
    "gn:asciiname":"Jholani",
    "gn:country_code":"IN",
    "gn:dem":1440,
    "gn:feature_class":"P",
    "gn:feature_code":"PPL",
    "gn:name":"Jhol\u0101ni",
    "gn:population":0,
    "gn:timezone":"Asia/Kolkata",
    "iso:country":"IN",
    "wof:name":"Jholani",
    "wof:placetype":"locality"
},
  "geometry": {"coordinates":[79.50173000000002,29.77517000000001],"type":"Point"}
}