{
  "type": "Feature",
  "properties": {
    "gn:admin1_code":"19.0",
    "gn:admin2_code":"582.0",
    "gn:asciiname":"Baichareddihalli",
    "gn:country_code":"IN",
    "gn:dem":742,
    "gn:feature_class":"P",
    "gn:feature_code":"PPL",
    "gn:name":"Baichareddihalli",
    "gn:population":0,
    "gn:timezone":"Asia/Kolkata",
    "iso:country":"IN",
    "wof:name":"Baichareddihalli",
    "wof:placetype":"locality"
},
  "geometry": {"coordinates":[77.63136,13.64912],"type":"Point"}
}