{
  "type": "Feature",
  "properties": {
    "iso:country":"IN",
    "ks:ks_alt_nam":"illikkunnu",
    "ks:ks_name":"Illikkunnu",
    "ks:ks_pop":30,
    "ks:ks_type":"HABITATION",
    "name:eng_x_preferred":[
        "Illikkunnu"
    ],
    "wof:name":"Illikkunnu",
    "wof:placetype":"locality",
    "wof:population":30
},
  "geometry": {"coordinates":[76.612435,9.903927],"type":"Point"}
}