{
  "type": "Feature",
  "properties": {
    "gn:admin1_code":"16.0",
    "gn:admin2_code":"503.0",
    "gn:asciiname":"Asegaon",
    "gn:country_code":"IN",
    "gn:dem":287,
    "gn:feature_class":"P",
    "gn:feature_code":"PPL",
    "gn:name":"\u0100segaon",
    "gn:population":0,
    "gn:timezone":"Asia/Kolkata",
    "iso:country":"IN",
    "ks:ks_alt_nam":"\u0100segaon",
    "ks:ks_name":"Asegaon",
    "ks:ks_pop":1161,
    "ks:ks_type":"VILLAGE",
    "name:eng_x_preferred":[
        "Asegaon"
    ],
    "name:eng_x_variant":[
        "\u0100segaon"
    ],
    "wof:name":"Asegaon",
    "wof:placetype":"locality",
    "wof:population":1161
},
  "geometry": {"coordinates":[78.15275,20.730746],"type":"Point"}
}