{
  "type": "Feature",
  "properties": {
    "gn:admin1_code":"2",
    "gn:admin2_code":"544.0",
    "gn:asciiname":"Koduru",
    "gn:country_code":"IN",
    "gn:dem":90,
    "gn:feature_class":"P",
    "gn:feature_code":"PPL",
    "gn:name":"Kod\u016bru",
    "gn:population":0,
    "gn:timezone":"Asia/Kolkata",
    "iso:country":"IN",
    "name:tel_x_preferred":[
        "\u0c15\u0c4b\u0c21\u0c42\u0c30\u0c41"
    ],
    "name:vie_x_preferred":[
        "Koduru"
    ],
    "wof:name":"Koduru",
    "wof:placetype":"neighbourhood"
},
  "geometry": {"coordinates":[82.78972,17.90976],"type":"Point"}
}