{
  "type": "Feature",
  "properties": {
    "gn:admin1_code":"36",
    "gn:admin2_code":"142.0",
    "gn:asciiname":"Rasulpur Telia",
    "gn:country_code":"IN",
    "gn:dem":201,
    "gn:feature_class":"P",
    "gn:feature_code":"PPL",
    "gn:name":"Ras\u016blp\u016br Teli\u0101",
    "gn:population":0,
    "gn:timezone":"Asia/Kolkata",
    "iso:country":"IN",
    "ks:ks_alt_nam":"Ras\u016blp\u016br Teli\u0101",
    "ks:ks_name":"Rasulpur Telia",
    "ks:ks_type":"VILLAGE",
    "name:eng_x_preferred":[
        "Rasulpur Telia"
    ],
    "name:eng_x_variant":[
        "Ras\u016blp\u016br Teli\u0101"
    ],
    "name:und_x_variant":[
        "Ras\u016blp\u016br Teli\u0101",
        "Matthna"
    ],
    "wof:name":"Rasulpur Telia",
    "wof:placetype":"locality"
},
  "geometry": {"coordinates":[78.01938,28.365537],"type":"Point"}
}