{
  "type": "Feature",
  "properties": {
    "iso:country":"IN",
    "ks:ks_name":"Rome Nagar Colony",
    "ks:ks_pop":110,
    "ks:ks_type":"HABITATION",
    "name:eng_x_preferred":[
        "Rome Nagar Colony"
    ],
    "wof:name":"Rome Nagar Colony",
    "wof:placetype":"locality",
    "wof:population":110
},
  "geometry": {"coordinates":[79.75479199999999,12.501156],"type":"Point"}
}