{
  "type": "Feature",
  "properties": {
    "iso:country":"IN",
    "ks:ks_name":"Nagapali",
    "ks:ks_pop":130,
    "ks:ks_type":"VILLAGE",
    "name:eng_x_preferred":[
        "Nagapali"
    ],
    "wof:name":"Nagapali",
    "wof:placetype":"locality",
    "wof:population":130
},
  "geometry": {"coordinates":[83.788923,20.931707],"type":"Point"}
}