{
  "type": "Feature",
  "properties": {
    "iso:country":"IN",
    "ks:ks_alt_nam":"Chokdi falya",
    "ks:ks_name":"Chokdi Falya",
    "ks:ks_pop":182,
    "ks:ks_type":"HABITATION",
    "ks:ks_uagg_main":0,
    "name:eng_x_preferred":[
        "Chokdi Falya"
    ],
    "wof:name":"Chokdi Falya",
    "wof:placetype":"neighbourhood",
    "wof:population":182
},
  "geometry": {"coordinates":[73.128111,20.468556],"type":"Point"}
}