{
  "type": "Feature",
  "properties": {
    "iso:country":"IN",
    "ks:ks_name":"Ajgardand",
    "ks:ks_pop":96,
    "ks:ks_type":"HABITATION",
    "name:eng_x_preferred":[
        "Ajgardand"
    ],
    "wof:name":"Ajgardand",
    "wof:placetype":"locality",
    "wof:population":96
},
  "geometry": {"coordinates":[82.21373,22.739033],"type":"Point"}
}