{
  "type": "Feature",
  "properties": {
    "iso:country":"IN",
    "ks:ks_name":"Rasulpur Mishra",
    "ks:ks_pop":11,
    "ks:ks_type":"HABITATION",
    "name:eng_x_preferred":[
        "Rasulpur Mishra"
    ],
    "wof:name":"Rasulpur Mishra",
    "wof:placetype":"locality",
    "wof:population":11
},
  "geometry": {"coordinates":[83.163231,26.397166],"type":"Point"}
}