{
  "type": "Feature",
  "properties": {
    "gn:admin1_code":"38.0",
    "gn:admin2_code":"358.0",
    "gn:asciiname":"Dipaua",
    "gn:country_code":"IN",
    "gn:dem":293,
    "gn:feature_class":"P",
    "gn:feature_code":"PPL",
    "gn:name":"Dipau\u0101",
    "gn:population":0,
    "gn:timezone":"Asia/Kolkata",
    "iso:country":"IN",
    "ks:ks_alt_nam":"Dipau\u0101",
    "ks:ks_name":"Dipaua",
    "ks:ks_pop":848,
    "ks:ks_type":"VILLAGE",
    "ks:ks_uagg_main":0,
    "name:eng_x_preferred":[
        "Dipaua"
    ],
    "name:eng_x_variant":[
        "Dipau\u0101"
    ],
    "wof:name":"Dipaua",
    "wof:placetype":"neighbourhood",
    "wof:population":848
},
  "geometry": {"coordinates":[84.277917,24.206472],"type":"Point"}
}