{
  "type": "Feature",
  "properties": {
    "iso:country":"IN",
    "ks:ks_name":"Bovalekarwadi",
    "ks:ks_pop":52,
    "ks:ks_type":"HABITATION",
    "name:eng_x_preferred":[
        "Bovalekarwadi"
    ],
    "wof:name":"Bovalekarwadi",
    "wof:placetype":"locality",
    "wof:population":52
},
  "geometry": {"coordinates":[73.595359,15.911346],"type":"Point"}
}