{
  "type": "Feature",
  "properties": {
    "iso:country":"IN",
    "ks:ks_name":"Khempuriya",
    "ks:ks_pop":297,
    "ks:ks_type":"VILLAGE",
    "name:eng_x_preferred":[
        "Khempuriya"
    ],
    "wof:name":"Khempuriya",
    "wof:placetype":"locality",
    "wof:population":297
},
  "geometry": {"coordinates":[74.669648,23.970271],"type":"Point"}
}