{
  "type": "Feature",
  "properties": {
    "gn:admin1_code":"39",
    "gn:admin2_code":"61.0",
    "gn:asciiname":"Kuirali",
    "gn:country_code":"IN",
    "gn:dem":1134,
    "gn:feature_class":"P",
    "gn:feature_code":"PPL",
    "gn:name":"Ku\u012br\u0101li",
    "gn:population":0,
    "gn:timezone":"Asia/Kolkata",
    "iso:country":"IN",
    "ks:ks_alt_nam":"Ku\u012br\u0101li",
    "ks:ks_name":"Kuirali",
    "ks:ks_type":"VILLAGE",
    "name:eng_x_preferred":[
        "Kuirali"
    ],
    "name:eng_x_variant":[
        "Ku\u012br\u0101li"
    ],
    "wof:name":"Kuirali",
    "wof:placetype":"locality"
},
  "geometry": {"coordinates":[78.828836,29.701161],"type":"Point"}
}