{
  "type": "Feature",
  "properties": {
    "gn:admin1_code":"36.0",
    "gn:admin2_code":"170.0",
    "gn:asciiname":"Buba",
    "gn:country_code":"IN",
    "gn:dem":113,
    "gn:feature_class":"P",
    "gn:feature_code":"PPL",
    "gn:name":"B\u016bba",
    "gn:population":0,
    "gn:timezone":"Asia/Kolkata",
    "iso:country":"IN",
    "name:cat_x_preferred":[
        "Buba"
    ],
    "name:ceb_x_preferred":[
        "Buba"
    ],
    "name:deu_x_preferred":[
        "Buba"
    ],
    "name:epo_x_preferred":[
        "Buba"
    ],
    "name:fin_x_preferred":[
        "Buba"
    ],
    "name:frr_x_preferred":[
        "Buba"
    ],
    "name:ita_x_preferred":[
        "Buba"
    ],
    "name:kor_x_preferred":[
        "\ubd80\ubc14"
    ],
    "name:lit_x_preferred":[
        "Buba"
    ],
    "name:nld_x_preferred":[
        "Buba"
    ],
    "name:pol_x_preferred":[
        "Buba"
    ],
    "name:por_x_preferred":[
        "Buba"
    ],
    "name:ron_x_preferred":[
        "Buba"
    ],
    "name:swe_x_preferred":[
        "Buba"
    ],
    "wof:name":"Buba",
    "wof:placetype":"locality"
},
  "geometry": {"coordinates":[80.86162,25.59785],"type":"Point"}
}