{
  "type": "Feature",
  "properties": {
    "gn:admin1_code":"11.0",
    "gn:admin2_code":"33.0",
    "gn:asciiname":"Lanu",
    "gn:country_code":"IN",
    "gn:dem":1941,
    "gn:feature_class":"P",
    "gn:feature_code":"PPL",
    "gn:name":"Lanu",
    "gn:population":0,
    "gn:timezone":"Asia/Kolkata",
    "iso:country":"IN",
    "wof:name":"Lanu",
    "wof:placetype":"locality"
},
  "geometry": {"coordinates":[77.33578,31.16659000000001],"type":"Point"}
}