{
  "type": "Feature",
  "properties": {
    "iso:country":"IN",
    "ks:ks_name":"Konge",
    "ks:ks_pop":255,
    "ks:ks_type":"HABITATION",
    "name:eng_x_preferred":[
        "Konge"
    ],
    "wof:name":"Konge",
    "wof:placetype":"locality",
    "wof:population":255
},
  "geometry": {"coordinates":[81.038241,19.424577],"type":"Point"}
}