{
  "type": "Feature",
  "properties": {
    "gn:admin1_code":"36",
    "gn:admin2_code":"181.0",
    "gn:asciiname":"Langrigular Chaukanian",
    "gn:country_code":"IN",
    "gn:dem":124,
    "gn:feature_class":"P",
    "gn:feature_code":"PPL",
    "gn:name":"Langrigular Chaukani\u0101n",
    "gn:population":0,
    "gn:timezone":"Asia/Kolkata",
    "iso:country":"IN",
    "wof:name":"Langrigular Chaukanian",
    "wof:placetype":"neighbourhood"
},
  "geometry": {"coordinates":[81.76482,27.59966],"type":"Point"}
}