{
  "type": "Feature",
  "properties": {
    "iso:country":"IN",
    "ks:ks_name":"Shivraj",
    "ks:ks_pop":579,
    "ks:ks_type":"VILLAGE",
    "name:eng_x_preferred":[
        "Shivraj"
    ],
    "wof:name":"Shivraj",
    "wof:placetype":"locality",
    "wof:population":579
},
  "geometry": {"coordinates":[77.92500200000001,25.198487],"type":"Point"}
}