{
  "type": "Feature",
  "properties": {
    "iso:country":"IN",
    "ks:ks_name":"Kalankudieruppu",
    "ks:ks_pop":100,
    "ks:ks_type":"HABITATION",
    "name:eng_x_preferred":[
        "Kalankudieruppu"
    ],
    "wof:name":"Kalankudieruppu",
    "wof:placetype":"locality",
    "wof:population":100
},
  "geometry": {"coordinates":[77.927649,8.436838],"type":"Point"}
}