{
  "type": "Feature",
  "properties": {
    "gn:admin1_code":"12.0",
    "gn:admin2_code":"008",
    "gn:asciiname":"Dusilporichrakh",
    "gn:country_code":"IN",
    "gn:dem":1583,
    "gn:feature_class":"P",
    "gn:feature_code":"PPL",
    "gn:name":"Dusilporichrakh",
    "gn:population":0,
    "gn:timezone":"Asia/Kolkata",
    "iso:country":"IN",
    "name:und_x_variant":[
        "Dusilparichrakh"
    ],
    "wof:name":"Dusilporichrakh",
    "wof:placetype":"locality"
},
  "geometry": {"coordinates":[74.61407,34.16921],"type":"Point"}
}