{
  "type": "Feature",
  "properties": {
    "iso:country":"IN",
    "ks:ks_name":"Basaveswara Temple",
    "ks:ks_pop":86,
    "ks:ks_type":"HABITATION",
    "name:eng_x_preferred":[
        "Basaveswara Temple"
    ],
    "wof:name":"Basaveswara Temple",
    "wof:placetype":"locality",
    "wof:population":86
},
  "geometry": {"coordinates":[76.300065,13.429088],"type":"Point"}
}