{
  "type": "Feature",
  "properties": {
    "iso:country":"IN",
    "ks:ks_name":"Baritoli",
    "ks:ks_pop":176,
    "ks:ks_type":"HABITATION",
    "name:eng_x_preferred":[
        "Baritoli"
    ],
    "wof:name":"Baritoli",
    "wof:placetype":"locality",
    "wof:population":176
},
  "geometry": {"coordinates":[85.39905299999999,23.473527],"type":"Point"}
}