{
  "type": "Feature",
  "properties": {
    "iso:country":"IN",
    "ks:ks_name":"Veshiwadi",
    "ks:ks_pop":64,
    "ks:ks_type":"HABITATION",
    "name:eng_x_preferred":[
        "Veshiwadi"
    ],
    "wof:name":"Veshiwadi",
    "wof:placetype":"locality",
    "wof:population":64
},
  "geometry": {"coordinates":[73.75873199999999,15.967496],"type":"Point"}
}