{
  "type": "Feature",
  "properties": {
    "gn:admin1_code":"16.0",
    "gn:admin2_code":"508.0",
    "gn:asciiname":"Kusansur",
    "gn:country_code":"IN",
    "gn:dem":201,
    "gn:feature_class":"P",
    "gn:feature_code":"PPL",
    "gn:name":"Kusansur",
    "gn:population":0,
    "gn:timezone":"Asia/Kolkata",
    "iso:country":"IN",
    "ks:ks_name":"Kasansur",
    "ks:ks_pop":188,
    "ks:ks_type":"VILLAGE",
    "name:eng_x_preferred":[
        "Kasansur"
    ],
    "name:eng_x_variant":[
        "Kusansur"
    ],
    "wof:name":"Kasansur",
    "wof:placetype":"locality",
    "wof:population":188
},
  "geometry": {"coordinates":[80.49860099999999,19.363278],"type":"Point"}
}