{
  "type": "Feature",
  "properties": {
    "gn:admin1_code":"34.0",
    "gn:admin2_code":"229.0",
    "gn:asciiname":"Beldar Bigha",
    "gn:country_code":"IN",
    "gn:dem":75,
    "gn:feature_class":"P",
    "gn:feature_code":"PPL",
    "gn:name":"Beld\u0101r Bigha",
    "gn:population":0,
    "gn:timezone":"Asia/Kolkata",
    "iso:country":"IN",
    "wof:name":"Beldar Bigha",
    "wof:placetype":"locality"
},
  "geometry": {"coordinates":[85.27471,25.03819],"type":"Point"}
}