{
  "type": "Feature",
  "properties": {
    "iso:country":"IN",
    "ks:ks_name":"Maiki Ka Purwa",
    "ks:ks_pop":89,
    "ks:ks_type":"HABITATION",
    "name:eng_x_preferred":[
        "Maiki Ka Purwa"
    ],
    "wof:name":"Maiki Ka Purwa",
    "wof:placetype":"locality",
    "wof:population":89
},
  "geometry": {"coordinates":[80.49311899999999,25.299682],"type":"Point"}
}