{
  "type": "Feature",
  "properties": {
    "iso:country":"IN",
    "ks:ks_name":"Kontaria",
    "ks:ks_pop":232,
    "ks:ks_type":"VILLAGE",
    "name:eng_x_preferred":[
        "Kontaria"
    ],
    "wof:name":"Kontaria",
    "wof:placetype":"locality",
    "wof:population":232
},
  "geometry": {"coordinates":[85.44258600000001,22.201906],"type":"Point"}
}