{
  "type": "Feature",
  "properties": {
    "iso:country":"IN",
    "ks:ks_name":"Unchakheda",
    "ks:ks_pop":100,
    "ks:ks_type":"VILLAGE",
    "name:eng_x_preferred":[
        "Unchakheda"
    ],
    "wof:name":"Unchakheda",
    "wof:placetype":"locality",
    "wof:population":100
},
  "geometry": {"coordinates":[78.816429,22.626747],"type":"Point"}
}