{
  "type": "Feature",
  "properties": {
    "gn:admin1_code":"23",
    "gn:admin2_code":"37.0",
    "gn:asciiname":"Ghulamgarh",
    "gn:country_code":"IN",
    "gn:dem":241,
    "gn:feature_class":"P",
    "gn:feature_code":"PPL",
    "gn:name":"Ghul\u0101mgarh",
    "gn:population":0,
    "gn:timezone":"Asia/Kolkata",
    "iso:country":"IN",
    "ks:ks_alt_nam":"Ghul\u0101mgarh",
    "ks:ks_name":"Ghulamgarh",
    "ks:ks_pop":90,
    "ks:ks_type":"VILLAGE",
    "name:eng_x_preferred":[
        "Ghulamgarh"
    ],
    "name:eng_x_variant":[
        "Ghul\u0101mgarh"
    ],
    "wof:name":"Ghulamgarh",
    "wof:placetype":"locality",
    "wof:population":90
},
  "geometry": {"coordinates":[75.812291,31.02404],"type":"Point"}
}