{
  "type": "Feature",
  "properties": {
    "iso:country":"IN",
    "ks:ks_name":"Khurmabad",
    "ks:ks_pop":62,
    "ks:ks_type":"HABITATION",
    "name:eng_x_preferred":[
        "Khurmabad"
    ],
    "wof:name":"Khurmabad",
    "wof:placetype":"locality",
    "wof:population":62
},
  "geometry": {"coordinates":[77.37969,24.325277],"type":"Point"}
}