{
  "type": "Feature",
  "properties": {
    "iso:country":"IN",
    "ks:ks_alt_nam":"Peddivaripalem of clpalemGP",
    "ks:ks_name":"Peddivaripalem Of Clpalemgp",
    "ks:ks_pop":639,
    "ks:ks_type":"HABITATION",
    "ks:ks_uagg_main":0,
    "name:eng_x_preferred":[
        "Peddivaripalem Of Clpalemgp"
    ],
    "wof:name":"Peddivaripalem Of Clpalemgp",
    "wof:placetype":"neighbourhood",
    "wof:population":639
},
  "geometry": {"coordinates":[80.449004,16.115637],"type":"Point"}
}