{
  "type": "Feature",
  "properties": {
    "gn:admin1_code":"34.0",
    "gn:admin2_code":"213.0",
    "gn:asciiname":"Bhirkhi Uttarwari",
    "gn:country_code":"IN",
    "gn:dem":49,
    "gn:feature_class":"P",
    "gn:feature_code":"PPL",
    "gn:name":"Bhirkhi Uttarw\u0101ri",
    "gn:population":0,
    "gn:timezone":"Asia/Kolkata",
    "iso:country":"IN",
    "wof:name":"Bhirkhi Uttarwari",
    "wof:placetype":"locality"
},
  "geometry": {"coordinates":[86.78763000000002,25.91396],"type":"Point"}
}