{
  "type": "Feature",
  "properties": {
    "gn:admin1_code":"34.0",
    "gn:admin2_code":"218.0",
    "gn:asciiname":"Bhagwanpur Hat",
    "gn:country_code":"IN",
    "gn:dem":65,
    "gn:feature_class":"P",
    "gn:feature_code":"PPL",
    "gn:name":"Bhagw\u0101npur H\u0101t",
    "gn:population":0,
    "gn:timezone":"Asia/Kolkata",
    "iso:country":"IN",
    "ks:ks_alt_nam":"Bhagw\u0101npur H\u0101t",
    "ks:ks_name":"Bhagwanpur Hat",
    "ks:ks_pop":3769,
    "ks:ks_type":"VILLAGE",
    "ks:ks_uagg_main":0,
    "name:bih_x_preferred":[
        "\u092d\u0917\u0935\u093e\u0928\u092a\u0941\u0930 \u0939\u093e\u091f"
    ],
    "name:eng_x_preferred":[
        "Bhagwanpur Hat"
    ],
    "name:eng_x_variant":[
        "Bhagw\u0101npur H\u0101t"
    ],
    "name:hin_x_preferred":[
        "\u092d\u0917\u0935\u093e\u0928\u092a\u0941\u0930 \u0939\u093e\u091f"
    ],
    "wof:name":"Bhagwanpur Hat",
    "wof:placetype":"neighbourhood",
    "wof:population":3769
},
  "geometry": {"coordinates":[84.683134,26.097876],"type":"Point"}
}