{
  "type": "Feature",
  "properties": {
    "iso:country":"IN",
    "ks:ks_name":"Gorrelametta",
    "ks:ks_pop":100,
    "ks:ks_type":"HABITATION",
    "name:eng_x_preferred":[
        "Gorrelametta"
    ],
    "wof:name":"Gorrelametta",
    "wof:placetype":"locality",
    "wof:population":100
},
  "geometry": {"coordinates":[82.463061,18.324139],"type":"Point"}
}