{
  "type": "Feature",
  "properties": {
    "iso:country":"IN",
    "ks:ks_alt_nam":"CHANDOLI VASAHAT  KALAMA WADI VASAHAT",
    "ks:ks_name":"Chandoli Vasahat Kalama Wadi Vasahat",
    "ks:ks_pop":175,
    "ks:ks_type":"HABITATION",
    "ks:ks_uagg_main":0,
    "name:eng_x_preferred":[
        "Chandoli Vasahat Kalama Wadi Vasahat"
    ],
    "name:eng_x_variant":[
        "CHANDOLI VASAHAT  KALAMA WADI VASAHAT"
    ],
    "wof:name":"Chandoli Vasahat Kalama Wadi Vasahat",
    "wof:placetype":"neighbourhood",
    "wof:population":175
},
  "geometry": {"coordinates":[74.513311,16.796639],"type":"Point"}
}