{
  "type": "Feature",
  "properties": {
    "gn:admin1_code":"9.0",
    "gn:admin2_code":"471",
    "gn:asciiname":"Kahipur",
    "gn:country_code":"IN",
    "gn:dem":151,
    "gn:feature_class":"P",
    "gn:feature_code":"PPL",
    "gn:name":"Kah\u012bpur",
    "gn:population":0,
    "gn:timezone":"Asia/Kolkata",
    "iso:country":"IN",
    "name:und_x_variant":[
        "Kah\u012bpur",
        "Kaipur"
    ],
    "wof:name":"Kahipur",
    "wof:placetype":"locality"
},
  "geometry": {"coordinates":[72.66502,23.74518],"type":"Point"}
}