{
  "type": "Feature",
  "properties": {
    "iso:country":"IN",
    "ks:ks_alt_nam":"Odalguri pt 2",
    "ks:ks_name":"Odalguri Pt 2",
    "ks:ks_pop":555,
    "ks:ks_type":"HABITATION",
    "name:eng_x_preferred":[
        "Odalguri Pt 2"
    ],
    "wof:name":"Odalguri Pt 2",
    "wof:placetype":"locality",
    "wof:population":555
},
  "geometry": {"coordinates":[90.578001,26.534086],"type":"Point"}
}