{
  "type": "Feature",
  "properties": {
    "iso:country":"IN",
    "ks:ks_alt_nam":"PAWANPUR",
    "ks:ks_name":"Pawanpur",
    "ks:ks_pop":700,
    "ks:ks_type":"HABITATION",
    "name:eng_x_preferred":[
        "Pawanpur"
    ],
    "wof:name":"Pawanpur",
    "wof:placetype":"locality",
    "wof:population":700
},
  "geometry": {"coordinates":[84.210932,25.432075],"type":"Point"}
}