{
  "type": "Feature",
  "properties": {
    "iso:country":"IN",
    "ks:ks_alt_nam":"MP Raju Kandriga",
    "ks:ks_name":"Mp Raju Kandriga",
    "ks:ks_pop":34,
    "ks:ks_type":"HABITATION",
    "ks:ks_uagg_main":0,
    "name:eng_x_preferred":[
        "Mp Raju Kandriga"
    ],
    "wof:name":"Mp Raju Kandriga",
    "wof:placetype":"neighbourhood",
    "wof:population":34
},
  "geometry": {"coordinates":[79.682856,13.384922],"type":"Point"}
}