{
  "type": "Feature",
  "properties": {
    "iso:country":"IN",
    "ks:ks_name":"Andichiendal",
    "ks:ks_pop":80,
    "ks:ks_type":"VILLAGE",
    "name:eng_x_preferred":[
        "Andichiendal"
    ],
    "wof:name":"Andichiendal",
    "wof:placetype":"locality",
    "wof:population":80
},
  "geometry": {"coordinates":[78.891265,9.553313],"type":"Point"}
}