{
  "type": "Feature",
  "properties": {
    "iso:country":"IN",
    "ks:ks_name":"Bhabhuon Ki Beri",
    "ks:ks_pop":415,
    "ks:ks_type":"HABITATION",
    "name:eng_x_preferred":[
        "Bhabhuon Ki Beri"
    ],
    "wof:name":"Bhabhuon Ki Beri",
    "wof:placetype":"locality",
    "wof:population":415
},
  "geometry": {"coordinates":[71.736814,25.440419],"type":"Point"}
}