{
  "type": "Feature",
  "properties": {
    "gn:admin1_code":"21.0",
    "gn:admin2_code":"370",
    "gn:asciiname":"Bheran",
    "gn:country_code":"IN",
    "gn:dem":147,
    "gn:feature_class":"P",
    "gn:feature_code":"PPL",
    "gn:name":"Bheran",
    "gn:population":0,
    "gn:timezone":"Asia/Kolkata",
    "iso:country":"IN",
    "wof:name":"Bheran",
    "wof:placetype":"neighbourhood"
},
  "geometry": {"coordinates":[83.75275000000001,21.19982],"type":"Point"}
}