{
  "type": "Feature",
  "properties": {
    "iso:country":"IN",
    "ks:ks_name":"Muntamamididoddi",
    "ks:ks_pop":45,
    "ks:ks_type":"HABITATION",
    "name:eng_x_preferred":[
        "Muntamamididoddi"
    ],
    "wof:name":"Muntamamididoddi",
    "wof:placetype":"locality",
    "wof:population":45
},
  "geometry": {"coordinates":[82.346265,17.501989],"type":"Point"}
}