{
  "type": "Feature",
  "properties": {
    "iso:country":"IN",
    "ks:ks_alt_nam":"Pavannur motta",
    "ks:ks_name":"Pavannur Motta",
    "ks:ks_pop":5012,
    "ks:ks_type":"HABITATION",
    "name:eng_x_preferred":[
        "Pavannur Motta"
    ],
    "wof:name":"Pavannur Motta",
    "wof:placetype":"locality",
    "wof:population":5012
},
  "geometry": {"coordinates":[75.480802,11.989438],"type":"Point"}
}