{
  "type": "Feature",
  "properties": {
    "iso:country":"IN",
    "ks:ks_alt_nam":"Sangam and Weavers colony",
    "ks:ks_name":"Sangam And Weavers Colony",
    "ks:ks_pop":364,
    "ks:ks_type":"HABITATION",
    "name:eng_x_preferred":[
        "Sangam And Weavers Colony"
    ],
    "wof:name":"Sangam And Weavers Colony",
    "wof:placetype":"locality",
    "wof:population":364
},
  "geometry": {"coordinates":[81.85395200000001,16.415318],"type":"Point"}
}