{
  "type": "Feature",
  "properties": {
    "iso:country":"IN",
    "ks:ks_name":"Charmakarwadi",
    "ks:ks_pop":40,
    "ks:ks_type":"HABITATION",
    "name:eng_x_preferred":[
        "Charmakarwadi"
    ],
    "wof:name":"Charmakarwadi",
    "wof:placetype":"locality",
    "wof:population":40
},
  "geometry": {"coordinates":[73.718673,15.737277],"type":"Point"}
}