{
  "type": "Feature",
  "properties": {
    "iso:country":"IN",
    "ks:ks_name":"Bhalugura",
    "ks:ks_pop":39,
    "ks:ks_type":"VILLAGE",
    "name:eng_x_preferred":[
        "Bhalugura"
    ],
    "wof:name":"Bhalugura",
    "wof:placetype":"locality",
    "wof:population":39
},
  "geometry": {"coordinates":[82.744749,18.514215],"type":"Point"}
}