{
  "type": "Feature",
  "properties": {
    "iso:country":"IN",
    "ks:ks_name":"Chingra Panrkidih",
    "ks:ks_pop":1472,
    "ks:ks_type":"VILLAGE",
    "name:eng_x_preferred":[
        "Chingra Panrkidih"
    ],
    "wof:name":"Chingra Panrkidih",
    "wof:placetype":"locality",
    "wof:population":1472
},
  "geometry": {"coordinates":[86.122151,23.027727],"type":"Point"}
}