{
  "type": "Feature",
  "properties": {
    "iso:country":"IN",
    "ks:ks_name":"Rayakarpada",
    "ks:ks_pop":335,
    "ks:ks_type":"HABITATION",
    "name:eng_x_preferred":[
        "Rayakarpada"
    ],
    "wof:name":"Rayakarpada",
    "wof:placetype":"locality",
    "wof:population":335
},
  "geometry": {"coordinates":[73.492616,19.339091],"type":"Point"}
}