{
  "type": "Feature",
  "properties": {
    "gn:admin1_code":"23.0",
    "gn:admin2_code":"41.0",
    "gn:asciiname":"Bholewal Jadid",
    "gn:country_code":"IN",
    "gn:dem":231,
    "gn:feature_class":"P",
    "gn:feature_code":"PPL",
    "gn:name":"Bholew\u0101l Jad\u012bd",
    "gn:population":0,
    "gn:timezone":"Asia/Kolkata",
    "iso:country":"IN",
    "name:pan_x_preferred":[
        "\u0a2d\u0a4b\u0a32\u0a47\u0a35\u0a3e\u0a32 \u0a1c\u0a26\u0a40\u0a26"
    ],
    "wof:name":"Bholewal Jadid",
    "wof:placetype":"locality"
},
  "geometry": {"coordinates":[75.72261,30.98643],"type":"Point"}
}