{
  "type": "Feature",
  "properties": {
    "iso:country":"IN",
    "ks:ks_name":"Bhagavathi",
    "ks:ks_pop":494,
    "ks:ks_type":"HABITATION",
    "name:eng_x_preferred":[
        "Bhagavathi"
    ],
    "wof:name":"Bhagavathi",
    "wof:placetype":"locality",
    "wof:population":494
},
  "geometry": {"coordinates":[74.628162,13.816189],"type":"Point"}
}