{
  "type": "Feature",
  "properties": {
    "iso:country":"IN",
    "ks:ks_name":"Talav Faliya",
    "ks:ks_pop":440,
    "ks:ks_type":"HABITATION",
    "name:eng_x_preferred":[
        "Talav Faliya"
    ],
    "wof:name":"Talav Faliya",
    "wof:placetype":"locality",
    "wof:population":440
},
  "geometry": {"coordinates":[73.699067,22.7518],"type":"Point"}
}