{
  "type": "Feature",
  "properties": {
    "iso:country":"IN",
    "ks:ks_alt_nam":"Pendari khaspara",
    "ks:ks_name":"Pendari Khaspara",
    "ks:ks_pop":328,
    "ks:ks_type":"HABITATION",
    "name:eng_x_preferred":[
        "Pendari Khaspara"
    ],
    "wof:name":"Pendari Khaspara",
    "wof:placetype":"locality",
    "wof:population":328
},
  "geometry": {"coordinates":[83.347583,23.435999],"type":"Point"}
}