{
  "type": "Feature",
  "properties": {
    "iso:country":"IN",
    "ks:ks_name":"Barahi-Da-Pathar",
    "ks:ks_pop":455,
    "ks:ks_type":"VILLAGE",
    "ks:ks_uagg_main":0,
    "name:eng_x_preferred":[
        "Barahi-Da-Pathar"
    ],
    "wof:name":"Barahi-Da-Pathar",
    "wof:placetype":"neighbourhood",
    "wof:population":455
},
  "geometry": {"coordinates":[95.11516,27.527984],"type":"Point"}
}