{
  "type": "Feature",
  "properties": {
    "iso:country":"IN",
    "ks:ks_name":"Veerwadi",
    "ks:ks_pop":391,
    "ks:ks_type":"HABITATION",
    "name:eng_x_preferred":[
        "Veerwadi"
    ],
    "wof:name":"Veerwadi",
    "wof:placetype":"locality",
    "wof:population":391
},
  "geometry": {"coordinates":[73.414574,16.417939],"type":"Point"}
}