{
  "type": "Feature",
  "properties": {
    "iso:country":"IN",
    "ks:ks_name":"Bhadurpur",
    "ks:ks_pop":0,
    "ks:ks_type":"VILLAGE",
    "name:eng_x_preferred":[
        "Bhadurpur"
    ],
    "wof:name":"Bhadurpur",
    "wof:placetype":"locality",
    "wof:population":0
},
  "geometry": {"coordinates":[87.34993299999999,23.798206],"type":"Point"}
}