{
  "type": "Feature",
  "properties": {
    "iso:country":"IN",
    "ks:ks_name":"Srikrishna Nagar",
    "ks:ks_pop":120,
    "ks:ks_type":"HABITATION",
    "name:eng_x_preferred":[
        "Srikrishna Nagar"
    ],
    "wof:name":"Srikrishna Nagar",
    "wof:placetype":"locality",
    "wof:population":120
},
  "geometry": {"coordinates":[77.340383,8.238097],"type":"Point"}
}