{
  "type": "Feature",
  "properties": {
    "gn:admin1_code":"12.0",
    "gn:admin2_code":"001",
    "gn:asciiname":"Kakrosa",
    "gn:country_code":"IN",
    "gn:dem":1796,
    "gn:feature_class":"P",
    "gn:feature_code":"PPL",
    "gn:name":"Kakrosa",
    "gn:population":0,
    "gn:timezone":"Asia/Kolkata",
    "iso:country":"IN",
    "wof:name":"Kakrosa",
    "wof:placetype":"locality"
},
  "geometry": {"coordinates":[74.15505999999998,34.45447],"type":"Point"}
}