{
  "type": "Feature",
  "properties": {
    "iso:country":"IN",
    "ks:ks_name":"Melerdanga",
    "ks:ks_pop":1527,
    "ks:ks_type":"HABITATION",
    "name:eng_x_preferred":[
        "Melerdanga"
    ],
    "wof:name":"Melerdanga",
    "wof:placetype":"locality",
    "wof:population":1527
},
  "geometry": {"coordinates":[87.881676,24.149441],"type":"Point"}
}