{
  "type": "Feature",
  "properties": {
    "iso:country":"IN",
    "ks:ks_name":"Rabidaspur",
    "ks:ks_pop":2163,
    "ks:ks_type":"VILLAGE",
    "name:eng_x_preferred":[
        "Rabidaspur"
    ],
    "wof:name":"Rabidaspur",
    "wof:placetype":"locality",
    "wof:population":2163
},
  "geometry": {"coordinates":[87.73728,22.49813],"type":"Point"}
}