{
  "type": "Feature",
  "properties": {
    "iso:country":"IN",
    "ks:ks_name":"Hari Ram Madaya",
    "ks:ks_pop":97,
    "ks:ks_type":"HABITATION",
    "name:eng_x_preferred":[
        "Hari Ram Madaya"
    ],
    "wof:name":"Hari Ram Madaya",
    "wof:placetype":"locality",
    "wof:population":97
},
  "geometry": {"coordinates":[79.690264,27.26291],"type":"Point"}
}