{
  "type": "Feature",
  "properties": {
    "iso:country":"IN",
    "ks:ks_name":"Kamrain Arazi",
    "ks:ks_pop":93,
    "ks:ks_type":"VILLAGE",
    "ks:ks_uagg_main":0,
    "name:eng_x_preferred":[
        "Kamrain Arazi"
    ],
    "wof:name":"Kamrain Arazi",
    "wof:placetype":"neighbourhood",
    "wof:population":93
},
  "geometry": {"coordinates":[86.706187,25.178176],"type":"Point"}
}