{
  "type": "Feature",
  "properties": {
    "gn:admin1_code":"12.0",
    "gn:admin2_code":"011",
    "gn:asciiname":"Laimlun",
    "gn:country_code":"IN",
    "gn:dem":2094,
    "gn:feature_class":"P",
    "gn:feature_code":"PPL",
    "gn:name":"Laimlun",
    "gn:population":0,
    "gn:timezone":"Asia/Kolkata",
    "iso:country":"IN",
    "wof:name":"Laimlun",
    "wof:placetype":"locality"
},
  "geometry": {"coordinates":[74.92310999999999,34.30799],"type":"Point"}
}