{
  "type": "Feature",
  "properties": {
    "iso:country":"IN",
    "ks:ks_alt_nam":"BAKHATPURA",
    "ks:ks_name":"Bakhatpura",
    "ks:ks_pop":205,
    "ks:ks_type":"HABITATION",
    "name:eng_x_preferred":[
        "Bakhatpura"
    ],
    "wof:name":"Bakhatpura",
    "wof:placetype":"locality",
    "wof:population":205
},
  "geometry": {"coordinates":[74.67222700000001,23.857795],"type":"Point"}
}