{
  "type": "Feature",
  "properties": {
    "gn:admin1_code":"10.0",
    "gn:admin2_code":"80.0",
    "gn:asciiname":"Churaud",
    "gn:country_code":"IN",
    "gn:dem":213,
    "gn:feature_class":"P",
    "gn:feature_code":"PPL",
    "gn:name":"Churaud",
    "gn:population":0,
    "gn:timezone":"Asia/Kolkata",
    "iso:country":"IN",
    "wof:name":"Churaud",
    "wof:placetype":"locality"
},
  "geometry": {"coordinates":[75.66115000000001,29.00565],"type":"Point"}
}