{
  "type": "Feature",
  "properties": {
    "iso:country":"IN",
    "ks:ks_name":"Koiri Purwa (m)",
    "ks:ks_pop":183,
    "ks:ks_type":"HABITATION",
    "name:eng_x_preferred":[
        "Koiri Purwa (m)"
    ],
    "wof:name":"Koiri Purwa (m)",
    "wof:placetype":"locality",
    "wof:population":183
},
  "geometry": {"coordinates":[83.025617,26.731456],"type":"Point"}
}