{
  "type": "Feature",
  "properties": {
    "iso:country":"IN",
    "ks:ks_name":"Bhoori Doongri",
    "ks:ks_pop":131,
    "ks:ks_type":"VILLAGE",
    "name:eng_x_preferred":[
        "Bhoori Doongri"
    ],
    "wof:name":"Bhoori Doongri",
    "wof:placetype":"locality",
    "wof:population":131
},
  "geometry": {"coordinates":[76.28748299999999,27.734799],"type":"Point"}
}