{
  "type": "Feature",
  "properties": {
    "iso:country":"IN",
    "ks:ks_name":"Belbuni",
    "ks:ks_pop":21,
    "ks:ks_type":"VILLAGE",
    "name:eng_x_preferred":[
        "Belbuni"
    ],
    "wof:name":"Belbuni",
    "wof:placetype":"locality",
    "wof:population":21
},
  "geometry": {"coordinates":[87.68213,24.178017],"type":"Point"}
}