{
  "type": "Feature",
  "properties": {
    "iso:country":"IN",
    "ks:ks_name":"Pambukodu",
    "ks:ks_pop":203,
    "ks:ks_type":"HABITATION",
    "name:eng_x_preferred":[
        "Pambukodu"
    ],
    "wof:name":"Pambukodu",
    "wof:placetype":"locality",
    "wof:population":203
},
  "geometry": {"coordinates":[75.85265200000001,11.668792],"type":"Point"}
}