{
  "type": "Feature",
  "properties": {
    "gn:admin1_code":"2.0",
    "gn:admin2_code":"551.0",
    "gn:asciiname":"Kottapalle",
    "gn:country_code":"IN",
    "gn:dem":399,
    "gn:feature_class":"P",
    "gn:feature_code":"PPL",
    "gn:name":"Kottapalle",
    "gn:population":0,
    "gn:timezone":"Asia/Kolkata",
    "iso:country":"IN",
    "ks:ks_name":"Kothapalli",
    "ks:ks_pop":67,
    "ks:ks_type":"HABITATION",
    "name:eng_x_preferred":[
        "Kothapalli"
    ],
    "name:eng_x_variant":[
        "Kottapalle"
    ],
    "wof:name":"Kothapalli",
    "wof:placetype":"locality",
    "wof:population":67
},
  "geometry": {"coordinates":[78.456587,14.076374],"type":"Point"}
}