{
  "type": "Feature",
  "properties": {
    "gn:country":"IN",
    "gn:fcode":"PPL",
    "gn:population":11847,
    "iso:country":"IN",
    "name:bho_x_preferred":[
        "\u0905\u0924\u0930\u094c\u0932\u093f\u092f\u093e"
    ],
    "name:bpy_x_preferred":[
        "\u0986\u09a4\u09cd\u09b0\u09cc\u09b2\u09bf\u09af\u09bc\u09be"
    ],
    "name:ceb_x_preferred":[
        "Atrauli\u0101"
    ],
    "name:eng_x_preferred":[
        "Atraulia"
    ],
    "name:hin_x_preferred":[
        "\u0905\u0924\u0930\u094c\u0932\u093f\u092f\u093e"
    ],
    "name:ita_x_preferred":[
        "Atraulia"
    ],
    "name:mlg_x_preferred":[
        "Atraulia"
    ],
    "name:msa_x_preferred":[
        "Atraulia"
    ],
    "name:nan_x_preferred":[
        "Atraulia"
    ],
    "name:new_x_preferred":[
        "\u0905\u0924\u094d\u0930\u094c\u0932\u0940\u092f"
    ],
    "name:nld_x_preferred":[
        "Atraulia"
    ],
    "name:pol_x_preferred":[
        "Atraulia"
    ],
    "name:por_x_preferred":[
        "Atraulia"
    ],
    "name:spa_x_preferred":[
        "Atraulia"
    ],
    "name:swe_x_preferred":[
        "Atrauli\u0101"
    ],
    "name:und_x_variant":[
        "Atrauliya"
    ],
    "name:urd_x_preferred":[
        "\u0627\u062a\u0631\u0648\u0644\u06cc\u0627"
    ],
    "name:vie_x_preferred":[
        "Atraulia"
    ],
    "name:zho_x_preferred":[
        "\u963f\u7279\u52b3\u5229\u4e9a"
    ],
    "qs:name":"Atrauli",
    "qs:name_adm0":"India",
    "qs:name_adm1":"Uttar Pradesh",
    "qs:photos_9r":0,
    "qs:photos_sr":0,
    "qs:placetype":"Town",
    "qs:pop_sr":"6",
    "wd:wordcount":405,
    "wof:name":"Atrauli",
    "wof:placetype":"locality",
    "wof:population":11847
},
  "geometry": {"coordinates":[82.94698,26.33274],"type":"Point"}
}