{
  "type": "Feature",
  "properties": {
    "gn:admin1_code":"35",
    "gn:admin2_code":"440.0",
    "gn:asciiname":"Tiri",
    "gn:country_code":"IN",
    "gn:dem":408,
    "gn:feature_class":"P",
    "gn:feature_code":"PPL",
    "gn:name":"Tiri",
    "gn:population":0,
    "gn:timezone":"Asia/Kolkata",
    "iso:country":"IN",
    "name:ceb_x_preferred":[
        "Tiri"
    ],
    "name:swe_x_preferred":[
        "Tiri"
    ],
    "wof:name":"Tiri",
    "wof:placetype":"locality"
},
  "geometry": {"coordinates":[75.28785000000001,21.73118],"type":"Point"}
}