{
  "type": "Feature",
  "properties": {
    "gn:admin1_code":"16.0",
    "gn:admin2_code":"521",
    "gn:asciiname":"Ghod",
    "gn:country_code":"IN",
    "gn:dem":669,
    "gn:feature_class":"P",
    "gn:feature_code":"PPL",
    "gn:name":"Ghod",
    "gn:population":0,
    "gn:timezone":"Asia/Kolkata",
    "iso:country":"IN",
    "name:und_x_variant":[
        "Ghoda",
        "Ghod"
    ],
    "wof:name":"Ghod",
    "wof:placetype":"neighbourhood"
},
  "geometry": {"coordinates":[73.83869,19.04654],"type":"Point"}
}