{
  "type": "Feature",
  "properties": {
    "gn:admin1_code":"25.0",
    "gn:admin2_code":"620.0",
    "gn:asciiname":"Anaivilundankeni",
    "gn:country_code":"IN",
    "gn:dem":93,
    "gn:feature_class":"P",
    "gn:feature_code":"PPL",
    "gn:name":"\u0100naivilund\u0101nkeni",
    "gn:population":0,
    "gn:timezone":"Asia/Kolkata",
    "iso:country":"IN",
    "wof:name":"Anaivilundankeni",
    "wof:placetype":"locality"
},
  "geometry": {"coordinates":[79.04494,10.67818],"type":"Point"}
}