{
  "type": "Feature",
  "properties": {
    "gn:admin1_code":"25.0",
    "gn:admin2_code":"620.0",
    "gn:asciiname":"Anaivilundankeni",
    "gn:country_code":"IN",
    "gn:dem":93,
    "gn:feature_class":"P",
    "gn:feature_code":"PPL",
    "gn:name":"\u0100naivilund\u0101nkeni",
    "gn:population":0,
    "gn:timezone":"Asia/Kolkata",
    "iso:country":"IN",
    "ks:ks_name":"Anaiviluthankeni",
    "ks:ks_pop":405,
    "ks:ks_type":"HABITATION",
    "name:eng_x_preferred":[
        "Anaiviluthankeni"
    ],
    "name:eng_x_variant":[
        "Anaivilundankeni"
    ],
    "wof:name":"Anaiviluthankeni",
    "wof:placetype":"locality",
    "wof:population":405
},
  "geometry": {"coordinates":[79.052019,10.666308],"type":"Point"}
}