{
  "type": "Feature",
  "properties": {
    "iso:country":"IN",
    "ks:ks_name":"Banglapara",
    "ks:ks_pop":405,
    "ks:ks_type":"HABITATION",
    "name:eng_x_preferred":[
        "Banglapara"
    ],
    "wof:name":"Banglapara",
    "wof:placetype":"locality",
    "wof:population":405
},
  "geometry": {"coordinates":[81.64664999999999,20.533547],"type":"Point"}
}