{
  "type": "Feature",
  "properties": {
    "iso:country":"IN",
    "ks:ks_name":"Chopadewasti",
    "ks:ks_pop":241,
    "ks:ks_type":"HABITATION",
    "name:eng_x_preferred":[
        "Chopadewasti"
    ],
    "wof:name":"Chopadewasti",
    "wof:placetype":"locality",
    "wof:population":241
},
  "geometry": {"coordinates":[74.564859,19.158678],"type":"Point"}
}