{
  "type": "Feature",
  "properties": {
    "iso:country":"IN",
    "ks:ks_name":"Karkhana",
    "ks:ks_pop":100,
    "ks:ks_type":"HABITATION",
    "name:eng_x_preferred":[
        "Karkhana"
    ],
    "wof:name":"Karkhana",
    "wof:placetype":"locality",
    "wof:population":100
},
  "geometry": {"coordinates":[82.60212900000001,26.431262],"type":"Point"}
}