{
  "type": "Feature",
  "properties": {
    "gn:admin1_code":"35",
    "gn:admin2_code":"466.0",
    "gn:asciiname":"Palakna",
    "gn:country_code":"IN",
    "gn:dem":303,
    "gn:feature_class":"P",
    "gn:feature_code":"PPL",
    "gn:name":"Palakna",
    "gn:population":0,
    "gn:timezone":"Asia/Kolkata",
    "iso:country":"IN",
    "wof:name":"Palakna",
    "wof:placetype":"neighbourhood"
},
  "geometry": {"coordinates":[76.43640000000001,21.88668],"type":"Point"}
}