{
  "type": "Feature",
  "properties": {
    "iso:country":"IN",
    "ks:ks_alt_nam":"Methia tarn",
    "ks:ks_name":"Methia Tarn",
    "ks:ks_pop":62,
    "ks:ks_type":"HABITATION",
    "name:eng_x_preferred":[
        "Methia Tarn"
    ],
    "wof:name":"Methia Tarn",
    "wof:placetype":"locality",
    "wof:population":62
},
  "geometry": {"coordinates":[86.520736,24.543571],"type":"Point"}
}