{
  "type": "Feature",
  "properties": {
    "iso:country":"IN",
    "ks:ks_name":"Madrupnagar",
    "ks:ks_pop":738,
    "ks:ks_type":"HABITATION",
    "name:eng_x_preferred":[
        "Madrupnagar"
    ],
    "wof:name":"Madrupnagar",
    "wof:placetype":"locality",
    "wof:population":738
},
  "geometry": {"coordinates":[72.433424,26.886216],"type":"Point"}
}