{
  "type": "Feature",
  "properties": {
    "iso:country":"IN",
    "ks:ks_name":"Khantoli",
    "ks:ks_pop":250,
    "ks:ks_type":"HABITATION",
    "name:eng_x_preferred":[
        "Khantoli"
    ],
    "wof:name":"Khantoli",
    "wof:placetype":"locality",
    "wof:population":250
},
  "geometry": {"coordinates":[84.98289800000001,23.297516],"type":"Point"}
}