{
  "type": "Feature",
  "properties": {
    "gn:admin1_code":"19.0",
    "gn:admin2_code":"574.0",
    "gn:asciiname":"Hongara Hosur",
    "gn:country_code":"IN",
    "gn:dem":828,
    "gn:feature_class":"P",
    "gn:feature_code":"PPL",
    "gn:name":"Hongara Hos\u016br",
    "gn:population":0,
    "gn:timezone":"Asia/Kolkata",
    "iso:country":"IN",
    "ks:ks_name":"Hangarahosur",
    "ks:ks_pop":10,
    "ks:ks_type":"HABITATION",
    "name:eng_x_preferred":[
        "Hangarahosur"
    ],
    "name:eng_x_variant":[
        "Hongara Hosur"
    ],
    "wof:name":"Hangarahosur",
    "wof:placetype":"locality",
    "wof:population":10
},
  "geometry": {"coordinates":[76.34016800000001,12.835406],"type":"Point"}
}