{
  "type": "Feature",
  "properties": {
    "iso:country":"IN",
    "ks:ks_name":"Teja Nagar Newra",
    "ks:ks_pop":983,
    "ks:ks_type":"HABITATION",
    "name:eng_x_preferred":[
        "Teja Nagar Newra"
    ],
    "wof:name":"Teja Nagar Newra",
    "wof:placetype":"locality",
    "wof:population":983
},
  "geometry": {"coordinates":[72.982288,26.717459],"type":"Point"}
}