{
  "type": "Feature",
  "properties": {
    "iso:country":"IN",
    "ks:ks_alt_nam":"Limbya tanda",
    "ks:ks_name":"Limbya Tanda",
    "ks:ks_pop":231,
    "ks:ks_type":"HABITATION",
    "name:eng_x_preferred":[
        "Limbya Tanda"
    ],
    "wof:name":"Limbya Tanda",
    "wof:placetype":"locality",
    "wof:population":231
},
  "geometry": {"coordinates":[78.251214,16.762649],"type":"Point"}
}