{
  "type": "Feature",
  "properties": {
    "iso:country":"IN",
    "ks:ks_name":"Thanda",
    "ks:ks_pop":269,
    "ks:ks_type":"HABITATION",
    "name:eng_x_preferred":[
        "Thanda"
    ],
    "wof:name":"Thanda",
    "wof:placetype":"locality",
    "wof:population":269
},
  "geometry": {"coordinates":[76.223281,13.390851],"type":"Point"}
}