{
  "type": "Feature",
  "properties": {
    "gn:admin1_code":"35",
    "gn:admin2_code":"461.0",
    "gn:asciiname":"Pharisemar",
    "gn:country_code":"IN",
    "gn:dem":841,
    "gn:feature_class":"P",
    "gn:feature_code":"PPL",
    "gn:name":"Pharisem\u0101r",
    "gn:population":0,
    "gn:timezone":"Asia/Kolkata",
    "iso:country":"IN",
    "ks:ks_name":"Pharrisemar",
    "ks:ks_pop":617,
    "ks:ks_type":"VILLAGE",
    "name:eng_x_preferred":[
        "Pharrisemar"
    ],
    "name:eng_x_variant":[
        "Pharisemar"
    ],
    "wof:name":"Pharrisemar",
    "wof:placetype":"locality",
    "wof:population":617
},
  "geometry": {"coordinates":[81.702969,22.760233],"type":"Point"}
}