{
  "type": "Feature",
  "properties": {
    "iso:country":"IN",
    "ks:ks_name":"Bhaliapadar",
    "ks:ks_pop":24,
    "ks:ks_type":"VILLAGE",
    "name:eng_x_preferred":[
        "Bhaliapadar"
    ],
    "wof:name":"Bhaliapadar",
    "wof:placetype":"locality",
    "wof:population":24
},
  "geometry": {"coordinates":[82.393345,18.472478],"type":"Point"}
}