{
  "type": "Feature",
  "properties": {
    "iso:country":"IN",
    "ks:ks_name":"Purni Dhanganin",
    "ks:ks_pop":172,
    "ks:ks_type":"VILLAGE",
    "name:eng_x_preferred":[
        "Purni Dhanganin"
    ],
    "wof:name":"Purni Dhanganin",
    "wof:placetype":"locality",
    "wof:population":172
},
  "geometry": {"coordinates":[84.948241,24.397983],"type":"Point"}
}