{
  "type": "Feature",
  "properties": {
    "iso:country":"IN",
    "ks:ks_name":"Netampara",
    "ks:ks_pop":85,
    "ks:ks_type":"HABITATION",
    "name:eng_x_preferred":[
        "Netampara"
    ],
    "wof:name":"Netampara",
    "wof:placetype":"locality",
    "wof:population":85
},
  "geometry": {"coordinates":[80.942987,20.54001],"type":"Point"}
}