{
  "type": "Feature",
  "properties": {
    "gn:admin1_code":"23.0",
    "gn:admin2_code":"43.0",
    "gn:asciiname":"Burewala",
    "gn:country_code":"IN",
    "gn:dem":206,
    "gn:feature_class":"P",
    "gn:feature_code":"PPL",
    "gn:name":"B\u016brew\u0101la",
    "gn:population":0,
    "gn:timezone":"Asia/Kolkata",
    "iso:country":"IN",
    "name:ben_x_preferred":[
        "\u09ac\u09c1\u09b0\u09c7\u0993\u09af\u09bc\u09be\u09b2\u09be"
    ],
    "name:ceb_x_preferred":[
        "Mandi B\u016brew\u0101la"
    ],
    "name:fas_x_preferred":[
        "\u0628\u0648\u0631\u06cc\u0648\u0627\u0644\u0627"
    ],
    "name:fra_x_preferred":[
        "Burewala"
    ],
    "name:ita_x_preferred":[
        "Burewala"
    ],
    "name:pnb_x_preferred":[
        "\u0628\u0648\u0631\u06cc\u0648\u0627\u0644\u0627"
    ],
    "name:pol_x_preferred":[
        "Burewala"
    ],
    "name:por_x_preferred":[
        "Burewala"
    ],
    "name:pus_x_preferred":[
        "\u0628\u0648\u0631\u064a\u0648\u0627\u0644\u0647"
    ],
    "name:rus_x_preferred":[
        "\u0411\u0443\u0440\u0435\u0432\u0430\u043b\u0430"
    ],
    "name:srp_x_preferred":[
        "\u0411\u0443\u0440\u0435\u0432\u0430\u043b\u0430"
    ],
    "name:swe_x_preferred":[
        "Burewala"
    ],
    "name:urd_x_preferred":[
        "\u0628\u0648\u0631\u06d2 \u0648\u0627\u0644\u0627"
    ],
    "name:vie_x_preferred":[
        "Burewala"
    ],
    "name:war_x_preferred":[
        "Burewala"
    ],
    "wof:name":"Burewala",
    "wof:placetype":"locality"
},
  "geometry": {"coordinates":[74.85693000000001,31.0259],"type":"Point"}
}