{
  "type": "Feature",
  "properties": {
    "iso:country":"IN",
    "ks:ks_name":"Sunari",
    "ks:ks_pop":16,
    "ks:ks_type":"VILLAGE",
    "name:eng_x_preferred":[
        "Sunari"
    ],
    "wof:name":"Sunari",
    "wof:placetype":"locality",
    "wof:population":16
},
  "geometry": {"coordinates":[78.641867,30.18094],"type":"Point"}
}