{
  "type": "Feature",
  "properties": {
    "iso:country":"IN",
    "ks:ks_name":"Bhanua",
    "ks:ks_type":"VILLAGE",
    "name:eng_x_preferred":[
        "Bhanua"
    ],
    "wof:name":"Bhanua",
    "wof:placetype":"locality"
},
  "geometry": {"coordinates":[84.090509,26.460473],"type":"Point"}
}