{
  "type": "Feature",
  "properties": {
    "gn:admin1_code":"11",
    "gn:admin2_code":"34.0",
    "gn:asciiname":"Kutang Dogri",
    "gn:country_code":"IN",
    "gn:dem":2980,
    "gn:feature_class":"P",
    "gn:feature_code":"PPL",
    "gn:name":"Kutang Dogri",
    "gn:population":0,
    "gn:timezone":"Asia/Kolkata",
    "iso:country":"IN",
    "wof:name":"Kutang Dogri",
    "wof:placetype":"locality"
},
  "geometry": {"coordinates":[78.35521,31.65273],"type":"Point"}
}