{
  "type": "Feature",
  "properties": {
    "iso:country":"IN",
    "ks:ks_name":"Punas Raja",
    "ks:ks_pop":1334,
    "ks:ks_type":"VILLAGE",
    "name:eng_x_preferred":[
        "Punas Raja"
    ],
    "wof:name":"Punas Raja",
    "wof:placetype":"locality",
    "wof:population":1334
},
  "geometry": {"coordinates":[85.42946000000001,26.14017],"type":"Point"}
}