{
  "type": "Feature",
  "properties": {
    "gn:admin1_code":"35",
    "gn:admin2_code":"436.0",
    "gn:asciiname":"Jalalpura",
    "gn:country_code":"IN",
    "gn:dem":513,
    "gn:feature_class":"P",
    "gn:feature_code":"PPL",
    "gn:name":"Jal\u0101lpura",
    "gn:population":0,
    "gn:timezone":"Asia/Kolkata",
    "iso:country":"IN",
    "name:und_x_variant":[
        "Jal\u0101lpura",
        "Dakhanpura"
    ],
    "wof:name":"Jalalpura",
    "wof:placetype":"locality"
},
  "geometry": {"coordinates":[76.13155999999999,23.23136],"type":"Point"}
}