{
  "type": "Feature",
  "properties": {
    "iso:country":"IN",
    "ks:ks_name":"Sulijaddi",
    "ks:ks_pop":88,
    "ks:ks_type":"HABITATION",
    "name:eng_x_preferred":[
        "Sulijaddi"
    ],
    "wof:name":"Sulijaddi",
    "wof:placetype":"locality",
    "wof:population":88
},
  "geometry": {"coordinates":[74.855329,14.5402],"type":"Point"}
}