{
  "type": "Feature",
  "properties": {
    "iso:country":"IN",
    "ks:ks_name":"32 STG",
    "ks:ks_pop":854,
    "ks:ks_type":"VILLAGE",
    "name:eng_x_preferred":[
        "32 STG"
    ],
    "wof:name":"32 STG",
    "wof:placetype":"locality",
    "wof:population":854
},
  "geometry": {"coordinates":[74.02369400000001,29.443431],"type":"Point"}
}