{
  "type": "Feature",
  "properties": {
    "iso:country":"IN",
    "ks:ks_name":"Mohammadpur Jati",
    "ks:ks_pop":0,
    "ks:ks_type":"VILLAGE",
    "ks:ks_uagg_main":0,
    "name:eng_x_preferred":[
        "Mohammadpur Jati"
    ],
    "wof:name":"Mohammadpur Jati",
    "wof:placetype":"locality",
    "wof:population":0
},
  "geometry": {"coordinates":[78.485287,28.922942],"type":"Point"}
}