{
  "type": "Feature",
  "properties": {
    "iso:country":"IN",
    "ks:ks_name":"Hadinmakki",
    "ks:ks_pop":57,
    "ks:ks_type":"HABITATION",
    "name:eng_x_preferred":[
        "Hadinmakki"
    ],
    "wof:name":"Hadinmakki",
    "wof:placetype":"locality",
    "wof:population":57
},
  "geometry": {"coordinates":[74.39411800000001,14.587849],"type":"Point"}
}