{
  "type": "Feature",
  "properties": {
    "iso:country":"IN",
    "ks:ks_name":"Alasua",
    "ks:ks_pop":548,
    "ks:ks_type":"HABITATION",
    "name:eng_x_preferred":[
        "Alasua"
    ],
    "wof:name":"Alasua",
    "wof:placetype":"locality",
    "wof:population":548
},
  "geometry": {"coordinates":[85.408732,20.687966],"type":"Point"}
}