{
  "type": "Feature",
  "properties": {
    "gn:admin1_code":"2.0",
    "gn:admin2_code":"544.0",
    "gn:asciiname":"Malimunda",
    "gn:country_code":"IN",
    "gn:dem":672,
    "gn:feature_class":"P",
    "gn:feature_code":"PPL",
    "gn:name":"M\u0101limunda",
    "gn:population":0,
    "gn:timezone":"Asia/Kolkata",
    "iso:country":"IN",
    "ks:ks_name":"Mallimunda",
    "ks:ks_pop":11,
    "ks:ks_type":"HABITATION",
    "name:eng_x_preferred":[
        "Mallimunda"
    ],
    "name:eng_x_variant":[
        "Malimunda"
    ],
    "wof:name":"Mallimunda",
    "wof:placetype":"locality",
    "wof:population":11
},
  "geometry": {"coordinates":[82.45843000000001,18.419195],"type":"Point"}
}