{
  "type": "Feature",
  "properties": {
    "iso:country":"IN",
    "ks:ks_name":"Panasalagondi",
    "ks:ks_pop":36,
    "ks:ks_type":"HABITATION",
    "name:eng_x_preferred":[
        "Panasalagondi"
    ],
    "wof:name":"Panasalagondi",
    "wof:placetype":"locality",
    "wof:population":36
},
  "geometry": {"coordinates":[82.619979,18.134955],"type":"Point"}
}