{
  "type": "Feature",
  "properties": {
    "iso:country":"IN",
    "ks:ks_name":"Bhawanipur",
    "ks:ks_pop":0,
    "ks:ks_type":"VILLAGE",
    "name:eng_x_preferred":[
        "Bhawanipur"
    ],
    "wof:name":"Bhawanipur",
    "wof:placetype":"locality",
    "wof:population":0
},
  "geometry": {"coordinates":[85.47325499999999,26.267791],"type":"Point"}
}