{
  "type": "Feature",
  "properties": {
    "gn:admin1_code":"36",
    "gn:admin2_code":"200.0",
    "gn:asciiname":"Chandauli",
    "gn:country_code":"IN",
    "gn:dem":304,
    "gn:feature_class":"P",
    "gn:feature_code":"PPL",
    "gn:name":"Chandauli",
    "gn:population":0,
    "gn:timezone":"Asia/Kolkata",
    "iso:country":"IN",
    "name:bpy_x_preferred":[
        "\u099a\u09be\u09a8\u09cd\u09a6\u09be\u0989\u09b2\u09bf"
    ],
    "name:ceb_x_preferred":[
        "Chandauli"
    ],
    "name:deu_x_preferred":[
        "Chandauli"
    ],
    "name:fra_x_preferred":[
        "Chandauli"
    ],
    "name:guj_x_preferred":[
        "\u0a9a\u0aa8\u0acd\u0aa6\u0acc\u0ab2\u0ac0"
    ],
    "name:hin_x_preferred":[
        "\u091a\u0928\u094d\u0926\u094c\u0932\u0940"
    ],
    "name:ita_x_preferred":[
        "Chandauli"
    ],
    "name:mlg_x_preferred":[
        "Chandauli"
    ],
    "name:msa_x_preferred":[
        "Chandauli"
    ],
    "name:new_x_preferred":[
        "\u091a\u0928\u094d\u0926\u094c\u0932\u0940"
    ],
    "name:nld_x_preferred":[
        "Chandauli"
    ],
    "name:pnb_x_preferred":[
        "\u0686\u0646\u0688\u0648\u0644\u06cc"
    ],
    "name:pol_x_preferred":[
        "Chandauli"
    ],
    "name:rus_x_preferred":[
        "\u0427\u0430\u043d\u0434\u0430\u0443\u043b\u0438"
    ],
    "name:san_x_preferred":[
        "\u091a\u0928\u094d\u0926\u094c\u0932\u0940"
    ],
    "name:swe_x_preferred":[
        "Chandauli"
    ],
    "name:und_x_variant":[
        "Orauli"
    ],
    "name:urd_x_preferred":[
        "\u0686\u0646\u062f\u0648\u0644\u06cc"
    ],
    "name:vie_x_preferred":[
        "Chandauli"
    ],
    "name:zho_x_preferred":[
        "\u94b1\u9053\u5229"
    ],
    "wof:name":"Chandauli",
    "wof:placetype":"locality"
},
  "geometry": {"coordinates":[82.97983000000001,24.7427],"type":"Point"}
}