{
  "type": "Feature",
  "properties": {
    "iso:country":"IN",
    "ks:ks_alt_nam":"Namla busty",
    "ks:ks_name":"Namla Busty",
    "ks:ks_pop":438,
    "ks:ks_type":"HABITATION",
    "name:eng_x_preferred":[
        "Namla Busty"
    ],
    "wof:name":"Namla Busty",
    "wof:placetype":"locality",
    "wof:population":438
},
  "geometry": {"coordinates":[88.105096,27.09809],"type":"Point"}
}