{
  "type": "Feature",
  "properties": {
    "gn:admin1_code":"38.0",
    "gn:admin2_code":"352.0",
    "gn:asciiname":"Bara Pagaro",
    "gn:country_code":"IN",
    "gn:dem":42,
    "gn:feature_class":"P",
    "gn:feature_code":"PPL",
    "gn:name":"Bara Pagaro",
    "gn:population":0,
    "gn:timezone":"Asia/Kolkata",
    "iso:country":"IN",
    "wof:name":"Bara Pagaro",
    "wof:placetype":"locality"
},
  "geometry": {"coordinates":[87.68066999999998,25.21477],"type":"Point"}
}