{
  "type": "Feature",
  "properties": {
    "iso:country":"IN",
    "ks:ks_alt_nam":"MUSHAR BASTI",
    "ks:ks_name":"Mushar Basti",
    "ks:ks_pop":10,
    "ks:ks_type":"HABITATION",
    "name:eng_x_preferred":[
        "Mushar Basti"
    ],
    "wof:name":"Mushar Basti",
    "wof:placetype":"locality",
    "wof:population":10
},
  "geometry": {"coordinates":[82.263842,26.139202],"type":"Point"}
}