{
  "type": "Feature",
  "properties": {
    "gn:admin1_code":"34.0",
    "gn:admin2_code":"217.0",
    "gn:asciiname":"Karmaini Ghazi",
    "gn:country_code":"IN",
    "gn:dem":75,
    "gn:feature_class":"P",
    "gn:feature_code":"PPL",
    "gn:name":"Karmaini Gh\u0101zi",
    "gn:population":0,
    "gn:timezone":"Asia/Kolkata",
    "iso:country":"IN",
    "ks:ks_alt_nam":"Karmaini Gh\u0101zi",
    "ks:ks_name":"Karmaini Ghazi",
    "ks:ks_pop":2016,
    "ks:ks_type":"VILLAGE",
    "name:eng_x_preferred":[
        "Karmaini Ghazi"
    ],
    "name:eng_x_variant":[
        "Karmaini Gh\u0101zi"
    ],
    "wof:name":"Karmaini Ghazi",
    "wof:placetype":"locality",
    "wof:population":2016
},
  "geometry": {"coordinates":[84.31881799999999,26.575413],"type":"Point"}
}