{
  "type": "Feature",
  "properties": {
    "iso:country":"IN",
    "ks:ks_name":"Baya Khurd",
    "ks:ks_pop":655,
    "ks:ks_type":"VILLAGE",
    "name:eng_x_preferred":[
        "Baya Khurd"
    ],
    "wof:name":"Baya Khurd",
    "wof:placetype":"locality",
    "wof:population":655
},
  "geometry": {"coordinates":[83.76884200000001,23.772424],"type":"Point"}
}