{
  "type": "Feature",
  "properties": {
    "iso:country":"IN",
    "ks:ks_name":"Gokul Bigha",
    "ks:ks_pop":618,
    "ks:ks_type":"HABITATION",
    "name:eng_x_preferred":[
        "Gokul Bigha"
    ],
    "wof:name":"Gokul Bigha",
    "wof:placetype":"locality",
    "wof:population":618
},
  "geometry": {"coordinates":[84.33717900000001,24.8602],"type":"Point"}
}