{
  "type": "Feature",
  "properties": {
    "iso:country":"IN",
    "ks:ks_name":"Jibansing",
    "ks:ks_pop":866,
    "ks:ks_type":"VILLAGE",
    "name:eng_x_preferred":[
        "Jibansing"
    ],
    "wof:name":"Jibansing",
    "wof:placetype":"locality",
    "wof:population":866
},
  "geometry": {"coordinates":[88.163004,26.615236],"type":"Point"}
}