{
  "type": "Feature",
  "properties": {
    "gn:admin1_code":"16.0",
    "gn:admin2_code":"513.0",
    "gn:asciiname":"Chikalthana Buzurg",
    "gn:country_code":"IN",
    "gn:dem":434,
    "gn:feature_class":"P",
    "gn:feature_code":"PPL",
    "gn:name":"Chikalth\u0101na Buzurg",
    "gn:population":0,
    "gn:timezone":"Asia/Kolkata",
    "iso:country":"IN",
    "wof:name":"Chikalthana Buzurg",
    "wof:placetype":"neighbourhood"
},
  "geometry": {"coordinates":[76.48565000000001,19.55744],"type":"Point"}
}