{
  "type": "Feature",
  "properties": {
    "gn:admin1_code":"36",
    "gn:admin2_code":"202.0",
    "gn:asciiname":"Rambans",
    "gn:country_code":"IN",
    "gn:dem":179,
    "gn:feature_class":"P",
    "gn:feature_code":"PPL",
    "gn:name":"R\u0101mb\u0101ns",
    "gn:population":0,
    "gn:timezone":"Asia/Kolkata",
    "iso:country":"IN",
    "name:und_x_variant":[
        "R\u0101mb\u0101ns",
        "Nagla Dhak"
    ],
    "wof:name":"Rambans",
    "wof:placetype":"locality"
},
  "geometry": {"coordinates":[78.62251999999999,27.8622],"type":"Point"}
}