{
  "type": "Feature",
  "properties": {
    "iso:country":"IN",
    "ks:ks_name":"Parassery",
    "ks:ks_pop":568,
    "ks:ks_type":"HABITATION",
    "name:eng_x_preferred":[
        "Parassery"
    ],
    "wof:name":"Parassery",
    "wof:placetype":"locality",
    "wof:population":568
},
  "geometry": {"coordinates":[76.34201400000001,11.169426],"type":"Point"}
}