{
  "type": "Feature",
  "properties": {
    "iso:country":"IN",
    "ks:ks_alt_nam":"Talli Pt II",
    "ks:ks_name":"Talli Pt Ii",
    "ks:ks_pop":1699,
    "ks:ks_type":"HABITATION",
    "name:eng_x_preferred":[
        "Talli Pt Ii"
    ],
    "wof:name":"Talli Pt Ii",
    "wof:placetype":"locality",
    "wof:population":1699
},
  "geometry": {"coordinates":[89.771501,26.166354],"type":"Point"}
}