{
  "type": "Feature",
  "properties": {
    "iso:country":"IN",
    "ks:ks_name":"Makaput",
    "ks:ks_pop":176,
    "ks:ks_type":"HABITATION",
    "name:eng_x_preferred":[
        "Makaput"
    ],
    "wof:name":"Makaput",
    "wof:placetype":"locality",
    "wof:population":176
},
  "geometry": {"coordinates":[82.678105,18.339994],"type":"Point"}
}