{
  "type": "Feature",
  "properties": {
    "iso:country":"IN",
    "ks:ks_name":"Govindpur",
    "ks:ks_pop":315,
    "ks:ks_type":"VILLAGE",
    "name:eng_x_preferred":[
        "Govindpur"
    ],
    "wof:name":"Govindpur",
    "wof:placetype":"locality",
    "wof:population":315
},
  "geometry": {"coordinates":[83.06488400000001,25.27496],"type":"Point"}
}