{
  "type": "Feature",
  "properties": {
    "iso:country":"IN",
    "ks:ks_name":"Irumbamthadam",
    "ks:ks_pop":694,
    "ks:ks_type":"HABITATION",
    "name:eng_x_preferred":[
        "Irumbamthadam"
    ],
    "wof:name":"Irumbamthadam",
    "wof:placetype":"locality",
    "wof:population":694
},
  "geometry": {"coordinates":[75.744851,11.726212],"type":"Point"}
}