{
  "type": "Feature",
  "properties": {
    "iso:country":"IN",
    "ks:ks_name":"Church Thanda",
    "ks:ks_pop":100,
    "ks:ks_type":"HABITATION",
    "name:eng_x_preferred":[
        "Church Thanda"
    ],
    "wof:name":"Church Thanda",
    "wof:placetype":"locality",
    "wof:population":100
},
  "geometry": {"coordinates":[78.27474100000001,19.236662],"type":"Point"}
}