{
  "type": "Feature",
  "properties": {
    "iso:country":"IN",
    "ks:ks_name":"Gaurangapur",
    "ks:ks_pop":1770,
    "ks:ks_type":"VILLAGE",
    "name:eng_x_preferred":[
        "Gaurangapur"
    ],
    "wof:name":"Gaurangapur",
    "wof:placetype":"locality",
    "wof:population":1770
},
  "geometry": {"coordinates":[87.883161,22.29008],"type":"Point"}
}