{
  "type": "Feature",
  "properties": {
    "iso:country":"IN",
    "ks:ks_name":"Pure Bishenan",
    "ks:ks_pop":180,
    "ks:ks_type":"HABITATION",
    "ks:ks_uagg_main":0,
    "name:eng_x_preferred":[
        "Pure Bishenan"
    ],
    "wof:name":"Pure Bishenan",
    "wof:placetype":"neighbourhood",
    "wof:population":180
},
  "geometry": {"coordinates":[81.30063800000001,26.223949],"type":"Point"}
}