{
  "type": "Feature",
  "properties": {
    "gn:admin1_code":"35",
    "gn:admin2_code":"457.0",
    "gn:asciiname":"Ghunkairi",
    "gn:country_code":"IN",
    "gn:dem":350,
    "gn:feature_class":"P",
    "gn:feature_code":"PPL",
    "gn:name":"Ghunkairi",
    "gn:population":0,
    "gn:timezone":"Asia/Kolkata",
    "iso:country":"IN",
    "ks:ks_name":"Ghunkairi",
    "ks:ks_type":"VILLAGE",
    "name:eng_x_preferred":[
        "Ghunkairi"
    ],
    "wof:name":"Ghunkairi",
    "wof:placetype":"locality"
},
  "geometry": {"coordinates":[79.852841,21.831304],"type":"Point"}
}