{
  "type": "Feature",
  "properties": {
    "iso:country":"IN",
    "ks:ks_alt_nam":"TAKHIRAI PARA",
    "ks:ks_name":"Takhirai Para",
    "ks:ks_pop":20,
    "ks:ks_type":"HABITATION",
    "name:eng_x_preferred":[
        "Takhirai Para"
    ],
    "wof:name":"Takhirai Para",
    "wof:placetype":"locality",
    "wof:population":20
},
  "geometry": {"coordinates":[91.41798799999999,23.909878],"type":"Point"}
}