{
  "type": "Feature",
  "properties": {
    "iso:country":"IN",
    "ks:ks_alt_nam":"DAKKHIN GAON KYAR",
    "ks:ks_name":"Dakkhin Gaon Kyar",
    "ks:ks_pop":303,
    "ks:ks_type":"HABITATION",
    "name:eng_x_preferred":[
        "Dakkhin Gaon Kyar"
    ],
    "wof:name":"Dakkhin Gaon Kyar",
    "wof:placetype":"locality",
    "wof:population":303
},
  "geometry": {"coordinates":[81.596362,26.58504],"type":"Point"}
}