{
  "type": "Feature",
  "properties": {
    "gn:admin1_code":"16",
    "gn:admin2_code":"505.0",
    "gn:asciiname":"Tuyapar",
    "gn:country_code":"IN",
    "gn:dem":416,
    "gn:feature_class":"P",
    "gn:feature_code":"PPL",
    "gn:name":"Tuy\u0101p\u0101r",
    "gn:population":0,
    "gn:timezone":"Asia/Kolkata",
    "iso:country":"IN",
    "ks:ks_alt_nam":"Tuy\u0101p\u0101r",
    "ks:ks_name":"Tuyapar",
    "ks:ks_pop":92,
    "ks:ks_type":"VILLAGE",
    "name:eng_x_preferred":[
        "Tuyapar"
    ],
    "name:eng_x_variant":[
        "Tuy\u0101p\u0101r"
    ],
    "wof:name":"Tuyapar",
    "wof:placetype":"locality",
    "wof:population":92
},
  "geometry": {"coordinates":[79.258903,21.544116],"type":"Point"}
}