{
  "type": "Feature",
  "properties": {
    "gn:admin1_code":"40",
    "gn:admin2_code":"533.0",
    "gn:asciiname":"Madnur",
    "gn:country_code":"IN",
    "gn:dem":392,
    "gn:feature_class":"P",
    "gn:feature_code":"PPL",
    "gn:name":"Madn\u016br",
    "gn:population":0,
    "gn:timezone":"Asia/Kolkata",
    "iso:country":"IN",
    "name:new_x_preferred":[
        "\u092e\u0926\u094d\u0928\u0942\u0930\u0941 \u092e\u0923\u094d\u0921\u0932"
    ],
    "name:tel_x_preferred":[
        "\u0c2e\u0c26\u0c4d\u0c28\u0c42\u0c30\u0c4d"
    ],
    "name:und_x_variant":[
        "Madn\u016br"
    ],
    "name:urd_x_preferred":[
        "\u0645\u06cc\u0688\u0646\u0648\u0631"
    ],
    "wof:name":"Madnur",
    "wof:placetype":"locality"
},
  "geometry": {"coordinates":[77.62449000000002,18.50247],"type":"Point"}
}