{
  "type": "Feature",
  "properties": {
    "iso:country":"IN",
    "ks:ks_name":"Patoti",
    "ks:ks_pop":431,
    "ks:ks_type":"VILLAGE",
    "name:eng_x_preferred":[
        "Patoti"
    ],
    "wof:name":"Patoti",
    "wof:placetype":"locality",
    "wof:population":431
},
  "geometry": {"coordinates":[78.95313899999999,30.047097],"type":"Point"}
}