{
  "type": "Feature",
  "properties": {
    "iso:country":"IN",
    "ks:ks_name":"Magha Ki Dhani",
    "ks:ks_pop":429,
    "ks:ks_type":"VILLAGE",
    "name:eng_x_preferred":[
        "Magha Ki Dhani"
    ],
    "wof:name":"Magha Ki Dhani",
    "wof:placetype":"locality",
    "wof:population":429
},
  "geometry": {"coordinates":[71.82518899999999,25.143047],"type":"Point"}
}