{
  "type": "Feature",
  "properties": {
    "iso:country":"IN",
    "ks:ks_name":"Baragharia",
    "ks:ks_pop":1456,
    "ks:ks_type":"VILLAGE",
    "ks:ks_uagg_main":0,
    "name:eng_x_preferred":[
        "Baragharia"
    ],
    "wof:name":"Baragharia",
    "wof:placetype":"neighbourhood",
    "wof:population":1456
},
  "geometry": {"coordinates":[88.39622799999999,26.746601],"type":"Point"}
}