{
  "type": "Feature",
  "properties": {
    "iso:country":"IN",
    "ks:ks_name":"Mandva",
    "ks:ks_pop":954,
    "ks:ks_type":"VILLAGE",
    "name:eng_x_preferred":[
        "Mandva"
    ],
    "wof:name":"Mandva",
    "wof:placetype":"locality",
    "wof:population":954
},
  "geometry": {"coordinates":[73.74490299999999,23.492654],"type":"Point"}
}