{
  "type": "Feature",
  "properties": {
    "gn:admin1_code":"35",
    "gn:admin2_code":"426.0",
    "gn:asciiname":"Kudar",
    "gn:country_code":"IN",
    "gn:dem":447,
    "gn:feature_class":"P",
    "gn:feature_code":"PPL",
    "gn:name":"Kud\u0101r",
    "gn:population":0,
    "gn:timezone":"Asia/Kolkata",
    "iso:country":"IN",
    "name:ava_x_preferred":[
        "\u041aI\u0443\u0434\u0430\u0440\u0430\u043b"
    ],
    "name:krc_x_preferred":[
        "\u041a\u044a\u0443\u0434\u0430\u0440\u043b\u044b\u043b\u0430"
    ],
    "name:oss_x_preferred":[
        "\u041a\u044a\u0443\u044b\u0434\u0430\u0440"
    ],
    "name:rus_x_preferred":[
        "\u041a\u0443\u0434\u0430\u0440\u0446\u044b"
    ],
    "wof:name":"Kudar",
    "wof:placetype":"locality"
},
  "geometry": {"coordinates":[80.18558,24.79309],"type":"Point"}
}