{
  "type": "Feature",
  "properties": {
    "gn:admin1_code":"35.0",
    "gn:admin2_code":"428.0",
    "gn:asciiname":"Mahadpur",
    "gn:country_code":"IN",
    "gn:dem":367,
    "gn:feature_class":"P",
    "gn:feature_code":"PPL",
    "gn:name":"Mahadpur",
    "gn:population":0,
    "gn:timezone":"Asia/Kolkata",
    "iso:country":"IN",
    "wof:name":"Mahadpur",
    "wof:placetype":"locality"
},
  "geometry": {"coordinates":[79.28740000000001,23.7672],"type":"Point"}
}