{
  "type": "Feature",
  "properties": {
    "gn:admin1_code":"34.0",
    "gn:admin2_code":"231.0",
    "gn:asciiname":"Bargaon",
    "gn:country_code":"IN",
    "gn:dem":74,
    "gn:feature_class":"P",
    "gn:feature_code":"PPL",
    "gn:name":"Bargaon",
    "gn:population":0,
    "gn:timezone":"Asia/Kolkata",
    "iso:country":"IN",
    "ks:ks_name":"Bargaon",
    "ks:ks_pop":6000,
    "ks:ks_type":"VILLAGE",
    "name:eng_x_preferred":[
        "Bargaon"
    ],
    "wof:name":"Bargaon",
    "wof:placetype":"locality",
    "wof:population":6000
},
  "geometry": {"coordinates":[84.653398,25.33857],"type":"Point"}
}