{
  "type": "Feature",
  "properties": {
    "iso:country":"IN",
    "ks:ks_name":"Jakhda",
    "ks:ks_pop":0,
    "ks:ks_type":"VILLAGE",
    "name:eng_x_preferred":[
        "Jakhda"
    ],
    "wof:name":"Jakhda",
    "wof:placetype":"locality",
    "wof:population":0
},
  "geometry": {"coordinates":[77.20990399999999,25.599879],"type":"Point"}
}