{
  "type": "Feature",
  "properties": {
    "gn:admin1_code":"12",
    "gn:admin2_code":"18.0",
    "gn:asciiname":"Klishu",
    "gn:country_code":"IN",
    "gn:dem":3193,
    "gn:feature_class":"P",
    "gn:feature_code":"PPL",
    "gn:name":"Klishu",
    "gn:population":0,
    "gn:timezone":"Asia/Kolkata",
    "iso:country":"IN",
    "wof:name":"Klishu",
    "wof:placetype":"locality"
},
  "geometry": {"coordinates":[76.09311,33.25321],"type":"Point"}
}