{
  "type": "Feature",
  "properties": {
    "gn:admin1_code":"34.0",
    "gn:admin2_code":"228.0",
    "gn:asciiname":"Toi",
    "gn:country_code":"IN",
    "gn:dem":54,
    "gn:feature_class":"P",
    "gn:feature_code":"PPL",
    "gn:name":"Toi",
    "gn:population":0,
    "gn:timezone":"Asia/Kolkata",
    "iso:country":"IN",
    "name:ceb_x_preferred":[
        "Toi"
    ],
    "name:fra_x_preferred":[
        "Toi"
    ],
    "name:nld_x_preferred":[
        "Toi"
    ],
    "name:swe_x_preferred":[
        "Toi"
    ],
    "wof:name":"Toi",
    "wof:placetype":"locality"
},
  "geometry": {"coordinates":[85.73804,25.24456],"type":"Point"}
}