{
  "type": "Feature",
  "properties": {
    "iso:country":"IN",
    "ks:ks_name":"Mahammadpur Marwat",
    "ks:ks_pop":223,
    "ks:ks_type":"VILLAGE",
    "name:eng_x_preferred":[
        "Mahammadpur Marwat"
    ],
    "wof:name":"Mahammadpur Marwat",
    "wof:placetype":"locality",
    "wof:population":223
},
  "geometry": {"coordinates":[84.578264,26.339478],"type":"Point"}
}