{
  "type": "Feature",
  "properties": {
    "iso:country":"IN",
    "ks:ks_name":"Atkatawa Tola",
    "ks:ks_pop":192,
    "ks:ks_type":"HABITATION",
    "name:eng_x_preferred":[
        "Atkatawa Tola"
    ],
    "wof:name":"Atkatawa Tola",
    "wof:placetype":"locality",
    "wof:population":192
},
  "geometry": {"coordinates":[83.014769,24.025314],"type":"Point"}
}