{
  "type": "Feature",
  "properties": {
    "iso:country":"IN",
    "ks:ks_name":"Noloni Bari",
    "ks:ks_pop":605,
    "ks:ks_type":"VILLAGE",
    "ks:ks_uagg_main":0,
    "name:eng_x_preferred":[
        "Noloni Bari"
    ],
    "wof:name":"Noloni Bari",
    "wof:placetype":"neighbourhood",
    "wof:population":605
},
  "geometry": {"coordinates":[93.478678,26.897956],"type":"Point"}
}