{
  "type": "Feature",
  "properties": {
    "gn:admin1_code":"24.0",
    "gn:admin2_code":"129.0",
    "gn:asciiname":"Lakshmipura",
    "gn:country_code":"IN",
    "gn:dem":338,
    "gn:feature_class":"P",
    "gn:feature_code":"PPL",
    "gn:name":"Lakshmipura",
    "gn:population":0,
    "gn:timezone":"Asia/Kolkata",
    "iso:country":"IN",
    "wof:name":"Lakshmipura",
    "wof:placetype":"locality"
},
  "geometry": {"coordinates":[76.25901,24.39132],"type":"Point"}
}