{
  "type": "Feature",
  "properties": {
    "iso:country":"IN",
    "ks:ks_name":"Mahudi Falia",
    "ks:ks_pop":372,
    "ks:ks_type":"HABITATION",
    "name:eng_x_preferred":[
        "Mahudi Falia"
    ],
    "wof:name":"Mahudi Falia",
    "wof:placetype":"locality",
    "wof:population":372
},
  "geometry": {"coordinates":[74.20097199999999,22.955667],"type":"Point"}
}