{
  "type": "Feature",
  "properties": {
    "gn:admin1_code":"36.0",
    "gn:admin2_code":"152",
    "gn:asciiname":"Kundauli",
    "gn:country_code":"IN",
    "gn:dem":146,
    "gn:feature_class":"P",
    "gn:feature_code":"PPL",
    "gn:name":"Kundauli",
    "gn:population":0,
    "gn:timezone":"Asia/Kolkata",
    "iso:country":"IN",
    "ks:ks_name":"Kundauli",
    "ks:ks_pop":591,
    "ks:ks_type":"VILLAGE",
    "name:eng_x_preferred":[
        "Kundauli"
    ],
    "wof:name":"Kundauli",
    "wof:placetype":"locality",
    "wof:population":591
},
  "geometry": {"coordinates":[79.672192,27.617072],"type":"Point"}
}