{
  "type": "Feature",
  "properties": {
    "iso:country":"IN",
    "ks:ks_name":"Mahesh Patti",
    "ks:ks_pop":118,
    "ks:ks_type":"VILLAGE",
    "name:eng_x_preferred":[
        "Mahesh Patti"
    ],
    "wof:name":"Mahesh Patti",
    "wof:placetype":"locality",
    "wof:population":118
},
  "geometry": {"coordinates":[85.720973,26.238572],"type":"Point"}
}