{
  "type": "Feature",
  "properties": {
    "iso:country":"IN",
    "name:ara_x_preferred":[
        "\u0643\u0648\u0641\u0627\u0628\u0627\u062f\u0627\u0645 \u0634\u0627\u0646\u062a\u064a \u0646\u0627\u062c\u0627\u0631"
    ],
    "name:ben_bn_x_preferred":[
        "\u0995\u09c2\u09ad\u09be\u09aa\u09a6\u09ae \u09b6\u09be\u09a8\u09cd\u09a4\u09bf \u09a8\u0997\u09b0"
    ],
    "name:ben_in_x_preferred":[
        "\u0995\u09c2\u09ad\u09be\u09aa\u09a6\u09ae \u09b6\u09be\u09a8\u09cd\u09a4\u09bf \u09a8\u0997\u09b0"
    ],
    "name:guj_x_preferred":[
        "\u0a95\u0ac1\u0ab5\u0abe\u0aaa\u0aa6\u0aae \u0ab6\u0abe\u0a82\u0aa4\u0abf \u0aa8\u0a97\u0ab0"
    ],
    "name:hin_x_preferred":[
        "\u0915\u0942\u0935\u092a\u0926\u092e \u0936\u093e\u0902\u0924\u093f \u0928\u0917\u0930"
    ],
    "name:kan_x_preferred":[
        "\u0c95\u0cc2\u0cb5\u0caa\u0ca6\u0cae\u0ccd"
    ],
    "name:mal_x_preferred":[
        "\u0d15\u0d42\u0d35\u0d2a\u0d26\u0d02 \u0d36\u0d3e\u0d28\u0d4d\u0d24\u0d3f \u0d28\u0d17\u0d7c"
    ],
    "name:mar_x_preferred":[
        "\u0915\u0941\u0935\u093e\u092a\u093e\u0926\u093e\u092e \u0936\u093e\u0902\u0924\u0940 \u0928\u0917\u0930"
    ],
    "name:pan_x_preferred":[
        "\u0a15\u0a42\u0a35\u0a3e\u0a2a\u0a26\u0a2e \u0a36\u0a3e\u0a02\u0a24\u0a40 \u0a28\u0a17\u0a30"
    ],
    "name:tam_x_preferred":[
        "\u0b95\u0bc2\u0bb5\u0baa\u0b9f\u0bae\u0bcd \u0b9a\u0bbe\u0ba8\u0bcd\u0ba4\u0bbf \u0ba8\u0b95\u0bb0\u0bcd"
    ],
    "name:tel_x_preferred":[
        "\u0c15\u0c42\u0c35\u0c2a\u0c3e\u0c26\u0c2e\u0c4d \u0c36\u0c3e\u0c02\u0c24\u0c3f \u0c28\u0c17\u0c30\u0c4d"
    ],
    "name:urd_x_preferred":[
        "\u06a9\u0648\u0648\u0627 \u067e\u062f\u0645 \u0634\u0627\u0646\u062a\u06cc \u0646\u06af\u0631"
    ],
    "qs:name":"Koovapadam Shanti Nagar",
    "qs:name_adm0":"India",
    "qs:name_adm1":"Kerala",
    "qs:photos":105,
    "qs:photos_1k":21,
    "qs:photos_9k":1,
    "qs:photos_9r":3,
    "qs:photos_all":105,
    "qs:photos_sr":3,
    "qs:placetype":"Suburb",
    "qs:pop_sr":"0",
    "wof:name":"Koovapadam Shanti Nagar",
    "wof:placetype":"neighbourhood"
},
  "geometry": {"coordinates":[76.25279999999999,9.9569],"type":"Point"}
}