{
  "type": "Feature",
  "properties": {
    "iso:country":"IN",
    "qs:name":"Koovapadam Shanti Nagar",
    "qs:name_adm0":"India",
    "qs:name_adm1":"Kerala",
    "qs:photos":105,
    "qs:photos_1k":21,
    "qs:photos_9k":1,
    "qs:photos_9r":3,
    "qs:photos_all":105,
    "qs:photos_sr":3,
    "qs:placetype":"Suburb",
    "qs:pop_sr":"0",
    "wof:name":"Koovapadam Shanti Nagar",
    "wof:placetype":"neighbourhood"
},
  "geometry": {"coordinates":[76.25279999999999,9.9569],"type":"Point"}
}