{
  "type": "Feature",
  "properties": {
    "iso:country":"IN",
    "ks:ks_name":"Kuzhithiri",
    "ks:ks_pop":1004,
    "ks:ks_type":"HABITATION",
    "ks:ks_uagg_main":0,
    "name:eng_x_preferred":[
        "Kuzhithiri"
    ],
    "wof:name":"Kuzhithiri",
    "wof:placetype":"neighbourhood",
    "wof:population":1004
},
  "geometry": {"coordinates":[76.307041,9.906424],"type":"Point"}
}