{
  "type": "Feature",
  "properties": {
    "iso:country":"IN",
    "ks:ks_name":"Kasturi Koppalu",
    "ks:ks_pop":522,
    "ks:ks_type":"HABITATION",
    "name:eng_x_preferred":[
        "Kasturi Koppalu"
    ],
    "wof:name":"Kasturi Koppalu",
    "wof:placetype":"locality",
    "wof:population":522
},
  "geometry": {"coordinates":[76.181836,13.315941],"type":"Point"}
}