{
  "type": "Feature",
  "properties": {
    "gn:admin1_code":"40.0",
    "gn:admin2_code":"535.0",
    "gn:asciiname":"Anantsagar",
    "gn:country_code":"IN",
    "gn:dem":557,
    "gn:feature_class":"P",
    "gn:feature_code":"PPL",
    "gn:name":"Anants\u0101gar",
    "gn:population":0,
    "gn:timezone":"Asia/Kolkata",
    "iso:country":"IN",
    "wof:name":"Anantsagar",
    "wof:placetype":"locality"
},
  "geometry": {"coordinates":[78.48581999999998,17.97905],"type":"Point"}
}