{
  "type": "Feature",
  "properties": {
    "iso:country":"IN",
    "ks:ks_name":"22 GG",
    "ks:ks_pop":134,
    "ks:ks_type":"VILLAGE",
    "name:eng_x_preferred":[
        "22 GG"
    ],
    "wof:name":"22 GG",
    "wof:placetype":"locality",
    "wof:population":134
},
  "geometry": {"coordinates":[73.78188400000001,29.831498],"type":"Point"}
}