{
  "type": "Feature",
  "properties": {
    "gn:admin1_code":"34.0",
    "gn:admin2_code":"219.0",
    "gn:asciiname":"Barhia",
    "gn:country_code":"IN",
    "gn:dem":62,
    "gn:feature_class":"P",
    "gn:feature_code":"PPL",
    "gn:name":"Barhia",
    "gn:population":0,
    "gn:timezone":"Asia/Kolkata",
    "iso:country":"IN",
    "wof:name":"Barhia",
    "wof:placetype":"locality"
},
  "geometry": {"coordinates":[84.57858,25.97412000000001],"type":"Point"}
}