{
  "type": "Feature",
  "properties": {
    "gn:admin1_code":"16",
    "gn:admin2_code":"506.0",
    "gn:asciiname":"Gobarwahi Heti",
    "gn:country_code":"IN",
    "gn:dem":333,
    "gn:feature_class":"P",
    "gn:feature_code":"PPL",
    "gn:name":"Gobarw\u0101hi Heti",
    "gn:population":0,
    "gn:timezone":"Asia/Kolkata",
    "iso:country":"IN",
    "wof:name":"Gobarwahi Heti",
    "wof:placetype":"locality"
},
  "geometry": {"coordinates":[79.73031999999998,21.50581],"type":"Point"}
}