{
  "type": "Feature",
  "properties": {
    "iso:country":"IN",
    "ks:ks_name":"Jamalpur.",
    "ks:ks_pop":398,
    "ks:ks_type":"HABITATION",
    "ks:ks_uagg_main":0,
    "name:eng_x_preferred":[
        "Jamalpur."
    ],
    "wof:name":"Jamalpur.",
    "wof:placetype":"neighbourhood",
    "wof:population":398
},
  "geometry": {"coordinates":[87.712682,21.709738],"type":"Point"}
}