{
  "type": "Feature",
  "properties": {
    "iso:country":"IN",
    "ks:ks_alt_nam":"Kott\u016br",
    "ks:ks_name":"Kottur",
    "ks:ks_pop":404,
    "ks:ks_type":"VILLAGE",
    "name:eng_x_preferred":[
        "Kottur"
    ],
    "name:eng_x_variant":[
        "Kott\u016br"
    ],
    "wof:name":"Kottur",
    "wof:placetype":"locality",
    "wof:population":404
},
  "geometry": {"coordinates":[78.734133,10.321785],"type":"Point"}
}