{
  "type": "Feature",
  "properties": {
    "iso:country":"IN",
    "ks:ks_name":"Thana",
    "ks:ks_pop":0,
    "ks:ks_type":"VILLAGE",
    "name:eng_x_preferred":[
        "Thana"
    ],
    "wof:name":"Thana",
    "wof:placetype":"locality",
    "wof:population":0
},
  "geometry": {"coordinates":[76.84508,22.405411],"type":"Point"}
}