{
  "type": "Feature",
  "properties": {
    "iso:country":"IN",
    "ks:ks_name":"6 PTD-A",
    "ks:ks_pop":61,
    "ks:ks_type":"VILLAGE",
    "ks:ks_uagg_main":0,
    "name:eng_x_preferred":[
        "6 PTD-A"
    ],
    "wof:name":"6 PTD-A",
    "wof:placetype":"neighbourhood",
    "wof:population":61
},
  "geometry": {"coordinates":[73.35965400000001,29.37703],"type":"Point"}
}