{
  "type": "Feature",
  "properties": {
    "gn:admin1_code":"39",
    "gn:admin2_code":"61.0",
    "gn:asciiname":"Rewa",
    "gn:country_code":"IN",
    "gn:dem":1600,
    "gn:feature_class":"P",
    "gn:feature_code":"PPL",
    "gn:name":"Rewa",
    "gn:population":0,
    "gn:timezone":"Asia/Kolkata",
    "iso:country":"IN",
    "ks:ks_name":"Rewa",
    "ks:ks_type":"VILLAGE",
    "name:ara_x_preferred":[
        "\u0631\u064a\u0648\u0627"
    ],
    "name:ben_bn_x_preferred":[
        "\u09b0\u09bf\u0993\u09cd\u09df\u09be"
    ],
    "name:ben_in_x_preferred":[
        "\u09b0\u09bf\u0993\u09cd\u09df\u09be"
    ],
    "name:ben_x_preferred":[
        "\u09b0\u09c7\u0993\u09af\u09bc\u09be"
    ],
    "name:bih_x_preferred":[
        "\u0930\u0940\u0935\u093e"
    ],
    "name:bpy_x_preferred":[
        "\u09b0\u09c7\u09f1\u09be"
    ],
    "name:ceb_x_preferred":[
        "Rewa"
    ],
    "name:deu_x_preferred":[
        "Rewa"
    ],
    "name:eng_x_preferred":[
        "Rewa"
    ],
    "name:fin_x_preferred":[
        "Rewa"
    ],
    "name:fra_x_preferred":[
        "Rewa"
    ],
    "name:guj_x_preferred":[
        "\u0ab0\u0ac7\u0ab5\u0abe"
    ],
    "name:hin_x_preferred":[
        "\u0930\u0940\u0935\u093e"
    ],
    "name:ita_x_preferred":[
        "Rewa"
    ],
    "name:kan_x_preferred":[
        "\u0cb0\u0cc7\u0cb5\u0cbe"
    ],
    "name:mal_x_preferred":[
        "\u0d30\u0d47\u0d35"
    ],
    "name:mar_x_preferred":[
        "\u0930\u0940\u0935\u093e"
    ],
    "name:msa_x_preferred":[
        "Rewa"
    ],
    "name:nld_x_preferred":[
        "Rewa"
    ],
    "name:pan_x_preferred":[
        "\u0a30\u0a47\u0a35\u0a3e"
    ],
    "name:pol_x_preferred":[
        "Rewa"
    ],
    "name:por_x_preferred":[
        "Rewa"
    ],
    "name:spa_x_preferred":[
        "Rewa"
    ],
    "name:swe_x_preferred":[
        "Rewa"
    ],
    "name:tam_x_preferred":[
        "\u0bb0\u0bc7\u0bb5\u0bbe"
    ],
    "name:tel_x_preferred":[
        "\u0c30\u0c47\u0c35\u0c3e"
    ],
    "name:urd_x_preferred":[
        "\u0631\u06cc\u0648\u0627"
    ],
    "wof:name":"Rewa",
    "wof:placetype":"locality"
},
  "geometry": {"coordinates":[78.928141,29.769977],"type":"Point"}
}