{
  "type": "Feature",
  "properties": {
    "iso:country":"IN",
    "ks:ks_name":"Kalgari",
    "ks:ks_pop":163,
    "ks:ks_type":"VILLAGE",
    "name:eng_x_preferred":[
        "Kalgari"
    ],
    "wof:name":"Kalgari",
    "wof:placetype":"locality",
    "wof:population":163
},
  "geometry": {"coordinates":[78.91460600000001,30.103382],"type":"Point"}
}