{
  "type": "Feature",
  "properties": {
    "gn:admin1_code":"39.0",
    "gn:admin2_code":"64.0",
    "gn:asciiname":"Dilkot",
    "gn:country_code":"IN",
    "gn:dem":1284,
    "gn:feature_class":"P",
    "gn:feature_code":"PPL",
    "gn:name":"Dilkot",
    "gn:population":0,
    "gn:timezone":"Asia/Kolkata",
    "iso:country":"IN",
    "wof:name":"Dilkot",
    "wof:placetype":"locality"
},
  "geometry": {"coordinates":[79.59153000000001,29.61758],"type":"Point"}
}