{
  "type": "Feature",
  "properties": {
    "iso:country":"IN",
    "ks:ks_name":"Kaithwar",
    "ks:ks_pop":972,
    "ks:ks_type":"VILLAGE",
    "ks:ks_uagg_main":0,
    "name:eng_x_preferred":[
        "Kaithwar"
    ],
    "wof:name":"Kaithwar",
    "wof:placetype":"neighbourhood",
    "wof:population":972
},
  "geometry": {"coordinates":[86.449546,26.060421],"type":"Point"}
}