{
  "type": "Feature",
  "properties": {
    "iso:country":"IN",
    "ks:ks_name":"Guddirukya Tanda",
    "ks:ks_pop":155,
    "ks:ks_type":"HABITATION",
    "name:eng_x_preferred":[
        "Guddirukya Tanda"
    ],
    "wof:name":"Guddirukya Tanda",
    "wof:placetype":"locality",
    "wof:population":155
},
  "geometry": {"coordinates":[77.91973900000001,17.006997],"type":"Point"}
}