{
  "type": "Feature",
  "properties": {
    "iso:country":"IN",
    "ks:ks_name":"Binduidi",
    "ks:ks_pop":334,
    "ks:ks_type":"VILLAGE",
    "name:eng_x_preferred":[
        "Binduidi"
    ],
    "wof:name":"Binduidi",
    "wof:placetype":"locality",
    "wof:population":334
},
  "geometry": {"coordinates":[86.813613,23.624718],"type":"Point"}
}