{
  "type": "Feature",
  "properties": {
    "iso:country":"IN",
    "ks:ks_name":"1 KSM",
    "ks:ks_pop":349,
    "ks:ks_type":"VILLAGE",
    "name:eng_x_preferred":[
        "1 KSM"
    ],
    "wof:name":"1 KSM",
    "wof:placetype":"locality",
    "wof:population":349
},
  "geometry": {"coordinates":[73.721306,29.238642],"type":"Point"}
}