{
  "type": "Feature",
  "properties": {
    "gn:admin1_code":"2.0",
    "gn:admin2_code":"544.0",
    "gn:asciiname":"Changavalasa",
    "gn:country_code":"IN",
    "gn:dem":1010,
    "gn:feature_class":"P",
    "gn:feature_code":"PPL",
    "gn:name":"Changavalasa",
    "gn:population":0,
    "gn:timezone":"Asia/Kolkata",
    "iso:country":"IN",
    "wof:name":"Changavalasa",
    "wof:placetype":"locality"
},
  "geometry": {"coordinates":[82.46618000000002,18.20355],"type":"Point"}
}