{
  "type": "Feature",
  "properties": {
    "iso:country":"IN",
    "ks:ks_name":"Sunkuradi",
    "ks:ks_pop":58,
    "ks:ks_type":"HABITATION",
    "name:eng_x_preferred":[
        "Sunkuradi"
    ],
    "wof:name":"Sunkuradi",
    "wof:placetype":"locality",
    "wof:population":58
},
  "geometry": {"coordinates":[75.271286,13.406173],"type":"Point"}
}