{
  "type": "Feature",
  "properties": {
    "iso:country":"IN",
    "ks:ks_name":"Patkijore",
    "ks:ks_pop":868,
    "ks:ks_type":"VILLAGE",
    "name:eng_x_preferred":[
        "Patkijore"
    ],
    "wof:name":"Patkijore",
    "wof:placetype":"locality",
    "wof:population":868
},
  "geometry": {"coordinates":[83.99094700000001,22.204296],"type":"Point"}
}