{
  "type": "Feature",
  "properties": {
    "gn:admin1_code":"25.0",
    "gn:admin2_code":"606.0",
    "gn:asciiname":"Brinivasapuram",
    "gn:country_code":"IN",
    "gn:dem":152,
    "gn:feature_class":"P",
    "gn:feature_code":"PPL",
    "gn:name":"Br\u012bniv\u0101sapuram",
    "gn:population":0,
    "gn:timezone":"Asia/Kolkata",
    "iso:country":"IN",
    "ks:ks_name":"Srinivasapuram",
    "ks:ks_pop":356,
    "ks:ks_type":"HABITATION",
    "name:eng_x_preferred":[
        "Srinivasapuram"
    ],
    "name:eng_x_variant":[
        "Brinivasapuram"
    ],
    "name:und_x_variant":[
        "Br\u012bniv\u0101sapuram",
        "Attimalaipattu"
    ],
    "wof:name":"Srinivasapuram",
    "wof:placetype":"locality",
    "wof:population":356
},
  "geometry": {"coordinates":[79.26339400000001,12.616211],"type":"Point"}
}