{
  "type": "Feature",
  "properties": {
    "gn:admin1_code":"25.0",
    "gn:admin2_code":"606.0",
    "gn:asciiname":"Brinivasapuram",
    "gn:country_code":"IN",
    "gn:dem":152,
    "gn:feature_class":"P",
    "gn:feature_code":"PPL",
    "gn:name":"Br\u012bniv\u0101sapuram",
    "gn:population":0,
    "gn:timezone":"Asia/Kolkata",
    "iso:country":"IN",
    "name:und_x_variant":[
        "Br\u012bniv\u0101sapuram",
        "Attimalaipattu"
    ],
    "wof:name":"Brinivasapuram",
    "wof:placetype":"locality"
},
  "geometry": {"coordinates":[79.25853000000002,12.61865],"type":"Point"}
}