{
  "type": "Feature",
  "properties": {
    "gn:admin1_code":"12.0",
    "gn:admin2_code":"18.0",
    "gn:asciiname":"Jawot",
    "gn:country_code":"IN",
    "gn:dem":3283,
    "gn:feature_class":"P",
    "gn:feature_code":"PPL",
    "gn:name":"Jaw\u014dt",
    "gn:population":0,
    "gn:timezone":"Asia/Kolkata",
    "iso:country":"IN",
    "wof:name":"Jawot",
    "wof:placetype":"locality"
},
  "geometry": {"coordinates":[76.08946999999998,33.08265],"type":"Point"}
}