{
  "type": "Feature",
  "properties": {
    "iso:country":"IN",
    "ks:ks_name":"Naokhuli",
    "ks:ks_pop":744,
    "ks:ks_type":"VILLAGE",
    "name:eng_x_preferred":[
        "Naokhuli"
    ],
    "wof:name":"Naokhuli",
    "wof:placetype":"locality",
    "wof:population":744
},
  "geometry": {"coordinates":[89.62536900000001,26.326424],"type":"Point"}
}