{
  "type": "Feature",
  "properties": {
    "gn:admin1_code":"36.0",
    "gn:admin2_code":"175.0",
    "gn:asciiname":"Mathpur",
    "gn:country_code":"IN",
    "gn:dem":103,
    "gn:feature_class":"P",
    "gn:feature_code":"PPL",
    "gn:name":"M\u0101thpur",
    "gn:population":0,
    "gn:timezone":"Asia/Kolkata",
    "iso:country":"IN",
    "ks:ks_name":"Matpur",
    "ks:ks_pop":280,
    "ks:ks_type":"HABITATION",
    "name:eng_x_preferred":[
        "Matpur"
    ],
    "name:eng_x_variant":[
        "Mathpur"
    ],
    "wof:name":"Matpur",
    "wof:placetype":"locality",
    "wof:population":280
},
  "geometry": {"coordinates":[81.935286,25.67688],"type":"Point"}
}