{
  "type": "Feature",
  "properties": {
    "iso:country":"IN",
    "ks:ks_name":"Kadamba",
    "ks:ks_pop":369,
    "ks:ks_type":"HABITATION",
    "name:eng_x_preferred":[
        "Kadamba"
    ],
    "wof:name":"Kadamba",
    "wof:placetype":"locality",
    "wof:population":369
},
  "geometry": {"coordinates":[82.26669800000001,18.714479],"type":"Point"}
}