{
  "type": "Feature",
  "properties": {
    "iso:country":"IN",
    "ks:ks_alt_nam":"NAI AND MALI BASTI",
    "ks:ks_name":"Nai And Mali Basti",
    "ks:ks_pop":156,
    "ks:ks_type":"HABITATION",
    "ks:ks_uagg_main":0,
    "name:eng_x_preferred":[
        "Nai And Mali Basti"
    ],
    "wof:name":"Nai And Mali Basti",
    "wof:placetype":"neighbourhood",
    "wof:population":156
},
  "geometry": {"coordinates":[82.306682,25.457471],"type":"Point"}
}