{
  "type": "Feature",
  "properties": {
    "iso:country":"IN",
    "ks:ks_name":"Lara Bora",
    "ks:ks_pop":296,
    "ks:ks_type":"VILLAGE",
    "name:eng_x_preferred":[
        "Lara Bora"
    ],
    "wof:name":"Lara Bora",
    "wof:placetype":"locality",
    "wof:population":296
},
  "geometry": {"coordinates":[80.034356,29.227656],"type":"Point"}
}