{
  "type": "Feature",
  "properties": {
    "iso:country":"IN",
    "ks:ks_name":"Bavikere",
    "ks:ks_pop":289,
    "ks:ks_type":"HABITATION",
    "name:eng_x_preferred":[
        "Bavikere"
    ],
    "wof:name":"Bavikere",
    "wof:placetype":"locality",
    "wof:population":289
},
  "geometry": {"coordinates":[75.162615,13.629601],"type":"Point"}
}