{
  "type": "Feature",
  "properties": {
    "gn:admin1_code":"11",
    "gn:admin2_code":"34.0",
    "gn:asciiname":"Purbani",
    "gn:country_code":"IN",
    "gn:dem":2242,
    "gn:feature_class":"P",
    "gn:feature_code":"PPL",
    "gn:name":"Purbani",
    "gn:population":0,
    "gn:timezone":"Asia/Kolkata",
    "iso:country":"IN",
    "wof:name":"Purbani",
    "wof:placetype":"locality"
},
  "geometry": {"coordinates":[78.29873000000001,31.59134],"type":"Point"}
}