{
  "type": "Feature",
  "properties": {
    "gn:admin1_code":"02",
    "gn:admin2_code":"548.0",
    "gn:asciiname":"Undavalli",
    "gn:country_code":"IN",
    "gn:dem":28,
    "gn:feature_class":"P",
    "gn:feature_code":"PPL",
    "gn:name":"Undavalli",
    "gn:population":0,
    "gn:timezone":"Asia/Kolkata",
    "iso:country":"IN",
    "name:tel_x_preferred":[
        "\u0c09\u0c02\u0c21\u0c35\u0c32\u0c4d\u0c32\u0c3f"
    ],
    "name:und_x_variant":[
        "Undavalle"
    ],
    "wof:name":"Undavalli",
    "wof:placetype":"locality"
},
  "geometry": {"coordinates":[80.58574,16.49566],"type":"Point"}
}