{
  "type": "Feature",
  "properties": {
    "iso:country":"IN",
    "ks:ks_name":"Bariya Faliya",
    "ks:ks_pop":1230,
    "ks:ks_type":"HABITATION",
    "name:eng_x_preferred":[
        "Bariya Faliya"
    ],
    "wof:name":"Bariya Faliya",
    "wof:placetype":"locality",
    "wof:population":1230
},
  "geometry": {"coordinates":[73.77255599999999,23.152194],"type":"Point"}
}