{
  "type": "Feature",
  "properties": {
    "gn:admin1_code":"16",
    "gn:admin2_code":"510.0",
    "gn:asciiname":"Dublipod",
    "gn:country_code":"IN",
    "gn:dem":282,
    "gn:feature_class":"P",
    "gn:feature_code":"PPL",
    "gn:name":"Dubl\u012bpod",
    "gn:population":0,
    "gn:timezone":"Asia/Kolkata",
    "iso:country":"IN",
    "ks:ks_alt_nam":"dublipod",
    "ks:ks_name":"Dublipod",
    "ks:ks_pop":469,
    "ks:ks_type":"HABITATION",
    "name:eng_x_preferred":[
        "Dublipod"
    ],
    "wof:name":"Dublipod",
    "wof:placetype":"locality",
    "wof:population":469
},
  "geometry": {"coordinates":[78.683119,19.903934],"type":"Point"}
}