{
  "type": "Feature",
  "properties": {
    "iso:country":"IN",
    "ks:ks_name":"Hebbarandi",
    "ks:ks_pop":144,
    "ks:ks_type":"HABITATION",
    "name:eng_x_preferred":[
        "Hebbarandi"
    ],
    "wof:name":"Hebbarandi",
    "wof:placetype":"locality",
    "wof:population":144
},
  "geometry": {"coordinates":[74.793554,13.688528],"type":"Point"}
}