{
  "type": "Feature",
  "properties": {
    "gn:admin1_code":"36.0",
    "gn:admin2_code":"160.0",
    "gn:asciiname":"Kaklai",
    "gn:country_code":"IN",
    "gn:dem":151,
    "gn:feature_class":"P",
    "gn:feature_code":"PPL",
    "gn:name":"Kaklai",
    "gn:population":0,
    "gn:timezone":"Asia/Kolkata",
    "iso:country":"IN",
    "name:und_x_variant":[
        "Jal\u0101lpur",
        "Kaklai"
    ],
    "wof:name":"Kaklai",
    "wof:placetype":"neighbourhood"
},
  "geometry": {"coordinates":[79.55638999999999,26.97102],"type":"Point"}
}