{
  "type": "Feature",
  "properties": {
    "iso:country":"IN",
    "ks:ks_name":"Vazhaveedu",
    "ks:ks_pop":765,
    "ks:ks_type":"HABITATION",
    "name:eng_x_preferred":[
        "Vazhaveedu"
    ],
    "wof:name":"Vazhaveedu",
    "wof:placetype":"locality",
    "wof:population":765
},
  "geometry": {"coordinates":[77.123653,9.684993],"type":"Point"}
}