{
  "type": "Feature",
  "properties": {
    "iso:country":"IN",
    "ks:ks_name":"Nilaiya",
    "ks:ks_pop":132,
    "ks:ks_type":"VILLAGE",
    "name:eng_x_preferred":[
        "Nilaiya"
    ],
    "wof:name":"Nilaiya",
    "wof:placetype":"locality",
    "wof:population":132
},
  "geometry": {"coordinates":[86.59671299999999,24.54958],"type":"Point"}
}