{
  "type": "Feature",
  "properties": {
    "iso:country":"IN",
    "ks:ks_name":"Digha",
    "ks:ks_pop":206,
    "ks:ks_type":"VILLAGE",
    "name:eng_x_preferred":[
        "Digha"
    ],
    "wof:name":"Digha",
    "wof:placetype":"locality",
    "wof:population":206
},
  "geometry": {"coordinates":[87.53408399999999,22.517749],"type":"Point"}
}