{
  "type": "Feature",
  "properties": {
    "gn:admin1_code":"40",
    "gn:admin2_code":"538.0",
    "gn:asciiname":"Bijuwar",
    "gn:country_code":"IN",
    "gn:dem":405,
    "gn:feature_class":"P",
    "gn:feature_code":"PPL",
    "gn:name":"Bijuw\u0101r",
    "gn:population":0,
    "gn:timezone":"Asia/Kolkata",
    "iso:country":"IN",
    "name:msa_x_preferred":[
        "Bijuwar"
    ],
    "name:nep_x_preferred":[
        "\u092c\u093f\u091c\u0941\u092c\u093e\u0930"
    ],
    "name:new_x_preferred":[
        "\u092c\u093f\u091c\u0941\u092c\u093e\u0930"
    ],
    "name:pol_x_preferred":[
        "Bijuwar"
    ],
    "wof:name":"Bijuwar",
    "wof:placetype":"locality"
},
  "geometry": {"coordinates":[77.60084000000001,16.62161],"type":"Point"}
}