{
  "type": "Feature",
  "properties": {
    "iso:country":"IN",
    "ks:ks_name":"Matigadia",
    "ks:ks_pop":45,
    "ks:ks_type":"HABITATION",
    "name:eng_x_preferred":[
        "Matigadia"
    ],
    "wof:name":"Matigadia",
    "wof:placetype":"locality",
    "wof:population":45
},
  "geometry": {"coordinates":[85.018792,20.504348],"type":"Point"}
}