{
  "type": "Feature",
  "properties": {
    "gn:admin1_code":"24.0",
    "gn:admin2_code":"119.0",
    "gn:asciiname":"Banseli",
    "gn:country_code":"IN",
    "gn:dem":453,
    "gn:feature_class":"P",
    "gn:feature_code":"PPL",
    "gn:name":"B\u0101nseli",
    "gn:population":0,
    "gn:timezone":"Asia/Kolkata",
    "iso:country":"IN",
    "ks:ks_alt_nam":"B\u0101nseli",
    "ks:ks_name":"Banseli",
    "ks:ks_pop":3375,
    "ks:ks_type":"VILLAGE",
    "name:eng_x_preferred":[
        "Banseli"
    ],
    "name:eng_x_variant":[
        "B\u0101nseli"
    ],
    "wof:name":"Banseli",
    "wof:placetype":"locality",
    "wof:population":3375
},
  "geometry": {"coordinates":[74.552161,26.516383],"type":"Point"}
}