{
  "type": "Feature",
  "properties": {
    "iso:country":"IN",
    "ks:ks_name":"Raghunathpur",
    "ks:ks_pop":5552,
    "ks:ks_type":"VILLAGE",
    "ks:ks_uagg_main":0,
    "name:eng_x_preferred":[
        "Raghunathpur"
    ],
    "wof:name":"Raghunathpur",
    "wof:placetype":"neighbourhood",
    "wof:population":5552
},
  "geometry": {"coordinates":[88.036858,24.608782],"type":"Point"}
}