{
  "type": "Feature",
  "properties": {
    "iso:country":"IN",
    "ks:ks_name":"Mahdewa",
    "ks:ks_type":"VILLAGE",
    "ks:ks_uagg_main":0,
    "name:eng_x_preferred":[
        "Mahdewa"
    ],
    "wof:name":"Mahdewa",
    "wof:placetype":"neighbourhood"
},
  "geometry": {"coordinates":[83.08643600000001,26.982369],"type":"Point"}
}