{
  "type": "Feature",
  "properties": {
    "iso:country":"IN",
    "ks:ks_name":"Karkihaklu",
    "ks:ks_pop":19,
    "ks:ks_type":"HABITATION",
    "name:eng_x_preferred":[
        "Karkihaklu"
    ],
    "wof:name":"Karkihaklu",
    "wof:placetype":"locality",
    "wof:population":19
},
  "geometry": {"coordinates":[74.726513,14.502853],"type":"Point"}
}