{
  "type": "Feature",
  "properties": {
    "iso:country":"IN",
    "ks:ks_name":"Vadachettiyandal",
    "ks:ks_pop":1498,
    "ks:ks_type":"VILLAGE",
    "name:eng_x_preferred":[
        "Vadachettiyandal"
    ],
    "wof:name":"Vadachettiyandal",
    "wof:placetype":"locality",
    "wof:population":1498
},
  "geometry": {"coordinates":[78.941794,11.866601],"type":"Point"}
}