{
  "type": "Feature",
  "properties": {
    "iso:country":"IN",
    "ks:ks_name":"Kanigadia",
    "ks:ks_pop":426,
    "ks:ks_type":"VILLAGE",
    "name:eng_x_preferred":[
        "Kanigadia"
    ],
    "wof:name":"Kanigadia",
    "wof:placetype":"locality",
    "wof:population":426
},
  "geometry": {"coordinates":[86.688828,21.568806],"type":"Point"}
}