{
  "type": "Feature",
  "properties": {
    "iso:country":"IN",
    "ks:ks_name":"Muthukalivalasu",
    "ks:ks_pop":105,
    "ks:ks_type":"HABITATION",
    "name:eng_x_preferred":[
        "Muthukalivalasu"
    ],
    "wof:name":"Muthukalivalasu",
    "wof:placetype":"locality",
    "wof:population":105
},
  "geometry": {"coordinates":[77.532377,10.967278],"type":"Point"}
}