{
  "type": "Feature",
  "properties": {
    "gn:admin1_code":"11",
    "gn:admin2_code":"30.0",
    "gn:asciiname":"Dasgaon",
    "gn:country_code":"IN",
    "gn:dem":681,
    "gn:feature_class":"P",
    "gn:feature_code":"PPL",
    "gn:name":"Dasgaon",
    "gn:population":0,
    "gn:timezone":"Asia/Kolkata",
    "iso:country":"IN",
    "name:mar_x_preferred":[
        "\u0926\u093e\u0938\u0917\u093e\u0902\u0935"
    ],
    "wof:name":"Dasgaon",
    "wof:placetype":"locality"
},
  "geometry": {"coordinates":[76.82001,31.40298],"type":"Point"}
}