{
  "type": "Feature",
  "properties": {
    "gn:admin1_code":"36",
    "gn:admin2_code":"175.0",
    "gn:asciiname":"Shahabpur",
    "gn:country_code":"IN",
    "gn:dem":94,
    "gn:feature_class":"P",
    "gn:feature_code":"PPL",
    "gn:name":"Shah\u0101bpur",
    "gn:population":0,
    "gn:timezone":"Asia/Kolkata",
    "iso:country":"IN",
    "ks:ks_name":"Sahabpur",
    "ks:ks_pop":823,
    "ks:ks_type":"VILLAGE",
    "ks:ks_uagg_main":0,
    "name:eng_x_preferred":[
        "Sahabpur"
    ],
    "name:fas_x_preferred":[
        "\u0634\u0647\u0627\u0628\u067e\u0648\u0631"
    ],
    "name:por_x_preferred":[
        "Shahabpur"
    ],
    "wof:name":"Sahabpur",
    "wof:placetype":"neighbourhood",
    "wof:population":823
},
  "geometry": {"coordinates":[82.212605,25.492176],"type":"Point"}
}