{
  "type": "Feature",
  "properties": {
    "iso:country":"IN",
    "ks:ks_name":"Padmaniya",
    "ks:ks_pop":351,
    "ks:ks_type":"HABITATION",
    "name:eng_x_preferred":[
        "Padmaniya"
    ],
    "wof:name":"Padmaniya",
    "wof:placetype":"locality",
    "wof:population":351
},
  "geometry": {"coordinates":[80.793041,25.034897],"type":"Point"}
}