{
  "type": "Feature",
  "properties": {
    "iso:country":"IN",
    "ks:ks_name":"Nss Hab",
    "ks:ks_pop":478,
    "ks:ks_type":"HABITATION",
    "name:eng_x_preferred":[
        "Nss Hab"
    ],
    "wof:name":"Nss Hab",
    "wof:placetype":"locality",
    "wof:population":478
},
  "geometry": {"coordinates":[76.823032,9.05409],"type":"Point"}
}