{
  "type": "Feature",
  "properties": {
    "gn:admin1_code":"11.0",
    "gn:admin2_code":"27.0",
    "gn:asciiname":"Tarla Riara",
    "gn:country_code":"IN",
    "gn:dem":2604,
    "gn:feature_class":"P",
    "gn:feature_code":"PPL",
    "gn:name":"Tarla Ri\u0101ra",
    "gn:population":0,
    "gn:timezone":"Asia/Kolkata",
    "iso:country":"IN",
    "wof:name":"Tarla Riara",
    "wof:placetype":"locality"
},
  "geometry": {"coordinates":[77.12758000000002,31.4708],"type":"Point"}
}