{
  "type": "Feature",
  "properties": {
    "iso:country":"IN",
    "ks:ks_name":"Madathur",
    "ks:ks_pop":448,
    "ks:ks_type":"HABITATION",
    "ks:ks_uagg_main":0,
    "name:eng_x_preferred":[
        "Madathur"
    ],
    "wof:name":"Madathur",
    "wof:placetype":"neighbourhood",
    "wof:population":448
},
  "geometry": {"coordinates":[77.345551,8.916375],"type":"Point"}
}