{
  "type": "Feature",
  "properties": {
    "gn:admin1_code":"10",
    "gn:admin2_code":"83.0",
    "gn:asciiname":"Wazirpur",
    "gn:country_code":"IN",
    "gn:dem":220,
    "gn:feature_class":"P",
    "gn:feature_code":"PPL",
    "gn:name":"Waz\u012brpur",
    "gn:population":0,
    "gn:timezone":"Asia/Kolkata",
    "iso:country":"IN",
    "ks:ks_name":"Wazirpur",
    "ks:ks_pop":2461,
    "ks:ks_type":"VILLAGE",
    "ks:ks_uagg_main":0,
    "name:ara_x_preferred":[
        "\u0648\u0632\u064a\u0631\u0628\u0648\u0631"
    ],
    "name:ben_bn_x_preferred":[
        "\u0993\u09df\u09be\u099c\u09bf\u09b0\u09aa\u09c1\u09b0"
    ],
    "name:ben_in_x_preferred":[
        "\u0993\u09df\u09be\u099c\u09bf\u09b0\u09aa\u09c1\u09b0"
    ],
    "name:eng_x_preferred":[
        "Wazirpur"
    ],
    "name:guj_x_preferred":[
        "\u0ab5\u0a9d\u0abf\u0ab0\u0aaa\u0ac1\u0ab0"
    ],
    "name:hin_x_preferred":[
        "\u0935\u095b\u0940\u0930\u092a\u0941\u0930"
    ],
    "name:kan_x_preferred":[
        "\u0cb5\u0c9c\u0cbf\u0cb0\u0ccd"
    ],
    "name:mal_x_preferred":[
        "\u0d35\u0d3e\u0d38\u0d3f\u0d7c\u0d2a\u0d42\u0d7c"
    ],
    "name:mar_x_preferred":[
        "\u0935\u091c\u0940\u0930\u092a\u0942\u0930"
    ],
    "name:pan_x_preferred":[
        "\u0a35\u0a1c\u0a3c\u0a40\u0a30\u0a2a\u0a41\u0a30"
    ],
    "name:tam_x_preferred":[
        "\u0bb5\u0bbe\u0b9c\u0bbf\u0bb0\u0bcd\u0baa\u0bc2\u0bb0\u0bcd"
    ],
    "name:tel_x_preferred":[
        "\u0c35\u0c3e\u0c1c\u0c3f\u0c30\u0c4d"
    ],
    "name:urd_x_preferred":[
        "\u0648\u0632\u06cc\u0631 \u067e\u0648\u0631"
    ],
    "wof:name":"Wazirpur",
    "wof:placetype":"neighbourhood",
    "wof:population":2461
},
  "geometry": {"coordinates":[76.57235300000001,28.683148],"type":"Point"}
}