{
  "type": "Feature",
  "properties": {
    "iso:country":"IN",
    "ks:ks_name":"Gardenpadar",
    "ks:ks_pop":137,
    "ks:ks_type":"VILLAGE",
    "name:eng_x_preferred":[
        "Gardenpadar"
    ],
    "wof:name":"Gardenpadar",
    "wof:placetype":"locality",
    "wof:population":137
},
  "geometry": {"coordinates":[82.185958,18.268011],"type":"Point"}
}