{
  "type": "Feature",
  "properties": {
    "iso:country":"IN",
    "ks:ks_name":"Gollapeta",
    "ks:ks_pop":63,
    "ks:ks_type":"HABITATION",
    "name:eng_x_preferred":[
        "Gollapeta"
    ],
    "wof:name":"Gollapeta",
    "wof:placetype":"locality",
    "wof:population":63
},
  "geometry": {"coordinates":[83.82421100000001,18.173044],"type":"Point"}
}