{
  "type": "Feature",
  "properties": {
    "iso:country":"IN",
    "ks:ks_alt_nam":"Lala purwa",
    "ks:ks_name":"Lala Purwa",
    "ks:ks_pop":203,
    "ks:ks_type":"HABITATION",
    "name:eng_x_preferred":[
        "Lala Purwa"
    ],
    "wof:name":"Lala Purwa",
    "wof:placetype":"locality",
    "wof:population":203
},
  "geometry": {"coordinates":[80.80756,27.655624],"type":"Point"}
}