{
  "type": "Feature",
  "properties": {
    "gn:admin1_code":"36.0",
    "gn:admin2_code":"161.0",
    "gn:asciiname":"Katela",
    "gn:country_code":"IN",
    "gn:dem":153,
    "gn:feature_class":"P",
    "gn:feature_code":"PPL",
    "gn:name":"Katela",
    "gn:population":0,
    "gn:timezone":"Asia/Kolkata",
    "iso:country":"IN",
    "name:est_x_preferred":[
        "Katela"
    ],
    "name:hye_x_preferred":[
        "\u053f\u0561\u057f\u0565\u056c\u0561"
    ],
    "name:pol_x_preferred":[
        "Katela"
    ],
    "name:vol_x_preferred":[
        "Katela"
    ],
    "wof:name":"Katela",
    "wof:placetype":"locality"
},
  "geometry": {"coordinates":[79.31961,26.86956],"type":"Point"}
}