{
  "type": "Feature",
  "properties": {
    "iso:country":"IN",
    "ks:ks_alt_nam":"East tola",
    "ks:ks_name":"East Tola",
    "ks:ks_pop":47,
    "ks:ks_type":"HABITATION",
    "name:eng_x_preferred":[
        "East Tola"
    ],
    "wof:name":"East Tola",
    "wof:placetype":"locality",
    "wof:population":47
},
  "geometry": {"coordinates":[86.82988,24.59975],"type":"Point"}
}