{
  "type": "Feature",
  "properties": {
    "gn:admin1_code":"37",
    "gn:admin2_code":"413.0",
    "gn:asciiname":"Karaki",
    "gn:country_code":"IN",
    "gn:dem":332,
    "gn:feature_class":"P",
    "gn:feature_code":"PPL",
    "gn:name":"Kar\u0101ki",
    "gn:population":0,
    "gn:timezone":"Asia/Kolkata",
    "iso:country":"IN",
    "ks:ks_alt_nam":"Kar\u0101ki",
    "ks:ks_name":"Karaki",
    "ks:ks_pop":581,
    "ks:ks_type":"VILLAGE",
    "name:eng_x_preferred":[
        "Karaki"
    ],
    "name:eng_x_variant":[
        "Kar\u0101ki"
    ],
    "wof:name":"Karaki",
    "wof:placetype":"locality",
    "wof:population":581
},
  "geometry": {"coordinates":[80.78088700000001,20.259823],"type":"Point"}
}