{
  "type": "Feature",
  "properties": {
    "iso:country":"IN",
    "ks:ks_name":"Futabhug",
    "ks:ks_pop":1331,
    "ks:ks_type":"VILLAGE",
    "name:eng_x_preferred":[
        "Futabhug"
    ],
    "wof:name":"Futabhug",
    "wof:placetype":"locality",
    "wof:population":1331
},
  "geometry": {"coordinates":[93.77113799999999,26.926202],"type":"Point"}
}