{
  "type": "Feature",
  "properties": {
    "iso:country":"IN",
    "ks:ks_name":"Tadhodia Falia",
    "ks:ks_pop":347,
    "ks:ks_type":"HABITATION",
    "name:eng_x_preferred":[
        "Tadhodia Falia"
    ],
    "wof:name":"Tadhodia Falia",
    "wof:placetype":"locality",
    "wof:population":347
},
  "geometry": {"coordinates":[73.870194,22.688722],"type":"Point"}
}