{
  "type": "Feature",
  "properties": {
    "gn:admin1_code":"35.0",
    "gn:admin2_code":"430.0",
    "gn:asciiname":"Sandoh",
    "gn:country_code":"IN",
    "gn:dem":108,
    "gn:feature_class":"P",
    "gn:feature_code":"PPL",
    "gn:name":"Sandoh",
    "gn:population":0,
    "gn:timezone":"Asia/Kolkata",
    "iso:country":"IN",
    "wof:name":"Sandoh",
    "wof:placetype":"locality"
},
  "geometry": {"coordinates":[81.63509000000001,25.04246],"type":"Point"}
}