{
  "type": "Feature",
  "properties": {
    "gn:admin1_code":"36",
    "gn:admin2_code":"143.0",
    "gn:asciiname":"Kanakpur",
    "gn:country_code":"IN",
    "gn:dem":185,
    "gn:feature_class":"P",
    "gn:feature_code":"PPL",
    "gn:name":"Kanakp\u016br",
    "gn:population":0,
    "gn:timezone":"Asia/Kolkata",
    "iso:country":"IN",
    "name:ceb_x_preferred":[
        "Kakanpur"
    ],
    "name:fra_x_preferred":[
        "Kakanpur"
    ],
    "name:mai_x_preferred":[
        "\u0915\u0928\u0915\u092a\u0942\u0930"
    ],
    "name:msa_x_preferred":[
        "Kakanpur"
    ],
    "name:nep_x_preferred":[
        "\u0915\u0928\u0915\u092a\u0942\u0930"
    ],
    "name:new_x_preferred":[
        "\u0915\u0915\u0928\u092a\u0941\u0930"
    ],
    "name:pol_x_preferred":[
        "Kakanpur"
    ],
    "wof:name":"Kanakpur",
    "wof:placetype":"locality"
},
  "geometry": {"coordinates":[78.38533000000002,28.09987000000001],"type":"Point"}
}