{
  "type": "Feature",
  "properties": {
    "iso:country":"IN",
    "ks:ks_name":"No.4 Sunapur Mazi",
    "ks:ks_pop":369,
    "ks:ks_type":"HABITATION",
    "name:eng_x_preferred":[
        "No.4 Sunapur Mazi"
    ],
    "wof:name":"No.4 Sunapur Mazi",
    "wof:placetype":"locality",
    "wof:population":369
},
  "geometry": {"coordinates":[94.32069,27.443996],"type":"Point"}
}