{
  "type": "Feature",
  "properties": {
    "iso:country":"IN",
    "ks:ks_name":"Boladi",
    "ks:ks_pop":264,
    "ks:ks_type":"HABITATION",
    "name:eng_x_preferred":[
        "Boladi"
    ],
    "wof:name":"Boladi",
    "wof:placetype":"locality",
    "wof:population":264
},
  "geometry": {"coordinates":[69.83516899999999,23.349889],"type":"Point"}
}