{
  "type": "Feature",
  "properties": {
    "iso:country":"IN",
    "ks:ks_alt_nam":"CHAVANWASTI",
    "ks:ks_name":"Chavanwasti",
    "ks:ks_pop":130,
    "ks:ks_type":"HABITATION",
    "name:eng_x_preferred":[
        "Chavanwasti"
    ],
    "wof:name":"Chavanwasti",
    "wof:placetype":"locality",
    "wof:population":130
},
  "geometry": {"coordinates":[74.84678599999999,16.913392],"type":"Point"}
}