{
  "type": "Feature",
  "properties": {
    "gn:admin1_code":"36",
    "gn:admin2_code":"168.0",
    "gn:asciiname":"Barbaspura",
    "gn:country_code":"IN",
    "gn:dem":142,
    "gn:feature_class":"P",
    "gn:feature_code":"PPL",
    "gn:name":"Barbaspura",
    "gn:population":0,
    "gn:timezone":"Asia/Kolkata",
    "iso:country":"IN",
    "name:eng_x_preferred":[
        "Barbaspura"
    ],
    "wof:name":"Barbaspura",
    "wof:placetype":"neighbourhood"
},
  "geometry": {"coordinates":[80.06243000000001,25.43329],"type":"Point"}
}