{
  "type": "Feature",
  "properties": {
    "iso:country":"IN",
    "ks:ks_name":"Kadime",
    "ks:ks_pop":366,
    "ks:ks_type":"HABITATION",
    "name:eng_x_preferred":[
        "Kadime"
    ],
    "wof:name":"Kadime",
    "wof:placetype":"locality",
    "wof:population":366
},
  "geometry": {"coordinates":[74.33080099999999,14.572605],"type":"Point"}
}