{
  "type": "Feature",
  "properties": {
    "gn:admin1_code":"11.0",
    "gn:admin2_code":"33.0",
    "gn:asciiname":"Manlog",
    "gn:country_code":"IN",
    "gn:dem":2227,
    "gn:feature_class":"P",
    "gn:feature_code":"PPL",
    "gn:name":"Manlog",
    "gn:population":0,
    "gn:timezone":"Asia/Kolkata",
    "iso:country":"IN",
    "wof:name":"Manlog",
    "wof:placetype":"locality"
},
  "geometry": {"coordinates":[77.44667,31.13759000000001],"type":"Point"}
}