{
  "type": "Feature",
  "properties": {
    "iso:country":"IN",
    "ks:ks_name":"Thodukulam",
    "ks:ks_pop":103,
    "ks:ks_type":"HABITATION",
    "name:eng_x_preferred":[
        "Thodukulam"
    ],
    "wof:name":"Thodukulam",
    "wof:placetype":"locality",
    "wof:population":103
},
  "geometry": {"coordinates":[78.680233,9.747555],"type":"Point"}
}