{
  "type": "Feature",
  "properties": {
    "iso:country":"IN",
    "ks:ks_name":"Assameralga",
    "ks:ks_pop":686,
    "ks:ks_type":"VILLAGE",
    "name:eng_x_preferred":[
        "Assameralga"
    ],
    "wof:name":"Assameralga",
    "wof:placetype":"locality",
    "wof:population":686
},
  "geometry": {"coordinates":[89.96078199999999,25.923549],"type":"Point"}
}