{
  "type": "Feature",
  "properties": {
    "iso:country":"IN",
    "ks:ks_name":"Amlatilla",
    "ks:ks_pop":179,
    "ks:ks_type":"HABITATION",
    "ks:ks_uagg_main":0,
    "name:eng_x_preferred":[
        "Amlatilla"
    ],
    "wof:name":"Amlatilla",
    "wof:placetype":"neighbourhood",
    "wof:population":179
},
  "geometry": {"coordinates":[91.946218,24.327645],"type":"Point"}
}