{
  "type": "Feature",
  "properties": {
    "gn:admin1_code":"25.0",
    "gn:admin2_code":"619.0",
    "gn:asciiname":"Kankoduttavanitam",
    "gn:country_code":"IN",
    "gn:dem":20,
    "gn:feature_class":"P",
    "gn:feature_code":"PPL",
    "gn:name":"Kankoduttavanitam",
    "gn:population":0,
    "gn:timezone":"Asia/Kolkata",
    "iso:country":"IN",
    "ks:ks_name":"Kankoduthavanitham",
    "ks:ks_pop":1002,
    "ks:ks_type":"VILLAGE",
    "ks:ks_uagg_main":0,
    "name:eng_x_preferred":[
        "Kankoduthavanitham"
    ],
    "wof:name":"Kankoduthavanitham",
    "wof:placetype":"neighbourhood",
    "wof:population":1002
},
  "geometry": {"coordinates":[79.540442,10.746269],"type":"Point"}
}