{
  "type": "Feature",
  "properties": {
    "iso:country":"IN",
    "ks:ks_name":"Tokojan Basti",
    "ks:ks_pop":860,
    "ks:ks_type":"HABITATION",
    "ks:ks_uagg_main":0,
    "name:eng_x_preferred":[
        "Tokojan Basti"
    ],
    "wof:name":"Tokojan Basti",
    "wof:placetype":"neighbourhood",
    "wof:population":860
},
  "geometry": {"coordinates":[93.77361000000001,26.153005],"type":"Point"}
}