{
  "type": "Feature",
  "properties": {
    "iso:country":"IN",
    "ks:ks_name":"Dumrahar Diara",
    "ks:ks_pop":0,
    "ks:ks_type":"VILLAGE",
    "name:eng_x_preferred":[
        "Dumrahar Diara"
    ],
    "wof:name":"Dumrahar Diara",
    "wof:placetype":"locality",
    "wof:population":0
},
  "geometry": {"coordinates":[84.05550599999999,26.103046],"type":"Point"}
}