{
  "type": "Feature",
  "properties": {
    "iso:country":"IN",
    "qs:name":"Andilo",
    "qs:name_adm0":"India",
    "qs:name_adm1":"Orissa",
    "qs:photos":90,
    "qs:photos_1k":18,
    "qs:photos_9k":1,
    "qs:photos_9r":3,
    "qs:photos_all":90,
    "qs:photos_sr":3,
    "qs:placetype":"Town",
    "qs:pop_sr":"0",
    "wof:name":"Andilo",
    "wof:placetype":"locality"
},
  "geometry": {"coordinates":[85.88077,20.3207835],"type":"Point"}
}