{
  "type": "Feature",
  "properties": {
    "gn:admin1_code":"36",
    "gn:admin2_code":"134.0",
    "gn:asciiname":"Milak",
    "gn:country_code":"IN",
    "gn:dem":253,
    "gn:feature_class":"P",
    "gn:feature_code":"PPL",
    "gn:name":"Milak",
    "gn:population":0,
    "gn:timezone":"Asia/Kolkata",
    "iso:country":"IN",
    "name:und_x_variant":[
        "Bhagw\u0101npur Prat\u0101p"
    ],
    "wof:name":"Milak",
    "wof:placetype":"locality"
},
  "geometry": {"coordinates":[78.38699,29.50368],"type":"Point"}
}