{
  "type": "Feature",
  "properties": {
    "gn:admin1_code":"39.0",
    "gn:admin2_code":"64.0",
    "gn:asciiname":"Taltai",
    "gn:country_code":"IN",
    "gn:dem":963,
    "gn:feature_class":"P",
    "gn:feature_code":"PPL",
    "gn:name":"Talt\u0101i",
    "gn:population":0,
    "gn:timezone":"Asia/Kolkata",
    "iso:country":"IN",
    "ks:ks_alt_nam":"Talt\u0101i",
    "ks:ks_name":"Taltai",
    "ks:ks_type":"VILLAGE",
    "name:eng_x_preferred":[
        "Taltai"
    ],
    "name:eng_x_variant":[
        "Talt\u0101i"
    ],
    "wof:name":"Taltai",
    "wof:placetype":"locality"
},
  "geometry": {"coordinates":[79.243213,29.810823],"type":"Point"}
}