{
  "type": "Feature",
  "properties": {
    "iso:country":"IN",
    "ks:ks_name":"Dombabeda",
    "ks:ks_pop":78,
    "ks:ks_type":"HABITATION",
    "name:eng_x_preferred":[
        "Dombabeda"
    ],
    "wof:name":"Dombabeda",
    "wof:placetype":"locality",
    "wof:population":78
},
  "geometry": {"coordinates":[82.389304,18.621327],"type":"Point"}
}