{
  "type": "Feature",
  "properties": {
    "iso:country":"IN",
    "ks:ks_name":"Borkatri",
    "ks:ks_pop":497,
    "ks:ks_type":"HABITATION",
    "name:eng_x_preferred":[
        "Borkatri"
    ],
    "wof:name":"Borkatri",
    "wof:placetype":"locality",
    "wof:population":497
},
  "geometry": {"coordinates":[74.79224600000001,16.694226],"type":"Point"}
}