{
  "type": "Feature",
  "properties": {
    "iso:country":"IN",
    "ks:ks_name":"Jajoli Gaon",
    "ks:ks_pop":1143,
    "ks:ks_type":"VILLAGE",
    "name:eng_x_preferred":[
        "Jajoli Gaon"
    ],
    "wof:name":"Jajoli Gaon",
    "wof:placetype":"locality",
    "wof:population":1143
},
  "geometry": {"coordinates":[94.931759,27.076083],"type":"Point"}
}