{
  "type": "Feature",
  "properties": {
    "gn:admin1_code":"36",
    "gn:admin2_code":"154.0",
    "gn:asciiname":"Ghaznipur",
    "gn:country_code":"IN",
    "gn:dem":133,
    "gn:feature_class":"P",
    "gn:feature_code":"PPL",
    "gn:name":"Ghaznipur",
    "gn:population":0,
    "gn:timezone":"Asia/Kolkata",
    "iso:country":"IN",
    "wof:name":"Ghaznipur",
    "wof:placetype":"neighbourhood"
},
  "geometry": {"coordinates":[80.97727,27.5627],"type":"Point"}
}