{
  "type": "Feature",
  "properties": {
    "gn:admin1_code":"35.0",
    "gn:admin2_code":"449.0",
    "gn:asciiname":"Akola",
    "gn:country_code":"IN",
    "gn:dem":332,
    "gn:feature_class":"P",
    "gn:feature_code":"PPL",
    "gn:name":"Akola",
    "gn:population":0,
    "gn:timezone":"Asia/Kolkata",
    "iso:country":"IN",
    "wof:name":"Akola",
    "wof:placetype":"locality"
},
  "geometry": {"coordinates":[78.25277,22.7496],"type":"Point"}
}