{
  "type": "Feature",
  "properties": {
    "iso:country":"IN",
    "ks:ks_name":"Devsipur",
    "ks:ks_pop":198,
    "ks:ks_type":"HABITATION",
    "name:eng_x_preferred":[
        "Devsipur"
    ],
    "wof:name":"Devsipur",
    "wof:placetype":"locality",
    "wof:population":198
},
  "geometry": {"coordinates":[83.331177,25.909219],"type":"Point"}
}