{
  "type": "Feature",
  "properties": {
    "iso:country":"IN",
    "ks:ks_name":"Pubung Busty",
    "ks:ks_pop":920,
    "ks:ks_type":"HABITATION",
    "name:eng_x_preferred":[
        "Pubung Busty"
    ],
    "wof:name":"Pubung Busty",
    "wof:placetype":"locality",
    "wof:population":920
},
  "geometry": {"coordinates":[88.196674,26.999959],"type":"Point"}
}