{
  "type": "Feature",
  "properties": {
    "iso:country":"IN",
    "ks:ks_name":"Upadhya Purwa",
    "ks:ks_pop":94,
    "ks:ks_type":"HABITATION",
    "name:eng_x_preferred":[
        "Upadhya Purwa"
    ],
    "wof:name":"Upadhya Purwa",
    "wof:placetype":"locality",
    "wof:population":94
},
  "geometry": {"coordinates":[82.663533,26.745676],"type":"Point"}
}