{
  "type": "Feature",
  "properties": {
    "gn:admin1_code":"34.0",
    "gn:admin2_code":"240.0",
    "gn:asciiname":"Chainpur",
    "gn:country_code":"IN",
    "gn:dem":82,
    "gn:feature_class":"P",
    "gn:feature_code":"PPL",
    "gn:name":"Chainpur",
    "gn:population":0,
    "gn:timezone":"Asia/Kolkata",
    "iso:country":"IN",
    "name:ceb_x_preferred":[
        "Chainpur"
    ],
    "name:deu_x_preferred":[
        "Chainpur"
    ],
    "name:nep_x_preferred":[
        "\u091a\u0948\u0928\u092a\u0941\u0930"
    ],
    "name:new_x_preferred":[
        "\u091a\u0948\u0928\u092a\u0941\u0930"
    ],
    "name:pol_x_preferred":[
        "Chainpur"
    ],
    "wof:name":"Chainpur",
    "wof:placetype":"neighbourhood"
},
  "geometry": {"coordinates":[84.66806,25.14112],"type":"Point"}
}