{
  "type": "Feature",
  "properties": {
    "iso:country":"IN",
    "ks:ks_name":"Tetelgaon",
    "ks:ks_pop":694,
    "ks:ks_type":"HABITATION",
    "name:eng_x_preferred":[
        "Tetelgaon"
    ],
    "wof:name":"Tetelgaon",
    "wof:placetype":"locality",
    "wof:population":694
},
  "geometry": {"coordinates":[83.600639,20.976531],"type":"Point"}
}