{
  "type": "Feature",
  "properties": {
    "iso:country":"IN",
    "ks:ks_name":"Nirail",
    "ks:ks_pop":1189,
    "ks:ks_type":"VILLAGE",
    "name:eng_x_preferred":[
        "Nirail"
    ],
    "wof:name":"Nirail",
    "wof:placetype":"locality",
    "wof:population":1189
},
  "geometry": {"coordinates":[88.31303800000001,25.050644],"type":"Point"}
}