{
  "type": "Feature",
  "properties": {
    "gn:admin1_code":"36",
    "gn:admin2_code":"193.0",
    "gn:asciiname":"Kusaha Khurd",
    "gn:country_code":"IN",
    "gn:dem":72,
    "gn:feature_class":"P",
    "gn:feature_code":"PPL",
    "gn:name":"Kusah\u0101 Khurd",
    "gn:population":0,
    "gn:timezone":"Asia/Kolkata",
    "iso:country":"IN",
    "ks:ks_name":"Kusha Khurd",
    "ks:ks_pop":319,
    "ks:ks_type":"VILLAGE",
    "name:eng_x_preferred":[
        "Kusha Khurd"
    ],
    "name:eng_x_variant":[
        "Kusaha Khurd"
    ],
    "wof:name":"Kusha Khurd",
    "wof:placetype":"locality",
    "wof:population":319
},
  "geometry": {"coordinates":[83.798101,25.858684],"type":"Point"}
}