{
  "type": "Feature",
  "properties": {
    "iso:country":"IN",
    "ks:ks_name":"Jhil Pura",
    "ks:ks_pop":90,
    "ks:ks_type":"HABITATION",
    "name:eng_x_preferred":[
        "Jhil Pura"
    ],
    "wof:name":"Jhil Pura",
    "wof:placetype":"locality",
    "wof:population":90
},
  "geometry": {"coordinates":[78.18429500000001,26.987444],"type":"Point"}
}