{
  "type": "Feature",
  "properties": {
    "gn:admin1_code":"35",
    "gn:admin2_code":"429.0",
    "gn:asciiname":"Kangar",
    "gn:country_code":"IN",
    "gn:dem":394,
    "gn:feature_class":"P",
    "gn:feature_code":"PPL",
    "gn:name":"Kang\u0101r",
    "gn:population":0,
    "gn:timezone":"Asia/Kolkata",
    "iso:country":"IN",
    "name:und_x_variant":[
        "Kang\u0101r",
        "Kangar"
    ],
    "wof:name":"Kangar",
    "wof:placetype":"locality"
},
  "geometry": {"coordinates":[80.60616,24.76419],"type":"Point"}
}