{
  "type": "Feature",
  "properties": {
    "iso:country":"IN",
    "ks:ks_name":"Shivpur",
    "ks:ks_pop":265,
    "ks:ks_type":"HABITATION",
    "name:eng_x_preferred":[
        "Shivpur"
    ],
    "wof:name":"Shivpur",
    "wof:placetype":"locality",
    "wof:population":265
},
  "geometry": {"coordinates":[83.081171,27.386175],"type":"Point"}
}