{
  "type": "Feature",
  "properties": {
    "gn:admin1_code":"36.0",
    "gn:admin2_code":"180.0",
    "gn:asciiname":"Haidarabad",
    "gn:country_code":"IN",
    "gn:dem":109,
    "gn:feature_class":"P",
    "gn:feature_code":"PPL",
    "gn:name":"Haidarab\u0101d",
    "gn:population":0,
    "gn:timezone":"Asia/Kolkata",
    "iso:country":"IN",
    "wof:name":"Haidarabad",
    "wof:placetype":"locality"
},
  "geometry": {"coordinates":[81.62623000000001,27.23532],"type":"Point"}
}