{
  "type": "Feature",
  "properties": {
    "iso:country":"IN",
    "ks:ks_name":"Nimursingha",
    "ks:ks_pop":124,
    "ks:ks_type":"VILLAGE",
    "name:eng_x_preferred":[
        "Nimursingha"
    ],
    "wof:name":"Nimursingha",
    "wof:placetype":"locality",
    "wof:population":124
},
  "geometry": {"coordinates":[83.589958,20.407585],"type":"Point"}
}