{
  "type": "Feature",
  "properties": {
    "gn:admin1_code":"36",
    "gn:admin2_code":"177.0",
    "gn:asciiname":"Achari Purwa",
    "gn:country_code":"IN",
    "gn:dem":104,
    "gn:feature_class":"P",
    "gn:feature_code":"PPL",
    "gn:name":"Ach\u0101ri Purwa",
    "gn:population":0,
    "gn:timezone":"Asia/Kolkata",
    "iso:country":"IN",
    "wof:name":"Achari Purwa",
    "wof:placetype":"locality"
},
  "geometry": {"coordinates":[82.19818000000002,26.74598],"type":"Point"}
}