{
  "type": "Feature",
  "properties": {
    "iso:country":"IN",
    "ks:ks_alt_nam":"nadi par tola",
    "ks:ks_name":"Nadi Par Tola",
    "ks:ks_pop":260,
    "ks:ks_type":"HABITATION",
    "name:eng_x_preferred":[
        "Nadi Par Tola"
    ],
    "wof:name":"Nadi Par Tola",
    "wof:placetype":"locality",
    "wof:population":260
},
  "geometry": {"coordinates":[86.514188,24.579825],"type":"Point"}
}