{
  "type": "Feature",
  "properties": {
    "gn:admin1_code":"35.0",
    "gn:admin2_code":"431",
    "gn:asciiname":"Bharhut",
    "gn:country_code":"IN",
    "gn:dem":474,
    "gn:feature_class":"P",
    "gn:feature_code":"PPL",
    "gn:name":"Bharhut",
    "gn:population":0,
    "gn:timezone":"Asia/Kolkata",
    "iso:country":"IN",
    "name:ces_x_preferred":[
        "Bh\u00e1rhut"
    ],
    "name:deu_x_preferred":[
        "Bharhut"
    ],
    "name:fra_x_preferred":[
        "Bharhut"
    ],
    "name:hin_x_preferred":[
        "\u092d\u0930\u0939\u0941\u0924"
    ],
    "name:mar_x_preferred":[
        "\u092d\u0930\u0939\u0941\u0924"
    ],
    "name:nld_x_preferred":[
        "Bharhut"
    ],
    "name:spa_x_preferred":[
        "Bharhut"
    ],
    "name:tam_x_preferred":[
        "\u0baa\u0bb0\u0bcd\u0b95\u0bc1\u0b9f\u0bcd"
    ],
    "wof:name":"Bharhut",
    "wof:placetype":"locality"
},
  "geometry": {"coordinates":[80.96167,23.51362],"type":"Point"}
}