{
  "type": "Feature",
  "properties": {
    "iso:country":"IN",
    "ks:ks_name":"Nehru Nagar Tanda",
    "ks:ks_pop":488,
    "ks:ks_type":"HABITATION",
    "name:eng_x_preferred":[
        "Nehru Nagar Tanda"
    ],
    "wof:name":"Nehru Nagar Tanda",
    "wof:placetype":"locality",
    "wof:population":488
},
  "geometry": {"coordinates":[76.548919,17.520493],"type":"Point"}
}