{
  "type": "Feature",
  "properties": {
    "iso:country":"IN",
    "ks:ks_name":"Kubudadihi",
    "ks:ks_pop":701,
    "ks:ks_type":"HABITATION",
    "name:eng_x_preferred":[
        "Kubudadihi"
    ],
    "wof:name":"Kubudadihi",
    "wof:placetype":"locality",
    "wof:population":701
},
  "geometry": {"coordinates":[82.085599,19.919452],"type":"Point"}
}