{
  "type": "Feature",
  "properties": {
    "gn:admin1_code":"2.0",
    "gn:admin2_code":"554.0",
    "gn:asciiname":"Halasapuram",
    "gn:country_code":"IN",
    "gn:dem":724,
    "gn:feature_class":"P",
    "gn:feature_code":"PPL",
    "gn:name":"Halas\u0101puram",
    "gn:population":0,
    "gn:timezone":"Asia/Kolkata",
    "iso:country":"IN",
    "wof:name":"Halasapuram",
    "wof:placetype":"neighbourhood"
},
  "geometry": {"coordinates":[78.66364,13.32746],"type":"Point"}
}