{
  "type": "Feature",
  "properties": {
    "gn:admin1_code":"12",
    "gn:admin2_code":"15.0",
    "gn:asciiname":"Kontsu",
    "gn:country_code":"IN",
    "gn:dem":1654,
    "gn:feature_class":"P",
    "gn:feature_code":"PPL",
    "gn:name":"Konts\u016b",
    "gn:population":0,
    "gn:timezone":"Asia/Kolkata",
    "iso:country":"IN",
    "wof:name":"Kontsu",
    "wof:placetype":"locality"
},
  "geometry": {"coordinates":[75.06376999999998,33.66561],"type":"Point"}
}