{
  "type": "Feature",
  "properties": {
    "gn:admin1_code":"35",
    "gn:admin2_code":"456.0",
    "gn:asciiname":"Pempur",
    "gn:country_code":"IN",
    "gn:dem":638,
    "gn:feature_class":"P",
    "gn:feature_code":"PPL",
    "gn:name":"Pempur",
    "gn:population":0,
    "gn:timezone":"Asia/Kolkata",
    "iso:country":"IN",
    "ks:ks_name":"Prempur",
    "ks:ks_pop":368,
    "ks:ks_type":"HABITATION",
    "ks:ks_uagg_main":0,
    "name:eng_x_preferred":[
        "Prempur"
    ],
    "wof:name":"Prempur",
    "wof:placetype":"neighbourhood",
    "wof:population":368
},
  "geometry": {"coordinates":[79.737668,22.588415],"type":"Point"}
}