{
  "type": "Feature",
  "properties": {
    "iso:country":"IN",
    "ks:ks_name":"Dharleto",
    "ks:ks_pop":398,
    "ks:ks_type":"VILLAGE",
    "ks:ks_uagg_main":0,
    "name:eng_x_preferred":[
        "Dharleto"
    ],
    "wof:name":"Dharleto",
    "wof:placetype":"neighbourhood",
    "wof:population":398
},
  "geometry": {"coordinates":[86.428093,24.193041],"type":"Point"}
}