{
  "type": "Feature",
  "properties": {
    "gn:admin1_code":"25.0",
    "gn:admin2_code":"611.0",
    "gn:asciiname":"Pakkam",
    "gn:country_code":"IN",
    "gn:dem":953,
    "gn:feature_class":"P",
    "gn:feature_code":"PPL",
    "gn:name":"Pakkam",
    "gn:population":0,
    "gn:timezone":"Asia/Kolkata",
    "iso:country":"IN",
    "wof:name":"Pakkam",
    "wof:placetype":"locality"
},
  "geometry": {"coordinates":[76.47573,11.56129],"type":"Point"}
}