{
  "type": "Feature",
  "properties": {
    "iso:country":"IN",
    "ks:ks_alt_nam":"konnadu",
    "ks:ks_name":"Konnadu",
    "ks:ks_pop":850,
    "ks:ks_type":"HABITATION",
    "name:eng_x_preferred":[
        "Konnadu"
    ],
    "wof:name":"Konnadu",
    "wof:placetype":"locality",
    "wof:population":850
},
  "geometry": {"coordinates":[76.29395599999999,11.553574],"type":"Point"}
}