{
  "type": "Feature",
  "properties": {
    "iso:country":"IN",
    "name:bpy_x_preferred":[
        "\u0986\u09ae\u09cd\u09ae\u09be\u0987\u09a8\u09be\u0987\u0995\u09be\u09a8\u09c1\u09b0"
    ],
    "name:eng_x_preferred":[
        "Ammainaickanur"
    ],
    "name:fas_x_preferred":[
        "\u0627\u0645\u0627\u06cc\u0646\u0627\u06cc\u06a9\u0627\u0646\u0648\u0631"
    ],
    "name:fra_x_preferred":[
        "Ammainaickanur"
    ],
    "name:ita_x_preferred":[
        "Ammainaickanur"
    ],
    "name:min_x_preferred":[
        "Ammainaickanur"
    ],
    "name:msa_x_preferred":[
        "Ammainaickanur"
    ],
    "name:nan_x_preferred":[
        "Ammainaickanur"
    ],
    "name:new_x_preferred":[
        "\u0905\u092e\u094d\u092e\u0928\u0948\u0915\u0928\u0941\u0930"
    ],
    "name:nld_x_preferred":[
        "Ammainaickanur"
    ],
    "name:por_x_preferred":[
        "Ammainaickanur"
    ],
    "name:tam_x_preferred":[
        "\u0b85\u0bae\u0bcd\u0bae\u0bc8\u0ba8\u0bbe\u0baf\u0b95\u0bcd\u0b95\u0ba9\u0bc2\u0bb0\u0bcd"
    ],
    "name:vie_x_preferred":[
        "Ammainaickanur"
    ],
    "name:zho_x_preferred":[
        "\u963f\u8fc8\u5948\u5361\u52aa\u5c14"
    ],
    "qs:name":"Ammainaickanur",
    "qs:name_adm0":"India",
    "qs:name_adm1":"Tamil Nadu",
    "qs:photos":11,
    "qs:photos_1k":2,
    "qs:photos_9k":1,
    "qs:photos_9r":1,
    "qs:photos_all":11,
    "qs:photos_sr":1,
    "qs:placetype":"Town",
    "qs:pop_sr":"0",
    "wd:wordcount":103,
    "wof:name":"Ammainaickanur",
    "wof:placetype":"locality"
},
  "geometry": {"coordinates":[77.90697299999999,10.232961],"type":"Point"}
}