{
  "type": "Feature",
  "properties": {
    "iso:country":"IN",
    "ks:ks_name":"Parsauri",
    "ks:ks_pop":731,
    "ks:ks_type":"VILLAGE",
    "ks:ks_uagg_main":0,
    "name:eng_x_preferred":[
        "Parsauri"
    ],
    "wof:name":"Parsauri",
    "wof:placetype":"neighbourhood",
    "wof:population":731
},
  "geometry": {"coordinates":[83.003291,25.54911],"type":"Point"}
}