{
  "type": "Feature",
  "properties": {
    "gn:admin1_code":"16",
    "gn:admin2_code":"515.0",
    "gn:asciiname":"Vakad",
    "gn:country_code":"IN",
    "gn:dem":623,
    "gn:feature_class":"P",
    "gn:feature_code":"PPL",
    "gn:name":"V\u0101kad",
    "gn:population":0,
    "gn:timezone":"Asia/Kolkata",
    "iso:country":"IN",
    "wof:name":"Vakad",
    "wof:placetype":"locality"
},
  "geometry": {"coordinates":[75.48311,20.15393],"type":"Point"}
}