{
  "type": "Feature",
  "properties": {
    "iso:country":"IN",
    "ks:ks_name":"Talebail",
    "ks:ks_pop":1215,
    "ks:ks_type":"HABITATION",
    "name:eng_x_preferred":[
        "Talebail"
    ],
    "wof:name":"Talebail",
    "wof:placetype":"locality",
    "wof:population":1215
},
  "geometry": {"coordinates":[74.29844799999999,14.632479],"type":"Point"}
}