{
  "type": "Feature",
  "properties": {
    "iso:country":"IN",
    "ks:ks_name":"Rehri",
    "ks:ks_pop":275,
    "ks:ks_type":"HABITATION",
    "ks:ks_uagg_main":0,
    "name:eng_x_preferred":[
        "Rehri"
    ],
    "wof:name":"Rehri",
    "wof:placetype":"neighbourhood",
    "wof:population":275
},
  "geometry": {"coordinates":[81.950852,26.580677],"type":"Point"}
}