{
  "type": "Feature",
  "properties": {
    "iso:country":"IN",
    "ks:ks_name":"Salhaya",
    "ks:ks_pop":690,
    "ks:ks_type":"VILLAGE",
    "ks:ks_uagg_main":0,
    "name:eng_x_preferred":[
        "Salhaya"
    ],
    "wof:name":"Salhaya",
    "wof:placetype":"neighbourhood",
    "wof:population":690
},
  "geometry": {"coordinates":[81.734818,22.251992],"type":"Point"}
}