{
  "type": "Feature",
  "properties": {
    "iso:country":"IN",
    "ks:ks_name":"Mutnaza Lara Larni",
    "ks:ks_pop":0,
    "ks:ks_type":"VILLAGE",
    "name:eng_x_preferred":[
        "Mutnaza Lara Larni"
    ],
    "wof:name":"Mutnaza Lara Larni",
    "wof:placetype":"locality",
    "wof:population":0
},
  "geometry": {"coordinates":[85.855594,26.086378],"type":"Point"}
}