{
  "type": "Feature",
  "properties": {
    "gn:admin1_code":"36",
    "gn:admin2_code":"178.0",
    "gn:asciiname":"Tandwa Misr",
    "gn:country_code":"IN",
    "gn:dem":91,
    "gn:feature_class":"P",
    "gn:feature_code":"PPL",
    "gn:name":"Tandwa Misr",
    "gn:population":0,
    "gn:timezone":"Asia/Kolkata",
    "iso:country":"IN",
    "wof:name":"Tandwa Misr",
    "wof:placetype":"locality"
},
  "geometry": {"coordinates":[82.76398,26.48814],"type":"Point"}
}