{
  "type": "Feature",
  "properties": {
    "gn:admin1_code":"17",
    "gn:admin2_code":"273.0",
    "gn:asciiname":"Lagairong",
    "gn:country_code":"IN",
    "gn:dem":797,
    "gn:feature_class":"P",
    "gn:feature_code":"PPL",
    "gn:name":"Lagairong",
    "gn:population":0,
    "gn:timezone":"Asia/Kolkata",
    "iso:country":"IN",
    "wof:name":"Lagairong",
    "wof:placetype":"locality"
},
  "geometry": {"coordinates":[93.51708000000001,24.69529],"type":"Point"}
}