{
  "type": "Feature",
  "properties": {
    "iso:country":"IN",
    "ks:ks_name":"Angrolli Hosur",
    "ks:ks_pop":18,
    "ks:ks_type":"HABITATION",
    "name:eng_x_preferred":[
        "Angrolli Hosur"
    ],
    "wof:name":"Angrolli Hosur",
    "wof:placetype":"locality",
    "wof:population":18
},
  "geometry": {"coordinates":[74.79876299999999,15.323527],"type":"Point"}
}