{
  "type": "Feature",
  "properties": {
    "gn:admin1_code":"36.0",
    "gn:admin2_code":"164.0",
    "gn:asciiname":"Mangrasa",
    "gn:country_code":"IN",
    "gn:dem":128,
    "gn:feature_class":"P",
    "gn:feature_code":"PPL",
    "gn:name":"Mangr\u0101sa",
    "gn:population":0,
    "gn:timezone":"Asia/Kolkata",
    "iso:country":"IN",
    "ks:ks_name":"Magrasa",
    "ks:ks_pop":1795,
    "ks:ks_type":"VILLAGE",
    "ks:ks_uagg_main":0,
    "name:eng_x_preferred":[
        "Magrasa"
    ],
    "wof:name":"Magrasa",
    "wof:placetype":"neighbourhood",
    "wof:population":1795
},
  "geometry": {"coordinates":[80.2975,26.351389],"type":"Point"}
}