{
  "type": "Feature",
  "properties": {
    "gn:admin1_code":"13.0",
    "gn:admin2_code":"596.0",
    "gn:asciiname":"Vadakamalai",
    "gn:country_code":"IN",
    "gn:dem":434,
    "gn:feature_class":"P",
    "gn:feature_code":"PPL",
    "gn:name":"Vadakamalai",
    "gn:population":0,
    "gn:timezone":"Asia/Kolkata",
    "iso:country":"IN",
    "wof:name":"Vadakamalai",
    "wof:placetype":"locality"
},
  "geometry": {"coordinates":[76.90992,9.60287],"type":"Point"}
}