{
  "type": "Feature",
  "properties": {
    "iso:country":"IN",
    "ks:ks_name":"Gumma Digagumma",
    "ks:ks_pop":64,
    "ks:ks_type":"HABITATION",
    "name:eng_x_preferred":[
        "Gumma Digagumma"
    ],
    "wof:name":"Gumma Digagumma",
    "wof:placetype":"locality",
    "wof:population":64
},
  "geometry": {"coordinates":[82.37503599999999,18.412993],"type":"Point"}
}