{
  "type": "Feature",
  "properties": {
    "gn:admin1_code":"34.0",
    "gn:admin2_code":"220.0",
    "gn:asciiname":"Balghat Bharatpur",
    "gn:country_code":"IN",
    "gn:dem":53,
    "gn:feature_class":"P",
    "gn:feature_code":"PPL",
    "gn:name":"Balgh\u0101t Bharatpur",
    "gn:population":0,
    "gn:timezone":"Asia/Kolkata",
    "iso:country":"IN",
    "ks:ks_name":"Balghat Bharathpur",
    "ks:ks_pop":143,
    "ks:ks_type":"VILLAGE",
    "name:eng_x_preferred":[
        "Balghat Bharathpur"
    ],
    "name:eng_x_variant":[
        "Balghat Bharatpur"
    ],
    "wof:name":"Balghat Bharathpur",
    "wof:placetype":"locality",
    "wof:population":143
},
  "geometry": {"coordinates":[85.457865,25.770116],"type":"Point"}
}