{
  "type": "Feature",
  "properties": {
    "iso:country":"IN",
    "ks:ks_name":"Chapia Bari",
    "ks:ks_pop":295,
    "ks:ks_type":"HABITATION",
    "name:eng_x_preferred":[
        "Chapia Bari"
    ],
    "wof:name":"Chapia Bari",
    "wof:placetype":"locality",
    "wof:population":295
},
  "geometry": {"coordinates":[91.620926,23.536677],"type":"Point"}
}