{
  "type": "Feature",
  "properties": {
    "iso:country":"IN",
    "ks:ks_name":"Kimbhiri",
    "ks:ks_pop":31,
    "ks:ks_type":"VILLAGE",
    "name:eng_x_preferred":[
        "Kimbhiri"
    ],
    "wof:name":"Kimbhiri",
    "wof:placetype":"locality",
    "wof:population":31
},
  "geometry": {"coordinates":[84.85660900000001,20.098432],"type":"Point"}
}