{
  "type": "Feature",
  "properties": {
    "iso:country":"IN",
    "ks:ks_name":"Chhani Gaon",
    "ks:ks_pop":53,
    "ks:ks_type":"VILLAGE",
    "name:eng_x_preferred":[
        "Chhani Gaon"
    ],
    "wof:name":"Chhani Gaon",
    "wof:placetype":"locality",
    "wof:population":53
},
  "geometry": {"coordinates":[78.036601,30.589945],"type":"Point"}
}