{
  "type": "Feature",
  "properties": {
    "iso:country":"IN",
    "ks:ks_name":"Gadiyapudi",
    "ks:ks_pop":1358,
    "ks:ks_type":"VILLAGE",
    "name:eng_x_preferred":[
        "Gadiyapudi"
    ],
    "wof:name":"Gadiyapudi",
    "wof:placetype":"locality",
    "wof:population":1358
},
  "geometry": {"coordinates":[79.967928,15.693334],"type":"Point"}
}