{
  "type": "Feature",
  "properties": {
    "iso:country":"IN",
    "ks:ks_alt_nam":"Dabhi tanda",
    "ks:ks_name":"Dabhi Tanda",
    "ks:ks_pop":421,
    "ks:ks_type":"HABITATION",
    "name:eng_x_preferred":[
        "Dabhi Tanda"
    ],
    "wof:name":"Dabhi Tanda",
    "wof:placetype":"locality",
    "wof:population":421
},
  "geometry": {"coordinates":[76.472577,18.85223],"type":"Point"}
}