{
  "type": "Feature",
  "properties": {
    "iso:country":"IN",
    "ks:ks_name":"Rahmoria",
    "ks:ks_pop":579,
    "ks:ks_type":"HABITATION",
    "name:eng_x_preferred":[
        "Rahmoria"
    ],
    "wof:name":"Rahmoria",
    "wof:placetype":"locality",
    "wof:population":579
},
  "geometry": {"coordinates":[95.10081700000001,27.538374],"type":"Point"}
}