{
  "type": "Feature",
  "properties": {
    "iso:country":"IN",
    "ks:ks_name":"Maldar",
    "ks:ks_pop":838,
    "ks:ks_type":"VILLAGE",
    "name:eng_x_preferred":[
        "Maldar"
    ],
    "wof:name":"Maldar",
    "wof:placetype":"locality",
    "wof:population":838
},
  "geometry": {"coordinates":[73.00254700000001,24.915489],"type":"Point"}
}