{
  "type": "Feature",
  "properties": {
    "gn:admin1_code":"13.0",
    "gn:admin2_code":"593.0",
    "gn:asciiname":"Mangalamkunnu",
    "gn:country_code":"IN",
    "gn:dem":122,
    "gn:feature_class":"P",
    "gn:feature_code":"PPL",
    "gn:name":"Mangalamkunnu",
    "gn:population":0,
    "gn:timezone":"Asia/Kolkata",
    "iso:country":"IN",
    "wof:name":"Mangalamkunnu",
    "wof:placetype":"locality"
},
  "geometry": {"coordinates":[76.39674000000002,10.88812],"type":"Point"}
}