{
  "type": "Feature",
  "properties": {
    "iso:country":"IN",
    "ks:ks_name":"Pundra",
    "ks:ks_pop":430,
    "ks:ks_type":"VILLAGE",
    "name:eng_x_preferred":[
        "Pundra"
    ],
    "wof:name":"Pundra",
    "wof:placetype":"locality",
    "wof:population":430
},
  "geometry": {"coordinates":[86.72086899999999,21.893784],"type":"Point"}
}