{
  "type": "Feature",
  "properties": {
    "gn:admin1_code":"2.0",
    "gn:admin2_code":"553.0",
    "gn:asciiname":"Rayapuram",
    "gn:country_code":"IN",
    "gn:dem":651,
    "gn:feature_class":"P",
    "gn:feature_code":"PPL",
    "gn:name":"R\u0101y\u0101puram",
    "gn:population":0,
    "gn:timezone":"Asia/Kolkata",
    "iso:country":"IN",
    "name:ara_x_preferred":[
        "\u0631\u0648\u064a\u0627\u0628\u0648\u0631\u0627\u0645"
    ],
    "name:ben_bn_x_preferred":[
        "\u09b0\u09be\u09df\u09be\u09aa\u09c1\u09b0\u09ae"
    ],
    "name:ben_in_x_preferred":[
        "\u09b0\u09be\u09df\u09be\u09aa\u09c1\u09b0\u09ae"
    ],
    "name:guj_x_preferred":[
        "\u0ab0\u0aaf\u0abe\u0aaa\u0ac1\u0ab0\u0aae"
    ],
    "name:hin_x_preferred":[
        "\u0930\u093e\u092f\u093e\u092a\u0941\u0930\u092e"
    ],
    "name:kan_x_preferred":[
        "\u0cb0\u0cbe\u0caf\u0ca8\u0caa\u0cc1\u0cb0\u0c82"
    ],
    "name:mal_x_preferred":[
        "\u0d31\u0d3e\u0d2f\u0d2a\u0d41\u0d30\u0d02"
    ],
    "name:mar_x_preferred":[
        "\u0930\u093e\u092f\u092a\u0941\u0930\u092e"
    ],
    "name:pan_x_preferred":[
        "\u0a30\u0a3e\u0a07\u0a06\u0a2a\u0a41\u0a30\u0a2e"
    ],
    "name:tam_x_preferred":[
        "\u0bb0\u0bbe\u0baf\u0baa\u0bc1\u0bb0\u0bae\u0bcd"
    ],
    "name:tel_x_preferred":[
        "\u0c30\u0c3e\u0c2f\u0c2a\u0c41\u0c30\u0c02"
    ],
    "name:urd_x_preferred":[
        "\u0631\u0627\u06cc\u0627 \u067e\u0648\u0631\u0645"
    ],
    "wof:name":"Rayapuram",
    "wof:placetype":"locality"
},
  "geometry": {"coordinates":[77.32066999999998,13.91471],"type":"Point"}
}