{
  "type": "Feature",
  "properties": {
    "iso:country":"IN",
    "ks:ks_name":"Bagrikhuti No 1",
    "ks:ks_pop":587,
    "ks:ks_type":"VILLAGE",
    "ks:ks_uagg_main":0,
    "name:eng_x_preferred":[
        "Bagrikhuti No 1"
    ],
    "wof:name":"Bagrikhuti No 1",
    "wof:placetype":"neighbourhood",
    "wof:population":587
},
  "geometry": {"coordinates":[91.673976,26.749292],"type":"Point"}
}