{
  "type": "Feature",
  "properties": {
    "gn:admin1_code":"36.0",
    "gn:admin2_code":"135.0",
    "gn:asciiname":"Qaziwala",
    "gn:country_code":"IN",
    "gn:dem":187,
    "gn:feature_class":"P",
    "gn:feature_code":"PPL",
    "gn:name":"Q\u0101z\u012bw\u0101la",
    "gn:population":0,
    "gn:timezone":"Asia/Kolkata",
    "iso:country":"IN",
    "wof:name":"Qaziwala",
    "wof:placetype":"neighbourhood"
},
  "geometry": {"coordinates":[78.87336000000001,28.52621],"type":"Point"}
}