{
  "type": "Feature",
  "properties": {
    "iso:country":"IN",
    "ks:ks_name":"Umreila Malla",
    "ks:ks_pop":85,
    "ks:ks_type":"VILLAGE",
    "name:eng_x_preferred":[
        "Umreila Malla"
    ],
    "wof:name":"Umreila Malla",
    "wof:placetype":"locality",
    "wof:population":85
},
  "geometry": {"coordinates":[78.579055,29.80376],"type":"Point"}
}