{
  "type": "Feature",
  "properties": {
    "gn:admin1_code":"36",
    "gn:admin2_code":"180.0",
    "gn:asciiname":"Chandpara",
    "gn:country_code":"IN",
    "gn:dem":120,
    "gn:feature_class":"P",
    "gn:feature_code":"PPL",
    "gn:name":"Ch\u0101ndp\u0101ra",
    "gn:population":0,
    "gn:timezone":"Asia/Kolkata",
    "iso:country":"IN",
    "name:ben_x_preferred":[
        "\u099a\u09be\u0981\u09a6\u09aa\u09be\u09a1\u09bc\u09be"
    ],
    "wof:name":"Chandpara",
    "wof:placetype":"neighbourhood"
},
  "geometry": {"coordinates":[81.41511,27.59813],"type":"Point"}
}