{
  "type": "Feature",
  "properties": {
    "iso:country":"IN",
    "ks:ks_name":"Hariharpur Purabtola",
    "ks:ks_pop":500,
    "ks:ks_type":"HABITATION",
    "name:eng_x_preferred":[
        "Hariharpur Purabtola"
    ],
    "wof:name":"Hariharpur Purabtola",
    "wof:placetype":"locality",
    "wof:population":500
},
  "geometry": {"coordinates":[83.540627,23.937465],"type":"Point"}
}