{
  "type": "Feature",
  "properties": {
    "iso:country":"IN",
    "ks:ks_name":"Bhutahitola",
    "ks:ks_pop":244,
    "ks:ks_type":"HABITATION",
    "name:eng_x_preferred":[
        "Bhutahitola"
    ],
    "wof:name":"Bhutahitola",
    "wof:placetype":"locality",
    "wof:population":244
},
  "geometry": {"coordinates":[83.98942,23.619218],"type":"Point"}
}