{
  "type": "Feature",
  "properties": {
    "gn:admin1_code":"38.0",
    "gn:admin2_code":"347.0",
    "gn:asciiname":"Sangrampur Khurd",
    "gn:country_code":"IN",
    "gn:dem":264,
    "gn:feature_class":"P",
    "gn:feature_code":"PPL",
    "gn:name":"Sangr\u0101mpur Khurd",
    "gn:population":0,
    "gn:timezone":"Asia/Kolkata",
    "iso:country":"IN",
    "ks:ks_name":"Sangrampur Khurd",
    "ks:ks_pop":110,
    "ks:ks_type":"VILLAGE",
    "name:eng_x_preferred":[
        "Sangrampur Khurd"
    ],
    "wof:name":"Sangrampur Khurd",
    "wof:placetype":"locality",
    "wof:population":110
},
  "geometry": {"coordinates":[84.5399,24.246367],"type":"Point"}
}