{
  "type": "Feature",
  "properties": {
    "iso:country":"IN",
    "ks:ks_name":"Hemari Timung",
    "ks:ks_pop":158,
    "ks:ks_type":"HABITATION",
    "name:eng_x_preferred":[
        "Hemari Timung"
    ],
    "wof:name":"Hemari Timung",
    "wof:placetype":"locality",
    "wof:population":158
},
  "geometry": {"coordinates":[93.182789,26.29516],"type":"Point"}
}