{
  "type": "Feature",
  "properties": {
    "gn:admin1_code":"39.0",
    "gn:admin2_code":"64.0",
    "gn:asciiname":"Jalshwar",
    "gn:country_code":"IN",
    "gn:dem":1228,
    "gn:feature_class":"P",
    "gn:feature_code":"PPL",
    "gn:name":"Jalshw\u0101r",
    "gn:population":0,
    "gn:timezone":"Asia/Kolkata",
    "iso:country":"IN",
    "ks:ks_name":"Jol Swar",
    "ks:ks_pop":136,
    "ks:ks_type":"HABITATION",
    "name:eng_x_preferred":[
        "Jol Swar"
    ],
    "name:eng_x_variant":[
        "Jalshwar"
    ],
    "wof:name":"Jol Swar",
    "wof:placetype":"locality",
    "wof:population":136
},
  "geometry": {"coordinates":[79.60433,29.613891],"type":"Point"}
}