{
  "type": "Feature",
  "properties": {
    "iso:country":"IN",
    "ks:ks_name":"Baradangua",
    "ks:ks_pop":281,
    "ks:ks_type":"HABITATION",
    "name:eng_x_preferred":[
        "Baradangua"
    ],
    "wof:name":"Baradangua",
    "wof:placetype":"locality",
    "wof:population":281
},
  "geometry": {"coordinates":[86.71411000000001,22.514813],"type":"Point"}
}