{
  "type": "Feature",
  "properties": {
    "gn:admin1_code":"35",
    "gn:admin2_code":"455.0",
    "gn:asciiname":"Chhinddhana",
    "gn:country_code":"IN",
    "gn:dem":669,
    "gn:feature_class":"P",
    "gn:feature_code":"PPL",
    "gn:name":"Chhinddh\u0101na",
    "gn:population":0,
    "gn:timezone":"Asia/Kolkata",
    "iso:country":"IN",
    "wof:name":"Chhinddhana",
    "wof:placetype":"locality"
},
  "geometry": {"coordinates":[78.47013000000003,22.12671],"type":"Point"}
}