{
  "type": "Feature",
  "properties": {
    "gn:admin1_code":"39",
    "gn:admin2_code":"61.0",
    "gn:asciiname":"Nad",
    "gn:country_code":"IN",
    "gn:dem":980,
    "gn:feature_class":"P",
    "gn:feature_code":"PPL",
    "gn:name":"N\u0101d",
    "gn:population":0,
    "gn:timezone":"Asia/Kolkata",
    "iso:country":"IN",
    "ks:ks_alt_nam":"N\u0101d",
    "ks:ks_name":"Nad",
    "ks:ks_pop":117,
    "ks:ks_type":"VILLAGE",
    "name:eng_x_preferred":[
        "Nad"
    ],
    "name:eng_x_variant":[
        "N\u0101d"
    ],
    "name:und_x_variant":[
        "N\u0101d",
        "N\u0101rh"
    ],
    "wof:name":"Nad",
    "wof:placetype":"locality",
    "wof:population":117
},
  "geometry": {"coordinates":[78.92152,29.810651],"type":"Point"}
}