{
  "type": "Feature",
  "properties": {
    "gn:admin1_code":"39",
    "gn:admin2_code":"61.0",
    "gn:asciiname":"Nad",
    "gn:country_code":"IN",
    "gn:dem":980,
    "gn:feature_class":"P",
    "gn:feature_code":"PPL",
    "gn:name":"N\u0101d",
    "gn:population":0,
    "gn:timezone":"Asia/Kolkata",
    "iso:country":"IN",
    "name:und_x_variant":[
        "N\u0101d",
        "N\u0101rh"
    ],
    "wof:name":"Nad",
    "wof:placetype":"locality"
},
  "geometry": {"coordinates":[78.92520999999998,29.81128],"type":"Point"}
}