{
  "type": "Feature",
  "properties": {
    "iso:country":"IN",
    "ks:ks_name":"Eguvamallalaguda",
    "ks:ks_pop":109,
    "ks:ks_type":"HABITATION",
    "name:eng_x_preferred":[
        "Eguvamallalaguda"
    ],
    "wof:name":"Eguvamallalaguda",
    "wof:placetype":"locality",
    "wof:population":109
},
  "geometry": {"coordinates":[83.860136,18.674538],"type":"Point"}
}