{
  "type": "Feature",
  "properties": {
    "gn:admin1_code":"25.0",
    "gn:admin2_code":"611.0",
    "gn:asciiname":"Karikalbela",
    "gn:country_code":"IN",
    "gn:dem":2120,
    "gn:feature_class":"P",
    "gn:feature_code":"PPL",
    "gn:name":"Karikalbela",
    "gn:population":0,
    "gn:timezone":"Asia/Kolkata",
    "iso:country":"IN",
    "wof:name":"Karikalbela",
    "wof:placetype":"locality"
},
  "geometry": {"coordinates":[76.67253000000002,11.35297],"type":"Point"}
}