{
  "type": "Feature",
  "properties": {
    "iso:country":"IN",
    "ks:ks_name":"Goraia Nagla",
    "ks:ks_pop":97,
    "ks:ks_type":"HABITATION",
    "ks:ks_uagg_main":0,
    "name:eng_x_preferred":[
        "Goraia Nagla"
    ],
    "wof:name":"Goraia Nagla",
    "wof:placetype":"neighbourhood",
    "wof:population":97
},
  "geometry": {"coordinates":[79.06823,27.847307],"type":"Point"}
}