{
  "type": "Feature",
  "properties": {
    "gn:admin1_code":"7.0",
    "gn:admin2_code":"97.0",
    "gn:asciiname":"Krishnanagar",
    "gn:country_code":"IN",
    "gn:dem":225,
    "gn:feature_class":"P",
    "gn:feature_code":"PPL",
    "gn:name":"Krishn\u0101nagar",
    "gn:population":0,
    "gn:timezone":"Asia/Kolkata",
    "iso:country":"IN",
    "name:ara_x_preferred":[
        "\u0643\u0631\u064a\u0634\u0646\u0627\u0646\u062c\u0627\u0631"
    ],
    "name:ben_x_preferred":[
        "\u0995\u09c3\u09b7\u09cd\u09a3\u09a8\u0997\u09b0"
    ],
    "name:deu_x_preferred":[
        "Krishnanagar"
    ],
    "name:fas_x_preferred":[
        "\u06a9\u0631\u06cc\u0634\u0646\u0627\u0646\u06af\u0627\u0631"
    ],
    "name:heb_x_preferred":[
        "\u05e7\u05e8\u05d9\u05e9\u05e0\u05e0\u05d0\u05d2\u05e8"
    ],
    "name:hin_x_preferred":[
        "\u0915\u0943\u0937\u094d\u0923\u0928\u0917\u0930"
    ],
    "name:hun_x_preferred":[
        "Krishnanagar"
    ],
    "name:ind_x_preferred":[
        "Krishnanagar"
    ],
    "name:kor_x_preferred":[
        "\ud06c\ub9ac\uc288\ub098\uac00\ub974"
    ],
    "name:por_x_preferred":[
        "Krishnanagar"
    ],
    "name:tur_x_preferred":[
        "Krishnanagar"
    ],
    "wof:name":"Krishnanagar",
    "wof:placetype":"neighbourhood"
},
  "geometry": {"coordinates":[77.18966,28.56599],"type":"Point"}
}