{
  "type": "Feature",
  "properties": {
    "iso:country":"IN",
    "ks:ks_name":"Pushapalli",
    "ks:ks_pop":424,
    "ks:ks_type":"VILLAGE",
    "name:eng_x_preferred":[
        "Pushapalli"
    ],
    "wof:name":"Pushapalli",
    "wof:placetype":"locality",
    "wof:population":424
},
  "geometry": {"coordinates":[81.66894499999999,18.360362],"type":"Point"}
}