{
  "type": "Feature",
  "properties": {
    "iso:country":"IN",
    "ks:ks_name":"Oddipalle",
    "ks:ks_pop":369,
    "ks:ks_type":"HABITATION",
    "name:eng_x_preferred":[
        "Oddipalle"
    ],
    "wof:name":"Oddipalle",
    "wof:placetype":"locality",
    "wof:population":369
},
  "geometry": {"coordinates":[78.581491,13.562579],"type":"Point"}
}