{
  "type": "Feature",
  "properties": {
    "iso:country":"IN",
    "ks:ks_alt_nam":"MUJAWAR WADA",
    "ks:ks_name":"Mujawar Wada",
    "ks:ks_pop":138,
    "ks:ks_type":"HABITATION",
    "name:eng_x_preferred":[
        "Mujawar Wada"
    ],
    "wof:name":"Mujawar Wada",
    "wof:placetype":"locality",
    "wof:population":138
},
  "geometry": {"coordinates":[74.43922000000001,17.224863],"type":"Point"}
}