{
  "type": "Feature",
  "properties": {
    "gn:admin1_code":"24.0",
    "gn:admin2_code":"110",
    "gn:asciiname":"Jamadar ki Dhani",
    "gn:country_code":"IN",
    "gn:dem":412,
    "gn:feature_class":"P",
    "gn:feature_code":"PPL",
    "gn:name":"Jam\u0101d\u0101r ki Dh\u0101ni",
    "gn:population":0,
    "gn:timezone":"Asia/Kolkata",
    "iso:country":"IN",
    "wof:name":"Jamadar ki Dhani",
    "wof:placetype":"locality"
},
  "geometry": {"coordinates":[75.67789999999999,26.88913],"type":"Point"}
}