{
  "type": "Feature",
  "properties": {
    "iso:country":"IN",
    "ks:ks_name":"Thoralli",
    "ks:ks_pop":15,
    "ks:ks_type":"HABITATION",
    "name:eng_x_preferred":[
        "Thoralli"
    ],
    "wof:name":"Thoralli",
    "wof:placetype":"locality",
    "wof:population":15
},
  "geometry": {"coordinates":[75.23449100000001,13.392354],"type":"Point"}
}