{
  "type": "Feature",
  "properties": {
    "iso:country":"IN",
    "ks:ks_name":"Gadhi Doolpur",
    "ks:ks_pop":235,
    "ks:ks_type":"HABITATION",
    "ks:ks_uagg_main":0,
    "name:eng_x_preferred":[
        "Gadhi Doolpur"
    ],
    "wof:name":"Gadhi Doolpur",
    "wof:placetype":"neighbourhood",
    "wof:population":235
},
  "geometry": {"coordinates":[78.68989000000001,27.081009],"type":"Point"}
}