{
  "type": "Feature",
  "properties": {
    "gn:country":"IN",
    "gn:fcode":"PPL",
    "gn:pop":65805,
    "iso:country":"IN",
    "name:ben_x_preferred":[
        "\u09ac\u09be\u09b8\u09ac\u0995\u09b2\u09cd\u09af\u09be\u09a3"
    ],
    "name:bpy_x_preferred":[
        "\u09ac\u09be\u09b8\u09ac\u0995\u09b2\u09cd\u09af\u09be\u09a8"
    ],
    "name:cat_x_preferred":[
        "Basavakalyan"
    ],
    "name:ceb_x_preferred":[
        "Basavakalyan Taluk"
    ],
    "name:deu_x_preferred":[
        "Basavakalyan"
    ],
    "name:eng_x_preferred":[
        "Basavakalyan"
    ],
    "name:fra_x_preferred":[
        "Basavakalyan"
    ],
    "name:guj_x_preferred":[
        "\u0aac\u0ab8\u0abe\u0ab5\u0abe\u0a95\u0ab2\u0acd\u0aaf\u0abe\u0aa3"
    ],
    "name:hin_x_preferred":[
        "\u092c\u0938\u0935\u0915\u0932\u094d\u092f\u093e\u0923"
    ],
    "name:ita_x_preferred":[
        "Basavakalyan"
    ],
    "name:jpn_x_preferred":[
        "\u30d0\u30b5\u30f4\u30a1\u30ab\u30ea\u30e4\u30fc\u30f3"
    ],
    "name:kan_x_preferred":[
        "\u0cac\u0cb8\u0cb5\u0c95\u0cb2\u0ccd\u0caf\u0cbe\u0ca3"
    ],
    "name:kor_x_preferred":[
        "\ubc14\uc0ac\ubc14\uce7c\ub9ac\uc548"
    ],
    "name:mal_x_preferred":[
        "\u0d2c\u0d3e\u0d38\u0d35\u0d15\u0d32\u0d4d\u0d2f\u0d3e\u0d7a"
    ],
    "name:mlg_x_preferred":[
        "Basavakalyan"
    ],
    "name:msa_x_preferred":[
        "Basavakalyan"
    ],
    "name:nan_x_preferred":[
        "Basavakalyan"
    ],
    "name:new_x_preferred":[
        "\u092c\u0938\u092d\u0915\u0932\u094d\u092f\u093e\u0923"
    ],
    "name:nld_x_preferred":[
        "Basavakalyan"
    ],
    "name:pan_x_preferred":[
        "\u0a2c\u0a38\u0a35\u0a15\u0a32\u0a3f\u0a06\u0a23"
    ],
    "name:por_x_preferred":[
        "Basavakalyan"
    ],
    "name:rus_x_preferred":[
        "\u0411\u0430\u0441\u0430\u0432\u0430\u043a\u0430\u043b\u044c\u044f\u043d"
    ],
    "name:san_x_preferred":[
        "\u092c\u0938\u0935\u0915\u0932\u094d\u092f\u093e\u0923\u092e\u094d"
    ],
    "name:spa_x_preferred":[
        "Basavakalyan"
    ],
    "name:swe_x_preferred":[
        "Basavakalyan Taluk"
    ],
    "name:tam_x_preferred":[
        "\u0baa\u0bbe\u0b9a\u0bb5\u0b95\u0bb2\u0bcd\u0baf\u0bbe\u0ba3\u0bcd"
    ],
    "name:tel_x_preferred":[
        "\u0c2c\u0c38\u0c35\u0c15\u0c33\u0c4d\u0c2f\u0c3e\u0c23\u0c4d"
    ],
    "name:tur_x_preferred":[
        "Basavakalyan"
    ],
    "name:unk_x_variant":[
        "Kaly\u0101ni"
    ],
    "name:urd_x_preferred":[
        "\u0628\u0627\u0633\u0627\u0648\u0627\u06a9\u0627\u0644\u06cc\u0627\u0646"
    ],
    "name:vie_x_preferred":[
        "Basavakalyan"
    ],
    "name:zho_x_preferred":[
        "\u5df4\u8428\u74e6\u5361\u5c14\u5ef6"
    ],
    "qs:name":"Basavakalyan",
    "qs:name_adm0":"India",
    "qs:name_adm1":"Karnataka",
    "qs:photos_9k":1,
    "qs:photos_9r":1,
    "qs:photos_all":1,
    "qs:photos_sr":0,
    "qs:placetype":"Town",
    "qs:pop_sr":"8",
    "wd:wordcount":1040,
    "wof:name":"Basavakalyan",
    "wof:placetype":"locality",
    "wof:population":65805
},
  "geometry": {"coordinates":[76.94972,17.87445],"type":"Point"}
}