{
  "type": "Feature",
  "properties": {
    "iso:country":"IN",
    "ks:ks_alt_nam":"KHANDEKAR WASTI",
    "ks:ks_name":"Khandekar Wasti",
    "ks:ks_pop":112,
    "ks:ks_type":"HABITATION",
    "name:eng_x_preferred":[
        "Khandekar Wasti"
    ],
    "wof:name":"Khandekar Wasti",
    "wof:placetype":"locality",
    "wof:population":112
},
  "geometry": {"coordinates":[75.290902,17.189241],"type":"Point"}
}