{
  "type": "Feature",
  "properties": {
    "iso:country":"IN",
    "ks:ks_name":"Jhandenager",
    "ks:ks_pop":185,
    "ks:ks_type":"HABITATION",
    "name:eng_x_preferred":[
        "Jhandenager"
    ],
    "wof:name":"Jhandenager",
    "wof:placetype":"locality",
    "wof:population":185
},
  "geometry": {"coordinates":[83.020279,27.408586],"type":"Point"}
}