{
  "type": "Feature",
  "properties": {
    "iso:country":"IN",
    "ks:ks_name":"Koleshwar Khurd",
    "ks:ks_pop":486,
    "ks:ks_type":"VILLAGE",
    "name:eng_x_preferred":[
        "Koleshwar Khurd"
    ],
    "wof:name":"Koleshwar Khurd",
    "wof:placetype":"locality",
    "wof:population":486
},
  "geometry": {"coordinates":[76.386792,27.076427],"type":"Point"}
}