{
  "type": "Feature",
  "properties": {
    "iso:country":"IN",
    "ks:ks_name":"Burnupani",
    "ks:ks_pop":298,
    "ks:ks_type":"HABITATION",
    "name:eng_x_preferred":[
        "Burnupani"
    ],
    "wof:name":"Burnupani",
    "wof:placetype":"locality",
    "wof:population":298
},
  "geometry": {"coordinates":[83.283362,22.607221],"type":"Point"}
}