{
  "type": "Feature",
  "properties": {
    "iso:country":"IN",
    "ks:ks_name":"Langkiding",
    "ks:ks_pop":137,
    "ks:ks_type":"HABITATION",
    "name:eng_x_preferred":[
        "Langkiding"
    ],
    "wof:name":"Langkiding",
    "wof:placetype":"locality",
    "wof:population":137
},
  "geometry": {"coordinates":[92.77469600000001,25.72167],"type":"Point"}
}