{
  "type": "Feature",
  "properties": {
    "gn:admin1_code":"25.0",
    "gn:admin2_code":"631.0",
    "gn:asciiname":"Chitsuruganapalli",
    "gn:country_code":"IN",
    "gn:dem":890,
    "gn:feature_class":"P",
    "gn:feature_code":"PPL",
    "gn:name":"Chitsuruganapalli",
    "gn:population":0,
    "gn:timezone":"Asia/Kolkata",
    "iso:country":"IN",
    "wof:name":"Chitsuruganapalli",
    "wof:placetype":"locality"
},
  "geometry": {"coordinates":[77.79903,12.83991],"type":"Point"}
}