{
  "type": "Feature",
  "properties": {
    "iso:country":"IN",
    "ks:ks_name":"Champatotha",
    "ks:ks_pop":1520,
    "ks:ks_type":"VILLAGE",
    "ks:ks_uagg_main":0,
    "name:eng_x_preferred":[
        "Champatotha"
    ],
    "wof:name":"Champatotha",
    "wof:placetype":"neighbourhood",
    "wof:population":1520
},
  "geometry": {"coordinates":[85.184107,20.407267],"type":"Point"}
}