{
  "type": "Feature",
  "properties": {
    "gn:admin1_code":"12.0",
    "gn:admin2_code":"1.0",
    "gn:asciiname":"Rariab",
    "gn:country_code":"IN",
    "gn:dem":2198,
    "gn:feature_class":"P",
    "gn:feature_code":"PPL",
    "gn:name":"Rar\u012bab",
    "gn:population":0,
    "gn:timezone":"Asia/Kolkata",
    "iso:country":"IN",
    "wof:name":"Rariab",
    "wof:placetype":"locality"
},
  "geometry": {"coordinates":[74.2813,34.60155],"type":"Point"}
}