{
  "type": "Feature",
  "properties": {
    "iso:country":"IN",
    "ks:ks_name":"Baina-Ojapara",
    "ks:ks_pop":1826,
    "ks:ks_type":"VILLAGE",
    "ks:ks_uagg_main":0,
    "name:eng_x_preferred":[
        "Baina-Ojapara"
    ],
    "wof:name":"Baina-Ojapara",
    "wof:placetype":"neighbourhood",
    "wof:population":1826
},
  "geometry": {"coordinates":[91.973775,26.412238],"type":"Point"}
}