{
  "type": "Feature",
  "properties": {
    "iso:country":"IN",
    "ks:ks_name":"Bhalujhola",
    "ks:ks_pop":164,
    "ks:ks_type":"HABITATION",
    "name:eng_x_preferred":[
        "Bhalujhola"
    ],
    "wof:name":"Bhalujhola",
    "wof:placetype":"locality",
    "wof:population":164
},
  "geometry": {"coordinates":[82.23644400000001,18.863422],"type":"Point"}
}