{
  "type": "Feature",
  "properties": {
    "iso:country":"IN",
    "ks:ks_name":"Karmaini Premwalia",
    "ks:ks_pop":3786,
    "ks:ks_type":"VILLAGE",
    "ks:ks_uagg_main":0,
    "name:eng_x_preferred":[
        "Karmaini Premwalia"
    ],
    "wof:name":"Karmaini Premwalia",
    "wof:placetype":"neighbourhood",
    "wof:population":3786
},
  "geometry": {"coordinates":[83.975443,26.725052],"type":"Point"}
}