{
  "type": "Feature",
  "properties": {
    "iso:country":"IN",
    "ks:ks_name":"Hatgachi Dakshin",
    "ks:ks_pop":1193,
    "ks:ks_type":"HABITATION",
    "name:eng_x_preferred":[
        "Hatgachi Dakshin"
    ],
    "wof:name":"Hatgachi Dakshin",
    "wof:placetype":"locality",
    "wof:population":1193
},
  "geometry": {"coordinates":[88.835126,22.429593],"type":"Point"}
}