{
  "type": "Feature",
  "properties": {
    "iso:country":"IN",
    "ks:ks_name":"Nunmati I",
    "ks:ks_pop":928,
    "ks:ks_type":"HABITATION",
    "name:eng_x_preferred":[
        "Nunmati I"
    ],
    "wof:name":"Nunmati I",
    "wof:placetype":"locality",
    "wof:population":928
},
  "geometry": {"coordinates":[90.342116,26.197099],"type":"Point"}
}