{
  "type": "Feature",
  "properties": {
    "iso:country":"IN",
    "ks:ks_name":"Satajhari",
    "ks:ks_pop":180,
    "ks:ks_type":"VILLAGE",
    "name:eng_x_preferred":[
        "Satajhari"
    ],
    "wof:name":"Satajhari",
    "wof:placetype":"locality",
    "wof:population":180
},
  "geometry": {"coordinates":[84.795036,20.384437],"type":"Point"}
}