{
  "type": "Feature",
  "properties": {
    "gn:admin1_code":"34.0",
    "gn:admin2_code":"224.0",
    "gn:asciiname":"Jan Muhammadpur",
    "gn:country_code":"IN",
    "gn:dem":49,
    "gn:feature_class":"P",
    "gn:feature_code":"PPL",
    "gn:name":"J\u0101n Muhammadpur",
    "gn:population":0,
    "gn:timezone":"Asia/Kolkata",
    "iso:country":"IN",
    "ks:ks_alt_nam":"J\u0101n Muhammadpur",
    "ks:ks_name":"Jan Muhammadpur",
    "ks:ks_type":"VILLAGE",
    "ks:ks_uagg_main":0,
    "name:eng_x_preferred":[
        "Jan Muhammadpur"
    ],
    "name:eng_x_variant":[
        "J\u0101n Muhammadpur"
    ],
    "wof:name":"Jan Muhammadpur",
    "wof:placetype":"neighbourhood"
},
  "geometry": {"coordinates":[87.25477100000001,25.275933],"type":"Point"}
}