{
  "type": "Feature",
  "properties": {
    "iso:country":"IN",
    "ks:ks_name":"Raebandh",
    "ks:ks_pop":225,
    "ks:ks_type":"VILLAGE",
    "name:eng_x_preferred":[
        "Raebandh"
    ],
    "wof:name":"Raebandh",
    "wof:placetype":"locality",
    "wof:population":225
},
  "geometry": {"coordinates":[86.978725,24.340613],"type":"Point"}
}