{
  "type": "Feature",
  "properties": {
    "gn:admin1_code":"19",
    "gn:admin2_code":"579.0",
    "gn:asciiname":"Chik Kolga",
    "gn:country_code":"IN",
    "gn:dem":403,
    "gn:feature_class":"P",
    "gn:feature_code":"PPL",
    "gn:name":"Chik Kolga",
    "gn:population":0,
    "gn:timezone":"Asia/Kolkata",
    "iso:country":"IN",
    "wof:name":"Chik Kolga",
    "wof:placetype":"locality"
},
  "geometry": {"coordinates":[76.71321,17.1569],"type":"Point"}
}