{
  "type": "Feature",
  "properties": {
    "gn:admin1_code":"16",
    "gn:admin2_code":"505.0",
    "gn:asciiname":"Saori",
    "gn:country_code":"IN",
    "gn:dem":276,
    "gn:feature_class":"P",
    "gn:feature_code":"PPL",
    "gn:name":"S\u0101ori",
    "gn:population":0,
    "gn:timezone":"Asia/Kolkata",
    "iso:country":"IN",
    "name:jpn_x_preferred":[
        "\u3055\u304a\u308a"
    ],
    "name:kor_x_preferred":[
        "\uc0ac\uc624\ub9ac"
    ],
    "wof:name":"Saori",
    "wof:placetype":"neighbourhood"
},
  "geometry": {"coordinates":[79.25927,21.12665],"type":"Point"}
}