{
  "type": "Feature",
  "properties": {
    "gn:admin1_code":"36",
    "gn:admin2_code":"197.0",
    "gn:asciiname":"Barhauna",
    "gn:country_code":"IN",
    "gn:dem":86,
    "gn:feature_class":"P",
    "gn:feature_code":"PPL",
    "gn:name":"Barhaun\u0101",
    "gn:population":0,
    "gn:timezone":"Asia/Kolkata",
    "iso:country":"IN",
    "ks:ks_name":"Badhauna",
    "ks:ks_pop":1531,
    "ks:ks_type":"VILLAGE",
    "name:eng_x_preferred":[
        "Badhauna"
    ],
    "name:eng_x_variant":[
        "Barhauna"
    ],
    "wof:name":"Badhauna",
    "wof:placetype":"locality",
    "wof:population":1531
},
  "geometry": {"coordinates":[82.86040199999999,25.557026],"type":"Point"}
}