{
  "type": "Feature",
  "properties": {
    "gn:admin1_code":"34.0",
    "gn:admin2_code":"219.0",
    "gn:asciiname":"Hankarpur",
    "gn:country_code":"IN",
    "gn:dem":63,
    "gn:feature_class":"P",
    "gn:feature_code":"PPL",
    "gn:name":"Hank\u0101rpur",
    "gn:population":0,
    "gn:timezone":"Asia/Kolkata",
    "iso:country":"IN",
    "ks:ks_name":"Hankarpur",
    "ks:ks_pop":1060,
    "ks:ks_type":"VILLAGE",
    "ks:ks_uagg_main":0,
    "name:eng_x_preferred":[
        "Hankarpur"
    ],
    "wof:name":"Hankarpur",
    "wof:placetype":"neighbourhood",
    "wof:population":1060
},
  "geometry": {"coordinates":[84.786085,26.056823],"type":"Point"}
}