{
  "type": "Feature",
  "properties": {
    "gn:admin1_code":"2.0",
    "gn:admin2_code":"546.0",
    "gn:asciiname":"Kollivarigudem",
    "gn:country_code":"IN",
    "gn:dem":134,
    "gn:feature_class":"P",
    "gn:feature_code":"PPL",
    "gn:name":"Kolliv\u0101rig\u016bdem",
    "gn:population":0,
    "gn:timezone":"Asia/Kolkata",
    "iso:country":"IN",
    "ks:ks_alt_nam":"Kolliv\u0101rig\u016bdem",
    "ks:ks_name":"Kollivarigudem",
    "ks:ks_pop":864,
    "ks:ks_type":"VILLAGE",
    "name:eng_x_preferred":[
        "Kollivarigudem"
    ],
    "name:eng_x_variant":[
        "Kolliv\u0101rig\u016bdem"
    ],
    "wof:name":"Kollivarigudem",
    "wof:placetype":"locality",
    "wof:population":864
},
  "geometry": {"coordinates":[81.072839,17.158877],"type":"Point"}
}