{
  "type": "Feature",
  "properties": {
    "iso:country":"IN",
    "ks:ks_alt_nam":"Pub Kalita supa",
    "ks:ks_name":"Pub Kalita Supa",
    "ks:ks_pop":264,
    "ks:ks_type":"HABITATION",
    "name:eng_x_preferred":[
        "Pub Kalita Supa"
    ],
    "wof:name":"Pub Kalita Supa",
    "wof:placetype":"locality",
    "wof:population":264
},
  "geometry": {"coordinates":[91.589941,26.590094],"type":"Point"}
}