{
  "type": "Feature",
  "properties": {
    "gn:admin1_code":"34.0",
    "gn:admin2_code":"217.0",
    "gn:asciiname":"Bhojpurwa",
    "gn:country_code":"IN",
    "gn:dem":66,
    "gn:feature_class":"P",
    "gn:feature_code":"PPL",
    "gn:name":"Bhojpurwa",
    "gn:population":0,
    "gn:timezone":"Asia/Kolkata",
    "iso:country":"IN",
    "ks:ks_name":"Bhojpurwa",
    "ks:ks_pop":668,
    "ks:ks_type":"VILLAGE",
    "ks:ks_uagg_main":0,
    "name:eng_x_preferred":[
        "Bhojpurwa"
    ],
    "wof:name":"Bhojpurwa",
    "wof:placetype":"neighbourhood",
    "wof:population":668
},
  "geometry": {"coordinates":[84.695858,26.320955],"type":"Point"}
}