{
  "type": "Feature",
  "properties": {
    "gn:admin1_code":"23",
    "gn:admin2_code":"48.0",
    "gn:asciiname":"Jhabali Sani",
    "gn:country_code":"IN",
    "gn:dem":255,
    "gn:feature_class":"P",
    "gn:feature_code":"PPL",
    "gn:name":"Jhab\u0101li S\u0101n\u012b",
    "gn:population":0,
    "gn:timezone":"Asia/Kolkata",
    "iso:country":"IN",
    "ks:ks_alt_nam":"Jhab\u0101li S\u0101n\u012b",
    "ks:ks_name":"Jhabali Sani",
    "ks:ks_pop":503,
    "ks:ks_type":"VILLAGE",
    "name:eng_x_preferred":[
        "Jhabali Sani"
    ],
    "name:eng_x_variant":[
        "Jhab\u0101li S\u0101n\u012b"
    ],
    "wof:name":"Jhabali Sani",
    "wof:placetype":"locality",
    "wof:population":503
},
  "geometry": {"coordinates":[76.25592899999999,30.524923],"type":"Point"}
}