{
  "type": "Feature",
  "properties": {
    "gn:admin1_code":"16.0",
    "gn:admin2_code":"516",
    "gn:asciiname":"Bhaitana",
    "gn:country_code":"IN",
    "gn:dem":681,
    "gn:feature_class":"P",
    "gn:feature_code":"PPL",
    "gn:name":"Bhaitana",
    "gn:population":0,
    "gn:timezone":"Asia/Kolkata",
    "iso:country":"IN",
    "wof:name":"Bhaitana",
    "wof:placetype":"neighbourhood"
},
  "geometry": {"coordinates":[73.90143999999999,20.6068],"type":"Point"}
}