{
  "type": "Feature",
  "properties": {
    "iso:country":"IN",
    "ks:ks_alt_nam":"DEBENDRAPUR",
    "ks:ks_name":"Debendrapur",
    "ks:ks_pop":552,
    "ks:ks_type":"HABITATION",
    "name:eng_x_preferred":[
        "Debendrapur"
    ],
    "wof:name":"Debendrapur",
    "wof:placetype":"locality",
    "wof:population":552
},
  "geometry": {"coordinates":[88.51970799999999,26.628762],"type":"Point"}
}