{
  "type": "Feature",
  "properties": {
    "gn:admin1_code":"25.0",
    "gn:admin2_code":"605.0",
    "gn:asciiname":"Nariyaneri",
    "gn:country_code":"IN",
    "gn:dem":419,
    "gn:feature_class":"P",
    "gn:feature_code":"PPL",
    "gn:name":"Nariyan\u0113ri",
    "gn:population":0,
    "gn:timezone":"Asia/Kolkata",
    "iso:country":"IN",
    "wof:name":"Nariyaneri",
    "wof:placetype":"locality"
},
  "geometry": {"coordinates":[78.48884,12.49245],"type":"Point"}
}