{
  "type": "Feature",
  "properties": {
    "gn:admin1_code":"16",
    "gn:admin2_code":"516.0",
    "gn:asciiname":"Vanjari Huts",
    "gn:country_code":"IN",
    "gn:dem":635,
    "gn:feature_class":"P",
    "gn:feature_code":"PPL",
    "gn:name":"Vanj\u0101ri Huts",
    "gn:population":0,
    "gn:timezone":"Asia/Kolkata",
    "iso:country":"IN",
    "wof:name":"Vanjari Huts",
    "wof:placetype":"locality"
},
  "geometry": {"coordinates":[74.86547,20.24817],"type":"Point"}
}