{
  "type": "Feature",
  "properties": {
    "gn:admin1_code":"36",
    "gn:admin2_code":"165.0",
    "gn:asciiname":"Patreta",
    "gn:country_code":"IN",
    "gn:dem":110,
    "gn:feature_class":"P",
    "gn:feature_code":"PPL",
    "gn:name":"Patreta",
    "gn:population":0,
    "gn:timezone":"Asia/Kolkata",
    "iso:country":"IN",
    "ks:ks_name":"Patreta",
    "ks:ks_pop":1628,
    "ks:ks_type":"VILLAGE",
    "name:eng_x_preferred":[
        "Patreta"
    ],
    "wof:name":"Patreta",
    "wof:placetype":"locality",
    "wof:population":1628
},
  "geometry": {"coordinates":[79.80632900000001,25.893541],"type":"Point"}
}