{
  "type": "Feature",
  "properties": {
    "gn:admin1_code":"25.0",
    "gn:admin2_code":"605.0",
    "gn:asciiname":"Nangamangalam",
    "gn:country_code":"IN",
    "gn:dem":146,
    "gn:feature_class":"P",
    "gn:feature_code":"PPL",
    "gn:name":"Nangamangalam",
    "gn:population":0,
    "gn:timezone":"Asia/Kolkata",
    "iso:country":"IN",
    "name:tam_x_preferred":[
        "\u0ba8\u0b99\u0bcd\u0b95\u0bae\u0b99\u0bcd\u0b95\u0bb3\u0bae\u0bcd"
    ],
    "name:tel_x_preferred":[
        "\u0c28\u0c02\u0c17\u0c2e\u0c02\u0c17\u0c33\u0c02"
    ],
    "wof:name":"Nangamangalam",
    "wof:placetype":"locality"
},
  "geometry": {"coordinates":[79.32028000000003,12.75075],"type":"Point"}
}