{
  "type": "Feature",
  "properties": {
    "iso:country":"IN",
    "ks:ks_name":"Goranahalli",
    "ks:ks_pop":103,
    "ks:ks_type":"HABITATION",
    "name:eng_x_preferred":[
        "Goranahalli"
    ],
    "wof:name":"Goranahalli",
    "wof:placetype":"locality",
    "wof:population":103
},
  "geometry": {"coordinates":[75.198866,13.840503],"type":"Point"}
}