{
  "type": "Feature",
  "properties": {
    "gn:admin1_code":"12.0",
    "gn:admin2_code":"18.0",
    "gn:asciiname":"Pransan",
    "gn:country_code":"IN",
    "gn:dem":2768,
    "gn:feature_class":"P",
    "gn:feature_code":"PPL",
    "gn:name":"Pr\u0101nsan",
    "gn:population":0,
    "gn:timezone":"Asia/Kolkata",
    "iso:country":"IN",
    "wof:name":"Pransan",
    "wof:placetype":"locality"
},
  "geometry": {"coordinates":[75.97311999999999,33.54588],"type":"Point"}
}