{
  "type": "Feature",
  "properties": {
    "gn:admin1_code":"37.0",
    "gn:admin2_code":"408.0",
    "gn:asciiname":"Mahrartola",
    "gn:country_code":"IN",
    "gn:dem":334,
    "gn:feature_class":"P",
    "gn:feature_code":"PPL",
    "gn:name":"Mahr\u0101rtola",
    "gn:population":0,
    "gn:timezone":"Asia/Kolkata",
    "iso:country":"IN",
    "name:eng_x_preferred":[
        "Mahr\u0101rtola"
    ],
    "wof:name":"Mahrartola",
    "wof:placetype":"locality"
},
  "geometry": {"coordinates":[81.01553,21.54372],"type":"Point"}
}