{
  "type": "Feature",
  "properties": {
    "gn:admin1_code":"19.0",
    "gn:admin2_code":"566.0",
    "gn:asciiname":"Obalapura",
    "gn:country_code":"IN",
    "gn:dem":642,
    "gn:feature_class":"P",
    "gn:feature_code":"PPL",
    "gn:name":"Obal\u0101pura",
    "gn:population":0,
    "gn:timezone":"Asia/Kolkata",
    "iso:country":"IN",
    "wof:name":"Obalapura",
    "wof:placetype":"locality"
},
  "geometry": {"coordinates":[76.69221999999998,13.7919],"type":"Point"}
}