{
  "type": "Feature",
  "properties": {
    "iso:country":"IN",
    "ks:ks_name":"Kabbarhatti",
    "ks:ks_pop":130,
    "ks:ks_type":"HABITATION",
    "name:eng_x_preferred":[
        "Kabbarhatti"
    ],
    "wof:name":"Kabbarhatti",
    "wof:placetype":"locality",
    "wof:population":130
},
  "geometry": {"coordinates":[76.483864,13.187344],"type":"Point"}
}