{
  "type": "Feature",
  "properties": {
    "gn:admin1_code":"12.0",
    "gn:admin2_code":"9.0",
    "gn:asciiname":"Takia Ahmad Shah",
    "gn:country_code":"IN",
    "gn:dem":1714,
    "gn:feature_class":"P",
    "gn:feature_code":"PPL",
    "gn:name":"Takia Ahmad Sh\u0101h",
    "gn:population":0,
    "gn:timezone":"Asia/Kolkata",
    "iso:country":"IN",
    "name:eng_x_preferred":[
        "Takia Ahmad Sh\u0101h"
    ],
    "wof:name":"Takia Ahmad Shah",
    "wof:placetype":"locality"
},
  "geometry": {"coordinates":[74.70121,34.41203],"type":"Point"}
}