{
  "type": "Feature",
  "properties": {
    "gn:admin1_code":"36.0",
    "gn:admin2_code":"149.0",
    "gn:asciiname":"Azadnagar",
    "gn:country_code":"IN",
    "gn:dem":186,
    "gn:feature_class":"P",
    "gn:feature_code":"PPL",
    "gn:name":"\u0100z\u0101dnagar",
    "gn:population":0,
    "gn:timezone":"Asia/Kolkata",
    "iso:country":"IN",
    "name:und_x_variant":[
        "\u0100z\u0101dnagar",
        "Gang\u0101pur"
    ],
    "wof:name":"Azadnagar",
    "wof:placetype":"locality"
},
  "geometry": {"coordinates":[78.75614,28.31747],"type":"Point"}
}