{
  "type": "Feature",
  "properties": {
    "iso:country":"IN",
    "ks:ks_name":"Butchirajupeta",
    "ks:ks_pop":64,
    "ks:ks_type":"HABITATION",
    "name:eng_x_preferred":[
        "Butchirajupeta"
    ],
    "wof:name":"Butchirajupeta",
    "wof:placetype":"locality",
    "wof:population":64
},
  "geometry": {"coordinates":[83.58062700000001,18.389188],"type":"Point"}
}