{
  "type": "Feature",
  "properties": {
    "gn:admin1_code":"36.0",
    "gn:admin2_code":"184.0",
    "gn:asciiname":"Minan",
    "gn:country_code":"IN",
    "gn:dem":97,
    "gn:feature_class":"P",
    "gn:feature_code":"PPL",
    "gn:name":"M\u012bn\u0101n",
    "gn:population":0,
    "gn:timezone":"Asia/Kolkata",
    "iso:country":"IN",
    "name:fas_x_preferred":[
        "\u0645\u06cc\u0646\u0627\u0646"
    ],
    "wof:name":"Minan",
    "wof:placetype":"locality"
},
  "geometry": {"coordinates":[82.72601,27.32723],"type":"Point"}
}