{
  "type": "Feature",
  "properties": {
    "iso:country":"IN",
    "ks:ks_name":"Puljhari",
    "ks:ks_pop":435,
    "ks:ks_type":"VILLAGE",
    "name:eng_x_preferred":[
        "Puljhari"
    ],
    "wof:name":"Puljhari",
    "wof:placetype":"locality",
    "wof:population":435
},
  "geometry": {"coordinates":[87.107139,24.341378],"type":"Point"}
}