{
  "type": "Feature",
  "properties": {
    "iso:country":"IN",
    "ks:ks_name":"Khemiyanaparu",
    "ks:ks_pop":2723,
    "ks:ks_type":"HABITATION",
    "name:eng_x_preferred":[
        "Khemiyanaparu"
    ],
    "wof:name":"Khemiyanaparu",
    "wof:placetype":"locality",
    "wof:population":2723
},
  "geometry": {"coordinates":[72.192262,24.109419],"type":"Point"}
}