{
  "type": "Feature",
  "properties": {
    "iso:country":"IN",
    "ks:ks_name":"Bhadrapali",
    "ks:ks_pop":122,
    "ks:ks_type":"VILLAGE",
    "name:eng_x_preferred":[
        "Bhadrapali"
    ],
    "wof:name":"Bhadrapali",
    "wof:placetype":"locality",
    "wof:population":122
},
  "geometry": {"coordinates":[83.87491300000001,20.696954],"type":"Point"}
}