{
  "type": "Feature",
  "properties": {
    "iso:country":"IN",
    "ks:ks_name":"Seeyolon Ki Dhani",
    "ks:ks_pop":460,
    "ks:ks_type":"HABITATION",
    "name:eng_x_preferred":[
        "Seeyolon Ki Dhani"
    ],
    "wof:name":"Seeyolon Ki Dhani",
    "wof:placetype":"locality",
    "wof:population":460
},
  "geometry": {"coordinates":[71.812303,25.840828],"type":"Point"}
}