{
  "type": "Feature",
  "properties": {
    "gn:admin1_code":"34.0",
    "gn:admin2_code":"211.0",
    "gn:asciiname":"Kanharia",
    "gn:country_code":"IN",
    "gn:dem":47,
    "gn:feature_class":"P",
    "gn:feature_code":"PPL",
    "gn:name":"Kanharia",
    "gn:population":0,
    "gn:timezone":"Asia/Kolkata",
    "iso:country":"IN",
    "wof:name":"Kanharia",
    "wof:placetype":"locality"
},
  "geometry": {"coordinates":[87.72014,25.93423],"type":"Point"}
}