{
  "type": "Feature",
  "properties": {
    "iso:country":"IN",
    "ks:ks_name":"Pinjra",
    "ks:ks_pop":477,
    "ks:ks_type":"VILLAGE",
    "ks:ks_uagg_main":0,
    "name:eng_x_preferred":[
        "Pinjra"
    ],
    "wof:name":"Pinjra",
    "wof:placetype":"neighbourhood",
    "wof:population":477
},
  "geometry": {"coordinates":[73.01052,20.871304],"type":"Point"}
}