{
  "type": "Feature",
  "properties": {
    "gn:admin1_code":"19.0",
    "gn:admin2_code":"555.0",
    "gn:asciiname":"Krishna Kittur",
    "gn:country_code":"IN",
    "gn:dem":541,
    "gn:feature_class":"P",
    "gn:feature_code":"PPL",
    "gn:name":"Krishna Kittur",
    "gn:population":0,
    "gn:timezone":"Asia/Kolkata",
    "iso:country":"IN",
    "name:und_x_variant":[
        "Krishna-kittur"
    ],
    "wof:name":"Krishna Kittur",
    "wof:placetype":"locality"
},
  "geometry": {"coordinates":[74.91938,16.63828],"type":"Point"}
}