{
  "type": "Feature",
  "properties": {
    "iso:country":"IN",
    "ks:ks_name":"Charkaha",
    "ks:ks_type":"VILLAGE",
    "name:eng_x_preferred":[
        "Charkaha"
    ],
    "wof:name":"Charkaha",
    "wof:placetype":"locality"
},
  "geometry": {"coordinates":[83.31246400000001,26.646622],"type":"Point"}
}