{
  "type": "Feature",
  "properties": {
    "iso:country":"IN",
    "ks:ks_name":"Bageshwar",
    "ks:ks_pop":108,
    "ks:ks_type":"VILLAGE",
    "name:eng_x_preferred":[
        "Bageshwar"
    ],
    "name:hin_x_preferred":[
        "\u092c\u093e\u0917\u0947\u0936\u094d\u0935\u0930"
    ],
    "wof:name":"Bageshwar",
    "wof:placetype":"locality",
    "wof:population":108
},
  "geometry": {"coordinates":[78.585666,30.113948],"type":"Point"}
}