{
  "type": "Feature",
  "properties": {
    "gn:admin1_code":"35",
    "gn:admin2_code":"427.0",
    "gn:asciiname":"Sadpur",
    "gn:country_code":"IN",
    "gn:dem":366,
    "gn:feature_class":"P",
    "gn:feature_code":"PPL",
    "gn:name":"S\u0101dpur",
    "gn:population":0,
    "gn:timezone":"Asia/Kolkata",
    "iso:country":"IN",
    "name:ben_x_preferred":[
        "\u09b8\u09be\u09a6\u09aa\u09c1\u09b0"
    ],
    "name:bpy_x_preferred":[
        "\u09b8\u09a6\u09aa\u09c1\u09b0"
    ],
    "name:ita_x_preferred":[
        "Sadpur"
    ],
    "name:mlg_x_preferred":[
        "Sadpur"
    ],
    "name:msa_x_preferred":[
        "Sadpur"
    ],
    "name:nld_x_preferred":[
        "Sadpur"
    ],
    "name:por_x_preferred":[
        "Sadpur"
    ],
    "name:urd_x_preferred":[
        "\u0633\u062f\u067e\u0648\u0631"
    ],
    "name:vie_x_preferred":[
        "Sadpur"
    ],
    "name:zho_x_preferred":[
        "\u8428\u5fb7\u666e\u5c14"
    ],
    "wof:name":"Sadpur",
    "wof:placetype":"locality"
},
  "geometry": {"coordinates":[79.13816,24.38634],"type":"Point"}
}