{
  "type": "Feature",
  "properties": {
    "iso:country":"IN",
    "ks:ks_alt_nam":"BARA YADAV TOLA",
    "ks:ks_name":"Bara Yadav Tola",
    "ks:ks_pop":668,
    "ks:ks_type":"HABITATION",
    "name:eng_x_preferred":[
        "Bara Yadav Tola"
    ],
    "wof:name":"Bara Yadav Tola",
    "wof:placetype":"locality",
    "wof:population":668
},
  "geometry": {"coordinates":[86.63016500000001,26.051535],"type":"Point"}
}