{
  "type": "Feature",
  "properties": {
    "gn:admin1_code":"38.0",
    "gn:admin2_code":"362.0",
    "gn:asciiname":"Sugapahari",
    "gn:country_code":"IN",
    "gn:dem":131,
    "gn:feature_class":"P",
    "gn:feature_code":"PPL",
    "gn:name":"Sugapah\u0101ri",
    "gn:population":0,
    "gn:timezone":"Asia/Kolkata",
    "iso:country":"IN",
    "ks:ks_name":"Sugapahari",
    "ks:ks_pop":161,
    "ks:ks_type":"VILLAGE",
    "name:eng_x_preferred":[
        "Sugapahari"
    ],
    "wof:name":"Sugapahari",
    "wof:placetype":"locality",
    "wof:population":161
},
  "geometry": {"coordinates":[87.562343,24.308909],"type":"Point"}
}