{
  "type": "Feature",
  "properties": {
    "gn:admin1_code":"36",
    "gn:admin2_code":"178.0",
    "gn:asciiname":"Upadhiapur",
    "gn:country_code":"IN",
    "gn:dem":95,
    "gn:feature_class":"P",
    "gn:feature_code":"PPL",
    "gn:name":"Upadhi\u0101pur",
    "gn:population":0,
    "gn:timezone":"Asia/Kolkata",
    "iso:country":"IN",
    "ks:ks_alt_nam":"Upadhi\u0101pur",
    "ks:ks_name":"Upadhiapur",
    "ks:ks_type":"VILLAGE",
    "ks:ks_uagg_main":0,
    "name:eng_x_preferred":[
        "Upadhiapur"
    ],
    "name:eng_x_variant":[
        "Upadhi\u0101pur"
    ],
    "wof:name":"Upadhiapur",
    "wof:placetype":"neighbourhood"
},
  "geometry": {"coordinates":[82.426748,26.341783],"type":"Point"}
}