{
  "type": "Feature",
  "properties": {
    "iso:country":"IN",
    "ks:ks_name":"Birabarpur",
    "ks:ks_pop":1298,
    "ks:ks_type":"VILLAGE",
    "ks:ks_uagg_main":0,
    "name:eng_x_preferred":[
        "Birabarpur"
    ],
    "wof:name":"Birabarpur",
    "wof:placetype":"neighbourhood",
    "wof:population":1298
},
  "geometry": {"coordinates":[85.447664,20.445112],"type":"Point"}
}