{
  "type": "Feature",
  "properties": {
    "iso:country":"IN",
    "ks:ks_name":"Godawas",
    "ks:ks_pop":331,
    "ks:ks_type":"VILLAGE",
    "name:eng_x_preferred":[
        "Godawas"
    ],
    "wof:name":"Godawas",
    "wof:placetype":"locality",
    "wof:population":331
},
  "geometry": {"coordinates":[72.681528,26.149531],"type":"Point"}
}