{
  "type": "Feature",
  "properties": {
    "iso:country":"IN",
    "ks:ks_name":"Pakra Buzurg",
    "ks:ks_pop":3091,
    "ks:ks_type":"VILLAGE",
    "name:eng_x_preferred":[
        "Pakra Buzurg"
    ],
    "wof:name":"Pakra Buzurg",
    "wof:placetype":"locality",
    "wof:population":3091
},
  "geometry": {"coordinates":[80.806383,26.372106],"type":"Point"}
}