{
  "type": "Feature",
  "properties": {
    "gn:admin1_code":"36",
    "gn:admin2_code":"134.0",
    "gn:asciiname":"Faridnagar",
    "gn:country_code":"IN",
    "gn:dem":237,
    "gn:feature_class":"P",
    "gn:feature_code":"PPL",
    "gn:name":"Far\u012bdnagar",
    "gn:population":0,
    "gn:timezone":"Asia/Kolkata",
    "iso:country":"IN",
    "name:bpy_x_preferred":[
        "\u09ab\u09b0\u09bf\u09a6\u09a8\u0997\u09b0"
    ],
    "name:ceb_x_preferred":[
        "Far\u012bdnagar"
    ],
    "name:fas_x_preferred":[
        "\u0641\u0631\u06cc\u062f\u0646\u06af\u0631"
    ],
    "name:hin_x_preferred":[
        "\u092b\u0930\u0940\u0926\u0928\u0917\u0930"
    ],
    "name:ita_x_preferred":[
        "Faridnagar"
    ],
    "name:mlg_x_preferred":[
        "Faridnagar"
    ],
    "name:msa_x_preferred":[
        "Faridnagar"
    ],
    "name:new_x_preferred":[
        "\u092b\u0930\u093f\u0926\u0928\u0917\u0930"
    ],
    "name:nld_x_preferred":[
        "Faridnagar"
    ],
    "name:pol_x_preferred":[
        "Faridnagar"
    ],
    "name:por_x_preferred":[
        "Faridnagar"
    ],
    "name:swe_x_preferred":[
        "Far\u012bdnagar"
    ],
    "name:urd_x_preferred":[
        "\u0641\u0631\u06cc\u062f \u0646\u06af\u0631"
    ],
    "name:vie_x_preferred":[
        "Faridnagar"
    ],
    "name:zho_x_preferred":[
        "\u6cd5\u91cc\u5fb7\u7eb3\u52a0\u5c14"
    ],
    "wof:name":"Faridnagar",
    "wof:placetype":"locality"
},
  "geometry": {"coordinates":[78.35024,29.31403],"type":"Point"}
}