{
  "type": "Feature",
  "properties": {
    "iso:country":"IN",
    "ks:ks_name":"Banua Chuk",
    "ks:ks_pop":495,
    "ks:ks_type":"HABITATION",
    "name:eng_x_preferred":[
        "Banua Chuk"
    ],
    "wof:name":"Banua Chuk",
    "wof:placetype":"locality",
    "wof:population":495
},
  "geometry": {"coordinates":[95.208043,27.15961],"type":"Point"}
}