{
  "type": "Feature",
  "properties": {
    "iso:country":"IN",
    "ks:ks_name":"Trikoleya",
    "ks:ks_pop":1500,
    "ks:ks_type":"VILLAGE",
    "ks:ks_uagg_main":0,
    "name:eng_x_preferred":[
        "Trikoleya"
    ],
    "wof:name":"Trikoleya",
    "wof:placetype":"neighbourhood",
    "wof:population":1500
},
  "geometry": {"coordinates":[80.49026000000001,28.466644],"type":"Point"}
}