{
  "type": "Feature",
  "properties": {
    "iso:country":"IN",
    "ks:ks_name":"Kalmettu",
    "ks:ks_pop":60,
    "ks:ks_type":"HABITATION",
    "name:eng_x_preferred":[
        "Kalmettu"
    ],
    "wof:name":"Kalmettu",
    "wof:placetype":"locality",
    "wof:population":60
},
  "geometry": {"coordinates":[74.73322,14.596439],"type":"Point"}
}