{
  "type": "Feature",
  "properties": {
    "gn:admin1_code":"11",
    "gn:admin2_code":"33.0",
    "gn:asciiname":"Batiana",
    "gn:country_code":"IN",
    "gn:dem":1615,
    "gn:feature_class":"P",
    "gn:feature_code":"PPL",
    "gn:name":"Bati\u0101na",
    "gn:population":0,
    "gn:timezone":"Asia/Kolkata",
    "iso:country":"IN",
    "name:cat_x_preferred":[
        "Batiana"
    ],
    "name:vie_x_preferred":[
        "Batiana"
    ],
    "wof:name":"Batiana",
    "wof:placetype":"locality"
},
  "geometry": {"coordinates":[77.12608,31.04803],"type":"Point"}
}