{
  "type": "Feature",
  "properties": {
    "iso:country":"IN",
    "ks:ks_name":"Killemachi",
    "ks:ks_pop":104,
    "ks:ks_type":"HABITATION",
    "name:eng_x_preferred":[
        "Killemachi"
    ],
    "wof:name":"Killemachi",
    "wof:placetype":"locality",
    "wof:population":104
},
  "geometry": {"coordinates":[73.353089,17.814456],"type":"Point"}
}