{
  "type": "Feature",
  "properties": {
    "iso:country":"IN",
    "ks:ks_name":"Mottekuni",
    "ks:ks_pop":79,
    "ks:ks_type":"HABITATION",
    "name:eng_x_preferred":[
        "Mottekuni"
    ],
    "wof:name":"Mottekuni",
    "wof:placetype":"locality",
    "wof:population":79
},
  "geometry": {"coordinates":[74.383978,14.541659],"type":"Point"}
}