{
  "type": "Feature",
  "properties": {
    "gn:admin1_code":"19.0",
    "gn:admin2_code":"568.0",
    "gn:asciiname":"Chunchinakoppa",
    "gn:country_code":"IN",
    "gn:dem":609,
    "gn:feature_class":"P",
    "gn:feature_code":"PPL",
    "gn:name":"Chunchinakoppa",
    "gn:population":0,
    "gn:timezone":"Asia/Kolkata",
    "iso:country":"IN",
    "wof:name":"Chunchinakoppa",
    "wof:placetype":"locality"
},
  "geometry": {"coordinates":[75.30169000000002,14.24261],"type":"Point"}
}