{
  "type": "Feature",
  "properties": {
    "iso:country":"IN",
    "ks:ks_name":"Dhadkigora",
    "ks:ks_pop":0,
    "ks:ks_type":"VILLAGE",
    "name:eng_x_preferred":[
        "Dhadkigora"
    ],
    "wof:name":"Dhadkigora",
    "wof:placetype":"locality",
    "wof:population":0
},
  "geometry": {"coordinates":[86.74839,23.251846],"type":"Point"}
}