{
  "type": "Feature",
  "properties": {
    "gn:admin1_code":"12.0",
    "gn:asciiname":"Barwan",
    "gn:country_code":"IN",
    "gn:dem":2187,
    "gn:feature_class":"P",
    "gn:feature_code":"PPL",
    "gn:name":"Barwan",
    "gn:population":0,
    "gn:timezone":"Asia/Kolkata",
    "iso:country":"IN",
    "wof:name":"Barwan",
    "wof:placetype":"locality"
},
  "geometry": {"coordinates":[73.89023,34.38627],"type":"Point"}
}