{
  "type": "Feature",
  "properties": {
    "iso:country":"IN",
    "ks:ks_alt_nam":"2 BKM",
    "ks:ks_name":"2 Bkm",
    "ks:ks_pop":133,
    "ks:ks_type":"HABITATION",
    "name:eng_x_preferred":[
        "2 Bkm"
    ],
    "wof:name":"2 Bkm",
    "wof:placetype":"locality",
    "wof:population":133
},
  "geometry": {"coordinates":[73.633017,29.114591],"type":"Point"}
}