{
  "type": "Feature",
  "properties": {
    "gn:admin1_code":"19.0",
    "gn:admin2_code":"574.0",
    "gn:asciiname":"Buka",
    "gn:country_code":"IN",
    "gn:dem":871,
    "gn:feature_class":"P",
    "gn:feature_code":"PPL",
    "gn:name":"B\u016bka",
    "gn:population":0,
    "gn:timezone":"Asia/Kolkata",
    "iso:country":"IN",
    "name:ceb_x_preferred":[
        "Buka"
    ],
    "name:deu_x_preferred":[
        "Buka"
    ],
    "name:nld_x_preferred":[
        "Buka"
    ],
    "name:pol_x_preferred":[
        "Buka"
    ],
    "name:rus_x_preferred":[
        "\u0411\u0443\u043a\u0430"
    ],
    "name:swe_x_preferred":[
        "Buka"
    ],
    "name:ukr_x_preferred":[
        "\u0411\u0443\u043a\u0430"
    ],
    "name:uzb_x_preferred":[
        "Bo\u02bbka"
    ],
    "wof:name":"Buka",
    "wof:placetype":"locality"
},
  "geometry": {"coordinates":[76.56413000000001,12.94008],"type":"Point"}
}