{
  "type": "Feature",
  "properties": {
    "gn:admin1_code":"19.0",
    "gn:admin2_code":"569.0",
    "gn:asciiname":"Surgee Katte Hadi",
    "gn:country_code":"IN",
    "gn:dem":48,
    "gn:feature_class":"P",
    "gn:feature_code":"PPL",
    "gn:name":"Surgee Katte Hadi",
    "gn:population":0,
    "gn:timezone":"Asia/Kolkata",
    "iso:country":"IN",
    "wof:name":"Surgee Katte Hadi",
    "wof:placetype":"locality"
},
  "geometry": {"coordinates":[74.81704999999999,13.49585],"type":"Point"}
}