{
  "type": "Feature",
  "properties": {
    "gn:admin1_code":"25.0",
    "gn:admin2_code":"621.0",
    "gn:asciiname":"Pallavaranpatti",
    "gn:country_code":"IN",
    "gn:dem":63,
    "gn:feature_class":"P",
    "gn:feature_code":"PPL",
    "gn:name":"Pallavar\u0101npatti",
    "gn:population":0,
    "gn:timezone":"Asia/Kolkata",
    "iso:country":"IN",
    "wof:name":"Pallavaranpatti",
    "wof:placetype":"locality"
},
  "geometry": {"coordinates":[79.09668000000001,10.57987],"type":"Point"}
}