{
  "type": "Feature",
  "properties": {
    "iso:country":"IN",
    "ks:ks_name":"Konattu",
    "ks:ks_pop":144,
    "ks:ks_type":"HABITATION",
    "name:eng_x_preferred":[
        "Konattu"
    ],
    "wof:name":"Konattu",
    "wof:placetype":"locality",
    "wof:population":144
},
  "geometry": {"coordinates":[74.76106900000001,13.557947],"type":"Point"}
}