{
  "type": "Feature",
  "properties": {
    "iso:country":"IN",
    "ks:ks_name":"Kafal Gaon Bichla",
    "ks:ks_pop":62,
    "ks:ks_type":"VILLAGE",
    "name:eng_x_preferred":[
        "Kafal Gaon Bichla"
    ],
    "wof:name":"Kafal Gaon Bichla",
    "wof:placetype":"locality",
    "wof:population":62
},
  "geometry": {"coordinates":[79.128005,29.9247],"type":"Point"}
}