{
  "type": "Feature",
  "properties": {
    "iso:country":"IN",
    "ks:ks_name":"Susnigerya",
    "ks:ks_pop":3971,
    "ks:ks_type":"VILLAGE",
    "ks:ks_uagg_main":0,
    "name:eng_x_preferred":[
        "Susnigerya"
    ],
    "wof:name":"Susnigerya",
    "wof:placetype":"neighbourhood",
    "wof:population":3971
},
  "geometry": {"coordinates":[86.2075,22.754175],"type":"Point"}
}