{
  "type": "Feature",
  "properties": {
    "iso:country":"IN",
    "ks:ks_name":"Ligri Bari N.C.",
    "ks:ks_pop":441,
    "ks:ks_type":"VILLAGE",
    "name:eng_x_preferred":[
        "Ligri Bari N.C."
    ],
    "wof:name":"Ligri Bari N.C.",
    "wof:placetype":"locality",
    "wof:population":441
},
  "geometry": {"coordinates":[94.542056,27.055331],"type":"Point"}
}