{
  "type": "Feature",
  "properties": {
    "gn:admin1_code":"36",
    "gn:admin2_code":"134.0",
    "gn:asciiname":"Tukhmanpur Harbans",
    "gn:country_code":"IN",
    "gn:dem":245,
    "gn:feature_class":"P",
    "gn:feature_code":"PPL",
    "gn:name":"Tukhm\u0101npur Harbans",
    "gn:population":0,
    "gn:timezone":"Asia/Kolkata",
    "iso:country":"IN",
    "wof:name":"Tukhmanpur Harbans",
    "wof:placetype":"locality"
},
  "geometry": {"coordinates":[78.46449,29.44773],"type":"Point"}
}