{
  "type": "Feature",
  "properties": {
    "gn:admin1_code":"23",
    "gn:admin2_code":"35.0",
    "gn:asciiname":"Tibbar",
    "gn:country_code":"IN",
    "gn:dem":265,
    "gn:feature_class":"P",
    "gn:feature_code":"PPL",
    "gn:name":"Tibbar",
    "gn:population":0,
    "gn:timezone":"Asia/Kolkata",
    "iso:country":"IN",
    "name:und_x_variant":[
        "Tibber",
        "Tibbar"
    ],
    "wof:name":"Tibbar",
    "wof:placetype":"locality"
},
  "geometry": {"coordinates":[75.41592,31.96973],"type":"Point"}
}