{
  "type": "Feature",
  "properties": {
    "iso:country":"IN",
    "ks:ks_name":"Raba",
    "ks:ks_pop":716,
    "ks:ks_type":"VILLAGE",
    "name:eng_x_preferred":[
        "Raba"
    ],
    "wof:name":"Raba",
    "wof:placetype":"locality",
    "wof:population":716
},
  "geometry": {"coordinates":[85.315636,21.678087],"type":"Point"}
}