{
  "type": "Feature",
  "properties": {
    "iso:country":"IN",
    "ks:ks_alt_nam":"PIPAL SARI FALI",
    "ks:ks_name":"Pipal Sari Fali",
    "ks:ks_pop":100,
    "ks:ks_type":"HABITATION",
    "name:eng_x_preferred":[
        "Pipal Sari Fali"
    ],
    "wof:name":"Pipal Sari Fali",
    "wof:placetype":"locality",
    "wof:population":100
},
  "geometry": {"coordinates":[72.95460799999999,24.473506],"type":"Point"}
}