{
  "type": "Feature",
  "properties": {
    "iso:country":"IN",
    "ks:ks_name":"Mandanjala",
    "ks:ks_pop":105,
    "ks:ks_type":"HABITATION",
    "name:eng_x_preferred":[
        "Mandanjala"
    ],
    "wof:name":"Mandanjala",
    "wof:placetype":"locality",
    "wof:population":105
},
  "geometry": {"coordinates":[75.433381,12.919063],"type":"Point"}
}