{
  "type": "Feature",
  "properties": {
    "iso:country":"IN",
    "ks:ks_name":"Keshariya Wadi",
    "ks:ks_pop":45,
    "ks:ks_type":"HABITATION",
    "name:eng_x_preferred":[
        "Keshariya Wadi"
    ],
    "wof:name":"Keshariya Wadi",
    "wof:placetype":"locality",
    "wof:population":45
},
  "geometry": {"coordinates":[74.68403600000001,22.58224],"type":"Point"}
}