{
  "type": "Feature",
  "properties": {
    "gn:admin1_code":"34.0",
    "gn:admin2_code":"204.0",
    "gn:asciiname":"Bairiya",
    "gn:country_code":"IN",
    "gn:dem":68,
    "gn:feature_class":"P",
    "gn:feature_code":"PPL",
    "gn:name":"Bairiy\u0101",
    "gn:population":0,
    "gn:timezone":"Asia/Kolkata",
    "iso:country":"IN",
    "ks:ks_alt_nam":"Bairiy\u0101",
    "ks:ks_name":"Bairiya",
    "ks:ks_pop":1493,
    "ks:ks_type":"VILLAGE",
    "ks:ks_uagg_main":0,
    "name:ceb_x_preferred":[
        "Bairiya"
    ],
    "name:eng_x_preferred":[
        "Bairiya"
    ],
    "name:eng_x_variant":[
        "Bairiy\u0101"
    ],
    "name:hin_x_preferred":[
        "\u092c\u0948\u0930\u093f\u092f\u093e"
    ],
    "name:mai_x_preferred":[
        "\u092c\u0948\u0930\u093f\u092f\u093e"
    ],
    "name:msa_x_preferred":[
        "Bairiya"
    ],
    "name:new_x_preferred":[
        "\u092c\u0948\u0930\u093f\u092f\u093e"
    ],
    "name:pol_x_preferred":[
        "Bairiya"
    ],
    "wof:name":"Bairiya",
    "wof:placetype":"neighbourhood",
    "wof:population":1493
},
  "geometry": {"coordinates":[84.825813,26.330787],"type":"Point"}
}