{
  "type": "Feature",
  "properties": {
    "iso:country":"IN",
    "ks:ks_name":"Gowranga Pur",
    "ks:ks_pop":321,
    "ks:ks_type":"VILLAGE",
    "name:eng_x_preferred":[
        "Gowranga Pur"
    ],
    "wof:name":"Gowranga Pur",
    "wof:placetype":"locality",
    "wof:population":321
},
  "geometry": {"coordinates":[94.783832,27.611806],"type":"Point"}
}