{
  "type": "Feature",
  "properties": {
    "gn:admin1_code":"3.0",
    "gn:admin2_code":"300.0",
    "gn:asciiname":"Khoiraghutu",
    "gn:country_code":"IN",
    "gn:dem":48,
    "gn:feature_class":"P",
    "gn:feature_code":"PPL",
    "gn:name":"Khoiraghutu",
    "gn:population":0,
    "gn:timezone":"Asia/Kolkata",
    "iso:country":"IN",
    "wof:name":"Khoiraghutu",
    "wof:placetype":"locality"
},
  "geometry": {"coordinates":[89.87696,26.42249],"type":"Point"}
}