{
  "type": "Feature",
  "properties": {
    "iso:country":"IN",
    "ks:ks_name":"Hiretemminal",
    "ks:ks_pop":988,
    "ks:ks_type":"HABITATION",
    "name:eng_x_preferred":[
        "Hiretemminal"
    ],
    "wof:name":"Hiretemminal",
    "wof:placetype":"locality",
    "wof:population":988
},
  "geometry": {"coordinates":[76.411069,15.69242],"type":"Point"}
}