{
  "type": "Feature",
  "properties": {
    "iso:country":"IN",
    "ks:ks_alt_nam":"Jugs\u0101lai",
    "ks:ks_alt_nam_2":"Jugsalai",
    "ks:ks_name":"Bagbera",
    "ks:ks_pop":67121,
    "ks:ks_type":"VILLAGE",
    "ks:ks_uagg_main":0,
    "name:eng_x_preferred":[
        "Bagbera"
    ],
    "name:eng_x_variant":[
        "Jugs\u0101lai",
        "Jugsalai"
    ],
    "name:hin_x_preferred":[
        "\u092c\u093e\u0917\u092c\u0947\u0930\u093e"
    ],
    "wof:name":"Bagbera",
    "wof:placetype":"neighbourhood",
    "wof:population":67121
},
  "geometry": {"coordinates":[86.183509,22.776684],"type":"Point"}
}