{
  "type": "Feature",
  "properties": {
    "iso:country":"IN",
    "ks:ks_name":"Dhaneshpur",
    "ks:ks_pop":412,
    "ks:ks_type":"VILLAGE",
    "name:eng_x_preferred":[
        "Dhaneshpur"
    ],
    "wof:name":"Dhaneshpur",
    "wof:placetype":"locality",
    "wof:population":412
},
  "geometry": {"coordinates":[84.00960499999999,23.224351],"type":"Point"}
}