{
  "type": "Feature",
  "properties": {
    "iso:country":"IN",
    "ks:ks_alt_nam":"Kavungal south",
    "ks:ks_name":"Kavungal South",
    "ks:ks_pop":2774,
    "ks:ks_type":"HABITATION",
    "name:eng_x_preferred":[
        "Kavungal South"
    ],
    "wof:name":"Kavungal South",
    "wof:placetype":"neighbourhood",
    "wof:population":2774
},
  "geometry": {"coordinates":[76.35257300000001,9.588443],"type":"Point"}
}