{
  "type": "Feature",
  "properties": {
    "gn:admin1_code":"2.0",
    "gn:admin2_code":"551.0",
    "gn:asciiname":"Chikativaripalle",
    "gn:country_code":"IN",
    "gn:dem":211,
    "gn:feature_class":"P",
    "gn:feature_code":"PPL",
    "gn:name":"Ch\u012bkativ\u0101ripalle",
    "gn:population":0,
    "gn:timezone":"Asia/Kolkata",
    "iso:country":"IN",
    "ks:ks_name":"Cheekativaripalle",
    "ks:ks_pop":183,
    "ks:ks_type":"HABITATION",
    "name:eng_x_preferred":[
        "Cheekativaripalle"
    ],
    "name:eng_x_variant":[
        "Chikativaripalle"
    ],
    "wof:name":"Cheekativaripalle",
    "wof:placetype":"locality",
    "wof:population":183
},
  "geometry": {"coordinates":[78.900566,14.730685],"type":"Point"}
}