{
  "type": "Feature",
  "properties": {
    "gn:admin1_code":"35.0",
    "gn:admin2_code":"463.0",
    "gn:asciiname":"Dala",
    "gn:country_code":"IN",
    "gn:dem":429,
    "gn:feature_class":"P",
    "gn:feature_code":"PPL",
    "gn:name":"D\u0101la",
    "gn:population":0,
    "gn:timezone":"Asia/Kolkata",
    "iso:country":"IN",
    "name:ceb_x_preferred":[
        "Dala"
    ],
    "name:deu_x_preferred":[
        "Dala"
    ],
    "name:fin_x_preferred":[
        "Dala"
    ],
    "name:fra_x_preferred":[
        "Dala"
    ],
    "name:ita_x_preferred":[
        "Dala"
    ],
    "name:nld_x_preferred":[
        "Dala"
    ],
    "name:swe_x_preferred":[
        "Dala"
    ],
    "wof:name":"Dala",
    "wof:placetype":"locality"
},
  "geometry": {"coordinates":[82.62465999999998,24.27664],"type":"Point"}
}