{
  "type": "Feature",
  "properties": {
    "iso:country":"IN",
    "ks:ks_name":"Buddigar Gajgarh",
    "ks:ks_pop":245,
    "ks:ks_type":"VILLAGE",
    "name:eng_x_preferred":[
        "Buddigar Gajgarh"
    ],
    "wof:name":"Buddigar Gajgarh",
    "wof:placetype":"locality",
    "wof:population":245
},
  "geometry": {"coordinates":[78.748672,22.612499],"type":"Point"}
}