{
  "type": "Feature",
  "properties": {
    "gn:admin1_code":"13.0",
    "gn:admin2_code":"600",
    "gn:asciiname":"Kondalseri",
    "gn:country_code":"IN",
    "gn:dem":23,
    "gn:feature_class":"P",
    "gn:feature_code":"PPL",
    "gn:name":"Kond\u0101lseri",
    "gn:population":0,
    "gn:timezone":"Asia/Kolkata",
    "iso:country":"IN",
    "wof:name":"Kondalseri",
    "wof:placetype":"locality"
},
  "geometry": {"coordinates":[76.65954000000001,8.80213],"type":"Point"}
}