{
  "type": "Feature",
  "properties": {
    "gn:admin1_code":"2.0",
    "gn:admin2_code":"553",
    "gn:asciiname":"Honnuru",
    "gn:country_code":"IN",
    "gn:dem":446,
    "gn:feature_class":"P",
    "gn:feature_code":"PPL",
    "gn:name":"Honn\u016bru",
    "gn:population":0,
    "gn:timezone":"Asia/Kolkata",
    "iso:country":"IN",
    "wof:name":"Honnuru",
    "wof:placetype":"neighbourhood"
},
  "geometry": {"coordinates":[77.08571999999999,14.90806],"type":"Point"}
}