{
  "type": "Feature",
  "properties": {
    "iso:country":"IN",
    "ks:ks_name":"Chyoli",
    "ks:ks_pop":80,
    "ks:ks_type":"VILLAGE",
    "name:eng_x_preferred":[
        "Chyoli"
    ],
    "wof:name":"Chyoli",
    "wof:placetype":"locality",
    "wof:population":80
},
  "geometry": {"coordinates":[79.02756100000001,30.114864],"type":"Point"}
}