{
  "type": "Feature",
  "properties": {
    "iso:country":"IN",
    "ks:ks_alt_nam":"VATTAPARAMBU",
    "ks:ks_name":"Vattaparambu",
    "ks:ks_pop":1918,
    "ks:ks_type":"HABITATION",
    "name:eng_x_preferred":[
        "Vattaparambu"
    ],
    "wof:name":"Vattaparambu",
    "wof:placetype":"locality",
    "wof:population":1918
},
  "geometry": {"coordinates":[76.095406,10.830492],"type":"Point"}
}