{
  "type": "Feature",
  "properties": {
    "iso:country":"IN",
    "ks:ks_name":"Kamargadia",
    "ks:ks_pop":169,
    "ks:ks_type":"VILLAGE",
    "ks:ks_uagg_main":0,
    "name:eng_x_preferred":[
        "Kamargadia"
    ],
    "wof:name":"Kamargadia",
    "wof:placetype":"locality",
    "wof:population":169
},
  "geometry": {"coordinates":[87.41866400000001,21.668306],"type":"Point"}
}