{
  "type": "Feature",
  "properties": {
    "gn:admin1_code":"36.0",
    "gn:admin2_code":"179.0",
    "gn:asciiname":"Rusha Dih",
    "gn:country_code":"IN",
    "gn:dem":106,
    "gn:feature_class":"P",
    "gn:feature_code":"PPL",
    "gn:name":"Rusha D\u012bh",
    "gn:population":0,
    "gn:timezone":"Asia/Kolkata",
    "iso:country":"IN",
    "wof:name":"Rusha Dih",
    "wof:placetype":"neighbourhood"
},
  "geometry": {"coordinates":[81.84672999999999,26.33628],"type":"Point"}
}