{
  "type": "Feature",
  "properties": {
    "iso:country":"IN",
    "ks:ks_name":"Therkku Sanganthiradu",
    "ks:ks_pop":420,
    "ks:ks_type":"HABITATION",
    "name:eng_x_preferred":[
        "Therkku Sanganthiradu"
    ],
    "wof:name":"Therkku Sanganthiradu",
    "wof:placetype":"locality",
    "wof:population":420
},
  "geometry": {"coordinates":[77.566085,8.704827],"type":"Point"}
}