{
  "type": "Feature",
  "properties": {
    "iso:country":"IN",
    "ks:ks_name":"Chirirpar Kachari Punji",
    "ks:ks_pop":391,
    "ks:ks_type":"HABITATION",
    "name:eng_x_preferred":[
        "Chirirpar Kachari Punji"
    ],
    "wof:name":"Chirirpar Kachari Punji",
    "wof:placetype":"locality",
    "wof:population":391
},
  "geometry": {"coordinates":[93.070083,24.948093],"type":"Point"}
}