{
  "type": "Feature",
  "properties": {
    "gn:admin1_code":"23.0",
    "gn:admin2_code":"44.0",
    "gn:asciiname":"Khaneke Dhab",
    "gn:country_code":"IN",
    "gn:dem":194,
    "gn:feature_class":"P",
    "gn:feature_code":"PPL",
    "gn:name":"Kh\u0101neke Dh\u0101b",
    "gn:population":0,
    "gn:timezone":"Asia/Kolkata",
    "iso:country":"IN",
    "wof:name":"Khaneke Dhab",
    "wof:placetype":"locality"
},
  "geometry": {"coordinates":[74.45475,30.30694],"type":"Point"}
}