{
  "type": "Feature",
  "properties": {
    "iso:country":"IN",
    "ks:ks_name":"Valani",
    "ks:ks_pop":1164,
    "ks:ks_type":"HABITATION",
    "name:eng_x_preferred":[
        "Valani"
    ],
    "wof:name":"Valani",
    "wof:placetype":"locality",
    "wof:population":1164
},
  "geometry": {"coordinates":[76.195021,11.115188],"type":"Point"}
}