{
  "type": "Feature",
  "properties": {
    "iso:country":"IN",
    "ks:ks_name":"Pedatankidi",
    "ks:ks_pop":141,
    "ks:ks_type":"VILLAGE",
    "name:eng_x_preferred":[
        "Pedatankidi"
    ],
    "wof:name":"Pedatankidi",
    "wof:placetype":"locality",
    "wof:population":141
},
  "geometry": {"coordinates":[83.697164,18.725391],"type":"Point"}
}