{
  "type": "Feature",
  "properties": {
    "gn:admin1_code":"2.0",
    "gn:admin2_code":"549.0",
    "gn:asciiname":"Gannavaram",
    "gn:country_code":"IN",
    "gn:dem":29,
    "gn:feature_class":"P",
    "gn:feature_code":"PPL",
    "gn:name":"Gannavaram",
    "gn:population":0,
    "gn:timezone":"Asia/Kolkata",
    "iso:country":"IN",
    "wof:name":"Gannavaram",
    "wof:placetype":"locality"
},
  "geometry": {"coordinates":[80.17300999999998,15.96797],"type":"Point"}
}