{
  "type": "Feature",
  "properties": {
    "gn:admin1_code":"2.0",
    "gn:admin2_code":"549.0",
    "gn:asciiname":"Gannavaram",
    "gn:country_code":"IN",
    "gn:dem":29,
    "gn:feature_class":"P",
    "gn:feature_code":"PPL",
    "gn:name":"Gannavaram",
    "gn:population":0,
    "gn:timezone":"Asia/Kolkata",
    "iso:country":"IN",
    "name:ceb_x_preferred":[
        "Gannavaram"
    ],
    "name:hin_x_preferred":[
        "\u0917\u0928\u094d\u0928\u0935\u0930\u0902"
    ],
    "name:new_x_preferred":[
        "\u0917\u0928\u094d\u0928\u0935\u0930\u0902"
    ],
    "name:swe_x_preferred":[
        "Gannavaram"
    ],
    "name:tel_x_preferred":[
        "\u0c17\u0c28\u0c4d\u0c28\u0c35\u0c30\u0c02"
    ],
    "name:urd_x_preferred":[
        "\u06af\u0646\u0627\u0648\u0631\u0645"
    ],
    "wof:name":"Gannavaram",
    "wof:placetype":"locality"
},
  "geometry": {"coordinates":[80.17300999999998,15.96797],"type":"Point"}
}