{
  "type": "Feature",
  "properties": {
    "iso:country":"IN",
    "ks:ks_alt_nam":"Diblong III",
    "ks:ks_name":"Diblong Iii",
    "ks:ks_pop":6,
    "ks:ks_type":"HABITATION",
    "name:eng_x_preferred":[
        "Diblong Iii"
    ],
    "wof:name":"Diblong Iii",
    "wof:placetype":"locality",
    "wof:population":6
},
  "geometry": {"coordinates":[93.096311,25.609108],"type":"Point"}
}