{
  "type": "Feature",
  "properties": {
    "iso:country":"IN",
    "ks:ks_name":"Vadakku Veliyanadu",
    "ks:ks_pop":715,
    "ks:ks_type":"HABITATION",
    "ks:ks_uagg_main":0,
    "name:eng_x_preferred":[
        "Vadakku Veliyanadu"
    ],
    "wof:name":"Vadakku Veliyanadu",
    "wof:placetype":"neighbourhood",
    "wof:population":715
},
  "geometry": {"coordinates":[76.467189,9.453459],"type":"Point"}
}