{
  "type": "Feature",
  "properties": {
    "iso:country":"IN",
    "ks:ks_name":"Patharghata",
    "ks:ks_pop":6905,
    "ks:ks_type":"VILLAGE",
    "ks:ks_uagg_main":0,
    "name:eng_x_preferred":[
        "Patharghata"
    ],
    "wof:name":"Patharghata",
    "wof:placetype":"locality",
    "wof:population":6905
},
  "geometry": {"coordinates":[88.501429,22.569982],"type":"Point"}
}