{
  "type": "Feature",
  "properties": {
    "iso:country":"IN",
    "ks:ks_name":"Doolalli",
    "ks:ks_pop":22,
    "ks:ks_type":"HABITATION",
    "name:eng_x_preferred":[
        "Doolalli"
    ],
    "wof:name":"Doolalli",
    "wof:placetype":"locality",
    "wof:population":22
},
  "geometry": {"coordinates":[74.73490099999999,14.764487],"type":"Point"}
}