{
  "type": "Feature",
  "properties": {
    "iso:country":"IN",
    "ks:ks_alt_nam":"IGRU",
    "ks:ks_name":"Igru",
    "ks:ks_pop":1051,
    "ks:ks_type":"HABITATION",
    "name:eng_x_preferred":[
        "Igru"
    ],
    "wof:name":"Igru",
    "wof:placetype":"locality",
    "wof:population":1051
},
  "geometry": {"coordinates":[84.394701,23.943412],"type":"Point"}
}