{
  "type": "Feature",
  "properties": {
    "gn:admin1_code":"36",
    "gn:admin2_code":"158.0",
    "gn:asciiname":"Mahabir Bakhsh Purwa",
    "gn:country_code":"IN",
    "gn:dem":112,
    "gn:feature_class":"P",
    "gn:feature_code":"PPL",
    "gn:name":"Mah\u0101b\u012br Bakhsh Purwa",
    "gn:population":0,
    "gn:timezone":"Asia/Kolkata",
    "iso:country":"IN",
    "wof:name":"Mahabir Bakhsh Purwa",
    "wof:placetype":"locality"
},
  "geometry": {"coordinates":[81.37838000000001,26.08614],"type":"Point"}
}