{
  "type": "Feature",
  "properties": {
    "iso:country":"IN",
    "ks:ks_name":"Padali Gujar",
    "ks:ks_type":"VILLAGE",
    "ks:ks_uagg_main":0,
    "name:eng_x_preferred":[
        "Padali Gujar"
    ],
    "wof:name":"Padali Gujar",
    "wof:placetype":"neighbourhood"
},
  "geometry": {"coordinates":[77.870969,29.845681],"type":"Point"}
}