{
  "type": "Feature",
  "properties": {
    "iso:country":"IN",
    "ks:ks_name":"Sirusengulipatti",
    "ks:ks_pop":238,
    "ks:ks_type":"HABITATION",
    "name:eng_x_preferred":[
        "Sirusengulipatti"
    ],
    "wof:name":"Sirusengulipatti",
    "wof:placetype":"locality",
    "wof:population":238
},
  "geometry": {"coordinates":[78.59356,9.907667],"type":"Point"}
}