{
  "type": "Feature",
  "properties": {
    "gn:admin1_code":"2",
    "gn:admin2_code":"544.0",
    "gn:asciiname":"Mulakarayabayalu",
    "gn:country_code":"IN",
    "gn:dem":802,
    "gn:feature_class":"P",
    "gn:feature_code":"PPL",
    "gn:name":"Mulakar\u0101yabayalu",
    "gn:population":0,
    "gn:timezone":"Asia/Kolkata",
    "iso:country":"IN",
    "wof:name":"Mulakarayabayalu",
    "wof:placetype":"locality"
},
  "geometry": {"coordinates":[82.40065,17.84212999999999],"type":"Point"}
}