{
  "type": "Feature",
  "properties": {
    "gn:admin1_code":"39.0",
    "gn:admin2_code":"63.0",
    "gn:asciiname":"Gogni",
    "gn:country_code":"IN",
    "gn:dem":1486,
    "gn:feature_class":"P",
    "gn:feature_code":"PPL",
    "gn:name":"Gogni",
    "gn:population":0,
    "gn:timezone":"Asia/Kolkata",
    "iso:country":"IN",
    "wof:name":"Gogni",
    "wof:placetype":"locality"
},
  "geometry": {"coordinates":[79.81669000000002,29.8475],"type":"Point"}
}