{
  "type": "Feature",
  "properties": {
    "iso:country":"IN",
    "ks:ks_name":"Basko",
    "ks:ks_pop":208,
    "ks:ks_type":"VILLAGE",
    "name:eng_x_preferred":[
        "Basko"
    ],
    "wof:name":"Basko",
    "wof:placetype":"locality",
    "wof:population":208
},
  "geometry": {"coordinates":[87.544667,24.628239],"type":"Point"}
}