{
  "type": "Feature",
  "properties": {
    "gn:admin1_code":"24.0",
    "gn:admin2_code":"104",
    "gn:asciiname":"Dugal Kota",
    "gn:country_code":"IN",
    "gn:dem":279,
    "gn:feature_class":"P",
    "gn:feature_code":"PPL",
    "gn:name":"D\u016bgal Kota",
    "gn:population":0,
    "gn:timezone":"Asia/Kolkata",
    "iso:country":"IN",
    "name:und_x_variant":[
        "D\u016bgal Kota",
        "Gugal Kota"
    ],
    "wof:name":"Dugal Kota",
    "wof:placetype":"neighbourhood"
},
  "geometry": {"coordinates":[76.47714999999999,28.02935],"type":"Point"}
}