{
  "type": "Feature",
  "properties": {
    "iso:country":"IN",
    "ks:ks_name":"Kantu Falia",
    "ks:ks_pop":365,
    "ks:ks_type":"HABITATION",
    "name:eng_x_preferred":[
        "Kantu Falia"
    ],
    "wof:name":"Kantu Falia",
    "wof:placetype":"locality",
    "wof:population":365
},
  "geometry": {"coordinates":[73.6942,22.527883],"type":"Point"}
}