{
  "type": "Feature",
  "properties": {
    "gn:admin1_code":"21.0",
    "gn:admin2_code":"399.0",
    "gn:asciiname":"Tharvada",
    "gn:country_code":"IN",
    "gn:dem":501,
    "gn:feature_class":"P",
    "gn:feature_code":"PPL",
    "gn:name":"Tharv\u0101da",
    "gn:population":0,
    "gn:timezone":"Asia/Kolkata",
    "iso:country":"IN",
    "wof:name":"Tharvada",
    "wof:placetype":"neighbourhood"
},
  "geometry": {"coordinates":[82.29304,18.24898],"type":"Point"}
}