{
  "type": "Feature",
  "properties": {
    "iso:country":"IN",
    "ks:ks_alt_nam":"Kikara falia",
    "ks:ks_name":"Kikara Falia",
    "ks:ks_pop":1126,
    "ks:ks_type":"HABITATION",
    "name:eng_x_preferred":[
        "Kikara Falia"
    ],
    "wof:name":"Kikara Falia",
    "wof:placetype":"locality",
    "wof:population":1126
},
  "geometry": {"coordinates":[74.421278,22.804111],"type":"Point"}
}