{
  "type": "Feature",
  "properties": {
    "iso:country":"IN",
    "ks:ks_alt_nam":"Lower Dhobia kura",
    "ks:ks_name":"Lower Dhobia Kura",
    "ks:ks_pop":343,
    "ks:ks_type":"HABITATION",
    "name:eng_x_preferred":[
        "Lower Dhobia Kura"
    ],
    "wof:name":"Lower Dhobia Kura",
    "wof:placetype":"locality",
    "wof:population":343
},
  "geometry": {"coordinates":[86.37682700000001,24.760446],"type":"Point"}
}