{
  "type": "Feature",
  "properties": {
    "iso:country":"IN",
    "ks:ks_name":"Madhaliwadi",
    "ks:ks_pop":396,
    "ks:ks_type":"HABITATION",
    "name:eng_x_preferred":[
        "Madhaliwadi"
    ],
    "wof:name":"Madhaliwadi",
    "wof:placetype":"locality",
    "wof:population":396
},
  "geometry": {"coordinates":[73.393118,16.483445],"type":"Point"}
}