{
  "type": "Feature",
  "properties": {
    "iso:country":"IN",
    "ks:ks_name":"Duburai",
    "ks:ks_pop":322,
    "ks:ks_type":"HABITATION",
    "name:eng_x_preferred":[
        "Duburai"
    ],
    "wof:name":"Duburai",
    "wof:placetype":"locality",
    "wof:population":322
},
  "geometry": {"coordinates":[87.020504,21.559559],"type":"Point"}
}