{
  "type": "Feature",
  "properties": {
    "iso:country":"IN",
    "ks:ks_name":"Forest Block",
    "ks:ks_pop":10,
    "ks:ks_type":"VILLAGE",
    "name:eng_x_preferred":[
        "Forest Block"
    ],
    "wof:name":"Forest Block",
    "wof:placetype":"locality",
    "wof:population":10
},
  "geometry": {"coordinates":[86.090439,22.840971],"type":"Point"}
}