{
  "type": "Feature",
  "properties": {
    "iso:country":"IN",
    "ks:ks_name":"Posani",
    "ks:ks_pop":1533,
    "ks:ks_type":"VILLAGE",
    "name:eng_x_preferred":[
        "Posani"
    ],
    "wof:name":"Posani",
    "wof:placetype":"locality",
    "wof:population":1533
},
  "geometry": {"coordinates":[75.19731299999999,27.805259],"type":"Point"}
}