{
  "type": "Feature",
  "properties": {
    "iso:country":"IN",
    "ks:ks_name":"Hunnur Sarpali Vasti",
    "ks:ks_pop":249,
    "ks:ks_type":"HABITATION",
    "name:eng_x_preferred":[
        "Hunnur Sarpali Vasti"
    ],
    "wof:name":"Hunnur Sarpali Vasti",
    "wof:placetype":"locality",
    "wof:population":249
},
  "geometry": {"coordinates":[75.311245,16.466998],"type":"Point"}
}