{
  "type": "Feature",
  "properties": {
    "iso:country":"IN",
    "ks:ks_name":"N. Garhi",
    "ks:ks_pop":496,
    "ks:ks_type":"HABITATION",
    "ks:ks_uagg_main":0,
    "name:eng_x_preferred":[
        "N. Garhi"
    ],
    "wof:name":"N. Garhi",
    "wof:placetype":"neighbourhood",
    "wof:population":496
},
  "geometry": {"coordinates":[78.660659,27.249126],"type":"Point"}
}