{
  "type": "Feature",
  "properties": {
    "gn:admin1_code":"19.0",
    "gn:admin2_code":"577.0",
    "gn:asciiname":"Hemmanhalli",
    "gn:country_code":"IN",
    "gn:dem":757,
    "gn:feature_class":"P",
    "gn:feature_code":"PPL",
    "gn:name":"Hemmanhalli",
    "gn:population":0,
    "gn:timezone":"Asia/Kolkata",
    "iso:country":"IN",
    "wof:name":"Hemmanhalli",
    "wof:placetype":"locality"
},
  "geometry": {"coordinates":[76.48094,12.41794],"type":"Point"}
}