{
  "type": "Feature",
  "properties": {
    "gn:admin1_code":"36.0",
    "gn:admin2_code":"137.0",
    "gn:asciiname":"Ujhari",
    "gn:country_code":"IN",
    "gn:dem":205,
    "gn:feature_class":"P",
    "gn:feature_code":"PPL",
    "gn:name":"Ujh\u0101ri",
    "gn:population":0,
    "gn:timezone":"Asia/Kolkata",
    "iso:country":"IN",
    "name:bpy_x_preferred":[
        "\u0989\u099d\u09be\u09b0\u09bf"
    ],
    "name:ita_x_preferred":[
        "Ujhari"
    ],
    "name:msa_x_preferred":[
        "Ujhari"
    ],
    "name:nld_x_preferred":[
        "Ujhari"
    ],
    "name:pol_x_preferred":[
        "Ujhari"
    ],
    "name:por_x_preferred":[
        "Ujhari"
    ],
    "name:urd_x_preferred":[
        "\u0627\u0648\u062c\u06be\u0627\u0631\u06cc"
    ],
    "name:vie_x_preferred":[
        "Ujhari"
    ],
    "name:zho_x_preferred":[
        "\u4e4c\u8d3e\u91cc"
    ],
    "wof:name":"Ujhari",
    "wof:placetype":"locality"
},
  "geometry": {"coordinates":[78.35791,28.65879],"type":"Point"}
}