{
  "type": "Feature",
  "properties": {
    "gn:admin1_code":"39.0",
    "gn:admin2_code":"061",
    "gn:asciiname":"Jui",
    "gn:country_code":"IN",
    "gn:dem":1035,
    "gn:feature_class":"P",
    "gn:feature_code":"PPL",
    "gn:name":"Jui",
    "gn:population":0,
    "gn:timezone":"Asia/Kolkata",
    "iso:country":"IN",
    "name:spa_x_preferred":[
        "Jui"
    ],
    "wof:name":"Jui",
    "wof:placetype":"locality"
},
  "geometry": {"coordinates":[78.72684,29.83835],"type":"Point"}
}