{
  "type": "Feature",
  "properties": {
    "gn:admin1_code":"35.0",
    "gn:admin2_code":"455.0",
    "gn:asciiname":"Mordongri Khurd",
    "gn:country_code":"IN",
    "gn:dem":716,
    "gn:feature_class":"P",
    "gn:feature_code":"PPL",
    "gn:name":"Mordongri Khurd",
    "gn:population":0,
    "gn:timezone":"Asia/Kolkata",
    "iso:country":"IN",
    "wof:name":"Mordongri Khurd",
    "wof:placetype":"locality"
},
  "geometry": {"coordinates":[78.66715000000001,22.04761],"type":"Point"}
}