{
  "type": "Feature",
  "properties": {
    "iso:country":"IN",
    "ks:ks_name":"Erate",
    "ks:ks_pop":29,
    "ks:ks_type":"HABITATION",
    "name:eng_x_preferred":[
        "Erate"
    ],
    "wof:name":"Erate",
    "wof:placetype":"locality",
    "wof:population":29
},
  "geometry": {"coordinates":[75.33989800000001,12.803057],"type":"Point"}
}