{
  "type": "Feature",
  "properties": {
    "gn:admin1_code":"19.0",
    "gn:admin2_code":"564.0",
    "gn:asciiname":"Varaha",
    "gn:country_code":"IN",
    "gn:dem":638,
    "gn:feature_class":"P",
    "gn:feature_code":"PPL",
    "gn:name":"Varaha",
    "gn:population":0,
    "gn:timezone":"Asia/Kolkata",
    "iso:country":"IN",
    "name:ben_x_preferred":[
        "\u09ac\u09b0\u09be\u09b9"
    ],
    "name:bre_x_preferred":[
        "Var\u00e2ha"
    ],
    "name:cat_x_preferred":[
        "Varaha"
    ],
    "name:deu_x_preferred":[
        "Varaha"
    ],
    "name:ell_x_preferred":[
        "\u0392\u03b1\u03c1\u03ac\u03c7\u03b1"
    ],
    "name:fra_x_preferred":[
        "Var\u00e2ha"
    ],
    "name:hin_x_preferred":[
        "\u0935\u0930\u093e\u0939\u093e\u0935\u0924\u093e\u0930"
    ],
    "name:hun_x_preferred":[
        "Var\u00e1ha"
    ],
    "name:ind_x_preferred":[
        "Waraha"
    ],
    "name:ita_x_preferred":[
        "Var\u0101ha"
    ],
    "name:jav_x_preferred":[
        "Waraha"
    ],
    "name:jpn_x_preferred":[
        "\u30f4\u30a1\u30e9\u30fc\u30cf"
    ],
    "name:kan_x_preferred":[
        "\u0cb5\u0cb0\u0cbe\u0cb9\u0cbe\u0cb5\u0ca4\u0cbe\u0cb0"
    ],
    "name:mai_x_preferred":[
        "\u092c\u0930\u093e\u0939 \u0905\u0935\u0924\u093e\u0930"
    ],
    "name:mal_x_preferred":[
        "\u0d35\u0d30\u0d3e\u0d39\u0d02"
    ],
    "name:mar_x_preferred":[
        "\u0935\u0930\u093e\u0939 \u0905\u0935\u0924\u093e\u0930"
    ],
    "name:msa_x_preferred":[
        "Waraha"
    ],
    "name:nep_x_preferred":[
        "\u092c\u0930\u093e\u0939 \u0905\u0935\u0924\u093e\u0930"
    ],
    "name:nld_x_preferred":[
        "Varaha"
    ],
    "name:nno_x_preferred":[
        "Varaha"
    ],
    "name:ori_x_preferred":[
        "\u0b2c\u0b30\u0b3e\u0b39"
    ],
    "name:pan_x_preferred":[
        "\u0a35\u0a30\u0a3e\u0a39\u0a3e"
    ],
    "name:pol_x_preferred":[
        "Waraha"
    ],
    "name:por_x_preferred":[
        "Varaha"
    ],
    "name:ron_x_preferred":[
        "Varaha"
    ],
    "name:rus_x_preferred":[
        "\u0412\u0430\u0440\u0430\u0445\u0430"
    ],
    "name:spa_x_preferred":[
        "Varaja"
    ],
    "name:swe_x_preferred":[
        "Varaha"
    ],
    "name:tam_x_preferred":[
        "\u0bb5\u0bb0\u0bbe\u0b95 \u0b85\u0bb5\u0ba4\u0bbe\u0bb0\u0bae\u0bcd"
    ],
    "name:tat_x_preferred":[
        "\u0412\u0430\u0440\u0430\u0445\u0430"
    ],
    "name:tel_x_preferred":[
        "\u0c35\u0c30\u0c3e\u0c39\u0c3e\u0c35\u0c24\u0c3e\u0c30\u0c2e\u0c41"
    ],
    "name:tha_x_preferred":[
        "\u0e1e\u0e23\u0e30\u0e27\u0e23\u0e32\u0e2b\u0e30"
    ],
    "name:tur_x_preferred":[
        "Varaha"
    ],
    "name:ukr_x_preferred":[
        "\u0412\u0430\u0440\u0430\u0445\u0430"
    ],
    "name:urd_x_preferred":[
        "\u0648\u0631\u0627\u06c1"
    ],
    "name:zho_x_preferred":[
        "\u7b4f\u7f57\u8bc3"
    ],
    "wof:name":"Varaha",
    "wof:placetype":"locality"
},
  "geometry": {"coordinates":[75.37193000000001,14.39108],"type":"Point"}
}