{
  "type": "Feature",
  "properties": {
    "iso:country":"IN",
    "ks:ks_name":"Madipu",
    "ks:ks_pop":24,
    "ks:ks_type":"HABITATION",
    "name:eng_x_preferred":[
        "Madipu"
    ],
    "wof:name":"Madipu",
    "wof:placetype":"locality",
    "wof:population":24
},
  "geometry": {"coordinates":[75.452524,12.783419],"type":"Point"}
}