{
  "type": "Feature",
  "properties": {
    "iso:country":"IN",
    "ks:ks_alt_nam":"chamtol2",
    "ks:ks_name":"Chamtol2",
    "ks:ks_pop":117,
    "ks:ks_type":"HABITATION",
    "name:eng_x_preferred":[
        "Chamtol2"
    ],
    "wof:name":"Chamtol2",
    "wof:placetype":"locality",
    "wof:population":117
},
  "geometry": {"coordinates":[83.3152,25.035111],"type":"Point"}
}