{
  "type": "Feature",
  "properties": {
    "iso:country":"IN",
    "ks:ks_name":"Udai Tola",
    "ks:ks_pop":105,
    "ks:ks_type":"HABITATION",
    "name:eng_x_preferred":[
        "Udai Tola"
    ],
    "wof:name":"Udai Tola",
    "wof:placetype":"locality",
    "wof:population":105
},
  "geometry": {"coordinates":[86.68293,22.566931],"type":"Point"}
}