{
  "type": "Feature",
  "properties": {
    "gn:admin1_code":"21.0",
    "gn:admin2_code":"397.0",
    "gn:asciiname":"Dhansulipara",
    "gn:country_code":"IN",
    "gn:dem":644,
    "gn:feature_class":"P",
    "gn:feature_code":"PPL",
    "gn:name":"Dhansulip\u0101ra",
    "gn:population":0,
    "gn:timezone":"Asia/Kolkata",
    "iso:country":"IN",
    "wof:name":"Dhansulipara",
    "wof:placetype":"locality"
},
  "geometry": {"coordinates":[81.96941,19.87614],"type":"Point"}
}