{
  "type": "Feature",
  "properties": {
    "gn:admin1_code":"34.0",
    "gn:admin2_code":"237.0",
    "gn:asciiname":"Bishunathpur",
    "gn:country_code":"IN",
    "gn:dem":59,
    "gn:feature_class":"P",
    "gn:feature_code":"PPL",
    "gn:name":"Bishun\u0101thpur",
    "gn:population":0,
    "gn:timezone":"Asia/Kolkata",
    "iso:country":"IN",
    "ks:ks_alt_nam":"BISHWANATHPUR",
    "ks:ks_name":"Bishwanathpur",
    "ks:ks_pop":255,
    "ks:ks_type":"HABITATION",
    "name:eng_x_preferred":[
        "Bishwanathpur"
    ],
    "name:eng_x_variant":[
        "Bishunathpur"
    ],
    "wof:name":"Bishwanathpur",
    "wof:placetype":"locality",
    "wof:population":255
},
  "geometry": {"coordinates":[85.76458599999999,25.092343],"type":"Point"}
}