{
  "type": "Feature",
  "properties": {
    "iso:country":"IN",
    "ks:ks_name":"Anantpur Gangauli",
    "ks:ks_pop":2097,
    "ks:ks_type":"VILLAGE",
    "name:eng_x_preferred":[
        "Anantpur Gangauli"
    ],
    "wof:name":"Anantpur Gangauli",
    "wof:placetype":"locality",
    "wof:population":2097
},
  "geometry": {"coordinates":[85.26610700000001,26.017281],"type":"Point"}
}