{
  "type": "Feature",
  "properties": {
    "iso:country":"IN",
    "ks:ks_name":"Thimiri",
    "ks:ks_pop":1903,
    "ks:ks_type":"VILLAGE",
    "name:eng_x_preferred":[
        "Thimiri"
    ],
    "wof:name":"Thimiri",
    "wof:placetype":"locality",
    "wof:population":1903
},
  "geometry": {"coordinates":[75.38610799999999,12.200054],"type":"Point"}
}