{
  "type": "Feature",
  "properties": {
    "iso:country":"IN",
    "ks:ks_name":"Chathuwa",
    "ks:ks_pop":3063,
    "ks:ks_type":"VILLAGE",
    "name:eng_x_preferred":[
        "Chathuwa"
    ],
    "wof:name":"Chathuwa",
    "wof:placetype":"locality",
    "wof:population":3063
},
  "geometry": {"coordinates":[81.52760000000001,26.4113],"type":"Point"}
}