{
  "type": "Feature",
  "properties": {
    "gn:admin1_code":"34.0",
    "gn:admin2_code":"203.0",
    "gn:asciiname":"Chanpatia",
    "gn:country_code":"IN",
    "gn:dem":99,
    "gn:feature_class":"P",
    "gn:feature_code":"PPL",
    "gn:name":"Chanpati\u0101",
    "gn:population":0,
    "gn:timezone":"Asia/Kolkata",
    "iso:country":"IN",
    "name:ben_x_preferred":[
        "\u099a\u09be\u09a8\u09aa\u09be\u09a4\u09bf\u09af\u09bc\u09be"
    ],
    "name:bpy_x_preferred":[
        "\u099a\u09be\u09a8\u09aa\u09be\u09a4\u09bf\u09af\u09bc\u09be"
    ],
    "name:ita_x_preferred":[
        "Chanpatia"
    ],
    "name:msa_x_preferred":[
        "Chanpatia"
    ],
    "name:new_x_preferred":[
        "\u091a\u0928\u094d\u092a\u091f\u093f\u092f\u093e"
    ],
    "name:nld_x_preferred":[
        "Chanpatia"
    ],
    "name:por_x_preferred":[
        "Chanpatia"
    ],
    "name:spa_x_preferred":[
        "Chanpatia"
    ],
    "name:vie_x_preferred":[
        "Chanpatia"
    ],
    "name:zho_x_preferred":[
        "\u94b1\u5e15\u8482\u4e9a"
    ],
    "wof:name":"Chanpatia",
    "wof:placetype":"locality"
},
  "geometry": {"coordinates":[84.55266999999998,27.17406],"type":"Point"}
}