{
  "type": "Feature",
  "properties": {
    "gn:admin1_code":"36",
    "gn:admin2_code":"180.0",
    "gn:asciiname":"Sadarkha",
    "gn:country_code":"IN",
    "gn:dem":114,
    "gn:feature_class":"P",
    "gn:feature_code":"PPL",
    "gn:name":"Sadarkha",
    "gn:population":0,
    "gn:timezone":"Asia/Kolkata",
    "iso:country":"IN",
    "wof:name":"Sadarkha",
    "wof:placetype":"neighbourhood"
},
  "geometry": {"coordinates":[81.55542,27.31767],"type":"Point"}
}