{
  "type": "Feature",
  "properties": {
    "iso:country":"IN",
    "ks:ks_name":"Katarepada",
    "ks:ks_pop":45,
    "ks:ks_type":"HABITATION",
    "name:eng_x_preferred":[
        "Katarepada"
    ],
    "wof:name":"Katarepada",
    "wof:placetype":"locality",
    "wof:population":45
},
  "geometry": {"coordinates":[73.024869,19.680417],"type":"Point"}
}