{
  "type": "Feature",
  "properties": {
    "iso:country":"IN",
    "ks:ks_name":"Painsara",
    "ks:ks_pop":489,
    "ks:ks_type":"VILLAGE",
    "name:eng_x_preferred":[
        "Painsara"
    ],
    "wof:name":"Painsara",
    "wof:placetype":"locality",
    "wof:population":489
},
  "geometry": {"coordinates":[81.598215,19.838047],"type":"Point"}
}