{
  "type": "Feature",
  "properties": {
    "gn:admin1_code":"19.0",
    "gn:admin2_code":"584.0",
    "gn:asciiname":"Hammahallidoddi",
    "gn:country_code":"IN",
    "gn:dem":647,
    "gn:feature_class":"P",
    "gn:feature_code":"PPL",
    "gn:name":"Hammahallidoddi",
    "gn:population":0,
    "gn:timezone":"Asia/Kolkata",
    "iso:country":"IN",
    "wof:name":"Hammahallidoddi",
    "wof:placetype":"neighbourhood"
},
  "geometry": {"coordinates":[77.23276,12.59223],"type":"Point"}
}