{
  "type": "Feature",
  "properties": {
    "iso:country":"IN",
    "ks:ks_name":"Sonawani",
    "ks:ks_pop":0,
    "ks:ks_type":"VILLAGE",
    "name:eng_x_preferred":[
        "Sonawani"
    ],
    "wof:name":"Sonawani",
    "wof:placetype":"locality",
    "wof:population":0
},
  "geometry": {"coordinates":[79.85712700000001,21.923385],"type":"Point"}
}