{
  "type": "Feature",
  "properties": {
    "iso:country":"IN",
    "ks:ks_alt_nam":"Kappalavari peta",
    "ks:ks_name":"Kappalavari Peta",
    "ks:ks_pop":193,
    "ks:ks_type":"HABITATION",
    "name:eng_x_preferred":[
        "Kappalavari Peta"
    ],
    "wof:name":"Kappalavari Peta",
    "wof:placetype":"locality",
    "wof:population":193
},
  "geometry": {"coordinates":[82.252517,16.601231],"type":"Point"}
}