{
  "type": "Feature",
  "properties": {
    "iso:country":"IN",
    "ks:ks_name":"Vazhappara",
    "ks:ks_pop":1328,
    "ks:ks_type":"HABITATION",
    "name:eng_x_preferred":[
        "Vazhappara"
    ],
    "wof:name":"Vazhappara",
    "wof:placetype":"locality",
    "wof:population":1328
},
  "geometry": {"coordinates":[76.887158,9.10722],"type":"Point"}
}