{
  "type": "Feature",
  "properties": {
    "iso:country":"IN",
    "ks:ks_name":"Gattapad",
    "ks:ks_pop":403,
    "ks:ks_type":"HABITATION",
    "name:eng_x_preferred":[
        "Gattapad"
    ],
    "wof:name":"Gattapad",
    "wof:placetype":"locality",
    "wof:population":403
},
  "geometry": {"coordinates":[81.15322500000001,18.063539],"type":"Point"}
}