{
  "type": "Feature",
  "properties": {
    "iso:country":"IN",
    "ks:ks_name":"Gadaipur",
    "ks:ks_pop":1172,
    "ks:ks_type":"HABITATION",
    "ks:ks_uagg_main":0,
    "name:eng_x_preferred":[
        "Gadaipur"
    ],
    "wof:name":"Gadaipur",
    "wof:placetype":"neighbourhood",
    "wof:population":1172
},
  "geometry": {"coordinates":[88.049725,24.467843],"type":"Point"}
}