{
  "type": "Feature",
  "properties": {
    "iso:country":"IN",
    "ks:ks_alt_nam":"Kumaria BA",
    "ks:ks_name":"Kumaria Ba",
    "ks:ks_pop":24,
    "ks:ks_type":"HABITATION",
    "ks:ks_uagg_main":0,
    "name:eng_x_preferred":[
        "Kumaria Ba"
    ],
    "wof:name":"Kumaria Ba",
    "wof:placetype":"neighbourhood",
    "wof:population":24
},
  "geometry": {"coordinates":[78.101444,29.080693],"type":"Point"}
}