{
  "type": "Feature",
  "properties": {
    "iso:country":"IN",
    "ks:ks_name":"Gidhauli",
    "ks:ks_pop":150,
    "ks:ks_type":"VILLAGE",
    "name:eng_x_preferred":[
        "Gidhauli"
    ],
    "wof:name":"Gidhauli",
    "wof:placetype":"locality",
    "wof:population":150
},
  "geometry": {"coordinates":[83.104276,25.293408],"type":"Point"}
}