{
  "type": "Feature",
  "properties": {
    "gn:admin1_code":"36",
    "gn:admin2_code":"200.0",
    "gn:asciiname":"Kaspani",
    "gn:country_code":"IN",
    "gn:dem":214,
    "gn:feature_class":"P",
    "gn:feature_code":"PPL",
    "gn:name":"K\u0101sp\u0101ni",
    "gn:population":0,
    "gn:timezone":"Asia/Kolkata",
    "iso:country":"IN",
    "ks:ks_name":"Kaspani",
    "ks:ks_pop":775,
    "ks:ks_type":"HABITATION",
    "name:eng_x_preferred":[
        "Kaspani"
    ],
    "wof:name":"Kaspani",
    "wof:placetype":"locality",
    "wof:population":775
},
  "geometry": {"coordinates":[82.913912,24.466996],"type":"Point"}
}