{
  "type": "Feature",
  "properties": {
    "iso:country":"IN",
    "ks:ks_name":"Ramagoundanur",
    "ks:ks_pop":401,
    "ks:ks_type":"HABITATION",
    "ks:ks_uagg_main":0,
    "name:eng_x_preferred":[
        "Ramagoundanur"
    ],
    "wof:name":"Ramagoundanur",
    "wof:placetype":"neighbourhood",
    "wof:population":401
},
  "geometry": {"coordinates":[78.028488,11.888777],"type":"Point"}
}