{
  "type": "Feature",
  "properties": {
    "iso:country":"IN",
    "ks:ks_name":"Mahuajara",
    "ks:ks_pop":235,
    "ks:ks_type":"HABITATION",
    "name:eng_x_preferred":[
        "Mahuajara"
    ],
    "wof:name":"Mahuajara",
    "wof:placetype":"locality",
    "wof:population":235
},
  "geometry": {"coordinates":[85.254099,23.555517],"type":"Point"}
}