{
  "type": "Feature",
  "properties": {
    "gn:admin1_code":"21",
    "gn:admin2_code":"381.0",
    "gn:asciiname":"Natara",
    "gn:country_code":"IN",
    "gn:dem":18,
    "gn:feature_class":"P",
    "gn:feature_code":"PPL",
    "gn:name":"Natara",
    "gn:population":0,
    "gn:timezone":"Asia/Kolkata",
    "iso:country":"IN",
    "wof:name":"Natara",
    "wof:placetype":"locality"
},
  "geometry": {"coordinates":[86.17008,20.46396],"type":"Point"}
}