{
  "type": "Feature",
  "properties": {
    "gn:admin1_code":"21",
    "gn:admin2_code":"381.0",
    "gn:asciiname":"Natara",
    "gn:country_code":"IN",
    "gn:dem":18,
    "gn:feature_class":"P",
    "gn:feature_code":"PPL",
    "gn:name":"Natara",
    "gn:population":0,
    "gn:timezone":"Asia/Kolkata",
    "iso:country":"IN",
    "name:ara_x_preferred":[
        "\u0646\u0627\u062a\u0627\u0631\u0627"
    ],
    "name:ben_x_preferred":[
        "\u09a8\u09be\u09a4\u09be\u09b0\u09be"
    ],
    "name:deu_x_preferred":[
        "Natara"
    ],
    "name:ell_x_preferred":[
        "\u039d\u03b1\u03c4\u03ac\u03c1\u03b1"
    ],
    "name:eng_x_preferred":[
        "Natara"
    ],
    "name:fas_x_preferred":[
        "\u0646\u0627\u062a\u0627\u0631\u0627"
    ],
    "name:fra_x_preferred":[
        "Natara"
    ],
    "name:heb_x_preferred":[
        "\u05e0\u05d8\u05e8\u05d4"
    ],
    "name:hin_x_preferred":[
        "\u0928\u0924\u093e\u0930\u093e"
    ],
    "name:hun_x_preferred":[
        "Natara"
    ],
    "name:ind_x_preferred":[
        "Natara"
    ],
    "name:ita_x_preferred":[
        "Natara"
    ],
    "name:jpn_x_preferred":[
        "\u30ca\u30bf\u30e9"
    ],
    "name:kor_x_preferred":[
        "\ub098\ud0c0\ub77c"
    ],
    "name:nld_x_preferred":[
        "Natara"
    ],
    "name:pol_x_preferred":[
        "Natara"
    ],
    "name:por_x_preferred":[
        "Natara"
    ],
    "name:rus_x_preferred":[
        "\u041d\u0430\u0442\u0430\u0440\u0430"
    ],
    "name:spa_x_preferred":[
        "Natara"
    ],
    "name:swe_x_preferred":[
        "Natara"
    ],
    "name:tur_x_preferred":[
        "Natara"
    ],
    "name:ukr_x_preferred":[
        "\u041d\u0430\u0442\u0430\u0440\u0430"
    ],
    "name:urd_x_preferred":[
        "\u0646\u0627\u062a\u0627\u0631\u0627"
    ],
    "name:vie_x_preferred":[
        "Natara"
    ],
    "name:zho_cn_x_preferred":[
        "\u540d\u826f"
    ],
    "name:zho_tw_x_preferred":[
        "\u7d0d\u5854\u62c9"
    ],
    "wof:name":"Natara",
    "wof:placetype":"locality"
},
  "geometry": {"coordinates":[86.17008,20.46396],"type":"Point"}
}