{
  "type": "Feature",
  "properties": {
    "iso:country":"IN",
    "ks:ks_name":"Neredumanuguda",
    "ks:ks_pop":25,
    "ks:ks_type":"HABITATION",
    "name:eng_x_preferred":[
        "Neredumanuguda"
    ],
    "wof:name":"Neredumanuguda",
    "wof:placetype":"locality",
    "wof:population":25
},
  "geometry": {"coordinates":[83.770839,18.885107],"type":"Point"}
}