{
  "type": "Feature",
  "properties": {
    "iso:country":"IN",
    "ks:ks_name":"Kulavaipatty",
    "ks:ks_pop":103,
    "ks:ks_type":"HABITATION",
    "name:eng_x_preferred":[
        "Kulavaipatty"
    ],
    "wof:name":"Kulavaipatty",
    "wof:placetype":"locality",
    "wof:population":103
},
  "geometry": {"coordinates":[78.707517,10.544609],"type":"Point"}
}