{
  "type": "Feature",
  "properties": {
    "iso:country":"IN",
    "ks:ks_name":"Naduapal",
    "ks:ks_pop":174,
    "ks:ks_type":"VILLAGE",
    "ks:ks_uagg_main":0,
    "name:eng_x_preferred":[
        "Naduapal"
    ],
    "wof:name":"Naduapal",
    "wof:placetype":"neighbourhood",
    "wof:population":174
},
  "geometry": {"coordinates":[86.766914,21.581083],"type":"Point"}
}