{
  "type": "Feature",
  "properties": {
    "iso:country":"IN",
    "ks:ks_name":"Madigapalli",
    "ks:ks_pop":151,
    "ks:ks_type":"HABITATION",
    "name:eng_x_preferred":[
        "Madigapalli"
    ],
    "wof:name":"Madigapalli",
    "wof:placetype":"locality",
    "wof:population":151
},
  "geometry": {"coordinates":[79.19816,14.297249],"type":"Point"}
}