{
  "type": "Feature",
  "properties": {
    "gn:admin1_code":"24.0",
    "gn:admin2_code":"116",
    "gn:asciiname":"Bakra",
    "gn:country_code":"IN",
    "gn:dem":138,
    "gn:feature_class":"P",
    "gn:feature_code":"PPL",
    "gn:name":"B\u0101kra",
    "gn:population":0,
    "gn:timezone":"Asia/Kolkata",
    "iso:country":"IN",
    "name:und_x_variant":[
        "Bakra-Road",
        "B\u0101kra"
    ],
    "wof:name":"Bakra",
    "wof:placetype":"locality"
},
  "geometry": {"coordinates":[72.45664000000002,25.25337],"type":"Point"}
}