{
  "type": "Feature",
  "properties": {
    "iso:country":"IN",
    "ks:ks_name":"Gulbaha",
    "ks:ks_pop":287,
    "ks:ks_type":"HABITATION",
    "name:eng_x_preferred":[
        "Gulbaha"
    ],
    "wof:name":"Gulbaha",
    "wof:placetype":"locality",
    "wof:population":287
},
  "geometry": {"coordinates":[80.180196,26.965905],"type":"Point"}
}