{
  "type": "Feature",
  "properties": {
    "iso:country":"IN",
    "ks:ks_name":"Anthapura",
    "ks:ks_pop":952,
    "ks:ks_type":"VILLAGE",
    "name:eng_x_preferred":[
        "Anthapura"
    ],
    "wof:name":"Anthapura",
    "wof:placetype":"locality",
    "wof:population":952
},
  "geometry": {"coordinates":[76.893283,13.477443],"type":"Point"}
}