{
  "type": "Feature",
  "properties": {
    "iso:country":"IN",
    "ks:ks_name":"Paiyur Kattukudiyiauppu",
    "ks:ks_pop":453,
    "ks:ks_type":"HABITATION",
    "name:eng_x_preferred":[
        "Paiyur Kattukudiyiauppu"
    ],
    "wof:name":"Paiyur Kattukudiyiauppu",
    "wof:placetype":"locality",
    "wof:population":453
},
  "geometry": {"coordinates":[78.524322,9.85594],"type":"Point"}
}