{
  "type": "Feature",
  "properties": {
    "gn:admin1_code":"34.0",
    "gn:admin2_code":"235.0",
    "gn:asciiname":"Kalalbigha",
    "gn:country_code":"IN",
    "gn:dem":148,
    "gn:feature_class":"P",
    "gn:feature_code":"PPL",
    "gn:name":"Kal\u0101lbigh\u0101",
    "gn:population":0,
    "gn:timezone":"Asia/Kolkata",
    "iso:country":"IN",
    "ks:ks_alt_nam":"kalash Bigha",
    "ks:ks_name":"Kalash Bigha",
    "ks:ks_pop":102,
    "ks:ks_type":"HABITATION",
    "name:eng_x_preferred":[
        "Kalash Bigha"
    ],
    "name:eng_x_variant":[
        "Kalalbigha"
    ],
    "wof:name":"Kalash Bigha",
    "wof:placetype":"locality",
    "wof:population":102
},
  "geometry": {"coordinates":[84.44494,24.60713],"type":"Point"}
}