{
  "type": "Feature",
  "properties": {
    "gn:admin1_code":"34.0",
    "gn:admin2_code":"235.0",
    "gn:asciiname":"Kalalbigha",
    "gn:country_code":"IN",
    "gn:dem":148,
    "gn:feature_class":"P",
    "gn:feature_code":"PPL",
    "gn:name":"Kal\u0101lbigh\u0101",
    "gn:population":0,
    "gn:timezone":"Asia/Kolkata",
    "iso:country":"IN",
    "wof:name":"Kalalbigha",
    "wof:placetype":"locality"
},
  "geometry": {"coordinates":[84.43588000000003,24.60606],"type":"Point"}
}