{
  "type": "Feature",
  "properties": {
    "iso:country":"IN",
    "ks:ks_name":"Durga High School Area Kukkundoor",
    "ks:ks_pop":300,
    "ks:ks_type":"HABITATION",
    "ks:ks_uagg_main":0,
    "name:eng_x_preferred":[
        "Durga High School Area Kukkundoor"
    ],
    "wof:name":"Durga High School Area Kukkundoor",
    "wof:placetype":"locality",
    "wof:population":300
},
  "geometry": {"coordinates":[74.984675,13.248376],"type":"Point"}
}