{
  "type": "Feature",
  "properties": {
    "iso:country":"IN",
    "ks:ks_name":"Kothapeta",
    "ks:ks_pop":62,
    "ks:ks_type":"HABITATION",
    "name:eng_x_preferred":[
        "Kothapeta"
    ],
    "wof:name":"Kothapeta",
    "wof:placetype":"locality",
    "wof:population":62
},
  "geometry": {"coordinates":[83.945859,18.724068],"type":"Point"}
}