{
  "type": "Feature",
  "properties": {
    "gn:admin1_code":"13.0",
    "gn:admin2_code":"590.0",
    "gn:asciiname":"Pacchati",
    "gn:country_code":"IN",
    "gn:dem":926,
    "gn:feature_class":"P",
    "gn:feature_code":"PPL",
    "gn:name":"Pacch\u0101ti",
    "gn:population":0,
    "gn:timezone":"Asia/Kolkata",
    "iso:country":"IN",
    "wof:name":"Pacchati",
    "wof:placetype":"locality"
},
  "geometry": {"coordinates":[76.27685,11.71564],"type":"Point"}
}