{
  "type": "Feature",
  "properties": {
    "iso:country":"IN",
    "ks:ks_name":"Jhumukaposi",
    "ks:ks_pop":401,
    "ks:ks_type":"VILLAGE",
    "name:eng_x_preferred":[
        "Jhumukaposi"
    ],
    "wof:name":"Jhumukaposi",
    "wof:placetype":"locality",
    "wof:population":401
},
  "geometry": {"coordinates":[85.603505,21.44967],"type":"Point"}
}