{
  "type": "Feature",
  "properties": {
    "iso:country":"IN",
    "ks:ks_alt_nam":"BAMHANI",
    "ks:ks_name":"Bamhani",
    "ks:ks_pop":156,
    "ks:ks_type":"HABITATION",
    "name:eng_x_preferred":[
        "Bamhani"
    ],
    "wof:name":"Bamhani",
    "wof:placetype":"locality",
    "wof:population":156
},
  "geometry": {"coordinates":[83.805453,23.055193],"type":"Point"}
}