{
  "type": "Feature",
  "properties": {
    "gn:admin1_code":"39",
    "gn:admin2_code":"57.0",
    "gn:asciiname":"Ringi",
    "gn:country_code":"IN",
    "gn:dem":2101,
    "gn:feature_class":"P",
    "gn:feature_code":"PPL",
    "gn:name":"Ringi",
    "gn:population":0,
    "gn:timezone":"Asia/Kolkata",
    "iso:country":"IN",
    "name:und_x_variant":[
        "Rini"
    ],
    "wof:name":"Ringi",
    "wof:placetype":"locality"
},
  "geometry": {"coordinates":[79.65141,30.48509],"type":"Point"}
}