{
  "type": "Feature",
  "properties": {
    "iso:country":"IN",
    "ks:ks_name":"Pothurajumetta",
    "ks:ks_pop":96,
    "ks:ks_type":"HABITATION",
    "name:eng_x_preferred":[
        "Pothurajumetta"
    ],
    "wof:name":"Pothurajumetta",
    "wof:placetype":"locality",
    "wof:population":96
},
  "geometry": {"coordinates":[82.622658,18.052525],"type":"Point"}
}