{
  "type": "Feature",
  "properties": {
    "gn:admin1_code":"36.0",
    "gn:admin2_code":"158.0",
    "gn:asciiname":"Sarai Madho",
    "gn:country_code":"IN",
    "gn:dem":114,
    "gn:feature_class":"P",
    "gn:feature_code":"PPL",
    "gn:name":"Sar\u0101i M\u0101dho",
    "gn:population":0,
    "gn:timezone":"Asia/Kolkata",
    "iso:country":"IN",
    "ks:ks_alt_nam":"Sar\u0101i M\u0101dho",
    "ks:ks_name":"Sarai Madho",
    "ks:ks_pop":941,
    "ks:ks_type":"VILLAGE",
    "ks:ks_uagg_main":0,
    "name:eng_x_preferred":[
        "Sarai Madho"
    ],
    "name:eng_x_variant":[
        "Sar\u0101i M\u0101dho"
    ],
    "wof:name":"Sarai Madho",
    "wof:placetype":"neighbourhood",
    "wof:population":941
},
  "geometry": {"coordinates":[81.514377,26.53871],"type":"Point"}
}