{
  "type": "Feature",
  "properties": {
    "iso:country":"IN",
    "ks:ks_name":"Gufa",
    "ks:ks_pop":14,
    "ks:ks_type":"HABITATION",
    "name:eng_x_preferred":[
        "Gufa"
    ],
    "wof:name":"Gufa",
    "wof:placetype":"locality",
    "wof:population":14
},
  "geometry": {"coordinates":[81.348553,19.221743],"type":"Point"}
}