{
  "type": "Feature",
  "properties": {
    "gn:admin1_code":"19.0",
    "gn:admin2_code":"573.0",
    "gn:asciiname":"Mallarajapura",
    "gn:country_code":"IN",
    "gn:dem":861,
    "gn:feature_class":"P",
    "gn:feature_code":"PPL",
    "gn:name":"Mallar\u0101j\u0101pura",
    "gn:population":0,
    "gn:timezone":"Asia/Kolkata",
    "iso:country":"IN",
    "ks:ks_alt_nam":"Mallar\u0101j\u0101pura",
    "ks:ks_name":"Mallarajapura",
    "ks:ks_pop":121,
    "ks:ks_type":"VILLAGE",
    "name:eng_x_preferred":[
        "Mallarajapura"
    ],
    "name:eng_x_variant":[
        "Mallar\u0101j\u0101pura"
    ],
    "wof:name":"Mallarajapura",
    "wof:placetype":"locality",
    "wof:population":121
},
  "geometry": {"coordinates":[76.710247,12.887322],"type":"Point"}
}