{
  "type": "Feature",
  "properties": {
    "gn:admin1_code":"24.0",
    "gn:admin2_code":"114",
    "gn:asciiname":"Phojdaran Ki Dhani",
    "gn:country_code":"IN",
    "gn:dem":225,
    "gn:feature_class":"P",
    "gn:feature_code":"PPL",
    "gn:name":"Phojd\u0101r\u0101n Ki Dh\u0101ni",
    "gn:population":0,
    "gn:timezone":"Asia/Kolkata",
    "iso:country":"IN",
    "wof:name":"Phojdaran Ki Dhani",
    "wof:placetype":"locality"
},
  "geometry": {"coordinates":[71.88015,26.5679],"type":"Point"}
}