{
  "type": "Feature",
  "properties": {
    "iso:country":"IN",
    "ks:ks_name":"Purba Bowthakurani",
    "ks:ks_pop":778,
    "ks:ks_type":"HABITATION",
    "name:eng_x_preferred":[
        "Purba Bowthakurani"
    ],
    "wof:name":"Purba Bowthakurani",
    "wof:placetype":"locality",
    "wof:population":778
},
  "geometry": {"coordinates":[88.911995,22.378442],"type":"Point"}
}