{
  "type": "Feature",
  "properties": {
    "iso:country":"IN",
    "ks:ks_name":"Hemawas",
    "ks:ks_pop":1117,
    "ks:ks_type":"HABITATION",
    "name:eng_x_preferred":[
        "Hemawas"
    ],
    "wof:name":"Hemawas",
    "wof:placetype":"locality",
    "wof:population":1117
},
  "geometry": {"coordinates":[71.234478,24.877353],"type":"Point"}
}