{
  "type": "Feature",
  "properties": {
    "iso:country":"IN",
    "ks:ks_name":"Murtikodla",
    "ks:ks_pop":119,
    "ks:ks_type":"HABITATION",
    "name:eng_x_preferred":[
        "Murtikodla"
    ],
    "wof:name":"Murtikodla",
    "wof:placetype":"locality",
    "wof:population":119
},
  "geometry": {"coordinates":[74.472146,14.297199],"type":"Point"}
}