{
  "type": "Feature",
  "properties": {
    "iso:country":"IN",
    "ks:ks_name":"Balighat",
    "ks:ks_pop":290,
    "ks:ks_type":"HABITATION",
    "name:eng_x_preferred":[
        "Balighat"
    ],
    "wof:name":"Balighat",
    "wof:placetype":"locality",
    "wof:population":290
},
  "geometry": {"coordinates":[82.87509,18.92361],"type":"Point"}
}