{
  "type": "Feature",
  "properties": {
    "iso:country":"IN",
    "ks:ks_alt_nam":"6 E RURAL",
    "ks:ks_name":"6 E Rural",
    "ks:ks_pop":52,
    "ks:ks_type":"HABITATION",
    "name:eng_x_preferred":[
        "6 E Rural"
    ],
    "wof:name":"6 E Rural",
    "wof:placetype":"locality",
    "wof:population":52
},
  "geometry": {"coordinates":[73.905119,29.905919],"type":"Point"}
}