{
  "type": "Feature",
  "properties": {
    "gn:admin1_code":"36",
    "gn:admin2_code":"198.0",
    "gn:asciiname":"Dadarha",
    "gn:country_code":"IN",
    "gn:dem":90,
    "gn:feature_class":"P",
    "gn:feature_code":"PPL",
    "gn:name":"Dadarha",
    "gn:population":0,
    "gn:timezone":"Asia/Kolkata",
    "iso:country":"IN",
    "ks:ks_name":"Dadaraha",
    "ks:ks_pop":307,
    "ks:ks_type":"VILLAGE",
    "ks:ks_uagg_main":0,
    "name:eng_x_preferred":[
        "Dadaraha"
    ],
    "wof:name":"Dadaraha",
    "wof:placetype":"locality",
    "wof:population":307
},
  "geometry": {"coordinates":[82.480509,25.337958],"type":"Point"}
}