{
  "type": "Feature",
  "properties": {
    "iso:country":"IN",
    "ks:ks_name":"Komarapalayam",
    "ks:ks_pop":1203,
    "ks:ks_type":"HABITATION",
    "ks:ks_uagg_main":0,
    "name:eng_x_preferred":[
        "Komarapalayam"
    ],
    "wof:name":"Komarapalayam",
    "wof:placetype":"locality",
    "wof:population":1203
},
  "geometry": {"coordinates":[77.764448,11.299393],"type":"Point"}
}