{
  "type": "Feature",
  "properties": {
    "iso:country":"IN",
    "ks:ks_name":"Mundatola",
    "ks:ks_pop":247,
    "ks:ks_type":"HABITATION",
    "name:eng_x_preferred":[
        "Mundatola"
    ],
    "wof:name":"Mundatola",
    "wof:placetype":"neighbourhood",
    "wof:population":247
},
  "geometry": {"coordinates":[84.914754,22.272931],"type":"Point"}
}