{
  "type": "Feature",
  "properties": {
    "gn:admin1_code":"36.0",
    "gn:admin2_code":"143.0",
    "gn:asciiname":"Ballamgarh",
    "gn:country_code":"IN",
    "gn:dem":188,
    "gn:feature_class":"P",
    "gn:feature_code":"PPL",
    "gn:name":"Ballamgarh",
    "gn:population":0,
    "gn:timezone":"Asia/Kolkata",
    "iso:country":"IN",
    "wof:name":"Ballamgarh",
    "wof:placetype":"neighbourhood"
},
  "geometry": {"coordinates":[77.81231,27.83206],"type":"Point"}
}