{
  "type": "Feature",
  "properties": {
    "gn:admin1_code":"36.0",
    "gn:admin2_code":"171.0",
    "gn:asciiname":"Purwa Ghog",
    "gn:country_code":"IN",
    "gn:dem":103,
    "gn:feature_class":"P",
    "gn:feature_code":"PPL",
    "gn:name":"Purwa Ghog",
    "gn:population":0,
    "gn:timezone":"Asia/Kolkata",
    "iso:country":"IN",
    "name:und_x_variant":[
        "Raghauli"
    ],
    "wof:name":"Purwa Ghog",
    "wof:placetype":"neighbourhood"
},
  "geometry": {"coordinates":[81.18509,25.35293],"type":"Point"}
}