{
  "type": "Feature",
  "properties": {
    "iso:country":"IN",
    "ks:ks_name":"Danduguda",
    "ks:ks_pop":293,
    "ks:ks_type":"VILLAGE",
    "name:eng_x_preferred":[
        "Danduguda"
    ],
    "wof:name":"Danduguda",
    "wof:placetype":"locality",
    "wof:population":293
},
  "geometry": {"coordinates":[82.77971700000001,19.204573],"type":"Point"}
}