{
  "type": "Feature",
  "properties": {
    "gn:admin1_code":"19.0",
    "gn:admin2_code":"577.0",
    "gn:asciiname":"Bogadi",
    "gn:country_code":"IN",
    "gn:dem":761,
    "gn:feature_class":"P",
    "gn:feature_code":"PPL",
    "gn:name":"Bog\u0101di",
    "gn:population":0,
    "gn:timezone":"Asia/Kolkata",
    "iso:country":"IN",
    "ks:ks_alt_nam":"Bog\u0101di",
    "ks:ks_name":"Bogadi",
    "ks:ks_type":"URBAN",
    "ks:ks_uagg_main":0,
    "name:ceb_x_preferred":[
        "Bogadi"
    ],
    "name:nep_x_preferred":[
        "\u092c\u094b\u0917\u093e\u0921\u0940"
    ],
    "name:new_x_preferred":[
        "\u092c\u094b\u0917\u093e\u0921\u0940"
    ],
    "name:pol_x_preferred":[
        "Bogadi"
    ],
    "name:vie_x_preferred":[
        "Bogadi"
    ],
    "wof:name":"Bogadi",
    "wof:placetype":"neighbourhood"
},
  "geometry": {"coordinates":[76.59820999999999,12.30301],"type":"Point"}
}