{
  "type": "Feature",
  "properties": {
    "gn:admin1_code":"37",
    "gn:admin2_code":"406.0",
    "gn:asciiname":"Amne",
    "gn:country_code":"IN",
    "gn:dem":308,
    "gn:feature_class":"P",
    "gn:feature_code":"PPL",
    "gn:name":"Amne",
    "gn:population":0,
    "gn:timezone":"Asia/Kolkata",
    "iso:country":"IN",
    "ks:ks_name":"Amne",
    "ks:ks_pop":1824,
    "ks:ks_type":"VILLAGE",
    "name:eng_x_preferred":[
        "Amne"
    ],
    "wof:name":"Amne",
    "wof:placetype":"locality",
    "wof:population":1824
},
  "geometry": {"coordinates":[81.998952,22.26872],"type":"Point"}
}