{
  "type": "Feature",
  "properties": {
    "iso:country":"IN",
    "ks:ks_name":"18 MOD",
    "ks:ks_pop":153,
    "ks:ks_type":"VILLAGE",
    "name:eng_x_preferred":[
        "18 MOD"
    ],
    "wof:name":"18 MOD",
    "wof:placetype":"locality",
    "wof:population":153
},
  "geometry": {"coordinates":[74.062658,29.605614],"type":"Point"}
}