{
  "type": "Feature",
  "properties": {
    "gn:admin1_code":"35",
    "gn:admin2_code":"425.0",
    "gn:asciiname":"Gauma Khurd",
    "gn:country_code":"IN",
    "gn:dem":235,
    "gn:feature_class":"P",
    "gn:feature_code":"PPL",
    "gn:name":"Gauma Khurd",
    "gn:population":0,
    "gn:timezone":"Asia/Kolkata",
    "iso:country":"IN",
    "ks:ks_name":"Gomakhurd",
    "ks:ks_pop":999,
    "ks:ks_type":"VILLAGE",
    "name:eng_x_preferred":[
        "Gomakhurd"
    ],
    "name:eng_x_variant":[
        "Gauma Khurd"
    ],
    "wof:name":"Gomakhurd",
    "wof:placetype":"locality",
    "wof:population":999
},
  "geometry": {"coordinates":[79.873963,24.984203],"type":"Point"}
}