{
  "type": "Feature",
  "properties": {
    "gn:admin1_code":"34",
    "gn:admin2_code":"233.0",
    "gn:asciiname":"Barahia",
    "gn:country_code":"IN",
    "gn:dem":70,
    "gn:feature_class":"P",
    "gn:feature_code":"PPL",
    "gn:name":"Barahia",
    "gn:population":0,
    "gn:timezone":"Asia/Kolkata",
    "iso:country":"IN",
    "ks:ks_name":"Barahiya",
    "ks:ks_pop":102,
    "ks:ks_type":"HABITATION",
    "name:eng_x_preferred":[
        "Barahiya"
    ],
    "name:eng_x_variant":[
        "Barahia"
    ],
    "wof:name":"Barahiya",
    "wof:placetype":"locality",
    "wof:population":102
},
  "geometry": {"coordinates":[83.630033,25.253958],"type":"Point"}
}