{
  "type": "Feature",
  "properties": {
    "iso:country":"IN",
    "ks:ks_alt_nam":"sindiputtuu",
    "ks:ks_name":"Sindiputtuu",
    "ks:ks_pop":34,
    "ks:ks_type":"HABITATION",
    "name:eng_x_preferred":[
        "Sindiputtuu"
    ],
    "wof:name":"Sindiputtuu",
    "wof:placetype":"locality",
    "wof:population":34
},
  "geometry": {"coordinates":[82.450064,17.983981],"type":"Point"}
}