{
  "type": "Feature",
  "properties": {
    "iso:country":"IN",
    "ks:ks_name":"Bara Raghunathpur",
    "ks:ks_pop":2304,
    "ks:ks_type":"VILLAGE",
    "ks:ks_uagg_main":0,
    "name:eng_x_preferred":[
        "Bara Raghunathpur"
    ],
    "wof:name":"Bara Raghunathpur",
    "wof:placetype":"locality",
    "wof:population":2304
},
  "geometry": {"coordinates":[88.78327299999999,25.245418],"type":"Point"}
}