{
  "type": "Feature",
  "properties": {
    "gn:admin1_code":"34.0",
    "gn:admin2_code":"231.0",
    "gn:asciiname":"Thakuri",
    "gn:country_code":"IN",
    "gn:dem":79,
    "gn:feature_class":"P",
    "gn:feature_code":"PPL",
    "gn:name":"Th\u0101kuri",
    "gn:population":0,
    "gn:timezone":"Asia/Kolkata",
    "iso:country":"IN",
    "name:hin_x_preferred":[
        "\u0920\u0915\u0941\u0930\u0940"
    ],
    "name:nep_x_preferred":[
        "\u0920\u0915\u0941\u0930\u0940"
    ],
    "name:zho_x_preferred":[
        "\u5854\u5eab\u91cc"
    ],
    "wof:name":"Thakuri",
    "wof:placetype":"locality"
},
  "geometry": {"coordinates":[84.43028000000002,25.37648],"type":"Point"}
}