{
  "type": "Feature",
  "properties": {
    "iso:country":"IN",
    "ks:ks_name":"Chhoti Bambori",
    "ks:ks_pop":415,
    "ks:ks_type":"VILLAGE",
    "name:eng_x_preferred":[
        "Chhoti Bambori"
    ],
    "wof:name":"Chhoti Bambori",
    "wof:placetype":"locality",
    "wof:population":415
},
  "geometry": {"coordinates":[74.718098,24.044448],"type":"Point"}
}