{
  "type": "Feature",
  "properties": {
    "iso:country":"IN",
    "ks:ks_name":"Sanadei",
    "ks:ks_pop":724,
    "ks:ks_type":"VILLAGE",
    "name:eng_x_preferred":[
        "Sanadei"
    ],
    "wof:name":"Sanadei",
    "wof:placetype":"locality",
    "wof:population":724
},
  "geometry": {"coordinates":[86.41078400000001,21.479539],"type":"Point"}
}