{
  "type": "Feature",
  "properties": {
    "iso:country":"IN",
    "ks:ks_name":"Later",
    "ks:ks_pop":267,
    "ks:ks_type":"VILLAGE",
    "name:eng_x_preferred":[
        "Later"
    ],
    "wof:name":"Later",
    "wof:placetype":"locality",
    "wof:population":267
},
  "geometry": {"coordinates":[83.694469,20.365062],"type":"Point"}
}