{
  "type": "Feature",
  "properties": {
    "gn:admin1_code":"25.0",
    "gn:admin2_code":"609.0",
    "gn:asciiname":"Kanjarandippudur",
    "gn:country_code":"IN",
    "gn:dem":210,
    "gn:feature_class":"P",
    "gn:feature_code":"PPL",
    "gn:name":"K\u0101njar\u0101ndippud\u016br",
    "gn:population":0,
    "gn:timezone":"Asia/Kolkata",
    "iso:country":"IN",
    "wof:name":"Kanjarandippudur",
    "wof:placetype":"locality"
},
  "geometry": {"coordinates":[77.90908,11.32097],"type":"Point"}
}