{
  "type": "Feature",
  "properties": {
    "iso:country":"IN",
    "ks:ks_name":"Sali Ramayana Doddi",
    "ks:ks_pop":261,
    "ks:ks_type":"HABITATION",
    "name:eng_x_preferred":[
        "Sali Ramayana Doddi"
    ],
    "wof:name":"Sali Ramayana Doddi",
    "wof:placetype":"locality",
    "wof:population":261
},
  "geometry": {"coordinates":[76.63034399999999,16.31906],"type":"Point"}
}