{
  "type": "Feature",
  "properties": {
    "gn:admin1_code":"21.0",
    "gn:admin2_code":"386.0",
    "gn:asciiname":"Kathakhuntia",
    "gn:country_code":"IN",
    "gn:dem":45,
    "gn:feature_class":"P",
    "gn:feature_code":"PPL",
    "gn:name":"Kathakhuntia",
    "gn:population":0,
    "gn:timezone":"Asia/Kolkata",
    "iso:country":"IN",
    "wof:name":"Kathakhuntia",
    "wof:placetype":"locality"
},
  "geometry": {"coordinates":[85.53418000000001,20.22812],"type":"Point"}
}