{
  "type": "Feature",
  "properties": {
    "gn:admin1_code":"21.0",
    "gn:admin2_code":"386.0",
    "gn:asciiname":"Kathakhuntia",
    "gn:country_code":"IN",
    "gn:dem":45,
    "gn:feature_class":"P",
    "gn:feature_code":"PPL",
    "gn:name":"Kathakhuntia",
    "gn:population":0,
    "gn:timezone":"Asia/Kolkata",
    "iso:country":"IN",
    "ks:ks_name":"Kathakhuntia",
    "ks:ks_pop":595,
    "ks:ks_type":"VILLAGE",
    "name:eng_x_preferred":[
        "Kathakhuntia"
    ],
    "wof:name":"Kathakhuntia",
    "wof:placetype":"locality",
    "wof:population":595
},
  "geometry": {"coordinates":[85.537643,20.226842],"type":"Point"}
}