{
  "type": "Feature",
  "properties": {
    "iso:country":"IN",
    "ks:ks_name":"Fesual Gaon 1",
    "ks:ks_pop":516,
    "ks:ks_type":"HABITATION",
    "name:eng_x_preferred":[
        "Fesual Gaon 1"
    ],
    "wof:name":"Fesual Gaon 1",
    "wof:placetype":"locality",
    "wof:population":516
},
  "geometry": {"coordinates":[94.031279,26.438307],"type":"Point"}
}