{
  "type": "Feature",
  "properties": {
    "iso:country":"IN",
    "ks:ks_name":"Korwadih",
    "ks:ks_pop":246,
    "ks:ks_type":"HABITATION",
    "name:eng_x_preferred":[
        "Korwadih"
    ],
    "wof:name":"Korwadih",
    "wof:placetype":"locality",
    "wof:population":246
},
  "geometry": {"coordinates":[86.39031199999999,24.844001],"type":"Point"}
}