{
  "type": "Feature",
  "properties": {
    "iso:country":"IN",
    "ks:ks_name":"Khirurhi",
    "ks:ks_pop":6,
    "ks:ks_type":"VILLAGE",
    "name:eng_x_preferred":[
        "Khirurhi"
    ],
    "wof:name":"Khirurhi",
    "wof:placetype":"locality",
    "wof:population":6
},
  "geometry": {"coordinates":[79.466988,29.550154],"type":"Point"}
}