{
  "type": "Feature",
  "properties": {
    "iso:country":"IN",
    "ks:ks_name":"Sansaplata",
    "ks:ks_pop":24,
    "ks:ks_type":"VILLAGE",
    "name:eng_x_preferred":[
        "Sansaplata"
    ],
    "wof:name":"Sansaplata",
    "wof:placetype":"locality",
    "wof:population":24
},
  "geometry": {"coordinates":[84.700104,21.943771],"type":"Point"}
}