{
  "type": "Feature",
  "properties": {
    "iso:country":"IN",
    "ks:ks_name":"Piranoor",
    "ks:ks_pop":6817,
    "ks:ks_type":"VILLAGE",
    "ks:ks_uagg_main":0,
    "name:eng_x_preferred":[
        "Piranoor"
    ],
    "wof:name":"Piranoor",
    "wof:placetype":"neighbourhood",
    "wof:population":6817
},
  "geometry": {"coordinates":[77.26303900000001,8.972362],"type":"Point"}
}