{
  "type": "Feature",
  "properties": {
    "iso:country":"IN",
    "ks:ks_alt_nam":"RAHIKPUR",
    "ks:ks_name":"Rahikpur",
    "ks:ks_pop":1579,
    "ks:ks_type":"HABITATION",
    "name:eng_x_preferred":[
        "Rahikpur"
    ],
    "wof:name":"Rahikpur",
    "wof:placetype":"locality",
    "wof:population":1579
},
  "geometry": {"coordinates":[87.61107800000001,25.951027],"type":"Point"}
}