{
  "type": "Feature",
  "properties": {
    "iso:country":"IN",
    "ks:ks_alt_nam":"Chaq Saiuddin urf poore Mati",
    "ks:ks_name":"Chaq Saiuddin Urf Poore Mati",
    "ks:ks_pop":694,
    "ks:ks_type":"HABITATION",
    "name:eng_x_preferred":[
        "Chaq Saiuddin Urf Poore Mati"
    ],
    "wof:name":"Chaq Saiuddin Urf Poore Mati",
    "wof:placetype":"locality",
    "wof:population":694
},
  "geometry": {"coordinates":[81.97189,25.543958],"type":"Point"}
}