{
  "type": "Feature",
  "properties": {
    "iso:country":"IN",
    "ks:ks_name":"Mangarh Mal.",
    "ks:ks_pop":394,
    "ks:ks_type":"VILLAGE",
    "name:eng_x_preferred":[
        "Mangarh Mal."
    ],
    "wof:name":"Mangarh Mal.",
    "wof:placetype":"locality",
    "wof:population":394
},
  "geometry": {"coordinates":[81.294264,22.690928],"type":"Point"}
}