{
  "type": "Feature",
  "properties": {
    "iso:country":"IN",
    "ks:ks_alt_nam":"WARKARI PANAND 2",
    "ks:ks_name":"Warkari Panand 2",
    "ks:ks_pop":114,
    "ks:ks_type":"HABITATION",
    "name:eng_x_preferred":[
        "Warkari Panand 2"
    ],
    "wof:name":"Warkari Panand 2",
    "wof:placetype":"locality",
    "wof:population":114
},
  "geometry": {"coordinates":[74.103551,16.91815],"type":"Point"}
}