{
  "type": "Feature",
  "properties": {
    "gn:admin1_code":"28.0",
    "gn:admin2_code":"337",
    "gn:asciiname":"Sikarpur",
    "gn:country_code":"IN",
    "gn:dem":6,
    "gn:feature_class":"P",
    "gn:feature_code":"PPL",
    "gn:name":"Sikarpur",
    "gn:population":0,
    "gn:timezone":"Asia/Kolkata",
    "iso:country":"IN",
    "ks:ks_name":"Sikharpur",
    "ks:ks_pop":3760,
    "ks:ks_type":"VILLAGE",
    "ks:ks_uagg_main":0,
    "name:eng_x_preferred":[
        "Sikharpur"
    ],
    "wof:name":"Sikharpur",
    "wof:placetype":"locality",
    "wof:population":3760
},
  "geometry": {"coordinates":[88.528312,22.598175],"type":"Point"}
}