{
  "type": "Feature",
  "properties": {
    "gn:admin1_code":"36",
    "gn:admin2_code":"192.0",
    "gn:asciiname":"Hatia",
    "gn:country_code":"IN",
    "gn:dem":78,
    "gn:feature_class":"P",
    "gn:feature_code":"PPL",
    "gn:name":"Hatia",
    "gn:population":0,
    "gn:timezone":"Asia/Kolkata",
    "iso:country":"IN",
    "name:ori_x_preferred":[
        "\u0b39\u0b1f\u0b3f\u0b06"
    ],
    "name:urd_x_preferred":[
        "\u06c1\u0627\u0679\u06cc\u0627"
    ],
    "wof:name":"Hatia",
    "wof:placetype":"locality"
},
  "geometry": {"coordinates":[83.5009,25.99607],"type":"Point"}
}