{
  "type": "Feature",
  "properties": {
    "iso:country":"IN",
    "ks:ks_name":"Hariganj",
    "ks:ks_pop":180,
    "ks:ks_type":"HABITATION",
    "name:eng_x_preferred":[
        "Hariganj"
    ],
    "wof:name":"Hariganj",
    "wof:placetype":"locality",
    "wof:population":180
},
  "geometry": {"coordinates":[82.855019,27.272998],"type":"Point"}
}