{
  "type": "Feature",
  "properties": {
    "iso:country":"IN",
    "ks:ks_name":"Marhiya",
    "ks:ks_pop":273,
    "ks:ks_type":"HABITATION",
    "name:eng_x_preferred":[
        "Marhiya"
    ],
    "wof:name":"Marhiya",
    "wof:placetype":"locality",
    "wof:population":273
},
  "geometry": {"coordinates":[80.624391,27.530148],"type":"Point"}
}