{
  "type": "Feature",
  "properties": {
    "gn:admin1_code":"35",
    "gn:admin2_code":"453.0",
    "gn:asciiname":"Bhaluchuha",
    "gn:country_code":"IN",
    "gn:dem":777,
    "gn:feature_class":"P",
    "gn:feature_code":"PPL",
    "gn:name":"Bh\u0101luchuha",
    "gn:population":0,
    "gn:timezone":"Asia/Kolkata",
    "iso:country":"IN",
    "ks:ks_alt_nam":"Bh\u0101luchuha",
    "ks:ks_name":"Bhaluchuha",
    "ks:ks_pop":416,
    "ks:ks_type":"VILLAGE",
    "name:eng_x_preferred":[
        "Bhaluchuha"
    ],
    "name:eng_x_variant":[
        "Bh\u0101luchuha"
    ],
    "wof:name":"Bhaluchuha",
    "wof:placetype":"locality",
    "wof:population":416
},
  "geometry": {"coordinates":[81.19349800000001,22.799058],"type":"Point"}
}