{
  "type": "Feature",
  "properties": {
    "gn:admin1_code":"35",
    "gn:admin2_code":"453.0",
    "gn:asciiname":"Bhaluchuha",
    "gn:country_code":"IN",
    "gn:dem":777,
    "gn:feature_class":"P",
    "gn:feature_code":"PPL",
    "gn:name":"Bh\u0101luchuha",
    "gn:population":0,
    "gn:timezone":"Asia/Kolkata",
    "iso:country":"IN",
    "wof:name":"Bhaluchuha",
    "wof:placetype":"locality"
},
  "geometry": {"coordinates":[81.19274,22.80085],"type":"Point"}
}