{
  "type": "Feature",
  "properties": {
    "iso:country":"IN",
    "ks:ks_name":"Naugaon",
    "ks:ks_pop":102,
    "ks:ks_type":"VILLAGE",
    "name:eng_x_preferred":[
        "Naugaon"
    ],
    "wof:name":"Naugaon",
    "wof:placetype":"locality",
    "wof:population":102
},
  "geometry": {"coordinates":[79.26035899999999,29.789687],"type":"Point"}
}