{
  "type": "Feature",
  "properties": {
    "iso:country":"IN",
    "ks:ks_name":"Ramappanahatti",
    "ks:ks_pop":630,
    "ks:ks_type":"HABITATION",
    "name:eng_x_preferred":[
        "Ramappanahatti"
    ],
    "wof:name":"Ramappanahatti",
    "wof:placetype":"locality",
    "wof:population":630
},
  "geometry": {"coordinates":[76.60046699999999,13.511617],"type":"Point"}
}