{
  "type": "Feature",
  "properties": {
    "iso:country":"IN",
    "ks:ks_alt_nam":"kholodhanya",
    "ks:ks_name":"Kholodhanya",
    "ks:ks_pop":127,
    "ks:ks_type":"HABITATION",
    "ks:ks_uagg_main":0,
    "name:eng_x_preferred":[
        "Kholodhanya"
    ],
    "wof:name":"Kholodhanya",
    "wof:placetype":"neighbourhood",
    "wof:population":127
},
  "geometry": {"coordinates":[74.4764,18.2633],"type":"Point"}
}