{
  "type": "Feature",
  "properties": {
    "iso:country":"IN",
    "ks:ks_alt_nam":"Jahda T\u0101l",
    "ks:ks_name":"Jahda Tal",
    "ks:ks_type":"VILLAGE",
    "name:eng_x_preferred":[
        "Jahda Tal"
    ],
    "name:eng_x_variant":[
        "Jahda T\u0101l"
    ],
    "wof:name":"Jahda Tal",
    "wof:placetype":"locality"
},
  "geometry": {"coordinates":[83.344939,26.853214],"type":"Point"}
}