{
  "type": "Feature",
  "properties": {
    "gn:admin1_code":"36.0",
    "gn:admin2_code":"189.0",
    "gn:asciiname":"Padri Tilok Rai",
    "gn:country_code":"IN",
    "gn:dem":82,
    "gn:feature_class":"P",
    "gn:feature_code":"PPL",
    "gn:name":"Padri Tilok Rai",
    "gn:population":0,
    "gn:timezone":"Asia/Kolkata",
    "iso:country":"IN",
    "ks:ks_name":"Padri Tilok Rai",
    "ks:ks_type":"VILLAGE",
    "name:eng_x_preferred":[
        "Padri Tilok Rai"
    ],
    "wof:name":"Padri Tilok Rai",
    "wof:placetype":"locality"
},
  "geometry": {"coordinates":[84.134715,26.704848],"type":"Point"}
}