{
  "type": "Feature",
  "properties": {
    "iso:country":"IN",
    "ks:ks_name":"Abgargadde",
    "ks:ks_pop":31,
    "ks:ks_type":"HABITATION",
    "name:eng_x_preferred":[
        "Abgargadde"
    ],
    "wof:name":"Abgargadde",
    "wof:placetype":"locality",
    "wof:population":31
},
  "geometry": {"coordinates":[74.849344,14.398487],"type":"Point"}
}