{
  "type": "Feature",
  "properties": {
    "iso:country":"IN",
    "ks:ks_alt_nam":"RATANPURA BARANI",
    "ks:ks_name":"Ratanpura Barani",
    "ks:ks_pop":62,
    "ks:ks_type":"HABITATION",
    "name:eng_x_preferred":[
        "Ratanpura Barani"
    ],
    "wof:name":"Ratanpura Barani",
    "wof:placetype":"locality",
    "wof:population":62
},
  "geometry": {"coordinates":[73.733075,29.505475],"type":"Point"}
}