{
  "type": "Feature",
  "properties": {
    "gn:admin1_code":"40",
    "gn:admin2_code":"538.0",
    "gn:asciiname":"Srinivaspur",
    "gn:country_code":"IN",
    "gn:dem":420,
    "gn:feature_class":"P",
    "gn:feature_code":"PPL",
    "gn:name":"Sr\u012bniv\u0101spur",
    "gn:population":0,
    "gn:timezone":"Asia/Kolkata",
    "iso:country":"IN",
    "name:ben_x_preferred":[
        "\u09b6\u09cd\u09b0\u09c0\u09a8\u09bf\u09ac\u09be\u09b8\u09aa\u09c1\u09b0"
    ],
    "name:bpy_x_preferred":[
        "\u09b6\u09cd\u09b0\u09c0\u09a8\u09bf\u09ac\u09be\u09b8\u09aa\u09c1\u09b0"
    ],
    "name:ceb_x_preferred":[
        "Sr\u012bniv\u0101spur"
    ],
    "name:ita_x_preferred":[
        "Srinivaspur"
    ],
    "name:mlg_x_preferred":[
        "Srinivaspur"
    ],
    "name:msa_x_preferred":[
        "Srinivaspur"
    ],
    "name:nld_x_preferred":[
        "Srinivaspur"
    ],
    "name:ori_x_preferred":[
        "\u0b36\u0b4d\u0b30\u0b40\u0b28\u0b3f\u0b2c\u0b3e\u0b38\u0b2a\u0b41\u0b30"
    ],
    "name:por_x_preferred":[
        "Srinivaspur"
    ],
    "name:spa_x_preferred":[
        "Srinivaspur"
    ],
    "name:swe_x_preferred":[
        "Sr\u012bniv\u0101spur"
    ],
    "name:vie_x_preferred":[
        "Srinivaspur"
    ],
    "name:zho_x_preferred":[
        "\u65af\u91cc\u5c3c\u74e6\u65af\u666e\u5c14"
    ],
    "wof:name":"Srinivaspur",
    "wof:placetype":"locality"
},
  "geometry": {"coordinates":[78.06291,16.34038],"type":"Point"}
}