{
  "type": "Feature",
  "properties": {
    "iso:country":"IN",
    "ks:ks_name":"Kasarmalai",
    "ks:ks_pop":116,
    "ks:ks_type":"HABITATION",
    "name:eng_x_preferred":[
        "Kasarmalai"
    ],
    "wof:name":"Kasarmalai",
    "wof:placetype":"locality",
    "wof:population":116
},
  "geometry": {"coordinates":[73.250668,18.107497],"type":"Point"}
}