{
  "type": "Feature",
  "properties": {
    "iso:country":"IN",
    "ks:ks_name":"Sundalpur",
    "ks:ks_pop":4940,
    "ks:ks_type":"VILLAGE",
    "ks:ks_uagg_main":0,
    "name:eng_x_preferred":[
        "Sundalpur"
    ],
    "wof:name":"Sundalpur",
    "wof:placetype":"neighbourhood",
    "wof:population":4940
},
  "geometry": {"coordinates":[88.677103,24.01251],"type":"Point"}
}