{
  "type": "Feature",
  "properties": {
    "iso:country":"IN",
    "ks:ks_name":"Sondha Ryt",
    "ks:ks_pop":110,
    "ks:ks_type":"HABITATION",
    "name:eng_x_preferred":[
        "Sondha Ryt"
    ],
    "wof:name":"Sondha Ryt",
    "wof:placetype":"locality",
    "wof:population":110
},
  "geometry": {"coordinates":[81.072834,22.588475],"type":"Point"}
}