{
  "type": "Feature",
  "properties": {
    "iso:country":"IN",
    "ks:ks_name":"Jagwaram",
    "ks:ks_pop":484,
    "ks:ks_type":"HABITATION",
    "name:eng_x_preferred":[
        "Jagwaram"
    ],
    "wof:name":"Jagwaram",
    "wof:placetype":"locality",
    "wof:population":484
},
  "geometry": {"coordinates":[81.319442,18.128734],"type":"Point"}
}