{
  "type": "Feature",
  "properties": {
    "gn:admin1_code":"35.0",
    "gn:admin2_code":"438.0",
    "gn:asciiname":"Jholana",
    "gn:country_code":"IN",
    "gn:dem":484,
    "gn:feature_class":"P",
    "gn:feature_code":"PPL",
    "gn:name":"Jhol\u0101na",
    "gn:population":0,
    "gn:timezone":"Asia/Kolkata",
    "iso:country":"IN",
    "wof:name":"Jholana",
    "wof:placetype":"neighbourhood"
},
  "geometry": {"coordinates":[74.98885,22.78201],"type":"Point"}
}