{
  "type": "Feature",
  "properties": {
    "iso:country":"IN",
    "ks:ks_name":"Gotiakham",
    "ks:ks_pop":15,
    "ks:ks_type":"HABITATION",
    "name:eng_x_preferred":[
        "Gotiakham"
    ],
    "wof:name":"Gotiakham",
    "wof:placetype":"locality",
    "wof:population":15
},
  "geometry": {"coordinates":[79.324603,29.426459],"type":"Point"}
}