{
  "type": "Feature",
  "properties": {
    "iso:country":"IN",
    "ks:ks_name":"Kharpeti",
    "ks:ks_pop":82,
    "ks:ks_type":"HABITATION",
    "name:eng_x_preferred":[
        "Kharpeti"
    ],
    "wof:name":"Kharpeti",
    "wof:placetype":"locality",
    "wof:population":82
},
  "geometry": {"coordinates":[73.455144,17.016206],"type":"Point"}
}