{
  "type": "Feature",
  "properties": {
    "iso:country":"IN",
    "ks:ks_alt_nam":"arkera",
    "ks:ks_name":"Arkera",
    "ks:ks_pop":73,
    "ks:ks_type":"HABITATION",
    "name:eng_x_preferred":[
        "Arkera"
    ],
    "wof:name":"Arkera",
    "wof:placetype":"locality",
    "wof:population":73
},
  "geometry": {"coordinates":[85.318668,22.703894],"type":"Point"}
}