{
  "type": "Feature",
  "properties": {
    "iso:country":"IN",
    "ks:ks_name":"Nadagallu",
    "ks:ks_pop":254,
    "ks:ks_type":"HABITATION",
    "name:eng_x_preferred":[
        "Nadagallu"
    ],
    "wof:name":"Nadagallu",
    "wof:placetype":"locality",
    "wof:population":254
},
  "geometry": {"coordinates":[75.56729199999999,12.643225],"type":"Point"}
}