{
  "type": "Feature",
  "properties": {
    "iso:country":"IN",
    "ks:ks_alt_nam":"CHIRIMAR PURWA",
    "ks:ks_name":"Chirimar Purwa",
    "ks:ks_pop":43,
    "ks:ks_type":"HABITATION",
    "ks:ks_uagg_main":0,
    "name:eng_x_preferred":[
        "Chirimar Purwa"
    ],
    "wof:name":"Chirimar Purwa",
    "wof:placetype":"neighbourhood",
    "wof:population":43
},
  "geometry": {"coordinates":[81.605723,27.35075],"type":"Point"}
}