{
  "type": "Feature",
  "properties": {
    "iso:country":"IN",
    "ks:ks_name":"Indarpur Uraopara",
    "ks:ks_pop":656,
    "ks:ks_type":"HABITATION",
    "name:eng_x_preferred":[
        "Indarpur Uraopara"
    ],
    "wof:name":"Indarpur Uraopara",
    "wof:placetype":"locality",
    "wof:population":656
},
  "geometry": {"coordinates":[83.15740599999999,23.050682],"type":"Point"}
}