{
  "type": "Feature",
  "properties": {
    "iso:country":"IN",
    "ks:ks_alt_nam":"China Pitch raju Cheruvu thanda",
    "ks:ks_name":"China Pitch Raju Cheruvu Thanda",
    "ks:ks_pop":439,
    "ks:ks_type":"HABITATION",
    "name:eng_x_preferred":[
        "China Pitch Raju Cheruvu Thanda"
    ],
    "wof:name":"China Pitch Raju Cheruvu Thanda",
    "wof:placetype":"locality",
    "wof:population":439
},
  "geometry": {"coordinates":[79.29920799999999,16.124481],"type":"Point"}
}