{
  "type": "Feature",
  "properties": {
    "iso:country":"IN",
    "ks:ks_name":"Baulbhauliya",
    "ks:ks_pop":250,
    "ks:ks_type":"HABITATION",
    "name:eng_x_preferred":[
        "Baulbhauliya"
    ],
    "wof:name":"Baulbhauliya",
    "wof:placetype":"locality",
    "wof:population":250
},
  "geometry": {"coordinates":[82.25283,27.2251],"type":"Point"}
}