{
  "type": "Feature",
  "properties": {
    "iso:country":"IN",
    "ks:ks_name":"Tola Alakh Dabri",
    "ks:ks_pop":338,
    "ks:ks_type":"VILLAGE",
    "ks:ks_uagg_main":0,
    "name:eng_x_preferred":[
        "Tola Alakh Dabri"
    ],
    "wof:name":"Tola Alakh Dabri",
    "wof:placetype":"neighbourhood",
    "wof:population":338
},
  "geometry": {"coordinates":[84.27017600000001,26.984103],"type":"Point"}
}