{
  "type": "Feature",
  "properties": {
    "iso:country":"IN",
    "ks:ks_name":"Naldipi",
    "ks:ks_pop":1020,
    "ks:ks_type":"VILLAGE",
    "ks:ks_uagg_main":0,
    "name:eng_x_preferred":[
        "Naldipi"
    ],
    "wof:name":"Naldipi",
    "wof:placetype":"neighbourhood",
    "wof:population":1020
},
  "geometry": {"coordinates":[88.045635,24.048466],"type":"Point"}
}