{
  "type": "Feature",
  "properties": {
    "iso:country":"IN",
    "ks:ks_name":"Khairwaripara",
    "ks:ks_pop":157,
    "ks:ks_type":"VILLAGE",
    "name:eng_x_preferred":[
        "Khairwaripara"
    ],
    "wof:name":"Khairwaripara",
    "wof:placetype":"locality",
    "wof:population":157
},
  "geometry": {"coordinates":[82.51126600000001,23.688286],"type":"Point"}
}