{
  "type": "Feature",
  "properties": {
    "iso:country":"IN",
    "ks:ks_alt_nam":"MADHYA MAHESHPUR",
    "ks:ks_name":"Madhya Maheshpur",
    "ks:ks_pop":428,
    "ks:ks_type":"HABITATION",
    "ks:ks_uagg_main":0,
    "name:eng_x_preferred":[
        "Madhya Maheshpur"
    ],
    "wof:name":"Madhya Maheshpur",
    "wof:placetype":"neighbourhood",
    "wof:population":428
},
  "geometry": {"coordinates":[91.403267,23.853275],"type":"Point"}
}