{
  "type": "Feature",
  "properties": {
    "gn:admin1_code":"19.0",
    "gn:admin2_code":"567.0",
    "gn:asciiname":"Yadihalli",
    "gn:country_code":"IN",
    "gn:dem":581,
    "gn:feature_class":"P",
    "gn:feature_code":"PPL",
    "gn:name":"Yadihalli",
    "gn:population":0,
    "gn:timezone":"Asia/Kolkata",
    "iso:country":"IN",
    "wof:name":"Yadihalli",
    "wof:placetype":"locality"
},
  "geometry": {"coordinates":[75.91592,14.66546],"type":"Point"}
}