{
  "type": "Feature",
  "properties": {
    "iso:country":"IN",
    "ks:ks_name":"Udaipur",
    "ks:ks_pop":503,
    "ks:ks_type":"VILLAGE",
    "name:eng_x_preferred":[
        "Udaipur"
    ],
    "wof:name":"Udaipur",
    "wof:placetype":"locality",
    "wof:population":503
},
  "geometry": {"coordinates":[85.115694,26.024737],"type":"Point"}
}