{
  "type": "Feature",
  "properties": {
    "iso:country":"IN",
    "ks:ks_name":"Koppala",
    "ks:ks_pop":515,
    "ks:ks_type":"HABITATION",
    "name:eng_x_preferred":[
        "Koppala"
    ],
    "wof:name":"Koppala",
    "wof:placetype":"locality",
    "wof:population":515
},
  "geometry": {"coordinates":[74.99748200000001,12.821625],"type":"Point"}
}