{
  "type": "Feature",
  "properties": {
    "iso:country":"IN",
    "ks:ks_name":"Eregowdana Koppalu",
    "ks:ks_pop":206,
    "ks:ks_type":"HABITATION",
    "name:eng_x_preferred":[
        "Eregowdana Koppalu"
    ],
    "wof:name":"Eregowdana Koppalu",
    "wof:placetype":"locality",
    "wof:population":206
},
  "geometry": {"coordinates":[76.871436,12.665283],"type":"Point"}
}