{
  "type": "Feature",
  "properties": {
    "gn:admin1_code":"11.0",
    "gn:admin2_code":"32.0",
    "gn:asciiname":"Surajpur",
    "gn:country_code":"IN",
    "gn:dem":389,
    "gn:feature_class":"P",
    "gn:feature_code":"PPL",
    "gn:name":"S\u016brajpur",
    "gn:population":0,
    "gn:timezone":"Asia/Kolkata",
    "iso:country":"IN",
    "name:ara_x_preferred":[
        "\u0633\u0627\u0631\u062c \u0628\u0648\u0631"
    ],
    "name:ben_x_preferred":[
        "\u09b8\u09c1\u09b0\u099c\u09aa\u09c1\u09b0"
    ],
    "name:bpy_x_preferred":[
        "\u09b8\u09c1\u09b0\u099c\u09aa\u09c1\u09b0"
    ],
    "name:ceb_x_preferred":[
        "Surajpur"
    ],
    "name:fra_x_preferred":[
        "Surajpur"
    ],
    "name:hin_x_preferred":[
        "\u0938\u0942\u0930\u091c\u092a\u0941\u0930"
    ],
    "name:ita_x_preferred":[
        "Surajpur"
    ],
    "name:mlg_x_preferred":[
        "Surajpur"
    ],
    "name:msa_x_preferred":[
        "Surajpur"
    ],
    "name:nld_x_preferred":[
        "Surajpur"
    ],
    "name:swe_x_preferred":[
        "Surajpur"
    ],
    "name:tgl_x_preferred":[
        "Surajpur"
    ],
    "name:tur_x_preferred":[
        "Surajpur"
    ],
    "name:urd_x_preferred":[
        "\u0633\u0648\u0631\u062c \u067e\u0648\u0631"
    ],
    "name:vie_x_preferred":[
        "Surajpur"
    ],
    "name:zho_x_preferred":[
        "\u82cf\u62c9\u6770\u666e\u5c14"
    ],
    "wof:name":"Surajpur",
    "wof:placetype":"locality"
},
  "geometry": {"coordinates":[77.57406999999998,30.45164],"type":"Point"}
}