{
  "type": "Feature",
  "properties": {
    "iso:country":"IN",
    "ks:ks_alt_nam":"21 SPM",
    "ks:ks_name":"21 Spm",
    "ks:ks_pop":11,
    "ks:ks_type":"HABITATION",
    "name:eng_x_preferred":[
        "21 Spm"
    ],
    "wof:name":"21 Spm",
    "wof:placetype":"locality",
    "wof:population":11
},
  "geometry": {"coordinates":[73.91393600000001,29.721142],"type":"Point"}
}