{
  "type": "Feature",
  "properties": {
    "iso:country":"IN",
    "ks:ks_name":"Chausa Pasuram Tola",
    "ks:ks_pop":2072,
    "ks:ks_type":"HABITATION",
    "name:eng_x_preferred":[
        "Chausa Pasuram Tola"
    ],
    "wof:name":"Chausa Pasuram Tola",
    "wof:placetype":"locality",
    "wof:population":2072
},
  "geometry": {"coordinates":[87.007936,25.536383],"type":"Point"}
}