{
  "type": "Feature",
  "properties": {
    "gn:admin1_code":"35.0",
    "gn:admin2_code":"428.0",
    "gn:asciiname":"Mahua Kheda",
    "gn:country_code":"IN",
    "gn:dem":354,
    "gn:feature_class":"P",
    "gn:feature_code":"PPL",
    "gn:name":"Mahua Kheda",
    "gn:population":0,
    "gn:timezone":"Asia/Kolkata",
    "iso:country":"IN",
    "wof:name":"Mahua Kheda",
    "wof:placetype":"locality"
},
  "geometry": {"coordinates":[79.4269,23.59913],"type":"Point"}
}