{
  "type": "Feature",
  "properties": {
    "gn:admin1_code":"11",
    "gn:admin2_code":"23.0",
    "gn:asciiname":"Chanaota Khas",
    "gn:country_code":"IN",
    "gn:dem":1998,
    "gn:feature_class":"P",
    "gn:feature_code":"PPL",
    "gn:name":"Chanaota Kh\u0101s",
    "gn:population":0,
    "gn:timezone":"Asia/Kolkata",
    "iso:country":"IN",
    "wof:name":"Chanaota Khas",
    "wof:placetype":"locality"
},
  "geometry": {"coordinates":[76.48466999999999,32.38192],"type":"Point"}
}