{
  "type": "Feature",
  "properties": {
    "iso:country":"IN",
    "ks:ks_name":"Kankabati",
    "ks:ks_pop":623,
    "ks:ks_type":"VILLAGE",
    "name:eng_x_preferred":[
        "Kankabati"
    ],
    "wof:name":"Kankabati",
    "wof:placetype":"locality",
    "wof:population":623
},
  "geometry": {"coordinates":[87.64597999999999,23.031857],"type":"Point"}
}