{
  "type": "Feature",
  "properties": {
    "iso:country":"IN",
    "ks:ks_name":"Dumerghat",
    "ks:ks_pop":108,
    "ks:ks_type":"HABITATION",
    "name:eng_x_preferred":[
        "Dumerghat"
    ],
    "wof:name":"Dumerghat",
    "wof:placetype":"locality",
    "wof:population":108
},
  "geometry": {"coordinates":[82.225877,20.22851],"type":"Point"}
}