{
  "type": "Feature",
  "properties": {
    "iso:country":"IN",
    "ks:ks_name":"Maheshpur",
    "ks:ks_pop":8264,
    "ks:ks_type":"VILLAGE",
    "name:eng_x_preferred":[
        "Maheshpur"
    ],
    "wof:name":"Maheshpur",
    "wof:placetype":"locality",
    "wof:population":8264
},
  "geometry": {"coordinates":[88.03757299999999,24.858495],"type":"Point"}
}