{
  "type": "Feature",
  "properties": {
    "iso:country":"IN",
    "ks:ks_name":"Khalchebamber",
    "ks:ks_pop":264,
    "ks:ks_type":"HABITATION",
    "name:eng_x_preferred":[
        "Khalchebamber"
    ],
    "wof:name":"Khalchebamber",
    "wof:placetype":"locality",
    "wof:population":264
},
  "geometry": {"coordinates":[73.71444099999999,15.830494],"type":"Point"}
}