{
  "type": "Feature",
  "properties": {
    "gn:admin1_code":"36",
    "gn:admin2_code":"146.0",
    "gn:asciiname":"Sankuri Kalan",
    "gn:country_code":"IN",
    "gn:dem":164,
    "gn:feature_class":"P",
    "gn:feature_code":"PPL",
    "gn:name":"Sankuri Kal\u0101n",
    "gn:population":0,
    "gn:timezone":"Asia/Kolkata",
    "iso:country":"IN",
    "ks:ks_alt_nam":"Sankuri Kal\u0101n",
    "ks:ks_name":"Sankuri Kalan",
    "ks:ks_pop":215,
    "ks:ks_type":"VILLAGE",
    "name:eng_x_preferred":[
        "Sankuri Kalan"
    ],
    "name:eng_x_variant":[
        "Sankuri Kal\u0101n"
    ],
    "wof:name":"Sankuri Kalan",
    "wof:placetype":"locality",
    "wof:population":215
},
  "geometry": {"coordinates":[78.383585,26.975451],"type":"Point"}
}