{
  "type": "Feature",
  "properties": {
    "gn:admin1_code":"34.0",
    "gn:admin2_code":"204.0",
    "gn:asciiname":"Chaman",
    "gn:country_code":"IN",
    "gn:dem":67,
    "gn:feature_class":"P",
    "gn:feature_code":"PPL",
    "gn:name":"Chaman",
    "gn:population":0,
    "gn:timezone":"Asia/Kolkata",
    "iso:country":"IN",
    "name:ben_x_preferred":[
        "\u099a\u09ae\u09a8"
    ],
    "name:deu_x_preferred":[
        "Chaman"
    ],
    "name:fas_x_preferred":[
        "\u0686\u0645\u0646"
    ],
    "name:fra_x_preferred":[
        "Chaman"
    ],
    "name:heb_x_preferred":[
        "\u05e6'\u05de\u05d0\u05df"
    ],
    "name:hin_x_preferred":[
        "\u091a\u092e\u0928"
    ],
    "name:hun_x_preferred":[
        "Chaman"
    ],
    "name:ita_x_preferred":[
        "Chaman"
    ],
    "name:jpn_x_preferred":[
        "\u30c1\u30e3\u30de\u30f3"
    ],
    "name:lit_x_preferred":[
        "\u010camanas"
    ],
    "name:msa_x_preferred":[
        "Chaman"
    ],
    "name:nep_x_preferred":[
        "\u091a\u092e\u0928"
    ],
    "name:pnb_x_preferred":[
        "\u0686\u0645\u0646"
    ],
    "name:pol_x_preferred":[
        "\u0106aman"
    ],
    "name:por_x_preferred":[
        "Chaman"
    ],
    "name:pus_x_preferred":[
        "\u0686\u0645\u0646"
    ],
    "name:rus_x_preferred":[
        "\u0427\u0430\u043c\u0430\u043d"
    ],
    "name:snd_x_preferred":[
        "\u0686\u0645\u0646"
    ],
    "name:spa_x_preferred":[
        "Chaman"
    ],
    "name:swe_x_preferred":[
        "Chaman"
    ],
    "name:tur_x_preferred":[
        "\u00c7aman"
    ],
    "name:ukr_x_preferred":[
        "\u0427\u0430\u043c\u0430\u043d"
    ],
    "name:urd_x_preferred":[
        "\u0686\u0645\u0646"
    ],
    "name:vie_x_preferred":[
        "Chaman"
    ],
    "wof:name":"Chaman",
    "wof:placetype":"neighbourhood"
},
  "geometry": {"coordinates":[84.93572,26.50644],"type":"Point"}
}