{
  "type": "Feature",
  "properties": {
    "gn:admin1_code":"36",
    "gn:admin2_code":"201.0",
    "gn:asciiname":"Jaithra Second Portion",
    "gn:country_code":"IN",
    "gn:dem":165,
    "gn:feature_class":"P",
    "gn:feature_code":"PPL",
    "gn:name":"Jaithra Second Portion",
    "gn:population":0,
    "gn:timezone":"Asia/Kolkata",
    "iso:country":"IN",
    "name:und_x_variant":[
        "Mah\u0101ia"
    ],
    "wof:name":"Jaithra Second Portion",
    "wof:placetype":"neighbourhood"
},
  "geometry": {"coordinates":[79.02554000000001,27.5361],"type":"Point"}
}