{
  "type": "Feature",
  "properties": {
    "iso:country":"IN",
    "ks:ks_alt_nam":"Chorg\u0101nwa",
    "ks:ks_name":"Chorganwa",
    "ks:ks_pop":647,
    "ks:ks_type":"VILLAGE",
    "name:eng_x_preferred":[
        "Chorganwa"
    ],
    "name:eng_x_variant":[
        "Chorg\u0101nwa"
    ],
    "wof:name":"Chorganwa",
    "wof:placetype":"locality",
    "wof:population":647
},
  "geometry": {"coordinates":[85.705113,23.746218],"type":"Point"}
}