{
  "type": "Feature",
  "properties": {
    "iso:country":"IN",
    "ks:ks_name":"Babhuo Ki Dhani",
    "ks:ks_pop":521,
    "ks:ks_type":"HABITATION",
    "name:eng_x_preferred":[
        "Babhuo Ki Dhani"
    ],
    "wof:name":"Babhuo Ki Dhani",
    "wof:placetype":"locality",
    "wof:population":521
},
  "geometry": {"coordinates":[71.69519699999999,25.592183],"type":"Point"}
}