{
  "type": "Feature",
  "properties": {
    "iso:country":"IN",
    "ks:ks_name":"Aruniasol",
    "ks:ks_pop":0,
    "ks:ks_type":"VILLAGE",
    "name:eng_x_preferred":[
        "Aruniasol"
    ],
    "wof:name":"Aruniasol",
    "wof:placetype":"locality",
    "wof:population":0
},
  "geometry": {"coordinates":[87.27218499999999,22.535602],"type":"Point"}
}