{
  "type": "Feature",
  "properties": {
    "gn:admin1_code":"19",
    "gn:admin2_code":"559.0",
    "gn:asciiname":"Chikkanatti",
    "gn:country_code":"IN",
    "gn:dem":524,
    "gn:feature_class":"P",
    "gn:feature_code":"PPL",
    "gn:name":"Chikkanatti",
    "gn:population":0,
    "gn:timezone":"Asia/Kolkata",
    "iso:country":"IN",
    "wof:name":"Chikkanatti",
    "wof:placetype":"locality"
},
  "geometry": {"coordinates":[76.69305,16.16209],"type":"Point"}
}