{
  "type": "Feature",
  "properties": {
    "iso:country":"IN",
    "ks:ks_alt_nam":"32 MJD-A",
    "ks:ks_name":"32 Mjd-a",
    "ks:ks_pop":30,
    "ks:ks_type":"HABITATION",
    "name:eng_x_preferred":[
        "32 Mjd-a"
    ],
    "wof:name":"32 Mjd-a",
    "wof:placetype":"locality",
    "wof:population":30
},
  "geometry": {"coordinates":[74.145673,29.780759],"type":"Point"}
}