{
  "type": "Feature",
  "properties": {
    "iso:country":"IN",
    "ks:ks_name":"Zeley",
    "ks:ks_pop":780,
    "ks:ks_type":"HABITATION",
    "name:eng_x_preferred":[
        "Zeley"
    ],
    "wof:name":"Zeley",
    "wof:placetype":"locality",
    "wof:population":780
},
  "geometry": {"coordinates":[75.7141,32.404023],"type":"Point"}
}