{
  "type": "Feature",
  "properties": {
    "gn:admin1_code":"36",
    "gn:admin2_code":"195.0",
    "gn:asciiname":"Kadipur",
    "gn:country_code":"IN",
    "gn:dem":72,
    "gn:feature_class":"P",
    "gn:feature_code":"PPL",
    "gn:name":"K\u0101d\u012bpur",
    "gn:population":0,
    "gn:timezone":"Asia/Kolkata",
    "iso:country":"IN",
    "name:bpy_x_preferred":[
        "\u0995\u09be\u09a6\u09bf\u09aa\u09c1\u09b0"
    ],
    "name:ceb_x_preferred":[
        "K\u0101d\u012bpur"
    ],
    "name:fra_x_preferred":[
        "Kadipur"
    ],
    "name:hin_x_preferred":[
        "\u0915\u093e\u0926\u0940\u092a\u0941\u0930"
    ],
    "name:ita_x_preferred":[
        "Kadipur"
    ],
    "name:mlg_x_preferred":[
        "Kadipur"
    ],
    "name:msa_x_preferred":[
        "Kadipur"
    ],
    "name:new_x_preferred":[
        "\u0915\u093e\u0921\u093f\u092a\u0941\u0930"
    ],
    "name:nld_x_preferred":[
        "Kadipur"
    ],
    "name:pol_x_preferred":[
        "Kadipur"
    ],
    "name:por_x_preferred":[
        "Kadipur"
    ],
    "name:swe_x_preferred":[
        "K\u0101d\u012bpur"
    ],
    "name:urd_x_preferred":[
        "\u06a9\u062f\u06cc \u067e\u0648\u0631"
    ],
    "name:vie_x_preferred":[
        "Kadipur"
    ],
    "name:zho_x_preferred":[
        "\u5361\u8fea\u666e\u5c14"
    ],
    "wof:name":"Kadipur",
    "wof:placetype":"locality"
},
  "geometry": {"coordinates":[83.71375999999999,25.77541],"type":"Point"}
}