{
  "type": "Feature",
  "properties": {
    "gn:admin1_code":"19.0",
    "gn:admin2_code":"569.0",
    "gn:asciiname":"Parika",
    "gn:country_code":"IN",
    "gn:dem":48,
    "gn:feature_class":"P",
    "gn:feature_code":"PPL",
    "gn:name":"Parika",
    "gn:population":0,
    "gn:timezone":"Asia/Kolkata",
    "iso:country":"IN",
    "name:ceb_x_preferred":[
        "Parika"
    ],
    "name:deu_x_preferred":[
        "Parika"
    ],
    "name:fra_x_preferred":[
        "Parika"
    ],
    "name:lit_x_preferred":[
        "Parika"
    ],
    "name:pol_x_preferred":[
        "Parika"
    ],
    "name:por_x_preferred":[
        "Parika"
    ],
    "name:spa_x_preferred":[
        "Parika"
    ],
    "name:swe_x_preferred":[
        "Parika"
    ],
    "name:zho_x_preferred":[
        "\u5e15\u91cc\u5361"
    ],
    "wof:name":"Parika",
    "wof:placetype":"locality"
},
  "geometry": {"coordinates":[74.82755,13.35454],"type":"Point"}
}