{
  "type": "Feature",
  "properties": {
    "iso:country":"IN",
    "ks:ks_name":"Muthukallu",
    "ks:ks_pop":1315,
    "ks:ks_type":"HABITATION",
    "name:eng_x_preferred":[
        "Muthukallu"
    ],
    "wof:name":"Muthukallu",
    "wof:placetype":"locality",
    "wof:population":1315
},
  "geometry": {"coordinates":[76.58892299999999,9.938512],"type":"Point"}
}