{
  "type": "Feature",
  "properties": {
    "iso:country":"IN",
    "ks:ks_name":"Parakulam",
    "ks:ks_pop":484,
    "ks:ks_type":"HABITATION",
    "name:eng_x_preferred":[
        "Parakulam"
    ],
    "wof:name":"Parakulam",
    "wof:placetype":"locality",
    "wof:population":484
},
  "geometry": {"coordinates":[76.93870200000001,9.26045],"type":"Point"}
}