{
  "type": "Feature",
  "properties": {
    "iso:country":"IN",
    "ks:ks_alt_nam":"MOHAN PARA",
    "ks:ks_name":"Mohan Para",
    "ks:ks_pop":61,
    "ks:ks_type":"HABITATION",
    "name:eng_x_preferred":[
        "Mohan Para"
    ],
    "wof:name":"Mohan Para",
    "wof:placetype":"locality",
    "wof:population":61
},
  "geometry": {"coordinates":[91.49185199999999,23.667195],"type":"Point"}
}