{
  "type": "Feature",
  "properties": {
    "iso:country":"IN",
    "ks:ks_name":"Larauli",
    "ks:ks_pop":250,
    "ks:ks_type":"VILLAGE",
    "name:eng_x_preferred":[
        "Larauli"
    ],
    "wof:name":"Larauli",
    "wof:placetype":"locality",
    "wof:population":250
},
  "geometry": {"coordinates":[85.30626700000001,22.840662],"type":"Point"}
}