{
  "type": "Feature",
  "properties": {
    "iso:country":"IN",
    "ks:ks_name":"Pati Mushran",
    "ks:ks_pop":3599,
    "ks:ks_type":"VILLAGE",
    "name:eng_x_preferred":[
        "Pati Mushran"
    ],
    "wof:name":"Pati Mushran",
    "wof:placetype":"locality",
    "wof:population":3599
},
  "geometry": {"coordinates":[82.165046,24.653567],"type":"Point"}
}