{
  "type": "Feature",
  "properties": {
    "iso:country":"IN",
    "ks:ks_alt_nam":"K\u0101ripah\u0101ri",
    "ks:ks_name":"Karipahari",
    "ks:ks_pop":44,
    "ks:ks_type":"VILLAGE",
    "name:eng_x_preferred":[
        "Karipahari"
    ],
    "name:eng_x_variant":[
        "K\u0101ripah\u0101ri"
    ],
    "wof:name":"Karipahari",
    "wof:placetype":"locality",
    "wof:population":44
},
  "geometry": {"coordinates":[86.389808,24.083723],"type":"Point"}
}