{
  "type": "Feature",
  "properties": {
    "iso:country":"IN",
    "ks:ks_name":"Saharajdhab",
    "ks:ks_pop":132,
    "ks:ks_type":"VILLAGE",
    "name:eng_x_preferred":[
        "Saharajdhab"
    ],
    "wof:name":"Saharajdhab",
    "wof:placetype":"locality",
    "wof:population":132
},
  "geometry": {"coordinates":[87.62467700000001,24.833141],"type":"Point"}
}