{
  "type": "Feature",
  "properties": {
    "iso:country":"IN",
    "ks:ks_alt_nam":"Paul para",
    "ks:ks_name":"Paul Para",
    "ks:ks_pop":461,
    "ks:ks_type":"HABITATION",
    "name:eng_x_preferred":[
        "Paul Para"
    ],
    "wof:name":"Paul Para",
    "wof:placetype":"locality",
    "wof:population":461
},
  "geometry": {"coordinates":[91.337934,23.247287],"type":"Point"}
}