{
  "type": "Feature",
  "properties": {
    "gn:admin1_code":"38.0",
    "gn:admin2_code":"351.0",
    "gn:asciiname":"Kaldigra",
    "gn:country_code":"IN",
    "gn:dem":110,
    "gn:feature_class":"P",
    "gn:feature_code":"PPL",
    "gn:name":"K\u0101ld\u012bgra",
    "gn:population":0,
    "gn:timezone":"Asia/Kolkata",
    "iso:country":"IN",
    "ks:ks_alt_nam":"K\u0101ld\u012bgra",
    "ks:ks_name":"Kaldigra",
    "ks:ks_pop":47,
    "ks:ks_type":"VILLAGE",
    "name:eng_x_preferred":[
        "Kaldigra"
    ],
    "name:eng_x_variant":[
        "K\u0101ld\u012bgra"
    ],
    "wof:name":"Kaldigra",
    "wof:placetype":"locality",
    "wof:population":47
},
  "geometry": {"coordinates":[87.448578,25.028446],"type":"Point"}
}