{
  "type": "Feature",
  "properties": {
    "iso:country":"IN",
    "ks:ks_name":"Semra",
    "ks:ks_pop":1686,
    "ks:ks_type":"VILLAGE",
    "ks:ks_uagg_main":0,
    "name:eng_x_preferred":[
        "Semra"
    ],
    "wof:name":"Semra",
    "wof:placetype":"neighbourhood",
    "wof:population":1686
},
  "geometry": {"coordinates":[85.03597000000001,26.445448],"type":"Point"}
}