{
  "type": "Feature",
  "properties": {
    "iso:country":"IN",
    "ks:ks_name":"Baripur",
    "ks:ks_pop":310,
    "ks:ks_type":"HABITATION",
    "name:eng_x_preferred":[
        "Baripur"
    ],
    "wof:name":"Baripur",
    "wof:placetype":"locality",
    "wof:population":310
},
  "geometry": {"coordinates":[82.35136,26.674204],"type":"Point"}
}