{
  "type": "Feature",
  "properties": {
    "iso:country":"IN",
    "ks:ks_name":"Nevalse",
    "ks:ks_pop":93,
    "ks:ks_type":"HABITATION",
    "name:eng_x_preferred":[
        "Nevalse"
    ],
    "wof:name":"Nevalse",
    "wof:placetype":"locality",
    "wof:population":93
},
  "geometry": {"coordinates":[74.448686,14.618489],"type":"Point"}
}