{
  "type": "Feature",
  "properties": {
    "iso:country":"IN",
    "ks:ks_name":"Hantalguda",
    "ks:ks_pop":241,
    "ks:ks_type":"VILLAGE",
    "name:eng_x_preferred":[
        "Hantalguda"
    ],
    "wof:name":"Hantalguda",
    "wof:placetype":"locality",
    "wof:population":241
},
  "geometry": {"coordinates":[82.300409,18.203449],"type":"Point"}
}