{
  "type": "Feature",
  "properties": {
    "gn:admin1_code":"39.0",
    "gn:admin2_code":"64.0",
    "gn:asciiname":"Gharkhet",
    "gn:country_code":"IN",
    "gn:dem":976,
    "gn:feature_class":"P",
    "gn:feature_code":"PPL",
    "gn:name":"Gharkhet",
    "gn:population":0,
    "gn:timezone":"Asia/Kolkata",
    "iso:country":"IN",
    "wof:name":"Gharkhet",
    "wof:placetype":"locality"
},
  "geometry": {"coordinates":[79.22689,29.62797],"type":"Point"}
}