{
  "type": "Feature",
  "properties": {
    "gn:admin1_code":"39.0",
    "gn:admin2_code":"64.0",
    "gn:asciiname":"Gharkhet",
    "gn:country_code":"IN",
    "gn:dem":976,
    "gn:feature_class":"P",
    "gn:feature_code":"PPL",
    "gn:name":"Gharkhet",
    "gn:population":0,
    "gn:timezone":"Asia/Kolkata",
    "iso:country":"IN",
    "ks:ks_name":"Gharkheton",
    "ks:ks_pop":69,
    "ks:ks_type":"VILLAGE",
    "name:eng_x_preferred":[
        "Gharkheton"
    ],
    "name:eng_x_variant":[
        "Gharkhet"
    ],
    "wof:name":"Gharkheton",
    "wof:placetype":"locality",
    "wof:population":69
},
  "geometry": {"coordinates":[79.225486,29.627134],"type":"Point"}
}