{
  "type": "Feature",
  "properties": {
    "iso:country":"IN",
    "ks:ks_name":"Bapdevwadi",
    "ks:ks_pop":194,
    "ks:ks_type":"HABITATION",
    "name:eng_x_preferred":[
        "Bapdevwadi"
    ],
    "wof:name":"Bapdevwadi",
    "wof:placetype":"locality",
    "wof:population":194
},
  "geometry": {"coordinates":[73.268086,18.877582],"type":"Point"}
}