{
  "type": "Feature",
  "properties": {
    "iso:country":"IN",
    "ks:ks_name":"Kothanadipalli",
    "ks:ks_pop":1,
    "ks:ks_type":"HABITATION",
    "name:eng_x_preferred":[
        "Kothanadipalli"
    ],
    "wof:name":"Kothanadipalli",
    "wof:placetype":"locality",
    "wof:population":1
},
  "geometry": {"coordinates":[83.548047,18.052837],"type":"Point"}
}