{
  "type": "Feature",
  "properties": {
    "iso:country":"IN",
    "ks:ks_name":"Kullu",
    "ks:ks_pop":87,
    "ks:ks_type":"VILLAGE",
    "name:eng_x_preferred":[
        "Kullu"
    ],
    "wof:name":"Kullu",
    "wof:placetype":"locality",
    "wof:population":87
},
  "geometry": {"coordinates":[84.820363,24.460945],"type":"Point"}
}