{
  "type": "Feature",
  "properties": {
    "iso:country":"IN",
    "ks:ks_alt_nam":"S.MUSLIM TOLA",
    "ks:ks_name":"S.muslim Tola",
    "ks:ks_pop":473,
    "ks:ks_type":"HABITATION",
    "name:eng_x_preferred":[
        "S.muslim Tola"
    ],
    "wof:name":"S.muslim Tola",
    "wof:placetype":"locality",
    "wof:population":473
},
  "geometry": {"coordinates":[86.55542,26.057393],"type":"Point"}
}