{
  "type": "Feature",
  "properties": {
    "iso:country":"IN",
    "ks:ks_name":"Duduburi",
    "ks:ks_pop":106,
    "ks:ks_type":"VILLAGE",
    "name:eng_x_preferred":[
        "Duduburi"
    ],
    "wof:name":"Duduburi",
    "wof:placetype":"locality",
    "wof:population":106
},
  "geometry": {"coordinates":[84.25731500000001,19.645022],"type":"Point"}
}