{
  "type": "Feature",
  "properties": {
    "iso:country":"IN",
    "ks:ks_name":"Surabail",
    "ks:ks_pop":50,
    "ks:ks_type":"HABITATION",
    "name:eng_x_preferred":[
        "Surabail"
    ],
    "wof:name":"Surabail",
    "wof:placetype":"locality",
    "wof:population":50
},
  "geometry": {"coordinates":[74.857443,14.841374],"type":"Point"}
}