{
  "type": "Feature",
  "properties": {
    "iso:country":"IN",
    "ks:ks_name":"Talav Dedki Faliya",
    "ks:ks_pop":412,
    "ks:ks_type":"HABITATION",
    "name:eng_x_preferred":[
        "Talav Dedki Faliya"
    ],
    "wof:name":"Talav Dedki Faliya",
    "wof:placetype":"locality",
    "wof:population":412
},
  "geometry": {"coordinates":[73.78375,22.7441],"type":"Point"}
}