{
  "type": "Feature",
  "properties": {
    "iso:country":"IN",
    "ks:ks_name":"Pattabavu",
    "ks:ks_pop":133,
    "ks:ks_type":"HABITATION",
    "name:eng_x_preferred":[
        "Pattabavu"
    ],
    "wof:name":"Pattabavu",
    "wof:placetype":"locality",
    "wof:population":133
},
  "geometry": {"coordinates":[74.93749,13.328624],"type":"Point"}
}