{
  "type": "Feature",
  "properties": {
    "iso:country":"IN",
    "ks:ks_name":"Gaikwad Wasti",
    "ks:ks_pop":579,
    "ks:ks_type":"HABITATION",
    "name:eng_x_preferred":[
        "Gaikwad Wasti"
    ],
    "wof:name":"Gaikwad Wasti",
    "wof:placetype":"locality",
    "wof:population":579
},
  "geometry": {"coordinates":[75.01900000000001,18.021],"type":"Point"}
}