{
  "type": "Feature",
  "properties": {
    "gn:admin1_code":"25.0",
    "gn:admin2_code":"606.0",
    "gn:asciiname":"Valavachchanur",
    "gn:country_code":"IN",
    "gn:dem":143,
    "gn:feature_class":"P",
    "gn:feature_code":"PPL",
    "gn:name":"V\u0101lavachchan\u016br",
    "gn:population":0,
    "gn:timezone":"Asia/Kolkata",
    "iso:country":"IN",
    "ks:ks_alt_nam":"V\u0101lavachchan\u016br",
    "ks:ks_name":"Valavachchanur",
    "ks:ks_type":"VILLAGE",
    "name:eng_x_preferred":[
        "Valavachchanur"
    ],
    "name:eng_x_variant":[
        "V\u0101lavachchan\u016br"
    ],
    "wof:name":"Valavachchanur",
    "wof:placetype":"locality"
},
  "geometry": {"coordinates":[78.9866,12.064873],"type":"Point"}
}