{
  "type": "Feature",
  "properties": {
    "iso:country":"IN",
    "ks:ks_name":"Laxmipura",
    "ks:ks_pop":176,
    "ks:ks_type":"HABITATION",
    "name:eng_x_preferred":[
        "Laxmipura"
    ],
    "wof:name":"Laxmipura",
    "wof:placetype":"locality",
    "wof:population":176
},
  "geometry": {"coordinates":[76.322734,12.830191],"type":"Point"}
}