{
  "type": "Feature",
  "properties": {
    "iso:country":"IN",
    "ks:ks_alt_nam":"Dumri Parm\u0101nandpur",
    "ks:ks_name":"Dumri Parmanandpur",
    "ks:ks_type":"VILLAGE",
    "name:eng_x_preferred":[
        "Dumri Parmanandpur"
    ],
    "name:eng_x_variant":[
        "Dumri Parm\u0101nandpur"
    ],
    "wof:name":"Dumri Parmanandpur",
    "wof:placetype":"locality"
},
  "geometry": {"coordinates":[84.95885199999999,26.13757],"type":"Point"}
}