{
  "type": "Feature",
  "properties": {
    "gn:admin1_code":"35.0",
    "gn:admin2_code":"454.0",
    "gn:asciiname":"Baniagaon",
    "gn:country_code":"IN",
    "gn:dem":519,
    "gn:feature_class":"P",
    "gn:feature_code":"PPL",
    "gn:name":"Bani\u0101gaon",
    "gn:population":0,
    "gn:timezone":"Asia/Kolkata",
    "iso:country":"IN",
    "ks:ks_name":"Baniyagaon",
    "ks:ks_pop":181,
    "ks:ks_type":"VILLAGE",
    "name:eng_x_preferred":[
        "Baniyagaon"
    ],
    "name:eng_x_variant":[
        "Baniagaon"
    ],
    "wof:name":"Baniyagaon",
    "wof:placetype":"locality",
    "wof:population":181
},
  "geometry": {"coordinates":[80.47179199999999,22.405245],"type":"Point"}
}