{
  "type": "Feature",
  "properties": {
    "iso:country":"IN",
    "ks:ks_alt_nam":"Bhola ka Purwa",
    "ks:ks_name":"Bhola Ka Purwa",
    "ks:ks_pop":256,
    "ks:ks_type":"HABITATION",
    "name:eng_x_preferred":[
        "Bhola Ka Purwa"
    ],
    "wof:name":"Bhola Ka Purwa",
    "wof:placetype":"locality",
    "wof:population":256
},
  "geometry": {"coordinates":[81.100382,26.295207],"type":"Point"}
}