{
  "type": "Feature",
  "properties": {
    "iso:country":"IN",
    "ks:ks_name":"Krishnareddikandriga",
    "ks:ks_pop":69,
    "ks:ks_type":"HABITATION",
    "name:eng_x_preferred":[
        "Krishnareddikandriga"
    ],
    "wof:name":"Krishnareddikandriga",
    "wof:placetype":"locality",
    "wof:population":69
},
  "geometry": {"coordinates":[79.278226,13.184986],"type":"Point"}
}