{
  "type": "Feature",
  "properties": {
    "gn:admin1_code":"19.0",
    "gn:admin2_code":"582.0",
    "gn:asciiname":"Kariganapalya",
    "gn:country_code":"IN",
    "gn:dem":987,
    "gn:feature_class":"P",
    "gn:feature_code":"PPL",
    "gn:name":"Karig\u0101napalya",
    "gn:population":0,
    "gn:timezone":"Asia/Kolkata",
    "iso:country":"IN",
    "wof:name":"Kariganapalya",
    "wof:placetype":"locality"
},
  "geometry": {"coordinates":[77.73952,13.53139],"type":"Point"}
}