{
  "type": "Feature",
  "properties": {
    "gn:admin1_code":"24.0",
    "gn:admin2_code":"101.0",
    "gn:asciiname":"Bakhusar",
    "gn:country_code":"IN",
    "gn:dem":213,
    "gn:feature_class":"P",
    "gn:feature_code":"PPL",
    "gn:name":"Bakh\u016bsar",
    "gn:population":0,
    "gn:timezone":"Asia/Kolkata",
    "iso:country":"IN",
    "wof:name":"Bakhusar",
    "wof:placetype":"locality"
},
  "geometry": {"coordinates":[74.16727,28.71881],"type":"Point"}
}