{
  "type": "Feature",
  "properties": {
    "gn:admin1_code":"24.0",
    "gn:admin2_code":"101.0",
    "gn:asciiname":"Khodala",
    "gn:country_code":"IN",
    "gn:dem":208,
    "gn:feature_class":"P",
    "gn:feature_code":"PPL",
    "gn:name":"Khod\u0101la",
    "gn:population":0,
    "gn:timezone":"Asia/Kolkata",
    "iso:country":"IN",
    "name:und_x_variant":[
        "Khod\u0101la",
        "Shaikhsar Naya V\u0101s"
    ],
    "wof:name":"Khodala",
    "wof:placetype":"locality"
},
  "geometry": {"coordinates":[74.05646,28.63867],"type":"Point"}
}