{
  "type": "Feature",
  "properties": {
    "gn:admin1_code":"11.0",
    "gn:admin2_code":"24.0",
    "gn:asciiname":"Jhalun",
    "gn:country_code":"IN",
    "gn:dem":532,
    "gn:feature_class":"P",
    "gn:feature_code":"PPL",
    "gn:name":"Jhal\u016bn",
    "gn:population":0,
    "gn:timezone":"Asia/Kolkata",
    "iso:country":"IN",
    "wof:name":"Jhalun",
    "wof:placetype":"locality"
},
  "geometry": {"coordinates":[75.9605,32.19978],"type":"Point"}
}