{
  "type": "Feature",
  "properties": {
    "iso:country":"IN",
    "ks:ks_name":"Shekhpur Paliyari Khas",
    "ks:ks_pop":239,
    "ks:ks_type":"HABITATION",
    "ks:ks_uagg_main":0,
    "name:eng_x_preferred":[
        "Shekhpur Paliyari Khas"
    ],
    "wof:name":"Shekhpur Paliyari Khas",
    "wof:placetype":"neighbourhood",
    "wof:population":239
},
  "geometry": {"coordinates":[82.852282,26.167507],"type":"Point"}
}