{
  "type": "Feature",
  "properties": {
    "gn:admin1_code":"25.0",
    "gn:admin2_code":"631.0",
    "gn:asciiname":"Sokkarasanapalli",
    "gn:country_code":"IN",
    "gn:dem":860,
    "gn:feature_class":"P",
    "gn:feature_code":"PPL",
    "gn:name":"Sokkarasanapalli",
    "gn:population":0,
    "gn:timezone":"Asia/Kolkata",
    "iso:country":"IN",
    "wof:name":"Sokkarasanapalli",
    "wof:placetype":"locality"
},
  "geometry": {"coordinates":[77.83195000000001,12.85853],"type":"Point"}
}