{
  "type": "Feature",
  "properties": {
    "iso:country":"IN",
    "ks:ks_name":"Thulukkanpatti",
    "ks:ks_pop":180,
    "ks:ks_type":"HABITATION",
    "name:eng_x_preferred":[
        "Thulukkanpatti"
    ],
    "wof:name":"Thulukkanpatti",
    "wof:placetype":"locality",
    "wof:population":180
},
  "geometry": {"coordinates":[78.72662,10.572703],"type":"Point"}
}