{
  "type": "Feature",
  "properties": {
    "gn:admin1_code":"36.0",
    "gn:admin2_code":"135.0",
    "gn:asciiname":"Nimwalibasti",
    "gn:country_code":"IN",
    "gn:dem":204,
    "gn:feature_class":"P",
    "gn:feature_code":"PPL",
    "gn:name":"N\u012bmw\u0101l\u012bbasti",
    "gn:population":0,
    "gn:timezone":"Asia/Kolkata",
    "iso:country":"IN",
    "ks:ks_alt_nam":"N\u012bmw\u0101l\u012bbasti",
    "ks:ks_name":"Nimwalibasti",
    "ks:ks_type":"VILLAGE",
    "ks:ks_uagg_main":0,
    "name:eng_x_preferred":[
        "Nimwalibasti"
    ],
    "name:eng_x_variant":[
        "N\u012bmw\u0101l\u012bbasti"
    ],
    "wof:name":"Nimwalibasti",
    "wof:placetype":"locality"
},
  "geometry": {"coordinates":[78.557379,28.597225],"type":"Point"}
}