{
  "type": "Feature",
  "properties": {
    "iso:country":"IN",
    "ks:ks_name":"Katarachunghoopur",
    "ks:ks_pop":1661,
    "ks:ks_type":"VILLAGE",
    "name:eng_x_preferred":[
        "Katarachunghoopur"
    ],
    "wof:name":"Katarachunghoopur",
    "wof:placetype":"locality",
    "wof:population":1661
},
  "geometry": {"coordinates":[82.35670500000001,26.34456],"type":"Point"}
}