{
  "type": "Feature",
  "properties": {
    "iso:country":"IN",
    "ks:ks_name":"Donkaiputtu",
    "ks:ks_pop":156,
    "ks:ks_type":"VILLAGE",
    "name:eng_x_preferred":[
        "Donkaiputtu"
    ],
    "wof:name":"Donkaiputtu",
    "wof:placetype":"locality",
    "wof:population":156
},
  "geometry": {"coordinates":[82.925389,18.163574],"type":"Point"}
}