{
  "type": "Feature",
  "properties": {
    "iso:country":"IN",
    "ks:ks_name":"Pokharatola",
    "ks:ks_pop":110,
    "ks:ks_type":"HABITATION",
    "name:eng_x_preferred":[
        "Pokharatola"
    ],
    "wof:name":"Pokharatola",
    "wof:placetype":"locality",
    "wof:population":110
},
  "geometry": {"coordinates":[83.33055899999999,24.744377],"type":"Point"}
}