{
  "type": "Feature",
  "properties": {
    "iso:country":"IN",
    "ks:ks_name":"Mahesh Raidih",
    "ks:ks_pop":723,
    "ks:ks_type":"VILLAGE",
    "ks:ks_uagg_main":0,
    "name:eng_x_preferred":[
        "Mahesh Raidih"
    ],
    "wof:name":"Mahesh Raidih",
    "wof:placetype":"neighbourhood",
    "wof:population":723
},
  "geometry": {"coordinates":[86.109758,24.41211],"type":"Point"}
}