{
  "type": "Feature",
  "properties": {
    "iso:country":"IN",
    "ks:ks_name":"Ekaghariapalli",
    "ks:ks_pop":214,
    "ks:ks_type":"VILLAGE",
    "name:eng_x_preferred":[
        "Ekaghariapalli"
    ],
    "wof:name":"Ekaghariapalli",
    "wof:placetype":"locality",
    "wof:population":214
},
  "geometry": {"coordinates":[84.806696,20.008218],"type":"Point"}
}