{
  "type": "Feature",
  "properties": {
    "gn:admin1_code":"16",
    "gn:admin2_code":"506.0",
    "gn:asciiname":"Asola",
    "gn:country_code":"IN",
    "gn:dem":228,
    "gn:feature_class":"P",
    "gn:feature_code":"PPL",
    "gn:name":"\u0100sola",
    "gn:population":0,
    "gn:timezone":"Asia/Kolkata",
    "iso:country":"IN",
    "name:ben_x_preferred":[
        "\u0985\u09b8\u09cb\u09b2\u09be"
    ],
    "name:ceb_x_preferred":[
        "Asola"
    ],
    "name:deu_x_preferred":[
        "Asola"
    ],
    "name:ita_x_preferred":[
        "Asola"
    ],
    "name:nld_x_preferred":[
        "Asola"
    ],
    "name:swe_x_preferred":[
        "Asola"
    ],
    "name:vie_x_preferred":[
        "Asola"
    ],
    "wof:name":"Asola",
    "wof:placetype":"locality"
},
  "geometry": {"coordinates":[79.87069,20.74027],"type":"Point"}
}