{
  "type": "Feature",
  "properties": {
    "iso:country":"IN",
    "ks:ks_name":"Brindabani",
    "ks:ks_pop":223,
    "ks:ks_type":"VILLAGE",
    "name:eng_x_preferred":[
        "Brindabani"
    ],
    "wof:name":"Brindabani",
    "wof:placetype":"locality",
    "wof:population":223
},
  "geometry": {"coordinates":[87.310642,24.305619],"type":"Point"}
}