{
  "type": "Feature",
  "properties": {
    "iso:country":"IN",
    "ks:ks_name":"Tomar Ki Marheya",
    "ks:ks_pop":24,
    "ks:ks_type":"HABITATION",
    "name:eng_x_preferred":[
        "Tomar Ki Marheya"
    ],
    "wof:name":"Tomar Ki Marheya",
    "wof:placetype":"locality",
    "wof:population":24
},
  "geometry": {"coordinates":[78.078138,27.041258],"type":"Point"}
}