{
  "type": "Feature",
  "properties": {
    "iso:country":"IN",
    "ks:ks_name":"Veerwadi",
    "ks:ks_pop":259,
    "ks:ks_type":"HABITATION",
    "name:eng_x_preferred":[
        "Veerwadi"
    ],
    "wof:name":"Veerwadi",
    "wof:placetype":"locality",
    "wof:population":259
},
  "geometry": {"coordinates":[73.471276,16.888453],"type":"Point"}
}