{
  "type": "Feature",
  "properties": {
    "iso:country":"IN",
    "ks:ks_name":"Powai Forest Vill",
    "ks:ks_pop":1723,
    "ks:ks_type":"HABITATION",
    "name:eng_x_preferred":[
        "Powai Forest Vill"
    ],
    "wof:name":"Powai Forest Vill",
    "wof:placetype":"locality",
    "wof:population":1723
},
  "geometry": {"coordinates":[95.620198,27.320753],"type":"Point"}
}