{
  "type": "Feature",
  "properties": {
    "gn:admin1_code":"37.0",
    "gn:admin2_code":"413",
    "gn:asciiname":"Dhaneli",
    "gn:country_code":"IN",
    "gn:dem":626,
    "gn:feature_class":"P",
    "gn:feature_code":"PPL",
    "gn:name":"Dhaneli",
    "gn:population":0,
    "gn:timezone":"Asia/Kolkata",
    "iso:country":"IN",
    "ks:ks_name":"Dhaneli",
    "ks:ks_pop":813,
    "ks:ks_type":"VILLAGE",
    "name:eng_x_preferred":[
        "Dhaneli"
    ],
    "wof:name":"Dhaneli",
    "wof:placetype":"locality",
    "wof:population":813
},
  "geometry": {"coordinates":[81.236251,20.160062],"type":"Point"}
}