{
  "type": "Feature",
  "properties": {
    "gn:admin1_code":"37.0",
    "gn:admin2_code":"413",
    "gn:asciiname":"Dhaneli",
    "gn:country_code":"IN",
    "gn:dem":626,
    "gn:feature_class":"P",
    "gn:feature_code":"PPL",
    "gn:name":"Dhaneli",
    "gn:population":0,
    "gn:timezone":"Asia/Kolkata",
    "iso:country":"IN",
    "wof:name":"Dhaneli",
    "wof:placetype":"locality"
},
  "geometry": {"coordinates":[81.23625,20.16006],"type":"Point"}
}