{
  "type": "Feature",
  "properties": {
    "gn:admin1_code":"25",
    "gn:admin2_code":"606.0",
    "gn:asciiname":"Thanipadi",
    "gn:cc2":"IN",
    "gn:country_code":"IN",
    "gn:dem":210,
    "gn:feature_class":"P",
    "gn:feature_code":"PPL",
    "gn:name":"Thanipadi",
    "gn:population":0,
    "gn:timezone":"Asia/Kolkata",
    "iso:country":"IN",
    "name:und_x_variant":[
        "Tanipadi",
        "Tanipp\u0101di"
    ],
    "wof:name":"Thanipadi",
    "wof:placetype":"locality"
},
  "geometry": {"coordinates":[78.83416,12.10819],"type":"Point"}
}