{
  "type": "Feature",
  "properties": {
    "iso:country":"IN",
    "ks:ks_name":"Jakharo Ki Dhani",
    "ks:ks_pop":257,
    "ks:ks_type":"HABITATION",
    "name:eng_x_preferred":[
        "Jakharo Ki Dhani"
    ],
    "wof:name":"Jakharo Ki Dhani",
    "wof:placetype":"locality",
    "wof:population":257
},
  "geometry": {"coordinates":[71.095275,25.656025],"type":"Point"}
}