{
  "type": "Feature",
  "properties": {
    "iso:country":"IN",
    "ks:ks_name":"Navalepatilwasti",
    "ks:ks_pop":499,
    "ks:ks_type":"HABITATION",
    "name:eng_x_preferred":[
        "Navalepatilwasti"
    ],
    "wof:name":"Navalepatilwasti",
    "wof:placetype":"locality",
    "wof:population":499
},
  "geometry": {"coordinates":[75.224532,18.507128],"type":"Point"}
}