{
  "type": "Feature",
  "properties": {
    "iso:country":"IN",
    "ks:ks_alt_nam":"Ling\u0101pur",
    "ks:ks_name":"Lingapur",
    "ks:ks_type":"VILLAGE",
    "name:eng_x_preferred":[
        "Lingapur"
    ],
    "name:eng_x_variant":[
        "Ling\u0101pur"
    ],
    "wof:name":"Lingapur",
    "wof:placetype":"locality"
},
  "geometry": {"coordinates":[76.305336,15.275169],"type":"Point"}
}