{
  "type": "Feature",
  "properties": {
    "iso:country":"IN",
    "ks:ks_name":"Bhangera",
    "ks:ks_pop":9,
    "ks:ks_type":"VILLAGE",
    "name:eng_x_preferred":[
        "Bhangera"
    ],
    "wof:name":"Bhangera",
    "wof:placetype":"locality",
    "wof:population":9
},
  "geometry": {"coordinates":[74.802573,28.615664],"type":"Point"}
}