{
  "type": "Feature",
  "properties": {
    "gn:admin1_code":"2",
    "gn:admin2_code":"545.0",
    "gn:asciiname":"Nakkaratipalem",
    "gn:country_code":"IN",
    "gn:dem":302,
    "gn:feature_class":"P",
    "gn:feature_code":"PPL",
    "gn:name":"Nakkar\u0101tip\u0101lem",
    "gn:population":0,
    "gn:timezone":"Asia/Kolkata",
    "iso:country":"IN",
    "ks:ks_name":"Nakkarathipalem",
    "ks:ks_pop":66,
    "ks:ks_type":"HABITATION",
    "name:eng_x_preferred":[
        "Nakkarathipalem"
    ],
    "name:eng_x_variant":[
        "Nakkaratipalem"
    ],
    "wof:name":"Nakkarathipalem",
    "wof:placetype":"locality",
    "wof:population":66
},
  "geometry": {"coordinates":[81.987922,17.670597],"type":"Point"}
}