{
  "type": "Feature",
  "properties": {
    "gn:admin1_code":"28.0",
    "gn:admin2_code":"343",
    "gn:asciiname":"Bhangar",
    "gn:country_code":"IN",
    "gn:dem":10,
    "gn:feature_class":"P",
    "gn:feature_code":"PPL",
    "gn:name":"Bh\u0101ngar",
    "gn:population":0,
    "gn:timezone":"Asia/Kolkata",
    "iso:country":"IN",
    "ks:ks_alt_nam":"Bh\u0101ngar",
    "ks:ks_name":"Bhangar",
    "ks:ks_type":"VILLAGE",
    "ks:ks_uagg_main":0,
    "name:eng_x_preferred":[
        "Bhangar"
    ],
    "name:eng_x_variant":[
        "Bh\u0101ngar"
    ],
    "name:und_x_variant":[
        "Bh\u0101ngar"
    ],
    "wof:name":"Bhangar",
    "wof:placetype":"neighbourhood"
},
  "geometry": {"coordinates":[88.604527,22.509247],"type":"Point"}
}