{
  "type": "Feature",
  "properties": {
    "gn:admin1_code":"24.0",
    "gn:admin2_code":"122.0",
    "gn:asciiname":"Akarsada",
    "gn:country_code":"IN",
    "gn:dem":457,
    "gn:feature_class":"P",
    "gn:feature_code":"PPL",
    "gn:name":"Akars\u0101da",
    "gn:population":0,
    "gn:timezone":"Asia/Kolkata",
    "iso:country":"IN",
    "wof:name":"Akarsada",
    "wof:placetype":"locality"
},
  "geometry": {"coordinates":[74.39154000000001,25.84518],"type":"Point"}
}