{
  "type": "Feature",
  "properties": {
    "gn:admin1_code":"23.0",
    "gn:admin2_code":"45.0",
    "gn:asciiname":"Baihbal Khurd",
    "gn:country_code":"IN",
    "gn:dem":211,
    "gn:feature_class":"P",
    "gn:feature_code":"PPL",
    "gn:name":"Baihbal Khurd",
    "gn:population":0,
    "gn:timezone":"Asia/Kolkata",
    "iso:country":"IN",
    "name:und_x_variant":[
        "Ni\u0101miw\u0101la"
    ],
    "wof:name":"Baihbal Khurd",
    "wof:placetype":"locality"
},
  "geometry": {"coordinates":[74.91263000000002,30.50199000000001],"type":"Point"}
}