{
  "type": "Feature",
  "properties": {
    "gn:admin1_code":"34.0",
    "gn:admin2_code":"212.0",
    "gn:asciiname":"Bargaon",
    "gn:country_code":"IN",
    "gn:dem":36,
    "gn:feature_class":"P",
    "gn:feature_code":"PPL",
    "gn:name":"Bargaon",
    "gn:population":0,
    "gn:timezone":"Asia/Kolkata",
    "iso:country":"IN",
    "ks:ks_name":"Bargaon",
    "ks:ks_pop":2843,
    "ks:ks_type":"VILLAGE",
    "ks:ks_uagg_main":0,
    "name:eng_x_preferred":[
        "Bargaon"
    ],
    "wof:name":"Bargaon",
    "wof:placetype":"neighbourhood",
    "wof:population":2843
},
  "geometry": {"coordinates":[87.44956500000001,25.553602],"type":"Point"}
}