{
  "type": "Feature",
  "properties": {
    "gn:admin1_code":"12.0",
    "gn:asciiname":"Khui",
    "gn:country_code":"IN",
    "gn:dem":741,
    "gn:feature_class":"P",
    "gn:feature_code":"PPL",
    "gn:name":"Khui",
    "gn:population":0,
    "gn:timezone":"Asia/Kolkata",
    "iso:country":"IN",
    "name:cat_x_preferred":[
        "Khui"
    ],
    "name:deu_x_preferred":[
        "Chui"
    ],
    "name:fra_x_preferred":[
        "Khoui"
    ],
    "name:hun_x_preferred":[
        "Hui"
    ],
    "name:ita_x_preferred":[
        "Khui"
    ],
    "name:jpn_x_preferred":[
        "\u30af\u30a4"
    ],
    "name:kat_x_preferred":[
        "\u10ee\u10e3\u10d8"
    ],
    "name:spa_x_preferred":[
        "Jui"
    ],
    "name:swe_x_preferred":[
        "Khui"
    ],
    "name:vie_x_preferred":[
        "Khui"
    ],
    "wof:name":"Khui",
    "wof:placetype":"locality"
},
  "geometry": {"coordinates":[74.28333000000001,33.10556],"type":"Point"}
}