{
  "type": "Feature",
  "properties": {
    "iso:country":"IN",
    "ks:ks_name":"Kaldiapar",
    "ks:ks_pop":345,
    "ks:ks_type":"HABITATION",
    "name:eng_x_preferred":[
        "Kaldiapar"
    ],
    "wof:name":"Kaldiapar",
    "wof:placetype":"locality",
    "wof:population":345
},
  "geometry": {"coordinates":[91.24111600000001,26.7214],"type":"Point"}
}