{
  "type": "Feature",
  "properties": {
    "iso:country":"IN",
    "ks:ks_name":"Anna Nagar",
    "ks:ks_pop":365,
    "ks:ks_type":"HABITATION",
    "ks:ks_uagg_main":0,
    "name:eng_x_preferred":[
        "Anna Nagar"
    ],
    "wof:name":"Anna Nagar",
    "wof:placetype":"neighbourhood",
    "wof:population":365
},
  "geometry": {"coordinates":[80.141395,13.365428],"type":"Point"}
}