{
  "type": "Feature",
  "properties": {
    "iso:country":"IN",
    "ks:ks_alt_nam":"kodari",
    "ks:ks_name":"Kodari",
    "ks:ks_pop":92,
    "ks:ks_type":"HABITATION",
    "ks:ks_uagg_main":0,
    "name:eng_x_preferred":[
        "Kodari"
    ],
    "wof:name":"Kodari",
    "wof:placetype":"neighbourhood",
    "wof:population":92
},
  "geometry": {"coordinates":[81.70040899999999,27.356106],"type":"Point"}
}