{
  "type": "Feature",
  "properties": {
    "iso:country":"IN",
    "ks:ks_name":"Tenth Block",
    "ks:ks_pop":2000,
    "ks:ks_type":"HABITATION",
    "name:eng_x_preferred":[
        "Tenth Block"
    ],
    "wof:name":"Tenth Block",
    "wof:placetype":"locality",
    "wof:population":2000
},
  "geometry": {"coordinates":[76.858486,9.340904],"type":"Point"}
}