{
  "type": "Feature",
  "properties": {
    "iso:country":"IN",
    "ks:ks_name":"Konjavade",
    "ks:ks_pop":1158,
    "ks:ks_type":"VILLAGE",
    "name:eng_x_preferred":[
        "Konjavade"
    ],
    "wof:name":"Konjavade",
    "wof:placetype":"locality",
    "wof:population":1158
},
  "geometry": {"coordinates":[73.973967,17.519125],"type":"Point"}
}