{
  "type": "Feature",
  "properties": {
    "iso:country":"IN",
    "ks:ks_name":"Bolakottai",
    "ks:ks_pop":169,
    "ks:ks_type":"HABITATION",
    "name:eng_x_preferred":[
        "Bolakottai"
    ],
    "wof:name":"Bolakottai",
    "wof:placetype":"locality",
    "wof:population":169
},
  "geometry": {"coordinates":[77.88996400000001,12.355508],"type":"Point"}
}