{
  "type": "Feature",
  "properties": {
    "iso:country":"IN",
    "ks:ks_name":"Pasor Falia",
    "ks:ks_pop":1231,
    "ks:ks_type":"HABITATION",
    "name:eng_x_preferred":[
        "Pasor Falia"
    ],
    "wof:name":"Pasor Falia",
    "wof:placetype":"locality",
    "wof:population":1231
},
  "geometry": {"coordinates":[73.974,23.213028],"type":"Point"}
}