{
  "type": "Feature",
  "properties": {
    "iso:country":"IN",
    "ks:ks_name":"Chorvalu Faliya",
    "ks:ks_pop":355,
    "ks:ks_type":"HABITATION",
    "name:eng_x_preferred":[
        "Chorvalu Faliya"
    ],
    "wof:name":"Chorvalu Faliya",
    "wof:placetype":"locality",
    "wof:population":355
},
  "geometry": {"coordinates":[73.47029999999999,22.790083],"type":"Point"}
}