{
  "type": "Feature",
  "properties": {
    "iso:country":"IN",
    "ks:ks_name":"Karampatty",
    "ks:ks_pop":155,
    "ks:ks_type":"HABITATION",
    "name:eng_x_preferred":[
        "Karampatty"
    ],
    "wof:name":"Karampatty",
    "wof:placetype":"locality",
    "wof:population":155
},
  "geometry": {"coordinates":[78.63552,10.472479],"type":"Point"}
}