{
  "type": "Feature",
  "properties": {
    "gn:admin1_code":"10.0",
    "gn:admin2_code":"78.0",
    "gn:asciiname":"Nathwan",
    "gn:country_code":"IN",
    "gn:dem":218,
    "gn:feature_class":"P",
    "gn:feature_code":"PPL",
    "gn:name":"Nathw\u0101n",
    "gn:population":0,
    "gn:timezone":"Asia/Kolkata",
    "iso:country":"IN",
    "ks:ks_alt_nam":"Nathw\u0101n",
    "ks:ks_name":"Nathwan",
    "ks:ks_pop":1531,
    "ks:ks_type":"VILLAGE",
    "name:eng_x_preferred":[
        "Nathwan"
    ],
    "name:eng_x_variant":[
        "Nathw\u0101n"
    ],
    "wof:name":"Nathwan",
    "wof:placetype":"locality",
    "wof:population":1531
},
  "geometry": {"coordinates":[75.61145399999999,29.674355],"type":"Point"}
}