{
  "type": "Feature",
  "properties": {
    "iso:country":"IN",
    "ks:ks_name":"Amghata",
    "ks:ks_pop":489,
    "ks:ks_type":"VILLAGE",
    "name:eng_x_preferred":[
        "Amghata"
    ],
    "wof:name":"Amghata",
    "wof:placetype":"locality",
    "wof:population":489
},
  "geometry": {"coordinates":[86.945003,24.508694],"type":"Point"}
}