{
  "type": "Feature",
  "properties": {
    "iso:country":"IN",
    "ks:ks_name":"Gonduguda",
    "ks:ks_pop":200,
    "ks:ks_type":"HABITATION",
    "name:eng_x_preferred":[
        "Gonduguda"
    ],
    "wof:name":"Gonduguda",
    "wof:placetype":"locality",
    "wof:population":200
},
  "geometry": {"coordinates":[78.47568200000001,19.140157],"type":"Point"}
}