{
  "type": "Feature",
  "properties": {
    "gn:admin1_code":"34.0",
    "gn:admin2_code":"221.0",
    "gn:asciiname":"Bishunpur Beri",
    "gn:country_code":"IN",
    "gn:dem":53,
    "gn:feature_class":"P",
    "gn:feature_code":"PPL",
    "gn:name":"Bishunpur Beri",
    "gn:population":0,
    "gn:timezone":"Asia/Kolkata",
    "iso:country":"IN",
    "ks:ks_name":"Bishunpur Beri",
    "ks:ks_pop":6943,
    "ks:ks_type":"VILLAGE",
    "ks:ks_uagg_main":0,
    "name:eng_x_preferred":[
        "Bishunpur Beri"
    ],
    "wof:name":"Bishunpur Beri",
    "wof:placetype":"neighbourhood",
    "wof:population":6943
},
  "geometry": {"coordinates":[85.64984,25.550502],"type":"Point"}
}