{
  "type": "Feature",
  "properties": {
    "gn:admin1_code":"34.0",
    "gn:admin2_code":"222.0",
    "gn:asciiname":"Bhadiha",
    "gn:country_code":"IN",
    "gn:dem":48,
    "gn:feature_class":"P",
    "gn:feature_code":"PPL",
    "gn:name":"Bhadiha",
    "gn:population":0,
    "gn:timezone":"Asia/Kolkata",
    "iso:country":"IN",
    "ks:ks_name":"Bhadiha",
    "ks:ks_type":"VILLAGE",
    "name:eng_x_preferred":[
        "Bhadiha"
    ],
    "wof:name":"Bhadiha",
    "wof:placetype":"locality"
},
  "geometry": {"coordinates":[85.984275,25.548259],"type":"Point"}
}