{
  "type": "Feature",
  "properties": {
    "iso:country":"IN",
    "ks:ks_name":"Kothagud",
    "ks:ks_pop":101,
    "ks:ks_type":"HABITATION",
    "name:eng_x_preferred":[
        "Kothagud"
    ],
    "wof:name":"Kothagud",
    "wof:placetype":"locality",
    "wof:population":101
},
  "geometry": {"coordinates":[83.840485,18.661302],"type":"Point"}
}