{
  "type": "Feature",
  "properties": {
    "gn:admin1_code":"11",
    "gn:admin2_code":"34.0",
    "gn:asciiname":"Ukhyang Santang Dogri",
    "gn:country_code":"IN",
    "gn:dem":3023,
    "gn:feature_class":"P",
    "gn:feature_code":"PPL",
    "gn:name":"Ukhyang S\u0101ntang Dogri",
    "gn:population":0,
    "gn:timezone":"Asia/Kolkata",
    "iso:country":"IN",
    "wof:name":"Ukhyang Santang Dogri",
    "wof:placetype":"locality"
},
  "geometry": {"coordinates":[78.34744000000001,31.5754],"type":"Point"}
}