{
  "type": "Feature",
  "properties": {
    "gn:admin1_code":"36",
    "gn:admin2_code":"169.0",
    "gn:asciiname":"Ragaulia Khurd",
    "gn:country_code":"IN",
    "gn:dem":221,
    "gn:feature_class":"P",
    "gn:feature_code":"PPL",
    "gn:name":"Ragaulia Khurd",
    "gn:population":0,
    "gn:timezone":"Asia/Kolkata",
    "iso:country":"IN",
    "ks:ks_name":"Ragaulia Khurd",
    "ks:ks_type":"VILLAGE",
    "ks:ks_uagg_main":0,
    "name:eng_x_preferred":[
        "Ragaulia Khurd"
    ],
    "wof:name":"Ragaulia Khurd",
    "wof:placetype":"neighbourhood"
},
  "geometry": {"coordinates":[79.65640500000001,25.215402],"type":"Point"}
}