{
  "type": "Feature",
  "properties": {
    "iso:country":"IN",
    "ks:ks_name":"Rang Nagar Chohan Bosti",
    "ks:ks_pop":181,
    "ks:ks_type":"HABITATION",
    "name:eng_x_preferred":[
        "Rang Nagar Chohan Bosti"
    ],
    "wof:name":"Rang Nagar Chohan Bosti",
    "wof:placetype":"locality",
    "wof:population":181
},
  "geometry": {"coordinates":[93.23601499999999,26.040226],"type":"Point"}
}