{
  "type": "Feature",
  "properties": {
    "gn:admin1_code":"23",
    "gn:admin2_code":"39.0",
    "gn:asciiname":"Sotran",
    "gn:country_code":"IN",
    "gn:dem":249,
    "gn:feature_class":"P",
    "gn:feature_code":"PPL",
    "gn:name":"Sotran",
    "gn:population":0,
    "gn:timezone":"Asia/Kolkata",
    "iso:country":"IN",
    "ks:ks_name":"Sotran",
    "ks:ks_type":"VILLAGE",
    "name:por_x_preferred":[
        "Sotran"
    ],
    "wof:name":"Sotran",
    "wof:placetype":"neighbourhood"
},
  "geometry": {"coordinates":[75.98493999999999,31.17913],"type":"Point"}
}