{
  "type": "Feature",
  "properties": {
    "iso:country":"IN",
    "ks:ks_alt_nam":"MUNDATOLI",
    "ks:ks_name":"Mundatoli",
    "ks:ks_pop":130,
    "ks:ks_type":"HABITATION",
    "name:eng_x_preferred":[
        "Mundatoli"
    ],
    "wof:name":"Mundatoli",
    "wof:placetype":"locality",
    "wof:population":130
},
  "geometry": {"coordinates":[85.862041,22.396145],"type":"Point"}
}