{
  "type": "Feature",
  "properties": {
    "gn:admin1_code":"2",
    "gn:admin2_code":"548.0",
    "gn:asciiname":"Bhimavaram",
    "gn:country_code":"IN",
    "gn:dem":70,
    "gn:feature_class":"P",
    "gn:feature_code":"PPL",
    "gn:name":"Bh\u012bmavaram",
    "gn:population":0,
    "gn:timezone":"Asia/Kolkata",
    "iso:country":"IN",
    "name:bih_x_preferred":[
        "\u092d\u0940\u092e\u093e\u0935\u0930\u092e"
    ],
    "name:bpy_x_preferred":[
        "\u09ad\u09c7\u09ae\u09be\u09ac\u09be\u09b0\u09be\u09ae"
    ],
    "name:ceb_x_preferred":[
        "Bh\u012bmavaram"
    ],
    "name:ita_x_preferred":[
        "Bhimavaram"
    ],
    "name:mlg_x_preferred":[
        "Bhimavaram"
    ],
    "name:msa_x_preferred":[
        "Bheemavaram"
    ],
    "name:new_x_preferred":[
        "\u092d\u0940\u092e\u0935\u0930\u093e\u092e"
    ],
    "name:ori_x_preferred":[
        "\u0b2d\u0b3f\u0b2e\u0b3e\u0b2c\u0b30\u0b2e"
    ],
    "name:pam_x_preferred":[
        "Bhimavaram"
    ],
    "name:por_x_preferred":[
        "Bhimavaram"
    ],
    "name:swe_x_preferred":[
        "Bhimavaram"
    ],
    "name:tam_x_preferred":[
        "\u0baa\u0bc0\u0bae\u0bb5\u0bb0\u0bae\u0bcd"
    ],
    "name:tel_x_preferred":[
        "\u0c2d\u0c40\u0c2e\u0c35\u0c30\u0c02"
    ],
    "name:tgl_x_preferred":[
        "Bhimavaram"
    ],
    "name:urd_x_preferred":[
        "\u0628\u06be\u06cc\u0645\u0627\u0648\u0631\u0645"
    ],
    "name:vie_x_preferred":[
        "Bheemavaram"
    ],
    "name:war_x_preferred":[
        "Bheemavaram"
    ],
    "name:zho_x_preferred":[
        "\u8d1d\u57c3\u9a6c\u74e6\u62c9\u59c6"
    ],
    "wof:name":"Bhimavaram",
    "wof:placetype":"locality"
},
  "geometry": {"coordinates":[80.16979000000001,16.42077],"type":"Point"}
}