{
  "type": "Feature",
  "properties": {
    "iso:country":"IN",
    "ks:ks_name":"Adiste",
    "ks:ks_pop":535,
    "ks:ks_type":"VILLAGE",
    "name:eng_x_preferred":[
        "Adiste"
    ],
    "wof:name":"Adiste",
    "wof:placetype":"locality",
    "wof:population":535
},
  "geometry": {"coordinates":[73.339084,18.033525],"type":"Point"}
}