{
  "type": "Feature",
  "properties": {
    "gn:admin1_code":"34.0",
    "gn:admin2_code":"224.0",
    "gn:asciiname":"Garia",
    "gn:country_code":"IN",
    "gn:dem":40,
    "gn:feature_class":"P",
    "gn:feature_code":"PPL",
    "gn:name":"Garia",
    "gn:population":0,
    "gn:timezone":"Asia/Kolkata",
    "iso:country":"IN",
    "name:ben_x_preferred":[
        "\u0997\u09a1\u09bc\u09bf\u09af\u09bc\u09be"
    ],
    "wof:name":"Garia",
    "wof:placetype":"locality"
},
  "geometry": {"coordinates":[87.05426999999997,25.34417],"type":"Point"}
}