{
  "type": "Feature",
  "properties": {
    "iso:country":"IN",
    "ks:ks_name":"N. Dali",
    "ks:ks_pop":122,
    "ks:ks_type":"HABITATION",
    "name:eng_x_preferred":[
        "N. Dali"
    ],
    "wof:name":"N. Dali",
    "wof:placetype":"locality",
    "wof:population":122
},
  "geometry": {"coordinates":[78.67109000000001,27.328329],"type":"Point"}
}