{
  "type": "Feature",
  "properties": {
    "iso:country":"IN",
    "ks:ks_alt_nam":"narsanda",
    "ks:ks_name":"Narsanda",
    "ks:ks_pop":513,
    "ks:ks_type":"HABITATION",
    "name:eng_x_preferred":[
        "Narsanda"
    ],
    "wof:name":"Narsanda",
    "wof:placetype":"locality",
    "wof:population":513
},
  "geometry": {"coordinates":[85.403312,22.48424],"type":"Point"}
}