{
  "type": "Feature",
  "properties": {
    "iso:country":"IN",
    "ks:ks_name":"Bagri Dhar",
    "ks:ks_pop":85,
    "ks:ks_type":"HABITATION",
    "name:eng_x_preferred":[
        "Bagri Dhar"
    ],
    "wof:name":"Bagri Dhar",
    "wof:placetype":"locality",
    "wof:population":85
},
  "geometry": {"coordinates":[78.94016999999999,29.8938],"type":"Point"}
}