{
  "type": "Feature",
  "properties": {
    "iso:country":"IN",
    "ks:ks_name":"Katha",
    "ks:ks_pop":342,
    "ks:ks_type":"HABITATION",
    "ks:ks_uagg_main":0,
    "name:eng_x_preferred":[
        "Katha"
    ],
    "wof:name":"Katha",
    "wof:placetype":"locality",
    "wof:population":342
},
  "geometry": {"coordinates":[80.404068,26.492475],"type":"Point"}
}