{
  "type": "Feature",
  "properties": {
    "gn:admin1_code":"23",
    "gn:admin2_code":"37.0",
    "gn:asciiname":"Darapur",
    "gn:country_code":"IN",
    "gn:dem":220,
    "gn:feature_class":"P",
    "gn:feature_code":"PPL",
    "gn:name":"D\u0101r\u0101pur",
    "gn:population":0,
    "gn:timezone":"Asia/Kolkata",
    "iso:country":"IN",
    "name:fas_x_preferred":[
        "\u062f\u0627\u0631\u0627\u067e\u0648\u0631"
    ],
    "name:urd_x_preferred":[
        "\u062f\u0627\u0631\u0627 \u067e\u0648\u0631"
    ],
    "wof:name":"Darapur",
    "wof:placetype":"locality"
},
  "geometry": {"coordinates":[75.30301999999998,31.13677],"type":"Point"}
}