{
  "type": "Feature",
  "properties": {
    "gn:admin1_code":"36",
    "gn:admin2_code":"191.0",
    "gn:asciiname":"Tahirpur Sakaha",
    "gn:country_code":"IN",
    "gn:dem":85,
    "gn:feature_class":"P",
    "gn:feature_code":"PPL",
    "gn:name":"T\u0101hirpur Sak\u0101h\u0101",
    "gn:population":0,
    "gn:timezone":"Asia/Kolkata",
    "iso:country":"IN",
    "wof:name":"Tahirpur Sakaha",
    "wof:placetype":"locality"
},
  "geometry": {"coordinates":[82.99238000000003,25.70142],"type":"Point"}
}