{
  "type": "Feature",
  "properties": {
    "iso:country":"IN",
    "ks:ks_alt_nam":"Harsuw\u0101ra",
    "ks:ks_name":"Harsuwara",
    "ks:ks_type":"VILLAGE",
    "ks:ks_uagg_main":0,
    "name:eng_x_preferred":[
        "Harsuwara"
    ],
    "name:eng_x_variant":[
        "Harsuw\u0101ra"
    ],
    "wof:name":"Harsuwara",
    "wof:placetype":"neighbourhood"
},
  "geometry": {"coordinates":[78.331413,29.608969],"type":"Point"}
}