{
  "type": "Feature",
  "properties": {
    "gn:admin1_code":"23",
    "gn:admin2_code":"43.0",
    "gn:asciiname":"Lakkhoke Bahram",
    "gn:country_code":"IN",
    "gn:dem":194,
    "gn:feature_class":"P",
    "gn:feature_code":"PPL",
    "gn:name":"Lakkhoke Bahr\u0101m",
    "gn:population":0,
    "gn:timezone":"Asia/Kolkata",
    "iso:country":"IN",
    "wof:name":"Lakkhoke Bahram",
    "wof:placetype":"locality"
},
  "geometry": {"coordinates":[74.4487,30.82523],"type":"Point"}
}