{
  "type": "Feature",
  "properties": {
    "iso:country":"IN",
    "ks:ks_alt_nam":"Malum Rai para",
    "ks:ks_name":"Malum Rai Para",
    "ks:ks_pop":60,
    "ks:ks_type":"HABITATION",
    "name:eng_x_preferred":[
        "Malum Rai Para"
    ],
    "wof:name":"Malum Rai Para",
    "wof:placetype":"locality",
    "wof:population":60
},
  "geometry": {"coordinates":[91.590204,23.422087],"type":"Point"}
}