{
  "type": "Feature",
  "properties": {
    "iso:country":"IN",
    "ks:ks_name":"Asda Dakshin",
    "ks:ks_pop":194,
    "ks:ks_type":"VILLAGE",
    "ks:ks_uagg_main":0,
    "name:eng_x_preferred":[
        "Asda Dakshin"
    ],
    "wof:name":"Asda Dakshin",
    "wof:placetype":"neighbourhood",
    "wof:population":194
},
  "geometry": {"coordinates":[87.46082199999999,21.873069],"type":"Point"}
}