{
  "type": "Feature",
  "properties": {
    "iso:country":"IN",
    "ks:ks_alt_nam":"Pand\u012bb\u0101h\u0101l",
    "ks:ks_name":"Pandibahal",
    "ks:ks_type":"VILLAGE",
    "name:eng_x_preferred":[
        "Pandibahal"
    ],
    "name:eng_x_variant":[
        "Pand\u012bb\u0101h\u0101l"
    ],
    "wof:name":"Pandibahal",
    "wof:placetype":"locality"
},
  "geometry": {"coordinates":[84.26316300000001,21.558069],"type":"Point"}
}