{
  "type": "Feature",
  "properties": {
    "iso:country":"IN",
    "ks:ks_alt_nam":"DebitolaPt I",
    "ks:ks_name":"Debitolapt I",
    "ks:ks_pop":262,
    "ks:ks_type":"HABITATION",
    "name:eng_x_preferred":[
        "Debitolapt I"
    ],
    "wof:name":"Debitolapt I",
    "wof:placetype":"locality",
    "wof:population":262
},
  "geometry": {"coordinates":[90.00732600000001,26.159318],"type":"Point"}
}