{
  "type": "Feature",
  "properties": {
    "iso:country":"IN",
    "ks:ks_name":"Madhukuruda",
    "ks:ks_pop":296,
    "ks:ks_type":"VILLAGE",
    "name:eng_x_preferred":[
        "Madhukuruda"
    ],
    "wof:name":"Madhukuruda",
    "wof:placetype":"locality",
    "wof:population":296
},
  "geometry": {"coordinates":[83.8917,19.449359],"type":"Point"}
}