{
  "type": "Feature",
  "properties": {
    "iso:country":"IN",
    "ks:ks_name":"Jogipura Alias Motipura",
    "ks:ks_pop":438,
    "ks:ks_type":"HABITATION",
    "name:eng_x_preferred":[
        "Jogipura Alias Motipura"
    ],
    "wof:name":"Jogipura Alias Motipura",
    "wof:placetype":"locality",
    "wof:population":438
},
  "geometry": {"coordinates":[76.880352,24.301631],"type":"Point"}
}