{
  "type": "Feature",
  "properties": {
    "iso:country":"IN",
    "ks:ks_name":"Bottaiguda",
    "ks:ks_pop":15,
    "ks:ks_type":"HABITATION",
    "name:eng_x_preferred":[
        "Bottaiguda"
    ],
    "wof:name":"Bottaiguda",
    "wof:placetype":"locality",
    "wof:population":15
},
  "geometry": {"coordinates":[83.739375,18.755123],"type":"Point"}
}