{
  "type": "Feature",
  "properties": {
    "iso:country":"IN",
    "ks:ks_name":"Paikapadapatna",
    "ks:ks_pop":3942,
    "ks:ks_type":"HABITATION",
    "ks:ks_uagg_main":0,
    "name:eng_x_preferred":[
        "Paikapadapatna"
    ],
    "wof:name":"Paikapadapatna",
    "wof:placetype":"neighbourhood",
    "wof:population":3942
},
  "geometry": {"coordinates":[85.072998,20.465523],"type":"Point"}
}