{
  "type": "Feature",
  "properties": {
    "gn:admin1_code":"36",
    "gn:admin2_code":"178.0",
    "gn:asciiname":"Mahmudpur",
    "gn:country_code":"IN",
    "gn:dem":96,
    "gn:feature_class":"P",
    "gn:feature_code":"PPL",
    "gn:name":"Mahm\u016bdpur",
    "gn:population":0,
    "gn:timezone":"Asia/Kolkata",
    "iso:country":"IN",
    "ks:ks_alt_nam":"Mahm\u016bdpur",
    "ks:ks_name":"Mahmudpur",
    "ks:ks_type":"VILLAGE",
    "ks:ks_uagg_main":0,
    "name:eng_x_preferred":[
        "Mahmudpur"
    ],
    "name:eng_x_variant":[
        "Mahm\u016bdpur"
    ],
    "wof:name":"Mahmudpur",
    "wof:placetype":"neighbourhood"
},
  "geometry": {"coordinates":[82.637171,26.399495],"type":"Point"}
}