{
  "type": "Feature",
  "properties": {
    "iso:country":"IN",
    "ks:ks_name":"Kurukkalnadarpatti",
    "ks:ks_pop":189,
    "ks:ks_type":"HABITATION",
    "ks:ks_uagg_main":0,
    "name:eng_x_preferred":[
        "Kurukkalnadarpatti"
    ],
    "wof:name":"Kurukkalnadarpatti",
    "wof:placetype":"neighbourhood",
    "wof:population":189
},
  "geometry": {"coordinates":[77.41480300000001,8.871316],"type":"Point"}
}