{
  "type": "Feature",
  "properties": {
    "gn:admin1_code":"19.0",
    "gn:admin2_code":"570.0",
    "gn:asciiname":"Gaurigadde",
    "gn:country_code":"IN",
    "gn:dem":646,
    "gn:feature_class":"P",
    "gn:feature_code":"PPL",
    "gn:name":"Gaurigadde",
    "gn:population":0,
    "gn:timezone":"Asia/Kolkata",
    "iso:country":"IN",
    "ks:ks_name":"Gowrigadde",
    "ks:ks_pop":33,
    "ks:ks_type":"HABITATION",
    "name:eng_x_preferred":[
        "Gowrigadde"
    ],
    "name:eng_x_variant":[
        "Gaurigadde"
    ],
    "wof:name":"Gowrigadde",
    "wof:placetype":"locality",
    "wof:population":33
},
  "geometry": {"coordinates":[75.259424,13.510499],"type":"Point"}
}