{
  "type": "Feature",
  "properties": {
    "iso:country":"IN",
    "ks:ks_name":"Kalusalewasti",
    "ks:ks_pop":150,
    "ks:ks_type":"HABITATION",
    "name:eng_x_preferred":[
        "Kalusalewasti"
    ],
    "wof:name":"Kalusalewasti",
    "wof:placetype":"locality",
    "wof:population":150
},
  "geometry": {"coordinates":[75.051511,17.656696],"type":"Point"}
}