{
  "type": "Feature",
  "properties": {
    "iso:country":"IN",
    "ks:ks_name":"Gumadhar",
    "ks:ks_pop":309,
    "ks:ks_type":"HABITATION",
    "name:eng_x_preferred":[
        "Gumadhar"
    ],
    "wof:name":"Gumadhar",
    "wof:placetype":"locality",
    "wof:population":309
},
  "geometry": {"coordinates":[84.568573,21.843219],"type":"Point"}
}