{
  "type": "Feature",
  "properties": {
    "iso:country":"IN",
    "ks:ks_name":"Sinduri",
    "ks:ks_pop":131,
    "ks:ks_type":"VILLAGE",
    "name:eng_x_preferred":[
        "Sinduri"
    ],
    "wof:name":"Sinduri",
    "wof:placetype":"locality",
    "wof:population":131
},
  "geometry": {"coordinates":[78.39202400000001,30.050508],"type":"Point"}
}