{
  "type": "Feature",
  "properties": {
    "iso:country":"IN",
    "ks:ks_name":"Sera",
    "ks:ks_pop":999,
    "ks:ks_type":"VILLAGE",
    "name:eng_x_preferred":[
        "Sera"
    ],
    "wof:name":"Sera",
    "wof:placetype":"locality",
    "wof:population":999
},
  "geometry": {"coordinates":[74.66953100000001,23.451624],"type":"Point"}
}