{
  "type": "Feature",
  "properties": {
    "iso:country":"IN",
    "ks:ks_name":"Naya Aalore",
    "ks:ks_pop":534,
    "ks:ks_type":"HABITATION",
    "name:eng_x_preferred":[
        "Naya Aalore"
    ],
    "wof:name":"Naya Aalore",
    "wof:placetype":"locality",
    "wof:population":534
},
  "geometry": {"coordinates":[80.681982,20.119932],"type":"Point"}
}