{
  "type": "Feature",
  "properties": {
    "iso:country":"IN",
    "ks:ks_name":"Dhamsara",
    "ks:ks_pop":1509,
    "ks:ks_type":"HABITATION",
    "name:eng_x_preferred":[
        "Dhamsara"
    ],
    "wof:name":"Dhamsara",
    "wof:placetype":"locality",
    "wof:population":1509
},
  "geometry": {"coordinates":[72.680502,24.482063],"type":"Point"}
}