{
  "type": "Feature",
  "properties": {
    "iso:country":"IN",
    "ks:ks_name":"Kodagibylu",
    "ks:ks_pop":29,
    "ks:ks_type":"HABITATION",
    "name:eng_x_preferred":[
        "Kodagibylu"
    ],
    "wof:name":"Kodagibylu",
    "wof:placetype":"locality",
    "wof:population":29
},
  "geometry": {"coordinates":[75.417554,13.599435],"type":"Point"}
}