{
  "type": "Feature",
  "properties": {
    "iso:country":"IN",
    "ks:ks_name":"Jangidiri",
    "ks:ks_pop":563,
    "ks:ks_type":"VILLAGE",
    "name:eng_x_preferred":[
        "Jangidiri"
    ],
    "wof:name":"Jangidiri",
    "wof:placetype":"locality",
    "wof:population":563
},
  "geometry": {"coordinates":[84.972059,22.111012],"type":"Point"}
}