{
  "type": "Feature",
  "properties": {
    "iso:country":"IN",
    "ks:ks_name":"Idnar",
    "ks:ks_pop":94,
    "ks:ks_type":"HABITATION",
    "name:eng_x_preferred":[
        "Idnar"
    ],
    "wof:name":"Idnar",
    "wof:placetype":"locality",
    "wof:population":94
},
  "geometry": {"coordinates":[81.144243,19.317042],"type":"Point"}
}