{
  "type": "Feature",
  "properties": {
    "gn:admin1_code":"24.0",
    "gn:admin2_code":"115.0",
    "gn:asciiname":"Dandali",
    "gn:country_code":"IN",
    "gn:dem":106,
    "gn:feature_class":"P",
    "gn:feature_code":"PPL",
    "gn:name":"Dandali",
    "gn:population":0,
    "gn:timezone":"Asia/Kolkata",
    "iso:country":"IN",
    "wof:name":"Dandali",
    "wof:placetype":"locality"
},
  "geometry": {"coordinates":[71.92877,25.69984],"type":"Point"}
}