{
  "type": "Feature",
  "properties": {
    "iso:country":"IN",
    "ks:ks_name":"Karukkapadam Rd",
    "ks:ks_pop":297,
    "ks:ks_type":"HABITATION",
    "ks:ks_uagg_main":0,
    "name:eng_x_preferred":[
        "Karukkapadam Rd"
    ],
    "wof:name":"Karukkapadam Rd",
    "wof:placetype":"locality",
    "wof:population":297
},
  "geometry": {"coordinates":[76.291442,10.427363],"type":"Point"}
}