{
  "type": "Feature",
  "properties": {
    "iso:country":"IN",
    "ks:ks_name":"Palaiendal",
    "ks:ks_pop":227,
    "ks:ks_type":"HABITATION",
    "name:eng_x_preferred":[
        "Palaiendal"
    ],
    "wof:name":"Palaiendal",
    "wof:placetype":"locality",
    "wof:population":227
},
  "geometry": {"coordinates":[78.674688,9.72727],"type":"Point"}
}