{
  "type": "Feature",
  "properties": {
    "gn:admin1_code":"36",
    "gn:admin2_code":"158.0",
    "gn:asciiname":"Pura Sanaullah",
    "gn:country_code":"IN",
    "gn:dem":115,
    "gn:feature_class":"P",
    "gn:feature_code":"PPL",
    "gn:name":"Pura San\u0101ull\u0101h",
    "gn:population":0,
    "gn:timezone":"Asia/Kolkata",
    "iso:country":"IN",
    "ks:ks_name":"Pure Sanaulla",
    "ks:ks_pop":500,
    "ks:ks_type":"HABITATION",
    "ks:ks_uagg_main":0,
    "name:eng_x_preferred":[
        "Pure Sanaulla"
    ],
    "wof:name":"Pure Sanaulla",
    "wof:placetype":"neighbourhood",
    "wof:population":500
},
  "geometry": {"coordinates":[81.544552,26.203937],"type":"Point"}
}