{
  "type": "Feature",
  "properties": {
    "iso:country":"IN",
    "ks:ks_name":"Teji Ka Pura",
    "ks:ks_pop":915,
    "ks:ks_type":"HABITATION",
    "name:eng_x_preferred":[
        "Teji Ka Pura"
    ],
    "wof:name":"Teji Ka Pura",
    "wof:placetype":"locality",
    "wof:population":915
},
  "geometry": {"coordinates":[82.47075599999999,25.314995],"type":"Point"}
}