{
  "type": "Feature",
  "properties": {
    "iso:country":"IN",
    "ks:ks_alt_nam":"Chandu LT",
    "ks:ks_name":"Chandu Lt",
    "ks:ks_pop":383,
    "ks:ks_type":"HABITATION",
    "name:eng_x_preferred":[
        "Chandu Lt"
    ],
    "wof:name":"Chandu Lt",
    "wof:placetype":"locality",
    "wof:population":383
},
  "geometry": {"coordinates":[75.918685,17.042875],"type":"Point"}
}