{
  "type": "Feature",
  "properties": {
    "iso:country":"IN",
    "ks:ks_alt_nam":"VaLavankattalai",
    "ks:ks_name":"Valavankattalai",
    "ks:ks_pop":200,
    "ks:ks_type":"HABITATION",
    "name:eng_x_preferred":[
        "Valavankattalai"
    ],
    "wof:name":"Valavankattalai",
    "wof:placetype":"locality",
    "wof:population":200
},
  "geometry": {"coordinates":[79.760987,10.613636],"type":"Point"}
}