{
  "type": "Feature",
  "properties": {
    "iso:country":"IN",
    "ks:ks_name":"Khale Tola",
    "ks:ks_pop":145,
    "ks:ks_type":"HABITATION",
    "name:eng_x_preferred":[
        "Khale Tola"
    ],
    "wof:name":"Khale Tola",
    "wof:placetype":"locality",
    "wof:population":145
},
  "geometry": {"coordinates":[83.013733,23.943661],"type":"Point"}
}