{
  "type": "Feature",
  "properties": {
    "gn:admin1_code":"36",
    "gn:admin2_code":"140.0",
    "gn:asciiname":"Katehra Jafarabad",
    "gn:country_code":"IN",
    "gn:dem":214,
    "gn:feature_class":"P",
    "gn:feature_code":"PPL",
    "gn:name":"Katehra J\u0101far\u0101b\u0101d",
    "gn:population":0,
    "gn:timezone":"Asia/Kolkata",
    "iso:country":"IN",
    "ks:ks_alt_nam":"Katehra J\u0101far\u0101b\u0101d",
    "ks:ks_name":"Katehra Jafarabad",
    "ks:ks_type":"VILLAGE",
    "ks:ks_uagg_main":0,
    "name:eng_x_preferred":[
        "Katehra Jafarabad"
    ],
    "name:eng_x_variant":[
        "Katehra J\u0101far\u0101b\u0101d"
    ],
    "wof:name":"Katehra Jafarabad",
    "wof:placetype":"neighbourhood"
},
  "geometry": {"coordinates":[78.079115,28.706101],"type":"Point"}
}