{
  "type": "Feature",
  "properties": {
    "gn:admin1_code":"12.0",
    "gn:admin2_code":"9.0",
    "gn:asciiname":"Shajimarg",
    "gn:country_code":"IN",
    "gn:dem":1601,
    "gn:feature_class":"P",
    "gn:feature_code":"PPL",
    "gn:name":"Sh\u0101jimarg",
    "gn:population":0,
    "gn:timezone":"Asia/Kolkata",
    "iso:country":"IN",
    "name:eng_x_preferred":[
        "Sh\u0101jimarg"
    ],
    "wof:name":"Shajimarg",
    "wof:placetype":"locality"
},
  "geometry": {"coordinates":[74.55800000000001,34.43221],"type":"Point"}
}