{
  "type": "Feature",
  "properties": {
    "iso:country":"IN",
    "ks:ks_name":"Nadubettu",
    "ks:ks_pop":408,
    "ks:ks_type":"HABITATION",
    "name:eng_x_preferred":[
        "Nadubettu"
    ],
    "wof:name":"Nadubettu",
    "wof:placetype":"locality",
    "wof:population":408
},
  "geometry": {"coordinates":[75.006201,13.5357],"type":"Point"}
}