{
  "type": "Feature",
  "properties": {
    "iso:country":"IN",
    "ks:ks_name":"Balamunda",
    "ks:ks_pop":459,
    "ks:ks_type":"VILLAGE",
    "name:eng_x_preferred":[
        "Balamunda"
    ],
    "wof:name":"Balamunda",
    "wof:placetype":"locality",
    "wof:population":459
},
  "geometry": {"coordinates":[84.094025,18.927307],"type":"Point"}
}