{
  "type": "Feature",
  "properties": {
    "gn:admin1_code":"12.0",
    "gn:admin2_code":"12.0",
    "gn:asciiname":"Naunagar",
    "gn:country_code":"IN",
    "gn:dem":1636,
    "gn:feature_class":"P",
    "gn:feature_code":"PPL",
    "gn:name":"Naunagar",
    "gn:population":0,
    "gn:timezone":"Asia/Kolkata",
    "iso:country":"IN",
    "wof:name":"Naunagar",
    "wof:placetype":"locality"
},
  "geometry": {"coordinates":[74.96335999999999,33.84074],"type":"Point"}
}