{
  "type": "Feature",
  "properties": {
    "iso:country":"IN",
    "ks:ks_name":"Araha Musahari",
    "ks:ks_pop":315,
    "ks:ks_type":"HABITATION",
    "name:eng_x_preferred":[
        "Araha Musahari"
    ],
    "wof:name":"Araha Musahari",
    "wof:placetype":"locality",
    "wof:population":315
},
  "geometry": {"coordinates":[86.835599,25.92257],"type":"Point"}
}