{
  "type": "Feature",
  "properties": {
    "gn:admin1_code":"25.0",
    "gn:admin2_code":"610.0",
    "gn:asciiname":"Ichorabudoddi",
    "gn:country_code":"IN",
    "gn:dem":776,
    "gn:feature_class":"P",
    "gn:feature_code":"PPL",
    "gn:name":"Ichorabudoddi",
    "gn:population":0,
    "gn:timezone":"Asia/Kolkata",
    "iso:country":"IN",
    "wof:name":"Ichorabudoddi",
    "wof:placetype":"locality"
},
  "geometry": {"coordinates":[77.37461,11.776],"type":"Point"}
}