{
  "type": "Feature",
  "properties": {
    "iso:country":"IN",
    "ks:ks_name":"Papiowali",
    "ks:ks_pop":818,
    "ks:ks_type":"HABITATION",
    "name:eng_x_preferred":[
        "Papiowali"
    ],
    "wof:name":"Papiowali",
    "wof:placetype":"locality",
    "wof:population":818
},
  "geometry": {"coordinates":[78.88865300000001,28.886516],"type":"Point"}
}