{
  "type": "Feature",
  "properties": {
    "gn:admin1_code":"11",
    "gn:admin2_code":"23.0",
    "gn:asciiname":"Kherna",
    "gn:country_code":"IN",
    "gn:dem":1500,
    "gn:feature_class":"P",
    "gn:feature_code":"PPL",
    "gn:name":"Kherna",
    "gn:population":0,
    "gn:timezone":"Asia/Kolkata",
    "iso:country":"IN",
    "wof:name":"Kherna",
    "wof:placetype":"locality"
},
  "geometry": {"coordinates":[76.06308,32.83067],"type":"Point"}
}