{
  "type": "Feature",
  "properties": {
    "iso:country":"IN",
    "ks:ks_name":"Jitpura",
    "ks:ks_pop":203,
    "ks:ks_type":"HABITATION",
    "name:eng_x_preferred":[
        "Jitpura"
    ],
    "wof:name":"Jitpura",
    "wof:placetype":"locality",
    "wof:population":203
},
  "geometry": {"coordinates":[73.43429999999999,22.729533],"type":"Point"}
}