{
  "type": "Feature",
  "properties": {
    "iso:country":"IN",
    "ks:ks_alt_nam":"DHOBI LINE",
    "ks:ks_name":"Dhobi Line",
    "ks:ks_pop":1103,
    "ks:ks_type":"HABITATION",
    "ks:ks_uagg_main":0,
    "name:eng_x_preferred":[
        "Dhobi Line"
    ],
    "wof:name":"Dhobi Line",
    "wof:placetype":"neighbourhood",
    "wof:population":1103
},
  "geometry": {"coordinates":[89.758589,26.626962],"type":"Point"}
}