{
  "type": "Feature",
  "properties": {
    "gn:admin1_code":"36",
    "gn:admin2_code":"146.0",
    "gn:asciiname":"Mandi Mirzakhan",
    "gn:country_code":"IN",
    "gn:dem":182,
    "gn:feature_class":"P",
    "gn:feature_code":"PPL",
    "gn:name":"Mandi Mirz\u0101kh\u0101n",
    "gn:population":0,
    "gn:timezone":"Asia/Kolkata",
    "iso:country":"IN",
    "wof:name":"Mandi Mirzakhan",
    "wof:placetype":"locality"
},
  "geometry": {"coordinates":[77.62125999999998,27.06661],"type":"Point"}
}