{
  "type": "Feature",
  "properties": {
    "gn:admin1_code":"19.0",
    "gn:admin2_code":"583.0",
    "gn:asciiname":"Bokipur",
    "gn:country_code":"IN",
    "gn:dem":932,
    "gn:feature_class":"P",
    "gn:feature_code":"PPL",
    "gn:name":"Bokipur",
    "gn:population":0,
    "gn:timezone":"Asia/Kolkata",
    "iso:country":"IN",
    "wof:name":"Bokipur",
    "wof:placetype":"neighbourhood"
},
  "geometry": {"coordinates":[77.62739000000001,13.2944],"type":"Point"}
}