{
  "type": "Feature",
  "properties": {
    "gn:admin1_code":"35",
    "gn:admin2_code":"449.0",
    "gn:asciiname":"Kangighat",
    "gn:country_code":"IN",
    "gn:dem":520,
    "gn:feature_class":"P",
    "gn:feature_code":"PPL",
    "gn:name":"K\u0101ngigh\u0101t",
    "gn:population":0,
    "gn:timezone":"Asia/Kolkata",
    "iso:country":"IN",
    "ks:ks_name":"Kanji Ghat",
    "ks:ks_pop":85,
    "ks:ks_type":"VILLAGE",
    "name:eng_x_preferred":[
        "Kanji Ghat"
    ],
    "name:eng_x_variant":[
        "Kangighat"
    ],
    "wof:name":"Kanji Ghat",
    "wof:placetype":"locality",
    "wof:population":85
},
  "geometry": {"coordinates":[78.49214600000001,22.463694],"type":"Point"}
}