{
  "type": "Feature",
  "properties": {
    "iso:country":"IN",
    "ks:ks_name":"Uttareswar",
    "ks:ks_pop":935,
    "ks:ks_type":"VILLAGE",
    "name:eng_x_preferred":[
        "Uttareswar"
    ],
    "wof:name":"Uttareswar",
    "wof:placetype":"locality",
    "wof:population":935
},
  "geometry": {"coordinates":[85.45946499999999,20.15266],"type":"Point"}
}