{
  "type": "Feature",
  "properties": {
    "iso:country":"IN",
    "ks:ks_name":"Banspahari",
    "ks:ks_pop":170,
    "ks:ks_type":"VILLAGE",
    "name:eng_x_preferred":[
        "Banspahari"
    ],
    "wof:name":"Banspahari",
    "wof:placetype":"locality",
    "wof:population":170
},
  "geometry": {"coordinates":[87.121714,24.042163],"type":"Point"}
}