{
  "type": "Feature",
  "properties": {
    "iso:country":"IN",
    "ks:ks_name":"Dumri",
    "ks:ks_pop":0,
    "ks:ks_type":"VILLAGE",
    "name:eng_x_preferred":[
        "Dumri"
    ],
    "wof:name":"Dumri",
    "wof:placetype":"locality",
    "wof:population":0
},
  "geometry": {"coordinates":[85.322211,24.666004],"type":"Point"}
}