{
  "type": "Feature",
  "properties": {
    "iso:country":"IN",
    "ks:ks_name":"Lakhavath Gangu Thanda",
    "ks:ks_pop":191,
    "ks:ks_type":"HABITATION",
    "name:eng_x_preferred":[
        "Lakhavath Gangu Thanda"
    ],
    "wof:name":"Lakhavath Gangu Thanda",
    "wof:placetype":"locality",
    "wof:population":191
},
  "geometry": {"coordinates":[79.55992000000001,17.634318],"type":"Point"}
}