{
  "type": "Feature",
  "properties": {
    "gn:admin1_code":"18.0",
    "gn:admin2_code":"293",
    "gn:asciiname":"Digligiri",
    "gn:country_code":"IN",
    "gn:dem":95,
    "gn:feature_class":"P",
    "gn:feature_code":"PPL",
    "gn:name":"Digligiri",
    "gn:population":0,
    "gn:timezone":"Asia/Kolkata",
    "iso:country":"IN",
    "name:und_x_variant":[
        "Digli",
        "Digligiri"
    ],
    "wof:name":"Digligiri",
    "wof:placetype":"locality"
},
  "geometry": {"coordinates":[89.86324,25.4101],"type":"Point"}
}