{
  "type": "Feature",
  "properties": {
    "iso:country":"IN",
    "ks:ks_name":"Weavers Colony",
    "ks:ks_pop":915,
    "ks:ks_type":"HABITATION",
    "name:eng_x_preferred":[
        "Weavers Colony"
    ],
    "wof:name":"Weavers Colony",
    "wof:placetype":"locality",
    "wof:population":915
},
  "geometry": {"coordinates":[82.047786,16.634379],"type":"Point"}
}