{
  "type": "Feature",
  "properties": {
    "iso:country":"IN",
    "ks:ks_name":"Bedon Ka Bera",
    "ks:ks_pop":2355,
    "ks:ks_type":"HABITATION",
    "name:eng_x_preferred":[
        "Bedon Ka Bera"
    ],
    "wof:name":"Bedon Ka Bera",
    "wof:placetype":"locality",
    "wof:population":2355
},
  "geometry": {"coordinates":[72.82240299999999,26.942008],"type":"Point"}
}