{
  "type": "Feature",
  "properties": {
    "iso:country":"IN",
    "ks:ks_alt_nam":"SURYAWANSHI",
    "ks:ks_name":"Suryawanshi",
    "ks:ks_pop":28,
    "ks:ks_type":"HABITATION",
    "name:eng_x_preferred":[
        "Suryawanshi"
    ],
    "wof:name":"Suryawanshi",
    "wof:placetype":"locality",
    "wof:population":28
},
  "geometry": {"coordinates":[74.945284,17.063887],"type":"Point"}
}