{
  "type": "Feature",
  "properties": {
    "iso:country":"IN",
    "ks:ks_name":"Mundrupadi",
    "ks:ks_pop":544,
    "ks:ks_type":"HABITATION",
    "name:eng_x_preferred":[
        "Mundrupadi"
    ],
    "wof:name":"Mundrupadi",
    "wof:placetype":"locality",
    "wof:population":544
},
  "geometry": {"coordinates":[75.37952300000001,12.98671],"type":"Point"}
}