{
  "type": "Feature",
  "properties": {
    "iso:country":"IN",
    "ks:ks_alt_nam":"kavagaoundankottai",
    "ks:ks_name":"Kavagaoundankottai",
    "ks:ks_pop":245,
    "ks:ks_type":"HABITATION",
    "name:eng_x_preferred":[
        "Kavagaoundankottai"
    ],
    "wof:name":"Kavagaoundankottai",
    "wof:placetype":"locality",
    "wof:population":245
},
  "geometry": {"coordinates":[78.166405,12.467983],"type":"Point"}
}