{
  "type": "Feature",
  "properties": {
    "gn:admin1_code":"35",
    "gn:admin2_code":"458.0",
    "gn:asciiname":"Bhairauder",
    "gn:country_code":"IN",
    "gn:dem":482,
    "gn:feature_class":"P",
    "gn:feature_code":"PPL",
    "gn:name":"Bhairauder",
    "gn:population":0,
    "gn:timezone":"Asia/Kolkata",
    "iso:country":"IN",
    "wof:name":"Bhairauder",
    "wof:placetype":"locality"
},
  "geometry": {"coordinates":[77.24284,24.40086],"type":"Point"}
}