{
  "type": "Feature",
  "properties": {
    "gn:admin1_code":"16",
    "gn:admin2_code":"497.0",
    "gn:asciiname":"Mandara",
    "gn:country_code":"IN",
    "gn:dem":137,
    "gn:feature_class":"P",
    "gn:feature_code":"PPL",
    "gn:name":"Mand\u0101ra",
    "gn:population":0,
    "gn:timezone":"Asia/Kolkata",
    "iso:country":"IN",
    "name:bar_x_preferred":[
        "Mandara"
    ],
    "name:cat_x_preferred":[
        "Mandara"
    ],
    "name:deu_x_preferred":[
        "Mandara"
    ],
    "name:fra_x_preferred":[
        "Mandara"
    ],
    "name:ita_x_preferred":[
        "Mandara"
    ],
    "name:nld_x_preferred":[
        "Mandara"
    ],
    "name:rus_x_preferred":[
        "\u041c\u0430\u043d\u0434\u0430\u0440\u0430"
    ],
    "wof:name":"Mandara",
    "wof:placetype":"locality"
},
  "geometry": {"coordinates":[73.87659000000002,21.51604],"type":"Point"}
}