{
  "type": "Feature",
  "properties": {
    "gn:admin1_code":"16",
    "gn:admin2_code":"497.0",
    "gn:asciiname":"Mandara",
    "gn:country_code":"IN",
    "gn:dem":137,
    "gn:feature_class":"P",
    "gn:feature_code":"PPL",
    "gn:name":"Mand\u0101ra",
    "gn:population":0,
    "gn:timezone":"Asia/Kolkata",
    "iso:country":"IN",
    "wof:name":"Mandara",
    "wof:placetype":"locality"
},
  "geometry": {"coordinates":[73.87659000000002,21.51604],"type":"Point"}
}