{
  "type": "Feature",
  "properties": {
    "gn:admin1_code":"12.0",
    "gn:admin2_code":"008",
    "gn:asciiname":"Shogpur",
    "gn:country_code":"IN",
    "gn:dem":1600,
    "gn:feature_class":"P",
    "gn:feature_code":"PPL",
    "gn:name":"Shogpur",
    "gn:population":0,
    "gn:timezone":"Asia/Kolkata",
    "iso:country":"IN",
    "wof:name":"Shogpur",
    "wof:placetype":"locality"
},
  "geometry": {"coordinates":[74.37815999999999,34.27727],"type":"Point"}
}