{
  "type": "Feature",
  "properties": {
    "iso:country":"IN",
    "ks:ks_name":"Umrakot Urf Baidanu",
    "ks:ks_pop":385,
    "ks:ks_type":"VILLAGE",
    "name:eng_x_preferred":[
        "Umrakot Urf Baidanu"
    ],
    "wof:name":"Umrakot Urf Baidanu",
    "wof:placetype":"locality",
    "wof:population":385
},
  "geometry": {"coordinates":[79.294893,30.289737],"type":"Point"}
}