{
  "type": "Feature",
  "properties": {
    "iso:country":"IN",
    "ks:ks_name":"Pideli",
    "ks:ks_pop":149,
    "ks:ks_type":"VILLAGE",
    "name:eng_x_preferred":[
        "Pideli"
    ],
    "wof:name":"Pideli",
    "wof:placetype":"locality",
    "wof:population":149
},
  "geometry": {"coordinates":[83.671149,20.100056],"type":"Point"}
}