{
  "type": "Feature",
  "properties": {
    "gn:admin1_code":"38",
    "gn:admin2_code":"358.0",
    "gn:asciiname":"Naugarh",
    "gn:country_code":"IN",
    "gn:dem":159,
    "gn:feature_class":"P",
    "gn:feature_code":"PPL",
    "gn:name":"Naugarh",
    "gn:population":0,
    "gn:timezone":"Asia/Kolkata",
    "iso:country":"IN",
    "ks:ks_name":"Nawgarh",
    "ks:ks_pop":782,
    "ks:ks_type":"VILLAGE",
    "ks:ks_uagg_main":0,
    "name:eng_x_preferred":[
        "Nawgarh"
    ],
    "name:fas_x_preferred":[
        "\u0646\u0648\u06af\u0631\u0647"
    ],
    "name:hin_x_preferred":[
        "\u0928\u094c\u0917\u0922\u093c"
    ],
    "name:new_x_preferred":[
        "\u0928\u094c\u0917\u0922 \u0924\u0939\u0938\u0940\u0932"
    ],
    "name:urd_x_preferred":[
        "\u0646\u0648\u06af\u0691\u06be"
    ],
    "wof:name":"Nawgarh",
    "wof:placetype":"neighbourhood",
    "wof:population":782
},
  "geometry": {"coordinates":[83.841362,24.381061],"type":"Point"}
}