{
  "type": "Feature",
  "properties": {
    "iso:country":"IN",
    "ks:ks_name":"Nagbugar Urf Farkhet",
    "ks:ks_pop":673,
    "ks:ks_type":"VILLAGE",
    "name:eng_x_preferred":[
        "Nagbugar Urf Farkhet"
    ],
    "wof:name":"Nagbugar Urf Farkhet",
    "wof:placetype":"locality",
    "wof:population":673
},
  "geometry": {"coordinates":[79.44780900000001,30.263491],"type":"Point"}
}