{
  "type": "Feature",
  "properties": {
    "iso:country":"IN",
    "ks:ks_name":"Sannara",
    "ks:ks_pop":126,
    "ks:ks_type":"HABITATION",
    "name:eng_x_preferred":[
        "Sannara"
    ],
    "wof:name":"Sannara",
    "wof:placetype":"locality",
    "wof:population":126
},
  "geometry": {"coordinates":[75.56010999999999,12.712535],"type":"Point"}
}