{
  "type": "Feature",
  "properties": {
    "iso:country":"IN",
    "ks:ks_name":"Keranipur",
    "ks:ks_pop":29,
    "ks:ks_type":"VILLAGE",
    "name:eng_x_preferred":[
        "Keranipur"
    ],
    "wof:name":"Keranipur",
    "wof:placetype":"locality",
    "wof:population":29
},
  "geometry": {"coordinates":[86.984202,23.234201],"type":"Point"}
}