{
  "type": "Feature",
  "properties": {
    "iso:country":"IN",
    "ks:ks_alt_nam":"DONKA BASA",
    "ks:ks_name":"Donka Basa",
    "ks:ks_pop":58,
    "ks:ks_type":"HABITATION",
    "name:eng_x_preferred":[
        "Donka Basa"
    ],
    "wof:name":"Donka Basa",
    "wof:placetype":"locality",
    "wof:population":58
},
  "geometry": {"coordinates":[85.60828600000001,22.384885],"type":"Point"}
}