{
  "type": "Feature",
  "properties": {
    "iso:country":"IN",
    "ks:ks_name":"Hirna",
    "ks:ks_pop":224,
    "ks:ks_type":"HABITATION",
    "name:eng_x_preferred":[
        "Hirna"
    ],
    "wof:name":"Hirna",
    "wof:placetype":"locality",
    "wof:population":224
},
  "geometry": {"coordinates":[86.779737,24.722997],"type":"Point"}
}