{
  "type": "Feature",
  "properties": {
    "gn:admin1_code":"36.0",
    "gn:admin2_code":"136.0",
    "gn:asciiname":"Bhura",
    "gn:country_code":"IN",
    "gn:dem":211,
    "gn:feature_class":"P",
    "gn:feature_code":"PPL",
    "gn:name":"Bh\u016bra",
    "gn:population":0,
    "gn:timezone":"Asia/Kolkata",
    "iso:country":"IN",
    "name:und_x_variant":[
        "Bh\u016bra",
        "Husainganj"
    ],
    "wof:name":"Bhura",
    "wof:placetype":"locality"
},
  "geometry": {"coordinates":[79.19674999999999,28.99722],"type":"Point"}
}