{
  "type": "Feature",
  "properties": {
    "gn:admin1_code":"21",
    "gn:admin2_code":"394.0",
    "gn:asciiname":"Piparchheri",
    "gn:country_code":"IN",
    "gn:dem":306,
    "gn:feature_class":"P",
    "gn:feature_code":"PPL",
    "gn:name":"Piparchheri",
    "gn:population":0,
    "gn:timezone":"Asia/Kolkata",
    "iso:country":"IN",
    "wof:name":"Piparchheri",
    "wof:placetype":"neighbourhood"
},
  "geometry": {"coordinates":[82.68017999999999,20.80025],"type":"Point"}
}