{
  "type": "Feature",
  "properties": {
    "iso:country":"IN",
    "ks:ks_name":"Majgaon Kachari",
    "ks:ks_pop":159,
    "ks:ks_type":"HABITATION",
    "ks:ks_uagg_main":0,
    "name:eng_x_preferred":[
        "Majgaon Kachari"
    ],
    "wof:name":"Majgaon Kachari",
    "wof:placetype":"neighbourhood",
    "wof:population":159
},
  "geometry": {"coordinates":[94.905114,27.70232],"type":"Point"}
}