{
  "type": "Feature",
  "properties": {
    "iso:country":"IN",
    "ks:ks_name":"Kadupada",
    "ks:ks_pop":376,
    "ks:ks_type":"HABITATION",
    "name:eng_x_preferred":[
        "Kadupada"
    ],
    "wof:name":"Kadupada",
    "wof:placetype":"locality",
    "wof:population":376
},
  "geometry": {"coordinates":[72.792165,20.044221],"type":"Point"}
}