{
  "type": "Feature",
  "properties": {
    "iso:country":"IN",
    "ks:ks_name":"Maliguda",
    "ks:ks_pop":152,
    "ks:ks_type":"VILLAGE",
    "name:eng_x_preferred":[
        "Maliguda"
    ],
    "wof:name":"Maliguda",
    "wof:placetype":"locality",
    "wof:population":152
},
  "geometry": {"coordinates":[82.270443,18.114496],"type":"Point"}
}