{
  "type": "Feature",
  "properties": {
    "iso:country":"IN",
    "ks:ks_name":"Ngaya Pam2",
    "ks:ks_pop":1107,
    "ks:ks_type":"HABITATION",
    "name:eng_x_preferred":[
        "Ngaya Pam2"
    ],
    "wof:name":"Ngaya Pam2",
    "wof:placetype":"locality",
    "wof:population":1107
},
  "geometry": {"coordinates":[92.731222,26.133754],"type":"Point"}
}