{
  "type": "Feature",
  "properties": {
    "iso:country":"IN",
    "ks:ks_name":"Karimajalu",
    "ks:ks_pop":65,
    "ks:ks_type":"HABITATION",
    "name:eng_x_preferred":[
        "Karimajalu"
    ],
    "wof:name":"Karimajalu",
    "wof:placetype":"locality",
    "wof:population":65
},
  "geometry": {"coordinates":[74.96966399999999,13.364756],"type":"Point"}
}