{
  "type": "Feature",
  "properties": {
    "gn:admin1_code":"25.0",
    "gn:admin2_code":"612.0",
    "gn:asciiname":"Mallaiyakavundanpatti",
    "gn:country_code":"IN",
    "gn:dem":334,
    "gn:feature_class":"P",
    "gn:feature_code":"PPL",
    "gn:name":"Mallaiyakavundanpatti",
    "gn:population":0,
    "gn:timezone":"Asia/Kolkata",
    "iso:country":"IN",
    "wof:name":"Mallaiyakavundanpatti",
    "wof:placetype":"locality"
},
  "geometry": {"coordinates":[77.42164,10.49186],"type":"Point"}
}