{
  "type": "Feature",
  "properties": {
    "iso:country":"IN",
    "ks:ks_name":"Nagadopur",
    "ks:ks_pop":509,
    "ks:ks_type":"VILLAGE",
    "ks:ks_uagg_main":0,
    "name:eng_x_preferred":[
        "Nagadopur"
    ],
    "wof:name":"Nagadopur",
    "wof:placetype":"neighbourhood",
    "wof:population":509
},
  "geometry": {"coordinates":[83.444036,26.01916],"type":"Point"}
}