{
  "type": "Feature",
  "properties": {
    "gn:admin1_code":"37.0",
    "gn:admin2_code":"416.0",
    "gn:asciiname":"Gorgonda",
    "gn:country_code":"IN",
    "gn:dem":135,
    "gn:feature_class":"P",
    "gn:feature_code":"PPL",
    "gn:name":"Gorgonda",
    "gn:population":0,
    "gn:timezone":"Asia/Kolkata",
    "iso:country":"IN",
    "ks:ks_name":"Gorgunda",
    "ks:ks_pop":574,
    "ks:ks_type":"VILLAGE",
    "name:eng_x_preferred":[
        "Gorgunda"
    ],
    "name:eng_x_variant":[
        "Gorgonda"
    ],
    "wof:name":"Gorgunda",
    "wof:placetype":"locality",
    "wof:population":574
},
  "geometry": {"coordinates":[81.44349800000001,18.178184],"type":"Point"}
}