{
  "type": "Feature",
  "properties": {
    "gn:admin1_code":"23",
    "gn:admin2_code":"38.0",
    "gn:asciiname":"Begumpur Jandlala",
    "gn:country_code":"IN",
    "gn:dem":254,
    "gn:feature_class":"P",
    "gn:feature_code":"PPL",
    "gn:name":"Begumpur Jandlala",
    "gn:population":0,
    "gn:timezone":"Asia/Kolkata",
    "iso:country":"IN",
    "wof:name":"Begumpur Jandlala",
    "wof:placetype":"neighbourhood"
},
  "geometry": {"coordinates":[75.71915,31.57046],"type":"Point"}
}