{
  "type": "Feature",
  "properties": {
    "iso:country":"IN",
    "ks:ks_name":"Panchkuta Ki Dhani",
    "ks:ks_pop":286,
    "ks:ks_type":"VILLAGE",
    "name:eng_x_preferred":[
        "Panchkuta Ki Dhani"
    ],
    "wof:name":"Panchkuta Ki Dhani",
    "wof:placetype":"locality",
    "wof:population":286
},
  "geometry": {"coordinates":[74.11677299999999,26.805617],"type":"Point"}
}