{
  "type": "Feature",
  "properties": {
    "iso:country":"IN",
    "ks:ks_name":"Khairatidand",
    "ks:ks_pop":11,
    "ks:ks_type":"HABITATION",
    "name:eng_x_preferred":[
        "Khairatidand"
    ],
    "wof:name":"Khairatidand",
    "wof:placetype":"locality",
    "wof:population":11
},
  "geometry": {"coordinates":[82.615008,23.228645],"type":"Point"}
}