{
  "type": "Feature",
  "properties": {
    "gn:admin1_code":"10.0",
    "gn:admin2_code":"76.0",
    "gn:asciiname":"Korar Ibrahimpur",
    "gn:country_code":"IN",
    "gn:dem":220,
    "gn:feature_class":"P",
    "gn:feature_code":"PPL",
    "gn:name":"Kor\u0101r Ibrahimpur",
    "gn:population":0,
    "gn:timezone":"Asia/Kolkata",
    "iso:country":"IN",
    "wof:name":"Korar Ibrahimpur",
    "wof:placetype":"locality"
},
  "geometry": {"coordinates":[77.05956,29.05297],"type":"Point"}
}