{
  "type": "Feature",
  "properties": {
    "iso:country":"IN",
    "ks:ks_name":"Pandepurwa",
    "ks:ks_pop":329,
    "ks:ks_type":"HABITATION",
    "ks:ks_uagg_main":0,
    "name:eng_x_preferred":[
        "Pandepurwa"
    ],
    "wof:name":"Pandepurwa",
    "wof:placetype":"neighbourhood",
    "wof:population":329
},
  "geometry": {"coordinates":[81.989673,27.079707],"type":"Point"}
}