{
  "type": "Feature",
  "properties": {
    "gn:admin1_code":"24.0",
    "gn:admin2_code":"121",
    "gn:asciiname":"Bahadurpura",
    "gn:country_code":"IN",
    "gn:dem":257,
    "gn:feature_class":"P",
    "gn:feature_code":"PPL",
    "gn:name":"Bah\u0101durpura",
    "gn:population":0,
    "gn:timezone":"Asia/Kolkata",
    "iso:country":"IN",
    "name:fas_x_preferred":[
        "\u067e\u0647\u0627\u062f\u0631\u067e\u0648\u0631\u0647"
    ],
    "name:urd_x_preferred":[
        "\u0628\u06c1\u0627\u062f\u0631 \u067e\u0648\u0631\u06c1"
    ],
    "wof:name":"Bahadurpura",
    "wof:placetype":"locality"
},
  "geometry": {"coordinates":[75.67789999999999,25.42985],"type":"Point"}
}