{
  "type": "Feature",
  "properties": {
    "iso:country":"IN",
    "ks:ks_name":"Nanidhodi Falia",
    "ks:ks_pop":323,
    "ks:ks_type":"HABITATION",
    "name:eng_x_preferred":[
        "Nanidhodi Falia"
    ],
    "wof:name":"Nanidhodi Falia",
    "wof:placetype":"locality",
    "wof:population":323
},
  "geometry": {"coordinates":[73.283861,20.311222],"type":"Point"}
}