{
  "type": "Feature",
  "properties": {
    "gn:admin1_code":"36",
    "gn:admin2_code":"200.0",
    "gn:asciiname":"Lahas",
    "gn:country_code":"IN",
    "gn:dem":305,
    "gn:feature_class":"P",
    "gn:feature_code":"PPL",
    "gn:name":"Lahas",
    "gn:population":0,
    "gn:timezone":"Asia/Kolkata",
    "iso:country":"IN",
    "name:arg_x_preferred":[
        "Lah\u00e0s"
    ],
    "name:bug_x_preferred":[
        "Lahas"
    ],
    "name:cat_x_preferred":[
        "Lah\u00e0s"
    ],
    "name:ceb_x_preferred":[
        "Lahas"
    ],
    "name:eus_x_preferred":[
        "Lahas"
    ],
    "name:fra_x_preferred":[
        "Lahas"
    ],
    "name:hun_x_preferred":[
        "Lahas"
    ],
    "name:ind_x_preferred":[
        "Lahas"
    ],
    "name:ita_x_preferred":[
        "Lahas"
    ],
    "name:lat_x_preferred":[
        "Lahas"
    ],
    "name:mlg_x_preferred":[
        "Lahas"
    ],
    "name:msa_x_preferred":[
        "Lahas"
    ],
    "name:nld_x_preferred":[
        "Lahas"
    ],
    "name:oci_x_preferred":[
        "Lah\u00e0s"
    ],
    "name:pms_x_preferred":[
        "Lahas"
    ],
    "name:pol_x_preferred":[
        "Lahas"
    ],
    "name:por_x_preferred":[
        "Lahas"
    ],
    "name:ron_x_preferred":[
        "Lahas"
    ],
    "name:rus_x_preferred":[
        "\u041b\u0430\u0430\u0441"
    ],
    "name:slk_x_preferred":[
        "Lahas"
    ],
    "name:spa_x_preferred":[
        "Lahas"
    ],
    "name:swe_x_preferred":[
        "Lahas"
    ],
    "name:ukr_x_preferred":[
        "\u041b\u0430\u0430\u0441"
    ],
    "name:vie_x_preferred":[
        "Lahas"
    ],
    "name:vol_x_preferred":[
        "Lahas"
    ],
    "name:war_x_preferred":[
        "Lahas"
    ],
    "name:zho_x_preferred":[
        "\u62c9\u963f"
    ],
    "wof:name":"Lahas",
    "wof:placetype":"locality"
},
  "geometry": {"coordinates":[82.6619,24.74658],"type":"Point"}
}