{
  "type": "Feature",
  "properties": {
    "iso:country":"IN",
    "ks:ks_alt_nam":"JAGTAP WASTI",
    "ks:ks_name":"Jagtap Wasti",
    "ks:ks_pop":77,
    "ks:ks_type":"HABITATION",
    "name:eng_x_preferred":[
        "Jagtap Wasti"
    ],
    "wof:name":"Jagtap Wasti",
    "wof:placetype":"locality",
    "wof:population":77
},
  "geometry": {"coordinates":[74.858649,16.948048],"type":"Point"}
}