{
  "type": "Feature",
  "properties": {
    "gn:admin1_code":"16",
    "gn:admin2_code":"503.0",
    "gn:asciiname":"Aliabad",
    "gn:country_code":"IN",
    "gn:dem":381,
    "gn:feature_class":"P",
    "gn:feature_code":"PPL",
    "gn:name":"Ali\u0101b\u0101d",
    "gn:population":0,
    "gn:timezone":"Asia/Kolkata",
    "iso:country":"IN",
    "ks:ks_alt_nam":"Ali\u0101b\u0101d",
    "ks:ks_name":"Aliabad",
    "ks:ks_type":"VILLAGE",
    "name:ara_x_preferred":[
        "\u0639\u0644\u064a \u0622\u0628\u0627\u062f"
    ],
    "name:azb_x_preferred":[
        "\u0639\u0644\u06cc\u200c\u0622\u0628\u0627\u062f"
    ],
    "name:aze_x_preferred":[
        "\u018fliabad"
    ],
    "name:ben_bn_x_preferred":[
        "\u0986\u09b2\u09bf\u09df\u09be\u09ac\u09be\u09a6"
    ],
    "name:ben_in_x_preferred":[
        "\u0986\u09b2\u09bf\u09df\u09be\u09ac\u09be\u09a6"
    ],
    "name:eng_x_preferred":[
        "Aliabad"
    ],
    "name:eng_x_variant":[
        "Ali\u0101b\u0101d"
    ],
    "name:fas_x_preferred":[
        "\u0639\u0644\u06cc\u200c\u0622\u0628\u0627\u062f"
    ],
    "name:guj_x_preferred":[
        "\u0a85\u0ab2\u0ac0\u0aac\u0abe\u0aa6"
    ],
    "name:hin_x_preferred":[
        "\u0906\u0932\u093f\u092f\u093e\u092c\u093e\u0926"
    ],
    "name:ita_x_preferred":[
        "Aliabad"
    ],
    "name:kan_x_preferred":[
        "\u0c85\u0cb2\u0cbf\u0caf\u0cbe\u0cac\u0cbe\u0ca6\u0ccd"
    ],
    "name:kat_x_preferred":[
        "\u10d0\u10da\u10d8\u10d0\u10d1\u10d0\u10d3\u10d8"
    ],
    "name:mal_x_preferred":[
        "\u0d06\u0d32\u0d3f\u0d2f\u0d2c\u0d3e\u0d26\u0d4d"
    ],
    "name:mar_x_preferred":[
        "\u0905\u0932\u093f\u092f\u093e\u092c\u093e\u0926"
    ],
    "name:mzn_x_preferred":[
        "\u0639\u0644\u06cc\u200c\u0622\u0628\u0627\u062f"
    ],
    "name:nld_x_preferred":[
        "Aliabad"
    ],
    "name:pan_x_preferred":[
        "\u0a05\u0a32\u0a40\u0a06\u0a2c\u0a3e\u0a26"
    ],
    "name:pol_x_preferred":[
        "Aliabad"
    ],
    "name:tam_x_preferred":[
        "\u0b85\u0bb2\u0bbf\u0baf\u0bbe\u0baa\u0bbe\u0ba4\u0bcd"
    ],
    "name:tel_x_preferred":[
        "\u0c05\u0c32\u0c3f\u0c2f\u0c3e\u0c2c\u0c3e\u0c26\u0c4d"
    ],
    "name:tur_x_preferred":[
        "Aliabad"
    ],
    "name:urd_x_preferred":[
        "\u0639\u0644\u06cc \u0622\u0628\u0627\u062f"
    ],
    "wof:name":"Aliabad",
    "wof:placetype":"locality"
},
  "geometry": {"coordinates":[77.762845,20.859326],"type":"Point"}
}