{
  "type": "Feature",
  "properties": {
    "iso:country":"IN",
    "ks:ks_name":"Dimirimunda",
    "ks:ks_pop":195,
    "ks:ks_type":"HABITATION",
    "name:eng_x_preferred":[
        "Dimirimunda"
    ],
    "wof:name":"Dimirimunda",
    "wof:placetype":"locality",
    "wof:population":195
},
  "geometry": {"coordinates":[84.317954,21.491561],"type":"Point"}
}