{
  "type": "Feature",
  "properties": {
    "gn:admin1_code":"36.0",
    "gn:admin2_code":"173.0",
    "gn:asciiname":"Bechuram Tiwari ka Purwa",
    "gn:country_code":"IN",
    "gn:dem":110,
    "gn:feature_class":"P",
    "gn:feature_code":"PPL",
    "gn:name":"Bechur\u0101m Tiw\u0101ri ka Purwa",
    "gn:population":0,
    "gn:timezone":"Asia/Kolkata",
    "iso:country":"IN",
    "wof:name":"Bechuram Tiwari ka Purwa",
    "wof:placetype":"locality"
},
  "geometry": {"coordinates":[81.47469,25.84066],"type":"Point"}
}