{
  "type": "Feature",
  "properties": {
    "iso:country":"IN",
    "ks:ks_name":"Aror",
    "ks:ks_pop":1157,
    "ks:ks_type":"HABITATION",
    "name:eng_x_preferred":[
        "Aror"
    ],
    "wof:name":"Aror",
    "wof:placetype":"locality",
    "wof:population":1157
},
  "geometry": {"coordinates":[74.240161,23.561222],"type":"Point"}
}