{
  "type": "Feature",
  "properties": {
    "iso:country":"IN",
    "ks:ks_name":"Katbawadia",
    "ks:ks_pop":324,
    "ks:ks_type":"VILLAGE",
    "name:eng_x_preferred":[
        "Katbawadia"
    ],
    "wof:name":"Katbawadia",
    "wof:placetype":"locality",
    "wof:population":324
},
  "geometry": {"coordinates":[76.653263,22.2158],"type":"Point"}
}