{
  "type": "Feature",
  "properties": {
    "gn:admin1_code":"35",
    "gn:admin2_code":"424.0",
    "gn:asciiname":"Dhimarpur",
    "gn:country_code":"IN",
    "gn:dem":216,
    "gn:feature_class":"P",
    "gn:feature_code":"PPL",
    "gn:name":"Dh\u012bmarpur",
    "gn:population":0,
    "gn:timezone":"Asia/Kolkata",
    "iso:country":"IN",
    "wof:name":"Dhimarpur",
    "wof:placetype":"locality"
},
  "geometry": {"coordinates":[78.64513000000002,25.38867],"type":"Point"}
}