{
  "type": "Feature",
  "properties": {
    "iso:country":"IN",
    "ks:ks_name":"Musegar",
    "ks:ks_pop":20,
    "ks:ks_type":"HABITATION",
    "name:eng_x_preferred":[
        "Musegar"
    ],
    "wof:name":"Musegar",
    "wof:placetype":"locality",
    "wof:population":20
},
  "geometry": {"coordinates":[74.777411,14.324184],"type":"Point"}
}