{
  "type": "Feature",
  "properties": {
    "iso:country":"IN",
    "ks:ks_name":"Buggadda",
    "ks:ks_pop":11,
    "ks:ks_type":"HABITATION",
    "name:eng_x_preferred":[
        "Buggadda"
    ],
    "wof:name":"Buggadda",
    "wof:placetype":"locality",
    "wof:population":11
},
  "geometry": {"coordinates":[78.226221,13.605431],"type":"Point"}
}