{
  "type": "Feature",
  "properties": {
    "iso:country":"IN",
    "ks:ks_name":"Karkawaya",
    "ks:ks_pop":229,
    "ks:ks_type":"HABITATION",
    "name:eng_x_preferred":[
        "Karkawaya"
    ],
    "wof:name":"Karkawaya",
    "wof:placetype":"locality",
    "wof:population":229
},
  "geometry": {"coordinates":[80.54697899999999,19.374233],"type":"Point"}
}