{
  "type": "Feature",
  "properties": {
    "gn:admin1_code":"36.0",
    "gn:admin2_code":"134.0",
    "gn:asciiname":"Kamrajpur",
    "gn:country_code":"IN",
    "gn:dem":257,
    "gn:feature_class":"P",
    "gn:feature_code":"PPL",
    "gn:name":"K\u0101mr\u0101jpur",
    "gn:population":0,
    "gn:timezone":"Asia/Kolkata",
    "iso:country":"IN",
    "wof:name":"Kamrajpur",
    "wof:placetype":"locality"
},
  "geometry": {"coordinates":[78.16338,29.60701],"type":"Point"}
}