{
  "type": "Feature",
  "properties": {
    "iso:country":"IN",
    "ks:ks_name":"Garhper",
    "ks:ks_pop":495,
    "ks:ks_type":"HABITATION",
    "name:eng_x_preferred":[
        "Garhper"
    ],
    "wof:name":"Garhper",
    "wof:placetype":"locality",
    "wof:population":495
},
  "geometry": {"coordinates":[84.682337,24.509856],"type":"Point"}
}