{
  "type": "Feature",
  "properties": {
    "iso:country":"IN",
    "ks:ks_alt_nam":"N  NIVAS",
    "ks:ks_name":"N Nivas",
    "ks:ks_pop":144,
    "ks:ks_type":"HABITATION",
    "ks:ks_uagg_main":0,
    "name:eng_x_preferred":[
        "N Nivas"
    ],
    "name:eng_x_variant":[
        "N  NIVAS"
    ],
    "wof:name":"N Nivas",
    "wof:placetype":"neighbourhood",
    "wof:population":144
},
  "geometry": {"coordinates":[78.931415,27.640953],"type":"Point"}
}