{
  "type": "Feature",
  "properties": {
    "iso:country":"IN",
    "ks:ks_name":"Baggguvanipeta",
    "ks:ks_pop":675,
    "ks:ks_type":"HABITATION",
    "ks:ks_uagg_main":0,
    "name:eng_x_preferred":[
        "Baggguvanipeta"
    ],
    "wof:name":"Baggguvanipeta",
    "wof:placetype":"neighbourhood",
    "wof:population":675
},
  "geometry": {"coordinates":[83.96991,18.337963],"type":"Point"}
}