{
  "type": "Feature",
  "properties": {
    "iso:country":"IN",
    "ks:ks_name":"Rampatan",
    "ks:ks_pop":27,
    "ks:ks_type":"HABITATION",
    "name:eng_x_preferred":[
        "Rampatan"
    ],
    "wof:name":"Rampatan",
    "wof:placetype":"locality",
    "wof:population":27
},
  "geometry": {"coordinates":[78.770807,23.543201],"type":"Point"}
}