{
  "type": "Feature",
  "properties": {
    "iso:country":"IN",
    "ks:ks_name":"Jamdarwasti",
    "ks:ks_pop":190,
    "ks:ks_type":"HABITATION",
    "name:eng_x_preferred":[
        "Jamdarwasti"
    ],
    "wof:name":"Jamdarwasti",
    "wof:placetype":"locality",
    "wof:population":190
},
  "geometry": {"coordinates":[74.504893,18.637482],"type":"Point"}
}