{
  "type": "Feature",
  "properties": {
    "iso:country":"IN",
    "ks:ks_name":"Harhu",
    "ks:ks_pop":412,
    "ks:ks_type":"VILLAGE",
    "name:eng_x_preferred":[
        "Harhu"
    ],
    "wof:name":"Harhu",
    "wof:placetype":"locality",
    "wof:population":412
},
  "geometry": {"coordinates":[84.96412100000001,23.601389],"type":"Point"}
}