{
  "type": "Feature",
  "properties": {
    "iso:country":"IN",
    "ks:ks_name":"Bhatkarkond",
    "ks:ks_pop":109,
    "ks:ks_type":"HABITATION",
    "name:eng_x_preferred":[
        "Bhatkarkond"
    ],
    "wof:name":"Bhatkarkond",
    "wof:placetype":"locality",
    "wof:population":109
},
  "geometry": {"coordinates":[73.391381,16.947503],"type":"Point"}
}