{
  "type": "Feature",
  "properties": {
    "gn:admin1_code":"40.0",
    "gn:admin2_code":"533.0",
    "gn:asciiname":"Singojiwada",
    "gn:country_code":"IN",
    "gn:dem":562,
    "gn:feature_class":"P",
    "gn:feature_code":"PPL",
    "gn:name":"Singojiw\u0101d\u0101",
    "gn:population":0,
    "gn:timezone":"Asia/Kolkata",
    "iso:country":"IN",
    "wof:name":"Singojiwada",
    "wof:placetype":"locality"
},
  "geometry": {"coordinates":[78.24786,18.35508],"type":"Point"}
}