{
  "type": "Feature",
  "properties": {
    "iso:country":"IN",
    "ks:ks_name":"Naraharipursasan",
    "ks:ks_pop":421,
    "ks:ks_type":"VILLAGE",
    "name:eng_x_preferred":[
        "Naraharipursasan"
    ],
    "wof:name":"Naraharipursasan",
    "wof:placetype":"locality",
    "wof:population":421
},
  "geometry": {"coordinates":[85.19110000000001,19.788881],"type":"Point"}
}