{
  "type": "Feature",
  "properties": {
    "iso:country":"IN",
    "ks:ks_name":"Suri Tola",
    "ks:ks_pop":672,
    "ks:ks_type":"HABITATION",
    "ks:ks_uagg_main":0,
    "name:eng_x_preferred":[
        "Suri Tola"
    ],
    "wof:name":"Suri Tola",
    "wof:placetype":"neighbourhood",
    "wof:population":672
},
  "geometry": {"coordinates":[86.790927,26.139665],"type":"Point"}
}