{
  "type": "Feature",
  "properties": {
    "iso:country":"IN",
    "qs:name":"Bhokara",
    "qs:name_adm0":"India",
    "qs:name_adm1":"Maharashtra",
    "qs:photos":6,
    "qs:photos_1k":1,
    "qs:photos_9k":1,
    "qs:photos_9r":1,
    "qs:photos_all":6,
    "qs:photos_sr":1,
    "qs:placetype":"Town",
    "qs:pop_sr":"0",
    "wof:name":"Bhokara",
    "wof:placetype":"neighbourhood"
},
  "geometry": {"coordinates":[79.062331,21.182265],"type":"Point"}
}