{
  "type": "Feature",
  "properties": {
    "gn:admin1_code":"13.0",
    "gn:admin2_code":"601.0",
    "gn:asciiname":"Karipartala",
    "gn:country_code":"IN",
    "gn:dem":44,
    "gn:feature_class":"P",
    "gn:feature_code":"PPL",
    "gn:name":"Karipartala",
    "gn:population":0,
    "gn:timezone":"Asia/Kolkata",
    "iso:country":"IN",
    "wof:name":"Karipartala",
    "wof:placetype":"locality"
},
  "geometry": {"coordinates":[76.92239000000002,8.55582],"type":"Point"}
}