{
  "type": "Feature",
  "properties": {
    "gn:admin1_code":"35.0",
    "gn:admin2_code":"452.0",
    "gn:asciiname":"Marko",
    "gn:country_code":"IN",
    "gn:dem":364,
    "gn:feature_class":"P",
    "gn:feature_code":"PPL",
    "gn:name":"M\u0101rko",
    "gn:population":0,
    "gn:timezone":"Asia/Kolkata",
    "iso:country":"IN",
    "name:aze_x_preferred":[
        "Marko"
    ],
    "name:ceb_x_preferred":[
        "Marko"
    ],
    "name:deu_x_preferred":[
        "Marko"
    ],
    "name:ell_x_preferred":[
        "\u039c\u03ac\u03c1\u03ba\u03bf"
    ],
    "name:epo_x_preferred":[
        "Marko"
    ],
    "name:eus_x_preferred":[
        "Marko"
    ],
    "name:fra_x_preferred":[
        "Marko"
    ],
    "name:ita_x_preferred":[
        "Marko"
    ],
    "name:por_x_preferred":[
        "Marko"
    ],
    "name:rus_x_preferred":[
        "\u041c\u0430\u0440\u043a\u043e"
    ],
    "name:slk_x_preferred":[
        "Marko"
    ],
    "name:slv_x_preferred":[
        "Marko"
    ],
    "name:ukr_x_preferred":[
        "\u041c\u0430\u0440\u043a\u043e"
    ],
    "wof:name":"Marko",
    "wof:placetype":"locality"
},
  "geometry": {"coordinates":[78.90555999999999,22.93456],"type":"Point"}
}