{
  "type": "Feature",
  "properties": {
    "gn:admin1_code":"2.0",
    "gn:admin2_code":"549.0",
    "gn:asciiname":"Garladinne",
    "gn:country_code":"IN",
    "gn:dem":157,
    "gn:feature_class":"P",
    "gn:feature_code":"PPL",
    "gn:name":"G\u0101rladinne",
    "gn:population":0,
    "gn:timezone":"Asia/Kolkata",
    "iso:country":"IN",
    "name:ceb_x_preferred":[
        "G\u0101rladinne"
    ],
    "name:new_x_preferred":[
        "\u0917\u093e\u0930\u094d\u0932\u0926\u093f\u0928\u094d\u0928\u0947 \u092e\u0923\u094d\u0921\u0932"
    ],
    "name:swe_x_preferred":[
        "G\u0101rladinne"
    ],
    "name:tam_x_preferred":[
        "\u0b95\u0bbe\u0bb0\u0bcd\u0bb2\u0ba4\u0bbf\u0ba9\u0bcd\u0ba9\u0bc7"
    ],
    "name:tel_x_preferred":[
        "\u0c17\u0c3e\u0c30\u0c4d\u0c32\u0c26\u0c3f\u0c28\u0c4d\u0c28\u0c46"
    ],
    "name:tgl_x_preferred":[
        "Garladinne"
    ],
    "name:urd_x_preferred":[
        "\u06af\u0627\u0631\u0644\u0627\u062f\u06cc\u0646\u06d2"
    ],
    "wof:name":"Garladinne",
    "wof:placetype":"locality"
},
  "geometry": {"coordinates":[79.38108000000003,15.65202],"type":"Point"}
}