{
  "type": "Feature",
  "properties": {
    "gn:admin1_code":"34.0",
    "gn:admin2_code":"221.0",
    "gn:asciiname":"Larjha",
    "gn:country_code":"IN",
    "gn:dem":46,
    "gn:feature_class":"P",
    "gn:feature_code":"PPL",
    "gn:name":"Larjha",
    "gn:population":0,
    "gn:timezone":"Asia/Kolkata",
    "iso:country":"IN",
    "wof:name":"Larjha",
    "wof:placetype":"locality"
},
  "geometry": {"coordinates":[86.27087,25.74062],"type":"Point"}
}