{
  "type": "Feature",
  "properties": {
    "iso:country":"IN",
    "ks:ks_name":"Katgharwa",
    "ks:ks_pop":192,
    "ks:ks_type":"HABITATION",
    "name:eng_x_preferred":[
        "Katgharwa"
    ],
    "wof:name":"Katgharwa",
    "wof:placetype":"locality",
    "wof:population":192
},
  "geometry": {"coordinates":[82.901552,27.028778],"type":"Point"}
}