{
  "type": "Feature",
  "properties": {
    "gn:admin1_code":"35",
    "gn:admin2_code":"455.0",
    "gn:asciiname":"Ataria",
    "gn:country_code":"IN",
    "gn:dem":771,
    "gn:feature_class":"P",
    "gn:feature_code":"PPL",
    "gn:name":"Ataria",
    "gn:population":0,
    "gn:timezone":"Asia/Kolkata",
    "iso:country":"IN",
    "name:eus_x_preferred":[
        "Ataria"
    ],
    "name:spa_x_preferred":[
        "Ataria"
    ],
    "wof:name":"Ataria",
    "wof:placetype":"locality"
},
  "geometry": {"coordinates":[78.8813,22.49741],"type":"Point"}
}