{
  "type": "Feature",
  "properties": {
    "gn:admin1_code":"11",
    "gn:admin2_code":"24.0",
    "gn:asciiname":"Bharehr Uparli",
    "gn:country_code":"IN",
    "gn:dem":1854,
    "gn:feature_class":"P",
    "gn:feature_code":"PPL",
    "gn:name":"Bharehr Uparli",
    "gn:population":0,
    "gn:timezone":"Asia/Kolkata",
    "iso:country":"IN",
    "wof:name":"Bharehr Uparli",
    "wof:placetype":"locality"
},
  "geometry": {"coordinates":[76.68318000000002,32.10981],"type":"Point"}
}