{
  "type": "Feature",
  "properties": {
    "gn:admin1_code":"16.0",
    "gn:admin2_code":"499.0",
    "gn:asciiname":"Pasardi",
    "gn:country_code":"IN",
    "gn:dem":285,
    "gn:feature_class":"P",
    "gn:feature_code":"PPL",
    "gn:name":"P\u0101sardi",
    "gn:population":0,
    "gn:timezone":"Asia/Kolkata",
    "iso:country":"IN",
    "ks:ks_alt_nam":"P\u0101sardi",
    "ks:ks_name":"Pasardi",
    "ks:ks_pop":1361,
    "ks:ks_type":"VILLAGE",
    "ks:ks_uagg_main":0,
    "name:eng_x_preferred":[
        "Pasardi"
    ],
    "name:eng_x_variant":[
        "P\u0101sardi"
    ],
    "wof:name":"Pasardi",
    "wof:placetype":"neighbourhood",
    "wof:population":1361
},
  "geometry": {"coordinates":[75.170716,20.582313],"type":"Point"}
}