{
  "type": "Feature",
  "properties": {
    "iso:country":"IN",
    "ks:ks_name":"Baberi",
    "ks:ks_pop":160,
    "ks:ks_type":"VILLAGE",
    "name:eng_x_preferred":[
        "Baberi"
    ],
    "wof:name":"Baberi",
    "wof:placetype":"locality",
    "wof:population":160
},
  "geometry": {"coordinates":[83.65750800000001,19.469765],"type":"Point"}
}