{
  "type": "Feature",
  "properties": {
    "iso:country":"IN",
    "ks:ks_alt_nam":"Dhani khera",
    "ks:ks_name":"Dhani Khera",
    "ks:ks_pop":422,
    "ks:ks_type":"HABITATION",
    "name:eng_x_preferred":[
        "Dhani Khera"
    ],
    "wof:name":"Dhani Khera",
    "wof:placetype":"locality",
    "wof:population":422
},
  "geometry": {"coordinates":[80.29328099999999,26.973194],"type":"Point"}
}