{
  "type": "Feature",
  "properties": {
    "iso:country":"IN",
    "ks:ks_alt_nam":"Chamakkad-Amala Rd Junc",
    "ks:ks_name":"Chamakkad-amala Rd Junc",
    "ks:ks_pop":589,
    "ks:ks_type":"HABITATION",
    "name:eng_x_preferred":[
        "Chamakkad-amala Rd Junc"
    ],
    "wof:name":"Chamakkad-amala Rd Junc",
    "wof:placetype":"locality",
    "wof:population":589
},
  "geometry": {"coordinates":[76.18508,10.563158],"type":"Point"}
}