{
  "type": "Feature",
  "properties": {
    "gn:admin1_code":"21.0",
    "gn:admin2_code":"384.0",
    "gn:asciiname":"Talamaliha",
    "gn:country_code":"IN",
    "gn:dem":187,
    "gn:feature_class":"P",
    "gn:feature_code":"PPL",
    "gn:name":"Talamaliha",
    "gn:population":0,
    "gn:timezone":"Asia/Kolkata",
    "iso:country":"IN",
    "wof:name":"Talamaliha",
    "wof:placetype":"locality"
},
  "geometry": {"coordinates":[84.57200999999998,20.84403],"type":"Point"}
}