{
  "type": "Feature",
  "properties": {
    "gn:admin1_code":"24.0",
    "gn:admin2_code":"129.0",
    "gn:asciiname":"Deoli",
    "gn:country_code":"IN",
    "gn:dem":346,
    "gn:feature_class":"P",
    "gn:feature_code":"PPL",
    "gn:name":"Deoli",
    "gn:population":0,
    "gn:timezone":"Asia/Kolkata",
    "iso:country":"IN",
    "name:ben_x_preferred":[
        "\u09a6\u09c7\u0993\u09b2\u09bf"
    ],
    "name:bih_x_preferred":[
        "\u0926\u0947\u0935\u0932\u0940"
    ],
    "name:ceb_x_preferred":[
        "Deoli"
    ],
    "name:nld_x_preferred":[
        "Deoli"
    ],
    "name:swe_x_preferred":[
        "Deoli"
    ],
    "wof:name":"Deoli",
    "wof:placetype":"locality"
},
  "geometry": {"coordinates":[76.34506,24.38108],"type":"Point"}
}