{
  "type": "Feature",
  "properties": {
    "gn:admin1_code":"36.0",
    "gn:admin2_code":"135.0",
    "gn:asciiname":"Bhartara",
    "gn:country_code":"IN",
    "gn:dem":191,
    "gn:feature_class":"P",
    "gn:feature_code":"PPL",
    "gn:name":"Bhartara",
    "gn:population":0,
    "gn:timezone":"Asia/Kolkata",
    "iso:country":"IN",
    "ks:ks_name":"Bhartra",
    "ks:ks_pop":1258,
    "ks:ks_type":"VILLAGE",
    "name:eng_x_preferred":[
        "Bhartra"
    ],
    "name:eng_x_variant":[
        "Bhartara"
    ],
    "wof:name":"Bhartra",
    "wof:placetype":"locality",
    "wof:population":1258
},
  "geometry": {"coordinates":[78.678804,28.426576],"type":"Point"}
}