{
  "type": "Feature",
  "properties": {
    "iso:country":"IN",
    "ks:ks_name":"Binuda",
    "ks:ks_pop":93,
    "ks:ks_type":"VILLAGE",
    "name:eng_x_preferred":[
        "Binuda"
    ],
    "wof:name":"Binuda",
    "wof:placetype":"locality",
    "wof:population":93
},
  "geometry": {"coordinates":[86.94340800000001,24.602753],"type":"Point"}
}