{
  "type": "Feature",
  "properties": {
    "iso:country":"IN",
    "ks:ks_name":"Maldihi",
    "ks:ks_pop":412,
    "ks:ks_type":"VILLAGE",
    "name:eng_x_preferred":[
        "Maldihi"
    ],
    "wof:name":"Maldihi",
    "wof:placetype":"locality",
    "wof:population":412
},
  "geometry": {"coordinates":[87.54585899999999,23.844564],"type":"Point"}
}