{
  "type": "Feature",
  "properties": {
    "iso:country":"IN",
    "ks:ks_name":"Lethanguda",
    "ks:ks_pop":213,
    "ks:ks_type":"HABITATION",
    "name:eng_x_preferred":[
        "Lethanguda"
    ],
    "wof:name":"Lethanguda",
    "wof:placetype":"locality",
    "wof:population":213
},
  "geometry": {"coordinates":[79.418835,19.289557],"type":"Point"}
}