{
  "type": "Feature",
  "properties": {
    "iso:country":"IN",
    "ks:ks_name":"Batawada",
    "ks:ks_pop":70,
    "ks:ks_type":"HABITATION",
    "name:eng_x_preferred":[
        "Batawada"
    ],
    "wof:name":"Batawada",
    "wof:placetype":"locality",
    "wof:population":70
},
  "geometry": {"coordinates":[74.558485,15.482842],"type":"Point"}
}