{
  "type": "Feature",
  "properties": {
    "iso:country":"IN",
    "ks:ks_name":"Patilwadi",
    "ks:ks_pop":73,
    "ks:ks_type":"HABITATION",
    "name:eng_x_preferred":[
        "Patilwadi"
    ],
    "wof:name":"Patilwadi",
    "wof:placetype":"locality",
    "wof:population":73
},
  "geometry": {"coordinates":[73.89360600000001,16.876811],"type":"Point"}
}