{
  "type": "Feature",
  "properties": {
    "iso:country":"IN",
    "ks:ks_name":"Chak Puran Berya",
    "ks:ks_pop":5,
    "ks:ks_type":"VILLAGE",
    "name:eng_x_preferred":[
        "Chak Puran Berya"
    ],
    "wof:name":"Chak Puran Berya",
    "wof:placetype":"locality",
    "wof:population":5
},
  "geometry": {"coordinates":[87.462245,22.609469],"type":"Point"}
}