{
  "type": "Feature",
  "properties": {
    "gn:admin1_code":"36",
    "gn:admin2_code":"188.0",
    "gn:asciiname":"Belwa",
    "gn:country_code":"IN",
    "gn:dem":85,
    "gn:feature_class":"P",
    "gn:feature_code":"PPL",
    "gn:name":"Belwa",
    "gn:population":0,
    "gn:timezone":"Asia/Kolkata",
    "iso:country":"IN",
    "name:new_x_preferred":[
        "\u092c\u0947\u0932\u0935\u093e"
    ],
    "wof:name":"Belwa",
    "wof:placetype":"neighbourhood"
},
  "geometry": {"coordinates":[83.55542,26.71785],"type":"Point"}
}