{
  "type": "Feature",
  "properties": {
    "iso:country":"IN",
    "ks:ks_name":"Devarajanahalli",
    "ks:ks_pop":40,
    "ks:ks_type":"VILLAGE",
    "name:eng_x_preferred":[
        "Devarajanahalli"
    ],
    "wof:name":"Devarajanahalli",
    "wof:placetype":"locality",
    "wof:population":40
},
  "geometry": {"coordinates":[76.992054,13.433555],"type":"Point"}
}