{
  "type": "Feature",
  "properties": {
    "iso:country":"IN",
    "ks:ks_alt_nam":"PURE MEDAI",
    "ks:ks_name":"Pure Medai",
    "ks:ks_pop":82,
    "ks:ks_type":"HABITATION",
    "ks:ks_uagg_main":0,
    "name:eng_x_preferred":[
        "Pure Medai"
    ],
    "wof:name":"Pure Medai",
    "wof:placetype":"neighbourhood",
    "wof:population":82
},
  "geometry": {"coordinates":[81.767696,26.100656],"type":"Point"}
}