{
  "type": "Feature",
  "properties": {
    "iso:country":"IN",
    "ks:ks_name":"Paradampattu",
    "ks:ks_pop":176,
    "ks:ks_type":"HABITATION",
    "name:eng_x_preferred":[
        "Paradampattu"
    ],
    "wof:name":"Paradampattu",
    "wof:placetype":"locality",
    "wof:population":176
},
  "geometry": {"coordinates":[79.624954,11.53015],"type":"Point"}
}