{
  "type": "Feature",
  "properties": {
    "iso:country":"IN",
    "ks:ks_name":"Nagla Gupkapur",
    "ks:ks_pop":698,
    "ks:ks_type":"HABITATION",
    "ks:ks_uagg_main":0,
    "name:eng_x_preferred":[
        "Nagla Gupkapur"
    ],
    "wof:name":"Nagla Gupkapur",
    "wof:placetype":"neighbourhood",
    "wof:population":698
},
  "geometry": {"coordinates":[79.36509100000001,26.688834],"type":"Point"}
}