{
  "type": "Feature",
  "properties": {
    "iso:country":"IN",
    "ks:ks_name":"Getijharan",
    "ks:ks_pop":258,
    "ks:ks_type":"VILLAGE",
    "name:eng_x_preferred":[
        "Getijharan"
    ],
    "wof:name":"Getijharan",
    "wof:placetype":"locality",
    "wof:population":258
},
  "geometry": {"coordinates":[85.00953699999999,22.155585],"type":"Point"}
}