{
  "type": "Feature",
  "properties": {
    "gn:admin1_code":"36",
    "gn:admin2_code":"157.0",
    "gn:asciiname":"Halimabad",
    "gn:country_code":"IN",
    "gn:dem":116,
    "gn:feature_class":"P",
    "gn:feature_code":"PPL",
    "gn:name":"Hal\u012bm\u0101b\u0101d",
    "gn:population":0,
    "gn:timezone":"Asia/Kolkata",
    "iso:country":"IN",
    "wof:name":"Halimabad",
    "wof:placetype":"neighbourhood"
},
  "geometry": {"coordinates":[81.13366000000001,26.81285],"type":"Point"}
}