{
  "type": "Feature",
  "properties": {
    "iso:country":"IN",
    "ks:ks_name":"Karuppakoilpatti",
    "ks:ks_pop":502,
    "ks:ks_type":"HABITATION",
    "name:eng_x_preferred":[
        "Karuppakoilpatti"
    ],
    "wof:name":"Karuppakoilpatti",
    "wof:placetype":"locality",
    "wof:population":502
},
  "geometry": {"coordinates":[78.399473,10.526516],"type":"Point"}
}