{
  "type": "Feature",
  "properties": {
    "iso:country":"IN",
    "ks:ks_name":"Sikni",
    "ks:ks_pop":74,
    "ks:ks_type":"VILLAGE",
    "name:eng_x_preferred":[
        "Sikni"
    ],
    "wof:name":"Sikni",
    "wof:placetype":"locality",
    "wof:population":74
},
  "geometry": {"coordinates":[84.02322100000001,24.36263],"type":"Point"}
}