{
  "type": "Feature",
  "properties": {
    "iso:country":"IN",
    "name:eng_x_preferred":[
        "Sector 10"
    ],
    "qs:gn_adm0_cc":"IN",
    "qs:gn_local":1274746,
    "qs:gn_nam_loc":"Chandigarh, Chandigarh, Chandigarh, IN",
    "qs:gn_namadm1":"05",
    "qs:local_max":950,
    "qs:local_sum":2657,
    "qs:localhoods":19,
    "qs:name":"Sector 10",
    "qs:name_adm0":"India",
    "qs:name_adm1":"Chandigarh",
    "qs:name_adm2":"Chandigarh",
    "qs:name_local":"Chandigarh",
    "qs:photo_max":81,
    "qs:photo_sum":416,
    "qs:placetype":"Suburb",
    "qs:quad_count":19,
    "qs:woe_adm0":23424848,
    "qs:woe_adm1":20070456,
    "qs:woe_adm2":12586629,
    "qs:woe_lau":0,
    "qs:woe_local":2295391,
    "qs:woe_ver":"7.10.0",
    "wof:lang":[
        "eng"
    ],
    "wof:name":"Sector 10",
    "wof:placetype":"neighbourhood"
},
  "geometry": {"coordinates":[76.78875499999999,30.747484],"type":"Point"}
}