{
  "type": "Feature",
  "properties": {
    "gn:admin1_code":"21.0",
    "gn:admin2_code":"395.0",
    "gn:asciiname":"Madanpur Rampur",
    "gn:country_code":"IN",
    "gn:dem":192,
    "gn:feature_class":"P",
    "gn:feature_code":"PPL",
    "gn:name":"Madanpur Rampur",
    "gn:population":0,
    "gn:timezone":"Asia/Kolkata",
    "iso:country":"IN",
    "name:urd_x_preferred":[
        "\u0645\u0639\u062f\u0646\u067e\u0648\u0631 \u0631\u0627\u0645\u067e\u0648\u0631"
    ],
    "wof:name":"Madanpur Rampur",
    "wof:placetype":"locality"
},
  "geometry": {"coordinates":[83.5311,20.3203],"type":"Point"}
}