{
  "type": "Feature",
  "properties": {
    "gn:admin1_code":"34.0",
    "gn:admin2_code":"219.0",
    "gn:asciiname":"Mira Musehri",
    "gn:country_code":"IN",
    "gn:dem":58,
    "gn:feature_class":"P",
    "gn:feature_code":"PPL",
    "gn:name":"Mira Musehri",
    "gn:population":0,
    "gn:timezone":"Asia/Kolkata",
    "iso:country":"IN",
    "ks:ks_name":"Mira Musehri",
    "ks:ks_pop":2762,
    "ks:ks_type":"VILLAGE",
    "ks:ks_uagg_main":0,
    "name:eng_x_preferred":[
        "Mira Musehri"
    ],
    "wof:name":"Mira Musehri",
    "wof:placetype":"neighbourhood",
    "wof:population":2762
},
  "geometry": {"coordinates":[84.747044,25.849717],"type":"Point"}
}