{
  "type": "Feature",
  "properties": {
    "iso:country":"IN",
    "ks:ks_name":"Chak Arabad",
    "ks:ks_pop":0,
    "ks:ks_type":"VILLAGE",
    "name:eng_x_preferred":[
        "Chak Arabad"
    ],
    "wof:name":"Chak Arabad",
    "wof:placetype":"locality",
    "wof:population":0
},
  "geometry": {"coordinates":[87.20259900000001,23.428932],"type":"Point"}
}