{
  "type": "Feature",
  "properties": {
    "iso:country":"IN",
    "ks:ks_name":"Nandiveer Matha",
    "ks:ks_pop":58,
    "ks:ks_type":"HABITATION",
    "name:eng_x_preferred":[
        "Nandiveer Matha"
    ],
    "wof:name":"Nandiveer Matha",
    "wof:placetype":"locality",
    "wof:population":58
},
  "geometry": {"coordinates":[75.71832499999999,15.26965],"type":"Point"}
}