{
  "type": "Feature",
  "properties": {
    "iso:country":"IN",
    "ks:ks_name":"Dodubylu",
    "ks:ks_pop":73,
    "ks:ks_type":"HABITATION",
    "name:eng_x_preferred":[
        "Dodubylu"
    ],
    "wof:name":"Dodubylu",
    "wof:placetype":"locality",
    "wof:population":73
},
  "geometry": {"coordinates":[75.11769,13.487222],"type":"Point"}
}