{
  "type": "Feature",
  "properties": {
    "iso:country":"IN",
    "ks:ks_name":"Lodhera",
    "ks:ks_pop":676,
    "ks:ks_type":"VILLAGE",
    "name:eng_x_preferred":[
        "Lodhera"
    ],
    "wof:name":"Lodhera",
    "wof:placetype":"locality",
    "wof:population":676
},
  "geometry": {"coordinates":[75.850385,26.434483],"type":"Point"}
}