{
  "type": "Feature",
  "properties": {
    "iso:country":"IN",
    "ks:ks_name":"Gomat Chauraya",
    "ks:ks_pop":660,
    "ks:ks_type":"HABITATION",
    "name:eng_x_preferred":[
        "Gomat Chauraya"
    ],
    "wof:name":"Gomat Chauraya",
    "wof:placetype":"locality",
    "wof:population":660
},
  "geometry": {"coordinates":[77.797781,27.961337],"type":"Point"}
}