{
  "type": "Feature",
  "properties": {
    "gn:admin1_code":"21",
    "gn:admin2_code":"370.0",
    "gn:asciiname":"Kansdol",
    "gn:country_code":"IN",
    "gn:dem":182,
    "gn:feature_class":"P",
    "gn:feature_code":"PPL",
    "gn:name":"Kansdol",
    "gn:population":0,
    "gn:timezone":"Asia/Kolkata",
    "iso:country":"IN",
    "wof:name":"Kansdol",
    "wof:placetype":"locality"
},
  "geometry": {"coordinates":[83.37085,20.92501],"type":"Point"}
}