{
  "type": "Feature",
  "properties": {
    "gn:admin1_code":"36.0",
    "gn:asciiname":"Chandwa",
    "gn:country_code":"IN",
    "gn:dem":124,
    "gn:feature_class":"P",
    "gn:feature_code":"PPL",
    "gn:name":"Chandwa",
    "gn:population":0,
    "gn:timezone":"Asia/Kolkata",
    "iso:country":"IN",
    "ks:ks_name":"Chundwa",
    "ks:ks_pop":554,
    "ks:ks_type":"VILLAGE",
    "ks:ks_uagg_main":0,
    "name:eng_x_preferred":[
        "Chundwa"
    ],
    "wof:name":"Chundwa",
    "wof:placetype":"neighbourhood",
    "wof:population":554
},
  "geometry": {"coordinates":[81.61783,25.174139],"type":"Point"}
}