{
  "type": "Feature",
  "properties": {
    "iso:country":"IN",
    "ks:ks_name":"Majha Bangapur",
    "ks:ks_pop":625,
    "ks:ks_type":"HABITATION",
    "name:eng_x_preferred":[
        "Majha Bangapur"
    ],
    "wof:name":"Majha Bangapur",
    "wof:placetype":"locality",
    "wof:population":625
},
  "geometry": {"coordinates":[83.089344,26.378401],"type":"Point"}
}