{
  "type": "Feature",
  "properties": {
    "gn:admin1_code":"36",
    "gn:admin2_code":"202.0",
    "gn:asciiname":"Rayon",
    "gn:country_code":"IN",
    "gn:dem":171,
    "gn:feature_class":"P",
    "gn:feature_code":"PPL",
    "gn:name":"Rayon",
    "gn:population":0,
    "gn:timezone":"Asia/Kolkata",
    "iso:country":"IN",
    "name:ara_x_preferred":[
        "\u0631\u0627\u064a\u0648\u0646"
    ],
    "name:cat_x_preferred":[
        "Rai\u00f3"
    ],
    "name:ces_x_preferred":[
        "Visk\u00f3zov\u00e1 vl\u00e1kna"
    ],
    "name:est_x_preferred":[
        "Viskooskiud"
    ],
    "name:eus_x_preferred":[
        "Rayon"
    ],
    "name:fas_x_preferred":[
        "\u0627\u0628\u0631\u06cc\u0634\u0645 \u0645\u0635\u0646\u0648\u0639\u06cc"
    ],
    "name:fin_x_preferred":[
        "Viskoosi"
    ],
    "name:gle_x_preferred":[
        "R\u00e9\u00f3n"
    ],
    "name:hin_x_preferred":[
        "\u0930\u0947\u092f\u093e\u0928"
    ],
    "name:hun_x_preferred":[
        "M\u0171selyem"
    ],
    "name:ind_x_preferred":[
        "Rayon"
    ],
    "name:ita_x_preferred":[
        "Rayon"
    ],
    "name:jpn_x_preferred":[
        "\u30ec\u30fc\u30e8\u30f3"
    ],
    "name:kan_x_preferred":[
        "\u0cb0\u0cc7\u0caf\u0cbe\u0ca8\u0ccd"
    ],
    "name:kor_x_preferred":[
        "\ub808\uc774\uc628"
    ],
    "name:nld_x_preferred":[
        "Kunstzijde"
    ],
    "name:pol_x_preferred":[
        "W\u0142\u00f3kna wiskozowe"
    ],
    "name:por_x_preferred":[
        "Raiom"
    ],
    "name:rus_x_preferred":[
        "\u0412\u0438\u0441\u043a\u043e\u0437\u043d\u043e\u0435 \u0432\u043e\u043b\u043e\u043a\u043d\u043e"
    ],
    "name:spa_x_preferred":[
        "Ray\u00f3n"
    ],
    "name:tgl_x_preferred":[
        "Rayon"
    ],
    "name:tur_x_preferred":[
        "Bitkisel ipek"
    ],
    "name:ukr_x_preferred":[
        "\u0412\u0456\u0441\u043a\u043e\u0437\u043d\u0435 \u0432\u043e\u043b\u043e\u043a\u043d\u043e"
    ],
    "name:war_x_preferred":[
        "Rayon"
    ],
    "wof:name":"Rayon",
    "wof:placetype":"locality"
},
  "geometry": {"coordinates":[78.90255000000001,27.75185],"type":"Point"}
}