{
  "type": "Feature",
  "properties": {
    "gn:admin1_code":"2",
    "gn:admin2_code":"546.0",
    "gn:asciiname":"Tanalkunta",
    "gn:country_code":"IN",
    "gn:dem":79,
    "gn:feature_class":"P",
    "gn:feature_code":"PPL",
    "gn:name":"T\u0101nalkunta",
    "gn:population":0,
    "gn:timezone":"Asia/Kolkata",
    "iso:country":"IN",
    "ks:ks_name":"Tanalakunta",
    "ks:ks_pop":70,
    "ks:ks_type":"HABITATION",
    "name:eng_x_preferred":[
        "Tanalakunta"
    ],
    "name:eng_x_variant":[
        "Tanalkunta"
    ],
    "wof:name":"Tanalakunta",
    "wof:placetype":"locality",
    "wof:population":70
},
  "geometry": {"coordinates":[81.567986,17.251062],"type":"Point"}
}