{
  "type": "Feature",
  "properties": {
    "iso:country":"IN",
    "ks:ks_name":"Akolha",
    "ks:ks_pop":1,
    "ks:ks_type":"HABITATION",
    "name:eng_x_preferred":[
        "Akolha"
    ],
    "wof:name":"Akolha",
    "wof:placetype":"locality",
    "wof:population":1
},
  "geometry": {"coordinates":[82.683902,26.687544],"type":"Point"}
}