{
  "type": "Feature",
  "properties": {
    "iso:country":"IN",
    "ks:ks_name":"2 DWSM",
    "ks:ks_pop":257,
    "ks:ks_type":"VILLAGE",
    "name:eng_x_preferred":[
        "2 DWSM"
    ],
    "wof:name":"2 DWSM",
    "wof:placetype":"locality",
    "wof:population":257
},
  "geometry": {"coordinates":[73.605171,29.170499],"type":"Point"}
}