{
  "type": "Feature",
  "properties": {
    "iso:country":"IN",
    "ks:ks_name":"Nausahara",
    "ks:ks_pop":171,
    "ks:ks_type":"HABITATION",
    "name:eng_x_preferred":[
        "Nausahara"
    ],
    "wof:name":"Nausahara",
    "wof:placetype":"locality",
    "wof:population":171
},
  "geometry": {"coordinates":[81.99909,27.82897],"type":"Point"}
}