{
  "type": "Feature",
  "properties": {
    "gn:country":"IN",
    "gn:fcode":"PPL",
    "gn:population":13627,
    "iso:country":"IN",
    "ks:ks_name":"Attayampatti",
    "ks:ks_pop":12698,
    "ks:ks_type":"VILLAGE",
    "ks:ks_uagg_main":0,
    "name:bpy_x_preferred":[
        "\u0986\u09a4\u09cd\u09a4\u09af\u09bc\u09be\u09ae\u09aa\u09be\u09a4\u09cd\u09a4\u09bf"
    ],
    "name:ceb_x_preferred":[
        "\u0100ttayy\u0101mpatti"
    ],
    "name:eng_x_preferred":[
        "Attayampatti"
    ],
    "name:fra_x_preferred":[
        "Attayampatti"
    ],
    "name:ita_x_preferred":[
        "Attayampatti"
    ],
    "name:msa_x_preferred":[
        "Attayampatti"
    ],
    "name:nan_x_preferred":[
        "Attayampatti"
    ],
    "name:new_x_preferred":[
        "\u0905\u0924\u094d\u0924\u092f\u093e\u092e\u092a\u091f\u094d\u091f\u0940"
    ],
    "name:nld_x_preferred":[
        "Attayampatti"
    ],
    "name:por_x_preferred":[
        "Attayampatti"
    ],
    "name:spa_x_preferred":[
        "Attayampatti"
    ],
    "name:swe_x_preferred":[
        "\u0100ttayy\u0101mpatti"
    ],
    "name:tam_x_preferred":[
        "\u0b86\u0b9f\u0bcd\u0b9f\u0bc8\u0baf\u0bbe\u0bae\u0bcd\u0baa\u0b9f\u0bcd\u0b9f\u0bbf"
    ],
    "name:vie_x_preferred":[
        "Attayampatti"
    ],
    "name:zho_x_preferred":[
        "\u963f\u5854\u8036\u59c6\u5e15\u8482"
    ],
    "qs:name":"Attayampatti",
    "qs:name_adm0":"India",
    "qs:name_adm1":"Tamil Nadu",
    "qs:photos_9r":0,
    "qs:photos_sr":0,
    "qs:placetype":"Town",
    "qs:pop_sr":"6",
    "wof:name":"Attayampatti",
    "wof:placetype":"neighbourhood",
    "wof:population":12698
},
  "geometry": {"coordinates":[78.048768,11.529795],"type":"Point"}
}