{
  "type": "Feature",
  "properties": {
    "gn:admin1_code":"24.0",
    "gn:admin2_code":"102",
    "gn:asciiname":"Jandwa",
    "gn:country_code":"IN",
    "gn:dem":308,
    "gn:feature_class":"P",
    "gn:feature_code":"PPL",
    "gn:name":"J\u0101ndwa",
    "gn:population":0,
    "gn:timezone":"Asia/Kolkata",
    "iso:country":"IN",
    "name:und_x_variant":[
        "J\u0101ndwa",
        "J\u0101noa"
    ],
    "wof:name":"Jandwa",
    "wof:placetype":"locality"
},
  "geometry": {"coordinates":[74.81662,28.12845],"type":"Point"}
}