{
  "type": "Feature",
  "properties": {
    "iso:country":"IN",
    "ks:ks_name":"Naurang Dih",
    "ks:ks_pop":142,
    "ks:ks_type":"HABITATION",
    "name:eng_x_preferred":[
        "Naurang Dih"
    ],
    "wof:name":"Naurang Dih",
    "wof:placetype":"locality",
    "wof:population":142
},
  "geometry": {"coordinates":[82.332482,27.336547],"type":"Point"}
}