{
  "type": "Feature",
  "properties": {
    "gn:admin1_code":"19.0",
    "gn:admin2_code":"570.0",
    "gn:asciiname":"Dwaranahalu",
    "gn:country_code":"IN",
    "gn:dem":726,
    "gn:feature_class":"P",
    "gn:feature_code":"PPL",
    "gn:name":"Dw\u0101ranah\u0101lu",
    "gn:population":0,
    "gn:timezone":"Asia/Kolkata",
    "iso:country":"IN",
    "wof:name":"Dwaranahalu",
    "wof:placetype":"locality"
},
  "geometry": {"coordinates":[75.83635,13.67644],"type":"Point"}
}