{
  "type": "Feature",
  "properties": {
    "iso:country":"IN",
    "ks:ks_name":"Lambanitandya",
    "ks:ks_pop":97,
    "ks:ks_type":"HABITATION",
    "name:eng_x_preferred":[
        "Lambanitandya"
    ],
    "wof:name":"Lambanitandya",
    "wof:placetype":"locality",
    "wof:population":97
},
  "geometry": {"coordinates":[76.46286000000001,13.31415],"type":"Point"}
}