{
  "type": "Feature",
  "properties": {
    "iso:country":"IN",
    "ks:ks_alt_nam":"Jaderi ADC",
    "ks:ks_name":"Jaderi Adc",
    "ks:ks_pop":170,
    "ks:ks_type":"HABITATION",
    "name:eng_x_preferred":[
        "Jaderi Adc"
    ],
    "wof:name":"Jaderi Adc",
    "wof:placetype":"locality",
    "wof:population":170
},
  "geometry": {"coordinates":[79.708744,13.093616],"type":"Point"}
}