{
  "type": "Feature",
  "properties": {
    "iso:country":"IN",
    "ks:ks_name":"Mudala",
    "ks:ks_pop":160,
    "ks:ks_type":"HABITATION",
    "name:eng_x_preferred":[
        "Mudala"
    ],
    "wof:name":"Mudala",
    "wof:placetype":"locality",
    "wof:population":160
},
  "geometry": {"coordinates":[75.51143,12.815788],"type":"Point"}
}