{
  "type": "Feature",
  "properties": {
    "iso:country":"IN",
    "ks:ks_name":"Amri",
    "ks:ks_pop":98,
    "ks:ks_type":"VILLAGE",
    "name:eng_x_preferred":[
        "Amri"
    ],
    "wof:name":"Amri",
    "wof:placetype":"locality",
    "wof:population":98
},
  "geometry": {"coordinates":[86.999509,24.484733],"type":"Point"}
}