{
  "type": "Feature",
  "properties": {
    "gn:admin1_code":"16",
    "gn:admin2_code":"508.0",
    "gn:asciiname":"Kurandi",
    "gn:country_code":"IN",
    "gn:dem":226,
    "gn:feature_class":"P",
    "gn:feature_code":"PPL",
    "gn:name":"Kurandi",
    "gn:population":0,
    "gn:timezone":"Asia/Kolkata",
    "iso:country":"IN",
    "ks:ks_name":"Kurandi",
    "ks:ks_pop":483,
    "ks:ks_type":"VILLAGE",
    "ks:ks_uagg_main":0,
    "name:eng_x_preferred":[
        "Kurandi"
    ],
    "name:msa_x_preferred":[
        "Kurandi"
    ],
    "wof:name":"Kurandi",
    "wof:placetype":"neighbourhood",
    "wof:population":483
},
  "geometry": {"coordinates":[80.147426,20.40807],"type":"Point"}
}