{
  "type": "Feature",
  "properties": {
    "iso:country":"IN",
    "ks:ks_name":"Degaon",
    "ks:ks_pop":956,
    "ks:ks_type":"VILLAGE",
    "name:eng_x_preferred":[
        "Degaon"
    ],
    "wof:name":"Degaon",
    "wof:placetype":"locality",
    "wof:population":956
},
  "geometry": {"coordinates":[73.29725500000001,17.641217],"type":"Point"}
}