{
  "type": "Feature",
  "properties": {
    "iso:country":"IN",
    "ks:ks_name":"Besingisahi",
    "ks:ks_pop":26,
    "ks:ks_type":"VILLAGE",
    "name:eng_x_preferred":[
        "Besingisahi"
    ],
    "wof:name":"Besingisahi",
    "wof:placetype":"locality",
    "wof:population":26
},
  "geometry": {"coordinates":[84.12369,20.190956],"type":"Point"}
}