{
  "type": "Feature",
  "properties": {
    "gn:admin1_code":"38.0",
    "gn:admin2_code":"347.0",
    "gn:asciiname":"Bhang Kurkutta",
    "gn:country_code":"IN",
    "gn:dem":427,
    "gn:feature_class":"P",
    "gn:feature_code":"PPL",
    "gn:name":"Bh\u0101ng Kurkutta",
    "gn:population":0,
    "gn:timezone":"Asia/Kolkata",
    "iso:country":"IN",
    "wof:name":"Bhang Kurkutta",
    "wof:placetype":"locality"
},
  "geometry": {"coordinates":[85.00563000000002,24.33199],"type":"Point"}
}