{
  "type": "Feature",
  "properties": {
    "gn:admin1_code":"38.0",
    "gn:admin2_code":"347.0",
    "gn:asciiname":"Bhang Kurkutta",
    "gn:country_code":"IN",
    "gn:dem":427,
    "gn:feature_class":"P",
    "gn:feature_code":"PPL",
    "gn:name":"Bh\u0101ng Kurkutta",
    "gn:population":0,
    "gn:timezone":"Asia/Kolkata",
    "iso:country":"IN",
    "ks:ks_alt_nam":"Bh\u0101ng Kurkutta",
    "ks:ks_name":"Bhang Kurkutta",
    "ks:ks_type":"VILLAGE",
    "name:eng_x_preferred":[
        "Bhang Kurkutta"
    ],
    "name:eng_x_variant":[
        "Bh\u0101ng Kurkutta"
    ],
    "wof:name":"Bhang Kurkutta",
    "wof:placetype":"locality"
},
  "geometry": {"coordinates":[85.005634,24.331992],"type":"Point"}
}