{
  "type": "Feature",
  "properties": {
    "gn:admin1_code":"2.0",
    "gn:admin2_code":"543.0",
    "gn:asciiname":"Jala",
    "gn:country_code":"IN",
    "gn:dem":286,
    "gn:feature_class":"P",
    "gn:feature_code":"PPL",
    "gn:name":"Jala",
    "gn:population":0,
    "gn:timezone":"Asia/Kolkata",
    "iso:country":"IN",
    "ks:ks_name":"Jala",
    "ks:ks_pop":164,
    "ks:ks_type":"VILLAGE",
    "name:ceb_x_preferred":[
        "Jala"
    ],
    "name:eng_x_preferred":[
        "Jala"
    ],
    "name:fra_x_preferred":[
        "Jala"
    ],
    "name:hrv_x_preferred":[
        "Jala"
    ],
    "name:srp_x_preferred":[
        "Jala"
    ],
    "name:swe_x_preferred":[
        "Jala"
    ],
    "wof:name":"Jala",
    "wof:placetype":"locality",
    "wof:population":164
},
  "geometry": {"coordinates":[83.416601,18.967608],"type":"Point"}
}