{
  "type": "Feature",
  "properties": {
    "iso:country":"IN",
    "ks:ks_name":"Barsu",
    "ks:ks_pop":11,
    "ks:ks_type":"VILLAGE",
    "name:eng_x_preferred":[
        "Barsu"
    ],
    "wof:name":"Barsu",
    "wof:placetype":"locality",
    "wof:population":11
},
  "geometry": {"coordinates":[78.996414,30.28634],"type":"Point"}
}