{
  "type": "Feature",
  "properties": {
    "gn:admin1_code":"25.0",
    "gn:admin2_code":"631.0",
    "gn:asciiname":"Talikottanur",
    "gn:country_code":"IN",
    "gn:dem":905,
    "gn:feature_class":"P",
    "gn:feature_code":"PPL",
    "gn:name":"Talikottan\u016br",
    "gn:population":0,
    "gn:timezone":"Asia/Kolkata",
    "iso:country":"IN",
    "wof:name":"Talikottanur",
    "wof:placetype":"locality"
},
  "geometry": {"coordinates":[77.69230999999998,12.57329],"type":"Point"}
}