{
  "type": "Feature",
  "properties": {
    "iso:country":"IN",
    "ks:ks_name":"Bhatpara",
    "ks:ks_pop":1907,
    "ks:ks_type":"VILLAGE",
    "name:ben_x_preferred":[
        "\u09ad\u09be\u099f\u09aa\u09be\u09a1\u09bc\u09be"
    ],
    "name:eng_x_preferred":[
        "Bhatpara"
    ],
    "name:hin_x_preferred":[
        "\u092d\u093e\u091f\u092a\u093e\u0921\u093c\u093e"
    ],
    "wof:name":"Bhatpara",
    "wof:placetype":"locality",
    "wof:population":1907
},
  "geometry": {"coordinates":[87.509524,23.308143],"type":"Point"}
}