{
  "type": "Feature",
  "properties": {
    "iso:country":"IN",
    "ks:ks_name":"Gamulai",
    "ks:ks_pop":264,
    "ks:ks_type":"VILLAGE",
    "name:eng_x_preferred":[
        "Gamulai"
    ],
    "wof:name":"Gamulai",
    "wof:placetype":"locality",
    "wof:population":264
},
  "geometry": {"coordinates":[85.331755,22.034644],"type":"Point"}
}