{
  "type": "Feature",
  "properties": {
    "iso:country":"IN",
    "ks:ks_name":"Khedkarwasti",
    "ks:ks_pop":255,
    "ks:ks_type":"HABITATION",
    "name:eng_x_preferred":[
        "Khedkarwasti"
    ],
    "wof:name":"Khedkarwasti",
    "wof:placetype":"locality",
    "wof:population":255
},
  "geometry": {"coordinates":[74.968023,18.729553],"type":"Point"}
}