{
  "type": "Feature",
  "properties": {
    "gn:admin1_code":"21",
    "gn:admin2_code":"371.0",
    "gn:asciiname":"Jora Dungri",
    "gn:country_code":"IN",
    "gn:dem":188,
    "gn:feature_class":"P",
    "gn:feature_code":"PPL",
    "gn:name":"Jora Dungri",
    "gn:population":0,
    "gn:timezone":"Asia/Kolkata",
    "iso:country":"IN",
    "wof:name":"Jora Dungri",
    "wof:placetype":"locality"
},
  "geometry": {"coordinates":[83.73224999999999,21.67232000000001],"type":"Point"}
}