{
  "type": "Feature",
  "properties": {
    "iso:country":"IN",
    "ks:ks_name":"Chinthakarra",
    "ks:ks_pop":83,
    "ks:ks_type":"HABITATION",
    "name:eng_x_preferred":[
        "Chinthakarra"
    ],
    "wof:name":"Chinthakarra",
    "wof:placetype":"locality",
    "wof:population":83
},
  "geometry": {"coordinates":[79.037172,19.423051],"type":"Point"}
}