{
  "type": "Feature",
  "properties": {
    "gn:admin1_code":"36",
    "gn:admin2_code":"144.0",
    "gn:asciiname":"Bonai",
    "gn:country_code":"IN",
    "gn:dem":180,
    "gn:feature_class":"P",
    "gn:feature_code":"PPL",
    "gn:name":"Bonai",
    "gn:population":0,
    "gn:timezone":"Asia/Kolkata",
    "iso:country":"IN",
    "name:cat_x_preferred":[
        "Bonai"
    ],
    "name:deu_x_preferred":[
        "Bonai"
    ],
    "name:ori_x_preferred":[
        "\u0b2c\u0b23\u0b3e\u0b07 \u0b30\u0b3e\u0b1c\u0b4d\u0b5f"
    ],
    "wof:name":"Bonai",
    "wof:placetype":"locality"
},
  "geometry": {"coordinates":[78.2394,27.5616],"type":"Point"}
}