{
  "type": "Feature",
  "properties": {
    "iso:country":"IN",
    "ks:ks_alt_nam":"konnar keri",
    "ks:ks_name":"Konnar Keri",
    "ks:ks_pop":164,
    "ks:ks_type":"HABITATION",
    "name:eng_x_preferred":[
        "Konnar Keri"
    ],
    "wof:name":"Konnar Keri",
    "wof:placetype":"locality",
    "wof:population":164
},
  "geometry": {"coordinates":[74.51401,14.096591],"type":"Point"}
}