{
  "type": "Feature",
  "properties": {
    "iso:country":"IN",
    "ks:ks_name":"Pahadpara",
    "ks:ks_pop":717,
    "ks:ks_type":"HABITATION",
    "name:eng_x_preferred":[
        "Pahadpara"
    ],
    "wof:name":"Pahadpara",
    "wof:placetype":"locality",
    "wof:population":717
},
  "geometry": {"coordinates":[82.342512,22.978093],"type":"Point"}
}