{
  "type": "Feature",
  "properties": {
    "iso:country":"IN",
    "ks:ks_name":"Misiguda",
    "ks:ks_pop":66,
    "ks:ks_type":"HABITATION",
    "name:eng_x_preferred":[
        "Misiguda"
    ],
    "wof:name":"Misiguda",
    "wof:placetype":"locality",
    "wof:population":66
},
  "geometry": {"coordinates":[81.610575,18.126722],"type":"Point"}
}