{
  "type": "Feature",
  "properties": {
    "iso:country":"IN",
    "ks:ks_name":"Bodapara",
    "ks:ks_pop":151,
    "ks:ks_type":"HABITATION",
    "name:eng_x_preferred":[
        "Bodapara"
    ],
    "wof:name":"Bodapara",
    "wof:placetype":"locality",
    "wof:population":151
},
  "geometry": {"coordinates":[81.652029,19.237681],"type":"Point"}
}