{
  "type": "Feature",
  "properties": {
    "gn:admin1_code":"37.0",
    "gn:admin2_code":"403.0",
    "gn:asciiname":"Salihari",
    "gn:country_code":"IN",
    "gn:dem":274,
    "gn:feature_class":"P",
    "gn:feature_code":"PPL",
    "gn:name":"Salihari",
    "gn:population":0,
    "gn:timezone":"Asia/Kolkata",
    "iso:country":"IN",
    "wof:name":"Salihari",
    "wof:placetype":"locality"
},
  "geometry": {"coordinates":[83.46035000000001,22.05577000000001],"type":"Point"}
}