{
  "type": "Feature",
  "properties": {
    "iso:country":"IN",
    "ks:ks_name":"Nundarha",
    "ks:ks_pop":781,
    "ks:ks_type":"VILLAGE",
    "name:eng_x_preferred":[
        "Nundarha"
    ],
    "wof:name":"Nundarha",
    "wof:placetype":"locality",
    "wof:population":781
},
  "geometry": {"coordinates":[83.402978,22.206128],"type":"Point"}
}