{
  "type": "Feature",
  "properties": {
    "iso:country":"IN",
    "ks:ks_name":"Amarapur",
    "ks:ks_pop":717,
    "ks:ks_type":"VILLAGE",
    "ks:ks_uagg_main":0,
    "name:eng_x_preferred":[
        "Amarapur"
    ],
    "wof:name":"Amarapur",
    "wof:placetype":"neighbourhood",
    "wof:population":717
},
  "geometry": {"coordinates":[73.886188,19.202841],"type":"Point"}
}