{
  "type": "Feature",
  "properties": {
    "iso:country":"IN",
    "ks:ks_name":"Padikkeel",
    "ks:ks_pop":1082,
    "ks:ks_type":"HABITATION",
    "name:eng_x_preferred":[
        "Padikkeel"
    ],
    "wof:name":"Padikkeel",
    "wof:placetype":"locality",
    "wof:population":1082
},
  "geometry": {"coordinates":[75.21108099999999,12.221406],"type":"Point"}
}