{
  "type": "Feature",
  "properties": {
    "gn:admin1_code":"28.0",
    "gn:admin2_code":"334.0",
    "gn:asciiname":"Pattapara",
    "gn:country_code":"IN",
    "gn:dem":46,
    "gn:feature_class":"P",
    "gn:feature_code":"PPL",
    "gn:name":"Patt\u0101p\u0101ra",
    "gn:population":0,
    "gn:timezone":"Asia/Kolkata",
    "iso:country":"IN",
    "wof:name":"Pattapara",
    "wof:placetype":"locality"
},
  "geometry": {"coordinates":[87.79994000000001,24.26431],"type":"Point"}
}