{
  "type": "Feature",
  "properties": {
    "iso:country":"IN",
    "ks:ks_name":"Dasupuram",
    "ks:ks_pop":222,
    "ks:ks_type":"HABITATION",
    "name:eng_x_preferred":[
        "Dasupuram"
    ],
    "wof:name":"Dasupuram",
    "wof:placetype":"locality",
    "wof:population":222
},
  "geometry": {"coordinates":[84.312307,18.743603],"type":"Point"}
}