{
  "type": "Feature",
  "properties": {
    "iso:country":"IN",
    "name:ben_x_preferred":[
        "\u09ac\u0995\u0996\u09be\u09b2\u09bf"
    ],
    "name:dut_x_preferred":[
        "Bakkhali"
    ],
    "name:eng_x_preferred":[
        "Bakkhali"
    ],
    "name:fre_x_preferred":[
        "Bakkhali"
    ],
    "qs:name":"Bakkali",
    "qs:name_adm0":"India",
    "qs:name_adm1":"West Bengal",
    "qs:photos":147,
    "qs:photos_1k":30,
    "qs:photos_9k":1,
    "qs:photos_9r":3,
    "qs:photos_all":147,
    "qs:photos_sr":3,
    "qs:placetype":"Town",
    "qs:pop_sr":"0",
    "wof:name":"Bakkali",
    "wof:placetype":"locality"
},
  "geometry": {"coordinates":[88.250427,21.571368],"type":"Point"}
}