{
  "type": "Feature",
  "properties": {
    "gn:admin1_code":"34.0",
    "gn:admin2_code":"221.0",
    "gn:asciiname":"Hasanpur Kaiju",
    "gn:country_code":"IN",
    "gn:dem":52,
    "gn:feature_class":"P",
    "gn:feature_code":"PPL",
    "gn:name":"Hasanpur Kaiju",
    "gn:population":0,
    "gn:timezone":"Asia/Kolkata",
    "iso:country":"IN",
    "ks:ks_name":"Hasanpur Kainju",
    "ks:ks_pop":839,
    "ks:ks_type":"VILLAGE",
    "name:eng_x_preferred":[
        "Hasanpur Kainju"
    ],
    "name:eng_x_variant":[
        "Hasanpur Kaiju"
    ],
    "wof:name":"Hasanpur Kainju",
    "wof:placetype":"locality",
    "wof:population":839
},
  "geometry": {"coordinates":[85.61081299999999,25.833835],"type":"Point"}
}