{
  "type": "Feature",
  "properties": {
    "gn:admin1_code":"34.0",
    "gn:admin2_code":"221.0",
    "gn:asciiname":"Hasanpur Kaiju",
    "gn:country_code":"IN",
    "gn:dem":52,
    "gn:feature_class":"P",
    "gn:feature_code":"PPL",
    "gn:name":"Hasanpur Kaiju",
    "gn:population":0,
    "gn:timezone":"Asia/Kolkata",
    "iso:country":"IN",
    "wof:name":"Hasanpur Kaiju",
    "wof:placetype":"locality"
},
  "geometry": {"coordinates":[85.61395999999998,25.83063],"type":"Point"}
}