{
  "type": "Feature",
  "properties": {
    "iso:country":"IN",
    "ks:ks_name":"Kalia Pujariguda",
    "ks:ks_pop":280,
    "ks:ks_type":"VILLAGE",
    "name:eng_x_preferred":[
        "Kalia Pujariguda"
    ],
    "wof:name":"Kalia Pujariguda",
    "wof:placetype":"locality",
    "wof:population":280
},
  "geometry": {"coordinates":[82.107302,18.53139],"type":"Point"}
}