{
  "type": "Feature",
  "properties": {
    "gn:admin1_code":"25.0",
    "gn:admin2_code":"630.0",
    "gn:asciiname":"Nallampalli",
    "gn:country_code":"IN",
    "gn:dem":494,
    "gn:feature_class":"P",
    "gn:feature_code":"PPL",
    "gn:name":"Nallampalli",
    "gn:population":0,
    "gn:timezone":"Asia/Kolkata",
    "iso:country":"IN",
    "name:tam_x_preferred":[
        "\u0ba8\u0bb2\u0bcd\u0bb2\u0bae\u0bcd\u0baa\u0bb3\u0bcd\u0bb3\u0bbf"
    ],
    "wof:name":"Nallampalli",
    "wof:placetype":"locality"
},
  "geometry": {"coordinates":[78.11811,12.05747],"type":"Point"}
}