{
  "type": "Feature",
  "properties": {
    "iso:country":"IN",
    "ks:ks_alt_nam":"Halder and Goala Para",
    "ks:ks_name":"Halder And Goala Para",
    "ks:ks_pop":1015,
    "ks:ks_type":"HABITATION",
    "name:eng_x_preferred":[
        "Halder And Goala Para"
    ],
    "wof:name":"Halder And Goala Para",
    "wof:placetype":"locality",
    "wof:population":1015
},
  "geometry": {"coordinates":[88.13001,22.384533],"type":"Point"}
}