{
  "type": "Feature",
  "properties": {
    "gn:admin1_code":"36",
    "gn:admin2_code":"188.0",
    "gn:asciiname":"Marai",
    "gn:country_code":"IN",
    "gn:dem":82,
    "gn:feature_class":"P",
    "gn:feature_code":"PPL",
    "gn:name":"Marai",
    "gn:population":0,
    "gn:timezone":"Asia/Kolkata",
    "iso:country":"IN",
    "name:ceb_x_preferred":[
        "Marai"
    ],
    "name:deu_x_preferred":[
        "Marai"
    ],
    "name:swe_x_preferred":[
        "Marai"
    ],
    "wof:name":"Marai",
    "wof:placetype":"locality"
},
  "geometry": {"coordinates":[83.35379,26.50757],"type":"Point"}
}