{
  "type": "Feature",
  "properties": {
    "iso:country":"IN",
    "ks:ks_alt_nam":"Mallikolla tanda",
    "ks:ks_name":"Mallikolla Tanda",
    "ks:ks_pop":432,
    "ks:ks_type":"HABITATION",
    "name:eng_x_preferred":[
        "Mallikolla Tanda"
    ],
    "wof:name":"Mallikolla Tanda",
    "wof:placetype":"locality",
    "wof:population":432
},
  "geometry": {"coordinates":[77.088077,17.5417],"type":"Point"}
}