{
  "type": "Feature",
  "properties": {
    "iso:country":"IN",
    "ks:ks_name":"Turukdia",
    "ks:ks_pop":0,
    "ks:ks_type":"VILLAGE",
    "name:eng_x_preferred":[
        "Turukdia"
    ],
    "wof:name":"Turukdia",
    "wof:placetype":"locality",
    "wof:population":0
},
  "geometry": {"coordinates":[86.849828,25.11185],"type":"Point"}
}