{
  "type": "Feature",
  "properties": {
    "iso:country":"IN",
    "ks:ks_name":"Mahuliabad",
    "ks:ks_pop":0,
    "ks:ks_type":"VILLAGE",
    "name:eng_x_preferred":[
        "Mahuliabad"
    ],
    "wof:name":"Mahuliabad",
    "wof:placetype":"locality",
    "wof:population":0
},
  "geometry": {"coordinates":[86.712019,24.230414],"type":"Point"}
}