{
  "type": "Feature",
  "properties": {
    "iso:country":"IN",
    "ks:ks_name":"8 MGM",
    "ks:ks_pop":156,
    "ks:ks_type":"VILLAGE",
    "name:eng_x_preferred":[
        "8 MGM"
    ],
    "wof:name":"8 MGM",
    "wof:placetype":"locality",
    "wof:population":156
},
  "geometry": {"coordinates":[73.005804,28.843286],"type":"Point"}
}