{
  "type": "Feature",
  "properties": {
    "iso:country":"IN",
    "ks:ks_name":"Kalasanakoppa",
    "ks:ks_pop":679,
    "ks:ks_type":"VILLAGE",
    "name:eng_x_preferred":[
        "Kalasanakoppa"
    ],
    "wof:name":"Kalasanakoppa",
    "wof:placetype":"locality",
    "wof:population":679
},
  "geometry": {"coordinates":[74.956892,15.3318],"type":"Point"}
}