{
  "type": "Feature",
  "properties": {
    "iso:country":"IN",
    "ks:ks_name":"Tadhodi",
    "ks:ks_pop":809,
    "ks:ks_type":"VILLAGE",
    "name:eng_x_preferred":[
        "Tadhodi"
    ],
    "wof:name":"Tadhodi",
    "wof:placetype":"locality",
    "wof:population":809
},
  "geometry": {"coordinates":[72.68601700000001,24.239688],"type":"Point"}
}