{
  "type": "Feature",
  "properties": {
    "gn:admin1_code":"12.0",
    "gn:asciiname":"Tad",
    "gn:country_code":"IN",
    "gn:dem":1397,
    "gn:feature_class":"P",
    "gn:feature_code":"PPL",
    "gn:name":"Tad",
    "gn:population":0,
    "gn:timezone":"Asia/Kolkata",
    "iso:country":"IN",
    "name:deu_x_preferred":[
        "Tad"
    ],
    "name:fas_x_preferred":[
        "\u0637\u0627\u062f"
    ],
    "wof:name":"Tad",
    "wof:placetype":"locality"
},
  "geometry": {"coordinates":[73.81905,34.35425],"type":"Point"}
}