{
  "type": "Feature",
  "properties": {
    "iso:country":"IN",
    "name:bpy_x_preferred":[
        "\u099d\u09c1\u09b8\u09bf \u0995\u09cb\u09b9\u09be\u09a8\u09be"
    ],
    "name:eng_x_preferred":[
        "Jhusi Kohna"
    ],
    "name:fra_x_preferred":[
        "Jhusi Kohna"
    ],
    "name:ita_x_preferred":[
        "Jhusi Kohna"
    ],
    "name:msa_x_preferred":[
        "Jhusi Kohna"
    ],
    "name:nan_x_preferred":[
        "Jhusi Kohna"
    ],
    "name:new_x_preferred":[
        "\u091d\u0941\u0938\u0940 \u0915\u094b\u0939\u094d\u0928\u093e"
    ],
    "name:nld_x_preferred":[
        "Jhusi Kohna"
    ],
    "name:pol_x_preferred":[
        "Jhusi Kohna"
    ],
    "name:por_x_preferred":[
        "Jhusi Kohna"
    ],
    "name:urd_x_preferred":[
        "\u062c\u06be\u0648\u0633\u06cc \u06a9\u0648\u06c1\u0646\u0627"
    ],
    "name:vie_x_preferred":[
        "Jhusi Kohna"
    ],
    "name:zho_x_preferred":[
        "\u4e45\u897f\u79d1\u8d6b\u7eb3"
    ],
    "qs:name":"Jhusi Kohna",
    "qs:name_adm0":"India",
    "qs:name_adm1":"Uttar Pradesh",
    "qs:photos":53,
    "qs:photos_1k":11,
    "qs:photos_9k":1,
    "qs:photos_9r":4,
    "qs:photos_all":184,
    "qs:photos_sr":2,
    "qs:placetype":"Town",
    "qs:pop_sr":"0",
    "wd:wordcount":108,
    "wof:name":"Jhusi Kohna",
    "wof:placetype":"locality"
},
  "geometry": {"coordinates":[81.884536,25.430097],"type":"Point"}
}