{
  "type": "Feature",
  "properties": {
    "gn:admin1_code":"36.0",
    "gn:admin2_code":"149.0",
    "gn:asciiname":"Bazirganj",
    "gn:country_code":"IN",
    "gn:dem":184,
    "gn:feature_class":"P",
    "gn:feature_code":"PPL",
    "gn:name":"Baz\u012brganj",
    "gn:population":0,
    "gn:timezone":"Asia/Kolkata",
    "iso:country":"IN",
    "name:und_x_variant":[
        "Baz\u012brganj",
        "Mazra Kahrola"
    ],
    "wof:name":"Bazirganj",
    "wof:placetype":"locality"
},
  "geometry": {"coordinates":[78.34855,28.34377000000001],"type":"Point"}
}