{
  "type": "Feature",
  "properties": {
    "iso:country":"IN",
    "ks:ks_name":"Isampur",
    "ks:ks_pop":96,
    "ks:ks_type":"HABITATION",
    "name:eng_x_preferred":[
        "Isampur"
    ],
    "wof:name":"Isampur",
    "wof:placetype":"locality",
    "wof:population":96
},
  "geometry": {"coordinates":[83.16466,27.356714],"type":"Point"}
}