{
  "type": "Feature",
  "properties": {
    "iso:country":"IN",
    "ks:ks_name":"Simlachak Urf Phitkoriya",
    "ks:ks_pop":179,
    "ks:ks_type":"VILLAGE",
    "name:eng_x_preferred":[
        "Simlachak Urf Phitkoriya"
    ],
    "wof:name":"Simlachak Urf Phitkoriya",
    "wof:placetype":"locality",
    "wof:population":179
},
  "geometry": {"coordinates":[86.912451,24.153815],"type":"Point"}
}