{
  "type": "Feature",
  "properties": {
    "iso:country":"IN",
    "ks:ks_alt_nam":"IDER MAL",
    "ks:ks_name":"Ider Mal",
    "ks:ks_pop":150,
    "ks:ks_type":"HABITATION",
    "name:eng_x_preferred":[
        "Ider Mal"
    ],
    "wof:name":"Ider Mal",
    "wof:placetype":"locality",
    "wof:population":150
},
  "geometry": {"coordinates":[72.80246099999999,24.413019],"type":"Point"}
}