{
  "type": "Feature",
  "properties": {
    "iso:country":"IN",
    "ks:ks_name":"Momichapada",
    "ks:ks_pop":172,
    "ks:ks_type":"HABITATION",
    "name:eng_x_preferred":[
        "Momichapada"
    ],
    "wof:name":"Momichapada",
    "wof:placetype":"locality",
    "wof:population":172
},
  "geometry": {"coordinates":[73.013318,19.631009],"type":"Point"}
}