{
  "type": "Feature",
  "properties": {
    "gn:admin1_code":"25.0",
    "gn:admin2_code":"619.0",
    "gn:asciiname":"Kakkaiyadi",
    "gn:country_code":"IN",
    "gn:dem":19,
    "gn:feature_class":"P",
    "gn:feature_code":"PPL",
    "gn:name":"K\u0101kkaiy\u0101di",
    "gn:population":0,
    "gn:timezone":"Asia/Kolkata",
    "iso:country":"IN",
    "ks:ks_alt_nam":"K\u0101kkaiy\u0101di",
    "ks:ks_name":"Kakkaiyadi",
    "ks:ks_pop":1244,
    "ks:ks_type":"VILLAGE",
    "name:eng_x_preferred":[
        "Kakkaiyadi"
    ],
    "name:eng_x_variant":[
        "K\u0101kkaiy\u0101di"
    ],
    "wof:name":"Kakkaiyadi",
    "wof:placetype":"locality",
    "wof:population":1244
},
  "geometry": {"coordinates":[79.551484,10.693913],"type":"Point"}
}