{
  "type": "Feature",
  "properties": {
    "iso:country":"IN",
    "ks:ks_name":"Pujaripara 2",
    "ks:ks_pop":116,
    "ks:ks_type":"HABITATION",
    "name:eng_x_preferred":[
        "Pujaripara 2"
    ],
    "wof:name":"Pujaripara 2",
    "wof:placetype":"locality",
    "wof:population":116
},
  "geometry": {"coordinates":[82.156325,19.930267],"type":"Point"}
}