{
  "type": "Feature",
  "properties": {
    "gn:admin1_code":"35",
    "gn:admin2_code":"455.0",
    "gn:asciiname":"Saoli",
    "gn:country_code":"IN",
    "gn:dem":723,
    "gn:feature_class":"P",
    "gn:feature_code":"PPL",
    "gn:name":"Saoli",
    "gn:population":0,
    "gn:timezone":"Asia/Kolkata",
    "iso:country":"IN",
    "name:und_x_variant":[
        "S\u0101onli"
    ],
    "wof:name":"Saoli",
    "wof:placetype":"locality"
},
  "geometry": {"coordinates":[78.76737,21.96737000000001],"type":"Point"}
}