{
  "type": "Feature",
  "properties": {
    "iso:country":"IN",
    "ks:ks_name":"P Koppalu",
    "ks:ks_pop":729,
    "ks:ks_type":"HABITATION",
    "name:eng_x_preferred":[
        "P Koppalu"
    ],
    "wof:name":"P Koppalu",
    "wof:placetype":"locality",
    "wof:population":729
},
  "geometry": {"coordinates":[76.238643,12.365256],"type":"Point"}
}