{
  "type": "Feature",
  "properties": {
    "gn:admin1_code":"35.0",
    "gn:admin2_code":"440.0",
    "gn:asciiname":"Ramkola",
    "gn:country_code":"IN",
    "gn:dem":227,
    "gn:feature_class":"P",
    "gn:feature_code":"PPL",
    "gn:name":"R\u0101mkola",
    "gn:population":0,
    "gn:timezone":"Asia/Kolkata",
    "iso:country":"IN",
    "name:bpy_x_preferred":[
        "\u09b0\u09be\u09ae\u0995\u09cb\u09b2\u09be"
    ],
    "name:ceb_x_preferred":[
        "R\u0101mkola"
    ],
    "name:hin_x_preferred":[
        "\u0930\u093e\u092e\u0915\u094b\u0932\u093e"
    ],
    "name:ita_x_preferred":[
        "Ramkola"
    ],
    "name:msa_x_preferred":[
        "Ramkola"
    ],
    "name:nld_x_preferred":[
        "Ramkola"
    ],
    "name:pol_x_preferred":[
        "Ramkola"
    ],
    "name:por_x_preferred":[
        "Ramkola"
    ],
    "name:swe_x_preferred":[
        "R\u0101mkola"
    ],
    "name:urd_x_preferred":[
        "\u0631\u0627\u0645\u06a9\u0648\u0644\u0627"
    ],
    "name:vie_x_preferred":[
        "Ramkola"
    ],
    "name:zho_x_preferred":[
        "\u62c9\u59c6\u79d1\u62c9"
    ],
    "wof:name":"Ramkola",
    "wof:placetype":"neighbourhood"
},
  "geometry": {"coordinates":[76.05606,22.32958],"type":"Point"}
}