{
  "type": "Feature",
  "properties": {
    "iso:country":"IN",
    "ks:ks_name":"Mathadkeri",
    "ks:ks_pop":67,
    "ks:ks_type":"HABITATION",
    "name:eng_x_preferred":[
        "Mathadkeri"
    ],
    "wof:name":"Mathadkeri",
    "wof:placetype":"locality",
    "wof:population":67
},
  "geometry": {"coordinates":[74.80853999999999,14.741086],"type":"Point"}
}