{
  "type": "Feature",
  "properties": {
    "gn:admin1_code":"36",
    "gn:admin2_code":"194.0",
    "gn:asciiname":"Masora",
    "gn:country_code":"IN",
    "gn:dem":78,
    "gn:feature_class":"P",
    "gn:feature_code":"PPL",
    "gn:name":"Masor\u0101",
    "gn:population":0,
    "gn:timezone":"Asia/Kolkata",
    "iso:country":"IN",
    "wof:name":"Masora",
    "wof:placetype":"neighbourhood"
},
  "geometry": {"coordinates":[82.94136,25.61733],"type":"Point"}
}