{
  "type": "Feature",
  "properties": {
    "gn:admin1_code":"09",
    "gn:admin2_code":"485.0",
    "gn:asciiname":"Randhikpur",
    "gn:country_code":"IN",
    "gn:dem":203,
    "gn:feature_class":"P",
    "gn:feature_code":"PPL",
    "gn:name":"Randhikpur",
    "gn:population":0,
    "gn:timezone":"Asia/Kolkata",
    "iso:country":"IN",
    "wof:name":"Randhikpur",
    "wof:placetype":"locality"
},
  "geometry": {"coordinates":[73.96419,22.9716],"type":"Point"}
}