{
  "type": "Feature",
  "properties": {
    "iso:country":"IN",
    "ks:ks_name":"Kuihar",
    "ks:ks_pop":809,
    "ks:ks_type":"HABITATION",
    "name:eng_x_preferred":[
        "Kuihar"
    ],
    "wof:name":"Kuihar",
    "wof:placetype":"neighbourhood",
    "wof:population":809
},
  "geometry": {"coordinates":[80.349141,26.345736],"type":"Point"}
}