{
  "type": "Feature",
  "properties": {
    "gn:admin1_code":"16.0",
    "gn:admin2_code":"514.0",
    "gn:asciiname":"Gadegayhan",
    "gn:country_code":"IN",
    "gn:dem":569,
    "gn:feature_class":"P",
    "gn:feature_code":"PPL",
    "gn:name":"G\u0101degayh\u0101n",
    "gn:population":0,
    "gn:timezone":"Asia/Kolkata",
    "iso:country":"IN",
    "wof:name":"Gadegayhan",
    "wof:placetype":"locality"
},
  "geometry": {"coordinates":[75.92775999999998,20.11854],"type":"Point"}
}