{
  "type": "Feature",
  "properties": {
    "iso:country":"IN",
    "ks:ks_alt_nam":"chellanam south",
    "ks:ks_name":"Chellanam South",
    "ks:ks_pop":2322,
    "ks:ks_type":"HABITATION",
    "name:eng_x_preferred":[
        "Chellanam South"
    ],
    "wof:name":"Chellanam South",
    "wof:placetype":"locality",
    "wof:population":2322
},
  "geometry": {"coordinates":[76.280861,9.801745],"type":"Point"}
}