{
  "type": "Feature",
  "properties": {
    "iso:country":"IN",
    "ks:ks_name":"Mojaka Tola",
    "ks:ks_pop":594,
    "ks:ks_type":"HABITATION",
    "ks:ks_uagg_main":0,
    "name:eng_x_preferred":[
        "Mojaka Tola"
    ],
    "wof:name":"Mojaka Tola",
    "wof:placetype":"neighbourhood",
    "wof:population":594
},
  "geometry": {"coordinates":[84.832446,25.44206],"type":"Point"}
}