{
  "type": "Feature",
  "properties": {
    "iso:country":"IN",
    "ks:ks_name":"Khokhar South",
    "ks:ks_pop":99,
    "ks:ks_type":"VILLAGE",
    "name:eng_x_preferred":[
        "Khokhar South"
    ],
    "wof:name":"Khokhar South",
    "wof:placetype":"locality",
    "wof:population":99
},
  "geometry": {"coordinates":[72.051158,26.268042],"type":"Point"}
}