{
  "type": "Feature",
  "properties": {
    "gn:population":118259,
    "iso:country":"IN",
    "name:bpy_x_preferred":[
        "\u0989\u09aa\u09b2 \u0995\u09be\u09b2\u09a8"
    ],
    "name:ceb_x_preferred":[
        "Uppal Kalan"
    ],
    "name:eng_x_preferred":[
        "Uppal Kalan"
    ],
    "name:ita_x_preferred":[
        "Uppal Kalan"
    ],
    "name:msa_x_preferred":[
        "Uppal Kalan"
    ],
    "name:nld_x_preferred":[
        "Uppal Kalan"
    ],
    "name:ori_x_preferred":[
        "\u0b09\u0b2a\u0b4d\u0b2a\u0b33 \u0b15\u0b3e\u0b32\u0b3e\u0b28"
    ],
    "name:por_x_preferred":[
        "Uppal Kalan"
    ],
    "name:swe_x_preferred":[
        "Uppal Kalan"
    ],
    "name:tel_x_preferred":[
        "\u0c09\u0c2a\u0c4d\u0c2a\u0c32\u0c4d"
    ],
    "name:unk_x_variant":[
        "Pedda Uppal",
        "Uppal Kalan"
    ],
    "name:urd_x_preferred":[
        "\u0627\u067e\u0644 \u06a9\u0644\u0627\u06ba"
    ],
    "name:vie_x_preferred":[
        "Uppal Kalan"
    ],
    "name:zho_x_preferred":[
        "\u4e4c\u666e\u5e15\u5c14\u5361\u5170"
    ],
    "qs:gn_adm0_cc":"IN",
    "qs:gn_fcode":"PPL",
    "qs:gn_local":1269843,
    "qs:gn_namadm1":"02",
    "qs:gn_name":"Uppal Kalan",
    "qs:local_max":1198,
    "qs:local_sum":10545,
    "qs:localhoods":56,
    "qs:name":"Uppal Kalan",
    "qs:name_adm0":"India",
    "qs:name_adm1":"Andhra Pradesh",
    "qs:name_adm2":"Rangareddi",
    "qs:name_local":"Hyderabad",
    "qs:photo_max":2,
    "qs:photo_sum":8,
    "qs:placetype":"Suburb",
    "qs:quad_count":4,
    "qs:woe_adm0":23424848,
    "qs:woe_adm1":2345740,
    "qs:woe_adm2":12586344,
    "qs:woe_lau":0,
    "qs:woe_local":2295414,
    "qs:woe_ver":"7.10.0",
    "wd:wordcount":300,
    "wof:lang":[
        "eng"
    ],
    "wof:name":"Uppal Kalan",
    "wof:placetype":"neighbourhood",
    "wof:population":118259
},
  "geometry": {"coordinates":[78.574219,17.392579],"type":"Point"}
}