{
  "type": "Feature",
  "properties": {
    "iso:country":"IN",
    "ks:ks_name":"Patangagudi",
    "ks:ks_pop":79,
    "ks:ks_type":"VILLAGE",
    "name:eng_x_preferred":[
        "Patangagudi"
    ],
    "wof:name":"Patangagudi",
    "wof:placetype":"locality",
    "wof:population":79
},
  "geometry": {"coordinates":[83.582127,19.590609],"type":"Point"}
}