{
  "type": "Feature",
  "properties": {
    "iso:country":"IN",
    "ks:ks_name":"Raheri Kh.",
    "ks:ks_pop":604,
    "ks:ks_type":"VILLAGE",
    "name:eng_x_preferred":[
        "Raheri Kh."
    ],
    "wof:name":"Raheri Kh.",
    "wof:placetype":"locality",
    "wof:population":604
},
  "geometry": {"coordinates":[76.262072,20.003329],"type":"Point"}
}