{
  "type": "Feature",
  "properties": {
    "iso:country":"IN",
    "ks:ks_name":"Rasuladangi",
    "ks:ks_pop":697,
    "ks:ks_type":"HABITATION",
    "name:eng_x_preferred":[
        "Rasuladangi"
    ],
    "wof:name":"Rasuladangi",
    "wof:placetype":"locality",
    "wof:population":697
},
  "geometry": {"coordinates":[88.307197,26.290872],"type":"Point"}
}