{
  "type": "Feature",
  "properties": {
    "gn:admin1_code":"1.0",
    "gn:admin2_code":"638.0",
    "gn:asciiname":"Changua",
    "gn:country_code":"IN",
    "gn:dem":128,
    "gn:feature_class":"P",
    "gn:feature_code":"PPL",
    "gn:name":"Changua",
    "gn:population":0,
    "gn:timezone":"Asia/Kolkata",
    "iso:country":"IN",
    "name:glg_x_preferred":[
        "Changua"
    ],
    "name:spa_x_preferred":[
        "Changua"
    ],
    "name:tam_x_preferred":[
        "\u0b9a\u0ba9\u0bcd\u0b95\u0bc1\u0bb5\u0bbe"
    ],
    "wof:name":"Changua",
    "wof:placetype":"locality"
},
  "geometry": {"coordinates":[93.4952,8.02902],"type":"Point"}
}