{
  "type": "Feature",
  "properties": {
    "gn:admin1_code":"19.0",
    "gn:admin2_code":"582.0",
    "gn:asciiname":"Kanaganhalli",
    "gn:country_code":"IN",
    "gn:dem":954,
    "gn:feature_class":"P",
    "gn:feature_code":"PPL",
    "gn:name":"Kanaganhalli",
    "gn:population":0,
    "gn:timezone":"Asia/Kolkata",
    "iso:country":"IN",
    "wof:name":"Kanaganhalli",
    "wof:placetype":"locality"
},
  "geometry": {"coordinates":[77.64174,13.40343],"type":"Point"}
}