{
  "type": "Feature",
  "properties": {
    "iso:country":"IN",
    "ks:ks_name":"Pure Thakur Ram Tiwari Ka Pura",
    "ks:ks_pop":50,
    "ks:ks_type":"HABITATION",
    "ks:ks_uagg_main":0,
    "name:eng_x_preferred":[
        "Pure Thakur Ram Tiwari Ka Pura"
    ],
    "wof:name":"Pure Thakur Ram Tiwari Ka Pura",
    "wof:placetype":"neighbourhood",
    "wof:population":50
},
  "geometry": {"coordinates":[81.70939799999999,26.333472],"type":"Point"}
}