{
  "type": "Feature",
  "properties": {
    "gn:admin1_code":"35",
    "gn:admin2_code":"428.0",
    "gn:asciiname":"Naiagaon",
    "gn:country_code":"IN",
    "gn:dem":343,
    "gn:feature_class":"P",
    "gn:feature_code":"PPL",
    "gn:name":"Nai\u0101gaon",
    "gn:population":0,
    "gn:timezone":"Asia/Kolkata",
    "iso:country":"IN",
    "name:und_x_variant":[
        "Nai\u0101gaon",
        "Dharka"
    ],
    "wof:name":"Naiagaon",
    "wof:placetype":"locality"
},
  "geometry": {"coordinates":[79.64501,23.73347],"type":"Point"}
}