{
  "type": "Feature",
  "properties": {
    "iso:country":"IN",
    "ks:ks_name":"Kottayapatti",
    "ks:ks_pop":152,
    "ks:ks_type":"HABITATION",
    "name:eng_x_preferred":[
        "Kottayapatti"
    ],
    "wof:name":"Kottayapatti",
    "wof:placetype":"locality",
    "wof:population":152
},
  "geometry": {"coordinates":[78.716475,10.278478],"type":"Point"}
}