{
  "type": "Feature",
  "properties": {
    "iso:country":"IN",
    "ks:ks_name":"Dudi Marwari",
    "ks:ks_pop":560,
    "ks:ks_type":"HABITATION",
    "name:eng_x_preferred":[
        "Dudi Marwari"
    ],
    "wof:name":"Dudi Marwari",
    "wof:placetype":"locality",
    "wof:population":560
},
  "geometry": {"coordinates":[80.317487,23.449739],"type":"Point"}
}