{
  "type": "Feature",
  "properties": {
    "iso:country":"IN",
    "ks:ks_name":"Barandahalli",
    "ks:ks_pop":416,
    "ks:ks_type":"VILLAGE",
    "ks:ks_uagg_main":0,
    "name:eng_x_preferred":[
        "Barandahalli"
    ],
    "wof:name":"Barandahalli",
    "wof:placetype":"neighbourhood",
    "wof:population":416
},
  "geometry": {"coordinates":[78.140902,13.162341],"type":"Point"}
}