{
  "type": "Feature",
  "properties": {
    "iso:country":"IN",
    "ks:ks_name":"Badi",
    "ks:ks_pop":223,
    "ks:ks_type":"HABITATION",
    "name:eng_x_preferred":[
        "Badi"
    ],
    "wof:name":"Badi",
    "wof:placetype":"locality",
    "wof:population":223
},
  "geometry": {"coordinates":[76.428528,22.716576],"type":"Point"}
}