{
  "type": "Feature",
  "properties": {
    "iso:country":"IN",
    "ks:ks_name":"Dam Gurha",
    "ks:ks_pop":148,
    "ks:ks_type":"HABITATION",
    "name:eng_x_preferred":[
        "Dam Gurha"
    ],
    "wof:name":"Dam Gurha",
    "wof:placetype":"locality",
    "wof:population":148
},
  "geometry": {"coordinates":[86.23014999999999,24.021367],"type":"Point"}
}