{
  "type": "Feature",
  "properties": {
    "iso:country":"IN",
    "ks:ks_name":"Chakamani",
    "ks:ks_pop":0,
    "ks:ks_type":"VILLAGE",
    "name:eng_x_preferred":[
        "Chakamani"
    ],
    "wof:name":"Chakamani",
    "wof:placetype":"locality",
    "wof:population":0
},
  "geometry": {"coordinates":[87.226128,21.78198],"type":"Point"}
}