{
  "type": "Feature",
  "properties": {
    "iso:country":"IN",
    "ks:ks_name":"Mohammadpur",
    "ks:ks_pop":191,
    "ks:ks_type":"VILLAGE",
    "ks:ks_uagg_main":0,
    "name:eng_x_preferred":[
        "Mohammadpur"
    ],
    "wof:name":"Mohammadpur",
    "wof:placetype":"neighbourhood",
    "wof:population":191
},
  "geometry": {"coordinates":[85.063756,25.128563],"type":"Point"}
}