{
  "type": "Feature",
  "properties": {
    "iso:country":"IN",
    "ks:ks_name":"Hatpara",
    "ks:ks_pop":176,
    "ks:ks_type":"VILLAGE",
    "name:eng_x_preferred":[
        "Hatpara"
    ],
    "wof:name":"Hatpara",
    "wof:placetype":"locality",
    "wof:population":176
},
  "geometry": {"coordinates":[88.134514,24.367595],"type":"Point"}
}