{
  "type": "Feature",
  "properties": {
    "iso:country":"IN",
    "ks:ks_name":"Rudravat",
    "ks:ks_pop":290,
    "ks:ks_type":"VILLAGE",
    "name:eng_x_preferred":[
        "Rudravat"
    ],
    "wof:name":"Rudravat",
    "wof:placetype":"locality",
    "wof:population":290
},
  "geometry": {"coordinates":[73.125581,18.08071],"type":"Point"}
}