{
  "type": "Feature",
  "properties": {
    "iso:country":"IN",
    "ks:ks_name":"Baghadangar",
    "ks:ks_pop":143,
    "ks:ks_type":"VILLAGE",
    "name:eng_x_preferred":[
        "Baghadangar"
    ],
    "wof:name":"Baghadangar",
    "wof:placetype":"locality",
    "wof:population":143
},
  "geometry": {"coordinates":[83.366924,19.453252],"type":"Point"}
}