{
  "type": "Feature",
  "properties": {
    "iso:country":"IN",
    "ks:ks_name":"Kumharwara",
    "ks:ks_pop":366,
    "ks:ks_type":"VILLAGE",
    "ks:ks_uagg_main":0,
    "name:eng_x_preferred":[
        "Kumharwara"
    ],
    "wof:name":"Kumharwara",
    "wof:placetype":"neighbourhood",
    "wof:population":366
},
  "geometry": {"coordinates":[73.46637800000001,24.092397],"type":"Point"}
}