{
  "type": "Feature",
  "properties": {
    "iso:country":"IN",
    "ks:ks_name":"Kurunjkhol",
    "ks:ks_pop":201,
    "ks:ks_type":"VILLAGE",
    "name:eng_x_preferred":[
        "Kurunjkhol"
    ],
    "wof:name":"Kurunjkhol",
    "wof:placetype":"locality",
    "wof:population":201
},
  "geometry": {"coordinates":[83.390404,22.297244],"type":"Point"}
}