{
  "type": "Feature",
  "properties": {
    "iso:country":"IN",
    "ks:ks_name":"Badaraghunathpur",
    "ks:ks_pop":425,
    "ks:ks_type":"VILLAGE",
    "ks:ks_uagg_main":0,
    "name:eng_x_preferred":[
        "Badaraghunathpur"
    ],
    "wof:name":"Badaraghunathpur",
    "wof:placetype":"neighbourhood",
    "wof:population":425
},
  "geometry": {"coordinates":[85.728053,20.236402],"type":"Point"}
}