{
  "type": "Feature",
  "properties": {
    "iso:country":"IN",
    "ks:ks_name":"Mirzapur Kesho",
    "ks:ks_pop":0,
    "ks:ks_type":"VILLAGE",
    "name:eng_x_preferred":[
        "Mirzapur Kesho"
    ],
    "wof:name":"Mirzapur Kesho",
    "wof:placetype":"locality",
    "wof:population":0
},
  "geometry": {"coordinates":[78.17415699999999,29.38341],"type":"Point"}
}