{
  "type": "Feature",
  "properties": {
    "iso:country":"IN",
    "ks:ks_name":"Naugaon",
    "ks:ks_pop":62,
    "ks:ks_type":"VILLAGE",
    "name:eng_x_preferred":[
        "Naugaon"
    ],
    "wof:name":"Naugaon",
    "wof:placetype":"locality",
    "wof:population":62
},
  "geometry": {"coordinates":[79.10015799999999,30.244367],"type":"Point"}
}