{
  "type": "Feature",
  "properties": {
    "iso:country":"IN",
    "ks:ks_name":"Basavannapadavalu",
    "ks:ks_pop":34,
    "ks:ks_type":"HABITATION",
    "name:eng_x_preferred":[
        "Basavannapadavalu"
    ],
    "wof:name":"Basavannapadavalu",
    "wof:placetype":"locality",
    "wof:population":34
},
  "geometry": {"coordinates":[77.875647,15.200867],"type":"Point"}
}