{
  "type": "Feature",
  "properties": {
    "iso:country":"IN",
    "ks:ks_name":"Bahulya",
    "ks:ks_pop":489,
    "ks:ks_type":"VILLAGE",
    "ks:ks_uagg_main":0,
    "name:eng_x_preferred":[
        "Bahulya"
    ],
    "wof:name":"Bahulya",
    "wof:placetype":"neighbourhood",
    "wof:population":489
},
  "geometry": {"coordinates":[87.660025,21.854094],"type":"Point"}
}