{
  "type": "Feature",
  "properties": {
    "iso:country":"IN",
    "ks:ks_name":"Jarabandahalli",
    "ks:ks_type":"VILLAGE",
    "name:eng_x_preferred":[
        "Jarabandahalli"
    ],
    "wof:name":"Jarabandahalli",
    "wof:placetype":"locality"
},
  "geometry": {"coordinates":[77.53313199999999,13.687058],"type":"Point"}
}