{
  "type": "Feature",
  "properties": {
    "gn:admin1_code":"23.0",
    "gn:admin2_code":"51.0",
    "gn:asciiname":"Majri",
    "gn:country_code":"IN",
    "gn:dem":278,
    "gn:feature_class":"P",
    "gn:feature_code":"PPL",
    "gn:name":"M\u0101jri",
    "gn:population":0,
    "gn:timezone":"Asia/Kolkata",
    "iso:country":"IN",
    "name:ara_x_preferred":[
        "\u0645\u0627\u062c\u0631\u064a"
    ],
    "name:ben_bn_x_preferred":[
        "\u09ae\u09be\u099c\u09b0\u09bf"
    ],
    "name:ben_in_x_preferred":[
        "\u09ae\u09be\u099c\u09b0\u09bf"
    ],
    "name:guj_x_preferred":[
        "\u0aae\u0a9c\u0ab0\u0ac0"
    ],
    "name:hin_x_preferred":[
        "\u092e\u093e\u091c\u0930\u0940"
    ],
    "name:kan_x_preferred":[
        "\u0cae\u0c9c\u0ccd\u0cb0\u0cbf"
    ],
    "name:mal_x_preferred":[
        "\u0d2e\u0d1c\u0d4d\u0d30\u0d3f"
    ],
    "name:mar_x_preferred":[
        "\u092e\u093e\u091c\u0930\u0940"
    ],
    "name:pan_x_preferred":[
        "\u0a2e\u0a3e\u0a1c\u0a30\u0a40"
    ],
    "name:tam_x_preferred":[
        "\u0bae\u0b9c\u0bcd\u0bb0\u0bbf"
    ],
    "name:tel_x_preferred":[
        "\u0c2e\u0c1c\u0c4d\u0c30\u0c3f"
    ],
    "name:urd_x_preferred":[
        "\u0645\u062c\u0631\u06cc"
    ],
    "wof:name":"Majri",
    "wof:placetype":"locality"
},
  "geometry": {"coordinates":[76.43131,30.82531],"type":"Point"}
}