{
  "type": "Feature",
  "properties": {
    "iso:country":"IN",
    "ks:ks_name":"Dhoomsagar",
    "ks:ks_pop":465,
    "ks:ks_type":"VILLAGE",
    "name:eng_x_preferred":[
        "Dhoomsagar"
    ],
    "wof:name":"Dhoomsagar",
    "wof:placetype":"locality",
    "wof:population":465
},
  "geometry": {"coordinates":[72.23606100000001,26.226653],"type":"Point"}
}