{
  "type": "Feature",
  "properties": {
    "iso:country":"IN",
    "ks:ks_name":"Sea Bird Colony",
    "ks:ks_pop":92,
    "ks:ks_type":"HABITATION",
    "name:eng_x_preferred":[
        "Sea Bird Colony"
    ],
    "wof:name":"Sea Bird Colony",
    "wof:placetype":"locality",
    "wof:population":92
},
  "geometry": {"coordinates":[74.285516,14.712021],"type":"Point"}
}