{
  "type": "Feature",
  "properties": {
    "gn:admin1_code":"34.0",
    "gn:admin2_code":"222.0",
    "gn:asciiname":"Bala Chak",
    "gn:country_code":"IN",
    "gn:dem":46,
    "gn:feature_class":"P",
    "gn:feature_code":"PPL",
    "gn:name":"B\u0101la Chak",
    "gn:population":0,
    "gn:timezone":"Asia/Kolkata",
    "iso:country":"IN",
    "ks:ks_alt_nam":"B\u0101la Chak",
    "ks:ks_name":"Bala Chak",
    "ks:ks_pop":1675,
    "ks:ks_type":"VILLAGE",
    "ks:ks_uagg_main":0,
    "name:eng_x_preferred":[
        "Bala Chak"
    ],
    "name:eng_x_variant":[
        "B\u0101la Chak"
    ],
    "wof:name":"Bala Chak",
    "wof:placetype":"neighbourhood",
    "wof:population":1675
},
  "geometry": {"coordinates":[86.290673,25.413252],"type":"Point"}
}