{
  "type": "Feature",
  "properties": {
    "iso:country":"IN",
    "ks:ks_name":"Shekh Parsa",
    "ks:ks_pop":1005,
    "ks:ks_type":"VILLAGE",
    "ks:ks_uagg_main":0,
    "name:eng_x_preferred":[
        "Shekh Parsa"
    ],
    "wof:name":"Shekh Parsa",
    "wof:placetype":"locality",
    "wof:population":1005
},
  "geometry": {"coordinates":[84.493365,26.374748],"type":"Point"}
}