{
  "type": "Feature",
  "properties": {
    "iso:country":"IN",
    "ks:ks_name":"Chikapanasa",
    "ks:ks_pop":348,
    "ks:ks_type":"HABITATION",
    "name:eng_x_preferred":[
        "Chikapanasa"
    ],
    "wof:name":"Chikapanasa",
    "wof:placetype":"locality",
    "wof:population":348
},
  "geometry": {"coordinates":[81.656638,17.938292],"type":"Point"}
}