{
  "type": "Feature",
  "properties": {
    "iso:country":"IN",
    "ks:ks_name":"Dumuripadar",
    "ks:ks_pop":36,
    "ks:ks_type":"HABITATION",
    "name:eng_x_preferred":[
        "Dumuripadar"
    ],
    "wof:name":"Dumuripadar",
    "wof:placetype":"locality",
    "wof:population":36
},
  "geometry": {"coordinates":[83.07583200000001,18.817087],"type":"Point"}
}