{
  "type": "Feature",
  "properties": {
    "iso:country":"IN",
    "ks:ks_name":"Daberi",
    "ks:ks_pop":2,
    "ks:ks_type":"HABITATION",
    "name:eng_x_preferred":[
        "Daberi"
    ],
    "wof:name":"Daberi",
    "wof:placetype":"locality",
    "wof:population":2
},
  "geometry": {"coordinates":[83.916766,20.564073],"type":"Point"}
}