{
  "type": "Feature",
  "properties": {
    "iso:country":"IN",
    "ks:ks_name":"Kudlurchettalli",
    "ks:ks_pop":1254,
    "ks:ks_type":"VILLAGE",
    "name:eng_x_preferred":[
        "Kudlurchettalli"
    ],
    "wof:name":"Kudlurchettalli",
    "wof:placetype":"locality",
    "wof:population":1254
},
  "geometry": {"coordinates":[75.852214,12.373343],"type":"Point"}
}