{
  "type": "Feature",
  "properties": {
    "iso:country":"IN",
    "ks:ks_name":"Uparabalan Tarakhara",
    "ks:ks_pop":1,
    "ks:ks_type":"VILLAGE",
    "name:eng_x_preferred":[
        "Uparabalan Tarakhara"
    ],
    "wof:name":"Uparabalan Tarakhara",
    "wof:placetype":"locality",
    "wof:population":1
},
  "geometry": {"coordinates":[85.163325,19.643732],"type":"Point"}
}