{
  "type": "Feature",
  "properties": {
    "gn:admin1_code":"9.0",
    "gn:admin2_code":"482.0",
    "gn:asciiname":"Kasor",
    "gn:country_code":"IN",
    "gn:dem":34,
    "gn:feature_class":"P",
    "gn:feature_code":"PPL",
    "gn:name":"Kasor",
    "gn:population":0,
    "gn:timezone":"Asia/Kolkata",
    "iso:country":"IN",
    "wof:name":"Kasor",
    "wof:placetype":"locality"
},
  "geometry": {"coordinates":[72.77360999999998,22.55029],"type":"Point"}
}