{
  "type": "Feature",
  "properties": {
    "gn:admin1_code":"36",
    "gn:admin2_code":"146.0",
    "gn:asciiname":"Kaheri",
    "gn:country_code":"IN",
    "gn:dem":160,
    "gn:feature_class":"P",
    "gn:feature_code":"PPL",
    "gn:name":"Kaheri",
    "gn:population":0,
    "gn:timezone":"Asia/Kolkata",
    "iso:country":"IN",
    "ks:ks_name":"Kahedi",
    "ks:ks_pop":935,
    "ks:ks_type":"HABITATION",
    "name:eng_x_preferred":[
        "Kahedi"
    ],
    "name:eng_x_variant":[
        "Kaheri"
    ],
    "wof:name":"Kahedi",
    "wof:placetype":"locality",
    "wof:population":935
},
  "geometry": {"coordinates":[78.222938,26.856979],"type":"Point"}
}