{
  "type": "Feature",
  "properties": {
    "iso:country":"IN",
    "ks:ks_name":"Mansakata Bharat Chak",
    "ks:ks_pop":362,
    "ks:ks_type":"VILLAGE",
    "name:eng_x_preferred":[
        "Mansakata Bharat Chak"
    ],
    "wof:name":"Mansakata Bharat Chak",
    "wof:placetype":"locality",
    "wof:population":362
},
  "geometry": {"coordinates":[87.990876,22.056926],"type":"Point"}
}