{
  "type": "Feature",
  "properties": {
    "iso:country":"IN",
    "ks:ks_name":"Garudamuthur",
    "ks:ks_pop":660,
    "ks:ks_type":"HABITATION",
    "name:eng_x_preferred":[
        "Garudamuthur"
    ],
    "wof:name":"Garudamuthur",
    "wof:placetype":"locality",
    "wof:population":660
},
  "geometry": {"coordinates":[77.342597,10.872354],"type":"Point"}
}