{
  "type": "Feature",
  "properties": {
    "iso:country":"IN",
    "ks:ks_name":"Hainhole",
    "ks:ks_pop":191,
    "ks:ks_type":"HABITATION",
    "name:eng_x_preferred":[
        "Hainhole"
    ],
    "wof:name":"Hainhole",
    "wof:placetype":"locality",
    "wof:population":191
},
  "geometry": {"coordinates":[74.564966,14.046983],"type":"Point"}
}