{
  "type": "Feature",
  "properties": {
    "gn:admin1_code":"36.0",
    "gn:admin2_code":"193",
    "gn:asciiname":"Aundi",
    "gn:country_code":"IN",
    "gn:dem":67,
    "gn:feature_class":"P",
    "gn:feature_code":"PPL",
    "gn:name":"Aund\u012b",
    "gn:population":0,
    "gn:timezone":"Asia/Kolkata",
    "iso:country":"IN",
    "name:und_x_variant":[
        "Aund\u012b",
        "Aundi"
    ],
    "wof:name":"Aundi",
    "wof:placetype":"locality"
},
  "geometry": {"coordinates":[83.97984,25.79987],"type":"Point"}
}