{
  "type": "Feature",
  "properties": {
    "gn:admin1_code":"23.0",
    "gn:admin2_code":"35.0",
    "gn:asciiname":"Chhina",
    "gn:country_code":"IN",
    "gn:dem":252,
    "gn:feature_class":"P",
    "gn:feature_code":"PPL",
    "gn:name":"Chhina",
    "gn:population":0,
    "gn:timezone":"Asia/Kolkata",
    "iso:country":"IN",
    "name:hin_x_preferred":[
        "\u091b\u0940\u0928\u093e"
    ],
    "wof:name":"Chhina",
    "wof:placetype":"locality"
},
  "geometry": {"coordinates":[75.27115999999999,31.89959],"type":"Point"}
}