{
  "type": "Feature",
  "properties": {
    "gn:admin1_code":"34.0",
    "gn:admin2_code":"229.0",
    "gn:asciiname":"Sirsi",
    "gn:country_code":"IN",
    "gn:dem":53,
    "gn:feature_class":"P",
    "gn:feature_code":"PPL",
    "gn:name":"Sirsi",
    "gn:population":0,
    "gn:timezone":"Asia/Kolkata",
    "iso:country":"IN",
    "name:ceb_x_preferred":[
        "Sirsi"
    ],
    "name:pol_x_preferred":[
        "Sirsi"
    ],
    "name:swe_x_preferred":[
        "Sirsi"
    ],
    "name:vie_x_preferred":[
        "Sirsi"
    ],
    "wof:name":"Sirsi",
    "wof:placetype":"locality"
},
  "geometry": {"coordinates":[85.48408000000001,25.4022],"type":"Point"}
}