{
  "type": "Feature",
  "properties": {
    "iso:country":"IN",
    "ks:ks_name":"Pandua",
    "ks:ks_pop":563,
    "ks:ks_type":"HABITATION",
    "name:eng_x_preferred":[
        "Pandua"
    ],
    "wof:name":"Pandua",
    "wof:placetype":"locality",
    "wof:population":563
},
  "geometry": {"coordinates":[85.134952,22.679363],"type":"Point"}
}