{
  "type": "Feature",
  "properties": {
    "iso:country":"IN",
    "ks:ks_name":"Negi Gaon",
    "ks:ks_pop":32,
    "ks:ks_type":"VILLAGE",
    "ks:ks_uagg_main":0,
    "name:eng_x_preferred":[
        "Negi Gaon"
    ],
    "wof:name":"Negi Gaon",
    "wof:placetype":"neighbourhood",
    "wof:population":32
},
  "geometry": {"coordinates":[79.319855,29.40739],"type":"Point"}
}