{
  "type": "Feature",
  "properties": {
    "iso:country":"IN",
    "ks:ks_alt_nam":"1 SAH TOLA",
    "ks:ks_name":"1 Sah Tola",
    "ks:ks_pop":360,
    "ks:ks_type":"HABITATION",
    "ks:ks_uagg_main":0,
    "name:eng_x_preferred":[
        "1 Sah Tola"
    ],
    "wof:name":"1 Sah Tola",
    "wof:placetype":"neighbourhood",
    "wof:population":360
},
  "geometry": {"coordinates":[87.42283399999999,25.951389],"type":"Point"}
}