{
  "type": "Feature",
  "properties": {
    "iso:country":"IN",
    "ks:ks_alt_nam":"KHIKHIRTOLI",
    "ks:ks_name":"Khikhirtoli",
    "ks:ks_pop":125,
    "ks:ks_type":"HABITATION",
    "name:eng_x_preferred":[
        "Khikhirtoli"
    ],
    "wof:name":"Khikhirtoli",
    "wof:placetype":"locality",
    "wof:population":125
},
  "geometry": {"coordinates":[83.733543,23.104185],"type":"Point"}
}