{
  "type": "Feature",
  "properties": {
    "gn:admin1_code":"19.0",
    "gn:admin2_code":"583.0",
    "gn:asciiname":"Bhimaravatanhalli",
    "gn:country_code":"IN",
    "gn:dem":921,
    "gn:feature_class":"P",
    "gn:feature_code":"PPL",
    "gn:name":"Bhimar\u0101vatanhalli",
    "gn:population":0,
    "gn:timezone":"Asia/Kolkata",
    "iso:country":"IN",
    "wof:name":"Bhimaravatanhalli",
    "wof:placetype":"locality"
},
  "geometry": {"coordinates":[77.4042,13.3266],"type":"Point"}
}