{
  "type": "Feature",
  "properties": {
    "iso:country":"IN",
    "ks:ks_alt_nam":"Thakarwadi madhali",
    "ks:ks_name":"Thakarwadi Madhali",
    "ks:ks_pop":255,
    "ks:ks_type":"HABITATION",
    "name:eng_x_preferred":[
        "Thakarwadi Madhali"
    ],
    "wof:name":"Thakarwadi Madhali",
    "wof:placetype":"locality",
    "wof:population":255
},
  "geometry": {"coordinates":[73.78486100000001,18.942841],"type":"Point"}
}