{
  "type": "Feature",
  "properties": {
    "iso:country":"IN",
    "ks:ks_name":"Kataiya",
    "ks:ks_pop":97,
    "ks:ks_type":"VILLAGE",
    "name:eng_x_preferred":[
        "Kataiya"
    ],
    "wof:name":"Kataiya",
    "wof:placetype":"locality",
    "wof:population":97
},
  "geometry": {"coordinates":[80.072653,23.341804],"type":"Point"}
}