{
  "type": "Feature",
  "properties": {
    "iso:country":"IN",
    "ks:ks_name":"Arasinahdlu",
    "ks:ks_pop":65,
    "ks:ks_type":"HABITATION",
    "name:eng_x_preferred":[
        "Arasinahdlu"
    ],
    "wof:name":"Arasinahdlu",
    "wof:placetype":"locality",
    "wof:population":65
},
  "geometry": {"coordinates":[75.362908,13.318883],"type":"Point"}
}