{
  "type": "Feature",
  "properties": {
    "gn:admin1_code":"12.0",
    "gn:admin2_code":"004",
    "gn:asciiname":"Zuti",
    "gn:country_code":"IN",
    "gn:dem":3286,
    "gn:feature_class":"P",
    "gn:feature_code":"PPL",
    "gn:name":"Z\u016bti",
    "gn:population":0,
    "gn:timezone":"Asia/Kolkata",
    "iso:country":"IN",
    "wof:name":"Zuti",
    "wof:placetype":"locality"
},
  "geometry": {"coordinates":[76.42208000000002,34.64862],"type":"Point"}
}