{
  "type": "Feature",
  "properties": {
    "iso:country":"IN",
    "ks:ks_alt_nam":"HANUMAN NAGAR",
    "ks:ks_name":"Hanuman Nagar",
    "ks:ks_pop":384,
    "ks:ks_type":"HABITATION",
    "name:eng_x_preferred":[
        "Hanuman Nagar"
    ],
    "wof:name":"Hanuman Nagar",
    "wof:placetype":"locality",
    "wof:population":384
},
  "geometry": {"coordinates":[85.73204200000001,26.122999],"type":"Point"}
}