{
  "type": "Feature",
  "properties": {
    "iso:country":"IN",
    "ks:ks_name":"Kawoimari",
    "ks:ks_pop":662,
    "ks:ks_type":"HABITATION",
    "name:eng_x_preferred":[
        "Kawoimari"
    ],
    "wof:name":"Kawoimari",
    "wof:placetype":"locality",
    "wof:population":662
},
  "geometry": {"coordinates":[92.128339,26.402238],"type":"Point"}
}