{
  "type": "Feature",
  "properties": {
    "iso:country":"IN",
    "ks:ks_name":"Husnapur",
    "ks:ks_pop":0,
    "ks:ks_type":"VILLAGE",
    "name:eng_x_preferred":[
        "Husnapur"
    ],
    "wof:name":"Husnapur",
    "wof:placetype":"locality",
    "wof:population":0
},
  "geometry": {"coordinates":[78.292863,20.680264],"type":"Point"}
}