{
  "type": "Feature",
  "properties": {
    "gn:admin1_code":"30.0",
    "gn:admin2_code":"258",
    "gn:asciiname":"Ipilin",
    "gn:country_code":"IN",
    "gn:dem":912,
    "gn:feature_class":"P",
    "gn:feature_code":"PPL",
    "gn:name":"Ipilin",
    "gn:population":0,
    "gn:timezone":"Asia/Kolkata",
    "iso:country":"IN",
    "wof:name":"Ipilin",
    "wof:placetype":"locality"
},
  "geometry": {"coordinates":[95.69086,28.40004],"type":"Point"}
}