{
  "type": "Feature",
  "properties": {
    "iso:country":"IN",
    "ks:ks_name":"Mastihaklu",
    "ks:ks_pop":49,
    "ks:ks_type":"HABITATION",
    "name:eng_x_preferred":[
        "Mastihaklu"
    ],
    "wof:name":"Mastihaklu",
    "wof:placetype":"locality",
    "wof:population":49
},
  "geometry": {"coordinates":[74.74656899999999,14.308922],"type":"Point"}
}