{
  "type": "Feature",
  "properties": {
    "iso:country":"IN",
    "ks:ks_name":"Ramdihi",
    "ks:ks_pop":163,
    "ks:ks_type":"VILLAGE",
    "name:eng_x_preferred":[
        "Ramdihi"
    ],
    "wof:name":"Ramdihi",
    "wof:placetype":"locality",
    "wof:population":163
},
  "geometry": {"coordinates":[87.018765,23.276943],"type":"Point"}
}