{
  "type": "Feature",
  "properties": {
    "gn:admin1_code":"34.0",
    "gn:admin2_code":"236.0",
    "gn:asciiname":"Partapi",
    "gn:country_code":"IN",
    "gn:dem":170,
    "gn:feature_class":"P",
    "gn:feature_code":"PPL",
    "gn:name":"Part\u0101pi",
    "gn:population":0,
    "gn:timezone":"Asia/Kolkata",
    "iso:country":"IN",
    "ks:ks_alt_nam":"Part\u0101pi",
    "ks:ks_name":"Partapi",
    "ks:ks_type":"VILLAGE",
    "ks:ks_uagg_main":0,
    "name:eng_x_preferred":[
        "Partapi"
    ],
    "name:eng_x_variant":[
        "Part\u0101pi"
    ],
    "wof:name":"Partapi",
    "wof:placetype":"neighbourhood"
},
  "geometry": {"coordinates":[85.02650300000001,24.510232],"type":"Point"}
}