{
  "type": "Feature",
  "properties": {
    "gn:admin1_code":"39.0",
    "gn:admin2_code":"63.0",
    "gn:asciiname":"Jamkhetola",
    "gn:country_code":"IN",
    "gn:dem":1425,
    "gn:feature_class":"P",
    "gn:feature_code":"PPL",
    "gn:name":"Jamkhetola",
    "gn:population":0,
    "gn:timezone":"Asia/Kolkata",
    "iso:country":"IN",
    "ks:ks_name":"Jamkhitola",
    "ks:ks_pop":6,
    "ks:ks_type":"VILLAGE",
    "name:eng_x_preferred":[
        "Jamkhitola"
    ],
    "name:eng_x_variant":[
        "Jamkhetola"
    ],
    "wof:name":"Jamkhitola",
    "wof:placetype":"locality",
    "wof:population":6
},
  "geometry": {"coordinates":[79.71347900000001,29.830193],"type":"Point"}
}