{
  "type": "Feature",
  "properties": {
    "iso:country":"IN",
    "ks:ks_name":"Menangodu",
    "ks:ks_pop":27,
    "ks:ks_type":"HABITATION",
    "name:eng_x_preferred":[
        "Menangodu"
    ],
    "wof:name":"Menangodu",
    "wof:placetype":"locality",
    "wof:population":27
},
  "geometry": {"coordinates":[75.86034600000001,12.023959],"type":"Point"}
}