{
  "type": "Feature",
  "properties": {
    "iso:country":"IN",
    "ks:ks_name":"Yesgaon",
    "ks:ks_pop":2108,
    "ks:ks_type":"VILLAGE",
    "ks:ks_uagg_main":0,
    "name:eng_x_preferred":[
        "Yesgaon"
    ],
    "wof:name":"Yesgaon",
    "wof:placetype":"neighbourhood",
    "wof:population":2108
},
  "geometry": {"coordinates":[74.488862,19.946205],"type":"Point"}
}