{
  "type": "Feature",
  "properties": {
    "iso:country":"IN",
    "ks:ks_name":"Parsotimpur Satgharia",
    "ks:ks_pop":0,
    "ks:ks_type":"VILLAGE",
    "name:eng_x_preferred":[
        "Parsotimpur Satgharia"
    ],
    "wof:name":"Parsotimpur Satgharia",
    "wof:placetype":"locality",
    "wof:population":0
},
  "geometry": {"coordinates":[86.67603,25.194139],"type":"Point"}
}