{
  "type": "Feature",
  "properties": {
    "iso:country":"IN",
    "qs:name":"Hanuman Nagar",
    "qs:name_adm0":"India",
    "qs:name_adm1":"Maharashtra",
    "qs:photos":80,
    "qs:photos_1k":16,
    "qs:photos_9k":1,
    "qs:photos_9r":3,
    "qs:photos_all":80,
    "qs:photos_sr":3,
    "qs:placetype":"Suburb",
    "qs:pop_sr":"0",
    "wd:wordcount":13,
    "wof:name":"Hanuman Nagar",
    "wof:placetype":"neighbourhood"
},
  "geometry": {"coordinates":[73.8403015,18.521059],"type":"Point"}
}