{
  "type": "Feature",
  "properties": {
    "iso:country":"IN",
    "name:ara_x_preferred":[
        "\u0647\u0627\u0646\u0648\u0645\u0627\u0646 \u0646\u0627\u062c\u0627\u0631"
    ],
    "name:ben_bn_x_preferred":[
        "\u09b9\u09a8\u09c2\u09ae\u09be\u09a8 \u09a8\u0997\u09b0"
    ],
    "name:ben_in_x_preferred":[
        "\u09b9\u09a8\u09c2\u09ae\u09be\u09a8 \u09a8\u0997\u09b0"
    ],
    "name:guj_x_preferred":[
        "\u0a85\u0aa8\u0ac1\u0aae\u0abe\u0aa8 \u0aa8\u0a97\u0ab0"
    ],
    "name:hin_x_preferred":[
        "\u0939\u0928\u0941\u092e\u093e\u0928 \u0928\u0917\u0930"
    ],
    "name:kan_x_preferred":[
        "\u0cb9\u0ca8\u0cc1\u0cae\u0cbe\u0ca8\u0ccd"
    ],
    "name:mal_x_preferred":[
        "\u0d39\u0d28\u0d41\u0d2e\u0d3e\u0d7b \u0d28\u0d17\u0d7c"
    ],
    "name:mar_x_preferred":[
        "\u0939\u0928\u0941\u092e\u093e\u0928 \u0928\u0917\u0930"
    ],
    "name:pan_x_preferred":[
        "\u0a39\u0a28\u0a42\u0a2e\u0a3e\u0a28 \u0a28\u0a17\u0a30"
    ],
    "name:tam_x_preferred":[
        "\u0b85\u0ba9\u0bc1\u0bae\u0bbe\u0ba9\u0bcd \u0ba8\u0b95\u0bb0\u0bcd"
    ],
    "name:tel_x_preferred":[
        "\u0c39\u0c28\u0c41\u0c2e\u0c3e\u0c28\u0c4d \u0c28\u0c17\u0c30\u0c4d"
    ],
    "name:urd_x_preferred":[
        "\u06c1\u0645\u0627\u06cc\u0648\u06ba \u0646\u06af\u0631"
    ],
    "qs:name":"Hanuman Nagar",
    "qs:name_adm0":"India",
    "qs:name_adm1":"Maharashtra",
    "qs:photos":80,
    "qs:photos_1k":16,
    "qs:photos_9k":1,
    "qs:photos_9r":3,
    "qs:photos_all":80,
    "qs:photos_sr":3,
    "qs:placetype":"Suburb",
    "qs:pop_sr":"0",
    "wd:wordcount":13,
    "wof:name":"Hanuman Nagar",
    "wof:placetype":"neighbourhood"
},
  "geometry": {"coordinates":[73.8403015,18.521059],"type":"Point"}
}