{
  "type": "Feature",
  "properties": {
    "gn:admin1_code":"36",
    "gn:admin2_code":"193.0",
    "gn:asciiname":"Shankarpur",
    "gn:country_code":"IN",
    "gn:dem":72,
    "gn:feature_class":"P",
    "gn:feature_code":"PPL",
    "gn:name":"Shankarpur",
    "gn:population":0,
    "gn:timezone":"Asia/Kolkata",
    "iso:country":"IN",
    "ks:ks_name":"Shankarpur",
    "ks:ks_type":"VILLAGE",
    "ks:ks_uagg_main":0,
    "name:eng_x_preferred":[
        "Shankarpur"
    ],
    "name:und_x_variant":[
        "Bishanpura"
    ],
    "wof:name":"Shankarpur",
    "wof:placetype":"neighbourhood"
},
  "geometry": {"coordinates":[83.986687,25.885591],"type":"Point"}
}