{
  "type": "Feature",
  "properties": {
    "iso:country":"IN",
    "ks:ks_name":"Yedatittu",
    "ks:ks_pop":42,
    "ks:ks_type":"HABITATION",
    "name:eng_x_preferred":[
        "Yedatittu"
    ],
    "wof:name":"Yedatittu",
    "wof:placetype":"locality",
    "wof:population":42
},
  "geometry": {"coordinates":[76.61664500000001,12.417373],"type":"Point"}
}