{
  "type": "Feature",
  "properties": {
    "iso:country":"IN",
    "ks:ks_name":"Badraiahnapalya",
    "ks:ks_pop":97,
    "ks:ks_type":"HABITATION",
    "name:eng_x_preferred":[
        "Badraiahnapalya"
    ],
    "wof:name":"Badraiahnapalya",
    "wof:placetype":"locality",
    "wof:population":97
},
  "geometry": {"coordinates":[77.19558499999999,13.085613],"type":"Point"}
}