{
  "type": "Feature",
  "properties": {
    "iso:country":"IN",
    "ks:ks_name":"Baladoba",
    "ks:ks_pop":6100,
    "ks:ks_type":"VILLAGE",
    "name:eng_x_preferred":[
        "Baladoba"
    ],
    "wof:name":"Baladoba",
    "wof:placetype":"locality",
    "wof:population":6100
},
  "geometry": {"coordinates":[90.001952,25.904645],"type":"Point"}
}