{
  "type": "Feature",
  "properties": {
    "iso:country":"IN",
    "ks:ks_alt_nam":"Saugada falia",
    "ks:ks_name":"Saugada Falia",
    "ks:ks_pop":687,
    "ks:ks_type":"HABITATION",
    "name:eng_x_preferred":[
        "Saugada Falia"
    ],
    "wof:name":"Saugada Falia",
    "wof:placetype":"locality",
    "wof:population":687
},
  "geometry": {"coordinates":[74.310444,22.92725],"type":"Point"}
}