{
  "type": "Feature",
  "properties": {
    "iso:country":"IN",
    "ks:ks_alt_nam":"BERADWASTI",
    "ks:ks_name":"Beradwasti",
    "ks:ks_pop":293,
    "ks:ks_type":"HABITATION",
    "name:eng_x_preferred":[
        "Beradwasti"
    ],
    "wof:name":"Beradwasti",
    "wof:placetype":"locality",
    "wof:population":293
},
  "geometry": {"coordinates":[75.543679,17.136995],"type":"Point"}
}