{
  "type": "Feature",
  "properties": {
    "gn:admin1_code":"24.0",
    "gn:admin2_code":"130.0",
    "gn:asciiname":"Bhagal",
    "gn:country_code":"IN",
    "gn:dem":749,
    "gn:feature_class":"P",
    "gn:feature_code":"PPL",
    "gn:name":"Bhagal",
    "gn:population":0,
    "gn:timezone":"Asia/Kolkata",
    "iso:country":"IN",
    "name:guj_x_preferred":[
        "\u0aad\u0abe\u0a97\u0ab3"
    ],
    "wof:name":"Bhagal",
    "wof:placetype":"locality"
},
  "geometry": {"coordinates":[73.53886999999997,24.9448],"type":"Point"}
}