{
  "type": "Feature",
  "properties": {
    "gn:admin1_code":"2.0",
    "gn:admin2_code":"554.0",
    "gn:asciiname":"Bhimavaram",
    "gn:country_code":"IN",
    "gn:dem":53,
    "gn:feature_class":"P",
    "gn:feature_code":"PPL",
    "gn:name":"Bh\u012bm\u0101varam",
    "gn:population":0,
    "gn:timezone":"Asia/Kolkata",
    "iso:country":"IN",
    "wof:name":"Bhimavaram",
    "wof:placetype":"locality"
},
  "geometry": {"coordinates":[79.76966,13.81978],"type":"Point"}
}