{
  "type": "Feature",
  "properties": {
    "gn:admin1_code":"10.0",
    "gn:admin2_code":"74.0",
    "gn:asciiname":"Nagla Megha",
    "gn:country_code":"IN",
    "gn:dem":244,
    "gn:feature_class":"P",
    "gn:feature_code":"PPL",
    "gn:name":"Nagla Megha",
    "gn:population":0,
    "gn:timezone":"Asia/Kolkata",
    "iso:country":"IN",
    "wof:name":"Nagla Megha",
    "wof:placetype":"locality"
},
  "geometry": {"coordinates":[77.06605999999999,29.62336],"type":"Point"}
}