{
  "type": "Feature",
  "properties": {
    "iso:country":"IN",
    "ks:ks_name":"Dhankauda",
    "ks:ks_pop":4202,
    "ks:ks_type":"VILLAGE",
    "ks:ks_uagg_main":0,
    "name:eng_x_preferred":[
        "Dhankauda"
    ],
    "wof:name":"Dhankauda",
    "wof:placetype":"neighbourhood",
    "wof:population":4202
},
  "geometry": {"coordinates":[84.00880100000001,21.468411],"type":"Point"}
}