{
  "type": "Feature",
  "properties": {
    "iso:country":"IN",
    "ks:ks_name":"Chittanahally",
    "ks:ks_pop":120,
    "ks:ks_type":"HABITATION",
    "name:eng_x_preferred":[
        "Chittanahally"
    ],
    "wof:name":"Chittanahally",
    "wof:placetype":"locality",
    "wof:population":120
},
  "geometry": {"coordinates":[75.987319,12.898601],"type":"Point"}
}