{
  "type": "Feature",
  "properties": {
    "iso:country":"IN",
    "ks:ks_name":"Baunsiapada",
    "ks:ks_pop":172,
    "ks:ks_type":"VILLAGE",
    "name:eng_x_preferred":[
        "Baunsiapada"
    ],
    "wof:name":"Baunsiapada",
    "wof:placetype":"locality",
    "wof:population":172
},
  "geometry": {"coordinates":[85.075805,19.614693],"type":"Point"}
}