{
  "type": "Feature",
  "properties": {
    "iso:country":"IN",
    "ks:ks_alt_nam":"She box khera",
    "ks:ks_name":"She Box Khera",
    "ks:ks_pop":194,
    "ks:ks_type":"HABITATION",
    "ks:ks_uagg_main":0,
    "name:eng_x_preferred":[
        "She Box Khera"
    ],
    "wof:name":"She Box Khera",
    "wof:placetype":"neighbourhood",
    "wof:population":194
},
  "geometry": {"coordinates":[80.442837,26.940273],"type":"Point"}
}