{
  "type": "Feature",
  "properties": {
    "iso:country":"IN",
    "ks:ks_name":"Saradamaha",
    "ks:ks_pop":130,
    "ks:ks_type":"VILLAGE",
    "name:eng_x_preferred":[
        "Saradamaha"
    ],
    "wof:name":"Saradamaha",
    "wof:placetype":"locality",
    "wof:population":130
},
  "geometry": {"coordinates":[84.24282599999999,20.242575],"type":"Point"}
}