{
  "type": "Feature",
  "properties": {
    "gn:admin1_code":"25.0",
    "gn:admin2_code":"604.0",
    "gn:asciiname":"Timmarajanpettal",
    "gn:country_code":"IN",
    "gn:dem":69,
    "gn:feature_class":"P",
    "gn:feature_code":"PPL",
    "gn:name":"Timmar\u0101janpettal",
    "gn:population":0,
    "gn:timezone":"Asia/Kolkata",
    "iso:country":"IN",
    "wof:name":"Timmarajanpettal",
    "wof:placetype":"locality"
},
  "geometry": {"coordinates":[79.78423000000002,12.79867],"type":"Point"}
}