{
  "type": "Feature",
  "properties": {
    "iso:country":"IN",
    "ks:ks_name":"Abimatha Colony",
    "ks:ks_pop":160,
    "ks:ks_type":"HABITATION",
    "name:eng_x_preferred":[
        "Abimatha Colony"
    ],
    "wof:name":"Abimatha Colony",
    "wof:placetype":"locality",
    "wof:population":160
},
  "geometry": {"coordinates":[75.677207,12.989146],"type":"Point"}
}