{
  "type": "Feature",
  "properties": {
    "iso:country":"IN",
    "ks:ks_name":"Chakphutahi",
    "ks:ks_pop":287,
    "ks:ks_type":"HABITATION",
    "name:eng_x_preferred":[
        "Chakphutahi"
    ],
    "wof:name":"Chakphutahi",
    "wof:placetype":"locality",
    "wof:population":287
},
  "geometry": {"coordinates":[82.53854699999999,25.353565],"type":"Point"}
}