{
  "type": "Feature",
  "properties": {
    "gn:admin1_code":"11.0",
    "gn:admin2_code":"33.0",
    "gn:asciiname":"Nyuri",
    "gn:country_code":"IN",
    "gn:dem":2361,
    "gn:feature_class":"P",
    "gn:feature_code":"PPL",
    "gn:name":"Ny\u016bri",
    "gn:population":0,
    "gn:timezone":"Asia/Kolkata",
    "iso:country":"IN",
    "wof:name":"Nyuri",
    "wof:placetype":"locality"
},
  "geometry": {"coordinates":[77.37929,31.19004],"type":"Point"}
}