{
  "type": "Feature",
  "properties": {
    "gn:admin1_code":"21.0",
    "gn:admin2_code":"390",
    "gn:asciiname":"Dhormopur",
    "gn:country_code":"IN",
    "gn:dem":596,
    "gn:feature_class":"P",
    "gn:feature_code":"PPL",
    "gn:name":"Dhormopur",
    "gn:population":0,
    "gn:timezone":"Asia/Kolkata",
    "iso:country":"IN",
    "wof:name":"Dhormopur",
    "wof:placetype":"locality"
},
  "geometry": {"coordinates":[84.11058,20.10681],"type":"Point"}
}