{
  "type": "Feature",
  "properties": {
    "iso:country":"IN",
    "ks:ks_name":"Bom",
    "ks:ks_pop":256,
    "ks:ks_type":"HABITATION",
    "name:eng_x_preferred":[
        "Bom"
    ],
    "wof:name":"Bom",
    "wof:placetype":"locality",
    "wof:population":256
},
  "geometry": {"coordinates":[84.192718,19.303095],"type":"Point"}
}