{
  "type": "Feature",
  "properties": {
    "iso:country":"IN",
    "name:eng_x_preferred":[
        "JP Nagar Phase 1"
    ],
    "qs:gn_adm0_cc":"IN",
    "qs:gn_fcode":"PPL",
    "qs:gn_local":1277333,
    "qs:gn_nam_loc":"Bangalore, Bangalore, Karnataka, IN",
    "qs:gn_namadm1":"19",
    "qs:gn_name":"JP NAGAR 2ND PHASE",
    "qs:local_max":7342,
    "qs:local_sum":38996,
    "qs:localhoods":89,
    "qs:name":"JP Nagar Phase 1",
    "qs:name_adm0":"India",
    "qs:name_adm1":"Karnataka",
    "qs:name_adm2":"Bangalore",
    "qs:name_local":"Bangalore",
    "qs:photo_max":27,
    "qs:photo_sum":42,
    "qs:placetype":"Suburb",
    "qs:quad_count":3,
    "qs:woe_adm0":23424848,
    "qs:woe_adm1":2345753,
    "qs:woe_adm2":12586572,
    "qs:woe_lau":0,
    "qs:woe_local":2295420,
    "qs:woe_ver":"7.10.0",
    "wof:lang":[
        "eng"
    ],
    "wof:name":"JP Nagar Phase 1",
    "wof:placetype":"neighbourhood"
},
  "geometry": {"coordinates":[77.578256,12.919671],"type":"Point"}
}