{
  "type": "Feature",
  "properties": {
    "iso:country":"IN",
    "ks:ks_name":"Brahmanikholha",
    "ks:ks_pop":351,
    "ks:ks_type":"VILLAGE",
    "name:eng_x_preferred":[
        "Brahmanikholha"
    ],
    "wof:name":"Brahmanikholha",
    "wof:placetype":"locality",
    "wof:population":351
},
  "geometry": {"coordinates":[86.800022,20.616565],"type":"Point"}
}