{
  "type": "Feature",
  "properties": {
    "gn:admin1_code":"35.0",
    "gn:admin2_code":"423",
    "gn:asciiname":"Kakrela",
    "gn:country_code":"IN",
    "gn:dem":319,
    "gn:feature_class":"P",
    "gn:feature_code":"PPL",
    "gn:name":"Kakrela",
    "gn:population":0,
    "gn:timezone":"Asia/Kolkata",
    "iso:country":"IN",
    "wof:name":"Kakrela",
    "wof:placetype":"locality"
},
  "geometry": {"coordinates":[78.26869000000001,24.98226],"type":"Point"}
}