{
  "type": "Feature",
  "properties": {
    "iso:country":"IN",
    "ks:ks_alt_nam":"UTTAR ATHAI BARI",
    "ks:ks_name":"Uttar Athai Bari",
    "ks:ks_pop":183,
    "ks:ks_type":"HABITATION",
    "ks:ks_uagg_main":0,
    "name:eng_x_preferred":[
        "Uttar Athai Bari"
    ],
    "wof:name":"Uttar Athai Bari",
    "wof:placetype":"neighbourhood",
    "wof:population":183
},
  "geometry": {"coordinates":[91.572194,24.018097],"type":"Point"}
}