{
  "type": "Feature",
  "properties": {
    "iso:country":"IN",
    "ks:ks_alt_nam":"Marathamkod college",
    "ks:ks_name":"Marathamkod College",
    "ks:ks_pop":262,
    "ks:ks_type":"HABITATION",
    "name:eng_x_preferred":[
        "Marathamkod College"
    ],
    "wof:name":"Marathamkod College",
    "wof:placetype":"locality",
    "wof:population":262
},
  "geometry": {"coordinates":[76.10900100000001,10.668674],"type":"Point"}
}