{
  "type": "Feature",
  "properties": {
    "iso:country":"IN",
    "ks:ks_name":"Dadia Tal",
    "ks:ks_pop":412,
    "ks:ks_type":"VILLAGE",
    "name:eng_x_preferred":[
        "Dadia Tal"
    ],
    "wof:name":"Dadia Tal",
    "wof:placetype":"locality",
    "wof:population":412
},
  "geometry": {"coordinates":[83.059676,27.150845],"type":"Point"}
}