{
  "type": "Feature",
  "properties": {
    "gn:admin1_code":"24.0",
    "gn:admin2_code":"103",
    "gn:asciiname":"Rokha ki Dhani",
    "gn:country_code":"IN",
    "gn:dem":324,
    "gn:feature_class":"P",
    "gn:feature_code":"PPL",
    "gn:name":"Rokha ki Dh\u0101ni",
    "gn:population":0,
    "gn:timezone":"Asia/Kolkata",
    "iso:country":"IN",
    "wof:name":"Rokha ki Dhani",
    "wof:placetype":"neighbourhood"
},
  "geometry": {"coordinates":[75.48990000000001,28.1928],"type":"Point"}
}