{
  "type": "Feature",
  "properties": {
    "gn:admin1_code":"36.0",
    "gn:admin2_code":"155.0",
    "gn:asciiname":"Mujahidpur",
    "gn:country_code":"IN",
    "gn:dem":146,
    "gn:feature_class":"P",
    "gn:feature_code":"PPL",
    "gn:name":"Muj\u0101hidpur",
    "gn:population":0,
    "gn:timezone":"Asia/Kolkata",
    "iso:country":"IN",
    "ks:ks_alt_nam":"Muj\u0101hidpur",
    "ks:ks_name":"Mujahidpur",
    "ks:ks_type":"VILLAGE",
    "ks:ks_uagg_main":0,
    "name:eng_x_preferred":[
        "Mujahidpur"
    ],
    "name:eng_x_variant":[
        "Muj\u0101hidpur"
    ],
    "wof:name":"Mujahidpur",
    "wof:placetype":"neighbourhood"
},
  "geometry": {"coordinates":[80.017802,27.405176],"type":"Point"}
}