{
  "type": "Feature",
  "properties": {
    "gn:admin1_code":"36",
    "gn:admin2_code":"194.0",
    "gn:asciiname":"Chaukia",
    "gn:country_code":"IN",
    "gn:dem":84,
    "gn:feature_class":"P",
    "gn:feature_code":"PPL",
    "gn:name":"Chauki\u0101",
    "gn:population":0,
    "gn:timezone":"Asia/Kolkata",
    "iso:country":"IN",
    "ks:ks_name":"Chaukian",
    "ks:ks_pop":1324,
    "ks:ks_type":"VILLAGE",
    "name:eng_x_preferred":[
        "Chaukian"
    ],
    "name:eng_x_variant":[
        "Chaukia"
    ],
    "wof:name":"Chaukian",
    "wof:placetype":"locality",
    "wof:population":1324
},
  "geometry": {"coordinates":[82.869339,25.653693],"type":"Point"}
}