{
  "type": "Feature",
  "properties": {
    "iso:country":"IN",
    "ks:ks_name":"Vellur",
    "ks:ks_pop":770,
    "ks:ks_type":"HABITATION",
    "name:eng_x_preferred":[
        "Vellur"
    ],
    "wof:name":"Vellur",
    "wof:placetype":"locality",
    "wof:population":770
},
  "geometry": {"coordinates":[79.134653,11.24991],"type":"Point"}
}