{
  "type": "Feature",
  "properties": {
    "iso:country":"IN",
    "name:eng_x_preferred":[
        "Moon Nagar"
    ],
    "qs:gn_adm0_cc":"IN",
    "qs:gn_local":1255364,
    "qs:gn_nam_loc":"surat",
    "qs:gn_namadm1":"09",
    "qs:local_max":275,
    "qs:local_sum":734,
    "qs:localhoods":8,
    "qs:name":"Moon Nagar",
    "qs:name_adm0":"India",
    "qs:name_adm1":"Gujarat",
    "qs:name_adm2":"Surat",
    "qs:name_local":"Surat",
    "qs:photo_max":40,
    "qs:photo_sum":97,
    "qs:placetype":"Suburb",
    "qs:quad_count":8,
    "qs:woe_adm0":23424848,
    "qs:woe_adm1":2345743,
    "qs:woe_adm2":12586432,
    "qs:woe_lau":0,
    "qs:woe_local":2295405,
    "qs:woe_ver":"7.10.0",
    "wof:lang":[
        "eng"
    ],
    "wof:name":"Moon Nagar",
    "wof:placetype":"neighbourhood"
},
  "geometry": {"coordinates":[72.791022,21.17855],"type":"Point"}
}