{
  "type": "Feature",
  "properties": {
    "iso:country":"IN",
    "ks:ks_name":"Devipura",
    "ks:ks_pop":75,
    "ks:ks_type":"VILLAGE",
    "name:eng_x_preferred":[
        "Devipura"
    ],
    "wof:name":"Devipura",
    "wof:placetype":"locality",
    "wof:population":75
},
  "geometry": {"coordinates":[77.15294,24.249143],"type":"Point"}
}