{
  "type": "Feature",
  "properties": {
    "gn:admin1_code":"2.0",
    "gn:admin2_code":"554.0",
    "gn:asciiname":"Balijipalli",
    "gn:country_code":"IN",
    "gn:dem":537,
    "gn:feature_class":"P",
    "gn:feature_code":"PPL",
    "gn:name":"Balijipalli",
    "gn:population":0,
    "gn:timezone":"Asia/Kolkata",
    "iso:country":"IN",
    "wof:name":"Balijipalli",
    "wof:placetype":"locality"
},
  "geometry": {"coordinates":[79.02676,13.57527],"type":"Point"}
}