{
  "type": "Feature",
  "properties": {
    "gn:admin1_code":"2.0",
    "gn:admin2_code":"553.0",
    "gn:asciiname":"Chintalacheruvu",
    "gn:country_code":"IN",
    "gn:dem":303,
    "gn:feature_class":"P",
    "gn:feature_code":"PPL",
    "gn:name":"Chintalacheruvu",
    "gn:population":0,
    "gn:timezone":"Asia/Kolkata",
    "iso:country":"IN",
    "name:tel_x_preferred":[
        "\u0c1a\u0c3f\u0c02\u0c24\u0c32\u0c1a\u0c46\u0c30\u0c41\u0c35\u0c41"
    ],
    "wof:name":"Chintalacheruvu",
    "wof:placetype":"locality"
},
  "geometry": {"coordinates":[77.76474,14.98949],"type":"Point"}
}