{
  "type": "Feature",
  "properties": {
    "iso:country":"IN",
    "ks:ks_name":"Baramelu",
    "ks:ks_pop":200,
    "ks:ks_type":"HABITATION",
    "name:eng_x_preferred":[
        "Baramelu"
    ],
    "wof:name":"Baramelu",
    "wof:placetype":"locality",
    "wof:population":200
},
  "geometry": {"coordinates":[75.447615,12.883574],"type":"Point"}
}