{
  "type": "Feature",
  "properties": {
    "iso:country":"IN",
    "ks:ks_name":"Junapra",
    "ks:ks_pop":260,
    "ks:ks_type":"HABITATION",
    "name:eng_x_preferred":[
        "Junapra"
    ],
    "wof:name":"Junapra",
    "wof:placetype":"locality",
    "wof:population":260
},
  "geometry": {"coordinates":[83.321253,22.507894],"type":"Point"}
}