{
  "type": "Feature",
  "properties": {
    "gn:admin1_code":"25.0",
    "gn:admin2_code":"602.0",
    "gn:asciiname":"Polivakkamkandigai",
    "gn:country_code":"IN",
    "gn:dem":61,
    "gn:feature_class":"P",
    "gn:feature_code":"PPL",
    "gn:name":"Poliv\u0101kkamkandigai",
    "gn:population":0,
    "gn:timezone":"Asia/Kolkata",
    "iso:country":"IN",
    "wof:name":"Polivakkamkandigai",
    "wof:placetype":"neighbourhood"
},
  "geometry": {"coordinates":[79.90801,13.05381],"type":"Point"}
}