{
  "type": "Feature",
  "properties": {
    "iso:country":"IN",
    "ks:ks_name":"Lubhansar",
    "ks:ks_pop":499,
    "ks:ks_type":"HABITATION",
    "name:eng_x_preferred":[
        "Lubhansar"
    ],
    "wof:name":"Lubhansar",
    "wof:placetype":"locality",
    "wof:population":499
},
  "geometry": {"coordinates":[72.195342,26.738178],"type":"Point"}
}