{
  "type": "Feature",
  "properties": {
    "iso:country":"IN",
    "ks:ks_name":"Jodhpur",
    "ks:ks_type":"VILLAGE",
    "name:eng_x_preferred":[
        "Jodhpur"
    ],
    "wof:name":"Jodhpur",
    "wof:placetype":"locality"
},
  "geometry": {"coordinates":[77.393525,30.093676],"type":"Point"}
}