{
  "type": "Feature",
  "properties": {
    "iso:country":"IN",
    "ks:ks_name":"Kitumba",
    "ks:ks_pop":519,
    "ks:ks_type":"VILLAGE",
    "name:eng_x_preferred":[
        "Kitumba"
    ],
    "wof:name":"Kitumba",
    "wof:placetype":"locality",
    "wof:population":519
},
  "geometry": {"coordinates":[84.034862,18.972075],"type":"Point"}
}