{
  "type": "Feature",
  "properties": {
    "iso:country":"IN",
    "ks:ks_name":"Koshtiwadi",
    "ks:ks_pop":39,
    "ks:ks_type":"HABITATION",
    "name:eng_x_preferred":[
        "Koshtiwadi"
    ],
    "wof:name":"Koshtiwadi",
    "wof:placetype":"locality",
    "wof:population":39
},
  "geometry": {"coordinates":[73.32055800000001,17.510914],"type":"Point"}
}