{
  "type": "Feature",
  "properties": {
    "gn:admin1_code":"34.0",
    "gn:admin2_code":"225.0",
    "gn:asciiname":"Naraun",
    "gn:country_code":"IN",
    "gn:dem":73,
    "gn:feature_class":"P",
    "gn:feature_code":"PPL",
    "gn:name":"Naraun",
    "gn:population":0,
    "gn:timezone":"Asia/Kolkata",
    "iso:country":"IN",
    "wof:name":"Naraun",
    "wof:placetype":"locality"
},
  "geometry": {"coordinates":[86.74061,25.00002000000001],"type":"Point"}
}