{
  "type": "Feature",
  "properties": {
    "iso:country":"IN",
    "ks:ks_name":"Maruthinagar",
    "ks:ks_pop":353,
    "ks:ks_type":"HABITATION",
    "name:eng_x_preferred":[
        "Maruthinagar"
    ],
    "wof:name":"Maruthinagar",
    "wof:placetype":"locality",
    "wof:population":353
},
  "geometry": {"coordinates":[83.17375,18.111191],"type":"Point"}
}