{
  "type": "Feature",
  "properties": {
    "iso:country":"IN",
    "ks:ks_name":"Dhobinchipa",
    "ks:ks_pop":111,
    "ks:ks_type":"VILLAGE",
    "ks:ks_uagg_main":0,
    "name:eng_x_preferred":[
        "Dhobinchipa"
    ],
    "wof:name":"Dhobinchipa",
    "wof:placetype":"neighbourhood",
    "wof:population":111
},
  "geometry": {"coordinates":[87.300957,24.37218],"type":"Point"}
}