{
  "type": "Feature",
  "properties": {
    "gn:admin1_code":"35.0",
    "gn:admin2_code":"434.0",
    "gn:asciiname":"Kalaria",
    "gn:country_code":"IN",
    "gn:dem":441,
    "gn:feature_class":"P",
    "gn:feature_code":"PPL",
    "gn:name":"Kal\u0101ria",
    "gn:population":0,
    "gn:timezone":"Asia/Kolkata",
    "iso:country":"IN",
    "wof:name":"Kalaria",
    "wof:placetype":"locality"
},
  "geometry": {"coordinates":[75.43558,23.83084],"type":"Point"}
}