{
  "type": "Feature",
  "properties": {
    "gn:admin1_code":"35",
    "gn:admin2_code":"429.0",
    "gn:asciiname":"Barmipur",
    "gn:country_code":"IN",
    "gn:dem":374,
    "gn:feature_class":"P",
    "gn:feature_code":"PPL",
    "gn:name":"Barmipur",
    "gn:population":0,
    "gn:timezone":"Asia/Kolkata",
    "iso:country":"IN",
    "wof:name":"Barmipur",
    "wof:placetype":"neighbourhood"
},
  "geometry": {"coordinates":[80.66298,24.99777],"type":"Point"}
}