{
  "type": "Feature",
  "properties": {
    "gn:admin1_code":"36.0",
    "gn:admin2_code":"140.0",
    "gn:asciiname":"Misbahpur",
    "gn:country_code":"IN",
    "gn:dem":217,
    "gn:feature_class":"P",
    "gn:feature_code":"PPL",
    "gn:name":"Misb\u0101hpur",
    "gn:population":0,
    "gn:timezone":"Asia/Kolkata",
    "iso:country":"IN",
    "wof:name":"Misbahpur",
    "wof:placetype":"locality"
},
  "geometry": {"coordinates":[77.55229,28.76798],"type":"Point"}
}