{
  "type": "Feature",
  "properties": {
    "gn:admin1_code":"11.0",
    "gn:admin2_code":"31.0",
    "gn:asciiname":"Ashnala",
    "gn:country_code":"IN",
    "gn:dem":811,
    "gn:feature_class":"P",
    "gn:feature_code":"PPL",
    "gn:name":"Ashn\u0101la",
    "gn:population":0,
    "gn:timezone":"Asia/Kolkata",
    "iso:country":"IN",
    "wof:name":"Ashnala",
    "wof:placetype":"locality"
},
  "geometry": {"coordinates":[77.04718000000003,30.789],"type":"Point"}
}