{
  "type": "Feature",
  "properties": {
    "iso:country":"IN",
    "ks:ks_alt_nam":"Aaramam JN",
    "ks:ks_name":"Aaramam Jn",
    "ks:ks_pop":2055,
    "ks:ks_type":"HABITATION",
    "name:eng_x_preferred":[
        "Aaramam Jn"
    ],
    "wof:name":"Aaramam Jn",
    "wof:placetype":"locality",
    "wof:population":2055
},
  "geometry": {"coordinates":[76.853398,8.812123],"type":"Point"}
}