{
  "type": "Feature",
  "properties": {
    "iso:country":"IN",
    "ks:ks_name":"Sajanagarh",
    "ks:ks_pop":2565,
    "ks:ks_type":"VILLAGE",
    "name:eng_x_preferred":[
        "Sajanagarh"
    ],
    "wof:name":"Sajanagarh",
    "wof:placetype":"locality",
    "wof:population":2565
},
  "geometry": {"coordinates":[86.72887,21.480945],"type":"Point"}
}