{
  "type": "Feature",
  "properties": {
    "gn:admin1_code":"9.0",
    "gn:admin2_code":"468",
    "gn:asciiname":"Chitrod",
    "gn:country_code":"IN",
    "gn:dem":127,
    "gn:feature_class":"P",
    "gn:feature_code":"PPL",
    "gn:name":"Chitrod",
    "gn:population":0,
    "gn:timezone":"Asia/Kolkata",
    "iso:country":"IN",
    "name:guj_x_preferred":[
        "\u0a9a\u0abf\u0aa4\u0acd\u0ab0\u0acb\u0aa1"
    ],
    "name:und_x_variant":[
        "Chitror",
        "Chitrod"
    ],
    "wof:name":"Chitrod",
    "wof:placetype":"locality"
},
  "geometry": {"coordinates":[70.67766999999998,23.40995],"type":"Point"}
}