{
  "type": "Feature",
  "properties": {
    "iso:country":"IN",
    "ks:ks_name":"Khale",
    "ks:ks_pop":391,
    "ks:ks_type":"HABITATION",
    "name:eng_x_preferred":[
        "Khale"
    ],
    "wof:name":"Khale",
    "wof:placetype":"locality",
    "wof:population":391
},
  "geometry": {"coordinates":[81.69565,27.12088],"type":"Point"}
}