{
  "type": "Feature",
  "properties": {
    "iso:country":"IN",
    "ks:ks_alt_nam":"BHOIRAGHOL MAJOR SUPA",
    "ks:ks_name":"Bhoiraghol Major Supa",
    "ks:ks_pop":283,
    "ks:ks_type":"HABITATION",
    "name:eng_x_preferred":[
        "Bhoiraghol Major Supa"
    ],
    "wof:name":"Bhoiraghol Major Supa",
    "wof:placetype":"locality",
    "wof:population":283
},
  "geometry": {"coordinates":[91.36589499999999,26.332287],"type":"Point"}
}