{
  "type": "Feature",
  "properties": {
    "iso:country":"IN",
    "ks:ks_name":"Baria",
    "ks:ks_pop":242,
    "ks:ks_type":"HABITATION",
    "name:eng_x_preferred":[
        "Baria"
    ],
    "wof:name":"Baria",
    "wof:placetype":"locality",
    "wof:population":242
},
  "geometry": {"coordinates":[73.465436,21.014776],"type":"Point"}
}