{
  "type": "Feature",
  "properties": {
    "iso:country":"IN",
    "ks:ks_name":"Sawaipur",
    "ks:ks_pop":826,
    "ks:ks_type":"HABITATION",
    "name:eng_x_preferred":[
        "Sawaipur"
    ],
    "wof:name":"Sawaipur",
    "wof:placetype":"locality",
    "wof:population":826
},
  "geometry": {"coordinates":[80.263333,26.050833],"type":"Point"}
}