{
  "type": "Feature",
  "properties": {
    "gn:admin1_code":"34.0",
    "gn:admin2_code":"222.0",
    "gn:asciiname":"Suja",
    "gn:country_code":"IN",
    "gn:dem":46,
    "gn:feature_class":"P",
    "gn:feature_code":"PPL",
    "gn:name":"Suja",
    "gn:population":0,
    "gn:timezone":"Asia/Kolkata",
    "iso:country":"IN",
    "ks:ks_name":"Suja",
    "ks:ks_pop":3668,
    "ks:ks_type":"VILLAGE",
    "ks:ks_uagg_main":0,
    "name:eng_x_preferred":[
        "Suja"
    ],
    "wof:name":"Suja",
    "wof:placetype":"neighbourhood",
    "wof:population":3668
},
  "geometry": {"coordinates":[86.16378899999999,25.428067],"type":"Point"}
}