{
  "type": "Feature",
  "properties": {
    "iso:country":"IN",
    "ks:ks_name":"Bingora",
    "ks:ks_pop":196,
    "ks:ks_type":"VILLAGE",
    "name:eng_x_preferred":[
        "Bingora"
    ],
    "wof:name":"Bingora",
    "wof:placetype":"locality",
    "wof:population":196
},
  "geometry": {"coordinates":[84.98812100000001,22.62964],"type":"Point"}
}