{
  "type": "Feature",
  "properties": {
    "iso:country":"IN",
    "ks:ks_name":"Padmavatipur",
    "ks:ks_pop":1907,
    "ks:ks_type":"HABITATION",
    "name:eng_x_preferred":[
        "Padmavatipur"
    ],
    "wof:name":"Padmavatipur",
    "wof:placetype":"locality",
    "wof:population":1907
},
  "geometry": {"coordinates":[75.657844,14.676346],"type":"Point"}
}