{
  "type": "Feature",
  "properties": {
    "iso:country":"IN",
    "ks:ks_alt_nam":"Sadaiyankuppam",
    "ks:ks_name":"Sadayankuppam",
    "ks:ks_pop":1940,
    "ks:ks_type":"VILLAGE",
    "ks:ks_uagg_main":0,
    "name:eng_x_preferred":[
        "Sadayankuppam"
    ],
    "name:eng_x_variant":[
        "Sadaiyankuppam"
    ],
    "wof:name":"Sadayankuppam",
    "wof:placetype":"neighbourhood",
    "wof:population":1940
},
  "geometry": {"coordinates":[80.28916700000001,13.182222],"type":"Point"}
}