{
  "type": "Feature",
  "properties": {
    "iso:country":"IN",
    "ks:ks_name":"Chhota Patma",
    "ks:ks_pop":92,
    "ks:ks_type":"VILLAGE",
    "name:eng_x_preferred":[
        "Chhota Patma"
    ],
    "wof:name":"Chhota Patma",
    "wof:placetype":"locality",
    "wof:population":92
},
  "geometry": {"coordinates":[87.42894200000001,24.87771],"type":"Point"}
}