{
  "type": "Feature",
  "properties": {
    "gn:admin1_code":"35.0",
    "gn:admin2_code":"453.0",
    "gn:asciiname":"Piparia Khurd",
    "gn:country_code":"IN",
    "gn:dem":724,
    "gn:feature_class":"P",
    "gn:feature_code":"PPL",
    "gn:name":"Piparia Khurd",
    "gn:population":0,
    "gn:timezone":"Asia/Kolkata",
    "iso:country":"IN",
    "wof:name":"Piparia Khurd",
    "wof:placetype":"neighbourhood"
},
  "geometry": {"coordinates":[80.91721,23.11535],"type":"Point"}
}