{
  "type": "Feature",
  "properties": {
    "iso:country":"IN",
    "ks:ks_alt_nam":"GUDIYALA",
    "ks:ks_name":"Gudiyala",
    "ks:ks_pop":669,
    "ks:ks_type":"HABITATION",
    "name:eng_x_preferred":[
        "Gudiyala"
    ],
    "wof:name":"Gudiyala",
    "wof:placetype":"locality",
    "wof:population":669
},
  "geometry": {"coordinates":[72.602025,26.440092],"type":"Point"}
}