{
  "type": "Feature",
  "properties": {
    "gn:admin1_code":"11.0",
    "gn:admin2_code":"33.0",
    "gn:asciiname":"Bagoti",
    "gn:country_code":"IN",
    "gn:dem":1576,
    "gn:feature_class":"P",
    "gn:feature_code":"PPL",
    "gn:name":"Bagoti",
    "gn:population":0,
    "gn:timezone":"Asia/Kolkata",
    "iso:country":"IN",
    "wof:name":"Bagoti",
    "wof:placetype":"locality"
},
  "geometry": {"coordinates":[77.28936,31.15003],"type":"Point"}
}