{
  "type": "Feature",
  "properties": {
    "iso:country":"IN",
    "ks:ks_name":"Sarpajoy Para",
    "ks:ks_pop":185,
    "ks:ks_type":"HABITATION",
    "name:eng_x_preferred":[
        "Sarpajoy Para"
    ],
    "wof:name":"Sarpajoy Para",
    "wof:placetype":"locality",
    "wof:population":185
},
  "geometry": {"coordinates":[92.19059900000001,23.714083],"type":"Point"}
}