{
  "type": "Feature",
  "properties": {
    "gn:admin1_code":"21.0",
    "gn:admin2_code":"387",
    "gn:asciiname":"Chapamanik",
    "gn:country_code":"IN",
    "gn:dem":13,
    "gn:feature_class":"P",
    "gn:feature_code":"PPL",
    "gn:name":"Ch\u0101pam\u0101nik",
    "gn:population":0,
    "gn:timezone":"Asia/Kolkata",
    "iso:country":"IN",
    "wof:name":"Chapamanik",
    "wof:placetype":"locality"
},
  "geometry": {"coordinates":[85.66667,19.75],"type":"Point"}
}