{
  "type": "Feature",
  "properties": {
    "iso:country":"IN",
    "ks:ks_name":"Seujipam",
    "ks:ks_pop":690,
    "ks:ks_type":"HABITATION",
    "ks:ks_uagg_main":0,
    "name:eng_x_preferred":[
        "Seujipam"
    ],
    "wof:name":"Seujipam",
    "wof:placetype":"neighbourhood",
    "wof:population":690
},
  "geometry": {"coordinates":[95.16492100000001,27.10377],"type":"Point"}
}