{
  "type": "Feature",
  "properties": {
    "iso:country":"IN",
    "ks:ks_name":"Rituwa",
    "ks:ks_pop":24,
    "ks:ks_type":"VILLAGE",
    "name:eng_x_preferred":[
        "Rituwa"
    ],
    "wof:name":"Rituwa",
    "wof:placetype":"locality",
    "wof:population":24
},
  "geometry": {"coordinates":[80.304205,23.654178],"type":"Point"}
}