{
  "type": "Feature",
  "properties": {
    "gn:admin1_code":"34.0",
    "gn:admin2_code":"236.0",
    "gn:asciiname":"Itwan",
    "gn:country_code":"IN",
    "gn:dem":158,
    "gn:feature_class":"P",
    "gn:feature_code":"PPL",
    "gn:name":"Itw\u0101n",
    "gn:population":0,
    "gn:timezone":"Asia/Kolkata",
    "iso:country":"IN",
    "ks:ks_alt_nam":"Itw\u0101n",
    "ks:ks_name":"Itwan",
    "ks:ks_pop":794,
    "ks:ks_type":"VILLAGE",
    "ks:ks_uagg_main":0,
    "name:eng_x_preferred":[
        "Itwan"
    ],
    "name:eng_x_variant":[
        "Itw\u0101n"
    ],
    "wof:name":"Itwan",
    "wof:placetype":"neighbourhood",
    "wof:population":794
},
  "geometry": {"coordinates":[85.22371800000001,24.625373],"type":"Point"}
}