{
  "type": "Feature",
  "properties": {
    "gn:admin1_code":"34.0",
    "gn:admin2_code":"232",
    "gn:asciiname":"Kamarpur",
    "gn:country_code":"IN",
    "gn:dem":70,
    "gn:feature_class":"P",
    "gn:feature_code":"PPL",
    "gn:name":"K\u0101m\u0101rpur",
    "gn:population":0,
    "gn:timezone":"Asia/Kolkata",
    "iso:country":"IN",
    "ks:ks_alt_nam":"K\u0101m\u0101rpur",
    "ks:ks_name":"Kamarpur",
    "ks:ks_pop":2348,
    "ks:ks_type":"VILLAGE",
    "name:eng_x_preferred":[
        "Kamarpur"
    ],
    "name:eng_x_variant":[
        "K\u0101m\u0101rpur"
    ],
    "wof:name":"Kamarpur",
    "wof:placetype":"locality",
    "wof:population":2348
},
  "geometry": {"coordinates":[83.934459,25.527693],"type":"Point"}
}