{
  "type": "Feature",
  "properties": {
    "gn:admin1_code":"36",
    "gn:admin2_code":"142.0",
    "gn:asciiname":"Mukimpur",
    "gn:country_code":"IN",
    "gn:dem":200,
    "gn:feature_class":"P",
    "gn:feature_code":"PPL",
    "gn:name":"Muk\u012bmpur",
    "gn:population":0,
    "gn:timezone":"Asia/Kolkata",
    "iso:country":"IN",
    "ks:ks_name":"Mukeempur",
    "ks:ks_pop":654,
    "ks:ks_type":"VILLAGE",
    "name:eng_x_preferred":[
        "Mukeempur"
    ],
    "name:eng_x_variant":[
        "Mukimpur"
    ],
    "wof:name":"Mukeempur",
    "wof:placetype":"locality",
    "wof:population":654
},
  "geometry": {"coordinates":[77.919994,28.362087],"type":"Point"}
}