{
  "type": "Feature",
  "properties": {
    "iso:country":"IN",
    "ks:ks_alt_nam":"DHARI TOLA",
    "ks:ks_name":"Dhari Tola",
    "ks:ks_pop":123,
    "ks:ks_type":"HABITATION",
    "name:eng_x_preferred":[
        "Dhari Tola"
    ],
    "wof:name":"Dhari Tola",
    "wof:placetype":"locality",
    "wof:population":123
},
  "geometry": {"coordinates":[85.96310200000001,25.085271],"type":"Point"}
}