{
  "type": "Feature",
  "properties": {
    "gn:admin1_code":"39.0",
    "gn:admin2_code":"60.0",
    "gn:asciiname":"Bhakro",
    "gn:country_code":"IN",
    "gn:dem":1641,
    "gn:feature_class":"P",
    "gn:feature_code":"PPL",
    "gn:name":"Bhakro",
    "gn:population":0,
    "gn:timezone":"Asia/Kolkata",
    "iso:country":"IN",
    "wof:name":"Bhakro",
    "wof:placetype":"locality"
},
  "geometry": {"coordinates":[77.91188000000002,30.61433],"type":"Point"}
}