{
  "type": "Feature",
  "properties": {
    "gn:admin1_code":"12",
    "gn:admin2_code":"15.0",
    "gn:asciiname":"Ruzul",
    "gn:country_code":"IN",
    "gn:dem":1801,
    "gn:feature_class":"P",
    "gn:feature_code":"PPL",
    "gn:name":"Ruzul",
    "gn:population":0,
    "gn:timezone":"Asia/Kolkata",
    "iso:country":"IN",
    "wof:name":"Ruzul",
    "wof:placetype":"locality"
},
  "geometry": {"coordinates":[75.11729,33.57913],"type":"Point"}
}