{
  "type": "Feature",
  "properties": {
    "iso:country":"IN",
    "ks:ks_name":"Mashaner Path",
    "ks:ks_pop":366,
    "ks:ks_type":"HABITATION",
    "name:eng_x_preferred":[
        "Mashaner Path"
    ],
    "wof:name":"Mashaner Path",
    "wof:placetype":"locality",
    "wof:population":366
},
  "geometry": {"coordinates":[89.50142200000001,26.349889],"type":"Point"}
}