{
  "type": "Feature",
  "properties": {
    "iso:country":"IN",
    "ks:ks_alt_nam":"vatrampalayam",
    "ks:ks_name":"Vatrampalayam",
    "ks:ks_pop":600,
    "ks:ks_type":"HABITATION",
    "name:eng_x_preferred":[
        "Vatrampalayam"
    ],
    "wof:name":"Vatrampalayam",
    "wof:placetype":"locality",
    "wof:population":600
},
  "geometry": {"coordinates":[77.760739,11.553373],"type":"Point"}
}