{
  "type": "Feature",
  "properties": {
    "iso:country":"IN",
    "ks:ks_name":"Sabal Mara",
    "ks:ks_pop":430,
    "ks:ks_type":"VILLAGE",
    "ks:ks_uagg_main":0,
    "name:eng_x_preferred":[
        "Sabal Mara"
    ],
    "wof:name":"Sabal Mara",
    "wof:placetype":"neighbourhood",
    "wof:population":430
},
  "geometry": {"coordinates":[86.87692300000001,22.344139],"type":"Point"}
}