{
  "type": "Feature",
  "properties": {
    "gn:admin1_code":"39.0",
    "gn:admin2_code":"60.0",
    "gn:asciiname":"Boha",
    "gn:country_code":"IN",
    "gn:dem":1694,
    "gn:feature_class":"P",
    "gn:feature_code":"PPL",
    "gn:name":"Boha",
    "gn:population":0,
    "gn:timezone":"Asia/Kolkata",
    "iso:country":"IN",
    "name:deu_x_preferred":[
        "Boha"
    ],
    "name:eus_x_preferred":[
        "Boha"
    ],
    "name:fra_x_preferred":[
        "Boha"
    ],
    "name:ita_x_preferred":[
        "Boha"
    ],
    "name:oci_x_preferred":[
        "Boha"
    ],
    "wof:name":"Boha",
    "wof:placetype":"locality"
},
  "geometry": {"coordinates":[77.83515,30.65334],"type":"Point"}
}