{
  "type": "Feature",
  "properties": {
    "iso:country":"IN",
    "ks:ks_name":"Jalsa",
    "ks:ks_pop":0,
    "ks:ks_type":"VILLAGE",
    "name:eng_x_preferred":[
        "Jalsa"
    ],
    "wof:name":"Jalsa",
    "wof:placetype":"locality",
    "wof:population":0
},
  "geometry": {"coordinates":[88.284481,25.150379],"type":"Point"}
}