{
  "type": "Feature",
  "properties": {
    "iso:country":"IN",
    "ks:ks_name":"Dano",
    "ks:ks_pop":110,
    "ks:ks_type":"VILLAGE",
    "ks:ks_uagg_main":0,
    "name:eng_x_preferred":[
        "Dano"
    ],
    "wof:name":"Dano",
    "wof:placetype":"neighbourhood",
    "wof:population":110
},
  "geometry": {"coordinates":[82.697407,26.90271],"type":"Point"}
}