{
  "type": "Feature",
  "properties": {
    "gn:admin1_code":"19",
    "gn:admin2_code":"575.0",
    "gn:asciiname":"Punjalkatte",
    "gn:country_code":"IN",
    "gn:dem":92,
    "gn:feature_class":"P",
    "gn:feature_code":"PPL",
    "gn:name":"Punjalkatte",
    "gn:population":0,
    "gn:timezone":"Asia/Kolkata",
    "iso:country":"IN",
    "wof:name":"Punjalkatte",
    "wof:placetype":"neighbourhood"
},
  "geometry": {"coordinates":[75.17162999999999,12.95061],"type":"Point"}
}