{
  "type": "Feature",
  "properties": {
    "iso:country":"IN",
    "name:ceb_x_preferred":[
        "Chela"
    ],
    "name:deu_x_preferred":[
        "Chela"
    ],
    "name:ita_x_preferred":[
        "Chela"
    ],
    "name:nds_x_preferred":[
        "Chela"
    ],
    "name:nor_x_preferred":[
        "Chela"
    ],
    "name:pol_x_preferred":[
        "Chela"
    ],
    "name:spa_x_preferred":[
        "Chela"
    ],
    "name:swe_x_preferred":[
        "Chela"
    ],
    "qs:name":"Chela",
    "qs:name_adm0":"India",
    "qs:name_adm1":"Gujarat",
    "qs:photos":15,
    "qs:photos_1k":3,
    "qs:photos_9k":1,
    "qs:photos_9r":1,
    "qs:photos_all":15,
    "qs:photos_sr":1,
    "qs:placetype":"Town",
    "qs:pop_sr":"0",
    "wd:wordcount":96,
    "wof:name":"Chela",
    "wof:placetype":"locality"
},
  "geometry": {"coordinates":[70.101,22.386499],"type":"Point"}
}