{
  "type": "Feature",
  "properties": {
    "iso:country":"IN",
    "ks:ks_name":"Ulthiga",
    "ks:ks_pop":160,
    "ks:ks_type":"VILLAGE",
    "name:eng_x_preferred":[
        "Ulthiga"
    ],
    "wof:name":"Ulthiga",
    "wof:placetype":"locality",
    "wof:population":160
},
  "geometry": {"coordinates":[75.036725,13.630356],"type":"Point"}
}