{
  "type": "Feature",
  "properties": {
    "iso:country":"IN",
    "ks:ks_name":"Thakurati",
    "ks:ks_pop":143,
    "ks:ks_type":"HABITATION",
    "name:eng_x_preferred":[
        "Thakurati"
    ],
    "wof:name":"Thakurati",
    "wof:placetype":"locality",
    "wof:population":143
},
  "geometry": {"coordinates":[82.614683,23.466728],"type":"Point"}
}