{
  "type": "Feature",
  "properties": {
    "iso:country":"IN",
    "ks:ks_name":"Talyachapada",
    "ks:ks_pop":70,
    "ks:ks_type":"HABITATION",
    "name:eng_x_preferred":[
        "Talyachapada"
    ],
    "wof:name":"Talyachapada",
    "wof:placetype":"locality",
    "wof:population":70
},
  "geometry": {"coordinates":[74.001065,21.062968],"type":"Point"}
}