{
  "type": "Feature",
  "properties": {
    "gn:admin1_code":"39.0",
    "gn:admin2_code":"64.0",
    "gn:asciiname":"Tirnaili",
    "gn:country_code":"IN",
    "gn:dem":1153,
    "gn:feature_class":"P",
    "gn:feature_code":"PPL",
    "gn:name":"Tirnaili",
    "gn:population":0,
    "gn:timezone":"Asia/Kolkata",
    "iso:country":"IN",
    "ks:ks_name":"Tirnaili",
    "ks:ks_type":"VILLAGE",
    "name:eng_x_preferred":[
        "Tirnaili"
    ],
    "wof:name":"Tirnaili",
    "wof:placetype":"locality"
},
  "geometry": {"coordinates":[79.86914899999999,29.683136],"type":"Point"}
}