{
  "type": "Feature",
  "properties": {
    "iso:country":"IN",
    "ks:ks_name":"Borchuk",
    "ks:ks_pop":322,
    "ks:ks_type":"HABITATION",
    "name:eng_x_preferred":[
        "Borchuk"
    ],
    "wof:name":"Borchuk",
    "wof:placetype":"locality",
    "wof:population":322
},
  "geometry": {"coordinates":[95.183122,27.09627],"type":"Point"}
}