{
  "type": "Feature",
  "properties": {
    "gn:admin1_code":"23.0",
    "gn:admin2_code":"51.0",
    "gn:asciiname":"Balan",
    "gn:country_code":"IN",
    "gn:dem":277,
    "gn:feature_class":"P",
    "gn:feature_code":"PPL",
    "gn:name":"Bal\u0101n",
    "gn:population":0,
    "gn:timezone":"Asia/Kolkata",
    "iso:country":"IN",
    "name:bul_x_preferred":[
        "\u0411\u0430\u043b\u0430\u043d"
    ],
    "name:cat_x_preferred":[
        "Balan"
    ],
    "name:ceb_x_preferred":[
        "Balan"
    ],
    "name:ces_x_preferred":[
        "Balan"
    ],
    "name:deu_x_preferred":[
        "Balan"
    ],
    "name:epo_x_preferred":[
        "Balan"
    ],
    "name:fas_x_preferred":[
        "\u0628\u0627\u0644\u0627\u0646"
    ],
    "name:fra_x_preferred":[
        "Balan"
    ],
    "name:heb_x_preferred":[
        "\u05d1\u05dc\u05df"
    ],
    "name:hun_x_preferred":[
        "Balan"
    ],
    "name:ita_x_preferred":[
        "Balan"
    ],
    "name:nds_x_preferred":[
        "Balan"
    ],
    "name:nld_x_preferred":[
        "Balan"
    ],
    "name:pol_x_preferred":[
        "Balan"
    ],
    "name:por_x_preferred":[
        "Balan"
    ],
    "name:ron_x_preferred":[
        "Balan"
    ],
    "name:rus_x_preferred":[
        "\u0411\u0430\u043b\u0430\u043d"
    ],
    "name:scn_x_preferred":[
        "Balan"
    ],
    "name:slk_x_preferred":[
        "Balan"
    ],
    "name:spa_x_preferred":[
        "Balan"
    ],
    "name:srp_x_preferred":[
        "\u0411\u0430\u043b\u0430\u043d"
    ],
    "name:swe_x_preferred":[
        "Balan"
    ],
    "name:ukr_x_preferred":[
        "\u0411\u0430\u043b\u0430\u043d"
    ],
    "wof:name":"Balan",
    "wof:placetype":"locality"
},
  "geometry": {"coordinates":[76.44589999999999,30.80272],"type":"Point"}
}