{
  "type": "Feature",
  "properties": {
    "iso:country":"IN",
    "ks:ks_name":"Mayyaganam",
    "ks:ks_pop":1699,
    "ks:ks_type":"HABITATION",
    "name:eng_x_preferred":[
        "Mayyaganam"
    ],
    "wof:name":"Mayyaganam",
    "wof:placetype":"locality",
    "wof:population":1699
},
  "geometry": {"coordinates":[75.202878,12.326339],"type":"Point"}
}