{
  "type": "Feature",
  "properties": {
    "iso:country":"IN",
    "ks:ks_name":"1NR",
    "ks:ks_pop":2168,
    "ks:ks_type":"VILLAGE",
    "ks:ks_uagg_main":0,
    "name:eng_x_preferred":[
        "1NR"
    ],
    "wof:name":"1NR",
    "wof:placetype":"neighbourhood",
    "wof:population":2168
},
  "geometry": {"coordinates":[74.098828,29.447106],"type":"Point"}
}