{
  "type": "Feature",
  "properties": {
    "iso:country":"IN",
    "ks:ks_name":"Kaharan Purwa",
    "ks:ks_pop":164,
    "ks:ks_type":"HABITATION",
    "name:eng_x_preferred":[
        "Kaharan Purwa"
    ],
    "wof:name":"Kaharan Purwa",
    "wof:placetype":"locality",
    "wof:population":164
},
  "geometry": {"coordinates":[82.107679,27.078597],"type":"Point"}
}