{
  "type": "Feature",
  "properties": {
    "iso:country":"IN",
    "ks:ks_name":"Bhore Wassti",
    "ks:ks_pop":58,
    "ks:ks_type":"HABITATION",
    "name:eng_x_preferred":[
        "Bhore Wassti"
    ],
    "wof:name":"Bhore Wassti",
    "wof:placetype":"locality",
    "wof:population":58
},
  "geometry": {"coordinates":[75.566507,18.530646],"type":"Point"}
}