{
  "type": "Feature",
  "properties": {
    "iso:country":"IN",
    "ks:ks_name":"Gaonkarwadi",
    "ks:ks_pop":212,
    "ks:ks_type":"HABITATION",
    "name:eng_x_preferred":[
        "Gaonkarwadi"
    ],
    "wof:name":"Gaonkarwadi",
    "wof:placetype":"locality",
    "wof:population":212
},
  "geometry": {"coordinates":[73.804119,16.278328],"type":"Point"}
}