{
  "type": "Feature",
  "properties": {
    "iso:country":"IN",
    "ks:ks_name":"Tameshwar Urf Ahirauti Tola",
    "ks:ks_pop":75,
    "ks:ks_type":"HABITATION",
    "name:eng_x_preferred":[
        "Tameshwar Urf Ahirauti Tola"
    ],
    "wof:name":"Tameshwar Urf Ahirauti Tola",
    "wof:placetype":"locality",
    "wof:population":75
},
  "geometry": {"coordinates":[83.39733699999999,26.889343],"type":"Point"}
}