{
  "type": "Feature",
  "properties": {
    "gn:admin1_code":"40.0",
    "gn:admin2_code":"538.0",
    "gn:asciiname":"Pangal",
    "gn:country_code":"IN",
    "gn:dem":343,
    "gn:feature_class":"P",
    "gn:feature_code":"PPL",
    "gn:name":"P\u0101ngal",
    "gn:population":0,
    "gn:timezone":"Asia/Kolkata",
    "iso:country":"IN",
    "name:cat_x_preferred":[
        "Pangals"
    ],
    "wof:name":"Pangal",
    "wof:placetype":"locality"
},
  "geometry": {"coordinates":[77.99165000000001,16.25475],"type":"Point"}
}