{
  "type": "Feature",
  "properties": {
    "iso:country":"IN",
    "ks:ks_name":"Dhobia Singha",
    "ks:ks_pop":7,
    "ks:ks_type":"VILLAGE",
    "name:eng_x_preferred":[
        "Dhobia Singha"
    ],
    "wof:name":"Dhobia Singha",
    "wof:placetype":"locality",
    "wof:population":7
},
  "geometry": {"coordinates":[86.17385,24.242832],"type":"Point"}
}