{
  "type": "Feature",
  "properties": {
    "gn:admin1_code":"36",
    "gn:admin2_code":"194.0",
    "gn:asciiname":"Rakasman Jakia Rain",
    "gn:country_code":"IN",
    "gn:dem":87,
    "gn:feature_class":"P",
    "gn:feature_code":"PPL",
    "gn:name":"Rakasman Jakia Rain",
    "gn:population":0,
    "gn:timezone":"Asia/Kolkata",
    "iso:country":"IN",
    "wof:name":"Rakasman Jakia Rain",
    "wof:placetype":"locality"
},
  "geometry": {"coordinates":[82.79701,25.61719],"type":"Point"}
}