{
  "type": "Feature",
  "properties": {
    "iso:country":"IN",
    "ks:ks_name":"Panithavayal",
    "ks:ks_pop":603,
    "ks:ks_type":"HABITATION",
    "name:eng_x_preferred":[
        "Panithavayal"
    ],
    "wof:name":"Panithavayal",
    "wof:placetype":"locality",
    "wof:population":603
},
  "geometry": {"coordinates":[78.77755999999999,9.569785],"type":"Point"}
}