{
  "type": "Feature",
  "properties": {
    "gn:admin1_code":"36",
    "gn:admin2_code":"181.0",
    "gn:asciiname":"Mankaura Kondri",
    "gn:country_code":"IN",
    "gn:dem":112,
    "gn:feature_class":"P",
    "gn:feature_code":"PPL",
    "gn:name":"Mankaura Kondri",
    "gn:population":0,
    "gn:timezone":"Asia/Kolkata",
    "iso:country":"IN",
    "ks:ks_name":"Mankaura Kondri",
    "ks:ks_type":"VILLAGE",
    "name:eng_x_preferred":[
        "Mankaura Kondri"
    ],
    "wof:name":"Mankaura Kondri",
    "wof:placetype":"locality"
},
  "geometry": {"coordinates":[81.98120400000001,27.572382],"type":"Point"}
}