{
  "type": "Feature",
  "properties": {
    "iso:country":"IN",
    "ks:ks_name":"Mahajubilee College Road",
    "ks:ks_pop":740,
    "ks:ks_type":"HABITATION",
    "name:eng_x_preferred":[
        "Mahajubilee College Road"
    ],
    "wof:name":"Mahajubilee College Road",
    "wof:placetype":"locality",
    "wof:population":740
},
  "geometry": {"coordinates":[76.276753,10.710163],"type":"Point"}
}