{
  "type": "Feature",
  "properties": {
    "iso:country":"IN",
    "ks:ks_name":"Khalachi Hulewadi",
    "ks:ks_pop":168,
    "ks:ks_type":"HABITATION",
    "name:eng_x_preferred":[
        "Khalachi Hulewadi"
    ],
    "wof:name":"Khalachi Hulewadi",
    "wof:placetype":"locality",
    "wof:population":168
},
  "geometry": {"coordinates":[73.749965,16.292008],"type":"Point"}
}