{
  "type": "Feature",
  "properties": {
    "iso:country":"IN",
    "ks:ks_name":"Gadabavalasa",
    "ks:ks_pop":77,
    "ks:ks_type":"HABITATION",
    "name:eng_x_preferred":[
        "Gadabavalasa"
    ],
    "wof:name":"Gadabavalasa",
    "wof:placetype":"locality",
    "wof:population":77
},
  "geometry": {"coordinates":[83.562,18.764161],"type":"Point"}
}