{
  "type": "Feature",
  "properties": {
    "iso:country":"IN",
    "ks:ks_name":"Mahalbaldi",
    "ks:ks_pop":0,
    "ks:ks_type":"VILLAGE",
    "name:eng_x_preferred":[
        "Mahalbaldi"
    ],
    "wof:name":"Mahalbaldi",
    "wof:placetype":"locality",
    "wof:population":0
},
  "geometry": {"coordinates":[88.283637,24.927423],"type":"Point"}
}