{
  "type": "Feature",
  "properties": {
    "iso:country":"IN",
    "ks:ks_alt_nam":"Mitr\u0101on",
    "ks:ks_name":"Mitraon",
    "ks:ks_type":"VILLAGE",
    "ks:ks_uagg_main":0,
    "name:eng_x_preferred":[
        "Mitraon"
    ],
    "name:eng_x_variant":[
        "Mitr\u0101on"
    ],
    "wof:name":"Mitraon",
    "wof:placetype":"neighbourhood"
},
  "geometry": {"coordinates":[76.945984,28.606227],"type":"Point"}
}