{
  "type": "Feature",
  "properties": {
    "gn:admin1_code":"21.0",
    "gn:admin2_code":"390.0",
    "gn:asciiname":"Parigad",
    "gn:country_code":"IN",
    "gn:dem":606,
    "gn:feature_class":"P",
    "gn:feature_code":"PPL",
    "gn:name":"P\u0101rigad",
    "gn:population":0,
    "gn:timezone":"Asia/Kolkata",
    "iso:country":"IN",
    "ks:ks_alt_nam":"P\u0101rigad",
    "ks:ks_name":"Parigad",
    "ks:ks_type":"VILLAGE",
    "name:eng_x_preferred":[
        "Parigad"
    ],
    "name:eng_x_variant":[
        "P\u0101rigad"
    ],
    "wof:name":"Parigad",
    "wof:placetype":"locality"
},
  "geometry": {"coordinates":[83.854938,19.964257],"type":"Point"}
}