{
  "type": "Feature",
  "properties": {
    "iso:country":"IN",
    "ks:ks_name":"Bondeli",
    "ks:ks_pop":47,
    "ks:ks_type":"HABITATION",
    "name:eng_x_preferred":[
        "Bondeli"
    ],
    "wof:name":"Bondeli",
    "wof:placetype":"locality",
    "wof:population":47
},
  "geometry": {"coordinates":[74.279059,15.243084],"type":"Point"}
}