{
  "type": "Feature",
  "properties": {
    "iso:country":"IN",
    "ks:ks_name":"Bibipur",
    "ks:ks_pop":47,
    "ks:ks_type":"HABITATION",
    "ks:ks_uagg_main":0,
    "name:eng_x_preferred":[
        "Bibipur"
    ],
    "wof:name":"Bibipur",
    "wof:placetype":"neighbourhood",
    "wof:population":47
},
  "geometry": {"coordinates":[82.29533600000001,26.512268],"type":"Point"}
}