{
  "type": "Feature",
  "properties": {
    "iso:country":"IN",
    "ks:ks_name":"Biroj Pada",
    "ks:ks_pop":426,
    "ks:ks_type":"HABITATION",
    "name:eng_x_preferred":[
        "Biroj Pada"
    ],
    "wof:name":"Biroj Pada",
    "wof:placetype":"locality",
    "wof:population":426
},
  "geometry": {"coordinates":[73.408428,20.30707],"type":"Point"}
}