{
  "type": "Feature",
  "properties": {
    "iso:country":"IN",
    "ks:ks_name":"Lahanzelliya",
    "ks:ks_pop":105,
    "ks:ks_type":"VILLAGE",
    "name:eng_x_preferred":[
        "Lahanzelliya"
    ],
    "wof:name":"Lahanzelliya",
    "wof:placetype":"locality",
    "wof:population":105
},
  "geometry": {"coordinates":[80.507204,20.446426],"type":"Point"}
}