{
  "type": "Feature",
  "properties": {
    "iso:country":"IN",
    "ks:ks_name":"Dukhali",
    "ks:ks_pop":115,
    "ks:ks_type":"VILLAGE",
    "name:eng_x_preferred":[
        "Dukhali"
    ],
    "wof:name":"Dukhali",
    "wof:placetype":"locality",
    "wof:population":115
},
  "geometry": {"coordinates":[73.94372199999999,22.684444],"type":"Point"}
}