{
  "type": "Feature",
  "properties": {
    "iso:country":"IN",
    "ks:ks_name":"Chenga",
    "ks:ks_pop":0,
    "ks:ks_type":"VILLAGE",
    "name:eng_x_preferred":[
        "Chenga"
    ],
    "wof:name":"Chenga",
    "wof:placetype":"locality",
    "wof:population":0
},
  "geometry": {"coordinates":[87.247613,22.066009],"type":"Point"}
}