{
  "type": "Feature",
  "properties": {
    "gn:admin1_code":"36.0",
    "gn:admin2_code":"184.0",
    "gn:asciiname":"Pandia",
    "gn:country_code":"IN",
    "gn:dem":93,
    "gn:feature_class":"P",
    "gn:feature_code":"PPL",
    "gn:name":"Pandia",
    "gn:population":0,
    "gn:timezone":"Asia/Kolkata",
    "iso:country":"IN",
    "name:bul_x_preferred":[
        "\u041f\u0430\u043d\u0434\u0438\u044f"
    ],
    "name:deu_x_preferred":[
        "Pandia"
    ],
    "name:fas_x_preferred":[
        "\u067e\u0627\u0646\u062f\u06cc\u0627"
    ],
    "name:hun_x_preferred":[
        "Pandia"
    ],
    "name:ita_x_preferred":[
        "Pandia"
    ],
    "name:jpn_x_preferred":[
        "\u30d1\u30f3\u30c7\u30a3\u30fc\u30a2"
    ],
    "name:lit_x_preferred":[
        "Pandija"
    ],
    "name:nld_x_preferred":[
        "Pandia"
    ],
    "name:por_x_preferred":[
        "Pandia"
    ],
    "name:spa_x_preferred":[
        "Pandia"
    ],
    "name:srp_x_preferred":[
        "\u041f\u0430\u043d\u0434\u0438\u0458\u0430"
    ],
    "wof:name":"Pandia",
    "wof:placetype":"locality"
},
  "geometry": {"coordinates":[82.68946,27.12736],"type":"Point"}
}