{
  "type": "Feature",
  "properties": {
    "gn:admin1_code":"19.0",
    "gn:admin2_code":"577.0",
    "gn:asciiname":"Madahalli Koppal",
    "gn:country_code":"IN",
    "gn:dem":801,
    "gn:feature_class":"P",
    "gn:feature_code":"PPL",
    "gn:name":"M\u0101dahalli Koppal",
    "gn:population":0,
    "gn:timezone":"Asia/Kolkata",
    "iso:country":"IN",
    "wof:name":"Madahalli Koppal",
    "wof:placetype":"neighbourhood"
},
  "geometry": {"coordinates":[76.36947000000001,12.30922],"type":"Point"}
}