{
  "type": "Feature",
  "properties": {
    "iso:country":"IN",
    "ks:ks_name":"Mehta Tola",
    "ks:ks_pop":1058,
    "ks:ks_type":"HABITATION",
    "name:eng_x_preferred":[
        "Mehta Tola"
    ],
    "wof:name":"Mehta Tola",
    "wof:placetype":"locality",
    "wof:population":1058
},
  "geometry": {"coordinates":[87.171336,25.790262],"type":"Point"}
}