{
  "type": "Feature",
  "properties": {
    "gn:admin1_code":"09",
    "gn:admin2_code":"486.0",
    "gn:asciiname":"Tadkachhla",
    "gn:country_code":"IN",
    "gn:dem":255,
    "gn:feature_class":"P",
    "gn:feature_code":"PPL",
    "gn:name":"T\u0101dkachhla",
    "gn:population":0,
    "gn:timezone":"Asia/Kolkata",
    "iso:country":"IN",
    "wof:name":"Tadkachhla",
    "wof:placetype":"locality"
},
  "geometry": {"coordinates":[73.95508000000002,22.03387],"type":"Point"}
}