{
  "type": "Feature",
  "properties": {
    "iso:country":"IN",
    "ks:ks_name":"Mauje Bhasahi",
    "ks:ks_pop":170,
    "ks:ks_type":"HABITATION",
    "name:eng_x_preferred":[
        "Mauje Bhasahi"
    ],
    "wof:name":"Mauje Bhasahi",
    "wof:placetype":"locality",
    "wof:population":170
},
  "geometry": {"coordinates":[84.47808999999999,26.498055],"type":"Point"}
}