{
  "type": "Feature",
  "properties": {
    "iso:country":"IN",
    "ks:ks_name":"New Hanumanpur Thanda",
    "ks:ks_pop":81,
    "ks:ks_type":"HABITATION",
    "name:eng_x_preferred":[
        "New Hanumanpur Thanda"
    ],
    "wof:name":"New Hanumanpur Thanda",
    "wof:placetype":"locality",
    "wof:population":81
},
  "geometry": {"coordinates":[78.535163,17.856317],"type":"Point"}
}