{
  "type": "Feature",
  "properties": {
    "gn:admin1_code":"36",
    "gn:admin2_code":"179.0",
    "gn:asciiname":"Paigapur",
    "gn:country_code":"IN",
    "gn:dem":103,
    "gn:feature_class":"P",
    "gn:feature_code":"PPL",
    "gn:name":"Paig\u0101pur",
    "gn:population":0,
    "gn:timezone":"Asia/Kolkata",
    "iso:country":"IN",
    "ks:ks_alt_nam":"Paig\u0101pur",
    "ks:ks_name":"Paigapur",
    "ks:ks_type":"VILLAGE",
    "ks:ks_uagg_main":0,
    "name:eng_x_preferred":[
        "Paigapur"
    ],
    "name:eng_x_variant":[
        "Paig\u0101pur"
    ],
    "wof:name":"Paigapur",
    "wof:placetype":"neighbourhood"
},
  "geometry": {"coordinates":[82.043689,26.291755],"type":"Point"}
}