{
  "type": "Feature",
  "properties": {
    "gn:admin1_code":"19.0",
    "gn:asciiname":"Chippar",
    "gn:country_code":"IN",
    "gn:dem":55,
    "gn:feature_class":"P",
    "gn:feature_code":"PPL",
    "gn:name":"Chipp\u0101r",
    "gn:population":0,
    "gn:timezone":"Asia/Kolkata",
    "iso:country":"IN",
    "ks:ks_name":"Chippar",
    "ks:ks_pop":1058,
    "ks:ks_type":"HABITATION",
    "name:eng_x_preferred":[
        "Chippar"
    ],
    "name:mal_x_preferred":[
        "\u0d1a\u0d3f\u0d2a\u0d4d\u0d2a\u0d3e\u0d7c"
    ],
    "wof:name":"Chippar",
    "wof:placetype":"locality",
    "wof:population":1058
},
  "geometry": {"coordinates":[75.004627,12.710863],"type":"Point"}
}