{
  "type": "Feature",
  "properties": {
    "gn:admin1_code":"21",
    "gn:admin2_code":"394.0",
    "gn:asciiname":"Kholigaon",
    "gn:country_code":"IN",
    "gn:dem":445,
    "gn:feature_class":"P",
    "gn:feature_code":"PPL",
    "gn:name":"Kholigaon",
    "gn:population":0,
    "gn:timezone":"Asia/Kolkata",
    "iso:country":"IN",
    "ks:ks_name":"Kholigaon",
    "ks:ks_pop":476,
    "ks:ks_type":"VILLAGE",
    "name:eng_x_preferred":[
        "Kholigaon"
    ],
    "wof:name":"Kholigaon",
    "wof:placetype":"locality",
    "wof:population":476
},
  "geometry": {"coordinates":[82.52382,20.575764],"type":"Point"}
}