{
  "type": "Feature",
  "properties": {
    "iso:country":"IN",
    "ks:ks_name":"Lulad",
    "ks:ks_pop":171,
    "ks:ks_type":"VILLAGE",
    "name:eng_x_preferred":[
        "Lulad"
    ],
    "wof:name":"Lulad",
    "wof:placetype":"locality",
    "wof:population":171
},
  "geometry": {"coordinates":[78.87487,30.01848],"type":"Point"}
}