{
  "type": "Feature",
  "properties": {
    "iso:country":"IN",
    "ks:ks_name":"Manjhipara",
    "ks:ks_pop":164,
    "ks:ks_type":"HABITATION",
    "name:eng_x_preferred":[
        "Manjhipara"
    ],
    "wof:name":"Manjhipara",
    "wof:placetype":"locality",
    "wof:population":164
},
  "geometry": {"coordinates":[81.562067,19.013623],"type":"Point"}
}