{
  "type": "Feature",
  "properties": {
    "iso:country":"IN",
    "ks:ks_name":"Burhna",
    "ks:ks_pop":53,
    "ks:ks_type":"VILLAGE",
    "name:eng_x_preferred":[
        "Burhna"
    ],
    "wof:name":"Burhna",
    "wof:placetype":"locality",
    "wof:population":53
},
  "geometry": {"coordinates":[86.050658,24.700042],"type":"Point"}
}