{
  "type": "Feature",
  "properties": {
    "iso:country":"IN",
    "ks:ks_name":"Dakshin Bhasapur",
    "ks:ks_pop":509,
    "ks:ks_type":"VILLAGE",
    "name:eng_x_preferred":[
        "Dakshin Bhasapur"
    ],
    "wof:name":"Dakshin Bhasapur",
    "wof:placetype":"locality",
    "wof:population":509
},
  "geometry": {"coordinates":[87.658271,23.234799],"type":"Point"}
}