{
  "type": "Feature",
  "properties": {
    "iso:country":"IN",
    "ks:ks_name":"Goibandha",
    "ks:ks_pop":198,
    "ks:ks_type":"HABITATION",
    "name:eng_x_preferred":[
        "Goibandha"
    ],
    "wof:name":"Goibandha",
    "wof:placetype":"locality",
    "wof:population":198
},
  "geometry": {"coordinates":[82.53948699999999,19.660251],"type":"Point"}
}