{
  "type": "Feature",
  "properties": {
    "iso:country":"IN",
    "ks:ks_alt_nam":"Peraiy\u016br",
    "ks:ks_name":"Peraiyur",
    "ks:ks_pop":3811,
    "ks:ks_type":"VILLAGE",
    "name:eng_x_preferred":[
        "Peraiyur"
    ],
    "name:eng_x_variant":[
        "Peraiy\u016br"
    ],
    "wof:name":"Peraiyur",
    "wof:placetype":"locality",
    "wof:population":3811
},
  "geometry": {"coordinates":[78.435321,9.352275],"type":"Point"}
}