{
  "type": "Feature",
  "properties": {
    "gn:admin1_code":"34.0",
    "gn:admin2_code":"209.0",
    "gn:asciiname":"Kurwa",
    "gn:country_code":"IN",
    "gn:dem":61,
    "gn:feature_class":"P",
    "gn:feature_code":"PPL",
    "gn:name":"Kurwa",
    "gn:population":0,
    "gn:timezone":"Asia/Kolkata",
    "iso:country":"IN",
    "ks:ks_name":"Kurwa",
    "ks:ks_pop":739,
    "ks:ks_type":"VILLAGE",
    "ks:ks_uagg_main":0,
    "name:eng_x_preferred":[
        "Kurwa"
    ],
    "wof:name":"Kurwa",
    "wof:placetype":"neighbourhood",
    "wof:population":739
},
  "geometry": {"coordinates":[87.28849099999999,26.192961],"type":"Point"}
}