{
  "type": "Feature",
  "properties": {
    "iso:country":"IN",
    "ks:ks_alt_nam":"Naba chandra para",
    "ks:ks_name":"Naba Chandra Para",
    "ks:ks_pop":344,
    "ks:ks_type":"HABITATION",
    "name:eng_x_preferred":[
        "Naba Chandra Para"
    ],
    "wof:name":"Naba Chandra Para",
    "wof:placetype":"locality",
    "wof:population":344
},
  "geometry": {"coordinates":[91.348388,23.344681],"type":"Point"}
}