{
  "type": "Feature",
  "properties": {
    "iso:country":"IN",
    "ks:ks_alt_nam":"mahargoan",
    "ks:ks_name":"Mahargoan",
    "ks:ks_pop":342,
    "ks:ks_type":"HABITATION",
    "name:eng_x_preferred":[
        "Mahargoan"
    ],
    "wof:name":"Mahargoan",
    "wof:placetype":"locality",
    "wof:population":342
},
  "geometry": {"coordinates":[78.947391,30.375368],"type":"Point"}
}