{
  "type": "Feature",
  "properties": {
    "iso:country":"IN",
    "ks:ks_alt_nam":"KHAUTITOLA",
    "ks:ks_name":"Khautitola",
    "ks:ks_pop":181,
    "ks:ks_type":"HABITATION",
    "name:eng_x_preferred":[
        "Khautitola"
    ],
    "wof:name":"Khautitola",
    "wof:placetype":"locality",
    "wof:population":181
},
  "geometry": {"coordinates":[84.960561,23.759754],"type":"Point"}
}