{
  "type": "Feature",
  "properties": {
    "iso:country":"IN",
    "ks:ks_name":"Jalpura",
    "ks:ks_pop":1561,
    "ks:ks_type":"VILLAGE",
    "ks:ks_uagg_main":0,
    "name:eng_x_preferred":[
        "Jalpura"
    ],
    "wof:name":"Jalpura",
    "wof:placetype":"neighbourhood",
    "wof:population":1561
},
  "geometry": {"coordinates":[77.439635,28.544386],"type":"Point"}
}