{
  "type": "Feature",
  "properties": {
    "gn:admin1_code":"2.0",
    "gn:admin2_code":"543.0",
    "gn:asciiname":"Chandrammapeta",
    "gn:country_code":"IN",
    "gn:dem":116,
    "gn:feature_class":"P",
    "gn:feature_code":"PPL",
    "gn:name":"Chandrammapeta",
    "gn:population":0,
    "gn:timezone":"Asia/Kolkata",
    "iso:country":"IN",
    "ks:ks_name":"Chandrayyapeta",
    "ks:ks_pop":117,
    "ks:ks_type":"HABITATION",
    "name:eng_x_preferred":[
        "Chandrayyapeta"
    ],
    "name:eng_x_variant":[
        "Chandrammapeta"
    ],
    "wof:name":"Chandrayyapeta",
    "wof:placetype":"locality",
    "wof:population":117
},
  "geometry": {"coordinates":[83.30445899999999,18.661889],"type":"Point"}
}