{
  "type": "Feature",
  "properties": {
    "iso:country":"IN",
    "ks:ks_name":"Girinayakanapalya",
    "ks:ks_pop":56,
    "ks:ks_type":"HABITATION",
    "name:eng_x_preferred":[
        "Girinayakanapalya"
    ],
    "wof:name":"Girinayakanapalya",
    "wof:placetype":"locality",
    "wof:population":56
},
  "geometry": {"coordinates":[77.03204100000001,13.128115],"type":"Point"}
}