{
  "type": "Feature",
  "properties": {
    "iso:country":"IN",
    "ks:ks_name":"Barkop",
    "ks:ks_pop":1184,
    "ks:ks_type":"VILLAGE",
    "name:eng_x_preferred":[
        "Barkop"
    ],
    "wof:name":"Barkop",
    "wof:placetype":"locality",
    "wof:population":1184
},
  "geometry": {"coordinates":[87.255016,24.937654],"type":"Point"}
}