{
  "type": "Feature",
  "properties": {
    "iso:country":"IN",
    "ks:ks_name":"Kuthal Gaon",
    "ks:ks_pop":140,
    "ks:ks_type":"VILLAGE",
    "ks:ks_uagg_main":0,
    "name:eng_x_preferred":[
        "Kuthal Gaon"
    ],
    "wof:name":"Kuthal Gaon",
    "wof:placetype":"locality",
    "wof:population":140
},
  "geometry": {"coordinates":[78.089467,30.399307],"type":"Point"}
}