{
  "type": "Feature",
  "properties": {
    "iso:country":"IN",
    "ks:ks_name":"Bajora",
    "ks:ks_pop":332,
    "ks:ks_type":"VILLAGE",
    "ks:ks_uagg_main":0,
    "name:eng_x_preferred":[
        "Bajora"
    ],
    "wof:name":"Bajora",
    "wof:placetype":"neighbourhood",
    "wof:population":332
},
  "geometry": {"coordinates":[86.908734,23.164228],"type":"Point"}
}