{
  "type": "Feature",
  "properties": {
    "iso:country":"IN",
    "ks:ks_name":"Karimane",
    "ks:ks_pop":16,
    "ks:ks_type":"VILLAGE",
    "name:eng_x_preferred":[
        "Karimane"
    ],
    "wof:name":"Karimane",
    "wof:placetype":"locality",
    "wof:population":16
},
  "geometry": {"coordinates":[75.365565,13.447397],"type":"Point"}
}