{
  "type": "Feature",
  "properties": {
    "iso:country":"IN",
    "ks:ks_name":"Chhatahar",
    "ks:ks_pop":622,
    "ks:ks_type":"VILLAGE",
    "ks:ks_uagg_main":0,
    "name:eng_x_preferred":[
        "Chhatahar"
    ],
    "wof:name":"Chhatahar",
    "wof:placetype":"neighbourhood",
    "wof:population":622
},
  "geometry": {"coordinates":[85.972973,20.104219],"type":"Point"}
}