{
  "type": "Feature",
  "properties": {
    "iso:country":"IN",
    "ks:ks_name":"Jamalpur",
    "ks:ks_pop":3752,
    "ks:ks_type":"VILLAGE",
    "ks:ks_uagg_main":0,
    "name:eng_x_preferred":[
        "Jamalpur"
    ],
    "wof:name":"Jamalpur",
    "wof:placetype":"locality",
    "wof:population":3752
},
  "geometry": {"coordinates":[88.16559700000001,22.447629],"type":"Point"}
}