{
  "type": "Feature",
  "properties": {
    "iso:country":"IN",
    "ks:ks_alt_nam":"1 No.Kundil",
    "ks:ks_name":"1 No.kundil",
    "ks:ks_pop":226,
    "ks:ks_type":"HABITATION",
    "name:eng_x_preferred":[
        "1 No.kundil"
    ],
    "wof:name":"1 No.kundil",
    "wof:placetype":"locality",
    "wof:population":226
},
  "geometry": {"coordinates":[95.64959500000001,27.821826],"type":"Point"}
}