{
  "type": "Feature",
  "properties": {
    "gn:admin1_code":"36",
    "gn:admin2_code":"185.0",
    "gn:asciiname":"Khamaria Shujaet",
    "gn:country_code":"IN",
    "gn:dem":92,
    "gn:feature_class":"P",
    "gn:feature_code":"PPL",
    "gn:name":"Khamaria Shujaet",
    "gn:population":0,
    "gn:timezone":"Asia/Kolkata",
    "iso:country":"IN",
    "ks:ks_name":"Khamariya Sujat",
    "ks:ks_pop":531,
    "ks:ks_type":"VILLAGE",
    "name:eng_x_preferred":[
        "Khamariya Sujat"
    ],
    "name:eng_x_variant":[
        "Khamaria Shujaet"
    ],
    "wof:name":"Khamariya Sujat",
    "wof:placetype":"locality",
    "wof:population":531
},
  "geometry": {"coordinates":[82.474379,26.762419],"type":"Point"}
}