{
  "type": "Feature",
  "properties": {
    "iso:country":"IN",
    "ks:ks_name":"Jajiwal Shribalaji",
    "ks:ks_pop":272,
    "ks:ks_type":"HABITATION",
    "name:eng_x_preferred":[
        "Jajiwal Shribalaji"
    ],
    "wof:name":"Jajiwal Shribalaji",
    "wof:placetype":"locality",
    "wof:population":272
},
  "geometry": {"coordinates":[73.227768,26.368615],"type":"Point"}
}