{
  "type": "Feature",
  "properties": {
    "iso:country":"IN",
    "ks:ks_name":"Tilla Bari Camp",
    "ks:ks_pop":148,
    "ks:ks_type":"HABITATION",
    "name:eng_x_preferred":[
        "Tilla Bari Camp"
    ],
    "wof:name":"Tilla Bari Camp",
    "wof:placetype":"locality",
    "wof:population":148
},
  "geometry": {"coordinates":[91.675607,23.672681],"type":"Point"}
}