{
  "type": "Feature",
  "properties": {
    "iso:country":"IN",
    "ks:ks_name":"Bandhawabhaibant",
    "ks:ks_pop":2277,
    "ks:ks_type":"HABITATION",
    "name:eng_x_preferred":[
        "Bandhawabhaibant"
    ],
    "wof:name":"Bandhawabhaibant",
    "wof:placetype":"locality",
    "wof:population":2277
},
  "geometry": {"coordinates":[81.698502,24.815564],"type":"Point"}
}