{
  "type": "Feature",
  "properties": {
    "iso:country":"IN",
    "ks:ks_name":"Bhaga Talab",
    "ks:ks_pop":723,
    "ks:ks_type":"VILLAGE",
    "name:eng_x_preferred":[
        "Bhaga Talab"
    ],
    "wof:name":"Bhaga Talab",
    "wof:placetype":"locality",
    "wof:population":723
},
  "geometry": {"coordinates":[73.938979,23.483313],"type":"Point"}
}