{
  "type": "Feature",
  "properties": {
    "iso:country":"IN",
    "ks:ks_alt_nam":"Jiyau khara",
    "ks:ks_name":"Jiyau Khara",
    "ks:ks_pop":21,
    "ks:ks_type":"HABITATION",
    "name:eng_x_preferred":[
        "Jiyau Khara"
    ],
    "wof:name":"Jiyau Khara",
    "wof:placetype":"locality",
    "wof:population":21
},
  "geometry": {"coordinates":[69.648484,26.866958],"type":"Point"}
}