{
  "type": "Feature",
  "properties": {
    "gn:admin1_code":"2",
    "gn:admin2_code":"545.0",
    "gn:asciiname":"Buchchi Sityyammapeta",
    "gn:country_code":"IN",
    "gn:dem":81,
    "gn:feature_class":"P",
    "gn:feature_code":"PPL",
    "gn:name":"Buchchi S\u012btyyammapeta",
    "gn:population":0,
    "gn:timezone":"Asia/Kolkata",
    "iso:country":"IN",
    "wof:name":"Buchchi Sityyammapeta",
    "wof:placetype":"locality"
},
  "geometry": {"coordinates":[82.56404000000001,17.45624],"type":"Point"}
}