{
  "type": "Feature",
  "properties": {
    "iso:country":"IN",
    "ks:ks_name":"Ganigarapalya",
    "ks:ks_pop":74,
    "ks:ks_type":"HABITATION",
    "name:eng_x_preferred":[
        "Ganigarapalya"
    ],
    "wof:name":"Ganigarapalya",
    "wof:placetype":"locality",
    "wof:population":74
},
  "geometry": {"coordinates":[77.36429200000001,13.055495],"type":"Point"}
}