{
  "type": "Feature",
  "properties": {
    "iso:country":"IN",
    "ks:ks_name":"Nawadih",
    "ks:ks_pop":430,
    "ks:ks_type":"HABITATION",
    "name:eng_x_preferred":[
        "Nawadih"
    ],
    "wof:name":"Nawadih",
    "wof:placetype":"locality",
    "wof:population":430
},
  "geometry": {"coordinates":[83.091565,22.248567],"type":"Point"}
}