{
  "type": "Feature",
  "properties": {
    "iso:country":"IN",
    "ks:ks_name":"6 SAD",
    "ks:ks_pop":184,
    "ks:ks_type":"VILLAGE",
    "name:eng_x_preferred":[
        "6 SAD"
    ],
    "wof:name":"6 SAD",
    "wof:placetype":"locality",
    "wof:population":184
},
  "geometry": {"coordinates":[73.556861,29.41225],"type":"Point"}
}