{
  "type": "Feature",
  "properties": {
    "iso:country":"IN",
    "ks:ks_name":"Bagasol",
    "ks:ks_pop":531,
    "ks:ks_type":"VILLAGE",
    "ks:ks_uagg_main":0,
    "name:eng_x_preferred":[
        "Bagasol"
    ],
    "wof:name":"Bagasol",
    "wof:placetype":"neighbourhood",
    "wof:population":531
},
  "geometry": {"coordinates":[87.402334,22.506599],"type":"Point"}
}