{
  "type": "Feature",
  "properties": {
    "iso:country":"IN",
    "ks:ks_name":"Janatha Colony",
    "ks:ks_pop":130,
    "ks:ks_type":"HABITATION",
    "name:eng_x_preferred":[
        "Janatha Colony"
    ],
    "wof:name":"Janatha Colony",
    "wof:placetype":"locality",
    "wof:population":130
},
  "geometry": {"coordinates":[77.260901,13.120626],"type":"Point"}
}