{
  "type": "Feature",
  "properties": {
    "gn:admin1_code":"13.0",
    "gn:admin2_code":"592.0",
    "gn:asciiname":"Anantavur",
    "gn:country_code":"IN",
    "gn:dem":34,
    "gn:feature_class":"P",
    "gn:feature_code":"PPL",
    "gn:name":"Anant\u0101v\u016br",
    "gn:population":0,
    "gn:timezone":"Asia/Kolkata",
    "iso:country":"IN",
    "name:fas_x_preferred":[
        "\u0627\u0646\u0627\u0646\u062a\u0648\u0631"
    ],
    "name:mal_x_preferred":[
        "\u0d05\u0d28\u0d28\u0d4d\u0d24\u0d3e\u0d35\u0d42\u0d7c"
    ],
    "wof:name":"Anantavur",
    "wof:placetype":"locality"
},
  "geometry": {"coordinates":[75.98403,10.90567],"type":"Point"}
}