{
  "type": "Feature",
  "properties": {
    "iso:country":"IN",
    "ks:ks_name":"Salidaha Paschim",
    "ks:ks_pop":800,
    "ks:ks_type":"HABITATION",
    "name:eng_x_preferred":[
        "Salidaha Paschim"
    ],
    "wof:name":"Salidaha Paschim",
    "wof:placetype":"locality",
    "wof:population":800
},
  "geometry": {"coordinates":[88.479782,22.899253],"type":"Point"}
}