{
  "type": "Feature",
  "properties": {
    "iso:country":"IN",
    "ks:ks_name":"Jhala",
    "ks:ks_pop":20,
    "ks:ks_type":"HABITATION",
    "name:eng_x_preferred":[
        "Jhala"
    ],
    "wof:name":"Jhala",
    "wof:placetype":"locality",
    "wof:population":20
},
  "geometry": {"coordinates":[80.420661,27.46117],"type":"Point"}
}