{
  "type": "Feature",
  "properties": {
    "iso:country":"IN",
    "ks:ks_alt_nam":"New AD Colony",
    "ks:ks_name":"New Ad Colony",
    "ks:ks_pop":190,
    "ks:ks_type":"HABITATION",
    "name:eng_x_preferred":[
        "New Ad Colony"
    ],
    "wof:name":"New Ad Colony",
    "wof:placetype":"locality",
    "wof:population":190
},
  "geometry": {"coordinates":[78.926717,10.172745],"type":"Point"}
}