{
  "type": "Feature",
  "properties": {
    "iso:country":"IN",
    "ks:ks_name":"Sharampur",
    "ks:ks_pop":3894,
    "ks:ks_type":"HABITATION",
    "ks:ks_uagg_main":0,
    "name:eng_x_preferred":[
        "Sharampur"
    ],
    "wof:name":"Sharampur",
    "wof:placetype":"locality",
    "wof:population":3894
},
  "geometry": {"coordinates":[88.319716,22.745632],"type":"Point"}
}