{
  "type": "Feature",
  "properties": {
    "iso:country":"IN",
    "qs:name":"Kumbharwadi Tarf Palpene",
    "qs:name_adm0":"India",
    "qs:name_adm1":"Maharashtra",
    "qs:photos":3,
    "qs:photos_1k":1,
    "qs:photos_9k":1,
    "qs:photos_9r":1,
    "qs:photos_all":3,
    "qs:photos_sr":1,
    "qs:placetype":"Town",
    "qs:pop_sr":"0",
    "wof:name":"Kumbharwadi Tarf Palpene",
    "wof:placetype":"locality"
},
  "geometry": {"coordinates":[73.195381,17.471274],"type":"Point"}
}