{
  "type": "Feature",
  "properties": {
    "iso:country":"IN",
    "ks:ks_name":"Belgaon",
    "ks:ks_type":"VILLAGE",
    "name:eng_x_preferred":[
        "Belgaon"
    ],
    "wof:name":"Belgaon",
    "wof:placetype":"locality"
},
  "geometry": {"coordinates":[79.212322,20.332736],"type":"Point"}
}