{
  "type": "Feature",
  "properties": {
    "gn:admin1_code":"2",
    "gn:admin2_code":"547.0",
    "gn:asciiname":"Chattannavaram",
    "gn:country_code":"IN",
    "gn:dem":59,
    "gn:feature_class":"P",
    "gn:feature_code":"PPL",
    "gn:name":"Chattannavaram",
    "gn:population":0,
    "gn:timezone":"Asia/Kolkata",
    "iso:country":"IN",
    "wof:name":"Chattannavaram",
    "wof:placetype":"locality"
},
  "geometry": {"coordinates":[80.42220999999998,16.78054],"type":"Point"}
}