{
  "type": "Feature",
  "properties": {
    "iso:country":"IN",
    "ks:ks_name":"Umdap",
    "ks:ks_pop":470,
    "ks:ks_type":"HABITATION",
    "name:eng_x_preferred":[
        "Umdap"
    ],
    "wof:name":"Umdap",
    "wof:placetype":"locality",
    "wof:population":470
},
  "geometry": {"coordinates":[92.475747,25.850377],"type":"Point"}
}