{
  "type": "Feature",
  "properties": {
    "iso:country":"IN",
    "ks:ks_name":"Jhinkia",
    "ks:ks_pop":602,
    "ks:ks_type":"VILLAGE",
    "ks:ks_uagg_main":0,
    "name:eng_x_preferred":[
        "Jhinkia"
    ],
    "wof:name":"Jhinkia",
    "wof:placetype":"neighbourhood",
    "wof:population":602
},
  "geometry": {"coordinates":[88.632374,22.610012],"type":"Point"}
}