{
  "type": "Feature",
  "properties": {
    "gn:admin1_code":"19.0",
    "gn:admin2_code":"574.0",
    "gn:asciiname":"Suledevarahalli",
    "gn:country_code":"IN",
    "gn:dem":992,
    "gn:feature_class":"P",
    "gn:feature_code":"PPL",
    "gn:name":"S\u016bledevarahalli",
    "gn:population":0,
    "gn:timezone":"Asia/Kolkata",
    "iso:country":"IN",
    "wof:name":"Suledevarahalli",
    "wof:placetype":"locality"
},
  "geometry": {"coordinates":[76.01554,13.10809],"type":"Point"}
}