{
  "type": "Feature",
  "properties": {
    "gn:admin1_code":"19.0",
    "gn:admin2_code":"574.0",
    "gn:asciiname":"Suledevarahalli",
    "gn:country_code":"IN",
    "gn:dem":992,
    "gn:feature_class":"P",
    "gn:feature_code":"PPL",
    "gn:name":"S\u016bledevarahalli",
    "gn:population":0,
    "gn:timezone":"Asia/Kolkata",
    "iso:country":"IN",
    "ks:ks_name":"Suledevarahalli",
    "ks:ks_pop":93,
    "ks:ks_type":"HABITATION",
    "name:eng_x_preferred":[
        "Suledevarahalli"
    ],
    "wof:name":"Suledevarahalli",
    "wof:placetype":"locality",
    "wof:population":93
},
  "geometry": {"coordinates":[76.016992,13.110975],"type":"Point"}
}