{
  "type": "Feature",
  "properties": {
    "iso:country":"IN",
    "ks:ks_name":"Baheraha",
    "ks:ks_pop":465,
    "ks:ks_type":"VILLAGE",
    "name:eng_x_preferred":[
        "Baheraha"
    ],
    "wof:name":"Baheraha",
    "wof:placetype":"locality",
    "wof:population":465
},
  "geometry": {"coordinates":[81.441575,23.467774],"type":"Point"}
}