{
  "type": "Feature",
  "properties": {
    "iso:country":"IN",
    "ks:ks_name":"Chak Bagadari",
    "ks:ks_pop":407,
    "ks:ks_type":"HABITATION",
    "name:eng_x_preferred":[
        "Chak Bagadari"
    ],
    "wof:name":"Chak Bagadari",
    "wof:placetype":"locality",
    "wof:population":407
},
  "geometry": {"coordinates":[83.151557,23.97605],"type":"Point"}
}