{
  "type": "Feature",
  "properties": {
    "iso:country":"IN",
    "ks:ks_name":"Deep Nagar",
    "ks:ks_pop":356,
    "ks:ks_type":"HABITATION",
    "name:eng_x_preferred":[
        "Deep Nagar"
    ],
    "wof:name":"Deep Nagar",
    "wof:placetype":"locality",
    "wof:population":356
},
  "geometry": {"coordinates":[72.16793199999999,27.253379],"type":"Point"}
}