{
  "type": "Feature",
  "properties": {
    "iso:country":"IN",
    "ks:ks_name":"Manjunthacolony",
    "ks:ks_pop":93,
    "ks:ks_type":"HABITATION",
    "name:eng_x_preferred":[
        "Manjunthacolony"
    ],
    "wof:name":"Manjunthacolony",
    "wof:placetype":"locality",
    "wof:population":93
},
  "geometry": {"coordinates":[78.775193,13.261209],"type":"Point"}
}