{
  "type": "Feature",
  "properties": {
    "iso:country":"IN",
    "ks:ks_name":"Rajulapadu",
    "ks:ks_pop":80,
    "ks:ks_type":"HABITATION",
    "name:eng_x_preferred":[
        "Rajulapadu"
    ],
    "wof:name":"Rajulapadu",
    "wof:placetype":"locality",
    "wof:population":80
},
  "geometry": {"coordinates":[82.14770900000001,17.771251],"type":"Point"}
}