{
  "type": "Feature",
  "properties": {
    "gn:admin1_code":"16",
    "gn:admin2_code":"522.0",
    "gn:asciiname":"Manjur",
    "gn:country_code":"IN",
    "gn:dem":605,
    "gn:feature_class":"P",
    "gn:feature_code":"PPL",
    "gn:name":"Manj\u016br",
    "gn:population":0,
    "gn:timezone":"Asia/Kolkata",
    "iso:country":"IN",
    "wof:name":"Manjur",
    "wof:placetype":"locality"
},
  "geometry": {"coordinates":[74.31667,18.93333],"type":"Point"}
}