{
  "type": "Feature",
  "properties": {
    "iso:country":"IN",
    "ks:ks_name":"Mukundapur",
    "ks:ks_pop":876,
    "ks:ks_type":"VILLAGE",
    "ks:ks_uagg_main":0,
    "name:eng_x_preferred":[
        "Mukundapur"
    ],
    "wof:name":"Mukundapur",
    "wof:placetype":"neighbourhood",
    "wof:population":876
},
  "geometry": {"coordinates":[84.45689,19.18017],"type":"Point"}
}