{
  "type": "Feature",
  "properties": {
    "gn:admin1_code":"36",
    "gn:admin2_code":"194.0",
    "gn:asciiname":"Bansgaon",
    "gn:country_code":"IN",
    "gn:dem":90,
    "gn:feature_class":"P",
    "gn:feature_code":"PPL",
    "gn:name":"B\u0101nsg\u0101on",
    "gn:population":0,
    "gn:timezone":"Asia/Kolkata",
    "iso:country":"IN",
    "name:bih_x_preferred":[
        "\u092c\u093e\u0901\u0938\u0917\u093e\u0901\u0935"
    ],
    "name:bpy_x_preferred":[
        "\u09ac\u09a8\u09b8\u0997\u09be\u0981\u0993"
    ],
    "name:ceb_x_preferred":[
        "B\u0101nsgaon"
    ],
    "name:ita_x_preferred":[
        "Bansgaon"
    ],
    "name:mlg_x_preferred":[
        "Bansgaon"
    ],
    "name:msa_x_preferred":[
        "Bansgaon"
    ],
    "name:new_x_preferred":[
        "\u092c\u093e\u0902\u0938\u0917\u093e\u0935\u0902"
    ],
    "name:nld_x_preferred":[
        "Bansgaon"
    ],
    "name:pol_x_preferred":[
        "Bansgaon"
    ],
    "name:por_x_preferred":[
        "Bansgaon"
    ],
    "name:swe_x_preferred":[
        "B\u0101nsgaon"
    ],
    "name:urd_x_preferred":[
        "\u0628\u0627\u0646\u0633 \u06af\u0627\u0624\u06ba"
    ],
    "name:vie_x_preferred":[
        "Bansgaon"
    ],
    "name:zho_x_preferred":[
        "\u73ed\u65af\u52a0\u5965\u6069"
    ],
    "wof:name":"Bansgaon",
    "wof:placetype":"locality"
},
  "geometry": {"coordinates":[82.55696999999998,26.05388],"type":"Point"}
}