{
  "type": "Feature",
  "properties": {
    "iso:country":"IN",
    "ks:ks_alt_nam":"NAWADIH 3",
    "ks:ks_name":"Nawadih 3",
    "ks:ks_pop":252,
    "ks:ks_type":"HABITATION",
    "name:eng_x_preferred":[
        "Nawadih 3"
    ],
    "wof:name":"Nawadih 3",
    "wof:placetype":"locality",
    "wof:population":252
},
  "geometry": {"coordinates":[84.859611,24.24576],"type":"Point"}
}