{
  "type": "Feature",
  "properties": {
    "gn:admin1_code":"2.0",
    "gn:admin2_code":"553.0",
    "gn:asciiname":"Ravanahalli",
    "gn:country_code":"IN",
    "gn:dem":474,
    "gn:feature_class":"P",
    "gn:feature_code":"PPL",
    "gn:name":"Ravanahalli",
    "gn:population":0,
    "gn:timezone":"Asia/Kolkata",
    "iso:country":"IN",
    "wof:name":"Ravanahalli",
    "wof:placetype":"locality"
},
  "geometry": {"coordinates":[77.06403,14.6801],"type":"Point"}
}