{
  "type": "Feature",
  "properties": {
    "iso:country":"IN",
    "ks:ks_name":"Bhari",
    "ks:ks_pop":470,
    "ks:ks_type":"VILLAGE",
    "name:eng_x_preferred":[
        "Bhari"
    ],
    "wof:name":"Bhari",
    "wof:placetype":"locality",
    "wof:population":470
},
  "geometry": {"coordinates":[83.13617499999999,27.349992],"type":"Point"}
}