{
  "type": "Feature",
  "properties": {
    "iso:country":"IN",
    "ks:ks_alt_nam":"JARIAMAHTOLA",
    "ks:ks_name":"Jariamahtola",
    "ks:ks_pop":436,
    "ks:ks_type":"HABITATION",
    "name:eng_x_preferred":[
        "Jariamahtola"
    ],
    "wof:name":"Jariamahtola",
    "wof:placetype":"locality",
    "wof:population":436
},
  "geometry": {"coordinates":[85.708938,24.05618],"type":"Point"}
}