{
  "type": "Feature",
  "properties": {
    "iso:country":"IN",
    "ks:ks_name":"Bharaua",
    "ks:ks_type":"VILLAGE",
    "name:eng_x_preferred":[
        "Bharaua"
    ],
    "wof:name":"Bharaua",
    "wof:placetype":"locality"
},
  "geometry": {"coordinates":[79.57314599999999,28.328239],"type":"Point"}
}