{
  "type": "Feature",
  "properties": {
    "iso:country":"IN",
    "ks:ks_name":"Baje Dakshinal",
    "ks:ks_pop":368,
    "ks:ks_type":"VILLAGE",
    "ks:ks_uagg_main":0,
    "name:eng_x_preferred":[
        "Baje Dakshinal"
    ],
    "wof:name":"Baje Dakshinal",
    "wof:placetype":"neighbourhood",
    "wof:population":368
},
  "geometry": {"coordinates":[88.184301,25.516252],"type":"Point"}
}