{
  "type": "Feature",
  "properties": {
    "iso:country":"IN",
    "ks:ks_name":"Rettaikulam",
    "ks:ks_pop":1131,
    "ks:ks_type":"HABITATION",
    "name:eng_x_preferred":[
        "Rettaikulam"
    ],
    "wof:name":"Rettaikulam",
    "wof:placetype":"locality",
    "wof:population":1131
},
  "geometry": {"coordinates":[77.415122,8.99333],"type":"Point"}
}