{
  "type": "Feature",
  "properties": {
    "iso:country":"IN",
    "ks:ks_alt_nam":"BALASO SHINDE WASTI",
    "ks:ks_name":"Balaso Shinde Wasti",
    "ks:ks_pop":75,
    "ks:ks_type":"HABITATION",
    "name:eng_x_preferred":[
        "Balaso Shinde Wasti"
    ],
    "wof:name":"Balaso Shinde Wasti",
    "wof:placetype":"locality",
    "wof:population":75
},
  "geometry": {"coordinates":[74.73886899999999,17.273614],"type":"Point"}
}