{
  "type": "Feature",
  "properties": {
    "iso:country":"IN",
    "ks:ks_name":"Reja Nagar",
    "ks:ks_pop":0,
    "ks:ks_type":"VILLAGE",
    "name:eng_x_preferred":[
        "Reja Nagar"
    ],
    "wof:name":"Reja Nagar",
    "wof:placetype":"locality",
    "wof:population":0
},
  "geometry": {"coordinates":[87.979888,22.225914],"type":"Point"}
}