{
  "type": "Feature",
  "properties": {
    "iso:country":"IN",
    "ks:ks_name":"Tawarinagar",
    "ks:ks_pop":139,
    "ks:ks_type":"HABITATION",
    "name:eng_x_preferred":[
        "Tawarinagar"
    ],
    "wof:name":"Tawarinagar",
    "wof:placetype":"locality",
    "wof:population":139
},
  "geometry": {"coordinates":[71.651,27.764333],"type":"Point"}
}