{
  "type": "Feature",
  "properties": {
    "gn:admin1_code":"36",
    "gn:admin2_code":"169.0",
    "gn:asciiname":"Sudamapuri",
    "gn:country_code":"IN",
    "gn:dem":177,
    "gn:feature_class":"P",
    "gn:feature_code":"PPL",
    "gn:name":"Sud\u0101m\u0101puri",
    "gn:population":0,
    "gn:timezone":"Asia/Kolkata",
    "iso:country":"IN",
    "ks:ks_alt_nam":"Sud\u0101m\u0101puri",
    "ks:ks_name":"Sudamapuri",
    "ks:ks_pop":237,
    "ks:ks_type":"VILLAGE",
    "name:eng_x_preferred":[
        "Sudamapuri"
    ],
    "name:eng_x_variant":[
        "Sud\u0101m\u0101puri"
    ],
    "wof:name":"Sudamapuri",
    "wof:placetype":"locality",
    "wof:population":237
},
  "geometry": {"coordinates":[79.753547,25.451325],"type":"Point"}
}