{
  "type": "Feature",
  "properties": {
    "gn:admin1_code":"24.0",
    "gn:admin2_code":"110.0",
    "gn:asciiname":"Kanwarpura",
    "gn:country_code":"IN",
    "gn:dem":370,
    "gn:feature_class":"P",
    "gn:feature_code":"PPL",
    "gn:name":"Kanwarpura",
    "gn:population":0,
    "gn:timezone":"Asia/Kolkata",
    "iso:country":"IN",
    "ks:ks_name":"Kanwarpura",
    "ks:ks_pop":2025,
    "ks:ks_type":"VILLAGE",
    "ks:ks_uagg_main":0,
    "name:eng_x_preferred":[
        "Kanwarpura"
    ],
    "wof:name":"Kanwarpura",
    "wof:placetype":"neighbourhood",
    "wof:population":2025
},
  "geometry": {"coordinates":[76.141468,27.662297],"type":"Point"}
}