{
  "type": "Feature",
  "properties": {
    "iso:country":"IN",
    "ks:ks_alt_nam":"Serengd\u012bh",
    "ks:ks_name":"Serengdih",
    "ks:ks_pop":370,
    "ks:ks_type":"VILLAGE",
    "name:eng_x_preferred":[
        "Serengdih"
    ],
    "name:eng_x_variant":[
        "Serengd\u012bh"
    ],
    "wof:name":"Serengdih",
    "wof:placetype":"locality",
    "wof:population":370
},
  "geometry": {"coordinates":[85.56385,23.267266],"type":"Point"}
}