{
  "type": "Feature",
  "properties": {
    "iso:country":"IN",
    "ks:ks_name":"Pub Bhadragaon I",
    "ks:ks_pop":415,
    "ks:ks_type":"HABITATION",
    "name:eng_x_preferred":[
        "Pub Bhadragaon I"
    ],
    "wof:name":"Pub Bhadragaon I",
    "wof:placetype":"locality",
    "wof:population":415
},
  "geometry": {"coordinates":[90.465891,26.442013],"type":"Point"}
}