{
  "type": "Feature",
  "properties": {
    "iso:country":"IN",
    "ks:ks_name":"Dombekai",
    "ks:ks_pop":27,
    "ks:ks_type":"HABITATION",
    "name:eng_x_preferred":[
        "Dombekai"
    ],
    "wof:name":"Dombekai",
    "wof:placetype":"locality",
    "wof:population":27
},
  "geometry": {"coordinates":[74.824032,14.348288],"type":"Point"}
}