{
  "type": "Feature",
  "properties": {
    "gn:admin1_code":"35.0",
    "gn:admin2_code":"427.0",
    "gn:asciiname":"Bhilaiya",
    "gn:country_code":"IN",
    "gn:dem":482,
    "gn:feature_class":"P",
    "gn:feature_code":"PPL",
    "gn:name":"Bhilaiya",
    "gn:population":0,
    "gn:timezone":"Asia/Kolkata",
    "iso:country":"IN",
    "wof:name":"Bhilaiya",
    "wof:placetype":"locality"
},
  "geometry": {"coordinates":[78.91943000000001,23.41768],"type":"Point"}
}