{
  "type": "Feature",
  "properties": {
    "iso:country":"IN",
    "ks:ks_name":"Thannarampoyil",
    "ks:ks_pop":224,
    "ks:ks_type":"HABITATION",
    "name:eng_x_preferred":[
        "Thannarampoyil"
    ],
    "wof:name":"Thannarampoyil",
    "wof:placetype":"locality",
    "wof:population":224
},
  "geometry": {"coordinates":[75.747383,11.639992],"type":"Point"}
}