{
  "type": "Feature",
  "properties": {
    "gn:admin1_code":"35",
    "gn:admin2_code":"427.0",
    "gn:asciiname":"Dhana",
    "gn:country_code":"IN",
    "gn:dem":395,
    "gn:feature_class":"P",
    "gn:feature_code":"PPL",
    "gn:name":"Dh\u0101na",
    "gn:population":0,
    "gn:timezone":"Asia/Kolkata",
    "iso:country":"IN",
    "name:ben_x_preferred":[
        "\u09a7\u09be\u09a8\u09be"
    ],
    "name:bpy_x_preferred":[
        "\u09a7\u09be\u09a8\u09be"
    ],
    "name:ceb_x_preferred":[
        "Dh\u0101na"
    ],
    "name:ita_x_preferred":[
        "Dhana"
    ],
    "name:msa_x_preferred":[
        "Dhana"
    ],
    "name:new_x_preferred":[
        "\u0927\u093e\u0928\u093e"
    ],
    "name:nld_x_preferred":[
        "Dhana"
    ],
    "name:por_x_preferred":[
        "Dhana"
    ],
    "name:spa_x_preferred":[
        "Dhana"
    ],
    "name:swe_x_preferred":[
        "Dh\u0101na"
    ],
    "name:vie_x_preferred":[
        "Dhana"
    ],
    "wof:name":"Dhana",
    "wof:placetype":"locality"
},
  "geometry": {"coordinates":[78.10568000000001,24.29752],"type":"Point"}
}