{
  "type": "Feature",
  "properties": {
    "iso:country":"IN",
    "ks:ks_name":"Dongarwadi",
    "ks:ks_pop":66,
    "ks:ks_type":"HABITATION",
    "name:eng_x_preferred":[
        "Dongarwadi"
    ],
    "wof:name":"Dongarwadi",
    "wof:placetype":"locality",
    "wof:population":66
},
  "geometry": {"coordinates":[73.319456,16.907336],"type":"Point"}
}