{
  "type": "Feature",
  "properties": {
    "iso:country":"IN",
    "ks:ks_name":"Ghorbandha",
    "ks:ks_pop":467,
    "ks:ks_type":"VILLAGE",
    "name:eng_x_preferred":[
        "Ghorbandha"
    ],
    "wof:name":"Ghorbandha",
    "wof:placetype":"locality",
    "wof:population":467
},
  "geometry": {"coordinates":[82.231534,23.913414],"type":"Point"}
}