{
  "type": "Feature",
  "properties": {
    "iso:country":"IN",
    "ks:ks_name":"Daudpur",
    "ks:ks_pop":577,
    "ks:ks_type":"VILLAGE",
    "ks:ks_uagg_main":0,
    "name:eng_x_preferred":[
        "Daudpur"
    ],
    "wof:name":"Daudpur",
    "wof:placetype":"neighbourhood",
    "wof:population":577
},
  "geometry": {"coordinates":[88.159873,25.70782],"type":"Point"}
}