{
  "type": "Feature",
  "properties": {
    "gn:admin1_code":"12",
    "gn:admin2_code":"15.0",
    "gn:asciiname":"Lagapur",
    "gn:country_code":"IN",
    "gn:dem":2094,
    "gn:feature_class":"P",
    "gn:feature_code":"PPL",
    "gn:name":"Lagapur",
    "gn:population":0,
    "gn:timezone":"Asia/Kolkata",
    "iso:country":"IN",
    "wof:name":"Lagapur",
    "wof:placetype":"locality"
},
  "geometry": {"coordinates":[74.98489000000002,33.56559],"type":"Point"}
}