{
  "type": "Feature",
  "properties": {
    "iso:country":"IN",
    "ks:ks_name":"Kappegondi",
    "ks:ks_pop":70,
    "ks:ks_type":"HABITATION",
    "name:eng_x_preferred":[
        "Kappegondi"
    ],
    "wof:name":"Kappegondi",
    "wof:placetype":"locality",
    "wof:population":70
},
  "geometry": {"coordinates":[81.577894,18.61714],"type":"Point"}
}