{
  "type": "Feature",
  "properties": {
    "gn:admin1_code":"38.0",
    "gn:admin2_code":"353.0",
    "gn:asciiname":"Naraindih",
    "gn:country_code":"IN",
    "gn:dem":138,
    "gn:feature_class":"P",
    "gn:feature_code":"PPL",
    "gn:name":"N\u0101r\u0101indih",
    "gn:population":0,
    "gn:timezone":"Asia/Kolkata",
    "iso:country":"IN",
    "ks:ks_alt_nam":"N\u0101r\u0101indih",
    "ks:ks_name":"Naraindih",
    "ks:ks_pop":243,
    "ks:ks_type":"VILLAGE",
    "name:eng_x_preferred":[
        "Naraindih"
    ],
    "name:eng_x_variant":[
        "N\u0101r\u0101indih"
    ],
    "wof:name":"Naraindih",
    "wof:placetype":"locality",
    "wof:population":243
},
  "geometry": {"coordinates":[87.71690599999999,24.587093],"type":"Point"}
}