{
  "type": "Feature",
  "properties": {
    "iso:country":"IN",
    "ks:ks_alt_nam":"Mangola gair ahatmal",
    "ks:ks_name":"Mangola Gair Ahatmal",
    "ks:ks_pop":420,
    "ks:ks_type":"HABITATION",
    "name:eng_x_preferred":[
        "Mangola Gair Ahatmal"
    ],
    "wof:name":"Mangola Gair Ahatmal",
    "wof:placetype":"locality",
    "wof:population":420
},
  "geometry": {"coordinates":[77.13491999999999,29.606395],"type":"Point"}
}