{
  "type": "Feature",
  "properties": {
    "iso:country":"IN",
    "ks:ks_name":"Thavittamokai",
    "ks:ks_pop":300,
    "ks:ks_type":"HABITATION",
    "name:eng_x_preferred":[
        "Thavittamokai"
    ],
    "wof:name":"Thavittamokai",
    "wof:placetype":"locality",
    "wof:population":300
},
  "geometry": {"coordinates":[76.74573100000001,11.447577],"type":"Point"}
}