{
  "type": "Feature",
  "properties": {
    "iso:country":"IN",
    "ks:ks_name":"Rupla Thanda",
    "ks:ks_pop":30,
    "ks:ks_type":"HABITATION",
    "name:eng_x_preferred":[
        "Rupla Thanda"
    ],
    "wof:name":"Rupla Thanda",
    "wof:placetype":"locality",
    "wof:population":30
},
  "geometry": {"coordinates":[78.303102,17.809204],"type":"Point"}
}