{
  "type": "Feature",
  "properties": {
    "iso:country":"IN",
    "ks:ks_name":"Ratambewadi",
    "ks:ks_pop":79,
    "ks:ks_type":"HABITATION",
    "name:eng_x_preferred":[
        "Ratambewadi"
    ],
    "wof:name":"Ratambewadi",
    "wof:placetype":"locality",
    "wof:population":79
},
  "geometry": {"coordinates":[73.717403,16.180305],"type":"Point"}
}