{
  "type": "Feature",
  "properties": {
    "gn:admin1_code":"36",
    "gn:admin2_code":"179.0",
    "gn:asciiname":"Purwa Kuber",
    "gn:country_code":"IN",
    "gn:dem":103,
    "gn:feature_class":"P",
    "gn:feature_code":"PPL",
    "gn:name":"Purwa Kuber",
    "gn:population":0,
    "gn:timezone":"Asia/Kolkata",
    "iso:country":"IN",
    "wof:name":"Purwa Kuber",
    "wof:placetype":"locality"
},
  "geometry": {"coordinates":[82.01260000000001,26.3563],"type":"Point"}
}