{
  "type": "Feature",
  "properties": {
    "iso:country":"IN",
    "ks:ks_name":"Paradaniputtu",
    "ks:ks_pop":204,
    "ks:ks_type":"HABITATION",
    "name:eng_x_preferred":[
        "Paradaniputtu"
    ],
    "wof:name":"Paradaniputtu",
    "wof:placetype":"locality",
    "wof:population":204
},
  "geometry": {"coordinates":[82.61096999999999,18.135678],"type":"Point"}
}