{
  "type": "Feature",
  "properties": {
    "iso:country":"IN",
    "ks:ks_name":"Raimara",
    "ks:ks_pop":396,
    "ks:ks_type":"VILLAGE",
    "name:eng_x_preferred":[
        "Raimara"
    ],
    "wof:name":"Raimara",
    "wof:placetype":"locality",
    "wof:population":396
},
  "geometry": {"coordinates":[86.08264699999999,22.866885],"type":"Point"}
}