{
  "type": "Feature",
  "properties": {
    "iso:country":"IN",
    "ks:ks_name":"Palasadi",
    "ks:ks_pop":797,
    "ks:ks_type":"VILLAGE",
    "name:eng_x_preferred":[
        "Palasadi"
    ],
    "wof:name":"Palasadi",
    "wof:placetype":"locality",
    "wof:population":797
},
  "geometry": {"coordinates":[74.747175,22.644824],"type":"Point"}
}