{
  "type": "Feature",
  "properties": {
    "iso:country":"IN",
    "ks:ks_alt_nam":"indo khera",
    "ks:ks_name":"Indo Khera",
    "ks:ks_pop":656,
    "ks:ks_type":"HABITATION",
    "name:eng_x_preferred":[
        "Indo Khera"
    ],
    "wof:name":"Indo Khera",
    "wof:placetype":"locality",
    "wof:population":656
},
  "geometry": {"coordinates":[80.920232,26.691862],"type":"Point"}
}