{
  "type": "Feature",
  "properties": {
    "gn:admin1_code":"19.0",
    "gn:admin2_code":"569.0",
    "gn:asciiname":"Shirangur",
    "gn:country_code":"IN",
    "gn:dem":94,
    "gn:feature_class":"P",
    "gn:feature_code":"PPL",
    "gn:name":"Shirang\u016br",
    "gn:population":0,
    "gn:timezone":"Asia/Kolkata",
    "iso:country":"IN",
    "ks:ks_name":"Shirangoor",
    "ks:ks_pop":216,
    "ks:ks_type":"HABITATION",
    "name:eng_x_preferred":[
        "Shirangoor"
    ],
    "name:eng_x_variant":[
        "Shirangur"
    ],
    "wof:name":"Shirangoor",
    "wof:placetype":"locality",
    "wof:population":216
},
  "geometry": {"coordinates":[75.00839999999999,13.523475],"type":"Point"}
}