{
  "type": "Feature",
  "properties": {
    "iso:country":"IN",
    "ks:ks_name":"Gundagar",
    "ks:ks_pop":39,
    "ks:ks_type":"HABITATION",
    "name:eng_x_preferred":[
        "Gundagar"
    ],
    "wof:name":"Gundagar",
    "wof:placetype":"locality",
    "wof:population":39
},
  "geometry": {"coordinates":[74.43803200000001,14.491571],"type":"Point"}
}