{
  "type": "Feature",
  "properties": {
    "iso:country":"IN",
    "ks:ks_name":"Post Office Jn",
    "ks:ks_pop":970,
    "ks:ks_type":"HABITATION",
    "name:eng_x_preferred":[
        "Post Office Jn"
    ],
    "wof:name":"Post Office Jn",
    "wof:placetype":"locality",
    "wof:population":970
},
  "geometry": {"coordinates":[76.67828,8.986827],"type":"Point"}
}