{
  "type": "Feature",
  "properties": {
    "iso:country":"IN",
    "ks:ks_alt_nam":"Aagre mohitewadi",
    "ks:ks_name":"Aagre Mohitewadi",
    "ks:ks_pop":120,
    "ks:ks_type":"HABITATION",
    "name:eng_x_preferred":[
        "Aagre Mohitewadi"
    ],
    "wof:name":"Aagre Mohitewadi",
    "wof:placetype":"locality",
    "wof:population":120
},
  "geometry": {"coordinates":[73.44888899999999,17.088056],"type":"Point"}
}