{
  "type": "Feature",
  "properties": {
    "iso:country":"IN",
    "ks:ks_name":"Ponrashol",
    "ks:ks_pop":149,
    "ks:ks_type":"VILLAGE",
    "name:eng_x_preferred":[
        "Ponrashol"
    ],
    "wof:name":"Ponrashol",
    "wof:placetype":"locality",
    "wof:population":149
},
  "geometry": {"coordinates":[87.441744,22.815494],"type":"Point"}
}