{
  "type": "Feature",
  "properties": {
    "iso:country":"IN",
    "ks:ks_name":"Doddalaxmipura",
    "ks:ks_type":"VILLAGE",
    "name:eng_x_preferred":[
        "Doddalaxmipura"
    ],
    "wof:name":"Doddalaxmipura",
    "wof:placetype":"locality"
},
  "geometry": {"coordinates":[76.942234,12.30951],"type":"Point"}
}