{
  "type": "Feature",
  "properties": {
    "iso:country":"IN",
    "ks:ks_alt_nam":"Barkhata Pt II",
    "ks:ks_name":"Barkhata Pt Ii",
    "ks:ks_pop":222,
    "ks:ks_type":"HABITATION",
    "name:eng_x_preferred":[
        "Barkhata Pt Ii"
    ],
    "wof:name":"Barkhata Pt Ii",
    "wof:placetype":"locality",
    "wof:population":222
},
  "geometry": {"coordinates":[90.51289,26.326143],"type":"Point"}
}