{
  "type": "Feature",
  "properties": {
    "gn:admin1_code":"24",
    "gn:admin2_code":"127.0",
    "gn:asciiname":"Bhulaheri",
    "gn:country_code":"IN",
    "gn:dem":274,
    "gn:feature_class":"P",
    "gn:feature_code":"PPL",
    "gn:name":"Bh\u016bl\u0101heri",
    "gn:population":0,
    "gn:timezone":"Asia/Kolkata",
    "iso:country":"IN",
    "wof:name":"Bhulaheri",
    "wof:placetype":"locality"
},
  "geometry": {"coordinates":[76.40422,24.91382],"type":"Point"}
}