{
  "type": "Feature",
  "properties": {
    "iso:country":"IN",
    "ks:ks_name":"Da-Gaon",
    "ks:ks_pop":804,
    "ks:ks_type":"VILLAGE",
    "ks:ks_uagg_main":0,
    "name:eng_x_preferred":[
        "Da-Gaon"
    ],
    "wof:name":"Da-Gaon",
    "wof:placetype":"neighbourhood",
    "wof:population":804
},
  "geometry": {"coordinates":[93.80582,26.908798],"type":"Point"}
}