{
  "type": "Feature",
  "properties": {
    "iso:country":"IN",
    "ks:ks_name":"Patkura",
    "ks:ks_pop":1510,
    "ks:ks_type":"VILLAGE",
    "name:eng_x_preferred":[
        "Patkura"
    ],
    "wof:name":"Patkura",
    "wof:placetype":"locality",
    "wof:population":1510
},
  "geometry": {"coordinates":[83.123462,22.758638],"type":"Point"}
}