{
  "type": "Feature",
  "properties": {
    "gn:admin1_code":"16.0",
    "gn:admin2_code":"520.0",
    "gn:asciiname":"Vadhav",
    "gn:country_code":"IN",
    "gn:dem":6,
    "gn:feature_class":"P",
    "gn:feature_code":"PPL",
    "gn:name":"Vadhav",
    "gn:population":0,
    "gn:timezone":"Asia/Kolkata",
    "iso:country":"IN",
    "wof:name":"Vadhav",
    "wof:placetype":"locality"
},
  "geometry": {"coordinates":[73.03205,18.76181],"type":"Point"}
}