{
  "type": "Feature",
  "properties": {
    "gn:admin1_code":"36.0",
    "gn:admin2_code":"183.0",
    "gn:asciiname":"Madhai Jot",
    "gn:country_code":"IN",
    "gn:dem":108,
    "gn:feature_class":"P",
    "gn:feature_code":"PPL",
    "gn:name":"Madhai Jot",
    "gn:population":0,
    "gn:timezone":"Asia/Kolkata",
    "iso:country":"IN",
    "ks:ks_name":"Madhai Jot",
    "ks:ks_type":"VILLAGE",
    "ks:ks_uagg_main":0,
    "name:eng_x_preferred":[
        "Madhai Jot"
    ],
    "name:und_x_variant":[
        "Bishunpur R\u0101ja"
    ],
    "wof:name":"Madhai Jot",
    "wof:placetype":"neighbourhood"
},
  "geometry": {"coordinates":[82.109363,27.296279],"type":"Point"}
}