{
  "type": "Feature",
  "properties": {
    "iso:country":"IN",
    "ks:ks_name":"Kantagerya",
    "ks:ks_pop":64,
    "ks:ks_type":"VILLAGE",
    "ks:ks_uagg_main":0,
    "name:eng_x_preferred":[
        "Kantagerya"
    ],
    "wof:name":"Kantagerya",
    "wof:placetype":"locality",
    "wof:population":64
},
  "geometry": {"coordinates":[87.281126,22.376609],"type":"Point"}
}