{
  "type": "Feature",
  "properties": {
    "iso:country":"IN",
    "ks:ks_name":"Mahua Kheda Singhai",
    "ks:ks_pop":0,
    "ks:ks_type":"VILLAGE",
    "name:eng_x_preferred":[
        "Mahua Kheda Singhai"
    ],
    "wof:name":"Mahua Kheda Singhai",
    "wof:placetype":"locality",
    "wof:population":0
},
  "geometry": {"coordinates":[78.455359,23.486387],"type":"Point"}
}