{
  "type": "Feature",
  "properties": {
    "gn:admin1_code":"19.0",
    "gn:admin2_code":"573.0",
    "gn:asciiname":"Bandur",
    "gn:country_code":"IN",
    "gn:dem":657,
    "gn:feature_class":"P",
    "gn:feature_code":"PPL",
    "gn:name":"Band\u016br",
    "gn:population":0,
    "gn:timezone":"Asia/Kolkata",
    "iso:country":"IN",
    "name:deu_x_preferred":[
        "Bandur"
    ],
    "name:pol_x_preferred":[
        "Bandur"
    ],
    "wof:name":"Bandur",
    "wof:placetype":"locality"
},
  "geometry": {"coordinates":[77.00275000000001,12.39648],"type":"Point"}
}