{
  "type": "Feature",
  "properties": {
    "iso:country":"IN",
    "ks:ks_name":"Narel Khera",
    "ks:ks_pop":1989,
    "ks:ks_type":"VILLAGE",
    "name:eng_x_preferred":[
        "Narel Khera"
    ],
    "wof:name":"Narel Khera",
    "wof:placetype":"locality",
    "wof:population":1989
},
  "geometry": {"coordinates":[75.253885,29.533829],"type":"Point"}
}