{
  "type": "Feature",
  "properties": {
    "iso:country":"IN",
    "ks:ks_name":"Sandadvan",
    "ks:ks_pop":339,
    "ks:ks_type":"HABITATION",
    "name:eng_x_preferred":[
        "Sandadvan"
    ],
    "wof:name":"Sandadvan",
    "wof:placetype":"locality",
    "wof:population":339
},
  "geometry": {"coordinates":[73.395,21.175333],"type":"Point"}
}