{
  "type": "Feature",
  "properties": {
    "iso:country":"IN",
    "ks:ks_name":"Satamwadi",
    "ks:ks_pop":172,
    "ks:ks_type":"HABITATION",
    "name:eng_x_preferred":[
        "Satamwadi"
    ],
    "wof:name":"Satamwadi",
    "wof:placetype":"locality",
    "wof:population":172
},
  "geometry": {"coordinates":[73.513182,16.224665],"type":"Point"}
}