{
  "type": "Feature",
  "properties": {
    "gn:admin1_code":"36",
    "gn:admin2_code":"181.0",
    "gn:asciiname":"Madara",
    "gn:country_code":"IN",
    "gn:dem":115,
    "gn:feature_class":"P",
    "gn:feature_code":"PPL",
    "gn:name":"Mad\u0101ra",
    "gn:population":0,
    "gn:timezone":"Asia/Kolkata",
    "iso:country":"IN",
    "name:bul_x_preferred":[
        "\u041c\u0430\u0434\u0430\u0440\u0430"
    ],
    "name:ceb_x_preferred":[
        "Madara"
    ],
    "name:deu_x_preferred":[
        "Madara"
    ],
    "name:fin_x_preferred":[
        "Madara"
    ],
    "name:fra_x_preferred":[
        "Madara"
    ],
    "name:ind_x_preferred":[
        "Madara"
    ],
    "name:ita_x_preferred":[
        "Madara"
    ],
    "name:lav_x_preferred":[
        "Madara"
    ],
    "name:por_x_preferred":[
        "Madara"
    ],
    "name:rus_x_preferred":[
        "\u041c\u0430\u0434\u0430\u0440\u0430"
    ],
    "name:slk_x_preferred":[
        "Madara"
    ],
    "name:spa_x_preferred":[
        "Madara"
    ],
    "name:swe_x_preferred":[
        "Madara"
    ],
    "name:tgl_x_preferred":[
        "Madara"
    ],
    "name:ukr_x_preferred":[
        "\u041c\u0430\u0434\u0430\u0440\u0430"
    ],
    "wof:name":"Madara",
    "wof:placetype":"locality"
},
  "geometry": {"coordinates":[81.89015999999999,27.60787],"type":"Point"}
}