{
  "type": "Feature",
  "properties": {
    "iso:country":"IN",
    "ks:ks_name":"Khertha",
    "ks:ks_pop":0,
    "ks:ks_type":"VILLAGE",
    "name:eng_x_preferred":[
        "Khertha"
    ],
    "wof:name":"Khertha",
    "wof:placetype":"locality",
    "wof:population":0
},
  "geometry": {"coordinates":[81.516049,20.575346],"type":"Point"}
}