{
  "type": "Feature",
  "properties": {
    "gn:admin1_code":"28.0",
    "gn:admin2_code":"332.0",
    "gn:asciiname":"Ilam",
    "gn:country_code":"IN",
    "gn:dem":32,
    "gn:feature_class":"P",
    "gn:feature_code":"PPL",
    "gn:name":"Il\u0101m",
    "gn:population":0,
    "gn:timezone":"Asia/Kolkata",
    "iso:country":"IN",
    "name:bul_x_preferred":[
        "\u0418\u043b\u0430\u043c"
    ],
    "name:ceb_x_preferred":[
        "Ilam"
    ],
    "name:deu_x_preferred":[
        "Ilam"
    ],
    "name:fra_x_preferred":[
        "Ilam"
    ],
    "name:hye_x_preferred":[
        "\u053b\u056c\u0561\u0574"
    ],
    "name:nep_x_preferred":[
        "\u0907\u0932\u093e\u092e"
    ],
    "name:nld_x_preferred":[
        "Ilam"
    ],
    "name:pol_x_preferred":[
        "Ilam"
    ],
    "name:rus_x_preferred":[
        "\u0418\u043b\u0430\u043c"
    ],
    "name:spa_x_preferred":[
        "Ilam"
    ],
    "name:swe_x_preferred":[
        "Ilam"
    ],
    "name:vie_x_preferred":[
        "Ilam"
    ],
    "wof:name":"Ilam",
    "wof:placetype":"locality"
},
  "geometry": {"coordinates":[87.95294,25.39249],"type":"Point"}
}