{
  "type": "Feature",
  "properties": {
    "gn:admin1_code":"25.0",
    "gn:admin2_code":"604.0",
    "gn:asciiname":"Kottaikadu",
    "gn:country_code":"IN",
    "gn:dem":15,
    "gn:feature_class":"P",
    "gn:feature_code":"PPL",
    "gn:name":"Kottaik\u0101du",
    "gn:population":0,
    "gn:timezone":"Asia/Kolkata",
    "iso:country":"IN",
    "ks:ks_alt_nam":"Kottaik\u0101du",
    "ks:ks_name":"Kottaikadu",
    "ks:ks_pop":2686,
    "ks:ks_type":"VILLAGE",
    "ks:ks_uagg_main":0,
    "name:eng_x_preferred":[
        "Kottaikadu"
    ],
    "name:eng_x_variant":[
        "Kottaik\u0101du"
    ],
    "wof:name":"Kottaikadu",
    "wof:placetype":"neighbourhood",
    "wof:population":2686
},
  "geometry": {"coordinates":[79.982258,12.255557],"type":"Point"}
}