{
  "type": "Feature",
  "properties": {
    "iso:country":"IN",
    "ks:ks_alt_nam":"Bhag\u0101munda",
    "ks:ks_name":"Bhagamunda",
    "ks:ks_type":"VILLAGE",
    "name:eng_x_preferred":[
        "Bhagamunda"
    ],
    "name:eng_x_variant":[
        "Bhag\u0101munda"
    ],
    "wof:name":"Bhagamunda",
    "wof:placetype":"locality"
},
  "geometry": {"coordinates":[84.741529,20.84191],"type":"Point"}
}