{
  "type": "Feature",
  "properties": {
    "iso:country":"IN",
    "ks:ks_name":"Karjeepara Singimari Nadi",
    "ks:ks_pop":1248,
    "ks:ks_type":"HABITATION",
    "name:eng_x_preferred":[
        "Karjeepara Singimari Nadi"
    ],
    "wof:name":"Karjeepara Singimari Nadi",
    "wof:placetype":"locality",
    "wof:population":1248
},
  "geometry": {"coordinates":[89.53359500000001,26.430627],"type":"Point"}
}