{
  "type": "Feature",
  "properties": {
    "iso:country":"IN",
    "ks:ks_name":"Ghoriyawara",
    "ks:ks_pop":618,
    "ks:ks_type":"HABITATION",
    "name:eng_x_preferred":[
        "Ghoriyawara"
    ],
    "wof:name":"Ghoriyawara",
    "wof:placetype":"locality",
    "wof:population":618
},
  "geometry": {"coordinates":[73.74024,24.04921],"type":"Point"}
}