{
  "type": "Feature",
  "properties": {
    "iso:country":"IN",
    "ks:ks_name":"Samantpura",
    "ks:ks_pop":674,
    "ks:ks_type":"VILLAGE",
    "name:eng_x_preferred":[
        "Samantpura"
    ],
    "wof:name":"Samantpura",
    "wof:placetype":"locality",
    "wof:population":674
},
  "geometry": {"coordinates":[76.969453,27.170536],"type":"Point"}
}