{
  "type": "Feature",
  "properties": {
    "gn:admin1_code":"36",
    "gn:admin2_code":"155.0",
    "gn:asciiname":"Donga",
    "gn:country_code":"IN",
    "gn:dem":134,
    "gn:feature_class":"P",
    "gn:feature_code":"PPL",
    "gn:name":"Dong\u0101",
    "gn:population":0,
    "gn:timezone":"Asia/Kolkata",
    "iso:country":"IN",
    "name:ceb_x_preferred":[
        "Donga"
    ],
    "name:deu_x_preferred":[
        "Donga"
    ],
    "name:fas_x_preferred":[
        "\u062f\u0648\u0646\u06af\u0627"
    ],
    "name:fra_x_preferred":[
        "Donga"
    ],
    "name:heb_x_preferred":[
        "\u05d3\u05d5\u05e0\u05d2\u05d4"
    ],
    "name:ita_x_preferred":[
        "Donga"
    ],
    "name:jpn_x_preferred":[
        "\u30c9\u30f3\u30ac"
    ],
    "name:slk_x_preferred":[
        "Donga"
    ],
    "name:swe_x_preferred":[
        "Donga"
    ],
    "wof:name":"Donga",
    "wof:placetype":"neighbourhood"
},
  "geometry": {"coordinates":[80.50024000000001,27.02489],"type":"Point"}
}