{
  "type": "Feature",
  "properties": {
    "gn:admin1_code":"36",
    "gn:admin2_code":"144.0",
    "gn:asciiname":"Tilokpur",
    "gn:country_code":"IN",
    "gn:dem":180,
    "gn:feature_class":"P",
    "gn:feature_code":"PPL",
    "gn:name":"Tilokpur",
    "gn:population":0,
    "gn:timezone":"Asia/Kolkata",
    "iso:country":"IN",
    "name:hin_x_preferred":[
        "\u0924\u093f\u0932\u094b\u0915\u092a\u0941\u0930"
    ],
    "wof:name":"Tilokpur",
    "wof:placetype":"locality"
},
  "geometry": {"coordinates":[78.18151,27.55943],"type":"Point"}
}