{
  "type": "Feature",
  "properties": {
    "gn:admin1_code":"36",
    "gn:admin2_code":"144.0",
    "gn:asciiname":"Tilokpur",
    "gn:country_code":"IN",
    "gn:dem":180,
    "gn:feature_class":"P",
    "gn:feature_code":"PPL",
    "gn:name":"Tilokpur",
    "gn:population":0,
    "gn:timezone":"Asia/Kolkata",
    "iso:country":"IN",
    "ks:ks_name":"Trilokpur",
    "ks:ks_pop":292,
    "ks:ks_type":"HABITATION",
    "name:eng_x_preferred":[
        "Trilokpur"
    ],
    "name:eng_x_variant":[
        "Tilokpur"
    ],
    "name:hin_x_preferred":[
        "\u0924\u093f\u0932\u094b\u0915\u092a\u0941\u0930"
    ],
    "wof:name":"Trilokpur",
    "wof:placetype":"locality",
    "wof:population":292
},
  "geometry": {"coordinates":[78.180809,27.559477],"type":"Point"}
}