{
  "type": "Feature",
  "properties": {
    "gn:admin1_code":"36",
    "gn:admin2_code":"196.0",
    "gn:asciiname":"Piprahat",
    "gn:country_code":"IN",
    "gn:dem":102,
    "gn:feature_class":"P",
    "gn:feature_code":"PPL",
    "gn:name":"Pipr\u0101hat",
    "gn:population":0,
    "gn:timezone":"Asia/Kolkata",
    "iso:country":"IN",
    "ks:ks_alt_nam":"Pipr\u0101hat",
    "ks:ks_name":"Piprahat",
    "ks:ks_type":"VILLAGE",
    "ks:ks_uagg_main":0,
    "name:eng_x_preferred":[
        "Piprahat"
    ],
    "name:eng_x_variant":[
        "Pipr\u0101hat"
    ],
    "wof:name":"Piprahat",
    "wof:placetype":"neighbourhood"
},
  "geometry": {"coordinates":[83.198052,25.025413],"type":"Point"}
}