{
  "type": "Feature",
  "properties": {
    "iso:country":"IN",
    "ks:ks_name":"Dumariya 2",
    "ks:ks_pop":384,
    "ks:ks_type":"HABITATION",
    "name:eng_x_preferred":[
        "Dumariya 2"
    ],
    "wof:name":"Dumariya 2",
    "wof:placetype":"locality",
    "wof:population":384
},
  "geometry": {"coordinates":[83.289402,24.637363],"type":"Point"}
}