{
  "type": "Feature",
  "properties": {
    "gn:admin1_code":"36.0",
    "gn:admin2_code":"140.0",
    "gn:asciiname":"Rasulpur Bahlolpur",
    "gn:country_code":"IN",
    "gn:dem":216,
    "gn:feature_class":"P",
    "gn:feature_code":"PPL",
    "gn:name":"Rasulpur Bahlolpur",
    "gn:population":0,
    "gn:timezone":"Asia/Kolkata",
    "iso:country":"IN",
    "wof:name":"Rasulpur Bahlolpur",
    "wof:placetype":"locality"
},
  "geometry": {"coordinates":[77.91783000000002,28.72246],"type":"Point"}
}