{
  "type": "Feature",
  "properties": {
    "iso:country":"IN",
    "ks:ks_name":"Chamaran Purwa",
    "ks:ks_pop":301,
    "ks:ks_type":"HABITATION",
    "ks:ks_uagg_main":0,
    "name:eng_x_preferred":[
        "Chamaran Purwa"
    ],
    "wof:name":"Chamaran Purwa",
    "wof:placetype":"neighbourhood",
    "wof:population":301
},
  "geometry": {"coordinates":[81.44064,27.750877],"type":"Point"}
}