{
  "type": "Feature",
  "properties": {
    "iso:country":"IN",
    "ks:ks_name":"Sudhapur",
    "ks:ks_pop":163,
    "ks:ks_type":"VILLAGE",
    "name:eng_x_preferred":[
        "Sudhapur"
    ],
    "wof:name":"Sudhapur",
    "wof:placetype":"locality",
    "wof:population":163
},
  "geometry": {"coordinates":[86.094059,22.886573],"type":"Point"}
}