{
  "type": "Feature",
  "properties": {
    "gn:admin1_code":"09",
    "gn:admin2_code":"482.0",
    "gn:asciiname":"Nahapa",
    "gn:country_code":"IN",
    "gn:dem":39,
    "gn:feature_class":"P",
    "gn:feature_code":"PPL",
    "gn:name":"N\u0101h\u0101pa",
    "gn:population":0,
    "gn:timezone":"Asia/Kolkata",
    "iso:country":"IN",
    "name:und_x_variant":[
        "V\u00e1nta",
        "N\u0101h\u0101pa"
    ],
    "wof:name":"Nahapa",
    "wof:placetype":"locality"
},
  "geometry": {"coordinates":[72.91535999999998,22.4768],"type":"Point"}
}