{
  "type": "Feature",
  "properties": {
    "gn:admin1_code":"24.0",
    "gn:admin2_code":"110.0",
    "gn:asciiname":"Sawata ki Dhani",
    "gn:country_code":"IN",
    "gn:dem":505,
    "gn:feature_class":"P",
    "gn:feature_code":"PPL",
    "gn:name":"S\u0101wata ki Dh\u0101ni",
    "gn:population":0,
    "gn:timezone":"Asia/Kolkata",
    "iso:country":"IN",
    "wof:name":"Sawata ki Dhani",
    "wof:placetype":"locality"
},
  "geometry": {"coordinates":[75.84244,27.24944],"type":"Point"}
}