{
  "type": "Feature",
  "properties": {
    "iso:country":"IN",
    "ks:ks_name":"43 LNP",
    "ks:ks_pop":65,
    "ks:ks_type":"VILLAGE",
    "name:eng_x_preferred":[
        "43 LNP"
    ],
    "wof:name":"43 LNP",
    "wof:placetype":"locality",
    "wof:population":65
},
  "geometry": {"coordinates":[73.766424,29.647815],"type":"Point"}
}