{
  "type": "Feature",
  "properties": {
    "iso:country":"IN",
    "ks:ks_name":"Talkhiro",
    "ks:ks_pop":0,
    "ks:ks_type":"VILLAGE",
    "name:eng_x_preferred":[
        "Talkhiro"
    ],
    "wof:name":"Talkhiro",
    "wof:placetype":"locality",
    "wof:population":0
},
  "geometry": {"coordinates":[84.475928,26.078442],"type":"Point"}
}