{
  "type": "Feature",
  "properties": {
    "iso:country":"IN",
    "ks:ks_name":"Alapakkam Village",
    "ks:ks_pop":624,
    "ks:ks_type":"HABITATION",
    "ks:ks_uagg_main":0,
    "name:eng_x_preferred":[
        "Alapakkam Village"
    ],
    "wof:name":"Alapakkam Village",
    "wof:placetype":"neighbourhood",
    "wof:population":624
},
  "geometry": {"coordinates":[80.111103,12.89723],"type":"Point"}
}