{
  "type": "Feature",
  "properties": {
    "iso:country":"IN",
    "ks:ks_name":"Raghab Chak",
    "ks:ks_pop":148,
    "ks:ks_type":"VILLAGE",
    "name:eng_x_preferred":[
        "Raghab Chak"
    ],
    "wof:name":"Raghab Chak",
    "wof:placetype":"locality",
    "wof:population":148
},
  "geometry": {"coordinates":[87.468645,22.424581],"type":"Point"}
}