{
  "type": "Feature",
  "properties": {
    "iso:country":"IN",
    "ks:ks_name":"Nanu Purva",
    "ks:ks_pop":191,
    "ks:ks_type":"HABITATION",
    "name:eng_x_preferred":[
        "Nanu Purva"
    ],
    "wof:name":"Nanu Purva",
    "wof:placetype":"locality",
    "wof:population":191
},
  "geometry": {"coordinates":[80.150181,26.879208],"type":"Point"}
}