{
  "type": "Feature",
  "properties": {
    "gn:admin1_code":"21.0",
    "gn:admin2_code":"398.0",
    "gn:asciiname":"Talbilamsili",
    "gn:country_code":"IN",
    "gn:dem":834,
    "gn:feature_class":"P",
    "gn:feature_code":"PPL",
    "gn:name":"Talbil\u0101msili",
    "gn:population":0,
    "gn:timezone":"Asia/Kolkata",
    "iso:country":"IN",
    "wof:name":"Talbilamsili",
    "wof:placetype":"locality"
},
  "geometry": {"coordinates":[83.00785999999999,19.0033],"type":"Point"}
}