{
  "type": "Feature",
  "properties": {
    "gn:admin1_code":"19.0",
    "gn:admin2_code":"576.0",
    "gn:asciiname":"Hoddur",
    "gn:country_code":"IN",
    "gn:dem":834,
    "gn:feature_class":"P",
    "gn:feature_code":"PPLL",
    "gn:name":"Hoddur",
    "gn:population":0,
    "gn:timezone":"Asia/Kolkata",
    "iso:country":"IN",
    "wof:name":"Hoddur",
    "wof:placetype":"locality"
},
  "geometry": {"coordinates":[75.93276999999998,12.13196],"type":"Point"}
}