{
  "type": "Feature",
  "properties": {
    "iso:country":"IN",
    "ks:ks_name":"Bhalugadia",
    "ks:ks_pop":797,
    "ks:ks_type":"VILLAGE",
    "name:eng_x_preferred":[
        "Bhalugadia"
    ],
    "wof:name":"Bhalugadia",
    "wof:placetype":"locality",
    "wof:population":797
},
  "geometry": {"coordinates":[85.01106299999999,20.957907],"type":"Point"}
}