{
  "type": "Feature",
  "properties": {
    "gn:admin1_code":"11",
    "gn:admin2_code":"33.0",
    "gn:asciiname":"Pharoti",
    "gn:country_code":"IN",
    "gn:dem":1446,
    "gn:feature_class":"P",
    "gn:feature_code":"PPL",
    "gn:name":"Pharoti",
    "gn:population":0,
    "gn:timezone":"Asia/Kolkata",
    "iso:country":"IN",
    "wof:name":"Pharoti",
    "wof:placetype":"locality"
},
  "geometry": {"coordinates":[77.05748,31.15524000000001],"type":"Point"}
}