{
  "type": "Feature",
  "properties": {
    "gn:admin1_code":"16",
    "gn:admin2_code":"499.0",
    "gn:asciiname":"Chandsani",
    "gn:country_code":"IN",
    "gn:dem":183,
    "gn:feature_class":"P",
    "gn:feature_code":"PPL",
    "gn:name":"Chandsani",
    "gn:population":0,
    "gn:timezone":"Asia/Kolkata",
    "iso:country":"IN",
    "ks:ks_name":"Chandsani",
    "ks:ks_pop":1007,
    "ks:ks_type":"VILLAGE",
    "ks:ks_uagg_main":0,
    "name:eng_x_preferred":[
        "Chandsani"
    ],
    "wof:name":"Chandsani",
    "wof:placetype":"neighbourhood",
    "wof:population":1007
},
  "geometry": {"coordinates":[75.47586200000001,21.189482],"type":"Point"}
}