{
  "type": "Feature",
  "properties": {
    "iso:country":"IN",
    "name:ast_x_preferred":[
        "Kumbalam"
    ],
    "name:bul_x_preferred":[
        "\u041a\u0443\u043c\u0431\u0430\u043b\u0430\u043c"
    ],
    "name:ceb_x_preferred":[
        "Kumbalam"
    ],
    "name:deu_x_preferred":[
        "Kumbalam"
    ],
    "name:eng_x_preferred":[
        "Kumbalam"
    ],
    "name:mal_x_preferred":[
        "\u0d15\u0d41\u0d2e\u0d4d\u0d2a\u0d33\u0d02"
    ],
    "name:nld_x_preferred":[
        "Kumbalam"
    ],
    "name:spa_x_preferred":[
        "Manganam"
    ],
    "name:spa_x_variant":[
        "Kumbalam"
    ],
    "name:swe_x_preferred":[
        "Kumbalam"
    ],
    "qs:name":"Kumbalam",
    "qs:name_adm0":"India",
    "qs:name_adm1":"Kerala",
    "qs:photos":18,
    "qs:photos_1k":4,
    "qs:photos_9k":1,
    "qs:photos_9r":1,
    "qs:photos_all":18,
    "qs:photos_sr":1,
    "qs:placetype":"Town",
    "qs:pop_sr":"0",
    "wd:wordcount":17,
    "wof:name":"Kumbalam",
    "wof:placetype":"neighbourhood"
},
  "geometry": {"coordinates":[76.315713,9.886904],"type":"Point"}
}