{
  "type": "Feature",
  "properties": {
    "iso:country":"IN",
    "ks:ks_name":"Dudhanipod",
    "ks:ks_pop":84,
    "ks:ks_type":"HABITATION",
    "name:eng_x_preferred":[
        "Dudhanipod"
    ],
    "wof:name":"Dudhanipod",
    "wof:placetype":"locality",
    "wof:population":84
},
  "geometry": {"coordinates":[78.47416699999999,19.983611],"type":"Point"}
}