{
  "type": "Feature",
  "properties": {
    "iso:country":"IN",
    "ks:ks_name":"Gujihakanda",
    "ks:ks_pop":91,
    "ks:ks_type":"VILLAGE",
    "ks:ks_uagg_main":0,
    "name:eng_x_preferred":[
        "Gujihakanda"
    ],
    "wof:name":"Gujihakanda",
    "wof:placetype":"neighbourhood",
    "wof:population":91
},
  "geometry": {"coordinates":[86.924316,22.333029],"type":"Point"}
}