{
  "type": "Feature",
  "properties": {
    "iso:country":"IN",
    "ks:ks_name":"Badra",
    "ks:ks_pop":104,
    "ks:ks_type":"VILLAGE",
    "name:eng_x_preferred":[
        "Badra"
    ],
    "wof:name":"Badra",
    "wof:placetype":"locality",
    "wof:population":104
},
  "geometry": {"coordinates":[81.440563,23.591045],"type":"Point"}
}