{
  "type": "Feature",
  "properties": {
    "gn:admin1_code":"35.0",
    "gn:admin2_code":"447.0",
    "gn:asciiname":"Keriya",
    "gn:country_code":"IN",
    "gn:dem":403,
    "gn:feature_class":"P",
    "gn:feature_code":"PPL",
    "gn:name":"Keriya",
    "gn:population":0,
    "gn:timezone":"Asia/Kolkata",
    "iso:country":"IN",
    "name:ceb_x_preferred":[
        "Keriya"
    ],
    "name:ces_x_preferred":[
        "Kerija"
    ],
    "name:lit_x_preferred":[
        "Kerija"
    ],
    "name:pol_x_preferred":[
        "Keriya"
    ],
    "name:rus_x_preferred":[
        "\u041a\u0435\u0440\u0438\u044f"
    ],
    "name:swe_x_preferred":[
        "Keriya"
    ],
    "wof:name":"Keriya",
    "wof:placetype":"locality"
},
  "geometry": {"coordinates":[78.06739,22.15659],"type":"Point"}
}