{
  "type": "Feature",
  "properties": {
    "iso:country":"IN",
    "ks:ks_name":"Karmatanr",
    "ks:ks_pop":156,
    "ks:ks_type":"HABITATION",
    "name:eng_x_preferred":[
        "Karmatanr"
    ],
    "wof:name":"Karmatanr",
    "wof:placetype":"locality",
    "wof:population":156
},
  "geometry": {"coordinates":[86.144132,24.825662],"type":"Point"}
}