{
  "type": "Feature",
  "properties": {
    "iso:country":"IN",
    "ks:ks_name":"Uppertola",
    "ks:ks_pop":251,
    "ks:ks_type":"HABITATION",
    "name:eng_x_preferred":[
        "Uppertola"
    ],
    "wof:name":"Uppertola",
    "wof:placetype":"locality",
    "wof:population":251
},
  "geometry": {"coordinates":[85.203923,23.58833],"type":"Point"}
}