{
  "type": "Feature",
  "properties": {
    "iso:country":"IN",
    "ks:ks_name":"Katiguda",
    "ks:ks_pop":124,
    "ks:ks_type":"HABITATION",
    "name:eng_x_preferred":[
        "Katiguda"
    ],
    "wof:name":"Katiguda",
    "wof:placetype":"locality",
    "wof:population":124
},
  "geometry": {"coordinates":[82.214624,18.614427],"type":"Point"}
}