{
  "type": "Feature",
  "properties": {
    "iso:country":"IN",
    "ks:ks_name":"Korli",
    "ks:ks_pop":177,
    "ks:ks_type":"VILLAGE",
    "name:eng_x_preferred":[
        "Korli"
    ],
    "wof:name":"Korli",
    "wof:placetype":"locality",
    "wof:population":177
},
  "geometry": {"coordinates":[81.605028,19.222912],"type":"Point"}
}