{
  "type": "Feature",
  "properties": {
    "iso:country":"IN",
    "ks:ks_alt_nam":"Mohamodpur T.E.",
    "ks:ks_name":"Mohamodpur T.e.",
    "ks:ks_pop":441,
    "ks:ks_type":"HABITATION",
    "name:eng_x_preferred":[
        "Mohamodpur T.e."
    ],
    "wof:name":"Mohamodpur T.e.",
    "wof:placetype":"locality",
    "wof:population":441
},
  "geometry": {"coordinates":[92.49907399999999,24.741997],"type":"Point"}
}