{
  "type": "Feature",
  "properties": {
    "iso:country":"IN",
    "ks:ks_name":"Makhuna",
    "ks:ks_pop":310,
    "ks:ks_type":"VILLAGE",
    "name:eng_x_preferred":[
        "Makhuna"
    ],
    "wof:name":"Makhuna",
    "wof:placetype":"locality",
    "wof:population":310
},
  "geometry": {"coordinates":[86.41792599999999,22.122617],"type":"Point"}
}