{
  "type": "Feature",
  "properties": {
    "iso:country":"IN",
    "ks:ks_name":"Banahata Bazar",
    "ks:ks_pop":78,
    "ks:ks_type":"HABITATION",
    "ks:ks_uagg_main":0,
    "name:eng_x_preferred":[
        "Banahata Bazar"
    ],
    "wof:name":"Banahata Bazar",
    "wof:placetype":"neighbourhood",
    "wof:population":78
},
  "geometry": {"coordinates":[84.064756,26.590593],"type":"Point"}
}