{
  "type": "Feature",
  "properties": {
    "iso:country":"IN",
    "ks:ks_name":"Sukulpara Nakti Nala",
    "ks:ks_pop":551,
    "ks:ks_type":"HABITATION",
    "name:eng_x_preferred":[
        "Sukulpara Nakti Nala"
    ],
    "wof:name":"Sukulpara Nakti Nala",
    "wof:placetype":"locality",
    "wof:population":551
},
  "geometry": {"coordinates":[82.609494,21.201952],"type":"Point"}
}