{
  "type": "Feature",
  "properties": {
    "iso:country":"IN",
    "ks:ks_name":"Bank Tola",
    "ks:ks_pop":300,
    "ks:ks_type":"HABITATION",
    "ks:ks_uagg_main":0,
    "name:eng_x_preferred":[
        "Bank Tola"
    ],
    "wof:name":"Bank Tola",
    "wof:placetype":"neighbourhood",
    "wof:population":300
},
  "geometry": {"coordinates":[87.898033,26.216649],"type":"Point"}
}