{
  "type": "Feature",
  "properties": {
    "iso:country":"IN",
    "ks:ks_name":"Potarewasti",
    "ks:ks_pop":139,
    "ks:ks_type":"HABITATION",
    "name:eng_x_preferred":[
        "Potarewasti"
    ],
    "wof:name":"Potarewasti",
    "wof:placetype":"locality",
    "wof:population":139
},
  "geometry": {"coordinates":[74.960651,18.467481],"type":"Point"}
}