{
  "type": "Feature",
  "properties": {
    "iso:country":"IN",
    "ks:ks_alt_nam":"\u0100makhoh",
    "ks:ks_name":"Amakhoh",
    "ks:ks_pop":302,
    "ks:ks_type":"VILLAGE",
    "name:eng_x_preferred":[
        "Amakhoh"
    ],
    "name:eng_x_variant":[
        "\u0100makhoh"
    ],
    "wof:name":"Amakhoh",
    "wof:placetype":"locality",
    "wof:population":302
},
  "geometry": {"coordinates":[80.27288900000001,22.494229],"type":"Point"}
}