{
  "type": "Feature",
  "properties": {
    "gn:admin1_code":"34.0",
    "gn:admin2_code":"235.0",
    "gn:asciiname":"Dhawa",
    "gn:country_code":"IN",
    "gn:dem":104,
    "gn:feature_class":"P",
    "gn:feature_code":"PPL",
    "gn:name":"Dhawa",
    "gn:population":0,
    "gn:timezone":"Asia/Kolkata",
    "iso:country":"IN",
    "ks:ks_name":"Dhawa",
    "ks:ks_pop":766,
    "ks:ks_type":"VILLAGE",
    "ks:ks_uagg_main":0,
    "name:ceb_x_preferred":[
        "Dhawa"
    ],
    "name:eng_x_preferred":[
        "Dhawa"
    ],
    "name:mai_x_preferred":[
        "\u0927\u093e\u0935\u093e"
    ],
    "name:swe_x_preferred":[
        "Dhawa"
    ],
    "wof:name":"Dhawa",
    "wof:placetype":"neighbourhood",
    "wof:population":766
},
  "geometry": {"coordinates":[84.326516,24.872662],"type":"Point"}
}