{
  "type": "Feature",
  "properties": {
    "iso:country":"IN",
    "ks:ks_name":"Tadopani",
    "ks:ks_pop":180,
    "ks:ks_type":"VILLAGE",
    "name:eng_x_preferred":[
        "Tadopani"
    ],
    "wof:name":"Tadopani",
    "wof:placetype":"locality",
    "wof:population":180
},
  "geometry": {"coordinates":[82.636853,18.923426],"type":"Point"}
}