{
  "type": "Feature",
  "properties": {
    "iso:country":"IN",
    "ks:ks_name":"Gosaeepur Tola",
    "ks:ks_pop":196,
    "ks:ks_type":"HABITATION",
    "ks:ks_uagg_main":0,
    "name:eng_x_preferred":[
        "Gosaeepur Tola"
    ],
    "wof:name":"Gosaeepur Tola",
    "wof:placetype":"neighbourhood",
    "wof:population":196
},
  "geometry": {"coordinates":[83.24062600000001,27.069561],"type":"Point"}
}