{
  "type": "Feature",
  "properties": {
    "iso:country":"IN",
    "ks:ks_name":"Thakarwadi",
    "ks:ks_pop":581,
    "ks:ks_type":"HABITATION",
    "name:eng_x_preferred":[
        "Thakarwadi"
    ],
    "wof:name":"Thakarwadi",
    "wof:placetype":"locality",
    "wof:population":581
},
  "geometry": {"coordinates":[73.93804299999999,19.091334],"type":"Point"}
}