{
  "type": "Feature",
  "properties": {
    "gn:admin1_code":"19",
    "gn:admin2_code":"558.0",
    "gn:asciiname":"Nandyal",
    "gn:country_code":"IN",
    "gn:dem":501,
    "gn:feature_class":"P",
    "gn:feature_code":"PPL",
    "gn:name":"Nandy\u0101l",
    "gn:population":0,
    "gn:timezone":"Asia/Kolkata",
    "iso:country":"IN",
    "name:bih_x_preferred":[
        "\u0928\u093e\u0902\u0926\u092f\u093e\u0932"
    ],
    "name:bpy_x_preferred":[
        "\u09a8\u09be\u09a8\u09a6\u09af\u09bc\u09be\u09b2"
    ],
    "name:ceb_x_preferred":[
        "Nandy\u0101l"
    ],
    "name:deu_x_preferred":[
        "Nandyal"
    ],
    "name:fra_x_preferred":[
        "Nandyal"
    ],
    "name:hin_x_preferred":[
        "\u0928\u093e\u0902\u0926\u092f\u093e\u0932"
    ],
    "name:ita_x_preferred":[
        "Nandyal"
    ],
    "name:mar_x_preferred":[
        "\u0928\u0902\u0926\u094d\u092f\u093e\u0932"
    ],
    "name:mlg_x_preferred":[
        "Nandyal"
    ],
    "name:msa_x_preferred":[
        "Nandyal"
    ],
    "name:nep_x_preferred":[
        "\u0928\u093e\u0902\u0926\u092f\u093e\u0932"
    ],
    "name:new_x_preferred":[
        "\u0928\u0928\u094d\u0926\u094d\u092f\u093e\u0932"
    ],
    "name:nld_x_preferred":[
        "Nandyal"
    ],
    "name:ori_x_preferred":[
        "\u0b28\u0b28\u0b4d\u0b26\u0b4d\u0b5f\u0b3e\u0b32"
    ],
    "name:pam_x_preferred":[
        "Nandyal"
    ],
    "name:pol_x_preferred":[
        "Nandyal"
    ],
    "name:por_x_preferred":[
        "Nandyal"
    ],
    "name:srp_x_preferred":[
        "\u041d\u0430\u043d\u0434\u0458\u0430\u043b"
    ],
    "name:swe_x_preferred":[
        "Nandyal"
    ],
    "name:tam_x_preferred":[
        "\u0ba8\u0ba8\u0bcd\u0ba4\u0bbf\u0baf\u0bbe\u0bb2\u0bcd"
    ],
    "name:tel_x_preferred":[
        "\u0c28\u0c02\u0c26\u0c4d\u0c2f\u0c3e\u0c32"
    ],
    "name:tgl_x_preferred":[
        "Nandyal"
    ],
    "name:urd_x_preferred":[
        "\u0646\u0646\u062f\u06cc\u0627\u0644"
    ],
    "name:vie_x_preferred":[
        "Nandyal"
    ],
    "name:war_x_preferred":[
        "Nandyal"
    ],
    "name:zho_x_preferred":[
        "\u7eb3\u6069\u8fea\u4e9a\u5c14"
    ],
    "wof:name":"Nandyal",
    "wof:placetype":"locality"
},
  "geometry": {"coordinates":[77.51518,18.27401],"type":"Point"}
}