{
  "type": "Feature",
  "properties": {
    "iso:country":"IN",
    "ks:ks_name":"Dost Mohmmadpur",
    "ks:ks_pop":786,
    "ks:ks_type":"VILLAGE",
    "name:eng_x_preferred":[
        "Dost Mohmmadpur"
    ],
    "wof:name":"Dost Mohmmadpur",
    "wof:placetype":"locality",
    "wof:population":786
},
  "geometry": {"coordinates":[85.14721299999999,25.338401],"type":"Point"}
}