{
  "type": "Feature",
  "properties": {
    "iso:country":"IN",
    "ks:ks_name":"Parbotipur",
    "ks:ks_pop":1331,
    "ks:ks_type":"HABITATION",
    "name:eng_x_preferred":[
        "Parbotipur"
    ],
    "wof:name":"Parbotipur",
    "wof:placetype":"locality",
    "wof:population":1331
},
  "geometry": {"coordinates":[95.668848,27.560548],"type":"Point"}
}