{
  "type": "Feature",
  "properties": {
    "gn:admin1_code":"34.0",
    "gn:admin2_code":"220.0",
    "gn:asciiname":"Mukhtarpur",
    "gn:country_code":"IN",
    "gn:dem":53,
    "gn:feature_class":"P",
    "gn:feature_code":"PPL",
    "gn:name":"Mukht\u0101rpur",
    "gn:population":0,
    "gn:timezone":"Asia/Kolkata",
    "iso:country":"IN",
    "name:eng_x_preferred":[
        "Mukht\u0101rpur"
    ],
    "wof:name":"Mukhtarpur",
    "wof:placetype":"locality"
},
  "geometry": {"coordinates":[85.50488,25.60244],"type":"Point"}
}