{
  "type": "Feature",
  "properties": {
    "gn:admin1_code":"34.0",
    "gn:admin2_code":"220.0",
    "gn:asciiname":"Mukhtarpur",
    "gn:country_code":"IN",
    "gn:dem":53,
    "gn:feature_class":"P",
    "gn:feature_code":"PPL",
    "gn:name":"Mukht\u0101rpur",
    "gn:population":0,
    "gn:timezone":"Asia/Kolkata",
    "iso:country":"IN",
    "ks:ks_name":"Mokhtarpur",
    "ks:ks_pop":1560,
    "ks:ks_type":"VILLAGE",
    "name:eng_x_preferred":[
        "Mokhtarpur"
    ],
    "name:eng_x_variant":[
        "Mukhtarpur"
    ],
    "wof:name":"Mokhtarpur",
    "wof:placetype":"locality",
    "wof:population":1560
},
  "geometry": {"coordinates":[85.502776,25.594145],"type":"Point"}
}