{
  "type": "Feature",
  "properties": {
    "iso:country":"IN",
    "ks:ks_alt_nam":"Chhatar singh Nagar",
    "ks:ks_name":"Chhatar Singh Nagar",
    "ks:ks_pop":336,
    "ks:ks_type":"HABITATION",
    "name:eng_x_preferred":[
        "Chhatar Singh Nagar"
    ],
    "wof:name":"Chhatar Singh Nagar",
    "wof:placetype":"locality",
    "wof:population":336
},
  "geometry": {"coordinates":[72.417339,26.641011],"type":"Point"}
}