{
  "type": "Feature",
  "properties": {
    "iso:country":"IN",
    "ks:ks_alt_nam":"Nallipp\u0101laiyam",
    "ks:ks_name":"Nallippalaiyam",
    "ks:ks_pop":7961,
    "ks:ks_type":"VILLAGE",
    "ks:ks_uagg_main":0,
    "name:eng_x_preferred":[
        "Nallippalaiyam"
    ],
    "name:eng_x_variant":[
        "Nallipp\u0101laiyam"
    ],
    "wof:name":"Nallippalaiyam",
    "wof:placetype":"locality",
    "wof:population":7961
},
  "geometry": {"coordinates":[78.149485,11.238836],"type":"Point"}
}