{
  "type": "Feature",
  "properties": {
    "iso:country":"IN",
    "ks:ks_name":"Bishunpur",
    "ks:ks_pop":8,
    "ks:ks_type":"VILLAGE",
    "name:eng_x_preferred":[
        "Bishunpur"
    ],
    "wof:name":"Bishunpur",
    "wof:placetype":"locality",
    "wof:population":8
},
  "geometry": {"coordinates":[87.059027,24.591647],"type":"Point"}
}