{
  "type": "Feature",
  "properties": {
    "iso:country":"IN",
    "ks:ks_name":"Chandragarh",
    "ks:ks_pop":541,
    "ks:ks_type":"VILLAGE",
    "name:eng_x_preferred":[
        "Chandragarh"
    ],
    "wof:name":"Chandragarh",
    "wof:placetype":"locality",
    "wof:population":541
},
  "geometry": {"coordinates":[82.18715400000001,24.85468],"type":"Point"}
}