{
  "type": "Feature",
  "properties": {
    "gn:admin1_code":"16.0",
    "gn:admin2_code":"524",
    "gn:asciiname":"Godri",
    "gn:country_code":"IN",
    "gn:dem":609,
    "gn:feature_class":"P",
    "gn:feature_code":"PPL",
    "gn:name":"Godri",
    "gn:population":0,
    "gn:timezone":"Asia/Kolkata",
    "iso:country":"IN",
    "wof:name":"Godri",
    "wof:placetype":"locality"
},
  "geometry": {"coordinates":[76.64109999999999,18.31461],"type":"Point"}
}