{
  "type": "Feature",
  "properties": {
    "iso:country":"IN",
    "ks:ks_name":"Bhaliapadar",
    "ks:ks_pop":493,
    "ks:ks_type":"VILLAGE",
    "name:eng_x_preferred":[
        "Bhaliapadar"
    ],
    "wof:name":"Bhaliapadar",
    "wof:placetype":"locality",
    "wof:population":493
},
  "geometry": {"coordinates":[84.066962,20.853246],"type":"Point"}
}