{
  "type": "Feature",
  "properties": {
    "iso:country":"IN",
    "ks:ks_name":"Chatilo",
    "ks:ks_pop":318,
    "ks:ks_type":"VILLAGE",
    "ks:ks_uagg_main":0,
    "name:eng_x_preferred":[
        "Chatilo"
    ],
    "wof:name":"Chatilo",
    "wof:placetype":"neighbourhood",
    "wof:population":318
},
  "geometry": {"coordinates":[85.989508,20.545312],"type":"Point"}
}