{
  "type": "Feature",
  "properties": {
    "iso:country":"IN",
    "ks:ks_name":"Lala Basti",
    "ks:ks_pop":327,
    "ks:ks_type":"HABITATION",
    "name:eng_x_preferred":[
        "Lala Basti"
    ],
    "wof:name":"Lala Basti",
    "wof:placetype":"locality",
    "wof:population":327
},
  "geometry": {"coordinates":[92.89228300000001,25.120732],"type":"Point"}
}