{
  "type": "Feature",
  "properties": {
    "iso:country":"IN",
    "ks:ks_alt_nam":"Bark\u0101dih",
    "ks:ks_name":"Barkadih",
    "ks:ks_pop":1053,
    "ks:ks_type":"VILLAGE",
    "name:eng_x_preferred":[
        "Barkadih"
    ],
    "name:eng_x_variant":[
        "Bark\u0101dih"
    ],
    "wof:name":"Barkadih",
    "wof:placetype":"locality",
    "wof:population":1053
},
  "geometry": {"coordinates":[84.35402999999999,23.760652],"type":"Point"}
}