{
  "type": "Feature",
  "properties": {
    "gn:admin1_code":"34",
    "gn:admin2_code":"234.0",
    "gn:asciiname":"Tumba",
    "gn:country_code":"IN",
    "gn:dem":127,
    "gn:feature_class":"P",
    "gn:feature_code":"PPL",
    "gn:name":"Tumb\u0101",
    "gn:population":0,
    "gn:timezone":"Asia/Kolkata",
    "iso:country":"IN",
    "ks:ks_name":"Tumba",
    "ks:ks_pop":4872,
    "ks:ks_type":"VILLAGE",
    "ks:ks_uagg_main":0,
    "name:ceb_x_preferred":[
        "Tumba"
    ],
    "name:ces_x_preferred":[
        "Tumba"
    ],
    "name:deu_x_preferred":[
        "Tumba"
    ],
    "name:eng_x_preferred":[
        "Tumba"
    ],
    "name:fin_x_preferred":[
        "Tumba"
    ],
    "name:fra_x_preferred":[
        "Tumba"
    ],
    "name:hrv_x_preferred":[
        "Tumba"
    ],
    "name:ita_x_preferred":[
        "Tumba"
    ],
    "name:lat_x_preferred":[
        "Tumba"
    ],
    "name:lav_x_preferred":[
        "Tumba"
    ],
    "name:nld_x_preferred":[
        "Tumba"
    ],
    "name:pol_x_preferred":[
        "Tumba"
    ],
    "name:slk_x_preferred":[
        "Tumba"
    ],
    "name:swe_x_preferred":[
        "Tumba"
    ],
    "name:und_x_variant":[
        "Tumb\u0101"
    ],
    "wof:name":"Tumba",
    "wof:placetype":"neighbourhood",
    "wof:population":4872
},
  "geometry": {"coordinates":[84.02972200000001,24.73812],"type":"Point"}
}