{
  "type": "Feature",
  "properties": {
    "iso:country":"IN",
    "ks:ks_name":"Vandoor",
    "ks:ks_pop":922,
    "ks:ks_type":"VILLAGE",
    "name:eng_x_preferred":[
        "Vandoor"
    ],
    "wof:name":"Vandoor",
    "wof:placetype":"locality",
    "wof:population":922
},
  "geometry": {"coordinates":[74.463835,14.32817],"type":"Point"}
}