{
  "type": "Feature",
  "properties": {
    "gn:admin1_code":"12.0",
    "gn:admin2_code":"6.0",
    "gn:asciiname":"Jattah Dassal",
    "gn:country_code":"IN",
    "gn:dem":1038,
    "gn:feature_class":"P",
    "gn:feature_code":"PPL",
    "gn:name":"Jatt\u0101h Dassal",
    "gn:population":0,
    "gn:timezone":"Asia/Kolkata",
    "iso:country":"IN",
    "wof:name":"Jattah Dassal",
    "wof:placetype":"locality"
},
  "geometry": {"coordinates":[74.29794,33.36064],"type":"Point"}
}