{
  "type": "Feature",
  "properties": {
    "iso:country":"IN",
    "ks:ks_alt_nam":"PUKRUGUTU",
    "ks:ks_name":"Pukrugutu",
    "ks:ks_pop":333,
    "ks:ks_type":"HABITATION",
    "name:eng_x_preferred":[
        "Pukrugutu"
    ],
    "wof:name":"Pukrugutu",
    "wof:placetype":"locality",
    "wof:population":333
},
  "geometry": {"coordinates":[85.740759,22.510881],"type":"Point"}
}