{
  "type": "Feature",
  "properties": {
    "iso:country":"IN",
    "ks:ks_name":"Naugaon",
    "ks:ks_pop":80,
    "ks:ks_type":"VILLAGE",
    "name:eng_x_preferred":[
        "Naugaon"
    ],
    "wof:name":"Naugaon",
    "wof:placetype":"locality",
    "wof:population":80
},
  "geometry": {"coordinates":[79.378112,30.092427],"type":"Point"}
}