{
  "type": "Feature",
  "properties": {
    "gn:admin1_code":"24.0",
    "gn:admin2_code":"120",
    "gn:asciiname":"Ramnagar",
    "gn:country_code":"IN",
    "gn:dem":296,
    "gn:feature_class":"P",
    "gn:feature_code":"PPL",
    "gn:name":"R\u0101mnagar",
    "gn:population":0,
    "gn:timezone":"Asia/Kolkata",
    "iso:country":"IN",
    "name:und_x_variant":[
        "M\u012brnagar",
        "R\u0101mnagar"
    ],
    "wof:name":"Ramnagar",
    "wof:placetype":"locality"
},
  "geometry": {"coordinates":[75.72575000000001,25.97738],"type":"Point"}
}