{
  "type": "Feature",
  "properties": {
    "iso:country":"IN",
    "ks:ks_name":"Kannukudipatti",
    "ks:ks_pop":339,
    "ks:ks_type":"HABITATION",
    "name:eng_x_preferred":[
        "Kannukudipatti"
    ],
    "wof:name":"Kannukudipatti",
    "wof:placetype":"locality",
    "wof:population":339
},
  "geometry": {"coordinates":[79.09721500000001,10.491526],"type":"Point"}
}