{
  "type": "Feature",
  "properties": {
    "iso:country":"IN",
    "ks:ks_name":"Pandilu",
    "ks:ks_pop":182,
    "ks:ks_type":"HABITATION",
    "name:eng_x_preferred":[
        "Pandilu"
    ],
    "wof:name":"Pandilu",
    "wof:placetype":"locality",
    "wof:population":182
},
  "geometry": {"coordinates":[75.15829100000001,13.048459],"type":"Point"}
}