{
  "type": "Feature",
  "properties": {
    "gn:admin1_code":"36",
    "gn:admin2_code":"191.0",
    "gn:asciiname":"Gambhirpur",
    "gn:country_code":"IN",
    "gn:dem":85,
    "gn:feature_class":"P",
    "gn:feature_code":"PPL",
    "gn:name":"Gambh\u012brpur",
    "gn:population":0,
    "gn:timezone":"Asia/Kolkata",
    "iso:country":"IN",
    "name:und_x_variant":[
        "Gambh\u012brpur",
        "Baira D\u012bh"
    ],
    "wof:name":"Gambhirpur",
    "wof:placetype":"locality"
},
  "geometry": {"coordinates":[82.9939,25.94267],"type":"Point"}
}