{
  "type": "Feature",
  "properties": {
    "iso:country":"IN",
    "ks:ks_name":"Sarupothar Gaon East",
    "ks:ks_pop":1424,
    "ks:ks_type":"HABITATION",
    "name:eng_x_preferred":[
        "Sarupothar Gaon East"
    ],
    "wof:name":"Sarupothar Gaon East",
    "wof:placetype":"locality",
    "wof:population":1424
},
  "geometry": {"coordinates":[95.039923,27.483075],"type":"Point"}
}