{
  "type": "Feature",
  "properties": {
    "gn:admin1_code":"24.0",
    "gn:admin2_code":"125.0",
    "gn:asciiname":"Patapur",
    "gn:country_code":"IN",
    "gn:dem":244,
    "gn:feature_class":"P",
    "gn:feature_code":"PPL",
    "gn:name":"P\u0101t\u0101pur",
    "gn:population":0,
    "gn:timezone":"Asia/Kolkata",
    "iso:country":"IN",
    "ks:ks_alt_nam":"P\u0101t\u0101pur",
    "ks:ks_name":"Patapur",
    "ks:ks_type":"VILLAGE",
    "name:eng_x_preferred":[
        "Patapur"
    ],
    "name:eng_x_variant":[
        "P\u0101t\u0101pur"
    ],
    "wof:name":"Patapur",
    "wof:placetype":"locality"
},
  "geometry": {"coordinates":[74.36790999999999,23.285069],"type":"Point"}
}