{
  "type": "Feature",
  "properties": {
    "iso:country":"IN",
    "ks:ks_name":"Baraiktoli",
    "ks:ks_pop":109,
    "ks:ks_type":"HABITATION",
    "name:eng_x_preferred":[
        "Baraiktoli"
    ],
    "wof:name":"Baraiktoli",
    "wof:placetype":"locality",
    "wof:population":109
},
  "geometry": {"coordinates":[84.920284,22.658622],"type":"Point"}
}