{
  "type": "Feature",
  "properties": {
    "iso:country":"IN",
    "ks:ks_name":"Pekin Mudza",
    "ks:ks_pop":527,
    "ks:ks_type":"VILLAGE",
    "name:eng_x_preferred":[
        "Pekin Mudza"
    ],
    "wof:name":"Pekin Mudza",
    "wof:placetype":"locality",
    "wof:population":527
},
  "geometry": {"coordinates":[80.44843400000001,20.092123],"type":"Point"}
}