{
  "type": "Feature",
  "properties": {
    "iso:country":"IN",
    "ks:ks_name":"Paschim Subankhata",
    "ks:ks_pop":224,
    "ks:ks_type":"HABITATION",
    "name:eng_x_preferred":[
        "Paschim Subankhata"
    ],
    "wof:name":"Paschim Subankhata",
    "wof:placetype":"locality",
    "wof:population":224
},
  "geometry": {"coordinates":[91.414163,26.76263],"type":"Point"}
}