{
  "type": "Feature",
  "properties": {
    "gn:admin1_code":"24.0",
    "gn:admin2_code":"128.0",
    "gn:asciiname":"Berubeh",
    "gn:country_code":"IN",
    "gn:dem":431,
    "gn:feature_class":"P",
    "gn:feature_code":"PPL",
    "gn:name":"Ber\u016bbeh",
    "gn:population":0,
    "gn:timezone":"Asia/Kolkata",
    "iso:country":"IN",
    "ks:ks_alt_nam":"Ber\u016bbeh",
    "ks:ks_name":"Berubeh",
    "ks:ks_pop":532,
    "ks:ks_type":"VILLAGE",
    "name:eng_x_preferred":[
        "Berubeh"
    ],
    "name:eng_x_variant":[
        "Ber\u016bbeh"
    ],
    "wof:name":"Berubeh",
    "wof:placetype":"locality",
    "wof:population":532
},
  "geometry": {"coordinates":[76.79253,24.437981],"type":"Point"}
}