{
  "type": "Feature",
  "properties": {
    "iso:country":"IN",
    "qs:name":"Panchsheel Enclave",
    "qs:name_adm0":"India",
    "qs:name_adm1":"Delhi",
    "qs:photos":11,
    "qs:photos_1k":2,
    "qs:photos_9k":1,
    "qs:photos_9r":1,
    "qs:photos_all":11,
    "qs:photos_sr":1,
    "qs:placetype":"Suburb",
    "qs:pop_sr":"0",
    "wof:name":"Panchsheel Enclave",
    "wof:placetype":"neighbourhood"
},
  "geometry": {"coordinates":[77.22805,28.549544],"type":"Point"}
}