{
  "type": "Feature",
  "properties": {
    "iso:country":"IN",
    "ks:ks_name":"Thar Punjat",
    "ks:ks_pop":69,
    "ks:ks_type":"HABITATION",
    "name:eng_x_preferred":[
        "Thar Punjat"
    ],
    "wof:name":"Thar Punjat",
    "wof:placetype":"locality",
    "wof:population":69
},
  "geometry": {"coordinates":[78.452609,27.092519],"type":"Point"}
}