{
  "type": "Feature",
  "properties": {
    "iso:country":"IN",
    "ks:ks_name":"Mutharmudi School",
    "ks:ks_pop":143,
    "ks:ks_type":"HABITATION",
    "name:eng_x_preferred":[
        "Mutharmudi School"
    ],
    "wof:name":"Mutharmudi School",
    "wof:placetype":"locality",
    "wof:population":143
},
  "geometry": {"coordinates":[75.755278,12.335278],"type":"Point"}
}