{
  "type": "Feature",
  "properties": {
    "gn:admin1_code":"24.0",
    "gn:admin2_code":"104.0",
    "gn:asciiname":"Chhangalki",
    "gn:country_code":"IN",
    "gn:dem":234,
    "gn:feature_class":"P",
    "gn:feature_code":"PPL",
    "gn:name":"Chh\u0101ngalki",
    "gn:population":0,
    "gn:timezone":"Asia/Kolkata",
    "iso:country":"IN",
    "wof:name":"Chhangalki",
    "wof:placetype":"locality"
},
  "geometry": {"coordinates":[76.86443,27.46816],"type":"Point"}
}