{
  "type": "Feature",
  "properties": {
    "iso:country":"IN",
    "ks:ks_name":"Aylabari T E",
    "ks:ks_pop":1038,
    "ks:ks_type":"HABITATION",
    "name:eng_x_preferred":[
        "Aylabari T E"
    ],
    "wof:name":"Aylabari T E",
    "wof:placetype":"locality",
    "wof:population":1038
},
  "geometry": {"coordinates":[92.32340600000001,24.822507],"type":"Point"}
}