{
  "type": "Feature",
  "properties": {
    "iso:country":"IN",
    "ks:ks_name":"Melachinnayapuram",
    "ks:ks_pop":610,
    "ks:ks_type":"HABITATION",
    "name:eng_x_preferred":[
        "Melachinnayapuram"
    ],
    "wof:name":"Melachinnayapuram",
    "wof:placetype":"locality",
    "wof:population":610
},
  "geometry": {"coordinates":[77.90300999999999,9.474047],"type":"Point"}
}