{
  "type": "Feature",
  "properties": {
    "iso:country":"IN",
    "ks:ks_name":"Nagla Gadria Teja",
    "ks:ks_pop":486,
    "ks:ks_type":"HABITATION",
    "name:eng_x_preferred":[
        "Nagla Gadria Teja"
    ],
    "wof:name":"Nagla Gadria Teja",
    "wof:placetype":"locality",
    "wof:population":486
},
  "geometry": {"coordinates":[78.15566099999999,27.842031],"type":"Point"}
}