{
  "type": "Feature",
  "properties": {
    "gn:admin1_code":"16",
    "gn:admin2_code":"521.0",
    "gn:asciiname":"Wadgaon",
    "gn:country_code":"IN",
    "gn:dem":550,
    "gn:feature_class":"P",
    "gn:feature_code":"PPL",
    "gn:name":"Wadgaon",
    "gn:population":0,
    "gn:timezone":"Asia/Kolkata",
    "iso:country":"IN",
    "name:und_x_variant":[
        "Vadgaon-Nimbalkar",
        "Wadgaon"
    ],
    "wof:name":"Wadgaon",
    "wof:placetype":"locality"
},
  "geometry": {"coordinates":[74.36193,18.12964],"type":"Point"}
}