{
  "type": "Feature",
  "properties": {
    "gn:admin1_code":"11.0",
    "gn:admin2_code":"26.0",
    "gn:asciiname":"Bishal",
    "gn:country_code":"IN",
    "gn:dem":2015,
    "gn:feature_class":"P",
    "gn:feature_code":"PPL",
    "gn:name":"Bishal",
    "gn:population":0,
    "gn:timezone":"Asia/Kolkata",
    "iso:country":"IN",
    "wof:name":"Bishal",
    "wof:placetype":"locality"
},
  "geometry": {"coordinates":[77.34480000000001,31.46156],"type":"Point"}
}