{
  "type": "Feature",
  "properties": {
    "iso:country":"IN",
    "ks:ks_name":"Naaruvanipalli",
    "ks:ks_pop":81,
    "ks:ks_type":"HABITATION",
    "name:eng_x_preferred":[
        "Naaruvanipalli"
    ],
    "wof:name":"Naaruvanipalli",
    "wof:placetype":"locality",
    "wof:population":81
},
  "geometry": {"coordinates":[79.128412,15.287319],"type":"Point"}
}