{
  "type": "Feature",
  "properties": {
    "gn:admin1_code":"10",
    "gn:admin2_code":"77.0",
    "gn:asciiname":"Durjanpur",
    "gn:country_code":"IN",
    "gn:dem":227,
    "gn:feature_class":"P",
    "gn:feature_code":"PPL",
    "gn:name":"Durjanpur",
    "gn:population":0,
    "gn:timezone":"Asia/Kolkata",
    "iso:country":"IN",
    "wof:name":"Durjanpur",
    "wof:placetype":"locality"
},
  "geometry": {"coordinates":[76.02773000000001,29.45254000000001],"type":"Point"}
}