{
  "type": "Feature",
  "properties": {
    "iso:country":"IN",
    "ks:ks_name":"Andiyadar Jar",
    "ks:ks_pop":555,
    "ks:ks_type":"VILLAGE",
    "name:eng_x_preferred":[
        "Andiyadar Jar"
    ],
    "wof:name":"Andiyadar Jar",
    "wof:placetype":"locality",
    "wof:population":555
},
  "geometry": {"coordinates":[80.618909,22.800258],"type":"Point"}
}