{
  "type": "Feature",
  "properties": {
    "gn:admin1_code":"25.0",
    "gn:admin2_code":"631.0",
    "gn:asciiname":"Pungurutti",
    "gn:country_code":"IN",
    "gn:dem":567,
    "gn:feature_class":"P",
    "gn:feature_code":"PPL",
    "gn:name":"Pungurutti",
    "gn:population":0,
    "gn:timezone":"Asia/Kolkata",
    "iso:country":"IN",
    "wof:name":"Pungurutti",
    "wof:placetype":"neighbourhood"
},
  "geometry": {"coordinates":[78.29956,12.62628],"type":"Point"}
}