{
  "type": "Feature",
  "properties": {
    "gn:admin1_code":"36.0",
    "gn:admin2_code":"154.0",
    "gn:asciiname":"Chitauri",
    "gn:country_code":"IN",
    "gn:dem":131,
    "gn:feature_class":"P",
    "gn:feature_code":"PPL",
    "gn:name":"Chitauri",
    "gn:population":0,
    "gn:timezone":"Asia/Kolkata",
    "iso:country":"IN",
    "name:fas_x_preferred":[
        "\u0686\u06cc\u062a\u0627\u0648\u0631\u06cc"
    ],
    "name:ita_x_preferred":[
        "Chitauri"
    ],
    "name:por_x_preferred":[
        "Chitauri"
    ],
    "name:rus_x_preferred":[
        "\u0427\u0438\u0442\u0430\u0443\u0440\u0438"
    ],
    "name:spa_x_preferred":[
        "Chitauri"
    ],
    "wof:name":"Chitauri",
    "wof:placetype":"locality"
},
  "geometry": {"coordinates":[80.50798,27.29933],"type":"Point"}
}