{
  "type": "Feature",
  "properties": {
    "iso:country":"IN",
    "ks:ks_alt_nam":"D\u0101hugutu",
    "ks:ks_name":"Dahugutu",
    "ks:ks_type":"VILLAGE",
    "ks:ks_uagg_main":0,
    "name:eng_x_preferred":[
        "Dahugutu"
    ],
    "name:eng_x_variant":[
        "D\u0101hugutu"
    ],
    "wof:name":"Dahugutu",
    "wof:placetype":"neighbourhood"
},
  "geometry": {"coordinates":[85.276915,23.080441],"type":"Point"}
}