{
  "type": "Feature",
  "properties": {
    "gn:admin1_code":"38.0",
    "gn:admin2_code":"352.0",
    "gn:asciiname":"Kasari",
    "gn:country_code":"IN",
    "gn:dem":191,
    "gn:feature_class":"P",
    "gn:feature_code":"PPL",
    "gn:name":"Kas\u0101ri",
    "gn:population":0,
    "gn:timezone":"Asia/Kolkata",
    "iso:country":"IN",
    "name:deu_x_preferred":[
        "Kasari"
    ],
    "name:est_x_preferred":[
        "Kasari"
    ],
    "name:hye_x_preferred":[
        "\u053f\u0561\u057d\u0561\u057c\u056b"
    ],
    "name:nld_x_preferred":[
        "Kasari"
    ],
    "name:pol_x_preferred":[
        "Kasari"
    ],
    "name:spa_x_preferred":[
        "Kasari"
    ],
    "name:ukr_x_preferred":[
        "\u041a\u0430\u0437\u0430\u0440\u0456"
    ],
    "name:vol_x_preferred":[
        "Kasari"
    ],
    "wof:name":"Kasari",
    "wof:placetype":"locality"
},
  "geometry": {"coordinates":[87.68836,25.15294],"type":"Point"}
}