{
  "type": "Feature",
  "properties": {
    "gn:admin1_code":"38.0",
    "gn:admin2_code":"352.0",
    "gn:asciiname":"Kasari",
    "gn:country_code":"IN",
    "gn:dem":191,
    "gn:feature_class":"P",
    "gn:feature_code":"PPL",
    "gn:name":"Kas\u0101ri",
    "gn:population":0,
    "gn:timezone":"Asia/Kolkata",
    "iso:country":"IN",
    "wof:name":"Kasari",
    "wof:placetype":"locality"
},
  "geometry": {"coordinates":[87.68836,25.15294],"type":"Point"}
}