{
  "type": "Feature",
  "properties": {
    "gn:admin1_code":"35.0",
    "gn:admin2_code":"451.0",
    "gn:asciiname":"Chhapra",
    "gn:country_code":"IN",
    "gn:dem":542,
    "gn:feature_class":"P",
    "gn:feature_code":"PPL",
    "gn:name":"Chhapra",
    "gn:population":0,
    "gn:timezone":"Asia/Kolkata",
    "iso:country":"IN",
    "wof:name":"Chhapra",
    "wof:placetype":"locality"
},
  "geometry": {"coordinates":[80.33374999999999,23.19389],"type":"Point"}
}