{
  "type": "Feature",
  "properties": {
    "iso:country":"IN",
    "ks:ks_alt_nam":"SAYAPPANANA",
    "ks:ks_name":"Sayappanana",
    "ks:ks_pop":56,
    "ks:ks_type":"HABITATION",
    "ks:ks_uagg_main":0,
    "name:eng_x_preferred":[
        "Sayappanana"
    ],
    "wof:name":"Sayappanana",
    "wof:placetype":"neighbourhood",
    "wof:population":56
},
  "geometry": {"coordinates":[74.765665,17.213887],"type":"Point"}
}