{
  "type": "Feature",
  "properties": {
    "iso:country":"IN",
    "ks:ks_name":"Khera Kalyanpura",
    "ks:ks_pop":120,
    "ks:ks_type":"VILLAGE",
    "name:eng_x_preferred":[
        "Khera Kalyanpura"
    ],
    "wof:name":"Khera Kalyanpura",
    "wof:placetype":"locality",
    "wof:population":120
},
  "geometry": {"coordinates":[73.75951999999999,25.491983],"type":"Point"}
}