{
  "type": "Feature",
  "properties": {
    "iso:country":"IN",
    "ks:ks_name":"Radha Nagari",
    "ks:ks_pop":95,
    "ks:ks_type":"HABITATION",
    "name:eng_x_preferred":[
        "Radha Nagari"
    ],
    "wof:name":"Radha Nagari",
    "wof:placetype":"locality",
    "wof:population":95
},
  "geometry": {"coordinates":[80.802789,26.56517],"type":"Point"}
}