{
  "type": "Feature",
  "properties": {
    "gn:admin1_code":"11.0",
    "gn:admin2_code":"27.0",
    "gn:asciiname":"Dadhaun",
    "gn:country_code":"IN",
    "gn:dem":2224,
    "gn:feature_class":"P",
    "gn:feature_code":"PPL",
    "gn:name":"Dadhaun",
    "gn:population":0,
    "gn:timezone":"Asia/Kolkata",
    "iso:country":"IN",
    "wof:name":"Dadhaun",
    "wof:placetype":"locality"
},
  "geometry": {"coordinates":[77.2715,31.45788],"type":"Point"}
}