{
  "type": "Feature",
  "properties": {
    "gn:admin1_code":"40.0",
    "gn:admin2_code":"539.0",
    "gn:asciiname":"Nichin Dona",
    "gn:country_code":"IN",
    "gn:dem":79,
    "gn:feature_class":"P",
    "gn:feature_code":"PPL",
    "gn:name":"Nichin Dona",
    "gn:population":0,
    "gn:timezone":"Asia/Kolkata",
    "iso:country":"IN",
    "wof:name":"Nichin Dona",
    "wof:placetype":"locality"
},
  "geometry": {"coordinates":[79.93481,16.71861],"type":"Point"}
}