{
  "type": "Feature",
  "properties": {
    "gn:admin1_code":"12.0",
    "gn:admin2_code":"001",
    "gn:asciiname":"Bodkut Machpur",
    "gn:country_code":"IN",
    "gn:dem":1617,
    "gn:feature_class":"P",
    "gn:feature_code":"PPL",
    "gn:name":"Bodkut Machpur",
    "gn:population":0,
    "gn:timezone":"Asia/Kolkata",
    "iso:country":"IN",
    "wof:name":"Bodkut Machpur",
    "wof:placetype":"locality"
},
  "geometry": {"coordinates":[74.25434,34.39603],"type":"Point"}
}