{
  "type": "Feature",
  "properties": {
    "iso:country":"IN",
    "ks:ks_name":"Lakkulu",
    "ks:ks_pop":149,
    "ks:ks_type":"VILLAGE",
    "name:eng_x_preferred":[
        "Lakkulu"
    ],
    "wof:name":"Lakkulu",
    "wof:placetype":"locality",
    "wof:population":149
},
  "geometry": {"coordinates":[82.47854100000001,17.978471],"type":"Point"}
}