{
  "type": "Feature",
  "properties": {
    "gn:admin1_code":"34.0",
    "gn:admin2_code":"221.0",
    "gn:asciiname":"Hajpurwa",
    "gn:country_code":"IN",
    "gn:dem":52,
    "gn:feature_class":"P",
    "gn:feature_code":"PPL",
    "gn:name":"Hajpurwa",
    "gn:population":0,
    "gn:timezone":"Asia/Kolkata",
    "iso:country":"IN",
    "ks:ks_name":"Hajpurwa",
    "ks:ks_pop":2567,
    "ks:ks_type":"VILLAGE",
    "name:eng_x_preferred":[
        "Hajpurwa"
    ],
    "wof:name":"Hajpurwa",
    "wof:placetype":"locality",
    "wof:population":2567
},
  "geometry": {"coordinates":[85.71122200000001,26.00247],"type":"Point"}
}