{
  "type": "Feature",
  "properties": {
    "gn:admin1_code":"35",
    "gn:admin2_code":"456.0",
    "gn:asciiname":"Kuro",
    "gn:country_code":"IN",
    "gn:dem":503,
    "gn:feature_class":"P",
    "gn:feature_code":"PPL",
    "gn:name":"Kuro",
    "gn:population":0,
    "gn:timezone":"Asia/Kolkata",
    "iso:country":"IN",
    "name:bul_x_preferred":[
        "\u041a\u0443\u0440\u043e"
    ],
    "name:ceb_x_preferred":[
        "Kuro"
    ],
    "name:fra_x_preferred":[
        "Kuro"
    ],
    "name:ita_x_preferred":[
        "Kuro"
    ],
    "name:nld_x_preferred":[
        "Kuro"
    ],
    "name:swe_x_preferred":[
        "Kuro"
    ],
    "wof:name":"Kuro",
    "wof:placetype":"locality"
},
  "geometry": {"coordinates":[79.84040999999998,22.47592],"type":"Point"}
}