{
  "type": "Feature",
  "properties": {
    "gn:admin1_code":"12.0",
    "gn:admin2_code":"003",
    "gn:asciiname":"Gaik",
    "gn:country_code":"IN",
    "gn:dem":4520,
    "gn:feature_class":"P",
    "gn:feature_code":"PPL",
    "gn:name":"Gaik",
    "gn:population":0,
    "gn:timezone":"Asia/Kolkata",
    "iso:country":"IN",
    "wof:name":"Gaik",
    "wof:placetype":"locality"
},
  "geometry": {"coordinates":[78.13333,33.55],"type":"Point"}
}