{
  "type": "Feature",
  "properties": {
    "iso:country":"IN",
    "ks:ks_name":"Bando",
    "ks:ks_pop":329,
    "ks:ks_type":"VILLAGE",
    "ks:ks_uagg_main":0,
    "name:eng_x_preferred":[
        "Bando"
    ],
    "wof:name":"Bando",
    "wof:placetype":"neighbourhood",
    "wof:population":329
},
  "geometry": {"coordinates":[85.024473,23.402503],"type":"Point"}
}