{
  "type": "Feature",
  "properties": {
    "iso:country":"IN",
    "ks:ks_name":"Lagotiya Purwa",
    "ks:ks_pop":140,
    "ks:ks_type":"HABITATION",
    "name:eng_x_preferred":[
        "Lagotiya Purwa"
    ],
    "wof:name":"Lagotiya Purwa",
    "wof:placetype":"locality",
    "wof:population":140
},
  "geometry": {"coordinates":[81.65874599999999,26.594352],"type":"Point"}
}