{
  "type": "Feature",
  "properties": {
    "iso:country":"IN",
    "ks:ks_alt_nam":"PUNARWASH",
    "ks:ks_name":"Punarwash",
    "ks:ks_pop":437,
    "ks:ks_type":"HABITATION",
    "name:eng_x_preferred":[
        "Punarwash"
    ],
    "wof:name":"Punarwash",
    "wof:placetype":"locality",
    "wof:population":437
},
  "geometry": {"coordinates":[86.53765799999999,25.54779],"type":"Point"}
}