{
  "type": "Feature",
  "properties": {
    "iso:country":"IN",
    "ks:ks_alt_nam":"Madhup\u0101li",
    "ks:ks_name":"Madhupali",
    "ks:ks_type":"VILLAGE",
    "name:eng_x_preferred":[
        "Madhupali"
    ],
    "name:eng_x_variant":[
        "Madhup\u0101li"
    ],
    "wof:name":"Madhupali",
    "wof:placetype":"locality"
},
  "geometry": {"coordinates":[84.683121,21.329495],"type":"Point"}
}