{
  "type": "Feature",
  "properties": {
    "iso:country":"IN",
    "ks:ks_name":"Chinchkheda",
    "ks:ks_pop":436,
    "ks:ks_type":"VILLAGE",
    "name:eng_x_preferred":[
        "Chinchkheda"
    ],
    "wof:name":"Chinchkheda",
    "wof:placetype":"locality",
    "wof:population":436
},
  "geometry": {"coordinates":[74.993149,19.8993],"type":"Point"}
}