{
  "type": "Feature",
  "properties": {
    "iso:country":"IN",
    "ks:ks_name":"Assonigudem",
    "ks:ks_pop":142,
    "ks:ks_type":"HABITATION",
    "ks:ks_uagg_main":0,
    "name:eng_x_preferred":[
        "Assonigudem"
    ],
    "wof:name":"Assonigudem",
    "wof:placetype":"neighbourhood",
    "wof:population":142
},
  "geometry": {"coordinates":[78.99278099999999,17.306294],"type":"Point"}
}