{
  "type": "Feature",
  "properties": {
    "gn:admin1_code":"11",
    "gn:admin2_code":"23.0",
    "gn:asciiname":"Kalsara",
    "gn:country_code":"IN",
    "gn:dem":2021,
    "gn:feature_class":"P",
    "gn:feature_code":"PPL",
    "gn:name":"Kalsara",
    "gn:population":0,
    "gn:timezone":"Asia/Kolkata",
    "iso:country":"IN",
    "wof:name":"Kalsara",
    "wof:placetype":"locality"
},
  "geometry": {"coordinates":[76.00638000000002,32.77458],"type":"Point"}
}