{
  "type": "Feature",
  "properties": {
    "gn:admin1_code":"02",
    "gn:admin2_code":"542.0",
    "gn:asciiname":"Sigadam",
    "gn:country_code":"IN",
    "gn:dem":68,
    "gn:feature_class":"P",
    "gn:feature_code":"PPL",
    "gn:name":"Sigadam",
    "gn:population":0,
    "gn:timezone":"Asia/Kolkata",
    "iso:country":"IN",
    "wof:name":"Sigadam",
    "wof:placetype":"locality"
},
  "geometry": {"coordinates":[83.68174999999999,18.37869],"type":"Point"}
}