{
  "type": "Feature",
  "properties": {
    "iso:country":"IN",
    "ks:ks_name":"Tarkoni Nal",
    "ks:ks_pop":941,
    "ks:ks_type":"VILLAGE",
    "name:eng_x_preferred":[
        "Tarkoni Nal"
    ],
    "wof:name":"Tarkoni Nal",
    "wof:placetype":"locality",
    "wof:population":941
},
  "geometry": {"coordinates":[73.82575,23.398528],"type":"Point"}
}