{
  "type": "Feature",
  "properties": {
    "iso:country":"IN",
    "ks:ks_name":"Othaveedu",
    "ks:ks_pop":100,
    "ks:ks_type":"HABITATION",
    "name:eng_x_preferred":[
        "Othaveedu"
    ],
    "wof:name":"Othaveedu",
    "wof:placetype":"locality",
    "wof:population":100
},
  "geometry": {"coordinates":[78.354778,9.382522],"type":"Point"}
}