{
  "type": "Feature",
  "properties": {
    "iso:country":"IN",
    "ks:ks_name":"Khemunda",
    "ks:ks_pop":50,
    "ks:ks_type":"HABITATION",
    "name:eng_x_preferred":[
        "Khemunda"
    ],
    "wof:name":"Khemunda",
    "wof:placetype":"locality",
    "wof:population":50
},
  "geometry": {"coordinates":[84.629879,19.256825],"type":"Point"}
}