{
  "type": "Feature",
  "properties": {
    "gn:admin1_code":"24.0",
    "gn:admin2_code":"119.0",
    "gn:asciiname":"Dorai",
    "gn:country_code":"IN",
    "gn:dem":462,
    "gn:feature_class":"P",
    "gn:feature_code":"PPL",
    "gn:name":"Dor\u0101i",
    "gn:population":0,
    "gn:timezone":"Asia/Kolkata",
    "iso:country":"IN",
    "ks:ks_alt_nam":"Dor\u0101i",
    "ks:ks_name":"Dorai",
    "ks:ks_type":"VILLAGE",
    "ks:ks_uagg_main":0,
    "name:eng_x_preferred":[
        "Dorai"
    ],
    "name:eng_x_variant":[
        "Dor\u0101i"
    ],
    "wof:name":"Dorai",
    "wof:placetype":"neighbourhood"
},
  "geometry": {"coordinates":[74.628221,26.394795],"type":"Point"}
}