{
  "type": "Feature",
  "properties": {
    "iso:country":"IN",
    "ks:ks_name":"Mirdo Pathar",
    "ks:ks_pop":647,
    "ks:ks_type":"HABITATION",
    "ks:ks_uagg_main":0,
    "name:eng_x_preferred":[
        "Mirdo Pathar"
    ],
    "wof:name":"Mirdo Pathar",
    "wof:placetype":"neighbourhood",
    "wof:population":647
},
  "geometry": {"coordinates":[93.151578,26.082422],"type":"Point"}
}