{
  "type": "Feature",
  "properties": {
    "gn:admin1_code":"25.0",
    "gn:admin2_code":"604.0",
    "gn:asciiname":"Tiruvenkatapuram",
    "gn:country_code":"IN",
    "gn:dem":47,
    "gn:feature_class":"P",
    "gn:feature_code":"PPL",
    "gn:name":"Tiruvenkatapuram",
    "gn:population":0,
    "gn:timezone":"Asia/Kolkata",
    "iso:country":"IN",
    "ks:ks_name":"Thiruvengadapuram",
    "ks:ks_pop":232,
    "ks:ks_type":"HABITATION",
    "name:eng_x_preferred":[
        "Thiruvengadapuram"
    ],
    "name:eng_x_variant":[
        "Tiruvenkatapuram"
    ],
    "wof:name":"Thiruvengadapuram",
    "wof:placetype":"locality",
    "wof:population":232
},
  "geometry": {"coordinates":[79.79669199999999,12.559047],"type":"Point"}
}