{
  "type": "Feature",
  "properties": {
    "gn:admin1_code":"36",
    "gn:admin2_code":"186.0",
    "gn:asciiname":"Mustafabad",
    "gn:country_code":"IN",
    "gn:dem":88,
    "gn:feature_class":"P",
    "gn:feature_code":"PPL",
    "gn:name":"Mustaf\u0101b\u0101d",
    "gn:population":0,
    "gn:timezone":"Asia/Kolkata",
    "iso:country":"IN",
    "ks:ks_alt_nam":"Mustaf\u0101b\u0101d",
    "ks:ks_name":"Mustafabad",
    "ks:ks_type":"VILLAGE",
    "ks:ks_uagg_main":0,
    "name:eng_x_preferred":[
        "Mustafabad"
    ],
    "name:eng_x_variant":[
        "Mustaf\u0101b\u0101d"
    ],
    "wof:name":"Mustafabad",
    "wof:placetype":"neighbourhood"
},
  "geometry": {"coordinates":[82.98260000000001,26.795233],"type":"Point"}
}