{
  "type": "Feature",
  "properties": {
    "iso:country":"IN",
    "ks:ks_name":"Baraguda",
    "ks:ks_pop":280,
    "ks:ks_type":"HABITATION",
    "name:eng_x_preferred":[
        "Baraguda"
    ],
    "wof:name":"Baraguda",
    "wof:placetype":"locality",
    "wof:population":280
},
  "geometry": {"coordinates":[82.1195,19.815127],"type":"Point"}
}