{
  "type": "Feature",
  "properties": {
    "gn:admin1_code":"2.0",
    "gn:admin2_code":"553.0",
    "gn:asciiname":"Narasappagaripalle",
    "gn:country_code":"IN",
    "gn:dem":683,
    "gn:feature_class":"P",
    "gn:feature_code":"PPL",
    "gn:name":"Narasappag\u0101ripalle",
    "gn:population":0,
    "gn:timezone":"Asia/Kolkata",
    "iso:country":"IN",
    "ks:ks_alt_nam":"Narasappagari palli",
    "ks:ks_name":"Narasappagari Palli",
    "ks:ks_pop":185,
    "ks:ks_type":"HABITATION",
    "name:eng_x_preferred":[
        "Narasappagari Palli"
    ],
    "name:eng_x_variant":[
        "Narasappagaripalle"
    ],
    "wof:name":"Narasappagari Palli",
    "wof:placetype":"locality",
    "wof:population":185
},
  "geometry": {"coordinates":[78.217685,14.1633],"type":"Point"}
}