{
  "type": "Feature",
  "properties": {
    "gn:admin1_code":"19.0",
    "gn:admin2_code":"570.0",
    "gn:asciiname":"Thadagase",
    "gn:country_code":"IN",
    "gn:dem":1025,
    "gn:feature_class":"P",
    "gn:feature_code":"PPL",
    "gn:name":"Thadagase",
    "gn:population":0,
    "gn:timezone":"Asia/Kolkata",
    "iso:country":"IN",
    "wof:name":"Thadagase",
    "wof:placetype":"locality"
},
  "geometry": {"coordinates":[75.70595,13.23346],"type":"Point"}
}