{
  "type": "Feature",
  "properties": {
    "iso:country":"IN",
    "ks:ks_name":"Syed Abbas Pur",
    "ks:ks_pop":1595,
    "ks:ks_type":"VILLAGE",
    "ks:ks_uagg_main":0,
    "name:eng_x_preferred":[
        "Syed Abbas Pur"
    ],
    "wof:name":"Syed Abbas Pur",
    "wof:placetype":"neighbourhood",
    "wof:population":1595
},
  "geometry": {"coordinates":[80.469303,26.576697],"type":"Point"}
}