{
  "type": "Feature",
  "properties": {
    "iso:country":"IN",
    "ks:ks_name":"Jamani",
    "ks:ks_pop":0,
    "ks:ks_type":"VILLAGE",
    "name:eng_x_preferred":[
        "Jamani"
    ],
    "wof:name":"Jamani",
    "wof:placetype":"locality",
    "wof:population":0
},
  "geometry": {"coordinates":[79.128654,20.306293],"type":"Point"}
}