{
  "type": "Feature",
  "properties": {
    "iso:country":"IN",
    "ks:ks_name":"Wasali",
    "ks:ks_pop":1342,
    "ks:ks_type":"VILLAGE",
    "name:eng_x_preferred":[
        "Wasali"
    ],
    "wof:name":"Wasali",
    "wof:placetype":"neighbourhood",
    "wof:population":1342
},
  "geometry": {"coordinates":[73.68437,19.983984],"type":"Point"}
}