{
  "type": "Feature",
  "properties": {
    "gn:admin1_code":"16.0",
    "gn:admin2_code":"515.0",
    "gn:asciiname":"Borsar Khurd",
    "gn:country_code":"IN",
    "gn:dem":549,
    "gn:feature_class":"P",
    "gn:feature_code":"PPL",
    "gn:name":"Borsar Khurd",
    "gn:population":0,
    "gn:timezone":"Asia/Kolkata",
    "iso:country":"IN",
    "ks:ks_name":"Borsar Khurd",
    "ks:ks_type":"VILLAGE",
    "ks:ks_uagg_main":0,
    "name:eng_x_preferred":[
        "Borsar Khurd"
    ],
    "wof:name":"Borsar Khurd",
    "wof:placetype":"neighbourhood"
},
  "geometry": {"coordinates":[75.051669,20.099415],"type":"Point"}
}