{
  "type": "Feature",
  "properties": {
    "gn:admin1_code":"3.0",
    "gn:admin2_code":"303.0",
    "gn:asciiname":"Kalgachia",
    "gn:country_code":"IN",
    "gn:dem":46,
    "gn:feature_class":"P",
    "gn:feature_code":"PPL",
    "gn:name":"Kalgachia",
    "gn:population":0,
    "gn:timezone":"Asia/Kolkata",
    "iso:country":"IN",
    "ks:ks_name":"Kalgachia",
    "ks:ks_pop":1073,
    "ks:ks_type":"VILLAGE",
    "name:eng_x_preferred":[
        "Kalgachia"
    ],
    "wof:name":"Kalgachia",
    "wof:placetype":"locality",
    "wof:population":1073
},
  "geometry": {"coordinates":[90.86980200000001,26.353685],"type":"Point"}
}