{
  "type": "Feature",
  "properties": {
    "gn:admin1_code":"3.0",
    "gn:admin2_code":"303.0",
    "gn:asciiname":"Kalgachia",
    "gn:country_code":"IN",
    "gn:dem":46,
    "gn:feature_class":"P",
    "gn:feature_code":"PPL",
    "gn:name":"Kalgachia",
    "gn:population":0,
    "gn:timezone":"Asia/Kolkata",
    "iso:country":"IN",
    "wof:name":"Kalgachia",
    "wof:placetype":"locality"
},
  "geometry": {"coordinates":[90.87109,26.35921],"type":"Point"}
}