{
  "type": "Feature",
  "properties": {
    "iso:country":"IN",
    "ks:ks_name":"Lvechusani",
    "ks:ks_pop":113,
    "ks:ks_type":"VILLAGE",
    "name:eng_x_preferred":[
        "Lvechusani"
    ],
    "wof:name":"Lvechusani",
    "wof:placetype":"locality",
    "wof:population":113
},
  "geometry": {"coordinates":[79.439511,29.323347],"type":"Point"}
}