{
  "type": "Feature",
  "properties": {
    "iso:country":"IN",
    "ks:ks_name":"Puneri",
    "ks:ks_pop":65,
    "ks:ks_type":"HABITATION",
    "name:eng_x_preferred":[
        "Puneri"
    ],
    "wof:name":"Puneri",
    "wof:placetype":"locality",
    "wof:population":65
},
  "geometry": {"coordinates":[75.632071,12.616104],"type":"Point"}
}