{
  "type": "Feature",
  "properties": {
    "iso:country":"IN",
    "ks:ks_alt_nam":"Dharhani\u0101n",
    "ks:ks_name":"Dharhanian",
    "ks:ks_pop":0,
    "ks:ks_type":"VILLAGE",
    "name:eng_x_preferred":[
        "Dharhanian"
    ],
    "name:eng_x_variant":[
        "Dharhani\u0101n"
    ],
    "wof:name":"Dharhanian",
    "wof:placetype":"locality",
    "wof:population":0
},
  "geometry": {"coordinates":[83.661451,25.090273],"type":"Point"}
}