{
  "type": "Feature",
  "properties": {
    "iso:country":"IN",
    "ks:ks_name":"Ragund",
    "ks:ks_pop":34,
    "ks:ks_type":"HABITATION",
    "name:eng_x_preferred":[
        "Ragund"
    ],
    "wof:name":"Ragund",
    "wof:placetype":"locality",
    "wof:population":34
},
  "geometry": {"coordinates":[74.75230000000001,14.883722],"type":"Point"}
}