{
  "type": "Feature",
  "properties": {
    "iso:country":"IN",
    "ks:ks_name":"Khairapada",
    "ks:ks_pop":499,
    "ks:ks_type":"VILLAGE",
    "ks:ks_uagg_main":0,
    "name:eng_x_preferred":[
        "Khairapada"
    ],
    "wof:name":"Khairapada",
    "wof:placetype":"neighbourhood",
    "wof:population":499
},
  "geometry": {"coordinates":[85.852783,20.38913],"type":"Point"}
}