{
  "type": "Feature",
  "properties": {
    "iso:country":"IN",
    "ks:ks_name":"Mugupur",
    "ks:ks_pop":367,
    "ks:ks_type":"VILLAGE",
    "ks:ks_uagg_main":0,
    "name:eng_x_preferred":[
        "Mugupur"
    ],
    "wof:name":"Mugupur",
    "wof:placetype":"neighbourhood",
    "wof:population":367
},
  "geometry": {"coordinates":[86.201066,21.157307],"type":"Point"}
}