{
  "type": "Feature",
  "properties": {
    "iso:country":"IN",
    "ks:ks_name":"Dasanaikana Hatty",
    "ks:ks_pop":441,
    "ks:ks_type":"HABITATION",
    "ks:ks_uagg_main":0,
    "name:eng_x_preferred":[
        "Dasanaikana Hatty"
    ],
    "wof:name":"Dasanaikana Hatty",
    "wof:placetype":"neighbourhood",
    "wof:population":441
},
  "geometry": {"coordinates":[76.686854,14.291236],"type":"Point"}
}