{
  "type": "Feature",
  "properties": {
    "iso:country":"IN",
    "ks:ks_name":"Rampur",
    "ks:ks_pop":1047,
    "ks:ks_type":"VILLAGE",
    "ks:ks_uagg_main":0,
    "name:eng_x_preferred":[
        "Rampur"
    ],
    "name:hin_x_preferred":[
        "\u0930\u093e\u092e\u092a\u0941\u0930"
    ],
    "wof:name":"Rampur",
    "wof:placetype":"neighbourhood",
    "wof:population":1047
},
  "geometry": {"coordinates":[85.79174,26.417144],"type":"Point"}
}