{
  "type": "Feature",
  "properties": {
    "gn:admin1_code":"19.0",
    "gn:admin2_code":"565.0",
    "gn:asciiname":"Mudlapuram",
    "gn:country_code":"IN",
    "gn:dem":492,
    "gn:feature_class":"P",
    "gn:feature_code":"PPL",
    "gn:name":"Mudl\u0101puram",
    "gn:population":0,
    "gn:timezone":"Asia/Kolkata",
    "iso:country":"IN",
    "ks:ks_alt_nam":"Mudl\u0101puram",
    "ks:ks_alt_nam_2":"Mudlapuram",
    "ks:ks_name":"Mudlapura",
    "ks:ks_type":"VILLAGE",
    "name:eng_x_preferred":[
        "Mudlapura"
    ],
    "name:eng_x_variant":[
        "Mudlapuram",
        "Mudl\u0101puram"
    ],
    "wof:name":"Mudlapura",
    "wof:placetype":"locality"
},
  "geometry": {"coordinates":[76.309522,15.205869],"type":"Point"}
}