{
  "type": "Feature",
  "properties": {
    "gn:admin1_code":"10",
    "gn:admin2_code":"83.0",
    "gn:asciiname":"Chhapar",
    "gn:country_code":"IN",
    "gn:dem":225,
    "gn:feature_class":"P",
    "gn:feature_code":"PPL",
    "gn:name":"Chhap\u0101r",
    "gn:population":0,
    "gn:timezone":"Asia/Kolkata",
    "iso:country":"IN",
    "name:ben_x_preferred":[
        "\u099b\u09be\u09aa\u09be\u09b0"
    ],
    "name:bpy_x_preferred":[
        "\u099b\u09be\u09aa\u09be\u09b0"
    ],
    "name:ceb_x_preferred":[
        "Chh\u0101par"
    ],
    "name:hin_x_preferred":[
        "\u091b\u093e\u092a\u0930"
    ],
    "name:ita_x_preferred":[
        "Chhapar"
    ],
    "name:msa_x_preferred":[
        "Chhapar"
    ],
    "name:new_x_preferred":[
        "\u091b\u092a\u0930"
    ],
    "name:por_x_preferred":[
        "Chhapar"
    ],
    "name:swe_x_preferred":[
        "Chh\u0101par"
    ],
    "name:vie_x_preferred":[
        "Chhapar"
    ],
    "wof:name":"Chhapar",
    "wof:placetype":"locality"
},
  "geometry": {"coordinates":[76.59793000000001,28.44264],"type":"Point"}
}