{
  "type": "Feature",
  "properties": {
    "iso:country":"IN",
    "ks:ks_alt_nam":"Waz\u012br\u0101b\u0101d",
    "ks:ks_name":"Wazirabad",
    "ks:ks_type":"VILLAGE",
    "ks:ks_uagg_main":0,
    "name:eng_x_preferred":[
        "Wazirabad"
    ],
    "name:eng_x_variant":[
        "Waz\u012br\u0101b\u0101d"
    ],
    "wof:name":"Wazirabad",
    "wof:placetype":"neighbourhood"
},
  "geometry": {"coordinates":[77.22432999999999,28.724947],"type":"Point"}
}