{
  "type": "Feature",
  "properties": {
    "gn:admin1_code":"36",
    "gn:admin2_code":"132.0",
    "gn:asciiname":"Belka",
    "gn:country_code":"IN",
    "gn:dem":313,
    "gn:feature_class":"P",
    "gn:feature_code":"PPL",
    "gn:name":"Belka",
    "gn:population":0,
    "gn:timezone":"Asia/Kolkata",
    "iso:country":"IN",
    "wof:name":"Belka",
    "wof:placetype":"locality"
},
  "geometry": {"coordinates":[77.64715,30.18524],"type":"Point"}
}