{
  "type": "Feature",
  "properties": {
    "iso:country":"IN",
    "ks:ks_name":"Sahni Tola",
    "ks:ks_pop":233,
    "ks:ks_type":"HABITATION",
    "ks:ks_uagg_main":0,
    "name:eng_x_preferred":[
        "Sahni Tola"
    ],
    "wof:name":"Sahni Tola",
    "wof:placetype":"neighbourhood",
    "wof:population":233
},
  "geometry": {"coordinates":[87.153916,25.578563],"type":"Point"}
}