{
  "type": "Feature",
  "properties": {
    "iso:country":"IN",
    "ks:ks_name":"Girllaguda",
    "ks:ks_pop":87,
    "ks:ks_type":"HABITATION",
    "name:eng_x_preferred":[
        "Girllaguda"
    ],
    "wof:name":"Girllaguda",
    "wof:placetype":"locality",
    "wof:population":87
},
  "geometry": {"coordinates":[82.62632000000001,18.745548],"type":"Point"}
}