{
  "type": "Feature",
  "properties": {
    "gn:admin1_code":"23.0",
    "gn:admin2_code":"050",
    "gn:asciiname":"Govindwal",
    "gn:country_code":"IN",
    "gn:dem":233,
    "gn:feature_class":"P",
    "gn:feature_code":"PPL",
    "gn:name":"Govindw\u0101l",
    "gn:population":0,
    "gn:timezone":"Asia/Kolkata",
    "iso:country":"IN",
    "name:und_x_variant":[
        "Akbarpur",
        "Govindw\u0101l"
    ],
    "wof:name":"Govindwal",
    "wof:placetype":"locality"
},
  "geometry": {"coordinates":[75.14408,31.36706],"type":"Point"}
}