{
  "type": "Feature",
  "properties": {
    "iso:country":"IN",
    "ks:ks_name":"Bondulapanuku",
    "ks:ks_pop":19,
    "ks:ks_type":"HABITATION",
    "name:eng_x_preferred":[
        "Bondulapanuku"
    ],
    "wof:name":"Bondulapanuku",
    "wof:placetype":"locality",
    "wof:population":19
},
  "geometry": {"coordinates":[82.68349499999999,17.958237],"type":"Point"}
}