{
  "type": "Feature",
  "properties": {
    "gn:admin1_code":"11",
    "gn:admin2_code":"23.0",
    "gn:asciiname":"Hasluod",
    "gn:country_code":"IN",
    "gn:dem":1335,
    "gn:feature_class":"P",
    "gn:feature_code":"PPL",
    "gn:name":"Hasl\u016bod",
    "gn:population":0,
    "gn:timezone":"Asia/Kolkata",
    "iso:country":"IN",
    "wof:name":"Hasluod",
    "wof:placetype":"locality"
},
  "geometry": {"coordinates":[76.16674,32.78098],"type":"Point"}
}