{
  "type": "Feature",
  "properties": {
    "gn:admin1_code":"2.0",
    "gn:admin2_code":"553.0",
    "gn:asciiname":"Bandarlapalle",
    "gn:country_code":"IN",
    "gn:dem":604,
    "gn:feature_class":"P",
    "gn:feature_code":"PPL",
    "gn:name":"Band\u0101rlapalle",
    "gn:population":0,
    "gn:timezone":"Asia/Kolkata",
    "iso:country":"IN",
    "name:tel_x_preferred":[
        "\u0c2c\u0c02\u0c26\u0c30\u0c4d\u0c32\u0c2a\u0c32\u0c4d\u0c32\u0c46"
    ],
    "wof:name":"Bandarlapalle",
    "wof:placetype":"locality"
},
  "geometry": {"coordinates":[78.27965,14.03883],"type":"Point"}
}