{
  "type": "Feature",
  "properties": {
    "iso:country":"IN",
    "ks:ks_name":"Samarjap",
    "ks:ks_pop":740,
    "ks:ks_type":"VILLAGE",
    "name:eng_x_preferred":[
        "Samarjap"
    ],
    "wof:name":"Samarjap",
    "wof:placetype":"locality",
    "wof:population":740
},
  "geometry": {"coordinates":[74.12158599999999,24.122306],"type":"Point"}
}