{
  "type": "Feature",
  "properties": {
    "iso:country":"IN",
    "ks:ks_name":"Paras Purva",
    "ks:ks_pop":76,
    "ks:ks_type":"HABITATION",
    "name:eng_x_preferred":[
        "Paras Purva"
    ],
    "wof:name":"Paras Purva",
    "wof:placetype":"locality",
    "wof:population":76
},
  "geometry": {"coordinates":[81.02260099999999,28.361521],"type":"Point"}
}