{
  "type": "Feature",
  "properties": {
    "iso:country":"IN",
    "ks:ks_name":"Sahada I",
    "ks:ks_pop":1014,
    "ks:ks_type":"HABITATION",
    "name:eng_x_preferred":[
        "Sahada I"
    ],
    "wof:name":"Sahada I",
    "wof:placetype":"locality",
    "wof:population":1014
},
  "geometry": {"coordinates":[87.018776,21.533976],"type":"Point"}
}