{
  "type": "Feature",
  "properties": {
    "iso:country":"IN",
    "ks:ks_name":"Ganadabettu",
    "ks:ks_pop":29,
    "ks:ks_type":"HABITATION",
    "name:eng_x_preferred":[
        "Ganadabettu"
    ],
    "wof:name":"Ganadabettu",
    "wof:placetype":"locality",
    "wof:population":29
},
  "geometry": {"coordinates":[74.95889200000001,13.503619],"type":"Point"}
}