{
  "type": "Feature",
  "properties": {
    "iso:country":"IN",
    "ks:ks_name":"Devpuri",
    "ks:ks_pop":1123,
    "ks:ks_type":"VILLAGE",
    "name:eng_x_preferred":[
        "Devpuri"
    ],
    "wof:name":"Devpuri",
    "wof:placetype":"locality",
    "wof:population":1123
},
  "geometry": {"coordinates":[79.439792,29.985415],"type":"Point"}
}