{
  "type": "Feature",
  "properties": {
    "gn:admin1_code":"19.0",
    "gn:admin2_code":"567.0",
    "gn:asciiname":"Nellihankalu",
    "gn:country_code":"IN",
    "gn:dem":820,
    "gn:feature_class":"P",
    "gn:feature_code":"PPL",
    "gn:name":"Nellihankalu",
    "gn:population":0,
    "gn:timezone":"Asia/Kolkata",
    "iso:country":"IN",
    "wof:name":"Nellihankalu",
    "wof:placetype":"locality"
},
  "geometry": {"coordinates":[75.94925000000001,13.87639],"type":"Point"}
}