{
  "type": "Feature",
  "properties": {
    "iso:country":"IN",
    "ks:ks_name":"Dharampur Jarang",
    "ks:ks_pop":1842,
    "ks:ks_type":"VILLAGE",
    "name:eng_x_preferred":[
        "Dharampur Jarang"
    ],
    "wof:name":"Dharampur Jarang",
    "wof:placetype":"locality",
    "wof:population":1842
},
  "geometry": {"coordinates":[85.25259,25.928329],"type":"Point"}
}