{
  "type": "Feature",
  "properties": {
    "iso:country":"IN",
    "ks:ks_name":"Birkel",
    "ks:ks_pop":747,
    "ks:ks_type":"VILLAGE",
    "name:eng_x_preferred":[
        "Birkel"
    ],
    "wof:name":"Birkel",
    "wof:placetype":"locality",
    "wof:population":747
},
  "geometry": {"coordinates":[85.239947,22.685101],"type":"Point"}
}