{
  "type": "Feature",
  "properties": {
    "iso:country":"IN",
    "ks:ks_alt_nam":"KEELANAKOPPALU",
    "ks:ks_name":"Keelanakoppalu",
    "ks:ks_pop":294,
    "ks:ks_type":"HABITATION",
    "name:eng_x_preferred":[
        "Keelanakoppalu"
    ],
    "wof:name":"Keelanakoppalu",
    "wof:placetype":"locality",
    "wof:population":294
},
  "geometry": {"coordinates":[76.509049,12.575673],"type":"Point"}
}