{
  "type": "Feature",
  "properties": {
    "gn:admin1_code":"36.0",
    "gn:admin2_code":"132.0",
    "gn:asciiname":"Rupri Gujar",
    "gn:country_code":"IN",
    "gn:dem":280,
    "gn:feature_class":"P",
    "gn:feature_code":"PPL",
    "gn:name":"R\u016bpri G\u016bjar",
    "gn:population":0,
    "gn:timezone":"Asia/Kolkata",
    "iso:country":"IN",
    "name:und_x_variant":[
        "R\u016bpri G\u016bjar",
        "Kap\u016brpur"
    ],
    "wof:name":"Rupri Gujar",
    "wof:placetype":"locality"
},
  "geometry": {"coordinates":[77.49797,29.96478],"type":"Point"}
}