{
  "type": "Feature",
  "properties": {
    "gn:admin1_code":"11.0",
    "gn:admin2_code":"27.0",
    "gn:asciiname":"Lahthro",
    "gn:country_code":"IN",
    "gn:dem":1240,
    "gn:feature_class":"P",
    "gn:feature_code":"PPL",
    "gn:name":"Lahthro",
    "gn:population":0,
    "gn:timezone":"Asia/Kolkata",
    "iso:country":"IN",
    "wof:name":"Lahthro",
    "wof:placetype":"locality"
},
  "geometry": {"coordinates":[77.21003,31.32968],"type":"Point"}
}