{
  "type": "Feature",
  "properties": {
    "gn:admin1_code":"25.0",
    "gn:admin2_code":"606.0",
    "gn:asciiname":"Koraimaduvu",
    "gn:country_code":"IN",
    "gn:dem":670,
    "gn:feature_class":"P",
    "gn:feature_code":"PPL",
    "gn:name":"Koraimaduvu",
    "gn:population":0,
    "gn:timezone":"Asia/Kolkata",
    "iso:country":"IN",
    "wof:name":"Koraimaduvu",
    "wof:placetype":"locality"
},
  "geometry": {"coordinates":[78.94703,12.68383],"type":"Point"}
}