{
  "type": "Feature",
  "properties": {
    "iso:country":"IN",
    "ks:ks_name":"Varikkulam",
    "ks:ks_pop":1580,
    "ks:ks_type":"HABITATION",
    "name:eng_x_preferred":[
        "Varikkulam"
    ],
    "wof:name":"Varikkulam",
    "wof:placetype":"locality",
    "wof:population":1580
},
  "geometry": {"coordinates":[76.402438,9.450116],"type":"Point"}
}