{
  "type": "Feature",
  "properties": {
    "iso:country":"IN",
    "ks:ks_name":"Banamalipur",
    "ks:ks_pop":287,
    "ks:ks_type":"VILLAGE",
    "name:eng_x_preferred":[
        "Banamalipur"
    ],
    "wof:name":"Banamalipur",
    "wof:placetype":"locality",
    "wof:population":287
},
  "geometry": {"coordinates":[87.656206,22.499251],"type":"Point"}
}