{
  "type": "Feature",
  "properties": {
    "iso:country":"IN",
    "ks:ks_name":"Nayapara",
    "ks:ks_pop":260,
    "ks:ks_type":"HABITATION",
    "name:eng_x_preferred":[
        "Nayapara"
    ],
    "wof:name":"Nayapara",
    "wof:placetype":"locality",
    "wof:population":260
},
  "geometry": {"coordinates":[81.10113200000001,20.502868],"type":"Point"}
}