{
  "type": "Feature",
  "properties": {
    "iso:country":"IN",
    "ks:ks_name":"Sannamangalam",
    "ks:ks_pop":447,
    "ks:ks_type":"HABITATION",
    "ks:ks_uagg_main":0,
    "name:eng_x_preferred":[
        "Sannamangalam"
    ],
    "wof:name":"Sannamangalam",
    "wof:placetype":"neighbourhood",
    "wof:population":447
},
  "geometry": {"coordinates":[79.82947299999999,10.828151],"type":"Point"}
}