{
  "type": "Feature",
  "properties": {
    "iso:country":"IN",
    "ks:ks_name":"Dhamilo",
    "ks:ks_pop":511,
    "ks:ks_type":"VILLAGE",
    "ks:ks_uagg_main":0,
    "name:eng_x_preferred":[
        "Dhamilo"
    ],
    "wof:name":"Dhamilo",
    "wof:placetype":"neighbourhood",
    "wof:population":511
},
  "geometry": {"coordinates":[85.92099399999999,20.295039],"type":"Point"}
}