{
  "type": "Feature",
  "properties": {
    "gn:admin1_code":"39.0",
    "gn:admin2_code":"63.0",
    "gn:asciiname":"Nail",
    "gn:country_code":"IN",
    "gn:dem":1144,
    "gn:feature_class":"P",
    "gn:feature_code":"PPL",
    "gn:name":"N\u0101il",
    "gn:population":0,
    "gn:timezone":"Asia/Kolkata",
    "iso:country":"IN",
    "name:ben_x_preferred":[
        "\u09a8\u0996"
    ],
    "name:ceb_x_preferred":[
        "Nail"
    ],
    "name:deu_x_preferred":[
        "Nail"
    ],
    "name:ita_x_preferred":[
        "Nail"
    ],
    "name:jpn_x_preferred":[
        "\u30cd\u30a4\u30eb"
    ],
    "name:por_x_preferred":[
        "Nail"
    ],
    "name:yid_x_preferred":[
        "\u05e0\u05d0\u05d2\u05dc"
    ],
    "wof:name":"Nail",
    "wof:placetype":"locality"
},
  "geometry": {"coordinates":[79.82184000000002,29.79007],"type":"Point"}
}