{
  "type": "Feature",
  "properties": {
    "iso:country":"IN",
    "ks:ks_name":"Jamujori",
    "ks:ks_pop":107,
    "ks:ks_type":"VILLAGE",
    "ks:ks_uagg_main":0,
    "name:eng_x_preferred":[
        "Jamujori"
    ],
    "wof:name":"Jamujori",
    "wof:placetype":"neighbourhood",
    "wof:population":107
},
  "geometry": {"coordinates":[86.079661,20.792665],"type":"Point"}
}