{
  "type": "Feature",
  "properties": {
    "gn:admin1_code":"3.0",
    "gn:admin2_code":"320.0",
    "gn:asciiname":"Dhaligaon",
    "gn:country_code":"IN",
    "gn:dem":69,
    "gn:feature_class":"P",
    "gn:feature_code":"PPL",
    "gn:name":"Dhaligaon",
    "gn:population":0,
    "gn:timezone":"Asia/Kolkata",
    "iso:country":"IN",
    "wof:name":"Dhaligaon",
    "wof:placetype":"locality"
},
  "geometry": {"coordinates":[90.52159,26.4973],"type":"Point"}
}