{
  "type": "Feature",
  "properties": {
    "iso:country":"IN",
    "ks:ks_name":"Melamovarkarai",
    "ks:ks_pop":465,
    "ks:ks_type":"HABITATION",
    "ks:ks_uagg_main":0,
    "name:eng_x_preferred":[
        "Melamovarkarai"
    ],
    "wof:name":"Melamovarkarai",
    "wof:placetype":"neighbourhood",
    "wof:population":465
},
  "geometry": {"coordinates":[79.841273,11.216623],"type":"Point"}
}