{
  "type": "Feature",
  "properties": {
    "gn:admin1_code":"37",
    "gn:admin2_code":"410.0",
    "gn:asciiname":"Tikrapara",
    "gn:country_code":"IN",
    "gn:dem":302,
    "gn:feature_class":"P",
    "gn:feature_code":"PPL",
    "gn:name":"Tikr\u0101p\u0101ra",
    "gn:population":0,
    "gn:timezone":"Asia/Kolkata",
    "iso:country":"IN",
    "name:und_x_variant":[
        "Tikr\u0101p\u0101ra",
        "Gabhr\u0101p\u0101ra"
    ],
    "wof:name":"Tikrapara",
    "wof:placetype":"locality"
},
  "geometry": {"coordinates":[81.63738000000002,21.22477],"type":"Point"}
}