{
  "type": "Feature",
  "properties": {
    "iso:country":"IN",
    "ks:ks_name":"Sripal Ka Dera",
    "ks:ks_pop":62,
    "ks:ks_type":"HABITATION",
    "name:eng_x_preferred":[
        "Sripal Ka Dera"
    ],
    "wof:name":"Sripal Ka Dera",
    "wof:placetype":"locality",
    "wof:population":62
},
  "geometry": {"coordinates":[80.78272800000001,25.495816],"type":"Point"}
}