{
  "type": "Feature",
  "properties": {
    "gn:admin1_code":"24.0",
    "gn:admin2_code":"125.0",
    "gn:asciiname":"Masa",
    "gn:country_code":"IN",
    "gn:dem":247,
    "gn:feature_class":"P",
    "gn:feature_code":"PPL",
    "gn:name":"M\u0101sa",
    "gn:population":0,
    "gn:timezone":"Asia/Kolkata",
    "iso:country":"IN",
    "name:fra_x_preferred":[
        "Masa"
    ],
    "name:kor_x_preferred":[
        "\ub9c8\uc0ac"
    ],
    "name:msa_x_preferred":[
        "Masa"
    ],
    "name:ukr_x_preferred":[
        "\u041c\u0430\u0441\u0430"
    ],
    "name:zho_x_preferred":[
        "\u9a6c\u8428"
    ],
    "wof:name":"Masa",
    "wof:placetype":"locality"
},
  "geometry": {"coordinates":[74.33162,23.29183],"type":"Point"}
}