{
  "type": "Feature",
  "properties": {
    "iso:country":"IN",
    "ks:ks_name":"Bhavanichiwadi",
    "ks:ks_pop":149,
    "ks:ks_type":"HABITATION",
    "name:eng_x_preferred":[
        "Bhavanichiwadi"
    ],
    "wof:name":"Bhavanichiwadi",
    "wof:placetype":"locality",
    "wof:population":149
},
  "geometry": {"coordinates":[73.294184,19.766649],"type":"Point"}
}