{
  "type": "Feature",
  "properties": {
    "iso:country":"IN",
    "ks:ks_name":"Gobra",
    "ks:ks_pop":34,
    "ks:ks_type":"VILLAGE",
    "name:eng_x_preferred":[
        "Gobra"
    ],
    "wof:name":"Gobra",
    "wof:placetype":"locality",
    "wof:population":34
},
  "geometry": {"coordinates":[86.30596300000001,20.282216],"type":"Point"}
}