{
  "type": "Feature",
  "properties": {
    "gn:admin1_code":"12",
    "gn:admin2_code":"20.0",
    "gn:asciiname":"Bulldan",
    "gn:country_code":"IN",
    "gn:dem":2136,
    "gn:feature_class":"P",
    "gn:feature_code":"PPL",
    "gn:name":"Bulldan",
    "gn:population":0,
    "gn:timezone":"Asia/Kolkata",
    "iso:country":"IN",
    "wof:name":"Bulldan",
    "wof:placetype":"locality"
},
  "geometry": {"coordinates":[74.95668000000001,33.27169],"type":"Point"}
}