{
  "type": "Feature",
  "properties": {
    "iso:country":"IN",
    "ks:ks_name":"Rampur",
    "ks:ks_pop":1018,
    "ks:ks_type":"HABITATION",
    "ks:ks_uagg_main":0,
    "name:eng_x_preferred":[
        "Rampur"
    ],
    "name:hin_x_preferred":[
        "\u0930\u093e\u092e\u092a\u0941\u0930"
    ],
    "wof:name":"Rampur",
    "wof:placetype":"neighbourhood",
    "wof:population":1018
},
  "geometry": {"coordinates":[84.69389,25.509256],"type":"Point"}
}