{
  "type": "Feature",
  "properties": {
    "iso:country":"IN",
    "ks:ks_name":"Dangajore",
    "ks:ks_pop":891,
    "ks:ks_type":"VILLAGE",
    "name:eng_x_preferred":[
        "Dangajore"
    ],
    "wof:name":"Dangajore",
    "wof:placetype":"locality",
    "wof:population":891
},
  "geometry": {"coordinates":[84.42524899999999,21.924375],"type":"Point"}
}