{
  "type": "Feature",
  "properties": {
    "iso:country":"IN",
    "ks:ks_alt_nam":"Letua N.C.",
    "ks:ks_name":"Letua N.c.",
    "ks:ks_pop":44,
    "ks:ks_type":"HABITATION",
    "name:eng_x_preferred":[
        "Letua N.c."
    ],
    "wof:name":"Letua N.c.",
    "wof:placetype":"locality",
    "wof:population":44
},
  "geometry": {"coordinates":[94.364114,27.326658],"type":"Point"}
}