{
  "type": "Feature",
  "properties": {
    "iso:country":"IN",
    "ks:ks_alt_nam":"Kor\u0101di",
    "ks:ks_name":"Koradi",
    "ks:ks_type":"URBAN",
    "name:eng_x_preferred":[
        "Koradi"
    ],
    "name:eng_x_variant":[
        "Kor\u0101di"
    ],
    "wof:name":"Koradi",
    "wof:placetype":"locality"
},
  "geometry": {"coordinates":[79.105746,21.247575],"type":"Point"}
}