{
  "type": "Feature",
  "properties": {
    "iso:country":"IN",
    "ks:ks_name":"Madanpur",
    "ks:ks_pop":426,
    "ks:ks_type":"VILLAGE",
    "ks:ks_uagg_main":0,
    "name:eng_x_preferred":[
        "Madanpur"
    ],
    "wof:name":"Madanpur",
    "wof:placetype":"neighbourhood",
    "wof:population":426
},
  "geometry": {"coordinates":[88.619862,25.250524],"type":"Point"}
}