{
  "type": "Feature",
  "properties": {
    "gn:admin1_code":"36.0",
    "gn:admin2_code":"136.0",
    "gn:asciiname":"Bhola Nagla",
    "gn:country_code":"IN",
    "gn:dem":213,
    "gn:feature_class":"P",
    "gn:feature_code":"PPL",
    "gn:name":"Bhola Nagla",
    "gn:population":0,
    "gn:timezone":"Asia/Kolkata",
    "iso:country":"IN",
    "ks:ks_name":"Bhola Nagla",
    "ks:ks_pop":630,
    "ks:ks_type":"VILLAGE",
    "ks:ks_uagg_main":0,
    "name:eng_x_preferred":[
        "Bhola Nagla"
    ],
    "wof:name":"Bhola Nagla",
    "wof:placetype":"neighbourhood",
    "wof:population":630
},
  "geometry": {"coordinates":[78.94721800000001,29.051518],"type":"Point"}
}