{
  "type": "Feature",
  "properties": {
    "gn:admin1_code":"36.0",
    "gn:admin2_code":"134.0",
    "gn:asciiname":"Roshan Zamirpur",
    "gn:country_code":"IN",
    "gn:dem":221,
    "gn:feature_class":"P",
    "gn:feature_code":"PPL",
    "gn:name":"Roshan Zam\u012brpur",
    "gn:population":0,
    "gn:timezone":"Asia/Kolkata",
    "iso:country":"IN",
    "ks:ks_alt_nam":"Roshan Zam\u012brpur",
    "ks:ks_name":"Roshan Zamirpur",
    "ks:ks_type":"VILLAGE",
    "name:eng_x_preferred":[
        "Roshan Zamirpur"
    ],
    "name:eng_x_variant":[
        "Roshan Zam\u012brpur"
    ],
    "wof:name":"Roshan Zamirpur",
    "wof:placetype":"locality"
},
  "geometry": {"coordinates":[78.615205,29.315765],"type":"Point"}
}