{
  "type": "Feature",
  "properties": {
    "iso:country":"IN",
    "ks:ks_name":"Ramkrishnapally C",
    "ks:ks_pop":272,
    "ks:ks_type":"HABITATION",
    "name:eng_x_preferred":[
        "Ramkrishnapally C"
    ],
    "wof:name":"Ramkrishnapally C",
    "wof:placetype":"locality",
    "wof:population":272
},
  "geometry": {"coordinates":[88.315719,26.307232],"type":"Point"}
}