{
  "type": "Feature",
  "properties": {
    "gn:admin1_code":"21.0",
    "gn:admin2_code":"396.0",
    "gn:asciiname":"Tilesu",
    "gn:country_code":"IN",
    "gn:dem":296,
    "gn:feature_class":"P",
    "gn:feature_code":"PPL",
    "gn:name":"T\u012blesu",
    "gn:population":0,
    "gn:timezone":"Asia/Kolkata",
    "iso:country":"IN",
    "ks:ks_alt_nam":"T\u012blesu",
    "ks:ks_name":"Tilesu",
    "ks:ks_type":"VILLAGE",
    "name:eng_x_preferred":[
        "Tilesu"
    ],
    "name:eng_x_variant":[
        "T\u012blesu"
    ],
    "wof:name":"Tilesu",
    "wof:placetype":"locality"
},
  "geometry": {"coordinates":[83.402626,19.05051],"type":"Point"}
}