{
  "type": "Feature",
  "properties": {
    "iso:country":"IN",
    "ks:ks_name":"Motijhorajhar NC",
    "ks:ks_pop":321,
    "ks:ks_type":"VILLAGE",
    "name:eng_x_preferred":[
        "Motijhorajhar NC"
    ],
    "wof:name":"Motijhorajhar NC",
    "wof:placetype":"locality",
    "wof:population":321
},
  "geometry": {"coordinates":[89.94556799999999,26.314005],"type":"Point"}
}