{
  "type": "Feature",
  "properties": {
    "gn:admin1_code":"2",
    "gn:admin2_code":"544.0",
    "gn:asciiname":"Meba",
    "gn:country_code":"IN",
    "gn:dem":1236,
    "gn:feature_class":"P",
    "gn:feature_code":"PPL",
    "gn:name":"Meba",
    "gn:population":0,
    "gn:timezone":"Asia/Kolkata",
    "iso:country":"IN",
    "ks:ks_name":"Mebha",
    "ks:ks_pop":213,
    "ks:ks_type":"HABITATION",
    "name:eng_x_preferred":[
        "Mebha"
    ],
    "name:eng_x_variant":[
        "Meba"
    ],
    "wof:name":"Mebha",
    "wof:placetype":"locality",
    "wof:population":213
},
  "geometry": {"coordinates":[82.75093200000001,18.138709],"type":"Point"}
}