{
  "type": "Feature",
  "properties": {
    "gn:admin1_code":"37",
    "gn:admin2_code":"403.0",
    "gn:asciiname":"Nawagaon",
    "gn:country_code":"IN",
    "gn:dem":264,
    "gn:feature_class":"P",
    "gn:feature_code":"PPL",
    "gn:name":"Nawagaon",
    "gn:population":0,
    "gn:timezone":"Asia/Kolkata",
    "iso:country":"IN",
    "ks:ks_name":"Nawagaon",
    "ks:ks_pop":362,
    "ks:ks_type":"VILLAGE",
    "name:eng_x_preferred":[
        "Nawagaon"
    ],
    "wof:name":"Nawagaon",
    "wof:placetype":"locality",
    "wof:population":362
},
  "geometry": {"coordinates":[83.456945,21.968869],"type":"Point"}
}