{
  "type": "Feature",
  "properties": {
    "iso:country":"IN",
    "ks:ks_name":"Thotadakoppa",
    "ks:ks_type":"VILLAGE",
    "name:eng_x_preferred":[
        "Thotadakoppa"
    ],
    "wof:name":"Thotadakoppa",
    "wof:placetype":"locality"
},
  "geometry": {"coordinates":[75.318427,13.785347],"type":"Point"}
}