{
  "type": "Feature",
  "properties": {
    "iso:country":"IN",
    "ks:ks_name":"Gokal",
    "ks:ks_pop":1369,
    "ks:ks_type":"VILLAGE",
    "name:eng_x_preferred":[
        "Gokal"
    ],
    "wof:name":"Gokal",
    "wof:placetype":"locality",
    "wof:population":1369
},
  "geometry": {"coordinates":[72.391097,28.127861],"type":"Point"}
}