{
  "type": "Feature",
  "properties": {
    "iso:country":"IN",
    "ks:ks_name":"Belapur",
    "ks:ks_pop":324,
    "ks:ks_type":"HABITATION",
    "name:eng_x_preferred":[
        "Belapur"
    ],
    "wof:name":"Belapur",
    "wof:placetype":"locality",
    "wof:population":324
},
  "geometry": {"coordinates":[82.261831,24.926747],"type":"Point"}
}