{
  "type": "Feature",
  "properties": {
    "iso:country":"IN",
    "ks:ks_alt_nam":"Ch\u012blgarh",
    "ks:ks_name":"Chilgarh",
    "ks:ks_pop":55,
    "ks:ks_type":"VILLAGE",
    "name:eng_x_preferred":[
        "Chilgarh"
    ],
    "name:eng_x_variant":[
        "Ch\u012blgarh"
    ],
    "wof:name":"Chilgarh",
    "wof:placetype":"locality",
    "wof:population":55
},
  "geometry": {"coordinates":[78.786933,23.432924],"type":"Point"}
}