{
  "type": "Feature",
  "properties": {
    "iso:country":"IN",
    "ks:ks_alt_nam":"Jah\u0101ni\u0101npur",
    "ks:ks_name":"Jahanianpur",
    "ks:ks_type":"VILLAGE",
    "name:eng_x_preferred":[
        "Jahanianpur"
    ],
    "name:eng_x_variant":[
        "Jah\u0101ni\u0101npur"
    ],
    "wof:name":"Jahanianpur",
    "wof:placetype":"locality"
},
  "geometry": {"coordinates":[83.455133,25.869988],"type":"Point"}
}