{
  "type": "Feature",
  "properties": {
    "iso:country":"IN",
    "ks:ks_name":"Jhikdiyapura",
    "ks:ks_pop":233,
    "ks:ks_type":"HABITATION",
    "name:eng_x_preferred":[
        "Jhikdiyapura"
    ],
    "wof:name":"Jhikdiyapura",
    "wof:placetype":"locality",
    "wof:population":233
},
  "geometry": {"coordinates":[75.50124099999999,22.45297],"type":"Point"}
}