{
  "type": "Feature",
  "properties": {
    "iso:country":"IN",
    "ks:ks_name":"Kakua",
    "ks:ks_pop":428,
    "ks:ks_type":"VILLAGE",
    "name:eng_x_preferred":[
        "Kakua"
    ],
    "wof:name":"Kakua",
    "wof:placetype":"locality",
    "wof:population":428
},
  "geometry": {"coordinates":[82.623628,18.457607],"type":"Point"}
}