{
  "type": "Feature",
  "properties": {
    "gn:admin1_code":"38",
    "gn:admin2_code":"346.0",
    "gn:asciiname":"Nagar Untari",
    "gn:country_code":"IN",
    "gn:dem":247,
    "gn:feature_class":"P",
    "gn:feature_code":"PPL",
    "gn:name":"Nagar Unt\u0101ri",
    "gn:population":0,
    "gn:timezone":"Asia/Kolkata",
    "iso:country":"IN",
    "name:und_x_variant":[
        "Nagar Unt\u0101ri"
    ],
    "wof:name":"Nagar Untari",
    "wof:placetype":"locality"
},
  "geometry": {"coordinates":[83.49387,24.28046],"type":"Point"}
}