{
  "type": "Feature",
  "properties": {
    "gn:admin1_code":"21.0",
    "gn:admin2_code":"377.0",
    "gn:asciiname":"Purusottampur",
    "gn:country_code":"IN",
    "gn:dem":16,
    "gn:feature_class":"P",
    "gn:feature_code":"PPL",
    "gn:name":"Purusottampur",
    "gn:population":0,
    "gn:timezone":"Asia/Kolkata",
    "iso:country":"IN",
    "ks:ks_name":"Purusottampur",
    "ks:ks_pop":272,
    "ks:ks_type":"VILLAGE",
    "ks:ks_uagg_main":0,
    "name:ben_x_preferred":[
        "\u09aa\u09c1\u09b0\u09c1\u09b7\u09cb\u09a4\u09cd\u09a4\u09ae\u09aa\u09c1\u09b0"
    ],
    "name:bpy_x_preferred":[
        "\u09aa\u09c1\u09b0\u09c1\u09b7\u09cb\u09a4\u09cd\u09a4\u09ae\u09aa\u09c1\u09b0"
    ],
    "name:eng_x_preferred":[
        "Purusottampur"
    ],
    "name:ita_x_preferred":[
        "Purusottampur"
    ],
    "name:msa_x_preferred":[
        "Purusottampur"
    ],
    "name:new_x_preferred":[
        "\u092a\u0941\u0930\u0941\u0938\u094b\u0924\u094d\u0924\u092e\u092a\u0941\u0930"
    ],
    "name:nld_x_preferred":[
        "Purusottampur"
    ],
    "name:ori_x_preferred":[
        "\u0b2a\u0b41\u0b30\u0b41\u0b37\u0b4b\u0b24\u0b4d\u0b24\u0b2e\u0b2a\u0b41\u0b30"
    ],
    "name:por_x_preferred":[
        "Purusottampur"
    ],
    "name:vie_x_preferred":[
        "Purusottampur"
    ],
    "name:zho_x_preferred":[
        "\u666e\u9c81\u7d22\u5854\u59c6\u666e\u5c14"
    ],
    "wof:name":"Purusottampur",
    "wof:placetype":"neighbourhood",
    "wof:population":272
},
  "geometry": {"coordinates":[87.209045,21.620634],"type":"Point"}
}