{
  "type": "Feature",
  "properties": {
    "iso:country":"IN",
    "ks:ks_alt_nam":"WAIBINI ENGTI",
    "ks:ks_name":"Waibini Engti",
    "ks:ks_pop":335,
    "ks:ks_type":"HABITATION",
    "ks:ks_uagg_main":0,
    "name:eng_x_preferred":[
        "Waibini Engti"
    ],
    "wof:name":"Waibini Engti",
    "wof:placetype":"neighbourhood",
    "wof:population":335
},
  "geometry": {"coordinates":[93.12785700000001,26.146015],"type":"Point"}
}