{
  "type": "Feature",
  "properties": {
    "gn:admin1_code":"11",
    "gn:admin2_code":"23.0",
    "gn:asciiname":"Kaiga",
    "gn:country_code":"IN",
    "gn:dem":1596,
    "gn:feature_class":"P",
    "gn:feature_code":"PPL",
    "gn:name":"Kaiga",
    "gn:population":0,
    "gn:timezone":"Asia/Kolkata",
    "iso:country":"IN",
    "wof:name":"Kaiga",
    "wof:placetype":"locality"
},
  "geometry": {"coordinates":[76.12711999999998,32.725],"type":"Point"}
}