{
  "type": "Feature",
  "properties": {
    "iso:country":"IN",
    "ks:ks_name":"Kamagaru",
    "ks:ks_pop":12,
    "ks:ks_type":"HABITATION",
    "name:eng_x_preferred":[
        "Kamagaru"
    ],
    "wof:name":"Kamagaru",
    "wof:placetype":"locality",
    "wof:population":12
},
  "geometry": {"coordinates":[74.73326,14.033043],"type":"Point"}
}