{
  "type": "Feature",
  "properties": {
    "iso:country":"IN",
    "ks:ks_name":"Gobpal",
    "ks:ks_pop":132,
    "ks:ks_type":"HABITATION",
    "name:eng_x_preferred":[
        "Gobpal"
    ],
    "wof:name":"Gobpal",
    "wof:placetype":"locality",
    "wof:population":132
},
  "geometry": {"coordinates":[86.59733,21.47051],"type":"Point"}
}