{
  "type": "Feature",
  "properties": {
    "gn:admin1_code":"34.0",
    "gn:admin2_code":"234.0",
    "gn:asciiname":"Mahadeva",
    "gn:country_code":"IN",
    "gn:dem":113,
    "gn:feature_class":"P",
    "gn:feature_code":"PPL",
    "gn:name":"Mah\u0101deva",
    "gn:population":0,
    "gn:timezone":"Asia/Kolkata",
    "iso:country":"IN",
    "name:bih_x_preferred":[
        "\u092e\u0939\u093e\u0926\u0947\u0935\u093e"
    ],
    "name:deu_x_preferred":[
        "Mahadeva"
    ],
    "name:dty_x_preferred":[
        "\u092e\u0939\u093e\u0926\u0947\u0935\u093e \u0917\u093e\u0935\u093f\u0938"
    ],
    "name:ind_x_preferred":[
        "Mahadewa"
    ],
    "name:nep_x_preferred":[
        "\u092e\u0939\u093e\u0926\u0947\u0935\u093e"
    ],
    "name:pol_x_preferred":[
        "Mahadewa"
    ],
    "name:por_x_preferred":[
        "Mahadeva"
    ],
    "wof:name":"Mahadeva",
    "wof:placetype":"locality"
},
  "geometry": {"coordinates":[84.00593000000001,24.90882],"type":"Point"}
}