{
  "type": "Feature",
  "properties": {
    "iso:country":"IN",
    "ks:ks_name":"Nathivandla Palle",
    "ks:ks_pop":63,
    "ks:ks_type":"HABITATION",
    "name:eng_x_preferred":[
        "Nathivandla Palle"
    ],
    "wof:name":"Nathivandla Palle",
    "wof:placetype":"locality",
    "wof:population":63
},
  "geometry": {"coordinates":[78.59701800000001,13.937193],"type":"Point"}
}