{
  "type": "Feature",
  "properties": {
    "gn:admin1_code":"28.0",
    "gn:admin2_code":"334.0",
    "gn:asciiname":"Sadampara",
    "gn:country_code":"IN",
    "gn:dem":33,
    "gn:feature_class":"P",
    "gn:feature_code":"PPL",
    "gn:name":"Sadamp\u0101ra",
    "gn:population":0,
    "gn:timezone":"Asia/Kolkata",
    "iso:country":"IN",
    "wof:name":"Sadampara",
    "wof:placetype":"locality"
},
  "geometry": {"coordinates":[87.8241,24.11849],"type":"Point"}
}