{
  "type": "Feature",
  "properties": {
    "iso:country":"IN",
    "ks:ks_name":"Photo",
    "ks:ks_pop":286,
    "ks:ks_type":"HABITATION",
    "ks:ks_uagg_main":0,
    "name:eng_x_preferred":[
        "Photo"
    ],
    "wof:name":"Photo",
    "wof:placetype":"neighbourhood",
    "wof:population":286
},
  "geometry": {"coordinates":[93.80810099999999,26.025635],"type":"Point"}
}