{
  "type": "Feature",
  "properties": {
    "iso:country":"IN",
    "ks:ks_name":"Kilkila",
    "ks:ks_pop":1286,
    "ks:ks_type":"VILLAGE",
    "name:eng_x_preferred":[
        "Kilkila"
    ],
    "wof:name":"Kilkila",
    "wof:placetype":"locality",
    "wof:population":1286
},
  "geometry": {"coordinates":[83.74924,22.253221],"type":"Point"}
}