{
  "type": "Feature",
  "properties": {
    "iso:country":"IN",
    "ks:ks_name":"Venkagaddapalli",
    "ks:ks_pop":30,
    "ks:ks_type":"HABITATION",
    "name:eng_x_preferred":[
        "Venkagaddapalli"
    ],
    "wof:name":"Venkagaddapalli",
    "wof:placetype":"locality",
    "wof:population":30
},
  "geometry": {"coordinates":[78.682528,14.059502],"type":"Point"}
}