{
  "type": "Feature",
  "properties": {
    "gn:admin1_code":"11",
    "gn:admin2_code":"27.0",
    "gn:asciiname":"Dokla Maori",
    "gn:country_code":"IN",
    "gn:dem":1720,
    "gn:feature_class":"P",
    "gn:feature_code":"PPL",
    "gn:name":"Dokla M\u0101ori",
    "gn:population":0,
    "gn:timezone":"Asia/Kolkata",
    "iso:country":"IN",
    "wof:name":"Dokla Maori",
    "wof:placetype":"locality"
},
  "geometry": {"coordinates":[76.98987,31.39218],"type":"Point"}
}