{
  "type": "Feature",
  "properties": {
    "iso:country":"IN",
    "ks:ks_name":"Loharpada",
    "ks:ks_pop":551,
    "ks:ks_type":"HABITATION",
    "name:eng_x_preferred":[
        "Loharpada"
    ],
    "wof:name":"Loharpada",
    "wof:placetype":"locality",
    "wof:population":551
},
  "geometry": {"coordinates":[72.996202,19.862735],"type":"Point"}
}