{
  "type": "Feature",
  "properties": {
    "iso:country":"IN",
    "ks:ks_name":"Navinagri",
    "ks:ks_pop":905,
    "ks:ks_type":"HABITATION",
    "name:eng_x_preferred":[
        "Navinagri"
    ],
    "wof:name":"Navinagri",
    "wof:placetype":"locality",
    "wof:population":905
},
  "geometry": {"coordinates":[73.07986099999999,20.575528],"type":"Point"}
}