{
  "type": "Feature",
  "properties": {
    "iso:country":"IN",
    "ks:ks_name":"Haraizen Basti",
    "ks:ks_pop":360,
    "ks:ks_type":"HABITATION",
    "name:eng_x_preferred":[
        "Haraizen Basti"
    ],
    "wof:name":"Haraizen Basti",
    "wof:placetype":"locality",
    "wof:population":360
},
  "geometry": {"coordinates":[82.63113300000001,25.683465],"type":"Point"}
}