{
  "type": "Feature",
  "properties": {
    "gn:admin1_code":"19.0",
    "gn:admin2_code":"574.0",
    "gn:asciiname":"Patnahosahalli",
    "gn:country_code":"IN",
    "gn:dem":917,
    "gn:feature_class":"P",
    "gn:feature_code":"PPL",
    "gn:name":"Patnahosahalli",
    "gn:population":0,
    "gn:timezone":"Asia/Kolkata",
    "iso:country":"IN",
    "wof:name":"Patnahosahalli",
    "wof:placetype":"locality"
},
  "geometry": {"coordinates":[76.01044,12.78339],"type":"Point"}
}