{
  "type": "Feature",
  "properties": {
    "gn:admin1_code":"19.0",
    "gn:admin2_code":"574.0",
    "gn:asciiname":"Patnahosahalli",
    "gn:country_code":"IN",
    "gn:dem":917,
    "gn:feature_class":"P",
    "gn:feature_code":"PPL",
    "gn:name":"Patnahosahalli",
    "gn:population":0,
    "gn:timezone":"Asia/Kolkata",
    "iso:country":"IN",
    "ks:ks_name":"Puttanahosahalli",
    "ks:ks_pop":54,
    "ks:ks_type":"HABITATION",
    "name:eng_x_preferred":[
        "Puttanahosahalli"
    ],
    "name:eng_x_variant":[
        "Patnahosahalli"
    ],
    "wof:name":"Puttanahosahalli",
    "wof:placetype":"locality",
    "wof:population":54
},
  "geometry": {"coordinates":[76.009399,12.781253],"type":"Point"}
}