{
  "type": "Feature",
  "properties": {
    "iso:country":"IN",
    "ks:ks_name":"Ujjaini",
    "ks:ks_pop":446,
    "ks:ks_type":"VILLAGE",
    "name:eng_x_preferred":[
        "Ujjaini"
    ],
    "wof:name":"Ujjaini",
    "wof:placetype":"locality",
    "wof:population":446
},
  "geometry": {"coordinates":[73.24919300000001,19.786956],"type":"Point"}
}