{
  "type": "Feature",
  "properties": {
    "gn:admin1_code":"19.0",
    "gn:admin2_code":"574.0",
    "gn:asciiname":"Goravanahalli",
    "gn:country_code":"IN",
    "gn:dem":943,
    "gn:feature_class":"P",
    "gn:feature_code":"PPL",
    "gn:name":"Goravanahalli",
    "gn:population":0,
    "gn:timezone":"Asia/Kolkata",
    "iso:country":"IN",
    "ks:ks_name":"Goravanahalli",
    "ks:ks_pop":167,
    "ks:ks_type":"VILLAGE",
    "name:eng_x_preferred":[
        "Goravanahalli"
    ],
    "wof:name":"Goravanahalli",
    "wof:placetype":"locality",
    "wof:population":167
},
  "geometry": {"coordinates":[75.753513,13.007165],"type":"Point"}
}