{
  "type": "Feature",
  "properties": {
    "iso:country":"IN",
    "ks:ks_name":"Shankerpur Korer",
    "ks:ks_pop":260,
    "ks:ks_type":"VILLAGE",
    "name:eng_x_preferred":[
        "Shankerpur Korer"
    ],
    "wof:name":"Shankerpur Korer",
    "wof:placetype":"locality",
    "wof:population":260
},
  "geometry": {"coordinates":[79.563856,27.612444],"type":"Point"}
}