{
  "type": "Feature",
  "properties": {
    "iso:country":"IN",
    "ks:ks_name":"Kukreti Dhar",
    "ks:ks_pop":89,
    "ks:ks_type":"VILLAGE",
    "name:eng_x_preferred":[
        "Kukreti Dhar"
    ],
    "wof:name":"Kukreti Dhar",
    "wof:placetype":"locality",
    "wof:population":89
},
  "geometry": {"coordinates":[78.377663,30.043423],"type":"Point"}
}