{
  "type": "Feature",
  "properties": {
    "iso:country":"IN",
    "ks:ks_alt_nam":"Aantharwanpimpri lambatanda",
    "ks:ks_name":"Aantharwanpimpri Lambatanda",
    "ks:ks_pop":110,
    "ks:ks_type":"HABITATION",
    "name:eng_x_preferred":[
        "Aantharwanpimpri Lambatanda"
    ],
    "wof:name":"Aantharwanpimpri Lambatanda",
    "wof:placetype":"locality",
    "wof:population":110
},
  "geometry": {"coordinates":[75.826849,19.020879],"type":"Point"}
}