{
  "type": "Feature",
  "properties": {
    "gn:admin1_code":"36",
    "gn:admin2_code":"166.0",
    "gn:asciiname":"Sersa",
    "gn:country_code":"IN",
    "gn:dem":173,
    "gn:feature_class":"P",
    "gn:feature_code":"PPL",
    "gn:name":"Sersa",
    "gn:population":0,
    "gn:timezone":"Asia/Kolkata",
    "iso:country":"IN",
    "wof:name":"Sersa",
    "wof:placetype":"locality"
},
  "geometry": {"coordinates":[79.01755,25.88039],"type":"Point"}
}