{
  "type": "Feature",
  "properties": {
    "iso:country":"IN",
    "ks:ks_name":"Kakad Kuva P Umarda",
    "ks:ks_pop":566,
    "ks:ks_type":"VILLAGE",
    "name:eng_x_preferred":[
        "Kakad Kuva P Umarda"
    ],
    "wof:name":"Kakad Kuva P Umarda",
    "wof:placetype":"locality",
    "wof:population":566
},
  "geometry": {"coordinates":[73.565749,21.073253],"type":"Point"}
}