{
  "type": "Feature",
  "properties": {
    "iso:country":"IN",
    "ks:ks_name":"Bramhanwadi",
    "ks:ks_pop":130,
    "ks:ks_type":"HABITATION",
    "name:eng_x_preferred":[
        "Bramhanwadi"
    ],
    "wof:name":"Bramhanwadi",
    "wof:placetype":"locality",
    "wof:population":130
},
  "geometry": {"coordinates":[73.533925,16.744731],"type":"Point"}
}