{
  "type": "Feature",
  "properties": {
    "iso:country":"IN",
    "ks:ks_alt_nam":"KUNAIKHALI",
    "ks:ks_name":"Kunaikhali",
    "ks:ks_pop":2202,
    "ks:ks_type":"HABITATION",
    "ks:ks_uagg_main":0,
    "name:eng_x_preferred":[
        "Kunaikhali"
    ],
    "wof:name":"Kunaikhali",
    "wof:placetype":"neighbourhood",
    "wof:population":2202
},
  "geometry": {"coordinates":[88.578102,23.8946],"type":"Point"}
}