{
  "type": "Feature",
  "properties": {
    "iso:country":"IN",
    "ks:ks_name":"Baksullapur",
    "ks:ks_pop":83,
    "ks:ks_type":"HABITATION",
    "ks:ks_uagg_main":0,
    "name:eng_x_preferred":[
        "Baksullapur"
    ],
    "wof:name":"Baksullapur",
    "wof:placetype":"neighbourhood",
    "wof:population":83
},
  "geometry": {"coordinates":[81.8698,27.5991],"type":"Point"}
}