{
  "type": "Feature",
  "properties": {
    "iso:country":"IN",
    "ks:ks_name":"Shrirampur",
    "ks:ks_pop":1870,
    "ks:ks_type":"VILLAGE",
    "ks:ks_uagg_main":0,
    "name:eng_x_preferred":[
        "Shrirampur"
    ],
    "wof:name":"Shrirampur",
    "wof:placetype":"locality",
    "wof:population":1870
},
  "geometry": {"coordinates":[85.944329,26.033971],"type":"Point"}
}