{
  "type": "Feature",
  "properties": {
    "iso:country":"IN",
    "ks:ks_name":"Shrirampur",
    "ks:ks_pop":1870,
    "ks:ks_type":"VILLAGE",
    "ks:ks_uagg_main":0,
    "name:eng_x_preferred":[
        "Shrirampur"
    ],
    "name:hin_x_preferred":[
        "\u0936\u094d\u0930\u0940\u0930\u093e\u092e\u092a\u0941\u0930"
    ],
    "name:mar_x_preferred":[
        "\u0936\u094d\u0930\u0940\u0930\u093e\u092e\u092a\u0942\u0930"
    ],
    "wof:name":"Shrirampur",
    "wof:placetype":"locality",
    "wof:population":1870
},
  "geometry": {"coordinates":[85.944329,26.033971],"type":"Point"}
}