{
  "type": "Feature",
  "properties": {
    "iso:country":"IN",
    "ks:ks_name":"Vankagaddavooru",
    "ks:ks_pop":107,
    "ks:ks_type":"HABITATION",
    "name:eng_x_preferred":[
        "Vankagaddavooru"
    ],
    "wof:name":"Vankagaddavooru",
    "wof:placetype":"locality",
    "wof:population":107
},
  "geometry": {"coordinates":[78.929698,13.263175],"type":"Point"}
}