{
  "type": "Feature",
  "properties": {
    "gn:admin1_code":"39.0",
    "gn:admin2_code":"64.0",
    "gn:asciiname":"Nigrali",
    "gn:country_code":"IN",
    "gn:dem":1271,
    "gn:feature_class":"P",
    "gn:feature_code":"PPL",
    "gn:name":"Nigr\u0101li",
    "gn:population":0,
    "gn:timezone":"Asia/Kolkata",
    "iso:country":"IN",
    "ks:ks_alt_nam":"Nigr\u0101li",
    "ks:ks_name":"Nigrali",
    "ks:ks_type":"VILLAGE",
    "name:eng_x_preferred":[
        "Nigrali"
    ],
    "name:eng_x_variant":[
        "Nigr\u0101li"
    ],
    "wof:name":"Nigrali",
    "wof:placetype":"locality"
},
  "geometry": {"coordinates":[79.283002,29.610316],"type":"Point"}
}