{
  "type": "Feature",
  "properties": {
    "iso:country":"IN",
    "ks:ks_name":"Tejalpatti No 1",
    "ks:ks_pop":693,
    "ks:ks_type":"HABITATION",
    "ks:ks_uagg_main":0,
    "name:eng_x_preferred":[
        "Tejalpatti No 1"
    ],
    "wof:name":"Tejalpatti No 1",
    "wof:placetype":"neighbourhood",
    "wof:population":693
},
  "geometry": {"coordinates":[92.995149,26.839278],"type":"Point"}
}