{
  "type": "Feature",
  "properties": {
    "iso:country":"IN",
    "ks:ks_name":"Kokralpara",
    "ks:ks_pop":449,
    "ks:ks_type":"HABITATION",
    "name:eng_x_preferred":[
        "Kokralpara"
    ],
    "wof:name":"Kokralpara",
    "wof:placetype":"locality",
    "wof:population":449
},
  "geometry": {"coordinates":[81.873407,18.614437],"type":"Point"}
}