{
  "type": "Feature",
  "properties": {
    "iso:country":"IN",
    "ks:ks_name":"N M Colony",
    "ks:ks_pop":165,
    "ks:ks_type":"HABITATION",
    "name:eng_x_preferred":[
        "N M Colony"
    ],
    "wof:name":"N M Colony",
    "wof:placetype":"locality",
    "wof:population":165
},
  "geometry": {"coordinates":[75.997691,12.204046],"type":"Point"}
}