{
  "type": "Feature",
  "properties": {
    "iso:country":"IN",
    "ks:ks_name":"Bhosalewadi",
    "ks:ks_pop":38,
    "ks:ks_type":"HABITATION",
    "name:eng_x_preferred":[
        "Bhosalewadi"
    ],
    "wof:name":"Bhosalewadi",
    "wof:placetype":"locality",
    "wof:population":38
},
  "geometry": {"coordinates":[73.442078,16.579769],"type":"Point"}
}