{
  "type": "Feature",
  "properties": {
    "iso:country":"IN",
    "ks:ks_name":"Ranewadi",
    "ks:ks_pop":551,
    "ks:ks_type":"VILLAGE",
    "name:eng_x_preferred":[
        "Ranewadi"
    ],
    "wof:name":"Ranewadi",
    "wof:placetype":"locality",
    "wof:population":551
},
  "geometry": {"coordinates":[73.141406,18.279953],"type":"Point"}
}