{
  "type": "Feature",
  "properties": {
    "iso:country":"IN",
    "ks:ks_alt_nam":"PACHDHARPARA",
    "ks:ks_name":"Pachdharpara",
    "ks:ks_pop":241,
    "ks:ks_type":"HABITATION",
    "name:eng_x_preferred":[
        "Pachdharpara"
    ],
    "wof:name":"Pachdharpara",
    "wof:placetype":"locality",
    "wof:population":241
},
  "geometry": {"coordinates":[81.809618,22.214723],"type":"Point"}
}