{
  "type": "Feature",
  "properties": {
    "iso:country":"IN",
    "ks:ks_alt_nam":"N\u0101moli",
    "ks:ks_name":"Namoli",
    "ks:ks_type":"VILLAGE",
    "ks:ks_uagg_main":0,
    "name:eng_x_preferred":[
        "Namoli"
    ],
    "name:eng_x_variant":[
        "N\u0101moli"
    ],
    "wof:name":"Namoli",
    "wof:placetype":"neighbourhood"
},
  "geometry": {"coordinates":[77.476474,28.476247],"type":"Point"}
}