{
  "type": "Feature",
  "properties": {
    "gn:admin1_code":"36.0",
    "gn:admin2_code":"162",
    "gn:asciiname":"Kudarkot",
    "gn:country_code":"IN",
    "gn:dem":164,
    "gn:feature_class":"P",
    "gn:feature_code":"PPL",
    "gn:name":"Kudarkot",
    "gn:population":0,
    "gn:timezone":"Asia/Kolkata",
    "iso:country":"IN",
    "name:und_x_variant":[
        "Kudarkut",
        "Kudarkot"
    ],
    "wof:name":"Kudarkot",
    "wof:placetype":"locality"
},
  "geometry": {"coordinates":[79.39239000000001,26.81132],"type":"Point"}
}