{
  "type": "Feature",
  "properties": {
    "iso:country":"IN",
    "ks:ks_name":"Duhukuriya",
    "ks:ks_pop":464,
    "ks:ks_type":"VILLAGE",
    "name:eng_x_preferred":[
        "Duhukuriya"
    ],
    "wof:name":"Duhukuriya",
    "wof:placetype":"locality",
    "wof:population":464
},
  "geometry": {"coordinates":[81.79105800000001,23.973665],"type":"Point"}
}