{
  "type": "Feature",
  "properties": {
    "iso:country":"IN",
    "ks:ks_name":"Patel Para",
    "ks:ks_pop":131,
    "ks:ks_type":"HABITATION",
    "name:eng_x_preferred":[
        "Patel Para"
    ],
    "wof:name":"Patel Para",
    "wof:placetype":"locality",
    "wof:population":131
},
  "geometry": {"coordinates":[71.23777800000001,21.024444],"type":"Point"}
}