{
  "type": "Feature",
  "properties": {
    "iso:country":"IN",
    "ks:ks_alt_nam":"BHUIYAN TOLA",
    "ks:ks_name":"Bhuiyan Tola",
    "ks:ks_pop":119,
    "ks:ks_type":"HABITATION",
    "name:eng_x_preferred":[
        "Bhuiyan Tola"
    ],
    "wof:name":"Bhuiyan Tola",
    "wof:placetype":"locality",
    "wof:population":119
},
  "geometry": {"coordinates":[85.071169,24.239364],"type":"Point"}
}