{
  "type": "Feature",
  "properties": {
    "iso:country":"IN",
    "ks:ks_alt_nam":"CHEMBAI",
    "ks:ks_name":"Chembai",
    "ks:ks_pop":1526,
    "ks:ks_type":"HABITATION",
    "ks:ks_uagg_main":0,
    "name:eng_x_preferred":[
        "Chembai"
    ],
    "wof:name":"Chembai",
    "wof:placetype":"locality",
    "wof:population":1526
},
  "geometry": {"coordinates":[76.543571,10.764124],"type":"Point"}
}