{
  "type": "Feature",
  "properties": {
    "gn:admin1_code":"25",
    "gn:admin2_code":"604.0",
    "gn:asciiname":"Kilur",
    "gn:country_code":"IN",
    "gn:dem":33,
    "gn:feature_class":"P",
    "gn:feature_code":"PPL",
    "gn:name":"K\u012bl\u016br",
    "gn:population":0,
    "gn:timezone":"Asia/Kolkata",
    "iso:country":"IN",
    "ks:ks_alt_nam":"K\u012bl\u016br",
    "ks:ks_name":"Kilur",
    "ks:ks_pop":150,
    "ks:ks_type":"VILLAGE",
    "name:eng_x_preferred":[
        "Kilur"
    ],
    "name:eng_x_variant":[
        "K\u012bl\u016br"
    ],
    "wof:name":"Kilur",
    "wof:placetype":"locality",
    "wof:population":150
},
  "geometry": {"coordinates":[80.1164,12.743612],"type":"Point"}
}