{
  "type": "Feature",
  "properties": {
    "gn:admin1_code":"37",
    "gn:admin2_code":"406.0",
    "gn:asciiname":"Kuli",
    "gn:country_code":"IN",
    "gn:dem":271,
    "gn:feature_class":"P",
    "gn:feature_code":"PPL",
    "gn:name":"Kuli",
    "gn:population":0,
    "gn:timezone":"Asia/Kolkata",
    "iso:country":"IN",
    "name:ceb_x_preferred":[
        "Kuli"
    ],
    "name:deu_x_preferred":[
        "Kuli"
    ],
    "name:nds_x_preferred":[
        "Kuli"
    ],
    "name:nor_x_preferred":[
        "Kuli"
    ],
    "name:swe_x_preferred":[
        "Kuli"
    ],
    "wof:name":"Kuli",
    "wof:placetype":"locality"
},
  "geometry": {"coordinates":[82.41429000000002,22.14451],"type":"Point"}
}