{
  "type": "Feature",
  "properties": {
    "iso:country":"IN",
    "ks:ks_name":"Sidhapali",
    "ks:ks_pop":26,
    "ks:ks_type":"VILLAGE",
    "name:eng_x_preferred":[
        "Sidhapali"
    ],
    "wof:name":"Sidhapali",
    "wof:placetype":"locality",
    "wof:population":26
},
  "geometry": {"coordinates":[84.85660900000001,20.045844],"type":"Point"}
}