{
  "type": "Feature",
  "properties": {
    "gn:admin1_code":"16.0",
    "gn:admin2_code":"504.0",
    "gn:asciiname":"Anandwadi",
    "gn:country_code":"IN",
    "gn:dem":309,
    "gn:feature_class":"P",
    "gn:feature_code":"PPL",
    "gn:name":"\u0100nandw\u0101di",
    "gn:population":0,
    "gn:timezone":"Asia/Kolkata",
    "iso:country":"IN",
    "ks:ks_alt_nam":"\u0100nandw\u0101di",
    "ks:ks_name":"Anandwadi",
    "ks:ks_type":"VILLAGE",
    "ks:ks_uagg_main":0,
    "name:eng_x_preferred":[
        "Anandwadi"
    ],
    "name:eng_x_variant":[
        "\u0100nandw\u0101di"
    ],
    "wof:name":"Anandwadi",
    "wof:placetype":"neighbourhood"
},
  "geometry": {"coordinates":[78.16715000000001,21.122528],"type":"Point"}
}