{
  "type": "Feature",
  "properties": {
    "gn:admin1_code":"11",
    "gn:admin2_code":"31.0",
    "gn:asciiname":"Kathtoh",
    "gn:country_code":"IN",
    "gn:dem":956,
    "gn:feature_class":"P",
    "gn:feature_code":"PPL",
    "gn:name":"Kathtoh",
    "gn:population":0,
    "gn:timezone":"Asia/Kolkata",
    "iso:country":"IN",
    "wof:name":"Kathtoh",
    "wof:placetype":"locality"
},
  "geometry": {"coordinates":[76.89545,30.92732],"type":"Point"}
}