{
  "type": "Feature",
  "properties": {
    "iso:country":"IN",
    "ks:ks_name":"Bass Azam Shahpur",
    "ks:ks_pop":3835,
    "ks:ks_type":"HABITATION",
    "name:eng_x_preferred":[
        "Bass Azam Shahpur"
    ],
    "wof:name":"Bass Azam Shahpur",
    "wof:placetype":"locality",
    "wof:population":3835
},
  "geometry": {"coordinates":[76.172577,29.142001],"type":"Point"}
}