{
  "type": "Feature",
  "properties": {
    "iso:country":"IN",
    "ks:ks_name":"Amtola",
    "ks:ks_pop":60,
    "ks:ks_type":"VILLAGE",
    "name:eng_x_preferred":[
        "Amtola"
    ],
    "wof:name":"Amtola",
    "wof:placetype":"locality",
    "wof:population":60
},
  "geometry": {"coordinates":[87.610827,24.802563],"type":"Point"}
}