{
  "type": "Feature",
  "properties": {
    "gn:admin1_code":"16.0",
    "gn:admin2_code":"522.0",
    "gn:asciiname":"Bhalawna",
    "gn:country_code":"IN",
    "gn:dem":704,
    "gn:feature_class":"P",
    "gn:feature_code":"PPL",
    "gn:name":"Bhalawna",
    "gn:population":0,
    "gn:timezone":"Asia/Kolkata",
    "iso:country":"IN",
    "wof:name":"Bhalawna",
    "wof:placetype":"locality"
},
  "geometry": {"coordinates":[74.57356,19.11661],"type":"Point"}
}