{
  "type": "Feature",
  "properties": {
    "gn:admin1_code":"36",
    "gn:admin2_code":"179.0",
    "gn:asciiname":"Amari",
    "gn:country_code":"IN",
    "gn:dem":98,
    "gn:feature_class":"P",
    "gn:feature_code":"PPL",
    "gn:name":"Am\u0101ri",
    "gn:population":0,
    "gn:timezone":"Asia/Kolkata",
    "iso:country":"IN",
    "name:ceb_x_preferred":[
        "Amari"
    ],
    "name:deu_x_preferred":[
        "Amari"
    ],
    "name:ita_x_preferred":[
        "Amari"
    ],
    "name:nld_x_preferred":[
        "Amari"
    ],
    "name:rus_x_preferred":[
        "\u0410\u043c\u0430\u0440\u0438"
    ],
    "name:swe_x_preferred":[
        "Amari"
    ],
    "wof:name":"Amari",
    "wof:placetype":"locality"
},
  "geometry": {"coordinates":[82.10336,26.06926],"type":"Point"}
}