{
  "type": "Feature",
  "properties": {
    "iso:country":"IN",
    "ks:ks_name":"Purusottampur",
    "ks:ks_pop":334,
    "ks:ks_type":"VILLAGE",
    "ks:ks_uagg_main":0,
    "name:eng_x_preferred":[
        "Purusottampur"
    ],
    "wof:name":"Purusottampur",
    "wof:placetype":"neighbourhood",
    "wof:population":334
},
  "geometry": {"coordinates":[86.262272,20.526517],"type":"Point"}
}