{
  "type": "Feature",
  "properties": {
    "gn:admin1_code":"36",
    "gn:admin2_code":"154.0",
    "gn:asciiname":"Beshambar Lal Purwa",
    "gn:country_code":"IN",
    "gn:dem":119,
    "gn:feature_class":"P",
    "gn:feature_code":"PPL",
    "gn:name":"Beshambar L\u0101l Purwa",
    "gn:population":0,
    "gn:timezone":"Asia/Kolkata",
    "iso:country":"IN",
    "wof:name":"Beshambar Lal Purwa",
    "wof:placetype":"neighbourhood"
},
  "geometry": {"coordinates":[81.30208,27.39793],"type":"Point"}
}