{
  "type": "Feature",
  "properties": {
    "iso:country":"IN",
    "ks:ks_alt_nam":"PATHARE WASTI",
    "ks:ks_name":"Pathare Wasti",
    "ks:ks_pop":220,
    "ks:ks_type":"HABITATION",
    "name:eng_x_preferred":[
        "Pathare Wasti"
    ],
    "wof:name":"Pathare Wasti",
    "wof:placetype":"locality",
    "wof:population":220
},
  "geometry": {"coordinates":[74.553529,19.62169],"type":"Point"}
}