{
  "type": "Feature",
  "properties": {
    "gn:admin1_code":"35",
    "gn:admin2_code":"461.0",
    "gn:asciiname":"Gadidadar",
    "gn:country_code":"IN",
    "gn:dem":1119,
    "gn:feature_class":"P",
    "gn:feature_code":"PPL",
    "gn:name":"Gadid\u0101dar",
    "gn:population":0,
    "gn:timezone":"Asia/Kolkata",
    "iso:country":"IN",
    "ks:ks_name":"Gadhidadar",
    "ks:ks_pop":335,
    "ks:ks_type":"VILLAGE",
    "name:eng_x_preferred":[
        "Gadhidadar"
    ],
    "name:eng_x_variant":[
        "Gadidadar"
    ],
    "wof:name":"Gadhidadar",
    "wof:placetype":"locality",
    "wof:population":335
},
  "geometry": {"coordinates":[81.604623,22.862988],"type":"Point"}
}