{
  "type": "Feature",
  "properties": {
    "iso:country":"IN",
    "ks:ks_name":"Iyyalottipallam",
    "ks:ks_pop":248,
    "ks:ks_type":"HABITATION",
    "ks:ks_uagg_main":0,
    "name:eng_x_preferred":[
        "Iyyalottipallam"
    ],
    "wof:name":"Iyyalottipallam",
    "wof:placetype":"neighbourhood",
    "wof:population":248
},
  "geometry": {"coordinates":[78.094953,12.418901],"type":"Point"}
}