{
  "type": "Feature",
  "properties": {
    "iso:country":"IN",
    "ks:ks_alt_nam":"MANJARE KOLE VASTI",
    "ks:ks_name":"Manjare Kole Vasti",
    "ks:ks_pop":84,
    "ks:ks_type":"HABITATION",
    "name:eng_x_preferred":[
        "Manjare Kole Vasti"
    ],
    "wof:name":"Manjare Kole Vasti",
    "wof:placetype":"locality",
    "wof:population":84
},
  "geometry": {"coordinates":[74.949203,16.88732],"type":"Point"}
}