{
  "type": "Feature",
  "properties": {
    "iso:country":"IN",
    "ks:ks_alt_nam":"alaanickal njaralmpuzha",
    "ks:ks_name":"Alaanickal Njaralmpuzha",
    "ks:ks_pop":270,
    "ks:ks_type":"HABITATION",
    "name:eng_x_preferred":[
        "Alaanickal Njaralmpuzha"
    ],
    "wof:name":"Alaanickal Njaralmpuzha",
    "wof:placetype":"locality",
    "wof:population":270
},
  "geometry": {"coordinates":[76.81928499999999,9.820821],"type":"Point"}
}