{
  "type": "Feature",
  "properties": {
    "gn:admin1_code":"10",
    "gn:admin2_code":"73.0",
    "gn:asciiname":"Julani Khera",
    "gn:country_code":"IN",
    "gn:dem":237,
    "gn:feature_class":"P",
    "gn:feature_code":"PPL",
    "gn:name":"J\u016bl\u0101ni Khera",
    "gn:population":0,
    "gn:timezone":"Asia/Kolkata",
    "iso:country":"IN",
    "name:und_x_variant":[
        "J\u016bl\u0101ni Khera",
        "S\u016brta Khera"
    ],
    "wof:name":"Julani Khera",
    "wof:placetype":"locality"
},
  "geometry": {"coordinates":[76.33271999999999,29.64465],"type":"Point"}
}