{
  "type": "Feature",
  "properties": {
    "gn:admin1_code":"39.0",
    "gn:admin2_code":"060",
    "gn:asciiname":"Dagur",
    "gn:country_code":"IN",
    "gn:dem":999,
    "gn:feature_class":"P",
    "gn:feature_code":"PPL",
    "gn:name":"D\u0101gur",
    "gn:population":0,
    "gn:timezone":"Asia/Kolkata",
    "iso:country":"IN",
    "name:isl_x_preferred":[
        "Dagur"
    ],
    "wof:name":"Dagur",
    "wof:placetype":"locality"
},
  "geometry": {"coordinates":[77.99563000000001,30.41904000000001],"type":"Point"}
}