{
  "type": "Feature",
  "properties": {
    "iso:country":"IN",
    "ks:ks_name":"Srikantpara",
    "ks:ks_pop":653,
    "ks:ks_type":"VILLAGE",
    "ks:ks_uagg_main":0,
    "name:eng_x_preferred":[
        "Srikantpara"
    ],
    "wof:name":"Srikantpara",
    "wof:placetype":"neighbourhood",
    "wof:population":653
},
  "geometry": {"coordinates":[87.78819300000001,24.798842],"type":"Point"}
}