{
  "type": "Feature",
  "properties": {
    "iso:country":"IN",
    "ks:ks_name":"Mobhkhana Muvada",
    "ks:ks_pop":194,
    "ks:ks_type":"HABITATION",
    "name:eng_x_preferred":[
        "Mobhkhana Muvada"
    ],
    "wof:name":"Mobhkhana Muvada",
    "wof:placetype":"locality",
    "wof:population":194
},
  "geometry": {"coordinates":[73.359667,22.667528],"type":"Point"}
}