{
  "type": "Feature",
  "properties": {
    "iso:country":"IN",
    "ks:ks_name":"Sultanpur Chak Harihar",
    "ks:ks_pop":719,
    "ks:ks_type":"VILLAGE",
    "name:eng_x_preferred":[
        "Sultanpur Chak Harihar"
    ],
    "wof:name":"Sultanpur Chak Harihar",
    "wof:placetype":"locality",
    "wof:population":719
},
  "geometry": {"coordinates":[85.562748,25.874266],"type":"Point"}
}