{
  "type": "Feature",
  "properties": {
    "iso:country":"IN",
    "ks:ks_name":"Dukhnikhalsa",
    "ks:ks_pop":460,
    "ks:ks_type":"HABITATION",
    "name:eng_x_preferred":[
        "Dukhnikhalsa"
    ],
    "wof:name":"Dukhnikhalsa",
    "wof:placetype":"locality",
    "wof:population":460
},
  "geometry": {"coordinates":[75.35484,22.46092],"type":"Point"}
}