{
  "type": "Feature",
  "properties": {
    "iso:country":"IN",
    "ks:ks_name":"Kariganur",
    "ks:ks_pop":714,
    "ks:ks_type":"HABITATION",
    "name:eng_x_preferred":[
        "Kariganur"
    ],
    "wof:name":"Kariganur",
    "wof:placetype":"locality",
    "wof:population":714
},
  "geometry": {"coordinates":[76.355158,16.520878],"type":"Point"}
}