{
  "type": "Feature",
  "properties": {
    "iso:country":"IN",
    "ks:ks_alt_nam":"Am Chogunian",
    "ks:ks_name":"Am",
    "ks:ks_type":"VILLAGE",
    "name:eng_x_preferred":[
        "Am"
    ],
    "name:eng_x_variant":[
        "Am Chogunian"
    ],
    "wof:name":"Am",
    "wof:placetype":"locality"
},
  "geometry": {"coordinates":[79.741356,29.203626],"type":"Point"}
}