{
  "type": "Feature",
  "properties": {
    "iso:country":"IN",
    "ks:ks_name":"Kadamdih",
    "ks:ks_pop":106,
    "ks:ks_type":"HABITATION",
    "name:eng_x_preferred":[
        "Kadamdih"
    ],
    "wof:name":"Kadamdih",
    "wof:placetype":"locality",
    "wof:population":106
},
  "geometry": {"coordinates":[85.571551,22.989857],"type":"Point"}
}