{
  "type": "Feature",
  "properties": {
    "iso:country":"IN",
    "ks:ks_name":"Pandamakkal",
    "ks:ks_pop":859,
    "ks:ks_type":"HABITATION",
    "name:eng_x_preferred":[
        "Pandamakkal"
    ],
    "wof:name":"Pandamakkal",
    "wof:placetype":"locality",
    "wof:population":859
},
  "geometry": {"coordinates":[76.728172,9.622087],"type":"Point"}
}