{
  "type": "Feature",
  "properties": {
    "gn:admin1_code":"35",
    "gn:admin2_code":"456.0",
    "gn:asciiname":"Kekra Tola",
    "gn:country_code":"IN",
    "gn:dem":574,
    "gn:feature_class":"P",
    "gn:feature_code":"PPL",
    "gn:name":"Kekra Tol\u0101",
    "gn:population":0,
    "gn:timezone":"Asia/Kolkata",
    "iso:country":"IN",
    "wof:name":"Kekra Tola",
    "wof:placetype":"locality"
},
  "geometry": {"coordinates":[79.49757,22.50245],"type":"Point"}
}