{
  "type": "Feature",
  "properties": {
    "gn:admin1_code":"23.0",
    "gn:admin2_code":"38.0",
    "gn:asciiname":"Kang",
    "gn:country_code":"IN",
    "gn:dem":298,
    "gn:feature_class":"P",
    "gn:feature_code":"PPL",
    "gn:name":"Kang",
    "gn:population":0,
    "gn:timezone":"Asia/Kolkata",
    "iso:country":"IN",
    "name:ceb_x_preferred":[
        "Kang"
    ],
    "name:deu_x_preferred":[
        "Kang"
    ],
    "name:fin_x_preferred":[
        "Kang"
    ],
    "name:fra_x_preferred":[
        "Kang"
    ],
    "name:ita_x_preferred":[
        "Kang"
    ],
    "name:nor_x_preferred":[
        "Kang"
    ],
    "name:rus_x_preferred":[
        "\u041a\u0430\u043d\u0433"
    ],
    "name:spa_x_preferred":[
        "Kang"
    ],
    "name:swe_x_preferred":[
        "Kang"
    ],
    "name:tha_x_preferred":[
        "\u0e04\u0e31\u0e07"
    ],
    "wof:name":"Kang",
    "wof:placetype":"locality"
},
  "geometry": {"coordinates":[75.81589,31.66],"type":"Point"}
}