{
  "type": "Feature",
  "properties": {
    "iso:country":"IN",
    "ks:ks_name":"Mathiya",
    "ks:ks_pop":57,
    "ks:ks_type":"HABITATION",
    "ks:ks_uagg_main":0,
    "name:eng_x_preferred":[
        "Mathiya"
    ],
    "wof:name":"Mathiya",
    "wof:placetype":"neighbourhood",
    "wof:population":57
},
  "geometry": {"coordinates":[83.491912,27.044274],"type":"Point"}
}