{
  "type": "Feature",
  "properties": {
    "gn:admin1_code":"36.0",
    "gn:admin2_code":"176",
    "gn:asciiname":"Bilehra",
    "gn:country_code":"IN",
    "gn:dem":124,
    "gn:feature_class":"P",
    "gn:feature_code":"PPL",
    "gn:name":"Bilehra",
    "gn:population":0,
    "gn:timezone":"Asia/Kolkata",
    "iso:country":"IN",
    "wof:name":"Bilehra",
    "wof:placetype":"neighbourhood"
},
  "geometry": {"coordinates":[81.23693,27.24905],"type":"Point"}
}