{
  "type": "Feature",
  "properties": {
    "gn:admin1_code":"34.0",
    "gn:admin2_code":"207.0",
    "gn:asciiname":"Ektara",
    "gn:country_code":"IN",
    "gn:dem":64,
    "gn:feature_class":"P",
    "gn:feature_code":"PPL",
    "gn:name":"Ekt\u0101ra",
    "gn:population":0,
    "gn:timezone":"Asia/Kolkata",
    "iso:country":"IN",
    "name:ben_x_preferred":[
        "\u098f\u0995\u09a4\u09be\u09b0\u09be"
    ],
    "name:deu_x_preferred":[
        "Ektara"
    ],
    "name:epo_x_preferred":[
        "Ekataro"
    ],
    "name:eus_x_preferred":[
        "Ektara"
    ],
    "name:fra_x_preferred":[
        "Ektara"
    ],
    "name:hin_x_preferred":[
        "\u090f\u0915\u0924\u093e\u0930\u093e"
    ],
    "name:ind_x_preferred":[
        "Ektara"
    ],
    "name:ita_x_preferred":[
        "Ektara"
    ],
    "name:mar_x_preferred":[
        "\u090f\u0915\u0924\u093e\u0930\u0940"
    ],
    "name:nep_x_preferred":[
        "\u090f\u0915\u0924\u093e\u0930\u0947"
    ],
    "name:nld_x_preferred":[
        "Ektar"
    ],
    "name:pan_x_preferred":[
        "\u0a07\u0a71\u0a15\u0a24\u0a3e\u0a30\u0a3e"
    ],
    "name:pnb_x_preferred":[
        "\u0627\u06a9\u062a\u0627\u0631\u06c1"
    ],
    "name:pol_x_preferred":[
        "Ektara"
    ],
    "name:por_x_preferred":[
        "Ektara gopichand"
    ],
    "name:spa_x_preferred":[
        "Ek tara"
    ],
    "name:swe_x_preferred":[
        "Ektar"
    ],
    "name:urd_x_preferred":[
        "\u0627\u06cc\u06a9\u062a\u0627\u0631\u0627"
    ],
    "wof:name":"Ektara",
    "wof:placetype":"locality"
},
  "geometry": {"coordinates":[85.99656,26.45671],"type":"Point"}
}