{
  "type": "Feature",
  "properties": {
    "iso:country":"IN",
    "ks:ks_name":"Nala Domehar",
    "ks:ks_pop":102,
    "ks:ks_type":"VILLAGE",
    "name:eng_x_preferred":[
        "Nala Domehar"
    ],
    "wof:name":"Nala Domehar",
    "wof:placetype":"locality",
    "wof:population":102
},
  "geometry": {"coordinates":[76.976788,30.780475],"type":"Point"}
}