{
  "type": "Feature",
  "properties": {
    "iso:country":"IN",
    "ks:ks_name":"Chikni Nari",
    "ks:ks_pop":1091,
    "ks:ks_type":"VILLAGE",
    "name:eng_x_preferred":[
        "Chikni Nari"
    ],
    "wof:name":"Chikni Nari",
    "wof:placetype":"locality",
    "wof:population":1091
},
  "geometry": {"coordinates":[72.508533,26.935117],"type":"Point"}
}