{
  "type": "Feature",
  "properties": {
    "gn:admin1_code":"37",
    "gn:admin2_code":"404.0",
    "gn:asciiname":"Tuman",
    "gn:country_code":"IN",
    "gn:dem":369,
    "gn:feature_class":"P",
    "gn:feature_code":"PPL",
    "gn:name":"T\u016bm\u0101n",
    "gn:population":0,
    "gn:timezone":"Asia/Kolkata",
    "iso:country":"IN",
    "name:cat_x_preferred":[
        "Tuman"
    ],
    "name:ceb_x_preferred":[
        "Tuman"
    ],
    "name:deu_x_preferred":[
        "Tuman"
    ],
    "name:rus_x_preferred":[
        "\u0422\u0443\u043c\u0430\u043d"
    ],
    "name:ukr_x_preferred":[
        "\u0422\u0443\u043c\u0430\u043d"
    ],
    "name:uzb_x_preferred":[
        "Tuman"
    ],
    "wof:name":"Tuman",
    "wof:placetype":"locality"
},
  "geometry": {"coordinates":[82.41795,22.57349],"type":"Point"}
}