{
  "type": "Feature",
  "properties": {
    "gn:admin1_code":"40.0",
    "gn:admin2_code":"539.0",
    "gn:asciiname":"Bhimanpalli",
    "gn:country_code":"IN",
    "gn:dem":389,
    "gn:feature_class":"P",
    "gn:feature_code":"PPL",
    "gn:name":"Bh\u012bmanpalli",
    "gn:population":0,
    "gn:timezone":"Asia/Kolkata",
    "iso:country":"IN",
    "wof:name":"Bhimanpalli",
    "wof:placetype":"locality"
},
  "geometry": {"coordinates":[78.83555,17.3282],"type":"Point"}
}