{
  "type": "Feature",
  "properties": {
    "iso:country":"IN",
    "ks:ks_name":"Sikkula Hotel",
    "ks:ks_pop":39,
    "ks:ks_type":"HABITATION",
    "ks:ks_uagg_main":0,
    "name:eng_x_preferred":[
        "Sikkula Hotel"
    ],
    "wof:name":"Sikkula Hotel",
    "wof:placetype":"neighbourhood",
    "wof:population":39
},
  "geometry": {"coordinates":[78.54507700000001,13.490663],"type":"Point"}
}