{
  "type": "Feature",
  "properties": {
    "iso:country":"IN",
    "ks:ks_name":"Chirugunia",
    "ks:ks_pop":0,
    "ks:ks_type":"VILLAGE",
    "name:eng_x_preferred":[
        "Chirugunia"
    ],
    "wof:name":"Chirugunia",
    "wof:placetype":"locality",
    "wof:population":0
},
  "geometry": {"coordinates":[85.785472,20.972774],"type":"Point"}
}