{
  "type": "Feature",
  "properties": {
    "iso:country":"IN",
    "ks:ks_name":"Tikuli",
    "ks:ks_pop":14,
    "ks:ks_type":"VILLAGE",
    "name:eng_x_preferred":[
        "Tikuli"
    ],
    "wof:name":"Tikuli",
    "wof:placetype":"locality",
    "wof:population":14
},
  "geometry": {"coordinates":[85.909769,24.623237],"type":"Point"}
}