{
  "type": "Feature",
  "properties": {
    "iso:country":"IN",
    "ks:ks_name":"Bapujinagar",
    "ks:ks_pop":1,
    "ks:ks_type":"HABITATION",
    "name:eng_x_preferred":[
        "Bapujinagar"
    ],
    "wof:name":"Bapujinagar",
    "wof:placetype":"locality",
    "wof:population":1
},
  "geometry": {"coordinates":[79.68373699999999,13.839748],"type":"Point"}
}