{
  "type": "Feature",
  "properties": {
    "iso:country":"IN",
    "ks:ks_name":"Doddamane",
    "ks:ks_pop":71,
    "ks:ks_type":"HABITATION",
    "name:eng_x_preferred":[
        "Doddamane"
    ],
    "wof:name":"Doddamane",
    "wof:placetype":"locality",
    "wof:population":71
},
  "geometry": {"coordinates":[74.85125600000001,13.970692],"type":"Point"}
}