{
  "type": "Feature",
  "properties": {
    "gn:admin1_code":"34.0",
    "gn:admin2_code":"237.0",
    "gn:asciiname":"Majhila Auwal",
    "gn:country_code":"IN",
    "gn:dem":141,
    "gn:feature_class":"P",
    "gn:feature_code":"PPL",
    "gn:name":"Majhila Auwal",
    "gn:population":0,
    "gn:timezone":"Asia/Kolkata",
    "iso:country":"IN",
    "ks:ks_name":"Majhila Auwal",
    "ks:ks_type":"VILLAGE",
    "name:eng_x_preferred":[
        "Majhila Auwal"
    ],
    "wof:name":"Majhila Auwal",
    "wof:placetype":"locality"
},
  "geometry": {"coordinates":[85.446648,24.650618],"type":"Point"}
}