{
  "type": "Feature",
  "properties": {
    "iso:country":"IN",
    "ks:ks_name":"Podpada",
    "ks:ks_pop":52,
    "ks:ks_type":"HABITATION",
    "name:eng_x_preferred":[
        "Podpada"
    ],
    "wof:name":"Podpada",
    "wof:placetype":"locality",
    "wof:population":52
},
  "geometry": {"coordinates":[83.402219,19.969698],"type":"Point"}
}