{
  "type": "Feature",
  "properties": {
    "gn:admin1_code":"23.0",
    "gn:admin2_code":"54.0",
    "gn:asciiname":"Mahta",
    "gn:country_code":"IN",
    "gn:dem":222,
    "gn:feature_class":"P",
    "gn:feature_code":"PPL",
    "gn:name":"Mahta",
    "gn:population":0,
    "gn:timezone":"Asia/Kolkata",
    "iso:country":"IN",
    "wof:name":"Mahta",
    "wof:placetype":"locality"
},
  "geometry": {"coordinates":[75.40805999999998,30.28805],"type":"Point"}
}