{
  "type": "Feature",
  "properties": {
    "gn:admin1_code":"23.0",
    "gn:admin2_code":"54.0",
    "gn:asciiname":"Mahta",
    "gn:country_code":"IN",
    "gn:dem":222,
    "gn:feature_class":"P",
    "gn:feature_code":"PPL",
    "gn:name":"Mahta",
    "gn:population":0,
    "gn:timezone":"Asia/Kolkata",
    "iso:country":"IN",
    "name:eng_x_preferred":[
        "Mehta"
    ],
    "name:eng_x_variant":[
        "Mahta"
    ],
    "wof:name":"Mehta",
    "wof:placetype":"locality"
},
  "geometry": {"coordinates":[75.40806000000001,30.28805],"type":"Point"}
}