{
  "type": "Feature",
  "properties": {
    "gn:admin1_code":"40.0",
    "gn:admin2_code":"535.0",
    "gn:asciiname":"Kurmapalli",
    "gn:country_code":"IN",
    "gn:dem":531,
    "gn:feature_class":"P",
    "gn:feature_code":"PPL",
    "gn:name":"Kurmapalli",
    "gn:population":0,
    "gn:timezone":"Asia/Kolkata",
    "iso:country":"IN",
    "ks:ks_name":"Kurmapally",
    "ks:ks_pop":357,
    "ks:ks_type":"HABITATION",
    "ks:ks_uagg_main":0,
    "name:eng_x_preferred":[
        "Kurmapally"
    ],
    "wof:name":"Kurmapally",
    "wof:placetype":"neighbourhood",
    "wof:population":357
},
  "geometry": {"coordinates":[78.390642,18.023251],"type":"Point"}
}