{
  "type": "Feature",
  "properties": {
    "iso:country":"IN",
    "ks:ks_name":"Chellantheru",
    "ks:ks_pop":310,
    "ks:ks_type":"HABITATION",
    "name:eng_x_preferred":[
        "Chellantheru"
    ],
    "wof:name":"Chellantheru",
    "wof:placetype":"locality",
    "wof:population":310
},
  "geometry": {"coordinates":[77.879834,11.672855],"type":"Point"}
}