{
  "type": "Feature",
  "properties": {
    "iso:country":"IN",
    "ks:ks_name":"Patanpur",
    "ks:ks_pop":619,
    "ks:ks_type":"VILLAGE",
    "name:eng_x_preferred":[
        "Patanpur"
    ],
    "wof:name":"Patanpur",
    "wof:placetype":"locality",
    "wof:population":619
},
  "geometry": {"coordinates":[87.009033,24.028095],"type":"Point"}
}