{
  "type": "Feature",
  "properties": {
    "gn:admin1_code":"12.0",
    "gn:admin2_code":"021",
    "gn:asciiname":"Chat",
    "gn:country_code":"IN",
    "gn:dem":495,
    "gn:feature_class":"P",
    "gn:feature_code":"PPL",
    "gn:name":"Chat",
    "gn:population":0,
    "gn:timezone":"Asia/Kolkata",
    "iso:country":"IN",
    "name:ceb_x_preferred":[
        "Chat"
    ],
    "name:deu_x_preferred":[
        "Chat"
    ],
    "name:fra_x_preferred":[
        "Chat"
    ],
    "name:nld_x_preferred":[
        "Chatten"
    ],
    "name:oci_x_preferred":[
        "Chat"
    ],
    "name:rus_x_preferred":[
        "\u0427\u0430\u0442"
    ],
    "name:slk_x_preferred":[
        "Chat"
    ],
    "name:swe_x_preferred":[
        "Chat"
    ],
    "name:ukr_x_preferred":[
        "\u0427\u0430\u0442"
    ],
    "wof:name":"Chat",
    "wof:placetype":"locality"
},
  "geometry": {"coordinates":[74.98085999999998,32.6927],"type":"Point"}
}