{
  "type": "Feature",
  "properties": {
    "iso:country":"IN",
    "ks:ks_name":"Cheekalavaripalle",
    "ks:ks_pop":182,
    "ks:ks_type":"HABITATION",
    "ks:ks_uagg_main":0,
    "name:eng_x_preferred":[
        "Cheekalavaripalle"
    ],
    "wof:name":"Cheekalavaripalle",
    "wof:placetype":"neighbourhood",
    "wof:population":182
},
  "geometry": {"coordinates":[78.857322,13.454275],"type":"Point"}
}