{
  "type": "Feature",
  "properties": {
    "iso:country":"IN",
    "ks:ks_name":"Peethapura",
    "ks:ks_pop":938,
    "ks:ks_type":"HABITATION",
    "name:eng_x_preferred":[
        "Peethapura"
    ],
    "wof:name":"Peethapura",
    "wof:placetype":"locality",
    "wof:population":938
},
  "geometry": {"coordinates":[72.214626,24.688637],"type":"Point"}
}