{
  "type": "Feature",
  "properties": {
    "iso:country":"IN",
    "ks:ks_name":"Nagla Thakuri",
    "ks:ks_pop":350,
    "ks:ks_type":"HABITATION",
    "ks:ks_uagg_main":0,
    "name:eng_x_preferred":[
        "Nagla Thakuri"
    ],
    "wof:name":"Nagla Thakuri",
    "wof:placetype":"neighbourhood",
    "wof:population":350
},
  "geometry": {"coordinates":[79.12639799999999,26.745672],"type":"Point"}
}