{
  "type": "Feature",
  "properties": {
    "iso:country":"IN",
    "ks:ks_name":"Bishunitikar",
    "ks:ks_pop":1057,
    "ks:ks_type":"VILLAGE",
    "ks:ks_uagg_main":0,
    "name:eng_x_preferred":[
        "Bishunitikar"
    ],
    "wof:name":"Bishunitikar",
    "wof:placetype":"neighbourhood",
    "wof:population":1057
},
  "geometry": {"coordinates":[85.855699,24.594797],"type":"Point"}
}