{
  "type": "Feature",
  "properties": {
    "iso:country":"IN",
    "ks:ks_name":"Babanaik Tanda",
    "ks:ks_pop":208,
    "ks:ks_type":"HABITATION",
    "name:eng_x_preferred":[
        "Babanaik Tanda"
    ],
    "wof:name":"Babanaik Tanda",
    "wof:placetype":"locality",
    "wof:population":208
},
  "geometry": {"coordinates":[78.759333,19.232106],"type":"Point"}
}