{
  "type": "Feature",
  "properties": {
    "iso:country":"IN",
    "ks:ks_name":"Ganigar Hittla",
    "ks:ks_pop":33,
    "ks:ks_type":"HABITATION",
    "name:eng_x_preferred":[
        "Ganigar Hittla"
    ],
    "wof:name":"Ganigar Hittla",
    "wof:placetype":"locality",
    "wof:population":33
},
  "geometry": {"coordinates":[74.51150800000001,14.218493],"type":"Point"}
}