{
  "type": "Feature",
  "properties": {
    "iso:country":"IN",
    "ks:ks_name":"Kishori",
    "ks:ks_pop":825,
    "ks:ks_type":"VILLAGE",
    "name:eng_x_preferred":[
        "Kishori"
    ],
    "wof:name":"Kishori",
    "wof:placetype":"locality",
    "wof:population":825
},
  "geometry": {"coordinates":[82.36886199999999,23.449655],"type":"Point"}
}