{
  "type": "Feature",
  "properties": {
    "iso:country":"IN",
    "ks:ks_name":"Ghospur",
    "ks:ks_pop":58,
    "ks:ks_type":"VILLAGE",
    "name:eng_x_preferred":[
        "Ghospur"
    ],
    "wof:name":"Ghospur",
    "wof:placetype":"locality",
    "wof:population":58
},
  "geometry": {"coordinates":[87.28131999999999,25.028229],"type":"Point"}
}