{
  "type": "Feature",
  "properties": {
    "iso:country":"IN",
    "ks:ks_name":"Tandabai",
    "ks:ks_pop":660,
    "ks:ks_type":"VILLAGE",
    "name:eng_x_preferred":[
        "Tandabai"
    ],
    "wof:name":"Tandabai",
    "wof:placetype":"locality",
    "wof:population":660
},
  "geometry": {"coordinates":[81.534482,17.974475],"type":"Point"}
}