{
  "type": "Feature",
  "properties": {
    "iso:country":"IN",
    "ks:ks_name":"Thiar Devil II",
    "ks:ks_pop":141,
    "ks:ks_type":"VILLAGE",
    "name:eng_x_preferred":[
        "Thiar Devil II"
    ],
    "wof:name":"Thiar Devil II",
    "wof:placetype":"locality",
    "wof:population":141
},
  "geometry": {"coordinates":[86.310929,20.782538],"type":"Point"}
}