{
  "type": "Feature",
  "properties": {
    "iso:country":"IN",
    "ks:ks_name":"Bajethhalli",
    "ks:ks_pop":30,
    "ks:ks_type":"HABITATION",
    "name:eng_x_preferred":[
        "Bajethhalli"
    ],
    "wof:name":"Bajethhalli",
    "wof:placetype":"locality",
    "wof:population":30
},
  "geometry": {"coordinates":[75.26615700000001,12.914423],"type":"Point"}
}