{
  "type": "Feature",
  "properties": {
    "iso:country":"IN",
    "ks:ks_name":"Chota Mahauwa",
    "ks:ks_pop":365,
    "ks:ks_type":"HABITATION",
    "name:eng_x_preferred":[
        "Chota Mahauwa"
    ],
    "wof:name":"Chota Mahauwa",
    "wof:placetype":"locality",
    "wof:population":365
},
  "geometry": {"coordinates":[82.83022200000001,27.273513],"type":"Point"}
}