{
  "type": "Feature",
  "properties": {
    "iso:country":"IN",
    "ks:ks_name":"Marberya",
    "ks:ks_pop":2935,
    "ks:ks_type":"VILLAGE",
    "name:eng_x_preferred":[
        "Marberya"
    ],
    "wof:name":"Marberya",
    "wof:placetype":"locality",
    "wof:population":2935
},
  "geometry": {"coordinates":[87.884339,22.473073],"type":"Point"}
}