{
  "type": "Feature",
  "properties": {
    "gn:admin1_code":"16.0",
    "gn:admin2_code":"503.0",
    "gn:asciiname":"Bhatkuli",
    "gn:country_code":"IN",
    "gn:dem":264,
    "gn:feature_class":"P",
    "gn:feature_code":"PPL",
    "gn:name":"Bh\u0101tkuli",
    "gn:population":0,
    "gn:timezone":"Asia/Kolkata",
    "iso:country":"IN",
    "name:mar_x_preferred":[
        "\u092d\u093e\u0924\u0915\u0941\u0932\u0940"
    ],
    "wof:name":"Bhatkuli",
    "wof:placetype":"locality"
},
  "geometry": {"coordinates":[78.23174,20.69385],"type":"Point"}
}