{
  "type": "Feature",
  "properties": {
    "iso:country":"IN",
    "ks:ks_name":"Sodigadde",
    "ks:ks_pop":33,
    "ks:ks_type":"HABITATION",
    "name:eng_x_preferred":[
        "Sodigadde"
    ],
    "wof:name":"Sodigadde",
    "wof:placetype":"locality",
    "wof:population":33
},
  "geometry": {"coordinates":[74.400751,14.524343],"type":"Point"}
}