{
  "type": "Feature",
  "properties": {
    "iso:country":"IN",
    "ks:ks_name":"Gaur",
    "ks:ks_pop":546,
    "ks:ks_type":"HABITATION",
    "name:eng_x_preferred":[
        "Gaur"
    ],
    "wof:name":"Gaur",
    "wof:placetype":"locality",
    "wof:population":546
},
  "geometry": {"coordinates":[81.12136099999999,27.722474],"type":"Point"}
}