{
  "type": "Feature",
  "properties": {
    "iso:country":"IN",
    "ks:ks_name":"Koskatti",
    "ks:ks_pop":439,
    "ks:ks_type":"HABITATION",
    "name:eng_x_preferred":[
        "Koskatti"
    ],
    "wof:name":"Koskatti",
    "wof:placetype":"locality",
    "wof:population":439
},
  "geometry": {"coordinates":[82.508486,22.654666],"type":"Point"}
}