{
  "type": "Feature",
  "properties": {
    "iso:country":"IN",
    "ks:ks_name":"Mirzapur",
    "ks:ks_pop":1280,
    "ks:ks_type":"VILLAGE",
    "ks:ks_uagg_main":0,
    "name:eng_x_preferred":[
        "Mirzapur"
    ],
    "wof:name":"Mirzapur",
    "wof:placetype":"locality",
    "wof:population":1280
},
  "geometry": {"coordinates":[85.918881,26.085655],"type":"Point"}
}