{
  "type": "Feature",
  "properties": {
    "gn:admin1_code":"21.0",
    "gn:admin2_code":"386",
    "gn:asciiname":"Chandaka",
    "gn:country_code":"IN",
    "gn:dem":41,
    "gn:feature_class":"P",
    "gn:feature_code":"PPL",
    "gn:name":"Chandaka",
    "gn:population":0,
    "gn:timezone":"Asia/Kolkata",
    "iso:country":"IN",
    "wof:name":"Chandaka",
    "wof:placetype":"neighbourhood"
},
  "geometry": {"coordinates":[85.76667,20.36667],"type":"Point"}
}