{
  "type": "Feature",
  "properties": {
    "iso:country":"IN",
    "ks:ks_name":"Nattikulam",
    "ks:ks_pop":520,
    "ks:ks_type":"HABITATION",
    "name:eng_x_preferred":[
        "Nattikulam"
    ],
    "wof:name":"Nattikulam",
    "wof:placetype":"locality",
    "wof:population":520
},
  "geometry": {"coordinates":[79.50237,10.631727],"type":"Point"}
}