{
  "type": "Feature",
  "properties": {
    "iso:country":"IN",
    "ks:ks_name":"Vekta",
    "ks:ks_pop":1427,
    "ks:ks_type":"VILLAGE",
    "name:eng_x_preferred":[
        "Vekta"
    ],
    "wof:name":"Vekta",
    "wof:placetype":"locality",
    "wof:population":1427
},
  "geometry": {"coordinates":[86.924755,20.734456],"type":"Point"}
}