{
  "type": "Feature",
  "properties": {
    "iso:country":"IN",
    "ks:ks_name":"Sindhiring",
    "ks:ks_pop":41,
    "ks:ks_type":"HABITATION",
    "name:eng_x_preferred":[
        "Sindhiring"
    ],
    "wof:name":"Sindhiring",
    "wof:placetype":"locality",
    "wof:population":41
},
  "geometry": {"coordinates":[83.96408099999999,19.057385],"type":"Point"}
}