{
  "type": "Feature",
  "properties": {
    "iso:country":"IN",
    "ks:ks_name":"Baghipakar",
    "ks:ks_type":"VILLAGE",
    "ks:ks_uagg_main":0,
    "name:eng_x_preferred":[
        "Baghipakar"
    ],
    "wof:name":"Baghipakar",
    "wof:placetype":"neighbourhood"
},
  "geometry": {"coordinates":[84.56535700000001,25.628372],"type":"Point"}
}