{
  "type": "Feature",
  "properties": {
    "iso:country":"IN",
    "ks:ks_name":"Pachdeul",
    "ks:ks_pop":59,
    "ks:ks_type":"HABITATION",
    "name:eng_x_preferred":[
        "Pachdeul"
    ],
    "wof:name":"Pachdeul",
    "wof:placetype":"locality",
    "wof:population":59
},
  "geometry": {"coordinates":[76.648425,20.373793],"type":"Point"}
}