{
  "type": "Feature",
  "properties": {
    "iso:country":"IN",
    "ks:ks_alt_nam":"Muhammadpur Niz\u0101mat",
    "ks:ks_alt_nam_2":"Muhammadpur Nizamat",
    "ks:ks_name":"Mahammadpur Nizamat",
    "ks:ks_pop":0,
    "ks:ks_type":"VILLAGE",
    "name:eng_x_preferred":[
        "Mahammadpur Nizamat"
    ],
    "name:eng_x_variant":[
        "Muhammadpur Niz\u0101mat",
        "Muhammadpur Nizamat"
    ],
    "wof:name":"Mahammadpur Nizamat",
    "wof:placetype":"locality",
    "wof:population":0
},
  "geometry": {"coordinates":[84.88608600000001,26.22803],"type":"Point"}
}