{
  "type": "Feature",
  "properties": {
    "iso:country":"IN",
    "ks:ks_name":"Dammadihatti",
    "ks:ks_pop":85,
    "ks:ks_type":"HABITATION",
    "name:eng_x_preferred":[
        "Dammadihatti"
    ],
    "wof:name":"Dammadihatti",
    "wof:placetype":"locality",
    "wof:population":85
},
  "geometry": {"coordinates":[76.556676,13.616101],"type":"Point"}
}