{
  "type": "Feature",
  "properties": {
    "gn:admin1_code":"12.0",
    "gn:admin2_code":"001",
    "gn:asciiname":"Kahawut",
    "gn:country_code":"IN",
    "gn:dem":1603,
    "gn:feature_class":"P",
    "gn:feature_code":"PPL",
    "gn:name":"K\u0101h\u0101wut",
    "gn:population":0,
    "gn:timezone":"Asia/Kolkata",
    "iso:country":"IN",
    "wof:name":"Kahawut",
    "wof:placetype":"locality"
},
  "geometry": {"coordinates":[74.27325999999999,34.49232],"type":"Point"}
}