{
  "type": "Feature",
  "properties": {
    "gn:admin1_code":"19.0",
    "gn:admin2_code":"562.0",
    "gn:asciiname":"Mangalgatti",
    "gn:country_code":"IN",
    "gn:dem":690,
    "gn:feature_class":"P",
    "gn:feature_code":"PPL",
    "gn:name":"Mangalgatti",
    "gn:population":0,
    "gn:timezone":"Asia/Kolkata",
    "iso:country":"IN",
    "wof:name":"Mangalgatti",
    "wof:placetype":"locality"
},
  "geometry": {"coordinates":[74.96354000000002,15.54403],"type":"Point"}
}