{
  "type": "Feature",
  "properties": {
    "iso:country":"IN",
    "ks:ks_name":"Karandlaje",
    "ks:ks_pop":80,
    "ks:ks_type":"HABITATION",
    "name:eng_x_preferred":[
        "Karandlaje"
    ],
    "wof:name":"Karandlaje",
    "wof:placetype":"locality",
    "wof:population":80
},
  "geometry": {"coordinates":[75.375232,12.7331],"type":"Point"}
}