{
  "type": "Feature",
  "properties": {
    "iso:country":"IN",
    "ks:ks_name":"Goena",
    "ks:ks_pop":81,
    "ks:ks_type":"VILLAGE",
    "name:eng_x_preferred":[
        "Goena"
    ],
    "wof:name":"Goena",
    "wof:placetype":"locality",
    "wof:population":81
},
  "geometry": {"coordinates":[79.082137,19.285907],"type":"Point"}
}