{
  "type": "Feature",
  "properties": {
    "gn:admin1_code":"36",
    "gn:admin2_code":"200.0",
    "gn:asciiname":"Auradandi",
    "gn:country_code":"IN",
    "gn:dem":246,
    "gn:feature_class":"P",
    "gn:feature_code":"PPL",
    "gn:name":"Aur\u0101dandi",
    "gn:population":0,
    "gn:timezone":"Asia/Kolkata",
    "iso:country":"IN",
    "ks:ks_name":"Auradand",
    "ks:ks_pop":779,
    "ks:ks_type":"HABITATION",
    "name:eng_x_preferred":[
        "Auradand"
    ],
    "name:eng_x_variant":[
        "Auradandi"
    ],
    "wof:name":"Auradand",
    "wof:placetype":"locality",
    "wof:population":779
},
  "geometry": {"coordinates":[83.22283,24.333821],"type":"Point"}
}