{
  "type": "Feature",
  "properties": {
    "iso:country":"IN",
    "ks:ks_name":"Chamaran Ka Pura",
    "ks:ks_pop":147,
    "ks:ks_type":"HABITATION",
    "name:eng_x_preferred":[
        "Chamaran Ka Pura"
    ],
    "wof:name":"Chamaran Ka Pura",
    "wof:placetype":"locality",
    "wof:population":147
},
  "geometry": {"coordinates":[81.372069,25.472984],"type":"Point"}
}