{
  "type": "Feature",
  "properties": {
    "gn:admin1_code":"23.0",
    "gn:admin2_code":"43.0",
    "gn:asciiname":"Dulchike",
    "gn:country_code":"IN",
    "gn:dem":197,
    "gn:feature_class":"P",
    "gn:feature_code":"PPL",
    "gn:name":"Dulchike",
    "gn:population":0,
    "gn:timezone":"Asia/Kolkata",
    "iso:country":"IN",
    "name:und_x_variant":[
        "Akke"
    ],
    "wof:name":"Dulchike",
    "wof:placetype":"locality"
},
  "geometry": {"coordinates":[74.60364,30.99382],"type":"Point"}
}