{
  "type": "Feature",
  "properties": {
    "iso:country":"IN",
    "ks:ks_name":"Babarpada",
    "ks:ks_pop":168,
    "ks:ks_type":"HABITATION",
    "name:eng_x_preferred":[
        "Babarpada"
    ],
    "wof:name":"Babarpada",
    "wof:placetype":"locality",
    "wof:population":168
},
  "geometry": {"coordinates":[73.15351200000001,19.569136],"type":"Point"}
}