{
  "type": "Feature",
  "properties": {
    "gn:admin1_code":"36",
    "gn:admin2_code":"172.0",
    "gn:asciiname":"Tihar",
    "gn:country_code":"IN",
    "gn:dem":105,
    "gn:feature_class":"P",
    "gn:feature_code":"PPL",
    "gn:name":"Tih\u0101r",
    "gn:population":0,
    "gn:timezone":"Asia/Kolkata",
    "iso:country":"IN",
    "ks:ks_alt_nam":"Tih\u0101r",
    "ks:ks_name":"Tihar",
    "ks:ks_pop":1438,
    "ks:ks_type":"VILLAGE",
    "name:eng_x_preferred":[
        "Tihar"
    ],
    "name:eng_x_variant":[
        "Tih\u0101r"
    ],
    "name:nld_x_preferred":[
        "Tihar"
    ],
    "wof:name":"Tihar",
    "wof:placetype":"locality",
    "wof:population":1438
},
  "geometry": {"coordinates":[81.039663,25.609632],"type":"Point"}
}