{
  "type": "Feature",
  "properties": {
    "iso:country":"IN",
    "ks:ks_name":"Chak Sanga Ka Bas",
    "ks:ks_pop":31,
    "ks:ks_type":"HABITATION",
    "name:eng_x_preferred":[
        "Chak Sanga Ka Bas"
    ],
    "wof:name":"Chak Sanga Ka Bas",
    "wof:placetype":"locality",
    "wof:population":31
},
  "geometry": {"coordinates":[75.936161,27.444106],"type":"Point"}
}