{
  "type": "Feature",
  "properties": {
    "iso:country":"IN",
    "ks:ks_alt_nam":"Lachma tanda",
    "ks:ks_name":"Lachma Tanda",
    "ks:ks_pop":136,
    "ks:ks_type":"HABITATION",
    "name:eng_x_preferred":[
        "Lachma Tanda"
    ],
    "wof:name":"Lachma Tanda",
    "wof:placetype":"locality",
    "wof:population":136
},
  "geometry": {"coordinates":[77.59134400000001,18.150343],"type":"Point"}
}