{
  "type": "Feature",
  "properties": {
    "gn:admin1_code":"11",
    "gn:admin2_code":"23.0",
    "gn:asciiname":"Sadiot",
    "gn:country_code":"IN",
    "gn:dem":866,
    "gn:feature_class":"P",
    "gn:feature_code":"PPL",
    "gn:name":"Sadiot",
    "gn:population":0,
    "gn:timezone":"Asia/Kolkata",
    "iso:country":"IN",
    "wof:name":"Sadiot",
    "wof:placetype":"locality"
},
  "geometry": {"coordinates":[76.00766,32.38454],"type":"Point"}
}