{
  "type": "Feature",
  "properties": {
    "iso:country":"IN",
    "ks:ks_name":"Balsernga",
    "ks:ks_pop":238,
    "ks:ks_type":"HABITATION",
    "name:eng_x_preferred":[
        "Balsernga"
    ],
    "wof:name":"Balsernga",
    "wof:placetype":"locality",
    "wof:population":238
},
  "geometry": {"coordinates":[83.10221199999999,22.642239],"type":"Point"}
}