{
  "type": "Feature",
  "properties": {
    "iso:country":"IN",
    "ks:ks_alt_nam":"GURILING DONGAR ROAD",
    "ks:ks_name":"Guriling Dongar Road",
    "ks:ks_pop":50,
    "ks:ks_type":"HABITATION",
    "name:eng_x_preferred":[
        "Guriling Dongar Road"
    ],
    "wof:name":"Guriling Dongar Road",
    "wof:placetype":"locality",
    "wof:population":50
},
  "geometry": {"coordinates":[74.84028000000001,16.918773],"type":"Point"}
}