{
  "type": "Feature",
  "properties": {
    "iso:country":"IN",
    "ks:ks_name":"Budhanhera",
    "ks:ks_pop":35,
    "ks:ks_type":"VILLAGE",
    "ks:ks_uagg_main":0,
    "name:eng_x_preferred":[
        "Budhanhera"
    ],
    "wof:name":"Budhanhera",
    "wof:placetype":"neighbourhood",
    "wof:population":35
},
  "geometry": {"coordinates":[76.47374000000001,24.872946],"type":"Point"}
}