{
  "type": "Feature",
  "properties": {
    "iso:country":"IN",
    "ks:ks_name":"Mewpur Barchauli",
    "ks:ks_pop":381,
    "ks:ks_type":"VILLAGE",
    "ks:ks_uagg_main":0,
    "name:eng_x_preferred":[
        "Mewpur Barchauli"
    ],
    "wof:name":"Mewpur Barchauli",
    "wof:placetype":"neighbourhood",
    "wof:population":381
},
  "geometry": {"coordinates":[82.458208,26.061775],"type":"Point"}
}