{
  "type": "Feature",
  "properties": {
    "iso:country":"IN",
    "ks:ks_name":"Thagachaguppe",
    "ks:ks_pop":1000,
    "ks:ks_type":"VILLAGE",
    "ks:ks_uagg_main":0,
    "name:eng_x_preferred":[
        "Thagachaguppe"
    ],
    "wof:name":"Thagachaguppe",
    "wof:placetype":"locality",
    "wof:population":1000
},
  "geometry": {"coordinates":[77.452173,12.868956],"type":"Point"}
}