{
  "type": "Feature",
  "properties": {
    "gn:admin1_code":"16.0",
    "gn:admin2_code":"503.0",
    "gn:asciiname":"Bhili",
    "gn:country_code":"IN",
    "gn:dem":281,
    "gn:feature_class":"P",
    "gn:feature_code":"PPL",
    "gn:name":"Bhili",
    "gn:population":0,
    "gn:timezone":"Asia/Kolkata",
    "iso:country":"IN",
    "wof:name":"Bhili",
    "wof:placetype":"locality"
},
  "geometry": {"coordinates":[78.17183,20.7563],"type":"Point"}
}