{
  "type": "Feature",
  "properties": {
    "iso:country":"IN",
    "ks:ks_alt_nam":"NONIYA TOLA",
    "ks:ks_name":"Noniya Tola",
    "ks:ks_pop":438,
    "ks:ks_type":"HABITATION",
    "name:eng_x_preferred":[
        "Noniya Tola"
    ],
    "wof:name":"Noniya Tola",
    "wof:placetype":"locality",
    "wof:population":438
},
  "geometry": {"coordinates":[84.957247,25.946157],"type":"Point"}
}