{
  "type": "Feature",
  "properties": {
    "iso:country":"IN",
    "ks:ks_alt_nam":"MALAPALLI",
    "ks:ks_name":"Malapalli",
    "ks:ks_pop":268,
    "ks:ks_type":"HABITATION",
    "ks:ks_uagg_main":0,
    "name:eng_x_preferred":[
        "Malapalli"
    ],
    "wof:name":"Malapalli",
    "wof:placetype":"neighbourhood",
    "wof:population":268
},
  "geometry": {"coordinates":[80.755144,16.009523],"type":"Point"}
}