{
  "type": "Feature",
  "properties": {
    "gn:admin1_code":"34.0",
    "gn:admin2_code":"213.0",
    "gn:asciiname":"Kantahi",
    "gn:country_code":"IN",
    "gn:dem":47,
    "gn:feature_class":"P",
    "gn:feature_code":"PPL",
    "gn:name":"Kant\u0101hi",
    "gn:population":0,
    "gn:timezone":"Asia/Kolkata",
    "iso:country":"IN",
    "wof:name":"Kantahi",
    "wof:placetype":"neighbourhood"
},
  "geometry": {"coordinates":[86.92543999999999,25.80952],"type":"Point"}
}