{
  "type": "Feature",
  "properties": {
    "gn:admin1_code":"16.0",
    "gn:admin2_code":"499.0",
    "gn:asciiname":"Pimpri Hat",
    "gn:country_code":"IN",
    "gn:dem":286,
    "gn:feature_class":"P",
    "gn:feature_code":"PPL",
    "gn:name":"Pimpri Hat",
    "gn:population":0,
    "gn:timezone":"Asia/Kolkata",
    "iso:country":"IN",
    "ks:ks_name":"Pimprihat",
    "ks:ks_pop":2150,
    "ks:ks_type":"VILLAGE",
    "ks:ks_uagg_main":0,
    "name:eng_x_preferred":[
        "Pimprihat"
    ],
    "wof:name":"Pimprihat",
    "wof:placetype":"neighbourhood",
    "wof:population":2150
},
  "geometry": {"coordinates":[75.10900100000001,20.645746],"type":"Point"}
}