{
  "type": "Feature",
  "properties": {
    "iso:country":"IN",
    "ks:ks_alt_nam":"M.Arehalla",
    "ks:ks_name":"M.arehalla",
    "ks:ks_pop":82,
    "ks:ks_type":"HABITATION",
    "name:eng_x_preferred":[
        "M.arehalla"
    ],
    "wof:name":"M.arehalla",
    "wof:placetype":"locality",
    "wof:population":82
},
  "geometry": {"coordinates":[74.887474,14.549305],"type":"Point"}
}