{
  "type": "Feature",
  "properties": {
    "iso:country":"IN",
    "ks:ks_name":"Abbettu",
    "ks:ks_pop":64,
    "ks:ks_type":"HABITATION",
    "name:eng_x_preferred":[
        "Abbettu"
    ],
    "wof:name":"Abbettu",
    "wof:placetype":"locality",
    "wof:population":64
},
  "geometry": {"coordinates":[74.79000000000001,13.22],"type":"Point"}
}