{
  "type": "Feature",
  "properties": {
    "iso:country":"IN",
    "ks:ks_name":"Kantiwa",
    "ks:ks_pop":294,
    "ks:ks_type":"HABITATION",
    "name:eng_x_preferred":[
        "Kantiwa"
    ],
    "wof:name":"Kantiwa",
    "wof:placetype":"locality",
    "wof:population":294
},
  "geometry": {"coordinates":[84.66656399999999,22.869978],"type":"Point"}
}