{
  "type": "Feature",
  "properties": {
    "gn:admin1_code":"16",
    "gn:admin2_code":"498.0",
    "gn:asciiname":"Sindkheda",
    "gn:country_code":"IN",
    "gn:dem":164,
    "gn:feature_class":"P",
    "gn:feature_code":"PPL",
    "gn:name":"Sindkheda",
    "gn:population":0,
    "gn:timezone":"Asia/Kolkata",
    "iso:country":"IN",
    "name:guj_x_preferred":[
        "\u0ab6\u0abf\u0a82\u0aa6\u0a96\u0ac7\u0aa1\u0abe"
    ],
    "name:hin_x_preferred":[
        "\u0936\u093f\u0902\u0926\u0916\u0947\u0921\u093c\u093e"
    ],
    "name:mar_x_preferred":[
        "\u0936\u093f\u0902\u0926\u0916\u0947\u0921\u093e"
    ],
    "name:und_x_variant":[
        "Sindkeda",
        "Sindkheda"
    ],
    "name:urd_x_preferred":[
        "\u0633\u0646\u062f\u06a9\u06be\u06cc\u0691\u0627"
    ],
    "wof:name":"Sindkheda",
    "wof:placetype":"locality"
},
  "geometry": {"coordinates":[74.7444,21.27101],"type":"Point"}
}