{
  "type": "Feature",
  "properties": {
    "gn:admin1_code":"16",
    "gn:admin2_code":"498.0",
    "gn:asciiname":"Sindkheda",
    "gn:country_code":"IN",
    "gn:dem":164,
    "gn:feature_class":"P",
    "gn:feature_code":"PPL",
    "gn:name":"Sindkheda",
    "gn:population":0,
    "gn:timezone":"Asia/Kolkata",
    "iso:country":"IN",
    "name:und_x_variant":[
        "Sindkeda",
        "Sindkheda"
    ],
    "wof:name":"Sindkheda",
    "wof:placetype":"locality"
},
  "geometry": {"coordinates":[74.7444,21.27101],"type":"Point"}
}