{
  "type": "Feature",
  "properties": {
    "gn:admin1_code":"12.0",
    "gn:admin2_code":"001",
    "gn:asciiname":"Khaipur",
    "gn:country_code":"IN",
    "gn:dem":1649,
    "gn:feature_class":"P",
    "gn:feature_code":"PPL",
    "gn:name":"Khaipur",
    "gn:population":0,
    "gn:timezone":"Asia/Kolkata",
    "iso:country":"IN",
    "wof:name":"Khaipur",
    "wof:placetype":"locality"
},
  "geometry": {"coordinates":[74.20999999999999,34.42177],"type":"Point"}
}