{
  "type": "Feature",
  "properties": {
    "gn:admin1_code":"38.0",
    "gn:admin2_code":"349",
    "gn:asciiname":"Gawan",
    "gn:country_code":"IN",
    "gn:dem":190,
    "gn:feature_class":"P",
    "gn:feature_code":"PPL",
    "gn:name":"G\u0101w\u0101n",
    "gn:population":0,
    "gn:timezone":"Asia/Kolkata",
    "iso:country":"IN",
    "name:bpy_x_preferred":[
        "\u0997\u09cc\u09af\u09bc\u09be\u09a8"
    ],
    "name:ceb_x_preferred":[
        "Gaw\u0101n"
    ],
    "name:ita_x_preferred":[
        "Gawan"
    ],
    "name:mlg_x_preferred":[
        "Gawan"
    ],
    "name:msa_x_preferred":[
        "Gawan"
    ],
    "name:new_x_preferred":[
        "\u0917\u0935\u0928"
    ],
    "name:nld_x_preferred":[
        "Gawan"
    ],
    "name:pol_x_preferred":[
        "Gawan"
    ],
    "name:por_x_preferred":[
        "Gawan"
    ],
    "name:swe_x_preferred":[
        "Gaw\u0101n"
    ],
    "name:urd_x_preferred":[
        "\u06af\u0648\u0627\u0646"
    ],
    "name:vie_x_preferred":[
        "Gawan"
    ],
    "wof:name":"Gawan",
    "wof:placetype":"locality"
},
  "geometry": {"coordinates":[85.91636,24.61792],"type":"Point"}
}