{
  "type": "Feature",
  "properties": {
    "gn:admin1_code":"2",
    "gn:admin2_code":"544.0",
    "gn:asciiname":"Tontaguda",
    "gn:country_code":"IN",
    "gn:dem":975,
    "gn:feature_class":"P",
    "gn:feature_code":"PPL",
    "gn:name":"Tontag\u016bda",
    "gn:population":0,
    "gn:timezone":"Asia/Kolkata",
    "iso:country":"IN",
    "wof:name":"Tontaguda",
    "wof:placetype":"locality"
},
  "geometry": {"coordinates":[82.94795999999999,18.26536],"type":"Point"}
}