{
  "type": "Feature",
  "properties": {
    "gn:admin1_code":"11.0",
    "gn:admin2_code":"32.0",
    "gn:asciiname":"Bagna",
    "gn:country_code":"IN",
    "gn:dem":1388,
    "gn:feature_class":"P",
    "gn:feature_code":"PPL",
    "gn:name":"Bagna",
    "gn:population":0,
    "gn:timezone":"Asia/Kolkata",
    "iso:country":"IN",
    "name:ceb_x_preferred":[
        "Bagna"
    ],
    "name:pol_x_preferred":[
        "Bagna"
    ],
    "name:swe_x_preferred":[
        "Bagna"
    ],
    "name:ukr_x_preferred":[
        "\u0411\u0430\u0491\u043d\u0430"
    ],
    "wof:name":"Bagna",
    "wof:placetype":"locality"
},
  "geometry": {"coordinates":[77.73260000000001,30.70697],"type":"Point"}
}