{
  "type": "Feature",
  "properties": {
    "iso:country":"IN",
    "ks:ks_name":"Tanrtoli",
    "ks:ks_pop":105,
    "ks:ks_type":"HABITATION",
    "name:eng_x_preferred":[
        "Tanrtoli"
    ],
    "wof:name":"Tanrtoli",
    "wof:placetype":"locality",
    "wof:population":105
},
  "geometry": {"coordinates":[84.32680999999999,23.42074],"type":"Point"}
}