{
  "type": "Feature",
  "properties": {
    "iso:country":"IN",
    "ks:ks_name":"Keela Kanjankollai",
    "ks:ks_pop":696,
    "ks:ks_type":"HABITATION",
    "name:eng_x_preferred":[
        "Keela Kanjankollai"
    ],
    "wof:name":"Keela Kanjankollai",
    "wof:placetype":"locality",
    "wof:population":696
},
  "geometry": {"coordinates":[79.478241,11.173357],"type":"Point"}
}