{
  "type": "Feature",
  "properties": {
    "gn:admin1_code":"36",
    "gn:admin2_code":"166.0",
    "gn:asciiname":"Mau Ranipur",
    "gn:country_code":"IN",
    "gn:dem":208,
    "gn:feature_class":"P",
    "gn:feature_code":"PPL",
    "gn:name":"Mau R\u0101n\u012bpur",
    "gn:population":0,
    "gn:timezone":"Asia/Kolkata",
    "iso:country":"IN",
    "ks:ks_alt_nam":"Mau R\u0101n\u012bpur",
    "ks:ks_name":"Mau Ranipur",
    "ks:ks_type":"VILLAGE",
    "ks:ks_uagg_main":0,
    "name:eng_x_preferred":[
        "Mau Ranipur"
    ],
    "name:eng_x_variant":[
        "Mau R\u0101n\u012bpur"
    ],
    "wof:name":"Mau Ranipur",
    "wof:placetype":"neighbourhood"
},
  "geometry": {"coordinates":[79.13276,25.244149],"type":"Point"}
}