{
  "type": "Feature",
  "properties": {
    "gn:admin1_code":"12.0",
    "gn:admin2_code":"010",
    "gn:asciiname":"Dodarhama",
    "gn:country_code":"IN",
    "gn:dem":1585,
    "gn:feature_class":"P",
    "gn:feature_code":"PPL",
    "gn:name":"Dodarh\u0101ma",
    "gn:population":0,
    "gn:timezone":"Asia/Kolkata",
    "iso:country":"IN",
    "name:und_x_variant":[
        "Dodarh\u0101ma",
        "G\u0101ndarbal"
    ],
    "wof:name":"Dodarhama",
    "wof:placetype":"locality"
},
  "geometry": {"coordinates":[74.77106999999999,34.21141],"type":"Point"}
}