{
  "type": "Feature",
  "properties": {
    "iso:country":"IN",
    "ks:ks_name":"Bakain",
    "ks:ks_pop":272,
    "ks:ks_type":"VILLAGE",
    "name:eng_x_preferred":[
        "Bakain"
    ],
    "wof:name":"Bakain",
    "wof:placetype":"locality",
    "wof:population":272
},
  "geometry": {"coordinates":[84.77549500000001,24.299416],"type":"Point"}
}