{
  "type": "Feature",
  "properties": {
    "gn:admin1_code":"9.0",
    "gn:admin2_code":"477",
    "gn:asciiname":"Gurgat",
    "gn:country_code":"IN",
    "gn:dem":27,
    "gn:feature_class":"P",
    "gn:feature_code":"PPL",
    "gn:name":"Gurgat",
    "gn:population":0,
    "gn:timezone":"Asia/Kolkata",
    "iso:country":"IN",
    "wof:name":"Gurgat",
    "wof:placetype":"neighbourhood"
},
  "geometry": {"coordinates":[69.19247,22.19719],"type":"Point"}
}