{
  "type": "Feature",
  "properties": {
    "gn:admin1_code":"36",
    "gn:admin2_code":"173.0",
    "gn:asciiname":"Mirpur",
    "gn:country_code":"IN",
    "gn:dem":108,
    "gn:feature_class":"P",
    "gn:feature_code":"PPL",
    "gn:name":"M\u012brpur",
    "gn:population":0,
    "gn:timezone":"Asia/Kolkata",
    "iso:country":"IN",
    "name:ben_x_preferred":[
        "\u09ae\u09bf\u09b0\u09aa\u09c1\u09b0"
    ],
    "name:ita_x_preferred":[
        "Mirpur"
    ],
    "name:sco_x_preferred":[
        "Mirpur"
    ],
    "name:snd_x_preferred":[
        "\u0645\u064a\u0631\u067e\u0648\u0631"
    ],
    "name:und_x_variant":[
        "M\u012brpur",
        "Banohi"
    ],
    "wof:name":"Mirpur",
    "wof:placetype":"neighbourhood"
},
  "geometry": {"coordinates":[81.57949000000001,25.71796],"type":"Point"}
}