{
  "type": "Feature",
  "properties": {
    "gn:admin1_code":"36",
    "gn:admin2_code":"177.0",
    "gn:asciiname":"Kaurila",
    "gn:country_code":"IN",
    "gn:dem":99,
    "gn:feature_class":"P",
    "gn:feature_code":"PPL",
    "gn:name":"Kaur\u012bla",
    "gn:population":0,
    "gn:timezone":"Asia/Kolkata",
    "iso:country":"IN",
    "wof:name":"Kaurila",
    "wof:placetype":"locality"
},
  "geometry": {"coordinates":[82.39024999999999,26.63099],"type":"Point"}
}