{
  "type": "Feature",
  "properties": {
    "iso:country":"IN",
    "ks:ks_name":"Tamsade",
    "ks:ks_pop":67,
    "ks:ks_type":"HABITATION",
    "name:eng_x_preferred":[
        "Tamsade"
    ],
    "wof:name":"Tamsade",
    "wof:placetype":"locality",
    "wof:population":67
},
  "geometry": {"coordinates":[73.4636,17.877929],"type":"Point"}
}