{
  "type": "Feature",
  "properties": {
    "iso:country":"IN",
    "ks:ks_name":"Pailachhanpur",
    "ks:ks_pop":923,
    "ks:ks_type":"VILLAGE",
    "name:eng_x_preferred":[
        "Pailachhanpur"
    ],
    "wof:name":"Pailachhanpur",
    "wof:placetype":"locality",
    "wof:population":923
},
  "geometry": {"coordinates":[87.719303,21.721304],"type":"Point"}
}