{
  "type": "Feature",
  "properties": {
    "iso:country":"IN",
    "ks:ks_name":"Chak Dhean",
    "ks:ks_pop":185,
    "ks:ks_type":"VILLAGE",
    "name:eng_x_preferred":[
        "Chak Dhean"
    ],
    "wof:name":"Chak Dhean",
    "wof:placetype":"locality",
    "wof:population":185
},
  "geometry": {"coordinates":[85.663859,25.813794],"type":"Point"}
}