{
  "type": "Feature",
  "properties": {
    "iso:country":"IN",
    "ks:ks_name":"Dansara",
    "ks:ks_pop":359,
    "ks:ks_type":"VILLAGE",
    "name:eng_x_preferred":[
        "Dansara"
    ],
    "wof:name":"Dansara",
    "wof:placetype":"locality",
    "wof:population":359
},
  "geometry": {"coordinates":[78.585882,30.130597],"type":"Point"}
}