{
  "type": "Feature",
  "properties": {
    "iso:country":"IN",
    "ks:ks_name":"Suatala",
    "ks:ks_pop":49,
    "ks:ks_type":"VILLAGE",
    "name:eng_x_preferred":[
        "Suatala"
    ],
    "wof:name":"Suatala",
    "wof:placetype":"locality",
    "wof:population":49
},
  "geometry": {"coordinates":[78.788414,23.515726],"type":"Point"}
}