{
  "type": "Feature",
  "properties": {
    "gn:admin1_code":"34.0",
    "gn:admin2_code":"209.0",
    "gn:asciiname":"Gerki",
    "gn:country_code":"IN",
    "gn:dem":53,
    "gn:feature_class":"P",
    "gn:feature_code":"PPL",
    "gn:name":"Gerki",
    "gn:population":0,
    "gn:timezone":"Asia/Kolkata",
    "iso:country":"IN",
    "ks:ks_name":"Gerki",
    "ks:ks_pop":1565,
    "ks:ks_type":"VILLAGE",
    "ks:ks_uagg_main":0,
    "name:eng_x_preferred":[
        "Gerki"
    ],
    "wof:name":"Gerki",
    "wof:placetype":"neighbourhood",
    "wof:population":1565
},
  "geometry": {"coordinates":[87.552463,26.111738],"type":"Point"}
}