{
  "type": "Feature",
  "properties": {
    "iso:country":"IN",
    "ks:ks_name":"Arimeni Kandriga",
    "ks:ks_pop":186,
    "ks:ks_type":"HABITATION",
    "name:eng_x_preferred":[
        "Arimeni Kandriga"
    ],
    "wof:name":"Arimeni Kandriga",
    "wof:placetype":"locality",
    "wof:population":186
},
  "geometry": {"coordinates":[79.908146,13.748924],"type":"Point"}
}