{
  "type": "Feature",
  "properties": {
    "iso:country":"IN",
    "ks:ks_name":"Tiwaran",
    "ks:ks_pop":131,
    "ks:ks_type":"HABITATION",
    "ks:ks_uagg_main":0,
    "name:eng_x_preferred":[
        "Tiwaran"
    ],
    "wof:name":"Tiwaran",
    "wof:placetype":"neighbourhood",
    "wof:population":131
},
  "geometry": {"coordinates":[82.033197,25.91038],"type":"Point"}
}