{
  "type": "Feature",
  "properties": {
    "iso:country":"IN",
    "ks:ks_alt_nam":"MALAH TOLA",
    "ks:ks_name":"Malah Tola",
    "ks:ks_pop":400,
    "ks:ks_type":"HABITATION",
    "name:eng_x_preferred":[
        "Malah Tola"
    ],
    "wof:name":"Malah Tola",
    "wof:placetype":"locality",
    "wof:population":400
},
  "geometry": {"coordinates":[84.92688200000001,26.112155],"type":"Point"}
}