{
  "type": "Feature",
  "properties": {
    "gn:admin1_code":"37",
    "gn:admin2_code":"404.0",
    "gn:asciiname":"Lahrapara",
    "gn:country_code":"IN",
    "gn:dem":324,
    "gn:feature_class":"P",
    "gn:feature_code":"PPL",
    "gn:name":"Lahr\u0101p\u0101ra",
    "gn:population":0,
    "gn:timezone":"Asia/Kolkata",
    "iso:country":"IN",
    "ks:ks_name":"Laharapara",
    "ks:ks_pop":1030,
    "ks:ks_type":"HABITATION",
    "name:eng_x_preferred":[
        "Laharapara"
    ],
    "name:eng_x_variant":[
        "Lahrapara"
    ],
    "wof:name":"Laharapara",
    "wof:placetype":"locality",
    "wof:population":1030
},
  "geometry": {"coordinates":[82.241383,22.407336],"type":"Point"}
}