{
  "type": "Feature",
  "properties": {
    "iso:country":"IN",
    "ks:ks_alt_nam":"Yadav tola",
    "ks:ks_name":"Yadav Tola",
    "ks:ks_pop":182,
    "ks:ks_type":"HABITATION",
    "name:eng_x_preferred":[
        "Yadav Tola"
    ],
    "wof:name":"Yadav Tola",
    "wof:placetype":"locality",
    "wof:population":182
},
  "geometry": {"coordinates":[85.95141599999999,24.548984],"type":"Point"}
}