{
  "type": "Feature",
  "properties": {
    "iso:country":"IN",
    "ks:ks_alt_nam":"PASCHIM TOLA",
    "ks:ks_name":"Paschim Tola",
    "ks:ks_pop":803,
    "ks:ks_type":"HABITATION",
    "name:eng_x_preferred":[
        "Paschim Tola"
    ],
    "wof:name":"Paschim Tola",
    "wof:placetype":"locality",
    "wof:population":803
},
  "geometry": {"coordinates":[83.952488,26.780917],"type":"Point"}
}