{
  "type": "Feature",
  "properties": {
    "iso:country":"IN",
    "ks:ks_name":"Raoda",
    "ks:ks_pop":233,
    "ks:ks_type":"VILLAGE",
    "name:eng_x_preferred":[
        "Raoda"
    ],
    "wof:name":"Raoda",
    "wof:placetype":"locality",
    "wof:population":233
},
  "geometry": {"coordinates":[74.611197,23.276957],"type":"Point"}
}