{
  "type": "Feature",
  "properties": {
    "iso:country":"IN",
    "ks:ks_name":"Seepura",
    "ks:ks_pop":7,
    "ks:ks_type":"VILLAGE",
    "name:eng_x_preferred":[
        "Seepura"
    ],
    "wof:name":"Seepura",
    "wof:placetype":"locality",
    "wof:population":7
},
  "geometry": {"coordinates":[79.066864,26.102441],"type":"Point"}
}