{
  "type": "Feature",
  "properties": {
    "iso:country":"IN",
    "ks:ks_name":"Churegaon",
    "ks:ks_pop":321,
    "ks:ks_type":"VILLAGE",
    "name:eng_x_preferred":[
        "Churegaon"
    ],
    "wof:name":"Churegaon",
    "wof:placetype":"locality",
    "wof:population":321
},
  "geometry": {"coordinates":[81.31905999999999,19.995067],"type":"Point"}
}