{
  "type": "Feature",
  "properties": {
    "gn:admin1_code":"12.0",
    "gn:admin2_code":"001",
    "gn:asciiname":"Bamhom",
    "gn:country_code":"IN",
    "gn:dem":1618,
    "gn:feature_class":"P",
    "gn:feature_code":"PPL",
    "gn:name":"Bamhom",
    "gn:population":0,
    "gn:timezone":"Asia/Kolkata",
    "iso:country":"IN",
    "name:eng_x_preferred":[
        "Bamhom"
    ],
    "wof:name":"Bamhom",
    "wof:placetype":"locality"
},
  "geometry": {"coordinates":[74.27193,34.50623],"type":"Point"}
}