{
  "type": "Feature",
  "properties": {
    "gn:admin1_code":"21.0",
    "gn:admin2_code":"398.0",
    "gn:asciiname":"Lenduru Maliguda",
    "gn:country_code":"IN",
    "gn:dem":848,
    "gn:feature_class":"P",
    "gn:feature_code":"PPL",
    "gn:name":"Lenduru Maliguda",
    "gn:population":0,
    "gn:timezone":"Asia/Kolkata",
    "iso:country":"IN",
    "wof:name":"Lenduru Maliguda",
    "wof:placetype":"locality"
},
  "geometry": {"coordinates":[82.82603,18.83951],"type":"Point"}
}