{
  "type": "Feature",
  "properties": {
    "iso:country":"IN",
    "ks:ks_name":"Mela Pluthigudi",
    "ks:ks_pop":312,
    "ks:ks_type":"HABITATION",
    "name:eng_x_preferred":[
        "Mela Pluthigudi"
    ],
    "wof:name":"Mela Pluthigudi",
    "wof:placetype":"locality",
    "wof:population":312
},
  "geometry": {"coordinates":[79.58958199999999,10.622452],"type":"Point"}
}