{
  "type": "Feature",
  "properties": {
    "iso:country":"IN",
    "ks:ks_name":"Nurpur Kharagpur",
    "ks:ks_pop":956,
    "ks:ks_type":"VILLAGE",
    "name:eng_x_preferred":[
        "Nurpur Kharagpur"
    ],
    "wof:name":"Nurpur Kharagpur",
    "wof:placetype":"locality",
    "wof:population":956
},
  "geometry": {"coordinates":[79.574229,26.856388],"type":"Point"}
}