{
  "type": "Feature",
  "properties": {
    "iso:country":"IN",
    "ks:ks_name":"Belandi",
    "ks:ks_pop":38,
    "ks:ks_type":"VILLAGE",
    "name:eng_x_preferred":[
        "Belandi"
    ],
    "wof:name":"Belandi",
    "wof:placetype":"locality",
    "wof:population":38
},
  "geometry": {"coordinates":[83.672622,19.541555],"type":"Point"}
}