{
  "type": "Feature",
  "properties": {
    "gn:admin1_code":"36.0",
    "gn:admin2_code":"202",
    "gn:asciiname":"Nawabganj Nagaria",
    "gn:country_code":"IN",
    "gn:dem":159,
    "gn:feature_class":"P",
    "gn:feature_code":"PPL",
    "gn:name":"Naw\u0101bganj Nagaria",
    "gn:population":0,
    "gn:timezone":"Asia/Kolkata",
    "iso:country":"IN",
    "wof:name":"Nawabganj Nagaria",
    "wof:placetype":"locality"
},
  "geometry": {"coordinates":[79.03907,27.7846],"type":"Point"}
}