{
  "type": "Feature",
  "properties": {
    "iso:country":"IN",
    "ks:ks_name":"Gobri",
    "ks:ks_pop":9,
    "ks:ks_type":"VILLAGE",
    "name:eng_x_preferred":[
        "Gobri"
    ],
    "wof:name":"Gobri",
    "wof:placetype":"locality",
    "wof:population":9
},
  "geometry": {"coordinates":[87.64804100000001,24.992064],"type":"Point"}
}