{
  "type": "Feature",
  "properties": {
    "gn:admin1_code":"34",
    "gn:admin2_code":"233.0",
    "gn:asciiname":"Shukul Purwa",
    "gn:country_code":"IN",
    "gn:dem":91,
    "gn:feature_class":"P",
    "gn:feature_code":"PPL",
    "gn:name":"Shukul Purwa",
    "gn:population":0,
    "gn:timezone":"Asia/Kolkata",
    "iso:country":"IN",
    "ks:ks_name":"Shukulpur",
    "ks:ks_pop":499,
    "ks:ks_type":"VILLAGE",
    "name:eng_x_preferred":[
        "Shukulpur"
    ],
    "name:eng_x_variant":[
        "Shukul Purwa"
    ],
    "wof:name":"Shukulpur",
    "wof:placetype":"locality",
    "wof:population":499
},
  "geometry": {"coordinates":[83.455213,25.020959],"type":"Point"}
}