{
  "type": "Feature",
  "properties": {
    "gn:admin1_code":"11",
    "gn:admin2_code":"23.0",
    "gn:asciiname":"Tandli",
    "gn:country_code":"IN",
    "gn:dem":1815,
    "gn:feature_class":"P",
    "gn:feature_code":"PPL",
    "gn:name":"Tandli",
    "gn:population":0,
    "gn:timezone":"Asia/Kolkata",
    "iso:country":"IN",
    "wof:name":"Tandli",
    "wof:placetype":"locality"
},
  "geometry": {"coordinates":[76.16169000000002,32.53492],"type":"Point"}
}