{
  "type": "Feature",
  "properties": {
    "iso:country":"IN",
    "ks:ks_name":"J H C Mallaru",
    "ks:ks_pop":436,
    "ks:ks_type":"HABITATION",
    "name:eng_x_preferred":[
        "J H C Mallaru"
    ],
    "wof:name":"J H C Mallaru",
    "wof:placetype":"locality",
    "wof:population":436
},
  "geometry": {"coordinates":[74.772447,13.225201],"type":"Point"}
}