{
  "type": "Feature",
  "properties": {
    "gn:admin1_code":"37",
    "gn:admin2_code":"406.0",
    "gn:asciiname":"Pankota",
    "gn:country_code":"IN",
    "gn:dem":606,
    "gn:feature_class":"P",
    "gn:feature_code":"PPL",
    "gn:name":"Pankota",
    "gn:population":0,
    "gn:timezone":"Asia/Kolkata",
    "iso:country":"IN",
    "ks:ks_name":"Pankota",
    "ks:ks_pop":837,
    "ks:ks_type":"VILLAGE",
    "name:eng_x_preferred":[
        "Pankota"
    ],
    "wof:name":"Pankota",
    "wof:placetype":"locality",
    "wof:population":837
},
  "geometry": {"coordinates":[82.01106299999999,22.728499],"type":"Point"}
}