{
  "type": "Feature",
  "properties": {
    "iso:country":"IN",
    "ks:ks_name":"Tandahar",
    "ks:ks_pop":230,
    "ks:ks_type":"HABITATION",
    "name:eng_x_preferred":[
        "Tandahar"
    ],
    "wof:name":"Tandahar",
    "wof:placetype":"locality",
    "wof:population":230
},
  "geometry": {"coordinates":[86.206203,19.89767],"type":"Point"}
}