{
  "type": "Feature",
  "properties": {
    "gn:admin1_code":"25",
    "gn:admin2_code":"625.0",
    "gn:asciiname":"Settur",
    "gn:country_code":"IN",
    "gn:dem":173,
    "gn:feature_class":"P",
    "gn:feature_code":"PPL",
    "gn:name":"Sett\u016br",
    "gn:population":0,
    "gn:timezone":"Asia/Kolkata",
    "iso:country":"IN",
    "name:bpy_x_preferred":[
        "\u09b8\u09c7\u0987\u09a5\u09c1\u09b0"
    ],
    "name:ita_x_preferred":[
        "Seithur"
    ],
    "name:msa_x_preferred":[
        "Seithur"
    ],
    "name:nld_x_preferred":[
        "Seithur"
    ],
    "name:por_x_preferred":[
        "Seithur"
    ],
    "name:tam_x_preferred":[
        "\u0b9a\u0bc7\u0ba4\u0bcd\u0ba4\u0bc2\u0bb0\u0bcd"
    ],
    "name:und_x_variant":[
        "Sett\u016br"
    ],
    "name:vie_x_preferred":[
        "Seithur"
    ],
    "name:zho_x_preferred":[
        "\u585e\u4f0a\u56fe\u5c14"
    ],
    "wof:name":"Settur",
    "wof:placetype":"neighbourhood"
},
  "geometry": {"coordinates":[77.47841,9.40564],"type":"Point"}
}