{
  "type": "Feature",
  "properties": {
    "gn:admin1_code":"37.0",
    "gn:admin2_code":"414.0",
    "gn:asciiname":"Uridgaon",
    "gn:country_code":"IN",
    "gn:dem":627,
    "gn:feature_class":"P",
    "gn:feature_code":"PPL",
    "gn:name":"Uridgaon",
    "gn:population":0,
    "gn:timezone":"Asia/Kolkata",
    "iso:country":"IN",
    "ks:ks_name":"Uridgaon",
    "ks:ks_type":"VILLAGE",
    "name:eng_x_preferred":[
        "Uridgaon"
    ],
    "wof:name":"Uridgaon",
    "wof:placetype":"locality"
},
  "geometry": {"coordinates":[81.970403,19.774138],"type":"Point"}
}