{
  "type": "Feature",
  "properties": {
    "iso:country":"IN",
    "ks:ks_name":"Bakoor",
    "ks:ks_pop":48,
    "ks:ks_type":"HABITATION",
    "name:eng_x_preferred":[
        "Bakoor"
    ],
    "wof:name":"Bakoor",
    "wof:placetype":"locality",
    "wof:population":48
},
  "geometry": {"coordinates":[81.083882,19.379303],"type":"Point"}
}