{
  "type": "Feature",
  "properties": {
    "iso:country":"IN",
    "ks:ks_name":"Niduvangeri Colony",
    "ks:ks_pop":150,
    "ks:ks_type":"HABITATION",
    "name:eng_x_preferred":[
        "Niduvangeri Colony"
    ],
    "wof:name":"Niduvangeri Colony",
    "wof:placetype":"locality",
    "wof:population":150
},
  "geometry": {"coordinates":[76.03694400000001,12.110833],"type":"Point"}
}