{
  "type": "Feature",
  "properties": {
    "iso:country":"IN",
    "ks:ks_name":"Nerao",
    "ks:ks_pop":352,
    "ks:ks_type":"VILLAGE",
    "name:eng_x_preferred":[
        "Nerao"
    ],
    "wof:name":"Nerao",
    "wof:placetype":"locality",
    "wof:population":352
},
  "geometry": {"coordinates":[73.38285500000001,18.22729],"type":"Point"}
}