{
  "type": "Feature",
  "properties": {
    "gn:admin1_code":"35",
    "gn:admin2_code":"424.0",
    "gn:asciiname":"Shankargarh",
    "gn:country_code":"IN",
    "gn:dem":295,
    "gn:feature_class":"P",
    "gn:feature_code":"PPL",
    "gn:name":"Shankargarh",
    "gn:population":0,
    "gn:timezone":"Asia/Kolkata",
    "iso:country":"IN",
    "name:bih_x_preferred":[
        "\u0936\u0902\u0915\u0930\u0917\u0922\u093c"
    ],
    "name:bpy_x_preferred":[
        "\u09b6\u0999\u09cd\u0995\u09b0\u0997\u09a1\u09bc"
    ],
    "name:ceb_x_preferred":[
        "Shankargarh"
    ],
    "name:ita_x_preferred":[
        "Shankargarh"
    ],
    "name:msa_x_preferred":[
        "Shankargarh"
    ],
    "name:nld_x_preferred":[
        "Shankargarh"
    ],
    "name:pol_x_preferred":[
        "Shankargarh"
    ],
    "name:por_x_preferred":[
        "Shankargarh"
    ],
    "name:swe_x_preferred":[
        "Shankargarh"
    ],
    "name:urd_x_preferred":[
        "\u0634\u0646\u06a9\u0631 \u06af\u0691\u06be"
    ],
    "name:vie_x_preferred":[
        "Shankargarh"
    ],
    "name:zho_x_preferred":[
        "\u65af\u6c49\u5361\u5c14\u52a0\u5c14"
    ],
    "wof:name":"Shankargarh",
    "wof:placetype":"locality"
},
  "geometry": {"coordinates":[78.67397,25.14581],"type":"Point"}
}