{
  "type": "Feature",
  "properties": {
    "gn:admin1_code":"35",
    "gn:admin2_code":"423.0",
    "gn:asciiname":"Kharguwaha",
    "gn:country_code":"IN",
    "gn:dem":388,
    "gn:feature_class":"P",
    "gn:feature_code":"PPL",
    "gn:name":"Kharguw\u0101ha",
    "gn:population":0,
    "gn:timezone":"Asia/Kolkata",
    "iso:country":"IN",
    "wof:name":"Kharguwaha",
    "wof:placetype":"locality"
},
  "geometry": {"coordinates":[78.06301999999999,25.21752],"type":"Point"}
}