{
  "type": "Feature",
  "properties": {
    "iso:country":"IN",
    "ks:ks_name":"Karri",
    "ks:ks_pop":545,
    "ks:ks_type":"VILLAGE",
    "name:eng_x_preferred":[
        "Karri"
    ],
    "wof:name":"Karri",
    "wof:placetype":"locality",
    "wof:population":545
},
  "geometry": {"coordinates":[82.712988,23.903626],"type":"Point"}
}