{
  "type": "Feature",
  "properties": {
    "gn:admin1_code":"34.0",
    "gn:admin2_code":"220.0",
    "gn:asciiname":"Desri",
    "gn:country_code":"IN",
    "gn:dem":52,
    "gn:feature_class":"P",
    "gn:feature_code":"PPL",
    "gn:name":"Desri",
    "gn:population":0,
    "gn:timezone":"Asia/Kolkata",
    "iso:country":"IN",
    "ks:ks_name":"Desri",
    "ks:ks_pop":9337,
    "ks:ks_type":"VILLAGE",
    "name:eng_x_preferred":[
        "Desri"
    ],
    "wof:name":"Desri",
    "wof:placetype":"locality",
    "wof:population":9337
},
  "geometry": {"coordinates":[85.408241,25.669137],"type":"Point"}
}