{
  "type": "Feature",
  "properties": {
    "gn:admin1_code":"13.0",
    "gn:admin2_code":"595.0",
    "gn:asciiname":"Kidamangalam",
    "gn:country_code":"IN",
    "gn:dem":7,
    "gn:feature_class":"P",
    "gn:feature_code":"PPL",
    "gn:name":"Kidamangalam",
    "gn:population":0,
    "gn:timezone":"Asia/Kolkata",
    "iso:country":"IN",
    "ks:ks_name":"Kedamangalam",
    "ks:ks_pop":1500,
    "ks:ks_type":"HABITATION",
    "ks:ks_uagg_main":0,
    "name:eng_x_preferred":[
        "Kedamangalam"
    ],
    "wof:name":"Kedamangalam",
    "wof:placetype":"neighbourhood",
    "wof:population":1500
},
  "geometry": {"coordinates":[76.223967,10.124584],"type":"Point"}
}