{
  "type": "Feature",
  "properties": {
    "gn:admin1_code":"34.0",
    "gn:admin2_code":"212.0",
    "gn:asciiname":"Chikni",
    "gn:country_code":"IN",
    "gn:dem":41,
    "gn:feature_class":"P",
    "gn:feature_code":"PPL",
    "gn:name":"Chikni",
    "gn:population":0,
    "gn:timezone":"Asia/Kolkata",
    "iso:country":"IN",
    "wof:name":"Chikni",
    "wof:placetype":"neighbourhood"
},
  "geometry": {"coordinates":[87.86312,25.83069],"type":"Point"}
}