{
  "type": "Feature",
  "properties": {
    "gn:admin1_code":"34.0",
    "gn:admin2_code":"208.0",
    "gn:asciiname":"Barhampur",
    "gn:country_code":"IN",
    "gn:dem":74,
    "gn:feature_class":"P",
    "gn:feature_code":"PPL",
    "gn:name":"Barh\u0101mpur",
    "gn:population":0,
    "gn:timezone":"Asia/Kolkata",
    "iso:country":"IN",
    "ks:ks_alt_nam":"Barh\u0101mpur",
    "ks:ks_name":"Barhampur",
    "ks:ks_type":"VILLAGE",
    "name:eng_x_preferred":[
        "Barhampur"
    ],
    "name:eng_x_variant":[
        "Barh\u0101mpur"
    ],
    "wof:name":"Barhampur",
    "wof:placetype":"locality"
},
  "geometry": {"coordinates":[87.03017,26.446728],"type":"Point"}
}