{
  "type": "Feature",
  "properties": {
    "gn:admin1_code":"39.0",
    "gn:admin2_code":"61.0",
    "gn:asciiname":"Ghuriyana",
    "gn:country_code":"IN",
    "gn:dem":1344,
    "gn:feature_class":"P",
    "gn:feature_code":"PPL",
    "gn:name":"Ghuriy\u0101na",
    "gn:population":0,
    "gn:timezone":"Asia/Kolkata",
    "iso:country":"IN",
    "wof:name":"Ghuriyana",
    "wof:placetype":"locality"
},
  "geometry": {"coordinates":[79.05606,29.83175],"type":"Point"}
}