{
  "type": "Feature",
  "properties": {
    "iso:country":"IN",
    "ks:ks_name":"Gavitpada",
    "ks:ks_pop":62,
    "ks:ks_type":"HABITATION",
    "name:eng_x_preferred":[
        "Gavitpada"
    ],
    "wof:name":"Gavitpada",
    "wof:placetype":"locality",
    "wof:population":62
},
  "geometry": {"coordinates":[73.18419400000001,19.54568],"type":"Point"}
}