{
  "type": "Feature",
  "properties": {
    "iso:country":"IN",
    "ks:ks_name":"Ghinhu Chhapra Urf Parhadwa",
    "ks:ks_pop":220,
    "ks:ks_type":"VILLAGE",
    "name:eng_x_preferred":[
        "Ghinhu Chhapra Urf Parhadwa"
    ],
    "wof:name":"Ghinhu Chhapra Urf Parhadwa",
    "wof:placetype":"locality",
    "wof:population":220
},
  "geometry": {"coordinates":[84.245008,26.362967],"type":"Point"}
}