{
  "type": "Feature",
  "properties": {
    "iso:country":"IN",
    "ks:ks_name":"Chhedi Purwa",
    "ks:ks_pop":38,
    "ks:ks_type":"HABITATION",
    "ks:ks_uagg_main":0,
    "name:eng_x_preferred":[
        "Chhedi Purwa"
    ],
    "wof:name":"Chhedi Purwa",
    "wof:placetype":"neighbourhood",
    "wof:population":38
},
  "geometry": {"coordinates":[81.87655599999999,27.689781],"type":"Point"}
}