{
  "type": "Feature",
  "properties": {
    "gn:admin1_code":"24.0",
    "gn:admin2_code":"109.0",
    "gn:asciiname":"Kishorpura",
    "gn:country_code":"IN",
    "gn:dem":269,
    "gn:feature_class":"P",
    "gn:feature_code":"PPL",
    "gn:name":"Kishorpura",
    "gn:population":0,
    "gn:timezone":"Asia/Kolkata",
    "iso:country":"IN",
    "ks:ks_name":"Kishorpura",
    "ks:ks_pop":1892,
    "ks:ks_type":"VILLAGE",
    "name:eng_x_preferred":[
        "Kishorpura"
    ],
    "wof:name":"Kishorpura",
    "wof:placetype":"locality",
    "wof:population":1892
},
  "geometry": {"coordinates":[76.41788200000001,26.460184],"type":"Point"}
}