{
  "type": "Feature",
  "properties": {
    "gn:admin1_code":"12",
    "gn:admin2_code":"13.0",
    "gn:asciiname":"Aivind",
    "gn:country_code":"IN",
    "gn:dem":2024,
    "gn:feature_class":"P",
    "gn:feature_code":"PPL",
    "gn:name":"Aivind",
    "gn:population":0,
    "gn:timezone":"Asia/Kolkata",
    "iso:country":"IN",
    "wof:name":"Aivind",
    "wof:placetype":"locality"
},
  "geometry": {"coordinates":[74.8734,33.69696],"type":"Point"}
}