{
  "type": "Feature",
  "properties": {
    "iso:country":"IN",
    "ks:ks_alt_nam":"HARIJAN TOLA",
    "ks:ks_name":"Harijan Tola",
    "ks:ks_pop":123,
    "ks:ks_type":"HABITATION",
    "name:eng_x_preferred":[
        "Harijan Tola"
    ],
    "wof:name":"Harijan Tola",
    "wof:placetype":"locality",
    "wof:population":123
},
  "geometry": {"coordinates":[86.40571199999999,24.966654],"type":"Point"}
}