{
  "type": "Feature",
  "properties": {
    "gn:admin1_code":"24",
    "gn:admin2_code":"123.0",
    "gn:asciiname":"Basol",
    "gn:country_code":"IN",
    "gn:dem":553,
    "gn:feature_class":"P",
    "gn:feature_code":"PPL",
    "gn:name":"B\u0101sol",
    "gn:population":0,
    "gn:timezone":"Asia/Kolkata",
    "iso:country":"IN",
    "ks:ks_alt_nam":"B\u0101sol",
    "ks:ks_name":"Basol",
    "ks:ks_type":"VILLAGE",
    "ks:ks_uagg_main":0,
    "name:eng_x_preferred":[
        "Basol"
    ],
    "name:eng_x_variant":[
        "B\u0101sol"
    ],
    "wof:name":"Basol",
    "wof:placetype":"neighbourhood"
},
  "geometry": {"coordinates":[73.902657,25.070815],"type":"Point"}
}