{
  "type": "Feature",
  "properties": {
    "iso:country":"IN",
    "ks:ks_name":"Vaitagwadi",
    "ks:ks_pop":172,
    "ks:ks_type":"HABITATION",
    "name:eng_x_preferred":[
        "Vaitagwadi"
    ],
    "wof:name":"Vaitagwadi",
    "wof:placetype":"locality",
    "wof:population":172
},
  "geometry": {"coordinates":[73.41054200000001,19.554659],"type":"Point"}
}