{
  "type": "Feature",
  "properties": {
    "iso:country":"IN",
    "ks:ks_name":"Bhuiya Tola",
    "ks:ks_pop":54,
    "ks:ks_type":"HABITATION",
    "name:eng_x_preferred":[
        "Bhuiya Tola"
    ],
    "wof:name":"Bhuiya Tola",
    "wof:placetype":"locality",
    "wof:population":54
},
  "geometry": {"coordinates":[84.334694,24.616127],"type":"Point"}
}