{
  "type": "Feature",
  "properties": {
    "gn:admin1_code":"36.0",
    "gn:admin2_code":"165",
    "gn:asciiname":"Machkacha",
    "gn:country_code":"IN",
    "gn:dem":129,
    "gn:feature_class":"P",
    "gn:feature_code":"PPL",
    "gn:name":"Machkacha",
    "gn:population":0,
    "gn:timezone":"Asia/Kolkata",
    "iso:country":"IN",
    "ks:ks_name":"Machkachha",
    "ks:ks_pop":232,
    "ks:ks_type":"VILLAGE",
    "name:eng_x_preferred":[
        "Machkachha"
    ],
    "name:eng_x_variant":[
        "Machkacha"
    ],
    "name:und_x_variant":[
        "Machkachha"
    ],
    "wof:name":"Machkachha",
    "wof:placetype":"locality",
    "wof:population":232
},
  "geometry": {"coordinates":[79.10043899999999,26.284259],"type":"Point"}
}