{
  "type": "Feature",
  "properties": {
    "gn:admin1_code":"36.0",
    "gn:admin2_code":"165",
    "gn:asciiname":"Machkacha",
    "gn:country_code":"IN",
    "gn:dem":129,
    "gn:feature_class":"P",
    "gn:feature_code":"PPL",
    "gn:name":"Machkacha",
    "gn:population":0,
    "gn:timezone":"Asia/Kolkata",
    "iso:country":"IN",
    "name:und_x_variant":[
        "Machkachha"
    ],
    "wof:name":"Machkacha",
    "wof:placetype":"locality"
},
  "geometry": {"coordinates":[79.09598000000003,26.28796],"type":"Point"}
}