{
  "type": "Feature",
  "properties": {
    "iso:country":"IN",
    "ks:ks_name":"Saw Ghontipara",
    "ks:ks_pop":607,
    "ks:ks_type":"HABITATION",
    "ks:ks_uagg_main":0,
    "name:eng_x_preferred":[
        "Saw Ghontipara"
    ],
    "wof:name":"Saw Ghontipara",
    "wof:placetype":"neighbourhood",
    "wof:population":607
},
  "geometry": {"coordinates":[87.950329,22.567538],"type":"Point"}
}