{
  "type": "Feature",
  "properties": {
    "gn:admin1_code":"24",
    "gn:admin2_code":"108.0",
    "gn:asciiname":"Lahsora",
    "gn:country_code":"IN",
    "gn:dem":221,
    "gn:feature_class":"P",
    "gn:feature_code":"PPL",
    "gn:name":"Lahsora",
    "gn:population":0,
    "gn:timezone":"Asia/Kolkata",
    "iso:country":"IN",
    "wof:name":"Lahsora",
    "wof:placetype":"locality"
},
  "geometry": {"coordinates":[76.42103,25.82818],"type":"Point"}
}