{
  "type": "Feature",
  "properties": {
    "iso:country":"IN",
    "ks:ks_name":"Belpada",
    "ks:ks_pop":832,
    "ks:ks_type":"HABITATION",
    "name:eng_x_preferred":[
        "Belpada"
    ],
    "wof:name":"Belpada",
    "wof:placetype":"locality",
    "wof:population":832
},
  "geometry": {"coordinates":[82.808339,20.070274],"type":"Point"}
}