{
  "type": "Feature",
  "properties": {
    "iso:country":"IN",
    "ks:ks_alt_nam":"MAINATAICHA MALA",
    "ks:ks_name":"Mainataicha Mala",
    "ks:ks_pop":90,
    "ks:ks_type":"HABITATION",
    "name:eng_x_preferred":[
        "Mainataicha Mala"
    ],
    "wof:name":"Mainataicha Mala",
    "wof:placetype":"locality",
    "wof:population":90
},
  "geometry": {"coordinates":[74.365002,17.364579],"type":"Point"}
}