{
  "type": "Feature",
  "properties": {
    "gn:admin1_code":"34.0",
    "gn:admin2_code":"211.0",
    "gn:asciiname":"Dangraha",
    "gn:country_code":"IN",
    "gn:dem":43,
    "gn:feature_class":"P",
    "gn:feature_code":"PPL",
    "gn:name":"Dangr\u0101ha",
    "gn:population":0,
    "gn:timezone":"Asia/Kolkata",
    "iso:country":"IN",
    "ks:ks_alt_nam":"Dangr\u0101ha",
    "ks:ks_name":"Dangraha",
    "ks:ks_pop":1173,
    "ks:ks_type":"VILLAGE",
    "name:ceb_x_preferred":[
        "Dangraha"
    ],
    "name:eng_x_preferred":[
        "Dangraha"
    ],
    "name:eng_x_variant":[
        "Dangr\u0101ha"
    ],
    "name:mai_x_preferred":[
        "\u0921\u0902\u0917\u094d\u0930\u093e\u0939\u093e"
    ],
    "name:msa_x_preferred":[
        "Dangraha"
    ],
    "name:nep_x_preferred":[
        "\u0926\u093e\u0902\u0917\u094d\u0930\u0939"
    ],
    "name:new_x_preferred":[
        "\u0926\u093e\u0902\u0917\u094d\u0930\u0939"
    ],
    "name:pol_x_preferred":[
        "Dangraha"
    ],
    "wof:name":"Dangraha",
    "wof:placetype":"locality",
    "wof:population":1173
},
  "geometry": {"coordinates":[87.411703,25.844808],"type":"Point"}
}