{
  "type": "Feature",
  "properties": {
    "iso:country":"IN",
    "ks:ks_name":"Natun Boroighat",
    "ks:ks_pop":298,
    "ks:ks_type":"VILLAGE",
    "ks:ks_uagg_main":0,
    "name:eng_x_preferred":[
        "Natun Boroighat"
    ],
    "wof:name":"Natun Boroighat",
    "wof:placetype":"neighbourhood",
    "wof:population":298
},
  "geometry": {"coordinates":[93.42730899999999,26.865354],"type":"Point"}
}