{
  "type": "Feature",
  "properties": {
    "iso:country":"IN",
    "ks:ks_name":"Dumariya Bank",
    "ks:ks_pop":91,
    "ks:ks_type":"VILLAGE",
    "name:eng_x_preferred":[
        "Dumariya Bank"
    ],
    "wof:name":"Dumariya Bank",
    "wof:placetype":"locality",
    "wof:population":91
},
  "geometry": {"coordinates":[86.77994700000001,24.126248],"type":"Point"}
}