{
  "type": "Feature",
  "properties": {
    "iso:country":"IN",
    "ks:ks_name":"Mokhi",
    "ks:ks_pop":986,
    "ks:ks_type":"VILLAGE",
    "name:eng_x_preferred":[
        "Mokhi"
    ],
    "wof:name":"Mokhi",
    "wof:placetype":"locality",
    "wof:population":986
},
  "geometry": {"coordinates":[73.46337800000001,24.688922],"type":"Point"}
}