{
  "type": "Feature",
  "properties": {
    "iso:country":"IN",
    "qs:name":"Prasar Bharti Residential Area",
    "qs:name_adm0":"India",
    "qs:name_adm1":"Goa",
    "qs:photos":24,
    "qs:photos_1k":5,
    "qs:photos_9k":1,
    "qs:photos_9r":1,
    "qs:photos_all":24,
    "qs:photos_sr":1,
    "qs:placetype":"Suburb",
    "qs:pop_sr":"0",
    "wof:name":"Prasar Bharti Residential Area",
    "wof:placetype":"neighbourhood"
},
  "geometry": {"coordinates":[73.823618,15.48896],"type":"Point"}
}