{
  "type": "Feature",
  "properties": {
    "iso:country":"IN",
    "name:ara_x_preferred":[
        "\u0645\u0646\u0637\u0642\u0629 \u0628\u0631\u0627\u0633\u0627\u0631 \u0628\u0647\u0627\u0631\u062a\u064a \u0627\u0644\u0633\u0643\u0646\u064a\u0629"
    ],
    "name:ben_bn_x_preferred":[
        "\u09aa\u09cd\u09b0\u09b8\u09be\u09b0 \u09ad\u09be\u09b0\u09a4\u09c0 \u0986\u09ac\u09be\u09b8\u09bf\u0995 \u0985\u099e\u09cd\u099a\u09b2"
    ],
    "name:ben_in_x_preferred":[
        "\u09aa\u09cd\u09b0\u09b8\u09be\u09b0 \u09ad\u09be\u09b0\u09a4\u09c0 \u0986\u09ac\u09be\u09b8\u09bf\u0995 \u0985\u099e\u09cd\u099a\u09b2"
    ],
    "name:guj_x_preferred":[
        "\u0aaa\u0acd\u0ab0\u0ab8\u0abe\u0ab0 \u0aad\u0abe\u0ab0\u0aa4\u0ac0 \u0ab0\u0ac7\u0ab8\u0abf\u0aa1\u0aa8\u0acd\u0ab6\u0abf\u0aaf\u0ab2 \u0ab5\u0abf\u0ab8\u0acd\u0aa4\u0abe\u0ab0"
    ],
    "name:hin_x_preferred":[
        "\u092a\u094d\u0930\u0938\u093e\u0930 \u092d\u093e\u0930\u0924\u0940 \u0930\u0947\u091c\u093f\u0921\u0947\u0902\u0936\u093f\u092f\u0932 \u090f\u0930\u093f\u092f\u093e"
    ],
    "name:kan_x_preferred":[
        "\u0caa\u0ccd\u0cb0\u0cb8\u0cbe\u0cb0 \u0cad\u0cbe\u0cb0\u0ca4\u0cbf \u0cb0\u0cc6\u0cb8\u0cbf\u0ca1\u0cc6\u0ca8\u0ccd\u0cb7\u0cbf\u0caf\u0cb2\u0ccd \u0c8f\u0cb0\u0cbf\u0caf\u0cbe"
    ],
    "name:mal_x_preferred":[
        "\u0d2a\u0d4d\u0d30\u0d38\u0d3e\u0d7c \u0d2d\u0d3e\u0d30\u0d24\u0d3f \u0d31\u0d46\u0d38\u0d3f\u0d21\u0d7b\u0d37\u0d4d\u0d2f\u0d7d \u0d0f\u0d30\u0d3f\u0d2f"
    ],
    "name:mar_x_preferred":[
        "\u092a\u094d\u0930\u0938\u093e\u0930 \u092d\u093e\u0930\u0924\u0940 \u0928\u093f\u0935\u093e\u0938\u0940 \u0915\u094d\u0937\u0947\u0924\u094d\u0930"
    ],
    "name:pan_x_preferred":[
        "\u0a2a\u0a4d\u0a30\u0a38\u0a3e\u0a30 \u0a2d\u0a3e\u0a30\u0a24\u0a40 \u0a30\u0a3f\u0a39\u0a3e\u0a07\u0a36\u0a40 \u0a07\u0a32\u0a3e\u0a15\u0a3e"
    ],
    "name:tam_x_preferred":[
        "\u0baa\u0bbf\u0bb0\u0b9a\u0bbe\u0bb0\u0bcd \u0baa\u0bbe\u0bb0\u0ba4\u0bbf \u0b95\u0bc1\u0b9f\u0bbf\u0baf\u0bbf\u0bb0\u0bc1\u0baa\u0bcd\u0baa\u0bc1\u0baa\u0bcd \u0baa\u0b95\u0bc1\u0ba4\u0bbf"
    ],
    "name:tel_x_preferred":[
        "\u0c2a\u0c4d\u0c30\u0c38\u0c3e\u0c30\u0c4d \u0c2d\u0c3e\u0c30\u0c24\u0c3f \u0c30\u0c46\u0c38\u0c3f\u0c21\u0c46\u0c28\u0c4d\u0c37\u0c3f\u0c2f\u0c32\u0c4d \u0c0f\u0c30\u0c3f\u0c2f\u0c3e"
    ],
    "name:urd_x_preferred":[
        "\u067e\u0631\u0633\u0627\u0631 \u0628\u06be\u0627\u0631\u062a\u06cc \u0631\u06cc\u0632\u06cc\u0688\u0646\u0634\u06cc\u0644 \u0627\u06cc\u0631\u06cc\u0627"
    ],
    "qs:name":"Prasar Bharti Residential Area",
    "qs:name_adm0":"India",
    "qs:name_adm1":"Goa",
    "qs:photos":24,
    "qs:photos_1k":5,
    "qs:photos_9k":1,
    "qs:photos_9r":1,
    "qs:photos_all":24,
    "qs:photos_sr":1,
    "qs:placetype":"Suburb",
    "qs:pop_sr":"0",
    "wof:name":"Prasar Bharti Residential Area",
    "wof:placetype":"neighbourhood"
},
  "geometry": {"coordinates":[73.823618,15.48896],"type":"Point"}
}