{
  "type": "Feature",
  "properties": {
    "iso:country":"IN",
    "ks:ks_name":"Majhipada",
    "ks:ks_pop":18,
    "ks:ks_type":"HABITATION",
    "name:eng_x_preferred":[
        "Majhipada"
    ],
    "wof:name":"Majhipada",
    "wof:placetype":"locality",
    "wof:population":18
},
  "geometry": {"coordinates":[83.427864,19.782602],"type":"Point"}
}