{
  "type": "Feature",
  "properties": {
    "iso:country":"IN",
    "ks:ks_name":"Jawal",
    "ks:ks_pop":279,
    "ks:ks_type":"VILLAGE",
    "name:eng_x_preferred":[
        "Jawal"
    ],
    "wof:name":"Jawal",
    "wof:placetype":"locality",
    "wof:population":279
},
  "geometry": {"coordinates":[84.509413,23.451019],"type":"Point"}
}