{
  "type": "Feature",
  "properties": {
    "gn:admin1_code":"39",
    "gn:asciiname":"Mongra",
    "gn:country_code":"IN",
    "gn:dem":1241,
    "gn:feature_class":"P",
    "gn:feature_code":"PPL",
    "gn:name":"Mongra",
    "gn:population":0,
    "gn:timezone":"Asia/Kolkata",
    "iso:country":"IN",
    "wof:name":"Mongra",
    "wof:placetype":"locality"
},
  "geometry": {"coordinates":[77.82290999999999,31.06458],"type":"Point"}
}