{
  "type": "Feature",
  "properties": {
    "gn:admin1_code":"37",
    "gn:admin2_code":"414.0",
    "gn:asciiname":"Dondrakot",
    "gn:country_code":"IN",
    "gn:dem":585,
    "gn:feature_class":"P",
    "gn:feature_code":"PPL",
    "gn:name":"Dondrakot",
    "gn:population":0,
    "gn:timezone":"Asia/Kolkata",
    "iso:country":"IN",
    "wof:name":"Dondrakot",
    "wof:placetype":"locality"
},
  "geometry": {"coordinates":[82.08811999999998,19.22115],"type":"Point"}
}