{
  "type": "Feature",
  "properties": {
    "iso:country":"IN",
    "ks:ks_name":"Kampanimala Jn",
    "ks:ks_pop":398,
    "ks:ks_type":"HABITATION",
    "name:eng_x_preferred":[
        "Kampanimala Jn"
    ],
    "wof:name":"Kampanimala Jn",
    "wof:placetype":"locality",
    "wof:population":398
},
  "geometry": {"coordinates":[76.89232199999999,8.834934],"type":"Point"}
}