{
  "type": "Feature",
  "properties": {
    "gn:admin1_code":"36",
    "gn:admin2_code":"186.0",
    "gn:asciiname":"Purwa Nibohia",
    "gn:country_code":"IN",
    "gn:dem":83,
    "gn:feature_class":"P",
    "gn:feature_code":"PPL",
    "gn:name":"Purwa Nibohia",
    "gn:population":0,
    "gn:timezone":"Asia/Kolkata",
    "iso:country":"IN",
    "wof:name":"Purwa Nibohia",
    "wof:placetype":"neighbourhood"
},
  "geometry": {"coordinates":[83.08072,26.81846],"type":"Point"}
}