{
  "type": "Feature",
  "properties": {
    "gn:admin1_code":"2",
    "gn:admin2_code":"544.0",
    "gn:asciiname":"Peddabayal",
    "gn:country_code":"IN",
    "gn:dem":985,
    "gn:feature_class":"P",
    "gn:feature_code":"PPL",
    "gn:name":"Peddabayal",
    "gn:population":0,
    "gn:timezone":"Asia/Kolkata",
    "iso:country":"IN",
    "wof:name":"Peddabayal",
    "wof:placetype":"locality"
},
  "geometry": {"coordinates":[82.87615,18.10404],"type":"Point"}
}