{
  "type": "Feature",
  "properties": {
    "gn:admin1_code":"2",
    "gn:admin2_code":"544.0",
    "gn:asciiname":"Peddabayal",
    "gn:country_code":"IN",
    "gn:dem":985,
    "gn:feature_class":"P",
    "gn:feature_code":"PPL",
    "gn:name":"Peddabayal",
    "gn:population":0,
    "gn:timezone":"Asia/Kolkata",
    "iso:country":"IN",
    "ks:ks_name":"Pedabayalu",
    "ks:ks_pop":121,
    "ks:ks_type":"VILLAGE",
    "name:eng_x_preferred":[
        "Pedabayalu"
    ],
    "name:eng_x_variant":[
        "Peddabayal"
    ],
    "wof:name":"Pedabayalu",
    "wof:placetype":"locality",
    "wof:population":121
},
  "geometry": {"coordinates":[82.875896,18.103846],"type":"Point"}
}