{
  "type": "Feature",
  "properties": {
    "gn:admin1_code":"36",
    "gn:admin2_code":"148.0",
    "gn:asciiname":"Sultanganj",
    "gn:country_code":"IN",
    "gn:dem":162,
    "gn:feature_class":"P",
    "gn:feature_code":"PPL",
    "gn:name":"Sult\u0101nganj",
    "gn:population":0,
    "gn:timezone":"Asia/Kolkata",
    "iso:country":"IN",
    "name:ben_x_preferred":[
        "\u09b8\u09c1\u09b2\u09a4\u09be\u09a8\u0997\u099e\u09cd\u099c"
    ],
    "name:bpy_x_preferred":[
        "\u09b8\u09c1\u09b2\u09a4\u09be\u09a8\u0997\u099e\u09cd\u099c"
    ],
    "name:ceb_x_preferred":[
        "Sult\u0101nganj"
    ],
    "name:hin_x_preferred":[
        "\u0938\u0941\u0932\u094d\u0924\u093e\u0928\u0917\u0902\u091c"
    ],
    "name:ita_x_preferred":[
        "Sultanganj"
    ],
    "name:mai_x_preferred":[
        "\u0938\u0941\u0932\u094d\u0924\u093e\u0928\u0917\u091e\u094d\u091c"
    ],
    "name:msa_x_preferred":[
        "Sultanganj"
    ],
    "name:nld_x_preferred":[
        "Sultanganj"
    ],
    "name:ori_x_preferred":[
        "\u0b38\u0b41\u0b32\u0b24\u0b3e\u0b28\u0b2a\u0b41\u0b30"
    ],
    "name:por_x_preferred":[
        "Sultanganj"
    ],
    "name:spa_x_preferred":[
        "Sultanganj"
    ],
    "name:swe_x_preferred":[
        "Sult\u0101nganj"
    ],
    "name:vie_x_preferred":[
        "Sultanganj"
    ],
    "name:zho_x_preferred":[
        "\u82cf\u5c14\u5510\u7518\u6770"
    ],
    "wof:name":"Sultanganj",
    "wof:placetype":"locality"
},
  "geometry": {"coordinates":[79.09699000000001,27.3152],"type":"Point"}
}