{
  "type": "Feature",
  "properties": {
    "iso:country":"IN",
    "ks:ks_name":"Lakaddhar",
    "ks:ks_pop":951,
    "ks:ks_type":"VILLAGE",
    "ks:ks_uagg_main":0,
    "name:eng_x_preferred":[
        "Lakaddhar"
    ],
    "wof:name":"Lakaddhar",
    "wof:placetype":"neighbourhood",
    "wof:population":951
},
  "geometry": {"coordinates":[70.962005,22.708951],"type":"Point"}
}