{
  "type": "Feature",
  "properties": {
    "iso:country":"IN",
    "ks:ks_name":"Jagadanandapur",
    "ks:ks_pop":1230,
    "ks:ks_type":"URBAN",
    "ks:ks_uagg_main":0,
    "name:eng_x_preferred":[
        "Jagadanandapur"
    ],
    "wof:name":"Jagadanandapur",
    "wof:placetype":"locality",
    "wof:population":1230
},
  "geometry": {"coordinates":[88.169738,23.584052],"type":"Point"}
}