{
  "type": "Feature",
  "properties": {
    "iso:country":"IN",
    "ks:ks_alt_nam":"KHAMLIKALA",
    "ks:ks_name":"Khamlikala",
    "ks:ks_pop":254,
    "ks:ks_type":"HABITATION",
    "name:eng_x_preferred":[
        "Khamlikala"
    ],
    "wof:name":"Khamlikala",
    "wof:placetype":"locality",
    "wof:population":254
},
  "geometry": {"coordinates":[81.73139399999999,22.639188],"type":"Point"}
}