{
  "type": "Feature",
  "properties": {
    "iso:country":"IN",
    "ks:ks_name":"Gijorra",
    "ks:ks_pop":187,
    "ks:ks_type":"HABITATION",
    "name:eng_x_preferred":[
        "Gijorra"
    ],
    "wof:name":"Gijorra",
    "wof:placetype":"locality",
    "wof:population":187
},
  "geometry": {"coordinates":[78.112168,25.922994],"type":"Point"}
}