{
  "type": "Feature",
  "properties": {
    "iso:country":"IN",
    "ks:ks_alt_nam":"HUNASEKOPPA",
    "ks:ks_name":"Hunasekoppa",
    "ks:ks_pop":29,
    "ks:ks_type":"HABITATION",
    "name:eng_x_preferred":[
        "Hunasekoppa"
    ],
    "wof:name":"Hunasekoppa",
    "wof:placetype":"locality",
    "wof:population":29
},
  "geometry": {"coordinates":[75.170492,13.750114],"type":"Point"}
}