{
  "type": "Feature",
  "properties": {
    "iso:country":"IN",
    "ks:ks_name":"Dalkhaiya Deepa",
    "ks:ks_pop":196,
    "ks:ks_type":"HABITATION",
    "name:eng_x_preferred":[
        "Dalkhaiya Deepa"
    ],
    "wof:name":"Dalkhaiya Deepa",
    "wof:placetype":"locality",
    "wof:population":196
},
  "geometry": {"coordinates":[82.733501,21.457877],"type":"Point"}
}