{
  "type": "Feature",
  "properties": {
    "gn:admin1_code":"36.0",
    "gn:admin2_code":"170.0",
    "gn:asciiname":"Duben Purwa",
    "gn:country_code":"IN",
    "gn:dem":144,
    "gn:feature_class":"P",
    "gn:feature_code":"PPL",
    "gn:name":"Duben Purwa",
    "gn:population":0,
    "gn:timezone":"Asia/Kolkata",
    "iso:country":"IN",
    "wof:name":"Duben Purwa",
    "wof:placetype":"locality"
},
  "geometry": {"coordinates":[80.53071,25.11715],"type":"Point"}
}