{
  "type": "Feature",
  "properties": {
    "iso:country":"IN",
    "ks:ks_alt_nam":"GANGA HARI PARA",
    "ks:ks_name":"Ganga Hari Para",
    "ks:ks_pop":149,
    "ks:ks_type":"HABITATION",
    "name:eng_x_preferred":[
        "Ganga Hari Para"
    ],
    "wof:name":"Ganga Hari Para",
    "wof:placetype":"locality",
    "wof:population":149
},
  "geometry": {"coordinates":[91.428409,23.738048],"type":"Point"}
}