{
  "type": "Feature",
  "properties": {
    "iso:country":"IN",
    "ks:ks_name":"Kothagollapalle",
    "ks:ks_pop":29,
    "ks:ks_type":"HABITATION",
    "name:eng_x_preferred":[
        "Kothagollapalle"
    ],
    "wof:name":"Kothagollapalle",
    "wof:placetype":"locality",
    "wof:population":29
},
  "geometry": {"coordinates":[79.11544499999999,13.816294],"type":"Point"}
}