{
  "type": "Feature",
  "properties": {
    "iso:country":"IN",
    "ks:ks_name":"Jai Singhpur Kanak",
    "ks:ks_pop":606,
    "ks:ks_type":"VILLAGE",
    "ks:ks_uagg_main":0,
    "name:eng_x_preferred":[
        "Jai Singhpur Kanak"
    ],
    "wof:name":"Jai Singhpur Kanak",
    "wof:placetype":"neighbourhood",
    "wof:population":606
},
  "geometry": {"coordinates":[79.35085100000001,26.929463],"type":"Point"}
}