{
  "type": "Feature",
  "properties": {
    "gn:admin1_code":"37",
    "gn:admin2_code":"410.0",
    "gn:asciiname":"Bhatia",
    "gn:country_code":"IN",
    "gn:dem":284,
    "gn:feature_class":"P",
    "gn:feature_code":"PPL",
    "gn:name":"Bhatia",
    "gn:population":0,
    "gn:timezone":"Asia/Kolkata",
    "iso:country":"IN",
    "name:deu_x_preferred":[
        "Bhatia"
    ],
    "name:fin_x_preferred":[
        "Bhatia"
    ],
    "name:hin_x_preferred":[
        "\u092d\u093e\u091f\u093f\u092f\u093e"
    ],
    "wof:name":"Bhatia",
    "wof:placetype":"locality"
},
  "geometry": {"coordinates":[82.0368,21.4264],"type":"Point"}
}