{
  "type": "Feature",
  "properties": {
    "gn:admin1_code":"25.0",
    "gn:admin2_code":"610.0",
    "gn:asciiname":"Molakavundanpaalyam",
    "gn:country_code":"IN",
    "gn:dem":272,
    "gn:feature_class":"P",
    "gn:feature_code":"PPL",
    "gn:name":"Molakavundanp\u0101alyam",
    "gn:population":0,
    "gn:timezone":"Asia/Kolkata",
    "iso:country":"IN",
    "wof:name":"Molakavundanpaalyam",
    "wof:placetype":"locality"
},
  "geometry": {"coordinates":[77.43075,11.36772],"type":"Point"}
}