{
  "type": "Feature",
  "properties": {
    "iso:country":"IN",
    "ks:ks_name":"Bauria",
    "ks:ks_pop":2170,
    "ks:ks_type":"VILLAGE",
    "name:eng_x_preferred":[
        "Bauria"
    ],
    "wof:name":"Bauria",
    "wof:placetype":"locality",
    "wof:population":2170
},
  "geometry": {"coordinates":[87.16982400000001,24.524082],"type":"Point"}
}