{
  "type": "Feature",
  "properties": {
    "iso:country":"IN",
    "ks:ks_name":"Ganjhutola",
    "ks:ks_pop":30,
    "ks:ks_type":"HABITATION",
    "name:eng_x_preferred":[
        "Ganjhutola"
    ],
    "wof:name":"Ganjhutola",
    "wof:placetype":"locality",
    "wof:population":30
},
  "geometry": {"coordinates":[85.14687000000001,22.437072],"type":"Point"}
}