{
  "type": "Feature",
  "properties": {
    "iso:country":"IN",
    "ks:ks_name":"Adgadi",
    "ks:ks_pop":323,
    "ks:ks_type":"HABITATION",
    "name:eng_x_preferred":[
        "Adgadi"
    ],
    "wof:name":"Adgadi",
    "wof:placetype":"locality",
    "wof:population":323
},
  "geometry": {"coordinates":[82.184856,20.192098],"type":"Point"}
}