{
  "type": "Feature",
  "properties": {
    "iso:country":"IN",
    "ks:ks_name":"Arikkulam",
    "ks:ks_pop":17143,
    "ks:ks_type":"VILLAGE",
    "name:eng_x_preferred":[
        "Arikkulam"
    ],
    "wof:name":"Arikkulam",
    "wof:placetype":"locality",
    "wof:population":17143
},
  "geometry": {"coordinates":[75.72183099999999,11.4863],"type":"Point"}
}