{
  "type": "Feature",
  "properties": {
    "iso:country":"IN",
    "ks:ks_name":"Pathinaputtu",
    "ks:ks_pop":12,
    "ks:ks_type":"HABITATION",
    "name:eng_x_preferred":[
        "Pathinaputtu"
    ],
    "wof:name":"Pathinaputtu",
    "wof:placetype":"locality",
    "wof:population":12
},
  "geometry": {"coordinates":[82.496786,18.478911],"type":"Point"}
}