{
  "type": "Feature",
  "properties": {
    "gn:admin1_code":"25.0",
    "gn:admin2_code":"607",
    "gn:asciiname":"Gudraippattu",
    "gn:country_code":"IN",
    "gn:dem":55,
    "gn:feature_class":"P",
    "gn:feature_code":"PPL",
    "gn:name":"G\u016bdraippattu",
    "gn:population":0,
    "gn:timezone":"Asia/Kolkata",
    "iso:country":"IN",
    "wof:name":"Gudraippattu",
    "wof:placetype":"neighbourhood"
},
  "geometry": {"coordinates":[79.60274,12.15966],"type":"Point"}
}