{
  "type": "Feature",
  "properties": {
    "gn:admin1_code":"35",
    "gn:admin2_code":"427.0",
    "gn:asciiname":"Arsi",
    "gn:country_code":"IN",
    "gn:dem":517,
    "gn:feature_class":"P",
    "gn:feature_code":"PPL",
    "gn:name":"Arsi",
    "gn:population":0,
    "gn:timezone":"Asia/Kolkata",
    "iso:country":"IN",
    "name:cat_x_preferred":[
        "Arsi"
    ],
    "name:ceb_x_preferred":[
        "Arsi"
    ],
    "name:deu_x_preferred":[
        "Arsi"
    ],
    "name:fra_x_preferred":[
        "Arsi"
    ],
    "name:ita_x_preferred":[
        "Arsi"
    ],
    "name:spa_x_preferred":[
        "Arsi"
    ],
    "name:swe_x_preferred":[
        "Arsi"
    ],
    "wof:name":"Arsi",
    "wof:placetype":"locality"
},
  "geometry": {"coordinates":[79.08152,23.21085],"type":"Point"}
}