{
  "type": "Feature",
  "properties": {
    "iso:country":"IN",
    "ks:ks_name":"Rar",
    "ks:ks_pop":81,
    "ks:ks_type":"HABITATION",
    "name:eng_x_preferred":[
        "Rar"
    ],
    "wof:name":"Rar",
    "wof:placetype":"locality",
    "wof:population":81
},
  "geometry": {"coordinates":[80.69509100000001,24.280637],"type":"Point"}
}