{
  "type": "Feature",
  "properties": {
    "iso:country":"IN",
    "ks:ks_name":"Paraspari",
    "ks:ks_pop":400,
    "ks:ks_type":"HABITATION",
    "name:eng_x_preferred":[
        "Paraspari"
    ],
    "wof:name":"Paraspari",
    "wof:placetype":"locality",
    "wof:population":400
},
  "geometry": {"coordinates":[82.979682,24.380855],"type":"Point"}
}