{
  "type": "Feature",
  "properties": {
    "iso:country":"IN",
    "ks:ks_name":"Mahrahurnar",
    "ks:ks_pop":385,
    "ks:ks_type":"VILLAGE",
    "name:eng_x_preferred":[
        "Mahrahurnar"
    ],
    "wof:name":"Mahrahurnar",
    "wof:placetype":"locality",
    "wof:population":385
},
  "geometry": {"coordinates":[81.397319,18.659201],"type":"Point"}
}