{
  "type": "Feature",
  "properties": {
    "iso:country":"IN",
    "ks:ks_name":"Amakhokhara",
    "ks:ks_pop":538,
    "ks:ks_type":"VILLAGE",
    "name:eng_x_preferred":[
        "Amakhokhara"
    ],
    "wof:name":"Amakhokhara",
    "wof:placetype":"locality",
    "wof:population":538
},
  "geometry": {"coordinates":[82.51731700000001,22.534128],"type":"Point"}
}