{
  "type": "Feature",
  "properties": {
    "iso:country":"IN",
    "ks:ks_alt_nam":"Durg\u0101pras\u0101d",
    "ks:ks_name":"Durgaprasad",
    "ks:ks_pop":866,
    "ks:ks_type":"VILLAGE",
    "name:eng_x_preferred":[
        "Durgaprasad"
    ],
    "name:eng_x_variant":[
        "Durg\u0101pras\u0101d"
    ],
    "wof:name":"Durgaprasad",
    "wof:placetype":"locality",
    "wof:population":866
},
  "geometry": {"coordinates":[84.448814,20.118798],"type":"Point"}
}