{
  "type": "Feature",
  "properties": {
    "iso:country":"IN",
    "ks:ks_name":"Jiav",
    "ks:ks_pop":1550,
    "ks:ks_type":"VILLAGE",
    "name:eng_x_preferred":[
        "Jiav"
    ],
    "wof:name":"Jiav",
    "wof:placetype":"locality",
    "wof:population":1550
},
  "geometry": {"coordinates":[72.82343,21.111349],"type":"Point"}
}