{
  "type": "Feature",
  "properties": {
    "iso:country":"IN",
    "ks:ks_alt_nam":"Tunda chauri",
    "ks:ks_name":"Tunda Chauri",
    "ks:ks_pop":351,
    "ks:ks_type":"HABITATION",
    "name:eng_x_preferred":[
        "Tunda Chauri"
    ],
    "wof:name":"Tunda Chauri",
    "wof:placetype":"locality",
    "wof:population":351
},
  "geometry": {"coordinates":[80.00267700000001,29.678625],"type":"Point"}
}