{
  "type": "Feature",
  "properties": {
    "iso:country":"IN",
    "ks:ks_name":"Chakamanpur",
    "ks:ks_pop":401,
    "ks:ks_type":"VILLAGE",
    "name:eng_x_preferred":[
        "Chakamanpur"
    ],
    "wof:name":"Chakamanpur",
    "wof:placetype":"locality",
    "wof:population":401
},
  "geometry": {"coordinates":[86.402163,23.990577],"type":"Point"}
}