{
  "type": "Feature",
  "properties": {
    "gn:admin1_code":"24",
    "gn:admin2_code":"106.0",
    "gn:asciiname":"Jagirpura",
    "gn:country_code":"IN",
    "gn:dem":169,
    "gn:feature_class":"P",
    "gn:feature_code":"PPL",
    "gn:name":"Jag\u012brpura",
    "gn:population":0,
    "gn:timezone":"Asia/Kolkata",
    "iso:country":"IN",
    "wof:name":"Jagirpura",
    "wof:placetype":"locality"
},
  "geometry": {"coordinates":[78.0147,26.8216],"type":"Point"}
}