{
  "type": "Feature",
  "properties": {
    "gn:admin1_code":"25.0",
    "gn:admin2_code":"631.0",
    "gn:asciiname":"Peddakullu",
    "gn:country_code":"IN",
    "gn:dem":828,
    "gn:feature_class":"P",
    "gn:feature_code":"PPL",
    "gn:name":"Peddak\u016bllu",
    "gn:population":0,
    "gn:timezone":"Asia/Kolkata",
    "iso:country":"IN",
    "wof:name":"Peddakullu",
    "wof:placetype":"locality"
},
  "geometry": {"coordinates":[77.8836,12.74256],"type":"Point"}
}