{
  "type": "Feature",
  "properties": {
    "iso:country":"IN",
    "ks:ks_name":"Pasin Purwa",
    "ks:ks_pop":269,
    "ks:ks_type":"HABITATION",
    "name:eng_x_preferred":[
        "Pasin Purwa"
    ],
    "wof:name":"Pasin Purwa",
    "wof:placetype":"locality",
    "wof:population":269
},
  "geometry": {"coordinates":[81.593035,27.013893],"type":"Point"}
}