{
  "type": "Feature",
  "properties": {
    "iso:country":"IN",
    "ks:ks_name":"Bhainsana Gwalpur Ehatmali",
    "ks:ks_pop":1480,
    "ks:ks_type":"VILLAGE",
    "name:eng_x_preferred":[
        "Bhainsana Gwalpur Ehatmali"
    ],
    "wof:name":"Bhainsana Gwalpur Ehatmali",
    "wof:placetype":"locality",
    "wof:population":1480
},
  "geometry": {"coordinates":[79.79395700000001,28.43578],"type":"Point"}
}