{
  "type": "Feature",
  "properties": {
    "iso:country":"IN",
    "ks:ks_name":"Nadipada",
    "ks:ks_pop":90,
    "ks:ks_type":"HABITATION",
    "name:eng_x_preferred":[
        "Nadipada"
    ],
    "wof:name":"Nadipada",
    "wof:placetype":"locality",
    "wof:population":90
},
  "geometry": {"coordinates":[73.218417,20.145667],"type":"Point"}
}