{
  "type": "Feature",
  "properties": {
    "iso:country":"IN",
    "ks:ks_name":"N Gattakaval",
    "ks:ks_pop":100,
    "ks:ks_type":"HABITATION",
    "name:eng_x_preferred":[
        "N Gattakaval"
    ],
    "wof:name":"N Gattakaval",
    "wof:placetype":"locality",
    "wof:population":100
},
  "geometry": {"coordinates":[76.53463000000001,13.186134],"type":"Point"}
}