{
  "type": "Feature",
  "properties": {
    "iso:country":"IN",
    "ks:ks_name":"Khan Tola",
    "ks:ks_pop":276,
    "ks:ks_type":"HABITATION",
    "ks:ks_uagg_main":0,
    "name:eng_x_preferred":[
        "Khan Tola"
    ],
    "wof:name":"Khan Tola",
    "wof:placetype":"neighbourhood",
    "wof:population":276
},
  "geometry": {"coordinates":[85.28011600000001,26.660977],"type":"Point"}
}