{
  "type": "Feature",
  "properties": {
    "iso:country":"IN",
    "ks:ks_name":"Beeravaripeta",
    "ks:ks_pop":194,
    "ks:ks_type":"HABITATION",
    "name:eng_x_preferred":[
        "Beeravaripeta"
    ],
    "wof:name":"Beeravaripeta",
    "wof:placetype":"locality",
    "wof:population":194
},
  "geometry": {"coordinates":[81.927486,16.678571],"type":"Point"}
}