{
  "type": "Feature",
  "properties": {
    "iso:country":"IN",
    "ks:ks_name":"Fulkumari F V",
    "ks:ks_pop":808,
    "ks:ks_type":"HABITATION",
    "name:eng_x_preferred":[
        "Fulkumari F V"
    ],
    "wof:name":"Fulkumari F V",
    "wof:placetype":"locality",
    "wof:population":808
},
  "geometry": {"coordinates":[89.906746,26.620135],"type":"Point"}
}