{
  "type": "Feature",
  "properties": {
    "iso:country":"IN",
    "ks:ks_name":"Susartali",
    "ks:ks_pop":84,
    "ks:ks_type":"HABITATION",
    "name:eng_x_preferred":[
        "Susartali"
    ],
    "wof:name":"Susartali",
    "wof:placetype":"locality",
    "wof:population":84
},
  "geometry": {"coordinates":[73.652815,16.073156],"type":"Point"}
}