{
  "type": "Feature",
  "properties": {
    "iso:country":"IN",
    "ks:ks_name":"Peruvandal",
    "ks:ks_pop":269,
    "ks:ks_type":"HABITATION",
    "name:eng_x_preferred":[
        "Peruvandal"
    ],
    "wof:name":"Peruvandal",
    "wof:placetype":"locality",
    "wof:population":269
},
  "geometry": {"coordinates":[78.890574,9.730637],"type":"Point"}
}