{
  "type": "Feature",
  "properties": {
    "iso:country":"IN",
    "ks:ks_name":"Yerlakatte",
    "ks:ks_pop":1279,
    "ks:ks_type":"VILLAGE",
    "name:eng_x_preferred":[
        "Yerlakatte"
    ],
    "wof:name":"Yerlakatte",
    "wof:placetype":"locality",
    "wof:population":1279
},
  "geometry": {"coordinates":[76.260327,14.64848],"type":"Point"}
}