{
  "type": "Feature",
  "properties": {
    "iso:country":"IN",
    "ks:ks_name":"Barkheda",
    "ks:ks_pop":368,
    "ks:ks_type":"VILLAGE",
    "name:eng_x_preferred":[
        "Barkheda"
    ],
    "wof:name":"Barkheda",
    "wof:placetype":"locality",
    "wof:population":368
},
  "geometry": {"coordinates":[77.272463,25.011865],"type":"Point"}
}