{
  "type": "Feature",
  "properties": {
    "iso:country":"IN",
    "ks:ks_name":"Tenguriya",
    "ks:ks_pop":265,
    "ks:ks_type":"HABITATION",
    "ks:ks_uagg_main":0,
    "name:eng_x_preferred":[
        "Tenguriya"
    ],
    "wof:name":"Tenguriya",
    "wof:placetype":"neighbourhood",
    "wof:population":265
},
  "geometry": {"coordinates":[79.163156,26.627269],"type":"Point"}
}