{
  "type": "Feature",
  "properties": {
    "iso:country":"IN",
    "ks:ks_alt_nam":"Sult\u0101npur",
    "ks:ks_name":"Sultanpur",
    "ks:ks_pop":1,
    "ks:ks_type":"VILLAGE",
    "name:eng_x_preferred":[
        "Sultanpur"
    ],
    "name:eng_x_variant":[
        "Sult\u0101npur"
    ],
    "name:hin_x_preferred":[
        "\u0938\u0941\u0932\u094d\u0924\u093e\u0928\u092a\u0941\u0930"
    ],
    "wof:name":"Sultanpur",
    "wof:placetype":"locality",
    "wof:population":1
},
  "geometry": {"coordinates":[76.386442,20.949635],"type":"Point"}
}