{
  "type": "Feature",
  "properties": {
    "iso:country":"IN",
    "ks:ks_name":"Daba",
    "ks:ks_pop":216,
    "ks:ks_type":"VILLAGE",
    "name:eng_x_preferred":[
        "Daba"
    ],
    "wof:name":"Daba",
    "wof:placetype":"locality",
    "wof:population":216
},
  "geometry": {"coordinates":[82.660304,18.404076],"type":"Point"}
}