{
  "type": "Feature",
  "properties": {
    "iso:country":"IN",
    "ks:ks_alt_nam":"K\u0101mat",
    "ks:ks_name":"Kamat",
    "ks:ks_pop":6,
    "ks:ks_type":"VILLAGE",
    "name:eng_x_preferred":[
        "Kamat"
    ],
    "name:eng_x_variant":[
        "K\u0101mat"
    ],
    "wof:name":"Kamat",
    "wof:placetype":"locality",
    "wof:population":6
},
  "geometry": {"coordinates":[84.543789,24.200831],"type":"Point"}
}