{
  "type": "Feature",
  "properties": {
    "iso:country":"IN",
    "ks:ks_name":"Semaria Pararia",
    "ks:ks_pop":6506,
    "ks:ks_type":"VILLAGE",
    "ks:ks_uagg_main":0,
    "name:eng_x_preferred":[
        "Semaria Pararia"
    ],
    "wof:name":"Semaria Pararia",
    "wof:placetype":"neighbourhood",
    "wof:population":6506
},
  "geometry": {"coordinates":[84.72573300000001,25.676891],"type":"Point"}
}