{
  "type": "Feature",
  "properties": {
    "iso:country":"IN",
    "ks:ks_name":"Kalki",
    "ks:ks_pop":24,
    "ks:ks_type":"HABITATION",
    "name:eng_x_preferred":[
        "Kalki"
    ],
    "wof:name":"Kalki",
    "wof:placetype":"locality",
    "wof:population":24
},
  "geometry": {"coordinates":[75.119292,13.817666],"type":"Point"}
}