{
  "type": "Feature",
  "properties": {
    "iso:country":"IN",
    "ks:ks_name":"Miadi Khurd",
    "ks:ks_pop":217,
    "ks:ks_type":"VILLAGE",
    "name:eng_x_preferred":[
        "Miadi Khurd"
    ],
    "wof:name":"Miadi Khurd",
    "wof:placetype":"locality",
    "wof:population":217
},
  "geometry": {"coordinates":[74.66853999999999,31.816495],"type":"Point"}
}