{
  "type": "Feature",
  "properties": {
    "gn:admin1_code":"21.0",
    "gn:admin2_code":"396.0",
    "gn:asciiname":"Mallapadar",
    "gn:country_code":"IN",
    "gn:dem":150,
    "gn:feature_class":"P",
    "gn:feature_code":"PPL",
    "gn:name":"Mallapadar",
    "gn:population":0,
    "gn:timezone":"Asia/Kolkata",
    "iso:country":"IN",
    "ks:ks_name":"Malapadar",
    "ks:ks_pop":207,
    "ks:ks_type":"VILLAGE",
    "name:eng_x_preferred":[
        "Malapadar"
    ],
    "name:eng_x_variant":[
        "Mallapadar"
    ],
    "wof:name":"Malapadar",
    "wof:placetype":"locality",
    "wof:population":207
},
  "geometry": {"coordinates":[83.937873,19.156937],"type":"Point"}
}