{
  "type": "Feature",
  "properties": {
    "iso:country":"IN",
    "ks:ks_name":"Limpada",
    "ks:ks_pop":150,
    "ks:ks_type":"HABITATION",
    "name:eng_x_preferred":[
        "Limpada"
    ],
    "wof:name":"Limpada",
    "wof:placetype":"locality",
    "wof:population":150
},
  "geometry": {"coordinates":[82.841095,19.796697],"type":"Point"}
}