{
  "type": "Feature",
  "properties": {
    "iso:country":"IN",
    "ks:ks_name":"Sota",
    "ks:ks_type":"VILLAGE",
    "name:eng_x_preferred":[
        "Sota"
    ],
    "wof:name":"Sota",
    "wof:placetype":"locality"
},
  "geometry": {"coordinates":[84.439966,26.236248],"type":"Point"}
}