{
  "type": "Feature",
  "properties": {
    "iso:country":"IN",
    "ks:ks_name":"Upper Tola",
    "ks:ks_pop":118,
    "ks:ks_type":"HABITATION",
    "name:eng_x_preferred":[
        "Upper Tola"
    ],
    "wof:name":"Upper Tola",
    "wof:placetype":"locality",
    "wof:population":118
},
  "geometry": {"coordinates":[86.29072499999999,24.63971],"type":"Point"}
}