{
  "type": "Feature",
  "properties": {
    "iso:country":"IN",
    "ks:ks_name":"Padmatanr",
    "ks:ks_pop":49,
    "ks:ks_type":"HABITATION",
    "name:eng_x_preferred":[
        "Padmatanr"
    ],
    "wof:name":"Padmatanr",
    "wof:placetype":"locality",
    "wof:population":49
},
  "geometry": {"coordinates":[86.147227,24.580803],"type":"Point"}
}