{
  "type": "Feature",
  "properties": {
    "iso:country":"IN",
    "ks:ks_name":"Nainder Para",
    "ks:ks_pop":333,
    "ks:ks_type":"HABITATION",
    "name:eng_x_preferred":[
        "Nainder Para"
    ],
    "wof:name":"Nainder Para",
    "wof:placetype":"locality",
    "wof:population":333
},
  "geometry": {"coordinates":[91.28413399999999,23.390614],"type":"Point"}
}