{
  "type": "Feature",
  "properties": {
    "iso:country":"IN",
    "ks:ks_alt_nam":"Belk\u0101pi",
    "ks:ks_name":"Belkapi",
    "ks:ks_pop":7979,
    "ks:ks_type":"VILLAGE",
    "ks:ks_uagg_main":0,
    "name:eng_x_preferred":[
        "Belkapi"
    ],
    "name:eng_x_variant":[
        "Belk\u0101pi"
    ],
    "wof:name":"Belkapi",
    "wof:placetype":"neighbourhood",
    "wof:population":7979
},
  "geometry": {"coordinates":[85.64168100000001,24.158943],"type":"Point"}
}