{
  "type": "Feature",
  "properties": {
    "iso:country":"IN",
    "ks:ks_name":"Tola Harni",
    "ks:ks_pop":210,
    "ks:ks_type":"VILLAGE",
    "name:eng_x_preferred":[
        "Tola Harni"
    ],
    "wof:name":"Tola Harni",
    "wof:placetype":"locality",
    "wof:population":210
},
  "geometry": {"coordinates":[86.333084,24.588324],"type":"Point"}
}