{
  "type": "Feature",
  "properties": {
    "iso:country":"IN",
    "ks:ks_name":"Kumbhipalli",
    "ks:ks_pop":460,
    "ks:ks_type":"HABITATION",
    "name:eng_x_preferred":[
        "Kumbhipalli"
    ],
    "wof:name":"Kumbhipalli",
    "wof:placetype":"locality",
    "wof:population":460
},
  "geometry": {"coordinates":[84.611621,20.08948],"type":"Point"}
}