{
  "type": "Feature",
  "properties": {
    "iso:country":"IN",
    "ks:ks_name":"Bherugarh Alias Ramgarh",
    "ks:ks_pop":1246,
    "ks:ks_type":"VILLAGE",
    "name:eng_x_preferred":[
        "Bherugarh Alias Ramgarh"
    ],
    "wof:name":"Bherugarh Alias Ramgarh",
    "wof:placetype":"locality",
    "wof:population":1246
},
  "geometry": {"coordinates":[74.771957,23.148123],"type":"Point"}
}