{
  "type": "Feature",
  "properties": {
    "iso:country":"IN",
    "ks:ks_name":"Gudivadagunta",
    "ks:ks_pop":130,
    "ks:ks_type":"HABITATION",
    "name:eng_x_preferred":[
        "Gudivadagunta"
    ],
    "wof:name":"Gudivadagunta",
    "wof:placetype":"locality",
    "wof:population":130
},
  "geometry": {"coordinates":[80.062883,14.684177],"type":"Point"}
}