{
  "type": "Feature",
  "properties": {
    "gn:admin1_code":"36",
    "gn:admin2_code":"155.0",
    "gn:asciiname":"Lauli",
    "gn:country_code":"IN",
    "gn:dem":133,
    "gn:feature_class":"P",
    "gn:feature_code":"PPL",
    "gn:name":"Lauli",
    "gn:population":0,
    "gn:timezone":"Asia/Kolkata",
    "iso:country":"IN",
    "name:deu_x_preferred":[
        "Lauli"
    ],
    "name:est_x_preferred":[
        "Lauli"
    ],
    "name:fra_x_preferred":[
        "Lauli"
    ],
    "name:hye_x_preferred":[
        "\u053c\u0561\u0578\u0582\u056c\u056b"
    ],
    "name:pol_x_preferred":[
        "Lauli"
    ],
    "name:vol_x_preferred":[
        "Lauli"
    ],
    "wof:name":"Lauli",
    "wof:placetype":"locality"
},
  "geometry": {"coordinates":[80.59336,27.15368],"type":"Point"}
}