{
  "type": "Feature",
  "properties": {
    "iso:country":"IN",
    "ks:ks_name":"Kanti (62)",
    "ks:ks_pop":46,
    "ks:ks_type":"HABITATION",
    "name:eng_x_preferred":[
        "Kanti (62)"
    ],
    "wof:name":"Kanti (62)",
    "wof:placetype":"locality",
    "wof:population":46
},
  "geometry": {"coordinates":[81.328485,24.956037],"type":"Point"}
}