{
  "type": "Feature",
  "properties": {
    "gn:admin1_code":"38",
    "gn:admin2_code":"346.0",
    "gn:asciiname":"Baliari",
    "gn:country_code":"IN",
    "gn:dem":143,
    "gn:feature_class":"P",
    "gn:feature_code":"PPL",
    "gn:name":"Bali\u0101ri",
    "gn:population":0,
    "gn:timezone":"Asia/Kolkata",
    "iso:country":"IN",
    "name:bih_x_preferred":[
        "\u092c\u0932\u093f\u092f\u093e\u0930\u0940"
    ],
    "name:bpy_x_preferred":[
        "\u09ac\u09be\u09b2\u09bf\u09af\u09bc\u09be\u09b0\u09bf"
    ],
    "name:ita_x_preferred":[
        "Baliari"
    ],
    "name:msa_x_preferred":[
        "Baliari"
    ],
    "name:new_x_preferred":[
        "\u092c\u0932\u093f\u092f\u093e\u0930\u0940"
    ],
    "name:nld_x_preferred":[
        "Baliari"
    ],
    "name:por_x_preferred":[
        "Baliari"
    ],
    "name:vie_x_preferred":[
        "Baliari"
    ],
    "name:zho_x_preferred":[
        "\u5df4\u5229\u4e9a\u91cc"
    ],
    "wof:name":"Baliari",
    "wof:placetype":"locality"
},
  "geometry": {"coordinates":[83.80685,24.49184],"type":"Point"}
}