{
  "type": "Feature",
  "properties": {
    "gn:admin1_code":"12.0",
    "gn:admin2_code":"021",
    "gn:asciiname":"Gasan",
    "gn:country_code":"IN",
    "gn:dem":501,
    "gn:feature_class":"P",
    "gn:feature_code":"PPL",
    "gn:name":"Gas\u0101n",
    "gn:population":0,
    "gn:timezone":"Asia/Kolkata",
    "iso:country":"IN",
    "name:kat_x_preferred":[
        "\u10d2\u10d0\u10e1\u10d0\u10dc\u10d8"
    ],
    "wof:name":"Gasan",
    "wof:placetype":"locality"
},
  "geometry": {"coordinates":[74.8073,32.99596],"type":"Point"}
}