{
  "type": "Feature",
  "properties": {
    "gn:admin1_code":"24.0",
    "gn:admin2_code":"109.0",
    "gn:asciiname":"Biharipura",
    "gn:country_code":"IN",
    "gn:dem":293,
    "gn:feature_class":"P",
    "gn:feature_code":"PPL",
    "gn:name":"Bih\u0101r\u012bpura",
    "gn:population":0,
    "gn:timezone":"Asia/Kolkata",
    "iso:country":"IN",
    "name:ara_x_preferred":[
        "\u0628\u064a\u0647\u0627\u0631\u064a\u0628\u0648\u0631\u0627"
    ],
    "name:ben_bn_x_preferred":[
        "\u09ac\u09bf\u09b9\u09be\u09b0\u09c0\u09aa\u09c1\u09b0\u09be"
    ],
    "name:ben_in_x_preferred":[
        "\u09ac\u09bf\u09b9\u09be\u09b0\u09c0\u09aa\u09c1\u09b0\u09be"
    ],
    "name:guj_x_preferred":[
        "\u0aac\u0abf\u0ab9\u0abe\u0ab0\u0ac0\u0aaa\u0ac1\u0ab0\u0abe"
    ],
    "name:hin_x_preferred":[
        "\u092c\u093f\u0939\u093e\u0930\u0940\u092a\u0941\u0930\u093e"
    ],
    "name:kan_x_preferred":[
        "\u0cac\u0cbf\u0cb9\u0cbe\u0cb0\u0cbf\u0caa\u0cc1\u0cb0"
    ],
    "name:mal_x_preferred":[
        "\u0d2c\u0d3f\u0d39\u0d3e\u0d30\u0d3f\u0d2a\u0d41\u0d30"
    ],
    "name:mar_x_preferred":[
        "\u092c\u093f\u0939\u093e\u0930\u0940\u092a\u0941\u0930\u093e"
    ],
    "name:pan_x_preferred":[
        "\u0a2c\u0a3f\u0a39\u0a3e\u0a30\u0a40\u0a2a\u0a41\u0a30\u0a3e"
    ],
    "name:tam_x_preferred":[
        "\u0baa\u0bbf\u0b95\u0bbe\u0bb0\u0bbf\u0baa\u0bc1\u0bb0\u0bbe"
    ],
    "name:tel_x_preferred":[
        "\u0c2c\u0c48\u0c39\u0c30\u0c3f\u0c2a\u0c41\u0c30\u0c3e"
    ],
    "name:urd_x_preferred":[
        "\u0628\u06c1\u0627\u0631\u06cc \u067e\u0648\u0631\u06c1"
    ],
    "wof:name":"Biharipura",
    "wof:placetype":"locality"
},
  "geometry": {"coordinates":[76.34163000000002,26.52602000000001],"type":"Point"}
}