{
  "type": "Feature",
  "properties": {
    "iso:country":"IN",
    "ks:ks_name":"Dokribehari",
    "ks:ks_pop":129,
    "ks:ks_type":"HABITATION",
    "name:eng_x_preferred":[
        "Dokribehari"
    ],
    "wof:name":"Dokribehari",
    "wof:placetype":"locality",
    "wof:population":129
},
  "geometry": {"coordinates":[83.37239599999999,22.441824],"type":"Point"}
}