{
  "type": "Feature",
  "properties": {
    "iso:country":"IN",
    "ks:ks_name":"Dakshin Angad Baria",
    "ks:ks_pop":1426,
    "ks:ks_type":"VILLAGE",
    "name:eng_x_preferred":[
        "Dakshin Angad Baria"
    ],
    "wof:name":"Dakshin Angad Baria",
    "wof:placetype":"locality",
    "wof:population":1426
},
  "geometry": {"coordinates":[88.619101,22.291984],"type":"Point"}
}