{
  "type": "Feature",
  "properties": {
    "gn:admin1_code":"39.0",
    "gn:admin2_code":"66.0",
    "gn:asciiname":"Amtana",
    "gn:country_code":"IN",
    "gn:dem":1390,
    "gn:feature_class":"P",
    "gn:feature_code":"PPL",
    "gn:name":"\u0100mtana",
    "gn:population":0,
    "gn:timezone":"Asia/Kolkata",
    "iso:country":"IN",
    "ks:ks_alt_nam":"\u0100mtana",
    "ks:ks_name":"Amtana",
    "ks:ks_type":"VILLAGE",
    "name:eng_x_preferred":[
        "Amtana"
    ],
    "name:eng_x_variant":[
        "\u0100mtana"
    ],
    "wof:name":"Amtana",
    "wof:placetype":"locality"
},
  "geometry": {"coordinates":[79.38968800000001,29.360658],"type":"Point"}
}