{
  "type": "Feature",
  "properties": {
    "gn:admin1_code":"37",
    "gn:admin2_code":"406.0",
    "gn:asciiname":"Bagharra",
    "gn:country_code":"IN",
    "gn:dem":558,
    "gn:feature_class":"P",
    "gn:feature_code":"PPL",
    "gn:name":"Bagharra",
    "gn:population":0,
    "gn:timezone":"Asia/Kolkata",
    "iso:country":"IN",
    "ks:ks_name":"Bagharra",
    "ks:ks_type":"VILLAGE",
    "name:eng_x_preferred":[
        "Bagharra"
    ],
    "wof:name":"Bagharra",
    "wof:placetype":"locality"
},
  "geometry": {"coordinates":[82.06710099999999,22.87682],"type":"Point"}
}