{
  "type": "Feature",
  "properties": {
    "gn:admin1_code":"12.0",
    "gn:admin2_code":"22.0",
    "gn:asciiname":"Sri Partabsinghpura",
    "gn:country_code":"IN",
    "gn:dem":290,
    "gn:feature_class":"P",
    "gn:feature_code":"PPL",
    "gn:name":"Sri Part\u0101bsinghpura",
    "gn:population":0,
    "gn:timezone":"Asia/Kolkata",
    "iso:country":"IN",
    "wof:name":"Sri Partabsinghpura",
    "wof:placetype":"locality"
},
  "geometry": {"coordinates":[74.91341,32.49292],"type":"Point"}
}