{
  "type": "Feature",
  "properties": {
    "iso:country":"IN",
    "ks:ks_name":"Durga Pur",
    "ks:ks_pop":320,
    "ks:ks_type":"VILLAGE",
    "name:eng_x_preferred":[
        "Durga Pur"
    ],
    "wof:name":"Durga Pur",
    "wof:placetype":"locality",
    "wof:population":320
},
  "geometry": {"coordinates":[87.28488400000001,22.090584],"type":"Point"}
}