{
  "type": "Feature",
  "properties": {
    "iso:country":"IN",
    "ks:ks_name":"Shirkewadi",
    "ks:ks_pop":115,
    "ks:ks_type":"HABITATION",
    "name:eng_x_preferred":[
        "Shirkewadi"
    ],
    "wof:name":"Shirkewadi",
    "wof:placetype":"locality",
    "wof:population":115
},
  "geometry": {"coordinates":[73.44030600000001,17.521231],"type":"Point"}
}