{
  "type": "Feature",
  "properties": {
    "iso:country":"IN",
    "ks:ks_alt_nam":"JUNGAL BLOCK",
    "ks:ks_name":"Jungal Block",
    "ks:ks_pop":590,
    "ks:ks_type":"HABITATION",
    "name:eng_x_preferred":[
        "Jungal Block"
    ],
    "wof:name":"Jungal Block",
    "wof:placetype":"locality",
    "wof:population":590
},
  "geometry": {"coordinates":[92.497626,24.478639],"type":"Point"}
}