{
  "type": "Feature",
  "properties": {
    "gn:admin1_code":"37.0",
    "gn:admin2_code":"413.0",
    "gn:asciiname":"Koliyari",
    "gn:country_code":"IN",
    "gn:dem":493,
    "gn:feature_class":"P",
    "gn:feature_code":"PPL",
    "gn:name":"Koliyari",
    "gn:population":0,
    "gn:timezone":"Asia/Kolkata",
    "iso:country":"IN",
    "ks:ks_name":"Koliyari",
    "ks:ks_pop":480,
    "ks:ks_type":"VILLAGE",
    "name:eng_x_preferred":[
        "Koliyari"
    ],
    "wof:name":"Koliyari",
    "wof:placetype":"locality",
    "wof:population":480
},
  "geometry": {"coordinates":[81.317339,20.245146],"type":"Point"}
}