{
  "type": "Feature",
  "properties": {
    "gn:admin1_code":"10.0",
    "gn:admin2_code":"85.0",
    "gn:asciiname":"Fatehpuri Pipa",
    "gn:country_code":"IN",
    "gn:dem":244,
    "gn:feature_class":"P",
    "gn:feature_code":"PPL",
    "gn:name":"Fatehpuri P\u012bpa",
    "gn:population":0,
    "gn:timezone":"Asia/Kolkata",
    "iso:country":"IN",
    "ks:ks_alt_nam":"Fatehpuri P\u012bpa",
    "ks:ks_name":"Fatehpuri Pipa",
    "ks:ks_type":"VILLAGE",
    "ks:ks_uagg_main":0,
    "name:eng_x_preferred":[
        "Fatehpuri Pipa"
    ],
    "name:eng_x_variant":[
        "Fatehpuri P\u012bpa"
    ],
    "wof:name":"Fatehpuri Pipa",
    "wof:placetype":"neighbourhood"
},
  "geometry": {"coordinates":[76.681917,28.182848],"type":"Point"}
}