{
  "type": "Feature",
  "properties": {
    "gn:admin1_code":"24",
    "gn:admin2_code":"110.0",
    "gn:asciiname":"Chawan ka Mand",
    "gn:country_code":"IN",
    "gn:dem":378,
    "gn:feature_class":"P",
    "gn:feature_code":"PPL",
    "gn:name":"Ch\u0101wan ka Mand",
    "gn:population":0,
    "gn:timezone":"Asia/Kolkata",
    "iso:country":"IN",
    "ks:ks_name":"Chawand Ka Mand",
    "ks:ks_pop":2558,
    "ks:ks_type":"VILLAGE",
    "ks:ks_uagg_main":0,
    "name:eng_x_preferred":[
        "Chawand Ka Mand"
    ],
    "wof:name":"Chawand Ka Mand",
    "wof:placetype":"locality",
    "wof:population":2558
},
  "geometry": {"coordinates":[75.916342,26.972735],"type":"Point"}
}