{
  "type": "Feature",
  "properties": {
    "iso:country":"IN",
    "ks:ks_name":"Tetrail",
    "ks:ks_pop":820,
    "ks:ks_type":"VILLAGE",
    "ks:ks_uagg_main":0,
    "name:eng_x_preferred":[
        "Tetrail"
    ],
    "wof:name":"Tetrail",
    "wof:placetype":"neighbourhood",
    "wof:population":820
},
  "geometry": {"coordinates":[88.594291,25.381802],"type":"Point"}
}