{
  "type": "Feature",
  "properties": {
    "gn:admin1_code":"2.0",
    "gn:admin2_code":"547.0",
    "gn:asciiname":"Marikunta",
    "gn:country_code":"IN",
    "gn:dem":81,
    "gn:feature_class":"P",
    "gn:feature_code":"PPL",
    "gn:name":"Marikunta",
    "gn:population":0,
    "gn:timezone":"Asia/Kolkata",
    "iso:country":"IN",
    "ks:ks_name":"Marri Kunta",
    "ks:ks_pop":291,
    "ks:ks_type":"HABITATION",
    "name:eng_x_preferred":[
        "Marri Kunta"
    ],
    "name:eng_x_variant":[
        "Marikunta"
    ],
    "wof:name":"Marri Kunta",
    "wof:placetype":"locality",
    "wof:population":291
},
  "geometry": {"coordinates":[80.887621,16.788573],"type":"Point"}
}