{
  "type": "Feature",
  "properties": {
    "iso:country":"IN",
    "ks:ks_name":"Chauraha",
    "ks:ks_pop":42,
    "ks:ks_type":"HABITATION",
    "ks:ks_uagg_main":0,
    "name:eng_x_preferred":[
        "Chauraha"
    ],
    "wof:name":"Chauraha",
    "wof:placetype":"neighbourhood",
    "wof:population":42
},
  "geometry": {"coordinates":[83.185378,26.580703],"type":"Point"}
}