{
  "type": "Feature",
  "properties": {
    "gn:admin1_code":"16",
    "gn:admin2_code":"508.0",
    "gn:asciiname":"Khardi",
    "gn:country_code":"IN",
    "gn:dem":241,
    "gn:feature_class":"P",
    "gn:feature_code":"PPL",
    "gn:name":"Kh\u0101rdi",
    "gn:population":0,
    "gn:timezone":"Asia/Kolkata",
    "iso:country":"IN",
    "ks:ks_alt_nam":"Kh\u0101rdi",
    "ks:ks_name":"Khardi",
    "ks:ks_pop":57,
    "ks:ks_type":"VILLAGE",
    "name:eng_x_preferred":[
        "Khardi"
    ],
    "name:eng_x_variant":[
        "Kh\u0101rdi"
    ],
    "wof:name":"Khardi",
    "wof:placetype":"locality",
    "wof:population":57
},
  "geometry": {"coordinates":[80.193504,20.388429],"type":"Point"}
}