{
  "type": "Feature",
  "properties": {
    "iso:country":"IN",
    "ks:ks_name":"Sagjuriya",
    "ks:ks_pop":992,
    "ks:ks_type":"VILLAGE",
    "name:eng_x_preferred":[
        "Sagjuriya"
    ],
    "wof:name":"Sagjuriya",
    "wof:placetype":"locality",
    "wof:population":992
},
  "geometry": {"coordinates":[87.002551,23.903631],"type":"Point"}
}