{
  "type": "Feature",
  "properties": {
    "iso:country":"IN",
    "ks:ks_alt_nam":"Milakpur G\u016bjar",
    "ks:ks_name":"Milakpur Gujar",
    "ks:ks_type":"VILLAGE",
    "ks:ks_uagg_main":0,
    "name:eng_x_preferred":[
        "Milakpur Gujar"
    ],
    "name:eng_x_variant":[
        "Milakpur G\u016bjar"
    ],
    "wof:name":"Milakpur Gujar",
    "wof:placetype":"neighbourhood"
},
  "geometry": {"coordinates":[76.826324,28.197903],"type":"Point"}
}