{
  "type": "Feature",
  "properties": {
    "gn:admin1_code":"16.0",
    "gn:admin2_code":"499.0",
    "gn:asciiname":"Tekvada Budrukh",
    "gn:country_code":"IN",
    "gn:dem":293,
    "gn:feature_class":"P",
    "gn:feature_code":"PPL",
    "gn:name":"Tekv\u0101da Budrukh",
    "gn:population":0,
    "gn:timezone":"Asia/Kolkata",
    "iso:country":"IN",
    "wof:name":"Tekvada Budrukh",
    "wof:placetype":"neighbourhood"
},
  "geometry": {"coordinates":[75.06516000000001,20.59092],"type":"Point"}
}