{
  "type": "Feature",
  "properties": {
    "iso:country":"IN",
    "ks:ks_alt_nam":"pinnalankottai",
    "ks:ks_name":"Pinnalankottai",
    "ks:ks_pop":197,
    "ks:ks_type":"HABITATION",
    "name:eng_x_preferred":[
        "Pinnalankottai"
    ],
    "wof:name":"Pinnalankottai",
    "wof:placetype":"locality",
    "wof:population":197
},
  "geometry": {"coordinates":[78.743545,9.820265],"type":"Point"}
}