{
  "type": "Feature",
  "properties": {
    "gn:admin1_code":"19.0",
    "gn:admin2_code":"574.0",
    "gn:asciiname":"Timmanahalli",
    "gn:country_code":"IN",
    "gn:dem":964,
    "gn:feature_class":"P",
    "gn:feature_code":"PPL",
    "gn:name":"Timmanahalli",
    "gn:population":0,
    "gn:timezone":"Asia/Kolkata",
    "iso:country":"IN",
    "ks:ks_name":"Thimmanahalli",
    "ks:ks_pop":144,
    "ks:ks_type":"HABITATION",
    "name:eng_x_preferred":[
        "Thimmanahalli"
    ],
    "name:eng_x_variant":[
        "Timmanahalli"
    ],
    "wof:name":"Thimmanahalli",
    "wof:placetype":"locality",
    "wof:population":144
},
  "geometry": {"coordinates":[76.22393700000001,13.10692],"type":"Point"}
}