{
  "type": "Feature",
  "properties": {
    "iso:country":"IN",
    "ks:ks_name":"Miyan Tola",
    "ks:ks_pop":440,
    "ks:ks_type":"HABITATION",
    "ks:ks_uagg_main":0,
    "name:eng_x_preferred":[
        "Miyan Tola"
    ],
    "wof:name":"Miyan Tola",
    "wof:placetype":"neighbourhood",
    "wof:population":440
},
  "geometry": {"coordinates":[84.131561,26.949933],"type":"Point"}
}