{
  "type": "Feature",
  "properties": {
    "iso:country":"IN",
    "ks:ks_name":"Khairana",
    "ks:ks_pop":46,
    "ks:ks_type":"VILLAGE",
    "name:eng_x_preferred":[
        "Khairana"
    ],
    "wof:name":"Khairana",
    "wof:placetype":"locality",
    "wof:population":46
},
  "geometry": {"coordinates":[78.35181300000001,29.975196],"type":"Point"}
}