{
  "type": "Feature",
  "properties": {
    "iso:country":"IN",
    "ks:ks_name":"Anjaikana",
    "ks:ks_pop":183,
    "ks:ks_type":"VILLAGE",
    "name:eng_x_preferred":[
        "Anjaikana"
    ],
    "wof:name":"Anjaikana",
    "wof:placetype":"locality",
    "wof:population":183
},
  "geometry": {"coordinates":[84.11713,19.13237],"type":"Point"}
}