{
  "type": "Feature",
  "properties": {
    "gn:admin1_code":"11",
    "gn:admin2_code":"33.0",
    "gn:asciiname":"Gewas",
    "gn:country_code":"IN",
    "gn:dem":2231,
    "gn:feature_class":"P",
    "gn:feature_code":"PPL",
    "gn:name":"Gew\u0101s",
    "gn:population":0,
    "gn:timezone":"Asia/Kolkata",
    "iso:country":"IN",
    "wof:name":"Gewas",
    "wof:placetype":"locality"
},
  "geometry": {"coordinates":[77.82759,31.17509],"type":"Point"}
}