{
  "type": "Feature",
  "properties": {
    "gn:admin1_code":"19.0",
    "gn:admin2_code":"574.0",
    "gn:asciiname":"Mallenahalli",
    "gn:country_code":"IN",
    "gn:dem":897,
    "gn:feature_class":"P",
    "gn:feature_code":"PPL",
    "gn:name":"Mallenahalli",
    "gn:population":0,
    "gn:timezone":"Asia/Kolkata",
    "iso:country":"IN",
    "ks:ks_name":"Mallenahalli",
    "ks:ks_pop":210,
    "ks:ks_type":"VILLAGE",
    "name:eng_x_preferred":[
        "Mallenahalli"
    ],
    "wof:name":"Mallenahalli",
    "wof:placetype":"locality",
    "wof:population":210
},
  "geometry": {"coordinates":[76.019198,12.779577],"type":"Point"}
}