{
  "type": "Feature",
  "properties": {
    "gn:admin1_code":"36",
    "gn:admin2_code":"154.0",
    "gn:asciiname":"Dhirpur",
    "gn:country_code":"IN",
    "gn:dem":134,
    "gn:feature_class":"P",
    "gn:feature_code":"PPL",
    "gn:name":"Dhirpur",
    "gn:population":0,
    "gn:timezone":"Asia/Kolkata",
    "iso:country":"IN",
    "name:ara_x_preferred":[
        "\u062f\u064a\u0631\u0628\u0648\u0631"
    ],
    "name:ben_bn_x_preferred":[
        "\u09a7\u09bf\u09b0\u09aa\u09c1\u09b0"
    ],
    "name:ben_in_x_preferred":[
        "\u09a7\u09bf\u09b0\u09aa\u09c1\u09b0"
    ],
    "name:guj_x_preferred":[
        "\u0aa7\u0abf\u0ab0\u0aaa\u0ac1\u0ab0"
    ],
    "name:hin_x_preferred":[
        "\u0927\u0940\u0930\u092a\u0941\u0930"
    ],
    "name:kan_x_preferred":[
        "\u0ca7\u0cc0\u0cb0\u0ccd"
    ],
    "name:mal_x_preferred":[
        "\u0d26\u0d3f\u0d7c\u0d2a\u0d42\u0d7c"
    ],
    "name:mar_x_preferred":[
        "\u0927\u0940\u0930\u092a\u0942\u0930"
    ],
    "name:pan_x_preferred":[
        "\u0a27\u0a40\u0a30\u0a2a\u0a41\u0a30"
    ],
    "name:tam_x_preferred":[
        "\u0ba4\u0bbf\u0bb0\u0bcd\u0baa\u0bc2\u0bb0\u0bcd"
    ],
    "name:tel_x_preferred":[
        "\u0c27\u0c3f\u0c30\u0c4d"
    ],
    "name:urd_x_preferred":[
        "\u062f\u06be\u06cc\u0631 \u067e\u0648\u0631"
    ],
    "wof:name":"Dhirpur",
    "wof:placetype":"locality"
},
  "geometry": {"coordinates":[81.00923,27.28091],"type":"Point"}
}