{
  "type": "Feature",
  "properties": {
    "iso:country":"IN",
    "ks:ks_name":"Machchavanipalem",
    "ks:ks_pop":1053,
    "ks:ks_type":"VILLAGE",
    "ks:ks_uagg_main":0,
    "name:eng_x_preferred":[
        "Machchavanipalem"
    ],
    "wof:name":"Machchavanipalem",
    "wof:placetype":"neighbourhood",
    "wof:population":1053
},
  "geometry": {"coordinates":[82.72677,17.762976],"type":"Point"}
}