{
  "type": "Feature",
  "properties": {
    "iso:country":"IN",
    "ks:ks_name":"Beloor",
    "ks:ks_pop":3621,
    "ks:ks_type":"VILLAGE",
    "name:eng_x_preferred":[
        "Beloor"
    ],
    "wof:name":"Beloor",
    "wof:placetype":"locality",
    "wof:population":3621
},
  "geometry": {"coordinates":[74.74373300000001,13.540621],"type":"Point"}
}