{
  "type": "Feature",
  "properties": {
    "iso:country":"IN",
    "ks:ks_name":"Ravwadi",
    "ks:ks_pop":26,
    "ks:ks_type":"HABITATION",
    "name:eng_x_preferred":[
        "Ravwadi"
    ],
    "wof:name":"Ravwadi",
    "wof:placetype":"locality",
    "wof:population":26
},
  "geometry": {"coordinates":[73.73305499999999,16.590416],"type":"Point"}
}