{
  "type": "Feature",
  "properties": {
    "iso:country":"IN",
    "ks:ks_name":"Hospitalpara",
    "ks:ks_pop":1030,
    "ks:ks_type":"HABITATION",
    "name:eng_x_preferred":[
        "Hospitalpara"
    ],
    "wof:name":"Hospitalpara",
    "wof:placetype":"locality",
    "wof:population":1030
},
  "geometry": {"coordinates":[88.273841,22.925597],"type":"Point"}
}