{
  "type": "Feature",
  "properties": {
    "iso:country":"IN",
    "ks:ks_name":"Chandal Dilha",
    "ks:ks_pop":92,
    "ks:ks_type":"HABITATION",
    "ks:ks_uagg_main":0,
    "name:eng_x_preferred":[
        "Chandal Dilha"
    ],
    "wof:name":"Chandal Dilha",
    "wof:placetype":"neighbourhood",
    "wof:population":92
},
  "geometry": {"coordinates":[84.490544,24.404397],"type":"Point"}
}