{
  "type": "Feature",
  "properties": {
    "iso:country":"IN",
    "ks:ks_name":"Bandiyasemal",
    "ks:ks_pop":337,
    "ks:ks_type":"HABITATION",
    "name:eng_x_preferred":[
        "Bandiyasemal"
    ],
    "wof:name":"Bandiyasemal",
    "wof:placetype":"locality",
    "wof:population":337
},
  "geometry": {"coordinates":[74.604354,21.766567],"type":"Point"}
}