{
  "type": "Feature",
  "properties": {
    "iso:country":"IN",
    "ks:ks_name":"Desu Mazra",
    "ks:ks_type":"VILLAGE",
    "ks:ks_uagg_main":0,
    "name:eng_x_preferred":[
        "Desu Mazra"
    ],
    "wof:name":"Desu Mazra",
    "wof:placetype":"neighbourhood"
},
  "geometry": {"coordinates":[76.670288,30.743896],"type":"Point"}
}