{
  "type": "Feature",
  "properties": {
    "iso:country":"IN",
    "ks:ks_name":"Helar Chak",
    "ks:ks_pop":496,
    "ks:ks_type":"VILLAGE",
    "name:eng_x_preferred":[
        "Helar Chak"
    ],
    "wof:name":"Helar Chak",
    "wof:placetype":"locality",
    "wof:population":496
},
  "geometry": {"coordinates":[87.80293399999999,22.809475],"type":"Point"}
}