{
  "type": "Feature",
  "properties": {
    "iso:country":"IN",
    "ks:ks_name":"Krishna Sagar",
    "ks:ks_pop":1251,
    "ks:ks_type":"VILLAGE",
    "name:eng_x_preferred":[
        "Krishna Sagar"
    ],
    "wof:name":"Krishna Sagar",
    "wof:placetype":"locality",
    "wof:population":1251
},
  "geometry": {"coordinates":[80.793295,17.705414],"type":"Point"}
}