{
  "type": "Feature",
  "properties": {
    "iso:country":"IN",
    "ks:ks_name":"Ostapal",
    "ks:ks_pop":130,
    "ks:ks_type":"VILLAGE",
    "name:eng_x_preferred":[
        "Ostapal"
    ],
    "wof:name":"Ostapal",
    "wof:placetype":"locality",
    "wof:population":130
},
  "geometry": {"coordinates":[85.219857,20.515032],"type":"Point"}
}