{
  "type": "Feature",
  "properties": {
    "iso:country":"IN",
    "ks:ks_name":"Nachitola",
    "ks:ks_pop":57,
    "ks:ks_type":"VILLAGE",
    "name:eng_x_preferred":[
        "Nachitola"
    ],
    "wof:name":"Nachitola",
    "wof:placetype":"locality",
    "wof:population":57
},
  "geometry": {"coordinates":[85.474468,23.05219],"type":"Point"}
}