{
  "type": "Feature",
  "properties": {
    "iso:country":"IN",
    "ks:ks_alt_nam":"D.Halli",
    "ks:ks_name":"D.halli",
    "ks:ks_pop":195,
    "ks:ks_type":"HABITATION",
    "name:eng_x_preferred":[
        "D.halli"
    ],
    "wof:name":"D.halli",
    "wof:placetype":"locality",
    "wof:population":195
},
  "geometry": {"coordinates":[76.04432,13.16448],"type":"Point"}
}