{
  "type": "Feature",
  "properties": {
    "gn:admin1_code":"35.0",
    "gn:admin2_code":"439.0",
    "gn:asciiname":"Kaneriya",
    "gn:country_code":"IN",
    "gn:dem":585,
    "gn:feature_class":"P",
    "gn:feature_code":"PPL",
    "gn:name":"Kaneriya",
    "gn:population":0,
    "gn:timezone":"Asia/Kolkata",
    "iso:country":"IN",
    "wof:name":"Kaneriya",
    "wof:placetype":"locality"
},
  "geometry": {"coordinates":[75.63467,22.36179],"type":"Point"}
}