{
  "type": "Feature",
  "properties": {
    "iso:country":"IN",
    "ks:ks_name":"Phulwariya Tikari",
    "ks:ks_pop":182,
    "ks:ks_type":"HABITATION",
    "name:eng_x_preferred":[
        "Phulwariya Tikari"
    ],
    "wof:name":"Phulwariya Tikari",
    "wof:placetype":"locality",
    "wof:population":182
},
  "geometry": {"coordinates":[82.312533,25.188158],"type":"Point"}
}