{
  "type": "Feature",
  "properties": {
    "iso:country":"IN",
    "ks:ks_name":"Honnemarada Halli Bharathipura",
    "ks:ks_pop":95,
    "ks:ks_type":"HABITATION",
    "name:eng_x_preferred":[
        "Honnemarada Halli Bharathipura"
    ],
    "wof:name":"Honnemarada Halli Bharathipura",
    "wof:placetype":"locality",
    "wof:population":95
},
  "geometry": {"coordinates":[76.297999,12.171185],"type":"Point"}
}