{
  "type": "Feature",
  "properties": {
    "iso:country":"IN",
    "ks:ks_name":"Rampur",
    "ks:ks_pop":1517,
    "ks:ks_type":"VILLAGE",
    "name:eng_x_preferred":[
        "Rampur"
    ],
    "name:hin_x_preferred":[
        "\u0930\u093e\u092e\u092a\u0941\u0930"
    ],
    "wof:name":"Rampur",
    "wof:placetype":"locality",
    "wof:population":1517
},
  "geometry": {"coordinates":[76.173117,31.290079],"type":"Point"}
}