{
  "type": "Feature",
  "properties": {
    "iso:country":"IN",
    "ks:ks_name":"Kakodunga No 1",
    "ks:ks_pop":1000,
    "ks:ks_type":"HABITATION",
    "name:eng_x_preferred":[
        "Kakodunga No 1"
    ],
    "wof:name":"Kakodunga No 1",
    "wof:placetype":"locality",
    "wof:population":1000
},
  "geometry": {"coordinates":[94.05907500000001,26.633086],"type":"Point"}
}