{
  "type": "Feature",
  "properties": {
    "gn:admin1_code":"12.0",
    "gn:admin2_code":"1.0",
    "gn:asciiname":"Gagal",
    "gn:country_code":"IN",
    "gn:dem":1950,
    "gn:feature_class":"P",
    "gn:feature_code":"PPL",
    "gn:name":"G\u0101gal",
    "gn:population":0,
    "gn:timezone":"Asia/Kolkata",
    "iso:country":"IN",
    "name:ceb_x_preferred":[
        "G\u0101gal"
    ],
    "name:ckb_x_preferred":[
        "\u06af\u0627\u06af\u0644"
    ],
    "name:fas_x_preferred":[
        "\u06af\u0627\u06af\u0644"
    ],
    "name:ita_x_preferred":[
        "Gagal"
    ],
    "name:swe_x_preferred":[
        "G\u0101gal"
    ],
    "wof:name":"Gagal",
    "wof:placetype":"locality"
},
  "geometry": {"coordinates":[74.39755,34.5603],"type":"Point"}
}