{
  "type": "Feature",
  "properties": {
    "gn:admin1_code":"21",
    "gn:admin2_code":"384.0",
    "gn:asciiname":"Nuahata",
    "gn:country_code":"IN",
    "gn:dem":97,
    "gn:feature_class":"P",
    "gn:feature_code":"PPL",
    "gn:name":"N\u016b\u0101hat\u0101",
    "gn:population":0,
    "gn:timezone":"Asia/Kolkata",
    "iso:country":"IN",
    "ks:ks_name":"Nuahata",
    "ks:ks_pop":4696,
    "ks:ks_type":"URBAN",
    "name:eng_x_preferred":[
        "Nuahata"
    ],
    "wof:name":"Nuahata",
    "wof:placetype":"locality",
    "wof:population":4696
},
  "geometry": {"coordinates":[85.230035,20.831191],"type":"Point"}
}