{
  "type": "Feature",
  "properties": {
    "gn:admin1_code":"21",
    "gn:admin2_code":"384.0",
    "gn:asciiname":"Nuahata",
    "gn:country_code":"IN",
    "gn:dem":97,
    "gn:feature_class":"P",
    "gn:feature_code":"PPL",
    "gn:name":"N\u016b\u0101hat\u0101",
    "gn:population":0,
    "gn:timezone":"Asia/Kolkata",
    "iso:country":"IN",
    "wof:name":"Nuahata",
    "wof:placetype":"locality"
},
  "geometry": {"coordinates":[85.23411,20.83586],"type":"Point"}
}