{
  "type": "Feature",
  "properties": {
    "gn:admin1_code":"34.0",
    "gn:admin2_code":"222.0",
    "gn:asciiname":"Koria",
    "gn:country_code":"IN",
    "gn:dem":50,
    "gn:feature_class":"P",
    "gn:feature_code":"PPL",
    "gn:name":"Koria",
    "gn:population":0,
    "gn:timezone":"Asia/Kolkata",
    "iso:country":"IN",
    "ks:ks_name":"Koria",
    "ks:ks_pop":873,
    "ks:ks_type":"VILLAGE",
    "ks:ks_uagg_main":0,
    "name:eng_x_preferred":[
        "Koria"
    ],
    "name:fin_x_preferred":[
        "Koria"
    ],
    "name:kor_x_preferred":[
        "\ucf54\ub9ac\uc544"
    ],
    "name:swe_x_preferred":[
        "Koria"
    ],
    "wof:name":"Koria",
    "wof:placetype":"neighbourhood",
    "wof:population":873
},
  "geometry": {"coordinates":[86.130319,25.53136],"type":"Point"}
}