{
  "type": "Feature",
  "properties": {
    "iso:country":"IN",
    "ks:ks_alt_nam":"C.Family",
    "ks:ks_name":"C.family",
    "ks:ks_pop":36,
    "ks:ks_type":"HABITATION",
    "name:eng_x_preferred":[
        "C.family"
    ],
    "wof:name":"C.family",
    "wof:placetype":"locality",
    "wof:population":36
},
  "geometry": {"coordinates":[75.87527799999999,12.221944],"type":"Point"}
}