{
  "type": "Feature",
  "properties": {
    "iso:country":"IN",
    "ks:ks_name":"Dumurdiha",
    "ks:ks_pop":421,
    "ks:ks_type":"VILLAGE",
    "name:eng_x_preferred":[
        "Dumurdiha"
    ],
    "wof:name":"Dumurdiha",
    "wof:placetype":"locality",
    "wof:population":421
},
  "geometry": {"coordinates":[86.111842,21.650773],"type":"Point"}
}