{
  "type": "Feature",
  "properties": {
    "iso:country":"IN",
    "ks:ks_name":"Dabaguda",
    "ks:ks_pop":88,
    "ks:ks_type":"HABITATION",
    "name:eng_x_preferred":[
        "Dabaguda"
    ],
    "wof:name":"Dabaguda",
    "wof:placetype":"locality",
    "wof:population":88
},
  "geometry": {"coordinates":[79.219328,19.071356],"type":"Point"}
}