{
  "type": "Feature",
  "properties": {
    "iso:country":"IN",
    "ks:ks_name":"Prasadpur",
    "ks:ks_pop":982,
    "ks:ks_type":"VILLAGE",
    "ks:ks_uagg_main":0,
    "name:eng_x_preferred":[
        "Prasadpur"
    ],
    "wof:name":"Prasadpur",
    "wof:placetype":"neighbourhood",
    "wof:population":982
},
  "geometry": {"coordinates":[82.90192399999999,26.859277],"type":"Point"}
}