{
  "type": "Feature",
  "properties": {
    "iso:country":"IN",
    "ks:ks_name":"Madanpura",
    "ks:ks_pop":263,
    "ks:ks_type":"VILLAGE",
    "ks:ks_uagg_main":0,
    "name:eng_x_preferred":[
        "Madanpura"
    ],
    "wof:name":"Madanpura",
    "wof:placetype":"neighbourhood",
    "wof:population":263
},
  "geometry": {"coordinates":[76.637756,25.25852],"type":"Point"}
}