{
  "type": "Feature",
  "properties": {
    "gn:admin1_code":"36.0",
    "gn:admin2_code":"161.0",
    "gn:asciiname":"Kathotia",
    "gn:country_code":"IN",
    "gn:dem":153,
    "gn:feature_class":"P",
    "gn:feature_code":"PPL",
    "gn:name":"Kathotia",
    "gn:population":0,
    "gn:timezone":"Asia/Kolkata",
    "iso:country":"IN",
    "wof:name":"Kathotia",
    "wof:placetype":"locality"
},
  "geometry": {"coordinates":[79.30453,26.90872],"type":"Point"}
}