{
  "type": "Feature",
  "properties": {
    "gn:admin1_code":"11",
    "gn:admin2_code":"31.0",
    "gn:asciiname":"Baniala",
    "gn:country_code":"IN",
    "gn:dem":427,
    "gn:feature_class":"P",
    "gn:feature_code":"PPL",
    "gn:name":"Bani\u0101la",
    "gn:population":0,
    "gn:timezone":"Asia/Kolkata",
    "iso:country":"IN",
    "wof:name":"Baniala",
    "wof:placetype":"locality"
},
  "geometry": {"coordinates":[76.67744999999999,31.16244],"type":"Point"}
}