{
  "type": "Feature",
  "properties": {
    "iso:country":"IN",
    "ks:ks_name":"Lingavaram",
    "ks:ks_pop":124,
    "ks:ks_type":"HABITATION",
    "name:eng_x_preferred":[
        "Lingavaram"
    ],
    "wof:name":"Lingavaram",
    "wof:placetype":"locality",
    "wof:population":124
},
  "geometry": {"coordinates":[81.906392,17.819069],"type":"Point"}
}