{
  "type": "Feature",
  "properties": {
    "iso:country":"IN",
    "ks:ks_name":"Jalarupaduru",
    "ks:ks_pop":103,
    "ks:ks_type":"HABITATION",
    "name:eng_x_preferred":[
        "Jalarupaduru"
    ],
    "wof:name":"Jalarupaduru",
    "wof:placetype":"locality",
    "wof:population":103
},
  "geometry": {"coordinates":[82.44420700000001,18.435366],"type":"Point"}
}