{
  "type": "Feature",
  "properties": {
    "gn:admin1_code":"36",
    "gn:admin2_code":"179.0",
    "gn:asciiname":"Tarkahi",
    "gn:country_code":"IN",
    "gn:dem":99,
    "gn:feature_class":"P",
    "gn:feature_code":"PPL",
    "gn:name":"Tark\u0101hi",
    "gn:population":0,
    "gn:timezone":"Asia/Kolkata",
    "iso:country":"IN",
    "wof:name":"Tarkahi",
    "wof:placetype":"locality"
},
  "geometry": {"coordinates":[82.31593000000002,26.17857],"type":"Point"}
}