{
  "type": "Feature",
  "properties": {
    "gn:admin1_code":"12.0",
    "gn:asciiname":"Dalimond",
    "gn:country_code":"IN",
    "gn:dem":3565,
    "gn:feature_class":"P",
    "gn:feature_code":"PPL",
    "gn:name":"Dalimond",
    "gn:population":0,
    "gn:timezone":"Asia/Kolkata",
    "iso:country":"IN",
    "wof:name":"Dalimond",
    "wof:placetype":"locality"
},
  "geometry": {"coordinates":[75.10556,34.56944],"type":"Point"}
}