{
  "type": "Feature",
  "properties": {
    "iso:country":"IN",
    "ks:ks_name":"Guar",
    "ks:ks_pop":1504,
    "ks:ks_type":"VILLAGE",
    "name:eng_x_preferred":[
        "Guar"
    ],
    "wof:name":"Guar",
    "wof:placetype":"locality",
    "wof:population":1504
},
  "geometry": {"coordinates":[83.340007,26.533888],"type":"Point"}
}