{
  "type": "Feature",
  "properties": {
    "gn:country":"IN",
    "gn:fcode":"PPL",
    "gn:pop":36694,
    "iso:country":"IN",
    "name:dut_x_preferred":[
        "Barwala"
    ],
    "name:eng_x_preferred":[
        "Barwala"
    ],
    "name:ita_x_preferred":[
        "Barwala"
    ],
    "name:unk_x_variant":[
        "Barw\u0101la"
    ],
    "qs:name":"Barwala",
    "qs:name_adm0":"India",
    "qs:name_adm1":"Haryana",
    "qs:photos_9k":1,
    "qs:photos_9r":1,
    "qs:photos_all":1,
    "qs:photos_sr":0,
    "qs:placetype":"Town",
    "qs:pop_sr":"7",
    "wd:wordcount":42,
    "wof:name":"Barwala",
    "wof:placetype":"locality",
    "wof:population":36694
},
  "geometry": {"coordinates":[75.90669,29.3666],"type":"Point"}
}