{
  "type": "Feature",
  "properties": {
    "iso:country":"IN",
    "ks:ks_name":"Velagar",
    "ks:ks_pop":419,
    "ks:ks_type":"VILLAGE",
    "name:eng_x_preferred":[
        "Velagar"
    ],
    "wof:name":"Velagar",
    "wof:placetype":"locality",
    "wof:population":419
},
  "geometry": {"coordinates":[73.66293,15.769214],"type":"Point"}
}