{
  "type": "Feature",
  "properties": {
    "gn:admin1_code":"35",
    "gn:admin2_code":"447.0",
    "gn:asciiname":"Dabida",
    "gn:country_code":"IN",
    "gn:dem":365,
    "gn:feature_class":"P",
    "gn:feature_code":"PPL",
    "gn:name":"D\u0101b\u012bda",
    "gn:population":0,
    "gn:timezone":"Asia/Kolkata",
    "iso:country":"IN",
    "name:azb_x_preferred":[
        "\u062f\u0628\u06cc\u062f\u0627"
    ],
    "name:fas_x_preferred":[
        "\u062f\u0628\u06cc\u062f\u0627"
    ],
    "wof:name":"Dabida",
    "wof:placetype":"locality"
},
  "geometry": {"coordinates":[77.29732,21.79941],"type":"Point"}
}