{
  "type": "Feature",
  "properties": {
    "iso:country":"IN",
    "ks:ks_name":"Amarutani",
    "ks:ks_pop":455,
    "ks:ks_type":"HABITATION",
    "name:eng_x_preferred":[
        "Amarutani"
    ],
    "wof:name":"Amarutani",
    "wof:placetype":"locality",
    "wof:population":455
},
  "geometry": {"coordinates":[83.603166,27.132375],"type":"Point"}
}