{
  "type": "Feature",
  "properties": {
    "iso:country":"IN",
    "ks:ks_name":"Damami",
    "ks:ks_pop":2321,
    "ks:ks_type":"VILLAGE",
    "ks:ks_uagg_main":0,
    "name:eng_x_preferred":[
        "Damami"
    ],
    "wof:name":"Damami",
    "wof:placetype":"neighbourhood",
    "wof:population":2321
},
  "geometry": {"coordinates":[85.42761900000001,26.470393],"type":"Point"}
}