{
  "type": "Feature",
  "properties": {
    "iso:country":"IN",
    "ks:ks_name":"Gotonga",
    "ks:ks_pop":2623,
    "ks:ks_type":"VILLAGE",
    "name:eng_x_preferred":[
        "Gotonga"
    ],
    "wof:name":"Gotonga",
    "wof:placetype":"locality",
    "wof:population":2623
},
  "geometry": {"coordinates":[92.871315,26.432028],"type":"Point"}
}