{
  "type": "Feature",
  "properties": {
    "gn:admin1_code":"16.0",
    "gn:admin2_code":"503.0",
    "gn:asciiname":"Hasimpur",
    "gn:country_code":"IN",
    "gn:dem":330,
    "gn:feature_class":"P",
    "gn:feature_code":"PPL",
    "gn:name":"H\u0101simpur",
    "gn:population":0,
    "gn:timezone":"Asia/Kolkata",
    "iso:country":"IN",
    "wof:name":"Hasimpur",
    "wof:placetype":"locality"
},
  "geometry": {"coordinates":[78.00537,21.24272],"type":"Point"}
}