{
  "type": "Feature",
  "properties": {
    "iso:country":"IN",
    "ks:ks_name":"Rakiv Nagar",
    "ks:ks_pop":368,
    "ks:ks_type":"HABITATION",
    "ks:ks_uagg_main":0,
    "name:eng_x_preferred":[
        "Rakiv Nagar"
    ],
    "wof:name":"Rakiv Nagar",
    "wof:placetype":"neighbourhood",
    "wof:population":368
},
  "geometry": {"coordinates":[81.06440000000001,27.032254],"type":"Point"}
}