{
  "type": "Feature",
  "properties": {
    "iso:country":"IN",
    "ks:ks_name":"Thennur",
    "ks:ks_pop":959,
    "ks:ks_type":"HABITATION",
    "name:eng_x_preferred":[
        "Thennur"
    ],
    "wof:name":"Thennur",
    "wof:placetype":"locality",
    "wof:population":959
},
  "geometry": {"coordinates":[77.086476,8.698677],"type":"Point"}
}