{
  "type": "Feature",
  "properties": {
    "iso:country":"IN",
    "ks:ks_alt_nam":"barkadwadi",
    "ks:ks_name":"Barkadwadi",
    "ks:ks_pop":192,
    "ks:ks_type":"HABITATION",
    "name:eng_x_preferred":[
        "Barkadwadi"
    ],
    "wof:name":"Barkadwadi",
    "wof:placetype":"locality",
    "wof:population":192
},
  "geometry": {"coordinates":[74.3507,18.2332],"type":"Point"}
}