{
  "type": "Feature",
  "properties": {
    "iso:country":"IN",
    "ks:ks_name":"Samburam Patti",
    "ks:ks_pop":260,
    "ks:ks_type":"HABITATION",
    "name:eng_x_preferred":[
        "Samburam Patti"
    ],
    "wof:name":"Samburam Patti",
    "wof:placetype":"locality",
    "wof:population":260
},
  "geometry": {"coordinates":[79.001068,10.344458],"type":"Point"}
}