{
  "type": "Feature",
  "properties": {
    "gn:admin1_code":"34.0",
    "gn:admin2_code":"212.0",
    "gn:asciiname":"Madarsa",
    "gn:country_code":"IN",
    "gn:dem":36,
    "gn:feature_class":"P",
    "gn:feature_code":"PPL",
    "gn:name":"Madarsa",
    "gn:population":0,
    "gn:timezone":"Asia/Kolkata",
    "iso:country":"IN",
    "ks:ks_name":"Madarsa",
    "ks:ks_pop":1213,
    "ks:ks_type":"VILLAGE",
    "name:eng_x_preferred":[
        "Madarsa"
    ],
    "wof:name":"Madarsa",
    "wof:placetype":"locality",
    "wof:population":1213
},
  "geometry": {"coordinates":[87.303533,25.578657],"type":"Point"}
}