{
  "type": "Feature",
  "properties": {
    "gn:admin1_code":"24.0",
    "gn:admin2_code":"126.0",
    "gn:asciiname":"Kachnariya",
    "gn:country_code":"IN",
    "gn:dem":447,
    "gn:feature_class":"P",
    "gn:feature_code":"PPL",
    "gn:name":"Kachn\u0101r\u012bya",
    "gn:population":0,
    "gn:timezone":"Asia/Kolkata",
    "iso:country":"IN",
    "wof:name":"Kachnariya",
    "wof:placetype":"locality"
},
  "geometry": {"coordinates":[74.50829,25.01968],"type":"Point"}
}