{
  "type": "Feature",
  "properties": {
    "iso:country":"IN",
    "ks:ks_name":"Khilta",
    "ks:ks_pop":637,
    "ks:ks_type":"VILLAGE",
    "ks:ks_uagg_main":0,
    "name:eng_x_preferred":[
        "Khilta"
    ],
    "wof:name":"Khilta",
    "wof:placetype":"neighbourhood",
    "wof:population":637
},
  "geometry": {"coordinates":[87.106797,25.18218],"type":"Point"}
}