{
  "type": "Feature",
  "properties": {
    "iso:country":"IN",
    "ks:ks_name":"Bhagtiadih",
    "ks:ks_pop":178,
    "ks:ks_type":"VILLAGE",
    "name:eng_x_preferred":[
        "Bhagtiadih"
    ],
    "wof:name":"Bhagtiadih",
    "wof:placetype":"locality",
    "wof:population":178
},
  "geometry": {"coordinates":[87.021188,24.578887],"type":"Point"}
}