{
  "type": "Feature",
  "properties": {
    "iso:country":"IN",
    "ks:ks_name":"Bhira",
    "ks:ks_pop":244,
    "ks:ks_type":"VILLAGE",
    "name:eng_x_preferred":[
        "Bhira"
    ],
    "wof:name":"Bhira",
    "wof:placetype":"locality",
    "wof:population":244
},
  "geometry": {"coordinates":[79.831261,22.786457],"type":"Point"}
}