{
  "type": "Feature",
  "properties": {
    "iso:country":"IN",
    "ks:ks_name":"Chinakilivachi",
    "ks:ks_pop":165,
    "ks:ks_type":"HABITATION",
    "name:eng_x_preferred":[
        "Chinakilivachi"
    ],
    "wof:name":"Chinakilivachi",
    "wof:placetype":"locality",
    "wof:population":165
},
  "geometry": {"coordinates":[78.588939,9.804856],"type":"Point"}
}