{
  "type": "Feature",
  "properties": {
    "iso:country":"IN",
    "ks:ks_name":"Malapalli Kothapalli",
    "ks:ks_pop":111,
    "ks:ks_type":"HABITATION",
    "name:eng_x_preferred":[
        "Malapalli Kothapalli"
    ],
    "wof:name":"Malapalli Kothapalli",
    "wof:placetype":"locality",
    "wof:population":111
},
  "geometry": {"coordinates":[78.69848500000001,13.894877],"type":"Point"}
}