{
  "type": "Feature",
  "properties": {
    "iso:country":"IN",
    "ks:ks_name":"Karha Basa",
    "ks:ks_pop":96,
    "ks:ks_type":"HABITATION",
    "ks:ks_uagg_main":0,
    "name:eng_x_preferred":[
        "Karha Basa"
    ],
    "wof:name":"Karha Basa",
    "wof:placetype":"neighbourhood",
    "wof:population":96
},
  "geometry": {"coordinates":[86.84544699999999,25.461366],"type":"Point"}
}