{
  "type": "Feature",
  "properties": {
    "iso:country":"IN",
    "ks:ks_name":"Bidaremane",
    "ks:ks_pop":89,
    "ks:ks_type":"HABITATION",
    "name:eng_x_preferred":[
        "Bidaremane"
    ],
    "wof:name":"Bidaremane",
    "wof:placetype":"locality",
    "wof:population":89
},
  "geometry": {"coordinates":[75.541944,13.559762],"type":"Point"}
}