{
  "type": "Feature",
  "properties": {
    "iso:country":"IN",
    "ks:ks_alt_nam":"Dangarar naya Basti",
    "ks:ks_name":"Dangarar Naya Basti",
    "ks:ks_pop":553,
    "ks:ks_type":"HABITATION",
    "name:eng_x_preferred":[
        "Dangarar Naya Basti"
    ],
    "wof:name":"Dangarar Naya Basti",
    "wof:placetype":"locality",
    "wof:population":553
},
  "geometry": {"coordinates":[88.052092,26.225152],"type":"Point"}
}