{
  "type": "Feature",
  "properties": {
    "gn:admin1_code":"11.0",
    "gn:admin2_code":"33.0",
    "gn:asciiname":"Chaunri",
    "gn:country_code":"IN",
    "gn:dem":2264,
    "gn:feature_class":"P",
    "gn:feature_code":"PPL",
    "gn:name":"Chaunri",
    "gn:population":0,
    "gn:timezone":"Asia/Kolkata",
    "iso:country":"IN",
    "wof:name":"Chaunri",
    "wof:placetype":"locality"
},
  "geometry": {"coordinates":[77.54884,31.20895],"type":"Point"}
}