{
  "type": "Feature",
  "properties": {
    "gn:admin1_code":"10.0",
    "gn:admin2_code":"81.0",
    "gn:asciiname":"Dhana Narsan",
    "gn:country_code":"IN",
    "gn:dem":220,
    "gn:feature_class":"P",
    "gn:feature_code":"PPL",
    "gn:name":"Dh\u0101na Nars\u0101n",
    "gn:population":0,
    "gn:timezone":"Asia/Kolkata",
    "iso:country":"IN",
    "wof:name":"Dhana Narsan",
    "wof:placetype":"locality"
},
  "geometry": {"coordinates":[76.1524,28.73851],"type":"Point"}
}