{
  "type": "Feature",
  "properties": {
    "iso:country":"IN",
    "ks:ks_name":"Gokalpura",
    "ks:ks_pop":1032,
    "ks:ks_type":"VILLAGE",
    "name:eng_x_preferred":[
        "Gokalpura"
    ],
    "wof:name":"Gokalpura",
    "wof:placetype":"neighbourhood",
    "wof:population":1032
},
  "geometry": {"coordinates":[73.11226000000001,22.272032],"type":"Point"}
}