{
  "type": "Feature",
  "properties": {
    "iso:country":"IN",
    "ks:ks_alt_nam":"CHOUGLE MALA",
    "ks:ks_name":"Chougle Mala",
    "ks:ks_pop":108,
    "ks:ks_type":"HABITATION",
    "name:eng_x_preferred":[
        "Chougle Mala"
    ],
    "wof:name":"Chougle Mala",
    "wof:placetype":"locality",
    "wof:population":108
},
  "geometry": {"coordinates":[74.922816,16.980673],"type":"Point"}
}