{
  "type": "Feature",
  "properties": {
    "iso:country":"IN",
    "ks:ks_name":"Kewat Tola",
    "ks:ks_pop":195,
    "ks:ks_type":"HABITATION",
    "name:eng_x_preferred":[
        "Kewat Tola"
    ],
    "wof:name":"Kewat Tola",
    "wof:placetype":"locality",
    "wof:population":195
},
  "geometry": {"coordinates":[82.99803799999999,27.113197],"type":"Point"}
}