{
  "type": "Feature",
  "properties": {
    "iso:country":"IN",
    "ks:ks_alt_nam":"ZAN ZANE WASTI",
    "ks:ks_name":"Zan Zane Wasti",
    "ks:ks_pop":255,
    "ks:ks_type":"HABITATION",
    "name:eng_x_preferred":[
        "Zan Zane Wasti"
    ],
    "wof:name":"Zan Zane Wasti",
    "wof:placetype":"locality",
    "wof:population":255
},
  "geometry": {"coordinates":[74.777545,18.442387],"type":"Point"}
}