{
  "type": "Feature",
  "properties": {
    "gn:admin1_code":"25.0",
    "gn:admin2_code":"633.0",
    "gn:asciiname":"Silanayakkanpatti",
    "gn:country_code":"IN",
    "gn:dem":299,
    "gn:feature_class":"P",
    "gn:feature_code":"PPL",
    "gn:name":"S\u012blan\u0101yakkanpatti",
    "gn:population":0,
    "gn:timezone":"Asia/Kolkata",
    "iso:country":"IN",
    "wof:name":"Silanayakkanpatti",
    "wof:placetype":"locality"
},
  "geometry": {"coordinates":[77.45274999999999,10.70337],"type":"Point"}
}