{
  "type": "Feature",
  "properties": {
    "iso:country":"IN",
    "ks:ks_alt_nam":"Mankala keri",
    "ks:ks_name":"Mankala Keri",
    "ks:ks_pop":94,
    "ks:ks_type":"HABITATION",
    "name:eng_x_preferred":[
        "Mankala Keri"
    ],
    "wof:name":"Mankala Keri",
    "wof:placetype":"locality",
    "wof:population":94
},
  "geometry": {"coordinates":[76.20166999999999,15.822828],"type":"Point"}
}