{
  "type": "Feature",
  "properties": {
    "iso:country":"IN",
    "ks:ks_name":"Gadkhol",
    "ks:ks_pop":81,
    "ks:ks_type":"VILLAGE",
    "name:eng_x_preferred":[
        "Gadkhol"
    ],
    "wof:name":"Gadkhol",
    "wof:placetype":"locality",
    "wof:population":81
},
  "geometry": {"coordinates":[84.525085,21.294387],"type":"Point"}
}