{
  "type": "Feature",
  "properties": {
    "gn:admin1_code":"35",
    "gn:admin2_code":"423.0",
    "gn:asciiname":"Akhai Mahadev",
    "gn:country_code":"IN",
    "gn:dem":469,
    "gn:feature_class":"P",
    "gn:feature_code":"PPL",
    "gn:name":"Akh\u0101i Mah\u0101dev",
    "gn:population":0,
    "gn:timezone":"Asia/Kolkata",
    "iso:country":"IN",
    "wof:name":"Akhai Mahadev",
    "wof:placetype":"locality"
},
  "geometry": {"coordinates":[77.53816999999999,24.95068],"type":"Point"}
}