{
  "type": "Feature",
  "properties": {
    "gn:admin1_code":"35",
    "gn:admin2_code":"423.0",
    "gn:asciiname":"Akhai Mahadev",
    "gn:country_code":"IN",
    "gn:dem":469,
    "gn:feature_class":"P",
    "gn:feature_code":"PPL",
    "gn:name":"Akh\u0101i Mah\u0101dev",
    "gn:population":0,
    "gn:timezone":"Asia/Kolkata",
    "iso:country":"IN",
    "ks:ks_alt_nam":"Akh\u0101i Mah\u0101dev",
    "ks:ks_name":"Akhai Mahadev",
    "ks:ks_type":"VILLAGE",
    "name:eng_x_preferred":[
        "Akhai Mahadev"
    ],
    "name:eng_x_variant":[
        "Akh\u0101i Mah\u0101dev"
    ],
    "wof:name":"Akhai Mahadev",
    "wof:placetype":"locality"
},
  "geometry": {"coordinates":[77.538172,24.950681],"type":"Point"}
}