{
  "type": "Feature",
  "properties": {
    "gn:admin1_code":"36",
    "gn:admin2_code":"148.0",
    "gn:asciiname":"Baragaon",
    "gn:country_code":"IN",
    "gn:dem":163,
    "gn:feature_class":"P",
    "gn:feature_code":"PPL",
    "gn:name":"Bar\u0101gaon",
    "gn:population":0,
    "gn:timezone":"Asia/Kolkata",
    "iso:country":"IN",
    "ks:ks_alt_nam":"Bar\u0101gaon",
    "ks:ks_name":"Baragaon",
    "ks:ks_type":"VILLAGE",
    "name:eng_x_preferred":[
        "Baragaon"
    ],
    "name:eng_x_variant":[
        "Bar\u0101gaon"
    ],
    "name:ita_x_preferred":[
        "Baragaon"
    ],
    "name:nld_x_preferred":[
        "Baragaon"
    ],
    "name:pol_x_preferred":[
        "Baragaon"
    ],
    "wof:name":"Baragaon",
    "wof:placetype":"locality"
},
  "geometry": {"coordinates":[78.949986,27.167563],"type":"Point"}
}