{
  "type": "Feature",
  "properties": {
    "iso:country":"IN",
    "ks:ks_name":"Appalaicheruvu",
    "ks:ks_pop":438,
    "ks:ks_type":"HABITATION",
    "name:eng_x_preferred":[
        "Appalaicheruvu"
    ],
    "wof:name":"Appalaicheruvu",
    "wof:placetype":"locality",
    "wof:population":438
},
  "geometry": {"coordinates":[78.97769,18.072688],"type":"Point"}
}