{
  "type": "Feature",
  "properties": {
    "iso:country":"IN",
    "ks:ks_name":"Kajari Nandapur",
    "ks:ks_pop":125,
    "ks:ks_type":"HABITATION",
    "name:eng_x_preferred":[
        "Kajari Nandapur"
    ],
    "wof:name":"Kajari Nandapur",
    "wof:placetype":"locality",
    "wof:population":125
},
  "geometry": {"coordinates":[82.57919800000001,26.341351],"type":"Point"}
}