{
  "type": "Feature",
  "properties": {
    "gn:admin1_code":"35",
    "gn:admin2_code":"447.0",
    "gn:asciiname":"Semalpura",
    "gn:country_code":"IN",
    "gn:dem":395,
    "gn:feature_class":"P",
    "gn:feature_code":"PPL",
    "gn:name":"Semalpura",
    "gn:population":0,
    "gn:timezone":"Asia/Kolkata",
    "iso:country":"IN",
    "wof:name":"Semalpura",
    "wof:placetype":"locality"
},
  "geometry": {"coordinates":[77.84921999999997,22.34746],"type":"Point"}
}