{
  "type": "Feature",
  "properties": {
    "gn:admin1_code":"16",
    "gn:admin2_code":"505.0",
    "gn:asciiname":"Musalkund",
    "gn:country_code":"IN",
    "gn:dem":308,
    "gn:feature_class":"P",
    "gn:feature_code":"PPL",
    "gn:name":"Musalkund",
    "gn:population":0,
    "gn:timezone":"Asia/Kolkata",
    "iso:country":"IN",
    "ks:ks_name":"Musalkund",
    "ks:ks_type":"VILLAGE",
    "name:eng_x_preferred":[
        "Musalkund"
    ],
    "wof:name":"Musalkund",
    "wof:placetype":"locality"
},
  "geometry": {"coordinates":[79.219059,20.932195],"type":"Point"}
}