{
  "type": "Feature",
  "properties": {
    "gn:admin1_code":"16",
    "gn:admin2_code":"505.0",
    "gn:asciiname":"Musalkund",
    "gn:country_code":"IN",
    "gn:dem":308,
    "gn:feature_class":"P",
    "gn:feature_code":"PPL",
    "gn:name":"Musalkund",
    "gn:population":0,
    "gn:timezone":"Asia/Kolkata",
    "iso:country":"IN",
    "wof:name":"Musalkund",
    "wof:placetype":"locality"
},
  "geometry": {"coordinates":[79.21906,20.9322],"type":"Point"}
}