{
  "type": "Feature",
  "properties": {
    "iso:country":"IN",
    "ks:ks_name":"Kurkuti",
    "ks:ks_pop":194,
    "ks:ks_type":"VILLAGE",
    "name:eng_x_preferred":[
        "Kurkuti"
    ],
    "wof:name":"Kurkuti",
    "wof:placetype":"locality",
    "wof:population":194
},
  "geometry": {"coordinates":[79.833285,30.717169],"type":"Point"}
}