{
  "type": "Feature",
  "properties": {
    "gn:admin1_code":"36.0",
    "gn:admin2_code":"138.0",
    "gn:asciiname":"Lutfullapur Baksar",
    "gn:country_code":"IN",
    "gn:dem":226,
    "gn:feature_class":"P",
    "gn:feature_code":"PPL",
    "gn:name":"Lutfull\u0101pur Baksar",
    "gn:population":0,
    "gn:timezone":"Asia/Kolkata",
    "iso:country":"IN",
    "wof:name":"Lutfullapur Baksar",
    "wof:placetype":"locality"
},
  "geometry": {"coordinates":[77.85508,28.97258],"type":"Point"}
}