{
  "type": "Feature",
  "properties": {
    "gn:admin1_code":"36.0",
    "gn:admin2_code":"134.0",
    "gn:asciiname":"Narayanwala",
    "gn:country_code":"IN",
    "gn:dem":269,
    "gn:feature_class":"P",
    "gn:feature_code":"PPL",
    "gn:name":"Nar\u0101yanw\u0101la",
    "gn:population":0,
    "gn:timezone":"Asia/Kolkata",
    "iso:country":"IN",
    "name:und_x_variant":[
        "Nar\u0101yanw\u0101la",
        "Nar\u0101yanpur"
    ],
    "wof:name":"Narayanwala",
    "wof:placetype":"locality"
},
  "geometry": {"coordinates":[78.57302,29.491],"type":"Point"}
}