{
  "type": "Feature",
  "properties": {
    "gn:admin1_code":"36.0",
    "gn:admin2_code":"134.0",
    "gn:asciiname":"Narayanwala",
    "gn:country_code":"IN",
    "gn:dem":269,
    "gn:feature_class":"P",
    "gn:feature_code":"PPL",
    "gn:name":"Nar\u0101yanw\u0101la",
    "gn:population":0,
    "gn:timezone":"Asia/Kolkata",
    "iso:country":"IN",
    "ks:ks_name":"Narainwala",
    "ks:ks_pop":26,
    "ks:ks_type":"HABITATION",
    "name:eng_x_preferred":[
        "Narainwala"
    ],
    "name:eng_x_variant":[
        "Narayanwala"
    ],
    "name:und_x_variant":[
        "Nar\u0101yanw\u0101la",
        "Nar\u0101yanpur"
    ],
    "wof:name":"Narainwala",
    "wof:placetype":"locality",
    "wof:population":26
},
  "geometry": {"coordinates":[78.58734200000001,29.495495],"type":"Point"}
}