{
  "type": "Feature",
  "properties": {
    "iso:country":"IN",
    "ks:ks_name":"Farera",
    "ks:ks_pop":131,
    "ks:ks_type":"VILLAGE",
    "name:eng_x_preferred":[
        "Farera"
    ],
    "wof:name":"Farera",
    "wof:placetype":"locality",
    "wof:population":131
},
  "geometry": {"coordinates":[76.488669,25.648839],"type":"Point"}
}