{
  "type": "Feature",
  "properties": {
    "iso:country":"IN",
    "ks:ks_name":"Dhanwar Ryt.",
    "ks:ks_pop":59,
    "ks:ks_type":"VILLAGE",
    "name:eng_x_preferred":[
        "Dhanwar Ryt."
    ],
    "wof:name":"Dhanwar Ryt.",
    "wof:placetype":"locality",
    "wof:population":59
},
  "geometry": {"coordinates":[80.493368,22.25931],"type":"Point"}
}