{
  "type": "Feature",
  "properties": {
    "iso:country":"IN",
    "ks:ks_name":"Chaor Kot Malla",
    "ks:ks_pop":56,
    "ks:ks_type":"VILLAGE",
    "name:eng_x_preferred":[
        "Chaor Kot Malla"
    ],
    "wof:name":"Chaor Kot Malla",
    "wof:placetype":"locality",
    "wof:population":56
},
  "geometry": {"coordinates":[79.05616499999999,29.911387],"type":"Point"}
}