{
  "type": "Feature",
  "properties": {
    "gn:admin1_code":"34.0",
    "gn:admin2_code":"236.0",
    "gn:asciiname":"Telwari",
    "gn:country_code":"IN",
    "gn:dem":212,
    "gn:feature_class":"P",
    "gn:feature_code":"PPL",
    "gn:name":"Telw\u0101ri",
    "gn:population":0,
    "gn:timezone":"Asia/Kolkata",
    "iso:country":"IN",
    "ks:ks_alt_nam":"Telw\u0101ri",
    "ks:ks_name":"Telwari",
    "ks:ks_pop":1319,
    "ks:ks_type":"VILLAGE",
    "name:eng_x_preferred":[
        "Telwari"
    ],
    "name:eng_x_variant":[
        "Telw\u0101ri"
    ],
    "wof:name":"Telwari",
    "wof:placetype":"locality",
    "wof:population":1319
},
  "geometry": {"coordinates":[84.524385,24.372638],"type":"Point"}
}