{
  "type": "Feature",
  "properties": {
    "gn:admin1_code":"19.0",
    "gn:admin2_code":"581.0",
    "gn:asciiname":"Bangavadi",
    "gn:country_code":"IN",
    "gn:dem":738,
    "gn:feature_class":"P",
    "gn:feature_code":"PPL",
    "gn:name":"Bangav\u0101di",
    "gn:population":0,
    "gn:timezone":"Asia/Kolkata",
    "iso:country":"IN",
    "wof:name":"Bangavadi",
    "wof:placetype":"locality"
},
  "geometry": {"coordinates":[78.55074999999999,13.27519],"type":"Point"}
}