{
  "type": "Feature",
  "properties": {
    "iso:country":"IN",
    "ks:ks_name":"Baramor",
    "ks:ks_pop":502,
    "ks:ks_type":"VILLAGE",
    "name:eng_x_preferred":[
        "Baramor"
    ],
    "wof:name":"Baramor",
    "wof:placetype":"locality",
    "wof:population":502
},
  "geometry": {"coordinates":[87.16377199999999,22.118918],"type":"Point"}
}