{
  "type": "Feature",
  "properties": {
    "iso:country":"IN",
    "ks:ks_name":"Koiri Tola",
    "ks:ks_pop":709,
    "ks:ks_type":"HABITATION",
    "name:eng_x_preferred":[
        "Koiri Tola"
    ],
    "wof:name":"Koiri Tola",
    "wof:placetype":"locality",
    "wof:population":709
},
  "geometry": {"coordinates":[86.126321,24.359529],"type":"Point"}
}