{
  "type": "Feature",
  "properties": {
    "gn:admin1_code":"11.0",
    "gn:admin2_code":"33.0",
    "gn:asciiname":"Tipra",
    "gn:country_code":"IN",
    "gn:dem":2005,
    "gn:feature_class":"P",
    "gn:feature_code":"PPL",
    "gn:name":"Tipra",
    "gn:population":0,
    "gn:timezone":"Asia/Kolkata",
    "iso:country":"IN",
    "wof:name":"Tipra",
    "wof:placetype":"locality"
},
  "geometry": {"coordinates":[77.55660999999998,31.00193],"type":"Point"}
}