{
  "type": "Feature",
  "properties": {
    "iso:country":"IN",
    "ks:ks_name":"Peleppuram Jn-2",
    "ks:ks_pop":357,
    "ks:ks_type":"HABITATION",
    "name:eng_x_preferred":[
        "Peleppuram Jn-2"
    ],
    "wof:name":"Peleppuram Jn-2",
    "wof:placetype":"locality",
    "wof:population":357
},
  "geometry": {"coordinates":[76.177542,11.161694],"type":"Point"}
}