{
  "type": "Feature",
  "properties": {
    "iso:country":"IN",
    "ks:ks_alt_nam":"Therkku sreerangampalayam",
    "ks:ks_name":"Therkku Sreerangampalayam",
    "ks:ks_pop":582,
    "ks:ks_type":"HABITATION",
    "name:eng_x_preferred":[
        "Therkku Sreerangampalayam"
    ],
    "wof:name":"Therkku Sreerangampalayam",
    "wof:placetype":"locality",
    "wof:population":582
},
  "geometry": {"coordinates":[77.39722399999999,11.178976],"type":"Point"}
}