{
  "type": "Feature",
  "properties": {
    "iso:country":"IN",
    "ks:ks_name":"Bavadabailu",
    "ks:ks_pop":283,
    "ks:ks_type":"HABITATION",
    "name:eng_x_preferred":[
        "Bavadabailu"
    ],
    "wof:name":"Bavadabailu",
    "wof:placetype":"locality",
    "wof:population":283
},
  "geometry": {"coordinates":[75.024441,13.010065],"type":"Point"}
}