{
  "type": "Feature",
  "properties": {
    "gn:admin1_code":"36.0",
    "gn:admin2_code":"149",
    "gn:asciiname":"Afzalpur",
    "gn:country_code":"IN",
    "gn:dem":157,
    "gn:feature_class":"P",
    "gn:feature_code":"PPL",
    "gn:name":"Afzalpur",
    "gn:population":0,
    "gn:timezone":"Asia/Kolkata",
    "iso:country":"IN",
    "name:ben_x_preferred":[
        "\u0986\u09ab\u099c\u09be\u09b2\u09aa\u09c1\u09b0"
    ],
    "name:bpy_x_preferred":[
        "\u0986\u09ab\u099c\u09be\u09b2\u09aa\u09c1\u09b0"
    ],
    "name:ceb_x_preferred":[
        "Afzalpur Taluk"
    ],
    "name:ita_x_preferred":[
        "Afzalpur"
    ],
    "name:kan_x_preferred":[
        "\u0c85\u0cab\u0c9c\u0cb2\u0ccd\u0caa\u0cc1\u0cb0"
    ],
    "name:min_x_preferred":[
        "Afzalpur"
    ],
    "name:mlg_x_preferred":[
        "Afzalpur"
    ],
    "name:msa_x_preferred":[
        "Afzalpur"
    ],
    "name:new_x_preferred":[
        "\u0905\u092b\u094d\u091c\u0932\u092a\u0941\u0930"
    ],
    "name:nld_x_preferred":[
        "Afzalpur"
    ],
    "name:ori_x_preferred":[
        "\u0b05\u0b2b\u0b1c\u0b32\u0b2a\u0b41\u0b30"
    ],
    "name:por_x_preferred":[
        "Afzalpur"
    ],
    "name:spa_x_preferred":[
        "Afzalpur"
    ],
    "name:swe_x_preferred":[
        "Afzalpur Taluk"
    ],
    "name:urd_x_preferred":[
        "\u0627\u0641\u0636\u0644\u067e\u0648\u0631"
    ],
    "name:vie_x_preferred":[
        "Afzalpur"
    ],
    "name:zho_x_preferred":[
        "\u963f\u592b\u624e\u5c14\u666e\u5c14"
    ],
    "wof:name":"Afzalpur",
    "wof:placetype":"locality"
},
  "geometry": {"coordinates":[79.39891,27.97206],"type":"Point"}
}