{
  "type": "Feature",
  "properties": {
    "gn:admin1_code":"12",
    "gn:admin2_code":"14.0",
    "gn:asciiname":"Gagarwain",
    "gn:country_code":"IN",
    "gn:dem":2629,
    "gn:feature_class":"P",
    "gn:feature_code":"PPL",
    "gn:name":"G\u0101garwa\u012bn",
    "gn:population":0,
    "gn:timezone":"Asia/Kolkata",
    "iso:country":"IN",
    "wof:name":"Gagarwain",
    "wof:placetype":"locality"
},
  "geometry": {"coordinates":[75.38894000000001,34.06724000000001],"type":"Point"}
}