{
  "type": "Feature",
  "properties": {
    "iso:country":"IN",
    "ks:ks_name":"Konwargaon",
    "ks:ks_pop":599,
    "ks:ks_type":"VILLAGE",
    "name:eng_x_preferred":[
        "Konwargaon"
    ],
    "wof:name":"Konwargaon",
    "wof:placetype":"locality",
    "wof:population":599
},
  "geometry": {"coordinates":[92.21409199999999,26.215509],"type":"Point"}
}