{
  "type": "Feature",
  "properties": {
    "gn:admin1_code":"36",
    "gn:admin2_code":"134.0",
    "gn:asciiname":"Kanheri",
    "gn:country_code":"IN",
    "gn:dem":227,
    "gn:feature_class":"P",
    "gn:feature_code":"PPL",
    "gn:name":"Kanheri",
    "gn:population":0,
    "gn:timezone":"Asia/Kolkata",
    "iso:country":"IN",
    "name:ara_x_preferred":[
        "\u0643\u0627\u0646\u0647\u064a\u0631\u064a"
    ],
    "name:ben_bn_x_preferred":[
        "\u0995\u09be\u09a8\u09b9\u09c7\u09b0\u09bf"
    ],
    "name:ben_in_x_preferred":[
        "\u0995\u09be\u09a8\u09b9\u09c7\u09b0\u09bf"
    ],
    "name:guj_x_preferred":[
        "\u0a95\u0aa8\u0ac7\u0ab0\u0ac0"
    ],
    "name:hin_x_preferred":[
        "\u0915\u093e\u0928\u094d\u0939\u0947\u0930\u0940"
    ],
    "name:kan_x_preferred":[
        "\u0c95\u0ca8\u0ccd\u0cb9\u0cc7\u0cb0\u0cbf"
    ],
    "name:mal_x_preferred":[
        "\u0d15\u0d3e\u0d1e\u0d4d\u0d1e\u0d47\u0d30\u0d3f"
    ],
    "name:mar_x_preferred":[
        "\u0915\u093e\u0928\u094d\u0939\u0947\u0930\u0940"
    ],
    "name:pan_x_preferred":[
        "\u0a15\u0a28\u0a39\u0a48\u0a30\u0a40"
    ],
    "name:tam_x_preferred":[
        "\u0b95\u0ba9\u0bcd\u0bb9\u0bc6\u0bb0\u0bbf"
    ],
    "name:tel_x_preferred":[
        "\u0c15\u0c28\u0c4d\u0c39\u0c46\u0c30\u0c40"
    ],
    "name:urd_x_preferred":[
        "\u06a9\u0646\u06c1\u0631\u06cc"
    ],
    "wof:name":"Kanheri",
    "wof:placetype":"locality"
},
  "geometry": {"coordinates":[78.46804,29.18417],"type":"Point"}
}