{
  "type": "Feature",
  "properties": {
    "gn:admin1_code":"36",
    "gn:admin2_code":"165.0",
    "gn:asciiname":"Pal",
    "gn:country_code":"IN",
    "gn:dem":131,
    "gn:feature_class":"P",
    "gn:feature_code":"PPL",
    "gn:name":"P\u0101l",
    "gn:population":0,
    "gn:timezone":"Asia/Kolkata",
    "iso:country":"IN",
    "ks:ks_alt_nam":"P\u0101l",
    "ks:ks_name":"Pal",
    "ks:ks_pop":1572,
    "ks:ks_type":"VILLAGE",
    "name:eng_x_preferred":[
        "Pal"
    ],
    "name:eng_x_variant":[
        "P\u0101l"
    ],
    "wof:name":"Pal",
    "wof:placetype":"locality",
    "wof:population":1572
},
  "geometry": {"coordinates":[79.604817,26.246656],"type":"Point"}
}