{
  "type": "Feature",
  "properties": {
    "iso:country":"IN",
    "ks:ks_name":"Tipukial",
    "ks:ks_pop":377,
    "ks:ks_type":"VILLAGE",
    "ks:ks_uagg_main":0,
    "name:eng_x_preferred":[
        "Tipukial"
    ],
    "wof:name":"Tipukial",
    "wof:placetype":"locality",
    "wof:population":377
},
  "geometry": {"coordinates":[94.13612999999999,27.280765],"type":"Point"}
}