{
  "type": "Feature",
  "properties": {
    "gn:country":"IN",
    "gn:fcode":"PPL",
    "gn:pop":0,
    "iso:country":"IN",
    "qs:name":"Mahargaon",
    "qs:name_adm0":"India",
    "qs:name_adm1":"Uttarakhand",
    "qs:photos":152,
    "qs:photos_1k":31,
    "qs:photos_9k":1,
    "qs:photos_9r":4,
    "qs:photos_all":152,
    "qs:photos_sr":4,
    "qs:placetype":"Town",
    "qs:pop_sr":"0",
    "wof:name":"Mahargaon",
    "wof:placetype":"locality",
    "wof:population":0
},
  "geometry": {"coordinates":[78.73702,29.80385],"type":"Point"}
}