{
  "type": "Feature",
  "properties": {
    "iso:country":"IN",
    "ks:ks_name":"Boodajalu",
    "ks:ks_pop":280,
    "ks:ks_type":"HABITATION",
    "name:eng_x_preferred":[
        "Boodajalu"
    ],
    "wof:name":"Boodajalu",
    "wof:placetype":"locality",
    "wof:population":280
},
  "geometry": {"coordinates":[75.401365,12.900097],"type":"Point"}
}