{
  "type": "Feature",
  "properties": {
    "iso:country":"IN",
    "ks:ks_name":"Rundha",
    "ks:ks_pop":0,
    "ks:ks_type":"VILLAGE",
    "name:eng_x_preferred":[
        "Rundha"
    ],
    "wof:name":"Rundha",
    "wof:placetype":"locality",
    "wof:population":0
},
  "geometry": {"coordinates":[73.405655,21.318358],"type":"Point"}
}