{
  "type": "Feature",
  "properties": {
    "iso:country":"IN",
    "ks:ks_alt_nam":"Coloni road",
    "ks:ks_name":"Coloni Road",
    "ks:ks_pop":819,
    "ks:ks_type":"HABITATION",
    "name:eng_x_preferred":[
        "Coloni Road"
    ],
    "wof:name":"Coloni Road",
    "wof:placetype":"locality",
    "wof:population":819
},
  "geometry": {"coordinates":[76.35489200000001,11.399492],"type":"Point"}
}