{
  "type": "Feature",
  "properties": {
    "iso:country":"IN",
    "ks:ks_name":"Hanumankheda",
    "ks:ks_pop":513,
    "ks:ks_type":"VILLAGE",
    "name:eng_x_preferred":[
        "Hanumankheda"
    ],
    "wof:name":"Hanumankheda",
    "wof:placetype":"locality",
    "wof:population":513
},
  "geometry": {"coordinates":[76.701762,25.401528],"type":"Point"}
}