{
  "type": "Feature",
  "properties": {
    "iso:country":"IN",
    "ks:ks_alt_nam":"KADAMWASTI",
    "ks:ks_name":"Kadamwasti",
    "ks:ks_pop":225,
    "ks:ks_type":"HABITATION",
    "name:eng_x_preferred":[
        "Kadamwasti"
    ],
    "wof:name":"Kadamwasti",
    "wof:placetype":"locality",
    "wof:population":225
},
  "geometry": {"coordinates":[74.892021,16.944937],"type":"Point"}
}