{
  "type": "Feature",
  "properties": {
    "iso:country":"IN",
    "ks:ks_name":"Handi",
    "ks:ks_pop":0,
    "ks:ks_type":"VILLAGE",
    "name:eng_x_preferred":[
        "Handi"
    ],
    "wof:name":"Handi",
    "wof:placetype":"locality",
    "wof:population":0
},
  "geometry": {"coordinates":[76.60793700000001,25.395063],"type":"Point"}
}