{
  "type": "Feature",
  "properties": {
    "gn:admin1_code":"35.0",
    "gn:admin2_code":"462.0",
    "gn:asciiname":"Padariya Kalan",
    "gn:country_code":"IN",
    "gn:dem":257,
    "gn:feature_class":"P",
    "gn:feature_code":"PPL",
    "gn:name":"Padariya Kalan",
    "gn:population":0,
    "gn:timezone":"Asia/Kolkata",
    "iso:country":"IN",
    "wof:name":"Padariya Kalan",
    "wof:placetype":"locality"
},
  "geometry": {"coordinates":[81.93366999999998,24.5066],"type":"Point"}
}