{
  "type": "Feature",
  "properties": {
    "iso:country":"IN",
    "ks:ks_name":"Kumakolang",
    "ks:ks_pop":545,
    "ks:ks_type":"VILLAGE",
    "name:eng_x_preferred":[
        "Kumakolang"
    ],
    "wof:name":"Kumakolang",
    "wof:placetype":"locality",
    "wof:population":545
},
  "geometry": {"coordinates":[81.90459,18.726088],"type":"Point"}
}