{
  "type": "Feature",
  "properties": {
    "iso:country":"IN",
    "ks:ks_name":"Gerra",
    "ks:ks_pop":111,
    "ks:ks_type":"HABITATION",
    "name:eng_x_preferred":[
        "Gerra"
    ],
    "wof:name":"Gerra",
    "wof:placetype":"locality",
    "wof:population":111
},
  "geometry": {"coordinates":[80.40206999999999,19.29893],"type":"Point"}
}