{
  "type": "Feature",
  "properties": {
    "gn:country":"IN",
    "gn:fcode":"PPL",
    "gn:pop":71042,
    "iso:country":"IN",
    "name:unk_x_variant":[
        "Kamaredi"
    ],
    "qs:name":"K\u0101m\u0101reddi",
    "qs:photos_9r":0,
    "qs:photos_sr":0,
    "qs:pop_sr":"8",
    "wof:name":"K\u0101m\u0101reddi",
    "wof:placetype":"locality",
    "wof:population":71042
},
  "geometry": {"coordinates":[78.34177,18.32001],"type":"Point"}
}