{
  "type": "Feature",
  "properties": {
    "gn:admin1_code":"34.0",
    "gn:admin2_code":"235.0",
    "gn:asciiname":"Gaiwalbigha",
    "gn:country_code":"IN",
    "gn:dem":118,
    "gn:feature_class":"P",
    "gn:feature_code":"PPL",
    "gn:name":"Gaiw\u0101lbigh\u0101",
    "gn:population":0,
    "gn:timezone":"Asia/Kolkata",
    "iso:country":"IN",
    "ks:ks_name":"Gaiwalbigha",
    "ks:ks_pop":431,
    "ks:ks_type":"HABITATION",
    "name:eng_x_preferred":[
        "Gaiwalbigha"
    ],
    "wof:name":"Gaiwalbigha",
    "wof:placetype":"locality",
    "wof:population":431
},
  "geometry": {"coordinates":[84.49106399999999,24.687818],"type":"Point"}
}