{
  "type": "Feature",
  "properties": {
    "gn:admin1_code":"38.0",
    "gn:admin2_code":"352.0",
    "gn:asciiname":"Jadutola Ghaghra",
    "gn:country_code":"IN",
    "gn:dem":113,
    "gn:feature_class":"P",
    "gn:feature_code":"PPL",
    "gn:name":"J\u0101dutola Gh\u0101ghra",
    "gn:population":0,
    "gn:timezone":"Asia/Kolkata",
    "iso:country":"IN",
    "ks:ks_alt_nam":"J\u0101dutola Gh\u0101ghra",
    "ks:ks_name":"Jadutola Ghaghra",
    "ks:ks_pop":91,
    "ks:ks_type":"VILLAGE",
    "name:eng_x_preferred":[
        "Jadutola Ghaghra"
    ],
    "name:eng_x_variant":[
        "J\u0101dutola Gh\u0101ghra"
    ],
    "wof:name":"Jadutola Ghaghra",
    "wof:placetype":"locality",
    "wof:population":91
},
  "geometry": {"coordinates":[87.65325300000001,25.038972],"type":"Point"}
}