{
  "type": "Feature",
  "properties": {
    "gn:admin1_code":"38.0",
    "gn:admin2_code":"352.0",
    "gn:asciiname":"Jadutola Ghaghra",
    "gn:country_code":"IN",
    "gn:dem":113,
    "gn:feature_class":"P",
    "gn:feature_code":"PPL",
    "gn:name":"J\u0101dutola Gh\u0101ghra",
    "gn:population":0,
    "gn:timezone":"Asia/Kolkata",
    "iso:country":"IN",
    "wof:name":"Jadutola Ghaghra",
    "wof:placetype":"locality"
},
  "geometry": {"coordinates":[87.65325,25.03897000000001],"type":"Point"}
}