{
  "type": "Feature",
  "properties": {
    "iso:country":"IN",
    "ks:ks_name":"Pathli Gaon",
    "ks:ks_pop":22,
    "ks:ks_type":"VILLAGE",
    "name:eng_x_preferred":[
        "Pathli Gaon"
    ],
    "wof:name":"Pathli Gaon",
    "wof:placetype":"locality",
    "wof:population":22
},
  "geometry": {"coordinates":[78.688491,30.206313],"type":"Point"}
}