{
  "type": "Feature",
  "properties": {
    "iso:country":"IN",
    "ks:ks_name":"Thasilnaikanur",
    "ks:ks_pop":189,
    "ks:ks_type":"HABITATION",
    "ks:ks_uagg_main":0,
    "name:eng_x_preferred":[
        "Thasilnaikanur"
    ],
    "wof:name":"Thasilnaikanur",
    "wof:placetype":"neighbourhood",
    "wof:population":189
},
  "geometry": {"coordinates":[78.01372000000001,10.707661],"type":"Point"}
}