{
  "type": "Feature",
  "properties": {
    "iso:country":"IN",
    "ks:ks_name":"Kodai Singh Ka Tola",
    "ks:ks_pop":13,
    "ks:ks_type":"HABITATION",
    "ks:ks_uagg_main":0,
    "name:eng_x_preferred":[
        "Kodai Singh Ka Tola"
    ],
    "wof:name":"Kodai Singh Ka Tola",
    "wof:placetype":"neighbourhood",
    "wof:population":13
},
  "geometry": {"coordinates":[83.76168800000001,27.161759],"type":"Point"}
}