{
  "type": "Feature",
  "properties": {
    "iso:country":"IN",
    "ks:ks_alt_nam":"E.M.Temple",
    "ks:ks_name":"E.m.temple",
    "ks:ks_pop":47,
    "ks:ks_type":"HABITATION",
    "name:eng_x_preferred":[
        "E.m.temple"
    ],
    "wof:name":"E.m.temple",
    "wof:placetype":"locality",
    "wof:population":47
},
  "geometry": {"coordinates":[75.951695,12.10946],"type":"Point"}
}