{
  "type": "Feature",
  "properties": {
    "iso:country":"IN",
    "ks:ks_name":"Gol Tilla",
    "ks:ks_pop":427,
    "ks:ks_type":"HABITATION",
    "name:eng_x_preferred":[
        "Gol Tilla"
    ],
    "wof:name":"Gol Tilla",
    "wof:placetype":"locality",
    "wof:population":427
},
  "geometry": {"coordinates":[91.36881099999999,23.134236],"type":"Point"}
}