{
  "type": "Feature",
  "properties": {
    "iso:country":"IN",
    "ks:ks_name":"Markota",
    "ks:ks_type":"VILLAGE",
    "name:eng_x_preferred":[
        "Markota"
    ],
    "wof:name":"Markota",
    "wof:placetype":"locality"
},
  "geometry": {"coordinates":[78.949039,29.686398],"type":"Point"}
}