{
  "type": "Feature",
  "properties": {
    "iso:country":"IN",
    "ks:ks_name":"Panaspadar",
    "ks:ks_pop":86,
    "ks:ks_type":"VILLAGE",
    "name:eng_x_preferred":[
        "Panaspadar"
    ],
    "wof:name":"Panaspadar",
    "wof:placetype":"locality",
    "wof:population":86
},
  "geometry": {"coordinates":[82.24050099999999,18.281886],"type":"Point"}
}