{
  "type": "Feature",
  "properties": {
    "iso:country":"IN",
    "ks:ks_name":"Samya",
    "ks:ks_pop":0,
    "ks:ks_type":"VILLAGE",
    "name:eng_x_preferred":[
        "Samya"
    ],
    "wof:name":"Samya",
    "wof:placetype":"locality",
    "wof:population":0
},
  "geometry": {"coordinates":[75.29053399999999,24.366603],"type":"Point"}
}