{
  "type": "Feature",
  "properties": {
    "gn:admin1_code":"2",
    "gn:admin2_code":"546.0",
    "gn:asciiname":"Suryaraopeta",
    "gn:country_code":"IN",
    "gn:dem":10,
    "gn:feature_class":"P",
    "gn:feature_code":"PPL",
    "gn:name":"S\u016bryar\u0101opeta",
    "gn:population":0,
    "gn:timezone":"Asia/Kolkata",
    "iso:country":"IN",
    "name:bpy_x_preferred":[
        "\u09b8\u09c1\u09b0\u09bf\u09af\u09bc\u09be\u09b0\u09be\u0993\u09aa\u09c7\u09a4"
    ],
    "name:ita_x_preferred":[
        "Suryaraopeta"
    ],
    "name:msa_x_preferred":[
        "Suryaraopeta"
    ],
    "name:nld_x_preferred":[
        "Suryaraopeta"
    ],
    "name:por_x_preferred":[
        "Suryaraopeta"
    ],
    "name:vie_x_preferred":[
        "Suryaraopeta"
    ],
    "name:zho_x_preferred":[
        "\u82cf\u91cc\u4e9a\u62c9\u5965\u4f69\u5854"
    ],
    "wof:name":"Suryaraopeta",
    "wof:placetype":"locality"
},
  "geometry": {"coordinates":[81.41964,16.54597],"type":"Point"}
}