{
  "type": "Feature",
  "properties": {
    "iso:country":"IN",
    "ks:ks_name":"Mulluva Kunnu",
    "ks:ks_pop":946,
    "ks:ks_type":"HABITATION",
    "name:eng_x_preferred":[
        "Mulluva Kunnu"
    ],
    "wof:name":"Mulluva Kunnu",
    "wof:placetype":"locality",
    "wof:population":946
},
  "geometry": {"coordinates":[76.133956,10.900278],"type":"Point"}
}