{
  "type": "Feature",
  "properties": {
    "iso:country":"IN",
    "ks:ks_name":"Badakharikuti",
    "ks:ks_pop":97,
    "ks:ks_type":"VILLAGE",
    "name:eng_x_preferred":[
        "Badakharikuti"
    ],
    "wof:name":"Badakharikuti",
    "wof:placetype":"locality",
    "wof:population":97
},
  "geometry": {"coordinates":[83.84639199999999,19.363279],"type":"Point"}
}