{
  "type": "Feature",
  "properties": {
    "iso:country":"IN",
    "ks:ks_name":"Hadali",
    "ks:ks_pop":126,
    "ks:ks_type":"HABITATION",
    "name:eng_x_preferred":[
        "Hadali"
    ],
    "wof:name":"Hadali",
    "wof:placetype":"locality",
    "wof:population":126
},
  "geometry": {"coordinates":[74.80359,13.6295],"type":"Point"}
}