{
  "type": "Feature",
  "properties": {
    "iso:country":"IN",
    "ks:ks_name":"Ervuailu",
    "ks:ks_pop":2761,
    "ks:ks_type":"VILLAGE",
    "name:eng_x_preferred":[
        "Ervuailu"
    ],
    "wof:name":"Ervuailu",
    "wof:placetype":"locality",
    "wof:population":2761
},
  "geometry": {"coordinates":[75.012838,12.997102],"type":"Point"}
}