{
  "type": "Feature",
  "properties": {
    "iso:country":"IN",
    "ks:ks_name":"Nandepuvaripalem",
    "ks:ks_pop":299,
    "ks:ks_type":"HABITATION",
    "name:eng_x_preferred":[
        "Nandepuvaripalem"
    ],
    "wof:name":"Nandepuvaripalem",
    "wof:placetype":"locality",
    "wof:population":299
},
  "geometry": {"coordinates":[81.948274,16.624351],"type":"Point"}
}