{
  "type": "Feature",
  "properties": {
    "iso:country":"IN",
    "ks:ks_name":"Kottappally",
    "ks:ks_pop":19417,
    "ks:ks_type":"VILLAGE",
    "name:eng_x_preferred":[
        "Kottappally"
    ],
    "wof:name":"Kottappally",
    "wof:placetype":"locality",
    "wof:population":19417
},
  "geometry": {"coordinates":[75.658933,11.608614],"type":"Point"}
}