{
  "type": "Feature",
  "properties": {
    "gn:admin1_code":"2.0",
    "gn:admin2_code":"551.0",
    "gn:asciiname":"Palampalle",
    "gn:country_code":"IN",
    "gn:dem":129,
    "gn:feature_class":"P",
    "gn:feature_code":"PPL",
    "gn:name":"P\u0101lampalle",
    "gn:population":0,
    "gn:timezone":"Asia/Kolkata",
    "iso:country":"IN",
    "ks:ks_alt_nam":"P\u0101lampalle",
    "ks:ks_name":"Palampalle",
    "ks:ks_type":"VILLAGE",
    "ks:ks_uagg_main":0,
    "name:eng_x_preferred":[
        "Palampalle"
    ],
    "name:eng_x_variant":[
        "P\u0101lampalle"
    ],
    "wof:name":"Palampalle",
    "wof:placetype":"locality"
},
  "geometry": {"coordinates":[78.813546,14.50103],"type":"Point"}
}