{
  "type": "Feature",
  "properties": {
    "iso:country":"IN",
    "ks:ks_name":"1 No Mashusudanpur",
    "ks:ks_pop":1398,
    "ks:ks_type":"HABITATION",
    "name:eng_x_preferred":[
        "1 No Mashusudanpur"
    ],
    "wof:name":"1 No Mashusudanpur",
    "wof:placetype":"locality",
    "wof:population":1398
},
  "geometry": {"coordinates":[88.58329500000001,22.07365],"type":"Point"}
}