{
  "type": "Feature",
  "properties": {
    "gn:country":"IN",
    "gn:fcode":"PPL",
    "gn:pop":57283,
    "iso:country":"IN",
    "name:ben_x_preferred":[
        "\u09a8\u0995\u09b6\u09be\u09b2\u09ac\u09be\u09a1\u09bc\u09bf"
    ],
    "name:dut_x_preferred":[
        "Naxalbari"
    ],
    "name:eng_x_preferred":[
        "Naxalbari"
    ],
    "name:fre_x_preferred":[
        "Naxalbari"
    ],
    "name:hin_x_preferred":[
        "\u0928\u0915\u094d\u0938\u0932\u092c\u093e\u0921\u093c\u0940"
    ],
    "name:ita_x_preferred":[
        "Naxalbari"
    ],
    "name:mal_x_preferred":[
        "\u0d28\u0d15\u0d4d\u0d38\u0d7d\u0d2c\u0d3e\u0d30\u0d3f"
    ],
    "name:nob_x_preferred":[
        "Naxalbari"
    ],
    "name:rus_x_preferred":[
        "\u041d\u0430\u043a\u0441\u0430\u043b\u0431\u0430\u0440\u0438"
    ],
    "name:sco_x_preferred":[
        "Naxalbari"
    ],
    "name:spa_x_preferred":[
        "Naxalbari"
    ],
    "name:swe_x_preferred":[
        "Naxalbari"
    ],
    "name:tam_x_preferred":[
        "\u0ba8\u0b95\u0bcd\u0b9a\u0bb2\u0bcd\u0baa\u0bbe\u0bb0\u0bbf"
    ],
    "name:unk_x_variant":[
        "Naxalbari"
    ],
    "qs:name":"Naksalb\u0101ri",
    "qs:photos_9r":0,
    "qs:photos_sr":0,
    "qs:pop_sr":"8",
    "wd:elevation":152.0,
    "wd:wordcount":777,
    "wof:name":"Naksalb\u0101ri",
    "wof:placetype":"locality",
    "wof:population":57283
},
  "geometry": {"coordinates":[88.22,26.6827],"type":"Point"}
}