{
  "type": "Feature",
  "properties": {
    "gn:admin1_code":"19.0",
    "gn:admin2_code":"567.0",
    "gn:asciiname":"Kurimeganahalli",
    "gn:country_code":"IN",
    "gn:dem":650,
    "gn:feature_class":"P",
    "gn:feature_code":"PPL",
    "gn:name":"Kurimeganahalli",
    "gn:population":0,
    "gn:timezone":"Asia/Kolkata",
    "iso:country":"IN",
    "wof:name":"Kurimeganahalli",
    "wof:placetype":"locality"
},
  "geometry": {"coordinates":[76.06183,14.52666],"type":"Point"}
}