{
  "type": "Feature",
  "properties": {
    "iso:country":"IN",
    "ks:ks_alt_nam":"Balh\u0101rpur",
    "ks:ks_name":"Balharpur",
    "ks:ks_type":"VILLAGE",
    "name:eng_x_preferred":[
        "Balharpur"
    ],
    "name:eng_x_variant":[
        "Balh\u0101rpur"
    ],
    "wof:name":"Balharpur",
    "wof:placetype":"locality"
},
  "geometry": {"coordinates":[77.126947,25.11052],"type":"Point"}
}