{
  "type": "Feature",
  "properties": {
    "gn:admin1_code":"12.0",
    "gn:admin2_code":"14.0",
    "gn:asciiname":"Raylhmandu",
    "gn:country_code":"IN",
    "gn:dem":3391,
    "gn:feature_class":"P",
    "gn:feature_code":"PPL",
    "gn:name":"R\u0101ylhmandu",
    "gn:population":0,
    "gn:timezone":"Asia/Kolkata",
    "iso:country":"IN",
    "wof:name":"Raylhmandu",
    "wof:placetype":"locality"
},
  "geometry": {"coordinates":[75.45578,33.4468],"type":"Point"}
}