{
  "type": "Feature",
  "properties": {
    "iso:country":"IN",
    "ks:ks_name":"Muslim Colony",
    "ks:ks_pop":69,
    "ks:ks_type":"HABITATION",
    "name:eng_x_preferred":[
        "Muslim Colony"
    ],
    "wof:name":"Muslim Colony",
    "wof:placetype":"locality",
    "wof:population":69
},
  "geometry": {"coordinates":[74.289339,14.715916],"type":"Point"}
}