{
  "type": "Feature",
  "properties": {
    "iso:country":"IN",
    "ks:ks_name":"H.honnavally",
    "ks:ks_pop":784,
    "ks:ks_type":"HABITATION",
    "name:eng_x_preferred":[
        "H.honnavally"
    ],
    "wof:name":"H.honnavally",
    "wof:placetype":"locality",
    "wof:population":784
},
  "geometry": {"coordinates":[75.90941599999999,12.826798],"type":"Point"}
}