{
  "type": "Feature",
  "properties": {
    "gn:admin1_code":"10.0",
    "gn:admin2_code":"69.0",
    "gn:asciiname":"Bandh",
    "gn:country_code":"IN",
    "gn:dem":855,
    "gn:feature_class":"P",
    "gn:feature_code":"PPL",
    "gn:name":"B\u0101ndh",
    "gn:population":0,
    "gn:timezone":"Asia/Kolkata",
    "iso:country":"IN",
    "name:hin_x_preferred":[
        "\u092c\u0928\u094d\u0926"
    ],
    "name:nld_x_preferred":[
        "Bandh"
    ],
    "name:nor_x_preferred":[
        "Bandh"
    ],
    "name:pol_x_preferred":[
        "Bandh"
    ],
    "name:por_x_preferred":[
        "Bandh"
    ],
    "name:rus_x_preferred":[
        "\u0411\u0430\u043d\u0434\u0445"
    ],
    "name:tam_x_preferred":[
        "\u0b95\u0b9f\u0bc8\u0baf\u0b9f\u0bc8\u0baa\u0bcd\u0baa\u0bc1"
    ],
    "name:tel_x_preferred":[
        "\u0c2c\u0c02\u0c26\u0c4d"
    ],
    "wof:name":"Bandh",
    "wof:placetype":"locality"
},
  "geometry": {"coordinates":[77.13864000000002,30.66722],"type":"Point"}
}