{
  "type": "Feature",
  "properties": {
    "gn:admin1_code":"28.0",
    "gn:admin2_code":"328.0",
    "gn:asciiname":"Banarhat",
    "gn:country_code":"IN",
    "gn:dem":157,
    "gn:feature_class":"P",
    "gn:feature_code":"PPL",
    "gn:name":"Banarhat",
    "gn:population":0,
    "gn:timezone":"Asia/Kolkata",
    "iso:country":"IN",
    "name:hin_x_preferred":[
        "\u092c\u093e\u0928\u0930\u0939\u093e\u091f"
    ],
    "name:zho_x_preferred":[
        "\u5df4\u7eb3\u5c14\u54c8\u7279\u6cf0\u963f\u52a0\u5c14\u767b"
    ],
    "wof:name":"Banarhat",
    "wof:placetype":"neighbourhood"
},
  "geometry": {"coordinates":[89.02869,26.792],"type":"Point"}
}