{
  "type": "Feature",
  "properties": {
    "gn:admin1_code":"16.0",
    "gn:admin2_code":"505.0",
    "gn:asciiname":"Isapur Khurd",
    "gn:country_code":"IN",
    "gn:dem":436,
    "gn:feature_class":"P",
    "gn:feature_code":"PPL",
    "gn:name":"Is\u0101pur Khurd",
    "gn:population":0,
    "gn:timezone":"Asia/Kolkata",
    "iso:country":"IN",
    "wof:name":"Isapur Khurd",
    "wof:placetype":"locality"
},
  "geometry": {"coordinates":[78.64684,21.32701],"type":"Point"}
}