{
  "type": "Feature",
  "properties": {
    "iso:country":"IN",
    "ks:ks_name":"Fakeernaikthnada",
    "ks:ks_pop":277,
    "ks:ks_type":"HABITATION",
    "name:eng_x_preferred":[
        "Fakeernaikthnada"
    ],
    "wof:name":"Fakeernaikthnada",
    "wof:placetype":"locality",
    "wof:population":277
},
  "geometry": {"coordinates":[78.660505,19.393363],"type":"Point"}
}