{
  "type": "Feature",
  "properties": {
    "gn:admin1_code":"11",
    "gn:admin2_code":"31.0",
    "gn:asciiname":"Thala",
    "gn:country_code":"IN",
    "gn:dem":455,
    "gn:feature_class":"P",
    "gn:feature_code":"PPL",
    "gn:name":"Thala",
    "gn:population":0,
    "gn:timezone":"Asia/Kolkata",
    "iso:country":"IN",
    "name:ceb_x_preferred":[
        "Thala"
    ],
    "name:deu_x_preferred":[
        "Thala"
    ],
    "name:fra_x_preferred":[
        "Thala"
    ],
    "wof:name":"Thala",
    "wof:placetype":"locality"
},
  "geometry": {"coordinates":[76.71826,31.1483],"type":"Point"}
}