{
  "type": "Feature",
  "properties": {
    "gn:admin1_code":"21",
    "gn:admin2_code":"392.0",
    "gn:asciiname":"Cherupali",
    "gn:country_code":"IN",
    "gn:dem":136,
    "gn:feature_class":"P",
    "gn:feature_code":"PPL",
    "gn:name":"Cherup\u0101li",
    "gn:population":0,
    "gn:timezone":"Asia/Kolkata",
    "iso:country":"IN",
    "wof:name":"Cherupali",
    "wof:placetype":"locality"
},
  "geometry": {"coordinates":[83.80319,21.08177],"type":"Point"}
}