{
  "type": "Feature",
  "properties": {
    "iso:country":"IN",
    "ks:ks_name":"Sreenivasapuram",
    "ks:ks_pop":27,
    "ks:ks_type":"HABITATION",
    "name:eng_x_preferred":[
        "Sreenivasapuram"
    ],
    "wof:name":"Sreenivasapuram",
    "wof:placetype":"locality",
    "wof:population":27
},
  "geometry": {"coordinates":[78.694704,14.687906],"type":"Point"}
}