{
  "type": "Feature",
  "properties": {
    "iso:country":"IN",
    "ks:ks_name":"Bharganwa",
    "ks:ks_pop":115,
    "ks:ks_type":"VILLAGE",
    "name:eng_x_preferred":[
        "Bharganwa"
    ],
    "wof:name":"Bharganwa",
    "wof:placetype":"locality",
    "wof:population":115
},
  "geometry": {"coordinates":[83.12619599999999,24.632653],"type":"Point"}
}