{
  "type": "Feature",
  "properties": {
    "iso:country":"IN",
    "ks:ks_name":"Gadgalia",
    "ks:ks_pop":305,
    "ks:ks_type":"HABITATION",
    "name:eng_x_preferred":[
        "Gadgalia"
    ],
    "wof:name":"Gadgalia",
    "wof:placetype":"locality",
    "wof:population":305
},
  "geometry": {"coordinates":[88.083589,22.979384],"type":"Point"}
}