{
  "type": "Feature",
  "properties": {
    "iso:country":"IN",
    "ks:ks_name":"Neknam Chak",
    "ks:ks_pop":1567,
    "ks:ks_type":"VILLAGE",
    "ks:ks_uagg_main":0,
    "name:eng_x_preferred":[
        "Neknam Chak"
    ],
    "wof:name":"Neknam Chak",
    "wof:placetype":"neighbourhood",
    "wof:population":1567
},
  "geometry": {"coordinates":[85.259281,26.311504],"type":"Point"}
}