{
  "type": "Feature",
  "properties": {
    "iso:country":"IN",
    "ks:ks_name":"Dihuli",
    "ks:ks_pop":321,
    "ks:ks_type":"HABITATION",
    "name:eng_x_preferred":[
        "Dihuli"
    ],
    "wof:name":"Dihuli",
    "wof:placetype":"locality",
    "wof:population":321
},
  "geometry": {"coordinates":[79.75366699999999,27.121507],"type":"Point"}
}