{
  "type": "Feature",
  "properties": {
    "gn:admin1_code":"40",
    "gn:admin2_code":"540.0",
    "gn:asciiname":"Pedda Nagaram",
    "gn:country_code":"IN",
    "gn:dem":200,
    "gn:feature_class":"P",
    "gn:feature_code":"PPL",
    "gn:name":"Pedda N\u0101g\u0101ram",
    "gn:population":0,
    "gn:timezone":"Asia/Kolkata",
    "iso:country":"IN",
    "name:eng_x_preferred":[
        "Pedda N\u0101g\u0101ram"
    ],
    "wof:name":"Pedda Nagaram",
    "wof:placetype":"locality"
},
  "geometry": {"coordinates":[79.82141999999997,17.46216],"type":"Point"}
}