{
  "type": "Feature",
  "properties": {
    "iso:country":"IN",
    "ks:ks_name":"Pinglewasti",
    "ks:ks_pop":89,
    "ks:ks_type":"HABITATION",
    "name:eng_x_preferred":[
        "Pinglewasti"
    ],
    "wof:name":"Pinglewasti",
    "wof:placetype":"locality",
    "wof:population":89
},
  "geometry": {"coordinates":[74.304755,19.356336],"type":"Point"}
}