{
  "type": "Feature",
  "properties": {
    "iso:country":"IN",
    "ks:ks_name":"Bhashnirchar Pt.II",
    "ks:ks_pop":389,
    "ks:ks_type":"VILLAGE",
    "name:eng_x_preferred":[
        "Bhashnirchar Pt.II"
    ],
    "wof:name":"Bhashnirchar Pt.II",
    "wof:placetype":"locality",
    "wof:population":389
},
  "geometry": {"coordinates":[89.928898,25.999056],"type":"Point"}
}