{
  "type": "Feature",
  "properties": {
    "iso:country":"IN",
    "ks:ks_name":"Lumi Sipu",
    "ks:ks_pop":33,
    "ks:ks_type":"HABITATION",
    "name:eng_x_preferred":[
        "Lumi Sipu"
    ],
    "wof:name":"Lumi Sipu",
    "wof:placetype":"locality",
    "wof:population":33
},
  "geometry": {"coordinates":[94.177864,27.482653],"type":"Point"}
}