{
  "type": "Feature",
  "properties": {
    "gn:admin1_code":"25.0",
    "gn:admin2_code":"632.0",
    "gn:asciiname":"Attavanaichemmilanjanpatti",
    "gn:country_code":"IN",
    "gn:dem":360,
    "gn:feature_class":"P",
    "gn:feature_code":"PPL",
    "gn:name":"Attavanaichemm\u012blanjanpatti",
    "gn:population":0,
    "gn:timezone":"Asia/Kolkata",
    "iso:country":"IN",
    "wof:name":"Attavanaichemmilanjanpatti",
    "wof:placetype":"locality"
},
  "geometry": {"coordinates":[77.04297,11.24538],"type":"Point"}
}