{
  "type": "Feature",
  "properties": {
    "iso:country":"IN",
    "ks:ks_alt_nam":"Kadamtala 1 No. and 2 No.",
    "ks:ks_name":"Kadamtala 1 No. And 2 No.",
    "ks:ks_pop":107,
    "ks:ks_type":"HABITATION",
    "ks:ks_uagg_main":0,
    "name:eng_x_preferred":[
        "Kadamtala 1 No. And 2 No."
    ],
    "wof:name":"Kadamtala 1 No. And 2 No.",
    "wof:placetype":"neighbourhood",
    "wof:population":107
},
  "geometry": {"coordinates":[94.79212699999999,27.592877],"type":"Point"}
}