{
  "type": "Feature",
  "properties": {
    "gn:admin1_code":"2.0",
    "gn:admin2_code":"549.0",
    "gn:asciiname":"Nagandla",
    "gn:country_code":"IN",
    "gn:dem":30,
    "gn:feature_class":"P",
    "gn:feature_code":"PPL",
    "gn:name":"N\u0101gandla",
    "gn:population":0,
    "gn:timezone":"Asia/Kolkata",
    "iso:country":"IN",
    "name:tel_x_preferred":[
        "\u0c28\u0c3e\u0c17\u0c02\u0c21\u0c4d\u0c32"
    ],
    "name:und_x_variant":[
        "N\u0101gandla"
    ],
    "wof:name":"Nagandla",
    "wof:placetype":"locality"
},
  "geometry": {"coordinates":[80.14431999999999,15.88228],"type":"Point"}
}