{
  "type": "Feature",
  "properties": {
    "iso:country":"IN",
    "ks:ks_name":"Khan Khas",
    "ks:ks_pop":677,
    "ks:ks_type":"HABITATION",
    "ks:ks_uagg_main":0,
    "name:eng_x_preferred":[
        "Khan Khas"
    ],
    "wof:name":"Khan Khas",
    "wof:placetype":"neighbourhood",
    "wof:population":677
},
  "geometry": {"coordinates":[82.509253,26.540322],"type":"Point"}
}