{
  "type": "Feature",
  "properties": {
    "gn:admin1_code":"25.0",
    "gn:admin2_code":"611.0",
    "gn:asciiname":"Kilodayaratti",
    "gn:country_code":"IN",
    "gn:dem":2012,
    "gn:feature_class":"P",
    "gn:feature_code":"PPL",
    "gn:name":"K\u012blodayaratti",
    "gn:population":0,
    "gn:timezone":"Asia/Kolkata",
    "iso:country":"IN",
    "wof:name":"Kilodayaratti",
    "wof:placetype":"locality"
},
  "geometry": {"coordinates":[76.73877,11.35851],"type":"Point"}
}