{
  "type": "Feature",
  "properties": {
    "gn:admin1_code":"24.0",
    "gn:admin2_code":"118.0",
    "gn:asciiname":"Khari",
    "gn:country_code":"IN",
    "gn:dem":179,
    "gn:feature_class":"P",
    "gn:feature_code":"PPL",
    "gn:name":"Kh\u0101ri",
    "gn:population":0,
    "gn:timezone":"Asia/Kolkata",
    "iso:country":"IN",
    "name:ceb_x_preferred":[
        "Khari"
    ],
    "name:deu_x_preferred":[
        "Khari"
    ],
    "name:msa_x_preferred":[
        "Khari"
    ],
    "name:new_x_preferred":[
        "\u0916\u0930\u0940"
    ],
    "name:pol_x_preferred":[
        "Khari"
    ],
    "wof:name":"Khari",
    "wof:placetype":"locality"
},
  "geometry": {"coordinates":[73.01881,25.93342],"type":"Point"}
}