{
  "type": "Feature",
  "properties": {
    "gn:admin1_code":"12.0",
    "gn:admin2_code":"19.0",
    "gn:asciiname":"Sarna",
    "gn:country_code":"IN",
    "gn:dem":1320,
    "gn:feature_class":"P",
    "gn:feature_code":"PPL",
    "gn:name":"S\u0101rna",
    "gn:population":0,
    "gn:timezone":"Asia/Kolkata",
    "iso:country":"IN",
    "name:deu_x_preferred":[
        "Sarna"
    ],
    "name:fra_x_preferred":[
        "Sarna"
    ],
    "name:ita_x_preferred":[
        "Sarna"
    ],
    "name:pol_x_preferred":[
        "Sarna"
    ],
    "name:spa_x_preferred":[
        "Sarna"
    ],
    "name:srp_x_preferred":[
        "Sarna"
    ],
    "wof:name":"Sarna",
    "wof:placetype":"locality"
},
  "geometry": {"coordinates":[75.36883,32.68638],"type":"Point"}
}