{
  "type": "Feature",
  "properties": {
    "iso:country":"IN",
    "ks:ks_name":"Munthamamidi",
    "ks:ks_pop":36,
    "ks:ks_type":"HABITATION",
    "name:eng_x_preferred":[
        "Munthamamidi"
    ],
    "wof:name":"Munthamamidi",
    "wof:placetype":"locality",
    "wof:population":36
},
  "geometry": {"coordinates":[82.595939,18.148374],"type":"Point"}
}