{
  "type": "Feature",
  "properties": {
    "iso:country":"IN",
    "ks:ks_name":"Gdulhiya",
    "ks:ks_pop":499,
    "ks:ks_type":"HABITATION",
    "ks:ks_uagg_main":0,
    "name:eng_x_preferred":[
        "Gdulhiya"
    ],
    "wof:name":"Gdulhiya",
    "wof:placetype":"neighbourhood",
    "wof:population":499
},
  "geometry": {"coordinates":[83.54050700000001,27.167998],"type":"Point"}
}