{
  "type": "Feature",
  "properties": {
    "gn:admin1_code":"34.0",
    "gn:admin2_code":"234.0",
    "gn:asciiname":"Bariyarpur",
    "gn:country_code":"IN",
    "gn:dem":83,
    "gn:feature_class":"P",
    "gn:feature_code":"PPL",
    "gn:name":"Bariy\u0101rpur",
    "gn:population":0,
    "gn:timezone":"Asia/Kolkata",
    "iso:country":"IN",
    "name:fra_x_preferred":[
        "Bariyarpur"
    ],
    "name:pol_x_preferred":[
        "Bariyarpur"
    ],
    "wof:name":"Bariyarpur",
    "wof:placetype":"locality"
},
  "geometry": {"coordinates":[84.02403000000002,25.25472],"type":"Point"}
}