{
  "type": "Feature",
  "properties": {
    "iso:country":"IN",
    "ks:ks_name":"Das Para Purba",
    "ks:ks_pop":2921,
    "ks:ks_type":"HABITATION",
    "name:eng_x_preferred":[
        "Das Para Purba"
    ],
    "wof:name":"Das Para Purba",
    "wof:placetype":"locality",
    "wof:population":2921
},
  "geometry": {"coordinates":[88.68064800000001,22.213951],"type":"Point"}
}