{
  "type": "Feature",
  "properties": {
    "gn:admin1_code":"35.0",
    "gn:admin2_code":"463.0",
    "gn:asciiname":"Pipra",
    "gn:country_code":"IN",
    "gn:dem":391,
    "gn:feature_class":"P",
    "gn:feature_code":"PPL",
    "gn:name":"Pipra",
    "gn:population":0,
    "gn:timezone":"Asia/Kolkata",
    "iso:country":"IN",
    "name:bre_x_preferred":[
        "Pipra"
    ],
    "name:cat_x_preferred":[
        "Pipra"
    ],
    "name:ceb_x_preferred":[
        "Pipra"
    ],
    "name:fas_x_preferred":[
        "\u0631\u0646\u06af\u06cc\u0646\u06a9"
    ],
    "name:fin_x_preferred":[
        "Tulitanssijat"
    ],
    "name:fra_x_preferred":[
        "Pipra"
    ],
    "name:hun_x_preferred":[
        "Pipra"
    ],
    "name:mrj_x_preferred":[
        "\u041f\u0438\u043f\u0440\u0430\u0432\u043b\u04d3"
    ],
    "name:new_x_preferred":[
        "\u092a\u093f\u092a\u094d\u0930\u093e"
    ],
    "name:nld_x_preferred":[
        "Pipra"
    ],
    "name:pol_x_preferred":[
        "Pipra"
    ],
    "name:por_x_preferred":[
        "Pipra"
    ],
    "name:rus_x_preferred":[
        "\u041f\u0438\u043f\u0440\u044b"
    ],
    "name:spa_x_preferred":[
        "Pipra"
    ],
    "name:swe_x_preferred":[
        "Pipra"
    ],
    "name:vie_x_preferred":[
        "Pipra"
    ],
    "name:war_x_preferred":[
        "Pipra"
    ],
    "wof:name":"Pipra",
    "wof:placetype":"locality"
},
  "geometry": {"coordinates":[82.57728,24.26272],"type":"Point"}
}