{
  "type": "Feature",
  "properties": {
    "iso:country":"IN",
    "ks:ks_name":"Rengalbahal",
    "ks:ks_pop":559,
    "ks:ks_type":"VILLAGE",
    "name:eng_x_preferred":[
        "Rengalbahal"
    ],
    "wof:name":"Rengalbahal",
    "wof:placetype":"locality",
    "wof:population":559
},
  "geometry": {"coordinates":[84.656637,21.341983],"type":"Point"}
}