{
  "type": "Feature",
  "properties": {
    "gn:admin1_code":"37.0",
    "gn:admin2_code":"411.0",
    "gn:asciiname":"Kurrubhata",
    "gn:country_code":"IN",
    "gn:dem":315,
    "gn:feature_class":"P",
    "gn:feature_code":"PPL",
    "gn:name":"Kurrubhata",
    "gn:population":0,
    "gn:timezone":"Asia/Kolkata",
    "iso:country":"IN",
    "wof:name":"Kurrubhata",
    "wof:placetype":"locality"
},
  "geometry": {"coordinates":[82.39671,21.23534],"type":"Point"}
}