{
  "type": "Feature",
  "properties": {
    "iso:country":"IN",
    "ks:ks_name":"Kotady Khurd",
    "ks:ks_pop":28,
    "ks:ks_type":"HABITATION",
    "name:eng_x_preferred":[
        "Kotady Khurd"
    ],
    "wof:name":"Kotady Khurd",
    "wof:placetype":"locality",
    "wof:population":28
},
  "geometry": {"coordinates":[75.260721,24.533576],"type":"Point"}
}