{
  "type": "Feature",
  "properties": {
    "iso:country":"IN",
    "ks:ks_name":"Hadirtoli",
    "ks:ks_pop":206,
    "ks:ks_type":"HABITATION",
    "name:eng_x_preferred":[
        "Hadirtoli"
    ],
    "wof:name":"Hadirtoli",
    "wof:placetype":"locality",
    "wof:population":206
},
  "geometry": {"coordinates":[84.97153900000001,23.136947],"type":"Point"}
}