{
  "type": "Feature",
  "properties": {
    "gn:admin1_code":"11",
    "gn:admin2_code":"23.0",
    "gn:asciiname":"Tair Uparli",
    "gn:country_code":"IN",
    "gn:dem":2095,
    "gn:feature_class":"P",
    "gn:feature_code":"PPL",
    "gn:name":"Tair \u016aparli",
    "gn:population":0,
    "gn:timezone":"Asia/Kolkata",
    "iso:country":"IN",
    "wof:name":"Tair Uparli",
    "wof:placetype":"locality"
},
  "geometry": {"coordinates":[76.55199,32.34338],"type":"Point"}
}