{
  "type": "Feature",
  "properties": {
    "iso:country":"IN",
    "ks:ks_alt_nam":"kalkawadi",
    "ks:ks_name":"Kalkawadi",
    "ks:ks_pop":98,
    "ks:ks_type":"HABITATION",
    "name:eng_x_preferred":[
        "Kalkawadi"
    ],
    "wof:name":"Kalkawadi",
    "wof:placetype":"locality",
    "wof:population":98
},
  "geometry": {"coordinates":[73.823526,18.043331],"type":"Point"}
}