{
  "type": "Feature",
  "properties": {
    "iso:country":"IN",
    "ks:ks_name":"Roopapur",
    "ks:ks_pop":638,
    "ks:ks_type":"VILLAGE",
    "ks:ks_uagg_main":0,
    "name:eng_x_preferred":[
        "Roopapur"
    ],
    "wof:name":"Roopapur",
    "wof:placetype":"neighbourhood",
    "wof:population":638
},
  "geometry": {"coordinates":[78.97724700000001,29.050513],"type":"Point"}
}