{
  "type": "Feature",
  "properties": {
    "iso:country":"IN",
    "ks:ks_name":"28 BD",
    "ks:ks_pop":294,
    "ks:ks_type":"VILLAGE",
    "name:eng_x_preferred":[
        "28 BD"
    ],
    "wof:name":"28 BD",
    "wof:placetype":"locality",
    "wof:population":294
},
  "geometry": {"coordinates":[72.48721500000001,28.784236],"type":"Point"}
}