{
  "type": "Feature",
  "properties": {
    "iso:country":"IN",
    "ks:ks_name":"Waijapur",
    "ks:ks_pop":261,
    "ks:ks_type":"VILLAGE",
    "ks:ks_uagg_main":0,
    "name:eng_x_preferred":[
        "Waijapur"
    ],
    "wof:name":"Waijapur",
    "wof:placetype":"neighbourhood",
    "wof:population":261
},
  "geometry": {"coordinates":[78.101389,20.542222],"type":"Point"}
}