{
  "type": "Feature",
  "properties": {
    "gn:admin1_code":"19.0",
    "gn:admin2_code":"574.0",
    "gn:asciiname":"Hirigarje",
    "gn:country_code":"IN",
    "gn:dem":1040,
    "gn:feature_class":"P",
    "gn:feature_code":"PPL",
    "gn:name":"Hirigarje",
    "gn:population":0,
    "gn:timezone":"Asia/Kolkata",
    "iso:country":"IN",
    "ks:ks_name":"Hirigarje",
    "ks:ks_pop":531,
    "ks:ks_type":"VILLAGE",
    "name:eng_x_preferred":[
        "Hirigarje"
    ],
    "wof:name":"Hirigarje",
    "wof:placetype":"locality",
    "wof:population":531
},
  "geometry": {"coordinates":[75.823684,13.047151],"type":"Point"}
}