{
  "type": "Feature",
  "properties": {
    "gn:admin1_code":"16",
    "gn:admin2_code":"505.0",
    "gn:asciiname":"Dudhbardi",
    "gn:country_code":"IN",
    "gn:dem":324,
    "gn:feature_class":"P",
    "gn:feature_code":"PPL",
    "gn:name":"Dudhbardi",
    "gn:population":0,
    "gn:timezone":"Asia/Kolkata",
    "iso:country":"IN",
    "ks:ks_name":"Dudhbardi",
    "ks:ks_type":"VILLAGE",
    "name:eng_x_preferred":[
        "Dudhbardi"
    ],
    "wof:name":"Dudhbardi",
    "wof:placetype":"locality"
},
  "geometry": {"coordinates":[78.938614,21.425224],"type":"Point"}
}