{
  "type": "Feature",
  "properties": {
    "iso:country":"IN",
    "ks:ks_name":"Badrakali",
    "ks:ks_pop":1000,
    "ks:ks_type":"HABITATION",
    "ks:ks_uagg_main":0,
    "name:eng_x_preferred":[
        "Badrakali"
    ],
    "wof:name":"Badrakali",
    "wof:placetype":"neighbourhood",
    "wof:population":1000
},
  "geometry": {"coordinates":[76.40226699999999,10.203814],"type":"Point"}
}