{
  "type": "Feature",
  "properties": {
    "iso:country":"IN",
    "ks:ks_name":"Ahari",
    "ks:ks_pop":874,
    "ks:ks_type":"VILLAGE",
    "name:eng_x_preferred":[
        "Ahari"
    ],
    "wof:name":"Ahari",
    "wof:placetype":"locality",
    "wof:population":874
},
  "geometry": {"coordinates":[86.75904300000001,21.854584],"type":"Point"}
}