{
  "type": "Feature",
  "properties": {
    "iso:country":"IN",
    "ks:ks_name":"Dauapura",
    "ks:ks_pop":247,
    "ks:ks_type":"HABITATION",
    "name:eng_x_preferred":[
        "Dauapura"
    ],
    "wof:name":"Dauapura",
    "wof:placetype":"locality",
    "wof:population":247
},
  "geometry": {"coordinates":[78.572113,24.931704],"type":"Point"}
}