{
  "type": "Feature",
  "properties": {
    "gn:admin1_code":"34.0",
    "gn:admin2_code":"221.0",
    "gn:asciiname":"Pokhraira",
    "gn:country_code":"IN",
    "gn:dem":56,
    "gn:feature_class":"P",
    "gn:feature_code":"PPL",
    "gn:name":"Pokhraira",
    "gn:population":0,
    "gn:timezone":"Asia/Kolkata",
    "iso:country":"IN",
    "ks:ks_name":"Pokhraira",
    "ks:ks_pop":2749,
    "ks:ks_type":"VILLAGE",
    "name:eng_x_preferred":[
        "Pokhraira"
    ],
    "wof:name":"Pokhraira",
    "wof:placetype":"locality",
    "wof:population":2749
},
  "geometry": {"coordinates":[85.75504599999999,25.914857],"type":"Point"}
}