{
  "type": "Feature",
  "properties": {
    "gn:admin1_code":"35",
    "gn:admin2_code":"425.0",
    "gn:asciiname":"Obripurwa",
    "gn:country_code":"IN",
    "gn:dem":301,
    "gn:feature_class":"P",
    "gn:feature_code":"PPL",
    "gn:name":"Obr\u012bpurwa",
    "gn:population":0,
    "gn:timezone":"Asia/Kolkata",
    "iso:country":"IN",
    "wof:name":"Obripurwa",
    "wof:placetype":"locality"
},
  "geometry": {"coordinates":[79.2594,24.63247],"type":"Point"}
}