{
  "type": "Feature",
  "properties": {
    "iso:country":"IN",
    "qs:name":"Dhorom",
    "qs:name_adm0":"India",
    "qs:name_adm1":"Meghalaya",
    "qs:photos":6,
    "qs:photos_1k":1,
    "qs:photos_9k":1,
    "qs:photos_9r":1,
    "qs:photos_all":6,
    "qs:photos_sr":1,
    "qs:placetype":"Town",
    "qs:pop_sr":"0",
    "wof:name":"Dhorom",
    "wof:placetype":"locality"
},
  "geometry": {"coordinates":[91.73866599999999,25.155166],"type":"Point"}
}