{
  "type": "Feature",
  "properties": {
    "iso:country":"IN",
    "ks:ks_name":"Siripuria",
    "ks:ks_pop":942,
    "ks:ks_type":"HABITATION",
    "ks:ks_uagg_main":0,
    "name:eng_x_preferred":[
        "Siripuria"
    ],
    "wof:name":"Siripuria",
    "wof:placetype":"neighbourhood",
    "wof:population":942
},
  "geometry": {"coordinates":[94.50927799999999,26.965066],"type":"Point"}
}