{
  "type": "Feature",
  "properties": {
    "gn:admin1_code":"36",
    "gn:admin2_code":"135.0",
    "gn:asciiname":"Bagia Sagar Patti",
    "gn:country_code":"IN",
    "gn:dem":210,
    "gn:feature_class":"P",
    "gn:feature_code":"PPL",
    "gn:name":"Bagia S\u0101gar Patti",
    "gn:population":0,
    "gn:timezone":"Asia/Kolkata",
    "iso:country":"IN",
    "wof:name":"Bagia Sagar Patti",
    "wof:placetype":"locality"
},
  "geometry": {"coordinates":[78.60864000000002,29.0031],"type":"Point"}
}