{
  "type": "Feature",
  "properties": {
    "iso:country":"IN",
    "ks:ks_name":"Gulladamane",
    "ks:ks_pop":5,
    "ks:ks_type":"HABITATION",
    "name:eng_x_preferred":[
        "Gulladamane"
    ],
    "wof:name":"Gulladamane",
    "wof:placetype":"locality",
    "wof:population":5
},
  "geometry": {"coordinates":[75.01193600000001,13.726826],"type":"Point"}
}