{
  "type": "Feature",
  "properties": {
    "gn:admin1_code":"21.0",
    "gn:admin2_code":"398",
    "gn:asciiname":"Dummuriputtu",
    "gn:country_code":"IN",
    "gn:dem":874,
    "gn:feature_class":"P",
    "gn:feature_code":"PPL",
    "gn:name":"Dummuriputtu",
    "gn:population":0,
    "gn:timezone":"Asia/Kolkata",
    "iso:country":"IN",
    "name:und_x_variant":[
        "Dumuriput"
    ],
    "wof:name":"Dummuriputtu",
    "wof:placetype":"locality"
},
  "geometry": {"coordinates":[82.79761999999999,18.76914],"type":"Point"}
}