{
  "type": "Feature",
  "properties": {
    "iso:country":"IN",
    "ks:ks_name":"Harijanvas",
    "ks:ks_pop":106,
    "ks:ks_type":"HABITATION",
    "name:eng_x_preferred":[
        "Harijanvas"
    ],
    "wof:name":"Harijanvas",
    "wof:placetype":"locality",
    "wof:population":106
},
  "geometry": {"coordinates":[72.83580600000001,20.973167],"type":"Point"}
}