{
  "type": "Feature",
  "properties": {
    "iso:country":"IN",
    "ks:ks_alt_nam":"Wakan wasti",
    "ks:ks_name":"Wakan Wasti",
    "ks:ks_pop":164,
    "ks:ks_type":"HABITATION",
    "name:eng_x_preferred":[
        "Wakan Wasti"
    ],
    "wof:name":"Wakan Wasti",
    "wof:placetype":"locality",
    "wof:population":164
},
  "geometry": {"coordinates":[75.226426,18.677129],"type":"Point"}
}