{
  "type": "Feature",
  "properties": {
    "gn:admin1_code":"34",
    "gn:asciiname":"Lohara",
    "gn:country_code":"IN",
    "gn:dem":74,
    "gn:feature_class":"P",
    "gn:feature_code":"PPL",
    "gn:name":"Loh\u0101ra",
    "gn:population":0,
    "gn:timezone":"Asia/Kolkata",
    "iso:country":"IN",
    "ks:ks_alt_nam":"Loh\u0101ra",
    "ks:ks_name":"Lohara",
    "ks:ks_pop":322,
    "ks:ks_type":"VILLAGE",
    "ks:ks_uagg_main":0,
    "name:eng_x_preferred":[
        "Lohara"
    ],
    "name:eng_x_variant":[
        "Loh\u0101ra"
    ],
    "wof:name":"Lohara",
    "wof:placetype":"neighbourhood",
    "wof:population":322
},
  "geometry": {"coordinates":[83.478094,25.278323],"type":"Point"}
}