{
  "type": "Feature",
  "properties": {
    "iso:country":"IN",
    "ks:ks_name":"Koora",
    "ks:ks_pop":53,
    "ks:ks_type":"HABITATION",
    "name:eng_x_preferred":[
        "Koora"
    ],
    "wof:name":"Koora",
    "wof:placetype":"locality",
    "wof:population":53
},
  "geometry": {"coordinates":[75.34489499999999,12.744147],"type":"Point"}
}