{
  "type": "Feature",
  "properties": {
    "gn:admin1_code":"21",
    "gn:admin2_code":"395.0",
    "gn:asciiname":"Upar Ampadar",
    "gn:country_code":"IN",
    "gn:dem":757,
    "gn:feature_class":"P",
    "gn:feature_code":"PPL",
    "gn:name":"Upar Ampadar",
    "gn:population":0,
    "gn:timezone":"Asia/Kolkata",
    "iso:country":"IN",
    "ks:ks_name":"Uperampadar",
    "ks:ks_pop":198,
    "ks:ks_type":"VILLAGE",
    "name:eng_x_preferred":[
        "Uperampadar"
    ],
    "name:eng_x_variant":[
        "Upar Ampadar"
    ],
    "wof:name":"Uperampadar",
    "wof:placetype":"locality",
    "wof:population":198
},
  "geometry": {"coordinates":[83.135034,19.525735],"type":"Point"}
}