{
  "type": "Feature",
  "properties": {
    "iso:country":"IN",
    "ks:ks_name":"Tola Gunth",
    "ks:ks_pop":100,
    "ks:ks_type":"VILLAGE",
    "name:eng_x_preferred":[
        "Tola Gunth"
    ],
    "wof:name":"Tola Gunth",
    "wof:placetype":"locality",
    "wof:population":100
},
  "geometry": {"coordinates":[79.604455,29.827106],"type":"Point"}
}