{
  "type": "Feature",
  "properties": {
    "gn:admin1_code":"39",
    "gn:admin2_code":"61.0",
    "gn:asciiname":"Ratwari",
    "gn:country_code":"IN",
    "gn:dem":1414,
    "gn:feature_class":"P",
    "gn:feature_code":"PPL",
    "gn:name":"Ratw\u0101ri",
    "gn:population":0,
    "gn:timezone":"Asia/Kolkata",
    "iso:country":"IN",
    "ks:ks_alt_nam":"Ratw\u0101ri",
    "ks:ks_alt_nam_2":"Ratwari",
    "ks:ks_name":"Ratwar",
    "ks:ks_pop":269,
    "ks:ks_type":"VILLAGE",
    "name:eng_x_preferred":[
        "Ratwar"
    ],
    "name:eng_x_variant":[
        "Ratwari",
        "Ratw\u0101ri"
    ],
    "wof:name":"Ratwar",
    "wof:placetype":"locality",
    "wof:population":269
},
  "geometry": {"coordinates":[78.863713,29.79422],"type":"Point"}
}