{
  "type": "Feature",
  "properties": {
    "gn:admin1_code":"11",
    "gn:admin2_code":"31.0",
    "gn:asciiname":"Maleth",
    "gn:country_code":"IN",
    "gn:dem":601,
    "gn:feature_class":"P",
    "gn:feature_code":"PPL",
    "gn:name":"Maleth",
    "gn:population":0,
    "gn:timezone":"Asia/Kolkata",
    "iso:country":"IN",
    "name:bih_x_preferred":[
        "\u092e\u0932\u0947\u0920"
    ],
    "name:ceb_x_preferred":[
        "Maleth"
    ],
    "name:dty_x_preferred":[
        "\u092e\u0932\u0947\u0920 \u0917\u093e\u0935\u093f\u0938"
    ],
    "name:fra_x_preferred":[
        "Maleth"
    ],
    "name:mai_x_preferred":[
        "\u092e\u0932\u0947\u0920"
    ],
    "name:msa_x_preferred":[
        "Maleth"
    ],
    "name:nep_x_preferred":[
        "\u092e\u0932\u0947\u0920"
    ],
    "name:new_x_preferred":[
        "\u092e\u0932\u0947\u0920"
    ],
    "name:pol_x_preferred":[
        "Maleth"
    ],
    "wof:name":"Maleth",
    "wof:placetype":"locality"
},
  "geometry": {"coordinates":[76.7084,31.12629],"type":"Point"}
}