{
  "type": "Feature",
  "properties": {
    "iso:country":"IN",
    "ks:ks_name":"Amjuri",
    "ks:ks_pop":112,
    "ks:ks_type":"HABITATION",
    "name:eng_x_preferred":[
        "Amjuri"
    ],
    "wof:name":"Amjuri",
    "wof:placetype":"locality",
    "wof:population":112
},
  "geometry": {"coordinates":[92.36273300000001,26.133169],"type":"Point"}
}