{
  "type": "Feature",
  "properties": {
    "gn:admin1_code":"12",
    "gn:admin2_code":"15.0",
    "gn:asciiname":"Siungur",
    "gn:country_code":"IN",
    "gn:dem":1980,
    "gn:feature_class":"P",
    "gn:feature_code":"PPL",
    "gn:name":"Siungur",
    "gn:population":0,
    "gn:timezone":"Asia/Kolkata",
    "iso:country":"IN",
    "wof:name":"Siungur",
    "wof:placetype":"locality"
},
  "geometry": {"coordinates":[74.8934,33.61425999999999],"type":"Point"}
}