{
  "type": "Feature",
  "properties": {
    "gn:country":"IN",
    "gn:fcode":"PPL",
    "gn:population":0,
    "iso:country":"IN",
    "name:ara_x_preferred":[
        "\u0631\u0627\u0645\u0628\u0627\u063a"
    ],
    "name:ben_bn_x_preferred":[
        "\u09b0\u09be\u09ae\u09ac\u09be\u0997"
    ],
    "name:ben_in_x_preferred":[
        "\u09b0\u09be\u09ae\u09ac\u09be\u0997"
    ],
    "name:eng_x_preferred":[
        "Rambagh"
    ],
    "name:guj_x_preferred":[
        "\u0ab0\u0abe\u0aae\u0aac\u0abe\u0a97"
    ],
    "name:hin_x_preferred":[
        "\u0930\u093e\u092e\u092c\u093e\u0917"
    ],
    "name:kan_x_preferred":[
        "\u0cb0\u0cbe\u0cae\u0ccd"
    ],
    "name:mal_x_preferred":[
        "\u0d31\u0d3e\u0d02\u0d2c\u0d3e\u0d17\u0d4d"
    ],
    "name:mar_x_preferred":[
        "\u0930\u093e\u092e\u092c\u093e\u0917"
    ],
    "name:nld_x_preferred":[
        "Rambagh"
    ],
    "name:pan_x_preferred":[
        "\u0a30\u0a3e\u0a2e\u0a2c\u0a3e\u0a17"
    ],
    "name:tam_x_preferred":[
        "\u0bb0\u0bbe\u0bae\u0bcd\u0baa\u0bbe\u0b95\u0bcd"
    ],
    "name:tel_x_preferred":[
        "\u0c30\u0c3e\u0c02\u0c2c\u0c3e\u0c17\u0c4d"
    ],
    "name:urd_x_preferred":[
        "\u0631\u0627\u0645 \u0628\u0627\u063a"
    ],
    "qs:name":"Rambagh",
    "qs:name_adm0":"India",
    "qs:name_adm1":"Jammu and Kashmir",
    "qs:photos":12,
    "qs:photos_1k":2,
    "qs:photos_9k":1,
    "qs:photos_9r":1,
    "qs:photos_all":12,
    "qs:photos_sr":1,
    "qs:placetype":"Suburb",
    "qs:pop_sr":"0",
    "wd:wordcount":21,
    "wof:name":"Rambagh",
    "wof:placetype":"neighbourhood",
    "wof:population":0
},
  "geometry": {"coordinates":[74.80588,34.0513],"type":"Point"}
}