{
  "type": "Feature",
  "properties": {
    "iso:country":"IN",
    "ks:ks_name":"Sakalma",
    "ks:ks_pop":182,
    "ks:ks_type":"VILLAGE",
    "name:eng_x_preferred":[
        "Sakalma"
    ],
    "wof:name":"Sakalma",
    "wof:placetype":"locality",
    "wof:population":182
},
  "geometry": {"coordinates":[87.46625,24.556429],"type":"Point"}
}