{
  "type": "Feature",
  "properties": {
    "gn:admin1_code":"34.0",
    "gn:admin2_code":"231.0",
    "gn:asciiname":"Pharna",
    "gn:country_code":"IN",
    "gn:dem":58,
    "gn:feature_class":"P",
    "gn:feature_code":"PPL",
    "gn:name":"Ph\u0101rna",
    "gn:population":0,
    "gn:timezone":"Asia/Kolkata",
    "iso:country":"IN",
    "ks:ks_alt_nam":"Ph\u0101rna",
    "ks:ks_name":"Pharna",
    "ks:ks_pop":2313,
    "ks:ks_type":"VILLAGE",
    "ks:ks_uagg_main":0,
    "name:eng_x_preferred":[
        "Pharna"
    ],
    "name:eng_x_variant":[
        "Ph\u0101rna"
    ],
    "wof:name":"Pharna",
    "wof:placetype":"neighbourhood",
    "wof:population":2313
},
  "geometry": {"coordinates":[84.701587,25.636444],"type":"Point"}
}