{
  "type": "Feature",
  "properties": {
    "iso:country":"IN",
    "ks:ks_name":"Debattar Bapupara Pt-I",
    "ks:ks_pop":414,
    "ks:ks_type":"VILLAGE",
    "ks:ks_uagg_main":0,
    "name:eng_x_preferred":[
        "Debattar Bapupara Pt-I"
    ],
    "wof:name":"Debattar Bapupara Pt-I",
    "wof:placetype":"neighbourhood",
    "wof:population":414
},
  "geometry": {"coordinates":[90.537457,26.083051],"type":"Point"}
}