{
  "type": "Feature",
  "properties": {
    "gn:admin1_code":"35",
    "gn:admin2_code":"460.0",
    "gn:asciiname":"Jhiriyatola",
    "gn:country_code":"IN",
    "gn:dem":376,
    "gn:feature_class":"P",
    "gn:feature_code":"PPL",
    "gn:name":"Jhiriy\u0101tola",
    "gn:population":0,
    "gn:timezone":"Asia/Kolkata",
    "iso:country":"IN",
    "wof:name":"Jhiriyatola",
    "wof:placetype":"locality"
},
  "geometry": {"coordinates":[81.28646999999999,24.08788],"type":"Point"}
}