{
  "type": "Feature",
  "properties": {
    "iso:country":"IN",
    "ks:ks_name":"Bad Bigha",
    "ks:ks_pop":534,
    "ks:ks_type":"VILLAGE",
    "name:eng_x_preferred":[
        "Bad Bigha"
    ],
    "wof:name":"Bad Bigha",
    "wof:placetype":"locality",
    "wof:population":534
},
  "geometry": {"coordinates":[84.952834,23.965712],"type":"Point"}
}