{
  "type": "Feature",
  "properties": {
    "iso:country":"IN",
    "ks:ks_name":"Puninata",
    "ks:ks_pop":341,
    "ks:ks_type":"VILLAGE",
    "name:eng_x_preferred":[
        "Puninata"
    ],
    "wof:name":"Puninata",
    "wof:placetype":"locality",
    "wof:population":341
},
  "geometry": {"coordinates":[83.823049,20.272495],"type":"Point"}
}