{
  "type": "Feature",
  "properties": {
    "iso:country":"IN",
    "ks:ks_name":"Rabga",
    "ks:ks_pop":285,
    "ks:ks_type":"VILLAGE",
    "name:eng_x_preferred":[
        "Rabga"
    ],
    "wof:name":"Rabga",
    "wof:placetype":"locality",
    "wof:population":285
},
  "geometry": {"coordinates":[85.6742,22.624049],"type":"Point"}
}