{
  "type": "Feature",
  "properties": {
    "gn:admin1_code":"36.0",
    "gn:admin2_code":"174.0",
    "gn:asciiname":"Bholanath ka Purwa",
    "gn:country_code":"IN",
    "gn:dem":109,
    "gn:feature_class":"P",
    "gn:feature_code":"PPL",
    "gn:name":"Bhol\u0101nath ka Purwa",
    "gn:population":0,
    "gn:timezone":"Asia/Kolkata",
    "iso:country":"IN",
    "ks:ks_name":"Bhola Nath Ka Dera",
    "ks:ks_pop":121,
    "ks:ks_type":"HABITATION",
    "name:eng_x_preferred":[
        "Bhola Nath Ka Dera"
    ],
    "name:eng_x_variant":[
        "Bholanath ka Purwa"
    ],
    "wof:name":"Bhola Nath Ka Dera",
    "wof:placetype":"locality",
    "wof:population":121
},
  "geometry": {"coordinates":[81.34639,25.43783],"type":"Point"}
}