{
  "type": "Feature",
  "properties": {
    "iso:country":"IN",
    "ks:ks_alt_nam":"Anw\u0101r",
    "ks:ks_name":"Anwar",
    "ks:ks_pop":0,
    "ks:ks_type":"VILLAGE",
    "name:eng_x_preferred":[
        "Anwar"
    ],
    "name:eng_x_variant":[
        "Anw\u0101r"
    ],
    "wof:name":"Anwar",
    "wof:placetype":"locality",
    "wof:population":0
},
  "geometry": {"coordinates":[84.305164,26.032879],"type":"Point"}
}