{
  "type": "Feature",
  "properties": {
    "iso:country":"IN",
    "ks:ks_name":"Dhovadoloni",
    "ks:ks_pop":185,
    "ks:ks_type":"HABITATION",
    "name:eng_x_preferred":[
        "Dhovadoloni"
    ],
    "wof:name":"Dhovadoloni",
    "wof:placetype":"locality",
    "wof:population":185
},
  "geometry": {"coordinates":[92.466342,26.167541],"type":"Point"}
}