{
  "type": "Feature",
  "properties": {
    "iso:country":"IN",
    "ks:ks_name":"Kottalu",
    "ks:ks_pop":133,
    "ks:ks_type":"HABITATION",
    "name:eng_x_preferred":[
        "Kottalu"
    ],
    "wof:name":"Kottalu",
    "wof:placetype":"locality",
    "wof:population":133
},
  "geometry": {"coordinates":[79.678558,14.894543],"type":"Point"}
}