{
  "type": "Feature",
  "properties": {
    "gn:admin1_code":"38.0",
    "gn:admin2_code":"353.0",
    "gn:asciiname":"Kundamatia",
    "gn:country_code":"IN",
    "gn:dem":176,
    "gn:feature_class":"P",
    "gn:feature_code":"PPL",
    "gn:name":"Kund\u0101m\u0101tia",
    "gn:population":0,
    "gn:timezone":"Asia/Kolkata",
    "iso:country":"IN",
    "ks:ks_alt_nam":"Kund\u0101m\u0101tia",
    "ks:ks_name":"Kundamatia",
    "ks:ks_pop":263,
    "ks:ks_type":"VILLAGE",
    "name:eng_x_preferred":[
        "Kundamatia"
    ],
    "name:eng_x_variant":[
        "Kund\u0101m\u0101tia"
    ],
    "wof:name":"Kundamatia",
    "wof:placetype":"locality",
    "wof:population":263
},
  "geometry": {"coordinates":[87.51259400000001,24.604532],"type":"Point"}
}