{
  "type": "Feature",
  "properties": {
    "gn:admin1_code":"21.0",
    "gn:admin2_code":"398.0",
    "gn:asciiname":"Tentulipoda",
    "gn:country_code":"IN",
    "gn:dem":805,
    "gn:feature_class":"P",
    "gn:feature_code":"PPL",
    "gn:name":"Tentulipoda",
    "gn:population":0,
    "gn:timezone":"Asia/Kolkata",
    "iso:country":"IN",
    "ks:ks_name":"Tentulipada",
    "ks:ks_pop":43,
    "ks:ks_type":"VILLAGE",
    "name:eng_x_preferred":[
        "Tentulipada"
    ],
    "name:eng_x_variant":[
        "Tentulipoda"
    ],
    "wof:name":"Tentulipada",
    "wof:placetype":"locality",
    "wof:population":43
},
  "geometry": {"coordinates":[82.49296200000001,18.667572],"type":"Point"}
}