{
  "type": "Feature",
  "properties": {
    "gn:admin1_code":"21",
    "gn:admin2_code":"371.0",
    "gn:asciiname":"Chingriurha",
    "gn:country_code":"IN",
    "gn:dem":221,
    "gn:feature_class":"P",
    "gn:feature_code":"PPL",
    "gn:name":"Chingriurha",
    "gn:population":0,
    "gn:timezone":"Asia/Kolkata",
    "iso:country":"IN",
    "wof:name":"Chingriurha",
    "wof:placetype":"locality"
},
  "geometry": {"coordinates":[83.88399,21.80594],"type":"Point"}
}