{
  "type": "Feature",
  "properties": {
    "iso:country":"IN",
    "ks:ks_alt_nam":"Madhya Dakshin para",
    "ks:ks_name":"Madhya Dakshin Para",
    "ks:ks_pop":231,
    "ks:ks_type":"HABITATION",
    "name:eng_x_preferred":[
        "Madhya Dakshin Para"
    ],
    "wof:name":"Madhya Dakshin Para",
    "wof:placetype":"locality",
    "wof:population":231
},
  "geometry": {"coordinates":[91.51322500000001,23.52078],"type":"Point"}
}