{
  "type": "Feature",
  "properties": {
    "iso:country":"IN",
    "ks:ks_name":"Gaur Purwa",
    "ks:ks_pop":285,
    "ks:ks_type":"HABITATION",
    "name:eng_x_preferred":[
        "Gaur Purwa"
    ],
    "wof:name":"Gaur Purwa",
    "wof:placetype":"locality",
    "wof:population":285
},
  "geometry": {"coordinates":[81.019834,25.248645],"type":"Point"}
}