{
  "type": "Feature",
  "properties": {
    "gn:admin1_code":"2",
    "gn:admin2_code":"547.0",
    "gn:asciiname":"Sangamudi",
    "gn:country_code":"IN",
    "gn:dem":10,
    "gn:feature_class":"P",
    "gn:feature_code":"PPL",
    "gn:name":"Sangam\u016bdi",
    "gn:population":0,
    "gn:timezone":"Asia/Kolkata",
    "iso:country":"IN",
    "wof:name":"Sangamudi",
    "wof:placetype":"locality"
},
  "geometry": {"coordinates":[81.3616,16.38249],"type":"Point"}
}