{
  "type": "Feature",
  "properties": {
    "gn:admin1_code":"36.0",
    "gn:admin2_code":"175.0",
    "gn:asciiname":"Mustafabad",
    "gn:country_code":"IN",
    "gn:dem":99,
    "gn:feature_class":"P",
    "gn:feature_code":"PPL",
    "gn:name":"Mustaf\u0101b\u0101d",
    "gn:population":0,
    "gn:timezone":"Asia/Kolkata",
    "iso:country":"IN",
    "ks:ks_alt_nam":"Mustaf\u0101b\u0101d",
    "ks:ks_name":"Mustafabad",
    "ks:ks_pop":44,
    "ks:ks_type":"VILLAGE",
    "name:eng_x_preferred":[
        "Mustafabad"
    ],
    "name:eng_x_variant":[
        "Mustaf\u0101b\u0101d"
    ],
    "wof:name":"Mustafabad",
    "wof:placetype":"locality",
    "wof:population":44
},
  "geometry": {"coordinates":[81.974825,25.579563],"type":"Point"}
}