{
  "type": "Feature",
  "properties": {
    "iso:country":"IN",
    "ks:ks_name":"Rasai Mog Para",
    "ks:ks_pop":259,
    "ks:ks_type":"HABITATION",
    "name:eng_x_preferred":[
        "Rasai Mog Para"
    ],
    "wof:name":"Rasai Mog Para",
    "wof:placetype":"locality",
    "wof:population":259
},
  "geometry": {"coordinates":[91.753433,23.267936],"type":"Point"}
}