{
  "type": "Feature",
  "properties": {
    "gn:admin1_code":"39",
    "gn:admin2_code":"60.0",
    "gn:asciiname":"Kharshar Khera",
    "gn:country_code":"IN",
    "gn:dem":2129,
    "gn:feature_class":"P",
    "gn:feature_code":"PPL",
    "gn:name":"Kharshar Khera",
    "gn:population":0,
    "gn:timezone":"Asia/Kolkata",
    "iso:country":"IN",
    "wof:name":"Kharshar Khera",
    "wof:placetype":"locality"
},
  "geometry": {"coordinates":[77.91725,30.88073],"type":"Point"}
}