{
  "type": "Feature",
  "properties": {
    "iso:country":"IN",
    "ks:ks_name":"Pallakare",
    "ks:ks_pop":67,
    "ks:ks_type":"HABITATION",
    "name:eng_x_preferred":[
        "Pallakare"
    ],
    "wof:name":"Pallakare",
    "wof:placetype":"locality",
    "wof:population":67
},
  "geometry": {"coordinates":[75.843333,12.2925],"type":"Point"}
}