{
  "type": "Feature",
  "properties": {
    "iso:country":"IN",
    "ks:ks_name":"Dubaulia",
    "ks:ks_pop":775,
    "ks:ks_type":"VILLAGE",
    "name:eng_x_preferred":[
        "Dubaulia"
    ],
    "wof:name":"Dubaulia",
    "wof:placetype":"locality",
    "wof:population":775
},
  "geometry": {"coordinates":[83.014674,27.356198],"type":"Point"}
}