{
  "type": "Feature",
  "properties": {
    "iso:country":"IN",
    "ks:ks_name":"Pampukala",
    "ks:ks_pop":45,
    "ks:ks_type":"HABITATION",
    "name:eng_x_preferred":[
        "Pampukala"
    ],
    "wof:name":"Pampukala",
    "wof:placetype":"locality",
    "wof:population":45
},
  "geometry": {"coordinates":[77.06417,8.322168],"type":"Point"}
}