{
  "type": "Feature",
  "properties": {
    "iso:country":"IN",
    "ks:ks_name":"Nipaniya-b",
    "ks:ks_pop":880,
    "ks:ks_type":"VILLAGE",
    "ks:ks_uagg_main":0,
    "name:eng_x_preferred":[
        "Nipaniya-b"
    ],
    "wof:name":"Nipaniya-b",
    "wof:placetype":"neighbourhood",
    "wof:population":880
},
  "geometry": {"coordinates":[82.04893300000001,21.962572],"type":"Point"}
}