{
  "type": "Feature",
  "properties": {
    "gn:admin1_code":"12.0",
    "gn:admin2_code":"7.0",
    "gn:asciiname":"Thar",
    "gn:country_code":"IN",
    "gn:dem":644,
    "gn:feature_class":"P",
    "gn:feature_code":"PPL",
    "gn:name":"Th\u0101r",
    "gn:population":0,
    "gn:timezone":"Asia/Kolkata",
    "iso:country":"IN",
    "name:ceb_x_preferred":[
        "Thar"
    ],
    "name:deu_x_preferred":[
        "Thar"
    ],
    "name:fra_x_preferred":[
        "Thar"
    ],
    "name:nld_x_preferred":[
        "Thar"
    ],
    "name:swe_x_preferred":[
        "Thar"
    ],
    "wof:name":"Thar",
    "wof:placetype":"locality"
},
  "geometry": {"coordinates":[75.32164,32.56547],"type":"Point"}
}