{
  "type": "Feature",
  "properties": {
    "gn:admin1_code":"36",
    "gn:admin2_code":"166.0",
    "gn:asciiname":"Rampura",
    "gn:country_code":"IN",
    "gn:dem":206,
    "gn:feature_class":"P",
    "gn:feature_code":"PPL",
    "gn:name":"Rampura",
    "gn:population":0,
    "gn:timezone":"Asia/Kolkata",
    "iso:country":"IN",
    "name:cat_x_preferred":[
        "Rampura"
    ],
    "name:pol_x_preferred":[
        "Rampura"
    ],
    "wof:name":"Rampura",
    "wof:placetype":"locality"
},
  "geometry": {"coordinates":[78.95045999999998,25.59362],"type":"Point"}
}