{
  "type": "Feature",
  "properties": {
    "iso:country":"IN",
    "ks:ks_name":"Kochari",
    "ks:ks_pop":707,
    "ks:ks_type":"VILLAGE",
    "name:eng_x_preferred":[
        "Kochari"
    ],
    "wof:name":"Kochari",
    "wof:placetype":"locality",
    "wof:population":707
},
  "geometry": {"coordinates":[81.34317299999999,24.816833],"type":"Point"}
}