{
  "type": "Feature",
  "properties": {
    "iso:country":"IN",
    "ks:ks_alt_nam":"SUTHARO KA TALA",
    "ks:ks_name":"Sutharo Ka Tala",
    "ks:ks_pop":760,
    "ks:ks_type":"HABITATION",
    "name:eng_x_preferred":[
        "Sutharo Ka Tala"
    ],
    "wof:name":"Sutharo Ka Tala",
    "wof:placetype":"locality",
    "wof:population":760
},
  "geometry": {"coordinates":[71.5057,25.714255],"type":"Point"}
}