{
  "type": "Feature",
  "properties": {
    "iso:country":"IN",
    "ks:ks_name":"Simada Falia",
    "ks:ks_pop":666,
    "ks:ks_type":"HABITATION",
    "name:eng_x_preferred":[
        "Simada Falia"
    ],
    "wof:name":"Simada Falia",
    "wof:placetype":"locality",
    "wof:population":666
},
  "geometry": {"coordinates":[73.919472,22.619472],"type":"Point"}
}