{
  "type": "Feature",
  "properties": {
    "iso:country":"IN",
    "ks:ks_alt_nam":"anapara",
    "ks:ks_name":"Anapara",
    "ks:ks_pop":450,
    "ks:ks_type":"HABITATION",
    "name:eng_x_preferred":[
        "Anapara"
    ],
    "wof:name":"Anapara",
    "wof:placetype":"locality",
    "wof:population":450
},
  "geometry": {"coordinates":[75.743084,11.379124],"type":"Point"}
}