{
  "type": "Feature",
  "properties": {
    "iso:country":"IN",
    "ks:ks_name":"Iswaraberi",
    "ks:ks_pop":106,
    "ks:ks_type":"VILLAGE",
    "ks:ks_uagg_main":0,
    "name:eng_x_preferred":[
        "Iswaraberi"
    ],
    "wof:name":"Iswaraberi",
    "wof:placetype":"neighbourhood",
    "wof:population":106
},
  "geometry": {"coordinates":[77.84518799999999,9.745813],"type":"Point"}
}