{
  "type": "Feature",
  "properties": {
    "iso:country":"IN",
    "ks:ks_name":"Kummongot",
    "ks:ks_pop":955,
    "ks:ks_type":"HABITATION",
    "ks:ks_uagg_main":0,
    "name:eng_x_preferred":[
        "Kummongot"
    ],
    "wof:name":"Kummongot",
    "wof:placetype":"neighbourhood",
    "wof:population":955
},
  "geometry": {"coordinates":[75.847224,11.332346],"type":"Point"}
}