{
  "type": "Feature",
  "properties": {
    "gn:admin1_code":"19.0",
    "gn:admin2_code":"573.0",
    "gn:asciiname":"Malamkuppa",
    "gn:country_code":"IN",
    "gn:dem":670,
    "gn:feature_class":"P",
    "gn:feature_code":"PPL",
    "gn:name":"M\u0101l\u0101mkuppa",
    "gn:population":0,
    "gn:timezone":"Asia/Kolkata",
    "iso:country":"IN",
    "wof:name":"Malamkuppa",
    "wof:placetype":"locality"
},
  "geometry": {"coordinates":[77.05153,12.73828],"type":"Point"}
}