{
  "type": "Feature",
  "properties": {
    "iso:country":"IN",
    "ks:ks_alt_nam":"DADHARI FV",
    "ks:ks_name":"Dadhari Fv",
    "ks:ks_pop":437,
    "ks:ks_type":"HABITATION",
    "name:eng_x_preferred":[
        "Dadhari Fv"
    ],
    "wof:name":"Dadhari Fv",
    "wof:placetype":"locality",
    "wof:population":437
},
  "geometry": {"coordinates":[77.556315,21.974612],"type":"Point"}
}