{
  "type": "Feature",
  "properties": {
    "iso:country":"IN",
    "ks:ks_name":"Shiyabhel",
    "ks:ks_pop":94,
    "ks:ks_type":"VILLAGE",
    "name:eng_x_preferred":[
        "Shiyabhel"
    ],
    "wof:name":"Shiyabhel",
    "wof:placetype":"locality",
    "wof:population":94
},
  "geometry": {"coordinates":[79.050436,29.704342],"type":"Point"}
}