{
  "type": "Feature",
  "properties": {
    "iso:country":"IN",
    "ks:ks_name":"Pratap Singh Ka Dera",
    "ks:ks_pop":200,
    "ks:ks_type":"HABITATION",
    "name:eng_x_preferred":[
        "Pratap Singh Ka Dera"
    ],
    "wof:name":"Pratap Singh Ka Dera",
    "wof:placetype":"locality",
    "wof:population":200
},
  "geometry": {"coordinates":[80.901139,25.733614],"type":"Point"}
}