{
  "type": "Feature",
  "properties": {
    "iso:country":"IN",
    "ks:ks_name":"Atchiyyapeta",
    "ks:ks_pop":60,
    "ks:ks_type":"HABITATION",
    "name:eng_x_preferred":[
        "Atchiyyapeta"
    ],
    "wof:name":"Atchiyyapeta",
    "wof:placetype":"locality",
    "wof:population":60
},
  "geometry": {"coordinates":[82.45890199999999,17.69291],"type":"Point"}
}