{
  "type": "Feature",
  "properties": {
    "iso:country":"IN",
    "ks:ks_name":"Kachupukur",
    "ks:ks_pop":5348,
    "ks:ks_type":"VILLAGE",
    "ks:ks_uagg_main":0,
    "name:eng_x_preferred":[
        "Kachupukur"
    ],
    "wof:name":"Kachupukur",
    "wof:placetype":"neighbourhood",
    "wof:population":5348
},
  "geometry": {"coordinates":[88.24964900000001,24.983988],"type":"Point"}
}