{
  "type": "Feature",
  "properties": {
    "iso:country":"IN",
    "ks:ks_name":"Chitauri",
    "ks:ks_pop":526,
    "ks:ks_type":"VILLAGE",
    "name:eng_x_preferred":[
        "Chitauri"
    ],
    "wof:name":"Chitauri",
    "wof:placetype":"locality",
    "wof:population":526
},
  "geometry": {"coordinates":[79.223961,26.270659],"type":"Point"}
}