{
  "type": "Feature",
  "properties": {
    "iso:country":"IN",
    "ks:ks_alt_nam":"Jhala purwa",
    "ks:ks_name":"Jhala Purwa",
    "ks:ks_pop":116,
    "ks:ks_type":"HABITATION",
    "name:eng_x_preferred":[
        "Jhala Purwa"
    ],
    "wof:name":"Jhala Purwa",
    "wof:placetype":"locality",
    "wof:population":116
},
  "geometry": {"coordinates":[80.83485400000001,27.592996],"type":"Point"}
}