{
  "type": "Feature",
  "properties": {
    "gn:admin1_code":"38",
    "gn:admin2_code":"368.0",
    "gn:asciiname":"Tholkabad",
    "gn:country_code":"IN",
    "gn:dem":539,
    "gn:feature_class":"P",
    "gn:feature_code":"PPL",
    "gn:name":"Tholk\u0101b\u0101d",
    "gn:population":0,
    "gn:timezone":"Asia/Kolkata",
    "iso:country":"IN",
    "wof:name":"Tholkabad",
    "wof:placetype":"locality"
},
  "geometry": {"coordinates":[85.18714,22.13249],"type":"Point"}
}