{
  "type": "Feature",
  "properties": {
    "iso:country":"IN",
    "ks:ks_name":"Moukhuti Gaon",
    "ks:ks_pop":427,
    "ks:ks_type":"HABITATION",
    "ks:ks_uagg_main":0,
    "name:eng_x_preferred":[
        "Moukhuti Gaon"
    ],
    "wof:name":"Moukhuti Gaon",
    "wof:placetype":"neighbourhood",
    "wof:population":427
},
  "geometry": {"coordinates":[93.820516,26.182287],"type":"Point"}
}