{
  "type": "Feature",
  "properties": {
    "iso:country":"IN",
    "ks:ks_name":"Kherullahpur",
    "ks:ks_pop":589,
    "ks:ks_type":"VILLAGE",
    "name:eng_x_preferred":[
        "Kherullahpur"
    ],
    "wof:name":"Kherullahpur",
    "wof:placetype":"locality",
    "wof:population":589
},
  "geometry": {"coordinates":[79.122061,28.818157],"type":"Point"}
}