{
  "type": "Feature",
  "properties": {
    "gn:admin1_code":"11.0",
    "gn:admin2_code":"27.0",
    "gn:asciiname":"Chadda",
    "gn:country_code":"IN",
    "gn:dem":2552,
    "gn:feature_class":"P",
    "gn:feature_code":"PPL",
    "gn:name":"Chadda",
    "gn:population":0,
    "gn:timezone":"Asia/Kolkata",
    "iso:country":"IN",
    "wof:name":"Chadda",
    "wof:placetype":"locality"
},
  "geometry": {"coordinates":[77.19951,31.47663],"type":"Point"}
}