{
  "type": "Feature",
  "properties": {
    "iso:country":"IN",
    "ks:ks_name":"Dholeshwar",
    "ks:ks_pop":100,
    "ks:ks_type":"HABITATION",
    "name:eng_x_preferred":[
        "Dholeshwar"
    ],
    "wof:name":"Dholeshwar",
    "wof:placetype":"locality",
    "wof:population":100
},
  "geometry": {"coordinates":[75.027008,19.140596],"type":"Point"}
}