{
  "type": "Feature",
  "properties": {
    "gn:admin1_code":"25.0",
    "gn:admin2_code":"602.0",
    "gn:asciiname":"Chengalpatikhandigai",
    "gn:country_code":"IN",
    "gn:dem":163,
    "gn:feature_class":"P",
    "gn:feature_code":"PPL",
    "gn:name":"Chengalpatikhandigai",
    "gn:population":0,
    "gn:timezone":"Asia/Kolkata",
    "iso:country":"IN",
    "ks:ks_name":"Sengalpathi Kandigai",
    "ks:ks_pop":121,
    "ks:ks_type":"HABITATION",
    "name:eng_x_preferred":[
        "Sengalpathi Kandigai"
    ],
    "name:eng_x_variant":[
        "Chengalpatikhandigai"
    ],
    "wof:name":"Sengalpathi Kandigai",
    "wof:placetype":"locality",
    "wof:population":121
},
  "geometry": {"coordinates":[79.457128,13.17734],"type":"Point"}
}