{
  "type": "Feature",
  "properties": {
    "iso:country":"IN",
    "ks:ks_name":"Nanara",
    "ks:ks_pop":2155,
    "ks:ks_type":"VILLAGE",
    "ks:ks_uagg_main":0,
    "name:eng_x_preferred":[
        "Nanara"
    ],
    "wof:name":"Nanara",
    "wof:placetype":"neighbourhood",
    "wof:population":2155
},
  "geometry": {"coordinates":[91.727547,26.363702],"type":"Point"}
}