{
  "type": "Feature",
  "properties": {
    "iso:country":"IN",
    "ks:ks_name":"Manwaripara",
    "ks:ks_pop":261,
    "ks:ks_type":"HABITATION",
    "name:eng_x_preferred":[
        "Manwaripara"
    ],
    "wof:name":"Manwaripara",
    "wof:placetype":"locality",
    "wof:population":261
},
  "geometry": {"coordinates":[82.71127,23.782259],"type":"Point"}
}