{
  "type": "Feature",
  "properties": {
    "iso:country":"IN",
    "ks:ks_name":"Bheradih",
    "ks:ks_pop":487,
    "ks:ks_type":"HABITATION",
    "ks:ks_uagg_main":0,
    "name:eng_x_preferred":[
        "Bheradih"
    ],
    "wof:name":"Bheradih",
    "wof:placetype":"neighbourhood",
    "wof:population":487
},
  "geometry": {"coordinates":[86.86836700000001,24.890313],"type":"Point"}
}