{
  "type": "Feature",
  "properties": {
    "iso:country":"IN",
    "ks:ks_name":"Mureedsar",
    "ks:ks_pop":105,
    "ks:ks_type":"VILLAGE",
    "name:eng_x_preferred":[
        "Mureedsar"
    ],
    "wof:name":"Mureedsar",
    "wof:placetype":"locality",
    "wof:population":105
},
  "geometry": {"coordinates":[73.109105,27.639831],"type":"Point"}
}