{
  "type": "Feature",
  "properties": {
    "iso:country":"IN",
    "ks:ks_name":"Tugaon",
    "ks:ks_pop":248,
    "ks:ks_type":"VILLAGE",
    "name:eng_x_preferred":[
        "Tugaon"
    ],
    "wof:name":"Tugaon",
    "wof:placetype":"locality",
    "wof:population":248
},
  "geometry": {"coordinates":[77.309735,17.88746],"type":"Point"}
}