{
  "type": "Feature",
  "properties": {
    "iso:country":"IN",
    "ks:ks_name":"Gorakhpur Dihwa",
    "ks:ks_pop":218,
    "ks:ks_type":"HABITATION",
    "name:eng_x_preferred":[
        "Gorakhpur Dihwa"
    ],
    "wof:name":"Gorakhpur Dihwa",
    "wof:placetype":"locality",
    "wof:population":218
},
  "geometry": {"coordinates":[83.137355,27.343249],"type":"Point"}
}