{
  "type": "Feature",
  "properties": {
    "gn:admin1_code":"28",
    "gn:admin2_code":"339.0",
    "gn:asciiname":"Phulkusma",
    "gn:country_code":"IN",
    "gn:dem":119,
    "gn:feature_class":"P",
    "gn:feature_code":"PPL",
    "gn:name":"Phulkusma",
    "gn:population":0,
    "gn:timezone":"Asia/Kolkata",
    "iso:country":"IN",
    "wof:name":"Phulkusma",
    "wof:placetype":"locality"
},
  "geometry": {"coordinates":[86.86558000000002,22.70987],"type":"Point"}
}