{
  "type": "Feature",
  "properties": {
    "iso:country":"IN",
    "ks:ks_alt_nam":"Yetep\u0101l",
    "ks:ks_name":"Yetepal",
    "ks:ks_type":"VILLAGE",
    "name:eng_x_preferred":[
        "Yetepal"
    ],
    "name:eng_x_variant":[
        "Yetep\u0101l"
    ],
    "wof:name":"Yetepal",
    "wof:placetype":"locality"
},
  "geometry": {"coordinates":[81.15266,18.786031],"type":"Point"}
}