{
  "type": "Feature",
  "properties": {
    "iso:country":"IN",
    "ks:ks_name":"Navamuvada",
    "ks:ks_pop":173,
    "ks:ks_type":"HABITATION",
    "name:eng_x_preferred":[
        "Navamuvada"
    ],
    "wof:name":"Navamuvada",
    "wof:placetype":"locality",
    "wof:population":173
},
  "geometry": {"coordinates":[72.984278,22.931611],"type":"Point"}
}