{
  "type": "Feature",
  "properties": {
    "iso:country":"IN",
    "ks:ks_name":"Gonai Chhapra",
    "ks:ks_pop":2100,
    "ks:ks_type":"HABITATION",
    "ks:ks_uagg_main":0,
    "name:eng_x_preferred":[
        "Gonai Chhapra"
    ],
    "wof:name":"Gonai Chhapra",
    "wof:placetype":"neighbourhood",
    "wof:population":2100
},
  "geometry": {"coordinates":[83.90337700000001,26.794034],"type":"Point"}
}