{
  "type": "Feature",
  "properties": {
    "iso:country":"IN",
    "ks:ks_name":"Thimmapur",
    "ks:ks_pop":836,
    "ks:ks_type":"HABITATION",
    "name:eng_x_preferred":[
        "Thimmapur"
    ],
    "wof:name":"Thimmapur",
    "wof:placetype":"locality",
    "wof:population":836
},
  "geometry": {"coordinates":[76.71502700000001,15.578817],"type":"Point"}
}