{
  "type": "Feature",
  "properties": {
    "gn:admin1_code":"36.0",
    "gn:admin2_code":"158.0",
    "gn:asciiname":"Salarpur",
    "gn:country_code":"IN",
    "gn:dem":114,
    "gn:feature_class":"P",
    "gn:feature_code":"PPL",
    "gn:name":"S\u0101l\u0101rpur",
    "gn:population":0,
    "gn:timezone":"Asia/Kolkata",
    "iso:country":"IN",
    "name:urd_x_preferred":[
        "\u0633\u0627\u0644\u0627\u0631 \u067e\u0648\u0631"
    ],
    "wof:name":"Salarpur",
    "wof:placetype":"locality"
},
  "geometry": {"coordinates":[81.31841,25.98501],"type":"Point"}
}