{
  "type": "Feature",
  "properties": {
    "iso:country":"IN",
    "ks:ks_name":"Bhadar",
    "ks:ks_pop":436,
    "ks:ks_type":"HABITATION",
    "name:eng_x_preferred":[
        "Bhadar"
    ],
    "wof:name":"Bhadar",
    "wof:placetype":"locality",
    "wof:population":436
},
  "geometry": {"coordinates":[83.74175099999999,23.545656],"type":"Point"}
}