{
  "type": "Feature",
  "properties": {
    "gn:admin1_code":"23.0",
    "gn:admin2_code":"049",
    "gn:asciiname":"Baba Bakala",
    "gn:country_code":"IN",
    "gn:dem":240,
    "gn:feature_class":"P",
    "gn:feature_code":"PPL",
    "gn:name":"B\u0101ba Bak\u0101la",
    "gn:population":0,
    "gn:timezone":"Asia/Kolkata",
    "iso:country":"IN",
    "name:fra_x_preferred":[
        "Baba Bakala"
    ],
    "name:pan_x_preferred":[
        "\u0a2c\u0a3e\u0a2c\u0a3e \u0a2c\u0a15\u0a3e\u0a32\u0a3e"
    ],
    "name:rus_x_preferred":[
        "\u0411\u0430\u0431\u0430 \u0411\u0430\u043a\u0430\u043b\u0430"
    ],
    "name:und_x_variant":[
        "Babahakala",
        "B\u0101ba Bak\u0101la"
    ],
    "name:urd_x_preferred":[
        "\u0628\u0627\u0628\u0627 \u0628\u06a9\u0627\u0644\u0627"
    ],
    "wof:name":"Baba Bakala",
    "wof:placetype":"locality"
},
  "geometry": {"coordinates":[75.26389,31.55545],"type":"Point"}
}