{
  "type": "Feature",
  "properties": {
    "gn:admin1_code":"23.0",
    "gn:admin2_code":"049",
    "gn:asciiname":"Baba Bakala",
    "gn:country_code":"IN",
    "gn:dem":240,
    "gn:feature_class":"P",
    "gn:feature_code":"PPL",
    "gn:name":"B\u0101ba Bak\u0101la",
    "gn:population":0,
    "gn:timezone":"Asia/Kolkata",
    "iso:country":"IN",
    "name:und_x_variant":[
        "Babahakala",
        "B\u0101ba Bak\u0101la"
    ],
    "wof:name":"Baba Bakala",
    "wof:placetype":"locality"
},
  "geometry": {"coordinates":[75.26389,31.55545],"type":"Point"}
}