{
  "type": "Feature",
  "properties": {
    "iso:country":"IN",
    "ks:ks_name":"Nawa Dih",
    "ks:ks_pop":689,
    "ks:ks_type":"VILLAGE",
    "name:eng_x_preferred":[
        "Nawa Dih"
    ],
    "wof:name":"Nawa Dih",
    "wof:placetype":"locality",
    "wof:population":689
},
  "geometry": {"coordinates":[85.938346,22.690253],"type":"Point"}
}