{
  "type": "Feature",
  "properties": {
    "iso:country":"IN",
    "ks:ks_name":"Ajepur",
    "ks:ks_pop":469,
    "ks:ks_type":"VILLAGE",
    "name:eng_x_preferred":[
        "Ajepur"
    ],
    "wof:name":"Ajepur",
    "wof:placetype":"locality",
    "wof:population":469
},
  "geometry": {"coordinates":[73.24505600000001,23.976556],"type":"Point"}
}