{
  "type": "Feature",
  "properties": {
    "iso:country":"IN",
    "ks:ks_name":"Cherichuan",
    "ks:ks_pop":136,
    "ks:ks_type":"HABITATION",
    "name:eng_x_preferred":[
        "Cherichuan"
    ],
    "wof:name":"Cherichuan",
    "wof:placetype":"locality",
    "wof:population":136
},
  "geometry": {"coordinates":[82.538849,20.536749],"type":"Point"}
}