{
  "type": "Feature",
  "properties": {
    "iso:country":"IN",
    "ks:ks_alt_nam":"Chandan nali",
    "ks:ks_name":"Chandan Nali",
    "ks:ks_pop":14,
    "ks:ks_type":"HABITATION",
    "name:eng_x_preferred":[
        "Chandan Nali"
    ],
    "wof:name":"Chandan Nali",
    "wof:placetype":"locality",
    "wof:population":14
},
  "geometry": {"coordinates":[74.07021,20.579792],"type":"Point"}
}