{
  "type": "Feature",
  "properties": {
    "iso:country":"IN",
    "ks:ks_name":"Chanda Bigha",
    "ks:ks_pop":360,
    "ks:ks_type":"HABITATION",
    "name:eng_x_preferred":[
        "Chanda Bigha"
    ],
    "wof:name":"Chanda Bigha",
    "wof:placetype":"locality",
    "wof:population":360
},
  "geometry": {"coordinates":[85.38614699999999,25.364119],"type":"Point"}
}