{
  "type": "Feature",
  "properties": {
    "gn:admin1_code":"19.0",
    "gn:admin2_code":"572.0",
    "gn:asciiname":"Chokkanhalli",
    "gn:country_code":"IN",
    "gn:dem":897,
    "gn:feature_class":"P",
    "gn:feature_code":"PPL",
    "gn:name":"Chokkanhalli",
    "gn:population":0,
    "gn:timezone":"Asia/Kolkata",
    "iso:country":"IN",
    "wof:name":"Chokkanhalli",
    "wof:placetype":"locality"
},
  "geometry": {"coordinates":[77.68735,13.11318],"type":"Point"}
}