{
  "type": "Feature",
  "properties": {
    "iso:country":"IN",
    "ks:ks_alt_nam":"Panchani para",
    "ks:ks_name":"Panchani Para",
    "ks:ks_pop":1149,
    "ks:ks_type":"HABITATION",
    "name:eng_x_preferred":[
        "Panchani Para"
    ],
    "wof:name":"Panchani Para",
    "wof:placetype":"locality",
    "wof:population":1149
},
  "geometry": {"coordinates":[89.70133,26.332642],"type":"Point"}
}