{
  "type": "Feature",
  "properties": {
    "iso:country":"IN",
    "ks:ks_alt_nam":"gaokarwadi",
    "ks:ks_name":"Gaokarwadi",
    "ks:ks_pop":115,
    "ks:ks_type":"HABITATION",
    "name:eng_x_preferred":[
        "Gaokarwadi"
    ],
    "wof:name":"Gaokarwadi",
    "wof:placetype":"locality",
    "wof:population":115
},
  "geometry": {"coordinates":[73.378561,16.547617],"type":"Point"}
}