{
  "type": "Feature",
  "properties": {
    "iso:country":"IN",
    "ks:ks_name":"Ranjeetpura",
    "ks:ks_pop":4242,
    "ks:ks_type":"VILLAGE",
    "name:eng_x_preferred":[
        "Ranjeetpura"
    ],
    "wof:name":"Ranjeetpura",
    "wof:placetype":"locality",
    "wof:population":4242
},
  "geometry": {"coordinates":[72.03807,28.070778],"type":"Point"}
}