{
  "type": "Feature",
  "properties": {
    "gn:admin1_code":"23.0",
    "gn:admin2_code":"42.0",
    "gn:asciiname":"Bisanpura",
    "gn:country_code":"IN",
    "gn:dem":225,
    "gn:feature_class":"P",
    "gn:feature_code":"PPL",
    "gn:name":"Bisanp\u016bra",
    "gn:population":0,
    "gn:timezone":"Asia/Kolkata",
    "iso:country":"IN",
    "ks:ks_alt_nam":"Bisanp\u016bra",
    "ks:ks_alt_nam_2":"Bisanpura",
    "ks:ks_name":"Bishanpura",
    "ks:ks_pop":0,
    "ks:ks_type":"VILLAGE",
    "name:eng_x_preferred":[
        "Bishanpura"
    ],
    "name:eng_x_variant":[
        "Bisanpura",
        "Bisanp\u016bra"
    ],
    "wof:name":"Bishanpura",
    "wof:placetype":"locality",
    "wof:population":0
},
  "geometry": {"coordinates":[75.201548,30.742585],"type":"Point"}
}