{
  "type": "Feature",
  "properties": {
    "gn:admin1_code":"11.0",
    "gn:admin2_code":"32.0",
    "gn:asciiname":"Thountha",
    "gn:country_code":"IN",
    "gn:dem":1669,
    "gn:feature_class":"P",
    "gn:feature_code":"PPL",
    "gn:name":"Thountha",
    "gn:population":0,
    "gn:timezone":"Asia/Kolkata",
    "iso:country":"IN",
    "wof:name":"Thountha",
    "wof:placetype":"locality"
},
  "geometry": {"coordinates":[77.63488000000002,30.62638],"type":"Point"}
}