{
  "type": "Feature",
  "properties": {
    "gn:admin1_code":"40",
    "gn:admin2_code":"535.0",
    "gn:asciiname":"Bhanapur",
    "gn:country_code":"IN",
    "gn:dem":522,
    "gn:feature_class":"P",
    "gn:feature_code":"PPL",
    "gn:name":"Bh\u0101n\u0101pur",
    "gn:population":0,
    "gn:timezone":"Asia/Kolkata",
    "iso:country":"IN",
    "name:ara_x_preferred":[
        "\u0628\u0647\u0627\u0646\u0628\u0648\u0631"
    ],
    "name:ben_bn_x_preferred":[
        "\u09ad\u09be\u09a8\u09be\u09aa\u09c1\u09b0"
    ],
    "name:ben_in_x_preferred":[
        "\u09ad\u09be\u09a8\u09be\u09aa\u09c1\u09b0"
    ],
    "name:guj_x_preferred":[
        "\u0aad\u0abe\u0aa8\u0aaa\u0ac1\u0ab0"
    ],
    "name:hin_x_preferred":[
        "\u092d\u093e\u0928\u092a\u0941\u0930"
    ],
    "name:kan_x_preferred":[
        "\u0cad\u0cbe\u0ca8\u0cbe\u0caa\u0cc1\u0cb0"
    ],
    "name:mal_x_preferred":[
        "\u0d2d\u0d28\u0d3e\u0d2a\u0d42\u0d7c"
    ],
    "name:mar_x_preferred":[
        "\u092d\u093e\u0928\u093e\u092a\u0941\u0930"
    ],
    "name:pan_x_preferred":[
        "\u0a2d\u0a3e\u0a28\u0a3e\u0a2a\u0a41\u0a30"
    ],
    "name:tam_x_preferred":[
        "\u0baa\u0bbe\u0ba9\u0baa\u0bc2\u0bb0\u0bcd"
    ],
    "name:tel_x_preferred":[
        "\u0c2d\u0c28\u0c3e\u0c2a\u0c42\u0c30\u0c4d"
    ],
    "name:urd_x_preferred":[
        "\u0628\u06be\u0627\u0646\u0627 \u067e\u0648\u0631"
    ],
    "wof:name":"Bhanapur",
    "wof:placetype":"locality"
},
  "geometry": {"coordinates":[77.77060999999998,18.02178],"type":"Point"}
}