{
  "type": "Feature",
  "properties": {
    "iso:country":"IN",
    "ks:ks_name":"Bara",
    "ks:ks_pop":4571,
    "ks:ks_type":"VILLAGE",
    "ks:ks_uagg_main":0,
    "name:eng_x_preferred":[
        "Bara"
    ],
    "wof:name":"Bara",
    "wof:placetype":"locality",
    "wof:population":4571
},
  "geometry": {"coordinates":[88.518494,22.726758],"type":"Point"}
}