{
  "type": "Feature",
  "properties": {
    "gn:admin1_code":"35",
    "gn:admin2_code":"427.0",
    "gn:asciiname":"Balarkheri",
    "gn:country_code":"IN",
    "gn:dem":407,
    "gn:feature_class":"P",
    "gn:feature_code":"PPL",
    "gn:name":"Bal\u0101rkheri",
    "gn:population":0,
    "gn:timezone":"Asia/Kolkata",
    "iso:country":"IN",
    "ks:ks_name":"Balarkhedi",
    "ks:ks_pop":200,
    "ks:ks_type":"VILLAGE",
    "name:eng_x_preferred":[
        "Balarkhedi"
    ],
    "name:eng_x_variant":[
        "Balarkheri"
    ],
    "wof:name":"Balarkhedi",
    "wof:placetype":"locality",
    "wof:population":200
},
  "geometry": {"coordinates":[78.293846,24.352897],"type":"Point"}
}