{
  "type": "Feature",
  "properties": {
    "gn:country":"IN",
    "gn:fcode":"PPL",
    "gn:population":15142,
    "iso:country":"IN",
    "name:ben_x_preferred":[
        "\u09b9\u09bf\u09a8\u09a6\u09cb\u09b0\u09bf\u09af\u09bc\u09be"
    ],
    "name:bpy_x_preferred":[
        "\u09b9\u09bf\u09a8\u09a6\u09cb\u09b0\u09bf\u09af\u09bc\u09be"
    ],
    "name:ceb_x_preferred":[
        "Hindori\u0101"
    ],
    "name:eng_x_preferred":[
        "Hindoria"
    ],
    "name:hin_x_preferred":[
        "\u0939\u093f\u0928\u094d\u0926\u094b\u0930\u093f\u092f\u093e"
    ],
    "name:ita_x_preferred":[
        "Hindoria"
    ],
    "name:msa_x_preferred":[
        "Hindoria"
    ],
    "name:nan_x_preferred":[
        "Hindoria"
    ],
    "name:new_x_preferred":[
        "\u0939\u093f\u0928\u094d\u0926\u094b\u0930\u093f\u092f\u093e"
    ],
    "name:nld_x_preferred":[
        "Hindoria"
    ],
    "name:por_x_preferred":[
        "Hindoria"
    ],
    "name:spa_x_preferred":[
        "Hindoria"
    ],
    "name:swe_x_preferred":[
        "Hindori\u0101"
    ],
    "name:vie_x_preferred":[
        "Hindoria"
    ],
    "name:zho_x_preferred":[
        "\u5e0c\u6069\u591a\u91cc\u4e9a"
    ],
    "qs:name":"Hindoria",
    "qs:name_adm0":"India",
    "qs:name_adm1":"Madhya Pradesh",
    "qs:photos_9r":0,
    "qs:photos_sr":0,
    "qs:placetype":"Town",
    "qs:pop_sr":"6",
    "wd:wordcount":431,
    "wof:name":"Hindoria",
    "wof:placetype":"locality",
    "wof:population":15142
},
  "geometry": {"coordinates":[79.56904,23.90264],"type":"Point"}
}