{
  "type": "Feature",
  "properties": {
    "gn:admin1_code":"34.0",
    "gn:admin2_code":"215.0",
    "gn:asciiname":"Barampura",
    "gn:country_code":"IN",
    "gn:dem":52,
    "gn:feature_class":"P",
    "gn:feature_code":"PPL",
    "gn:name":"Barampura",
    "gn:population":0,
    "gn:timezone":"Asia/Kolkata",
    "iso:country":"IN",
    "wof:name":"Barampura",
    "wof:placetype":"locality"
},
  "geometry": {"coordinates":[86.29468,26.07061],"type":"Point"}
}