{
  "type": "Feature",
  "properties": {
    "iso:country":"IN",
    "ks:ks_name":"Majhipada",
    "ks:ks_pop":44,
    "ks:ks_type":"HABITATION",
    "name:eng_x_preferred":[
        "Majhipada"
    ],
    "wof:name":"Majhipada",
    "wof:placetype":"locality",
    "wof:population":44
},
  "geometry": {"coordinates":[82.93498,19.483085],"type":"Point"}
}