{
  "type": "Feature",
  "properties": {
    "iso:country":"IN",
    "ks:ks_name":"Balidanga",
    "ks:ks_pop":1142,
    "ks:ks_type":"VILLAGE",
    "ks:ks_uagg_main":0,
    "name:eng_x_preferred":[
        "Balidanga"
    ],
    "wof:name":"Balidanga",
    "wof:placetype":"neighbourhood",
    "wof:population":1142
},
  "geometry": {"coordinates":[88.20929700000001,23.621883],"type":"Point"}
}