{
  "type": "Feature",
  "properties": {
    "iso:country":"IN",
    "ks:ks_name":"Pure Lal",
    "ks:ks_pop":97,
    "ks:ks_type":"HABITATION",
    "name:eng_x_preferred":[
        "Pure Lal"
    ],
    "wof:name":"Pure Lal",
    "wof:placetype":"locality",
    "wof:population":97
},
  "geometry": {"coordinates":[81.655963,26.474512],"type":"Point"}
}