{
  "type": "Feature",
  "properties": {
    "iso:country":"IN",
    "ks:ks_name":"Pimpalwadi",
    "ks:ks_pop":470,
    "ks:ks_type":"HABITATION",
    "name:eng_x_preferred":[
        "Pimpalwadi"
    ],
    "wof:name":"Pimpalwadi",
    "wof:placetype":"locality",
    "wof:population":470
},
  "geometry": {"coordinates":[73.804632,16.367342],"type":"Point"}
}