{
  "type": "Feature",
  "properties": {
    "iso:country":"IN",
    "ks:ks_alt_nam":"Huhu\u0101",
    "ks:ks_alt_nam_2":"Huhua",
    "ks:ks_name":"Huhu",
    "ks:ks_type":"VILLAGE",
    "ks:ks_uagg_main":0,
    "name:eng_x_preferred":[
        "Huhu"
    ],
    "name:eng_x_variant":[
        "Huhu\u0101",
        "Huhua"
    ],
    "wof:name":"Huhu",
    "wof:placetype":"locality"
},
  "geometry": {"coordinates":[85.55544500000001,23.620102],"type":"Point"}
}