{
  "type": "Feature",
  "properties": {
    "iso:country":"IN",
    "ks:ks_alt_nam":"Mannarkulanj pamba",
    "ks:ks_name":"Mannarkulanj Pamba",
    "ks:ks_pop":100,
    "ks:ks_type":"HABITATION",
    "name:eng_x_preferred":[
        "Mannarkulanj Pamba"
    ],
    "wof:name":"Mannarkulanj Pamba",
    "wof:placetype":"locality",
    "wof:population":100
},
  "geometry": {"coordinates":[76.938495,9.389744],"type":"Point"}
}