{
  "type": "Feature",
  "properties": {
    "iso:country":"IN",
    "ks:ks_name":"Halechikkahosuru",
    "ks:ks_pop":261,
    "ks:ks_type":"HABITATION",
    "name:eng_x_preferred":[
        "Halechikkahosuru"
    ],
    "wof:name":"Halechikkahosuru",
    "wof:placetype":"locality",
    "wof:population":261
},
  "geometry": {"coordinates":[76.279276,12.298243],"type":"Point"}
}