{
  "type": "Feature",
  "properties": {
    "iso:country":"IN",
    "ks:ks_name":"Tambesthal",
    "ks:ks_pop":143,
    "ks:ks_type":"HABITATION",
    "name:eng_x_preferred":[
        "Tambesthal"
    ],
    "wof:name":"Tambesthal",
    "wof:placetype":"locality",
    "wof:population":143
},
  "geometry": {"coordinates":[74.146855,19.033524],"type":"Point"}
}