{
  "type": "Feature",
  "properties": {
    "gn:admin1_code":"10.0",
    "gn:admin2_code":"71.0",
    "gn:asciiname":"Bhatauli",
    "gn:country_code":"IN",
    "gn:dem":282,
    "gn:feature_class":"P",
    "gn:feature_code":"PPL",
    "gn:name":"Bhatauli",
    "gn:population":0,
    "gn:timezone":"Asia/Kolkata",
    "iso:country":"IN",
    "wof:name":"Bhatauli",
    "wof:placetype":"locality"
},
  "geometry": {"coordinates":[77.27725,30.1839],"type":"Point"}
}