{
  "type": "Feature",
  "properties": {
    "iso:country":"IN",
    "ks:ks_name":"Adali",
    "ks:ks_pop":17,
    "ks:ks_type":"HABITATION",
    "name:eng_x_preferred":[
        "Adali"
    ],
    "wof:name":"Adali",
    "wof:placetype":"locality",
    "wof:population":17
},
  "geometry": {"coordinates":[78.604207,29.884434],"type":"Point"}
}