{
  "type": "Feature",
  "properties": {
    "iso:country":"IN",
    "ks:ks_name":"Talagadia",
    "ks:ks_pop":370,
    "ks:ks_type":"HABITATION",
    "name:eng_x_preferred":[
        "Talagadia"
    ],
    "wof:name":"Talagadia",
    "wof:placetype":"locality",
    "wof:population":370
},
  "geometry": {"coordinates":[86.979883,21.465743],"type":"Point"}
}