{
  "type": "Feature",
  "properties": {
    "gn:admin1_code":"11",
    "gn:admin2_code":"34.0",
    "gn:asciiname":"Tebong Thach",
    "gn:cc2":"IN",
    "gn:country_code":"IN",
    "gn:dem":4705,
    "gn:feature_class":"P",
    "gn:feature_code":"PPL",
    "gn:name":"Tebong Th\u0101ch",
    "gn:population":0,
    "gn:timezone":"Asia/Kolkata",
    "iso:country":"IN",
    "name:und_x_variant":[
        "Tebong Thanga",
        "Tebong Th\u0101ch"
    ],
    "wof:name":"Tebong Thach",
    "wof:placetype":"locality"
},
  "geometry": {"coordinates":[78.15000000000001,31.78333],"type":"Point"}
}