{
  "type": "Feature",
  "properties": {
    "gn:admin1_code":"34.0",
    "gn:asciiname":"Sotha Chal",
    "gn:country_code":"IN",
    "gn:dem":70,
    "gn:feature_class":"P",
    "gn:feature_code":"PPL",
    "gn:name":"Sotha Chal",
    "gn:population":0,
    "gn:timezone":"Asia/Kolkata",
    "iso:country":"IN",
    "ks:ks_name":"Sotha Chak",
    "ks:ks_pop":152,
    "ks:ks_type":"VILLAGE",
    "ks:ks_uagg_main":0,
    "name:eng_x_preferred":[
        "Sotha Chak"
    ],
    "wof:name":"Sotha Chak",
    "wof:placetype":"neighbourhood",
    "wof:population":152
},
  "geometry": {"coordinates":[84.095415,26.240455],"type":"Point"}
}