{
  "type": "Feature",
  "properties": {
    "iso:country":"IN",
    "ks:ks_alt_nam":"NAMANJOY PARA",
    "ks:ks_name":"Namanjoy Para",
    "ks:ks_pop":19,
    "ks:ks_type":"HABITATION",
    "ks:ks_uagg_main":0,
    "name:eng_x_preferred":[
        "Namanjoy Para"
    ],
    "wof:name":"Namanjoy Para",
    "wof:placetype":"neighbourhood",
    "wof:population":19
},
  "geometry": {"coordinates":[91.702901,23.933654],"type":"Point"}
}