{
  "type": "Feature",
  "properties": {
    "gn:admin1_code":"11",
    "gn:admin2_code":"23.0",
    "gn:asciiname":"Mesh Got",
    "gn:country_code":"IN",
    "gn:dem":3020,
    "gn:feature_class":"P",
    "gn:feature_code":"PPL",
    "gn:name":"Mesh Got",
    "gn:population":0,
    "gn:timezone":"Asia/Kolkata",
    "iso:country":"IN",
    "wof:name":"Mesh Got",
    "wof:placetype":"locality"
},
  "geometry": {"coordinates":[76.46080000000001,32.99114],"type":"Point"}
}