{
  "type": "Feature",
  "properties": {
    "gn:admin1_code":"24",
    "gn:admin2_code":"111.0",
    "gn:asciiname":"Rohal",
    "gn:country_code":"IN",
    "gn:dem":316,
    "gn:feature_class":"P",
    "gn:feature_code":"PPL",
    "gn:name":"Rohal",
    "gn:population":0,
    "gn:timezone":"Asia/Kolkata",
    "iso:country":"IN",
    "ks:ks_name":"Rohal",
    "ks:ks_pop":2309,
    "ks:ks_type":"VILLAGE",
    "ks:ks_uagg_main":0,
    "name:eng_x_preferred":[
        "Rohal"
    ],
    "name:khm_x_preferred":[
        "\u1783\u17bb\u17c6\u179a\u17a0\u17b6\u179b"
    ],
    "name:pol_x_preferred":[
        "Rohal Rohal"
    ],
    "name:spa_x_preferred":[
        "Rohal"
    ],
    "name:und_x_variant":[
        "Rol"
    ],
    "wof:name":"Rohal",
    "wof:placetype":"neighbourhood",
    "wof:population":2309
},
  "geometry": {"coordinates":[74.866253,28.044608],"type":"Point"}
}