{
  "type": "Feature",
  "properties": {
    "iso:country":"IN",
    "ks:ks_name":"Bhangiyavad",
    "ks:ks_pop":643,
    "ks:ks_type":"VILLAGE",
    "name:eng_x_preferred":[
        "Bhangiyavad"
    ],
    "wof:name":"Bhangiyavad",
    "wof:placetype":"locality",
    "wof:population":643
},
  "geometry": {"coordinates":[73.902806,21.993389],"type":"Point"}
}