{
  "type": "Feature",
  "properties": {
    "iso:country":"IN",
    "ks:ks_name":"Ulubari",
    "ks:ks_pop":403,
    "ks:ks_type":"VILLAGE",
    "ks:ks_uagg_main":0,
    "name:eng_x_preferred":[
        "Ulubari"
    ],
    "wof:name":"Ulubari",
    "wof:placetype":"neighbourhood",
    "wof:population":403
},
  "geometry": {"coordinates":[90.773481,26.587115],"type":"Point"}
}