{
  "type": "Feature",
  "properties": {
    "iso:country":"IN",
    "ks:ks_alt_nam":"MADHYA GHANIAMURA",
    "ks:ks_name":"Madhya Ghaniamura",
    "ks:ks_pop":444,
    "ks:ks_type":"HABITATION",
    "ks:ks_uagg_main":0,
    "name:eng_x_preferred":[
        "Madhya Ghaniamura"
    ],
    "wof:name":"Madhya Ghaniamura",
    "wof:placetype":"neighbourhood",
    "wof:population":444
},
  "geometry": {"coordinates":[91.238663,23.666003],"type":"Point"}
}