{
  "type": "Feature",
  "properties": {
    "iso:country":"IN",
    "ks:ks_name":"Biyane Gundi Munigoor",
    "ks:ks_pop":102,
    "ks:ks_type":"HABITATION",
    "name:eng_x_preferred":[
        "Biyane Gundi Munigoor"
    ],
    "wof:name":"Biyane Gundi Munigoor",
    "wof:placetype":"locality",
    "wof:population":102
},
  "geometry": {"coordinates":[75.523611,12.468056],"type":"Point"}
}