{
  "type": "Feature",
  "properties": {
    "gn:admin1_code":"40.0",
    "gn:admin2_code":"537",
    "gn:asciiname":"Yamjal",
    "gn:cc2":"IN",
    "gn:country_code":"IN",
    "gn:dem":537,
    "gn:feature_class":"P",
    "gn:feature_code":"PPL",
    "gn:name":"Yamj\u0101l",
    "gn:population":0,
    "gn:timezone":"Asia/Kolkata",
    "iso:country":"IN",
    "name:und_x_variant":[
        "Yemjal",
        "Yamj\u0101l"
    ],
    "wof:name":"Yamjal",
    "wof:placetype":"neighbourhood"
},
  "geometry": {"coordinates":[78.57666999999999,17.26944],"type":"Point"}
}