{
  "type": "Feature",
  "properties": {
    "gn:admin1_code":"11.0",
    "gn:admin2_code":"32.0",
    "gn:asciiname":"Moiralti",
    "gn:country_code":"IN",
    "gn:dem":1987,
    "gn:feature_class":"P",
    "gn:feature_code":"PPL",
    "gn:name":"Moir\u0101lti",
    "gn:population":0,
    "gn:timezone":"Asia/Kolkata",
    "iso:country":"IN",
    "wof:name":"Moiralti",
    "wof:placetype":"locality"
},
  "geometry": {"coordinates":[77.54214,30.73316],"type":"Point"}
}