{
  "type": "Feature",
  "properties": {
    "iso:country":"IN",
    "ks:ks_name":"Sankiklarpuram",
    "ks:ks_pop":112,
    "ks:ks_type":"HABITATION",
    "name:eng_x_preferred":[
        "Sankiklarpuram"
    ],
    "wof:name":"Sankiklarpuram",
    "wof:placetype":"locality",
    "wof:population":112
},
  "geometry": {"coordinates":[77.707437,10.180826],"type":"Point"}
}