{
  "type": "Feature",
  "properties": {
    "iso:country":"IN",
    "ks:ks_name":"Barhi Purwa",
    "ks:ks_pop":262,
    "ks:ks_type":"HABITATION",
    "name:eng_x_preferred":[
        "Barhi Purwa"
    ],
    "wof:name":"Barhi Purwa",
    "wof:placetype":"locality",
    "wof:population":262
},
  "geometry": {"coordinates":[81.782875,27.275336],"type":"Point"}
}