{
  "type": "Feature",
  "properties": {
    "iso:country":"IN",
    "ks:ks_name":"Kusmaha",
    "ks:ks_pop":646,
    "ks:ks_type":"VILLAGE",
    "name:eng_x_preferred":[
        "Kusmaha"
    ],
    "wof:name":"Kusmaha",
    "wof:placetype":"locality",
    "wof:population":646
},
  "geometry": {"coordinates":[87.3785,24.617502],"type":"Point"}
}