{
  "type": "Feature",
  "properties": {
    "iso:country":"IN",
    "ks:ks_name":"Nara Shimul",
    "ks:ks_pop":278,
    "ks:ks_type":"HABITATION",
    "name:eng_x_preferred":[
        "Nara Shimul"
    ],
    "wof:name":"Nara Shimul",
    "wof:placetype":"locality",
    "wof:population":278
},
  "geometry": {"coordinates":[86.841989,22.168493],"type":"Point"}
}