{
  "type": "Feature",
  "properties": {
    "iso:country":"IN",
    "ks:ks_name":"Totapara",
    "ks:ks_pop":656,
    "ks:ks_type":"VILLAGE",
    "name:eng_x_preferred":[
        "Totapara"
    ],
    "wof:name":"Totapara",
    "wof:placetype":"locality",
    "wof:population":656
},
  "geometry": {"coordinates":[87.23257099999999,21.900026],"type":"Point"}
}