{
  "type": "Feature",
  "properties": {
    "iso:country":"IN",
    "ks:ks_name":"Chaipurwa",
    "ks:ks_pop":324,
    "ks:ks_type":"HABITATION",
    "name:eng_x_preferred":[
        "Chaipurwa"
    ],
    "wof:name":"Chaipurwa",
    "wof:placetype":"locality",
    "wof:population":324
},
  "geometry": {"coordinates":[81.20359500000001,27.948892],"type":"Point"}
}