{
  "type": "Feature",
  "properties": {
    "iso:country":"IN",
    "ks:ks_name":"Amra Mog Para",
    "ks:ks_pop":230,
    "ks:ks_type":"HABITATION",
    "name:eng_x_preferred":[
        "Amra Mog Para"
    ],
    "wof:name":"Amra Mog Para",
    "wof:placetype":"locality",
    "wof:population":230
},
  "geometry": {"coordinates":[91.64473099999999,23.121705],"type":"Point"}
}