{
  "type": "Feature",
  "properties": {
    "iso:country":"IN",
    "ks:ks_alt_nam":"Ayir\u0101puram",
    "ks:ks_name":"Ayirapuram",
    "ks:ks_type":"VILLAGE",
    "name:eng_x_preferred":[
        "Ayirapuram"
    ],
    "name:eng_x_variant":[
        "Ayir\u0101puram"
    ],
    "wof:name":"Ayirapuram",
    "wof:placetype":"locality"
},
  "geometry": {"coordinates":[76.50604199999999,10.032787],"type":"Point"}
}