{
  "type": "Feature",
  "properties": {
    "iso:country":"IN",
    "ks:ks_name":"Kodiyadka",
    "ks:ks_pop":19,
    "ks:ks_type":"HABITATION",
    "name:eng_x_preferred":[
        "Kodiyadka"
    ],
    "wof:name":"Kodiyadka",
    "wof:placetype":"locality",
    "wof:population":19
},
  "geometry": {"coordinates":[75.342539,12.674444],"type":"Point"}
}