{
  "type": "Feature",
  "properties": {
    "iso:country":"IN",
    "ks:ks_name":"Chellapillaikuttai",
    "ks:ks_pop":6610,
    "ks:ks_type":"VILLAGE",
    "ks:ks_uagg_main":0,
    "name:eng_x_preferred":[
        "Chellapillaikuttai"
    ],
    "wof:name":"Chellapillaikuttai",
    "wof:placetype":"locality",
    "wof:population":6610
},
  "geometry": {"coordinates":[78.055421,11.709884],"type":"Point"}
}