{
  "type": "Feature",
  "properties": {
    "iso:country":"IN",
    "ks:ks_name":"Mundhakata",
    "ks:ks_pop":968,
    "ks:ks_type":"VILLAGE",
    "name:eng_x_preferred":[
        "Mundhakata"
    ],
    "wof:name":"Mundhakata",
    "wof:placetype":"locality",
    "wof:population":968
},
  "geometry": {"coordinates":[86.524119,22.19752],"type":"Point"}
}