{
  "type": "Feature",
  "properties": {
    "gn:admin1_code":"36",
    "gn:admin2_code":"146.0",
    "gn:asciiname":"Hirner Nawada Khera",
    "gn:country_code":"IN",
    "gn:dem":172,
    "gn:feature_class":"P",
    "gn:feature_code":"PPL",
    "gn:name":"Hirner Naw\u0101da Khera",
    "gn:population":0,
    "gn:timezone":"Asia/Kolkata",
    "iso:country":"IN",
    "wof:name":"Hirner Nawada Khera",
    "wof:placetype":"locality"
},
  "geometry": {"coordinates":[78.10854,27.05672],"type":"Point"}
}