{
  "type": "Feature",
  "properties": {
    "gn:admin1_code":"36.0",
    "gn:admin2_code":"163.0",
    "gn:asciiname":"Munawarpur Rasulabad",
    "gn:country_code":"IN",
    "gn:dem":139,
    "gn:feature_class":"P",
    "gn:feature_code":"PPL",
    "gn:name":"Munawarpur Ras\u016bl\u0101b\u0101d",
    "gn:population":0,
    "gn:timezone":"Asia/Kolkata",
    "iso:country":"IN",
    "wof:name":"Munawarpur Rasulabad",
    "wof:placetype":"locality"
},
  "geometry": {"coordinates":[79.87501999999998,26.70413],"type":"Point"}
}