{
  "type": "Feature",
  "properties": {
    "gn:admin1_code":"9.0",
    "gn:admin2_code":"471",
    "gn:asciiname":"Bhandu",
    "gn:country_code":"IN",
    "gn:dem":100,
    "gn:feature_class":"P",
    "gn:feature_code":"PPL",
    "gn:name":"Bh\u0101ndu",
    "gn:population":0,
    "gn:timezone":"Asia/Kolkata",
    "iso:country":"IN",
    "name:guj_x_preferred":[
        "\u0aad\u0abe\u0a82\u0aa1\u0ac1"
    ],
    "name:und_x_variant":[
        "Bh\u0101ndu"
    ],
    "wof:name":"Bhandu",
    "wof:placetype":"locality"
},
  "geometry": {"coordinates":[72.38695,23.70267],"type":"Point"}
}