{
  "type": "Feature",
  "properties": {
    "gn:admin1_code":"16.0",
    "gn:admin2_code":"515.0",
    "gn:asciiname":"Kavatgaon",
    "gn:country_code":"IN",
    "gn:dem":593,
    "gn:feature_class":"P",
    "gn:feature_code":"PPL",
    "gn:name":"Kavatgaon",
    "gn:population":0,
    "gn:timezone":"Asia/Kolkata",
    "iso:country":"IN",
    "wof:name":"Kavatgaon",
    "wof:placetype":"locality"
},
  "geometry": {"coordinates":[75.17503000000001,20.14326],"type":"Point"}
}