{
  "type": "Feature",
  "properties": {
    "iso:country":"IN",
    "ks:ks_alt_nam":"Chalio city",
    "ks:ks_name":"Chalio City",
    "ks:ks_pop":525,
    "ks:ks_type":"HABITATION",
    "name:eng_x_preferred":[
        "Chalio City"
    ],
    "wof:name":"Chalio City",
    "wof:placetype":"locality",
    "wof:population":525
},
  "geometry": {"coordinates":[85.029329,23.528418],"type":"Point"}
}