{
  "type": "Feature",
  "properties": {
    "iso:country":"IN",
    "ks:ks_alt_nam":"Palwar Gyodi ka Khoda",
    "ks:ks_name":"Palwar Gyodi Ka Khoda",
    "ks:ks_pop":1064,
    "ks:ks_type":"HABITATION",
    "ks:ks_uagg_main":0,
    "name:eng_x_preferred":[
        "Palwar Gyodi Ka Khoda"
    ],
    "wof:name":"Palwar Gyodi Ka Khoda",
    "wof:placetype":"neighbourhood",
    "wof:population":1064
},
  "geometry": {"coordinates":[79.981055,25.606812],"type":"Point"}
}