{
  "type": "Feature",
  "properties": {
    "gn:admin1_code":"19.0",
    "gn:admin2_code":"572.0",
    "gn:asciiname":"Jayanagar 9th Block",
    "gn:country_code":"IN",
    "gn:dem":920,
    "gn:feature_class":"P",
    "gn:feature_code":"PPL",
    "gn:name":"Jayanagar 9th Block",
    "gn:population":0,
    "gn:timezone":"Asia/Kolkata",
    "iso:country":"IN",
    "wof:name":"Jayanagar 9th Block",
    "wof:placetype":"neighbourhood"
},
  "geometry": {"coordinates":[77.5924,12.91965],"type":"Point"}
}