{
  "type": "Feature",
  "properties": {
    "iso:country":"IN",
    "ks:ks_name":"Muthambi",
    "ks:ks_pop":908,
    "ks:ks_type":"HABITATION",
    "ks:ks_uagg_main":0,
    "name:eng_x_preferred":[
        "Muthambi"
    ],
    "wof:name":"Muthambi",
    "wof:placetype":"neighbourhood",
    "wof:population":908
},
  "geometry": {"coordinates":[75.73343199999999,11.483668],"type":"Point"}
}