{
  "type": "Feature",
  "properties": {
    "gn:admin1_code":"19.0",
    "gn:admin2_code":"568.0",
    "gn:asciiname":"Achapura",
    "gn:country_code":"IN",
    "gn:dem":643,
    "gn:feature_class":"P",
    "gn:feature_code":"PPL",
    "gn:name":"Ach\u0101pura",
    "gn:population":0,
    "gn:timezone":"Asia/Kolkata",
    "iso:country":"IN",
    "name:fas_x_preferred":[
        "\u0627\u0686\u0627\u067e\u0648\u0631\u0627"
    ],
    "name:vie_x_preferred":[
        "Achapura"
    ],
    "wof:name":"Achapura",
    "wof:placetype":"locality"
},
  "geometry": {"coordinates":[75.22781999999999,14.06879],"type":"Point"}
}