{
  "type": "Feature",
  "properties": {
    "iso:country":"IN",
    "ks:ks_alt_nam":"MAHUABERA",
    "ks:ks_name":"Mahuabera",
    "ks:ks_pop":610,
    "ks:ks_type":"HABITATION",
    "name:eng_x_preferred":[
        "Mahuabera"
    ],
    "wof:name":"Mahuabera",
    "wof:placetype":"locality",
    "wof:population":610
},
  "geometry": {"coordinates":[85.322052,24.624391],"type":"Point"}
}