{
  "type": "Feature",
  "properties": {
    "iso:country":"IN",
    "ks:ks_name":"Chatridih",
    "ks:ks_type":"VILLAGE",
    "name:eng_x_preferred":[
        "Chatridih"
    ],
    "wof:name":"Chatridih",
    "wof:placetype":"locality"
},
  "geometry": {"coordinates":[86.19253500000001,24.608039],"type":"Point"}
}