{
  "type": "Feature",
  "properties": {
    "gn:admin1_code":"13.0",
    "gn:admin2_code":"594.0",
    "gn:asciiname":"Vanmenad",
    "gn:country_code":"IN",
    "gn:dem":14,
    "gn:feature_class":"P",
    "gn:feature_code":"PPL",
    "gn:name":"Vanm\u0113n\u0101d",
    "gn:population":0,
    "gn:timezone":"Asia/Kolkata",
    "iso:country":"IN",
    "ks:ks_name":"Venmanad",
    "ks:ks_pop":9687,
    "ks:ks_type":"VILLAGE",
    "name:eng_x_preferred":[
        "Venmanad"
    ],
    "name:eng_x_variant":[
        "Vanmenad"
    ],
    "wof:name":"Venmanad",
    "wof:placetype":"locality",
    "wof:population":9687
},
  "geometry": {"coordinates":[76.054812,10.550823],"type":"Point"}
}