{
  "type": "Feature",
  "properties": {
    "gn:admin1_code":"13.0",
    "gn:admin2_code":"594.0",
    "gn:asciiname":"Vanmenad",
    "gn:country_code":"IN",
    "gn:dem":14,
    "gn:feature_class":"P",
    "gn:feature_code":"PPL",
    "gn:name":"Vanm\u0113n\u0101d",
    "gn:population":0,
    "gn:timezone":"Asia/Kolkata",
    "iso:country":"IN",
    "wof:name":"Vanmenad",
    "wof:placetype":"locality"
},
  "geometry": {"coordinates":[76.0624,10.5567],"type":"Point"}
}