{
  "type": "Feature",
  "properties": {
    "iso:country":"IN",
    "ks:ks_alt_nam":"Mariyapuram-Yohannanmedu-Rd",
    "ks:ks_name":"Mariyapuram-yohannanmedu-rd",
    "ks:ks_pop":300,
    "ks:ks_type":"HABITATION",
    "name:eng_x_preferred":[
        "Mariyapuram-yohannanmedu-rd"
    ],
    "wof:name":"Mariyapuram-yohannanmedu-rd",
    "wof:placetype":"locality",
    "wof:population":300
},
  "geometry": {"coordinates":[76.97468000000001,9.863665],"type":"Point"}
}