{
  "type": "Feature",
  "properties": {
    "gn:admin1_code":"19.0",
    "gn:admin2_code":"572.0",
    "gn:asciiname":"Adakimaranhalli",
    "gn:country_code":"IN",
    "gn:dem":858,
    "gn:feature_class":"P",
    "gn:feature_code":"PPL",
    "gn:name":"Adakim\u0101ranhalli",
    "gn:population":0,
    "gn:timezone":"Asia/Kolkata",
    "iso:country":"IN",
    "ks:ks_name":"Adakamaranahalli",
    "ks:ks_pop":1519,
    "ks:ks_type":"VILLAGE",
    "ks:ks_uagg_main":0,
    "name:eng_x_preferred":[
        "Adakamaranahalli"
    ],
    "wof:name":"Adakamaranahalli",
    "wof:placetype":"locality",
    "wof:population":1519
},
  "geometry": {"coordinates":[77.44440299999999,13.067395],"type":"Point"}
}