{
  "type": "Feature",
  "properties": {
    "gn:admin1_code":"28.0",
    "gn:admin2_code":"341.0",
    "gn:asciiname":"Dihi Bhursut",
    "gn:country_code":"IN",
    "gn:dem":12,
    "gn:feature_class":"P",
    "gn:feature_code":"PPL",
    "gn:name":"Dihi Bhursut",
    "gn:population":0,
    "gn:timezone":"Asia/Kolkata",
    "iso:country":"IN",
    "wof:name":"Dihi Bhursut",
    "wof:placetype":"locality"
},
  "geometry": {"coordinates":[87.98003,22.77103],"type":"Point"}
}