{
  "type": "Feature",
  "properties": {
    "iso:country":"IN",
    "ks:ks_name":"Talav Faliyu",
    "ks:ks_pop":143,
    "ks:ks_type":"HABITATION",
    "ks:ks_uagg_main":0,
    "name:eng_x_preferred":[
        "Talav Faliyu"
    ],
    "wof:name":"Talav Faliyu",
    "wof:placetype":"neighbourhood",
    "wof:population":143
},
  "geometry": {"coordinates":[72.774056,20.253889],"type":"Point"}
}