{
  "type": "Feature",
  "properties": {
    "gn:admin1_code":"36",
    "gn:admin2_code":"147.0",
    "gn:asciiname":"Pilakhtar Fateh",
    "gn:country_code":"IN",
    "gn:dem":177,
    "gn:feature_class":"P",
    "gn:feature_code":"PPL",
    "gn:name":"Pilakhtar Fateh",
    "gn:population":0,
    "gn:timezone":"Asia/Kolkata",
    "iso:country":"IN",
    "ks:ks_name":"Pilakhtar Fateh",
    "ks:ks_pop":1213,
    "ks:ks_type":"VILLAGE",
    "ks:ks_uagg_main":0,
    "name:eng_x_preferred":[
        "Pilakhtar Fateh"
    ],
    "wof:name":"Pilakhtar Fateh",
    "wof:placetype":"neighbourhood",
    "wof:population":1213
},
  "geometry": {"coordinates":[78.546823,27.349131],"type":"Point"}
}