{
  "type": "Feature",
  "properties": {
    "iso:country":"IN",
    "ks:ks_alt_nam":"Avhad wasti",
    "ks:ks_name":"Avhad Wasti",
    "ks:ks_pop":96,
    "ks:ks_type":"HABITATION",
    "ks:ks_uagg_main":0,
    "name:eng_x_preferred":[
        "Avhad Wasti"
    ],
    "wof:name":"Avhad Wasti",
    "wof:placetype":"neighbourhood",
    "wof:population":96
},
  "geometry": {"coordinates":[74.444883,19.884955],"type":"Point"}
}