{
  "type": "Feature",
  "properties": {
    "iso:country":"IN",
    "ks:ks_name":"2 KM",
    "ks:ks_pop":130,
    "ks:ks_type":"VILLAGE",
    "name:eng_x_preferred":[
        "2 KM"
    ],
    "wof:name":"2 KM",
    "wof:placetype":"locality",
    "wof:population":130
},
  "geometry": {"coordinates":[72.878669,28.929521],"type":"Point"}
}