{
  "type": "Feature",
  "properties": {
    "gn:admin1_code":"36",
    "gn:admin2_code":"156.0",
    "gn:asciiname":"Maharani Khera",
    "gn:country_code":"IN",
    "gn:dem":126,
    "gn:feature_class":"P",
    "gn:feature_code":"PPL",
    "gn:name":"Mah\u0101r\u0101ni Khera",
    "gn:population":0,
    "gn:timezone":"Asia/Kolkata",
    "iso:country":"IN",
    "ks:ks_alt_nam":"Mah\u0101r\u0101ni Khera",
    "ks:ks_name":"Maharani Khera",
    "ks:ks_type":"VILLAGE",
    "ks:ks_uagg_main":0,
    "name:eng_x_preferred":[
        "Maharani Khera"
    ],
    "name:eng_x_variant":[
        "Mah\u0101r\u0101ni Khera"
    ],
    "wof:name":"Maharani Khera",
    "wof:placetype":"neighbourhood"
},
  "geometry": {"coordinates":[80.91417,26.445599],"type":"Point"}
}