{
  "type": "Feature",
  "properties": {
    "iso:country":"IN",
    "ks:ks_name":"Bavadawa Sidhwadamar",
    "ks:ks_pop":828,
    "ks:ks_type":"HABITATION",
    "name:eng_x_preferred":[
        "Bavadawa Sidhwadamar"
    ],
    "wof:name":"Bavadawa Sidhwadamar",
    "wof:placetype":"locality",
    "wof:population":828
},
  "geometry": {"coordinates":[83.01367500000001,24.542557],"type":"Point"}
}