{
  "type": "Feature",
  "properties": {
    "iso:country":"IN",
    "ks:ks_alt_nam":"B\u0101l\u0101ju",
    "ks:ks_name":"Balaju",
    "ks:ks_pop":28,
    "ks:ks_type":"VILLAGE",
    "name:eng_x_preferred":[
        "Balaju"
    ],
    "name:eng_x_variant":[
        "B\u0101l\u0101ju"
    ],
    "wof:name":"Balaju",
    "wof:placetype":"locality",
    "wof:population":28
},
  "geometry": {"coordinates":[84.475578,20.414108],"type":"Point"}
}