{
  "type": "Feature",
  "properties": {
    "gn:admin1_code":"12.0",
    "gn:admin2_code":"7.0",
    "gn:asciiname":"Mela",
    "gn:country_code":"IN",
    "gn:dem":473,
    "gn:feature_class":"P",
    "gn:feature_code":"PPL",
    "gn:name":"Mela",
    "gn:population":0,
    "gn:timezone":"Asia/Kolkata",
    "iso:country":"IN",
    "name:kan_x_preferred":[
        "\u0cae\u0cc7\u0cb3"
    ],
    "name:mal_x_preferred":[
        "\u0d2e\u0d47\u0d33"
    ],
    "name:pan_x_preferred":[
        "\u0a2e\u0a47\u0a32\u0a3e"
    ],
    "name:rus_x_preferred":[
        "\u041c\u0435\u043b\u0430"
    ],
    "wof:name":"Mela",
    "wof:placetype":"locality"
},
  "geometry": {"coordinates":[75.30459,32.50057],"type":"Point"}
}