{
  "type": "Feature",
  "properties": {
    "iso:country":"IN",
    "ks:ks_alt_nam":"PANDHARKI WASTI",
    "ks:ks_name":"Pandharki Wasti",
    "ks:ks_pop":53,
    "ks:ks_type":"HABITATION",
    "name:eng_x_preferred":[
        "Pandharki Wasti"
    ],
    "wof:name":"Pandharki Wasti",
    "wof:placetype":"locality",
    "wof:population":53
},
  "geometry": {"coordinates":[74.484318,17.361768],"type":"Point"}
}