{
  "type": "Feature",
  "properties": {
    "gn:admin1_code":"36",
    "gn:admin2_code":"161.0",
    "gn:asciiname":"Kantihar",
    "gn:country_code":"IN",
    "gn:dem":152,
    "gn:feature_class":"P",
    "gn:feature_code":"PPL",
    "gn:name":"Kantih\u0101r",
    "gn:population":0,
    "gn:timezone":"Asia/Kolkata",
    "iso:country":"IN",
    "ks:ks_alt_nam":"Kantih\u0101r",
    "ks:ks_name":"Kantihar",
    "ks:ks_type":"VILLAGE",
    "name:eng_x_preferred":[
        "Kantihar"
    ],
    "name:eng_x_variant":[
        "Kantih\u0101r"
    ],
    "wof:name":"Kantihar",
    "wof:placetype":"locality"
},
  "geometry": {"coordinates":[78.96869,26.877217],"type":"Point"}
}