{
  "type": "Feature",
  "properties": {
    "iso:country":"IN",
    "ks:ks_name":"Marhra",
    "ks:ks_pop":522,
    "ks:ks_type":"VILLAGE",
    "name:eng_x_preferred":[
        "Marhra"
    ],
    "wof:name":"Marhra",
    "wof:placetype":"locality",
    "wof:population":522
},
  "geometry": {"coordinates":[82.982215,24.689989],"type":"Point"}
}