{
  "type": "Feature",
  "properties": {
    "iso:country":"IN",
    "ks:ks_name":"Badgad",
    "ks:ks_pop":1154,
    "ks:ks_type":"VILLAGE",
    "name:eng_x_preferred":[
        "Badgad"
    ],
    "wof:name":"Badgad",
    "wof:placetype":"locality",
    "wof:population":1154
},
  "geometry": {"coordinates":[82.67462,24.351664],"type":"Point"}
}