{
  "type": "Feature",
  "properties": {
    "gn:admin1_code":"23.0",
    "gn:admin2_code":"53.0",
    "gn:asciiname":"Fatehgarh",
    "gn:country_code":"IN",
    "gn:dem":240,
    "gn:feature_class":"P",
    "gn:feature_code":"PPL",
    "gn:name":"Fatehgarh",
    "gn:population":0,
    "gn:timezone":"Asia/Kolkata",
    "iso:country":"IN",
    "name:und_x_variant":[
        "Kheri Khurd"
    ],
    "wof:name":"Fatehgarh",
    "wof:placetype":"locality"
},
  "geometry": {"coordinates":[75.68394000000001,30.42107],"type":"Point"}
}