{
  "type": "Feature",
  "properties": {
    "gn:admin1_code":"36",
    "gn:admin2_code":"145.0",
    "gn:asciiname":"Mansa",
    "gn:country_code":"IN",
    "gn:dem":180,
    "gn:feature_class":"P",
    "gn:feature_code":"PPL",
    "gn:name":"Mansa",
    "gn:population":0,
    "gn:timezone":"Asia/Kolkata",
    "iso:country":"IN",
    "name:ceb_x_preferred":[
        "Mansa"
    ],
    "name:deu_x_preferred":[
        "Mansa"
    ],
    "name:fra_x_preferred":[
        "Mansa"
    ],
    "name:ita_x_preferred":[
        "Mansa"
    ],
    "name:jpn_x_preferred":[
        "\u30de\u30f3\u30b5"
    ],
    "name:nld_x_preferred":[
        "Mansa"
    ],
    "name:por_x_preferred":[
        "Mansa"
    ],
    "name:ron_x_preferred":[
        "Mansa"
    ],
    "name:rus_x_preferred":[
        "\u041c\u0430\u043d\u0441\u0430"
    ],
    "name:spa_x_preferred":[
        "Mansa"
    ],
    "name:swe_x_preferred":[
        "Mansa"
    ],
    "wof:name":"Mansa",
    "wof:placetype":"locality"
},
  "geometry": {"coordinates":[77.8759,27.38449],"type":"Point"}
}