{
  "type": "Feature",
  "properties": {
    "gn:admin1_code":"36",
    "gn:admin2_code":"145.0",
    "gn:asciiname":"Mansa",
    "gn:country_code":"IN",
    "gn:dem":180,
    "gn:feature_class":"P",
    "gn:feature_code":"PPL",
    "gn:name":"Mansa",
    "gn:population":0,
    "gn:timezone":"Asia/Kolkata",
    "iso:country":"IN",
    "name:ara_x_preferred":[
        "\u0645\u0627\u0646\u0633\u0627"
    ],
    "name:ben_bn_x_preferred":[
        "\u09ae\u09be\u09a8\u09b8\u09be"
    ],
    "name:ben_in_x_preferred":[
        "\u09ae\u09be\u09a8\u09b8\u09be"
    ],
    "name:ceb_x_preferred":[
        "Mansa"
    ],
    "name:deu_x_preferred":[
        "Mansa"
    ],
    "name:fra_x_preferred":[
        "Mansa"
    ],
    "name:guj_x_preferred":[
        "\u0aae\u0abe\u0aa3\u0ab8\u0abe"
    ],
    "name:hin_x_preferred":[
        "\u092e\u093e\u0902\u0938\u093e"
    ],
    "name:hin_x_variant":[
        "\u092e\u0928\u0938\u093e"
    ],
    "name:hun_x_preferred":[
        "Mansa"
    ],
    "name:ind_x_preferred":[
        "Mansa"
    ],
    "name:ita_x_preferred":[
        "Mansa"
    ],
    "name:jpn_x_preferred":[
        "\u30de\u30f3\u30b5"
    ],
    "name:kan_x_preferred":[
        "\u0cae\u0ca8\u0ccd\u0cb8\u0cbe"
    ],
    "name:mal_x_preferred":[
        "\u0d2e\u0d7b\u0d38"
    ],
    "name:mar_x_preferred":[
        "\u092e\u093e\u0928\u0938\u093e"
    ],
    "name:nld_x_preferred":[
        "Mansa"
    ],
    "name:pan_x_preferred":[
        "\u0a2e\u0a3e\u0a23\u0a38\u0a3e"
    ],
    "name:por_x_preferred":[
        "Mansa"
    ],
    "name:ron_x_preferred":[
        "Mansa"
    ],
    "name:rus_x_preferred":[
        "\u041c\u0430\u043d\u0441\u0430"
    ],
    "name:spa_x_preferred":[
        "Mansa"
    ],
    "name:swe_x_preferred":[
        "Mansa"
    ],
    "name:tam_x_preferred":[
        "\u0bae\u0ba9\u0bcd\u0b9a\u0bbe"
    ],
    "name:tel_x_preferred":[
        "\u0c2e\u0c28\u0c4d\u0c38\u0c3e"
    ],
    "name:urd_x_preferred":[
        "\u0645\u0646\u0633\u0627"
    ],
    "name:vie_x_preferred":[
        "Mansa"
    ],
    "wof:name":"Mansa",
    "wof:placetype":"locality"
},
  "geometry": {"coordinates":[77.8759,27.38449],"type":"Point"}
}