{
  "type": "Feature",
  "properties": {
    "gn:admin1_code":"12.0",
    "gn:asciiname":"Kachar",
    "gn:country_code":"IN",
    "gn:dem":2300,
    "gn:feature_class":"P",
    "gn:feature_code":"PPL",
    "gn:name":"Kachar",
    "gn:population":0,
    "gn:timezone":"Asia/Kolkata",
    "iso:country":"IN",
    "name:und_x_variant":[
        "Kachhar"
    ],
    "wof:name":"Kachar",
    "wof:placetype":"locality"
},
  "geometry": {"coordinates":[73.99798,34.05298],"type":"Point"}
}