{
  "type": "Feature",
  "properties": {
    "gn:admin1_code":"19.0",
    "gn:admin2_code":"573.0",
    "gn:asciiname":"Kottanahalli",
    "gn:country_code":"IN",
    "gn:dem":643,
    "gn:feature_class":"P",
    "gn:feature_code":"PPL",
    "gn:name":"Kottanahalli",
    "gn:population":0,
    "gn:timezone":"Asia/Kolkata",
    "iso:country":"IN",
    "ks:ks_name":"Kothana Halli",
    "ks:ks_pop":853,
    "ks:ks_type":"VILLAGE",
    "ks:ks_uagg_main":0,
    "name:eng_x_preferred":[
        "Kothana Halli"
    ],
    "wof:name":"Kothana Halli",
    "wof:placetype":"neighbourhood",
    "wof:population":853
},
  "geometry": {"coordinates":[77.019176,12.623105],"type":"Point"}
}