{
  "type": "Feature",
  "properties": {
    "iso:country":"IN",
    "ks:ks_name":"Mohiuddinpur",
    "ks:ks_pop":376,
    "ks:ks_type":"VILLAGE",
    "ks:ks_uagg_main":0,
    "name:eng_x_preferred":[
        "Mohiuddinpur"
    ],
    "wof:name":"Mohiuddinpur",
    "wof:placetype":"neighbourhood",
    "wof:population":376
},
  "geometry": {"coordinates":[78.24926600000001,29.521774],"type":"Point"}
}