{
  "type": "Feature",
  "properties": {
    "iso:country":"IN",
    "ks:ks_name":"Vishnoiyon Ka Tala",
    "ks:ks_type":"VILLAGE",
    "name:eng_x_preferred":[
        "Vishnoiyon Ka Tala"
    ],
    "wof:name":"Vishnoiyon Ka Tala",
    "wof:placetype":"locality"
},
  "geometry": {"coordinates":[71.18262199999999,25.631044],"type":"Point"}
}