{
  "type": "Feature",
  "properties": {
    "iso:country":"IN",
    "ks:ks_name":"Kotharevellapalem",
    "ks:ks_pop":24,
    "ks:ks_type":"HABITATION",
    "name:eng_x_preferred":[
        "Kotharevellapalem"
    ],
    "wof:name":"Kotharevellapalem",
    "wof:placetype":"locality",
    "wof:population":24
},
  "geometry": {"coordinates":[82.938045,18.033572],"type":"Point"}
}