{
  "type": "Feature",
  "properties": {
    "iso:country":"IN",
    "ks:ks_name":"Marasarakottige",
    "ks:ks_pop":318,
    "ks:ks_type":"HABITATION",
    "name:eng_x_preferred":[
        "Marasarakottige"
    ],
    "wof:name":"Marasarakottige",
    "wof:placetype":"locality",
    "wof:population":318
},
  "geometry": {"coordinates":[76.642287,13.165],"type":"Point"}
}