{
  "type": "Feature",
  "properties": {
    "iso:country":"IN",
    "ks:ks_name":"Rajapalayam Colony",
    "ks:ks_pop":759,
    "ks:ks_type":"HABITATION",
    "name:eng_x_preferred":[
        "Rajapalayam Colony"
    ],
    "wof:name":"Rajapalayam Colony",
    "wof:placetype":"locality",
    "wof:population":759
},
  "geometry": {"coordinates":[79.842657,13.259009],"type":"Point"}
}