{
  "type": "Feature",
  "properties": {
    "gn:admin1_code":"35.0",
    "gn:admin2_code":"436.0",
    "gn:asciiname":"Nimkheri",
    "gn:country_code":"IN",
    "gn:dem":459,
    "gn:feature_class":"P",
    "gn:feature_code":"PPL",
    "gn:name":"N\u012bmkheri",
    "gn:population":0,
    "gn:timezone":"Asia/Kolkata",
    "iso:country":"IN",
    "wof:name":"Nimkheri",
    "wof:placetype":"locality"
},
  "geometry": {"coordinates":[76.62775000000001,23.2489],"type":"Point"}
}