{
  "type": "Feature",
  "properties": {
    "iso:country":"IN",
    "ks:ks_name":"Taraimardih",
    "ks:ks_pop":185,
    "ks:ks_type":"HABITATION",
    "name:eng_x_preferred":[
        "Taraimardih"
    ],
    "wof:name":"Taraimardih",
    "wof:placetype":"locality",
    "wof:population":185
},
  "geometry": {"coordinates":[83.00861,22.362832],"type":"Point"}
}