{
  "type": "Feature",
  "properties": {
    "iso:country":"IN",
    "ks:ks_name":"Suvar Falia",
    "ks:ks_pop":652,
    "ks:ks_type":"HABITATION",
    "name:eng_x_preferred":[
        "Suvar Falia"
    ],
    "wof:name":"Suvar Falia",
    "wof:placetype":"locality",
    "wof:population":652
},
  "geometry": {"coordinates":[74.207139,23.132167],"type":"Point"}
}