{
  "type": "Feature",
  "properties": {
    "gn:admin1_code":"36.0",
    "gn:admin2_code":"185.0",
    "gn:asciiname":"Matia",
    "gn:country_code":"IN",
    "gn:dem":93,
    "gn:feature_class":"P",
    "gn:feature_code":"PPL",
    "gn:name":"Matia",
    "gn:population":0,
    "gn:timezone":"Asia/Kolkata",
    "iso:country":"IN",
    "name:ceb_x_preferred":[
        "Matia"
    ],
    "name:swe_x_preferred":[
        "Matia"
    ],
    "wof:name":"Matia",
    "wof:placetype":"locality"
},
  "geometry": {"coordinates":[82.64749999999999,27.026],"type":"Point"}
}