{
  "type": "Feature",
  "properties": {
    "iso:country":"IN",
    "ks:ks_name":"Chowbatia",
    "ks:ks_pop":245,
    "ks:ks_type":"VILLAGE",
    "name:eng_x_preferred":[
        "Chowbatia"
    ],
    "wof:name":"Chowbatia",
    "wof:placetype":"locality",
    "wof:population":245
},
  "geometry": {"coordinates":[87.443613,21.779714],"type":"Point"}
}