{
  "type": "Feature",
  "properties": {
    "iso:country":"IN",
    "ks:ks_name":"Pottidibba",
    "ks:ks_pop":282,
    "ks:ks_type":"HABITATION",
    "name:eng_x_preferred":[
        "Pottidibba"
    ],
    "wof:name":"Pottidibba",
    "wof:placetype":"locality",
    "wof:population":282
},
  "geometry": {"coordinates":[80.791296,16.297311],"type":"Point"}
}