{
  "type": "Feature",
  "properties": {
    "iso:country":"IN",
    "ks:ks_name":"Harbiichha.",
    "ks:ks_pop":878,
    "ks:ks_type":"HABITATION",
    "ks:ks_uagg_main":0,
    "name:eng_x_preferred":[
        "Harbiichha."
    ],
    "wof:name":"Harbiichha.",
    "wof:placetype":"neighbourhood",
    "wof:population":878
},
  "geometry": {"coordinates":[86.59400100000001,25.725334],"type":"Point"}
}