{
  "type": "Feature",
  "properties": {
    "gn:admin1_code":"35",
    "gn:admin2_code":"448.0",
    "gn:asciiname":"Dudhkach Khurd",
    "gn:country_code":"IN",
    "gn:dem":291,
    "gn:feature_class":"P",
    "gn:feature_code":"PPL",
    "gn:name":"Dudhkach Khurd",
    "gn:population":0,
    "gn:timezone":"Asia/Kolkata",
    "iso:country":"IN",
    "ks:ks_name":"Dudhakatch Khurd",
    "ks:ks_pop":152,
    "ks:ks_type":"VILLAGE",
    "name:eng_x_preferred":[
        "Dudhakatch Khurd"
    ],
    "name:eng_x_variant":[
        "Dudhkach Khurd"
    ],
    "wof:name":"Dudhakatch Khurd",
    "wof:placetype":"locality",
    "wof:population":152
},
  "geometry": {"coordinates":[77.112173,22.330366],"type":"Point"}
}