{
  "type": "Feature",
  "properties": {
    "gn:admin1_code":"39.0",
    "gn:admin2_code":"64.0",
    "gn:asciiname":"Gudkade",
    "gn:country_code":"IN",
    "gn:dem":1218,
    "gn:feature_class":"P",
    "gn:feature_code":"PPL",
    "gn:name":"Gudk\u0101de",
    "gn:population":0,
    "gn:timezone":"Asia/Kolkata",
    "iso:country":"IN",
    "wof:name":"Gudkade",
    "wof:placetype":"locality"
},
  "geometry": {"coordinates":[79.6387,29.66836],"type":"Point"}
}