{
  "type": "Feature",
  "properties": {
    "gn:admin1_code":"19.0",
    "gn:admin2_code":"565.0",
    "gn:asciiname":"Mariyammanahalli",
    "gn:country_code":"IN",
    "gn:dem":524,
    "gn:feature_class":"P",
    "gn:feature_code":"PPL",
    "gn:name":"Mariyammanahalli",
    "gn:population":0,
    "gn:timezone":"Asia/Kolkata",
    "iso:country":"IN",
    "name:kan_x_preferred":[
        "\u0cae\u0cb0\u0cbf\u0caf\u0cae\u0ccd\u0cae\u0ca8\u0cb9\u0cb3\u0ccd\u0cb3\u0cbf"
    ],
    "wof:name":"Mariyammanahalli",
    "wof:placetype":"locality"
},
  "geometry": {"coordinates":[76.35648,15.15939],"type":"Point"}
}