{
  "type": "Feature",
  "properties": {
    "gn:admin1_code":"36",
    "gn:admin2_code":"199.0",
    "gn:asciiname":"Kurkuthia Pande",
    "gn:country_code":"IN",
    "gn:dem":87,
    "gn:feature_class":"P",
    "gn:feature_code":"PPL",
    "gn:name":"Kurkuthia P\u0101nde",
    "gn:population":0,
    "gn:timezone":"Asia/Kolkata",
    "iso:country":"IN",
    "ks:ks_name":"Kurkuthiya Pandey",
    "ks:ks_pop":1776,
    "ks:ks_type":"VILLAGE",
    "ks:ks_uagg_main":0,
    "name:eng_x_preferred":[
        "Kurkuthiya Pandey"
    ],
    "name:und_x_variant":[
        "Kurkuthia P\u0101nde",
        "Belwaria"
    ],
    "wof:name":"Kurkuthiya Pandey",
    "wof:placetype":"neighbourhood",
    "wof:population":1776
},
  "geometry": {"coordinates":[82.63945099999999,25.170131],"type":"Point"}
}