{
  "type": "Feature",
  "properties": {
    "iso:country":"IN",
    "ks:ks_name":"Vidyagiri",
    "ks:ks_pop":321,
    "ks:ks_type":"HABITATION",
    "name:eng_x_preferred":[
        "Vidyagiri"
    ],
    "wof:name":"Vidyagiri",
    "wof:placetype":"locality",
    "wof:population":321
},
  "geometry": {"coordinates":[75.090143,12.599604],"type":"Point"}
}