{
  "type": "Feature",
  "properties": {
    "iso:country":"IN",
    "ks:ks_alt_nam":"Guttameedi gudicelu",
    "ks:ks_name":"Guttameedi Gudicelu",
    "ks:ks_pop":84,
    "ks:ks_type":"HABITATION",
    "name:eng_x_preferred":[
        "Guttameedi Gudicelu"
    ],
    "wof:name":"Guttameedi Gudicelu",
    "wof:placetype":"locality",
    "wof:population":84
},
  "geometry": {"coordinates":[77.922203,16.991514],"type":"Point"}
}