{
  "type": "Feature",
  "properties": {
    "iso:country":"IN",
    "ks:ks_name":"Nilavagilu",
    "ks:ks_pop":1392,
    "ks:ks_type":"VILLAGE",
    "name:eng_x_preferred":[
        "Nilavagilu"
    ],
    "wof:name":"Nilavagilu",
    "wof:placetype":"locality",
    "wof:population":1392
},
  "geometry": {"coordinates":[75.26862199999999,13.521421],"type":"Point"}
}