{
  "type": "Feature",
  "properties": {
    "gn:admin1_code":"19.0",
    "gn:admin2_code":"560.0",
    "gn:asciiname":"Lakshmapura",
    "gn:country_code":"IN",
    "gn:dem":552,
    "gn:feature_class":"P",
    "gn:feature_code":"PPL",
    "gn:name":"Lakshm\u0101pura",
    "gn:population":0,
    "gn:timezone":"Asia/Kolkata",
    "iso:country":"IN",
    "wof:name":"Lakshmapura",
    "wof:placetype":"neighbourhood"
},
  "geometry": {"coordinates":[76.04331999999999,15.36757],"type":"Point"}
}