{
  "type": "Feature",
  "properties": {
    "iso:country":"IN",
    "ks:ks_name":"Bhavani Nagar Tanda",
    "ks:ks_pop":223,
    "ks:ks_type":"HABITATION",
    "name:eng_x_preferred":[
        "Bhavani Nagar Tanda"
    ],
    "wof:name":"Bhavani Nagar Tanda",
    "wof:placetype":"locality",
    "wof:population":223
},
  "geometry": {"coordinates":[77.232592,18.520905],"type":"Point"}
}