{
  "type": "Feature",
  "properties": {
    "iso:country":"IN",
    "ks:ks_name":"Shampur",
    "ks:ks_pop":51,
    "ks:ks_type":"VILLAGE",
    "name:eng_x_preferred":[
        "Shampur"
    ],
    "wof:name":"Shampur",
    "wof:placetype":"locality",
    "wof:population":51
},
  "geometry": {"coordinates":[86.562442,25.206555],"type":"Point"}
}