{
  "type": "Feature",
  "properties": {
    "iso:country":"IN",
    "ks:ks_name":"Donelapalli",
    "ks:ks_pop":203,
    "ks:ks_type":"HABITATION",
    "name:eng_x_preferred":[
        "Donelapalli"
    ],
    "wof:name":"Donelapalli",
    "wof:placetype":"locality",
    "wof:population":203
},
  "geometry": {"coordinates":[81.972156,17.347271],"type":"Point"}
}