{
  "type": "Feature",
  "properties": {
    "iso:country":"IN",
    "ks:ks_name":"Rajupeta",
    "ks:ks_pop":138,
    "ks:ks_type":"VILLAGE",
    "name:eng_x_preferred":[
        "Rajupeta"
    ],
    "wof:name":"Rajupeta",
    "wof:placetype":"locality",
    "wof:population":138
},
  "geometry": {"coordinates":[80.966909,17.827329],"type":"Point"}
}