{
  "type": "Feature",
  "properties": {
    "gn:admin1_code":"13.0",
    "gn:admin2_code":"591",
    "gn:asciiname":"Kakkayam",
    "gn:country_code":"IN",
    "gn:dem":8,
    "gn:feature_class":"P",
    "gn:feature_code":"PPL",
    "gn:name":"Kakkayam",
    "gn:population":0,
    "gn:timezone":"Asia/Kolkata",
    "iso:country":"IN",
    "wof:name":"Kakkayam",
    "wof:placetype":"neighbourhood"
},
  "geometry": {"coordinates":[75.83333,11.25],"type":"Point"}
}