{
  "type": "Feature",
  "properties": {
    "gn:admin1_code":"16",
    "gn:admin2_code":"513.0",
    "gn:asciiname":"Debechwadi",
    "gn:country_code":"IN",
    "gn:dem":500,
    "gn:feature_class":"P",
    "gn:feature_code":"PPL",
    "gn:name":"Debechw\u0101di",
    "gn:population":0,
    "gn:timezone":"Asia/Kolkata",
    "iso:country":"IN",
    "wof:name":"Debechwadi",
    "wof:placetype":"locality"
},
  "geometry": {"coordinates":[76.65505999999998,18.85337],"type":"Point"}
}