{
  "type": "Feature",
  "properties": {
    "gn:admin1_code":"12.0",
    "gn:admin2_code":"18.0",
    "gn:asciiname":"Homul",
    "gn:country_code":"IN",
    "gn:dem":3144,
    "gn:feature_class":"P",
    "gn:feature_code":"PPL",
    "gn:name":"H\u014dmul",
    "gn:population":0,
    "gn:timezone":"Asia/Kolkata",
    "iso:country":"IN",
    "wof:name":"Homul",
    "wof:placetype":"locality"
},
  "geometry": {"coordinates":[75.78326,33.61214],"type":"Point"}
}