{
  "type": "Feature",
  "properties": {
    "gn:admin1_code":"37",
    "gn:admin2_code":"410.0",
    "gn:asciiname":"Kumhari",
    "gn:country_code":"IN",
    "gn:dem":254,
    "gn:feature_class":"P",
    "gn:feature_code":"PPL",
    "gn:name":"Kumh\u0101ri",
    "gn:population":0,
    "gn:timezone":"Asia/Kolkata",
    "iso:country":"IN",
    "name:ben_x_preferred":[
        "\u0995\u09c1\u09ae\u09b9\u09be\u09b0\u09bf"
    ],
    "name:bpy_x_preferred":[
        "\u0995\u09c1\u09ae\u09b9\u09be\u09b0\u09bf"
    ],
    "name:ceb_x_preferred":[
        "Kumh\u0101ri"
    ],
    "name:ita_x_preferred":[
        "Kumhari"
    ],
    "name:msa_x_preferred":[
        "Kumhari"
    ],
    "name:new_x_preferred":[
        "\u0915\u0941\u092e\u094d\u0939\u0930\u0940"
    ],
    "name:nld_x_preferred":[
        "Kumhari"
    ],
    "name:por_x_preferred":[
        "Kumhari"
    ],
    "name:spa_x_preferred":[
        "Kumhari"
    ],
    "name:swe_x_preferred":[
        "Kumh\u0101ri"
    ],
    "name:urd_x_preferred":[
        "\u06a9\u0645\u06c1\u0627\u0631\u06cc"
    ],
    "name:vie_x_preferred":[
        "Kumhari"
    ],
    "name:zho_x_preferred":[
        "\u5e93\u59c6\u54c8\u91cc"
    ],
    "wof:name":"Kumhari",
    "wof:placetype":"locality"
},
  "geometry": {"coordinates":[82.31376999999998,21.59339],"type":"Point"}
}