{
  "type": "Feature",
  "properties": {
    "gn:admin1_code":"36",
    "gn:admin2_code":"200.0",
    "gn:asciiname":"Sagardah",
    "gn:country_code":"IN",
    "gn:dem":319,
    "gn:feature_class":"P",
    "gn:feature_code":"PPL",
    "gn:name":"S\u0101gardah",
    "gn:population":0,
    "gn:timezone":"Asia/Kolkata",
    "iso:country":"IN",
    "ks:ks_name":"Sogardah",
    "ks:ks_pop":723,
    "ks:ks_type":"HABITATION",
    "name:eng_x_preferred":[
        "Sogardah"
    ],
    "name:eng_x_variant":[
        "Sagardah"
    ],
    "wof:name":"Sogardah",
    "wof:placetype":"locality",
    "wof:population":723
},
  "geometry": {"coordinates":[82.802454,24.346265],"type":"Point"}
}