{
  "type": "Feature",
  "properties": {
    "iso:country":"IN",
    "ks:ks_name":"Bhilla Patti.",
    "ks:ks_pop":279,
    "ks:ks_type":"HABITATION",
    "name:eng_x_preferred":[
        "Bhilla Patti."
    ],
    "wof:name":"Bhilla Patti.",
    "wof:placetype":"locality",
    "wof:population":279
},
  "geometry": {"coordinates":[86.792058,25.844817],"type":"Point"}
}