{
  "type": "Feature",
  "properties": {
    "gn:admin1_code":"36",
    "gn:admin2_code":"144.0",
    "gn:asciiname":"Khariya",
    "gn:country_code":"IN",
    "gn:dem":178,
    "gn:feature_class":"P",
    "gn:feature_code":"PPL",
    "gn:name":"Khariya",
    "gn:population":0,
    "gn:timezone":"Asia/Kolkata",
    "iso:country":"IN",
    "name:bpy_x_preferred":[
        "\u0996\u09be\u09b0\u09bf\u09af\u09bc\u09be"
    ],
    "name:ita_x_preferred":[
        "Khariya"
    ],
    "name:msa_x_preferred":[
        "Khariya"
    ],
    "name:new_x_preferred":[
        "\u0916\u0930\u093f\u092f\u093e"
    ],
    "name:nld_x_preferred":[
        "Khariya"
    ],
    "name:pol_x_preferred":[
        "Khariya"
    ],
    "name:por_x_preferred":[
        "Khariya"
    ],
    "name:urd_x_preferred":[
        "\u06a9\u06be\u06cc\u0631\u06cc\u0627"
    ],
    "name:vie_x_preferred":[
        "Khariya"
    ],
    "name:zho_x_preferred":[
        "\u5361\u91cc\u8036"
    ],
    "wof:name":"Khariya",
    "wof:placetype":"neighbourhood"
},
  "geometry": {"coordinates":[78.46993000000001,27.75256],"type":"Point"}
}