{
  "type": "Feature",
  "properties": {
    "iso:country":"IN",
    "ks:ks_alt_nam":"R\u0101mpura",
    "ks:ks_name":"Rampura",
    "ks:ks_type":"VILLAGE",
    "ks:ks_uagg_main":0,
    "name:eng_x_preferred":[
        "Rampura"
    ],
    "name:eng_x_variant":[
        "R\u0101mpura"
    ],
    "wof:name":"Rampura",
    "wof:placetype":"neighbourhood"
},
  "geometry": {"coordinates":[74.231514,26.031646],"type":"Point"}
}