{
  "type": "Feature",
  "properties": {
    "iso:country":"IN",
    "ks:ks_name":"Theeyur",
    "ks:ks_pop":85,
    "ks:ks_type":"HABITATION",
    "name:eng_x_preferred":[
        "Theeyur"
    ],
    "wof:name":"Theeyur",
    "wof:placetype":"locality",
    "wof:population":85
},
  "geometry": {"coordinates":[79.03167500000001,9.955385],"type":"Point"}
}