{
  "type": "Feature",
  "properties": {
    "gn:admin1_code":"36.0",
    "gn:admin2_code":"194.0",
    "gn:asciiname":"Dilshadpur",
    "gn:country_code":"IN",
    "gn:dem":88,
    "gn:feature_class":"P",
    "gn:feature_code":"PPL",
    "gn:name":"Dilsh\u0101dpur",
    "gn:population":0,
    "gn:timezone":"Asia/Kolkata",
    "iso:country":"IN",
    "name:und_x_variant":[
        "Dilsh\u0101dpur",
        "Teji B\u0101z\u0101r"
    ],
    "wof:name":"Dilshadpur",
    "wof:placetype":"locality"
},
  "geometry": {"coordinates":[82.43989999999999,25.82142],"type":"Point"}
}