{
  "type": "Feature",
  "properties": {
    "iso:country":"IN",
    "ks:ks_name":"Ravapara",
    "ks:ks_pop":1223,
    "ks:ks_type":"HABITATION",
    "name:eng_x_preferred":[
        "Ravapara"
    ],
    "wof:name":"Ravapara",
    "wof:placetype":"locality",
    "wof:population":1223
},
  "geometry": {"coordinates":[90.562764,26.649737],"type":"Point"}
}