{
  "type": "Feature",
  "properties": {
    "iso:country":"IN",
    "ks:ks_name":"Mandir Fa",
    "ks:ks_pop":153,
    "ks:ks_type":"HABITATION",
    "ks:ks_uagg_main":0,
    "name:eng_x_preferred":[
        "Mandir Fa"
    ],
    "wof:name":"Mandir Fa",
    "wof:placetype":"neighbourhood",
    "wof:population":153
},
  "geometry": {"coordinates":[73.01044400000001,20.455361],"type":"Point"}
}