{
  "type": "Feature",
  "properties": {
    "iso:country":"IN",
    "ks:ks_alt_nam":"Nivai wadi",
    "ks:ks_name":"Nivai Wadi",
    "ks:ks_pop":82,
    "ks:ks_type":"HABITATION",
    "name:eng_x_preferred":[
        "Nivai Wadi"
    ],
    "wof:name":"Nivai Wadi",
    "wof:placetype":"locality",
    "wof:population":82
},
  "geometry": {"coordinates":[73.381289,17.176061],"type":"Point"}
}