{
  "type": "Feature",
  "properties": {
    "gn:admin1_code":"36.0",
    "gn:admin2_code":"133.0",
    "gn:asciiname":"Tandhera",
    "gn:country_code":"IN",
    "gn:dem":244,
    "gn:feature_class":"P",
    "gn:feature_code":"PPL",
    "gn:name":"Tandhera",
    "gn:population":0,
    "gn:timezone":"Asia/Kolkata",
    "iso:country":"IN",
    "wof:name":"Tandhera",
    "wof:placetype":"locality"
},
  "geometry": {"coordinates":[77.93796999999998,29.37016],"type":"Point"}
}