{
  "type": "Feature",
  "properties": {
    "iso:country":"IN",
    "ks:ks_name":"Sallevar",
    "ks:ks_pop":279,
    "ks:ks_type":"HABITATION",
    "name:eng_x_preferred":[
        "Sallevar"
    ],
    "wof:name":"Sallevar",
    "wof:placetype":"locality",
    "wof:population":279
},
  "geometry": {"coordinates":[74.476983,14.378716],"type":"Point"}
}