{
  "type": "Feature",
  "properties": {
    "gn:admin1_code":"34.0",
    "gn:admin2_code":"235.0",
    "gn:asciiname":"Kauriari",
    "gn:country_code":"IN",
    "gn:dem":152,
    "gn:feature_class":"P",
    "gn:feature_code":"PPL",
    "gn:name":"Kaur\u012b\u0101r\u012b",
    "gn:population":0,
    "gn:timezone":"Asia/Kolkata",
    "iso:country":"IN",
    "ks:ks_alt_nam":"Kaur\u012b\u0101r\u012b",
    "ks:ks_name":"Kauriari",
    "ks:ks_pop":973,
    "ks:ks_type":"VILLAGE",
    "ks:ks_uagg_main":0,
    "name:eng_x_preferred":[
        "Kauriari"
    ],
    "name:eng_x_variant":[
        "Kaur\u012b\u0101r\u012b"
    ],
    "wof:name":"Kauriari",
    "wof:placetype":"neighbourhood",
    "wof:population":973
},
  "geometry": {"coordinates":[84.379497,24.586028],"type":"Point"}
}