{
  "type": "Feature",
  "properties": {
    "iso:country":"IN",
    "ks:ks_name":"Mata Falia",
    "ks:ks_pop":180,
    "ks:ks_type":"HABITATION",
    "name:eng_x_preferred":[
        "Mata Falia"
    ],
    "wof:name":"Mata Falia",
    "wof:placetype":"locality",
    "wof:population":180
},
  "geometry": {"coordinates":[73.386861,20.792167],"type":"Point"}
}