{
  "type": "Feature",
  "properties": {
    "iso:country":"IN",
    "ks:ks_name":"Chhoti Marhi",
    "ks:ks_pop":1169,
    "ks:ks_type":"HABITATION",
    "ks:ks_uagg_main":0,
    "name:eng_x_preferred":[
        "Chhoti Marhi"
    ],
    "wof:name":"Chhoti Marhi",
    "wof:placetype":"neighbourhood",
    "wof:population":1169
},
  "geometry": {"coordinates":[83.041275,25.606916],"type":"Point"}
}