{
  "type": "Feature",
  "properties": {
    "iso:country":"IN",
    "ks:ks_name":"Raitla",
    "ks:ks_pop":190,
    "ks:ks_type":"HABITATION",
    "ks:ks_uagg_main":0,
    "name:eng_x_preferred":[
        "Raitla"
    ],
    "wof:name":"Raitla",
    "wof:placetype":"neighbourhood",
    "wof:population":190
},
  "geometry": {"coordinates":[80.933801,27.222385],"type":"Point"}
}