{
  "type": "Feature",
  "properties": {
    "iso:country":"IN",
    "ks:ks_name":"Mohanpur Pt IV",
    "ks:ks_pop":1172,
    "ks:ks_type":"VILLAGE",
    "name:eng_x_preferred":[
        "Mohanpur Pt IV"
    ],
    "wof:name":"Mohanpur Pt IV",
    "wof:placetype":"locality",
    "wof:population":1172
},
  "geometry": {"coordinates":[92.63997000000001,24.769949],"type":"Point"}
}