{
  "type": "Feature",
  "properties": {
    "iso:country":"IN",
    "ks:ks_name":"Patil Vasahat",
    "ks:ks_pop":130,
    "ks:ks_type":"HABITATION",
    "name:eng_x_preferred":[
        "Patil Vasahat"
    ],
    "wof:name":"Patil Vasahat",
    "wof:placetype":"locality",
    "wof:population":130
},
  "geometry": {"coordinates":[74.437067,16.219526],"type":"Point"}
}