{
  "type": "Feature",
  "properties": {
    "iso:country":"IN",
    "ks:ks_name":"Mukhi Falia",
    "ks:ks_pop":181,
    "ks:ks_type":"HABITATION",
    "name:eng_x_preferred":[
        "Mukhi Falia"
    ],
    "wof:name":"Mukhi Falia",
    "wof:placetype":"locality",
    "wof:population":181
},
  "geometry": {"coordinates":[73.38161100000001,23.466722],"type":"Point"}
}