{
  "type": "Feature",
  "properties": {
    "iso:country":"IN",
    "ks:ks_name":"Madandi",
    "ks:ks_pop":228,
    "ks:ks_type":"VILLAGE",
    "ks:ks_uagg_main":0,
    "name:eng_x_preferred":[
        "Madandi"
    ],
    "wof:name":"Madandi",
    "wof:placetype":"neighbourhood",
    "wof:population":228
},
  "geometry": {"coordinates":[86.70587999999999,23.794359],"type":"Point"}
}