{
  "type": "Feature",
  "properties": {
    "iso:country":"IN",
    "ks:ks_alt_nam":"Dakhingaon FV",
    "ks:ks_name":"Dakhingaon Fv",
    "ks:ks_pop":1452,
    "ks:ks_type":"HABITATION",
    "name:eng_x_preferred":[
        "Dakhingaon Fv"
    ],
    "wof:name":"Dakhingaon Fv",
    "wof:placetype":"locality",
    "wof:population":1452
},
  "geometry": {"coordinates":[90.394408,26.723348],"type":"Point"}
}