{
  "type": "Feature",
  "properties": {
    "gn:admin1_code":"21.0",
    "gn:admin2_code":"397.0",
    "gn:asciiname":"Baragam",
    "gn:country_code":"IN",
    "gn:dem":661,
    "gn:feature_class":"P",
    "gn:feature_code":"PPL",
    "gn:name":"Barag\u0101m",
    "gn:population":0,
    "gn:timezone":"Asia/Kolkata",
    "iso:country":"IN",
    "wof:name":"Baragam",
    "wof:placetype":"neighbourhood"
},
  "geometry": {"coordinates":[81.95716,19.94263],"type":"Point"}
}