{
  "type": "Feature",
  "properties": {
    "gn:admin1_code":"2.0",
    "gn:admin2_code":"543.0",
    "gn:asciiname":"Jammunarayanapuram",
    "gn:country_code":"IN",
    "gn:dem":51,
    "gn:feature_class":"P",
    "gn:feature_code":"PPL",
    "gn:name":"Jammun\u0101r\u0101yanapuram",
    "gn:population":0,
    "gn:timezone":"Asia/Kolkata",
    "iso:country":"IN",
    "wof:name":"Jammunarayanapuram",
    "wof:placetype":"neighbourhood"
},
  "geometry": {"coordinates":[83.43308,18.09363],"type":"Point"}
}