{
  "type": "Feature",
  "properties": {
    "iso:country":"IN",
    "ks:ks_name":"Pinaravalli",
    "ks:ks_pop":61,
    "ks:ks_type":"HABITATION",
    "name:eng_x_preferred":[
        "Pinaravalli"
    ],
    "wof:name":"Pinaravalli",
    "wof:placetype":"locality",
    "wof:population":61
},
  "geometry": {"coordinates":[82.357511,18.221642],"type":"Point"}
}