{
  "type": "Feature",
  "properties": {
    "iso:country":"IN",
    "ks:ks_name":"Shivajipeth",
    "ks:ks_pop":382,
    "ks:ks_type":"HABITATION",
    "name:eng_x_preferred":[
        "Shivajipeth"
    ],
    "wof:name":"Shivajipeth",
    "wof:placetype":"locality",
    "wof:population":382
},
  "geometry": {"coordinates":[73.621075,16.55682],"type":"Point"}
}