{
  "type": "Feature",
  "properties": {
    "gn:admin1_code":"21.0",
    "gn:admin2_code":"398.0",
    "gn:asciiname":"Chittalaputtu",
    "gn:country_code":"IN",
    "gn:dem":904,
    "gn:feature_class":"P",
    "gn:feature_code":"PPL",
    "gn:name":"Chittalaputtu",
    "gn:population":0,
    "gn:timezone":"Asia/Kolkata",
    "iso:country":"IN",
    "wof:name":"Chittalaputtu",
    "wof:placetype":"locality"
},
  "geometry": {"coordinates":[82.72596999999998,18.54243],"type":"Point"}
}