{
  "type": "Feature",
  "properties": {
    "gn:admin1_code":"2.0",
    "gn:admin2_code":"554.0",
    "gn:asciiname":"Ramapuram",
    "gn:country_code":"IN",
    "gn:dem":663,
    "gn:feature_class":"P",
    "gn:feature_code":"PPL",
    "gn:name":"R\u0101mapuram",
    "gn:population":0,
    "gn:timezone":"Asia/Kolkata",
    "iso:country":"IN",
    "name:ceb_x_preferred":[
        "Ramapuram"
    ],
    "name:ita_x_preferred":[
        "Ramapuram"
    ],
    "name:mal_x_preferred":[
        "\u0d30\u0d3e\u0d2e\u0d2a\u0d41\u0d30\u0d02"
    ],
    "name:swe_x_preferred":[
        "Ramapuram"
    ],
    "wof:name":"Ramapuram",
    "wof:placetype":"locality"
},
  "geometry": {"coordinates":[78.71051,13.19025],"type":"Point"}
}