{
  "type": "Feature",
  "properties": {
    "iso:country":"IN",
    "ks:ks_name":"Sukhnaiyapara",
    "ks:ks_pop":136,
    "ks:ks_type":"HABITATION",
    "name:eng_x_preferred":[
        "Sukhnaiyapara"
    ],
    "wof:name":"Sukhnaiyapara",
    "wof:placetype":"locality",
    "wof:population":136
},
  "geometry": {"coordinates":[82.94795999999999,23.44613],"type":"Point"}
}