{
  "type": "Feature",
  "properties": {
    "iso:country":"IN",
    "ks:ks_name":"Shemdemane",
    "ks:ks_pop":52,
    "ks:ks_type":"HABITATION",
    "name:eng_x_preferred":[
        "Shemdemane"
    ],
    "wof:name":"Shemdemane",
    "wof:placetype":"locality",
    "wof:population":52
},
  "geometry": {"coordinates":[74.544774,14.912722],"type":"Point"}
}