{
  "type": "Feature",
  "properties": {
    "iso:country":"IN",
    "ks:ks_alt_nam":"chouthaiwadi",
    "ks:ks_name":"Chouthaiwadi",
    "ks:ks_pop":46,
    "ks:ks_type":"HABITATION",
    "ks:ks_uagg_main":0,
    "name:eng_x_preferred":[
        "Chouthaiwadi"
    ],
    "wof:name":"Chouthaiwadi",
    "wof:placetype":"neighbourhood",
    "wof:population":46
},
  "geometry": {"coordinates":[73.474969,17.526614],"type":"Point"}
}