{
  "type": "Feature",
  "properties": {
    "iso:country":"IN",
    "ks:ks_name":"Puringiri",
    "ks:ks_pop":20,
    "ks:ks_type":"HABITATION",
    "name:eng_x_preferred":[
        "Puringiri"
    ],
    "wof:name":"Puringiri",
    "wof:placetype":"locality",
    "wof:population":20
},
  "geometry": {"coordinates":[75.105519,13.010538],"type":"Point"}
}