{
  "type": "Feature",
  "properties": {
    "iso:country":"IN",
    "ks:ks_name":"Pratappur",
    "ks:ks_pop":1718,
    "ks:ks_type":"VILLAGE",
    "name:eng_x_preferred":[
        "Pratappur"
    ],
    "wof:name":"Pratappur",
    "wof:placetype":"locality",
    "wof:population":1718
},
  "geometry": {"coordinates":[80.238889,26.435556],"type":"Point"}
}