{
  "type": "Feature",
  "properties": {
    "iso:country":"IN",
    "ks:ks_name":"Bardhora",
    "ks:ks_pop":200,
    "ks:ks_type":"HABITATION",
    "name:eng_x_preferred":[
        "Bardhora"
    ],
    "wof:name":"Bardhora",
    "wof:placetype":"locality",
    "wof:population":200
},
  "geometry": {"coordinates":[85.002624,23.553331],"type":"Point"}
}