{
  "type": "Feature",
  "properties": {
    "iso:country":"IN",
    "ks:ks_name":"Paradipallam",
    "ks:ks_pop":589,
    "ks:ks_type":"HABITATION",
    "name:eng_x_preferred":[
        "Paradipallam"
    ],
    "wof:name":"Paradipallam",
    "wof:placetype":"locality",
    "wof:population":589
},
  "geometry": {"coordinates":[77.197627,10.235316],"type":"Point"}
}