{
  "type": "Feature",
  "properties": {
    "gn:admin1_code":"11.0",
    "gn:admin2_code":"033",
    "gn:asciiname":"Panihana",
    "gn:country_code":"IN",
    "gn:dem":984,
    "gn:feature_class":"P",
    "gn:feature_code":"PPL",
    "gn:name":"Pan\u012bh\u0101na",
    "gn:population":0,
    "gn:timezone":"Asia/Kolkata",
    "iso:country":"IN",
    "name:und_x_variant":[
        "Pan\u012bh\u0101na",
        "Panhy\u0101na"
    ],
    "wof:name":"Panihana",
    "wof:placetype":"locality"
},
  "geometry": {"coordinates":[77.05079000000001,31.20988],"type":"Point"}
}