{
  "type": "Feature",
  "properties": {
    "gn:admin1_code":"10.0",
    "gn:admin2_code":"71.0",
    "gn:asciiname":"Shahjahanpur",
    "gn:country_code":"IN",
    "gn:dem":289,
    "gn:feature_class":"P",
    "gn:feature_code":"PPL",
    "gn:name":"Sh\u0101hjah\u0101npur",
    "gn:population":0,
    "gn:timezone":"Asia/Kolkata",
    "iso:country":"IN",
    "name:azb_x_preferred":[
        "\u0634\u0627\u0647\u200c\u062c\u0647\u0627\u0646\u200c\u067e\u0648\u0631"
    ],
    "name:bih_x_preferred":[
        "\u0936\u093e\u0939\u091c\u0939\u093e\u0901\u092a\u0941\u0930"
    ],
    "name:bpy_x_preferred":[
        "\u09b6\u09be\u09b9\u099c\u09be\u09b9\u09be\u09a8\u09aa\u09c1\u09b0"
    ],
    "name:cat_x_preferred":[
        "Shahjahanpur"
    ],
    "name:ceb_x_preferred":[
        "Sh\u0101hjah\u0101npur"
    ],
    "name:deu_x_preferred":[
        "Shahjahanpur"
    ],
    "name:fas_x_preferred":[
        "\u0634\u0627\u0647\u200c\u062c\u0647\u0627\u0646\u200c\u067e\u0648\u0631"
    ],
    "name:fra_x_preferred":[
        "Shahjahanpur"
    ],
    "name:guj_x_preferred":[
        "\u0ab6\u0abe\u0ab9\u0a9c\u0ab9\u0abe\u0a82\u0aaa\u0ac1\u0ab0"
    ],
    "name:hin_x_preferred":[
        "\u0936\u093e\u0939\u091c\u0939\u093e\u0901\u092a\u0941\u0930"
    ],
    "name:ita_x_preferred":[
        "Shahjahanpur"
    ],
    "name:jpn_x_preferred":[
        "\u30b7\u30e3\u30fc\u30b8\u30e3\u30cf\u30fc\u30f3\u30d7\u30eb"
    ],
    "name:mlg_x_preferred":[
        "Shahjahanpur"
    ],
    "name:msa_x_preferred":[
        "Pangkalan Shahjahanpur"
    ],
    "name:nld_x_preferred":[
        "Shahjahanpur"
    ],
    "name:ori_x_preferred":[
        "\u0b36\u0b39\u0b3e\u0b1c\u0b3e\u0b39\u0b3e\u0b28\u0b2a\u0b41\u0b30"
    ],
    "name:pol_x_preferred":[
        "Shahjahanpur"
    ],
    "name:rus_x_preferred":[
        "\u0428\u0430\u0445\u0434\u0436\u0430\u0445\u0430\u043d\u043f\u0443\u0440"
    ],
    "name:san_x_preferred":[
        "\u0936\u093e\u0939\u091c\u0939\u093e\u0928\u092a\u0941\u0930\u092e\u094d"
    ],
    "name:srp_x_preferred":[
        "\u0428\u0430\u0445\u045f\u0430\u0445\u0430\u043d\u043f\u0443\u0440"
    ],
    "name:swe_x_preferred":[
        "Shahjahanpur"
    ],
    "name:urd_x_preferred":[
        "\u0634\u0627\u06c1\u062c\u06c1\u0627\u06ba \u067e\u0648\u0631"
    ],
    "name:vie_x_preferred":[
        "Shahjahanpur"
    ],
    "name:war_x_preferred":[
        "Shahjahanpur"
    ],
    "name:zho_x_preferred":[
        "\u65af\u54c8\u8d6b\u8d3e\u6c49\u666e\u5c14"
    ],
    "wof:name":"Shahjahanpur",
    "wof:placetype":"locality"
},
  "geometry": {"coordinates":[77.42858000000003,30.24619],"type":"Point"}
}