{
  "type": "Feature",
  "properties": {
    "gn:admin1_code":"10.0",
    "gn:admin2_code":"71.0",
    "gn:asciiname":"Shahjahanpur",
    "gn:country_code":"IN",
    "gn:dem":289,
    "gn:feature_class":"P",
    "gn:feature_code":"PPL",
    "gn:name":"Sh\u0101hjah\u0101npur",
    "gn:population":0,
    "gn:timezone":"Asia/Kolkata",
    "iso:country":"IN",
    "wof:name":"Shahjahanpur",
    "wof:placetype":"locality"
},
  "geometry": {"coordinates":[77.42858000000003,30.24619],"type":"Point"}
}