{
  "type": "Feature",
  "properties": {
    "iso:country":"IN",
    "ks:ks_name":"Bhawaniyapur",
    "ks:ks_pop":380,
    "ks:ks_type":"HABITATION",
    "name:eng_x_preferred":[
        "Bhawaniyapur"
    ],
    "wof:name":"Bhawaniyapur",
    "wof:placetype":"locality",
    "wof:population":380
},
  "geometry": {"coordinates":[83.188832,27.2257],"type":"Point"}
}