{
  "type": "Feature",
  "properties": {
    "iso:country":"IN",
    "ks:ks_name":"Dauniapalli",
    "ks:ks_pop":0,
    "ks:ks_type":"VILLAGE",
    "name:eng_x_preferred":[
        "Dauniapalli"
    ],
    "wof:name":"Dauniapalli",
    "wof:placetype":"locality",
    "wof:population":0
},
  "geometry": {"coordinates":[85.240747,20.161843],"type":"Point"}
}