{
  "type": "Feature",
  "properties": {
    "iso:country":"IN",
    "ks:ks_name":"Maheemapur",
    "ks:ks_pop":332,
    "ks:ks_type":"VILLAGE",
    "name:eng_x_preferred":[
        "Maheemapur"
    ],
    "wof:name":"Maheemapur",
    "wof:placetype":"locality",
    "wof:population":332
},
  "geometry": {"coordinates":[85.474732,26.413751],"type":"Point"}
}