{
  "type": "Feature",
  "properties": {
    "iso:country":"IN",
    "ks:ks_name":"Puthoor",
    "ks:ks_pop":200,
    "ks:ks_type":"HABITATION",
    "name:eng_x_preferred":[
        "Puthoor"
    ],
    "wof:name":"Puthoor",
    "wof:placetype":"locality",
    "wof:population":200
},
  "geometry": {"coordinates":[75.923395,11.790979],"type":"Point"}
}