{
  "type": "Feature",
  "properties": {
    "iso:country":"IN",
    "ks:ks_name":"Bodadihi",
    "ks:ks_pop":87,
    "ks:ks_type":"HABITATION",
    "name:eng_x_preferred":[
        "Bodadihi"
    ],
    "wof:name":"Bodadihi",
    "wof:placetype":"locality",
    "wof:population":87
},
  "geometry": {"coordinates":[86.72301,22.619954],"type":"Point"}
}