{
  "type": "Feature",
  "properties": {
    "iso:country":"IN",
    "ks:ks_name":"Shyani",
    "ks:ks_pop":504,
    "ks:ks_type":"HABITATION",
    "name:eng_x_preferred":[
        "Shyani"
    ],
    "wof:name":"Shyani",
    "wof:placetype":"locality",
    "wof:population":504
},
  "geometry": {"coordinates":[78.84308799999999,25.30294],"type":"Point"}
}