{
  "type": "Feature",
  "properties": {
    "iso:country":"IN",
    "ks:ks_name":"Lekhapani Nepali",
    "ks:ks_pop":937,
    "ks:ks_type":"VILLAGE",
    "name:eng_x_preferred":[
        "Lekhapani Nepali"
    ],
    "wof:name":"Lekhapani Nepali",
    "wof:placetype":"locality",
    "wof:population":937
},
  "geometry": {"coordinates":[95.829886,27.31496],"type":"Point"}
}