{
  "type": "Feature",
  "properties": {
    "gn:admin1_code":"19.0",
    "gn:admin2_code":"584.0",
    "gn:asciiname":"Lakkenhalli",
    "gn:country_code":"IN",
    "gn:dem":817,
    "gn:feature_class":"P",
    "gn:feature_code":"PPL",
    "gn:name":"Lakkenhalli",
    "gn:population":0,
    "gn:timezone":"Asia/Kolkata",
    "iso:country":"IN",
    "wof:name":"Lakkenhalli",
    "wof:placetype":"locality"
},
  "geometry": {"coordinates":[77.13791999999999,13.12491],"type":"Point"}
}