{
  "type": "Feature",
  "properties": {
    "iso:country":"IN",
    "ks:ks_alt_nam":"chotigulariya",
    "ks:ks_name":"Chotigulariya",
    "ks:ks_pop":116,
    "ks:ks_type":"HABITATION",
    "name:eng_x_preferred":[
        "Chotigulariya"
    ],
    "wof:name":"Chotigulariya",
    "wof:placetype":"locality",
    "wof:population":116
},
  "geometry": {"coordinates":[81.783242,27.307365],"type":"Point"}
}