{
  "type": "Feature",
  "properties": {
    "gn:admin1_code":"36",
    "gn:admin2_code":"196.0",
    "gn:asciiname":"Barhan",
    "gn:country_code":"IN",
    "gn:dem":79,
    "gn:feature_class":"P",
    "gn:feature_code":"PPL",
    "gn:name":"Barhan",
    "gn:population":0,
    "gn:timezone":"Asia/Kolkata",
    "iso:country":"IN",
    "name:msa_x_preferred":[
        "Barhan"
    ],
    "name:nno_x_preferred":[
        "Barhan"
    ],
    "wof:name":"Barhan",
    "wof:placetype":"locality"
},
  "geometry": {"coordinates":[83.42819,25.38542],"type":"Point"}
}