{
  "type": "Feature",
  "properties": {
    "iso:country":"IN",
    "ks:ks_name":"Gadabavalasa",
    "ks:ks_pop":90,
    "ks:ks_type":"HABITATION",
    "name:eng_x_preferred":[
        "Gadabavalasa"
    ],
    "wof:name":"Gadabavalasa",
    "wof:placetype":"locality",
    "wof:population":90
},
  "geometry": {"coordinates":[83.611881,18.764934],"type":"Point"}
}