{
  "type": "Feature",
  "properties": {
    "gn:admin1_code":"39.0",
    "gn:admin2_code":"64.0",
    "gn:asciiname":"Kasan",
    "gn:country_code":"IN",
    "gn:dem":1455,
    "gn:feature_class":"P",
    "gn:feature_code":"PPL",
    "gn:name":"Kas\u0101n",
    "gn:population":0,
    "gn:timezone":"Asia/Kolkata",
    "iso:country":"IN",
    "ks:ks_name":"Kasan",
    "ks:ks_pop":264,
    "ks:ks_type":"VILLAGE",
    "name:bar_x_preferred":[
        "Kasan"
    ],
    "name:ceb_x_preferred":[
        "Kasan"
    ],
    "name:deu_x_preferred":[
        "Kasan"
    ],
    "name:eng_x_preferred":[
        "Kasan"
    ],
    "name:ita_x_preferred":[
        "Kasan"
    ],
    "name:rus_x_preferred":[
        "\u041a\u0430\u0441\u0430\u043d"
    ],
    "name:swe_x_preferred":[
        "Kasan"
    ],
    "name:ukr_x_preferred":[
        "\u041a\u0430\u0441\u0430\u043d"
    ],
    "wof:name":"Kasan",
    "wof:placetype":"locality",
    "wof:population":264
},
  "geometry": {"coordinates":[79.830523,29.69581],"type":"Point"}
}