{
  "type": "Feature",
  "properties": {
    "gn:admin1_code":"36",
    "gn:admin2_code":"134.0",
    "gn:asciiname":"Mollawala",
    "gn:country_code":"IN",
    "gn:dem":247,
    "gn:feature_class":"P",
    "gn:feature_code":"PPL",
    "gn:name":"Moll\u0101w\u0101la",
    "gn:population":0,
    "gn:timezone":"Asia/Kolkata",
    "iso:country":"IN",
    "name:und_x_variant":[
        "Moll\u0101w\u0101la",
        "Aurangzebpur Hard\u0101s"
    ],
    "wof:name":"Mollawala",
    "wof:placetype":"neighbourhood"
},
  "geometry": {"coordinates":[78.44467,29.46772],"type":"Point"}
}