{
  "type": "Feature",
  "properties": {
    "gn:admin1_code":"11",
    "gn:admin2_code":"27.0",
    "gn:asciiname":"Badhu",
    "gn:country_code":"IN",
    "gn:dem":1378,
    "gn:feature_class":"P",
    "gn:feature_code":"PPL",
    "gn:name":"B\u0101dhu",
    "gn:population":0,
    "gn:timezone":"Asia/Kolkata",
    "iso:country":"IN",
    "wof:name":"Badhu",
    "wof:placetype":"locality"
},
  "geometry": {"coordinates":[76.93503,31.44865],"type":"Point"}
}