{
  "type": "Feature",
  "properties": {
    "gn:admin1_code":"35.0",
    "gn:admin2_code":"431.0",
    "gn:asciiname":"Birsinpur",
    "gn:country_code":"IN",
    "gn:dem":446,
    "gn:feature_class":"P",
    "gn:feature_code":"PPL",
    "gn:name":"Birsinpur",
    "gn:population":0,
    "gn:timezone":"Asia/Kolkata",
    "iso:country":"IN",
    "wof:name":"Birsinpur",
    "wof:placetype":"locality"
},
  "geometry": {"coordinates":[80.5861,23.4457],"type":"Point"}
}