{
  "type": "Feature",
  "properties": {
    "iso:country":"IN",
    "ks:ks_name":"Begodi",
    "ks:ks_pop":45,
    "ks:ks_type":"VILLAGE",
    "name:eng_x_preferred":[
        "Begodi"
    ],
    "wof:name":"Begodi",
    "wof:placetype":"locality",
    "wof:population":45
},
  "geometry": {"coordinates":[74.70021300000001,14.225849],"type":"Point"}
}