{
  "type": "Feature",
  "properties": {
    "iso:country":"IN",
    "ks:ks_name":"Hachekoti",
    "ks:ks_pop":28,
    "ks:ks_type":"HABITATION",
    "name:eng_x_preferred":[
        "Hachekoti"
    ],
    "wof:name":"Hachekoti",
    "wof:placetype":"locality",
    "wof:population":28
},
  "geometry": {"coordinates":[81.02909099999999,19.326586],"type":"Point"}
}