{
  "type": "Feature",
  "properties": {
    "gn:admin1_code":"11",
    "gn:admin2_code":"27.0",
    "gn:asciiname":"Jarl",
    "gn:country_code":"IN",
    "gn:dem":781,
    "gn:feature_class":"P",
    "gn:feature_code":"PPL",
    "gn:name":"J\u0101rl",
    "gn:population":0,
    "gn:timezone":"Asia/Kolkata",
    "iso:country":"IN",
    "name:bre_x_preferred":[
        "Jarl"
    ],
    "name:dan_x_preferred":[
        "Jarl"
    ],
    "name:deu_x_preferred":[
        "Jarl"
    ],
    "name:fra_x_preferred":[
        "Jarl"
    ],
    "name:ita_x_preferred":[
        "Jarl"
    ],
    "name:nds_x_preferred":[
        "Jarl"
    ],
    "name:nor_x_preferred":[
        "Jarl"
    ],
    "wof:name":"Jarl",
    "wof:placetype":"locality"
},
  "geometry": {"coordinates":[76.97773000000002,31.31778],"type":"Point"}
}