{
  "type": "Feature",
  "properties": {
    "iso:country":"IN",
    "ks:ks_name":"Uchageri",
    "ks:ks_pop":562,
    "ks:ks_type":"VILLAGE",
    "name:eng_x_preferred":[
        "Uchageri"
    ],
    "wof:name":"Uchageri",
    "wof:placetype":"locality",
    "wof:population":562
},
  "geometry": {"coordinates":[74.92848499999999,14.823825],"type":"Point"}
}