{
  "type": "Feature",
  "properties": {
    "iso:country":"IN",
    "ks:ks_name":"Kaithauli Urf Larauli",
    "ks:ks_pop":0,
    "ks:ks_type":"VILLAGE",
    "name:eng_x_preferred":[
        "Kaithauli Urf Larauli"
    ],
    "wof:name":"Kaithauli Urf Larauli",
    "wof:placetype":"locality",
    "wof:population":0
},
  "geometry": {"coordinates":[83.79691,25.662035],"type":"Point"}
}