{
  "type": "Feature",
  "properties": {
    "iso:country":"IN",
    "ks:ks_name":"Bamanadevi",
    "ks:ks_pop":182,
    "ks:ks_type":"HABITATION",
    "name:eng_x_preferred":[
        "Bamanadevi"
    ],
    "wof:name":"Bamanadevi",
    "wof:placetype":"locality",
    "wof:population":182
},
  "geometry": {"coordinates":[73.77064900000001,16.031799],"type":"Point"}
}