{
  "type": "Feature",
  "properties": {
    "iso:country":"IN",
    "ks:ks_name":"Bhoori Daud",
    "ks:ks_pop":1232,
    "ks:ks_type":"HABITATION",
    "name:eng_x_preferred":[
        "Bhoori Daud"
    ],
    "wof:name":"Bhoori Daud",
    "wof:placetype":"locality",
    "wof:population":1232
},
  "geometry": {"coordinates":[74.24715,23.296114],"type":"Point"}
}