{
  "type": "Feature",
  "properties": {
    "iso:country":"IN",
    "ks:ks_name":"Pachim Amtala",
    "ks:ks_pop":1466,
    "ks:ks_type":"VILLAGE",
    "name:eng_x_preferred":[
        "Pachim Amtala"
    ],
    "wof:name":"Pachim Amtala",
    "wof:placetype":"locality",
    "wof:population":1466
},
  "geometry": {"coordinates":[92.81617300000001,25.979811],"type":"Point"}
}