{
  "type": "Feature",
  "properties": {
    "iso:country":"IN",
    "ks:ks_name":"Muda Kheda",
    "ks:ks_pop":31,
    "ks:ks_type":"HABITATION",
    "name:eng_x_preferred":[
        "Muda Kheda"
    ],
    "wof:name":"Muda Kheda",
    "wof:placetype":"locality",
    "wof:population":31
},
  "geometry": {"coordinates":[79.69735,23.863482],"type":"Point"}
}