{
  "type": "Feature",
  "properties": {
    "gn:admin1_code":"25.0",
    "gn:admin2_code":"612.0",
    "gn:asciiname":"Sukkamanayakkanpatti",
    "gn:country_code":"IN",
    "gn:dem":320,
    "gn:feature_class":"P",
    "gn:feature_code":"PPL",
    "gn:name":"Sukkaman\u0101yakkanpatti",
    "gn:population":0,
    "gn:timezone":"Asia/Kolkata",
    "iso:country":"IN",
    "wof:name":"Sukkamanayakkanpatti",
    "wof:placetype":"locality"
},
  "geometry": {"coordinates":[77.45541999999998,10.48685],"type":"Point"}
}