{
  "type": "Feature",
  "properties": {
    "gn:admin1_code":"24.0",
    "gn:admin2_code":"109.0",
    "gn:asciiname":"Chenpura Pipaliya",
    "gn:country_code":"IN",
    "gn:dem":320,
    "gn:feature_class":"P",
    "gn:feature_code":"PPL",
    "gn:name":"Chenpura P\u012bpaliya",
    "gn:population":0,
    "gn:timezone":"Asia/Kolkata",
    "iso:country":"IN",
    "wof:name":"Chenpura Pipaliya",
    "wof:placetype":"neighbourhood"
},
  "geometry": {"coordinates":[76.21436,26.71517],"type":"Point"}
}