{
  "type": "Feature",
  "properties": {
    "iso:country":"IN",
    "ks:ks_name":"Indalwat",
    "ks:ks_pop":433,
    "ks:ks_type":"HABITATION",
    "name:eng_x_preferred":[
        "Indalwat"
    ],
    "wof:name":"Indalwat",
    "wof:placetype":"locality",
    "wof:population":433
},
  "geometry": {"coordinates":[74.16217899999999,22.47658],"type":"Point"}
}