{
  "type": "Feature",
  "properties": {
    "gn:admin1_code":"36",
    "gn:admin2_code":"132.0",
    "gn:asciiname":"Bahera",
    "gn:country_code":"IN",
    "gn:dem":295,
    "gn:feature_class":"P",
    "gn:feature_code":"PPL",
    "gn:name":"Bahera",
    "gn:population":0,
    "gn:timezone":"Asia/Kolkata",
    "iso:country":"IN",
    "ks:ks_name":"Bahera",
    "ks:ks_pop":1716,
    "ks:ks_type":"VILLAGE",
    "ks:ks_uagg_main":0,
    "name:eng_x_preferred":[
        "Bahera"
    ],
    "name:mal_x_preferred":[
        "\u0d2c\u0d39\u0d47\u0d31"
    ],
    "wof:name":"Bahera",
    "wof:placetype":"neighbourhood",
    "wof:population":1716
},
  "geometry": {"coordinates":[77.677435,30.058456],"type":"Point"}
}