{
  "type": "Feature",
  "properties": {
    "iso:country":"IN",
    "ks:ks_name":"Mirzapur",
    "ks:ks_pop":836,
    "ks:ks_type":"VILLAGE",
    "name:eng_x_preferred":[
        "Mirzapur"
    ],
    "wof:name":"Mirzapur",
    "wof:placetype":"locality",
    "wof:population":836
},
  "geometry": {"coordinates":[80.30528,26.55374],"type":"Point"}
}