{
  "type": "Feature",
  "properties": {
    "iso:country":"IN",
    "ks:ks_alt_nam":"anaburu koracharahatti",
    "ks:ks_name":"Anaburu Koracharahatti",
    "ks:ks_pop":88,
    "ks:ks_type":"HABITATION",
    "name:eng_x_preferred":[
        "Anaburu Koracharahatti"
    ],
    "wof:name":"Anaburu Koracharahatti",
    "wof:placetype":"locality",
    "wof:population":88
},
  "geometry": {"coordinates":[76.38742499999999,14.603245],"type":"Point"}
}