{
  "type": "Feature",
  "properties": {
    "iso:country":"IN",
    "ks:ks_name":"Purani Bazar",
    "ks:ks_pop":1395,
    "ks:ks_type":"HABITATION",
    "name:eng_x_preferred":[
        "Purani Bazar"
    ],
    "wof:name":"Purani Bazar",
    "wof:placetype":"locality",
    "wof:population":1395
},
  "geometry": {"coordinates":[86.732086,26.051485],"type":"Point"}
}