{
  "type": "Feature",
  "properties": {
    "iso:country":"IN",
    "ks:ks_alt_nam":"Kol P\u0101nde",
    "ks:ks_name":"Kol Pande",
    "ks:ks_type":"VILLAGE",
    "ks:ks_uagg_main":0,
    "name:eng_x_preferred":[
        "Kol Pande"
    ],
    "name:eng_x_variant":[
        "Kol P\u0101nde"
    ],
    "wof:name":"Kol Pande",
    "wof:placetype":"neighbourhood"
},
  "geometry": {"coordinates":[83.176255,26.063407],"type":"Point"}
}