{
  "type": "Feature",
  "properties": {
    "iso:country":"IN",
    "ks:ks_name":"Betegeri",
    "ks:ks_pop":37,
    "ks:ks_type":"HABITATION",
    "name:eng_x_preferred":[
        "Betegeri"
    ],
    "wof:name":"Betegeri",
    "wof:placetype":"locality",
    "wof:population":37
},
  "geometry": {"coordinates":[75.168848,13.590201],"type":"Point"}
}