{
  "type": "Feature",
  "properties": {
    "iso:country":"IN",
    "ks:ks_alt_nam":"GARMAL",
    "ks:ks_name":"Garmal",
    "ks:ks_pop":204,
    "ks:ks_type":"HABITATION",
    "name:eng_x_preferred":[
        "Garmal"
    ],
    "wof:name":"Garmal",
    "wof:placetype":"locality",
    "wof:population":204
},
  "geometry": {"coordinates":[75.057557,18.708844],"type":"Point"}
}