{
  "type": "Feature",
  "properties": {
    "iso:country":"IN",
    "ks:ks_name":"Kokani Dhangarwada",
    "ks:ks_pop":89,
    "ks:ks_type":"HABITATION",
    "name:eng_x_preferred":[
        "Kokani Dhangarwada"
    ],
    "wof:name":"Kokani Dhangarwada",
    "wof:placetype":"locality",
    "wof:population":89
},
  "geometry": {"coordinates":[73.935456,16.457225],"type":"Point"}
}