{
  "type": "Feature",
  "properties": {
    "iso:country":"IN",
    "ks:ks_name":"Teliyan",
    "ks:ks_pop":310,
    "ks:ks_type":"HABITATION",
    "ks:ks_uagg_main":0,
    "name:eng_x_preferred":[
        "Teliyan"
    ],
    "wof:name":"Teliyan",
    "wof:placetype":"neighbourhood",
    "wof:population":310
},
  "geometry": {"coordinates":[82.613772,25.982803],"type":"Point"}
}