{
  "type": "Feature",
  "properties": {
    "iso:country":"IN",
    "ks:ks_name":"Yenugugummi",
    "ks:ks_pop":94,
    "ks:ks_type":"HABITATION",
    "name:eng_x_preferred":[
        "Yenugugummi"
    ],
    "wof:name":"Yenugugummi",
    "wof:placetype":"locality",
    "wof:population":94
},
  "geometry": {"coordinates":[82.55031200000001,17.971327],"type":"Point"}
}