{
  "type": "Feature",
  "properties": {
    "gn:admin1_code":"36",
    "gn:admin2_code":"191.0",
    "gn:asciiname":"Jamwari",
    "gn:country_code":"IN",
    "gn:dem":82,
    "gn:feature_class":"P",
    "gn:feature_code":"PPL",
    "gn:name":"Jamwar\u012b",
    "gn:population":0,
    "gn:timezone":"Asia/Kolkata",
    "iso:country":"IN",
    "ks:ks_name":"Jamuwari",
    "ks:ks_pop":847,
    "ks:ks_type":"VILLAGE",
    "ks:ks_uagg_main":0,
    "name:eng_x_preferred":[
        "Jamuwari"
    ],
    "wof:name":"Jamuwari",
    "wof:placetype":"neighbourhood",
    "wof:population":847
},
  "geometry": {"coordinates":[83.297721,26.286516],"type":"Point"}
}