{
  "type": "Feature",
  "properties": {
    "iso:country":"IN",
    "ks:ks_name":"Kaintira",
    "ks:ks_pop":278,
    "ks:ks_type":"VILLAGE",
    "name:eng_x_preferred":[
        "Kaintira"
    ],
    "wof:name":"Kaintira",
    "wof:placetype":"locality",
    "wof:population":278
},
  "geometry": {"coordinates":[84.878401,20.534386],"type":"Point"}
}