{
  "type": "Feature",
  "properties": {
    "iso:country":"IN",
    "ks:ks_name":"Vachanwadi",
    "ks:ks_pop":288,
    "ks:ks_type":"HABITATION",
    "name:eng_x_preferred":[
        "Vachanwadi"
    ],
    "wof:name":"Vachanwadi",
    "wof:placetype":"locality",
    "wof:population":288
},
  "geometry": {"coordinates":[73.287222,17.463056],"type":"Point"}
}