{
  "type": "Feature",
  "properties": {
    "iso:country":"IN",
    "ks:ks_name":"Baprahia",
    "ks:ks_pop":750,
    "ks:ks_type":"HABITATION",
    "name:eng_x_preferred":[
        "Baprahia"
    ],
    "wof:name":"Baprahia",
    "wof:placetype":"locality",
    "wof:population":750
},
  "geometry": {"coordinates":[82.532121,27.040718],"type":"Point"}
}