{
  "type": "Feature",
  "properties": {
    "iso:country":"IN",
    "ks:ks_alt_nam":"chaptiyah",
    "ks:ks_name":"Chaptiyah",
    "ks:ks_pop":367,
    "ks:ks_type":"HABITATION",
    "name:eng_x_preferred":[
        "Chaptiyah"
    ],
    "wof:name":"Chaptiyah",
    "wof:placetype":"locality",
    "wof:population":367
},
  "geometry": {"coordinates":[82.163799,25.016769],"type":"Point"}
}