{
  "type": "Feature",
  "properties": {
    "iso:country":"IN",
    "ks:ks_name":"Newajipur",
    "ks:ks_pop":286,
    "ks:ks_type":"HABITATION",
    "name:eng_x_preferred":[
        "Newajipur"
    ],
    "wof:name":"Newajipur",
    "wof:placetype":"locality",
    "wof:population":286
},
  "geometry": {"coordinates":[80.47812399999999,27.178249],"type":"Point"}
}