{
  "type": "Feature",
  "properties": {
    "iso:country":"IN",
    "ks:ks_name":"Magubandh",
    "ks:ks_pop":48,
    "ks:ks_type":"VILLAGE",
    "name:eng_x_preferred":[
        "Magubandh"
    ],
    "wof:name":"Magubandh",
    "wof:placetype":"locality",
    "wof:population":48
},
  "geometry": {"coordinates":[85.377768,23.232465],"type":"Point"}
}