{
  "type": "Feature",
  "properties": {
    "iso:country":"IN",
    "ks:ks_name":"Poram Chapori",
    "ks:ks_pop":205,
    "ks:ks_type":"HABITATION",
    "name:eng_x_preferred":[
        "Poram Chapori"
    ],
    "wof:name":"Poram Chapori",
    "wof:placetype":"locality",
    "wof:population":205
},
  "geometry": {"coordinates":[93.764884,26.834899],"type":"Point"}
}