{
  "type": "Feature",
  "properties": {
    "iso:country":"IN",
    "ks:ks_name":"Bir Khurampur",
    "ks:ks_pop":2,
    "ks:ks_type":"VILLAGE",
    "name:eng_x_preferred":[
        "Bir Khurampur"
    ],
    "wof:name":"Bir Khurampur",
    "wof:placetype":"locality",
    "wof:population":2
},
  "geometry": {"coordinates":[75.825076,31.310396],"type":"Point"}
}