{
  "type": "Feature",
  "properties": {
    "iso:country":"IN",
    "ks:ks_name":"Pantrangam",
    "ks:ks_pop":358,
    "ks:ks_type":"VILLAGE",
    "name:eng_x_preferred":[
        "Pantrangam"
    ],
    "wof:name":"Pantrangam",
    "wof:placetype":"locality",
    "wof:population":358
},
  "geometry": {"coordinates":[80.15602699999999,13.790829],"type":"Point"}
}