{
  "type": "Feature",
  "properties": {
    "iso:country":"IN",
    "ks:ks_name":"Gondhalwadi",
    "ks:ks_pop":109,
    "ks:ks_type":"HABITATION",
    "name:eng_x_preferred":[
        "Gondhalwadi"
    ],
    "wof:name":"Gondhalwadi",
    "wof:placetype":"locality",
    "wof:population":109
},
  "geometry": {"coordinates":[73.162206,17.566553],"type":"Point"}
}