{
  "type": "Feature",
  "properties": {
    "iso:country":"IN",
    "ks:ks_name":"Bankat",
    "ks:ks_pop":259,
    "ks:ks_type":"HABITATION",
    "name:eng_x_preferred":[
        "Bankat"
    ],
    "wof:name":"Bankat",
    "wof:placetype":"locality",
    "wof:population":259
},
  "geometry": {"coordinates":[84.63112099999999,24.573205],"type":"Point"}
}