{
  "type": "Feature",
  "properties": {
    "iso:country":"IN",
    "ks:ks_name":"Murna",
    "ks:ks_pop":851,
    "ks:ks_type":"VILLAGE",
    "ks:ks_uagg_main":0,
    "name:eng_x_preferred":[
        "Murna"
    ],
    "wof:name":"Murna",
    "wof:placetype":"neighbourhood",
    "wof:population":851
},
  "geometry": {"coordinates":[85.944215,24.340001],"type":"Point"}
}