{
  "type": "Feature",
  "properties": {
    "iso:country":"IN",
    "ks:ks_alt_nam":"Khodiyar pura",
    "ks:ks_name":"Khodiyar Pura",
    "ks:ks_pop":495,
    "ks:ks_type":"HABITATION",
    "name:eng_x_preferred":[
        "Khodiyar Pura"
    ],
    "wof:name":"Khodiyar Pura",
    "wof:placetype":"locality",
    "wof:population":495
},
  "geometry": {"coordinates":[72.607083,22.70325],"type":"Point"}
}