{
  "type": "Feature",
  "properties": {
    "iso:country":"IN",
    "ks:ks_alt_nam":"kariyewadi",
    "ks:ks_name":"Kariyewadi",
    "ks:ks_pop":25,
    "ks:ks_type":"HABITATION",
    "name:eng_x_preferred":[
        "Kariyewadi"
    ],
    "wof:name":"Kariyewadi",
    "wof:placetype":"locality",
    "wof:population":25
},
  "geometry": {"coordinates":[74.059472,15.667444],"type":"Point"}
}