{
  "type": "Feature",
  "properties": {
    "iso:country":"IN",
    "ks:ks_name":"Chitaloor",
    "ks:ks_pop":190,
    "ks:ks_type":"HABITATION",
    "name:eng_x_preferred":[
        "Chitaloor"
    ],
    "wof:name":"Chitaloor",
    "wof:placetype":"locality",
    "wof:population":190
},
  "geometry": {"coordinates":[78.394374,9.829102],"type":"Point"}
}