{
  "type": "Feature",
  "properties": {
    "iso:country":"IN",
    "ks:ks_name":"Sungajan Block No. 3",
    "ks:ks_pop":775,
    "ks:ks_type":"HABITATION",
    "name:eng_x_preferred":[
        "Sungajan Block No. 3"
    ],
    "wof:name":"Sungajan Block No. 3",
    "wof:placetype":"locality",
    "wof:population":775
},
  "geometry": {"coordinates":[93.82677,26.074062],"type":"Point"}
}