{
  "type": "Feature",
  "properties": {
    "iso:country":"IN",
    "ks:ks_name":"Khara Suhia",
    "ks:ks_pop":143,
    "ks:ks_type":"VILLAGE",
    "ks:ks_uagg_main":0,
    "name:eng_x_preferred":[
        "Khara Suhia"
    ],
    "wof:name":"Khara Suhia",
    "wof:placetype":"neighbourhood",
    "wof:population":143
},
  "geometry": {"coordinates":[87.70904,26.306629],"type":"Point"}
}