{
  "type": "Feature",
  "properties": {
    "iso:country":"IN",
    "ks:ks_name":"Amarpura",
    "ks:ks_pop":100,
    "ks:ks_type":"VILLAGE",
    "name:eng_x_preferred":[
        "Amarpura"
    ],
    "wof:name":"Amarpura",
    "wof:placetype":"locality",
    "wof:population":100
},
  "geometry": {"coordinates":[71.95959999999999,25.494047],"type":"Point"}
}