{
  "type": "Feature",
  "properties": {
    "gn:admin1_code":"40.0",
    "gn:admin2_code":"541.0",
    "gn:asciiname":"Reddigudem",
    "gn:country_code":"IN",
    "gn:dem":149,
    "gn:feature_class":"P",
    "gn:feature_code":"PPL",
    "gn:name":"Reddig\u016bdem",
    "gn:population":0,
    "gn:timezone":"Asia/Kolkata",
    "iso:country":"IN",
    "wof:name":"Reddigudem",
    "wof:placetype":"locality"
},
  "geometry": {"coordinates":[81.03793,17.39927999999999],"type":"Point"}
}