{
  "type": "Feature",
  "properties": {
    "iso:country":"IN",
    "ks:ks_name":"Hitul",
    "ks:ks_pop":202,
    "ks:ks_type":"HABITATION",
    "name:eng_x_preferred":[
        "Hitul"
    ],
    "wof:name":"Hitul",
    "wof:placetype":"locality",
    "wof:population":202
},
  "geometry": {"coordinates":[81.07351800000001,19.295413],"type":"Point"}
}