{
  "type": "Feature",
  "properties": {
    "iso:country":"IN",
    "ks:ks_name":"Dewdanr",
    "ks:ks_pop":62,
    "ks:ks_type":"VILLAGE",
    "name:eng_x_preferred":[
        "Dewdanr"
    ],
    "wof:name":"Dewdanr",
    "wof:placetype":"locality",
    "wof:population":62
},
  "geometry": {"coordinates":[87.30919299999999,24.639063],"type":"Point"}
}