{
  "type": "Feature",
  "properties": {
    "gn:admin1_code":"23.0",
    "gn:admin2_code":"50.0",
    "gn:asciiname":"Munda",
    "gn:country_code":"IN",
    "gn:dem":221,
    "gn:feature_class":"P",
    "gn:feature_code":"PPL",
    "gn:name":"Munda",
    "gn:population":0,
    "gn:timezone":"Asia/Kolkata",
    "iso:country":"IN",
    "name:bar_x_preferred":[
        "Munda"
    ],
    "name:cat_x_preferred":[
        "Munda"
    ],
    "name:ceb_x_preferred":[
        "Munda"
    ],
    "name:deu_x_preferred":[
        "Munda"
    ],
    "name:fin_x_preferred":[
        "Munda"
    ],
    "name:fra_x_preferred":[
        "Munda"
    ],
    "name:ita_x_preferred":[
        "Munda"
    ],
    "name:jpn_x_preferred":[
        "\u30e0\u30f3\u30c0"
    ],
    "name:nld_x_preferred":[
        "Munda"
    ],
    "name:pol_x_preferred":[
        "Munda"
    ],
    "name:rus_x_preferred":[
        "\u041c\u0443\u043d\u0434\u0430"
    ],
    "name:swe_x_preferred":[
        "Munda"
    ],
    "wof:name":"Munda",
    "wof:placetype":"locality"
},
  "geometry": {"coordinates":[75.06928000000001,31.29087],"type":"Point"}
}