{
  "type": "Feature",
  "properties": {
    "gn:admin1_code":"16",
    "gn:admin2_code":"511.0",
    "gn:asciiname":"Bamanguda",
    "gn:country_code":"IN",
    "gn:dem":273,
    "gn:feature_class":"P",
    "gn:feature_code":"PPL",
    "gn:name":"B\u0101manguda",
    "gn:population":0,
    "gn:timezone":"Asia/Kolkata",
    "iso:country":"IN",
    "wof:name":"Bamanguda",
    "wof:placetype":"locality"
},
  "geometry": {"coordinates":[78.15725999999999,19.88282],"type":"Point"}
}