{
  "type": "Feature",
  "properties": {
    "gn:admin1_code":"16",
    "gn:admin2_code":"515.0",
    "gn:asciiname":"Kharaj",
    "gn:country_code":"IN",
    "gn:dem":594,
    "gn:feature_class":"P",
    "gn:feature_code":"PPL",
    "gn:name":"Kharaj",
    "gn:population":0,
    "gn:timezone":"Asia/Kolkata",
    "iso:country":"IN",
    "name:ara_x_preferred":[
        "\u062e\u0631\u0627\u062c"
    ],
    "name:aze_x_preferred":[
        "X\u0259rac"
    ],
    "name:bak_x_preferred":[
        "\u0425\u0430\u0440\u0430\u0436"
    ],
    "name:ben_x_preferred":[
        "\u0996\u09be\u09b0\u09be\u099c"
    ],
    "name:bos_x_preferred":[
        "Hara\u010d"
    ],
    "name:cat_x_preferred":[
        "Kharaj"
    ],
    "name:epo_x_preferred":[
        "\u0124ara\u0109o"
    ],
    "name:fas_x_preferred":[
        "\u062e\u0631\u0627\u062c"
    ],
    "name:fra_x_preferred":[
        "Khar\u00e2j"
    ],
    "name:heb_x_preferred":[
        "\u05d7'\u05e8\u05d0\u05d2'"
    ],
    "name:hrv_x_preferred":[
        "Hara\u010d"
    ],
    "name:hye_x_preferred":[
        "\u053d\u0561\u0580\u0561\u057b"
    ],
    "name:ind_x_preferred":[
        "Kharaj"
    ],
    "name:ita_x_preferred":[
        "Khar\u0101j"
    ],
    "name:jpn_x_preferred":[
        "\u30cf\u30e9\u30fc\u30b8\u30e5"
    ],
    "name:kat_x_preferred":[
        "\u10ee\u10d0\u10e0\u10d0\u10ef\u10d0"
    ],
    "name:kaz_x_preferred":[
        "\u0425\u0430\u0440\u0430\u0434\u0436"
    ],
    "name:kor_x_preferred":[
        "\ud558\ub77c\uc988"
    ],
    "name:msa_x_preferred":[
        "Kharaj"
    ],
    "name:pol_x_preferred":[
        "Charad\u017c"
    ],
    "name:por_x_preferred":[
        "Caraje"
    ],
    "name:rus_x_preferred":[
        "\u0425\u0430\u0440\u0430\u0434\u0436"
    ],
    "name:spa_x_preferred":[
        "Jarach"
    ],
    "name:sqi_x_preferred":[
        "Hara\u00e7i"
    ],
    "name:srp_x_preferred":[
        "Hara\u010d"
    ],
    "name:tur_x_preferred":[
        "Hara\u00e7"
    ],
    "name:ukr_x_preferred":[
        "\u0425\u0430\u0440\u0430\u0434\u0436"
    ],
    "name:urd_x_preferred":[
        "\u062e\u0631\u0627\u062c"
    ],
    "name:uzb_x_preferred":[
        "Xiroj"
    ],
    "wof:name":"Kharaj",
    "wof:placetype":"locality"
},
  "geometry": {"coordinates":[74.79656,20.12763],"type":"Point"}
}