{
  "type": "Feature",
  "properties": {
    "iso:country":"IN",
    "ks:ks_name":"Sourapendraguda",
    "ks:ks_pop":0,
    "ks:ks_type":"VILLAGE",
    "name:eng_x_preferred":[
        "Sourapendraguda"
    ],
    "wof:name":"Sourapendraguda",
    "wof:placetype":"locality",
    "wof:population":0
},
  "geometry": {"coordinates":[83.94373400000001,19.318851],"type":"Point"}
}