{
  "type": "Feature",
  "properties": {
    "iso:country":"IN",
    "ks:ks_name":"Usarhiya H.b.",
    "ks:ks_pop":175,
    "ks:ks_type":"HABITATION",
    "name:eng_x_preferred":[
        "Usarhiya H.b."
    ],
    "wof:name":"Usarhiya H.b.",
    "wof:placetype":"locality",
    "wof:population":175
},
  "geometry": {"coordinates":[83.17880599999999,25.795894],"type":"Point"}
}