{
  "type": "Feature",
  "properties": {
    "gn:admin1_code":"19.0",
    "gn:admin2_code":"577.0",
    "gn:asciiname":"Kavalanahalli",
    "gn:country_code":"IN",
    "gn:dem":861,
    "gn:feature_class":"P",
    "gn:feature_code":"PPL",
    "gn:name":"Kavalanahalli",
    "gn:population":0,
    "gn:timezone":"Asia/Kolkata",
    "iso:country":"IN",
    "wof:name":"Kavalanahalli",
    "wof:placetype":"locality"
},
  "geometry": {"coordinates":[76.12608,12.5222],"type":"Point"}
}