{
  "type": "Feature",
  "properties": {
    "iso:country":"IN",
    "ks:ks_name":"Bhair Thana",
    "ks:ks_pop":3204,
    "ks:ks_type":"VILLAGE",
    "name:eng_x_preferred":[
        "Bhair Thana"
    ],
    "wof:name":"Bhair Thana",
    "wof:placetype":"locality",
    "wof:population":3204
},
  "geometry": {"coordinates":[89.271512,26.217511],"type":"Point"}
}