{
  "type": "Feature",
  "properties": {
    "iso:country":"IN",
    "ks:ks_alt_nam":"Main\u0101ha",
    "ks:ks_name":"Mainaha",
    "ks:ks_type":"VILLAGE",
    "name:eng_x_preferred":[
        "Mainaha"
    ],
    "name:eng_x_variant":[
        "Main\u0101ha"
    ],
    "wof:name":"Mainaha",
    "wof:placetype":"locality"
},
  "geometry": {"coordinates":[86.54283599999999,26.199578],"type":"Point"}
}