{
  "type": "Feature",
  "properties": {
    "gn:admin1_code":"02",
    "gn:asciiname":"Polluru",
    "gn:country_code":"IN",
    "gn:dem":99,
    "gn:feature_class":"P",
    "gn:feature_code":"PPL",
    "gn:name":"Poll\u016bru",
    "gn:population":0,
    "gn:timezone":"Asia/Kolkata",
    "iso:country":"IN",
    "name:und_x_variant":[
        "Pollur",
        "Poll\u016bru"
    ],
    "wof:name":"Polluru",
    "wof:placetype":"locality"
},
  "geometry": {"coordinates":[81.65181,17.86257],"type":"Point"}
}