{
  "type": "Feature",
  "properties": {
    "iso:country":"IN",
    "ks:ks_name":"Gunogi",
    "ks:ks_pop":378,
    "ks:ks_type":"VILLAGE",
    "name:eng_x_preferred":[
        "Gunogi"
    ],
    "wof:name":"Gunogi",
    "wof:placetype":"locality",
    "wof:population":378
},
  "geometry": {"coordinates":[78.35909100000001,30.373321],"type":"Point"}
}