{
  "type": "Feature",
  "properties": {
    "gn:admin1_code":"11",
    "gn:admin2_code":"23.0",
    "gn:asciiname":"Chobia",
    "gn:country_code":"IN",
    "gn:dem":2004,
    "gn:feature_class":"P",
    "gn:feature_code":"PPL",
    "gn:name":"Chobia",
    "gn:population":0,
    "gn:timezone":"Asia/Kolkata",
    "iso:country":"IN",
    "wof:name":"Chobia",
    "wof:placetype":"locality"
},
  "geometry": {"coordinates":[76.57628000000003,32.46422],"type":"Point"}
}