{
  "type": "Feature",
  "properties": {
    "iso:country":"IN",
    "ks:ks_name":"Aawaspara",
    "ks:ks_pop":75,
    "ks:ks_type":"HABITATION",
    "name:eng_x_preferred":[
        "Aawaspara"
    ],
    "wof:name":"Aawaspara",
    "wof:placetype":"locality",
    "wof:population":75
},
  "geometry": {"coordinates":[81.110443,20.121719],"type":"Point"}
}