{
  "type": "Feature",
  "properties": {
    "gn:admin1_code":"36.0",
    "gn:admin2_code":"182.0",
    "gn:asciiname":"Pura Matai Bhainsaha",
    "gn:country_code":"IN",
    "gn:dem":104,
    "gn:feature_class":"P",
    "gn:feature_code":"PPL",
    "gn:name":"Pura Matai Bhains\u0101ha",
    "gn:population":0,
    "gn:timezone":"Asia/Kolkata",
    "iso:country":"IN",
    "wof:name":"Pura Matai Bhainsaha",
    "wof:placetype":"locality"
},
  "geometry": {"coordinates":[82.32155999999998,27.21357],"type":"Point"}
}