{
  "type": "Feature",
  "properties": {
    "gn:admin1_code":"36",
    "gn:admin2_code":"194.0",
    "gn:asciiname":"Aswa",
    "gn:country_code":"IN",
    "gn:dem":89,
    "gn:feature_class":"P",
    "gn:feature_code":"PPL",
    "gn:name":"Aswa",
    "gn:population":0,
    "gn:timezone":"Asia/Kolkata",
    "iso:country":"IN",
    "name:ceb_x_preferred":[
        "Aswa"
    ],
    "name:deu_x_preferred":[
        "Aswa"
    ],
    "name:swe_x_preferred":[
        "Aswa"
    ],
    "wof:name":"Aswa",
    "wof:placetype":"locality"
},
  "geometry": {"coordinates":[82.51635999999998,25.46872],"type":"Point"}
}