{
  "type": "Feature",
  "properties": {
    "iso:country":"IN",
    "ks:ks_name":"Arwa",
    "ks:ks_pop":4216,
    "ks:ks_type":"VILLAGE",
    "ks:ks_uagg_main":0,
    "name:eng_x_preferred":[
        "Arwa"
    ],
    "wof:name":"Arwa",
    "wof:placetype":"neighbourhood",
    "wof:population":4216
},
  "geometry": {"coordinates":[85.91627,25.584638],"type":"Point"}
}