{
  "type": "Feature",
  "properties": {
    "iso:country":"IN",
    "ks:ks_name":"Vilvamarathupatti",
    "ks:ks_pop":700,
    "ks:ks_type":"HABITATION",
    "name:eng_x_preferred":[
        "Vilvamarathupatti"
    ],
    "wof:name":"Vilvamarathupatti",
    "wof:placetype":"locality",
    "wof:population":700
},
  "geometry": {"coordinates":[78.16963199999999,9.1542],"type":"Point"}
}