{
  "type": "Feature",
  "properties": {
    "gn:admin1_code":"9",
    "gn:admin2_code":"485.0",
    "gn:asciiname":"Lakhanpur",
    "gn:country_code":"IN",
    "gn:dem":229,
    "gn:feature_class":"P",
    "gn:feature_code":"PPL",
    "gn:name":"Lakhanpur",
    "gn:population":0,
    "gn:timezone":"Asia/Kolkata",
    "iso:country":"IN",
    "name:fra_x_preferred":[
        "Lakhanpur"
    ],
    "name:pol_x_preferred":[
        "Lakhanpur"
    ],
    "wof:name":"Lakhanpur",
    "wof:placetype":"locality"
},
  "geometry": {"coordinates":[74.08615,23.1354],"type":"Point"}
}