{
  "type": "Feature",
  "properties": {
    "iso:country":"IN",
    "ks:ks_name":"Amguri Pt II",
    "ks:ks_pop":749,
    "ks:ks_type":"VILLAGE",
    "ks:ks_uagg_main":0,
    "name:eng_x_preferred":[
        "Amguri Pt II"
    ],
    "wof:name":"Amguri Pt II",
    "wof:placetype":"neighbourhood",
    "wof:population":749
},
  "geometry": {"coordinates":[90.66712,26.299833],"type":"Point"}
}