{
  "type": "Feature",
  "properties": {
    "iso:country":"IN",
    "ks:ks_name":"Bhawar Bigha",
    "ks:ks_pop":147,
    "ks:ks_type":"HABITATION",
    "name:eng_x_preferred":[
        "Bhawar Bigha"
    ],
    "wof:name":"Bhawar Bigha",
    "wof:placetype":"locality",
    "wof:population":147
},
  "geometry": {"coordinates":[84.43841999999999,24.630201],"type":"Point"}
}