{
  "type": "Feature",
  "properties": {
    "iso:country":"IN",
    "ks:ks_name":"Thapadpada",
    "ks:ks_pop":99,
    "ks:ks_type":"HABITATION",
    "name:eng_x_preferred":[
        "Thapadpada"
    ],
    "wof:name":"Thapadpada",
    "wof:placetype":"locality",
    "wof:population":99
},
  "geometry": {"coordinates":[73.144276,19.554445],"type":"Point"}
}