{
  "type": "Feature",
  "properties": {
    "gn:admin1_code":"39.0",
    "gn:admin2_code":"60.0",
    "gn:asciiname":"Khar Kota",
    "gn:country_code":"IN",
    "gn:dem":1179,
    "gn:feature_class":"P",
    "gn:feature_code":"PPL",
    "gn:name":"Khar Kota",
    "gn:population":0,
    "gn:timezone":"Asia/Kolkata",
    "iso:country":"IN",
    "wof:name":"Khar Kota",
    "wof:placetype":"locality"
},
  "geometry": {"coordinates":[77.96025,30.69226],"type":"Point"}
}