{
  "type": "Feature",
  "properties": {
    "iso:country":"IN",
    "ks:ks_name":"Kudarbahal",
    "ks:ks_pop":560,
    "ks:ks_type":"VILLAGE",
    "name:eng_x_preferred":[
        "Kudarbahal"
    ],
    "wof:name":"Kudarbahal",
    "wof:placetype":"locality",
    "wof:population":560
},
  "geometry": {"coordinates":[84.950047,22.212674],"type":"Point"}
}