{
  "type": "Feature",
  "properties": {
    "gn:admin1_code":"34.0",
    "gn:admin2_code":"239.0",
    "gn:asciiname":"Kalanaur",
    "gn:country_code":"IN",
    "gn:dem":78,
    "gn:feature_class":"P",
    "gn:feature_code":"PPL",
    "gn:name":"K\u0101l\u0101naur",
    "gn:population":0,
    "gn:timezone":"Asia/Kolkata",
    "iso:country":"IN",
    "name:cat_x_preferred":[
        "Kalanaur"
    ],
    "name:ceb_x_preferred":[
        "Kalanaur"
    ],
    "name:nld_x_preferred":[
        "Kalanaur"
    ],
    "name:swe_x_preferred":[
        "Kalanaur"
    ],
    "wof:name":"Kalanaur",
    "wof:placetype":"locality"
},
  "geometry": {"coordinates":[85.01241,25.09533],"type":"Point"}
}