{
  "type": "Feature",
  "properties": {
    "gn:admin1_code":"36",
    "gn:admin2_code":"196.0",
    "gn:asciiname":"Nairhi",
    "gn:country_code":"IN",
    "gn:dem":79,
    "gn:feature_class":"P",
    "gn:feature_code":"PPL",
    "gn:name":"Nairhi",
    "gn:population":0,
    "gn:timezone":"Asia/Kolkata",
    "iso:country":"IN",
    "wof:name":"Nairhi",
    "wof:placetype":"locality"
},
  "geometry": {"coordinates":[83.23358,25.4983],"type":"Point"}
}