{
  "type": "Feature",
  "properties": {
    "gn:admin1_code":"24.0",
    "gn:admin2_code":"119.0",
    "gn:asciiname":"Kheradand",
    "gn:country_code":"IN",
    "gn:dem":481,
    "gn:feature_class":"P",
    "gn:feature_code":"PPL",
    "gn:name":"Kheradand",
    "gn:population":0,
    "gn:timezone":"Asia/Kolkata",
    "iso:country":"IN",
    "ks:ks_name":"Khera Dand",
    "ks:ks_pop":414,
    "ks:ks_type":"VILLAGE",
    "ks:ks_uagg_main":0,
    "name:eng_x_preferred":[
        "Khera Dand"
    ],
    "wof:name":"Khera Dand",
    "wof:placetype":"neighbourhood",
    "wof:population":414
},
  "geometry": {"coordinates":[74.243951,26.025408],"type":"Point"}
}