{
  "type": "Feature",
  "properties": {
    "iso:country":"IN",
    "ks:ks_alt_nam":"Paschim para",
    "ks:ks_name":"Paschim Para",
    "ks:ks_pop":667,
    "ks:ks_type":"HABITATION",
    "name:eng_x_preferred":[
        "Paschim Para"
    ],
    "wof:name":"Paschim Para",
    "wof:placetype":"locality",
    "wof:population":667
},
  "geometry": {"coordinates":[91.16261,23.623642],"type":"Point"}
}