{
  "type": "Feature",
  "properties": {
    "gn:admin1_code":"35",
    "gn:admin2_code":"447.0",
    "gn:asciiname":"Jamuthana",
    "gn:country_code":"IN",
    "gn:dem":477,
    "gn:feature_class":"P",
    "gn:feature_code":"PPL",
    "gn:name":"J\u0101m\u016bth\u0101na",
    "gn:population":0,
    "gn:timezone":"Asia/Kolkata",
    "iso:country":"IN",
    "wof:name":"Jamuthana",
    "wof:placetype":"locality"
},
  "geometry": {"coordinates":[77.72384,21.79988],"type":"Point"}
}