{
  "type": "Feature",
  "properties": {
    "iso:country":"IN",
    "ks:ks_alt_nam":"PATEL BASTI",
    "ks:ks_name":"Patel Basti",
    "ks:ks_pop":840,
    "ks:ks_type":"HABITATION",
    "name:eng_x_preferred":[
        "Patel Basti"
    ],
    "wof:name":"Patel Basti",
    "wof:placetype":"locality",
    "wof:population":840
},
  "geometry": {"coordinates":[82.08200100000001,25.639744],"type":"Point"}
}