{
  "type": "Feature",
  "properties": {
    "gn:admin1_code":"35",
    "gn:admin2_code":"452.0",
    "gn:asciiname":"Non",
    "gn:country_code":"IN",
    "gn:dem":382,
    "gn:feature_class":"P",
    "gn:feature_code":"PPL",
    "gn:name":"Non",
    "gn:population":0,
    "gn:timezone":"Asia/Kolkata",
    "iso:country":"IN",
    "name:ceb_x_preferred":[
        "Non"
    ],
    "name:fra_x_preferred":[
        "Non"
    ],
    "name:kor_x_preferred":[
        "\ub17c"
    ],
    "name:nld_x_preferred":[
        "Non"
    ],
    "name:nor_x_preferred":[
        "Non"
    ],
    "name:pol_x_preferred":[
        "Non"
    ],
    "name:swe_x_preferred":[
        "Non"
    ],
    "wof:name":"Non",
    "wof:placetype":"locality"
},
  "geometry": {"coordinates":[79.42984,22.942],"type":"Point"}
}