{
  "type": "Feature",
  "properties": {
    "gn:admin1_code":"39.0",
    "gn:admin2_code":"64.0",
    "gn:asciiname":"Garsari",
    "gn:country_code":"IN",
    "gn:dem":1079,
    "gn:feature_class":"P",
    "gn:feature_code":"PPL",
    "gn:name":"Gars\u0101ri",
    "gn:population":0,
    "gn:timezone":"Asia/Kolkata",
    "iso:country":"IN",
    "ks:ks_alt_nam":"Gars\u0101ri",
    "ks:ks_name":"Garsari",
    "ks:ks_type":"VILLAGE",
    "name:eng_x_preferred":[
        "Garsari"
    ],
    "name:eng_x_variant":[
        "Gars\u0101ri"
    ],
    "wof:name":"Garsari",
    "wof:placetype":"locality"
},
  "geometry": {"coordinates":[79.370547,29.844824],"type":"Point"}
}