{
  "type": "Feature",
  "properties": {
    "iso:country":"IN",
    "ks:ks_name":"Ibrahimpur",
    "ks:ks_pop":91,
    "ks:ks_type":"HABITATION",
    "name:eng_x_preferred":[
        "Ibrahimpur"
    ],
    "wof:name":"Ibrahimpur",
    "wof:placetype":"locality",
    "wof:population":91
},
  "geometry": {"coordinates":[75.485258,19.770036],"type":"Point"}
}