{
  "type": "Feature",
  "properties": {
    "iso:country":"IN",
    "ks:ks_name":"School Para",
    "ks:ks_pop":1117,
    "ks:ks_type":"HABITATION",
    "name:eng_x_preferred":[
        "School Para"
    ],
    "wof:name":"School Para",
    "wof:placetype":"locality",
    "wof:population":1117
},
  "geometry": {"coordinates":[88.84817099999999,22.204568],"type":"Point"}
}