{
  "type": "Feature",
  "properties": {
    "iso:country":"IN",
    "ks:ks_name":"Kemmampatty",
    "ks:ks_pop":106,
    "ks:ks_type":"HABITATION",
    "name:eng_x_preferred":[
        "Kemmampatty"
    ],
    "wof:name":"Kemmampatty",
    "wof:placetype":"locality",
    "wof:population":106
},
  "geometry": {"coordinates":[78.194517,11.398486],"type":"Point"}
}