{
  "type": "Feature",
  "properties": {
    "iso:country":"IN",
    "ks:ks_name":"Kaphol Gaon",
    "ks:ks_pop":257,
    "ks:ks_type":"VILLAGE",
    "ks:ks_uagg_main":0,
    "name:eng_x_preferred":[
        "Kaphol Gaon"
    ],
    "wof:name":"Kaphol Gaon",
    "wof:placetype":"neighbourhood",
    "wof:population":257
},
  "geometry": {"coordinates":[78.66348499999999,30.530641],"type":"Point"}
}