{
  "type": "Feature",
  "properties": {
    "gn:admin1_code":"10.0",
    "gn:admin2_code":"081",
    "gn:asciiname":"Dhani Daryapur",
    "gn:country_code":"IN",
    "gn:dem":219,
    "gn:feature_class":"P",
    "gn:feature_code":"PPL",
    "gn:name":"Dh\u0101ni Dary\u0101pur",
    "gn:population":0,
    "gn:timezone":"Asia/Kolkata",
    "iso:country":"IN",
    "wof:name":"Dhani Daryapur",
    "wof:placetype":"locality"
},
  "geometry": {"coordinates":[75.73907,28.87333],"type":"Point"}
}