{
  "type": "Feature",
  "properties": {
    "gn:admin1_code":"36.0",
    "gn:admin2_code":"175.0",
    "gn:asciiname":"Sarwa Gauhan",
    "gn:country_code":"IN",
    "gn:dem":108,
    "gn:feature_class":"P",
    "gn:feature_code":"PPL",
    "gn:name":"Sarwa Gauhan",
    "gn:population":0,
    "gn:timezone":"Asia/Kolkata",
    "iso:country":"IN",
    "name:und_x_variant":[
        "Singhgarh"
    ],
    "wof:name":"Sarwa Gauhan",
    "wof:placetype":"neighbourhood"
},
  "geometry": {"coordinates":[81.78879000000001,25.69623],"type":"Point"}
}