{
  "type": "Feature",
  "properties": {
    "gn:admin1_code":"39",
    "gn:admin2_code":"60.0",
    "gn:asciiname":"Danguta Khera",
    "gn:country_code":"IN",
    "gn:dem":1917,
    "gn:feature_class":"P",
    "gn:feature_code":"PPL",
    "gn:name":"D\u0101ng\u016bta Khera",
    "gn:population":0,
    "gn:timezone":"Asia/Kolkata",
    "iso:country":"IN",
    "wof:name":"Danguta Khera",
    "wof:placetype":"locality"
},
  "geometry": {"coordinates":[77.95171999999999,30.86096],"type":"Point"}
}