{
  "type": "Feature",
  "properties": {
    "iso:country":"IN",
    "ks:ks_name":"Pure Dulham",
    "ks:ks_pop":209,
    "ks:ks_type":"HABITATION",
    "ks:ks_uagg_main":0,
    "name:eng_x_preferred":[
        "Pure Dulham"
    ],
    "wof:name":"Pure Dulham",
    "wof:placetype":"neighbourhood",
    "wof:population":209
},
  "geometry": {"coordinates":[81.924661,26.68897],"type":"Point"}
}