{
  "type": "Feature",
  "properties": {
    "iso:country":"IN",
    "ks:ks_name":"Keratalo",
    "ks:ks_pop":293,
    "ks:ks_type":"HABITATION",
    "name:eng_x_preferred":[
        "Keratalo"
    ],
    "wof:name":"Keratalo",
    "wof:placetype":"locality",
    "wof:population":293
},
  "geometry": {"coordinates":[82.19768000000001,18.759705],"type":"Point"}
}