{
  "type": "Feature",
  "properties": {
    "gn:admin1_code":"35.0",
    "gn:admin2_code":"438.0",
    "gn:asciiname":"Jamanjhiri",
    "gn:country_code":"IN",
    "gn:dem":315,
    "gn:feature_class":"P",
    "gn:feature_code":"PPL",
    "gn:name":"J\u0101manjh\u012bri",
    "gn:population":0,
    "gn:timezone":"Asia/Kolkata",
    "iso:country":"IN",
    "ks:ks_name":"Jamanjhiri",
    "ks:ks_pop":332,
    "ks:ks_type":"HABITATION",
    "name:eng_x_preferred":[
        "Jamanjhiri"
    ],
    "wof:name":"Jamanjhiri",
    "wof:placetype":"locality",
    "wof:population":332
},
  "geometry": {"coordinates":[75.543863,22.370882],"type":"Point"}
}