{
  "type": "Feature",
  "properties": {
    "gn:admin1_code":"36",
    "gn:admin2_code":"178.0",
    "gn:asciiname":"Bela Bagh",
    "gn:country_code":"IN",
    "gn:dem":96,
    "gn:feature_class":"P",
    "gn:feature_code":"PPL",
    "gn:name":"Bel\u0101 B\u0101gh",
    "gn:population":0,
    "gn:timezone":"Asia/Kolkata",
    "iso:country":"IN",
    "wof:name":"Bela Bagh",
    "wof:placetype":"neighbourhood"
},
  "geometry": {"coordinates":[82.46042,26.54332],"type":"Point"}
}