{
  "type": "Feature",
  "properties": {
    "iso:country":"IN",
    "ks:ks_name":"Gadaga",
    "ks:ks_pop":250,
    "ks:ks_type":"HABITATION",
    "name:eng_x_preferred":[
        "Gadaga"
    ],
    "wof:name":"Gadaga",
    "wof:placetype":"locality",
    "wof:population":250
},
  "geometry": {"coordinates":[73.25465,19.128481],"type":"Point"}
}