{
  "type": "Feature",
  "properties": {
    "gn:admin1_code":"35",
    "gn:admin2_code":"430.0",
    "gn:asciiname":"Turki",
    "gn:country_code":"IN",
    "gn:dem":314,
    "gn:feature_class":"P",
    "gn:feature_code":"PPL",
    "gn:name":"Turki",
    "gn:population":0,
    "gn:timezone":"Asia/Kolkata",
    "iso:country":"IN",
    "name:bak_x_preferred":[
        "\u0422\u04e9\u0440\u043a\u0438"
    ],
    "name:fin_x_preferred":[
        "T\u00fcrki"
    ],
    "name:ita_x_preferred":[
        "Turki"
    ],
    "name:rus_x_preferred":[
        "\u0422\u044e\u0440\u043a\u0438"
    ],
    "name:tyv_x_preferred":[
        "\u0422\u04af\u0440\u043a \u0434\u044b\u043b"
    ],
    "name:ukr_x_preferred":[
        "\u041c\u043e\u0432\u0430 \u0442\u044e\u0440\u043a\u0438"
    ],
    "name:uzb_x_preferred":[
        "Turkiy til"
    ],
    "wof:name":"Turki",
    "wof:placetype":"locality"
},
  "geometry": {"coordinates":[81.33849000000002,24.58659],"type":"Point"}
}