{
  "type": "Feature",
  "properties": {
    "iso:country":"IN",
    "name:ben_x_preferred":[
        "\u09ac\u09bf\u09b0\u09be\u099c\u09aa\u09c7\u09a4"
    ],
    "name:bpy_x_preferred":[
        "\u09ac\u09bf\u09b0\u09be\u099c\u09aa\u09c7\u09a4"
    ],
    "name:deu_x_preferred":[
        "Virajpet"
    ],
    "name:eng_x_preferred":[
        "Virajpet"
    ],
    "name:fra_x_preferred":[
        "Virajpet"
    ],
    "name:guj_x_preferred":[
        "\u0ab5\u0abf\u0ab0\u0abe\u0a9c\u0aaa\u0ac7\u0a9f"
    ],
    "name:ind_x_preferred":[
        "Virajpet"
    ],
    "name:ita_x_preferred":[
        "Virajpet"
    ],
    "name:jpn_x_preferred":[
        "\u30d3\u30e9\u30b8\u30da\u30c3\u30c8"
    ],
    "name:kan_x_preferred":[
        "\u0cb5\u0cbf\u0cb0\u0cbe\u0c9c\u0caa\u0cc7\u0c9f\u0cc6"
    ],
    "name:kor_x_preferred":[
        "\ube44\ub77c\uc988\ud398\ud2b8"
    ],
    "name:mal_x_preferred":[
        "\u0d35\u0d40\u0d30\u0d3e\u0d1c\u0d4d\u0d2a\u0d47\u0d1f\u0d4d\u0d1f"
    ],
    "name:mlg_x_preferred":[
        "Virajpet"
    ],
    "name:msa_x_preferred":[
        "Virajpet"
    ],
    "name:nan_x_preferred":[
        "Virajpet"
    ],
    "name:new_x_preferred":[
        "\u0935\u093f\u0930\u093e\u091c\u092a\u0947\u091f"
    ],
    "name:nld_x_preferred":[
        "Virajpet"
    ],
    "name:ori_x_preferred":[
        "\u0b2d\u0b3f\u0b30\u0b3e\u0b1c\u0b2a\u0b47\u0b1f"
    ],
    "name:por_x_preferred":[
        "Virajpet"
    ],
    "name:rus_x_preferred":[
        "\u0412\u0438\u0440\u0430\u0434\u0436\u043f\u0435\u0442"
    ],
    "name:spa_x_preferred":[
        "Virajpet"
    ],
    "name:tam_x_preferred":[
        "\u0bb5\u0bbf\u0bb0\u0bbe\u0b9a\u0bc1\u0baa\u0bcd\u0baa\u0bc7\u0b9f\u0bcd\u0b9f\u0bc8"
    ],
    "name:tel_x_preferred":[
        "\u0c35\u0c3f\u0c30\u0c3e\u0c1c\u0c2a\u0c47\u0c1f"
    ],
    "name:urd_x_preferred":[
        "\u0648\u06cc\u0631\u0627\u062c\u067e\u06cc\u062a"
    ],
    "name:vie_x_preferred":[
        "Virajpet"
    ],
    "name:zho_x_preferred":[
        "\u7ef4\u62c9\u6770\u4f69\u7279"
    ],
    "qs:name":"Virajpet",
    "qs:name_adm0":"India",
    "qs:name_adm1":"Karnataka",
    "qs:photos":120,
    "qs:photos_1k":24,
    "qs:photos_9k":1,
    "qs:photos_9r":4,
    "qs:photos_all":181,
    "qs:photos_sr":3,
    "qs:placetype":"Town",
    "qs:pop_sr":"0",
    "wd:wordcount":708,
    "wof:name":"Virajpet",
    "wof:placetype":"locality"
},
  "geometry": {"coordinates":[75.80394699999999,12.193059],"type":"Point"}
}