{
  "type": "Feature",
  "properties": {
    "iso:country":"IN",
    "ks:ks_name":"Bag Begam Shah",
    "ks:ks_pop":0,
    "ks:ks_type":"VILLAGE",
    "ks:ks_uagg_main":0,
    "name:eng_x_preferred":[
        "Bag Begam Shah"
    ],
    "wof:name":"Bag Begam Shah",
    "wof:placetype":"locality",
    "wof:population":0
},
  "geometry": {"coordinates":[83.595646,25.59803],"type":"Point"}
}