{
  "type": "Feature",
  "properties": {
    "iso:country":"IN",
    "ks:ks_name":"Jaitpur",
    "ks:ks_pop":904,
    "ks:ks_type":"HABITATION",
    "name:eng_x_preferred":[
        "Jaitpur"
    ],
    "wof:name":"Jaitpur",
    "wof:placetype":"locality",
    "wof:population":904
},
  "geometry": {"coordinates":[82.118093,26.836369],"type":"Point"}
}