{
  "type": "Feature",
  "properties": {
    "iso:country":"IN",
    "ks:ks_name":"Berasi",
    "ks:ks_pop":1123,
    "ks:ks_type":"HABITATION",
    "name:eng_x_preferred":[
        "Berasi"
    ],
    "wof:name":"Berasi",
    "wof:placetype":"locality",
    "wof:population":1123
},
  "geometry": {"coordinates":[86.08211300000001,23.086191],"type":"Point"}
}