{
  "type": "Feature",
  "properties": {
    "gn:admin1_code":"21.0",
    "gn:admin2_code":"396.0",
    "gn:asciiname":"Kanjakana",
    "gn:country_code":"IN",
    "gn:dem":1107,
    "gn:feature_class":"P",
    "gn:feature_code":"PPL",
    "gn:name":"Kanj\u0101k\u0101na",
    "gn:population":0,
    "gn:timezone":"Asia/Kolkata",
    "iso:country":"IN",
    "ks:ks_alt_nam":"Kanj\u0101k\u0101na",
    "ks:ks_name":"Kanjakana",
    "ks:ks_type":"VILLAGE",
    "name:eng_x_preferred":[
        "Kanjakana"
    ],
    "name:eng_x_variant":[
        "Kanj\u0101k\u0101na"
    ],
    "wof:name":"Kanjakana",
    "wof:placetype":"locality"
},
  "geometry": {"coordinates":[83.143522,19.298663],"type":"Point"}
}