{
  "type": "Feature",
  "properties": {
    "iso:country":"IN",
    "ks:ks_name":"Dadadamaha",
    "ks:ks_pop":52,
    "ks:ks_type":"VILLAGE",
    "name:eng_x_preferred":[
        "Dadadamaha"
    ],
    "wof:name":"Dadadamaha",
    "wof:placetype":"locality",
    "wof:population":52
},
  "geometry": {"coordinates":[84.404979,20.214392],"type":"Point"}
}