{
  "type": "Feature",
  "properties": {
    "gn:admin1_code":"21.0",
    "gn:admin2_code":"398.0",
    "gn:asciiname":"Turiavalasa",
    "gn:country_code":"IN",
    "gn:dem":982,
    "gn:feature_class":"P",
    "gn:feature_code":"PPL",
    "gn:name":"Turiavalasa",
    "gn:population":0,
    "gn:timezone":"Asia/Kolkata",
    "iso:country":"IN",
    "wof:name":"Turiavalasa",
    "wof:placetype":"locality"
},
  "geometry": {"coordinates":[82.99325999999998,18.63481],"type":"Point"}
}