{
  "type": "Feature",
  "properties": {
    "iso:country":"IN",
    "ks:ks_name":"Selapara",
    "ks:ks_pop":525,
    "ks:ks_type":"HABITATION",
    "name:eng_x_preferred":[
        "Selapara"
    ],
    "wof:name":"Selapara",
    "wof:placetype":"locality",
    "wof:population":525
},
  "geometry": {"coordinates":[90.616072,25.971809],"type":"Point"}
}