{
  "type": "Feature",
  "properties": {
    "gn:admin1_code":"19.0",
    "gn:admin2_code":"563.0",
    "gn:asciiname":"Hosgadde",
    "gn:country_code":"IN",
    "gn:dem":447,
    "gn:feature_class":"P",
    "gn:feature_code":"PPL",
    "gn:name":"Hosgadde",
    "gn:population":0,
    "gn:timezone":"Asia/Kolkata",
    "iso:country":"IN",
    "wof:name":"Hosgadde",
    "wof:placetype":"locality"
},
  "geometry": {"coordinates":[74.53879999999999,14.86593],"type":"Point"}
}