{
  "type": "Feature",
  "properties": {
    "iso:country":"IN",
    "ks:ks_name":"Singanahally",
    "ks:ks_pop":260,
    "ks:ks_type":"HABITATION",
    "name:eng_x_preferred":[
        "Singanahally"
    ],
    "wof:name":"Singanahally",
    "wof:placetype":"locality",
    "wof:population":260
},
  "geometry": {"coordinates":[76.259,12.962],"type":"Point"}
}