{
  "type": "Feature",
  "properties": {
    "gn:admin1_code":"25",
    "gn:admin2_code":"628.0",
    "gn:asciiname":"Vikramasingapuram",
    "gn:country_code":"IN",
    "gn:dem":88,
    "gn:feature_class":"P",
    "gn:feature_code":"PPL",
    "gn:name":"Vikramasingapuram",
    "gn:population":0,
    "gn:timezone":"Asia/Kolkata",
    "iso:country":"IN",
    "wof:name":"Vikramasingapuram",
    "wof:placetype":"locality"
},
  "geometry": {"coordinates":[77.39031999999997,8.71477],"type":"Point"}
}