{
  "type": "Feature",
  "properties": {
    "gn:admin1_code":"25",
    "gn:admin2_code":"628.0",
    "gn:asciiname":"Vikramasingapuram",
    "gn:country_code":"IN",
    "gn:dem":88,
    "gn:feature_class":"P",
    "gn:feature_code":"PPL",
    "gn:name":"Vikramasingapuram",
    "gn:population":0,
    "gn:timezone":"Asia/Kolkata",
    "iso:country":"IN",
    "name:bpy_x_preferred":[
        "\u09ac\u09bf\u0995\u09cd\u09b0\u09ae\u09b8\u09bf\u0982\u09b9\u09aa\u09c1\u09b0\u09ae"
    ],
    "name:hif_x_preferred":[
        "Vikramasingapuram"
    ],
    "name:ita_x_preferred":[
        "Vikramasingapuram"
    ],
    "name:msa_x_preferred":[
        "Vikramasingapuram"
    ],
    "name:new_x_preferred":[
        "\u0935\u093f\u0915\u094d\u0930\u092e\u0938\u093f\u0902\u0939\u092a\u0941\u0930\u092e\u094d"
    ],
    "name:nld_x_preferred":[
        "Vikramasingapuram"
    ],
    "name:por_x_preferred":[
        "Vikramasingapuram"
    ],
    "name:tam_x_preferred":[
        "\u0bb5\u0bbf\u0b95\u0bcd\u0b95\u0bbf\u0bb0\u0bae\u0b9a\u0bbf\u0b99\u0bcd\u0b95\u0baa\u0bc1\u0bb0\u0bae\u0bcd"
    ],
    "name:urd_x_preferred":[
        "\u0648\u06a9\u0631\u0645\u0627\u0633\u06cc\u0646\u06af\u0627\u067e\u0648\u0631\u0645"
    ],
    "name:vie_x_preferred":[
        "Vikramasingapuram"
    ],
    "name:zho_x_preferred":[
        "\u7ef4\u514b\u62c9\u9a6c\u8f9b\u683c\u963f\u666e\u62c9\u59c6"
    ],
    "wof:name":"Vikramasingapuram",
    "wof:placetype":"locality"
},
  "geometry": {"coordinates":[77.39031999999997,8.71477],"type":"Point"}
}