{
  "type": "Feature",
  "properties": {
    "iso:country":"IN",
    "ks:ks_alt_nam":"Phadatare tota",
    "ks:ks_name":"Phadatare Tota",
    "ks:ks_pop":193,
    "ks:ks_type":"HABITATION",
    "name:eng_x_preferred":[
        "Phadatare Tota"
    ],
    "wof:name":"Phadatare Tota",
    "wof:placetype":"locality",
    "wof:population":193
},
  "geometry": {"coordinates":[75.296403,16.821118],"type":"Point"}
}