{
  "type": "Feature",
  "properties": {
    "iso:country":"IN",
    "ks:ks_name":"Basudebpur",
    "ks:ks_pop":466,
    "ks:ks_type":"VILLAGE",
    "name:eng_x_preferred":[
        "Basudebpur"
    ],
    "wof:name":"Basudebpur",
    "wof:placetype":"locality",
    "wof:population":466
},
  "geometry": {"coordinates":[88.11236599999999,22.26702],"type":"Point"}
}