{
  "type": "Feature",
  "properties": {
    "iso:country":"IN",
    "ks:ks_name":"Dubballa",
    "ks:ks_pop":57,
    "ks:ks_type":"HABITATION",
    "name:eng_x_preferred":[
        "Dubballa"
    ],
    "wof:name":"Dubballa",
    "wof:placetype":"locality",
    "wof:population":57
},
  "geometry": {"coordinates":[78.865694,17.177036],"type":"Point"}
}