{
  "type": "Feature",
  "properties": {
    "gn:admin1_code":"35",
    "gn:admin2_code":"459.0",
    "gn:asciiname":"Gurha",
    "gn:country_code":"IN",
    "gn:dem":394,
    "gn:feature_class":"P",
    "gn:feature_code":"PPL",
    "gn:name":"Gurha",
    "gn:population":0,
    "gn:timezone":"Asia/Kolkata",
    "iso:country":"IN",
    "ks:ks_name":"Gurha",
    "ks:ks_type":"VILLAGE",
    "name:eng_x_preferred":[
        "Gurha"
    ],
    "wof:name":"Gurha",
    "wof:placetype":"locality"
},
  "geometry": {"coordinates":[78.17946000000001,24.534867],"type":"Point"}
}