{
  "type": "Feature",
  "properties": {
    "gn:admin1_code":"25.0",
    "gn:admin2_code":"618.0",
    "gn:asciiname":"Kalasapadi",
    "gn:country_code":"IN",
    "gn:dem":4,
    "gn:feature_class":"P",
    "gn:feature_code":"PPL",
    "gn:name":"Kalasap\u0101di",
    "gn:population":0,
    "gn:timezone":"Asia/Kolkata",
    "iso:country":"IN",
    "wof:name":"Kalasapadi",
    "wof:placetype":"locality"
},
  "geometry": {"coordinates":[79.79094000000001,10.71071],"type":"Point"}
}