{
  "type": "Feature",
  "properties": {
    "gn:admin1_code":"25.0",
    "gn:admin2_code":"618.0",
    "gn:asciiname":"Kalasapadi",
    "gn:country_code":"IN",
    "gn:dem":4,
    "gn:feature_class":"P",
    "gn:feature_code":"PPL",
    "gn:name":"Kalasap\u0101di",
    "gn:population":0,
    "gn:timezone":"Asia/Kolkata",
    "iso:country":"IN",
    "ks:ks_name":"Kalasambadi",
    "ks:ks_pop":194,
    "ks:ks_type":"HABITATION",
    "name:eng_x_preferred":[
        "Kalasambadi"
    ],
    "name:eng_x_variant":[
        "Kalasapadi"
    ],
    "wof:name":"Kalasambadi",
    "wof:placetype":"locality",
    "wof:population":194
},
  "geometry": {"coordinates":[79.788928,10.711235],"type":"Point"}
}