{
  "type": "Feature",
  "properties": {
    "gn:admin1_code":"13.0",
    "gn:admin2_code":"594.0",
    "gn:asciiname":"Poyya",
    "gn:country_code":"IN",
    "gn:dem":19,
    "gn:feature_class":"P",
    "gn:feature_code":"PPL",
    "gn:name":"Poyya",
    "gn:population":0,
    "gn:timezone":"Asia/Kolkata",
    "iso:country":"IN",
    "name:mal_x_preferred":[
        "\u0d2a\u0d4a\u0d2f\u0d4d\u0d2f"
    ],
    "name:msa_x_preferred":[
        "Poyya"
    ],
    "wof:name":"Poyya",
    "wof:placetype":"locality"
},
  "geometry": {"coordinates":[76.25508000000001,10.20989],"type":"Point"}
}