{
  "type": "Feature",
  "properties": {
    "iso:country":"IN",
    "ks:ks_name":"Kalayanapuram I Sethi",
    "ks:ks_pop":4795,
    "ks:ks_type":"VILLAGE",
    "ks:ks_uagg_main":0,
    "name:eng_x_preferred":[
        "Kalayanapuram I Sethi"
    ],
    "wof:name":"Kalayanapuram I Sethi",
    "wof:placetype":"neighbourhood",
    "wof:population":4795
},
  "geometry": {"coordinates":[79.118692,10.871248],"type":"Point"}
}