{
  "type": "Feature",
  "properties": {
    "iso:country":"IN",
    "ks:ks_alt_nam":"LOHIYA PURWA",
    "ks:ks_name":"Lohiya Purwa",
    "ks:ks_pop":65,
    "ks:ks_type":"HABITATION",
    "name:eng_x_preferred":[
        "Lohiya Purwa"
    ],
    "wof:name":"Lohiya Purwa",
    "wof:placetype":"locality",
    "wof:population":65
},
  "geometry": {"coordinates":[81.261673,28.108907],"type":"Point"}
}