{
  "type": "Feature",
  "properties": {
    "iso:country":"IN",
    "ks:ks_name":"Chotang Parth",
    "ks:ks_pop":250,
    "ks:ks_type":"HABITATION",
    "name:eng_x_preferred":[
        "Chotang Parth"
    ],
    "wof:name":"Chotang Parth",
    "wof:placetype":"locality",
    "wof:population":250
},
  "geometry": {"coordinates":[84.317498,23.304008],"type":"Point"}
}