{
  "type": "Feature",
  "properties": {
    "iso:country":"IN",
    "ks:ks_name":"Rajabad",
    "ks:ks_pop":88,
    "ks:ks_type":"VILLAGE",
    "name:eng_x_preferred":[
        "Rajabad"
    ],
    "wof:name":"Rajabad",
    "wof:placetype":"locality",
    "wof:population":88
},
  "geometry": {"coordinates":[87.08057100000001,24.531712],"type":"Point"}
}