{
  "type": "Feature",
  "properties": {
    "gn:admin1_code":"36",
    "gn:admin2_code":"186.0",
    "gn:asciiname":"Baidauli",
    "gn:country_code":"IN",
    "gn:dem":85,
    "gn:feature_class":"P",
    "gn:feature_code":"PPL",
    "gn:name":"Baidauli",
    "gn:population":0,
    "gn:timezone":"Asia/Kolkata",
    "iso:country":"IN",
    "name:ceb_x_preferred":[
        "Baidauli"
    ],
    "name:fra_x_preferred":[
        "Baidauli"
    ],
    "name:mai_x_preferred":[
        "\u092c\u0947\u0926\u094c\u0932\u0940"
    ],
    "name:msa_x_preferred":[
        "Baidauli"
    ],
    "name:nep_x_preferred":[
        "\u092c\u0947\u0926\u094c\u0932\u0940"
    ],
    "name:new_x_preferred":[
        "\u092c\u0948\u0926\u094c\u0932\u0940"
    ],
    "name:pol_x_preferred":[
        "Baidauli"
    ],
    "wof:name":"Baidauli",
    "wof:placetype":"locality"
},
  "geometry": {"coordinates":[83.10455,26.85903],"type":"Point"}
}