{
  "type": "Feature",
  "properties": {
    "iso:country":"IN",
    "ks:ks_alt_nam":"JHARIPUR",
    "ks:ks_name":"Jharipur",
    "ks:ks_pop":96,
    "ks:ks_type":"HABITATION",
    "name:eng_x_preferred":[
        "Jharipur"
    ],
    "wof:name":"Jharipur",
    "wof:placetype":"locality",
    "wof:population":96
},
  "geometry": {"coordinates":[85.8664,24.0451],"type":"Point"}
}