{
  "type": "Feature",
  "properties": {
    "iso:country":"IN",
    "ks:ks_name":"Pillivarilanka",
    "ks:ks_pop":169,
    "ks:ks_type":"HABITATION",
    "name:eng_x_preferred":[
        "Pillivarilanka"
    ],
    "wof:name":"Pillivarilanka",
    "wof:placetype":"locality",
    "wof:population":169
},
  "geometry": {"coordinates":[80.79058999999999,16.324051],"type":"Point"}
}