{
  "type": "Feature",
  "properties": {
    "iso:country":"IN",
    "ks:ks_name":"Bankari",
    "ks:ks_pop":148,
    "ks:ks_type":"HABITATION",
    "name:eng_x_preferred":[
        "Bankari"
    ],
    "wof:name":"Bankari",
    "wof:placetype":"locality",
    "wof:population":148
},
  "geometry": {"coordinates":[82.95674200000001,27.146424],"type":"Point"}
}