{
  "type": "Feature",
  "properties": {
    "iso:country":"IN",
    "ks:ks_alt_nam":"HARINCHATWA",
    "ks:ks_name":"Harinchatwa",
    "ks:ks_pop":205,
    "ks:ks_type":"HABITATION",
    "name:eng_x_preferred":[
        "Harinchatwa"
    ],
    "wof:name":"Harinchatwa",
    "wof:placetype":"locality",
    "wof:population":205
},
  "geometry": {"coordinates":[84.761039,24.496134],"type":"Point"}
}