{
  "type": "Feature",
  "properties": {
    "iso:country":"IN",
    "ks:ks_alt_nam":"PAL BASTI",
    "ks:ks_name":"Pal Basti",
    "ks:ks_pop":81,
    "ks:ks_type":"HABITATION",
    "name:eng_x_preferred":[
        "Pal Basti"
    ],
    "wof:name":"Pal Basti",
    "wof:placetype":"locality",
    "wof:population":81
},
  "geometry": {"coordinates":[82.211217,26.203465],"type":"Point"}
}