{
  "type": "Feature",
  "properties": {
    "iso:country":"IN",
    "ks:ks_name":"Kumari",
    "ks:ks_pop":282,
    "ks:ks_type":"VILLAGE",
    "name:eng_x_preferred":[
        "Kumari"
    ],
    "wof:name":"Kumari",
    "wof:placetype":"locality",
    "wof:population":282
},
  "geometry": {"coordinates":[86.01651,23.045082],"type":"Point"}
}