{
  "type": "Feature",
  "properties": {
    "gn:admin1_code":"34.0",
    "gn:admin2_code":"232.0",
    "gn:asciiname":"Bhagwatpur",
    "gn:country_code":"IN",
    "gn:dem":76,
    "gn:feature_class":"P",
    "gn:feature_code":"PPL",
    "gn:name":"Bhagwatpur",
    "gn:population":0,
    "gn:timezone":"Asia/Kolkata",
    "iso:country":"IN",
    "wof:name":"Bhagwatpur",
    "wof:placetype":"locality"
},
  "geometry": {"coordinates":[84.24252,25.45236],"type":"Point"}
}