{
  "type": "Feature",
  "properties": {
    "iso:country":"IN",
    "ks:ks_name":"Koilnaickanpatti",
    "ks:ks_pop":577,
    "ks:ks_type":"HABITATION",
    "name:eng_x_preferred":[
        "Koilnaickanpatti"
    ],
    "wof:name":"Koilnaickanpatti",
    "wof:placetype":"locality",
    "wof:population":577
},
  "geometry": {"coordinates":[78.42282400000001,12.229532],"type":"Point"}
}