{
  "type": "Feature",
  "properties": {
    "iso:country":"IN",
    "ks:ks_name":"Irattaikulam",
    "ks:ks_pop":362,
    "ks:ks_type":"HABITATION",
    "name:eng_x_preferred":[
        "Irattaikulam"
    ],
    "wof:name":"Irattaikulam",
    "wof:placetype":"locality",
    "wof:population":362
},
  "geometry": {"coordinates":[78.26737199999999,9.722894],"type":"Point"}
}