{
  "type": "Feature",
  "properties": {
    "iso:country":"IN",
    "ks:ks_name":"9 STG",
    "ks:ks_pop":375,
    "ks:ks_type":"VILLAGE",
    "name:eng_x_preferred":[
        "9 STG"
    ],
    "wof:name":"9 STG",
    "wof:placetype":"locality",
    "wof:population":375
},
  "geometry": {"coordinates":[74.19815,29.544528],"type":"Point"}
}