{
  "type": "Feature",
  "properties": {
    "iso:country":"IN",
    "ks:ks_name":"Maharajpurhill",
    "ks:ks_pop":46,
    "ks:ks_type":"VILLAGE",
    "name:eng_x_preferred":[
        "Maharajpurhill"
    ],
    "wof:name":"Maharajpurhill",
    "wof:placetype":"locality",
    "wof:population":46
},
  "geometry": {"coordinates":[86.104021,22.005345],"type":"Point"}
}