{
  "type": "Feature",
  "properties": {
    "iso:country":"IN",
    "ks:ks_name":"Tangarpasi",
    "ks:ks_pop":63,
    "ks:ks_type":"VILLAGE",
    "name:eng_x_preferred":[
        "Tangarpasi"
    ],
    "wof:name":"Tangarpasi",
    "wof:placetype":"locality",
    "wof:population":63
},
  "geometry": {"coordinates":[85.765241,21.360377],"type":"Point"}
}