{
  "type": "Feature",
  "properties": {
    "iso:country":"IN",
    "ks:ks_name":"Padiaposi",
    "ks:ks_pop":691,
    "ks:ks_type":"VILLAGE",
    "name:eng_x_preferred":[
        "Padiaposi"
    ],
    "wof:name":"Padiaposi",
    "wof:placetype":"locality",
    "wof:population":691
},
  "geometry": {"coordinates":[85.508636,21.193312],"type":"Point"}
}