{
  "type": "Feature",
  "properties": {
    "gn:admin1_code":"36",
    "gn:admin2_code":"185.0",
    "gn:asciiname":"Kandhaipur",
    "gn:country_code":"IN",
    "gn:dem":93,
    "gn:feature_class":"P",
    "gn:feature_code":"PPL",
    "gn:name":"Kandhaipur",
    "gn:population":0,
    "gn:timezone":"Asia/Kolkata",
    "iso:country":"IN",
    "ks:ks_name":"Kandhaipur",
    "ks:ks_pop":208,
    "ks:ks_type":"VILLAGE",
    "ks:ks_uagg_main":0,
    "name:eng_x_preferred":[
        "Kandhaipur"
    ],
    "wof:name":"Kandhaipur",
    "wof:placetype":"neighbourhood",
    "wof:population":208
},
  "geometry": {"coordinates":[82.301394,26.768396],"type":"Point"}
}