{
  "type": "Feature",
  "properties": {
    "gn:admin1_code":"9.0",
    "gn:admin2_code":"472.0",
    "gn:asciiname":"Nawanagar",
    "gn:country_code":"IN",
    "gn:dem":107,
    "gn:feature_class":"P",
    "gn:feature_code":"PPL",
    "gn:name":"Naw\u0101nagar",
    "gn:population":0,
    "gn:timezone":"Asia/Kolkata",
    "iso:country":"IN",
    "name:hin_x_preferred":[
        "\u0928\u0935\u093e\u0928\u0917\u0930"
    ],
    "wof:name":"Nawanagar",
    "wof:placetype":"locality"
},
  "geometry": {"coordinates":[73.09805,23.24414],"type":"Point"}
}