{
  "type": "Feature",
  "properties": {
    "iso:country":"IN",
    "ks:ks_alt_nam":"Bajit pur Dakshin",
    "ks:ks_name":"Bajit Pur Dakshin",
    "ks:ks_pop":508,
    "ks:ks_type":"HABITATION",
    "name:eng_x_preferred":[
        "Bajit Pur Dakshin"
    ],
    "wof:name":"Bajit Pur Dakshin",
    "wof:placetype":"locality",
    "wof:population":508
},
  "geometry": {"coordinates":[88.92372,23.17923],"type":"Point"}
}