{
  "type": "Feature",
  "properties": {
    "iso:country":"IN",
    "ks:ks_name":"Kendugura",
    "ks:ks_pop":357,
    "ks:ks_type":"VILLAGE",
    "name:eng_x_preferred":[
        "Kendugura"
    ],
    "wof:name":"Kendugura",
    "wof:placetype":"locality",
    "wof:population":357
},
  "geometry": {"coordinates":[83.824245,20.489475],"type":"Point"}
}