{
  "type": "Feature",
  "properties": {
    "iso:country":"IN",
    "ks:ks_name":"Langchingbar",
    "ks:ks_pop":43,
    "ks:ks_type":"HABITATION",
    "name:eng_x_preferred":[
        "Langchingbar"
    ],
    "wof:name":"Langchingbar",
    "wof:placetype":"locality",
    "wof:population":43
},
  "geometry": {"coordinates":[92.627358,25.948654],"type":"Point"}
}