{
  "type": "Feature",
  "properties": {
    "iso:country":"IN",
    "ks:ks_name":"Kanawas",
    "ks:ks_pop":31,
    "ks:ks_type":"VILLAGE",
    "name:eng_x_preferred":[
        "Kanawas"
    ],
    "wof:name":"Kanawas",
    "wof:placetype":"locality",
    "wof:population":31
},
  "geometry": {"coordinates":[72.357946,26.039102],"type":"Point"}
}