{
  "type": "Feature",
  "properties": {
    "gn:admin1_code":"13.0",
    "gn:admin2_code":"600.0",
    "gn:asciiname":"Pulimad",
    "gn:country_code":"IN",
    "gn:dem":11,
    "gn:feature_class":"P",
    "gn:feature_code":"PPL",
    "gn:name":"Pulim\u0101d",
    "gn:population":0,
    "gn:timezone":"Asia/Kolkata",
    "iso:country":"IN",
    "wof:name":"Pulimad",
    "wof:placetype":"locality"
},
  "geometry": {"coordinates":[76.55707,8.94976],"type":"Point"}
}