{
  "type": "Feature",
  "properties": {
    "iso:country":"IN",
    "ks:ks_name":"Musalmanwadi",
    "ks:ks_pop":256,
    "ks:ks_type":"VILLAGE",
    "ks:ks_uagg_main":0,
    "name:eng_x_preferred":[
        "Musalmanwadi"
    ],
    "wof:name":"Musalmanwadi",
    "wof:placetype":"neighbourhood",
    "wof:population":256
},
  "geometry": {"coordinates":[74.01333099999999,16.645042],"type":"Point"}
}