{
  "type": "Feature",
  "properties": {
    "gn:admin1_code":"25.0",
    "gn:admin2_code":"633.0",
    "gn:asciiname":"Kongalnagaram Pudur",
    "gn:country_code":"IN",
    "gn:dem":375,
    "gn:feature_class":"P",
    "gn:feature_code":"PPL",
    "gn:name":"Kongalnagaram Pud\u016br",
    "gn:population":0,
    "gn:timezone":"Asia/Kolkata",
    "iso:country":"IN",
    "wof:name":"Kongalnagaram Pudur",
    "wof:placetype":"locality"
},
  "geometry": {"coordinates":[77.18770000000001,10.68037],"type":"Point"}
}