{
  "type": "Feature",
  "properties": {
    "iso:country":"IN",
    "ks:ks_alt_nam":"CHAKUR",
    "ks:ks_name":"Chakur",
    "ks:ks_pop":740,
    "ks:ks_type":"HABITATION",
    "ks:ks_uagg_main":0,
    "name:eng_x_preferred":[
        "Chakur"
    ],
    "wof:name":"Chakur",
    "wof:placetype":"neighbourhood",
    "wof:population":740
},
  "geometry": {"coordinates":[88.474361,26.771915],"type":"Point"}
}