{
  "type": "Feature",
  "properties": {
    "gn:admin1_code":"35",
    "gn:admin2_code":"456.0",
    "gn:asciiname":"Nawalgaon",
    "gn:country_code":"IN",
    "gn:dem":514,
    "gn:feature_class":"P",
    "gn:feature_code":"PPL",
    "gn:name":"Nawalgaon",
    "gn:population":0,
    "gn:timezone":"Asia/Kolkata",
    "iso:country":"IN",
    "wof:name":"Nawalgaon",
    "wof:placetype":"locality"
},
  "geometry": {"coordinates":[79.62321,22.36642],"type":"Point"}
}