{
  "type": "Feature",
  "properties": {
    "iso:country":"IN",
    "ks:ks_name":"Moltha",
    "ks:ks_pop":44,
    "ks:ks_type":"VILLAGE",
    "name:eng_x_preferred":[
        "Moltha"
    ],
    "wof:name":"Moltha",
    "wof:placetype":"locality",
    "wof:population":44
},
  "geometry": {"coordinates":[78.867755,30.106693],"type":"Point"}
}