{
  "type": "Feature",
  "properties": {
    "iso:country":"IN",
    "ks:ks_name":"Doyyaguda",
    "ks:ks_pop":32,
    "ks:ks_type":"HABITATION",
    "name:eng_x_preferred":[
        "Doyyaguda"
    ],
    "wof:name":"Doyyaguda",
    "wof:placetype":"locality",
    "wof:population":32
},
  "geometry": {"coordinates":[83.662869,19.004806],"type":"Point"}
}