{
  "type": "Feature",
  "properties": {
    "iso:country":"IN",
    "ks:ks_name":"Syli Tea Garden",
    "ks:ks_pop":4494,
    "ks:ks_type":"VILLAGE",
    "ks:ks_uagg_main":0,
    "name:eng_x_preferred":[
        "Syli Tea Garden"
    ],
    "wof:name":"Syli Tea Garden",
    "wof:placetype":"neighbourhood",
    "wof:population":4494
},
  "geometry": {"coordinates":[88.6739,26.889053],"type":"Point"}
}