{
  "type": "Feature",
  "properties": {
    "gn:admin1_code":"34.0",
    "gn:admin2_code":"211.0",
    "gn:asciiname":"Pothia",
    "gn:country_code":"IN",
    "gn:dem":48,
    "gn:feature_class":"P",
    "gn:feature_code":"PPL",
    "gn:name":"Pothia",
    "gn:population":0,
    "gn:timezone":"Asia/Kolkata",
    "iso:country":"IN",
    "name:ces_x_preferred":[
        "Pothia"
    ],
    "name:ell_x_preferred":[
        "\u03a0\u03cc\u03b8\u03b9\u03b1"
    ],
    "name:fin_x_preferred":[
        "P\u00f3thia"
    ],
    "name:fra_x_preferred":[
        "Pothia"
    ],
    "name:nld_x_preferred":[
        "Pothia"
    ],
    "name:srp_x_preferred":[
        "\u041f\u043e\u0442\u0438\u0458\u0430"
    ],
    "name:swe_x_preferred":[
        "Pothia"
    ],
    "wof:name":"Pothia",
    "wof:placetype":"locality"
},
  "geometry": {"coordinates":[87.61662,25.9156],"type":"Point"}
}