{
  "type": "Feature",
  "properties": {
    "iso:country":"IN",
    "ks:ks_name":"Thar Divansingh",
    "ks:ks_pop":57,
    "ks:ks_type":"HABITATION",
    "name:eng_x_preferred":[
        "Thar Divansingh"
    ],
    "wof:name":"Thar Divansingh",
    "wof:placetype":"locality",
    "wof:population":57
},
  "geometry": {"coordinates":[78.421013,27.04762],"type":"Point"}
}