{
  "type": "Feature",
  "properties": {
    "iso:country":"IN",
    "qs:name":"Bantara",
    "qs:name_adm0":"India",
    "qs:name_adm1":"West Bengal",
    "qs:photos":6,
    "qs:photos_1k":1,
    "qs:photos_9k":1,
    "qs:photos_9r":1,
    "qs:photos_all":6,
    "qs:photos_sr":1,
    "qs:placetype":"Suburb",
    "qs:pop_sr":"0",
    "wof:name":"Bantara",
    "wof:placetype":"neighbourhood"
},
  "geometry": {"coordinates":[88.325958,22.574706],"type":"Point"}
}