{
  "type": "Feature",
  "properties": {
    "iso:country":"IN",
    "name:ara_x_preferred":[
        "\u0628\u0627\u0646\u062a\u0631\u0627"
    ],
    "name:ben_bn_x_preferred":[
        "\u09ac\u09be\u09a8\u09a4\u09be\u09b0\u09be"
    ],
    "name:ben_in_x_preferred":[
        "\u09ac\u09be\u09a8\u09a4\u09be\u09b0\u09be"
    ],
    "name:guj_x_preferred":[
        "\u0aac\u0a82\u0aa4\u0abe\u0ab0\u0abe"
    ],
    "name:hin_x_preferred":[
        "\u092c\u093e\u0902\u0924\u0930\u093e"
    ],
    "name:kan_x_preferred":[
        "\u0cac\u0c82\u0ca4\u0cbe\u0cb0\u0cbe"
    ],
    "name:mal_x_preferred":[
        "\u0d2c\u0d28\u0d4d\u0d24\u0d3e\u0d30"
    ],
    "name:mar_x_preferred":[
        "\u092c\u0902\u091f\u093e\u0930\u093e"
    ],
    "name:pan_x_preferred":[
        "\u0a2c\u0a28\u0a1f\u0a3e\u0a30\u0a3e"
    ],
    "name:tam_x_preferred":[
        "\u0baa\u0ba8\u0bcd\u0ba4\u0bb0\u0bbe"
    ],
    "name:tel_x_preferred":[
        "\u0c2c\u0c02\u0c1f\u0c3e\u0c30\u0c3e"
    ],
    "name:urd_x_preferred":[
        "\u0628\u0646\u062a\u0627\u0631\u0627"
    ],
    "qs:name":"Bantara",
    "qs:name_adm0":"India",
    "qs:name_adm1":"West Bengal",
    "qs:photos":6,
    "qs:photos_1k":1,
    "qs:photos_9k":1,
    "qs:photos_9r":1,
    "qs:photos_all":6,
    "qs:photos_sr":1,
    "qs:placetype":"Suburb",
    "qs:pop_sr":"0",
    "wof:name":"Bantara",
    "wof:placetype":"neighbourhood"
},
  "geometry": {"coordinates":[88.325958,22.574706],"type":"Point"}
}