{
  "type": "Feature",
  "properties": {
    "iso:country":"IN",
    "ks:ks_name":"Vellamthadam Jn",
    "ks:ks_pop":1315,
    "ks:ks_type":"HABITATION",
    "name:eng_x_preferred":[
        "Vellamthadam Jn"
    ],
    "wof:name":"Vellamthadam Jn",
    "wof:placetype":"locality",
    "wof:population":1315
},
  "geometry": {"coordinates":[76.53990899999999,9.947824],"type":"Point"}
}