{
  "type": "Feature",
  "properties": {
    "iso:country":"IN",
    "ks:ks_alt_nam":"Pump house  Horsili Hills",
    "ks:ks_name":"Pump House Horsili Hills",
    "ks:ks_pop":9,
    "ks:ks_type":"HABITATION",
    "ks:ks_uagg_main":0,
    "name:eng_x_preferred":[
        "Pump House Horsili Hills"
    ],
    "name:eng_x_variant":[
        "Pump house  Horsili Hills"
    ],
    "wof:name":"Pump House Horsili Hills",
    "wof:placetype":"neighbourhood",
    "wof:population":9
},
  "geometry": {"coordinates":[78.44577099999999,13.642118],"type":"Point"}
}