{
  "type": "Feature",
  "properties": {
    "gn:admin1_code":"35.0",
    "gn:admin2_code":"455.0",
    "gn:asciiname":"Koramau",
    "gn:country_code":"IN",
    "gn:dem":701,
    "gn:feature_class":"P",
    "gn:feature_code":"PPL",
    "gn:name":"Kor\u0101mau",
    "gn:population":0,
    "gn:timezone":"Asia/Kolkata",
    "iso:country":"IN",
    "ks:ks_name":"Kodamau",
    "ks:ks_pop":791,
    "ks:ks_type":"VILLAGE",
    "name:eng_x_preferred":[
        "Kodamau"
    ],
    "name:eng_x_variant":[
        "Koramau"
    ],
    "wof:name":"Kodamau",
    "wof:placetype":"locality",
    "wof:population":791
},
  "geometry": {"coordinates":[78.8698,21.958275],"type":"Point"}
}