{
  "type": "Feature",
  "properties": {
    "gn:admin1_code":"12.0",
    "gn:admin2_code":"7.0",
    "gn:asciiname":"Dankhun",
    "gn:country_code":"IN",
    "gn:dem":1860,
    "gn:feature_class":"P",
    "gn:feature_code":"PPL",
    "gn:name":"Dankhun",
    "gn:population":0,
    "gn:timezone":"Asia/Kolkata",
    "iso:country":"IN",
    "wof:name":"Dankhun",
    "wof:placetype":"locality"
},
  "geometry": {"coordinates":[75.63545000000001,32.72763],"type":"Point"}
}