{
  "type": "Feature",
  "properties": {
    "iso:country":"IN",
    "ks:ks_name":"Dhurwamore",
    "ks:ks_pop":298,
    "ks:ks_type":"HABITATION",
    "name:eng_x_preferred":[
        "Dhurwamore"
    ],
    "wof:name":"Dhurwamore",
    "wof:placetype":"locality",
    "wof:population":298
},
  "geometry": {"coordinates":[84.955697,23.65762],"type":"Point"}
}