{
  "type": "Feature",
  "properties": {
    "gn:admin1_code":"35",
    "gn:admin2_code":"430.0",
    "gn:asciiname":"Baisanpurwa",
    "gn:country_code":"IN",
    "gn:dem":125,
    "gn:feature_class":"P",
    "gn:feature_code":"PPL",
    "gn:name":"Baisanpurwa",
    "gn:population":0,
    "gn:timezone":"Asia/Kolkata",
    "iso:country":"IN",
    "ks:ks_name":"Baisanpurwa",
    "ks:ks_pop":240,
    "ks:ks_type":"HABITATION",
    "name:eng_x_preferred":[
        "Baisanpurwa"
    ],
    "wof:name":"Baisanpurwa",
    "wof:placetype":"locality",
    "wof:population":240
},
  "geometry": {"coordinates":[81.40379900000001,24.982892],"type":"Point"}
}