{
  "type": "Feature",
  "properties": {
    "iso:country":"IN",
    "ks:ks_name":"Khakhaswakoni",
    "ks:ks_pop":3,
    "ks:ks_type":"VILLAGE",
    "name:eng_x_preferred":[
        "Khakhaswakoni"
    ],
    "wof:name":"Khakhaswakoni",
    "wof:placetype":"locality",
    "wof:population":3
},
  "geometry": {"coordinates":[85.8905,24.59745],"type":"Point"}
}