{
  "type": "Feature",
  "properties": {
    "gn:admin1_code":"19.0",
    "gn:admin2_code":"577.0",
    "gn:asciiname":"Galavina Attikuppe",
    "gn:country_code":"IN",
    "gn:dem":837,
    "gn:feature_class":"P",
    "gn:feature_code":"PPL",
    "gn:name":"Galavina Attikuppe",
    "gn:population":0,
    "gn:timezone":"Asia/Kolkata",
    "iso:country":"IN",
    "wof:name":"Galavina Attikuppe",
    "wof:placetype":"locality"
},
  "geometry": {"coordinates":[76.33929000000001,12.63603],"type":"Point"}
}