{
  "type": "Feature",
  "properties": {
    "iso:country":"IN",
    "ks:ks_name":"Kolahera",
    "ks:ks_pop":951,
    "ks:ks_type":"VILLAGE",
    "name:eng_x_preferred":[
        "Kolahera"
    ],
    "wof:name":"Kolahera",
    "wof:placetype":"locality",
    "wof:population":951
},
  "geometry": {"coordinates":[75.968158,25.725061],"type":"Point"}
}