{
  "type": "Feature",
  "properties": {
    "iso:country":"IN",
    "ks:ks_name":"Chikkaluvara",
    "ks:ks_pop":785,
    "ks:ks_type":"HABITATION",
    "name:eng_x_preferred":[
        "Chikkaluvara"
    ],
    "wof:name":"Chikkaluvara",
    "wof:placetype":"locality",
    "wof:population":785
},
  "geometry": {"coordinates":[75.943611,12.560833],"type":"Point"}
}