{
  "type": "Feature",
  "properties": {
    "gn:admin1_code":"36.0",
    "gn:admin2_code":"151.0",
    "gn:asciiname":"Kureli",
    "gn:country_code":"IN",
    "gn:dem":167,
    "gn:feature_class":"P",
    "gn:feature_code":"PPL",
    "gn:name":"Kureli",
    "gn:population":0,
    "gn:timezone":"Asia/Kolkata",
    "iso:country":"IN",
    "name:ceb_x_preferred":[
        "Kureli"
    ],
    "name:fra_x_preferred":[
        "Kureli"
    ],
    "name:mai_x_preferred":[
        "\u0915\u0941\u0930\u0947\u0932\u0940"
    ],
    "name:msa_x_preferred":[
        "Kureli"
    ],
    "name:nep_x_preferred":[
        "\u0915\u0941\u0930\u0947\u0932\u0940"
    ],
    "name:new_x_preferred":[
        "\u0915\u0941\u0930\u0947\u0932\u0940"
    ],
    "name:pol_x_preferred":[
        "Kureli"
    ],
    "wof:name":"Kureli",
    "wof:placetype":"locality"
},
  "geometry": {"coordinates":[79.90964,28.13901],"type":"Point"}
}