{
  "type": "Feature",
  "properties": {
    "gn:admin1_code":"12.0",
    "gn:admin2_code":"16.0",
    "gn:asciiname":"Mehad",
    "gn:country_code":"IN",
    "gn:dem":3100,
    "gn:feature_class":"P",
    "gn:feature_code":"PPL",
    "gn:name":"Meh\u0101d",
    "gn:population":0,
    "gn:timezone":"Asia/Kolkata",
    "iso:country":"IN",
    "wof:name":"Mehad",
    "wof:placetype":"locality"
},
  "geometry": {"coordinates":[76.06376,33.00092],"type":"Point"}
}