{
  "type": "Feature",
  "properties": {
    "iso:country":"IN",
    "ks:ks_name":"3 RMG",
    "ks:ks_pop":20,
    "ks:ks_type":"VILLAGE",
    "name:eng_x_preferred":[
        "3 RMG"
    ],
    "wof:name":"3 RMG",
    "wof:placetype":"locality",
    "wof:population":20
},
  "geometry": {"coordinates":[74.919338,29.161799],"type":"Point"}
}