{
  "type": "Feature",
  "properties": {
    "gn:admin1_code":"11.0",
    "gn:admin2_code":"32.0",
    "gn:asciiname":"Bakarla",
    "gn:country_code":"IN",
    "gn:dem":662,
    "gn:feature_class":"P",
    "gn:feature_code":"PPL",
    "gn:name":"Bak\u0101rla",
    "gn:population":0,
    "gn:timezone":"Asia/Kolkata",
    "iso:country":"IN",
    "wof:name":"Bakarla",
    "wof:placetype":"locality"
},
  "geometry": {"coordinates":[77.24105,30.5881],"type":"Point"}
}