{
  "type": "Feature",
  "properties": {
    "iso:country":"IN",
    "ks:ks_name":"Harijan Basti m",
    "ks:ks_pop":180,
    "ks:ks_type":"HABITATION",
    "name:eng_x_preferred":[
        "Harijan Basti m"
    ],
    "wof:name":"Harijan Basti m",
    "wof:placetype":"locality",
    "wof:population":180
},
  "geometry": {"coordinates":[82.915902,26.576088],"type":"Point"}
}