{
  "type": "Feature",
  "properties": {
    "gn:admin1_code":"21",
    "gn:admin2_code":"375.0",
    "gn:asciiname":"Sagarpata",
    "gn:country_code":"IN",
    "gn:dem":247,
    "gn:feature_class":"P",
    "gn:feature_code":"PPL",
    "gn:name":"Sagarp\u0101ta",
    "gn:population":0,
    "gn:timezone":"Asia/Kolkata",
    "iso:country":"IN",
    "wof:name":"Sagarpata",
    "wof:placetype":"locality"
},
  "geometry": {"coordinates":[85.91889999999999,21.24909],"type":"Point"}
}