{
  "type": "Feature",
  "properties": {
    "gn:admin1_code":"36.0",
    "gn:admin2_code":"164.0",
    "gn:asciiname":"Samarau",
    "gn:country_code":"IN",
    "gn:dem":123,
    "gn:feature_class":"P",
    "gn:feature_code":"PPL",
    "gn:name":"Samarau",
    "gn:population":0,
    "gn:timezone":"Asia/Kolkata",
    "iso:country":"IN",
    "wof:name":"Samarau",
    "wof:placetype":"locality"
},
  "geometry": {"coordinates":[80.37518,26.28174000000001],"type":"Point"}
}