{
  "type": "Feature",
  "properties": {
    "iso:country":"IN",
    "ks:ks_name":"Moshalpara",
    "ks:ks_pop":224,
    "ks:ks_type":"HABITATION",
    "name:eng_x_preferred":[
        "Moshalpara"
    ],
    "wof:name":"Moshalpara",
    "wof:placetype":"locality",
    "wof:population":224
},
  "geometry": {"coordinates":[81.483413,18.44551],"type":"Point"}
}