{
  "type": "Feature",
  "properties": {
    "gn:admin1_code":"12.0",
    "gn:asciiname":"Dakhan",
    "gn:country_code":"IN",
    "gn:dem":1574,
    "gn:feature_class":"P",
    "gn:feature_code":"PPL",
    "gn:name":"Dakhan",
    "gn:population":0,
    "gn:timezone":"Asia/Karachi",
    "iso:country":"IN",
    "wof:name":"Dakhan",
    "wof:placetype":"locality"
},
  "geometry": {"coordinates":[73.78248000000001,34.37583],"type":"Point"}
}