{
  "type": "Feature",
  "properties": {
    "gn:admin1_code":"12.0",
    "gn:asciiname":"Dakhan",
    "gn:country_code":"IN",
    "gn:dem":1574,
    "gn:feature_class":"P",
    "gn:feature_code":"PPL",
    "gn:name":"Dakhan",
    "gn:population":0,
    "gn:timezone":"Asia/Karachi",
    "iso:country":"IN",
    "name:ceb_x_preferred":[
        "Dakh\u0101n"
    ],
    "name:fas_x_preferred":[
        "\u062f\u062e\u0627\u0646"
    ],
    "name:swe_x_preferred":[
        "Dakh\u0101n"
    ],
    "name:ukr_x_preferred":[
        "\u0414\u0430\u0445\u0430\u043d"
    ],
    "wof:name":"Dakhan",
    "wof:placetype":"locality"
},
  "geometry": {"coordinates":[73.78248000000001,34.37583],"type":"Point"}
}