{
  "type": "Feature",
  "properties": {
    "iso:country":"IN",
    "ks:ks_name":"Bhanu Dhar Para",
    "ks:ks_pop":106,
    "ks:ks_type":"HABITATION",
    "ks:ks_uagg_main":0,
    "name:eng_x_preferred":[
        "Bhanu Dhar Para"
    ],
    "wof:name":"Bhanu Dhar Para",
    "wof:placetype":"neighbourhood",
    "wof:population":106
},
  "geometry": {"coordinates":[91.98339,24.090239],"type":"Point"}
}