{
  "type": "Feature",
  "properties": {
    "gn:admin1_code":"34.0",
    "gn:admin2_code":"203.0",
    "gn:asciiname":"Tutuhiya",
    "gn:country_code":"IN",
    "gn:dem":93,
    "gn:feature_class":"P",
    "gn:feature_code":"PPL",
    "gn:name":"Tutuhiy\u0101",
    "gn:population":0,
    "gn:timezone":"Asia/Kolkata",
    "iso:country":"IN",
    "ks:ks_name":"Tutuhia",
    "ks:ks_pop":81,
    "ks:ks_type":"VILLAGE",
    "ks:ks_uagg_main":0,
    "name:eng_x_preferred":[
        "Tutuhia"
    ],
    "wof:name":"Tutuhia",
    "wof:placetype":"neighbourhood",
    "wof:population":81
},
  "geometry": {"coordinates":[84.35242599999999,27.100986],"type":"Point"}
}