{
  "type": "Feature",
  "properties": {
    "iso:country":"IN",
    "ks:ks_name":"Aherwasti",
    "ks:ks_pop":113,
    "ks:ks_type":"HABITATION",
    "name:eng_x_preferred":[
        "Aherwasti"
    ],
    "wof:name":"Aherwasti",
    "wof:placetype":"locality",
    "wof:population":113
},
  "geometry": {"coordinates":[74.28987499999999,19.65564],"type":"Point"}
}