{
  "type": "Feature",
  "properties": {
    "gn:admin1_code":"39",
    "gn:admin2_code":"61.0",
    "gn:asciiname":"Kotli",
    "gn:country_code":"IN",
    "gn:dem":1134,
    "gn:feature_class":"P",
    "gn:feature_code":"PPL",
    "gn:name":"Kotli",
    "gn:population":0,
    "gn:timezone":"Asia/Kolkata",
    "iso:country":"IN",
    "name:ben_x_preferred":[
        "\u0995\u09cb\u09a4\u09b2\u09bf"
    ],
    "name:ceb_x_preferred":[
        "Kotli"
    ],
    "name:fas_x_preferred":[
        "\u06a9\u0648\u062a\u0644\u06cc"
    ],
    "name:hin_x_preferred":[
        "\u0915\u094b\u091f\u0932\u0940"
    ],
    "name:ita_x_preferred":[
        "Kotli"
    ],
    "name:lit_x_preferred":[
        "Kotlis"
    ],
    "name:pnb_x_preferred":[
        "\u06a9\u0648\u0679\u0644\u06cc"
    ],
    "name:pol_x_preferred":[
        "Kotli"
    ],
    "name:rus_x_preferred":[
        "\u041a\u043e\u0442\u043b\u0438"
    ],
    "name:urd_x_preferred":[
        "\u06a9\u0648\u0679\u0644\u06cc"
    ],
    "wof:name":"Kotli",
    "wof:placetype":"locality"
},
  "geometry": {"coordinates":[78.86301,30.10791],"type":"Point"}
}