{
  "type": "Feature",
  "properties": {
    "gn:admin1_code":"36",
    "gn:admin2_code":"158.0",
    "gn:asciiname":"Shankar Bakhsh Khera",
    "gn:country_code":"IN",
    "gn:dem":121,
    "gn:feature_class":"P",
    "gn:feature_code":"PPL",
    "gn:name":"Shankar Bakhsh Khera",
    "gn:population":0,
    "gn:timezone":"Asia/Kolkata",
    "iso:country":"IN",
    "wof:name":"Shankar Bakhsh Khera",
    "wof:placetype":"locality"
},
  "geometry": {"coordinates":[80.91831999999999,26.32619],"type":"Point"}
}