{
  "type": "Feature",
  "properties": {
    "iso:country":"IN",
    "ks:ks_name":"Bandharas",
    "ks:ks_pop":478,
    "ks:ks_type":"HABITATION",
    "name:eng_x_preferred":[
        "Bandharas"
    ],
    "wof:name":"Bandharas",
    "wof:placetype":"locality",
    "wof:population":478
},
  "geometry": {"coordinates":[81.594976,19.682384],"type":"Point"}
}