{
  "type": "Feature",
  "properties": {
    "gn:admin1_code":"36.0",
    "gn:admin2_code":"151.0",
    "gn:asciiname":"Nawadia Bisem",
    "gn:country_code":"IN",
    "gn:dem":190,
    "gn:feature_class":"P",
    "gn:feature_code":"PPL",
    "gn:name":"Nawadia Bisem",
    "gn:population":0,
    "gn:timezone":"Asia/Kolkata",
    "iso:country":"IN",
    "ks:ks_name":"Nawadia Bisem",
    "ks:ks_type":"VILLAGE",
    "name:eng_x_preferred":[
        "Nawadia Bisem"
    ],
    "wof:name":"Nawadia Bisem",
    "wof:placetype":"locality"
},
  "geometry": {"coordinates":[79.73462000000001,28.690159],"type":"Point"}
}