{
  "type": "Feature",
  "properties": {
    "gn:admin1_code":"39.0",
    "gn:admin2_code":"64.0",
    "gn:asciiname":"Tyautha",
    "gn:country_code":"IN",
    "gn:dem":1021,
    "gn:feature_class":"P",
    "gn:feature_code":"PPL",
    "gn:name":"Tyautha",
    "gn:population":0,
    "gn:timezone":"Asia/Kolkata",
    "iso:country":"IN",
    "wof:name":"Tyautha",
    "wof:placetype":"locality"
},
  "geometry": {"coordinates":[79.18819000000001,29.85103],"type":"Point"}
}