{
  "type": "Feature",
  "properties": {
    "iso:country":"IN",
    "ks:ks_name":"Lalacha Tanda",
    "ks:ks_pop":105,
    "ks:ks_type":"HABITATION",
    "name:eng_x_preferred":[
        "Lalacha Tanda"
    ],
    "wof:name":"Lalacha Tanda",
    "wof:placetype":"locality",
    "wof:population":105
},
  "geometry": {"coordinates":[75.150391,20.032062],"type":"Point"}
}