{
  "type": "Feature",
  "properties": {
    "iso:country":"IN",
    "ks:ks_alt_nam":"PURANI DHAKNI",
    "ks:ks_name":"Purani Dhakni",
    "ks:ks_pop":155,
    "ks:ks_type":"HABITATION",
    "name:eng_x_preferred":[
        "Purani Dhakni"
    ],
    "wof:name":"Purani Dhakni",
    "wof:placetype":"locality",
    "wof:population":155
},
  "geometry": {"coordinates":[85.58946299999999,24.775464],"type":"Point"}
}