{
  "type": "Feature",
  "properties": {
    "iso:country":"IN",
    "ks:ks_name":"R N Kajra",
    "ks:ks_pop":1020,
    "ks:ks_type":"HABITATION",
    "name:eng_x_preferred":[
        "R N Kajra"
    ],
    "wof:name":"R N Kajra",
    "wof:placetype":"locality",
    "wof:population":1020
},
  "geometry": {"coordinates":[85.82425600000001,26.585394],"type":"Point"}
}