{
  "type": "Feature",
  "properties": {
    "gn:admin1_code":"19.0",
    "gn:admin2_code":"580",
    "gn:asciiname":"Agni",
    "gn:country_code":"IN",
    "gn:dem":476,
    "gn:feature_class":"P",
    "gn:feature_code":"PPL",
    "gn:name":"Agni",
    "gn:population":0,
    "gn:timezone":"Asia/Kolkata",
    "iso:country":"IN",
    "name:ceb_x_preferred":[
        "Agni"
    ],
    "name:fas_x_preferred":[
        "\u0627\u06af\u0646\u06cc"
    ],
    "name:urd_x_preferred":[
        "\u0627\u06af\u0646\u06cc"
    ],
    "name:vie_x_preferred":[
        "Agni"
    ],
    "wof:name":"Agni",
    "wof:placetype":"locality"
},
  "geometry": {"coordinates":[76.46911999999998,16.56413],"type":"Point"}
}