{
  "type": "Feature",
  "properties": {
    "iso:country":"IN",
    "ks:ks_alt_nam":"Tilaiya Kal\u0101n",
    "ks:ks_name":"Tilaiya Kalan",
    "ks:ks_type":"VILLAGE",
    "ks:ks_uagg_main":0,
    "name:eng_x_preferred":[
        "Tilaiya Kalan"
    ],
    "name:eng_x_variant":[
        "Tilaiya Kal\u0101n"
    ],
    "wof:name":"Tilaiya Kalan",
    "wof:placetype":"neighbourhood"
},
  "geometry": {"coordinates":[84.984863,24.486594],"type":"Point"}
}