{
  "type": "Feature",
  "properties": {
    "iso:country":"IN",
    "ks:ks_name":"Hardatdih",
    "ks:ks_pop":546,
    "ks:ks_type":"VILLAGE",
    "ks:ks_uagg_main":0,
    "name:eng_x_preferred":[
        "Hardatdih"
    ],
    "wof:name":"Hardatdih",
    "wof:placetype":"neighbourhood",
    "wof:population":546
},
  "geometry": {"coordinates":[85.96259499999999,24.456355],"type":"Point"}
}