{
  "type": "Feature",
  "properties": {
    "gn:admin1_code":"19",
    "gn:admin2_code":"559.0",
    "gn:asciiname":"Tamalgaddi",
    "gn:country_code":"IN",
    "gn:dem":496,
    "gn:feature_class":"P",
    "gn:feature_code":"PPL",
    "gn:name":"T\u0101malgaddi",
    "gn:population":0,
    "gn:timezone":"Asia/Kolkata",
    "iso:country":"IN",
    "ks:ks_alt_nam":"T\u0101malgaddi",
    "ks:ks_name":"Tamalgaddi",
    "ks:ks_type":"VILLAGE",
    "name:eng_x_preferred":[
        "Tamalgaddi"
    ],
    "name:eng_x_variant":[
        "T\u0101malgaddi"
    ],
    "wof:name":"Tamalgaddi",
    "wof:placetype":"locality"
},
  "geometry": {"coordinates":[76.30408199999999,16.131951],"type":"Point"}
}