{
  "type": "Feature",
  "properties": {
    "gn:admin1_code":"19",
    "gn:admin2_code":"559.0",
    "gn:asciiname":"Tamalgaddi",
    "gn:country_code":"IN",
    "gn:dem":496,
    "gn:feature_class":"P",
    "gn:feature_code":"PPL",
    "gn:name":"T\u0101malgaddi",
    "gn:population":0,
    "gn:timezone":"Asia/Kolkata",
    "iso:country":"IN",
    "wof:name":"Tamalgaddi",
    "wof:placetype":"locality"
},
  "geometry": {"coordinates":[76.30408,16.13195],"type":"Point"}
}