{
  "type": "Feature",
  "properties": {
    "gn:admin1_code":"12",
    "gn:asciiname":"Goli",
    "gn:country_code":"IN",
    "gn:dem":2283,
    "gn:feature_class":"P",
    "gn:feature_code":"PPL",
    "gn:name":"Goli",
    "gn:population":0,
    "gn:timezone":"Asia/Kolkata",
    "iso:country":"IN",
    "name:ceb_x_preferred":[
        "Goli"
    ],
    "name:deu_x_preferred":[
        "Goli"
    ],
    "name:swe_x_preferred":[
        "Goli"
    ],
    "name:ukr_x_preferred":[
        "\u0413\u043e\u043b\u0456"
    ],
    "wof:name":"Goli",
    "wof:placetype":"locality"
},
  "geometry": {"coordinates":[74.05183000000002,34.03288],"type":"Point"}
}