{
  "type": "Feature",
  "properties": {
    "iso:country":"IN",
    "ks:ks_name":"Chinnasekkadu",
    "ks:ks_type":"VILLAGE",
    "ks:ks_uagg_main":0,
    "name:eng_x_preferred":[
        "Chinnasekkadu"
    ],
    "wof:name":"Chinnasekkadu",
    "wof:placetype":"neighbourhood"
},
  "geometry": {"coordinates":[80.257266,13.160892],"type":"Point"}
}