{
  "type": "Feature",
  "properties": {
    "iso:country":"IN",
    "ks:ks_name":"Natineralga Pt 1",
    "ks:ks_pop":348,
    "ks:ks_type":"VILLAGE",
    "name:eng_x_preferred":[
        "Natineralga Pt 1"
    ],
    "wof:name":"Natineralga Pt 1",
    "wof:placetype":"locality",
    "wof:population":348
},
  "geometry": {"coordinates":[89.957317,25.892578],"type":"Point"}
}