{
  "type": "Feature",
  "properties": {
    "gn:admin1_code":"36",
    "gn:admin2_code":"173.0",
    "gn:asciiname":"Kambhit",
    "gn:country_code":"IN",
    "gn:dem":103,
    "gn:feature_class":"P",
    "gn:feature_code":"PPL",
    "gn:name":"Kambh\u012bt",
    "gn:population":0,
    "gn:timezone":"Asia/Kolkata",
    "iso:country":"IN",
    "ks:ks_alt_nam":"Kambh\u012bt",
    "ks:ks_name":"Kambhit",
    "ks:ks_type":"VILLAGE",
    "ks:ks_uagg_main":0,
    "name:eng_x_preferred":[
        "Kambhit"
    ],
    "name:eng_x_variant":[
        "Kambh\u012bt"
    ],
    "wof:name":"Kambhit",
    "wof:placetype":"neighbourhood"
},
  "geometry": {"coordinates":[81.667089,25.874679],"type":"Point"}
}