{
  "type": "Feature",
  "properties": {
    "iso:country":"IN",
    "ks:ks_name":"Gaiwadpada",
    "ks:ks_pop":26,
    "ks:ks_type":"HABITATION",
    "name:eng_x_preferred":[
        "Gaiwadpada"
    ],
    "wof:name":"Gaiwadpada",
    "wof:placetype":"locality",
    "wof:population":26
},
  "geometry": {"coordinates":[72.943623,19.911039],"type":"Point"}
}