{
  "type": "Feature",
  "properties": {
    "gn:admin1_code":"11.0",
    "gn:admin2_code":"033",
    "gn:asciiname":"Dharath",
    "gn:country_code":"IN",
    "gn:dem":1432,
    "gn:feature_class":"P",
    "gn:feature_code":"PPL",
    "gn:name":"Dh\u0101rath",
    "gn:population":0,
    "gn:timezone":"Asia/Kolkata",
    "iso:country":"IN",
    "name:und_x_variant":[
        "Dh\u0101rath",
        "Dh\u0101rat"
    ],
    "wof:name":"Dharath",
    "wof:placetype":"locality"
},
  "geometry": {"coordinates":[77.0805,31.13014],"type":"Point"}
}