{
  "type": "Feature",
  "properties": {
    "iso:country":"IN",
    "ks:ks_name":"Kajke",
    "ks:ks_pop":176,
    "ks:ks_type":"HABITATION",
    "name:eng_x_preferred":[
        "Kajke"
    ],
    "wof:name":"Kajke",
    "wof:placetype":"locality",
    "wof:population":176
},
  "geometry": {"coordinates":[74.852852,13.442504],"type":"Point"}
}