{
  "type": "Feature",
  "properties": {
    "iso:country":"IN",
    "ks:ks_name":"Rasidpur",
    "ks:ks_pop":211,
    "ks:ks_type":"VILLAGE",
    "ks:ks_uagg_main":0,
    "name:eng_x_preferred":[
        "Rasidpur"
    ],
    "wof:name":"Rasidpur",
    "wof:placetype":"neighbourhood",
    "wof:population":211
},
  "geometry": {"coordinates":[88.344025,25.629822],"type":"Point"}
}