{
  "type": "Feature",
  "properties": {
    "gn:admin1_code":"16",
    "gn:admin2_code":"527.0",
    "gn:asciiname":"Mardi",
    "gn:country_code":"IN",
    "gn:dem":694,
    "gn:feature_class":"P",
    "gn:feature_code":"PPL",
    "gn:name":"Mardi",
    "gn:population":0,
    "gn:timezone":"Asia/Kolkata",
    "iso:country":"IN",
    "wof:name":"Mardi",
    "wof:placetype":"locality"
},
  "geometry": {"coordinates":[74.69490999999999,17.74063],"type":"Point"}
}