{
  "type": "Feature",
  "properties": {
    "iso:country":"IN",
    "ks:ks_name":"Chavara Falia",
    "ks:ks_pop":278,
    "ks:ks_type":"HABITATION",
    "name:eng_x_preferred":[
        "Chavara Falia"
    ],
    "wof:name":"Chavara Falia",
    "wof:placetype":"locality",
    "wof:population":278
},
  "geometry": {"coordinates":[73.160028,20.347028],"type":"Point"}
}