{
  "type": "Feature",
  "properties": {
    "gn:admin1_code":"11.0",
    "gn:admin2_code":"033",
    "gn:asciiname":"Junga",
    "gn:country_code":"IN",
    "gn:dem":1609,
    "gn:feature_class":"P",
    "gn:feature_code":"PPL",
    "gn:name":"J\u016bnga",
    "gn:population":0,
    "gn:timezone":"Asia/Kolkata",
    "iso:country":"IN",
    "name:und_x_variant":[
        "J\u016bnga"
    ],
    "wof:name":"Junga",
    "wof:placetype":"locality"
},
  "geometry": {"coordinates":[77.19131999999998,31.02447],"type":"Point"}
}