{
  "type": "Feature",
  "properties": {
    "gn:admin1_code":"34.0",
    "gn:admin2_code":"235.0",
    "gn:asciiname":"Panti",
    "gn:country_code":"IN",
    "gn:dem":113,
    "gn:feature_class":"P",
    "gn:feature_code":"PPL",
    "gn:name":"P\u0101nti",
    "gn:population":0,
    "gn:timezone":"Asia/Kolkata",
    "iso:country":"IN",
    "name:deu_x_preferred":[
        "Panti Bliss"
    ],
    "name:fra_x_preferred":[
        "Panti"
    ],
    "name:gle_x_preferred":[
        "Panti"
    ],
    "name:spa_x_preferred":[
        "Panti"
    ],
    "wof:name":"Panti",
    "wof:placetype":"locality"
},
  "geometry": {"coordinates":[84.68380000000001,24.79148],"type":"Point"}
}