{
  "type": "Feature",
  "properties": {
    "gn:admin1_code":"34.0",
    "gn:admin2_code":"235.0",
    "gn:asciiname":"Panti",
    "gn:country_code":"IN",
    "gn:dem":113,
    "gn:feature_class":"P",
    "gn:feature_code":"PPL",
    "gn:name":"P\u0101nti",
    "gn:population":0,
    "gn:timezone":"Asia/Kolkata",
    "iso:country":"IN",
    "ks:ks_alt_nam":"P\u0101nti",
    "ks:ks_name":"Panti",
    "ks:ks_pop":1242,
    "ks:ks_type":"VILLAGE",
    "name:deu_x_preferred":[
        "Panti Bliss"
    ],
    "name:eng_x_preferred":[
        "Panti"
    ],
    "name:eng_x_variant":[
        "P\u0101nti"
    ],
    "name:fra_x_preferred":[
        "Panti"
    ],
    "name:gle_x_preferred":[
        "Panti"
    ],
    "name:spa_x_preferred":[
        "Panti"
    ],
    "wof:name":"Panti",
    "wof:placetype":"locality",
    "wof:population":1242
},
  "geometry": {"coordinates":[84.68655,24.785438],"type":"Point"}
}