{
  "type": "Feature",
  "properties": {
    "gn:admin1_code":"19",
    "gn:admin2_code":"579.0",
    "gn:asciiname":"Halgattaragi",
    "gn:country_code":"IN",
    "gn:dem":416,
    "gn:feature_class":"P",
    "gn:feature_code":"PPL",
    "gn:name":"H\u0101lgattaragi",
    "gn:population":0,
    "gn:timezone":"Asia/Kolkata",
    "iso:country":"IN",
    "wof:name":"Halgattaragi",
    "wof:placetype":"locality"
},
  "geometry": {"coordinates":[76.47232,16.95921],"type":"Point"}
}