{
  "type": "Feature",
  "properties": {
    "iso:country":"IN",
    "ks:ks_name":"Nunmati Pachim",
    "ks:ks_pop":147,
    "ks:ks_type":"HABITATION",
    "name:eng_x_preferred":[
        "Nunmati Pachim"
    ],
    "wof:name":"Nunmati Pachim",
    "wof:placetype":"locality",
    "wof:population":147
},
  "geometry": {"coordinates":[91.395532,26.040046],"type":"Point"}
}