{
  "type": "Feature",
  "properties": {
    "iso:country":"IN",
    "ks:ks_name":"Gorakodu",
    "ks:ks_pop":29,
    "ks:ks_type":"HABITATION",
    "name:eng_x_preferred":[
        "Gorakodu"
    ],
    "wof:name":"Gorakodu",
    "wof:placetype":"locality",
    "wof:population":29
},
  "geometry": {"coordinates":[75.22744899999999,13.601952],"type":"Point"}
}