{
  "type": "Feature",
  "properties": {
    "iso:country":"IN",
    "ks:ks_name":"Ganesh Purwa",
    "ks:ks_pop":240,
    "ks:ks_type":"HABITATION",
    "name:eng_x_preferred":[
        "Ganesh Purwa"
    ],
    "wof:name":"Ganesh Purwa",
    "wof:placetype":"locality",
    "wof:population":240
},
  "geometry": {"coordinates":[81.81935900000001,27.234911],"type":"Point"}
}