{
  "type": "Feature",
  "properties": {
    "gn:admin1_code":"39.0",
    "gn:admin2_code":"63.0",
    "gn:asciiname":"Bhantola",
    "gn:country_code":"IN",
    "gn:dem":1661,
    "gn:feature_class":"P",
    "gn:feature_code":"PPL",
    "gn:name":"Bhantola",
    "gn:population":0,
    "gn:timezone":"Asia/Kolkata",
    "iso:country":"IN",
    "ks:ks_name":"Bhantola",
    "ks:ks_pop":283,
    "ks:ks_type":"VILLAGE",
    "name:eng_x_preferred":[
        "Bhantola"
    ],
    "wof:name":"Bhantola",
    "wof:placetype":"locality",
    "wof:population":283
},
  "geometry": {"coordinates":[79.95217599999999,29.862389],"type":"Point"}
}