{
  "type": "Feature",
  "properties": {
    "iso:country":"IN",
    "ks:ks_name":"Kundla Ahar",
    "ks:ks_pop":0,
    "ks:ks_type":"VILLAGE",
    "name:eng_x_preferred":[
        "Kundla Ahar"
    ],
    "wof:name":"Kundla Ahar",
    "wof:placetype":"locality",
    "wof:population":0
},
  "geometry": {"coordinates":[84.85188100000001,25.158071],"type":"Point"}
}