{
  "type": "Feature",
  "properties": {
    "iso:country":"IN",
    "ks:ks_name":"Pure Chet",
    "ks:ks_pop":167,
    "ks:ks_type":"HABITATION",
    "name:eng_x_preferred":[
        "Pure Chet"
    ],
    "wof:name":"Pure Chet",
    "wof:placetype":"locality",
    "wof:population":167
},
  "geometry": {"coordinates":[81.822835,26.233411],"type":"Point"}
}