{
  "type": "Feature",
  "properties": {
    "iso:country":"IN",
    "ks:ks_name":"Gadi Gamna",
    "ks:ks_pop":1555,
    "ks:ks_type":"VILLAGE",
    "name:eng_x_preferred":[
        "Gadi Gamna"
    ],
    "wof:name":"Gadi Gamna",
    "wof:placetype":"locality",
    "wof:population":1555
},
  "geometry": {"coordinates":[74.58260900000001,23.331361],"type":"Point"}
}