{
  "type": "Feature",
  "properties": {
    "gn:admin1_code":"24.0",
    "gn:admin2_code":"123.0",
    "gn:asciiname":"Tiparakhera",
    "gn:country_code":"IN",
    "gn:dem":704,
    "gn:feature_class":"P",
    "gn:feature_code":"PPL",
    "gn:name":"Tip\u0101rakhera",
    "gn:population":0,
    "gn:timezone":"Asia/Kolkata",
    "iso:country":"IN",
    "wof:name":"Tiparakhera",
    "wof:placetype":"locality"
},
  "geometry": {"coordinates":[73.84383000000003,25.3899],"type":"Point"}
}