{
  "type": "Feature",
  "properties": {
    "iso:country":"IN",
    "ks:ks_name":"Sewalon Ki Dhani",
    "ks:ks_pop":412,
    "ks:ks_type":"HABITATION",
    "name:eng_x_preferred":[
        "Sewalon Ki Dhani"
    ],
    "wof:name":"Sewalon Ki Dhani",
    "wof:placetype":"locality",
    "wof:population":412
},
  "geometry": {"coordinates":[73.278631,26.187647],"type":"Point"}
}