{
  "type": "Feature",
  "properties": {
    "gn:admin1_code":"39.0",
    "gn:admin2_code":"63.0",
    "gn:asciiname":"Bijoria",
    "gn:country_code":"IN",
    "gn:dem":1110,
    "gn:feature_class":"P",
    "gn:feature_code":"PPL",
    "gn:name":"Bijoria",
    "gn:population":0,
    "gn:timezone":"Asia/Kolkata",
    "iso:country":"IN",
    "ks:ks_name":"Bijori",
    "ks:ks_pop":71,
    "ks:ks_type":"VILLAGE",
    "name:eng_x_preferred":[
        "Bijori"
    ],
    "name:eng_x_variant":[
        "Bijoria"
    ],
    "wof:name":"Bijori",
    "wof:placetype":"locality",
    "wof:population":71
},
  "geometry": {"coordinates":[79.747186,29.823625],"type":"Point"}
}