{
  "type": "Feature",
  "properties": {
    "iso:country":"IN",
    "ks:ks_alt_nam":"Kon\u0101pur",
    "ks:ks_name":"Konapur",
    "ks:ks_type":"VILLAGE",
    "name:eng_x_preferred":[
        "Konapur"
    ],
    "name:eng_x_variant":[
        "Kon\u0101pur"
    ],
    "wof:name":"Konapur",
    "wof:placetype":"locality"
},
  "geometry": {"coordinates":[75.34743400000001,14.619845],"type":"Point"}
}