{
  "type": "Feature",
  "properties": {
    "iso:country":"IN",
    "ks:ks_name":"Dhobianpurwa",
    "ks:ks_pop":244,
    "ks:ks_type":"HABITATION",
    "ks:ks_uagg_main":0,
    "name:eng_x_preferred":[
        "Dhobianpurwa"
    ],
    "wof:name":"Dhobianpurwa",
    "wof:placetype":"neighbourhood",
    "wof:population":244
},
  "geometry": {"coordinates":[81.331048,27.406392],"type":"Point"}
}