{
  "type": "Feature",
  "properties": {
    "iso:country":"IN",
    "ks:ks_name":"Talekhar",
    "ks:ks_pop":298,
    "ks:ks_type":"HABITATION",
    "name:eng_x_preferred":[
        "Talekhar"
    ],
    "wof:name":"Talekhar",
    "wof:placetype":"locality",
    "wof:population":298
},
  "geometry": {"coordinates":[73.10357,18.605739],"type":"Point"}
}