{
  "type": "Feature",
  "properties": {
    "iso:country":"IN",
    "ks:ks_name":"Kaysth Tola",
    "ks:ks_pop":92,
    "ks:ks_type":"HABITATION",
    "ks:ks_uagg_main":0,
    "name:eng_x_preferred":[
        "Kaysth Tola"
    ],
    "wof:name":"Kaysth Tola",
    "wof:placetype":"neighbourhood",
    "wof:population":92
},
  "geometry": {"coordinates":[86.834006,26.393805],"type":"Point"}
}