{
  "type": "Feature",
  "properties": {
    "iso:country":"IN",
    "ks:ks_name":"Charmkarwadi",
    "ks:ks_pop":14,
    "ks:ks_type":"HABITATION",
    "name:eng_x_preferred":[
        "Charmkarwadi"
    ],
    "wof:name":"Charmkarwadi",
    "wof:placetype":"locality",
    "wof:population":14
},
  "geometry": {"coordinates":[73.29777799999999,17.511389],"type":"Point"}
}