{
  "type": "Feature",
  "properties": {
    "gn:admin1_code":"19.0",
    "gn:admin2_code":"572",
    "gn:asciiname":"Azad Nagar",
    "gn:country_code":"IN",
    "gn:dem":879,
    "gn:feature_class":"P",
    "gn:feature_code":"PPL",
    "gn:name":"Azad Nagar",
    "gn:population":0,
    "gn:timezone":"Asia/Kolkata",
    "iso:country":"IN",
    "wof:name":"Azad Nagar",
    "wof:placetype":"locality"
},
  "geometry": {"coordinates":[77.55566999999998,12.95642],"type":"Point"}
}