{
  "type": "Feature",
  "properties": {
    "iso:country":"IN",
    "ks:ks_name":"Thikriya",
    "ks:ks_pop":546,
    "ks:ks_type":"VILLAGE",
    "name:eng_x_preferred":[
        "Thikriya"
    ],
    "wof:name":"Thikriya",
    "wof:placetype":"locality",
    "wof:population":546
},
  "geometry": {"coordinates":[74.584892,23.286829],"type":"Point"}
}