{
  "type": "Feature",
  "properties": {
    "iso:country":"IN",
    "ks:ks_name":"Bariya Faliya",
    "ks:ks_pop":409,
    "ks:ks_type":"HABITATION",
    "name:eng_x_preferred":[
        "Bariya Faliya"
    ],
    "wof:name":"Bariya Faliya",
    "wof:placetype":"locality",
    "wof:population":409
},
  "geometry": {"coordinates":[73.78736000000001,22.927784],"type":"Point"}
}