{
  "type": "Feature",
  "properties": {
    "iso:country":"IN",
    "ks:ks_name":"Kuzhimoola Jn",
    "ks:ks_pop":980,
    "ks:ks_type":"HABITATION",
    "name:eng_x_preferred":[
        "Kuzhimoola Jn"
    ],
    "wof:name":"Kuzhimoola Jn",
    "wof:placetype":"locality",
    "wof:population":980
},
  "geometry": {"coordinates":[76.047926,11.196536],"type":"Point"}
}