{
  "type": "Feature",
  "properties": {
    "iso:country":"IN",
    "ks:ks_name":"Gangapatti",
    "ks:ks_pop":904,
    "ks:ks_type":"VILLAGE",
    "name:eng_x_preferred":[
        "Gangapatti"
    ],
    "wof:name":"Gangapatti",
    "wof:placetype":"locality",
    "wof:population":904
},
  "geometry": {"coordinates":[85.93523399999999,26.116472],"type":"Point"}
}