{
  "type": "Feature",
  "properties": {
    "iso:country":"IN",
    "ks:ks_name":"Ghatpada Falia",
    "ks:ks_pop":102,
    "ks:ks_type":"HABITATION",
    "name:eng_x_preferred":[
        "Ghatpada Falia"
    ],
    "wof:name":"Ghatpada Falia",
    "wof:placetype":"locality",
    "wof:population":102
},
  "geometry": {"coordinates":[73.22536100000001,20.181083],"type":"Point"}
}