{
  "type": "Feature",
  "properties": {
    "iso:country":"IN",
    "ks:ks_name":"Bhaleya",
    "ks:ks_pop":4373,
    "ks:ks_type":"VILLAGE",
    "name:eng_x_preferred":[
        "Bhaleya"
    ],
    "wof:name":"Bhaleya",
    "wof:placetype":"locality",
    "wof:population":4373
},
  "geometry": {"coordinates":[88.56730399999999,22.279173],"type":"Point"}
}