{
  "type": "Feature",
  "properties": {
    "iso:country":"IN",
    "ks:ks_name":"Kodaguda",
    "ks:ks_pop":132,
    "ks:ks_type":"HABITATION",
    "name:eng_x_preferred":[
        "Kodaguda"
    ],
    "wof:name":"Kodaguda",
    "wof:placetype":"locality",
    "wof:population":132
},
  "geometry": {"coordinates":[82.042079,18.26146],"type":"Point"}
}