{
  "type": "Feature",
  "properties": {
    "iso:country":"IN",
    "ks:ks_name":"Andia Rty",
    "ks:ks_pop":595,
    "ks:ks_type":"HABITATION",
    "name:eng_x_preferred":[
        "Andia Rty"
    ],
    "wof:name":"Andia Rty",
    "wof:placetype":"locality",
    "wof:population":595
},
  "geometry": {"coordinates":[80.73469299999999,22.847661],"type":"Point"}
}