{
  "type": "Feature",
  "properties": {
    "iso:country":"IN",
    "ks:ks_name":"Jurhan Mehda",
    "ks:ks_pop":132,
    "ks:ks_type":"VILLAGE",
    "name:eng_x_preferred":[
        "Jurhan Mehda"
    ],
    "wof:name":"Jurhan Mehda",
    "wof:placetype":"locality",
    "wof:population":132
},
  "geometry": {"coordinates":[80.68998000000001,19.889267],"type":"Point"}
}