{
  "type": "Feature",
  "properties": {
    "iso:country":"IN",
    "ks:ks_name":"Benipur",
    "ks:ks_pop":100,
    "ks:ks_type":"HABITATION",
    "name:eng_x_preferred":[
        "Benipur"
    ],
    "wof:name":"Benipur",
    "wof:placetype":"locality",
    "wof:population":100
},
  "geometry": {"coordinates":[86.552492,21.012014],"type":"Point"}
}