{
  "type": "Feature",
  "properties": {
    "gn:country":"IN",
    "gn:fcode":"PPL",
    "gn:population":0,
    "iso:country":"IN",
    "name:bpy_x_preferred":[
        "\u09ac\u09be\u0999\u09cd\u0995\u09bf"
    ],
    "name:ceb_x_preferred":[
        "Banki"
    ],
    "name:fra_x_preferred":[
        "Banki"
    ],
    "name:ita_x_preferred":[
        "Banki"
    ],
    "name:nld_x_preferred":[
        "Banki"
    ],
    "name:pol_x_preferred":[
        "Banki"
    ],
    "name:rus_x_preferred":[
        "\u0411\u0430\u043d\u043a\u0438"
    ],
    "name:srp_x_preferred":[
        "\u0411\u0430\u043d\u043a\u0438"
    ],
    "name:swe_x_preferred":[
        "Banki"
    ],
    "qs_pg:aaroncc":"IN",
    "qs_pg:gn_country":"IN",
    "qs_pg:gn_fcode":"PPL",
    "qs_pg:gn_pop":0,
    "qs_pg:name":"Banki",
    "qs_pg:name_adm0":"India",
    "qs_pg:name_adm1":"Uttar Pradesh",
    "qs_pg:photos_9k":1,
    "qs_pg:photos_9r":1,
    "qs_pg:photos_all":1,
    "qs_pg:photos_sr":0,
    "qs_pg:pop_sr":0,
    "qs_pg:qs_pg_placetype":"locality",
    "qs_pg:qs_pg_placetype_gp":"Town",
    "qs_pg:woe_adm0":23424848,
    "woe:adm0_id":23424848,
    "woe:name_adm0":"India",
    "woe:name_adm1":"Uttar Pradesh",
    "woe:placetype":"Town",
    "wof:name":"Banki",
    "wof:placetype":"neighbourhood"
},
  "geometry": {"coordinates":[80.24069,26.47312],"type":"Point"}
}