{
  "type": "Feature",
  "properties": {
    "iso:country":"IN",
    "ks:ks_name":"6 SJM A",
    "ks:ks_pop":582,
    "ks:ks_type":"VILLAGE",
    "name:eng_x_preferred":[
        "6 SJM A"
    ],
    "wof:name":"6 SJM A",
    "wof:placetype":"locality",
    "wof:population":582
},
  "geometry": {"coordinates":[72.782612,28.764839],"type":"Point"}
}