{
  "type": "Feature",
  "properties": {
    "gn:admin1_code":"39.0",
    "gn:admin2_code":"59.0",
    "gn:asciiname":"Ghattudhar",
    "gn:country_code":"IN",
    "gn:dem":1454,
    "gn:feature_class":"P",
    "gn:feature_code":"PPL",
    "gn:name":"Ghattudh\u0101r",
    "gn:population":0,
    "gn:timezone":"Asia/Kolkata",
    "iso:country":"IN",
    "wof:name":"Ghattudhar",
    "wof:placetype":"locality"
},
  "geometry": {"coordinates":[78.05794,30.48206],"type":"Point"}
}