{
  "type": "Feature",
  "properties": {
    "gn:admin1_code":"35",
    "gn:admin2_code":"442.0",
    "gn:asciiname":"Paka",
    "gn:country_code":"IN",
    "gn:dem":440,
    "gn:feature_class":"P",
    "gn:feature_code":"PPL",
    "gn:name":"P\u0101ka",
    "gn:population":0,
    "gn:timezone":"Asia/Kolkata",
    "iso:country":"IN",
    "name:bos_x_preferred":[
        "Paka"
    ],
    "name:ceb_x_preferred":[
        "Paka"
    ],
    "name:fra_x_preferred":[
        "Paka"
    ],
    "name:hrv_x_preferred":[
        "Paka"
    ],
    "name:hun_x_preferred":[
        "Paka"
    ],
    "name:nld_x_preferred":[
        "Paka"
    ],
    "name:pol_x_preferred":[
        "Paka"
    ],
    "name:slv_x_preferred":[
        "Paka"
    ],
    "name:srp_x_preferred":[
        "\u041f\u0430\u043a\u0430"
    ],
    "name:swa_x_preferred":[
        "Paka"
    ],
    "wof:name":"Paka",
    "wof:placetype":"locality"
},
  "geometry": {"coordinates":[76.66032,23.86238],"type":"Point"}
}