{
  "type": "Feature",
  "properties": {
    "iso:country":"IN",
    "ks:ks_name":"Panipatty",
    "ks:ks_pop":120,
    "ks:ks_type":"HABITATION",
    "name:eng_x_preferred":[
        "Panipatty"
    ],
    "wof:name":"Panipatty",
    "wof:placetype":"locality",
    "wof:population":120
},
  "geometry": {"coordinates":[78.672693,10.537829],"type":"Point"}
}