{
  "type": "Feature",
  "properties": {
    "gn:admin1_code":"2.0",
    "gn:admin2_code":"542.0",
    "gn:asciiname":"Jelupinayudupeta",
    "gn:country_code":"IN",
    "gn:dem":17,
    "gn:feature_class":"P",
    "gn:feature_code":"PPL",
    "gn:name":"Jelupin\u0101yudupeta",
    "gn:population":0,
    "gn:timezone":"Asia/Kolkata",
    "iso:country":"IN",
    "wof:name":"Jelupinayudupeta",
    "wof:placetype":"neighbourhood"
},
  "geometry": {"coordinates":[83.87823,18.31849],"type":"Point"}
}