{
  "type": "Feature",
  "properties": {
    "iso:country":"IN",
    "ks:ks_name":"Jarkiholli",
    "ks:ks_pop":664,
    "ks:ks_type":"VILLAGE",
    "name:eng_x_preferred":[
        "Jarkiholli"
    ],
    "wof:name":"Jarkiholli",
    "wof:placetype":"locality",
    "wof:population":664
},
  "geometry": {"coordinates":[74.571116,16.095024],"type":"Point"}
}