{
  "type": "Feature",
  "properties": {
    "gn:admin1_code":"10",
    "gn:admin2_code":"81.0",
    "gn:asciiname":"Siwana",
    "gn:country_code":"IN",
    "gn:dem":219,
    "gn:feature_class":"P",
    "gn:feature_code":"PPL",
    "gn:name":"Siw\u0101na",
    "gn:population":0,
    "gn:timezone":"Asia/Kolkata",
    "iso:country":"IN",
    "name:ceb_x_preferred":[
        "Siw\u0101na"
    ],
    "name:swe_x_preferred":[
        "Siw\u0101na"
    ],
    "wof:name":"Siwana",
    "wof:placetype":"locality"
},
  "geometry": {"coordinates":[76.06034,29.00584000000001],"type":"Point"}
}