{
  "type": "Feature",
  "properties": {
    "gn:admin1_code":"10",
    "gn:admin2_code":"81.0",
    "gn:asciiname":"Kiskanda",
    "gn:country_code":"IN",
    "gn:dem":266,
    "gn:feature_class":"P",
    "gn:feature_code":"PPL",
    "gn:name":"Kiskanda",
    "gn:population":0,
    "gn:timezone":"Asia/Kolkata",
    "iso:country":"IN",
    "wof:name":"Kiskanda",
    "wof:placetype":"locality"
},
  "geometry": {"coordinates":[75.97372,28.47343],"type":"Point"}
}