{
  "type": "Feature",
  "properties": {
    "iso:country":"IN",
    "ks:ks_name":"Kadavacheri",
    "ks:ks_pop":1137,
    "ks:ks_type":"VILLAGE",
    "ks:ks_uagg_main":0,
    "name:eng_x_preferred":[
        "Kadavacheri"
    ],
    "wof:name":"Kadavacheri",
    "wof:placetype":"neighbourhood",
    "wof:population":1137
},
  "geometry": {"coordinates":[79.69771299999999,11.377419],"type":"Point"}
}