{
  "type": "Feature",
  "properties": {
    "iso:country":"IN",
    "ks:ks_name":"Dohriya Buzurg",
    "ks:ks_pop":797,
    "ks:ks_type":"HABITATION",
    "name:eng_x_preferred":[
        "Dohriya Buzurg"
    ],
    "wof:name":"Dohriya Buzurg",
    "wof:placetype":"locality",
    "wof:population":797
},
  "geometry": {"coordinates":[82.96766,27.446727],"type":"Point"}
}