{
  "type": "Feature",
  "properties": {
    "gn:admin1_code":"37.0",
    "gn:admin2_code":"417.0",
    "gn:asciiname":"Irli",
    "gn:country_code":"IN",
    "gn:dem":381,
    "gn:feature_class":"P",
    "gn:feature_code":"PPL",
    "gn:name":"Irli",
    "gn:population":0,
    "gn:timezone":"Asia/Kolkata",
    "iso:country":"IN",
    "wof:name":"Irli",
    "wof:placetype":"locality"
},
  "geometry": {"coordinates":[81.12690000000001,18.72994],"type":"Point"}
}