{
  "type": "Feature",
  "properties": {
    "iso:country":"IN",
    "ks:ks_name":"Purana Songkhai",
    "ks:ks_pop":251,
    "ks:ks_type":"HABITATION",
    "name:eng_x_preferred":[
        "Purana Songkhai"
    ],
    "wof:name":"Purana Songkhai",
    "wof:placetype":"locality",
    "wof:population":251
},
  "geometry": {"coordinates":[93.290812,25.095667],"type":"Point"}
}