{
  "type": "Feature",
  "properties": {
    "iso:country":"IN",
    "ks:ks_name":"Palasdala",
    "ks:ks_pop":198,
    "ks:ks_type":"HABITATION",
    "name:eng_x_preferred":[
        "Palasdala"
    ],
    "wof:name":"Palasdala",
    "wof:placetype":"locality",
    "wof:population":198
},
  "geometry": {"coordinates":[73.829734,15.951661],"type":"Point"}
}