{
  "type": "Feature",
  "properties": {
    "iso:country":"IN",
    "ks:ks_name":"Tisiya Tola",
    "ks:ks_pop":813,
    "ks:ks_type":"HABITATION",
    "name:eng_x_preferred":[
        "Tisiya Tola"
    ],
    "wof:name":"Tisiya Tola",
    "wof:placetype":"locality",
    "wof:population":813
},
  "geometry": {"coordinates":[83.67475,23.839214],"type":"Point"}
}