{
  "type": "Feature",
  "properties": {
    "iso:country":"IN",
    "ks:ks_name":"Sobhanagar",
    "ks:ks_pop":96,
    "ks:ks_type":"HABITATION",
    "name:eng_x_preferred":[
        "Sobhanagar"
    ],
    "wof:name":"Sobhanagar",
    "wof:placetype":"locality",
    "wof:population":96
},
  "geometry": {"coordinates":[81.027325,27.231856],"type":"Point"}
}