{
  "type": "Feature",
  "properties": {
    "iso:country":"IN",
    "ks:ks_name":"Marhi",
    "ks:ks_pop":789,
    "ks:ks_type":"HABITATION",
    "name:eng_x_preferred":[
        "Marhi"
    ],
    "wof:name":"Marhi",
    "wof:placetype":"locality",
    "wof:population":789
},
  "geometry": {"coordinates":[81.411965,25.408483],"type":"Point"}
}