{
  "type": "Feature",
  "properties": {
    "gn:admin1_code":"35.0",
    "gn:admin2_code":"457.0",
    "gn:asciiname":"Bhanderi",
    "gn:country_code":"IN",
    "gn:dem":578,
    "gn:feature_class":"P",
    "gn:feature_code":"PPL",
    "gn:name":"Bhander\u012b",
    "gn:population":0,
    "gn:timezone":"Asia/Kolkata",
    "iso:country":"IN",
    "wof:name":"Bhanderi",
    "wof:placetype":"locality"
},
  "geometry": {"coordinates":[80.53327,21.73644],"type":"Point"}
}