{
  "type": "Feature",
  "properties": {
    "gn:admin1_code":"35.0",
    "gn:admin2_code":"457.0",
    "gn:asciiname":"Bhanderi",
    "gn:country_code":"IN",
    "gn:dem":578,
    "gn:feature_class":"P",
    "gn:feature_code":"PPL",
    "gn:name":"Bhander\u012b",
    "gn:population":0,
    "gn:timezone":"Asia/Kolkata",
    "iso:country":"IN",
    "ks:ks_alt_nam":"Bhander\u012b",
    "ks:ks_name":"Bhanderi",
    "ks:ks_pop":406,
    "ks:ks_type":"VILLAGE",
    "name:eng_x_preferred":[
        "Bhanderi"
    ],
    "name:eng_x_variant":[
        "Bhander\u012b"
    ],
    "wof:name":"Bhanderi",
    "wof:placetype":"locality",
    "wof:population":406
},
  "geometry": {"coordinates":[80.53327299999999,21.736436],"type":"Point"}
}