{
  "type": "Feature",
  "properties": {
    "iso:country":"IN",
    "ks:ks_name":"Dudhkasoi",
    "ks:ks_pop":643,
    "ks:ks_type":"HABITATION",
    "name:eng_x_preferred":[
        "Dudhkasoi"
    ],
    "wof:name":"Dudhkasoi",
    "wof:placetype":"locality",
    "wof:population":643
},
  "geometry": {"coordinates":[86.252883,24.720329],"type":"Point"}
}