{
  "type": "Feature",
  "properties": {
    "gn:admin1_code":"16.0",
    "gn:admin2_code":"528",
    "gn:asciiname":"Jaigarh",
    "gn:country_code":"IN",
    "gn:dem":22,
    "gn:feature_class":"P",
    "gn:feature_code":"PPL",
    "gn:name":"Jaigarh",
    "gn:population":0,
    "gn:timezone":"Asia/Kolkata",
    "iso:country":"IN",
    "name:und_x_variant":[
        "Jaygad",
        "Jaigarh"
    ],
    "wof:name":"Jaigarh",
    "wof:placetype":"locality"
},
  "geometry": {"coordinates":[73.22063,17.29524],"type":"Point"}
}