{
  "type": "Feature",
  "properties": {
    "iso:country":"IN",
    "ks:ks_name":"Tatamaha",
    "ks:ks_pop":541,
    "ks:ks_type":"VILLAGE",
    "name:eng_x_preferred":[
        "Tatamaha"
    ],
    "wof:name":"Tatamaha",
    "wof:placetype":"locality",
    "wof:population":541
},
  "geometry": {"coordinates":[84.25629600000001,20.084807],"type":"Point"}
}