{
  "type": "Feature",
  "properties": {
    "gn:admin1_code":"24.0",
    "gn:admin2_code":"130.0",
    "gn:asciiname":"Gaunri",
    "gn:country_code":"IN",
    "gn:dem":307,
    "gn:feature_class":"P",
    "gn:feature_code":"PPL",
    "gn:name":"Gaunri",
    "gn:population":0,
    "gn:timezone":"Asia/Kolkata",
    "iso:country":"IN",
    "wof:name":"Gaunri",
    "wof:placetype":"locality"
},
  "geometry": {"coordinates":[73.94455000000001,24.26873],"type":"Point"}
}