{
  "type": "Feature",
  "properties": {
    "gn:admin1_code":"36",
    "gn:admin2_code":"156.0",
    "gn:asciiname":"Kanchanpur",
    "gn:country_code":"IN",
    "gn:dem":127,
    "gn:feature_class":"P",
    "gn:feature_code":"PPL",
    "gn:name":"Kanchanpur",
    "gn:population":0,
    "gn:timezone":"Asia/Kolkata",
    "iso:country":"IN",
    "name:ceb_x_preferred":[
        "Kanchanpur"
    ],
    "name:nld_x_preferred":[
        "Kanchanpur"
    ],
    "wof:name":"Kanchanpur",
    "wof:placetype":"locality"
},
  "geometry": {"coordinates":[80.90498000000002,26.54128],"type":"Point"}
}