{
  "type": "Feature",
  "properties": {
    "iso:country":"IN",
    "ks:ks_name":"Kallampattii",
    "ks:ks_pop":1801,
    "ks:ks_type":"VILLAGE",
    "ks:ks_uagg_main":0,
    "name:eng_x_preferred":[
        "Kallampattii"
    ],
    "wof:name":"Kallampattii",
    "wof:placetype":"neighbourhood",
    "wof:population":1801
},
  "geometry": {"coordinates":[78.520495,10.362656],"type":"Point"}
}