{
  "type": "Feature",
  "properties": {
    "iso:country":"IN",
    "ks:ks_name":"Keterchak",
    "ks:ks_pop":712,
    "ks:ks_type":"HABITATION",
    "name:eng_x_preferred":[
        "Keterchak"
    ],
    "wof:name":"Keterchak",
    "wof:placetype":"locality",
    "wof:population":712
},
  "geometry": {"coordinates":[88.933499,22.401846],"type":"Point"}
}