{
  "type": "Feature",
  "properties": {
    "iso:country":"IN",
    "ks:ks_name":"Unchwa Purwa",
    "ks:ks_pop":680,
    "ks:ks_type":"HABITATION",
    "name:eng_x_preferred":[
        "Unchwa Purwa"
    ],
    "wof:name":"Unchwa Purwa",
    "wof:placetype":"locality",
    "wof:population":680
},
  "geometry": {"coordinates":[81.63907500000001,27.643573],"type":"Point"}
}