{
  "type": "Feature",
  "properties": {
    "iso:country":"IN",
    "ks:ks_alt_nam":"BARKA TOLA",
    "ks:ks_name":"Barka Tola",
    "ks:ks_pop":202,
    "ks:ks_type":"HABITATION",
    "name:eng_x_preferred":[
        "Barka Tola"
    ],
    "wof:name":"Barka Tola",
    "wof:placetype":"locality",
    "wof:population":202
},
  "geometry": {"coordinates":[84.184804,24.008767],"type":"Point"}
}