{
  "type": "Feature",
  "properties": {
    "iso:country":"IN",
    "ks:ks_name":"Aguiya Chak",
    "ks:ks_pop":162,
    "ks:ks_type":"VILLAGE",
    "ks:ks_uagg_main":0,
    "name:eng_x_preferred":[
        "Aguiya Chak"
    ],
    "wof:name":"Aguiya Chak",
    "wof:placetype":"neighbourhood",
    "wof:population":162
},
  "geometry": {"coordinates":[86.617957,24.197292],"type":"Point"}
}