{
  "type": "Feature",
  "properties": {
    "gn:admin1_code":"36",
    "gn:admin2_code":"201.0",
    "gn:asciiname":"Nagla Bhura",
    "gn:country_code":"IN",
    "gn:dem":166,
    "gn:feature_class":"P",
    "gn:feature_code":"PPL",
    "gn:name":"Nagla Bh\u016bra",
    "gn:population":0,
    "gn:timezone":"Asia/Kolkata",
    "iso:country":"IN",
    "name:und_x_variant":[
        "Nagla Bh\u016bra",
        "Nagla \u0100nandpur"
    ],
    "wof:name":"Nagla Bhura",
    "wof:placetype":"neighbourhood"
},
  "geometry": {"coordinates":[78.94213999999999,27.55281],"type":"Point"}
}