{
  "type": "Feature",
  "properties": {
    "iso:country":"IN",
    "ks:ks_name":"Tinia Khar",
    "ks:ks_pop":13,
    "ks:ks_type":"HABITATION",
    "name:eng_x_preferred":[
        "Tinia Khar"
    ],
    "wof:name":"Tinia Khar",
    "wof:placetype":"locality",
    "wof:population":13
},
  "geometry": {"coordinates":[84.416945,23.762113],"type":"Point"}
}