{
  "type": "Feature",
  "properties": {
    "iso:country":"IN",
    "ks:ks_name":"Tatijhariya",
    "ks:ks_pop":818,
    "ks:ks_type":"VILLAGE",
    "name:eng_x_preferred":[
        "Tatijhariya"
    ],
    "wof:name":"Tatijhariya",
    "wof:placetype":"locality",
    "wof:population":818
},
  "geometry": {"coordinates":[83.90276,23.375907],"type":"Point"}
}