{
  "type": "Feature",
  "properties": {
    "gn:admin1_code":"34.0",
    "gn:admin2_code":"240.0",
    "gn:asciiname":"Mahua Bagh",
    "gn:country_code":"IN",
    "gn:dem":77,
    "gn:feature_class":"P",
    "gn:feature_code":"PPL",
    "gn:name":"Mahua Bagh",
    "gn:population":0,
    "gn:timezone":"Asia/Kolkata",
    "iso:country":"IN",
    "ks:ks_name":"Mahua Bigha",
    "ks:ks_pop":178,
    "ks:ks_type":"HABITATION",
    "name:eng_x_preferred":[
        "Mahua Bigha"
    ],
    "name:eng_x_variant":[
        "Mahua Bagh"
    ],
    "wof:name":"Mahua Bigha",
    "wof:placetype":"locality",
    "wof:population":178
},
  "geometry": {"coordinates":[84.73251999999999,25.171933],"type":"Point"}
}