{
  "type": "Feature",
  "properties": {
    "gn:admin1_code":"35",
    "gn:admin2_code":"456.0",
    "gn:asciiname":"Tinsi",
    "gn:country_code":"IN",
    "gn:dem":565,
    "gn:feature_class":"P",
    "gn:feature_code":"PPL",
    "gn:name":"Tinsi",
    "gn:population":0,
    "gn:timezone":"Asia/Kolkata",
    "iso:country":"IN",
    "ks:ks_name":"Tinsi",
    "ks:ks_type":"VILLAGE",
    "name:eng_x_preferred":[
        "Tinsi"
    ],
    "wof:name":"Tinsi",
    "wof:placetype":"locality"
},
  "geometry": {"coordinates":[79.78193,22.76044],"type":"Point"}
}