{
  "type": "Feature",
  "properties": {
    "gn:admin1_code":"37",
    "gn:admin2_code":"404.0",
    "gn:asciiname":"Amlibahara",
    "gn:country_code":"IN",
    "gn:dem":440,
    "gn:feature_class":"P",
    "gn:feature_code":"PPL",
    "gn:name":"Aml\u012bbah\u0101ra",
    "gn:population":0,
    "gn:timezone":"Asia/Kolkata",
    "iso:country":"IN",
    "wof:name":"Amlibahara",
    "wof:placetype":"locality"
},
  "geometry": {"coordinates":[82.30691,22.91651],"type":"Point"}
}