{
  "type": "Feature",
  "properties": {
    "iso:country":"IN",
    "ks:ks_name":"Sanaia Reang Para",
    "ks:ks_pop":192,
    "ks:ks_type":"HABITATION",
    "name:eng_x_preferred":[
        "Sanaia Reang Para"
    ],
    "wof:name":"Sanaia Reang Para",
    "wof:placetype":"locality",
    "wof:population":192
},
  "geometry": {"coordinates":[91.916172,24.119329],"type":"Point"}
}