{
  "type": "Feature",
  "properties": {
    "iso:country":"IN",
    "ks:ks_name":"Uttar Gopinathpur",
    "ks:ks_pop":2172,
    "ks:ks_type":"VILLAGE",
    "ks:ks_uagg_main":0,
    "name:eng_x_preferred":[
        "Uttar Gopinathpur"
    ],
    "wof:name":"Uttar Gopinathpur",
    "wof:placetype":"neighbourhood",
    "wof:population":2172
},
  "geometry": {"coordinates":[88.374161,22.311621],"type":"Point"}
}