{
  "type": "Feature",
  "properties": {
    "iso:country":"IN",
    "ks:ks_name":"15 RP",
    "ks:ks_pop":483,
    "ks:ks_type":"VILLAGE",
    "name:eng_x_preferred":[
        "15 RP"
    ],
    "wof:name":"15 RP",
    "wof:placetype":"locality",
    "wof:population":483
},
  "geometry": {"coordinates":[74.341042,29.33955],"type":"Point"}
}