{
  "type": "Feature",
  "properties": {
    "gn:admin1_code":"35",
    "gn:admin2_code":"450.0",
    "gn:asciiname":"Sivrajipura",
    "gn:country_code":"IN",
    "gn:dem":434,
    "gn:feature_class":"P",
    "gn:feature_code":"PPL",
    "gn:name":"Sivr\u0101j\u012bpura",
    "gn:population":0,
    "gn:timezone":"Asia/Kolkata",
    "iso:country":"IN",
    "wof:name":"Sivrajipura",
    "wof:placetype":"locality"
},
  "geometry": {"coordinates":[79.96588,23.63792],"type":"Point"}
}