{
  "type": "Feature",
  "properties": {
    "gn:country":"IN",
    "gn:fcode":"PPLX",
    "gn:population":0,
    "iso:country":"IN",
    "name:ara_x_preferred":[
        "\u062e\u0627\u0646 \u0627\u0644\u0645\u0628\u0648\u0631\u0627"
    ],
    "name:ben_bn_x_preferred":[
        "\u0996\u09be\u09a8 \u0986\u09b2\u09ae\u09aa\u09c1\u09b0\u09be"
    ],
    "name:ben_in_x_preferred":[
        "\u0996\u09be\u09a8 \u0986\u09b2\u09ae\u09aa\u09c1\u09b0\u09be"
    ],
    "name:guj_x_preferred":[
        "\u0a96\u0abe\u0aa8 \u0a86\u0ab2\u0aae\u0aaa\u0ac1\u0ab0\u0abe"
    ],
    "name:hin_x_preferred":[
        "\u0916\u093e\u0928 \u0906\u0932\u092e\u092a\u0941\u0930\u093e"
    ],
    "name:kan_x_preferred":[
        "\u0c96\u0cbe\u0ca8\u0ccd"
    ],
    "name:mal_x_preferred":[
        "\u0d16\u0d3e\u0d7b \u0d06\u0d32\u0d3e\u0d02\u0d2a\u0d41\u0d30"
    ],
    "name:mar_x_preferred":[
        "\u0916\u093e\u0928 \u0906\u0932\u092e\u092a\u0941\u0930\u093e"
    ],
    "name:pan_x_preferred":[
        "\u0a16\u0a3e\u0a28 \u0a06\u0a32\u0a2e\u0a2a\u0a41\u0a30\u0a3e"
    ],
    "name:tam_x_preferred":[
        "\u0b95\u0bbe\u0ba9\u0bcd \u0b86\u0bb2\u0bae\u0bcd\u0baa\u0bc1\u0bb0\u0bbe"
    ],
    "name:tel_x_preferred":[
        "\u0c16\u0c3e\u0c28\u0c4d \u0c06\u0c32\u0c02\u0c2a\u0c41\u0c30\u0c3e"
    ],
    "name:und_x_variant":[
        "Khan Alampur"
    ],
    "name:urd_x_preferred":[
        "\u062e\u0627\u0646 \u0639\u0627\u0644\u0645 \u067e\u0648\u0631\u06c1"
    ],
    "qs:name":"Khan Alampura",
    "qs:name_adm0":"India",
    "qs:name_adm1":"Uttar Pradesh",
    "qs:photos":119,
    "qs:photos_1k":24,
    "qs:photos_9k":1,
    "qs:photos_9r":3,
    "qs:photos_all":119,
    "qs:photos_sr":3,
    "qs:placetype":"Suburb",
    "qs:pop_sr":"0",
    "wof:name":"Khan Alampura",
    "wof:placetype":"neighbourhood",
    "wof:population":0
},
  "geometry": {"coordinates":[77.56667,29.95],"type":"Point"}
}