{
  "type": "Feature",
  "properties": {
    "iso:country":"IN",
    "ks:ks_name":"Bairia",
    "ks:ks_pop":3316,
    "ks:ks_type":"VILLAGE",
    "name:eng_x_preferred":[
        "Bairia"
    ],
    "wof:name":"Bairia",
    "wof:placetype":"locality",
    "wof:population":3316
},
  "geometry": {"coordinates":[85.343474,26.142775],"type":"Point"}
}