{
  "type": "Feature",
  "properties": {
    "iso:country":"IN",
    "ks:ks_name":"Bandhamajhiguda",
    "ks:ks_pop":332,
    "ks:ks_type":"HABITATION",
    "name:eng_x_preferred":[
        "Bandhamajhiguda"
    ],
    "wof:name":"Bandhamajhiguda",
    "wof:placetype":"locality",
    "wof:population":332
},
  "geometry": {"coordinates":[82.17325099999999,18.528913],"type":"Point"}
}