{
  "type": "Feature",
  "properties": {
    "iso:country":"IN",
    "ks:ks_name":"Simri",
    "ks:ks_pop":1171,
    "ks:ks_type":"VILLAGE",
    "ks:ks_uagg_main":0,
    "name:eng_x_preferred":[
        "Simri"
    ],
    "wof:name":"Simri",
    "wof:placetype":"neighbourhood",
    "wof:population":1171
},
  "geometry": {"coordinates":[85.512997,25.460036],"type":"Point"}
}