{
  "type": "Feature",
  "properties": {
    "iso:country":"IN",
    "ks:ks_name":"Nadimiveedhi",
    "ks:ks_pop":147,
    "ks:ks_type":"VILLAGE",
    "name:eng_x_preferred":[
        "Nadimiveedhi"
    ],
    "wof:name":"Nadimiveedhi",
    "wof:placetype":"locality",
    "wof:population":147
},
  "geometry": {"coordinates":[82.24823000000001,17.936228],"type":"Point"}
}