{
  "type": "Feature",
  "properties": {
    "iso:country":"IN",
    "ks:ks_name":"Tarabanga",
    "ks:ks_pop":288,
    "ks:ks_type":"VILLAGE",
    "name:eng_x_preferred":[
        "Tarabanga"
    ],
    "wof:name":"Tarabanga",
    "wof:placetype":"locality",
    "wof:population":288
},
  "geometry": {"coordinates":[84.418038,19.260255],"type":"Point"}
}