{
  "type": "Feature",
  "properties": {
    "gn:admin1_code":"11",
    "gn:admin2_code":"30.0",
    "gn:asciiname":"Bhareri",
    "gn:country_code":"IN",
    "gn:dem":960,
    "gn:feature_class":"P",
    "gn:feature_code":"PPL",
    "gn:name":"Bhareri",
    "gn:population":0,
    "gn:timezone":"Asia/Kolkata",
    "iso:country":"IN",
    "wof:name":"Bhareri",
    "wof:placetype":"locality"
},
  "geometry": {"coordinates":[76.75873,31.49744],"type":"Point"}
}