{
  "type": "Feature",
  "properties": {
    "iso:country":"IN",
    "ks:ks_name":"Dablipada",
    "ks:ks_pop":913,
    "ks:ks_type":"HABITATION",
    "name:eng_x_preferred":[
        "Dablipada"
    ],
    "wof:name":"Dablipada",
    "wof:placetype":"locality",
    "wof:population":913
},
  "geometry": {"coordinates":[72.96423299999999,20.178515],"type":"Point"}
}