{
  "type": "Feature",
  "properties": {
    "iso:country":"IN",
    "ks:ks_name":"Inchha Kharkhari",
    "ks:ks_pop":637,
    "ks:ks_type":"VILLAGE",
    "name:eng_x_preferred":[
        "Inchha Kharkhari"
    ],
    "wof:name":"Inchha Kharkhari",
    "wof:placetype":"locality",
    "wof:population":637
},
  "geometry": {"coordinates":[75.621543,29.219957],"type":"Point"}
}