{
  "type": "Feature",
  "properties": {
    "iso:country":"IN",
    "ks:ks_name":"Bijjala",
    "ks:ks_pop":95,
    "ks:ks_type":"HABITATION",
    "name:eng_x_preferred":[
        "Bijjala"
    ],
    "wof:name":"Bijjala",
    "wof:placetype":"locality",
    "wof:population":95
},
  "geometry": {"coordinates":[75.194849,13.794673],"type":"Point"}
}