{
  "type": "Feature",
  "properties": {
    "gn:admin1_code":"3.0",
    "gn:admin2_code":"311.0",
    "gn:asciiname":"Chnagmai",
    "gn:country_code":"IN",
    "gn:dem":112,
    "gn:feature_class":"P",
    "gn:feature_code":"PPL",
    "gn:name":"Chnagmai",
    "gn:population":0,
    "gn:timezone":"Asia/Kolkata",
    "iso:country":"IN",
    "wof:name":"Chnagmai",
    "wof:placetype":"locality"
},
  "geometry": {"coordinates":[94.83262000000001,26.86904],"type":"Point"}
}