{
  "type": "Feature",
  "properties": {
    "iso:country":"IN",
    "ks:ks_name":"Haravadi",
    "ks:ks_pop":23,
    "ks:ks_type":"HABITATION",
    "name:eng_x_preferred":[
        "Haravadi"
    ],
    "wof:name":"Haravadi",
    "wof:placetype":"locality",
    "wof:population":23
},
  "geometry": {"coordinates":[74.720584,14.059968],"type":"Point"}
}