{
  "type": "Feature",
  "properties": {
    "iso:country":"IN",
    "ks:ks_alt_nam":"Didimbiri HC",
    "ks:ks_name":"Didimbiri Hc",
    "ks:ks_pop":220,
    "ks:ks_type":"HABITATION",
    "name:eng_x_preferred":[
        "Didimbiri Hc"
    ],
    "wof:name":"Didimbiri Hc",
    "wof:placetype":"locality",
    "wof:population":220
},
  "geometry": {"coordinates":[75.06914500000001,13.203986],"type":"Point"}
}