{
  "type": "Feature",
  "properties": {
    "iso:country":"IN",
    "ks:ks_name":"Natun Batabari",
    "ks:ks_pop":1455,
    "ks:ks_type":"HABITATION",
    "ks:ks_uagg_main":0,
    "name:eng_x_preferred":[
        "Natun Batabari"
    ],
    "wof:name":"Natun Batabari",
    "wof:placetype":"neighbourhood",
    "wof:population":1455
},
  "geometry": {"coordinates":[92.351704,26.377574],"type":"Point"}
}