{
  "type": "Feature",
  "properties": {
    "gn:admin1_code":"24",
    "gn:admin2_code":"105.0",
    "gn:asciiname":"Madhogarh",
    "gn:country_code":"IN",
    "gn:dem":202,
    "gn:feature_class":"P",
    "gn:feature_code":"PPL",
    "gn:name":"M\u0101dhogarh",
    "gn:population":0,
    "gn:timezone":"Asia/Kolkata",
    "iso:country":"IN",
    "name:und_x_variant":[
        "M\u0101dhogarh",
        "J\u0101gli"
    ],
    "wof:name":"Madhogarh",
    "wof:placetype":"locality"
},
  "geometry": {"coordinates":[77.05462,27.64192],"type":"Point"}
}