{
  "type": "Feature",
  "properties": {
    "iso:country":"IN",
    "ks:ks_name":"Gobardhandanga",
    "ks:ks_pop":2115,
    "ks:ks_type":"VILLAGE",
    "ks:ks_uagg_main":0,
    "name:eng_x_preferred":[
        "Gobardhandanga"
    ],
    "wof:name":"Gobardhandanga",
    "wof:placetype":"neighbourhood",
    "wof:population":2115
},
  "geometry": {"coordinates":[88.22560799999999,24.268657],"type":"Point"}
}