{
  "type": "Feature",
  "properties": {
    "iso:country":"IN",
    "ks:ks_name":"Badagakajekar",
    "ks:ks_pop":296,
    "ks:ks_type":"HABITATION",
    "name:eng_x_preferred":[
        "Badagakajekar"
    ],
    "wof:name":"Badagakajekar",
    "wof:placetype":"locality",
    "wof:population":296
},
  "geometry": {"coordinates":[75.18912899999999,12.898909],"type":"Point"}
}