{
  "type": "Feature",
  "properties": {
    "iso:country":"IN",
    "ks:ks_name":"Kotemal",
    "ks:ks_pop":81,
    "ks:ks_type":"HABITATION",
    "name:eng_x_preferred":[
        "Kotemal"
    ],
    "wof:name":"Kotemal",
    "wof:placetype":"locality",
    "wof:population":81
},
  "geometry": {"coordinates":[74.20150599999999,18.529212],"type":"Point"}
}