{
  "type": "Feature",
  "properties": {
    "iso:country":"IN",
    "ks:ks_name":"Kanchmahal",
    "ks:ks_pop":199,
    "ks:ks_type":"VILLAGE",
    "name:eng_x_preferred":[
        "Kanchmahal"
    ],
    "wof:name":"Kanchmahal",
    "wof:placetype":"locality",
    "wof:population":199
},
  "geometry": {"coordinates":[78.048171,18.344777],"type":"Point"}
}