{
  "type": "Feature",
  "properties": {
    "iso:country":"IN",
    "ks:ks_name":"Setramthanda",
    "ks:ks_pop":54,
    "ks:ks_type":"HABITATION",
    "name:eng_x_preferred":[
        "Setramthanda"
    ],
    "wof:name":"Setramthanda",
    "wof:placetype":"locality",
    "wof:population":54
},
  "geometry": {"coordinates":[79.77549399999999,17.373179],"type":"Point"}
}