{
  "type": "Feature",
  "properties": {
    "iso:country":"IN",
    "ks:ks_name":"Karnikalanka",
    "ks:ks_pop":214,
    "ks:ks_type":"HABITATION",
    "name:eng_x_preferred":[
        "Karnikalanka"
    ],
    "wof:name":"Karnikalanka",
    "wof:placetype":"locality",
    "wof:population":214
},
  "geometry": {"coordinates":[82.522913,18.0264],"type":"Point"}
}