{
  "type": "Feature",
  "properties": {
    "iso:country":"IN",
    "ks:ks_alt_nam":"MANDALEWASTI",
    "ks:ks_name":"Mandalewasti",
    "ks:ks_pop":77,
    "ks:ks_type":"HABITATION",
    "name:eng_x_preferred":[
        "Mandalewasti"
    ],
    "wof:name":"Mandalewasti",
    "wof:placetype":"locality",
    "wof:population":77
},
  "geometry": {"coordinates":[74.678393,17.071985],"type":"Point"}
}