{
  "type": "Feature",
  "properties": {
    "gn:admin1_code":"37.0",
    "gn:admin2_code":"416.0",
    "gn:asciiname":"Tongras",
    "gn:country_code":"IN",
    "gn:dem":321,
    "gn:feature_class":"P",
    "gn:feature_code":"PPL",
    "gn:name":"Tongr\u0101s",
    "gn:population":0,
    "gn:timezone":"Asia/Kolkata",
    "iso:country":"IN",
    "wof:name":"Tongras",
    "wof:placetype":"locality"
},
  "geometry": {"coordinates":[81.58091999999998,18.57231],"type":"Point"}
}