{
  "type": "Feature",
  "properties": {
    "iso:country":"IN",
    "ks:ks_alt_nam":"Monipur TE",
    "ks:ks_name":"Monipur Te",
    "ks:ks_pop":190,
    "ks:ks_type":"HABITATION",
    "name:eng_x_preferred":[
        "Monipur Te"
    ],
    "wof:name":"Monipur Te",
    "wof:placetype":"locality",
    "wof:population":190
},
  "geometry": {"coordinates":[92.5556,24.392332],"type":"Point"}
}