{
  "type": "Feature",
  "properties": {
    "gn:admin1_code":"17.0",
    "gn:admin2_code":"279",
    "gn:asciiname":"Hanggou",
    "gn:country_code":"IN",
    "gn:dem":1235,
    "gn:feature_class":"P",
    "gn:feature_code":"PPL",
    "gn:name":"Hanggou",
    "gn:population":0,
    "gn:timezone":"Asia/Kolkata",
    "iso:country":"IN",
    "name:und_x_variant":[
        "Hangao",
        "Hanggou"
    ],
    "wof:name":"Hanggou",
    "wof:placetype":"locality"
},
  "geometry": {"coordinates":[94.40401,24.89581],"type":"Point"}
}