{
  "type": "Feature",
  "properties": {
    "iso:country":"IN",
    "ks:ks_name":"Nagla Shes",
    "ks:ks_pop":498,
    "ks:ks_type":"HABITATION",
    "name:eng_x_preferred":[
        "Nagla Shes"
    ],
    "wof:name":"Nagla Shes",
    "wof:placetype":"locality",
    "wof:population":498
},
  "geometry": {"coordinates":[78.395886,27.693528],"type":"Point"}
}