{
  "type": "Feature",
  "properties": {
    "iso:country":"IN",
    "ks:ks_alt_nam":"Sithalur colony",
    "ks:ks_name":"Sithalur Colony",
    "ks:ks_pop":501,
    "ks:ks_type":"HABITATION",
    "name:eng_x_preferred":[
        "Sithalur Colony"
    ],
    "wof:name":"Sithalur Colony",
    "wof:placetype":"locality",
    "wof:population":501
},
  "geometry": {"coordinates":[79.48021799999999,11.888117],"type":"Point"}
}