{
  "type": "Feature",
  "properties": {
    "iso:country":"IN",
    "ks:ks_name":"Bagi Chandra Para",
    "ks:ks_pop":378,
    "ks:ks_type":"HABITATION",
    "name:eng_x_preferred":[
        "Bagi Chandra Para"
    ],
    "wof:name":"Bagi Chandra Para",
    "wof:placetype":"locality",
    "wof:population":378
},
  "geometry": {"coordinates":[92.21056299999999,23.822581],"type":"Point"}
}