{
  "type": "Feature",
  "properties": {
    "iso:country":"IN",
    "ks:ks_name":"Baghaila",
    "ks:ks_pop":338,
    "ks:ks_type":"HABITATION",
    "ks:ks_uagg_main":0,
    "name:eng_x_preferred":[
        "Baghaila"
    ],
    "wof:name":"Baghaila",
    "wof:placetype":"neighbourhood",
    "wof:population":338
},
  "geometry": {"coordinates":[82.580437,24.908524],"type":"Point"}
}