{
  "type": "Feature",
  "properties": {
    "gn:admin1_code":"35.0",
    "gn:admin2_code":"457.0",
    "gn:asciiname":"Wara",
    "gn:country_code":"IN",
    "gn:dem":307,
    "gn:feature_class":"P",
    "gn:feature_code":"PPL",
    "gn:name":"W\u0101ra",
    "gn:population":0,
    "gn:timezone":"Asia/Kolkata",
    "iso:country":"IN",
    "name:ceb_x_preferred":[
        "Wara"
    ],
    "name:deu_x_preferred":[
        "Wara"
    ],
    "name:fra_x_preferred":[
        "Wara"
    ],
    "name:swe_x_preferred":[
        "Wara"
    ],
    "wof:name":"Wara",
    "wof:placetype":"locality"
},
  "geometry": {"coordinates":[80.3729,21.62152],"type":"Point"}
}