{
  "type": "Feature",
  "properties": {
    "gn:admin1_code":"16.0",
    "gn:admin2_code":"527.0",
    "gn:asciiname":"Katarkhatav",
    "gn:country_code":"IN",
    "gn:dem":720,
    "gn:feature_class":"P",
    "gn:feature_code":"PPL",
    "gn:name":"K\u0101tarkhatav",
    "gn:population":0,
    "gn:timezone":"Asia/Kolkata",
    "iso:country":"IN",
    "wof:name":"Katarkhatav",
    "wof:placetype":"locality"
},
  "geometry": {"coordinates":[74.51990000000001,17.56668],"type":"Point"}
}