{
  "type": "Feature",
  "properties": {
    "iso:country":"IN",
    "ks:ks_name":"Rampur",
    "ks:ks_pop":398,
    "ks:ks_type":"VILLAGE",
    "name:eng_x_preferred":[
        "Rampur"
    ],
    "wof:name":"Rampur",
    "wof:placetype":"locality",
    "wof:population":398
},
  "geometry": {"coordinates":[82.919904,23.236112],"type":"Point"}
}