{
  "type": "Feature",
  "properties": {
    "gn:admin1_code":"35",
    "gn:admin2_code":"423.0",
    "gn:asciiname":"Tighri",
    "gn:country_code":"IN",
    "gn:dem":451,
    "gn:feature_class":"P",
    "gn:feature_code":"PPL",
    "gn:name":"Tighri",
    "gn:population":0,
    "gn:timezone":"Asia/Kolkata",
    "iso:country":"IN",
    "name:ara_x_preferred":[
        "\u062a\u064a\u063a\u0631\u064a"
    ],
    "name:ben_bn_x_preferred":[
        "\u09a4\u09bf\u0998\u09cd\u09b0\u09bf"
    ],
    "name:ben_in_x_preferred":[
        "\u09a4\u09bf\u0998\u09cd\u09b0\u09bf"
    ],
    "name:guj_x_preferred":[
        "\u0a9f\u0ac0\u0a98\u0ab0\u0ac0"
    ],
    "name:hin_x_preferred":[
        "\u0924\u093f\u0918\u0930\u0940"
    ],
    "name:kan_x_preferred":[
        "\u0ca4\u0cbf\u0c97\u0ccd\u0cb0\u0cbf"
    ],
    "name:mal_x_preferred":[
        "\u0d24\u0d3f\u0d17\u0d4d\u0d30\u0d3f"
    ],
    "name:mar_x_preferred":[
        "\u0924\u093f\u0918\u094d\u0930\u0940"
    ],
    "name:pan_x_preferred":[
        "\u0a1f\u0a3f\u0a18\u0a30\u0a40"
    ],
    "name:tam_x_preferred":[
        "\u0b9f\u0bbf\u0b95\u0bcd\u0bb0\u0bbf"
    ],
    "name:tel_x_preferred":[
        "\u0c1f\u0c3f\u0c18\u0c4d\u0c30\u0c3f"
    ],
    "name:urd_x_preferred":[
        "\u062a\u06af\u06be\u0691\u06cc"
    ],
    "wof:name":"Tighri",
    "wof:placetype":"locality"
},
  "geometry": {"coordinates":[77.50976,25.44017],"type":"Point"}
}