{
  "type": "Feature",
  "properties": {
    "gn:admin1_code":"35.0",
    "gn:admin2_code":"446",
    "gn:asciiname":"Dahod",
    "gn:country_code":"IN",
    "gn:dem":465,
    "gn:feature_class":"P",
    "gn:feature_code":"PPL",
    "gn:name":"D\u0101hod",
    "gn:population":0,
    "gn:timezone":"Asia/Kolkata",
    "iso:country":"IN",
    "name:ara_x_preferred":[
        "\u062f\u0627\u0647\u0648\u062f"
    ],
    "name:bpy_x_preferred":[
        "\u09a6\u09be\u09b9\u09cb\u09a6"
    ],
    "name:ceb_x_preferred":[
        "D\u0101hod"
    ],
    "name:fra_x_preferred":[
        "Dahod"
    ],
    "name:guj_x_preferred":[
        "\u0aa6\u0abe\u0ab9\u0acb\u0aa6"
    ],
    "name:hin_x_preferred":[
        "\u0926\u093e\u0939\u094b\u0926"
    ],
    "name:ita_x_preferred":[
        "Dahod"
    ],
    "name:jpn_x_preferred":[
        "\u30c0\u30fc\u30db\u30fc\u30c9"
    ],
    "name:mar_x_preferred":[
        "\u0926\u093e\u0939\u094b\u0926"
    ],
    "name:mlg_x_preferred":[
        "Dahod"
    ],
    "name:msa_x_preferred":[
        "Dohad"
    ],
    "name:new_x_preferred":[
        "\u0926\u094b\u0939\u093e\u0926"
    ],
    "name:pam_x_preferred":[
        "Dahod"
    ],
    "name:ron_x_preferred":[
        "Dahod"
    ],
    "name:rus_x_preferred":[
        "\u0414\u0430\u0445\u043e\u0434"
    ],
    "name:san_x_preferred":[
        "\u0926\u093e\u0939\u094b\u0926"
    ],
    "name:spa_x_preferred":[
        "Dahod"
    ],
    "name:swe_x_preferred":[
        "Dohad"
    ],
    "name:tam_x_preferred":[
        "\u0ba4\u0bbe\u0b95\u0bcb\u0ba4\u0bcd"
    ],
    "name:urd_x_preferred":[
        "\u062f\u0627\u0624\u062f"
    ],
    "name:vie_x_preferred":[
        "Dohad"
    ],
    "name:xmf_x_preferred":[
        "\u10d3\u10d0\u10f0\u10dd\u10d3\u10d8"
    ],
    "name:zho_x_preferred":[
        "\u591a\u54c8\u5fb7"
    ],
    "wof:name":"Dahod",
    "wof:placetype":"locality"
},
  "geometry": {"coordinates":[77.48980999999998,23.03621],"type":"Point"}
}