{
  "type": "Feature",
  "properties": {
    "iso:country":"IN",
    "ks:ks_name":"Chunau",
    "ks:ks_pop":56,
    "ks:ks_type":"HABITATION",
    "name:eng_x_preferred":[
        "Chunau"
    ],
    "wof:name":"Chunau",
    "wof:placetype":"locality",
    "wof:population":56
},
  "geometry": {"coordinates":[77.92426500000001,30.557727],"type":"Point"}
}