{
  "type": "Feature",
  "properties": {
    "iso:country":"IN",
    "ks:ks_name":"Bhagirath Reang Para",
    "ks:ks_pop":264,
    "ks:ks_type":"HABITATION",
    "name:eng_x_preferred":[
        "Bhagirath Reang Para"
    ],
    "wof:name":"Bhagirath Reang Para",
    "wof:placetype":"locality",
    "wof:population":264
},
  "geometry": {"coordinates":[91.764805,24.070285],"type":"Point"}
}