{
  "type": "Feature",
  "properties": {
    "gn:admin1_code":"12",
    "gn:admin2_code":"14.0",
    "gn:asciiname":"Silgom",
    "gn:country_code":"IN",
    "gn:dem":1714,
    "gn:feature_class":"P",
    "gn:feature_code":"PPL",
    "gn:name":"Silg\u014dm",
    "gn:population":0,
    "gn:timezone":"Asia/Kolkata",
    "iso:country":"IN",
    "wof:name":"Silgom",
    "wof:placetype":"locality"
},
  "geometry": {"coordinates":[75.24439,33.82245],"type":"Point"}
}