{
  "type": "Feature",
  "properties": {
    "gn:admin1_code":"39.0",
    "gn:admin2_code":"66.0",
    "gn:asciiname":"Phetua",
    "gn:country_code":"IN",
    "gn:dem":1355,
    "gn:feature_class":"P",
    "gn:feature_code":"PPL",
    "gn:name":"Phetua",
    "gn:population":0,
    "gn:timezone":"Asia/Kolkata",
    "iso:country":"IN",
    "wof:name":"Phetua",
    "wof:placetype":"locality"
},
  "geometry": {"coordinates":[79.70728000000003,29.33918],"type":"Point"}
}