{
  "type": "Feature",
  "properties": {
    "gn:admin1_code":"37.0",
    "gn:admin2_code":"410.0",
    "gn:asciiname":"Chuchrungpur",
    "gn:country_code":"IN",
    "gn:dem":272,
    "gn:feature_class":"P",
    "gn:feature_code":"PPL",
    "gn:name":"Chuchrungpur",
    "gn:population":0,
    "gn:timezone":"Asia/Kolkata",
    "iso:country":"IN",
    "wof:name":"Chuchrungpur",
    "wof:placetype":"locality"
},
  "geometry": {"coordinates":[82.04344,21.56242],"type":"Point"}
}