{
  "type": "Feature",
  "properties": {
    "iso:country":"IN",
    "ks:ks_name":"Apaliyas",
    "ks:ks_pop":845,
    "ks:ks_type":"HABITATION",
    "name:eng_x_preferred":[
        "Apaliyas"
    ],
    "wof:name":"Apaliyas",
    "wof:placetype":"locality",
    "wof:population":845
},
  "geometry": {"coordinates":[74.649083,25.723986],"type":"Point"}
}