{
  "type": "Feature",
  "properties": {
    "iso:country":"IN",
    "ks:ks_name":"Sarai Holi",
    "ks:ks_pop":1701,
    "ks:ks_type":"VILLAGE",
    "name:eng_x_preferred":[
        "Sarai Holi"
    ],
    "wof:name":"Sarai Holi",
    "wof:placetype":"locality",
    "wof:population":1701
},
  "geometry": {"coordinates":[80.36854099999999,26.112245],"type":"Point"}
}