{
  "type": "Feature",
  "properties": {
    "gn:admin1_code":"34.0",
    "gn:admin2_code":"216.0",
    "gn:asciiname":"Chandpur Fateh",
    "gn:country_code":"IN",
    "gn:dem":56,
    "gn:feature_class":"P",
    "gn:feature_code":"PPL",
    "gn:name":"Ch\u0101ndpur Fateh",
    "gn:population":0,
    "gn:timezone":"Asia/Kolkata",
    "iso:country":"IN",
    "ks:ks_alt_nam":"Ch\u0101ndpur Fateh",
    "ks:ks_name":"Chandpur Fateh",
    "ks:ks_pop":3092,
    "ks:ks_type":"VILLAGE",
    "name:eng_x_preferred":[
        "Chandpur Fateh"
    ],
    "name:eng_x_variant":[
        "Ch\u0101ndpur Fateh"
    ],
    "wof:name":"Chandpur Fateh",
    "wof:placetype":"locality",
    "wof:population":3092
},
  "geometry": {"coordinates":[85.490763,25.921605],"type":"Point"}
}