{
  "type": "Feature",
  "properties": {
    "iso:country":"IN",
    "ks:ks_name":"Bhopat Purwa",
    "ks:ks_pop":104,
    "ks:ks_type":"HABITATION",
    "ks:ks_uagg_main":0,
    "name:eng_x_preferred":[
        "Bhopat Purwa"
    ],
    "wof:name":"Bhopat Purwa",
    "wof:placetype":"neighbourhood",
    "wof:population":104
},
  "geometry": {"coordinates":[82.213161,26.927989],"type":"Point"}
}