{
  "type": "Feature",
  "properties": {
    "iso:country":"IN",
    "ks:ks_alt_nam":"J\u0101mun\u0101li",
    "ks:ks_name":"Jamunali",
    "ks:ks_pop":0,
    "ks:ks_type":"VILLAGE",
    "name:eng_x_preferred":[
        "Jamunali"
    ],
    "name:eng_x_variant":[
        "J\u0101mun\u0101li"
    ],
    "wof:name":"Jamunali",
    "wof:placetype":"locality",
    "wof:population":0
},
  "geometry": {"coordinates":[85.299515,21.063164],"type":"Point"}
}