{
  "type": "Feature",
  "properties": {
    "iso:country":"IN",
    "ks:ks_name":"Chandarkarwadi",
    "ks:ks_pop":51,
    "ks:ks_type":"HABITATION",
    "name:eng_x_preferred":[
        "Chandarkarwadi"
    ],
    "wof:name":"Chandarkarwadi",
    "wof:placetype":"locality",
    "wof:population":51
},
  "geometry": {"coordinates":[73.43111399999999,17.197117],"type":"Point"}
}