{
  "type": "Feature",
  "properties": {
    "gn:admin1_code":"12.0",
    "gn:admin2_code":"19.0",
    "gn:asciiname":"Palnun",
    "gn:country_code":"IN",
    "gn:dem":673,
    "gn:feature_class":"P",
    "gn:feature_code":"PPL",
    "gn:name":"Palnun",
    "gn:population":0,
    "gn:timezone":"Asia/Kolkata",
    "iso:country":"IN",
    "wof:name":"Palnun",
    "wof:placetype":"locality"
},
  "geometry": {"coordinates":[75.29331999999999,32.67529],"type":"Point"}
}