{
  "type": "Feature",
  "properties": {
    "gn:country":"IN",
    "gn:fcode":"PPL",
    "gn:population":29378,
    "iso:country":"IN",
    "name:ben_x_preferred":[
        "\u09aa\u09be\u09b2\u09be\u0995\u09cb\u09a8\u09cd\u09a1\u09be"
    ],
    "name:cat_x_preferred":[
        "Palakonda"
    ],
    "name:ceb_x_preferred":[
        "P\u0101lkonda"
    ],
    "name:deu_x_preferred":[
        "Palakonda"
    ],
    "name:eng_x_preferred":[
        "Palakonda"
    ],
    "name:fra_x_preferred":[
        "Palakonda"
    ],
    "name:guj_x_preferred":[
        "\u0aaa\u0abe\u0ab2\u0abe\u0a95\u0acb\u0aa8\u0acd\u0aa1\u0abe"
    ],
    "name:jpn_x_preferred":[
        "\u30d1\u30e9\u30b3\u30f3\u30c0"
    ],
    "name:kan_x_preferred":[
        "\u0caa\u0cbe\u0cb2\u0c95\u0cca\u0c82\u0ca1"
    ],
    "name:kor_x_preferred":[
        "\ud314\ub77c\ucf58\ub2e4"
    ],
    "name:new_x_preferred":[
        "\u092a\u093e\u0932\u0915\u094b\u0902\u0921 \u092e\u0923\u094d\u0921\u0932"
    ],
    "name:nld_x_preferred":[
        "Palakonda"
    ],
    "name:por_x_preferred":[
        "Palakonda"
    ],
    "name:rus_x_preferred":[
        "\u041f\u0430\u043b\u0430\u043a\u043e\u043d\u0434\u0430"
    ],
    "name:spa_x_preferred":[
        "Palakonda"
    ],
    "name:swe_x_preferred":[
        "P\u0101lkonda"
    ],
    "name:tam_x_preferred":[
        "\u0baa\u0bb2\u0b95\u0bca\u0ba3\u0bcd\u0b9f\u0bbe"
    ],
    "name:tel_x_colloquial":[
        "\u0c2a\u0c3e\u0c32\u0c15\u0c4a\u0c02\u0c21"
    ],
    "name:tel_x_historical":[
        "\u0c2a\u0c3e\u0c32\u0c15\u0c4a\u0c02\u0c21"
    ],
    "name:tel_x_preferred":[
        "\u0c2a\u0c3e\u0c32\u0c15\u0c4a\u0c02\u0c21"
    ],
    "name:urd_x_preferred":[
        "\u067e\u0627\u0644\u0627\u06a9\u0648\u0646\u0688\u0627"
    ],
    "qs:name":"P\u0101lkonda",
    "qs:photos_9r":0,
    "qs:photos_sr":0,
    "qs:pop_sr":"7",
    "wd:wordcount":333,
    "wof:name":"P\u0101lkonda",
    "wof:placetype":"locality",
    "wof:population":29378
},
  "geometry": {"coordinates":[83.75503999999999,18.60354],"type":"Point"}
}