{
  "type": "Feature",
  "properties": {
    "iso:country":"IN",
    "ks:ks_name":"Malkapur b",
    "ks:ks_pop":4,
    "ks:ks_type":"HABITATION",
    "name:eng_x_preferred":[
        "Malkapur b"
    ],
    "wof:name":"Malkapur b",
    "wof:placetype":"locality",
    "wof:population":4
},
  "geometry": {"coordinates":[77.764448,21.022009],"type":"Point"}
}