{
  "type": "Feature",
  "properties": {
    "iso:country":"IN",
    "ks:ks_name":"Jantha Colony",
    "ks:ks_pop":60,
    "ks:ks_type":"HABITATION",
    "ks:ks_uagg_main":0,
    "name:eng_x_preferred":[
        "Jantha Colony"
    ],
    "wof:name":"Jantha Colony",
    "wof:placetype":"neighbourhood",
    "wof:population":60
},
  "geometry": {"coordinates":[74.76061300000001,14.698448],"type":"Point"}
}