{
  "type": "Feature",
  "properties": {
    "gn:admin1_code":"16",
    "gn:admin2_code":"530.0",
    "gn:asciiname":"Yelvan",
    "gn:country_code":"IN",
    "gn:dem":773,
    "gn:feature_class":"P",
    "gn:feature_code":"PPL",
    "gn:name":"Yelvan",
    "gn:population":0,
    "gn:timezone":"Asia/Kolkata",
    "iso:country":"IN",
    "wof:name":"Yelvan",
    "wof:placetype":"locality"
},
  "geometry": {"coordinates":[73.82212,16.85366],"type":"Point"}
}