{
  "type": "Feature",
  "properties": {
    "gn:admin1_code":"21",
    "gn:admin2_code":"394.0",
    "gn:asciiname":"Duajhar",
    "gn:country_code":"IN",
    "gn:dem":239,
    "gn:feature_class":"P",
    "gn:feature_code":"PPL",
    "gn:name":"Du\u0101jhar",
    "gn:population":0,
    "gn:timezone":"Asia/Kolkata",
    "iso:country":"IN",
    "wof:name":"Duajhar",
    "wof:placetype":"locality"
},
  "geometry": {"coordinates":[82.74829,20.23414],"type":"Point"}
}