{
  "type": "Feature",
  "properties": {
    "gn:admin1_code":"36.0",
    "gn:admin2_code":"138.0",
    "gn:asciiname":"Pachgaon",
    "gn:country_code":"IN",
    "gn:dem":224,
    "gn:feature_class":"P",
    "gn:feature_code":"PPL",
    "gn:name":"Pachgaon",
    "gn:population":0,
    "gn:timezone":"Asia/Kolkata",
    "iso:country":"IN",
    "name:und_x_variant":[
        "Patti Amarsingh"
    ],
    "wof:name":"Pachgaon",
    "wof:placetype":"locality"
},
  "geometry": {"coordinates":[77.82544,28.93069],"type":"Point"}
}