{
  "type": "Feature",
  "properties": {
    "gn:admin1_code":"35.0",
    "gn:admin2_code":"419.0",
    "gn:asciiname":"Lohabasai",
    "gn:country_code":"IN",
    "gn:dem":202,
    "gn:feature_class":"P",
    "gn:feature_code":"PPL",
    "gn:name":"Loh\u0101basai",
    "gn:population":0,
    "gn:timezone":"Asia/Kolkata",
    "iso:country":"IN",
    "ks:ks_name":"Loha Basai",
    "ks:ks_pop":1675,
    "ks:ks_type":"VILLAGE",
    "name:eng_x_preferred":[
        "Loha Basai"
    ],
    "name:eng_x_variant":[
        "Lohabasai"
    ],
    "wof:name":"Loha Basai",
    "wof:placetype":"locality",
    "wof:population":1675
},
  "geometry": {"coordinates":[77.910585,26.316142],"type":"Point"}
}