{
  "type": "Feature",
  "properties": {
    "gn:admin1_code":"38",
    "gn:admin2_code":"346.0",
    "gn:asciiname":"Loka",
    "gn:country_code":"IN",
    "gn:dem":189,
    "gn:feature_class":"P",
    "gn:feature_code":"PPL",
    "gn:name":"Loka",
    "gn:population":0,
    "gn:timezone":"Asia/Kolkata",
    "iso:country":"IN",
    "name:fra_x_preferred":[
        "Loka"
    ],
    "name:hin_x_preferred":[
        "\u0932\u094b\u0915"
    ],
    "name:hun_x_preferred":[
        "L\u00f3ka"
    ],
    "name:kan_x_preferred":[
        "\u0cb2\u0ccb\u0c95"
    ],
    "name:lit_x_preferred":[
        "Loka"
    ],
    "name:pol_x_preferred":[
        "Loka"
    ],
    "name:por_x_preferred":[
        "Loka"
    ],
    "name:rus_x_preferred":[
        "\u041b\u043e\u043a\u0430"
    ],
    "name:slk_x_preferred":[
        "L\u00f3ka"
    ],
    "name:slv_x_preferred":[
        "Loka"
    ],
    "name:srp_x_preferred":[
        "\u0421\u0432\u0435\u0442"
    ],
    "name:tam_x_preferred":[
        "\u0bb2\u0bcb\u0b95\u0bae\u0bcd"
    ],
    "name:ukr_x_preferred":[
        "\u041b\u043e\u043a\u0430"
    ],
    "name:urd_x_preferred":[
        "\u0644\u0648\u06a9"
    ],
    "wof:name":"Loka",
    "wof:placetype":"locality"
},
  "geometry": {"coordinates":[83.73522,24.35198],"type":"Point"}
}