{
  "type": "Feature",
  "properties": {
    "iso:country":"IN",
    "ks:ks_name":"Palavwadi",
    "ks:ks_pop":531,
    "ks:ks_type":"HABITATION",
    "name:eng_x_preferred":[
        "Palavwadi"
    ],
    "wof:name":"Palavwadi",
    "wof:placetype":"locality",
    "wof:population":531
},
  "geometry": {"coordinates":[73.89601,16.20214],"type":"Point"}
}