{
  "type": "Feature",
  "properties": {
    "iso:country":"IN",
    "ks:ks_name":"Upper Anchalbadi",
    "ks:ks_pop":126,
    "ks:ks_type":"VILLAGE",
    "name:eng_x_preferred":[
        "Upper Anchalbadi"
    ],
    "wof:name":"Upper Anchalbadi",
    "wof:placetype":"locality",
    "wof:population":126
},
  "geometry": {"coordinates":[83.280182,19.273836],"type":"Point"}
}