{
  "type": "Feature",
  "properties": {
    "iso:country":"IN",
    "ks:ks_name":"Majara Kalan",
    "ks:ks_pop":19,
    "ks:ks_type":"VILLAGE",
    "name:eng_x_preferred":[
        "Majara Kalan"
    ],
    "wof:name":"Majara Kalan",
    "wof:placetype":"locality",
    "wof:population":19
},
  "geometry": {"coordinates":[75.74459899999999,31.001136],"type":"Point"}
}