{
  "type": "Feature",
  "properties": {
    "iso:country":"IN",
    "ks:ks_name":"Pukhuripar",
    "ks:ks_pop":458,
    "ks:ks_type":"VILLAGE",
    "name:eng_x_preferred":[
        "Pukhuripar"
    ],
    "wof:name":"Pukhuripar",
    "wof:placetype":"locality",
    "wof:population":458
},
  "geometry": {"coordinates":[91.257091,26.081993],"type":"Point"}
}