{
  "type": "Feature",
  "properties": {
    "gn:admin1_code":"10.0",
    "gn:admin2_code":"86.0",
    "gn:asciiname":"Khaintawas",
    "gn:country_code":"IN",
    "gn:dem":221,
    "gn:feature_class":"P",
    "gn:feature_code":"PPL",
    "gn:name":"Khaint\u0101w\u0101s",
    "gn:population":0,
    "gn:timezone":"Asia/Kolkata",
    "iso:country":"IN",
    "wof:name":"Khaintawas",
    "wof:placetype":"locality"
},
  "geometry": {"coordinates":[76.87826,28.43805],"type":"Point"}
}