{
  "type": "Feature",
  "properties": {
    "iso:country":"IN",
    "ks:ks_name":"Chikhalwadi",
    "ks:ks_pop":118,
    "ks:ks_type":"HABITATION",
    "name:eng_x_preferred":[
        "Chikhalwadi"
    ],
    "wof:name":"Chikhalwadi",
    "wof:placetype":"locality",
    "wof:population":118
},
  "geometry": {"coordinates":[73.72416699999999,18.883889],"type":"Point"}
}