{
  "type": "Feature",
  "properties": {
    "iso:country":"IN",
    "ks:ks_name":"Belkhera Protected Forest",
    "ks:ks_type":"VILLAGE",
    "name:eng_x_preferred":[
        "Belkhera Protected Forest"
    ],
    "wof:name":"Belkhera Protected Forest",
    "wof:placetype":"locality"
},
  "geometry": {"coordinates":[78.572378,22.405237],"type":"Point"}
}