{
  "type": "Feature",
  "properties": {
    "gn:admin1_code":"36",
    "gn:admin2_code":"191.0",
    "gn:asciiname":"Usraha",
    "gn:country_code":"IN",
    "gn:dem":90,
    "gn:feature_class":"P",
    "gn:feature_code":"PPL",
    "gn:name":"Usraha",
    "gn:population":0,
    "gn:timezone":"Asia/Kolkata",
    "iso:country":"IN",
    "ks:ks_name":"Usraha",
    "ks:ks_pop":1491,
    "ks:ks_type":"VILLAGE",
    "ks:ks_uagg_main":0,
    "name:eng_x_preferred":[
        "Usraha"
    ],
    "wof:name":"Usraha",
    "wof:placetype":"neighbourhood",
    "wof:population":1491
},
  "geometry": {"coordinates":[82.72392000000001,26.256001],"type":"Point"}
}