{
  "type": "Feature",
  "properties": {
    "gn:admin1_code":"11",
    "gn:admin2_code":"33.0",
    "gn:asciiname":"Serti",
    "gn:country_code":"IN",
    "gn:dem":2321,
    "gn:feature_class":"P",
    "gn:feature_code":"PPL",
    "gn:name":"Serti",
    "gn:population":0,
    "gn:timezone":"Asia/Kolkata",
    "iso:country":"IN",
    "wof:name":"Serti",
    "wof:placetype":"locality"
},
  "geometry": {"coordinates":[77.62260000000001,30.8621],"type":"Point"}
}