{
  "type": "Feature",
  "properties": {
    "iso:country":"IN",
    "ks:ks_name":"Jaradanga",
    "ks:ks_pop":19,
    "ks:ks_type":"VILLAGE",
    "name:eng_x_preferred":[
        "Jaradanga"
    ],
    "wof:name":"Jaradanga",
    "wof:placetype":"locality",
    "wof:population":19
},
  "geometry": {"coordinates":[83.864816,20.276809],"type":"Point"}
}