{
  "type": "Feature",
  "properties": {
    "gn:admin1_code":"35",
    "gn:admin2_code":"428.0",
    "gn:asciiname":"Anjani",
    "gn:country_code":"IN",
    "gn:dem":355,
    "gn:feature_class":"P",
    "gn:feature_code":"PPL",
    "gn:name":"\u0100njani",
    "gn:population":0,
    "gn:timezone":"Asia/Kolkata",
    "iso:country":"IN",
    "name:azb_x_preferred":[
        "\u0627\u0646\u062c\u0627\u0646\u06cc \u062a\u0648\u0645\u0627\u0633"
    ],
    "name:ces_x_preferred":[
        "Anjani"
    ],
    "name:deu_x_preferred":[
        "Anjani"
    ],
    "name:fas_x_preferred":[
        "\u0627\u0646\u062c\u0627\u0646\u06cc \u062a\u0648\u0645\u0627\u0633"
    ],
    "name:fra_x_preferred":[
        "Anjani Thomas"
    ],
    "name:heb_x_preferred":[
        "\u05d0\u05e0\u05d2'\u05d0\u05e0\u05d9"
    ],
    "name:ita_x_preferred":[
        "Anjani"
    ],
    "name:mar_x_preferred":[
        "\u0905\u0902\u091c\u0928\u0940 \u0925\u0949\u092e\u0938"
    ],
    "name:nor_x_preferred":[
        "Anjani Thomas"
    ],
    "name:pol_x_preferred":[
        "Anjani Thomas"
    ],
    "name:spa_x_preferred":[
        "Anjani"
    ],
    "wof:name":"Anjani",
    "wof:placetype":"locality"
},
  "geometry": {"coordinates":[79.42232,24.13281],"type":"Point"}
}