{
  "type": "Feature",
  "properties": {
    "iso:country":"IN",
    "ks:ks_name":"Nagla Nagli",
    "ks:ks_pop":533,
    "ks:ks_type":"VILLAGE",
    "ks:ks_uagg_main":0,
    "name:eng_x_preferred":[
        "Nagla Nagli"
    ],
    "wof:name":"Nagla Nagli",
    "wof:placetype":"neighbourhood",
    "wof:population":533
},
  "geometry": {"coordinates":[77.37964100000001,28.499159],"type":"Point"}
}