{
  "type": "Feature",
  "properties": {
    "iso:country":"IN",
    "ks:ks_name":"Jalipada",
    "ks:ks_pop":45,
    "ks:ks_type":"HABITATION",
    "name:eng_x_preferred":[
        "Jalipada"
    ],
    "wof:name":"Jalipada",
    "wof:placetype":"locality",
    "wof:population":45
},
  "geometry": {"coordinates":[82.61408900000001,19.720773],"type":"Point"}
}