{
  "type": "Feature",
  "properties": {
    "iso:country":"IN",
    "ks:ks_name":"Jot Harananda",
    "ks:ks_pop":324,
    "ks:ks_type":"VILLAGE",
    "name:eng_x_preferred":[
        "Jot Harananda"
    ],
    "wof:name":"Jot Harananda",
    "wof:placetype":"locality",
    "wof:population":324
},
  "geometry": {"coordinates":[88.15007799999999,22.957679],"type":"Point"}
}