{
  "type": "Feature",
  "properties": {
    "iso:country":"IN",
    "ks:ks_name":"Junaparana",
    "ks:ks_pop":168,
    "ks:ks_type":"VILLAGE",
    "name:eng_x_preferred":[
        "Junaparana"
    ],
    "wof:name":"Junaparana",
    "wof:placetype":"locality",
    "wof:population":168
},
  "geometry": {"coordinates":[75.174452,24.935988],"type":"Point"}
}