{
  "type": "Feature",
  "properties": {
    "gn:admin1_code":"3.0",
    "gn:admin2_code":"305.0",
    "gn:asciiname":"Madhatari",
    "gn:country_code":"IN",
    "gn:dem":70,
    "gn:feature_class":"P",
    "gn:feature_code":"PPL",
    "gn:name":"Madhatari",
    "gn:population":0,
    "gn:timezone":"Asia/Kolkata",
    "iso:country":"IN",
    "wof:name":"Madhatari",
    "wof:placetype":"locality"
},
  "geometry": {"coordinates":[92.96006,26.58638],"type":"Point"}
}