{
  "type": "Feature",
  "properties": {
    "iso:country":"IN",
    "ks:ks_name":"Daldali",
    "ks:ks_pop":228,
    "ks:ks_type":"VILLAGE",
    "name:eng_x_preferred":[
        "Daldali"
    ],
    "wof:name":"Daldali",
    "wof:placetype":"locality",
    "wof:population":228
},
  "geometry": {"coordinates":[86.978388,24.320164],"type":"Point"}
}