{
  "type": "Feature",
  "properties": {
    "iso:country":"IN",
    "ks:ks_alt_nam":"Kasiy\u0101dih",
    "ks:ks_name":"Kasiyadih",
    "ks:ks_pop":585,
    "ks:ks_type":"VILLAGE",
    "name:eng_x_preferred":[
        "Kasiyadih"
    ],
    "name:eng_x_variant":[
        "Kasiy\u0101dih"
    ],
    "wof:name":"Kasiyadih",
    "wof:placetype":"locality",
    "wof:population":585
},
  "geometry": {"coordinates":[84.64970700000001,23.544311],"type":"Point"}
}