{
  "type": "Feature",
  "properties": {
    "iso:country":"IN",
    "ks:ks_name":"Ramera",
    "ks:ks_pop":894,
    "ks:ks_type":"VILLAGE",
    "name:eng_x_preferred":[
        "Ramera"
    ],
    "wof:name":"Ramera",
    "wof:placetype":"locality",
    "wof:population":894
},
  "geometry": {"coordinates":[73.452167,23.712556],"type":"Point"}
}