{
  "type": "Feature",
  "properties": {
    "iso:country":"IN",
    "ks:ks_alt_nam":"tengadapather",
    "ks:ks_name":"Tengadapather",
    "ks:ks_pop":45,
    "ks:ks_type":"HABITATION",
    "name:eng_x_preferred":[
        "Tengadapather"
    ],
    "wof:name":"Tengadapather",
    "wof:placetype":"locality",
    "wof:population":45
},
  "geometry": {"coordinates":[84.279932,20.337094],"type":"Point"}
}