{
  "type": "Feature",
  "properties": {
    "gn:admin1_code":"12.0",
    "gn:admin2_code":"008",
    "gn:asciiname":"Tsipadaij",
    "gn:country_code":"IN",
    "gn:dem":1699,
    "gn:feature_class":"P",
    "gn:feature_code":"PPL",
    "gn:name":"Tsipada\u012bj",
    "gn:population":0,
    "gn:timezone":"Asia/Kolkata",
    "iso:country":"IN",
    "wof:name":"Tsipadaij",
    "wof:placetype":"locality"
},
  "geometry": {"coordinates":[74.27046,34.30494],"type":"Point"}
}