{
  "type": "Feature",
  "properties": {
    "iso:country":"IN",
    "ks:ks_name":"Nai Ledri",
    "ks:ks_pop":6541,
    "ks:ks_type":"HABITATION",
    "name:eng_x_preferred":[
        "Nai Ledri"
    ],
    "wof:name":"Nai Ledri",
    "wof:placetype":"locality",
    "wof:population":6541
},
  "geometry": {"coordinates":[82.19167299999999,23.172558],"type":"Point"}
}