{
  "type": "Feature",
  "properties": {
    "iso:country":"IN",
    "ks:ks_name":"Kajaltor",
    "ks:ks_pop":0,
    "ks:ks_type":"VILLAGE",
    "name:eng_x_preferred":[
        "Kajaltor"
    ],
    "wof:name":"Kajaltor",
    "wof:placetype":"locality",
    "wof:population":0
},
  "geometry": {"coordinates":[88.790098,25.410875],"type":"Point"}
}