{
  "type": "Feature",
  "properties": {
    "gn:admin1_code":"19.0",
    "gn:admin2_code":"576.0",
    "gn:asciiname":"Chenivada",
    "gn:country_code":"IN",
    "gn:dem":829,
    "gn:feature_class":"P",
    "gn:feature_code":"PPLL",
    "gn:name":"Chenivada",
    "gn:population":0,
    "gn:timezone":"Asia/Kolkata",
    "iso:country":"IN",
    "wof:name":"Chenivada",
    "wof:placetype":"locality"
},
  "geometry": {"coordinates":[75.91806,12.11292],"type":"Point"}
}