{
  "type": "Feature",
  "properties": {
    "gn:admin1_code":"36",
    "gn:admin2_code":"158.0",
    "gn:asciiname":"Pura Lalji",
    "gn:country_code":"IN",
    "gn:dem":115,
    "gn:feature_class":"P",
    "gn:feature_code":"PPL",
    "gn:name":"Pura L\u0101lji",
    "gn:population":0,
    "gn:timezone":"Asia/Kolkata",
    "iso:country":"IN",
    "ks:ks_name":"Pure Lalji",
    "ks:ks_pop":130,
    "ks:ks_type":"HABITATION",
    "name:eng_x_preferred":[
        "Pure Lalji"
    ],
    "name:eng_x_variant":[
        "Pura Lalji"
    ],
    "wof:name":"Pure Lalji",
    "wof:placetype":"locality",
    "wof:population":130
},
  "geometry": {"coordinates":[81.332331,26.007426],"type":"Point"}
}