{
  "type": "Feature",
  "properties": {
    "gn:admin1_code":"35.0",
    "gn:admin2_code":"442.0",
    "gn:asciiname":"Rawatpura",
    "gn:country_code":"IN",
    "gn:dem":466,
    "gn:feature_class":"P",
    "gn:feature_code":"PPL",
    "gn:name":"R\u0101watpura",
    "gn:population":0,
    "gn:timezone":"Asia/Kolkata",
    "iso:country":"IN",
    "wof:name":"Rawatpura",
    "wof:placetype":"locality"
},
  "geometry": {"coordinates":[76.85349000000002,23.5586],"type":"Point"}
}