{
  "type": "Feature",
  "properties": {
    "iso:country":"IN",
    "ks:ks_name":"Balagodu",
    "ks:ks_pop":9,
    "ks:ks_type":"HABITATION",
    "name:eng_x_preferred":[
        "Balagodu"
    ],
    "wof:name":"Balagodu",
    "wof:placetype":"locality",
    "wof:population":9
},
  "geometry": {"coordinates":[75.185811,13.729018],"type":"Point"}
}