{
  "type": "Feature",
  "properties": {
    "iso:country":"IN",
    "ks:ks_alt_nam":"LALGOL BASA",
    "ks:ks_name":"Lalgol Basa",
    "ks:ks_pop":245,
    "ks:ks_type":"HABITATION",
    "ks:ks_uagg_main":0,
    "name:eng_x_preferred":[
        "Lalgol Basa"
    ],
    "wof:name":"Lalgol Basa",
    "wof:placetype":"neighbourhood",
    "wof:population":245
},
  "geometry": {"coordinates":[86.783551,25.576387],"type":"Point"}
}