{
  "type": "Feature",
  "properties": {
    "iso:country":"IN",
    "ks:ks_name":"Temari",
    "ks:ks_pop":1136,
    "ks:ks_type":"HABITATION",
    "name:eng_x_preferred":[
        "Temari"
    ],
    "wof:name":"Temari",
    "wof:placetype":"locality",
    "wof:population":1136
},
  "geometry": {"coordinates":[81.16775,21.282199],"type":"Point"}
}