{
  "type": "Feature",
  "properties": {
    "iso:country":"IN",
    "ks:ks_name":"Kuchli",
    "ks:ks_pop":1108,
    "ks:ks_type":"VILLAGE",
    "name:eng_x_preferred":[
        "Kuchli"
    ],
    "wof:name":"Kuchli",
    "wof:placetype":"locality",
    "wof:population":1108
},
  "geometry": {"coordinates":[87.412199,22.153339],"type":"Point"}
}