{
  "type": "Feature",
  "properties": {
    "iso:country":"IN",
    "ks:ks_name":"Pujariguda1",
    "ks:ks_pop":160,
    "ks:ks_type":"HABITATION",
    "name:eng_x_preferred":[
        "Pujariguda1"
    ],
    "wof:name":"Pujariguda1",
    "wof:placetype":"locality",
    "wof:population":160
},
  "geometry": {"coordinates":[82.554363,19.141857],"type":"Point"}
}