{
  "type": "Feature",
  "properties": {
    "gn:admin1_code":"35",
    "gn:admin2_code":"428.0",
    "gn:asciiname":"Khaira",
    "gn:country_code":"IN",
    "gn:dem":314,
    "gn:feature_class":"P",
    "gn:feature_code":"PPL",
    "gn:name":"Khaira",
    "gn:population":0,
    "gn:timezone":"Asia/Kolkata",
    "iso:country":"IN",
    "name:eng_x_preferred":[
        "Khaira"
    ],
    "name:hin_x_preferred":[
        "\u0916\u0948\u0930\u093e"
    ],
    "name:new_x_preferred":[
        "\u0916\u0948\u0930\u093e"
    ],
    "wof:name":"Khaira",
    "wof:placetype":"locality"
},
  "geometry": {"coordinates":[79.79401,24.31255],"type":"Point"}
}