{
  "type": "Feature",
  "properties": {
    "gn:admin1_code":"36",
    "gn:admin2_code":"176.0",
    "gn:asciiname":"Baikunthipur",
    "gn:country_code":"IN",
    "gn:dem":126,
    "gn:feature_class":"P",
    "gn:feature_code":"PPL",
    "gn:name":"Baikunthipur",
    "gn:population":0,
    "gn:timezone":"Asia/Kolkata",
    "iso:country":"IN",
    "wof:name":"Baikunthipur",
    "wof:placetype":"locality"
},
  "geometry": {"coordinates":[81.1053,27.18729],"type":"Point"}
}