{
  "type": "Feature",
  "properties": {
    "iso:country":"IN",
    "ks:ks_name":"Khiriya Ta Papda",
    "ks:ks_pop":108,
    "ks:ks_type":"VILLAGE",
    "name:eng_x_preferred":[
        "Khiriya Ta Papda"
    ],
    "wof:name":"Khiriya Ta Papda",
    "wof:placetype":"locality",
    "wof:population":108
},
  "geometry": {"coordinates":[78.456519,23.458315],"type":"Point"}
}