{
  "type": "Feature",
  "properties": {
    "iso:country":"IN",
    "ks:ks_name":"Dattawadi",
    "ks:ks_pop":272,
    "ks:ks_type":"HABITATION",
    "name:eng_x_preferred":[
        "Dattawadi"
    ],
    "wof:name":"Dattawadi",
    "wof:placetype":"locality",
    "wof:population":272
},
  "geometry": {"coordinates":[73.633867,18.704237],"type":"Point"}
}