{
  "type": "Feature",
  "properties": {
    "iso:country":"IN",
    "ks:ks_name":"Kholvada",
    "ks:ks_pop":591,
    "ks:ks_type":"VILLAGE",
    "ks:ks_uagg_main":0,
    "name:eng_x_preferred":[
        "Kholvada"
    ],
    "wof:name":"Kholvada",
    "wof:placetype":"neighbourhood",
    "wof:population":591
},
  "geometry": {"coordinates":[72.35447000000001,23.90903],"type":"Point"}
}