{
  "type": "Feature",
  "properties": {
    "gn:admin1_code":"19.0",
    "gn:admin2_code":"583.0",
    "gn:asciiname":"Mallapur",
    "gn:country_code":"IN",
    "gn:dem":894,
    "gn:feature_class":"P",
    "gn:feature_code":"PPL",
    "gn:name":"Mallapur",
    "gn:population":0,
    "gn:timezone":"Asia/Kolkata",
    "iso:country":"IN",
    "name:ara_x_preferred":[
        "\u0645\u0627\u0644\u0627\u0628\u0648\u0631"
    ],
    "name:ben_bn_x_preferred":[
        "\u09ae\u09be\u09b2\u09cd\u09b2\u09be\u09aa\u09c1\u09b0"
    ],
    "name:ben_in_x_preferred":[
        "\u09ae\u09b2\u09cd\u09b2\u09aa\u09c1\u09b0"
    ],
    "name:guj_x_preferred":[
        "\u0aae\u0ab2\u0acd\u0ab2\u0aaa\u0ac1\u0ab0"
    ],
    "name:hin_x_preferred":[
        "\u092e\u0932\u094d\u0932\u093e\u092a\u0941\u0930"
    ],
    "name:kan_x_preferred":[
        "\u0cae\u0cb2\u0ccd\u0cb2\u0cbe\u0caa\u0cc1\u0cb0"
    ],
    "name:mal_x_preferred":[
        "\u0d2e\u0d32\u0d4d\u0d32\u0d3e\u0d2a\u0d4d\u0d2a\u0d42\u0d30\u0d4d\u200d"
    ],
    "name:mar_x_preferred":[
        "\u092e\u0932\u094d\u0932\u093e\u092a\u0942\u0930"
    ],
    "name:pam_x_preferred":[
        "Mallapur"
    ],
    "name:pan_x_preferred":[
        "\u0a2e\u0a71\u0a32\u0a3e\u0a2a\u0a41\u0a30"
    ],
    "name:tam_x_preferred":[
        "\u0bae\u0bb2\u0bcd\u0bb2\u0bbe\u0baa\u0bc2\u0bb0\u0bcd"
    ],
    "name:tel_x_preferred":[
        "\u0c2e\u0c32\u0c4d\u0c32\u0c3e\u0c2a\u0c42\u0c30\u0c4d"
    ],
    "name:urd_x_preferred":[
        "\u0645\u0644\u0627 \u067e\u0648\u0631"
    ],
    "wof:name":"Mallapur",
    "wof:placetype":"locality"
},
  "geometry": {"coordinates":[77.39968,13.07438],"type":"Point"}
}