{
  "type": "Feature",
  "properties": {
    "iso:country":"IN",
    "ks:ks_name":"Khori Faliya",
    "ks:ks_pop":40,
    "ks:ks_type":"HABITATION",
    "name:eng_x_preferred":[
        "Khori Faliya"
    ],
    "wof:name":"Khori Faliya",
    "wof:placetype":"locality",
    "wof:population":40
},
  "geometry": {"coordinates":[73.231278,20.462667],"type":"Point"}
}