{
  "type": "Feature",
  "properties": {
    "iso:country":"IN",
    "ks:ks_name":"Sadpur Inglish",
    "ks:ks_pop":0,
    "ks:ks_type":"VILLAGE",
    "name:eng_x_preferred":[
        "Sadpur Inglish"
    ],
    "wof:name":"Sadpur Inglish",
    "wof:placetype":"locality",
    "wof:population":0
},
  "geometry": {"coordinates":[86.729069,25.176892],"type":"Point"}
}