{
  "type": "Feature",
  "properties": {
    "iso:country":"IN",
    "ks:ks_name":"Jogiabari",
    "ks:ks_pop":506,
    "ks:ks_type":"HABITATION",
    "name:eng_x_preferred":[
        "Jogiabari"
    ],
    "wof:name":"Jogiabari",
    "wof:placetype":"locality",
    "wof:population":506
},
  "geometry": {"coordinates":[82.29657400000001,24.820923],"type":"Point"}
}