{
  "type": "Feature",
  "properties": {
    "iso:country":"IN",
    "ks:ks_alt_nam":"B colony",
    "ks:ks_name":"B Colony",
    "ks:ks_pop":180,
    "ks:ks_type":"HABITATION",
    "ks:ks_uagg_main":0,
    "name:eng_x_preferred":[
        "B Colony"
    ],
    "wof:name":"B Colony",
    "wof:placetype":"neighbourhood",
    "wof:population":180
},
  "geometry": {"coordinates":[82.06040400000001,18.257565],"type":"Point"}
}