{
  "type": "Feature",
  "properties": {
    "iso:country":"IN",
    "ks:ks_name":"Gulalpur",
    "ks:ks_pop":1258,
    "ks:ks_type":"HABITATION",
    "name:eng_x_preferred":[
        "Gulalpur"
    ],
    "wof:name":"Gulalpur",
    "wof:placetype":"locality",
    "wof:population":1258
},
  "geometry": {"coordinates":[78.622499,26.923088],"type":"Point"}
}