{
  "type": "Feature",
  "properties": {
    "iso:country":"IN",
    "ks:ks_name":"Mathiya",
    "ks:ks_pop":756,
    "ks:ks_type":"HABITATION",
    "name:eng_x_preferred":[
        "Mathiya"
    ],
    "wof:name":"Mathiya",
    "wof:placetype":"locality",
    "wof:population":756
},
  "geometry": {"coordinates":[83.995288,25.504112],"type":"Point"}
}