{
  "type": "Feature",
  "properties": {
    "gn:admin1_code":"34.0",
    "gn:admin2_code":"224.0",
    "gn:asciiname":"Danda Bazar",
    "gn:country_code":"IN",
    "gn:dem":41,
    "gn:feature_class":"P",
    "gn:feature_code":"PPL",
    "gn:name":"Danda B\u0101z\u0101r",
    "gn:population":0,
    "gn:timezone":"Asia/Kolkata",
    "iso:country":"IN",
    "ks:ks_alt_nam":"Danda B\u0101z\u0101r",
    "ks:ks_name":"Danda Bazar",
    "ks:ks_type":"VILLAGE",
    "ks:ks_uagg_main":0,
    "name:bih_x_preferred":[
        "\u0921\u093e\u0901\u0921\u093e\u092c\u091c\u093e\u0930"
    ],
    "name:ceb_x_preferred":[
        "Danda Bazar"
    ],
    "name:eng_x_preferred":[
        "Danda Bazar"
    ],
    "name:eng_x_variant":[
        "Danda B\u0101z\u0101r"
    ],
    "name:mai_x_preferred":[
        "\u0921\u093e\u0901\u0921\u093e\u092c\u091c\u093e\u0930"
    ],
    "name:nep_x_preferred":[
        "\u0921\u093e\u0901\u0921\u093e\u092c\u091c\u093e\u0930"
    ],
    "name:new_x_preferred":[
        "\u0926\u0923\u094d\u0921 \u092c\u091c\u093e\u0930"
    ],
    "name:pol_x_preferred":[
        "Danda Bazar"
    ],
    "wof:name":"Danda Bazar",
    "wof:placetype":"neighbourhood"
},
  "geometry": {"coordinates":[87.016683,25.148176],"type":"Point"}
}