{
  "type": "Feature",
  "properties": {
    "gn:admin1_code":"37",
    "gn:admin2_code":"410.0",
    "gn:asciiname":"Chhuiha",
    "gn:country_code":"IN",
    "gn:dem":252,
    "gn:feature_class":"P",
    "gn:feature_code":"PPL",
    "gn:name":"Chhuiha",
    "gn:population":0,
    "gn:timezone":"Asia/Kolkata",
    "iso:country":"IN",
    "ks:ks_name":"Chhuiha",
    "ks:ks_type":"VILLAGE",
    "name:eng_x_preferred":[
        "Chhuiha"
    ],
    "wof:name":"Chhuiha",
    "wof:placetype":"locality"
},
  "geometry": {"coordinates":[82.212525,21.668093],"type":"Point"}
}