{
  "type": "Feature",
  "properties": {
    "gn:admin1_code":"19.0",
    "gn:admin2_code":"574.0",
    "gn:asciiname":"Muddanahalli",
    "gn:country_code":"IN",
    "gn:dem":958,
    "gn:feature_class":"P",
    "gn:feature_code":"PPL",
    "gn:name":"Muddanahalli",
    "gn:population":0,
    "gn:timezone":"Asia/Kolkata",
    "iso:country":"IN",
    "wof:name":"Muddanahalli",
    "wof:placetype":"locality"
},
  "geometry": {"coordinates":[76.0436,13.00882],"type":"Point"}
}