{
  "type": "Feature",
  "properties": {
    "gn:admin1_code":"10",
    "gn:admin2_code":"85.0",
    "gn:asciiname":"Tahna Dipalpur",
    "gn:country_code":"IN",
    "gn:dem":234,
    "gn:feature_class":"P",
    "gn:feature_code":"PPL",
    "gn:name":"Tahna D\u012bp\u0101lpur",
    "gn:population":0,
    "gn:timezone":"Asia/Kolkata",
    "iso:country":"IN",
    "wof:name":"Tahna Dipalpur",
    "wof:placetype":"locality"
},
  "geometry": {"coordinates":[76.61135999999998,28.29597],"type":"Point"}
}