{
  "type": "Feature",
  "properties": {
    "gn:admin1_code":"11",
    "gn:admin2_code":"31.0",
    "gn:asciiname":"Kalianpur",
    "gn:country_code":"IN",
    "gn:dem":369,
    "gn:feature_class":"P",
    "gn:feature_code":"PPL",
    "gn:name":"Kali\u0101npur",
    "gn:population":0,
    "gn:timezone":"Asia/Kolkata",
    "iso:country":"IN",
    "wof:name":"Kalianpur",
    "wof:placetype":"locality"
},
  "geometry": {"coordinates":[76.64828,31.16325],"type":"Point"}
}