{
  "type": "Feature",
  "properties": {
    "gn:admin1_code":"35",
    "gn:admin2_code":"455.0",
    "gn:asciiname":"Baichhapar",
    "gn:country_code":"IN",
    "gn:dem":656,
    "gn:feature_class":"P",
    "gn:feature_code":"PPL",
    "gn:name":"Baichh\u0101par",
    "gn:population":0,
    "gn:timezone":"Asia/Kolkata",
    "iso:country":"IN",
    "ks:ks_alt_nam":"Baichh\u0101par",
    "ks:ks_name":"Baichhapar",
    "ks:ks_pop":402,
    "ks:ks_type":"VILLAGE",
    "name:eng_x_preferred":[
        "Baichhapar"
    ],
    "name:eng_x_variant":[
        "Baichh\u0101par"
    ],
    "wof:name":"Baichhapar",
    "wof:placetype":"locality",
    "wof:population":402
},
  "geometry": {"coordinates":[79.003325,22.54313],"type":"Point"}
}