{
  "type": "Feature",
  "properties": {
    "iso:country":"IN",
    "ks:ks_name":"Kesam",
    "ks:ks_pop":688,
    "ks:ks_type":"VILLAGE",
    "name:eng_x_preferred":[
        "Kesam"
    ],
    "wof:name":"Kesam",
    "wof:placetype":"locality",
    "wof:population":688
},
  "geometry": {"coordinates":[86.216983,22.041696],"type":"Point"}
}