{
  "type": "Feature",
  "properties": {
    "gn:admin1_code":"36.0",
    "gn:admin2_code":"175.0",
    "gn:asciiname":"Amanganj",
    "gn:country_code":"IN",
    "gn:dem":103,
    "gn:feature_class":"P",
    "gn:feature_code":"PPL",
    "gn:name":"Am\u0101nganj",
    "gn:population":0,
    "gn:timezone":"Asia/Kolkata",
    "iso:country":"IN",
    "name:ben_x_preferred":[
        "\u0986\u09ae\u09be\u09a8\u0997\u099e\u09cd\u099c"
    ],
    "name:bpy_x_preferred":[
        "\u0986\u09ae\u09be\u09a8\u0997\u099e\u09cd\u099c"
    ],
    "name:ceb_x_preferred":[
        "Am\u0101nganj"
    ],
    "name:fas_x_preferred":[
        "\u0627\u0645\u0627\u0646\u200c\u06a9\u0646\u062c"
    ],
    "name:ita_x_preferred":[
        "Amanganj"
    ],
    "name:min_x_preferred":[
        "Amanganj"
    ],
    "name:msa_x_preferred":[
        "Amanganj"
    ],
    "name:new_x_preferred":[
        "\u0905\u092e\u0928\u0917\u091e\u094d\u091c"
    ],
    "name:nld_x_preferred":[
        "Amanganj"
    ],
    "name:por_x_preferred":[
        "Amanganj"
    ],
    "name:spa_x_preferred":[
        "Amanganj"
    ],
    "name:swe_x_preferred":[
        "Am\u0101nganj"
    ],
    "name:vie_x_preferred":[
        "Amanganj"
    ],
    "name:zho_x_preferred":[
        "\u963f\u8292\u683c\u963f\u6069\u6770"
    ],
    "wof:name":"Amanganj",
    "wof:placetype":"locality"
},
  "geometry": {"coordinates":[81.89184,25.67328],"type":"Point"}
}