{
  "type": "Feature",
  "properties": {
    "gn:admin1_code":"2.0",
    "gn:admin2_code":"543.0",
    "gn:asciiname":"Sambirguda",
    "gn:country_code":"IN",
    "gn:dem":581,
    "gn:feature_class":"P",
    "gn:feature_code":"PPL",
    "gn:name":"Sambirg\u016bda",
    "gn:population":0,
    "gn:timezone":"Asia/Kolkata",
    "iso:country":"IN",
    "wof:name":"Sambirguda",
    "wof:placetype":"locality"
},
  "geometry": {"coordinates":[83.74949000000002,18.84195],"type":"Point"}
}