{
  "type": "Feature",
  "properties": {
    "gn:admin1_code":"40.0",
    "gn:admin2_code":"540.0",
    "gn:asciiname":"Botalapalli",
    "gn:country_code":"IN",
    "gn:dem":247,
    "gn:feature_class":"P",
    "gn:feature_code":"PPL",
    "gn:name":"Botalapalli",
    "gn:population":0,
    "gn:timezone":"Asia/Kolkata",
    "iso:country":"IN",
    "wof:name":"Botalapalli",
    "wof:placetype":"locality"
},
  "geometry": {"coordinates":[79.69701999999999,18.04379],"type":"Point"}
}