{
  "type": "Feature",
  "properties": {
    "iso:country":"IN",
    "ks:ks_name":"Borriguda",
    "ks:ks_pop":295,
    "ks:ks_type":"VILLAGE",
    "name:eng_x_preferred":[
        "Borriguda"
    ],
    "wof:name":"Borriguda",
    "wof:placetype":"locality",
    "wof:population":295
},
  "geometry": {"coordinates":[82.965232,18.319096],"type":"Point"}
}