{
  "type": "Feature",
  "properties": {
    "iso:country":"IN",
    "ks:ks_name":"Hamti Kapari",
    "ks:ks_pop":316,
    "ks:ks_type":"VILLAGE",
    "name:eng_x_preferred":[
        "Hamti Kapari"
    ],
    "wof:name":"Hamti Kapari",
    "wof:placetype":"locality",
    "wof:population":316
},
  "geometry": {"coordinates":[80.053033,30.025054],"type":"Point"}
}