{
  "type": "Feature",
  "properties": {
    "iso:country":"IN",
    "ks:ks_name":"Pura Dayal",
    "ks:ks_pop":246,
    "ks:ks_type":"HABITATION",
    "name:eng_x_preferred":[
        "Pura Dayal"
    ],
    "wof:name":"Pura Dayal",
    "wof:placetype":"locality",
    "wof:population":246
},
  "geometry": {"coordinates":[83.328205,26.43185],"type":"Point"}
}