{
  "type": "Feature",
  "properties": {
    "gn:admin1_code":"37.0",
    "gn:admin2_code":"409.0",
    "gn:asciiname":"Parsahi",
    "gn:country_code":"IN",
    "gn:dem":312,
    "gn:feature_class":"P",
    "gn:feature_code":"PPL",
    "gn:name":"Pars\u0101hi",
    "gn:population":0,
    "gn:timezone":"Asia/Kolkata",
    "iso:country":"IN",
    "wof:name":"Parsahi",
    "wof:placetype":"locality"
},
  "geometry": {"coordinates":[81.28984,20.80895],"type":"Point"}
}