{
  "type": "Feature",
  "properties": {
    "gn:country":"IN",
    "gn:fcode":"PPL",
    "gn:pop":38435,
    "iso:country":"IN",
    "name:bpy_x_preferred":[
        "\u099a\u09be\u0995\u09cd\u09b2\u09be\u09b8\u09bf"
    ],
    "name:chi_x_preferred":[
        "\u6070\u514b\u62c9\u897f"
    ],
    "name:dut_x_preferred":[
        "Chaklasi"
    ],
    "name:eng_x_preferred":[
        "Chaklasi"
    ],
    "name:fre_x_preferred":[
        "Chaklasi"
    ],
    "name:guj_x_preferred":[
        "\u0a9a\u0a95\u0ab2\u0abe\u0ab8\u0ac0"
    ],
    "name:ita_x_preferred":[
        "Chaklasi"
    ],
    "name:may_x_preferred":[
        "Chaklasi"
    ],
    "name:new_x_preferred":[
        "\u091a\u0915\u0932\u093e\u0938\u0940"
    ],
    "name:por_x_preferred":[
        "Chaklasi"
    ],
    "name:spa_x_preferred":[
        "Chaklasi"
    ],
    "name:swe_x_preferred":[
        "Chakl\u0101si"
    ],
    "name:vie_x_preferred":[
        "Chaklasi"
    ],
    "qs:name":"Chakl\u0101si",
    "qs:photos_9r":0,
    "qs:photos_sr":0,
    "qs:pop_sr":"7",
    "wd:wordcount":139,
    "wof:name":"Chakl\u0101si",
    "wof:placetype":"locality",
    "wof:population":38435
},
  "geometry": {"coordinates":[72.94497,22.6532],"type":"Point"}
}