{
  "type": "Feature",
  "properties": {
    "iso:country":"IN",
    "ks:ks_name":"Kalabari - I",
    "ks:ks_pop":342,
    "ks:ks_type":"HABITATION",
    "name:eng_x_preferred":[
        "Kalabari - I"
    ],
    "wof:name":"Kalabari - I",
    "wof:placetype":"locality",
    "wof:population":342
},
  "geometry": {"coordinates":[91.82055800000001,23.775448],"type":"Point"}
}