{
  "type": "Feature",
  "properties": {
    "gn:admin1_code":"25.0",
    "gn:admin2_code":"606.0",
    "gn:asciiname":"Manjampundi",
    "gn:country_code":"IN",
    "gn:dem":181,
    "gn:feature_class":"P",
    "gn:feature_code":"PPL",
    "gn:name":"Manjamp\u016bndi",
    "gn:population":0,
    "gn:timezone":"Asia/Kolkata",
    "iso:country":"IN",
    "ks:ks_alt_nam":"Manjamp\u016bndi",
    "ks:ks_name":"Manjampundi",
    "ks:ks_type":"VILLAGE",
    "ks:ks_uagg_main":0,
    "name:eng_x_preferred":[
        "Manjampundi"
    ],
    "name:eng_x_variant":[
        "Manjamp\u016bndi"
    ],
    "wof:name":"Manjampundi",
    "wof:placetype":"neighbourhood"
},
  "geometry": {"coordinates":[79.024817,12.18439],"type":"Point"}
}