{
  "type": "Feature",
  "properties": {
    "gn:admin1_code":"37.0",
    "gn:admin2_code":"414",
    "gn:asciiname":"Kodunigud",
    "gn:country_code":"IN",
    "gn:dem":620,
    "gn:feature_class":"P",
    "gn:feature_code":"PPL",
    "gn:name":"Kodunigud",
    "gn:population":0,
    "gn:timezone":"Asia/Kolkata",
    "iso:country":"IN",
    "wof:name":"Kodunigud",
    "wof:placetype":"locality"
},
  "geometry": {"coordinates":[81.44925000000001,19.88473],"type":"Point"}
}