{
  "type": "Feature",
  "properties": {
    "iso:country":"IN",
    "ks:ks_name":"Hiwali",
    "ks:ks_pop":200,
    "ks:ks_type":"HABITATION",
    "name:eng_x_preferred":[
        "Hiwali"
    ],
    "wof:name":"Hiwali",
    "wof:placetype":"locality",
    "wof:population":200
},
  "geometry": {"coordinates":[73.330305,20.106246],"type":"Point"}
}