{
  "type": "Feature",
  "properties": {
    "iso:country":"IN",
    "ks:ks_alt_nam":"shukul purwa",
    "ks:ks_name":"Shukul Purwa",
    "ks:ks_pop":73,
    "ks:ks_type":"HABITATION",
    "ks:ks_uagg_main":0,
    "name:eng_x_preferred":[
        "Shukul Purwa"
    ],
    "wof:name":"Shukul Purwa",
    "wof:placetype":"neighbourhood",
    "wof:population":73
},
  "geometry": {"coordinates":[81.67197,27.420572],"type":"Point"}
}