{
  "type": "Feature",
  "properties": {
    "iso:country":"IN",
    "ks:ks_name":"Thar Bhogiya",
    "ks:ks_pop":450,
    "ks:ks_type":"HABITATION",
    "name:eng_x_preferred":[
        "Thar Bhogiya"
    ],
    "wof:name":"Thar Bhogiya",
    "wof:placetype":"locality",
    "wof:population":450
},
  "geometry": {"coordinates":[78.345394,27.250733],"type":"Point"}
}