{
  "type": "Feature",
  "properties": {
    "iso:country":"IN",
    "ks:ks_name":"Kotul",
    "ks:ks_pop":312,
    "ks:ks_type":"VILLAGE",
    "name:eng_x_preferred":[
        "Kotul"
    ],
    "wof:name":"Kotul",
    "wof:placetype":"locality",
    "wof:population":312
},
  "geometry": {"coordinates":[81.073638,20.007919],"type":"Point"}
}