{
  "type": "Feature",
  "properties": {
    "iso:country":"IN",
    "ks:ks_name":"Kharbona",
    "ks:ks_pop":0,
    "ks:ks_type":"VILLAGE",
    "name:eng_x_preferred":[
        "Kharbona"
    ],
    "wof:name":"Kharbona",
    "wof:placetype":"locality",
    "wof:population":0
},
  "geometry": {"coordinates":[86.86499499999999,23.246802],"type":"Point"}
}