{
  "type": "Feature",
  "properties": {
    "gn:admin1_code":"36",
    "gn:admin2_code":"185.0",
    "gn:asciiname":"Madnapur",
    "gn:country_code":"IN",
    "gn:dem":99,
    "gn:feature_class":"P",
    "gn:feature_code":"PPL",
    "gn:name":"Madn\u0101pur",
    "gn:population":0,
    "gn:timezone":"Asia/Kolkata",
    "iso:country":"IN",
    "name:urd_x_preferred":[
        "\u0645\u062f\u0646\u0627\u067e\u0648\u0631"
    ],
    "wof:name":"Madnapur",
    "wof:placetype":"locality"
},
  "geometry": {"coordinates":[82.25480999999998,26.913],"type":"Point"}
}