{
  "type": "Feature",
  "properties": {
    "iso:country":"IN",
    "ks:ks_name":"Muslim Basti",
    "ks:ks_pop":350,
    "ks:ks_type":"HABITATION",
    "name:eng_x_preferred":[
        "Muslim Basti"
    ],
    "wof:name":"Muslim Basti",
    "wof:placetype":"locality",
    "wof:population":350
},
  "geometry": {"coordinates":[83.317127,24.779019],"type":"Point"}
}