{
  "type": "Feature",
  "properties": {
    "iso:country":"IN",
    "ks:ks_name":"Ghungurpada",
    "ks:ks_pop":111,
    "ks:ks_type":"VILLAGE",
    "name:eng_x_preferred":[
        "Ghungurpada"
    ],
    "wof:name":"Ghungurpada",
    "wof:placetype":"locality",
    "wof:population":111
},
  "geometry": {"coordinates":[84.703777,20.584197],"type":"Point"}
}