{
  "type": "Feature",
  "properties": {
    "gn:admin1_code":"37",
    "gn:admin2_code":"413.0",
    "gn:asciiname":"Dangra",
    "gn:country_code":"IN",
    "gn:dem":360,
    "gn:feature_class":"P",
    "gn:feature_code":"PPL",
    "gn:name":"D\u0101ngra",
    "gn:population":0,
    "gn:timezone":"Asia/Kolkata",
    "iso:country":"IN",
    "ks:ks_alt_nam":"D\u0101ngra",
    "ks:ks_name":"Dangra",
    "ks:ks_pop":460,
    "ks:ks_type":"VILLAGE",
    "name:eng_x_preferred":[
        "Dangra"
    ],
    "name:eng_x_variant":[
        "D\u0101ngra"
    ],
    "wof:name":"Dangra",
    "wof:placetype":"locality",
    "wof:population":460
},
  "geometry": {"coordinates":[80.968986,20.269051],"type":"Point"}
}