{
  "type": "Feature",
  "properties": {
    "iso:country":"IN",
    "ks:ks_name":"Dinupura",
    "ks:ks_pop":0,
    "ks:ks_type":"VILLAGE",
    "name:eng_x_preferred":[
        "Dinupura"
    ],
    "wof:name":"Dinupura",
    "wof:placetype":"locality",
    "wof:population":0
},
  "geometry": {"coordinates":[79.536883,25.923978],"type":"Point"}
}