{
  "type": "Feature",
  "properties": {
    "iso:country":"IN",
    "ks:ks_name":"Pandrapani",
    "ks:ks_pop":149,
    "ks:ks_type":"HABITATION",
    "name:eng_x_preferred":[
        "Pandrapani"
    ],
    "wof:name":"Pandrapani",
    "wof:placetype":"locality",
    "wof:population":149
},
  "geometry": {"coordinates":[84.92028500000001,22.74657],"type":"Point"}
}