{
  "type": "Feature",
  "properties": {
    "gn:admin1_code":"13.0",
    "gn:admin2_code":"591.0",
    "gn:asciiname":"Pannikkottur",
    "gn:country_code":"IN",
    "gn:dem":58,
    "gn:feature_class":"P",
    "gn:feature_code":"PPL",
    "gn:name":"Pannikk\u014dtt\u016br",
    "gn:population":0,
    "gn:timezone":"Asia/Kolkata",
    "iso:country":"IN",
    "ks:ks_name":"Pannikkottur",
    "ks:ks_pop":298,
    "ks:ks_type":"HABITATION",
    "name:eng_x_preferred":[
        "Pannikkottur"
    ],
    "wof:name":"Pannikkottur",
    "wof:placetype":"locality",
    "wof:population":298
},
  "geometry": {"coordinates":[75.87376399999999,11.401944],"type":"Point"}
}