{
  "type": "Feature",
  "properties": {
    "iso:country":"IN",
    "ks:ks_name":"Raibandh",
    "ks:ks_pop":0,
    "ks:ks_type":"VILLAGE",
    "name:eng_x_preferred":[
        "Raibandh"
    ],
    "wof:name":"Raibandh",
    "wof:placetype":"locality",
    "wof:population":0
},
  "geometry": {"coordinates":[86.889672,23.46819],"type":"Point"}
}