{
  "type": "Feature",
  "properties": {
    "iso:country":"IN",
    "ks:ks_name":"Oghani",
    "ks:ks_pop":1349,
    "ks:ks_type":"VILLAGE",
    "name:eng_x_preferred":[
        "Oghani"
    ],
    "wof:name":"Oghani",
    "wof:placetype":"locality",
    "wof:population":1349
},
  "geometry": {"coordinates":[73.921389,21.685817],"type":"Point"}
}