{
  "type": "Feature",
  "properties": {
    "iso:country":"IN",
    "ks:ks_alt_nam":"pindra",
    "ks:ks_name":"Pindra",
    "ks:ks_pop":641,
    "ks:ks_type":"HABITATION",
    "name:eng_x_preferred":[
        "Pindra"
    ],
    "wof:name":"Pindra",
    "wof:placetype":"locality",
    "wof:population":641
},
  "geometry": {"coordinates":[86.49154,24.305241],"type":"Point"}
}