{
  "type": "Feature",
  "properties": {
    "iso:country":"IN",
    "ks:ks_name":"Ippalaguda",
    "ks:ks_pop":94,
    "ks:ks_type":"HABITATION",
    "name:eng_x_preferred":[
        "Ippalaguda"
    ],
    "wof:name":"Ippalaguda",
    "wof:placetype":"locality",
    "wof:population":94
},
  "geometry": {"coordinates":[83.644327,18.900454],"type":"Point"}
}