{
  "type": "Feature",
  "properties": {
    "gn:admin1_code":"11",
    "gn:admin2_code":"23.0",
    "gn:asciiname":"Dhar Mandian",
    "gn:country_code":"IN",
    "gn:dem":1208,
    "gn:feature_class":"P",
    "gn:feature_code":"PPL",
    "gn:name":"Dh\u0101r Mandi\u0101n",
    "gn:population":0,
    "gn:timezone":"Asia/Kolkata",
    "iso:country":"IN",
    "wof:name":"Dhar Mandian",
    "wof:placetype":"locality"
},
  "geometry": {"coordinates":[76.00794,32.36808],"type":"Point"}
}