{
  "type": "Feature",
  "properties": {
    "iso:country":"IN",
    "ks:ks_name":"Sadakput",
    "ks:ks_pop":35,
    "ks:ks_type":"HABITATION",
    "name:eng_x_preferred":[
        "Sadakput"
    ],
    "wof:name":"Sadakput",
    "wof:placetype":"locality",
    "wof:population":35
},
  "geometry": {"coordinates":[82.189898,18.728861],"type":"Point"}
}