{
  "type": "Feature",
  "properties": {
    "iso:country":"IN",
    "ks:ks_alt_nam":"Lis\u0101ri",
    "ks:ks_name":"Lisari",
    "ks:ks_type":"VILLAGE",
    "ks:ks_uagg_main":0,
    "name:eng_x_preferred":[
        "Lisari"
    ],
    "name:eng_x_variant":[
        "Lis\u0101ri"
    ],
    "wof:name":"Lisari",
    "wof:placetype":"neighbourhood"
},
  "geometry": {"coordinates":[77.700411,28.9385],"type":"Point"}
}