{
  "type": "Feature",
  "properties": {
    "iso:country":"IN",
    "ks:ks_name":"Ranganimote",
    "ks:ks_pop":339,
    "ks:ks_type":"HABITATION",
    "name:eng_x_preferred":[
        "Ranganimote"
    ],
    "wof:name":"Ranganimote",
    "wof:placetype":"locality",
    "wof:population":339
},
  "geometry": {"coordinates":[74.486155,14.267522],"type":"Point"}
}