{
  "type": "Feature",
  "properties": {
    "iso:country":"IN",
    "ks:ks_name":"Chipanpalli",
    "ks:ks_pop":35,
    "ks:ks_type":"HABITATION",
    "name:eng_x_preferred":[
        "Chipanpalli"
    ],
    "wof:name":"Chipanpalli",
    "wof:placetype":"locality",
    "wof:population":35
},
  "geometry": {"coordinates":[80.415916,18.833233],"type":"Point"}
}