{
  "type": "Feature",
  "properties": {
    "iso:country":"IN",
    "ks:ks_name":"Kunjanpadi",
    "ks:ks_pop":1417,
    "ks:ks_type":"HABITATION",
    "name:eng_x_preferred":[
        "Kunjanpadi"
    ],
    "wof:name":"Kunjanpadi",
    "wof:placetype":"locality",
    "wof:population":1417
},
  "geometry": {"coordinates":[76.093766,10.871635],"type":"Point"}
}