{
  "type": "Feature",
  "properties": {
    "gn:admin1_code":"39.0",
    "gn:admin2_code":"64.0",
    "gn:asciiname":"Gahna Hit",
    "gn:country_code":"IN",
    "gn:dem":937,
    "gn:feature_class":"P",
    "gn:feature_code":"PPL",
    "gn:name":"Gahna Hit",
    "gn:population":0,
    "gn:timezone":"Asia/Kolkata",
    "iso:country":"IN",
    "wof:name":"Gahna Hit",
    "wof:placetype":"locality"
},
  "geometry": {"coordinates":[79.25700999999999,29.71639],"type":"Point"}
}