{
  "type": "Feature",
  "properties": {
    "iso:country":"IN",
    "ks:ks_name":"Adibasi Para",
    "ks:ks_pop":1035,
    "ks:ks_type":"HABITATION",
    "name:eng_x_preferred":[
        "Adibasi Para"
    ],
    "wof:name":"Adibasi Para",
    "wof:placetype":"locality",
    "wof:population":1035
},
  "geometry": {"coordinates":[88.900238,22.209769],"type":"Point"}
}