{
  "type": "Feature",
  "properties": {
    "iso:country":"IN",
    "ks:ks_name":"Bagerwa",
    "ks:ks_pop":135,
    "ks:ks_type":"HABITATION",
    "name:eng_x_preferred":[
        "Bagerwa"
    ],
    "wof:name":"Bagerwa",
    "wof:placetype":"locality",
    "wof:population":135
},
  "geometry": {"coordinates":[82.908006,25.605084],"type":"Point"}
}