{
  "type": "Feature",
  "properties": {
    "gn:admin1_code":"11.0",
    "gn:admin2_code":"26.0",
    "gn:asciiname":"Thog",
    "gn:country_code":"IN",
    "gn:dem":1589,
    "gn:feature_class":"P",
    "gn:feature_code":"PPL",
    "gn:name":"Thog",
    "gn:population":0,
    "gn:timezone":"Asia/Kolkata",
    "iso:country":"IN",
    "wof:name":"Thog",
    "wof:placetype":"locality"
},
  "geometry": {"coordinates":[77.42814,31.4339],"type":"Point"}
}