{
  "type": "Feature",
  "properties": {
    "iso:country":"IN",
    "ks:ks_name":"Rampur T Reotipur",
    "ks:ks_pop":0,
    "ks:ks_type":"VILLAGE",
    "name:eng_x_preferred":[
        "Rampur T Reotipur"
    ],
    "wof:name":"Rampur T Reotipur",
    "wof:placetype":"locality",
    "wof:population":0
},
  "geometry": {"coordinates":[83.753484,25.547781],"type":"Point"}
}