{
  "type": "Feature",
  "properties": {
    "iso:country":"IN",
    "ks:ks_name":"Panikapara",
    "ks:ks_pop":991,
    "ks:ks_type":"HABITATION",
    "name:eng_x_preferred":[
        "Panikapara"
    ],
    "wof:name":"Panikapara",
    "wof:placetype":"locality",
    "wof:population":991
},
  "geometry": {"coordinates":[83.592725,22.385408],"type":"Point"}
}