{
  "type": "Feature",
  "properties": {
    "gn:admin1_code":"36.0",
    "gn:admin2_code":"132",
    "gn:asciiname":"Badshahipur",
    "gn:country_code":"IN",
    "gn:dem":328,
    "gn:feature_class":"P",
    "gn:feature_code":"PPL",
    "gn:name":"B\u0101dsh\u0101h\u012bpur",
    "gn:population":0,
    "gn:timezone":"Asia/Kolkata",
    "iso:country":"IN",
    "name:und_x_variant":[
        "B\u0101dsh\u0101h\u012bpur",
        "B\u0101dsh\u014dh\u012bpur"
    ],
    "wof:name":"Badshahipur",
    "wof:placetype":"locality"
},
  "geometry": {"coordinates":[77.81783,30.12559000000001],"type":"Point"}
}