{
  "type": "Feature",
  "properties": {
    "gn:admin1_code":"36.0",
    "gn:admin2_code":"132",
    "gn:asciiname":"Bastam",
    "gn:country_code":"IN",
    "gn:dem":262,
    "gn:feature_class":"P",
    "gn:feature_code":"PPL",
    "gn:name":"B\u0101stam",
    "gn:population":0,
    "gn:timezone":"Asia/Kolkata",
    "iso:country":"IN",
    "ks:ks_name":"Bastam",
    "ks:ks_pop":1596,
    "ks:ks_type":"VILLAGE",
    "ks:ks_uagg_main":0,
    "name:ara_x_preferred":[
        "\u0628\u0633\u0637\u0627\u0645"
    ],
    "name:aze_x_preferred":[
        "B\u0259stam"
    ],
    "name:cat_x_preferred":[
        "Bastam"
    ],
    "name:eng_x_preferred":[
        "Bastam"
    ],
    "name:fas_x_preferred":[
        "\u0628\u0633\u0637\u0627\u0645"
    ],
    "name:fra_x_preferred":[
        "Bastam"
    ],
    "name:ita_x_preferred":[
        "Bastam"
    ],
    "name:mlg_x_preferred":[
        "Bastam"
    ],
    "name:tgk_x_preferred":[
        "\u0411\u0430\u0441\u0442\u043e\u043c"
    ],
    "name:urd_x_preferred":[
        "\u0628\u0633\u0637\u0627\u0645"
    ],
    "name:zho_x_preferred":[
        "\u5df4\u65af\u5854\u59c6"
    ],
    "wof:name":"Bastam",
    "wof:placetype":"neighbourhood",
    "wof:population":1596
},
  "geometry": {"coordinates":[77.689087,29.741163],"type":"Point"}
}