{
  "type": "Feature",
  "properties": {
    "iso:country":"IN",
    "ks:ks_name":"Margiya Mahura",
    "ks:ks_pop":406,
    "ks:ks_type":"VILLAGE",
    "name:eng_x_preferred":[
        "Margiya Mahura"
    ],
    "wof:name":"Margiya Mahura",
    "wof:placetype":"locality",
    "wof:population":406
},
  "geometry": {"coordinates":[73.819974,23.747456],"type":"Point"}
}