{
  "type": "Feature",
  "properties": {
    "iso:country":"IN",
    "ks:ks_name":"Pattanr",
    "ks:ks_pop":612,
    "ks:ks_type":"VILLAGE",
    "name:eng_x_preferred":[
        "Pattanr"
    ],
    "wof:name":"Pattanr",
    "wof:placetype":"locality",
    "wof:population":612
},
  "geometry": {"coordinates":[86.166684,23.257046],"type":"Point"}
}