{
  "type": "Feature",
  "properties": {
    "iso:country":"IN",
    "ks:ks_name":"Sakhaupur",
    "ks:ks_pop":435,
    "ks:ks_type":"HABITATION",
    "ks:ks_uagg_main":0,
    "name:eng_x_preferred":[
        "Sakhaupur"
    ],
    "wof:name":"Sakhaupur",
    "wof:placetype":"neighbourhood",
    "wof:population":435
},
  "geometry": {"coordinates":[83.79646,25.891151],"type":"Point"}
}