{
  "type": "Feature",
  "properties": {
    "iso:country":"IN",
    "ks:ks_name":"Jagannathpur",
    "ks:ks_pop":551,
    "ks:ks_type":"VILLAGE",
    "name:eng_x_preferred":[
        "Jagannathpur"
    ],
    "wof:name":"Jagannathpur",
    "wof:placetype":"locality",
    "wof:population":551
},
  "geometry": {"coordinates":[92.031543,24.218954],"type":"Point"}
}