{
  "type": "Feature",
  "properties": {
    "gn:admin1_code":"19.0",
    "gn:admin2_code":"575.0",
    "gn:asciiname":"Halemajalu",
    "gn:country_code":"IN",
    "gn:dem":188,
    "gn:feature_class":"P",
    "gn:feature_code":"PPL",
    "gn:name":"Halemajalu",
    "gn:population":0,
    "gn:timezone":"Asia/Kolkata",
    "iso:country":"IN",
    "ks:ks_name":"Halamajalu",
    "ks:ks_pop":609,
    "ks:ks_type":"HABITATION",
    "name:eng_x_preferred":[
        "Halamajalu"
    ],
    "name:eng_x_variant":[
        "Halemajalu"
    ],
    "wof:name":"Halamajalu",
    "wof:placetype":"locality",
    "wof:population":609
},
  "geometry": {"coordinates":[75.55275399999999,12.627935],"type":"Point"}
}