{
  "type": "Feature",
  "properties": {
    "gn:admin1_code":"36",
    "gn:admin2_code":"180.0",
    "gn:asciiname":"Siripalpur",
    "gn:country_code":"IN",
    "gn:dem":113,
    "gn:feature_class":"P",
    "gn:feature_code":"PPL",
    "gn:name":"Sirip\u0101lpur",
    "gn:population":0,
    "gn:timezone":"Asia/Kolkata",
    "iso:country":"IN",
    "wof:name":"Siripalpur",
    "wof:placetype":"locality"
},
  "geometry": {"coordinates":[81.66093000000002,27.39364],"type":"Point"}
}