{
  "type": "Feature",
  "properties": {
    "iso:country":"IN",
    "ks:ks_alt_nam":"B\u0101npur",
    "ks:ks_name":"Banpur",
    "ks:ks_pop":309,
    "ks:ks_type":"VILLAGE",
    "name:eng_x_preferred":[
        "Banpur"
    ],
    "name:eng_x_variant":[
        "B\u0101npur"
    ],
    "wof:name":"Banpur",
    "wof:placetype":"locality",
    "wof:population":309
},
  "geometry": {"coordinates":[84.879403,22.976823],"type":"Point"}
}