{
  "type": "Feature",
  "properties": {
    "iso:country":"IN",
    "ks:ks_alt_nam":"BETHUBARI Pt I",
    "ks:ks_name":"Bethubari Pt I",
    "ks:ks_pop":1012,
    "ks:ks_type":"HABITATION",
    "name:eng_x_preferred":[
        "Bethubari Pt I"
    ],
    "wof:name":"Bethubari Pt I",
    "wof:placetype":"locality",
    "wof:population":1012
},
  "geometry": {"coordinates":[92.381525,24.551185],"type":"Point"}
}