{
  "type": "Feature",
  "properties": {
    "gn:admin1_code":"35",
    "gn:admin2_code":"439.0",
    "gn:asciiname":"Karodiya",
    "gn:country_code":"IN",
    "gn:dem":597,
    "gn:feature_class":"P",
    "gn:feature_code":"PPL",
    "gn:name":"Karodiya",
    "gn:population":0,
    "gn:timezone":"Asia/Kolkata",
    "iso:country":"IN",
    "wof:name":"Karodiya",
    "wof:placetype":"locality"
},
  "geometry": {"coordinates":[75.70265999999999,22.60222000000001],"type":"Point"}
}