{
  "type": "Feature",
  "properties": {
    "gn:admin1_code":"2",
    "gn:admin2_code":"545.0",
    "gn:asciiname":"Kottada",
    "gn:country_code":"IN",
    "gn:dem":123,
    "gn:feature_class":"P",
    "gn:feature_code":"PPL",
    "gn:name":"Kott\u0101da",
    "gn:population":0,
    "gn:timezone":"Asia/Kolkata",
    "iso:country":"IN",
    "ks:ks_name":"Kothada",
    "ks:ks_pop":883,
    "ks:ks_type":"VILLAGE",
    "name:eng_x_preferred":[
        "Kothada"
    ],
    "name:eng_x_variant":[
        "Kottada"
    ],
    "wof:name":"Kothada",
    "wof:placetype":"locality",
    "wof:population":883
},
  "geometry": {"coordinates":[81.890771,17.36029],"type":"Point"}
}