{
  "type": "Feature",
  "properties": {
    "gn:admin1_code":"36.0",
    "gn:admin2_code":"185.0",
    "gn:asciiname":"Lohrauli Khurd",
    "gn:country_code":"IN",
    "gn:dem":88,
    "gn:feature_class":"P",
    "gn:feature_code":"PPL",
    "gn:name":"Lohrauli Khurd",
    "gn:population":0,
    "gn:timezone":"Asia/Kolkata",
    "iso:country":"IN",
    "ks:ks_name":"Lohrauli Khurd",
    "ks:ks_pop":324,
    "ks:ks_type":"VILLAGE",
    "name:eng_x_preferred":[
        "Lohrauli Khurd"
    ],
    "wof:name":"Lohrauli Khurd",
    "wof:placetype":"locality",
    "wof:population":324
},
  "geometry": {"coordinates":[82.81227,27.048209],"type":"Point"}
}