{
  "type": "Feature",
  "properties": {
    "iso:country":"IN",
    "ks:ks_name":"Dadilai",
    "ks:ks_pop":48,
    "ks:ks_type":"VILLAGE",
    "name:eng_x_preferred":[
        "Dadilai"
    ],
    "wof:name":"Dadilai",
    "wof:placetype":"locality",
    "wof:population":48
},
  "geometry": {"coordinates":[84.071105,20.269733],"type":"Point"}
}