{
  "type": "Feature",
  "properties": {
    "gn:admin1_code":"2",
    "gn:admin2_code":"548.0",
    "gn:asciiname":"Ellamanda",
    "gn:country_code":"IN",
    "gn:dem":61,
    "gn:feature_class":"P",
    "gn:feature_code":"PPL",
    "gn:name":"Ellamanda",
    "gn:population":0,
    "gn:timezone":"Asia/Kolkata",
    "iso:country":"IN",
    "name:tel_x_preferred":[
        "\u0c2f\u0c32\u0c4d\u0c32\u0c2e\u0c02\u0c26"
    ],
    "wof:name":"Ellamanda",
    "wof:placetype":"locality"
},
  "geometry": {"coordinates":[80.05458,16.1847],"type":"Point"}
}