{
  "type": "Feature",
  "properties": {
    "iso:country":"IN",
    "ks:ks_name":"Melkuppam",
    "ks:ks_pop":160,
    "ks:ks_type":"HABITATION",
    "name:eng_x_preferred":[
        "Melkuppam"
    ],
    "wof:name":"Melkuppam",
    "wof:placetype":"locality",
    "wof:population":160
},
  "geometry": {"coordinates":[78.882518,12.394042],"type":"Point"}
}