{
  "type": "Feature",
  "properties": {
    "iso:country":"IN",
    "ks:ks_name":"Godhia",
    "ks:ks_pop":227,
    "ks:ks_type":"HABITATION",
    "name:eng_x_preferred":[
        "Godhia"
    ],
    "wof:name":"Godhia",
    "wof:placetype":"locality",
    "wof:population":227
},
  "geometry": {"coordinates":[81.306433,27.795728],"type":"Point"}
}