{
  "type": "Feature",
  "properties": {
    "iso:country":"IN",
    "ks:ks_name":"Dhola",
    "ks:ks_pop":805,
    "ks:ks_type":"VILLAGE",
    "name:eng_x_preferred":[
        "Dhola"
    ],
    "wof:name":"Dhola",
    "wof:placetype":"locality",
    "wof:population":805
},
  "geometry": {"coordinates":[85.877894,19.935218],"type":"Point"}
}