{
  "type": "Feature",
  "properties": {
    "iso:country":"IN",
    "ks:ks_name":"Machhpukur",
    "ks:ks_pop":4009,
    "ks:ks_type":"HABITATION",
    "name:eng_x_preferred":[
        "Machhpukur"
    ],
    "wof:name":"Machhpukur",
    "wof:placetype":"locality",
    "wof:population":4009
},
  "geometry": {"coordinates":[88.54487,22.326488],"type":"Point"}
}