{
  "type": "Feature",
  "properties": {
    "gn:admin1_code":"35.0",
    "gn:admin2_code":"463.0",
    "gn:asciiname":"Surguri",
    "gn:country_code":"IN",
    "gn:dem":318,
    "gn:feature_class":"P",
    "gn:feature_code":"PPL",
    "gn:name":"Surguri",
    "gn:population":0,
    "gn:timezone":"Asia/Kolkata",
    "iso:country":"IN",
    "wof:name":"Surguri",
    "wof:placetype":"locality"
},
  "geometry": {"coordinates":[82.70175,24.324],"type":"Point"}
}