{
  "type": "Feature",
  "properties": {
    "iso:country":"IN",
    "ks:ks_name":"Lunigan",
    "ks:ks_pop":1085,
    "ks:ks_type":"VILLAGE",
    "ks:ks_uagg_main":0,
    "name:eng_x_preferred":[
        "Lunigan"
    ],
    "wof:name":"Lunigan",
    "wof:placetype":"neighbourhood",
    "wof:population":1085
},
  "geometry": {"coordinates":[86.10591700000001,20.123526],"type":"Point"}
}