{
  "type": "Feature",
  "properties": {
    "iso:country":"IN",
    "ks:ks_name":"Harizon Basti",
    "ks:ks_pop":250,
    "ks:ks_type":"HABITATION",
    "ks:ks_uagg_main":0,
    "name:eng_x_preferred":[
        "Harizon Basti"
    ],
    "wof:name":"Harizon Basti",
    "wof:placetype":"neighbourhood",
    "wof:population":250
},
  "geometry": {"coordinates":[83.94968799999999,27.040069],"type":"Point"}
}