{
  "type": "Feature",
  "properties": {
    "iso:country":"IN",
    "name:ara_x_preferred":[
        "\u0627\u0644\u0642\u0637\u0627\u0639 15-2"
    ],
    "name:ben_bn_x_preferred":[
        "\u09b8\u09c7\u0995\u09cd\u099f\u09b0 15-2"
    ],
    "name:ben_in_x_preferred":[
        "\u09b8\u09c7\u0995\u09cd\u099f\u09b0 15-2"
    ],
    "name:eng_x_preferred":[
        "Sector 15 Part 2"
    ],
    "name:eng_x_variant":[
        "Sector 15 II"
    ],
    "name:guj_x_preferred":[
        "\u0ab8\u0ac7\u0a95\u0acd\u0a9f\u0ab0 15-2"
    ],
    "name:hin_x_preferred":[
        "\u0938\u0947\u0915\u094d\u091f\u0930 15-2"
    ],
    "name:kan_x_preferred":[
        "\u0cb8\u0cc6\u0c95\u0ccd\u0c9f\u0cb0\u0ccd 15-2"
    ],
    "name:mal_x_preferred":[
        "\u0d38\u0d46\u0d15\u0d4d\u0d1f\u0d30\u0d4d"
    ],
    "name:mar_x_preferred":[
        "\u0938\u0947\u0915\u094d\u091f\u0930 15-2"
    ],
    "name:pan_x_preferred":[
        "\u0a38\u0a48\u0a15\u0a1f\u0a30 15-2"
    ],
    "name:tam_x_preferred":[
        "\u0baa\u0bbf\u0bb0\u0bbf\u0bb5\u0bc1 15-2"
    ],
    "name:tel_x_preferred":[
        "\u0c38\u0c46\u0c15\u0c4d\u0c1f\u0c30\u0c4d"
    ],
    "name:urd_x_preferred":[
        "\u0633\u06cc\u06a9\u0679\u0631 15-2"
    ],
    "qs:gn_adm0_cc":"IN",
    "qs:gn_local":1270642,
    "qs:gn_nam_loc":"Gurgaon, Gurgaon, Haryana, IN",
    "qs:gn_namadm1":"10",
    "qs:local_max":764,
    "qs:local_sum":4037,
    "qs:localhoods":24,
    "qs:name":"Sector 15 Part 2",
    "qs:name_adm0":"India",
    "qs:name_adm1":"Haryana",
    "qs:name_adm2":"Gurgaon",
    "qs:name_local":"Gurgaon",
    "qs:photo_max":101,
    "qs:photo_sum":270,
    "qs:placetype":"Suburb",
    "qs:quad_count":13,
    "qs:woe_adm0":23424848,
    "qs:woe_adm1":2345744,
    "qs:woe_adm2":12586441,
    "qs:woe_lau":0,
    "qs:woe_local":2295020,
    "qs:woe_ver":"7.10.0",
    "wof:lang":[
        "eng"
    ],
    "wof:name":"Sector 15-2",
    "wof:placetype":"neighbourhood"
},
  "geometry": {"coordinates":[77.04535,28.461784],"type":"Point"}
}