{
  "type": "Feature",
  "properties": {
    "iso:country":"IN",
    "ks:ks_name":"Turungagarh",
    "ks:ks_pop":469,
    "ks:ks_type":"VILLAGE",
    "name:eng_x_preferred":[
        "Turungagarh"
    ],
    "wof:name":"Turungagarh",
    "wof:placetype":"locality",
    "wof:population":469
},
  "geometry": {"coordinates":[83.916776,22.178695],"type":"Point"}
}