{
  "type": "Feature",
  "properties": {
    "iso:country":"IN",
    "ks:ks_name":"Manoharanagara",
    "ks:ks_pop":203,
    "ks:ks_type":"HABITATION",
    "ks:ks_uagg_main":0,
    "name:eng_x_preferred":[
        "Manoharanagara"
    ],
    "wof:name":"Manoharanagara",
    "wof:placetype":"neighbourhood",
    "wof:population":203
},
  "geometry": {"coordinates":[74.86660000000001,13.187615],"type":"Point"}
}