{
  "type": "Feature",
  "properties": {
    "gn:admin1_code":"35.0",
    "gn:admin2_code":"457.0",
    "gn:asciiname":"Sirka",
    "gn:country_code":"IN",
    "gn:dem":454,
    "gn:feature_class":"P",
    "gn:feature_code":"PPL",
    "gn:name":"Sirka",
    "gn:population":0,
    "gn:timezone":"Asia/Kolkata",
    "iso:country":"IN",
    "ks:ks_name":"Sirka",
    "ks:ks_pop":68,
    "ks:ks_type":"HABITATION",
    "name:ceb_x_preferred":[
        "Sirka"
    ],
    "name:ces_x_preferred":[
        "Sirka"
    ],
    "name:deu_x_preferred":[
        "Sirka"
    ],
    "name:eng_x_preferred":[
        "Sirka"
    ],
    "name:fra_x_preferred":[
        "Sirka"
    ],
    "wof:name":"Sirka",
    "wof:placetype":"locality",
    "wof:population":68
},
  "geometry": {"coordinates":[80.494227,21.625298],"type":"Point"}
}