{
  "type": "Feature",
  "properties": {
    "gn:admin1_code":"19.0",
    "gn:admin2_code":"574.0",
    "gn:asciiname":"Mattigalale",
    "gn:country_code":"IN",
    "gn:dem":1014,
    "gn:feature_class":"P",
    "gn:feature_code":"PPL",
    "gn:name":"Mattigalale",
    "gn:population":0,
    "gn:timezone":"Asia/Kolkata",
    "iso:country":"IN",
    "ks:ks_name":"Mathigalale",
    "ks:ks_pop":99,
    "ks:ks_type":"VILLAGE",
    "name:eng_x_preferred":[
        "Mathigalale"
    ],
    "name:eng_x_variant":[
        "Mattigalale"
    ],
    "wof:name":"Mathigalale",
    "wof:placetype":"locality",
    "wof:population":99
},
  "geometry": {"coordinates":[75.833872,13.019232],"type":"Point"}
}