{
  "type": "Feature",
  "properties": {
    "iso:country":"IN",
    "ks:ks_name":"Mahudipada",
    "ks:ks_pop":317,
    "ks:ks_type":"HABITATION",
    "name:eng_x_preferred":[
        "Mahudipada"
    ],
    "wof:name":"Mahudipada",
    "wof:placetype":"locality",
    "wof:population":317
},
  "geometry": {"coordinates":[74.855724,23.375963],"type":"Point"}
}