{
  "type": "Feature",
  "properties": {
    "iso:country":"IN",
    "ks:ks_name":"Dhulekundu",
    "ks:ks_pop":1309,
    "ks:ks_type":"HABITATION",
    "name:eng_x_preferred":[
        "Dhulekundu"
    ],
    "wof:name":"Dhulekundu",
    "wof:placetype":"locality",
    "wof:population":1309
},
  "geometry": {"coordinates":[87.76354600000001,22.724244],"type":"Point"}
}