{
  "type": "Feature",
  "properties": {
    "iso:country":"IN",
    "ks:ks_name":"Kadirepalli",
    "ks:ks_pop":302,
    "ks:ks_type":"HABITATION",
    "name:eng_x_preferred":[
        "Kadirepalli"
    ],
    "wof:name":"Kadirepalli",
    "wof:placetype":"locality",
    "wof:population":302
},
  "geometry": {"coordinates":[78.512867,14.428269],"type":"Point"}
}