{
  "type": "Feature",
  "properties": {
    "iso:country":"IN",
    "ks:ks_name":"Thenkarai",
    "ks:ks_pop":11597,
    "ks:ks_type":"VILLAGE",
    "ks:ks_uagg_main":0,
    "name:eng_x_preferred":[
        "Thenkarai"
    ],
    "wof:name":"Thenkarai",
    "wof:placetype":"locality",
    "wof:population":11597
},
  "geometry": {"coordinates":[77.548717,10.11606],"type":"Point"}
}