{
  "type": "Feature",
  "properties": {
    "gn:admin1_code":"2.0",
    "gn:asciiname":"Sadarlahalli",
    "gn:country_code":"IN",
    "gn:dem":683,
    "gn:feature_class":"P",
    "gn:feature_code":"PPL",
    "gn:name":"S\u0101darlahalli",
    "gn:population":0,
    "gn:timezone":"Asia/Kolkata",
    "iso:country":"IN",
    "wof:name":"Sadarlahalli",
    "wof:placetype":"locality"
},
  "geometry": {"coordinates":[77.61635,13.74037],"type":"Point"}
}