{
  "type": "Feature",
  "properties": {
    "iso:country":"IN",
    "ks:ks_name":"Nadody Hebri",
    "ks:ks_pop":62,
    "ks:ks_type":"HABITATION",
    "name:eng_x_preferred":[
        "Nadody Hebri"
    ],
    "wof:name":"Nadody Hebri",
    "wof:placetype":"locality",
    "wof:population":62
},
  "geometry": {"coordinates":[74.976849,13.439063],"type":"Point"}
}