{
  "type": "Feature",
  "properties": {
    "iso:country":"IN",
    "ks:ks_name":"Dhasai Ryt",
    "ks:ks_pop":0,
    "ks:ks_type":"VILLAGE",
    "name:eng_x_preferred":[
        "Dhasai Ryt"
    ],
    "wof:name":"Dhasai Ryt",
    "wof:placetype":"locality",
    "wof:population":0
},
  "geometry": {"coordinates":[77.948589,22.325628],"type":"Point"}
}