{
  "type": "Feature",
  "properties": {
    "gn:admin1_code":"19.0",
    "gn:admin2_code":"574.0",
    "gn:asciiname":"Kanoguppe",
    "gn:country_code":"IN",
    "gn:dem":1013,
    "gn:feature_class":"P",
    "gn:feature_code":"PPL",
    "gn:name":"Kanoguppe",
    "gn:population":0,
    "gn:timezone":"Asia/Kolkata",
    "iso:country":"IN",
    "wof:name":"Kanoguppe",
    "wof:placetype":"locality"
},
  "geometry": {"coordinates":[75.80712,13.08319],"type":"Point"}
}