{
  "type": "Feature",
  "properties": {
    "gn:admin1_code":"19.0",
    "gn:admin2_code":"574.0",
    "gn:asciiname":"Kanoguppe",
    "gn:country_code":"IN",
    "gn:dem":1013,
    "gn:feature_class":"P",
    "gn:feature_code":"PPL",
    "gn:name":"Kanoguppe",
    "gn:population":0,
    "gn:timezone":"Asia/Kolkata",
    "iso:country":"IN",
    "ks:ks_name":"Kanaguppe",
    "ks:ks_pop":451,
    "ks:ks_type":"VILLAGE",
    "name:eng_x_preferred":[
        "Kanaguppe"
    ],
    "name:eng_x_variant":[
        "Kanoguppe"
    ],
    "wof:name":"Kanaguppe",
    "wof:placetype":"locality",
    "wof:population":451
},
  "geometry": {"coordinates":[75.80875399999999,13.084096],"type":"Point"}
}