{
  "type": "Feature",
  "properties": {
    "gn:admin1_code":"36",
    "gn:admin2_code":"175.0",
    "gn:asciiname":"Sewai",
    "gn:country_code":"IN",
    "gn:dem":116,
    "gn:feature_class":"P",
    "gn:feature_code":"PPL",
    "gn:name":"Sewai",
    "gn:population":0,
    "gn:timezone":"Asia/Kolkata",
    "iso:country":"IN",
    "name:bih_x_preferred":[
        "\u0938\u0947\u0935\u093e\u0908"
    ],
    "name:bpy_x_preferred":[
        "\u09b8\u09c7\u09f1\u09be\u0987"
    ],
    "name:ind_x_preferred":[
        "Sewai"
    ],
    "name:ita_x_preferred":[
        "Sewai"
    ],
    "name:msa_x_preferred":[
        "Sewai"
    ],
    "name:nld_x_preferred":[
        "Sewai"
    ],
    "name:por_x_preferred":[
        "Sewai"
    ],
    "name:vie_x_preferred":[
        "Sewai"
    ],
    "name:zho_x_preferred":[
        "\u585e\u74e6\u4f0a"
    ],
    "wof:name":"Sewai",
    "wof:placetype":"locality"
},
  "geometry": {"coordinates":[81.97506,24.94915],"type":"Point"}
}