{
  "type": "Feature",
  "properties": {
    "gn:admin1_code":"11.0",
    "gn:admin2_code":"27.0",
    "gn:asciiname":"Ude Nal",
    "gn:country_code":"IN",
    "gn:dem":1750,
    "gn:feature_class":"P",
    "gn:feature_code":"PPL",
    "gn:name":"Ude N\u0101l",
    "gn:population":0,
    "gn:timezone":"Asia/Kolkata",
    "iso:country":"IN",
    "wof:name":"Ude Nal",
    "wof:placetype":"locality"
},
  "geometry": {"coordinates":[77.14403,31.2895],"type":"Point"}
}