{
  "type": "Feature",
  "properties": {
    "iso:country":"IN",
    "ks:ks_alt_nam":"Kh\u0101pri",
    "ks:ks_name":"Khapri",
    "ks:ks_type":"VILLAGE",
    "name:eng_x_preferred":[
        "Khapri"
    ],
    "name:eng_x_variant":[
        "Kh\u0101pri"
    ],
    "wof:name":"Khapri",
    "wof:placetype":"neighbourhood"
},
  "geometry": {"coordinates":[79.043819,21.053048],"type":"Point"}
}