{
  "type": "Feature",
  "properties": {
    "iso:country":"IN",
    "ks:ks_name":"Kundi",
    "ks:ks_pop":598,
    "ks:ks_type":"VILLAGE",
    "name:eng_x_preferred":[
        "Kundi"
    ],
    "wof:name":"Kundi",
    "wof:placetype":"locality",
    "wof:population":598
},
  "geometry": {"coordinates":[84.955516,23.853187],"type":"Point"}
}