{
  "type": "Feature",
  "properties": {
    "iso:country":"IN",
    "ks:ks_name":"Nagjhori",
    "ks:ks_pop":219,
    "ks:ks_type":"VILLAGE",
    "name:eng_x_preferred":[
        "Nagjhori"
    ],
    "wof:name":"Nagjhori",
    "wof:placetype":"locality",
    "wof:population":219
},
  "geometry": {"coordinates":[83.596675,20.117406],"type":"Point"}
}