{
  "type": "Feature",
  "properties": {
    "iso:country":"IN",
    "ks:ks_name":"Simtoli",
    "ks:ks_pop":144,
    "ks:ks_type":"VILLAGE",
    "name:eng_x_preferred":[
        "Simtoli"
    ],
    "wof:name":"Simtoli",
    "wof:placetype":"locality",
    "wof:population":144
},
  "geometry": {"coordinates":[79.265407,30.165957],"type":"Point"}
}