{
  "type": "Feature",
  "properties": {
    "gn:admin1_code":"13.0",
    "gn:admin2_code":"601.0",
    "gn:asciiname":"Puthenthope",
    "gn:country_code":"IN",
    "gn:dem":11,
    "gn:feature_class":"P",
    "gn:feature_code":"PPL",
    "gn:name":"Puthenthope",
    "gn:population":0,
    "gn:timezone":"Asia/Kolkata",
    "iso:country":"IN",
    "wof:name":"Puthenthope",
    "wof:placetype":"locality"
},
  "geometry": {"coordinates":[76.83533,8.57677],"type":"Point"}
}