{
  "type": "Feature",
  "properties": {
    "iso:country":"IN",
    "ks:ks_name":"Totaguda",
    "ks:ks_pop":147,
    "ks:ks_type":"VILLAGE",
    "name:eng_x_preferred":[
        "Totaguda"
    ],
    "wof:name":"Totaguda",
    "wof:placetype":"locality",
    "wof:population":147
},
  "geometry": {"coordinates":[82.33709,18.378014],"type":"Point"}
}