{
  "type": "Feature",
  "properties": {
    "iso:country":"IN",
    "ks:ks_name":"Keralkudl",
    "ks:ks_pop":95,
    "ks:ks_type":"HABITATION",
    "name:eng_x_preferred":[
        "Keralkudl"
    ],
    "wof:name":"Keralkudl",
    "wof:placetype":"locality",
    "wof:population":95
},
  "geometry": {"coordinates":[74.630352,14.234367],"type":"Point"}
}