{
  "type": "Feature",
  "properties": {
    "gn:admin1_code":"35.0",
    "gn:admin2_code":"454.0",
    "gn:asciiname":"Seda",
    "gn:country_code":"IN",
    "gn:dem":643,
    "gn:feature_class":"P",
    "gn:feature_code":"PPL",
    "gn:name":"Sed\u0101",
    "gn:population":0,
    "gn:timezone":"Asia/Kolkata",
    "iso:country":"IN",
    "name:ast_x_preferred":[
        "Seda"
    ],
    "name:cat_x_preferred":[
        "Seda"
    ],
    "name:ceb_x_preferred":[
        "Seda"
    ],
    "name:ces_x_preferred":[
        "Seda"
    ],
    "name:deu_x_preferred":[
        "Seda"
    ],
    "name:fra_x_preferred":[
        "Seda"
    ],
    "name:glg_x_preferred":[
        "Seda"
    ],
    "name:kaz_x_preferred":[
        "\u0421\u0435\u0434\u0430"
    ],
    "name:lav_x_preferred":[
        "Seda"
    ],
    "name:lit_x_preferred":[
        "Seda"
    ],
    "name:por_x_preferred":[
        "Seda"
    ],
    "name:rus_x_preferred":[
        "\u0421\u0435\u0434\u0430"
    ],
    "name:spa_x_preferred":[
        "Seda"
    ],
    "name:swe_x_preferred":[
        "Seda"
    ],
    "name:ukr_x_preferred":[
        "\u0421\u0435\u0434\u0430"
    ],
    "wof:name":"Seda",
    "wof:placetype":"locality"
},
  "geometry": {"coordinates":[80.97778000000002,22.43901],"type":"Point"}
}