{
  "type": "Feature",
  "properties": {
    "iso:country":"IN",
    "ks:ks_name":"Mundakonda",
    "ks:ks_pop":31,
    "ks:ks_type":"HABITATION",
    "name:eng_x_preferred":[
        "Mundakonda"
    ],
    "wof:name":"Mundakonda",
    "wof:placetype":"locality",
    "wof:population":31
},
  "geometry": {"coordinates":[75.05762900000001,13.828261],"type":"Point"}
}