{
  "type": "Feature",
  "properties": {
    "gn:admin1_code":"2.0",
    "gn:admin2_code":"542.0",
    "gn:asciiname":"Kurmarajupuram",
    "gn:country_code":"IN",
    "gn:dem":68,
    "gn:feature_class":"P",
    "gn:feature_code":"PPL",
    "gn:name":"K\u016brmar\u0101jupuram",
    "gn:population":0,
    "gn:timezone":"Asia/Kolkata",
    "iso:country":"IN",
    "wof:name":"Kurmarajupuram",
    "wof:placetype":"neighbourhood"
},
  "geometry": {"coordinates":[83.70558,18.60378],"type":"Point"}
}