{
  "type": "Feature",
  "properties": {
    "iso:country":"IN",
    "ks:ks_name":"Timbi Faliya",
    "ks:ks_pop":843,
    "ks:ks_type":"HABITATION",
    "name:eng_x_preferred":[
        "Timbi Faliya"
    ],
    "wof:name":"Timbi Faliya",
    "wof:placetype":"locality",
    "wof:population":843
},
  "geometry": {"coordinates":[74.293361,23.075194],"type":"Point"}
}