{
  "type": "Feature",
  "properties": {
    "iso:country":"IN",
    "ks:ks_name":"Mangasidda",
    "ks:ks_pop":240,
    "ks:ks_type":"HABITATION",
    "name:eng_x_preferred":[
        "Mangasidda"
    ],
    "wof:name":"Mangasidda",
    "wof:placetype":"locality",
    "wof:population":240
},
  "geometry": {"coordinates":[74.79798599999999,13.60934],"type":"Point"}
}