{
  "type": "Feature",
  "properties": {
    "iso:country":"IN",
    "ks:ks_name":"Bakari Doloni",
    "ks:ks_pop":1016,
    "ks:ks_type":"VILLAGE",
    "ks:ks_uagg_main":0,
    "name:eng_x_preferred":[
        "Bakari Doloni"
    ],
    "wof:name":"Bakari Doloni",
    "wof:placetype":"neighbourhood",
    "wof:population":1016
},
  "geometry": {"coordinates":[93.56133199999999,26.820738],"type":"Point"}
}