{
  "type": "Feature",
  "properties": {
    "iso:country":"IN",
    "ks:ks_alt_nam":"Tupidhar pt-I",
    "ks:ks_name":"Tupidhar Pt-i",
    "ks:ks_pop":367,
    "ks:ks_type":"HABITATION",
    "name:eng_x_preferred":[
        "Tupidhar Pt-i"
    ],
    "wof:name":"Tupidhar Pt-i",
    "wof:placetype":"locality",
    "wof:population":367
},
  "geometry": {"coordinates":[92.921763,24.608183],"type":"Point"}
}