{
  "type": "Feature",
  "properties": {
    "gn:admin1_code":"36",
    "gn:admin2_code":"197.0",
    "gn:asciiname":"Hathi",
    "gn:country_code":"IN",
    "gn:dem":86,
    "gn:feature_class":"P",
    "gn:feature_code":"PPL",
    "gn:name":"H\u0101thi",
    "gn:population":0,
    "gn:timezone":"Asia/Kolkata",
    "iso:country":"IN",
    "name:fra_x_preferred":[
        "Colonel Hathi"
    ],
    "name:heb_x_preferred":[
        "\u05e7\u05d5\u05dc\u05d5\u05e0\u05dc \u05d4\u05d0\u05d8\u05d9"
    ],
    "name:ita_x_preferred":[
        "Hathi"
    ],
    "wof:name":"Hathi",
    "wof:placetype":"locality"
},
  "geometry": {"coordinates":[82.82529,25.35527],"type":"Point"}
}