{
  "type": "Feature",
  "properties": {
    "iso:country":"IN",
    "ks:ks_name":"Varachi Gavkarwadi",
    "ks:ks_pop":451,
    "ks:ks_type":"HABITATION",
    "name:eng_x_preferred":[
        "Varachi Gavkarwadi"
    ],
    "wof:name":"Varachi Gavkarwadi",
    "wof:placetype":"locality",
    "wof:population":451
},
  "geometry": {"coordinates":[73.816472,15.856083],"type":"Point"}
}