{
  "type": "Feature",
  "properties": {
    "iso:country":"IN",
    "ks:ks_name":"Janata Housing Colony",
    "ks:ks_pop":151,
    "ks:ks_type":"HABITATION",
    "name:eng_x_preferred":[
        "Janata Housing Colony"
    ],
    "wof:name":"Janata Housing Colony",
    "wof:placetype":"locality",
    "wof:population":151
},
  "geometry": {"coordinates":[74.39241699999999,14.543763],"type":"Point"}
}