{
  "type": "Feature",
  "properties": {
    "gn:admin1_code":"38",
    "gn:admin2_code":"358.0",
    "gn:asciiname":"Tisibar Khurd",
    "gn:country_code":"IN",
    "gn:dem":188,
    "gn:feature_class":"P",
    "gn:feature_code":"PPL",
    "gn:name":"Tis\u012bb\u0101r Khurd",
    "gn:population":0,
    "gn:timezone":"Asia/Kolkata",
    "iso:country":"IN",
    "ks:ks_alt_nam":"Tis\u012bb\u0101r Khurd",
    "ks:ks_name":"Tisibar Khurd",
    "ks:ks_type":"VILLAGE",
    "ks:ks_uagg_main":0,
    "name:eng_x_preferred":[
        "Tisibar Khurd"
    ],
    "name:eng_x_variant":[
        "Tis\u012bb\u0101r Khurd"
    ],
    "wof:name":"Tisibar Khurd",
    "wof:placetype":"neighbourhood"
},
  "geometry": {"coordinates":[83.91652499999999,24.319901],"type":"Point"}
}