{
  "type": "Feature",
  "properties": {
    "iso:country":"IN",
    "ks:ks_alt_nam":"Palathankari east",
    "ks:ks_name":"Palathankari East",
    "ks:ks_pop":190,
    "ks:ks_type":"HABITATION",
    "name:eng_x_preferred":[
        "Palathankari East"
    ],
    "wof:name":"Palathankari East",
    "wof:placetype":"locality",
    "wof:population":190
},
  "geometry": {"coordinates":[78.67686500000001,11.44165],"type":"Point"}
}