{
  "type": "Feature",
  "properties": {
    "gn:admin1_code":"24.0",
    "gn:admin2_code":"120.0",
    "gn:asciiname":"Duragpura",
    "gn:country_code":"IN",
    "gn:dem":278,
    "gn:feature_class":"P",
    "gn:feature_code":"PPL",
    "gn:name":"Dur\u0101gpura",
    "gn:population":0,
    "gn:timezone":"Asia/Kolkata",
    "iso:country":"IN",
    "wof:name":"Duragpura",
    "wof:placetype":"locality"
},
  "geometry": {"coordinates":[76.12073000000002,26.53381],"type":"Point"}
}