{
  "type": "Feature",
  "properties": {
    "iso:country":"IN",
    "ks:ks_name":"Kikkatiguda",
    "ks:ks_pop":146,
    "ks:ks_type":"VILLAGE",
    "name:eng_x_preferred":[
        "Kikkatiguda"
    ],
    "wof:name":"Kikkatiguda",
    "wof:placetype":"locality",
    "wof:population":146
},
  "geometry": {"coordinates":[83.04272899999999,18.331684],"type":"Point"}
}