{
  "type": "Feature",
  "properties": {
    "iso:country":"IN",
    "ks:ks_name":"Sannakusanahadlu",
    "ks:ks_pop":121,
    "ks:ks_type":"HABITATION",
    "name:eng_x_preferred":[
        "Sannakusanahadlu"
    ],
    "wof:name":"Sannakusanahadlu",
    "wof:placetype":"locality",
    "wof:population":121
},
  "geometry": {"coordinates":[75.327832,13.309285],"type":"Point"}
}