{
  "type": "Feature",
  "properties": {
    "iso:country":"IN",
    "ks:ks_name":"Pushpagiri",
    "ks:ks_pop":750,
    "ks:ks_type":"HABITATION",
    "name:eng_x_preferred":[
        "Pushpagiri"
    ],
    "wof:name":"Pushpagiri",
    "wof:placetype":"locality",
    "wof:population":750
},
  "geometry": {"coordinates":[76.067674,11.333333],"type":"Point"}
}