{
  "type": "Feature",
  "properties": {
    "iso:country":"IN",
    "ks:ks_name":"Basi Mog Para-4",
    "ks:ks_pop":404,
    "ks:ks_type":"HABITATION",
    "name:eng_x_preferred":[
        "Basi Mog Para-4"
    ],
    "wof:name":"Basi Mog Para-4",
    "wof:placetype":"locality",
    "wof:population":404
},
  "geometry": {"coordinates":[91.531209,23.303128],"type":"Point"}
}