{
  "type": "Feature",
  "properties": {
    "iso:country":"IN",
    "ks:ks_name":"Biswanathpur",
    "ks:ks_pop":309,
    "ks:ks_type":"HABITATION",
    "ks:ks_uagg_main":0,
    "name:eng_x_preferred":[
        "Biswanathpur"
    ],
    "wof:name":"Biswanathpur",
    "wof:placetype":"neighbourhood",
    "wof:population":309
},
  "geometry": {"coordinates":[85.630858,21.710912],"type":"Point"}
}