{
  "type": "Feature",
  "properties": {
    "iso:country":"IN",
    "ks:ks_name":"Kodsalli Kumbri",
    "ks:ks_pop":102,
    "ks:ks_type":"HABITATION",
    "name:eng_x_preferred":[
        "Kodsalli Kumbri"
    ],
    "wof:name":"Kodsalli Kumbri",
    "wof:placetype":"locality",
    "wof:population":102
},
  "geometry": {"coordinates":[74.569255,14.877376],"type":"Point"}
}