{
  "type": "Feature",
  "properties": {
    "iso:country":"IN",
    "ks:ks_name":"Cheharia",
    "ks:ks_pop":749,
    "ks:ks_type":"HABITATION",
    "name:eng_x_preferred":[
        "Cheharia"
    ],
    "wof:name":"Cheharia",
    "wof:placetype":"locality",
    "wof:population":749
},
  "geometry": {"coordinates":[83.412352,25.221558],"type":"Point"}
}