{
  "type": "Feature",
  "properties": {
    "iso:country":"IN",
    "ks:ks_alt_nam":"Jalloo ki Jhor",
    "ks:ks_name":"Jalloo Ki Jhor",
    "ks:ks_pop":55,
    "ks:ks_type":"HABITATION",
    "name:eng_x_preferred":[
        "Jalloo Ki Jhor"
    ],
    "wof:name":"Jalloo Ki Jhor",
    "wof:placetype":"locality",
    "wof:population":55
},
  "geometry": {"coordinates":[77.475933,26.483483],"type":"Point"}
}