{
  "type": "Feature",
  "properties": {
    "iso:country":"IN",
    "ks:ks_name":"Kotodi",
    "ks:ks_pop":237,
    "ks:ks_type":"VILLAGE",
    "name:eng_x_preferred":[
        "Kotodi"
    ],
    "wof:name":"Kotodi",
    "wof:placetype":"locality",
    "wof:population":237
},
  "geometry": {"coordinates":[80.915558,20.032447],"type":"Point"}
}