{
  "type": "Feature",
  "properties": {
    "iso:country":"IN",
    "ks:ks_name":"Savarpada",
    "ks:ks_pop":102,
    "ks:ks_type":"HABITATION",
    "name:eng_x_preferred":[
        "Savarpada"
    ],
    "wof:name":"Savarpada",
    "wof:placetype":"locality",
    "wof:population":102
},
  "geometry": {"coordinates":[73.258611,20.215028],"type":"Point"}
}