{
  "type": "Feature",
  "properties": {
    "gn:admin1_code":"24.0",
    "gn:admin2_code":"128.0",
    "gn:asciiname":"Gobindpura",
    "gn:country_code":"IN",
    "gn:dem":349,
    "gn:feature_class":"P",
    "gn:feature_code":"PPL",
    "gn:name":"Gobindpura",
    "gn:population":0,
    "gn:timezone":"Asia/Kolkata",
    "iso:country":"IN",
    "wof:name":"Gobindpura",
    "wof:placetype":"locality"
},
  "geometry": {"coordinates":[76.86126999999998,24.57832],"type":"Point"}
}