{
  "type": "Feature",
  "properties": {
    "gn:admin1_code":"24.0",
    "gn:admin2_code":"128.0",
    "gn:asciiname":"Gobindpura",
    "gn:country_code":"IN",
    "gn:dem":349,
    "gn:feature_class":"P",
    "gn:feature_code":"PPL",
    "gn:name":"Gobindpura",
    "gn:population":0,
    "gn:timezone":"Asia/Kolkata",
    "iso:country":"IN",
    "ks:ks_name":"Gobin Pura",
    "ks:ks_pop":468,
    "ks:ks_type":"VILLAGE",
    "name:eng_x_preferred":[
        "Gobin Pura"
    ],
    "name:eng_x_variant":[
        "Gobindpura"
    ],
    "wof:name":"Gobin Pura",
    "wof:placetype":"locality",
    "wof:population":468
},
  "geometry": {"coordinates":[76.85976100000001,24.583713],"type":"Point"}
}