{
  "type": "Feature",
  "properties": {
    "iso:country":"IN",
    "ks:ks_name":"Kaneri Ryt.",
    "ks:ks_pop":403,
    "ks:ks_type":"VILLAGE",
    "name:eng_x_preferred":[
        "Kaneri Ryt."
    ],
    "wof:name":"Kaneri Ryt.",
    "wof:placetype":"locality",
    "wof:population":403
},
  "geometry": {"coordinates":[80.677117,23.005613],"type":"Point"}
}