{
  "type": "Feature",
  "properties": {
    "gn:admin1_code":"13.0",
    "gn:admin2_code":"600.0",
    "gn:asciiname":"Annur",
    "gn:country_code":"IN",
    "gn:dem":87,
    "gn:feature_class":"P",
    "gn:feature_code":"PPL",
    "gn:name":"Ann\u016br",
    "gn:population":0,
    "gn:timezone":"Asia/Kolkata",
    "iso:country":"IN",
    "name:bpy_x_preferred":[
        "\u0986\u09a8\u09cd\u09a8\u09c1\u09b0"
    ],
    "name:ceb_x_preferred":[
        "Annur"
    ],
    "name:ita_x_preferred":[
        "Annur"
    ],
    "name:msa_x_preferred":[
        "Annur"
    ],
    "name:new_x_preferred":[
        "\u0905\u0928\u094d\u0928\u0941\u0930"
    ],
    "name:nld_x_preferred":[
        "Annur"
    ],
    "name:por_x_preferred":[
        "Annur"
    ],
    "name:swe_x_preferred":[
        "Annur"
    ],
    "name:tam_x_preferred":[
        "\u0b85\u0ba9\u0bcd\u0ba9\u0bc2\u0bb0\u0bcd"
    ],
    "name:urd_x_preferred":[
        "\u0627\u0646\u0648\u0631 \u062a\u0639\u0642\u0644\u06c1"
    ],
    "name:vie_x_preferred":[
        "Annur"
    ],
    "wof:name":"Annur",
    "wof:placetype":"locality"
},
  "geometry": {"coordinates":[76.74632,8.97337],"type":"Point"}
}