{
  "type": "Feature",
  "properties": {
    "iso:country":"IN",
    "ks:ks_name":"Burakayalabanda",
    "ks:ks_pop":72,
    "ks:ks_type":"HABITATION",
    "name:eng_x_preferred":[
        "Burakayalabanda"
    ],
    "wof:name":"Burakayalabanda",
    "wof:placetype":"locality",
    "wof:population":72
},
  "geometry": {"coordinates":[78.964,13.523672],"type":"Point"}
}