{
  "type": "Feature",
  "properties": {
    "gn:admin1_code":"24.0",
    "gn:admin2_code":"126.0",
    "gn:asciiname":"Pitampura",
    "gn:country_code":"IN",
    "gn:dem":464,
    "gn:feature_class":"P",
    "gn:feature_code":"PPL",
    "gn:name":"Pitampura",
    "gn:population":0,
    "gn:timezone":"Asia/Kolkata",
    "iso:country":"IN",
    "name:ara_x_preferred":[
        "\u0628\u064a\u062a\u0645\u0628\u0648\u0631\u0627"
    ],
    "name:ben_bn_x_preferred":[
        "\u09aa\u09bf\u09a4\u09ae\u09aa\u09c1\u09b0\u09be"
    ],
    "name:ben_in_x_preferred":[
        "\u09aa\u09bf\u09a4\u09ae\u09aa\u09c1\u09b0\u09be"
    ],
    "name:guj_x_preferred":[
        "\u0aaa\u0abf\u0aa4\u0abe\u0aae\u0aaa\u0ac1\u0ab0\u0abe"
    ],
    "name:hin_x_preferred":[
        "\u092a\u0940\u0924\u092e\u092a\u0941\u0930\u093e"
    ],
    "name:kan_x_preferred":[
        "\u0caa\u0cbf\u0ca4\u0cbe\u0cae\u0ccd"
    ],
    "name:mal_x_preferred":[
        "\u0d24\u0d3f\u0d32\u0d15\u0d4d \u0d28\u0d17\u0d7c \u0d2a\u0d3f\u0d31\u0d4d\u0d31\u0d3e\u0d02\u0d2a\u0d41\u0d30"
    ],
    "name:mar_x_preferred":[
        "\u092a\u093f\u0924\u092e\u092a\u0941\u0930\u093e"
    ],
    "name:pan_x_preferred":[
        "\u0a2a\u0a40\u0a24\u0a2e\u0a2a\u0a41\u0a30\u0a3e"
    ],
    "name:tam_x_preferred":[
        "\u0baa\u0bc0\u0ba4\u0bae\u0bcd\u0baa\u0bc1\u0bb0\u0bbe"
    ],
    "name:tel_x_preferred":[
        "\u0c2a\u0c3f\u0c24\u0c3e\u0c02\u0c2a\u0c41\u0c30\u0c3e"
    ],
    "name:urd_x_preferred":[
        "\u067e\u06cc\u062a\u0645 \u067e\u0648\u0631\u06c1"
    ],
    "wof:name":"Pitampura",
    "wof:placetype":"locality"
},
  "geometry": {"coordinates":[74.22139,24.71912],"type":"Point"}
}