{
  "type": "Feature",
  "properties": {
    "iso:country":"IN",
    "ks:ks_name":"Ramhetapur",
    "ks:ks_pop":30,
    "ks:ks_type":"HABITATION",
    "name:eng_x_preferred":[
        "Ramhetapur"
    ],
    "wof:name":"Ramhetapur",
    "wof:placetype":"locality",
    "wof:population":30
},
  "geometry": {"coordinates":[81.48038200000001,25.179507],"type":"Point"}
}