{
  "type": "Feature",
  "properties": {
    "gn:admin1_code":"36",
    "gn:admin2_code":"147.0",
    "gn:asciiname":"Aidalpur",
    "gn:country_code":"IN",
    "gn:dem":164,
    "gn:feature_class":"P",
    "gn:feature_code":"PPL",
    "gn:name":"Aidalpur",
    "gn:population":0,
    "gn:timezone":"Asia/Kolkata",
    "iso:country":"IN",
    "name:fas_x_preferred":[
        "\u0627\u06cc\u062f\u0627\u0644\u067e\u0648\u0631"
    ],
    "name:pan_x_preferred":[
        "\u0a10\u0a26\u0a32\u0a2a\u0a41\u0a30"
    ],
    "wof:name":"Aidalpur",
    "wof:placetype":"locality"
},
  "geometry": {"coordinates":[78.6567,27.01503],"type":"Point"}
}