{
  "type": "Feature",
  "properties": {
    "iso:country":"IN",
    "ks:ks_name":"Narsapuram",
    "ks:ks_pop":31,
    "ks:ks_type":"HABITATION",
    "name:eng_x_preferred":[
        "Narsapuram"
    ],
    "wof:name":"Narsapuram",
    "wof:placetype":"locality",
    "wof:population":31
},
  "geometry": {"coordinates":[80.460032,18.067015],"type":"Point"}
}