{
  "type": "Feature",
  "properties": {
    "iso:country":"IN",
    "ks:ks_name":"Palaniappa Lease",
    "ks:ks_pop":42,
    "ks:ks_type":"HABITATION",
    "name:eng_x_preferred":[
        "Palaniappa Lease"
    ],
    "wof:name":"Palaniappa Lease",
    "wof:placetype":"locality",
    "wof:population":42
},
  "geometry": {"coordinates":[76.748643,11.258383],"type":"Point"}
}