{
  "type": "Feature",
  "properties": {
    "iso:country":"IN",
    "ks:ks_alt_nam":"Kalyana malla Lali Kalyani",
    "ks:ks_name":"Kalyana Malla Lali Kalyani",
    "ks:ks_pop":138,
    "ks:ks_type":"HABITATION",
    "name:eng_x_preferred":[
        "Kalyana Malla Lali Kalyani"
    ],
    "wof:name":"Kalyana Malla Lali Kalyani",
    "wof:placetype":"locality",
    "wof:population":138
},
  "geometry": {"coordinates":[79.298265,29.95855],"type":"Point"}
}