{
  "type": "Feature",
  "properties": {
    "iso:country":"IN",
    "ks:ks_name":"Boldiabathan",
    "ks:ks_pop":1011,
    "ks:ks_type":"HABITATION",
    "name:eng_x_preferred":[
        "Boldiabathan"
    ],
    "wof:name":"Boldiabathan",
    "wof:placetype":"locality",
    "wof:population":1011
},
  "geometry": {"coordinates":[90.176441,26.43007],"type":"Point"}
}