{
  "type": "Feature",
  "properties": {
    "iso:country":"IN",
    "ks:ks_name":"New Tola",
    "ks:ks_pop":199,
    "ks:ks_type":"HABITATION",
    "ks:ks_uagg_main":0,
    "name:eng_x_preferred":[
        "New Tola"
    ],
    "wof:name":"New Tola",
    "wof:placetype":"neighbourhood",
    "wof:population":199
},
  "geometry": {"coordinates":[87.11593999999999,25.703076],"type":"Point"}
}