{
  "type": "Feature",
  "properties": {
    "iso:country":"IN",
    "ks:ks_name":"Kochukaboru",
    "ks:ks_pop":270,
    "ks:ks_type":"HABITATION",
    "name:eng_x_preferred":[
        "Kochukaboru"
    ],
    "wof:name":"Kochukaboru",
    "wof:placetype":"locality",
    "wof:population":270
},
  "geometry": {"coordinates":[93.99600700000001,26.543259],"type":"Point"}
}