{
  "type": "Feature",
  "properties": {
    "iso:country":"IN",
    "ks:ks_name":"Narikuravar Colony",
    "ks:ks_pop":268,
    "ks:ks_type":"HABITATION",
    "name:eng_x_preferred":[
        "Narikuravar Colony"
    ],
    "wof:name":"Narikuravar Colony",
    "wof:placetype":"locality",
    "wof:population":268
},
  "geometry": {"coordinates":[79.696347,12.608868],"type":"Point"}
}