{
  "type": "Feature",
  "properties": {
    "iso:country":"IN",
    "ks:ks_name":"Gundka Colony",
    "ks:ks_pop":52,
    "ks:ks_type":"HABITATION",
    "name:eng_x_preferred":[
        "Gundka Colony"
    ],
    "wof:name":"Gundka Colony",
    "wof:placetype":"locality",
    "wof:population":52
},
  "geometry": {"coordinates":[75.541948,12.626354],"type":"Point"}
}