{
  "type": "Feature",
  "properties": {
    "gn:admin1_code":"40.0",
    "gn:admin2_code":"535.0",
    "gn:asciiname":"Sitarampalli",
    "gn:country_code":"IN",
    "gn:dem":564,
    "gn:feature_class":"P",
    "gn:feature_code":"PPL",
    "gn:name":"S\u012bt\u0101r\u0101mpalli",
    "gn:population":0,
    "gn:timezone":"Asia/Kolkata",
    "iso:country":"IN",
    "wof:name":"Sitarampalli",
    "wof:placetype":"locality"
},
  "geometry": {"coordinates":[78.55648000000002,17.79235],"type":"Point"}
}