{
  "type": "Feature",
  "properties": {
    "iso:country":"IN",
    "ks:ks_name":"Gopakul",
    "ks:ks_pop":400,
    "ks:ks_type":"HABITATION",
    "name:eng_x_preferred":[
        "Gopakul"
    ],
    "wof:name":"Gopakul",
    "wof:placetype":"locality",
    "wof:population":400
},
  "geometry": {"coordinates":[86.480028,20.852016],"type":"Point"}
}