{
  "type": "Feature",
  "properties": {
    "gn:admin1_code":"19",
    "gn:admin2_code":"555.0",
    "gn:asciiname":"Sambre",
    "gn:country_code":"IN",
    "gn:dem":745,
    "gn:feature_class":"P",
    "gn:feature_code":"PPL",
    "gn:name":"S\u0101mbre",
    "gn:population":0,
    "gn:timezone":"Asia/Kolkata",
    "iso:country":"IN",
    "name:und_x_variant":[
        "Sambra",
        "S\u0101mbre"
    ],
    "wof:name":"Sambre",
    "wof:placetype":"locality"
},
  "geometry": {"coordinates":[74.61142,15.87003],"type":"Point"}
}