{
  "type": "Feature",
  "properties": {
    "iso:country":"IN",
    "ks:ks_name":"Nawapada",
    "ks:ks_pop":90,
    "ks:ks_type":"VILLAGE",
    "name:eng_x_preferred":[
        "Nawapada"
    ],
    "wof:name":"Nawapada",
    "wof:placetype":"locality",
    "wof:population":90
},
  "geometry": {"coordinates":[74.90888099999999,22.575829],"type":"Point"}
}