{
  "type": "Feature",
  "properties": {
    "iso:country":"IN",
    "ks:ks_name":"Bindpuri",
    "ks:ks_pop":383,
    "ks:ks_type":"VILLAGE",
    "name:eng_x_preferred":[
        "Bindpuri"
    ],
    "wof:name":"Bindpuri",
    "wof:placetype":"locality",
    "wof:population":383
},
  "geometry": {"coordinates":[79.906485,25.913843],"type":"Point"}
}