{
  "type": "Feature",
  "properties": {
    "iso:country":"IN",
    "ks:ks_name":"Chamarauti",
    "ks:ks_pop":464,
    "ks:ks_type":"HABITATION",
    "name:eng_x_preferred":[
        "Chamarauti"
    ],
    "wof:name":"Chamarauti",
    "wof:placetype":"locality",
    "wof:population":464
},
  "geometry": {"coordinates":[82.58181999999999,25.944201],"type":"Point"}
}