{
  "type": "Feature",
  "properties": {
    "iso:country":"IN",
    "ks:ks_name":"Uppanadarakoppa",
    "ks:ks_pop":15,
    "ks:ks_type":"HABITATION",
    "name:eng_x_preferred":[
        "Uppanadarakoppa"
    ],
    "wof:name":"Uppanadarakoppa",
    "wof:placetype":"locality",
    "wof:population":15
},
  "geometry": {"coordinates":[74.319391,14.638099],"type":"Point"}
}