{
  "type": "Feature",
  "properties": {
    "iso:country":"IN",
    "ks:ks_name":"Chintaganalla",
    "ks:ks_pop":203,
    "ks:ks_type":"HABITATION",
    "name:eng_x_preferred":[
        "Chintaganalla"
    ],
    "wof:name":"Chintaganalla",
    "wof:placetype":"locality",
    "wof:population":203
},
  "geometry": {"coordinates":[82.723444,18.019406],"type":"Point"}
}