{
  "type": "Feature",
  "properties": {
    "iso:country":"IN",
    "ks:ks_name":"Kasthambadi",
    "ks:ks_pop":116,
    "ks:ks_type":"HABITATION",
    "name:eng_x_preferred":[
        "Kasthambadi"
    ],
    "wof:name":"Kasthambadi",
    "wof:placetype":"locality",
    "wof:population":116
},
  "geometry": {"coordinates":[79.539603,12.388093],"type":"Point"}
}