{
  "type": "Feature",
  "properties": {
    "iso:country":"IN",
    "ks:ks_name":"Fatehpur",
    "ks:ks_type":"VILLAGE",
    "name:eng_x_preferred":[
        "Fatehpur"
    ],
    "wof:name":"Fatehpur",
    "wof:placetype":"locality"
},
  "geometry": {"coordinates":[77.931777,28.737018],"type":"Point"}
}