{
  "type": "Feature",
  "properties": {
    "gn:country":"IN",
    "gn:fcode":"PPL",
    "gn:population":10392,
    "iso:country":"IN",
    "name:und_x_variant":[
        "Nagireddipalle"
    ],
    "qs:name":"N\u0101gireddipalli",
    "qs:photos_9r":0,
    "qs:photos_sr":0,
    "qs:pop_sr":"6",
    "wof:name":"N\u0101gireddipalli",
    "wof:placetype":"locality",
    "wof:population":10392
},
  "geometry": {"coordinates":[79.10083,14.26965],"type":"Point"}
}