{
  "type": "Feature",
  "properties": {
    "gn:admin1_code":"37.0",
    "gn:admin2_code":"410.0",
    "gn:asciiname":"Jarandih",
    "gn:country_code":"IN",
    "gn:dem":435,
    "gn:feature_class":"P",
    "gn:feature_code":"PPL",
    "gn:name":"Jarandih",
    "gn:population":0,
    "gn:timezone":"Asia/Kolkata",
    "iso:country":"IN",
    "wof:name":"Jarandih",
    "wof:placetype":"locality"
},
  "geometry": {"coordinates":[82.28145000000001,20.39346],"type":"Point"}
}