{
  "type": "Feature",
  "properties": {
    "gn:admin1_code":"37.0",
    "gn:admin2_code":"410.0",
    "gn:asciiname":"Jarandih",
    "gn:country_code":"IN",
    "gn:dem":435,
    "gn:feature_class":"P",
    "gn:feature_code":"PPL",
    "gn:name":"Jarandih",
    "gn:population":0,
    "gn:timezone":"Asia/Kolkata",
    "iso:country":"IN",
    "ks:ks_name":"Jarandih",
    "ks:ks_pop":214,
    "ks:ks_type":"VILLAGE",
    "name:eng_x_preferred":[
        "Jarandih"
    ],
    "wof:name":"Jarandih",
    "wof:placetype":"locality",
    "wof:population":214
},
  "geometry": {"coordinates":[82.281109,20.392738],"type":"Point"}
}