{
  "type": "Feature",
  "properties": {
    "gn:admin1_code":"11.0",
    "gn:admin2_code":"32.0",
    "gn:asciiname":"Jharinwa",
    "gn:country_code":"IN",
    "gn:dem":1551,
    "gn:feature_class":"P",
    "gn:feature_code":"PPL",
    "gn:name":"Jharinwa",
    "gn:population":0,
    "gn:timezone":"Asia/Kolkata",
    "iso:country":"IN",
    "wof:name":"Jharinwa",
    "wof:placetype":"locality"
},
  "geometry": {"coordinates":[77.25629000000001,30.72866],"type":"Point"}
}