{
  "type": "Feature",
  "properties": {
    "iso:country":"IN",
    "ks:ks_name":"Koriya",
    "ks:ks_pop":185,
    "ks:ks_type":"HABITATION",
    "name:eng_x_preferred":[
        "Koriya"
    ],
    "wof:name":"Koriya",
    "wof:placetype":"locality",
    "wof:population":185
},
  "geometry": {"coordinates":[86.165239,23.996283],"type":"Point"}
}