{
  "type": "Feature",
  "properties": {
    "gn:admin1_code":"35.0",
    "gn:admin2_code":"445.0",
    "gn:asciiname":"Bijori",
    "gn:country_code":"IN",
    "gn:dem":525,
    "gn:feature_class":"P",
    "gn:feature_code":"PPL",
    "gn:name":"B\u012bjori",
    "gn:population":0,
    "gn:timezone":"Asia/Kolkata",
    "iso:country":"IN",
    "ks:ks_alt_nam":"B\u012bjori",
    "ks:ks_name":"Bijori",
    "ks:ks_pop":217,
    "ks:ks_type":"VILLAGE",
    "name:eng_x_preferred":[
        "Bijori"
    ],
    "name:eng_x_variant":[
        "B\u012bjori"
    ],
    "wof:name":"Bijori",
    "wof:placetype":"locality",
    "wof:population":217
},
  "geometry": {"coordinates":[76.923711,22.945664],"type":"Point"}
}