{
  "type": "Feature",
  "properties": {
    "iso:country":"IN",
    "ks:ks_name":"Ram Nagar Tola",
    "ks:ks_pop":200,
    "ks:ks_type":"HABITATION",
    "name:eng_x_preferred":[
        "Ram Nagar Tola"
    ],
    "wof:name":"Ram Nagar Tola",
    "wof:placetype":"locality",
    "wof:population":200
},
  "geometry": {"coordinates":[83.62140599999999,26.814906],"type":"Point"}
}