{
  "type": "Feature",
  "properties": {
    "iso:country":"IN",
    "ks:ks_alt_nam":"KAHALE BAGIYA",
    "ks:ks_name":"Kahale Bagiya",
    "ks:ks_pop":81,
    "ks:ks_type":"HABITATION",
    "ks:ks_uagg_main":0,
    "name:eng_x_preferred":[
        "Kahale Bagiya"
    ],
    "wof:name":"Kahale Bagiya",
    "wof:placetype":"neighbourhood",
    "wof:population":81
},
  "geometry": {"coordinates":[81.511123,27.639223],"type":"Point"}
}