{
  "type": "Feature",
  "properties": {
    "iso:country":"IN",
    "ks:ks_name":"Santosh Nagar Vishnoi Ki Dhani",
    "ks:ks_pop":284,
    "ks:ks_type":"HABITATION",
    "name:eng_x_preferred":[
        "Santosh Nagar Vishnoi Ki Dhani"
    ],
    "wof:name":"Santosh Nagar Vishnoi Ki Dhani",
    "wof:placetype":"locality",
    "wof:population":284
},
  "geometry": {"coordinates":[71.440169,25.348192],"type":"Point"}
}