{
  "type": "Feature",
  "properties": {
    "gn:country":"IN",
    "iso:country":"IN",
    "name:ara_x_preferred":[
        "\u062c\u0627\u0646\u064a\u0634 \u0628\u0648\u0631\u0627"
    ],
    "name:ben_bn_x_preferred":[
        "\u0997\u09a8\u09c7\u09b6 \u09aa\u09c1\u09b0\u09be"
    ],
    "name:ben_in_x_preferred":[
        "\u0997\u09a8\u09c7\u09b6 \u09aa\u09c1\u09b0\u09be"
    ],
    "name:guj_x_preferred":[
        "\u0a97\u0aa3\u0ac7\u0ab6 \u0aaa\u0ac1\u0ab0\u0abe"
    ],
    "name:hin_x_preferred":[
        "\u0917\u0923\u0947\u0936 \u092a\u0941\u0930\u093e"
    ],
    "name:kan_x_preferred":[
        "\u0c97\u0ca3\u0cc7\u0cb6\u0ccd"
    ],
    "name:mal_x_preferred":[
        "\u0d17\u0d23\u0d47\u0d37\u0d4d \u0d2a\u0d41\u0d30"
    ],
    "name:mar_x_preferred":[
        "\u0917\u0923\u0947\u0936 \u092a\u0941\u0930\u093e"
    ],
    "name:pan_x_preferred":[
        "\u0a17\u0a23\u0a47\u0a36 \u0a2a\u0a41\u0a30\u0a3e"
    ],
    "name:tam_x_preferred":[
        "\u0b95\u0ba3\u0bc7\u0bb7\u0bcd \u0baa\u0bc1\u0bb0\u0bbe"
    ],
    "name:tel_x_preferred":[
        "\u0c17\u0c23\u0c47\u0c37\u0c4d \u0c2a\u0c41\u0c30\u0c3e"
    ],
    "name:urd_x_preferred":[
        "\u06af\u0646\u06cc\u0634 \u067e\u0648\u0631\u06c1"
    ],
    "qs:name":"Ganesh Pura",
    "qs:name_adm0":"India",
    "qs:name_adm1":"Maharashtra",
    "qs:photos":12,
    "qs:photos_1k":2,
    "qs:photos_9k":1,
    "qs:photos_9r":1,
    "qs:photos_all":12,
    "qs:photos_sr":1,
    "qs:placetype":"Suburb",
    "qs:pop_sr":"0",
    "wof:name":"Ganesh Pura",
    "wof:placetype":"neighbourhood"
},
  "geometry": {"coordinates":[73.03389199999999,19.003596],"type":"Point"}
}