{
  "type": "Feature",
  "properties": {
    "gn:country":"IN",
    "iso:country":"IN",
    "qs:name":"Ganesh Pura",
    "qs:name_adm0":"India",
    "qs:name_adm1":"Maharashtra",
    "qs:photos":12,
    "qs:photos_1k":2,
    "qs:photos_9k":1,
    "qs:photos_9r":1,
    "qs:photos_all":12,
    "qs:photos_sr":1,
    "qs:placetype":"Suburb",
    "qs:pop_sr":"0",
    "wof:name":"Ganesh Pura",
    "wof:placetype":"neighbourhood"
},
  "geometry": {"coordinates":[73.03389199999999,19.003596],"type":"Point"}
}