{
  "type": "Feature",
  "properties": {
    "iso:country":"IN",
    "ks:ks_name":"Mailta",
    "ks:ks_pop":44,
    "ks:ks_type":"VILLAGE",
    "name:eng_x_preferred":[
        "Mailta"
    ],
    "wof:name":"Mailta",
    "wof:placetype":"locality",
    "wof:population":44
},
  "geometry": {"coordinates":[79.968475,29.381906],"type":"Point"}
}