{
  "type": "Feature",
  "properties": {
    "iso:country":"IN",
    "ks:ks_name":"Belaguan",
    "ks:ks_pop":17,
    "ks:ks_type":"VILLAGE",
    "name:eng_x_preferred":[
        "Belaguan"
    ],
    "wof:name":"Belaguan",
    "wof:placetype":"locality",
    "wof:population":17
},
  "geometry": {"coordinates":[85.381669,20.096575],"type":"Point"}
}