{
  "type": "Feature",
  "properties": {
    "gn:admin1_code":"36.0",
    "gn:admin2_code":"155.0",
    "gn:asciiname":"Raigawan",
    "gn:country_code":"IN",
    "gn:dem":156,
    "gn:feature_class":"P",
    "gn:feature_code":"PPL",
    "gn:name":"Raigaw\u0101n",
    "gn:population":0,
    "gn:timezone":"Asia/Kolkata",
    "iso:country":"IN",
    "wof:name":"Raigawan",
    "wof:placetype":"locality"
},
  "geometry": {"coordinates":[80.00166,27.71973],"type":"Point"}
}