{
  "type": "Feature",
  "properties": {
    "gn:admin1_code":"39",
    "gn:admin2_code":"61.0",
    "gn:asciiname":"Danddhar Malla",
    "gn:country_code":"IN",
    "gn:dem":1235,
    "gn:feature_class":"P",
    "gn:feature_code":"PPL",
    "gn:name":"Danddh\u0101r Malla",
    "gn:population":0,
    "gn:timezone":"Asia/Kolkata",
    "iso:country":"IN",
    "wof:name":"Danddhar Malla",
    "wof:placetype":"locality"
},
  "geometry": {"coordinates":[78.96767,29.72582],"type":"Point"}
}