{
  "type": "Feature",
  "properties": {
    "iso:country":"IN",
    "ks:ks_name":"Asana Kasimpur",
    "ks:ks_pop":0,
    "ks:ks_type":"VILLAGE",
    "name:eng_x_preferred":[
        "Asana Kasimpur"
    ],
    "wof:name":"Asana Kasimpur",
    "wof:placetype":"locality",
    "wof:population":0
},
  "geometry": {"coordinates":[81.422549,25.402621],"type":"Point"}
}