{
  "type": "Feature",
  "properties": {
    "gn:admin1_code":"16",
    "gn:admin2_code":"510.0",
    "gn:asciiname":"Yedsi",
    "gn:country_code":"IN",
    "gn:dem":208,
    "gn:feature_class":"P",
    "gn:feature_code":"PPL",
    "gn:name":"Yedsi",
    "gn:population":0,
    "gn:timezone":"Asia/Kolkata",
    "iso:country":"IN",
    "ks:ks_name":"Yedsi",
    "ks:ks_pop":668,
    "ks:ks_type":"VILLAGE",
    "name:eng_x_preferred":[
        "Yedsi"
    ],
    "wof:name":"Yedsi",
    "wof:placetype":"locality",
    "wof:population":668
},
  "geometry": {"coordinates":[78.882581,19.769085],"type":"Point"}
}