{
  "type": "Feature",
  "properties": {
    "iso:country":"IN",
    "ks:ks_name":"Malkaguda",
    "ks:ks_pop":91,
    "ks:ks_type":"HABITATION",
    "name:eng_x_preferred":[
        "Malkaguda"
    ],
    "wof:name":"Malkaguda",
    "wof:placetype":"locality",
    "wof:population":91
},
  "geometry": {"coordinates":[78.710354,19.494263],"type":"Point"}
}