{
  "type": "Feature",
  "properties": {
    "iso:country":"IN",
    "ks:ks_name":"Madiguru",
    "ks:ks_pop":138,
    "ks:ks_type":"VILLAGE",
    "name:eng_x_preferred":[
        "Madiguru"
    ],
    "wof:name":"Madiguru",
    "wof:placetype":"locality",
    "wof:population":138
},
  "geometry": {"coordinates":[81.448171,17.833239],"type":"Point"}
}