{
  "type": "Feature",
  "properties": {
    "gn:admin1_code":"36.0",
    "gn:admin2_code":"160",
    "gn:asciiname":"Harharpur",
    "gn:country_code":"IN",
    "gn:dem":149,
    "gn:feature_class":"P",
    "gn:feature_code":"PPL",
    "gn:name":"Harharpur",
    "gn:population":0,
    "gn:timezone":"Asia/Kolkata",
    "iso:country":"IN",
    "name:und_x_variant":[
        "Mah\u0101digir",
        "Harharpur"
    ],
    "wof:name":"Harharpur",
    "wof:placetype":"locality"
},
  "geometry": {"coordinates":[79.4789,27.09884000000001],"type":"Point"}
}