{
  "type": "Feature",
  "properties": {
    "iso:country":"IN",
    "ks:ks_alt_nam":"balapar",
    "ks:ks_name":"Balapar",
    "ks:ks_pop":200,
    "ks:ks_type":"HABITATION",
    "name:eng_x_preferred":[
        "Balapar"
    ],
    "wof:name":"Balapar",
    "wof:placetype":"locality",
    "wof:population":200
},
  "geometry": {"coordinates":[68.68962500000001,23.655917],"type":"Point"}
}