{
  "type": "Feature",
  "properties": {
    "iso:country":"IN",
    "ks:ks_name":"Mahavath Purwa",
    "ks:ks_pop":89,
    "ks:ks_type":"HABITATION",
    "name:eng_x_preferred":[
        "Mahavath Purwa"
    ],
    "wof:name":"Mahavath Purwa",
    "wof:placetype":"locality",
    "wof:population":89
},
  "geometry": {"coordinates":[81.858374,27.568099],"type":"Point"}
}