{
  "type": "Feature",
  "properties": {
    "iso:country":"IN",
    "ks:ks_alt_nam":"Nijamdin ki basti",
    "ks:ks_name":"Nijamdin Ki Basti",
    "ks:ks_pop":76,
    "ks:ks_type":"HABITATION",
    "name:eng_x_preferred":[
        "Nijamdin Ki Basti"
    ],
    "wof:name":"Nijamdin Ki Basti",
    "wof:placetype":"locality",
    "wof:population":76
},
  "geometry": {"coordinates":[72.025289,27.356633],"type":"Point"}
}