{
  "type": "Feature",
  "properties": {
    "iso:country":"IN",
    "ks:ks_name":"Kyara",
    "ks:ks_pop":867,
    "ks:ks_type":"VILLAGE",
    "name:eng_x_preferred":[
        "Kyara"
    ],
    "wof:name":"Kyara",
    "wof:placetype":"locality",
    "wof:population":867
},
  "geometry": {"coordinates":[74.16944700000001,24.076056],"type":"Point"}
}