{
  "type": "Feature",
  "properties": {
    "iso:country":"IN",
    "ks:ks_name":"Govaraipada",
    "ks:ks_pop":70,
    "ks:ks_type":"HABITATION",
    "name:eng_x_preferred":[
        "Govaraipada"
    ],
    "wof:name":"Govaraipada",
    "wof:placetype":"locality",
    "wof:population":70
},
  "geometry": {"coordinates":[72.866409,19.723449],"type":"Point"}
}