{
  "type": "Feature",
  "properties": {
    "iso:country":"IN",
    "ks:ks_alt_nam":"tandelpada",
    "ks:ks_name":"Tandelpada",
    "ks:ks_pop":114,
    "ks:ks_type":"HABITATION",
    "name:eng_x_preferred":[
        "Tandelpada"
    ],
    "wof:name":"Tandelpada",
    "wof:placetype":"locality",
    "wof:population":114
},
  "geometry": {"coordinates":[72.950664,19.83262],"type":"Point"}
}