{
  "type": "Feature",
  "properties": {
    "iso:country":"IN",
    "ks:ks_name":"Guhadihi",
    "ks:ks_pop":53,
    "ks:ks_type":"HABITATION",
    "name:eng_x_preferred":[
        "Guhadihi"
    ],
    "wof:name":"Guhadihi",
    "wof:placetype":"locality",
    "wof:population":53
},
  "geometry": {"coordinates":[81.756084,19.797058],"type":"Point"}
}