{
  "type": "Feature",
  "properties": {
    "iso:country":"IN",
    "ks:ks_name":"Raragar",
    "ks:ks_pop":270,
    "ks:ks_type":"VILLAGE",
    "name:eng_x_preferred":[
        "Raragar"
    ],
    "wof:name":"Raragar",
    "wof:placetype":"locality",
    "wof:population":270
},
  "geometry": {"coordinates":[78.728376,30.353163],"type":"Point"}
}