{
  "type": "Feature",
  "properties": {
    "iso:country":"IN",
    "ks:ks_name":"Dakhin Borpothar",
    "ks:ks_pop":401,
    "ks:ks_type":"VILLAGE",
    "ks:ks_uagg_main":0,
    "name:eng_x_preferred":[
        "Dakhin Borpothar"
    ],
    "wof:name":"Dakhin Borpothar",
    "wof:placetype":"neighbourhood",
    "wof:population":401
},
  "geometry": {"coordinates":[94.964393,27.198988],"type":"Point"}
}