{
  "type": "Feature",
  "properties": {
    "iso:country":"IN",
    "ks:ks_alt_nam":"NAWA TOLIYA",
    "ks:ks_name":"Nawa Toliya",
    "ks:ks_pop":2456,
    "ks:ks_type":"HABITATION",
    "name:eng_x_preferred":[
        "Nawa Toliya"
    ],
    "wof:name":"Nawa Toliya",
    "wof:placetype":"locality",
    "wof:population":2456
},
  "geometry": {"coordinates":[86.588694,25.494747],"type":"Point"}
}