{
  "type": "Feature",
  "properties": {
    "iso:country":"IN",
    "ks:ks_name":"Lanji",
    "ks:ks_pop":566,
    "ks:ks_type":"VILLAGE",
    "name:eng_x_preferred":[
        "Lanji"
    ],
    "wof:name":"Lanji",
    "wof:placetype":"locality",
    "wof:population":566
},
  "geometry": {"coordinates":[85.571504,22.812575],"type":"Point"}
}