{
  "type": "Feature",
  "properties": {
    "iso:country":"IN",
    "ks:ks_name":"Sagadipatana",
    "ks:ks_pop":759,
    "ks:ks_type":"VILLAGE",
    "ks:ks_uagg_main":0,
    "name:eng_x_preferred":[
        "Sagadipatana"
    ],
    "wof:name":"Sagadipatana",
    "wof:placetype":"neighbourhood",
    "wof:population":759
},
  "geometry": {"coordinates":[86.054194,20.429313],"type":"Point"}
}