{
  "type": "Feature",
  "properties": {
    "iso:country":"IN",
    "ks:ks_alt_nam":"GERUKATTE",
    "ks:ks_name":"Gerukatte",
    "ks:ks_pop":139,
    "ks:ks_type":"HABITATION",
    "name:eng_x_preferred":[
        "Gerukatte"
    ],
    "wof:name":"Gerukatte",
    "wof:placetype":"locality",
    "wof:population":139
},
  "geometry": {"coordinates":[75.230508,13.807321],"type":"Point"}
}