{
  "type": "Feature",
  "properties": {
    "gn:admin1_code":"39",
    "gn:admin2_code":"60.0",
    "gn:asciiname":"Kanarwala",
    "gn:country_code":"IN",
    "gn:dem":507,
    "gn:feature_class":"P",
    "gn:feature_code":"PPL",
    "gn:name":"K\u0101narw\u0101la",
    "gn:population":0,
    "gn:timezone":"Asia/Kolkata",
    "iso:country":"IN",
    "ks:ks_name":"Kanhar Wala",
    "ks:ks_pop":3739,
    "ks:ks_type":"VILLAGE",
    "ks:ks_uagg_main":0,
    "name:eng_x_preferred":[
        "Kanhar Wala"
    ],
    "wof:name":"Kanhar Wala",
    "wof:placetype":"neighbourhood",
    "wof:population":3739
},
  "geometry": {"coordinates":[78.151088,30.186445],"type":"Point"}
}