{
  "type": "Feature",
  "properties": {
    "iso:country":"IN",
    "ks:ks_name":"Mutia Khana Gaon",
    "ks:ks_pop":2245,
    "ks:ks_type":"HABITATION",
    "name:eng_x_preferred":[
        "Mutia Khana Gaon"
    ],
    "wof:name":"Mutia Khana Gaon",
    "wof:placetype":"locality",
    "wof:population":2245
},
  "geometry": {"coordinates":[95.30113299999999,27.448517],"type":"Point"}
}