{
  "type": "Feature",
  "properties": {
    "iso:country":"IN",
    "ks:ks_name":"Barai",
    "ks:ks_pop":0,
    "ks:ks_type":"VILLAGE",
    "name:eng_x_preferred":[
        "Barai"
    ],
    "wof:name":"Barai",
    "wof:placetype":"locality",
    "wof:population":0
},
  "geometry": {"coordinates":[76.994275,25.43328],"type":"Point"}
}