{
  "type": "Feature",
  "properties": {
    "iso:country":"IN",
    "ks:ks_name":"Jogulaputtu",
    "ks:ks_pop":116,
    "ks:ks_type":"VILLAGE",
    "name:eng_x_preferred":[
        "Jogulaputtu"
    ],
    "wof:name":"Jogulaputtu",
    "wof:placetype":"locality",
    "wof:population":116
},
  "geometry": {"coordinates":[82.539316,18.008722],"type":"Point"}
}