{
  "type": "Feature",
  "properties": {
    "gn:admin1_code":"11",
    "gn:admin2_code":"23.0",
    "gn:asciiname":"Angari",
    "gn:country_code":"IN",
    "gn:dem":2183,
    "gn:feature_class":"P",
    "gn:feature_code":"PPL",
    "gn:name":"Ang\u0101ri",
    "gn:population":0,
    "gn:timezone":"Asia/Kolkata",
    "iso:country":"IN",
    "wof:name":"Angari",
    "wof:placetype":"locality"
},
  "geometry": {"coordinates":[76.29448000000002,32.49672],"type":"Point"}
}