{
  "type": "Feature",
  "properties": {
    "iso:country":"IN",
    "ks:ks_alt_nam":"attoththazhe",
    "ks:ks_name":"Attoththazhe",
    "ks:ks_pop":245,
    "ks:ks_type":"HABITATION",
    "name:eng_x_preferred":[
        "Attoththazhe"
    ],
    "wof:name":"Attoththazhe",
    "wof:placetype":"locality",
    "wof:population":245
},
  "geometry": {"coordinates":[75.75877,11.603767],"type":"Point"}
}