{
  "type": "Feature",
  "properties": {
    "gn:admin1_code":"37",
    "gn:admin2_code":"411.0",
    "gn:asciiname":"Bonda",
    "gn:country_code":"IN",
    "gn:dem":253,
    "gn:feature_class":"P",
    "gn:feature_code":"PPL",
    "gn:name":"Bonda",
    "gn:population":0,
    "gn:timezone":"Asia/Kolkata",
    "iso:country":"IN",
    "name:ara_x_preferred":[
        "\u0628\u0648\u0646\u062f\u0627"
    ],
    "name:bul_x_preferred":[
        "\u0411\u043e\u043d\u0434\u0430"
    ],
    "name:fra_x_preferred":[
        "Bonda"
    ],
    "name:ita_x_preferred":[
        "Bonda"
    ],
    "name:kan_x_preferred":[
        "\u0cac\u0ccb\u0c82\u0ca1\u0cbe"
    ],
    "name:mal_x_preferred":[
        "\u0d2c\u0d4b\u0d23\u0d4d\u0d1f"
    ],
    "name:pan_x_preferred":[
        "\u0a2c\u0a4b\u0a02\u0a21\u0a3e"
    ],
    "name:spa_x_preferred":[
        "Bonda"
    ],
    "name:tam_x_preferred":[
        "\u0baa\u0bcb\u0ba3\u0bcd\u0b9f\u0bbe"
    ],
    "name:tel_x_preferred":[
        "\u0c2c\u0c4b\u0c02\u0c21\u0c3e"
    ],
    "wof:name":"Bonda",
    "wof:placetype":"locality"
},
  "geometry": {"coordinates":[83.0515,21.33811],"type":"Point"}
}