{
  "type": "Feature",
  "properties": {
    "iso:country":"IN",
    "ks:ks_name":"Yadav Basti",
    "ks:ks_pop":36,
    "ks:ks_type":"HABITATION",
    "ks:ks_uagg_main":0,
    "name:eng_x_preferred":[
        "Yadav Basti"
    ],
    "wof:name":"Yadav Basti",
    "wof:placetype":"neighbourhood",
    "wof:population":36
},
  "geometry": {"coordinates":[82.45703,26.167109],"type":"Point"}
}