{
  "type": "Feature",
  "properties": {
    "iso:country":"IN",
    "ks:ks_alt_nam":"GARASAI",
    "ks:ks_name":"Garasai",
    "ks:ks_pop":607,
    "ks:ks_type":"HABITATION",
    "name:eng_x_preferred":[
        "Garasai"
    ],
    "wof:name":"Garasai",
    "wof:placetype":"locality",
    "wof:population":607
},
  "geometry": {"coordinates":[85.86828,22.140922],"type":"Point"}
}