{
  "type": "Feature",
  "properties": {
    "iso:country":"IN",
    "ks:ks_name":"Noorpur",
    "ks:ks_pop":7,
    "ks:ks_type":"VILLAGE",
    "ks:ks_uagg_main":0,
    "name:eng_x_preferred":[
        "Noorpur"
    ],
    "wof:name":"Noorpur",
    "wof:placetype":"neighbourhood",
    "wof:population":7
},
  "geometry": {"coordinates":[82.95474400000001,26.24284],"type":"Point"}
}