{
  "type": "Feature",
  "properties": {
    "iso:country":"IN",
    "ks:ks_name":"Kalabati",
    "ks:ks_pop":488,
    "ks:ks_type":"VILLAGE",
    "name:eng_x_preferred":[
        "Kalabati"
    ],
    "wof:name":"Kalabati",
    "wof:placetype":"locality",
    "wof:population":488
},
  "geometry": {"coordinates":[87.07704099999999,22.869213],"type":"Point"}
}