{
  "type": "Feature",
  "properties": {
    "iso:country":"IN",
    "ks:ks_name":"Asharithode Jn",
    "ks:ks_pop":957,
    "ks:ks_type":"HABITATION",
    "name:eng_x_preferred":[
        "Asharithode Jn"
    ],
    "wof:name":"Asharithode Jn",
    "wof:placetype":"locality",
    "wof:population":957
},
  "geometry": {"coordinates":[76.041662,11.192974],"type":"Point"}
}