{
  "type": "Feature",
  "properties": {
    "iso:country":"IN",
    "ks:ks_name":"Kusturia",
    "ks:ks_pop":456,
    "ks:ks_type":"VILLAGE",
    "name:eng_x_preferred":[
        "Kusturia"
    ],
    "wof:name":"Kusturia",
    "wof:placetype":"locality",
    "wof:population":456
},
  "geometry": {"coordinates":[87.26253699999999,21.977469],"type":"Point"}
}