{
  "type": "Feature",
  "properties": {
    "gn:admin1_code":"11.0",
    "gn:admin2_code":"32.0",
    "gn:asciiname":"Khanagan",
    "gn:country_code":"IN",
    "gn:dem":1772,
    "gn:feature_class":"P",
    "gn:feature_code":"PPL",
    "gn:name":"Khan\u0101gan",
    "gn:population":0,
    "gn:timezone":"Asia/Kolkata",
    "iso:country":"IN",
    "wof:name":"Khanagan",
    "wof:placetype":"locality"
},
  "geometry": {"coordinates":[77.26384,30.72759000000001],"type":"Point"}
}