{
  "type": "Feature",
  "properties": {
    "gn:admin1_code":"36",
    "gn:admin2_code":"188.0",
    "gn:asciiname":"Surdahi",
    "gn:country_code":"IN",
    "gn:dem":82,
    "gn:feature_class":"P",
    "gn:feature_code":"PPL",
    "gn:name":"Surdahi",
    "gn:population":0,
    "gn:timezone":"Asia/Kolkata",
    "iso:country":"IN",
    "ks:ks_name":"Surdahi",
    "ks:ks_pop":537,
    "ks:ks_type":"VILLAGE",
    "ks:ks_uagg_main":0,
    "name:eng_x_preferred":[
        "Surdahi"
    ],
    "wof:name":"Surdahi",
    "wof:placetype":"neighbourhood",
    "wof:population":537
},
  "geometry": {"coordinates":[83.170378,26.787342],"type":"Point"}
}