{
  "type": "Feature",
  "properties": {
    "iso:country":"IN",
    "ks:ks_name":"Bheramuri",
    "ks:ks_pop":128,
    "ks:ks_type":"HABITATION",
    "name:eng_x_preferred":[
        "Bheramuri"
    ],
    "wof:name":"Bheramuri",
    "wof:placetype":"locality",
    "wof:population":128
},
  "geometry": {"coordinates":[87.620848,23.847082],"type":"Point"}
}