{
  "type": "Feature",
  "properties": {
    "iso:country":"IN",
    "ks:ks_alt_nam":"Sahari Pt-I",
    "ks:ks_name":"Sahari Pt-i",
    "ks:ks_pop":600,
    "ks:ks_type":"HABITATION",
    "name:eng_x_preferred":[
        "Sahari Pt-i"
    ],
    "wof:name":"Sahari Pt-i",
    "wof:placetype":"locality",
    "wof:population":600
},
  "geometry": {"coordinates":[90.502466,26.149939],"type":"Point"}
}