{
  "type": "Feature",
  "properties": {
    "gn:admin1_code":"40",
    "gn:admin2_code":"538.0",
    "gn:asciiname":"Kanakapur",
    "gn:country_code":"IN",
    "gn:dem":425,
    "gn:feature_class":"P",
    "gn:feature_code":"PPL",
    "gn:name":"Kanakapur",
    "gn:population":0,
    "gn:timezone":"Asia/Kolkata",
    "iso:country":"IN",
    "ks:ks_name":"Kanakapur",
    "ks:ks_type":"VILLAGE",
    "name:eng_x_preferred":[
        "Kanakapur"
    ],
    "wof:name":"Kanakapur",
    "wof:placetype":"locality"
},
  "geometry": {"coordinates":[77.960888,16.636535],"type":"Point"}
}