{
  "type": "Feature",
  "properties": {
    "iso:country":"IN",
    "ks:ks_name":"Periyathattan",
    "ks:ks_pop":106,
    "ks:ks_type":"HABITATION",
    "name:eng_x_preferred":[
        "Periyathattan"
    ],
    "wof:name":"Periyathattan",
    "wof:placetype":"locality",
    "wof:population":106
},
  "geometry": {"coordinates":[79.003338,12.779813],"type":"Point"}
}