{
  "type": "Feature",
  "properties": {
    "iso:country":"IN",
    "ks:ks_name":"Bhelwa Milik",
    "ks:ks_pop":0,
    "ks:ks_type":"VILLAGE",
    "name:eng_x_preferred":[
        "Bhelwa Milik"
    ],
    "wof:name":"Bhelwa Milik",
    "wof:placetype":"locality",
    "wof:population":0
},
  "geometry": {"coordinates":[87.201131,25.616051],"type":"Point"}
}