{
  "type": "Feature",
  "properties": {
    "iso:country":"IN",
    "ks:ks_name":"Niz-Geruajhar",
    "ks:ks_pop":602,
    "ks:ks_type":"VILLAGE",
    "ks:ks_uagg_main":0,
    "name:eng_x_preferred":[
        "Niz-Geruajhar"
    ],
    "wof:name":"Niz-Geruajhar",
    "wof:placetype":"neighbourhood",
    "wof:population":602
},
  "geometry": {"coordinates":[91.87032499999999,26.812066],"type":"Point"}
}