{
  "type": "Feature",
  "properties": {
    "gn:admin1_code":"24.0",
    "gn:admin2_code":"121",
    "gn:asciiname":"Raghunathpura",
    "gn:country_code":"IN",
    "gn:dem":289,
    "gn:feature_class":"P",
    "gn:feature_code":"PPL",
    "gn:name":"Raghun\u0101thpura",
    "gn:population":0,
    "gn:timezone":"Asia/Kolkata",
    "iso:country":"IN",
    "ks:ks_name":"Rughnathpura",
    "ks:ks_pop":1023,
    "ks:ks_type":"HABITATION",
    "name:eng_x_preferred":[
        "Rughnathpura"
    ],
    "name:eng_x_variant":[
        "Raghunathpura"
    ],
    "name:hin_x_preferred":[
        "\u0930\u0918\u0941\u0928\u093e\u0925\u092a\u0941\u0930\u093e"
    ],
    "name:pan_x_preferred":[
        "\u0a30\u0a18\u0a41\u0a28\u0a3e\u0a25\u0a2a\u0a41\u0a30\u0a3e"
    ],
    "name:und_x_variant":[
        "Raghun\u0101thpura",
        "Raghun\u0101ihpura"
    ],
    "wof:name":"Rughnathpura",
    "wof:placetype":"locality",
    "wof:population":1023
},
  "geometry": {"coordinates":[75.548288,25.515514],"type":"Point"}
}