{
  "type": "Feature",
  "properties": {
    "gn:admin1_code":"24.0",
    "gn:admin2_code":"121",
    "gn:asciiname":"Raghunathpura",
    "gn:country_code":"IN",
    "gn:dem":289,
    "gn:feature_class":"P",
    "gn:feature_code":"PPL",
    "gn:name":"Raghun\u0101thpura",
    "gn:population":0,
    "gn:timezone":"Asia/Kolkata",
    "iso:country":"IN",
    "name:und_x_variant":[
        "Raghun\u0101thpura",
        "Raghun\u0101ihpura"
    ],
    "wof:name":"Raghunathpura",
    "wof:placetype":"locality"
},
  "geometry": {"coordinates":[75.54600000000001,25.51632],"type":"Point"}
}