{
  "type": "Feature",
  "properties": {
    "iso:country":"IN",
    "ks:ks_name":"Akatahawa",
    "ks:ks_pop":624,
    "ks:ks_type":"HABITATION",
    "ks:ks_uagg_main":0,
    "name:eng_x_preferred":[
        "Akatahawa"
    ],
    "wof:name":"Akatahawa",
    "wof:placetype":"neighbourhood",
    "wof:population":624
},
  "geometry": {"coordinates":[83.834526,26.918198],"type":"Point"}
}