{
  "type": "Feature",
  "properties": {
    "iso:country":"IN",
    "ks:ks_name":"Heth Chakwa",
    "ks:ks_pop":169,
    "ks:ks_type":"VILLAGE",
    "ks:ks_uagg_main":0,
    "name:eng_x_preferred":[
        "Heth Chakwa"
    ],
    "wof:name":"Heth Chakwa",
    "wof:placetype":"neighbourhood",
    "wof:population":169
},
  "geometry": {"coordinates":[87.028772,24.501708],"type":"Point"}
}