{
  "type": "Feature",
  "properties": {
    "gn:admin1_code":"34.0",
    "gn:admin2_code":"238.0",
    "gn:asciiname":"Musehritola",
    "gn:country_code":"IN",
    "gn:dem":72,
    "gn:feature_class":"P",
    "gn:feature_code":"PPL",
    "gn:name":"Musehr\u012btola",
    "gn:population":0,
    "gn:timezone":"Asia/Kolkata",
    "iso:country":"IN",
    "wof:name":"Musehritola",
    "wof:placetype":"locality"
},
  "geometry": {"coordinates":[86.16454,25.00809],"type":"Point"}
}