{
  "type": "Feature",
  "properties": {
    "iso:country":"IN",
    "ks:ks_name":"Kanera",
    "ks:ks_pop":143,
    "ks:ks_type":"VILLAGE",
    "name:eng_x_preferred":[
        "Kanera"
    ],
    "wof:name":"Kanera",
    "wof:placetype":"locality",
    "wof:population":143
},
  "geometry": {"coordinates":[77.092743,24.645048],"type":"Point"}
}