{
  "type": "Feature",
  "properties": {
    "gn:admin1_code":"24.0",
    "gn:admin2_code":"122.0",
    "gn:asciiname":"Ora",
    "gn:country_code":"IN",
    "gn:dem":561,
    "gn:feature_class":"P",
    "gn:feature_code":"PPL",
    "gn:name":"Ora",
    "gn:population":0,
    "gn:timezone":"Asia/Kolkata",
    "iso:country":"IN",
    "name:ceb_x_preferred":[
        "Ora"
    ],
    "name:ces_x_preferred":[
        "Ora"
    ],
    "name:deu_x_preferred":[
        "Ora"
    ],
    "name:fin_x_preferred":[
        "Ora"
    ],
    "name:fra_x_preferred":[
        "Ora"
    ],
    "name:heb_x_preferred":[
        "\u05d0\u05d5\u05e8\u05d4"
    ],
    "name:hun_x_preferred":[
        "Ora"
    ],
    "name:hye_x_preferred":[
        "\u0555\u0580\u0561"
    ],
    "name:nld_x_preferred":[
        "Ora"
    ],
    "name:nor_x_preferred":[
        "Ora"
    ],
    "name:pol_x_preferred":[
        "Ora"
    ],
    "name:ron_x_preferred":[
        "Ora"
    ],
    "name:rus_x_preferred":[
        "\u041e\u0440\u0430"
    ],
    "name:swe_x_preferred":[
        "Ora"
    ],
    "name:ukr_x_preferred":[
        "\u041e\u0440\u0430"
    ],
    "wof:name":"Ora",
    "wof:placetype":"locality"
},
  "geometry": {"coordinates":[74.08629999999999,25.45245],"type":"Point"}
}