{
  "type": "Feature",
  "properties": {
    "iso:country":"IN",
    "ks:ks_name":"Sakhari",
    "ks:ks_pop":34,
    "ks:ks_type":"VILLAGE",
    "name:eng_x_preferred":[
        "Sakhari"
    ],
    "wof:name":"Sakhari",
    "wof:placetype":"locality",
    "wof:population":34
},
  "geometry": {"coordinates":[73.490802,18.370273],"type":"Point"}
}