{
  "type": "Feature",
  "properties": {
    "gn:admin1_code":"19.0",
    "gn:admin2_code":"578.0",
    "gn:asciiname":"Triambakpur",
    "gn:country_code":"IN",
    "gn:dem":839,
    "gn:feature_class":"P",
    "gn:feature_code":"PPL",
    "gn:name":"Triambakp\u016br",
    "gn:population":0,
    "gn:timezone":"Asia/Kolkata",
    "iso:country":"IN",
    "wof:name":"Triambakpur",
    "wof:placetype":"locality"
},
  "geometry": {"coordinates":[76.76475000000001,11.80191],"type":"Point"}
}