{
  "type": "Feature",
  "properties": {
    "iso:country":"IN",
    "ks:ks_name":"No-5",
    "ks:ks_pop":266,
    "ks:ks_type":"HABITATION",
    "ks:ks_uagg_main":0,
    "name:eng_x_preferred":[
        "No-5"
    ],
    "wof:name":"No-5",
    "wof:placetype":"neighbourhood",
    "wof:population":266
},
  "geometry": {"coordinates":[80.330974,28.245832],"type":"Point"}
}