{
  "type": "Feature",
  "properties": {
    "iso:country":"IN",
    "ks:ks_name":"Bandebommasandra",
    "ks:ks_pop":829,
    "ks:ks_type":"VILLAGE",
    "name:eng_x_preferred":[
        "Bandebommasandra"
    ],
    "wof:name":"Bandebommasandra",
    "wof:placetype":"locality",
    "wof:population":829
},
  "geometry": {"coordinates":[77.67918,13.075884],"type":"Point"}
}