{
  "type": "Feature",
  "properties": {
    "iso:country":"IN",
    "ks:ks_name":"Katinkel",
    "ks:ks_pop":721,
    "ks:ks_type":"VILLAGE",
    "name:eng_x_preferred":[
        "Katinkel"
    ],
    "wof:name":"Katinkel",
    "wof:placetype":"locality",
    "wof:population":721
},
  "geometry": {"coordinates":[85.23318,22.62704],"type":"Point"}
}