{
  "type": "Feature",
  "properties": {
    "iso:country":"IN",
    "ks:ks_alt_nam":"Karapuram jn",
    "ks:ks_name":"Karapuram Jn",
    "ks:ks_pop":338,
    "ks:ks_type":"HABITATION",
    "ks:ks_uagg_main":0,
    "name:eng_x_preferred":[
        "Karapuram Jn"
    ],
    "wof:name":"Karapuram Jn",
    "wof:placetype":"neighbourhood",
    "wof:population":338
},
  "geometry": {"coordinates":[76.330054,11.325476],"type":"Point"}
}