{
  "type": "Feature",
  "properties": {
    "iso:country":"IN",
    "ks:ks_alt_nam":"Vadvali mu",
    "ks:ks_name":"Vadvali Mu",
    "ks:ks_pop":875,
    "ks:ks_type":"HABITATION",
    "name:eng_x_preferred":[
        "Vadvali Mu"
    ],
    "wof:name":"Vadvali Mu",
    "wof:placetype":"locality",
    "wof:population":875
},
  "geometry": {"coordinates":[73.02158300000001,22.739083],"type":"Point"}
}