{
  "type": "Feature",
  "properties": {
    "iso:country":"IN",
    "ks:ks_name":"Wadanbagh Thanda",
    "ks:ks_pop":126,
    "ks:ks_type":"HABITATION",
    "name:eng_x_preferred":[
        "Wadanbagh Thanda"
    ],
    "wof:name":"Wadanbagh Thanda",
    "wof:placetype":"locality",
    "wof:population":126
},
  "geometry": {"coordinates":[77.53737,18.103347],"type":"Point"}
}