{
  "type": "Feature",
  "properties": {
    "gn:admin1_code":"35.0",
    "gn:admin2_code":"465.0",
    "gn:asciiname":"Mandar",
    "gn:country_code":"IN",
    "gn:dem":345,
    "gn:feature_class":"P",
    "gn:feature_code":"PPL",
    "gn:name":"Mand\u00e1r",
    "gn:population":0,
    "gn:timezone":"Asia/Kolkata",
    "iso:country":"IN",
    "ks:ks_name":"Mandhar",
    "ks:ks_pop":711,
    "ks:ks_type":"VILLAGE",
    "name:ceb_x_preferred":[
        "Mandar"
    ],
    "name:deu_x_preferred":[
        "Mandar"
    ],
    "name:eng_x_preferred":[
        "Mandhar"
    ],
    "name:eng_x_variant":[
        "Mandar"
    ],
    "name:fra_x_preferred":[
        "Mandar"
    ],
    "name:ind_x_preferred":[
        "Mandar"
    ],
    "wof:name":"Mandhar",
    "wof:placetype":"locality",
    "wof:population":711
},
  "geometry": {"coordinates":[74.254582,22.459854],"type":"Point"}
}