{
  "type": "Feature",
  "properties": {
    "gn:admin1_code":"35.0",
    "gn:admin2_code":"465.0",
    "gn:asciiname":"Mandar",
    "gn:country_code":"IN",
    "gn:dem":345,
    "gn:feature_class":"P",
    "gn:feature_code":"PPL",
    "gn:name":"Mand\u00e1r",
    "gn:population":0,
    "gn:timezone":"Asia/Kolkata",
    "iso:country":"IN",
    "name:ceb_x_preferred":[
        "Mandar"
    ],
    "name:deu_x_preferred":[
        "Mandar"
    ],
    "name:fra_x_preferred":[
        "Mandar"
    ],
    "name:ind_x_preferred":[
        "Mandar"
    ],
    "wof:name":"Mandar",
    "wof:placetype":"locality"
},
  "geometry": {"coordinates":[74.2514,22.47163],"type":"Point"}
}