{
  "type": "Feature",
  "properties": {
    "gn:admin1_code":"13.0",
    "gn:admin2_code":"588.0",
    "gn:asciiname":"Motlankote",
    "gn:country_code":"IN",
    "gn:dem":105,
    "gn:feature_class":"P",
    "gn:feature_code":"PPL",
    "gn:name":"Motlankote",
    "gn:population":0,
    "gn:timezone":"Asia/Kolkata",
    "iso:country":"IN",
    "wof:name":"Motlankote",
    "wof:placetype":"locality"
},
  "geometry": {"coordinates":[75.10889,12.45478],"type":"Point"}
}