{
  "type": "Feature",
  "properties": {
    "gn:admin1_code":"16.0",
    "gn:admin2_code":"503",
    "gn:asciiname":"Adula",
    "gn:country_code":"IN",
    "gn:dem":279,
    "gn:feature_class":"P",
    "gn:feature_code":"PPL",
    "gn:name":"Adula",
    "gn:population":0,
    "gn:timezone":"Asia/Kolkata",
    "iso:country":"IN",
    "name:und_x_variant":[
        "Adul"
    ],
    "wof:name":"Adula",
    "wof:placetype":"locality"
},
  "geometry": {"coordinates":[77.21035000000001,20.94018],"type":"Point"}
}