{
  "type": "Feature",
  "properties": {
    "iso:country":"IN",
    "ks:ks_alt_nam":"DAGADU PATIL WASTI",
    "ks:ks_name":"Dagadu Patil Wasti",
    "ks:ks_pop":106,
    "ks:ks_type":"HABITATION",
    "name:eng_x_preferred":[
        "Dagadu Patil Wasti"
    ],
    "wof:name":"Dagadu Patil Wasti",
    "wof:placetype":"locality",
    "wof:population":106
},
  "geometry": {"coordinates":[74.941632,17.309138],"type":"Point"}
}