{
  "type": "Feature",
  "properties": {
    "iso:country":"IN",
    "ks:ks_name":"Asarkho",
    "ks:ks_pop":258,
    "ks:ks_type":"VILLAGE",
    "name:eng_x_preferred":[
        "Asarkho"
    ],
    "wof:name":"Asarkho",
    "wof:placetype":"locality",
    "wof:population":258
},
  "geometry": {"coordinates":[86.176114,24.654007],"type":"Point"}
}