{
  "type": "Feature",
  "properties": {
    "iso:country":"IN",
    "ks:ks_name":"Ummanagaruvu",
    "ks:ks_pop":512,
    "ks:ks_type":"HABITATION",
    "name:eng_x_preferred":[
        "Ummanagaruvu"
    ],
    "wof:name":"Ummanagaruvu",
    "wof:placetype":"locality",
    "wof:population":512
},
  "geometry": {"coordinates":[81.92715,16.624993],"type":"Point"}
}