{
  "type": "Feature",
  "properties": {
    "iso:country":"IN",
    "ks:ks_name":"Janapara",
    "ks:ks_pop":512,
    "ks:ks_type":"HABITATION",
    "ks:ks_uagg_main":0,
    "name:eng_x_preferred":[
        "Janapara"
    ],
    "wof:name":"Janapara",
    "wof:placetype":"locality",
    "wof:population":512
},
  "geometry": {"coordinates":[88.130899,22.595321],"type":"Point"}
}