{
  "type": "Feature",
  "properties": {
    "gn:admin1_code":"25.0",
    "gn:admin2_code":"604.0",
    "gn:asciiname":"Nesappakkam",
    "gn:country_code":"IN",
    "gn:dem":23,
    "gn:feature_class":"P",
    "gn:feature_code":"PPL",
    "gn:name":"Nesapp\u0101kkam",
    "gn:population":0,
    "gn:timezone":"Asia/Kolkata",
    "iso:country":"IN",
    "ks:ks_name":"Nesapakkam",
    "ks:ks_pop":680,
    "ks:ks_type":"VILLAGE",
    "name:eng_x_preferred":[
        "Nesapakkam"
    ],
    "name:eng_x_variant":[
        "Nesappakkam"
    ],
    "wof:name":"Nesapakkam",
    "wof:placetype":"locality",
    "wof:population":680
},
  "geometry": {"coordinates":[79.984645,12.432518],"type":"Point"}
}