{
  "type": "Feature",
  "properties": {
    "iso:country":"IN",
    "ks:ks_alt_nam":"Dhai ki char",
    "ks:ks_name":"Dhai Ki Char",
    "ks:ks_pop":48,
    "ks:ks_type":"HABITATION",
    "name:eng_x_preferred":[
        "Dhai Ki Char"
    ],
    "wof:name":"Dhai Ki Char",
    "wof:placetype":"locality",
    "wof:population":48
},
  "geometry": {"coordinates":[79.199693,29.775042],"type":"Point"}
}