{
  "type": "Feature",
  "properties": {
    "iso:country":"IN",
    "ks:ks_name":"Gotimatipara",
    "ks:ks_pop":86,
    "ks:ks_type":"HABITATION",
    "name:eng_x_preferred":[
        "Gotimatipara"
    ],
    "wof:name":"Gotimatipara",
    "wof:placetype":"locality",
    "wof:population":86
},
  "geometry": {"coordinates":[81.87161,19.043582],"type":"Point"}
}