{
  "type": "Feature",
  "properties": {
    "iso:country":"IN",
    "ks:ks_name":"Hagrudihi",
    "ks:ks_type":"VILLAGE",
    "name:eng_x_preferred":[
        "Hagrudihi"
    ],
    "wof:name":"Hagrudihi",
    "wof:placetype":"locality"
},
  "geometry": {"coordinates":[84.40044,21.730561],"type":"Point"}
}