{
  "type": "Feature",
  "properties": {
    "iso:country":"IN",
    "ks:ks_name":"Ghodazar",
    "ks:ks_pop":1731,
    "ks:ks_type":"HABITATION",
    "name:eng_x_preferred":[
        "Ghodazar"
    ],
    "wof:name":"Ghodazar",
    "wof:placetype":"locality",
    "wof:population":1731
},
  "geometry": {"coordinates":[74.055278,22.746917],"type":"Point"}
}