{
  "type": "Feature",
  "properties": {
    "iso:country":"IN",
    "ks:ks_name":"Mujjale",
    "ks:ks_pop":100,
    "ks:ks_type":"HABITATION",
    "name:eng_x_preferred":[
        "Mujjale"
    ],
    "wof:name":"Mujjale",
    "wof:placetype":"locality",
    "wof:population":100
},
  "geometry": {"coordinates":[75.218349,12.852415],"type":"Point"}
}