{
  "type": "Feature",
  "properties": {
    "gn:admin1_code":"21.0",
    "gn:admin2_code":"393",
    "gn:asciiname":"Dangbal",
    "gn:country_code":"IN",
    "gn:dem":235,
    "gn:feature_class":"P",
    "gn:feature_code":"PPL",
    "gn:name":"Dangbal",
    "gn:population":0,
    "gn:timezone":"Asia/Kolkata",
    "iso:country":"IN",
    "wof:name":"Dangbal",
    "wof:placetype":"locality"
},
  "geometry": {"coordinates":[83.21666999999999,20.86667000000001],"type":"Point"}
}