{
  "type": "Feature",
  "properties": {
    "gn:admin1_code":"21",
    "gn:admin2_code":"395.0",
    "gn:asciiname":"Maskuti",
    "gn:country_code":"IN",
    "gn:dem":509,
    "gn:feature_class":"P",
    "gn:feature_code":"PPL",
    "gn:name":"Maskuti",
    "gn:population":0,
    "gn:timezone":"Asia/Kolkata",
    "iso:country":"IN",
    "ks:ks_name":"Muskuti",
    "ks:ks_pop":78,
    "ks:ks_type":"VILLAGE",
    "name:eng_x_preferred":[
        "Muskuti"
    ],
    "name:eng_x_variant":[
        "Maskuti"
    ],
    "wof:name":"Muskuti",
    "wof:placetype":"locality",
    "wof:population":78
},
  "geometry": {"coordinates":[83.320182,19.829498],"type":"Point"}
}