{
  "type": "Feature",
  "properties": {
    "gn:admin1_code":"11",
    "gn:admin2_code":"23.0",
    "gn:asciiname":"Gwalnu",
    "gn:country_code":"IN",
    "gn:dem":1981,
    "gn:feature_class":"P",
    "gn:feature_code":"PPL",
    "gn:name":"Gw\u0101lnu",
    "gn:population":0,
    "gn:timezone":"Asia/Kolkata",
    "iso:country":"IN",
    "wof:name":"Gwalnu",
    "wof:placetype":"locality"
},
  "geometry": {"coordinates":[76.09298000000003,32.46084],"type":"Point"}
}