{
  "type": "Feature",
  "properties": {
    "iso:country":"IN",
    "ks:ks_name":"Sc Bc Colony",
    "ks:ks_pop":607,
    "ks:ks_type":"HABITATION",
    "ks:ks_uagg_main":0,
    "name:eng_x_preferred":[
        "Sc Bc Colony"
    ],
    "wof:name":"Sc Bc Colony",
    "wof:placetype":"neighbourhood",
    "wof:population":607
},
  "geometry": {"coordinates":[80.11905,17.2061],"type":"Point"}
}