{
  "type": "Feature",
  "properties": {
    "gn:admin1_code":"11",
    "gn:admin2_code":"23.0",
    "gn:asciiname":"That",
    "gn:country_code":"IN",
    "gn:dem":1433,
    "gn:feature_class":"P",
    "gn:feature_code":"PPL",
    "gn:name":"That",
    "gn:population":0,
    "gn:timezone":"Asia/Kolkata",
    "iso:country":"IN",
    "wof:name":"That",
    "wof:placetype":"locality"
},
  "geometry": {"coordinates":[76.12878000000001,32.58642],"type":"Point"}
}