{
  "type": "Feature",
  "properties": {
    "gn:admin1_code":"35",
    "gn:admin2_code":"427.0",
    "gn:asciiname":"Karrai",
    "gn:country_code":"IN",
    "gn:dem":389,
    "gn:feature_class":"P",
    "gn:feature_code":"PPL",
    "gn:name":"Karrai",
    "gn:population":0,
    "gn:timezone":"Asia/Kolkata",
    "iso:country":"IN",
    "wof:name":"Karrai",
    "wof:placetype":"locality"
},
  "geometry": {"coordinates":[78.91741999999998,24.2647],"type":"Point"}
}