{
  "type": "Feature",
  "properties": {
    "iso:country":"IN",
    "ks:ks_name":"Dhakuri",
    "ks:ks_pop":207,
    "ks:ks_type":"HABITATION",
    "name:eng_x_preferred":[
        "Dhakuri"
    ],
    "wof:name":"Dhakuri",
    "wof:placetype":"locality",
    "wof:population":207
},
  "geometry": {"coordinates":[78.274154,25.32903],"type":"Point"}
}