{
  "type": "Feature",
  "properties": {
    "iso:country":"IN",
    "ks:ks_name":"Hudasimulpur",
    "ks:ks_pop":1004,
    "ks:ks_type":"VILLAGE",
    "ks:ks_uagg_main":0,
    "name:eng_x_preferred":[
        "Hudasimulpur"
    ],
    "wof:name":"Hudasimulpur",
    "wof:placetype":"neighbourhood",
    "wof:population":1004
},
  "geometry": {"coordinates":[88.763034,22.939496],"type":"Point"}
}