{
  "type": "Feature",
  "properties": {
    "iso:country":"IN",
    "ks:ks_name":"Chinnabylu Pacharlavandlapalle",
    "ks:ks_pop":53,
    "ks:ks_type":"HABITATION",
    "name:eng_x_preferred":[
        "Chinnabylu Pacharlavandlapalle"
    ],
    "wof:name":"Chinnabylu Pacharlavandlapalle",
    "wof:placetype":"locality",
    "wof:population":53
},
  "geometry": {"coordinates":[79.188256,13.731152],"type":"Point"}
}