{
  "type": "Feature",
  "properties": {
    "iso:country":"IN",
    "ks:ks_name":"Areni Goojar",
    "ks:ks_pop":1050,
    "ks:ks_type":"HABITATION",
    "name:eng_x_preferred":[
        "Areni Goojar"
    ],
    "wof:name":"Areni Goojar",
    "wof:placetype":"locality",
    "wof:population":1050
},
  "geometry": {"coordinates":[77.165953,26.664489],"type":"Point"}
}