{
  "type": "Feature",
  "properties": {
    "iso:country":"IN",
    "ks:ks_alt_nam":"HAATSAI",
    "ks:ks_name":"Haatsai",
    "ks:ks_pop":318,
    "ks:ks_type":"HABITATION",
    "name:eng_x_preferred":[
        "Haatsai"
    ],
    "wof:name":"Haatsai",
    "wof:placetype":"locality",
    "wof:population":318
},
  "geometry": {"coordinates":[85.77813399999999,22.111128],"type":"Point"}
}