{
  "type": "Feature",
  "properties": {
    "gn:admin1_code":"11",
    "gn:admin2_code":"27.0",
    "gn:asciiname":"Cheli",
    "gn:country_code":"IN",
    "gn:dem":1198,
    "gn:feature_class":"P",
    "gn:feature_code":"PPL",
    "gn:name":"Cheli",
    "gn:population":0,
    "gn:timezone":"Asia/Kolkata",
    "iso:country":"IN",
    "name:ast_x_preferred":[
        "Cheli"
    ],
    "name:fra_x_preferred":[
        "Cheli"
    ],
    "name:spa_x_preferred":[
        "Cheli"
    ],
    "wof:name":"Cheli",
    "wof:placetype":"locality"
},
  "geometry": {"coordinates":[76.91119,31.85846],"type":"Point"}
}