{
  "type": "Feature",
  "properties": {
    "gn:admin1_code":"34.0",
    "gn:admin2_code":"207.0",
    "gn:asciiname":"Rada",
    "gn:country_code":"IN",
    "gn:dem":62,
    "gn:feature_class":"P",
    "gn:feature_code":"PPL",
    "gn:name":"Rada",
    "gn:population":0,
    "gn:timezone":"Asia/Kolkata",
    "iso:country":"IN",
    "name:fin_x_preferred":[
        "Rada"
    ],
    "name:ita_x_preferred":[
        "Rada"
    ],
    "name:jpn_x_preferred":[
        "\u30e9\u30fc\u30c0"
    ],
    "name:pol_x_preferred":[
        "Rada"
    ],
    "name:rus_x_preferred":[
        "\u0420\u0430\u0434\u0430"
    ],
    "name:ukr_x_preferred":[
        "\u0420\u0430\u0434\u0430"
    ],
    "wof:name":"Rada",
    "wof:placetype":"neighbourhood"
},
  "geometry": {"coordinates":[86.01817,26.37039],"type":"Point"}
}