{
  "type": "Feature",
  "properties": {
    "gn:admin1_code":"25.0",
    "gn:admin2_code":"606.0",
    "gn:asciiname":"Odamangalam",
    "gn:country_code":"IN",
    "gn:dem":772,
    "gn:feature_class":"P",
    "gn:feature_code":"PPL",
    "gn:name":"Odamangalam",
    "gn:population":0,
    "gn:timezone":"Asia/Kolkata",
    "iso:country":"IN",
    "ks:ks_name":"Odamangalam",
    "ks:ks_type":"VILLAGE",
    "name:eng_x_preferred":[
        "Odamangalam"
    ],
    "wof:name":"Odamangalam",
    "wof:placetype":"locality"
},
  "geometry": {"coordinates":[78.940254,12.607311],"type":"Point"}
}