{
  "type": "Feature",
  "properties": {
    "iso:country":"IN",
    "ks:ks_name":"Despada",
    "ks:ks_pop":50,
    "ks:ks_type":"HABITATION",
    "name:eng_x_preferred":[
        "Despada"
    ],
    "wof:name":"Despada",
    "wof:placetype":"locality",
    "wof:population":50
},
  "geometry": {"coordinates":[73.010107,20.05436],"type":"Point"}
}