{
  "type": "Feature",
  "properties": {
    "iso:country":"IN",
    "ks:ks_name":"Machale Wasti",
    "ks:ks_pop":238,
    "ks:ks_type":"HABITATION",
    "name:eng_x_preferred":[
        "Machale Wasti"
    ],
    "wof:name":"Machale Wasti",
    "wof:placetype":"locality",
    "wof:population":238
},
  "geometry": {"coordinates":[74.34690000000001,18.3586],"type":"Point"}
}