{
  "type": "Feature",
  "properties": {
    "gn:admin1_code":"35",
    "gn:admin2_code":"423.0",
    "gn:asciiname":"Marewa",
    "gn:country_code":"IN",
    "gn:dem":361,
    "gn:feature_class":"P",
    "gn:feature_code":"PPL",
    "gn:name":"Marewa",
    "gn:population":0,
    "gn:timezone":"Asia/Kolkata",
    "iso:country":"IN",
    "ks:ks_name":"Marewa",
    "ks:ks_type":"VILLAGE",
    "name:eng_x_preferred":[
        "Marewa"
    ],
    "wof:name":"Marewa",
    "wof:placetype":"locality"
},
  "geometry": {"coordinates":[77.683978,25.606305],"type":"Point"}
}