{
  "type": "Feature",
  "properties": {
    "iso:country":"IN",
    "ks:ks_alt_nam":"DEWKI TOLA",
    "ks:ks_name":"Dewki Tola",
    "ks:ks_pop":93,
    "ks:ks_type":"HABITATION",
    "name:eng_x_preferred":[
        "Dewki Tola"
    ],
    "wof:name":"Dewki Tola",
    "wof:placetype":"locality",
    "wof:population":93
},
  "geometry": {"coordinates":[86.603055,26.235914],"type":"Point"}
}