{
  "type": "Feature",
  "properties": {
    "iso:country":"IN",
    "ks:ks_name":"Nasemane",
    "ks:ks_pop":82,
    "ks:ks_type":"HABITATION",
    "name:eng_x_preferred":[
        "Nasemane"
    ],
    "wof:name":"Nasemane",
    "wof:placetype":"locality",
    "wof:population":82
},
  "geometry": {"coordinates":[75.458899,13.561721],"type":"Point"}
}