{
  "type": "Feature",
  "properties": {
    "gn:admin1_code":"21.0",
    "gn:admin2_code":"372.0",
    "gn:asciiname":"Bansimal",
    "gn:country_code":"IN",
    "gn:dem":283,
    "gn:feature_class":"P",
    "gn:feature_code":"PPL",
    "gn:name":"Bansimal",
    "gn:population":0,
    "gn:timezone":"Asia/Kolkata",
    "iso:country":"IN",
    "wof:name":"Bansimal",
    "wof:placetype":"locality"
},
  "geometry": {"coordinates":[83.98368000000001,21.69874],"type":"Point"}
}