{
  "type": "Feature",
  "properties": {
    "iso:country":"IN",
    "ks:ks_name":"Malam",
    "ks:ks_pop":1637,
    "ks:ks_type":"VILLAGE",
    "ks:ks_uagg_main":0,
    "name:eng_x_preferred":[
        "Malam"
    ],
    "wof:name":"Malam",
    "wof:placetype":"neighbourhood",
    "wof:population":1637
},
  "geometry": {"coordinates":[88.381935,25.385721],"type":"Point"}
}