{
  "type": "Feature",
  "properties": {
    "iso:country":"IN",
    "ks:ks_name":"Nailaha Bari",
    "ks:ks_pop":465,
    "ks:ks_type":"HABITATION",
    "name:eng_x_preferred":[
        "Nailaha Bari"
    ],
    "wof:name":"Nailaha Bari",
    "wof:placetype":"locality",
    "wof:population":465
},
  "geometry": {"coordinates":[91.832469,23.912218],"type":"Point"}
}