{
  "type": "Feature",
  "properties": {
    "iso:country":"IN",
    "ks:ks_name":"Chenpuriya",
    "ks:ks_pop":226,
    "ks:ks_type":"HABITATION",
    "name:eng_x_preferred":[
        "Chenpuriya"
    ],
    "wof:name":"Chenpuriya",
    "wof:placetype":"locality",
    "wof:population":226
},
  "geometry": {"coordinates":[75.74118300000001,24.537565],"type":"Point"}
}