{
  "type": "Feature",
  "properties": {
    "iso:country":"IN",
    "ks:ks_alt_nam":"Bin toli",
    "ks:ks_name":"Bin Toli",
    "ks:ks_pop":241,
    "ks:ks_type":"HABITATION",
    "name:eng_x_preferred":[
        "Bin Toli"
    ],
    "wof:name":"Bin Toli",
    "wof:placetype":"locality",
    "wof:population":241
},
  "geometry": {"coordinates":[84.42445600000001,27.159492],"type":"Point"}
}