{
  "type": "Feature",
  "properties": {
    "gn:admin1_code":"35.0",
    "gn:admin2_code":"455.0",
    "gn:asciiname":"Champakhera",
    "gn:country_code":"IN",
    "gn:dem":820,
    "gn:feature_class":"P",
    "gn:feature_code":"PPL",
    "gn:name":"Champ\u0101khera",
    "gn:population":0,
    "gn:timezone":"Asia/Kolkata",
    "iso:country":"IN",
    "ks:ks_name":"Champakheda",
    "ks:ks_pop":533,
    "ks:ks_type":"HABITATION",
    "name:eng_x_preferred":[
        "Champakheda"
    ],
    "name:eng_x_variant":[
        "Champakhera"
    ],
    "wof:name":"Champakheda",
    "wof:placetype":"locality",
    "wof:population":533
},
  "geometry": {"coordinates":[78.95572,22.502422],"type":"Point"}
}