{
  "type": "Feature",
  "properties": {
    "gn:admin1_code":"35.0",
    "gn:admin2_code":"455.0",
    "gn:asciiname":"Champakhera",
    "gn:country_code":"IN",
    "gn:dem":820,
    "gn:feature_class":"P",
    "gn:feature_code":"PPL",
    "gn:name":"Champ\u0101khera",
    "gn:population":0,
    "gn:timezone":"Asia/Kolkata",
    "iso:country":"IN",
    "wof:name":"Champakhera",
    "wof:placetype":"locality"
},
  "geometry": {"coordinates":[78.95584000000002,22.50279],"type":"Point"}
}