{
  "type": "Feature",
  "properties": {
    "gn:admin1_code":"33.0",
    "gn:admin2_code":"586.0",
    "gn:asciiname":"Velovado",
    "gn:country_code":"IN",
    "gn:dem":21,
    "gn:feature_class":"P",
    "gn:feature_code":"PPL",
    "gn:name":"Velovado",
    "gn:population":0,
    "gn:timezone":"Asia/Kolkata",
    "iso:country":"IN",
    "wof:name":"Velovado",
    "wof:placetype":"locality"
},
  "geometry": {"coordinates":[74.08494,14.97051],"type":"Point"}
}