{
  "type": "Feature",
  "properties": {
    "iso:country":"IN",
    "ks:ks_name":"Mamor Ahatmal",
    "ks:ks_pop":241,
    "ks:ks_type":"HABITATION",
    "name:eng_x_preferred":[
        "Mamor Ahatmal"
    ],
    "wof:name":"Mamor Ahatmal",
    "wof:placetype":"locality",
    "wof:population":241
},
  "geometry": {"coordinates":[77.151663,29.354217],"type":"Point"}
}