{
  "type": "Feature",
  "properties": {
    "iso:country":"IN",
    "ks:ks_alt_nam":"SHEKYA THANDA",
    "ks:ks_name":"Shekya Thanda",
    "ks:ks_pop":110,
    "ks:ks_type":"HABITATION",
    "name:eng_x_preferred":[
        "Shekya Thanda"
    ],
    "wof:name":"Shekya Thanda",
    "wof:placetype":"locality",
    "wof:population":110
},
  "geometry": {"coordinates":[78.18152499999999,17.955209],"type":"Point"}
}