{
  "type": "Feature",
  "properties": {
    "gn:admin1_code":"24.0",
    "gn:admin2_code":"128.0",
    "gn:asciiname":"Kanara",
    "gn:country_code":"IN",
    "gn:dem":231,
    "gn:feature_class":"P",
    "gn:feature_code":"PPL",
    "gn:name":"Kan\u0101ra",
    "gn:population":0,
    "gn:timezone":"Asia/Kolkata",
    "iso:country":"IN",
    "name:hin_x_preferred":[
        "\u0915\u0930\u093e\u0935\u0932\u0940"
    ],
    "name:ind_x_preferred":[
        "Kanara"
    ],
    "name:kan_x_preferred":[
        "\u0c95\u0cc6\u0ca8\u0cb0\u0cbe"
    ],
    "name:mal_x_preferred":[
        "\u0d15\u0d3e\u0d28\u0d31"
    ],
    "name:san_x_preferred":[
        "\u0915\u0930\u094d\u0923\u093e\u091f\u0915\u0938\u094d\u092f \u0938\u093e\u0917\u0930\u0924\u0940\u0930\u093e\u0923\u093f"
    ],
    "name:swe_x_preferred":[
        "Kanara"
    ],
    "name:urd_x_preferred":[
        "\u06a9\u0631\u0627\u0648\u0627\u0644\u06cc"
    ],
    "name:zho_x_preferred":[
        "\u5361\u7d0d\u9054"
    ],
    "wof:name":"Kanara",
    "wof:placetype":"locality"
},
  "geometry": {"coordinates":[76.34470999999998,25.37115],"type":"Point"}
}