{
  "type": "Feature",
  "properties": {
    "gn:admin1_code":"16",
    "gn:admin2_code":"525.0",
    "gn:asciiname":"Shahapur",
    "gn:country_code":"IN",
    "gn:dem":504,
    "gn:feature_class":"P",
    "gn:feature_code":"PPL",
    "gn:name":"Sh\u0101hapur",
    "gn:population":0,
    "gn:timezone":"Asia/Kolkata",
    "iso:country":"IN",
    "name:ben_x_preferred":[
        "\u09b6\u09be\u09b9\u09be\u09aa\u09c1\u09b0"
    ],
    "name:bpy_x_preferred":[
        "\u09b6\u09be\u09b9\u09be\u09aa\u09c1\u09b0"
    ],
    "name:ceb_x_preferred":[
        "Sh\u0101h\u0101pur"
    ],
    "name:hin_x_preferred":[
        "\u0936\u0939\u093e\u092a\u0941\u0930"
    ],
    "name:ita_x_preferred":[
        "Shahapur"
    ],
    "name:mar_x_preferred":[
        "\u0936\u0939\u093e\u092a\u0942\u0930"
    ],
    "name:msa_x_preferred":[
        "Shahapur"
    ],
    "name:nld_x_preferred":[
        "Shahapur"
    ],
    "name:por_x_preferred":[
        "Shahapur"
    ],
    "name:swe_x_preferred":[
        "Sh\u0101h\u0101pur"
    ],
    "name:vie_x_preferred":[
        "Shahapur"
    ],
    "name:zho_x_preferred":[
        "\u65af\u54c8\u54c8\u666e\u5c14"
    ],
    "wof:name":"Shahapur",
    "wof:placetype":"locality"
},
  "geometry": {"coordinates":[76.23331,17.73624],"type":"Point"}
}