{
  "type": "Feature",
  "properties": {
    "iso:country":"IN",
    "ks:ks_name":"Bhagavanpura",
    "ks:ks_pop":584,
    "ks:ks_type":"HABITATION",
    "name:eng_x_preferred":[
        "Bhagavanpura"
    ],
    "wof:name":"Bhagavanpura",
    "wof:placetype":"locality",
    "wof:population":584
},
  "geometry": {"coordinates":[72.936925,22.726894],"type":"Point"}
}