{
  "type": "Feature",
  "properties": {
    "iso:country":"IN",
    "ks:ks_alt_nam":"Get\u0101munda",
    "ks:ks_name":"Getamunda",
    "ks:ks_pop":120,
    "ks:ks_type":"VILLAGE",
    "name:eng_x_preferred":[
        "Getamunda"
    ],
    "name:eng_x_variant":[
        "Get\u0101munda"
    ],
    "wof:name":"Getamunda",
    "wof:placetype":"locality",
    "wof:population":120
},
  "geometry": {"coordinates":[84.388778,20.575472],"type":"Point"}
}