{
  "type": "Feature",
  "properties": {
    "gn:admin1_code":"28.0",
    "gn:admin2_code":"332.0",
    "gn:asciiname":"Talgram",
    "gn:country_code":"IN",
    "gn:dem":32,
    "gn:feature_class":"P",
    "gn:feature_code":"PPL",
    "gn:name":"T\u0101lgr\u0101m",
    "gn:population":0,
    "gn:timezone":"Asia/Kolkata",
    "iso:country":"IN",
    "name:bpy_x_preferred":[
        "\u09a4\u09be\u09b2\u0997\u09cd\u09b0\u09be\u09ae"
    ],
    "name:ceb_x_preferred":[
        "T\u0101lgr\u0101m"
    ],
    "name:ita_x_preferred":[
        "Talgram"
    ],
    "name:mlg_x_preferred":[
        "Talgram"
    ],
    "name:msa_x_preferred":[
        "Talgram"
    ],
    "name:nld_x_preferred":[
        "Talgram"
    ],
    "name:pol_x_preferred":[
        "Talgram"
    ],
    "name:por_x_preferred":[
        "Talgram"
    ],
    "name:rus_x_preferred":[
        "\u0422\u0430\u043b\u0433\u0440\u0430\u043c"
    ],
    "name:swe_x_preferred":[
        "T\u0101lgr\u0101m"
    ],
    "name:urd_x_preferred":[
        "\u062a\u0644\u06af\u0631\u0627\u0645"
    ],
    "name:vie_x_preferred":[
        "Talgram"
    ],
    "name:zho_x_preferred":[
        "\u5854\u5c14\u683c\u62c9\u59c6"
    ],
    "wof:name":"Talgram",
    "wof:placetype":"locality"
},
  "geometry": {"coordinates":[87.80095,25.42782],"type":"Point"}
}