{
  "type": "Feature",
  "properties": {
    "gn:admin1_code":"19.0",
    "gn:admin2_code":"566.0",
    "gn:asciiname":"Gollarahatti",
    "gn:country_code":"IN",
    "gn:dem":646,
    "gn:feature_class":"P",
    "gn:feature_code":"PPL",
    "gn:name":"Gollarahatti",
    "gn:population":0,
    "gn:timezone":"Asia/Kolkata",
    "iso:country":"IN",
    "wof:name":"Gollarahatti",
    "wof:placetype":"locality"
},
  "geometry": {"coordinates":[76.68859999999999,13.78486],"type":"Point"}
}