{
  "type": "Feature",
  "properties": {
    "iso:country":"IN",
    "ks:ks_alt_nam":"Zadi falia",
    "ks:ks_name":"Zadi Falia",
    "ks:ks_pop":64,
    "ks:ks_type":"HABITATION",
    "name:eng_x_preferred":[
        "Zadi Falia"
    ],
    "wof:name":"Zadi Falia",
    "wof:placetype":"locality",
    "wof:population":64
},
  "geometry": {"coordinates":[73.496056,21.025944],"type":"Point"}
}