{
  "type": "Feature",
  "properties": {
    "iso:country":"IN",
    "ks:ks_name":"Belun",
    "ks:ks_pop":963,
    "ks:ks_type":"VILLAGE",
    "name:eng_x_preferred":[
        "Belun"
    ],
    "wof:name":"Belun",
    "wof:placetype":"locality",
    "wof:population":963
},
  "geometry": {"coordinates":[87.563231,22.289417],"type":"Point"}
}