{
  "type": "Feature",
  "properties": {
    "gn:admin1_code":"34.0",
    "gn:admin2_code":"215.0",
    "gn:asciiname":"Imamganj",
    "gn:country_code":"IN",
    "gn:dem":52,
    "gn:feature_class":"P",
    "gn:feature_code":"PPL",
    "gn:name":"Im\u0101mganj",
    "gn:population":0,
    "gn:timezone":"Asia/Kolkata",
    "iso:country":"IN",
    "ks:ks_name":"Imamganj",
    "ks:ks_pop":476,
    "ks:ks_type":"HABITATION",
    "ks:ks_uagg_main":0,
    "name:eng_x_preferred":[
        "Imamganj"
    ],
    "wof:name":"Imamganj",
    "wof:placetype":"neighbourhood",
    "wof:population":476
},
  "geometry": {"coordinates":[86.255628,26.069957],"type":"Point"}
}