{
  "type": "Feature",
  "properties": {
    "iso:country":"IN",
    "ks:ks_alt_nam":"Dhup cherra",
    "ks:ks_name":"Dhup Cherra",
    "ks:ks_pop":370,
    "ks:ks_type":"HABITATION",
    "name:eng_x_preferred":[
        "Dhup Cherra"
    ],
    "wof:name":"Dhup Cherra",
    "wof:placetype":"locality",
    "wof:population":370
},
  "geometry": {"coordinates":[91.359011,23.358779],"type":"Point"}
}