{
  "type": "Feature",
  "properties": {
    "iso:country":"IN",
    "ks:ks_name":"Semaltha",
    "ks:ks_type":"VILLAGE",
    "name:eng_x_preferred":[
        "Semaltha"
    ],
    "wof:name":"Semaltha",
    "wof:placetype":"locality"
},
  "geometry": {"coordinates":[78.72036900000001,30.412595],"type":"Point"}
}