{
  "type": "Feature",
  "properties": {
    "iso:country":"IN",
    "ks:ks_name":"Pakri",
    "ks:ks_pop":499,
    "ks:ks_type":"VILLAGE",
    "name:eng_x_preferred":[
        "Pakri"
    ],
    "wof:name":"Pakri",
    "wof:placetype":"locality",
    "wof:population":499
},
  "geometry": {"coordinates":[87.648411,24.532477],"type":"Point"}
}