{
  "type": "Feature",
  "properties": {
    "gn:admin1_code":"25.0",
    "gn:admin2_code":"607.0",
    "gn:asciiname":"Annampakkam",
    "gn:country_code":"IN",
    "gn:dem":31,
    "gn:feature_class":"P",
    "gn:feature_code":"PPL",
    "gn:name":"Annamp\u0101kkam",
    "gn:population":0,
    "gn:timezone":"Asia/Kolkata",
    "iso:country":"IN",
    "wof:name":"Annampakkam",
    "wof:placetype":"locality"
},
  "geometry": {"coordinates":[79.79592,12.2982],"type":"Point"}
}