{
  "type": "Feature",
  "properties": {
    "iso:country":"IN",
    "ks:ks_alt_nam":"Khandiche galu",
    "ks:ks_name":"Khandiche Galu",
    "ks:ks_pop":147,
    "ks:ks_type":"HABITATION",
    "name:eng_x_preferred":[
        "Khandiche Galu"
    ],
    "wof:name":"Khandiche Galu",
    "wof:placetype":"locality",
    "wof:population":147
},
  "geometry": {"coordinates":[73.727181,16.087726],"type":"Point"}
}