{
  "type": "Feature",
  "properties": {
    "iso:country":"IN",
    "ks:ks_name":"Devasthanada Dasanapura",
    "ks:ks_pop":29,
    "ks:ks_type":"VILLAGE",
    "name:eng_x_preferred":[
        "Devasthanada Dasanapura"
    ],
    "wof:name":"Devasthanada Dasanapura",
    "wof:placetype":"locality",
    "wof:population":29
},
  "geometry": {"coordinates":[77.131229,13.001506],"type":"Point"}
}