{
  "type": "Feature",
  "properties": {
    "iso:country":"IN",
    "ks:ks_alt_nam":"BIJAKURAKHAS",
    "ks:ks_name":"Bijakurakhas",
    "ks:ks_pop":225,
    "ks:ks_type":"HABITATION",
    "name:eng_x_preferred":[
        "Bijakurakhas"
    ],
    "wof:name":"Bijakurakhas",
    "wof:placetype":"locality",
    "wof:population":225
},
  "geometry": {"coordinates":[82.865876,23.807198],"type":"Point"}
}