{
  "type": "Feature",
  "properties": {
    "gn:admin1_code":"19.0",
    "gn:admin2_code":"563.0",
    "gn:asciiname":"Abbigadde",
    "gn:country_code":"IN",
    "gn:dem":535,
    "gn:feature_class":"P",
    "gn:feature_code":"PPL",
    "gn:name":"Abbigadde",
    "gn:population":0,
    "gn:timezone":"Asia/Kolkata",
    "iso:country":"IN",
    "wof:name":"Abbigadde",
    "wof:placetype":"locality"
},
  "geometry": {"coordinates":[74.70683000000002,14.41102],"type":"Point"}
}