{
  "type": "Feature",
  "properties": {
    "iso:country":"IN",
    "ks:ks_name":"Chhotaelageria",
    "ks:ks_pop":20,
    "ks:ks_type":"VILLAGE",
    "name:eng_x_preferred":[
        "Chhotaelageria"
    ],
    "wof:name":"Chhotaelageria",
    "wof:placetype":"locality",
    "wof:population":20
},
  "geometry": {"coordinates":[87.177572,22.863881],"type":"Point"}
}