{
  "type": "Feature",
  "properties": {
    "iso:country":"IN",
    "ks:ks_name":"Mohd Nagar (west)",
    "ks:ks_pop":113,
    "ks:ks_type":"HABITATION",
    "name:eng_x_preferred":[
        "Mohd Nagar (west)"
    ],
    "wof:name":"Mohd Nagar (west)",
    "wof:placetype":"locality",
    "wof:population":113
},
  "geometry": {"coordinates":[83.162538,27.450583],"type":"Point"}
}