{
  "type": "Feature",
  "properties": {
    "iso:country":"IN",
    "ks:ks_name":"Pirpur",
    "ks:ks_pop":2950,
    "ks:ks_type":"HABITATION",
    "ks:ks_uagg_main":0,
    "name:eng_x_preferred":[
        "Pirpur"
    ],
    "wof:name":"Pirpur",
    "wof:placetype":"neighbourhood",
    "wof:population":2950
},
  "geometry": {"coordinates":[87.984566,25.017945],"type":"Point"}
}