{
  "type": "Feature",
  "properties": {
    "gn:country":"IN",
    "gn:fcode":"PPL",
    "gn:pop":11389,
    "iso:country":"IN",
    "name:bpy_x_preferred":[
        "\u09b2\u09be\u0996\u09a8\u09be"
    ],
    "name:eng_x_preferred":[
        "Lakhna"
    ],
    "name:fra_x_preferred":[
        "Lakhna"
    ],
    "name:hif_x_preferred":[
        "Lakhna"
    ],
    "name:hin_x_preferred":[
        "\u0932\u0916\u0928\u093e"
    ],
    "name:ita_x_preferred":[
        "Lakhna"
    ],
    "name:mlg_x_preferred":[
        "Lakhna"
    ],
    "name:msa_x_preferred":[
        "Lakhna"
    ],
    "name:nan_x_preferred":[
        "Lakhna"
    ],
    "name:new_x_preferred":[
        "\u0932\u0916\u0928\u093e"
    ],
    "name:nld_x_preferred":[
        "Lakhna"
    ],
    "name:pol_x_preferred":[
        "Lakhna"
    ],
    "name:por_x_preferred":[
        "Lakhna"
    ],
    "name:sco_x_preferred":[
        "Lakhna"
    ],
    "name:swe_x_preferred":[
        "Dakhn\u0101"
    ],
    "name:unk_x_variant":[
        "Lakhn\u0101"
    ],
    "name:urd_x_preferred":[
        "\u0644\u06a9\u06be\u0646\u0627"
    ],
    "name:vie_x_preferred":[
        "Lakhna"
    ],
    "name:zho_x_preferred":[
        "\u62c9\u514b\u7eb3"
    ],
    "qs:name":"Dakhn\u0101",
    "qs:photos_9r":0,
    "qs:photos_sr":0,
    "qs:pop_sr":"6",
    "wof:name":"Dakhn\u0101",
    "wof:placetype":"locality",
    "wof:population":11389
},
  "geometry": {"coordinates":[79.14848000000001,26.64832],"type":"Point"}
}