{
  "type": "Feature",
  "properties": {
    "iso:country":"IN",
    "ks:ks_name":"Chuna Kolwan",
    "ks:ks_pop":592,
    "ks:ks_type":"VILLAGE",
    "name:eng_x_preferred":[
        "Chuna Kolwan"
    ],
    "wof:name":"Chuna Kolwan",
    "wof:placetype":"locality",
    "wof:population":592
},
  "geometry": {"coordinates":[73.56268,16.75698],"type":"Point"}
}