{
  "type": "Feature",
  "properties": {
    "iso:country":"IN",
    "ks:ks_name":"Joypur T E",
    "ks:ks_pop":419,
    "ks:ks_type":"HABITATION",
    "ks:ks_uagg_main":0,
    "name:eng_x_preferred":[
        "Joypur T E"
    ],
    "wof:name":"Joypur T E",
    "wof:placetype":"neighbourhood",
    "wof:population":419
},
  "geometry": {"coordinates":[95.373195,27.252997],"type":"Point"}
}