{
  "type": "Feature",
  "properties": {
    "iso:country":"IN",
    "ks:ks_alt_nam":"GANJ TOLA",
    "ks:ks_name":"Ganj Tola",
    "ks:ks_pop":803,
    "ks:ks_type":"HABITATION",
    "name:eng_x_preferred":[
        "Ganj Tola"
    ],
    "wof:name":"Ganj Tola",
    "wof:placetype":"locality",
    "wof:population":803
},
  "geometry": {"coordinates":[87.440736,25.505196],"type":"Point"}
}