{
  "type": "Feature",
  "properties": {
    "iso:country":"IN",
    "ks:ks_name":"Karthigaipatti",
    "ks:ks_pop":103,
    "ks:ks_type":"HABITATION",
    "name:eng_x_preferred":[
        "Karthigaipatti"
    ],
    "wof:name":"Karthigaipatti",
    "wof:placetype":"locality",
    "wof:population":103
},
  "geometry": {"coordinates":[77.709767,9.487902],"type":"Point"}
}