{
  "type": "Feature",
  "properties": {
    "iso:country":"IN",
    "ks:ks_alt_nam":"MADHUGAJA PARA",
    "ks:ks_name":"Madhugaja Para",
    "ks:ks_pop":174,
    "ks:ks_type":"HABITATION",
    "name:eng_x_preferred":[
        "Madhugaja Para"
    ],
    "wof:name":"Madhugaja Para",
    "wof:placetype":"locality",
    "wof:population":174
},
  "geometry": {"coordinates":[91.69772,24.033361],"type":"Point"}
}