{
  "type": "Feature",
  "properties": {
    "iso:country":"IN",
    "ks:ks_name":"Bahadur Garh",
    "ks:ks_pop":1172,
    "ks:ks_type":"HABITATION",
    "name:eng_x_preferred":[
        "Bahadur Garh"
    ],
    "wof:name":"Bahadur Garh",
    "wof:placetype":"locality",
    "wof:population":1172
},
  "geometry": {"coordinates":[80.38972200000001,26.231389],"type":"Point"}
}