{
  "type": "Feature",
  "properties": {
    "iso:country":"IN",
    "ks:ks_name":"Phili Tola",
    "ks:ks_pop":293,
    "ks:ks_type":"HABITATION",
    "name:eng_x_preferred":[
        "Phili Tola"
    ],
    "wof:name":"Phili Tola",
    "wof:placetype":"locality",
    "wof:population":293
},
  "geometry": {"coordinates":[83.526264,24.111315],"type":"Point"}
}