{
  "type": "Feature",
  "properties": {
    "iso:country":"IN",
    "ks:ks_name":"Kadama",
    "ks:ks_pop":147,
    "ks:ks_type":"HABITATION",
    "name:eng_x_preferred":[
        "Kadama"
    ],
    "wof:name":"Kadama",
    "wof:placetype":"locality",
    "wof:population":147
},
  "geometry": {"coordinates":[74.859525,13.106562],"type":"Point"}
}