{
  "type": "Feature",
  "properties": {
    "iso:country":"IN",
    "ks:ks_name":"Niwada Dhamanu",
    "ks:ks_pop":775,
    "ks:ks_type":"HABITATION",
    "name:eng_x_preferred":[
        "Niwada Dhamanu"
    ],
    "wof:name":"Niwada Dhamanu",
    "wof:placetype":"locality",
    "wof:population":775
},
  "geometry": {"coordinates":[80.12379300000001,26.745793],"type":"Point"}
}