{
  "type": "Feature",
  "properties": {
    "iso:country":"IN",
    "ks:ks_alt_nam":"Midde and Molla Para",
    "ks:ks_name":"Midde And Molla Para",
    "ks:ks_pop":2642,
    "ks:ks_type":"HABITATION",
    "name:eng_x_preferred":[
        "Midde And Molla Para"
    ],
    "wof:name":"Midde And Molla Para",
    "wof:placetype":"locality",
    "wof:population":2642
},
  "geometry": {"coordinates":[88.56434299999999,22.302373],"type":"Point"}
}