{
  "type": "Feature",
  "properties": {
    "iso:country":"IN",
    "ks:ks_alt_nam":"Chinikiro Jaru\u0101dih",
    "ks:ks_name":"Chinikiro Jaruadih",
    "ks:ks_pop":1577,
    "ks:ks_type":"VILLAGE",
    "name:eng_x_preferred":[
        "Chinikiro Jaruadih"
    ],
    "name:eng_x_variant":[
        "Chinikiro Jaru\u0101dih"
    ],
    "wof:name":"Chinikiro Jaruadih",
    "wof:placetype":"locality",
    "wof:population":1577
},
  "geometry": {"coordinates":[85.948087,23.957395],"type":"Point"}
}