{
  "type": "Feature",
  "properties": {
    "iso:country":"IN",
    "ks:ks_name":"Latiborchuk",
    "ks:ks_pop":531,
    "ks:ks_type":"VILLAGE",
    "ks:ks_uagg_main":0,
    "name:eng_x_preferred":[
        "Latiborchuk"
    ],
    "wof:name":"Latiborchuk",
    "wof:placetype":"neighbourhood",
    "wof:population":531
},
  "geometry": {"coordinates":[94.370312,27.105366],"type":"Point"}
}