{
  "type": "Feature",
  "properties": {
    "iso:country":"IN",
    "ks:ks_name":"Brozokal",
    "ks:ks_pop":665,
    "ks:ks_type":"HABITATION",
    "name:eng_x_preferred":[
        "Brozokal"
    ],
    "wof:name":"Brozokal",
    "wof:placetype":"locality",
    "wof:population":665
},
  "geometry": {"coordinates":[90.152044,26.435618],"type":"Point"}
}