{
  "type": "Feature",
  "properties": {
    "iso:country":"IN",
    "ks:ks_name":"Balapara Saljhar",
    "ks:ks_pop":92,
    "ks:ks_type":"VILLAGE",
    "name:eng_x_preferred":[
        "Balapara Saljhar"
    ],
    "wof:name":"Balapara Saljhar",
    "wof:placetype":"locality",
    "wof:population":92
},
  "geometry": {"coordinates":[90.093174,26.32898],"type":"Point"}
}