{
  "type": "Feature",
  "properties": {
    "gn:admin1_code":"19",
    "gn:admin2_code":"579.0",
    "gn:asciiname":"Chattarsal",
    "gn:country_code":"IN",
    "gn:dem":439,
    "gn:feature_class":"P",
    "gn:feature_code":"PPL",
    "gn:name":"Chattars\u0101l",
    "gn:population":0,
    "gn:timezone":"Asia/Kolkata",
    "iso:country":"IN",
    "wof:name":"Chattarsal",
    "wof:placetype":"locality"
},
  "geometry": {"coordinates":[77.42780999999999,17.31146],"type":"Point"}
}