{
  "type": "Feature",
  "properties": {
    "gn:admin1_code":"12.0",
    "gn:admin2_code":"1.0",
    "gn:asciiname":"Kairihom",
    "gn:country_code":"IN",
    "gn:dem":1701,
    "gn:feature_class":"P",
    "gn:feature_code":"PPL",
    "gn:name":"Kairihom",
    "gn:population":0,
    "gn:timezone":"Asia/Kolkata",
    "iso:country":"IN",
    "wof:name":"Kairihom",
    "wof:placetype":"locality"
},
  "geometry": {"coordinates":[74.22154999999999,34.49936],"type":"Point"}
}