{
  "type": "Feature",
  "properties": {
    "gn:admin1_code":"39.0",
    "gn:admin2_code":"64.0",
    "gn:asciiname":"Basurikhet",
    "gn:country_code":"IN",
    "gn:dem":1871,
    "gn:feature_class":"P",
    "gn:feature_code":"PPL",
    "gn:name":"Basurikhet",
    "gn:population":0,
    "gn:timezone":"Asia/Kolkata",
    "iso:country":"IN",
    "wof:name":"Basurikhet",
    "wof:placetype":"locality"
},
  "geometry": {"coordinates":[79.58218000000002,29.71502000000001],"type":"Point"}
}