{
  "type": "Feature",
  "properties": {
    "iso:country":"IN",
    "ks:ks_name":"Deulpota",
    "ks:ks_pop":1192,
    "ks:ks_type":"VILLAGE",
    "name:eng_x_preferred":[
        "Deulpota"
    ],
    "wof:name":"Deulpota",
    "wof:placetype":"locality",
    "wof:population":1192
},
  "geometry": {"coordinates":[88.078761,22.169834],"type":"Point"}
}