{
  "type": "Feature",
  "properties": {
    "iso:country":"IN",
    "ks:ks_name":"Dalabar",
    "ks:ks_pop":1907,
    "ks:ks_type":"VILLAGE",
    "name:eng_x_preferred":[
        "Dalabar"
    ],
    "wof:name":"Dalabar",
    "wof:placetype":"locality",
    "wof:population":1907
},
  "geometry": {"coordinates":[87.03386399999999,23.910086],"type":"Point"}
}