{
  "type": "Feature",
  "properties": {
    "iso:country":"IN",
    "ks:ks_name":"Haridapara",
    "ks:ks_pop":252,
    "ks:ks_type":"HABITATION",
    "name:eng_x_preferred":[
        "Haridapara"
    ],
    "wof:name":"Haridapara",
    "wof:placetype":"locality",
    "wof:population":252
},
  "geometry": {"coordinates":[82.50134799999999,19.703123],"type":"Point"}
}