{
  "type": "Feature",
  "properties": {
    "iso:country":"IN",
    "ks:ks_name":"Moronde",
    "ks:ks_pop":565,
    "ks:ks_type":"VILLAGE",
    "name:eng_x_preferred":[
        "Moronde"
    ],
    "wof:name":"Moronde",
    "wof:placetype":"locality",
    "wof:population":565
},
  "geometry": {"coordinates":[73.041646,18.565581],"type":"Point"}
}