{
  "type": "Feature",
  "properties": {
    "gn:admin1_code":"39.0",
    "gn:admin2_code":"66.0",
    "gn:asciiname":"Malli Gurgari",
    "gn:country_code":"IN",
    "gn:dem":1550,
    "gn:feature_class":"P",
    "gn:feature_code":"PPL",
    "gn:name":"Malli Gurgari",
    "gn:population":0,
    "gn:timezone":"Asia/Kolkata",
    "iso:country":"IN",
    "wof:name":"Malli Gurgari",
    "wof:placetype":"locality"
},
  "geometry": {"coordinates":[79.77485,29.2719],"type":"Point"}
}