{
  "type": "Feature",
  "properties": {
    "gn:admin1_code":"37",
    "gn:admin2_code":"409.0",
    "gn:asciiname":"Kusumkasa",
    "gn:country_code":"IN",
    "gn:dem":389,
    "gn:feature_class":"P",
    "gn:feature_code":"PPL",
    "gn:name":"Kusumkasa",
    "gn:population":0,
    "gn:timezone":"Asia/Kolkata",
    "iso:country":"IN",
    "wof:name":"Kusumkasa",
    "wof:placetype":"locality"
},
  "geometry": {"coordinates":[81.08351,20.63985],"type":"Point"}
}