{
  "type": "Feature",
  "properties": {
    "iso:country":"IN",
    "ks:ks_name":"Thumguttavaddepalle",
    "ks:ks_pop":41,
    "ks:ks_type":"HABITATION",
    "name:eng_x_preferred":[
        "Thumguttavaddepalle"
    ],
    "wof:name":"Thumguttavaddepalle",
    "wof:placetype":"locality",
    "wof:population":41
},
  "geometry": {"coordinates":[78.915701,14.092949],"type":"Point"}
}