{
  "type": "Feature",
  "properties": {
    "gn:admin1_code":"35.0",
    "gn:admin2_code":"429.0",
    "gn:asciiname":"Majhgawan",
    "gn:country_code":"IN",
    "gn:dem":369,
    "gn:feature_class":"P",
    "gn:feature_code":"PPL",
    "gn:name":"Majhgaw\u0101n",
    "gn:population":0,
    "gn:timezone":"Asia/Kolkata",
    "iso:country":"IN",
    "name:hin_x_preferred":[
        "\u092e\u091d\u0917\u0935\u093e\u0902"
    ],
    "wof:name":"Majhgawan",
    "wof:placetype":"locality"
},
  "geometry": {"coordinates":[80.7774,24.00301],"type":"Point"}
}