{
  "type": "Feature",
  "properties": {
    "gn:admin1_code":"11",
    "gn:admin2_code":"23.0",
    "gn:asciiname":"Sithlu Ther",
    "gn:country_code":"IN",
    "gn:dem":1795,
    "gn:feature_class":"P",
    "gn:feature_code":"PPL",
    "gn:name":"Sithlu Ther",
    "gn:population":0,
    "gn:timezone":"Asia/Kolkata",
    "iso:country":"IN",
    "wof:name":"Sithlu Ther",
    "wof:placetype":"locality"
},
  "geometry": {"coordinates":[76.12373000000002,32.32176],"type":"Point"}
}