{
  "type": "Feature",
  "properties": {
    "gn:admin1_code":"12.0",
    "gn:admin2_code":"7.0",
    "gn:asciiname":"Mun",
    "gn:country_code":"IN",
    "gn:dem":654,
    "gn:feature_class":"P",
    "gn:feature_code":"PPL",
    "gn:name":"M\u016bn",
    "gn:population":0,
    "gn:timezone":"Asia/Kolkata",
    "iso:country":"IN",
    "name:ara_x_preferred":[
        "\u0645\u0648\u0646"
    ],
    "name:ben_x_preferred":[
        "\u09ae\u09c1\u09a8"
    ],
    "name:ceb_x_preferred":[
        "Mun"
    ],
    "name:deu_x_preferred":[
        "Mun"
    ],
    "name:ell_x_preferred":[
        "\u039c\u03bf\u03c5\u03bd"
    ],
    "name:fas_x_preferred":[
        "\u0645\u0648\u0646"
    ],
    "name:fra_x_preferred":[
        "Mun"
    ],
    "name:heb_x_preferred":[
        "\u05d0\u05d2\u05dd \u05de\u05d5\u05e0\u05d3\u05d5\u05d9\u05e1\u05e7\u05d5\u05d9\u05d4"
    ],
    "name:hin_x_preferred":[
        "\u092e\u0941\u0928"
    ],
    "name:hun_x_preferred":[
        "Mun"
    ],
    "name:ind_x_preferred":[
        "Mun"
    ],
    "name:nld_x_preferred":[
        "Mun"
    ],
    "name:pol_x_preferred":[
        "Mun"
    ],
    "name:rus_x_preferred":[
        "\u041c\u0443\u043d"
    ],
    "name:srn_x_preferred":[
        "Mun"
    ],
    "name:swe_x_preferred":[
        "Mun"
    ],
    "name:tpi_x_preferred":[
        "Mun"
    ],
    "name:tur_x_preferred":[
        "Mun"
    ],
    "name:urd_x_preferred":[
        "\u0645\u0648\u0646"
    ],
    "name:vol_x_preferred":[
        "Mun"
    ],
    "wof:name":"Mun",
    "wof:placetype":"locality"
},
  "geometry": {"coordinates":[75.37627999999999,32.58908],"type":"Point"}
}