{
  "type": "Feature",
  "properties": {
    "iso:country":"IN",
    "ks:ks_name":"Kakardhar",
    "ks:ks_pop":19,
    "ks:ks_type":"HABITATION",
    "name:eng_x_preferred":[
        "Kakardhar"
    ],
    "wof:name":"Kakardhar",
    "wof:placetype":"locality",
    "wof:population":19
},
  "geometry": {"coordinates":[78.764308,29.872135],"type":"Point"}
}