{
  "type": "Feature",
  "properties": {
    "iso:country":"IN",
    "ks:ks_name":"Gouranga Reang Para",
    "ks:ks_pop":45,
    "ks:ks_type":"HABITATION",
    "ks:ks_uagg_main":0,
    "name:eng_x_preferred":[
        "Gouranga Reang Para"
    ],
    "wof:name":"Gouranga Reang Para",
    "wof:placetype":"neighbourhood",
    "wof:population":45
},
  "geometry": {"coordinates":[91.739541,23.320436],"type":"Point"}
}