{
  "type": "Feature",
  "properties": {
    "iso:country":"IN",
    "ks:ks_name":"Puranpur",
    "ks:ks_pop":491,
    "ks:ks_type":"HABITATION",
    "name:eng_x_preferred":[
        "Puranpur"
    ],
    "wof:name":"Puranpur",
    "wof:placetype":"locality",
    "wof:population":491
},
  "geometry": {"coordinates":[82.032274,25.524975],"type":"Point"}
}