{
  "type": "Feature",
  "properties": {
    "iso:country":"IN",
    "ks:ks_name":"Fatehpur Dhak",
    "ks:ks_pop":0,
    "ks:ks_type":"VILLAGE",
    "name:eng_x_preferred":[
        "Fatehpur Dhak"
    ],
    "wof:name":"Fatehpur Dhak",
    "wof:placetype":"locality",
    "wof:population":0
},
  "geometry": {"coordinates":[76.147412,30.672674],"type":"Point"}
}