{
  "type": "Feature",
  "properties": {
    "gn:admin1_code":"19.0",
    "gn:admin2_code":"572.0",
    "gn:asciiname":"Kanamangala",
    "gn:country_code":"IN",
    "gn:dem":871,
    "gn:feature_class":"P",
    "gn:feature_code":"PPL",
    "gn:name":"Kanamangala",
    "gn:population":0,
    "gn:timezone":"Asia/Kolkata",
    "iso:country":"IN",
    "wof:name":"Kanamangala",
    "wof:placetype":"locality"
},
  "geometry": {"coordinates":[77.76969,13.02759],"type":"Point"}
}