{
  "type": "Feature",
  "properties": {
    "gn:admin1_code":"12.0",
    "gn:admin2_code":"021",
    "gn:asciiname":"Chata",
    "gn:country_code":"IN",
    "gn:dem":529,
    "gn:feature_class":"P",
    "gn:feature_code":"PPL",
    "gn:name":"Ch\u0101ta",
    "gn:population":0,
    "gn:timezone":"Asia/Kolkata",
    "iso:country":"IN",
    "name:ind_x_preferred":[
        "Chata"
    ],
    "name:tgl_x_preferred":[
        "Chata"
    ],
    "name:vie_x_preferred":[
        "Chata"
    ],
    "wof:name":"Chata",
    "wof:placetype":"locality"
},
  "geometry": {"coordinates":[74.95364000000002,32.69762],"type":"Point"}
}