{
  "type": "Feature",
  "properties": {
    "gn:admin1_code":"2",
    "gn:admin2_code":"548.0",
    "gn:asciiname":"Chamarru",
    "gn:country_code":"IN",
    "gn:dem":40,
    "gn:feature_class":"P",
    "gn:feature_code":"PPL",
    "gn:name":"Ch\u0101marru",
    "gn:population":0,
    "gn:timezone":"Asia/Kolkata",
    "iso:country":"IN",
    "name:tel_x_preferred":[
        "\u0c1a\u0c3e\u0c2e\u0c30\u0c4d\u0c30\u0c41"
    ],
    "wof:name":"Chamarru",
    "wof:placetype":"locality"
},
  "geometry": {"coordinates":[80.13096,16.6434],"type":"Point"}
}