{
  "type": "Feature",
  "properties": {
    "gn:admin1_code":"36",
    "gn:admin2_code":"134.0",
    "gn:asciiname":"Nawada",
    "gn:country_code":"IN",
    "gn:dem":245,
    "gn:feature_class":"P",
    "gn:feature_code":"PPL",
    "gn:name":"Naw\u0101da",
    "gn:population":0,
    "gn:timezone":"Asia/Kolkata",
    "iso:country":"IN",
    "name:ara_x_preferred":[
        "\u0646\u0648\u0627\u062f\u0627"
    ],
    "name:ben_x_preferred":[
        "\u09a8\u0993\u09af\u09bc\u09be\u09a6\u09be"
    ],
    "name:bih_x_preferred":[
        "\u0928\u0935\u093e\u0926\u093e"
    ],
    "name:bpy_x_preferred":[
        "\u09a8\u09be\u09f1\u09be\u09a6\u09be"
    ],
    "name:ceb_x_preferred":[
        "Naw\u0101da"
    ],
    "name:fas_x_preferred":[
        "\u0646\u0627\u0648\u0627\u062f\u0627"
    ],
    "name:hif_x_preferred":[
        "Nawada"
    ],
    "name:hin_x_preferred":[
        "\u0928\u0935\u093e\u0926\u093e"
    ],
    "name:ita_x_preferred":[
        "Nawada"
    ],
    "name:mal_x_preferred":[
        "\u0d28\u0d35\u0d3e\u0d21"
    ],
    "name:mlg_x_preferred":[
        "Nawada"
    ],
    "name:msa_x_preferred":[
        "Nawada"
    ],
    "name:nep_x_preferred":[
        "\u0928\u0935\u093e\u0926\u093e"
    ],
    "name:new_x_preferred":[
        "\u0928\u0935\u093e\u0926\u093e"
    ],
    "name:ori_x_preferred":[
        "\u0b28\u0b3e\u0b71\u0b3e\u0b21\u0b3c\u0b3e"
    ],
    "name:por_x_preferred":[
        "Nawada"
    ],
    "name:rus_x_preferred":[
        "\u041d\u0430\u0432\u0430\u0434\u0430"
    ],
    "name:san_x_preferred":[
        "\u0928\u0935\u093e\u0926\u093e"
    ],
    "name:spa_x_preferred":[
        "Nawada"
    ],
    "name:swe_x_preferred":[
        "Nawada"
    ],
    "name:und_x_variant":[
        "Mahm\u016bdpur K\u0101m\u012bl"
    ],
    "name:urd_x_preferred":[
        "\u0646\u0648\u0627\u062f\u06c1"
    ],
    "name:vie_x_preferred":[
        "Nawada"
    ],
    "name:zho_x_preferred":[
        "\u7eb3\u74e6\u8fbe"
    ],
    "wof:name":"Nawada",
    "wof:placetype":"locality"
},
  "geometry": {"coordinates":[78.34243000000002,29.35836],"type":"Point"}
}