{
  "type": "Feature",
  "properties": {
    "gn:admin1_code":"16.0",
    "gn:admin2_code":"508.0",
    "gn:asciiname":"Muttapur",
    "gn:country_code":"IN",
    "gn:dem":116,
    "gn:feature_class":"P",
    "gn:feature_code":"PPL",
    "gn:name":"Mutt\u0101pur",
    "gn:population":0,
    "gn:timezone":"Asia/Kolkata",
    "iso:country":"IN",
    "ks:ks_alt_nam":"Mutt\u0101pur",
    "ks:ks_name":"Muttapur",
    "ks:ks_type":"VILLAGE",
    "name:eng_x_preferred":[
        "Muttapur"
    ],
    "name:eng_x_variant":[
        "Mutt\u0101pur"
    ],
    "wof:name":"Muttapur",
    "wof:placetype":"locality"
},
  "geometry": {"coordinates":[80.227397,18.724873],"type":"Point"}
}