{
  "type": "Feature",
  "properties": {
    "iso:country":"IN",
    "ks:ks_name":"Vutakosu",
    "ks:ks_pop":105,
    "ks:ks_type":"VILLAGE",
    "name:eng_x_preferred":[
        "Vutakosu"
    ],
    "wof:name":"Vutakosu",
    "wof:placetype":"locality",
    "wof:population":105
},
  "geometry": {"coordinates":[83.38137999999999,18.921298],"type":"Point"}
}