{
  "type": "Feature",
  "properties": {
    "gn:admin1_code":"16.0",
    "gn:admin2_code":"507",
    "gn:asciiname":"Goregaon",
    "gn:country_code":"IN",
    "gn:dem":326,
    "gn:feature_class":"P",
    "gn:feature_code":"PPL",
    "gn:name":"Goregaon",
    "gn:population":0,
    "gn:timezone":"Asia/Kolkata",
    "iso:country":"IN",
    "name:ben_x_preferred":[
        "\u0997\u09cb\u09b0\u09c7\u0997\u09be\u0981\u0993"
    ],
    "name:bpy_x_preferred":[
        "\u0997\u09cb\u09b0\u09c7\u0997\u09be\u0981\u0993"
    ],
    "name:guj_x_preferred":[
        "\u0a97\u0acb\u0ab0\u0ac7\u0a97\u0abe\u0a82\u0ab5"
    ],
    "name:hin_x_preferred":[
        "\u0917\u094b\u0930\u0947\u0917\u093e\u0901\u0935"
    ],
    "name:mar_x_preferred":[
        "\u0917\u094b\u0930\u0947\u0917\u093e\u0935"
    ],
    "name:new_x_preferred":[
        "\u0917\u094b\u0930\u0947\u0917\u093e\u0902\u0935"
    ],
    "name:tam_x_preferred":[
        "\u0b95\u0bcb\u0bb0\u0bc7\u0b95\u0bbe\u0bb5\u0bcd"
    ],
    "wof:name":"Goregaon",
    "wof:placetype":"locality"
},
  "geometry": {"coordinates":[80.20831,21.34867],"type":"Point"}
}