{
  "type": "Feature",
  "properties": {
    "gn:admin1_code":"16.0",
    "gn:admin2_code":"507",
    "gn:asciiname":"Goregaon",
    "gn:country_code":"IN",
    "gn:dem":326,
    "gn:feature_class":"P",
    "gn:feature_code":"PPL",
    "gn:name":"Goregaon",
    "gn:population":0,
    "gn:timezone":"Asia/Kolkata",
    "iso:country":"IN",
    "wof:name":"Goregaon",
    "wof:placetype":"locality"
},
  "geometry": {"coordinates":[80.20831,21.34867],"type":"Point"}
}