{
  "type": "Feature",
  "properties": {
    "gn:admin1_code":"16.0",
    "gn:admin2_code":"507",
    "gn:asciiname":"Goregaon",
    "gn:country_code":"IN",
    "gn:dem":326,
    "gn:feature_class":"P",
    "gn:feature_code":"PPL",
    "gn:name":"Goregaon",
    "gn:population":0,
    "gn:timezone":"Asia/Kolkata",
    "iso:country":"IN",
    "name:ara_x_preferred":[
        "\u063a\u0648\u0631\u063a\u0627\u0648\u0646"
    ],
    "name:ben_bn_x_preferred":[
        "\u0997\u09cb\u09b0\u09c7\u0997\u09be\u0981\u0993"
    ],
    "name:ben_in_x_preferred":[
        "\u0997\u09cb\u09b0\u09c7\u0997\u09be\u0981\u0993"
    ],
    "name:ben_x_preferred":[
        "\u0997\u09cb\u09b0\u09c7\u0997\u09be\u0981\u0993"
    ],
    "name:bpy_x_preferred":[
        "\u0997\u09cb\u09b0\u09c7\u0997\u09be\u0981\u0993"
    ],
    "name:guj_x_preferred":[
        "\u0a97\u0acb\u0ab0\u0ac7\u0a97\u0abe\u0a82\u0ab5"
    ],
    "name:hin_x_preferred":[
        "\u0917\u094b\u0930\u0947\u0917\u093e\u0901\u0935"
    ],
    "name:kan_x_preferred":[
        "\u0c97\u0ccb\u0cb0\u0cc6\u0c97\u0cbe\u0c82\u0cb5\u0ccd"
    ],
    "name:mal_x_preferred":[
        "\u0d17\u0d41\u0d21\u0d4d\u0d17\u0d3e\u0d35\u0d4d"
    ],
    "name:mar_x_preferred":[
        "\u0917\u094b\u0930\u0947\u0917\u093e\u0935"
    ],
    "name:new_x_preferred":[
        "\u0917\u094b\u0930\u0947\u0917\u093e\u0902\u0935"
    ],
    "name:pan_x_preferred":[
        "\u0a17\u0a4b\u0a30\u0a47\u0a17\u0a3e\u0a13\u0a02"
    ],
    "name:tam_x_preferred":[
        "\u0b95\u0bcb\u0bb0\u0bc7\u0b95\u0bbe\u0ba9\u0bcd"
    ],
    "name:tam_x_variant":[
        "\u0b95\u0bcb\u0bb0\u0bc7\u0b95\u0bbe\u0bb5\u0bcd"
    ],
    "name:tel_x_preferred":[
        "\u0c17\u0c4b\u0c30\u0c47\u0c17\u0c3e\u0c35\u0c4d"
    ],
    "name:urd_x_preferred":[
        "\u06af\u0648\u0631\u06d2 \u06af\u0627\u0624\u06ba"
    ],
    "wof:name":"Goregaon",
    "wof:placetype":"locality"
},
  "geometry": {"coordinates":[80.20831,21.34867],"type":"Point"}
}