{
  "type": "Feature",
  "properties": {
    "gn:admin1_code":"24.0",
    "gn:admin2_code":"118.0",
    "gn:asciiname":"Septawa",
    "gn:country_code":"IN",
    "gn:dem":278,
    "gn:feature_class":"P",
    "gn:feature_code":"PPL",
    "gn:name":"Sept\u0101wa",
    "gn:population":0,
    "gn:timezone":"Asia/Kolkata",
    "iso:country":"IN",
    "ks:ks_alt_nam":"Sept\u0101wa",
    "ks:ks_name":"Septawa",
    "ks:ks_pop":701,
    "ks:ks_type":"VILLAGE",
    "name:eng_x_preferred":[
        "Septawa"
    ],
    "name:eng_x_variant":[
        "Sept\u0101wa"
    ],
    "wof:name":"Septawa",
    "wof:placetype":"locality",
    "wof:population":701
},
  "geometry": {"coordinates":[73.477594,25.511289],"type":"Point"}
}