{
  "type": "Feature",
  "properties": {
    "iso:country":"IN",
    "ks:ks_alt_nam":"kayapoyil",
    "ks:ks_name":"Kayapoyil",
    "ks:ks_pop":4375,
    "ks:ks_type":"HABITATION",
    "name:eng_x_preferred":[
        "Kayapoyil"
    ],
    "wof:name":"Kayapoyil",
    "wof:placetype":"locality",
    "wof:population":4375
},
  "geometry": {"coordinates":[75.362188,12.203385],"type":"Point"}
}