{
  "type": "Feature",
  "properties": {
    "gn:admin1_code":"36.0",
    "gn:admin2_code":"176.0",
    "gn:asciiname":"Sarawan",
    "gn:country_code":"IN",
    "gn:dem":129,
    "gn:feature_class":"P",
    "gn:feature_code":"PPL",
    "gn:name":"Sar\u0101wan",
    "gn:population":0,
    "gn:timezone":"Asia/Kolkata",
    "iso:country":"IN",
    "name:cat_x_preferred":[
        "Sarawan"
    ],
    "name:fra_x_preferred":[
        "Sarawan"
    ],
    "name:ita_x_preferred":[
        "Sarawan"
    ],
    "wof:name":"Sarawan",
    "wof:placetype":"neighbourhood"
},
  "geometry": {"coordinates":[80.99369,27.15207],"type":"Point"}
}