{
  "type": "Feature",
  "properties": {
    "gn:admin1_code":"11",
    "gn:admin2_code":"27.0",
    "gn:asciiname":"Katiur",
    "gn:country_code":"IN",
    "gn:dem":1669,
    "gn:feature_class":"P",
    "gn:feature_code":"PPL",
    "gn:name":"Kati\u016br",
    "gn:population":0,
    "gn:timezone":"Asia/Kolkata",
    "iso:country":"IN",
    "wof:name":"Katiur",
    "wof:placetype":"locality"
},
  "geometry": {"coordinates":[76.9404,31.85475],"type":"Point"}
}