{
  "type": "Feature",
  "properties": {
    "iso:country":"IN",
    "ks:ks_name":"Kharadi Phalan",
    "ks:ks_pop":284,
    "ks:ks_type":"HABITATION",
    "name:eng_x_preferred":[
        "Kharadi Phalan"
    ],
    "wof:name":"Kharadi Phalan",
    "wof:placetype":"locality",
    "wof:population":284
},
  "geometry": {"coordinates":[73.661298,23.953872],"type":"Point"}
}