{
  "type": "Feature",
  "properties": {
    "iso:country":"IN",
    "ks:ks_alt_nam":"Bichua piter",
    "ks:ks_name":"Bichua Piter",
    "ks:ks_pop":179,
    "ks:ks_type":"HABITATION",
    "name:eng_x_preferred":[
        "Bichua Piter"
    ],
    "wof:name":"Bichua Piter",
    "wof:placetype":"locality",
    "wof:population":179
},
  "geometry": {"coordinates":[79.172798,23.074432],"type":"Point"}
}