{
  "type": "Feature",
  "properties": {
    "iso:country":"IN",
    "ks:ks_name":"Bainpura Khalsa",
    "ks:ks_pop":994,
    "ks:ks_type":"VILLAGE",
    "name:eng_x_preferred":[
        "Bainpura Khalsa"
    ],
    "wof:name":"Bainpura Khalsa",
    "wof:placetype":"locality",
    "wof:population":994
},
  "geometry": {"coordinates":[77.616381,26.730789],"type":"Point"}
}