{
  "type": "Feature",
  "properties": {
    "gn:admin1_code":"16.0",
    "gn:admin2_code":"510.0",
    "gn:asciiname":"Sakhar",
    "gn:country_code":"IN",
    "gn:dem":194,
    "gn:feature_class":"P",
    "gn:feature_code":"PPL",
    "gn:name":"S\u0101khar",
    "gn:population":0,
    "gn:timezone":"Asia/Kolkata",
    "iso:country":"IN",
    "ks:ks_name":"Sakhara",
    "ks:ks_pop":2243,
    "ks:ks_type":"VILLAGE",
    "name:eng_x_preferred":[
        "Sakhara"
    ],
    "name:eng_x_variant":[
        "Sakhar"
    ],
    "wof:name":"Sakhara",
    "wof:placetype":"locality",
    "wof:population":2243
},
  "geometry": {"coordinates":[79.12532299999999,19.883389],"type":"Point"}
}