{
  "type": "Feature",
  "properties": {
    "gn:admin1_code":"36",
    "gn:admin2_code":"175.0",
    "gn:asciiname":"Patulki",
    "gn:country_code":"IN",
    "gn:dem":97,
    "gn:feature_class":"P",
    "gn:feature_code":"PPL",
    "gn:name":"Patulki",
    "gn:population":0,
    "gn:timezone":"Asia/Kolkata",
    "iso:country":"IN",
    "ks:ks_name":"Patulki",
    "ks:ks_pop":2541,
    "ks:ks_type":"VILLAGE",
    "ks:ks_uagg_main":0,
    "name:eng_x_preferred":[
        "Patulki"
    ],
    "wof:name":"Patulki",
    "wof:placetype":"neighbourhood",
    "wof:population":2541
},
  "geometry": {"coordinates":[82.026661,25.569047],"type":"Point"}
}