{
  "type": "Feature",
  "properties": {
    "gn:admin1_code":"36.0",
    "gn:admin2_code":"134.0",
    "gn:asciiname":"Umarpur Bangar",
    "gn:country_code":"IN",
    "gn:dem":230,
    "gn:feature_class":"P",
    "gn:feature_code":"PPL",
    "gn:name":"Umarpur B\u0101ngar",
    "gn:population":0,
    "gn:timezone":"Asia/Kolkata",
    "iso:country":"IN",
    "wof:name":"Umarpur Bangar",
    "wof:placetype":"locality"
},
  "geometry": {"coordinates":[78.53461,29.33167000000001],"type":"Point"}
}