{
  "type": "Feature",
  "properties": {
    "gn:admin1_code":"34.0",
    "gn:admin2_code":"235.0",
    "gn:asciiname":"Ahmadabad",
    "gn:country_code":"IN",
    "gn:dem":106,
    "gn:feature_class":"P",
    "gn:feature_code":"PPL",
    "gn:name":"Ahmad\u0101b\u0101d",
    "gn:population":0,
    "gn:timezone":"Asia/Kolkata",
    "iso:country":"IN",
    "name:ara_x_preferred":[
        "\u0623\u062d\u0645\u062f \u0623\u0628\u0627\u062f"
    ],
    "name:azb_x_preferred":[
        "\u0627\u062d\u0645\u062f\u0622\u0628\u0627\u062f"
    ],
    "name:cat_x_preferred":[
        "Ahmadabad"
    ],
    "name:ceb_x_preferred":[
        "Ahmadabad"
    ],
    "name:fas_x_preferred":[
        "\u0627\u062d\u0645\u062f\u0622\u0628\u0627\u062f"
    ],
    "name:fra_x_preferred":[
        "Ahmadabad"
    ],
    "name:ita_x_preferred":[
        "Ahmadabad"
    ],
    "name:kat_x_preferred":[
        "\u10d0\u10f0\u10db\u10d0\u10d3\u10d0\u10d1\u10d0\u10d3\u10d8"
    ],
    "name:swe_x_preferred":[
        "Ahmadabad"
    ],
    "name:urd_x_preferred":[
        "\u0627\u062d\u0645\u062f \u0622\u0628\u0627\u062f"
    ],
    "name:vie_x_preferred":[
        "Ahmadabad"
    ],
    "wof:name":"Ahmadabad",
    "wof:placetype":"locality"
},
  "geometry": {"coordinates":[84.40985000000001,24.81966],"type":"Point"}
}