{
  "type": "Feature",
  "properties": {
    "gn:admin1_code":"19.0",
    "gn:asciiname":"Khanderajuri",
    "gn:country_code":"IN",
    "gn:dem":597,
    "gn:feature_class":"P",
    "gn:feature_code":"PPL",
    "gn:name":"Khander\u0101juri",
    "gn:population":0,
    "gn:timezone":"Asia/Kolkata",
    "iso:country":"IN",
    "wof:name":"Khanderajuri",
    "wof:placetype":"locality"
},
  "geometry": {"coordinates":[74.72085,16.87032],"type":"Point"}
}