{
  "type": "Feature",
  "properties": {
    "iso:country":"IN",
    "ks:ks_alt_nam":"VADACHA MALA",
    "ks:ks_name":"Vadacha Mala",
    "ks:ks_pop":232,
    "ks:ks_type":"HABITATION",
    "name:eng_x_preferred":[
        "Vadacha Mala"
    ],
    "wof:name":"Vadacha Mala",
    "wof:placetype":"locality",
    "wof:population":232
},
  "geometry": {"coordinates":[74.35896,17.405812],"type":"Point"}
}