{
  "type": "Feature",
  "properties": {
    "iso:country":"IN",
    "ks:ks_name":"Bankheda",
    "ks:ks_pop":1073,
    "ks:ks_type":"VILLAGE",
    "ks:ks_uagg_main":0,
    "name:eng_x_preferred":[
        "Bankheda"
    ],
    "wof:name":"Bankheda",
    "wof:placetype":"neighbourhood",
    "wof:population":1073
},
  "geometry": {"coordinates":[77.206868,23.509006],"type":"Point"}
}