{
  "type": "Feature",
  "properties": {
    "iso:country":"IN",
    "ks:ks_name":"Tangeshwar",
    "ks:ks_pop":130,
    "ks:ks_type":"HABITATION",
    "name:eng_x_preferred":[
        "Tangeshwar"
    ],
    "wof:name":"Tangeshwar",
    "wof:placetype":"locality",
    "wof:population":130
},
  "geometry": {"coordinates":[86.675608,24.815557],"type":"Point"}
}