{
  "type": "Feature",
  "properties": {
    "iso:country":"IN",
    "ks:ks_name":"Kamtolipurwa",
    "ks:ks_pop":384,
    "ks:ks_type":"HABITATION",
    "name:eng_x_preferred":[
        "Kamtolipurwa"
    ],
    "wof:name":"Kamtolipurwa",
    "wof:placetype":"locality",
    "wof:population":384
},
  "geometry": {"coordinates":[80.13197099999999,29.740496],"type":"Point"}
}