{
  "type": "Feature",
  "properties": {
    "iso:country":"IN",
    "ks:ks_name":"Misran",
    "ks:ks_pop":240,
    "ks:ks_type":"HABITATION",
    "ks:ks_uagg_main":0,
    "name:eng_x_preferred":[
        "Misran"
    ],
    "wof:name":"Misran",
    "wof:placetype":"neighbourhood",
    "wof:population":240
},
  "geometry": {"coordinates":[81.996002,25.801021],"type":"Point"}
}