{
  "type": "Feature",
  "properties": {
    "iso:country":"IN",
    "qs:name":"Raikhad",
    "qs:name_adm0":"India",
    "qs:name_adm1":"Gujarat",
    "qs:photos":45,
    "qs:photos_1k":9,
    "qs:photos_9k":1,
    "qs:photos_9r":2,
    "qs:photos_all":45,
    "qs:photos_sr":2,
    "qs:placetype":"Suburb",
    "qs:pop_sr":"0",
    "wof:name":"Raikhad",
    "wof:placetype":"neighbourhood"
},
  "geometry": {"coordinates":[72.576928,23.021623],"type":"Point"}
}