{
  "type": "Feature",
  "properties": {
    "iso:country":"IN",
    "ks:ks_name":"Mavani Muvadi",
    "ks:ks_pop":412,
    "ks:ks_type":"VILLAGE",
    "name:eng_x_preferred":[
        "Mavani Muvadi"
    ],
    "wof:name":"Mavani Muvadi",
    "wof:placetype":"locality",
    "wof:population":412
},
  "geometry": {"coordinates":[72.911832,23.372436],"type":"Point"}
}