{
  "type": "Feature",
  "properties": {
    "gn:admin1_code":"37",
    "gn:admin2_code":"414.0",
    "gn:asciiname":"Mandradguda",
    "gn:country_code":"IN",
    "gn:dem":577,
    "gn:feature_class":"P",
    "gn:feature_code":"PPL",
    "gn:name":"Mandr\u0101dguda",
    "gn:population":0,
    "gn:timezone":"Asia/Kolkata",
    "iso:country":"IN",
    "wof:name":"Mandradguda",
    "wof:placetype":"neighbourhood"
},
  "geometry": {"coordinates":[82.05516,19.28207],"type":"Point"}
}