{
  "type": "Feature",
  "properties": {
    "iso:country":"IN",
    "ks:ks_name":"Gachhgerya",
    "ks:ks_pop":0,
    "ks:ks_type":"VILLAGE",
    "name:eng_x_preferred":[
        "Gachhgerya"
    ],
    "wof:name":"Gachhgerya",
    "wof:placetype":"locality",
    "wof:population":0
},
  "geometry": {"coordinates":[87.46262900000001,22.433881],"type":"Point"}
}