{
  "type": "Feature",
  "properties": {
    "iso:country":"IN",
    "ks:ks_name":"Boudhwadi",
    "ks:ks_pop":91,
    "ks:ks_type":"HABITATION",
    "name:eng_x_preferred":[
        "Boudhwadi"
    ],
    "wof:name":"Boudhwadi",
    "wof:placetype":"locality",
    "wof:population":91
},
  "geometry": {"coordinates":[73.646844,16.782489],"type":"Point"}
}