{
  "type": "Feature",
  "properties": {
    "iso:country":"IN",
    "ks:ks_name":"Dugineypalle",
    "ks:ks_pop":1852,
    "ks:ks_type":"VILLAGE",
    "name:eng_x_preferred":[
        "Dugineypalle"
    ],
    "wof:name":"Dugineypalle",
    "wof:placetype":"locality",
    "wof:population":1852
},
  "geometry": {"coordinates":[80.64101599999999,18.095688],"type":"Point"}
}