{
  "type": "Feature",
  "properties": {
    "gn:admin1_code":"37",
    "gn:admin2_code":"417.0",
    "gn:asciiname":"Cherkanti",
    "gn:country_code":"IN",
    "gn:dem":312,
    "gn:feature_class":"P",
    "gn:feature_code":"PPL",
    "gn:name":"Cherkanti",
    "gn:population":0,
    "gn:timezone":"Asia/Kolkata",
    "iso:country":"IN",
    "wof:name":"Cherkanti",
    "wof:placetype":"locality"
},
  "geometry": {"coordinates":[80.92756999999997,18.79563],"type":"Point"}
}