{
  "type": "Feature",
  "properties": {
    "gn:admin1_code":"9.0",
    "gn:admin2_code":"485.0",
    "gn:asciiname":"Walunda",
    "gn:country_code":"IN",
    "gn:dem":195,
    "gn:feature_class":"P",
    "gn:feature_code":"PPL",
    "gn:name":"Walunda",
    "gn:population":0,
    "gn:timezone":"Asia/Kolkata",
    "iso:country":"IN",
    "wof:name":"Walunda",
    "wof:placetype":"locality"
},
  "geometry": {"coordinates":[74.04379,23.26108],"type":"Point"}
}