{
  "type": "Feature",
  "properties": {
    "iso:country":"IN",
    "ks:ks_name":"Sellikaraipatti",
    "ks:ks_pop":104,
    "ks:ks_type":"HABITATION",
    "name:eng_x_preferred":[
        "Sellikaraipatti"
    ],
    "wof:name":"Sellikaraipatti",
    "wof:placetype":"locality",
    "wof:population":104
},
  "geometry": {"coordinates":[78.329148,10.097777],"type":"Point"}
}