{
  "type": "Feature",
  "properties": {
    "gn:admin1_code":"21.0",
    "gn:admin2_code":"384",
    "gn:asciiname":"Ghosar",
    "gn:country_code":"IN",
    "gn:dem":154,
    "gn:feature_class":"P",
    "gn:feature_code":"PPL",
    "gn:name":"Ghosar",
    "gn:population":0,
    "gn:timezone":"Asia/Kolkata",
    "iso:country":"IN",
    "wof:name":"Ghosar",
    "wof:placetype":"locality"
},
  "geometry": {"coordinates":[84.48495,20.95254],"type":"Point"}
}