{
  "type": "Feature",
  "properties": {
    "iso:country":"IN",
    "ks:ks_name":"Hatimara",
    "ks:ks_pop":98,
    "ks:ks_type":"VILLAGE",
    "ks:ks_uagg_main":0,
    "name:eng_x_preferred":[
        "Hatimara"
    ],
    "wof:name":"Hatimara",
    "wof:placetype":"neighbourhood",
    "wof:population":98
},
  "geometry": {"coordinates":[87.179891,21.733453],"type":"Point"}
}