{
  "type": "Feature",
  "properties": {
    "iso:country":"IN",
    "ks:ks_name":"Citigadekeri",
    "ks:ks_pop":90,
    "ks:ks_type":"HABITATION",
    "name:eng_x_preferred":[
        "Citigadekeri"
    ],
    "wof:name":"Citigadekeri",
    "wof:placetype":"locality",
    "wof:population":90
},
  "geometry": {"coordinates":[74.485203,14.369367],"type":"Point"}
}