{
  "type": "Feature",
  "properties": {
    "iso:country":"IN",
    "ks:ks_name":"Kandhakaithapalli",
    "ks:ks_pop":39,
    "ks:ks_type":"VILLAGE",
    "name:eng_x_preferred":[
        "Kandhakaithapalli"
    ],
    "wof:name":"Kandhakaithapalli",
    "wof:placetype":"locality",
    "wof:population":39
},
  "geometry": {"coordinates":[84.548597,19.721841],"type":"Point"}
}