{
  "type": "Feature",
  "properties": {
    "iso:country":"IN",
    "ks:ks_alt_nam":"Sengarwar hajarir",
    "ks:ks_name":"Sengarwar Hajarir",
    "ks:ks_pop":169,
    "ks:ks_type":"HABITATION",
    "name:eng_x_preferred":[
        "Sengarwar Hajarir"
    ],
    "wof:name":"Sengarwar Hajarir",
    "wof:placetype":"locality",
    "wof:population":169
},
  "geometry": {"coordinates":[81.719308,24.851228],"type":"Point"}
}