{
  "type": "Feature",
  "properties": {
    "iso:country":"IN",
    "ks:ks_name":"Uttar Paschim Para",
    "ks:ks_pop":1602,
    "ks:ks_type":"HABITATION",
    "name:eng_x_preferred":[
        "Uttar Paschim Para"
    ],
    "wof:name":"Uttar Paschim Para",
    "wof:placetype":"locality",
    "wof:population":1602
},
  "geometry": {"coordinates":[88.12396,21.637638],"type":"Point"}
}