{
  "type": "Feature",
  "properties": {
    "iso:country":"IN",
    "ks:ks_alt_nam":"Namdang  (Namdang  I)",
    "ks:ks_name":"Namdang (namdang I)",
    "ks:ks_pop":4,
    "ks:ks_type":"HABITATION",
    "name:eng_x_preferred":[
        "Namdang (namdang I)"
    ],
    "name:eng_x_variant":[
        "Namdang  (Namdang  I)"
    ],
    "wof:name":"Namdang (namdang I)",
    "wof:placetype":"locality",
    "wof:population":4
},
  "geometry": {"coordinates":[95.704356,27.249852],"type":"Point"}
}