{
  "type": "Feature",
  "properties": {
    "gn:admin1_code":"23.0",
    "gn:admin2_code":"52.0",
    "gn:asciiname":"Baronjian",
    "gn:country_code":"IN",
    "gn:dem":352,
    "gn:feature_class":"P",
    "gn:feature_code":"PPL",
    "gn:name":"Baronji\u0101n",
    "gn:population":0,
    "gn:timezone":"Asia/Kolkata",
    "iso:country":"IN",
    "ks:ks_alt_nam":"Baronji\u0101n",
    "ks:ks_name":"Baronjian",
    "ks:ks_pop":1444,
    "ks:ks_type":"VILLAGE",
    "name:eng_x_preferred":[
        "Baronjian"
    ],
    "name:eng_x_variant":[
        "Baronji\u0101n"
    ],
    "wof:name":"Baronjian",
    "wof:placetype":"locality",
    "wof:population":1444
},
  "geometry": {"coordinates":[76.733374,30.819212],"type":"Point"}
}