{
  "type": "Feature",
  "properties": {
    "iso:country":"IN",
    "ks:ks_name":"Pasiyan",
    "ks:ks_pop":670,
    "ks:ks_type":"HABITATION",
    "name:eng_x_preferred":[
        "Pasiyan"
    ],
    "wof:name":"Pasiyan",
    "wof:placetype":"locality",
    "wof:population":670
},
  "geometry": {"coordinates":[81.996055,25.205113],"type":"Point"}
}