{
  "type": "Feature",
  "properties": {
    "gn:admin1_code":"19.0",
    "gn:admin2_code":"570.0",
    "gn:asciiname":"Halimakki",
    "gn:country_code":"IN",
    "gn:dem":688,
    "gn:feature_class":"P",
    "gn:feature_code":"PPL",
    "gn:name":"Halimakki",
    "gn:population":0,
    "gn:timezone":"Asia/Kolkata",
    "iso:country":"IN",
    "ks:ks_name":"Halamakki",
    "ks:ks_pop":20,
    "ks:ks_type":"HABITATION",
    "name:eng_x_preferred":[
        "Halamakki"
    ],
    "name:eng_x_variant":[
        "Halimakki"
    ],
    "wof:name":"Halamakki",
    "wof:placetype":"locality",
    "wof:population":20
},
  "geometry": {"coordinates":[75.13782,13.323767],"type":"Point"}
}