{
  "type": "Feature",
  "properties": {
    "gn:admin1_code":"2.0",
    "gn:admin2_code":"544.0",
    "gn:asciiname":"Gundiru",
    "gn:country_code":"IN",
    "gn:dem":970,
    "gn:feature_class":"P",
    "gn:feature_code":"PPL",
    "gn:name":"Gund\u012bru",
    "gn:population":0,
    "gn:timezone":"Asia/Kolkata",
    "iso:country":"IN",
    "wof:name":"Gundiru",
    "wof:placetype":"locality"
},
  "geometry": {"coordinates":[82.63656999999998,18.0643],"type":"Point"}
}