{
  "type": "Feature",
  "properties": {
    "iso:country":"IN",
    "ks:ks_name":"Dhokshet",
    "ks:ks_pop":1115,
    "ks:ks_type":"VILLAGE",
    "name:eng_x_preferred":[
        "Dhokshet"
    ],
    "wof:name":"Dhokshet",
    "wof:placetype":"locality",
    "wof:population":1115
},
  "geometry": {"coordinates":[73.27421200000001,18.665405],"type":"Point"}
}