{
  "type": "Feature",
  "properties": {
    "gn:admin1_code":"11",
    "gn:admin2_code":"23.0",
    "gn:asciiname":"Dugb",
    "gn:country_code":"IN",
    "gn:dem":1943,
    "gn:feature_class":"P",
    "gn:feature_code":"PPL",
    "gn:name":"D\u016bgb",
    "gn:population":0,
    "gn:timezone":"Asia/Kolkata",
    "iso:country":"IN",
    "wof:name":"Dugb",
    "wof:placetype":"locality"
},
  "geometry": {"coordinates":[76.05985,32.51878],"type":"Point"}
}