{
  "type": "Feature",
  "properties": {
    "iso:country":"IN",
    "ks:ks_name":"Rampur Jaganpur",
    "ks:ks_pop":257,
    "ks:ks_type":"HABITATION",
    "name:eng_x_preferred":[
        "Rampur Jaganpur"
    ],
    "wof:name":"Rampur Jaganpur",
    "wof:placetype":"locality",
    "wof:population":257
},
  "geometry": {"coordinates":[82.62392699999999,26.553245],"type":"Point"}
}