{
  "type": "Feature",
  "properties": {
    "iso:country":"IN",
    "ks:ks_name":"Rasoolpur Araura",
    "ks:ks_pop":1104,
    "ks:ks_type":"VILLAGE",
    "ks:ks_uagg_main":0,
    "name:eng_x_preferred":[
        "Rasoolpur Araura"
    ],
    "wof:name":"Rasoolpur Araura",
    "wof:placetype":"neighbourhood",
    "wof:population":1104
},
  "geometry": {"coordinates":[79.024278,27.762818],"type":"Point"}
}