{
  "type": "Feature",
  "properties": {
    "gn:admin1_code":"16.0",
    "gn:admin2_code":"525",
    "gn:asciiname":"Gosaiwadi",
    "gn:country_code":"IN",
    "gn:dem":529,
    "gn:feature_class":"P",
    "gn:feature_code":"PPL",
    "gn:name":"Gos\u0101iw\u0101di",
    "gn:population":0,
    "gn:timezone":"Asia/Kolkata",
    "iso:country":"IN",
    "wof:name":"Gosaiwadi",
    "wof:placetype":"locality"
},
  "geometry": {"coordinates":[76.02464000000001,17.93908],"type":"Point"}
}