{
  "type": "Feature",
  "properties": {
    "gn:admin1_code":"13",
    "gn:admin2_code":"593.0",
    "gn:asciiname":"Vallappuzha",
    "gn:country_code":"IN",
    "gn:dem":49,
    "gn:feature_class":"P",
    "gn:feature_code":"PPL",
    "gn:name":"Vallappuzha",
    "gn:population":0,
    "gn:timezone":"Asia/Kolkata",
    "iso:country":"IN",
    "name:und_x_variant":[
        "Vallapputha",
        "Vallapula",
        "Vallappula",
        "Vallappuzha"
    ],
    "wof:name":"Vallappuzha",
    "wof:placetype":"locality"
},
  "geometry": {"coordinates":[76.25236,10.84028],"type":"Point"}
}