{
  "type": "Feature",
  "properties": {
    "gn:admin1_code":"19.0",
    "gn:admin2_code":"568",
    "gn:asciiname":"Anantapur",
    "gn:country_code":"IN",
    "gn:dem":649,
    "gn:feature_class":"P",
    "gn:feature_code":"PPL",
    "gn:name":"Anantapur",
    "gn:population":0,
    "gn:timezone":"Asia/Kolkata",
    "iso:country":"IN",
    "name:ara_x_preferred":[
        "\u0627\u0646\u0627\u0646\u062a\u0627\u0628\u0648\u0631"
    ],
    "name:bih_x_preferred":[
        "\u0905\u0928\u0902\u0924\u092a\u0941\u0930"
    ],
    "name:bpy_x_preferred":[
        "\u0985\u09a8\u09a8\u09cd\u09a4\u09aa\u09c1\u09b0"
    ],
    "name:cat_x_preferred":[
        "Anantapur"
    ],
    "name:ceb_x_preferred":[
        "Anantapur"
    ],
    "name:deu_x_preferred":[
        "Anantapur"
    ],
    "name:ell_x_preferred":[
        "\u0391\u03bd\u03ac\u03bd\u03c4\u03b1\u03c0\u03bf\u03c5\u03c1"
    ],
    "name:fas_x_preferred":[
        "\u0622\u0646\u0627\u0646\u062a\u0627\u067e\u0648\u0631"
    ],
    "name:fin_x_preferred":[
        "Anantapur"
    ],
    "name:fra_x_preferred":[
        "Anantapur"
    ],
    "name:hin_x_preferred":[
        "\u0905\u0928\u0902\u0924\u092a\u0942\u0930"
    ],
    "name:ita_x_preferred":[
        "Anantapur"
    ],
    "name:jpn_x_preferred":[
        "\u30a2\u30ca\u30f3\u30bf\u30d7\u30eb"
    ],
    "name:kan_x_preferred":[
        "\u0c85\u0ca8\u0c82\u0ca4\u0caa\u0cc1\u0cb0"
    ],
    "name:mar_x_preferred":[
        "\u0905\u0928\u0902\u0924\u092a\u0942\u0930"
    ],
    "name:new_x_preferred":[
        "\u0905\u0928\u0928\u094d\u0924\u092a\u0941\u0930"
    ],
    "name:ori_x_preferred":[
        "\u0b05\u0b28\u0b28\u0b4d\u0b24\u0b2a\u0b41\u0b30"
    ],
    "name:pnb_x_preferred":[
        "\u0627\u0646\u0646\u062a \u067e\u0648\u0631"
    ],
    "name:pol_x_preferred":[
        "Anantapur"
    ],
    "name:por_x_preferred":[
        "Anantapur"
    ],
    "name:rus_x_preferred":[
        "\u0410\u043d\u0430\u043d\u0442\u0430\u043f\u0443\u0440"
    ],
    "name:san_x_preferred":[
        "\u0905\u0928\u0928\u094d\u0924\u092a\u0941\u0930\u092e\u094d"
    ],
    "name:spa_x_preferred":[
        "Anantapur"
    ],
    "name:srp_x_preferred":[
        "\u0410\u043d\u0430\u043d\u0442\u0430\u043f\u0443\u0440"
    ],
    "name:swe_x_preferred":[
        "Anantapur"
    ],
    "name:tam_x_preferred":[
        "\u0b85\u0ba9\u0ba8\u0bcd\u0ba4\u0baa\u0bc2\u0bb0\u0bcd"
    ],
    "name:tcy_x_preferred":[
        "\u0c85\u0ca8\u0c82\u0ca4\u0caa\u0cc1\u0cb0"
    ],
    "name:tel_x_preferred":[
        "\u0c05\u0c28\u0c02\u0c24\u0c2a\u0c41\u0c30\u0c02"
    ],
    "name:tgl_x_preferred":[
        "Anantapur"
    ],
    "name:ukr_x_preferred":[
        "\u0410\u043d\u0430\u043d\u0442\u0430\u043f\u0443\u0440"
    ],
    "name:und_x_variant":[
        "Anand\u0101puram"
    ],
    "name:urd_x_preferred":[
        "\u0627\u0646\u0646\u062a\u067e\u0648\u0631"
    ],
    "name:vie_x_preferred":[
        "Anantapur"
    ],
    "name:war_x_preferred":[
        "Anantapur"
    ],
    "name:zho_x_preferred":[
        "\u963f\u7eb3\u6069\u5854\u666e\u5c14"
    ],
    "wof:name":"Anantapur",
    "wof:placetype":"locality"
},
  "geometry": {"coordinates":[75.21330999999998,14.07563],"type":"Point"}
}