{
  "type": "Feature",
  "properties": {
    "gn:admin1_code":"19.0",
    "gn:admin2_code":"568",
    "gn:asciiname":"Anantapur",
    "gn:country_code":"IN",
    "gn:dem":649,
    "gn:feature_class":"P",
    "gn:feature_code":"PPL",
    "gn:name":"Anantapur",
    "gn:population":0,
    "gn:timezone":"Asia/Kolkata",
    "iso:country":"IN",
    "name:und_x_variant":[
        "Anand\u0101puram"
    ],
    "wof:name":"Anantapur",
    "wof:placetype":"locality"
},
  "geometry": {"coordinates":[75.21330999999998,14.07563],"type":"Point"}
}