{
  "type": "Feature",
  "properties": {
    "iso:country":"IN",
    "ks:ks_name":"Pullelavaripalem",
    "ks:ks_pop":565,
    "ks:ks_type":"HABITATION",
    "name:eng_x_preferred":[
        "Pullelavaripalem"
    ],
    "wof:name":"Pullelavaripalem",
    "wof:placetype":"locality",
    "wof:population":565
},
  "geometry": {"coordinates":[81.886627,16.67002],"type":"Point"}
}