{
  "type": "Feature",
  "properties": {
    "gn:admin1_code":"34.0",
    "gn:admin2_code":"239.0",
    "gn:asciiname":"Sohi Chak",
    "gn:country_code":"IN",
    "gn:dem":65,
    "gn:feature_class":"P",
    "gn:feature_code":"PPL",
    "gn:name":"Sohi Chak",
    "gn:population":0,
    "gn:timezone":"Asia/Kolkata",
    "iso:country":"IN",
    "ks:ks_name":"Sohi Chak",
    "ks:ks_pop":293,
    "ks:ks_type":"VILLAGE",
    "ks:ks_uagg_main":0,
    "name:eng_x_preferred":[
        "Sohi Chak"
    ],
    "wof:name":"Sohi Chak",
    "wof:placetype":"neighbourhood",
    "wof:population":293
},
  "geometry": {"coordinates":[85.009928,25.262208],"type":"Point"}
}