{
  "type": "Feature",
  "properties": {
    "iso:country":"IN",
    "ks:ks_alt_nam":"Bidyapur supa",
    "ks:ks_name":"Bidyapur Supa",
    "ks:ks_pop":215,
    "ks:ks_type":"HABITATION",
    "name:eng_x_preferred":[
        "Bidyapur Supa"
    ],
    "wof:name":"Bidyapur Supa",
    "wof:placetype":"locality",
    "wof:population":215
},
  "geometry": {"coordinates":[91.48000500000001,26.630626],"type":"Point"}
}