{
  "type": "Feature",
  "properties": {
    "iso:country":"IN",
    "ks:ks_name":"Berasar",
    "ks:ks_pop":320,
    "ks:ks_type":"HABITATION",
    "name:eng_x_preferred":[
        "Berasar"
    ],
    "wof:name":"Berasar",
    "wof:placetype":"locality",
    "wof:population":320
},
  "geometry": {"coordinates":[72.37095100000001,27.949921],"type":"Point"}
}