{
  "type": "Feature",
  "properties": {
    "gn:admin1_code":"35.0",
    "gn:admin2_code":"455.0",
    "gn:asciiname":"Khapa",
    "gn:country_code":"IN",
    "gn:dem":1059,
    "gn:feature_class":"P",
    "gn:feature_code":"PPL",
    "gn:name":"Kh\u0101pa",
    "gn:population":0,
    "gn:timezone":"Asia/Kolkata",
    "iso:country":"IN",
    "wof:name":"Khapa",
    "wof:placetype":"locality"
},
  "geometry": {"coordinates":[78.51878000000001,22.27911],"type":"Point"}
}