{
  "type": "Feature",
  "properties": {
    "gn:admin1_code":"35.0",
    "gn:admin2_code":"455.0",
    "gn:asciiname":"Khapa",
    "gn:country_code":"IN",
    "gn:dem":1059,
    "gn:feature_class":"P",
    "gn:feature_code":"PPL",
    "gn:name":"Kh\u0101pa",
    "gn:population":0,
    "gn:timezone":"Asia/Kolkata",
    "iso:country":"IN",
    "name:ben_x_preferred":[
        "\u0996\u09be\u09aa\u09be"
    ],
    "name:bpy_x_preferred":[
        "\u0996\u09be\u09aa\u09be"
    ],
    "name:ind_x_preferred":[
        "Khapa"
    ],
    "name:ita_x_preferred":[
        "Khapa"
    ],
    "name:msa_x_preferred":[
        "Khapa"
    ],
    "name:new_x_preferred":[
        "\u0916\u092a\u093e"
    ],
    "name:nld_x_preferred":[
        "Khapa"
    ],
    "name:por_x_preferred":[
        "Khapa"
    ],
    "name:urd_x_preferred":[
        "\u06a9\u06be\u0627\u067e\u0627"
    ],
    "name:vie_x_preferred":[
        "Khapa"
    ],
    "wof:name":"Khapa",
    "wof:placetype":"locality"
},
  "geometry": {"coordinates":[78.51878000000001,22.27911],"type":"Point"}
}