{
  "type": "Feature",
  "properties": {
    "gn:admin1_code":"37",
    "gn:asciiname":"Dhini",
    "gn:country_code":"IN",
    "gn:dem":678,
    "gn:feature_class":"P",
    "gn:feature_code":"PPL",
    "gn:name":"Dh\u012bn\u012b",
    "gn:population":0,
    "gn:timezone":"Asia/Kolkata",
    "iso:country":"IN",
    "ks:ks_name":"Dhiri",
    "ks:ks_pop":42,
    "ks:ks_type":"HABITATION",
    "name:eng_x_preferred":[
        "Dhiri"
    ],
    "name:eng_x_variant":[
        "Dhini"
    ],
    "wof:name":"Dhiri",
    "wof:placetype":"locality",
    "wof:population":42
},
  "geometry": {"coordinates":[80.724739,21.481632],"type":"Point"}
}