{
  "type": "Feature",
  "properties": {
    "iso:country":"IN",
    "ks:ks_name":"Rautara",
    "ks:ks_pop":527,
    "ks:ks_type":"VILLAGE",
    "ks:ks_uagg_main":0,
    "name:eng_x_preferred":[
        "Rautara"
    ],
    "wof:name":"Rautara",
    "wof:placetype":"neighbourhood",
    "wof:population":527
},
  "geometry": {"coordinates":[87.727998,23.979127],"type":"Point"}
}