{
  "type": "Feature",
  "properties": {
    "iso:country":"IN",
    "ks:ks_name":"Mathadagadde",
    "ks:ks_pop":13,
    "ks:ks_type":"HABITATION",
    "name:eng_x_preferred":[
        "Mathadagadde"
    ],
    "wof:name":"Mathadagadde",
    "wof:placetype":"locality",
    "wof:population":13
},
  "geometry": {"coordinates":[74.83141999999999,14.278202],"type":"Point"}
}