{
  "type": "Feature",
  "properties": {
    "gn:country":"IN",
    "gn:fcode":"PPL",
    "gn:population":32380,
    "iso:country":"IN",
    "name:ast_x_preferred":[
        "Karamsad"
    ],
    "name:bpy_x_preferred":[
        "\u0995\u09b0\u09ae\u09b8\u09be\u09a6"
    ],
    "name:bul_x_preferred":[
        "\u041a\u0430\u0440\u0430\u043c\u0441\u0430\u0434"
    ],
    "name:ceb_x_preferred":[
        "Karamsad"
    ],
    "name:eng_x_preferred":[
        "Karamsad"
    ],
    "name:fra_x_preferred":[
        "Karamsad"
    ],
    "name:guj_x_preferred":[
        "\u0a95\u0ab0\u0aae\u0ab8\u0aa6"
    ],
    "name:hin_x_preferred":[
        "\u0915\u0930\u092e\u0938\u0926"
    ],
    "name:ita_x_preferred":[
        "Karamsad"
    ],
    "name:msa_x_preferred":[
        "Karamsad"
    ],
    "name:new_x_preferred":[
        "\u0915\u0930\u092e\u094d\u0938\u093e\u0926"
    ],
    "name:nld_x_preferred":[
        "Karamsad"
    ],
    "name:pam_x_preferred":[
        "Karamsad"
    ],
    "name:spa_x_preferred":[
        "Karamsad"
    ],
    "name:swe_x_preferred":[
        "Karamsad"
    ],
    "name:vie_x_preferred":[
        "Karamsad"
    ],
    "name:zho_x_preferred":[
        "\u5361\u62c9\u59c6\u8428\u5fb7"
    ],
    "qs_pg:aaroncc":"IN",
    "qs_pg:gn_country":"IN",
    "qs_pg:gn_fcode":"PPL",
    "qs_pg:gn_pop":32380,
    "qs_pg:name":"Karmad",
    "qs_pg:name_adm0":"India",
    "qs_pg:name_adm1":"Gujarat",
    "qs_pg:photos_9r":0,
    "qs_pg:photos_sr":0,
    "qs_pg:pop_sr":7,
    "qs_pg:qs_pg_placetype":"locality",
    "qs_pg:qs_pg_placetype_gp":"Town",
    "qs_pg:woe_adm0":23424848,
    "woe:adm0_id":23424848,
    "woe:name_adm0":"India",
    "woe:name_adm1":"Gujarat",
    "woe:placetype":"Town",
    "wof:name":"Karmad",
    "wof:placetype":"neighbourhood",
    "wof:population":32380
},
  "geometry": {"coordinates":[72.90392,22.54243],"type":"Point"}
}