{
  "type": "Feature",
  "properties": {
    "iso:country":"IN",
    "ks:ks_alt_nam":"aeramthotam",
    "ks:ks_name":"Aeramthotam",
    "ks:ks_pop":318,
    "ks:ks_type":"HABITATION",
    "name:eng_x_preferred":[
        "Aeramthotam"
    ],
    "wof:name":"Aeramthotam",
    "wof:placetype":"locality",
    "wof:population":318
},
  "geometry": {"coordinates":[75.778729,11.594858],"type":"Point"}
}