{
  "type": "Feature",
  "properties": {
    "iso:country":"IN",
    "ks:ks_name":"Chak Abdul Ghani",
    "ks:ks_pop":1435,
    "ks:ks_type":"VILLAGE",
    "name:eng_x_preferred":[
        "Chak Abdul Ghani"
    ],
    "wof:name":"Chak Abdul Ghani",
    "wof:placetype":"locality",
    "wof:population":1435
},
  "geometry": {"coordinates":[85.45831699999999,25.732442],"type":"Point"}
}