{
  "type": "Feature",
  "properties": {
    "gn:admin1_code":"36.0",
    "gn:admin2_code":"155.0",
    "gn:asciiname":"Lohkanpur",
    "gn:country_code":"IN",
    "gn:dem":148,
    "gn:feature_class":"P",
    "gn:feature_code":"PPL",
    "gn:name":"Lohkanpur",
    "gn:population":0,
    "gn:timezone":"Asia/Kolkata",
    "iso:country":"IN",
    "ks:ks_name":"Lohkanpur",
    "ks:ks_pop":531,
    "ks:ks_type":"VILLAGE",
    "ks:ks_uagg_main":0,
    "name:eng_x_preferred":[
        "Lohkanpur"
    ],
    "wof:name":"Lohkanpur",
    "wof:placetype":"neighbourhood",
    "wof:population":531
},
  "geometry": {"coordinates":[80.172372,27.530968],"type":"Point"}
}