{
  "type": "Feature",
  "properties": {
    "iso:country":"IN",
    "ks:ks_name":"Jadhav Pawar Wasti",
    "ks:ks_pop":494,
    "ks:ks_type":"HABITATION",
    "name:eng_x_preferred":[
        "Jadhav Pawar Wasti"
    ],
    "wof:name":"Jadhav Pawar Wasti",
    "wof:placetype":"locality",
    "wof:population":494
},
  "geometry": {"coordinates":[74.259835,18.834839],"type":"Point"}
}