{
  "type": "Feature",
  "properties": {
    "iso:country":"IN",
    "ks:ks_name":"Jyotirling Wasti",
    "ks:ks_pop":107,
    "ks:ks_type":"HABITATION",
    "name:eng_x_preferred":[
        "Jyotirling Wasti"
    ],
    "wof:name":"Jyotirling Wasti",
    "wof:placetype":"locality",
    "wof:population":107
},
  "geometry": {"coordinates":[74.24415500000001,18.281034],"type":"Point"}
}