{
  "type": "Feature",
  "properties": {
    "iso:country":"IN",
    "ks:ks_name":"Janagadapalli",
    "ks:ks_pop":63,
    "ks:ks_type":"HABITATION",
    "name:eng_x_preferred":[
        "Janagadapalli"
    ],
    "wof:name":"Janagadapalli",
    "wof:placetype":"locality",
    "wof:population":63
},
  "geometry": {"coordinates":[82.807878,18.029994],"type":"Point"}
}