{
  "type": "Feature",
  "properties": {
    "gn:admin1_code":"36.0",
    "gn:admin2_code":"183.0",
    "gn:asciiname":"Hardayal Singh",
    "gn:country_code":"IN",
    "gn:dem":107,
    "gn:feature_class":"P",
    "gn:feature_code":"PPL",
    "gn:name":"Harday\u0101l Singh",
    "gn:population":0,
    "gn:timezone":"Asia/Kolkata",
    "iso:country":"IN",
    "name:fin_x_preferred":[
        "Hardayal Singh"
    ],
    "name:hun_x_preferred":[
        "Hardyal Singh"
    ],
    "name:nor_x_preferred":[
        "Hardyal Singh"
    ],
    "wof:name":"Hardayal Singh",
    "wof:placetype":"locality"
},
  "geometry": {"coordinates":[81.67313,27.09319],"type":"Point"}
}