{
  "type": "Feature",
  "properties": {
    "iso:country":"IN",
    "ks:ks_name":"Panchmohali",
    "ks:ks_pop":451,
    "ks:ks_type":"VILLAGE",
    "name:eng_x_preferred":[
        "Panchmohali"
    ],
    "wof:name":"Panchmohali",
    "wof:placetype":"locality",
    "wof:population":451
},
  "geometry": {"coordinates":[86.94107,23.899741],"type":"Point"}
}