{
  "type": "Feature",
  "properties": {
    "gn:admin1_code":"34.0",
    "gn:admin2_code":"222.0",
    "gn:asciiname":"Gamharia",
    "gn:country_code":"IN",
    "gn:dem":44,
    "gn:feature_class":"P",
    "gn:feature_code":"PPL",
    "gn:name":"Gamharia",
    "gn:population":0,
    "gn:timezone":"Asia/Kolkata",
    "iso:country":"IN",
    "ks:ks_name":"Gamharia",
    "ks:ks_pop":102,
    "ks:ks_type":"VILLAGE",
    "ks:ks_uagg_main":0,
    "name:eng_x_preferred":[
        "Gamharia"
    ],
    "name:hif_x_preferred":[
        "Gamhari"
    ],
    "name:hin_x_preferred":[
        "\u0917\u092e\u094d\u0939\u0930\u093f\u092f\u093e"
    ],
    "wof:name":"Gamharia",
    "wof:placetype":"neighbourhood",
    "wof:population":102
},
  "geometry": {"coordinates":[86.19896,25.583675],"type":"Point"}
}