{
  "type": "Feature",
  "properties": {
    "iso:country":"IN",
    "ks:ks_alt_nam":"HUSAMBU",
    "ks:ks_name":"Husambu",
    "ks:ks_pop":281,
    "ks:ks_type":"HABITATION",
    "name:eng_x_preferred":[
        "Husambu"
    ],
    "wof:name":"Husambu",
    "wof:placetype":"locality",
    "wof:population":281
},
  "geometry": {"coordinates":[84.22163999999999,23.404439],"type":"Point"}
}