{
  "type": "Feature",
  "properties": {
    "gn:admin1_code":"34.0",
    "gn:admin2_code":"218.0",
    "gn:asciiname":"Pipra Kalan",
    "gn:country_code":"IN",
    "gn:dem":64,
    "gn:feature_class":"P",
    "gn:feature_code":"PPL",
    "gn:name":"Pipra Kal\u0101n",
    "gn:population":0,
    "gn:timezone":"Asia/Kolkata",
    "iso:country":"IN",
    "ks:ks_alt_nam":"Pipra Kal\u0101n",
    "ks:ks_name":"Pipra Kalan",
    "ks:ks_pop":1054,
    "ks:ks_type":"VILLAGE",
    "ks:ks_uagg_main":0,
    "name:eng_x_preferred":[
        "Pipra Kalan"
    ],
    "name:eng_x_variant":[
        "Pipra Kal\u0101n"
    ],
    "wof:name":"Pipra Kalan",
    "wof:placetype":"neighbourhood",
    "wof:population":1054
},
  "geometry": {"coordinates":[84.56499599999999,26.059379],"type":"Point"}
}