{
  "type": "Feature",
  "properties": {
    "iso:country":"IN",
    "ks:ks_name":"Kamar Gerya",
    "ks:ks_pop":362,
    "ks:ks_type":"VILLAGE",
    "name:eng_x_preferred":[
        "Kamar Gerya"
    ],
    "wof:name":"Kamar Gerya",
    "wof:placetype":"locality",
    "wof:population":362
},
  "geometry": {"coordinates":[87.40205,22.523339],"type":"Point"}
}