{
  "type": "Feature",
  "properties": {
    "iso:country":"IN",
    "ks:ks_name":"Meusa",
    "ks:ks_pop":193,
    "ks:ks_type":"VILLAGE",
    "ks:ks_uagg_main":0,
    "name:eng_x_preferred":[
        "Meusa"
    ],
    "wof:name":"Meusa",
    "wof:placetype":"neighbourhood",
    "wof:population":193
},
  "geometry": {"coordinates":[83.239169,26.621512],"type":"Point"}
}