{
  "type": "Feature",
  "properties": {
    "gn:admin1_code":"34.0",
    "gn:admin2_code":"234.0",
    "gn:asciiname":"Chiksil",
    "gn:country_code":"IN",
    "gn:dem":91,
    "gn:feature_class":"P",
    "gn:feature_code":"PPL",
    "gn:name":"Chiksil",
    "gn:population":0,
    "gn:timezone":"Asia/Kolkata",
    "iso:country":"IN",
    "ks:ks_name":"Chiksil",
    "ks:ks_pop":2006,
    "ks:ks_type":"VILLAGE",
    "name:eng_x_preferred":[
        "Chiksil"
    ],
    "wof:name":"Chiksil",
    "wof:placetype":"locality",
    "wof:population":2006
},
  "geometry": {"coordinates":[84.340276,25.193181],"type":"Point"}
}