{
  "type": "Feature",
  "properties": {
    "iso:country":"IN",
    "ks:ks_name":"Bhoivada Faliya",
    "ks:ks_pop":360,
    "ks:ks_type":"HABITATION",
    "name:eng_x_preferred":[
        "Bhoivada Faliya"
    ],
    "wof:name":"Bhoivada Faliya",
    "wof:placetype":"locality",
    "wof:population":360
},
  "geometry": {"coordinates":[73.441444,23.138806],"type":"Point"}
}