{
  "type": "Feature",
  "properties": {
    "iso:country":"IN",
    "ks:ks_alt_nam":"Bholainagavade wasti",
    "ks:ks_name":"Bholainagavade Wasti",
    "ks:ks_pop":154,
    "ks:ks_type":"HABITATION",
    "name:eng_x_preferred":[
        "Bholainagavade Wasti"
    ],
    "wof:name":"Bholainagavade Wasti",
    "wof:placetype":"locality",
    "wof:population":154
},
  "geometry": {"coordinates":[74.11473100000001,18.536941],"type":"Point"}
}