{
  "type": "Feature",
  "properties": {
    "iso:country":"IN",
    "ks:ks_name":"Parkarwadi",
    "ks:ks_pop":61,
    "ks:ks_type":"HABITATION",
    "name:eng_x_preferred":[
        "Parkarwadi"
    ],
    "wof:name":"Parkarwadi",
    "wof:placetype":"locality",
    "wof:population":61
},
  "geometry": {"coordinates":[73.52739800000001,16.364502],"type":"Point"}
}