{
  "type": "Feature",
  "properties": {
    "iso:country":"IN",
    "ks:ks_name":"Chakla",
    "ks:ks_pop":1045,
    "ks:ks_type":"VILLAGE",
    "name:eng_x_preferred":[
        "Chakla"
    ],
    "wof:name":"Chakla",
    "wof:placetype":"locality",
    "wof:population":1045
},
  "geometry": {"coordinates":[84.75004300000001,24.36867],"type":"Point"}
}