{
  "type": "Feature",
  "properties": {
    "iso:country":"IN",
    "ks:ks_name":"Nakanwasti",
    "ks:ks_pop":200,
    "ks:ks_type":"HABITATION",
    "name:eng_x_preferred":[
        "Nakanwasti"
    ],
    "wof:name":"Nakanwasti",
    "wof:placetype":"locality",
    "wof:population":200
},
  "geometry": {"coordinates":[74.874775,18.731887],"type":"Point"}
}