{
  "type": "Feature",
  "properties": {
    "gn:admin1_code":"31.0",
    "gn:admin2_code":"286.0",
    "gn:asciiname":"South Kanghmun",
    "gn:country_code":"IN",
    "gn:dem":795,
    "gn:feature_class":"P",
    "gn:feature_code":"PPL",
    "gn:name":"South Kanghmun",
    "gn:population":0,
    "gn:timezone":"Asia/Kolkata",
    "iso:country":"IN",
    "wof:name":"South Kanghmun",
    "wof:placetype":"locality"
},
  "geometry": {"coordinates":[92.74037,23.21416],"type":"Point"}
}