{
  "type": "Feature",
  "properties": {
    "gn:admin1_code":"19.0",
    "gn:admin2_code":"563.0",
    "gn:asciiname":"Abbolli",
    "gn:country_code":"IN",
    "gn:dem":56,
    "gn:feature_class":"P",
    "gn:feature_code":"PPL",
    "gn:name":"Abbolli",
    "gn:population":0,
    "gn:timezone":"Asia/Kolkata",
    "iso:country":"IN",
    "ks:ks_name":"Abbolli",
    "ks:ks_pop":106,
    "ks:ks_type":"VILLAGE",
    "name:eng_x_preferred":[
        "Abbolli"
    ],
    "name:fas_x_preferred":[
        "\u0627\u0628\u0648\u0644\u06cc"
    ],
    "name:vie_x_preferred":[
        "Abbolli"
    ],
    "wof:name":"Abbolli",
    "wof:placetype":"locality",
    "wof:population":106
},
  "geometry": {"coordinates":[74.579116,14.402484],"type":"Point"}
}