{
  "type": "Feature",
  "properties": {
    "iso:country":"IN",
    "ks:ks_name":"Erukulapalle",
    "ks:ks_pop":22,
    "ks:ks_type":"HABITATION",
    "name:eng_x_preferred":[
        "Erukulapalle"
    ],
    "wof:name":"Erukulapalle",
    "wof:placetype":"locality",
    "wof:population":22
},
  "geometry": {"coordinates":[79.014109,13.766211],"type":"Point"}
}