{
  "type": "Feature",
  "properties": {
    "iso:country":"IN",
    "ks:ks_name":"Tompalapadu",
    "ks:ks_pop":283,
    "ks:ks_type":"HABITATION",
    "name:eng_x_preferred":[
        "Tompalapadu"
    ],
    "wof:name":"Tompalapadu",
    "wof:placetype":"locality",
    "wof:population":283
},
  "geometry": {"coordinates":[83.798711,18.846896],"type":"Point"}
}