{
  "type": "Feature",
  "properties": {
    "gn:admin1_code":"35.0",
    "gn:admin2_code":"437.0",
    "gn:asciiname":"Charbarli",
    "gn:country_code":"IN",
    "gn:dem":563,
    "gn:feature_class":"P",
    "gn:feature_code":"PPL",
    "gn:name":"Ch\u0101rbarli",
    "gn:population":0,
    "gn:timezone":"Asia/Kolkata",
    "iso:country":"IN",
    "ks:ks_alt_nam":"Ch\u0101rbarli",
    "ks:ks_name":"Charbarli",
    "ks:ks_pop":822,
    "ks:ks_type":"VILLAGE",
    "name:eng_x_preferred":[
        "Charbarli"
    ],
    "name:eng_x_variant":[
        "Ch\u0101rbarli"
    ],
    "wof:name":"Charbarli",
    "wof:placetype":"locality",
    "wof:population":822
},
  "geometry": {"coordinates":[76.291314,22.62297],"type":"Point"}
}