{
  "type": "Feature",
  "properties": {
    "gn:admin1_code":"36",
    "gn:admin2_code":"162.0",
    "gn:asciiname":"Gyani",
    "gn:country_code":"IN",
    "gn:dem":144,
    "gn:feature_class":"P",
    "gn:feature_code":"PPL",
    "gn:name":"Gy\u0101ni",
    "gn:population":0,
    "gn:timezone":"Asia/Kolkata",
    "iso:country":"IN",
    "name:fra_x_preferred":[
        "Giani"
    ],
    "name:por_x_preferred":[
        "Gyani"
    ],
    "wof:name":"Gyani",
    "wof:placetype":"neighbourhood"
},
  "geometry": {"coordinates":[79.69522000000001,26.74656],"type":"Point"}
}