{
  "type": "Feature",
  "properties": {
    "gn:admin1_code":"36",
    "gn:admin2_code":"146.0",
    "gn:asciiname":"Nagla Hasnu",
    "gn:country_code":"IN",
    "gn:dem":185,
    "gn:feature_class":"P",
    "gn:feature_code":"PPL",
    "gn:name":"Nagla Hasnu",
    "gn:population":0,
    "gn:timezone":"Asia/Kolkata",
    "iso:country":"IN",
    "wof:name":"Nagla Hasnu",
    "wof:placetype":"locality"
},
  "geometry": {"coordinates":[77.55894000000001,26.90567],"type":"Point"}
}