{
  "type": "Feature",
  "properties": {
    "gn:admin1_code":"19.0",
    "gn:admin2_code":"569.0",
    "gn:asciiname":"Pithbail",
    "gn:country_code":"IN",
    "gn:dem":630,
    "gn:feature_class":"P",
    "gn:feature_code":"PPL",
    "gn:name":"Pithbail",
    "gn:population":0,
    "gn:timezone":"Asia/Kolkata",
    "iso:country":"IN",
    "wof:name":"Pithbail",
    "wof:placetype":"locality"
},
  "geometry": {"coordinates":[75.08450000000001,13.38738],"type":"Point"}
}