{
  "type": "Feature",
  "properties": {
    "iso:country":"IN",
    "ks:ks_name":"Sundar Singh",
    "ks:ks_pop":508,
    "ks:ks_type":"HABITATION",
    "name:eng_x_preferred":[
        "Sundar Singh"
    ],
    "wof:name":"Sundar Singh",
    "wof:placetype":"locality",
    "wof:population":508
},
  "geometry": {"coordinates":[82.171578,27.080503],"type":"Point"}
}