{
  "type": "Feature",
  "properties": {
    "gn:admin1_code":"2.0",
    "gn:admin2_code":"549.0",
    "gn:asciiname":"Peddaparti Ankireddipalem",
    "gn:country_code":"IN",
    "gn:dem":19,
    "gn:feature_class":"P",
    "gn:feature_code":"PPL",
    "gn:name":"Peddaparti Ankireddipalem",
    "gn:population":0,
    "gn:timezone":"Asia/Kolkata",
    "iso:country":"IN",
    "wof:name":"Peddaparti Ankireddipalem",
    "wof:placetype":"locality"
},
  "geometry": {"coordinates":[80.20968000000001,15.90655],"type":"Point"}
}