{
  "type": "Feature",
  "properties": {
    "iso:country":"IN",
    "ks:ks_alt_nam":"MALIBHAG",
    "ks:ks_name":"Malibhag",
    "ks:ks_pop":112,
    "ks:ks_type":"HABITATION",
    "name:eng_x_preferred":[
        "Malibhag"
    ],
    "wof:name":"Malibhag",
    "wof:placetype":"locality",
    "wof:population":112
},
  "geometry": {"coordinates":[74.44678500000001,16.978136],"type":"Point"}
}