{
  "type": "Feature",
  "properties": {
    "iso:country":"IN",
    "ks:ks_name":"Uttarchak",
    "ks:ks_pop":371,
    "ks:ks_type":"VILLAGE",
    "name:eng_x_preferred":[
        "Uttarchak"
    ],
    "wof:name":"Uttarchak",
    "wof:placetype":"locality",
    "wof:population":371
},
  "geometry": {"coordinates":[86.858845,21.413143],"type":"Point"}
}