{
  "type": "Feature",
  "properties": {
    "iso:country":"IN",
    "ks:ks_name":"Jalash L",
    "ks:ks_pop":10,
    "ks:ks_type":"HABITATION",
    "name:eng_x_preferred":[
        "Jalash L"
    ],
    "wof:name":"Jalash L",
    "wof:placetype":"locality",
    "wof:population":10
},
  "geometry": {"coordinates":[85.517022,20.922177],"type":"Point"}
}