{
  "type": "Feature",
  "properties": {
    "gn:admin1_code":"2.0",
    "gn:admin2_code":"551.0",
    "gn:asciiname":"Kolikavaripalli",
    "gn:country_code":"IN",
    "gn:dem":156,
    "gn:feature_class":"P",
    "gn:feature_code":"PPL",
    "gn:name":"Kolikav\u0101ripalli",
    "gn:population":0,
    "gn:timezone":"Asia/Kolkata",
    "iso:country":"IN",
    "name:und_x_variant":[
        "Kolikav\u0101ripalli",
        "Boyapalli"
    ],
    "wof:name":"Kolikavaripalli",
    "wof:placetype":"neighbourhood"
},
  "geometry": {"coordinates":[79.06371,14.30614],"type":"Point"}
}