{
  "type": "Feature",
  "properties": {
    "iso:country":"IN",
    "ks:ks_name":"Gulampurwa",
    "ks:ks_pop":177,
    "ks:ks_type":"HABITATION",
    "ks:ks_uagg_main":0,
    "name:eng_x_preferred":[
        "Gulampurwa"
    ],
    "wof:name":"Gulampurwa",
    "wof:placetype":"neighbourhood",
    "wof:population":177
},
  "geometry": {"coordinates":[81.48099499999999,27.254815],"type":"Point"}
}