{
  "type": "Feature",
  "properties": {
    "iso:country":"IN",
    "ks:ks_name":"Mavinahalli",
    "ks:ks_pop":129,
    "ks:ks_type":"HABITATION",
    "name:eng_x_preferred":[
        "Mavinahalli"
    ],
    "wof:name":"Mavinahalli",
    "wof:placetype":"locality",
    "wof:population":129
},
  "geometry": {"coordinates":[75.69307999999999,13.249455],"type":"Point"}
}