{
  "type": "Feature",
  "properties": {
    "iso:country":"IN",
    "ks:ks_name":"Dakshin Chagalmarabond",
    "ks:ks_pop":678,
    "ks:ks_type":"HABITATION",
    "name:eng_x_preferred":[
        "Dakshin Chagalmarabond"
    ],
    "wof:name":"Dakshin Chagalmarabond",
    "wof:placetype":"locality",
    "wof:population":678
},
  "geometry": {"coordinates":[92.318787,24.381877],"type":"Point"}
}