{
  "type": "Feature",
  "properties": {
    "iso:country":"IN",
    "ks:ks_name":"Bishunpur",
    "ks:ks_pop":944,
    "ks:ks_type":"VILLAGE",
    "name:eng_x_preferred":[
        "Bishunpur"
    ],
    "wof:name":"Bishunpur",
    "wof:placetype":"locality",
    "wof:population":944
},
  "geometry": {"coordinates":[85.37774400000001,26.245924],"type":"Point"}
}