{
  "type": "Feature",
  "properties": {
    "iso:country":"IN",
    "ks:ks_name":"Turka",
    "ks:ks_pop":12,
    "ks:ks_type":"HABITATION",
    "name:eng_x_preferred":[
        "Turka"
    ],
    "wof:name":"Turka",
    "wof:placetype":"locality",
    "wof:population":12
},
  "geometry": {"coordinates":[81.871717,24.654682],"type":"Point"}
}