{
  "type": "Feature",
  "properties": {
    "gn:admin1_code":"19",
    "gn:admin2_code":"563.0",
    "gn:asciiname":"Hallikop",
    "gn:country_code":"IN",
    "gn:dem":555,
    "gn:feature_class":"P",
    "gn:feature_code":"PPL",
    "gn:name":"Hallikop",
    "gn:population":0,
    "gn:timezone":"Asia/Kolkata",
    "iso:country":"IN",
    "wof:name":"Hallikop",
    "wof:placetype":"locality"
},
  "geometry": {"coordinates":[74.90042,14.72397],"type":"Point"}
}