{
  "type": "Feature",
  "properties": {
    "iso:country":"IN",
    "ks:ks_name":"Mondal Santra Kayal Para",
    "ks:ks_pop":696,
    "ks:ks_type":"HABITATION",
    "name:eng_x_preferred":[
        "Mondal Santra Kayal Para"
    ],
    "wof:name":"Mondal Santra Kayal Para",
    "wof:placetype":"locality",
    "wof:population":696
},
  "geometry": {"coordinates":[88.222813,22.375973],"type":"Point"}
}