{
  "type": "Feature",
  "properties": {
    "iso:country":"IN",
    "ks:ks_name":"Sanaswadi",
    "ks:ks_pop":551,
    "ks:ks_type":"HABITATION",
    "name:eng_x_preferred":[
        "Sanaswadi"
    ],
    "wof:name":"Sanaswadi",
    "wof:placetype":"locality",
    "wof:population":551
},
  "geometry": {"coordinates":[74.000174,18.231875],"type":"Point"}
}