{
  "type": "Feature",
  "properties": {
    "iso:country":"IN",
    "ks:ks_name":"Ac Colony",
    "ks:ks_pop":202,
    "ks:ks_type":"HABITATION",
    "name:eng_x_preferred":[
        "Ac Colony"
    ],
    "wof:name":"Ac Colony",
    "wof:placetype":"locality",
    "wof:population":202
},
  "geometry": {"coordinates":[78.942925,12.835243],"type":"Point"}
}