{
  "type": "Feature",
  "properties": {
    "iso:country":"IN",
    "ks:ks_name":"Bhadibathan",
    "ks:ks_pop":199,
    "ks:ks_type":"HABITATION",
    "name:eng_x_preferred":[
        "Bhadibathan"
    ],
    "wof:name":"Bhadibathan",
    "wof:placetype":"locality",
    "wof:population":199
},
  "geometry": {"coordinates":[82.948463,24.567238],"type":"Point"}
}