{
  "type": "Feature",
  "properties": {
    "iso:country":"IN",
    "ks:ks_name":"Nagla Roopram",
    "ks:ks_pop":200,
    "ks:ks_type":"HABITATION",
    "name:eng_x_preferred":[
        "Nagla Roopram"
    ],
    "wof:name":"Nagla Roopram",
    "wof:placetype":"locality",
    "wof:population":200
},
  "geometry": {"coordinates":[77.260378,26.973246],"type":"Point"}
}