{
  "type": "Feature",
  "properties": {
    "iso:country":"IN",
    "ks:ks_name":"Phumen Ingti",
    "ks:ks_pop":181,
    "ks:ks_type":"HABITATION",
    "name:eng_x_preferred":[
        "Phumen Ingti"
    ],
    "wof:name":"Phumen Ingti",
    "wof:placetype":"locality",
    "wof:population":181
},
  "geometry": {"coordinates":[93.37688300000001,25.87513],"type":"Point"}
}