{
  "type": "Feature",
  "properties": {
    "gn:admin1_code":"35",
    "gn:admin2_code":"455.0",
    "gn:asciiname":"Murra",
    "gn:country_code":"IN",
    "gn:dem":649,
    "gn:feature_class":"P",
    "gn:feature_code":"PPL",
    "gn:name":"Murra",
    "gn:population":0,
    "gn:timezone":"Asia/Kolkata",
    "iso:country":"IN",
    "ks:ks_name":"Murra",
    "ks:ks_pop":869,
    "ks:ks_type":"HABITATION",
    "name:eng_x_preferred":[
        "Murra"
    ],
    "wof:name":"Murra",
    "wof:placetype":"locality",
    "wof:population":869
},
  "geometry": {"coordinates":[79.059189,21.822788],"type":"Point"}
}