{
  "type": "Feature",
  "properties": {
    "iso:country":"IN",
    "ks:ks_name":"Upparalli",
    "ks:ks_pop":482,
    "ks:ks_type":"HABITATION",
    "name:eng_x_preferred":[
        "Upparalli"
    ],
    "wof:name":"Upparalli",
    "wof:placetype":"locality",
    "wof:population":482
},
  "geometry": {"coordinates":[74.656733,13.781828],"type":"Point"}
}