{
  "type": "Feature",
  "properties": {
    "gn:admin1_code":"24.0",
    "gn:admin2_code":"128.0",
    "gn:asciiname":"Amroli",
    "gn:country_code":"IN",
    "gn:dem":332,
    "gn:feature_class":"P",
    "gn:feature_code":"PPL",
    "gn:name":"Amroli",
    "gn:population":0,
    "gn:timezone":"Asia/Kolkata",
    "iso:country":"IN",
    "name:ceb_x_preferred":[
        "Amroli"
    ],
    "name:fas_x_preferred":[
        "\u0627\u0645\u0631\u0648\u0644\u06cc"
    ],
    "name:guj_x_preferred":[
        "\u0a85\u0aae\u0ab0\u0acb\u0ab2\u0ac0"
    ],
    "name:swe_x_preferred":[
        "Amroli"
    ],
    "name:tam_x_preferred":[
        "\u0b85\u0bae\u0bcd\u0bb0\u0bcb\u0bb2\u0bbf"
    ],
    "wof:name":"Amroli",
    "wof:placetype":"locality"
},
  "geometry": {"coordinates":[76.87021,25.19139],"type":"Point"}
}