{
  "type": "Feature",
  "properties": {
    "iso:country":"IN",
    "ks:ks_name":"Hiratalavdi",
    "ks:ks_pop":1838,
    "ks:ks_type":"HABITATION",
    "name:eng_x_preferred":[
        "Hiratalavdi"
    ],
    "wof:name":"Hiratalavdi",
    "wof:placetype":"locality",
    "wof:population":1838
},
  "geometry": {"coordinates":[73.1285,22.602611],"type":"Point"}
}