{
  "type": "Feature",
  "properties": {
    "gn:admin1_code":"16",
    "gn:admin2_code":"503.0",
    "gn:asciiname":"Kotmi",
    "gn:country_code":"IN",
    "gn:dem":776,
    "gn:feature_class":"P",
    "gn:feature_code":"PPL",
    "gn:name":"Kotmi",
    "gn:population":0,
    "gn:timezone":"Asia/Kolkata",
    "iso:country":"IN",
    "wof:name":"Kotmi",
    "wof:placetype":"locality"
},
  "geometry": {"coordinates":[77.55094,21.6145],"type":"Point"}
}