{
  "type": "Feature",
  "properties": {
    "iso:country":"IN",
    "ks:ks_name":"Chandpur",
    "ks:ks_pop":182,
    "ks:ks_type":"VILLAGE",
    "name:eng_x_preferred":[
        "Chandpur"
    ],
    "wof:name":"Chandpur",
    "wof:placetype":"locality",
    "wof:population":182
},
  "geometry": {"coordinates":[76.455298,31.127716],"type":"Point"}
}