{
  "type": "Feature",
  "properties": {
    "iso:country":"IN",
    "ks:ks_name":"Badalasahi",
    "ks:ks_pop":95,
    "ks:ks_type":"VILLAGE",
    "name:eng_x_preferred":[
        "Badalasahi"
    ],
    "wof:name":"Badalasahi",
    "wof:placetype":"locality",
    "wof:population":95
},
  "geometry": {"coordinates":[84.33332299999999,20.474926],"type":"Point"}
}