{
  "type": "Feature",
  "properties": {
    "iso:country":"IN",
    "ks:ks_name":"Saruapani",
    "ks:ks_pop":115,
    "ks:ks_type":"VILLAGE",
    "name:eng_x_preferred":[
        "Saruapani"
    ],
    "wof:name":"Saruapani",
    "wof:placetype":"locality",
    "wof:population":115
},
  "geometry": {"coordinates":[87.46083400000001,24.45341],"type":"Point"}
}