{
  "type": "Feature",
  "properties": {
    "iso:country":"IN",
    "ks:ks_name":"Anneramankeri",
    "ks:ks_pop":27,
    "ks:ks_type":"HABITATION",
    "name:eng_x_preferred":[
        "Anneramankeri"
    ],
    "wof:name":"Anneramankeri",
    "wof:placetype":"locality",
    "wof:population":27
},
  "geometry": {"coordinates":[74.50628500000001,14.320107],"type":"Point"}
}