{
  "type": "Feature",
  "properties": {
    "iso:country":"IN",
    "ks:ks_alt_nam":"Belguri supa",
    "ks:ks_name":"Belguri Supa",
    "ks:ks_pop":231,
    "ks:ks_type":"HABITATION",
    "name:eng_x_preferred":[
        "Belguri Supa"
    ],
    "wof:name":"Belguri Supa",
    "wof:placetype":"locality",
    "wof:population":231
},
  "geometry": {"coordinates":[91.448684,26.734569],"type":"Point"}
}