{
  "type": "Feature",
  "properties": {
    "iso:country":"IN",
    "ks:ks_name":"Bagsari",
    "ks:ks_pop":1098,
    "ks:ks_type":"VILLAGE",
    "ks:ks_uagg_main":0,
    "name:eng_x_preferred":[
        "Bagsari"
    ],
    "wof:name":"Bagsari",
    "wof:placetype":"neighbourhood",
    "wof:population":1098
},
  "geometry": {"coordinates":[71.606453,24.788903],"type":"Point"}
}