{
  "type": "Feature",
  "properties": {
    "iso:country":"IN",
    "ks:ks_name":"Khohpura",
    "ks:ks_pop":165,
    "ks:ks_type":"HABITATION",
    "name:eng_x_preferred":[
        "Khohpura"
    ],
    "wof:name":"Khohpura",
    "wof:placetype":"locality",
    "wof:population":165
},
  "geometry": {"coordinates":[77.474987,26.712989],"type":"Point"}
}