{
  "type": "Feature",
  "properties": {
    "gn:admin1_code":"19.0",
    "gn:admin2_code":"581.0",
    "gn:asciiname":"Girijampyate",
    "gn:country_code":"IN",
    "gn:dem":840,
    "gn:feature_class":"P",
    "gn:feature_code":"PPL",
    "gn:name":"Girijampyate",
    "gn:population":0,
    "gn:timezone":"Asia/Kolkata",
    "iso:country":"IN",
    "ks:ks_name":"Girijampete",
    "ks:ks_pop":159,
    "ks:ks_type":"VILLAGE",
    "ks:ks_uagg_main":0,
    "name:eng_x_preferred":[
        "Girijampete"
    ],
    "wof:name":"Girijampete",
    "wof:placetype":"neighbourhood",
    "wof:population":159
},
  "geometry": {"coordinates":[78.04431599999999,13.20546],"type":"Point"}
}