{
  "type": "Feature",
  "properties": {
    "iso:country":"IN",
    "ks:ks_name":"Sadhakanagar",
    "ks:ks_pop":431,
    "ks:ks_type":"VILLAGE",
    "name:eng_x_preferred":[
        "Sadhakanagar"
    ],
    "wof:name":"Sadhakanagar",
    "wof:placetype":"locality",
    "wof:population":431
},
  "geometry": {"coordinates":[86.164884,20.457898],"type":"Point"}
}