{
  "type": "Feature",
  "properties": {
    "gn:admin1_code":"40",
    "gn:admin2_code":"538.0",
    "gn:asciiname":"Devadarukunta Tanda",
    "gn:country_code":"IN",
    "gn:dem":436,
    "gn:feature_class":"P",
    "gn:feature_code":"PPL",
    "gn:name":"Devad\u0101rukunta T\u0101nda",
    "gn:population":0,
    "gn:timezone":"Asia/Kolkata",
    "iso:country":"IN",
    "wof:name":"Devadarukunta Tanda",
    "wof:placetype":"locality"
},
  "geometry": {"coordinates":[78.61983000000002,16.43877],"type":"Point"}
}