{
  "type": "Feature",
  "properties": {
    "gn:admin1_code":"34.0",
    "gn:admin2_code":"208.0",
    "gn:asciiname":"Khuti",
    "gn:country_code":"IN",
    "gn:dem":62,
    "gn:feature_class":"P",
    "gn:feature_code":"PPL",
    "gn:name":"Khuti",
    "gn:population":0,
    "gn:timezone":"Asia/Kolkata",
    "iso:country":"IN",
    "wof:name":"Khuti",
    "wof:placetype":"locality"
},
  "geometry": {"coordinates":[86.99856,26.19892],"type":"Point"}
}