{
  "type": "Feature",
  "properties": {
    "gn:admin1_code":"36.0",
    "gn:admin2_code":"158.0",
    "gn:asciiname":"Jahangirabad",
    "gn:country_code":"IN",
    "gn:dem":106,
    "gn:feature_class":"P",
    "gn:feature_code":"PPL",
    "gn:name":"Jahang\u012br\u0101b\u0101d",
    "gn:population":0,
    "gn:timezone":"Asia/Kolkata",
    "iso:country":"IN",
    "name:bpy_x_preferred":[
        "\u099c\u09be\u09b9\u09be\u0999\u09cd\u0997\u09bf\u09b0\u09be\u09ac\u09be\u09a6"
    ],
    "name:fas_x_preferred":[
        "\u062c\u0647\u0627\u0646\u06af\u06cc\u0631\u0622\u0628\u0627\u062f"
    ],
    "name:ita_x_preferred":[
        "Jahangirabad"
    ],
    "name:mlg_x_preferred":[
        "Jahangirabad"
    ],
    "name:msa_x_preferred":[
        "Jahangirabad"
    ],
    "name:new_x_preferred":[
        "\u091c\u0939\u093e\u0902\u0917\u093f\u0930\u093e\u0935\u093e\u0926"
    ],
    "name:nld_x_preferred":[
        "Jahangirabad"
    ],
    "name:pol_x_preferred":[
        "Jahangirabad"
    ],
    "name:por_x_preferred":[
        "Jahangirabad"
    ],
    "name:swe_x_preferred":[
        "Jahangirabad"
    ],
    "name:urd_x_preferred":[
        "\u062c\u06c1\u0627\u0646\u06af\u06cc\u0631\u0628\u062f"
    ],
    "name:vie_x_preferred":[
        "Jahangirabad"
    ],
    "name:zho_x_preferred":[
        "\u8d3e\u676d\u683c\u4f0a\u62c9\u5df4\u5fb7"
    ],
    "wof:name":"Jahangirabad",
    "wof:placetype":"locality"
},
  "geometry": {"coordinates":[80.99876999999999,26.08886],"type":"Point"}
}