{
  "type": "Feature",
  "properties": {
    "gn:admin1_code":"35",
    "gn:admin2_code":"426.0",
    "gn:asciiname":"Chakarbhata",
    "gn:country_code":"IN",
    "gn:dem":415,
    "gn:feature_class":"P",
    "gn:feature_code":"PPL",
    "gn:name":"Chakarbhata",
    "gn:population":0,
    "gn:timezone":"Asia/Kolkata",
    "iso:country":"IN",
    "ks:ks_name":"Chakarbhata",
    "ks:ks_pop":448,
    "ks:ks_type":"VILLAGE",
    "name:eng_x_preferred":[
        "Chakarbhata"
    ],
    "wof:name":"Chakarbhata",
    "wof:placetype":"locality",
    "wof:population":448
},
  "geometry": {"coordinates":[80.17450599999999,24.028996],"type":"Point"}
}