{
  "type": "Feature",
  "properties": {
    "iso:country":"IN",
    "ks:ks_name":"Kadani",
    "ks:ks_pop":185,
    "ks:ks_type":"HABITATION",
    "name:eng_x_preferred":[
        "Kadani"
    ],
    "wof:name":"Kadani",
    "wof:placetype":"locality",
    "wof:population":185
},
  "geometry": {"coordinates":[78.601286,9.669866],"type":"Point"}
}