{
  "type": "Feature",
  "properties": {
    "iso:country":"IN",
    "ks:ks_name":"Udaipur",
    "ks:ks_pop":11,
    "ks:ks_type":"VILLAGE",
    "name:eng_x_preferred":[
        "Udaipur"
    ],
    "name:hin_x_preferred":[
        "\u0909\u0926\u092f\u092a\u0941\u0930"
    ],
    "wof:name":"Udaipur",
    "wof:placetype":"locality",
    "wof:population":11
},
  "geometry": {"coordinates":[80.478076,24.83529],"type":"Point"}
}