{
  "type": "Feature",
  "properties": {
    "iso:country":"IN",
    "ks:ks_name":"Sarregaon",
    "ks:ks_pop":119,
    "ks:ks_type":"VILLAGE",
    "name:eng_x_preferred":[
        "Sarregaon"
    ],
    "wof:name":"Sarregaon",
    "wof:placetype":"locality",
    "wof:population":119
},
  "geometry": {"coordinates":[80.265587,20.893448],"type":"Point"}
}