{
  "type": "Feature",
  "properties": {
    "gn:admin1_code":"34.0",
    "gn:admin2_code":"221.0",
    "gn:asciiname":"Ahar",
    "gn:country_code":"IN",
    "gn:dem":54,
    "gn:feature_class":"P",
    "gn:feature_code":"PPL",
    "gn:name":"Ahar",
    "gn:population":0,
    "gn:timezone":"Asia/Kolkata",
    "iso:country":"IN",
    "name:ara_x_preferred":[
        "\u0623\u0647\u0631"
    ],
    "name:azb_x_preferred":[
        "\u0627\u0647\u0631"
    ],
    "name:aze_x_preferred":[
        "\u018fh\u0259r"
    ],
    "name:cat_x_preferred":[
        "Ahar"
    ],
    "name:ceb_x_preferred":[
        "Ahar"
    ],
    "name:deu_x_preferred":[
        "Ahar"
    ],
    "name:fas_x_preferred":[
        "\u0627\u0647\u0631"
    ],
    "name:fra_x_preferred":[
        "Ahar"
    ],
    "name:hin_x_preferred":[
        "\u0905\u0939\u093e\u0930"
    ],
    "name:ita_x_preferred":[
        "Ahar"
    ],
    "name:kor_x_preferred":[
        "\uc544\ud558\ub974"
    ],
    "name:mlg_x_preferred":[
        "Ahar"
    ],
    "name:msa_x_preferred":[
        "Ahar"
    ],
    "name:pnb_x_preferred":[
        "\u0627\u06c1\u0627\u0631"
    ],
    "name:pol_x_preferred":[
        "Ahar"
    ],
    "name:ron_x_preferred":[
        "Ahar"
    ],
    "name:rus_x_preferred":[
        "\u0410\u0445\u0430\u0440"
    ],
    "name:spa_x_preferred":[
        "Ahar"
    ],
    "name:swe_x_preferred":[
        "Ahar"
    ],
    "name:tgk_x_preferred":[
        "\u0410\u04b3\u0430\u0440"
    ],
    "name:tur_x_preferred":[
        "Eher"
    ],
    "name:urd_x_preferred":[
        "\u0627\u06c1\u0631"
    ],
    "name:vie_x_preferred":[
        "Ahar"
    ],
    "name:zho_x_preferred":[
        "\u963f\u54c8\u5c14"
    ],
    "wof:name":"Ahar",
    "wof:placetype":"locality"
},
  "geometry": {"coordinates":[85.66016999999999,25.8445],"type":"Point"}
}