{
  "type": "Feature",
  "properties": {
    "gn:admin1_code":"34.0",
    "gn:admin2_code":"236.0",
    "gn:asciiname":"Tanakpur",
    "gn:country_code":"IN",
    "gn:dem":121,
    "gn:feature_class":"P",
    "gn:feature_code":"PPL",
    "gn:name":"Tanakpur",
    "gn:population":0,
    "gn:timezone":"Asia/Kolkata",
    "iso:country":"IN",
    "name:bpy_x_preferred":[
        "\u099f\u09a8\u0995\u09aa\u09c1\u09b0"
    ],
    "name:ceb_x_preferred":[
        "Tanakpur"
    ],
    "name:hin_x_preferred":[
        "\u091f\u0928\u0915\u092a\u0941\u0930"
    ],
    "name:ita_x_preferred":[
        "Tanakpur"
    ],
    "name:mlg_x_preferred":[
        "Tanakpur"
    ],
    "name:msa_x_preferred":[
        "Tanakpur"
    ],
    "name:nld_x_preferred":[
        "Tanakpur"
    ],
    "name:pol_x_preferred":[
        "Tanakpur"
    ],
    "name:por_x_preferred":[
        "Tanakpur"
    ],
    "name:rus_x_preferred":[
        "\u0422\u0430\u043d\u0430\u043a\u043f\u0443\u0440"
    ],
    "name:swe_x_preferred":[
        "Tanakpur"
    ],
    "name:ukr_x_preferred":[
        "\u0422\u0430\u043d\u0430\u043a\u043f\u0443\u0440"
    ],
    "name:urd_x_preferred":[
        "\u0679\u0646\u06a9\u067e\u0648\u0631"
    ],
    "name:vie_x_preferred":[
        "Tanakpur"
    ],
    "name:zho_x_preferred":[
        "\u5854\u7eb3\u514b\u666e\u5c14"
    ],
    "wof:name":"Tanakpur",
    "wof:placetype":"locality"
},
  "geometry": {"coordinates":[85.08771999999998,24.73401],"type":"Point"}
}