{
  "type": "Feature",
  "properties": {
    "gn:admin1_code":"9.0",
    "gn:admin2_code":"484.0",
    "gn:asciiname":"Nansalai",
    "gn:country_code":"IN",
    "gn:dem":98,
    "gn:feature_class":"P",
    "gn:feature_code":"PPL",
    "gn:name":"N\u0101nsal\u0101i",
    "gn:population":0,
    "gn:timezone":"Asia/Kolkata",
    "iso:country":"IN",
    "ks:ks_name":"Nan Salai",
    "ks:ks_pop":221,
    "ks:ks_type":"VILLAGE",
    "name:eng_x_preferred":[
        "Nan Salai"
    ],
    "name:eng_x_variant":[
        "Nansalai"
    ],
    "wof:name":"Nan Salai",
    "wof:placetype":"locality",
    "wof:population":221
},
  "geometry": {"coordinates":[73.703389,23.094528],"type":"Point"}
}