{
  "type": "Feature",
  "properties": {
    "iso:country":"IN",
    "ks:ks_alt_nam":"KENDADANGRI",
    "ks:ks_name":"Kendadangri",
    "ks:ks_pop":678,
    "ks:ks_type":"HABITATION",
    "name:eng_x_preferred":[
        "Kendadangri"
    ],
    "wof:name":"Kendadangri",
    "wof:placetype":"locality",
    "wof:population":678
},
  "geometry": {"coordinates":[86.758813,22.561174],"type":"Point"}
}