{
  "type": "Feature",
  "properties": {
    "iso:country":"IN",
    "ks:ks_name":"Kottagam",
    "ks:ks_pop":510,
    "ks:ks_type":"HABITATION",
    "name:eng_x_preferred":[
        "Kottagam"
    ],
    "wof:name":"Kottagam",
    "wof:placetype":"locality",
    "wof:population":510
},
  "geometry": {"coordinates":[79.661807,10.51097],"type":"Point"}
}