{
  "type": "Feature",
  "properties": {
    "iso:country":"IN",
    "ks:ks_name":"Udiyanguri",
    "ks:ks_pop":460,
    "ks:ks_type":"VILLAGE",
    "name:eng_x_preferred":[
        "Udiyanguri"
    ],
    "wof:name":"Udiyanguri",
    "wof:placetype":"locality",
    "wof:population":460
},
  "geometry": {"coordinates":[91.076207,26.646876],"type":"Point"}
}