{
  "type": "Feature",
  "properties": {
    "iso:country":"IN",
    "ks:ks_name":"Pal Para",
    "ks:ks_pop":850,
    "ks:ks_type":"HABITATION",
    "name:eng_x_preferred":[
        "Pal Para"
    ],
    "wof:name":"Pal Para",
    "wof:placetype":"locality",
    "wof:population":850
},
  "geometry": {"coordinates":[91.267414,26.085018],"type":"Point"}
}