{
  "type": "Feature",
  "properties": {
    "gn:admin1_code":"35.0",
    "gn:admin2_code":"455.0",
    "gn:asciiname":"Salaiya Khurd",
    "gn:country_code":"IN",
    "gn:dem":750,
    "gn:feature_class":"P",
    "gn:feature_code":"PPL",
    "gn:name":"Salaiya Khurd",
    "gn:population":0,
    "gn:timezone":"Asia/Kolkata",
    "iso:country":"IN",
    "wof:name":"Salaiya Khurd",
    "wof:placetype":"locality"
},
  "geometry": {"coordinates":[78.73148,21.98163],"type":"Point"}
}