{
  "type": "Feature",
  "properties": {
    "gn:admin1_code":"21.0",
    "gn:admin2_code":"398.0",
    "gn:asciiname":"Tulu Lellari",
    "gn:country_code":"IN",
    "gn:dem":714,
    "gn:feature_class":"P",
    "gn:feature_code":"PPL",
    "gn:name":"Tulu Lell\u0101ri",
    "gn:population":0,
    "gn:timezone":"Asia/Kolkata",
    "iso:country":"IN",
    "wof:name":"Tulu Lellari",
    "wof:placetype":"locality"
},
  "geometry": {"coordinates":[83.20149000000001,18.98073],"type":"Point"}
}