{
  "type": "Feature",
  "properties": {
    "gn:admin1_code":"9.0",
    "gn:admin2_code":"472.0",
    "gn:asciiname":"Chula",
    "gn:country_code":"IN",
    "gn:dem":219,
    "gn:feature_class":"P",
    "gn:feature_code":"PPL",
    "gn:name":"Chula",
    "gn:population":0,
    "gn:timezone":"Asia/Kolkata",
    "iso:country":"IN",
    "name:ceb_x_preferred":[
        "Chula"
    ],
    "name:deu_x_preferred":[
        "Chula"
    ],
    "name:por_x_preferred":[
        "Chula"
    ],
    "name:swe_x_preferred":[
        "Chula"
    ],
    "name:tha_x_preferred":[
        "Chula"
    ],
    "name:ukr_x_preferred":[
        "\u0427\u0443\u043b\u0430"
    ],
    "wof:name":"Chula",
    "wof:placetype":"locality"
},
  "geometry": {"coordinates":[73.07129999999999,23.90941],"type":"Point"}
}