{
  "type": "Feature",
  "properties": {
    "iso:country":"IN",
    "ks:ks_name":"Horatti",
    "ks:ks_pop":148,
    "ks:ks_type":"HABITATION",
    "name:eng_x_preferred":[
        "Horatti"
    ],
    "wof:name":"Horatti",
    "wof:placetype":"locality",
    "wof:population":148
},
  "geometry": {"coordinates":[75.313273,13.218647],"type":"Point"}
}