{
  "type": "Feature",
  "properties": {
    "gn:admin1_code":"11",
    "gn:admin2_code":"31.0",
    "gn:asciiname":"Gandhol",
    "gn:country_code":"IN",
    "gn:dem":1135,
    "gn:feature_class":"P",
    "gn:feature_code":"PPL",
    "gn:name":"Gandhol",
    "gn:population":0,
    "gn:timezone":"Asia/Kolkata",
    "iso:country":"IN",
    "name:cat_x_preferred":[
        "Gandhol"
    ],
    "wof:name":"Gandhol",
    "wof:placetype":"locality"
},
  "geometry": {"coordinates":[76.96016999999998,30.92065],"type":"Point"}
}