{
  "type": "Feature",
  "properties": {
    "iso:country":"IN",
    "ks:ks_name":"Thavasipatti",
    "ks:ks_pop":712,
    "ks:ks_type":"HABITATION",
    "name:eng_x_preferred":[
        "Thavasipatti"
    ],
    "wof:name":"Thavasipatti",
    "wof:placetype":"locality",
    "wof:population":712
},
  "geometry": {"coordinates":[78.367893,10.324983],"type":"Point"}
}