{
  "type": "Feature",
  "properties": {
    "gn:admin1_code":"19.0",
    "gn:admin2_code":"570.0",
    "gn:asciiname":"Kodadadlu",
    "gn:country_code":"IN",
    "gn:dem":1137,
    "gn:feature_class":"P",
    "gn:feature_code":"PPL",
    "gn:name":"Kodadadlu",
    "gn:population":0,
    "gn:timezone":"Asia/Kolkata",
    "iso:country":"IN",
    "wof:name":"Kodadadlu",
    "wof:placetype":"locality"
},
  "geometry": {"coordinates":[75.53564,13.0778],"type":"Point"}
}