{
  "type": "Feature",
  "properties": {
    "gn:admin1_code":"21",
    "gn:admin2_code":"398.0",
    "gn:asciiname":"Kinuboro",
    "gn:country_code":"IN",
    "gn:dem":1093,
    "gn:feature_class":"P",
    "gn:feature_code":"PPL",
    "gn:name":"Kinuboro",
    "gn:population":0,
    "gn:timezone":"Asia/Kolkata",
    "iso:country":"IN",
    "wof:name":"Kinuboro",
    "wof:placetype":"locality"
},
  "geometry": {"coordinates":[82.77922,18.43238],"type":"Point"}
}