{
  "type": "Feature",
  "properties": {
    "iso:country":"IN",
    "ks:ks_name":"Khairabad",
    "ks:ks_pop":119,
    "ks:ks_type":"VILLAGE",
    "name:eng_x_preferred":[
        "Khairabad"
    ],
    "wof:name":"Khairabad",
    "wof:placetype":"locality",
    "wof:population":119
},
  "geometry": {"coordinates":[86.185554,24.386311],"type":"Point"}
}