{
  "type": "Feature",
  "properties": {
    "iso:country":"IN",
    "ks:ks_name":"Bahadurpur Ta.Ibrahimpur",
    "ks:ks_pop":2174,
    "ks:ks_type":"VILLAGE",
    "name:eng_x_preferred":[
        "Bahadurpur Ta.Ibrahimpur"
    ],
    "wof:name":"Bahadurpur Ta.Ibrahimpur",
    "wof:placetype":"locality",
    "wof:population":2174
},
  "geometry": {"coordinates":[81.935734,25.480572],"type":"Point"}
}