{
  "type": "Feature",
  "properties": {
    "gn:admin1_code":"36.0",
    "gn:admin2_code":"158.0",
    "gn:asciiname":"Pura Parshadi Ahir",
    "gn:country_code":"IN",
    "gn:dem":117,
    "gn:feature_class":"P",
    "gn:feature_code":"PPL",
    "gn:name":"Pura Parsh\u0101di Ahir",
    "gn:population":0,
    "gn:timezone":"Asia/Kolkata",
    "iso:country":"IN",
    "wof:name":"Pura Parshadi Ahir",
    "wof:placetype":"locality"
},
  "geometry": {"coordinates":[81.0796,26.13459],"type":"Point"}
}