{
  "type": "Feature",
  "properties": {
    "iso:country":"IN",
    "ks:ks_alt_nam":"Bagha lamti",
    "ks:ks_name":"Bagha Lamti",
    "ks:ks_pop":197,
    "ks:ks_type":"HABITATION",
    "name:eng_x_preferred":[
        "Bagha Lamti"
    ],
    "wof:name":"Bagha Lamti",
    "wof:placetype":"locality",
    "wof:population":197
},
  "geometry": {"coordinates":[82.840716,19.09645],"type":"Point"}
}