{
  "type": "Feature",
  "properties": {
    "iso:country":"IN",
    "ks:ks_name":"Janaha Plot",
    "ks:ks_pop":531,
    "ks:ks_type":"HABITATION",
    "name:eng_x_preferred":[
        "Janaha Plot"
    ],
    "wof:name":"Janaha Plot",
    "wof:placetype":"locality",
    "wof:population":531
},
  "geometry": {"coordinates":[75.07326999999999,14.992579],"type":"Point"}
}