{
  "type": "Feature",
  "properties": {
    "iso:country":"IN",
    "ks:ks_name":"Kuledi",
    "ks:ks_pop":252,
    "ks:ks_type":"VILLAGE",
    "name:eng_x_preferred":[
        "Kuledi"
    ],
    "wof:name":"Kuledi",
    "wof:placetype":"locality",
    "wof:population":252
},
  "geometry": {"coordinates":[78.703408,30.355373],"type":"Point"}
}