{
  "type": "Feature",
  "properties": {
    "gn:admin1_code":"02",
    "gn:admin2_code":"550.0",
    "gn:asciiname":"Zuvvaladinne",
    "gn:country_code":"IN",
    "gn:dem":7,
    "gn:feature_class":"P",
    "gn:feature_code":"PPL",
    "gn:name":"Zuvvaladinne",
    "gn:population":0,
    "gn:timezone":"Asia/Kolkata",
    "iso:country":"IN",
    "wof:name":"Zuvvaladinne",
    "wof:placetype":"locality"
},
  "geometry": {"coordinates":[80.07044999999999,14.80796],"type":"Point"}
}