{
  "type": "Feature",
  "properties": {
    "gn:admin1_code":"13.0",
    "gn:admin2_code":"592.0",
    "gn:asciiname":"Tennala",
    "gn:country_code":"IN",
    "gn:dem":36,
    "gn:feature_class":"P",
    "gn:feature_code":"PPL",
    "gn:name":"Tennala",
    "gn:population":0,
    "gn:timezone":"Asia/Kolkata",
    "iso:country":"IN",
    "ks:ks_name":"Thennala",
    "ks:ks_pop":1169,
    "ks:ks_type":"HABITATION",
    "name:eng_x_preferred":[
        "Thennala"
    ],
    "name:eng_x_variant":[
        "Tennala"
    ],
    "wof:name":"Thennala",
    "wof:placetype":"locality",
    "wof:population":1169
},
  "geometry": {"coordinates":[75.930035,10.993266],"type":"Point"}
}