{
  "type": "Feature",
  "properties": {
    "gn:admin1_code":"34.0",
    "gn:admin2_code":"232.0",
    "gn:asciiname":"Kharhatanrdera",
    "gn:country_code":"IN",
    "gn:dem":71,
    "gn:feature_class":"P",
    "gn:feature_code":"PPL",
    "gn:name":"Kharh\u0101t\u0101nrdera",
    "gn:population":0,
    "gn:timezone":"Asia/Kolkata",
    "iso:country":"IN",
    "wof:name":"Kharhatanrdera",
    "wof:placetype":"neighbourhood"
},
  "geometry": {"coordinates":[84.21789,25.53643],"type":"Point"}
}