{
  "type": "Feature",
  "properties": {
    "iso:country":"IN",
    "ks:ks_alt_nam":"tiki milan",
    "ks:ks_name":"Tiki Milan",
    "ks:ks_pop":78,
    "ks:ks_type":"HABITATION",
    "name:eng_x_preferred":[
        "Tiki Milan"
    ],
    "wof:name":"Tiki Milan",
    "wof:placetype":"locality",
    "wof:population":78
},
  "geometry": {"coordinates":[85.096677,22.557593],"type":"Point"}
}