{
  "type": "Feature",
  "properties": {
    "iso:country":"IN",
    "ks:ks_name":"Gahilwar Khurd",
    "ks:ks_pop":3,
    "ks:ks_type":"HABITATION",
    "name:eng_x_preferred":[
        "Gahilwar Khurd"
    ],
    "wof:name":"Gahilwar Khurd",
    "wof:placetype":"locality",
    "wof:population":3
},
  "geometry": {"coordinates":[81.196377,24.837895],"type":"Point"}
}