{
  "type": "Feature",
  "properties": {
    "iso:country":"IN",
    "ks:ks_name":"Hingori",
    "ks:ks_pop":120,
    "ks:ks_type":"HABITATION",
    "name:eng_x_preferred":[
        "Hingori"
    ],
    "wof:name":"Hingori",
    "wof:placetype":"locality",
    "wof:population":120
},
  "geometry": {"coordinates":[73.531436,23.727122],"type":"Point"}
}