{
  "type": "Feature",
  "properties": {
    "iso:country":"IN",
    "ks:ks_name":"Bhatotar",
    "ks:ks_pop":0,
    "ks:ks_type":"VILLAGE",
    "name:eng_x_preferred":[
        "Bhatotar"
    ],
    "wof:name":"Bhatotar",
    "wof:placetype":"locality",
    "wof:population":0
},
  "geometry": {"coordinates":[87.448674,25.288272],"type":"Point"}
}