{
  "type": "Feature",
  "properties": {
    "gn:admin1_code":"2",
    "gn:admin2_code":"548.0",
    "gn:asciiname":"Regalagadda",
    "gn:country_code":"IN",
    "gn:dem":54,
    "gn:feature_class":"P",
    "gn:feature_code":"PPL",
    "gn:name":"Regalagadda",
    "gn:population":0,
    "gn:timezone":"Asia/Kolkata",
    "iso:country":"IN",
    "ks:ks_name":"Regulagadda",
    "ks:ks_pop":1514,
    "ks:ks_type":"HABITATION",
    "ks:ks_uagg_main":0,
    "name:eng_x_preferred":[
        "Regulagadda"
    ],
    "wof:name":"Regulagadda",
    "wof:placetype":"neighbourhood",
    "wof:population":1514
},
  "geometry": {"coordinates":[80.206023,16.294022],"type":"Point"}
}