{
  "type": "Feature",
  "properties": {
    "iso:country":"IN",
    "ks:ks_name":"Kalidih",
    "ks:ks_pop":50,
    "ks:ks_type":"HABITATION",
    "name:eng_x_preferred":[
        "Kalidih"
    ],
    "wof:name":"Kalidih",
    "wof:placetype":"locality",
    "wof:population":50
},
  "geometry": {"coordinates":[85.681783,24.581782],"type":"Point"}
}