{
  "type": "Feature",
  "properties": {
    "iso:country":"IN",
    "ks:ks_name":"Thennambuvayal",
    "ks:ks_pop":105,
    "ks:ks_type":"HABITATION",
    "name:eng_x_preferred":[
        "Thennambuvayal"
    ],
    "wof:name":"Thennambuvayal",
    "wof:placetype":"locality",
    "wof:population":105
},
  "geometry": {"coordinates":[78.806668,9.901962],"type":"Point"}
}