{
  "type": "Feature",
  "properties": {
    "iso:country":"IN",
    "ks:ks_name":"Panjaje",
    "ks:ks_pop":360,
    "ks:ks_type":"HABITATION",
    "name:eng_x_preferred":[
        "Panjaje"
    ],
    "wof:name":"Panjaje",
    "wof:placetype":"locality",
    "wof:population":360
},
  "geometry": {"coordinates":[74.97987999999999,12.802491],"type":"Point"}
}