{
  "type": "Feature",
  "properties": {
    "iso:country":"IN",
    "ks:ks_name":"Cherlapally",
    "ks:ks_pop":65,
    "ks:ks_type":"HABITATION",
    "name:eng_x_preferred":[
        "Cherlapally"
    ],
    "wof:name":"Cherlapally",
    "wof:placetype":"locality",
    "wof:population":65
},
  "geometry": {"coordinates":[80.534052,17.655966],"type":"Point"}
}