{
  "type": "Feature",
  "properties": {
    "iso:country":"IN",
    "ks:ks_alt_nam":"Chauhano-Ka-Khandela",
    "ks:ks_name":"Chauhano-ka-khandela",
    "ks:ks_pop":329,
    "ks:ks_type":"HABITATION",
    "name:eng_x_preferred":[
        "Chauhano-ka-khandela"
    ],
    "wof:name":"Chauhano-ka-khandela",
    "wof:placetype":"locality",
    "wof:population":329
},
  "geometry": {"coordinates":[74.06533899999999,24.044489],"type":"Point"}
}