{
  "type": "Feature",
  "properties": {
    "gn:admin1_code":"24.0",
    "gn:admin2_code":"103",
    "gn:asciiname":"Bari Dhani",
    "gn:country_code":"IN",
    "gn:dem":361,
    "gn:feature_class":"P",
    "gn:feature_code":"PPL",
    "gn:name":"Bari Dh\u0101ni",
    "gn:population":0,
    "gn:timezone":"Asia/Kolkata",
    "iso:country":"IN",
    "wof:name":"Bari Dhani",
    "wof:placetype":"neighbourhood"
},
  "geometry": {"coordinates":[75.51058999999999,28.0157],"type":"Point"}
}