{
  "type": "Feature",
  "properties": {
    "iso:country":"IN",
    "ks:ks_name":"Bangaria",
    "ks:ks_pop":574,
    "ks:ks_type":"VILLAGE",
    "name:eng_x_preferred":[
        "Bangaria"
    ],
    "wof:name":"Bangaria",
    "wof:placetype":"locality",
    "wof:population":574
},
  "geometry": {"coordinates":[84.12440700000001,27.186678],"type":"Point"}
}