{
  "type": "Feature",
  "properties": {
    "iso:country":"IN",
    "ks:ks_name":"Lalang Pt II",
    "ks:ks_pop":2673,
    "ks:ks_type":"VILLAGE",
    "ks:ks_uagg_main":0,
    "name:eng_x_preferred":[
        "Lalang Pt II"
    ],
    "wof:name":"Lalang Pt II",
    "wof:placetype":"neighbourhood",
    "wof:population":2673
},
  "geometry": {"coordinates":[93.018745,24.804404],"type":"Point"}
}