{
  "type": "Feature",
  "properties": {
    "gn:admin1_code":"34.0",
    "gn:admin2_code":"219.0",
    "gn:asciiname":"Ahir",
    "gn:country_code":"IN",
    "gn:dem":58,
    "gn:feature_class":"P",
    "gn:feature_code":"PPL",
    "gn:name":"Ah\u012br",
    "gn:population":0,
    "gn:timezone":"Asia/Kolkata",
    "iso:country":"IN",
    "name:cat_x_preferred":[
        "Ahirs"
    ],
    "name:guj_x_preferred":[
        "\u0a86\u0ab9\u0ac0\u0ab0"
    ],
    "name:hif_x_preferred":[
        "Ahir"
    ],
    "name:hin_x_preferred":[
        "\u0905\u0939\u0940\u0930"
    ],
    "name:ita_x_preferred":[
        "Ahir"
    ],
    "name:mai_x_preferred":[
        "\u0905\u0939\u0940\u0930"
    ],
    "name:nor_x_preferred":[
        "Abhira"
    ],
    "name:pan_x_preferred":[
        "\u0a05\u0a39\u0a40\u0a30"
    ],
    "name:pli_x_preferred":[
        "\u0905\u0939\u0940\u0930"
    ],
    "name:pnb_x_preferred":[
        "\u0622\u06c1\u06cc\u0631"
    ],
    "name:pol_x_preferred":[
        "Ahir"
    ],
    "name:por_x_preferred":[
        "Abhira"
    ],
    "name:san_x_preferred":[
        "\u0906\u092d\u0940\u0930\u0903"
    ],
    "name:snd_x_preferred":[
        "\u0622\u0647\u064a\u0631"
    ],
    "name:spa_x_preferred":[
        "Ahir"
    ],
    "name:urd_x_preferred":[
        "\u0622\u06c1\u06cc\u0631"
    ],
    "wof:name":"Ahir",
    "wof:placetype":"neighbourhood"
},
  "geometry": {"coordinates":[85.04199,25.96049],"type":"Point"}
}