{
  "type": "Feature",
  "properties": {
    "iso:country":"IN",
    "ks:ks_name":"Arazi Napara",
    "ks:ks_pop":269,
    "ks:ks_type":"VILLAGE",
    "ks:ks_uagg_main":0,
    "name:eng_x_preferred":[
        "Arazi Napara"
    ],
    "wof:name":"Arazi Napara",
    "wof:placetype":"neighbourhood",
    "wof:population":269
},
  "geometry": {"coordinates":[87.92189500000001,24.610032],"type":"Point"}
}