{
  "type": "Feature",
  "properties": {
    "iso:country":"IN",
    "ks:ks_name":"Pipartola",
    "ks:ks_pop":98,
    "ks:ks_type":"HABITATION",
    "name:eng_x_preferred":[
        "Pipartola"
    ],
    "wof:name":"Pipartola",
    "wof:placetype":"locality",
    "wof:population":98
},
  "geometry": {"coordinates":[80.391884,20.826395],"type":"Point"}
}