{
  "type": "Feature",
  "properties": {
    "gn:admin1_code":"34.0",
    "gn:admin2_code":"209.0",
    "gn:asciiname":"Dumaria",
    "gn:country_code":"IN",
    "gn:dem":52,
    "gn:feature_class":"P",
    "gn:feature_code":"PPL",
    "gn:name":"Dumaria",
    "gn:population":0,
    "gn:timezone":"Asia/Kolkata",
    "iso:country":"IN",
    "ks:ks_name":"Dumaria",
    "ks:ks_pop":3274,
    "ks:ks_type":"VILLAGE",
    "name:cat_x_preferred":[
        "Dumaria"
    ],
    "name:eng_x_preferred":[
        "Dumaria"
    ],
    "name:tam_x_preferred":[
        "\u0ba4\u0bc1\u0bae\u0bbe\u0bb0\u0bbf\u0baf\u0bbe"
    ],
    "wof:name":"Dumaria",
    "wof:placetype":"locality",
    "wof:population":3274
},
  "geometry": {"coordinates":[87.539903,26.058219],"type":"Point"}
}