{
  "type": "Feature",
  "properties": {
    "iso:country":"IN",
    "ks:ks_name":"Laxmipuram",
    "ks:ks_pop":301,
    "ks:ks_type":"VILLAGE",
    "name:eng_x_preferred":[
        "Laxmipuram"
    ],
    "wof:name":"Laxmipuram",
    "wof:placetype":"locality",
    "wof:population":301
},
  "geometry": {"coordinates":[78.595643,18.342703],"type":"Point"}
}