{
  "type": "Feature",
  "properties": {
    "gn:admin1_code":"36",
    "gn:admin2_code":"200.0",
    "gn:asciiname":"Kuthar",
    "gn:country_code":"IN",
    "gn:dem":328,
    "gn:feature_class":"P",
    "gn:feature_code":"PPL",
    "gn:name":"Kuthar",
    "gn:population":0,
    "gn:timezone":"Asia/Kolkata",
    "iso:country":"IN",
    "name:cat_x_preferred":[
        "Kuthar"
    ],
    "name:fra_x_preferred":[
        "Kuthar"
    ],
    "name:pan_x_preferred":[
        "\u0a15\u0a41\u0a25\u0a3e\u0a30 \u0a30\u0a3f\u0a06\u0a38\u0a24"
    ],
    "wof:name":"Kuthar",
    "wof:placetype":"locality"
},
  "geometry": {"coordinates":[83.25444,24.6272],"type":"Point"}
}