{
  "type": "Feature",
  "properties": {
    "iso:country":"IN",
    "ks:ks_name":"Madhupur",
    "ks:ks_pop":276,
    "ks:ks_type":"HABITATION",
    "name:eng_x_preferred":[
        "Madhupur"
    ],
    "wof:name":"Madhupur",
    "wof:placetype":"locality",
    "wof:population":276
},
  "geometry": {"coordinates":[86.714603,22.705386],"type":"Point"}
}