{
  "type": "Feature",
  "properties": {
    "iso:country":"IN",
    "ks:ks_alt_nam":"Majar\u0101gollappatti",
    "ks:ks_name":"Majaragollappatti",
    "ks:ks_type":"URBAN",
    "ks:ks_uagg_main":0,
    "name:eng_x_preferred":[
        "Majaragollappatti"
    ],
    "name:eng_x_variant":[
        "Majar\u0101gollappatti"
    ],
    "wof:name":"Majaragollappatti",
    "wof:placetype":"locality"
},
  "geometry": {"coordinates":[78.073892,11.668109],"type":"Point"}
}