{
  "type": "Feature",
  "properties": {
    "iso:country":"IN",
    "ks:ks_name":"Godipatana",
    "ks:ks_pop":188,
    "ks:ks_type":"VILLAGE",
    "name:eng_x_preferred":[
        "Godipatana"
    ],
    "wof:name":"Godipatana",
    "wof:placetype":"locality",
    "wof:population":188
},
  "geometry": {"coordinates":[85.447829,20.154879],"type":"Point"}
}