{
  "type": "Feature",
  "properties": {
    "iso:country":"IN",
    "ks:ks_name":"Guddethotta Basar",
    "ks:ks_pop":220,
    "ks:ks_type":"HABITATION",
    "name:eng_x_preferred":[
        "Guddethotta Basar"
    ],
    "wof:name":"Guddethotta Basar",
    "wof:placetype":"locality",
    "wof:population":220
},
  "geometry": {"coordinates":[75.353517,13.350304],"type":"Point"}
}