{
  "type": "Feature",
  "properties": {
    "iso:country":"IN",
    "ks:ks_alt_nam":"bazartola",
    "ks:ks_name":"Bazartola",
    "ks:ks_pop":835,
    "ks:ks_type":"HABITATION",
    "name:eng_x_preferred":[
        "Bazartola"
    ],
    "wof:name":"Bazartola",
    "wof:placetype":"locality",
    "wof:population":835
},
  "geometry": {"coordinates":[85.36673,25.793443],"type":"Point"}
}