{
  "type": "Feature",
  "properties": {
    "iso:country":"IN",
    "ks:ks_name":"Irpanar",
    "ks:ks_pop":75,
    "ks:ks_type":"HABITATION",
    "name:eng_x_preferred":[
        "Irpanar"
    ],
    "wof:name":"Irpanar",
    "wof:placetype":"locality",
    "wof:population":75
},
  "geometry": {"coordinates":[81.115871,19.619759],"type":"Point"}
}