{
  "type": "Feature",
  "properties": {
    "iso:country":"IN",
    "ks:ks_name":"West Bodra",
    "ks:ks_pop":1784,
    "ks:ks_type":"HABITATION",
    "ks:ks_uagg_main":0,
    "name:eng_x_preferred":[
        "West Bodra"
    ],
    "wof:name":"West Bodra",
    "wof:placetype":"neighbourhood",
    "wof:population":1784
},
  "geometry": {"coordinates":[88.166273,26.603257],"type":"Point"}
}