{
  "type": "Feature",
  "properties": {
    "iso:country":"IN",
    "ks:ks_name":"Hadahi",
    "ks:ks_pop":582,
    "ks:ks_type":"HABITATION",
    "name:eng_x_preferred":[
        "Hadahi"
    ],
    "wof:name":"Hadahi",
    "wof:placetype":"locality",
    "wof:population":582
},
  "geometry": {"coordinates":[84.416342,24.42217],"type":"Point"}
}