{
  "type": "Feature",
  "properties": {
    "iso:country":"IN",
    "ks:ks_alt_nam":"Baur\u0101ha",
    "ks:ks_name":"Bauraha",
    "ks:ks_pop":2909,
    "ks:ks_type":"VILLAGE",
    "name:eng_x_preferred":[
        "Bauraha"
    ],
    "name:eng_x_variant":[
        "Baur\u0101ha"
    ],
    "wof:name":"Bauraha",
    "wof:placetype":"locality",
    "wof:population":2909
},
  "geometry": {"coordinates":[86.617338,26.242484],"type":"Point"}
}