{
  "type": "Feature",
  "properties": {
    "gn:admin1_code":"36.0",
    "gn:admin2_code":"158.0",
    "gn:asciiname":"Pura Dundi",
    "gn:country_code":"IN",
    "gn:dem":116,
    "gn:feature_class":"P",
    "gn:feature_code":"PPL",
    "gn:name":"Pura Dundi",
    "gn:population":0,
    "gn:timezone":"Asia/Kolkata",
    "iso:country":"IN",
    "ks:ks_name":"Pure Dundy",
    "ks:ks_pop":239,
    "ks:ks_type":"VILLAGE",
    "name:eng_x_preferred":[
        "Pure Dundy"
    ],
    "name:eng_x_variant":[
        "Pura Dundi"
    ],
    "wof:name":"Pure Dundy",
    "wof:placetype":"locality",
    "wof:population":239
},
  "geometry": {"coordinates":[81.40170000000001,26.3499],"type":"Point"}
}