{
  "type": "Feature",
  "properties": {
    "iso:country":"IN",
    "ks:ks_name":"Rawani",
    "ks:ks_pop":0,
    "ks:ks_type":"VILLAGE",
    "name:eng_x_preferred":[
        "Rawani"
    ],
    "wof:name":"Rawani",
    "wof:placetype":"locality",
    "wof:population":0
},
  "geometry": {"coordinates":[79.230266,26.378441],"type":"Point"}
}