{
  "type": "Feature",
  "properties": {
    "iso:country":"IN",
    "ks:ks_name":"Pipela",
    "ks:ks_pop":1822,
    "ks:ks_type":"HABITATION",
    "name:eng_x_preferred":[
        "Pipela"
    ],
    "wof:name":"Pipela",
    "wof:placetype":"locality",
    "wof:population":1822
},
  "geometry": {"coordinates":[72.95066,24.64314],"type":"Point"}
}