{
  "type": "Feature",
  "properties": {
    "iso:country":"IN",
    "ks:ks_alt_nam":"boirgaon",
    "ks:ks_name":"Boirgaon",
    "ks:ks_pop":93,
    "ks:ks_type":"HABITATION",
    "name:eng_x_preferred":[
        "Boirgaon"
    ],
    "wof:name":"Boirgaon",
    "wof:placetype":"locality",
    "wof:population":93
},
  "geometry": {"coordinates":[82.084356,20.201316],"type":"Point"}
}