{
  "type": "Feature",
  "properties": {
    "iso:country":"IN",
    "ks:ks_alt_nam":"Gugulothu thanda",
    "ks:ks_name":"Gugulothu Thanda",
    "ks:ks_pop":93,
    "ks:ks_type":"HABITATION",
    "name:eng_x_preferred":[
        "Gugulothu Thanda"
    ],
    "wof:name":"Gugulothu Thanda",
    "wof:placetype":"locality",
    "wof:population":93
},
  "geometry": {"coordinates":[79.697624,17.752005],"type":"Point"}
}