{
  "type": "Feature",
  "properties": {
    "gn:admin1_code":"2",
    "gn:admin2_code":"545.0",
    "gn:asciiname":"Burugavada",
    "gn:country_code":"IN",
    "gn:dem":285,
    "gn:feature_class":"P",
    "gn:feature_code":"PPL",
    "gn:name":"B\u016brugav\u0101da",
    "gn:population":0,
    "gn:timezone":"Asia/Kolkata",
    "iso:country":"IN",
    "ks:ks_name":"Buruguwada",
    "ks:ks_pop":66,
    "ks:ks_type":"HABITATION",
    "name:eng_x_preferred":[
        "Buruguwada"
    ],
    "name:eng_x_variant":[
        "Burugavada"
    ],
    "wof:name":"Buruguwada",
    "wof:placetype":"locality",
    "wof:population":66
},
  "geometry": {"coordinates":[82.001302,17.64223],"type":"Point"}
}