{
  "type": "Feature",
  "properties": {
    "gn:admin1_code":"19.0",
    "gn:admin2_code":"569.0",
    "gn:asciiname":"Uliyargoli",
    "gn:country_code":"IN",
    "gn:dem":13,
    "gn:feature_class":"P",
    "gn:feature_code":"PPLL",
    "gn:name":"Uliy\u0101rg\u014dli",
    "gn:population":0,
    "gn:timezone":"Asia/Kolkata",
    "iso:country":"IN",
    "ks:ks_alt_nam":"Uliy\u0101rg\u014dli",
    "ks:ks_name":"Uliyargoli",
    "ks:ks_type":"VILLAGE",
    "ks:ks_uagg_main":0,
    "name:eng_x_preferred":[
        "Uliyargoli"
    ],
    "name:eng_x_variant":[
        "Uliy\u0101rg\u014dli"
    ],
    "wof:name":"Uliyargoli",
    "wof:placetype":"neighbourhood"
},
  "geometry": {"coordinates":[74.742041,13.240893],"type":"Point"}
}