{
  "type": "Feature",
  "properties": {
    "iso:country":"IN",
    "ks:ks_name":"Simra Urf Simra Chak Fatma",
    "ks:ks_pop":1164,
    "ks:ks_type":"VILLAGE",
    "name:eng_x_preferred":[
        "Simra Urf Simra Chak Fatma"
    ],
    "wof:name":"Simra Urf Simra Chak Fatma",
    "wof:placetype":"locality",
    "wof:population":1164
},
  "geometry": {"coordinates":[85.552671,25.665577],"type":"Point"}
}