{
  "type": "Feature",
  "properties": {
    "gn:admin1_code":"2.0",
    "gn:admin2_code":"544.0",
    "gn:asciiname":"Jillabode",
    "gn:country_code":"IN",
    "gn:dem":1148,
    "gn:feature_class":"P",
    "gn:feature_code":"PPL",
    "gn:name":"Jillabode",
    "gn:population":0,
    "gn:timezone":"Asia/Kolkata",
    "iso:country":"IN",
    "wof:name":"Jillabode",
    "wof:placetype":"locality"
},
  "geometry": {"coordinates":[82.74127,18.0782],"type":"Point"}
}