{
  "type": "Feature",
  "properties": {
    "gn:admin1_code":"10.0",
    "gn:admin2_code":"80.0",
    "gn:asciiname":"Guzar",
    "gn:country_code":"IN",
    "gn:dem":216,
    "gn:feature_class":"P",
    "gn:feature_code":"PPL",
    "gn:name":"Guz\u0101r",
    "gn:population":0,
    "gn:timezone":"Asia/Kolkata",
    "iso:country":"IN",
    "name:kir_x_preferred":[
        "\u0413\u0443\u0437\u0430\u0440"
    ],
    "name:uzb_x_preferred":[
        "Guzar"
    ],
    "wof:name":"Guzar",
    "wof:placetype":"locality"
},
  "geometry": {"coordinates":[75.8062,29.01967],"type":"Point"}
}