{
  "type": "Feature",
  "properties": {
    "iso:country":"IN",
    "ks:ks_name":"Kithalingi",
    "ks:ks_pop":195,
    "ks:ks_type":"VILLAGE",
    "name:eng_x_preferred":[
        "Kithalingi"
    ],
    "wof:name":"Kithalingi",
    "wof:placetype":"locality",
    "wof:population":195
},
  "geometry": {"coordinates":[83.017595,18.303361],"type":"Point"}
}