{
  "type": "Feature",
  "properties": {
    "gn:admin1_code":"12.0",
    "gn:asciiname":"Hampathar",
    "gn:country_code":"IN",
    "gn:dem":3085,
    "gn:feature_class":"P",
    "gn:feature_code":"PPL",
    "gn:name":"H\u0101mpathar",
    "gn:population":0,
    "gn:timezone":"Asia/Kolkata",
    "iso:country":"IN",
    "wof:name":"Hampathar",
    "wof:placetype":"locality"
},
  "geometry": {"coordinates":[74.33841,34.7019],"type":"Point"}
}