{
  "type": "Feature",
  "properties": {
    "iso:country":"IN",
    "ks:ks_name":"Giri Tola North",
    "ks:ks_pop":267,
    "ks:ks_type":"HABITATION",
    "name:eng_x_preferred":[
        "Giri Tola North"
    ],
    "wof:name":"Giri Tola North",
    "wof:placetype":"locality",
    "wof:population":267
},
  "geometry": {"coordinates":[84.24079999999999,26.534179],"type":"Point"}
}