{
  "type": "Feature",
  "properties": {
    "iso:country":"IN",
    "ks:ks_alt_nam":"HESSASAI",
    "ks:ks_name":"Hessasai",
    "ks:ks_pop":125,
    "ks:ks_type":"HABITATION",
    "name:eng_x_preferred":[
        "Hessasai"
    ],
    "wof:name":"Hessasai",
    "wof:placetype":"locality",
    "wof:population":125
},
  "geometry": {"coordinates":[85.63714899999999,22.368322],"type":"Point"}
}