{
  "type": "Feature",
  "properties": {
    "gn:admin1_code":"11.0",
    "gn:admin2_code":"26.0",
    "gn:asciiname":"Charanj",
    "gn:country_code":"IN",
    "gn:dem":2240,
    "gn:feature_class":"P",
    "gn:feature_code":"PPL",
    "gn:name":"Char\u0101nj",
    "gn:population":0,
    "gn:timezone":"Asia/Kolkata",
    "iso:country":"IN",
    "wof:name":"Charanj",
    "wof:placetype":"locality"
},
  "geometry": {"coordinates":[77.50888,31.41216],"type":"Point"}
}