{
  "type": "Feature",
  "properties": {
    "iso:country":"IN",
    "ks:ks_name":"Shahnagar Sindhiyon Ki Dhani",
    "ks:ks_pop":630,
    "ks:ks_type":"HABITATION",
    "name:eng_x_preferred":[
        "Shahnagar Sindhiyon Ki Dhani"
    ],
    "wof:name":"Shahnagar Sindhiyon Ki Dhani",
    "wof:placetype":"locality",
    "wof:population":630
},
  "geometry": {"coordinates":[72.049858,25.635772],"type":"Point"}
}