{
  "type": "Feature",
  "properties": {
    "gn:admin1_code":"11",
    "gn:admin2_code":"27.0",
    "gn:asciiname":"Kafru",
    "gn:country_code":"IN",
    "gn:dem":1824,
    "gn:feature_class":"P",
    "gn:feature_code":"PPL",
    "gn:name":"Kafru",
    "gn:population":0,
    "gn:timezone":"Asia/Kolkata",
    "iso:country":"IN",
    "wof:name":"Kafru",
    "wof:placetype":"locality"
},
  "geometry": {"coordinates":[76.85809999999999,32.00526],"type":"Point"}
}