{
  "type": "Feature",
  "properties": {
    "gn:admin1_code":"11",
    "gn:admin2_code":"24.0",
    "gn:asciiname":"Meti",
    "gn:country_code":"IN",
    "gn:dem":995,
    "gn:feature_class":"P",
    "gn:feature_code":"PPL",
    "gn:name":"Meti",
    "gn:population":0,
    "gn:timezone":"Asia/Kolkata",
    "iso:country":"IN",
    "wof:name":"Meti",
    "wof:placetype":"locality"
},
  "geometry": {"coordinates":[76.27665,32.21174],"type":"Point"}
}