{
  "type": "Feature",
  "properties": {
    "gn:admin1_code":"35.0",
    "gn:admin2_code":"457.0",
    "gn:asciiname":"Wara",
    "gn:country_code":"IN",
    "gn:dem":309,
    "gn:feature_class":"P",
    "gn:feature_code":"PPL",
    "gn:name":"W\u0101r\u0101",
    "gn:population":0,
    "gn:timezone":"Asia/Kolkata",
    "iso:country":"IN",
    "ks:ks_name":"Wara",
    "ks:ks_pop":2601,
    "ks:ks_type":"VILLAGE",
    "ks:ks_uagg_main":0,
    "name:ceb_x_preferred":[
        "Wara"
    ],
    "name:deu_x_preferred":[
        "Wara"
    ],
    "name:eng_x_preferred":[
        "Wara"
    ],
    "name:fra_x_preferred":[
        "Wara"
    ],
    "name:swe_x_preferred":[
        "Wara"
    ],
    "wof:name":"Wara",
    "wof:placetype":"neighbourhood",
    "wof:population":2601
},
  "geometry": {"coordinates":[80.063187,21.773779],"type":"Point"}
}