{
  "type": "Feature",
  "properties": {
    "iso:country":"IN",
    "ks:ks_name":"Panjania",
    "ks:ks_pop":2023,
    "ks:ks_type":"VILLAGE",
    "name:eng_x_preferred":[
        "Panjania"
    ],
    "wof:name":"Panjania",
    "wof:placetype":"locality",
    "wof:population":2023
},
  "geometry": {"coordinates":[86.739923,23.888685],"type":"Point"}
}