{
  "type": "Feature",
  "properties": {
    "gn:admin1_code":"40",
    "gn:admin2_code":"539.0",
    "gn:asciiname":"Ketepalli",
    "gn:country_code":"IN",
    "gn:dem":250,
    "gn:feature_class":"P",
    "gn:feature_code":"PPL",
    "gn:name":"Ketepalli",
    "gn:population":0,
    "gn:timezone":"Asia/Kolkata",
    "iso:country":"IN",
    "wof:name":"Ketepalli",
    "wof:placetype":"locality"
},
  "geometry": {"coordinates":[79.00238,16.59331],"type":"Point"}
}