{
  "type": "Feature",
  "properties": {
    "iso:country":"IN",
    "ks:ks_name":"Sipaiyon Ki Dhani",
    "ks:ks_pop":1613,
    "ks:ks_type":"HABITATION",
    "name:eng_x_preferred":[
        "Sipaiyon Ki Dhani"
    ],
    "wof:name":"Sipaiyon Ki Dhani",
    "wof:placetype":"locality",
    "wof:population":1613
},
  "geometry": {"coordinates":[71.304725,24.75385],"type":"Point"}
}