{
  "type": "Feature",
  "properties": {
    "gn:admin1_code":"35",
    "gn:admin2_code":"430.0",
    "gn:asciiname":"Kona",
    "gn:country_code":"IN",
    "gn:dem":332,
    "gn:feature_class":"P",
    "gn:feature_code":"PPL",
    "gn:name":"Kona",
    "gn:population":0,
    "gn:timezone":"Asia/Kolkata",
    "iso:country":"IN",
    "name:cat_x_preferred":[
        "Kona"
    ],
    "name:ceb_x_preferred":[
        "Kona"
    ],
    "name:dan_x_preferred":[
        "Kona"
    ],
    "name:deu_x_preferred":[
        "Kona"
    ],
    "name:fin_x_preferred":[
        "Kona"
    ],
    "name:fra_x_preferred":[
        "Kona"
    ],
    "name:nno_x_preferred":[
        "Kona"
    ],
    "name:spa_x_preferred":[
        "Kona"
    ],
    "name:swe_x_preferred":[
        "Kona"
    ],
    "wof:name":"Kona",
    "wof:placetype":"locality"
},
  "geometry": {"coordinates":[81.82460999999998,24.69998],"type":"Point"}
}