{
  "type": "Feature",
  "properties": {
    "gn:admin1_code":"35",
    "gn:admin2_code":"423.0",
    "gn:asciiname":"Pohri",
    "gn:country_code":"IN",
    "gn:dem":428,
    "gn:feature_class":"P",
    "gn:feature_code":"PPL",
    "gn:name":"Pohri",
    "gn:population":0,
    "gn:timezone":"Asia/Kolkata",
    "iso:country":"IN",
    "name:und_x_variant":[
        "Paur\u012b"
    ],
    "wof:name":"Pohri",
    "wof:placetype":"locality"
},
  "geometry": {"coordinates":[77.36036999999997,25.53637],"type":"Point"}
}