{
  "type": "Feature",
  "properties": {
    "iso:country":"IN",
    "ks:ks_name":"Kotegadde",
    "ks:ks_pop":30,
    "ks:ks_type":"HABITATION",
    "name:eng_x_preferred":[
        "Kotegadde"
    ],
    "wof:name":"Kotegadde",
    "wof:placetype":"locality",
    "wof:population":30
},
  "geometry": {"coordinates":[75.20853099999999,13.435197],"type":"Point"}
}