{
  "type": "Feature",
  "properties": {
    "iso:country":"IN",
    "ks:ks_alt_nam":"Kaml\u0101pur",
    "ks:ks_name":"Kamlapur",
    "ks:ks_type":"VILLAGE",
    "name:eng_x_preferred":[
        "Kamlapur"
    ],
    "name:eng_x_variant":[
        "Kaml\u0101pur"
    ],
    "wof:name":"Kamlapur",
    "wof:placetype":"locality"
},
  "geometry": {"coordinates":[77.54600499999999,25.967971],"type":"Point"}
}