{
  "type": "Feature",
  "properties": {
    "iso:country":"IN",
    "ks:ks_alt_nam":"Bhodan ka Wela",
    "ks:ks_name":"Bhodan Ka Wela",
    "ks:ks_pop":1114,
    "ks:ks_type":"HABITATION",
    "name:eng_x_preferred":[
        "Bhodan Ka Wela"
    ],
    "wof:name":"Bhodan Ka Wela",
    "wof:placetype":"locality",
    "wof:population":1114
},
  "geometry": {"coordinates":[74.180379,23.872373],"type":"Point"}
}