{
  "type": "Feature",
  "properties": {
    "iso:country":"IN",
    "ks:ks_name":"Mahespur",
    "ks:ks_pop":621,
    "ks:ks_type":"VILLAGE",
    "name:eng_x_preferred":[
        "Mahespur"
    ],
    "wof:name":"Mahespur",
    "wof:placetype":"locality",
    "wof:population":621
},
  "geometry": {"coordinates":[83.642884,22.487204],"type":"Point"}
}