{
  "type": "Feature",
  "properties": {
    "iso:country":"IN",
    "ks:ks_name":"Hakabedapara",
    "ks:ks_pop":99,
    "ks:ks_type":"HABITATION",
    "name:eng_x_preferred":[
        "Hakabedapara"
    ],
    "wof:name":"Hakabedapara",
    "wof:placetype":"locality",
    "wof:population":99
},
  "geometry": {"coordinates":[81.40855000000001,19.524753],"type":"Point"}
}