{
  "type": "Feature",
  "properties": {
    "iso:country":"IN",
    "ks:ks_alt_nam":"SALAMPUR",
    "ks:ks_name":"Salampur",
    "ks:ks_pop":257,
    "ks:ks_type":"HABITATION",
    "name:eng_x_preferred":[
        "Salampur"
    ],
    "wof:name":"Salampur",
    "wof:placetype":"locality",
    "wof:population":257
},
  "geometry": {"coordinates":[85.85365899999999,24.951376],"type":"Point"}
}