{
  "type": "Feature",
  "properties": {
    "gn:admin1_code":"13.0",
    "gn:admin2_code":"592.0",
    "gn:asciiname":"Kannirakkod",
    "gn:country_code":"IN",
    "gn:dem":8,
    "gn:feature_class":"P",
    "gn:feature_code":"PPL",
    "gn:name":"K\u0101nn\u012brakk\u014dd",
    "gn:population":0,
    "gn:timezone":"Asia/Kolkata",
    "iso:country":"IN",
    "wof:name":"Kannirakkod",
    "wof:placetype":"locality"
},
  "geometry": {"coordinates":[75.95227,10.90239],"type":"Point"}
}