{
  "type": "Feature",
  "properties": {
    "iso:country":"IN",
    "ks:ks_alt_nam":"kendgarha",
    "ks:ks_name":"Kendgarha",
    "ks:ks_pop":333,
    "ks:ks_type":"HABITATION",
    "name:eng_x_preferred":[
        "Kendgarha"
    ],
    "wof:name":"Kendgarha",
    "wof:placetype":"locality",
    "wof:population":333
},
  "geometry": {"coordinates":[86.38081699999999,23.656362],"type":"Point"}
}