{
  "type": "Feature",
  "properties": {
    "iso:country":"IN",
    "ks:ks_name":"Ekari",
    "ks:ks_pop":1317,
    "ks:ks_type":"VILLAGE",
    "ks:ks_uagg_main":0,
    "name:eng_x_preferred":[
        "Ekari"
    ],
    "wof:name":"Ekari",
    "wof:placetype":"neighbourhood",
    "wof:population":1317
},
  "geometry": {"coordinates":[85.76490200000001,26.494413],"type":"Point"}
}