{
  "type": "Feature",
  "properties": {
    "gn:admin1_code":"35.0",
    "gn:admin2_code":"453.0",
    "gn:asciiname":"Dadargaon",
    "gn:country_code":"IN",
    "gn:dem":746,
    "gn:feature_class":"P",
    "gn:feature_code":"PPL",
    "gn:name":"Dadargaon",
    "gn:population":0,
    "gn:timezone":"Asia/Kolkata",
    "iso:country":"IN",
    "wof:name":"Dadargaon",
    "wof:placetype":"locality"
},
  "geometry": {"coordinates":[80.55171999999997,23.07229],"type":"Point"}
}