{
  "type": "Feature",
  "properties": {
    "iso:country":"IN",
    "ks:ks_alt_nam":"NAGLA HARISINGH",
    "ks:ks_name":"Nagla Harisingh",
    "ks:ks_pop":56,
    "ks:ks_type":"HABITATION",
    "ks:ks_uagg_main":0,
    "name:eng_x_preferred":[
        "Nagla Harisingh"
    ],
    "wof:name":"Nagla Harisingh",
    "wof:placetype":"neighbourhood",
    "wof:population":56
},
  "geometry": {"coordinates":[78.995172,26.84871],"type":"Point"}
}