{
  "type": "Feature",
  "properties": {
    "gn:admin1_code":"35.0",
    "gn:admin2_code":"438.0",
    "gn:asciiname":"Gajgota",
    "gn:country_code":"IN",
    "gn:dem":287,
    "gn:feature_class":"P",
    "gn:feature_code":"PPL",
    "gn:name":"G\u0101jgota",
    "gn:population":0,
    "gn:timezone":"Asia/Kolkata",
    "iso:country":"IN",
    "ks:ks_alt_nam":"G\u0101jgota",
    "ks:ks_name":"Gajgota",
    "ks:ks_pop":4243,
    "ks:ks_type":"VILLAGE",
    "name:eng_x_preferred":[
        "Gajgota"
    ],
    "name:eng_x_variant":[
        "G\u0101jgota"
    ],
    "wof:name":"Gajgota",
    "wof:placetype":"locality",
    "wof:population":4243
},
  "geometry": {"coordinates":[74.593253,22.173965],"type":"Point"}
}