{
  "type": "Feature",
  "properties": {
    "iso:country":"IN",
    "ks:ks_name":"Silakot",
    "ks:ks_pop":78,
    "ks:ks_type":"VILLAGE",
    "name:eng_x_preferred":[
        "Silakot"
    ],
    "wof:name":"Silakot",
    "wof:placetype":"locality",
    "wof:population":78
},
  "geometry": {"coordinates":[79.238561,30.042852],"type":"Point"}
}