{
  "type": "Feature",
  "properties": {
    "gn:admin1_code":"36",
    "gn:admin2_code":"135.0",
    "gn:asciiname":"Bujpur Asa",
    "gn:country_code":"IN",
    "gn:dem":198,
    "gn:feature_class":"P",
    "gn:feature_code":"PPL",
    "gn:name":"B\u016bjpur \u0100sa",
    "gn:population":0,
    "gn:timezone":"Asia/Kolkata",
    "iso:country":"IN",
    "ks:ks_alt_nam":"B\u016bjpur \u0100sa",
    "ks:ks_name":"Bujpur Asa",
    "ks:ks_type":"VILLAGE",
    "ks:ks_uagg_main":0,
    "name:eng_x_preferred":[
        "Bujpur Asa"
    ],
    "name:eng_x_variant":[
        "B\u016bjpur \u0100sa"
    ],
    "wof:name":"Bujpur Asa",
    "wof:placetype":"neighbourhood"
},
  "geometry": {"coordinates":[78.90692,28.851199],"type":"Point"}
}