{
  "type": "Feature",
  "properties": {
    "gn:admin1_code":"9.0",
    "gn:admin2_code":"472",
    "gn:asciiname":"Chorimal",
    "gn:country_code":"IN",
    "gn:dem":259,
    "gn:feature_class":"P",
    "gn:feature_code":"PPL",
    "gn:name":"Chorimal",
    "gn:population":0,
    "gn:timezone":"Asia/Kolkata",
    "iso:country":"IN",
    "name:und_x_variant":[
        "Chorunal",
        "Chorimal"
    ],
    "wof:name":"Chorimal",
    "wof:placetype":"locality"
},
  "geometry": {"coordinates":[73.30799,23.86325],"type":"Point"}
}