{
  "type": "Feature",
  "properties": {
    "gn:admin1_code":"19.0",
    "gn:admin2_code":"573.0",
    "gn:asciiname":"Choknahalli",
    "gn:country_code":"IN",
    "gn:dem":738,
    "gn:feature_class":"P",
    "gn:feature_code":"PPL",
    "gn:name":"Choknahalli",
    "gn:population":0,
    "gn:timezone":"Asia/Kolkata",
    "iso:country":"IN",
    "wof:name":"Choknahalli",
    "wof:placetype":"locality"
},
  "geometry": {"coordinates":[76.82353000000001,12.6388],"type":"Point"}
}