{
  "type": "Feature",
  "properties": {
    "iso:country":"IN",
    "ks:ks_name":"Adabari Pt.I",
    "ks:ks_pop":3288,
    "ks:ks_type":"VILLAGE",
    "ks:ks_uagg_main":0,
    "name:eng_x_preferred":[
        "Adabari Pt.I"
    ],
    "wof:name":"Adabari Pt.I",
    "wof:placetype":"neighbourhood",
    "wof:population":3288
},
  "geometry": {"coordinates":[89.931527,26.034949],"type":"Point"}
}