{
  "type": "Feature",
  "properties": {
    "gn:admin1_code":"36.0",
    "gn:admin2_code":"181.0",
    "gn:asciiname":"Purwa Kori",
    "gn:country_code":"IN",
    "gn:dem":150,
    "gn:feature_class":"P",
    "gn:feature_code":"PPL",
    "gn:name":"Purwa Kori",
    "gn:population":0,
    "gn:timezone":"Asia/Kolkata",
    "iso:country":"IN",
    "wof:name":"Purwa Kori",
    "wof:placetype":"neighbourhood"
},
  "geometry": {"coordinates":[82.12147,27.7766],"type":"Point"}
}