{
  "type": "Feature",
  "properties": {
    "iso:country":"IN",
    "ks:ks_name":"Purasgod",
    "ks:ks_pop":37,
    "ks:ks_type":"HABITATION",
    "name:eng_x_preferred":[
        "Purasgod"
    ],
    "wof:name":"Purasgod",
    "wof:placetype":"locality",
    "wof:population":37
},
  "geometry": {"coordinates":[74.53426399999999,14.420092],"type":"Point"}
}