{
  "type": "Feature",
  "properties": {
    "iso:country":"IN",
    "ks:ks_name":"Konnangulam",
    "ks:ks_pop":487,
    "ks:ks_type":"HABITATION",
    "name:eng_x_preferred":[
        "Konnangulam"
    ],
    "wof:name":"Konnangulam",
    "wof:placetype":"locality",
    "wof:population":487
},
  "geometry": {"coordinates":[76.72251,9.45126],"type":"Point"}
}