{
  "type": "Feature",
  "properties": {
    "iso:country":"IN",
    "ks:ks_name":"Loniyan Purwa-i",
    "ks:ks_pop":317,
    "ks:ks_type":"HABITATION",
    "name:eng_x_preferred":[
        "Loniyan Purwa-i"
    ],
    "wof:name":"Loniyan Purwa-i",
    "wof:placetype":"locality",
    "wof:population":317
},
  "geometry": {"coordinates":[81.90858,27.568787],"type":"Point"}
}