{
  "type": "Feature",
  "properties": {
    "gn:admin1_code":"38.0",
    "gn:admin2_code":"351.0",
    "gn:asciiname":"Malia Chak",
    "gn:country_code":"IN",
    "gn:dem":61,
    "gn:feature_class":"P",
    "gn:feature_code":"PPL",
    "gn:name":"Malia Chak",
    "gn:population":0,
    "gn:timezone":"Asia/Kolkata",
    "iso:country":"IN",
    "wof:name":"Malia Chak",
    "wof:placetype":"locality"
},
  "geometry": {"coordinates":[87.23380999999998,25.03427000000001],"type":"Point"}
}