{
  "type": "Feature",
  "properties": {
    "iso:country":"IN",
    "ks:ks_name":"Peetha Pura",
    "ks:ks_pop":969,
    "ks:ks_type":"HABITATION",
    "name:eng_x_preferred":[
        "Peetha Pura"
    ],
    "wof:name":"Peetha Pura",
    "wof:placetype":"locality",
    "wof:population":969
},
  "geometry": {"coordinates":[74.191506,23.425653],"type":"Point"}
}