{
  "type": "Feature",
  "properties": {
    "iso:country":"IN",
    "ks:ks_name":"Kadamtal",
    "ks:ks_pop":259,
    "ks:ks_type":"VILLAGE",
    "name:eng_x_preferred":[
        "Kadamtal"
    ],
    "wof:name":"Kadamtal",
    "wof:placetype":"locality",
    "wof:population":259
},
  "geometry": {"coordinates":[84.173855,19.020882],"type":"Point"}
}