{
  "type": "Feature",
  "properties": {
    "iso:country":"IN",
    "ks:ks_name":"Thakur Basti",
    "ks:ks_pop":945,
    "ks:ks_type":"HABITATION",
    "name:eng_x_preferred":[
        "Thakur Basti"
    ],
    "wof:name":"Thakur Basti",
    "wof:placetype":"locality",
    "wof:population":945
},
  "geometry": {"coordinates":[82.24902,25.732973],"type":"Point"}
}