{
  "type": "Feature",
  "properties": {
    "iso:country":"IN",
    "ks:ks_name":"Murlamath",
    "ks:ks_pop":78,
    "ks:ks_type":"HABITATION",
    "name:eng_x_preferred":[
        "Murlamath"
    ],
    "wof:name":"Murlamath",
    "wof:placetype":"locality",
    "wof:population":78
},
  "geometry": {"coordinates":[85.00178699999999,25.098564],"type":"Point"}
}