{
  "type": "Feature",
  "properties": {
    "iso:country":"IN",
    "ks:ks_name":"Karamtola",
    "ks:ks_pop":110,
    "ks:ks_type":"VILLAGE",
    "name:eng_x_preferred":[
        "Karamtola"
    ],
    "wof:name":"Karamtola",
    "wof:placetype":"locality",
    "wof:population":110
},
  "geometry": {"coordinates":[87.469196,25.026248],"type":"Point"}
}