{
  "type": "Feature",
  "properties": {
    "iso:country":"IN",
    "ks:ks_name":"Kukudagada",
    "ks:ks_pop":266,
    "ks:ks_type":"VILLAGE",
    "name:eng_x_preferred":[
        "Kukudagada"
    ],
    "wof:name":"Kukudagada",
    "wof:placetype":"locality",
    "wof:population":266
},
  "geometry": {"coordinates":[82.942508,19.430666],"type":"Point"}
}