{
  "type": "Feature",
  "properties": {
    "iso:country":"IN",
    "ks:ks_name":"Ashoki",
    "ks:ks_pop":371,
    "ks:ks_type":"VILLAGE",
    "name:eng_x_preferred":[
        "Ashoki"
    ],
    "wof:name":"Ashoki",
    "wof:placetype":"locality",
    "wof:population":371
},
  "geometry": {"coordinates":[86.120786,22.053744],"type":"Point"}
}