{
  "type": "Feature",
  "properties": {
    "iso:country":"IN",
    "ks:ks_name":"Karamata",
    "ks:ks_pop":120,
    "ks:ks_type":"HABITATION",
    "name:eng_x_preferred":[
        "Karamata"
    ],
    "wof:name":"Karamata",
    "wof:placetype":"locality",
    "wof:population":120
},
  "geometry": {"coordinates":[82.0106,20.033328],"type":"Point"}
}