{
  "type": "Feature",
  "properties": {
    "iso:country":"IN",
    "ks:ks_name":"Uperbera",
    "ks:ks_pop":236,
    "ks:ks_type":"VILLAGE",
    "name:eng_x_preferred":[
        "Uperbera"
    ],
    "wof:name":"Uperbera",
    "wof:placetype":"locality",
    "wof:population":236
},
  "geometry": {"coordinates":[85.98662400000001,22.8548],"type":"Point"}
}