{
  "type": "Feature",
  "properties": {
    "iso:country":"IN",
    "ks:ks_alt_nam":"Borra pooluguda",
    "ks:ks_name":"Borra Pooluguda",
    "ks:ks_pop":130,
    "ks:ks_type":"HABITATION",
    "name:eng_x_preferred":[
        "Borra Pooluguda"
    ],
    "wof:name":"Borra Pooluguda",
    "wof:placetype":"locality",
    "wof:population":130
},
  "geometry": {"coordinates":[83.055581,18.179952],"type":"Point"}
}