{
  "type": "Feature",
  "properties": {
    "iso:country":"IN",
    "ks:ks_name":"Atpadkar Vasti",
    "ks:ks_pop":193,
    "ks:ks_type":"HABITATION",
    "name:eng_x_preferred":[
        "Atpadkar Vasti"
    ],
    "wof:name":"Atpadkar Vasti",
    "wof:placetype":"locality",
    "wof:population":193
},
  "geometry": {"coordinates":[75.081018,16.886764],"type":"Point"}
}