{
  "type": "Feature",
  "properties": {
    "iso:country":"IN",
    "ks:ks_alt_nam":"Muthugagadde podu",
    "ks:ks_name":"Muthugagadde Podu",
    "ks:ks_pop":120,
    "ks:ks_type":"HABITATION",
    "name:eng_x_preferred":[
        "Muthugagadde Podu"
    ],
    "wof:name":"Muthugagadde Podu",
    "wof:placetype":"locality",
    "wof:population":120
},
  "geometry": {"coordinates":[77.143539,11.982397],"type":"Point"}
}