{
  "type": "Feature",
  "properties": {
    "iso:country":"IN",
    "ks:ks_alt_nam":"BANGLA SAI",
    "ks:ks_name":"Bangla Sai",
    "ks:ks_pop":227,
    "ks:ks_type":"HABITATION",
    "name:eng_x_preferred":[
        "Bangla Sai"
    ],
    "wof:name":"Bangla Sai",
    "wof:placetype":"locality",
    "wof:population":227
},
  "geometry": {"coordinates":[85.55364400000001,22.210536],"type":"Point"}
}