{
  "type": "Feature",
  "properties": {
    "iso:country":"IN",
    "ks:ks_name":"Budaguda",
    "ks:ks_pop":356,
    "ks:ks_type":"HABITATION",
    "ks:ks_uagg_main":0,
    "name:eng_x_preferred":[
        "Budaguda"
    ],
    "wof:name":"Budaguda",
    "wof:placetype":"neighbourhood",
    "wof:population":356
},
  "geometry": {"coordinates":[82.242028,19.374966],"type":"Point"}
}