{
  "type": "Feature",
  "properties": {
    "gn:admin1_code":"38.0",
    "gn:admin2_code":"360.0",
    "gn:asciiname":"Meru",
    "gn:country_code":"IN",
    "gn:dem":592,
    "gn:feature_class":"P",
    "gn:feature_code":"PPL",
    "gn:name":"Meru",
    "gn:population":0,
    "gn:timezone":"Asia/Kolkata",
    "iso:country":"IN",
    "name:bel_x_preferred":[
        "\u041c\u0435\u0440\u0443"
    ],
    "name:bpy_x_preferred":[
        "\u09ae\u09c7\u09b0\u09c1"
    ],
    "name:bul_x_preferred":[
        "\u041c\u0435\u0440\u0443"
    ],
    "name:ceb_x_preferred":[
        "Meru"
    ],
    "name:deu_x_preferred":[
        "Meru"
    ],
    "name:fas_x_preferred":[
        "\u0645\u0631\u0648"
    ],
    "name:fin_x_preferred":[
        "Meru"
    ],
    "name:fra_x_preferred":[
        "Meru"
    ],
    "name:heb_x_preferred":[
        "\u05de\u05e8\u05d5"
    ],
    "name:hrv_x_preferred":[
        "Meru"
    ],
    "name:hun_x_preferred":[
        "Meru"
    ],
    "name:ind_x_preferred":[
        "Meru"
    ],
    "name:ita_x_preferred":[
        "Meru"
    ],
    "name:msa_x_preferred":[
        "Meru"
    ],
    "name:new_x_preferred":[
        "\u092e\u0947\u0930\u0941"
    ],
    "name:nld_x_preferred":[
        "Meru"
    ],
    "name:pol_x_preferred":[
        "Meru"
    ],
    "name:rus_x_preferred":[
        "\u041c\u0435\u0440\u0443"
    ],
    "name:slk_x_preferred":[
        "Meru"
    ],
    "name:srp_x_preferred":[
        "\u041c\u0435\u0440\u0443"
    ],
    "name:swa_x_preferred":[
        "Meru"
    ],
    "name:swe_x_preferred":[
        "Meru"
    ],
    "name:ukr_x_preferred":[
        "\u041c\u0435\u0440\u0443"
    ],
    "wof:name":"Meru",
    "wof:placetype":"locality"
},
  "geometry": {"coordinates":[85.46731,24.00967],"type":"Point"}
}