{
  "type": "Feature",
  "properties": {
    "iso:country":"IN",
    "ks:ks_name":"Teliwadi",
    "ks:ks_pop":114,
    "ks:ks_type":"HABITATION",
    "name:eng_x_preferred":[
        "Teliwadi"
    ],
    "wof:name":"Teliwadi",
    "wof:placetype":"locality",
    "wof:population":114
},
  "geometry": {"coordinates":[73.76815499999999,15.947157],"type":"Point"}
}