{
  "type": "Feature",
  "properties": {
    "iso:country":"IN",
    "ks:ks_name":"Kaitha",
    "ks:ks_pop":10,
    "ks:ks_type":"VILLAGE",
    "name:eng_x_preferred":[
        "Kaitha"
    ],
    "wof:name":"Kaitha",
    "wof:placetype":"locality",
    "wof:population":10
},
  "geometry": {"coordinates":[85.770392,20.908429],"type":"Point"}
}