{
  "type": "Feature",
  "properties": {
    "iso:country":"IN",
    "ks:ks_name":"Koylipur",
    "ks:ks_pop":137,
    "ks:ks_type":"HABITATION",
    "name:eng_x_preferred":[
        "Koylipur"
    ],
    "wof:name":"Koylipur",
    "wof:placetype":"locality",
    "wof:population":137
},
  "geometry": {"coordinates":[80.995395,27.853655],"type":"Point"}
}