{
  "type": "Feature",
  "properties": {
    "iso:country":"IN",
    "ks:ks_alt_nam":"Gutuh\u0101tu",
    "ks:ks_name":"Gutuhatu",
    "ks:ks_pop":758,
    "ks:ks_type":"VILLAGE",
    "name:eng_x_preferred":[
        "Gutuhatu"
    ],
    "name:eng_x_variant":[
        "Gutuh\u0101tu"
    ],
    "wof:name":"Gutuhatu",
    "wof:placetype":"locality",
    "wof:population":758
},
  "geometry": {"coordinates":[85.717782,22.665843],"type":"Point"}
}