{
  "type": "Feature",
  "properties": {
    "gn:admin1_code":"19.0",
    "gn:admin2_code":"570.0",
    "gn:asciiname":"Mundagodu",
    "gn:country_code":"IN",
    "gn:dem":1045,
    "gn:feature_class":"P",
    "gn:feature_code":"PPL",
    "gn:name":"Mundagodu",
    "gn:population":0,
    "gn:timezone":"Asia/Kolkata",
    "iso:country":"IN",
    "wof:name":"Mundagodu",
    "wof:placetype":"locality"
},
  "geometry": {"coordinates":[75.52725,13.08841],"type":"Point"}
}