{
  "type": "Feature",
  "properties": {
    "iso:country":"IN",
    "ks:ks_name":"Ajodhyakundu",
    "ks:ks_pop":0,
    "ks:ks_type":"VILLAGE",
    "name:eng_x_preferred":[
        "Ajodhyakundu"
    ],
    "wof:name":"Ajodhyakundu",
    "wof:placetype":"locality",
    "wof:population":0
},
  "geometry": {"coordinates":[87.712301,22.707548],"type":"Point"}
}