{
  "type": "Feature",
  "properties": {
    "iso:country":"IN",
    "ks:ks_name":"Vinayk Kind",
    "ks:ks_pop":189,
    "ks:ks_type":"HABITATION",
    "name:eng_x_preferred":[
        "Vinayk Kind"
    ],
    "wof:name":"Vinayk Kind",
    "wof:placetype":"locality",
    "wof:population":189
},
  "geometry": {"coordinates":[73.531944,19.9225],"type":"Point"}
}