{
  "type": "Feature",
  "properties": {
    "gn:admin1_code":"39.0",
    "gn:admin2_code":"63.0",
    "gn:asciiname":"Kilabkhet",
    "gn:country_code":"IN",
    "gn:dem":1811,
    "gn:feature_class":"P",
    "gn:feature_code":"PPL",
    "gn:name":"Kil\u0101bkhet",
    "gn:population":0,
    "gn:timezone":"Asia/Kolkata",
    "iso:country":"IN",
    "wof:name":"Kilabkhet",
    "wof:placetype":"locality"
},
  "geometry": {"coordinates":[79.52103000000002,29.95892000000001],"type":"Point"}
}