{
  "type": "Feature",
  "properties": {
    "gn:admin1_code":"24.0",
    "gn:admin2_code":"100.0",
    "gn:asciiname":"Chak Bhojasar",
    "gn:country_code":"IN",
    "gn:dem":205,
    "gn:feature_class":"P",
    "gn:feature_code":"PPL",
    "gn:name":"Chak Bhojasar",
    "gn:population":0,
    "gn:timezone":"Asia/Kolkata",
    "iso:country":"IN",
    "name:und_x_variant":[
        "Mithli"
    ],
    "wof:name":"Chak Bhojasar",
    "wof:placetype":"locality"
},
  "geometry": {"coordinates":[75.14282,29.16931],"type":"Point"}
}