{
  "type": "Feature",
  "properties": {
    "iso:country":"IN",
    "ks:ks_name":"Giranga",
    "ks:ks_pop":2878,
    "ks:ks_type":"VILLAGE",
    "ks:ks_uagg_main":0,
    "name:eng_x_preferred":[
        "Giranga"
    ],
    "wof:name":"Giranga",
    "wof:placetype":"neighbourhood",
    "wof:population":2878
},
  "geometry": {"coordinates":[85.16869699999999,20.852288],"type":"Point"}
}