{
  "type": "Feature",
  "properties": {
    "gn:admin1_code":"36.0",
    "gn:admin2_code":"182.0",
    "gn:asciiname":"Nayanagar",
    "gn:country_code":"IN",
    "gn:dem":105,
    "gn:feature_class":"P",
    "gn:feature_code":"PPL",
    "gn:name":"Nay\u0101nagar",
    "gn:population":0,
    "gn:timezone":"Asia/Kolkata",
    "iso:country":"IN",
    "ks:ks_name":"Naya Nager",
    "ks:ks_pop":2593,
    "ks:ks_type":"VILLAGE",
    "ks:ks_uagg_main":0,
    "name:eng_x_preferred":[
        "Naya Nager"
    ],
    "wof:name":"Naya Nager",
    "wof:placetype":"neighbourhood",
    "wof:population":2593
},
  "geometry": {"coordinates":[82.317026,27.170249],"type":"Point"}
}