{
  "type": "Feature",
  "properties": {
    "gn:admin1_code":"19.0",
    "gn:admin2_code":"569.0",
    "gn:asciiname":"Tenka Mijar",
    "gn:country_code":"IN",
    "gn:dem":142,
    "gn:feature_class":"P",
    "gn:feature_code":"PPLL",
    "gn:name":"Tenka Mij\u0101r",
    "gn:population":0,
    "gn:timezone":"Asia/Kolkata",
    "iso:country":"IN",
    "ks:ks_alt_nam":"Tenka Mij\u0101r",
    "ks:ks_name":"Tenka Mijar",
    "ks:ks_type":"VILLAGE",
    "name:eng_x_preferred":[
        "Tenka Mijar"
    ],
    "name:eng_x_variant":[
        "Tenka Mij\u0101r"
    ],
    "wof:name":"Tenka Mijar",
    "wof:placetype":"locality"
},
  "geometry": {"coordinates":[74.950867,13.024009],"type":"Point"}
}