{
  "type": "Feature",
  "properties": {
    "iso:country":"IN",
    "ks:ks_alt_nam":"kakkadavu",
    "ks:ks_name":"Kakkadavu",
    "ks:ks_pop":890,
    "ks:ks_type":"HABITATION",
    "name:eng_x_preferred":[
        "Kakkadavu"
    ],
    "wof:name":"Kakkadavu",
    "wof:placetype":"locality",
    "wof:population":890
},
  "geometry": {"coordinates":[76.008301,11.719462],"type":"Point"}
}