{
  "type": "Feature",
  "properties": {
    "iso:country":"IN",
    "ks:ks_name":"Malwadiwasti",
    "ks:ks_pop":314,
    "ks:ks_type":"HABITATION",
    "name:eng_x_preferred":[
        "Malwadiwasti"
    ],
    "wof:name":"Malwadiwasti",
    "wof:placetype":"locality",
    "wof:population":314
},
  "geometry": {"coordinates":[75.21473,18.456438],"type":"Point"}
}