{
  "type": "Feature",
  "properties": {
    "iso:country":"IN",
    "ks:ks_name":"Belgawhan",
    "ks:ks_pop":0,
    "ks:ks_type":"VILLAGE",
    "name:eng_x_preferred":[
        "Belgawhan"
    ],
    "wof:name":"Belgawhan",
    "wof:placetype":"locality",
    "wof:population":0
},
  "geometry": {"coordinates":[77.597348,19.355648],"type":"Point"}
}