{
  "type": "Feature",
  "properties": {
    "gn:admin1_code":"34.0",
    "gn:admin2_code":"219.0",
    "gn:asciiname":"Darwa",
    "gn:country_code":"IN",
    "gn:dem":59,
    "gn:feature_class":"P",
    "gn:feature_code":"PPL",
    "gn:name":"Darwa",
    "gn:population":0,
    "gn:timezone":"Asia/Kolkata",
    "iso:country":"IN",
    "ks:ks_name":"Darwa",
    "ks:ks_pop":1669,
    "ks:ks_type":"VILLAGE",
    "ks:ks_uagg_main":0,
    "name:eng_x_preferred":[
        "Darwa"
    ],
    "wof:name":"Darwa",
    "wof:placetype":"neighbourhood",
    "wof:population":1669
},
  "geometry": {"coordinates":[84.800943,26.013929],"type":"Point"}
}