{
  "type": "Feature",
  "properties": {
    "iso:country":"IN",
    "ks:ks_alt_nam":"PUROHIT KI DHANI",
    "ks:ks_name":"Purohit Ki Dhani",
    "ks:ks_pop":50,
    "ks:ks_type":"HABITATION",
    "name:eng_x_preferred":[
        "Purohit Ki Dhani"
    ],
    "wof:name":"Purohit Ki Dhani",
    "wof:placetype":"locality",
    "wof:population":50
},
  "geometry": {"coordinates":[74.347053,29.222917],"type":"Point"}
}