{
  "type": "Feature",
  "properties": {
    "gn:admin1_code":"21.0",
    "gn:admin2_code":"375",
    "gn:asciiname":"Joruri",
    "gn:country_code":"IN",
    "gn:dem":497,
    "gn:feature_class":"P",
    "gn:feature_code":"PPL",
    "gn:name":"Joruri",
    "gn:population":0,
    "gn:timezone":"Asia/Kolkata",
    "iso:country":"IN",
    "wof:name":"Joruri",
    "wof:placetype":"locality"
},
  "geometry": {"coordinates":[85.42319000000001,21.95443],"type":"Point"}
}