{
  "type": "Feature",
  "properties": {
    "gn:admin1_code":"11",
    "gn:admin2_code":"23.0",
    "gn:asciiname":"Bhatokni",
    "gn:country_code":"IN",
    "gn:dem":3503,
    "gn:feature_class":"P",
    "gn:feature_code":"PPL",
    "gn:name":"Bhatokni",
    "gn:population":0,
    "gn:timezone":"Asia/Kolkata",
    "iso:country":"IN",
    "wof:name":"Bhatokni",
    "wof:placetype":"locality"
},
  "geometry": {"coordinates":[76.43319,33.15546],"type":"Point"}
}