{
  "type": "Feature",
  "properties": {
    "iso:country":"IN",
    "ks:ks_name":"Manawala Borida",
    "ks:ks_pop":355,
    "ks:ks_type":"VILLAGE",
    "name:eng_x_preferred":[
        "Manawala Borida"
    ],
    "wof:name":"Manawala Borida",
    "wof:placetype":"locality",
    "wof:population":355
},
  "geometry": {"coordinates":[74.068246,23.144817],"type":"Point"}
}