{
  "type": "Feature",
  "properties": {
    "iso:country":"IN",
    "ks:ks_name":"Suknakhali",
    "ks:ks_pop":39,
    "ks:ks_type":"VILLAGE",
    "name:eng_x_preferred":[
        "Suknakhali"
    ],
    "wof:name":"Suknakhali",
    "wof:placetype":"locality",
    "wof:population":39
},
  "geometry": {"coordinates":[87.185571,21.972114],"type":"Point"}
}