{
  "type": "Feature",
  "properties": {
    "iso:country":"IN",
    "ks:ks_name":"Somar Bigha",
    "ks:ks_pop":90,
    "ks:ks_type":"HABITATION",
    "ks:ks_uagg_main":0,
    "name:eng_x_preferred":[
        "Somar Bigha"
    ],
    "wof:name":"Somar Bigha",
    "wof:placetype":"neighbourhood",
    "wof:population":90
},
  "geometry": {"coordinates":[84.52104799999999,25.045805],"type":"Point"}
}