{
  "type": "Feature",
  "properties": {
    "iso:country":"IN",
    "ks:ks_alt_nam":"Goovada padavu",
    "ks:ks_name":"Goovada Padavu",
    "ks:ks_pop":764,
    "ks:ks_type":"HABITATION",
    "name:eng_x_preferred":[
        "Goovada Padavu"
    ],
    "wof:name":"Goovada Padavu",
    "wof:placetype":"locality",
    "wof:population":764
},
  "geometry": {"coordinates":[74.915359,12.73488],"type":"Point"}
}