{
  "type": "Feature",
  "properties": {
    "gn:admin1_code":"38.0",
    "gn:admin2_code":"347.0",
    "gn:asciiname":"Hosir",
    "gn:country_code":"IN",
    "gn:dem":421,
    "gn:feature_class":"P",
    "gn:feature_code":"PPL",
    "gn:name":"Hosir",
    "gn:population":0,
    "gn:timezone":"Asia/Kolkata",
    "iso:country":"IN",
    "ks:ks_name":"Hosir",
    "ks:ks_pop":786,
    "ks:ks_type":"VILLAGE",
    "name:eng_x_preferred":[
        "Hosir"
    ],
    "wof:name":"Hosir",
    "wof:placetype":"locality",
    "wof:population":786
},
  "geometry": {"coordinates":[84.668224,24.028179],"type":"Point"}
}