{
  "type": "Feature",
  "properties": {
    "gn:admin1_code":"34.0",
    "gn:admin2_code":"211.0",
    "gn:asciiname":"Pandaria",
    "gn:country_code":"IN",
    "gn:dem":45,
    "gn:feature_class":"P",
    "gn:feature_code":"PPL",
    "gn:name":"Pandaria",
    "gn:population":0,
    "gn:timezone":"Asia/Kolkata",
    "iso:country":"IN",
    "name:hin_x_preferred":[
        "\u092a\u0902\u0921\u0930\u093f\u092f\u093e"
    ],
    "wof:name":"Pandaria",
    "wof:placetype":"locality"
},
  "geometry": {"coordinates":[87.12044,25.8027],"type":"Point"}
}