{
  "type": "Feature",
  "properties": {
    "iso:country":"IN",
    "ks:ks_name":"Lilhara",
    "ks:ks_pop":128,
    "ks:ks_type":"HABITATION",
    "name:eng_x_preferred":[
        "Lilhara"
    ],
    "wof:name":"Lilhara",
    "wof:placetype":"locality",
    "wof:population":128
},
  "geometry": {"coordinates":[82.359647,24.303246],"type":"Point"}
}