{
  "type": "Feature",
  "properties": {
    "iso:country":"IN",
    "ks:ks_name":"Halemane",
    "ks:ks_pop":15,
    "ks:ks_type":"HABITATION",
    "name:eng_x_preferred":[
        "Halemane"
    ],
    "wof:name":"Halemane",
    "wof:placetype":"locality",
    "wof:population":15
},
  "geometry": {"coordinates":[74.79707000000001,14.493837],"type":"Point"}
}