{
  "type": "Feature",
  "properties": {
    "iso:country":"IN",
    "ks:ks_name":"Chhina Kulari",
    "ks:ks_pop":64,
    "ks:ks_type":"VILLAGE",
    "name:eng_x_preferred":[
        "Chhina Kulari"
    ],
    "wof:name":"Chhina Kulari",
    "wof:placetype":"locality",
    "wof:population":64
},
  "geometry": {"coordinates":[79.24564700000001,30.064618],"type":"Point"}
}