{
  "type": "Feature",
  "properties": {
    "gn:country":"IN",
    "gn:fcode":"PPL",
    "gn:population":8036,
    "iso:country":"IN",
    "name:ara_x_preferred":[
        "\u0628\u064a\u0644\u0627\u0633\u0628\u0648\u0631"
    ],
    "name:ben_bn_x_preferred":[
        "\u09ac\u09bf\u09b2\u09be\u09b8\u09aa\u09c1\u09b0"
    ],
    "name:ben_in_x_preferred":[
        "\u09ac\u09bf\u09b2\u09be\u09b8\u09aa\u09c1\u09b0"
    ],
    "name:ben_x_preferred":[
        "\u09ac\u09bf\u09b2\u09be\u09b8\u09aa\u09c1\u09b0"
    ],
    "name:bpy_x_preferred":[
        "\u09ac\u09bf\u09b2\u09be\u09b8\u09aa\u09c1\u09b0"
    ],
    "name:eng_x_preferred":[
        "Bilaspur"
    ],
    "name:guj_x_preferred":[
        "\u0aac\u0abf\u0ab2\u0abe\u0ab8\u0aaa\u0ac1\u0ab0"
    ],
    "name:hin_x_preferred":[
        "\u092c\u093f\u0932\u093e\u0938\u092a\u0941\u0930"
    ],
    "name:ind_x_preferred":[
        "Bilaspur"
    ],
    "name:ita_x_preferred":[
        "Bilaspur"
    ],
    "name:kan_x_preferred":[
        "\u0cac\u0cbf\u0cb2\u0cbe\u0cb8\u0ccd"
    ],
    "name:mal_x_preferred":[
        "\u0d2c\u0d3f\u0d32\u0d3e\u0d38\u0d4d\u0d2a\u0d42\u0d7c"
    ],
    "name:mar_x_preferred":[
        "\u092c\u093f\u0932\u093e\u0938\u092a\u0942\u0930"
    ],
    "name:msa_x_preferred":[
        "Bilaspur"
    ],
    "name:nld_x_preferred":[
        "Bilaspur"
    ],
    "name:pan_x_preferred":[
        "\u0a2c\u0a3f\u0a32\u0a3e\u0a38\u0a2a\u0a41\u0a30"
    ],
    "name:pol_x_preferred":[
        "Bilaspur"
    ],
    "name:tam_x_preferred":[
        "\u0baa\u0bbf\u0bb2\u0bbe\u0bb8\u0bcd\u0baa\u0bc2\u0bb0\u0bcd"
    ],
    "name:tel_x_preferred":[
        "\u0c2c\u0c3f\u0c32\u0c3e\u0c38\u0c4d"
    ],
    "name:und_x_variant":[
        "B\u012bl\u0101spur"
    ],
    "name:urd_x_preferred":[
        "\u0628\u0644\u0627\u0633 \u067e\u0648\u0631"
    ],
    "name:urd_x_variant":[
        "\u0628\u0644\u0627\u0633\u067e\u0648\u0631",
        "\u0628\u0644\u0627\u0633\u067e\u0648\u0631\u060c \u06af\u0648\u062a\u0645 \u0628\u062f\u06be \u0646\u06af\u0631"
    ],
    "name:zho_x_preferred":[
        "\u6bd4\u62c9\u65af\u5e03\u5c14"
    ],
    "qs:name":"Bilaspur",
    "qs:name_adm0":"India",
    "qs:name_adm1":"Uttar Pradesh",
    "qs:photos_9r":0,
    "qs:photos_sr":0,
    "qs:placetype":"Town",
    "qs:pop_sr":"5",
    "wd:wordcount":135,
    "wof:name":"Bilaspur",
    "wof:placetype":"locality",
    "wof:population":8036
},
  "geometry": {"coordinates":[77.62246,28.39088],"type":"Point"}
}