{
  "type": "Feature",
  "properties": {
    "iso:country":"IN",
    "ks:ks_name":"Samajpada",
    "ks:ks_pop":146,
    "ks:ks_type":"HABITATION",
    "name:eng_x_preferred":[
        "Samajpada"
    ],
    "wof:name":"Samajpada",
    "wof:placetype":"locality",
    "wof:population":146
},
  "geometry": {"coordinates":[73.089944,20.40425],"type":"Point"}
}