{
  "type": "Feature",
  "properties": {
    "iso:country":"IN",
    "ks:ks_name":"Bhattira",
    "ks:ks_pop":134,
    "ks:ks_type":"VILLAGE",
    "name:eng_x_preferred":[
        "Bhattira"
    ],
    "wof:name":"Bhattira",
    "wof:placetype":"locality",
    "wof:population":134
},
  "geometry": {"coordinates":[86.565045,21.052035],"type":"Point"}
}