{
  "type": "Feature",
  "properties": {
    "iso:country":"IN",
    "ks:ks_name":"Rohida Para",
    "ks:ks_pop":162,
    "ks:ks_type":"HABITATION",
    "name:eng_x_preferred":[
        "Rohida Para"
    ],
    "wof:name":"Rohida Para",
    "wof:placetype":"locality",
    "wof:population":162
},
  "geometry": {"coordinates":[91.71889299999999,23.726963],"type":"Point"}
}