{
  "type": "Feature",
  "properties": {
    "iso:country":"IN",
    "ks:ks_name":"Samserpadar",
    "ks:ks_pop":683,
    "ks:ks_type":"VILLAGE",
    "ks:ks_uagg_main":0,
    "name:eng_x_preferred":[
        "Samserpadar"
    ],
    "wof:name":"Samserpadar",
    "wof:placetype":"neighbourhood",
    "wof:population":683
},
  "geometry": {"coordinates":[82.741901,20.216933],"type":"Point"}
}