{
  "type": "Feature",
  "properties": {
    "iso:country":"IN",
    "ks:ks_name":"Oraon Toli",
    "ks:ks_pop":195,
    "ks:ks_type":"HABITATION",
    "name:eng_x_preferred":[
        "Oraon Toli"
    ],
    "wof:name":"Oraon Toli",
    "wof:placetype":"locality",
    "wof:population":195
},
  "geometry": {"coordinates":[85.09221700000001,23.497495],"type":"Point"}
}