{
  "type": "Feature",
  "properties": {
    "gn:admin1_code":"12.0",
    "gn:asciiname":"Gujardar",
    "gn:country_code":"IN",
    "gn:dem":3122,
    "gn:feature_class":"P",
    "gn:feature_code":"PPL",
    "gn:name":"Gujardar",
    "gn:population":0,
    "gn:timezone":"Asia/Kolkata",
    "iso:country":"IN",
    "wof:name":"Gujardar",
    "wof:placetype":"locality"
},
  "geometry": {"coordinates":[74.06058,34.61968],"type":"Point"}
}