{
  "type": "Feature",
  "properties": {
    "iso:country":"IN",
    "ks:ks_name":"Khadi",
    "ks:ks_pop":2,
    "ks:ks_type":"HABITATION",
    "name:eng_x_preferred":[
        "Khadi"
    ],
    "wof:name":"Khadi",
    "wof:placetype":"locality",
    "wof:population":2
},
  "geometry": {"coordinates":[79.20601000000001,23.670911],"type":"Point"}
}