{
  "type": "Feature",
  "properties": {
    "iso:country":"IN",
    "ks:ks_name":"Bistaunsi",
    "ks:ks_pop":128,
    "ks:ks_type":"VILLAGE",
    "ks:ks_uagg_main":0,
    "name:eng_x_preferred":[
        "Bistaunsi"
    ],
    "wof:name":"Bistaunsi",
    "wof:placetype":"neighbourhood",
    "wof:population":128
},
  "geometry": {"coordinates":[78.13358700000001,30.624179],"type":"Point"}
}