{
  "type": "Feature",
  "properties": {
    "iso:country":"IN",
    "ks:ks_name":"Mangarwarakhas Mahal",
    "ks:ks_pop":46,
    "ks:ks_type":"VILLAGE",
    "name:eng_x_preferred":[
        "Mangarwarakhas Mahal"
    ],
    "wof:name":"Mangarwarakhas Mahal",
    "wof:placetype":"locality",
    "wof:population":46
},
  "geometry": {"coordinates":[87.064364,25.992312],"type":"Point"}
}