{
  "type": "Feature",
  "properties": {
    "iso:country":"IN",
    "ks:ks_name":"Ranikund Rarah",
    "ks:ks_type":"VILLAGE",
    "name:eng_x_preferred":[
        "Ranikund Rarah"
    ],
    "wof:name":"Ranikund Rarah",
    "wof:placetype":"locality"
},
  "geometry": {"coordinates":[77.54033,27.323324],"type":"Point"}
}