{
  "type": "Feature",
  "properties": {
    "gn:admin1_code":"36",
    "gn:admin2_code":"176.0",
    "gn:asciiname":"Harpalpur",
    "gn:country_code":"IN",
    "gn:dem":121,
    "gn:feature_class":"P",
    "gn:feature_code":"PPL",
    "gn:name":"Harp\u0101lpur",
    "gn:population":0,
    "gn:timezone":"Asia/Kolkata",
    "iso:country":"IN",
    "name:ben_x_preferred":[
        "\u09b9\u09be\u09b0\u09aa\u09b2\u09aa\u09c1\u09b0"
    ],
    "name:bpy_x_preferred":[
        "\u09b9\u09be\u09b0\u09aa\u09b2\u09aa\u09c1\u09b0"
    ],
    "name:ceb_x_preferred":[
        "Harp\u0101lpur"
    ],
    "name:ita_x_preferred":[
        "Harpalpur"
    ],
    "name:msa_x_preferred":[
        "Harpalpur"
    ],
    "name:new_x_preferred":[
        "\u0939\u0930\u094d\u092a\u093e\u0932\u092a\u0941\u0930"
    ],
    "name:nld_x_preferred":[
        "Harpalpur"
    ],
    "name:por_x_preferred":[
        "Harpalpur"
    ],
    "name:spa_x_preferred":[
        "Harpalpur"
    ],
    "name:swe_x_preferred":[
        "Harp\u0101lpur"
    ],
    "name:vie_x_preferred":[
        "Harpalpur"
    ],
    "name:zho_x_preferred":[
        "\u54c8\u5c14\u5e15\u5c14\u666e\u5c14"
    ],
    "wof:name":"Harpalpur",
    "wof:placetype":"locality"
},
  "geometry": {"coordinates":[81.42155,26.60383],"type":"Point"}
}