{
  "type": "Feature",
  "properties": {
    "iso:country":"IN",
    "ks:ks_name":"Tajpur Mahal",
    "ks:ks_pop":204,
    "ks:ks_type":"HABITATION",
    "name:eng_x_preferred":[
        "Tajpur Mahal"
    ],
    "wof:name":"Tajpur Mahal",
    "wof:placetype":"neighbourhood",
    "wof:population":204
},
  "geometry": {"coordinates":[77.80054199999999,23.338076],"type":"Point"}
}