{
  "type": "Feature",
  "properties": {
    "iso:country":"IN",
    "ks:ks_name":"Patel Falia",
    "ks:ks_pop":402,
    "ks:ks_type":"HABITATION",
    "name:eng_x_preferred":[
        "Patel Falia"
    ],
    "wof:name":"Patel Falia",
    "wof:placetype":"locality",
    "wof:population":402
},
  "geometry": {"coordinates":[74.255306,23.102528],"type":"Point"}
}