{
  "type": "Feature",
  "properties": {
    "gn:admin1_code":"13.0",
    "gn:admin2_code":"601.0",
    "gn:asciiname":"Tholikuzhi",
    "gn:country_code":"IN",
    "gn:dem":100,
    "gn:feature_class":"P",
    "gn:feature_code":"PPL",
    "gn:name":"Tholikuzhi",
    "gn:population":0,
    "gn:timezone":"Asia/Kolkata",
    "iso:country":"IN",
    "wof:name":"Tholikuzhi",
    "wof:placetype":"locality"
},
  "geometry": {"coordinates":[76.91755000000001,8.78731],"type":"Point"}
}