{
  "type": "Feature",
  "properties": {
    "iso:country":"IN",
    "ks:ks_name":"Kondangiputtu",
    "ks:ks_pop":13,
    "ks:ks_type":"HABITATION",
    "name:eng_x_preferred":[
        "Kondangiputtu"
    ],
    "wof:name":"Kondangiputtu",
    "wof:placetype":"locality",
    "wof:population":13
},
  "geometry": {"coordinates":[82.816337,18.036627],"type":"Point"}
}