{
  "type": "Feature",
  "properties": {
    "iso:country":"IN",
    "ks:ks_name":"Palkewara",
    "ks:ks_pop":675,
    "ks:ks_type":"VILLAGE",
    "name:eng_x_preferred":[
        "Palkewara"
    ],
    "wof:name":"Palkewara",
    "wof:placetype":"locality",
    "wof:population":675
},
  "geometry": {"coordinates":[82.622478,23.582345],"type":"Point"}
}