{
  "type": "Feature",
  "properties": {
    "iso:country":"IN",
    "ks:ks_name":"Akenipalle",
    "ks:ks_pop":9026,
    "ks:ks_type":"VILLAGE",
    "name:eng_x_preferred":[
        "Akenipalle"
    ],
    "wof:name":"Akenipalle",
    "wof:placetype":"neighbourhood",
    "wof:population":9026
},
  "geometry": {"coordinates":[79.488136,19.066836],"type":"Point"}
}