{
  "type": "Feature",
  "properties": {
    "iso:country":"IN",
    "ks:ks_name":"Siram",
    "ks:ks_pop":1007,
    "ks:ks_type":"VILLAGE",
    "name:eng_x_preferred":[
        "Siram"
    ],
    "wof:name":"Siram",
    "wof:placetype":"locality",
    "wof:population":1007
},
  "geometry": {"coordinates":[84.92593100000001,23.712034],"type":"Point"}
}