{
  "type": "Feature",
  "properties": {
    "gn:admin1_code":"11",
    "gn:admin2_code":"31.0",
    "gn:asciiname":"Androla",
    "gn:country_code":"IN",
    "gn:dem":344,
    "gn:feature_class":"P",
    "gn:feature_code":"PPL",
    "gn:name":"Androla",
    "gn:population":0,
    "gn:timezone":"Asia/Kolkata",
    "iso:country":"IN",
    "wof:name":"Androla",
    "wof:placetype":"locality"
},
  "geometry": {"coordinates":[76.65300000000001,31.13253],"type":"Point"}
}