{
  "type": "Feature",
  "properties": {
    "gn:gn_country":"IN",
    "gn:gn_fcode":"PPL",
    "gn:gn_pop":0,
    "iso:country":"IN",
    "qs_pg:aaroncc":"IN",
    "qs_pg:gn_country":"IN",
    "qs_pg:gn_fcode":"PPL",
    "qs_pg:gn_pop":0,
    "qs_pg:name":"Maneswar",
    "qs_pg:name_adm0":"India",
    "qs_pg:name_adm1":"Orissa",
    "qs_pg:photos_9r":0,
    "qs_pg:photos_sr":0,
    "qs_pg:pop_sr":0,
    "qs_pg:qs_pg_placetype":"locality",
    "qs_pg:qs_pg_placetype_gp":"Town",
    "qs_pg:woe_adm0":23424848,
    "woe:adm0_id":23424848,
    "woe:name_adm0":"India",
    "woe:name_adm1":"Orissa",
    "woe:placetype":"Town",
    "wof:name":"Maneswar",
    "wof:placetype":"locality"
},
  "geometry": {"coordinates":[84.03076,21.4157],"type":"Point"}
}