{
  "type": "Feature",
  "properties": {
    "iso:country":"IN",
    "name:eng_x_preferred":[
        "Mulund West"
    ],
    "qs:gn_adm0_cc":"IN",
    "qs:gn_fcode":"PPL",
    "qs:gn_local":1275339,
    "qs:gn_namadm1":"16",
    "qs:gn_name":"Mulund West",
    "qs:local_max":3819,
    "qs:local_sum":50908,
    "qs:localhoods":70,
    "qs:name":"Mulund West",
    "qs:name_adm0":"India",
    "qs:name_adm1":"Maharashtra",
    "qs:name_adm2":"Mumbai Suburban",
    "qs:name_local":"Mumbai",
    "qs:photo_max":26,
    "qs:photo_sum":110,
    "qs:placetype":"Suburb",
    "qs:quad_count":18,
    "qs:woe_adm0":23424848,
    "qs:woe_adm1":2345750,
    "qs:woe_adm2":28743745,
    "qs:woe_lau":0,
    "qs:woe_local":2295411,
    "qs:woe_ver":"7.10.0",
    "wof:lang":[
        "eng"
    ],
    "wof:name":"Mulund West",
    "wof:placetype":"neighbourhood"
},
  "geometry": {"coordinates":[72.944475,19.174745],"type":"Point"}
}