{
  "type": "Feature",
  "properties": {
    "gn:admin1_code":"36",
    "gn:admin2_code":"158.0",
    "gn:asciiname":"Pura Nunar",
    "gn:country_code":"IN",
    "gn:dem":111,
    "gn:feature_class":"P",
    "gn:feature_code":"PPL",
    "gn:name":"Pura Nun\u0101r",
    "gn:population":0,
    "gn:timezone":"Asia/Kolkata",
    "iso:country":"IN",
    "name:und_x_variant":[
        "Pura Nun\u0101r",
        "Debi D\u0101s"
    ],
    "wof:name":"Pura Nunar",
    "wof:placetype":"locality"
},
  "geometry": {"coordinates":[81.55894000000001,26.16957],"type":"Point"}
}