{
  "type": "Feature",
  "properties": {
    "iso:country":"IN",
    "ks:ks_name":"Bandi Hana",
    "ks:ks_pop":293,
    "ks:ks_type":"VILLAGE",
    "name:eng_x_preferred":[
        "Bandi Hana"
    ],
    "wof:name":"Bandi Hana",
    "wof:placetype":"locality",
    "wof:population":293
},
  "geometry": {"coordinates":[90.139081,26.11031],"type":"Point"}
}