{
  "type": "Feature",
  "properties": {
    "iso:country":"IN",
    "ks:ks_name":"Amhari",
    "ks:ks_pop":107,
    "ks:ks_type":"VILLAGE",
    "name:eng_x_preferred":[
        "Amhari"
    ],
    "wof:name":"Amhari",
    "wof:placetype":"locality",
    "wof:population":107
},
  "geometry": {"coordinates":[82.778049,26.77777],"type":"Point"}
}