{
  "type": "Feature",
  "properties": {
    "gn:admin1_code":"19.0",
    "gn:admin2_code":"565.0",
    "gn:asciiname":"Hitnahalli",
    "gn:country_code":"IN",
    "gn:dem":541,
    "gn:feature_class":"P",
    "gn:feature_code":"PPL",
    "gn:name":"Hitnahalli",
    "gn:population":0,
    "gn:timezone":"Asia/Kolkata",
    "iso:country":"IN",
    "ks:ks_name":"Hitnahalli",
    "ks:ks_type":"VILLAGE",
    "name:eng_x_preferred":[
        "Hitnahalli"
    ],
    "wof:name":"Hitnahalli",
    "wof:placetype":"locality"
},
  "geometry": {"coordinates":[75.91648600000001,14.907069],"type":"Point"}
}