{
  "type": "Feature",
  "properties": {
    "gn:admin1_code":"16",
    "gn:admin2_code":"511.0",
    "gn:asciiname":"Bimra",
    "gn:country_code":"IN",
    "gn:dem":513,
    "gn:feature_class":"P",
    "gn:feature_code":"PPL",
    "gn:name":"Bimra",
    "gn:population":0,
    "gn:timezone":"Asia/Kolkata",
    "iso:country":"IN",
    "wof:name":"Bimra",
    "wof:placetype":"locality"
},
  "geometry": {"coordinates":[77.51108000000001,18.32747],"type":"Point"}
}