{
  "type": "Feature",
  "properties": {
    "iso:country":"IN",
    "ks:ks_name":"Kartaymari II",
    "ks:ks_pop":704,
    "ks:ks_type":"VILLAGE",
    "name:eng_x_preferred":[
        "Kartaymari II"
    ],
    "wof:name":"Kartaymari II",
    "wof:placetype":"locality",
    "wof:population":704
},
  "geometry": {"coordinates":[90.087524,26.348268],"type":"Point"}
}