{
  "type": "Feature",
  "properties": {
    "iso:country":"IN",
    "ks:ks_alt_nam":"Mangliya Sadak CT",
    "ks:ks_name":"Mangliya Sadak Ct",
    "ks:ks_pop":10393,
    "ks:ks_type":"HABITATION",
    "name:eng_x_preferred":[
        "Mangliya Sadak Ct"
    ],
    "wof:name":"Mangliya Sadak Ct",
    "wof:placetype":"locality",
    "wof:population":10393
},
  "geometry": {"coordinates":[75.783694,22.44178],"type":"Point"}
}