{
  "type": "Feature",
  "properties": {
    "gn:admin1_code":"34.0",
    "gn:admin2_code":"217.0",
    "gn:asciiname":"Dube Pachamwa",
    "gn:country_code":"IN",
    "gn:dem":77,
    "gn:feature_class":"P",
    "gn:feature_code":"PPL",
    "gn:name":"Dube Pachamw\u0101",
    "gn:population":0,
    "gn:timezone":"Asia/Kolkata",
    "iso:country":"IN",
    "ks:ks_alt_nam":"Dube Pachamw\u0101",
    "ks:ks_name":"Dube Pachamwa",
    "ks:ks_type":"VILLAGE",
    "ks:ks_uagg_main":0,
    "name:eng_x_preferred":[
        "Dube Pachamwa"
    ],
    "name:eng_x_variant":[
        "Dube Pachamw\u0101"
    ],
    "wof:name":"Dube Pachamwa",
    "wof:placetype":"neighbourhood"
},
  "geometry": {"coordinates":[84.084007,26.534117],"type":"Point"}
}