{
  "type": "Feature",
  "properties": {
    "iso:country":"IN",
    "ks:ks_name":"Karimenagunta",
    "ks:ks_pop":118,
    "ks:ks_type":"VILLAGE",
    "name:eng_x_preferred":[
        "Karimenagunta"
    ],
    "wof:name":"Karimenagunta",
    "wof:placetype":"locality",
    "wof:population":118
},
  "geometry": {"coordinates":[79.682429,13.982643],"type":"Point"}
}