{
  "type": "Feature",
  "properties": {
    "iso:country":"IN",
    "ks:ks_name":"Sahdullahpur Satan",
    "ks:ks_pop":6370,
    "ks:ks_type":"HABITATION",
    "name:eng_x_preferred":[
        "Sahdullahpur Satan"
    ],
    "wof:name":"Sahdullahpur Satan",
    "wof:placetype":"locality",
    "wof:population":6370
},
  "geometry": {"coordinates":[85.236019,25.663858],"type":"Point"}
}