{
  "type": "Feature",
  "properties": {
    "iso:country":"IN",
    "ks:ks_name":"Nathusingh Nagar",
    "ks:ks_pop":253,
    "ks:ks_type":"HABITATION",
    "name:eng_x_preferred":[
        "Nathusingh Nagar"
    ],
    "wof:name":"Nathusingh Nagar",
    "wof:placetype":"locality",
    "wof:population":253
},
  "geometry": {"coordinates":[72.17893599999999,26.338592],"type":"Point"}
}