{
  "type": "Feature",
  "properties": {
    "iso:country":"IN",
    "ks:ks_name":"Madhia Mangal",
    "ks:ks_pop":282,
    "ks:ks_type":"HABITATION",
    "ks:ks_uagg_main":0,
    "name:eng_x_preferred":[
        "Madhia Mangal"
    ],
    "wof:name":"Madhia Mangal",
    "wof:placetype":"neighbourhood",
    "wof:population":282
},
  "geometry": {"coordinates":[80.221659,27.011261],"type":"Point"}
}