{
  "type": "Feature",
  "properties": {
    "iso:country":"IN",
    "ks:ks_name":"Kholatilla",
    "ks:ks_pop":342,
    "ks:ks_type":"HABITATION",
    "name:eng_x_preferred":[
        "Kholatilla"
    ],
    "wof:name":"Kholatilla",
    "wof:placetype":"locality",
    "wof:population":342
},
  "geometry": {"coordinates":[92.25966200000001,24.485701],"type":"Point"}
}