{
  "type": "Feature",
  "properties": {
    "iso:country":"IN",
    "ks:ks_alt_nam":"LONAR WASTI",
    "ks:ks_name":"Lonar Wasti",
    "ks:ks_pop":320,
    "ks:ks_type":"HABITATION",
    "name:eng_x_preferred":[
        "Lonar Wasti"
    ],
    "wof:name":"Lonar Wasti",
    "wof:placetype":"locality",
    "wof:population":320
},
  "geometry": {"coordinates":[75.137045,17.226077],"type":"Point"}
}