{
  "type": "Feature",
  "properties": {
    "iso:country":"IN",
    "ks:ks_name":"Sonari Gaon",
    "ks:ks_pop":360,
    "ks:ks_type":"HABITATION",
    "name:eng_x_preferred":[
        "Sonari Gaon"
    ],
    "wof:name":"Sonari Gaon",
    "wof:placetype":"locality",
    "wof:population":360
},
  "geometry": {"coordinates":[94.590743,26.918402],"type":"Point"}
}