{
  "type": "Feature",
  "properties": {
    "gn:admin1_code":"36.0",
    "gn:admin2_code":"173.0",
    "gn:asciiname":"Dewaini",
    "gn:country_code":"IN",
    "gn:dem":102,
    "gn:feature_class":"P",
    "gn:feature_code":"PPL",
    "gn:name":"Dewaini",
    "gn:population":0,
    "gn:timezone":"Asia/Kolkata",
    "iso:country":"IN",
    "ks:ks_name":"Dewani",
    "ks:ks_pop":1745,
    "ks:ks_type":"HABITATION",
    "name:eng_x_preferred":[
        "Dewani"
    ],
    "name:eng_x_variant":[
        "Dewaini"
    ],
    "wof:name":"Dewani",
    "wof:placetype":"locality",
    "wof:population":1745
},
  "geometry": {"coordinates":[81.895563,25.722783],"type":"Point"}
}