{
  "type": "Feature",
  "properties": {
    "gn:admin1_code":"36",
    "gn:admin2_code":"186.0",
    "gn:asciiname":"Arar",
    "gn:country_code":"IN",
    "gn:dem":83,
    "gn:feature_class":"P",
    "gn:feature_code":"PPL",
    "gn:name":"Ar\u0101r",
    "gn:population":0,
    "gn:timezone":"Asia/Kolkata",
    "iso:country":"IN",
    "name:ben_x_preferred":[
        "\u0986\u09b0\u09be\u09b0"
    ],
    "name:ceb_x_preferred":[
        "Arar"
    ],
    "name:deu_x_preferred":[
        "Arar"
    ],
    "name:ell_x_preferred":[
        "\u0391\u03c1\u03ac\u03c1"
    ],
    "name:est_x_preferred":[
        "Arar"
    ],
    "name:hin_x_preferred":[
        "\u0905\u0930\u093e\u0930"
    ],
    "name:hun_x_preferred":[
        "Arar"
    ],
    "name:ind_x_preferred":[
        "Arar"
    ],
    "name:spa_x_preferred":[
        "Arar"
    ],
    "name:swe_x_preferred":[
        "Arar"
    ],
    "wof:name":"Arar",
    "wof:placetype":"locality"
},
  "geometry": {"coordinates":[83.01264,26.87122],"type":"Point"}
}