{
  "type": "Feature",
  "properties": {
    "iso:country":"IN",
    "ks:ks_name":"Mundipurwa",
    "ks:ks_pop":108,
    "ks:ks_type":"HABITATION",
    "name:eng_x_preferred":[
        "Mundipurwa"
    ],
    "wof:name":"Mundipurwa",
    "wof:placetype":"locality",
    "wof:population":108
},
  "geometry": {"coordinates":[80.819791,27.599477],"type":"Point"}
}