{
  "type": "Feature",
  "properties": {
    "gn:admin1_code":"36",
    "gn:admin2_code":"143.0",
    "gn:asciiname":"Azamabad Machhua",
    "gn:country_code":"IN",
    "gn:dem":191,
    "gn:feature_class":"P",
    "gn:feature_code":"PPL",
    "gn:name":"\u0100zam\u0101b\u0101d Machhua",
    "gn:population":0,
    "gn:timezone":"Asia/Kolkata",
    "iso:country":"IN",
    "wof:name":"Azamabad Machhua",
    "wof:placetype":"locality"
},
  "geometry": {"coordinates":[78.19271999999999,27.92628],"type":"Point"}
}