{
  "type": "Feature",
  "properties": {
    "iso:country":"IN",
    "ks:ks_name":"Gumandput",
    "ks:ks_pop":42,
    "ks:ks_type":"HABITATION",
    "name:eng_x_preferred":[
        "Gumandput"
    ],
    "wof:name":"Gumandput",
    "wof:placetype":"locality",
    "wof:population":42
},
  "geometry": {"coordinates":[82.421441,18.499805],"type":"Point"}
}