{
  "type": "Feature",
  "properties": {
    "iso:country":"IN",
    "ks:ks_name":"Dakkhin Kahikuchi",
    "ks:ks_pop":568,
    "ks:ks_type":"HABITATION",
    "name:eng_x_preferred":[
        "Dakkhin Kahikuchi"
    ],
    "wof:name":"Dakkhin Kahikuchi",
    "wof:placetype":"locality",
    "wof:population":568
},
  "geometry": {"coordinates":[91.11281700000001,26.338414],"type":"Point"}
}