{
  "type": "Feature",
  "properties": {
    "gn:admin1_code":"35",
    "gn:admin2_code":"445.0",
    "gn:asciiname":"Lodabar",
    "gn:country_code":"IN",
    "gn:dem":336,
    "gn:feature_class":"P",
    "gn:feature_code":"PPL",
    "gn:name":"Lod\u0101b\u0101r",
    "gn:population":0,
    "gn:timezone":"Asia/Kolkata",
    "iso:country":"IN",
    "name:und_x_variant":[
        "Lod\u0101b\u0101r",
        "Hab\u012bbnagar"
    ],
    "wof:name":"Lodabar",
    "wof:placetype":"locality"
},
  "geometry": {"coordinates":[77.18925,22.8097],"type":"Point"}
}