{
  "type": "Feature",
  "properties": {
    "gn:admin1_code":"40",
    "gn:admin2_code":"533.0",
    "gn:asciiname":"Lakshmi Farm",
    "gn:country_code":"IN",
    "gn:dem":403,
    "gn:feature_class":"P",
    "gn:feature_code":"PPL",
    "gn:name":"Lakshmi Farm",
    "gn:population":0,
    "gn:timezone":"Asia/Kolkata",
    "iso:country":"IN",
    "wof:name":"Lakshmi Farm",
    "wof:placetype":"neighbourhood"
},
  "geometry": {"coordinates":[77.87602,18.54318],"type":"Point"}
}