{
  "type": "Feature",
  "properties": {
    "iso:country":"IN",
    "ks:ks_name":"Girdharpur",
    "ks:ks_pop":1223,
    "ks:ks_type":"VILLAGE",
    "ks:ks_uagg_main":0,
    "name:eng_x_preferred":[
        "Girdharpur"
    ],
    "wof:name":"Girdharpur",
    "wof:placetype":"neighbourhood",
    "wof:population":1223
},
  "geometry": {"coordinates":[77.635869,27.492906],"type":"Point"}
}