{
  "type": "Feature",
  "properties": {
    "gn:admin1_code":"24.0",
    "gn:admin2_code":"129.0",
    "gn:asciiname":"Biriyakheri Khurd",
    "gn:country_code":"IN",
    "gn:dem":337,
    "gn:feature_class":"P",
    "gn:feature_code":"PPL",
    "gn:name":"B\u012briy\u0101kheri Khurd",
    "gn:population":0,
    "gn:timezone":"Asia/Kolkata",
    "iso:country":"IN",
    "wof:name":"Biriyakheri Khurd",
    "wof:placetype":"locality"
},
  "geometry": {"coordinates":[76.02639000000001,24.50574],"type":"Point"}
}