{
  "type": "Feature",
  "properties": {
    "gn:admin1_code":"24.0",
    "gn:admin2_code":"118.0",
    "gn:asciiname":"Dharunda",
    "gn:country_code":"IN",
    "gn:dem":290,
    "gn:feature_class":"P",
    "gn:feature_code":"PPL",
    "gn:name":"Dh\u0101runda",
    "gn:population":0,
    "gn:timezone":"Asia/Kolkata",
    "iso:country":"IN",
    "wof:name":"Dharunda",
    "wof:placetype":"locality"
},
  "geometry": {"coordinates":[73.34256999999999,25.33218],"type":"Point"}
}