{
  "type": "Feature",
  "properties": {
    "iso:country":"IN",
    "ks:ks_name":"Chinchmal",
    "ks:ks_pop":194,
    "ks:ks_type":"HABITATION",
    "name:eng_x_preferred":[
        "Chinchmal"
    ],
    "wof:name":"Chinchmal",
    "wof:placetype":"locality",
    "wof:population":194
},
  "geometry": {"coordinates":[73.520594,20.636469],"type":"Point"}
}