{
  "type": "Feature",
  "properties": {
    "iso:country":"IN",
    "ks:ks_name":"Kalai Dev",
    "ks:ks_pop":79,
    "ks:ks_type":"HABITATION",
    "name:eng_x_preferred":[
        "Kalai Dev"
    ],
    "wof:name":"Kalai Dev",
    "wof:placetype":"locality",
    "wof:population":79
},
  "geometry": {"coordinates":[81.788701,27.583587],"type":"Point"}
}