{
  "type": "Feature",
  "properties": {
    "iso:country":"IN",
    "ks:ks_name":"Kasba Gopal",
    "ks:ks_pop":1,
    "ks:ks_type":"VILLAGE",
    "ks:ks_uagg_main":0,
    "name:eng_x_preferred":[
        "Kasba Gopal"
    ],
    "wof:name":"Kasba Gopal",
    "wof:placetype":"neighbourhood",
    "wof:population":1
},
  "geometry": {"coordinates":[85.09685899999999,26.35854],"type":"Point"}
}