{
  "type": "Feature",
  "properties": {
    "gn:admin1_code":"11.0",
    "gn:admin2_code":"26.0",
    "gn:asciiname":"Sagapha",
    "gn:country_code":"IN",
    "gn:dem":2349,
    "gn:feature_class":"P",
    "gn:feature_code":"PPL",
    "gn:name":"Sagapha",
    "gn:population":0,
    "gn:timezone":"Asia/Kolkata",
    "iso:country":"IN",
    "wof:name":"Sagapha",
    "wof:placetype":"locality"
},
  "geometry": {"coordinates":[77.55759999999999,31.55001],"type":"Point"}
}