{
  "type": "Feature",
  "properties": {
    "iso:country":"IN",
    "ks:ks_name":"Bhailiya",
    "ks:ks_pop":596,
    "ks:ks_type":"HABITATION",
    "name:eng_x_preferred":[
        "Bhailiya"
    ],
    "wof:name":"Bhailiya",
    "wof:placetype":"locality",
    "wof:population":596
},
  "geometry": {"coordinates":[82.26365800000001,27.66852],"type":"Point"}
}