{
  "type": "Feature",
  "properties": {
    "gn:admin1_code":"16",
    "gn:admin2_code":"503.0",
    "gn:asciiname":"Paibir",
    "gn:country_code":"IN",
    "gn:dem":421,
    "gn:feature_class":"P",
    "gn:feature_code":"PPL",
    "gn:name":"P\u0101ib\u012br",
    "gn:population":0,
    "gn:timezone":"Asia/Kolkata",
    "iso:country":"IN",
    "wof:name":"Paibir",
    "wof:placetype":"neighbourhood"
},
  "geometry": {"coordinates":[77.3691,21.2682],"type":"Point"}
}