{
  "type": "Feature",
  "properties": {
    "iso:country":"IN",
    "ks:ks_name":"Kanthavali",
    "ks:ks_pop":243,
    "ks:ks_type":"VILLAGE",
    "ks:ks_uagg_main":0,
    "name:eng_x_preferred":[
        "Kanthavali"
    ],
    "wof:name":"Kanthavali",
    "wof:placetype":"neighbourhood",
    "wof:population":243
},
  "geometry": {"coordinates":[73.04889799999999,18.903453],"type":"Point"}
}