{
  "type": "Feature",
  "properties": {
    "gn:admin1_code":"39.0",
    "gn:admin2_code":"66.0",
    "gn:asciiname":"Bachipur",
    "gn:country_code":"IN",
    "gn:dem":332,
    "gn:feature_class":"P",
    "gn:feature_code":"PPL",
    "gn:name":"Bach\u012bpur",
    "gn:population":0,
    "gn:timezone":"Asia/Kolkata",
    "iso:country":"IN",
    "ks:ks_alt_nam":"Bach\u012bpur",
    "ks:ks_name":"Bachipur",
    "ks:ks_type":"VILLAGE",
    "ks:ks_uagg_main":0,
    "name:eng_x_preferred":[
        "Bachipur"
    ],
    "name:eng_x_variant":[
        "Bach\u012bpur"
    ],
    "wof:name":"Bachipur",
    "wof:placetype":"neighbourhood"
},
  "geometry": {"coordinates":[79.51909999999999,29.135547],"type":"Point"}
}