{
  "type": "Feature",
  "properties": {
    "iso:country":"IN",
    "ks:ks_name":"Paprida",
    "ks:ks_pop":142,
    "ks:ks_type":"HABITATION",
    "name:eng_x_preferred":[
        "Paprida"
    ],
    "wof:name":"Paprida",
    "wof:placetype":"locality",
    "wof:population":142
},
  "geometry": {"coordinates":[85.824314,23.138104],"type":"Point"}
}