{
  "type": "Feature",
  "properties": {
    "gn:admin1_code":"36.0",
    "gn:admin2_code":"152.0",
    "gn:asciiname":"Nagaria Naubaramad",
    "gn:country_code":"IN",
    "gn:dem":157,
    "gn:feature_class":"P",
    "gn:feature_code":"PPL",
    "gn:name":"Nagaria Naubar\u0101mad",
    "gn:population":0,
    "gn:timezone":"Asia/Kolkata",
    "iso:country":"IN",
    "wof:name":"Nagaria Naubaramad",
    "wof:placetype":"locality"
},
  "geometry": {"coordinates":[79.51584,28.04307],"type":"Point"}
}