{
  "type": "Feature",
  "properties": {
    "iso:country":"IN",
    "ks:ks_name":"3 NZP",
    "ks:ks_pop":242,
    "ks:ks_type":"VILLAGE",
    "name:eng_x_preferred":[
        "3 NZP"
    ],
    "wof:name":"3 NZP",
    "wof:placetype":"locality",
    "wof:population":242
},
  "geometry": {"coordinates":[73.46740800000001,29.372201],"type":"Point"}
}