{
  "type": "Feature",
  "properties": {
    "gn:admin1_code":"2",
    "gn:admin2_code":"544.0",
    "gn:asciiname":"Chintalvalasa",
    "gn:country_code":"IN",
    "gn:dem":937,
    "gn:feature_class":"P",
    "gn:feature_code":"PPL",
    "gn:name":"Chintalvalasa",
    "gn:population":0,
    "gn:timezone":"Asia/Kolkata",
    "iso:country":"IN",
    "wof:name":"Chintalvalasa",
    "wof:placetype":"locality"
},
  "geometry": {"coordinates":[82.84023000000001,18.3073],"type":"Point"}
}