{
  "type": "Feature",
  "properties": {
    "iso:country":"IN",
    "ks:ks_alt_nam":"MARHAL CHHOTI",
    "ks:ks_name":"Marhal Chhoti",
    "ks:ks_pop":615,
    "ks:ks_type":"HABITATION",
    "ks:ks_uagg_main":0,
    "name:eng_x_preferred":[
        "Marhal Chhoti"
    ],
    "wof:name":"Marhal Chhoti",
    "wof:placetype":"neighbourhood",
    "wof:population":615
},
  "geometry": {"coordinates":[85.722976,24.987353],"type":"Point"}
}