{
  "type": "Feature",
  "properties": {
    "iso:country":"IN",
    "ks:ks_alt_nam":"Chakma para",
    "ks:ks_name":"Chakma Para",
    "ks:ks_pop":65,
    "ks:ks_type":"HABITATION",
    "name:eng_x_preferred":[
        "Chakma Para"
    ],
    "wof:name":"Chakma Para",
    "wof:placetype":"locality",
    "wof:population":65
},
  "geometry": {"coordinates":[91.52739800000001,23.360119],"type":"Point"}
}