{
  "type": "Feature",
  "properties": {
    "gn:admin1_code":"13.0",
    "gn:admin2_code":"591.0",
    "gn:asciiname":"Cheruvannur",
    "gn:country_code":"IN",
    "gn:dem":45,
    "gn:feature_class":"P",
    "gn:feature_code":"PPL",
    "gn:name":"Cheruvann\u016br",
    "gn:population":0,
    "gn:timezone":"Asia/Kolkata",
    "iso:country":"IN",
    "wof:name":"Cheruvannur",
    "wof:placetype":"locality"
},
  "geometry": {"coordinates":[75.70107,11.56635],"type":"Point"}
}