{
  "type": "Feature",
  "properties": {
    "iso:country":"IN",
    "ks:ks_name":"Pataram",
    "ks:ks_pop":252,
    "ks:ks_type":"VILLAGE",
    "ks:ks_uagg_main":0,
    "name:eng_x_preferred":[
        "Pataram"
    ],
    "wof:name":"Pataram",
    "wof:placetype":"neighbourhood",
    "wof:population":252
},
  "geometry": {"coordinates":[88.21183000000001,26.716927],"type":"Point"}
}