{
  "type": "Feature",
  "properties": {
    "gn:admin1_code":"19.0",
    "gn:admin2_code":"582.0",
    "gn:asciiname":"Nandyappagaripalli",
    "gn:country_code":"IN",
    "gn:dem":699,
    "gn:feature_class":"P",
    "gn:feature_code":"PPL",
    "gn:name":"Nandyappag\u0101ripalli",
    "gn:population":0,
    "gn:timezone":"Asia/Kolkata",
    "iso:country":"IN",
    "wof:name":"Nandyappagaripalli",
    "wof:placetype":"locality"
},
  "geometry": {"coordinates":[77.97764000000002,13.81311],"type":"Point"}
}