{
  "type": "Feature",
  "properties": {
    "iso:country":"IN",
    "ks:ks_name":"Khakhlechavas",
    "ks:ks_pop":358,
    "ks:ks_type":"HABITATION",
    "name:eng_x_preferred":[
        "Khakhlechavas"
    ],
    "wof:name":"Khakhlechavas",
    "wof:placetype":"locality",
    "wof:population":358
},
  "geometry": {"coordinates":[71.88870300000001,24.059835],"type":"Point"}
}