{
  "type": "Feature",
  "properties": {
    "iso:country":"IN",
    "ks:ks_alt_nam":"napitpara",
    "ks:ks_name":"Napitpara",
    "ks:ks_pop":2150,
    "ks:ks_type":"HABITATION",
    "ks:ks_uagg_main":0,
    "name:eng_x_preferred":[
        "Napitpara"
    ],
    "wof:name":"Napitpara",
    "wof:placetype":"neighbourhood",
    "wof:population":2150
},
  "geometry": {"coordinates":[88.013572,24.80132],"type":"Point"}
}