{
  "type": "Feature",
  "properties": {
    "iso:country":"IN",
    "ks:ks_alt_nam":"Adar par",
    "ks:ks_name":"Adar Par",
    "ks:ks_pop":1307,
    "ks:ks_type":"HABITATION",
    "name:eng_x_preferred":[
        "Adar Par"
    ],
    "wof:name":"Adar Par",
    "wof:placetype":"locality",
    "wof:population":1307
},
  "geometry": {"coordinates":[83.064779,25.46004],"type":"Point"}
}