{
  "type": "Feature",
  "properties": {
    "gn:admin1_code":"36",
    "gn:admin2_code":"134.0",
    "gn:asciiname":"Abufazalpur Tamela",
    "gn:country_code":"IN",
    "gn:dem":261,
    "gn:feature_class":"P",
    "gn:feature_code":"PPL",
    "gn:name":"Abufazalpur Tamela",
    "gn:population":0,
    "gn:timezone":"Asia/Kolkata",
    "iso:country":"IN",
    "wof:name":"Abufazalpur Tamela",
    "wof:placetype":"locality"
},
  "geometry": {"coordinates":[78.34214,29.54922],"type":"Point"}
}