{
  "type": "Feature",
  "properties": {
    "iso:country":"IN",
    "ks:ks_name":"Bhimkol",
    "ks:ks_pop":28,
    "ks:ks_type":"HABITATION",
    "name:eng_x_preferred":[
        "Bhimkol"
    ],
    "wof:name":"Bhimkol",
    "wof:placetype":"locality",
    "wof:population":28
},
  "geometry": {"coordinates":[74.16987899999999,14.901782],"type":"Point"}
}