{
  "type": "Feature",
  "properties": {
    "iso:country":"IN",
    "ks:ks_name":"Tola Moglatanr",
    "ks:ks_pop":0,
    "ks:ks_type":"VILLAGE",
    "name:eng_x_preferred":[
        "Tola Moglatanr"
    ],
    "wof:name":"Tola Moglatanr",
    "wof:placetype":"locality",
    "wof:population":0
},
  "geometry": {"coordinates":[86.352954,24.501977],"type":"Point"}
}