{
  "type": "Feature",
  "properties": {
    "gn:admin1_code":"34.0",
    "gn:admin2_code":"218.0",
    "gn:asciiname":"Bindwal",
    "gn:country_code":"IN",
    "gn:dem":66,
    "gn:feature_class":"P",
    "gn:feature_code":"PPL",
    "gn:name":"Bindwal",
    "gn:population":0,
    "gn:timezone":"Asia/Kolkata",
    "iso:country":"IN",
    "ks:ks_name":"Bindwal",
    "ks:ks_type":"VILLAGE",
    "ks:ks_uagg_main":0,
    "name:eng_x_preferred":[
        "Bindwal"
    ],
    "wof:name":"Bindwal",
    "wof:placetype":"neighbourhood"
},
  "geometry": {"coordinates":[84.58351999999999,26.242755],"type":"Point"}
}