{
  "type": "Feature",
  "properties": {
    "iso:country":"IN",
    "ks:ks_name":"Bahuari Mallah Tola",
    "ks:ks_pop":1510,
    "ks:ks_type":"HABITATION",
    "name:eng_x_preferred":[
        "Bahuari Mallah Tola"
    ],
    "wof:name":"Bahuari Mallah Tola",
    "wof:placetype":"locality",
    "wof:population":1510
},
  "geometry": {"coordinates":[84.899351,26.780049],"type":"Point"}
}