{
  "type": "Feature",
  "properties": {
    "gn:admin1_code":"12.0",
    "gn:admin2_code":"17.0",
    "gn:asciiname":"Anchan",
    "gn:country_code":"IN",
    "gn:dem":2114,
    "gn:feature_class":"P",
    "gn:feature_code":"PPL",
    "gn:name":"Anch\u0101n",
    "gn:population":0,
    "gn:timezone":"Asia/Kolkata",
    "iso:country":"IN",
    "name:tha_x_preferred":[
        "\u0e2d\u0e31\u0e0d\u0e0a\u0e25\u0e35 \u0e27\u0e34\u0e27\u0e31\u0e18\u0e19\u0e0a\u0e31\u0e22"
    ],
    "wof:name":"Anchan",
    "wof:placetype":"locality"
},
  "geometry": {"coordinates":[75.08894000000002,33.29832],"type":"Point"}
}