{
  "type": "Feature",
  "properties": {
    "iso:country":"IN",
    "ks:ks_name":"Long Teron",
    "ks:ks_pop":183,
    "ks:ks_type":"HABITATION",
    "ks:ks_uagg_main":0,
    "name:eng_x_preferred":[
        "Long Teron"
    ],
    "wof:name":"Long Teron",
    "wof:placetype":"neighbourhood",
    "wof:population":183
},
  "geometry": {"coordinates":[93.81258699999999,26.168788],"type":"Point"}
}