{
  "type": "Feature",
  "properties": {
    "gn:admin1_code":"35.0",
    "gn:admin2_code":"439.0",
    "gn:asciiname":"Bhil Baroli",
    "gn:country_code":"IN",
    "gn:dem":509,
    "gn:feature_class":"P",
    "gn:feature_code":"PPL",
    "gn:name":"Bh\u012bl Baroli",
    "gn:population":0,
    "gn:timezone":"Asia/Kolkata",
    "iso:country":"IN",
    "wof:name":"Bhil Baroli",
    "wof:placetype":"locality"
},
  "geometry": {"coordinates":[75.59272,22.96904],"type":"Point"}
}