{
  "type": "Feature",
  "properties": {
    "iso:country":"IN",
    "ks:ks_alt_nam":"NANHKAJOT",
    "ks:ks_name":"Nanhkajot",
    "ks:ks_pop":102,
    "ks:ks_type":"HABITATION",
    "name:eng_x_preferred":[
        "Nanhkajot"
    ],
    "wof:name":"Nanhkajot",
    "wof:placetype":"locality",
    "wof:population":102
},
  "geometry": {"coordinates":[84.72725699999999,24.468168],"type":"Point"}
}