{
  "type": "Feature",
  "properties": {
    "gn:admin1_code":"39.0",
    "gn:admin2_code":"64.0",
    "gn:asciiname":"Kohuna",
    "gn:country_code":"IN",
    "gn:dem":1895,
    "gn:feature_class":"P",
    "gn:feature_code":"PPL",
    "gn:name":"Kohuna",
    "gn:population":0,
    "gn:timezone":"Asia/Kolkata",
    "iso:country":"IN",
    "wof:name":"Kohuna",
    "wof:placetype":"neighbourhood"
},
  "geometry": {"coordinates":[79.66265,29.64573],"type":"Point"}
}