{
  "type": "Feature",
  "properties": {
    "gn:admin1_code":"3.0",
    "gn:admin2_code":"317.0",
    "gn:asciiname":"Khudra Purahuria",
    "gn:country_code":"IN",
    "gn:dem":19,
    "gn:feature_class":"P",
    "gn:feature_code":"PPL",
    "gn:name":"Khudra Purahuria",
    "gn:population":0,
    "gn:timezone":"Asia/Kolkata",
    "iso:country":"IN",
    "wof:name":"Khudra Purahuria",
    "wof:placetype":"locality"
},
  "geometry": {"coordinates":[92.28524,24.85046],"type":"Point"}
}