{
  "type": "Feature",
  "properties": {
    "iso:country":"IN",
    "ks:ks_name":"Chhota Khejuria",
    "ks:ks_pop":2356,
    "ks:ks_type":"VILLAGE",
    "ks:ks_uagg_main":0,
    "name:eng_x_preferred":[
        "Chhota Khejuria"
    ],
    "wof:name":"Chhota Khejuria",
    "wof:placetype":"locality",
    "wof:population":2356
},
  "geometry": {"coordinates":[88.378226,22.946844],"type":"Point"}
}