{
  "type": "Feature",
  "properties": {
    "gn:admin1_code":"36.0",
    "gn:admin2_code":"151.0",
    "gn:asciiname":"Richholia",
    "gn:country_code":"IN",
    "gn:dem":170,
    "gn:feature_class":"P",
    "gn:feature_code":"PPL",
    "gn:name":"Richholia",
    "gn:population":0,
    "gn:timezone":"Asia/Kolkata",
    "iso:country":"IN",
    "ks:ks_name":"Richhaulia",
    "ks:ks_pop":576,
    "ks:ks_type":"VILLAGE",
    "ks:ks_uagg_main":0,
    "name:eng_x_preferred":[
        "Richhaulia"
    ],
    "wof:name":"Richhaulia",
    "wof:placetype":"neighbourhood",
    "wof:population":576
},
  "geometry": {"coordinates":[79.721378,28.295078],"type":"Point"}
}