{
  "type": "Feature",
  "properties": {
    "iso:country":"IN",
    "ks:ks_name":"Baijnathpur",
    "ks:ks_pop":1335,
    "ks:ks_type":"VILLAGE",
    "ks:ks_uagg_main":0,
    "name:eng_x_preferred":[
        "Baijnathpur"
    ],
    "wof:name":"Baijnathpur",
    "wof:placetype":"neighbourhood",
    "wof:population":1335
},
  "geometry": {"coordinates":[85.029825,26.711329],"type":"Point"}
}