{
  "type": "Feature",
  "properties": {
    "gn:admin1_code":"28.0",
    "gn:admin2_code":"343",
    "gn:asciiname":"Fatehpur",
    "gn:country_code":"IN",
    "gn:dem":12,
    "gn:feature_class":"P",
    "gn:feature_code":"PPL",
    "gn:name":"Fatehpur",
    "gn:population":0,
    "gn:timezone":"Asia/Kolkata",
    "iso:country":"IN",
    "wof:name":"Fatehpur",
    "wof:placetype":"locality"
},
  "geometry": {"coordinates":[88.23626999999998,22.28601],"type":"Point"}
}