{
  "type": "Feature",
  "properties": {
    "iso:country":"IN",
    "ks:ks_name":"Puttenahalli",
    "ks:ks_pop":20,
    "ks:ks_type":"HABITATION",
    "name:eng_x_preferred":[
        "Puttenahalli"
    ],
    "wof:name":"Puttenahalli",
    "wof:placetype":"locality",
    "wof:population":20
},
  "geometry": {"coordinates":[75.95241,13.10541],"type":"Point"}
}