{
  "type": "Feature",
  "properties": {
    "iso:country":"IN",
    "ks:ks_name":"Gorkhanpada",
    "ks:ks_pop":84,
    "ks:ks_type":"HABITATION",
    "name:eng_x_preferred":[
        "Gorkhanpada"
    ],
    "wof:name":"Gorkhanpada",
    "wof:placetype":"locality",
    "wof:population":84
},
  "geometry": {"coordinates":[72.920164,19.977302],"type":"Point"}
}