{
  "type": "Feature",
  "properties": {
    "iso:country":"IN",
    "ks:ks_name":"Harisinga",
    "ks:ks_pop":341,
    "ks:ks_type":"HABITATION",
    "name:eng_x_preferred":[
        "Harisinga"
    ],
    "wof:name":"Harisinga",
    "wof:placetype":"locality",
    "wof:population":341
},
  "geometry": {"coordinates":[91.21043400000001,26.704637],"type":"Point"}
}