{
  "type": "Feature",
  "properties": {
    "iso:country":"IN",
    "ks:ks_name":"Bijaynagar",
    "ks:ks_pop":325,
    "ks:ks_type":"HABITATION",
    "name:eng_x_preferred":[
        "Bijaynagar"
    ],
    "wof:name":"Bijaynagar",
    "wof:placetype":"locality",
    "wof:population":325
},
  "geometry": {"coordinates":[90.246213,26.604265],"type":"Point"}
}