{
  "type": "Feature",
  "properties": {
    "iso:country":"IN",
    "ks:ks_alt_nam":"Arunthathiyar vattam",
    "ks:ks_name":"Arunthathiyar Vattam",
    "ks:ks_pop":400,
    "ks:ks_type":"HABITATION",
    "name:eng_x_preferred":[
        "Arunthathiyar Vattam"
    ],
    "wof:name":"Arunthathiyar Vattam",
    "wof:placetype":"locality",
    "wof:population":400
},
  "geometry": {"coordinates":[78.69929,12.534928],"type":"Point"}
}