{
  "type": "Feature",
  "properties": {
    "gn:admin1_code":"35",
    "gn:admin2_code":"456.0",
    "gn:asciiname":"Baruband",
    "gn:country_code":"IN",
    "gn:dem":527,
    "gn:feature_class":"P",
    "gn:feature_code":"PPL",
    "gn:name":"B\u0101r\u016bband",
    "gn:population":0,
    "gn:timezone":"Asia/Kolkata",
    "iso:country":"IN",
    "wof:name":"Baruband",
    "wof:placetype":"locality"
},
  "geometry": {"coordinates":[79.71434000000001,22.48743],"type":"Point"}
}