{
  "type": "Feature",
  "properties": {
    "iso:country":"IN",
    "ks:ks_name":"Warchiwadi",
    "ks:ks_pop":288,
    "ks:ks_type":"HABITATION",
    "name:eng_x_preferred":[
        "Warchiwadi"
    ],
    "wof:name":"Warchiwadi",
    "wof:placetype":"locality",
    "wof:population":288
},
  "geometry": {"coordinates":[73.609489,16.94266],"type":"Point"}
}