{
  "type": "Feature",
  "properties": {
    "gn:admin1_code":"36",
    "gn:admin2_code":"196.0",
    "gn:asciiname":"Bhusaula",
    "gn:country_code":"IN",
    "gn:dem":78,
    "gn:feature_class":"P",
    "gn:feature_code":"PPL",
    "gn:name":"Bhusaula",
    "gn:population":0,
    "gn:timezone":"Asia/Kolkata",
    "iso:country":"IN",
    "ks:ks_name":"Bhusaula",
    "ks:ks_pop":907,
    "ks:ks_type":"VILLAGE",
    "ks:ks_uagg_main":0,
    "name:eng_x_preferred":[
        "Bhusaula"
    ],
    "wof:name":"Bhusaula",
    "wof:placetype":"neighbourhood",
    "wof:population":907
},
  "geometry": {"coordinates":[83.22332299999999,25.518031],"type":"Point"}
}