{
  "type": "Feature",
  "properties": {
    "iso:country":"IN",
    "ks:ks_name":"Mallemapuram Maddimadugu",
    "ks:ks_pop":174,
    "ks:ks_type":"HABITATION",
    "ks:ks_uagg_main":0,
    "name:eng_x_preferred":[
        "Mallemapuram Maddimadugu"
    ],
    "wof:name":"Mallemapuram Maddimadugu",
    "wof:placetype":"neighbourhood",
    "wof:population":174
},
  "geometry": {"coordinates":[78.78017800000001,14.355718],"type":"Point"}
}