{
  "type": "Feature",
  "properties": {
    "gn:admin1_code":"2",
    "gn:admin2_code":"544.0",
    "gn:asciiname":"Gandhavaram",
    "gn:country_code":"IN",
    "gn:dem":53,
    "gn:feature_class":"P",
    "gn:feature_code":"PPL",
    "gn:name":"Gandhavaram",
    "gn:population":0,
    "gn:timezone":"Asia/Kolkata",
    "iso:country":"IN",
    "wof:name":"Gandhavaram",
    "wof:placetype":"locality"
},
  "geometry": {"coordinates":[82.98772,17.77238999999999],"type":"Point"}
}