{
  "type": "Feature",
  "properties": {
    "iso:country":"IN",
    "ks:ks_name":"Dhaniyadih",
    "ks:ks_pop":396,
    "ks:ks_type":"VILLAGE",
    "name:eng_x_preferred":[
        "Dhaniyadih"
    ],
    "wof:name":"Dhaniyadih",
    "wof:placetype":"locality",
    "wof:population":396
},
  "geometry": {"coordinates":[86.69166300000001,24.164666],"type":"Point"}
}