{
  "type": "Feature",
  "properties": {
    "gn:admin1_code":"34.0",
    "gn:admin2_code":"220.0",
    "gn:asciiname":"Harauli Fatehpur",
    "gn:country_code":"IN",
    "gn:dem":57,
    "gn:feature_class":"P",
    "gn:feature_code":"PPL",
    "gn:name":"Harauli Fatehpur",
    "gn:population":0,
    "gn:timezone":"Asia/Kolkata",
    "iso:country":"IN",
    "ks:ks_name":"Harauli Fatehpur",
    "ks:ks_pop":1514,
    "ks:ks_type":"VILLAGE",
    "name:eng_x_preferred":[
        "Harauli Fatehpur"
    ],
    "wof:name":"Harauli Fatehpur",
    "wof:placetype":"locality",
    "wof:population":1514
},
  "geometry": {"coordinates":[85.193141,25.767809],"type":"Point"}
}