{
  "type": "Feature",
  "properties": {
    "gn:admin1_code":"12.0",
    "gn:admin2_code":"14.0",
    "gn:asciiname":"Dadwan",
    "gn:country_code":"IN",
    "gn:dem":3041,
    "gn:feature_class":"P",
    "gn:feature_code":"PPL",
    "gn:name":"Dadw\u0101n",
    "gn:population":0,
    "gn:timezone":"Asia/Kolkata",
    "iso:country":"IN",
    "wof:name":"Dadwan",
    "wof:placetype":"locality"
},
  "geometry": {"coordinates":[75.43829000000002,33.45780999999999],"type":"Point"}
}