{
  "type": "Feature",
  "properties": {
    "iso:country":"IN",
    "ks:ks_name":"Suralikoppa",
    "ks:ks_pop":143,
    "ks:ks_type":"HABITATION",
    "name:eng_x_preferred":[
        "Suralikoppa"
    ],
    "wof:name":"Suralikoppa",
    "wof:placetype":"locality",
    "wof:population":143
},
  "geometry": {"coordinates":[75.13216,13.92576],"type":"Point"}
}