{
  "type": "Feature",
  "properties": {
    "gn:admin1_code":"19.0",
    "gn:admin2_code":"577.0",
    "gn:asciiname":"Gudamadanahalli",
    "gn:country_code":"IN",
    "gn:dem":711,
    "gn:feature_class":"P",
    "gn:feature_code":"PPL",
    "gn:name":"Gudam\u0101danahalli",
    "gn:population":0,
    "gn:timezone":"Asia/Kolkata",
    "iso:country":"IN",
    "ks:ks_alt_nam":"Gudam\u0101danahalli",
    "ks:ks_name":"Gudamadanahalli",
    "ks:ks_type":"VILLAGE",
    "ks:ks_uagg_main":0,
    "wof:name":"Gudamadanahalli",
    "wof:placetype":"neighbourhood"
},
  "geometry": {"coordinates":[76.66928,12.24774],"type":"Point"}
}