{
  "type": "Feature",
  "properties": {
    "iso:country":"IN",
    "name:eng_x_preferred":[
        "Bhadra"
    ],
    "name:mal_x_preferred":[
        "\u0d2d\u0d26\u0d4d\u0d30"
    ],
    "name:pan_x_preferred":[
        "\u0a2d\u0a26\u0a30"
    ],
    "qs:name":"Bhadra",
    "qs:name_adm0":"India",
    "qs:name_adm1":"Gujarat",
    "qs:photos":253,
    "qs:photos_1k":51,
    "qs:photos_9k":1,
    "qs:photos_9r":4,
    "qs:photos_all":253,
    "qs:photos_sr":5,
    "qs:placetype":"Suburb",
    "qs:pop_sr":"0",
    "wd:wordcount":218,
    "wof:name":"Bhadra",
    "wof:placetype":"neighbourhood"
},
  "geometry": {"coordinates":[72.577035,23.028525],"type":"Point"}
}