{
  "type": "Feature",
  "properties": {
    "iso:country":"IN",
    "name:asm_x_preferred":[
        "\u09ad\u09a6\u09cd\u09f0\u09be"
    ],
    "name:ben_x_preferred":[
        "\u09ad\u09a6\u09cd\u09f0\u09be"
    ],
    "name:eng_x_preferred":[
        "Bhadra"
    ],
    "name:hin_x_preferred":[
        "\u092d\u0926\u094d\u0930\u093e"
    ],
    "name:jpn_x_preferred":[
        "\u30d0\u30c9\u30e9"
    ],
    "name:kan_x_preferred":[
        "\u0cad\u0ca6\u0ccd\u0cb0"
    ],
    "name:khm_x_preferred":[
        "\u1797\u1791\u17d2\u179a\u17b6"
    ],
    "name:mal_x_preferred":[
        "\u0d2d\u0d26\u0d4d\u0d30"
    ],
    "name:mar_x_preferred":[
        "\u092d\u0926\u094d\u0930"
    ],
    "name:pan_x_preferred":[
        "\u0a2d\u0a26\u0a30"
    ],
    "name:rus_x_preferred":[
        "\u0411\u0445\u0430\u0434\u0440\u0430"
    ],
    "name:swa_x_preferred":[
        "Bhadra"
    ],
    "name:tam_x_preferred":[
        "\u0baa\u0ba4\u0bcd\u0bb0\u0bbe"
    ],
    "name:tha_x_preferred":[
        "\u0e1e\u0e23\u0e30\u0e19\u0e32\u0e07\u0e20\u0e31\u0e17\u0e23\u0e32"
    ],
    "name:zho_x_preferred":[
        "\u8dcb\u9640\u7f57"
    ],
    "qs:name":"Bhadra",
    "qs:name_adm0":"India",
    "qs:name_adm1":"Gujarat",
    "qs:photos":253,
    "qs:photos_1k":51,
    "qs:photos_9k":1,
    "qs:photos_9r":4,
    "qs:photos_all":253,
    "qs:photos_sr":5,
    "qs:placetype":"Suburb",
    "qs:pop_sr":"0",
    "wd:wordcount":218,
    "wof:name":"Bhadra",
    "wof:placetype":"neighbourhood"
},
  "geometry": {"coordinates":[72.577035,23.028525],"type":"Point"}
}