{
  "type": "Feature",
  "properties": {
    "gn:admin1_code":"25.0",
    "gn:admin2_code":"604.0",
    "gn:asciiname":"Govindavadi",
    "gn:country_code":"IN",
    "gn:dem":94,
    "gn:feature_class":"P",
    "gn:feature_code":"PPL",
    "gn:name":"Gov\u012bndav\u0101di",
    "gn:population":0,
    "gn:timezone":"Asia/Kolkata",
    "iso:country":"IN",
    "name:vie_x_preferred":[
        "Govindavadi"
    ],
    "wof:name":"Govindavadi",
    "wof:placetype":"locality"
},
  "geometry": {"coordinates":[79.66589,12.94483],"type":"Point"}
}