{
  "type": "Feature",
  "properties": {
    "iso:country":"IN",
    "ks:ks_name":"Dupadia",
    "ks:ks_pop":93,
    "ks:ks_type":"HABITATION",
    "name:eng_x_preferred":[
        "Dupadia"
    ],
    "wof:name":"Dupadia",
    "wof:placetype":"locality",
    "wof:population":93
},
  "geometry": {"coordinates":[76.932444,23.538856],"type":"Point"}
}