{
  "type": "Feature",
  "properties": {
    "iso:country":"IN",
    "ks:ks_alt_nam":"WEST TOLA",
    "ks:ks_name":"West Tola",
    "ks:ks_pop":50,
    "ks:ks_type":"HABITATION",
    "name:eng_x_preferred":[
        "West Tola"
    ],
    "wof:name":"West Tola",
    "wof:placetype":"locality",
    "wof:population":50
},
  "geometry": {"coordinates":[86.014212,25.135541],"type":"Point"}
}