{
  "type": "Feature",
  "properties": {
    "iso:country":"IN",
    "ks:ks_name":"Urrahat",
    "ks:ks_type":"VILLAGE",
    "ks:ks_uagg_main":0,
    "name:eng_x_preferred":[
        "Urrahat"
    ],
    "wof:name":"Urrahat",
    "wof:placetype":"neighbourhood"
},
  "geometry": {"coordinates":[81.308846,24.543294],"type":"Point"}
}