{
  "type": "Feature",
  "properties": {
    "gn:admin1_code":"21.0",
    "gn:admin2_code":"370.0",
    "gn:asciiname":"Gaisilet",
    "gn:country_code":"IN",
    "gn:dem":183,
    "gn:feature_class":"P",
    "gn:feature_code":"PPLL",
    "gn:name":"Gaisilet",
    "gn:population":0,
    "gn:timezone":"Asia/Kolkata",
    "iso:country":"IN",
    "wof:name":"Gaisilet",
    "wof:placetype":"locality"
},
  "geometry": {"coordinates":[83.31305,20.96106],"type":"Point"}
}