{
  "type": "Feature",
  "properties": {
    "gn:admin1_code":"10.0",
    "gn:admin2_code":"78.0",
    "gn:asciiname":"Nikhatia",
    "gn:country_code":"IN",
    "gn:dem":210,
    "gn:feature_class":"P",
    "gn:feature_code":"PPL",
    "gn:name":"Nikh\u0101tia",
    "gn:population":0,
    "gn:timezone":"Asia/Kolkata",
    "iso:country":"IN",
    "wof:name":"Nikhatia",
    "wof:placetype":"locality"
},
  "geometry": {"coordinates":[75.34291,29.5905],"type":"Point"}
}