{
  "type": "Feature",
  "properties": {
    "iso:country":"IN",
    "name:bpy_x_preferred":[
        "\u09aa\u09be\u09ae\u09cd\u09ae\u09be\u09b2"
    ],
    "name:eng_x_preferred":[
        "Pammal"
    ],
    "name:ita_x_preferred":[
        "Pammal"
    ],
    "name:mlg_x_preferred":[
        "Pammal"
    ],
    "name:msa_x_preferred":[
        "Pammal"
    ],
    "name:nld_x_preferred":[
        "Pammal"
    ],
    "name:tam_x_preferred":[
        "\u0baa\u0bae\u0bcd\u0bae\u0bb2\u0bcd"
    ],
    "name:unk_x_variant":[
        "Pammal"
    ],
    "name:vie_x_preferred":[
        "Pammal"
    ],
    "name:zho_min_nan_x_preferred":[
        "Pammal"
    ],
    "name:zho_x_preferred":[
        "\u5e15\u9a6c\u5c14"
    ],
    "qs:gn_adm0_cc":"IN",
    "qs:gn_local":1268159,
    "qs:gn_nam_loc":"Kancheepuram, Kanchipuram, Tamil Nadu, IN",
    "qs:gn_namadm1":"25",
    "qs:local_max":274,
    "qs:local_sum":2276,
    "qs:localhoods":28,
    "qs:name":"Pammal",
    "qs:name_adm0":"India",
    "qs:name_adm1":"Tamil Nadu",
    "qs:name_adm2":"Kancheepuram",
    "qs:name_local":"Kanchipuram",
    "qs:photo_max":1,
    "qs:photo_sum":2,
    "qs:placetype":"Suburb",
    "qs:quad_count":2,
    "qs:woe_adm0":23424848,
    "qs:woe_adm1":2345758,
    "qs:woe_adm2":12586683,
    "qs:woe_lau":0,
    "qs:woe_local":55924325,
    "qs:woe_ver":"7.10.0",
    "wd:wordcount":150,
    "wof:lang":[
        "eng"
    ],
    "wof:name":"Pammal",
    "wof:placetype":"neighbourhood"
},
  "geometry": {"coordinates":[80.12237500000001,12.969765],"type":"Point"}
}