{
  "type": "Feature",
  "properties": {
    "iso:country":"IN",
    "ks:ks_name":"Neerupaje",
    "ks:ks_pop":630,
    "ks:ks_type":"HABITATION",
    "name:eng_x_preferred":[
        "Neerupaje"
    ],
    "wof:name":"Neerupaje",
    "wof:placetype":"locality",
    "wof:population":630
},
  "geometry": {"coordinates":[75.04768,12.729085],"type":"Point"}
}