{
  "type": "Feature",
  "properties": {
    "gn:admin1_code":"34.0",
    "gn:admin2_code":"224",
    "gn:asciiname":"Bara",
    "gn:country_code":"IN",
    "gn:dem":63,
    "gn:feature_class":"P",
    "gn:feature_code":"PPL",
    "gn:name":"B\u0101ra",
    "gn:population":0,
    "gn:timezone":"Asia/Kolkata",
    "iso:country":"IN",
    "ks:ks_alt_nam":"B\u0101ra",
    "ks:ks_name":"Bara",
    "ks:ks_pop":2542,
    "ks:ks_type":"VILLAGE",
    "ks:ks_uagg_main":0,
    "name:bos_x_preferred":[
        "Bara"
    ],
    "name:bul_x_preferred":[
        "\u0411\u0430\u0440\u0430"
    ],
    "name:cat_x_preferred":[
        "Bara"
    ],
    "name:ceb_x_preferred":[
        "Bara"
    ],
    "name:ces_x_preferred":[
        "Bara"
    ],
    "name:deu_x_preferred":[
        "Bara"
    ],
    "name:eng_x_preferred":[
        "Bara"
    ],
    "name:eng_x_variant":[
        "B\u0101ra"
    ],
    "name:epo_x_preferred":[
        "Bara"
    ],
    "name:eus_x_preferred":[
        "Bara"
    ],
    "name:fra_x_preferred":[
        "Bara"
    ],
    "name:hye_x_preferred":[
        "\u0532\u0561\u0580\u0561"
    ],
    "name:ita_x_preferred":[
        "Bara"
    ],
    "name:jpn_x_preferred":[
        "\u30d0\u30e9"
    ],
    "name:lav_x_preferred":[
        "Bara"
    ],
    "name:lit_x_preferred":[
        "Bara"
    ],
    "name:nds_x_preferred":[
        "Bara"
    ],
    "name:nld_x_preferred":[
        "Bara"
    ],
    "name:pol_x_preferred":[
        "Bara"
    ],
    "name:por_x_preferred":[
        "Bara"
    ],
    "name:rus_x_preferred":[
        "\u0411\u0430\u0440\u0430"
    ],
    "name:spa_x_preferred":[
        "Bara"
    ],
    "name:srp_x_preferred":[
        "\u0411\u0430\u0440\u0430"
    ],
    "name:swe_x_preferred":[
        "Bara"
    ],
    "name:tgl_x_preferred":[
        "Bara"
    ],
    "name:ukr_x_preferred":[
        "\u0411\u0430\u0440\u0430"
    ],
    "name:vie_x_preferred":[
        "Bara"
    ],
    "wof:name":"Bara",
    "wof:placetype":"neighbourhood",
    "wof:population":2542
},
  "geometry": {"coordinates":[87.374743,25.218356],"type":"Point"}
}