{
  "type": "Feature",
  "properties": {
    "gn:admin1_code":"19.0",
    "gn:admin2_code":"564.0",
    "gn:asciiname":"Tadas",
    "gn:country_code":"IN",
    "gn:dem":673,
    "gn:feature_class":"P",
    "gn:feature_code":"PPL",
    "gn:name":"Tadas",
    "gn:population":0,
    "gn:timezone":"Asia/Kolkata",
    "iso:country":"IN",
    "name:ceb_x_preferred":[
        "Tadas"
    ],
    "name:swe_x_preferred":[
        "Tadas"
    ],
    "wof:name":"Tadas",
    "wof:placetype":"locality"
},
  "geometry": {"coordinates":[75.40675999999998,14.61185],"type":"Point"}
}