{
  "type": "Feature",
  "properties": {
    "iso:country":"IN",
    "ks:ks_name":"Barkapla",
    "ks:ks_pop":308,
    "ks:ks_type":"VILLAGE",
    "ks:ks_uagg_main":0,
    "name:eng_x_preferred":[
        "Barkapla"
    ],
    "wof:name":"Barkapla",
    "wof:placetype":"neighbourhood",
    "wof:population":308
},
  "geometry": {"coordinates":[91.20459200000001,26.339357],"type":"Point"}
}