{
  "type": "Feature",
  "properties": {
    "iso:country":"IN",
    "ks:ks_name":"Narayan Pur Dev",
    "ks:ks_pop":147,
    "ks:ks_type":"HABITATION",
    "name:eng_x_preferred":[
        "Narayan Pur Dev"
    ],
    "wof:name":"Narayan Pur Dev",
    "wof:placetype":"locality",
    "wof:population":147
},
  "geometry": {"coordinates":[80.80416099999999,27.113555],"type":"Point"}
}