{
  "type": "Feature",
  "properties": {
    "iso:country":"IN",
    "ks:ks_name":"Palasa Ka",
    "ks:ks_pop":1681,
    "ks:ks_type":"HABITATION",
    "name:eng_x_preferred":[
        "Palasa Ka"
    ],
    "wof:name":"Palasa Ka",
    "wof:placetype":"locality",
    "wof:population":1681
},
  "geometry": {"coordinates":[85.403634,21.923272],"type":"Point"}
}