{
  "type": "Feature",
  "properties": {
    "gn:admin1_code":"19.0",
    "gn:admin2_code":"570.0",
    "gn:asciiname":"Kotakal",
    "gn:country_code":"IN",
    "gn:dem":643,
    "gn:feature_class":"P",
    "gn:feature_code":"PPL",
    "gn:name":"Kotak\u0101l",
    "gn:population":0,
    "gn:timezone":"Asia/Kolkata",
    "iso:country":"IN",
    "wof:name":"Kotakal",
    "wof:placetype":"locality"
},
  "geometry": {"coordinates":[75.26408000000001,13.52788],"type":"Point"}
}