{
  "type": "Feature",
  "properties": {
    "iso:country":"IN",
    "ks:ks_name":"Kalyanpura",
    "ks:ks_pop":611,
    "ks:ks_type":"VILLAGE",
    "name:eng_x_preferred":[
        "Kalyanpura"
    ],
    "wof:name":"Kalyanpura",
    "wof:placetype":"locality",
    "wof:population":611
},
  "geometry": {"coordinates":[72.861028,23.879417],"type":"Point"}
}