{
  "type": "Feature",
  "properties": {
    "iso:country":"IN",
    "ks:ks_name":"Chilipodar",
    "ks:ks_pop":228,
    "ks:ks_type":"VILLAGE",
    "name:eng_x_preferred":[
        "Chilipodar"
    ],
    "wof:name":"Chilipodar",
    "wof:placetype":"locality",
    "wof:population":228
},
  "geometry": {"coordinates":[82.19302399999999,18.35421],"type":"Point"}
}