{
  "type": "Feature",
  "properties": {
    "gn:admin1_code":"36.0",
    "gn:admin2_code":"150.0",
    "gn:asciiname":"Nagaria Dehzabti",
    "gn:country_code":"IN",
    "gn:dem":165,
    "gn:feature_class":"P",
    "gn:feature_code":"PPL",
    "gn:name":"Nagaria Dehzabti",
    "gn:population":0,
    "gn:timezone":"Asia/Kolkata",
    "iso:country":"IN",
    "ks:ks_name":"Nagaria Dehzabti",
    "ks:ks_type":"VILLAGE",
    "name:eng_x_preferred":[
        "Nagaria Dehzabti"
    ],
    "wof:name":"Nagaria Dehzabti",
    "wof:placetype":"locality"
},
  "geometry": {"coordinates":[79.20719699999999,28.241209],"type":"Point"}
}