{
  "type": "Feature",
  "properties": {
    "iso:country":"IN",
    "ks:ks_name":"Dabhiwadi",
    "ks:ks_pop":74,
    "ks:ks_type":"HABITATION",
    "name:eng_x_preferred":[
        "Dabhiwadi"
    ],
    "wof:name":"Dabhiwadi",
    "wof:placetype":"locality",
    "wof:population":74
},
  "geometry": {"coordinates":[73.835733,16.165285],"type":"Point"}
}