{
  "type": "Feature",
  "properties": {
    "iso:country":"IN",
    "ks:ks_name":"Itapara",
    "ks:ks_pop":432,
    "ks:ks_type":"HABITATION",
    "ks:ks_uagg_main":0,
    "name:eng_x_preferred":[
        "Itapara"
    ],
    "wof:name":"Itapara",
    "wof:placetype":"neighbourhood",
    "wof:population":432
},
  "geometry": {"coordinates":[93.148055,26.202191],"type":"Point"}
}