{
  "type": "Feature",
  "properties": {
    "iso:country":"IN",
    "ks:ks_alt_nam":"Simar lagga rajbakti",
    "ks:ks_name":"Simar Lagga Rajbakti",
    "ks:ks_pop":10,
    "ks:ks_type":"HABITATION",
    "name:eng_x_preferred":[
        "Simar Lagga Rajbakti"
    ],
    "wof:name":"Simar Lagga Rajbakti",
    "wof:placetype":"locality",
    "wof:population":10
},
  "geometry": {"coordinates":[79.338086,30.313566],"type":"Point"}
}