{
  "type": "Feature",
  "properties": {
    "iso:country":"IN",
    "ks:ks_name":"Kalasahi",
    "ks:ks_pop":118,
    "ks:ks_type":"VILLAGE",
    "name:eng_x_preferred":[
        "Kalasahi"
    ],
    "wof:name":"Kalasahi",
    "wof:placetype":"locality",
    "wof:population":118
},
  "geometry": {"coordinates":[84.411069,19.099879],"type":"Point"}
}