{
  "type": "Feature",
  "properties": {
    "gn:admin1_code":"40",
    "gn:admin2_code":"538.0",
    "gn:asciiname":"Bhairampalli",
    "gn:country_code":"IN",
    "gn:dem":371,
    "gn:feature_class":"P",
    "gn:feature_code":"PPL",
    "gn:name":"Bhairampalli",
    "gn:population":0,
    "gn:timezone":"Asia/Kolkata",
    "iso:country":"IN",
    "wof:name":"Bhairampalli",
    "wof:placetype":"locality"
},
  "geometry": {"coordinates":[77.41207,16.56205],"type":"Point"}
}