{
  "type": "Feature",
  "properties": {
    "iso:country":"IN",
    "ks:ks_name":"Lakkapakalu",
    "ks:ks_pop":192,
    "ks:ks_type":"HABITATION",
    "name:eng_x_preferred":[
        "Lakkapakalu"
    ],
    "wof:name":"Lakkapakalu",
    "wof:placetype":"locality",
    "wof:population":192
},
  "geometry": {"coordinates":[82.166921,17.81875],"type":"Point"}
}