{
  "type": "Feature",
  "properties": {
    "iso:country":"IN",
    "name:bpy_x_preferred":[
        "\u09ae\u09a6\u09ae\u09ac\u09be\u0995\u09cd\u0995\u09be\u09ae"
    ],
    "name:bul_x_preferred":[
        "\u041c\u0430\u0434\u0430\u043c\u0431\u0430\u043a\u0430\u043c"
    ],
    "name:ceb_x_preferred":[
        "Madambakkam"
    ],
    "name:eng_x_preferred":[
        "Madambakkam"
    ],
    "name:fra_x_preferred":[
        "Madambakkam"
    ],
    "name:ita_x_preferred":[
        "Madambakkam"
    ],
    "name:mlg_x_preferred":[
        "Madambakkam"
    ],
    "name:msa_x_preferred":[
        "Madambakkam"
    ],
    "name:nan_x_preferred":[
        "Madambakkam"
    ],
    "name:new_x_preferred":[
        "\u092e\u0926\u092e\u094d\u092c\u0915\u094d\u0915\u092e"
    ],
    "name:nld_x_preferred":[
        "Madambakkam"
    ],
    "name:por_x_preferred":[
        "Madambakkam"
    ],
    "name:swe_x_preferred":[
        "Madambakkam"
    ],
    "name:tam_x_preferred":[
        "\u0bae\u0bbe\u0ba4\u0bae\u0bcd\u0baa\u0bbe\u0b95\u0bcd\u0b95\u0bae\u0bcd"
    ],
    "name:urd_x_preferred":[
        "\u0645\u06cc\u0688\u0627\u0645\u0628\u0627\u06a9\u0627\u0645"
    ],
    "name:vie_x_preferred":[
        "Madambakkam"
    ],
    "name:zho_x_preferred":[
        "\u9a6c\u8fbe\u59c6\u5df4\u5361\u59c6"
    ],
    "qs:name":"Madambakkam",
    "qs:name_adm0":"India",
    "qs:name_adm1":"Tamil Nadu",
    "qs:photos":1,
    "qs:photos_1k":1,
    "qs:photos_9k":1,
    "qs:photos_9r":1,
    "qs:photos_all":1,
    "qs:photos_sr":1,
    "qs:placetype":"Suburb",
    "qs:pop_sr":"0",
    "wd:wordcount":954,
    "wof:name":"Madambakkam",
    "wof:placetype":"neighbourhood"
},
  "geometry": {"coordinates":[80.121917,12.946261],"type":"Point"}
}