{
  "type": "Feature",
  "properties": {
    "iso:country":"IN",
    "name:ara_x_preferred":[
        "\u0645\u0627\u062f\u0627\u0645\u0628\u0643\u0627\u0645"
    ],
    "name:ben_bn_x_preferred":[
        "\u09ae\u09a6\u09ae\u09ac\u09be\u0995\u09cd\u0995\u09be\u09ae"
    ],
    "name:ben_in_x_preferred":[
        "\u09ae\u09a6\u09ae\u09ac\u09be\u0995\u09cd\u0995\u09be\u09ae"
    ],
    "name:ben_x_preferred":[
        "\u09ae\u09be\u09b8\u09ae\u09ac\u0995\u09cd\u0995\u09ae"
    ],
    "name:bpy_x_preferred":[
        "\u09ae\u09a6\u09ae\u09ac\u09be\u0995\u09cd\u0995\u09be\u09ae"
    ],
    "name:bul_x_preferred":[
        "\u041c\u0430\u0434\u0430\u043c\u0431\u0430\u043a\u0430\u043c"
    ],
    "name:ceb_x_preferred":[
        "Madambakkam"
    ],
    "name:eng_x_preferred":[
        "Madambakkam"
    ],
    "name:fra_x_preferred":[
        "Madambakkam"
    ],
    "name:guj_x_preferred":[
        "\u0aae\u0abe\u0aa6\u0aae\u0acd\u0aac\u0a95\u0aae\u0acd"
    ],
    "name:hin_x_preferred":[
        "\u092e\u0926\u092e\u094d\u092c\u0915\u094d\u0915\u092e"
    ],
    "name:hin_x_variant":[
        "\u092e\u093e\u0926\u092e\u092c\u093e\u0915\u094d\u0915\u092e"
    ],
    "name:ita_x_preferred":[
        "Madambakkam"
    ],
    "name:kan_x_preferred":[
        "\u0cae\u0ca1\u0c82\u0cac\u0cbe\u0c95\u0ccd\u0c95\u0cae\u0ccd"
    ],
    "name:mal_x_preferred":[
        "\u0d2e\u0d3e\u0d21\u0d2e\u0d4d\u0d2a\u0d3e\u0d15\u0d4d\u0d15\u0d02"
    ],
    "name:mar_x_preferred":[
        "\u092e\u093e\u0926\u0902\u092c\u0915\u094d\u0915\u092e"
    ],
    "name:mlg_x_preferred":[
        "Madambakkam"
    ],
    "name:msa_x_preferred":[
        "Madambakkam"
    ],
    "name:nan_x_preferred":[
        "Madambakkam"
    ],
    "name:new_x_preferred":[
        "\u092e\u0926\u092e\u094d\u092c\u0915\u094d\u0915\u092e"
    ],
    "name:nld_x_preferred":[
        "Madambakkam"
    ],
    "name:pan_x_preferred":[
        "\u0a2e\u0a48\u0a21\u0a2e\u0a2c\u0a71\u0a15\u0a2e"
    ],
    "name:por_x_preferred":[
        "Madambakkam"
    ],
    "name:spa_x_preferred":[
        "Madambakkam"
    ],
    "name:swe_x_preferred":[
        "Madambakkam"
    ],
    "name:tam_x_preferred":[
        "\u0bae\u0bbe\u0b9f\u0bae\u0bcd\u0baa\u0bbe\u0b95\u0bcd\u0b95\u0bae\u0bcd"
    ],
    "name:tam_x_variant":[
        "\u0bae\u0bbe\u0ba4\u0bae\u0bcd\u0baa\u0bbe\u0b95\u0bcd\u0b95\u0bae\u0bcd"
    ],
    "name:tel_x_preferred":[
        "\u0c2e\u0c47\u0c21\u0c02\u0c2c\u0c3e\u0c15\u0c02"
    ],
    "name:urd_x_preferred":[
        "\u0645\u0627\u062f\u0645\u0628\u0627\u06a9\u0651\u0645"
    ],
    "name:urd_x_variant":[
        "\u0645\u06cc\u0688\u0627\u0645\u0628\u0627\u06a9\u0627\u0645"
    ],
    "name:vie_x_preferred":[
        "Madambakkam"
    ],
    "name:zho_x_preferred":[
        "\u9a6c\u8fbe\u59c6\u5df4\u5361\u59c6"
    ],
    "qs:name":"Madambakkam",
    "qs:name_adm0":"India",
    "qs:name_adm1":"Tamil Nadu",
    "qs:photos":1,
    "qs:photos_1k":1,
    "qs:photos_9k":1,
    "qs:photos_9r":1,
    "qs:photos_all":1,
    "qs:photos_sr":1,
    "qs:placetype":"Suburb",
    "qs:pop_sr":"0",
    "wd:wordcount":954,
    "wof:name":"Madambakkam",
    "wof:placetype":"neighbourhood"
},
  "geometry": {"coordinates":[80.121917,12.946261],"type":"Point"}
}