{
  "type": "Feature",
  "properties": {
    "gn:admin1_code":"40.0",
    "gn:admin2_code":"532.0",
    "gn:asciiname":"Kazipet",
    "gn:country_code":"IN",
    "gn:dem":191,
    "gn:feature_class":"P",
    "gn:feature_code":"PPL",
    "gn:name":"K\u0101z\u012bpet",
    "gn:population":0,
    "gn:timezone":"Asia/Kolkata",
    "iso:country":"IN",
    "name:ara_x_preferred":[
        "\u0643\u0627\u0630\u0628\u064a\u062a"
    ],
    "name:ben_bn_x_preferred":[
        "\u0995\u09be\u099c\u09bf\u09aa\u09c7\u099f"
    ],
    "name:ben_in_x_preferred":[
        "\u0995\u09be\u099c\u09bf\u09aa\u09c7\u099f"
    ],
    "name:guj_x_preferred":[
        "\u0a95\u0abe\u0a9d\u0abf\u0aaa\u0ac7\u0a9f"
    ],
    "name:hin_x_preferred":[
        "\u0915\u093e\u095b\u0940\u092a\u0947\u091f"
    ],
    "name:kan_x_preferred":[
        "\u0c95\u0c9c\u0cbf\u0caa\u0cc7\u0c9f\u0ccd"
    ],
    "name:mal_x_preferred":[
        "\u0d15\u0d3e\u0d38\u0d3f\u0d2a\u0d47\u0d1f\u0d4d\u0d1f\u0d4d"
    ],
    "name:mar_x_preferred":[
        "\u0915\u093e\u091d\u093f\u092a\u0947\u091f"
    ],
    "name:pan_x_preferred":[
        "\u0a15\u0a3e\u0a1c\u0a3c\u0a40\u0a2a\u0a48\u0a1f"
    ],
    "name:por_x_preferred":[
        "Kazipet"
    ],
    "name:tam_x_preferred":[
        "\u0b95\u0bbe\u0b9c\u0bbf\u0baa\u0bc6\u0b9f\u0bcd"
    ],
    "name:tel_x_preferred":[
        "\u0c15\u0c3e\u0c1c\u0c40\u0c2a\u0c47\u0c1f"
    ],
    "name:urd_x_preferred":[
        "\u0642\u0627\u0636\u06cc \u067e\u06cc\u0679\u06be"
    ],
    "wof:name":"Kazipet",
    "wof:placetype":"locality"
},
  "geometry": {"coordinates":[79.61646999999998,19.12646],"type":"Point"}
}