{
  "type": "Feature",
  "properties": {
    "iso:country":"IN",
    "ks:ks_name":"Nelvoy Village",
    "ks:ks_pop":390,
    "ks:ks_type":"HABITATION",
    "name:eng_x_preferred":[
        "Nelvoy Village"
    ],
    "wof:name":"Nelvoy Village",
    "wof:placetype":"locality",
    "wof:population":390
},
  "geometry": {"coordinates":[80.090586,12.627601],"type":"Point"}
}