{
  "type": "Feature",
  "properties": {
    "gn:admin1_code":"9.0",
    "gn:admin2_code":"472",
    "gn:asciiname":"Bhiloda",
    "gn:country_code":"IN",
    "gn:dem":211,
    "gn:feature_class":"P",
    "gn:feature_code":"PPL",
    "gn:name":"Bhiloda",
    "gn:population":0,
    "gn:timezone":"Asia/Kolkata",
    "iso:country":"IN",
    "name:ben_x_preferred":[
        "\u09ad\u09bf\u09b2\u09cb\u09a1\u09be"
    ],
    "name:guj_x_preferred":[
        "\u0aad\u0abf\u0ab2\u0acb\u0aa1\u0abe"
    ],
    "name:hin_x_preferred":[
        "\u092d\u093f\u0932\u094b\u0921\u093c\u093e"
    ],
    "wof:name":"Bhiloda",
    "wof:placetype":"locality"
},
  "geometry": {"coordinates":[73.24704,23.7676],"type":"Point"}
}