{
  "type": "Feature",
  "properties": {
    "iso:country":"IN",
    "ks:ks_name":"Roopsar",
    "ks:ks_pop":500,
    "ks:ks_type":"HABITATION",
    "name:eng_x_preferred":[
        "Roopsar"
    ],
    "wof:name":"Roopsar",
    "wof:placetype":"locality",
    "wof:population":500
},
  "geometry": {"coordinates":[73.14173599999999,26.549253],"type":"Point"}
}