{
  "type": "Feature",
  "properties": {
    "gn:admin1_code":"2.0",
    "gn:admin2_code":"554.0",
    "gn:asciiname":"Tindigavandlapalle",
    "gn:country_code":"IN",
    "gn:dem":682,
    "gn:feature_class":"P",
    "gn:feature_code":"PPL",
    "gn:name":"Tindigav\u0101ndlapalle",
    "gn:population":0,
    "gn:timezone":"Asia/Kolkata",
    "iso:country":"IN",
    "ks:ks_name":"Thadigavandalapalle",
    "ks:ks_pop":301,
    "ks:ks_type":"HABITATION",
    "ks:ks_uagg_main":0,
    "name:eng_x_preferred":[
        "Thadigavandalapalle"
    ],
    "wof:name":"Thadigavandalapalle",
    "wof:placetype":"neighbourhood",
    "wof:population":301
},
  "geometry": {"coordinates":[78.131682,13.704525],"type":"Point"}
}