{
  "type": "Feature",
  "properties": {
    "iso:country":"IN",
    "ks:ks_name":"Kamarbandh",
    "ks:ks_pop":216,
    "ks:ks_type":"VILLAGE",
    "name:eng_x_preferred":[
        "Kamarbandh"
    ],
    "wof:name":"Kamarbandh",
    "wof:placetype":"locality",
    "wof:population":216
},
  "geometry": {"coordinates":[87.277506,23.117104],"type":"Point"}
}