{
  "type": "Feature",
  "properties": {
    "iso:country":"IN",
    "ks:ks_name":"Tankarai Chowdhury Para",
    "ks:ks_pop":306,
    "ks:ks_type":"HABITATION",
    "name:eng_x_preferred":[
        "Tankarai Chowdhury Para"
    ],
    "wof:name":"Tankarai Chowdhury Para",
    "wof:placetype":"locality",
    "wof:population":306
},
  "geometry": {"coordinates":[92.032235,23.685907],"type":"Point"}
}