{
  "type": "Feature",
  "properties": {
    "iso:country":"IN",
    "ks:ks_name":"Kamupahari",
    "ks:ks_pop":117,
    "ks:ks_type":"VILLAGE",
    "name:eng_x_preferred":[
        "Kamupahari"
    ],
    "wof:name":"Kamupahari",
    "wof:placetype":"locality",
    "wof:population":117
},
  "geometry": {"coordinates":[87.405539,24.568857],"type":"Point"}
}