{
  "type": "Feature",
  "properties": {
    "iso:country":"IN",
    "ks:ks_name":"Gosain Chak",
    "ks:ks_pop":0,
    "ks:ks_type":"VILLAGE",
    "name:eng_x_preferred":[
        "Gosain Chak"
    ],
    "wof:name":"Gosain Chak",
    "wof:placetype":"locality",
    "wof:population":0
},
  "geometry": {"coordinates":[87.31005399999999,25.064212],"type":"Point"}
}