{
  "type": "Feature",
  "properties": {
    "iso:country":"IN",
    "ks:ks_name":"Refuji Colony",
    "ks:ks_pop":1182,
    "ks:ks_type":"HABITATION",
    "name:eng_x_preferred":[
        "Refuji Colony"
    ],
    "wof:name":"Refuji Colony",
    "wof:placetype":"locality",
    "wof:population":1182
},
  "geometry": {"coordinates":[84.995733,26.650936],"type":"Point"}
}