{
  "type": "Feature",
  "properties": {
    "iso:country":"IN",
    "ks:ks_alt_nam":"K.G.Palli Madigapalli",
    "ks:ks_name":"K.g.palli Madigapalli",
    "ks:ks_pop":20,
    "ks:ks_type":"HABITATION",
    "name:eng_x_preferred":[
        "K.g.palli Madigapalli"
    ],
    "wof:name":"K.g.palli Madigapalli",
    "wof:placetype":"locality",
    "wof:population":20
},
  "geometry": {"coordinates":[78.507593,13.989821],"type":"Point"}
}