{
  "type": "Feature",
  "properties": {
    "gn:admin1_code":"35",
    "gn:admin2_code":"455.0",
    "gn:asciiname":"Dodakuhi",
    "gn:country_code":"IN",
    "gn:dem":838,
    "gn:feature_class":"P",
    "gn:feature_code":"PPL",
    "gn:name":"Dod\u0101kuhi",
    "gn:population":0,
    "gn:timezone":"Asia/Kolkata",
    "iso:country":"IN",
    "wof:name":"Dodakuhi",
    "wof:placetype":"locality"
},
  "geometry": {"coordinates":[79.00064,22.35407],"type":"Point"}
}