{
  "type": "Feature",
  "properties": {
    "gn:admin1_code":"35",
    "gn:admin2_code":"455.0",
    "gn:asciiname":"Dodakuhi",
    "gn:country_code":"IN",
    "gn:dem":838,
    "gn:feature_class":"P",
    "gn:feature_code":"PPL",
    "gn:name":"Dod\u0101kuhi",
    "gn:population":0,
    "gn:timezone":"Asia/Kolkata",
    "iso:country":"IN",
    "ks:ks_name":"Dhoda Kuhi",
    "ks:ks_pop":1351,
    "ks:ks_type":"VILLAGE",
    "name:eng_x_preferred":[
        "Dhoda Kuhi"
    ],
    "name:eng_x_variant":[
        "Dodakuhi"
    ],
    "wof:name":"Dhoda Kuhi",
    "wof:placetype":"locality",
    "wof:population":1351
},
  "geometry": {"coordinates":[78.995572,22.362211],"type":"Point"}
}