{
  "type": "Feature",
  "properties": {
    "gn:admin1_code":"16",
    "gn:admin2_code":"509.0",
    "gn:asciiname":"Yenoli",
    "gn:country_code":"IN",
    "gn:dem":252,
    "gn:feature_class":"P",
    "gn:feature_code":"PPL",
    "gn:name":"Yenoli",
    "gn:population":0,
    "gn:timezone":"Asia/Kolkata",
    "iso:country":"IN",
    "ks:ks_name":"Yenoli",
    "ks:ks_type":"VILLAGE",
    "name:eng_x_preferred":[
        "Yenoli"
    ],
    "wof:name":"Yenoli",
    "wof:placetype":"locality"
},
  "geometry": {"coordinates":[79.753388,20.42076],"type":"Point"}
}