{
  "type": "Feature",
  "properties": {
    "gn:admin1_code":"12",
    "gn:admin2_code":"12.0",
    "gn:asciiname":"Narastan",
    "gn:country_code":"IN",
    "gn:dem":2174,
    "gn:feature_class":"P",
    "gn:feature_code":"PPL",
    "gn:name":"N\u0101rast\u0101n",
    "gn:population":0,
    "gn:timezone":"Asia/Kolkata",
    "iso:country":"IN",
    "wof:name":"Narastan",
    "wof:placetype":"locality"
},
  "geometry": {"coordinates":[75.10103000000002,34.0553],"type":"Point"}
}