{
  "type": "Feature",
  "properties": {
    "iso:country":"IN",
    "ks:ks_name":"Kodonipally",
    "ks:ks_pop":313,
    "ks:ks_type":"HABITATION",
    "name:eng_x_preferred":[
        "Kodonipally"
    ],
    "wof:name":"Kodonipally",
    "wof:placetype":"locality",
    "wof:population":313
},
  "geometry": {"coordinates":[78.887114,16.426853],"type":"Point"}
}