{
  "type": "Feature",
  "properties": {
    "iso:country":"IN",
    "ks:ks_name":"Pukhuripara",
    "ks:ks_pop":167,
    "ks:ks_type":"HABITATION",
    "name:eng_x_preferred":[
        "Pukhuripara"
    ],
    "wof:name":"Pukhuripara",
    "wof:placetype":"locality",
    "wof:population":167
},
  "geometry": {"coordinates":[91.264577,25.909818],"type":"Point"}
}