{
  "type": "Feature",
  "properties": {
    "iso:country":"IN",
    "ks:ks_name":"Jeerugedda",
    "ks:ks_pop":91,
    "ks:ks_type":"HABITATION",
    "name:eng_x_preferred":[
        "Jeerugedda"
    ],
    "wof:name":"Jeerugedda",
    "wof:placetype":"locality",
    "wof:population":91
},
  "geometry": {"coordinates":[83.03533400000001,18.267688],"type":"Point"}
}