{
  "type": "Feature",
  "properties": {
    "iso:country":"IN",
    "ks:ks_name":"Kothur",
    "ks:ks_pop":84,
    "ks:ks_type":"HABITATION",
    "name:eng_x_preferred":[
        "Kothur"
    ],
    "wof:name":"Kothur",
    "wof:placetype":"locality",
    "wof:population":84
},
  "geometry": {"coordinates":[79.14135400000001,13.381363],"type":"Point"}
}