{
  "type": "Feature",
  "properties": {
    "gn:admin1_code":"36",
    "gn:admin2_code":"175.0",
    "gn:asciiname":"Haripur",
    "gn:country_code":"IN",
    "gn:dem":97,
    "gn:feature_class":"P",
    "gn:feature_code":"PPL",
    "gn:name":"Har\u012bpur",
    "gn:population":0,
    "gn:timezone":"Asia/Kolkata",
    "iso:country":"IN",
    "name:und_x_variant":[
        "Har\u012bpur",
        "Sarai D\u0101s\u016b"
    ],
    "wof:name":"Haripur",
    "wof:placetype":"locality"
},
  "geometry": {"coordinates":[82.08099,25.3827],"type":"Point"}
}