{
  "type": "Feature",
  "properties": {
    "gn:admin1_code":"39.0",
    "gn:admin2_code":"64.0",
    "gn:asciiname":"Sangura",
    "gn:country_code":"IN",
    "gn:dem":968,
    "gn:feature_class":"P",
    "gn:feature_code":"PPL",
    "gn:name":"S\u0101ngura",
    "gn:population":0,
    "gn:timezone":"Asia/Kolkata",
    "iso:country":"IN",
    "ks:ks_alt_nam":"S\u0101ngura",
    "ks:ks_name":"Sangura",
    "ks:ks_pop":172,
    "ks:ks_type":"VILLAGE",
    "name:eng_x_preferred":[
        "Sangura"
    ],
    "name:eng_x_variant":[
        "S\u0101ngura"
    ],
    "wof:name":"Sangura",
    "wof:placetype":"locality",
    "wof:population":172
},
  "geometry": {"coordinates":[79.36903599999999,29.687542],"type":"Point"}
}