{
  "type": "Feature",
  "properties": {
    "iso:country":"IN",
    "ks:ks_name":"Pawaibahra",
    "ks:ks_pop":571,
    "ks:ks_type":"HABITATION",
    "name:eng_x_preferred":[
        "Pawaibahra"
    ],
    "wof:name":"Pawaibahra",
    "wof:placetype":"locality",
    "wof:population":571
},
  "geometry": {"coordinates":[82.075985,23.436944],"type":"Point"}
}