{
  "type": "Feature",
  "properties": {
    "iso:country":"IN",
    "ks:ks_name":"Kushalpur",
    "ks:ks_pop":0,
    "ks:ks_type":"VILLAGE",
    "name:eng_x_preferred":[
        "Kushalpur"
    ],
    "wof:name":"Kushalpur",
    "wof:placetype":"locality",
    "wof:population":0
},
  "geometry": {"coordinates":[80.299848,27.513642],"type":"Point"}
}