{
  "type": "Feature",
  "properties": {
    "gn:admin1_code":"21.0",
    "gn:asciiname":"Guduru",
    "gn:country_code":"IN",
    "gn:dem":71,
    "gn:feature_class":"P",
    "gn:feature_code":"PPL",
    "gn:name":"G\u016bd\u016bru",
    "gn:population":0,
    "gn:timezone":"Asia/Kolkata",
    "iso:country":"IN",
    "ks:ks_name":"Guduru",
    "ks:ks_pop":597,
    "ks:ks_type":"VILLAGE",
    "name:eng_x_preferred":[
        "Guduru"
    ],
    "name:vie_x_preferred":[
        "Guduru"
    ],
    "wof:name":"Guduru",
    "wof:placetype":"locality",
    "wof:population":597
},
  "geometry": {"coordinates":[81.506764,17.813684],"type":"Point"}
}