{
  "type": "Feature",
  "properties": {
    "gn:admin1_code":"21",
    "gn:admin2_code":"395.0",
    "gn:asciiname":"Ghatikona",
    "gn:country_code":"IN",
    "gn:dem":213,
    "gn:feature_class":"P",
    "gn:feature_code":"PPL",
    "gn:name":"Gh\u0101tikona",
    "gn:population":0,
    "gn:timezone":"Asia/Kolkata",
    "iso:country":"IN",
    "ks:ks_name":"Ghatikana",
    "ks:ks_pop":27,
    "ks:ks_type":"VILLAGE",
    "name:eng_x_preferred":[
        "Ghatikana"
    ],
    "name:eng_x_variant":[
        "Ghatikona"
    ],
    "wof:name":"Ghatikana",
    "wof:placetype":"locality",
    "wof:population":27
},
  "geometry": {"coordinates":[83.02966000000001,19.98816],"type":"Point"}
}