{
  "type": "Feature",
  "properties": {
    "iso:country":"IN",
    "ks:ks_alt_nam":"Charupara JN",
    "ks:ks_name":"Charupara Jn",
    "ks:ks_pop":5012,
    "ks:ks_type":"HABITATION",
    "name:eng_x_preferred":[
        "Charupara Jn"
    ],
    "wof:name":"Charupara Jn",
    "wof:placetype":"locality",
    "wof:population":5012
},
  "geometry": {"coordinates":[76.899821,8.772773],"type":"Point"}
}