{
  "type": "Feature",
  "properties": {
    "gn:admin1_code":"12.0",
    "gn:admin2_code":"004",
    "gn:asciiname":"Silikche",
    "gn:country_code":"IN",
    "gn:dem":2674,
    "gn:feature_class":"P",
    "gn:feature_code":"PPL",
    "gn:name":"Silikche",
    "gn:population":0,
    "gn:timezone":"Asia/Kolkata",
    "iso:country":"IN",
    "wof:name":"Silikche",
    "wof:placetype":"locality"
},
  "geometry": {"coordinates":[76.12778,34.58472],"type":"Point"}
}