{
  "type": "Feature",
  "properties": {
    "gn:admin1_code":"34.0",
    "gn:admin2_code":"229.0",
    "gn:asciiname":"Panheta",
    "gn:country_code":"IN",
    "gn:dem":66,
    "gn:feature_class":"P",
    "gn:feature_code":"PPL",
    "gn:name":"Panheta",
    "gn:population":0,
    "gn:timezone":"Asia/Kolkata",
    "iso:country":"IN",
    "wof:name":"Panheta",
    "wof:placetype":"locality"
},
  "geometry": {"coordinates":[85.45331999999998,25.11317],"type":"Point"}
}