{
  "type": "Feature",
  "properties": {
    "gn:admin1_code":"36",
    "gn:admin2_code":"135.0",
    "gn:asciiname":"Niamatpur Ikrautia",
    "gn:country_code":"IN",
    "gn:dem":194,
    "gn:feature_class":"P",
    "gn:feature_code":"PPL",
    "gn:name":"Ni\u0101matpur Ikrautia",
    "gn:population":0,
    "gn:timezone":"Asia/Kolkata",
    "iso:country":"IN",
    "wof:name":"Niamatpur Ikrautia",
    "wof:placetype":"locality"
},
  "geometry": {"coordinates":[78.91164000000001,28.81705],"type":"Point"}
}