{
  "type": "Feature",
  "properties": {
    "iso:country":"IN",
    "ks:ks_name":"Sindhigiri",
    "ks:ks_pop":74,
    "ks:ks_type":"VILLAGE",
    "name:eng_x_preferred":[
        "Sindhigiri"
    ],
    "wof:name":"Sindhigiri",
    "wof:placetype":"locality",
    "wof:population":74
},
  "geometry": {"coordinates":[83.524286,19.928588],"type":"Point"}
}