{
  "type": "Feature",
  "properties": {
    "iso:country":"IN",
    "ks:ks_name":"Dhondha Nadipara",
    "ks:ks_pop":240,
    "ks:ks_type":"HABITATION",
    "name:eng_x_preferred":[
        "Dhondha Nadipara"
    ],
    "wof:name":"Dhondha Nadipara",
    "wof:placetype":"locality",
    "wof:population":240
},
  "geometry": {"coordinates":[83.204131,23.629394],"type":"Point"}
}