{
  "type": "Feature",
  "properties": {
    "iso:country":"IN",
    "ks:ks_name":"Nellitota",
    "ks:ks_pop":12,
    "ks:ks_type":"HABITATION",
    "name:eng_x_preferred":[
        "Nellitota"
    ],
    "wof:name":"Nellitota",
    "wof:placetype":"locality",
    "wof:population":12
},
  "geometry": {"coordinates":[74.599771,14.671741],"type":"Point"}
}