{
  "type": "Feature",
  "properties": {
    "iso:country":"IN",
    "ks:ks_alt_nam":"Mahesr\u0101",
    "ks:ks_name":"Mahesra",
    "ks:ks_pop":1467,
    "ks:ks_type":"VILLAGE",
    "ks:ks_uagg_main":0,
    "name:eng_x_preferred":[
        "Mahesra"
    ],
    "name:eng_x_variant":[
        "Mahesr\u0101"
    ],
    "wof:name":"Mahesra",
    "wof:placetype":"neighbourhood",
    "wof:population":1467
},
  "geometry": {"coordinates":[85.499084,24.012514],"type":"Point"}
}