{
  "type": "Feature",
  "properties": {
    "iso:country":"IN",
    "ks:ks_name":"Mangarpur",
    "ks:ks_type":"VILLAGE",
    "name:eng_x_preferred":[
        "Mangarpur"
    ],
    "wof:name":"Mangarpur",
    "wof:placetype":"locality"
},
  "geometry": {"coordinates":[78.42157400000001,28.629587],"type":"Point"}
}