{
  "type": "Feature",
  "properties": {
    "iso:country":"IN",
    "ks:ks_name":"Avudayankoilpatty",
    "ks:ks_pop":306,
    "ks:ks_type":"HABITATION",
    "name:eng_x_preferred":[
        "Avudayankoilpatty"
    ],
    "wof:name":"Avudayankoilpatty",
    "wof:placetype":"locality",
    "wof:population":306
},
  "geometry": {"coordinates":[78.83906,10.589726],"type":"Point"}
}