{
  "type": "Feature",
  "properties": {
    "gn:admin1_code":"2",
    "gn:admin2_code":"544.0",
    "gn:asciiname":"Lingapuram",
    "gn:country_code":"IN",
    "gn:dem":413,
    "gn:feature_class":"P",
    "gn:feature_code":"PPL",
    "gn:name":"Ling\u0101puram",
    "gn:population":0,
    "gn:timezone":"Asia/Kolkata",
    "iso:country":"IN",
    "ks:ks_alt_nam":"Ling\u0101puram",
    "ks:ks_name":"Lingapuram",
    "ks:ks_type":"VILLAGE",
    "name:eng_x_preferred":[
        "Lingapuram"
    ],
    "name:eng_x_variant":[
        "Ling\u0101puram"
    ],
    "wof:name":"Lingapuram",
    "wof:placetype":"locality"
},
  "geometry": {"coordinates":[82.48589699999999,17.740922],"type":"Point"}
}