{
  "type": "Feature",
  "properties": {
    "iso:country":"IN",
    "ks:ks_name":"Beedinakere",
    "ks:ks_pop":164,
    "ks:ks_type":"HABITATION",
    "name:eng_x_preferred":[
        "Beedinakere"
    ],
    "wof:name":"Beedinakere",
    "wof:placetype":"locality",
    "wof:population":164
},
  "geometry": {"coordinates":[74.833665,13.199661],"type":"Point"}
}