{
  "type": "Feature",
  "properties": {
    "gn:admin1_code":"36.0",
    "gn:admin2_code":"135.0",
    "gn:asciiname":"Dammu Nagla",
    "gn:country_code":"IN",
    "gn:dem":187,
    "gn:feature_class":"P",
    "gn:feature_code":"PPL",
    "gn:name":"Dammu Nagla",
    "gn:population":0,
    "gn:timezone":"Asia/Kolkata",
    "iso:country":"IN",
    "name:und_x_variant":[
        "Dampura"
    ],
    "wof:name":"Dammu Nagla",
    "wof:placetype":"locality"
},
  "geometry": {"coordinates":[78.88722,28.55571],"type":"Point"}
}