{
  "type": "Feature",
  "properties": {
    "gn:admin1_code":"16.0",
    "gn:admin2_code":"497.0",
    "gn:asciiname":"Pavla",
    "gn:country_code":"IN",
    "gn:dem":158,
    "gn:feature_class":"P",
    "gn:feature_code":"PPL",
    "gn:name":"P\u0101vla",
    "gn:population":0,
    "gn:timezone":"Asia/Kolkata",
    "iso:country":"IN",
    "name:bre_x_preferred":[
        "Pavla"
    ],
    "name:ces_x_preferred":[
        "Pavla"
    ],
    "name:fra_x_preferred":[
        "Pavla"
    ],
    "name:slv_x_preferred":[
        "Pavla"
    ],
    "wof:name":"Pavla",
    "wof:placetype":"locality"
},
  "geometry": {"coordinates":[74.06407,21.38799],"type":"Point"}
}