{
  "type": "Feature",
  "properties": {
    "iso:country":"IN",
    "ks:ks_name":"Gonda",
    "ks:ks_pop":307,
    "ks:ks_type":"VILLAGE",
    "name:eng_x_preferred":[
        "Gonda"
    ],
    "wof:name":"Gonda",
    "wof:placetype":"locality",
    "wof:population":307
},
  "geometry": {"coordinates":[80.51999000000001,24.754494],"type":"Point"}
}