{
  "type": "Feature",
  "properties": {
    "iso:country":"IN",
    "ks:ks_name":"Mankarguda",
    "ks:ks_pop":43,
    "ks:ks_type":"VILLAGE",
    "name:eng_x_preferred":[
        "Mankarguda"
    ],
    "wof:name":"Mankarguda",
    "wof:placetype":"locality",
    "wof:population":43
},
  "geometry": {"coordinates":[82.59456900000001,20.005884],"type":"Point"}
}