{
  "type": "Feature",
  "properties": {
    "gn:admin1_code":"35",
    "gn:admin2_code":"463.0",
    "gn:asciiname":"Antari",
    "gn:country_code":"IN",
    "gn:dem":423,
    "gn:feature_class":"P",
    "gn:feature_code":"PPL",
    "gn:name":"Ant\u0101ri",
    "gn:population":0,
    "gn:timezone":"Asia/Kolkata",
    "iso:country":"IN",
    "name:ben_x_preferred":[
        "\u0985\u09a8\u09cd\u09a4\u09b0\u09bf"
    ],
    "name:bpy_x_preferred":[
        "\u0985\u09a8\u09cd\u09a4\u09b0\u09bf"
    ],
    "name:ita_x_preferred":[
        "Antari"
    ],
    "name:msa_x_preferred":[
        "Antari"
    ],
    "name:new_x_preferred":[
        "\u0905\u0928\u094d\u0924\u0930\u0940"
    ],
    "name:nld_x_preferred":[
        "Antari"
    ],
    "name:por_x_preferred":[
        "Antari"
    ],
    "name:spa_x_preferred":[
        "Antari"
    ],
    "name:vie_x_preferred":[
        "Antari"
    ],
    "name:zho_x_preferred":[
        "\u963f\u6069\u5854\u91cc"
    ],
    "wof:name":"Antari",
    "wof:placetype":"locality"
},
  "geometry": {"coordinates":[82.37855,24.38639],"type":"Point"}
}