{
  "type": "Feature",
  "properties": {
    "gn:admin1_code":"2",
    "gn:admin2_code":"548.0",
    "gn:asciiname":"Garikepadu",
    "gn:country_code":"IN",
    "gn:dem":11,
    "gn:feature_class":"P",
    "gn:feature_code":"PPL",
    "gn:name":"Garikep\u0101du",
    "gn:population":0,
    "gn:timezone":"Asia/Kolkata",
    "iso:country":"IN",
    "wof:name":"Garikepadu",
    "wof:placetype":"locality"
},
  "geometry": {"coordinates":[80.45116,16.06922],"type":"Point"}
}