{
  "type": "Feature",
  "properties": {
    "iso:country":"IN",
    "ks:ks_name":"Soriyampatty",
    "ks:ks_pop":84,
    "ks:ks_type":"HABITATION",
    "name:eng_x_preferred":[
        "Soriyampatty"
    ],
    "wof:name":"Soriyampatty",
    "wof:placetype":"locality",
    "wof:population":84
},
  "geometry": {"coordinates":[78.565523,10.381949],"type":"Point"}
}