{
  "type": "Feature",
  "properties": {
    "iso:country":"IN",
    "ks:ks_name":"Neelahalli Camp",
    "ks:ks_pop":462,
    "ks:ks_type":"HABITATION",
    "name:eng_x_preferred":[
        "Neelahalli Camp"
    ],
    "wof:name":"Neelahalli Camp",
    "wof:placetype":"locality",
    "wof:population":462
},
  "geometry": {"coordinates":[76.687174,15.047155],"type":"Point"}
}