{
  "type": "Feature",
  "properties": {
    "iso:country":"IN",
    "ks:ks_name":"Amber",
    "ks:ks_pop":945,
    "ks:ks_type":"VILLAGE",
    "name:eng_x_preferred":[
        "Amber"
    ],
    "wof:name":"Amber",
    "wof:placetype":"locality",
    "wof:population":945
},
  "geometry": {"coordinates":[86.581643,20.540351],"type":"Point"}
}