{
  "type": "Feature",
  "properties": {
    "iso:country":"IN",
    "ks:ks_alt_nam":"Kebet\u0101ng",
    "ks:ks_name":"Kebetang",
    "ks:ks_pop":288,
    "ks:ks_type":"VILLAGE",
    "name:eng_x_preferred":[
        "Kebetang"
    ],
    "name:eng_x_variant":[
        "Kebet\u0101ng"
    ],
    "wof:name":"Kebetang",
    "wof:placetype":"locality",
    "wof:population":288
},
  "geometry": {"coordinates":[84.947361,22.59183],"type":"Point"}
}