{
  "type": "Feature",
  "properties": {
    "iso:country":"IN",
    "ks:ks_name":"Sardar Para",
    "ks:ks_pop":727,
    "ks:ks_type":"HABITATION",
    "name:eng_x_preferred":[
        "Sardar Para"
    ],
    "wof:name":"Sardar Para",
    "wof:placetype":"locality",
    "wof:population":727
},
  "geometry": {"coordinates":[88.838801,22.230302],"type":"Point"}
}