{
  "type": "Feature",
  "properties": {
    "iso:country":"IN",
    "ks:ks_name":"Burhi Salempur",
    "ks:ks_pop":128,
    "ks:ks_type":"VILLAGE",
    "ks:ks_uagg_main":0,
    "name:eng_x_preferred":[
        "Burhi Salempur"
    ],
    "wof:name":"Burhi Salempur",
    "wof:placetype":"neighbourhood",
    "wof:population":128
},
  "geometry": {"coordinates":[87.212594,24.872639],"type":"Point"}
}