{
  "type": "Feature",
  "properties": {
    "iso:country":"IN",
    "ks:ks_name":"Banddka",
    "ks:ks_pop":28,
    "ks:ks_type":"HABITATION",
    "name:eng_x_preferred":[
        "Banddka"
    ],
    "wof:name":"Banddka",
    "wof:placetype":"locality",
    "wof:population":28
},
  "geometry": {"coordinates":[75.463584,12.504804],"type":"Point"}
}