{
  "type": "Feature",
  "properties": {
    "iso:country":"IN",
    "ks:ks_name":"Dharmabeda",
    "ks:ks_pop":171,
    "ks:ks_type":"VILLAGE",
    "name:eng_x_preferred":[
        "Dharmabeda"
    ],
    "wof:name":"Dharmabeda",
    "wof:placetype":"locality",
    "wof:population":171
},
  "geometry": {"coordinates":[81.525301,19.220717],"type":"Point"}
}