{
  "type": "Feature",
  "properties": {
    "gn:admin1_code":"37.0",
    "gn:admin2_code":"416.0",
    "gn:asciiname":"Goipad",
    "gn:country_code":"IN",
    "gn:dem":609,
    "gn:feature_class":"P",
    "gn:feature_code":"PPL",
    "gn:name":"Goip\u0101d",
    "gn:population":0,
    "gn:timezone":"Asia/Kolkata",
    "iso:country":"IN",
    "wof:name":"Goipad",
    "wof:placetype":"locality"
},
  "geometry": {"coordinates":[81.27044000000002,18.56201],"type":"Point"}
}