{
  "type": "Feature",
  "properties": {
    "gn:admin1_code":"35.0",
    "gn:admin2_code":"454.0",
    "gn:asciiname":"Jhulpul",
    "gn:country_code":"IN",
    "gn:dem":502,
    "gn:feature_class":"P",
    "gn:feature_code":"PPL",
    "gn:name":"Jhulpul",
    "gn:population":0,
    "gn:timezone":"Asia/Kolkata",
    "iso:country":"IN",
    "wof:name":"Jhulpul",
    "wof:placetype":"locality"
},
  "geometry": {"coordinates":[80.09348,22.59296],"type":"Point"}
}