{
  "type": "Feature",
  "properties": {
    "iso:country":"IN",
    "ks:ks_name":"Jhankarpali",
    "ks:ks_pop":193,
    "ks:ks_type":"VILLAGE",
    "name:eng_x_preferred":[
        "Jhankarpali"
    ],
    "wof:name":"Jhankarpali",
    "wof:placetype":"locality",
    "wof:population":193
},
  "geometry": {"coordinates":[83.659029,20.879183],"type":"Point"}
}