{
  "type": "Feature",
  "properties": {
    "iso:country":"IN",
    "ks:ks_name":"Baruapara I",
    "ks:ks_pop":1798,
    "ks:ks_type":"HABITATION",
    "name:eng_x_preferred":[
        "Baruapara I"
    ],
    "wof:name":"Baruapara I",
    "wof:placetype":"locality",
    "wof:population":1798
},
  "geometry": {"coordinates":[90.093531,26.422946],"type":"Point"}
}