{
  "type": "Feature",
  "properties": {
    "iso:country":"IN",
    "ks:ks_name":"Lakhulo",
    "ks:ks_pop":154,
    "ks:ks_type":"HABITATION",
    "name:eng_x_preferred":[
        "Lakhulo"
    ],
    "wof:name":"Lakhulo",
    "wof:placetype":"locality",
    "wof:population":154
},
  "geometry": {"coordinates":[78.194744,24.871598],"type":"Point"}
}