{
  "type": "Feature",
  "properties": {
    "iso:country":"IN",
    "ks:ks_name":"Lakdisil",
    "ks:ks_pop":120,
    "ks:ks_type":"VILLAGE",
    "name:eng_x_preferred":[
        "Lakdisil"
    ],
    "wof:name":"Lakdisil",
    "wof:placetype":"locality",
    "wof:population":120
},
  "geometry": {"coordinates":[82.748335,19.021462],"type":"Point"}
}