{
  "type": "Feature",
  "properties": {
    "iso:country":"IN",
    "ks:ks_name":"Baramoolai H",
    "ks:ks_pop":700,
    "ks:ks_type":"HABITATION",
    "name:eng_x_preferred":[
        "Baramoolai H"
    ],
    "wof:name":"Baramoolai H",
    "wof:placetype":"locality",
    "wof:population":700
},
  "geometry": {"coordinates":[76.68274099999999,11.331519],"type":"Point"}
}