{
  "type": "Feature",
  "properties": {
    "iso:country":"IN",
    "ks:ks_name":"Kardu",
    "ks:ks_type":"VILLAGE",
    "name:eng_x_preferred":[
        "Kardu"
    ],
    "wof:name":"Kardu",
    "wof:placetype":"locality"
},
  "geometry": {"coordinates":[77.23308900000001,20.560997],"type":"Point"}
}