{
  "type": "Feature",
  "properties": {
    "iso:country":"IN",
    "ks:ks_name":"Kurudya",
    "ks:ks_pop":160,
    "ks:ks_type":"HABITATION",
    "name:eng_x_preferred":[
        "Kurudya"
    ],
    "wof:name":"Kurudya",
    "wof:placetype":"locality",
    "wof:population":160
},
  "geometry": {"coordinates":[75.37614499999999,13.036783],"type":"Point"}
}