{
  "type": "Feature",
  "properties": {
    "iso:country":"IN",
    "ks:ks_name":"Patadewadi",
    "ks:ks_pop":59,
    "ks:ks_type":"HABITATION",
    "name:eng_x_preferred":[
        "Patadewadi"
    ],
    "wof:name":"Patadewadi",
    "wof:placetype":"locality",
    "wof:population":59
},
  "geometry": {"coordinates":[73.74388399999999,16.292293],"type":"Point"}
}