{
  "type": "Feature",
  "properties": {
    "iso:country":"IN",
    "ks:ks_name":"Soroguda",
    "ks:ks_pop":75,
    "ks:ks_type":"VILLAGE",
    "name:eng_x_preferred":[
        "Soroguda"
    ],
    "wof:name":"Soroguda",
    "wof:placetype":"locality",
    "wof:population":75
},
  "geometry": {"coordinates":[83.29814399999999,19.664584],"type":"Point"}
}