{
  "type": "Feature",
  "properties": {
    "gn:admin1_code":"19.0",
    "gn:admin2_code":"568.0",
    "gn:asciiname":"Madaravalli",
    "gn:country_code":"IN",
    "gn:dem":633,
    "gn:feature_class":"P",
    "gn:feature_code":"PPL",
    "gn:name":"M\u0101daravalli",
    "gn:population":0,
    "gn:timezone":"Asia/Kolkata",
    "iso:country":"IN",
    "ks:ks_name":"Madravalli",
    "ks:ks_pop":9,
    "ks:ks_type":"VILLAGE",
    "name:eng_x_preferred":[
        "Madravalli"
    ],
    "name:eng_x_variant":[
        "Madaravalli"
    ],
    "wof:name":"Madravalli",
    "wof:placetype":"locality",
    "wof:population":9
},
  "geometry": {"coordinates":[75.33578799999999,14.173637],"type":"Point"}
}