{
  "type": "Feature",
  "properties": {
    "iso:country":"IN",
    "ks:ks_name":"Poomalai",
    "ks:ks_pop":188,
    "ks:ks_type":"HABITATION",
    "name:eng_x_preferred":[
        "Poomalai"
    ],
    "wof:name":"Poomalai",
    "wof:placetype":"locality",
    "wof:population":188
},
  "geometry": {"coordinates":[78.884372,12.863066],"type":"Point"}
}