{
  "type": "Feature",
  "properties": {
    "iso:country":"IN",
    "ks:ks_alt_nam":"VadagaraiValkudi",
    "ks:ks_name":"Vadagaraivalkudi",
    "ks:ks_pop":300,
    "ks:ks_type":"HABITATION",
    "name:eng_x_preferred":[
        "Vadagaraivalkudi"
    ],
    "wof:name":"Vadagaraivalkudi",
    "wof:placetype":"locality",
    "wof:population":300
},
  "geometry": {"coordinates":[79.66932199999999,10.833476],"type":"Point"}
}