{
  "type": "Feature",
  "properties": {
    "gn:admin1_code":"37",
    "gn:admin2_code":"407.0",
    "gn:asciiname":"Duldula",
    "gn:country_code":"IN",
    "gn:dem":806,
    "gn:feature_class":"P",
    "gn:feature_code":"PPL",
    "gn:name":"Duldula",
    "gn:population":0,
    "gn:timezone":"Asia/Kolkata",
    "iso:country":"IN",
    "wof:name":"Duldula",
    "wof:placetype":"locality"
},
  "geometry": {"coordinates":[81.06461999999998,22.19268],"type":"Point"}
}