{
  "type": "Feature",
  "properties": {
    "gn:admin1_code":"37",
    "gn:admin2_code":"407.0",
    "gn:asciiname":"Duldula",
    "gn:country_code":"IN",
    "gn:dem":806,
    "gn:feature_class":"P",
    "gn:feature_code":"PPL",
    "gn:name":"Duldula",
    "gn:population":0,
    "gn:timezone":"Asia/Kolkata",
    "iso:country":"IN",
    "ks:ks_name":"Duldula",
    "ks:ks_pop":438,
    "ks:ks_type":"VILLAGE",
    "name:eng_x_preferred":[
        "Duldula"
    ],
    "wof:name":"Duldula",
    "wof:placetype":"locality",
    "wof:population":438
},
  "geometry": {"coordinates":[81.067977,22.195662],"type":"Point"}
}