{
  "type": "Feature",
  "properties": {
    "gn:admin1_code":"3.0",
    "gn:admin2_code":"304.0",
    "gn:asciiname":"Sunduba",
    "gn:country_code":"IN",
    "gn:dem":58,
    "gn:feature_class":"P",
    "gn:feature_code":"PPL",
    "gn:name":"Sunduba",
    "gn:population":0,
    "gn:timezone":"Asia/Kolkata",
    "iso:country":"IN",
    "wof:name":"Sunduba",
    "wof:placetype":"locality"
},
  "geometry": {"coordinates":[92.22490000000001,26.3594],"type":"Point"}
}