{
  "type": "Feature",
  "properties": {
    "iso:country":"IN",
    "ks:ks_name":"Lakkamuttanahalli",
    "ks:ks_pop":118,
    "ks:ks_type":"VILLAGE",
    "name:eng_x_preferred":[
        "Lakkamuttanahalli"
    ],
    "wof:name":"Lakkamuttanahalli",
    "wof:placetype":"locality",
    "wof:population":118
},
  "geometry": {"coordinates":[77.318769,13.397073],"type":"Point"}
}