{
  "type": "Feature",
  "properties": {
    "gn:admin1_code":"35.0",
    "gn:admin2_code":"434.0",
    "gn:asciiname":"Indrawal Kalan",
    "gn:country_code":"IN",
    "gn:dem":476,
    "gn:feature_class":"P",
    "gn:feature_code":"PPL",
    "gn:name":"Indrawal Kalan",
    "gn:population":0,
    "gn:timezone":"Asia/Kolkata",
    "iso:country":"IN",
    "wof:name":"Indrawal Kalan",
    "wof:placetype":"locality"
},
  "geometry": {"coordinates":[74.8023,23.45569],"type":"Point"}
}