{
  "type": "Feature",
  "properties": {
    "gn:admin1_code":"35.0",
    "gn:admin2_code":"434.0",
    "gn:asciiname":"Indrawal Kalan",
    "gn:country_code":"IN",
    "gn:dem":476,
    "gn:feature_class":"P",
    "gn:feature_code":"PPL",
    "gn:name":"Indrawal Kalan",
    "gn:population":0,
    "gn:timezone":"Asia/Kolkata",
    "iso:country":"IN",
    "ks:ks_name":"Indrawal Kalan",
    "ks:ks_pop":463,
    "ks:ks_type":"VILLAGE",
    "name:eng_x_preferred":[
        "Indrawal Kalan"
    ],
    "wof:name":"Indrawal Kalan",
    "wof:placetype":"locality",
    "wof:population":463
},
  "geometry": {"coordinates":[74.81519299999999,23.46314],"type":"Point"}
}