{
  "type": "Feature",
  "properties": {
    "gn:admin1_code":"36",
    "gn:admin2_code":"185.0",
    "gn:asciiname":"Barah Chhatar Sirihwa",
    "gn:country_code":"IN",
    "gn:dem":84,
    "gn:feature_class":"P",
    "gn:feature_code":"PPL",
    "gn:name":"Barah Chhatar Sirihwa",
    "gn:population":0,
    "gn:timezone":"Asia/Kolkata",
    "iso:country":"IN",
    "wof:name":"Barah Chhatar Sirihwa",
    "wof:placetype":"locality"
},
  "geometry": {"coordinates":[82.68177,26.88179],"type":"Point"}
}