{
  "type": "Feature",
  "properties": {
    "gn:admin1_code":"36",
    "gn:admin2_code":"188.0",
    "gn:asciiname":"Turkaulia Urf Nathpur",
    "gn:country_code":"IN",
    "gn:dem":80,
    "gn:feature_class":"P",
    "gn:feature_code":"PPL",
    "gn:name":"Turkaulia Urf N\u0101thpur",
    "gn:population":0,
    "gn:timezone":"Asia/Kolkata",
    "iso:country":"IN",
    "wof:name":"Turkaulia Urf Nathpur",
    "wof:placetype":"neighbourhood"
},
  "geometry": {"coordinates":[83.37316,26.3295],"type":"Point"}
}