{
  "type": "Feature",
  "properties": {
    "iso:country":"IN",
    "ks:ks_name":"Baruni",
    "ks:ks_pop":60,
    "ks:ks_type":"HABITATION",
    "name:eng_x_preferred":[
        "Baruni"
    ],
    "wof:name":"Baruni",
    "wof:placetype":"locality",
    "wof:population":60
},
  "geometry": {"coordinates":[86.75872099999999,20.51997],"type":"Point"}
}