{
  "type": "Feature",
  "properties": {
    "gn:admin1_code":"39",
    "gn:admin2_code":"59.0",
    "gn:asciiname":"Ghursali",
    "gn:country_code":"IN",
    "gn:dem":692,
    "gn:feature_class":"P",
    "gn:feature_code":"PPL",
    "gn:name":"Ghurs\u0101li",
    "gn:population":0,
    "gn:timezone":"Asia/Kolkata",
    "iso:country":"IN",
    "wof:name":"Ghursali",
    "wof:placetype":"locality"
},
  "geometry": {"coordinates":[78.78955000000001,30.23617],"type":"Point"}
}