{
  "type": "Feature",
  "properties": {
    "gn:admin1_code":"39",
    "gn:admin2_code":"59.0",
    "gn:asciiname":"Ghursali",
    "gn:country_code":"IN",
    "gn:dem":692,
    "gn:feature_class":"P",
    "gn:feature_code":"PPL",
    "gn:name":"Ghurs\u0101li",
    "gn:population":0,
    "gn:timezone":"Asia/Kolkata",
    "iso:country":"IN",
    "name:aze_x_preferred":[
        "Qursal\u0131"
    ],
    "name:fas_x_preferred":[
        "\u063a\u0648\u0631\u0633\u0627\u0644\u06cc"
    ],
    "name:fra_x_preferred":[
        "Ghursal"
    ],
    "name:hye_x_preferred":[
        "\u0542\u0578\u0582\u0580\u057d\u0561\u056c\u056b"
    ],
    "name:ita_x_preferred":[
        "Ghursal"
    ],
    "name:kat_x_preferred":[
        "\u10e6\u10e3\u10e0\u10e1\u10d0\u10da\u10d8"
    ],
    "name:msa_x_preferred":[
        "Ghursal"
    ],
    "name:spa_x_preferred":[
        "Ghursali"
    ],
    "name:vie_x_preferred":[
        "Ghursal"
    ],
    "wof:name":"Ghursali",
    "wof:placetype":"locality"
},
  "geometry": {"coordinates":[78.78955000000001,30.23617],"type":"Point"}
}