{
  "type": "Feature",
  "properties": {
    "iso:country":"IN",
    "ks:ks_alt_nam":"CHINNA PUDUKOTTAI",
    "ks:ks_name":"Chinna Pudukottai",
    "ks:ks_pop":397,
    "ks:ks_type":"HABITATION",
    "ks:ks_uagg_main":0,
    "name:eng_x_preferred":[
        "Chinna Pudukottai"
    ],
    "wof:name":"Chinna Pudukottai",
    "wof:placetype":"neighbourhood",
    "wof:population":397
},
  "geometry": {"coordinates":[78.52815,9.59867],"type":"Point"}
}