{
  "type": "Feature",
  "properties": {
    "gn:admin1_code":"12.0",
    "gn:asciiname":"Chak Subhan Mir",
    "gn:country_code":"IN",
    "gn:dem":3180,
    "gn:feature_class":"P",
    "gn:feature_code":"PPL",
    "gn:name":"Chak Subh\u0101n M\u012br",
    "gn:population":0,
    "gn:timezone":"Asia/Kolkata",
    "iso:country":"IN",
    "wof:name":"Chak Subhan Mir",
    "wof:placetype":"locality"
},
  "geometry": {"coordinates":[75.06723000000002,34.61708],"type":"Point"}
}