{
  "type": "Feature",
  "properties": {
    "gn:admin1_code":"24.0",
    "gn:admin2_code":"102.0",
    "gn:asciiname":"Molisar Chhota",
    "gn:country_code":"IN",
    "gn:dem":308,
    "gn:feature_class":"P",
    "gn:feature_code":"PPL",
    "gn:name":"Mol\u012bsar Chhota",
    "gn:population":0,
    "gn:timezone":"Asia/Kolkata",
    "iso:country":"IN",
    "wof:name":"Molisar Chhota",
    "wof:placetype":"locality"
},
  "geometry": {"coordinates":[74.81216999999999,28.16352],"type":"Point"}
}