{
  "type": "Feature",
  "properties": {
    "iso:country":"IN",
    "ks:ks_name":"Kotipada",
    "ks:ks_pop":110,
    "ks:ks_type":"HABITATION",
    "name:eng_x_preferred":[
        "Kotipada"
    ],
    "wof:name":"Kotipada",
    "wof:placetype":"locality",
    "wof:population":110
},
  "geometry": {"coordinates":[72.981129,19.890913],"type":"Point"}
}