{
  "type": "Feature",
  "properties": {
    "iso:country":"IN",
    "ks:ks_name":"Bilhatia",
    "ks:ks_pop":88,
    "ks:ks_type":"VILLAGE",
    "name:eng_x_preferred":[
        "Bilhatia"
    ],
    "wof:name":"Bilhatia",
    "wof:placetype":"locality",
    "wof:population":88
},
  "geometry": {"coordinates":[88.112649,25.231324],"type":"Point"}
}