{
  "type": "Feature",
  "properties": {
    "iso:country":"IN",
    "ks:ks_name":"Shekhapur",
    "ks:ks_pop":484,
    "ks:ks_type":"HABITATION",
    "name:eng_x_preferred":[
        "Shekhapur"
    ],
    "wof:name":"Shekhapur",
    "wof:placetype":"locality",
    "wof:population":484
},
  "geometry": {"coordinates":[82.12833500000001,27.429473],"type":"Point"}
}