{
  "type": "Feature",
  "properties": {
    "gn:admin1_code":"11",
    "gn:admin2_code":"23.0",
    "gn:asciiname":"Chhao",
    "gn:country_code":"IN",
    "gn:dem":2357,
    "gn:feature_class":"P",
    "gn:feature_code":"PPL",
    "gn:name":"Chhao",
    "gn:population":0,
    "gn:timezone":"Asia/Kolkata",
    "iso:country":"IN",
    "wof:name":"Chhao",
    "wof:placetype":"locality"
},
  "geometry": {"coordinates":[76.45796999999997,32.92612],"type":"Point"}
}