{
  "type": "Feature",
  "properties": {
    "gn:admin1_code":"38",
    "gn:admin2_code":"358.0",
    "gn:asciiname":"Kachan",
    "gn:country_code":"IN",
    "gn:dem":392,
    "gn:feature_class":"P",
    "gn:feature_code":"PPL",
    "gn:name":"K\u0101chan",
    "gn:population":0,
    "gn:timezone":"Asia/Kolkata",
    "iso:country":"IN",
    "ks:ks_alt_nam":"K\u0101chan",
    "ks:ks_name":"Kachan",
    "ks:ks_pop":1861,
    "ks:ks_type":"VILLAGE",
    "name:ceb_x_preferred":[
        "Kachan"
    ],
    "name:eng_x_preferred":[
        "Kachan"
    ],
    "name:eng_x_variant":[
        "K\u0101chan"
    ],
    "name:swe_x_preferred":[
        "Kachan"
    ],
    "wof:name":"Kachan",
    "wof:placetype":"locality",
    "wof:population":1861
},
  "geometry": {"coordinates":[83.977439,23.900665],"type":"Point"}
}