{
  "type": "Feature",
  "properties": {
    "gn:admin1_code":"38",
    "gn:admin2_code":"358.0",
    "gn:asciiname":"Kachan",
    "gn:country_code":"IN",
    "gn:dem":392,
    "gn:feature_class":"P",
    "gn:feature_code":"PPL",
    "gn:name":"K\u0101chan",
    "gn:population":0,
    "gn:timezone":"Asia/Kolkata",
    "iso:country":"IN",
    "name:ceb_x_preferred":[
        "Kachan"
    ],
    "name:swe_x_preferred":[
        "Kachan"
    ],
    "wof:name":"Kachan",
    "wof:placetype":"locality"
},
  "geometry": {"coordinates":[83.97744,23.90067],"type":"Point"}
}