{
  "type": "Feature",
  "properties": {
    "gn:admin1_code":"36.0",
    "gn:admin2_code":"179.0",
    "gn:asciiname":"Gandi",
    "gn:country_code":"IN",
    "gn:dem":108,
    "gn:feature_class":"P",
    "gn:feature_code":"PPL",
    "gn:name":"Gandi",
    "gn:population":0,
    "gn:timezone":"Asia/Kolkata",
    "iso:country":"IN",
    "name:fra_x_preferred":[
        "Gandi"
    ],
    "name:jpn_x_preferred":[
        "Gandi"
    ],
    "name:swe_x_preferred":[
        "Gandi"
    ],
    "wof:name":"Gandi",
    "wof:placetype":"locality"
},
  "geometry": {"coordinates":[81.86790999999999,26.14903],"type":"Point"}
}