{
  "type": "Feature",
  "properties": {
    "gn:admin1_code":"36",
    "gn:admin2_code":"178.0",
    "gn:asciiname":"Bishunpur",
    "gn:country_code":"IN",
    "gn:dem":97,
    "gn:feature_class":"P",
    "gn:feature_code":"PPL",
    "gn:name":"Bishunpur",
    "gn:population":0,
    "gn:timezone":"Asia/Kolkata",
    "iso:country":"IN",
    "ks:ks_name":"Bishunpur",
    "ks:ks_type":"VILLAGE",
    "ks:ks_uagg_main":0,
    "name:ceb_x_preferred":[
        "Bishunpur"
    ],
    "name:eng_x_preferred":[
        "Bishunpur"
    ],
    "name:msa_x_preferred":[
        "Bishunpur"
    ],
    "name:new_x_preferred":[
        "\u0935\u093f\u0937\u094d\u0923\u0941\u092a\u0941\u0930"
    ],
    "name:pol_x_preferred":[
        "Bishunpur"
    ],
    "wof:name":"Bishunpur",
    "wof:placetype":"neighbourhood"
},
  "geometry": {"coordinates":[82.6238,26.527543],"type":"Point"}
}