{
  "type": "Feature",
  "properties": {
    "gn:admin1_code":"36",
    "gn:admin2_code":"196.0",
    "gn:asciiname":"Musahibpur",
    "gn:country_code":"IN",
    "gn:dem":106,
    "gn:feature_class":"P",
    "gn:feature_code":"PPL",
    "gn:name":"Mus\u0101hibpur",
    "gn:population":0,
    "gn:timezone":"Asia/Kolkata",
    "iso:country":"IN",
    "ks:ks_alt_nam":"Mus\u0101hibpur",
    "ks:ks_name":"Musahibpur",
    "ks:ks_type":"VILLAGE",
    "name:eng_x_preferred":[
        "Musahibpur"
    ],
    "name:eng_x_variant":[
        "Mus\u0101hibpur"
    ],
    "wof:name":"Musahibpur",
    "wof:placetype":"locality"
},
  "geometry": {"coordinates":[83.214439,24.997763],"type":"Point"}
}