{
  "type": "Feature",
  "properties": {
    "iso:country":"IN",
    "ks:ks_name":"Salmari No 3",
    "ks:ks_pop":343,
    "ks:ks_type":"HABITATION",
    "name:eng_x_preferred":[
        "Salmari No 3"
    ],
    "wof:name":"Salmari No 3",
    "wof:placetype":"locality",
    "wof:population":343
},
  "geometry": {"coordinates":[95.103542,27.264046],"type":"Point"}
}