{
  "type": "Feature",
  "properties": {
    "gn:admin1_code":"36.0",
    "gn:admin2_code":"162.0",
    "gn:asciiname":"Bibdour",
    "gn:country_code":"IN",
    "gn:dem":144,
    "gn:feature_class":"P",
    "gn:feature_code":"PPL",
    "gn:name":"Bibdour",
    "gn:population":0,
    "gn:timezone":"Asia/Kolkata",
    "iso:country":"IN",
    "wof:name":"Bibdour",
    "wof:placetype":"neighbourhood"
},
  "geometry": {"coordinates":[79.43695,26.62921],"type":"Point"}
}