{
  "type": "Feature",
  "properties": {
    "gn:admin1_code":"34.0",
    "gn:admin2_code":"230.0",
    "gn:asciiname":"Samsara",
    "gn:country_code":"IN",
    "gn:dem":63,
    "gn:feature_class":"P",
    "gn:feature_code":"PPL",
    "gn:name":"S\u0101msara",
    "gn:population":0,
    "gn:timezone":"Asia/Kolkata",
    "iso:country":"IN",
    "ks:ks_alt_nam":"S\u0101msara",
    "ks:ks_name":"Samsara",
    "ks:ks_pop":1919,
    "ks:ks_type":"VILLAGE",
    "ks:ks_uagg_main":0,
    "name:eng_x_preferred":[
        "Samsara"
    ],
    "name:eng_x_variant":[
        "S\u0101msara"
    ],
    "wof:name":"Samsara",
    "wof:placetype":"neighbourhood",
    "wof:population":1919
},
  "geometry": {"coordinates":[84.912554,25.565599],"type":"Point"}
}