{
  "type": "Feature",
  "properties": {
    "gn:admin1_code":"2.0",
    "gn:admin2_code":"542.0",
    "gn:asciiname":"Marripadu",
    "gn:country_code":"IN",
    "gn:dem":55,
    "gn:feature_class":"P",
    "gn:feature_code":"PPL",
    "gn:name":"Marrip\u0101du",
    "gn:population":0,
    "gn:timezone":"Asia/Kolkata",
    "iso:country":"IN",
    "ks:ks_alt_nam":"Marrip\u0101du",
    "ks:ks_name":"Marripadu",
    "ks:ks_pop":91,
    "ks:ks_type":"VILLAGE",
    "name:eng_x_preferred":[
        "Marripadu"
    ],
    "name:eng_x_variant":[
        "Marrip\u0101du"
    ],
    "name:new_x_preferred":[
        "\u092e\u0930\u094d\u0930\u093f\u092a\u093e\u0921\u0941 \u092e\u0923\u094d\u0921\u0932"
    ],
    "name:tel_x_preferred":[
        "\u0c2e\u0c30\u0c4d\u0c30\u0c3f\u0c2a\u0c3e\u0c21\u0c41 \u0c2e\u0c02\u0c21\u0c32\u0c02"
    ],
    "wof:name":"Marripadu",
    "wof:placetype":"locality",
    "wof:population":91
},
  "geometry": {"coordinates":[83.794344,18.58065],"type":"Point"}
}