{
  "type": "Feature",
  "properties": {
    "gn:admin1_code":"39.0",
    "gn:admin2_code":"59.0",
    "gn:asciiname":"Dhakraut",
    "gn:country_code":"IN",
    "gn:dem":2105,
    "gn:feature_class":"P",
    "gn:feature_code":"PPL",
    "gn:name":"Dhakraut",
    "gn:population":0,
    "gn:timezone":"Asia/Kolkata",
    "iso:country":"IN",
    "wof:name":"Dhakraut",
    "wof:placetype":"locality"
},
  "geometry": {"coordinates":[78.21123,30.46278],"type":"Point"}
}