{
  "type": "Feature",
  "properties": {
    "iso:country":"IN",
    "ks:ks_name":"7 NTW",
    "ks:ks_pop":33,
    "ks:ks_type":"VILLAGE",
    "name:eng_x_preferred":[
        "7 NTW"
    ],
    "wof:name":"7 NTW",
    "wof:placetype":"locality",
    "wof:population":33
},
  "geometry": {"coordinates":[74.423502,29.824668],"type":"Point"}
}