{
  "type": "Feature",
  "properties": {
    "iso:country":"IN",
    "ks:ks_name":"Shirsha",
    "ks:ks_pop":214,
    "ks:ks_type":"VILLAGE",
    "name:eng_x_preferred":[
        "Shirsha"
    ],
    "wof:name":"Shirsha",
    "wof:placetype":"locality",
    "wof:population":214
},
  "geometry": {"coordinates":[87.426453,23.95044],"type":"Point"}
}