{
  "type": "Feature",
  "properties": {
    "iso:country":"IN",
    "ks:ks_name":"Danta Chota Thadoda",
    "ks:ks_pop":509,
    "ks:ks_type":"HABITATION",
    "name:eng_x_preferred":[
        "Danta Chota Thadoda"
    ],
    "wof:name":"Danta Chota Thadoda",
    "wof:placetype":"locality",
    "wof:population":509
},
  "geometry": {"coordinates":[75.29862900000001,25.160122],"type":"Point"}
}