{
  "type": "Feature",
  "properties": {
    "iso:country":"IN",
    "ks:ks_name":"Nelyarni",
    "ks:ks_pop":12,
    "ks:ks_type":"HABITATION",
    "name:eng_x_preferred":[
        "Nelyarni"
    ],
    "wof:name":"Nelyarni",
    "wof:placetype":"locality",
    "wof:population":12
},
  "geometry": {"coordinates":[75.176695,12.684214],"type":"Point"}
}