{
  "type": "Feature",
  "properties": {
    "iso:country":"IN",
    "ks:ks_alt_nam":"S.PALLI MADIGAWADA",
    "ks:ks_name":"S.palli Madigawada",
    "ks:ks_pop":159,
    "ks:ks_type":"HABITATION",
    "ks:ks_uagg_main":0,
    "name:eng_x_preferred":[
        "S.palli Madigawada"
    ],
    "wof:name":"S.palli Madigawada",
    "wof:placetype":"neighbourhood",
    "wof:population":159
},
  "geometry": {"coordinates":[79.184181,14.225379],"type":"Point"}
}