{
  "type": "Feature",
  "properties": {
    "gn:admin1_code":"36",
    "gn:admin2_code":"134.0",
    "gn:asciiname":"Muhammadpur Taki",
    "gn:country_code":"IN",
    "gn:dem":243,
    "gn:feature_class":"P",
    "gn:feature_code":"PPL",
    "gn:name":"Muhammadpur Taki",
    "gn:population":0,
    "gn:timezone":"Asia/Kolkata",
    "iso:country":"IN",
    "name:und_x_variant":[
        "N\u0101r\u0101yani Shernagar"
    ],
    "wof:name":"Muhammadpur Taki",
    "wof:placetype":"neighbourhood"
},
  "geometry": {"coordinates":[78.3886,29.40402],"type":"Point"}
}