{
  "type": "Feature",
  "properties": {
    "iso:country":"IN",
    "ks:ks_alt_nam":"NONIYA TOLA",
    "ks:ks_name":"Noniya Tola",
    "ks:ks_pop":375,
    "ks:ks_type":"HABITATION",
    "ks:ks_uagg_main":0,
    "name:eng_x_preferred":[
        "Noniya Tola"
    ],
    "wof:name":"Noniya Tola",
    "wof:placetype":"neighbourhood",
    "wof:population":375
},
  "geometry": {"coordinates":[87.004785,26.222103],"type":"Point"}
}