{
  "type": "Feature",
  "properties": {
    "gn:admin1_code":"11",
    "gn:admin2_code":"24.0",
    "gn:asciiname":"Nau Gaza",
    "gn:country_code":"IN",
    "gn:dem":769,
    "gn:feature_class":"P",
    "gn:feature_code":"PPL",
    "gn:name":"Nau Gaza",
    "gn:population":0,
    "gn:timezone":"Asia/Kolkata",
    "iso:country":"IN",
    "wof:name":"Nau Gaza",
    "wof:placetype":"locality"
},
  "geometry": {"coordinates":[76.33676,32.08486],"type":"Point"}
}