{
  "type": "Feature",
  "properties": {
    "gn:admin1_code":"36",
    "gn:admin2_code":"198.0",
    "gn:asciiname":"Gokulpur",
    "gn:country_code":"IN",
    "gn:dem":91,
    "gn:feature_class":"P",
    "gn:feature_code":"PPL",
    "gn:name":"Gokulpur",
    "gn:population":0,
    "gn:timezone":"Asia/Kolkata",
    "iso:country":"IN",
    "wof:name":"Gokulpur",
    "wof:placetype":"neighbourhood"
},
  "geometry": {"coordinates":[82.3306,25.38352],"type":"Point"}
}