{
  "type": "Feature",
  "properties": {
    "iso:country":"IN",
    "ks:ks_name":"Kopa",
    "ks:ks_pop":143,
    "ks:ks_type":"VILLAGE",
    "name:eng_x_preferred":[
        "Kopa"
    ],
    "wof:name":"Kopa",
    "wof:placetype":"locality",
    "wof:population":143
},
  "geometry": {"coordinates":[85.369978,22.783737],"type":"Point"}
}