{
  "type": "Feature",
  "properties": {
    "gn:admin1_code":"36.0",
    "gn:admin2_code":"179.0",
    "gn:asciiname":"Sangipur",
    "gn:country_code":"IN",
    "gn:dem":105,
    "gn:feature_class":"P",
    "gn:feature_code":"PPL",
    "gn:name":"S\u0101ngipur",
    "gn:population":0,
    "gn:timezone":"Asia/Kolkata",
    "iso:country":"IN",
    "ks:ks_name":"Sangi Pur",
    "ks:ks_pop":257,
    "ks:ks_type":"HABITATION",
    "name:eng_x_preferred":[
        "Sangi Pur"
    ],
    "name:eng_x_variant":[
        "Sangipur"
    ],
    "wof:name":"Sangi Pur",
    "wof:placetype":"locality",
    "wof:population":257
},
  "geometry": {"coordinates":[81.844739,26.060749],"type":"Point"}
}