{
  "type": "Feature",
  "properties": {
    "iso:country":"IN",
    "ks:ks_name":"Atala",
    "ks:ks_pop":725,
    "ks:ks_type":"HABITATION",
    "name:eng_x_preferred":[
        "Atala"
    ],
    "wof:name":"Atala",
    "wof:placetype":"locality",
    "wof:population":725
},
  "geometry": {"coordinates":[75.284595,12.975676],"type":"Point"}
}