{
  "type": "Feature",
  "properties": {
    "gn:admin1_code":"37.0",
    "gn:admin2_code":"405",
    "gn:asciiname":"Burgahan",
    "gn:country_code":"IN",
    "gn:dem":305,
    "gn:feature_class":"P",
    "gn:feature_code":"PPL",
    "gn:name":"Burgahan",
    "gn:population":0,
    "gn:timezone":"Asia/Kolkata",
    "iso:country":"IN",
    "wof:name":"Burgahan",
    "wof:placetype":"locality"
},
  "geometry": {"coordinates":[82.51487,22.22263],"type":"Point"}
}