{
  "type": "Feature",
  "properties": {
    "gn:admin1_code":"36.0",
    "gn:admin2_code":"172.0",
    "gn:asciiname":"Teonja",
    "gn:country_code":"IN",
    "gn:dem":115,
    "gn:feature_class":"P",
    "gn:feature_code":"PPL",
    "gn:name":"Teonja",
    "gn:population":0,
    "gn:timezone":"Asia/Kolkata",
    "iso:country":"IN",
    "wof:name":"Teonja",
    "wof:placetype":"locality"
},
  "geometry": {"coordinates":[81.07559999999999,25.83049],"type":"Point"}
}