{
  "type": "Feature",
  "properties": {
    "iso:country":"IN",
    "ks:ks_name":"Bhatpal",
    "ks:ks_pop":425,
    "ks:ks_type":"VILLAGE",
    "name:eng_x_preferred":[
        "Bhatpal"
    ],
    "wof:name":"Bhatpal",
    "wof:placetype":"locality",
    "wof:population":425
},
  "geometry": {"coordinates":[81.475082,19.178907],"type":"Point"}
}