{
  "type": "Feature",
  "properties": {
    "iso:country":"IN",
    "ks:ks_name":"Dongarwadi",
    "ks:ks_pop":112,
    "ks:ks_type":"HABITATION",
    "name:eng_x_preferred":[
        "Dongarwadi"
    ],
    "wof:name":"Dongarwadi",
    "wof:placetype":"locality",
    "wof:population":112
},
  "geometry": {"coordinates":[73.80869199999999,15.950148],"type":"Point"}
}