{
  "type": "Feature",
  "properties": {
    "iso:country":"IN",
    "ks:ks_name":"Hussainipur",
    "ks:ks_pop":207,
    "ks:ks_type":"HABITATION",
    "name:eng_x_preferred":[
        "Hussainipur"
    ],
    "wof:name":"Hussainipur",
    "wof:placetype":"locality",
    "wof:population":207
},
  "geometry": {"coordinates":[78.019811,17.957274],"type":"Point"}
}