{
  "type": "Feature",
  "properties": {
    "iso:country":"IN",
    "ks:ks_name":"Sangram",
    "ks:ks_pop":397,
    "ks:ks_type":"VILLAGE",
    "name:eng_x_preferred":[
        "Sangram"
    ],
    "wof:name":"Sangram",
    "wof:placetype":"locality",
    "wof:population":397
},
  "geometry": {"coordinates":[86.90290899999999,22.499696],"type":"Point"}
}