{
  "type": "Feature",
  "properties": {
    "iso:country":"IN",
    "ks:ks_name":"Gorbi",
    "ks:ks_pop":2378,
    "ks:ks_type":"VILLAGE",
    "name:eng_x_preferred":[
        "Gorbi"
    ],
    "wof:name":"Gorbi",
    "wof:placetype":"locality",
    "wof:population":2378
},
  "geometry": {"coordinates":[82.581906,24.202569],"type":"Point"}
}