{
  "type": "Feature",
  "properties": {
    "iso:country":"IN",
    "ks:ks_name":"Andaniyon Ki Beri",
    "ks:ks_pop":120,
    "ks:ks_type":"HABITATION",
    "name:eng_x_preferred":[
        "Andaniyon Ki Beri"
    ],
    "wof:name":"Andaniyon Ki Beri",
    "wof:placetype":"locality",
    "wof:population":120
},
  "geometry": {"coordinates":[71.611839,25.408989],"type":"Point"}
}