{
  "type": "Feature",
  "properties": {
    "iso:country":"IN",
    "ks:ks_alt_nam":"Khaompur II",
    "ks:ks_name":"Khaompur Ii",
    "ks:ks_pop":1429,
    "ks:ks_type":"HABITATION",
    "ks:ks_uagg_main":0,
    "name:eng_x_preferred":[
        "Khaompur Ii"
    ],
    "wof:name":"Khaompur Ii",
    "wof:placetype":"neighbourhood",
    "wof:population":1429
},
  "geometry": {"coordinates":[87.890685,25.268424],"type":"Point"}
}