{
  "type": "Feature",
  "properties": {
    "gn:admin1_code":"25",
    "gn:admin2_code":"605.0",
    "gn:asciiname":"Vallam",
    "gn:country_code":"IN",
    "gn:dem":195,
    "gn:feature_class":"P",
    "gn:feature_code":"PPL",
    "gn:name":"Vallam",
    "gn:population":0,
    "gn:timezone":"Asia/Kolkata",
    "iso:country":"IN",
    "name:bpy_x_preferred":[
        "\u09ac\u09b2\u09b2\u09ae"
    ],
    "name:ceb_x_preferred":[
        "Vallam"
    ],
    "name:ita_x_preferred":[
        "Vallam"
    ],
    "name:msa_x_preferred":[
        "Vallam"
    ],
    "name:nld_x_preferred":[
        "Vallam"
    ],
    "name:por_x_preferred":[
        "Vallam"
    ],
    "name:swe_x_preferred":[
        "Vallam"
    ],
    "name:tam_x_preferred":[
        "\u0bb5\u0bb2\u0bcd\u0bb2\u0bae\u0bcd"
    ],
    "name:vie_x_preferred":[
        "Vallam"
    ],
    "wof:name":"Vallam",
    "wof:placetype":"locality"
},
  "geometry": {"coordinates":[79.15204,12.75366],"type":"Point"}
}