{
  "type": "Feature",
  "properties": {
    "gn:country":"IN",
    "gn:fcode":"PPL",
    "gn:population":37465,
    "iso:country":"IN",
    "name:ben_x_preferred":[
        "\u09ac\u09be\u0987\u09b0\u0997\u09a8\u09bf\u09af\u09bc\u09be"
    ],
    "name:bpy_x_preferred":[
        "\u09ac\u09be\u0987\u09b0\u0997\u09a8\u09bf\u09af\u09bc\u09be"
    ],
    "name:ceb_x_preferred":[
        "Bair\u0101gnia"
    ],
    "name:eng_x_preferred":[
        "Bairgania"
    ],
    "name:fra_x_preferred":[
        "Bairgania"
    ],
    "name:hin_x_preferred":[
        "\u092c\u0948\u0930\u0917\u0928\u093f\u092f\u093e"
    ],
    "name:ita_x_preferred":[
        "Bairgania"
    ],
    "name:msa_x_preferred":[
        "Bairgania"
    ],
    "name:nan_x_preferred":[
        "Bairgania"
    ],
    "name:new_x_preferred":[
        "\u092c\u0948\u0930\u0917\u093e\u0928\u093f\u092f\u093e"
    ],
    "name:nld_x_preferred":[
        "Bairgania"
    ],
    "name:por_x_preferred":[
        "Bairgania"
    ],
    "name:spa_x_preferred":[
        "Bairgania"
    ],
    "name:swe_x_preferred":[
        "Bair\u0101gnia"
    ],
    "name:vie_x_preferred":[
        "Bairgania"
    ],
    "name:zho_x_preferred":[
        "\u62dc\u5c14\u52a0\u5c3c\u4e9a"
    ],
    "qs:name":"Baigni",
    "qs:name_adm0":"India",
    "qs:name_adm1":"Bihar",
    "qs:photos_9r":0,
    "qs:photos_sr":0,
    "qs:placetype":"Town",
    "qs:pop_sr":"7",
    "wof:name":"Baigni",
    "wof:placetype":"locality",
    "wof:population":37465
},
  "geometry": {"coordinates":[85.27323,26.74062],"type":"Point"}
}