{
  "type": "Feature",
  "properties": {
    "iso:country":"IN",
    "ks:ks_name":"Kharkatwa",
    "ks:ks_type":"VILLAGE",
    "name:eng_x_preferred":[
        "Kharkatwa"
    ],
    "wof:name":"Kharkatwa",
    "wof:placetype":"locality"
},
  "geometry": {"coordinates":[83.29535199999999,26.776882],"type":"Point"}
}