{
  "type": "Feature",
  "properties": {
    "gn:admin1_code":"2.0",
    "gn:admin2_code":"554.0",
    "gn:asciiname":"Chinnabandapalli",
    "gn:country_code":"IN",
    "gn:dem":326,
    "gn:feature_class":"P",
    "gn:feature_code":"PPL",
    "gn:name":"Chinnabandapalli",
    "gn:population":0,
    "gn:timezone":"Asia/Kolkata",
    "iso:country":"IN",
    "wof:name":"Chinnabandapalli",
    "wof:placetype":"neighbourhood"
},
  "geometry": {"coordinates":[79.10236999999999,13.30426],"type":"Point"}
}