{
  "type": "Feature",
  "properties": {
    "iso:country":"IN",
    "ks:ks_name":"Trilochanpur",
    "ks:ks_pop":408,
    "ks:ks_type":"VILLAGE",
    "ks:ks_uagg_main":0,
    "name:eng_x_preferred":[
        "Trilochanpur"
    ],
    "wof:name":"Trilochanpur",
    "wof:placetype":"neighbourhood",
    "wof:population":408
},
  "geometry": {"coordinates":[86.844013,21.673958],"type":"Point"}
}