{
  "type": "Feature",
  "properties": {
    "iso:country":"IN",
    "ks:ks_name":"Gamtal",
    "ks:ks_pop":1410,
    "ks:ks_type":"HABITATION",
    "name:eng_x_preferred":[
        "Gamtal"
    ],
    "wof:name":"Gamtal",
    "wof:placetype":"locality",
    "wof:population":1410
},
  "geometry": {"coordinates":[73.5226,22.7126],"type":"Point"}
}