{
  "type": "Feature",
  "properties": {
    "iso:country":"IN",
    "ks:ks_name":"Chamudih",
    "ks:ks_pop":204,
    "ks:ks_type":"VILLAGE",
    "name:eng_x_preferred":[
        "Chamudih"
    ],
    "wof:name":"Chamudih",
    "wof:placetype":"locality",
    "wof:population":204
},
  "geometry": {"coordinates":[87.132606,24.63492],"type":"Point"}
}