{
  "type": "Feature",
  "properties": {
    "iso:country":"IN",
    "ks:ks_name":"Tawadewadi",
    "ks:ks_pop":86,
    "ks:ks_type":"HABITATION",
    "name:eng_x_preferred":[
        "Tawadewadi"
    ],
    "wof:name":"Tawadewadi",
    "wof:placetype":"locality",
    "wof:population":86
},
  "geometry": {"coordinates":[73.760881,16.660494],"type":"Point"}
}