{
  "type": "Feature",
  "properties": {
    "gn:admin1_code":"37",
    "gn:admin2_code":"409.0",
    "gn:asciiname":"Rakhi",
    "gn:country_code":"IN",
    "gn:dem":289,
    "gn:feature_class":"P",
    "gn:feature_code":"PPL",
    "gn:name":"R\u0101khi",
    "gn:population":0,
    "gn:timezone":"Asia/Kolkata",
    "iso:country":"IN",
    "name:ben_x_preferred":[
        "\u09b0\u09be\u0996\u09c0"
    ],
    "name:hin_x_preferred":[
        "\u0930\u093e\u0916\u0940"
    ],
    "name:mar_x_preferred":[
        "\u0930\u093e\u0916\u0940"
    ],
    "wof:name":"Rakhi",
    "wof:placetype":"locality"
},
  "geometry": {"coordinates":[81.34359000000001,21.58136],"type":"Point"}
}