{
  "type": "Feature",
  "properties": {
    "gn:admin1_code":"36",
    "gn:admin2_code":"179.0",
    "gn:asciiname":"Purabgaon",
    "gn:country_code":"IN",
    "gn:dem":111,
    "gn:feature_class":"P",
    "gn:feature_code":"PPL",
    "gn:name":"Purabg\u0101on",
    "gn:population":0,
    "gn:timezone":"Asia/Kolkata",
    "iso:country":"IN",
    "ks:ks_name":"Purab Gaon",
    "ks:ks_pop":697,
    "ks:ks_type":"HABITATION",
    "name:eng_x_preferred":[
        "Purab Gaon"
    ],
    "name:eng_x_variant":[
        "Purabgaon"
    ],
    "wof:name":"Purab Gaon",
    "wof:placetype":"locality",
    "wof:population":697
},
  "geometry": {"coordinates":[81.72108299999999,26.480719],"type":"Point"}
}