{
  "type": "Feature",
  "properties": {
    "iso:country":"IN",
    "ks:ks_name":"Bhutel",
    "ks:ks_pop":218,
    "ks:ks_type":"VILLAGE",
    "name:eng_x_preferred":[
        "Bhutel"
    ],
    "wof:name":"Bhutel",
    "wof:placetype":"locality",
    "wof:population":218
},
  "geometry": {"coordinates":[84.42118499999999,21.43732],"type":"Point"}
}