{
  "type": "Feature",
  "properties": {
    "gn:admin1_code":"39.0",
    "gn:admin2_code":"60.0",
    "gn:asciiname":"Koti",
    "gn:country_code":"IN",
    "gn:dem":1282,
    "gn:feature_class":"P",
    "gn:feature_code":"PPL",
    "gn:name":"Koti",
    "gn:population":0,
    "gn:timezone":"Asia/Kolkata",
    "iso:country":"IN",
    "wof:name":"Koti",
    "wof:placetype":"locality"
},
  "geometry": {"coordinates":[77.84987,30.64537],"type":"Point"}
}