{
  "type": "Feature",
  "properties": {
    "iso:country":"IN",
    "ks:ks_alt_nam":"Mysore patta",
    "ks:ks_name":"Mysore Patta",
    "ks:ks_pop":806,
    "ks:ks_type":"HABITATION",
    "name:eng_x_preferred":[
        "Mysore Patta"
    ],
    "wof:name":"Mysore Patta",
    "wof:placetype":"locality",
    "wof:population":806
},
  "geometry": {"coordinates":[76.059275,11.304897],"type":"Point"}
}