{
  "type": "Feature",
  "properties": {
    "iso:country":"IN",
    "ks:ks_name":"Hukani",
    "ks:ks_pop":414,
    "ks:ks_type":"HABITATION",
    "name:eng_x_preferred":[
        "Hukani"
    ],
    "wof:name":"Hukani",
    "wof:placetype":"locality",
    "wof:population":414
},
  "geometry": {"coordinates":[95.195199,27.299386],"type":"Point"}
}