{
  "type": "Feature",
  "properties": {
    "iso:country":"IN",
    "ks:ks_name":"Kesrisingh Nagar",
    "ks:ks_pop":84,
    "ks:ks_type":"HABITATION",
    "name:eng_x_preferred":[
        "Kesrisingh Nagar"
    ],
    "wof:name":"Kesrisingh Nagar",
    "wof:placetype":"locality",
    "wof:population":84
},
  "geometry": {"coordinates":[71.117769,27.280853],"type":"Point"}
}