{
  "type": "Feature",
  "properties": {
    "gn:admin1_code":"11",
    "gn:admin2_code":"25.0",
    "gn:asciiname":"Bhujund",
    "gn:country_code":"IN",
    "gn:dem":2931,
    "gn:feature_class":"P",
    "gn:feature_code":"PPL",
    "gn:name":"Bhuj\u016bnd",
    "gn:population":0,
    "gn:timezone":"Asia/Kolkata",
    "iso:country":"IN",
    "wof:name":"Bhujund",
    "wof:placetype":"locality"
},
  "geometry": {"coordinates":[76.43843000000003,32.76498],"type":"Point"}
}