{
  "type": "Feature",
  "properties": {
    "iso:country":"IN",
    "ks:ks_alt_nam":"Kalakulam jn",
    "ks:ks_name":"Kalakulam Jn",
    "ks:ks_pop":318,
    "ks:ks_type":"HABITATION",
    "name:eng_x_preferred":[
        "Kalakulam Jn"
    ],
    "wof:name":"Kalakulam Jn",
    "wof:placetype":"locality",
    "wof:population":318
},
  "geometry": {"coordinates":[76.34585,11.33046],"type":"Point"}
}