{
  "type": "Feature",
  "properties": {
    "iso:country":"IN",
    "ks:ks_name":"Lakhni",
    "ks:ks_pop":515,
    "ks:ks_type":"VILLAGE",
    "name:eng_x_preferred":[
        "Lakhni"
    ],
    "wof:name":"Lakhni",
    "wof:placetype":"locality",
    "wof:population":515
},
  "geometry": {"coordinates":[71.94765,25.157439],"type":"Point"}
}