{
  "type": "Feature",
  "properties": {
    "iso:country":"IN",
    "ks:ks_name":"Kubji Bedo",
    "ks:ks_pop":67,
    "ks:ks_type":"VILLAGE",
    "name:eng_x_preferred":[
        "Kubji Bedo"
    ],
    "wof:name":"Kubji Bedo",
    "wof:placetype":"locality",
    "wof:population":67
},
  "geometry": {"coordinates":[87.46225800000001,24.827174],"type":"Point"}
}