{
  "type": "Feature",
  "properties": {
    "gn:gn_country":"IN",
    "gn:gn_fcode":"PPL",
    "gn:gn_pop":21207,
    "gn:population":21207,
    "iso:country":"IN",
    "name:ben_x_preferred":[
        "\u09a7\u09b0\u09ae\u09aa\u09c1\u09b0"
    ],
    "name:cat_x_preferred":[
        "Dharampur"
    ],
    "name:deu_x_preferred":[
        "Dharampur"
    ],
    "name:eng_x_preferred":[
        "Dharampur"
    ],
    "name:fra_x_preferred":[
        "Dharampur"
    ],
    "name:guj_x_preferred":[
        "\u0aa7\u0ab0\u0aae\u0aaa\u0ac1\u0ab0"
    ],
    "name:ita_x_preferred":[
        "Dharampur"
    ],
    "name:jpn_x_preferred":[
        "\u30c0\u30fc\u30e9\u30e0\u30d7\u30fc\u30eb"
    ],
    "name:kan_x_preferred":[
        "\u0ca7\u0cb0\u0c82\u0caa\u0cc1\u0cb0\u0ccd"
    ],
    "name:kor_x_preferred":[
        "\ub2e4\ub78c\ud478\ub974"
    ],
    "name:msa_x_preferred":[
        "Dharampur"
    ],
    "name:new_x_preferred":[
        "\u0927\u0930\u094d\u092e\u092a\u0941\u0930 \u0968"
    ],
    "name:nld_x_preferred":[
        "Dharampur"
    ],
    "name:pam_x_preferred":[
        "Dharampur"
    ],
    "name:pol_x_preferred":[
        "Dharampur"
    ],
    "name:por_x_preferred":[
        "Dharampur"
    ],
    "name:rus_x_preferred":[
        "\u0414\u0445\u0430\u0440\u0430\u043c\u043f\u0443\u0440"
    ],
    "name:spa_x_preferred":[
        "Dharampur"
    ],
    "name:swe_x_preferred":[
        "Dharampur"
    ],
    "name:tam_x_preferred":[
        "\u0ba4\u0bb0\u0bae\u0bcd\u0baa\u0bc2\u0bb0\u0bcd"
    ],
    "name:tel_x_preferred":[
        "\u0c27\u0c30\u0c02\u0c2a\u0c42\u0c30\u0c4d"
    ],
    "name:unk_x_variant":[
        "Dharampore"
    ],
    "name:urd_x_preferred":[
        "\u062f\u06be\u0631\u0645 \u067e\u0648\u0631"
    ],
    "name:vie_x_preferred":[
        "Dharampur"
    ],
    "name:zho_x_preferred":[
        "\u8fbe\u62c9\u59c6\u666e\u5c14"
    ],
    "qs_pg:aaroncc":"IN",
    "qs_pg:gn_country":"IN",
    "qs_pg:gn_fcode":"PPL",
    "qs_pg:gn_pop":21207,
    "qs_pg:name":"Dharampor",
    "qs_pg:name_adm0":"India",
    "qs_pg:name_adm1":"Gujarat",
    "qs_pg:photos_9r":0,
    "qs_pg:photos_sr":0,
    "qs_pg:pop_sr":7,
    "qs_pg:qs_pg_placetype":"locality",
    "qs_pg:qs_pg_placetype_gp":"Town",
    "qs_pg:woe_adm0":23424848,
    "woe:adm0_id":23424848,
    "woe:name_adm0":"India",
    "woe:name_adm1":"Gujarat",
    "woe:placetype":"Town",
    "wof:name":"Dharampor",
    "wof:placetype":"locality",
    "wof:population":21207
},
  "geometry": {"coordinates":[73.17368,20.53693],"type":"Point"}
}