{
  "type": "Feature",
  "properties": {
    "gn:admin1_code":"7.0",
    "gn:admin2_code":"097",
    "gn:asciiname":"Surkhpur",
    "gn:country_code":"IN",
    "gn:dem":216,
    "gn:feature_class":"P",
    "gn:feature_code":"PPL",
    "gn:name":"Surkhpur",
    "gn:population":0,
    "gn:timezone":"Asia/Kolkata",
    "iso:country":"IN",
    "wof:name":"Surkhpur",
    "wof:placetype":"neighbourhood"
},
  "geometry": {"coordinates":[76.94268000000002,28.62569],"type":"Point"}
}