{
  "type": "Feature",
  "properties": {
    "iso:country":"IN",
    "ks:ks_name":"Gundwadi",
    "ks:ks_pop":311,
    "ks:ks_type":"HABITATION",
    "name:eng_x_preferred":[
        "Gundwadi"
    ],
    "wof:name":"Gundwadi",
    "wof:placetype":"locality",
    "wof:population":311
},
  "geometry": {"coordinates":[74.87564,18.551725],"type":"Point"}
}