{
  "type": "Feature",
  "properties": {
    "iso:country":"IN",
    "ks:ks_alt_nam":"Nedip\u0101nga",
    "ks:ks_name":"Nedipanga",
    "ks:ks_pop":330,
    "ks:ks_type":"VILLAGE",
    "name:eng_x_preferred":[
        "Nedipanga"
    ],
    "name:eng_x_variant":[
        "Nedip\u0101nga"
    ],
    "wof:name":"Nedipanga",
    "wof:placetype":"locality",
    "wof:population":330
},
  "geometry": {"coordinates":[84.09090399999999,20.453599],"type":"Point"}
}