{
  "type": "Feature",
  "properties": {
    "gn:admin1_code":"34.0",
    "gn:asciiname":"Khandhar",
    "gn:country_code":"IN",
    "gn:dem":79,
    "gn:feature_class":"P",
    "gn:feature_code":"PPL",
    "gn:name":"Kh\u0101ndh\u0101r",
    "gn:population":0,
    "gn:timezone":"Asia/Kolkata",
    "iso:country":"IN",
    "name:deu_x_preferred":[
        "Khandhar"
    ],
    "name:fas_x_preferred":[
        "\u0648\u06cc\u0631\u0627\u0646\u0647"
    ],
    "name:ind_x_preferred":[
        "Khandhar"
    ],
    "name:new_x_preferred":[
        "\u0915\u0902\u0927\u093e\u0930"
    ],
    "name:pan_x_preferred":[
        "\u0a16\u0a70\u0a21\u0a30"
    ],
    "name:tel_x_preferred":[
        "\u0c16\u0c3e\u0c02\u0c27\u0c3e\u0c30\u0c4d"
    ],
    "wof:name":"Khandhar",
    "wof:placetype":"locality"
},
  "geometry": {"coordinates":[87.46918000000002,25.19457],"type":"Point"}
}