{
  "type": "Feature",
  "properties": {
    "gn:admin1_code":"10.0",
    "gn:admin2_code":"075",
    "gn:asciiname":"Azizullahpur",
    "gn:country_code":"IN",
    "gn:dem":232,
    "gn:feature_class":"P",
    "gn:feature_code":"PPL",
    "gn:name":"Az\u012bzull\u0101hpur",
    "gn:population":0,
    "gn:timezone":"Asia/Kolkata",
    "iso:country":"IN",
    "ks:ks_name":"Azizullapur",
    "ks:ks_pop":1190,
    "ks:ks_type":"VILLAGE",
    "ks:ks_uagg_main":0,
    "name:eng_x_preferred":[
        "Azizullapur"
    ],
    "name:und_x_variant":[
        "Az\u012bzull\u0101hpur",
        "Azizullahpur"
    ],
    "wof:name":"Azizullapur",
    "wof:placetype":"locality",
    "wof:population":1190
},
  "geometry": {"coordinates":[76.99157599999999,29.436897],"type":"Point"}
}