{
  "type": "Feature",
  "properties": {
    "gn:admin1_code":"19.0",
    "gn:admin2_code":"566.0",
    "gn:asciiname":"Adavigollarahalli",
    "gn:country_code":"IN",
    "gn:dem":705,
    "gn:feature_class":"P",
    "gn:feature_code":"PPL",
    "gn:name":"Adavigollarahalli",
    "gn:population":0,
    "gn:timezone":"Asia/Kolkata",
    "iso:country":"IN",
    "name:fas_x_preferred":[
        "\u0627\u062f\u0627\u0648\u06cc\u06af\u0644\u0627\u0631\u0627\u0647\u0627\u0648\u06cc"
    ],
    "name:vie_x_preferred":[
        "Adavigollarahalli"
    ],
    "wof:name":"Adavigollarahalli",
    "wof:placetype":"locality"
},
  "geometry": {"coordinates":[76.26791,14.36161],"type":"Point"}
}