{
  "type": "Feature",
  "properties": {
    "iso:country":"IN",
    "ks:ks_name":"Brahmanidarh",
    "ks:ks_pop":318,
    "ks:ks_type":"VILLAGE",
    "name:eng_x_preferred":[
        "Brahmanidarh"
    ],
    "wof:name":"Brahmanidarh",
    "wof:placetype":"locality",
    "wof:population":318
},
  "geometry": {"coordinates":[84.98851500000001,21.701726],"type":"Point"}
}