{
  "type": "Feature",
  "properties": {
    "gn:admin1_code":"12.0",
    "gn:admin2_code":"001",
    "gn:asciiname":"Bari Bekh",
    "gn:country_code":"IN",
    "gn:dem":2443,
    "gn:feature_class":"P",
    "gn:feature_code":"PPL",
    "gn:name":"Bari Bekh",
    "gn:population":0,
    "gn:timezone":"Asia/Kolkata",
    "iso:country":"IN",
    "name:und_x_variant":[
        "Bari Baihk"
    ],
    "wof:name":"Bari Bekh",
    "wof:placetype":"locality"
},
  "geometry": {"coordinates":[73.99206,34.40405],"type":"Point"}
}