{
  "type": "Feature",
  "properties": {
    "iso:country":"IN",
    "ks:ks_name":"Kamlapadar",
    "ks:ks_pop":55,
    "ks:ks_type":"HABITATION",
    "name:eng_x_preferred":[
        "Kamlapadar"
    ],
    "wof:name":"Kamlapadar",
    "wof:placetype":"locality",
    "wof:population":55
},
  "geometry": {"coordinates":[81.24217899999999,19.001599],"type":"Point"}
}