{
  "type": "Feature",
  "properties": {
    "iso:country":"IN",
    "ks:ks_name":"Katikandar",
    "ks:ks_pop":448,
    "ks:ks_type":"HABITATION",
    "name:eng_x_preferred":[
        "Katikandar"
    ],
    "wof:name":"Katikandar",
    "wof:placetype":"locality",
    "wof:population":448
},
  "geometry": {"coordinates":[88.359674,25.266009],"type":"Point"}
}