{
  "type": "Feature",
  "properties": {
    "iso:country":"IN",
    "ks:ks_name":"Sail",
    "ks:ks_pop":526,
    "ks:ks_type":"VILLAGE",
    "name:eng_x_preferred":[
        "Sail"
    ],
    "wof:name":"Sail",
    "wof:placetype":"locality",
    "wof:population":526
},
  "geometry": {"coordinates":[80.236321,29.459386],"type":"Point"}
}