{
  "type": "Feature",
  "properties": {
    "iso:country":"IN",
    "ks:ks_alt_nam":"Bardad  pada",
    "ks:ks_name":"Bardad Pada",
    "ks:ks_pop":270,
    "ks:ks_type":"HABITATION",
    "ks:ks_uagg_main":0,
    "name:eng_x_preferred":[
        "Bardad Pada"
    ],
    "name:eng_x_variant":[
        "Bardad  pada"
    ],
    "wof:name":"Bardad Pada",
    "wof:placetype":"neighbourhood",
    "wof:population":270
},
  "geometry": {"coordinates":[73.213888,20.341038],"type":"Point"}
}