{
  "type": "Feature",
  "properties": {
    "gn:admin1_code":"34.0",
    "gn:admin2_code":"220.0",
    "gn:asciiname":"Harpur",
    "gn:country_code":"IN",
    "gn:dem":52,
    "gn:feature_class":"P",
    "gn:feature_code":"PPL",
    "gn:name":"Harpur",
    "gn:population":0,
    "gn:timezone":"Asia/Kolkata",
    "iso:country":"IN",
    "name:eng_x_preferred":[
        "Harpur"
    ],
    "name:new_x_preferred":[
        "\u0939\u0930\u094d\u092a\u0941\u0930"
    ],
    "wof:name":"Harpur",
    "wof:placetype":"locality"
},
  "geometry": {"coordinates":[85.53768000000002,25.64056],"type":"Point"}
}