{
  "type": "Feature",
  "properties": {
    "gn:admin1_code":"28.0",
    "gn:admin2_code":"337.0",
    "gn:asciiname":"Dakshineswar",
    "gn:country_code":"IN",
    "gn:dem":5,
    "gn:feature_class":"P",
    "gn:feature_code":"PPL",
    "gn:name":"Dakshineswar",
    "gn:population":0,
    "gn:timezone":"Asia/Kolkata",
    "iso:country":"IN",
    "name:ben_x_preferred":[
        "\u09a6\u0995\u09cd\u09b7\u09bf\u09a8\u09c7\u09b6\u09cd\u09ac\u09b0)"
    ],
    "wof:name":"Dakshineswar",
    "wof:placetype":"locality"
},
  "geometry": {"coordinates":[88.3672,22.65567],"type":"Point"}
}