{
  "type": "Feature",
  "properties": {
    "iso:country":"IN",
    "ks:ks_name":"Dawgoda",
    "ks:ks_pop":50,
    "ks:ks_type":"VILLAGE",
    "name:eng_x_preferred":[
        "Dawgoda"
    ],
    "wof:name":"Dawgoda",
    "wof:placetype":"locality",
    "wof:population":50
},
  "geometry": {"coordinates":[87.453684,24.846913],"type":"Point"}
}