{
  "type": "Feature",
  "properties": {
    "gn:admin1_code":"19.0",
    "gn:admin2_code":"569.0",
    "gn:asciiname":"Kelasunka",
    "gn:country_code":"IN",
    "gn:dem":120,
    "gn:feature_class":"P",
    "gn:feature_code":"PPL",
    "gn:name":"Kelasunka",
    "gn:population":0,
    "gn:timezone":"Asia/Kolkata",
    "iso:country":"IN",
    "ks:ks_name":"Kelasanka",
    "ks:ks_pop":240,
    "ks:ks_type":"HABITATION",
    "name:eng_x_preferred":[
        "Kelasanka"
    ],
    "name:eng_x_variant":[
        "Kelasunka"
    ],
    "wof:name":"Kelasanka",
    "wof:placetype":"locality",
    "wof:population":240
},
  "geometry": {"coordinates":[75.018693,13.610823],"type":"Point"}
}