{
  "type": "Feature",
  "properties": {
    "iso:country":"IN",
    "ks:ks_name":"Padani",
    "ks:ks_pop":225,
    "ks:ks_type":"HABITATION",
    "name:eng_x_preferred":[
        "Padani"
    ],
    "wof:name":"Padani",
    "wof:placetype":"locality",
    "wof:population":225
},
  "geometry": {"coordinates":[72.69001400000001,24.303357],"type":"Point"}
}