{
  "type": "Feature",
  "properties": {
    "iso:country":"IN",
    "ks:ks_name":"Vadakhera",
    "ks:ks_pop":33,
    "ks:ks_type":"VILLAGE",
    "name:eng_x_preferred":[
        "Vadakhera"
    ],
    "wof:name":"Vadakhera",
    "wof:placetype":"locality",
    "wof:population":33
},
  "geometry": {"coordinates":[72.83946400000001,24.968833],"type":"Point"}
}