{
  "type": "Feature",
  "properties": {
    "gn:admin1_code":"35",
    "gn:admin2_code":"454.0",
    "gn:asciiname":"Gorakhera",
    "gn:country_code":"IN",
    "gn:dem":414,
    "gn:feature_class":"P",
    "gn:feature_code":"PPL",
    "gn:name":"Gor\u0101khera",
    "gn:population":0,
    "gn:timezone":"Asia/Kolkata",
    "iso:country":"IN",
    "wof:name":"Gorakhera",
    "wof:placetype":"locality"
},
  "geometry": {"coordinates":[79.98358,22.9357],"type":"Point"}
}