{
  "type": "Feature",
  "properties": {
    "gn:admin1_code":"11",
    "gn:admin2_code":"23.0",
    "gn:asciiname":"Drammani",
    "gn:country_code":"IN",
    "gn:dem":948,
    "gn:feature_class":"P",
    "gn:feature_code":"PPL",
    "gn:name":"Drammani",
    "gn:population":0,
    "gn:timezone":"Asia/Kolkata",
    "iso:country":"IN",
    "wof:name":"Drammani",
    "wof:placetype":"locality"
},
  "geometry": {"coordinates":[76.00091999999999,32.39419],"type":"Point"}
}