{
  "type": "Feature",
  "properties": {
    "iso:country":"IN",
    "ks:ks_alt_nam":"PURE JALIM",
    "ks:ks_name":"Pure Jalim",
    "ks:ks_pop":368,
    "ks:ks_type":"HABITATION",
    "name:eng_x_preferred":[
        "Pure Jalim"
    ],
    "wof:name":"Pure Jalim",
    "wof:placetype":"locality",
    "wof:population":368
},
  "geometry": {"coordinates":[81.47009799999999,26.298151],"type":"Point"}
}