{
  "type": "Feature",
  "properties": {
    "iso:country":"IN",
    "ks:ks_name":"Kuriya Temple",
    "ks:ks_pop":300,
    "ks:ks_type":"HABITATION",
    "name:eng_x_preferred":[
        "Kuriya Temple"
    ],
    "wof:name":"Kuriya Temple",
    "wof:placetype":"locality",
    "wof:population":300
},
  "geometry": {"coordinates":[75.319985,12.882902],"type":"Point"}
}