{
  "type": "Feature",
  "properties": {
    "gn:admin1_code":"11",
    "gn:admin2_code":"23.0",
    "gn:asciiname":"Gwar",
    "gn:country_code":"IN",
    "gn:dem":2790,
    "gn:feature_class":"P",
    "gn:feature_code":"PPL",
    "gn:name":"Gw\u0101r",
    "gn:population":0,
    "gn:timezone":"Asia/Kolkata",
    "iso:country":"IN",
    "wof:name":"Gwar",
    "wof:placetype":"locality"
},
  "geometry": {"coordinates":[76.65186,32.29761],"type":"Point"}
}