{
  "type": "Feature",
  "properties": {
    "iso:country":"IN",
    "ks:ks_name":"Pokalewadi",
    "ks:ks_pop":287,
    "ks:ks_type":"HABITATION",
    "name:eng_x_preferred":[
        "Pokalewadi"
    ],
    "wof:name":"Pokalewadi",
    "wof:placetype":"locality",
    "wof:population":287
},
  "geometry": {"coordinates":[73.39359899999999,16.663338],"type":"Point"}
}