{
  "type": "Feature",
  "properties": {
    "gn:admin1_code":"12",
    "gn:admin2_code":"20.0",
    "gn:asciiname":"Kalaban",
    "gn:country_code":"IN",
    "gn:dem":2822,
    "gn:feature_class":"P",
    "gn:feature_code":"PPL",
    "gn:name":"Kalaban",
    "gn:population":0,
    "gn:timezone":"Asia/Kolkata",
    "iso:country":"IN",
    "wof:name":"Kalaban",
    "wof:placetype":"locality"
},
  "geometry": {"coordinates":[74.96070999999998,33.41781],"type":"Point"}
}