{
  "type": "Feature",
  "properties": {
    "iso:country":"IN",
    "ks:ks_name":"Ramjiguda",
    "ks:ks_pop":94,
    "ks:ks_type":"HABITATION",
    "name:eng_x_preferred":[
        "Ramjiguda"
    ],
    "wof:name":"Ramjiguda",
    "wof:placetype":"locality",
    "wof:population":94
},
  "geometry": {"coordinates":[79.253107,19.085749],"type":"Point"}
}