{
  "type": "Feature",
  "properties": {
    "gn:admin1_code":"28.0",
    "gn:admin2_code":"343",
    "gn:asciiname":"Iswaripur",
    "gn:country_code":"IN",
    "gn:dem":10,
    "gn:feature_class":"P",
    "gn:feature_code":"PPL",
    "gn:name":"Iswaripur",
    "gn:population":0,
    "gn:timezone":"Asia/Kolkata",
    "iso:country":"IN",
    "ks:ks_name":"Ishwaripur",
    "ks:ks_pop":3307,
    "ks:ks_type":"VILLAGE",
    "name:eng_x_preferred":[
        "Ishwaripur"
    ],
    "name:eng_x_variant":[
        "Iswaripur"
    ],
    "wof:name":"Ishwaripur",
    "wof:placetype":"locality",
    "wof:population":3307
},
  "geometry": {"coordinates":[88.130735,22.301909],"type":"Point"}
}