{
  "type": "Feature",
  "properties": {
    "gn:admin1_code":"24.0",
    "gn:admin2_code":"102",
    "gn:asciiname":"Bhavandesar",
    "gn:country_code":"IN",
    "gn:dem":313,
    "gn:feature_class":"P",
    "gn:feature_code":"PPL",
    "gn:name":"Bh\u0101vandesar",
    "gn:population":0,
    "gn:timezone":"Asia/Kolkata",
    "iso:country":"IN",
    "name:und_x_variant":[
        "Bh\u0101vandesar",
        "Bhaundesar"
    ],
    "wof:name":"Bhavandesar",
    "wof:placetype":"locality"
},
  "geometry": {"coordinates":[74.51990000000001,28.01999],"type":"Point"}
}