{
  "type": "Feature",
  "properties": {
    "gn:admin1_code":"23",
    "gn:admin2_code":"37.0",
    "gn:asciiname":"Khurshedpur",
    "gn:country_code":"IN",
    "gn:dem":233,
    "gn:feature_class":"P",
    "gn:feature_code":"PPL",
    "gn:name":"Khurshedpur",
    "gn:population":0,
    "gn:timezone":"Asia/Kolkata",
    "iso:country":"IN",
    "ks:ks_name":"Khurshedpur",
    "ks:ks_pop":962,
    "ks:ks_type":"VILLAGE",
    "ks:ks_uagg_main":0,
    "name:eng_x_preferred":[
        "Khurshedpur"
    ],
    "wof:name":"Khurshedpur",
    "wof:placetype":"neighbourhood",
    "wof:population":962
},
  "geometry": {"coordinates":[75.443096,31.103187],"type":"Point"}
}