{
  "type": "Feature",
  "properties": {
    "iso:country":"IN",
    "ks:ks_name":"Dongarshetpada",
    "ks:ks_pop":135,
    "ks:ks_type":"HABITATION",
    "name:eng_x_preferred":[
        "Dongarshetpada"
    ],
    "wof:name":"Dongarshetpada",
    "wof:placetype":"locality",
    "wof:population":135
},
  "geometry": {"coordinates":[73.188154,19.588321],"type":"Point"}
}