{
  "type": "Feature",
  "properties": {
    "iso:country":"IN",
    "ks:ks_name":"Patrapur",
    "ks:ks_pop":505,
    "ks:ks_type":"VILLAGE",
    "name:eng_x_preferred":[
        "Patrapur"
    ],
    "wof:name":"Patrapur",
    "wof:placetype":"locality",
    "wof:population":505
},
  "geometry": {"coordinates":[85.042478,19.563379],"type":"Point"}
}