{
  "type": "Feature",
  "properties": {
    "iso:country":"IN",
    "ks:ks_name":"Ghamner",
    "ks:ks_pop":149,
    "ks:ks_type":"VILLAGE",
    "name:eng_x_preferred":[
        "Ghamner"
    ],
    "wof:name":"Ghamner",
    "wof:placetype":"locality",
    "wof:population":149
},
  "geometry": {"coordinates":[72.384619,27.001961],"type":"Point"}
}