{
  "type": "Feature",
  "properties": {
    "iso:country":"IN",
    "ks:ks_name":"Dhdadpada",
    "ks:ks_pop":223,
    "ks:ks_type":"HABITATION",
    "name:eng_x_preferred":[
        "Dhdadpada"
    ],
    "wof:name":"Dhdadpada",
    "wof:placetype":"locality",
    "wof:population":223
},
  "geometry": {"coordinates":[72.755129,19.997879],"type":"Point"}
}