{
  "type": "Feature",
  "properties": {
    "iso:country":"IN",
    "ks:ks_name":"Patipada",
    "ks:ks_pop":0,
    "ks:ks_type":"VILLAGE",
    "name:eng_x_preferred":[
        "Patipada"
    ],
    "wof:name":"Patipada",
    "wof:placetype":"locality",
    "wof:population":0
},
  "geometry": {"coordinates":[73.99368,21.492765],"type":"Point"}
}