{
  "type": "Feature",
  "properties": {
    "gn:admin1_code":"11",
    "gn:admin2_code":"23.0",
    "gn:asciiname":"Drodu Adwar",
    "gn:country_code":"IN",
    "gn:dem":2506,
    "gn:feature_class":"P",
    "gn:feature_code":"PPL",
    "gn:name":"Drodu Adw\u0101r",
    "gn:population":0,
    "gn:timezone":"Asia/Kolkata",
    "iso:country":"IN",
    "wof:name":"Drodu Adwar",
    "wof:placetype":"locality"
},
  "geometry": {"coordinates":[76.01574000000002,32.77784],"type":"Point"}
}