{
  "type": "Feature",
  "properties": {
    "iso:country":"IN",
    "ks:ks_name":"Chatukupadu",
    "ks:ks_pop":1555,
    "ks:ks_type":"VILLAGE",
    "name:eng_x_preferred":[
        "Chatukupadu"
    ],
    "wof:name":"Chatukupadu",
    "wof:placetype":"locality",
    "wof:population":1555
},
  "geometry": {"coordinates":[79.835517,15.32612],"type":"Point"}
}