{
  "type": "Feature",
  "properties": {
    "iso:country":"IN",
    "ks:ks_name":"Korkoti",
    "ks:ks_pop":605,
    "ks:ks_type":"HABITATION",
    "name:eng_x_preferred":[
        "Korkoti"
    ],
    "wof:name":"Korkoti",
    "wof:placetype":"locality",
    "wof:population":605
},
  "geometry": {"coordinates":[81.466714,19.103261],"type":"Point"}
}