{
  "type": "Feature",
  "properties": {
    "iso:country":"IN",
    "ks:ks_alt_nam":"NAIKWASTI",
    "ks:ks_name":"Naikwasti",
    "ks:ks_pop":125,
    "ks:ks_type":"HABITATION",
    "name:eng_x_preferred":[
        "Naikwasti"
    ],
    "wof:name":"Naikwasti",
    "wof:placetype":"locality",
    "wof:population":125
},
  "geometry": {"coordinates":[74.720189,17.158372],"type":"Point"}
}