{
  "type": "Feature",
  "properties": {
    "iso:country":"IN",
    "ks:ks_name":"College Tilla West",
    "ks:ks_pop":550,
    "ks:ks_type":"HABITATION",
    "ks:ks_uagg_main":0,
    "name:eng_x_preferred":[
        "College Tilla West"
    ],
    "wof:name":"College Tilla West",
    "wof:placetype":"neighbourhood",
    "wof:population":550
},
  "geometry": {"coordinates":[91.468771,23.551023],"type":"Point"}
}