{
  "type": "Feature",
  "properties": {
    "iso:country":"IN",
    "ks:ks_name":"Choki",
    "ks:ks_pop":75,
    "ks:ks_type":"HABITATION",
    "name:eng_x_preferred":[
        "Choki"
    ],
    "wof:name":"Choki",
    "wof:placetype":"locality",
    "wof:population":75
},
  "geometry": {"coordinates":[74.40020800000001,23.123047],"type":"Point"}
}