{
  "type": "Feature",
  "properties": {
    "iso:country":"IN",
    "ks:ks_name":"Maratikoppa",
    "ks:ks_pop":92,
    "ks:ks_type":"HABITATION",
    "name:eng_x_preferred":[
        "Maratikoppa"
    ],
    "wof:name":"Maratikoppa",
    "wof:placetype":"locality",
    "wof:population":92
},
  "geometry": {"coordinates":[74.48708600000001,14.517264],"type":"Point"}
}