{
  "type": "Feature",
  "properties": {
    "gn:admin1_code":"35",
    "gn:admin2_code":"418.0",
    "gn:asciiname":"Nawalpura",
    "gn:country_code":"IN",
    "gn:dem":266,
    "gn:feature_class":"P",
    "gn:feature_code":"PPL",
    "gn:name":"Nawalpura",
    "gn:population":0,
    "gn:timezone":"Asia/Kolkata",
    "iso:country":"IN",
    "ks:ks_name":"Nabalpura",
    "ks:ks_pop":90,
    "ks:ks_type":"VILLAGE",
    "name:eng_x_preferred":[
        "Nabalpura"
    ],
    "name:eng_x_variant":[
        "Nawalpura"
    ],
    "wof:name":"Nabalpura",
    "wof:placetype":"locality",
    "wof:population":90
},
  "geometry": {"coordinates":[77.223259,25.597848],"type":"Point"}
}