{
  "type": "Feature",
  "properties": {
    "gn:admin1_code":"11.0",
    "gn:admin2_code":"34.0",
    "gn:asciiname":"Baru",
    "gn:country_code":"IN",
    "gn:dem":1435,
    "gn:feature_class":"P",
    "gn:feature_code":"PPL",
    "gn:name":"Baru",
    "gn:population":0,
    "gn:timezone":"Asia/Kolkata",
    "iso:country":"IN",
    "wof:name":"Baru",
    "wof:placetype":"locality"
},
  "geometry": {"coordinates":[78.00281,31.54243],"type":"Point"}
}