{
  "type": "Feature",
  "properties": {
    "iso:country":"IN",
    "ks:ks_name":"Lang Khang No.2",
    "ks:ks_pop":267,
    "ks:ks_type":"VILLAGE",
    "ks:ks_uagg_main":0,
    "name:eng_x_preferred":[
        "Lang Khang No.2"
    ],
    "wof:name":"Lang Khang No.2",
    "wof:placetype":"neighbourhood",
    "wof:population":267
},
  "geometry": {"coordinates":[93.073943,26.464229],"type":"Point"}
}