{
  "type": "Feature",
  "properties": {
    "iso:country":"IN",
    "ks:ks_name":"Kathalkuchi",
    "ks:ks_pop":128,
    "ks:ks_type":"HABITATION",
    "ks:ks_uagg_main":0,
    "name:eng_x_preferred":[
        "Kathalkuchi"
    ],
    "wof:name":"Kathalkuchi",
    "wof:placetype":"neighbourhood",
    "wof:population":128
},
  "geometry": {"coordinates":[91.13588300000001,25.914692],"type":"Point"}
}