{
  "type": "Feature",
  "properties": {
    "gn:admin1_code":"39.0",
    "gn:admin2_code":"57.0",
    "gn:asciiname":"Dunagiri",
    "gn:country_code":"IN",
    "gn:dem":3596,
    "gn:feature_class":"P",
    "gn:feature_code":"PPL",
    "gn:name":"D\u016bn\u0101giri",
    "gn:population":0,
    "gn:timezone":"Asia/Kolkata",
    "iso:country":"IN",
    "name:fin_x_preferred":[
        "Dunagiri"
    ],
    "name:pol_x_preferred":[
        "Dunagiri"
    ],
    "wof:name":"Dunagiri",
    "wof:placetype":"locality"
},
  "geometry": {"coordinates":[79.86999,30.59983],"type":"Point"}
}