{
  "type": "Feature",
  "properties": {
    "iso:country":"IN",
    "ks:ks_name":"Madhariya",
    "ks:ks_pop":205,
    "ks:ks_type":"HABITATION",
    "ks:ks_uagg_main":0,
    "name:eng_x_preferred":[
        "Madhariya"
    ],
    "wof:name":"Madhariya",
    "wof:placetype":"neighbourhood",
    "wof:population":205
},
  "geometry": {"coordinates":[80.74281999999999,27.845697],"type":"Point"}
}