{
  "type": "Feature",
  "properties": {
    "iso:country":"IN",
    "ks:ks_name":"Satibati",
    "ks:ks_pop":828,
    "ks:ks_type":"VILLAGE",
    "ks:ks_uagg_main":0,
    "name:eng_x_preferred":[
        "Satibati"
    ],
    "wof:name":"Satibati",
    "wof:placetype":"neighbourhood",
    "wof:population":828
},
  "geometry": {"coordinates":[86.657449,21.010567],"type":"Point"}
}