{
  "type": "Feature",
  "properties": {
    "gn:admin1_code":"19",
    "gn:admin2_code":"557.0",
    "gn:asciiname":"Hunashihal",
    "gn:country_code":"IN",
    "gn:dem":517,
    "gn:feature_class":"P",
    "gn:feature_code":"PPL",
    "gn:name":"Hunashih\u0101l",
    "gn:population":0,
    "gn:timezone":"Asia/Kolkata",
    "iso:country":"IN",
    "ks:ks_name":"Hunashyal",
    "ks:ks_pop":4026,
    "ks:ks_type":"HABITATION",
    "name:eng_x_preferred":[
        "Hunashyal"
    ],
    "name:eng_x_variant":[
        "Hunashihal"
    ],
    "wof:name":"Hunashyal",
    "wof:placetype":"locality",
    "wof:population":4026
},
  "geometry": {"coordinates":[76.32033800000001,16.702403],"type":"Point"}
}