{
  "type": "Feature",
  "properties": {
    "iso:country":"IN",
    "ks:ks_name":"Menagadu",
    "ks:ks_pop":112,
    "ks:ks_type":"HABITATION",
    "name:eng_x_preferred":[
        "Menagadu"
    ],
    "wof:name":"Menagadu",
    "wof:placetype":"locality",
    "wof:population":112
},
  "geometry": {"coordinates":[79.074485,10.148657],"type":"Point"}
}