{
  "type": "Feature",
  "properties": {
    "iso:country":"IN",
    "ks:ks_name":"Brahmanwadi",
    "ks:ks_pop":17,
    "ks:ks_type":"HABITATION",
    "name:eng_x_preferred":[
        "Brahmanwadi"
    ],
    "wof:name":"Brahmanwadi",
    "wof:placetype":"locality",
    "wof:population":17
},
  "geometry": {"coordinates":[73.119559,17.932967],"type":"Point"}
}