{
  "type": "Feature",
  "properties": {
    "gn:admin1_code":"25",
    "gn:admin2_code":"633.0",
    "gn:asciiname":"Muttur",
    "gn:country_code":"IN",
    "gn:dem":203,
    "gn:feature_class":"P",
    "gn:feature_code":"PPL",
    "gn:name":"Mutt\u016br",
    "gn:population":0,
    "gn:timezone":"Asia/Kolkata",
    "iso:country":"IN",
    "wof:name":"Muttur",
    "wof:placetype":"locality"
},
  "geometry": {"coordinates":[77.7363,11.04637],"type":"Point"}
}