{
  "type": "Feature",
  "properties": {
    "gn:admin1_code":"2.0",
    "gn:asciiname":"Mamidiguda",
    "gn:country_code":"IN",
    "gn:dem":234,
    "gn:feature_class":"P",
    "gn:feature_code":"PPL",
    "gn:name":"M\u0101midiguda",
    "gn:population":0,
    "gn:timezone":"Asia/Kolkata",
    "iso:country":"IN",
    "ks:ks_alt_nam":"M\u0101midiguda",
    "ks:ks_name":"Mamidiguda",
    "ks:ks_pop":65,
    "ks:ks_type":"VILLAGE",
    "name:eng_x_preferred":[
        "Mamidiguda"
    ],
    "name:eng_x_variant":[
        "M\u0101midiguda"
    ],
    "wof:name":"Mamidiguda",
    "wof:placetype":"locality",
    "wof:population":65
},
  "geometry": {"coordinates":[83.46512800000001,19.059225],"type":"Point"}
}