{
  "type": "Feature",
  "properties": {
    "gn:admin1_code":"2.0",
    "gn:asciiname":"Mamidiguda",
    "gn:country_code":"IN",
    "gn:dem":234,
    "gn:feature_class":"P",
    "gn:feature_code":"PPL",
    "gn:name":"M\u0101midiguda",
    "gn:population":0,
    "gn:timezone":"Asia/Kolkata",
    "iso:country":"IN",
    "wof:name":"Mamidiguda",
    "wof:placetype":"locality"
},
  "geometry": {"coordinates":[83.46507,19.05898],"type":"Point"}
}