{
  "type": "Feature",
  "properties": {
    "iso:country":"IN",
    "ks:ks_name":"Padinjattupadam",
    "ks:ks_pop":1400,
    "ks:ks_type":"HABITATION",
    "name:eng_x_preferred":[
        "Padinjattupadam"
    ],
    "wof:name":"Padinjattupadam",
    "wof:placetype":"locality",
    "wof:population":1400
},
  "geometry": {"coordinates":[75.866511,11.060403],"type":"Point"}
}