{
  "type": "Feature",
  "properties": {
    "iso:country":"IN",
    "ks:ks_alt_nam":"PATWA MUTFARKA",
    "ks:ks_name":"Patwa Mutfarka",
    "ks:ks_pop":47,
    "ks:ks_type":"HABITATION",
    "ks:ks_uagg_main":0,
    "name:eng_x_preferred":[
        "Patwa Mutfarka"
    ],
    "wof:name":"Patwa Mutfarka",
    "wof:placetype":"neighbourhood",
    "wof:population":47
},
  "geometry": {"coordinates":[82.248232,25.519477],"type":"Point"}
}