{
  "type": "Feature",
  "properties": {
    "gn:country":"IN",
    "gn:fcode":"PPL",
    "gn:population":0,
    "iso:country":"IN",
    "name:ara_x_preferred":[
        "\u0623\u0643\u0627\u062a\u064a\u062a\u0627\u0631\u0627"
    ],
    "name:ben_bn_x_preferred":[
        "\u0985\u0995\u09be\u099f\u09cd\u09a4\u09c7\u09a4\u09cd\u09a4\u09b0\u09be"
    ],
    "name:ben_in_x_preferred":[
        "\u0985\u0995\u09be\u099f\u09cd\u09a4\u09c7\u09a4\u09cd\u09a4\u09b0\u09be"
    ],
    "name:guj_x_preferred":[
        "\u0a85\u0a95\u0acd\u0aa4\u0ac7\u0aa4\u0acd\u0aa4\u0ab0"
    ],
    "name:hin_x_preferred":[
        "\u0905\u0915\u093e\u0924\u0947\u0924\u0930\u093e"
    ],
    "name:kan_x_preferred":[
        "\u0c85\u0c95\u0c9f\u0ccd\u0c9f\u0cc6\u0c9f\u0ccd\u0c9f\u0cbe\u0cb0\u0cbe"
    ],
    "name:mal_x_preferred":[
        "\u0d05\u0d15\u0d1f\u0d4d\u0d1f\u0d47\u0d1f\u0d4d\u0d1f\u0d31"
    ],
    "name:mar_x_preferred":[
        "\u0905\u0915\u094d\u0915\u091f\u094d\u091f\u0947\u0930\u093e"
    ],
    "name:pan_x_preferred":[
        "\u0a05\u0a15\u0a3e\u0a1f\u0a48\u0a1f\u0a3e\u0a30\u0a3e"
    ],
    "name:tam_x_preferred":[
        "\u0b85\u0b95\u0b9f\u0bcd\u0b9f\u0bc6\u0b9f\u0bcd\u0b9f\u0bb0\u0bbe"
    ],
    "name:tel_x_preferred":[
        "\u0c05\u0c15\u0c3e\u0c1f\u0c4d\u0c1f\u0c46\u0c1f\u0c4d\u0c1f\u0c3e\u0c30\u0c3e"
    ],
    "name:urd_x_preferred":[
        "\u0627\u06a9\u0627\u0679\u06cc\u0679\u0627\u0631\u0627"
    ],
    "qs:name":"Akattettara",
    "qs:name_adm0":"India",
    "qs:name_adm1":"Kerala",
    "qs:photos":19,
    "qs:photos_1k":4,
    "qs:photos_9k":1,
    "qs:photos_9r":1,
    "qs:photos_all":19,
    "qs:photos_sr":1,
    "qs:placetype":"Suburb",
    "qs:pop_sr":"0",
    "wof:name":"Akattettara",
    "wof:placetype":"neighbourhood",
    "wof:population":0
},
  "geometry": {"coordinates":[76.60092,10.834],"type":"Point"}
}