{
  "type": "Feature",
  "properties": {
    "iso:country":"IN",
    "ks:ks_name":"Sajankabettu",
    "ks:ks_pop":360,
    "ks:ks_type":"HABITATION",
    "name:eng_x_preferred":[
        "Sajankabettu"
    ],
    "wof:name":"Sajankabettu",
    "wof:placetype":"locality",
    "wof:population":360
},
  "geometry": {"coordinates":[75.112605,12.985365],"type":"Point"}
}