{
  "type": "Feature",
  "properties": {
    "iso:country":"IN",
    "ks:ks_alt_nam":"irular colony",
    "ks:ks_name":"Irular Colony",
    "ks:ks_pop":190,
    "ks:ks_type":"HABITATION",
    "name:eng_x_preferred":[
        "Irular Colony"
    ],
    "wof:name":"Irular Colony",
    "wof:placetype":"locality",
    "wof:population":190
},
  "geometry": {"coordinates":[79.52160000000001,12.23752],"type":"Point"}
}