{
  "type": "Feature",
  "properties": {
    "iso:country":"IN",
    "ks:ks_name":"Maudehra",
    "ks:ks_pop":0,
    "ks:ks_type":"VILLAGE",
    "name:eng_x_preferred":[
        "Maudehra"
    ],
    "wof:name":"Maudehra",
    "wof:placetype":"locality",
    "wof:population":0
},
  "geometry": {"coordinates":[83.75072400000001,25.16706],"type":"Point"}
}