{
  "type": "Feature",
  "properties": {
    "iso:country":"IN",
    "ks:ks_name":"Soppinamalli",
    "ks:ks_pop":61,
    "ks:ks_type":"HABITATION",
    "name:eng_x_preferred":[
        "Soppinamalli"
    ],
    "wof:name":"Soppinamalli",
    "wof:placetype":"locality",
    "wof:population":61
},
  "geometry": {"coordinates":[75.170562,13.980727],"type":"Point"}
}