{
  "type": "Feature",
  "properties": {
    "iso:country":"IN",
    "ks:ks_name":"Bansijori",
    "ks:ks_pop":464,
    "ks:ks_type":"VILLAGE",
    "name:eng_x_preferred":[
        "Bansijori"
    ],
    "wof:name":"Bansijori",
    "wof:placetype":"locality",
    "wof:population":464
},
  "geometry": {"coordinates":[87.58489299999999,24.804659],"type":"Point"}
}