{
  "type": "Feature",
  "properties": {
    "iso:country":"IN",
    "ks:ks_name":"Sonuan",
    "ks:ks_pop":353,
    "ks:ks_type":"VILLAGE",
    "name:eng_x_preferred":[
        "Sonuan"
    ],
    "wof:name":"Sonuan",
    "wof:placetype":"locality",
    "wof:population":353
},
  "geometry": {"coordinates":[85.423585,22.388139],"type":"Point"}
}