{
  "type": "Feature",
  "properties": {
    "iso:country":"IN",
    "ks:ks_name":"Materpada",
    "ks:ks_pop":482,
    "ks:ks_type":"HABITATION",
    "name:eng_x_preferred":[
        "Materpada"
    ],
    "wof:name":"Materpada",
    "wof:placetype":"locality",
    "wof:population":482
},
  "geometry": {"coordinates":[72.858192,20.021456],"type":"Point"}
}