{
  "type": "Feature",
  "properties": {
    "gn:admin1_code":"36",
    "gn:admin2_code":"199.0",
    "gn:asciiname":"Baikunthpur",
    "gn:country_code":"IN",
    "gn:dem":84,
    "gn:feature_class":"P",
    "gn:feature_code":"PPL",
    "gn:name":"Baikunthpur",
    "gn:population":0,
    "gn:timezone":"Asia/Kolkata",
    "iso:country":"IN",
    "ks:ks_name":"Baikunthpur",
    "ks:ks_type":"VILLAGE",
    "name:ceb_x_preferred":[
        "Baikunthpur"
    ],
    "name:eng_x_preferred":[
        "Baikunthpur"
    ],
    "name:ita_x_preferred":[
        "Baikunthpur"
    ],
    "name:nld_x_preferred":[
        "Baikunthpur"
    ],
    "name:swe_x_preferred":[
        "Baikunthpur"
    ],
    "wof:name":"Baikunthpur",
    "wof:placetype":"locality"
},
  "geometry": {"coordinates":[83.02349599999999,25.202393],"type":"Point"}
}