{
  "type": "Feature",
  "properties": {
    "iso:country":"IN",
    "ks:ks_alt_nam":"dakarewadi",
    "ks:ks_name":"Dakarewadi",
    "ks:ks_pop":142,
    "ks:ks_type":"HABITATION",
    "name:eng_x_preferred":[
        "Dakarewadi"
    ],
    "wof:name":"Dakarewadi",
    "wof:placetype":"locality",
    "wof:population":142
},
  "geometry": {"coordinates":[74.085842,16.2212],"type":"Point"}
}