{
  "type": "Feature",
  "properties": {
    "iso:country":"IN",
    "ks:ks_name":"Rank Geng",
    "ks:ks_pop":319,
    "ks:ks_type":"HABITATION",
    "name:eng_x_preferred":[
        "Rank Geng"
    ],
    "wof:name":"Rank Geng",
    "wof:placetype":"locality",
    "wof:population":319
},
  "geometry": {"coordinates":[81.702826,25.586808],"type":"Point"}
}