{
  "type": "Feature",
  "properties": {
    "iso:country":"IN",
    "ks:ks_name":"Maharajganj",
    "ks:ks_pop":412,
    "ks:ks_type":"VILLAGE",
    "name:eng_x_preferred":[
        "Maharajganj"
    ],
    "wof:name":"Maharajganj",
    "wof:placetype":"locality",
    "wof:population":412
},
  "geometry": {"coordinates":[86.512097,23.909463],"type":"Point"}
}