{
  "type": "Feature",
  "properties": {
    "gn:admin1_code":"11.0",
    "gn:admin2_code":"31.0",
    "gn:asciiname":"Neri",
    "gn:country_code":"IN",
    "gn:dem":1103,
    "gn:feature_class":"P",
    "gn:feature_code":"PPL",
    "gn:name":"Neri",
    "gn:population":0,
    "gn:timezone":"Asia/Kolkata",
    "iso:country":"IN",
    "name:ceb_x_preferred":[
        "Neri"
    ],
    "name:deu_x_preferred":[
        "Neri"
    ],
    "name:fra_x_preferred":[
        "Neri"
    ],
    "name:ita_x_preferred":[
        "Neri"
    ],
    "name:por_x_preferred":[
        "Neri"
    ],
    "name:rus_x_preferred":[
        "\u041d\u0435\u0440\u0438"
    ],
    "name:swe_x_preferred":[
        "Neri"
    ],
    "wof:name":"Neri",
    "wof:placetype":"locality"
},
  "geometry": {"coordinates":[77.03126,30.98685],"type":"Point"}
}