{
  "type": "Feature",
  "properties": {
    "iso:country":"IN",
    "ks:ks_name":"Bakpara Dineralga Pt-i",
    "ks:ks_pop":169,
    "ks:ks_type":"VILLAGE",
    "name:eng_x_preferred":[
        "Bakpara Dineralga Pt-i"
    ],
    "wof:name":"Bakpara Dineralga Pt-i",
    "wof:placetype":"locality",
    "wof:population":169
},
  "geometry": {"coordinates":[90.18534099999999,26.109537],"type":"Point"}
}