{
  "type": "Feature",
  "properties": {
    "iso:country":"IN",
    "ks:ks_name":"Mehgaonkala",
    "ks:ks_pop":476,
    "ks:ks_type":"HABITATION",
    "name:eng_x_preferred":[
        "Mehgaonkala"
    ],
    "wof:name":"Mehgaonkala",
    "wof:placetype":"locality",
    "wof:population":476
},
  "geometry": {"coordinates":[79.16402100000001,23.066303],"type":"Point"}
}