{
  "type": "Feature",
  "properties": {
    "iso:country":"IN",
    "ks:ks_name":"Beli Khurd",
    "ks:ks_pop":572,
    "ks:ks_type":"HABITATION",
    "name:eng_x_preferred":[
        "Beli Khurd"
    ],
    "wof:name":"Beli Khurd",
    "wof:placetype":"locality",
    "wof:population":572
},
  "geometry": {"coordinates":[82.3798,27.50165],"type":"Point"}
}