{
  "type": "Feature",
  "properties": {
    "iso:country":"IN",
    "ks:ks_name":"Sahangagopalpur",
    "ks:ks_pop":2107,
    "ks:ks_type":"VILLAGE",
    "name:eng_x_preferred":[
        "Sahangagopalpur"
    ],
    "wof:name":"Sahangagopalpur",
    "wof:placetype":"locality",
    "wof:population":2107
},
  "geometry": {"coordinates":[85.569642,20.423929],"type":"Point"}
}