{
  "type": "Feature",
  "properties": {
    "iso:country":"IN",
    "ks:ks_alt_nam":"Chintavari HPeta",
    "ks:ks_name":"Chintavari Hpeta",
    "ks:ks_pop":578,
    "ks:ks_type":"HABITATION",
    "name:eng_x_preferred":[
        "Chintavari Hpeta"
    ],
    "wof:name":"Chintavari Hpeta",
    "wof:placetype":"locality",
    "wof:population":578
},
  "geometry": {"coordinates":[81.866057,16.654283],"type":"Point"}
}