{
  "type": "Feature",
  "properties": {
    "iso:country":"IN",
    "ks:ks_name":"Singavaram",
    "ks:ks_pop":83,
    "ks:ks_type":"HABITATION",
    "name:eng_x_preferred":[
        "Singavaram"
    ],
    "wof:name":"Singavaram",
    "wof:placetype":"locality",
    "wof:population":83
},
  "geometry": {"coordinates":[82.326671,17.873514],"type":"Point"}
}