{
  "type": "Feature",
  "properties": {
    "iso:country":"IN",
    "ks:ks_name":"Haridharpur",
    "ks:ks_pop":0,
    "ks:ks_type":"VILLAGE",
    "name:eng_x_preferred":[
        "Haridharpur"
    ],
    "wof:name":"Haridharpur",
    "wof:placetype":"locality",
    "wof:population":0
},
  "geometry": {"coordinates":[88.29171700000001,22.778002],"type":"Point"}
}