{
  "type": "Feature",
  "properties": {
    "iso:country":"IN",
    "ks:ks_name":"Tedugu",
    "ks:ks_pop":142,
    "ks:ks_type":"VILLAGE",
    "name:eng_x_preferred":[
        "Tedugu"
    ],
    "wof:name":"Tedugu",
    "wof:placetype":"locality",
    "wof:population":142
},
  "geometry": {"coordinates":[84.098747,19.07966],"type":"Point"}
}