{
  "type": "Feature",
  "properties": {
    "iso:country":"IN",
    "ks:ks_name":"Malawada",
    "ks:ks_pop":80,
    "ks:ks_type":"HABITATION",
    "name:eng_x_preferred":[
        "Malawada"
    ],
    "wof:name":"Malawada",
    "wof:placetype":"locality",
    "wof:population":80
},
  "geometry": {"coordinates":[79.223859,14.364143],"type":"Point"}
}