{
  "type": "Feature",
  "properties": {
    "iso:country":"IN",
    "ks:ks_name":"Kharchhua",
    "ks:ks_pop":624,
    "ks:ks_type":"HABITATION",
    "name:eng_x_preferred":[
        "Kharchhua"
    ],
    "wof:name":"Kharchhua",
    "wof:placetype":"locality",
    "wof:population":624
},
  "geometry": {"coordinates":[84.673298,25.17994],"type":"Point"}
}