{
  "type": "Feature",
  "properties": {
    "iso:country":"IN",
    "ks:ks_name":"Vaktapur",
    "ks:ks_pop":137,
    "ks:ks_type":"HABITATION",
    "name:eng_x_preferred":[
        "Vaktapur"
    ],
    "wof:name":"Vaktapur",
    "wof:placetype":"locality",
    "wof:population":137
},
  "geometry": {"coordinates":[73.355861,23.693861],"type":"Point"}
}