{
  "type": "Feature",
  "properties": {
    "gn:admin1_code":"36",
    "gn:admin2_code":"155.0",
    "gn:asciiname":"Nurpur",
    "gn:country_code":"IN",
    "gn:dem":137,
    "gn:feature_class":"P",
    "gn:feature_code":"PPL",
    "gn:name":"N\u016brpur",
    "gn:population":0,
    "gn:timezone":"Asia/Kolkata",
    "iso:country":"IN",
    "name:ceb_x_preferred":[
        "Nurpur"
    ],
    "name:swe_x_preferred":[
        "Nurpur"
    ],
    "wof:name":"Nurpur",
    "wof:placetype":"locality"
},
  "geometry": {"coordinates":[79.84295999999998,27.31598],"type":"Point"}
}