{
  "type": "Feature",
  "properties": {
    "gn:admin1_code":"36",
    "gn:admin2_code":"195.0",
    "gn:asciiname":"Dharwara",
    "gn:country_code":"IN",
    "gn:dem":75,
    "gn:feature_class":"P",
    "gn:feature_code":"PPL",
    "gn:name":"Dharw\u0101ra",
    "gn:population":0,
    "gn:timezone":"Asia/Kolkata",
    "iso:country":"IN",
    "wof:name":"Dharwara",
    "wof:placetype":"neighbourhood"
},
  "geometry": {"coordinates":[83.68213,25.79172],"type":"Point"}
}