{
  "type": "Feature",
  "properties": {
    "iso:country":"IN",
    "ks:ks_name":"Maduwa Tola",
    "ks:ks_pop":95,
    "ks:ks_type":"HABITATION",
    "ks:ks_uagg_main":0,
    "name:eng_x_preferred":[
        "Maduwa Tola"
    ],
    "wof:name":"Maduwa Tola",
    "wof:placetype":"neighbourhood",
    "wof:population":95
},
  "geometry": {"coordinates":[83.528237,26.943902],"type":"Point"}
}