{
  "type": "Feature",
  "properties": {
    "gn:admin1_code":"16.0",
    "gn:admin2_code":"505.0",
    "gn:asciiname":"Panjra",
    "gn:country_code":"IN",
    "gn:dem":423,
    "gn:feature_class":"P",
    "gn:feature_code":"PPL",
    "gn:name":"P\u0101njra",
    "gn:population":0,
    "gn:timezone":"Asia/Kolkata",
    "iso:country":"IN",
    "name:und_x_variant":[
        "P\u0101njra",
        "Kukri"
    ],
    "wof:name":"Panjra",
    "wof:placetype":"locality"
},
  "geometry": {"coordinates":[78.64519,21.25672],"type":"Point"}
}