{
  "type": "Feature",
  "properties": {
    "gn:admin1_code":"35",
    "gn:admin2_code":"436.0",
    "gn:asciiname":"Retakheri",
    "gn:country_code":"IN",
    "gn:dem":476,
    "gn:feature_class":"P",
    "gn:feature_code":"PPL",
    "gn:name":"Retakheri",
    "gn:population":0,
    "gn:timezone":"Asia/Kolkata",
    "iso:country":"IN",
    "name:und_x_variant":[
        "Jiy\u0101jipura"
    ],
    "wof:name":"Retakheri",
    "wof:placetype":"locality"
},
  "geometry": {"coordinates":[76.37921,23.25843],"type":"Point"}
}