{
  "type": "Feature",
  "properties": {
    "gn:admin1_code":"37.0",
    "gn:admin2_code":"416.0",
    "gn:asciiname":"Muteli",
    "gn:country_code":"IN",
    "gn:dem":320,
    "gn:feature_class":"P",
    "gn:feature_code":"PPL",
    "gn:name":"Muteli",
    "gn:population":0,
    "gn:timezone":"Asia/Kolkata",
    "iso:country":"IN",
    "ks:ks_name":"Mutheli",
    "ks:ks_pop":220,
    "ks:ks_type":"VILLAGE",
    "name:eng_x_preferred":[
        "Mutheli"
    ],
    "name:eng_x_variant":[
        "Muteli"
    ],
    "wof:name":"Mutheli",
    "wof:placetype":"locality",
    "wof:population":220
},
  "geometry": {"coordinates":[81.617859,18.607319],"type":"Point"}
}