{
  "type": "Feature",
  "properties": {
    "iso:country":"IN",
    "ks:ks_name":"Deoki Jot",
    "ks:ks_pop":9,
    "ks:ks_type":"HABITATION",
    "name:eng_x_preferred":[
        "Deoki Jot"
    ],
    "wof:name":"Deoki Jot",
    "wof:placetype":"locality",
    "wof:population":9
},
  "geometry": {"coordinates":[82.61337399999999,26.662239],"type":"Point"}
}