{
  "type": "Feature",
  "properties": {
    "iso:country":"IN",
    "ks:ks_alt_nam":"Sakdi bari",
    "ks:ks_name":"Sakdi Bari",
    "ks:ks_pop":312,
    "ks:ks_type":"HABITATION",
    "name:eng_x_preferred":[
        "Sakdi Bari"
    ],
    "wof:name":"Sakdi Bari",
    "wof:placetype":"locality",
    "wof:population":312
},
  "geometry": {"coordinates":[73.949009,21.898886],"type":"Point"}
}