{
  "type": "Feature",
  "properties": {
    "gn:admin1_code":"09",
    "gn:admin2_code":"471.0",
    "gn:asciiname":"Sardarpur",
    "gn:country_code":"IN",
    "gn:dem":141,
    "gn:feature_class":"P",
    "gn:feature_code":"PPL",
    "gn:name":"Sard\u0101rpur",
    "gn:population":0,
    "gn:timezone":"Asia/Kolkata",
    "iso:country":"IN",
    "wof:name":"Sardarpur",
    "wof:placetype":"locality"
},
  "geometry": {"coordinates":[72.76850999999998,23.68927],"type":"Point"}
}