{
  "type": "Feature",
  "properties": {
    "gn:admin1_code":"35.0",
    "gn:admin2_code":"441.0",
    "gn:asciiname":"Gothania",
    "gn:country_code":"IN",
    "gn:dem":303,
    "gn:feature_class":"P",
    "gn:feature_code":"PPL",
    "gn:name":"Goth\u0101nia",
    "gn:population":0,
    "gn:timezone":"Asia/Kolkata",
    "iso:country":"IN",
    "wof:name":"Gothania",
    "wof:placetype":"locality"
},
  "geometry": {"coordinates":[75.0065,21.92615],"type":"Point"}
}