{
  "type": "Feature",
  "properties": {
    "gn:admin1_code":"35.0",
    "gn:admin2_code":"441.0",
    "gn:asciiname":"Gothania",
    "gn:country_code":"IN",
    "gn:dem":303,
    "gn:feature_class":"P",
    "gn:feature_code":"PPL",
    "gn:name":"Goth\u0101nia",
    "gn:population":0,
    "gn:timezone":"Asia/Kolkata",
    "iso:country":"IN",
    "ks:ks_alt_nam":"Goth\u0101nia",
    "ks:ks_name":"Gothania",
    "ks:ks_type":"VILLAGE",
    "name:eng_x_preferred":[
        "Gothania"
    ],
    "name:eng_x_variant":[
        "Goth\u0101nia"
    ],
    "wof:name":"Gothania",
    "wof:placetype":"locality"
},
  "geometry": {"coordinates":[75.006503,21.926149],"type":"Point"}
}