{
  "type": "Feature",
  "properties": {
    "gn:admin1_code":"02",
    "gn:admin2_code":"546.0",
    "gn:asciiname":"Maruteru",
    "gn:country_code":"IN",
    "gn:dem":15,
    "gn:feature_class":"P",
    "gn:feature_code":"PPL",
    "gn:name":"M\u0101ruteru",
    "gn:population":0,
    "gn:timezone":"Asia/Kolkata",
    "iso:country":"IN",
    "wof:name":"Maruteru",
    "wof:placetype":"locality"
},
  "geometry": {"coordinates":[81.73945000000001,16.62369],"type":"Point"}
}