{
  "type": "Feature",
  "properties": {
    "iso:country":"IN",
    "ks:ks_name":"Tola Barakol",
    "ks:ks_pop":461,
    "ks:ks_type":"VILLAGE",
    "name:eng_x_preferred":[
        "Tola Barakol"
    ],
    "wof:name":"Tola Barakol",
    "wof:placetype":"locality",
    "wof:population":461
},
  "geometry": {"coordinates":[86.327208,24.558862],"type":"Point"}
}