{
  "type": "Feature",
  "properties": {
    "iso:country":"IN",
    "ks:ks_alt_nam":"Vellora east",
    "ks:ks_name":"Vellora East",
    "ks:ks_pop":2120,
    "ks:ks_type":"HABITATION",
    "name:eng_x_preferred":[
        "Vellora East"
    ],
    "wof:name":"Vellora East",
    "wof:placetype":"locality",
    "wof:population":2120
},
  "geometry": {"coordinates":[75.350782,12.180117],"type":"Point"}
}