{
  "type": "Feature",
  "properties": {
    "gn:admin1_code":"19.0",
    "gn:admin2_code":"581.0",
    "gn:asciiname":"Timmasandra",
    "gn:country_code":"IN",
    "gn:dem":826,
    "gn:feature_class":"P",
    "gn:feature_code":"PPL",
    "gn:name":"Timmasandra",
    "gn:population":0,
    "gn:timezone":"Asia/Kolkata",
    "iso:country":"IN",
    "wof:name":"Timmasandra",
    "wof:placetype":"locality"
},
  "geometry": {"coordinates":[78.20166999999999,13.12017],"type":"Point"}
}