{
  "type": "Feature",
  "properties": {
    "iso:country":"IN",
    "ks:ks_name":"Kallamkuzhi",
    "ks:ks_pop":873,
    "ks:ks_type":"HABITATION",
    "name:eng_x_preferred":[
        "Kallamkuzhi"
    ],
    "wof:name":"Kallamkuzhi",
    "wof:placetype":"locality",
    "wof:population":873
},
  "geometry": {"coordinates":[76.51393899999999,10.978437],"type":"Point"}
}