{
  "type": "Feature",
  "properties": {
    "iso:country":"IN",
    "ks:ks_name":"Taldangal",
    "ks:ks_pop":276,
    "ks:ks_type":"VILLAGE",
    "name:eng_x_preferred":[
        "Taldangal"
    ],
    "wof:name":"Taldangal",
    "wof:placetype":"locality",
    "wof:population":276
},
  "geometry": {"coordinates":[87.17389,24.173425],"type":"Point"}
}