{
  "type": "Feature",
  "properties": {
    "iso:country":"IN",
    "ks:ks_name":"Jambalshitta",
    "ks:ks_pop":204,
    "ks:ks_type":"HABITATION",
    "name:eng_x_preferred":[
        "Jambalshitta"
    ],
    "wof:name":"Jambalshitta",
    "wof:placetype":"locality",
    "wof:population":204
},
  "geometry": {"coordinates":[74.19195999999999,14.857454],"type":"Point"}
}