{
  "type": "Feature",
  "properties": {
    "iso:country":"IN",
    "ks:ks_name":"Ambai Buzurg Uparhar",
    "ks:ks_pop":2375,
    "ks:ks_type":"VILLAGE",
    "ks:ks_uagg_main":0,
    "name:eng_x_preferred":[
        "Ambai Buzurg Uparhar"
    ],
    "wof:name":"Ambai Buzurg Uparhar",
    "wof:placetype":"neighbourhood",
    "wof:population":2375
},
  "geometry": {"coordinates":[81.376114,25.750514],"type":"Point"}
}