{
  "type": "Feature",
  "properties": {
    "gn:admin1_code":"3.0",
    "gn:admin2_code":"305",
    "gn:asciiname":"Chapanalla",
    "gn:country_code":"IN",
    "gn:dem":70,
    "gn:feature_class":"P",
    "gn:feature_code":"PPL",
    "gn:name":"Ch\u0101p\u0101n\u0101lla",
    "gn:population":0,
    "gn:timezone":"Asia/Kolkata",
    "iso:country":"IN",
    "name:und_x_variant":[
        "Chapenalla",
        "Ch\u0101p\u0101n\u0101lla"
    ],
    "wof:name":"Chapanalla",
    "wof:placetype":"locality"
},
  "geometry": {"coordinates":[92.88066999999999,26.33673],"type":"Point"}
}