{
  "type": "Feature",
  "properties": {
    "gn:admin1_code":"23",
    "gn:admin2_code":"40.0",
    "gn:asciiname":"Shahidgarh",
    "gn:country_code":"IN",
    "gn:dem":271,
    "gn:feature_class":"P",
    "gn:feature_code":"PPL",
    "gn:name":"Shah\u012bdgarh",
    "gn:population":0,
    "gn:timezone":"Asia/Kolkata",
    "iso:country":"IN",
    "wof:name":"Shahidgarh",
    "wof:placetype":"locality"
},
  "geometry": {"coordinates":[76.41226999999998,30.68016],"type":"Point"}
}