{
  "type": "Feature",
  "properties": {
    "iso:country":"IN",
    "ks:ks_name":"Dhamahapur N.Aurangabad",
    "ks:ks_type":"VILLAGE",
    "name:eng_x_preferred":[
        "Dhamahapur N.Aurangabad"
    ],
    "wof:name":"Dhamahapur N.Aurangabad",
    "wof:placetype":"locality"
},
  "geometry": {"coordinates":[82.506028,25.269611],"type":"Point"}
}