{
  "type": "Feature",
  "properties": {
    "gn:admin1_code":"25.0",
    "gn:admin2_code":"619.0",
    "gn:asciiname":"Allattambadi",
    "gn:country_code":"IN",
    "gn:dem":4,
    "gn:feature_class":"P",
    "gn:feature_code":"PPL",
    "gn:name":"Allattamb\u0101di",
    "gn:population":0,
    "gn:timezone":"Asia/Kolkata",
    "iso:country":"IN",
    "ks:ks_name":"Alathambadi",
    "ks:ks_pop":598,
    "ks:ks_type":"VILLAGE",
    "ks:ks_uagg_main":0,
    "name:eng_x_preferred":[
        "Alathambadi"
    ],
    "wof:name":"Alathambadi",
    "wof:placetype":"neighbourhood",
    "wof:population":598
},
  "geometry": {"coordinates":[79.65675899999999,10.602363],"type":"Point"}
}