{
  "type": "Feature",
  "properties": {
    "iso:country":"IN",
    "ks:ks_name":"Jot Balaram",
    "ks:ks_pop":85,
    "ks:ks_type":"VILLAGE",
    "name:eng_x_preferred":[
        "Jot Balaram"
    ],
    "wof:name":"Jot Balaram",
    "wof:placetype":"locality",
    "wof:population":85
},
  "geometry": {"coordinates":[88.338106,24.952316],"type":"Point"}
}