{
  "type": "Feature",
  "properties": {
    "iso:country":"IN",
    "ks:ks_name":"Kasalia",
    "ks:ks_pop":331,
    "ks:ks_type":"HABITATION",
    "ks:ks_uagg_main":0,
    "name:eng_x_preferred":[
        "Kasalia"
    ],
    "wof:name":"Kasalia",
    "wof:placetype":"neighbourhood",
    "wof:population":331
},
  "geometry": {"coordinates":[79.926124,27.54651],"type":"Point"}
}