{
  "type": "Feature",
  "properties": {
    "iso:country":"IN",
    "ks:ks_name":"Seethapatti",
    "ks:ks_pop":399,
    "ks:ks_type":"HABITATION",
    "name:eng_x_preferred":[
        "Seethapatti"
    ],
    "wof:name":"Seethapatti",
    "wof:placetype":"locality",
    "wof:population":399
},
  "geometry": {"coordinates":[78.342029,10.566227],"type":"Point"}
}