{
  "type": "Feature",
  "properties": {
    "iso:country":"IN",
    "ks:ks_name":"Balarampur",
    "ks:ks_pop":88,
    "ks:ks_type":"VILLAGE",
    "name:eng_x_preferred":[
        "Balarampur"
    ],
    "wof:name":"Balarampur",
    "wof:placetype":"locality",
    "wof:population":88
},
  "geometry": {"coordinates":[84.482944,19.238132],"type":"Point"}
}