{
  "type": "Feature",
  "properties": {
    "iso:country":"IN",
    "ks:ks_alt_nam":"NAYAK SAI",
    "ks:ks_name":"Nayak Sai",
    "ks:ks_pop":237,
    "ks:ks_type":"HABITATION",
    "name:eng_x_preferred":[
        "Nayak Sai"
    ],
    "wof:name":"Nayak Sai",
    "wof:placetype":"locality",
    "wof:population":237
},
  "geometry": {"coordinates":[85.631395,22.612094],"type":"Point"}
}