{
  "type": "Feature",
  "properties": {
    "gn:admin1_code":"28.0",
    "gn:admin2_code":"327",
    "gn:asciiname":"Ghum",
    "gn:country_code":"IN",
    "gn:dem":2165,
    "gn:feature_class":"P",
    "gn:feature_code":"PPL",
    "gn:name":"Ghum",
    "gn:population":0,
    "gn:timezone":"Asia/Kolkata",
    "iso:country":"IN",
    "name:und_x_variant":[
        "Ghoom",
        "Ghum"
    ],
    "wof:name":"Ghum",
    "wof:placetype":"locality"
},
  "geometry": {"coordinates":[88.25768000000002,27.00691],"type":"Point"}
}