{
  "type": "Feature",
  "properties": {
    "iso:country":"IN",
    "ks:ks_alt_nam":"PURE LAGDI",
    "ks:ks_name":"Pure Lagdi",
    "ks:ks_pop":130,
    "ks:ks_type":"HABITATION",
    "name:eng_x_preferred":[
        "Pure Lagdi"
    ],
    "wof:name":"Pure Lagdi",
    "wof:placetype":"locality",
    "wof:population":130
},
  "geometry": {"coordinates":[81.5197,26.2546],"type":"Point"}
}