{
  "type": "Feature",
  "properties": {
    "iso:country":"IN",
    "ks:ks_name":"Kenchni",
    "ks:ks_pop":0,
    "ks:ks_type":"VILLAGE",
    "name:eng_x_preferred":[
        "Kenchni"
    ],
    "wof:name":"Kenchni",
    "wof:placetype":"locality",
    "wof:population":0
},
  "geometry": {"coordinates":[76.33218599999999,24.500771],"type":"Point"}
}