{
  "type": "Feature",
  "properties": {
    "iso:country":"IN",
    "ks:ks_name":"Manjanakatte",
    "ks:ks_pop":265,
    "ks:ks_type":"HABITATION",
    "name:eng_x_preferred":[
        "Manjanakatte"
    ],
    "wof:name":"Manjanakatte",
    "wof:placetype":"locality",
    "wof:population":265
},
  "geometry": {"coordinates":[74.916489,13.051596],"type":"Point"}
}