{
  "type": "Feature",
  "properties": {
    "iso:country":"IN",
    "ks:ks_name":"25 KYD",
    "ks:ks_pop":1086,
    "ks:ks_type":"VILLAGE",
    "name:eng_x_preferred":[
        "25 KYD"
    ],
    "wof:name":"25 KYD",
    "wof:placetype":"locality",
    "wof:population":1086
},
  "geometry": {"coordinates":[72.55731900000001,28.761611],"type":"Point"}
}