{
  "type": "Feature",
  "properties": {
    "iso:country":"IN",
    "ks:ks_name":"Kizhakedambu",
    "ks:ks_pop":971,
    "ks:ks_type":"HABITATION",
    "name:eng_x_preferred":[
        "Kizhakedambu"
    ],
    "wof:name":"Kizhakedambu",
    "wof:placetype":"locality",
    "wof:population":971
},
  "geometry": {"coordinates":[76.692037,9.627315],"type":"Point"}
}