{
  "type": "Feature",
  "properties": {
    "iso:country":"IN",
    "ks:ks_alt_nam":"YEDEHADLU",
    "ks:ks_name":"Yedehadlu",
    "ks:ks_pop":36,
    "ks:ks_type":"HABITATION",
    "name:eng_x_preferred":[
        "Yedehadlu"
    ],
    "wof:name":"Yedehadlu",
    "wof:placetype":"locality",
    "wof:population":36
},
  "geometry": {"coordinates":[75.1789,13.637531],"type":"Point"}
}