{
  "type": "Feature",
  "properties": {
    "iso:country":"IN",
    "ks:ks_alt_nam":"Pu.Malayanur",
    "ks:ks_name":"Pu.malayanur",
    "ks:ks_pop":1101,
    "ks:ks_type":"HABITATION",
    "name:eng_x_preferred":[
        "Pu.malayanur"
    ],
    "wof:name":"Pu.malayanur",
    "wof:placetype":"locality",
    "wof:population":1101
},
  "geometry": {"coordinates":[79.21574099999999,11.687591],"type":"Point"}
}