{
  "type": "Feature",
  "properties": {
    "gn:admin1_code":"19.0",
    "gn:admin2_code":"570.0",
    "gn:asciiname":"Ballekere",
    "gn:country_code":"IN",
    "gn:dem":771,
    "gn:elevation":"760.0",
    "gn:feature_class":"P",
    "gn:feature_code":"PPLF",
    "gn:name":"Ballekere",
    "gn:population":0,
    "gn:timezone":"Asia/Kolkata",
    "iso:country":"IN",
    "wof:name":"Ballekere",
    "wof:placetype":"locality"
},
  "geometry": {"coordinates":[76.03402,13.49455],"type":"Point"}
}