{
  "type": "Feature",
  "properties": {
    "iso:country":"IN",
    "ks:ks_name":"Kharthasar",
    "ks:ks_pop":352,
    "ks:ks_type":"HABITATION",
    "name:eng_x_preferred":[
        "Kharthasar"
    ],
    "wof:name":"Kharthasar",
    "wof:placetype":"locality",
    "wof:population":352
},
  "geometry": {"coordinates":[71.531023,25.318412],"type":"Point"}
}