{
  "type": "Feature",
  "properties": {
    "iso:country":"IN",
    "ks:ks_name":"Dhobha",
    "ks:ks_pop":536,
    "ks:ks_type":"VILLAGE",
    "ks:ks_uagg_main":0,
    "name:eng_x_preferred":[
        "Dhobha"
    ],
    "wof:name":"Dhobha",
    "wof:placetype":"neighbourhood",
    "wof:population":536
},
  "geometry": {"coordinates":[85.45376400000001,26.319051],"type":"Point"}
}