{
  "type": "Feature",
  "properties": {
    "iso:country":"IN",
    "ks:ks_name":"Jogendra Para",
    "ks:ks_pop":299,
    "ks:ks_type":"HABITATION",
    "ks:ks_uagg_main":0,
    "name:eng_x_preferred":[
        "Jogendra Para"
    ],
    "wof:name":"Jogendra Para",
    "wof:placetype":"neighbourhood",
    "wof:population":299
},
  "geometry": {"coordinates":[91.77763299999999,23.206408],"type":"Point"}
}