{
  "type": "Feature",
  "properties": {
    "gn:admin1_code":"28",
    "gn:admin2_code":"328.0",
    "gn:asciiname":"Neora Nadi",
    "gn:country_code":"IN",
    "gn:dem":105,
    "gn:feature_class":"P",
    "gn:feature_code":"PPL",
    "gn:name":"Neor\u0101 Nad\u012b",
    "gn:population":0,
    "gn:timezone":"Asia/Kolkata",
    "iso:country":"IN",
    "wof:name":"Neora Nadi",
    "wof:placetype":"neighbourhood"
},
  "geometry": {"coordinates":[88.74356,26.72497],"type":"Point"}
}