{
  "type": "Feature",
  "properties": {
    "gn:admin1_code":"2.0",
    "gn:admin2_code":"546.0",
    "gn:asciiname":"Jillellaguden",
    "gn:country_code":"IN",
    "gn:dem":138,
    "gn:feature_class":"P",
    "gn:feature_code":"PPL",
    "gn:name":"Jillellag\u016bden",
    "gn:population":0,
    "gn:timezone":"Asia/Kolkata",
    "iso:country":"IN",
    "wof:name":"Jillellaguden",
    "wof:placetype":"locality"
},
  "geometry": {"coordinates":[81.20376,17.28061],"type":"Point"}
}