{
  "type": "Feature",
  "properties": {
    "iso:country":"IN",
    "ks:ks_alt_nam":"MUSLIM TOLA",
    "ks:ks_name":"Muslim Tola",
    "ks:ks_pop":826,
    "ks:ks_type":"HABITATION",
    "name:eng_x_preferred":[
        "Muslim Tola"
    ],
    "wof:name":"Muslim Tola",
    "wof:placetype":"locality",
    "wof:population":826
},
  "geometry": {"coordinates":[85.998302,25.514906],"type":"Point"}
}