{
  "type": "Feature",
  "properties": {
    "iso:country":"IN",
    "ks:ks_name":"Banari",
    "ks:ks_pop":161,
    "ks:ks_type":"HABITATION",
    "name:eng_x_preferred":[
        "Banari"
    ],
    "wof:name":"Banari",
    "wof:placetype":"locality",
    "wof:population":161
},
  "geometry": {"coordinates":[79.06990399999999,30.128076],"type":"Point"}
}