{
  "type": "Feature",
  "properties": {
    "gn:admin1_code":"39",
    "gn:admin2_code":"56.0",
    "gn:asciiname":"Tori Khera",
    "gn:country_code":"IN",
    "gn:dem":1200,
    "gn:feature_class":"P",
    "gn:feature_code":"PPL",
    "gn:name":"Tori Khera",
    "gn:population":0,
    "gn:timezone":"Asia/Kolkata",
    "iso:country":"IN",
    "wof:name":"Tori Khera",
    "wof:placetype":"locality"
},
  "geometry": {"coordinates":[77.83304,30.93631],"type":"Point"}
}