{
  "type": "Feature",
  "properties": {
    "gn:admin1_code":"25.0",
    "gn:admin2_code":"609.0",
    "gn:asciiname":"Pudur",
    "gn:country_code":"IN",
    "gn:dem":232,
    "gn:feature_class":"P",
    "gn:feature_code":"PPL",
    "gn:name":"Pud\u016br",
    "gn:population":0,
    "gn:timezone":"Asia/Kolkata",
    "iso:country":"IN",
    "name:nld_x_preferred":[
        "Pudur"
    ],
    "name:tam_x_preferred":[
        "\u0baa\u0bc1\u0ba4\u0bc2\u0bb0\u0bcd"
    ],
    "wof:name":"Pudur",
    "wof:placetype":"locality"
},
  "geometry": {"coordinates":[77.83346,11.41423],"type":"Point"}
}