{
  "type": "Feature",
  "properties": {
    "iso:country":"IN",
    "ks:ks_name":"Kumbarkodi",
    "ks:ks_pop":249,
    "ks:ks_type":"HABITATION",
    "name:eng_x_preferred":[
        "Kumbarkodi"
    ],
    "wof:name":"Kumbarkodi",
    "wof:placetype":"locality",
    "wof:population":249
},
  "geometry": {"coordinates":[74.685855,16.394667],"type":"Point"}
}