{
  "type": "Feature",
  "properties": {
    "iso:country":"IN",
    "ks:ks_name":"Devagudipalle",
    "ks:ks_pop":1798,
    "ks:ks_type":"VILLAGE",
    "ks:ks_uagg_main":0,
    "name:eng_x_preferred":[
        "Devagudipalle"
    ],
    "wof:name":"Devagudipalle",
    "wof:placetype":"neighbourhood",
    "wof:population":1798
},
  "geometry": {"coordinates":[78.691215,13.951682],"type":"Point"}
}