{
  "type": "Feature",
  "properties": {
    "iso:country":"IN",
    "ks:ks_name":"Hosamane",
    "ks:ks_pop":44,
    "ks:ks_type":"HABITATION",
    "name:eng_x_preferred":[
        "Hosamane"
    ],
    "wof:name":"Hosamane",
    "wof:placetype":"locality",
    "wof:population":44
},
  "geometry": {"coordinates":[74.921751,13.900108],"type":"Point"}
}