{
  "type": "Feature",
  "properties": {
    "iso:country":"IN",
    "ks:ks_name":"Vishnu Ki Dhani",
    "ks:ks_pop":915,
    "ks:ks_type":"HABITATION",
    "name:eng_x_preferred":[
        "Vishnu Ki Dhani"
    ],
    "wof:name":"Vishnu Ki Dhani",
    "wof:placetype":"locality",
    "wof:population":915
},
  "geometry": {"coordinates":[72.753964,26.737469],"type":"Point"}
}