{
  "type": "Feature",
  "properties": {
    "gn:country":"IN",
    "gn:fcode":"PPL",
    "gn:pop":21796,
    "iso:country":"IN",
    "name:ben_x_preferred":[
        "\u0995\u09c1\u099a\u09c7\u09b0\u09be"
    ],
    "name:bpy_x_preferred":[
        "\u0995\u09c1\u099a\u09c7\u09b0\u09be"
    ],
    "name:bul_x_preferred":[
        "\u041a\u0443\u0447\u0435\u0440\u0430"
    ],
    "name:chi_x_preferred":[
        "\u5e93\u5207\u62c9"
    ],
    "name:dut_x_preferred":[
        "Kuchera"
    ],
    "name:eng_x_preferred":[
        "Kuchera"
    ],
    "name:fre_x_preferred":[
        "Kuchera"
    ],
    "name:ita_x_preferred":[
        "Kuchera"
    ],
    "name:may_x_preferred":[
        "Kuchera"
    ],
    "name:mlg_x_preferred":[
        "Kuchera"
    ],
    "name:nan_x_preferred":[
        "Kuchera"
    ],
    "name:new_x_preferred":[
        "\u0915\u0941\u091a\u0947\u0930\u093e"
    ],
    "name:por_x_preferred":[
        "Kuchera"
    ],
    "name:rus_x_preferred":[
        "\u041a\u0443\u0447\u0435\u0440"
    ],
    "name:swe_x_preferred":[
        "Kuchera"
    ],
    "name:unk_x_variant":[
        "Kuchera"
    ],
    "name:vie_x_preferred":[
        "Kuchera"
    ],
    "qs:name":"Khera",
    "qs:name_adm0":"India",
    "qs:name_adm1":"Rajasthan",
    "qs:photos_9r":0,
    "qs:photos_sr":0,
    "qs:placetype":"Town",
    "qs:pop_sr":"7",
    "wd:wordcount":294,
    "wof:name":"Khera",
    "wof:placetype":"locality",
    "wof:population":21796
},
  "geometry": {"coordinates":[73.97108,26.98747],"type":"Point"}
}