{
  "type": "Feature",
  "properties": {
    "gn:country":"IN",
    "gn:fcode":"PPL",
    "gn:population":21796,
    "iso:country":"IN",
    "name:ara_x_preferred":[
        "\u062e\u064a\u0631\u0627"
    ],
    "name:ben_bn_x_preferred":[
        "\u0996\u09c7\u09b0\u09be"
    ],
    "name:ben_in_x_preferred":[
        "\u0996\u09c7\u09b0\u09be"
    ],
    "name:ben_x_preferred":[
        "\u0995\u09c1\u099a\u09c7\u09b0\u09be"
    ],
    "name:bpy_x_preferred":[
        "\u0995\u09c1\u099a\u09c7\u09b0\u09be"
    ],
    "name:bul_x_preferred":[
        "\u041a\u0443\u0447\u0435\u0440\u0430"
    ],
    "name:ceb_x_preferred":[
        "Kuchera"
    ],
    "name:eng_x_preferred":[
        "Kuchera"
    ],
    "name:fra_x_preferred":[
        "Kuchera"
    ],
    "name:guj_x_preferred":[
        "\u0a96\u0ac7\u0ab0\u0abe"
    ],
    "name:hin_x_preferred":[
        "\u0916\u0947\u095c\u093e"
    ],
    "name:hin_x_variant":[
        "\u0915\u0941\u091a\u0947\u0930\u093e"
    ],
    "name:ita_x_preferred":[
        "Kuchera"
    ],
    "name:kan_x_preferred":[
        "\u0c96\u0cc7\u0cb0\u0cbe"
    ],
    "name:mal_x_preferred":[
        "\u0d16\u0d47\u0d30"
    ],
    "name:mar_x_preferred":[
        "\u0916\u0947\u0930\u093e"
    ],
    "name:mlg_x_preferred":[
        "Kuchera"
    ],
    "name:msa_x_preferred":[
        "Kuchera"
    ],
    "name:nan_x_preferred":[
        "Kuchera"
    ],
    "name:new_x_preferred":[
        "\u0915\u0941\u091a\u0947\u0930\u093e"
    ],
    "name:nld_x_preferred":[
        "Kuchera"
    ],
    "name:pan_x_preferred":[
        "\u0a16\u0a47\u0a5c\u0a3e"
    ],
    "name:por_x_preferred":[
        "Kuchera"
    ],
    "name:rus_x_preferred":[
        "\u041a\u0443\u0447\u0435\u0440"
    ],
    "name:swe_x_preferred":[
        "Kuchera"
    ],
    "name:tam_x_preferred":[
        "\u0b95\u0bc7\u0bb0\u0bbe"
    ],
    "name:tel_x_preferred":[
        "\u0c16\u0c47\u0c30\u0c3e"
    ],
    "name:urd_x_preferred":[
        "\u06a9\u06be\u06cc\u0691\u0627"
    ],
    "name:vie_x_preferred":[
        "Kuchera"
    ],
    "name:zho_x_preferred":[
        "\u5e93\u5207\u62c9"
    ],
    "qs:name":"Khera",
    "qs:name_adm0":"India",
    "qs:name_adm1":"Rajasthan",
    "qs:photos_9r":0,
    "qs:photos_sr":0,
    "qs:placetype":"Town",
    "qs:pop_sr":"7",
    "wd:wordcount":294,
    "wof:name":"Khera",
    "wof:placetype":"locality",
    "wof:population":21796
},
  "geometry": {"coordinates":[73.97108,26.98747],"type":"Point"}
}