{
  "type": "Feature",
  "properties": {
    "gn:admin1_code":"34.0",
    "gn:admin2_code":"230.0",
    "gn:asciiname":"Dariyapur Anant",
    "gn:country_code":"IN",
    "gn:dem":71,
    "gn:feature_class":"P",
    "gn:feature_code":"PPL",
    "gn:name":"Dariy\u0101pur Anant",
    "gn:population":0,
    "gn:timezone":"Asia/Kolkata",
    "iso:country":"IN",
    "ks:ks_alt_nam":"Dariy\u0101pur Anant",
    "ks:ks_name":"Dariyapur Anant",
    "ks:ks_pop":1485,
    "ks:ks_type":"VILLAGE",
    "name:eng_x_preferred":[
        "Dariyapur Anant"
    ],
    "name:eng_x_variant":[
        "Dariy\u0101pur Anant"
    ],
    "wof:name":"Dariyapur Anant",
    "wof:placetype":"locality",
    "wof:population":1485
},
  "geometry": {"coordinates":[84.790638,25.331875],"type":"Point"}
}