{
  "type": "Feature",
  "properties": {
    "gn:admin1_code":"25.0",
    "gn:admin2_code":"610.0",
    "gn:asciiname":"Kulattuppalaiyam",
    "gn:country_code":"IN",
    "gn:dem":295,
    "gn:feature_class":"P",
    "gn:feature_code":"PPL",
    "gn:name":"Kulattupp\u0101laiyam",
    "gn:population":0,
    "gn:timezone":"Asia/Kolkata",
    "iso:country":"IN",
    "wof:name":"Kulattuppalaiyam",
    "wof:placetype":"locality"
},
  "geometry": {"coordinates":[77.48466999999999,11.3111],"type":"Point"}
}