{
  "type": "Feature",
  "properties": {
    "iso:country":"IN",
    "ks:ks_name":"Rajpoot Tola",
    "ks:ks_pop":2336,
    "ks:ks_type":"HABITATION",
    "name:eng_x_preferred":[
        "Rajpoot Tola"
    ],
    "wof:name":"Rajpoot Tola",
    "wof:placetype":"locality",
    "wof:population":2336
},
  "geometry": {"coordinates":[87.089416,26.251888],"type":"Point"}
}