{
  "type": "Feature",
  "properties": {
    "iso:country":"IN",
    "ks:ks_name":"5 H",
    "ks:ks_pop":47,
    "ks:ks_type":"VILLAGE",
    "name:eng_x_preferred":[
        "5 H"
    ],
    "wof:name":"5 H",
    "wof:placetype":"locality",
    "wof:population":47
},
  "geometry": {"coordinates":[73.1075,29.078333],"type":"Point"}
}