{
  "type": "Feature",
  "properties": {
    "iso:country":"IN",
    "ks:ks_name":"Okhari Khedi",
    "ks:ks_pop":72,
    "ks:ks_type":"VILLAGE",
    "name:eng_x_preferred":[
        "Okhari Khedi"
    ],
    "wof:name":"Okhari Khedi",
    "wof:placetype":"locality",
    "wof:population":72
},
  "geometry": {"coordinates":[77.333893,24.567504],"type":"Point"}
}