{
  "type": "Feature",
  "properties": {
    "iso:country":"IN",
    "ks:ks_alt_nam":"WANDREWASTI",
    "ks:ks_name":"Wandrewasti",
    "ks:ks_pop":225,
    "ks:ks_type":"HABITATION",
    "name:eng_x_preferred":[
        "Wandrewasti"
    ],
    "wof:name":"Wandrewasti",
    "wof:placetype":"locality",
    "wof:population":225
},
  "geometry": {"coordinates":[74.780446,17.093143],"type":"Point"}
}