{
  "type": "Feature",
  "properties": {
    "iso:country":"IN",
    "ks:ks_name":"Anandamohanpur",
    "ks:ks_pop":1417,
    "ks:ks_type":"VILLAGE",
    "ks:ks_uagg_main":0,
    "name:eng_x_preferred":[
        "Anandamohanpur"
    ],
    "wof:name":"Anandamohanpur",
    "wof:placetype":"neighbourhood",
    "wof:population":1417
},
  "geometry": {"coordinates":[88.010243,25.031809],"type":"Point"}
}