{
  "type": "Feature",
  "properties": {
    "iso:country":"IN",
    "ks:ks_name":"Vesonvai",
    "ks:ks_pop":601,
    "ks:ks_type":"VILLAGE",
    "name:eng_x_preferred":[
        "Vesonvai"
    ],
    "wof:name":"Vesonvai",
    "wof:placetype":"locality",
    "wof:population":601
},
  "geometry": {"coordinates":[79.817025,18.945118],"type":"Point"}
}