{
  "type": "Feature",
  "properties": {
    "gn:admin1_code":"37",
    "gn:admin2_code":"406.0",
    "gn:asciiname":"Bidbida",
    "gn:country_code":"IN",
    "gn:dem":252,
    "gn:feature_class":"P",
    "gn:feature_code":"PPL",
    "gn:name":"Bidbida",
    "gn:population":0,
    "gn:timezone":"Asia/Kolkata",
    "iso:country":"IN",
    "wof:name":"Bidbida",
    "wof:placetype":"locality"
},
  "geometry": {"coordinates":[81.94161,21.91825],"type":"Point"}
}