{
  "type": "Feature",
  "properties": {
    "gn:admin1_code":"2.0",
    "gn:admin2_code":"544.0",
    "gn:asciiname":"Degalvidi",
    "gn:country_code":"IN",
    "gn:dem":1098,
    "gn:feature_class":"P",
    "gn:feature_code":"PPL",
    "gn:name":"Degalv\u012bdi",
    "gn:population":0,
    "gn:timezone":"Asia/Kolkata",
    "iso:country":"IN",
    "wof:name":"Degalvidi",
    "wof:placetype":"locality"
},
  "geometry": {"coordinates":[82.63266999999998,18.09242],"type":"Point"}
}