{
  "type": "Feature",
  "properties": {
    "iso:country":"IN",
    "ks:ks_name":"Lalmati",
    "ks:ks_pop":105,
    "ks:ks_type":"HABITATION",
    "name:eng_x_preferred":[
        "Lalmati"
    ],
    "wof:name":"Lalmati",
    "wof:placetype":"locality",
    "wof:population":105
},
  "geometry": {"coordinates":[93.68751899999999,25.94226],"type":"Point"}
}