{
  "type": "Feature",
  "properties": {
    "gn:admin1_code":"36.0",
    "gn:admin2_code":"166.0",
    "gn:asciiname":"Barampura",
    "gn:country_code":"IN",
    "gn:dem":175,
    "gn:feature_class":"P",
    "gn:feature_code":"PPL",
    "gn:name":"Barampura",
    "gn:population":0,
    "gn:timezone":"Asia/Kolkata",
    "iso:country":"IN",
    "wof:name":"Barampura",
    "wof:placetype":"locality"
},
  "geometry": {"coordinates":[79.11587,25.65739],"type":"Point"}
}