{
  "type": "Feature",
  "properties": {
    "gn:admin1_code":"16.0",
    "gn:admin2_code":"498.0",
    "gn:asciiname":"Arni",
    "gn:country_code":"IN",
    "gn:dem":237,
    "gn:feature_class":"P",
    "gn:feature_code":"PPL",
    "gn:name":"Arni",
    "gn:population":0,
    "gn:timezone":"Asia/Kolkata",
    "iso:country":"IN",
    "name:als_x_preferred":[
        "Arni"
    ],
    "name:ceb_x_preferred":[
        "Arni"
    ],
    "name:deu_x_preferred":[
        "Arni"
    ],
    "name:epo_x_preferred":[
        "Arni"
    ],
    "name:fra_x_preferred":[
        "Arni"
    ],
    "name:ita_x_preferred":[
        "Arni"
    ],
    "name:lmo_x_preferred":[
        "Arni"
    ],
    "name:nld_x_preferred":[
        "Arni"
    ],
    "name:pol_x_preferred":[
        "Arni"
    ],
    "name:por_x_preferred":[
        "Arni"
    ],
    "name:swe_x_preferred":[
        "Arni"
    ],
    "wof:name":"Arni",
    "wof:placetype":"locality"
},
  "geometry": {"coordinates":[74.84602,20.92886],"type":"Point"}
}