{
  "type": "Feature",
  "properties": {
    "iso:country":"IN",
    "ks:ks_name":"Sreegram VI",
    "ks:ks_pop":6817,
    "ks:ks_type":"VILLAGE",
    "name:eng_x_preferred":[
        "Sreegram VI"
    ],
    "wof:name":"Sreegram VI",
    "wof:placetype":"locality",
    "wof:population":6817
},
  "geometry": {"coordinates":[90.37011699999999,26.247926],"type":"Point"}
}