{
  "type": "Feature",
  "properties": {
    "gn:admin1_code":"34.0",
    "gn:admin2_code":"236.0",
    "gn:asciiname":"Mir Chak",
    "gn:country_code":"IN",
    "gn:dem":128,
    "gn:feature_class":"P",
    "gn:feature_code":"PPL",
    "gn:name":"M\u012br Chak",
    "gn:population":0,
    "gn:timezone":"Asia/Kolkata",
    "iso:country":"IN",
    "ks:ks_alt_nam":"M\u012br Chak",
    "ks:ks_name":"Mir Chak",
    "ks:ks_type":"VILLAGE",
    "ks:ks_uagg_main":0,
    "name:eng_x_preferred":[
        "Mir Chak"
    ],
    "name:eng_x_variant":[
        "M\u012br Chak"
    ],
    "wof:name":"Mir Chak",
    "wof:placetype":"neighbourhood"
},
  "geometry": {"coordinates":[84.769555,24.66578],"type":"Point"}
}