{
  "type": "Feature",
  "properties": {
    "iso:country":"IN",
    "ks:ks_name":"Badepotka",
    "ks:ks_pop":930,
    "ks:ks_type":"HABITATION",
    "name:eng_x_preferred":[
        "Badepotka"
    ],
    "wof:name":"Badepotka",
    "wof:placetype":"locality",
    "wof:population":930
},
  "geometry": {"coordinates":[86.201183,22.169914],"type":"Point"}
}