{
  "type": "Feature",
  "properties": {
    "iso:country":"IN",
    "ks:ks_name":"Thigalarapalya",
    "ks:ks_pop":75,
    "ks:ks_type":"HABITATION",
    "name:eng_x_preferred":[
        "Thigalarapalya"
    ],
    "wof:name":"Thigalarapalya",
    "wof:placetype":"locality",
    "wof:population":75
},
  "geometry": {"coordinates":[77.01381499999999,13.056759],"type":"Point"}
}