{
  "type": "Feature",
  "properties": {
    "iso:country":"IN",
    "ks:ks_name":"Goradamunda",
    "ks:ks_pop":166,
    "ks:ks_type":"VILLAGE",
    "name:eng_x_preferred":[
        "Goradamunda"
    ],
    "wof:name":"Goradamunda",
    "wof:placetype":"locality",
    "wof:population":166
},
  "geometry": {"coordinates":[84.625568,20.469718],"type":"Point"}
}