{
  "type": "Feature",
  "properties": {
    "gn:admin1_code":"25.0",
    "gn:admin2_code":"610.0",
    "gn:asciiname":"Selambakavundanpalaiyampudur",
    "gn:country_code":"IN",
    "gn:dem":198,
    "gn:feature_class":"P",
    "gn:feature_code":"PPL",
    "gn:name":"Selambakavundanp\u0101laiyampud\u016br",
    "gn:population":0,
    "gn:timezone":"Asia/Kolkata",
    "iso:country":"IN",
    "wof:name":"Selambakavundanpalaiyampudur",
    "wof:placetype":"neighbourhood"
},
  "geometry": {"coordinates":[77.66862,11.49709],"type":"Point"}
}