{
  "type": "Feature",
  "properties": {
    "gn:admin1_code":"36.0",
    "gn:admin2_code":"160",
    "gn:asciiname":"Kiratpur",
    "gn:country_code":"IN",
    "gn:dem":141,
    "gn:feature_class":"P",
    "gn:feature_code":"PPL",
    "gn:name":"K\u012bratpur",
    "gn:population":0,
    "gn:timezone":"Asia/Kolkata",
    "iso:country":"IN",
    "name:deu_x_preferred":[
        "Kiratpur"
    ],
    "wof:name":"Kiratpur",
    "wof:placetype":"locality"
},
  "geometry": {"coordinates":[79.77159,27.18833],"type":"Point"}
}