{
  "type": "Feature",
  "properties": {
    "iso:country":"IN",
    "ks:ks_name":"Doddagadde",
    "ks:ks_pop":32,
    "ks:ks_type":"HABITATION",
    "name:eng_x_preferred":[
        "Doddagadde"
    ],
    "wof:name":"Doddagadde",
    "wof:placetype":"locality",
    "wof:population":32
},
  "geometry": {"coordinates":[74.799261,14.296568],"type":"Point"}
}