{
  "type": "Feature",
  "properties": {
    "iso:country":"IN",
    "ks:ks_name":"Rajadih",
    "ks:ks_pop":228,
    "ks:ks_type":"VILLAGE",
    "name:eng_x_preferred":[
        "Rajadih"
    ],
    "wof:name":"Rajadih",
    "wof:placetype":"locality",
    "wof:population":228
},
  "geometry": {"coordinates":[86.953858,24.474143],"type":"Point"}
}