{
  "type": "Feature",
  "properties": {
    "gn:admin1_code":"24.0",
    "gn:admin2_code":"101",
    "gn:asciiname":"Hathusar",
    "gn:country_code":"IN",
    "gn:dem":183,
    "gn:feature_class":"P",
    "gn:feature_code":"PPL",
    "gn:name":"H\u0101thusar",
    "gn:population":0,
    "gn:timezone":"Asia/Kolkata",
    "iso:country":"IN",
    "wof:name":"Hathusar",
    "wof:placetype":"locality"
},
  "geometry": {"coordinates":[73.57311,28.94452],"type":"Point"}
}