{
  "type": "Feature",
  "properties": {
    "iso:country":"IN",
    "ks:ks_name":"Koothakulam",
    "ks:ks_pop":1018,
    "ks:ks_type":"HABITATION",
    "ks:ks_uagg_main":0,
    "name:eng_x_preferred":[
        "Koothakulam"
    ],
    "wof:name":"Koothakulam",
    "wof:placetype":"neighbourhood",
    "wof:population":1018
},
  "geometry": {"coordinates":[76.851646,9.425598],"type":"Point"}
}