{
  "type": "Feature",
  "properties": {
    "gn:admin1_code":"12.0",
    "gn:admin2_code":"021",
    "gn:asciiname":"Hasle Chak",
    "gn:country_code":"IN",
    "gn:dem":283,
    "gn:feature_class":"P",
    "gn:feature_code":"PPL",
    "gn:name":"H\u0101sle Chak",
    "gn:population":0,
    "gn:timezone":"Asia/Kolkata",
    "iso:country":"IN",
    "name:und_x_variant":[
        "H\u0101sle Chak",
        "Chak H\u0101sil"
    ],
    "wof:name":"Hasle Chak",
    "wof:placetype":"locality"
},
  "geometry": {"coordinates":[74.87054000000001,32.57204],"type":"Point"}
}