{
  "type": "Feature",
  "properties": {
    "iso:country":"IN",
    "ks:ks_alt_nam":"Jayan mukku",
    "ks:ks_name":"Jayan Mukku",
    "ks:ks_pop":987,
    "ks:ks_type":"HABITATION",
    "name:eng_x_preferred":[
        "Jayan Mukku"
    ],
    "wof:name":"Jayan Mukku",
    "wof:placetype":"locality",
    "wof:population":987
},
  "geometry": {"coordinates":[76.601367,8.943143],"type":"Point"}
}