{
  "type": "Feature",
  "properties": {
    "iso:country":"IN",
    "ks:ks_name":"Theha Jaura",
    "ks:ks_pop":587,
    "ks:ks_type":"HABITATION",
    "name:eng_x_preferred":[
        "Theha Jaura"
    ],
    "wof:name":"Theha Jaura",
    "wof:placetype":"locality",
    "wof:population":587
},
  "geometry": {"coordinates":[77.69618199999999,26.418326],"type":"Point"}
}