{
  "type": "Feature",
  "properties": {
    "gn:admin1_code":"13.0",
    "gn:admin2_code":"590.0",
    "gn:asciiname":"Nivalkolli",
    "gn:country_code":"IN",
    "gn:dem":793,
    "gn:feature_class":"P",
    "gn:feature_code":"PPL",
    "gn:name":"Nivalkolli",
    "gn:population":0,
    "gn:timezone":"Asia/Kolkata",
    "iso:country":"IN",
    "wof:name":"Nivalkolli",
    "wof:placetype":"locality"
},
  "geometry": {"coordinates":[76.19986,11.76396],"type":"Point"}
}