{
  "type": "Feature",
  "properties": {
    "iso:country":"IN",
    "ks:ks_alt_nam":"AWADHIYA TOLA",
    "ks:ks_name":"Awadhiya Tola",
    "ks:ks_pop":172,
    "ks:ks_type":"HABITATION",
    "ks:ks_uagg_main":0,
    "name:eng_x_preferred":[
        "Awadhiya Tola"
    ],
    "wof:name":"Awadhiya Tola",
    "wof:placetype":"neighbourhood",
    "wof:population":172
},
  "geometry": {"coordinates":[84.348332,26.471903],"type":"Point"}
}