{
  "type": "Feature",
  "properties": {
    "iso:country":"IN",
    "ks:ks_name":"Gopalapuram",
    "ks:ks_pop":89,
    "ks:ks_type":"HABITATION",
    "name:eng_x_preferred":[
        "Gopalapuram"
    ],
    "wof:name":"Gopalapuram",
    "wof:placetype":"locality",
    "wof:population":89
},
  "geometry": {"coordinates":[80.63346300000001,17.222092],"type":"Point"}
}