{
  "type": "Feature",
  "properties": {
    "iso:country":"IN",
    "ks:ks_name":"Palenja",
    "ks:ks_pop":400,
    "ks:ks_type":"HABITATION",
    "name:eng_x_preferred":[
        "Palenja"
    ],
    "wof:name":"Palenja",
    "wof:placetype":"locality",
    "wof:population":400
},
  "geometry": {"coordinates":[75.452383,12.884605],"type":"Point"}
}