{
  "type": "Feature",
  "properties": {
    "iso:country":"IN",
    "ks:ks_name":"Olibakaspur",
    "ks:ks_pop":150,
    "ks:ks_type":"HABITATION",
    "name:eng_x_preferred":[
        "Olibakaspur"
    ],
    "wof:name":"Olibakaspur",
    "wof:placetype":"locality",
    "wof:population":150
},
  "geometry": {"coordinates":[83.23097199999999,27.203781],"type":"Point"}
}