{
  "type": "Feature",
  "properties": {
    "iso:country":"IN",
    "ks:ks_name":"Mah Mara",
    "ks:ks_pop":400,
    "ks:ks_type":"VILLAGE",
    "name:eng_x_preferred":[
        "Mah Mara"
    ],
    "wof:name":"Mah Mara",
    "wof:placetype":"locality",
    "wof:population":400
},
  "geometry": {"coordinates":[92.94784300000001,26.711206],"type":"Point"}
}