{
  "type": "Feature",
  "properties": {
    "iso:country":"IN",
    "ks:ks_name":"Natua",
    "ks:ks_pop":511,
    "ks:ks_type":"VILLAGE",
    "name:eng_x_preferred":[
        "Natua"
    ],
    "wof:name":"Natua",
    "wof:placetype":"locality",
    "wof:population":511
},
  "geometry": {"coordinates":[86.341825,23.406548],"type":"Point"}
}