{
  "type": "Feature",
  "properties": {
    "iso:country":"IN",
    "ks:ks_name":"Odakapa",
    "ks:ks_pop":67,
    "ks:ks_type":"VILLAGE",
    "name:eng_x_preferred":[
        "Odakapa"
    ],
    "wof:name":"Odakapa",
    "wof:placetype":"locality",
    "wof:population":67
},
  "geometry": {"coordinates":[84.840301,20.056651],"type":"Point"}
}