{
  "type": "Feature",
  "properties": {
    "iso:country":"IN",
    "ks:ks_name":"Kadmal",
    "ks:ks_pop":823,
    "ks:ks_type":"VILLAGE",
    "name:eng_x_preferred":[
        "Kadmal"
    ],
    "wof:name":"Kadmal",
    "wof:placetype":"locality",
    "wof:population":823
},
  "geometry": {"coordinates":[73.889853,20.776995],"type":"Point"}
}