{
  "type": "Feature",
  "properties": {
    "iso:country":"IN",
    "ks:ks_name":"Ali Chak",
    "ks:ks_pop":700,
    "ks:ks_type":"HABITATION",
    "name:eng_x_preferred":[
        "Ali Chak"
    ],
    "wof:name":"Ali Chak",
    "wof:placetype":"neighbourhood",
    "wof:population":700
},
  "geometry": {"coordinates":[85.210396,25.567243],"type":"Point"}
}