{
  "type": "Feature",
  "properties": {
    "iso:country":"IN",
    "ks:ks_name":"Soding Laga Trikot",
    "ks:ks_pop":73,
    "ks:ks_type":"HABITATION",
    "name:eng_x_preferred":[
        "Soding Laga Trikot"
    ],
    "wof:name":"Soding Laga Trikot",
    "wof:placetype":"locality",
    "wof:population":73
},
  "geometry": {"coordinates":[79.580474,30.044601],"type":"Point"}
}