{
  "type": "Feature",
  "properties": {
    "iso:country":"IN",
    "ks:ks_name":"Devpura",
    "ks:ks_pop":123,
    "ks:ks_type":"HABITATION",
    "name:eng_x_preferred":[
        "Devpura"
    ],
    "wof:name":"Devpura",
    "wof:placetype":"locality",
    "wof:population":123
},
  "geometry": {"coordinates":[71.608542,24.132809],"type":"Point"}
}