{
  "type": "Feature",
  "properties": {
    "gn:admin1_code":"24.0",
    "gn:admin2_code":"123.0",
    "gn:asciiname":"Magtalao",
    "gn:country_code":"IN",
    "gn:dem":575,
    "gn:feature_class":"P",
    "gn:feature_code":"PPL",
    "gn:name":"Magtal\u0101o",
    "gn:population":0,
    "gn:timezone":"Asia/Kolkata",
    "iso:country":"IN",
    "wof:name":"Magtalao",
    "wof:placetype":"neighbourhood"
},
  "geometry": {"coordinates":[73.79244,24.78334],"type":"Point"}
}