{
  "type": "Feature",
  "properties": {
    "iso:country":"IN",
    "ks:ks_name":"Butrakachhar",
    "ks:ks_pop":178,
    "ks:ks_type":"VILLAGE",
    "name:eng_x_preferred":[
        "Butrakachhar"
    ],
    "wof:name":"Butrakachhar",
    "wof:placetype":"locality",
    "wof:population":178
},
  "geometry": {"coordinates":[83.634568,22.195535],"type":"Point"}
}