{
  "type": "Feature",
  "properties": {
    "gn:admin1_code":"23",
    "gn:admin2_code":"35.0",
    "gn:asciiname":"Balwanda",
    "gn:country_code":"IN",
    "gn:dem":244,
    "gn:feature_class":"P",
    "gn:feature_code":"PPL",
    "gn:name":"Balwanda",
    "gn:population":0,
    "gn:timezone":"Asia/Kolkata",
    "iso:country":"IN",
    "wof:name":"Balwanda",
    "wof:placetype":"locality"
},
  "geometry": {"coordinates":[75.51210999999998,31.91137],"type":"Point"}
}