{
  "type": "Feature",
  "properties": {
    "gn:admin1_code":"2.0",
    "gn:admin2_code":"542.0",
    "gn:asciiname":"Korlam",
    "gn:country_code":"IN",
    "gn:dem":117,
    "gn:feature_class":"P",
    "gn:feature_code":"PPL",
    "gn:name":"Korl\u0101m",
    "gn:population":0,
    "gn:timezone":"Asia/Kolkata",
    "iso:country":"IN",
    "name:tel_x_preferred":[
        "\u0c15\u0c4a\u0c30\u0c4d\u0c32\u0c02"
    ],
    "wof:name":"Korlam",
    "wof:placetype":"locality"
},
  "geometry": {"coordinates":[83.49597,18.37555],"type":"Point"}
}