{
  "type": "Feature",
  "properties": {
    "gn:admin1_code":"19.0",
    "gn:admin2_code":"581.0",
    "gn:asciiname":"Bethalli",
    "gn:country_code":"IN",
    "gn:dem":851,
    "gn:feature_class":"P",
    "gn:feature_code":"PPL",
    "gn:name":"Bethalli",
    "gn:population":0,
    "gn:timezone":"Asia/Kolkata",
    "iso:country":"IN",
    "ks:ks_name":"Bettahalli",
    "ks:ks_pop":347,
    "ks:ks_type":"VILLAGE",
    "ks:ks_uagg_main":0,
    "name:eng_x_preferred":[
        "Bettahalli"
    ],
    "wof:name":"Bettahalli",
    "wof:placetype":"neighbourhood",
    "wof:population":347
},
  "geometry": {"coordinates":[78.11349300000001,12.979719],"type":"Point"}
}