{
  "type": "Feature",
  "properties": {
    "iso:country":"IN",
    "qs:name":"Civil Aviation Colony",
    "qs:name_adm0":"India",
    "qs:name_adm1":"Delhi",
    "qs:photos":15,
    "qs:photos_1k":3,
    "qs:photos_9k":1,
    "qs:photos_9r":1,
    "qs:photos_all":15,
    "qs:photos_sr":1,
    "qs:placetype":"Suburb",
    "qs:pop_sr":"0",
    "wof:name":"Civil Aviation Colony",
    "wof:placetype":"neighbourhood"
},
  "geometry": {"coordinates":[77.21237499999999,28.583694],"type":"Point"}
}