{
  "type": "Feature",
  "properties": {
    "gn:admin1_code":"37",
    "gn:admin2_code":"403.0",
    "gn:asciiname":"Lamidarha",
    "gn:country_code":"IN",
    "gn:dem":227,
    "gn:feature_class":"P",
    "gn:feature_code":"PPL",
    "gn:name":"L\u0101midarha",
    "gn:population":0,
    "gn:timezone":"Asia/Kolkata",
    "iso:country":"IN",
    "ks:ks_alt_nam":"L\u0101midarha",
    "ks:ks_name":"Lamidarha",
    "ks:ks_type":"VILLAGE",
    "name:eng_x_preferred":[
        "Lamidarha"
    ],
    "name:eng_x_variant":[
        "L\u0101midarha"
    ],
    "wof:name":"Lamidarha",
    "wof:placetype":"locality"
},
  "geometry": {"coordinates":[83.414722,21.925603],"type":"Point"}
}