{
  "type": "Feature",
  "properties": {
    "iso:country":"IN",
    "ks:ks_name":"Nagla Jalalpur",
    "ks:ks_pop":386,
    "ks:ks_type":"HABITATION",
    "name:eng_x_preferred":[
        "Nagla Jalalpur"
    ],
    "wof:name":"Nagla Jalalpur",
    "wof:placetype":"locality",
    "wof:population":386
},
  "geometry": {"coordinates":[78.549483,27.113397],"type":"Point"}
}