{
  "type": "Feature",
  "properties": {
    "gn:admin1_code":"9.0",
    "gn:admin2_code":"493.0",
    "gn:asciiname":"Balda",
    "gn:country_code":"IN",
    "gn:dem":102,
    "gn:feature_class":"P",
    "gn:feature_code":"PPL",
    "gn:name":"B\u0101lda",
    "gn:population":0,
    "gn:timezone":"Asia/Kolkata",
    "iso:country":"IN",
    "ks:ks_name":"Balde",
    "ks:ks_pop":2237,
    "ks:ks_type":"VILLAGE",
    "name:eng_x_preferred":[
        "Balde"
    ],
    "name:eng_x_variant":[
        "Balda"
    ],
    "wof:name":"Balde",
    "wof:placetype":"locality",
    "wof:population":2237
},
  "geometry": {"coordinates":[74.250818,21.521278],"type":"Point"}
}