{
  "type": "Feature",
  "properties": {
    "iso:country":"IN",
    "ks:ks_name":"Bankita",
    "ks:ks_pop":197,
    "ks:ks_type":"VILLAGE",
    "name:eng_x_preferred":[
        "Bankita"
    ],
    "wof:name":"Bankita",
    "wof:placetype":"locality",
    "wof:population":197
},
  "geometry": {"coordinates":[84.65564999999999,23.872595],"type":"Point"}
}