{
  "type": "Feature",
  "properties": {
    "gn:admin1_code":"36",
    "gn:admin2_code":"140.0",
    "gn:asciiname":"Abidpur Karan",
    "gn:country_code":"IN",
    "gn:dem":203,
    "gn:feature_class":"P",
    "gn:feature_code":"PPL",
    "gn:name":"Abidpur Karan",
    "gn:population":0,
    "gn:timezone":"Asia/Kolkata",
    "iso:country":"IN",
    "wof:name":"Abidpur Karan",
    "wof:placetype":"locality"
},
  "geometry": {"coordinates":[78.10665999999998,28.80569],"type":"Point"}
}