{
  "type": "Feature",
  "properties": {
    "gn:admin1_code":"16",
    "gn:admin2_code":"499.0",
    "gn:asciiname":"Daregaon",
    "gn:country_code":"IN",
    "gn:dem":168,
    "gn:feature_class":"P",
    "gn:feature_code":"PPL",
    "gn:name":"Daregaon",
    "gn:population":0,
    "gn:timezone":"Asia/Kolkata",
    "iso:country":"IN",
    "wof:name":"Daregaon",
    "wof:placetype":"locality"
},
  "geometry": {"coordinates":[75.06429,21.1134],"type":"Point"}
}