{
  "type": "Feature",
  "properties": {
    "iso:country":"IN",
    "ks:ks_name":"Ainlapali",
    "ks:ks_pop":112,
    "ks:ks_type":"HABITATION",
    "name:eng_x_preferred":[
        "Ainlapali"
    ],
    "wof:name":"Ainlapali",
    "wof:placetype":"locality",
    "wof:population":112
},
  "geometry": {"coordinates":[82.934545,20.522079],"type":"Point"}
}