{
  "type": "Feature",
  "properties": {
    "iso:country":"IN",
    "ks:ks_name":"Edayarembethi",
    "ks:ks_pop":886,
    "ks:ks_type":"VILLAGE",
    "ks:ks_uagg_main":0,
    "name:eng_x_preferred":[
        "Edayarembethi"
    ],
    "wof:name":"Edayarembethi",
    "wof:placetype":"neighbourhood",
    "wof:population":886
},
  "geometry": {"coordinates":[79.409195,10.676645],"type":"Point"}
}