{
  "type": "Feature",
  "properties": {
    "iso:country":"IN",
    "ks:ks_name":"Deepawatnagar",
    "ks:ks_pop":455,
    "ks:ks_type":"HABITATION",
    "name:eng_x_preferred":[
        "Deepawatnagar"
    ],
    "wof:name":"Deepawatnagar",
    "wof:placetype":"locality",
    "wof:population":455
},
  "geometry": {"coordinates":[72.488981,26.909398],"type":"Point"}
}