{
  "type": "Feature",
  "properties": {
    "iso:country":"IN",
    "ks:ks_name":"Muthyalapalli",
    "ks:ks_pop":75,
    "ks:ks_type":"HABITATION",
    "name:eng_x_preferred":[
        "Muthyalapalli"
    ],
    "wof:name":"Muthyalapalli",
    "wof:placetype":"locality",
    "wof:population":75
},
  "geometry": {"coordinates":[78.263842,12.847318],"type":"Point"}
}