{
  "type": "Feature",
  "properties": {
    "gn:admin1_code":"36.0",
    "gn:admin2_code":"177.0",
    "gn:asciiname":"Kabirapur Gujar",
    "gn:country_code":"IN",
    "gn:dem":109,
    "gn:feature_class":"P",
    "gn:feature_code":"PPL",
    "gn:name":"Kab\u012br\u0101pur G\u016bjar",
    "gn:population":0,
    "gn:timezone":"Asia/Kolkata",
    "iso:country":"IN",
    "wof:name":"Kabirapur Gujar",
    "wof:placetype":"neighbourhood"
},
  "geometry": {"coordinates":[81.81152,26.7525],"type":"Point"}
}