{
  "type": "Feature",
  "properties": {
    "iso:country":"IN",
    "ks:ks_name":"Raghunathpura",
    "ks:ks_pop":601,
    "ks:ks_type":"VILLAGE",
    "ks:ks_uagg_main":0,
    "name:eng_x_preferred":[
        "Raghunathpura"
    ],
    "wof:name":"Raghunathpura",
    "wof:placetype":"neighbourhood",
    "wof:population":601
},
  "geometry": {"coordinates":[75.360528,28.062444],"type":"Point"}
}