{
  "type": "Feature",
  "properties": {
    "iso:country":"IN",
    "ks:ks_name":"Bandapara",
    "ks:ks_pop":141,
    "ks:ks_type":"HABITATION",
    "name:eng_x_preferred":[
        "Bandapara"
    ],
    "wof:name":"Bandapara",
    "wof:placetype":"locality",
    "wof:population":141
},
  "geometry": {"coordinates":[81.840221,19.07048],"type":"Point"}
}