{
  "type": "Feature",
  "properties": {
    "iso:country":"IN",
    "ks:ks_name":"Abbi",
    "ks:ks_pop":68,
    "ks:ks_type":"HABITATION",
    "name:eng_x_preferred":[
        "Abbi"
    ],
    "wof:name":"Abbi",
    "wof:placetype":"locality",
    "wof:population":68
},
  "geometry": {"coordinates":[74.511512,14.464253],"type":"Point"}
}