{
  "type": "Feature",
  "properties": {
    "iso:country":"IN",
    "ks:ks_alt_nam":"Mandir FA",
    "ks:ks_name":"Mandir Fa",
    "ks:ks_pop":185,
    "ks:ks_type":"HABITATION",
    "name:eng_x_preferred":[
        "Mandir Fa"
    ],
    "wof:name":"Mandir Fa",
    "wof:placetype":"locality",
    "wof:population":185
},
  "geometry": {"coordinates":[73.033787,20.517928],"type":"Point"}
}