{
  "type": "Feature",
  "properties": {
    "iso:country":"IN",
    "ks:ks_name":"Malkapur",
    "ks:ks_pop":20,
    "ks:ks_type":"HABITATION",
    "name:eng_x_preferred":[
        "Malkapur"
    ],
    "name:hin_x_preferred":[
        "\u092e\u0932\u094d\u0915\u093e\u092a\u0941\u0930"
    ],
    "name:mar_x_preferred":[
        "\u092e\u0932\u0915\u093e\u092a\u0942\u0930"
    ],
    "wof:name":"Malkapur",
    "wof:placetype":"locality",
    "wof:population":20
},
  "geometry": {"coordinates":[77.89932399999999,21.339869],"type":"Point"}
}