{
  "type": "Feature",
  "properties": {
    "gn:admin1_code":"19.0",
    "gn:admin2_code":"577.0",
    "gn:asciiname":"Kogilvadi",
    "gn:country_code":"IN",
    "gn:dem":901,
    "gn:feature_class":"P",
    "gn:feature_code":"PPL",
    "gn:name":"Kogilvadi",
    "gn:population":0,
    "gn:timezone":"Asia/Kolkata",
    "iso:country":"IN",
    "wof:name":"Kogilvadi",
    "wof:placetype":"locality"
},
  "geometry": {"coordinates":[76.03963,12.30098],"type":"Point"}
}