{
  "type": "Feature",
  "properties": {
    "gn:admin1_code":"36",
    "gn:admin2_code":"143.0",
    "gn:asciiname":"Nagla Khub",
    "gn:country_code":"IN",
    "gn:dem":196,
    "gn:feature_class":"P",
    "gn:feature_code":"PPL",
    "gn:name":"Nagla Kh\u016bb",
    "gn:population":0,
    "gn:timezone":"Asia/Kolkata",
    "iso:country":"IN",
    "name:und_x_variant":[
        "Nagla Kh\u016bb",
        "Kaly\u0101npur"
    ],
    "wof:name":"Nagla Khub",
    "wof:placetype":"locality"
},
  "geometry": {"coordinates":[77.80119999999999,28.07695],"type":"Point"}
}