{
  "type": "Feature",
  "properties": {
    "gn:admin1_code":"12.0",
    "gn:admin2_code":"010",
    "gn:asciiname":"Haran",
    "gn:country_code":"IN",
    "gn:dem":1586,
    "gn:feature_class":"P",
    "gn:feature_code":"PPL",
    "gn:name":"Haran",
    "gn:population":0,
    "gn:timezone":"Asia/Kolkata",
    "iso:country":"IN",
    "name:ara_x_preferred":[
        "\u0647\u0627\u0631\u0627\u0646"
    ],
    "name:cat_x_preferred":[
        "Oasi d'Haran"
    ],
    "name:ces_x_preferred":[
        "H\u00e1ran"
    ],
    "name:dan_x_preferred":[
        "Haran"
    ],
    "name:deu_x_preferred":[
        "Haran"
    ],
    "name:fra_x_preferred":[
        "Haran"
    ],
    "name:heb_x_preferred":[
        "\u05d4\u05e8\u05df"
    ],
    "name:ind_x_preferred":[
        "Haran"
    ],
    "name:nld_x_preferred":[
        "Haran"
    ],
    "name:nor_x_preferred":[
        "Haran"
    ],
    "name:pol_x_preferred":[
        "Haran"
    ],
    "name:ron_x_preferred":[
        "Haran"
    ],
    "name:rus_x_preferred":[
        "\u0410\u0440\u0430\u043d"
    ],
    "name:spa_x_preferred":[
        "Har\u00e1n"
    ],
    "name:ukr_x_preferred":[
        "\u0413\u0430\u0440\u0430\u043d"
    ],
    "wof:name":"Haran",
    "wof:placetype":"locality"
},
  "geometry": {"coordinates":[74.76392,34.18694],"type":"Point"}
}