{
  "type": "Feature",
  "properties": {
    "iso:country":"IN",
    "ks:ks_alt_nam":"hamregaon suba",
    "ks:ks_name":"Hamregaon Suba",
    "ks:ks_pop":222,
    "ks:ks_type":"HABITATION",
    "ks:ks_uagg_main":0,
    "name:eng_x_preferred":[
        "Hamregaon Suba"
    ],
    "wof:name":"Hamregaon Suba",
    "wof:placetype":"neighbourhood",
    "wof:population":222
},
  "geometry": {"coordinates":[91.691215,26.303683],"type":"Point"}
}