{
  "type": "Feature",
  "properties": {
    "gn:admin1_code":"37",
    "gn:admin2_code":"406.0",
    "gn:asciiname":"Temri",
    "gn:country_code":"IN",
    "gn:dem":283,
    "gn:feature_class":"P",
    "gn:feature_code":"PPL",
    "gn:name":"Temri",
    "gn:population":0,
    "gn:timezone":"Asia/Kolkata",
    "iso:country":"IN",
    "name:ori_x_preferred":[
        "\u0b1f\u0b47\u0b2e\u0b30\u0b3f"
    ],
    "wof:name":"Temri",
    "wof:placetype":"locality"
},
  "geometry": {"coordinates":[81.65427,22.00956],"type":"Point"}
}