{
  "type": "Feature",
  "properties": {
    "iso:country":"IN",
    "ks:ks_alt_nam":"UJAN TARAPADA BARI",
    "ks:ks_name":"Ujan Tarapada Bari",
    "ks:ks_pop":460,
    "ks:ks_type":"HABITATION",
    "name:eng_x_preferred":[
        "Ujan Tarapada Bari"
    ],
    "wof:name":"Ujan Tarapada Bari",
    "wof:placetype":"locality",
    "wof:population":460
},
  "geometry": {"coordinates":[91.398472,23.618212],"type":"Point"}
}