{
  "type": "Feature",
  "properties": {
    "iso:country":"IN",
    "ks:ks_name":"Mukavale",
    "ks:ks_pop":270,
    "ks:ks_type":"VILLAGE",
    "name:eng_x_preferred":[
        "Mukavale"
    ],
    "wof:name":"Mukavale",
    "wof:placetype":"locality",
    "wof:population":270
},
  "geometry": {"coordinates":[73.7418,17.886993],"type":"Point"}
}