{
  "type": "Feature",
  "properties": {
    "iso:country":"IN",
    "ks:ks_name":"Kukupangi",
    "ks:ks_pop":239,
    "ks:ks_type":"VILLAGE",
    "name:eng_x_preferred":[
        "Kukupangi"
    ],
    "wof:name":"Kukupangi",
    "wof:placetype":"locality",
    "wof:population":239
},
  "geometry": {"coordinates":[85.27225300000001,20.604744],"type":"Point"}
}