{
  "type": "Feature",
  "properties": {
    "iso:country":"IN",
    "ks:ks_name":"Jathipatiagaon",
    "ks:ks_pop":332,
    "ks:ks_type":"VILLAGE",
    "name:eng_x_preferred":[
        "Jathipatiagaon"
    ],
    "wof:name":"Jathipatiagaon",
    "wof:placetype":"locality",
    "wof:population":332
},
  "geometry": {"coordinates":[94.71921399999999,26.957388],"type":"Point"}
}