{
  "type": "Feature",
  "properties": {
    "iso:country":"IN",
    "ks:ks_name":"Oramtola",
    "ks:ks_pop":200,
    "ks:ks_type":"HABITATION",
    "name:eng_x_preferred":[
        "Oramtola"
    ],
    "wof:name":"Oramtola",
    "wof:placetype":"locality",
    "wof:population":200
},
  "geometry": {"coordinates":[85.078992,22.289987],"type":"Point"}
}