{
  "type": "Feature",
  "properties": {
    "gn:admin1_code":"19.0",
    "gn:admin2_code":"570.0",
    "gn:asciiname":"Kunchur",
    "gn:country_code":"IN",
    "gn:dem":676,
    "gn:feature_class":"P",
    "gn:feature_code":"PPL",
    "gn:name":"Kunch\u016br",
    "gn:population":0,
    "gn:timezone":"Asia/Kolkata",
    "iso:country":"IN",
    "ks:ks_alt_nam":"Kunch\u016br",
    "ks:ks_name":"Kunchur",
    "ks:ks_pop":139,
    "ks:ks_type":"VILLAGE",
    "name:eng_x_preferred":[
        "Kunchur"
    ],
    "name:eng_x_variant":[
        "Kunch\u016br"
    ],
    "wof:name":"Kunchur",
    "wof:placetype":"locality",
    "wof:population":139
},
  "geometry": {"coordinates":[75.33095,13.50759],"type":"Point"}
}