{
  "type": "Feature",
  "properties": {
    "iso:country":"IN",
    "ks:ks_name":"Mamatha Colony",
    "ks:ks_pop":110,
    "ks:ks_type":"HABITATION",
    "name:eng_x_preferred":[
        "Mamatha Colony"
    ],
    "wof:name":"Mamatha Colony",
    "wof:placetype":"locality",
    "wof:population":110
},
  "geometry": {"coordinates":[76.083611,12.159167],"type":"Point"}
}