{
  "type": "Feature",
  "properties": {
    "gn:admin1_code":"19.0",
    "gn:admin2_code":"562.0",
    "gn:asciiname":"Hanmanhal",
    "gn:country_code":"IN",
    "gn:dem":635,
    "gn:feature_class":"P",
    "gn:feature_code":"PPL",
    "gn:name":"Hanm\u0101nh\u0101l",
    "gn:population":0,
    "gn:timezone":"Asia/Kolkata",
    "iso:country":"IN",
    "wof:name":"Hanmanhal",
    "wof:placetype":"locality"
},
  "geometry": {"coordinates":[75.01578000000001,15.62207],"type":"Point"}
}