{
  "type": "Feature",
  "properties": {
    "iso:country":"IN",
    "ks:ks_alt_nam":"THORAT WASTI",
    "ks:ks_name":"Thorat Wasti",
    "ks:ks_pop":208,
    "ks:ks_type":"HABITATION",
    "name:eng_x_preferred":[
        "Thorat Wasti"
    ],
    "wof:name":"Thorat Wasti",
    "wof:placetype":"locality",
    "wof:population":208
},
  "geometry": {"coordinates":[74.93622499999999,18.442045],"type":"Point"}
}