{
  "type": "Feature",
  "properties": {
    "iso:country":"IN",
    "name:ast_x_preferred":[
        "Mlappara"
    ],
    "name:eng_x_preferred":[
        "Mlappara"
    ],
    "name:nld_x_preferred":[
        "Mlappara"
    ],
    "qs:name":"Mlappara",
    "qs:name_adm0":"India",
    "qs:name_adm1":"Kerala",
    "qs:photos":41,
    "qs:photos_1k":8,
    "qs:photos_9k":1,
    "qs:photos_9r":2,
    "qs:photos_all":41,
    "qs:photos_sr":2,
    "qs:placetype":"Town",
    "qs:pop_sr":"0",
    "wd:wordcount":33,
    "wof:name":"Mlappara",
    "wof:placetype":"locality"
},
  "geometry": {"coordinates":[77.159516,9.440277],"type":"Point"}
}