{
  "type": "Feature",
  "properties": {
    "gn:admin1_code":"13.0",
    "gn:admin2_code":"591.0",
    "gn:asciiname":"Palangod",
    "gn:country_code":"IN",
    "gn:dem":58,
    "gn:feature_class":"P",
    "gn:feature_code":"PPL",
    "gn:name":"P\u0101lang\u014dd",
    "gn:population":0,
    "gn:timezone":"Asia/Kolkata",
    "iso:country":"IN",
    "wof:name":"Palangod",
    "wof:placetype":"locality"
},
  "geometry": {"coordinates":[75.86610999999998,11.40085],"type":"Point"}
}