{
  "type": "Feature",
  "properties": {
    "iso:country":"IN",
    "ks:ks_name":"Baghail",
    "ks:ks_pop":145,
    "ks:ks_type":"VILLAGE",
    "name:eng_x_preferred":[
        "Baghail"
    ],
    "wof:name":"Baghail",
    "wof:placetype":"locality",
    "wof:population":145
},
  "geometry": {"coordinates":[82.10263500000001,23.575242],"type":"Point"}
}