{
  "type": "Feature",
  "properties": {
    "iso:country":"IN",
    "ks:ks_name":"Palleri",
    "ks:ks_pop":32,
    "ks:ks_type":"HABITATION",
    "name:eng_x_preferred":[
        "Palleri"
    ],
    "wof:name":"Palleri",
    "wof:placetype":"locality",
    "wof:population":32
},
  "geometry": {"coordinates":[76.02416700000001,12.023333],"type":"Point"}
}