{
  "type": "Feature",
  "properties": {
    "gn:admin1_code":"34.0",
    "gn:admin2_code":"219.0",
    "gn:asciiname":"Mirpur Jaura",
    "gn:country_code":"IN",
    "gn:dem":57,
    "gn:feature_class":"P",
    "gn:feature_code":"PPL",
    "gn:name":"M\u012brpur Jaura",
    "gn:population":0,
    "gn:timezone":"Asia/Kolkata",
    "iso:country":"IN",
    "ks:ks_name":"Mirpur Juara",
    "ks:ks_pop":500,
    "ks:ks_type":"VILLAGE",
    "name:eng_x_preferred":[
        "Mirpur Juara"
    ],
    "name:eng_x_variant":[
        "Mirpur Jaura"
    ],
    "wof:name":"Mirpur Juara",
    "wof:placetype":"locality",
    "wof:population":500
},
  "geometry": {"coordinates":[84.86263099999999,25.752323],"type":"Point"}
}