{
  "type": "Feature",
  "properties": {
    "iso:country":"IN",
    "ks:ks_name":"Vaisserikal",
    "ks:ks_pop":389,
    "ks:ks_type":"HABITATION",
    "name:eng_x_preferred":[
        "Vaisserikal"
    ],
    "wof:name":"Vaisserikal",
    "wof:placetype":"locality",
    "wof:population":389
},
  "geometry": {"coordinates":[75.989859,11.473343],"type":"Point"}
}