{
  "type": "Feature",
  "properties": {
    "gn:admin1_code":"25.0",
    "gn:admin2_code":"614.0",
    "gn:asciiname":"Thuraiyur",
    "gn:country_code":"IN",
    "gn:dem":145,
    "gn:feature_class":"P",
    "gn:feature_code":"PPL",
    "gn:name":"Thuraiyur",
    "gn:population":0,
    "gn:timezone":"Asia/Kolkata",
    "iso:country":"IN",
    "wof:name":"Thuraiyur",
    "wof:placetype":"locality"
},
  "geometry": {"coordinates":[78.59911,11.14805],"type":"Point"}
}