{
  "type": "Feature",
  "properties": {
    "iso:country":"IN",
    "ks:ks_alt_nam":"thencodu",
    "ks:ks_name":"Thencodu",
    "ks:ks_pop":1200,
    "ks:ks_type":"HABITATION",
    "ks:ks_uagg_main":0,
    "name:eng_x_preferred":[
        "Thencodu"
    ],
    "wof:name":"Thencodu",
    "wof:placetype":"neighbourhood",
    "wof:population":1200
},
  "geometry": {"coordinates":[76.708077,10.006548],"type":"Point"}
}