{
  "type": "Feature",
  "properties": {
    "iso:country":"IN",
    "ks:ks_name":"Ashly Estate Jn.",
    "ks:ks_pop":965,
    "ks:ks_type":"HABITATION",
    "name:eng_x_preferred":[
        "Ashly Estate Jn."
    ],
    "wof:name":"Ashly Estate Jn.",
    "wof:placetype":"locality",
    "wof:population":965
},
  "geometry": {"coordinates":[76.968581,9.591679],"type":"Point"}
}