{
  "type": "Feature",
  "properties": {
    "gn:country":"IN",
    "gn:fcode":"PPL",
    "gn:pop":19903,
    "iso:country":"IN",
    "name:ben_x_preferred":[
        "\u09b8\u09be\u0993\u09af\u09bc\u09be\u09a6\u09be"
    ],
    "name:bpy_x_preferred":[
        "\u09b8\u09be\u09f1\u09be\u09a6\u09be"
    ],
    "name:eng_x_preferred":[
        "Savda"
    ],
    "name:fra_x_preferred":[
        "Savda"
    ],
    "name:ita_x_preferred":[
        "Savda"
    ],
    "name:msa_x_preferred":[
        "Savda"
    ],
    "name:nan_x_preferred":[
        "Savda"
    ],
    "name:nld_x_preferred":[
        "Savda"
    ],
    "name:por_x_preferred":[
        "Savda"
    ],
    "name:swe_x_preferred":[
        "S\u0101vda"
    ],
    "name:unk_x_variant":[
        "S\u0101vda"
    ],
    "name:urd_x_preferred":[
        "\u0633\u0627\u0648\u0688\u0627"
    ],
    "name:vie_x_preferred":[
        "Savda"
    ],
    "name:zho_x_preferred":[
        "\u8428\u6c83\u8fbe"
    ],
    "qs:name":"Savda",
    "qs:name_adm0":"India",
    "qs:name_adm1":"Maharashtra",
    "qs:photos_9r":0,
    "qs:photos_sr":0,
    "qs:placetype":"Town",
    "qs:pop_sr":"6",
    "wd:wordcount":155,
    "wof:name":"Savda",
    "wof:placetype":"locality",
    "wof:population":19903
},
  "geometry": {"coordinates":[75.88898,21.15035],"type":"Point"}
}