{
  "type": "Feature",
  "properties": {
    "iso:country":"IN",
    "ks:ks_alt_nam":"MALI WASTI",
    "ks:ks_name":"Mali Wasti",
    "ks:ks_pop":142,
    "ks:ks_type":"HABITATION",
    "name:eng_x_preferred":[
        "Mali Wasti"
    ],
    "wof:name":"Mali Wasti",
    "wof:placetype":"locality",
    "wof:population":142
},
  "geometry": {"coordinates":[74.89304,16.991828],"type":"Point"}
}