{
  "type": "Feature",
  "properties": {
    "gn:admin1_code":"36",
    "gn:admin2_code":"194.0",
    "gn:asciiname":"Dipapur",
    "gn:country_code":"IN",
    "gn:dem":86,
    "gn:feature_class":"P",
    "gn:feature_code":"PPL",
    "gn:name":"D\u012bp\u0101pur",
    "gn:population":0,
    "gn:timezone":"Asia/Kolkata",
    "iso:country":"IN",
    "ks:ks_name":"Dipapur",
    "ks:ks_pop":1873,
    "ks:ks_type":"VILLAGE",
    "name:eng_x_preferred":[
        "Dipapur"
    ],
    "wof:name":"Dipapur",
    "wof:placetype":"locality",
    "wof:population":1873
},
  "geometry": {"coordinates":[82.713273,25.538139],"type":"Point"}
}