{
  "type": "Feature",
  "properties": {
    "gn:admin1_code":"2.0",
    "gn:admin2_code":"550.0",
    "gn:asciiname":"Narasimhakhandrika",
    "gn:country_code":"IN",
    "gn:dem":65,
    "gn:feature_class":"P",
    "gn:feature_code":"PPL",
    "gn:name":"Narasimhakhandrika",
    "gn:population":0,
    "gn:timezone":"Asia/Kolkata",
    "iso:country":"IN",
    "name:und_x_variant":[
        "M\u0101lapalli"
    ],
    "wof:name":"Narasimhakhandrika",
    "wof:placetype":"locality"
},
  "geometry": {"coordinates":[79.72462,14.41501],"type":"Point"}
}