{
  "type": "Feature",
  "properties": {
    "iso:country":"IN",
    "ks:ks_name":"Echavadi",
    "ks:ks_pop":114,
    "ks:ks_type":"VILLAGE",
    "name:eng_x_preferred":[
        "Echavadi"
    ],
    "wof:name":"Echavadi",
    "wof:placetype":"locality",
    "wof:population":114
},
  "geometry": {"coordinates":[75.508476,13.886214],"type":"Point"}
}