{
  "type": "Feature",
  "properties": {
    "iso:country":"IN",
    "ks:ks_alt_nam":"Bautin\u0101li",
    "ks:ks_name":"Bautinali",
    "ks:ks_type":"VILLAGE",
    "name:eng_x_preferred":[
        "Bautinali"
    ],
    "name:eng_x_variant":[
        "Bautin\u0101li"
    ],
    "wof:name":"Bautinali",
    "wof:placetype":"locality"
},
  "geometry": {"coordinates":[85.29447999999999,21.069661],"type":"Point"}
}