{
  "type": "Feature",
  "properties": {
    "gn:admin1_code":"23.0",
    "gn:admin2_code":"50.0",
    "gn:asciiname":"Muse",
    "gn:country_code":"IN",
    "gn:dem":222,
    "gn:feature_class":"P",
    "gn:feature_code":"PPL",
    "gn:name":"M\u016bse",
    "gn:population":0,
    "gn:timezone":"Asia/Kolkata",
    "iso:country":"IN",
    "wof:name":"Muse",
    "wof:placetype":"locality"
},
  "geometry": {"coordinates":[74.75345,31.43093],"type":"Point"}
}