{
  "type": "Feature",
  "properties": {
    "gn:admin1_code":"36",
    "gn:admin2_code":"159.0",
    "gn:asciiname":"Hosanka Shah Alampur",
    "gn:country_code":"IN",
    "gn:dem":159,
    "gn:feature_class":"P",
    "gn:feature_code":"PPL",
    "gn:name":"Hosanka Sh\u0101h \u0100lampur",
    "gn:population":0,
    "gn:timezone":"Asia/Kolkata",
    "iso:country":"IN",
    "wof:name":"Hosanka Shah Alampur",
    "wof:placetype":"locality"
},
  "geometry": {"coordinates":[79.26819,27.56236],"type":"Point"}
}