{
  "type": "Feature",
  "properties": {
    "iso:country":"IN",
    "ks:ks_name":"Dhaneswer Ganj",
    "ks:ks_pop":50,
    "ks:ks_type":"HABITATION",
    "name:eng_x_preferred":[
        "Dhaneswer Ganj"
    ],
    "wof:name":"Dhaneswer Ganj",
    "wof:placetype":"locality",
    "wof:population":50
},
  "geometry": {"coordinates":[82.25201800000001,27.300793],"type":"Point"}
}