{
  "type": "Feature",
  "properties": {
    "iso:country":"IN",
    "ks:ks_name":"Babara",
    "ks:ks_pop":390,
    "ks:ks_type":"VILLAGE",
    "ks:ks_uagg_main":0,
    "name:eng_x_preferred":[
        "Babara"
    ],
    "wof:name":"Babara",
    "wof:placetype":"neighbourhood",
    "wof:population":390
},
  "geometry": {"coordinates":[86.648529,20.484649],"type":"Point"}
}