{
  "type": "Feature",
  "properties": {
    "iso:country":"IN",
    "ks:ks_name":"North Saragaon",
    "ks:ks_pop":1118,
    "ks:ks_type":"HABITATION",
    "name:eng_x_preferred":[
        "North Saragaon"
    ],
    "wof:name":"North Saragaon",
    "wof:placetype":"locality",
    "wof:population":1118
},
  "geometry": {"coordinates":[92.55827600000001,26.25565],"type":"Point"}
}