{
  "type": "Feature",
  "properties": {
    "iso:country":"IN",
    "ks:ks_name":"Bhualmaran",
    "ks:ks_pop":0,
    "ks:ks_type":"VILLAGE",
    "name:eng_x_preferred":[
        "Bhualmaran"
    ],
    "wof:name":"Bhualmaran",
    "wof:placetype":"locality",
    "wof:population":0
},
  "geometry": {"coordinates":[85.862506,24.645856],"type":"Point"}
}