{
  "type": "Feature",
  "properties": {
    "gn:admin1_code":"10.0",
    "gn:admin2_code":"070",
    "gn:asciiname":"Kangwal",
    "gn:country_code":"IN",
    "gn:dem":253,
    "gn:feature_class":"P",
    "gn:feature_code":"PPL",
    "gn:name":"Kangw\u0101l",
    "gn:population":0,
    "gn:timezone":"Asia/Kolkata",
    "iso:country":"IN",
    "wof:name":"Kangwal",
    "wof:placetype":"locality"
},
  "geometry": {"coordinates":[76.63379999999999,30.13887],"type":"Point"}
}