{
  "type": "Feature",
  "properties": {
    "iso:country":"IN",
    "ks:ks_name":"Satamaska",
    "ks:ks_pop":158,
    "ks:ks_type":"VILLAGE",
    "name:eng_x_preferred":[
        "Satamaska"
    ],
    "wof:name":"Satamaska",
    "wof:placetype":"locality",
    "wof:population":158
},
  "geometry": {"coordinates":[83.789833,20.230197],"type":"Point"}
}