{
  "type": "Feature",
  "properties": {
    "gn:admin1_code":"19.0",
    "gn:admin2_code":"570.0",
    "gn:asciiname":"Bhuvanakote",
    "gn:country_code":"IN",
    "gn:dem":662,
    "gn:feature_class":"P",
    "gn:feature_code":"PPL",
    "gn:name":"Bhuvanakote",
    "gn:population":0,
    "gn:timezone":"Asia/Kolkata",
    "iso:country":"IN",
    "ks:ks_name":"Bhuyanakote",
    "ks:ks_pop":1057,
    "ks:ks_type":"VILLAGE",
    "name:eng_x_preferred":[
        "Bhuyanakote"
    ],
    "name:eng_x_variant":[
        "Bhuvanakote"
    ],
    "wof:name":"Bhuyanakote",
    "wof:placetype":"locality",
    "wof:population":1057
},
  "geometry": {"coordinates":[75.33340200000001,13.452362],"type":"Point"}
}