{
  "type": "Feature",
  "properties": {
    "gn:admin1_code":"25.0",
    "gn:admin2_code":"633.0",
    "gn:asciiname":"Kurumalal",
    "gn:country_code":"IN",
    "gn:dem":1010,
    "gn:feature_class":"P",
    "gn:feature_code":"PPL",
    "gn:name":"Kurumalal",
    "gn:population":0,
    "gn:timezone":"Asia/Kolkata",
    "iso:country":"IN",
    "wof:name":"Kurumalal",
    "wof:placetype":"locality"
},
  "geometry": {"coordinates":[77.13136999999998,10.4287],"type":"Point"}
}