{
  "type": "Feature",
  "properties": {
    "gn:admin1_code":"36",
    "gn:admin2_code":"169.0",
    "gn:asciiname":"Ilahi Purwa",
    "gn:country_code":"IN",
    "gn:dem":133,
    "gn:feature_class":"P",
    "gn:feature_code":"PPL",
    "gn:name":"Il\u0101hi Purwa",
    "gn:population":0,
    "gn:timezone":"Asia/Kolkata",
    "iso:country":"IN",
    "ks:ks_name":"Ilahipurwa",
    "ks:ks_pop":1221,
    "ks:ks_type":"HABITATION",
    "name:eng_x_preferred":[
        "Ilahipurwa"
    ],
    "name:eng_x_variant":[
        "Ilahi Purwa"
    ],
    "wof:name":"Ilahipurwa",
    "wof:placetype":"locality",
    "wof:population":1221
},
  "geometry": {"coordinates":[80.008977,25.586769],"type":"Point"}
}