{
  "type": "Feature",
  "properties": {
    "gn:admin1_code":"23",
    "gn:admin2_code":"51.0",
    "gn:asciiname":"Jhinjri",
    "gn:country_code":"IN",
    "gn:dem":288,
    "gn:feature_class":"P",
    "gn:feature_code":"PPL",
    "gn:name":"Jhinjri",
    "gn:population":0,
    "gn:timezone":"Asia/Kolkata",
    "iso:country":"IN",
    "ks:ks_name":"Jhinjri",
    "ks:ks_pop":446,
    "ks:ks_type":"VILLAGE",
    "ks:ks_uagg_main":0,
    "name:eng_x_preferred":[
        "Jhinjri"
    ],
    "wof:name":"Jhinjri",
    "wof:placetype":"neighbourhood",
    "wof:population":446
},
  "geometry": {"coordinates":[76.49691199999999,31.177555],"type":"Point"}
}