{
  "type": "Feature",
  "properties": {
    "iso:country":"IN",
    "ks:ks_name":"Taharpur",
    "ks:ks_pop":1,
    "ks:ks_type":"VILLAGE",
    "name:eng_x_preferred":[
        "Taharpur"
    ],
    "wof:name":"Taharpur",
    "wof:placetype":"locality",
    "wof:population":1
},
  "geometry": {"coordinates":[78.61973399999999,20.646451],"type":"Point"}
}