{
  "type": "Feature",
  "properties": {
    "iso:country":"IN",
    "ks:ks_name":"Bankeswarpur",
    "ks:ks_pop":228,
    "ks:ks_type":"VILLAGE",
    "name:eng_x_preferred":[
        "Bankeswarpur"
    ],
    "wof:name":"Bankeswarpur",
    "wof:placetype":"locality",
    "wof:population":228
},
  "geometry": {"coordinates":[86.783378,21.222529],"type":"Point"}
}