{
  "type": "Feature",
  "properties": {
    "iso:country":"IN",
    "ks:ks_name":"Kalitapara",
    "ks:ks_pop":570,
    "ks:ks_type":"HABITATION",
    "name:eng_x_preferred":[
        "Kalitapara"
    ],
    "wof:name":"Kalitapara",
    "wof:placetype":"locality",
    "wof:population":570
},
  "geometry": {"coordinates":[91.07718300000001,25.969139],"type":"Point"}
}