{
  "type": "Feature",
  "properties": {
    "iso:country":"IN",
    "ks:ks_name":"Damuni",
    "ks:ks_pop":143,
    "ks:ks_type":"HABITATION",
    "name:eng_x_preferred":[
        "Damuni"
    ],
    "wof:name":"Damuni",
    "wof:placetype":"locality",
    "wof:population":143
},
  "geometry": {"coordinates":[73.45632500000001,23.786761],"type":"Point"}
}