{
  "type": "Feature",
  "properties": {
    "iso:country":"IN",
    "ks:ks_alt_nam":"PANANIYON KI DHANI",
    "ks:ks_name":"Pananiyon Ki Dhani",
    "ks:ks_pop":344,
    "ks:ks_type":"HABITATION",
    "name:eng_x_preferred":[
        "Pananiyon Ki Dhani"
    ],
    "wof:name":"Pananiyon Ki Dhani",
    "wof:placetype":"locality",
    "wof:population":344
},
  "geometry": {"coordinates":[70.964478,25.4451],"type":"Point"}
}