{
  "type": "Feature",
  "properties": {
    "iso:country":"IN",
    "ks:ks_name":"Ratimali",
    "ks:ks_pop":1359,
    "ks:ks_type":"HABITATION",
    "name:eng_x_preferred":[
        "Ratimali"
    ],
    "wof:name":"Ratimali",
    "wof:placetype":"locality",
    "wof:population":1359
},
  "geometry": {"coordinates":[74.694373,22.67756],"type":"Point"}
}