{
  "type": "Feature",
  "properties": {
    "iso:country":"IN",
    "ks:ks_name":"Tanvara",
    "ks:ks_pop":26,
    "ks:ks_type":"VILLAGE",
    "name:eng_x_preferred":[
        "Tanvara"
    ],
    "wof:name":"Tanvara",
    "wof:placetype":"locality",
    "wof:population":26
},
  "geometry": {"coordinates":[79.73712999999999,23.513636],"type":"Point"}
}