{
  "type": "Feature",
  "properties": {
    "gn:country":"IN",
    "gn:fcode":"PPL",
    "gn:population":47817,
    "iso:country":"IN",
    "name:ara_x_preferred":[
        "\u0648\u0631\u0648\u062f"
    ],
    "name:ben_x_preferred":[
        "\u0993\u09af\u09bc\u09be\u09b0\u09c1\u09a6"
    ],
    "name:bpy_x_preferred":[
        "\u09f1\u09be\u09b0\u09c1\u09a6"
    ],
    "name:ceb_x_preferred":[
        "Warud"
    ],
    "name:deu_x_preferred":[
        "Warud"
    ],
    "name:eng_x_preferred":[
        "Warud"
    ],
    "name:fra_x_preferred":[
        "Warud"
    ],
    "name:guj_x_preferred":[
        "\u0ab5\u0abe\u0ab0\u0ac1\u0aa6"
    ],
    "name:hif_x_preferred":[
        "Warud"
    ],
    "name:ind_x_preferred":[
        "Warud"
    ],
    "name:ita_x_preferred":[
        "Warud"
    ],
    "name:jpn_x_preferred":[
        "\u30ef\u30fc\u30eb\u30c3\u30c9"
    ],
    "name:kan_x_preferred":[
        "\u0cb5\u0cb0\u0cc1\u0ca6\u0ccd"
    ],
    "name:kor_x_preferred":[
        "\uc6cc\uc5b4\ub4dc"
    ],
    "name:mar_x_preferred":[
        "\u0935\u0930\u0941\u0921"
    ],
    "name:msa_x_preferred":[
        "Warud"
    ],
    "name:nan_x_preferred":[
        "Warud"
    ],
    "name:new_x_preferred":[
        "\u0935\u0930\u0941\u0926"
    ],
    "name:nld_x_preferred":[
        "Warud"
    ],
    "name:por_x_preferred":[
        "Warud"
    ],
    "name:rus_x_preferred":[
        "\u0412\u0430\u0440\u0443\u0434"
    ],
    "name:spa_x_preferred":[
        "Warud"
    ],
    "name:swe_x_preferred":[
        "Warud"
    ],
    "name:tam_x_preferred":[
        "\u0bb5\u0bb0\u0bc1\u0b9f\u0bcd"
    ],
    "name:tel_x_preferred":[
        "\u0c35\u0c30\u0c41\u0c26\u0c4d"
    ],
    "name:urd_x_preferred":[
        "\u0648\u0631\u0648\u0691"
    ],
    "name:vie_x_preferred":[
        "Warud"
    ],
    "name:zho_x_preferred":[
        "\u74e6\u9c81\u5fb7"
    ],
    "qs:name":"Jarud",
    "qs:name_adm0":"India",
    "qs:name_adm1":"Maharashtra",
    "qs:photos_9r":0,
    "qs:photos_sr":0,
    "qs:placetype":"Town",
    "qs:pop_sr":"7",
    "wof:name":"Jarud",
    "wof:placetype":"locality",
    "wof:population":47817
},
  "geometry": {"coordinates":[78.26858,21.47076],"type":"Point"}
}