{
  "type": "Feature",
  "properties": {
    "gn:admin1_code":"40",
    "gn:admin2_code":"541.0",
    "gn:asciiname":"Kudunuru",
    "gn:country_code":"IN",
    "gn:dem":65,
    "gn:feature_class":"P",
    "gn:feature_code":"PPL",
    "gn:name":"Kudun\u016bru",
    "gn:population":0,
    "gn:timezone":"Asia/Kolkata",
    "iso:country":"IN",
    "ks:ks_alt_nam":"Kudun\u016bru",
    "ks:ks_name":"Kudunuru",
    "ks:ks_type":"VILLAGE",
    "name:eng_x_preferred":[
        "Kudunuru"
    ],
    "name:eng_x_variant":[
        "Kudun\u016bru"
    ],
    "wof:name":"Kudunuru",
    "wof:placetype":"locality"
},
  "geometry": {"coordinates":[80.877332,17.978168],"type":"Point"}
}