{
  "type": "Feature",
  "properties": {
    "gn:admin1_code":"19.0",
    "gn:admin2_code":"568.0",
    "gn:asciiname":"Danandur",
    "gn:country_code":"IN",
    "gn:dem":609,
    "gn:feature_class":"P",
    "gn:feature_code":"PPL",
    "gn:name":"Danand\u016br",
    "gn:population":0,
    "gn:timezone":"Asia/Kolkata",
    "iso:country":"IN",
    "ks:ks_name":"Dananduru",
    "ks:ks_pop":230,
    "ks:ks_type":"HABITATION",
    "name:eng_x_preferred":[
        "Dananduru"
    ],
    "name:eng_x_variant":[
        "Danandur"
    ],
    "wof:name":"Dananduru",
    "wof:placetype":"locality",
    "wof:population":230
},
  "geometry": {"coordinates":[75.17518800000001,14.007708],"type":"Point"}
}