{
  "type": "Feature",
  "properties": {
    "iso:country":"IN",
    "ks:ks_alt_nam":"Major supa",
    "ks:ks_name":"Major Supa",
    "ks:ks_pop":147,
    "ks:ks_type":"HABITATION",
    "name:eng_x_preferred":[
        "Major Supa"
    ],
    "wof:name":"Major Supa",
    "wof:placetype":"locality",
    "wof:population":147
},
  "geometry": {"coordinates":[91.491634,26.562452],"type":"Point"}
}