{
  "type": "Feature",
  "properties": {
    "iso:country":"IN",
    "ks:ks_name":"Bhoidihi",
    "ks:ks_pop":0,
    "ks:ks_type":"VILLAGE",
    "name:eng_x_preferred":[
        "Bhoidihi"
    ],
    "wof:name":"Bhoidihi",
    "wof:placetype":"locality",
    "wof:population":0
},
  "geometry": {"coordinates":[84.121568,21.937482],"type":"Point"}
}