{
  "type": "Feature",
  "properties": {
    "iso:country":"IN",
    "ks:ks_alt_nam":"MANIRAM THAKUR PARA",
    "ks:ks_name":"Maniram Thakur Para",
    "ks:ks_pop":526,
    "ks:ks_type":"HABITATION",
    "name:eng_x_preferred":[
        "Maniram Thakur Para"
    ],
    "wof:name":"Maniram Thakur Para",
    "wof:placetype":"locality",
    "wof:population":526
},
  "geometry": {"coordinates":[91.29448600000001,23.577961],"type":"Point"}
}