{
  "type": "Feature",
  "properties": {
    "iso:country":"IN",
    "ks:ks_name":"Nidsingi",
    "ks:ks_type":"VILLAGE",
    "name:eng_x_preferred":[
        "Nidsingi"
    ],
    "wof:name":"Nidsingi",
    "wof:placetype":"locality"
},
  "geometry": {"coordinates":[75.12752999999999,14.870647],"type":"Point"}
}