{
  "type": "Feature",
  "properties": {
    "iso:country":"IN",
    "ks:ks_name":"Ramjui",
    "ks:ks_pop":174,
    "ks:ks_type":"VILLAGE",
    "name:eng_x_preferred":[
        "Ramjui"
    ],
    "wof:name":"Ramjui",
    "wof:placetype":"locality",
    "wof:population":174
},
  "geometry": {"coordinates":[85.261864,22.858198],"type":"Point"}
}