{
  "type": "Feature",
  "properties": {
    "iso:country":"IN",
    "ks:ks_name":"Thuhawan",
    "ks:ks_pop":1379,
    "ks:ks_type":"VILLAGE",
    "name:eng_x_preferred":[
        "Thuhawan"
    ],
    "wof:name":"Thuhawan",
    "wof:placetype":"locality",
    "wof:population":1379
},
  "geometry": {"coordinates":[85.333009,26.02838],"type":"Point"}
}