{
  "type": "Feature",
  "properties": {
    "iso:country":"IN",
    "ks:ks_name":"Bommanalli M",
    "ks:ks_pop":993,
    "ks:ks_type":"HABITATION",
    "name:eng_x_preferred":[
        "Bommanalli M"
    ],
    "wof:name":"Bommanalli M",
    "wof:placetype":"locality",
    "wof:population":993
},
  "geometry": {"coordinates":[76.703093,16.558589],"type":"Point"}
}