{
  "type": "Feature",
  "properties": {
    "gn:admin1_code":"35",
    "gn:admin2_code":"462.0",
    "gn:asciiname":"Barwani",
    "gn:country_code":"IN",
    "gn:dem":392,
    "gn:feature_class":"P",
    "gn:feature_code":"PPL",
    "gn:name":"Barw\u0101ni",
    "gn:population":0,
    "gn:timezone":"Asia/Kolkata",
    "iso:country":"IN",
    "name:ben_x_preferred":[
        "\u09ac\u09be\u09b0\u0993\u09af\u09bc\u09be\u09a8\u09bf"
    ],
    "name:bpy_x_preferred":[
        "\u09ac\u09be\u09b0\u09f1\u09be\u09a8\u09bf"
    ],
    "name:cat_x_preferred":[
        "Barwani"
    ],
    "name:ceb_x_preferred":[
        "Barw\u0101ni"
    ],
    "name:deu_x_preferred":[
        "Barwani"
    ],
    "name:hin_x_preferred":[
        "\u092c\u0921\u093c\u0935\u093e\u0928\u0940"
    ],
    "name:ita_x_preferred":[
        "Barwani"
    ],
    "name:mar_x_preferred":[
        "\u092c\u0921\u0935\u093e\u0928\u0940"
    ],
    "name:mlg_x_preferred":[
        "Barwani"
    ],
    "name:msa_x_preferred":[
        "Barwani"
    ],
    "name:new_x_preferred":[
        "\u092c\u0930\u094d\u0935\u093e\u0928\u0940"
    ],
    "name:pam_x_preferred":[
        "Barwani"
    ],
    "name:por_x_preferred":[
        "Barwani"
    ],
    "name:san_x_preferred":[
        "\u092c\u0921\u0935\u093e\u0928\u0940"
    ],
    "name:spa_x_preferred":[
        "Barwani"
    ],
    "name:swe_x_preferred":[
        "Barwani"
    ],
    "name:urd_x_preferred":[
        "\u0628\u0631\u0648\u0627\u0646\u06cc"
    ],
    "name:vie_x_preferred":[
        "Barwani"
    ],
    "name:zho_x_preferred":[
        "\u5df4\u5c14\u74e6\u5c3c"
    ],
    "wof:name":"Barwani",
    "wof:placetype":"locality"
},
  "geometry": {"coordinates":[81.76476,24.23583],"type":"Point"}
}