{
  "type": "Feature",
  "properties": {
    "iso:country":"IN",
    "ks:ks_name":"4 BLW",
    "ks:ks_pop":17,
    "ks:ks_type":"VILLAGE",
    "name:eng_x_preferred":[
        "4 BLW"
    ],
    "wof:name":"4 BLW",
    "wof:placetype":"locality",
    "wof:population":17
},
  "geometry": {"coordinates":[73.914789,29.643592],"type":"Point"}
}