{
  "type": "Feature",
  "properties": {
    "iso:country":"IN",
    "ks:ks_name":"Thakurpara",
    "ks:ks_pop":133,
    "ks:ks_type":"HABITATION",
    "name:eng_x_preferred":[
        "Thakurpara"
    ],
    "wof:name":"Thakurpara",
    "wof:placetype":"locality",
    "wof:population":133
},
  "geometry": {"coordinates":[88.206891,25.211324],"type":"Point"}
}