{
  "type": "Feature",
  "properties": {
    "iso:country":"IN",
    "ks:ks_name":"Senkaradu",
    "ks:ks_pop":230,
    "ks:ks_type":"HABITATION",
    "name:eng_x_preferred":[
        "Senkaradu"
    ],
    "wof:name":"Senkaradu",
    "wof:placetype":"locality",
    "wof:population":230
},
  "geometry": {"coordinates":[78.355328,11.733354],"type":"Point"}
}