{
  "type": "Feature",
  "properties": {
    "iso:country":"IN",
    "ks:ks_name":"Singupuram",
    "ks:ks_pop":205,
    "ks:ks_type":"VILLAGE",
    "name:eng_x_preferred":[
        "Singupuram"
    ],
    "wof:name":"Singupuram",
    "wof:placetype":"locality",
    "wof:population":205
},
  "geometry": {"coordinates":[84.395627,18.894675],"type":"Point"}
}