{
  "type": "Feature",
  "properties": {
    "gn:admin1_code":"2",
    "gn:admin2_code":"544.0",
    "gn:asciiname":"Egrudi",
    "gn:country_code":"IN",
    "gn:dem":1208,
    "gn:feature_class":"P",
    "gn:feature_code":"PPL",
    "gn:name":"Egrudi",
    "gn:population":0,
    "gn:timezone":"Asia/Kolkata",
    "iso:country":"IN",
    "ks:ks_name":"Egarudi",
    "ks:ks_pop":110,
    "ks:ks_type":"HABITATION",
    "name:eng_x_preferred":[
        "Egarudi"
    ],
    "name:eng_x_variant":[
        "Egrudi"
    ],
    "wof:name":"Egarudi",
    "wof:placetype":"locality",
    "wof:population":110
},
  "geometry": {"coordinates":[82.787103,18.195502],"type":"Point"}
}