{
  "type": "Feature",
  "properties": {
    "gn:admin1_code":"19.0",
    "gn:admin2_code":"571.0",
    "gn:asciiname":"Cholambi",
    "gn:country_code":"IN",
    "gn:dem":856,
    "gn:feature_class":"P",
    "gn:feature_code":"PPL",
    "gn:name":"Cholambi",
    "gn:population":0,
    "gn:timezone":"Asia/Kolkata",
    "iso:country":"IN",
    "wof:name":"Cholambi",
    "wof:placetype":"locality"
},
  "geometry": {"coordinates":[77.13573000000002,13.23523],"type":"Point"}
}