{
  "type": "Feature",
  "properties": {
    "iso:country":"IN",
    "ks:ks_alt_nam":"Long eh lobui",
    "ks:ks_name":"Long Eh Lobui",
    "ks:ks_pop":543,
    "ks:ks_type":"HABITATION",
    "name:eng_x_preferred":[
        "Long Eh Lobui"
    ],
    "wof:name":"Long Eh Lobui",
    "wof:placetype":"locality",
    "wof:population":543
},
  "geometry": {"coordinates":[92.48330900000001,25.925305],"type":"Point"}
}