{
  "type": "Feature",
  "properties": {
    "gn:admin1_code":"12.0",
    "gn:admin2_code":"9.0",
    "gn:asciiname":"Darmahom",
    "gn:country_code":"IN",
    "gn:dem":1687,
    "gn:feature_class":"P",
    "gn:feature_code":"PPL",
    "gn:name":"Darm\u0101hom",
    "gn:population":0,
    "gn:timezone":"Asia/Kolkata",
    "iso:country":"IN",
    "name:eng_x_preferred":[
        "Darm\u0101hom"
    ],
    "wof:name":"Darmahom",
    "wof:placetype":"locality"
},
  "geometry": {"coordinates":[74.65731,34.45553],"type":"Point"}
}