{
  "type": "Feature",
  "properties": {
    "iso:country":"IN",
    "ks:ks_name":"Hanumantwadi 2",
    "ks:ks_pop":148,
    "ks:ks_type":"HABITATION",
    "name:eng_x_preferred":[
        "Hanumantwadi 2"
    ],
    "wof:name":"Hanumantwadi 2",
    "wof:placetype":"locality",
    "wof:population":148
},
  "geometry": {"coordinates":[73.819551,16.291929],"type":"Point"}
}