{
  "type": "Feature",
  "properties": {
    "gn:admin1_code":"13.0",
    "gn:admin2_code":"590.0",
    "gn:asciiname":"Tanivayal",
    "gn:country_code":"IN",
    "gn:dem":829,
    "gn:feature_class":"P",
    "gn:feature_code":"PPL",
    "gn:name":"Tanivayal",
    "gn:population":0,
    "gn:timezone":"Asia/Kolkata",
    "iso:country":"IN",
    "wof:name":"Tanivayal",
    "wof:placetype":"neighbourhood"
},
  "geometry": {"coordinates":[76.21682,11.65123],"type":"Point"}
}