{
  "type": "Feature",
  "properties": {
    "iso:country":"IN",
    "ks:ks_name":"Gajipura",
    "ks:ks_pop":19,
    "ks:ks_type":"VILLAGE",
    "name:eng_x_preferred":[
        "Gajipura"
    ],
    "wof:name":"Gajipura",
    "wof:placetype":"locality",
    "wof:population":19
},
  "geometry": {"coordinates":[76.435835,22.755422],"type":"Point"}
}