{
  "type": "Feature",
  "properties": {
    "iso:country":"IN",
    "ks:ks_alt_nam":"Kh\u0101npur",
    "ks:ks_name":"Khanpur",
    "ks:ks_pop":3533,
    "ks:ks_type":"VILLAGE",
    "ks:ks_uagg_main":0,
    "name:eng_x_preferred":[
        "Khanpur"
    ],
    "name:eng_x_variant":[
        "Kh\u0101npur"
    ],
    "wof:name":"Khanpur",
    "wof:placetype":"neighbourhood",
    "wof:population":3533
},
  "geometry": {"coordinates":[79.601291,27.394141],"type":"Point"}
}