{
  "type": "Feature",
  "properties": {
    "gn:admin1_code":"24",
    "gn:admin2_code":"115.0",
    "gn:asciiname":"Majal",
    "gn:country_code":"IN",
    "gn:dem":152,
    "gn:feature_class":"P",
    "gn:feature_code":"PPL",
    "gn:name":"Majal",
    "gn:population":0,
    "gn:timezone":"Asia/Kolkata",
    "iso:country":"IN",
    "wof:name":"Majal",
    "wof:placetype":"locality"
},
  "geometry": {"coordinates":[72.70654999999999,25.81396],"type":"Point"}
}