{
  "type": "Feature",
  "properties": {
    "iso:country":"IN",
    "ks:ks_name":"Khaley Purwa",
    "ks:ks_pop":150,
    "ks:ks_type":"HABITATION",
    "name:eng_x_preferred":[
        "Khaley Purwa"
    ],
    "wof:name":"Khaley Purwa",
    "wof:placetype":"locality",
    "wof:population":150
},
  "geometry": {"coordinates":[81.862227,27.220429],"type":"Point"}
}