{
  "type": "Feature",
  "properties": {
    "iso:country":"IN",
    "ks:ks_alt_nam":"Khalis\u0101hi",
    "ks:ks_name":"Khalisahi",
    "ks:ks_type":"VILLAGE",
    "name:eng_x_preferred":[
        "Khalisahi"
    ],
    "name:eng_x_variant":[
        "Khalis\u0101hi"
    ],
    "wof:name":"Khalisahi",
    "wof:placetype":"locality"
},
  "geometry": {"coordinates":[84.899486,20.429903],"type":"Point"}
}