{
  "type": "Feature",
  "properties": {
    "iso:country":"IN",
    "ks:ks_name":"Chanpa Pukhuria",
    "ks:ks_pop":4919,
    "ks:ks_type":"VILLAGE",
    "name:eng_x_preferred":[
        "Chanpa Pukhuria"
    ],
    "wof:name":"Chanpa Pukhuria",
    "wof:placetype":"locality",
    "wof:population":4919
},
  "geometry": {"coordinates":[88.812202,22.657154],"type":"Point"}
}