{
  "type": "Feature",
  "properties": {
    "gn:admin1_code":"12",
    "gn:admin2_code":"14.0",
    "gn:asciiname":"Nagabanj",
    "gn:country_code":"IN",
    "gn:dem":1706,
    "gn:feature_class":"P",
    "gn:feature_code":"PPL",
    "gn:name":"N\u0101gabanj",
    "gn:population":0,
    "gn:timezone":"Asia/Kolkata",
    "iso:country":"IN",
    "wof:name":"Nagabanj",
    "wof:placetype":"locality"
},
  "geometry": {"coordinates":[75.23876,33.68742],"type":"Point"}
}