{
  "type": "Feature",
  "properties": {
    "iso:country":"IN",
    "ks:ks_name":"Purbapara",
    "ks:ks_pop":1201,
    "ks:ks_type":"HABITATION",
    "ks:ks_uagg_main":0,
    "name:eng_x_preferred":[
        "Purbapara"
    ],
    "wof:name":"Purbapara",
    "wof:placetype":"locality",
    "wof:population":1201
},
  "geometry": {"coordinates":[88.22547400000001,22.803129],"type":"Point"}
}