{
  "type": "Feature",
  "properties": {
    "gn:admin1_code":"35",
    "gn:admin2_code":"430.0",
    "gn:asciiname":"Hatwa",
    "gn:country_code":"IN",
    "gn:dem":349,
    "gn:feature_class":"P",
    "gn:feature_code":"PPL",
    "gn:name":"Hatwa",
    "gn:population":0,
    "gn:timezone":"Asia/Kolkata",
    "iso:country":"IN",
    "wof:name":"Hatwa",
    "wof:placetype":"locality"
},
  "geometry": {"coordinates":[81.76051,24.64485],"type":"Point"}
}