{
  "type": "Feature",
  "properties": {
    "iso:country":"IN",
    "ks:ks_name":"Puballi",
    "ks:ks_pop":630,
    "ks:ks_type":"HABITATION",
    "name:eng_x_preferred":[
        "Puballi"
    ],
    "wof:name":"Puballi",
    "wof:placetype":"locality",
    "wof:population":630
},
  "geometry": {"coordinates":[80.37533000000001,17.622692],"type":"Point"}
}