{
  "type": "Feature",
  "properties": {
    "gn:admin1_code":"34.0",
    "gn:admin2_code":"221.0",
    "gn:asciiname":"Shahzadpur",
    "gn:country_code":"IN",
    "gn:dem":50,
    "gn:feature_class":"P",
    "gn:feature_code":"PPL",
    "gn:name":"Sh\u0101hz\u0101dpur",
    "gn:population":0,
    "gn:timezone":"Asia/Kolkata",
    "iso:country":"IN",
    "name:eng_x_preferred":[
        "Sh\u0101hz\u0101dpur"
    ],
    "wof:name":"Shahzadpur",
    "wof:placetype":"locality"
},
  "geometry": {"coordinates":[85.73579000000002,25.72689],"type":"Point"}
}