{
  "type": "Feature",
  "properties": {
    "iso:country":"IN",
    "ks:ks_alt_nam":"DHAPDA RYT",
    "ks:ks_name":"Dhapda Ryt",
    "ks:ks_pop":208,
    "ks:ks_type":"HABITATION",
    "name:eng_x_preferred":[
        "Dhapda Ryt"
    ],
    "wof:name":"Dhapda Ryt",
    "wof:placetype":"locality",
    "wof:population":208
},
  "geometry": {"coordinates":[77.937495,22.288088],"type":"Point"}
}