{
  "type": "Feature",
  "properties": {
    "iso:country":"IN",
    "ks:ks_name":"Shantipur",
    "ks:ks_pop":700,
    "ks:ks_type":"HABITATION",
    "ks:ks_uagg_main":0,
    "name:eng_x_preferred":[
        "Shantipur"
    ],
    "wof:name":"Shantipur",
    "wof:placetype":"neighbourhood",
    "wof:population":700
},
  "geometry": {"coordinates":[72.470708,22.986822],"type":"Point"}
}