{
  "type": "Feature",
  "properties": {
    "iso:country":"IN",
    "ks:ks_name":"Seveguli",
    "ks:ks_pop":104,
    "ks:ks_type":"HABITATION",
    "name:eng_x_preferred":[
        "Seveguli"
    ],
    "wof:name":"Seveguli",
    "wof:placetype":"locality",
    "wof:population":104
},
  "geometry": {"coordinates":[74.45084799999999,14.754332],"type":"Point"}
}