{
  "type": "Feature",
  "properties": {
    "gn:admin1_code":"21",
    "gn:admin2_code":"393.0",
    "gn:asciiname":"Bagjhola",
    "gn:country_code":"IN",
    "gn:dem":158,
    "gn:feature_class":"P",
    "gn:feature_code":"PPL",
    "gn:name":"B\u0101gjhola",
    "gn:population":0,
    "gn:timezone":"Asia/Kolkata",
    "iso:country":"IN",
    "wof:name":"Bagjhola",
    "wof:placetype":"locality"
},
  "geometry": {"coordinates":[83.42328000000001,21.02592000000001],"type":"Point"}
}