{
  "type": "Feature",
  "properties": {
    "gn:admin1_code":"36",
    "gn:admin2_code":"201.0",
    "gn:asciiname":"Salimpur",
    "gn:country_code":"IN",
    "gn:dem":179,
    "gn:feature_class":"P",
    "gn:feature_code":"PPL",
    "gn:name":"Sal\u012bmpur",
    "gn:population":0,
    "gn:timezone":"Asia/Kolkata",
    "iso:country":"IN",
    "wof:name":"Salimpur",
    "wof:placetype":"locality"
},
  "geometry": {"coordinates":[78.41393000000002,27.57374],"type":"Point"}
}