{
  "type": "Feature",
  "properties": {
    "iso:country":"IN",
    "ks:ks_name":"Bobadghar",
    "ks:ks_pop":124,
    "ks:ks_type":"VILLAGE",
    "name:eng_x_preferred":[
        "Bobadghar"
    ],
    "wof:name":"Bobadghar",
    "wof:placetype":"locality",
    "wof:population":124
},
  "geometry": {"coordinates":[73.04315800000001,18.408987],"type":"Point"}
}