{
  "type": "Feature",
  "properties": {
    "gn:admin1_code":"12.0",
    "gn:admin2_code":"014",
    "gn:asciiname":"Achhibal",
    "gn:country_code":"IN",
    "gn:dem":1663,
    "gn:feature_class":"P",
    "gn:feature_code":"PPL",
    "gn:name":"Achh\u012bbal",
    "gn:population":0,
    "gn:timezone":"Asia/Kolkata",
    "iso:country":"IN",
    "name:und_x_variant":[
        "Acchabal",
        "Achhabal",
        "Achhaw\u0101l",
        "Achh\u012bbal",
        "Achhiw\u0101l",
        "Achabal"
    ],
    "wof:name":"Achhibal",
    "wof:placetype":"locality"
},
  "geometry": {"coordinates":[75.21835,33.68409],"type":"Point"}
}