{
  "type": "Feature",
  "properties": {
    "gn:admin1_code":"12.0",
    "gn:admin2_code":"014",
    "gn:asciiname":"Achhibal",
    "gn:country_code":"IN",
    "gn:dem":1663,
    "gn:feature_class":"P",
    "gn:feature_code":"PPL",
    "gn:name":"Achh\u012bbal",
    "gn:population":0,
    "gn:timezone":"Asia/Kolkata",
    "iso:country":"IN",
    "name:bpy_x_preferred":[
        "\u0985\u099a\u09ac\u09b2"
    ],
    "name:cat_x_preferred":[
        "Achabal"
    ],
    "name:fas_x_preferred":[
        "\u0627\u06a9\u0628\u0627\u0644"
    ],
    "name:ita_x_preferred":[
        "Achabal"
    ],
    "name:min_x_preferred":[
        "Achabal"
    ],
    "name:mlg_x_preferred":[
        "Achabal"
    ],
    "name:msa_x_preferred":[
        "Achabal"
    ],
    "name:new_x_preferred":[
        "\u0905\u091a\u092c\u0932"
    ],
    "name:nld_x_preferred":[
        "Achabal"
    ],
    "name:por_x_preferred":[
        "Achabal"
    ],
    "name:spa_x_preferred":[
        "Achabal"
    ],
    "name:und_x_variant":[
        "Acchabal",
        "Achhabal",
        "Achhaw\u0101l",
        "Achh\u012bbal",
        "Achhiw\u0101l",
        "Achabal"
    ],
    "name:urd_x_preferred":[
        "\u0627\u0686\u0628\u0627\u0644"
    ],
    "name:vie_x_preferred":[
        "Achabal"
    ],
    "name:zho_x_preferred":[
        "\u963f\u6070\u5df4\u5c14"
    ],
    "wof:name":"Achhibal",
    "wof:placetype":"locality"
},
  "geometry": {"coordinates":[75.21835,33.68409],"type":"Point"}
}