{
  "type": "Feature",
  "properties": {
    "gn:admin1_code":"25.0",
    "gn:admin2_code":"631.0",
    "gn:asciiname":"Echchanahalli",
    "gn:country_code":"IN",
    "gn:dem":728,
    "gn:feature_class":"P",
    "gn:feature_code":"PPL",
    "gn:name":"Echchanahalli",
    "gn:population":0,
    "gn:timezone":"Asia/Kolkata",
    "iso:country":"IN",
    "wof:name":"Echchanahalli",
    "wof:placetype":"locality"
},
  "geometry": {"coordinates":[78.03041999999998,12.49651],"type":"Point"}
}