{
  "type": "Feature",
  "properties": {
    "gn:admin1_code":"35",
    "gn:admin2_code":"458.0",
    "gn:asciiname":"Chim",
    "gn:country_code":"IN",
    "gn:dem":432,
    "gn:feature_class":"P",
    "gn:feature_code":"PPL",
    "gn:name":"Ch\u012bm",
    "gn:population":0,
    "gn:timezone":"Asia/Kolkata",
    "iso:country":"IN",
    "ks:ks_name":"Chim",
    "ks:ks_pop":397,
    "ks:ks_type":"HABITATION",
    "name:ceb_x_preferred":[
        "Chim"
    ],
    "name:deu_x_preferred":[
        "Chim"
    ],
    "name:eng_x_preferred":[
        "Chim"
    ],
    "name:swe_x_preferred":[
        "Chim"
    ],
    "wof:name":"Chim",
    "wof:placetype":"locality",
    "wof:population":397
},
  "geometry": {"coordinates":[77.176108,24.766971],"type":"Point"}
}