{
  "type": "Feature",
  "properties": {
    "gn:admin1_code":"37",
    "gn:admin2_code":"408.0",
    "gn:asciiname":"Chhirpani",
    "gn:country_code":"IN",
    "gn:dem":346,
    "gn:feature_class":"P",
    "gn:feature_code":"PPL",
    "gn:name":"Chhirp\u0101n\u012b",
    "gn:population":0,
    "gn:timezone":"Asia/Kolkata",
    "iso:country":"IN",
    "ks:ks_alt_nam":"Chhirp\u0101n\u012b",
    "ks:ks_name":"Chhirpani",
    "ks:ks_type":"VILLAGE",
    "ks:ks_uagg_main":0,
    "name:eng_x_preferred":[
        "Chhirpani"
    ],
    "name:eng_x_variant":[
        "Chhirp\u0101n\u012b"
    ],
    "wof:name":"Chhirpani",
    "wof:placetype":"neighbourhood"
},
  "geometry": {"coordinates":[80.76419300000001,21.178697],"type":"Point"}
}