{
  "type": "Feature",
  "properties": {
    "iso:country":"IN",
    "ks:ks_name":"Gobindapurbaid",
    "ks:ks_pop":71,
    "ks:ks_type":"VILLAGE",
    "name:eng_x_preferred":[
        "Gobindapurbaid"
    ],
    "wof:name":"Gobindapurbaid",
    "wof:placetype":"locality",
    "wof:population":71
},
  "geometry": {"coordinates":[87.088041,23.472899],"type":"Point"}
}