{
  "type": "Feature",
  "properties": {
    "gn:admin1_code":"11.0",
    "gn:admin2_code":"31.0",
    "gn:asciiname":"Deoghat",
    "gn:country_code":"IN",
    "gn:dem":1458,
    "gn:feature_class":"P",
    "gn:feature_code":"PPL",
    "gn:name":"Deoghat",
    "gn:population":0,
    "gn:timezone":"Asia/Kolkata",
    "iso:country":"IN",
    "wof:name":"Deoghat",
    "wof:placetype":"neighbourhood"
},
  "geometry": {"coordinates":[77.09113000000001,30.90808],"type":"Point"}
}