{
  "type": "Feature",
  "properties": {
    "iso:country":"IN",
    "ks:ks_name":"Musughat",
    "ks:ks_pop":119,
    "ks:ks_type":"HABITATION",
    "name:eng_x_preferred":[
        "Musughat"
    ],
    "wof:name":"Musughat",
    "wof:placetype":"locality",
    "wof:population":119
},
  "geometry": {"coordinates":[80.76579700000001,19.98174],"type":"Point"}
}