{
  "type": "Feature",
  "properties": {
    "gn:admin1_code":"36",
    "gn:admin2_code":"191.0",
    "gn:asciiname":"Fatehpur Bhatauli",
    "gn:country_code":"IN",
    "gn:dem":82,
    "gn:feature_class":"P",
    "gn:feature_code":"PPL",
    "gn:name":"Fatehpur Bhatauli",
    "gn:population":0,
    "gn:timezone":"Asia/Kolkata",
    "iso:country":"IN",
    "ks:ks_name":"Fatehpur Bhatuli",
    "ks:ks_pop":731,
    "ks:ks_type":"VILLAGE",
    "name:eng_x_preferred":[
        "Fatehpur Bhatuli"
    ],
    "name:eng_x_variant":[
        "Fatehpur Bhatauli"
    ],
    "wof:name":"Fatehpur Bhatuli",
    "wof:placetype":"locality",
    "wof:population":731
},
  "geometry": {"coordinates":[83.17420300000001,25.813331],"type":"Point"}
}