{
  "type": "Feature",
  "properties": {
    "gn:admin1_code":"16",
    "gn:admin2_code":"521.0",
    "gn:asciiname":"Raireshwar",
    "gn:country_code":"IN",
    "gn:dem":1347,
    "gn:feature_class":"P",
    "gn:feature_code":"PPL",
    "gn:name":"R\u0101ireshwar",
    "gn:population":0,
    "gn:timezone":"Asia/Kolkata",
    "iso:country":"IN",
    "name:mar_x_preferred":[
        "\u0930\u093e\u092f\u0930\u0947\u0936\u094d\u0935\u0930"
    ],
    "name:ukr_x_preferred":[
        "\u0420\u0430\u0439\u0440\u0435\u0448\u0432\u0430\u0440"
    ],
    "name:und_x_variant":[
        "R\u0101ireshwar"
    ],
    "name:urd_x_preferred":[
        "\u0631\u0627\u0626\u06d2 \u0631\u06cc\u0634\u0648\u0631"
    ],
    "wof:name":"Raireshwar",
    "wof:placetype":"locality"
},
  "geometry": {"coordinates":[73.72150999999999,18.04852],"type":"Point"}
}