{
  "type": "Feature",
  "properties": {
    "gn:admin1_code":"25.0",
    "gn:admin2_code":"633.0",
    "gn:asciiname":"Ramanathapuram",
    "gn:country_code":"IN",
    "gn:dem":219,
    "gn:feature_class":"P",
    "gn:feature_code":"PPL",
    "gn:name":"R\u0101man\u0101th\u0101puram",
    "gn:population":0,
    "gn:timezone":"Asia/Kolkata",
    "iso:country":"IN",
    "name:bpy_x_preferred":[
        "\u09b0\u09ae\u09a8\u09cd\u09a5\u09be\u09aa\u09c1\u09b0\u09ae"
    ],
    "name:cat_x_preferred":[
        "Ramanathapuram"
    ],
    "name:ceb_x_preferred":[
        "Ramanathapuram"
    ],
    "name:deu_x_preferred":[
        "Ramanathapuram"
    ],
    "name:fra_x_preferred":[
        "Ramanathapuram"
    ],
    "name:guj_x_preferred":[
        "\u0ab0\u0abe\u0aae\u0aa8\u0abe\u0aa5\u0aaa\u0ac1\u0ab0\u0aae"
    ],
    "name:hif_x_preferred":[
        "Ramanathapuram"
    ],
    "name:hin_x_preferred":[
        "\u0930\u093e\u092e\u0928\u093e\u0925\u092a\u0941\u0930\u092e"
    ],
    "name:ita_x_preferred":[
        "Ramanathapuram"
    ],
    "name:jpn_x_preferred":[
        "\u30e9\u30fc\u30de\u30ca\u30fc\u30bf\u30d7\u30e9\u30e0"
    ],
    "name:mar_x_preferred":[
        "\u0930\u093e\u092e\u0928\u093e\u0925\u092a\u0941\u0930\u092e"
    ],
    "name:mlg_x_preferred":[
        "Ramanathapuram"
    ],
    "name:msa_x_preferred":[
        "Ramanathapuram"
    ],
    "name:nep_x_preferred":[
        "\u0930\u093e\u092e\u093e\u0928\u093e\u0925\u092a\u0941\u0930\u092e"
    ],
    "name:ori_x_preferred":[
        "\u0b30\u0b3e\u0b2e\u0b28\u0b3e\u0b25\u0b2a\u0b41\u0b30\u0b2e"
    ],
    "name:pam_x_preferred":[
        "Ramanathapuram"
    ],
    "name:pol_x_preferred":[
        "Ramanathapuram"
    ],
    "name:por_x_preferred":[
        "Ramanathapuram"
    ],
    "name:ron_x_preferred":[
        "Ramanathapuram"
    ],
    "name:rus_x_preferred":[
        "\u0420\u0430\u043c\u0430\u043d\u0430\u0442\u0445\u0430\u043f\u0443\u0440\u0430\u043c"
    ],
    "name:san_x_preferred":[
        "\u0930\u093e\u092e\u0928\u093e\u0925\u092a\u0941\u0930\u092e\u094d"
    ],
    "name:spa_x_preferred":[
        "Ramanathapuram"
    ],
    "name:swe_x_preferred":[
        "Ramanathapuram"
    ],
    "name:tam_x_preferred":[
        "\u0b87\u0bb0\u0bbe\u0bae\u0ba8\u0bbe\u0ba4\u0baa\u0bc1\u0bb0\u0bae\u0bcd"
    ],
    "name:vie_x_preferred":[
        "Ramanathapuram"
    ],
    "name:zho_x_preferred":[
        "\u62c9\u9a6c\u7eb3\u5854\u666e\u62c9\u59c6"
    ],
    "wof:name":"Ramanathapuram",
    "wof:placetype":"locality"
},
  "geometry": {"coordinates":[77.72140999999998,11.04098],"type":"Point"}
}