{
  "type": "Feature",
  "properties": {
    "gn:admin1_code":"36",
    "gn:admin2_code":"194.0",
    "gn:asciiname":"Inglish Chak",
    "gn:country_code":"IN",
    "gn:dem":90,
    "gn:feature_class":"P",
    "gn:feature_code":"PPL",
    "gn:name":"Inglish Chak",
    "gn:population":0,
    "gn:timezone":"Asia/Kolkata",
    "iso:country":"IN",
    "name:und_x_variant":[
        "Haidar Husain",
        "Han\u012bf"
    ],
    "wof:name":"Inglish Chak",
    "wof:placetype":"neighbourhood"
},
  "geometry": {"coordinates":[82.43257,25.5403],"type":"Point"}
}