{
  "type": "Feature",
  "properties": {
    "iso:country":"IN",
    "ks:ks_name":"Rampur",
    "ks:ks_pop":235,
    "ks:ks_type":"VILLAGE",
    "name:eng_x_preferred":[
        "Rampur"
    ],
    "wof:name":"Rampur",
    "wof:placetype":"locality",
    "wof:population":235
},
  "geometry": {"coordinates":[78.49619,19.216153],"type":"Point"}
}