{
  "type": "Feature",
  "properties": {
    "gn:admin1_code":"2.0",
    "gn:admin2_code":"551.0",
    "gn:asciiname":"Peddapotupalli",
    "gn:country_code":"IN",
    "gn:dem":157,
    "gn:feature_class":"P",
    "gn:feature_code":"PPL",
    "gn:name":"Peddapotupalli",
    "gn:population":0,
    "gn:timezone":"Asia/Kolkata",
    "iso:country":"IN",
    "wof:name":"Peddapotupalli",
    "wof:placetype":"locality"
},
  "geometry": {"coordinates":[79.14896,14.704],"type":"Point"}
}