{
  "type": "Feature",
  "properties": {
    "gn:admin1_code":"11.0",
    "gn:admin2_code":"026",
    "gn:asciiname":"Kharag",
    "gn:country_code":"IN",
    "gn:dem":2543,
    "gn:feature_class":"P",
    "gn:feature_code":"PPL",
    "gn:name":"Khar\u0101g",
    "gn:population":0,
    "gn:timezone":"Asia/Kolkata",
    "iso:country":"IN",
    "name:und_x_variant":[
        "Khan\u0101g",
        "Khar\u0101g"
    ],
    "wof:name":"Kharag",
    "wof:placetype":"locality"
},
  "geometry": {"coordinates":[77.40384,31.51835],"type":"Point"}
}