{
  "type": "Feature",
  "properties": {
    "gn:admin1_code":"36",
    "gn:admin2_code":"195.0",
    "gn:asciiname":"Chakia Newaz",
    "gn:country_code":"IN",
    "gn:dem":82,
    "gn:feature_class":"P",
    "gn:feature_code":"PPL",
    "gn:name":"Chakia New\u0101z",
    "gn:population":0,
    "gn:timezone":"Asia/Kolkata",
    "iso:country":"IN",
    "ks:ks_alt_nam":"Chakia New\u0101z",
    "ks:ks_name":"Chakia Newaz",
    "ks:ks_type":"VILLAGE",
    "ks:ks_uagg_main":0,
    "name:eng_x_preferred":[
        "Chakia Newaz"
    ],
    "name:eng_x_variant":[
        "Chakia New\u0101z"
    ],
    "wof:name":"Chakia Newaz",
    "wof:placetype":"neighbourhood"
},
  "geometry": {"coordinates":[83.16258500000001,25.586469],"type":"Point"}
}