{
  "type": "Feature",
  "properties": {
    "gn:admin1_code":"35",
    "gn:admin2_code":"451.0",
    "gn:asciiname":"Khairua",
    "gn:country_code":"IN",
    "gn:dem":352,
    "gn:feature_class":"P",
    "gn:feature_code":"PPL",
    "gn:name":"Khairua",
    "gn:population":0,
    "gn:timezone":"Asia/Kolkata",
    "iso:country":"IN",
    "ks:ks_name":"Khairwa",
    "ks:ks_pop":92,
    "ks:ks_type":"VILLAGE",
    "name:eng_x_preferred":[
        "Khairwa"
    ],
    "name:eng_x_variant":[
        "Khairua"
    ],
    "wof:name":"Khairwa",
    "wof:placetype":"locality",
    "wof:population":92
},
  "geometry": {"coordinates":[79.662345,23.061421],"type":"Point"}
}