{
  "type": "Feature",
  "properties": {
    "iso:country":"IN",
    "ks:ks_name":"Karurpambulam",
    "ks:ks_pop":4702,
    "ks:ks_type":"VILLAGE",
    "ks:ks_uagg_main":0,
    "name:eng_x_preferred":[
        "Karurpambulam"
    ],
    "wof:name":"Karurpambulam",
    "wof:placetype":"neighbourhood",
    "wof:population":4702
},
  "geometry": {"coordinates":[79.79454200000001,10.395808],"type":"Point"}
}