{
  "type": "Feature",
  "properties": {
    "gn:admin1_code":"16",
    "gn:admin2_code":"508.0",
    "gn:asciiname":"Shivrajpur",
    "gn:country_code":"IN",
    "gn:dem":235,
    "gn:feature_class":"P",
    "gn:feature_code":"PPL",
    "gn:name":"Shivr\u0101jpur",
    "gn:population":0,
    "gn:timezone":"Asia/Kolkata",
    "iso:country":"IN",
    "name:bpy_x_preferred":[
        "\u09b6\u09bf\u09ac\u09b0\u09be\u099c\u09aa\u09c1\u09b0"
    ],
    "name:ita_x_preferred":[
        "Shivrajpur"
    ],
    "name:msa_x_preferred":[
        "Shivrajpur"
    ],
    "name:nld_x_preferred":[
        "Shivrajpur"
    ],
    "name:pol_x_preferred":[
        "Shivrajpur"
    ],
    "name:por_x_preferred":[
        "Shivrajpur"
    ],
    "name:urd_x_preferred":[
        "\u0634\u06cc\u0648\u0631\u0627\u062c \u067e\u0648\u0631"
    ],
    "name:vie_x_preferred":[
        "Shivrajpur"
    ],
    "name:zho_x_preferred":[
        "\u65af\u5e0c\u6c83\u62c9\u6770\u666e\u5c14"
    ],
    "wof:name":"Shivrajpur",
    "wof:placetype":"locality"
},
  "geometry": {"coordinates":[79.98817,20.57824],"type":"Point"}
}