{
  "type": "Feature",
  "properties": {
    "iso:country":"IN",
    "ks:ks_name":"4 UDM",
    "ks:ks_pop":36,
    "ks:ks_type":"VILLAGE",
    "name:eng_x_preferred":[
        "4 UDM"
    ],
    "wof:name":"4 UDM",
    "wof:placetype":"locality",
    "wof:population":36
},
  "geometry": {"coordinates":[73.286283,29.253357],"type":"Point"}
}