{
  "type": "Feature",
  "properties": {
    "gn:admin1_code":"39.0",
    "gn:admin2_code":"63.0",
    "gn:asciiname":"Dhari",
    "gn:country_code":"IN",
    "gn:dem":1243,
    "gn:feature_class":"P",
    "gn:feature_code":"PPL",
    "gn:name":"Dh\u0101ri",
    "gn:population":0,
    "gn:timezone":"Asia/Kolkata",
    "iso:country":"IN",
    "ks:ks_alt_nam":"Dh\u0101ri",
    "ks:ks_name":"Dhari",
    "ks:ks_pop":353,
    "ks:ks_type":"VILLAGE",
    "name:ceb_x_preferred":[
        "Dhari"
    ],
    "name:eng_x_preferred":[
        "Dhari"
    ],
    "name:eng_x_variant":[
        "Dh\u0101ri"
    ],
    "name:swe_x_preferred":[
        "Dhari"
    ],
    "wof:name":"Dhari",
    "wof:placetype":"locality",
    "wof:population":353
},
  "geometry": {"coordinates":[79.72110000000001,29.810923],"type":"Point"}
}