{
  "type": "Feature",
  "properties": {
    "gn:admin1_code":"12.0",
    "gn:admin2_code":"008",
    "gn:asciiname":"Kandhom",
    "gn:country_code":"IN",
    "gn:dem":1634,
    "gn:feature_class":"P",
    "gn:feature_code":"PPL",
    "gn:name":"K\u0101ndhom",
    "gn:population":0,
    "gn:timezone":"Asia/Kolkata",
    "iso:country":"IN",
    "wof:name":"Kandhom",
    "wof:placetype":"locality"
},
  "geometry": {"coordinates":[74.56726999999999,34.06245],"type":"Point"}
}