{
  "type": "Feature",
  "properties": {
    "gn:admin1_code":"34.0",
    "gn:admin2_code":"230.0",
    "gn:asciiname":"Ghanraj Chapra",
    "gn:country_code":"IN",
    "gn:dem":70,
    "gn:feature_class":"P",
    "gn:feature_code":"PPL",
    "gn:name":"Ghanr\u0101j Chapra",
    "gn:population":0,
    "gn:timezone":"Asia/Kolkata",
    "iso:country":"IN",
    "wof:name":"Ghanraj Chapra",
    "wof:placetype":"neighbourhood"
},
  "geometry": {"coordinates":[84.78948,25.42204],"type":"Point"}
}