{
  "type": "Feature",
  "properties": {
    "gn:admin1_code":"35.0",
    "gn:admin2_code":"451.0",
    "gn:asciiname":"Sadaphal",
    "gn:country_code":"IN",
    "gn:dem":571,
    "gn:feature_class":"P",
    "gn:feature_code":"PPL",
    "gn:name":"Sad\u0101phal",
    "gn:population":0,
    "gn:timezone":"Asia/Kolkata",
    "iso:country":"IN",
    "wof:name":"Sadaphal",
    "wof:placetype":"locality"
},
  "geometry": {"coordinates":[80.33804000000001,23.2239],"type":"Point"}
}