{
  "type": "Feature",
  "properties": {
    "iso:country":"IN",
    "ks:ks_name":"Moravavandlapalli",
    "ks:ks_pop":293,
    "ks:ks_type":"HABITATION",
    "name:eng_x_preferred":[
        "Moravavandlapalli"
    ],
    "wof:name":"Moravavandlapalli",
    "wof:placetype":"locality",
    "wof:population":293
},
  "geometry": {"coordinates":[78.781071,14.023932],"type":"Point"}
}