{
  "type": "Feature",
  "properties": {
    "gn:admin1_code":"34.0",
    "gn:admin2_code":"212.0",
    "gn:asciiname":"Chargoha",
    "gn:country_code":"IN",
    "gn:dem":31,
    "gn:feature_class":"P",
    "gn:feature_code":"PPL",
    "gn:name":"Chargoha",
    "gn:population":0,
    "gn:timezone":"Asia/Kolkata",
    "iso:country":"IN",
    "wof:name":"Chargoha",
    "wof:placetype":"locality"
},
  "geometry": {"coordinates":[87.67639,25.46266],"type":"Point"}
}