{
  "type": "Feature",
  "properties": {
    "iso:country":"IN",
    "ks:ks_name":"Sekhpur",
    "ks:ks_pop":113,
    "ks:ks_type":"VILLAGE",
    "name:eng_x_preferred":[
        "Sekhpur"
    ],
    "wof:name":"Sekhpur",
    "wof:placetype":"locality",
    "wof:population":113
},
  "geometry": {"coordinates":[87.906156,23.135439],"type":"Point"}
}