{
  "type": "Feature",
  "properties": {
    "iso:country":"IN",
    "ks:ks_name":"Fateganj Bankati",
    "ks:ks_pop":601,
    "ks:ks_type":"VILLAGE",
    "name:eng_x_preferred":[
        "Fateganj Bankati"
    ],
    "wof:name":"Fateganj Bankati",
    "wof:placetype":"locality",
    "wof:population":601
},
  "geometry": {"coordinates":[87.48261599999999,22.699656],"type":"Point"}
}