{
  "type": "Feature",
  "properties": {
    "iso:country":"IN",
    "ks:ks_name":"Kayakuchi Pam E 1",
    "ks:ks_pop":165,
    "ks:ks_type":"HABITATION",
    "name:eng_x_preferred":[
        "Kayakuchi Pam E 1"
    ],
    "wof:name":"Kayakuchi Pam E 1",
    "wof:placetype":"locality",
    "wof:population":165
},
  "geometry": {"coordinates":[91.132859,26.421953],"type":"Point"}
}