{
  "type": "Feature",
  "properties": {
    "gn:admin1_code":"35",
    "gn:admin2_code":"463.0",
    "gn:asciiname":"Jagahat",
    "gn:country_code":"IN",
    "gn:dem":295,
    "gn:feature_class":"P",
    "gn:feature_code":"PPL",
    "gn:name":"Jagahat",
    "gn:population":0,
    "gn:timezone":"Asia/Kolkata",
    "iso:country":"IN",
    "ks:ks_name":"Jagahat",
    "ks:ks_pop":702,
    "ks:ks_type":"VILLAGE",
    "name:eng_x_preferred":[
        "Jagahat"
    ],
    "wof:name":"Jagahat",
    "wof:placetype":"locality",
    "wof:population":702
},
  "geometry": {"coordinates":[82.10179100000001,24.302384],"type":"Point"}
}