{
  "type": "Feature",
  "properties": {
    "iso:country":"IN",
    "ks:ks_name":"Mavinkere",
    "ks:ks_pop":102,
    "ks:ks_type":"HABITATION",
    "name:eng_x_preferred":[
        "Mavinkere"
    ],
    "wof:name":"Mavinkere",
    "wof:placetype":"locality",
    "wof:population":102
},
  "geometry": {"coordinates":[74.77067099999999,13.67357],"type":"Point"}
}