{
  "type": "Feature",
  "properties": {
    "iso:country":"IN",
    "ks:ks_alt_nam":"BELODHA WASTI",
    "ks:ks_name":"Belodha Wasti",
    "ks:ks_pop":116,
    "ks:ks_type":"HABITATION",
    "name:eng_x_preferred":[
        "Belodha Wasti"
    ],
    "wof:name":"Belodha Wasti",
    "wof:placetype":"locality",
    "wof:population":116
},
  "geometry": {"coordinates":[74.98246,19.13976],"type":"Point"}
}