{
  "type": "Feature",
  "properties": {
    "iso:country":"IN",
    "ks:ks_name":"Goudasahi",
    "ks:ks_pop":358,
    "ks:ks_type":"HABITATION",
    "name:eng_x_preferred":[
        "Goudasahi"
    ],
    "wof:name":"Goudasahi",
    "wof:placetype":"locality",
    "wof:population":358
},
  "geometry": {"coordinates":[82.62300399999999,19.276982],"type":"Point"}
}