{
  "type": "Feature",
  "properties": {
    "gn:admin1_code":"25.0",
    "gn:admin2_code":"610.0",
    "gn:asciiname":"Chinnatambipalaiyam",
    "gn:country_code":"IN",
    "gn:dem":220,
    "gn:feature_class":"P",
    "gn:feature_code":"PPL",
    "gn:name":"Chinnatambip\u0101laiyam",
    "gn:population":0,
    "gn:timezone":"Asia/Kolkata",
    "iso:country":"IN",
    "ks:ks_name":"Chinnathambipalayam",
    "ks:ks_pop":896,
    "ks:ks_type":"HABITATION",
    "name:eng_x_preferred":[
        "Chinnathambipalayam"
    ],
    "name:eng_x_variant":[
        "Chinnatambipalaiyam"
    ],
    "wof:name":"Chinnathambipalayam",
    "wof:placetype":"locality",
    "wof:population":896
},
  "geometry": {"coordinates":[77.563142,11.564569],"type":"Point"}
}