{
  "type": "Feature",
  "properties": {
    "iso:country":"IN",
    "ks:ks_name":"Bandhanpada1",
    "ks:ks_pop":466,
    "ks:ks_type":"HABITATION",
    "name:eng_x_preferred":[
        "Bandhanpada1"
    ],
    "wof:name":"Bandhanpada1",
    "wof:placetype":"locality",
    "wof:population":466
},
  "geometry": {"coordinates":[82.552241,18.551785],"type":"Point"}
}