{
  "type": "Feature",
  "properties": {
    "iso:country":"IN",
    "ks:ks_alt_nam":"Nagar Kh\u0101s",
    "ks:ks_alt_nam_2":"Nagar Khas",
    "ks:ks_name":"Nagar",
    "ks:ks_pop":4540,
    "ks:ks_type":"VILLAGE",
    "name:eng_x_preferred":[
        "Nagar"
    ],
    "name:eng_x_variant":[
        "Nagar Kh\u0101s",
        "Nagar Khas"
    ],
    "wof:name":"Nagar",
    "wof:placetype":"locality",
    "wof:population":4540
},
  "geometry": {"coordinates":[71.75,25.25],"type":"Point"}
}