{
  "type": "Feature",
  "properties": {
    "gn:admin1_code":"33",
    "gn:admin2_code":"586.0",
    "gn:asciiname":"Patnem",
    "gn:country_code":"IN",
    "gn:dem":10,
    "gn:feature_class":"P",
    "gn:feature_code":"PPL",
    "gn:name":"Patnem",
    "gn:population":0,
    "gn:timezone":"Asia/Kolkata",
    "iso:country":"IN",
    "wof:name":"Patnem",
    "wof:placetype":"locality"
},
  "geometry": {"coordinates":[74.03783,14.99889],"type":"Point"}
}