{
  "type": "Feature",
  "properties": {
    "iso:country":"IN",
    "ks:ks_name":"Shergarh",
    "ks:ks_pop":83,
    "ks:ks_type":"HABITATION",
    "name:eng_x_preferred":[
        "Shergarh"
    ],
    "wof:name":"Shergarh",
    "wof:placetype":"locality",
    "wof:population":83
},
  "geometry": {"coordinates":[74.22109399999999,26.091306],"type":"Point"}
}