{
  "type": "Feature",
  "properties": {
    "iso:country":"IN",
    "ks:ks_name":"Aruli",
    "ks:ks_pop":175,
    "ks:ks_type":"HABITATION",
    "ks:ks_uagg_main":0,
    "name:eng_x_preferred":[
        "Aruli"
    ],
    "wof:name":"Aruli",
    "wof:placetype":"neighbourhood",
    "wof:population":175
},
  "geometry": {"coordinates":[79.77953100000001,27.331176],"type":"Point"}
}