{
  "type": "Feature",
  "properties": {
    "iso:country":"IN",
    "ks:ks_name":"Pashapani",
    "ks:ks_pop":153,
    "ks:ks_type":"HABITATION",
    "name:eng_x_preferred":[
        "Pashapani"
    ],
    "wof:name":"Pashapani",
    "wof:placetype":"locality",
    "wof:population":153
},
  "geometry": {"coordinates":[78.310517,22.59118],"type":"Point"}
}