{
  "type": "Feature",
  "properties": {
    "gn:admin1_code":"36.0",
    "gn:admin2_code":"142.0",
    "gn:asciiname":"Lohgra",
    "gn:country_code":"IN",
    "gn:dem":209,
    "gn:feature_class":"P",
    "gn:feature_code":"PPL",
    "gn:name":"Lohgra",
    "gn:population":0,
    "gn:timezone":"Asia/Kolkata",
    "iso:country":"IN",
    "wof:name":"Lohgra",
    "wof:placetype":"neighbourhood"
},
  "geometry": {"coordinates":[77.8494,28.52824],"type":"Point"}
}