{
  "type": "Feature",
  "properties": {
    "iso:country":"IN",
    "ks:ks_alt_nam":"PURE BHULAN",
    "ks:ks_name":"Pure Bhulan",
    "ks:ks_pop":20,
    "ks:ks_type":"HABITATION",
    "name:eng_x_preferred":[
        "Pure Bhulan"
    ],
    "wof:name":"Pure Bhulan",
    "wof:placetype":"locality",
    "wof:population":20
},
  "geometry": {"coordinates":[81.73739399999999,26.299615],"type":"Point"}
}