{
  "type": "Feature",
  "properties": {
    "iso:country":"IN",
    "ks:ks_name":"Rajarbag",
    "ks:ks_pop":9308,
    "ks:ks_type":"VILLAGE",
    "ks:ks_uagg_main":0,
    "name:eng_x_preferred":[
        "Rajarbag"
    ],
    "wof:name":"Rajarbag",
    "wof:placetype":"neighbourhood",
    "wof:population":9308
},
  "geometry": {"coordinates":[91.48569999999999,23.524144],"type":"Point"}
}