{
  "type": "Feature",
  "properties": {
    "iso:country":"IN",
    "ks:ks_alt_nam":"M\u0101l\u012bs\u0101hi",
    "ks:ks_name":"Malisahi",
    "ks:ks_type":"VILLAGE",
    "name:eng_x_preferred":[
        "Malisahi"
    ],
    "name:eng_x_variant":[
        "M\u0101l\u012bs\u0101hi"
    ],
    "wof:name":"Malisahi",
    "wof:placetype":"locality"
},
  "geometry": {"coordinates":[84.085613,20.757998],"type":"Point"}
}