{
  "type": "Feature",
  "properties": {
    "gn:admin1_code":"25.0",
    "gn:admin2_code":"621.0",
    "gn:asciiname":"Kadambankovil",
    "gn:country_code":"IN",
    "gn:dem":85,
    "gn:feature_class":"P",
    "gn:feature_code":"PPL",
    "gn:name":"Kadambankovil",
    "gn:population":0,
    "gn:timezone":"Asia/Kolkata",
    "iso:country":"IN",
    "ks:ks_name":"Kadambanarkoil",
    "ks:ks_pop":150,
    "ks:ks_type":"HABITATION",
    "name:eng_x_preferred":[
        "Kadambanarkoil"
    ],
    "name:eng_x_variant":[
        "Kadambankovil"
    ],
    "wof:name":"Kadambanarkoil",
    "wof:placetype":"locality",
    "wof:population":150
},
  "geometry": {"coordinates":[79.004553,10.545845],"type":"Point"}
}