{
  "type": "Feature",
  "properties": {
    "iso:country":"IN",
    "ks:ks_name":"Kangori",
    "ks:ks_pop":147,
    "ks:ks_type":"HABITATION",
    "name:eng_x_preferred":[
        "Kangori"
    ],
    "wof:name":"Kangori",
    "wof:placetype":"locality",
    "wof:population":147
},
  "geometry": {"coordinates":[74.853323,13.123574],"type":"Point"}
}