{
  "type": "Feature",
  "properties": {
    "gn:admin1_code":"24",
    "gn:admin2_code":"105.0",
    "gn:asciiname":"Kaithwara",
    "gn:country_code":"IN",
    "gn:dem":199,
    "gn:feature_class":"P",
    "gn:feature_code":"PPL",
    "gn:name":"Kaithw\u0101ra",
    "gn:population":0,
    "gn:timezone":"Asia/Kolkata",
    "iso:country":"IN",
    "ks:ks_alt_nam":"Kaithw\u0101ra",
    "ks:ks_name":"Kaithwara",
    "ks:ks_pop":5281,
    "ks:ks_type":"VILLAGE",
    "name:eng_x_preferred":[
        "Kaithwara"
    ],
    "name:eng_x_variant":[
        "Kaithw\u0101ra"
    ],
    "wof:name":"Kaithwara",
    "wof:placetype":"locality",
    "wof:population":5281
},
  "geometry": {"coordinates":[77.13726,27.58853],"type":"Point"}
}