{
  "type": "Feature",
  "properties": {
    "iso:country":"IN",
    "ks:ks_name":"Parikalu",
    "ks:ks_pop":108,
    "ks:ks_type":"HABITATION",
    "name:eng_x_preferred":[
        "Parikalu"
    ],
    "wof:name":"Parikalu",
    "wof:placetype":"locality",
    "wof:population":108
},
  "geometry": {"coordinates":[82.32217900000001,17.707608],"type":"Point"}
}