{
  "type": "Feature",
  "properties": {
    "iso:country":"IN",
    "ks:ks_name":"Dhansad F",
    "ks:ks_pop":547,
    "ks:ks_type":"HABITATION",
    "name:eng_x_preferred":[
        "Dhansad F"
    ],
    "wof:name":"Dhansad F",
    "wof:placetype":"locality",
    "wof:population":547
},
  "geometry": {"coordinates":[73.3305,20.857417],"type":"Point"}
}