{
  "type": "Feature",
  "properties": {
    "iso:country":"IN",
    "ks:ks_name":"Ghat Mura",
    "ks:ks_pop":174,
    "ks:ks_type":"VILLAGE",
    "name:eng_x_preferred":[
        "Ghat Mura"
    ],
    "wof:name":"Ghat Mura",
    "wof:placetype":"locality",
    "wof:population":174
},
  "geometry": {"coordinates":[87.45725,22.742919],"type":"Point"}
}