{
  "type": "Feature",
  "properties": {
    "iso:country":"IN",
    "ks:ks_name":"Chandla Dungerwas",
    "ks:ks_pop":1855,
    "ks:ks_type":"VILLAGE",
    "name:eng_x_preferred":[
        "Chandla Dungerwas"
    ],
    "wof:name":"Chandla Dungerwas",
    "wof:placetype":"locality",
    "wof:population":1855
},
  "geometry": {"coordinates":[76.89537199999999,28.298366],"type":"Point"}
}