{
  "type": "Feature",
  "properties": {
    "gn:admin1_code":"19.0",
    "gn:admin2_code":"574.0",
    "gn:asciiname":"Mandiganahalli",
    "gn:country_code":"IN",
    "gn:dem":1016,
    "gn:feature_class":"P",
    "gn:feature_code":"PPL",
    "gn:name":"Mandiganahalli",
    "gn:population":0,
    "gn:timezone":"Asia/Kolkata",
    "iso:country":"IN",
    "wof:name":"Mandiganahalli",
    "wof:placetype":"locality"
},
  "geometry": {"coordinates":[76.11006999999999,13.12758],"type":"Point"}
}