{
  "type": "Feature",
  "properties": {
    "gn:admin1_code":"19.0",
    "gn:admin2_code":"577.0",
    "gn:asciiname":"Bidagal Mudlamatha",
    "gn:country_code":"IN",
    "gn:dem":686,
    "gn:feature_class":"P",
    "gn:feature_code":"PPL",
    "gn:name":"Bidagal M\u016bdlamatha",
    "gn:population":0,
    "gn:timezone":"Asia/Kolkata",
    "iso:country":"IN",
    "wof:name":"Bidagal Mudlamatha",
    "wof:placetype":"locality"
},
  "geometry": {"coordinates":[76.39400999999999,12.00989],"type":"Point"}
}