{
  "type": "Feature",
  "properties": {
    "gn:admin1_code":"34.0",
    "gn:admin2_code":"216.0",
    "gn:asciiname":"Katesar",
    "gn:country_code":"IN",
    "gn:dem":54,
    "gn:feature_class":"P",
    "gn:feature_code":"PPL",
    "gn:name":"Katesar",
    "gn:population":0,
    "gn:timezone":"Asia/Kolkata",
    "iso:country":"IN",
    "ks:ks_name":"Katesar",
    "ks:ks_pop":3053,
    "ks:ks_type":"VILLAGE",
    "name:eng_x_preferred":[
        "Katesar"
    ],
    "wof:name":"Katesar",
    "wof:placetype":"locality",
    "wof:population":3053
},
  "geometry": {"coordinates":[85.515872,25.917332],"type":"Point"}
}