{
  "type": "Feature",
  "properties": {
    "iso:country":"IN",
    "ks:ks_alt_nam":"Chidambara  kottagam",
    "ks:ks_name":"Chidambara Kottagam",
    "ks:ks_pop":138,
    "ks:ks_type":"HABITATION",
    "ks:ks_uagg_main":0,
    "name:eng_x_preferred":[
        "Chidambara Kottagam"
    ],
    "name:eng_x_variant":[
        "Chidambara  kottagam"
    ],
    "wof:name":"Chidambara Kottagam",
    "wof:placetype":"neighbourhood",
    "wof:population":138
},
  "geometry": {"coordinates":[79.59021799999999,10.611057],"type":"Point"}
}