{
  "type": "Feature",
  "properties": {
    "gn:admin1_code":"39.0",
    "gn:admin2_code":"64.0",
    "gn:asciiname":"Juniyagarhi",
    "gn:country_code":"IN",
    "gn:dem":1907,
    "gn:feature_class":"P",
    "gn:feature_code":"PPL",
    "gn:name":"Juniy\u0101garhi",
    "gn:population":0,
    "gn:timezone":"Asia/Kolkata",
    "iso:country":"IN",
    "ks:ks_alt_nam":"Juniy\u0101garhi",
    "ks:ks_name":"Juniyagarhi",
    "ks:ks_type":"VILLAGE",
    "name:eng_x_preferred":[
        "Juniyagarhi"
    ],
    "name:eng_x_variant":[
        "Juniy\u0101garhi"
    ],
    "wof:name":"Juniyagarhi",
    "wof:placetype":"locality"
},
  "geometry": {"coordinates":[79.13605,29.869974],"type":"Point"}
}