{
  "type": "Feature",
  "properties": {
    "iso:country":"IN",
    "ks:ks_name":"Haribereni",
    "ks:ks_pop":314,
    "ks:ks_type":"VILLAGE",
    "name:eng_x_preferred":[
        "Haribereni"
    ],
    "wof:name":"Haribereni",
    "wof:placetype":"locality",
    "wof:population":314
},
  "geometry": {"coordinates":[84.982038,21.151054],"type":"Point"}
}