{
  "type": "Feature",
  "properties": {
    "iso:country":"IN",
    "ks:ks_name":"Thar Lahatai",
    "ks:ks_pop":49,
    "ks:ks_type":"HABITATION",
    "name:eng_x_preferred":[
        "Thar Lahatai"
    ],
    "wof:name":"Thar Lahatai",
    "wof:placetype":"locality",
    "wof:population":49
},
  "geometry": {"coordinates":[78.613753,26.972749],"type":"Point"}
}