{
  "type": "Feature",
  "properties": {
    "iso:country":"IN",
    "ks:ks_name":"Deosar",
    "ks:ks_pop":195,
    "ks:ks_type":"HABITATION",
    "name:eng_x_preferred":[
        "Deosar"
    ],
    "wof:name":"Deosar",
    "wof:placetype":"locality",
    "wof:population":195
},
  "geometry": {"coordinates":[71.53231700000001,25.305475],"type":"Point"}
}