{
  "type": "Feature",
  "properties": {
    "gn:admin1_code":"16",
    "gn:admin2_code":"509.0",
    "gn:asciiname":"Khatgaon",
    "gn:country_code":"IN",
    "gn:dem":251,
    "gn:feature_class":"P",
    "gn:feature_code":"PPL",
    "gn:name":"Kh\u0101tgaon",
    "gn:population":0,
    "gn:timezone":"Asia/Kolkata",
    "iso:country":"IN",
    "ks:ks_alt_nam":"Kh\u0101tgaon",
    "ks:ks_name":"Khatgaon",
    "ks:ks_type":"VILLAGE",
    "name:eng_x_preferred":[
        "Khatgaon"
    ],
    "name:eng_x_variant":[
        "Kh\u0101tgaon"
    ],
    "wof:name":"Khatgaon",
    "wof:placetype":"locality"
},
  "geometry": {"coordinates":[79.835577,20.382468],"type":"Point"}
}