{
  "type": "Feature",
  "properties": {
    "iso:country":"IN",
    "ks:ks_name":"Dabholwadi",
    "ks:ks_pop":185,
    "ks:ks_type":"HABITATION",
    "ks:ks_uagg_main":0,
    "name:eng_x_preferred":[
        "Dabholwadi"
    ],
    "wof:name":"Dabholwadi",
    "wof:placetype":"neighbourhood",
    "wof:population":185
},
  "geometry": {"coordinates":[73.126407,18.851934],"type":"Point"}
}