{
  "type": "Feature",
  "properties": {
    "gn:admin1_code":"25.0",
    "gn:admin2_code":"630.0",
    "gn:asciiname":"Gettur",
    "gn:country_code":"IN",
    "gn:dem":497,
    "gn:feature_class":"P",
    "gn:feature_code":"PPL",
    "gn:name":"Gett\u016br",
    "gn:population":0,
    "gn:timezone":"Asia/Kolkata",
    "iso:country":"IN",
    "ks:ks_name":"Gettur",
    "ks:ks_pop":795,
    "ks:ks_type":"HABITATION",
    "ks:ks_uagg_main":0,
    "name:eng_x_preferred":[
        "Gettur"
    ],
    "wof:name":"Gettur",
    "wof:placetype":"neighbourhood",
    "wof:population":795
},
  "geometry": {"coordinates":[77.962675,12.138178],"type":"Point"}
}