{
  "type": "Feature",
  "properties": {
    "iso:country":"IN",
    "ks:ks_name":"Dumirta",
    "ks:ks_pop":324,
    "ks:ks_type":"VILLAGE",
    "name:eng_x_preferred":[
        "Dumirta"
    ],
    "wof:name":"Dumirta",
    "wof:placetype":"locality",
    "wof:population":324
},
  "geometry": {"coordinates":[85.149145,22.356407],"type":"Point"}
}