{
  "type": "Feature",
  "properties": {
    "iso:country":"IN",
    "ks:ks_name":"Seeragampatty",
    "ks:ks_pop":319,
    "ks:ks_type":"HABITATION",
    "ks:ks_uagg_main":0,
    "name:eng_x_preferred":[
        "Seeragampatty"
    ],
    "wof:name":"Seeragampatty",
    "wof:placetype":"neighbourhood",
    "wof:population":319
},
  "geometry": {"coordinates":[77.88189800000001,10.169997],"type":"Point"}
}