{
  "type": "Feature",
  "properties": {
    "gn:admin1_code":"39.0",
    "gn:admin2_code":"68.0",
    "gn:asciiname":"Sisauna",
    "gn:country_code":"IN",
    "gn:dem":276,
    "gn:feature_class":"P",
    "gn:feature_code":"PPL",
    "gn:name":"Sisauna",
    "gn:population":0,
    "gn:timezone":"Asia/Kolkata",
    "iso:country":"IN",
    "ks:ks_name":"Sisauna",
    "ks:ks_pop":1625,
    "ks:ks_type":"VILLAGE",
    "ks:ks_uagg_main":0,
    "name:eng_x_preferred":[
        "Sisauna"
    ],
    "wof:name":"Sisauna",
    "wof:placetype":"neighbourhood",
    "wof:population":1625
},
  "geometry": {"coordinates":[77.800359,29.960141],"type":"Point"}
}