{
  "type": "Feature",
  "properties": {
    "gn:admin1_code":"2",
    "gn:admin2_code":"545.0",
    "gn:asciiname":"Errampalem",
    "gn:country_code":"IN",
    "gn:dem":124,
    "gn:feature_class":"P",
    "gn:feature_code":"PPL",
    "gn:name":"Erramp\u0101lem",
    "gn:population":0,
    "gn:timezone":"Asia/Kolkata",
    "iso:country":"IN",
    "ks:ks_name":"Yerrampalem",
    "ks:ks_pop":145,
    "ks:ks_type":"VILLAGE",
    "name:eng_x_preferred":[
        "Yerrampalem"
    ],
    "name:eng_x_variant":[
        "Errampalem"
    ],
    "wof:name":"Yerrampalem",
    "wof:placetype":"locality",
    "wof:population":145
},
  "geometry": {"coordinates":[81.891352,17.373718],"type":"Point"}
}