{
  "type": "Feature",
  "properties": {
    "iso:country":"IN",
    "ks:ks_name":"Bishunpur Mohan Urf Morangi",
    "ks:ks_pop":913,
    "ks:ks_type":"VILLAGE",
    "name:eng_x_preferred":[
        "Bishunpur Mohan Urf Morangi"
    ],
    "wof:name":"Bishunpur Mohan Urf Morangi",
    "wof:placetype":"locality",
    "wof:population":913
},
  "geometry": {"coordinates":[85.36552399999999,25.85465],"type":"Point"}
}