{
  "type": "Feature",
  "properties": {
    "iso:country":"IN",
    "ks:ks_name":"Kagodu",
    "ks:ks_pop":83,
    "ks:ks_type":"HABITATION",
    "name:eng_x_preferred":[
        "Kagodu"
    ],
    "wof:name":"Kagodu",
    "wof:placetype":"locality",
    "wof:population":83
},
  "geometry": {"coordinates":[75.0676,13.932878],"type":"Point"}
}