{
  "type": "Feature",
  "properties": {
    "iso:country":"IN",
    "ks:ks_name":"Madhopur",
    "ks:ks_pop":230,
    "ks:ks_type":"VILLAGE",
    "name:eng_x_preferred":[
        "Madhopur"
    ],
    "wof:name":"Madhopur",
    "wof:placetype":"locality",
    "wof:population":230
},
  "geometry": {"coordinates":[87.006241,24.072647],"type":"Point"}
}