{
  "type": "Feature",
  "properties": {
    "iso:country":"IN",
    "name:ara_x_preferred":[
        "\u0641\u064a\u0646\u0643\u0627\u062a\u0628\u0648\u0631\u0627\u0645"
    ],
    "name:ben_bn_x_preferred":[
        "\u09ad\u09c7\u0999\u09cd\u0995\u099f\u09aa\u09c2\u09b0\u09ae"
    ],
    "name:ben_in_x_preferred":[
        "\u09ad\u09c7\u0999\u09cd\u0995\u099f\u09aa\u09c2\u09b0\u09ae"
    ],
    "name:guj_x_preferred":[
        "\u0ab5\u0ac7\u0a82\u0a95\u0a9f\u0aaa\u0ac1\u0ab0\u0aae"
    ],
    "name:hin_x_preferred":[
        "\u0935\u0947\u0902\u0915\u091f\u092a\u0941\u0930\u092e"
    ],
    "name:kan_x_preferred":[
        "\u0cb5\u0cc6\u0c82\u0c95\u0c9f\u0caa\u0cc1\u0cb0\u0cae\u0ccd"
    ],
    "name:mal_x_preferred":[
        "\u0d35\u0d46\u0d19\u0d4d\u0d15\u0d1f\u0d2a\u0d41\u0d30\u0d02"
    ],
    "name:mar_x_preferred":[
        "\u0935\u094d\u092f\u0902\u0915\u091f\u092a\u0941\u0930\u092e"
    ],
    "name:pan_x_preferred":[
        "\u0a35\u0a48\u0a28\u0a15\u0a1f\u0a3e\u0a2a\u0a41\u0a30\u0a2e"
    ],
    "name:tam_x_preferred":[
        "\u0bb5\u0bc6\u0b99\u0bcd\u0b95\u0b9f\u0bbe\u0baa\u0bc1\u0bb0\u0bae\u0bcd"
    ],
    "name:tel_x_preferred":[
        "\u0c35\u0c46\u0c02\u0c15\u0c1f\u0c3e\u0c2a\u0c41\u0c30\u0c02"
    ],
    "name:tel_x_variant":[
        "\u0c35\u0c46\u0c02\u0c15\u0c1f\u0c3e\u0c2a\u0c41\u0c30\u0c02(\u0c05\u0c26\u0c4d\u0c26\u0c02\u0c15\u0c3f)"
    ],
    "name:urd_x_preferred":[
        "\u0648\u06cc\u0646\u06a9\u0679\u0627 \u067e\u0648\u0631\u0645"
    ],
    "qs:name":"Venkatapuram",
    "qs:name_adm0":"India",
    "qs:name_adm1":"Tamil Nadu",
    "qs:photos":4,
    "qs:photos_1k":1,
    "qs:photos_9k":1,
    "qs:photos_9r":1,
    "qs:photos_all":4,
    "qs:photos_sr":1,
    "qs:placetype":"Suburb",
    "qs:pop_sr":"0",
    "wd:wordcount":66,
    "wof:name":"Venkatapuram",
    "wof:placetype":"neighbourhood"
},
  "geometry": {"coordinates":[80.213584,13.148358],"type":"Point"}
}