{
  "type": "Feature",
  "properties": {
    "iso:country":"IN",
    "name:tel_x_preferred":[
        "\u0c35\u0c46\u0c02\u0c15\u0c1f\u0c3e\u0c2a\u0c41\u0c30\u0c02(\u0c05\u0c26\u0c4d\u0c26\u0c02\u0c15\u0c3f)"
    ],
    "qs:name":"Venkatapuram",
    "qs:name_adm0":"India",
    "qs:name_adm1":"Tamil Nadu",
    "qs:photos":4,
    "qs:photos_1k":1,
    "qs:photos_9k":1,
    "qs:photos_9r":1,
    "qs:photos_all":4,
    "qs:photos_sr":1,
    "qs:placetype":"Suburb",
    "qs:pop_sr":"0",
    "wd:wordcount":66,
    "wof:name":"Venkatapuram",
    "wof:placetype":"neighbourhood"
},
  "geometry": {"coordinates":[80.213584,13.148358],"type":"Point"}
}