{
  "type": "Feature",
  "properties": {
    "iso:country":"IN",
    "ks:ks_name":"Gundardiya",
    "ks:ks_pop":801,
    "ks:ks_type":"HABITATION",
    "name:eng_x_preferred":[
        "Gundardiya"
    ],
    "wof:name":"Gundardiya",
    "wof:placetype":"locality",
    "wof:population":801
},
  "geometry": {"coordinates":[75.92141100000001,23.551004],"type":"Point"}
}