{
  "type": "Feature",
  "properties": {
    "iso:country":"IN",
    "ks:ks_name":"Gaonthanpada",
    "ks:ks_pop":86,
    "ks:ks_type":"HABITATION",
    "name:eng_x_preferred":[
        "Gaonthanpada"
    ],
    "wof:name":"Gaonthanpada",
    "wof:placetype":"locality",
    "wof:population":86
},
  "geometry": {"coordinates":[72.876908,19.909656],"type":"Point"}
}