{
  "type": "Feature",
  "properties": {
    "iso:country":"IN",
    "ks:ks_name":"Banwadi",
    "ks:ks_pop":101,
    "ks:ks_type":"HABITATION",
    "name:eng_x_preferred":[
        "Banwadi"
    ],
    "wof:name":"Banwadi",
    "wof:placetype":"locality",
    "wof:population":101
},
  "geometry": {"coordinates":[73.275403,17.279214],"type":"Point"}
}