{
  "type": "Feature",
  "properties": {
    "gn:admin1_code":"36.0",
    "gn:admin2_code":"182.0",
    "gn:asciiname":"Mauli",
    "gn:country_code":"IN",
    "gn:dem":104,
    "gn:feature_class":"P",
    "gn:feature_code":"PPL",
    "gn:name":"Mauli",
    "gn:population":0,
    "gn:timezone":"Asia/Kolkata",
    "iso:country":"IN",
    "name:ind_x_preferred":[
        "Mauli"
    ],
    "name:min_x_preferred":[
        "Wangsa Mauliwarmadewa"
    ],
    "wof:name":"Mauli",
    "wof:placetype":"locality"
},
  "geometry": {"coordinates":[82.29907,27.34652],"type":"Point"}
}