{
  "type": "Feature",
  "properties": {
    "iso:country":"IN",
    "ks:ks_name":"Baldihi",
    "ks:ks_pop":0,
    "ks:ks_type":"VILLAGE",
    "name:eng_x_preferred":[
        "Baldihi"
    ],
    "wof:name":"Baldihi",
    "wof:placetype":"locality",
    "wof:population":0
},
  "geometry": {"coordinates":[85.297241,21.875029],"type":"Point"}
}