{
  "type": "Feature",
  "properties": {
    "gn:admin1_code":"2",
    "gn:admin2_code":"544.0",
    "gn:asciiname":"Arabupalem",
    "gn:country_code":"IN",
    "gn:dem":28,
    "gn:feature_class":"P",
    "gn:feature_code":"PPL",
    "gn:name":"Arabup\u0101lem",
    "gn:population":0,
    "gn:timezone":"Asia/Kolkata",
    "iso:country":"IN",
    "wof:name":"Arabupalem",
    "wof:placetype":"locality"
},
  "geometry": {"coordinates":[82.98165,17.64602],"type":"Point"}
}