{
  "type": "Feature",
  "properties": {
    "iso:country":"IN",
    "ks:ks_name":"Marampatty",
    "ks:ks_pop":101,
    "ks:ks_type":"HABITATION",
    "name:eng_x_preferred":[
        "Marampatty"
    ],
    "wof:name":"Marampatty",
    "wof:placetype":"locality",
    "wof:population":101
},
  "geometry": {"coordinates":[78.19848500000001,11.0638],"type":"Point"}
}