{
  "type": "Feature",
  "properties": {
    "gn:admin1_code":"23.0",
    "gn:admin2_code":"53.0",
    "gn:asciiname":"Manan",
    "gn:country_code":"IN",
    "gn:dem":244,
    "gn:feature_class":"P",
    "gn:feature_code":"PPL",
    "gn:name":"M\u0101n\u0101n",
    "gn:population":0,
    "gn:timezone":"Asia/Kolkata",
    "iso:country":"IN",
    "name:spa_x_preferred":[
        "Manan"
    ],
    "wof:name":"Manan",
    "wof:placetype":"locality"
},
  "geometry": {"coordinates":[75.94807,30.40377],"type":"Point"}
}