{
  "type": "Feature",
  "properties": {
    "iso:country":"IN",
    "ks:ks_name":"Hijlak",
    "ks:ks_pop":3207,
    "ks:ks_type":"VILLAGE",
    "ks:ks_uagg_main":0,
    "name:eng_x_preferred":[
        "Hijlak"
    ],
    "wof:name":"Hijlak",
    "wof:placetype":"neighbourhood",
    "wof:population":3207
},
  "geometry": {"coordinates":[87.95339,22.476186],"type":"Point"}
}