{
  "type": "Feature",
  "properties": {
    "gn:admin1_code":"25.0",
    "gn:admin2_code":"631.0",
    "gn:asciiname":"Kottagonda Palli",
    "gn:country_code":"IN",
    "gn:dem":899,
    "gn:feature_class":"P",
    "gn:feature_code":"PPL",
    "gn:name":"Kottagonda Palli",
    "gn:population":0,
    "gn:timezone":"Asia/Kolkata",
    "iso:country":"IN",
    "wof:name":"Kottagonda Palli",
    "wof:placetype":"locality"
},
  "geometry": {"coordinates":[77.779,12.72948],"type":"Point"}
}