{
  "type": "Feature",
  "properties": {
    "gn:admin1_code":"36",
    "gn:admin2_code":"152.0",
    "gn:asciiname":"Senjna Am Khera",
    "gn:country_code":"IN",
    "gn:dem":154,
    "gn:feature_class":"P",
    "gn:feature_code":"PPL",
    "gn:name":"S\u0113njn\u0101 \u0100m Kh\u0113r\u0101",
    "gn:population":0,
    "gn:timezone":"Asia/Kolkata",
    "iso:country":"IN",
    "wof:name":"Senjna Am Khera",
    "wof:placetype":"neighbourhood"
},
  "geometry": {"coordinates":[79.67079,27.79198],"type":"Point"}
}