{
  "type": "Feature",
  "properties": {
    "iso:country":"IN",
    "ks:ks_name":"Oila Nadipar",
    "ks:ks_pop":28,
    "ks:ks_type":"HABITATION",
    "name:eng_x_preferred":[
        "Oila Nadipar"
    ],
    "wof:name":"Oila Nadipar",
    "wof:placetype":"locality",
    "wof:population":28
},
  "geometry": {"coordinates":[80.76875099999999,24.287775],"type":"Point"}
}