{
  "type": "Feature",
  "properties": {
    "iso:country":"IN",
    "ks:ks_name":"Dugri Pant",
    "ks:ks_pop":247,
    "ks:ks_type":"VILLAGE",
    "name:eng_x_preferred":[
        "Dugri Pant"
    ],
    "wof:name":"Dugri Pant",
    "wof:placetype":"locality",
    "wof:population":247
},
  "geometry": {"coordinates":[80.071945,29.714566],"type":"Point"}
}