{
  "type": "Feature",
  "properties": {
    "iso:country":"IN",
    "ks:ks_name":"B.bachahalli",
    "ks:ks_pop":1235,
    "ks:ks_type":"VILLAGE",
    "name:eng_x_preferred":[
        "B.bachahalli"
    ],
    "wof:name":"B.bachahalli",
    "wof:placetype":"locality",
    "wof:population":1235
},
  "geometry": {"coordinates":[76.52057499999999,12.572953],"type":"Point"}
}