{
  "type": "Feature",
  "properties": {
    "iso:country":"IN",
    "ks:ks_name":"Balabhadrapur",
    "ks:ks_pop":0,
    "ks:ks_type":"VILLAGE",
    "name:eng_x_preferred":[
        "Balabhadrapur"
    ],
    "wof:name":"Balabhadrapur",
    "wof:placetype":"locality",
    "wof:population":0
},
  "geometry": {"coordinates":[85.46046,20.206623],"type":"Point"}
}