{
  "type": "Feature",
  "properties": {
    "iso:country":"IN",
    "ks:ks_name":"Andilpur",
    "ks:ks_pop":0,
    "ks:ks_type":"VILLAGE",
    "name:eng_x_preferred":[
        "Andilpur"
    ],
    "wof:name":"Andilpur",
    "wof:placetype":"locality",
    "wof:population":0
},
  "geometry": {"coordinates":[88.474502,22.234786],"type":"Point"}
}