{
  "type": "Feature",
  "properties": {
    "iso:country":"IN",
    "ks:ks_name":"Hinachi",
    "ks:ks_pop":75,
    "ks:ks_type":"HABITATION",
    "name:eng_x_preferred":[
        "Hinachi"
    ],
    "wof:name":"Hinachi",
    "wof:placetype":"locality",
    "wof:population":75
},
  "geometry": {"coordinates":[75.43303299999999,13.516263],"type":"Point"}
}