{
  "type": "Feature",
  "properties": {
    "iso:country":"IN",
    "ks:ks_name":"Kappankuzhi",
    "ks:ks_pop":1061,
    "ks:ks_type":"HABITATION",
    "ks:ks_uagg_main":0,
    "name:eng_x_preferred":[
        "Kappankuzhi"
    ],
    "wof:name":"Kappankuzhi",
    "wof:placetype":"neighbourhood",
    "wof:population":1061
},
  "geometry": {"coordinates":[76.552274,9.830888],"type":"Point"}
}