{
  "type": "Feature",
  "properties": {
    "iso:country":"IN",
    "ks:ks_name":"Gondurumale",
    "ks:ks_pop":70,
    "ks:ks_type":"HABITATION",
    "name:eng_x_preferred":[
        "Gondurumale"
    ],
    "wof:name":"Gondurumale",
    "wof:placetype":"locality",
    "wof:population":70
},
  "geometry": {"coordinates":[75.34918,13.997404],"type":"Point"}
}