{
  "type": "Feature",
  "properties": {
    "gn:admin1_code":"24.0",
    "gn:admin2_code":"130.0",
    "gn:asciiname":"Kagwas",
    "gn:country_code":"IN",
    "gn:dem":358,
    "gn:feature_class":"P",
    "gn:feature_code":"PPL",
    "gn:name":"K\u0101gwas",
    "gn:population":0,
    "gn:timezone":"Asia/Kolkata",
    "iso:country":"IN",
    "ks:ks_alt_nam":"K\u0101gwas",
    "ks:ks_name":"Kagwas",
    "ks:ks_type":"VILLAGE",
    "name:eng_x_preferred":[
        "Kagwas"
    ],
    "name:eng_x_variant":[
        "K\u0101gwas"
    ],
    "wof:name":"Kagwas",
    "wof:placetype":"locality"
},
  "geometry": {"coordinates":[73.147824,24.489978],"type":"Point"}
}