{
  "type": "Feature",
  "properties": {
    "gn:admin1_code":"2",
    "gn:admin2_code":"544.0",
    "gn:asciiname":"Chidipeta",
    "gn:country_code":"IN",
    "gn:dem":783,
    "gn:feature_class":"P",
    "gn:feature_code":"PPL",
    "gn:name":"Ch\u012bdipeta",
    "gn:population":0,
    "gn:timezone":"Asia/Kolkata",
    "iso:country":"IN",
    "ks:ks_name":"Chadipeta",
    "ks:ks_pop":218,
    "ks:ks_type":"VILLAGE",
    "ks:ks_uagg_main":0,
    "name:eng_x_preferred":[
        "Chadipeta"
    ],
    "wof:name":"Chadipeta",
    "wof:placetype":"neighbourhood",
    "wof:population":218
},
  "geometry": {"coordinates":[82.348552,17.873786],"type":"Point"}
}