{
  "type": "Feature",
  "properties": {
    "gn:admin1_code":"13.0",
    "gn:admin2_code":"600.0",
    "gn:asciiname":"Kuriyod",
    "gn:country_code":"IN",
    "gn:dem":66,
    "gn:feature_class":"P",
    "gn:feature_code":"PPL",
    "gn:name":"Kuriyod",
    "gn:population":0,
    "gn:timezone":"Asia/Kolkata",
    "iso:country":"IN",
    "wof:name":"Kuriyod",
    "wof:placetype":"locality"
},
  "geometry": {"coordinates":[76.87498000000002,8.85608],"type":"Point"}
}