{
  "type": "Feature",
  "properties": {
    "gn:admin1_code":"11",
    "gn:admin2_code":"33.0",
    "gn:asciiname":"Sewan",
    "gn:country_code":"IN",
    "gn:dem":1653,
    "gn:feature_class":"P",
    "gn:feature_code":"PPL",
    "gn:name":"Sewan",
    "gn:population":0,
    "gn:timezone":"Asia/Kolkata",
    "iso:country":"IN",
    "wof:name":"Sewan",
    "wof:placetype":"locality"
},
  "geometry": {"coordinates":[77.16488000000003,31.17395],"type":"Point"}
}