{
  "type": "Feature",
  "properties": {
    "iso:country":"IN",
    "ks:ks_name":"Ibrahimpur Mafi",
    "ks:ks_pop":30,
    "ks:ks_type":"VILLAGE",
    "name:eng_x_preferred":[
        "Ibrahimpur Mafi"
    ],
    "wof:name":"Ibrahimpur Mafi",
    "wof:placetype":"locality",
    "wof:population":30
},
  "geometry": {"coordinates":[76.82932,27.921969],"type":"Point"}
}