{
  "type": "Feature",
  "properties": {
    "iso:country":"IN",
    "ks:ks_alt_nam":"MANDAL TOLA",
    "ks:ks_name":"Mandal Tola",
    "ks:ks_pop":150,
    "ks:ks_type":"HABITATION",
    "name:eng_x_preferred":[
        "Mandal Tola"
    ],
    "wof:name":"Mandal Tola",
    "wof:placetype":"locality",
    "wof:population":150
},
  "geometry": {"coordinates":[86.1495,25.11757],"type":"Point"}
}