{
  "type": "Feature",
  "properties": {
    "gn:admin1_code":"34.0",
    "gn:admin2_code":"219.0",
    "gn:asciiname":"Sangrampur",
    "gn:country_code":"IN",
    "gn:dem":61,
    "gn:feature_class":"P",
    "gn:feature_code":"PPL",
    "gn:name":"Sangr\u0101mpur",
    "gn:population":0,
    "gn:timezone":"Asia/Kolkata",
    "iso:country":"IN",
    "ks:ks_name":"Sagrampur",
    "ks:ks_pop":1607,
    "ks:ks_type":"VILLAGE",
    "ks:ks_uagg_main":0,
    "name:eng_x_preferred":[
        "Sagrampur"
    ],
    "name:fra_x_preferred":[
        "Sangrampur"
    ],
    "name:new_x_preferred":[
        "\u0938\u0902\u0917\u094d\u0930\u093e\u092e\u092a\u0941\u0930 \u0917\u093e\u0935\u093f\u0938"
    ],
    "name:pol_x_preferred":[
        "Sangrampur"
    ],
    "wof:name":"Sagrampur",
    "wof:placetype":"neighbourhood",
    "wof:population":1607
},
  "geometry": {"coordinates":[84.917631,26.030069],"type":"Point"}
}