{
  "type": "Feature",
  "properties": {
    "iso:country":"IN",
    "ks:ks_name":"Goela Khurd",
    "ks:ks_type":"VILLAGE",
    "ks:ks_uagg_main":0,
    "name:eng_x_preferred":[
        "Goela Khurd"
    ],
    "wof:name":"Goela Khurd",
    "wof:placetype":"neighbourhood"
},
  "geometry": {"coordinates":[77.011318,28.58561],"type":"Point"}
}