{
  "type": "Feature",
  "properties": {
    "gn:admin1_code":"19.0",
    "gn:admin2_code":"567.0",
    "gn:asciiname":"Kenchanahalu",
    "gn:country_code":"IN",
    "gn:dem":714,
    "gn:feature_class":"P",
    "gn:feature_code":"PPL",
    "gn:name":"Kenchanah\u0101lu",
    "gn:population":0,
    "gn:timezone":"Asia/Kolkata",
    "iso:country":"IN",
    "wof:name":"Kenchanahalu",
    "wof:placetype":"locality"
},
  "geometry": {"coordinates":[76.03924000000001,13.97676],"type":"Point"}
}