{
  "type": "Feature",
  "properties": {
    "gn:admin1_code":"36.0",
    "gn:admin2_code":"135.0",
    "gn:asciiname":"Talwar",
    "gn:country_code":"IN",
    "gn:dem":207,
    "gn:feature_class":"P",
    "gn:feature_code":"PPL",
    "gn:name":"Talw\u0101r",
    "gn:population":0,
    "gn:timezone":"Asia/Kolkata",
    "iso:country":"IN",
    "ks:ks_alt_nam":"Talw\u0101r",
    "ks:ks_name":"Talwar",
    "ks:ks_pop":2486,
    "ks:ks_type":"VILLAGE",
    "ks:ks_uagg_main":0,
    "name:ben_x_preferred":[
        "\u09a4\u09b2\u09cb\u09af\u09bc\u09be\u09b0"
    ],
    "name:cat_x_preferred":[
        "Talwar"
    ],
    "name:deu_x_preferred":[
        "Talwar"
    ],
    "name:eng_x_preferred":[
        "Talwar"
    ],
    "name:eng_x_variant":[
        "Talw\u0101r"
    ],
    "name:fas_x_preferred":[
        "\u062a\u0644\u0648\u0627\u0631"
    ],
    "name:glg_x_preferred":[
        "Talwar"
    ],
    "name:hin_x_preferred":[
        "\u0924\u0932\u0935\u093e\u0930"
    ],
    "name:ita_x_preferred":[
        "Talwar"
    ],
    "name:jpn_x_preferred":[
        "\u30bf\u30eb\u30ef\u30fc\u30eb"
    ],
    "name:lit_x_preferred":[
        "Talvaras"
    ],
    "name:pol_x_preferred":[
        "Talwar"
    ],
    "name:ron_x_preferred":[
        "Talwar"
    ],
    "name:rus_x_preferred":[
        "\u0422\u0430\u043b\u044c\u0432\u0430\u0440"
    ],
    "name:snd_x_preferred":[
        "\u062a\u0644\u0648\u0627\u0631"
    ],
    "name:spa_x_preferred":[
        "Talwar"
    ],
    "wof:name":"Talwar",
    "wof:placetype":"neighbourhood",
    "wof:population":2486
},
  "geometry": {"coordinates":[78.55497200000001,28.764563],"type":"Point"}
}