{
  "type": "Feature",
  "properties": {
    "iso:country":"IN",
    "ks:ks_name":"Sonaram Para",
    "ks:ks_pop":280,
    "ks:ks_type":"HABITATION",
    "name:eng_x_preferred":[
        "Sonaram Para"
    ],
    "wof:name":"Sonaram Para",
    "wof:placetype":"locality",
    "wof:population":280
},
  "geometry": {"coordinates":[92.15150300000001,24.1993],"type":"Point"}
}