{
  "type": "Feature",
  "properties": {
    "gn:admin1_code":"2.0",
    "gn:admin2_code":"554.0",
    "gn:asciiname":"Varadappanayanipeta",
    "gn:country_code":"IN",
    "gn:dem":432,
    "gn:feature_class":"P",
    "gn:feature_code":"PPL",
    "gn:name":"Varadappan\u0101yanipeta",
    "gn:population":0,
    "gn:timezone":"Asia/Kolkata",
    "iso:country":"IN",
    "wof:name":"Varadappanayanipeta",
    "wof:placetype":"locality"
},
  "geometry": {"coordinates":[79.07384,13.53685],"type":"Point"}
}