{
  "type": "Feature",
  "properties": {
    "iso:country":"IN",
    "ks:ks_alt_nam":"PAHELA PAR",
    "ks:ks_name":"Pahela Par",
    "ks:ks_pop":302,
    "ks:ks_type":"HABITATION",
    "name:eng_x_preferred":[
        "Pahela Par"
    ],
    "wof:name":"Pahela Par",
    "wof:placetype":"locality",
    "wof:population":302
},
  "geometry": {"coordinates":[81.741033,26.153788],"type":"Point"}
}