{
  "type": "Feature",
  "properties": {
    "iso:country":"IN",
    "ks:ks_name":"Kotwarpara",
    "ks:ks_pop":166,
    "ks:ks_type":"HABITATION",
    "name:eng_x_preferred":[
        "Kotwarpara"
    ],
    "wof:name":"Kotwarpara",
    "wof:placetype":"locality",
    "wof:population":166
},
  "geometry": {"coordinates":[81.973102,19.392867],"type":"Point"}
}