{
  "type": "Feature",
  "properties": {
    "iso:country":"IN",
    "ks:ks_name":"Kanatia",
    "ks:ks_pop":711,
    "ks:ks_type":"VILLAGE",
    "name:eng_x_preferred":[
        "Kanatia"
    ],
    "wof:name":"Kanatia",
    "wof:placetype":"locality",
    "wof:population":711
},
  "geometry": {"coordinates":[86.700284,20.986664],"type":"Point"}
}