{
  "type": "Feature",
  "properties": {
    "iso:country":"IN",
    "ks:ks_name":"Nadavatti Family",
    "ks:ks_pop":156,
    "ks:ks_type":"HABITATION",
    "name:eng_x_preferred":[
        "Nadavatti Family"
    ],
    "wof:name":"Nadavatti Family",
    "wof:placetype":"locality",
    "wof:population":156
},
  "geometry": {"coordinates":[75.608611,12.335278],"type":"Point"}
}