{
  "type": "Feature",
  "properties": {
    "iso:country":"IN",
    "ks:ks_alt_nam":"Gurlhos\u016br",
    "ks:ks_name":"Gurlhosur",
    "ks:ks_pop":63,
    "ks:ks_type":"VILLAGE",
    "name:eng_x_preferred":[
        "Gurlhosur"
    ],
    "name:eng_x_variant":[
        "Gurlhos\u016br"
    ],
    "wof:name":"Gurlhosur",
    "wof:placetype":"locality",
    "wof:population":63
},
  "geometry": {"coordinates":[75.062174,15.790843],"type":"Point"}
}