{
  "type": "Feature",
  "properties": {
    "gn:admin1_code":"2.0",
    "gn:admin2_code":"551.0",
    "gn:asciiname":"Uppalapadu",
    "gn:country_code":"IN",
    "gn:dem":166,
    "gn:feature_class":"P",
    "gn:feature_code":"PPL",
    "gn:name":"Uppalap\u0101du",
    "gn:population":0,
    "gn:timezone":"Asia/Kolkata",
    "iso:country":"IN",
    "ks:ks_name":"Uppalapadu",
    "ks:ks_pop":271,
    "ks:ks_type":"HABITATION",
    "name:eng_x_preferred":[
        "Uppalapadu"
    ],
    "name:epo_x_preferred":[
        "Uppalapadu"
    ],
    "name:tel_x_preferred":[
        "\u0c09\u0c2a\u0c4d\u0c2a\u0c32\u0c2a\u0c3e\u0c21\u0c41"
    ],
    "wof:name":"Uppalapadu",
    "wof:placetype":"locality",
    "wof:population":271
},
  "geometry": {"coordinates":[78.608582,14.945167],"type":"Point"}
}