{
  "type": "Feature",
  "properties": {
    "iso:country":"IN",
    "ks:ks_name":"Bolewadi",
    "ks:ks_pop":217,
    "ks:ks_type":"HABITATION",
    "name:eng_x_preferred":[
        "Bolewadi"
    ],
    "wof:name":"Bolewadi",
    "wof:placetype":"locality",
    "wof:population":217
},
  "geometry": {"coordinates":[73.456011,17.238742],"type":"Point"}
}