{
  "type": "Feature",
  "properties": {
    "gn:admin1_code":"36.0",
    "gn:admin2_code":"176.0",
    "gn:asciiname":"Bhadras",
    "gn:country_code":"IN",
    "gn:dem":131,
    "gn:feature_class":"P",
    "gn:feature_code":"PPL",
    "gn:name":"Bhadras",
    "gn:population":0,
    "gn:timezone":"Asia/Kolkata",
    "iso:country":"IN",
    "wof:name":"Bhadras",
    "wof:placetype":"locality"
},
  "geometry": {"coordinates":[80.98992,27.22507],"type":"Point"}
}