{
  "type": "Feature",
  "properties": {
    "iso:country":"IN",
    "ks:ks_name":"5 KPD",
    "ks:ks_pop":130,
    "ks:ks_type":"VILLAGE",
    "name:eng_x_preferred":[
        "5 KPD"
    ],
    "wof:name":"5 KPD",
    "wof:placetype":"locality",
    "wof:population":130
},
  "geometry": {"coordinates":[72.875139,28.799252],"type":"Point"}
}