{
  "type": "Feature",
  "properties": {
    "gn:admin1_code":"21.0",
    "gn:admin2_code":"390.0",
    "gn:asciiname":"Pangama",
    "gn:country_code":"IN",
    "gn:dem":727,
    "gn:feature_class":"P",
    "gn:feature_code":"PPL",
    "gn:name":"Pangama",
    "gn:population":0,
    "gn:timezone":"Asia/Kolkata",
    "iso:country":"IN",
    "ks:ks_name":"Pangama",
    "ks:ks_type":"VILLAGE",
    "name:eng_x_preferred":[
        "Pangama"
    ],
    "wof:name":"Pangama",
    "wof:placetype":"locality"
},
  "geometry": {"coordinates":[83.868887,19.797034],"type":"Point"}
}