{
  "type": "Feature",
  "properties": {
    "gn:admin1_code":"21.0",
    "gn:admin2_code":"390.0",
    "gn:asciiname":"Pangama",
    "gn:country_code":"IN",
    "gn:dem":727,
    "gn:feature_class":"P",
    "gn:feature_code":"PPL",
    "gn:name":"Pangama",
    "gn:population":0,
    "gn:timezone":"Asia/Kolkata",
    "iso:country":"IN",
    "wof:name":"Pangama",
    "wof:placetype":"locality"
},
  "geometry": {"coordinates":[83.86889000000002,19.79703],"type":"Point"}
}