{
  "type": "Feature",
  "properties": {
    "iso:country":"IN",
    "ks:ks_name":"Kyara",
    "ks:ks_pop":547,
    "ks:ks_type":"VILLAGE",
    "name:eng_x_preferred":[
        "Kyara"
    ],
    "wof:name":"Kyara",
    "wof:placetype":"locality",
    "wof:population":547
},
  "geometry": {"coordinates":[72.80132500000001,24.571033],"type":"Point"}
}