{
  "type": "Feature",
  "properties": {
    "iso:country":"IN",
    "ks:ks_name":"Talale",
    "ks:ks_pop":856,
    "ks:ks_type":"VILLAGE",
    "name:eng_x_preferred":[
        "Talale"
    ],
    "wof:name":"Talale",
    "wof:placetype":"locality",
    "wof:population":856
},
  "geometry": {"coordinates":[75.295875,13.949957],"type":"Point"}
}