{
  "type": "Feature",
  "properties": {
    "gn:admin1_code":"39.0",
    "gn:admin2_code":"63.0",
    "gn:asciiname":"Kalag",
    "gn:country_code":"IN",
    "gn:dem":1386,
    "gn:feature_class":"P",
    "gn:feature_code":"PPL",
    "gn:name":"Kal\u0101g",
    "gn:population":0,
    "gn:timezone":"Asia/Kolkata",
    "iso:country":"IN",
    "ks:ks_name":"Kalang",
    "ks:ks_pop":112,
    "ks:ks_type":"VILLAGE",
    "name:eng_x_preferred":[
        "Kalang"
    ],
    "name:eng_x_variant":[
        "Kalag"
    ],
    "wof:name":"Kalang",
    "wof:placetype":"locality",
    "wof:population":112
},
  "geometry": {"coordinates":[79.826899,29.877294],"type":"Point"}
}