{
  "type": "Feature",
  "properties": {
    "gn:admin1_code":"35.0",
    "gn:admin2_code":"427",
    "gn:asciiname":"Gohar",
    "gn:country_code":"IN",
    "gn:dem":414,
    "gn:feature_class":"P",
    "gn:feature_code":"PPL",
    "gn:name":"Gohar",
    "gn:population":0,
    "gn:timezone":"Asia/Kolkata",
    "iso:country":"IN",
    "name:ceb_x_preferred":[
        "Gohar"
    ],
    "name:deu_x_preferred":[
        "Gohar"
    ],
    "name:rus_x_preferred":[
        "\u0413\u043e\u0445\u0430\u0440"
    ],
    "name:swe_x_preferred":[
        "Gohar"
    ],
    "wof:name":"Gohar",
    "wof:placetype":"locality"
},
  "geometry": {"coordinates":[78.13018000000002,24.04886],"type":"Point"}
}