{
  "type": "Feature",
  "properties": {
    "gn:admin1_code":"16",
    "gn:admin2_code":"510.0",
    "gn:asciiname":"Koli Buzurg",
    "gn:country_code":"IN",
    "gn:dem":268,
    "gn:feature_class":"P",
    "gn:feature_code":"PPL",
    "gn:name":"Koli Buzurg",
    "gn:population":0,
    "gn:timezone":"Asia/Kolkata",
    "iso:country":"IN",
    "wof:name":"Koli Buzurg",
    "wof:placetype":"neighbourhood"
},
  "geometry": {"coordinates":[78.18810000000001,20.06461],"type":"Point"}
}