{
  "type": "Feature",
  "properties": {
    "iso:country":"IN",
    "ks:ks_name":"Damasahi",
    "ks:ks_pop":93,
    "ks:ks_type":"VILLAGE",
    "ks:ks_uagg_main":0,
    "name:eng_x_preferred":[
        "Damasahi"
    ],
    "wof:name":"Damasahi",
    "wof:placetype":"neighbourhood",
    "wof:population":93
},
  "geometry": {"coordinates":[85.06546,20.465979],"type":"Point"}
}