{
  "type": "Feature",
  "properties": {
    "iso:country":"IN",
    "ks:ks_alt_nam":"M.G. Hatti",
    "ks:ks_name":"M.g. Hatti",
    "ks:ks_pop":62,
    "ks:ks_type":"HABITATION",
    "name:eng_x_preferred":[
        "M.g. Hatti"
    ],
    "wof:name":"M.g. Hatti",
    "wof:placetype":"locality",
    "wof:population":62
},
  "geometry": {"coordinates":[76.52329,13.114717],"type":"Point"}
}