{
  "type": "Feature",
  "properties": {
    "iso:country":"IN",
    "ks:ks_alt_nam":"PuduVellantheru",
    "ks:ks_name":"Puduvellantheru",
    "ks:ks_pop":206,
    "ks:ks_type":"HABITATION",
    "name:eng_x_preferred":[
        "Puduvellantheru"
    ],
    "wof:name":"Puduvellantheru",
    "wof:placetype":"locality",
    "wof:population":206
},
  "geometry": {"coordinates":[78.21551599999999,11.364546],"type":"Point"}
}