{
  "type": "Feature",
  "properties": {
    "gn:admin1_code":"36.0",
    "gn:admin2_code":"148",
    "gn:asciiname":"Ishapur Dikhatmai",
    "gn:country_code":"IN",
    "gn:dem":152,
    "gn:feature_class":"P",
    "gn:feature_code":"PPL",
    "gn:name":"Ish\u0101pur Dikhatmai",
    "gn:population":0,
    "gn:timezone":"Asia/Kolkata",
    "iso:country":"IN",
    "wof:name":"Ishapur Dikhatmai",
    "wof:placetype":"locality"
},
  "geometry": {"coordinates":[79.27263000000001,27.11923],"type":"Point"}
}