{
  "type": "Feature",
  "properties": {
    "gn:admin1_code":"2.0",
    "gn:admin2_code":"549",
    "gn:asciiname":"Inkollu",
    "gn:country_code":"IN",
    "gn:dem":22,
    "gn:feature_class":"P",
    "gn:feature_code":"PPL",
    "gn:name":"Inkollu",
    "gn:population":0,
    "gn:timezone":"Asia/Kolkata",
    "iso:country":"IN",
    "name:tel_x_preferred":[
        "\u0c07\u0c02\u0c15\u0c4a\u0c32\u0c4d\u0c32\u0c41"
    ],
    "name:und_x_variant":[
        "Inkole",
        "Inkollu"
    ],
    "name:urd_x_preferred":[
        "\u0627\u0646\u06a9\u0648\u0644\u0648"
    ],
    "wof:name":"Inkollu",
    "wof:placetype":"locality"
},
  "geometry": {"coordinates":[80.19208,15.82778],"type":"Point"}
}