{
  "type": "Feature",
  "properties": {
    "gn:admin1_code":"2.0",
    "gn:admin2_code":"549",
    "gn:asciiname":"Inkollu",
    "gn:country_code":"IN",
    "gn:dem":22,
    "gn:feature_class":"P",
    "gn:feature_code":"PPL",
    "gn:name":"Inkollu",
    "gn:population":0,
    "gn:timezone":"Asia/Kolkata",
    "iso:country":"IN",
    "name:und_x_variant":[
        "Inkole",
        "Inkollu"
    ],
    "wof:name":"Inkollu",
    "wof:placetype":"locality"
},
  "geometry": {"coordinates":[80.19208,15.82778],"type":"Point"}
}