{
  "type": "Feature",
  "properties": {
    "iso:country":"IN",
    "ks:ks_name":"Sankulamaddi",
    "ks:ks_pop":62,
    "ks:ks_type":"HABITATION",
    "name:eng_x_preferred":[
        "Sankulamaddi"
    ],
    "wof:name":"Sankulamaddi",
    "wof:placetype":"locality",
    "wof:population":62
},
  "geometry": {"coordinates":[82.499319,18.017664],"type":"Point"}
}