{
  "type": "Feature",
  "properties": {
    "iso:country":"IN",
    "ks:ks_name":"Kalbhavi",
    "ks:ks_pop":101,
    "ks:ks_type":"HABITATION",
    "name:eng_x_preferred":[
        "Kalbhavi"
    ],
    "wof:name":"Kalbhavi",
    "wof:placetype":"locality",
    "wof:population":101
},
  "geometry": {"coordinates":[74.331937,14.557781],"type":"Point"}
}