{
  "type": "Feature",
  "properties": {
    "iso:country":"IN",
    "ks:ks_alt_nam":"Beansa bad",
    "ks:ks_name":"Beansa Bad",
    "ks:ks_pop":262,
    "ks:ks_type":"HABITATION",
    "name:eng_x_preferred":[
        "Beansa Bad"
    ],
    "wof:name":"Beansa Bad",
    "wof:placetype":"locality",
    "wof:population":262
},
  "geometry": {"coordinates":[78.35401,27.094459],"type":"Point"}
}