{
  "type": "Feature",
  "properties": {
    "iso:country":"IN",
    "ks:ks_name":"Basalewasti",
    "ks:ks_pop":539,
    "ks:ks_type":"HABITATION",
    "name:eng_x_preferred":[
        "Basalewasti"
    ],
    "wof:name":"Basalewasti",
    "wof:placetype":"locality",
    "wof:population":539
},
  "geometry": {"coordinates":[75.16660899999999,18.36642],"type":"Point"}
}