{
  "type": "Feature",
  "properties": {
    "iso:country":"IN",
    "ks:ks_alt_nam":"Padiputlabayalu Reserved Forest",
    "ks:ks_name":"Padiputlabayalu",
    "ks:ks_pop":2844,
    "ks:ks_type":"VILLAGE",
    "name:eng_x_preferred":[
        "Padiputlabayalu"
    ],
    "name:eng_x_variant":[
        "Padiputlabayalu Reserved Forest"
    ],
    "wof:name":"Padiputlabayalu",
    "wof:placetype":"locality",
    "wof:population":2844
},
  "geometry": {"coordinates":[79.015761,13.502055],"type":"Point"}
}