{
  "type": "Feature",
  "properties": {
    "gn:admin1_code":"2.0",
    "gn:admin2_code":"553.0",
    "gn:asciiname":"Nandirayanahalli",
    "gn:country_code":"IN",
    "gn:dem":682,
    "gn:feature_class":"P",
    "gn:feature_code":"PPL",
    "gn:name":"Nandir\u0101yanahalli",
    "gn:population":0,
    "gn:timezone":"Asia/Kolkata",
    "iso:country":"IN",
    "ks:ks_name":"Nandarajanahalli",
    "ks:ks_pop":1474,
    "ks:ks_type":"HABITATION",
    "ks:ks_uagg_main":0,
    "name:eng_x_preferred":[
        "Nandarajanahalli"
    ],
    "wof:name":"Nandarajanahalli",
    "wof:placetype":"neighbourhood",
    "wof:population":1474
},
  "geometry": {"coordinates":[77.041901,13.783594],"type":"Point"}
}