{
  "type": "Feature",
  "properties": {
    "gn:admin1_code":"12.0",
    "gn:admin2_code":"020",
    "gn:asciiname":"Mardal",
    "gn:country_code":"IN",
    "gn:dem":800,
    "gn:feature_class":"P",
    "gn:feature_code":"PPL",
    "gn:name":"Mard\u0101l",
    "gn:population":0,
    "gn:timezone":"Asia/Kolkata",
    "iso:country":"IN",
    "wof:name":"Mardal",
    "wof:placetype":"locality"
},
  "geometry": {"coordinates":[74.91506,32.98332],"type":"Point"}
}