{
  "type": "Feature",
  "properties": {
    "gn:admin1_code":"36.0",
    "gn:admin2_code":"137.0",
    "gn:asciiname":"Kanrawa",
    "gn:country_code":"IN",
    "gn:dem":195,
    "gn:feature_class":"P",
    "gn:feature_code":"PPL",
    "gn:name":"Kanrawa",
    "gn:population":0,
    "gn:timezone":"Asia/Kolkata",
    "iso:country":"IN",
    "wof:name":"Kanrawa",
    "wof:placetype":"neighbourhood"
},
  "geometry": {"coordinates":[78.30152,28.63966],"type":"Point"}
}