{
  "type": "Feature",
  "properties": {
    "gn:admin1_code":"12.0",
    "gn:admin2_code":"8.0",
    "gn:asciiname":"Shahgund",
    "gn:country_code":"IN",
    "gn:dem":1578,
    "gn:feature_class":"P",
    "gn:feature_code":"PPL",
    "gn:name":"Sh\u0101hgund",
    "gn:population":0,
    "gn:timezone":"Asia/Kolkata",
    "iso:country":"IN",
    "name:eng_x_preferred":[
        "Sh\u0101hgund"
    ],
    "wof:name":"Shahgund",
    "wof:placetype":"locality"
},
  "geometry": {"coordinates":[74.57113000000003,34.28128],"type":"Point"}
}