{
  "type": "Feature",
  "properties": {
    "gn:admin1_code":"24.0",
    "gn:admin2_code":"121",
    "gn:asciiname":"Balapura",
    "gn:country_code":"IN",
    "gn:dem":253,
    "gn:feature_class":"P",
    "gn:feature_code":"PPL",
    "gn:name":"B\u0101l\u0101pura",
    "gn:population":0,
    "gn:timezone":"Asia/Kolkata",
    "iso:country":"IN",
    "ks:ks_alt_nam":"B\u0101l\u0101pura",
    "ks:ks_name":"Balapura",
    "ks:ks_type":"VILLAGE",
    "name:eng_x_preferred":[
        "Balapura"
    ],
    "name:eng_x_variant":[
        "B\u0101l\u0101pura"
    ],
    "wof:name":"Balapura",
    "wof:placetype":"locality"
},
  "geometry": {"coordinates":[75.68785099999999,25.415679],"type":"Point"}
}