{
  "type": "Feature",
  "properties": {
    "iso:country":"IN",
    "ks:ks_alt_nam":"KODASEPATIL VASTI",
    "ks:ks_name":"Kodasepatil Vasti",
    "ks:ks_pop":444,
    "ks:ks_type":"HABITATION",
    "name:eng_x_preferred":[
        "Kodasepatil Vasti"
    ],
    "wof:name":"Kodasepatil Vasti",
    "wof:placetype":"locality",
    "wof:population":444
},
  "geometry": {"coordinates":[76.267267,19.073068],"type":"Point"}
}