{
  "type": "Feature",
  "properties": {
    "gn:admin1_code":"16",
    "gn:admin2_code":"517.0",
    "gn:asciiname":"Nandgaon",
    "gn:country_code":"IN",
    "gn:dem":11,
    "gn:feature_class":"P",
    "gn:feature_code":"PPL",
    "gn:name":"N\u0101ndgaon",
    "gn:population":0,
    "gn:timezone":"Asia/Kolkata",
    "iso:country":"IN",
    "name:ceb_x_preferred":[
        "Nandgaon"
    ],
    "name:pol_x_preferred":[
        "Nandgaon"
    ],
    "name:swe_x_preferred":[
        "Nandgaon"
    ],
    "name:und_x_variant":[
        "Nandgom",
        "N\u0101ndgaon"
    ],
    "wof:name":"Nandgaon",
    "wof:placetype":"locality"
},
  "geometry": {"coordinates":[72.68839,19.76003],"type":"Point"}
}