{
  "type": "Feature",
  "properties": {
    "iso:country":"IN",
    "ks:ks_name":"Bahuda",
    "ks:ks_pop":214,
    "ks:ks_type":"VILLAGE",
    "ks:ks_uagg_main":0,
    "name:eng_x_preferred":[
        "Bahuda"
    ],
    "wof:name":"Bahuda",
    "wof:placetype":"neighbourhood",
    "wof:population":214
},
  "geometry": {"coordinates":[85.987335,20.545251],"type":"Point"}
}