{
  "type": "Feature",
  "properties": {
    "gn:admin1_code":"36.0",
    "gn:admin2_code":"139.0",
    "gn:asciiname":"Gopalpur Khadana",
    "gn:country_code":"IN",
    "gn:dem":224,
    "gn:feature_class":"P",
    "gn:feature_code":"PPL",
    "gn:name":"Gop\u0101lpur Khad\u0101na",
    "gn:population":0,
    "gn:timezone":"Asia/Kolkata",
    "iso:country":"IN",
    "name:und_x_variant":[
        "Gop\u0101lpur Khad\u0101na"
    ],
    "wof:name":"Gopalpur Khadana",
    "wof:placetype":"locality"
},
  "geometry": {"coordinates":[77.31766,29.21373],"type":"Point"}
}