{
  "type": "Feature",
  "properties": {
    "iso:country":"IN",
    "ks:ks_name":"Dedli",
    "ks:ks_pop":1008,
    "ks:ks_type":"VILLAGE",
    "name:eng_x_preferred":[
        "Dedli"
    ],
    "wof:name":"Dedli",
    "wof:placetype":"locality",
    "wof:population":1008
},
  "geometry": {"coordinates":[73.476113,23.729108],"type":"Point"}
}