{
  "type": "Feature",
  "properties": {
    "iso:country":"IN",
    "ks:ks_name":"Radhadeipur",
    "ks:ks_pop":2884,
    "ks:ks_type":"VILLAGE",
    "ks:ks_uagg_main":0,
    "name:eng_x_preferred":[
        "Radhadeipur"
    ],
    "wof:name":"Radhadeipur",
    "wof:placetype":"neighbourhood",
    "wof:population":2884
},
  "geometry": {"coordinates":[84.59571800000001,19.450868],"type":"Point"}
}