{
  "type": "Feature",
  "properties": {
    "iso:country":"IN",
    "ks:ks_name":"No. 1 Kishanpur",
    "ks:ks_pop":100,
    "ks:ks_type":"HABITATION",
    "name:eng_x_preferred":[
        "No. 1 Kishanpur"
    ],
    "wof:name":"No. 1 Kishanpur",
    "wof:placetype":"locality",
    "wof:population":100
},
  "geometry": {"coordinates":[91.362303,25.916522],"type":"Point"}
}