{
  "type": "Feature",
  "properties": {
    "gn:admin1_code":"12.0",
    "gn:admin2_code":"17.0",
    "gn:asciiname":"Jadani Trag",
    "gn:country_code":"IN",
    "gn:dem":2362,
    "gn:feature_class":"P",
    "gn:feature_code":"PPL",
    "gn:name":"Jad\u0101n\u012b Tr\u0101g",
    "gn:population":0,
    "gn:timezone":"Asia/Kolkata",
    "iso:country":"IN",
    "wof:name":"Jadani Trag",
    "wof:placetype":"locality"
},
  "geometry": {"coordinates":[75.20979,33.3013],"type":"Point"}
}