{
  "type": "Feature",
  "properties": {
    "iso:country":"IN",
    "ks:ks_alt_nam":"TELAIPARA",
    "ks:ks_name":"Telaipara",
    "ks:ks_pop":810,
    "ks:ks_type":"HABITATION",
    "name:eng_x_preferred":[
        "Telaipara"
    ],
    "wof:name":"Telaipara",
    "wof:placetype":"locality",
    "wof:population":810
},
  "geometry": {"coordinates":[87.49195,24.578061],"type":"Point"}
}