{
  "type": "Feature",
  "properties": {
    "iso:country":"IN",
    "ks:ks_name":"Harekoppa",
    "ks:ks_pop":38,
    "ks:ks_type":"HABITATION",
    "name:eng_x_preferred":[
        "Harekoppa"
    ],
    "wof:name":"Harekoppa",
    "wof:placetype":"locality",
    "wof:population":38
},
  "geometry": {"coordinates":[75.087915,13.890918],"type":"Point"}
}