{
  "type": "Feature",
  "properties": {
    "iso:country":"IN",
    "ks:ks_name":"Bachuwapur",
    "ks:ks_pop":177,
    "ks:ks_type":"HABITATION",
    "name:eng_x_preferred":[
        "Bachuwapur"
    ],
    "wof:name":"Bachuwapur",
    "wof:placetype":"locality",
    "wof:population":177
},
  "geometry": {"coordinates":[83.017999,26.384389],"type":"Point"}
}