{
  "type": "Feature",
  "properties": {
    "gn:admin1_code":"03",
    "gn:asciiname":"Shedhumi",
    "gn:country_code":"IN",
    "gn:dem":750,
    "gn:feature_class":"P",
    "gn:feature_code":"PPL",
    "gn:name":"Shedhumi",
    "gn:population":0,
    "gn:timezone":"Asia/Kolkata",
    "iso:country":"IN",
    "name:und_x_variant":[
        "Siduma",
        "Shedhumi"
    ],
    "wof:name":"Shedhumi",
    "wof:placetype":"locality"
},
  "geometry": {"coordinates":[93.95169,25.86814],"type":"Point"}
}