{
  "type": "Feature",
  "properties": {
    "iso:country":"IN",
    "ks:ks_alt_nam":"Lala panajinamuvada",
    "ks:ks_name":"Lala Panajinamuvada",
    "ks:ks_pop":219,
    "ks:ks_type":"HABITATION",
    "ks:ks_uagg_main":0,
    "name:eng_x_preferred":[
        "Lala Panajinamuvada"
    ],
    "wof:name":"Lala Panajinamuvada",
    "wof:placetype":"neighbourhood",
    "wof:population":219
},
  "geometry": {"coordinates":[73.21516699999999,22.950556],"type":"Point"}
}