{
  "type": "Feature",
  "properties": {
    "iso:country":"IN",
    "ks:ks_name":"Dharmajayanapalya",
    "ks:ks_pop":24,
    "ks:ks_type":"HABITATION",
    "name:eng_x_preferred":[
        "Dharmajayanapalya"
    ],
    "wof:name":"Dharmajayanapalya",
    "wof:placetype":"locality",
    "wof:population":24
},
  "geometry": {"coordinates":[77.33666700000001,13.296944],"type":"Point"}
}