{
  "type": "Feature",
  "properties": {
    "iso:country":"IN",
    "ks:ks_name":"Shribalaji",
    "ks:ks_pop":5565,
    "ks:ks_type":"HABITATION",
    "name:eng_x_preferred":[
        "Shribalaji"
    ],
    "wof:name":"Shribalaji",
    "wof:placetype":"locality",
    "wof:population":5565
},
  "geometry": {"coordinates":[73.76411299999999,27.504186],"type":"Point"}
}