{
  "type": "Feature",
  "properties": {
    "iso:country":"IN",
    "ks:ks_name":"Tir Mau Ahatmali",
    "ks:ks_pop":0,
    "ks:ks_type":"VILLAGE",
    "name:eng_x_preferred":[
        "Tir Mau Ahatmali"
    ],
    "wof:name":"Tir Mau Ahatmali",
    "wof:placetype":"locality",
    "wof:population":0
},
  "geometry": {"coordinates":[81.23509300000001,25.357221],"type":"Point"}
}