{
  "type": "Feature",
  "properties": {
    "iso:country":"IN",
    "ks:ks_name":"Karaitari",
    "ks:ks_pop":1784,
    "ks:ks_type":"VILLAGE",
    "ks:ks_uagg_main":0,
    "name:eng_x_preferred":[
        "Karaitari"
    ],
    "wof:name":"Karaitari",
    "wof:placetype":"neighbourhood",
    "wof:population":1784
},
  "geometry": {"coordinates":[90.166366,26.353903],"type":"Point"}
}