{
  "type": "Feature",
  "properties": {
    "gn:admin1_code":"36",
    "gn:admin2_code":"137.0",
    "gn:asciiname":"Para Khalsa",
    "gn:country_code":"IN",
    "gn:dem":223,
    "gn:feature_class":"P",
    "gn:feature_code":"PPL",
    "gn:name":"P\u0101ra Kh\u0101lsa",
    "gn:population":0,
    "gn:timezone":"Asia/Kolkata",
    "iso:country":"IN",
    "wof:name":"Para Khalsa",
    "wof:placetype":"locality"
},
  "geometry": {"coordinates":[78.3133,29.00883],"type":"Point"}
}