{
  "type": "Feature",
  "properties": {
    "gn:admin1_code":"36.0",
    "gn:admin2_code":"150.0",
    "gn:asciiname":"Bhagautipur",
    "gn:country_code":"IN",
    "gn:dem":170,
    "gn:feature_class":"P",
    "gn:feature_code":"PPL",
    "gn:name":"Bhagautipur",
    "gn:population":0,
    "gn:timezone":"Asia/Kolkata",
    "iso:country":"IN",
    "ks:ks_name":"Bhagautipur",
    "ks:ks_type":"VILLAGE",
    "name:eng_x_preferred":[
        "Bhagautipur"
    ],
    "wof:name":"Bhagautipur",
    "wof:placetype":"locality"
},
  "geometry": {"coordinates":[79.253174,28.472541],"type":"Point"}
}