{
  "type": "Feature",
  "properties": {
    "iso:country":"IN",
    "ks:ks_name":"Mahraura",
    "ks:ks_type":"VILLAGE",
    "name:eng_x_preferred":[
        "Mahraura"
    ],
    "wof:name":"Mahraura",
    "wof:placetype":"locality"
},
  "geometry": {"coordinates":[83.106899,25.90493],"type":"Point"}
}