{
  "type": "Feature",
  "properties": {
    "iso:country":"IN",
    "ks:ks_alt_nam":"Neetora mukku",
    "ks:ks_name":"Neetora Mukku",
    "ks:ks_pop":530,
    "ks:ks_type":"HABITATION",
    "name:eng_x_preferred":[
        "Neetora Mukku"
    ],
    "wof:name":"Neetora Mukku",
    "wof:placetype":"locality",
    "wof:population":530
},
  "geometry": {"coordinates":[75.864493,11.409824],"type":"Point"}
}