{
  "type": "Feature",
  "properties": {
    "gn:admin1_code":"11",
    "gn:admin2_code":"23.0",
    "gn:asciiname":"Thera Jhikla",
    "gn:country_code":"IN",
    "gn:dem":2071,
    "gn:feature_class":"P",
    "gn:feature_code":"PPL",
    "gn:name":"Thera Jhikla",
    "gn:population":0,
    "gn:timezone":"Asia/Kolkata",
    "iso:country":"IN",
    "wof:name":"Thera Jhikla",
    "wof:placetype":"locality"
},
  "geometry": {"coordinates":[76.03097,32.49883],"type":"Point"}
}