{
  "type": "Feature",
  "properties": {
    "iso:country":"IN",
    "ks:ks_name":"U Bilangsil",
    "ks:ks_pop":305,
    "ks:ks_type":"HABITATION",
    "name:eng_x_preferred":[
        "U Bilangsil"
    ],
    "wof:name":"U Bilangsil",
    "wof:placetype":"locality",
    "wof:population":305
},
  "geometry": {"coordinates":[83.007869,19.003259],"type":"Point"}
}