{
  "type": "Feature",
  "properties": {
    "iso:country":"IN",
    "ks:ks_alt_nam":"PASIA RAHIKA",
    "ks:ks_name":"Pasia Rahika",
    "ks:ks_pop":127,
    "ks:ks_type":"HABITATION",
    "name:eng_x_preferred":[
        "Pasia Rahika"
    ],
    "wof:name":"Pasia Rahika",
    "wof:placetype":"locality",
    "wof:population":127
},
  "geometry": {"coordinates":[87.3322,25.8333],"type":"Point"}
}