{
  "type": "Feature",
  "properties": {
    "gn:admin1_code":"24.0",
    "gn:admin2_code":"120",
    "gn:asciiname":"Amli",
    "gn:country_code":"IN",
    "gn:dem":246,
    "gn:feature_class":"P",
    "gn:feature_code":"PPL",
    "gn:name":"\u0100ml\u012b",
    "gn:population":0,
    "gn:timezone":"Asia/Kolkata",
    "iso:country":"IN",
    "name:ceb_x_preferred":[
        "Amli"
    ],
    "name:nld_x_preferred":[
        "Amli"
    ],
    "wof:name":"Amli",
    "wof:placetype":"locality"
},
  "geometry": {"coordinates":[76.29586,25.81838],"type":"Point"}
}