{
  "type": "Feature",
  "properties": {
    "iso:country":"IN",
    "ks:ks_name":"Ram Datt Purwa",
    "ks:ks_pop":1028,
    "ks:ks_type":"HABITATION",
    "name:eng_x_preferred":[
        "Ram Datt Purwa"
    ],
    "wof:name":"Ram Datt Purwa",
    "wof:placetype":"locality",
    "wof:population":1028
},
  "geometry": {"coordinates":[82.751282,26.591168],"type":"Point"}
}