{
  "type": "Feature",
  "properties": {
    "gn:admin1_code":"21.0",
    "gn:admin2_code":"398.0",
    "gn:asciiname":"Tondapada",
    "gn:country_code":"IN",
    "gn:dem":853,
    "gn:feature_class":"P",
    "gn:feature_code":"PPL",
    "gn:name":"Tondap\u0101da",
    "gn:population":0,
    "gn:timezone":"Asia/Kolkata",
    "iso:country":"IN",
    "wof:name":"Tondapada",
    "wof:placetype":"locality"
},
  "geometry": {"coordinates":[82.47598000000001,18.61568],"type":"Point"}
}