{
  "type": "Feature",
  "properties": {
    "iso:country":"IN",
    "ks:ks_name":"Athimoor",
    "ks:ks_pop":927,
    "ks:ks_type":"VILLAGE",
    "ks:ks_uagg_main":0,
    "name:eng_x_preferred":[
        "Athimoor"
    ],
    "wof:name":"Athimoor",
    "wof:placetype":"neighbourhood",
    "wof:population":927
},
  "geometry": {"coordinates":[79.08078399999999,12.534631],"type":"Point"}
}