{
  "type": "Feature",
  "properties": {
    "gn:admin1_code":"35",
    "gn:admin2_code":"436.0",
    "gn:asciiname":"Gailana",
    "gn:country_code":"IN",
    "gn:dem":406,
    "gn:feature_class":"P",
    "gn:feature_code":"PPL",
    "gn:name":"Gail\u0101na",
    "gn:population":0,
    "gn:timezone":"Asia/Kolkata",
    "iso:country":"IN",
    "wof:name":"Gailana",
    "wof:placetype":"neighbourhood"
},
  "geometry": {"coordinates":[76.16106000000001,23.96907],"type":"Point"}
}