{
  "type": "Feature",
  "properties": {
    "gn:admin1_code":"36",
    "gn:admin2_code":"188.0",
    "gn:asciiname":"Kasht Shiubans Dube",
    "gn:country_code":"IN",
    "gn:dem":79,
    "gn:feature_class":"P",
    "gn:feature_code":"PPL",
    "gn:name":"K\u0101sht Shiubans D\u016bbe",
    "gn:population":0,
    "gn:timezone":"Asia/Kolkata",
    "iso:country":"IN",
    "wof:name":"Kasht Shiubans Dube",
    "wof:placetype":"locality"
},
  "geometry": {"coordinates":[83.29761999999999,26.48642000000001],"type":"Point"}
}