{
  "type": "Feature",
  "properties": {
    "iso:country":"IN",
    "ks:ks_name":"Raviwar Peth",
    "ks:ks_pop":100,
    "ks:ks_type":"HABITATION",
    "name:eng_x_preferred":[
        "Raviwar Peth"
    ],
    "wof:name":"Raviwar Peth",
    "wof:placetype":"locality",
    "wof:population":100
},
  "geometry": {"coordinates":[75.08606,19.179],"type":"Point"}
}