{
  "type": "Feature",
  "properties": {
    "gn:admin1_code":"25.0",
    "gn:admin2_code":"632.0",
    "gn:asciiname":"Appanayakkanpalsiyam",
    "gn:country_code":"IN",
    "gn:dem":463,
    "gn:feature_class":"P",
    "gn:feature_code":"PPL",
    "gn:name":"Appan\u0101yakkanp\u0101lsiyam",
    "gn:population":0,
    "gn:timezone":"Asia/Kolkata",
    "iso:country":"IN",
    "wof:name":"Appanayakkanpalsiyam",
    "wof:placetype":"locality"
},
  "geometry": {"coordinates":[76.92751,11.07947],"type":"Point"}
}