{
  "type": "Feature",
  "properties": {
    "iso:country":"IN",
    "ks:ks_name":"Patharchapra",
    "ks:ks_pop":448,
    "ks:ks_type":"VILLAGE",
    "name:eng_x_preferred":[
        "Patharchapra"
    ],
    "wof:name":"Patharchapra",
    "wof:placetype":"locality",
    "wof:population":448
},
  "geometry": {"coordinates":[86.835075,23.972983],"type":"Point"}
}