{
  "type": "Feature",
  "properties": {
    "gn:admin1_code":"11.0",
    "gn:admin2_code":"26.0",
    "gn:asciiname":"Didi",
    "gn:country_code":"IN",
    "gn:dem":2323,
    "gn:feature_class":"P",
    "gn:feature_code":"PPL",
    "gn:name":"Didi",
    "gn:population":0,
    "gn:timezone":"Asia/Kolkata",
    "iso:country":"IN",
    "name:cat_x_preferred":[
        "Didi"
    ],
    "name:ceb_x_preferred":[
        "Didi"
    ],
    "name:ces_x_preferred":[
        "Didi"
    ],
    "name:deu_x_preferred":[
        "Didi"
    ],
    "name:fra_x_preferred":[
        "Didi"
    ],
    "name:gor_x_preferred":[
        "Didi"
    ],
    "name:heb_x_preferred":[
        "\u05d3\u05d9\u05d3\u05d9"
    ],
    "name:nld_x_preferred":[
        "Didi"
    ],
    "name:por_x_preferred":[
        "Didi"
    ],
    "name:ron_x_preferred":[
        "Didi"
    ],
    "name:rus_x_preferred":[
        "\u0414\u0438\u0434\u0438"
    ],
    "name:swe_x_preferred":[
        "Didi"
    ],
    "wof:name":"Didi",
    "wof:placetype":"locality"
},
  "geometry": {"coordinates":[77.37380999999998,31.49715],"type":"Point"}
}