{
  "type": "Feature",
  "properties": {
    "iso:country":"IN",
    "ks:ks_alt_nam":"Mithya thada",
    "ks:ks_name":"Mithya Thada",
    "ks:ks_pop":96,
    "ks:ks_type":"HABITATION",
    "name:eng_x_preferred":[
        "Mithya Thada"
    ],
    "wof:name":"Mithya Thada",
    "wof:placetype":"locality",
    "wof:population":96
},
  "geometry": {"coordinates":[79.773386,17.753469],"type":"Point"}
}