{
  "type": "Feature",
  "properties": {
    "iso:country":"IN",
    "ks:ks_name":"Rausar",
    "ks:ks_pop":1289,
    "ks:ks_type":"VILLAGE",
    "ks:ks_uagg_main":0,
    "name:eng_x_preferred":[
        "Rausar"
    ],
    "wof:name":"Rausar",
    "wof:placetype":"locality",
    "wof:population":1289
},
  "geometry": {"coordinates":[79.91249999999999,27.828376],"type":"Point"}
}