{
  "type": "Feature",
  "properties": {
    "iso:country":"IN",
    "ks:ks_name":"Baregaon",
    "ks:ks_pop":1695,
    "ks:ks_type":"VILLAGE",
    "ks:ks_uagg_main":0,
    "name:eng_x_preferred":[
        "Baregaon"
    ],
    "wof:name":"Baregaon",
    "wof:placetype":"neighbourhood",
    "wof:population":1695
},
  "geometry": {"coordinates":[90.879182,26.483291],"type":"Point"}
}