{
  "type": "Feature",
  "properties": {
    "iso:country":"IN",
    "ks:ks_name":"Rautara",
    "ks:ks_pop":648,
    "ks:ks_type":"VILLAGE",
    "name:eng_x_preferred":[
        "Rautara"
    ],
    "wof:name":"Rautara",
    "wof:placetype":"locality",
    "wof:population":648
},
  "geometry": {"coordinates":[86.73503700000001,24.374772],"type":"Point"}
}