{
  "type": "Feature",
  "properties": {
    "iso:country":"IN",
    "ks:ks_name":"Pamaran Nagla",
    "ks:ks_pop":119,
    "ks:ks_type":"HABITATION",
    "name:eng_x_preferred":[
        "Pamaran Nagla"
    ],
    "wof:name":"Pamaran Nagla",
    "wof:placetype":"locality",
    "wof:population":119
},
  "geometry": {"coordinates":[79.518607,27.083288],"type":"Point"}
}