{
  "type": "Feature",
  "properties": {
    "gn:admin1_code":"2.0",
    "gn:admin2_code":"554.0",
    "gn:asciiname":"Totakurapalle",
    "gn:country_code":"IN",
    "gn:dem":735,
    "gn:feature_class":"P",
    "gn:feature_code":"PPL",
    "gn:name":"Totakurapalle",
    "gn:population":0,
    "gn:timezone":"Asia/Kolkata",
    "iso:country":"IN",
    "wof:name":"Totakurapalle",
    "wof:placetype":"locality"
},
  "geometry": {"coordinates":[78.71168,13.41357],"type":"Point"}
}