{
  "type": "Feature",
  "properties": {
    "iso:country":"IN",
    "ks:ks_name":"Muthurayanahatti",
    "ks:ks_pop":164,
    "ks:ks_type":"HABITATION",
    "name:eng_x_preferred":[
        "Muthurayanahatti"
    ],
    "wof:name":"Muthurayanahatti",
    "wof:placetype":"locality",
    "wof:population":164
},
  "geometry": {"coordinates":[77.360899,13.968128],"type":"Point"}
}