{
  "type": "Feature",
  "properties": {
    "iso:country":"IN",
    "ks:ks_name":"Dwarakanagar",
    "ks:ks_pop":12,
    "ks:ks_type":"HABITATION",
    "name:eng_x_preferred":[
        "Dwarakanagar"
    ],
    "wof:name":"Dwarakanagar",
    "wof:placetype":"locality",
    "wof:population":12
},
  "geometry": {"coordinates":[78.608774,13.537497],"type":"Point"}
}