{
  "type": "Feature",
  "properties": {
    "iso:country":"IN",
    "ks:ks_name":"Chintalagunta",
    "ks:ks_pop":473,
    "ks:ks_type":"HABITATION",
    "ks:ks_uagg_main":0,
    "name:eng_x_preferred":[
        "Chintalagunta"
    ],
    "wof:name":"Chintalagunta",
    "wof:placetype":"neighbourhood",
    "wof:population":473
},
  "geometry": {"coordinates":[81.097129,16.361767],"type":"Point"}
}