{
  "type": "Feature",
  "properties": {
    "gn:admin1_code":"23.0",
    "gn:admin2_code":"36.0",
    "gn:asciiname":"Badshahpur",
    "gn:country_code":"IN",
    "gn:dem":222,
    "gn:feature_class":"P",
    "gn:feature_code":"PPL",
    "gn:name":"B\u0101dsh\u0101hpur",
    "gn:population":0,
    "gn:timezone":"Asia/Kolkata",
    "iso:country":"IN",
    "name:ceb_x_preferred":[
        "B\u0101dsh\u0101hpur"
    ],
    "name:swe_x_preferred":[
        "B\u0101dsh\u0101hpur"
    ],
    "wof:name":"Badshahpur",
    "wof:placetype":"locality"
},
  "geometry": {"coordinates":[75.395,31.44451],"type":"Point"}
}