{
  "type": "Feature",
  "properties": {
    "gn:admin1_code":"35",
    "gn:admin2_code":"419.0",
    "gn:asciiname":"Basai Harchand",
    "gn:country_code":"IN",
    "gn:dem":174,
    "gn:feature_class":"P",
    "gn:feature_code":"PPL",
    "gn:name":"Basai Harchand",
    "gn:population":0,
    "gn:timezone":"Asia/Kolkata",
    "iso:country":"IN",
    "wof:name":"Basai Harchand",
    "wof:placetype":"locality"
},
  "geometry": {"coordinates":[78.02715999999999,26.58324],"type":"Point"}
}