{
  "type": "Feature",
  "properties": {
    "gn:country":"IN",
    "gn:fcode":"PPL",
    "gn:population":6151,
    "iso:country":"IN",
    "name:bpy_x_preferred":[
        "\u0995\u09cb\u09b0\u09be\u09a1\u09be\u099a\u09c7\u09b0\u09bf"
    ],
    "name:ceb_x_preferred":[
        "Korad\u0101chcheri"
    ],
    "name:eng_x_preferred":[
        "Koradacheri"
    ],
    "name:fra_x_preferred":[
        "Koradacheri"
    ],
    "name:ita_x_preferred":[
        "Koradacheri"
    ],
    "name:msa_x_preferred":[
        "Koradacheri"
    ],
    "name:nan_x_preferred":[
        "Koradacheri"
    ],
    "name:new_x_preferred":[
        "\u0915\u094b\u0930\u093e\u0926\u093e\u091a\u0947\u0930\u0940"
    ],
    "name:nld_x_preferred":[
        "Koradacheri"
    ],
    "name:por_x_preferred":[
        "Koradacheri"
    ],
    "name:swe_x_preferred":[
        "Korad\u0101chcheri"
    ],
    "name:tam_x_preferred":[
        "\u0b95\u0bca\u0bb0\u0b9f\u0bbe\u0b9a\u0bcd\u0b9a\u0bc7\u0bb0\u0bbf"
    ],
    "name:vie_x_preferred":[
        "Koradacheri"
    ],
    "name:zho_x_preferred":[
        "\u79d1\u62c9\u8fbe\u5207\u91cc"
    ],
    "qs:name":"Koradacheri",
    "qs:name_adm0":"India",
    "qs:name_adm1":"Tamil Nadu",
    "qs:photos_9k":1,
    "qs:photos_9r":1,
    "qs:photos_all":1,
    "qs:photos_sr":0,
    "qs:placetype":"Town",
    "qs:pop_sr":"5",
    "wd:wordcount":152,
    "wof:name":"Koradacheri",
    "wof:placetype":"locality",
    "wof:population":6151
},
  "geometry": {"coordinates":[79.49209,10.76987],"type":"Point"}
}