{
  "type": "Feature",
  "properties": {
    "iso:country":"IN",
    "ks:ks_name":"M Kunduli",
    "ks:ks_pop":380,
    "ks:ks_type":"HABITATION",
    "name:eng_x_preferred":[
        "M Kunduli"
    ],
    "wof:name":"M Kunduli",
    "wof:placetype":"locality",
    "wof:population":380
},
  "geometry": {"coordinates":[82.893806,18.604549],"type":"Point"}
}