{
  "type": "Feature",
  "properties": {
    "iso:country":"IN",
    "ks:ks_alt_nam":"Chorbhahuli (F)",
    "ks:ks_name":"Chorbhahuli (f)",
    "ks:ks_pop":234,
    "ks:ks_type":"HABITATION",
    "name:eng_x_preferred":[
        "Chorbhahuli (f)"
    ],
    "wof:name":"Chorbhahuli (f)",
    "wof:placetype":"locality",
    "wof:population":234
},
  "geometry": {"coordinates":[79.366336,21.499086],"type":"Point"}
}