{
  "type": "Feature",
  "properties": {
    "iso:country":"IN",
    "ks:ks_name":"Chhotkisamdari",
    "ks:ks_pop":108,
    "ks:ks_type":"VILLAGE",
    "ks:ks_uagg_main":0,
    "name:eng_x_preferred":[
        "Chhotkisamdari"
    ],
    "wof:name":"Chhotkisamdari",
    "wof:placetype":"neighbourhood",
    "wof:population":108
},
  "geometry": {"coordinates":[84.338841,23.385377],"type":"Point"}
}