{
  "type": "Feature",
  "properties": {
    "iso:country":"IN",
    "ks:ks_name":"Chandranaikthanda",
    "ks:ks_pop":120,
    "ks:ks_type":"HABITATION",
    "name:eng_x_preferred":[
        "Chandranaikthanda"
    ],
    "wof:name":"Chandranaikthanda",
    "wof:placetype":"locality",
    "wof:population":120
},
  "geometry": {"coordinates":[78.902355,16.638523],"type":"Point"}
}