{
  "type": "Feature",
  "properties": {
    "iso:country":"IN",
    "ks:ks_name":"Palsapada",
    "ks:ks_pop":174,
    "ks:ks_type":"HABITATION",
    "name:eng_x_preferred":[
        "Palsapada"
    ],
    "wof:name":"Palsapada",
    "wof:placetype":"locality",
    "wof:population":174
},
  "geometry": {"coordinates":[82.855384,19.497863],"type":"Point"}
}