{
  "type": "Feature",
  "properties": {
    "gn:admin1_code":"35.0",
    "gn:admin2_code":"454.0",
    "gn:asciiname":"Urdalitola",
    "gn:country_code":"IN",
    "gn:dem":608,
    "gn:feature_class":"P",
    "gn:feature_code":"PPL",
    "gn:name":"Urdal\u012btol\u0101",
    "gn:population":0,
    "gn:timezone":"Asia/Kolkata",
    "iso:country":"IN",
    "wof:name":"Urdalitola",
    "wof:placetype":"locality"
},
  "geometry": {"coordinates":[80.66287,22.44862],"type":"Point"}
}