{
  "type": "Feature",
  "properties": {
    "iso:country":"IN",
    "ks:ks_name":"Torraguntapalem",
    "ks:ks_pop":2226,
    "ks:ks_type":"VILLAGE",
    "ks:ks_uagg_main":0,
    "name:eng_x_preferred":[
        "Torraguntapalem"
    ],
    "wof:name":"Torraguntapalem",
    "wof:placetype":"neighbourhood",
    "wof:population":2226
},
  "geometry": {"coordinates":[80.11228199999999,16.898138],"type":"Point"}
}