{
  "type": "Feature",
  "properties": {
    "iso:country":"IN",
    "ks:ks_name":"Punia",
    "ks:ks_pop":968,
    "ks:ks_type":"VILLAGE",
    "ks:ks_uagg_main":0,
    "name:eng_x_preferred":[
        "Punia"
    ],
    "wof:name":"Punia",
    "wof:placetype":"neighbourhood",
    "wof:population":968
},
  "geometry": {"coordinates":[75.99187499999999,31.173304],"type":"Point"}
}