{
  "type": "Feature",
  "properties": {
    "iso:country":"IN",
    "ks:ks_name":"Mohot",
    "ks:ks_pop":274,
    "ks:ks_type":"VILLAGE",
    "name:eng_x_preferred":[
        "Mohot"
    ],
    "wof:name":"Mohot",
    "wof:placetype":"locality",
    "wof:population":274
},
  "geometry": {"coordinates":[73.516244,18.080053],"type":"Point"}
}