{
  "type": "Feature",
  "properties": {
    "gn:admin1_code":"16.0",
    "gn:admin2_code":"497.0",
    "gn:asciiname":"Ranala Khurd",
    "gn:country_code":"IN",
    "gn:dem":204,
    "gn:feature_class":"P",
    "gn:feature_code":"PPL",
    "gn:name":"Ran\u0101la Khurd",
    "gn:population":0,
    "gn:timezone":"Asia/Kolkata",
    "iso:country":"IN",
    "wof:name":"Ranala Khurd",
    "wof:placetype":"locality"
},
  "geometry": {"coordinates":[74.13207,21.33979],"type":"Point"}
}