{
  "type": "Feature",
  "properties": {
    "iso:country":"IN",
    "ks:ks_name":"Ragdha",
    "ks:ks_pop":520,
    "ks:ks_type":"VILLAGE",
    "name:eng_x_preferred":[
        "Ragdha"
    ],
    "wof:name":"Ragdha",
    "wof:placetype":"locality",
    "wof:population":520
},
  "geometry": {"coordinates":[86.796632,21.851294],"type":"Point"}
}