{
  "type": "Feature",
  "properties": {
    "gn:admin1_code":"10.0",
    "gn:admin2_code":"074",
    "gn:asciiname":"Babarpur",
    "gn:country_code":"IN",
    "gn:dem":238,
    "gn:feature_class":"P",
    "gn:feature_code":"PPL",
    "gn:name":"B\u0101barpur",
    "gn:population":0,
    "gn:timezone":"Asia/Kolkata",
    "iso:country":"IN",
    "name:ara_x_preferred":[
        "\u0628\u0627\u0628\u0631\u0628\u0648\u0631"
    ],
    "name:ben_bn_x_preferred":[
        "\u09ac\u09be\u09ac\u09b0\u09aa\u09c1\u09b0"
    ],
    "name:ben_in_x_preferred":[
        "\u09ac\u09be\u09ac\u09b0\u09aa\u09c1\u09b0"
    ],
    "name:guj_x_preferred":[
        "\u0aac\u0abe\u0aac\u0ab0\u0aaa\u0ac1\u0ab0"
    ],
    "name:hin_x_preferred":[
        "\u092c\u093e\u092c\u0930\u092a\u0941\u0930"
    ],
    "name:kan_x_preferred":[
        "\u0cac\u0cbe\u0cac\u0cb0\u0ccd"
    ],
    "name:mal_x_preferred":[
        "\u0d2c\u0d3e\u0d2c\u0d7c\u0d2a\u0d42\u0d7c"
    ],
    "name:mar_x_preferred":[
        "\u092c\u093e\u092c\u0930\u092a\u0942\u0930"
    ],
    "name:pan_x_preferred":[
        "\u0a2c\u0a3e\u0a2c\u0a30\u0a2a\u0a41\u0a30"
    ],
    "name:tam_x_preferred":[
        "\u0baa\u0bbe\u0baa\u0bb0\u0bcd\u0baa\u0bc2\u0bb0\u0bcd"
    ],
    "name:tel_x_preferred":[
        "\u0c2c\u0c3e\u0c2c\u0c30\u0c4d"
    ],
    "name:urd_x_preferred":[
        "\u0628\u0627\u0628\u0631\u067e\u0648\u0631"
    ],
    "name:urd_x_variant":[
        "\u0628\u0627\u0628\u0631 \u067e\u0648\u0631"
    ],
    "wof:name":"Babarpur",
    "wof:placetype":"locality"
},
  "geometry": {"coordinates":[76.95701,29.46303],"type":"Point"}
}