{
  "type": "Feature",
  "properties": {
    "iso:country":"IN",
    "ks:ks_name":"Kargopahar",
    "ks:ks_pop":59,
    "ks:ks_type":"VILLAGE",
    "name:eng_x_preferred":[
        "Kargopahar"
    ],
    "wof:name":"Kargopahar",
    "wof:placetype":"locality",
    "wof:population":59
},
  "geometry": {"coordinates":[87.67711300000001,24.870062],"type":"Point"}
}