{
  "type": "Feature",
  "properties": {
    "gn:admin1_code":"36",
    "gn:admin2_code":"184.0",
    "gn:asciiname":"Bangawan",
    "gn:country_code":"IN",
    "gn:dem":87,
    "gn:feature_class":"P",
    "gn:feature_code":"PPL",
    "gn:name":"Bangaw\u0101n",
    "gn:population":0,
    "gn:timezone":"Asia/Kolkata",
    "iso:country":"IN",
    "name:ben_x_preferred":[
        "\u09ac\u09be\u0999\u09cd\u0997\u09be\u0993\u09af\u09bc\u09be\u09a8"
    ],
    "name:bpy_x_preferred":[
        "\u09ac\u09be\u0999\u09cd\u0997\u09be\u09f1\u09be\u09a8"
    ],
    "name:ind_x_preferred":[
        "Bangawan"
    ],
    "name:ita_x_preferred":[
        "Bangawan"
    ],
    "name:msa_x_preferred":[
        "Bangawan"
    ],
    "name:new_x_preferred":[
        "\u092c\u0928\u0917\u093e\u0935\u0928\u094d"
    ],
    "name:nld_x_preferred":[
        "Bangawan"
    ],
    "name:por_x_preferred":[
        "Bangawan"
    ],
    "name:vie_x_preferred":[
        "Bangawan"
    ],
    "name:zho_x_preferred":[
        "\u90a6\u683c\u963f\u4e07"
    ],
    "wof:name":"Bangawan",
    "wof:placetype":"neighbourhood"
},
  "geometry": {"coordinates":[83.11642999999999,27.22481],"type":"Point"}
}