{
  "type": "Feature",
  "properties": {
    "iso:country":"IN",
    "ks:ks_alt_nam":"Man\u012bl",
    "ks:ks_name":"Manil",
    "ks:ks_pop":664,
    "ks:ks_type":"VILLAGE",
    "name:eng_x_preferred":[
        "Manil"
    ],
    "name:eng_x_variant":[
        "Man\u012bl"
    ],
    "wof:name":"Manil",
    "wof:placetype":"locality",
    "wof:population":664
},
  "geometry": {"coordinates":[79.495627,30.127079],"type":"Point"}
}