{
  "type": "Feature",
  "properties": {
    "iso:country":"IN",
    "ks:ks_name":"Dolamunda",
    "ks:ks_pop":205,
    "ks:ks_type":"HABITATION",
    "name:eng_x_preferred":[
        "Dolamunda"
    ],
    "wof:name":"Dolamunda",
    "wof:placetype":"locality",
    "wof:population":205
},
  "geometry": {"coordinates":[82.259522,18.810201],"type":"Point"}
}