{
  "type": "Feature",
  "properties": {
    "gn:admin1_code":"36",
    "gn:admin2_code":"188.0",
    "gn:asciiname":"Balua",
    "gn:country_code":"IN",
    "gn:dem":83,
    "gn:feature_class":"P",
    "gn:feature_code":"PPL",
    "gn:name":"Balua",
    "gn:population":0,
    "gn:timezone":"Asia/Kolkata",
    "iso:country":"IN",
    "wof:name":"Balua",
    "wof:placetype":"neighbourhood"
},
  "geometry": {"coordinates":[83.20962,26.53006],"type":"Point"}
}