{
  "type": "Feature",
  "properties": {
    "iso:country":"IN",
    "ks:ks_name":"Wanivade",
    "ks:ks_pop":858,
    "ks:ks_type":"VILLAGE",
    "name:eng_x_preferred":[
        "Wanivade"
    ],
    "wof:name":"Wanivade",
    "wof:placetype":"locality",
    "wof:population":858
},
  "geometry": {"coordinates":[73.48576199999999,16.415437],"type":"Point"}
}