{
  "type": "Feature",
  "properties": {
    "iso:country":"IN",
    "ks:ks_alt_nam":"Bhomani Kadwasaron ki Dhani Karwasaro Ki Dhani",
    "ks:ks_name":"Bhomani Kadwasaron Ki Dhani Karwasaro Ki Dhani",
    "ks:ks_pop":107,
    "ks:ks_type":"HABITATION",
    "name:eng_x_preferred":[
        "Bhomani Kadwasaron Ki Dhani Karwasaro Ki Dhani"
    ],
    "wof:name":"Bhomani Kadwasaron Ki Dhani Karwasaro Ki Dhani",
    "wof:placetype":"locality",
    "wof:population":107
},
  "geometry": {"coordinates":[71.665294,25.423742],"type":"Point"}
}