{
  "type": "Feature",
  "properties": {
    "iso:country":"IN",
    "ks:ks_name":"Dasari",
    "ks:ks_pop":258,
    "ks:ks_type":"HABITATION",
    "name:eng_x_preferred":[
        "Dasari"
    ],
    "wof:name":"Dasari",
    "wof:placetype":"locality",
    "wof:population":258
},
  "geometry": {"coordinates":[88.833564,25.322707],"type":"Point"}
}