{
  "type": "Feature",
  "properties": {
    "iso:country":"IN",
    "ks:ks_name":"Doodha Ki Guwari",
    "ks:ks_pop":111,
    "ks:ks_type":"VILLAGE",
    "name:eng_x_preferred":[
        "Doodha Ki Guwari"
    ],
    "wof:name":"Doodha Ki Guwari",
    "wof:placetype":"locality",
    "wof:population":111
},
  "geometry": {"coordinates":[76.73849300000001,26.179186],"type":"Point"}
}