{
  "type": "Feature",
  "properties": {
    "iso:country":"IN",
    "ks:ks_name":"Pailapathar",
    "ks:ks_pop":63,
    "ks:ks_type":"HABITATION",
    "name:eng_x_preferred":[
        "Pailapathar"
    ],
    "wof:name":"Pailapathar",
    "wof:placetype":"locality",
    "wof:population":63
},
  "geometry": {"coordinates":[84.353685,23.618617],"type":"Point"}
}