{
  "type": "Feature",
  "properties": {
    "iso:country":"IN",
    "ks:ks_name":"Bangaon",
    "ks:ks_pop":1185,
    "ks:ks_type":"VILLAGE",
    "name:eng_x_preferred":[
        "Bangaon"
    ],
    "wof:name":"Bangaon",
    "wof:placetype":"locality",
    "wof:population":1185
},
  "geometry": {"coordinates":[83.84439399999999,22.532782],"type":"Point"}
}