{
  "type": "Feature",
  "properties": {
    "iso:country":"IN",
    "ks:ks_name":"Kepiti",
    "ks:ks_pop":142,
    "ks:ks_type":"VILLAGE",
    "name:eng_x_preferred":[
        "Kepiti"
    ],
    "wof:name":"Kepiti",
    "wof:placetype":"locality",
    "wof:population":142
},
  "geometry": {"coordinates":[83.657132,19.363199],"type":"Point"}
}