{
  "type": "Feature",
  "properties": {
    "gn:admin1_code":"36",
    "gn:admin2_code":"194.0",
    "gn:asciiname":"Koeripur",
    "gn:country_code":"IN",
    "gn:dem":92,
    "gn:feature_class":"P",
    "gn:feature_code":"PPL",
    "gn:name":"Koeripur",
    "gn:population":0,
    "gn:timezone":"Asia/Kolkata",
    "iso:country":"IN",
    "name:bpy_x_preferred":[
        "\u0995\u09cb\u09af\u09bc\u09c7\u09b0\u09bf\u09aa\u09c1\u09b0"
    ],
    "name:ita_x_preferred":[
        "Koeripur"
    ],
    "name:msa_x_preferred":[
        "Koeripur"
    ],
    "name:new_x_preferred":[
        "\u0915\u094b\u090f\u0930\u0940\u092a\u0941\u0930"
    ],
    "name:nld_x_preferred":[
        "Koeripur"
    ],
    "name:pol_x_preferred":[
        "Koeripur"
    ],
    "name:por_x_preferred":[
        "Koeripur"
    ],
    "name:urd_x_preferred":[
        "\u06a9\u0648\u0626\u06cc\u0631\u06cc \u067e\u0648\u0631"
    ],
    "name:vie_x_preferred":[
        "Koeripur"
    ],
    "name:zho_x_preferred":[
        "\u79d1\u57c3\u91cc\u666e\u5c14"
    ],
    "wof:name":"Koeripur",
    "wof:placetype":"locality"
},
  "geometry": {"coordinates":[82.57474000000001,26.06962],"type":"Point"}
}