{
  "type": "Feature",
  "properties": {
    "gn:country":"IN",
    "gn:fcode":"PPL",
    "gn:pop":9489,
    "iso:country":"IN",
    "name:ben_x_preferred":[
        "\u0997\u09be\u09b0\u09a5\u09be"
    ],
    "name:bpy_x_preferred":[
        "\u0997\u09be\u09b0\u09cc\u09a5\u09be"
    ],
    "name:bul_x_preferred":[
        "\u0413\u0430\u0440\u0430\u0443\u0442\u0445\u0430"
    ],
    "name:deu_x_preferred":[
        "Garautha"
    ],
    "name:eng_x_preferred":[
        "Garautha"
    ],
    "name:fra_x_preferred":[
        "Garautha"
    ],
    "name:guj_x_preferred":[
        "\u0a97\u0ab0\u0ac1\u0aa5\u0abe"
    ],
    "name:ita_x_preferred":[
        "Garautha"
    ],
    "name:jpn_x_preferred":[
        "\u30ac\u30e9\u30a6\u30b5"
    ],
    "name:kan_x_preferred":[
        "\u0c97\u0cb0\u0ccd\u0ca4\u0cbe"
    ],
    "name:kor_x_preferred":[
        "\uac00\ub77c\uc6b0\ud0c0"
    ],
    "name:mlg_x_preferred":[
        "Garautha"
    ],
    "name:msa_x_preferred":[
        "Garautha"
    ],
    "name:nan_x_preferred":[
        "Garautha"
    ],
    "name:new_x_preferred":[
        "\u0917\u0930\u094c\u0925\u093e"
    ],
    "name:nld_x_preferred":[
        "Garautha"
    ],
    "name:pol_x_preferred":[
        "Garautha"
    ],
    "name:por_x_preferred":[
        "Garautha"
    ],
    "name:rus_x_preferred":[
        "\u0413\u0430\u0440\u0430\u0443\u0442\u0445\u0430"
    ],
    "name:spa_x_preferred":[
        "Garautha"
    ],
    "name:swe_x_preferred":[
        "Garautha"
    ],
    "name:tam_x_preferred":[
        "\u0b95\u0bb0\u0bcc\u0ba4\u0bbe"
    ],
    "name:tel_x_preferred":[
        "\u0c17\u0c30\u0c4c\u0c24\u0c3e"
    ],
    "name:urd_x_preferred":[
        "\u06af\u0631\u0648\u0679\u06be\u0627"
    ],
    "name:vie_x_preferred":[
        "Garautha"
    ],
    "name:zho_x_preferred":[
        "\u52a0\u52b3\u5854"
    ],
    "qs:name":"Garautha",
    "qs:photos_9r":0,
    "qs:photos_sr":0,
    "qs:pop_sr":"5",
    "wd:wordcount":566,
    "wof:name":"Garautha",
    "wof:placetype":"locality",
    "wof:population":9489
},
  "geometry": {"coordinates":[79.29782,25.57145],"type":"Point"}
}