{
  "type": "Feature",
  "properties": {
    "iso:country":"IN",
    "ks:ks_name":"Peddamsettivaripalem",
    "ks:ks_pop":581,
    "ks:ks_type":"HABITATION",
    "name:eng_x_preferred":[
        "Peddamsettivaripalem"
    ],
    "wof:name":"Peddamsettivaripalem",
    "wof:placetype":"locality",
    "wof:population":581
},
  "geometry": {"coordinates":[82.04064700000001,16.739966],"type":"Point"}
}