{
  "type": "Feature",
  "properties": {
    "iso:country":"IN",
    "ks:ks_name":"Pipalyamircha",
    "ks:ks_pop":213,
    "ks:ks_type":"VILLAGE",
    "name:eng_x_preferred":[
        "Pipalyamircha"
    ],
    "wof:name":"Pipalyamircha",
    "wof:placetype":"locality",
    "wof:population":213
},
  "geometry": {"coordinates":[75.07853799999999,24.386297],"type":"Point"}
}