{
  "type": "Feature",
  "properties": {
    "gn:admin1_code":"19.0",
    "gn:admin2_code":"574.0",
    "gn:asciiname":"Mayagondanahalli",
    "gn:country_code":"IN",
    "gn:dem":864,
    "gn:feature_class":"P",
    "gn:feature_code":"PPL",
    "gn:name":"M\u0101yagondanahalli",
    "gn:population":0,
    "gn:timezone":"Asia/Kolkata",
    "iso:country":"IN",
    "wof:name":"Mayagondanahalli",
    "wof:placetype":"locality"
},
  "geometry": {"coordinates":[76.00351999999999,13.24138],"type":"Point"}
}