{
  "type": "Feature",
  "properties": {
    "gn:admin1_code":"36.0",
    "gn:admin2_code":"150.0",
    "gn:asciiname":"Mitapur Jagir",
    "gn:country_code":"IN",
    "gn:dem":198,
    "gn:feature_class":"P",
    "gn:feature_code":"PPL",
    "gn:name":"Mit\u0101pur J\u0101g\u012br",
    "gn:population":0,
    "gn:timezone":"Asia/Kolkata",
    "iso:country":"IN",
    "wof:name":"Mitapur Jagir",
    "wof:placetype":"locality"
},
  "geometry": {"coordinates":[79.54023000000002,28.77184],"type":"Point"}
}