{
  "type": "Feature",
  "properties": {
    "gn:admin1_code":"12.0",
    "gn:admin2_code":"7.0",
    "gn:asciiname":"Deoli",
    "gn:country_code":"IN",
    "gn:dem":535,
    "gn:feature_class":"P",
    "gn:feature_code":"PPL",
    "gn:name":"Deoli",
    "gn:population":0,
    "gn:timezone":"Asia/Kolkata",
    "iso:country":"IN",
    "name:ben_x_preferred":[
        "\u09a6\u09c7\u0993\u09b2\u09bf"
    ],
    "name:bih_x_preferred":[
        "\u0926\u0947\u0935\u0932\u0940"
    ],
    "name:ceb_x_preferred":[
        "Deoli"
    ],
    "name:hin_x_preferred":[
        "\u0926\u0947\u0935\u0932\u0940"
    ],
    "name:mar_x_preferred":[
        "\u0926\u0947\u0935\u0933\u0940"
    ],
    "name:nld_x_preferred":[
        "Deoli"
    ],
    "name:swe_x_preferred":[
        "Deoli"
    ],
    "wof:name":"Deoli",
    "wof:placetype":"locality"
},
  "geometry": {"coordinates":[75.46136,32.54352],"type":"Point"}
}