{
  "type": "Feature",
  "properties": {
    "iso:country":"IN",
    "ks:ks_name":"Naudiha",
    "ks:ks_pop":1288,
    "ks:ks_type":"VILLAGE",
    "name:eng_x_preferred":[
        "Naudiha"
    ],
    "wof:name":"Naudiha",
    "wof:placetype":"locality",
    "wof:population":1288
},
  "geometry": {"coordinates":[85.123752,24.61711],"type":"Point"}
}