{
  "type": "Feature",
  "properties": {
    "iso:country":"IN",
    "ks:ks_alt_nam":"KRISHNDEO TOLA",
    "ks:ks_name":"Krishndeo Tola",
    "ks:ks_pop":891,
    "ks:ks_type":"HABITATION",
    "ks:ks_uagg_main":0,
    "name:eng_x_preferred":[
        "Krishndeo Tola"
    ],
    "wof:name":"Krishndeo Tola",
    "wof:placetype":"neighbourhood",
    "wof:population":891
},
  "geometry": {"coordinates":[87.5159,25.72988],"type":"Point"}
}