{
  "type": "Feature",
  "properties": {
    "gn:admin1_code":"24",
    "gn:admin2_code":"101.0",
    "gn:asciiname":"Purana Sohajrasar",
    "gn:country_code":"IN",
    "gn:dem":202,
    "gn:feature_class":"P",
    "gn:feature_code":"PPL",
    "gn:name":"Pur\u0101na Sohajr\u0101sar",
    "gn:population":0,
    "gn:timezone":"Asia/Kolkata",
    "iso:country":"IN",
    "name:und_x_variant":[
        "Pur\u0101na Sohajr\u0101sar",
        "Saijar\u0101sar"
    ],
    "wof:name":"Purana Sohajrasar",
    "wof:placetype":"neighbourhood"
},
  "geometry": {"coordinates":[73.75973,28.34367],"type":"Point"}
}