{
  "type": "Feature",
  "properties": {
    "iso:country":"IN",
    "ks:ks_name":"Charimoola",
    "ks:ks_pop":380,
    "ks:ks_type":"HABITATION",
    "name:eng_x_preferred":[
        "Charimoola"
    ],
    "wof:name":"Charimoola",
    "wof:placetype":"locality",
    "wof:population":380
},
  "geometry": {"coordinates":[75.897057,11.780667],"type":"Point"}
}