{
  "type": "Feature",
  "properties": {
    "gn:admin1_code":"34.0",
    "gn:admin2_code":"203.0",
    "gn:asciiname":"Dhurbhari",
    "gn:country_code":"IN",
    "gn:dem":81,
    "gn:feature_class":"P",
    "gn:feature_code":"PPL",
    "gn:name":"Dhurbh\u0101ri",
    "gn:population":0,
    "gn:timezone":"Asia/Kolkata",
    "iso:country":"IN",
    "wof:name":"Dhurbhari",
    "wof:placetype":"locality"
},
  "geometry": {"coordinates":[84.51142,26.84621],"type":"Point"}
}