{
  "type": "Feature",
  "properties": {
    "gn:admin1_code":"36",
    "gn:admin2_code":"138.0",
    "gn:asciiname":"Jharina",
    "gn:country_code":"IN",
    "gn:dem":208,
    "gn:feature_class":"P",
    "gn:feature_code":"PPL",
    "gn:name":"Jharina",
    "gn:population":0,
    "gn:timezone":"Asia/Kolkata",
    "iso:country":"IN",
    "wof:name":"Jharina",
    "wof:placetype":"locality"
},
  "geometry": {"coordinates":[78.06263,28.85896],"type":"Point"}
}