{
  "type": "Feature",
  "properties": {
    "gn:admin1_code":"2.0",
    "gn:admin2_code":"551.0",
    "gn:asciiname":"Malluvaripalle",
    "gn:country_code":"IN",
    "gn:dem":196,
    "gn:feature_class":"P",
    "gn:feature_code":"PPL",
    "gn:name":"Malluv\u0101ripalle",
    "gn:population":0,
    "gn:timezone":"Asia/Kolkata",
    "iso:country":"IN",
    "ks:ks_alt_nam":"Malluv\u0101ripalle",
    "ks:ks_name":"Malluvaripalle",
    "ks:ks_type":"VILLAGE",
    "ks:ks_uagg_main":0,
    "name:eng_x_preferred":[
        "Malluvaripalle"
    ],
    "name:eng_x_variant":[
        "Malluv\u0101ripalle"
    ],
    "wof:name":"Malluvaripalle",
    "wof:placetype":"neighbourhood"
},
  "geometry": {"coordinates":[78.94518600000001,15.128159],"type":"Point"}
}