{
  "type": "Feature",
  "properties": {
    "iso:country":"IN",
    "ks:ks_name":"Kamtalu",
    "ks:ks_pop":35,
    "ks:ks_type":"HABITATION",
    "name:eng_x_preferred":[
        "Kamtalu"
    ],
    "wof:name":"Kamtalu",
    "wof:placetype":"locality",
    "wof:population":35
},
  "geometry": {"coordinates":[75.27627099999999,13.402896],"type":"Point"}
}