{
  "type": "Feature",
  "properties": {
    "gn:admin1_code":"36",
    "gn:admin2_code":"200.0",
    "gn:asciiname":"Reti Kalan",
    "gn:country_code":"IN",
    "gn:dem":334,
    "gn:feature_class":"P",
    "gn:feature_code":"PPL",
    "gn:name":"Reti Kal\u0101n",
    "gn:population":0,
    "gn:timezone":"Asia/Kolkata",
    "iso:country":"IN",
    "wof:name":"Reti Kalan",
    "wof:placetype":"locality"
},
  "geometry": {"coordinates":[83.28509,24.68405],"type":"Point"}
}