{
  "type": "Feature",
  "properties": {
    "gn:admin1_code":"36",
    "gn:admin2_code":"200.0",
    "gn:asciiname":"Reti Kalan",
    "gn:country_code":"IN",
    "gn:dem":334,
    "gn:feature_class":"P",
    "gn:feature_code":"PPL",
    "gn:name":"Reti Kal\u0101n",
    "gn:population":0,
    "gn:timezone":"Asia/Kolkata",
    "iso:country":"IN",
    "ks:ks_name":"Reti Kalan",
    "ks:ks_pop":175,
    "ks:ks_type":"VILLAGE",
    "name:eng_x_preferred":[
        "Reti Kalan"
    ],
    "wof:name":"Reti Kalan",
    "wof:placetype":"locality",
    "wof:population":175
},
  "geometry": {"coordinates":[83.291313,24.682709],"type":"Point"}
}