{
  "type": "Feature",
  "properties": {
    "iso:country":"IN",
    "ks:ks_name":"Iaanpur North T",
    "ks:ks_pop":118,
    "ks:ks_type":"HABITATION",
    "ks:ks_uagg_main":0,
    "name:eng_x_preferred":[
        "Iaanpur North T"
    ],
    "wof:name":"Iaanpur North T",
    "wof:placetype":"neighbourhood",
    "wof:population":118
},
  "geometry": {"coordinates":[85.610595,26.384253],"type":"Point"}
}