{
  "type": "Feature",
  "properties": {
    "gn:admin1_code":"2.0",
    "gn:admin2_code":"554.0",
    "gn:asciiname":"Nagari",
    "gn:country_code":"IN",
    "gn:dem":532,
    "gn:feature_class":"P",
    "gn:feature_code":"PPL",
    "gn:name":"Nagari",
    "gn:population":0,
    "gn:timezone":"Asia/Kolkata",
    "iso:country":"IN",
    "name:deu_x_preferred":[
        "Nagari"
    ],
    "name:ind_x_preferred":[
        "Nagari"
    ],
    "name:nld_x_preferred":[
        "Nagari"
    ],
    "name:slk_x_preferred":[
        "N\u00e1gar\u00ed"
    ],
    "wof:name":"Nagari",
    "wof:placetype":"locality"
},
  "geometry": {"coordinates":[79.05085,13.66316],"type":"Point"}
}