{
  "type": "Feature",
  "properties": {
    "iso:country":"IN",
    "ks:ks_name":"Veeryathanda",
    "ks:ks_pop":141,
    "ks:ks_type":"HABITATION",
    "name:eng_x_preferred":[
        "Veeryathanda"
    ],
    "wof:name":"Veeryathanda",
    "wof:placetype":"locality",
    "wof:population":141
},
  "geometry": {"coordinates":[79.94578199999999,18.011181],"type":"Point"}
}