{
  "type": "Feature",
  "properties": {
    "iso:country":"IN",
    "ks:ks_name":"Talyachiwadi",
    "ks:ks_pop":210,
    "ks:ks_type":"HABITATION",
    "name:eng_x_preferred":[
        "Talyachiwadi"
    ],
    "wof:name":"Talyachiwadi",
    "wof:placetype":"locality",
    "wof:population":210
},
  "geometry": {"coordinates":[73.179036,17.508761],"type":"Point"}
}