{
  "type": "Feature",
  "properties": {
    "iso:country":"IN",
    "ks:ks_name":"Razzakpur",
    "ks:ks_pop":158,
    "ks:ks_type":"HABITATION",
    "name:eng_x_preferred":[
        "Razzakpur"
    ],
    "wof:name":"Razzakpur",
    "wof:placetype":"locality",
    "wof:population":158
},
  "geometry": {"coordinates":[77.384112,21.231532],"type":"Point"}
}