{
  "type": "Feature",
  "properties": {
    "gn:admin1_code":"19.0",
    "gn:admin2_code":"581.0",
    "gn:asciiname":"Balagere",
    "gn:country_code":"IN",
    "gn:dem":851,
    "gn:feature_class":"P",
    "gn:feature_code":"PPL",
    "gn:name":"Balagere",
    "gn:population":0,
    "gn:timezone":"Asia/Kolkata",
    "iso:country":"IN",
    "wof:name":"Balagere",
    "wof:placetype":"locality"
},
  "geometry": {"coordinates":[78.09139999999999,13.2994],"type":"Point"}
}