{
  "type": "Feature",
  "properties": {
    "iso:country":"IN",
    "ks:ks_name":"Tulasipadar",
    "ks:ks_pop":21,
    "ks:ks_type":"VILLAGE",
    "name:eng_x_preferred":[
        "Tulasipadar"
    ],
    "wof:name":"Tulasipadar",
    "wof:placetype":"locality",
    "wof:population":21
},
  "geometry": {"coordinates":[83.516862,19.729092],"type":"Point"}
}