{
  "type": "Feature",
  "properties": {
    "iso:country":"IN",
    "ks:ks_name":"Baigni",
    "ks:ks_pop":1712,
    "ks:ks_type":"VILLAGE",
    "ks:ks_uagg_main":0,
    "name:eng_x_preferred":[
        "Baigni"
    ],
    "wof:name":"Baigni",
    "wof:placetype":"neighbourhood",
    "wof:population":1712
},
  "geometry": {"coordinates":[85.685531,26.233349],"type":"Point"}
}