{
  "type": "Feature",
  "properties": {
    "gn:admin1_code":"2",
    "gn:admin2_code":"544.0",
    "gn:asciiname":"Sagara",
    "gn:country_code":"IN",
    "gn:dem":961,
    "gn:feature_class":"P",
    "gn:feature_code":"PPL",
    "gn:name":"S\u0101gara",
    "gn:population":0,
    "gn:timezone":"Asia/Kolkata",
    "iso:country":"IN",
    "name:ceb_x_preferred":[
        "Sagara"
    ],
    "name:deu_x_preferred":[
        "Sagara"
    ],
    "name:nld_x_preferred":[
        "Sagara"
    ],
    "name:por_x_preferred":[
        "Sagara"
    ],
    "name:rus_x_preferred":[
        "\u0421\u0430\u0433\u0430\u0440\u0430"
    ],
    "name:spa_x_preferred":[
        "Sagara"
    ],
    "name:swe_x_preferred":[
        "Sagara"
    ],
    "wof:name":"Sagara",
    "wof:placetype":"locality"
},
  "geometry": {"coordinates":[82.81356,18.37527],"type":"Point"}
}