{
  "type": "Feature",
  "properties": {
    "iso:country":"IN",
    "ks:ks_name":"Tari",
    "ks:ks_pop":168,
    "ks:ks_type":"VILLAGE",
    "name:eng_x_preferred":[
        "Tari"
    ],
    "wof:name":"Tari",
    "wof:placetype":"locality",
    "wof:population":168
},
  "geometry": {"coordinates":[87.270915,24.328065],"type":"Point"}
}