{
  "type": "Feature",
  "properties": {
    "gn:admin1_code":"21",
    "gn:admin2_code":"370.0",
    "gn:asciiname":"Mahanpali",
    "gn:country_code":"IN",
    "gn:dem":212,
    "gn:feature_class":"P",
    "gn:feature_code":"PPL",
    "gn:name":"Mahanp\u0101li",
    "gn:population":0,
    "gn:timezone":"Asia/Kolkata",
    "iso:country":"IN",
    "ks:ks_alt_nam":"Mahanp\u0101li",
    "ks:ks_name":"Mahanpali",
    "ks:ks_type":"VILLAGE",
    "name:eng_x_preferred":[
        "Mahanpali"
    ],
    "name:eng_x_variant":[
        "Mahanp\u0101li"
    ],
    "wof:name":"Mahanpali",
    "wof:placetype":"locality"
},
  "geometry": {"coordinates":[83.057179,21.093422],"type":"Point"}
}