{
  "type": "Feature",
  "properties": {
    "iso:country":"IN",
    "ks:ks_name":"Nala Chhota",
    "ks:ks_pop":648,
    "ks:ks_type":"VILLAGE",
    "name:eng_x_preferred":[
        "Nala Chhota"
    ],
    "wof:name":"Nala Chhota",
    "wof:placetype":"locality",
    "wof:population":648
},
  "geometry": {"coordinates":[73.43275300000001,24.245794],"type":"Point"}
}