{
  "type": "Feature",
  "properties": {
    "gn:admin1_code":"34.0",
    "gn:admin2_code":"219.0",
    "gn:asciiname":"Hakam",
    "gn:country_code":"IN",
    "gn:dem":61,
    "gn:feature_class":"P",
    "gn:feature_code":"PPL",
    "gn:name":"Hak\u0101m",
    "gn:population":0,
    "gn:timezone":"Asia/Kolkata",
    "iso:country":"IN",
    "name:ara_x_preferred":[
        "\u062d\u0643\u0645"
    ],
    "name:ita_x_preferred":[
        "Hakam"
    ],
    "name:jpn_x_preferred":[
        "\u30cf\u30ab\u30e0"
    ],
    "name:rus_x_preferred":[
        "\u0425\u0430\u043a\u0430\u043c"
    ],
    "name:ukr_x_preferred":[
        "\u0410\u043b\u044c-\u0425\u0430\u043a\u0430\u043c"
    ],
    "wof:name":"Hakam",
    "wof:placetype":"locality"
},
  "geometry": {"coordinates":[84.55006,25.94939],"type":"Point"}
}