{
  "type": "Feature",
  "properties": {
    "iso:country":"IN",
    "ks:ks_name":"Pathar Chakri",
    "ks:ks_pop":229,
    "ks:ks_type":"HABITATION",
    "name:eng_x_preferred":[
        "Pathar Chakri"
    ],
    "wof:name":"Pathar Chakri",
    "wof:placetype":"locality",
    "wof:population":229
},
  "geometry": {"coordinates":[86.10847800000001,22.588622],"type":"Point"}
}