{
  "type": "Feature",
  "properties": {
    "gn:country":"IN",
    "gn:fcode":"PPL",
    "gn:population":15311,
    "iso:country":"IN",
    "name:ast_x_preferred":[
        "Kathor"
    ],
    "name:ceb_x_preferred":[
        "K\u0101thor"
    ],
    "name:eng_x_preferred":[
        "Kathor"
    ],
    "name:guj_x_preferred":[
        "\u0a95\u0aa0\u0acb\u0ab0"
    ],
    "name:nld_x_preferred":[
        "Kathor"
    ],
    "name:swe_x_preferred":[
        "K\u0101thor"
    ],
    "qs:name":"Kathor",
    "qs:name_adm0":"India",
    "qs:name_adm1":"Gujarat",
    "qs:photos_9r":0,
    "qs:photos_sr":0,
    "qs:placetype":"Town",
    "qs:pop_sr":"6",
    "wd:wordcount":8,
    "wof:name":"Kathor",
    "wof:placetype":"locality",
    "wof:population":15311
},
  "geometry": {"coordinates":[72.94070000000001,21.28854],"type":"Point"}
}