{
  "type": "Feature",
  "properties": {
    "gn:admin1_code":"35",
    "gn:admin2_code":"442.0",
    "gn:asciiname":"Kolu Kheri",
    "gn:country_code":"IN",
    "gn:dem":416,
    "gn:feature_class":"P",
    "gn:feature_code":"PPL",
    "gn:name":"Kolu Kheri",
    "gn:population":0,
    "gn:timezone":"Asia/Kolkata",
    "iso:country":"IN",
    "ks:ks_name":"Kolu Khedi",
    "ks:ks_pop":470,
    "ks:ks_type":"HABITATION",
    "ks:ks_uagg_main":0,
    "name:eng_x_preferred":[
        "Kolu Khedi"
    ],
    "wof:name":"Kolu Khedi",
    "wof:placetype":"neighbourhood",
    "wof:population":470
},
  "geometry": {"coordinates":[76.614655,23.948327],"type":"Point"}
}