{
  "type": "Feature",
  "properties": {
    "iso:country":"IN",
    "ks:ks_name":"Santra",
    "ks:ks_pop":929,
    "ks:ks_type":"VILLAGE",
    "name:eng_x_preferred":[
        "Santra"
    ],
    "wof:name":"Santra",
    "wof:placetype":"locality",
    "wof:population":929
},
  "geometry": {"coordinates":[88.642329,22.49412],"type":"Point"}
}