{
  "type": "Feature",
  "properties": {
    "iso:country":"IN",
    "ks:ks_name":"Amalya",
    "ks:ks_pop":302,
    "ks:ks_type":"VILLAGE",
    "name:eng_x_preferred":[
        "Amalya"
    ],
    "wof:name":"Amalya",
    "wof:placetype":"locality",
    "wof:population":302
},
  "geometry": {"coordinates":[75.379616,24.391271],"type":"Point"}
}