{
  "type": "Feature",
  "properties": {
    "iso:country":"IN",
    "ks:ks_name":"Vadagarai",
    "ks:ks_pop":826,
    "ks:ks_type":"VILLAGE",
    "ks:ks_uagg_main":0,
    "name:eng_x_preferred":[
        "Vadagarai"
    ],
    "wof:name":"Vadagarai",
    "wof:placetype":"locality",
    "wof:population":826
},
  "geometry": {"coordinates":[80.200018,13.18641],"type":"Point"}
}