{
  "type": "Feature",
  "properties": {
    "iso:country":"IN",
    "ks:ks_alt_nam":"Hatn\u0101da",
    "ks:ks_name":"Hatnada",
    "ks:ks_pop":174,
    "ks:ks_type":"VILLAGE",
    "name:eng_x_preferred":[
        "Hatnada"
    ],
    "name:eng_x_variant":[
        "Hatn\u0101da"
    ],
    "wof:name":"Hatnada",
    "wof:placetype":"locality",
    "wof:population":174
},
  "geometry": {"coordinates":[85.31265999999999,22.841016],"type":"Point"}
}