{
  "type": "Feature",
  "properties": {
    "gn:admin1_code":"36",
    "gn:admin2_code":"181.0",
    "gn:asciiname":"Tilakpur",
    "gn:country_code":"IN",
    "gn:dem":124,
    "gn:feature_class":"P",
    "gn:feature_code":"PPL",
    "gn:name":"Tilakpur",
    "gn:population":0,
    "gn:timezone":"Asia/Kolkata",
    "iso:country":"IN",
    "ks:ks_name":"Tilakpur",
    "ks:ks_pop":1637,
    "ks:ks_type":"VILLAGE",
    "name:ceb_x_preferred":[
        "Tilakpur"
    ],
    "name:eng_x_preferred":[
        "Tilakpur"
    ],
    "name:hin_x_preferred":[
        "\u0924\u093f\u0932\u0915\u092a\u0941\u0930"
    ],
    "name:msa_x_preferred":[
        "Tilakpur"
    ],
    "name:new_x_preferred":[
        "\u0924\u093f\u0932\u0915\u092a\u0941\u0930"
    ],
    "name:pol_x_preferred":[
        "Tilakpur"
    ],
    "wof:name":"Tilakpur",
    "wof:placetype":"locality",
    "wof:population":1637
},
  "geometry": {"coordinates":[81.786835,27.557337],"type":"Point"}
}