{
  "type": "Feature",
  "properties": {
    "gn:admin1_code":"11.0",
    "gn:asciiname":"Chak Bhathian",
    "gn:country_code":"IN",
    "gn:dem":307,
    "gn:feature_class":"P",
    "gn:feature_code":"PPL",
    "gn:name":"Chak Bhathi\u0101n",
    "gn:population":0,
    "gn:timezone":"Asia/Kolkata",
    "iso:country":"IN",
    "ks:ks_name":"Chak Bhattian",
    "ks:ks_pop":408,
    "ks:ks_type":"HABITATION",
    "name:eng_x_preferred":[
        "Chak Bhattian"
    ],
    "name:eng_x_variant":[
        "Chak Bhathian"
    ],
    "wof:name":"Chak Bhattian",
    "wof:placetype":"locality",
    "wof:population":408
},
  "geometry": {"coordinates":[75.65496400000001,32.17834],"type":"Point"}
}