{
  "type": "Feature",
  "properties": {
    "gn:admin1_code":"35",
    "gn:admin2_code":"430.0",
    "gn:asciiname":"Mahiyan",
    "gn:country_code":"IN",
    "gn:dem":319,
    "gn:feature_class":"P",
    "gn:feature_code":"PPL",
    "gn:name":"Mahiy\u0101n",
    "gn:population":0,
    "gn:timezone":"Asia/Kolkata",
    "iso:country":"IN",
    "ks:ks_name":"Mahiya",
    "ks:ks_pop":273,
    "ks:ks_type":"VILLAGE",
    "name:eng_x_preferred":[
        "Mahiya"
    ],
    "name:eng_x_variant":[
        "Mahiyan"
    ],
    "wof:name":"Mahiya",
    "wof:placetype":"locality",
    "wof:population":273
},
  "geometry": {"coordinates":[81.400774,24.475668],"type":"Point"}
}