{
  "type": "Feature",
  "properties": {
    "gn:admin1_code":"36",
    "gn:admin2_code":"178.0",
    "gn:asciiname":"Zafarpur Sakrauli",
    "gn:country_code":"IN",
    "gn:dem":86,
    "gn:feature_class":"P",
    "gn:feature_code":"PPL",
    "gn:name":"Zafarpur Sakrauli",
    "gn:population":0,
    "gn:timezone":"Asia/Kolkata",
    "iso:country":"IN",
    "ks:ks_name":"Jafarpur Sakrooli",
    "ks:ks_pop":980,
    "ks:ks_type":"VILLAGE",
    "ks:ks_uagg_main":0,
    "name:eng_x_preferred":[
        "Jafarpur Sakrooli"
    ],
    "wof:name":"Jafarpur Sakrooli",
    "wof:placetype":"neighbourhood",
    "wof:population":980
},
  "geometry": {"coordinates":[82.855267,26.194153],"type":"Point"}
}