{
  "type": "Feature",
  "properties": {
    "iso:country":"IN",
    "ks:ks_name":"Kabbagara Huvinmane",
    "ks:ks_pop":91,
    "ks:ks_type":"HABITATION",
    "name:eng_x_preferred":[
        "Kabbagara Huvinmane"
    ],
    "wof:name":"Kabbagara Huvinmane",
    "wof:placetype":"locality",
    "wof:population":91
},
  "geometry": {"coordinates":[74.79451299999999,14.388319],"type":"Point"}
}