{
  "type": "Feature",
  "properties": {
    "iso:country":"IN",
    "ks:ks_name":"Khetolai Budhan",
    "ks:ks_pop":40,
    "ks:ks_type":"VILLAGE",
    "name:eng_x_preferred":[
        "Khetolai Budhan"
    ],
    "wof:name":"Khetolai Budhan",
    "wof:placetype":"locality",
    "wof:population":40
},
  "geometry": {"coordinates":[72.89700999999999,27.769479],"type":"Point"}
}