{
  "type": "Feature",
  "properties": {
    "iso:country":"IN",
    "ks:ks_name":"Hosapete",
    "ks:ks_pop":35,
    "ks:ks_type":"HABITATION",
    "name:eng_x_preferred":[
        "Hosapete"
    ],
    "wof:name":"Hosapete",
    "wof:placetype":"locality",
    "wof:population":35
},
  "geometry": {"coordinates":[75.68560100000001,13.199154],"type":"Point"}
}