{
  "type": "Feature",
  "properties": {
    "iso:country":"IN",
    "ks:ks_name":"Ambedhkar Nagar",
    "ks:ks_pop":50,
    "ks:ks_type":"HABITATION",
    "name:eng_x_preferred":[
        "Ambedhkar Nagar"
    ],
    "wof:name":"Ambedhkar Nagar",
    "wof:placetype":"locality",
    "wof:population":50
},
  "geometry": {"coordinates":[79.483653,13.236391],"type":"Point"}
}