{
  "type": "Feature",
  "properties": {
    "gn:admin1_code":"38",
    "gn:admin2_code":"346.0",
    "gn:asciiname":"Hur",
    "gn:country_code":"IN",
    "gn:dem":193,
    "gn:feature_class":"P",
    "gn:feature_code":"PPL",
    "gn:name":"Hur",
    "gn:population":0,
    "gn:timezone":"Asia/Kolkata",
    "iso:country":"IN",
    "name:ceb_x_preferred":[
        "Hur"
    ],
    "name:fas_x_preferred":[
        "\u062d\u0648\u0631"
    ],
    "name:slk_x_preferred":[
        "Hur"
    ],
    "name:swe_x_preferred":[
        "Hur"
    ],
    "wof:name":"Hur",
    "wof:placetype":"locality"
},
  "geometry": {"coordinates":[83.85545999999999,24.16275],"type":"Point"}
}