{
  "type": "Feature",
  "properties": {
    "gn:admin1_code":"38",
    "gn:admin2_code":"346.0",
    "gn:asciiname":"Hur",
    "gn:country_code":"IN",
    "gn:dem":193,
    "gn:feature_class":"P",
    "gn:feature_code":"PPL",
    "gn:name":"Hur",
    "gn:population":0,
    "gn:timezone":"Asia/Kolkata",
    "iso:country":"IN",
    "ks:ks_name":"Hur",
    "ks:ks_pop":690,
    "ks:ks_type":"VILLAGE",
    "name:ceb_x_preferred":[
        "Hur"
    ],
    "name:eng_x_preferred":[
        "Hur"
    ],
    "name:fas_x_preferred":[
        "\u062d\u0648\u0631"
    ],
    "name:slk_x_preferred":[
        "Hur"
    ],
    "name:swe_x_preferred":[
        "Hur"
    ],
    "wof:name":"Hur",
    "wof:placetype":"locality",
    "wof:population":690
},
  "geometry": {"coordinates":[83.855463,24.162748],"type":"Point"}
}