{
  "type": "Feature",
  "properties": {
    "iso:country":"IN",
    "ks:ks_name":"Mahadevapura",
    "ks:ks_pop":1020,
    "ks:ks_type":"HABITATION",
    "name:eng_x_preferred":[
        "Mahadevapura"
    ],
    "wof:name":"Mahadevapura",
    "wof:placetype":"locality",
    "wof:population":1020
},
  "geometry": {"coordinates":[76.88766699999999,8.622202],"type":"Point"}
}