{
  "type": "Feature",
  "properties": {
    "gn:admin1_code":"11",
    "gn:admin2_code":"32.0",
    "gn:asciiname":"Gharirian",
    "gn:country_code":"IN",
    "gn:dem":1903,
    "gn:feature_class":"P",
    "gn:feature_code":"PPL",
    "gn:name":"Gharirian",
    "gn:population":0,
    "gn:timezone":"Asia/Kolkata",
    "iso:country":"IN",
    "wof:name":"Gharirian",
    "wof:placetype":"locality"
},
  "geometry": {"coordinates":[77.54737,30.76516],"type":"Point"}
}