{
  "type": "Feature",
  "properties": {
    "iso:country":"IN",
    "ks:ks_name":"Kolu Nimbayat",
    "ks:ks_pop":1702,
    "ks:ks_type":"VILLAGE",
    "name:eng_x_preferred":[
        "Kolu Nimbayat"
    ],
    "wof:name":"Kolu Nimbayat",
    "wof:placetype":"locality",
    "wof:population":1702
},
  "geometry": {"coordinates":[72.317581,26.888928],"type":"Point"}
}