{
  "type": "Feature",
  "properties": {
    "iso:country":"IN",
    "ks:ks_name":"Raiwadi",
    "ks:ks_pop":187,
    "ks:ks_type":"HABITATION",
    "name:eng_x_preferred":[
        "Raiwadi"
    ],
    "wof:name":"Raiwadi",
    "wof:placetype":"locality",
    "wof:population":187
},
  "geometry": {"coordinates":[73.621467,16.052937],"type":"Point"}
}