{
  "type": "Feature",
  "properties": {
    "iso:country":"IN",
    "ks:ks_name":"Dahisot",
    "ks:ks_pop":1438,
    "ks:ks_type":"VILLAGE",
    "ks:ks_uagg_main":0,
    "name:eng_x_preferred":[
        "Dahisot"
    ],
    "wof:name":"Dahisot",
    "wof:placetype":"neighbourhood",
    "wof:population":1438
},
  "geometry": {"coordinates":[85.258657,23.382837],"type":"Point"}
}