{
  "type": "Feature",
  "properties": {
    "gn:admin1_code":"2",
    "gn:admin2_code":"544.0",
    "gn:asciiname":"Batyaguda",
    "gn:country_code":"IN",
    "gn:dem":1040,
    "gn:feature_class":"P",
    "gn:feature_code":"PPL",
    "gn:name":"Batyag\u016bda",
    "gn:population":0,
    "gn:timezone":"Asia/Kolkata",
    "iso:country":"IN",
    "wof:name":"Batyaguda",
    "wof:placetype":"locality"
},
  "geometry": {"coordinates":[82.81826,18.38476],"type":"Point"}
}