{
  "type": "Feature",
  "properties": {
    "iso:country":"IN",
    "ks:ks_name":"Gher Dauhini",
    "ks:ks_pop":226,
    "ks:ks_type":"HABITATION",
    "name:eng_x_preferred":[
        "Gher Dauhini"
    ],
    "wof:name":"Gher Dauhini",
    "wof:placetype":"locality",
    "wof:population":226
},
  "geometry": {"coordinates":[78.496527,28.209252],"type":"Point"}
}