{
  "type": "Feature",
  "properties": {
    "iso:country":"IN",
    "ks:ks_name":"Dahawatola",
    "ks:ks_pop":215,
    "ks:ks_type":"HABITATION",
    "name:eng_x_preferred":[
        "Dahawatola"
    ],
    "wof:name":"Dahawatola",
    "wof:placetype":"locality",
    "wof:population":215
},
  "geometry": {"coordinates":[83.47877800000001,24.645366],"type":"Point"}
}