{
  "type": "Feature",
  "properties": {
    "iso:country":"IN",
    "ks:ks_name":"Chak Harati",
    "ks:ks_pop":5419,
    "ks:ks_type":"VILLAGE",
    "ks:ks_uagg_main":0,
    "name:eng_x_preferred":[
        "Chak Harati"
    ],
    "wof:name":"Chak Harati",
    "wof:placetype":"neighbourhood",
    "wof:population":5419
},
  "geometry": {"coordinates":[77.57623599999999,29.979577],"type":"Point"}
}