{
  "type": "Feature",
  "properties": {
    "iso:country":"IN",
    "ks:ks_name":"Singulagam",
    "ks:ks_pop":176,
    "ks:ks_type":"VILLAGE",
    "name:eng_x_preferred":[
        "Singulagam"
    ],
    "wof:name":"Singulagam",
    "wof:placetype":"locality",
    "wof:population":176
},
  "geometry": {"coordinates":[83.724464,20.39327],"type":"Point"}
}