{
  "type": "Feature",
  "properties": {
    "iso:country":"IN",
    "ks:ks_alt_nam":"SONON DEHULI",
    "ks:ks_name":"Sonon Dehuli",
    "ks:ks_pop":1451,
    "ks:ks_type":"HABITATION",
    "name:eng_x_preferred":[
        "Sonon Dehuli"
    ],
    "wof:name":"Sonon Dehuli",
    "wof:placetype":"locality",
    "wof:population":1451
},
  "geometry": {"coordinates":[86.116173,25.93689],"type":"Point"}
}