{
  "type": "Feature",
  "properties": {
    "iso:country":"IN",
    "ks:ks_name":"Bamundi Ganakpara",
    "ks:ks_pop":24,
    "ks:ks_type":"VILLAGE",
    "ks:ks_uagg_main":0,
    "name:eng_x_preferred":[
        "Bamundi Ganakpara"
    ],
    "wof:name":"Bamundi Ganakpara",
    "wof:placetype":"neighbourhood",
    "wof:population":24
},
  "geometry": {"coordinates":[91.48638,26.171237],"type":"Point"}
}