{
  "type": "Feature",
  "properties": {
    "gn:admin1_code":"11.0",
    "gn:admin2_code":"32.0",
    "gn:asciiname":"Tokion",
    "gn:country_code":"IN",
    "gn:dem":433,
    "gn:feature_class":"P",
    "gn:feature_code":"PPL",
    "gn:name":"Tokion",
    "gn:population":0,
    "gn:timezone":"Asia/Kolkata",
    "iso:country":"IN",
    "name:und_x_variant":[
        "S\u0101ns\u012bw\u0101la"
    ],
    "wof:name":"Tokion",
    "wof:placetype":"locality"
},
  "geometry": {"coordinates":[77.50506,30.49758],"type":"Point"}
}