{
  "type": "Feature",
  "properties": {
    "iso:country":"IN",
    "ks:ks_name":"Kothiapura",
    "ks:ks_pop":547,
    "ks:ks_type":"HABITATION",
    "name:eng_x_preferred":[
        "Kothiapura"
    ],
    "wof:name":"Kothiapura",
    "wof:placetype":"locality",
    "wof:population":547
},
  "geometry": {"coordinates":[73.477389,22.248139],"type":"Point"}
}