{
  "type": "Feature",
  "properties": {
    "gn:admin1_code":"12.0",
    "gn:admin2_code":"006",
    "gn:asciiname":"Buroth",
    "gn:country_code":"IN",
    "gn:dem":676,
    "gn:feature_class":"P",
    "gn:feature_code":"PPL",
    "gn:name":"Buroth",
    "gn:population":0,
    "gn:timezone":"Asia/Kolkata",
    "iso:country":"IN",
    "name:und_x_variant":[
        "Burothi"
    ],
    "wof:name":"Buroth",
    "wof:placetype":"locality"
},
  "geometry": {"coordinates":[74.17625,33.19622],"type":"Point"}
}