{
  "type": "Feature",
  "properties": {
    "gn:admin1_code":"35.0",
    "gn:admin2_code":"434.0",
    "gn:asciiname":"Biga-Patan",
    "gn:country_code":"IN",
    "gn:dem":403,
    "gn:feature_class":"P",
    "gn:feature_code":"PPL",
    "gn:name":"Biga-Patan",
    "gn:population":0,
    "gn:timezone":"Asia/Kolkata",
    "iso:country":"IN",
    "ks:ks_name":"Bikapatan",
    "ks:ks_pop":394,
    "ks:ks_type":"VILLAGE",
    "name:eng_x_preferred":[
        "Bikapatan"
    ],
    "name:eng_x_variant":[
        "Biga-Patan"
    ],
    "wof:name":"Bikapatan",
    "wof:placetype":"locality",
    "wof:population":394
},
  "geometry": {"coordinates":[74.918971,23.206015],"type":"Point"}
}