{
  "type": "Feature",
  "properties": {
    "gn:admin1_code":"35.0",
    "gn:admin2_code":"434.0",
    "gn:asciiname":"Biga-Patan",
    "gn:country_code":"IN",
    "gn:dem":403,
    "gn:feature_class":"P",
    "gn:feature_code":"PPL",
    "gn:name":"Biga-Patan",
    "gn:population":0,
    "gn:timezone":"Asia/Kolkata",
    "iso:country":"IN",
    "wof:name":"Biga-Patan",
    "wof:placetype":"locality"
},
  "geometry": {"coordinates":[74.91859000000002,23.1991],"type":"Point"}
}