{
  "type": "Feature",
  "properties": {
    "iso:country":"IN",
    "ks:ks_name":"Schooltoli",
    "ks:ks_pop":179,
    "ks:ks_type":"HABITATION",
    "name:eng_x_preferred":[
        "Schooltoli"
    ],
    "wof:name":"Schooltoli",
    "wof:placetype":"locality",
    "wof:population":179
},
  "geometry": {"coordinates":[84.976315,22.748244],"type":"Point"}
}