{
  "type": "Feature",
  "properties": {
    "iso:country":"IN",
    "ks:ks_name":"Uttar Brindabanbati",
    "ks:ks_pop":39,
    "ks:ks_type":"VILLAGE",
    "name:eng_x_preferred":[
        "Uttar Brindabanbati"
    ],
    "wof:name":"Uttar Brindabanbati",
    "wof:placetype":"locality",
    "wof:population":39
},
  "geometry": {"coordinates":[88.383983,24.998696],"type":"Point"}
}