{
  "type": "Feature",
  "properties": {
    "iso:country":"IN",
    "ks:ks_name":"Rampur Khaspara",
    "ks:ks_pop":857,
    "ks:ks_type":"HABITATION",
    "name:eng_x_preferred":[
        "Rampur Khaspara"
    ],
    "wof:name":"Rampur Khaspara",
    "wof:placetype":"locality",
    "wof:population":857
},
  "geometry": {"coordinates":[82.737053,23.453531],"type":"Point"}
}