{
  "type": "Feature",
  "properties": {
    "iso:country":"IN",
    "ks:ks_name":"Tharalu Estate",
    "ks:ks_pop":423,
    "ks:ks_type":"HABITATION",
    "name:eng_x_preferred":[
        "Tharalu Estate"
    ],
    "wof:name":"Tharalu Estate",
    "wof:placetype":"locality",
    "wof:population":423
},
  "geometry": {"coordinates":[77.533388,12.774204],"type":"Point"}
}