{
  "type": "Feature",
  "properties": {
    "iso:country":"IN",
    "ks:ks_name":"Abhayapur",
    "ks:ks_pop":253,
    "ks:ks_type":"VILLAGE",
    "name:eng_x_preferred":[
        "Abhayapur"
    ],
    "wof:name":"Abhayapur",
    "wof:placetype":"locality",
    "wof:population":253
},
  "geometry": {"coordinates":[84.553969,20.238926],"type":"Point"}
}