{
  "type": "Feature",
  "properties": {
    "iso:country":"IN",
    "ks:ks_name":"Zari",
    "ks:ks_pop":3251,
    "ks:ks_type":"VILLAGE",
    "name:eng_x_preferred":[
        "Zari"
    ],
    "wof:name":"Zari",
    "wof:placetype":"locality",
    "wof:population":3251
},
  "geometry": {"coordinates":[72.872474,20.145396],"type":"Point"}
}