{
  "type": "Feature",
  "properties": {
    "iso:country":"IN",
    "ks:ks_name":"Jivajini Muvadi",
    "ks:ks_pop":534,
    "ks:ks_type":"VILLAGE",
    "ks:ks_uagg_main":0,
    "name:eng_x_preferred":[
        "Jivajini Muvadi"
    ],
    "wof:name":"Jivajini Muvadi",
    "wof:placetype":"neighbourhood",
    "wof:population":534
},
  "geometry": {"coordinates":[72.820167,23.100278],"type":"Point"}
}