{
  "type": "Feature",
  "properties": {
    "iso:country":"IN",
    "ks:ks_name":"Kariya Purwa",
    "ks:ks_pop":160,
    "ks:ks_type":"HABITATION",
    "name:eng_x_preferred":[
        "Kariya Purwa"
    ],
    "wof:name":"Kariya Purwa",
    "wof:placetype":"locality",
    "wof:population":160
},
  "geometry": {"coordinates":[81.654618,27.12325],"type":"Point"}
}