{
  "type": "Feature",
  "properties": {
    "gn:admin1_code":"35.0",
    "gn:admin2_code":"464.0",
    "gn:asciiname":"Kachla",
    "gn:country_code":"IN",
    "gn:dem":306,
    "gn:feature_class":"P",
    "gn:feature_code":"PPL",
    "gn:name":"Kachla",
    "gn:population":0,
    "gn:timezone":"Asia/Kolkata",
    "iso:country":"IN",
    "ks:ks_name":"Kachala",
    "ks:ks_pop":798,
    "ks:ks_type":"VILLAGE",
    "name:eng_x_preferred":[
        "Kachala"
    ],
    "name:eng_x_variant":[
        "Kachla"
    ],
    "wof:name":"Kachala",
    "wof:placetype":"locality",
    "wof:population":798
},
  "geometry": {"coordinates":[74.52920399999999,22.847569],"type":"Point"}
}