{
  "type": "Feature",
  "properties": {
    "gn:admin1_code":"16.0",
    "gn:admin2_code":"510.0",
    "gn:asciiname":"Nandgaon",
    "gn:country_code":"IN",
    "gn:dem":222,
    "gn:feature_class":"P",
    "gn:feature_code":"PPL",
    "gn:name":"Nandgaon",
    "gn:population":0,
    "gn:timezone":"Asia/Kolkata",
    "iso:country":"IN",
    "name:ceb_x_preferred":[
        "Nandgaon"
    ],
    "name:pol_x_preferred":[
        "Nandgaon"
    ],
    "name:swe_x_preferred":[
        "Nandgaon"
    ],
    "wof:name":"Nandgaon",
    "wof:placetype":"locality"
},
  "geometry": {"coordinates":[78.96488000000002,19.8609],"type":"Point"}
}