{
  "type": "Feature",
  "properties": {
    "gn:admin1_code":"36.0",
    "gn:admin2_code":"132.0",
    "gn:asciiname":"Nogla Khari",
    "gn:country_code":"IN",
    "gn:dem":278,
    "gn:feature_class":"P",
    "gn:feature_code":"PPL",
    "gn:name":"Nogla Kh\u0101ri",
    "gn:population":0,
    "gn:timezone":"Asia/Kolkata",
    "iso:country":"IN",
    "name:und_x_variant":[
        "Nogla Kh\u0101ri",
        "B\u0101ri M\u0101zra"
    ],
    "wof:name":"Nogla Khari",
    "wof:placetype":"locality"
},
  "geometry": {"coordinates":[77.48132,29.96084],"type":"Point"}
}