{
  "type": "Feature",
  "properties": {
    "iso:country":"IN",
    "ks:ks_name":"Baliamale",
    "ks:ks_pop":612,
    "ks:ks_type":"HABITATION",
    "name:eng_x_preferred":[
        "Baliamale"
    ],
    "wof:name":"Baliamale",
    "wof:placetype":"locality",
    "wof:population":612
},
  "geometry": {"coordinates":[85.906443,20.195771],"type":"Point"}
}