{
  "type": "Feature",
  "properties": {
    "gn:admin1_code":"34.0",
    "gn:admin2_code":"229.0",
    "gn:asciiname":"Bhuthakhar",
    "gn:country_code":"IN",
    "gn:dem":53,
    "gn:feature_class":"P",
    "gn:feature_code":"PPL",
    "gn:name":"Bhuth\u0101kh\u0101r",
    "gn:population":0,
    "gn:timezone":"Asia/Kolkata",
    "iso:country":"IN",
    "ks:ks_alt_nam":"Bhuth\u0101kh\u0101r",
    "ks:ks_name":"Bhuthakhar",
    "ks:ks_pop":423,
    "ks:ks_type":"VILLAGE",
    "name:eng_x_preferred":[
        "Bhuthakhar"
    ],
    "name:eng_x_variant":[
        "Bhuth\u0101kh\u0101r"
    ],
    "wof:name":"Bhuthakhar",
    "wof:placetype":"locality",
    "wof:population":423
},
  "geometry": {"coordinates":[85.39626199999999,25.405669],"type":"Point"}
}