{
  "type": "Feature",
  "properties": {
    "iso:country":"IN",
    "ks:ks_name":"Rathava Falia",
    "ks:ks_pop":202,
    "ks:ks_type":"HABITATION",
    "name:eng_x_preferred":[
        "Rathava Falia"
    ],
    "wof:name":"Rathava Falia",
    "wof:placetype":"locality",
    "wof:population":202
},
  "geometry": {"coordinates":[73.46975,22.680217],"type":"Point"}
}