{
  "type": "Feature",
  "properties": {
    "iso:country":"IN",
    "ks:ks_name":"Bantolba Naya t",
    "ks:ks_pop":110,
    "ks:ks_type":"HABITATION",
    "ks:ks_uagg_main":0,
    "name:eng_x_preferred":[
        "Bantolba Naya t"
    ],
    "wof:name":"Bantolba Naya t",
    "wof:placetype":"neighbourhood",
    "wof:population":110
},
  "geometry": {"coordinates":[85.61188,26.381611],"type":"Point"}
}