{
  "type": "Feature",
  "properties": {
    "gn:admin1_code":"36",
    "gn:admin2_code":"180.0",
    "gn:asciiname":"Mohanpur Mafi",
    "gn:country_code":"IN",
    "gn:dem":117,
    "gn:feature_class":"P",
    "gn:feature_code":"PPL",
    "gn:name":"Mohanpur M\u0101fi",
    "gn:population":0,
    "gn:timezone":"Asia/Kolkata",
    "iso:country":"IN",
    "ks:ks_alt_nam":"Mohanpur M\u0101fi",
    "ks:ks_name":"Mohanpur Mafi",
    "ks:ks_type":"VILLAGE",
    "ks:ks_uagg_main":0,
    "name:eng_x_preferred":[
        "Mohanpur Mafi"
    ],
    "name:eng_x_variant":[
        "Mohanpur M\u0101fi"
    ],
    "wof:name":"Mohanpur Mafi",
    "wof:placetype":"neighbourhood"
},
  "geometry": {"coordinates":[81.699364,27.411164],"type":"Point"}
}