{
  "type": "Feature",
  "properties": {
    "iso:country":"IN",
    "ks:ks_name":"Nematanr",
    "ks:ks_pop":220,
    "ks:ks_type":"VILLAGE",
    "ks:ks_uagg_main":0,
    "name:eng_x_preferred":[
        "Nematanr"
    ],
    "wof:name":"Nematanr",
    "wof:placetype":"neighbourhood",
    "wof:population":220
},
  "geometry": {"coordinates":[86.142752,24.455094],"type":"Point"}
}