{
  "type": "Feature",
  "properties": {
    "iso:country":"IN",
    "ks:ks_name":"Awaspara",
    "ks:ks_pop":63,
    "ks:ks_type":"HABITATION",
    "name:eng_x_preferred":[
        "Awaspara"
    ],
    "wof:name":"Awaspara",
    "wof:placetype":"locality",
    "wof:population":63
},
  "geometry": {"coordinates":[81.21961899999999,19.715182],"type":"Point"}
}