{
  "type": "Feature",
  "properties": {
    "iso:country":"IN",
    "ks:ks_name":"Jhirigaon",
    "ks:ks_pop":85,
    "ks:ks_type":"VILLAGE",
    "name:eng_x_preferred":[
        "Jhirigaon"
    ],
    "wof:name":"Jhirigaon",
    "wof:placetype":"locality",
    "wof:population":85
},
  "geometry": {"coordinates":[82.86506,19.262769],"type":"Point"}
}