{
  "type": "Feature",
  "properties": {
    "iso:country":"IN",
    "ks:ks_name":"Kelanattar",
    "ks:ks_pop":18,
    "ks:ks_type":"HABITATION",
    "name:eng_x_preferred":[
        "Kelanattar"
    ],
    "wof:name":"Kelanattar",
    "wof:placetype":"locality",
    "wof:population":18
},
  "geometry": {"coordinates":[75.35471200000001,12.655433],"type":"Point"}
}