{
  "type": "Feature",
  "properties": {
    "iso:country":"IN",
    "ks:ks_name":"Vakilwasti",
    "ks:ks_pop":800,
    "ks:ks_type":"HABITATION",
    "name:eng_x_preferred":[
        "Vakilwasti"
    ],
    "wof:name":"Vakilwasti",
    "wof:placetype":"locality",
    "wof:population":800
},
  "geometry": {"coordinates":[74.41909699999999,18.44818],"type":"Point"}
}