{
  "type": "Feature",
  "properties": {
    "iso:country":"IN",
    "ks:ks_name":"Kinassery",
    "ks:ks_pop":1717,
    "ks:ks_type":"HABITATION",
    "ks:ks_uagg_main":0,
    "name:eng_x_preferred":[
        "Kinassery"
    ],
    "wof:name":"Kinassery",
    "wof:placetype":"neighbourhood",
    "wof:population":1717
},
  "geometry": {"coordinates":[76.396997,10.881218],"type":"Point"}
}