{
  "type": "Feature",
  "properties": {
    "iso:country":"IN",
    "ks:ks_name":"Khadgaon",
    "ks:ks_pop":1667,
    "ks:ks_type":"VILLAGE",
    "ks:ks_uagg_main":0,
    "name:eng_x_preferred":[
        "Khadgaon"
    ],
    "wof:name":"Khadgaon",
    "wof:placetype":"locality",
    "wof:population":1667
},
  "geometry": {"coordinates":[76.54708100000001,18.392186],"type":"Point"}
}