{
  "type": "Feature",
  "properties": {
    "iso:country":"IN",
    "ks:ks_name":"Lawapiri",
    "ks:ks_pop":613,
    "ks:ks_type":"VILLAGE",
    "ks:ks_uagg_main":0,
    "name:eng_x_preferred":[
        "Lawapiri"
    ],
    "wof:name":"Lawapiri",
    "wof:placetype":"neighbourhood",
    "wof:population":613
},
  "geometry": {"coordinates":[85.84926,23.365242],"type":"Point"}
}