{
  "type": "Feature",
  "properties": {
    "iso:country":"IN",
    "ks:ks_name":"Madanhana",
    "ks:ks_pop":166,
    "ks:ks_type":"HABITATION",
    "name:eng_x_preferred":[
        "Madanhana"
    ],
    "wof:name":"Madanhana",
    "wof:placetype":"locality",
    "wof:population":166
},
  "geometry": {"coordinates":[83.104147,27.231701],"type":"Point"}
}