{
  "type": "Feature",
  "properties": {
    "iso:country":"IN",
    "ks:ks_alt_nam":"Dol\u0101",
    "ks:ks_name":"Dola",
    "ks:ks_pop":275,
    "ks:ks_type":"VILLAGE",
    "name:eng_x_preferred":[
        "Dola"
    ],
    "name:eng_x_variant":[
        "Dol\u0101"
    ],
    "wof:name":"Dola",
    "wof:placetype":"locality",
    "wof:population":275
},
  "geometry": {"coordinates":[85.081973,23.267473],"type":"Point"}
}