{
  "type": "Feature",
  "properties": {
    "iso:country":"IN",
    "ks:ks_name":"Lala Tola",
    "ks:ks_pop":880,
    "ks:ks_type":"HABITATION",
    "name:eng_x_preferred":[
        "Lala Tola"
    ],
    "wof:name":"Lala Tola",
    "wof:placetype":"locality",
    "wof:population":880
},
  "geometry": {"coordinates":[84.382133,26.788398],"type":"Point"}
}