{
  "type": "Feature",
  "properties": {
    "gn:admin1_code":"2.0",
    "gn:admin2_code":"544.0",
    "gn:asciiname":"Duvvupeta",
    "gn:country_code":"IN",
    "gn:dem":41,
    "gn:feature_class":"P",
    "gn:feature_code":"PPL",
    "gn:name":"Duvvupeta",
    "gn:population":0,
    "gn:timezone":"Asia/Kolkata",
    "iso:country":"IN",
    "ks:ks_name":"Duvvupeta",
    "ks:ks_pop":361,
    "ks:ks_type":"HABITATION",
    "name:eng_x_preferred":[
        "Duvvupeta"
    ],
    "wof:name":"Duvvupeta",
    "wof:placetype":"locality",
    "wof:population":361
},
  "geometry": {"coordinates":[83.379559,18.000742],"type":"Point"}
}