{
  "type": "Feature",
  "properties": {
    "gn:admin1_code":"2.0",
    "gn:admin2_code":"550.0",
    "gn:asciiname":"Tellapadu",
    "gn:country_code":"IN",
    "gn:dem":73,
    "gn:feature_class":"P",
    "gn:feature_code":"PPL",
    "gn:name":"Tellap\u0101du",
    "gn:population":0,
    "gn:timezone":"Asia/Kolkata",
    "iso:country":"IN",
    "name:tel_x_preferred":[
        "\u0c24\u0c46\u0c32\u0c4d\u0c32\u0c2c\u0c3e\u0c21\u0c41"
    ],
    "name:urd_x_preferred":[
        "\u062a\u06cc\u0644\u0627\u067e\u0627\u0691\u0648"
    ],
    "wof:name":"Tellapadu",
    "wof:placetype":"locality"
},
  "geometry": {"coordinates":[79.64664,14.90776],"type":"Point"}
}