{
  "type": "Feature",
  "properties": {
    "iso:country":"IN",
    "ks:ks_name":"Burishol",
    "ks:ks_pop":159,
    "ks:ks_type":"VILLAGE",
    "name:eng_x_preferred":[
        "Burishol"
    ],
    "wof:name":"Burishol",
    "wof:placetype":"locality",
    "wof:population":159
},
  "geometry": {"coordinates":[86.70835,22.575624],"type":"Point"}
}