{
  "type": "Feature",
  "properties": {
    "iso:country":"IN",
    "ks:ks_name":"Kadwadih",
    "ks:ks_pop":365,
    "ks:ks_type":"VILLAGE",
    "name:eng_x_preferred":[
        "Kadwadih"
    ],
    "wof:name":"Kadwadih",
    "wof:placetype":"locality",
    "wof:population":365
},
  "geometry": {"coordinates":[85.87205899999999,22.128067],"type":"Point"}
}