{
  "type": "Feature",
  "properties": {
    "iso:country":"IN",
    "ks:ks_name":"Rule",
    "ks:ks_pop":150,
    "ks:ks_type":"HABITATION",
    "name:eng_x_preferred":[
        "Rule"
    ],
    "wof:name":"Rule",
    "wof:placetype":"locality",
    "wof:population":150
},
  "geometry": {"coordinates":[73.679463,17.791854],"type":"Point"}
}