{
  "type": "Feature",
  "properties": {
    "iso:country":"IN",
    "ks:ks_alt_nam":"RAMSANKAR BARI",
    "ks:ks_name":"Ramsankar Bari",
    "ks:ks_pop":73,
    "ks:ks_type":"HABITATION",
    "ks:ks_uagg_main":0,
    "name:eng_x_preferred":[
        "Ramsankar Bari"
    ],
    "wof:name":"Ramsankar Bari",
    "wof:placetype":"neighbourhood",
    "wof:population":73
},
  "geometry": {"coordinates":[91.68448600000001,24.133227],"type":"Point"}
}