{
  "type": "Feature",
  "properties": {
    "gn:admin1_code":"25",
    "gn:admin2_code":"604.0",
    "gn:asciiname":"Padalam",
    "gn:country_code":"IN",
    "gn:dem":28,
    "gn:feature_class":"P",
    "gn:feature_code":"PPL",
    "gn:name":"Pad\u0101lam",
    "gn:population":0,
    "gn:timezone":"Asia/Kolkata",
    "iso:country":"IN",
    "name:tam_x_preferred":[
        "\u0baa\u0b9f\u0bbe\u0bb3\u0bae\u0bcd"
    ],
    "name:und_x_variant":[
        "Pad\u0101lam"
    ],
    "wof:name":"Padalam",
    "wof:placetype":"locality"
},
  "geometry": {"coordinates":[79.94969,12.59256],"type":"Point"}
}