{
  "type": "Feature",
  "properties": {
    "iso:country":"IN",
    "ks:ks_name":"Chilaun Talla",
    "ks:ks_pop":213,
    "ks:ks_type":"HABITATION",
    "name:eng_x_preferred":[
        "Chilaun Talla"
    ],
    "wof:name":"Chilaun Talla",
    "wof:placetype":"locality",
    "wof:population":213
},
  "geometry": {"coordinates":[78.96743499999999,29.660675],"type":"Point"}
}