{
  "type": "Feature",
  "properties": {
    "iso:country":"IN",
    "ks:ks_name":"Cheddipurva",
    "ks:ks_pop":129,
    "ks:ks_type":"HABITATION",
    "ks:ks_uagg_main":0,
    "name:eng_x_preferred":[
        "Cheddipurva"
    ],
    "wof:name":"Cheddipurva",
    "wof:placetype":"neighbourhood",
    "wof:population":129
},
  "geometry": {"coordinates":[82.169482,27.581125],"type":"Point"}
}