{
  "type": "Feature",
  "properties": {
    "iso:country":"IN",
    "ks:ks_name":"Naranpura",
    "ks:ks_pop":383,
    "ks:ks_type":"HABITATION",
    "name:eng_x_preferred":[
        "Naranpura"
    ],
    "wof:name":"Naranpura",
    "wof:placetype":"locality",
    "wof:population":383
},
  "geometry": {"coordinates":[72.83475900000001,22.561115],"type":"Point"}
}