{
  "type": "Feature",
  "properties": {
    "iso:country":"IN",
    "ks:ks_name":"Poddar Tola",
    "ks:ks_pop":130,
    "ks:ks_type":"HABITATION",
    "name:eng_x_preferred":[
        "Poddar Tola"
    ],
    "wof:name":"Poddar Tola",
    "wof:placetype":"locality",
    "wof:population":130
},
  "geometry": {"coordinates":[86.96284300000001,25.113577],"type":"Point"}
}