{
  "type": "Feature",
  "properties": {
    "iso:country":"IN",
    "ks:ks_name":"Kakkayan Thottam",
    "ks:ks_pop":153,
    "ks:ks_type":"HABITATION",
    "name:eng_x_preferred":[
        "Kakkayan Thottam"
    ],
    "wof:name":"Kakkayan Thottam",
    "wof:placetype":"locality",
    "wof:population":153
},
  "geometry": {"coordinates":[77.987296,11.168469],"type":"Point"}
}