{
  "type": "Feature",
  "properties": {
    "gn:admin1_code":"34.0",
    "gn:admin2_code":"226.0",
    "gn:asciiname":"Ammabadar",
    "gn:country_code":"IN",
    "gn:dem":58,
    "gn:feature_class":"P",
    "gn:feature_code":"PPL",
    "gn:name":"Ammab\u0101dar",
    "gn:population":0,
    "gn:timezone":"Asia/Kolkata",
    "iso:country":"IN",
    "wof:name":"Ammabadar",
    "wof:placetype":"locality"
},
  "geometry": {"coordinates":[86.59912,25.07456],"type":"Point"}
}