{
  "type": "Feature",
  "properties": {
    "gn:admin1_code":"28.0",
    "gn:admin2_code":"334.0",
    "gn:asciiname":"Jankinagar",
    "gn:country_code":"IN",
    "gn:dem":29,
    "gn:feature_class":"P",
    "gn:feature_code":"PPL",
    "gn:name":"J\u0101nkinagar",
    "gn:population":0,
    "gn:timezone":"Asia/Kolkata",
    "iso:country":"IN",
    "ks:ks_name":"Janakinagar",
    "ks:ks_pop":334,
    "ks:ks_type":"HABITATION",
    "name:eng_x_preferred":[
        "Janakinagar"
    ],
    "name:eng_x_variant":[
        "Jankinagar"
    ],
    "wof:name":"Janakinagar",
    "wof:placetype":"locality",
    "wof:population":334
},
  "geometry": {"coordinates":[87.908665,24.495805],"type":"Point"}
}