{
  "type": "Feature",
  "properties": {
    "iso:country":"IN",
    "ks:ks_name":"Kotrapady",
    "ks:ks_pop":255,
    "ks:ks_type":"HABITATION",
    "name:eng_x_preferred":[
        "Kotrapady"
    ],
    "wof:name":"Kotrapady",
    "wof:placetype":"locality",
    "wof:population":255
},
  "geometry": {"coordinates":[74.893631,13.098356],"type":"Point"}
}