{
  "type": "Feature",
  "properties": {
    "iso:country":"IN",
    "ks:ks_alt_nam":"Meel santhampatti",
    "ks:ks_name":"Meel Santhampatti",
    "ks:ks_pop":210,
    "ks:ks_type":"HABITATION",
    "name:eng_x_preferred":[
        "Meel Santhampatti"
    ],
    "wof:name":"Meel Santhampatti",
    "wof:placetype":"locality",
    "wof:population":210
},
  "geometry": {"coordinates":[78.445437,12.34367],"type":"Point"}
}