{
  "type": "Feature",
  "properties": {
    "gn:admin1_code":"25.0",
    "gn:admin2_code":"604.0",
    "gn:asciiname":"Pudupakkam",
    "gn:country_code":"IN",
    "gn:dem":95,
    "gn:feature_class":"P",
    "gn:feature_code":"PPL",
    "gn:name":"Pudup\u0101kkam",
    "gn:population":0,
    "gn:timezone":"Asia/Kolkata",
    "iso:country":"IN",
    "wof:name":"Pudupakkam",
    "wof:placetype":"locality"
},
  "geometry": {"coordinates":[79.67171,12.9194],"type":"Point"}
}