{
  "type": "Feature",
  "properties": {
    "gn:admin1_code":"12.0",
    "gn:admin2_code":"16.0",
    "gn:asciiname":"Habrakh",
    "gn:country_code":"IN",
    "gn:dem":1863,
    "gn:feature_class":"P",
    "gn:feature_code":"PPL",
    "gn:name":"Habrakh",
    "gn:population":0,
    "gn:timezone":"Asia/Kolkata",
    "iso:country":"IN",
    "wof:name":"Habrakh",
    "wof:placetype":"locality"
},
  "geometry": {"coordinates":[75.55659,33.08934],"type":"Point"}
}