{
  "type": "Feature",
  "properties": {
    "gn:admin1_code":"11",
    "gn:admin2_code":"27.0",
    "gn:asciiname":"Lanihnun",
    "gn:country_code":"IN",
    "gn:dem":1110,
    "gn:feature_class":"P",
    "gn:feature_code":"PPL",
    "gn:name":"Lanihn\u016bn",
    "gn:population":0,
    "gn:timezone":"Asia/Kolkata",
    "iso:country":"IN",
    "wof:name":"Lanihnun",
    "wof:placetype":"locality"
},
  "geometry": {"coordinates":[76.97641,31.81406],"type":"Point"}
}