{
  "type": "Feature",
  "properties": {
    "iso:country":"IN",
    "ks:ks_name":"Shekhpur",
    "ks:ks_pop":70,
    "ks:ks_type":"HABITATION",
    "name:eng_x_preferred":[
        "Shekhpur"
    ],
    "wof:name":"Shekhpur",
    "wof:placetype":"locality",
    "wof:population":70
},
  "geometry": {"coordinates":[74.425076,22.398505],"type":"Point"}
}