{
  "type": "Feature",
  "properties": {
    "gn:admin1_code":"39",
    "gn:admin2_code":"60.0",
    "gn:asciiname":"Sane-ki-Bag",
    "gn:country_code":"IN",
    "gn:dem":1923,
    "gn:feature_class":"P",
    "gn:feature_code":"PPL",
    "gn:name":"S\u0101ne-ki-B\u0101g",
    "gn:population":0,
    "gn:timezone":"Asia/Kolkata",
    "iso:country":"IN",
    "wof:name":"Sane-ki-Bag",
    "wof:placetype":"locality"
},
  "geometry": {"coordinates":[77.94649,30.76401],"type":"Point"}
}