{
  "type": "Feature",
  "properties": {
    "iso:country":"IN",
    "ks:ks_name":"Mundatoli",
    "ks:ks_pop":535,
    "ks:ks_type":"HABITATION",
    "name:eng_x_preferred":[
        "Mundatoli"
    ],
    "wof:name":"Mundatoli",
    "wof:placetype":"locality",
    "wof:population":535
},
  "geometry": {"coordinates":[85.24063700000001,23.518881],"type":"Point"}
}