{
  "type": "Feature",
  "properties": {
    "gn:admin1_code":"19.0",
    "gn:admin2_code":"577.0",
    "gn:asciiname":"Madhuvanahalli",
    "gn:country_code":"IN",
    "gn:dem":811,
    "gn:feature_class":"P",
    "gn:feature_code":"PPL",
    "gn:name":"Madhuvanahalli",
    "gn:population":0,
    "gn:timezone":"Asia/Kolkata",
    "iso:country":"IN",
    "name:urd_x_preferred":[
        "\u0645\u062f\u06be\u0648\u0648\u0627\u0646\u0627\u06c1\u0627\u0644\u06cc"
    ],
    "wof:name":"Madhuvanahalli",
    "wof:placetype":"locality"
},
  "geometry": {"coordinates":[76.37473,12.4407],"type":"Point"}
}