{
  "type": "Feature",
  "properties": {
    "iso:country":"IN",
    "ks:ks_alt_nam":"Sirukadamb\u016br",
    "ks:ks_name":"Sirukadambur",
    "ks:ks_type":"VILLAGE",
    "ks:ks_uagg_main":0,
    "name:eng_x_preferred":[
        "Sirukadambur"
    ],
    "name:eng_x_variant":[
        "Sirukadamb\u016br"
    ],
    "wof:name":"Sirukadambur",
    "wof:placetype":"neighbourhood"
},
  "geometry": {"coordinates":[79.416279,12.260362],"type":"Point"}
}