{
  "type": "Feature",
  "properties": {
    "iso:country":"IN",
    "ks:ks_alt_nam":"permapara",
    "ks:ks_name":"Permapara",
    "ks:ks_pop":194,
    "ks:ks_type":"HABITATION",
    "name:eng_x_preferred":[
        "Permapara"
    ],
    "wof:name":"Permapara",
    "wof:placetype":"locality",
    "wof:population":194
},
  "geometry": {"coordinates":[81.62447899999999,18.735902],"type":"Point"}
}