{
  "type": "Feature",
  "properties": {
    "iso:country":"IN",
    "ks:ks_name":"Mathodu Gollarahatti",
    "ks:ks_pop":392,
    "ks:ks_type":"HABITATION",
    "name:eng_x_preferred":[
        "Mathodu Gollarahatti"
    ],
    "wof:name":"Mathodu Gollarahatti",
    "wof:placetype":"locality",
    "wof:population":392
},
  "geometry": {"coordinates":[76.401972,13.781613],"type":"Point"}
}