{
  "type": "Feature",
  "properties": {
    "gn:admin1_code":"35",
    "gn:admin2_code":"429.0",
    "gn:asciiname":"Bachia",
    "gn:country_code":"IN",
    "gn:dem":302,
    "gn:feature_class":"P",
    "gn:feature_code":"PPL",
    "gn:name":"Bachia",
    "gn:population":0,
    "gn:timezone":"Asia/Kolkata",
    "iso:country":"IN",
    "name:ceb_x_preferred":[
        "Bachia"
    ],
    "name:eus_x_preferred":[
        "Bachia"
    ],
    "name:fra_x_preferred":[
        "Bachia"
    ],
    "name:nld_x_preferred":[
        "Graafteju's"
    ],
    "name:pol_x_preferred":[
        "Bachia"
    ],
    "name:ron_x_preferred":[
        "Bachia"
    ],
    "name:spa_x_preferred":[
        "Bachia"
    ],
    "name:swe_x_preferred":[
        "Bachia"
    ],
    "name:war_x_preferred":[
        "Bachia"
    ],
    "wof:name":"Bachia",
    "wof:placetype":"locality"
},
  "geometry": {"coordinates":[80.90096,24.69518],"type":"Point"}
}