{
  "type": "Feature",
  "properties": {
    "gn:admin1_code":"38.0",
    "gn:asciiname":"Barmotar Lakheraj",
    "gn:country_code":"IN",
    "gn:dem":34,
    "gn:feature_class":"P",
    "gn:feature_code":"PPL",
    "gn:name":"Barmotar L\u0101kher\u0101j",
    "gn:population":0,
    "gn:timezone":"Asia/Kolkata",
    "iso:country":"IN",
    "ks:ks_name":"Barmotar Lakheraj",
    "ks:ks_pop":394,
    "ks:ks_type":"VILLAGE",
    "ks:ks_uagg_main":0,
    "name:eng_x_preferred":[
        "Barmotar Lakheraj"
    ],
    "wof:name":"Barmotar Lakheraj",
    "wof:placetype":"neighbourhood",
    "wof:population":394
},
  "geometry": {"coordinates":[87.48686499999999,25.27885],"type":"Point"}
}