{
  "type": "Feature",
  "properties": {
    "iso:country":"IN",
    "ks:ks_alt_nam":"Chathappan mukku",
    "ks:ks_name":"Chathappan Mukku",
    "ks:ks_pop":367,
    "ks:ks_type":"HABITATION",
    "name:eng_x_preferred":[
        "Chathappan Mukku"
    ],
    "wof:name":"Chathappan Mukku",
    "wof:placetype":"locality",
    "wof:population":367
},
  "geometry": {"coordinates":[76.012016,11.50019],"type":"Point"}
}