{
  "type": "Feature",
  "properties": {
    "iso:country":"IN",
    "ks:ks_name":"Urang Bosti",
    "ks:ks_pop":223,
    "ks:ks_type":"HABITATION",
    "name:eng_x_preferred":[
        "Urang Bosti"
    ],
    "wof:name":"Urang Bosti",
    "wof:placetype":"locality",
    "wof:population":223
},
  "geometry": {"coordinates":[94.034814,26.570846],"type":"Point"}
}