{
  "type": "Feature",
  "properties": {
    "gn:admin1_code":"28.0",
    "gn:admin2_code":"334.0",
    "gn:asciiname":"Aula",
    "gn:country_code":"IN",
    "gn:dem":45,
    "gn:feature_class":"P",
    "gn:feature_code":"PPL",
    "gn:name":"\u0100ula",
    "gn:population":0,
    "gn:timezone":"Asia/Kolkata",
    "iso:country":"IN",
    "name:cat_x_preferred":[
        "Aula"
    ],
    "name:ceb_x_preferred":[
        "Aula"
    ],
    "name:ces_x_preferred":[
        "Aula"
    ],
    "name:dan_x_preferred":[
        "Aula"
    ],
    "name:deu_x_preferred":[
        "Aula"
    ],
    "name:fin_x_preferred":[
        "Aula"
    ],
    "name:lat_x_preferred":[
        "Aula"
    ],
    "name:nld_x_preferred":[
        "Aula"
    ],
    "name:rus_x_preferred":[
        "\u0410\u0443\u043b\u0430"
    ],
    "name:slk_x_preferred":[
        "Aula"
    ],
    "name:spa_x_preferred":[
        "Aula"
    ],
    "name:swe_x_preferred":[
        "Aula"
    ],
    "wof:name":"Aula",
    "wof:placetype":"locality"
},
  "geometry": {"coordinates":[87.74963000000002,24.24563],"type":"Point"}
}