{
  "type": "Feature",
  "properties": {
    "gn:admin1_code":"12.0",
    "gn:admin2_code":"006",
    "gn:asciiname":"Kanga",
    "gn:country_code":"IN",
    "gn:dem":1548,
    "gn:feature_class":"P",
    "gn:feature_code":"PPL",
    "gn:name":"K\u0101nga",
    "gn:population":0,
    "gn:timezone":"Asia/Kolkata",
    "iso:country":"IN",
    "name:ceb_x_preferred":[
        "Kanga"
    ],
    "name:deu_x_preferred":[
        "Kanga"
    ],
    "name:fra_x_preferred":[
        "Kanga"
    ],
    "name:ita_x_preferred":[
        "Kanga"
    ],
    "name:nld_x_preferred":[
        "Kanga"
    ],
    "name:rus_x_preferred":[
        "\u041a\u0430\u043d\u0433\u0430"
    ],
    "name:swa_x_preferred":[
        "Kanga"
    ],
    "name:swe_x_preferred":[
        "Kanga"
    ],
    "name:und_x_variant":[
        "K\u0101nga",
        "Darwiy\u0101n"
    ],
    "wof:name":"Kanga",
    "wof:placetype":"locality"
},
  "geometry": {"coordinates":[74.20752,33.46175],"type":"Point"}
}