{
  "type": "Feature",
  "properties": {
    "iso:country":"IN",
    "ks:ks_name":"Baidyapara 2",
    "ks:ks_pop":225,
    "ks:ks_type":"HABITATION",
    "name:eng_x_preferred":[
        "Baidyapara 2"
    ],
    "wof:name":"Baidyapara 2",
    "wof:placetype":"locality",
    "wof:population":225
},
  "geometry": {"coordinates":[91.684318,26.268347],"type":"Point"}
}