{
  "type": "Feature",
  "properties": {
    "iso:country":"IN",
    "ks:ks_name":"Toyantoli",
    "ks:ks_pop":35,
    "ks:ks_type":"HABITATION",
    "name:eng_x_preferred":[
        "Toyantoli"
    ],
    "wof:name":"Toyantoli",
    "wof:placetype":"locality",
    "wof:population":35
},
  "geometry": {"coordinates":[85.266783,23.126792],"type":"Point"}
}