{
  "type": "Feature",
  "properties": {
    "iso:country":"IN",
    "ks:ks_name":"Mathilarithattu",
    "ks:ks_pop":1027,
    "ks:ks_type":"HABITATION",
    "name:eng_x_preferred":[
        "Mathilarithattu"
    ],
    "wof:name":"Mathilarithattu",
    "wof:placetype":"locality",
    "wof:population":1027
},
  "geometry": {"coordinates":[75.568089,12.146077],"type":"Point"}
}