{
  "type": "Feature",
  "properties": {
    "gn:admin1_code":"19.0",
    "gn:admin2_code":"570.0",
    "gn:asciiname":"Hosambala",
    "gn:country_code":"IN",
    "gn:dem":1018,
    "gn:feature_class":"P",
    "gn:feature_code":"PPL",
    "gn:name":"Hosamb\u00e1la",
    "gn:population":0,
    "gn:timezone":"Asia/Kolkata",
    "iso:country":"IN",
    "wof:name":"Hosambala",
    "wof:placetype":"locality"
},
  "geometry": {"coordinates":[75.61488,13.43097],"type":"Point"}
}