{
  "type": "Feature",
  "properties": {
    "gn:admin1_code":"36",
    "gn:admin2_code":"150.0",
    "gn:asciiname":"Sadullahganj",
    "gn:cc2":"IN",
    "gn:country_code":"IN",
    "gn:dem":164,
    "gn:feature_class":"P",
    "gn:feature_code":"PPL",
    "gn:name":"S\u0101dull\u0101hganj",
    "gn:population":0,
    "gn:timezone":"Asia/Kolkata",
    "iso:country":"IN",
    "name:und_x_variant":[
        "Sadulleganj",
        "S\u0101dull\u0101hganj"
    ],
    "wof:name":"Sadullahganj",
    "wof:placetype":"locality"
},
  "geometry": {"coordinates":[79.41667,28.18333],"type":"Point"}
}