{
  "type": "Feature",
  "properties": {
    "iso:country":"IN",
    "ks:ks_alt_nam":"Ezhiyathu padi",
    "ks:ks_name":"Ezhiyathu Padi",
    "ks:ks_pop":56,
    "ks:ks_type":"HABITATION",
    "name:eng_x_preferred":[
        "Ezhiyathu Padi"
    ],
    "wof:name":"Ezhiyathu Padi",
    "wof:placetype":"locality",
    "wof:population":56
},
  "geometry": {"coordinates":[76.84851399999999,9.156849],"type":"Point"}
}