{
  "type": "Feature",
  "properties": {
    "iso:country":"IN",
    "ks:ks_name":"Larha Ka Purwa (khakhapur)",
    "ks:ks_pop":450,
    "ks:ks_type":"HABITATION",
    "name:eng_x_preferred":[
        "Larha Ka Purwa (khakhapur)"
    ],
    "wof:name":"Larha Ka Purwa (khakhapur)",
    "wof:placetype":"locality",
    "wof:population":450
},
  "geometry": {"coordinates":[82.042779,25.768307],"type":"Point"}
}