{
  "type": "Feature",
  "properties": {
    "gn:admin1_code":"36",
    "gn:admin2_code":"195.0",
    "gn:asciiname":"Sagra",
    "gn:country_code":"IN",
    "gn:dem":78,
    "gn:feature_class":"P",
    "gn:feature_code":"PPL",
    "gn:name":"Sagra",
    "gn:population":0,
    "gn:timezone":"Asia/Kolkata",
    "iso:country":"IN",
    "name:ceb_x_preferred":[
        "Sagra"
    ],
    "name:deu_x_preferred":[
        "Sagra"
    ],
    "name:eus_x_preferred":[
        "Sagra"
    ],
    "name:fra_x_preferred":[
        "Sagra"
    ],
    "name:glg_x_preferred":[
        "Sagra"
    ],
    "name:ita_x_preferred":[
        "Sagra"
    ],
    "name:nld_x_preferred":[
        "Sagra"
    ],
    "name:spa_x_preferred":[
        "Sagra"
    ],
    "wof:name":"Sagra",
    "wof:placetype":"locality"
},
  "geometry": {"coordinates":[83.36206,25.59471],"type":"Point"}
}