{
  "type": "Feature",
  "properties": {
    "gn:admin1_code":"28.0",
    "gn:admin2_code":"330.0",
    "gn:asciiname":"Khikhirtola",
    "gn:country_code":"IN",
    "gn:dem":47,
    "gn:feature_class":"P",
    "gn:feature_code":"PPL",
    "gn:name":"Khikhirtola",
    "gn:population":0,
    "gn:timezone":"Asia/Kolkata",
    "iso:country":"IN",
    "wof:name":"Khikhirtola",
    "wof:placetype":"neighbourhood"
},
  "geometry": {"coordinates":[87.94149,25.98651],"type":"Point"}
}