{
  "type": "Feature",
  "properties": {
    "gn:country":"IN",
    "gn:fcode":"PPL",
    "gn:pop":19711,
    "iso:country":"IN",
    "name:bpy_x_preferred":[
        "\u099d\u09bf\u09a8\u099d\u09be\u09a8\u09be"
    ],
    "name:eng_x_preferred":[
        "Jhinjhana"
    ],
    "name:fra_x_preferred":[
        "Jhinjhana"
    ],
    "name:ita_x_preferred":[
        "Jhinjhana"
    ],
    "name:mlg_x_preferred":[
        "Jhinjhana"
    ],
    "name:msa_x_preferred":[
        "Jhinjhana"
    ],
    "name:nan_x_preferred":[
        "Jhinjhana"
    ],
    "name:new_x_preferred":[
        "\u091d\u093f\u0902\u091d\u0928\u093e"
    ],
    "name:nld_x_preferred":[
        "Jhinjhana"
    ],
    "name:pol_x_preferred":[
        "Jhinjhana"
    ],
    "name:por_x_preferred":[
        "Jhinjhana"
    ],
    "name:swe_x_preferred":[
        "Jhinjh\u0101na"
    ],
    "name:unk_x_variant":[
        "Jhinjh\u0101na"
    ],
    "name:urd_x_preferred":[
        "\u062c\u06be\u0646\u062c\u06be\u0627\u0646\u06c1"
    ],
    "name:vie_x_preferred":[
        "Jhinjhana"
    ],
    "name:zho_x_preferred":[
        "\u91d1\u8d3e\u7eb3"
    ],
    "qs:name":"Jhinjhana",
    "qs:name_adm0":"India",
    "qs:name_adm1":"Uttar Pradesh",
    "qs:photos_9r":0,
    "qs:photos_sr":0,
    "qs:placetype":"Town",
    "qs:pop_sr":"6",
    "wd:wordcount":496,
    "wof:name":"Jhinjhana",
    "wof:placetype":"locality",
    "wof:population":19711
},
  "geometry": {"coordinates":[77.22525,29.52177],"type":"Point"}
}