{
  "type": "Feature",
  "properties": {
    "iso:country":"IN",
    "ks:ks_alt_nam":"Kal\u012b\u0101na",
    "ks:ks_name":"Kaliana",
    "ks:ks_type":"VILLAGE",
    "name:eng_x_preferred":[
        "Kaliana"
    ],
    "name:eng_x_variant":[
        "Kal\u012b\u0101na"
    ],
    "wof:name":"Kaliana",
    "wof:placetype":"locality"
},
  "geometry": {"coordinates":[77.649058,29.516011],"type":"Point"}
}