{
  "type": "Feature",
  "properties": {
    "iso:country":"IN",
    "ks:ks_name":"Ranapada",
    "ks:ks_pop":312,
    "ks:ks_type":"HABITATION",
    "name:eng_x_preferred":[
        "Ranapada"
    ],
    "wof:name":"Ranapada",
    "wof:placetype":"locality",
    "wof:population":312
},
  "geometry": {"coordinates":[82.84105700000001,20.110813],"type":"Point"}
}