{
  "type": "Feature",
  "properties": {
    "iso:country":"IN",
    "ks:ks_alt_nam":"karukappilly",
    "ks:ks_name":"Karukappilly",
    "ks:ks_pop":898,
    "ks:ks_type":"HABITATION",
    "name:eng_x_preferred":[
        "Karukappilly"
    ],
    "wof:name":"Karukappilly",
    "wof:placetype":"locality",
    "wof:population":898
},
  "geometry": {"coordinates":[76.812259,9.854276],"type":"Point"}
}