{
  "type": "Feature",
  "properties": {
    "iso:country":"IN",
    "ks:ks_name":"Jharpara Pt I",
    "ks:ks_pop":975,
    "ks:ks_type":"VILLAGE",
    "ks:ks_uagg_main":0,
    "name:eng_x_preferred":[
        "Jharpara Pt I"
    ],
    "wof:name":"Jharpara Pt I",
    "wof:placetype":"neighbourhood",
    "wof:population":975
},
  "geometry": {"coordinates":[90.719723,26.305504],"type":"Point"}
}