{
  "type": "Feature",
  "properties": {
    "iso:country":"IN",
    "ks:ks_name":"Deuli",
    "ks:ks_pop":3286,
    "ks:ks_type":"URBAN",
    "ks:ks_uagg_main":0,
    "name:eng_x_preferred":[
        "Deuli"
    ],
    "wof:name":"Deuli",
    "wof:placetype":"neighbourhood",
    "wof:population":3286
},
  "geometry": {"coordinates":[87.792222,22.204813],"type":"Point"}
}