{
  "type": "Feature",
  "properties": {
    "iso:country":"IN",
    "ks:ks_name":"Gumdi",
    "ks:ks_pop":517,
    "ks:ks_type":"VILLAGE",
    "name:eng_x_preferred":[
        "Gumdi"
    ],
    "wof:name":"Gumdi",
    "wof:placetype":"locality",
    "wof:population":517
},
  "geometry": {"coordinates":[81.988574,19.657558],"type":"Point"}
}