{
  "type": "Feature",
  "properties": {
    "iso:country":"IN",
    "ks:ks_name":"Muttuvalli",
    "ks:ks_pop":72,
    "ks:ks_type":"HABITATION",
    "name:eng_x_preferred":[
        "Muttuvalli"
    ],
    "wof:name":"Muttuvalli",
    "wof:placetype":"locality",
    "wof:population":72
},
  "geometry": {"coordinates":[75.179784,13.520325],"type":"Point"}
}