{
  "type": "Feature",
  "properties": {
    "gn:admin1_code":"34.0",
    "gn:admin2_code":"236.0",
    "gn:asciiname":"Bansi",
    "gn:country_code":"IN",
    "gn:dem":195,
    "gn:feature_class":"P",
    "gn:feature_code":"PPL",
    "gn:name":"B\u0101nsi",
    "gn:population":0,
    "gn:timezone":"Asia/Kolkata",
    "iso:country":"IN",
    "name:bpy_x_preferred":[
        "\u09ac\u09a8\u09b8\u09bf"
    ],
    "name:ceb_x_preferred":[
        "B\u0101nsi"
    ],
    "name:hin_x_preferred":[
        "\u092c\u093e\u0902\u0938\u0940"
    ],
    "name:ita_x_preferred":[
        "Bansi"
    ],
    "name:mlg_x_preferred":[
        "Bansi"
    ],
    "name:msa_x_preferred":[
        "Bansi"
    ],
    "name:nld_x_preferred":[
        "Bansi"
    ],
    "name:pol_x_preferred":[
        "Bansi"
    ],
    "name:por_x_preferred":[
        "Bansi"
    ],
    "name:swe_x_preferred":[
        "B\u0101nsi"
    ],
    "name:urd_x_preferred":[
        "\u0628\u0646\u0633\u06cc"
    ],
    "name:vie_x_preferred":[
        "Bansi"
    ],
    "wof:name":"Bansi",
    "wof:placetype":"locality"
},
  "geometry": {"coordinates":[84.6105,24.42307000000001],"type":"Point"}
}