{
  "type": "Feature",
  "properties": {
    "iso:country":"IN",
    "ks:ks_name":"Borghata",
    "ks:ks_pop":224,
    "ks:ks_type":"VILLAGE",
    "name:eng_x_preferred":[
        "Borghata"
    ],
    "wof:name":"Borghata",
    "wof:placetype":"locality",
    "wof:population":224
},
  "geometry": {"coordinates":[74.949746,22.822524],"type":"Point"}
}