{
  "type": "Feature",
  "properties": {
    "iso:country":"IN",
    "ks:ks_name":"Gaondharwadi",
    "ks:ks_pop":28,
    "ks:ks_type":"HABITATION",
    "name:eng_x_preferred":[
        "Gaondharwadi"
    ],
    "wof:name":"Gaondharwadi",
    "wof:placetype":"locality",
    "wof:population":28
},
  "geometry": {"coordinates":[73.374092,17.545631],"type":"Point"}
}