{
  "type": "Feature",
  "properties": {
    "iso:country":"IN",
    "ks:ks_name":"Tetulkuriapahar",
    "ks:ks_pop":214,
    "ks:ks_type":"VILLAGE",
    "name:eng_x_preferred":[
        "Tetulkuriapahar"
    ],
    "wof:name":"Tetulkuriapahar",
    "wof:placetype":"locality",
    "wof:population":214
},
  "geometry": {"coordinates":[87.66983399999999,24.74418],"type":"Point"}
}