{
  "type": "Feature",
  "properties": {
    "iso:country":"IN",
    "ks:ks_name":"Panchpukhuria",
    "ks:ks_pop":694,
    "ks:ks_type":"VILLAGE",
    "name:eng_x_preferred":[
        "Panchpukhuria"
    ],
    "wof:name":"Panchpukhuria",
    "wof:placetype":"locality",
    "wof:population":694
},
  "geometry": {"coordinates":[87.85297300000001,22.300409],"type":"Point"}
}