{
  "type": "Feature",
  "properties": {
    "iso:country":"IN",
    "ks:ks_name":"Dhakad Para",
    "ks:ks_pop":418,
    "ks:ks_type":"HABITATION",
    "name:eng_x_preferred":[
        "Dhakad Para"
    ],
    "wof:name":"Dhakad Para",
    "wof:placetype":"locality",
    "wof:population":418
},
  "geometry": {"coordinates":[81.702529,19.631908],"type":"Point"}
}