{
  "type": "Feature",
  "properties": {
    "iso:country":"IN",
    "ks:ks_alt_nam":"Kaithakkal Jn east",
    "ks:ks_name":"Kaithakkal Jn East",
    "ks:ks_pop":540,
    "ks:ks_type":"HABITATION",
    "name:eng_x_preferred":[
        "Kaithakkal Jn East"
    ],
    "wof:name":"Kaithakkal Jn East",
    "wof:placetype":"locality",
    "wof:population":540
},
  "geometry": {"coordinates":[76.091793,11.245617],"type":"Point"}
}