{
  "type": "Feature",
  "properties": {
    "iso:country":"IN",
    "ks:ks_name":"Salakhari",
    "ks:ks_pop":886,
    "ks:ks_type":"VILLAGE",
    "name:eng_x_preferred":[
        "Salakhari"
    ],
    "wof:name":"Salakhari",
    "wof:placetype":"locality",
    "wof:population":886
},
  "geometry": {"coordinates":[73.896798,23.367786],"type":"Point"}
}