{
  "type": "Feature",
  "properties": {
    "gn:admin1_code":"16",
    "gn:admin2_code":"524.0",
    "gn:asciiname":"Shignal",
    "gn:country_code":"IN",
    "gn:dem":603,
    "gn:feature_class":"P",
    "gn:feature_code":"PPL",
    "gn:name":"Sh\u012bgn\u0101l",
    "gn:population":0,
    "gn:timezone":"Asia/Kolkata",
    "iso:country":"IN",
    "wof:name":"Shignal",
    "wof:placetype":"neighbourhood"
},
  "geometry": {"coordinates":[76.69664,18.08626],"type":"Point"}
}