{
  "type": "Feature",
  "properties": {
    "iso:country":"IN",
    "ks:ks_alt_nam":"Immadi vasti",
    "ks:ks_name":"Immadi Vasti",
    "ks:ks_pop":150,
    "ks:ks_type":"HABITATION",
    "name:eng_x_preferred":[
        "Immadi Vasti"
    ],
    "wof:name":"Immadi Vasti",
    "wof:placetype":"locality",
    "wof:population":150
},
  "geometry": {"coordinates":[75.520538,16.830489],"type":"Point"}
}