{
  "type": "Feature",
  "properties": {
    "iso:country":"IN",
    "ks:ks_name":"Kulingput",
    "ks:ks_pop":83,
    "ks:ks_type":"HABITATION",
    "name:eng_x_preferred":[
        "Kulingput"
    ],
    "wof:name":"Kulingput",
    "wof:placetype":"locality",
    "wof:population":83
},
  "geometry": {"coordinates":[82.644614,18.38564],"type":"Point"}
}