{
  "type": "Feature",
  "properties": {
    "iso:country":"IN",
    "ks:ks_name":"Jal Bagri",
    "ks:ks_pop":59,
    "ks:ks_type":"VILLAGE",
    "name:eng_x_preferred":[
        "Jal Bagri"
    ],
    "wof:name":"Jal Bagri",
    "wof:placetype":"locality",
    "wof:population":59
},
  "geometry": {"coordinates":[79.769949,29.622812],"type":"Point"}
}