{
  "type": "Feature",
  "properties": {
    "iso:country":"IN",
    "ks:ks_name":"Esarmar",
    "ks:ks_pop":55,
    "ks:ks_type":"HABITATION",
    "name:eng_x_preferred":[
        "Esarmar"
    ],
    "wof:name":"Esarmar",
    "wof:placetype":"locality",
    "wof:population":55
},
  "geometry": {"coordinates":[74.957538,13.34369],"type":"Point"}
}