{
  "type": "Feature",
  "properties": {
    "iso:country":"IN",
    "ks:ks_name":"Bankatiya",
    "ks:ks_pop":1452,
    "ks:ks_type":"VILLAGE",
    "ks:ks_uagg_main":0,
    "name:eng_x_preferred":[
        "Bankatiya"
    ],
    "wof:name":"Bankatiya",
    "wof:placetype":"neighbourhood",
    "wof:population":1452
},
  "geometry": {"coordinates":[83.434046,26.221534],"type":"Point"}
}