{
  "type": "Feature",
  "properties": {
    "gn:admin1_code":"35",
    "gn:admin2_code":"458.0",
    "gn:asciiname":"Chak Pagara",
    "gn:country_code":"IN",
    "gn:dem":485,
    "gn:feature_class":"P",
    "gn:feature_code":"PPL",
    "gn:name":"Chak Pagara",
    "gn:population":0,
    "gn:timezone":"Asia/Kolkata",
    "iso:country":"IN",
    "name:und_x_variant":[
        "Pr\u012btampur"
    ],
    "wof:name":"Chak Pagara",
    "wof:placetype":"locality"
},
  "geometry": {"coordinates":[77.44546,24.64281],"type":"Point"}
}