{
  "type": "Feature",
  "properties": {
    "gn:admin1_code":"2",
    "gn:admin2_code":"544.0",
    "gn:asciiname":"Maripalem",
    "gn:country_code":"IN",
    "gn:dem":913,
    "gn:feature_class":"P",
    "gn:feature_code":"PPL",
    "gn:name":"Maripalem",
    "gn:population":0,
    "gn:timezone":"Asia/Kolkata",
    "iso:country":"IN",
    "wof:name":"Maripalem",
    "wof:placetype":"locality"
},
  "geometry": {"coordinates":[82.76319000000002,18.18232],"type":"Point"}
}