{
  "type": "Feature",
  "properties": {
    "gn:admin1_code":"2",
    "gn:admin2_code":"544.0",
    "gn:asciiname":"Maripalem",
    "gn:country_code":"IN",
    "gn:dem":913,
    "gn:feature_class":"P",
    "gn:feature_code":"PPL",
    "gn:name":"Maripalem",
    "gn:population":0,
    "gn:timezone":"Asia/Kolkata",
    "iso:country":"IN",
    "ks:ks_name":"Marripalem",
    "ks:ks_pop":103,
    "ks:ks_type":"VILLAGE",
    "name:eng_x_preferred":[
        "Marripalem"
    ],
    "name:eng_x_variant":[
        "Maripalem"
    ],
    "wof:name":"Marripalem",
    "wof:placetype":"locality",
    "wof:population":103
},
  "geometry": {"coordinates":[82.763662,18.18189],"type":"Point"}
}