{
  "type": "Feature",
  "properties": {
    "gn:admin1_code":"16.0",
    "gn:admin2_code":"509.0",
    "gn:asciiname":"Sirsi",
    "gn:country_code":"IN",
    "gn:dem":187,
    "gn:feature_class":"P",
    "gn:feature_code":"PPL",
    "gn:name":"Sirsi",
    "gn:population":0,
    "gn:timezone":"Asia/Kolkata",
    "iso:country":"IN",
    "name:ceb_x_preferred":[
        "Sirsi"
    ],
    "name:pol_x_preferred":[
        "Sirsi"
    ],
    "name:swe_x_preferred":[
        "Sirsi"
    ],
    "name:vie_x_preferred":[
        "Sirsi"
    ],
    "wof:name":"Sirsi",
    "wof:placetype":"locality"
},
  "geometry": {"coordinates":[79.39277,19.67969],"type":"Point"}
}