{
  "type": "Feature",
  "properties": {
    "iso:country":"IN",
    "name:rus_x_preferred":[
        "\u041a\u0430\u043b\u044c\u044f\u043d"
    ],
    "name:und_x_variant":[
        "Kaly\u0101n"
    ],
    "qs:name":"Kalyan Dombivli",
    "qs:name_adm0":"India",
    "qs:name_adm1":"Maharashtra",
    "qs:photos":772,
    "qs:photos_1k":156,
    "qs:photos_9k":7,
    "qs:photos_9r":8,
    "qs:photos_all":1671,
    "qs:photos_sr":9,
    "qs:placetype":"Town",
    "qs:pop_sr":"0",
    "wd:wordcount":156,
    "wof:name":"Kalyan Dombivli",
    "wof:placetype":"neighbourhood"
},
  "geometry": {"coordinates":[73.08673,19.218177],"type":"Point"}
}