{
  "type": "Feature",
  "properties": {
    "gn:country":"IN",
    "gn:fcode":"PPL",
    "gn:population":19942,
    "iso:country":"IN",
    "name:und_x_variant":[
        "Charth\u0101wal"
    ],
    "qs:name":"Charth\u0101w\u0101l",
    "qs:photos_9r":0,
    "qs:photos_sr":0,
    "qs:pop_sr":"6",
    "wof:name":"Charth\u0101w\u0101l",
    "wof:placetype":"locality",
    "wof:population":19942
},
  "geometry": {"coordinates":[77.5937,29.54717],"type":"Point"}
}