{
  "type": "Feature",
  "properties": {
    "gn:admin1_code":"12.0",
    "gn:admin2_code":"005",
    "gn:asciiname":"Danni na Pir",
    "gn:country_code":"IN",
    "gn:dem":2033,
    "gn:feature_class":"P",
    "gn:feature_code":"PPL",
    "gn:name":"Danni na P\u012br",
    "gn:population":0,
    "gn:timezone":"Asia/Kolkata",
    "iso:country":"IN",
    "wof:name":"Danni na Pir",
    "wof:placetype":"locality"
},
  "geometry": {"coordinates":[74.13333,33.70278],"type":"Point"}
}