{
  "type": "Feature",
  "properties": {
    "iso:country":"IN",
    "ks:ks_name":"Kilara",
    "ks:ks_pop":309,
    "ks:ks_type":"HABITATION",
    "name:eng_x_preferred":[
        "Kilara"
    ],
    "wof:name":"Kilara",
    "wof:placetype":"locality",
    "wof:population":309
},
  "geometry": {"coordinates":[75.166206,13.036871],"type":"Point"}
}