{
  "type": "Feature",
  "properties": {
    "iso:country":"IN",
    "ks:ks_name":"Bham",
    "ks:ks_pop":550,
    "ks:ks_type":"HABITATION",
    "ks:ks_uagg_main":0,
    "name:eng_x_preferred":[
        "Bham"
    ],
    "wof:name":"Bham",
    "wof:placetype":"neighbourhood",
    "wof:population":550
},
  "geometry": {"coordinates":[73.870525,18.799489],"type":"Point"}
}