{
  "type": "Feature",
  "properties": {
    "iso:country":"IN",
    "ks:ks_name":"Selisunoli",
    "ks:ks_pop":256,
    "ks:ks_type":"VILLAGE",
    "name:eng_x_preferred":[
        "Selisunoli"
    ],
    "wof:name":"Selisunoli",
    "wof:placetype":"locality",
    "wof:population":256
},
  "geometry": {"coordinates":[79.43808,29.708899],"type":"Point"}
}