{
  "type": "Feature",
  "properties": {
    "iso:country":"IN",
    "ks:ks_name":"Amokhar",
    "ks:ks_pop":578,
    "ks:ks_type":"HABITATION",
    "name:eng_x_preferred":[
        "Amokhar"
    ],
    "wof:name":"Amokhar",
    "wof:placetype":"locality",
    "wof:population":578
},
  "geometry": {"coordinates":[84.85593799999999,24.848977],"type":"Point"}
}