{
  "type": "Feature",
  "properties": {
    "iso:country":"IN",
    "ks:ks_name":"Kondi",
    "ks:ks_pop":276,
    "ks:ks_type":"VILLAGE",
    "name:eng_x_preferred":[
        "Kondi"
    ],
    "wof:name":"Kondi",
    "wof:placetype":"locality",
    "wof:population":276
},
  "geometry": {"coordinates":[78.800623,19.637422],"type":"Point"}
}