{
  "type": "Feature",
  "properties": {
    "iso:country":"IN",
    "ks:ks_name":"Dartoli",
    "ks:ks_pop":87,
    "ks:ks_type":"HABITATION",
    "name:eng_x_preferred":[
        "Dartoli"
    ],
    "wof:name":"Dartoli",
    "wof:placetype":"locality",
    "wof:population":87
},
  "geometry": {"coordinates":[85.33667,23.082264],"type":"Point"}
}