{
  "type": "Feature",
  "properties": {
    "gn:admin1_code":"18.0",
    "gn:admin2_code":"293.0",
    "gn:asciiname":"Nidanpur",
    "gn:country_code":"IN",
    "gn:dem":40,
    "gn:feature_class":"P",
    "gn:feature_code":"PPL",
    "gn:name":"Nidanpur",
    "gn:population":0,
    "gn:timezone":"Asia/Kolkata",
    "iso:country":"IN",
    "wof:name":"Nidanpur",
    "wof:placetype":"locality"
},
  "geometry": {"coordinates":[90.11718999999999,25.93251],"type":"Point"}
}