{
  "type": "Feature",
  "properties": {
    "iso:country":"IN",
    "ks:ks_alt_nam":"Bhagw\u0101npur",
    "ks:ks_name":"Bhagwanpur",
    "ks:ks_pop":0,
    "ks:ks_type":"VILLAGE",
    "name:eng_x_preferred":[
        "Bhagwanpur"
    ],
    "name:eng_x_variant":[
        "Bhagw\u0101npur"
    ],
    "wof:name":"Bhagwanpur",
    "wof:placetype":"locality",
    "wof:population":0
},
  "geometry": {"coordinates":[84.20272300000001,23.150629],"type":"Point"}
}