{
  "type": "Feature",
  "properties": {
    "gn:admin1_code":"35.0",
    "gn:admin2_code":"427.0",
    "gn:asciiname":"Harrai",
    "gn:country_code":"IN",
    "gn:dem":417,
    "gn:feature_class":"P",
    "gn:feature_code":"PPL",
    "gn:name":"Harrai",
    "gn:population":0,
    "gn:timezone":"Asia/Kolkata",
    "iso:country":"IN",
    "name:ben_x_preferred":[
        "\u09b9\u09be\u09b0\u09b0\u09be\u0987"
    ],
    "name:bpy_x_preferred":[
        "\u09b9\u09be\u09b0\u09b0\u09be\u0987"
    ],
    "name:ceb_x_preferred":[
        "Harrai"
    ],
    "name:ita_x_preferred":[
        "Harrai"
    ],
    "name:msa_x_preferred":[
        "Harrai"
    ],
    "name:new_x_preferred":[
        "\u0939\u0930\u094d\u0930\u093e\u0908"
    ],
    "name:nld_x_preferred":[
        "Harrai"
    ],
    "name:por_x_preferred":[
        "Harrai"
    ],
    "name:spa_x_preferred":[
        "Harrai"
    ],
    "name:swe_x_preferred":[
        "Harrai"
    ],
    "name:vie_x_preferred":[
        "Harrai"
    ],
    "name:zho_x_preferred":[
        "\u54c8\u5c14\u8d56"
    ],
    "wof:name":"Harrai",
    "wof:placetype":"locality"
},
  "geometry": {"coordinates":[78.9931,23.2359],"type":"Point"}
}