{
  "type": "Feature",
  "properties": {
    "iso:country":"IN",
    "ks:ks_alt_nam":"KHUDIWAN",
    "ks:ks_name":"Khudiwan",
    "ks:ks_pop":455,
    "ks:ks_type":"HABITATION",
    "name:eng_x_preferred":[
        "Khudiwan"
    ],
    "wof:name":"Khudiwan",
    "wof:placetype":"locality",
    "wof:population":455
},
  "geometry": {"coordinates":[86.367689,25.210607],"type":"Point"}
}