{
  "type": "Feature",
  "properties": {
    "iso:country":"IN",
    "ks:ks_name":"Rong Eta Rongpi",
    "ks:ks_pop":183,
    "ks:ks_type":"HABITATION",
    "ks:ks_uagg_main":0,
    "name:eng_x_preferred":[
        "Rong Eta Rongpi"
    ],
    "wof:name":"Rong Eta Rongpi",
    "wof:placetype":"neighbourhood",
    "wof:population":183
},
  "geometry": {"coordinates":[93.107615,26.238368],"type":"Point"}
}