{
  "type": "Feature",
  "properties": {
    "iso:country":"IN",
    "ks:ks_name":"Chandrain",
    "ks:ks_pop":2921,
    "ks:ks_type":"VILLAGE",
    "ks:ks_uagg_main":0,
    "name:eng_x_preferred":[
        "Chandrain"
    ],
    "wof:name":"Chandrain",
    "wof:placetype":"neighbourhood",
    "wof:population":2921
},
  "geometry": {"coordinates":[86.457262,25.947267],"type":"Point"}
}