{
  "type": "Feature",
  "properties": {
    "gn:admin1_code":"24.0",
    "gn:admin2_code":"108.0",
    "gn:asciiname":"Dungri",
    "gn:country_code":"IN",
    "gn:dem":274,
    "gn:feature_class":"P",
    "gn:feature_code":"PPL",
    "gn:name":"D\u016bngri",
    "gn:population":0,
    "gn:timezone":"Asia/Kolkata",
    "iso:country":"IN",
    "name:guj_x_preferred":[
        "\u0aa1\u0ac1\u0a82\u0a97\u0ab0\u0ac0"
    ],
    "name:tam_x_preferred":[
        "\u0b9f\u0bc1\u0b99\u0bcd\u0b95\u0bbf\u0bb0\u0bbf"
    ],
    "wof:name":"Dungri",
    "wof:placetype":"locality"
},
  "geometry": {"coordinates":[76.1478,26.32393],"type":"Point"}
}