{
  "type": "Feature",
  "properties": {
    "gn:admin1_code":"24.0",
    "gn:admin2_code":"128.0",
    "gn:asciiname":"Mandola",
    "gn:country_code":"IN",
    "gn:dem":355,
    "gn:feature_class":"P",
    "gn:feature_code":"PPL",
    "gn:name":"Mandola",
    "gn:population":0,
    "gn:timezone":"Asia/Kolkata",
    "iso:country":"IN",
    "name:cat_x_preferred":[
        "Mandola"
    ],
    "name:ces_x_preferred":[
        "Mandola"
    ],
    "name:dan_x_preferred":[
        "Mandola"
    ],
    "name:deu_x_preferred":[
        "Mandola"
    ],
    "name:epo_x_preferred":[
        "Mandolo"
    ],
    "name:heb_x_preferred":[
        "\u05de\u05e0\u05d3\u05d5\u05dc\u05d4"
    ],
    "name:ita_x_preferred":[
        "Mandola"
    ],
    "name:jpn_x_preferred":[
        "\u30de\u30f3\u30c9\u30e9"
    ],
    "name:nld_x_preferred":[
        "Mandola"
    ],
    "name:nno_x_preferred":[
        "Mandola"
    ],
    "name:nor_x_preferred":[
        "Mandola"
    ],
    "name:oci_x_preferred":[
        "Mand\u00f2la"
    ],
    "name:pol_x_preferred":[
        "Mandola"
    ],
    "name:por_x_preferred":[
        "Mandola"
    ],
    "name:rus_x_preferred":[
        "\u041c\u0430\u043d\u0434\u043e\u043b\u0430"
    ],
    "name:spa_x_preferred":[
        "Mandola"
    ],
    "name:swe_x_preferred":[
        "Mandola"
    ],
    "name:ukr_x_preferred":[
        "\u041c\u0430\u043d\u0434\u043e\u043b\u0430"
    ],
    "wof:name":"Mandola",
    "wof:placetype":"locality"
},
  "geometry": {"coordinates":[76.78152,24.54636],"type":"Point"}
}