{
  "type": "Feature",
  "properties": {
    "iso:country":"IN",
    "ks:ks_name":"Shustri Pada",
    "ks:ks_pop":398,
    "ks:ks_type":"HABITATION",
    "name:eng_x_preferred":[
        "Shustri Pada"
    ],
    "wof:name":"Shustri Pada",
    "wof:placetype":"locality",
    "wof:population":398
},
  "geometry": {"coordinates":[73.282,20.402389],"type":"Point"}
}