{
  "type": "Feature",
  "properties": {
    "gn:admin1_code":"2.0",
    "gn:admin2_code":"544.0",
    "gn:asciiname":"Kumdiputtu",
    "gn:country_code":"IN",
    "gn:dem":921,
    "gn:feature_class":"P",
    "gn:feature_code":"PPL",
    "gn:name":"Kumdiputtu",
    "gn:population":0,
    "gn:timezone":"Asia/Kolkata",
    "iso:country":"IN",
    "wof:name":"Kumdiputtu",
    "wof:placetype":"locality"
},
  "geometry": {"coordinates":[82.49319,18.36447],"type":"Point"}
}