{
  "type": "Feature",
  "properties": {
    "gn:admin1_code":"35",
    "gn:admin2_code":"455.0",
    "gn:asciiname":"Sondhani",
    "gn:country_code":"IN",
    "gn:dem":598,
    "gn:feature_class":"P",
    "gn:feature_code":"PPL",
    "gn:name":"Sondhani",
    "gn:population":0,
    "gn:timezone":"Asia/Kolkata",
    "iso:country":"IN",
    "ks:ks_name":"Sondhni",
    "ks:ks_pop":455,
    "ks:ks_type":"VILLAGE",
    "name:eng_x_preferred":[
        "Sondhni"
    ],
    "name:eng_x_variant":[
        "Sondhani"
    ],
    "wof:name":"Sondhni",
    "wof:placetype":"locality",
    "wof:population":455
},
  "geometry": {"coordinates":[79.14368,22.615869],"type":"Point"}
}