{
  "type": "Feature",
  "properties": {
    "iso:country":"IN",
    "ks:ks_name":"Atthabatia",
    "ks:ks_pop":478,
    "ks:ks_type":"VILLAGE",
    "ks:ks_uagg_main":0,
    "name:eng_x_preferred":[
        "Atthabatia"
    ],
    "wof:name":"Atthabatia",
    "wof:placetype":"neighbourhood",
    "wof:population":478
},
  "geometry": {"coordinates":[87.293211,21.654948],"type":"Point"}
}