{
  "type": "Feature",
  "properties": {
    "iso:country":"IN",
    "ks:ks_name":"Chowkham",
    "ks:ks_pop":868,
    "ks:ks_type":"VILLAGE",
    "ks:ks_uagg_main":0,
    "name:eng_x_preferred":[
        "Chowkham"
    ],
    "wof:name":"Chowkham",
    "wof:placetype":"neighbourhood",
    "wof:population":868
},
  "geometry": {"coordinates":[94.57826900000001,27.491098],"type":"Point"}
}