{
  "type": "Feature",
  "properties": {
    "iso:country":"IN",
    "ks:ks_name":"Lukhurakhon",
    "ks:ks_pop":2252,
    "ks:ks_type":"VILLAGE",
    "name:eng_x_preferred":[
        "Lukhurakhon"
    ],
    "wof:name":"Lukhurakhon",
    "wof:placetype":"locality",
    "wof:population":2252
},
  "geometry": {"coordinates":[95.12691700000001,27.034121],"type":"Point"}
}