{
  "type": "Feature",
  "properties": {
    "iso:country":"IN",
    "ks:ks_name":"Girdharipur",
    "ks:ks_pop":544,
    "ks:ks_type":"VILLAGE",
    "name:eng_x_preferred":[
        "Girdharipur"
    ],
    "wof:name":"Girdharipur",
    "wof:placetype":"locality",
    "wof:population":544
},
  "geometry": {"coordinates":[85.577939,22.010225],"type":"Point"}
}