{
  "type": "Feature",
  "properties": {
    "gn:admin1_code":"12.0",
    "gn:asciiname":"Bangas",
    "gn:country_code":"IN",
    "gn:dem":2716,
    "gn:feature_class":"P",
    "gn:feature_code":"PPL",
    "gn:name":"Bangas",
    "gn:population":0,
    "gn:timezone":"Asia/Kolkata",
    "iso:country":"IN",
    "wof:name":"Bangas",
    "wof:placetype":"locality"
},
  "geometry": {"coordinates":[74.01616,34.63434],"type":"Point"}
}