{
  "type": "Feature",
  "properties": {
    "gn:admin1_code":"36.0",
    "gn:admin2_code":"154.0",
    "gn:asciiname":"Kalupur",
    "gn:country_code":"IN",
    "gn:dem":143,
    "gn:feature_class":"P",
    "gn:feature_code":"PPL",
    "gn:name":"K\u0101lupur",
    "gn:population":0,
    "gn:timezone":"Asia/Kolkata",
    "iso:country":"IN",
    "ks:ks_name":"Kalu Pur",
    "ks:ks_pop":225,
    "ks:ks_type":"HABITATION",
    "ks:ks_uagg_main":0,
    "name:ara_x_preferred":[
        "\u0643\u0627\u0644\u0648\u0628\u0648\u0631"
    ],
    "name:ben_bn_x_preferred":[
        "\u0995\u09be\u09b2\u09c1\u09aa\u09c1\u09b0"
    ],
    "name:ben_in_x_preferred":[
        "\u0995\u09be\u09b2\u09c1\u09aa\u09c1\u09b0"
    ],
    "name:eng_x_preferred":[
        "Kalu Pur"
    ],
    "name:guj_x_preferred":[
        "\u0a95\u0abe\u0ab2\u0ac1\u0aaa\u0ac1\u0ab0"
    ],
    "name:hin_x_preferred":[
        "\u0915\u093e\u0932\u0942\u092a\u0941\u0930"
    ],
    "name:kan_x_preferred":[
        "\u0c95\u0cb2\u0cc1\u0caa\u0cc1\u0cb0\u0ccd"
    ],
    "name:mal_x_preferred":[
        "\u0d15\u0d32\u0d41\u0d2a\u0d42\u0d7c"
    ],
    "name:mar_x_preferred":[
        "\u0915\u093e\u0933\u0942\u092a\u0942\u0930"
    ],
    "name:pan_x_preferred":[
        "\u0a15\u0a3e\u0a32\u0a42\u0a2a\u0a41\u0a30"
    ],
    "name:tam_x_preferred":[
        "\u0b95\u0bbe\u0bb2\u0bc1\u0baa\u0bc2\u0bb0\u0bcd"
    ],
    "name:tel_x_preferred":[
        "\u0c15\u0c3e\u0c32\u0c41\u0c2a\u0c42\u0c30\u0c4d"
    ],
    "name:urd_x_preferred":[
        "\u06a9\u0627\u0644\u0648 \u067e\u0648\u0631"
    ],
    "wof:name":"Kalu Pur",
    "wof:placetype":"neighbourhood",
    "wof:population":225
},
  "geometry": {"coordinates":[80.68297800000001,27.475187],"type":"Point"}
}