{
  "type": "Feature",
  "properties": {
    "iso:country":"IN",
    "ks:ks_alt_nam":"MusalKanda",
    "ks:ks_name":"Musalkanda",
    "ks:ks_pop":45,
    "ks:ks_type":"HABITATION",
    "name:eng_x_preferred":[
        "Musalkanda"
    ],
    "wof:name":"Musalkanda",
    "wof:placetype":"locality",
    "wof:population":45
},
  "geometry": {"coordinates":[79.271985,29.807178],"type":"Point"}
}