{
  "type": "Feature",
  "properties": {
    "iso:country":"IN",
    "ks:ks_name":"Manthnagnath",
    "ks:ks_pop":398,
    "ks:ks_type":"HABITATION",
    "name:eng_x_preferred":[
        "Manthnagnath"
    ],
    "wof:name":"Manthnagnath",
    "wof:placetype":"locality",
    "wof:population":398
},
  "geometry": {"coordinates":[84.436903,25.851204],"type":"Point"}
}