{
  "type": "Feature",
  "properties": {
    "gn:admin1_code":"36.0",
    "gn:admin2_code":"169.0",
    "gn:asciiname":"Didwara",
    "gn:country_code":"IN",
    "gn:dem":189,
    "gn:feature_class":"P",
    "gn:feature_code":"PPL",
    "gn:name":"Didw\u0101ra",
    "gn:population":0,
    "gn:timezone":"Asia/Kolkata",
    "iso:country":"IN",
    "wof:name":"Didwara",
    "wof:placetype":"locality"
},
  "geometry": {"coordinates":[79.44969,25.37909],"type":"Point"}
}