{
  "type": "Feature",
  "properties": {
    "iso:country":"IN",
    "ks:ks_name":"Bsapur",
    "ks:ks_pop":113,
    "ks:ks_type":"HABITATION",
    "name:eng_x_preferred":[
        "Bsapur"
    ],
    "wof:name":"Bsapur",
    "wof:placetype":"locality",
    "wof:population":113
},
  "geometry": {"coordinates":[74.537885,15.069397],"type":"Point"}
}