{
  "type": "Feature",
  "properties": {
    "iso:country":"IN",
    "ks:ks_name":"Dhuma",
    "ks:ks_pop":330,
    "ks:ks_type":"HABITATION",
    "name:eng_x_preferred":[
        "Dhuma"
    ],
    "wof:name":"Dhuma",
    "wof:placetype":"locality",
    "wof:population":330
},
  "geometry": {"coordinates":[83.287464,24.054729],"type":"Point"}
}