{
  "type": "Feature",
  "properties": {
    "gn:admin1_code":"19.0",
    "gn:admin2_code":"577.0",
    "gn:asciiname":"Mante Koppa",
    "gn:country_code":"IN",
    "gn:dem":849,
    "gn:feature_class":"P",
    "gn:feature_code":"PPL",
    "gn:name":"Mante Koppa",
    "gn:population":0,
    "gn:timezone":"Asia/Kolkata",
    "iso:country":"IN",
    "wof:name":"Mante Koppa",
    "wof:placetype":"neighbourhood"
},
  "geometry": {"coordinates":[75.96854,12.49845],"type":"Point"}
}