{
  "type": "Feature",
  "properties": {
    "iso:country":"IN",
    "ks:ks_alt_nam":"RAJPUT TOLA",
    "ks:ks_name":"Rajput Tola",
    "ks:ks_pop":900,
    "ks:ks_type":"HABITATION",
    "ks:ks_uagg_main":0,
    "name:eng_x_preferred":[
        "Rajput Tola"
    ],
    "wof:name":"Rajput Tola",
    "wof:placetype":"neighbourhood",
    "wof:population":900
},
  "geometry": {"coordinates":[84.66854600000001,26.319722],"type":"Point"}
}