{
  "type": "Feature",
  "properties": {
    "iso:country":"IN",
    "ks:ks_name":"Batabari",
    "ks:ks_pop":309,
    "ks:ks_type":"HABITATION",
    "name:eng_x_preferred":[
        "Batabari"
    ],
    "wof:name":"Batabari",
    "wof:placetype":"locality",
    "wof:population":309
},
  "geometry": {"coordinates":[91.43597800000001,26.623192],"type":"Point"}
}