{
  "type": "Feature",
  "properties": {
    "iso:country":"IN",
    "ks:ks_name":"Naitamara",
    "ks:ks_pop":1010,
    "ks:ks_type":"VILLAGE",
    "ks:ks_uagg_main":0,
    "name:eng_x_preferred":[
        "Naitamara"
    ],
    "wof:name":"Naitamara",
    "wof:placetype":"neighbourhood",
    "wof:population":1010
},
  "geometry": {"coordinates":[90.41375499999999,26.437626],"type":"Point"}
}