{
  "type": "Feature",
  "properties": {
    "iso:country":"IN",
    "ks:ks_name":"Orejal",
    "ks:ks_pop":11,
    "ks:ks_type":"HABITATION",
    "name:eng_x_preferred":[
        "Orejal"
    ],
    "wof:name":"Orejal",
    "wof:placetype":"locality",
    "wof:population":11
},
  "geometry": {"coordinates":[75.451724,12.812553],"type":"Point"}
}