{
  "type": "Feature",
  "properties": {
    "iso:country":"IN",
    "ks:ks_name":"Shunia",
    "ks:ks_pop":839,
    "ks:ks_type":"VILLAGE",
    "ks:ks_uagg_main":0,
    "name:eng_x_preferred":[
        "Shunia"
    ],
    "wof:name":"Shunia",
    "wof:placetype":"neighbourhood",
    "wof:population":839
},
  "geometry": {"coordinates":[87.786535,23.122443],"type":"Point"}
}