{
  "type": "Feature",
  "properties": {
    "iso:country":"IN",
    "ks:ks_name":"Vavol",
    "ks:ks_pop":12628,
    "ks:ks_type":"VILLAGE",
    "ks:ks_uagg_main":0,
    "name:eng_x_preferred":[
        "Vavol"
    ],
    "wof:name":"Vavol",
    "wof:placetype":"neighbourhood",
    "wof:population":12628
},
  "geometry": {"coordinates":[72.62136099999999,23.224972],"type":"Point"}
}