{
  "type": "Feature",
  "properties": {
    "iso:country":"IN",
    "ks:ks_name":"Pasaripada",
    "ks:ks_pop":178,
    "ks:ks_type":"HABITATION",
    "name:eng_x_preferred":[
        "Pasaripada"
    ],
    "wof:name":"Pasaripada",
    "wof:placetype":"locality",
    "wof:population":178
},
  "geometry": {"coordinates":[73.026066,20.075109],"type":"Point"}
}