{
  "type": "Feature",
  "properties": {
    "iso:country":"IN",
    "ks:ks_name":"Vitmalwadi",
    "ks:ks_pop":19,
    "ks:ks_type":"HABITATION",
    "name:eng_x_preferred":[
        "Vitmalwadi"
    ],
    "wof:name":"Vitmalwadi",
    "wof:placetype":"locality",
    "wof:population":19
},
  "geometry": {"coordinates":[73.32729399999999,17.634442],"type":"Point"}
}