{
  "type": "Feature",
  "properties": {
    "gn:admin1_code":"37",
    "gn:admin2_code":"408.0",
    "gn:asciiname":"Murargota",
    "gn:country_code":"IN",
    "gn:dem":423,
    "gn:feature_class":"P",
    "gn:feature_code":"PPL",
    "gn:name":"Mur\u0101rgota",
    "gn:population":0,
    "gn:timezone":"Asia/Kolkata",
    "iso:country":"IN",
    "ks:ks_alt_nam":"Mur\u0101rgota",
    "ks:ks_name":"Murargota",
    "ks:ks_pop":260,
    "ks:ks_type":"VILLAGE",
    "name:eng_x_preferred":[
        "Murargota"
    ],
    "name:eng_x_variant":[
        "Mur\u0101rgota"
    ],
    "wof:name":"Murargota",
    "wof:placetype":"locality",
    "wof:population":260
},
  "geometry": {"coordinates":[80.935484,20.501849],"type":"Point"}
}