{
  "type": "Feature",
  "properties": {
    "gn:admin1_code":"35.0",
    "gn:admin2_code":"418.0",
    "gn:asciiname":"Mahu",
    "gn:country_code":"IN",
    "gn:dem":241,
    "gn:feature_class":"P",
    "gn:feature_code":"PPL",
    "gn:name":"Mahu",
    "gn:population":0,
    "gn:timezone":"Asia/Kolkata",
    "iso:country":"IN",
    "name:ceb_x_preferred":[
        "Mahu"
    ],
    "name:deu_x_preferred":[
        "Mahu"
    ],
    "name:rus_x_preferred":[
        "\u041c\u0430\u0445\u0443"
    ],
    "name:spa_x_preferred":[
        "Mahu"
    ],
    "name:swe_x_preferred":[
        "Mahu"
    ],
    "wof:name":"Mahu",
    "wof:placetype":"locality"
},
  "geometry": {"coordinates":[76.69954,25.61666],"type":"Point"}
}