{
  "type": "Feature",
  "properties": {
    "gn:country":"IN",
    "gn:fcode":"PPL",
    "gn:pop":112141,
    "iso:country":"IN",
    "name:bho_x_preferred":[
        "\u091a\u093e\u0938"
    ],
    "name:bpy_x_preferred":[
        "\u099a\u09be\u09b8"
    ],
    "name:ceb_x_preferred":[
        "Ch\u0101s"
    ],
    "name:deu_x_preferred":[
        "Chas"
    ],
    "name:eng_x_preferred":[
        "Chas"
    ],
    "name:fra_x_preferred":[
        "Chas"
    ],
    "name:ita_x_preferred":[
        "Chas"
    ],
    "name:msa_x_preferred":[
        "Chas"
    ],
    "name:new_x_preferred":[
        "\u091a\u0938"
    ],
    "name:nld_x_preferred":[
        "Chas"
    ],
    "name:rus_x_preferred":[
        "\u0427\u0430\u0441"
    ],
    "name:spa_x_preferred":[
        "Chas"
    ],
    "name:swe_x_preferred":[
        "Chas"
    ],
    "name:unk_x_variant":[
        "Ch\u0101s"
    ],
    "name:vie_x_preferred":[
        "Chas"
    ],
    "name:zho_x_preferred":[
        "\u6070\u65af"
    ],
    "qs:name":"Chas",
    "qs:name_adm0":"India",
    "qs:name_adm1":"Jharkhand",
    "qs:photos_9k":1,
    "qs:photos_9r":1,
    "qs:photos_all":15,
    "qs:photos_sr":0,
    "qs:placetype":"Town",
    "qs:pop_sr":"9",
    "wd:wordcount":553,
    "wof:name":"Chas",
    "wof:placetype":"locality",
    "wof:population":112141
},
  "geometry": {"coordinates":[86.16712,23.63556],"type":"Point"}
}