{
  "type": "Feature",
  "properties": {
    "iso:country":"IN",
    "ks:ks_alt_nam":"Rowarpara N.C.",
    "ks:ks_name":"Rowarpara N.c.",
    "ks:ks_pop":113,
    "ks:ks_type":"HABITATION",
    "name:eng_x_preferred":[
        "Rowarpara N.c."
    ],
    "wof:name":"Rowarpara N.c.",
    "wof:placetype":"locality",
    "wof:population":113
},
  "geometry": {"coordinates":[90.139921,26.028778],"type":"Point"}
}