{
  "type": "Feature",
  "properties": {
    "iso:country":"IN",
    "ks:ks_name":"Lokhandepada",
    "ks:ks_pop":98,
    "ks:ks_type":"HABITATION",
    "name:eng_x_preferred":[
        "Lokhandepada"
    ],
    "wof:name":"Lokhandepada",
    "wof:placetype":"locality",
    "wof:population":98
},
  "geometry": {"coordinates":[73.175319,19.685201],"type":"Point"}
}