{
  "type": "Feature",
  "properties": {
    "iso:country":"IN",
    "ks:ks_name":"Kacheripada",
    "ks:ks_pop":1602,
    "ks:ks_type":"VILLAGE",
    "name:eng_x_preferred":[
        "Kacheripada"
    ],
    "wof:name":"Kacheripada",
    "wof:placetype":"locality",
    "wof:population":1602
},
  "geometry": {"coordinates":[86.39348699999999,20.471171],"type":"Point"}
}