{
  "type": "Feature",
  "properties": {
    "iso:country":"IN",
    "ks:ks_alt_nam":"Dimo Paham NC",
    "ks:ks_name":"Dimo Paham Nc",
    "ks:ks_pop":200,
    "ks:ks_type":"HABITATION",
    "name:eng_x_preferred":[
        "Dimo Paham Nc"
    ],
    "wof:name":"Dimo Paham Nc",
    "wof:placetype":"locality",
    "wof:population":200
},
  "geometry": {"coordinates":[91.71222299999999,25.983177],"type":"Point"}
}