{
  "type": "Feature",
  "properties": {
    "iso:country":"IN",
    "ks:ks_name":"Mangal Para",
    "ks:ks_pop":42,
    "ks:ks_type":"HABITATION",
    "name:eng_x_preferred":[
        "Mangal Para"
    ],
    "wof:name":"Mangal Para",
    "wof:placetype":"locality",
    "wof:population":42
},
  "geometry": {"coordinates":[91.426807,24.091785],"type":"Point"}
}