{
  "type": "Feature",
  "properties": {
    "iso:country":"IN",
    "ks:ks_name":"Kot Kinda",
    "ks:ks_pop":93,
    "ks:ks_type":"HABITATION",
    "name:eng_x_preferred":[
        "Kot Kinda"
    ],
    "wof:name":"Kot Kinda",
    "wof:placetype":"locality",
    "wof:population":93
},
  "geometry": {"coordinates":[78.47538400000001,29.914052],"type":"Point"}
}