{
  "type": "Feature",
  "properties": {
    "iso:country":"IN",
    "ks:ks_name":"Amilia",
    "ks:ks_pop":81,
    "ks:ks_type":"VILLAGE",
    "name:eng_x_preferred":[
        "Amilia"
    ],
    "wof:name":"Amilia",
    "wof:placetype":"locality",
    "wof:population":81
},
  "geometry": {"coordinates":[82.666875,24.742059],"type":"Point"}
}