{
  "type": "Feature",
  "properties": {
    "iso:country":"IN",
    "ks:ks_alt_nam":"gaothan",
    "ks:ks_name":"Gaothan",
    "ks:ks_pop":130,
    "ks:ks_type":"HABITATION",
    "name:eng_x_preferred":[
        "Gaothan"
    ],
    "wof:name":"Gaothan",
    "wof:placetype":"locality",
    "wof:population":130
},
  "geometry": {"coordinates":[73.68338300000001,17.5416],"type":"Point"}
}