{
  "type": "Feature",
  "properties": {
    "iso:country":"IN",
    "ks:ks_name":"Kishanpura",
    "ks:ks_pop":864,
    "ks:ks_type":"HABITATION",
    "name:eng_x_preferred":[
        "Kishanpura"
    ],
    "wof:name":"Kishanpura",
    "wof:placetype":"locality",
    "wof:population":864
},
  "geometry": {"coordinates":[72.184178,26.432253],"type":"Point"}
}