{
  "type": "Feature",
  "properties": {
    "iso:country":"IN",
    "ks:ks_name":"Hukratte",
    "ks:ks_pop":592,
    "ks:ks_type":"HABITATION",
    "name:eng_x_preferred":[
        "Hukratte"
    ],
    "wof:name":"Hukratte",
    "wof:placetype":"locality",
    "wof:population":592
},
  "geometry": {"coordinates":[75.107866,13.191091],"type":"Point"}
}