{
  "type": "Feature",
  "properties": {
    "iso:country":"IN",
    "ks:ks_name":"Shanthipalke",
    "ks:ks_pop":300,
    "ks:ks_type":"HABITATION",
    "name:eng_x_preferred":[
        "Shanthipalke"
    ],
    "wof:name":"Shanthipalke",
    "wof:placetype":"locality",
    "wof:population":300
},
  "geometry": {"coordinates":[74.85308499999999,13.089176],"type":"Point"}
}