{
  "type": "Feature",
  "properties": {
    "iso:country":"IN",
    "ks:ks_name":"Radhamohanpur",
    "ks:ks_pop":554,
    "ks:ks_type":"VILLAGE",
    "name:eng_x_preferred":[
        "Radhamohanpur"
    ],
    "wof:name":"Radhamohanpur",
    "wof:placetype":"locality",
    "wof:population":554
},
  "geometry": {"coordinates":[87.07496399999999,23.014221],"type":"Point"}
}