{
  "type": "Feature",
  "properties": {
    "iso:country":"IN",
    "ks:ks_name":"Madhyapara",
    "ks:ks_pop":1011,
    "ks:ks_type":"HABITATION",
    "ks:ks_uagg_main":0,
    "name:eng_x_preferred":[
        "Madhyapara"
    ],
    "wof:name":"Madhyapara",
    "wof:placetype":"locality",
    "wof:population":1011
},
  "geometry": {"coordinates":[88.14758999999999,22.760241],"type":"Point"}
}