{
  "type": "Feature",
  "properties": {
    "iso:country":"IN",
    "ks:ks_name":"Arunachalapuram",
    "ks:ks_pop":90,
    "ks:ks_type":"HABITATION",
    "ks:ks_uagg_main":0,
    "name:eng_x_preferred":[
        "Arunachalapuram"
    ],
    "wof:name":"Arunachalapuram",
    "wof:placetype":"neighbourhood",
    "wof:population":90
},
  "geometry": {"coordinates":[77.404596,8.845351],"type":"Point"}
}