{
  "type": "Feature",
  "properties": {
    "iso:country":"IN",
    "ks:ks_name":"Mundukodu",
    "ks:ks_pop":84,
    "ks:ks_type":"HABITATION",
    "name:eng_x_preferred":[
        "Mundukodu"
    ],
    "wof:name":"Mundukodu",
    "wof:placetype":"locality",
    "wof:population":84
},
  "geometry": {"coordinates":[74.963347,13.716959],"type":"Point"}
}