{
  "type": "Feature",
  "properties": {
    "gn:admin1_code":"23",
    "gn:admin2_code":"39.0",
    "gn:asciiname":"Rangowana",
    "gn:country_code":"IN",
    "gn:dem":255,
    "gn:feature_class":"P",
    "gn:feature_code":"PPL",
    "gn:name":"Rangow\u0101na",
    "gn:population":0,
    "gn:timezone":"Asia/Kolkata",
    "iso:country":"IN",
    "wof:name":"Rangowana",
    "wof:placetype":"locality"
},
  "geometry": {"coordinates":[76.01744000000002,31.05967],"type":"Point"}
}