{
  "type": "Feature",
  "properties": {
    "gn:admin1_code":"39",
    "gn:admin2_code":"61.0",
    "gn:asciiname":"Kathur",
    "gn:country_code":"IN",
    "gn:dem":913,
    "gn:feature_class":"P",
    "gn:feature_code":"PPL",
    "gn:name":"Kath\u016br",
    "gn:population":0,
    "gn:timezone":"Asia/Kolkata",
    "iso:country":"IN",
    "wof:name":"Kathur",
    "wof:placetype":"locality"
},
  "geometry": {"coordinates":[78.85894999999999,29.85236],"type":"Point"}
}