{
  "type": "Feature",
  "properties": {
    "iso:country":"IN",
    "ks:ks_name":"Paniyones",
    "ks:ks_pop":130,
    "ks:ks_type":"HABITATION",
    "name:eng_x_preferred":[
        "Paniyones"
    ],
    "wof:name":"Paniyones",
    "wof:placetype":"locality",
    "wof:population":130
},
  "geometry": {"coordinates":[69.927306,21.850333],"type":"Point"}
}