{
  "type": "Feature",
  "properties": {
    "iso:country":"IN",
    "ks:ks_alt_nam":"33.846 RD",
    "ks:ks_name":"33.846 Rd",
    "ks:ks_pop":62,
    "ks:ks_type":"HABITATION",
    "name:eng_x_preferred":[
        "33.846 Rd"
    ],
    "wof:name":"33.846 Rd",
    "wof:placetype":"locality",
    "wof:population":62
},
  "geometry": {"coordinates":[73.903649,29.13112],"type":"Point"}
}