{
  "type": "Feature",
  "properties": {
    "gn:admin1_code":"34.0",
    "gn:admin2_code":"221.0",
    "gn:asciiname":"Dadanpur",
    "gn:country_code":"IN",
    "gn:dem":52,
    "gn:feature_class":"P",
    "gn:feature_code":"PPL",
    "gn:name":"D\u0101danpur",
    "gn:population":0,
    "gn:timezone":"Asia/Kolkata",
    "iso:country":"IN",
    "ks:ks_alt_nam":"D\u0101danpur",
    "ks:ks_name":"Dadanpur",
    "ks:ks_pop":1228,
    "ks:ks_type":"VILLAGE",
    "name:eng_x_preferred":[
        "Dadanpur"
    ],
    "name:eng_x_variant":[
        "D\u0101danpur"
    ],
    "wof:name":"Dadanpur",
    "wof:placetype":"locality",
    "wof:population":1228
},
  "geometry": {"coordinates":[85.634708,25.72387],"type":"Point"}
}