{
  "type": "Feature",
  "properties": {
    "iso:country":"IN",
    "ks:ks_alt_nam":"Kh\u0101nji",
    "ks:ks_name":"Khanji",
    "ks:ks_type":"VILLAGE",
    "ks:ks_uagg_main":0,
    "name:eng_x_preferred":[
        "Khanji"
    ],
    "name:eng_x_variant":[
        "Kh\u0101nji"
    ],
    "wof:name":"Khanji",
    "wof:placetype":"neighbourhood"
},
  "geometry": {"coordinates":[79.012918,20.250492],"type":"Point"}
}