{
  "type": "Feature",
  "properties": {
    "gn:admin1_code":"25.0",
    "gn:admin2_code":"633.0",
    "gn:asciiname":"Porasappalaiyam",
    "gn:country_code":"IN",
    "gn:dem":224,
    "gn:feature_class":"P",
    "gn:feature_code":"PPL",
    "gn:name":"Por\u0101sapp\u0101laiyam",
    "gn:population":0,
    "gn:timezone":"Asia/Kolkata",
    "iso:country":"IN",
    "wof:name":"Porasappalaiyam",
    "wof:placetype":"locality"
},
  "geometry": {"coordinates":[77.70285,11.04327],"type":"Point"}
}