{
  "type": "Feature",
  "properties": {
    "iso:country":"IN",
    "ks:ks_name":"Kottam Indlu",
    "ks:ks_pop":101,
    "ks:ks_type":"HABITATION",
    "ks:ks_uagg_main":0,
    "name:eng_x_preferred":[
        "Kottam Indlu"
    ],
    "wof:name":"Kottam Indlu",
    "wof:placetype":"neighbourhood",
    "wof:population":101
},
  "geometry": {"coordinates":[79.38773399999999,13.208569],"type":"Point"}
}