{
  "type": "Feature",
  "properties": {
    "iso:country":"IN",
    "ks:ks_name":"Kiapanasi",
    "ks:ks_pop":129,
    "ks:ks_type":"VILLAGE",
    "name:eng_x_preferred":[
        "Kiapanasi"
    ],
    "wof:name":"Kiapanasi",
    "wof:placetype":"locality",
    "wof:population":129
},
  "geometry": {"coordinates":[87.12418099999999,21.722362],"type":"Point"}
}