{
  "type": "Feature",
  "properties": {
    "iso:country":"IN",
    "ks:ks_name":"Lambadithanda",
    "ks:ks_pop":59,
    "ks:ks_type":"HABITATION",
    "name:eng_x_preferred":[
        "Lambadithanda"
    ],
    "wof:name":"Lambadithanda",
    "wof:placetype":"locality",
    "wof:population":59
},
  "geometry": {"coordinates":[79.295379,17.898997],"type":"Point"}
}