{
  "type": "Feature",
  "properties": {
    "iso:country":"IN",
    "ks:ks_name":"Bagdharidand",
    "ks:ks_pop":252,
    "ks:ks_type":"HABITATION",
    "name:eng_x_preferred":[
        "Bagdharidand"
    ],
    "wof:name":"Bagdharidand",
    "wof:placetype":"locality",
    "wof:population":252
},
  "geometry": {"coordinates":[82.259783,22.692883],"type":"Point"}
}