{
  "type": "Feature",
  "properties": {
    "iso:country":"IN",
    "ks:ks_name":"Nahar Chhapra",
    "ks:ks_pop":184,
    "ks:ks_type":"HABITATION",
    "ks:ks_uagg_main":0,
    "name:eng_x_preferred":[
        "Nahar Chhapra"
    ],
    "wof:name":"Nahar Chhapra",
    "wof:placetype":"neighbourhood",
    "wof:population":184
},
  "geometry": {"coordinates":[83.782533,27.016185],"type":"Point"}
}