{
  "type": "Feature",
  "properties": {
    "gn:admin1_code":"16.0",
    "gn:admin2_code":"525.0",
    "gn:asciiname":"Wakdi",
    "gn:country_code":"IN",
    "gn:dem":629,
    "gn:feature_class":"P",
    "gn:feature_code":"PPL",
    "gn:name":"W\u0101kdi",
    "gn:population":0,
    "gn:timezone":"Asia/Kolkata",
    "iso:country":"IN",
    "wof:name":"Wakdi",
    "wof:placetype":"neighbourhood"
},
  "geometry": {"coordinates":[76.23016,18.57215],"type":"Point"}
}