{
  "type": "Feature",
  "properties": {
    "iso:country":"IN",
    "ks:ks_name":"12 S",
    "ks:ks_pop":26,
    "ks:ks_type":"VILLAGE",
    "name:eng_x_preferred":[
        "12 S"
    ],
    "wof:name":"12 S",
    "wof:placetype":"locality",
    "wof:population":26
},
  "geometry": {"coordinates":[73.497038,29.967052],"type":"Point"}
}