{
  "type": "Feature",
  "properties": {
    "iso:country":"IN",
    "ks:ks_name":"Champaguda",
    "ks:ks_pop":46,
    "ks:ks_type":"HABITATION",
    "name:eng_x_preferred":[
        "Champaguda"
    ],
    "wof:name":"Champaguda",
    "wof:placetype":"locality",
    "wof:population":46
},
  "geometry": {"coordinates":[83.036258,18.489804],"type":"Point"}
}