{
  "type": "Feature",
  "properties": {
    "iso:country":"IN",
    "ks:ks_name":"Sambuguda",
    "ks:ks_pop":104,
    "ks:ks_type":"HABITATION",
    "name:eng_x_preferred":[
        "Sambuguda"
    ],
    "wof:name":"Sambuguda",
    "wof:placetype":"locality",
    "wof:population":104
},
  "geometry": {"coordinates":[83.521635,18.999278],"type":"Point"}
}