{
  "type": "Feature",
  "properties": {
    "iso:country":"IN",
    "ks:ks_name":"Malinenivaripalli",
    "ks:ks_pop":271,
    "ks:ks_type":"HABITATION",
    "name:eng_x_preferred":[
        "Malinenivaripalli"
    ],
    "wof:name":"Malinenivaripalli",
    "wof:placetype":"locality",
    "wof:population":271
},
  "geometry": {"coordinates":[79.55661499999999,15.280128],"type":"Point"}
}