{
  "type": "Feature",
  "properties": {
    "iso:country":"IN",
    "ks:ks_name":"Kuthalingapuram",
    "ks:ks_pop":312,
    "ks:ks_type":"HABITATION",
    "ks:ks_uagg_main":0,
    "name:eng_x_preferred":[
        "Kuthalingapuram"
    ],
    "wof:name":"Kuthalingapuram",
    "wof:placetype":"neighbourhood",
    "wof:population":312
},
  "geometry": {"coordinates":[77.482291,8.850681],"type":"Point"}
}