{
  "type": "Feature",
  "properties": {
    "gn:admin1_code":"35",
    "gn:admin2_code":"443.0",
    "gn:asciiname":"Menkheri",
    "gn:country_code":"IN",
    "gn:dem":411,
    "gn:feature_class":"P",
    "gn:feature_code":"PPL",
    "gn:name":"Menkheri",
    "gn:population":0,
    "gn:timezone":"Asia/Kolkata",
    "iso:country":"IN",
    "ks:ks_name":"Menkheri",
    "ks:ks_type":"VILLAGE",
    "name:eng_x_preferred":[
        "Menkheri"
    ],
    "wof:name":"Menkheri",
    "wof:placetype":"locality"
},
  "geometry": {"coordinates":[77.94775,24.129575],"type":"Point"}
}