{
  "type": "Feature",
  "properties": {
    "iso:country":"IN",
    "ks:ks_name":"V Kaikatti",
    "ks:ks_pop":390,
    "ks:ks_type":"HABITATION",
    "name:eng_x_preferred":[
        "V Kaikatti"
    ],
    "wof:name":"V Kaikatti",
    "wof:placetype":"locality",
    "wof:population":390
},
  "geometry": {"coordinates":[78.465112,10.484715],"type":"Point"}
}