{
  "type": "Feature",
  "properties": {
    "iso:country":"IN",
    "ks:ks_name":"Chalakal",
    "ks:ks_pop":518,
    "ks:ks_type":"HABITATION",
    "name:eng_x_preferred":[
        "Chalakal"
    ],
    "wof:name":"Chalakal",
    "wof:placetype":"locality",
    "wof:population":518
},
  "geometry": {"coordinates":[76.556589,9.833736],"type":"Point"}
}