{
  "type": "Feature",
  "properties": {
    "gn:admin1_code":"35.0",
    "gn:admin2_code":"440.0",
    "gn:asciiname":"Mehta Khedi",
    "gn:country_code":"IN",
    "gn:dem":521,
    "gn:feature_class":"P",
    "gn:feature_code":"PPL",
    "gn:name":"Mehta Khedi",
    "gn:population":0,
    "gn:timezone":"Asia/Kolkata",
    "iso:country":"IN",
    "ks:ks_name":"Mehetya Khedi",
    "ks:ks_pop":667,
    "ks:ks_type":"HABITATION",
    "name:eng_x_preferred":[
        "Mehetya Khedi"
    ],
    "name:eng_x_variant":[
        "Mehta Khedi"
    ],
    "wof:name":"Mehetya Khedi",
    "wof:placetype":"locality",
    "wof:population":667
},
  "geometry": {"coordinates":[75.972945,21.442345],"type":"Point"}
}