{
  "type": "Feature",
  "properties": {
    "gn:admin1_code":"35.0",
    "gn:admin2_code":"440.0",
    "gn:asciiname":"Mehta Khedi",
    "gn:country_code":"IN",
    "gn:dem":521,
    "gn:feature_class":"P",
    "gn:feature_code":"PPL",
    "gn:name":"Mehta Khedi",
    "gn:population":0,
    "gn:timezone":"Asia/Kolkata",
    "iso:country":"IN",
    "wof:name":"Mehta Khedi",
    "wof:placetype":"locality"
},
  "geometry": {"coordinates":[75.95995000000001,21.42891],"type":"Point"}
}