{
  "type": "Feature",
  "properties": {
    "iso:country":"IN",
    "ks:ks_name":"Machkandi",
    "ks:ks_pop":381,
    "ks:ks_type":"VILLAGE",
    "name:eng_x_preferred":[
        "Machkandi"
    ],
    "wof:name":"Machkandi",
    "wof:placetype":"locality",
    "wof:population":381
},
  "geometry": {"coordinates":[79.145859,30.433295],"type":"Point"}
}