{
  "type": "Feature",
  "properties": {
    "iso:country":"IN",
    "ks:ks_name":"Karnawas Nenuoni Godaro Ki Dhani",
    "ks:ks_pop":125,
    "ks:ks_type":"HABITATION",
    "name:eng_x_preferred":[
        "Karnawas Nenuoni Godaro Ki Dhani"
    ],
    "wof:name":"Karnawas Nenuoni Godaro Ki Dhani",
    "wof:placetype":"locality",
    "wof:population":125
},
  "geometry": {"coordinates":[71.52253899999999,25.743619],"type":"Point"}
}