{
  "type": "Feature",
  "properties": {
    "iso:country":"IN",
    "ks:ks_name":"Akbarpur",
    "ks:ks_pop":392,
    "ks:ks_type":"VILLAGE",
    "name:eng_x_preferred":[
        "Akbarpur"
    ],
    "wof:name":"Akbarpur",
    "wof:placetype":"locality",
    "wof:population":392
},
  "geometry": {"coordinates":[77.71263399999999,29.334838],"type":"Point"}
}