{
  "type": "Feature",
  "properties": {
    "gn:admin1_code":"9.0",
    "gn:admin2_code":"483",
    "gn:asciiname":"Chhipri",
    "gn:country_code":"IN",
    "gn:dem":60,
    "gn:feature_class":"P",
    "gn:feature_code":"PPL",
    "gn:name":"Chhipri",
    "gn:population":0,
    "gn:timezone":"Asia/Kolkata",
    "iso:country":"IN",
    "name:und_x_variant":[
        "Chhipdi",
        "Chhipri"
    ],
    "wof:name":"Chhipri",
    "wof:placetype":"locality"
},
  "geometry": {"coordinates":[72.92004,22.96407],"type":"Point"}
}