{
  "type": "Feature",
  "properties": {
    "iso:country":"IN",
    "ks:ks_name":"Bhimara",
    "ks:ks_pop":777,
    "ks:ks_type":"VILLAGE",
    "ks:ks_uagg_main":0,
    "name:eng_x_preferred":[
        "Bhimara"
    ],
    "wof:name":"Bhimara",
    "wof:placetype":"neighbourhood",
    "wof:population":777
},
  "geometry": {"coordinates":[86.980769,23.018533],"type":"Point"}
}