{
  "type": "Feature",
  "properties": {
    "iso:country":"IN",
    "ks:ks_name":"Devalabail Kuchur",
    "ks:ks_pop":39,
    "ks:ks_type":"HABITATION",
    "name:eng_x_preferred":[
        "Devalabail Kuchur"
    ],
    "wof:name":"Devalabail Kuchur",
    "wof:placetype":"locality",
    "wof:population":39
},
  "geometry": {"coordinates":[74.98841299999999,13.481907],"type":"Point"}
}