{
  "type": "Feature",
  "properties": {
    "gn:admin1_code":"10.0",
    "gn:admin2_code":"85.0",
    "gn:asciiname":"Ramsinghpur",
    "gn:country_code":"IN",
    "gn:dem":271,
    "gn:feature_class":"P",
    "gn:feature_code":"PPL",
    "gn:name":"R\u0101msinghpur",
    "gn:population":0,
    "gn:timezone":"Asia/Kolkata",
    "iso:country":"IN",
    "ks:ks_name":"Ramsinghpur",
    "ks:ks_pop":272,
    "ks:ks_type":"VILLAGE",
    "name:eng_x_preferred":[
        "Ramsinghpur"
    ],
    "name:und_x_variant":[
        "R\u0101msinghpur"
    ],
    "wof:name":"Ramsinghpur",
    "wof:placetype":"locality",
    "wof:population":272
},
  "geometry": {"coordinates":[76.530916,28.066502],"type":"Point"}
}