{
  "type": "Feature",
  "properties": {
    "iso:country":"IN",
    "ks:ks_alt_nam":"Potti Devula thanda",
    "ks:ks_name":"Potti Devula Thanda",
    "ks:ks_pop":366,
    "ks:ks_type":"HABITATION",
    "name:eng_x_preferred":[
        "Potti Devula Thanda"
    ],
    "wof:name":"Potti Devula Thanda",
    "wof:placetype":"locality",
    "wof:population":366
},
  "geometry": {"coordinates":[79.146145,17.990584],"type":"Point"}
}