{
  "type": "Feature",
  "properties": {
    "iso:country":"IN",
    "ks:ks_name":"Jamundimaska",
    "ks:ks_pop":34,
    "ks:ks_type":"HABITATION",
    "name:eng_x_preferred":[
        "Jamundimaska"
    ],
    "wof:name":"Jamundimaska",
    "wof:placetype":"locality",
    "wof:population":34
},
  "geometry": {"coordinates":[83.252618,19.372078],"type":"Point"}
}