{
  "type": "Feature",
  "properties": {
    "iso:country":"IN",
    "ks:ks_name":"Munj Khedi",
    "ks:ks_pop":243,
    "ks:ks_type":"HABITATION",
    "name:eng_x_preferred":[
        "Munj Khedi"
    ],
    "wof:name":"Munj Khedi",
    "wof:placetype":"locality",
    "wof:population":243
},
  "geometry": {"coordinates":[76.69569799999999,24.110806],"type":"Point"}
}