{
  "type": "Feature",
  "properties": {
    "iso:country":"IN",
    "ks:ks_name":"Umdiangsiar",
    "ks:ks_pop":109,
    "ks:ks_type":"HABITATION",
    "name:eng_x_preferred":[
        "Umdiangsiar"
    ],
    "wof:name":"Umdiangsiar",
    "wof:placetype":"locality",
    "wof:population":109
},
  "geometry": {"coordinates":[91.310929,25.812717],"type":"Point"}
}