{
  "type": "Feature",
  "properties": {
    "gn:admin1_code":"11",
    "gn:admin2_code":"27.0",
    "gn:asciiname":"Suan",
    "gn:country_code":"IN",
    "gn:dem":905,
    "gn:feature_class":"P",
    "gn:feature_code":"PPL",
    "gn:name":"Su\u0101n",
    "gn:population":0,
    "gn:timezone":"Asia/Kolkata",
    "iso:country":"IN",
    "wof:name":"Suan",
    "wof:placetype":"locality"
},
  "geometry": {"coordinates":[76.80216999999998,31.87775],"type":"Point"}
}