{
  "type": "Feature",
  "properties": {
    "iso:country":"IN",
    "ks:ks_name":"Madan Kamdev",
    "ks:ks_pop":1050,
    "ks:ks_type":"HABITATION",
    "name:eng_x_preferred":[
        "Madan Kamdev"
    ],
    "wof:name":"Madan Kamdev",
    "wof:placetype":"locality",
    "wof:population":1050
},
  "geometry": {"coordinates":[91.751824,26.327343],"type":"Point"}
}