{
  "type": "Feature",
  "properties": {
    "gn:admin1_code":"37",
    "gn:admin2_code":"404.0",
    "gn:asciiname":"Dhanras",
    "gn:country_code":"IN",
    "gn:dem":404,
    "gn:feature_class":"P",
    "gn:feature_code":"PPL",
    "gn:name":"Dhanr\u0101s",
    "gn:population":0,
    "gn:timezone":"Asia/Kolkata",
    "iso:country":"IN",
    "ks:ks_alt_nam":"Dhanr\u0101s",
    "ks:ks_name":"Dhanras",
    "ks:ks_pop":331,
    "ks:ks_type":"VILLAGE",
    "name:eng_x_preferred":[
        "Dhanras"
    ],
    "name:eng_x_variant":[
        "Dhanr\u0101s"
    ],
    "wof:name":"Dhanras",
    "wof:placetype":"locality",
    "wof:population":331
},
  "geometry": {"coordinates":[82.338928,22.731905],"type":"Point"}
}