{
  "type": "Feature",
  "properties": {
    "iso:country":"IN",
    "ks:ks_name":"Dharmaj",
    "ks:ks_pop":199,
    "ks:ks_type":"VILLAGE",
    "ks:ks_uagg_main":0,
    "name:eng_x_preferred":[
        "Dharmaj"
    ],
    "wof:name":"Dharmaj",
    "wof:placetype":"neighbourhood",
    "wof:population":199
},
  "geometry": {"coordinates":[73.936167,22.317944],"type":"Point"}
}