{
  "type": "Feature",
  "properties": {
    "gn:admin1_code":"36",
    "gn:admin2_code":"198.0",
    "gn:asciiname":"Amlori",
    "gn:country_code":"IN",
    "gn:dem":90,
    "gn:feature_class":"P",
    "gn:feature_code":"PPL",
    "gn:name":"Amlori",
    "gn:population":0,
    "gn:timezone":"Asia/Kolkata",
    "iso:country":"IN",
    "wof:name":"Amlori",
    "wof:placetype":"neighbourhood"
},
  "geometry": {"coordinates":[82.52301,25.42418],"type":"Point"}
}