{
  "type": "Feature",
  "properties": {
    "iso:country":"IN",
    "ks:ks_name":"Jhimari",
    "ks:ks_pop":102,
    "ks:ks_type":"HABITATION",
    "name:eng_x_preferred":[
        "Jhimari"
    ],
    "wof:name":"Jhimari",
    "wof:placetype":"locality",
    "wof:population":102
},
  "geometry": {"coordinates":[84.02949700000001,22.587276],"type":"Point"}
}