{
  "type": "Feature",
  "properties": {
    "gn:admin1_code":"13.0",
    "gn:admin2_code":"600.0",
    "gn:asciiname":"Kadacheri",
    "gn:country_code":"IN",
    "gn:dem":103,
    "gn:feature_class":"P",
    "gn:feature_code":"PPL",
    "gn:name":"Kadacheri",
    "gn:population":0,
    "gn:timezone":"Asia/Kolkata",
    "iso:country":"IN",
    "ks:ks_name":"Kadaseri",
    "ks:ks_pop":1668,
    "ks:ks_type":"HABITATION",
    "name:eng_x_preferred":[
        "Kadaseri"
    ],
    "name:eng_x_variant":[
        "Kadacheri"
    ],
    "wof:name":"Kadaseri",
    "wof:placetype":"locality",
    "wof:population":1668
},
  "geometry": {"coordinates":[76.92057800000001,9.10172],"type":"Point"}
}