{
  "type": "Feature",
  "properties": {
    "gn:admin1_code":"2.0",
    "gn:admin2_code":"551.0",
    "gn:asciiname":"Dammanapalli",
    "gn:country_code":"IN",
    "gn:dem":179,
    "gn:feature_class":"P",
    "gn:feature_code":"PPL",
    "gn:name":"Dammanapalli",
    "gn:population":0,
    "gn:timezone":"Asia/Kolkata",
    "iso:country":"IN",
    "name:hin_x_preferred":[
        "\u0926\u092e\u094d\u092e\u0928\u092a\u0932\u094d\u0932\u0946"
    ],
    "name:mal_x_preferred":[
        "\u0d26\u0d2e\u0d4d\u0d2e\u0d28\u0d2a\u0d33\u0d4d\u0d33\u0d3f"
    ],
    "name:new_x_preferred":[
        "\u0926\u092e\u094d\u092e\u0928\u092a\u0932\u094d\u0932\u0946"
    ],
    "name:tel_x_preferred":[
        "\u0c26\u0c2e\u0c4d\u0c2e\u0c28\u0c2a\u0c32\u0c4d\u0c32\u0c46"
    ],
    "wof:name":"Dammanapalli",
    "wof:placetype":"locality"
},
  "geometry": {"coordinates":[79.03397,14.91414],"type":"Point"}
}