{
  "type": "Feature",
  "properties": {
    "iso:country":"IN",
    "ks:ks_alt_nam":"kelagina kumbar",
    "ks:ks_name":"Kelagina Kumbar",
    "ks:ks_pop":145,
    "ks:ks_type":"HABITATION",
    "name:eng_x_preferred":[
        "Kelagina Kumbar"
    ],
    "wof:name":"Kelagina Kumbar",
    "wof:placetype":"locality",
    "wof:population":145
},
  "geometry": {"coordinates":[74.627573,14.221912],"type":"Point"}
}