{
  "type": "Feature",
  "properties": {
    "gn:admin1_code":"34.0",
    "gn:admin2_code":"231.0",
    "gn:asciiname":"Isharpura",
    "gn:country_code":"IN",
    "gn:dem":62,
    "gn:feature_class":"P",
    "gn:feature_code":"PPL",
    "gn:name":"Isharpura",
    "gn:population":0,
    "gn:timezone":"Asia/Kolkata",
    "iso:country":"IN",
    "ks:ks_name":"Isharpura",
    "ks:ks_pop":4254,
    "ks:ks_type":"HABITATION",
    "ks:ks_uagg_main":0,
    "name:eng_x_preferred":[
        "Isharpura"
    ],
    "wof:name":"Isharpura",
    "wof:placetype":"neighbourhood",
    "wof:population":4254
},
  "geometry": {"coordinates":[84.36480400000001,25.678136],"type":"Point"}
}