{
  "type": "Feature",
  "properties": {
    "iso:country":"IN",
    "ks:ks_name":"Maulibhag",
    "ks:ks_pop":478,
    "ks:ks_type":"HABITATION",
    "name:eng_x_preferred":[
        "Maulibhag"
    ],
    "wof:name":"Maulibhag",
    "wof:placetype":"locality",
    "wof:population":478
},
  "geometry": {"coordinates":[83.854332,21.418846],"type":"Point"}
}