{
  "type": "Feature",
  "properties": {
    "iso:country":"IN",
    "ks:ks_name":"Tola Salaia",
    "ks:ks_pop":287,
    "ks:ks_type":"VILLAGE",
    "name:eng_x_preferred":[
        "Tola Salaia"
    ],
    "wof:name":"Tola Salaia",
    "wof:placetype":"locality",
    "wof:population":287
},
  "geometry": {"coordinates":[86.41624299999999,24.410199],"type":"Point"}
}