{
  "type": "Feature",
  "properties": {
    "gn:admin1_code":"3.0",
    "gn:admin2_code":"303.0",
    "gn:asciiname":"Nagaon",
    "gn:country_code":"IN",
    "gn:dem":41,
    "gn:feature_class":"P",
    "gn:feature_code":"PPL",
    "gn:name":"Nagaon",
    "gn:population":0,
    "gn:timezone":"Asia/Kolkata",
    "iso:country":"IN",
    "wof:name":"Nagaon",
    "wof:placetype":"locality"
},
  "geometry": {"coordinates":[91.11011999999999,26.30444],"type":"Point"}
}