{
  "type": "Feature",
  "properties": {
    "gn:admin1_code":"3.0",
    "gn:admin2_code":"303.0",
    "gn:asciiname":"Nagaon",
    "gn:country_code":"IN",
    "gn:dem":41,
    "gn:feature_class":"P",
    "gn:feature_code":"PPL",
    "gn:name":"Nagaon",
    "gn:population":0,
    "gn:timezone":"Asia/Kolkata",
    "iso:country":"IN",
    "name:asm_x_preferred":[
        "\u09a8\u0997\u09be\u0981\u0993"
    ],
    "name:ben_x_preferred":[
        "\u09a8\u0997\u09be\u0981\u0993"
    ],
    "name:bih_x_preferred":[
        "\u0928\u0917\u093e\u0901\u0935"
    ],
    "name:cat_x_preferred":[
        "Nagaon"
    ],
    "name:ceb_x_preferred":[
        "Nagaon"
    ],
    "name:deu_x_preferred":[
        "Nagaon"
    ],
    "name:fra_x_preferred":[
        "Nagaon"
    ],
    "name:hin_x_preferred":[
        "\u0928\u0917\u093e\u0901\u0935"
    ],
    "name:ita_x_preferred":[
        "Nagaon"
    ],
    "name:msa_x_preferred":[
        "Nagaon"
    ],
    "name:nep_x_preferred":[
        "\u0928\u094c\u0917\u093e\u0902\u0935"
    ],
    "name:new_x_preferred":[
        "\u0928\u0917\u093e\u0901\u0913"
    ],
    "name:nld_x_preferred":[
        "Nagaon"
    ],
    "name:oci_x_preferred":[
        "Nagaon"
    ],
    "name:ori_x_preferred":[
        "\u0b28\u0b3e\u0b17\u0b17\u0b3e\u0b01"
    ],
    "name:rus_x_preferred":[
        "\u041d\u0430\u0433\u0430\u043e\u043d"
    ],
    "name:san_x_preferred":[
        "\u0928\u0917\u093e\u0935-\u0928\u0917\u0930\u092e\u094d"
    ],
    "name:spa_x_preferred":[
        "Nagaon"
    ],
    "name:swe_x_preferred":[
        "Nagaon"
    ],
    "name:urd_x_preferred":[
        "\u0646\u0627\u06af\u0627\u0624\u06ba"
    ],
    "name:vie_x_preferred":[
        "Nagaon"
    ],
    "name:zho_x_preferred":[
        "\u7eb3\u52a0\u5965\u6069"
    ],
    "wof:name":"Nagaon",
    "wof:placetype":"locality"
},
  "geometry": {"coordinates":[91.11011999999999,26.30444],"type":"Point"}
}