{
  "type": "Feature",
  "properties": {
    "iso:country":"IN",
    "ks:ks_name":"Tola Puranchih",
    "ks:ks_pop":89,
    "ks:ks_type":"VILLAGE",
    "name:eng_x_preferred":[
        "Tola Puranchih"
    ],
    "wof:name":"Tola Puranchih",
    "wof:placetype":"locality",
    "wof:population":89
},
  "geometry": {"coordinates":[86.803836,24.720979],"type":"Point"}
}