{
  "type": "Feature",
  "properties": {
    "iso:country":"IN",
    "ks:ks_alt_nam":"T\u0101jpur",
    "ks:ks_name":"Tajpur",
    "ks:ks_pop":2839,
    "ks:ks_type":"VILLAGE",
    "name:eng_x_preferred":[
        "Tajpur"
    ],
    "name:eng_x_variant":[
        "T\u0101jpur"
    ],
    "wof:name":"Tajpur",
    "wof:placetype":"locality",
    "wof:population":2839
},
  "geometry": {"coordinates":[85.25711699999999,24.411016],"type":"Point"}
}