{
  "type": "Feature",
  "properties": {
    "gn:admin1_code":"39.0",
    "gn:admin2_code":"64.0",
    "gn:asciiname":"Machhidhar",
    "gn:country_code":"IN",
    "gn:dem":819,
    "gn:feature_class":"P",
    "gn:feature_code":"PPL",
    "gn:name":"Machhidh\u0101r",
    "gn:population":0,
    "gn:timezone":"Asia/Kolkata",
    "iso:country":"IN",
    "ks:ks_alt_nam":"Machhidh\u0101r",
    "ks:ks_name":"Machhidhar",
    "ks:ks_type":"VILLAGE",
    "name:eng_x_preferred":[
        "Machhidhar"
    ],
    "name:eng_x_variant":[
        "Machhidh\u0101r"
    ],
    "wof:name":"Machhidhar",
    "wof:placetype":"locality"
},
  "geometry": {"coordinates":[79.98723200000001,29.595051],"type":"Point"}
}