{
  "type": "Feature",
  "properties": {
    "gn:admin1_code":"39.0",
    "gn:admin2_code":"64.0",
    "gn:asciiname":"Machhidhar",
    "gn:country_code":"IN",
    "gn:dem":819,
    "gn:feature_class":"P",
    "gn:feature_code":"PPL",
    "gn:name":"Machhidh\u0101r",
    "gn:population":0,
    "gn:timezone":"Asia/Kolkata",
    "iso:country":"IN",
    "wof:name":"Machhidhar",
    "wof:placetype":"locality"
},
  "geometry": {"coordinates":[79.98723000000003,29.59505],"type":"Point"}
}