{
  "type": "Feature",
  "properties": {
    "gn:admin1_code":"23.0",
    "gn:admin2_code":"43.0",
    "gn:asciiname":"Budhoke",
    "gn:country_code":"IN",
    "gn:dem":183,
    "gn:feature_class":"P",
    "gn:feature_code":"PPL",
    "gn:name":"Budhoke",
    "gn:population":0,
    "gn:timezone":"Asia/Kolkata",
    "iso:country":"IN",
    "name:und_x_variant":[
        "Chak Lakhow\u0101l"
    ],
    "wof:name":"Budhoke",
    "wof:placetype":"locality"
},
  "geometry": {"coordinates":[74.19726,30.49967],"type":"Point"}
}