{
  "type": "Feature",
  "properties": {
    "iso:country":"IN",
    "ks:ks_alt_nam":"R\u0101mdega",
    "ks:ks_name":"Ramdega",
    "ks:ks_pop":103,
    "ks:ks_type":"VILLAGE",
    "name:eng_x_preferred":[
        "Ramdega"
    ],
    "name:eng_x_variant":[
        "R\u0101mdega"
    ],
    "wof:name":"Ramdega",
    "wof:placetype":"locality",
    "wof:population":103
},
  "geometry": {"coordinates":[84.359027,22.809735],"type":"Point"}
}