{
  "type": "Feature",
  "properties": {
    "gn:admin1_code":"19.0",
    "gn:admin2_code":"575.0",
    "gn:asciiname":"Chalangalu",
    "gn:country_code":"IN",
    "gn:dem":129,
    "gn:feature_class":"P",
    "gn:feature_code":"PPL",
    "gn:name":"Chalangalu",
    "gn:population":0,
    "gn:timezone":"Asia/Kolkata",
    "iso:country":"IN",
    "wof:name":"Chalangalu",
    "wof:placetype":"locality"
},
  "geometry": {"coordinates":[75.30495000000001,12.53346],"type":"Point"}
}