{
  "type": "Feature",
  "properties": {
    "iso:country":"IN",
    "ks:ks_name":"Salagan",
    "ks:ks_pop":1024,
    "ks:ks_type":"VILLAGE",
    "name:eng_x_preferred":[
        "Salagan"
    ],
    "wof:name":"Salagan",
    "wof:placetype":"locality",
    "wof:population":1024
},
  "geometry": {"coordinates":[86.147098,20.195815],"type":"Point"}
}