{
  "type": "Feature",
  "properties": {
    "iso:country":"IN",
    "ks:ks_name":"Doorvasanoor",
    "ks:ks_pop":335,
    "ks:ks_type":"HABITATION",
    "name:eng_x_preferred":[
        "Doorvasanoor"
    ],
    "wof:name":"Doorvasanoor",
    "wof:placetype":"locality",
    "wof:population":335
},
  "geometry": {"coordinates":[78.043852,12.525077],"type":"Point"}
}