{
  "type": "Feature",
  "properties": {
    "iso:country":"IN",
    "ks:ks_name":"Oyasilchak",
    "ks:ks_pop":870,
    "ks:ks_type":"VILLAGE",
    "name:eng_x_preferred":[
        "Oyasilchak"
    ],
    "wof:name":"Oyasilchak",
    "wof:placetype":"locality",
    "wof:population":870
},
  "geometry": {"coordinates":[87.93456999999999,21.823094],"type":"Point"}
}