{
  "type": "Feature",
  "properties": {
    "gn:admin1_code":"16.0",
    "gn:admin2_code":"515.0",
    "gn:asciiname":"Kavli",
    "gn:country_code":"IN",
    "gn:dem":365,
    "gn:feature_class":"P",
    "gn:feature_code":"PPL",
    "gn:name":"Kavli",
    "gn:population":0,
    "gn:timezone":"Asia/Kolkata",
    "iso:country":"IN",
    "wof:name":"Kavli",
    "wof:placetype":"locality"
},
  "geometry": {"coordinates":[75.50433000000002,20.53269],"type":"Point"}
}