{
  "type": "Feature",
  "properties": {
    "iso:country":"IN",
    "ks:ks_name":"Khatamali Falia",
    "ks:ks_pop":685,
    "ks:ks_type":"HABITATION",
    "name:eng_x_preferred":[
        "Khatamali Falia"
    ],
    "wof:name":"Khatamali Falia",
    "wof:placetype":"locality",
    "wof:population":685
},
  "geometry": {"coordinates":[73.7197,22.50015],"type":"Point"}
}