{
  "type": "Feature",
  "properties": {
    "iso:country":"IN",
    "ks:ks_alt_nam":"DHONDEWADI VIA JAGATAPMALA",
    "ks:ks_name":"Dhondewadi Via Jagatapmala",
    "ks:ks_pop":125,
    "ks:ks_type":"HABITATION",
    "name:eng_x_preferred":[
        "Dhondewadi Via Jagatapmala"
    ],
    "wof:name":"Dhondewadi Via Jagatapmala",
    "wof:placetype":"locality",
    "wof:population":125
},
  "geometry": {"coordinates":[74.63901300000001,17.165603],"type":"Point"}
}