{
  "type": "Feature",
  "properties": {
    "iso:country":"IN",
    "ks:ks_name":"Jhingwa",
    "ks:ks_pop":632,
    "ks:ks_type":"HABITATION",
    "name:eng_x_preferred":[
        "Jhingwa"
    ],
    "wof:name":"Jhingwa",
    "wof:placetype":"locality",
    "wof:population":632
},
  "geometry": {"coordinates":[81.343602,27.826763],"type":"Point"}
}