{
  "type": "Feature",
  "properties": {
    "iso:country":"IN",
    "ks:ks_name":"Bandhakud",
    "ks:ks_pop":764,
    "ks:ks_type":"VILLAGE",
    "name:eng_x_preferred":[
        "Bandhakud"
    ],
    "wof:name":"Bandhakud",
    "wof:placetype":"locality",
    "wof:population":764
},
  "geometry": {"coordinates":[86.533917,20.341836],"type":"Point"}
}