{
  "type": "Feature",
  "properties": {
    "gn:admin1_code":"36",
    "gn:admin2_code":"178.0",
    "gn:asciiname":"Purwa Badri",
    "gn:country_code":"IN",
    "gn:dem":83,
    "gn:feature_class":"P",
    "gn:feature_code":"PPL",
    "gn:name":"Purwa Badri",
    "gn:population":0,
    "gn:timezone":"Asia/Kolkata",
    "iso:country":"IN",
    "wof:name":"Purwa Badri",
    "wof:placetype":"locality"
},
  "geometry": {"coordinates":[83.11043000000002,26.32465],"type":"Point"}
}