{
  "type": "Feature",
  "properties": {
    "iso:country":"IN",
    "ks:ks_alt_nam":"J VANKAGADDA",
    "ks:ks_name":"J Vankagadda",
    "ks:ks_pop":190,
    "ks:ks_type":"HABITATION",
    "name:eng_x_preferred":[
        "J Vankagadda"
    ],
    "wof:name":"J Vankagadda",
    "wof:placetype":"locality",
    "wof:population":190
},
  "geometry": {"coordinates":[79.07983900000001,14.553844],"type":"Point"}
}