{
  "type": "Feature",
  "properties": {
    "gn:admin1_code":"16.0",
    "gn:admin2_code":"513.0",
    "gn:asciiname":"Mandwawadi",
    "gn:country_code":"IN",
    "gn:dem":453,
    "gn:feature_class":"P",
    "gn:feature_code":"PPL",
    "gn:name":"Mandw\u0101w\u0101di",
    "gn:population":0,
    "gn:timezone":"Asia/Kolkata",
    "iso:country":"IN",
    "wof:name":"Mandwawadi",
    "wof:placetype":"locality"
},
  "geometry": {"coordinates":[76.79207,19.6391],"type":"Point"}
}