{
  "type": "Feature",
  "properties": {
    "iso:country":"IN",
    "ks:ks_name":"Imlidand Karwan",
    "ks:ks_pop":139,
    "ks:ks_type":"HABITATION",
    "name:eng_x_preferred":[
        "Imlidand Karwan"
    ],
    "wof:name":"Imlidand Karwan",
    "wof:placetype":"locality",
    "wof:population":139
},
  "geometry": {"coordinates":[82.84745700000001,23.612586],"type":"Point"}
}