{
  "type": "Feature",
  "properties": {
    "iso:country":"IN",
    "ks:ks_alt_nam":"SARAITOLI",
    "ks:ks_name":"Saraitoli",
    "ks:ks_pop":359,
    "ks:ks_type":"HABITATION",
    "name:eng_x_preferred":[
        "Saraitoli"
    ],
    "wof:name":"Saraitoli",
    "wof:placetype":"locality",
    "wof:population":359
},
  "geometry": {"coordinates":[83.91734,22.463665],"type":"Point"}
}