{
  "type": "Feature",
  "properties": {
    "gn:admin1_code":"23.0",
    "gn:admin2_code":"36.0",
    "gn:asciiname":"Andrisa Khas",
    "gn:country_code":"IN",
    "gn:dem":210,
    "gn:feature_class":"P",
    "gn:feature_code":"PPL",
    "gn:name":"Andr\u012bsa Kh\u0101s",
    "gn:population":0,
    "gn:timezone":"Asia/Kolkata",
    "iso:country":"IN",
    "ks:ks_alt_nam":"Andr\u012bsa Kh\u0101s",
    "ks:ks_name":"Andrisa Khas",
    "ks:ks_pop":0,
    "ks:ks_type":"VILLAGE",
    "name:eng_x_preferred":[
        "Andrisa Khas"
    ],
    "name:eng_x_variant":[
        "Andr\u012bsa Kh\u0101s"
    ],
    "wof:name":"Andrisa Khas",
    "wof:placetype":"locality",
    "wof:population":0
},
  "geometry": {"coordinates":[75.070639,31.16936],"type":"Point"}
}