{
  "type": "Feature",
  "properties": {
    "iso:country":"IN",
    "ks:ks_name":"Hatipathar",
    "ks:ks_pop":25,
    "ks:ks_type":"VILLAGE",
    "name:eng_x_preferred":[
        "Hatipathar"
    ],
    "wof:name":"Hatipathar",
    "wof:placetype":"locality",
    "wof:population":25
},
  "geometry": {"coordinates":[84.37679300000001,19.902134],"type":"Point"}
}