{
  "type": "Feature",
  "properties": {
    "gn:admin1_code":"21.0",
    "gn:admin2_code":"378.0",
    "gn:asciiname":"Podapatna",
    "gn:country_code":"IN",
    "gn:dem":31,
    "gn:feature_class":"P",
    "gn:feature_code":"PPL",
    "gn:name":"Podapatna",
    "gn:population":0,
    "gn:timezone":"Asia/Kolkata",
    "iso:country":"IN",
    "wof:name":"Podapatna",
    "wof:placetype":"locality"
},
  "geometry": {"coordinates":[86.34401,21.14237],"type":"Point"}
}