{
  "type": "Feature",
  "properties": {
    "iso:country":"IN",
    "ks:ks_name":"Tadiveedhi",
    "ks:ks_pop":26,
    "ks:ks_type":"HABITATION",
    "name:eng_x_preferred":[
        "Tadiveedhi"
    ],
    "wof:name":"Tadiveedhi",
    "wof:placetype":"locality",
    "wof:population":26
},
  "geometry": {"coordinates":[82.596723,18.238905],"type":"Point"}
}