{
  "type": "Feature",
  "properties": {
    "gn:admin1_code":"2.0",
    "gn:admin2_code":"554.0",
    "gn:asciiname":"Komatiguruvayyagaripalli",
    "gn:country_code":"IN",
    "gn:dem":404,
    "gn:feature_class":"P",
    "gn:feature_code":"PPL",
    "gn:name":"Komatiguruvayyag\u0101ripalli",
    "gn:population":0,
    "gn:timezone":"Asia/Kolkata",
    "iso:country":"IN",
    "wof:name":"Komatiguruvayyagaripalli",
    "wof:placetype":"locality"
},
  "geometry": {"coordinates":[79.00451,13.38599],"type":"Point"}
}