{
  "type": "Feature",
  "properties": {
    "iso:country":"IN",
    "ks:ks_name":"Palgachhi",
    "ks:ks_pop":7197,
    "ks:ks_type":"VILLAGE",
    "name:eng_x_preferred":[
        "Palgachhi"
    ],
    "wof:name":"Palgachhi",
    "wof:placetype":"locality",
    "wof:population":7197
},
  "geometry": {"coordinates":[87.94628,24.840106],"type":"Point"}
}