{
  "type": "Feature",
  "properties": {
    "iso:country":"IN",
    "ks:ks_name":"Sohasa",
    "ks:ks_pop":1471,
    "ks:ks_type":"VILLAGE",
    "name:eng_x_preferred":[
        "Sohasa"
    ],
    "wof:name":"Sohasa",
    "wof:placetype":"locality",
    "wof:population":1471
},
  "geometry": {"coordinates":[80.25690899999999,27.377535],"type":"Point"}
}