{
  "type": "Feature",
  "properties": {
    "gn:admin1_code":"34.0",
    "gn:admin2_code":"209.0",
    "gn:asciiname":"Mohni",
    "gn:country_code":"IN",
    "gn:dem":49,
    "gn:feature_class":"P",
    "gn:feature_code":"PPL",
    "gn:name":"Mohni",
    "gn:population":0,
    "gn:timezone":"Asia/Kolkata",
    "iso:country":"IN",
    "name:ceb_x_preferred":[
        "Mohni"
    ],
    "name:ces_x_preferred":[
        "Mohni"
    ],
    "name:deu_x_preferred":[
        "Mohni"
    ],
    "name:est_x_preferred":[
        "Mohni"
    ],
    "name:fra_x_preferred":[
        "Mohni"
    ],
    "name:hrv_x_preferred":[
        "Mohni"
    ],
    "name:hye_x_preferred":[
        "\u0544\u0578\u0570\u0576\u056b \u056f\u0572\u0566\u056b"
    ],
    "name:pol_x_preferred":[
        "Mohni"
    ],
    "name:swe_x_preferred":[
        "Ekholm"
    ],
    "wof:name":"Mohni",
    "wof:placetype":"locality"
},
  "geometry": {"coordinates":[87.36461,26.03932],"type":"Point"}
}