{
  "type": "Feature",
  "properties": {
    "iso:country":"IN",
    "ks:ks_name":"Manalimoola",
    "ks:ks_pop":520,
    "ks:ks_type":"HABITATION",
    "name:eng_x_preferred":[
        "Manalimoola"
    ],
    "wof:name":"Manalimoola",
    "wof:placetype":"locality",
    "wof:population":520
},
  "geometry": {"coordinates":[75.848933,11.814485],"type":"Point"}
}