{
  "type": "Feature",
  "properties": {
    "gn:admin1_code":"11",
    "gn:admin2_code":"23.0",
    "gn:asciiname":"Mangalwas",
    "gn:country_code":"IN",
    "gn:dem":1996,
    "gn:feature_class":"P",
    "gn:feature_code":"PPL",
    "gn:name":"Mangalw\u0101s",
    "gn:population":0,
    "gn:timezone":"Asia/Kolkata",
    "iso:country":"IN",
    "wof:name":"Mangalwas",
    "wof:placetype":"locality"
},
  "geometry": {"coordinates":[76.16271999999999,32.80939],"type":"Point"}
}