{
  "type": "Feature",
  "properties": {
    "gn:country":"IN",
    "gn:fcode":"PPL",
    "gn:population":21260,
    "iso:country":"IN",
    "name:ben_x_preferred":[
        "\u099b\u09be\u099f\u09be"
    ],
    "name:bpy_x_preferred":[
        "\u099b\u09be\u09a4\u09be"
    ],
    "name:ceb_x_preferred":[
        "Chh\u0101ta"
    ],
    "name:deu_x_preferred":[
        "Chhata"
    ],
    "name:eng_x_preferred":[
        "Chhata"
    ],
    "name:fra_x_preferred":[
        "Chhata"
    ],
    "name:guj_x_preferred":[
        "\u0a9b\u0abe\u0aa4\u0abe"
    ],
    "name:ita_x_preferred":[
        "Chhata"
    ],
    "name:jpn_x_preferred":[
        "\u30c1\u30e3\u30bf"
    ],
    "name:kan_x_preferred":[
        "\u0c9b\u0ca0\u0cbe"
    ],
    "name:kor_x_preferred":[
        "\ucc28\ud558\ud0c0"
    ],
    "name:mlg_x_preferred":[
        "Chhata"
    ],
    "name:msa_x_preferred":[
        "Chhata"
    ],
    "name:nan_x_preferred":[
        "Chhata"
    ],
    "name:new_x_preferred":[
        "\u091b\u093e\u0924\u093e"
    ],
    "name:nld_x_preferred":[
        "Chhata"
    ],
    "name:pol_x_preferred":[
        "Chhata"
    ],
    "name:por_x_preferred":[
        "Chhata"
    ],
    "name:rus_x_preferred":[
        "\u0427\u0445\u0430\u0442\u0430"
    ],
    "name:spa_x_preferred":[
        "Chhata"
    ],
    "name:swe_x_preferred":[
        "Chh\u0101ta"
    ],
    "name:tam_x_preferred":[
        "\u0b9a\u0ba4\u0bbe"
    ],
    "name:tel_x_preferred":[
        "\u0c1b\u0c20"
    ],
    "name:urd_x_preferred":[
        "\u0686\u06be\u062a\u06c1"
    ],
    "name:vie_x_preferred":[
        "Chhata"
    ],
    "name:zho_x_preferred":[
        "\u6070\u5854"
    ],
    "qs:name":"Chh\u0101ta",
    "qs:photos_9r":0,
    "qs:photos_sr":0,
    "qs:pop_sr":"7",
    "wof:name":"Chh\u0101ta",
    "wof:placetype":"locality",
    "wof:population":21260
},
  "geometry": {"coordinates":[77.50945,27.72352],"type":"Point"}
}