{
  "type": "Feature",
  "properties": {
    "iso:country":"IN",
    "ks:ks_name":"Kattathamana",
    "ks:ks_pop":523,
    "ks:ks_type":"HABITATION",
    "name:eng_x_preferred":[
        "Kattathamana"
    ],
    "wof:name":"Kattathamana",
    "wof:placetype":"locality",
    "wof:population":523
},
  "geometry": {"coordinates":[75.003748,12.682079],"type":"Point"}
}