{
  "type": "Feature",
  "properties": {
    "gn:admin1_code":"34.0",
    "gn:admin2_code":"231.0",
    "gn:asciiname":"Nurpur",
    "gn:country_code":"IN",
    "gn:dem":57,
    "gn:feature_class":"P",
    "gn:feature_code":"PPL",
    "gn:name":"Nurpur",
    "gn:population":0,
    "gn:timezone":"Asia/Kolkata",
    "iso:country":"IN",
    "name:ceb_x_preferred":[
        "Nurpur"
    ],
    "name:swe_x_preferred":[
        "Nurpur"
    ],
    "wof:name":"Nurpur",
    "wof:placetype":"locality"
},
  "geometry": {"coordinates":[84.59302,25.68821],"type":"Point"}
}