{
  "type": "Feature",
  "properties": {
    "iso:country":"IN",
    "ks:ks_alt_nam":"Kantapada sasan",
    "ks:ks_name":"Kantapada Sasan",
    "ks:ks_pop":95,
    "ks:ks_type":"HABITATION",
    "name:eng_x_preferred":[
        "Kantapada Sasan"
    ],
    "wof:name":"Kantapada Sasan",
    "wof:placetype":"locality",
    "wof:population":95
},
  "geometry": {"coordinates":[86.751278,20.716513],"type":"Point"}
}