{
  "type": "Feature",
  "properties": {
    "gn:admin1_code":"7.0",
    "gn:admin2_code":"90.0",
    "gn:asciiname":"Khushk",
    "gn:country_code":"IN",
    "gn:dem":212,
    "gn:feature_class":"P",
    "gn:feature_code":"PPL",
    "gn:name":"Khushk",
    "gn:population":0,
    "gn:timezone":"Asia/Kolkata",
    "iso:country":"IN",
    "name:ara_x_preferred":[
        "\u0642\u0628\u064a\u0644\u0629 \u062e\u0648\u0634\u0643"
    ],
    "name:ben_bn_x_preferred":[
        "\u0996\u09c1\u09b8\u09cd\u0995"
    ],
    "name:ben_in_x_preferred":[
        "\u0996\u09c1\u09b8\u09cd\u0995"
    ],
    "name:guj_x_preferred":[
        "\u0a96\u0ac1\u0ab6\u0acd\u0a95"
    ],
    "name:hin_x_preferred":[
        "\u0916\u0941\u0936\u094d\u0915"
    ],
    "name:kan_x_preferred":[
        "\u0c96\u0cc1\u0cb7\u0ccd\u0c95\u0ccd"
    ],
    "name:mal_x_preferred":[
        "\u0d16\u0d41\u0d37\u0d4d\u0d15\u0d4d"
    ],
    "name:mar_x_preferred":[
        "\u0916\u0941\u0936\u094d\u0915"
    ],
    "name:pan_x_preferred":[
        "\u0a16\u0a41\u0a36\u0a15"
    ],
    "name:tam_x_preferred":[
        "\u0b95\u0bcc\u0bb7\u0bcd\u0b95\u0bcd"
    ],
    "name:tel_x_preferred":[
        "\u0c15\u0c41\u0c37\u0c4d\u0c15\u0c4d"
    ],
    "name:urd_x_preferred":[
        "\u062e\u0634\u06a9"
    ],
    "wof:name":"Khushk",
    "wof:placetype":"neighbourhood"
},
  "geometry": {"coordinates":[77.17641999999999,28.80223],"type":"Point"}
}