{
  "type": "Feature",
  "properties": {
    "gn:admin1_code":"7.0",
    "gn:admin2_code":"90.0",
    "gn:asciiname":"Khushk",
    "gn:country_code":"IN",
    "gn:dem":212,
    "gn:feature_class":"P",
    "gn:feature_code":"PPL",
    "gn:name":"Khushk",
    "gn:population":0,
    "gn:timezone":"Asia/Kolkata",
    "iso:country":"IN",
    "wof:name":"Khushk",
    "wof:placetype":"neighbourhood"
},
  "geometry": {"coordinates":[77.17641999999999,28.80223],"type":"Point"}
}