{
  "type": "Feature",
  "properties": {
    "gn:admin1_code":"34.0",
    "gn:admin2_code":"238.0",
    "gn:asciiname":"Dinnagar",
    "gn:country_code":"IN",
    "gn:dem":64,
    "gn:feature_class":"P",
    "gn:feature_code":"PPL",
    "gn:name":"D\u012bnnagar",
    "gn:population":0,
    "gn:timezone":"Asia/Kolkata",
    "iso:country":"IN",
    "ks:ks_alt_nam":"D\u012bnnagar",
    "ks:ks_name":"Dinnagar",
    "ks:ks_pop":4813,
    "ks:ks_type":"VILLAGE",
    "name:eng_x_preferred":[
        "Dinnagar"
    ],
    "name:eng_x_variant":[
        "D\u012bnnagar"
    ],
    "wof:name":"Dinnagar",
    "wof:placetype":"locality",
    "wof:population":4813
},
  "geometry": {"coordinates":[85.934029,24.996229],"type":"Point"}
}