{
  "type": "Feature",
  "properties": {
    "iso:country":"IN",
    "ks:ks_alt_nam":"Boda Amru thanda",
    "ks:ks_name":"Boda Amru Thanda",
    "ks:ks_pop":279,
    "ks:ks_type":"HABITATION",
    "ks:ks_uagg_main":0,
    "name:eng_x_preferred":[
        "Boda Amru Thanda"
    ],
    "wof:name":"Boda Amru Thanda",
    "wof:placetype":"neighbourhood",
    "wof:population":279
},
  "geometry": {"coordinates":[79.89810199999999,17.385594],"type":"Point"}
}