{
  "type": "Feature",
  "properties": {
    "iso:country":"IN",
    "ks:ks_name":"Dharhapatti Az Rakbe Chandip",
    "ks:ks_pop":345,
    "ks:ks_type":"VILLAGE",
    "name:eng_x_preferred":[
        "Dharhapatti Az Rakbe Chandip"
    ],
    "wof:name":"Dharhapatti Az Rakbe Chandip",
    "wof:placetype":"locality",
    "wof:population":345
},
  "geometry": {"coordinates":[86.863488,26.455242],"type":"Point"}
}