{
  "type": "Feature",
  "properties": {
    "gn:admin1_code":"40.0",
    "gn:admin2_code":"535",
    "gn:asciiname":"Kundapur",
    "gn:country_code":"IN",
    "gn:dem":575,
    "gn:feature_class":"P",
    "gn:feature_code":"PPL",
    "gn:name":"Kund\u0101pur",
    "gn:population":0,
    "gn:timezone":"Asia/Kolkata",
    "iso:country":"IN",
    "wof:name":"Kundapur",
    "wof:placetype":"locality"
},
  "geometry": {"coordinates":[78.29624,17.71043],"type":"Point"}
}