{
  "type": "Feature",
  "properties": {
    "gn:admin1_code":"36.0",
    "gn:admin2_code":"189.0",
    "gn:asciiname":"Ragarganj",
    "gn:country_code":"IN",
    "gn:dem":89,
    "gn:feature_class":"P",
    "gn:feature_code":"PPL",
    "gn:name":"Ragarganj",
    "gn:population":0,
    "gn:timezone":"Asia/Kolkata",
    "iso:country":"IN",
    "name:und_x_variant":[
        "Mah\u0101b\u012brganj"
    ],
    "wof:name":"Ragarganj",
    "wof:placetype":"locality"
},
  "geometry": {"coordinates":[83.78041999999998,26.87246],"type":"Point"}
}