{
  "type": "Feature",
  "properties": {
    "iso:country":"IN",
    "ks:ks_name":"Gadan Khera",
    "ks:ks_pop":472,
    "ks:ks_type":"VILLAGE",
    "name:eng_x_preferred":[
        "Gadan Khera"
    ],
    "wof:name":"Gadan Khera",
    "wof:placetype":"locality",
    "wof:population":472
},
  "geometry": {"coordinates":[80.140833,26.418889],"type":"Point"}
}