{
  "type": "Feature",
  "properties": {
    "iso:country":"IN",
    "ks:ks_name":"Sukhlahia",
    "ks:ks_pop":797,
    "ks:ks_type":"HABITATION",
    "name:eng_x_preferred":[
        "Sukhlahia"
    ],
    "wof:name":"Sukhlahia",
    "wof:placetype":"locality",
    "wof:population":797
},
  "geometry": {"coordinates":[84.954921,26.85411],"type":"Point"}
}