{
  "type": "Feature",
  "properties": {
    "gn:admin1_code":"28.0",
    "gn:admin2_code":"344",
    "gn:asciiname":"Goaltor",
    "gn:country_code":"IN",
    "gn:dem":74,
    "gn:feature_class":"P",
    "gn:feature_code":"PPL",
    "gn:name":"Go\u0101ltor",
    "gn:population":0,
    "gn:timezone":"Asia/Kolkata",
    "iso:country":"IN",
    "name:und_x_variant":[
        "Goaltore",
        "Go\u0101ltor"
    ],
    "wof:name":"Goaltor",
    "wof:placetype":"locality"
},
  "geometry": {"coordinates":[87.16964,22.70943],"type":"Point"}
}