{
  "type": "Feature",
  "properties": {
    "gn:admin1_code":"35",
    "gn:admin2_code":"428.0",
    "gn:asciiname":"Achalpura",
    "gn:country_code":"IN",
    "gn:dem":454,
    "gn:feature_class":"P",
    "gn:feature_code":"PPL",
    "gn:name":"Achalpura",
    "gn:population":0,
    "gn:timezone":"Asia/Kolkata",
    "iso:country":"IN",
    "ks:ks_name":"Achalpura",
    "ks:ks_pop":98,
    "ks:ks_type":"VILLAGE",
    "name:eng_x_preferred":[
        "Achalpura"
    ],
    "wof:name":"Achalpura",
    "wof:placetype":"locality",
    "wof:population":98
},
  "geometry": {"coordinates":[79.52923699999999,24.265954],"type":"Point"}
}