{
  "type": "Feature",
  "properties": {
    "gn:admin1_code":"36",
    "gn:admin2_code":"163.0",
    "gn:asciiname":"Sehu",
    "gn:country_code":"IN",
    "gn:dem":144,
    "gn:feature_class":"P",
    "gn:feature_code":"PPL",
    "gn:name":"Sehu",
    "gn:population":0,
    "gn:timezone":"Asia/Kolkata",
    "iso:country":"IN",
    "name:und_x_variant":[
        "P\u016bran Purwa"
    ],
    "wof:name":"Sehu",
    "wof:placetype":"neighbourhood"
},
  "geometry": {"coordinates":[79.71569,26.72724],"type":"Point"}
}