{
  "type": "Feature",
  "properties": {
    "gn:admin1_code":"39.0",
    "gn:admin2_code":"63.0",
    "gn:asciiname":"Baera",
    "gn:country_code":"IN",
    "gn:dem":1531,
    "gn:feature_class":"P",
    "gn:feature_code":"PPL",
    "gn:name":"Baera",
    "gn:population":0,
    "gn:timezone":"Asia/Kolkata",
    "iso:country":"IN",
    "wof:name":"Baera",
    "wof:placetype":"locality"
},
  "geometry": {"coordinates":[79.88934999999999,29.89689000000001],"type":"Point"}
}