{
  "type": "Feature",
  "properties": {
    "iso:country":"IN",
    "ks:ks_name":"Duppullanka",
    "ks:ks_pop":1754,
    "ks:ks_type":"HABITATION",
    "name:eng_x_preferred":[
        "Duppullanka"
    ],
    "wof:name":"Duppullanka",
    "wof:placetype":"locality",
    "wof:population":1754
},
  "geometry": {"coordinates":[82.222612,16.646459],"type":"Point"}
}