{
  "type": "Feature",
  "properties": {
    "iso:country":"IN",
    "ks:ks_name":"Mayamari",
    "ks:ks_pop":930,
    "ks:ks_type":"VILLAGE",
    "ks:ks_uagg_main":0,
    "name:eng_x_preferred":[
        "Mayamari"
    ],
    "wof:name":"Mayamari",
    "wof:placetype":"neighbourhood",
    "wof:population":930
},
  "geometry": {"coordinates":[88.75632,25.22535],"type":"Point"}
}