{
  "type": "Feature",
  "properties": {
    "iso:country":"IN",
    "ks:ks_name":"Lohara",
    "ks:ks_pop":1324,
    "ks:ks_type":"HABITATION",
    "name:eng_x_preferred":[
        "Lohara"
    ],
    "wof:name":"Lohara",
    "wof:placetype":"locality",
    "wof:population":1324
},
  "geometry": {"coordinates":[83.02867999999999,24.905637],"type":"Point"}
}