{
  "type": "Feature",
  "properties": {
    "gn:admin1_code":"39.0",
    "gn:admin2_code":"64.0",
    "gn:asciiname":"Jamoli",
    "gn:country_code":"IN",
    "gn:dem":1066,
    "gn:feature_class":"P",
    "gn:feature_code":"PPL",
    "gn:name":"Jamoli",
    "gn:population":0,
    "gn:timezone":"Asia/Kolkata",
    "iso:country":"IN",
    "ks:ks_name":"Jamoli",
    "ks:ks_type":"VILLAGE",
    "name:eng_x_preferred":[
        "Jamoli"
    ],
    "wof:name":"Jamoli",
    "wof:placetype":"locality"
},
  "geometry": {"coordinates":[79.309974,29.731984],"type":"Point"}
}