{
  "type": "Feature",
  "properties": {
    "gn:admin1_code":"35.0",
    "gn:admin2_code":"457.0",
    "gn:asciiname":"Amgaon",
    "gn:country_code":"IN",
    "gn:dem":315,
    "gn:feature_class":"P",
    "gn:feature_code":"PPL",
    "gn:name":"\u0100mgaon",
    "gn:population":0,
    "gn:timezone":"Asia/Kolkata",
    "iso:country":"IN",
    "wof:name":"Amgaon",
    "wof:placetype":"locality"
},
  "geometry": {"coordinates":[80.17296,21.93317],"type":"Point"}
}