{
  "type": "Feature",
  "properties": {
    "iso:country":"IN",
    "ks:ks_alt_nam":"SAKAIDIPA",
    "ks:ks_name":"Sakaidipa",
    "ks:ks_pop":323,
    "ks:ks_type":"HABITATION",
    "name:eng_x_preferred":[
        "Sakaidipa"
    ],
    "wof:name":"Sakaidipa",
    "wof:placetype":"locality",
    "wof:population":323
},
  "geometry": {"coordinates":[83.86544600000001,23.107445],"type":"Point"}
}