{
  "type": "Feature",
  "properties": {
    "gn:admin1_code":"35",
    "gn:admin2_code":"437.0",
    "gn:asciiname":"Chandgarh",
    "gn:country_code":"IN",
    "gn:dem":535,
    "gn:feature_class":"P",
    "gn:feature_code":"PPL",
    "gn:name":"Ch\u0101ndgarh",
    "gn:population":0,
    "gn:timezone":"Asia/Kolkata",
    "iso:country":"IN",
    "wof:name":"Chandgarh",
    "wof:placetype":"locality"
},
  "geometry": {"coordinates":[76.34125999999998,23.2135],"type":"Point"}
}