{
  "type": "Feature",
  "properties": {
    "gn:admin1_code":"25.0",
    "gn:admin2_code":"605.0",
    "gn:asciiname":"Gudanagaram",
    "gn:country_code":"IN",
    "gn:dem":271,
    "gn:feature_class":"P",
    "gn:feature_code":"PPL",
    "gn:name":"G\u016bdanagaram",
    "gn:population":0,
    "gn:timezone":"Asia/Kolkata",
    "iso:country":"IN",
    "ks:ks_name":"Goodanagaram",
    "ks:ks_pop":699,
    "ks:ks_type":"HABITATION",
    "ks:ks_uagg_main":0,
    "name:eng_x_preferred":[
        "Goodanagaram"
    ],
    "wof:name":"Goodanagaram",
    "wof:placetype":"neighbourhood",
    "wof:population":699
},
  "geometry": {"coordinates":[78.86953,12.910895],"type":"Point"}
}