{
  "type": "Feature",
  "properties": {
    "gn:admin1_code":"35",
    "gn:admin2_code":"424.0",
    "gn:asciiname":"Taparyan Hararan",
    "gn:country_code":"IN",
    "gn:dem":261,
    "gn:feature_class":"P",
    "gn:feature_code":"PPL",
    "gn:name":"Tapary\u0101n Har\u0101ran",
    "gn:population":0,
    "gn:timezone":"Asia/Kolkata",
    "iso:country":"IN",
    "wof:name":"Taparyan Hararan",
    "wof:placetype":"locality"
},
  "geometry": {"coordinates":[78.64008000000003,25.23637],"type":"Point"}
}