{
  "type": "Feature",
  "properties": {
    "gn:admin1_code":"35",
    "gn:admin2_code":"424.0",
    "gn:asciiname":"Taparyan Hararan",
    "gn:country_code":"IN",
    "gn:dem":261,
    "gn:feature_class":"P",
    "gn:feature_code":"PPL",
    "gn:name":"Tapary\u0101n Har\u0101ran",
    "gn:population":0,
    "gn:timezone":"Asia/Kolkata",
    "iso:country":"IN",
    "ks:ks_name":"Tapariya Hadaran",
    "ks:ks_pop":168,
    "ks:ks_type":"VILLAGE",
    "name:eng_x_preferred":[
        "Tapariya Hadaran"
    ],
    "name:eng_x_variant":[
        "Taparyan Hararan"
    ],
    "wof:name":"Tapariya Hadaran",
    "wof:placetype":"locality",
    "wof:population":168
},
  "geometry": {"coordinates":[78.640154,25.236201],"type":"Point"}
}