{
  "type": "Feature",
  "properties": {
    "iso:country":"IN",
    "ks:ks_name":"Umare",
    "ks:ks_pop":1275,
    "ks:ks_type":"VILLAGE",
    "name:eng_x_preferred":[
        "Umare"
    ],
    "wof:name":"Umare",
    "wof:placetype":"locality",
    "wof:population":1275
},
  "geometry": {"coordinates":[73.42362900000001,16.955581],"type":"Point"}
}