{
  "type": "Feature",
  "properties": {
    "iso:country":"IN",
    "ks:ks_name":"Ali-bend",
    "ks:ks_pop":121,
    "ks:ks_type":"HABITATION",
    "ks:ks_uagg_main":0,
    "name:eng_x_preferred":[
        "Ali-bend"
    ],
    "wof:name":"Ali-bend",
    "wof:placetype":"neighbourhood",
    "wof:population":121
},
  "geometry": {"coordinates":[74.010372,18.854779],"type":"Point"}
}