{
  "type": "Feature",
  "properties": {
    "iso:country":"IN",
    "ks:ks_name":"Shekhan Pur",
    "ks:ks_pop":1252,
    "ks:ks_type":"HABITATION",
    "name:eng_x_preferred":[
        "Shekhan Pur"
    ],
    "wof:name":"Shekhan Pur",
    "wof:placetype":"locality",
    "wof:population":1252
},
  "geometry": {"coordinates":[80.249346,27.119755],"type":"Point"}
}