{
  "type": "Feature",
  "properties": {
    "gn:admin1_code":"24.0",
    "gn:admin2_code":"128.0",
    "gn:asciiname":"Kusha",
    "gn:country_code":"IN",
    "gn:dem":249,
    "gn:feature_class":"P",
    "gn:feature_code":"PPL",
    "gn:name":"Kusha",
    "gn:population":0,
    "gn:timezone":"Asia/Kolkata",
    "iso:country":"IN",
    "name:ceb_x_preferred":[
        "Kusha"
    ],
    "name:deu_x_preferred":[
        "Kusha"
    ],
    "name:fra_x_preferred":[
        "Kusha"
    ],
    "name:rus_x_preferred":[
        "\u041a\u0443\u0448\u0430"
    ],
    "name:swe_x_preferred":[
        "Kusha"
    ],
    "wof:name":"Kusha",
    "wof:placetype":"locality"
},
  "geometry": {"coordinates":[76.4222,25.31782],"type":"Point"}
}