{
  "type": "Feature",
  "properties": {
    "iso:country":"IN",
    "ks:ks_name":"Naditola",
    "ks:ks_pop":272,
    "ks:ks_type":"HABITATION",
    "name:eng_x_preferred":[
        "Naditola"
    ],
    "wof:name":"Naditola",
    "wof:placetype":"locality",
    "wof:population":272
},
  "geometry": {"coordinates":[84.81101,22.187063],"type":"Point"}
}