{
  "type": "Feature",
  "properties": {
    "iso:country":"IN",
    "ks:ks_name":"Paldi",
    "ks:ks_pop":404,
    "ks:ks_type":"VILLAGE",
    "name:eng_x_preferred":[
        "Paldi"
    ],
    "wof:name":"Paldi",
    "wof:placetype":"locality",
    "wof:population":404
},
  "geometry": {"coordinates":[72.576779,22.370303],"type":"Point"}
}