{
  "type": "Feature",
  "properties": {
    "iso:country":"IN",
    "ks:ks_name":"Khas Jangal",
    "ks:ks_pop":113,
    "ks:ks_type":"VILLAGE",
    "name:eng_x_preferred":[
        "Khas Jangal"
    ],
    "wof:name":"Khas Jangal",
    "wof:placetype":"locality",
    "wof:population":113
},
  "geometry": {"coordinates":[87.12949399999999,22.039124],"type":"Point"}
}