{
  "type": "Feature",
  "properties": {
    "gn:admin1_code":"16",
    "gn:admin2_code":"503.0",
    "gn:asciiname":"Mardi",
    "gn:country_code":"IN",
    "gn:dem":392,
    "gn:feature_class":"P",
    "gn:feature_code":"PPL",
    "gn:name":"M\u0101rdi",
    "gn:population":0,
    "gn:timezone":"Asia/Kolkata",
    "iso:country":"IN",
    "name:bul_x_preferred":[
        "\u041c\u0430\u0440\u0434\u0438"
    ],
    "name:fra_x_preferred":[
        "Mardi"
    ],
    "name:por_x_preferred":[
        "Mardi"
    ],
    "wof:name":"Mardi",
    "wof:placetype":"locality"
},
  "geometry": {"coordinates":[77.92689,20.94066],"type":"Point"}
}