{
  "type": "Feature",
  "properties": {
    "gn:admin1_code":"39.0",
    "gn:admin2_code":"57.0",
    "gn:asciiname":"Gauchar",
    "gn:country_code":"IN",
    "gn:dem":944,
    "gn:feature_class":"P",
    "gn:feature_code":"PPL",
    "gn:name":"Gauchar",
    "gn:population":0,
    "gn:timezone":"Asia/Kolkata",
    "iso:country":"IN",
    "name:bpy_x_preferred":[
        "\u0997\u09cb\u099a\u09be\u09b0"
    ],
    "name:hin_x_preferred":[
        "\u0917\u094b\u091a\u0930"
    ],
    "name:ita_x_preferred":[
        "Gochar"
    ],
    "name:mlg_x_preferred":[
        "Gochar"
    ],
    "name:msa_x_preferred":[
        "Gochar"
    ],
    "name:new_x_preferred":[
        "\u0917\u094b\u091a\u0930"
    ],
    "name:nld_x_preferred":[
        "Gochar"
    ],
    "name:pol_x_preferred":[
        "Gochar"
    ],
    "name:por_x_preferred":[
        "Gochar"
    ],
    "name:vie_x_preferred":[
        "Gochar"
    ],
    "name:zho_x_preferred":[
        "\u6208\u6070\u5c14"
    ],
    "wof:name":"Gauchar",
    "wof:placetype":"locality"
},
  "geometry": {"coordinates":[79.17645,30.27763],"type":"Point"}
}