{
  "type": "Feature",
  "properties": {
    "gn:admin1_code":"39.0",
    "gn:admin2_code":"57.0",
    "gn:asciiname":"Gauchar",
    "gn:country_code":"IN",
    "gn:dem":944,
    "gn:feature_class":"P",
    "gn:feature_code":"PPL",
    "gn:name":"Gauchar",
    "gn:population":0,
    "gn:timezone":"Asia/Kolkata",
    "iso:country":"IN",
    "name:und_x_variant":[
        "Gochar"
    ],
    "wof:name":"Gauchar",
    "wof:placetype":"locality"
},
  "geometry": {"coordinates":[79.17645,30.27763],"type":"Point"}
}