{
  "type": "Feature",
  "properties": {
    "gn:admin1_code":"19.0",
    "gn:admin2_code":"574.0",
    "gn:asciiname":"Yallenahalli",
    "gn:country_code":"IN",
    "gn:dem":908,
    "gn:feature_class":"P",
    "gn:feature_code":"PPL",
    "gn:name":"Yallenahalli",
    "gn:population":0,
    "gn:timezone":"Asia/Kolkata",
    "iso:country":"IN",
    "wof:name":"Yallenahalli",
    "wof:placetype":"neighbourhood"
},
  "geometry": {"coordinates":[76.11060000000001,12.72088],"type":"Point"}
}