{
  "type": "Feature",
  "properties": {
    "iso:country":"IN",
    "ks:ks_name":"Guravwadi",
    "ks:ks_pop":50,
    "ks:ks_type":"HABITATION",
    "name:eng_x_preferred":[
        "Guravwadi"
    ],
    "wof:name":"Guravwadi",
    "wof:placetype":"locality",
    "wof:population":50
},
  "geometry": {"coordinates":[73.323403,17.588944],"type":"Point"}
}