{
  "type": "Feature",
  "properties": {
    "iso:country":"IN",
    "ks:ks_name":"Haralur",
    "ks:ks_pop":1186,
    "ks:ks_type":"VILLAGE",
    "ks:ks_uagg_main":0,
    "name:eng_x_preferred":[
        "Haralur"
    ],
    "wof:name":"Haralur",
    "wof:placetype":"neighbourhood",
    "wof:population":1186
},
  "geometry": {"coordinates":[77.662972,12.900399],"type":"Point"}
}