{
  "type": "Feature",
  "properties": {
    "gn:admin1_code":"38",
    "gn:admin2_code":"358.0",
    "gn:asciiname":"Patkhaulia",
    "gn:country_code":"IN",
    "gn:dem":158,
    "gn:feature_class":"P",
    "gn:feature_code":"PPL",
    "gn:name":"Patkhaulia",
    "gn:population":0,
    "gn:timezone":"Asia/Kolkata",
    "iso:country":"IN",
    "ks:ks_name":"Patkhaulia",
    "ks:ks_pop":277,
    "ks:ks_type":"VILLAGE",
    "ks:ks_uagg_main":0,
    "name:eng_x_preferred":[
        "Patkhaulia"
    ],
    "wof:name":"Patkhaulia",
    "wof:placetype":"neighbourhood",
    "wof:population":277
},
  "geometry": {"coordinates":[83.910448,24.481101],"type":"Point"}
}