{
  "type": "Feature",
  "properties": {
    "iso:country":"IN",
    "ks:ks_name":"Teja Purwa",
    "ks:ks_pop":255,
    "ks:ks_type":"HABITATION",
    "name:eng_x_preferred":[
        "Teja Purwa"
    ],
    "wof:name":"Teja Purwa",
    "wof:placetype":"locality",
    "wof:population":255
},
  "geometry": {"coordinates":[80.29723799999999,27.314352],"type":"Point"}
}