{
  "type": "Feature",
  "properties": {
    "gn:admin1_code":"36.0",
    "gn:admin2_code":"143.0",
    "gn:asciiname":"Dohora",
    "gn:country_code":"IN",
    "gn:dem":190,
    "gn:feature_class":"P",
    "gn:feature_code":"PPL",
    "gn:name":"Dohora",
    "gn:population":0,
    "gn:timezone":"Asia/Kolkata",
    "iso:country":"IN",
    "wof:name":"Dohora",
    "wof:placetype":"locality"
},
  "geometry": {"coordinates":[77.80329999999999,27.84312000000001],"type":"Point"}
}