{
  "type": "Feature",
  "properties": {
    "iso:country":"IN",
    "ks:ks_name":"Daunu",
    "ks:ks_pop":464,
    "ks:ks_type":"HABITATION",
    "name:eng_x_preferred":[
        "Daunu"
    ],
    "wof:name":"Daunu",
    "wof:placetype":"locality",
    "wof:population":464
},
  "geometry": {"coordinates":[80.038425,29.883647],"type":"Point"}
}