{
  "type": "Feature",
  "properties": {
    "iso:country":"IN",
    "ks:ks_name":"Dihwa",
    "ks:ks_pop":841,
    "ks:ks_type":"HABITATION",
    "name:eng_x_preferred":[
        "Dihwa"
    ],
    "wof:name":"Dihwa",
    "wof:placetype":"locality",
    "wof:population":841
},
  "geometry": {"coordinates":[82.29397,24.945174],"type":"Point"}
}