{
  "type": "Feature",
  "properties": {
    "gn:admin1_code":"34",
    "gn:admin2_code":"233.0",
    "gn:asciiname":"Atara",
    "gn:country_code":"IN",
    "gn:dem":382,
    "gn:feature_class":"P",
    "gn:feature_code":"PPL",
    "gn:name":"Atara",
    "gn:population":0,
    "gn:timezone":"Asia/Kolkata",
    "iso:country":"IN",
    "name:deu_x_preferred":[
        "Atara"
    ],
    "name:rus_x_preferred":[
        "\u0410\u0442\u0430\u0440\u0430"
    ],
    "wof:name":"Atara",
    "wof:placetype":"locality"
},
  "geometry": {"coordinates":[83.5172,24.80282],"type":"Point"}
}