{
  "type": "Feature",
  "properties": {
    "iso:country":"IN",
    "ks:ks_alt_nam":"Rani kura",
    "ks:ks_name":"Rani Kura",
    "ks:ks_pop":494,
    "ks:ks_type":"HABITATION",
    "name:eng_x_preferred":[
        "Rani Kura"
    ],
    "wof:name":"Rani Kura",
    "wof:placetype":"locality",
    "wof:population":494
},
  "geometry": {"coordinates":[85.902367,23.896634],"type":"Point"}
}