{
  "type": "Feature",
  "properties": {
    "gn:admin1_code":"34.0",
    "gn:admin2_code":"231.0",
    "gn:asciiname":"Labna",
    "gn:country_code":"IN",
    "gn:dem":86,
    "gn:feature_class":"P",
    "gn:feature_code":"PPL",
    "gn:name":"Labna",
    "gn:population":0,
    "gn:timezone":"Asia/Kolkata",
    "iso:country":"IN",
    "name:cat_x_preferred":[
        "Labn\u00e1"
    ],
    "name:deu_x_preferred":[
        "Labn\u00e1"
    ],
    "name:epo_x_preferred":[
        "Labn\u00e1"
    ],
    "name:fra_x_preferred":[
        "Labn\u00e1"
    ],
    "name:hun_x_preferred":[
        "Labn\u00e1"
    ],
    "name:ind_x_preferred":[
        "Labna"
    ],
    "name:ita_x_preferred":[
        "Labn\u00e1"
    ],
    "name:kat_x_preferred":[
        "\u10da\u10d0\u10d1\u10dc\u10d0"
    ],
    "name:mkd_x_preferred":[
        "\u041b\u0430\u0431\u043d\u0430"
    ],
    "name:nld_x_preferred":[
        "Labn\u00e1"
    ],
    "name:por_x_preferred":[
        "Labn\u00e1"
    ],
    "name:rus_x_preferred":[
        "\u041b\u0430\u0431\u043d\u0430"
    ],
    "name:spa_x_preferred":[
        "Labn\u00e1"
    ],
    "name:ukr_x_preferred":[
        "\u041b\u0430\u0431\u043d\u0430"
    ],
    "wof:name":"Labna",
    "wof:placetype":"locality"
},
  "geometry": {"coordinates":[84.44035,25.27896],"type":"Point"}
}