{
  "type": "Feature",
  "properties": {
    "gn:admin1_code":"9.0",
    "gn:admin2_code":"481",
    "gn:asciiname":"Janra",
    "gn:country_code":"IN",
    "gn:dem":66,
    "gn:feature_class":"P",
    "gn:feature_code":"PPL",
    "gn:name":"Janra",
    "gn:population":0,
    "gn:timezone":"Asia/Kolkata",
    "iso:country":"IN",
    "wof:name":"Janra",
    "wof:placetype":"locality"
},
  "geometry": {"coordinates":[71.69295,22.08467000000001],"type":"Point"}
}