{
  "type": "Feature",
  "properties": {
    "gn:admin1_code":"21.0",
    "gn:admin2_code":"388",
    "gn:asciiname":"Gaudagoth",
    "gn:country_code":"IN",
    "gn:dem":196,
    "gn:feature_class":"P",
    "gn:feature_code":"PPL",
    "gn:name":"Gaudagoth",
    "gn:population":0,
    "gn:timezone":"Asia/Kolkata",
    "iso:country":"IN",
    "wof:name":"Gaudagoth",
    "wof:placetype":"locality"
},
  "geometry": {"coordinates":[84.30060999999998,19.62295],"type":"Point"}
}