{
  "type": "Feature",
  "properties": {
    "iso:country":"IN",
    "ks:ks_name":"Kurkuria",
    "ks:ks_pop":234,
    "ks:ks_type":"HABITATION",
    "ks:ks_uagg_main":0,
    "name:eng_x_preferred":[
        "Kurkuria"
    ],
    "wof:name":"Kurkuria",
    "wof:placetype":"neighbourhood",
    "wof:population":234
},
  "geometry": {"coordinates":[91.942605,26.15631],"type":"Point"}
}