{
  "type": "Feature",
  "properties": {
    "gn:admin1_code":"39.0",
    "gn:admin2_code":"62.0",
    "gn:asciiname":"Bhainsath",
    "gn:country_code":"IN",
    "gn:dem":1289,
    "gn:feature_class":"P",
    "gn:feature_code":"PPL",
    "gn:name":"Bhains\u0101th",
    "gn:population":0,
    "gn:timezone":"Asia/Kolkata",
    "iso:country":"IN",
    "ks:ks_name":"Bhainsat",
    "ks:ks_pop":66,
    "ks:ks_type":"VILLAGE",
    "name:eng_x_preferred":[
        "Bhainsat"
    ],
    "name:eng_x_variant":[
        "Bhainsath"
    ],
    "wof:name":"Bhainsat",
    "wof:placetype":"locality",
    "wof:population":66
},
  "geometry": {"coordinates":[79.97147,29.703702],"type":"Point"}
}