{
  "type": "Feature",
  "properties": {
    "iso:country":"IN",
    "ks:ks_name":"Sidhdheshwar Khd",
    "ks:ks_pop":238,
    "ks:ks_type":"HABITATION",
    "name:eng_x_preferred":[
        "Sidhdheshwar Khd"
    ],
    "wof:name":"Sidhdheshwar Khd",
    "wof:placetype":"locality",
    "wof:population":238
},
  "geometry": {"coordinates":[73.213037,18.539636],"type":"Point"}
}