{
  "type": "Feature",
  "properties": {
    "gn:admin1_code":"19",
    "gn:admin2_code":"558.0",
    "gn:asciiname":"Bhimalkhed",
    "gn:country_code":"IN",
    "gn:dem":615,
    "gn:feature_class":"P",
    "gn:feature_code":"PPL",
    "gn:name":"Bh\u012bmalkhed",
    "gn:population":0,
    "gn:timezone":"Asia/Kolkata",
    "iso:country":"IN",
    "wof:name":"Bhimalkhed",
    "wof:placetype":"neighbourhood"
},
  "geometry": {"coordinates":[77.42694,17.66659],"type":"Point"}
}