{
  "type": "Feature",
  "properties": {
    "iso:country":"IN",
    "ks:ks_name":"Bhaliaganda",
    "ks:ks_pop":132,
    "ks:ks_type":"VILLAGE",
    "name:eng_x_preferred":[
        "Bhaliaganda"
    ],
    "wof:name":"Bhaliaganda",
    "wof:placetype":"locality",
    "wof:population":132
},
  "geometry": {"coordinates":[84.177066,19.342502],"type":"Point"}
}