{
  "type": "Feature",
  "properties": {
    "gn:admin1_code":"2.0",
    "gn:admin2_code":"543.0",
    "gn:asciiname":"Machivanipalem",
    "gn:country_code":"IN",
    "gn:dem":27,
    "gn:feature_class":"P",
    "gn:feature_code":"PPL",
    "gn:name":"Machiv\u0101nip\u0101lem",
    "gn:population":0,
    "gn:timezone":"Asia/Kolkata",
    "iso:country":"IN",
    "ks:ks_name":"Matchavanipalem",
    "ks:ks_pop":235,
    "ks:ks_type":"HABITATION",
    "ks:ks_uagg_main":0,
    "name:eng_x_preferred":[
        "Matchavanipalem"
    ],
    "wof:name":"Matchavanipalem",
    "wof:placetype":"neighbourhood",
    "wof:population":235
},
  "geometry": {"coordinates":[83.547639,18.067695],"type":"Point"}
}