{
  "type": "Feature",
  "properties": {
    "iso:country":"IN",
    "ks:ks_alt_nam":"Jiantan\u0101li",
    "ks:ks_name":"Jiantanali",
    "ks:ks_pop":431,
    "ks:ks_type":"VILLAGE",
    "name:eng_x_preferred":[
        "Jiantanali"
    ],
    "name:eng_x_variant":[
        "Jiantan\u0101li"
    ],
    "wof:name":"Jiantanali",
    "wof:placetype":"locality",
    "wof:population":431
},
  "geometry": {"coordinates":[84.54690100000001,20.918863],"type":"Point"}
}