{
  "type": "Feature",
  "properties": {
    "iso:country":"IN",
    "ks:ks_name":"Madhaoo",
    "ks:ks_pop":461,
    "ks:ks_type":"HABITATION",
    "name:eng_x_preferred":[
        "Madhaoo"
    ],
    "wof:name":"Madhaoo",
    "wof:placetype":"locality",
    "wof:population":461
},
  "geometry": {"coordinates":[80.76294300000001,24.454235],"type":"Point"}
}