{
  "type": "Feature",
  "properties": {
    "gn:admin1_code":"28",
    "gn:admin2_code":"335.0",
    "gn:asciiname":"Saktigarh",
    "gn:country_code":"IN",
    "gn:dem":30,
    "gn:feature_class":"P",
    "gn:feature_code":"PPL",
    "gn:name":"Saktigarh",
    "gn:population":0,
    "gn:timezone":"Asia/Kolkata",
    "iso:country":"IN",
    "wof:name":"Saktigarh",
    "wof:placetype":"locality"
},
  "geometry": {"coordinates":[87.97336999999997,23.20898],"type":"Point"}
}