{
  "type": "Feature",
  "properties": {
    "gn:admin1_code":"16",
    "gn:admin2_code":"513.0",
    "gn:asciiname":"Katkarwadi",
    "gn:country_code":"IN",
    "gn:dem":457,
    "gn:feature_class":"P",
    "gn:feature_code":"PPL",
    "gn:name":"K\u0101tkarw\u0101di",
    "gn:population":0,
    "gn:timezone":"Asia/Kolkata",
    "iso:country":"IN",
    "wof:name":"Katkarwadi",
    "wof:placetype":"locality"
},
  "geometry": {"coordinates":[76.71047,18.81392],"type":"Point"}
}