{
  "type": "Feature",
  "properties": {
    "iso:country":"IN",
    "ks:ks_alt_nam":"GOBRE PURWA",
    "ks:ks_name":"Gobre Purwa",
    "ks:ks_pop":108,
    "ks:ks_type":"HABITATION",
    "ks:ks_uagg_main":0,
    "name:eng_x_preferred":[
        "Gobre Purwa"
    ],
    "wof:name":"Gobre Purwa",
    "wof:placetype":"neighbourhood",
    "wof:population":108
},
  "geometry": {"coordinates":[81.702692,27.372477],"type":"Point"}
}