{
  "type": "Feature",
  "properties": {
    "iso:country":"IN",
    "ks:ks_name":"Hadakho",
    "ks:ks_pop":665,
    "ks:ks_type":"VILLAGE",
    "name:eng_x_preferred":[
        "Hadakho"
    ],
    "wof:name":"Hadakho",
    "wof:placetype":"locality",
    "wof:population":665
},
  "geometry": {"coordinates":[74.82460399999999,23.259204],"type":"Point"}
}