{
  "type": "Feature",
  "properties": {
    "gn:admin1_code":"16",
    "gn:admin2_code":"524.0",
    "gn:asciiname":"Sirur Tajband",
    "gn:country_code":"IN",
    "gn:dem":544,
    "gn:feature_class":"P",
    "gn:feature_code":"PPL",
    "gn:name":"Sir\u016br T\u0101jband",
    "gn:population":0,
    "gn:timezone":"Asia/Kolkata",
    "iso:country":"IN",
    "name:und_x_variant":[
        "Sir\u016br T\u0101jband"
    ],
    "wof:name":"Sirur Tajband",
    "wof:placetype":"locality"
},
  "geometry": {"coordinates":[76.96951999999997,18.63156],"type":"Point"}
}