{
  "type": "Feature",
  "properties": {
    "iso:country":"IN",
    "ks:ks_alt_nam":"Mela theru",
    "ks:ks_name":"Mela Theru",
    "ks:ks_pop":175,
    "ks:ks_type":"HABITATION",
    "name:eng_x_preferred":[
        "Mela Theru"
    ],
    "wof:name":"Mela Theru",
    "wof:placetype":"locality",
    "wof:population":175
},
  "geometry": {"coordinates":[79.71155,10.619592],"type":"Point"}
}