{
  "type": "Feature",
  "properties": {
    "gn:admin1_code":"10.0",
    "gn:admin2_code":"070",
    "gn:asciiname":"Jalubi",
    "gn:country_code":"IN",
    "gn:dem":268,
    "gn:feature_class":"P",
    "gn:feature_code":"PPL",
    "gn:name":"Jalubi",
    "gn:population":0,
    "gn:timezone":"Asia/Kolkata",
    "iso:country":"IN",
    "wof:name":"Jalubi",
    "wof:placetype":"locality"
},
  "geometry": {"coordinates":[76.95399999999999,30.17578],"type":"Point"}
}