{
  "type": "Feature",
  "properties": {
    "iso:country":"IN",
    "ks:ks_name":"Bhunihat",
    "ks:ks_pop":4770,
    "ks:ks_type":"VILLAGE",
    "ks:ks_uagg_main":0,
    "name:eng_x_preferred":[
        "Bhunihat"
    ],
    "wof:name":"Bhunihat",
    "wof:placetype":"neighbourhood",
    "wof:population":4770
},
  "geometry": {"coordinates":[88.20695600000001,24.297568],"type":"Point"}
}