{
  "type": "Feature",
  "properties": {
    "gn:admin1_code":"36.0",
    "gn:admin2_code":"135.0",
    "gn:asciiname":"Bhatauli",
    "gn:country_code":"IN",
    "gn:dem":207,
    "gn:feature_class":"P",
    "gn:feature_code":"PPL",
    "gn:name":"Bhatauli",
    "gn:population":0,
    "gn:timezone":"Asia/Kolkata",
    "iso:country":"IN",
    "name:bih_x_preferred":[
        "\u092d\u091f\u094c\u0932\u0940"
    ],
    "name:ceb_x_preferred":[
        "Bhatauli"
    ],
    "name:msa_x_preferred":[
        "Bhatauli"
    ],
    "name:nep_x_preferred":[
        "\u092d\u091f\u094c\u0932\u0940"
    ],
    "name:new_x_preferred":[
        "\u092d\u091f\u094c\u0932\u0940"
    ],
    "name:pol_x_preferred":[
        "Bhatauli"
    ],
    "wof:name":"Bhatauli",
    "wof:placetype":"locality"
},
  "geometry": {"coordinates":[78.7255,28.90109],"type":"Point"}
}