{
  "type": "Feature",
  "properties": {
    "gn:admin1_code":"16",
    "gn:admin2_code":"509.0",
    "gn:asciiname":"Panoli Mendha",
    "gn:country_code":"IN",
    "gn:dem":243,
    "gn:feature_class":"P",
    "gn:feature_code":"PPL",
    "gn:name":"P\u0101noli Mendha",
    "gn:population":0,
    "gn:timezone":"Asia/Kolkata",
    "iso:country":"IN",
    "ks:ks_name":"Panholi Mendha",
    "ks:ks_pop":217,
    "ks:ks_type":"VILLAGE",
    "ks:ks_uagg_main":0,
    "name:eng_x_preferred":[
        "Panholi Mendha"
    ],
    "wof:name":"Panholi Mendha",
    "wof:placetype":"neighbourhood",
    "wof:population":217
},
  "geometry": {"coordinates":[79.76834100000001,20.61559],"type":"Point"}
}