{
  "type": "Feature",
  "properties": {
    "iso:country":"IN",
    "ks:ks_name":"Purbajoypara",
    "ks:ks_pop":124,
    "ks:ks_type":"HABITATION",
    "name:eng_x_preferred":[
        "Purbajoypara"
    ],
    "wof:name":"Purbajoypara",
    "wof:placetype":"locality",
    "wof:population":124
},
  "geometry": {"coordinates":[92.212439,24.153352],"type":"Point"}
}