{
  "type": "Feature",
  "properties": {
    "iso:country":"IN",
    "ks:ks_name":"Pande Purwa",
    "ks:ks_pop":591,
    "ks:ks_type":"HABITATION",
    "name:eng_x_preferred":[
        "Pande Purwa"
    ],
    "wof:name":"Pande Purwa",
    "wof:placetype":"locality",
    "wof:population":591
},
  "geometry": {"coordinates":[80.91221,28.159471],"type":"Point"}
}