{
  "type": "Feature",
  "properties": {
    "gn:admin1_code":"35",
    "gn:admin2_code":"462.0",
    "gn:asciiname":"Garhwa",
    "gn:country_code":"IN",
    "gn:dem":299,
    "gn:feature_class":"P",
    "gn:feature_code":"PPL",
    "gn:name":"Garhwa",
    "gn:population":0,
    "gn:timezone":"Asia/Kolkata",
    "iso:country":"IN",
    "ks:ks_name":"Gadhwa",
    "ks:ks_pop":273,
    "ks:ks_type":"VILLAGE",
    "name:ara_x_preferred":[
        "\u062c\u0627\u0631\u0647\u0648\u0627"
    ],
    "name:ara_x_variant":[
        "\u0645\u0646\u0637\u0642\u0629 \u062c\u0627\u0631\u0647\u0648\u0627"
    ],
    "name:ben_bn_x_preferred":[
        "\u0997\u09dc\u0993\u09df\u09be"
    ],
    "name:ben_in_x_preferred":[
        "\u0997\u09dc\u0993\u09df\u09be"
    ],
    "name:bih_x_preferred":[
        "\u0917\u0922\u093c\u0935\u093e"
    ],
    "name:bpy_x_preferred":[
        "\u0997\u09b0\u09b9\u09f1\u09be"
    ],
    "name:ceb_x_preferred":[
        "Garwa"
    ],
    "name:eng_x_preferred":[
        "Gadhwa"
    ],
    "name:eng_x_variant":[
        "Garhwa"
    ],
    "name:fra_x_preferred":[
        "Garhwa"
    ],
    "name:guj_x_preferred":[
        "\u0a97\u0ab0\u0acd\u0ab5\u0abe\u0ab9"
    ],
    "name:guj_x_variant":[
        "\u0a97\u0aa2\u0ab5\u0abe"
    ],
    "name:hin_x_preferred":[
        "\u0917\u095d\u0935\u093e"
    ],
    "name:hin_x_variant":[
        "\u0917\u0922\u093c\u0935\u093e"
    ],
    "name:ita_x_preferred":[
        "Garhwa"
    ],
    "name:kan_x_preferred":[
        "\u0c97\u0cb0\u0ccd\u0cb5\u0cbe"
    ],
    "name:mai_x_preferred":[
        "\u0917\u0922\u0935\u093e"
    ],
    "name:mal_x_preferred":[
        "\u0d17\u0d7c\u0d35"
    ],
    "name:mar_x_preferred":[
        "\u0917\u0922\u0935\u093e"
    ],
    "name:mlg_x_preferred":[
        "Garhwa"
    ],
    "name:msa_x_preferred":[
        "Garhwa"
    ],
    "name:nep_x_preferred":[
        "\u0917\u0922\u0935\u093e"
    ],
    "name:new_x_preferred":[
        "\u0917\u0930\u094d\u0935\u093e"
    ],
    "name:pan_x_preferred":[
        "\u0a17\u0a5c\u0a35\u0a3e"
    ],
    "name:san_x_preferred":[
        "\u0917\u0922\u0935\u093e"
    ],
    "name:spa_x_preferred":[
        "Garhwa"
    ],
    "name:swe_x_preferred":[
        "Garhwa"
    ],
    "name:tam_x_preferred":[
        "\u0b95\u0bb0\u0bcd\u0bb5\u0bbe"
    ],
    "name:tel_x_preferred":[
        "\u0c17\u0c3e\u0c30\u0c4d\u0c35\u0c3e"
    ],
    "name:urd_x_preferred":[
        "\u06af\u0691\u06be\u0648\u0627"
    ],
    "name:urd_x_variant":[
        "\u06af\u0631\u06c1\u0648\u0627"
    ],
    "name:vie_x_preferred":[
        "Garhwa"
    ],
    "name:zho_x_preferred":[
        "\u52a0\u5c14\u8d6b\u74e6"
    ],
    "wof:name":"Gadhwa",
    "wof:placetype":"locality",
    "wof:population":273
},
  "geometry": {"coordinates":[81.409638,24.302316],"type":"Point"}
}