{
  "type": "Feature",
  "properties": {
    "iso:country":"IN",
    "ks:ks_name":"Yusufpur",
    "ks:ks_pop":990,
    "ks:ks_type":"HABITATION",
    "name:eng_x_preferred":[
        "Yusufpur"
    ],
    "wof:name":"Yusufpur",
    "wof:placetype":"locality",
    "wof:population":990
},
  "geometry": {"coordinates":[80.93154199999999,26.130619],"type":"Point"}
}