{
  "type": "Feature",
  "properties": {
    "iso:country":"IN",
    "ks:ks_name":"Arwaliya",
    "ks:ks_pop":1011,
    "ks:ks_type":"VILLAGE",
    "name:eng_x_preferred":[
        "Arwaliya"
    ],
    "wof:name":"Arwaliya",
    "wof:placetype":"neighbourhood",
    "wof:population":1011
},
  "geometry": {"coordinates":[77.397049,23.341826],"type":"Point"}
}