{
  "type": "Feature",
  "properties": {
    "iso:country":"IN",
    "ks:ks_name":"Jaridih",
    "ks:ks_pop":146,
    "ks:ks_type":"VILLAGE",
    "ks:ks_uagg_main":0,
    "name:eng_x_preferred":[
        "Jaridih"
    ],
    "wof:name":"Jaridih",
    "wof:placetype":"neighbourhood",
    "wof:population":146
},
  "geometry": {"coordinates":[86.681016,24.027674],"type":"Point"}
}