{
  "type": "Feature",
  "properties": {
    "iso:country":"IN",
    "ks:ks_name":"Aanjrel",
    "ks:ks_pop":150,
    "ks:ks_type":"HABITATION",
    "name:eng_x_preferred":[
        "Aanjrel"
    ],
    "wof:name":"Aanjrel",
    "wof:placetype":"locality",
    "wof:population":150
},
  "geometry": {"coordinates":[81.180272,19.816538],"type":"Point"}
}