{
  "type": "Feature",
  "properties": {
    "iso:country":"IN",
    "ks:ks_name":"Kalasibhanga",
    "ks:ks_pop":348,
    "ks:ks_type":"VILLAGE",
    "name:eng_x_preferred":[
        "Kalasibhanga"
    ],
    "wof:name":"Kalasibhanga",
    "wof:placetype":"locality",
    "wof:population":348
},
  "geometry": {"coordinates":[86.328731,22.32296],"type":"Point"}
}