{
  "type": "Feature",
  "properties": {
    "gn:admin1_code":"35.0",
    "gn:admin2_code":"454.0",
    "gn:asciiname":"Jeonara",
    "gn:country_code":"IN",
    "gn:dem":438,
    "gn:feature_class":"P",
    "gn:feature_code":"PPL",
    "gn:name":"Jeon\u0101r\u0101",
    "gn:population":0,
    "gn:timezone":"Asia/Kolkata",
    "iso:country":"IN",
    "name:ori_x_preferred":[
        "\u0b1c\u0b47\u0b2c\u0b28\u0b3e\u0b30\u0b3e \u0b17\u0b4d\u0b30\u0b3e\u0b2e"
    ],
    "wof:name":"Jeonara",
    "wof:placetype":"locality"
},
  "geometry": {"coordinates":[80.07992,22.46521],"type":"Point"}
}