{
  "type": "Feature",
  "properties": {
    "gn:admin1_code":"35",
    "gn:admin2_code":"462.0",
    "gn:asciiname":"Sahijanha",
    "gn:country_code":"IN",
    "gn:dem":380,
    "gn:feature_class":"P",
    "gn:feature_code":"PPL",
    "gn:name":"Sahijanha",
    "gn:population":0,
    "gn:timezone":"Asia/Kolkata",
    "iso:country":"IN",
    "ks:ks_name":"Sahijanaha",
    "ks:ks_pop":1962,
    "ks:ks_type":"VILLAGE",
    "name:eng_x_preferred":[
        "Sahijanaha"
    ],
    "name:eng_x_variant":[
        "Sahijanha"
    ],
    "wof:name":"Sahijanaha",
    "wof:placetype":"locality",
    "wof:population":1962
},
  "geometry": {"coordinates":[81.741208,24.142088],"type":"Point"}
}