{
  "type": "Feature",
  "properties": {
    "iso:country":"IN",
    "ks:ks_alt_nam":"Bich garha",
    "ks:ks_name":"Bich Garha",
    "ks:ks_pop":96,
    "ks:ks_type":"HABITATION",
    "name:eng_x_preferred":[
        "Bich Garha"
    ],
    "wof:name":"Bich Garha",
    "wof:placetype":"locality",
    "wof:population":96
},
  "geometry": {"coordinates":[86.436318,24.457853],"type":"Point"}
}