{
  "type": "Feature",
  "properties": {
    "iso:country":"IN",
    "ks:ks_name":"Rajnagarmangalpur",
    "ks:ks_pop":1194,
    "ks:ks_type":"VILLAGE",
    "ks:ks_uagg_main":0,
    "name:eng_x_preferred":[
        "Rajnagarmangalpur"
    ],
    "wof:name":"Rajnagarmangalpur",
    "wof:placetype":"neighbourhood",
    "wof:population":1194
},
  "geometry": {"coordinates":[86.41908100000001,21.176775],"type":"Point"}
}