{
  "type": "Feature",
  "properties": {
    "gn:admin1_code":"35",
    "gn:admin2_code":"462.0",
    "gn:asciiname":"Dim",
    "gn:country_code":"IN",
    "gn:dem":347,
    "gn:feature_class":"P",
    "gn:feature_code":"PPL",
    "gn:name":"D\u012bm",
    "gn:population":0,
    "gn:timezone":"Asia/Kolkata",
    "iso:country":"IN",
    "name:bos_x_preferred":[
        "Dim"
    ],
    "name:ceb_x_preferred":[
        "Dim"
    ],
    "name:fra_x_preferred":[
        "Dim"
    ],
    "name:swe_x_preferred":[
        "Dim"
    ],
    "wof:name":"Dim",
    "wof:placetype":"locality"
},
  "geometry": {"coordinates":[81.56596999999999,24.09072],"type":"Point"}
}