{
  "type": "Feature",
  "properties": {
    "gn:admin1_code":"21.0",
    "gn:admin2_code":"396.0",
    "gn:asciiname":"Bonpadar",
    "gn:country_code":"IN",
    "gn:dem":849,
    "gn:feature_class":"P",
    "gn:feature_code":"PPL",
    "gn:name":"Bonpadar",
    "gn:population":0,
    "gn:timezone":"Asia/Kolkata",
    "iso:country":"IN",
    "wof:name":"Bonpadar",
    "wof:placetype":"locality"
},
  "geometry": {"coordinates":[83.06331,19.13228],"type":"Point"}
}