{
  "type": "Feature",
  "properties": {
    "iso:country":"IN",
    "ks:ks_name":"Chanaga",
    "ks:ks_pop":1778,
    "ks:ks_type":"VILLAGE",
    "name:eng_x_preferred":[
        "Chanaga"
    ],
    "wof:name":"Chanaga",
    "wof:placetype":"locality",
    "wof:population":1778
},
  "geometry": {"coordinates":[83.133706,24.053642],"type":"Point"}
}