{
  "type": "Feature",
  "properties": {
    "iso:country":"IN",
    "ks:ks_alt_nam":"BAISAI SONAPOSI",
    "ks:ks_name":"Baisai Sonaposi",
    "ks:ks_pop":942,
    "ks:ks_type":"HABITATION",
    "name:eng_x_preferred":[
        "Baisai Sonaposi"
    ],
    "wof:name":"Baisai Sonaposi",
    "wof:placetype":"locality",
    "wof:population":942
},
  "geometry": {"coordinates":[85.899258,22.084736],"type":"Point"}
}