{
  "type": "Feature",
  "properties": {
    "iso:country":"IN",
    "ks:ks_name":"Jeedichetlapalem",
    "ks:ks_pop":256,
    "ks:ks_type":"HABITATION",
    "name:eng_x_preferred":[
        "Jeedichetlapalem"
    ],
    "wof:name":"Jeedichetlapalem",
    "wof:placetype":"locality",
    "wof:population":256
},
  "geometry": {"coordinates":[80.28552500000001,15.707324],"type":"Point"}
}