{
  "type": "Feature",
  "properties": {
    "gn:admin1_code":"24.0",
    "gn:admin2_code":"127.0",
    "gn:asciiname":"Brijpura",
    "gn:country_code":"IN",
    "gn:dem":274,
    "gn:feature_class":"P",
    "gn:feature_code":"PPL",
    "gn:name":"Brijpura",
    "gn:population":0,
    "gn:timezone":"Asia/Kolkata",
    "iso:country":"IN",
    "ks:ks_name":"Brijpura",
    "ks:ks_pop":35,
    "ks:ks_type":"VILLAGE",
    "name:eng_x_preferred":[
        "Brijpura"
    ],
    "wof:name":"Brijpura",
    "wof:placetype":"locality",
    "wof:population":35
},
  "geometry": {"coordinates":[76.07765999999999,25.153783],"type":"Point"}
}