{
  "type": "Feature",
  "properties": {
    "gn:admin1_code":"36",
    "gn:admin2_code":"168.0",
    "gn:asciiname":"Bahpur",
    "gn:country_code":"IN",
    "gn:dem":155,
    "gn:feature_class":"P",
    "gn:feature_code":"PPL",
    "gn:name":"B\u0101hpur",
    "gn:population":0,
    "gn:timezone":"Asia/Kolkata",
    "iso:country":"IN",
    "ks:ks_alt_nam":"B\u0101hpur",
    "ks:ks_name":"Bahpur",
    "ks:ks_type":"VILLAGE",
    "ks:ks_uagg_main":0,
    "name:eng_x_preferred":[
        "Bahpur"
    ],
    "name:eng_x_variant":[
        "B\u0101hpur"
    ],
    "wof:name":"Bahpur",
    "wof:placetype":"neighbourhood"
},
  "geometry": {"coordinates":[79.61992499999999,25.670085],"type":"Point"}
}