{
  "type": "Feature",
  "properties": {
    "iso:country":"IN",
    "ks:ks_name":"12 SLD",
    "ks:ks_pop":398,
    "ks:ks_type":"VILLAGE",
    "name:eng_x_preferred":[
        "12 SLD"
    ],
    "wof:name":"12 SLD",
    "wof:placetype":"locality",
    "wof:population":398
},
  "geometry": {"coordinates":[73.236853,28.886008],"type":"Point"}
}