{
  "type": "Feature",
  "properties": {
    "iso:country":"IN",
    "ks:ks_name":"Bhandarwadi",
    "ks:ks_pop":213,
    "ks:ks_type":"HABITATION",
    "name:eng_x_preferred":[
        "Bhandarwadi"
    ],
    "wof:name":"Bhandarwadi",
    "wof:placetype":"locality",
    "wof:population":213
},
  "geometry": {"coordinates":[73.30111100000001,16.940556],"type":"Point"}
}