{
  "type": "Feature",
  "properties": {
    "gn:admin1_code":"19.0",
    "gn:admin2_code":"570.0",
    "gn:asciiname":"Kire Sigara",
    "gn:country_code":"IN",
    "gn:dem":918,
    "gn:feature_class":"P",
    "gn:feature_code":"PPL",
    "gn:name":"Kire Sigara",
    "gn:population":0,
    "gn:timezone":"Asia/Kolkata",
    "iso:country":"IN",
    "wof:name":"Kire Sigara",
    "wof:placetype":"locality"
},
  "geometry": {"coordinates":[75.71923000000002,13.03563],"type":"Point"}
}