{
  "type": "Feature",
  "properties": {
    "iso:country":"IN",
    "ks:ks_name":"Chiraikui",
    "ks:ks_pop":419,
    "ks:ks_type":"HABITATION",
    "name:eng_x_preferred":[
        "Chiraikui"
    ],
    "wof:name":"Chiraikui",
    "wof:placetype":"locality",
    "wof:population":419
},
  "geometry": {"coordinates":[72.983389,22.188111],"type":"Point"}
}