{
  "type": "Feature",
  "properties": {
    "gn:admin1_code":"2.0",
    "gn:admin2_code":"543.0",
    "gn:asciiname":"Panasapeddikonavalasa",
    "gn:country_code":"IN",
    "gn:dem":206,
    "gn:feature_class":"P",
    "gn:feature_code":"PPL",
    "gn:name":"Panas\u0101peddikonavalasa",
    "gn:population":0,
    "gn:timezone":"Asia/Kolkata",
    "iso:country":"IN",
    "wof:name":"Panasapeddikonavalasa",
    "wof:placetype":"locality"
},
  "geometry": {"coordinates":[83.14206999999998,18.52605],"type":"Point"}
}