{
  "type": "Feature",
  "properties": {
    "iso:country":"IN",
    "ks:ks_name":"Kankekarwadi",
    "ks:ks_pop":207,
    "ks:ks_type":"HABITATION",
    "name:eng_x_preferred":[
        "Kankekarwadi"
    ],
    "wof:name":"Kankekarwadi",
    "wof:placetype":"locality",
    "wof:population":207
},
  "geometry": {"coordinates":[73.63646,16.508863],"type":"Point"}
}