{
  "type": "Feature",
  "properties": {
    "gn:admin1_code":"35",
    "gn:admin2_code":"427.0",
    "gn:asciiname":"Karaiya",
    "gn:country_code":"IN",
    "gn:dem":463,
    "gn:feature_class":"P",
    "gn:feature_code":"PPL",
    "gn:name":"Kara\u012bya",
    "gn:population":0,
    "gn:timezone":"Asia/Kolkata",
    "iso:country":"IN",
    "name:ceb_x_preferred":[
        "Karaiya"
    ],
    "name:swe_x_preferred":[
        "Karaiya"
    ],
    "wof:name":"Karaiya",
    "wof:placetype":"locality"
},
  "geometry": {"coordinates":[78.63096,24.12949],"type":"Point"}
}