{
  "type": "Feature",
  "properties": {
    "iso:country":"IN",
    "ks:ks_name":"Dungridih2",
    "ks:ks_pop":235,
    "ks:ks_type":"HABITATION",
    "name:eng_x_preferred":[
        "Dungridih2"
    ],
    "wof:name":"Dungridih2",
    "wof:placetype":"locality",
    "wof:population":235
},
  "geometry": {"coordinates":[86.134629,22.968151],"type":"Point"}
}