{
  "type": "Feature",
  "properties": {
    "iso:country":"IN",
    "ks:ks_alt_nam":"TUIBAGLAI",
    "ks:ks_name":"Tuibaglai",
    "ks:ks_pop":500,
    "ks:ks_type":"HABITATION",
    "name:eng_x_preferred":[
        "Tuibaglai"
    ],
    "wof:name":"Tuibaglai",
    "wof:placetype":"locality",
    "wof:population":500
},
  "geometry": {"coordinates":[91.73252100000001,23.969875],"type":"Point"}
}