{
  "type": "Feature",
  "properties": {
    "iso:country":"IN",
    "ks:ks_alt_nam":"Dimirin\u0101li",
    "ks:ks_name":"Dimirinali",
    "ks:ks_type":"VILLAGE",
    "name:eng_x_preferred":[
        "Dimirinali"
    ],
    "name:eng_x_variant":[
        "Dimirin\u0101li"
    ],
    "wof:name":"Dimirinali",
    "wof:placetype":"locality"
},
  "geometry": {"coordinates":[85.15713599999999,21.200034],"type":"Point"}
}