{
  "type": "Feature",
  "properties": {
    "iso:country":"IN",
    "ks:ks_name":"Othareddyur",
    "ks:ks_pop":102,
    "ks:ks_type":"HABITATION",
    "name:eng_x_preferred":[
        "Othareddyur"
    ],
    "wof:name":"Othareddyur",
    "wof:placetype":"locality",
    "wof:population":102
},
  "geometry": {"coordinates":[78.31608,10.546902],"type":"Point"}
}