{
  "type": "Feature",
  "properties": {
    "iso:country":"IN",
    "ks:ks_alt_nam":"iriyan church",
    "ks:ks_name":"Iriyan Church",
    "ks:ks_pop":580,
    "ks:ks_type":"HABITATION",
    "ks:ks_uagg_main":0,
    "name:eng_x_preferred":[
        "Iriyan Church"
    ],
    "wof:name":"Iriyan Church",
    "wof:placetype":"neighbourhood",
    "wof:population":580
},
  "geometry": {"coordinates":[77.156882,9.978764],"type":"Point"}
}