{
  "type": "Feature",
  "properties": {
    "iso:country":"IN",
    "ks:ks_alt_nam":"choura",
    "ks:ks_name":"Choura",
    "ks:ks_pop":350,
    "ks:ks_type":"HABITATION",
    "name:eng_x_preferred":[
        "Choura"
    ],
    "wof:name":"Choura",
    "wof:placetype":"locality",
    "wof:population":350
},
  "geometry": {"coordinates":[86.556427,24.311914],"type":"Point"}
}