{
  "type": "Feature",
  "properties": {
    "gn:admin1_code":"39.0",
    "gn:admin2_code":"061",
    "gn:asciiname":"Godi Bari",
    "gn:country_code":"IN",
    "gn:dem":874,
    "gn:feature_class":"P",
    "gn:feature_code":"PPL",
    "gn:name":"Godi Bari",
    "gn:population":0,
    "gn:timezone":"Asia/Kolkata",
    "iso:country":"IN",
    "ks:ks_name":"Godi Badi",
    "ks:ks_pop":164,
    "ks:ks_type":"VILLAGE",
    "name:eng_x_preferred":[
        "Godi Badi"
    ],
    "name:eng_x_variant":[
        "Godi Bari"
    ],
    "wof:name":"Godi Badi",
    "wof:placetype":"locality",
    "wof:population":164
},
  "geometry": {"coordinates":[78.61063300000001,29.818948],"type":"Point"}
}