{
  "type": "Feature",
  "properties": {
    "gn:admin1_code":"39.0",
    "gn:admin2_code":"061",
    "gn:asciiname":"Godi Bari",
    "gn:country_code":"IN",
    "gn:dem":874,
    "gn:feature_class":"P",
    "gn:feature_code":"PPL",
    "gn:name":"Godi Bari",
    "gn:population":0,
    "gn:timezone":"Asia/Kolkata",
    "iso:country":"IN",
    "wof:name":"Godi Bari",
    "wof:placetype":"locality"
},
  "geometry": {"coordinates":[78.6109,29.81893],"type":"Point"}
}