{
  "type": "Feature",
  "properties": {
    "iso:country":"IN",
    "ks:ks_name":"Barrivanipeta",
    "ks:ks_pop":68,
    "ks:ks_type":"HABITATION",
    "name:eng_x_preferred":[
        "Barrivanipeta"
    ],
    "wof:name":"Barrivanipeta",
    "wof:placetype":"locality",
    "wof:population":68
},
  "geometry": {"coordinates":[84.514563,18.766746],"type":"Point"}
}