{
  "type": "Feature",
  "properties": {
    "iso:country":"IN",
    "ks:ks_name":"Bhandariwadi",
    "ks:ks_pop":259,
    "ks:ks_type":"HABITATION",
    "name:eng_x_preferred":[
        "Bhandariwadi"
    ],
    "wof:name":"Bhandariwadi",
    "wof:placetype":"locality",
    "wof:population":259
},
  "geometry": {"coordinates":[73.45786,16.212525],"type":"Point"}
}