{
  "type": "Feature",
  "properties": {
    "iso:country":"IN",
    "ks:ks_name":"Beltharwa",
    "ks:ks_pop":782,
    "ks:ks_type":"VILLAGE",
    "name:eng_x_preferred":[
        "Beltharwa"
    ],
    "wof:name":"Beltharwa",
    "wof:placetype":"locality",
    "wof:population":782
},
  "geometry": {"coordinates":[85.859516,24.714993],"type":"Point"}
}