{
  "type": "Feature",
  "properties": {
    "gn:admin1_code":"39.0",
    "gn:admin2_code":"66.0",
    "gn:asciiname":"Pipri",
    "gn:country_code":"IN",
    "gn:dem":1261,
    "gn:feature_class":"P",
    "gn:feature_code":"PPL",
    "gn:name":"Pipri",
    "gn:population":0,
    "gn:timezone":"Asia/Kolkata",
    "iso:country":"IN",
    "wof:name":"Pipri",
    "wof:placetype":"locality"
},
  "geometry": {"coordinates":[79.82630999999998,29.35303],"type":"Point"}
}