{
  "type": "Feature",
  "properties": {
    "iso:country":"IN",
    "ks:ks_name":"Srinibash Para",
    "ks:ks_pop":295,
    "ks:ks_type":"HABITATION",
    "name:eng_x_preferred":[
        "Srinibash Para"
    ],
    "wof:name":"Srinibash Para",
    "wof:placetype":"locality",
    "wof:population":295
},
  "geometry": {"coordinates":[91.927207,23.92562],"type":"Point"}
}