{
  "type": "Feature",
  "properties": {
    "iso:country":"IN",
    "ks:ks_name":"Karagadde",
    "ks:ks_pop":6,
    "ks:ks_type":"HABITATION",
    "name:eng_x_preferred":[
        "Karagadde"
    ],
    "wof:name":"Karagadde",
    "wof:placetype":"locality",
    "wof:population":6
},
  "geometry": {"coordinates":[74.822931,14.659986],"type":"Point"}
}