{
  "type": "Feature",
  "properties": {
    "iso:country":"IN",
    "ks:ks_name":"Ghodipada",
    "ks:ks_pop":168,
    "ks:ks_type":"HABITATION",
    "name:eng_x_preferred":[
        "Ghodipada"
    ],
    "wof:name":"Ghodipada",
    "wof:placetype":"locality",
    "wof:population":168
},
  "geometry": {"coordinates":[73.164534,19.836809],"type":"Point"}
}