{
  "type": "Feature",
  "properties": {
    "gn:admin1_code":"9.0",
    "gn:admin2_code":"492",
    "gn:asciiname":"Gijram",
    "gn:cc2":"IN",
    "gn:country_code":"IN",
    "gn:dem":31,
    "gn:feature_class":"P",
    "gn:feature_code":"PPL",
    "gn:name":"Gijram",
    "gn:population":0,
    "gn:timezone":"Asia/Kolkata",
    "iso:country":"IN",
    "name:und_x_variant":[
        "Gyram",
        "Gijram"
    ],
    "wof:name":"Gijram",
    "wof:placetype":"locality"
},
  "geometry": {"coordinates":[73.11667,21.48333],"type":"Point"}
}