{
  "type": "Feature",
  "properties": {
    "iso:country":"IN",
    "ks:ks_name":"Arazi Kasimpur",
    "ks:ks_pop":1635,
    "ks:ks_type":"VILLAGE",
    "ks:ks_uagg_main":0,
    "name:eng_x_preferred":[
        "Arazi Kasimpur"
    ],
    "wof:name":"Arazi Kasimpur",
    "wof:placetype":"neighbourhood",
    "wof:population":1635
},
  "geometry": {"coordinates":[88.235285,25.682417],"type":"Point"}
}