{
  "type": "Feature",
  "properties": {
    "iso:country":"IN",
    "ks:ks_name":"Kharayat",
    "ks:ks_pop":49,
    "ks:ks_type":"HABITATION",
    "name:eng_x_preferred":[
        "Kharayat"
    ],
    "wof:name":"Kharayat",
    "wof:placetype":"locality",
    "wof:population":49
},
  "geometry": {"coordinates":[80.205218,29.180537],"type":"Point"}
}