{
  "type": "Feature",
  "properties": {
    "iso:country":"IN",
    "ks:ks_name":"Chinthalagumpu",
    "ks:ks_pop":242,
    "ks:ks_type":"HABITATION",
    "name:eng_x_preferred":[
        "Chinthalagumpu"
    ],
    "wof:name":"Chinthalagumpu",
    "wof:placetype":"locality",
    "wof:population":242
},
  "geometry": {"coordinates":[80.79307300000001,17.770284],"type":"Point"}
}