{
  "type": "Feature",
  "properties": {
    "gn:admin1_code":"36",
    "gn:admin2_code":"178.0",
    "gn:asciiname":"Narharpur",
    "gn:country_code":"IN",
    "gn:dem":98,
    "gn:feature_class":"P",
    "gn:feature_code":"PPL",
    "gn:name":"Narharpur",
    "gn:population":0,
    "gn:timezone":"Asia/Kolkata",
    "iso:country":"IN",
    "ks:ks_name":"Naraharpur",
    "ks:ks_pop":1088,
    "ks:ks_type":"VILLAGE",
    "ks:ks_uagg_main":0,
    "name:eng_x_preferred":[
        "Naraharpur"
    ],
    "wof:name":"Naraharpur",
    "wof:placetype":"neighbourhood",
    "wof:population":1088
},
  "geometry": {"coordinates":[82.40065800000001,26.426053],"type":"Point"}
}