{
  "type": "Feature",
  "properties": {
    "gn:admin1_code":"19.0",
    "gn:admin2_code":"570.0",
    "gn:asciiname":"Tenginamane",
    "gn:country_code":"IN",
    "gn:dem":675,
    "gn:feature_class":"P",
    "gn:feature_code":"PPL",
    "gn:name":"Tenginamane",
    "gn:population":0,
    "gn:timezone":"Asia/Kolkata",
    "iso:country":"IN",
    "wof:name":"Tenginamane",
    "wof:placetype":"neighbourhood"
},
  "geometry": {"coordinates":[75.35516,13.44303],"type":"Point"}
}