{
  "type": "Feature",
  "properties": {
    "gn:admin1_code":"36.0",
    "gn:admin2_code":"158.0",
    "gn:asciiname":"Lal Gany",
    "gn:country_code":"IN",
    "gn:dem":118,
    "gn:feature_class":"P",
    "gn:feature_code":"PPL",
    "gn:name":"L\u0101l Gany",
    "gn:population":0,
    "gn:timezone":"Asia/Kolkata",
    "iso:country":"IN",
    "ks:ks_name":"Lalganj",
    "ks:ks_pop":337,
    "ks:ks_type":"HABITATION",
    "ks:ks_uagg_main":0,
    "name:eng_x_preferred":[
        "Lalganj"
    ],
    "wof:name":"Lalganj",
    "wof:placetype":"neighbourhood",
    "wof:population":337
},
  "geometry": {"coordinates":[81.17686500000001,26.047659],"type":"Point"}
}