{
  "type": "Feature",
  "properties": {
    "iso:country":"IN",
    "ks:ks_name":"Arjanpur",
    "ks:ks_pop":779,
    "ks:ks_type":"VILLAGE",
    "name:eng_x_preferred":[
        "Arjanpur"
    ],
    "wof:name":"Arjanpur",
    "wof:placetype":"locality",
    "wof:population":779
},
  "geometry": {"coordinates":[92.82380499999999,24.569566],"type":"Point"}
}