{
  "type": "Feature",
  "properties": {
    "gn:admin1_code":"11.0",
    "gn:admin2_code":"33.0",
    "gn:asciiname":"Mekrari",
    "gn:country_code":"IN",
    "gn:dem":1717,
    "gn:feature_class":"P",
    "gn:feature_code":"PPL",
    "gn:name":"Mekr\u0101ri",
    "gn:population":0,
    "gn:timezone":"Asia/Kolkata",
    "iso:country":"IN",
    "wof:name":"Mekrari",
    "wof:placetype":"locality"
},
  "geometry": {"coordinates":[77.72462,31.1498],"type":"Point"}
}