{
  "type": "Feature",
  "properties": {
    "iso:country":"IN",
    "ks:ks_name":"Suleman Tola",
    "ks:ks_pop":348,
    "ks:ks_type":"HABITATION",
    "ks:ks_uagg_main":0,
    "name:eng_x_preferred":[
        "Suleman Tola"
    ],
    "wof:name":"Suleman Tola",
    "wof:placetype":"neighbourhood",
    "wof:population":348
},
  "geometry": {"coordinates":[87.79555999999999,26.275848],"type":"Point"}
}