{
  "type": "Feature",
  "properties": {
    "gn:admin1_code":"24",
    "gn:admin2_code":"130.0",
    "gn:asciiname":"Sayra",
    "gn:country_code":"IN",
    "gn:dem":881,
    "gn:feature_class":"P",
    "gn:feature_code":"PPL",
    "gn:name":"S\u0101yra",
    "gn:population":0,
    "gn:timezone":"Asia/Kolkata",
    "iso:country":"IN",
    "name:und_x_variant":[
        "Saera",
        "Saira",
        "S\u0101yra"
    ],
    "wof:name":"Sayra",
    "wof:placetype":"locality"
},
  "geometry": {"coordinates":[73.41806,24.98283],"type":"Point"}
}