{
  "type": "Feature",
  "properties": {
    "iso:country":"IN",
    "ks:ks_name":"Payikolly",
    "ks:ks_pop":600,
    "ks:ks_type":"HABITATION",
    "name:eng_x_preferred":[
        "Payikolly"
    ],
    "wof:name":"Payikolly",
    "wof:placetype":"locality",
    "wof:population":600
},
  "geometry": {"coordinates":[76.206187,11.579306],"type":"Point"}
}