{
  "type": "Feature",
  "properties": {
    "iso:country":"IN",
    "ks:ks_name":"Dilpa Bustry",
    "ks:ks_pop":613,
    "ks:ks_type":"HABITATION",
    "name:eng_x_preferred":[
        "Dilpa Bustry"
    ],
    "wof:name":"Dilpa Bustry",
    "wof:placetype":"locality",
    "wof:population":613
},
  "geometry": {"coordinates":[88.087435,27.0763],"type":"Point"}
}