{
  "type": "Feature",
  "properties": {
    "gn:admin1_code":"36",
    "gn:admin2_code":"201.0",
    "gn:asciiname":"Muhammadnagar Bajhera",
    "gn:country_code":"IN",
    "gn:dem":162,
    "gn:feature_class":"P",
    "gn:feature_code":"PPL",
    "gn:name":"Muhammadnagar Bajher\u0101",
    "gn:population":0,
    "gn:timezone":"Asia/Kolkata",
    "iso:country":"IN",
    "wof:name":"Muhammadnagar Bajhera",
    "wof:placetype":"locality"
},
  "geometry": {"coordinates":[79.24276999999999,27.49647],"type":"Point"}
}