{
  "type": "Feature",
  "properties": {
    "gn:admin1_code":"19.0",
    "gn:admin2_code":"568.0",
    "gn:asciiname":"Kunaji",
    "gn:country_code":"IN",
    "gn:dem":601,
    "gn:feature_class":"P",
    "gn:feature_code":"PPL",
    "gn:name":"Kunaji",
    "gn:population":0,
    "gn:timezone":"Asia/Kolkata",
    "iso:country":"IN",
    "ks:ks_name":"Kunaji",
    "ks:ks_type":"VILLAGE",
    "name:eng_x_preferred":[
        "Kunaji"
    ],
    "wof:name":"Kunaji",
    "wof:placetype":"locality"
},
  "geometry": {"coordinates":[75.12184600000001,14.362747],"type":"Point"}
}