{
  "type": "Feature",
  "properties": {
    "gn:admin1_code":"11",
    "gn:admin2_code":"27.0",
    "gn:asciiname":"Bagra",
    "gn:country_code":"IN",
    "gn:dem":1375,
    "gn:feature_class":"P",
    "gn:feature_code":"PPL",
    "gn:name":"Bagra",
    "gn:population":0,
    "gn:timezone":"Asia/Kolkata",
    "iso:country":"IN",
    "name:bul_x_preferred":[
        "\u0411\u0430\u0433\u0440\u0430"
    ],
    "name:ceb_x_preferred":[
        "Bagra"
    ],
    "name:rus_x_preferred":[
        "\u0411\u0430\u0433\u0440\u0430"
    ],
    "name:swe_x_preferred":[
        "Bagra"
    ],
    "wof:name":"Bagra",
    "wof:placetype":"locality"
},
  "geometry": {"coordinates":[76.98224,31.3632],"type":"Point"}
}