{
  "type": "Feature",
  "properties": {
    "iso:country":"IN",
    "ks:ks_name":"Banjarwara",
    "ks:ks_pop":1400,
    "ks:ks_type":"VILLAGE",
    "ks:ks_uagg_main":0,
    "name:eng_x_preferred":[
        "Banjarwara"
    ],
    "wof:name":"Banjarwara",
    "wof:placetype":"neighbourhood",
    "wof:population":1400
},
  "geometry": {"coordinates":[73.44996399999999,23.982575],"type":"Point"}
}