{
  "type": "Feature",
  "properties": {
    "gn:admin1_code":"2.0",
    "gn:admin2_code":"542.0",
    "gn:asciiname":"Gatada",
    "gn:country_code":"IN",
    "gn:dem":145,
    "gn:feature_class":"P",
    "gn:feature_code":"PPL",
    "gn:name":"G\u0101t\u0101da",
    "gn:population":0,
    "gn:timezone":"Asia/Kolkata",
    "iso:country":"IN",
    "name:und_x_variant":[
        "G\u0101t\u0101da",
        "Srirangar\u0101jupuram"
    ],
    "wof:name":"Gatada",
    "wof:placetype":"locality"
},
  "geometry": {"coordinates":[83.50405000000001,18.41445],"type":"Point"}
}