{
  "type": "Feature",
  "properties": {
    "iso:country":"IN",
    "ks:ks_name":"Panikkankuppam",
    "ks:ks_pop":3546,
    "ks:ks_type":"VILLAGE",
    "ks:ks_uagg_main":0,
    "name:eng_x_preferred":[
        "Panikkankuppam"
    ],
    "wof:name":"Panikkankuppam",
    "wof:placetype":"locality",
    "wof:population":3546
},
  "geometry": {"coordinates":[79.541732,11.749971],"type":"Point"}
}