{
  "type": "Feature",
  "properties": {
    "gn:admin1_code":"28.0",
    "gn:admin2_code":"338",
    "gn:asciiname":"Baladbandh",
    "gn:country_code":"IN",
    "gn:dem":16,
    "gn:feature_class":"P",
    "gn:feature_code":"PPL",
    "gn:name":"Baladbandh",
    "gn:population":0,
    "gn:timezone":"Asia/Kolkata",
    "iso:country":"IN",
    "wof:name":"Baladbandh",
    "wof:placetype":"locality"
},
  "geometry": {"coordinates":[88.10972,22.86861],"type":"Point"}
}