{
  "type": "Feature",
  "properties": {
    "iso:country":"IN",
    "ks:ks_name":"Sonadhan Para",
    "ks:ks_pop":94,
    "ks:ks_type":"HABITATION",
    "name:eng_x_preferred":[
        "Sonadhan Para"
    ],
    "wof:name":"Sonadhan Para",
    "wof:placetype":"locality",
    "wof:population":94
},
  "geometry": {"coordinates":[91.63996,23.198464],"type":"Point"}
}