{
  "type": "Feature",
  "properties": {
    "iso:country":"IN",
    "ks:ks_alt_nam":"lodhan purwa",
    "ks:ks_name":"Lodhan Purwa",
    "ks:ks_pop":119,
    "ks:ks_type":"HABITATION",
    "ks:ks_uagg_main":0,
    "name:eng_x_preferred":[
        "Lodhan Purwa"
    ],
    "wof:name":"Lodhan Purwa",
    "wof:placetype":"neighbourhood",
    "wof:population":119
},
  "geometry": {"coordinates":[81.57311799999999,27.488192],"type":"Point"}
}