{
  "type": "Feature",
  "properties": {
    "gn:admin1_code":"12.0",
    "gn:admin2_code":"7.0",
    "gn:asciiname":"Talawala Dabbar",
    "gn:country_code":"IN",
    "gn:dem":1694,
    "gn:feature_class":"P",
    "gn:feature_code":"PPL",
    "gn:name":"Talawala Dabbar",
    "gn:population":0,
    "gn:timezone":"Asia/Kolkata",
    "iso:country":"IN",
    "wof:name":"Talawala Dabbar",
    "wof:placetype":"locality"
},
  "geometry": {"coordinates":[75.56277,32.68532],"type":"Point"}
}