{
  "type": "Feature",
  "properties": {
    "iso:country":"IN",
    "ks:ks_name":"Pirozpur",
    "ks:ks_pop":1205,
    "ks:ks_type":"VILLAGE",
    "ks:ks_uagg_main":0,
    "name:eng_x_preferred":[
        "Pirozpur"
    ],
    "wof:name":"Pirozpur",
    "wof:placetype":"neighbourhood",
    "wof:population":1205
},
  "geometry": {"coordinates":[88.76148000000001,25.347225],"type":"Point"}
}