{
  "type": "Feature",
  "properties": {
    "gn:country":"IN",
    "gn:fcode":"PPL",
    "gn:population":0,
    "iso:country":"IN",
    "name:eng_x_preferred":[
        "Chashmashahi"
    ],
    "qs:gn_adm0_cc":"IN",
    "qs:gn_fcode":"PPL",
    "qs:gn_local":1255634,
    "qs:gn_nam_loc":"Srinagar, Srinagar, Jammu and Kashmir, IN",
    "qs:gn_namadm1":"12",
    "qs:gn_name":"Chashma Sh\u0101hi",
    "qs:local_max":800,
    "qs:local_sum":2636,
    "qs:localhoods":18,
    "qs:name":"Chashmashahi",
    "qs:name_adm0":"India",
    "qs:name_adm1":"Jammu and Kashmir",
    "qs:name_adm2":"Srinagar",
    "qs:name_local":"Srinagar",
    "qs:photo_max":28,
    "qs:photo_sum":35,
    "qs:placetype":"Suburb",
    "qs:quad_count":4,
    "qs:woe_adm0":23424848,
    "qs:woe_adm1":2345746,
    "qs:woe_adm2":12586462,
    "qs:woe_lau":0,
    "qs:woe_local":2295387,
    "qs:woe_ver":"7.10.0",
    "qs_pg:aaroncc":"IN",
    "qs_pg:gn_country":"IN",
    "qs_pg:gn_fcode":"PPL",
    "qs_pg:gn_pop":0,
    "qs_pg:name":"Chashmashahi",
    "qs_pg:name_adm0":"India",
    "qs_pg:name_adm1":"Jammu and Kashmir",
    "qs_pg:photos":34,
    "qs_pg:photos_1k":7,
    "qs_pg:photos_9k":1,
    "qs_pg:photos_9r":2,
    "qs_pg:photos_all":34,
    "qs_pg:photos_sr":2,
    "qs_pg:pop_sr":0,
    "qs_pg:qs_pg_placetype":"neighbourhood",
    "qs_pg:qs_pg_placetype_gp":"Suburb",
    "qs_pg:woe_adm0":23424848,
    "wof:lang":[
        "eng"
    ],
    "wof:name":"Chashmashahi",
    "wof:placetype":"neighbourhood"
},
  "geometry": {"coordinates":[74.886971,34.087047],"type":"Point"}
}