{
  "type": "Feature",
  "properties": {
    "iso:country":"IN",
    "ks:ks_name":"Charkwah",
    "ks:ks_pop":486,
    "ks:ks_type":"VILLAGE",
    "name:eng_x_preferred":[
        "Charkwah"
    ],
    "wof:name":"Charkwah",
    "wof:placetype":"locality",
    "wof:population":486
},
  "geometry": {"coordinates":[81.270178,23.89089],"type":"Point"}
}