{
  "type": "Feature",
  "properties": {
    "iso:country":"IN",
    "ks:ks_name":"Diripar",
    "ks:ks_pop":538,
    "ks:ks_type":"HABITATION",
    "name:eng_x_preferred":[
        "Diripar"
    ],
    "wof:name":"Diripar",
    "wof:placetype":"locality",
    "wof:population":538
},
  "geometry": {"coordinates":[85.46332700000001,25.224561],"type":"Point"}
}