{
  "type": "Feature",
  "properties": {
    "iso:country":"IN",
    "ks:ks_name":"Jhau Mahal",
    "ks:ks_pop":426,
    "ks:ks_type":"VILLAGE",
    "ks:ks_uagg_main":0,
    "name:eng_x_preferred":[
        "Jhau Mahal"
    ],
    "wof:name":"Jhau Mahal",
    "wof:placetype":"neighbourhood",
    "wof:population":426
},
  "geometry": {"coordinates":[88.470899,23.188366],"type":"Point"}
}