{
  "type": "Feature",
  "properties": {
    "iso:country":"IN",
    "ks:ks_alt_nam":"Bar\u0101ng",
    "ks:ks_name":"Barang",
    "ks:ks_pop":142,
    "ks:ks_type":"VILLAGE",
    "name:eng_x_preferred":[
        "Barang"
    ],
    "name:eng_x_variant":[
        "Bar\u0101ng"
    ],
    "wof:name":"Barang",
    "wof:placetype":"locality",
    "wof:population":142
},
  "geometry": {"coordinates":[84.42183300000001,23.275106],"type":"Point"}
}