{
  "type": "Feature",
  "properties": {
    "iso:country":"IN",
    "ks:ks_name":"Pachim Rihabari",
    "ks:ks_pop":325,
    "ks:ks_type":"VILLAGE",
    "name:eng_x_preferred":[
        "Pachim Rihabari"
    ],
    "wof:name":"Pachim Rihabari",
    "wof:placetype":"locality",
    "wof:population":325
},
  "geometry": {"coordinates":[91.19205599999999,26.607359],"type":"Point"}
}