{
  "type": "Feature",
  "properties": {
    "iso:country":"IN",
    "ks:ks_name":"Sayengia",
    "ks:ks_pop":224,
    "ks:ks_type":"HABITATION",
    "name:eng_x_preferred":[
        "Sayengia"
    ],
    "wof:name":"Sayengia",
    "wof:placetype":"locality",
    "wof:population":224
},
  "geometry": {"coordinates":[94.432649,27.549876],"type":"Point"}
}