{
  "type": "Feature",
  "properties": {
    "iso:country":"IN",
    "ks:ks_name":"Fakir Tola",
    "ks:ks_pop":1231,
    "ks:ks_type":"HABITATION",
    "name:eng_x_preferred":[
        "Fakir Tola"
    ],
    "wof:name":"Fakir Tola",
    "wof:placetype":"locality",
    "wof:population":1231
},
  "geometry": {"coordinates":[86.10105,25.546353],"type":"Point"}
}