{
  "type": "Feature",
  "properties": {
    "gn:admin1_code":"11.0",
    "gn:admin2_code":"33.0",
    "gn:asciiname":"Lauga",
    "gn:country_code":"IN",
    "gn:dem":1838,
    "gn:feature_class":"P",
    "gn:feature_code":"PPL",
    "gn:name":"Lauga",
    "gn:population":0,
    "gn:timezone":"Asia/Kolkata",
    "iso:country":"IN",
    "wof:name":"Lauga",
    "wof:placetype":"locality"
},
  "geometry": {"coordinates":[77.49138000000001,31.33256],"type":"Point"}
}