{
  "type": "Feature",
  "properties": {
    "iso:country":"IN",
    "ks:ks_name":"Varakara Rd End",
    "ks:ks_pop":285,
    "ks:ks_type":"HABITATION",
    "name:eng_x_preferred":[
        "Varakara Rd End"
    ],
    "wof:name":"Varakara Rd End",
    "wof:placetype":"locality",
    "wof:population":285
},
  "geometry": {"coordinates":[76.31415,10.446475],"type":"Point"}
}