{
  "type": "Feature",
  "properties": {
    "iso:country":"IN",
    "ks:ks_name":"Dokrichanchara",
    "ks:ks_pop":16,
    "ks:ks_type":"HABITATION",
    "name:eng_x_preferred":[
        "Dokrichanchara"
    ],
    "wof:name":"Dokrichanchara",
    "wof:placetype":"locality",
    "wof:population":16
},
  "geometry": {"coordinates":[82.548931,19.618306],"type":"Point"}
}