{
  "type": "Feature",
  "properties": {
    "gn:admin1_code":"19.0",
    "gn:admin2_code":"572.0",
    "gn:asciiname":"Soppanhalli",
    "gn:country_code":"IN",
    "gn:dem":921,
    "gn:feature_class":"P",
    "gn:feature_code":"PPL",
    "gn:name":"Soppanhalli",
    "gn:population":0,
    "gn:timezone":"Asia/Kolkata",
    "iso:country":"IN",
    "wof:name":"Soppanhalli",
    "wof:placetype":"locality"
},
  "geometry": {"coordinates":[77.67955000000001,12.74754],"type":"Point"}
}