{
  "type": "Feature",
  "properties": {
    "iso:country":"IN",
    "ks:ks_name":"Maraipara",
    "ks:ks_pop":212,
    "ks:ks_type":"HABITATION",
    "name:eng_x_preferred":[
        "Maraipara"
    ],
    "wof:name":"Maraipara",
    "wof:placetype":"locality",
    "wof:population":212
},
  "geometry": {"coordinates":[81.49594999999999,19.937106],"type":"Point"}
}