{
  "type": "Feature",
  "properties": {
    "iso:country":"IN",
    "ks:ks_alt_nam":"keelacheri",
    "ks:ks_name":"Keelacheri",
    "ks:ks_pop":429,
    "ks:ks_type":"HABITATION",
    "name:eng_x_preferred":[
        "Keelacheri"
    ],
    "wof:name":"Keelacheri",
    "wof:placetype":"locality",
    "wof:population":429
},
  "geometry": {"coordinates":[79.607072,10.565078],"type":"Point"}
}