{
  "type": "Feature",
  "properties": {
    "iso:country":"IN",
    "ks:ks_name":"Dudhiya Khera",
    "ks:ks_pop":21,
    "ks:ks_type":"HABITATION",
    "name:eng_x_preferred":[
        "Dudhiya Khera"
    ],
    "wof:name":"Dudhiya Khera",
    "wof:placetype":"locality",
    "wof:population":21
},
  "geometry": {"coordinates":[79.52395,26.482682],"type":"Point"}
}