{
  "type": "Feature",
  "properties": {
    "gn:admin1_code":"20.0",
    "gn:admin2_code":"267.0",
    "gn:asciiname":"Sangpurr",
    "gn:country_code":"IN",
    "gn:dem":2045,
    "gn:feature_class":"P",
    "gn:feature_code":"PPL",
    "gn:name":"Sangpurr",
    "gn:population":0,
    "gn:timezone":"Asia/Kolkata",
    "iso:country":"IN",
    "wof:name":"Sangpurr",
    "wof:placetype":"locality"
},
  "geometry": {"coordinates":[94.85146,26.13376],"type":"Point"}
}