{
  "type": "Feature",
  "properties": {
    "gn:admin1_code":"02",
    "gn:admin2_code":"549.0",
    "gn:asciiname":"Natalapadu",
    "gn:country_code":"IN",
    "gn:dem":21,
    "gn:feature_class":"P",
    "gn:feature_code":"PPL",
    "gn:name":"N\u0101talap\u0101du",
    "gn:population":0,
    "gn:timezone":"Asia/Kolkata",
    "iso:country":"IN",
    "name:und_x_variant":[
        "N\u0101talap\u0101du",
        "N\u016btalap\u0101du"
    ],
    "wof:name":"Natalapadu",
    "wof:placetype":"locality"
},
  "geometry": {"coordinates":[80.22972,15.93661],"type":"Point"}
}