{
  "type": "Feature",
  "properties": {
    "iso:country":"IN",
    "ks:ks_name":"Deogharia Grant",
    "ks:ks_pop":550,
    "ks:ks_type":"VILLAGE",
    "ks:ks_uagg_main":0,
    "name:eng_x_preferred":[
        "Deogharia Grant"
    ],
    "wof:name":"Deogharia Grant",
    "wof:placetype":"neighbourhood",
    "wof:population":550
},
  "geometry": {"coordinates":[94.187634,26.574466],"type":"Point"}
}