{
  "type": "Feature",
  "properties": {
    "iso:country":"IN",
    "ks:ks_alt_nam":"Medida and Kakulavari Group",
    "ks:ks_name":"Medida And Kakulavari Group",
    "ks:ks_pop":463,
    "ks:ks_type":"HABITATION",
    "name:eng_x_preferred":[
        "Medida And Kakulavari Group"
    ],
    "wof:name":"Medida And Kakulavari Group",
    "wof:placetype":"locality",
    "wof:population":463
},
  "geometry": {"coordinates":[81.868639,16.42671],"type":"Point"}
}