{
  "type": "Feature",
  "properties": {
    "iso:country":"IN",
    "ks:ks_name":"Totapara",
    "ks:ks_pop":593,
    "ks:ks_type":"VILLAGE",
    "name:eng_x_preferred":[
        "Totapara"
    ],
    "wof:name":"Totapara",
    "wof:placetype":"locality",
    "wof:population":593
},
  "geometry": {"coordinates":[82.47647600000001,18.615729],"type":"Point"}
}