{
  "type": "Feature",
  "properties": {
    "iso:country":"IN",
    "ks:ks_name":"Randiha",
    "ks:ks_pop":1707,
    "ks:ks_type":"VILLAGE",
    "ks:ks_uagg_main":0,
    "name:eng_x_preferred":[
        "Randiha"
    ],
    "wof:name":"Randiha",
    "wof:placetype":"neighbourhood",
    "wof:population":1707
},
  "geometry": {"coordinates":[87.478106,23.380644],"type":"Point"}
}