{
  "type": "Feature",
  "properties": {
    "gn:admin1_code":"35",
    "gn:admin2_code":"443.0",
    "gn:asciiname":"Chakna",
    "gn:country_code":"IN",
    "gn:dem":467,
    "gn:feature_class":"P",
    "gn:feature_code":"PPL",
    "gn:name":"Chakna",
    "gn:population":0,
    "gn:timezone":"Asia/Kolkata",
    "iso:country":"IN",
    "name:nor_x_preferred":[
        "Chakna"
    ],
    "wof:name":"Chakna",
    "wof:placetype":"locality"
},
  "geometry": {"coordinates":[77.67256,24.17981],"type":"Point"}
}