{
  "type": "Feature",
  "properties": {
    "gn:admin1_code":"25",
    "gn:admin2_code":"626.0",
    "gn:asciiname":"Mutturamalingapattanam",
    "gn:country_code":"IN",
    "gn:dem":9,
    "gn:feature_class":"P",
    "gn:feature_code":"PPL",
    "gn:name":"Muttur\u0101malingapattanam",
    "gn:population":0,
    "gn:timezone":"Asia/Kolkata",
    "iso:country":"IN",
    "wof:name":"Mutturamalingapattanam",
    "wof:placetype":"locality"
},
  "geometry": {"coordinates":[79.03483,9.76448],"type":"Point"}
}