{
  "type": "Feature",
  "properties": {
    "gn:admin1_code":"9",
    "gn:admin2_code":"485.0",
    "gn:asciiname":"Anwarpur",
    "gn:country_code":"IN",
    "gn:dem":251,
    "gn:feature_class":"P",
    "gn:feature_code":"PPL",
    "gn:name":"Anwarpur",
    "gn:population":0,
    "gn:timezone":"Asia/Kolkata",
    "iso:country":"IN",
    "name:und_x_variant":[
        "Umr\u0101la"
    ],
    "wof:name":"Anwarpur",
    "wof:placetype":"locality"
},
  "geometry": {"coordinates":[74.1758,23.12454],"type":"Point"}
}