{
  "type": "Feature",
  "properties": {
    "iso:country":"IN",
    "ks:ks_name":"Paschim Madhyagurguria",
    "ks:ks_pop":2320,
    "ks:ks_type":"HABITATION",
    "name:eng_x_preferred":[
        "Paschim Madhyagurguria"
    ],
    "wof:name":"Paschim Madhyagurguria",
    "wof:placetype":"locality",
    "wof:population":2320
},
  "geometry": {"coordinates":[88.5611,21.996333],"type":"Point"}
}