{
  "type": "Feature",
  "properties": {
    "iso:country":"IN",
    "ks:ks_name":"Ningapur",
    "ks:ks_pop":390,
    "ks:ks_type":"HABITATION",
    "name:eng_x_preferred":[
        "Ningapur"
    ],
    "wof:name":"Ningapur",
    "wof:placetype":"locality",
    "wof:population":390
},
  "geometry": {"coordinates":[74.76177,15.493993],"type":"Point"}
}