{
  "type": "Feature",
  "properties": {
    "gn:admin1_code":"24.0",
    "gn:admin2_code":"121",
    "gn:asciiname":"Anuppura",
    "gn:country_code":"IN",
    "gn:dem":273,
    "gn:feature_class":"P",
    "gn:feature_code":"PPL",
    "gn:name":"An\u016bppura",
    "gn:population":0,
    "gn:timezone":"Asia/Kolkata",
    "iso:country":"IN",
    "wof:name":"Anuppura",
    "wof:placetype":"locality"
},
  "geometry": {"coordinates":[75.52175,25.29849],"type":"Point"}
}