{
  "type": "Feature",
  "properties": {
    "gn:admin1_code":"23.0",
    "gn:admin2_code":"051",
    "gn:asciiname":"Bharatgarh",
    "gn:country_code":"IN",
    "gn:dem":322,
    "gn:feature_class":"P",
    "gn:feature_code":"PPL",
    "gn:name":"Bharatgarh",
    "gn:population":0,
    "gn:timezone":"Asia/Kolkata",
    "iso:country":"IN",
    "wof:name":"Bharatgarh",
    "wof:placetype":"locality"
},
  "geometry": {"coordinates":[76.60981,31.09817],"type":"Point"}
}