{
  "type": "Feature",
  "properties": {
    "iso:country":"IN",
    "ks:ks_name":"Rampur",
    "ks:ks_pop":590,
    "ks:ks_type":"HABITATION",
    "name:eng_x_preferred":[
        "Rampur"
    ],
    "name:hin_x_preferred":[
        "\u0930\u093e\u092e\u092a\u0941\u0930"
    ],
    "wof:name":"Rampur",
    "wof:placetype":"locality",
    "wof:population":590
},
  "geometry": {"coordinates":[73.36752799999999,23.449861],"type":"Point"}
}