{
  "type": "Feature",
  "properties": {
    "iso:country":"IN",
    "ks:ks_name":"Devla",
    "ks:ks_pop":2410,
    "ks:ks_type":"VILLAGE",
    "ks:ks_uagg_main":0,
    "name:eng_x_preferred":[
        "Devla"
    ],
    "wof:name":"Devla",
    "wof:placetype":"neighbourhood",
    "wof:population":2410
},
  "geometry": {"coordinates":[77.50558100000001,28.522305],"type":"Point"}
}