{
  "type": "Feature",
  "properties": {
    "gn:admin1_code":"24.0",
    "gn:admin2_code":"108.0",
    "gn:asciiname":"Sankara",
    "gn:country_code":"IN",
    "gn:dem":225,
    "gn:feature_class":"P",
    "gn:feature_code":"PPL",
    "gn:name":"S\u0101nkara",
    "gn:population":0,
    "gn:timezone":"Asia/Kolkata",
    "iso:country":"IN",
    "name:ceb_x_preferred":[
        "Sankara"
    ],
    "name:deu_x_preferred":[
        "Sankara"
    ],
    "name:fin_x_preferred":[
        "Sankara"
    ],
    "name:fra_x_preferred":[
        "Sankara"
    ],
    "name:nld_x_preferred":[
        "Sankara"
    ],
    "name:swe_x_preferred":[
        "Sankara"
    ],
    "wof:name":"Sankara",
    "wof:placetype":"locality"
},
  "geometry": {"coordinates":[76.58939000000002,26.26528],"type":"Point"}
}