{
  "type": "Feature",
  "properties": {
    "gn:admin1_code":"35.0",
    "gn:admin2_code":"445.0",
    "gn:asciiname":"Ramakhedi",
    "gn:country_code":"IN",
    "gn:dem":531,
    "gn:feature_class":"P",
    "gn:feature_code":"PPL",
    "gn:name":"Ramakhedi",
    "gn:population":0,
    "gn:timezone":"Asia/Kolkata",
    "iso:country":"IN",
    "wof:name":"Ramakhedi",
    "wof:placetype":"locality"
},
  "geometry": {"coordinates":[77.20878,23.11605],"type":"Point"}
}