{
  "type": "Feature",
  "properties": {
    "iso:country":"IN",
    "ks:ks_name":"Dongripada",
    "ks:ks_pop":800,
    "ks:ks_type":"HABITATION",
    "name:eng_x_preferred":[
        "Dongripada"
    ],
    "wof:name":"Dongripada",
    "wof:placetype":"locality",
    "wof:population":800
},
  "geometry": {"coordinates":[72.895672,20.180598],"type":"Point"}
}