{
  "type": "Feature",
  "properties": {
    "iso:country":"IN",
    "ks:ks_name":"Jum pt - VI",
    "ks:ks_pop":161,
    "ks:ks_type":"VILLAGE",
    "name:eng_x_preferred":[
        "Jum pt - VI"
    ],
    "wof:name":"Jum pt - VI",
    "wof:placetype":"locality",
    "wof:population":161
},
  "geometry": {"coordinates":[92.56829999999999,24.851867],"type":"Point"}
}