{
  "type": "Feature",
  "properties": {
    "iso:country":"IN",
    "ks:ks_alt_nam":"Naugaon Kh\u0101l",
    "ks:ks_alt_nam_2":"Naugaon Khal",
    "ks:ks_name":"Naugaon",
    "ks:ks_type":"VILLAGE",
    "name:eng_x_preferred":[
        "Naugaon"
    ],
    "name:eng_x_variant":[
        "Naugaon Kh\u0101l",
        "Naugaon Khal"
    ],
    "wof:name":"Naugaon",
    "wof:placetype":"locality"
},
  "geometry": {"coordinates":[78.865771,29.965965],"type":"Point"}
}