{
  "type": "Feature",
  "properties": {
    "iso:country":"IN",
    "ks:ks_name":"Gorgepara",
    "ks:ks_pop":262,
    "ks:ks_type":"HABITATION",
    "name:eng_x_preferred":[
        "Gorgepara"
    ],
    "wof:name":"Gorgepara",
    "wof:placetype":"locality",
    "wof:population":262
},
  "geometry": {"coordinates":[81.08783699999999,18.743149],"type":"Point"}
}