{
  "type": "Feature",
  "properties": {
    "iso:country":"IN",
    "ks:ks_alt_nam":"25 LGW-B",
    "ks:ks_name":"25 Lgw-b",
    "ks:ks_pop":1357,
    "ks:ks_type":"HABITATION",
    "name:eng_x_preferred":[
        "25 Lgw-b"
    ],
    "wof:name":"25 Lgw-b",
    "wof:placetype":"locality",
    "wof:population":1357
},
  "geometry": {"coordinates":[73.821494,29.53664],"type":"Point"}
}