{
  "type": "Feature",
  "properties": {
    "iso:country":"IN",
    "ks:ks_name":"Kolhedhav",
    "ks:ks_pop":301,
    "ks:ks_type":"HABITATION",
    "name:eng_x_preferred":[
        "Kolhedhav"
    ],
    "wof:name":"Kolhedhav",
    "wof:placetype":"locality",
    "wof:population":301
},
  "geometry": {"coordinates":[73.31249099999999,20.047648],"type":"Point"}
}