{
  "type": "Feature",
  "properties": {
    "iso:country":"IN",
    "ks:ks_name":"Miyalaje",
    "ks:ks_pop":100,
    "ks:ks_type":"HABITATION",
    "name:eng_x_preferred":[
        "Miyalaje"
    ],
    "wof:name":"Miyalaje",
    "wof:placetype":"locality",
    "wof:population":100
},
  "geometry": {"coordinates":[75.124493,13.003526],"type":"Point"}
}