{
  "type": "Feature",
  "properties": {
    "gn:country":"IN",
    "gn:fcode":"PPL",
    "gn:pop":0,
    "iso:country":"IN",
    "name:ast_x_preferred":[
        "Alahalli"
    ],
    "name:eng_x_preferred":[
        "Alahalli"
    ],
    "name:fas_x_preferred":[
        "\u0627\u0644\u0627\u0647\u0627\u0644\u06cc"
    ],
    "name:nld_x_preferred":[
        "Alahalli"
    ],
    "name:vie_x_preferred":[
        "Alahalli"
    ],
    "qs:name":"Alahalli",
    "qs:name_adm0":"India",
    "qs:name_adm1":"Karnataka",
    "qs:photos":32,
    "qs:photos_1k":6,
    "qs:photos_9k":1,
    "qs:photos_9r":2,
    "qs:photos_all":32,
    "qs:photos_sr":2,
    "qs:placetype":"Town",
    "qs:pop_sr":"0",
    "wd:wordcount":97,
    "wof:name":"Alahalli",
    "wof:placetype":"locality",
    "wof:population":0
},
  "geometry": {"coordinates":[77.51194,12.96107],"type":"Point"}
}