{
  "type": "Feature",
  "properties": {
    "gn:admin1_code":"35",
    "gn:admin2_code":"461.0",
    "gn:asciiname":"Boda",
    "gn:country_code":"IN",
    "gn:dem":821,
    "gn:feature_class":"P",
    "gn:feature_code":"PPL",
    "gn:name":"Boda",
    "gn:population":0,
    "gn:timezone":"Asia/Kolkata",
    "iso:country":"IN",
    "ks:ks_name":"Boda",
    "ks:ks_pop":788,
    "ks:ks_type":"VILLAGE",
    "name:ben_x_preferred":[
        "\u09ac\u09cb\u09a6"
    ],
    "name:bpy_x_preferred":[
        "\u09ac\u09cb\u09a6"
    ],
    "name:ceb_x_preferred":[
        "Boda"
    ],
    "name:deu_x_preferred":[
        "Boda"
    ],
    "name:eng_x_preferred":[
        "Boda"
    ],
    "name:fin_x_preferred":[
        "Boda"
    ],
    "name:fra_x_preferred":[
        "Boda"
    ],
    "name:ita_x_preferred":[
        "Boda"
    ],
    "name:nld_x_preferred":[
        "Boda"
    ],
    "name:oci_x_preferred":[
        "Boda"
    ],
    "name:pol_x_preferred":[
        "Boda"
    ],
    "name:por_x_preferred":[
        "Boda"
    ],
    "name:rus_x_preferred":[
        "\u0411\u043e\u0434\u0430"
    ],
    "name:spa_x_preferred":[
        "Boda"
    ],
    "name:swe_x_preferred":[
        "Boda"
    ],
    "wof:name":"Boda",
    "wof:placetype":"locality",
    "wof:population":788
},
  "geometry": {"coordinates":[81.57108100000001,22.837001],"type":"Point"}
}