{
  "type": "Feature",
  "properties": {
    "gn:admin1_code":"12.0",
    "gn:asciiname":"Sarodab",
    "gn:country_code":"IN",
    "gn:dem":2674,
    "gn:feature_class":"P",
    "gn:feature_code":"PPL",
    "gn:name":"Sarod\u0101b",
    "gn:population":0,
    "gn:timezone":"Asia/Kolkata",
    "iso:country":"IN",
    "wof:name":"Sarodab",
    "wof:placetype":"locality"
},
  "geometry": {"coordinates":[75.07814,34.54846],"type":"Point"}
}