{
  "type": "Feature",
  "properties": {
    "iso:country":"IN",
    "ks:ks_name":"Saraswatipur",
    "ks:ks_pop":182,
    "ks:ks_type":"VILLAGE",
    "name:eng_x_preferred":[
        "Saraswatipur"
    ],
    "wof:name":"Saraswatipur",
    "wof:placetype":"locality",
    "wof:population":182
},
  "geometry": {"coordinates":[87.33074499999999,22.533405],"type":"Point"}
}