{
  "type": "Feature",
  "properties": {
    "iso:country":"IN",
    "ks:ks_name":"Bhurkura",
    "ks:ks_pop":357,
    "ks:ks_type":"VILLAGE",
    "name:eng_x_preferred":[
        "Bhurkura"
    ],
    "wof:name":"Bhurkura",
    "wof:placetype":"locality",
    "wof:population":357
},
  "geometry": {"coordinates":[86.79589199999999,22.879807],"type":"Point"}
}