{
  "type": "Feature",
  "properties": {
    "iso:country":"IN",
    "ks:ks_name":"Hibibpur Urf Jaintpur",
    "ks:ks_pop":1373,
    "ks:ks_type":"VILLAGE",
    "name:eng_x_preferred":[
        "Hibibpur Urf Jaintpur"
    ],
    "wof:name":"Hibibpur Urf Jaintpur",
    "wof:placetype":"locality",
    "wof:population":1373
},
  "geometry": {"coordinates":[85.550473,25.885222],"type":"Point"}
}