{
  "type": "Feature",
  "properties": {
    "iso:country":"IN",
    "ks:ks_name":"Ladabahara",
    "ks:ks_pop":30,
    "ks:ks_type":"VILLAGE",
    "name:eng_x_preferred":[
        "Ladabahara"
    ],
    "wof:name":"Ladabahara",
    "wof:placetype":"locality",
    "wof:population":30
},
  "geometry": {"coordinates":[82.253168,20.39205],"type":"Point"}
}