{
  "type": "Feature",
  "properties": {
    "iso:country":"IN",
    "ks:ks_alt_nam":"Koupati gaon part 1",
    "ks:ks_name":"Koupati Gaon Part 1",
    "ks:ks_pop":1502,
    "ks:ks_type":"HABITATION",
    "ks:ks_uagg_main":0,
    "name:eng_x_preferred":[
        "Koupati Gaon Part 1"
    ],
    "wof:name":"Koupati Gaon Part 1",
    "wof:placetype":"neighbourhood",
    "wof:population":1502
},
  "geometry": {"coordinates":[92.280483,26.611276],"type":"Point"}
}