{
  "type": "Feature",
  "properties": {
    "gn:admin1_code":"36",
    "gn:admin2_code":"178.0",
    "gn:asciiname":"Naurahni Rampur",
    "gn:country_code":"IN",
    "gn:dem":90,
    "gn:feature_class":"P",
    "gn:feature_code":"PPL",
    "gn:name":"Naurahni R\u0101mpur",
    "gn:population":0,
    "gn:timezone":"Asia/Kolkata",
    "iso:country":"IN",
    "wof:name":"Naurahni Rampur",
    "wof:placetype":"locality"
},
  "geometry": {"coordinates":[82.79217,26.56777],"type":"Point"}
}