{
  "type": "Feature",
  "properties": {
    "iso:country":"IN",
    "ks:ks_name":"Tolvad",
    "ks:ks_pop":735,
    "ks:ks_type":"HABITATION",
    "name:eng_x_preferred":[
        "Tolvad"
    ],
    "wof:name":"Tolvad",
    "wof:placetype":"locality",
    "wof:population":735
},
  "geometry": {"coordinates":[72.8905,22.368972],"type":"Point"}
}