{
  "type": "Feature",
  "properties": {
    "iso:country":"IN",
    "ks:ks_name":"Lakshmi Narayanpur Arazi",
    "ks:ks_pop":0,
    "ks:ks_type":"VILLAGE",
    "name:eng_x_preferred":[
        "Lakshmi Narayanpur Arazi"
    ],
    "wof:name":"Lakshmi Narayanpur Arazi",
    "wof:placetype":"locality",
    "wof:population":0
},
  "geometry": {"coordinates":[87.97067699999999,24.017147],"type":"Point"}
}