{
  "type": "Feature",
  "properties": {
    "gn:admin1_code":"36",
    "gn:admin2_code":"137.0",
    "gn:asciiname":"Alipur",
    "gn:country_code":"IN",
    "gn:dem":223,
    "gn:feature_class":"P",
    "gn:feature_code":"PPL",
    "gn:name":"Al\u012bpur",
    "gn:population":0,
    "gn:timezone":"Asia/Kolkata",
    "iso:country":"IN",
    "name:cat_x_preferred":[
        "Alipur"
    ],
    "name:ceb_x_preferred":[
        "Alipur"
    ],
    "name:swe_x_preferred":[
        "Alipur"
    ],
    "wof:name":"Alipur",
    "wof:placetype":"locality"
},
  "geometry": {"coordinates":[78.35843,29.00453],"type":"Point"}
}