{
  "type": "Feature",
  "properties": {
    "iso:country":"IN",
    "ks:ks_name":"Telhaniya Rahika",
    "ks:ks_pop":116,
    "ks:ks_type":"HABITATION",
    "ks:ks_uagg_main":0,
    "name:eng_x_preferred":[
        "Telhaniya Rahika"
    ],
    "wof:name":"Telhaniya Rahika",
    "wof:placetype":"neighbourhood",
    "wof:population":116
},
  "geometry": {"coordinates":[87.62974,25.78158],"type":"Point"}
}