{
  "type": "Feature",
  "properties": {
    "iso:country":"IN",
    "ks:ks_name":"Tamaksili",
    "ks:ks_pop":87,
    "ks:ks_type":"HABITATION",
    "name:eng_x_preferred":[
        "Tamaksili"
    ],
    "wof:name":"Tamaksili",
    "wof:placetype":"locality",
    "wof:population":87
},
  "geometry": {"coordinates":[86.18726599999999,21.89545],"type":"Point"}
}