{
  "type": "Feature",
  "properties": {
    "iso:country":"IN",
    "ks:ks_name":"Barahnagar",
    "ks:ks_pop":827,
    "ks:ks_type":"VILLAGE",
    "name:eng_x_preferred":[
        "Barahnagar"
    ],
    "wof:name":"Barahnagar",
    "wof:placetype":"locality",
    "wof:population":827
},
  "geometry": {"coordinates":[83.291833,23.893763],"type":"Point"}
}