{
  "type": "Feature",
  "properties": {
    "iso:country":"IN",
    "ks:ks_name":"Kanda",
    "ks:ks_pop":61,
    "ks:ks_type":"VILLAGE",
    "name:eng_x_preferred":[
        "Kanda"
    ],
    "wof:name":"Kanda",
    "wof:placetype":"locality",
    "wof:population":61
},
  "geometry": {"coordinates":[79.765956,29.778671],"type":"Point"}
}