{
  "type": "Feature",
  "properties": {
    "iso:country":"IN",
    "ks:ks_name":"Sudugaadubailu",
    "ks:ks_pop":6,
    "ks:ks_type":"HABITATION",
    "name:eng_x_preferred":[
        "Sudugaadubailu"
    ],
    "wof:name":"Sudugaadubailu",
    "wof:placetype":"locality",
    "wof:population":6
},
  "geometry": {"coordinates":[75.011494,13.7979],"type":"Point"}
}