{
  "type": "Feature",
  "properties": {
    "iso:country":"IN",
    "ks:ks_alt_nam":"T\u0101libpur",
    "ks:ks_name":"Talibpur",
    "ks:ks_type":"VILLAGE",
    "name:eng_x_preferred":[
        "Talibpur"
    ],
    "name:eng_x_variant":[
        "T\u0101libpur"
    ],
    "wof:name":"Talibpur",
    "wof:placetype":"locality"
},
  "geometry": {"coordinates":[78.627099,29.172595],"type":"Point"}
}