{
  "type": "Feature",
  "properties": {
    "gn:admin1_code":"26",
    "gn:admin2_code":"291.0",
    "gn:asciiname":"Methraipara",
    "gn:country_code":"IN",
    "gn:dem":125,
    "gn:feature_class":"P",
    "gn:feature_code":"PPL",
    "gn:name":"Methr\u0101ip\u0101ra",
    "gn:population":0,
    "gn:timezone":"Asia/Kolkata",
    "iso:country":"IN",
    "name:und_x_variant":[
        "Meltraipara",
        "Methr\u0101ip\u0101ra"
    ],
    "wof:name":"Methraipara",
    "wof:placetype":"locality"
},
  "geometry": {"coordinates":[91.7938,23.74515],"type":"Point"}
}