{
  "type": "Feature",
  "properties": {
    "iso:country":"IN",
    "ks:ks_name":"Dakderapada",
    "ks:ks_pop":475,
    "ks:ks_type":"HABITATION",
    "name:eng_x_preferred":[
        "Dakderapada"
    ],
    "wof:name":"Dakderapada",
    "wof:placetype":"locality",
    "wof:population":475
},
  "geometry": {"coordinates":[84.069096,21.447895],"type":"Point"}
}