{
  "type": "Feature",
  "properties": {
    "gn:admin1_code":"36.0",
    "gn:admin2_code":"178.0",
    "gn:asciiname":"Tarauna Bansgaon",
    "gn:country_code":"IN",
    "gn:dem":86,
    "gn:feature_class":"P",
    "gn:feature_code":"PPL",
    "gn:name":"Tarauna B\u0101nsg\u0101on",
    "gn:population":0,
    "gn:timezone":"Asia/Kolkata",
    "iso:country":"IN",
    "name:und_x_variant":[
        "Tarauna B\u0101nsg\u0101on",
        "Tacauna"
    ],
    "wof:name":"Tarauna Bansgaon",
    "wof:placetype":"neighbourhood"
},
  "geometry": {"coordinates":[83.08316000000001,26.31362],"type":"Point"}
}