{
  "type": "Feature",
  "properties": {
    "iso:country":"IN",
    "ks:ks_name":"4 PTP",
    "ks:ks_pop":62,
    "ks:ks_type":"VILLAGE",
    "name:eng_x_preferred":[
        "4 PTP"
    ],
    "wof:name":"4 PTP",
    "wof:placetype":"locality",
    "wof:population":62
},
  "geometry": {"coordinates":[74.33880499999999,29.882061],"type":"Point"}
}