{
  "type": "Feature",
  "properties": {
    "gn:admin1_code":"34.0",
    "gn:admin2_code":"236.0",
    "gn:asciiname":"Deori",
    "gn:country_code":"IN",
    "gn:dem":236,
    "gn:feature_class":"P",
    "gn:feature_code":"PPL",
    "gn:name":"Deor\u012b",
    "gn:population":0,
    "gn:timezone":"Asia/Kolkata",
    "iso:country":"IN",
    "ks:ks_name":"Deuri",
    "ks:ks_pop":1033,
    "ks:ks_type":"VILLAGE",
    "ks:ks_uagg_main":0,
    "name:cat_x_preferred":[
        "Deori"
    ],
    "name:ceb_x_preferred":[
        "Deori"
    ],
    "name:eng_x_preferred":[
        "Deuri"
    ],
    "name:por_x_preferred":[
        "Deori"
    ],
    "name:swe_x_preferred":[
        "Deori"
    ],
    "wof:name":"Deuri",
    "wof:placetype":"neighbourhood",
    "wof:population":1033
},
  "geometry": {"coordinates":[84.352041,24.441984],"type":"Point"}
}