{
  "type": "Feature",
  "properties": {
    "iso:country":"IN",
    "ks:ks_alt_nam":"Pisk\u0101",
    "ks:ks_name":"Piska",
    "ks:ks_pop":519,
    "ks:ks_type":"VILLAGE",
    "name:eng_x_preferred":[
        "Piska"
    ],
    "name:eng_x_variant":[
        "Pisk\u0101"
    ],
    "wof:name":"Piska",
    "wof:placetype":"locality",
    "wof:population":519
},
  "geometry": {"coordinates":[85.81541300000001,23.397783],"type":"Point"}
}