{
  "type": "Feature",
  "properties": {
    "iso:country":"IN",
    "ks:ks_name":"Nakhare",
    "ks:ks_pop":2560,
    "ks:ks_type":"VILLAGE",
    "name:eng_x_preferred":[
        "Nakhare"
    ],
    "wof:name":"Nakhare",
    "wof:placetype":"locality",
    "wof:population":2560
},
  "geometry": {"coordinates":[73.362031,16.863223],"type":"Point"}
}