{
  "type": "Feature",
  "properties": {
    "gn:admin1_code":"16.0",
    "gn:admin2_code":"509.0",
    "gn:asciiname":"Moda",
    "gn:country_code":"IN",
    "gn:dem":356,
    "gn:feature_class":"P",
    "gn:feature_code":"PPL",
    "gn:name":"Moda",
    "gn:population":0,
    "gn:timezone":"Asia/Kolkata",
    "iso:country":"IN",
    "name:arg_x_preferred":[
        "Moda"
    ],
    "name:cat_x_preferred":[
        "Moda"
    ],
    "name:deu_x_preferred":[
        "Moda"
    ],
    "name:eus_x_preferred":[
        "Moda"
    ],
    "name:ita_x_preferred":[
        "Moda"
    ],
    "name:lav_x_preferred":[
        "Moda"
    ],
    "name:pol_x_preferred":[
        "Moda"
    ],
    "name:por_x_preferred":[
        "Moda"
    ],
    "name:rus_x_preferred":[
        "\u041c\u043e\u0434\u0430"
    ],
    "name:spa_x_preferred":[
        "Moda"
    ],
    "name:tur_x_preferred":[
        "Moda"
    ],
    "name:ukr_x_preferred":[
        "\u041c\u043e\u0434\u0430"
    ],
    "wof:name":"Moda",
    "wof:placetype":"locality"
},
  "geometry": {"coordinates":[79.03333000000001,19.5802],"type":"Point"}
}