{
  "type": "Feature",
  "properties": {
    "gn:admin1_code":"16.0",
    "gn:admin2_code":"509.0",
    "gn:asciiname":"Moda",
    "gn:country_code":"IN",
    "gn:dem":356,
    "gn:feature_class":"P",
    "gn:feature_code":"PPL",
    "gn:name":"Moda",
    "gn:population":0,
    "gn:timezone":"Asia/Kolkata",
    "iso:country":"IN",
    "wof:name":"Moda",
    "wof:placetype":"locality"
},
  "geometry": {"coordinates":[79.03333000000001,19.5802],"type":"Point"}
}