{
  "type": "Feature",
  "properties": {
    "gn:admin1_code":"39.0",
    "gn:admin2_code":"65.0",
    "gn:asciiname":"Blunri",
    "gn:country_code":"IN",
    "gn:dem":703,
    "gn:feature_class":"P",
    "gn:feature_code":"PPL",
    "gn:name":"Blunr\u012b",
    "gn:population":0,
    "gn:timezone":"Asia/Kolkata",
    "iso:country":"IN",
    "wof:name":"Blunri",
    "wof:placetype":"locality"
},
  "geometry": {"coordinates":[80.11304,29.19375],"type":"Point"}
}