{
  "type": "Feature",
  "properties": {
    "iso:country":"IN",
    "ks:ks_name":"Keladwadi",
    "ks:ks_pop":139,
    "ks:ks_type":"HABITATION",
    "name:eng_x_preferred":[
        "Keladwadi"
    ],
    "wof:name":"Keladwadi",
    "wof:placetype":"locality",
    "wof:population":139
},
  "geometry": {"coordinates":[73.077,18.42667],"type":"Point"}
}