{
  "type": "Feature",
  "properties": {
    "iso:country":"IN",
    "ks:ks_name":"Boddamamidi",
    "ks:ks_pop":74,
    "ks:ks_type":"HABITATION",
    "name:eng_x_preferred":[
        "Boddamamidi"
    ],
    "wof:name":"Boddamamidi",
    "wof:placetype":"locality",
    "wof:population":74
},
  "geometry": {"coordinates":[82.236964,17.787035],"type":"Point"}
}