{
  "type": "Feature",
  "properties": {
    "gn:admin1_code":"25.0",
    "gn:admin2_code":"609.0",
    "gn:asciiname":"Vaiyakkanjanpudur",
    "gn:country_code":"IN",
    "gn:dem":169,
    "gn:feature_class":"P",
    "gn:feature_code":"PPL",
    "gn:name":"Vaiyakk\u0101njanpud\u016br",
    "gn:population":0,
    "gn:timezone":"Asia/Kolkata",
    "iso:country":"IN",
    "wof:name":"Vaiyakkanjanpudur",
    "wof:placetype":"locality"
},
  "geometry": {"coordinates":[77.88828000000002,11.26344],"type":"Point"}
}