{
  "type": "Feature",
  "properties": {
    "iso:country":"IN",
    "ks:ks_alt_nam":"KUMBHIYA TARI",
    "ks:ks_name":"Kumbhiya Tari",
    "ks:ks_pop":143,
    "ks:ks_type":"HABITATION",
    "name:eng_x_preferred":[
        "Kumbhiya Tari"
    ],
    "wof:name":"Kumbhiya Tari",
    "wof:placetype":"locality",
    "wof:population":143
},
  "geometry": {"coordinates":[85.513333,24.526203],"type":"Point"}
}