{
  "type": "Feature",
  "properties": {
    "iso:country":"IN",
    "ks:ks_name":"Jamanpada 2",
    "ks:ks_pop":282,
    "ks:ks_type":"HABITATION",
    "name:eng_x_preferred":[
        "Jamanpada 2"
    ],
    "wof:name":"Jamanpada 2",
    "wof:placetype":"locality",
    "wof:population":282
},
  "geometry": {"coordinates":[73.19886099999999,20.224722],"type":"Point"}
}