{
  "type": "Feature",
  "properties": {
    "iso:country":"IN",
    "ks:ks_name":"Ng. Urri",
    "ks:ks_pop":405,
    "ks:ks_type":"HABITATION",
    "name:eng_x_preferred":[
        "Ng. Urri"
    ],
    "wof:name":"Ng. Urri",
    "wof:placetype":"locality",
    "wof:population":405
},
  "geometry": {"coordinates":[78.982145,27.604335],"type":"Point"}
}