{
  "type": "Feature",
  "properties": {
    "gn:admin1_code":"34.0",
    "gn:admin2_code":"221.0",
    "gn:asciiname":"Moghal Chak",
    "gn:country_code":"IN",
    "gn:dem":51,
    "gn:feature_class":"P",
    "gn:feature_code":"PPL",
    "gn:name":"Moghal Chak",
    "gn:population":0,
    "gn:timezone":"Asia/Kolkata",
    "iso:country":"IN",
    "ks:ks_name":"Mogal Chak",
    "ks:ks_pop":1784,
    "ks:ks_type":"VILLAGE",
    "ks:ks_uagg_main":0,
    "name:eng_x_preferred":[
        "Moghal Chak"
    ],
    "wof:name":"Mogal Chak",
    "wof:placetype":"neighbourhood",
    "wof:population":1784
},
  "geometry": {"coordinates":[85.66195999999999,25.58124],"type":"Point"}
}