{
  "type": "Feature",
  "properties": {
    "gn:admin1_code":"38.0",
    "gn:admin2_code":"366",
    "gn:asciiname":"Kamdara",
    "gn:country_code":"IN",
    "gn:dem":586,
    "gn:feature_class":"P",
    "gn:feature_code":"PPL",
    "gn:name":"Kamdara",
    "gn:population":0,
    "gn:timezone":"Asia/Kolkata",
    "iso:country":"IN",
    "name:und_x_variant":[
        "Kamdera",
        "Kamdara"
    ],
    "wof:name":"Kamdara",
    "wof:placetype":"locality"
},
  "geometry": {"coordinates":[84.91464000000001,22.90775],"type":"Point"}
}