{
  "type": "Feature",
  "properties": {
    "iso:country":"IN",
    "ks:ks_name":"Shemdadwadi",
    "ks:ks_pop":122,
    "ks:ks_type":"HABITATION",
    "name:eng_x_preferred":[
        "Shemdadwadi"
    ],
    "wof:name":"Shemdadwadi",
    "wof:placetype":"locality",
    "wof:population":122
},
  "geometry": {"coordinates":[73.80426199999999,19.476723],"type":"Point"}
}