{
  "type": "Feature",
  "properties": {
    "iso:country":"IN",
    "ks:ks_name":"Shibu Paswan Tola",
    "ks:ks_pop":145,
    "ks:ks_type":"HABITATION",
    "name:eng_x_preferred":[
        "Shibu Paswan Tola"
    ],
    "wof:name":"Shibu Paswan Tola",
    "wof:placetype":"locality",
    "wof:population":145
},
  "geometry": {"coordinates":[86.561216,25.989112],"type":"Point"}
}