{
  "type": "Feature",
  "properties": {
    "gn:admin1_code":"34.0",
    "gn:admin2_code":"234.0",
    "gn:asciiname":"Jugni",
    "gn:country_code":"IN",
    "gn:dem":87,
    "gn:feature_class":"P",
    "gn:feature_code":"PPL",
    "gn:name":"Jugni",
    "gn:population":0,
    "gn:timezone":"Asia/Kolkata",
    "iso:country":"IN",
    "name:pan_x_preferred":[
        "\u0a1c\u0a41\u0a17\u0a28\u0a40"
    ],
    "name:pnb_x_preferred":[
        "\u062c\u064f\u06af\u0646\u06cc"
    ],
    "wof:name":"Jugni",
    "wof:placetype":"neighbourhood"
},
  "geometry": {"coordinates":[84.25337,25.32214],"type":"Point"}
}