{
  "type": "Feature",
  "properties": {
    "iso:country":"IN",
    "ks:ks_name":"Chamliti",
    "ks:ks_pop":652,
    "ks:ks_type":"VILLAGE",
    "ks:ks_uagg_main":0,
    "name:eng_x_preferred":[
        "Chamliti"
    ],
    "wof:name":"Chamliti",
    "wof:placetype":"neighbourhood",
    "wof:population":652
},
  "geometry": {"coordinates":[86.540801,24.135489],"type":"Point"}
}