{
  "type": "Feature",
  "properties": {
    "iso:country":"IN",
    "ks:ks_alt_nam":"KAMBLE WASTI",
    "ks:ks_name":"Kamble Wasti",
    "ks:ks_pop":53,
    "ks:ks_type":"HABITATION",
    "name:eng_x_preferred":[
        "Kamble Wasti"
    ],
    "wof:name":"Kamble Wasti",
    "wof:placetype":"locality",
    "wof:population":53
},
  "geometry": {"coordinates":[75.522576,17.036994],"type":"Point"}
}