{
  "type": "Feature",
  "properties": {
    "gn:admin1_code":"37.0",
    "gn:admin2_code":"401.0",
    "gn:asciiname":"Saraidih",
    "gn:country_code":"IN",
    "gn:dem":804,
    "gn:feature_class":"P",
    "gn:feature_code":"PPL",
    "gn:name":"Saraidih",
    "gn:population":0,
    "gn:timezone":"Asia/Kolkata",
    "iso:country":"IN",
    "ks:ks_name":"Saraidih",
    "ks:ks_pop":248,
    "ks:ks_type":"VILLAGE",
    "name:eng_x_preferred":[
        "Saraidih"
    ],
    "wof:name":"Saraidih",
    "wof:placetype":"locality",
    "wof:population":248
},
  "geometry": {"coordinates":[83.704115,23.31938],"type":"Point"}
}