{
  "type": "Feature",
  "properties": {
    "gn:admin1_code":"37.0",
    "gn:admin2_code":"401.0",
    "gn:asciiname":"Saraidih",
    "gn:country_code":"IN",
    "gn:dem":804,
    "gn:feature_class":"P",
    "gn:feature_code":"PPL",
    "gn:name":"Saraidih",
    "gn:population":0,
    "gn:timezone":"Asia/Kolkata",
    "iso:country":"IN",
    "wof:name":"Saraidih",
    "wof:placetype":"locality"
},
  "geometry": {"coordinates":[83.71726,23.32507],"type":"Point"}
}