{
  "type": "Feature",
  "properties": {
    "iso:country":"IN",
    "ks:ks_name":"Baje",
    "ks:ks_pop":150,
    "ks:ks_type":"HABITATION",
    "name:eng_x_preferred":[
        "Baje"
    ],
    "wof:name":"Baje",
    "wof:placetype":"locality",
    "wof:population":150
},
  "geometry": {"coordinates":[75.129367,12.889106],"type":"Point"}
}