{
  "type": "Feature",
  "properties": {
    "iso:country":"IN",
    "ks:ks_name":"Bodavada",
    "ks:ks_pop":1239,
    "ks:ks_type":"VILLAGE",
    "ks:ks_uagg_main":0,
    "name:eng_x_preferred":[
        "Bodavada"
    ],
    "wof:name":"Bodavada",
    "wof:placetype":"neighbourhood",
    "wof:population":1239
},
  "geometry": {"coordinates":[80.369652,16.73759],"type":"Point"}
}