{
  "type": "Feature",
  "properties": {
    "gn:admin1_code":"12.0",
    "gn:admin2_code":"18.0",
    "gn:asciiname":"Tlenkal",
    "gn:country_code":"IN",
    "gn:dem":1685,
    "gn:feature_class":"P",
    "gn:feature_code":"PPL",
    "gn:name":"Tlenkal",
    "gn:population":0,
    "gn:timezone":"Asia/Kolkata",
    "iso:country":"IN",
    "wof:name":"Tlenkal",
    "wof:placetype":"locality"
},
  "geometry": {"coordinates":[75.85091,33.08754],"type":"Point"}
}