{
  "type": "Feature",
  "properties": {
    "iso:country":"IN",
    "ks:ks_alt_nam":"EGUVA KONGAVARIPALLE",
    "ks:ks_name":"Eguva Kongavaripalle",
    "ks:ks_pop":73,
    "ks:ks_type":"HABITATION",
    "name:eng_x_preferred":[
        "Eguva Kongavaripalle"
    ],
    "wof:name":"Eguva Kongavaripalle",
    "wof:placetype":"locality",
    "wof:population":73
},
  "geometry": {"coordinates":[78.47229299999999,13.699852],"type":"Point"}
}