{
  "type": "Feature",
  "properties": {
    "gn:admin1_code":"19.0",
    "gn:admin2_code":"575.0",
    "gn:asciiname":"Kasba",
    "gn:country_code":"IN",
    "gn:dem":113,
    "gn:feature_class":"P",
    "gn:feature_code":"PPLL",
    "gn:name":"Kasb\u0101",
    "gn:population":0,
    "gn:timezone":"Asia/Kolkata",
    "iso:country":"IN",
    "name:ceb_x_preferred":[
        "Kasba"
    ],
    "name:hin_x_preferred":[
        "\u0915\u0938\u094d\u092c\u093e"
    ],
    "name:new_x_preferred":[
        "\u0915\u0938\u094d\u092c\u093e"
    ],
    "name:nld_x_preferred":[
        "Kasba"
    ],
    "name:por_x_preferred":[
        "Kasba"
    ],
    "name:rus_x_preferred":[
        "\u041a\u0430\u0441\u0431\u0430"
    ],
    "name:swe_x_preferred":[
        "Kasba"
    ],
    "wof:name":"Kasba",
    "wof:placetype":"neighbourhood"
},
  "geometry": {"coordinates":[75.47345,12.74383],"type":"Point"}
}