{
  "type": "Feature",
  "properties": {
    "iso:country":"IN",
    "ks:ks_alt_nam":"NADAGADAMALAPALLE",
    "ks:ks_name":"Nadagadamalapalle",
    "ks:ks_pop":38,
    "ks:ks_type":"HABITATION",
    "name:eng_x_preferred":[
        "Nadagadamalapalle"
    ],
    "wof:name":"Nadagadamalapalle",
    "wof:placetype":"locality",
    "wof:population":38
},
  "geometry": {"coordinates":[78.41110500000001,13.700862],"type":"Point"}
}