{
  "type": "Feature",
  "properties": {
    "gn:admin1_code":"34.0",
    "gn:admin2_code":"211.0",
    "gn:asciiname":"Damohanatola",
    "gn:country_code":"IN",
    "gn:dem":49,
    "gn:feature_class":"P",
    "gn:feature_code":"PPL",
    "gn:name":"Damoh\u0101n\u0101tola",
    "gn:population":0,
    "gn:timezone":"Asia/Kolkata",
    "iso:country":"IN",
    "wof:name":"Damohanatola",
    "wof:placetype":"neighbourhood"
},
  "geometry": {"coordinates":[87.65364,26.07913],"type":"Point"}
}