{
  "type": "Feature",
  "properties": {
    "iso:country":"IN",
    "ks:ks_name":"Subrayanajaddu",
    "ks:ks_pop":21,
    "ks:ks_type":"HABITATION",
    "name:eng_x_preferred":[
        "Subrayanajaddu"
    ],
    "wof:name":"Subrayanajaddu",
    "wof:placetype":"locality",
    "wof:population":21
},
  "geometry": {"coordinates":[75.32446400000001,13.542951],"type":"Point"}
}