{
  "type": "Feature",
  "properties": {
    "gn:admin1_code":"36",
    "gn:admin2_code":"194.0",
    "gn:asciiname":"Dandupur",
    "gn:country_code":"IN",
    "gn:dem":88,
    "gn:feature_class":"P",
    "gn:feature_code":"PPL",
    "gn:name":"D\u0101nd\u016bpur",
    "gn:population":0,
    "gn:timezone":"Asia/Kolkata",
    "iso:country":"IN",
    "ks:ks_alt_nam":"D\u0101nd\u016bpur",
    "ks:ks_name":"Dandupur",
    "ks:ks_pop":844,
    "ks:ks_type":"VILLAGE",
    "ks:ks_uagg_main":0,
    "name:eng_x_preferred":[
        "Dandupur"
    ],
    "name:eng_x_variant":[
        "D\u0101nd\u016bpur"
    ],
    "wof:name":"Dandupur",
    "wof:placetype":"neighbourhood",
    "wof:population":844
},
  "geometry": {"coordinates":[82.43441900000001,25.812212],"type":"Point"}
}