{
  "type": "Feature",
  "properties": {
    "iso:country":"IN",
    "ks:ks_name":"Colony Para",
    "ks:ks_pop":570,
    "ks:ks_type":"HABITATION",
    "name:eng_x_preferred":[
        "Colony Para"
    ],
    "wof:name":"Colony Para",
    "wof:placetype":"locality",
    "wof:population":570
},
  "geometry": {"coordinates":[89.323069,26.269832],"type":"Point"}
}