{
  "type": "Feature",
  "properties": {
    "iso:country":"IN",
    "ks:ks_name":"Bagawda",
    "ks:ks_pop":8,
    "ks:ks_type":"HABITATION",
    "name:eng_x_preferred":[
        "Bagawda"
    ],
    "wof:name":"Bagawda",
    "wof:placetype":"locality",
    "wof:population":8
},
  "geometry": {"coordinates":[76.27059,22.79676],"type":"Point"}
}