{
  "type": "Feature",
  "properties": {
    "iso:country":"IN",
    "ks:ks_name":"Prasadchak",
    "ks:ks_pop":0,
    "ks:ks_type":"VILLAGE",
    "name:eng_x_preferred":[
        "Prasadchak"
    ],
    "wof:name":"Prasadchak",
    "wof:placetype":"locality",
    "wof:population":0
},
  "geometry": {"coordinates":[87.352816,22.280387],"type":"Point"}
}