{
  "type": "Feature",
  "properties": {
    "gn:admin1_code":"37",
    "gn:admin2_code":"406.0",
    "gn:asciiname":"Chhuia",
    "gn:country_code":"IN",
    "gn:dem":568,
    "gn:feature_class":"P",
    "gn:feature_code":"PPL",
    "gn:name":"Chhuia",
    "gn:population":0,
    "gn:timezone":"Asia/Kolkata",
    "iso:country":"IN",
    "ks:ks_alt_nam":"CHHUIHA",
    "ks:ks_name":"Chhuiha",
    "ks:ks_pop":406,
    "ks:ks_type":"HABITATION",
    "name:eng_x_preferred":[
        "Chhuiha"
    ],
    "name:eng_x_variant":[
        "Chhuia"
    ],
    "wof:name":"Chhuiha",
    "wof:placetype":"locality",
    "wof:population":406
},
  "geometry": {"coordinates":[81.90860000000001,22.455799],"type":"Point"}
}