{
  "type": "Feature",
  "properties": {
    "iso:country":"IN",
    "ks:ks_alt_nam":"Semr\u0101",
    "ks:ks_name":"Semra",
    "ks:ks_pop":671,
    "ks:ks_type":"VILLAGE",
    "name:eng_x_preferred":[
        "Semra"
    ],
    "name:eng_x_variant":[
        "Semr\u0101"
    ],
    "wof:name":"Semra",
    "wof:placetype":"locality",
    "wof:population":671
},
  "geometry": {"coordinates":[84.739121,23.087029],"type":"Point"}
}