{
  "type": "Feature",
  "properties": {
    "iso:country":"IN",
    "ks:ks_alt_nam":"DINABANDHU PARA",
    "ks:ks_name":"Dinabandhu Para",
    "ks:ks_pop":144,
    "ks:ks_type":"HABITATION",
    "name:eng_x_preferred":[
        "Dinabandhu Para"
    ],
    "wof:name":"Dinabandhu Para",
    "wof:placetype":"locality",
    "wof:population":144
},
  "geometry": {"coordinates":[91.476293,23.9061],"type":"Point"}
}