{
  "type": "Feature",
  "properties": {
    "gn:admin1_code":"35",
    "gn:admin2_code":"424.0",
    "gn:asciiname":"Lakhipur",
    "gn:country_code":"IN",
    "gn:dem":318,
    "gn:feature_class":"P",
    "gn:feature_code":"PPL",
    "gn:name":"Lakh\u012bpur",
    "gn:population":0,
    "gn:timezone":"Asia/Kolkata",
    "iso:country":"IN",
    "name:asm_x_preferred":[
        "\u09b2\u0995\u09cd\u09b7\u09c0\u09aa\u09c1\u09f0"
    ],
    "name:ben_x_preferred":[
        "\u09b2\u0995\u09cd\u09b7\u09c0\u09aa\u09c1\u09b0"
    ],
    "name:bpy_x_preferred":[
        "\u09b2\u0995\u09cd\u09b7\u09bf\u09aa\u09c1\u09b0"
    ],
    "name:ceb_x_preferred":[
        "Lakhipur"
    ],
    "name:fas_x_preferred":[
        "\u0644\u06a9\u0647\u06cc\u067e\u0648\u0631"
    ],
    "name:hin_x_preferred":[
        "\u0932\u0916\u0940\u092a\u0941\u0930"
    ],
    "name:ita_x_preferred":[
        "Lakhipur"
    ],
    "name:msa_x_preferred":[
        "Lakhipur"
    ],
    "name:new_x_preferred":[
        "\u0932\u0916\u093f\u092a\u0941\u0930"
    ],
    "name:urd_x_preferred":[
        "\u0644\u06a9\u06be\u06cc\u067e\u0648\u0631"
    ],
    "name:vie_x_preferred":[
        "Lakhipur"
    ],
    "name:zho_x_preferred":[
        "\u62c9\u57fa\u666e\u5c14"
    ],
    "wof:name":"Lakhipur",
    "wof:placetype":"locality"
},
  "geometry": {"coordinates":[78.71641,24.90828],"type":"Point"}
}