{
  "type": "Feature",
  "properties": {
    "iso:country":"IN",
    "ks:ks_name":"5 B",
    "ks:ks_pop":42,
    "ks:ks_type":"HABITATION",
    "name:eng_x_preferred":[
        "5 B"
    ],
    "wof:name":"5 B",
    "wof:placetype":"locality",
    "wof:population":42
},
  "geometry": {"coordinates":[73.950661,30.134667],"type":"Point"}
}