{
  "type": "Feature",
  "properties": {
    "iso:country":"IN",
    "ks:ks_name":"Pedapeta",
    "ks:ks_pop":587,
    "ks:ks_type":"HABITATION",
    "ks:ks_uagg_main":0,
    "name:eng_x_preferred":[
        "Pedapeta"
    ],
    "wof:name":"Pedapeta",
    "wof:placetype":"neighbourhood",
    "wof:population":587
},
  "geometry": {"coordinates":[81.64810300000001,16.437896],"type":"Point"}
}