{
  "type": "Feature",
  "properties": {
    "iso:country":"IN",
    "ks:ks_name":"Ravwadi",
    "ks:ks_pop":106,
    "ks:ks_type":"HABITATION",
    "name:eng_x_preferred":[
        "Ravwadi"
    ],
    "wof:name":"Ravwadi",
    "wof:placetype":"locality",
    "wof:population":106
},
  "geometry": {"coordinates":[73.764456,16.659247],"type":"Point"}
}