{
  "type": "Feature",
  "properties": {
    "iso:country":"IN",
    "ks:ks_name":"Mokhalingapuram",
    "ks:ks_pop":358,
    "ks:ks_type":"VILLAGE",
    "name:eng_x_preferred":[
        "Mokhalingapuram"
    ],
    "wof:name":"Mokhalingapuram",
    "wof:placetype":"locality",
    "wof:population":358
},
  "geometry": {"coordinates":[84.208168,18.66397],"type":"Point"}
}