{
  "type": "Feature",
  "properties": {
    "iso:country":"IN",
    "ks:ks_name":"Palasgaon Makta",
    "ks:ks_pop":0,
    "ks:ks_type":"VILLAGE",
    "name:eng_x_preferred":[
        "Palasgaon Makta"
    ],
    "wof:name":"Palasgaon Makta",
    "wof:placetype":"locality",
    "wof:population":0
},
  "geometry": {"coordinates":[79.76188,20.397351],"type":"Point"}
}