{
  "type": "Feature",
  "properties": {
    "iso:country":"IN",
    "ks:ks_name":"Chhaprai Khalsa",
    "ks:ks_pop":350,
    "ks:ks_type":"VILLAGE",
    "name:eng_x_preferred":[
        "Chhaprai Khalsa"
    ],
    "wof:name":"Chhaprai Khalsa",
    "wof:placetype":"locality",
    "wof:population":350
},
  "geometry": {"coordinates":[77.83395899999999,24.649281],"type":"Point"}
}