{
  "type": "Feature",
  "properties": {
    "iso:country":"IN",
    "ks:ks_name":"Matiasasan",
    "ks:ks_pop":102,
    "ks:ks_type":"VILLAGE",
    "ks:ks_uagg_main":0,
    "name:eng_x_preferred":[
        "Matiasasan"
    ],
    "wof:name":"Matiasasan",
    "wof:placetype":"neighbourhood",
    "wof:population":102
},
  "geometry": {"coordinates":[86.135925,20.814478],"type":"Point"}
}