{
  "type": "Feature",
  "properties": {
    "iso:country":"IN",
    "ks:ks_alt_nam":"KHABLA PARA",
    "ks:ks_name":"Khabla Para",
    "ks:ks_pop":575,
    "ks:ks_type":"HABITATION",
    "name:eng_x_preferred":[
        "Khabla Para"
    ],
    "wof:name":"Khabla Para",
    "wof:placetype":"locality",
    "wof:population":575
},
  "geometry": {"coordinates":[88.533556,26.610492],"type":"Point"}
}