{
  "type": "Feature",
  "properties": {
    "gn:admin1_code":"2.0",
    "gn:admin2_code":"544.0",
    "gn:asciiname":"Mulapadu",
    "gn:country_code":"IN",
    "gn:dem":162,
    "gn:feature_class":"P",
    "gn:feature_code":"PPL",
    "gn:name":"M\u016blap\u0101du",
    "gn:population":0,
    "gn:timezone":"Asia/Kolkata",
    "iso:country":"IN",
    "ks:ks_name":"Mulapadu",
    "ks:ks_pop":101,
    "ks:ks_type":"HABITATION",
    "name:eng_x_preferred":[
        "Mulapadu"
    ],
    "name:hin_x_preferred":[
        "\u092e\u0941\u0932\u092a\u093e\u0921\u0941"
    ],
    "name:new_x_preferred":[
        "\u092e\u0941\u0932\u092a\u093e\u0921\u0941"
    ],
    "name:tel_x_preferred":[
        "\u0c2e\u0c42\u0c32\u0c2a\u0c3e\u0c21\u0c41"
    ],
    "wof:name":"Mulapadu",
    "wof:placetype":"locality",
    "wof:population":101
},
  "geometry": {"coordinates":[83.23580699999999,18.229835],"type":"Point"}
}