{
  "type": "Feature",
  "properties": {
    "iso:country":"IN",
    "ks:ks_name":"Turuturi",
    "ks:ks_pop":0,
    "ks:ks_type":"VILLAGE",
    "name:eng_x_preferred":[
        "Turuturi"
    ],
    "wof:name":"Turuturi",
    "wof:placetype":"locality",
    "wof:population":0
},
  "geometry": {"coordinates":[84.93352,20.133065],"type":"Point"}
}