{
  "type": "Feature",
  "properties": {
    "iso:country":"IN",
    "ks:ks_name":"Chadakmara",
    "ks:ks_pop":62,
    "ks:ks_type":"VILLAGE",
    "name:eng_x_preferred":[
        "Chadakmara"
    ],
    "wof:name":"Chadakmara",
    "wof:placetype":"locality",
    "wof:population":62
},
  "geometry": {"coordinates":[84.72080800000001,21.512826],"type":"Point"}
}