{
  "type": "Feature",
  "properties": {
    "iso:country":"IN",
    "ks:ks_name":"Vandariya",
    "ks:ks_pop":129,
    "ks:ks_type":"HABITATION",
    "name:eng_x_preferred":[
        "Vandariya"
    ],
    "wof:name":"Vandariya",
    "wof:placetype":"locality",
    "wof:population":129
},
  "geometry": {"coordinates":[73.168978,23.081025],"type":"Point"}
}