{
  "type": "Feature",
  "properties": {
    "gn:admin1_code":"12.0",
    "gn:admin2_code":"22.0",
    "gn:asciiname":"Uperli Mautalian",
    "gn:country_code":"IN",
    "gn:dem":401,
    "gn:feature_class":"P",
    "gn:feature_code":"PPL",
    "gn:name":"Uperli Mautali\u0101n",
    "gn:population":0,
    "gn:timezone":"Asia/Kolkata",
    "iso:country":"IN",
    "name:und_x_variant":[
        "Uperli Mautali\u0101n",
        "Mautali\u0101n Kal\u0101n"
    ],
    "wof:name":"Uperli Mautalian",
    "wof:placetype":"locality"
},
  "geometry": {"coordinates":[75.07561,32.62296],"type":"Point"}
}