{
  "type": "Feature",
  "properties": {
    "gn:admin1_code":"2.0",
    "gn:admin2_code":"550.0",
    "gn:asciiname":"Chinnarayanipalem",
    "gn:country_code":"IN",
    "gn:dem":7,
    "gn:feature_class":"P",
    "gn:feature_code":"PPL",
    "gn:name":"Chinnar\u0101yanip\u0101lem",
    "gn:population":0,
    "gn:timezone":"Asia/Kolkata",
    "iso:country":"IN",
    "wof:name":"Chinnarayanipalem",
    "wof:placetype":"locality"
},
  "geometry": {"coordinates":[80.08543,14.75995],"type":"Point"}
}