{
  "type": "Feature",
  "properties": {
    "iso:country":"IN",
    "ks:ks_name":"Bar-Athiabari",
    "ks:ks_pop":1419,
    "ks:ks_type":"VILLAGE",
    "ks:ks_uagg_main":0,
    "name:eng_x_preferred":[
        "Bar-Athiabari"
    ],
    "wof:name":"Bar-Athiabari",
    "wof:placetype":"neighbourhood",
    "wof:population":1419
},
  "geometry": {"coordinates":[91.963714,26.429479],"type":"Point"}
}