{
  "type": "Feature",
  "properties": {
    "iso:country":"IN",
    "ks:ks_name":"Kharbeel",
    "ks:ks_pop":25,
    "ks:ks_type":"VILLAGE",
    "name:eng_x_preferred":[
        "Kharbeel"
    ],
    "wof:name":"Kharbeel",
    "wof:placetype":"locality",
    "wof:population":25
},
  "geometry": {"coordinates":[92.224734,26.150772],"type":"Point"}
}