{
  "type": "Feature",
  "properties": {
    "iso:country":"IN",
    "ks:ks_alt_nam":"Durga baag",
    "ks:ks_name":"Durga Baag",
    "ks:ks_pop":120,
    "ks:ks_type":"HABITATION",
    "name:eng_x_preferred":[
        "Durga Baag"
    ],
    "wof:name":"Durga Baag",
    "wof:placetype":"locality",
    "wof:population":120
},
  "geometry": {"coordinates":[80.424657,26.808239],"type":"Point"}
}