{
  "type": "Feature",
  "properties": {
    "gn:admin1_code":"36.0",
    "gn:admin2_code":"162.0",
    "gn:asciiname":"Nawada Lodhi",
    "gn:country_code":"IN",
    "gn:dem":145,
    "gn:feature_class":"P",
    "gn:feature_code":"PPL",
    "gn:name":"Naw\u0101da Lodhi",
    "gn:population":0,
    "gn:timezone":"Asia/Kolkata",
    "iso:country":"IN",
    "name:und_x_variant":[
        "Kar\u016bpaya",
        "Naw\u0101da Lodhi"
    ],
    "wof:name":"Nawada Lodhi",
    "wof:placetype":"locality"
},
  "geometry": {"coordinates":[79.55354,26.83361],"type":"Point"}
}