{
  "type": "Feature",
  "properties": {
    "iso:country":"IN",
    "ks:ks_name":"Konjeripalayam",
    "ks:ks_pop":222,
    "ks:ks_type":"HABITATION",
    "name:eng_x_preferred":[
        "Konjeripalayam"
    ],
    "wof:name":"Konjeripalayam",
    "wof:placetype":"locality",
    "wof:population":222
},
  "geometry": {"coordinates":[79.840447,13.246109],"type":"Point"}
}