{
  "type": "Feature",
  "properties": {
    "gn:admin1_code":"16",
    "gn:admin2_code":"525.0",
    "gn:asciiname":"Karla",
    "gn:country_code":"IN",
    "gn:dem":639,
    "gn:feature_class":"P",
    "gn:feature_code":"PPL",
    "gn:name":"K\u0101rla",
    "gn:population":0,
    "gn:timezone":"Asia/Kolkata",
    "iso:country":"IN",
    "name:ceb_x_preferred":[
        "Karla"
    ],
    "name:ces_x_preferred":[
        "Karla"
    ],
    "name:deu_x_preferred":[
        "Karla"
    ],
    "name:est_x_preferred":[
        "Karla"
    ],
    "name:fin_x_preferred":[
        "Karla"
    ],
    "name:hye_x_preferred":[
        "\u053f\u0561\u057c\u056c\u0561"
    ],
    "name:ita_x_preferred":[
        "Karla"
    ],
    "name:jpn_x_preferred":[
        "\u30ab\u30fc\u30e9"
    ],
    "name:nld_x_preferred":[
        "Karla"
    ],
    "name:pol_x_preferred":[
        "Karla"
    ],
    "name:rus_x_preferred":[
        "\u041a\u0430\u0440\u043b\u0430"
    ],
    "name:srp_x_preferred":[
        "\u041a\u0430\u0440\u043b\u0430"
    ],
    "name:swe_x_preferred":[
        "Karla"
    ],
    "name:vol_x_preferred":[
        "Karla"
    ],
    "wof:name":"Karla",
    "wof:placetype":"locality"
},
  "geometry": {"coordinates":[76.21439000000002,17.99507000000001],"type":"Point"}
}