{
  "type": "Feature",
  "properties": {
    "gn:admin1_code":"11",
    "gn:admin2_code":"33.0",
    "gn:asciiname":"Shal",
    "gn:country_code":"IN",
    "gn:dem":1578,
    "gn:feature_class":"P",
    "gn:feature_code":"PPL",
    "gn:name":"Shal",
    "gn:population":0,
    "gn:timezone":"Asia/Kolkata",
    "iso:country":"IN",
    "name:ara_x_preferred":[
        "\u0634\u0627\u0644"
    ],
    "name:aze_x_preferred":[
        "\u015eal"
    ],
    "name:ceb_x_preferred":[
        "Sh\u0101l"
    ],
    "name:fas_x_preferred":[
        "\u0634\u0627\u0644"
    ],
    "name:ita_x_preferred":[
        "Shal"
    ],
    "name:mlg_x_preferred":[
        "Shal"
    ],
    "name:pol_x_preferred":[
        "Szal"
    ],
    "name:rus_x_preferred":[
        "\u0428\u0430\u043b\u044c"
    ],
    "name:swe_x_preferred":[
        "Sh\u0101l"
    ],
    "name:tur_x_preferred":[
        "\u015eal"
    ],
    "wof:name":"Shal",
    "wof:placetype":"locality"
},
  "geometry": {"coordinates":[77.15334,31.13778],"type":"Point"}
}