{
  "type": "Feature",
  "properties": {
    "gn:admin1_code":"11",
    "gn:admin2_code":"33.0",
    "gn:asciiname":"Shal",
    "gn:country_code":"IN",
    "gn:dem":1578,
    "gn:feature_class":"P",
    "gn:feature_code":"PPL",
    "gn:name":"Shal",
    "gn:population":0,
    "gn:timezone":"Asia/Kolkata",
    "iso:country":"IN",
    "wof:name":"Shal",
    "wof:placetype":"locality"
},
  "geometry": {"coordinates":[77.15334,31.13778],"type":"Point"}
}