{
  "type": "Feature",
  "properties": {
    "iso:country":"IN",
    "ks:ks_alt_nam":"MANGLABARI JAYGAON BAZAR",
    "ks:ks_name":"Manglabari Jaygaon Bazar",
    "ks:ks_pop":397,
    "ks:ks_type":"HABITATION",
    "ks:ks_uagg_main":0,
    "name:eng_x_preferred":[
        "Manglabari Jaygaon Bazar"
    ],
    "wof:name":"Manglabari Jaygaon Bazar",
    "wof:placetype":"neighbourhood",
    "wof:population":397
},
  "geometry": {"coordinates":[89.380448,26.847619],"type":"Point"}
}