{
  "type": "Feature",
  "properties": {
    "iso:country":"IN",
    "ks:ks_alt_nam":"KANHUKHAB",
    "ks:ks_name":"Kanhukhab",
    "ks:ks_pop":124,
    "ks:ks_type":"HABITATION",
    "name:eng_x_preferred":[
        "Kanhukhab"
    ],
    "wof:name":"Kanhukhab",
    "wof:placetype":"locality",
    "wof:population":124
},
  "geometry": {"coordinates":[85.04327600000001,24.017076],"type":"Point"}
}