{
  "type": "Feature",
  "properties": {
    "gn:admin1_code":"28.0",
    "gn:admin2_code":"341",
    "gn:asciiname":"Jhikra",
    "gn:country_code":"IN",
    "gn:dem":15,
    "gn:feature_class":"P",
    "gn:feature_code":"PPL",
    "gn:name":"Jhikra",
    "gn:population":0,
    "gn:timezone":"Asia/Kolkata",
    "iso:country":"IN",
    "wof:name":"Jhikra",
    "wof:placetype":"locality"
},
  "geometry": {"coordinates":[87.91391999999998,22.6209],"type":"Point"}
}