{
  "type": "Feature",
  "properties": {
    "iso:country":"IN",
    "ks:ks_name":"Dalelpura",
    "ks:ks_pop":824,
    "ks:ks_type":"HABITATION",
    "name:eng_x_preferred":[
        "Dalelpura"
    ],
    "wof:name":"Dalelpura",
    "wof:placetype":"locality",
    "wof:population":824
},
  "geometry": {"coordinates":[76.74141299999999,24.107573],"type":"Point"}
}