{
  "type": "Feature",
  "properties": {
    "iso:country":"IN",
    "name:ara_x_preferred":[
        "\u0645\u062c\u062a\u0645\u0639 \u0623\u0643\u0634\u0627\u064a"
    ],
    "name:ben_bn_x_preferred":[
        "\u0985\u0995\u09cd\u09b7\u09af\u09bc \u09b8\u09cb\u09b8\u09be\u0987\u099f\u09bf"
    ],
    "name:ben_in_x_preferred":[
        "\u0985\u0995\u09cd\u09b7\u09af\u09bc \u09b8\u09cb\u09b8\u09be\u0987\u099f\u09bf"
    ],
    "name:eng_x_preferred":[
        "Akshay Society"
    ],
    "name:guj_x_preferred":[
        "\u0a85\u0a95\u0acd\u0ab7\u0aaf \u0ab8\u0acb\u0ab8\u0abe\u0aaf\u0a9f\u0ac0"
    ],
    "name:hin_x_preferred":[
        "\u0905\u0915\u094d\u0937\u092f \u0938\u094b\u0938\u093e\u0907\u091f\u0940"
    ],
    "name:kan_x_preferred":[
        "\u0c85\u0c95\u0ccd\u0cb7\u0caf\u0ccd"
    ],
    "name:mal_x_preferred":[
        "\u0d05\u0d15\u0d4d\u0d37\u0d2f\u0d4d \u0d38\u0d4a\u0d38\u0d48\u0d31\u0d4d\u0d31\u0d3f"
    ],
    "name:mar_x_preferred":[
        "\u0905\u0915\u094d\u0937\u092f \u0938\u094b\u0938\u093e\u092f\u091f\u0940"
    ],
    "name:pan_x_preferred":[
        "\u0a05\u0a15\u0a36\u0a48 \u0a38\u0a4b\u0a38\u0a3e\u0a07\u0a1f\u0a40"
    ],
    "name:tam_x_preferred":[
        "\u0b85\u0b95\u0bcd\u0b9a\u0baf\u0bcd \u0b9a\u0bae\u0bc2\u0b95\u0bae\u0bcd"
    ],
    "name:tel_x_preferred":[
        "\u0c05\u0c15\u0c4d\u0c37\u0c2f\u0c4d \u0c38\u0c4a\u0c38\u0c48\u0c1f\u0c40"
    ],
    "name:urd_x_preferred":[
        "\u0627\u06a9\u0634\u06d2 \u0633\u0648\u0633\u0627\u0626\u0679\u06cc"
    ],
    "qs:gn_local":0,
    "qs:local_max":206,
    "qs:local_sum":206,
    "qs:localhoods":1,
    "qs:name":"Akshay Society",
    "qs:name_adm0":"India",
    "qs:name_adm1":"Rajasthan",
    "qs:name_adm2":"Sirohi",
    "qs:name_local":"Mount Abu",
    "qs:photo_max":36,
    "qs:photo_sum":206,
    "qs:placetype":"Suburb",
    "qs:quad_count":21,
    "qs:woe_adm0":23424848,
    "qs:woe_adm1":2345757,
    "qs:woe_adm2":12586674,
    "qs:woe_lau":0,
    "qs:woe_local":2291766,
    "qs:woe_ver":"7.10.0",
    "wof:lang":[
        "eng"
    ],
    "wof:name":"Akshay Society",
    "wof:placetype":"neighbourhood"
},
  "geometry": {"coordinates":[72.710792,24.595378],"type":"Point"}
}