{
  "type": "Feature",
  "properties": {
    "iso:country":"IN",
    "name:eng_x_preferred":[
        "Akshay Society"
    ],
    "name:unk_x_variant":[
        "Akshay Society"
    ],
    "qs:gn_local":0,
    "qs:local_max":206,
    "qs:local_sum":206,
    "qs:localhoods":1,
    "qs:name":"Akshay Society",
    "qs:name_adm0":"India",
    "qs:name_adm1":"Rajasthan",
    "qs:name_adm2":"Sirohi",
    "qs:name_local":"Mount Abu",
    "qs:photo_max":36,
    "qs:photo_sum":206,
    "qs:placetype":"Suburb",
    "qs:quad_count":21,
    "qs:woe_adm0":23424848,
    "qs:woe_adm1":2345757,
    "qs:woe_adm2":12586674,
    "qs:woe_lau":0,
    "qs:woe_local":2291766,
    "qs:woe_ver":"7.10.0",
    "wof:lang":[
        "eng"
    ],
    "wof:name":"Akshay Society",
    "wof:placetype":"neighbourhood"
},
  "geometry": {"coordinates":[72.710792,24.595378],"type":"Point"}
}