{
  "type": "Feature",
  "properties": {
    "gn:admin1_code":"11",
    "gn:admin2_code":"23.0",
    "gn:asciiname":"Chalaru",
    "gn:country_code":"IN",
    "gn:dem":1806,
    "gn:feature_class":"P",
    "gn:feature_code":"PPL",
    "gn:name":"Chal\u0101ru",
    "gn:population":0,
    "gn:timezone":"Asia/Kolkata",
    "iso:country":"IN",
    "wof:name":"Chalaru",
    "wof:placetype":"locality"
},
  "geometry": {"coordinates":[76.20649,32.64393],"type":"Point"}
}