{
  "type": "Feature",
  "properties": {
    "iso:country":"IN",
    "ks:ks_name":"Bandhardih",
    "ks:ks_pop":495,
    "ks:ks_type":"HABITATION",
    "name:eng_x_preferred":[
        "Bandhardih"
    ],
    "wof:name":"Bandhardih",
    "wof:placetype":"locality",
    "wof:population":495
},
  "geometry": {"coordinates":[86.127206,23.574562],"type":"Point"}
}