{
  "type": "Feature",
  "properties": {
    "iso:country":"IN",
    "ks:ks_name":"Kasimpur",
    "ks:ks_pop":313,
    "ks:ks_type":"VILLAGE",
    "ks:ks_uagg_main":0,
    "name:eng_x_preferred":[
        "Kasimpur"
    ],
    "wof:name":"Kasimpur",
    "wof:placetype":"neighbourhood",
    "wof:population":313
},
  "geometry": {"coordinates":[87.37154200000001,21.652343],"type":"Point"}
}