{
  "type": "Feature",
  "properties": {
    "gn:admin1_code":"36",
    "gn:admin2_code":"174.0",
    "gn:asciiname":"Deobhita",
    "gn:country_code":"IN",
    "gn:dem":103,
    "gn:feature_class":"P",
    "gn:feature_code":"PPL",
    "gn:name":"Deobh\u012bta",
    "gn:population":0,
    "gn:timezone":"Asia/Kolkata",
    "iso:country":"IN",
    "ks:ks_alt_nam":"Deobh\u012bta",
    "ks:ks_name":"Deobhita",
    "ks:ks_type":"VILLAGE",
    "ks:ks_uagg_main":0,
    "name:eng_x_preferred":[
        "Deobhita"
    ],
    "name:eng_x_variant":[
        "Deobh\u012bta"
    ],
    "wof:name":"Deobhita",
    "wof:placetype":"neighbourhood"
},
  "geometry": {"coordinates":[81.441965,25.61182],"type":"Point"}
}