{
  "type": "Feature",
  "properties": {
    "gn:admin1_code":"11",
    "gn:admin2_code":"30.0",
    "gn:asciiname":"Kangri",
    "gn:country_code":"IN",
    "gn:dem":604,
    "gn:feature_class":"P",
    "gn:feature_code":"PPL",
    "gn:name":"K\u0101ngri",
    "gn:population":0,
    "gn:timezone":"Asia/Kolkata",
    "iso:country":"IN",
    "name:ceb_x_preferred":[
        "Kangri"
    ],
    "name:swe_x_preferred":[
        "Kangri"
    ],
    "wof:name":"Kangri",
    "wof:placetype":"locality"
},
  "geometry": {"coordinates":[76.79496,31.44729],"type":"Point"}
}