{
  "type": "Feature",
  "properties": {
    "gn:admin1_code":"36",
    "gn:admin2_code":"136.0",
    "gn:asciiname":"Saharia Narpat",
    "gn:country_code":"IN",
    "gn:dem":200,
    "gn:feature_class":"P",
    "gn:feature_code":"PPL",
    "gn:name":"Saharia N\u0101rpat",
    "gn:population":0,
    "gn:timezone":"Asia/Kolkata",
    "iso:country":"IN",
    "wof:name":"Saharia Narpat",
    "wof:placetype":"locality"
},
  "geometry": {"coordinates":[78.96687,28.92455],"type":"Point"}
}