{
  "type": "Feature",
  "properties": {
    "gn:admin1_code":"36",
    "gn:admin2_code":"134.0",
    "gn:asciiname":"Isapur",
    "gn:country_code":"IN",
    "gn:dem":237,
    "gn:feature_class":"P",
    "gn:feature_code":"PPL",
    "gn:name":"Is\u0101pur",
    "gn:population":0,
    "gn:timezone":"Asia/Kolkata",
    "iso:country":"IN",
    "name:und_x_variant":[
        "Is\u0101pur",
        "Phariy\u0101pur"
    ],
    "wof:name":"Isapur",
    "wof:placetype":"locality"
},
  "geometry": {"coordinates":[78.26964,29.31417],"type":"Point"}
}