{
  "type": "Feature",
  "properties": {
    "iso:country":"IN",
    "ks:ks_name":"Maldewadi",
    "ks:ks_pop":635,
    "ks:ks_type":"HABITATION",
    "name:eng_x_preferred":[
        "Maldewadi"
    ],
    "wof:name":"Maldewadi",
    "wof:placetype":"locality",
    "wof:population":635
},
  "geometry": {"coordinates":[73.503333,17.188333],"type":"Point"}
}