{
  "type": "Feature",
  "properties": {
    "gn:admin1_code":"12.0",
    "gn:admin2_code":"004",
    "gn:asciiname":"Chulichang",
    "gn:country_code":"IN",
    "gn:dem":2685,
    "gn:feature_class":"P",
    "gn:feature_code":"PPL",
    "gn:name":"Chulichang",
    "gn:population":0,
    "gn:timezone":"Asia/Kolkata",
    "iso:country":"IN",
    "wof:name":"Chulichang",
    "wof:placetype":"locality"
},
  "geometry": {"coordinates":[76.31088000000003,34.66895],"type":"Point"}
}