{
  "type": "Feature",
  "properties": {
    "iso:country":"IN",
    "ks:ks_name":"Matkhor",
    "ks:ks_pop":198,
    "ks:ks_type":"VILLAGE",
    "name:eng_x_preferred":[
        "Matkhor"
    ],
    "wof:name":"Matkhor",
    "wof:placetype":"locality",
    "wof:population":198
},
  "geometry": {"coordinates":[87.25687600000001,24.327359],"type":"Point"}
}