{
  "type": "Feature",
  "properties": {
    "iso:country":"IN",
    "ks:ks_name":"Burusi",
    "ks:ks_pop":133,
    "ks:ks_type":"VILLAGE",
    "name:eng_x_preferred":[
        "Burusi"
    ],
    "wof:name":"Burusi",
    "wof:placetype":"locality",
    "wof:population":133
},
  "geometry": {"coordinates":[84.303287,19.174021],"type":"Point"}
}