{
  "type": "Feature",
  "properties": {
    "gn:admin1_code":"12.0",
    "gn:admin2_code":"7.0",
    "gn:asciiname":"Nagrota Gujru",
    "gn:country_code":"IN",
    "gn:dem":760,
    "gn:feature_class":"P",
    "gn:feature_code":"PPL",
    "gn:name":"Nagrota Gujru",
    "gn:population":0,
    "gn:timezone":"Asia/Kolkata",
    "iso:country":"IN",
    "wof:name":"Nagrota Gujru",
    "wof:placetype":"locality"
},
  "geometry": {"coordinates":[75.39471,32.64812],"type":"Point"}
}