{
  "type": "Feature",
  "properties": {
    "iso:country":"IN",
    "ks:ks_name":"Keloth Venkatya Thanda",
    "ks:ks_pop":221,
    "ks:ks_type":"HABITATION",
    "name:eng_x_preferred":[
        "Keloth Venkatya Thanda"
    ],
    "wof:name":"Keloth Venkatya Thanda",
    "wof:placetype":"locality",
    "wof:population":221
},
  "geometry": {"coordinates":[79.801535,17.339551],"type":"Point"}
}