{
  "type": "Feature",
  "properties": {
    "iso:country":"IN",
    "ks:ks_name":"Chamroli",
    "ks:ks_pop":237,
    "ks:ks_type":"VILLAGE",
    "ks:ks_uagg_main":0,
    "name:eng_x_preferred":[
        "Chamroli"
    ],
    "wof:name":"Chamroli",
    "wof:placetype":"neighbourhood",
    "wof:population":237
},
  "geometry": {"coordinates":[80.13269200000001,29.430215],"type":"Point"}
}