{
  "type": "Feature",
  "properties": {
    "iso:country":"IN",
    "ks:ks_name":"Kauoha",
    "ks:ks_pop":1166,
    "ks:ks_type":"HABITATION",
    "name:eng_x_preferred":[
        "Kauoha"
    ],
    "wof:name":"Kauoha",
    "wof:placetype":"locality",
    "wof:population":1166
},
  "geometry": {"coordinates":[79.73379799999999,27.740825],"type":"Point"}
}