{
  "type": "Feature",
  "properties": {
    "iso:country":"IN",
    "ks:ks_name":"Pure Chhiddi",
    "ks:ks_pop":100,
    "ks:ks_type":"HABITATION",
    "name:eng_x_preferred":[
        "Pure Chhiddi"
    ],
    "wof:name":"Pure Chhiddi",
    "wof:placetype":"locality",
    "wof:population":100
},
  "geometry": {"coordinates":[81.42635300000001,26.549494],"type":"Point"}
}