{
  "type": "Feature",
  "properties": {
    "iso:country":"IN",
    "ks:ks_name":"Boratwadi",
    "ks:ks_pop":257,
    "ks:ks_type":"HABITATION",
    "name:eng_x_preferred":[
        "Boratwadi"
    ],
    "wof:name":"Boratwadi",
    "wof:placetype":"locality",
    "wof:population":257
},
  "geometry": {"coordinates":[74.88434700000001,17.944878],"type":"Point"}
}