{
  "type": "Feature",
  "properties": {
    "iso:country":"IN",
    "ks:ks_name":"Pure Ayodhya",
    "ks:ks_pop":367,
    "ks:ks_type":"HABITATION",
    "name:eng_x_preferred":[
        "Pure Ayodhya"
    ],
    "wof:name":"Pure Ayodhya",
    "wof:placetype":"locality",
    "wof:population":367
},
  "geometry": {"coordinates":[81.581872,25.499392],"type":"Point"}
}