{
  "type": "Feature",
  "properties": {
    "gn:admin1_code":"11.0",
    "gn:admin2_code":"27.0",
    "gn:asciiname":"Maidangarh",
    "gn:country_code":"IN",
    "gn:dem":1971,
    "gn:feature_class":"P",
    "gn:feature_code":"PPL",
    "gn:name":"Maid\u0101ngarh",
    "gn:population":0,
    "gn:timezone":"Asia/Kolkata",
    "iso:country":"IN",
    "wof:name":"Maidangarh",
    "wof:placetype":"locality"
},
  "geometry": {"coordinates":[77.07625999999998,31.42718],"type":"Point"}
}