{
  "type": "Feature",
  "properties": {
    "iso:country":"IN",
    "ks:ks_name":"Gaokarwadi",
    "ks:ks_pop":145,
    "ks:ks_type":"HABITATION",
    "name:eng_x_preferred":[
        "Gaokarwadi"
    ],
    "wof:name":"Gaokarwadi",
    "wof:placetype":"locality",
    "wof:population":145
},
  "geometry": {"coordinates":[73.848063,16.177661],"type":"Point"}
}