{
  "type": "Feature",
  "properties": {
    "gn:admin1_code":"34.0",
    "gn:admin2_code":"224.0",
    "gn:asciiname":"Dostani Arazi",
    "gn:country_code":"IN",
    "gn:dem":42,
    "gn:feature_class":"P",
    "gn:feature_code":"PPL",
    "gn:name":"Dostani Ar\u0101zi",
    "gn:population":0,
    "gn:timezone":"Asia/Kolkata",
    "iso:country":"IN",
    "ks:ks_name":"Dostani Arazi",
    "ks:ks_pop":178,
    "ks:ks_type":"VILLAGE",
    "ks:ks_uagg_main":0,
    "name:eng_x_preferred":[
        "Dostani Arazi"
    ],
    "wof:name":"Dostani Arazi",
    "wof:placetype":"neighbourhood",
    "wof:population":178
},
  "geometry": {"coordinates":[87.00854099999999,25.137629],"type":"Point"}
}