{
  "type": "Feature",
  "properties": {
    "iso:country":"IN",
    "ks:ks_name":"Fazal Guri",
    "ks:ks_pop":95,
    "ks:ks_type":"HABITATION",
    "name:eng_x_preferred":[
        "Fazal Guri"
    ],
    "wof:name":"Fazal Guri",
    "wof:placetype":"locality",
    "wof:population":95
},
  "geometry": {"coordinates":[82.499948,27.230313],"type":"Point"}
}