{
  "type": "Feature",
  "properties": {
    "iso:country":"IN",
    "ks:ks_alt_nam":"K.B Circle",
    "ks:ks_name":"K.b Circle",
    "ks:ks_pop":44,
    "ks:ks_type":"HABITATION",
    "name:eng_x_preferred":[
        "K.b Circle"
    ],
    "wof:name":"K.b Circle",
    "wof:placetype":"locality",
    "wof:population":44
},
  "geometry": {"coordinates":[74.972166,13.94377],"type":"Point"}
}