{
  "type": "Feature",
  "properties": {
    "gn:admin1_code":"36.0",
    "gn:admin2_code":"138.0",
    "gn:asciiname":"Rasulpur Zahid",
    "gn:country_code":"IN",
    "gn:dem":226,
    "gn:feature_class":"P",
    "gn:feature_code":"PPL",
    "gn:name":"Ras\u016blpur Z\u0101hid",
    "gn:population":0,
    "gn:timezone":"Asia/Kolkata",
    "iso:country":"IN",
    "wof:name":"Rasulpur Zahid",
    "wof:placetype":"locality"
},
  "geometry": {"coordinates":[77.4735,29.03637],"type":"Point"}
}