{
  "type": "Feature",
  "properties": {
    "gn:admin1_code":"34.0",
    "gn:admin2_code":"214.0",
    "gn:asciiname":"Patuwaha",
    "gn:country_code":"IN",
    "gn:dem":48,
    "gn:feature_class":"P",
    "gn:feature_code":"PPL",
    "gn:name":"Patuw\u0101ha",
    "gn:population":0,
    "gn:timezone":"Asia/Kolkata",
    "iso:country":"IN",
    "ks:ks_alt_nam":"Patuw\u0101ha",
    "ks:ks_name":"Patuwaha",
    "ks:ks_pop":4244,
    "ks:ks_type":"VILLAGE",
    "ks:ks_uagg_main":0,
    "name:eng_x_preferred":[
        "Patuwaha"
    ],
    "name:eng_x_variant":[
        "Patuw\u0101ha"
    ],
    "wof:name":"Patuwaha",
    "wof:placetype":"locality",
    "wof:population":4244
},
  "geometry": {"coordinates":[86.63979500000001,25.882345],"type":"Point"}
}