{
  "type": "Feature",
  "properties": {
    "iso:country":"IN",
    "ks:ks_name":"Manjodi",
    "ks:ks_pop":514,
    "ks:ks_type":"HABITATION",
    "name:eng_x_preferred":[
        "Manjodi"
    ],
    "wof:name":"Manjodi",
    "wof:placetype":"locality",
    "wof:population":514
},
  "geometry": {"coordinates":[86.635217,23.145564],"type":"Point"}
}