{
  "type": "Feature",
  "properties": {
    "gn:admin1_code":"12.0",
    "gn:admin2_code":"17.0",
    "gn:asciiname":"Zaban",
    "gn:country_code":"IN",
    "gn:dem":2429,
    "gn:feature_class":"P",
    "gn:feature_code":"PPL",
    "gn:name":"Zaban",
    "gn:population":0,
    "gn:timezone":"Asia/Kolkata",
    "iso:country":"IN",
    "name:cat_x_preferred":[
        "Zaban"
    ],
    "name:fra_x_preferred":[
        "Zaban"
    ],
    "name:glg_x_preferred":[
        "Zabano"
    ],
    "name:ita_x_preferred":[
        "Zabano"
    ],
    "name:rus_x_preferred":[
        "\u0417\u0430\u0431\u0430\u043d"
    ],
    "wof:name":"Zaban",
    "wof:placetype":"locality"
},
  "geometry": {"coordinates":[75.14171999999998,33.49825],"type":"Point"}
}