{
  "type": "Feature",
  "properties": {
    "gn:admin1_code":"12.0",
    "gn:admin2_code":"17.0",
    "gn:asciiname":"Zaban",
    "gn:country_code":"IN",
    "gn:dem":2429,
    "gn:feature_class":"P",
    "gn:feature_code":"PPL",
    "gn:name":"Zaban",
    "gn:population":0,
    "gn:timezone":"Asia/Kolkata",
    "iso:country":"IN",
    "wof:name":"Zaban",
    "wof:placetype":"locality"
},
  "geometry": {"coordinates":[75.14171999999998,33.49825],"type":"Point"}
}