{
  "type": "Feature",
  "properties": {
    "iso:country":"IN",
    "ks:ks_name":"Siyanda",
    "ks:ks_pop":3749,
    "ks:ks_type":"VILLAGE",
    "name:eng_x_preferred":[
        "Siyanda"
    ],
    "wof:name":"Siyanda",
    "wof:placetype":"locality",
    "wof:population":3749
},
  "geometry": {"coordinates":[72.38885000000001,26.344547],"type":"Point"}
}