{
  "type": "Feature",
  "properties": {
    "gn:admin1_code":"23.0",
    "gn:admin2_code":"48.0",
    "gn:asciiname":"Amamnagar",
    "gn:country_code":"IN",
    "gn:dem":245,
    "gn:feature_class":"P",
    "gn:feature_code":"PPL",
    "gn:name":"Am\u0101mnagar",
    "gn:population":0,
    "gn:timezone":"Asia/Kolkata",
    "iso:country":"IN",
    "name:und_x_variant":[
        "Am\u0101mnagar",
        "Niz\u0101ml\u012bw\u0101la"
    ],
    "wof:name":"Amamnagar",
    "wof:placetype":"locality"
},
  "geometry": {"coordinates":[76.29562,30.14642000000001],"type":"Point"}
}