{
  "type": "Feature",
  "properties": {
    "gn:admin1_code":"16",
    "gn:admin2_code":"508.0",
    "gn:asciiname":"Murkuri",
    "gn:country_code":"IN",
    "gn:dem":371,
    "gn:feature_class":"P",
    "gn:feature_code":"PPL",
    "gn:name":"Murkuri",
    "gn:population":0,
    "gn:timezone":"Asia/Kolkata",
    "iso:country":"IN",
    "ks:ks_name":"Murkuti",
    "ks:ks_pop":147,
    "ks:ks_type":"VILLAGE",
    "name:eng_x_preferred":[
        "Murkuti"
    ],
    "name:eng_x_variant":[
        "Murkuri"
    ],
    "wof:name":"Murkuti",
    "wof:placetype":"locality",
    "wof:population":147
},
  "geometry": {"coordinates":[80.356757,20.769433],"type":"Point"}
}