{
  "type": "Feature",
  "properties": {
    "iso:country":"IN",
    "ks:ks_alt_nam":"HARIJAN TOLI",
    "ks:ks_name":"Harijan Toli",
    "ks:ks_pop":283,
    "ks:ks_type":"HABITATION",
    "name:eng_x_preferred":[
        "Harijan Toli"
    ],
    "wof:name":"Harijan Toli",
    "wof:placetype":"locality",
    "wof:population":283
},
  "geometry": {"coordinates":[84.076071,25.499434],"type":"Point"}
}