{
  "type": "Feature",
  "properties": {
    "gn:admin1_code":"11.0",
    "gn:admin2_code":"27.0",
    "gn:asciiname":"Jharehr",
    "gn:country_code":"IN",
    "gn:dem":2074,
    "gn:feature_class":"P",
    "gn:feature_code":"PPL",
    "gn:name":"Jharehr",
    "gn:population":0,
    "gn:timezone":"Asia/Kolkata",
    "iso:country":"IN",
    "wof:name":"Jharehr",
    "wof:placetype":"locality"
},
  "geometry": {"coordinates":[77.28648000000003,31.45698],"type":"Point"}
}