{
  "type": "Feature",
  "properties": {
    "gn:admin1_code":"10.0",
    "gn:admin2_code":"069",
    "gn:asciiname":"Gunthala",
    "gn:country_code":"IN",
    "gn:dem":410,
    "gn:feature_class":"P",
    "gn:feature_code":"PPL",
    "gn:name":"Gunthala",
    "gn:population":0,
    "gn:timezone":"Asia/Kolkata",
    "iso:country":"IN",
    "wof:name":"Gunthala",
    "wof:placetype":"locality"
},
  "geometry": {"coordinates":[76.90545999999998,30.73109],"type":"Point"}
}