{
  "type": "Feature",
  "properties": {
    "gn:admin1_code":"10.0",
    "gn:admin2_code":"069",
    "gn:asciiname":"Gunthala",
    "gn:country_code":"IN",
    "gn:dem":410,
    "gn:feature_class":"P",
    "gn:feature_code":"PPL",
    "gn:name":"Gunthala",
    "gn:population":0,
    "gn:timezone":"Asia/Kolkata",
    "iso:country":"IN",
    "ks:ks_name":"Gumthala",
    "ks:ks_pop":170,
    "ks:ks_type":"VILLAGE",
    "name:eng_x_preferred":[
        "Gumthala"
    ],
    "name:eng_x_variant":[
        "Gunthala"
    ],
    "wof:name":"Gumthala",
    "wof:placetype":"locality",
    "wof:population":170
},
  "geometry": {"coordinates":[76.905097,30.731603],"type":"Point"}
}