{
  "type": "Feature",
  "properties": {
    "iso:country":"IN",
    "ks:ks_name":"Chavanwadi",
    "ks:ks_pop":55,
    "ks:ks_type":"HABITATION",
    "name:eng_x_preferred":[
        "Chavanwadi"
    ],
    "wof:name":"Chavanwadi",
    "wof:placetype":"locality",
    "wof:population":55
},
  "geometry": {"coordinates":[73.4986,16.058439],"type":"Point"}
}