{
  "type": "Feature",
  "properties": {
    "gn:admin1_code":"16.0",
    "gn:admin2_code":"512.0",
    "gn:asciiname":"Jamrun Buzurg",
    "gn:country_code":"IN",
    "gn:dem":483,
    "gn:feature_class":"P",
    "gn:feature_code":"PPL",
    "gn:name":"J\u0101mrun Buzurg",
    "gn:population":0,
    "gn:timezone":"Asia/Kolkata",
    "iso:country":"IN",
    "wof:name":"Jamrun Buzurg",
    "wof:placetype":"neighbourhood"
},
  "geometry": {"coordinates":[76.9517,19.78615],"type":"Point"}
}