{
  "type": "Feature",
  "properties": {
    "iso:country":"IN",
    "name:eng_x_preferred":[
        "Yashaswi Nagar"
    ],
    "name:unk_x_variant":[
        "Yashaswi Nagar"
    ],
    "qs:gn_adm0_cc":"IN",
    "qs:gn_local":1254661,
    "qs:gn_nam_loc":"thane",
    "qs:gn_namadm1":"16",
    "qs:local_max":180,
    "qs:local_sum":621,
    "qs:localhoods":9,
    "qs:name":"Yashaswi Nagar",
    "qs:name_adm0":"India",
    "qs:name_adm1":"Maharashtra",
    "qs:name_adm2":"Thane",
    "qs:name_local":"Thane",
    "qs:photo_max":82,
    "qs:photo_sum":98,
    "qs:placetype":"Suburb",
    "qs:quad_count":6,
    "qs:woe_adm0":23424848,
    "qs:woe_adm1":2345750,
    "qs:woe_adm2":12586551,
    "qs:woe_lau":0,
    "qs:woe_local":2295410,
    "qs:woe_ver":"7.10.0",
    "wof:lang":[
        "eng"
    ],
    "wof:name":"Yashaswi Nagar",
    "wof:placetype":"neighbourhood"
},
  "geometry": {"coordinates":[72.98406799999999,19.22228],"type":"Point"}
}