{
  "type": "Feature",
  "properties": {
    "iso:country":"IN",
    "ks:ks_alt_nam":"GOTA MAGRI",
    "ks:ks_name":"Gota Magri",
    "ks:ks_pop":70,
    "ks:ks_type":"HABITATION",
    "name:eng_x_preferred":[
        "Gota Magri"
    ],
    "wof:name":"Gota Magri",
    "wof:placetype":"locality",
    "wof:population":70
},
  "geometry": {"coordinates":[74.677892,23.839426],"type":"Point"}
}