{
  "type": "Feature",
  "properties": {
    "iso:country":"IN",
    "ks:ks_name":"Badari Shahpur",
    "ks:ks_pop":432,
    "ks:ks_type":"HABITATION",
    "name:eng_x_preferred":[
        "Badari Shahpur"
    ],
    "wof:name":"Badari Shahpur",
    "wof:placetype":"locality",
    "wof:population":432
},
  "geometry": {"coordinates":[81.518162,27.061871],"type":"Point"}
}