{
  "type": "Feature",
  "properties": {
    "gn:country":"IN",
    "gn:fcode":"PPL",
    "gn:pop":22201,
    "iso:country":"IN",
    "name:ast_x_preferred":[
        "Sahawar"
    ],
    "name:bpy_x_preferred":[
        "\u09b8\u09be\u09b9\u09be\u09f1\u09be\u09b0"
    ],
    "name:ceb_x_preferred":[
        "Sah\u0101war"
    ],
    "name:eng_x_preferred":[
        "Sahawar"
    ],
    "name:fra_x_preferred":[
        "Sahawar"
    ],
    "name:hif_x_preferred":[
        "Sahawar"
    ],
    "name:hin_x_preferred":[
        "\u0938\u0939\u093e\u0935\u0930"
    ],
    "name:ita_x_preferred":[
        "Sahawar"
    ],
    "name:mlg_x_preferred":[
        "Sahawar"
    ],
    "name:msa_x_preferred":[
        "Sahawar"
    ],
    "name:nan_x_preferred":[
        "Sahawar"
    ],
    "name:nld_x_preferred":[
        "Sahawar"
    ],
    "name:ori_x_preferred":[
        "\u0b38\u0b3e\u0b39\u0b3e\u0b71\u0b3e\u0b30"
    ],
    "name:pnb_x_preferred":[
        "\u0633\u06c1\u0627\u0648\u0631"
    ],
    "name:pol_x_preferred":[
        "Sahawar"
    ],
    "name:por_x_preferred":[
        "Sahawar"
    ],
    "name:swe_x_preferred":[
        "Sah\u0101war"
    ],
    "name:unk_x_variant":[
        "Sah\u0101war"
    ],
    "name:urd_x_preferred":[
        "\u0633\u06c1\u0627\u0648\u0631"
    ],
    "name:vie_x_preferred":[
        "Sahawar"
    ],
    "name:zho_x_preferred":[
        "\u8428\u54c8\u74e6\u5c14"
    ],
    "qs:name":"Sahar",
    "qs:name_adm0":"India",
    "qs:name_adm1":"Uttar Pradesh",
    "qs:photos_9r":0,
    "qs:photos_sr":0,
    "qs:placetype":"Town",
    "qs:pop_sr":"7",
    "wd:wordcount":73,
    "wof:name":"Sahar",
    "wof:placetype":"locality",
    "wof:population":22201
},
  "geometry": {"coordinates":[78.83358,27.79593],"type":"Point"}
}