{
  "type": "Feature",
  "properties": {
    "gn:country":"IN",
    "gn:fcode":"PPL",
    "gn:population":22201,
    "iso:country":"IN",
    "name:ara_x_preferred":[
        "\u0633\u0627\u0647\u0627\u0631"
    ],
    "name:ast_x_preferred":[
        "Sahawar"
    ],
    "name:ben_bn_x_preferred":[
        "\u09b8\u09b9\u09b0"
    ],
    "name:ben_in_x_preferred":[
        "\u09b8\u09b9\u09b0"
    ],
    "name:bpy_x_preferred":[
        "\u09b8\u09be\u09b9\u09be\u09f1\u09be\u09b0"
    ],
    "name:ceb_x_preferred":[
        "Sah\u0101war"
    ],
    "name:eng_x_preferred":[
        "Sahawar"
    ],
    "name:fas_x_preferred":[
        "\u0633\u0627\u0647\u0627\u0631"
    ],
    "name:fra_x_preferred":[
        "Sahawar"
    ],
    "name:guj_x_preferred":[
        "\u0ab6\u0ab9\u0ab0"
    ],
    "name:guj_x_variant":[
        "\u0ab8\u0abe\u0ab9\u0ab5\u0abe\u0ab0"
    ],
    "name:hif_x_preferred":[
        "Sahawar"
    ],
    "name:hin_x_preferred":[
        "\u0938\u0939\u0930"
    ],
    "name:hin_x_variant":[
        "\u0938\u0939\u093e\u0935\u0930"
    ],
    "name:ita_x_preferred":[
        "Sahawar"
    ],
    "name:kan_x_preferred":[
        "\u0cb8\u0cb9\u0cbe\u0cb0\u0ccd"
    ],
    "name:mal_x_preferred":[
        "\u0d38\u0d39\u0d30\u0d4d\u200d"
    ],
    "name:mar_x_preferred":[
        "\u0938\u0939\u093e\u0930"
    ],
    "name:mlg_x_preferred":[
        "Sahawar"
    ],
    "name:msa_x_preferred":[
        "Sahawar"
    ],
    "name:nan_x_preferred":[
        "Sahawar"
    ],
    "name:nld_x_preferred":[
        "Sahawar"
    ],
    "name:ori_x_preferred":[
        "\u0b38\u0b3e\u0b39\u0b3e\u0b71\u0b3e\u0b30"
    ],
    "name:pan_x_preferred":[
        "\u0a38\u0a3e\u0a39\u0a30"
    ],
    "name:pnb_x_preferred":[
        "\u0633\u06c1\u0627\u0648\u0631"
    ],
    "name:pol_x_preferred":[
        "Sahawar"
    ],
    "name:por_x_preferred":[
        "Sahawar"
    ],
    "name:spa_x_preferred":[
        "Sahawar"
    ],
    "name:swe_x_preferred":[
        "Sah\u0101war"
    ],
    "name:tam_x_preferred":[
        "\u0b9a\u0bb9\u0bbe\u0bb0\u0bcd"
    ],
    "name:tel_x_preferred":[
        "\u0c38\u0c39\u0c3e\u0c30\u0c4d"
    ],
    "name:urd_x_preferred":[
        "\u0633\u06c1\u0627\u0631"
    ],
    "name:urd_x_variant":[
        "\u0633\u06c1\u0627\u0648\u0631"
    ],
    "name:vie_x_preferred":[
        "Sahawar"
    ],
    "name:zho_x_preferred":[
        "\u8428\u54c8\u74e6\u5c14"
    ],
    "qs:name":"Sahar",
    "qs:name_adm0":"India",
    "qs:name_adm1":"Uttar Pradesh",
    "qs:photos_9r":0,
    "qs:photos_sr":0,
    "qs:placetype":"Town",
    "qs:pop_sr":"7",
    "wd:wordcount":73,
    "wof:name":"Sahar",
    "wof:placetype":"locality",
    "wof:population":22201
},
  "geometry": {"coordinates":[78.83358,27.79593],"type":"Point"}
}