{
  "type": "Feature",
  "properties": {
    "iso:country":"IN",
    "ks:ks_name":"27 NTR",
    "ks:ks_pop":267,
    "ks:ks_type":"VILLAGE",
    "name:eng_x_preferred":[
        "27 NTR"
    ],
    "wof:name":"27 NTR",
    "wof:placetype":"locality",
    "wof:population":267
},
  "geometry": {"coordinates":[74.831931,29.22156],"type":"Point"}
}