{
  "type": "Feature",
  "properties": {
    "iso:country":"IN",
    "ks:ks_name":"Jaisala",
    "ks:ks_pop":7115,
    "ks:ks_type":"VILLAGE",
    "name:eng_x_preferred":[
        "Jaisala"
    ],
    "wof:name":"Jaisala",
    "wof:placetype":"locality",
    "wof:population":7115
},
  "geometry": {"coordinates":[72.9353,27.2996],"type":"Point"}
}