{
  "type": "Feature",
  "properties": {
    "iso:country":"IN",
    "ks:ks_name":"6RWB",
    "ks:ks_pop":311,
    "ks:ks_type":"VILLAGE",
    "name:eng_x_preferred":[
        "6RWB"
    ],
    "wof:name":"6RWB",
    "wof:placetype":"locality",
    "wof:population":311
},
  "geometry": {"coordinates":[74.521717,29.421422],"type":"Point"}
}