{
  "type": "Feature",
  "properties": {
    "gn:admin1_code":"35.0",
    "gn:admin2_code":"466.0",
    "gn:asciiname":"Omkarmandhata",
    "gn:country_code":"IN",
    "gn:dem":192,
    "gn:feature_class":"P",
    "gn:feature_code":"PPL",
    "gn:name":"Omk\u0101rm\u0101ndh\u0101ta",
    "gn:population":0,
    "gn:timezone":"Asia/Kolkata",
    "iso:country":"IN",
    "wof:name":"Omkarmandhata",
    "wof:placetype":"neighbourhood"
},
  "geometry": {"coordinates":[76.14919999999999,22.24208],"type":"Point"}
}