{
  "type": "Feature",
  "properties": {
    "iso:country":"IN",
    "ks:ks_name":"Nigdhu",
    "ks:ks_pop":762,
    "ks:ks_type":"HABITATION",
    "name:eng_x_preferred":[
        "Nigdhu"
    ],
    "wof:name":"Nigdhu",
    "wof:placetype":"locality",
    "wof:population":762
},
  "geometry": {"coordinates":[76.80994800000001,29.887333],"type":"Point"}
}