{
  "type": "Feature",
  "properties": {
    "iso:country":"IN",
    "ks:ks_name":"Mandeel",
    "ks:ks_pop":1051,
    "ks:ks_type":"VILLAGE",
    "name:eng_x_preferred":[
        "Mandeel"
    ],
    "wof:name":"Mandeel",
    "wof:placetype":"locality",
    "wof:population":1051
},
  "geometry": {"coordinates":[75.096131,21.73193],"type":"Point"}
}