{
  "type": "Feature",
  "properties": {
    "iso:country":"IN",
    "ks:ks_name":"Sar Berya",
    "ks:ks_pop":1062,
    "ks:ks_type":"VILLAGE",
    "name:eng_x_preferred":[
        "Sar Berya"
    ],
    "wof:name":"Sar Berya",
    "wof:placetype":"locality",
    "wof:population":1062
},
  "geometry": {"coordinates":[87.97057700000001,22.177833],"type":"Point"}
}