{
  "type": "Feature",
  "properties": {
    "iso:country":"IN",
    "ks:ks_name":"Raja Bag",
    "ks:ks_pop":974,
    "ks:ks_type":"HABITATION",
    "ks:ks_uagg_main":0,
    "name:eng_x_preferred":[
        "Raja Bag"
    ],
    "wof:name":"Raja Bag",
    "wof:placetype":"neighbourhood",
    "wof:population":974
},
  "geometry": {"coordinates":[81.714698,27.488797],"type":"Point"}
}