{
  "type": "Feature",
  "properties": {
    "iso:country":"IN",
    "ks:ks_name":"Thakarwadi-1",
    "ks:ks_pop":831,
    "ks:ks_type":"HABITATION",
    "name:eng_x_preferred":[
        "Thakarwadi-1"
    ],
    "wof:name":"Thakarwadi-1",
    "wof:placetype":"locality",
    "wof:population":831
},
  "geometry": {"coordinates":[74.347514,19.23271],"type":"Point"}
}