{
  "type": "Feature",
  "properties": {
    "iso:country":"IN",
    "ks:ks_name":"Amada",
    "ks:ks_pop":1613,
    "ks:ks_type":"HABITATION",
    "name:eng_x_preferred":[
        "Amada"
    ],
    "wof:name":"Amada",
    "wof:placetype":"locality",
    "wof:population":1613
},
  "geometry": {"coordinates":[86.08557,26.388441],"type":"Point"}
}