{
  "type": "Feature",
  "properties": {
    "iso:country":"IN",
    "ks:ks_name":"Lower Tola",
    "ks:ks_pop":130,
    "ks:ks_type":"HABITATION",
    "name:eng_x_preferred":[
        "Lower Tola"
    ],
    "wof:name":"Lower Tola",
    "wof:placetype":"locality",
    "wof:population":130
},
  "geometry": {"coordinates":[86.161343,24.599172],"type":"Point"}
}