{
  "type": "Feature",
  "properties": {
    "iso:country":"IN",
    "ks:ks_name":"Rayappanpatti",
    "ks:ks_pop":140,
    "ks:ks_type":"HABITATION",
    "name:eng_x_preferred":[
        "Rayappanpatti"
    ],
    "wof:name":"Rayappanpatti",
    "wof:placetype":"locality",
    "wof:population":140
},
  "geometry": {"coordinates":[78.074822,10.383778],"type":"Point"}
}