{
  "type": "Feature",
  "properties": {
    "iso:country":"IN",
    "ks:ks_name":"Aurangabad",
    "ks:ks_pop":10514,
    "ks:ks_type":"URBAN",
    "ks:ks_uagg_main":0,
    "name:eng_x_preferred":[
        "Aurangabad"
    ],
    "name:hin_x_preferred":[
        "\u0914\u0930\u0902\u0917\u093e\u092c\u093e\u0926"
    ],
    "name:mar_x_preferred":[
        "\u0914\u0930\u0902\u0917\u093e\u092c\u093e\u0926"
    ],
    "wof:name":"Aurangabad",
    "wof:placetype":"neighbourhood",
    "wof:population":10514
},
  "geometry": {"coordinates":[88.042987,24.600363],"type":"Point"}
}