{
  "type": "Feature",
  "properties": {
    "iso:country":"IN",
    "ks:ks_name":"Karahi Khurd",
    "ks:ks_pop":1054,
    "ks:ks_type":"HABITATION",
    "name:eng_x_preferred":[
        "Karahi Khurd"
    ],
    "wof:name":"Karahi Khurd",
    "wof:placetype":"locality",
    "wof:population":1054
},
  "geometry": {"coordinates":[84.22451100000001,26.101648],"type":"Point"}
}