{
  "type": "Feature",
  "properties": {
    "gn:admin1_code":"2.0",
    "gn:admin2_code":"554.0",
    "gn:asciiname":"Brahmanacheruvu",
    "gn:country_code":"IN",
    "gn:dem":63,
    "gn:feature_class":"P",
    "gn:feature_code":"PPL",
    "gn:name":"Br\u0101hmanacheruvu",
    "gn:population":0,
    "gn:timezone":"Asia/Kolkata",
    "iso:country":"IN",
    "ks:ks_name":"Brahmana Cheruvu",
    "ks:ks_pop":269,
    "ks:ks_type":"VILLAGE",
    "name:eng_x_preferred":[
        "Brahmana Cheruvu"
    ],
    "name:eng_x_variant":[
        "Brahmanacheruvu"
    ],
    "wof:name":"Brahmana Cheruvu",
    "wof:placetype":"locality",
    "wof:population":269
},
  "geometry": {"coordinates":[79.760606,13.633943],"type":"Point"}
}