{
  "type": "Feature",
  "properties": {
    "gn:admin1_code":"36.0",
    "gn:admin2_code":"136.0",
    "gn:asciiname":"Dhanauri",
    "gn:country_code":"IN",
    "gn:dem":208,
    "gn:feature_class":"P",
    "gn:feature_code":"PPL",
    "gn:name":"Dhanaur\u012b",
    "gn:population":0,
    "gn:timezone":"Asia/Kolkata",
    "iso:country":"IN",
    "name:ceb_x_preferred":[
        "Dhanauri"
    ],
    "name:mai_x_preferred":[
        "\u0927\u0928\u094c\u0930\u0940"
    ],
    "name:msa_x_preferred":[
        "Dhanauri"
    ],
    "name:nep_x_preferred":[
        "\u0927\u0928\u094c\u0930\u0940"
    ],
    "name:new_x_preferred":[
        "\u0927\u0928\u094c\u0930\u0940"
    ],
    "name:pol_x_preferred":[
        "Dhanauri"
    ],
    "wof:name":"Dhanauri",
    "wof:placetype":"locality"
},
  "geometry": {"coordinates":[79.051,29.01132],"type":"Point"}
}