{
  "type": "Feature",
  "properties": {
    "iso:country":"IN",
    "ks:ks_name":"Ganeshnagar",
    "ks:ks_pop":48,
    "ks:ks_type":"HABITATION",
    "name:eng_x_preferred":[
        "Ganeshnagar"
    ],
    "wof:name":"Ganeshnagar",
    "wof:placetype":"locality",
    "wof:population":48
},
  "geometry": {"coordinates":[73.474695,16.346087],"type":"Point"}
}