{
  "type": "Feature",
  "properties": {
    "iso:country":"IN",
    "ks:ks_name":"Morakuzhi",
    "ks:ks_pop":217,
    "ks:ks_type":"HABITATION",
    "name:eng_x_preferred":[
        "Morakuzhi"
    ],
    "wof:name":"Morakuzhi",
    "wof:placetype":"locality",
    "wof:population":217
},
  "geometry": {"coordinates":[79.128232,11.16289],"type":"Point"}
}