{
  "type": "Feature",
  "properties": {
    "gn:admin1_code":"36.0",
    "gn:admin2_code":"158.0",
    "gn:asciiname":"Baba Purwa",
    "gn:country_code":"IN",
    "gn:dem":115,
    "gn:feature_class":"P",
    "gn:feature_code":"PPL",
    "gn:name":"B\u0101ba Purwa",
    "gn:population":0,
    "gn:timezone":"Asia/Kolkata",
    "iso:country":"IN",
    "ks:ks_name":"Babuka Purwa",
    "ks:ks_pop":250,
    "ks:ks_type":"HABITATION",
    "name:eng_x_preferred":[
        "Babuka Purwa"
    ],
    "name:eng_x_variant":[
        "Baba Purwa"
    ],
    "wof:name":"Babuka Purwa",
    "wof:placetype":"locality",
    "wof:population":250
},
  "geometry": {"coordinates":[81.4153,26.3647],"type":"Point"}
}