{
  "type": "Feature",
  "properties": {
    "iso:country":"IN",
    "ks:ks_name":"Larchak",
    "ks:ks_pop":2107,
    "ks:ks_type":"VILLAGE",
    "name:eng_x_preferred":[
        "Larchak"
    ],
    "wof:name":"Larchak",
    "wof:placetype":"locality",
    "wof:population":2107
},
  "geometry": {"coordinates":[88.093361,24.832339],"type":"Point"}
}