{
  "type": "Feature",
  "properties": {
    "gn:admin1_code":"34.0",
    "gn:admin2_code":"223.0",
    "gn:asciiname":"Marar",
    "gn:country_code":"IN",
    "gn:dem":43,
    "gn:feature_class":"P",
    "gn:feature_code":"PPL",
    "gn:name":"Marar",
    "gn:population":0,
    "gn:timezone":"Asia/Kolkata",
    "iso:country":"IN",
    "name:und_x_variant":[
        "Kam\u0101than"
    ],
    "wof:name":"Marar",
    "wof:placetype":"neighbourhood"
},
  "geometry": {"coordinates":[86.54935999999999,25.60157],"type":"Point"}
}