{
  "type": "Feature",
  "properties": {
    "gn:country":"IN",
    "gn:fcode":"PPL",
    "gn:population":4351,
    "iso:country":"IN",
    "name:ben_x_preferred":[
        "\u0997\u09cb\u0995\u09c1\u09b2"
    ],
    "name:bho_x_preferred":[
        "\u0917\u094b\u0915\u0941\u0932"
    ],
    "name:bpy_x_preferred":[
        "\u0997\u09cb\u0995\u09c1\u09b2"
    ],
    "name:bul_x_preferred":[
        "\u0413\u043e\u043a\u0443\u043b"
    ],
    "name:ceb_x_preferred":[
        "Gokul"
    ],
    "name:eng_x_preferred":[
        "Gokul"
    ],
    "name:guj_x_preferred":[
        "\u0a97\u0acb\u0a95\u0ac1\u0ab3"
    ],
    "name:hin_x_preferred":[
        "\u0917\u094b\u0915\u0941\u0932"
    ],
    "name:ita_x_preferred":[
        "Gokul"
    ],
    "name:jpn_x_preferred":[
        "\u30b4\u30fc\u30af\u30e9"
    ],
    "name:mai_x_preferred":[
        "\u0917\u094b\u0915\u0941\u0932"
    ],
    "name:mlg_x_preferred":[
        "Gokul"
    ],
    "name:msa_x_preferred":[
        "Gokul"
    ],
    "name:nan_x_preferred":[
        "Gokul"
    ],
    "name:nep_x_preferred":[
        "\u0917\u094b\u0915\u0941\u0932"
    ],
    "name:new_x_preferred":[
        "\u0917\u094b\u0915\u0941\u0932"
    ],
    "name:nld_x_preferred":[
        "Gokul"
    ],
    "name:ori_x_preferred":[
        "\u0b17\u0b4b\u0b15\u0b41\u0b33"
    ],
    "name:pol_x_preferred":[
        "Gokul"
    ],
    "name:rus_x_preferred":[
        "\u0413\u043e\u043a\u0443\u043b\u0430"
    ],
    "name:sin_x_preferred":[
        "\u0d9c\u0ddd\u0d9a\u0dd4\u0dbd\u0dca"
    ],
    "name:swe_x_preferred":[
        "Gokul"
    ],
    "name:tam_x_preferred":[
        "\u0b95\u0bcb\u0b95\u0bc1\u0bb2\u0bae\u0bcd"
    ],
    "name:ukr_x_preferred":[
        "\u0413\u043e\u043a\u0443\u043b"
    ],
    "name:urd_x_preferred":[
        "\u06af\u0648\u06a9\u0644"
    ],
    "name:vie_x_preferred":[
        "Gokul"
    ],
    "name:zho_x_preferred":[
        "\u6208\u5e93\u5c14"
    ],
    "qs:name":"Gokul",
    "qs:name_adm0":"India",
    "qs:name_adm1":"Uttar Pradesh",
    "qs:photos_9k":1,
    "qs:photos_9r":1,
    "qs:photos_all":7,
    "qs:photos_sr":0,
    "qs:placetype":"Town",
    "qs:pop_sr":"4",
    "wd:wordcount":202,
    "wof:name":"Gokul",
    "wof:placetype":"locality",
    "wof:population":4351
},
  "geometry": {"coordinates":[77.71983,27.43879],"type":"Point"}
}