{
  "type": "Feature",
  "properties": {
    "gn:admin1_code":"36.0",
    "gn:admin2_code":"168.0",
    "gn:asciiname":"Dharmol",
    "gn:country_code":"IN",
    "gn:dem":112,
    "gn:feature_class":"P",
    "gn:feature_code":"PPL",
    "gn:name":"Dharmol",
    "gn:population":0,
    "gn:timezone":"Asia/Kolkata",
    "iso:country":"IN",
    "wof:name":"Dharmol",
    "wof:placetype":"locality"
},
  "geometry": {"coordinates":[80.08318,25.92943],"type":"Point"}
}