{
  "type": "Feature",
  "properties": {
    "gn:admin1_code":"35.0",
    "gn:admin2_code":"447",
    "gn:asciiname":"Amraoti",
    "gn:country_code":"IN",
    "gn:dem":697,
    "gn:feature_class":"P",
    "gn:feature_code":"PPL",
    "gn:name":"Amraoti",
    "gn:population":0,
    "gn:timezone":"Asia/Kolkata",
    "iso:country":"IN",
    "name:und_x_variant":[
        "Amraot\u012b"
    ],
    "wof:name":"Amraoti",
    "wof:placetype":"locality"
},
  "geometry": {"coordinates":[78.19001999999998,21.63832],"type":"Point"}
}