{
  "type": "Feature",
  "properties": {
    "gn:admin1_code":"36.0",
    "gn:admin2_code":"162.0",
    "gn:asciiname":"Paighambarpur",
    "gn:country_code":"IN",
    "gn:dem":139,
    "gn:feature_class":"P",
    "gn:feature_code":"PPL",
    "gn:name":"Paighambarpur",
    "gn:population":0,
    "gn:timezone":"Asia/Kolkata",
    "iso:country":"IN",
    "ks:ks_name":"Paigambar Pur",
    "ks:ks_pop":530,
    "ks:ks_type":"HABITATION",
    "name:eng_x_preferred":[
        "Paigambar Pur"
    ],
    "name:eng_x_variant":[
        "Paighambarpur"
    ],
    "wof:name":"Paigambar Pur",
    "wof:placetype":"locality",
    "wof:population":530
},
  "geometry": {"coordinates":[79.484247,26.448257],"type":"Point"}
}