{
  "type": "Feature",
  "properties": {
    "iso:country":"IN",
    "ks:ks_name":"Moti Shero",
    "ks:ks_pop":549,
    "ks:ks_type":"VILLAGE",
    "name:eng_x_preferred":[
        "Moti Shero"
    ],
    "wof:name":"Moti Shero",
    "wof:placetype":"locality",
    "wof:population":549
},
  "geometry": {"coordinates":[74.05784199999999,23.235608],"type":"Point"}
}