{
  "type": "Feature",
  "properties": {
    "iso:country":"IN",
    "ks:ks_name":"Mannuchira",
    "ks:ks_pop":496,
    "ks:ks_type":"HABITATION",
    "name:eng_x_preferred":[
        "Mannuchira"
    ],
    "wof:name":"Mannuchira",
    "wof:placetype":"locality",
    "wof:population":496
},
  "geometry": {"coordinates":[76.29329799999999,9.797308],"type":"Point"}
}