{
  "type": "Feature",
  "properties": {
    "gn:admin1_code":"38.0",
    "gn:admin2_code":"353.0",
    "gn:asciiname":"Garamara",
    "gn:country_code":"IN",
    "gn:dem":60,
    "gn:feature_class":"P",
    "gn:feature_code":"PPL",
    "gn:name":"G\u0101r\u0101m\u0101ra",
    "gn:population":0,
    "gn:timezone":"Asia/Kolkata",
    "iso:country":"IN",
    "ks:ks_name":"Gara Mara",
    "ks:ks_pop":462,
    "ks:ks_type":"VILLAGE",
    "ks:ks_uagg_main":0,
    "name:eng_x_preferred":[
        "Gara Mara"
    ],
    "wof:name":"Gara Mara",
    "wof:placetype":"neighbourhood",
    "wof:population":462
},
  "geometry": {"coordinates":[87.78552999999999,24.372805],"type":"Point"}
}