{
  "type": "Feature",
  "properties": {
    "gn:admin1_code":"39",
    "gn:admin2_code":"61.0",
    "gn:asciiname":"Tairiya",
    "gn:country_code":"IN",
    "gn:dem":1076,
    "gn:feature_class":"P",
    "gn:feature_code":"PPL",
    "gn:name":"Tairiya",
    "gn:population":0,
    "gn:timezone":"Asia/Kolkata",
    "iso:country":"IN",
    "ks:ks_name":"Tairiya",
    "ks:ks_type":"VILLAGE",
    "name:eng_x_preferred":[
        "Tairiya"
    ],
    "wof:name":"Tairiya",
    "wof:placetype":"locality"
},
  "geometry": {"coordinates":[78.942368,29.624414],"type":"Point"}
}