{
  "type": "Feature",
  "properties": {
    "iso:country":"IN",
    "ks:ks_name":"Siddanakoppa",
    "ks:ks_pop":31,
    "ks:ks_type":"HABITATION",
    "name:eng_x_preferred":[
        "Siddanakoppa"
    ],
    "wof:name":"Siddanakoppa",
    "wof:placetype":"locality",
    "wof:population":31
},
  "geometry": {"coordinates":[74.980964,14.017406],"type":"Point"}
}