{
  "type": "Feature",
  "properties": {
    "iso:country":"IN",
    "ks:ks_name":"Nayakapu Guda",
    "ks:ks_pop":88,
    "ks:ks_type":"HABITATION",
    "name:eng_x_preferred":[
        "Nayakapu Guda"
    ],
    "wof:name":"Nayakapu Guda",
    "wof:placetype":"locality",
    "wof:population":88
},
  "geometry": {"coordinates":[78.947717,19.098289],"type":"Point"}
}