{
  "type": "Feature",
  "properties": {
    "iso:country":"IN",
    "ks:ks_name":"Ezhukulam",
    "ks:ks_pop":645,
    "ks:ks_type":"HABITATION",
    "ks:ks_uagg_main":0,
    "name:eng_x_preferred":[
        "Ezhukulam"
    ],
    "wof:name":"Ezhukulam",
    "wof:placetype":"neighbourhood",
    "wof:population":645
},
  "geometry": {"coordinates":[75.842133,11.425106],"type":"Point"}
}