{
  "type": "Feature",
  "properties": {
    "iso:country":"IN",
    "ks:ks_name":"Decentmukku",
    "ks:ks_pop":1089,
    "ks:ks_type":"HABITATION",
    "name:eng_x_preferred":[
        "Decentmukku"
    ],
    "wof:name":"Decentmukku",
    "wof:placetype":"locality",
    "wof:population":1089
},
  "geometry": {"coordinates":[76.799592,9.019904],"type":"Point"}
}