{
  "type": "Feature",
  "properties": {
    "iso:country":"IN",
    "ks:ks_name":"Ramgada",
    "ks:ks_pop":106,
    "ks:ks_type":"HABITATION",
    "name:eng_x_preferred":[
        "Ramgada"
    ],
    "wof:name":"Ramgada",
    "wof:placetype":"locality",
    "wof:population":106
},
  "geometry": {"coordinates":[84.033991,18.949347],"type":"Point"}
}