{
  "type": "Feature",
  "properties": {
    "gn:admin1_code":"24.0",
    "gn:admin2_code":"125.0",
    "gn:asciiname":"Kheria",
    "gn:country_code":"IN",
    "gn:dem":215,
    "gn:feature_class":"P",
    "gn:feature_code":"PPL",
    "gn:name":"Kheria",
    "gn:population":0,
    "gn:timezone":"Asia/Kolkata",
    "iso:country":"IN",
    "ks:ks_name":"Kheria",
    "ks:ks_type":"VILLAGE",
    "name:eng_x_preferred":[
        "Kheria"
    ],
    "wof:name":"Kheria",
    "wof:placetype":"locality"
},
  "geometry": {"coordinates":[74.199946,23.284424],"type":"Point"}
}