{
  "type": "Feature",
  "properties": {
    "iso:country":"IN",
    "ks:ks_name":"Arda",
    "ks:ks_pop":697,
    "ks:ks_type":"VILLAGE",
    "name:eng_x_preferred":[
        "Arda"
    ],
    "wof:name":"Arda",
    "wof:placetype":"locality",
    "wof:population":697
},
  "geometry": {"coordinates":[83.672342,20.594429],"type":"Point"}
}