{
  "type": "Feature",
  "properties": {
    "iso:country":"IN",
    "ks:ks_alt_nam":"Koiritola east",
    "ks:ks_name":"Koiritola East",
    "ks:ks_pop":600,
    "ks:ks_type":"HABITATION",
    "name:eng_x_preferred":[
        "Koiritola East"
    ],
    "wof:name":"Koiritola East",
    "wof:placetype":"locality",
    "wof:population":600
},
  "geometry": {"coordinates":[84.645016,24.739654],"type":"Point"}
}