{
  "type": "Feature",
  "properties": {
    "iso:country":"IN",
    "name:ast_x_preferred":[
        "Ravoor"
    ],
    "name:eng_x_preferred":[
        "Ravoor"
    ],
    "name:nld_x_preferred":[
        "Ravoor"
    ],
    "qs:name":"Ravoor",
    "qs:name_adm0":"India",
    "qs:name_adm1":"Andhra Pradesh",
    "qs:photos":7,
    "qs:photos_1k":1,
    "qs:photos_9k":1,
    "qs:photos_9r":1,
    "qs:photos_all":7,
    "qs:photos_sr":1,
    "qs:placetype":"Town",
    "qs:pop_sr":"0",
    "wd:wordcount":81,
    "wof:name":"Ravoor",
    "wof:placetype":"locality"
},
  "geometry": {"coordinates":[79.70392200000001,17.729393],"type":"Point"}
}