{
  "type": "Feature",
  "properties": {
    "iso:country":"IN",
    "ks:ks_name":"Peralaguddde",
    "ks:ks_pop":943,
    "ks:ks_type":"HABITATION",
    "name:eng_x_preferred":[
        "Peralaguddde"
    ],
    "wof:name":"Peralaguddde",
    "wof:placetype":"locality",
    "wof:population":943
},
  "geometry": {"coordinates":[75.12369099999999,13.059745],"type":"Point"}
}