{
  "type": "Feature",
  "properties": {
    "iso:country":"IN",
    "ks:ks_name":"Navera",
    "ks:ks_pop":2657,
    "ks:ks_type":"VILLAGE",
    "name:eng_x_preferred":[
        "Navera"
    ],
    "wof:name":"Navera",
    "wof:placetype":"locality",
    "wof:population":2657
},
  "geometry": {"coordinates":[73.039112,20.531512],"type":"Point"}
}