{
  "type": "Feature",
  "properties": {
    "iso:country":"IN",
    "ks:ks_name":"Lunhera Khurd",
    "ks:ks_pop":937,
    "ks:ks_type":"VILLAGE",
    "ks:ks_uagg_main":0,
    "name:eng_x_preferred":[
        "Lunhera Khurd"
    ],
    "wof:name":"Lunhera Khurd",
    "wof:placetype":"neighbourhood",
    "wof:population":937
},
  "geometry": {"coordinates":[75.42883399999999,22.15193],"type":"Point"}
}