{
  "type": "Feature",
  "properties": {
    "gn:admin1_code":"39.0",
    "gn:admin2_code":"62.0",
    "gn:asciiname":"Naili",
    "gn:country_code":"IN",
    "gn:dem":1062,
    "gn:feature_class":"P",
    "gn:feature_code":"PPL",
    "gn:name":"Naili",
    "gn:population":0,
    "gn:timezone":"Asia/Kolkata",
    "iso:country":"IN",
    "ks:ks_name":"Naili",
    "ks:ks_type":"VILLAGE",
    "name:eng_x_preferred":[
        "Naili"
    ],
    "wof:name":"Naili",
    "wof:placetype":"locality"
},
  "geometry": {"coordinates":[79.905644,29.729379],"type":"Point"}
}