{
  "type": "Feature",
  "properties": {
    "iso:country":"IN",
    "ks:ks_name":"Bhatura",
    "ks:ks_pop":0,
    "ks:ks_type":"VILLAGE",
    "name:eng_x_preferred":[
        "Bhatura"
    ],
    "wof:name":"Bhatura",
    "wof:placetype":"locality",
    "wof:population":0
},
  "geometry": {"coordinates":[87.740532,23.659276],"type":"Point"}
}