{
  "type": "Feature",
  "properties": {
    "iso:country":"IN",
    "ks:ks_alt_nam":"TALMA",
    "ks:ks_name":"Talma",
    "ks:ks_pop":513,
    "ks:ks_type":"HABITATION",
    "ks:ks_uagg_main":0,
    "name:eng_x_preferred":[
        "Talma"
    ],
    "wof:name":"Talma",
    "wof:placetype":"neighbourhood",
    "wof:population":513
},
  "geometry": {"coordinates":[88.580127,26.554644],"type":"Point"}
}