{
  "type": "Feature",
  "properties": {
    "gn:admin1_code":"23.0",
    "gn:admin2_code":"041",
    "gn:asciiname":"Sati",
    "gn:country_code":"IN",
    "gn:dem":257,
    "gn:feature_class":"P",
    "gn:feature_code":"PPL",
    "gn:name":"Sati",
    "gn:population":0,
    "gn:timezone":"Asia/Kolkata",
    "iso:country":"IN",
    "name:ara_x_preferred":[
        "\u0633\u0627\u062a\u064a"
    ],
    "name:bih_x_preferred":[
        "\u0938\u0924\u0940"
    ],
    "name:bul_x_preferred":[
        "\u0421\u0430\u0442\u0438"
    ],
    "name:cat_x_preferred":[
        "Sati"
    ],
    "name:ceb_x_preferred":[
        "Sati"
    ],
    "name:ces_x_preferred":[
        "Sat\u00ed"
    ],
    "name:dan_x_preferred":[
        "Sati"
    ],
    "name:deu_x_preferred":[
        "Sati"
    ],
    "name:fas_x_preferred":[
        "\u0633\u0627\u062a\u06cc"
    ],
    "name:fra_x_preferred":[
        "Sati"
    ],
    "name:ind_x_preferred":[
        "Sati"
    ],
    "name:jpn_x_preferred":[
        "\u30b5\u30c6\u30a3"
    ],
    "name:lit_x_preferred":[
        "Sati"
    ],
    "name:msa_x_preferred":[
        "Sati"
    ],
    "name:nld_x_preferred":[
        "Sati"
    ],
    "name:nor_x_preferred":[
        "Sati"
    ],
    "name:pol_x_preferred":[
        "Sati"
    ],
    "name:rus_x_preferred":[
        "\u0421\u0430\u0442\u0438"
    ],
    "name:sco_x_preferred":[
        "Sati"
    ],
    "name:spa_x_preferred":[
        "Sati"
    ],
    "name:srp_x_preferred":[
        "\u0421\u0430\u0442\u0438"
    ],
    "name:swe_x_preferred":[
        "Sati"
    ],
    "name:tha_x_preferred":[
        "\u0e2a\u0e15\u0e35"
    ],
    "name:ukr_x_preferred":[
        "\u0421\u0430\u0442\u0456"
    ],
    "name:urd_x_preferred":[
        "\u0633\u062a\u06cc"
    ],
    "wof:name":"Sati",
    "wof:placetype":"locality"
},
  "geometry": {"coordinates":[76.05421,30.58676],"type":"Point"}
}