{
  "type": "Feature",
  "properties": {
    "iso:country":"IN",
    "qs:name":"Amarpur Kashi",
    "qs:name_adm0":"India",
    "qs:name_adm1":"Uttar Pradesh",
    "qs:photos":4,
    "qs:photos_1k":1,
    "qs:photos_9k":1,
    "qs:photos_9r":1,
    "qs:photos_all":4,
    "qs:photos_sr":1,
    "qs:placetype":"Town",
    "qs:pop_sr":"0",
    "wof:name":"Amarpur Kashi",
    "wof:placetype":"locality"
},
  "geometry": {"coordinates":[78.79342750000001,28.551555],"type":"Point"}
}