{
  "type": "Feature",
  "properties": {
    "iso:country":"IN",
    "ks:ks_alt_nam":"B\u0101ghm\u0101ra",
    "ks:ks_name":"Baghmara",
    "ks:ks_pop":925,
    "ks:ks_type":"VILLAGE",
    "ks:ks_uagg_main":0,
    "name:eng_x_preferred":[
        "Baghmara"
    ],
    "name:eng_x_variant":[
        "B\u0101ghm\u0101ra"
    ],
    "wof:name":"Baghmara",
    "wof:placetype":"neighbourhood",
    "wof:population":925
},
  "geometry": {"coordinates":[85.911235,24.448164],"type":"Point"}
}