{
  "type": "Feature",
  "properties": {
    "iso:country":"IN",
    "ks:ks_name":"Kalluhattypalya",
    "ks:ks_pop":78,
    "ks:ks_type":"HABITATION",
    "name:eng_x_preferred":[
        "Kalluhattypalya"
    ],
    "wof:name":"Kalluhattypalya",
    "wof:placetype":"locality",
    "wof:population":78
},
  "geometry": {"coordinates":[77.318264,12.926094],"type":"Point"}
}