{
  "type": "Feature",
  "properties": {
    "gn:admin1_code":"36.0",
    "gn:admin2_code":"173.0",
    "gn:asciiname":"Kasapur",
    "gn:country_code":"IN",
    "gn:dem":100,
    "gn:feature_class":"P",
    "gn:feature_code":"PPL",
    "gn:name":"K\u0101s\u0101pur",
    "gn:population":0,
    "gn:timezone":"Asia/Kolkata",
    "iso:country":"IN",
    "ks:ks_name":"Kansapur",
    "ks:ks_pop":440,
    "ks:ks_type":"VILLAGE",
    "name:eng_x_preferred":[
        "Kansapur"
    ],
    "name:eng_x_variant":[
        "Kasapur"
    ],
    "wof:name":"Kansapur",
    "wof:placetype":"locality",
    "wof:population":440
},
  "geometry": {"coordinates":[81.804102,25.936829],"type":"Point"}
}