{
  "type": "Feature",
  "properties": {
    "iso:country":"IN",
    "ks:ks_name":"Illeampara",
    "ks:ks_pop":600,
    "ks:ks_type":"HABITATION",
    "name:eng_x_preferred":[
        "Illeampara"
    ],
    "wof:name":"Illeampara",
    "wof:placetype":"locality",
    "wof:population":600
},
  "geometry": {"coordinates":[75.75947600000001,11.684421],"type":"Point"}
}