{
  "type": "Feature",
  "properties": {
    "iso:country":"IN",
    "ks:ks_alt_nam":"Kalikapur Halder and Paik Para",
    "ks:ks_name":"Kalikapur Halder And Paik Para",
    "ks:ks_pop":810,
    "ks:ks_type":"HABITATION",
    "ks:ks_uagg_main":0,
    "name:eng_x_preferred":[
        "Kalikapur Halder And Paik Para"
    ],
    "wof:name":"Kalikapur Halder And Paik Para",
    "wof:placetype":"neighbourhood",
    "wof:population":810
},
  "geometry": {"coordinates":[88.410538,22.04118],"type":"Point"}
}