{
  "type": "Feature",
  "properties": {
    "gn:admin1_code":"21",
    "gn:admin2_code":"398.0",
    "gn:asciiname":"Adarvalasa",
    "gn:country_code":"IN",
    "gn:dem":965,
    "gn:feature_class":"P",
    "gn:feature_code":"PPL",
    "gn:name":"Adarvalasa",
    "gn:population":0,
    "gn:timezone":"Asia/Kolkata",
    "iso:country":"IN",
    "wof:name":"Adarvalasa",
    "wof:placetype":"neighbourhood"
},
  "geometry": {"coordinates":[82.92671,18.48667],"type":"Point"}
}