{
  "type": "Feature",
  "properties": {
    "iso:country":"IN",
    "ks:ks_name":"Anandabari T.E.",
    "ks:ks_pop":635,
    "ks:ks_type":"VILLAGE",
    "name:eng_x_preferred":[
        "Anandabari T.E."
    ],
    "wof:name":"Anandabari T.E.",
    "wof:placetype":"locality",
    "wof:population":635
},
  "geometry": {"coordinates":[95.408199,27.382324],"type":"Point"}
}