{
  "type": "Feature",
  "properties": {
    "gn:admin1_code":"19.0",
    "gn:admin2_code":"569.0",
    "gn:asciiname":"Todar",
    "gn:country_code":"IN",
    "gn:dem":111,
    "gn:feature_class":"P",
    "gn:feature_code":"PPLL",
    "gn:name":"T\u014dd\u0101r",
    "gn:population":0,
    "gn:timezone":"Asia/Kolkata",
    "iso:country":"IN",
    "wof:name":"Todar",
    "wof:placetype":"locality"
},
  "geometry": {"coordinates":[74.98721999999999,13.03029],"type":"Point"}
}