{
  "type": "Feature",
  "properties": {
    "iso:country":"IN",
    "ks:ks_name":"Babhania Hardo",
    "ks:ks_pop":40,
    "ks:ks_type":"VILLAGE",
    "name:eng_x_preferred":[
        "Babhania Hardo"
    ],
    "wof:name":"Babhania Hardo",
    "wof:placetype":"locality",
    "wof:population":40
},
  "geometry": {"coordinates":[83.89358,26.221147],"type":"Point"}
}