{
  "type": "Feature",
  "properties": {
    "gn:admin1_code":"2",
    "gn:admin2_code":"545.0",
    "gn:asciiname":"Mera Kachamavaram",
    "gn:country_code":"IN",
    "gn:dem":58,
    "gn:feature_class":"P",
    "gn:feature_code":"PPL",
    "gn:name":"Mera K\u0101ch\u0101mavaram",
    "gn:population":0,
    "gn:timezone":"Asia/Kolkata",
    "iso:country":"IN",
    "ks:ks_name":"Meraka Chamavaram",
    "ks:ks_pop":1556,
    "ks:ks_type":"VILLAGE",
    "ks:ks_uagg_main":0,
    "name:eng_x_preferred":[
        "Meraka Chamavaram"
    ],
    "wof:name":"Meraka Chamavaram",
    "wof:placetype":"neighbourhood",
    "wof:population":1556
},
  "geometry": {"coordinates":[82.36338000000001,17.33449],"type":"Point"}
}