{
  "type": "Feature",
  "properties": {
    "gn:admin1_code":"36.0",
    "gn:admin2_code":"183.0",
    "gn:asciiname":"Atraulia",
    "gn:country_code":"IN",
    "gn:dem":106,
    "gn:feature_class":"P",
    "gn:feature_code":"PPL",
    "gn:name":"Atraulia",
    "gn:population":0,
    "gn:timezone":"Asia/Kolkata",
    "iso:country":"IN",
    "name:bih_x_preferred":[
        "\u0905\u0924\u0930\u094c\u0932\u093f\u092f\u093e"
    ],
    "name:bpy_x_preferred":[
        "\u0986\u09a4\u09cd\u09b0\u09cc\u09b2\u09bf\u09af\u09bc\u09be"
    ],
    "name:ceb_x_preferred":[
        "Atrauli\u0101"
    ],
    "name:ita_x_preferred":[
        "Atraulia"
    ],
    "name:mlg_x_preferred":[
        "Atraulia"
    ],
    "name:msa_x_preferred":[
        "Atraulia"
    ],
    "name:new_x_preferred":[
        "\u0905\u0924\u094d\u0930\u094c\u0932\u0940\u092f"
    ],
    "name:nld_x_preferred":[
        "Atraulia"
    ],
    "name:pol_x_preferred":[
        "Atraulia"
    ],
    "name:por_x_preferred":[
        "Atraulia"
    ],
    "name:swe_x_preferred":[
        "Atrauli\u0101"
    ],
    "name:urd_x_preferred":[
        "\u0627\u062a\u0631\u0648\u0644\u06cc\u0627"
    ],
    "name:vie_x_preferred":[
        "Atraulia"
    ],
    "name:zho_x_preferred":[
        "\u963f\u7279\u52b3\u5229\u4e9a"
    ],
    "wof:name":"Atraulia",
    "wof:placetype":"locality"
},
  "geometry": {"coordinates":[81.57046,27.07496],"type":"Point"}
}