{
  "type": "Feature",
  "properties": {
    "iso:country":"IN",
    "ks:ks_name":"Badamulei",
    "ks:ks_pop":1177,
    "ks:ks_type":"VILLAGE",
    "name:eng_x_preferred":[
        "Badamulei"
    ],
    "wof:name":"Badamulei",
    "wof:placetype":"locality",
    "wof:population":1177
},
  "geometry": {"coordinates":[86.030092,20.25555],"type":"Point"}
}