{
  "type": "Feature",
  "properties": {
    "iso:country":"IN",
    "ks:ks_name":"Kanda",
    "ks:ks_pop":377,
    "ks:ks_type":"VILLAGE",
    "name:eng_x_preferred":[
        "Kanda"
    ],
    "wof:name":"Kanda",
    "wof:placetype":"locality",
    "wof:population":377
},
  "geometry": {"coordinates":[78.468755,30.444023],"type":"Point"}
}