{
  "type": "Feature",
  "properties": {
    "iso:country":"IN",
    "ks:ks_name":"Dungeri",
    "ks:ks_pop":107,
    "ks:ks_type":"VILLAGE",
    "name:eng_x_preferred":[
        "Dungeri"
    ],
    "wof:name":"Dungeri",
    "wof:placetype":"locality",
    "wof:population":107
},
  "geometry": {"coordinates":[83.786349,20.108031],"type":"Point"}
}