{
  "type": "Feature",
  "properties": {
    "iso:country":"IN",
    "ks:ks_name":"Lindiya",
    "ks:ks_pop":170,
    "ks:ks_type":"HABITATION",
    "name:eng_x_preferred":[
        "Lindiya"
    ],
    "wof:name":"Lindiya",
    "wof:placetype":"locality",
    "wof:population":170
},
  "geometry": {"coordinates":[73.237167,21.38475],"type":"Point"}
}