{
  "type": "Feature",
  "properties": {
    "iso:country":"IN",
    "ks:ks_name":"Bharangi",
    "ks:ks_type":"VILLAGE",
    "name:eng_x_preferred":[
        "Bharangi"
    ],
    "wof:name":"Bharangi",
    "wof:placetype":"locality"
},
  "geometry": {"coordinates":[74.876999,14.149578],"type":"Point"}
}