{
  "type": "Feature",
  "properties": {
    "iso:country":"IN",
    "ks:ks_name":"Shirpur",
    "ks:ks_pop":121,
    "ks:ks_type":"VILLAGE",
    "name:eng_x_preferred":[
        "Shirpur"
    ],
    "name:hin_x_preferred":[
        "\u0936\u093f\u0930\u092a\u0941\u0930"
    ],
    "name:mar_x_preferred":[
        "\u0936\u093f\u0930\u092a\u0942\u0930"
    ],
    "wof:name":"Shirpur",
    "wof:placetype":"locality",
    "wof:population":121
},
  "geometry": {"coordinates":[78.277857,21.444235],"type":"Point"}
}