{
  "type": "Feature",
  "properties": {
    "gn:admin1_code":"36.0",
    "gn:admin2_code":"159",
    "gn:asciiname":"Larhapur",
    "gn:country_code":"IN",
    "gn:dem":147,
    "gn:feature_class":"P",
    "gn:feature_code":"PPL",
    "gn:name":"Larh\u0101pur",
    "gn:population":0,
    "gn:timezone":"Asia/Kolkata",
    "iso:country":"IN",
    "ks:ks_name":"Ladha Pur",
    "ks:ks_pop":68,
    "ks:ks_type":"VILLAGE",
    "name:eng_x_preferred":[
        "Ladha Pur"
    ],
    "name:eng_x_variant":[
        "Larhapur"
    ],
    "wof:name":"Ladha Pur",
    "wof:placetype":"locality",
    "wof:population":68
},
  "geometry": {"coordinates":[79.66002899999999,27.550136],"type":"Point"}
}