{
  "type": "Feature",
  "properties": {
    "iso:country":"IN",
    "ks:ks_name":"Rimanpara",
    "ks:ks_pop":273,
    "ks:ks_type":"HABITATION",
    "name:eng_x_preferred":[
        "Rimanpara"
    ],
    "wof:name":"Rimanpara",
    "wof:placetype":"locality",
    "wof:population":273
},
  "geometry": {"coordinates":[81.310061,18.67682],"type":"Point"}
}