{
  "type": "Feature",
  "properties": {
    "iso:country":"IN",
    "ks:ks_name":"Kolharodkala",
    "ks:ks_pop":473,
    "ks:ks_type":"VILLAGE",
    "name:eng_x_preferred":[
        "Kolharodkala"
    ],
    "wof:name":"Kolharodkala",
    "wof:placetype":"locality",
    "wof:population":473
},
  "geometry": {"coordinates":[85.31687100000001,21.976882],"type":"Point"}
}