{
  "type": "Feature",
  "properties": {
    "iso:country":"IN",
    "ks:ks_name":"Jan Hat",
    "ks:ks_pop":2063,
    "ks:ks_type":"VILLAGE",
    "name:eng_x_preferred":[
        "Jan Hat"
    ],
    "wof:name":"Jan Hat",
    "wof:placetype":"locality",
    "wof:population":2063
},
  "geometry": {"coordinates":[87.681764,22.232921],"type":"Point"}
}