{
  "type": "Feature",
  "properties": {
    "iso:country":"IN",
    "ks:ks_name":"Haldukhata Malla",
    "ks:ks_pop":882,
    "ks:ks_type":"VILLAGE",
    "ks:ks_uagg_main":0,
    "name:eng_x_preferred":[
        "Haldukhata Malla"
    ],
    "wof:name":"Haldukhata Malla",
    "wof:placetype":"neighbourhood",
    "wof:population":882
},
  "geometry": {"coordinates":[78.434487,29.764417],"type":"Point"}
}