{
  "type": "Feature",
  "properties": {
    "iso:country":"IN",
    "ks:ks_name":"Hazara",
    "ks:ks_pop":54,
    "ks:ks_type":"VILLAGE",
    "name:eng_x_preferred":[
        "Hazara"
    ],
    "wof:name":"Hazara",
    "wof:placetype":"locality",
    "wof:population":54
},
  "geometry": {"coordinates":[75.085095,31.21705],"type":"Point"}
}