{
  "type": "Feature",
  "properties": {
    "gn:admin1_code":"36",
    "gn:admin2_code":"194.0",
    "gn:asciiname":"Khujhi",
    "gn:country_code":"IN",
    "gn:dem":86,
    "gn:feature_class":"P",
    "gn:feature_code":"PPL",
    "gn:name":"Khujh\u012b",
    "gn:population":0,
    "gn:timezone":"Asia/Kolkata",
    "iso:country":"IN",
    "ks:ks_name":"Khujjhi",
    "ks:ks_pop":2011,
    "ks:ks_type":"VILLAGE",
    "ks:ks_uagg_main":0,
    "name:eng_x_preferred":[
        "Khujjhi"
    ],
    "wof:name":"Khujjhi",
    "wof:placetype":"neighbourhood",
    "wof:population":2011
},
  "geometry": {"coordinates":[82.99355799999999,25.626222],"type":"Point"}
}