{
  "type": "Feature",
  "properties": {
    "iso:country":"IN",
    "ks:ks_name":"Hemavathicolony",
    "ks:ks_pop":50,
    "ks:ks_type":"HABITATION",
    "name:eng_x_preferred":[
        "Hemavathicolony"
    ],
    "wof:name":"Hemavathicolony",
    "wof:placetype":"locality",
    "wof:population":50
},
  "geometry": {"coordinates":[76.50328399999999,13.223736],"type":"Point"}
}