{
  "type": "Feature",
  "properties": {
    "iso:country":"IN",
    "ks:ks_name":"Charli Para",
    "ks:ks_pop":889,
    "ks:ks_type":"HABITATION",
    "name:eng_x_preferred":[
        "Charli Para"
    ],
    "wof:name":"Charli Para",
    "wof:placetype":"locality",
    "wof:population":889
},
  "geometry": {"coordinates":[81.868066,20.27501],"type":"Point"}
}