{
  "type": "Feature",
  "properties": {
    "gn:admin1_code":"36",
    "gn:admin2_code":"185.0",
    "gn:asciiname":"Mandaf",
    "gn:country_code":"IN",
    "gn:dem":92,
    "gn:feature_class":"P",
    "gn:feature_code":"PPL",
    "gn:name":"Mandaf",
    "gn:population":0,
    "gn:timezone":"Asia/Kolkata",
    "iso:country":"IN",
    "ks:ks_name":"Mandaf",
    "ks:ks_pop":344,
    "ks:ks_type":"VILLAGE",
    "ks:ks_uagg_main":0,
    "name:eng_x_preferred":[
        "Mandaf"
    ],
    "wof:name":"Mandaf",
    "wof:placetype":"neighbourhood",
    "wof:population":344
},
  "geometry": {"coordinates":[82.67068500000001,26.996732],"type":"Point"}
}