{
  "type": "Feature",
  "properties": {
    "iso:country":"IN",
    "ks:ks_name":"Purwa Chamaran",
    "ks:ks_pop":980,
    "ks:ks_type":"HABITATION",
    "name:eng_x_preferred":[
        "Purwa Chamaran"
    ],
    "wof:name":"Purwa Chamaran",
    "wof:placetype":"locality",
    "wof:population":980
},
  "geometry": {"coordinates":[79.479715,26.619524],"type":"Point"}
}