{
  "type": "Feature",
  "properties": {
    "iso:country":"IN",
    "name:ara_x_preferred":[
        "\u0628\u0648\u0631\u0641\u0627 \u0646\u0648\u0644\u062e\u0627"
    ],
    "name:ben_bn_x_preferred":[
        "\u09aa\u09c1\u09b0\u0993\u09df\u09be \u09a8\u0993\u09b2\u09be\u0996\u09be"
    ],
    "name:ben_in_x_preferred":[
        "\u09aa\u09c1\u09b0\u0993\u09df\u09be \u09a8\u0993\u09b2\u09be\u0996\u09be"
    ],
    "name:eng_x_preferred":[
        "Purwa Naulakha"
    ],
    "name:guj_x_preferred":[
        "\u0aaa\u0ac2\u0ab0\u0acd\u0ab5\u0abe \u0aa8\u0acc\u0ab2\u0a96\u0abe"
    ],
    "name:hin_x_preferred":[
        "\u092a\u0942\u0930\u094d\u0935 \u0928\u094c\u0932\u0916\u093e"
    ],
    "name:kan_x_preferred":[
        "\u0cab\u0cc2\u0cb0\u0ccd\u0cb5 \u0ca8\u0ccc\u0cb2\u0c96\u0cbe"
    ],
    "name:mal_x_preferred":[
        "\u0d2a\u0d42\u0d7c\u0d35 \u0d28\u0d57\u0d32\u0d16"
    ],
    "name:mar_x_preferred":[
        "\u092a\u0941\u0930\u0935\u093e \u0928\u094c\u0932\u093e\u0916\u093e"
    ],
    "name:pan_x_preferred":[
        "\u0a2a\u0a41\u0a30\u0a35\u0a3e \u0a28\u0a4c\u0a32\u0a71\u0a16\u0a3e"
    ],
    "name:tam_x_preferred":[
        "\u0baa\u0bc2\u0bb0\u0bcd\u0bb5\u0bbe \u0ba8\u0bcc\u0bb2\u0b95\u0bbe"
    ],
    "name:tel_x_preferred":[
        "\u0c2a\u0c42\u0c30\u0c4d\u0c35\u0c3e \u0c28\u0c4c\u0c32\u0c16\u0c3e"
    ],
    "name:urd_x_preferred":[
        "\u067e\u0648\u0631\u0648\u0627 \u0646\u0648\u0644\u06a9\u06be\u0627"
    ],
    "qs:gn_adm0_cc":"IN",
    "qs:gn_local":1279259,
    "qs:gn_nam_loc":"Agra, Agra, Uttar Pradesh, IN",
    "qs:gn_namadm1":"36",
    "qs:local_max":10925,
    "qs:local_sum":42779,
    "qs:localhoods":21,
    "qs:name":"Purwa Naulakha",
    "qs:name_adm0":"India",
    "qs:name_adm1":"Uttar Pradesh",
    "qs:name_adm2":"Agra",
    "qs:name_local":"Agra",
    "qs:photo_max":24,
    "qs:photo_sum":48,
    "qs:placetype":"Suburb",
    "qs:quad_count":5,
    "qs:woe_adm0":23424848,
    "qs:woe_adm1":2345760,
    "qs:woe_adm2":12586712,
    "qs:woe_lau":0,
    "qs:woe_local":2295399,
    "qs:woe_ver":"7.10.0",
    "wof:lang":[
        "eng"
    ],
    "wof:name":"Purwa Naulakha",
    "wof:placetype":"neighbourhood"
},
  "geometry": {"coordinates":[78.026329,27.159129],"type":"Point"}
}