{
  "type": "Feature",
  "properties": {
    "iso:country":"IN",
    "name:eng_x_preferred":[
        "Purwa Naulakha"
    ],
    "qs:gn_adm0_cc":"IN",
    "qs:gn_local":1279259,
    "qs:gn_nam_loc":"Agra, Agra, Uttar Pradesh, IN",
    "qs:gn_namadm1":"36",
    "qs:local_max":10925,
    "qs:local_sum":42779,
    "qs:localhoods":21,
    "qs:name":"Purwa Naulakha",
    "qs:name_adm0":"India",
    "qs:name_adm1":"Uttar Pradesh",
    "qs:name_adm2":"Agra",
    "qs:name_local":"Agra",
    "qs:photo_max":24,
    "qs:photo_sum":48,
    "qs:placetype":"Suburb",
    "qs:quad_count":5,
    "qs:woe_adm0":23424848,
    "qs:woe_adm1":2345760,
    "qs:woe_adm2":12586712,
    "qs:woe_lau":0,
    "qs:woe_local":2295399,
    "qs:woe_ver":"7.10.0",
    "wof:lang":[
        "eng"
    ],
    "wof:name":"Purwa Naulakha",
    "wof:placetype":"neighbourhood"
},
  "geometry": {"coordinates":[78.026329,27.159129],"type":"Point"}
}