{
  "type": "Feature",
  "properties": {
    "iso:country":"IN",
    "ks:ks_name":"Chak Chainpura",
    "ks:ks_pop":627,
    "ks:ks_type":"VILLAGE",
    "name:eng_x_preferred":[
        "Chak Chainpura"
    ],
    "wof:name":"Chak Chainpura",
    "wof:placetype":"locality",
    "wof:population":627
},
  "geometry": {"coordinates":[75.950733,26.993619],"type":"Point"}
}