{
  "type": "Feature",
  "properties": {
    "gn:admin1_code":"36",
    "gn:admin2_code":"157.0",
    "gn:asciiname":"Behari Lal Khera",
    "gn:country_code":"IN",
    "gn:dem":123,
    "gn:feature_class":"P",
    "gn:feature_code":"PPL",
    "gn:name":"Beh\u0101ri L\u0101l Khera",
    "gn:population":0,
    "gn:timezone":"Asia/Kolkata",
    "iso:country":"IN",
    "wof:name":"Behari Lal Khera",
    "wof:placetype":"locality"
},
  "geometry": {"coordinates":[81.10318000000002,26.60684],"type":"Point"}
}