{
  "type": "Feature",
  "properties": {
    "iso:country":"IN",
    "ks:ks_name":"Andhariyapura",
    "ks:ks_pop":463,
    "ks:ks_type":"HABITATION",
    "ks:ks_uagg_main":0,
    "name:eng_x_preferred":[
        "Andhariyapura"
    ],
    "wof:name":"Andhariyapura",
    "wof:placetype":"neighbourhood",
    "wof:population":463
},
  "geometry": {"coordinates":[72.771128,22.50168],"type":"Point"}
}