{
  "type": "Feature",
  "properties": {
    "iso:country":"IN",
    "ks:ks_name":"Kodi Baba",
    "ks:ks_pop":88,
    "ks:ks_type":"HABITATION",
    "name:eng_x_preferred":[
        "Kodi Baba"
    ],
    "wof:name":"Kodi Baba",
    "wof:placetype":"locality",
    "wof:population":88
},
  "geometry": {"coordinates":[80.760201,28.325334],"type":"Point"}
}