{
  "type": "Feature",
  "properties": {
    "iso:country":"IN",
    "ks:ks_name":"Dhamni",
    "ks:ks_pop":310,
    "ks:ks_type":"VILLAGE",
    "name:eng_x_preferred":[
        "Dhamni"
    ],
    "wof:name":"Dhamni",
    "wof:placetype":"locality",
    "wof:population":310
},
  "geometry": {"coordinates":[73.214825,18.710359],"type":"Point"}
}