{
  "type": "Feature",
  "properties": {
    "gn:admin1_code":"24.0",
    "gn:admin2_code":"113.0",
    "gn:asciiname":"Basni",
    "gn:country_code":"IN",
    "gn:dem":210,
    "gn:feature_class":"P",
    "gn:feature_code":"PPL",
    "gn:name":"B\u0101sni",
    "gn:population":0,
    "gn:timezone":"Asia/Kolkata",
    "iso:country":"IN",
    "ks:ks_alt_nam":"B\u0101sni",
    "ks:ks_name":"Basni",
    "ks:ks_type":"VILLAGE",
    "ks:ks_uagg_main":0,
    "name:eng_x_preferred":[
        "Basni"
    ],
    "name:eng_x_variant":[
        "B\u0101sni"
    ],
    "wof:name":"Basni",
    "wof:placetype":"locality"
},
  "geometry": {"coordinates":[72.932204,26.193562],"type":"Point"}
}