{
  "type": "Feature",
  "properties": {
    "iso:country":"IN",
    "ks:ks_name":"Kundakhai",
    "ks:ks_pop":0,
    "ks:ks_type":"VILLAGE",
    "name:eng_x_preferred":[
        "Kundakhai"
    ],
    "wof:name":"Kundakhai",
    "wof:placetype":"locality",
    "wof:population":0
},
  "geometry": {"coordinates":[85.13195,19.924765],"type":"Point"}
}