{
  "type": "Feature",
  "properties": {
    "gn:admin1_code":"37",
    "gn:admin2_code":"404.0",
    "gn:asciiname":"Barra",
    "gn:country_code":"IN",
    "gn:dem":421,
    "gn:feature_class":"P",
    "gn:feature_code":"PPL",
    "gn:name":"Barra",
    "gn:population":0,
    "gn:timezone":"Asia/Kolkata",
    "iso:country":"IN",
    "ks:ks_name":"Barra",
    "ks:ks_pop":441,
    "ks:ks_type":"VILLAGE",
    "name:ara_x_preferred":[
        "\u0628\u0627\u0631\u0627"
    ],
    "name:ben_bn_x_preferred":[
        "\u09ac\u09be\u09dc\u09be"
    ],
    "name:ben_in_x_preferred":[
        "\u09ac\u09be\u09dc\u09be"
    ],
    "name:bre_x_preferred":[
        "Barraigh"
    ],
    "name:ces_x_preferred":[
        "Barra"
    ],
    "name:cym_x_preferred":[
        "Barraigh"
    ],
    "name:deu_x_preferred":[
        "Barra"
    ],
    "name:ell_x_preferred":[
        "\u039c\u03c0\u03ac\u03c1\u03b1"
    ],
    "name:eng_x_preferred":[
        "Barra"
    ],
    "name:epo_x_preferred":[
        "Barra"
    ],
    "name:eus_x_preferred":[
        "Barra"
    ],
    "name:fin_x_preferred":[
        "Barra"
    ],
    "name:fra_x_preferred":[
        "Barra"
    ],
    "name:gla_x_preferred":[
        "Barraigh"
    ],
    "name:gle_x_preferred":[
        "Barraigh"
    ],
    "name:guj_x_preferred":[
        "\u0aac\u0ab0\u0abe"
    ],
    "name:hin_x_preferred":[
        "\u092c\u093e\u0930\u093e"
    ],
    "name:hun_x_preferred":[
        "Barra"
    ],
    "name:isl_x_preferred":[
        "Barrey"
    ],
    "name:jpn_x_preferred":[
        "\u30d0\u30e9\u5cf6"
    ],
    "name:kan_x_preferred":[
        "\u0cac\u0cb0\u0ccd\u0cb0\u0cbe"
    ],
    "name:lit_x_preferred":[
        "Bara"
    ],
    "name:mal_x_preferred":[
        "\u0d2c\u0d3e\u0d30"
    ],
    "name:mar_x_preferred":[
        "\u092c\u0930\u094d\u0930\u093e"
    ],
    "name:nld_x_preferred":[
        "Barra"
    ],
    "name:nno_x_preferred":[
        "Barra"
    ],
    "name:nor_x_preferred":[
        "Barra"
    ],
    "name:pan_x_preferred":[
        "\u0a2c\u0a3e\u0a30\u0a3e"
    ],
    "name:pol_x_preferred":[
        "Barra"
    ],
    "name:por_x_preferred":[
        "Barra"
    ],
    "name:rus_x_preferred":[
        "\u0411\u0430\u0440\u0440\u0430"
    ],
    "name:spa_x_preferred":[
        "Barra"
    ],
    "name:srp_x_preferred":[
        "\u0411\u0430\u0440\u0430"
    ],
    "name:swe_x_preferred":[
        "Barra"
    ],
    "name:tam_x_preferred":[
        "\u0baa\u0bb0\u0bcd\u0bb0\u0bbe"
    ],
    "name:tel_x_preferred":[
        "\u0c2c\u0c30\u0c4d\u0c30\u0c3e"
    ],
    "name:urd_x_preferred":[
        "\u0628\u0631\u0651\u0627"
    ],
    "name:vie_x_preferred":[
        "Barra"
    ],
    "name:zho_x_preferred":[
        "\u5df4\u62c9\u5c9b"
    ],
    "wof:name":"Barra",
    "wof:placetype":"locality",
    "wof:population":441
},
  "geometry": {"coordinates":[82.390838,22.795916],"type":"Point"}
}