{
  "type": "Feature",
  "properties": {
    "iso:country":"IN",
    "ks:ks_name":"Hatitand",
    "ks:ks_pop":493,
    "ks:ks_type":"VILLAGE",
    "name:eng_x_preferred":[
        "Hatitand"
    ],
    "wof:name":"Hatitand",
    "wof:placetype":"locality",
    "wof:population":493
},
  "geometry": {"coordinates":[86.000776,22.772026],"type":"Point"}
}