{
  "type": "Feature",
  "properties": {
    "iso:country":"IN",
    "ks:ks_name":"Gopalapuram",
    "ks:ks_pop":1250,
    "ks:ks_type":"HABITATION",
    "name:eng_x_preferred":[
        "Gopalapuram"
    ],
    "wof:name":"Gopalapuram",
    "wof:placetype":"locality",
    "wof:population":1250
},
  "geometry": {"coordinates":[75.665924,11.470768],"type":"Point"}
}