{
  "type": "Feature",
  "properties": {
    "iso:country":"IN",
    "ks:ks_name":"Lohar Purwa",
    "ks:ks_pop":127,
    "ks:ks_type":"HABITATION",
    "ks:ks_uagg_main":0,
    "name:eng_x_preferred":[
        "Lohar Purwa"
    ],
    "wof:name":"Lohar Purwa",
    "wof:placetype":"neighbourhood",
    "wof:population":127
},
  "geometry": {"coordinates":[82.01435499999999,27.440416],"type":"Point"}
}