{
  "type": "Feature",
  "properties": {
    "gn:admin1_code":"21.0",
    "gn:admin2_code":"398.0",
    "gn:asciiname":"Orona",
    "gn:country_code":"IN",
    "gn:dem":890,
    "gn:feature_class":"P",
    "gn:feature_code":"PPL",
    "gn:name":"Orona",
    "gn:population":0,
    "gn:timezone":"Asia/Kolkata",
    "iso:country":"IN",
    "name:bel_x_preferred":[
        "\u0410\u0440\u043e\u043d\u0430"
    ],
    "name:cat_x_preferred":[
        "Orona"
    ],
    "name:deu_x_preferred":[
        "Orona"
    ],
    "name:ell_x_preferred":[
        "\u039f\u03c1\u03cc\u03bd\u03b1 \u039d\u03ae\u03c3\u03bf\u03c2"
    ],
    "name:fas_x_preferred":[
        "\u0627\u0648\u0631\u0648\u0646\u0627"
    ],
    "name:fin_x_preferred":[
        "Orona"
    ],
    "name:fra_x_preferred":[
        "Orona"
    ],
    "name:glg_x_preferred":[
        "Atol Orona"
    ],
    "name:heb_x_preferred":[
        "\u05d0\u05d8\u05d5\u05dc \u05d0\u05d5\u05e8\u05d5\u05e0\u05d4"
    ],
    "name:hrv_x_preferred":[
        "Orona"
    ],
    "name:ita_x_preferred":[
        "Orona"
    ],
    "name:jpn_x_preferred":[
        "\u30aa\u30ed\u30ca\u5cf6"
    ],
    "name:kor_x_preferred":[
        "\uc624\ub85c\ub098"
    ],
    "name:mkd_x_preferred":[
        "\u041e\u0440\u043e\u043d\u0430"
    ],
    "name:nld_x_preferred":[
        "Orona"
    ],
    "name:nor_x_preferred":[
        "Orona"
    ],
    "name:por_x_preferred":[
        "Orona"
    ],
    "name:rus_x_preferred":[
        "\u041e\u0440\u043e\u043d\u0430"
    ],
    "name:spa_x_preferred":[
        "Atol\u00f3n Orona"
    ],
    "name:swe_x_preferred":[
        "Orona"
    ],
    "name:tur_x_preferred":[
        "Orona"
    ],
    "name:zho_x_preferred":[
        "\u5967\u7f85\u7d0d\u74b0\u7901"
    ],
    "wof:name":"Orona",
    "wof:placetype":"neighbourhood"
},
  "geometry": {"coordinates":[82.65033,18.61413],"type":"Point"}
}