{
  "type": "Feature",
  "properties": {
    "iso:country":"IN",
    "ks:ks_name":"Dakshin Para",
    "ks:ks_pop":1792,
    "ks:ks_type":"HABITATION",
    "name:eng_x_preferred":[
        "Dakshin Para"
    ],
    "wof:name":"Dakshin Para",
    "wof:placetype":"locality",
    "wof:population":1792
},
  "geometry": {"coordinates":[88.723167,22.066797],"type":"Point"}
}