{
  "type": "Feature",
  "properties": {
    "gn:admin1_code":"25",
    "gn:admin2_code":"616.0",
    "gn:asciiname":"Sendurai",
    "gn:country_code":"IN",
    "gn:dem":81,
    "gn:feature_class":"P",
    "gn:feature_code":"PPL",
    "gn:name":"Sendurai",
    "gn:population":0,
    "gn:timezone":"Asia/Kolkata",
    "iso:country":"IN",
    "wof:name":"Sendurai",
    "wof:placetype":"locality"
},
  "geometry": {"coordinates":[79.17675,11.25451],"type":"Point"}
}