{
  "type": "Feature",
  "properties": {
    "iso:country":"IN",
    "ks:ks_name":"Mahibila",
    "ks:ks_pop":327,
    "ks:ks_type":"VILLAGE",
    "name:eng_x_preferred":[
        "Mahibila"
    ],
    "wof:name":"Mahibila",
    "wof:placetype":"locality",
    "wof:population":327
},
  "geometry": {"coordinates":[83.74235,20.547168],"type":"Point"}
}