{
  "type": "Feature",
  "properties": {
    "iso:country":"IN",
    "ks:ks_name":"Nayal",
    "ks:ks_pop":43,
    "ks:ks_type":"VILLAGE",
    "name:eng_x_preferred":[
        "Nayal"
    ],
    "wof:name":"Nayal",
    "wof:placetype":"locality",
    "wof:population":43
},
  "geometry": {"coordinates":[79.94376200000001,29.663398],"type":"Point"}
}