{
  "type": "Feature",
  "properties": {
    "gn:admin1_code":"24.0",
    "gn:admin2_code":"103",
    "gn:asciiname":"Mohanpura",
    "gn:country_code":"IN",
    "gn:dem":334,
    "gn:feature_class":"P",
    "gn:feature_code":"PPL",
    "gn:name":"Mohanpura",
    "gn:population":0,
    "gn:timezone":"Asia/Kolkata",
    "iso:country":"IN",
    "name:und_x_variant":[
        "Bh\u0101marw\u0101si",
        "Mohanpura"
    ],
    "wof:name":"Mohanpura",
    "wof:placetype":"locality"
},
  "geometry": {"coordinates":[75.57155,28.17196],"type":"Point"}
}