{
  "type": "Feature",
  "properties": {
    "iso:country":"IN",
    "ks:ks_alt_nam":"baghiya purwa",
    "ks:ks_name":"Baghiya Purwa",
    "ks:ks_pop":56,
    "ks:ks_type":"HABITATION",
    "ks:ks_uagg_main":0,
    "name:eng_x_preferred":[
        "Baghiya Purwa"
    ],
    "wof:name":"Baghiya Purwa",
    "wof:placetype":"neighbourhood",
    "wof:population":56
},
  "geometry": {"coordinates":[81.631202,27.376168],"type":"Point"}
}