{
  "type": "Feature",
  "properties": {
    "gn:admin1_code":"24.0",
    "gn:admin2_code":"123.0",
    "gn:asciiname":"Dodiarakhera",
    "gn:country_code":"IN",
    "gn:dem":716,
    "gn:feature_class":"P",
    "gn:feature_code":"PPL",
    "gn:name":"Dodi\u0101rakhera",
    "gn:population":0,
    "gn:timezone":"Asia/Kolkata",
    "iso:country":"IN",
    "wof:name":"Dodiarakhera",
    "wof:placetype":"locality"
},
  "geometry": {"coordinates":[73.83104,25.39946],"type":"Point"}
}