{
  "type": "Feature",
  "properties": {
    "iso:country":"IN",
    "ks:ks_name":"Vairankuppam",
    "ks:ks_pop":150,
    "ks:ks_type":"HABITATION",
    "ks:ks_uagg_main":0,
    "name:eng_x_preferred":[
        "Vairankuppam"
    ],
    "wof:name":"Vairankuppam",
    "wof:placetype":"neighbourhood",
    "wof:population":150
},
  "geometry": {"coordinates":[79.73163700000001,11.63482],"type":"Point"}
}