{
  "type": "Feature",
  "properties": {
    "gn:admin1_code":"11",
    "gn:admin2_code":"31.0",
    "gn:asciiname":"Kaphileda",
    "gn:country_code":"IN",
    "gn:dem":1119,
    "gn:feature_class":"P",
    "gn:feature_code":"PPL",
    "gn:name":"Kaphileda",
    "gn:population":0,
    "gn:timezone":"Asia/Kolkata",
    "iso:country":"IN",
    "wof:name":"Kaphileda",
    "wof:placetype":"locality"
},
  "geometry": {"coordinates":[76.73784000000001,31.22055],"type":"Point"}
}