{
  "type": "Feature",
  "properties": {
    "gn:admin1_code":"39",
    "gn:admin2_code":"61.0",
    "gn:asciiname":"Masmoli",
    "gn:country_code":"IN",
    "gn:dem":1518,
    "gn:feature_class":"P",
    "gn:feature_code":"PPL",
    "gn:name":"Masmoli",
    "gn:population":0,
    "gn:timezone":"Asia/Kolkata",
    "iso:country":"IN",
    "wof:name":"Masmoli",
    "wof:placetype":"locality"
},
  "geometry": {"coordinates":[78.92655000000001,29.9054],"type":"Point"}
}