{
  "type": "Feature",
  "properties": {
    "gn:admin1_code":"34.0",
    "gn:admin2_code":"237.0",
    "gn:asciiname":"Kashi Chak",
    "gn:country_code":"IN",
    "gn:dem":62,
    "gn:feature_class":"P",
    "gn:feature_code":"PPL",
    "gn:name":"K\u0101shi Chak",
    "gn:population":0,
    "gn:timezone":"Asia/Kolkata",
    "iso:country":"IN",
    "ks:ks_alt_nam":"K\u0101shi Chak",
    "ks:ks_name":"Kashi Chak",
    "ks:ks_type":"VILLAGE",
    "ks:ks_uagg_main":0,
    "name:eng_x_preferred":[
        "Kashi Chak"
    ],
    "name:eng_x_variant":[
        "K\u0101shi Chak"
    ],
    "wof:name":"Kashi Chak",
    "wof:placetype":"neighbourhood"
},
  "geometry": {"coordinates":[85.72111,25.074575],"type":"Point"}
}