{
  "type": "Feature",
  "properties": {
    "iso:country":"IN",
    "ks:ks_name":"Charaker Kuthi",
    "ks:ks_pop":2315,
    "ks:ks_type":"VILLAGE",
    "name:eng_x_preferred":[
        "Charaker Kuthi"
    ],
    "wof:name":"Charaker Kuthi",
    "wof:placetype":"locality",
    "wof:population":2315
},
  "geometry": {"coordinates":[89.436441,26.272493],"type":"Point"}
}