{
  "type": "Feature",
  "properties": {
    "iso:country":"IN",
    "ks:ks_name":"Jamin Katnawar",
    "ks:ks_pop":174,
    "ks:ks_type":"VILLAGE",
    "name:eng_x_preferred":[
        "Jamin Katnawar"
    ],
    "wof:name":"Jamin Katnawar",
    "wof:placetype":"locality",
    "wof:population":174
},
  "geometry": {"coordinates":[84.03873900000001,26.904625],"type":"Point"}
}