{
  "type": "Feature",
  "properties": {
    "iso:country":"IN",
    "ks:ks_name":"Uriamguri Block",
    "ks:ks_pop":200,
    "ks:ks_type":"HABITATION",
    "name:eng_x_preferred":[
        "Uriamguri Block"
    ],
    "wof:name":"Uriamguri Block",
    "wof:placetype":"locality",
    "wof:population":200
},
  "geometry": {"coordinates":[95.22470800000001,27.340576],"type":"Point"}
}