{
  "type": "Feature",
  "properties": {
    "iso:country":"IN",
    "ks:ks_name":"Paglacherra NC",
    "ks:ks_pop":207,
    "ks:ks_type":"VILLAGE",
    "name:eng_x_preferred":[
        "Paglacherra NC"
    ],
    "wof:name":"Paglacherra NC",
    "wof:placetype":"locality",
    "wof:population":207
},
  "geometry": {"coordinates":[92.522757,24.440063],"type":"Point"}
}