{
  "type": "Feature",
  "properties": {
    "gn:admin1_code":"11.0",
    "gn:admin2_code":"27.0",
    "gn:asciiname":"Rakchui",
    "gn:country_code":"IN",
    "gn:dem":2406,
    "gn:feature_class":"P",
    "gn:feature_code":"PPL",
    "gn:name":"Rakch\u016bi",
    "gn:population":0,
    "gn:timezone":"Asia/Kolkata",
    "iso:country":"IN",
    "wof:name":"Rakchui",
    "wof:placetype":"locality"
},
  "geometry": {"coordinates":[77.16638,31.52991],"type":"Point"}
}