{
  "type": "Feature",
  "properties": {
    "iso:country":"IN",
    "ks:ks_name":"Dakasikula",
    "ks:ks_pop":766,
    "ks:ks_type":"VILLAGE",
    "name:eng_x_preferred":[
        "Dakasikula"
    ],
    "wof:name":"Dakasikula",
    "wof:placetype":"locality",
    "wof:population":766
},
  "geometry": {"coordinates":[83.819828,19.202786],"type":"Point"}
}