{
  "type": "Feature",
  "properties": {
    "gn:admin1_code":"12.0",
    "gn:admin2_code":"010",
    "gn:asciiname":"Baladevi",
    "gn:country_code":"IN",
    "gn:dem":1599,
    "gn:feature_class":"P",
    "gn:feature_code":"PPL",
    "gn:name":"B\u0101l\u0101devi",
    "gn:population":0,
    "gn:timezone":"Asia/Kolkata",
    "iso:country":"IN",
    "wof:name":"Baladevi",
    "wof:placetype":"locality"
},
  "geometry": {"coordinates":[74.93939,34.03564],"type":"Point"}
}