{
  "type": "Feature",
  "properties": {
    "iso:country":"IN",
    "ks:ks_name":"Vadi Pada",
    "ks:ks_pop":504,
    "ks:ks_type":"HABITATION",
    "ks:ks_uagg_main":0,
    "name:eng_x_preferred":[
        "Vadi Pada"
    ],
    "wof:name":"Vadi Pada",
    "wof:placetype":"neighbourhood",
    "wof:population":504
},
  "geometry": {"coordinates":[72.88122199999999,20.291722],"type":"Point"}
}