{
  "type": "Feature",
  "properties": {
    "iso:country":"IN",
    "ks:ks_name":"Shaini Ki Maddiyan",
    "ks:ks_pop":240,
    "ks:ks_type":"HABITATION",
    "name:eng_x_preferred":[
        "Shaini Ki Maddiyan"
    ],
    "wof:name":"Shaini Ki Maddiyan",
    "wof:placetype":"locality",
    "wof:population":240
},
  "geometry": {"coordinates":[79.245197,25.414835],"type":"Point"}
}