{
  "type": "Feature",
  "properties": {
    "iso:country":"IN",
    "ks:ks_name":"Chinra",
    "ks:ks_pop":11358,
    "ks:ks_type":"VILLAGE",
    "name:eng_x_preferred":[
        "Chinra"
    ],
    "wof:name":"Chinra",
    "wof:placetype":"locality",
    "wof:population":11358
},
  "geometry": {"coordinates":[87.914393,22.677348],"type":"Point"}
}