{
  "type": "Feature",
  "properties": {
    "gn:admin1_code":"34.0",
    "gn:admin2_code":"206.0",
    "gn:asciiname":"Narwara",
    "gn:country_code":"IN",
    "gn:dem":62,
    "gn:feature_class":"P",
    "gn:feature_code":"PPL",
    "gn:name":"Narw\u0101ra",
    "gn:population":0,
    "gn:timezone":"Asia/Kolkata",
    "iso:country":"IN",
    "wof:name":"Narwara",
    "wof:placetype":"neighbourhood"
},
  "geometry": {"coordinates":[85.30298000000001,26.36264],"type":"Point"}
}