{
  "type": "Feature",
  "properties": {
    "iso:country":"IN",
    "ks:ks_alt_nam":"1 DNG",
    "ks:ks_name":"1 Dng",
    "ks:ks_pop":13,
    "ks:ks_type":"HABITATION",
    "name:eng_x_preferred":[
        "1 Dng"
    ],
    "wof:name":"1 Dng",
    "wof:placetype":"locality",
    "wof:population":13
},
  "geometry": {"coordinates":[74.507564,29.906133],"type":"Point"}
}