{
  "type": "Feature",
  "properties": {
    "iso:country":"IN",
    "ks:ks_alt_nam":"AMAR SINGH",
    "ks:ks_name":"Amar Singh",
    "ks:ks_pop":95,
    "ks:ks_type":"HABITATION",
    "name:eng_x_preferred":[
        "Amar Singh"
    ],
    "wof:name":"Amar Singh",
    "wof:placetype":"locality",
    "wof:population":95
},
  "geometry": {"coordinates":[81.4037,26.24],"type":"Point"}
}