{
  "type": "Feature",
  "properties": {
    "iso:country":"IN",
    "ks:ks_name":"Vihel",
    "ks:ks_pop":0,
    "ks:ks_type":"VILLAGE",
    "name:eng_x_preferred":[
        "Vihel"
    ],
    "wof:name":"Vihel",
    "wof:placetype":"locality",
    "wof:population":0
},
  "geometry": {"coordinates":[72.775853,21.250687],"type":"Point"}
}