{
  "type": "Feature",
  "properties": {
    "iso:country":"IN",
    "ks:ks_name":"Arada",
    "ks:ks_pop":561,
    "ks:ks_type":"VILLAGE",
    "ks:ks_uagg_main":0,
    "name:eng_x_preferred":[
        "Arada"
    ],
    "wof:name":"Arada",
    "wof:placetype":"neighbourhood",
    "wof:population":561
},
  "geometry": {"coordinates":[86.191712,20.827224],"type":"Point"}
}