{
  "type": "Feature",
  "properties": {
    "iso:country":"IN",
    "ks:ks_name":"Pawarwadi",
    "ks:ks_pop":125,
    "ks:ks_type":"HABITATION",
    "name:eng_x_preferred":[
        "Pawarwadi"
    ],
    "wof:name":"Pawarwadi",
    "wof:placetype":"locality",
    "wof:population":125
},
  "geometry": {"coordinates":[74.0605,20.7644],"type":"Point"}
}