{
  "type": "Feature",
  "properties": {
    "iso:country":"IN",
    "ks:ks_name":"Amrae",
    "ks:ks_pop":355,
    "ks:ks_type":"VILLAGE",
    "name:eng_x_preferred":[
        "Amrae"
    ],
    "wof:name":"Amrae",
    "wof:placetype":"locality",
    "wof:population":355
},
  "geometry": {"coordinates":[85.47568099999999,22.529561],"type":"Point"}
}