{
  "type": "Feature",
  "properties": {
    "iso:country":"IN",
    "ks:ks_name":"Dhopa Tola",
    "ks:ks_pop":474,
    "ks:ks_type":"HABITATION",
    "name:eng_x_preferred":[
        "Dhopa Tola"
    ],
    "wof:name":"Dhopa Tola",
    "wof:placetype":"locality",
    "wof:population":474
},
  "geometry": {"coordinates":[81.51696200000001,22.931612],"type":"Point"}
}