{
  "type": "Feature",
  "properties": {
    "iso:country":"IN",
    "ks:ks_alt_nam":"N\u0101r\u0101yanpur",
    "ks:ks_name":"Narayanpur",
    "ks:ks_type":"VILLAGE",
    "name:eng_x_preferred":[
        "Narayanpur"
    ],
    "name:eng_x_variant":[
        "N\u0101r\u0101yanpur"
    ],
    "name:hin_x_preferred":[
        "\u0928\u093e\u0930\u093e\u092f\u0923\u092a\u0941\u0930"
    ],
    "wof:name":"Narayanpur",
    "wof:placetype":"locality"
},
  "geometry": {"coordinates":[78.926382,20.760375],"type":"Point"}
}