{
  "type": "Feature",
  "properties": {
    "iso:country":"IN",
    "ks:ks_name":"Mohammadabad",
    "ks:ks_pop":601,
    "ks:ks_type":"VILLAGE",
    "ks:ks_uagg_main":0,
    "name:eng_x_preferred":[
        "Mohammadabad"
    ],
    "wof:name":"Mohammadabad",
    "wof:placetype":"neighbourhood",
    "wof:population":601
},
  "geometry": {"coordinates":[86.989772,25.224947],"type":"Point"}
}