{
  "type": "Feature",
  "properties": {
    "iso:country":"IN",
    "ks:ks_alt_nam":"Indra colony",
    "ks:ks_name":"Indra Colony",
    "ks:ks_pop":399,
    "ks:ks_type":"HABITATION",
    "ks:ks_uagg_main":0,
    "name:eng_x_preferred":[
        "Indra Colony"
    ],
    "wof:name":"Indra Colony",
    "wof:placetype":"neighbourhood",
    "wof:population":399
},
  "geometry": {"coordinates":[77.611154,10.05663],"type":"Point"}
}