{
  "type": "Feature",
  "properties": {
    "iso:country":"IN",
    "ks:ks_name":"Panrrasholi",
    "ks:ks_pop":162,
    "ks:ks_type":"VILLAGE",
    "ks:ks_uagg_main":0,
    "name:eng_x_preferred":[
        "Panrrasholi"
    ],
    "wof:name":"Panrrasholi",
    "wof:placetype":"neighbourhood",
    "wof:population":162
},
  "geometry": {"coordinates":[86.694935,22.51504],"type":"Point"}
}