{
  "type": "Feature",
  "properties": {
    "iso:country":"IN",
    "ks:ks_name":"Bichodi",
    "ks:ks_pop":14,
    "ks:ks_type":"HABITATION",
    "name:eng_x_preferred":[
        "Bichodi"
    ],
    "wof:name":"Bichodi",
    "wof:placetype":"locality",
    "wof:population":14
},
  "geometry": {"coordinates":[75.38527000000001,13.65835],"type":"Point"}
}