{
  "type": "Feature",
  "properties": {
    "iso:country":"IN",
    "ks:ks_name":"Goppulatotamamidi",
    "ks:ks_pop":128,
    "ks:ks_type":"HABITATION",
    "name:eng_x_preferred":[
        "Goppulatotamamidi"
    ],
    "wof:name":"Goppulatotamamidi",
    "wof:placetype":"locality",
    "wof:population":128
},
  "geometry": {"coordinates":[81.855822,17.844333],"type":"Point"}
}