{
  "type": "Feature",
  "properties": {
    "iso:country":"IN",
    "ks:ks_name":"Tondali",
    "ks:ks_pop":805,
    "ks:ks_type":"VILLAGE",
    "name:eng_x_preferred":[
        "Tondali"
    ],
    "wof:name":"Tondali",
    "wof:placetype":"locality",
    "wof:population":805
},
  "geometry": {"coordinates":[73.417151,19.186951],"type":"Point"}
}