{
  "type": "Feature",
  "properties": {
    "gn:admin1_code":"19.0",
    "gn:admin2_code":"578.0",
    "gn:asciiname":"Kelsurpur",
    "gn:country_code":"IN",
    "gn:dem":812,
    "gn:feature_class":"P",
    "gn:feature_code":"PPL",
    "gn:name":"Kels\u016brp\u016br",
    "gn:population":0,
    "gn:timezone":"Asia/Kolkata",
    "iso:country":"IN",
    "wof:name":"Kelsurpur",
    "wof:placetype":"locality"
},
  "geometry": {"coordinates":[76.74143000000002,11.82522],"type":"Point"}
}