{
  "type": "Feature",
  "properties": {
    "iso:country":"IN",
    "ks:ks_name":"Ghugutiyalgaon",
    "ks:ks_pop":29,
    "ks:ks_type":"VILLAGE",
    "name:eng_x_preferred":[
        "Ghugutiyalgaon"
    ],
    "wof:name":"Ghugutiyalgaon",
    "wof:placetype":"locality",
    "wof:population":29
},
  "geometry": {"coordinates":[79.328722,29.831354],"type":"Point"}
}