{
  "type": "Feature",
  "properties": {
    "gn:admin1_code":"34.0",
    "gn:admin2_code":"227.0",
    "gn:asciiname":"Mustafapur",
    "gn:country_code":"IN",
    "gn:dem":47,
    "gn:feature_class":"P",
    "gn:feature_code":"PPL",
    "gn:name":"Mustaf\u0101pur",
    "gn:population":0,
    "gn:timezone":"Asia/Kolkata",
    "iso:country":"IN",
    "ks:ks_alt_nam":"Mustaf\u0101pur",
    "ks:ks_name":"Mustafapur",
    "ks:ks_pop":501,
    "ks:ks_type":"VILLAGE",
    "ks:ks_uagg_main":0,
    "name:eng_x_preferred":[
        "Mustafapur"
    ],
    "name:eng_x_variant":[
        "Mustaf\u0101pur"
    ],
    "wof:name":"Mustafapur",
    "wof:placetype":"neighbourhood",
    "wof:population":501
},
  "geometry": {"coordinates":[86.235882,25.220431],"type":"Point"}
}