{
  "type": "Feature",
  "properties": {
    "gn:admin1_code":"23.0",
    "gn:admin2_code":"35.0",
    "gn:asciiname":"Datial",
    "gn:country_code":"IN",
    "gn:dem":264,
    "gn:feature_class":"P",
    "gn:feature_code":"PPL",
    "gn:name":"Dati\u0101l",
    "gn:population":0,
    "gn:timezone":"Asia/Kolkata",
    "iso:country":"IN",
    "ks:ks_alt_nam":"Dati\u0101l",
    "ks:ks_name":"Datial",
    "ks:ks_pop":853,
    "ks:ks_type":"VILLAGE",
    "name:eng_x_preferred":[
        "Datial"
    ],
    "name:eng_x_variant":[
        "Dati\u0101l"
    ],
    "wof:name":"Datial",
    "wof:placetype":"locality",
    "wof:population":853
},
  "geometry": {"coordinates":[75.409865,32.242984],"type":"Point"}
}