{
  "type": "Feature",
  "properties": {
    "iso:country":"IN",
    "ks:ks_name":"Dhanauti Sultanpur",
    "ks:ks_pop":2161,
    "ks:ks_type":"VILLAGE",
    "ks:ks_uagg_main":0,
    "name:eng_x_preferred":[
        "Dhanauti Sultanpur"
    ],
    "wof:name":"Dhanauti Sultanpur",
    "wof:placetype":"neighbourhood",
    "wof:population":2161
},
  "geometry": {"coordinates":[84.974619,25.792551],"type":"Point"}
}