{
  "type": "Feature",
  "properties": {
    "gn:admin1_code":"10.0",
    "gn:admin2_code":"76.0",
    "gn:asciiname":"Garhi",
    "gn:country_code":"IN",
    "gn:dem":227,
    "gn:feature_class":"P",
    "gn:feature_code":"PPL",
    "gn:name":"Garhi",
    "gn:population":0,
    "gn:timezone":"Asia/Kolkata",
    "iso:country":"IN",
    "name:ara_x_preferred":[
        "\u062c\u0627\u0631\u0647\u064a"
    ],
    "name:ben_bn_x_preferred":[
        "\u0997\u09be\u09f0\u09cd\u09b9\u09bf"
    ],
    "name:ben_in_x_preferred":[
        "\u0997\u09be\u09f0\u09cd\u09b9\u09bf"
    ],
    "name:cat_x_preferred":[
        "Garhi"
    ],
    "name:guj_x_preferred":[
        "\u0a97\u0ab0\u0acd\u0ab9\u0ac0"
    ],
    "name:hin_x_preferred":[
        "\u0917\u095d\u0940"
    ],
    "name:kan_x_preferred":[
        "\u0c97\u0cb0\u0ccd\u0cb9\u0cbf"
    ],
    "name:mal_x_preferred":[
        "\u0d17\u0d3e\u0d30\u0d3f"
    ],
    "name:mar_x_preferred":[
        "\u0917\u0922\u0940"
    ],
    "name:pan_x_preferred":[
        "\u0a17\u0a5c\u0a4d\u0a39\u0a40"
    ],
    "name:tam_x_preferred":[
        "\u0b95\u0bb0\u0bcd\u0bb9\u0bbf"
    ],
    "name:tel_x_preferred":[
        "\u0c17\u0c30\u0c4d\u0c39\u0c3f"
    ],
    "name:urd_x_preferred":[
        "\u06af\u0691\u06be\u06cc"
    ],
    "wof:name":"Garhi",
    "wof:placetype":"locality"
},
  "geometry": {"coordinates":[76.71429999999999,29.13836],"type":"Point"}
}