{
  "type": "Feature",
  "properties": {
    "gn:admin1_code":"23.0",
    "gn:admin2_code":"048",
    "gn:asciiname":"Kakrala",
    "gn:country_code":"IN",
    "gn:dem":249,
    "gn:feature_class":"P",
    "gn:feature_code":"PPL",
    "gn:name":"Kakr\u0101la",
    "gn:population":0,
    "gn:timezone":"Asia/Kolkata",
    "iso:country":"IN",
    "name:und_x_variant":[
        "Kakrala Kalan",
        "Kakr\u0101la"
    ],
    "wof:name":"Kakrala",
    "wof:placetype":"locality"
},
  "geometry": {"coordinates":[76.09023000000001,30.37008],"type":"Point"}
}