{
  "type": "Feature",
  "properties": {
    "gn:admin1_code":"36",
    "gn:admin2_code":"147.0",
    "gn:asciiname":"Nagla Ghansham",
    "gn:country_code":"IN",
    "gn:dem":164,
    "gn:feature_class":"P",
    "gn:feature_code":"PPL",
    "gn:name":"Nagla Ghansh\u0101m",
    "gn:population":0,
    "gn:timezone":"Asia/Kolkata",
    "iso:country":"IN",
    "ks:ks_name":"Nagla Ghanshayam",
    "ks:ks_pop":380,
    "ks:ks_type":"HABITATION",
    "ks:ks_uagg_main":0,
    "name:eng_x_preferred":[
        "Nagla Ghanshayam"
    ],
    "wof:name":"Nagla Ghanshayam",
    "wof:placetype":"neighbourhood",
    "wof:population":380
},
  "geometry": {"coordinates":[78.50325100000001,27.174399],"type":"Point"}
}