{
  "type": "Feature",
  "properties": {
    "iso:country":"IN",
    "ks:ks_name":"Mahka",
    "ks:ks_pop":152,
    "ks:ks_type":"HABITATION",
    "name:eng_x_preferred":[
        "Mahka"
    ],
    "wof:name":"Mahka",
    "wof:placetype":"locality",
    "wof:population":152
},
  "geometry": {"coordinates":[79.26509299999999,23.287697],"type":"Point"}
}