{
  "type": "Feature",
  "properties": {
    "iso:country":"IN",
    "ks:ks_name":"Nedungulam",
    "ks:ks_pop":392,
    "ks:ks_type":"HABITATION",
    "name:eng_x_preferred":[
        "Nedungulam"
    ],
    "wof:name":"Nedungulam",
    "wof:placetype":"locality",
    "wof:population":392
},
  "geometry": {"coordinates":[78.876527,10.813163],"type":"Point"}
}