{
  "type": "Feature",
  "properties": {
    "iso:country":"IN",
    "ks:ks_alt_nam":"M\u0101nikpur",
    "ks:ks_name":"Manikpur",
    "ks:ks_pop":66,
    "ks:ks_type":"VILLAGE",
    "name:eng_x_preferred":[
        "Manikpur"
    ],
    "name:eng_x_variant":[
        "M\u0101nikpur"
    ],
    "wof:name":"Manikpur",
    "wof:placetype":"locality",
    "wof:population":66
},
  "geometry": {"coordinates":[83.703185,25.03756],"type":"Point"}
}