{
  "type": "Feature",
  "properties": {
    "iso:country":"IN",
    "name:ara_x_preferred":[
        "\u0628\u0627\u0646\u062f\u0644\u0627\u063a\u0648\u062f\u0627 (\u062c\u0627\u063a\u064a\u0631)"
    ],
    "name:ast_x_preferred":[
        "Bandlaguda Jagir"
    ],
    "name:ben_bn_x_preferred":[
        "\u09ac\u09be\u09a8\u09cd\u09a1\u09b2\u09be\u0997\u09c1\u09a1\u09be (\u099c\u09be\u0997\u09c0\u09b0)"
    ],
    "name:ben_in_x_preferred":[
        "\u09ac\u09be\u09a8\u09cd\u09a1\u09b2\u09be\u0997\u09c1\u09a1\u09be (\u099c\u09be\u0997\u09bf\u09b0)"
    ],
    "name:eng_x_preferred":[
        "Bandlaguda (Jagir)"
    ],
    "name:eng_x_variant":[
        "Bandlaguda",
        "Bandlaguda Jagir"
    ],
    "name:guj_x_preferred":[
        "\u0aac\u0a82\u0aa6\u0ab2\u0abe\u0a97\u0ac1\u0aa1\u0abe (\u0a9c\u0abe\u0a97\u0ac0\u0ab0)"
    ],
    "name:hin_x_preferred":[
        "\u092c\u093e\u0902\u0926\u0932\u093e\u0917\u0941\u095c\u093e (\u091c\u093e\u0917\u0940\u0930)"
    ],
    "name:kan_x_preferred":[
        "\u0cac\u0c82\u0ca6\u0ccd\u0cb2\u0c97\u0cc1\u0ca1 (\u0c9c\u0cbe\u0c97\u0cbf\u0cb0\u0ccd)"
    ],
    "name:mal_x_preferred":[
        "\u0d2c\u0d28\u0d4d\u0d26\u0d4d"
    ],
    "name:mar_x_preferred":[
        "\u092c\u0902\u0921\u0932\u093e\u0917\u0941\u0921\u093e (\u091c\u093e\u0917\u0940\u0930)"
    ],
    "name:nld_x_preferred":[
        "Bandlaguda Jagir"
    ],
    "name:pan_x_preferred":[
        "\u0a2c\u0a70\u0a26\u0a32\u0a3e\u0a17\u0a41\u0a21\u0a3e (\u0a1c\u0a17\u0a40\u0a30)"
    ],
    "name:tam_x_preferred":[
        "\u0baa\u0ba8\u0bcd\u0ba4\u0bcd\u0bb2\u0b95\u0bc1\u0b9f\u0bbe (\u0b9c\u0bbe\u0b95\u0bbf\u0bb0\u0bcd)"
    ],
    "name:tel_x_preferred":[
        "\u0c2c\u0c02\u0c21\u0c4d\u0c32\u0c17\u0c42\u0c21 (\u0c1c\u0c3e\u0c17\u0c3f\u0c30\u0c4d)"
    ],
    "name:tel_x_variant":[
        "\u0c2c\u0c02\u0c21\u0c4d\u0c32\u0c17\u0c42\u0c21"
    ],
    "name:urd_x_preferred":[
        "\u0628\u0646\u062f\u0644\u0627 \u06af\u0688\u0627 (\u062c\u0627\u06af\u06cc\u0631)"
    ],
    "qs:gn_adm0_cc":"IN",
    "qs:gn_local":1269843,
    "qs:local_max":1198,
    "qs:local_sum":10545,
    "qs:localhoods":56,
    "qs:name":"Bandlaguda (Jagir)",
    "qs:name_adm0":"India",
    "qs:name_adm1":"Andhra Pradesh",
    "qs:name_adm2":"Rangareddi",
    "qs:name_local":"Hyderabad",
    "qs:photo_max":41,
    "qs:photo_sum":41,
    "qs:placetype":"Suburb",
    "qs:quad_count":1,
    "qs:woe_adm0":23424848,
    "qs:woe_adm1":2345740,
    "qs:woe_adm2":12586344,
    "qs:woe_lau":0,
    "qs:woe_local":2295414,
    "qs:woe_ver":"7.10.0",
    "wd:wordcount":816,
    "wof:lang":[
        "eng"
    ],
    "wof:name":"Bandlaguda (Jagir)",
    "wof:placetype":"neighbourhood"
},
  "geometry": {"coordinates":[78.397064,17.359814],"type":"Point"}
}