{
  "type": "Feature",
  "properties": {
    "iso:country":"IN",
    "name:eng_x_preferred":[
        "Bandlaguda (Jagir)"
    ],
    "name:eng_x_variant":[
        "Bandlaguda"
    ],
    "name:unk_x_variant":[
        "Bandlaguda (Jagir)"
    ],
    "qs:gn_adm0_cc":"IN",
    "qs:gn_local":1269843,
    "qs:local_max":1198,
    "qs:local_sum":10545,
    "qs:localhoods":56,
    "qs:name":"Bandlaguda (Jagir)",
    "qs:name_adm0":"India",
    "qs:name_adm1":"Andhra Pradesh",
    "qs:name_adm2":"Rangareddi",
    "qs:name_local":"Hyderabad",
    "qs:photo_max":41,
    "qs:photo_sum":41,
    "qs:placetype":"Suburb",
    "qs:quad_count":1,
    "qs:woe_adm0":23424848,
    "qs:woe_adm1":2345740,
    "qs:woe_adm2":12586344,
    "qs:woe_lau":0,
    "qs:woe_local":2295414,
    "qs:woe_ver":"7.10.0",
    "wd:wordcount":816,
    "wof:lang":[
        "eng"
    ],
    "wof:name":"Bandlaguda (Jagir)",
    "wof:placetype":"neighbourhood"
},
  "geometry": {"coordinates":[78.397064,17.359814],"type":"Point"}
}