{
  "type": "Feature",
  "properties": {
    "iso:country":"IN",
    "ks:ks_name":"Harijana Colony Bellarpadi",
    "ks:ks_pop":47,
    "ks:ks_type":"HABITATION",
    "name:eng_x_preferred":[
        "Harijana Colony Bellarpadi"
    ],
    "wof:name":"Harijana Colony Bellarpadi",
    "wof:placetype":"locality",
    "wof:population":47
},
  "geometry": {"coordinates":[74.905028,13.367581],"type":"Point"}
}