{
  "type": "Feature",
  "properties": {
    "gn:admin1_code":"35.0",
    "gn:admin2_code":"431",
    "gn:asciiname":"Kamarwa",
    "gn:country_code":"IN",
    "gn:dem":466,
    "gn:feature_class":"P",
    "gn:feature_code":"PPL",
    "gn:name":"Kamarwa",
    "gn:population":0,
    "gn:timezone":"Asia/Kolkata",
    "iso:country":"IN",
    "name:und_x_variant":[
        "Kumarw\u00e1",
        "Kamarwa"
    ],
    "wof:name":"Kamarwa",
    "wof:placetype":"locality"
},
  "geometry": {"coordinates":[81.08554000000002,23.57031],"type":"Point"}
}