{
  "type": "Feature",
  "properties": {
    "gn:admin1_code":"36.0",
    "gn:admin2_code":"172.0",
    "gn:asciiname":"Ashiqpur",
    "gn:country_code":"IN",
    "gn:dem":116,
    "gn:feature_class":"P",
    "gn:feature_code":"PPL",
    "gn:name":"\u0100shiqpur",
    "gn:population":0,
    "gn:timezone":"Asia/Kolkata",
    "iso:country":"IN",
    "name:und_x_variant":[
        "\u0100shiqpur",
        "Aureiya"
    ],
    "wof:name":"Ashiqpur",
    "wof:placetype":"locality"
},
  "geometry": {"coordinates":[81.01288000000002,25.91287],"type":"Point"}
}