{
  "type": "Feature",
  "properties": {
    "gn:admin1_code":"34.0",
    "gn:admin2_code":"216.0",
    "gn:asciiname":"Baji Raut",
    "gn:country_code":"IN",
    "gn:dem":55,
    "gn:feature_class":"P",
    "gn:feature_code":"PPL",
    "gn:name":"B\u0101ji Raut",
    "gn:population":0,
    "gn:timezone":"Asia/Kolkata",
    "iso:country":"IN",
    "ks:ks_alt_nam":"B\u0101ji Raut",
    "ks:ks_name":"Baji Raut",
    "ks:ks_pop":1105,
    "ks:ks_type":"VILLAGE",
    "name:eng_x_preferred":[
        "Baji Raut"
    ],
    "name:eng_x_variant":[
        "B\u0101ji Raut"
    ],
    "wof:name":"Baji Raut",
    "wof:placetype":"locality",
    "wof:population":1105
},
  "geometry": {"coordinates":[85.517996,25.956766],"type":"Point"}
}