{
  "type": "Feature",
  "properties": {
    "iso:country":"IN",
    "ks:ks_name":"Champabari T E",
    "ks:ks_pop":564,
    "ks:ks_type":"HABITATION",
    "name:eng_x_preferred":[
        "Champabari T E"
    ],
    "wof:name":"Champabari T E",
    "wof:placetype":"locality",
    "wof:population":564
},
  "geometry": {"coordinates":[92.276273,24.624226],"type":"Point"}
}