{
  "type": "Feature",
  "properties": {
    "iso:country":"IN",
    "ks:ks_name":"Pura Babha",
    "ks:ks_pop":306,
    "ks:ks_type":"HABITATION",
    "name:eng_x_preferred":[
        "Pura Babha"
    ],
    "wof:name":"Pura Babha",
    "wof:placetype":"locality",
    "wof:population":306
},
  "geometry": {"coordinates":[81.672631,26.498076],"type":"Point"}
}