{
  "type": "Feature",
  "properties": {
    "iso:country":"IN",
    "ks:ks_name":"Mahuabathan",
    "ks:ks_pop":353,
    "ks:ks_type":"VILLAGE",
    "name:eng_x_preferred":[
        "Mahuabathan"
    ],
    "wof:name":"Mahuabathan",
    "wof:placetype":"locality",
    "wof:population":353
},
  "geometry": {"coordinates":[87.40166600000001,24.972852],"type":"Point"}
}