{
  "type": "Feature",
  "properties": {
    "iso:country":"IN",
    "ks:ks_name":"Tatiamora",
    "ks:ks_type":"VILLAGE",
    "ks:ks_uagg_main":0,
    "name:eng_x_preferred":[
        "Tatiamora"
    ],
    "wof:name":"Tatiamora",
    "wof:placetype":"neighbourhood"
},
  "geometry": {"coordinates":[94.055195,27.091647],"type":"Point"}
}