{
  "type": "Feature",
  "properties": {
    "iso:country":"IN",
    "ks:ks_name":"Amanat Manullah Jamadar",
    "ks:ks_pop":0,
    "ks:ks_type":"VILLAGE",
    "name:eng_x_preferred":[
        "Amanat Manullah Jamadar"
    ],
    "wof:name":"Amanat Manullah Jamadar",
    "wof:placetype":"locality",
    "wof:population":0
},
  "geometry": {"coordinates":[86.988417,25.52964],"type":"Point"}
}