{
  "type": "Feature",
  "properties": {
    "gn:admin1_code":"12",
    "gn:admin2_code":"18.0",
    "gn:asciiname":"Barthaun",
    "gn:country_code":"IN",
    "gn:dem":2786,
    "gn:feature_class":"P",
    "gn:feature_code":"PPL",
    "gn:name":"Barthaun",
    "gn:population":0,
    "gn:timezone":"Asia/Kolkata",
    "iso:country":"IN",
    "wof:name":"Barthaun",
    "wof:placetype":"locality"
},
  "geometry": {"coordinates":[76.28004,33.18029],"type":"Point"}
}