{
  "type": "Feature",
  "properties": {
    "gn:admin1_code":"40",
    "gn:admin2_code":"532.0",
    "gn:asciiname":"Islamnagar",
    "gn:country_code":"IN",
    "gn:dem":438,
    "gn:feature_class":"P",
    "gn:feature_code":"PPL",
    "gn:name":"Isl\u0101mnagar",
    "gn:population":0,
    "gn:timezone":"Asia/Kolkata",
    "iso:country":"IN",
    "name:hin_x_preferred":[
        "\u0907\u0938\u094d\u0932\u093e\u092e \u0928\u0917\u0930"
    ],
    "wof:name":"Islamnagar",
    "wof:placetype":"locality"
},
  "geometry": {"coordinates":[78.44419000000001,19.38445],"type":"Point"}
}