{
  "type": "Feature",
  "properties": {
    "iso:country":"IN",
    "ks:ks_name":"Tamkarwadi",
    "ks:ks_pop":780,
    "ks:ks_type":"HABITATION",
    "name:eng_x_preferred":[
        "Tamkarwadi"
    ],
    "wof:name":"Tamkarwadi",
    "wof:placetype":"locality",
    "wof:population":780
},
  "geometry": {"coordinates":[73.718383,18.302275],"type":"Point"}
}