{
  "type": "Feature",
  "properties": {
    "iso:country":"IN",
    "ks:ks_name":"Surhiya Dhani",
    "ks:ks_pop":300,
    "ks:ks_type":"HABITATION",
    "name:eng_x_preferred":[
        "Surhiya Dhani"
    ],
    "wof:name":"Surhiya Dhani",
    "wof:placetype":"locality",
    "wof:population":300
},
  "geometry": {"coordinates":[82.48853,27.313173],"type":"Point"}
}