{
  "type": "Feature",
  "properties": {
    "iso:country":"IN",
    "ks:ks_name":"Pandit Deeh",
    "ks:ks_pop":59,
    "ks:ks_type":"HABITATION",
    "name:eng_x_preferred":[
        "Pandit Deeh"
    ],
    "wof:name":"Pandit Deeh",
    "wof:placetype":"locality",
    "wof:population":59
},
  "geometry": {"coordinates":[83.001295,27.196629],"type":"Point"}
}