{
  "type": "Feature",
  "properties": {
    "gn:admin1_code":"19.0",
    "gn:admin2_code":"572",
    "gn:asciiname":"Chandapura",
    "gn:country_code":"IN",
    "gn:dem":878,
    "gn:feature_class":"P",
    "gn:feature_code":"PPL",
    "gn:name":"Chandapura",
    "gn:population":0,
    "gn:timezone":"Asia/Kolkata",
    "iso:country":"IN",
    "ks:ks_name":"Chandapura",
    "ks:ks_pop":1253,
    "ks:ks_type":"URBAN",
    "ks:ks_uagg_main":0,
    "name:eng_x_preferred":[
        "Chandapura"
    ],
    "name:tam_x_preferred":[
        "\u0b9a\u0ba8\u0bcd\u0ba4\u0bc8\u0baa\u0bc1\u0bb0\u0bae\u0bcd"
    ],
    "name:vie_x_preferred":[
        "Chandapura"
    ],
    "wof:name":"Chandapura",
    "wof:placetype":"locality",
    "wof:population":1253
},
  "geometry": {"coordinates":[77.70547500000001,12.800429],"type":"Point"}
}