{
  "type": "Feature",
  "properties": {
    "gn:admin1_code":"19.0",
    "gn:admin2_code":"582.0",
    "gn:asciiname":"Arigepalli",
    "gn:country_code":"IN",
    "gn:dem":751,
    "gn:feature_class":"P",
    "gn:feature_code":"PPL",
    "gn:name":"Arigepalli",
    "gn:population":0,
    "gn:timezone":"Asia/Kolkata",
    "iso:country":"IN",
    "wof:name":"Arigepalli",
    "wof:placetype":"locality"
},
  "geometry": {"coordinates":[77.82346,13.7058],"type":"Point"}
}