{
  "type": "Feature",
  "properties": {
    "iso:country":"IN",
    "ks:ks_name":"Bherbari",
    "ks:ks_pop":908,
    "ks:ks_type":"HABITATION",
    "name:eng_x_preferred":[
        "Bherbari"
    ],
    "wof:name":"Bherbari",
    "wof:placetype":"locality",
    "wof:population":908
},
  "geometry": {"coordinates":[90.639228,25.932078],"type":"Point"}
}