{
  "type": "Feature",
  "properties": {
    "iso:country":"IN",
    "ks:ks_name":"Jagatpur",
    "ks:ks_type":"VILLAGE",
    "ks:ks_uagg_main":0,
    "name:eng_x_preferred":[
        "Jagatpur"
    ],
    "wof:name":"Jagatpur",
    "wof:placetype":"neighbourhood"
},
  "geometry": {"coordinates":[83.390002,21.912065],"type":"Point"}
}