{
  "type": "Feature",
  "properties": {
    "gn:admin1_code":"36.0",
    "gn:admin2_code":"184.0",
    "gn:asciiname":"Shankar Jot",
    "gn:country_code":"IN",
    "gn:dem":96,
    "gn:feature_class":"P",
    "gn:feature_code":"PPL",
    "gn:name":"Shankar Jot",
    "gn:population":0,
    "gn:timezone":"Asia/Kolkata",
    "iso:country":"IN",
    "ks:ks_name":"Shankar Jot",
    "ks:ks_pop":392,
    "ks:ks_type":"VILLAGE",
    "ks:ks_uagg_main":0,
    "name:eng_x_preferred":[
        "Shankar Jot"
    ],
    "wof:name":"Shankar Jot",
    "wof:placetype":"neighbourhood",
    "wof:population":392
},
  "geometry": {"coordinates":[82.743205,27.229468],"type":"Point"}
}