{
  "type": "Feature",
  "properties": {
    "gn:admin1_code":"19.0",
    "gn:admin2_code":"573.0",
    "gn:asciiname":"Tenkhalli",
    "gn:country_code":"IN",
    "gn:dem":664,
    "gn:feature_class":"P",
    "gn:feature_code":"PPL",
    "gn:name":"Tenkhalli",
    "gn:population":0,
    "gn:timezone":"Asia/Kolkata",
    "iso:country":"IN",
    "wof:name":"Tenkhalli",
    "wof:placetype":"locality"
},
  "geometry": {"coordinates":[77.06571,12.31184],"type":"Point"}
}