{
  "type": "Feature",
  "properties": {
    "iso:country":"IN",
    "ks:ks_name":"Tumbebeedu",
    "ks:ks_pop":45,
    "ks:ks_type":"HABITATION",
    "name:eng_x_preferred":[
        "Tumbebeedu"
    ],
    "wof:name":"Tumbebeedu",
    "wof:placetype":"locality",
    "wof:population":45
},
  "geometry": {"coordinates":[74.794276,14.871856],"type":"Point"}
}