{
  "type": "Feature",
  "properties": {
    "iso:country":"IN",
    "ks:ks_name":"Manandipattu",
    "ks:ks_pop":900,
    "ks:ks_type":"HABITATION",
    "name:eng_x_preferred":[
        "Manandipattu"
    ],
    "wof:name":"Manandipattu",
    "wof:placetype":"locality",
    "wof:population":900
},
  "geometry": {"coordinates":[78.758589,12.270179],"type":"Point"}
}