{
  "type": "Feature",
  "properties": {
    "gn:admin1_code":"11.0",
    "gn:admin2_code":"32.0",
    "gn:asciiname":"Kot",
    "gn:country_code":"IN",
    "gn:dem":1278,
    "gn:feature_class":"P",
    "gn:feature_code":"PPL",
    "gn:name":"Kot",
    "gn:population":0,
    "gn:timezone":"Asia/Kolkata",
    "iso:country":"IN",
    "name:pol_x_preferred":[
        "Kot"
    ],
    "wof:name":"Kot",
    "wof:placetype":"locality"
},
  "geometry": {"coordinates":[77.12482,30.84053],"type":"Point"}
}