{
  "type": "Feature",
  "properties": {
    "iso:country":"IN",
    "ks:ks_name":"Baliyaguda",
    "ks:ks_pop":153,
    "ks:ks_type":"HABITATION",
    "name:eng_x_preferred":[
        "Baliyaguda"
    ],
    "wof:name":"Baliyaguda",
    "wof:placetype":"locality",
    "wof:population":153
},
  "geometry": {"coordinates":[82.818806,18.384044],"type":"Point"}
}