{
  "type": "Feature",
  "properties": {
    "iso:country":"IN",
    "ks:ks_name":"Vehagi",
    "ks:ks_pop":1016,
    "ks:ks_type":"VILLAGE",
    "name:eng_x_preferred":[
        "Vehagi"
    ],
    "wof:name":"Vehagi",
    "wof:placetype":"locality",
    "wof:population":1016
},
  "geometry": {"coordinates":[73.926704,21.739174],"type":"Point"}
}