{
  "type": "Feature",
  "properties": {
    "gn:admin1_code":"11.0",
    "gn:admin2_code":"32.0",
    "gn:asciiname":"Khangar",
    "gn:country_code":"IN",
    "gn:dem":905,
    "gn:feature_class":"P",
    "gn:feature_code":"PPL",
    "gn:name":"Khangar",
    "gn:population":0,
    "gn:timezone":"Asia/Kolkata",
    "iso:country":"IN",
    "name:ceb_x_preferred":[
        "Gora Khangar"
    ],
    "name:ces_x_preferred":[
        "Changar"
    ],
    "name:dan_x_preferred":[
        "Khangar"
    ],
    "name:hin_x_preferred":[
        "\u0916\u0902\u0917\u093e\u0930"
    ],
    "name:nld_x_preferred":[
        "Changar"
    ],
    "name:nno_x_preferred":[
        "Khangar"
    ],
    "name:nor_x_preferred":[
        "Khangar"
    ],
    "name:rus_x_preferred":[
        "\u0425\u0430\u043d\u0433\u0430\u0440"
    ],
    "name:slk_x_preferred":[
        "Changar"
    ],
    "name:zho_x_preferred":[
        "\u6f22\u52a0\u723e\u706b\u5c71"
    ],
    "wof:name":"Khangar",
    "wof:placetype":"locality"
},
  "geometry": {"coordinates":[77.12003,30.7216],"type":"Point"}
}