{
  "type": "Feature",
  "properties": {
    "gn:admin1_code":"7.0",
    "gn:admin2_code":"90.0",
    "gn:asciiname":"Kirari Sulemannagar",
    "gn:country_code":"IN",
    "gn:dem":215,
    "gn:feature_class":"P",
    "gn:feature_code":"PPL",
    "gn:name":"Kir\u0101ri Sulem\u0101nnagar",
    "gn:population":0,
    "gn:timezone":"Asia/Kolkata",
    "iso:country":"IN",
    "ks:ks_alt_nam":"Kir\u0101ri Sulem\u0101nnagar",
    "ks:ks_name":"Kirari Sulemannagar",
    "ks:ks_type":"VILLAGE",
    "ks:ks_uagg_main":0,
    "name:ara_x_preferred":[
        "\u0643\u064a\u0631\u0627\u0631\u064a \u0633\u0644\u064a\u0645\u0627\u0646 \u0646\u0627\u062c\u0627\u0631"
    ],
    "name:ben_bn_x_preferred":[
        "\u0995\u09bf\u09b0\u09be\u09b0\u09bf \u09b8\u09c1\u09b2\u09c7\u09ae\u09be\u09a8\u09a8\u0997\u09b0"
    ],
    "name:ben_in_x_preferred":[
        "\u0995\u09bf\u09b0\u09be\u09b0\u09bf \u09b8\u09c1\u09b2\u09c7\u09ae\u09be\u09a8\u09a8\u0997\u09b0"
    ],
    "name:guj_x_preferred":[
        "\u0a95\u0abf\u0ab0\u0abe\u0ab0\u0ac0 \u0ab8\u0ac1\u0ab2\u0ac7\u0aae\u0abe\u0aa8\u0aa8\u0a97\u0ab0"
    ],
    "name:hin_x_preferred":[
        "\u0915\u093f\u0930\u093e\u0930\u0940 \u0938\u0941\u0932\u0947\u092e\u093e\u0928\u0928\u0917\u0930"
    ],
    "name:kan_x_preferred":[
        "\u0c95\u0cbf\u0cb0\u0cbe\u0cb0\u0cbf \u0cb8\u0cc1\u0cb2\u0cc7\u0cae\u0cbe\u0ca8\u0ccd"
    ],
    "name:mal_x_preferred":[
        "\u0d15\u0d3f\u0d30\u0d3e\u0d30\u0d3f \u0d38\u0d41\u0d32\u0d46\u0d2e\u0d3e\u0d28\u0d17\u0d7c"
    ],
    "name:mar_x_preferred":[
        "\u0915\u093f\u0930\u093e\u0930\u0940 \u0938\u0941\u0932\u0947\u092e\u093e\u0928 \u0928\u0917\u0930"
    ],
    "name:pan_x_preferred":[
        "\u0a15\u0a3f\u0a30\u0a3e\u0a30\u0a40 \u0a38\u0a41\u0a32\u0a47\u0a2e\u0a3e\u0a28\u0a28\u0a17\u0a30"
    ],
    "name:tam_x_preferred":[
        "\u0b95\u0bbf\u0bb0\u0bbe\u0bb0\u0bbf \u0b9a\u0bc1\u0bb2\u0bc7\u0bae\u0bbe\u0ba9\u0bcd\u0ba8\u0b95\u0bb0\u0bcd"
    ],
    "name:tel_x_preferred":[
        "\u0c15\u0c3f\u0c30\u0c3e\u0c30\u0c3f \u0c38\u0c41\u0c32\u0c47\u0c2e\u0c3e\u0c28\u0c4d"
    ],
    "name:urd_x_preferred":[
        "\u06a9\u06cc\u0631\u0627\u0631\u06cc \u0633\u0644\u06cc\u0645\u0627\u0646 \u0646\u06af\u0631"
    ],
    "wof:name":"Kirari Sulemannagar",
    "wof:placetype":"neighbourhood"
},
  "geometry": {"coordinates":[77.06480000000001,28.69736],"type":"Point"}
}