{
  "type": "Feature",
  "properties": {
    "gn:country":"IN",
    "gn:fcode":"PPL",
    "gn:population":22642,
    "iso:country":"IN",
    "name:ben_x_preferred":[
        "\u09ae\u09be\u09a5\u09be\u09ad\u09be\u0999\u09cd\u0997\u09be"
    ],
    "name:bpy_x_preferred":[
        "\u09ae\u09be\u09a5\u09be\u09ad\u09be\u0999\u09cd\u0997\u09be"
    ],
    "name:ceb_x_preferred":[
        "M\u0101t\u0101bh\u0101nga"
    ],
    "name:eng_x_preferred":[
        "Mathabhanga"
    ],
    "name:fas_x_preferred":[
        "\u0645\u0627\u062a\u0647\u0627\u0628\u0646\u06af\u0627"
    ],
    "name:fra_x_preferred":[
        "Mathabhanga"
    ],
    "name:hif_x_preferred":[
        "Mathabhanga"
    ],
    "name:hin_x_preferred":[
        "\u092e\u093e\u0925\u093e\u092d\u093e\u0902\u0917\u093e"
    ],
    "name:ita_x_preferred":[
        "Mathabhanga"
    ],
    "name:msa_x_preferred":[
        "Mathabhanga"
    ],
    "name:new_x_preferred":[
        "\u092e\u093e\u0925\u093e\u092d\u0902\u0917\u093e"
    ],
    "name:nld_x_preferred":[
        "Mathabhanga"
    ],
    "name:ori_x_preferred":[
        "\u0b2e\u0b3e\u0b25\u0b3e\u0b2d\u0b3e\u0b19\u0b4d\u0b17\u0b3e"
    ],
    "name:por_x_preferred":[
        "Mathabhanga"
    ],
    "name:spa_x_preferred":[
        "Mathabhanga"
    ],
    "name:swe_x_preferred":[
        "M\u0101t\u0101bh\u0101nga"
    ],
    "name:urd_x_preferred":[
        "\u0645\u0627\u062a\u06be\u0627\u0628\u06be\u0646\u06af\u0627"
    ],
    "name:vie_x_preferred":[
        "Mathabhanga"
    ],
    "name:zho_x_preferred":[
        "\u9a6c\u5854\u90a6\u683c\u963f"
    ],
    "qs:name":"M\u0101t\u0101bh\u0101nga",
    "qs:photos_9r":0,
    "qs:photos_sr":0,
    "qs:pop_sr":"7",
    "wof:name":"M\u0101t\u0101bh\u0101nga",
    "wof:placetype":"locality",
    "wof:population":22642
},
  "geometry": {"coordinates":[89.21554999999999,26.34197],"type":"Point"}
}