{
  "type": "Feature",
  "properties": {
    "gn:admin1_code":"21.0",
    "gn:admin2_code":"386.0",
    "gn:asciiname":"Radhamohanpur",
    "gn:country_code":"IN",
    "gn:dem":17,
    "gn:feature_class":"P",
    "gn:feature_code":"PPL",
    "gn:name":"Radhamohanpur",
    "gn:population":0,
    "gn:timezone":"Asia/Kolkata",
    "iso:country":"IN",
    "ks:ks_name":"Radhamohanpur",
    "ks:ks_pop":545,
    "ks:ks_type":"VILLAGE",
    "name:eng_x_preferred":[
        "Radhamohanpur"
    ],
    "wof:name":"Radhamohanpur",
    "wof:placetype":"locality",
    "wof:population":545
},
  "geometry": {"coordinates":[85.83259700000001,20.198318],"type":"Point"}
}