{
  "type": "Feature",
  "properties": {
    "gn:admin1_code":"21.0",
    "gn:admin2_code":"386.0",
    "gn:asciiname":"Radhamohanpur",
    "gn:country_code":"IN",
    "gn:dem":17,
    "gn:feature_class":"P",
    "gn:feature_code":"PPL",
    "gn:name":"Radhamohanpur",
    "gn:population":0,
    "gn:timezone":"Asia/Kolkata",
    "iso:country":"IN",
    "wof:name":"Radhamohanpur",
    "wof:placetype":"locality"
},
  "geometry": {"coordinates":[85.83006999999998,20.20044],"type":"Point"}
}