{
  "type": "Feature",
  "properties": {
    "gn:admin1_code":"23.0",
    "gn:admin2_code":"41.0",
    "gn:asciiname":"Basi",
    "gn:country_code":"IN",
    "gn:dem":272,
    "gn:feature_class":"P",
    "gn:feature_code":"PPL",
    "gn:name":"Basi",
    "gn:population":0,
    "gn:timezone":"Asia/Kolkata",
    "iso:country":"IN",
    "name:ara_x_preferred":[
        "\u0628\u0627\u0633\u064a"
    ],
    "name:ben_bn_x_preferred":[
        "\u09ac\u09be\u09b8\u09bf"
    ],
    "name:ben_in_x_preferred":[
        "\u09ac\u09be\u09b8\u09bf"
    ],
    "name:cat_x_preferred":[
        "Basi"
    ],
    "name:guj_x_preferred":[
        "\u0aac\u0abe\u0ab8\u0ac0"
    ],
    "name:hin_x_preferred":[
        "\u092c\u093e\u0938\u0940"
    ],
    "name:ilo_x_preferred":[
        "Basi"
    ],
    "name:ita_x_preferred":[
        "Basi"
    ],
    "name:kan_x_preferred":[
        "\u0cac\u0cb8\u0cbf"
    ],
    "name:lit_x_preferred":[
        "Basis"
    ],
    "name:mal_x_preferred":[
        "\u0d2c\u0d47\u0d38\u0d3f"
    ],
    "name:mar_x_preferred":[
        "\u092c\u093e\u0938\u0940"
    ],
    "name:pan_x_preferred":[
        "\u0a2c\u0a38\u0a40"
    ],
    "name:spa_x_preferred":[
        "Basi"
    ],
    "name:tam_x_preferred":[
        "\u0baa\u0bb8\u0bbf"
    ],
    "name:tel_x_preferred":[
        "\u0c2c\u0c3e\u0c38\u0c3f"
    ],
    "name:und_x_variant":[
        "G\u016bjr\u0101n"
    ],
    "name:urd_x_preferred":[
        "\u0628\u0627\u0633\u06cc"
    ],
    "wof:name":"Basi",
    "wof:placetype":"locality"
},
  "geometry": {"coordinates":[76.35531999999998,30.88201],"type":"Point"}
}