{
  "type": "Feature",
  "properties": {
    "gn:admin1_code":"23.0",
    "gn:admin2_code":"41.0",
    "gn:asciiname":"Basi",
    "gn:country_code":"IN",
    "gn:dem":272,
    "gn:feature_class":"P",
    "gn:feature_code":"PPL",
    "gn:name":"Basi",
    "gn:population":0,
    "gn:timezone":"Asia/Kolkata",
    "iso:country":"IN",
    "name:cat_x_preferred":[
        "Basi"
    ],
    "name:ilo_x_preferred":[
        "Basi"
    ],
    "name:ita_x_preferred":[
        "Basi"
    ],
    "name:lit_x_preferred":[
        "Basis"
    ],
    "name:spa_x_preferred":[
        "Basi"
    ],
    "name:und_x_variant":[
        "G\u016bjr\u0101n"
    ],
    "wof:name":"Basi",
    "wof:placetype":"locality"
},
  "geometry": {"coordinates":[76.35531999999998,30.88201],"type":"Point"}
}