{
  "type": "Feature",
  "properties": {
    "iso:country":"IN",
    "ks:ks_name":"Satnami Chuk",
    "ks:ks_pop":399,
    "ks:ks_type":"HABITATION",
    "ks:ks_uagg_main":0,
    "name:eng_x_preferred":[
        "Satnami Chuk"
    ],
    "wof:name":"Satnami Chuk",
    "wof:placetype":"neighbourhood",
    "wof:population":399
},
  "geometry": {"coordinates":[95.165188,27.11108],"type":"Point"}
}