{
  "type": "Feature",
  "properties": {
    "iso:country":"IN",
    "ks:ks_name":"Agarchayanpur",
    "ks:ks_pop":48,
    "ks:ks_type":"VILLAGE",
    "name:eng_x_preferred":[
        "Agarchayanpur"
    ],
    "wof:name":"Agarchayanpur",
    "wof:placetype":"locality",
    "wof:population":48
},
  "geometry": {"coordinates":[86.740633,23.739263],"type":"Point"}
}