{
  "type": "Feature",
  "properties": {
    "iso:country":"IN",
    "ks:ks_alt_nam":"B\u0101nd\u0101bera",
    "ks:ks_name":"Bandabera",
    "ks:ks_pop":631,
    "ks:ks_type":"VILLAGE",
    "name:eng_x_preferred":[
        "Bandabera"
    ],
    "name:eng_x_variant":[
        "B\u0101nd\u0101bera"
    ],
    "wof:name":"Bandabera",
    "wof:placetype":"locality",
    "wof:population":631
},
  "geometry": {"coordinates":[85.583063,22.394187],"type":"Point"}
}