{
  "type": "Feature",
  "properties": {
    "iso:country":"IN",
    "ks:ks_name":"Daharua",
    "ks:ks_pop":0,
    "ks:ks_type":"VILLAGE",
    "name:eng_x_preferred":[
        "Daharua"
    ],
    "wof:name":"Daharua",
    "wof:placetype":"locality",
    "wof:population":0
},
  "geometry": {"coordinates":[86.74794,24.21887],"type":"Point"}
}