{
  "type": "Feature",
  "properties": {
    "gn:admin1_code":"19.0",
    "gn:admin2_code":"574.0",
    "gn:asciiname":"Nelgalli",
    "gn:country_code":"IN",
    "gn:dem":973,
    "gn:feature_class":"P",
    "gn:feature_code":"PPL",
    "gn:name":"Nelgalli",
    "gn:population":0,
    "gn:timezone":"Asia/Kolkata",
    "iso:country":"IN",
    "wof:name":"Nelgalli",
    "wof:placetype":"locality"
},
  "geometry": {"coordinates":[75.6365,12.98882],"type":"Point"}
}