{
  "type": "Feature",
  "properties": {
    "gn:admin1_code":"19.0",
    "gn:admin2_code":"574.0",
    "gn:asciiname":"Nelgalli",
    "gn:country_code":"IN",
    "gn:dem":973,
    "gn:feature_class":"P",
    "gn:feature_code":"PPL",
    "gn:name":"Nelgalli",
    "gn:population":0,
    "gn:timezone":"Asia/Kolkata",
    "iso:country":"IN",
    "ks:ks_name":"Nelagalli",
    "ks:ks_pop":310,
    "ks:ks_type":"VILLAGE",
    "name:eng_x_preferred":[
        "Nelagalli"
    ],
    "name:eng_x_variant":[
        "Nelgalli"
    ],
    "wof:name":"Nelagalli",
    "wof:placetype":"locality",
    "wof:population":310
},
  "geometry": {"coordinates":[75.631789,12.997462],"type":"Point"}
}