{
  "type": "Feature",
  "properties": {
    "iso:country":"IN",
    "ks:ks_name":"Matamaripally",
    "ks:ks_pop":72,
    "ks:ks_type":"HABITATION",
    "name:eng_x_preferred":[
        "Matamaripally"
    ],
    "wof:name":"Matamaripally",
    "wof:placetype":"locality",
    "wof:population":72
},
  "geometry": {"coordinates":[77.89866499999999,16.878977],"type":"Point"}
}