{
  "type": "Feature",
  "properties": {
    "gn:admin1_code":"36",
    "gn:admin2_code":"191.0",
    "gn:asciiname":"Salarpur",
    "gn:country_code":"IN",
    "gn:dem":82,
    "gn:feature_class":"P",
    "gn:feature_code":"PPL",
    "gn:name":"Sal\u0101rpur",
    "gn:population":0,
    "gn:timezone":"Asia/Kolkata",
    "iso:country":"IN",
    "ks:ks_alt_nam":"Sal\u0101rpur",
    "ks:ks_name":"Salarpur",
    "ks:ks_pop":1201,
    "ks:ks_type":"VILLAGE",
    "ks:ks_uagg_main":0,
    "name:eng_x_preferred":[
        "Salarpur"
    ],
    "name:eng_x_variant":[
        "Sal\u0101rpur"
    ],
    "name:urd_x_preferred":[
        "\u0633\u0627\u0644\u0627\u0631 \u067e\u0648\u0631"
    ],
    "wof:name":"Salarpur",
    "wof:placetype":"locality",
    "wof:population":1201
},
  "geometry": {"coordinates":[83.154614,26.028199],"type":"Point"}
}