{
  "type": "Feature",
  "properties": {
    "iso:country":"IN",
    "ks:ks_name":"Tetelpada",
    "ks:ks_pop":107,
    "ks:ks_type":"HABITATION",
    "name:eng_x_preferred":[
        "Tetelpada"
    ],
    "wof:name":"Tetelpada",
    "wof:placetype":"locality",
    "wof:population":107
},
  "geometry": {"coordinates":[82.66584,20.092803],"type":"Point"}
}