{
  "type": "Feature",
  "properties": {
    "iso:country":"IN",
    "ks:ks_alt_nam":"Bevinal SK",
    "ks:ks_name":"Bevinal Sk",
    "ks:ks_pop":221,
    "ks:ks_type":"HABITATION",
    "name:eng_x_preferred":[
        "Bevinal Sk"
    ],
    "wof:name":"Bevinal Sk",
    "wof:placetype":"locality",
    "wof:population":221
},
  "geometry": {"coordinates":[76.80819200000001,16.446988],"type":"Point"}
}