{
  "type": "Feature",
  "properties": {
    "gn:admin1_code":"12.0",
    "gn:admin2_code":"008",
    "gn:asciiname":"Gund-i-Khalil",
    "gn:country_code":"IN",
    "gn:dem":1584,
    "gn:feature_class":"P",
    "gn:feature_code":"PPL",
    "gn:name":"Gund-i-Khal\u012bl",
    "gn:population":0,
    "gn:timezone":"Asia/Kolkata",
    "iso:country":"IN",
    "wof:name":"Gund-i-Khalil",
    "wof:placetype":"locality"
},
  "geometry": {"coordinates":[74.65855000000001,34.10612],"type":"Point"}
}