{
  "type": "Feature",
  "properties": {
    "iso:country":"IN",
    "ks:ks_name":"Raipur",
    "ks:ks_pop":196,
    "ks:ks_type":"HABITATION",
    "ks:ks_uagg_main":0,
    "name:eng_x_preferred":[
        "Raipur"
    ],
    "wof:name":"Raipur",
    "wof:placetype":"neighbourhood",
    "wof:population":196
},
  "geometry": {"coordinates":[81.01738899999999,28.169767],"type":"Point"}
}