{
  "type": "Feature",
  "properties": {
    "iso:country":"IN",
    "ks:ks_name":"Thoggudem",
    "ks:ks_pop":126,
    "ks:ks_type":"HABITATION",
    "name:eng_x_preferred":[
        "Thoggudem"
    ],
    "wof:name":"Thoggudem",
    "wof:placetype":"locality",
    "wof:population":126
},
  "geometry": {"coordinates":[80.875507,17.387396],"type":"Point"}
}