{
  "type": "Feature",
  "properties": {
    "iso:country":"IN",
    "ks:ks_name":"Regulla",
    "ks:ks_pop":292,
    "ks:ks_type":"HABITATION",
    "name:eng_x_preferred":[
        "Regulla"
    ],
    "wof:name":"Regulla",
    "wof:placetype":"locality",
    "wof:population":292
},
  "geometry": {"coordinates":[80.472302,18.048247],"type":"Point"}
}