{
  "type": "Feature",
  "properties": {
    "iso:country":"IN",
    "qs:name":"Okhla Industrial Estate Phase 3",
    "qs:name_adm0":"India",
    "qs:name_adm1":"Delhi",
    "qs:photos":25,
    "qs:photos_1k":5,
    "qs:photos_9k":1,
    "qs:photos_9r":1,
    "qs:photos_all":25,
    "qs:photos_sr":1,
    "qs:placetype":"Suburb",
    "qs:pop_sr":"0",
    "wof:name":"Okhla Industrial Estate Phase 3",
    "wof:placetype":"neighbourhood"
},
  "geometry": {"coordinates":[77.265472,28.550713],"type":"Point"}
}