{
  "type": "Feature",
  "properties": {
    "iso:country":"IN",
    "ks:ks_name":"Usari",
    "ks:ks_pop":2,
    "ks:ks_type":"VILLAGE",
    "name:eng_x_preferred":[
        "Usari"
    ],
    "wof:name":"Usari",
    "wof:placetype":"locality",
    "wof:population":2
},
  "geometry": {"coordinates":[82.723637,26.05181],"type":"Point"}
}