{
  "type": "Feature",
  "properties": {
    "gn:admin1_code":"36.0",
    "gn:admin2_code":"171.0",
    "gn:asciiname":"Nadwaniyan",
    "gn:country_code":"IN",
    "gn:dem":247,
    "gn:feature_class":"P",
    "gn:feature_code":"PPL",
    "gn:name":"Nadwaniy\u0101n",
    "gn:population":0,
    "gn:timezone":"Asia/Kolkata",
    "iso:country":"IN",
    "ks:ks_alt_nam":"Nadwaniy\u0101n",
    "ks:ks_name":"Nadwaniyan",
    "ks:ks_type":"VILLAGE",
    "name:eng_x_preferred":[
        "Nadwaniyan"
    ],
    "name:eng_x_variant":[
        "Nadwaniy\u0101n"
    ],
    "wof:name":"Nadwaniyan",
    "wof:placetype":"locality"
},
  "geometry": {"coordinates":[81.05317700000001,25.031646],"type":"Point"}
}