{
  "type": "Feature",
  "properties": {
    "gn:admin1_code":"35.0",
    "gn:admin2_code":"443",
    "gn:asciiname":"Bilakheri",
    "gn:country_code":"IN",
    "gn:dem":424,
    "gn:feature_class":"P",
    "gn:feature_code":"PPL",
    "gn:name":"Bilakheri",
    "gn:population":0,
    "gn:timezone":"Asia/Kolkata",
    "iso:country":"IN",
    "ks:ks_name":"Bilakhedi",
    "ks:ks_pop":445,
    "ks:ks_type":"VILLAGE",
    "name:eng_x_preferred":[
        "Bilakhedi"
    ],
    "name:eng_x_variant":[
        "Bilakheri"
    ],
    "wof:name":"Bilakhedi",
    "wof:placetype":"locality",
    "wof:population":445
},
  "geometry": {"coordinates":[78.22942399999999,24.028127],"type":"Point"}
}