{
  "type": "Feature",
  "properties": {
    "gn:admin1_code":"11",
    "gn:admin2_code":"24.0",
    "gn:asciiname":"Katoli",
    "gn:country_code":"IN",
    "gn:dem":585,
    "gn:feature_class":"P",
    "gn:feature_code":"PPL",
    "gn:name":"Katoli",
    "gn:population":0,
    "gn:timezone":"Asia/Kolkata",
    "iso:country":"IN",
    "wof:name":"Katoli",
    "wof:placetype":"locality"
},
  "geometry": {"coordinates":[76.28283,31.75959000000001],"type":"Point"}
}