{
  "type": "Feature",
  "properties": {
    "iso:country":"IN",
    "ks:ks_name":"Chinnaipally",
    "ks:ks_pop":748,
    "ks:ks_type":"HABITATION",
    "name:eng_x_preferred":[
        "Chinnaipally"
    ],
    "wof:name":"Chinnaipally",
    "wof:placetype":"locality",
    "wof:population":748
},
  "geometry": {"coordinates":[77.58404899999999,16.02146],"type":"Point"}
}