{
  "type": "Feature",
  "properties": {
    "gn:admin1_code":"36.0",
    "gn:admin2_code":"132.0",
    "gn:asciiname":"Kundi",
    "gn:country_code":"IN",
    "gn:dem":267,
    "gn:feature_class":"P",
    "gn:feature_code":"PPL",
    "gn:name":"Kundi",
    "gn:population":0,
    "gn:timezone":"Asia/Kolkata",
    "iso:country":"IN",
    "name:ceb_x_preferred":[
        "Kundi"
    ],
    "name:swe_x_preferred":[
        "Kundi"
    ],
    "wof:name":"Kundi",
    "wof:placetype":"locality"
},
  "geometry": {"coordinates":[77.35519000000002,29.99894],"type":"Point"}
}