{
  "type": "Feature",
  "properties": {
    "iso:country":"IN",
    "ks:ks_name":"Kabir Chack",
    "ks:ks_pop":2142,
    "ks:ks_type":"VILLAGE",
    "ks:ks_uagg_main":0,
    "name:eng_x_preferred":[
        "Kabir Chack"
    ],
    "wof:name":"Kabir Chack",
    "wof:placetype":"neighbourhood",
    "wof:population":2142
},
  "geometry": {"coordinates":[85.913904,26.149811],"type":"Point"}
}