{
  "type": "Feature",
  "properties": {
    "gn:admin1_code":"34",
    "gn:admin2_code":"233.0",
    "gn:asciiname":"Deua",
    "gn:country_code":"IN",
    "gn:dem":104,
    "gn:feature_class":"P",
    "gn:feature_code":"PPL",
    "gn:name":"Deua",
    "gn:population":0,
    "gn:timezone":"Asia/Kolkata",
    "iso:country":"IN",
    "name:ceb_x_preferred":[
        "Deua imbutana"
    ],
    "name:nld_x_preferred":[
        "Deua imbutana"
    ],
    "name:swe_x_preferred":[
        "Deua imbutana"
    ],
    "name:vie_x_preferred":[
        "Deua imbutana"
    ],
    "name:war_x_preferred":[
        "Deua imbutana"
    ],
    "wof:name":"Deua",
    "wof:placetype":"locality"
},
  "geometry": {"coordinates":[83.55965999999999,24.93356],"type":"Point"}
}