{
  "type": "Feature",
  "properties": {
    "iso:country":"IN",
    "ks:ks_name":"Lakhiya",
    "ks:ks_pop":901,
    "ks:ks_type":"VILLAGE",
    "name:eng_x_preferred":[
        "Lakhiya"
    ],
    "wof:name":"Lakhiya",
    "wof:placetype":"locality",
    "wof:population":901
},
  "geometry": {"coordinates":[74.967484,23.264763],"type":"Point"}
}