{
  "type": "Feature",
  "properties": {
    "gn:admin1_code":"39.0",
    "gn:admin2_code":"63.0",
    "gn:asciiname":"Ason",
    "gn:country_code":"IN",
    "gn:dem":1048,
    "gn:feature_class":"P",
    "gn:feature_code":"PPL",
    "gn:name":"Ason",
    "gn:population":0,
    "gn:timezone":"Asia/Kolkata",
    "iso:country":"IN",
    "name:fra_x_preferred":[
        "Ason"
    ],
    "name:ukr_x_preferred":[
        "\u0410\u0441\u043e\u043d"
    ],
    "wof:name":"Ason",
    "wof:placetype":"locality"
},
  "geometry": {"coordinates":[79.88969,29.93323],"type":"Point"}
}