{
  "type": "Feature",
  "properties": {
    "gn:admin1_code":"34.0",
    "gn:admin2_code":"220.0",
    "gn:asciiname":"Shambhupur",
    "gn:country_code":"IN",
    "gn:dem":54,
    "gn:feature_class":"P",
    "gn:feature_code":"PPL",
    "gn:name":"Shambhupur",
    "gn:population":0,
    "gn:timezone":"Asia/Kolkata",
    "iso:country":"IN",
    "ks:ks_name":"Shembhupur",
    "ks:ks_pop":437,
    "ks:ks_type":"VILLAGE",
    "name:eng_x_preferred":[
        "Shembhupur"
    ],
    "name:eng_x_variant":[
        "Shambhupur"
    ],
    "wof:name":"Shembhupur",
    "wof:placetype":"locality",
    "wof:population":437
},
  "geometry": {"coordinates":[85.276,25.767],"type":"Point"}
}