{
  "type": "Feature",
  "properties": {
    "iso:country":"IN",
    "ks:ks_alt_nam":"Kanchiwalla FV",
    "ks:ks_name":"Kanchiwalla Fv",
    "ks:ks_pop":637,
    "ks:ks_type":"HABITATION",
    "name:eng_x_preferred":[
        "Kanchiwalla Fv"
    ],
    "wof:name":"Kanchiwalla Fv",
    "wof:placetype":"locality",
    "wof:population":637
},
  "geometry": {"coordinates":[92.500733,24.241034],"type":"Point"}
}