{
  "type": "Feature",
  "properties": {
    "gn:admin1_code":"39.0",
    "gn:admin2_code":"60.0",
    "gn:asciiname":"Khatari",
    "gn:country_code":"IN",
    "gn:dem":1500,
    "gn:feature_class":"P",
    "gn:feature_code":"PPL",
    "gn:name":"Khat\u0101ri",
    "gn:population":0,
    "gn:timezone":"Asia/Kolkata",
    "iso:country":"IN",
    "ks:ks_name":"Khatar",
    "ks:ks_pop":232,
    "ks:ks_type":"HABITATION",
    "name:eng_x_preferred":[
        "Khatar"
    ],
    "name:eng_x_variant":[
        "Khatari"
    ],
    "wof:name":"Khatar",
    "wof:placetype":"locality",
    "wof:population":232
},
  "geometry": {"coordinates":[77.87959600000001,30.568573],"type":"Point"}
}