{
  "type": "Feature",
  "properties": {
    "iso:country":"IN",
    "name:ast_x_preferred":[
        "Mattanur"
    ],
    "name:ben_x_preferred":[
        "\u09ae\u09a4\u09cd\u09a4\u09be\u09a8\u09cd\u09a8\u09c1\u09b0"
    ],
    "name:ben_x_variant":[
        "\u09ae\u099f\u09cd\u099f\u09a8\u09c2\u09b0"
    ],
    "name:bpy_x_preferred":[
        "\u09ae\u09a4\u09cd\u09a4\u09be\u09a8\u09cd\u09a8\u09c1\u09b0"
    ],
    "name:ceb_x_preferred":[
        "Mattan\u016br"
    ],
    "name:eng_x_preferred":[
        "Mattanur"
    ],
    "name:fas_x_preferred":[
        "\u0645\u062a\u0627\u0646\u0648\u0631"
    ],
    "name:fra_x_preferred":[
        "Mattanur"
    ],
    "name:ita_x_preferred":[
        "Mattannur"
    ],
    "name:jpn_x_preferred":[
        "\u30de\u30bf\u30cc\u30fc\u30eb"
    ],
    "name:mal_x_preferred":[
        "\u0d2e\u0d1f\u0d4d\u0d1f\u0d28\u0d4d\u0d28\u0d42\u0d7c"
    ],
    "name:msa_x_preferred":[
        "Mattannur"
    ],
    "name:new_x_preferred":[
        "\u092e\u091f\u094d\u091f\u0928\u094d\u0928\u0941\u0930"
    ],
    "name:nld_x_preferred":[
        "Mattanur"
    ],
    "name:ori_x_preferred":[
        "\u0b2e\u0b3e\u0b24\u0b4d\u0b24\u0b3e\u0b28\u0b4d\u0b28\u0b41\u0b30\u0b4d"
    ],
    "name:spa_x_preferred":[
        "Mattanur"
    ],
    "name:swe_x_preferred":[
        "Mattan\u016br"
    ],
    "name:tam_x_preferred":[
        "\u0bae\u0b9f\u0bcd\u0b9f\u0ba9\u0bc2\u0bb0\u0bcd"
    ],
    "name:urd_x_preferred":[
        "\u0645\u0627\u0679\u0627\u0646\u0648\u0631"
    ],
    "name:vie_x_preferred":[
        "Mattannur"
    ],
    "name:zho_x_preferred":[
        "\u9a6c\u5766\u52aa\u5c14"
    ],
    "qs:name":"Mattannur",
    "qs:name_adm0":"India",
    "qs:name_adm1":"Kerala",
    "qs:photos":90,
    "qs:photos_1k":18,
    "qs:photos_9k":1,
    "qs:photos_9r":3,
    "qs:photos_all":90,
    "qs:photos_sr":3,
    "qs:placetype":"Town",
    "qs:pop_sr":"0",
    "wd:wordcount":1413,
    "wof:name":"Mattannur",
    "wof:placetype":"locality"
},
  "geometry": {"coordinates":[75.56619600000001,11.908925],"type":"Point"}
}