{
  "type": "Feature",
  "properties": {
    "iso:country":"IN",
    "ks:ks_name":"Yadamane",
    "ks:ks_pop":23,
    "ks:ks_type":"HABITATION",
    "name:eng_x_preferred":[
        "Yadamane"
    ],
    "wof:name":"Yadamane",
    "wof:placetype":"locality",
    "wof:population":23
},
  "geometry": {"coordinates":[74.683483,13.992286],"type":"Point"}
}