{
  "type": "Feature",
  "properties": {
    "iso:country":"IN",
    "ks:ks_name":"Hehal",
    "ks:ks_type":"VILLAGE",
    "ks:ks_uagg_main":0,
    "name:eng_x_preferred":[
        "Hehal"
    ],
    "wof:name":"Hehal",
    "wof:placetype":"neighbourhood"
},
  "geometry": {"coordinates":[85.28566499999999,23.369504],"type":"Point"}
}