{
  "type": "Feature",
  "properties": {
    "iso:country":"IN",
    "ks:ks_name":"Bhauwapura",
    "ks:ks_pop":1005,
    "ks:ks_type":"VILLAGE",
    "name:eng_x_preferred":[
        "Bhauwapura"
    ],
    "wof:name":"Bhauwapura",
    "wof:placetype":"locality",
    "wof:population":1005
},
  "geometry": {"coordinates":[77.188688,26.548358],"type":"Point"}
}