{
  "type": "Feature",
  "properties": {
    "gn:admin1_code":"36.0",
    "gn:admin2_code":"150.0",
    "gn:asciiname":"Jiginian Patti Tisua",
    "gn:country_code":"IN",
    "gn:dem":162,
    "gn:feature_class":"P",
    "gn:feature_code":"PPL",
    "gn:name":"Jigini\u0101n Patti Tisua",
    "gn:population":0,
    "gn:timezone":"Asia/Kolkata",
    "iso:country":"IN",
    "wof:name":"Jiginian Patti Tisua",
    "wof:placetype":"locality"
},
  "geometry": {"coordinates":[79.58776999999998,28.12697],"type":"Point"}
}