{
  "type": "Feature",
  "properties": {
    "iso:country":"IN",
    "ks:ks_name":"Bandhershol",
    "ks:ks_pop":363,
    "ks:ks_type":"VILLAGE",
    "ks:ks_uagg_main":0,
    "name:eng_x_preferred":[
        "Bandhershol"
    ],
    "wof:name":"Bandhershol",
    "wof:placetype":"neighbourhood",
    "wof:population":363
},
  "geometry": {"coordinates":[87.411101,23.815731],"type":"Point"}
}