{
  "type": "Feature",
  "properties": {
    "gn:admin1_code":"36.0",
    "gn:admin2_code":"175.0",
    "gn:asciiname":"Pura Chandrabhansingh",
    "gn:country_code":"IN",
    "gn:dem":96,
    "gn:feature_class":"P",
    "gn:feature_code":"PPL",
    "gn:name":"Pura Chandrabh\u0101nsingh",
    "gn:population":0,
    "gn:timezone":"Asia/Kolkata",
    "iso:country":"IN",
    "wof:name":"Pura Chandrabhansingh",
    "wof:placetype":"locality"
},
  "geometry": {"coordinates":[81.88134000000002,25.29287],"type":"Point"}
}