{
  "type": "Feature",
  "properties": {
    "gn:admin1_code":"19.0",
    "gn:admin2_code":"567.0",
    "gn:asciiname":"Dasarahatti",
    "gn:country_code":"IN",
    "gn:dem":609,
    "gn:feature_class":"P",
    "gn:feature_code":"PPL",
    "gn:name":"D\u0101sarahatti",
    "gn:population":0,
    "gn:timezone":"Asia/Kolkata",
    "iso:country":"IN",
    "wof:name":"Dasarahatti",
    "wof:placetype":"locality"
},
  "geometry": {"coordinates":[75.59933000000002,14.11777],"type":"Point"}
}