{
  "type": "Feature",
  "properties": {
    "iso:country":"IN",
    "ks:ks_name":"Kulkunda Forest Qurters",
    "ks:ks_pop":162,
    "ks:ks_type":"HABITATION",
    "name:eng_x_preferred":[
        "Kulkunda Forest Qurters"
    ],
    "wof:name":"Kulkunda Forest Qurters",
    "wof:placetype":"locality",
    "wof:population":162
},
  "geometry": {"coordinates":[75.606526,12.686737],"type":"Point"}
}