{
  "type": "Feature",
  "properties": {
    "gn:admin1_code":"25.0",
    "gn:admin2_code":"630.0",
    "gn:asciiname":"Doranabettam",
    "gn:country_code":"IN",
    "gn:dem":607,
    "gn:feature_class":"P",
    "gn:feature_code":"PPL",
    "gn:name":"Doranabettam",
    "gn:population":0,
    "gn:timezone":"Asia/Kolkata",
    "iso:country":"IN",
    "wof:name":"Doranabettam",
    "wof:placetype":"neighbourhood"
},
  "geometry": {"coordinates":[78.01203,12.42201],"type":"Point"}
}