{
  "type": "Feature",
  "properties": {
    "iso:country":"IN",
    "ks:ks_name":"Bansberwa",
    "ks:ks_pop":280,
    "ks:ks_type":"VILLAGE",
    "name:eng_x_preferred":[
        "Bansberwa"
    ],
    "wof:name":"Bansberwa",
    "wof:placetype":"locality",
    "wof:population":280
},
  "geometry": {"coordinates":[87.28810199999999,24.403284],"type":"Point"}
}