{
  "type": "Feature",
  "properties": {
    "gn:admin1_code":"34.0",
    "gn:admin2_code":"220.0",
    "gn:asciiname":"Maraidih",
    "gn:country_code":"IN",
    "gn:dem":54,
    "gn:feature_class":"P",
    "gn:feature_code":"PPL",
    "gn:name":"Maraidih",
    "gn:population":0,
    "gn:timezone":"Asia/Kolkata",
    "iso:country":"IN",
    "ks:ks_name":"Maraidih",
    "ks:ks_type":"VILLAGE",
    "name:eng_x_preferred":[
        "Maraidih"
    ],
    "wof:name":"Maraidih",
    "wof:placetype":"locality"
},
  "geometry": {"coordinates":[85.503129,25.832083],"type":"Point"}
}