{
  "type": "Feature",
  "properties": {
    "iso:country":"IN",
    "ks:ks_name":"Beeja",
    "ks:ks_pop":153,
    "ks:ks_type":"HABITATION",
    "name:eng_x_preferred":[
        "Beeja"
    ],
    "wof:name":"Beeja",
    "wof:placetype":"locality",
    "wof:population":153
},
  "geometry": {"coordinates":[79.774359,23.280633],"type":"Point"}
}