{
  "type": "Feature",
  "properties": {
    "iso:country":"IN",
    "ks:ks_name":"Puki",
    "ks:ks_pop":1183,
    "ks:ks_type":"VILLAGE",
    "name:eng_x_preferred":[
        "Puki"
    ],
    "wof:name":"Puki",
    "wof:placetype":"locality",
    "wof:population":1183
},
  "geometry": {"coordinates":[82.581503,18.763562],"type":"Point"}
}