{
  "type": "Feature",
  "properties": {
    "gn:admin1_code":"36.0",
    "gn:admin2_code":"141.0",
    "gn:asciiname":"Yaqutpur",
    "gn:country_code":"IN",
    "gn:dem":197,
    "gn:feature_class":"P",
    "gn:feature_code":"PPL",
    "gn:name":"Y\u0101q\u016btpur",
    "gn:population":0,
    "gn:timezone":"Asia/Kolkata",
    "iso:country":"IN",
    "wof:name":"Yaqutpur",
    "wof:placetype":"locality"
},
  "geometry": {"coordinates":[77.42358,28.47134],"type":"Point"}
}