{
  "type": "Feature",
  "properties": {
    "gn:admin1_code":"25.0",
    "gn:admin2_code":"608.0",
    "gn:asciiname":"Irugalur Mettuppalaiyam",
    "gn:country_code":"IN",
    "gn:dem":264,
    "gn:feature_class":"P",
    "gn:feature_code":"PPL",
    "gn:name":"Irug\u0101l\u016br Mettupp\u0101laiyam",
    "gn:population":0,
    "gn:timezone":"Asia/Kolkata",
    "iso:country":"IN",
    "wof:name":"Irugalur Mettuppalaiyam",
    "wof:placetype":"locality"
},
  "geometry": {"coordinates":[77.961,11.50419],"type":"Point"}
}