{
  "type": "Feature",
  "properties": {
    "iso:country":"IN",
    "ks:ks_name":"7 RP-B",
    "ks:ks_pop":14,
    "ks:ks_type":"VILLAGE",
    "name:eng_x_preferred":[
        "7 RP-B"
    ],
    "wof:name":"7 RP-B",
    "wof:placetype":"locality",
    "wof:population":14
},
  "geometry": {"coordinates":[74.411197,29.383994],"type":"Point"}
}