{
  "type": "Feature",
  "properties": {
    "iso:country":"IN",
    "ks:ks_name":"Bharthapur",
    "ks:ks_pop":76,
    "ks:ks_type":"HABITATION",
    "name:eng_x_preferred":[
        "Bharthapur"
    ],
    "wof:name":"Bharthapur",
    "wof:placetype":"locality",
    "wof:population":76
},
  "geometry": {"coordinates":[83.080674,27.439462],"type":"Point"}
}