{
  "type": "Feature",
  "properties": {
    "gn:admin1_code":"25.0",
    "gn:admin2_code":"633.0",
    "gn:asciiname":"Puraviyakkavundanvalasu",
    "gn:country_code":"IN",
    "gn:dem":259,
    "gn:feature_class":"P",
    "gn:feature_code":"PPL",
    "gn:name":"Puraviyakkavundanvalasu",
    "gn:population":0,
    "gn:timezone":"Asia/Kolkata",
    "iso:country":"IN",
    "wof:name":"Puraviyakkavundanvalasu",
    "wof:placetype":"locality"
},
  "geometry": {"coordinates":[77.61535000000001,11.06484],"type":"Point"}
}