{
  "type": "Feature",
  "properties": {
    "iso:country":"IN",
    "ks:ks_name":"Muthri",
    "ks:ks_pop":15,
    "ks:ks_type":"HABITATION",
    "name:eng_x_preferred":[
        "Muthri"
    ],
    "wof:name":"Muthri",
    "wof:placetype":"locality",
    "wof:population":15
},
  "geometry": {"coordinates":[74.763626,14.012051],"type":"Point"}
}