{
  "type": "Feature",
  "properties": {
    "gn:admin1_code":"2.0",
    "gn:admin2_code":"542.0",
    "gn:asciiname":"Lodasingi",
    "gn:country_code":"IN",
    "gn:dem":672,
    "gn:feature_class":"P",
    "gn:feature_code":"PPL",
    "gn:name":"Lodasingi",
    "gn:population":0,
    "gn:timezone":"Asia/Kolkata",
    "iso:country":"IN",
    "wof:name":"Lodasingi",
    "wof:placetype":"locality"
},
  "geometry": {"coordinates":[83.78353,18.73697],"type":"Point"}
}