{
  "type": "Feature",
  "properties": {
    "iso:country":"IN",
    "ks:ks_alt_nam":"Bikha ka pura",
    "ks:ks_name":"Bikha Ka Pura",
    "ks:ks_pop":450,
    "ks:ks_type":"HABITATION",
    "name:eng_x_preferred":[
        "Bikha Ka Pura"
    ],
    "wof:name":"Bikha Ka Pura",
    "wof:placetype":"locality",
    "wof:population":450
},
  "geometry": {"coordinates":[81.930053,25.573156],"type":"Point"}
}