{
  "type": "Feature",
  "properties": {
    "gn:admin1_code":"35.0",
    "gn:admin2_code":"424.0",
    "gn:asciiname":"Suda",
    "gn:country_code":"IN",
    "gn:dem":319,
    "gn:feature_class":"P",
    "gn:feature_code":"PPL",
    "gn:name":"S\u016bda",
    "gn:population":0,
    "gn:timezone":"Asia/Kolkata",
    "iso:country":"IN",
    "name:ara_x_preferred":[
        "\u0633\u0648\u062f\u0627"
    ],
    "name:bre_x_preferred":[
        "Souda"
    ],
    "name:bul_x_preferred":[
        "\u0421\u0432\u0438\u0434\u0430\u0441"
    ],
    "name:cat_x_preferred":[
        "Su\u00efda"
    ],
    "name:ces_x_preferred":[
        "Suda"
    ],
    "name:dan_x_preferred":[
        "Suda"
    ],
    "name:deu_x_preferred":[
        "Suda"
    ],
    "name:ell_x_preferred":[
        "\u03a3\u03bf\u03cd\u03b4\u03b1"
    ],
    "name:epo_x_preferred":[
        "Suido"
    ],
    "name:eus_x_preferred":[
        "Suda"
    ],
    "name:fas_x_preferred":[
        "\u0633\u0648\u062f\u0627"
    ],
    "name:fin_x_preferred":[
        "Suda"
    ],
    "name:fra_x_preferred":[
        "Souda"
    ],
    "name:glg_x_preferred":[
        "Su\u00eddas"
    ],
    "name:heb_x_preferred":[
        "\u05e1\u05d5\u05d3\u05d0"
    ],
    "name:hun_x_preferred":[
        "Szuda-lexikon"
    ],
    "name:hye_x_preferred":[
        "\u054d\u0578\u0582\u0564\u0561"
    ],
    "name:ind_x_preferred":[
        "Suda"
    ],
    "name:ita_x_preferred":[
        "Suda"
    ],
    "name:jpn_x_preferred":[
        "\u30b9\u30fc\u30c0\u8f9e\u5178"
    ],
    "name:kat_x_preferred":[
        "\u10e1\u10d5\u10d8\u10d3\u10d0"
    ],
    "name:lat_x_preferred":[
        "Suda"
    ],
    "name:new_x_preferred":[
        "\u0938\u0941\u0926\u093e"
    ],
    "name:nld_x_preferred":[
        "Suda"
    ],
    "name:nor_x_preferred":[
        "Suda"
    ],
    "name:pol_x_preferred":[
        "Suda"
    ],
    "name:pol_x_variant":[
        "Ksi\u0119ga Suda"
    ],
    "name:por_x_preferred":[
        "Suda"
    ],
    "name:ron_x_preferred":[
        "Suda"
    ],
    "name:rus_x_preferred":[
        "\u0421\u0443\u0434\u0430"
    ],
    "name:slk_x_preferred":[
        "Suda"
    ],
    "name:spa_x_preferred":[
        "Suda"
    ],
    "name:swe_x_preferred":[
        "Suda"
    ],
    "name:tur_x_preferred":[
        "Suda"
    ],
    "name:ukr_x_preferred":[
        "\u0421\u0443\u0434\u0430"
    ],
    "name:urd_x_preferred":[
        "\u0633\u0648\u062f\u0627"
    ],
    "name:vie_x_preferred":[
        "S\u00f4ng Suda"
    ],
    "name:vls_x_preferred":[
        "Souda"
    ],
    "name:zho_x_preferred":[
        "\u82cf\u8fbe\u8f9e\u4e66"
    ],
    "wof:name":"Suda",
    "wof:placetype":"neighbourhood"
},
  "geometry": {"coordinates":[79.04987,24.65094],"type":"Point"}
}