{
  "type": "Feature",
  "properties": {
    "iso:country":"IN",
    "ks:ks_name":"Mahadoganj",
    "ks:ks_pop":20,
    "ks:ks_type":"HABITATION",
    "name:eng_x_preferred":[
        "Mahadoganj"
    ],
    "wof:name":"Mahadoganj",
    "wof:placetype":"locality",
    "wof:population":20
},
  "geometry": {"coordinates":[84.178399,25.376081],"type":"Point"}
}