{
  "type": "Feature",
  "properties": {
    "iso:country":"IN",
    "ks:ks_alt_nam":"R\u0101mj\u012bwanpur",
    "ks:ks_name":"Ramjiwanpur",
    "ks:ks_type":"VILLAGE",
    "name:eng_x_preferred":[
        "Ramjiwanpur"
    ],
    "name:eng_x_variant":[
        "R\u0101mj\u012bwanpur"
    ],
    "wof:name":"Ramjiwanpur",
    "wof:placetype":"locality"
},
  "geometry": {"coordinates":[79.005087,29.311424],"type":"Point"}
}