{
  "type": "Feature",
  "properties": {
    "iso:country":"IN",
    "ks:ks_alt_nam":"NAGLA KERATPUR",
    "ks:ks_name":"Nagla Keratpur",
    "ks:ks_pop":495,
    "ks:ks_type":"HABITATION",
    "name:eng_x_preferred":[
        "Nagla Keratpur"
    ],
    "wof:name":"Nagla Keratpur",
    "wof:placetype":"locality",
    "wof:population":495
},
  "geometry": {"coordinates":[78.81858200000001,26.855186],"type":"Point"}
}