{
  "type": "Feature",
  "properties": {
    "gn:admin1_code":"36",
    "gn:admin2_code":"153.0",
    "gn:asciiname":"Dhauns",
    "gn:country_code":"IN",
    "gn:dem":131,
    "gn:feature_class":"P",
    "gn:feature_code":"PPL",
    "gn:name":"Dhauns",
    "gn:population":0,
    "gn:timezone":"Asia/Kolkata",
    "iso:country":"IN",
    "wof:name":"Dhauns",
    "wof:placetype":"locality"
},
  "geometry": {"coordinates":[81.13150999999998,27.99832],"type":"Point"}
}