{
  "type": "Feature",
  "properties": {
    "gn:admin1_code":"10.0",
    "gn:admin2_code":"072",
    "gn:asciiname":"Haldaheri",
    "gn:country_code":"IN",
    "gn:dem":263,
    "gn:feature_class":"P",
    "gn:feature_code":"PPL",
    "gn:name":"Hald\u0101heri",
    "gn:population":0,
    "gn:timezone":"Asia/Kolkata",
    "iso:country":"IN",
    "wof:name":"Haldaheri",
    "wof:placetype":"locality"
},
  "geometry": {"coordinates":[76.82614000000002,30.22454],"type":"Point"}
}