{
  "type": "Feature",
  "properties": {
    "gn:admin1_code":"34.0",
    "gn:admin2_code":"229.0",
    "gn:asciiname":"Bangaria",
    "gn:country_code":"IN",
    "gn:dem":51,
    "gn:feature_class":"P",
    "gn:feature_code":"PPL",
    "gn:name":"Bangaria",
    "gn:population":0,
    "gn:timezone":"Asia/Kolkata",
    "iso:country":"IN",
    "wof:name":"Bangaria",
    "wof:placetype":"locality"
},
  "geometry": {"coordinates":[85.51711999999998,25.32216],"type":"Point"}
}