{
  "type": "Feature",
  "properties": {
    "gn:admin1_code":"25.0",
    "gn:admin2_code":"606.0",
    "gn:asciiname":"Tittanus",
    "gn:country_code":"IN",
    "gn:dem":732,
    "gn:feature_class":"P",
    "gn:feature_code":"PPL",
    "gn:name":"Tittan\u016bs",
    "gn:population":0,
    "gn:timezone":"Asia/Kolkata",
    "iso:country":"IN",
    "wof:name":"Tittanus",
    "wof:placetype":"locality"
},
  "geometry": {"coordinates":[78.93454,12.6243],"type":"Point"}
}