{
  "type": "Feature",
  "properties": {
    "gn:admin1_code":"36.0",
    "gn:admin2_code":"156.0",
    "gn:asciiname":"Tikri Ganesh",
    "gn:country_code":"IN",
    "gn:dem":117,
    "gn:feature_class":"P",
    "gn:feature_code":"PPL",
    "gn:name":"Tikri Ganesh",
    "gn:population":0,
    "gn:timezone":"Asia/Kolkata",
    "iso:country":"IN",
    "wof:name":"Tikri Ganesh",
    "wof:placetype":"locality"
},
  "geometry": {"coordinates":[80.47507,26.43147],"type":"Point"}
}