{
  "type": "Feature",
  "properties": {
    "iso:country":"IN",
    "ks:ks_name":"Bhains Gaon",
    "ks:ks_pop":245,
    "ks:ks_type":"VILLAGE",
    "name:eng_x_preferred":[
        "Bhains Gaon"
    ],
    "wof:name":"Bhains Gaon",
    "wof:placetype":"locality",
    "wof:population":245
},
  "geometry": {"coordinates":[78.976935,30.32083],"type":"Point"}
}