{
  "type": "Feature",
  "properties": {
    "iso:country":"IN",
    "ks:ks_name":"Rangtikra",
    "ks:ks_pop":307,
    "ks:ks_type":"HABITATION",
    "name:eng_x_preferred":[
        "Rangtikra"
    ],
    "wof:name":"Rangtikra",
    "wof:placetype":"locality",
    "wof:population":307
},
  "geometry": {"coordinates":[83.565628,21.227595],"type":"Point"}
}