{
  "type": "Feature",
  "properties": {
    "iso:country":"IN",
    "ks:ks_name":"Kotha",
    "ks:ks_type":"VILLAGE",
    "name:eng_x_preferred":[
        "Kotha"
    ],
    "wof:name":"Kotha",
    "wof:placetype":"locality"
},
  "geometry": {"coordinates":[83.144121,26.859953],"type":"Point"}
}