{
  "type": "Feature",
  "properties": {
    "iso:country":"IN",
    "ks:ks_name":"Chandradeipur",
    "ks:ks_pop":3027,
    "ks:ks_type":"VILLAGE",
    "ks:ks_uagg_main":0,
    "name:eng_x_preferred":[
        "Chandradeipur"
    ],
    "wof:name":"Chandradeipur",
    "wof:placetype":"neighbourhood",
    "wof:population":3027
},
  "geometry": {"coordinates":[86.110821,20.488441],"type":"Point"}
}