{
  "type": "Feature",
  "properties": {
    "iso:country":"IN",
    "ks:ks_name":"Kabadwadi",
    "ks:ks_pop":498,
    "ks:ks_type":"HABITATION",
    "name:eng_x_preferred":[
        "Kabadwadi"
    ],
    "wof:name":"Kabadwadi",
    "wof:placetype":"locality",
    "wof:population":498
},
  "geometry": {"coordinates":[73.86556,19.214186],"type":"Point"}
}