{
  "type": "Feature",
  "properties": {
    "iso:country":"IN",
    "ks:ks_alt_nam":"VELLARA",
    "ks:ks_name":"Vellara",
    "ks:ks_pop":1440,
    "ks:ks_type":"HABITATION",
    "name:eng_x_preferred":[
        "Vellara"
    ],
    "wof:name":"Vellara",
    "wof:placetype":"locality",
    "wof:population":1440
},
  "geometry": {"coordinates":[76.51559399999999,10.837994],"type":"Point"}
}