{
  "type": "Feature",
  "properties": {
    "gn:admin1_code":"28.0",
    "gn:admin2_code":"330",
    "gn:asciiname":"Kanki",
    "gn:country_code":"IN",
    "gn:dem":45,
    "gn:feature_class":"P",
    "gn:feature_code":"PPL",
    "gn:name":"K\u0101nki",
    "gn:population":0,
    "gn:timezone":"Asia/Kolkata",
    "iso:country":"IN",
    "ks:ks_alt_nam":"K\u0101nki",
    "ks:ks_name":"Kanki",
    "ks:ks_pop":1204,
    "ks:ks_type":"URBAN",
    "name:ceb_x_preferred":[
        "Kanki"
    ],
    "name:eng_x_preferred":[
        "Kanki"
    ],
    "name:eng_x_variant":[
        "K\u0101nki"
    ],
    "name:swe_x_preferred":[
        "Kanki"
    ],
    "name:und_x_variant":[
        "K\u0101nki"
    ],
    "wof:name":"Kanki",
    "wof:placetype":"locality",
    "wof:population":1204
},
  "geometry": {"coordinates":[87.87046100000001,26.018342],"type":"Point"}
}