{
  "type": "Feature",
  "properties": {
    "gn:admin1_code":"28.0",
    "gn:admin2_code":"330",
    "gn:asciiname":"Kanki",
    "gn:country_code":"IN",
    "gn:dem":45,
    "gn:feature_class":"P",
    "gn:feature_code":"PPL",
    "gn:name":"K\u0101nki",
    "gn:population":0,
    "gn:timezone":"Asia/Kolkata",
    "iso:country":"IN",
    "name:und_x_variant":[
        "K\u0101nki"
    ],
    "wof:name":"Kanki",
    "wof:placetype":"locality"
},
  "geometry": {"coordinates":[87.87045999999999,26.01834],"type":"Point"}
}