{
  "type": "Feature",
  "properties": {
    "iso:country":"IN",
    "ks:ks_name":"Den Terang Gaon",
    "ks:ks_pop":221,
    "ks:ks_type":"HABITATION",
    "ks:ks_uagg_main":0,
    "name:eng_x_preferred":[
        "Den Terang Gaon"
    ],
    "wof:name":"Den Terang Gaon",
    "wof:placetype":"neighbourhood",
    "wof:population":221
},
  "geometry": {"coordinates":[92.994359,26.228244],"type":"Point"}
}