{
  "type": "Feature",
  "properties": {
    "iso:country":"IN",
    "ks:ks_name":"Sadatpura",
    "ks:ks_pop":1592,
    "ks:ks_type":"VILLAGE",
    "ks:ks_uagg_main":0,
    "name:eng_x_preferred":[
        "Sadatpura"
    ],
    "wof:name":"Sadatpura",
    "wof:placetype":"locality",
    "wof:population":1592
},
  "geometry": {"coordinates":[72.994361,23.823667],"type":"Point"}
}