{
  "type": "Feature",
  "properties": {
    "iso:country":"IN",
    "ks:ks_name":"Mamar",
    "ks:ks_pop":108,
    "ks:ks_type":"VILLAGE",
    "name:eng_x_preferred":[
        "Mamar"
    ],
    "wof:name":"Mamar",
    "wof:placetype":"locality",
    "wof:population":108
},
  "geometry": {"coordinates":[85.32104,22.318074],"type":"Point"}
}