{
  "type": "Feature",
  "properties": {
    "gn:admin1_code":"28",
    "gn:admin2_code":"333.0",
    "gn:asciiname":"Sagardighi",
    "gn:country_code":"IN",
    "gn:dem":37,
    "gn:feature_class":"P",
    "gn:feature_code":"PPL",
    "gn:name":"S\u0101gard\u012bghi",
    "gn:population":0,
    "gn:timezone":"Asia/Kolkata",
    "iso:country":"IN",
    "ks:ks_name":"Sagardighi",
    "ks:ks_pop":1679,
    "ks:ks_type":"VILLAGE",
    "ks:ks_uagg_main":0,
    "name:eng_x_preferred":[
        "Sagardighi"
    ],
    "wof:name":"Sagardighi",
    "wof:placetype":"neighbourhood",
    "wof:population":1679
},
  "geometry": {"coordinates":[88.085261,24.291741],"type":"Point"}
}