{
  "type": "Feature",
  "properties": {
    "gn:admin1_code":"36",
    "gn:admin2_code":"191.0",
    "gn:asciiname":"Aho Patti",
    "gn:country_code":"IN",
    "gn:dem":82,
    "gn:feature_class":"P",
    "gn:feature_code":"PPL",
    "gn:name":"\u0100ho Patti",
    "gn:population":0,
    "gn:timezone":"Asia/Kolkata",
    "iso:country":"IN",
    "ks:ks_alt_nam":"\u0100ho Patti",
    "ks:ks_name":"Aho Patti",
    "ks:ks_type":"VILLAGE",
    "ks:ks_uagg_main":0,
    "name:eng_x_preferred":[
        "Aho Patti"
    ],
    "name:eng_x_variant":[
        "\u0100ho Patti"
    ],
    "wof:name":"Aho Patti",
    "wof:placetype":"locality"
},
  "geometry": {"coordinates":[83.21049600000001,26.08272],"type":"Point"}
}