{
  "type": "Feature",
  "properties": {
    "gn:admin1_code":"40.0",
    "gn:admin2_code":"538.0",
    "gn:asciiname":"Kottapalli",
    "gn:country_code":"IN",
    "gn:dem":332,
    "gn:feature_class":"P",
    "gn:feature_code":"PPL",
    "gn:name":"Kottapalli",
    "gn:population":0,
    "gn:timezone":"Asia/Kolkata",
    "iso:country":"IN",
    "ks:ks_name":"Kothapally",
    "ks:ks_pop":1518,
    "ks:ks_type":"HABITATION",
    "name:eng_x_preferred":[
        "Kothapally"
    ],
    "name:eng_x_variant":[
        "Kottapalli"
    ],
    "wof:name":"Kothapally",
    "wof:placetype":"locality",
    "wof:population":1518
},
  "geometry": {"coordinates":[77.543621,15.957556],"type":"Point"}
}