{
  "type": "Feature",
  "properties": {
    "iso:country":"IN",
    "ks:ks_name":"Harrabhat Koko",
    "ks:ks_pop":1033,
    "ks:ks_type":"HABITATION",
    "name:eng_x_preferred":[
        "Harrabhat Koko"
    ],
    "wof:name":"Harrabhat Koko",
    "wof:placetype":"locality",
    "wof:population":1033
},
  "geometry": {"coordinates":[80.75392100000001,22.472231],"type":"Point"}
}