{
  "type": "Feature",
  "properties": {
    "iso:country":"IN",
    "ks:ks_alt_nam":"GARING PARA",
    "ks:ks_name":"Garing Para",
    "ks:ks_pop":184,
    "ks:ks_type":"HABITATION",
    "ks:ks_uagg_main":0,
    "name:eng_x_preferred":[
        "Garing Para"
    ],
    "wof:name":"Garing Para",
    "wof:placetype":"neighbourhood",
    "wof:population":184
},
  "geometry": {"coordinates":[91.555531,23.951511],"type":"Point"}
}