{
  "type": "Feature",
  "properties": {
    "iso:country":"IN",
    "ks:ks_name":"Unaula Doim",
    "ks:ks_pop":294,
    "ks:ks_type":"VILLAGE",
    "name:eng_x_preferred":[
        "Unaula Doim"
    ],
    "wof:name":"Unaula Doim",
    "wof:placetype":"neighbourhood",
    "wof:population":294
},
  "geometry": {"coordinates":[83.469887,26.79361],"type":"Point"}
}