{
  "type": "Feature",
  "properties": {
    "iso:country":"IN",
    "ks:ks_name":"Valambakudi",
    "ks:ks_pop":1104,
    "ks:ks_type":"HABITATION",
    "name:eng_x_preferred":[
        "Valambakudi"
    ],
    "wof:name":"Valambakudi",
    "wof:placetype":"locality",
    "wof:population":1104
},
  "geometry": {"coordinates":[78.91902,10.723367],"type":"Point"}
}