{
  "type": "Feature",
  "properties": {
    "iso:country":"IN",
    "ks:ks_name":"Gagar Gaon",
    "ks:ks_pop":156,
    "ks:ks_type":"HABITATION",
    "name:eng_x_preferred":[
        "Gagar Gaon"
    ],
    "wof:name":"Gagar Gaon",
    "wof:placetype":"locality",
    "wof:population":156
},
  "geometry": {"coordinates":[78.391831,30.425865],"type":"Point"}
}