{
  "type": "Feature",
  "properties": {
    "iso:country":"IN",
    "ks:ks_name":"Aralia",
    "ks:ks_pop":3070,
    "ks:ks_type":"VILLAGE",
    "ks:ks_uagg_main":0,
    "name:eng_x_preferred":[
        "Aralia"
    ],
    "wof:name":"Aralia",
    "wof:placetype":"neighbourhood",
    "wof:population":3070
},
  "geometry": {"coordinates":[91.264678,23.495012],"type":"Point"}
}