{
  "type": "Feature",
  "properties": {
    "iso:country":"IN",
    "ks:ks_name":"Peeparna",
    "ks:ks_pop":200,
    "ks:ks_type":"VILLAGE",
    "name:eng_x_preferred":[
        "Peeparna"
    ],
    "wof:name":"Peeparna",
    "wof:placetype":"locality",
    "wof:population":200
},
  "geometry": {"coordinates":[73.34308900000001,24.879825],"type":"Point"}
}