{
  "type": "Feature",
  "properties": {
    "gn:admin1_code":"35.0",
    "gn:admin2_code":"422.0",
    "gn:asciiname":"Laitra",
    "gn:country_code":"IN",
    "gn:dem":196,
    "gn:feature_class":"P",
    "gn:feature_code":"PPL",
    "gn:name":"Laitra",
    "gn:population":0,
    "gn:timezone":"Asia/Kolkata",
    "iso:country":"IN",
    "wof:name":"Laitra",
    "wof:placetype":"neighbourhood"
},
  "geometry": {"coordinates":[78.48643,25.77016],"type":"Point"}
}