{
  "type": "Feature",
  "properties": {
    "iso:country":"IN",
    "ks:ks_name":"Chitradevarahatty",
    "ks:ks_pop":390,
    "ks:ks_type":"HABITATION",
    "name:eng_x_preferred":[
        "Chitradevarahatty"
    ],
    "wof:name":"Chitradevarahatty",
    "wof:placetype":"locality",
    "wof:population":390
},
  "geometry": {"coordinates":[76.598354,13.724755],"type":"Point"}
}