{
  "type": "Feature",
  "properties": {
    "gn:admin1_code":"39.0",
    "gn:admin2_code":"65.0",
    "gn:asciiname":"Machiadli Barela",
    "gn:country_code":"IN",
    "gn:dem":1111,
    "gn:feature_class":"P",
    "gn:feature_code":"PPL",
    "gn:name":"Machi\u0101dli Barela",
    "gn:population":0,
    "gn:timezone":"Asia/Kolkata",
    "iso:country":"IN",
    "wof:name":"Machiadli Barela",
    "wof:placetype":"locality"
},
  "geometry": {"coordinates":[79.92711,29.23779],"type":"Point"}
}