{
  "type": "Feature",
  "properties": {
    "iso:country":"IN",
    "ks:ks_name":"Khaira",
    "ks:ks_pop":902,
    "ks:ks_type":"VILLAGE",
    "ks:ks_uagg_main":0,
    "name:eng_x_preferred":[
        "Khaira"
    ],
    "wof:name":"Khaira",
    "wof:placetype":"neighbourhood",
    "wof:population":902
},
  "geometry": {"coordinates":[84.15975299999999,25.612815],"type":"Point"}
}