{
  "type": "Feature",
  "properties": {
    "iso:country":"IN",
    "ks:ks_name":"Pukurpara",
    "ks:ks_pop":1151,
    "ks:ks_type":"HABITATION",
    "ks:ks_uagg_main":0,
    "name:eng_x_preferred":[
        "Pukurpara"
    ],
    "wof:name":"Pukurpara",
    "wof:placetype":"neighbourhood",
    "wof:population":1151
},
  "geometry": {"coordinates":[87.887595,22.561104],"type":"Point"}
}