{
  "type": "Feature",
  "properties": {
    "gn:admin1_code":"24.0",
    "gn:admin2_code":"127.0",
    "gn:asciiname":"Jharamli",
    "gn:country_code":"IN",
    "gn:dem":262,
    "gn:feature_class":"P",
    "gn:feature_code":"PPL",
    "gn:name":"Jh\u0101r\u0101mli",
    "gn:population":0,
    "gn:timezone":"Asia/Kolkata",
    "iso:country":"IN",
    "wof:name":"Jharamli",
    "wof:placetype":"locality"
},
  "geometry": {"coordinates":[76.08168000000001,24.98064],"type":"Point"}
}