{
  "type": "Feature",
  "properties": {
    "gn:admin1_code":"13.0",
    "gn:admin2_code":"590.0",
    "gn:asciiname":"Patippura",
    "gn:country_code":"IN",
    "gn:dem":932,
    "gn:feature_class":"P",
    "gn:feature_code":"PPL",
    "gn:name":"Patippura",
    "gn:population":0,
    "gn:timezone":"Asia/Kolkata",
    "iso:country":"IN",
    "wof:name":"Patippura",
    "wof:placetype":"locality"
},
  "geometry": {"coordinates":[76.23994999999999,11.7322],"type":"Point"}
}