{
  "type": "Feature",
  "properties": {
    "iso:country":"IN",
    "ks:ks_name":"Hosamane",
    "ks:ks_pop":230,
    "ks:ks_type":"HABITATION",
    "name:eng_x_preferred":[
        "Hosamane"
    ],
    "wof:name":"Hosamane",
    "wof:placetype":"locality",
    "wof:population":230
},
  "geometry": {"coordinates":[75.103464,13.968199],"type":"Point"}
}