{
  "type": "Feature",
  "properties": {
    "iso:country":"IN",
    "ks:ks_name":"Bajpur",
    "ks:ks_pop":283,
    "ks:ks_type":"VILLAGE",
    "ks:ks_uagg_main":0,
    "name:eng_x_preferred":[
        "Bajpur"
    ],
    "wof:name":"Bajpur",
    "wof:placetype":"neighbourhood",
    "wof:population":283
},
  "geometry": {"coordinates":[87.53163499999999,22.312267],"type":"Point"}
}