{
  "type": "Feature",
  "properties": {
    "iso:country":"IN",
    "ks:ks_name":"Ponniyandal",
    "ks:ks_pop":594,
    "ks:ks_type":"VILLAGE",
    "name:eng_x_preferred":[
        "Ponniyandal"
    ],
    "wof:name":"Ponniyandal",
    "wof:placetype":"locality",
    "wof:population":594
},
  "geometry": {"coordinates":[79.07996799999999,11.894735],"type":"Point"}
}