{
  "type": "Feature",
  "properties": {
    "iso:country":"IN",
    "ks:ks_name":"P Pasin",
    "ks:ks_pop":120,
    "ks:ks_type":"HABITATION",
    "name:eng_x_preferred":[
        "P Pasin"
    ],
    "wof:name":"P Pasin",
    "wof:placetype":"locality",
    "wof:population":120
},
  "geometry": {"coordinates":[81.302091,26.283737],"type":"Point"}
}