{
  "type": "Feature",
  "properties": {
    "iso:country":"IN",
    "ks:ks_name":"Charkaghat",
    "ks:ks_pop":38,
    "ks:ks_type":"VILLAGE",
    "ks:ks_uagg_main":0,
    "name:eng_x_preferred":[
        "Charkaghat"
    ],
    "wof:name":"Charkaghat",
    "wof:placetype":"neighbourhood",
    "wof:population":38
},
  "geometry": {"coordinates":[87.180251,24.901102],"type":"Point"}
}