{
  "type": "Feature",
  "properties": {
    "iso:country":"IN",
    "ks:ks_name":"Sunariput",
    "ks:ks_pop":170,
    "ks:ks_type":"HABITATION",
    "name:eng_x_preferred":[
        "Sunariput"
    ],
    "wof:name":"Sunariput",
    "wof:placetype":"locality",
    "wof:population":170
},
  "geometry": {"coordinates":[82.620509,18.481457],"type":"Point"}
}