{
  "type": "Feature",
  "properties": {
    "iso:country":"IN",
    "ks:ks_alt_nam":"Tokot\u0101nr",
    "ks:ks_name":"Tokotanr",
    "ks:ks_type":"VILLAGE",
    "ks:ks_uagg_main":0,
    "name:eng_x_preferred":[
        "Tokotanr"
    ],
    "name:eng_x_variant":[
        "Tokot\u0101nr"
    ],
    "wof:name":"Tokotanr",
    "wof:placetype":"neighbourhood"
},
  "geometry": {"coordinates":[85.907552,24.452573],"type":"Point"}
}