{
  "type": "Feature",
  "properties": {
    "iso:country":"IN",
    "ks:ks_name":"Poradiha",
    "ks:ks_pop":1796,
    "ks:ks_type":"VILLAGE",
    "name:eng_x_preferred":[
        "Poradiha"
    ],
    "wof:name":"Poradiha",
    "wof:placetype":"locality",
    "wof:population":1796
},
  "geometry": {"coordinates":[86.171091,22.564889],"type":"Point"}
}