{
  "type": "Feature",
  "properties": {
    "iso:country":"IN",
    "ks:ks_name":"Uppar Beena",
    "ks:ks_pop":102,
    "ks:ks_type":"HABITATION",
    "name:eng_x_preferred":[
        "Uppar Beena"
    ],
    "wof:name":"Uppar Beena",
    "wof:placetype":"locality",
    "wof:population":102
},
  "geometry": {"coordinates":[85.092108,22.514428],"type":"Point"}
}