{
  "type": "Feature",
  "properties": {
    "iso:country":"IN",
    "ks:ks_name":"Jakhowapara",
    "ks:ks_pop":1085,
    "ks:ks_type":"VILLAGE",
    "ks:ks_uagg_main":0,
    "name:eng_x_preferred":[
        "Jakhowapara"
    ],
    "wof:name":"Jakhowapara",
    "wof:placetype":"neighbourhood",
    "wof:population":1085
},
  "geometry": {"coordinates":[90.90349999999999,25.944667],"type":"Point"}
}