{
  "type": "Feature",
  "properties": {
    "iso:country":"IN",
    "ks:ks_name":"Farasgaonkasai",
    "ks:ks_pop":495,
    "ks:ks_type":"VILLAGE",
    "name:eng_x_preferred":[
        "Farasgaonkasai"
    ],
    "wof:name":"Farasgaonkasai",
    "wof:placetype":"locality",
    "wof:population":495
},
  "geometry": {"coordinates":[81.392852,19.779064],"type":"Point"}
}