{
  "type": "Feature",
  "properties": {
    "iso:country":"IN",
    "ks:ks_name":"Jagannathpur",
    "ks:ks_pop":935,
    "ks:ks_type":"VILLAGE",
    "name:eng_x_preferred":[
        "Jagannathpur"
    ],
    "wof:name":"Jagannathpur",
    "wof:placetype":"locality",
    "wof:population":935
},
  "geometry": {"coordinates":[86.041404,20.555797],"type":"Point"}
}