{
  "type": "Feature",
  "properties": {
    "gn:admin1_code":"25.0",
    "gn:admin2_code":"610.0",
    "gn:asciiname":"Mulakadambur",
    "gn:country_code":"IN",
    "gn:dem":845,
    "gn:feature_class":"P",
    "gn:feature_code":"PPL",
    "gn:name":"M\u016blakadamb\u016br",
    "gn:population":0,
    "gn:timezone":"Asia/Kolkata",
    "iso:country":"IN",
    "wof:name":"Mulakadambur",
    "wof:placetype":"locality"
},
  "geometry": {"coordinates":[77.34089,11.63083],"type":"Point"}
}