{
  "type": "Feature",
  "properties": {
    "iso:country":"IN",
    "ks:ks_name":"Chak No. 4",
    "ks:ks_pop":6,
    "ks:ks_type":"VILLAGE",
    "name:eng_x_preferred":[
        "Chak No. 4"
    ],
    "wof:name":"Chak No. 4",
    "wof:placetype":"locality",
    "wof:population":6
},
  "geometry": {"coordinates":[72.865145,27.944969],"type":"Point"}
}