{
  "type": "Feature",
  "properties": {
    "gn:admin1_code":"34.0",
    "gn:admin2_code":"211.0",
    "gn:asciiname":"Chharrapatti",
    "gn:country_code":"IN",
    "gn:dem":37,
    "gn:feature_class":"P",
    "gn:feature_code":"PPL",
    "gn:name":"Chharr\u0101patti",
    "gn:population":0,
    "gn:timezone":"Asia/Kolkata",
    "iso:country":"IN",
    "name:und_x_variant":[
        "Chharr\u0101patti",
        "Lachhm\u012bpur"
    ],
    "wof:name":"Chharrapatti",
    "wof:placetype":"neighbourhood"
},
  "geometry": {"coordinates":[87.15459,25.53684],"type":"Point"}
}