{
  "type": "Feature",
  "properties": {
    "iso:country":"IN",
    "ks:ks_name":"Pogramunda",
    "ks:ks_pop":130,
    "ks:ks_type":"HABITATION",
    "name:eng_x_preferred":[
        "Pogramunda"
    ],
    "wof:name":"Pogramunda",
    "wof:placetype":"locality",
    "wof:population":130
},
  "geometry": {"coordinates":[84.036362,22.214381],"type":"Point"}
}