{
  "type": "Feature",
  "properties": {
    "iso:country":"IN",
    "ks:ks_name":"Vallankudikadu",
    "ks:ks_pop":379,
    "ks:ks_type":"HABITATION",
    "ks:ks_uagg_main":0,
    "name:eng_x_preferred":[
        "Vallankudikadu"
    ],
    "wof:name":"Vallankudikadu",
    "wof:placetype":"neighbourhood",
    "wof:population":379
},
  "geometry": {"coordinates":[79.43986700000001,10.608792],"type":"Point"}
}