{
  "type": "Feature",
  "properties": {
    "gn:admin1_code":"11.0",
    "gn:admin2_code":"32.0",
    "gn:asciiname":"Matil",
    "gn:country_code":"IN",
    "gn:dem":1608,
    "gn:feature_class":"P",
    "gn:feature_code":"PPL",
    "gn:name":"M\u0101til",
    "gn:population":0,
    "gn:timezone":"Asia/Kolkata",
    "iso:country":"IN",
    "wof:name":"Matil",
    "wof:placetype":"locality"
},
  "geometry": {"coordinates":[77.57746,30.66279],"type":"Point"}
}