{
  "type": "Feature",
  "properties": {
    "gn:admin1_code":"35.0",
    "gn:admin2_code":"440.0",
    "gn:asciiname":"Kumarkheda",
    "gn:country_code":"IN",
    "gn:dem":348,
    "gn:feature_class":"P",
    "gn:feature_code":"PPL",
    "gn:name":"Kumarkheda",
    "gn:population":0,
    "gn:timezone":"Asia/Kolkata",
    "iso:country":"IN",
    "wof:name":"Kumarkheda",
    "wof:placetype":"locality"
},
  "geometry": {"coordinates":[75.98181,21.66564],"type":"Point"}
}