{
  "type": "Feature",
  "properties": {
    "gn:country":"IN",
    "gn:fcode":"PPL",
    "gn:pop":42056,
    "iso:country":"IN",
    "name:ben_x_preferred":[
        "\u0995\u09be\u09a8\u09cd\u09a8\u09be\u09a6"
    ],
    "name:bpy_x_preferred":[
        "\u0995\u09be\u09a8\u09cd\u09a8\u09be\u09a6"
    ],
    "name:deu_x_preferred":[
        "Kannad"
    ],
    "name:eng_x_preferred":[
        "Kannad"
    ],
    "name:fra_x_preferred":[
        "Kannad"
    ],
    "name:guj_x_preferred":[
        "\u0a95\u0aa8\u0acd\u0aa8\u0aa1"
    ],
    "name:ita_x_preferred":[
        "Kannad"
    ],
    "name:jpn_x_preferred":[
        "\u30ab\u30f3\u30ca\u30c3\u30c9"
    ],
    "name:kan_x_preferred":[
        "\u0c95\u0ca8\u0ccd\u0ca8\u0ca1 \u0ca4\u0cbe\u0cb2\u0ccd\u0cb2\u0cc2\u0c95\u0cc1"
    ],
    "name:kor_x_preferred":[
        "\uce78\ub098\ub4dc"
    ],
    "name:mar_x_preferred":[
        "\u0915\u0928\u094d\u0928\u0921 \u0924\u093e\u0932\u0941\u0915\u093e"
    ],
    "name:msa_x_preferred":[
        "Kannad"
    ],
    "name:nan_x_preferred":[
        "Kannad"
    ],
    "name:new_x_preferred":[
        "\u0915\u0928\u094d\u0928\u0921"
    ],
    "name:nld_x_preferred":[
        "Kannad"
    ],
    "name:por_x_preferred":[
        "Kannad"
    ],
    "name:rus_x_preferred":[
        "\u041a\u0430\u043d\u043d\u0430\u0434"
    ],
    "name:spa_x_preferred":[
        "Kannad"
    ],
    "name:swe_x_preferred":[
        "Kannad"
    ],
    "name:tam_x_preferred":[
        "\u0b95\u0ba9\u0bcd\u0ba9\u0bbe\u0b9f\u0bcd"
    ],
    "name:tel_x_preferred":[
        "\u0c15\u0c28\u0c4d\u0c28\u0c3e\u0c21\u0c4d"
    ],
    "name:unk_x_variant":[
        "Kannad"
    ],
    "name:urd_x_preferred":[
        "\u06a9\u0646\u0691 \u062a\u0639\u0644\u0642\u06c1"
    ],
    "name:vie_x_preferred":[
        "Kannad"
    ],
    "qs:name":"Anad",
    "qs:name_adm0":"India",
    "qs:name_adm1":"Maharashtra",
    "qs:photos_9r":0,
    "qs:photos_sr":0,
    "qs:placetype":"Town",
    "qs:pop_sr":"7",
    "wd:wordcount":84,
    "wof:name":"Anad",
    "wof:placetype":"locality",
    "wof:population":42056
},
  "geometry": {"coordinates":[75.13800000000001,20.25784],"type":"Point"}
}