{
  "type": "Feature",
  "properties": {
    "iso:country":"IN",
    "ks:ks_name":"Sadadpada",
    "ks:ks_pop":350,
    "ks:ks_type":"HABITATION",
    "name:eng_x_preferred":[
        "Sadadpada"
    ],
    "wof:name":"Sadadpada",
    "wof:placetype":"locality",
    "wof:population":350
},
  "geometry": {"coordinates":[73.44981,20.299692],"type":"Point"}
}