{
  "type": "Feature",
  "properties": {
    "gn:admin1_code":"9.0",
    "gn:admin2_code":"483.0",
    "gn:asciiname":"Kupaji Muwara",
    "gn:country_code":"IN",
    "gn:dem":111,
    "gn:feature_class":"P",
    "gn:feature_code":"PPL",
    "gn:name":"Kup\u0101ji Muwara",
    "gn:population":0,
    "gn:timezone":"Asia/Kolkata",
    "iso:country":"IN",
    "wof:name":"Kupaji Muwara",
    "wof:placetype":"locality"
},
  "geometry": {"coordinates":[73.24165000000001,23.05138],"type":"Point"}
}