{
  "type": "Feature",
  "properties": {
    "iso:country":"IN",
    "ks:ks_name":"Jaldiha",
    "ks:ks_pop":952,
    "ks:ks_type":"VILLAGE",
    "name:eng_x_preferred":[
        "Jaldiha"
    ],
    "wof:name":"Jaldiha",
    "wof:placetype":"locality",
    "wof:population":952
},
  "geometry": {"coordinates":[84.950838,24.334358],"type":"Point"}
}