{
  "type": "Feature",
  "properties": {
    "gn:admin1_code":"12.0",
    "gn:admin2_code":"18.0",
    "gn:asciiname":"Pujni-ka-Bar",
    "gn:country_code":"IN",
    "gn:dem":2995,
    "gn:feature_class":"P",
    "gn:feature_code":"PPL",
    "gn:name":"Pujni-ka-B\u0101r",
    "gn:population":0,
    "gn:timezone":"Asia/Kolkata",
    "iso:country":"IN",
    "wof:name":"Pujni-ka-Bar",
    "wof:placetype":"locality"
},
  "geometry": {"coordinates":[75.99294,33.08000999999999],"type":"Point"}
}