{
  "type": "Feature",
  "properties": {
    "iso:country":"IN",
    "ks:ks_name":"Bhuvadwadi",
    "ks:ks_pop":54,
    "ks:ks_type":"HABITATION",
    "name:eng_x_preferred":[
        "Bhuvadwadi"
    ],
    "wof:name":"Bhuvadwadi",
    "wof:placetype":"locality",
    "wof:population":54
},
  "geometry": {"coordinates":[73.38490299999999,17.699883],"type":"Point"}
}