{
  "type": "Feature",
  "properties": {
    "iso:country":"IN",
    "ks:ks_name":"Laxmipurhut",
    "ks:ks_pop":734,
    "ks:ks_type":"HABITATION",
    "name:eng_x_preferred":[
        "Laxmipurhut"
    ],
    "wof:name":"Laxmipurhut",
    "wof:placetype":"locality",
    "wof:population":734
},
  "geometry": {"coordinates":[89.196387,26.659201],"type":"Point"}
}