{
  "type": "Feature",
  "properties": {
    "gn:admin1_code":"39.0",
    "gn:admin2_code":"63.0",
    "gn:asciiname":"Gainar",
    "gn:country_code":"IN",
    "gn:dem":1133,
    "gn:feature_class":"P",
    "gn:feature_code":"PPL",
    "gn:name":"Gainar",
    "gn:population":0,
    "gn:timezone":"Asia/Kolkata",
    "iso:country":"IN",
    "wof:name":"Gainar",
    "wof:placetype":"locality"
},
  "geometry": {"coordinates":[79.87347,29.93899],"type":"Point"}
}