{
  "type": "Feature",
  "properties": {
    "gn:admin1_code":"39.0",
    "gn:admin2_code":"63.0",
    "gn:asciiname":"Gainar",
    "gn:country_code":"IN",
    "gn:dem":1133,
    "gn:feature_class":"P",
    "gn:feature_code":"PPL",
    "gn:name":"Gainar",
    "gn:population":0,
    "gn:timezone":"Asia/Kolkata",
    "iso:country":"IN",
    "ks:ks_name":"Gainar",
    "ks:ks_pop":234,
    "ks:ks_type":"VILLAGE",
    "name:eng_x_preferred":[
        "Gainar"
    ],
    "wof:name":"Gainar",
    "wof:placetype":"locality",
    "wof:population":234
},
  "geometry": {"coordinates":[79.87106300000001,29.938317],"type":"Point"}
}