{
  "type": "Feature",
  "properties": {
    "iso:country":"IN",
    "ks:ks_alt_nam":"Behran falia",
    "ks:ks_name":"Behran Falia",
    "ks:ks_pop":415,
    "ks:ks_type":"HABITATION",
    "name:eng_x_preferred":[
        "Behran Falia"
    ],
    "wof:name":"Behran Falia",
    "wof:placetype":"locality",
    "wof:population":415
},
  "geometry": {"coordinates":[73.140972,20.225639],"type":"Point"}
}