{
  "type": "Feature",
  "properties": {
    "iso:country":"IN",
    "ks:ks_name":"Kenduguda2",
    "ks:ks_pop":409,
    "ks:ks_type":"HABITATION",
    "name:eng_x_preferred":[
        "Kenduguda2"
    ],
    "wof:name":"Kenduguda2",
    "wof:placetype":"locality",
    "wof:population":409
},
  "geometry": {"coordinates":[82.296182,18.960854],"type":"Point"}
}