{
  "type": "Feature",
  "properties": {
    "iso:country":"IN",
    "ks:ks_alt_nam":"kolearkhal",
    "ks:ks_name":"Kolearkhal",
    "ks:ks_pop":756,
    "ks:ks_type":"HABITATION",
    "name:eng_x_preferred":[
        "Kolearkhal"
    ],
    "wof:name":"Kolearkhal",
    "wof:placetype":"locality",
    "wof:population":756
},
  "geometry": {"coordinates":[90.306061,26.210297],"type":"Point"}
}