{
  "type": "Feature",
  "properties": {
    "iso:country":"IN",
    "ks:ks_alt_nam":"JOOKHAN KA PURA",
    "ks:ks_name":"Jookhan Ka Pura",
    "ks:ks_pop":6,
    "ks:ks_type":"HABITATION",
    "name:eng_x_preferred":[
        "Jookhan Ka Pura"
    ],
    "wof:name":"Jookhan Ka Pura",
    "wof:placetype":"locality",
    "wof:population":6
},
  "geometry": {"coordinates":[82.247996,26.456196],"type":"Point"}
}