{
  "type": "Feature",
  "properties": {
    "iso:country":"IN",
    "ks:ks_name":"Bediya Tola",
    "ks:ks_pop":39,
    "ks:ks_type":"HABITATION",
    "name:eng_x_preferred":[
        "Bediya Tola"
    ],
    "wof:name":"Bediya Tola",
    "wof:placetype":"locality",
    "wof:population":39
},
  "geometry": {"coordinates":[85.718998,23.515347],"type":"Point"}
}