{
  "type": "Feature",
  "properties": {
    "iso:country":"IN",
    "ks:ks_name":"Muthanampalayam",
    "ks:ks_pop":272,
    "ks:ks_type":"HABITATION",
    "name:eng_x_preferred":[
        "Muthanampalayam"
    ],
    "wof:name":"Muthanampalayam",
    "wof:placetype":"locality",
    "wof:population":272
},
  "geometry": {"coordinates":[78.10894500000001,11.394963],"type":"Point"}
}