{
  "type": "Feature",
  "properties": {
    "gn:admin1_code":"28.0",
    "gn:admin2_code":"336.0",
    "gn:asciiname":"Gopalpur",
    "gn:country_code":"IN",
    "gn:dem":16,
    "gn:feature_class":"P",
    "gn:feature_code":"PPL",
    "gn:name":"Gopalpur",
    "gn:population":0,
    "gn:timezone":"Asia/Kolkata",
    "iso:country":"IN",
    "name:ita_x_preferred":[
        "Gopalpur"
    ],
    "name:msa_x_preferred":[
        "Gopalpur"
    ],
    "name:new_x_preferred":[
        "\u0917\u094b\u092a\u093e\u0932\u092a\u0941\u0930"
    ],
    "name:nld_x_preferred":[
        "Gopalpur"
    ],
    "name:pnb_x_preferred":[
        "\u06af\u0648\u067e\u0627\u0644\u067e\u0648\u0631"
    ],
    "name:por_x_preferred":[
        "Gopalpur"
    ],
    "name:tam_x_preferred":[
        "\u0b95\u0bcb\u0baa\u0bbe\u0bb2\u0bcd\u0baa\u0bc2\u0bb0\u0bcd"
    ],
    "name:vie_x_preferred":[
        "Gopalpur"
    ],
    "name:zho_x_preferred":[
        "\u6208\u5e15\u5c14\u666e\u5c14"
    ],
    "wof:name":"Gopalpur",
    "wof:placetype":"locality"
},
  "geometry": {"coordinates":[88.54694000000001,23.12533],"type":"Point"}
}