{
  "type": "Feature",
  "properties": {
    "iso:country":"IN",
    "ks:ks_name":"Sandhisahi",
    "ks:ks_pop":43,
    "ks:ks_type":"VILLAGE",
    "name:eng_x_preferred":[
        "Sandhisahi"
    ],
    "wof:name":"Sandhisahi",
    "wof:placetype":"locality",
    "wof:population":43
},
  "geometry": {"coordinates":[84.074676,19.045582],"type":"Point"}
}