{
  "type": "Feature",
  "properties": {
    "iso:country":"IN",
    "ks:ks_name":"Bareigola",
    "ks:ks_pop":839,
    "ks:ks_type":"VILLAGE",
    "name:eng_x_preferred":[
        "Bareigola"
    ],
    "wof:name":"Bareigola",
    "wof:placetype":"locality",
    "wof:population":839
},
  "geometry": {"coordinates":[85.776774,21.192881],"type":"Point"}
}