{
  "type": "Feature",
  "properties": {
    "iso:country":"IN",
    "ks:ks_name":"Bukru",
    "ks:ks_pop":654,
    "ks:ks_type":"VILLAGE",
    "ks:ks_uagg_main":0,
    "name:eng_x_preferred":[
        "Bukru"
    ],
    "wof:name":"Bukru",
    "wof:placetype":"neighbourhood",
    "wof:population":654
},
  "geometry": {"coordinates":[84.96466599999999,23.979901],"type":"Point"}
}