{
  "type": "Feature",
  "properties": {
    "iso:country":"IN",
    "ks:ks_name":"Chak Chhakupal",
    "ks:ks_pop":4,
    "ks:ks_type":"VILLAGE",
    "name:eng_x_preferred":[
        "Chak Chhakupal"
    ],
    "wof:name":"Chak Chhakupal",
    "wof:placetype":"locality",
    "wof:population":4
},
  "geometry": {"coordinates":[87.439877,22.232896],"type":"Point"}
}