{
  "type": "Feature",
  "properties": {
    "iso:country":"IN",
    "ks:ks_name":"Similiput",
    "ks:ks_pop":121,
    "ks:ks_type":"VILLAGE",
    "name:eng_x_preferred":[
        "Similiput"
    ],
    "wof:name":"Similiput",
    "wof:placetype":"locality",
    "wof:population":121
},
  "geometry": {"coordinates":[82.743312,18.479047],"type":"Point"}
}