{
  "type": "Feature",
  "properties": {
    "gn:admin1_code":"2.0",
    "gn:admin2_code":"544.0",
    "gn:asciiname":"Palavalasa",
    "gn:country_code":"IN",
    "gn:dem":974,
    "gn:feature_class":"P",
    "gn:feature_code":"PPL",
    "gn:name":"P\u0101lavalasa",
    "gn:population":0,
    "gn:timezone":"Asia/Kolkata",
    "iso:country":"IN",
    "name:tel_x_preferred":[
        "\u0c2a\u0c3e\u0c32\u0c35\u0c32\u0c38"
    ],
    "wof:name":"Palavalasa",
    "wof:placetype":"locality"
},
  "geometry": {"coordinates":[82.60199,18.24972],"type":"Point"}
}