{
  "type": "Feature",
  "properties": {
    "iso:country":"IN",
    "ks:ks_alt_nam":"GONDAHI",
    "ks:ks_name":"Gondahi",
    "ks:ks_pop":526,
    "ks:ks_type":"HABITATION",
    "name:eng_x_preferred":[
        "Gondahi"
    ],
    "wof:name":"Gondahi",
    "wof:placetype":"locality",
    "wof:population":526
},
  "geometry": {"coordinates":[84.14751,24.67631],"type":"Point"}
}