{
  "type": "Feature",
  "properties": {
    "gn:admin1_code":"36.0",
    "gn:admin2_code":"171.0",
    "gn:asciiname":"Tari",
    "gn:country_code":"IN",
    "gn:dem":100,
    "gn:feature_class":"P",
    "gn:feature_code":"PPL",
    "gn:name":"T\u0101ri",
    "gn:population":0,
    "gn:timezone":"Asia/Kolkata",
    "iso:country":"IN",
    "name:ceb_x_preferred":[
        "Tari"
    ],
    "name:deu_x_preferred":[
        "Tari"
    ],
    "name:fra_x_preferred":[
        "Tari"
    ],
    "name:ita_x_preferred":[
        "Tari"
    ],
    "name:nds_x_preferred":[
        "Tari"
    ],
    "name:rus_x_preferred":[
        "\u0422\u0430\u0440\u0438"
    ],
    "name:swe_x_preferred":[
        "Tari"
    ],
    "wof:name":"Tari",
    "wof:placetype":"neighbourhood"
},
  "geometry": {"coordinates":[81.38106000000001,25.32864],"type":"Point"}
}