{
  "type": "Feature",
  "properties": {
    "iso:country":"IN",
    "ks:ks_name":"Chedekal",
    "ks:ks_pop":2083,
    "ks:ks_type":"HABITATION",
    "name:eng_x_preferred":[
        "Chedekal"
    ],
    "wof:name":"Chedekal",
    "wof:placetype":"locality",
    "wof:population":2083
},
  "geometry": {"coordinates":[75.061408,12.555009],"type":"Point"}
}