{
  "type": "Feature",
  "properties": {
    "iso:country":"IN",
    "ks:ks_name":"Mandha",
    "ks:ks_pop":167,
    "ks:ks_type":"VILLAGE",
    "name:eng_x_preferred":[
        "Mandha"
    ],
    "wof:name":"Mandha",
    "wof:placetype":"locality",
    "wof:population":167
},
  "geometry": {"coordinates":[78.543246,23.247719],"type":"Point"}
}