{
  "type": "Feature",
  "properties": {
    "iso:country":"IN",
    "ks:ks_name":"Angarpada",
    "ks:ks_pop":572,
    "ks:ks_type":"HABITATION",
    "name:eng_x_preferred":[
        "Angarpada"
    ],
    "wof:name":"Angarpada",
    "wof:placetype":"locality",
    "wof:population":572
},
  "geometry": {"coordinates":[86.09994500000001,22.11685],"type":"Point"}
}