{
  "type": "Feature",
  "properties": {
    "iso:country":"IN",
    "ks:ks_name":"Bamuha",
    "ks:ks_pop":2707,
    "ks:ks_type":"VILLAGE",
    "ks:ks_uagg_main":0,
    "name:eng_x_preferred":[
        "Bamuha"
    ],
    "wof:name":"Bamuha",
    "wof:placetype":"neighbourhood",
    "wof:population":2707
},
  "geometry": {"coordinates":[88.15176700000001,25.690696],"type":"Point"}
}