{
  "type": "Feature",
  "properties": {
    "iso:country":"IN",
    "ks:ks_name":"Monabari P P No 1 B L 1",
    "ks:ks_pop":684,
    "ks:ks_type":"HABITATION",
    "ks:ks_uagg_main":0,
    "name:eng_x_preferred":[
        "Monabari P P No 1 B L 1"
    ],
    "wof:name":"Monabari P P No 1 B L 1",
    "wof:placetype":"neighbourhood",
    "wof:population":684
},
  "geometry": {"coordinates":[93.25083100000001,26.762652],"type":"Point"}
}