{
  "type": "Feature",
  "properties": {
    "gn:admin1_code":"35.0",
    "gn:admin2_code":"446.0",
    "gn:asciiname":"Pratapgarh",
    "gn:country_code":"IN",
    "gn:dem":348,
    "gn:feature_class":"P",
    "gn:feature_code":"PPL",
    "gn:name":"Prat\u0101pgarh",
    "gn:population":0,
    "gn:timezone":"Asia/Kolkata",
    "iso:country":"IN",
    "name:ben_x_preferred":[
        "\u09aa\u09cd\u09b0\u09a4\u09be\u09aa\u0997\u09a1\u09bc"
    ],
    "name:cat_x_preferred":[
        "Pratapgarh"
    ],
    "name:ceb_x_preferred":[
        "Pratapgarh"
    ],
    "name:deu_x_preferred":[
        "Pratapgarh"
    ],
    "name:ita_x_preferred":[
        "Pratapgarh"
    ],
    "name:nld_x_preferred":[
        "Pratapgarh"
    ],
    "name:ori_x_preferred":[
        "\u0b2a\u0b4d\u0b30\u0b24\u0b3e\u0b2a\u0b17\u0b21\u0b3c"
    ],
    "name:pol_x_preferred":[
        "Pratapgarh"
    ],
    "name:rus_x_preferred":[
        "\u041f\u0440\u0430\u0442\u0430\u043f\u0433\u0430\u0440\u0445"
    ],
    "name:swe_x_preferred":[
        "Pratapgarh"
    ],
    "name:tam_x_preferred":[
        "\u0baa\u0bbf\u0bb0\u0ba4\u0bbe\u0baa\u0bcd\u0b95\u0bbe\u0b9f\u0bcd \u0bae\u0bbe\u0bb5\u0b9f\u0bcd\u0b9f\u0bae\u0bcd"
    ],
    "wof:name":"Pratapgarh",
    "wof:placetype":"locality"
},
  "geometry": {"coordinates":[78.33359,23.18811],"type":"Point"}
}