{
  "type": "Feature",
  "properties": {
    "iso:country":"IN",
    "ks:ks_name":"Kamdebpur",
    "ks:ks_pop":0,
    "ks:ks_type":"VILLAGE",
    "name:eng_x_preferred":[
        "Kamdebpur"
    ],
    "wof:name":"Kamdebpur",
    "wof:placetype":"locality",
    "wof:population":0
},
  "geometry": {"coordinates":[87.423524,22.789608],"type":"Point"}
}