{
  "type": "Feature",
  "properties": {
    "iso:country":"IN",
    "ks:ks_name":"Karahiya Tola",
    "ks:ks_pop":441,
    "ks:ks_type":"HABITATION",
    "name:eng_x_preferred":[
        "Karahiya Tola"
    ],
    "wof:name":"Karahiya Tola",
    "wof:placetype":"locality",
    "wof:population":441
},
  "geometry": {"coordinates":[83.016363,24.052388],"type":"Point"}
}