{
  "type": "Feature",
  "properties": {
    "iso:country":"IN",
    "ks:ks_alt_nam":"Melnanthiambadi ADC",
    "ks:ks_name":"Melnanthiambadi Adc",
    "ks:ks_pop":103,
    "ks:ks_type":"HABITATION",
    "name:eng_x_preferred":[
        "Melnanthiambadi Adc"
    ],
    "wof:name":"Melnanthiambadi Adc",
    "wof:placetype":"locality",
    "wof:population":103
},
  "geometry": {"coordinates":[79.380387,12.443217],"type":"Point"}
}