{
  "type": "Feature",
  "properties": {
    "gn:admin1_code":"11.0",
    "gn:admin2_code":"027",
    "gn:asciiname":"Jhatingri",
    "gn:country_code":"IN",
    "gn:dem":2021,
    "gn:feature_class":"P",
    "gn:feature_code":"PPL",
    "gn:name":"Jhatingri",
    "gn:population":0,
    "gn:timezone":"Asia/Kolkata",
    "iso:country":"IN",
    "name:und_x_variant":[
        "Jhatingr"
    ],
    "wof:name":"Jhatingri",
    "wof:placetype":"locality"
},
  "geometry": {"coordinates":[76.88443000000002,31.94703],"type":"Point"}
}