{
  "type": "Feature",
  "properties": {
    "gn:admin1_code":"19.0",
    "gn:admin2_code":"570.0",
    "gn:asciiname":"Gollarhatti",
    "gn:country_code":"IN",
    "gn:dem":732,
    "gn:feature_class":"P",
    "gn:feature_code":"PPL",
    "gn:name":"Gollarhatti",
    "gn:population":0,
    "gn:timezone":"Asia/Kolkata",
    "iso:country":"IN",
    "wof:name":"Gollarhatti",
    "wof:placetype":"locality"
},
  "geometry": {"coordinates":[76.19682,13.57153],"type":"Point"}
}