{
  "type": "Feature",
  "properties": {
    "iso:country":"IN",
    "ks:ks_name":"Pedapalem",
    "ks:ks_pop":586,
    "ks:ks_type":"HABITATION",
    "name:eng_x_preferred":[
        "Pedapalem"
    ],
    "wof:name":"Pedapalem",
    "wof:placetype":"neighbourhood",
    "wof:population":586
},
  "geometry": {"coordinates":[83.144015,17.609478],"type":"Point"}
}