{
  "type": "Feature",
  "properties": {
    "gn:admin1_code":"35",
    "gn:admin2_code":"423.0",
    "gn:asciiname":"Gwalia",
    "gn:country_code":"IN",
    "gn:dem":268,
    "gn:feature_class":"P",
    "gn:feature_code":"PPL",
    "gn:name":"Gw\u0101lia",
    "gn:population":0,
    "gn:timezone":"Asia/Kolkata",
    "iso:country":"IN",
    "name:cym_x_preferred":[
        "Gwalia"
    ],
    "wof:name":"Gwalia",
    "wof:placetype":"locality"
},
  "geometry": {"coordinates":[78.03005999999998,25.57091],"type":"Point"}
}