{
  "type": "Feature",
  "properties": {
    "iso:country":"IN",
    "ks:ks_name":"Sirodi",
    "ks:ks_pop":444,
    "ks:ks_type":"VILLAGE",
    "name:eng_x_preferred":[
        "Sirodi"
    ],
    "wof:name":"Sirodi",
    "wof:placetype":"locality",
    "wof:population":444
},
  "geometry": {"coordinates":[72.80176899999999,26.376339],"type":"Point"}
}