{
  "type": "Feature",
  "properties": {
    "iso:country":"IN",
    "ks:ks_name":"Ajeetgarh",
    "ks:ks_pop":287,
    "ks:ks_type":"HABITATION",
    "name:eng_x_preferred":[
        "Ajeetgarh"
    ],
    "wof:name":"Ajeetgarh",
    "wof:placetype":"locality",
    "wof:population":287
},
  "geometry": {"coordinates":[72.37169400000001,26.549714],"type":"Point"}
}