{
  "type": "Feature",
  "properties": {
    "iso:country":"IN",
    "ks:ks_name":"Joka",
    "ks:ks_pop":3647,
    "ks:ks_type":"VILLAGE",
    "ks:ks_uagg_main":0,
    "name:eng_x_preferred":[
        "Joka"
    ],
    "wof:name":"Joka",
    "wof:placetype":"neighbourhood",
    "wof:population":3647
},
  "geometry": {"coordinates":[87.96932099999999,22.488214],"type":"Point"}
}