{
  "type": "Feature",
  "properties": {
    "gn:admin1_code":"25.0",
    "gn:admin2_code":"630.0",
    "gn:asciiname":"Panekulam",
    "gn:country_code":"IN",
    "gn:dem":505,
    "gn:feature_class":"P",
    "gn:feature_code":"PPL",
    "gn:name":"Panekulam",
    "gn:population":0,
    "gn:timezone":"Asia/Kolkata",
    "iso:country":"IN",
    "wof:name":"Panekulam",
    "wof:placetype":"locality"
},
  "geometry": {"coordinates":[78.05299000000002,12.23017],"type":"Point"}
}