{
  "type": "Feature",
  "properties": {
    "gn:admin1_code":"36.0",
    "gn:admin2_code":"175.0",
    "gn:asciiname":"Kharian",
    "gn:country_code":"IN",
    "gn:dem":98,
    "gn:feature_class":"P",
    "gn:feature_code":"PPL",
    "gn:name":"Khari\u0101n",
    "gn:population":0,
    "gn:timezone":"Asia/Kolkata",
    "iso:country":"IN",
    "name:ben_x_preferred":[
        "\u0996\u09b0\u09bf\u09af\u09bc\u09be\u09a8"
    ],
    "name:ceb_x_preferred":[
        "Kh\u0101ri\u0101n"
    ],
    "name:deu_x_preferred":[
        "Kharian"
    ],
    "name:fas_x_preferred":[
        "\u062e\u0627\u0631\u06cc\u0627\u0646"
    ],
    "name:fra_x_preferred":[
        "Kharian"
    ],
    "name:ita_x_preferred":[
        "Kharian"
    ],
    "name:nor_x_preferred":[
        "Kharian"
    ],
    "name:pnb_x_preferred":[
        "\u06a9\u06be\u0627\u0631\u06cc\u0627\u06ba"
    ],
    "name:por_x_preferred":[
        "Kharian"
    ],
    "name:rus_x_preferred":[
        "\u041a\u0445\u0430\u0440\u0438\u044f\u043d"
    ],
    "name:spa_x_preferred":[
        "Kharian"
    ],
    "name:urd_x_preferred":[
        "\u06a9\u06be\u0627\u0631\u06cc\u0627\u06ba"
    ],
    "wof:name":"Kharian",
    "wof:placetype":"locality"
},
  "geometry": {"coordinates":[81.85068000000003,25.21117000000001],"type":"Point"}
}