{
  "type": "Feature",
  "properties": {
    "gn:admin1_code":"36",
    "gn:admin2_code":"175.0",
    "gn:asciiname":"Bharari",
    "gn:country_code":"IN",
    "gn:dem":98,
    "gn:feature_class":"P",
    "gn:feature_code":"PPL",
    "gn:name":"Bhar\u0101ri",
    "gn:population":0,
    "gn:timezone":"Asia/Kolkata",
    "iso:country":"IN",
    "ks:ks_alt_nam":"Bhar\u0101ri",
    "ks:ks_name":"Bharari",
    "ks:ks_type":"VILLAGE",
    "ks:ks_uagg_main":0,
    "name:eng_x_preferred":[
        "Bharari"
    ],
    "name:eng_x_variant":[
        "Bhar\u0101ri"
    ],
    "wof:name":"Bharari",
    "wof:placetype":"neighbourhood"
},
  "geometry": {"coordinates":[82.260859,25.111725],"type":"Point"}
}