{
  "type": "Feature",
  "properties": {
    "gn:admin1_code":"35",
    "gn:admin2_code":"436.0",
    "gn:asciiname":"Dudhpura",
    "gn:country_code":"IN",
    "gn:dem":451,
    "gn:feature_class":"P",
    "gn:feature_code":"PPL",
    "gn:name":"D\u016bdhpura",
    "gn:population":0,
    "gn:timezone":"Asia/Kolkata",
    "iso:country":"IN",
    "ks:ks_alt_nam":"D\u016bdhpura",
    "ks:ks_name":"Dudhpura",
    "ks:ks_pop":299,
    "ks:ks_type":"VILLAGE",
    "name:eng_x_preferred":[
        "Dudhpura"
    ],
    "name:eng_x_variant":[
        "D\u016bdhpura"
    ],
    "wof:name":"Dudhpura",
    "wof:placetype":"locality",
    "wof:population":299
},
  "geometry": {"coordinates":[76.086073,23.726184],"type":"Point"}
}