{
  "type": "Feature",
  "properties": {
    "gn:admin1_code":"21.0",
    "gn:admin2_code":"378.0",
    "gn:asciiname":"Barapada",
    "gn:country_code":"IN",
    "gn:dem":26,
    "gn:feature_class":"P",
    "gn:feature_code":"PPL",
    "gn:name":"Barapada",
    "gn:population":0,
    "gn:timezone":"Asia/Kolkata",
    "iso:country":"IN",
    "wof:name":"Barapada",
    "wof:placetype":"locality"
},
  "geometry": {"coordinates":[86.42284000000002,21.08638],"type":"Point"}
}