{
  "type": "Feature",
  "properties": {
    "iso:country":"IN",
    "ks:ks_name":"Naey Bhum",
    "ks:ks_pop":342,
    "ks:ks_type":"HABITATION",
    "name:eng_x_preferred":[
        "Naey Bhum"
    ],
    "wof:name":"Naey Bhum",
    "wof:placetype":"locality",
    "wof:population":342
},
  "geometry": {"coordinates":[84.462194,24.597861],"type":"Point"}
}