{
  "type": "Feature",
  "properties": {
    "iso:country":"IN",
    "ks:ks_name":"Melmaluru",
    "ks:ks_pop":93,
    "ks:ks_type":"HABITATION",
    "name:eng_x_preferred":[
        "Melmaluru"
    ],
    "wof:name":"Melmaluru",
    "wof:placetype":"locality",
    "wof:population":93
},
  "geometry": {"coordinates":[74.846723,13.970859],"type":"Point"}
}