{
  "type": "Feature",
  "properties": {
    "iso:country":"IN",
    "ks:ks_name":"Chowtaguntapali",
    "ks:ks_pop":166,
    "ks:ks_type":"HABITATION",
    "name:eng_x_preferred":[
        "Chowtaguntapali"
    ],
    "wof:name":"Chowtaguntapali",
    "wof:placetype":"locality",
    "wof:population":166
},
  "geometry": {"coordinates":[78.437619,13.696195],"type":"Point"}
}