{
  "type": "Feature",
  "properties": {
    "gn:admin1_code":"16",
    "gn:admin2_code":"505.0",
    "gn:asciiname":"Jogitola",
    "gn:country_code":"IN",
    "gn:dem":348,
    "gn:feature_class":"P",
    "gn:feature_code":"PPL",
    "gn:name":"Jogitola",
    "gn:population":0,
    "gn:timezone":"Asia/Kolkata",
    "iso:country":"IN",
    "ks:ks_name":"Jogitola",
    "ks:ks_type":"VILLAGE",
    "name:eng_x_preferred":[
        "Jogitola"
    ],
    "wof:name":"Jogitola",
    "wof:placetype":"locality"
},
  "geometry": {"coordinates":[79.489778,21.548062],"type":"Point"}
}