{
  "type": "Feature",
  "properties": {
    "iso:country":"IN",
    "ks:ks_name":"Uttar Para",
    "ks:ks_pop":364,
    "ks:ks_type":"HABITATION",
    "name:eng_x_preferred":[
        "Uttar Para"
    ],
    "wof:name":"Uttar Para",
    "wof:placetype":"locality",
    "wof:population":364
},
  "geometry": {"coordinates":[88.37065200000001,21.749788],"type":"Point"}
}