{
  "type": "Feature",
  "properties": {
    "gn:admin1_code":"24",
    "gn:admin2_code":"113.0",
    "gn:asciiname":"Mathania",
    "gn:country_code":"IN",
    "gn:dem":254,
    "gn:feature_class":"P",
    "gn:feature_code":"PPL",
    "gn:name":"Math\u0101nia",
    "gn:population":0,
    "gn:timezone":"Asia/Kolkata",
    "iso:country":"IN",
    "name:und_x_variant":[
        "Math\u0101nia"
    ],
    "wof:name":"Mathania",
    "wof:placetype":"locality"
},
  "geometry": {"coordinates":[72.97943000000002,26.53028],"type":"Point"}
}