{
  "type": "Feature",
  "properties": {
    "iso:country":"IN",
    "ks:ks_name":"Tarula",
    "ks:ks_pop":192,
    "ks:ks_type":"VILLAGE",
    "name:eng_x_preferred":[
        "Tarula"
    ],
    "wof:name":"Tarula",
    "wof:placetype":"locality",
    "wof:population":192
},
  "geometry": {"coordinates":[79.96322499999999,29.65226],"type":"Point"}
}