{
  "type": "Feature",
  "properties": {
    "gn:admin1_code":"24",
    "gn:admin2_code":"128.0",
    "gn:asciiname":"Nagori",
    "gn:country_code":"IN",
    "gn:dem":404,
    "gn:feature_class":"P",
    "gn:feature_code":"PPL",
    "gn:name":"N\u0101gori",
    "gn:population":0,
    "gn:timezone":"Asia/Kolkata",
    "iso:country":"IN",
    "name:fra_x_preferred":[
        "Nagori"
    ],
    "name:kan_x_preferred":[
        "\u0ca8\u0cbe\u0c97\u0ccb\u0cb0\u0cbf"
    ],
    "name:tam_x_preferred":[
        "\u0ba8\u0bbe\u0b95\u0bcb\u0bb0\u0bbf \u0bae\u0bbe\u0b9f\u0bc1"
    ],
    "wof:name":"Nagori",
    "wof:placetype":"locality"
},
  "geometry": {"coordinates":[76.99975000000001,25.18388],"type":"Point"}
}