{
  "type": "Feature",
  "properties": {
    "iso:country":"IN",
    "ks:ks_name":"Taduabahal",
    "ks:ks_pop":953,
    "ks:ks_type":"VILLAGE",
    "name:eng_x_preferred":[
        "Taduabahal"
    ],
    "wof:name":"Taduabahal",
    "wof:placetype":"locality",
    "wof:population":953
},
  "geometry": {"coordinates":[85.583895,21.985146],"type":"Point"}
}