{
  "type": "Feature",
  "properties": {
    "iso:country":"IN",
    "ks:ks_alt_nam":"R\u0101p\u0101ka Reserved Forest",
    "ks:ks_name":"Rapaka Reserved Forest",
    "ks:ks_type":"VILLAGE",
    "name:eng_x_preferred":[
        "Rapaka Reserved Forest"
    ],
    "name:eng_x_variant":[
        "R\u0101p\u0101ka Reserved Forest"
    ],
    "wof:name":"Rapaka Reserved Forest",
    "wof:placetype":"locality"
},
  "geometry": {"coordinates":[81.24487499999999,17.644252],"type":"Point"}
}