{
  "type": "Feature",
  "properties": {
    "iso:country":"IN",
    "ks:ks_name":"Dhigariya",
    "ks:ks_pop":470,
    "ks:ks_type":"HABITATION",
    "name:eng_x_preferred":[
        "Dhigariya"
    ],
    "wof:name":"Dhigariya",
    "wof:placetype":"locality",
    "wof:population":470
},
  "geometry": {"coordinates":[74.525767,27.233669],"type":"Point"}
}