{
  "type": "Feature",
  "properties": {
    "iso:country":"IN",
    "ks:ks_name":"Beni Ka Purwa",
    "ks:ks_pop":61,
    "ks:ks_type":"HABITATION",
    "name:eng_x_preferred":[
        "Beni Ka Purwa"
    ],
    "wof:name":"Beni Ka Purwa",
    "wof:placetype":"locality",
    "wof:population":61
},
  "geometry": {"coordinates":[80.442386,25.478524],"type":"Point"}
}