{
  "type": "Feature",
  "properties": {
    "iso:country":"IN",
    "ks:ks_name":"Kumarpur",
    "ks:ks_pop":753,
    "ks:ks_type":"VILLAGE",
    "name:eng_x_preferred":[
        "Kumarpur"
    ],
    "wof:name":"Kumarpur",
    "wof:placetype":"locality",
    "wof:population":753
},
  "geometry": {"coordinates":[87.89516500000001,22.206884],"type":"Point"}
}