{
  "type": "Feature",
  "properties": {
    "iso:country":"IN",
    "ks:ks_name":"Gangpur",
    "ks:ks_pop":732,
    "ks:ks_type":"VILLAGE",
    "name:eng_x_preferred":[
        "Gangpur"
    ],
    "wof:name":"Gangpur",
    "wof:placetype":"locality",
    "wof:population":732
},
  "geometry": {"coordinates":[79.118077,27.638724],"type":"Point"}
}