{
  "type": "Feature",
  "properties": {
    "iso:country":"IN",
    "ks:ks_name":"Moyzarwadi",
    "ks:ks_pop":385,
    "ks:ks_type":"HABITATION",
    "name:eng_x_preferred":[
        "Moyzarwadi"
    ],
    "wof:name":"Moyzarwadi",
    "wof:placetype":"locality",
    "wof:population":385
},
  "geometry": {"coordinates":[73.89635800000001,15.829727],"type":"Point"}
}