{
  "type": "Feature",
  "properties": {
    "gn:admin1_code":"25.0",
    "gn:admin2_code":"627.0",
    "gn:asciiname":"Nagalapuram",
    "gn:country_code":"IN",
    "gn:dem":43,
    "gn:feature_class":"P",
    "gn:feature_code":"PPL",
    "gn:name":"N\u0101gal\u0101puram",
    "gn:population":0,
    "gn:timezone":"Asia/Kolkata",
    "iso:country":"IN",
    "wof:name":"Nagalapuram",
    "wof:placetype":"locality"
},
  "geometry": {"coordinates":[78.13311999999998,9.23218],"type":"Point"}
}