{
  "type": "Feature",
  "properties": {
    "gn:admin1_code":"25.0",
    "gn:admin2_code":"627.0",
    "gn:asciiname":"Nagalapuram",
    "gn:country_code":"IN",
    "gn:dem":43,
    "gn:feature_class":"P",
    "gn:feature_code":"PPL",
    "gn:name":"N\u0101gal\u0101puram",
    "gn:population":0,
    "gn:timezone":"Asia/Kolkata",
    "iso:country":"IN",
    "name:ceb_x_preferred":[
        "N\u0101gal\u0101puram"
    ],
    "name:new_x_preferred":[
        "\u0928\u093e\u0917\u0932\u093e\u092a\u0941\u0930\u0902 \u092e\u0923\u094d\u0921\u0932"
    ],
    "name:pam_x_preferred":[
        "Nagalapuram"
    ],
    "name:swe_x_preferred":[
        "N\u0101gal\u0101puram"
    ],
    "name:tam_x_preferred":[
        "\u0ba8\u0bbe\u0b95\u0bb2\u0bbe\u0baa\u0bc1\u0bb0\u0bae\u0bcd"
    ],
    "name:tel_x_preferred":[
        "\u0c28\u0c3e\u0c17\u0c32\u0c3e\u0c2a\u0c41\u0c30\u0c02"
    ],
    "name:tgl_x_preferred":[
        "Nagalapuram"
    ],
    "name:urd_x_preferred":[
        "\u0646\u0627\u06af\u0644\u0627\u067e\u0648\u0631\u0645"
    ],
    "name:vie_x_preferred":[
        "Nagalapuram"
    ],
    "wof:name":"Nagalapuram",
    "wof:placetype":"locality"
},
  "geometry": {"coordinates":[78.13311999999998,9.23218],"type":"Point"}
}