{
  "type": "Feature",
  "properties": {
    "iso:country":"IN",
    "ks:ks_name":"Ratnayyammapeta",
    "ks:ks_pop":1121,
    "ks:ks_type":"HABITATION",
    "name:eng_x_preferred":[
        "Ratnayyammapeta"
    ],
    "wof:name":"Ratnayyammapeta",
    "wof:placetype":"locality",
    "wof:population":1121
},
  "geometry": {"coordinates":[82.55527600000001,17.274082],"type":"Point"}
}