{
  "type": "Feature",
  "properties": {
    "iso:country":"IN",
    "ks:ks_name":"Lankamaa",
    "ks:ks_pop":51,
    "ks:ks_type":"HABITATION",
    "name:eng_x_preferred":[
        "Lankamaa"
    ],
    "wof:name":"Lankamaa",
    "wof:placetype":"locality",
    "wof:population":51
},
  "geometry": {"coordinates":[85.964623,22.158108],"type":"Point"}
}