{
  "type": "Feature",
  "properties": {
    "gn:country":"IN",
    "gn:fcode":"PPL",
    "gn:population":0,
    "iso:country":"IN",
    "name:ben_x_preferred":[
        "\u0996\u09be\u09a8\u09be\u09aa\u09c1\u09b0"
    ],
    "name:bpy_x_preferred":[
        "\u0996\u09be\u09a8\u09be\u09aa\u09c1\u09b0"
    ],
    "name:ceb_x_preferred":[
        "Kh\u0101n\u0101pur"
    ],
    "name:ita_x_preferred":[
        "Khanapur"
    ],
    "name:kan_x_preferred":[
        "\u0c96\u0cbe\u0ca8\u0cbe\u0caa\u0cc1\u0cb0"
    ],
    "name:mar_x_preferred":[
        "\u0916\u093e\u0928\u093e\u092a\u0942\u0930"
    ],
    "name:mlg_x_preferred":[
        "Khanapur"
    ],
    "name:msa_x_preferred":[
        "Khanapur"
    ],
    "name:new_x_preferred":[
        "\u0916\u093e\u0928\u093e\u092a\u0941\u0930"
    ],
    "name:nld_x_preferred":[
        "Khanapur"
    ],
    "name:pam_x_preferred":[
        "Khanapur"
    ],
    "name:por_x_preferred":[
        "Khanapur"
    ],
    "name:san_x_preferred":[
        "\u0916\u093e\u0928\u093e\u092a\u0941\u0930\u092e\u094d"
    ],
    "name:swe_x_preferred":[
        "Kh\u0101n\u0101pur"
    ],
    "name:tam_x_preferred":[
        "\u0b95\u0bbe\u0ba9\u0bbe\u0baa\u0bc2\u0bb0\u0bcd"
    ],
    "name:vie_x_preferred":[
        "Khanapur"
    ],
    "name:zho_x_preferred":[
        "\u5361\u7eb3\u666e\u5c14"
    ],
    "qs:name":"Khanapur",
    "qs:name_adm0":"India",
    "qs:name_adm1":"Andhra Pradesh",
    "qs:photos_9r":0,
    "qs:photos_sr":0,
    "qs:placetype":"Town",
    "qs:pop_sr":"0",
    "wd:wordcount":383,
    "wof:name":"Khanapur",
    "wof:placetype":"locality",
    "wof:population":0
},
  "geometry": {"coordinates":[78.65134,17.17109],"type":"Point"}
}