{
  "type": "Feature",
  "properties": {
    "iso:country":"IN",
    "ks:ks_name":"Kavinmoola",
    "ks:ks_pop":400,
    "ks:ks_type":"HABITATION",
    "name:eng_x_preferred":[
        "Kavinmoola"
    ],
    "wof:name":"Kavinmoola",
    "wof:placetype":"locality",
    "wof:population":400
},
  "geometry": {"coordinates":[75.316108,12.042508],"type":"Point"}
}