{
  "type": "Feature",
  "properties": {
    "iso:country":"IN",
    "ks:ks_name":"Kaimakanpur",
    "ks:ks_pop":593,
    "ks:ks_type":"HABITATION",
    "ks:ks_uagg_main":0,
    "name:eng_x_preferred":[
        "Kaimakanpur"
    ],
    "wof:name":"Kaimakanpur",
    "wof:placetype":"neighbourhood",
    "wof:population":593
},
  "geometry": {"coordinates":[86.625585,20.789956],"type":"Point"}
}