{
  "type": "Feature",
  "properties": {
    "iso:country":"IN",
    "ks:ks_alt_nam":"Basireddi indlu",
    "ks:ks_name":"Basireddi Indlu",
    "ks:ks_pop":174,
    "ks:ks_type":"HABITATION",
    "name:eng_x_preferred":[
        "Basireddi Indlu"
    ],
    "wof:name":"Basireddi Indlu",
    "wof:placetype":"locality",
    "wof:population":174
},
  "geometry": {"coordinates":[78.96277600000001,13.38434],"type":"Point"}
}