{
  "type": "Feature",
  "properties": {
    "iso:country":"IN",
    "ks:ks_name":"Rangaguda",
    "ks:ks_pop":467,
    "ks:ks_type":"HABITATION",
    "name:eng_x_preferred":[
        "Rangaguda"
    ],
    "wof:name":"Rangaguda",
    "wof:placetype":"locality",
    "wof:population":467
},
  "geometry": {"coordinates":[83.68578100000001,18.795259],"type":"Point"}
}