{
  "type": "Feature",
  "properties": {
    "iso:country":"IN",
    "ks:ks_name":"Naharani Pathar",
    "ks:ks_pop":223,
    "ks:ks_type":"VILLAGE",
    "name:eng_x_preferred":[
        "Naharani Pathar"
    ],
    "wof:name":"Naharani Pathar",
    "wof:placetype":"locality",
    "wof:population":223
},
  "geometry": {"coordinates":[94.12242000000001,27.129342],"type":"Point"}
}