{
  "type": "Feature",
  "properties": {
    "iso:country":"IN",
    "ks:ks_name":"Leg Nagar",
    "ks:ks_pop":91,
    "ks:ks_type":"HABITATION",
    "name:eng_x_preferred":[
        "Leg Nagar"
    ],
    "wof:name":"Leg Nagar",
    "wof:placetype":"locality",
    "wof:population":91
},
  "geometry": {"coordinates":[77.26630400000001,23.925568],"type":"Point"}
}