{
  "type": "Feature",
  "properties": {
    "iso:country":"IN",
    "ks:ks_name":"Sewaka Dar",
    "ks:ks_pop":619,
    "ks:ks_type":"HABITATION",
    "name:eng_x_preferred":[
        "Sewaka Dar"
    ],
    "wof:name":"Sewaka Dar",
    "wof:placetype":"locality",
    "wof:population":619
},
  "geometry": {"coordinates":[82.960499,23.974922],"type":"Point"}
}