{
  "type": "Feature",
  "properties": {
    "iso:country":"IN",
    "ks:ks_name":"Bandha",
    "ks:ks_pop":431,
    "ks:ks_type":"HABITATION",
    "name:eng_x_preferred":[
        "Bandha"
    ],
    "wof:name":"Bandha",
    "wof:placetype":"locality",
    "wof:population":431
},
  "geometry": {"coordinates":[81.887325,20.438513],"type":"Point"}
}