{
  "type": "Feature",
  "properties": {
    "iso:country":"IN",
    "ks:ks_name":"Malarbadia",
    "ks:ks_pop":107,
    "ks:ks_type":"VILLAGE",
    "ks:ks_uagg_main":0,
    "name:eng_x_preferred":[
        "Malarbadia"
    ],
    "wof:name":"Malarbadia",
    "wof:placetype":"locality",
    "wof:population":107
},
  "geometry": {"coordinates":[87.451525,21.644755],"type":"Point"}
}