{
  "type": "Feature",
  "properties": {
    "iso:country":"IN",
    "ks:ks_name":"Kokatewadi",
    "ks:ks_pop":91,
    "ks:ks_type":"HABITATION",
    "name:eng_x_preferred":[
        "Kokatewadi"
    ],
    "wof:name":"Kokatewadi",
    "wof:placetype":"locality",
    "wof:population":91
},
  "geometry": {"coordinates":[73.634417,16.607199],"type":"Point"}
}