{
  "type": "Feature",
  "properties": {
    "iso:country":"IN",
    "ks:ks_alt_nam":"B\u0101l\u0101pur",
    "ks:ks_name":"Balapur",
    "ks:ks_pop":11,
    "ks:ks_type":"VILLAGE",
    "name:eng_x_preferred":[
        "Balapur"
    ],
    "name:eng_x_variant":[
        "B\u0101l\u0101pur"
    ],
    "wof:name":"Balapur",
    "wof:placetype":"locality",
    "wof:population":11
},
  "geometry": {"coordinates":[78.543531,20.668604],"type":"Point"}
}