{
  "type": "Feature",
  "properties": {
    "gn:admin1_code":"12.0",
    "gn:admin2_code":"008",
    "gn:asciiname":"Shunglipura",
    "gn:country_code":"IN",
    "gn:dem":1587,
    "gn:feature_class":"P",
    "gn:feature_code":"PPL",
    "gn:name":"Shunglipura",
    "gn:population":0,
    "gn:timezone":"Asia/Kolkata",
    "iso:country":"IN",
    "wof:name":"Shunglipura",
    "wof:placetype":"locality"
},
  "geometry": {"coordinates":[74.77113,34.11245],"type":"Point"}
}