{
  "type": "Feature",
  "properties": {
    "gn:admin1_code":"39.0",
    "gn:admin2_code":"61.0",
    "gn:asciiname":"Nauwon",
    "gn:country_code":"IN",
    "gn:dem":1527,
    "gn:feature_class":"P",
    "gn:feature_code":"PPL",
    "gn:name":"Nauwon",
    "gn:population":0,
    "gn:timezone":"Asia/Kolkata",
    "iso:country":"IN",
    "wof:name":"Nauwon",
    "wof:placetype":"locality"
},
  "geometry": {"coordinates":[79.1054,29.81363],"type":"Point"}
}