{
  "type": "Feature",
  "properties": {
    "iso:country":"IN",
    "ks:ks_name":"Marichamala",
    "ks:ks_pop":89,
    "ks:ks_type":"HABITATION",
    "name:eng_x_preferred":[
        "Marichamala"
    ],
    "wof:name":"Marichamala",
    "wof:placetype":"locality",
    "wof:population":89
},
  "geometry": {"coordinates":[82.98529600000001,18.835092],"type":"Point"}
}