{
  "type": "Feature",
  "properties": {
    "iso:country":"IN",
    "ks:ks_name":"Schoolpara",
    "ks:ks_pop":538,
    "ks:ks_type":"HABITATION",
    "name:eng_x_preferred":[
        "Schoolpara"
    ],
    "wof:name":"Schoolpara",
    "wof:placetype":"locality",
    "wof:population":538
},
  "geometry": {"coordinates":[81.42976,19.661044],"type":"Point"}
}