{
  "type": "Feature",
  "properties": {
    "iso:country":"IN",
    "ks:ks_name":"Nurpur",
    "ks:ks_pop":4361,
    "ks:ks_type":"VILLAGE",
    "ks:ks_uagg_main":0,
    "name:eng_x_preferred":[
        "Nurpur"
    ],
    "wof:name":"Nurpur",
    "wof:placetype":"neighbourhood",
    "wof:population":4361
},
  "geometry": {"coordinates":[86.9348,25.230295],"type":"Point"}
}