{
  "type": "Feature",
  "properties": {
    "iso:country":"IN",
    "ks:ks_name":"Kalloti",
    "ks:ks_pop":45,
    "ks:ks_type":"HABITATION",
    "name:eng_x_preferred":[
        "Kalloti"
    ],
    "wof:name":"Kalloti",
    "wof:placetype":"locality",
    "wof:population":45
},
  "geometry": {"coordinates":[74.790541,14.055337],"type":"Point"}
}