{
  "type": "Feature",
  "properties": {
    "iso:country":"IN",
    "ks:ks_name":"Bir Chhuchhakwas",
    "ks:ks_pop":3240,
    "ks:ks_type":"VILLAGE",
    "ks:ks_uagg_main":0,
    "name:eng_x_preferred":[
        "Bir Chhuchhakwas"
    ],
    "wof:name":"Bir Chhuchhakwas",
    "wof:placetype":"neighbourhood",
    "wof:population":3240
},
  "geometry": {"coordinates":[76.510535,28.598697],"type":"Point"}
}