{
  "type": "Feature",
  "properties": {
    "iso:country":"IN",
    "ks:ks_name":"Kannur Totada Wasti",
    "ks:ks_pop":219,
    "ks:ks_type":"HABITATION",
    "name:eng_x_preferred":[
        "Kannur Totada Wasti"
    ],
    "wof:name":"Kannur Totada Wasti",
    "wof:placetype":"locality",
    "wof:population":219
},
  "geometry": {"coordinates":[75.588013,16.658304],"type":"Point"}
}