{
  "type": "Feature",
  "properties": {
    "iso:country":"IN",
    "ks:ks_name":"Muhammadpur",
    "ks:ks_type":"VILLAGE",
    "name:eng_x_preferred":[
        "Muhammadpur"
    ],
    "wof:name":"Muhammadpur",
    "wof:placetype":"locality"
},
  "geometry": {"coordinates":[79.320831,28.825844],"type":"Point"}
}