{
  "type": "Feature",
  "properties": {
    "iso:country":"IN",
    "ks:ks_name":"Rudhai",
    "ks:ks_pop":2517,
    "ks:ks_type":"VILLAGE",
    "ks:ks_uagg_main":0,
    "name:eng_x_preferred":[
        "Rudhai"
    ],
    "wof:name":"Rudhai",
    "wof:placetype":"neighbourhood",
    "wof:population":2517
},
  "geometry": {"coordinates":[80.91317600000001,26.982549],"type":"Point"}
}