{
  "type": "Feature",
  "properties": {
    "gn:admin1_code":"9.0",
    "gn:admin2_code":"475.0",
    "gn:asciiname":"Navalgadh",
    "gn:country_code":"IN",
    "gn:dem":72,
    "gn:feature_class":"P",
    "gn:feature_code":"PPL",
    "gn:name":"Navalgadh",
    "gn:population":0,
    "gn:timezone":"Asia/Kolkata",
    "iso:country":"IN",
    "wof:name":"Navalgadh",
    "wof:placetype":"locality"
},
  "geometry": {"coordinates":[71.51915,22.9225],"type":"Point"}
}