{
  "type": "Feature",
  "properties": {
    "iso:country":"IN",
    "ks:ks_name":"Ravapara Pt I",
    "ks:ks_pop":358,
    "ks:ks_type":"HABITATION",
    "name:eng_x_preferred":[
        "Ravapara Pt I"
    ],
    "wof:name":"Ravapara Pt I",
    "wof:placetype":"locality",
    "wof:population":358
},
  "geometry": {"coordinates":[90.605784,26.461838],"type":"Point"}
}