{
  "type": "Feature",
  "properties": {
    "iso:country":"IN",
    "ks:ks_name":"Jadhavawadi",
    "ks:ks_pop":32,
    "ks:ks_type":"HABITATION",
    "name:eng_x_preferred":[
        "Jadhavawadi"
    ],
    "wof:name":"Jadhavawadi",
    "wof:placetype":"locality",
    "wof:population":32
},
  "geometry": {"coordinates":[73.47834,17.881248],"type":"Point"}
}