{
  "type": "Feature",
  "properties": {
    "iso:country":"IN",
    "ks:ks_name":"Uchanaicken Valava",
    "ks:ks_pop":227,
    "ks:ks_type":"HABITATION",
    "name:eng_x_preferred":[
        "Uchanaicken Valava"
    ],
    "wof:name":"Uchanaicken Valava",
    "wof:placetype":"locality",
    "wof:population":227
},
  "geometry": {"coordinates":[77.974664,11.808658],"type":"Point"}
}