{
  "type": "Feature",
  "properties": {
    "iso:country":"IN",
    "ks:ks_name":"Babultad",
    "ks:ks_pop":101,
    "ks:ks_type":"HABITATION",
    "name:eng_x_preferred":[
        "Babultad"
    ],
    "wof:name":"Babultad",
    "wof:placetype":"locality",
    "wof:population":101
},
  "geometry": {"coordinates":[74.59701699999999,21.667787],"type":"Point"}
}