{
  "type": "Feature",
  "properties": {
    "iso:country":"IN",
    "ks:ks_alt_nam":"Tellar JHC",
    "ks:ks_name":"Tellar Jhc",
    "ks:ks_pop":286,
    "ks:ks_type":"HABITATION",
    "name:eng_x_preferred":[
        "Tellar Jhc"
    ],
    "wof:name":"Tellar Jhc",
    "wof:placetype":"locality",
    "wof:population":286
},
  "geometry": {"coordinates":[75.026332,13.237357],"type":"Point"}
}