{
  "type": "Feature",
  "properties": {
    "gn:admin1_code":"36",
    "gn:admin2_code":"188.0",
    "gn:asciiname":"Madaria",
    "gn:country_code":"IN",
    "gn:dem":79,
    "gn:feature_class":"P",
    "gn:feature_code":"PPL",
    "gn:name":"Madaria",
    "gn:population":0,
    "gn:timezone":"Asia/Kolkata",
    "iso:country":"IN",
    "name:eus_x_preferred":[
        "Madaria"
    ],
    "name:fra_x_preferred":[
        "Madaria"
    ],
    "name:spa_x_preferred":[
        "Madaria"
    ],
    "wof:name":"Madaria",
    "wof:placetype":"locality"
},
  "geometry": {"coordinates":[83.40720999999998,26.31075],"type":"Point"}
}