{
  "type": "Feature",
  "properties": {
    "iso:country":"IN",
    "ks:ks_name":"Rajnagar",
    "ks:ks_pop":1443,
    "ks:ks_type":"HABITATION",
    "name:eng_x_preferred":[
        "Rajnagar"
    ],
    "wof:name":"Rajnagar",
    "wof:placetype":"locality",
    "wof:population":1443
},
  "geometry": {"coordinates":[88.25226000000001,21.94982],"type":"Point"}
}