{
  "type": "Feature",
  "properties": {
    "gn:admin1_code":"11.0",
    "gn:admin2_code":"33.0",
    "gn:asciiname":"Shapar",
    "gn:country_code":"IN",
    "gn:dem":1666,
    "gn:feature_class":"P",
    "gn:feature_code":"PPL",
    "gn:name":"Sh\u0101par",
    "gn:population":0,
    "gn:timezone":"Asia/Kolkata",
    "iso:country":"IN",
    "name:aze_x_preferred":[
        "\u015eapar"
    ],
    "wof:name":"Shapar",
    "wof:placetype":"locality"
},
  "geometry": {"coordinates":[77.33322,31.17213],"type":"Point"}
}