{
  "type": "Feature",
  "properties": {
    "gn:admin1_code":"21.0",
    "gn:admin2_code":"399.0",
    "gn:asciiname":"Kolagonda",
    "gn:country_code":"IN",
    "gn:dem":131,
    "gn:feature_class":"P",
    "gn:feature_code":"PPL",
    "gn:name":"Kolagonda",
    "gn:population":0,
    "gn:timezone":"Asia/Kolkata",
    "iso:country":"IN",
    "wof:name":"Kolagonda",
    "wof:placetype":"locality"
},
  "geometry": {"coordinates":[81.54682,18.11419],"type":"Point"}
}