{
  "type": "Feature",
  "properties": {
    "iso:country":"IN",
    "ks:ks_name":"Patkel Beriaa",
    "ks:ks_pop":44,
    "ks:ks_type":"HABITATION",
    "name:eng_x_preferred":[
        "Patkel Beriaa"
    ],
    "wof:name":"Patkel Beriaa",
    "wof:placetype":"locality",
    "wof:population":44
},
  "geometry": {"coordinates":[88.38195399999999,22.126905],"type":"Point"}
}