{
  "type": "Feature",
  "properties": {
    "iso:country":"IN",
    "ks:ks_name":"Viraipur",
    "ks:ks_pop":483,
    "ks:ks_type":"VILLAGE",
    "name:eng_x_preferred":[
        "Viraipur"
    ],
    "wof:name":"Viraipur",
    "wof:placetype":"locality",
    "wof:population":483
},
  "geometry": {"coordinates":[82.221681,26.286923],"type":"Point"}
}