{
  "type": "Feature",
  "properties": {
    "iso:country":"IN",
    "ks:ks_name":"Baghmari Kitakharwa",
    "ks:ks_pop":757,
    "ks:ks_type":"VILLAGE",
    "name:eng_x_preferred":[
        "Baghmari Kitakharwa"
    ],
    "wof:name":"Baghmari Kitakharwa",
    "wof:placetype":"locality",
    "wof:population":757
},
  "geometry": {"coordinates":[86.814288,24.521531],"type":"Point"}
}