{
  "type": "Feature",
  "properties": {
    "iso:country":"IN",
    "ks:ks_name":"Murain Ka Purwa",
    "ks:ks_pop":160,
    "ks:ks_type":"HABITATION",
    "name:eng_x_preferred":[
        "Murain Ka Purwa"
    ],
    "wof:name":"Murain Ka Purwa",
    "wof:placetype":"locality",
    "wof:population":160
},
  "geometry": {"coordinates":[81.02531,25.323744],"type":"Point"}
}