{
  "type": "Feature",
  "properties": {
    "gn:admin1_code":"36.0",
    "gn:admin2_code":"155.0",
    "gn:asciiname":"Dahti Salkupur",
    "gn:country_code":"IN",
    "gn:dem":143,
    "gn:feature_class":"P",
    "gn:feature_code":"PPL",
    "gn:name":"Dahti Salk\u016bpur",
    "gn:population":0,
    "gn:timezone":"Asia/Kolkata",
    "iso:country":"IN",
    "ks:ks_name":"Dahti Salukpur",
    "ks:ks_pop":2495,
    "ks:ks_type":"VILLAGE",
    "name:eng_x_preferred":[
        "Dahti Salukpur"
    ],
    "name:eng_x_variant":[
        "Dahti Salkupur"
    ],
    "wof:name":"Dahti Salukpur",
    "wof:placetype":"locality",
    "wof:population":2495
},
  "geometry": {"coordinates":[80.145276,27.214036],"type":"Point"}
}