{
  "type": "Feature",
  "properties": {
    "iso:country":"IN",
    "ks:ks_name":"Movadi",
    "ks:ks_pop":300,
    "ks:ks_type":"HABITATION",
    "name:eng_x_preferred":[
        "Movadi"
    ],
    "wof:name":"Movadi",
    "wof:placetype":"locality",
    "wof:population":300
},
  "geometry": {"coordinates":[74.661226,13.711734],"type":"Point"}
}