{
  "type": "Feature",
  "properties": {
    "gn:admin1_code":"21.0",
    "gn:admin2_code":"396.0",
    "gn:asciiname":"Srikhondi",
    "gn:country_code":"IN",
    "gn:dem":180,
    "gn:feature_class":"P",
    "gn:feature_code":"PPL",
    "gn:name":"Sr\u012bkhondi",
    "gn:population":0,
    "gn:timezone":"Asia/Kolkata",
    "iso:country":"IN",
    "ks:ks_name":"Sirikhandi",
    "ks:ks_pop":106,
    "ks:ks_type":"VILLAGE",
    "name:eng_x_preferred":[
        "Sirikhandi"
    ],
    "name:eng_x_variant":[
        "Srikhondi"
    ],
    "wof:name":"Sirikhandi",
    "wof:placetype":"locality",
    "wof:population":106
},
  "geometry": {"coordinates":[83.7246,19.275569],"type":"Point"}
}