{
  "type": "Feature",
  "properties": {
    "iso:country":"IN",
    "ks:ks_name":"Chinabarigam",
    "ks:ks_pop":198,
    "ks:ks_type":"HABITATION",
    "name:eng_x_preferred":[
        "Chinabarigam"
    ],
    "wof:name":"Chinabarigam",
    "wof:placetype":"locality",
    "wof:population":198
},
  "geometry": {"coordinates":[83.102895,18.602491],"type":"Point"}
}