{
  "type": "Feature",
  "properties": {
    "gn:admin1_code":"37",
    "gn:admin2_code":"401.0",
    "gn:asciiname":"Chumra",
    "gn:country_code":"IN",
    "gn:dem":430,
    "gn:feature_class":"P",
    "gn:feature_code":"PPL",
    "gn:name":"Chumr\u0101",
    "gn:population":0,
    "gn:timezone":"Asia/Kolkata",
    "iso:country":"IN",
    "ks:ks_name":"Chumra",
    "ks:ks_pop":1316,
    "ks:ks_type":"VILLAGE",
    "name:eng_x_preferred":[
        "Chumra"
    ],
    "wof:name":"Chumra",
    "wof:placetype":"locality",
    "wof:population":1316
},
  "geometry": {"coordinates":[83.530681,23.764077],"type":"Point"}
}