{
  "type": "Feature",
  "properties": {
    "gn:admin1_code":"37",
    "gn:admin2_code":"401.0",
    "gn:asciiname":"Chumra",
    "gn:country_code":"IN",
    "gn:dem":430,
    "gn:feature_class":"P",
    "gn:feature_code":"PPL",
    "gn:name":"Chumr\u0101",
    "gn:population":0,
    "gn:timezone":"Asia/Kolkata",
    "iso:country":"IN",
    "wof:name":"Chumra",
    "wof:placetype":"locality"
},
  "geometry": {"coordinates":[83.52349,23.78177],"type":"Point"}
}