{
  "type": "Feature",
  "properties": {
    "iso:country":"IN",
    "ks:ks_name":"Phitko",
    "ks:ks_pop":0,
    "ks:ks_type":"VILLAGE",
    "name:eng_x_preferred":[
        "Phitko"
    ],
    "wof:name":"Phitko",
    "wof:placetype":"locality",
    "wof:population":0
},
  "geometry": {"coordinates":[84.36695400000001,25.221395],"type":"Point"}
}