{
  "type": "Feature",
  "properties": {
    "gn:admin1_code":"36",
    "gn:admin2_code":"148.0",
    "gn:asciiname":"Anuppur",
    "gn:country_code":"IN",
    "gn:dem":155,
    "gn:feature_class":"P",
    "gn:feature_code":"PPL",
    "gn:name":"An\u016bppur",
    "gn:population":0,
    "gn:timezone":"Asia/Kolkata",
    "iso:country":"IN",
    "name:ben_x_preferred":[
        "\u0985\u09a8\u09c1\u09aa\u09aa\u09c1\u09b0"
    ],
    "name:bpy_x_preferred":[
        "\u0985\u09a8\u09c1\u09aa\u09aa\u09c1\u09b0"
    ],
    "name:ceb_x_preferred":[
        "An\u016bppur"
    ],
    "name:fra_x_preferred":[
        "Anuppur"
    ],
    "name:guj_x_preferred":[
        "\u0a85\u0aa8\u0ac2\u0aaa\u0aaa\u0ac1\u0ab0"
    ],
    "name:hin_x_preferred":[
        "\u0905\u0928\u0942\u092a\u092a\u0941\u0930"
    ],
    "name:ind_x_preferred":[
        "Anuppur"
    ],
    "name:ita_x_preferred":[
        "Anuppur"
    ],
    "name:jpn_x_preferred":[
        "\u30a2\u30cc\u30fc\u30d7\u30d7\u30eb"
    ],
    "name:mar_x_preferred":[
        "\u0905\u0928\u0941\u092a\u092a\u0942\u0930"
    ],
    "name:mlg_x_preferred":[
        "Anuppur"
    ],
    "name:msa_x_preferred":[
        "Anuppur"
    ],
    "name:new_x_preferred":[
        "\u0905\u0928\u0941\u092a\u092a\u0941\u0930"
    ],
    "name:pam_x_preferred":[
        "Anuppur"
    ],
    "name:por_x_preferred":[
        "Anuppur"
    ],
    "name:san_x_preferred":[
        "\u0905\u0928\u0942\u092a\u092a\u0941\u0930\u092e\u094d"
    ],
    "name:spa_x_preferred":[
        "Anuppur"
    ],
    "name:swe_x_preferred":[
        "An\u016bppur"
    ],
    "name:urd_x_preferred":[
        "\u0627\u0646\u0648\u067e \u067e\u0648\u0631"
    ],
    "name:vie_x_preferred":[
        "Anuppur"
    ],
    "name:zho_x_preferred":[
        "\u963f\u52aa\u666e\u5c14"
    ],
    "wof:name":"Anuppur",
    "wof:placetype":"locality"
},
  "geometry": {"coordinates":[79.15300000000001,27.05571],"type":"Point"}
}