{
  "type": "Feature",
  "properties": {
    "gn:admin1_code":"36",
    "gn:admin2_code":"178.0",
    "gn:asciiname":"Salona",
    "gn:country_code":"IN",
    "gn:dem":94,
    "gn:feature_class":"P",
    "gn:feature_code":"PPL",
    "gn:name":"Salona",
    "gn:population":0,
    "gn:timezone":"Asia/Kolkata",
    "iso:country":"IN",
    "name:ast_x_preferred":[
        "Salona"
    ],
    "name:bel_x_preferred":[
        "\u0421\u0430\u043b\u043e\u043d\u0430"
    ],
    "name:bos_x_preferred":[
        "Salona"
    ],
    "name:bul_x_preferred":[
        "\u0421\u0430\u043b\u043e\u043d\u0430"
    ],
    "name:cat_x_preferred":[
        "Salona"
    ],
    "name:deu_x_preferred":[
        "Salona"
    ],
    "name:ell_x_preferred":[
        "\u03a3\u03b1\u03bb\u03ce\u03bd\u03b1"
    ],
    "name:eus_x_preferred":[
        "Salona"
    ],
    "name:fas_x_preferred":[
        "\u0633\u0627\u0644\u0648\u0646\u0627"
    ],
    "name:fra_x_preferred":[
        "Salone"
    ],
    "name:hrv_x_preferred":[
        "Salona"
    ],
    "name:ind_x_preferred":[
        "Salona"
    ],
    "name:jpn_x_preferred":[
        "\u30b5\u30ed\u30ca"
    ],
    "name:kat_x_preferred":[
        "\u10e1\u10d0\u10da\u10dd\u10dc\u10d0"
    ],
    "name:kaz_x_preferred":[
        "\u0421\u0430\u043b\u043e\u043d\u0430"
    ],
    "name:nor_x_preferred":[
        "Salona"
    ],
    "name:rus_x_preferred":[
        "\u0421\u0430\u043b\u043e\u043d\u0430"
    ],
    "name:spa_x_preferred":[
        "Salona"
    ],
    "name:srp_x_preferred":[
        "\u0421\u0430\u043b\u043e\u043d\u0430"
    ],
    "name:swe_x_preferred":[
        "Salona"
    ],
    "name:tur_x_preferred":[
        "Salona"
    ],
    "name:zho_x_preferred":[
        "\u85a9\u7f85\u7d0d"
    ],
    "wof:name":"Salona",
    "wof:placetype":"neighbourhood"
},
  "geometry": {"coordinates":[82.54465,26.62308],"type":"Point"}
}