{
  "type": "Feature",
  "properties": {
    "iso:country":"IN",
    "ks:ks_name":"Mela Rajapatti",
    "ks:ks_pop":200,
    "ks:ks_type":"HABITATION",
    "name:eng_x_preferred":[
        "Mela Rajapatti"
    ],
    "wof:name":"Mela Rajapatti",
    "wof:placetype":"locality",
    "wof:population":200
},
  "geometry": {"coordinates":[78.193282,10.575218],"type":"Point"}
}