{
  "type": "Feature",
  "properties": {
    "gn:admin1_code":"24.0",
    "gn:admin2_code":"107.0",
    "gn:asciiname":"Rewansa",
    "gn:country_code":"IN",
    "gn:dem":301,
    "gn:feature_class":"P",
    "gn:feature_code":"PPL",
    "gn:name":"Rew\u0101nsa",
    "gn:population":0,
    "gn:timezone":"Asia/Kolkata",
    "iso:country":"IN",
    "ks:ks_name":"Rewasa",
    "ks:ks_pop":607,
    "ks:ks_type":"VILLAGE",
    "ks:ks_uagg_main":0,
    "name:eng_x_preferred":[
        "Rewasa"
    ],
    "wof:name":"Rewasa",
    "wof:placetype":"neighbourhood",
    "wof:population":607
},
  "geometry": {"coordinates":[76.526768,26.701757],"type":"Point"}
}