{
  "type": "Feature",
  "properties": {
    "iso:country":"IN",
    "ks:ks_name":"Sherpur Bahori",
    "ks:ks_pop":997,
    "ks:ks_type":"VILLAGE",
    "name:eng_x_preferred":[
        "Sherpur Bahori"
    ],
    "wof:name":"Sherpur Bahori",
    "wof:placetype":"locality",
    "wof:population":997
},
  "geometry": {"coordinates":[85.44784199999999,25.76179],"type":"Point"}
}