{
  "type": "Feature",
  "properties": {
    "gn:admin1_code":"36",
    "gn:admin2_code":"143.0",
    "gn:asciiname":"Chandwa Gobardhanpur",
    "gn:country_code":"IN",
    "gn:dem":184,
    "gn:feature_class":"P",
    "gn:feature_code":"PPL",
    "gn:name":"Chandwa Gobardhanp\u016br",
    "gn:population":0,
    "gn:timezone":"Asia/Kolkata",
    "iso:country":"IN",
    "wof:name":"Chandwa Gobardhanpur",
    "wof:placetype":"locality"
},
  "geometry": {"coordinates":[78.37928000000002,28.00079],"type":"Point"}
}