{
  "type": "Feature",
  "properties": {
    "iso:country":"IN",
    "ks:ks_alt_nam":"Purwa kothar 309",
    "ks:ks_name":"Purwa Kothar 309",
    "ks:ks_pop":589,
    "ks:ks_type":"HABITATION",
    "name:eng_x_preferred":[
        "Purwa Kothar 309"
    ],
    "wof:name":"Purwa Kothar 309",
    "wof:placetype":"locality",
    "wof:population":589
},
  "geometry": {"coordinates":[81.616079,24.729287],"type":"Point"}
}