{
  "type": "Feature",
  "properties": {
    "iso:country":"IN",
    "ks:ks_name":"Surappanahatty",
    "ks:ks_pop":249,
    "ks:ks_type":"HABITATION",
    "name:eng_x_preferred":[
        "Surappanahatty"
    ],
    "wof:name":"Surappanahatty",
    "wof:placetype":"locality",
    "wof:population":249
},
  "geometry": {"coordinates":[76.632749,13.740854],"type":"Point"}
}