{
  "type": "Feature",
  "properties": {
    "iso:country":"IN",
    "name:ara_x_preferred":[
        "\u0631\u0627\u0645 \u0628\u0627\u062c"
    ],
    "name:ben_bn_x_preferred":[
        "\u09b0\u09be\u09ae \u09ac\u09be\u0997"
    ],
    "name:ben_in_x_preferred":[
        "\u09b0\u09be\u09ae \u09ac\u09be\u0997"
    ],
    "name:eng_x_preferred":[
        "Ram Bag"
    ],
    "name:guj_x_preferred":[
        "\u0ab0\u0abe\u0aae \u0aac\u0abe\u0a97"
    ],
    "name:hin_x_preferred":[
        "\u0930\u093e\u092e \u092c\u093e\u0917"
    ],
    "name:kan_x_preferred":[
        "\u0cb0\u0cbe\u0cae\u0ccd \u0cac\u0cbe\u0c97\u0ccd"
    ],
    "name:mal_x_preferred":[
        "\u0d31\u0d3e\u0d02 \u0d2c\u0d3e\u0d17\u0d4d"
    ],
    "name:mar_x_preferred":[
        "\u0930\u093e\u092e \u092c\u093e\u0917"
    ],
    "name:pan_x_preferred":[
        "\u0a30\u0a3e\u0a2e \u0a2c\u0a3e\u0a17"
    ],
    "name:tam_x_preferred":[
        "\u0bb0\u0bbe\u0bae\u0bcd \u0baa\u0bbe\u0b95\u0bcd"
    ],
    "name:tel_x_preferred":[
        "\u0c30\u0c3e\u0c02 \u0c2c\u0c3e\u0c17\u0c4d"
    ],
    "name:urd_x_preferred":[
        "\u0631\u0627\u0645 \u0628\u0627\u063a"
    ],
    "qs:gn_adm0_cc":"IN",
    "qs:gn_local":1263370,
    "qs:gn_nam_loc":"matheran",
    "qs:gn_namadm1":"16",
    "qs:local_max":619,
    "qs:local_sum":636,
    "qs:localhoods":2,
    "qs:name":"Ram Bag",
    "qs:name_adm0":"India",
    "qs:name_adm1":"Maharashtra",
    "qs:name_adm2":"Raigarh",
    "qs:name_local":"Matheran",
    "qs:photo_max":9,
    "qs:photo_sum":17,
    "qs:placetype":"Suburb",
    "qs:quad_count":4,
    "qs:woe_adm0":23424848,
    "qs:woe_adm1":2345750,
    "qs:woe_adm2":12586545,
    "qs:woe_lau":0,
    "qs:woe_local":2292981,
    "qs:woe_ver":"7.10.0",
    "wof:lang":[
        "eng"
    ],
    "wof:name":"Ram Bag",
    "wof:placetype":"neighbourhood"
},
  "geometry": {"coordinates":[73.263459,18.970622],"type":"Point"}
}