{
  "type": "Feature",
  "properties": {
    "iso:country":"IN",
    "name:eng_x_preferred":[
        "Ram Bag"
    ],
    "qs:gn_adm0_cc":"IN",
    "qs:gn_local":1263370,
    "qs:gn_nam_loc":"matheran",
    "qs:gn_namadm1":"16",
    "qs:local_max":619,
    "qs:local_sum":636,
    "qs:localhoods":2,
    "qs:name":"Ram Bag",
    "qs:name_adm0":"India",
    "qs:name_adm1":"Maharashtra",
    "qs:name_adm2":"Raigarh",
    "qs:name_local":"Matheran",
    "qs:photo_max":9,
    "qs:photo_sum":17,
    "qs:placetype":"Suburb",
    "qs:quad_count":4,
    "qs:woe_adm0":23424848,
    "qs:woe_adm1":2345750,
    "qs:woe_adm2":12586545,
    "qs:woe_lau":0,
    "qs:woe_local":2292981,
    "qs:woe_ver":"7.10.0",
    "wof:lang":[
        "eng"
    ],
    "wof:name":"Ram Bag",
    "wof:placetype":"neighbourhood"
},
  "geometry": {"coordinates":[73.263459,18.970622],"type":"Point"}
}