{
  "type": "Feature",
  "properties": {
    "gn:admin1_code":"11.0",
    "gn:admin2_code":"24.0",
    "gn:asciiname":"Denkwan",
    "gn:country_code":"IN",
    "gn:dem":404,
    "gn:feature_class":"P",
    "gn:feature_code":"PPL",
    "gn:name":"Denkw\u0101n",
    "gn:population":0,
    "gn:timezone":"Asia/Kolkata",
    "iso:country":"IN",
    "wof:name":"Denkwan",
    "wof:placetype":"locality"
},
  "geometry": {"coordinates":[75.74601,32.23673],"type":"Point"}
}