{
  "type": "Feature",
  "properties": {
    "iso:country":"IN",
    "ks:ks_name":"Sarihakuchi",
    "ks:ks_pop":613,
    "ks:ks_type":"VILLAGE",
    "name:eng_x_preferred":[
        "Sarihakuchi"
    ],
    "wof:name":"Sarihakuchi",
    "wof:placetype":"locality",
    "wof:population":613
},
  "geometry": {"coordinates":[91.158728,26.312281],"type":"Point"}
}