{
  "type": "Feature",
  "properties": {
    "iso:country":"IN",
    "ks:ks_name":"Rajepur Shadipur",
    "ks:ks_pop":885,
    "ks:ks_type":"VILLAGE",
    "name:eng_x_preferred":[
        "Rajepur Shadipur"
    ],
    "wof:name":"Rajepur Shadipur",
    "wof:placetype":"locality",
    "wof:population":885
},
  "geometry": {"coordinates":[80.1725,26.696111],"type":"Point"}
}