{
  "type": "Feature",
  "properties": {
    "iso:country":"IN",
    "ks:ks_alt_nam":"KATHAUTIA",
    "ks:ks_name":"Kathautia",
    "ks:ks_pop":728,
    "ks:ks_type":"HABITATION",
    "name:eng_x_preferred":[
        "Kathautia"
    ],
    "wof:name":"Kathautia",
    "wof:placetype":"locality",
    "wof:population":728
},
  "geometry": {"coordinates":[84.845322,24.211575],"type":"Point"}
}