{
  "type": "Feature",
  "properties": {
    "iso:country":"IN",
    "ks:ks_name":"Naikurijagannath Chak-I",
    "ks:ks_pop":1678,
    "ks:ks_type":"VILLAGE",
    "name:eng_x_preferred":[
        "Naikurijagannath Chak-I"
    ],
    "wof:name":"Naikurijagannath Chak-I",
    "wof:placetype":"locality",
    "wof:population":1678
},
  "geometry": {"coordinates":[87.848724,22.319068],"type":"Point"}
}