{
  "type": "Feature",
  "properties": {
    "iso:country":"IN",
    "ks:ks_name":"Malgujarpara",
    "ks:ks_pop":491,
    "ks:ks_type":"HABITATION",
    "name:eng_x_preferred":[
        "Malgujarpara"
    ],
    "wof:name":"Malgujarpara",
    "wof:placetype":"locality",
    "wof:population":491
},
  "geometry": {"coordinates":[81.610437,19.428252],"type":"Point"}
}