{
  "type": "Feature",
  "properties": {
    "iso:country":"IN",
    "ks:ks_name":"Pindaran",
    "ks:ks_pop":632,
    "ks:ks_type":"VILLAGE",
    "name:eng_x_preferred":[
        "Pindaran"
    ],
    "wof:name":"Pindaran",
    "wof:placetype":"locality",
    "wof:population":632
},
  "geometry": {"coordinates":[72.53170799999999,25.927783],"type":"Point"}
}