{
  "type": "Feature",
  "properties": {
    "gn:admin1_code":"11",
    "gn:admin2_code":"23.0",
    "gn:asciiname":"Takwas",
    "gn:country_code":"IN",
    "gn:dem":3134,
    "gn:feature_class":"P",
    "gn:feature_code":"PPL",
    "gn:name":"Takw\u0101s",
    "gn:population":0,
    "gn:timezone":"Asia/Kolkata",
    "iso:country":"IN",
    "wof:name":"Takwas",
    "wof:placetype":"locality"
},
  "geometry": {"coordinates":[76.44173000000001,33.08664],"type":"Point"}
}