{
  "type": "Feature",
  "properties": {
    "iso:country":"IN",
    "ks:ks_name":"Hansali",
    "ks:ks_pop":233,
    "ks:ks_type":"HABITATION",
    "name:eng_x_preferred":[
        "Hansali"
    ],
    "wof:name":"Hansali",
    "wof:placetype":"locality",
    "wof:population":233
},
  "geometry": {"coordinates":[77.914162,24.338277],"type":"Point"}
}