{
  "type": "Feature",
  "properties": {
    "gn:admin1_code":"12.0",
    "gn:admin2_code":"16.0",
    "gn:asciiname":"Kako",
    "gn:country_code":"IN",
    "gn:dem":2064,
    "gn:feature_class":"P",
    "gn:feature_code":"PPL",
    "gn:name":"K\u0101k\u014d",
    "gn:population":0,
    "gn:timezone":"Asia/Kolkata",
    "iso:country":"IN",
    "name:ceb_x_preferred":[
        "Kako"
    ],
    "name:deu_x_preferred":[
        "Kako"
    ],
    "name:epo_x_preferred":[
        "Kako"
    ],
    "name:est_x_preferred":[
        "Kako"
    ],
    "name:fra_x_preferred":[
        "Kako"
    ],
    "name:ita_x_preferred":[
        "Kako"
    ],
    "name:spa_x_preferred":[
        "Kako"
    ],
    "name:swe_x_preferred":[
        "Kako"
    ],
    "wof:name":"Kako",
    "wof:placetype":"locality"
},
  "geometry": {"coordinates":[75.93056,33.00145],"type":"Point"}
}