{
  "type": "Feature",
  "properties": {
    "gn:admin1_code":"36",
    "gn:admin2_code":"134.0",
    "gn:asciiname":"Mukarpur Gujar",
    "gn:country_code":"IN",
    "gn:dem":232,
    "gn:feature_class":"P",
    "gn:feature_code":"PPL",
    "gn:name":"Mukarpur Gujar",
    "gn:population":0,
    "gn:timezone":"Asia/Kolkata",
    "iso:country":"IN",
    "wof:name":"Mukarpur Gujar",
    "wof:placetype":"locality"
},
  "geometry": {"coordinates":[78.18883000000002,29.23936],"type":"Point"}
}