{
  "type": "Feature",
  "properties": {
    "gn:admin1_code":"11",
    "gn:admin2_code":"23.0",
    "gn:asciiname":"Kalo-ka-Bhandar",
    "gn:country_code":"IN",
    "gn:dem":4672,
    "gn:feature_class":"P",
    "gn:feature_code":"PPL",
    "gn:name":"K\u0101lo-ka-Bhand\u0101r",
    "gn:population":0,
    "gn:timezone":"Asia/Kolkata",
    "iso:country":"IN",
    "wof:name":"Kalo-ka-Bhandar",
    "wof:placetype":"locality"
},
  "geometry": {"coordinates":[76.37509,32.82037],"type":"Point"}
}