{
  "type": "Feature",
  "properties": {
    "iso:country":"IN",
    "ks:ks_name":"Mallamkunnu",
    "ks:ks_pop":882,
    "ks:ks_type":"HABITATION",
    "name:eng_x_preferred":[
        "Mallamkunnu"
    ],
    "wof:name":"Mallamkunnu",
    "wof:placetype":"locality",
    "wof:population":882
},
  "geometry": {"coordinates":[76.485292,10.704295],"type":"Point"}
}