{
  "type": "Feature",
  "properties": {
    "iso:country":"IN",
    "ks:ks_name":"Galupada",
    "ks:ks_pop":1021,
    "ks:ks_type":"HABITATION",
    "name:eng_x_preferred":[
        "Galupada"
    ],
    "wof:name":"Galupada",
    "wof:placetype":"locality",
    "wof:population":1021
},
  "geometry": {"coordinates":[86.161151,20.248681],"type":"Point"}
}