{
  "type": "Feature",
  "properties": {
    "gn:admin1_code":"40",
    "gn:admin2_code":"537.0",
    "gn:asciiname":"Malaguduru",
    "gn:country_code":"IN",
    "gn:dem":620,
    "gn:feature_class":"P",
    "gn:feature_code":"PPL",
    "gn:name":"M\u0101lag\u016bd\u016bru",
    "gn:population":0,
    "gn:timezone":"Asia/Kolkata",
    "iso:country":"IN",
    "wof:name":"Malaguduru",
    "wof:placetype":"locality"
},
  "geometry": {"coordinates":[78.50157,17.08387999999999],"type":"Point"}
}