{
  "type": "Feature",
  "properties": {
    "iso:country":"IN",
    "ks:ks_name":"Laglesrapur",
    "ks:ks_pop":420,
    "ks:ks_type":"VILLAGE",
    "ks:ks_uagg_main":0,
    "name:eng_x_preferred":[
        "Laglesrapur"
    ],
    "wof:name":"Laglesrapur",
    "wof:placetype":"neighbourhood",
    "wof:population":420
},
  "geometry": {"coordinates":[80.492143,26.712391],"type":"Point"}
}