{
  "type": "Feature",
  "properties": {
    "iso:country":"IN",
    "ks:ks_name":"Olakana",
    "ks:ks_pop":1412,
    "ks:ks_type":"VILLAGE",
    "name:eng_x_preferred":[
        "Olakana"
    ],
    "wof:name":"Olakana",
    "wof:placetype":"locality",
    "wof:population":1412
},
  "geometry": {"coordinates":[86.270291,20.568771],"type":"Point"}
}