{
  "type": "Feature",
  "properties": {
    "gn:admin1_code":"36",
    "gn:admin2_code":"188.0",
    "gn:asciiname":"Panrpurwa Arazi",
    "gn:country_code":"IN",
    "gn:dem":80,
    "gn:feature_class":"P",
    "gn:feature_code":"PPL",
    "gn:name":"Panrpurwa Ar\u0101zi",
    "gn:population":0,
    "gn:timezone":"Asia/Kolkata",
    "iso:country":"IN",
    "wof:name":"Panrpurwa Arazi",
    "wof:placetype":"locality"
},
  "geometry": {"coordinates":[83.41942,26.52414000000001],"type":"Point"}
}