{
  "type": "Feature",
  "properties": {
    "iso:country":"IN",
    "ks:ks_name":"Avarankadu",
    "ks:ks_pop":112,
    "ks:ks_type":"HABITATION",
    "ks:ks_uagg_main":0,
    "name:eng_x_preferred":[
        "Avarankadu"
    ],
    "wof:name":"Avarankadu",
    "wof:placetype":"neighbourhood",
    "wof:population":112
},
  "geometry": {"coordinates":[78.784685,10.231206],"type":"Point"}
}