{
  "type": "Feature",
  "properties": {
    "gn:admin1_code":"35.0",
    "gn:asciiname":"Bedar",
    "gn:country_code":"IN",
    "gn:dem":418,
    "gn:feature_class":"P",
    "gn:feature_code":"PPL",
    "gn:name":"Bedar",
    "gn:population":0,
    "gn:timezone":"Asia/Kolkata",
    "iso:country":"IN",
    "name:ceb_x_preferred":[
        "Bedar"
    ],
    "name:swe_x_preferred":[
        "Bedar"
    ],
    "wof:name":"Bedar",
    "wof:placetype":"neighbourhood"
},
  "geometry": {"coordinates":[76.61776999999999,24.25437],"type":"Point"}
}