{
  "type": "Feature",
  "properties": {
    "iso:country":"IN",
    "ks:ks_name":"Phondipada",
    "ks:ks_pop":107,
    "ks:ks_type":"HABITATION",
    "name:eng_x_preferred":[
        "Phondipada"
    ],
    "wof:name":"Phondipada",
    "wof:placetype":"locality",
    "wof:population":107
},
  "geometry": {"coordinates":[72.942843,19.667686],"type":"Point"}
}