{
  "type": "Feature",
  "properties": {
    "gn:admin1_code":"36",
    "gn:admin2_code":"154.0",
    "gn:asciiname":"Daulatpur",
    "gn:country_code":"IN",
    "gn:dem":135,
    "gn:feature_class":"P",
    "gn:feature_code":"PPL",
    "gn:name":"Daulatpur",
    "gn:population":0,
    "gn:timezone":"Asia/Kolkata",
    "iso:country":"IN",
    "wof:name":"Daulatpur",
    "wof:placetype":"locality"
},
  "geometry": {"coordinates":[81.00729,27.29214],"type":"Point"}
}