{
  "type": "Feature",
  "properties": {
    "iso:country":"IN",
    "ks:ks_name":"Pure Naranga",
    "ks:ks_pop":135,
    "ks:ks_type":"HABITATION",
    "name:eng_x_preferred":[
        "Pure Naranga"
    ],
    "wof:name":"Pure Naranga",
    "wof:placetype":"locality",
    "wof:population":135
},
  "geometry": {"coordinates":[82.40646,26.846762],"type":"Point"}
}