{
  "type": "Feature",
  "properties": {
    "gn:admin1_code":"23.0",
    "gn:admin2_code":"50.0",
    "gn:asciiname":"Zunardan",
    "gn:country_code":"IN",
    "gn:dem":220,
    "gn:feature_class":"P",
    "gn:feature_code":"PPL",
    "gn:name":"Zun\u0101rd\u0101n",
    "gn:population":0,
    "gn:timezone":"Asia/Kolkata",
    "iso:country":"IN",
    "wof:name":"Zunardan",
    "wof:placetype":"locality"
},
  "geometry": {"coordinates":[74.89489,31.25688],"type":"Point"}
}