{
  "type": "Feature",
  "properties": {
    "gn:admin1_code":"23.0",
    "gn:admin2_code":"50.0",
    "gn:asciiname":"Zunardan",
    "gn:country_code":"IN",
    "gn:dem":220,
    "gn:feature_class":"P",
    "gn:feature_code":"PPL",
    "gn:name":"Zun\u0101rd\u0101n",
    "gn:population":0,
    "gn:timezone":"Asia/Kolkata",
    "iso:country":"IN",
    "ks:ks_alt_nam":"Zun\u0101rd\u0101n",
    "ks:ks_name":"Zunardan",
    "ks:ks_type":"VILLAGE",
    "name:eng_x_preferred":[
        "Zunardan"
    ],
    "name:eng_x_variant":[
        "Zun\u0101rd\u0101n"
    ],
    "wof:name":"Zunardan",
    "wof:placetype":"locality"
},
  "geometry": {"coordinates":[74.89489399999999,31.256881],"type":"Point"}
}