{
  "type": "Feature",
  "properties": {
    "gn:admin1_code":"9.0",
    "gn:admin2_code":"493.0",
    "gn:asciiname":"Balamba",
    "gn:country_code":"IN",
    "gn:dem":123,
    "gn:feature_class":"P",
    "gn:feature_code":"PPL",
    "gn:name":"B\u0101l\u0101mba",
    "gn:population":0,
    "gn:timezone":"Asia/Kolkata",
    "iso:country":"IN",
    "name:fra_x_preferred":[
        "Balamba"
    ],
    "wof:name":"Balamba",
    "wof:placetype":"locality"
},
  "geometry": {"coordinates":[74.0685,21.54119],"type":"Point"}
}