{
  "type": "Feature",
  "properties": {
    "gn:admin1_code":"9.0",
    "gn:admin2_code":"493.0",
    "gn:asciiname":"Balamba",
    "gn:country_code":"IN",
    "gn:dem":123,
    "gn:feature_class":"P",
    "gn:feature_code":"PPL",
    "gn:name":"B\u0101l\u0101mba",
    "gn:population":0,
    "gn:timezone":"Asia/Kolkata",
    "iso:country":"IN",
    "ks:ks_name":"Balambe",
    "ks:ks_pop":4419,
    "ks:ks_type":"VILLAGE",
    "name:eng_x_preferred":[
        "Balambe"
    ],
    "name:eng_x_variant":[
        "Balamba"
    ],
    "name:fra_x_preferred":[
        "Balamba"
    ],
    "wof:name":"Balambe",
    "wof:placetype":"locality",
    "wof:population":4419
},
  "geometry": {"coordinates":[74.071313,21.543902],"type":"Point"}
}