{
  "type": "Feature",
  "properties": {
    "iso:country":"IN",
    "ks:ks_alt_nam":"BICH TOLA",
    "ks:ks_name":"Bich Tola",
    "ks:ks_pop":197,
    "ks:ks_type":"HABITATION",
    "ks:ks_uagg_main":0,
    "name:eng_x_preferred":[
        "Bich Tola"
    ],
    "wof:name":"Bich Tola",
    "wof:placetype":"neighbourhood",
    "wof:population":197
},
  "geometry": {"coordinates":[87.35778000000001,25.909707],"type":"Point"}
}