{
  "type": "Feature",
  "properties": {
    "iso:country":"IN",
    "ks:ks_name":"Puttanna Nagara",
    "ks:ks_pop":270,
    "ks:ks_type":"HABITATION",
    "name:eng_x_preferred":[
        "Puttanna Nagara"
    ],
    "wof:name":"Puttanna Nagara",
    "wof:placetype":"locality",
    "wof:population":270
},
  "geometry": {"coordinates":[75.720111,13.893603],"type":"Point"}
}