{
  "type": "Feature",
  "properties": {
    "gn:admin1_code":"16",
    "gn:admin2_code":"502.0",
    "gn:asciiname":"Rudrala",
    "gn:country_code":"IN",
    "gn:dem":446,
    "gn:feature_class":"P",
    "gn:feature_code":"PPL",
    "gn:name":"Rudr\u0101la",
    "gn:population":0,
    "gn:timezone":"Asia/Kolkata",
    "iso:country":"IN",
    "name:und_x_variant":[
        "Rudr\u0101la",
        "Khapri"
    ],
    "wof:name":"Rudrala",
    "wof:placetype":"locality"
},
  "geometry": {"coordinates":[77.51206999999999,20.33373],"type":"Point"}
}