{
  "type": "Feature",
  "properties": {
    "gn:admin1_code":"9.0",
    "gn:admin2_code":"484.0",
    "gn:asciiname":"Ratanpur Kanbiwala",
    "gn:country_code":"IN",
    "gn:dem":166,
    "gn:feature_class":"P",
    "gn:feature_code":"PPL",
    "gn:name":"Ratanpur Kanbiw\u0101la",
    "gn:population":0,
    "gn:timezone":"Asia/Kolkata",
    "iso:country":"IN",
    "wof:name":"Ratanpur Kanbiwala",
    "wof:placetype":"neighbourhood"
},
  "geometry": {"coordinates":[73.95654999999999,23.13622],"type":"Point"}
}