{
  "type": "Feature",
  "properties": {
    "iso:country":"IN",
    "ks:ks_name":"Peedikappari",
    "ks:ks_pop":90,
    "ks:ks_type":"HABITATION",
    "name:eng_x_preferred":[
        "Peedikappari"
    ],
    "wof:name":"Peedikappari",
    "wof:placetype":"locality",
    "wof:population":90
},
  "geometry": {"coordinates":[76.83749,9.291205],"type":"Point"}
}