{
  "type": "Feature",
  "properties": {
    "iso:country":"IN",
    "ks:ks_name":"Katchalavada",
    "ks:ks_pop":68,
    "ks:ks_type":"VILLAGE",
    "name:eng_x_preferred":[
        "Katchalavada"
    ],
    "wof:name":"Katchalavada",
    "wof:placetype":"locality",
    "wof:population":68
},
  "geometry": {"coordinates":[81.725146,17.735713],"type":"Point"}
}