{
  "type": "Feature",
  "properties": {
    "iso:country":"IN",
    "ks:ks_alt_nam":"Massandoba FV",
    "ks:ks_name":"Massandoba Fv",
    "ks:ks_pop":173,
    "ks:ks_type":"HABITATION",
    "name:eng_x_preferred":[
        "Massandoba Fv"
    ],
    "wof:name":"Massandoba Fv",
    "wof:placetype":"locality",
    "wof:population":173
},
  "geometry": {"coordinates":[89.927392,26.386809],"type":"Point"}
}