{
  "type": "Feature",
  "properties": {
    "iso:country":"IN",
    "ks:ks_name":"Balarampur",
    "ks:ks_pop":33,
    "ks:ks_type":"VILLAGE",
    "name:eng_x_preferred":[
        "Balarampur"
    ],
    "wof:name":"Balarampur",
    "wof:placetype":"locality",
    "wof:population":33
},
  "geometry": {"coordinates":[87.175588,21.734913],"type":"Point"}
}