{
  "type": "Feature",
  "properties": {
    "iso:country":"IN",
    "ks:ks_name":"Usran",
    "ks:ks_pop":214,
    "ks:ks_type":"VILLAGE",
    "name:eng_x_preferred":[
        "Usran"
    ],
    "wof:name":"Usran",
    "wof:placetype":"locality",
    "wof:population":214
},
  "geometry": {"coordinates":[73.739718,19.252653],"type":"Point"}
}