{
  "type": "Feature",
  "properties": {
    "iso:country":"IN",
    "ks:ks_name":"Tandola",
    "ks:ks_pop":140,
    "ks:ks_type":"VILLAGE",
    "name:eng_x_preferred":[
        "Tandola"
    ],
    "wof:name":"Tandola",
    "wof:placetype":"locality",
    "wof:population":140
},
  "geometry": {"coordinates":[80.12720400000001,28.357307],"type":"Point"}
}