{
  "type": "Feature",
  "properties": {
    "iso:country":"IN",
    "ks:ks_name":"Patrimetta",
    "ks:ks_pop":127,
    "ks:ks_type":"VILLAGE",
    "name:eng_x_preferred":[
        "Patrimetta"
    ],
    "wof:name":"Patrimetta",
    "wof:placetype":"locality",
    "wof:population":127
},
  "geometry": {"coordinates":[82.765156,18.175218],"type":"Point"}
}