{
  "type": "Feature",
  "properties": {
    "gn:admin1_code":"12.0",
    "gn:admin2_code":"009",
    "gn:asciiname":"Nathipur",
    "gn:country_code":"IN",
    "gn:dem":1590,
    "gn:feature_class":"P",
    "gn:feature_code":"PPL",
    "gn:name":"Nathipur",
    "gn:population":0,
    "gn:timezone":"Asia/Kolkata",
    "iso:country":"IN",
    "wof:name":"Nathipur",
    "wof:placetype":"locality"
},
  "geometry": {"coordinates":[74.38965,34.36462],"type":"Point"}
}