{
  "type": "Feature",
  "properties": {
    "iso:country":"IN",
    "ks:ks_name":"Chamdhara",
    "ks:ks_pop":512,
    "ks:ks_type":"VILLAGE",
    "ks:ks_uagg_main":0,
    "name:eng_x_preferred":[
        "Chamdhara"
    ],
    "wof:name":"Chamdhara",
    "wof:placetype":"neighbourhood",
    "wof:population":512
},
  "geometry": {"coordinates":[92.90446900000001,26.777141],"type":"Point"}
}