{
  "type": "Feature",
  "properties": {
    "gn:admin1_code":"36",
    "gn:admin2_code":"135.0",
    "gn:asciiname":"Wilayatnagar",
    "gn:country_code":"IN",
    "gn:dem":215,
    "gn:feature_class":"P",
    "gn:feature_code":"PPL",
    "gn:name":"Wil\u0101yatnagar",
    "gn:population":0,
    "gn:timezone":"Asia/Kolkata",
    "iso:country":"IN",
    "name:und_x_variant":[
        "Wil\u0101yatnagar",
        "Budhanpur"
    ],
    "wof:name":"Wilayatnagar",
    "wof:placetype":"locality"
},
  "geometry": {"coordinates":[78.58181999999999,29.0304],"type":"Point"}
}