{
  "type": "Feature",
  "properties": {
    "gn:admin1_code":"36",
    "gn:admin2_code":"153.0",
    "gn:asciiname":"Sahibnagar",
    "gn:country_code":"IN",
    "gn:dem":132,
    "gn:feature_class":"P",
    "gn:feature_code":"PPL",
    "gn:name":"S\u0101hibnagar",
    "gn:population":0,
    "gn:timezone":"Asia/Kolkata",
    "iso:country":"IN",
    "name:fas_x_preferred":[
        "\u0633\u0647\u06cc\u0628\u200c\u0646\u06af\u0631"
    ],
    "name:urd_x_preferred":[
        "\u0633\u06c1\u06cc\u0628\u0646\u06af\u0631"
    ],
    "wof:name":"Sahibnagar",
    "wof:placetype":"locality"
},
  "geometry": {"coordinates":[81.10404,27.86975],"type":"Point"}
}