{
  "type": "Feature",
  "properties": {
    "iso:country":"IN",
    "ks:ks_name":"Korpos",
    "ks:ks_pop":6,
    "ks:ks_type":"VILLAGE",
    "name:eng_x_preferred":[
        "Korpos"
    ],
    "wof:name":"Korpos",
    "wof:placetype":"locality",
    "wof:population":6
},
  "geometry": {"coordinates":[85.465953,22.578878],"type":"Point"}
}