{
  "type": "Feature",
  "properties": {
    "iso:country":"IN",
    "ks:ks_name":"Keretattu Area",
    "ks:ks_pop":71,
    "ks:ks_type":"HABITATION",
    "name:eng_x_preferred":[
        "Keretattu Area"
    ],
    "wof:name":"Keretattu Area",
    "wof:placetype":"locality",
    "wof:population":71
},
  "geometry": {"coordinates":[75.67611100000001,12.210833],"type":"Point"}
}