{
  "type": "Feature",
  "properties": {
    "gn:admin1_code":"2.0",
    "gn:asciiname":"Venkatapur",
    "gn:country_code":"IN",
    "gn:dem":331,
    "gn:feature_class":"P",
    "gn:feature_code":"PPL",
    "gn:name":"Venkat\u0101pur",
    "gn:population":0,
    "gn:timezone":"Asia/Kolkata",
    "iso:country":"IN",
    "name:fas_x_preferred":[
        "\u0648\u0646\u06a9\u062a\u067e\u0648\u0631"
    ],
    "wof:name":"Venkatapur",
    "wof:placetype":"locality"
},
  "geometry": {"coordinates":[78.36688000000002,19.06943],"type":"Point"}
}