{
  "type": "Feature",
  "properties": {
    "gn:admin1_code":"35.0",
    "gn:admin2_code":"454.0",
    "gn:asciiname":"Seoni",
    "gn:country_code":"IN",
    "gn:dem":513,
    "gn:feature_class":"P",
    "gn:feature_code":"PPL",
    "gn:name":"Seon\u012b",
    "gn:population":0,
    "gn:timezone":"Asia/Kolkata",
    "iso:country":"IN",
    "ks:ks_name":"Seoni R",
    "ks:ks_pop":880,
    "ks:ks_type":"HABITATION",
    "name:ara_x_preferred":[
        "\u0633\u0648\u0646\u064a"
    ],
    "name:ben_bn_x_preferred":[
        "\u09b8\u09bf\u0993\u09a8\u09bf"
    ],
    "name:ben_in_x_preferred":[
        "\u09b8\u09bf\u0993\u09a8\u09bf"
    ],
    "name:eng_x_preferred":[
        "Seoni R"
    ],
    "name:eng_x_variant":[
        "Seoni"
    ],
    "name:guj_x_preferred":[
        "\u0ab8\u0abf\u0a93\u0aa8\u0ac0"
    ],
    "name:hin_x_preferred":[
        "\u0938\u093f\u092f\u094b\u0928\u0940"
    ],
    "name:kan_x_preferred":[
        "\u0cb8\u0cbf\u0caf\u0ccb\u0ca8\u0cbf"
    ],
    "name:mal_x_preferred":[
        "\u0d38\u0d3f\u0d2f\u0d4b\u0d23\u0d3f"
    ],
    "name:mar_x_preferred":[
        "\u0938\u093f\u0913\u0928\u0940"
    ],
    "name:pan_x_preferred":[
        "\u0a38\u0a3f\u0a13\u0a28\u0a40"
    ],
    "name:tam_x_preferred":[
        "\u0b9a\u0bbf\u0baf\u0bcb\u0ba9\u0bbf"
    ],
    "name:tel_x_preferred":[
        "\u0c38\u0c3f\u0c2f\u0c4b\u0c28\u0c3f"
    ],
    "name:urd_x_preferred":[
        "\u0633\u06cc\u0648\u0646\u06cc"
    ],
    "wof:name":"Seoni R",
    "wof:placetype":"locality",
    "wof:population":880
},
  "geometry": {"coordinates":[80.535766,22.953959],"type":"Point"}
}