{
  "type": "Feature",
  "properties": {
    "iso:country":"IN",
    "ks:ks_alt_nam":"Wetal wasti",
    "ks:ks_name":"Wetal Wasti",
    "ks:ks_pop":339,
    "ks:ks_type":"HABITATION",
    "name:eng_x_preferred":[
        "Wetal Wasti"
    ],
    "wof:name":"Wetal Wasti",
    "wof:placetype":"locality",
    "wof:population":339
},
  "geometry": {"coordinates":[75.36339599999999,19.350666],"type":"Point"}
}