{
  "type": "Feature",
  "properties": {
    "gn:admin1_code":"11",
    "gn:admin2_code":"24.0",
    "gn:asciiname":"Nanwalkor",
    "gn:country_code":"IN",
    "gn:dem":794,
    "gn:feature_class":"P",
    "gn:feature_code":"PPL",
    "gn:name":"Nanw\u0101lkor",
    "gn:population":0,
    "gn:timezone":"Asia/Kolkata",
    "iso:country":"IN",
    "wof:name":"Nanwalkor",
    "wof:placetype":"locality"
},
  "geometry": {"coordinates":[76.45702,31.98377],"type":"Point"}
}