{
  "type": "Feature",
  "properties": {
    "iso:country":"IN",
    "ks:ks_alt_nam":"KHARKATOLA",
    "ks:ks_name":"Kharkatola",
    "ks:ks_pop":534,
    "ks:ks_type":"HABITATION",
    "name:eng_x_preferred":[
        "Kharkatola"
    ],
    "wof:name":"Kharkatola",
    "wof:placetype":"locality",
    "wof:population":534
},
  "geometry": {"coordinates":[82.08118,23.051025],"type":"Point"}
}