{
  "type": "Feature",
  "properties": {
    "iso:country":"IN",
    "ks:ks_name":"Kikkeri",
    "ks:ks_pop":19,
    "ks:ks_type":"HABITATION",
    "name:eng_x_preferred":[
        "Kikkeri"
    ],
    "wof:name":"Kikkeri",
    "wof:placetype":"locality",
    "wof:population":19
},
  "geometry": {"coordinates":[74.640518,14.247619],"type":"Point"}
}