{
  "type": "Feature",
  "properties": {
    "iso:country":"IN",
    "ks:ks_name":"Jhalar Baori",
    "ks:ks_pop":7309,
    "ks:ks_type":"VILLAGE",
    "ks:ks_uagg_main":0,
    "name:eng_x_preferred":[
        "Jhalar Baori"
    ],
    "wof:name":"Jhalar Baori",
    "wof:placetype":"locality",
    "wof:population":7309
},
  "geometry": {"coordinates":[75.619748,24.936688],"type":"Point"}
}