{
  "type": "Feature",
  "properties": {
    "iso:country":"IN",
    "ks:ks_name":"Kelagaddekery",
    "ks:ks_pop":22,
    "ks:ks_type":"HABITATION",
    "name:eng_x_preferred":[
        "Kelagaddekery"
    ],
    "wof:name":"Kelagaddekery",
    "wof:placetype":"locality",
    "wof:population":22
},
  "geometry": {"coordinates":[74.989734,13.492767],"type":"Point"}
}