{
  "type": "Feature",
  "properties": {
    "iso:country":"IN",
    "ks:ks_name":"Kamangi",
    "ks:ks_pop":269,
    "ks:ks_type":"VILLAGE",
    "name:eng_x_preferred":[
        "Kamangi"
    ],
    "wof:name":"Kamangi",
    "wof:placetype":"locality",
    "wof:population":269
},
  "geometry": {"coordinates":[83.957701,20.113689],"type":"Point"}
}