{
  "type": "Feature",
  "properties": {
    "iso:country":"IN",
    "ks:ks_name":"Murtiyapur",
    "ks:ks_pop":523,
    "ks:ks_type":"HABITATION",
    "ks:ks_uagg_main":0,
    "name:eng_x_preferred":[
        "Murtiyapur"
    ],
    "wof:name":"Murtiyapur",
    "wof:placetype":"neighbourhood",
    "wof:population":523
},
  "geometry": {"coordinates":[82.26378800000001,24.818523],"type":"Point"}
}