{
  "type": "Feature",
  "properties": {
    "iso:country":"IN",
    "ks:ks_alt_nam":"dikarbi",
    "ks:ks_name":"Dikarbi",
    "ks:ks_pop":77,
    "ks:ks_type":"HABITATION",
    "name:eng_x_preferred":[
        "Dikarbi"
    ],
    "wof:name":"Dikarbi",
    "wof:placetype":"locality",
    "wof:population":77
},
  "geometry": {"coordinates":[92.819433,25.542824],"type":"Point"}
}