{
  "type": "Feature",
  "properties": {
    "iso:country":"IN",
    "ks:ks_name":"Gujraja",
    "ks:ks_pop":38,
    "ks:ks_type":"VILLAGE",
    "name:eng_x_preferred":[
        "Gujraja"
    ],
    "wof:name":"Gujraja",
    "wof:placetype":"locality",
    "wof:population":38
},
  "geometry": {"coordinates":[78.432159,30.038039],"type":"Point"}
}