{
  "type": "Feature",
  "properties": {
    "iso:country":"IN",
    "ks:ks_name":"Kumbra",
    "ks:ks_pop":385,
    "ks:ks_type":"HABITATION",
    "name:eng_x_preferred":[
        "Kumbra"
    ],
    "wof:name":"Kumbra",
    "wof:placetype":"locality",
    "wof:population":385
},
  "geometry": {"coordinates":[75.252808,12.693877],"type":"Point"}
}