{
  "type": "Feature",
  "properties": {
    "gn:admin1_code":"24.0",
    "gn:admin2_code":"110",
    "gn:asciiname":"Hathod",
    "gn:country_code":"IN",
    "gn:dem":437,
    "gn:feature_class":"P",
    "gn:feature_code":"PPL",
    "gn:name":"Hathod",
    "gn:population":0,
    "gn:timezone":"Asia/Kolkata",
    "iso:country":"IN",
    "ks:ks_name":"Hathod",
    "ks:ks_pop":6199,
    "ks:ks_type":"VILLAGE",
    "ks:ks_uagg_main":0,
    "name:eng_x_preferred":[
        "Hathod"
    ],
    "name:und_x_variant":[
        "H\u0101thod"
    ],
    "wof:name":"Hathod",
    "wof:placetype":"locality",
    "wof:population":6199
},
  "geometry": {"coordinates":[75.677194,26.962033],"type":"Point"}
}