{
  "type": "Feature",
  "properties": {
    "iso:country":"IN",
    "ks:ks_name":"Sialmari Pathar",
    "ks:ks_pop":463,
    "ks:ks_type":"VILLAGE",
    "ks:ks_uagg_main":0,
    "name:eng_x_preferred":[
        "Sialmari Pathar"
    ],
    "wof:name":"Sialmari Pathar",
    "wof:placetype":"neighbourhood",
    "wof:population":463
},
  "geometry": {"coordinates":[92.378635,26.621324],"type":"Point"}
}