{
  "type": "Feature",
  "properties": {
    "gn:admin1_code":"37",
    "gn:admin2_code":"405.0",
    "gn:asciiname":"Basantpur",
    "gn:country_code":"IN",
    "gn:dem":260,
    "gn:feature_class":"P",
    "gn:feature_code":"PPL",
    "gn:name":"Basantpur",
    "gn:population":0,
    "gn:timezone":"Asia/Kolkata",
    "iso:country":"IN",
    "ks:ks_name":"Basantpur",
    "ks:ks_pop":1663,
    "ks:ks_type":"VILLAGE",
    "ks:ks_uagg_main":0,
    "name:ara_x_preferred":[
        "\u0628\u0633\u0646\u062a \u0628\u0648\u0631"
    ],
    "name:ben_bn_x_preferred":[
        "\u09ac\u09b8\u09a8\u09cd\u09a4\u09aa\u09c1\u09b0"
    ],
    "name:ben_in_x_preferred":[
        "\u09ac\u09b8\u09a8\u09cd\u09a4\u09aa\u09c1\u09b0"
    ],
    "name:eng_x_preferred":[
        "Basantpur"
    ],
    "name:guj_x_preferred":[
        "\u0aac\u0ab8\u0a82\u0aa4\u0aaa\u0ac1\u0ab0"
    ],
    "name:hin_x_preferred":[
        "\u092c\u0938\u0902\u0924\u092a\u0941\u0930"
    ],
    "name:kan_x_preferred":[
        "\u0cac\u0cb8\u0c82\u0ca4\u0ccd"
    ],
    "name:mal_x_preferred":[
        "\u0d2c\u0d38\u0d28\u0d4d\u0d24\u0d4d\u0d2a\u0d42\u0d7c"
    ],
    "name:mar_x_preferred":[
        "\u092c\u0938\u0902\u0924\u092a\u0942\u0930"
    ],
    "name:pan_x_preferred":[
        "\u0a2c\u0a38\u0a70\u0a24\u0a2a\u0a41\u0a30"
    ],
    "name:pol_x_preferred":[
        "Basantpur"
    ],
    "name:tam_x_preferred":[
        "\u0baa\u0b9a\u0ba8\u0bcd\u0ba4\u0bcd\u0baa\u0bc2\u0bb0\u0bcd"
    ],
    "name:tel_x_preferred":[
        "\u0c2c\u0c38\u0c02\u0c24\u0c4d"
    ],
    "name:urd_x_preferred":[
        "\u0628\u0633\u0646\u062a \u067e\u0648\u0631"
    ],
    "wof:name":"Basantpur",
    "wof:placetype":"neighbourhood",
    "wof:population":1663
},
  "geometry": {"coordinates":[82.606689,22.041302],"type":"Point"}
}