{
  "type": "Feature",
  "properties": {
    "iso:country":"IN",
    "ks:ks_name":"Kashi Ram Ch. Para",
    "ks:ks_pop":207,
    "ks:ks_type":"HABITATION",
    "name:eng_x_preferred":[
        "Kashi Ram Ch. Para"
    ],
    "wof:name":"Kashi Ram Ch. Para",
    "wof:placetype":"locality",
    "wof:population":207
},
  "geometry": {"coordinates":[92.04016799999999,23.746615],"type":"Point"}
}