{
  "type": "Feature",
  "properties": {
    "iso:country":"IN",
    "ks:ks_name":"Gubbagadde",
    "ks:ks_pop":14,
    "ks:ks_type":"HABITATION",
    "name:eng_x_preferred":[
        "Gubbagadde"
    ],
    "wof:name":"Gubbagadde",
    "wof:placetype":"locality",
    "wof:population":14
},
  "geometry": {"coordinates":[75.419224,13.573141],"type":"Point"}
}