{
  "type": "Feature",
  "properties": {
    "iso:country":"IN",
    "qs:name":"Tal Tala",
    "qs:name_adm0":"India",
    "qs:name_adm1":"West Bengal",
    "qs:photos":4,
    "qs:photos_1k":1,
    "qs:photos_9k":1,
    "qs:photos_9r":1,
    "qs:photos_all":4,
    "qs:photos_sr":1,
    "qs:placetype":"Suburb",
    "qs:pop_sr":"0",
    "wof:name":"Tal Tala",
    "wof:placetype":"neighbourhood"
},
  "geometry": {"coordinates":[88.358745,22.54994],"type":"Point"}
}