{
  "type": "Feature",
  "properties": {
    "iso:country":"IN",
    "ks:ks_name":"Akon",
    "ks:ks_pop":1411,
    "ks:ks_type":"HABITATION",
    "name:eng_x_preferred":[
        "Akon"
    ],
    "wof:name":"Akon",
    "wof:placetype":"locality",
    "wof:population":1411
},
  "geometry": {"coordinates":[78.740268,26.764935],"type":"Point"}
}