{
  "type": "Feature",
  "properties": {
    "gn:admin1_code":"36",
    "gn:admin2_code":"191.0",
    "gn:asciiname":"Muthanpur Hadi Ali",
    "gn:country_code":"IN",
    "gn:dem":86,
    "gn:feature_class":"P",
    "gn:feature_code":"PPL",
    "gn:name":"Muthanpur H\u0101di Ali",
    "gn:population":0,
    "gn:timezone":"Asia/Kolkata",
    "iso:country":"IN",
    "wof:name":"Muthanpur Hadi Ali",
    "wof:placetype":"locality"
},
  "geometry": {"coordinates":[83.06012,26.0357],"type":"Point"}
}