{
  "type": "Feature",
  "properties": {
    "iso:country":"IN",
    "ks:ks_name":"Sal Kanta Para",
    "ks:ks_pop":85,
    "ks:ks_type":"HABITATION",
    "name:eng_x_preferred":[
        "Sal Kanta Para"
    ],
    "wof:name":"Sal Kanta Para",
    "wof:placetype":"locality",
    "wof:population":85
},
  "geometry": {"coordinates":[91.690113,23.685253],"type":"Point"}
}