{
  "type": "Feature",
  "properties": {
    "iso:country":"IN",
    "ks:ks_name":"Jhoredhari",
    "ks:ks_pop":814,
    "ks:ks_type":"HABITATION",
    "name:eng_x_preferred":[
        "Jhoredhari"
    ],
    "wof:name":"Jhoredhari",
    "wof:placetype":"locality",
    "wof:population":814
},
  "geometry": {"coordinates":[88.48144000000001,27.073375],"type":"Point"}
}