{
  "type": "Feature",
  "properties": {
    "iso:country":"IN",
    "ks:ks_name":"Dhanigaon",
    "ks:ks_pop":34,
    "ks:ks_type":"HABITATION",
    "name:eng_x_preferred":[
        "Dhanigaon"
    ],
    "wof:name":"Dhanigaon",
    "wof:placetype":"locality",
    "wof:population":34
},
  "geometry": {"coordinates":[79.969531,29.770352],"type":"Point"}
}