{
  "type": "Feature",
  "properties": {
    "iso:country":"IN",
    "ks:ks_name":"Khalhe Mahespuri Ryt.",
    "ks:ks_pop":294,
    "ks:ks_type":"VILLAGE",
    "name:eng_x_preferred":[
        "Khalhe Mahespuri Ryt."
    ],
    "wof:name":"Khalhe Mahespuri Ryt.",
    "wof:placetype":"locality",
    "wof:population":294
},
  "geometry": {"coordinates":[80.734292,23.046479],"type":"Point"}
}