{
  "type": "Feature",
  "properties": {
    "gn:admin1_code":"34.0",
    "gn:admin2_code":"237.0",
    "gn:asciiname":"Pasia",
    "gn:country_code":"IN",
    "gn:dem":123,
    "gn:feature_class":"P",
    "gn:feature_code":"PPL",
    "gn:name":"Pasia",
    "gn:population":0,
    "gn:timezone":"Asia/Kolkata",
    "iso:country":"IN",
    "ks:ks_name":"Pasia",
    "ks:ks_type":"VILLAGE",
    "name:eng_x_preferred":[
        "Pasia"
    ],
    "wof:name":"Pasia",
    "wof:placetype":"locality"
},
  "geometry": {"coordinates":[85.310945,24.737901],"type":"Point"}
}