{
  "type": "Feature",
  "properties": {
    "gn:admin1_code":"24.0",
    "gn:admin2_code":"108.0",
    "gn:asciiname":"Kayarda",
    "gn:country_code":"IN",
    "gn:dem":217,
    "gn:feature_class":"P",
    "gn:feature_code":"PPL",
    "gn:name":"Kay\u0101rda",
    "gn:population":0,
    "gn:timezone":"Asia/Kolkata",
    "iso:country":"IN",
    "wof:name":"Kayarda",
    "wof:placetype":"locality"
},
  "geometry": {"coordinates":[76.69696,26.06108],"type":"Point"}
}