{
  "type": "Feature",
  "properties": {
    "iso:country":"IN",
    "ks:ks_name":"Kumblemach",
    "ks:ks_pop":159,
    "ks:ks_type":"HABITATION",
    "name:eng_x_preferred":[
        "Kumblemach"
    ],
    "wof:name":"Kumblemach",
    "wof:placetype":"locality",
    "wof:population":159
},
  "geometry": {"coordinates":[73.42442800000001,18.343394],"type":"Point"}
}