{
  "type": "Feature",
  "properties": {
    "gn:admin1_code":"19.0",
    "gn:admin2_code":"583.0",
    "gn:asciiname":"Yakashipur",
    "gn:country_code":"IN",
    "gn:dem":885,
    "gn:feature_class":"P",
    "gn:feature_code":"PPL",
    "gn:name":"Yak\u0101shipur",
    "gn:population":0,
    "gn:timezone":"Asia/Kolkata",
    "iso:country":"IN",
    "wof:name":"Yakashipur",
    "wof:placetype":"locality"
},
  "geometry": {"coordinates":[77.51385999999999,13.25832],"type":"Point"}
}