{
  "type": "Feature",
  "properties": {
    "iso:country":"IN",
    "ks:ks_name":"Barahnoti",
    "ks:ks_pop":699,
    "ks:ks_type":"VILLAGE",
    "name:eng_x_preferred":[
        "Barahnoti"
    ],
    "wof:name":"Barahnoti",
    "wof:placetype":"locality",
    "wof:population":699
},
  "geometry": {"coordinates":[83.483294,24.078294],"type":"Point"}
}