{
  "type": "Feature",
  "properties": {
    "iso:country":"IN",
    "ks:ks_name":"Telgaon Bk.",
    "ks:ks_pop":5006,
    "ks:ks_type":"HABITATION",
    "name:eng_x_preferred":[
        "Telgaon Bk."
    ],
    "wof:name":"Telgaon Bk.",
    "wof:placetype":"locality",
    "wof:population":5006
},
  "geometry": {"coordinates":[76.17755,18.969542],"type":"Point"}
}