{
  "type": "Feature",
  "properties": {
    "iso:country":"IN",
    "ks:ks_name":"Sikiripada",
    "ks:ks_pop":21,
    "ks:ks_type":"VILLAGE",
    "name:eng_x_preferred":[
        "Sikiripada"
    ],
    "wof:name":"Sikiripada",
    "wof:placetype":"locality",
    "wof:population":21
},
  "geometry": {"coordinates":[83.638957,20.033012],"type":"Point"}
}