{
  "type": "Feature",
  "properties": {
    "iso:country":"IN",
    "ks:ks_name":"Siyardhar",
    "ks:ks_pop":916,
    "ks:ks_type":"VILLAGE",
    "name:eng_x_preferred":[
        "Siyardhar"
    ],
    "wof:name":"Siyardhar",
    "wof:placetype":"locality",
    "wof:population":916
},
  "geometry": {"coordinates":[83.703289,22.298379],"type":"Point"}
}