{
  "type": "Feature",
  "properties": {
    "gn:admin1_code":"25.0",
    "gn:admin2_code":"618.0",
    "gn:asciiname":"Mannakkudi",
    "gn:country_code":"IN",
    "gn:dem":6,
    "gn:feature_class":"P",
    "gn:feature_code":"PPL",
    "gn:name":"Mannakkudi",
    "gn:population":0,
    "gn:timezone":"Asia/Kolkata",
    "iso:country":"IN",
    "name:und_x_variant":[
        "Manakkudi"
    ],
    "wof:name":"Mannakkudi",
    "wof:placetype":"locality"
},
  "geometry": {"coordinates":[79.74744,10.57853],"type":"Point"}
}