{
  "type": "Feature",
  "properties": {
    "gn:admin1_code":"38.0",
    "gn:admin2_code":"347.0",
    "gn:asciiname":"Teona",
    "gn:country_code":"IN",
    "gn:dem":458,
    "gn:feature_class":"P",
    "gn:feature_code":"PPL",
    "gn:name":"Teon\u0101",
    "gn:population":0,
    "gn:timezone":"Asia/Kolkata",
    "iso:country":"IN",
    "ks:ks_alt_nam":"Teon\u0101",
    "ks:ks_name":"Teona",
    "ks:ks_pop":192,
    "ks:ks_type":"VILLAGE",
    "name:eng_x_preferred":[
        "Teona"
    ],
    "name:eng_x_variant":[
        "Teon\u0101"
    ],
    "wof:name":"Teona",
    "wof:placetype":"locality",
    "wof:population":192
},
  "geometry": {"coordinates":[84.71093500000001,24.083658],"type":"Point"}
}