{
  "type": "Feature",
  "properties": {
    "iso:country":"IN",
    "ks:ks_name":"Dhapalial Dimarugura",
    "ks:ks_pop":1439,
    "ks:ks_type":"VILLAGE",
    "ks:ks_uagg_main":0,
    "name:eng_x_preferred":[
        "Dhapalial Dimarugura"
    ],
    "wof:name":"Dhapalial Dimarugura",
    "wof:placetype":"neighbourhood",
    "wof:population":1439
},
  "geometry": {"coordinates":[94.427538,27.304082],"type":"Point"}
}