{
  "type": "Feature",
  "properties": {
    "iso:country":"IN",
    "ks:ks_name":"Vavilla Doruvu",
    "ks:ks_pop":238,
    "ks:ks_type":"HABITATION",
    "name:eng_x_preferred":[
        "Vavilla Doruvu"
    ],
    "wof:name":"Vavilla Doruvu",
    "wof:placetype":"locality",
    "wof:population":238
},
  "geometry": {"coordinates":[80.117633,14.108687],"type":"Point"}
}