{
  "type": "Feature",
  "properties": {
    "gn:admin1_code":"35",
    "gn:admin2_code":"426.0",
    "gn:asciiname":"Tikeria",
    "gn:country_code":"IN",
    "gn:dem":425,
    "gn:feature_class":"P",
    "gn:feature_code":"PPL",
    "gn:name":"Tikeria",
    "gn:population":0,
    "gn:timezone":"Asia/Kolkata",
    "iso:country":"IN",
    "wof:name":"Tikeria",
    "wof:placetype":"neighbourhood"
},
  "geometry": {"coordinates":[80.25294,24.14321],"type":"Point"}
}