{
  "type": "Feature",
  "properties": {
    "iso:country":"IN",
    "ks:ks_name":"Bheemjiguda",
    "ks:ks_pop":25,
    "ks:ks_type":"HABITATION",
    "name:eng_x_preferred":[
        "Bheemjiguda"
    ],
    "wof:name":"Bheemjiguda",
    "wof:placetype":"locality",
    "wof:population":25
},
  "geometry": {"coordinates":[79.14399299999999,19.178577],"type":"Point"}
}