{
  "type": "Feature",
  "properties": {
    "gn:admin1_code":"23",
    "gn:admin2_code":"48.0",
    "gn:asciiname":"Ganda Kheri",
    "gn:country_code":"IN",
    "gn:dem":272,
    "gn:feature_class":"P",
    "gn:feature_code":"PPL",
    "gn:name":"Ganda Kheri",
    "gn:population":0,
    "gn:timezone":"Asia/Kolkata",
    "iso:country":"IN",
    "ks:ks_name":"Ganda Kheri",
    "ks:ks_type":"VILLAGE",
    "name:eng_x_preferred":[
        "Ganda Kheri"
    ],
    "wof:name":"Ganda Kheri",
    "wof:placetype":"locality"
},
  "geometry": {"coordinates":[76.644464,30.453758],"type":"Point"}
}