{
  "type": "Feature",
  "properties": {
    "iso:country":"IN",
    "ks:ks_alt_nam":"N.Family",
    "ks:ks_name":"N.family",
    "ks:ks_pop":89,
    "ks:ks_type":"HABITATION",
    "name:eng_x_preferred":[
        "N.family"
    ],
    "wof:name":"N.family",
    "wof:placetype":"locality",
    "wof:population":89
},
  "geometry": {"coordinates":[75.830556,12.256667],"type":"Point"}
}