{
  "type": "Feature",
  "properties": {
    "iso:country":"IN",
    "ks:ks_name":"Bagdarri",
    "ks:ks_pop":729,
    "ks:ks_type":"HABITATION",
    "name:eng_x_preferred":[
        "Bagdarri"
    ],
    "wof:name":"Bagdarri",
    "wof:placetype":"locality",
    "wof:population":729
},
  "geometry": {"coordinates":[76.80663300000001,25.932272],"type":"Point"}
}