{
  "type": "Feature",
  "properties": {
    "iso:country":"IN",
    "ks:ks_name":"Khalvad",
    "ks:ks_pop":1423,
    "ks:ks_type":"VILLAGE",
    "ks:ks_uagg_main":0,
    "name:eng_x_preferred":[
        "Khalvad"
    ],
    "wof:name":"Khalvad",
    "wof:placetype":"neighbourhood",
    "wof:population":1423
},
  "geometry": {"coordinates":[73.203575,23.780513],"type":"Point"}
}