{
  "type": "Feature",
  "properties": {
    "iso:country":"IN",
    "ks:ks_name":"Kallebbe",
    "ks:ks_pop":58,
    "ks:ks_type":"HABITATION",
    "name:eng_x_preferred":[
        "Kallebbe"
    ],
    "wof:name":"Kallebbe",
    "wof:placetype":"locality",
    "wof:population":58
},
  "geometry": {"coordinates":[74.834006,14.442952],"type":"Point"}
}