{
  "type": "Feature",
  "properties": {
    "iso:country":"IN",
    "ks:ks_name":"Balita",
    "ks:ks_pop":962,
    "ks:ks_type":"VILLAGE",
    "name:eng_x_preferred":[
        "Balita"
    ],
    "wof:name":"Balita",
    "wof:placetype":"locality",
    "wof:population":962
},
  "geometry": {"coordinates":[85.44293500000001,22.073431],"type":"Point"}
}