{
  "type": "Feature",
  "properties": {
    "iso:country":"IN",
    "ks:ks_alt_nam":"BURUSAI",
    "ks:ks_name":"Burusai",
    "ks:ks_pop":452,
    "ks:ks_type":"HABITATION",
    "name:eng_x_preferred":[
        "Burusai"
    ],
    "wof:name":"Burusai",
    "wof:placetype":"locality",
    "wof:population":452
},
  "geometry": {"coordinates":[85.67188899999999,22.189473],"type":"Point"}
}