{
  "type": "Feature",
  "properties": {
    "gn:admin1_code":"2.0",
    "gn:admin2_code":"545.0",
    "gn:asciiname":"Kundada",
    "gn:country_code":"IN",
    "gn:dem":529,
    "gn:feature_class":"P",
    "gn:feature_code":"PPL",
    "gn:name":"Kund\u0101da",
    "gn:population":0,
    "gn:timezone":"Asia/Kolkata",
    "iso:country":"IN",
    "wof:name":"Kundada",
    "wof:placetype":"locality"
},
  "geometry": {"coordinates":[81.66038,17.56902],"type":"Point"}
}