{
  "type": "Feature",
  "properties": {
    "iso:country":"IN",
    "ks:ks_name":"Shokanmakki",
    "ks:ks_pop":98,
    "ks:ks_type":"HABITATION",
    "name:eng_x_preferred":[
        "Shokanmakki"
    ],
    "wof:name":"Shokanmakki",
    "wof:placetype":"locality",
    "wof:population":98
},
  "geometry": {"coordinates":[74.436145,14.418594],"type":"Point"}
}