{
  "type": "Feature",
  "properties": {
    "gn:admin1_code":"35",
    "gn:admin2_code":"451.0",
    "gn:asciiname":"Andia",
    "gn:country_code":"IN",
    "gn:dem":423,
    "gn:feature_class":"P",
    "gn:feature_code":"PPL",
    "gn:name":"Andia",
    "gn:population":0,
    "gn:timezone":"Asia/Kolkata",
    "iso:country":"IN",
    "name:cat_x_preferred":[
        "Serra d'Andia"
    ],
    "name:eus_x_preferred":[
        "Andimendi"
    ],
    "name:fas_x_preferred":[
        "\u0622\u0646\u062f\u06cc\u0627"
    ],
    "name:fra_x_preferred":[
        "Massif d'Andia"
    ],
    "name:jpn_x_preferred":[
        "\u30a2\u30f3\u30c7\u30a3\u30a2\u5c71\u5730"
    ],
    "name:zho_x_preferred":[
        "\u5b89\u8fea\u4e9e\u5c71\u8108"
    ],
    "wof:name":"Andia",
    "wof:placetype":"locality"
},
  "geometry": {"coordinates":[79.76217,23.05893],"type":"Point"}
}