{
  "type": "Feature",
  "properties": {
    "iso:country":"IN",
    "ks:ks_name":"Rampur Bax",
    "ks:ks_pop":150,
    "ks:ks_type":"VILLAGE",
    "name:eng_x_preferred":[
        "Rampur Bax"
    ],
    "wof:name":"Rampur Bax",
    "wof:placetype":"locality",
    "wof:population":150
},
  "geometry": {"coordinates":[83.06313299999999,26.33776],"type":"Point"}
}