{
  "type": "Feature",
  "properties": {
    "gn:admin1_code":"36.0",
    "gn:admin2_code":"167",
    "gn:asciiname":"Pandakhera",
    "gn:country_code":"IN",
    "gn:dem":364,
    "gn:feature_class":"P",
    "gn:feature_code":"PPL",
    "gn:name":"Pand\u0101khera",
    "gn:population":0,
    "gn:timezone":"Asia/Kolkata",
    "iso:country":"IN",
    "name:und_x_variant":[
        "Panda P\u012bpar",
        "Pand\u0101khera"
    ],
    "wof:name":"Pandakhera",
    "wof:placetype":"locality"
},
  "geometry": {"coordinates":[78.91408,24.50573],"type":"Point"}
}