{
  "type": "Feature",
  "properties": {
    "iso:country":"IN",
    "ks:ks_name":"Madila Khurd",
    "ks:ks_pop":152,
    "ks:ks_type":"VILLAGE",
    "name:eng_x_preferred":[
        "Madila Khurd"
    ],
    "wof:name":"Madila Khurd",
    "wof:placetype":"locality",
    "wof:population":152
},
  "geometry": {"coordinates":[81.929104,24.491573],"type":"Point"}
}