{
  "type": "Feature",
  "properties": {
    "iso:country":"IN",
    "ks:ks_name":"Koiri Tola",
    "ks:ks_pop":115,
    "ks:ks_type":"HABITATION",
    "name:eng_x_preferred":[
        "Koiri Tola"
    ],
    "wof:name":"Koiri Tola",
    "wof:placetype":"locality",
    "wof:population":115
},
  "geometry": {"coordinates":[84.270867,26.153551],"type":"Point"}
}