{
  "type": "Feature",
  "properties": {
    "iso:country":"IN",
    "ks:ks_name":"Jogipara",
    "ks:ks_pop":3906,
    "ks:ks_type":"VILLAGE",
    "ks:ks_uagg_main":0,
    "name:eng_x_preferred":[
        "Jogipara"
    ],
    "wof:name":"Jogipara",
    "wof:placetype":"neighbourhood",
    "wof:population":3906
},
  "geometry": {"coordinates":[92.092139,26.521426],"type":"Point"}
}