{
  "type": "Feature",
  "properties": {
    "iso:country":"IN",
    "ks:ks_name":"Char Serpur",
    "ks:ks_pop":0,
    "ks:ks_type":"VILLAGE",
    "name:eng_x_preferred":[
        "Char Serpur"
    ],
    "wof:name":"Char Serpur",
    "wof:placetype":"locality",
    "wof:population":0
},
  "geometry": {"coordinates":[88.211799,23.729239],"type":"Point"}
}