{
  "type": "Feature",
  "properties": {
    "gn:admin1_code":"16",
    "gn:admin2_code":"512.0",
    "gn:asciiname":"Narhapur",
    "gn:country_code":"IN",
    "gn:dem":377,
    "gn:feature_class":"P",
    "gn:feature_code":"PPL",
    "gn:name":"Narh\u0101pur",
    "gn:population":0,
    "gn:timezone":"Asia/Kolkata",
    "iso:country":"IN",
    "wof:name":"Narhapur",
    "wof:placetype":"locality"
},
  "geometry": {"coordinates":[77.10106999999998,19.16554],"type":"Point"}
}