{
  "type": "Feature",
  "properties": {
    "iso:country":"IN",
    "ks:ks_name":"Rundh Naiwara",
    "ks:ks_pop":26,
    "ks:ks_type":"VILLAGE",
    "name:eng_x_preferred":[
        "Rundh Naiwara"
    ],
    "wof:name":"Rundh Naiwara",
    "wof:placetype":"locality",
    "wof:population":26
},
  "geometry": {"coordinates":[77.080726,27.153241],"type":"Point"}
}