{
  "type": "Feature",
  "properties": {
    "iso:country":"IN",
    "ks:ks_alt_nam":"pulinkunnu west",
    "ks:ks_name":"Pulinkunnu West",
    "ks:ks_pop":1001,
    "ks:ks_type":"HABITATION",
    "ks:ks_uagg_main":0,
    "name:eng_x_preferred":[
        "Pulinkunnu West"
    ],
    "wof:name":"Pulinkunnu West",
    "wof:placetype":"neighbourhood",
    "wof:population":1001
},
  "geometry": {"coordinates":[76.44974499999999,9.457492],"type":"Point"}
}