{
  "type": "Feature",
  "properties": {
    "gn:admin1_code":"36",
    "gn:admin2_code":"187.0",
    "gn:asciiname":"Simrahna",
    "gn:country_code":"IN",
    "gn:dem":86,
    "gn:feature_class":"P",
    "gn:feature_code":"PPL",
    "gn:name":"Simrahna",
    "gn:population":0,
    "gn:timezone":"Asia/Kolkata",
    "iso:country":"IN",
    "wof:name":"Simrahna",
    "wof:placetype":"locality"
},
  "geometry": {"coordinates":[83.52846,26.92293],"type":"Point"}
}