{
  "type": "Feature",
  "properties": {
    "iso:country":"IN",
    "ks:ks_alt_nam":"Memala north",
    "ks:ks_name":"Memala North",
    "ks:ks_pop":815,
    "ks:ks_type":"HABITATION",
    "name:eng_x_preferred":[
        "Memala North"
    ],
    "wof:name":"Memala North",
    "wof:placetype":"locality",
    "wof:population":815
},
  "geometry": {"coordinates":[76.97615500000001,9.625279],"type":"Point"}
}