{
  "type": "Feature",
  "properties": {
    "iso:country":"IN",
    "ks:ks_name":"Jamdadewasti",
    "ks:ks_pop":475,
    "ks:ks_type":"HABITATION",
    "name:eng_x_preferred":[
        "Jamdadewasti"
    ],
    "wof:name":"Jamdadewasti",
    "wof:placetype":"locality",
    "wof:population":475
},
  "geometry": {"coordinates":[75.086232,17.878756],"type":"Point"}
}