{
  "type": "Feature",
  "properties": {
    "iso:country":"IN",
    "ks:ks_name":"Vasanthapura",
    "ks:ks_pop":853,
    "ks:ks_type":"VILLAGE",
    "name:eng_x_preferred":[
        "Vasanthapura"
    ],
    "wof:name":"Vasanthapura",
    "wof:placetype":"locality",
    "wof:population":853
},
  "geometry": {"coordinates":[77.938028,13.836343],"type":"Point"}
}