{
  "type": "Feature",
  "properties": {
    "iso:country":"IN",
    "ks:ks_alt_nam":"munna purwa",
    "ks:ks_name":"Munna Purwa",
    "ks:ks_pop":40,
    "ks:ks_type":"HABITATION",
    "ks:ks_uagg_main":0,
    "name:eng_x_preferred":[
        "Munna Purwa"
    ],
    "wof:name":"Munna Purwa",
    "wof:placetype":"neighbourhood",
    "wof:population":40
},
  "geometry": {"coordinates":[81.61971800000001,27.404897],"type":"Point"}
}