{
  "type": "Feature",
  "properties": {
    "iso:country":"IN",
    "ks:ks_name":"Project Colony",
    "ks:ks_pop":134,
    "ks:ks_type":"HABITATION",
    "ks:ks_uagg_main":0,
    "name:eng_x_preferred":[
        "Project Colony"
    ],
    "wof:name":"Project Colony",
    "wof:placetype":"neighbourhood",
    "wof:population":134
},
  "geometry": {"coordinates":[91.647672,23.026673],"type":"Point"}
}