{
  "type": "Feature",
  "properties": {
    "iso:country":"IN",
    "ks:ks_name":"Jadhavwadi",
    "ks:ks_pop":276,
    "ks:ks_type":"HABITATION",
    "name:eng_x_preferred":[
        "Jadhavwadi"
    ],
    "wof:name":"Jadhavwadi",
    "wof:placetype":"locality",
    "wof:population":276
},
  "geometry": {"coordinates":[73.603056,16.867778],"type":"Point"}
}