{
  "type": "Feature",
  "properties": {
    "iso:country":"IN",
    "ks:ks_name":"Simawadi",
    "ks:ks_pop":160,
    "ks:ks_type":"HABITATION",
    "name:eng_x_preferred":[
        "Simawadi"
    ],
    "wof:name":"Simawadi",
    "wof:placetype":"locality",
    "wof:population":160
},
  "geometry": {"coordinates":[73.376194,17.789208],"type":"Point"}
}