{
  "type": "Feature",
  "properties": {
    "iso:country":"IN",
    "ks:ks_name":"Oonaparaipatty",
    "ks:ks_pop":115,
    "ks:ks_type":"HABITATION",
    "name:eng_x_preferred":[
        "Oonaparaipatty"
    ],
    "wof:name":"Oonaparaipatty",
    "wof:placetype":"locality",
    "wof:population":115
},
  "geometry": {"coordinates":[78.35100199999999,10.797102],"type":"Point"}
}