{
  "type": "Feature",
  "properties": {
    "iso:country":"IN",
    "ks:ks_name":"Belahia Khera",
    "ks:ks_pop":514,
    "ks:ks_type":"HABITATION",
    "name:eng_x_preferred":[
        "Belahia Khera"
    ],
    "wof:name":"Belahia Khera",
    "wof:placetype":"locality",
    "wof:population":514
},
  "geometry": {"coordinates":[80.917484,26.597459],"type":"Point"}
}