{
  "type": "Feature",
  "properties": {
    "iso:country":"IN",
    "ks:ks_name":"Mauhariya 486 Kothar",
    "ks:ks_pop":792,
    "ks:ks_type":"HABITATION",
    "name:eng_x_preferred":[
        "Mauhariya 486 Kothar"
    ],
    "wof:name":"Mauhariya 486 Kothar",
    "wof:placetype":"locality",
    "wof:population":792
},
  "geometry": {"coordinates":[81.541933,24.78946],"type":"Point"}
}