{
  "type": "Feature",
  "properties": {
    "iso:country":"IN",
    "ks:ks_name":"Kokkamverum",
    "ks:ks_pop":490,
    "ks:ks_type":"HABITATION",
    "name:eng_x_preferred":[
        "Kokkamverum"
    ],
    "wof:name":"Kokkamverum",
    "wof:placetype":"locality",
    "wof:population":490
},
  "geometry": {"coordinates":[75.926787,11.444783],"type":"Point"}
}