{
  "type": "Feature",
  "properties": {
    "iso:country":"IN",
    "ks:ks_name":"Chak Baksan",
    "ks:ks_pop":22,
    "ks:ks_type":"VILLAGE",
    "name:eng_x_preferred":[
        "Chak Baksan"
    ],
    "wof:name":"Chak Baksan",
    "wof:placetype":"locality",
    "wof:population":22
},
  "geometry": {"coordinates":[83.684569,25.808971],"type":"Point"}
}