{
  "type": "Feature",
  "properties": {
    "gn:admin1_code":"12.0",
    "gn:admin2_code":"17.0",
    "gn:asciiname":"Aiblar",
    "gn:country_code":"IN",
    "gn:dem":2222,
    "gn:feature_class":"P",
    "gn:feature_code":"PPL",
    "gn:name":"Aiblar",
    "gn:population":0,
    "gn:timezone":"Asia/Kolkata",
    "iso:country":"IN",
    "wof:name":"Aiblar",
    "wof:placetype":"locality"
},
  "geometry": {"coordinates":[75.28180999999999,33.33708],"type":"Point"}
}