{
  "type": "Feature",
  "properties": {
    "iso:country":"IN",
    "ks:ks_name":"Katapukuria",
    "ks:ks_pop":637,
    "ks:ks_type":"HABITATION",
    "name:eng_x_preferred":[
        "Katapukuria"
    ],
    "wof:name":"Katapukuria",
    "wof:placetype":"locality",
    "wof:population":637
},
  "geometry": {"coordinates":[88.401844,22.22027],"type":"Point"}
}