{
  "type": "Feature",
  "properties": {
    "gn:admin1_code":"35.0",
    "gn:admin2_code":"456",
    "gn:asciiname":"Adegaon",
    "gn:country_code":"IN",
    "gn:dem":633,
    "gn:feature_class":"P",
    "gn:feature_code":"PPL",
    "gn:name":"Adegaon",
    "gn:population":0,
    "gn:timezone":"Asia/Kolkata",
    "iso:country":"IN",
    "name:cat_x_preferred":[
        "Adegaon"
    ],
    "wof:name":"Adegaon",
    "wof:placetype":"locality"
},
  "geometry": {"coordinates":[79.49006999999997,22.61641],"type":"Point"}
}