{
  "type": "Feature",
  "properties": {
    "iso:country":"IN",
    "ks:ks_name":"Garpa",
    "ks:ks_pop":284,
    "ks:ks_type":"HABITATION",
    "name:eng_x_preferred":[
        "Garpa"
    ],
    "wof:name":"Garpa",
    "wof:placetype":"locality",
    "wof:population":284
},
  "geometry": {"coordinates":[81.06896999999999,19.339947],"type":"Point"}
}