{
  "type": "Feature",
  "properties": {
    "iso:country":"IN",
    "ks:ks_name":"Dangadhar",
    "ks:ks_pop":328,
    "ks:ks_type":"HABITATION",
    "name:eng_x_preferred":[
        "Dangadhar"
    ],
    "wof:name":"Dangadhar",
    "wof:placetype":"locality",
    "wof:population":328
},
  "geometry": {"coordinates":[85.85087900000001,21.224462],"type":"Point"}
}