{
  "type": "Feature",
  "properties": {
    "gn:country":"IN",
    "gn:fcode":"PPL",
    "gn:population":36755,
    "iso:country":"IN",
    "name:ast_x_preferred":[
        "Vuyyuru"
    ],
    "name:ceb_x_preferred":[
        "Vuyy\u016bru"
    ],
    "name:eng_x_preferred":[
        "Vuyyuru"
    ],
    "name:new_x_preferred":[
        "\u0909\u092f\u094d\u092f\u0942\u0930\u0941 \u092e\u0923\u094d\u0921\u0932"
    ],
    "name:nld_x_preferred":[
        "Vuyyuru"
    ],
    "name:swe_x_preferred":[
        "Vuyy\u016bru"
    ],
    "name:tel_x_preferred":[
        "\u0c09\u0c2f\u0c4d\u0c2f\u0c42\u0c30\u0c41"
    ],
    "name:urd_x_preferred":[
        "\u0648\u06cc\u0648\u0631\u0648"
    ],
    "name:vie_x_preferred":[
        "Vuyyuru"
    ],
    "qs:name":"Vuyy\u016bru",
    "qs:photos_9r":0,
    "qs:photos_sr":0,
    "qs:pop_sr":"7",
    "wof:name":"Vuyy\u016bru",
    "wof:placetype":"locality",
    "wof:population":36755
},
  "geometry": {"coordinates":[80.84573,16.36188],"type":"Point"}
}