{
  "type": "Feature",
  "properties": {
    "iso:country":"IN",
    "ks:ks_alt_nam":"HARIJAN TOLA",
    "ks:ks_name":"Harijan Tola",
    "ks:ks_pop":620,
    "ks:ks_type":"HABITATION",
    "name:eng_x_preferred":[
        "Harijan Tola"
    ],
    "wof:name":"Harijan Tola",
    "wof:placetype":"locality",
    "wof:population":620
},
  "geometry": {"coordinates":[83.70492900000001,25.019911],"type":"Point"}
}