{
  "type": "Feature",
  "properties": {
    "gn:admin1_code":"36.0",
    "gn:admin2_code":"155",
    "gn:asciiname":"Khajuria Purwa",
    "gn:country_code":"IN",
    "gn:dem":136,
    "gn:feature_class":"P",
    "gn:feature_code":"PPL",
    "gn:name":"Khaj\u016bria Purwa",
    "gn:population":0,
    "gn:timezone":"Asia/Kolkata",
    "iso:country":"IN",
    "name:und_x_variant":[
        "Khaj\u016bria Purwa",
        "Khaj\u0101ria Purwa"
    ],
    "wof:name":"Khajuria Purwa",
    "wof:placetype":"locality"
},
  "geometry": {"coordinates":[79.81075,27.19888],"type":"Point"}
}