{
  "type": "Feature",
  "properties": {
    "gn:admin1_code":"35",
    "gn:admin2_code":"425.0",
    "gn:asciiname":"Putri",
    "gn:country_code":"IN",
    "gn:dem":226,
    "gn:feature_class":"P",
    "gn:feature_code":"PPL",
    "gn:name":"Putri",
    "gn:population":0,
    "gn:timezone":"Asia/Kolkata",
    "iso:country":"IN",
    "ks:ks_name":"Putari",
    "ks:ks_pop":644,
    "ks:ks_type":"VILLAGE",
    "name:eng_x_preferred":[
        "Putari"
    ],
    "name:eng_x_variant":[
        "Putri"
    ],
    "wof:name":"Putari",
    "wof:placetype":"locality",
    "wof:population":644
},
  "geometry": {"coordinates":[79.802499,24.963814],"type":"Point"}
}