{
  "type": "Feature",
  "properties": {
    "iso:country":"IN",
    "ks:ks_name":"Manjurahi",
    "ks:ks_pop":3,
    "ks:ks_type":"VILLAGE",
    "name:eng_x_preferred":[
        "Manjurahi"
    ],
    "wof:name":"Manjurahi",
    "wof:placetype":"locality",
    "wof:population":3
},
  "geometry": {"coordinates":[84.645032,24.309874],"type":"Point"}
}