{
  "type": "Feature",
  "properties": {
    "iso:country":"IN",
    "ks:ks_name":"Joygopalpur",
    "ks:ks_pop":6322,
    "ks:ks_type":"VILLAGE",
    "name:eng_x_preferred":[
        "Joygopalpur"
    ],
    "wof:name":"Joygopalpur",
    "wof:placetype":"locality",
    "wof:population":6322
},
  "geometry": {"coordinates":[88.89979200000001,22.268764],"type":"Point"}
}