{
  "type": "Feature",
  "properties": {
    "gn:admin1_code":"11.0",
    "gn:admin2_code":"31.0",
    "gn:asciiname":"Mauri",
    "gn:country_code":"IN",
    "gn:dem":1820,
    "gn:feature_class":"P",
    "gn:feature_code":"PPL",
    "gn:name":"M\u0101uri",
    "gn:population":0,
    "gn:timezone":"Asia/Kolkata",
    "iso:country":"IN",
    "name:bos_x_preferred":[
        "Mauri"
    ],
    "name:bre_x_preferred":[
        "Mauri"
    ],
    "name:ceb_x_preferred":[
        "Mauri"
    ],
    "name:deu_x_preferred":[
        "Mauri"
    ],
    "name:fin_x_preferred":[
        "Mauri"
    ],
    "name:fra_x_preferred":[
        "Mauri"
    ],
    "name:ita_x_preferred":[
        "Mauri"
    ],
    "name:rus_x_preferred":[
        "\u041c\u0430\u0443\u0440\u0438"
    ],
    "name:spa_x_preferred":[
        "Mauri"
    ],
    "wof:name":"Mauri",
    "wof:placetype":"locality"
},
  "geometry": {"coordinates":[77.07383,30.89991],"type":"Point"}
}