{
  "type": "Feature",
  "properties": {
    "iso:country":"IN",
    "ks:ks_alt_nam":"ANUSEWASTI",
    "ks:ks_name":"Anusewasti",
    "ks:ks_pop":101,
    "ks:ks_type":"HABITATION",
    "name:eng_x_preferred":[
        "Anusewasti"
    ],
    "wof:name":"Anusewasti",
    "wof:placetype":"locality",
    "wof:population":101
},
  "geometry": {"coordinates":[74.957052,17.437057],"type":"Point"}
}