{
  "type": "Feature",
  "properties": {
    "iso:country":"IN",
    "ks:ks_name":"Jalikhol",
    "ks:ks_pop":372,
    "ks:ks_type":"VILLAGE",
    "name:eng_x_preferred":[
        "Jalikhol"
    ],
    "wof:name":"Jalikhol",
    "wof:placetype":"locality",
    "wof:population":372
},
  "geometry": {"coordinates":[84.386162,21.581101],"type":"Point"}
}