{
  "type": "Feature",
  "properties": {
    "iso:country":"IN",
    "ks:ks_name":"Amral",
    "ks:ks_pop":1643,
    "ks:ks_type":"VILLAGE",
    "name:eng_x_preferred":[
        "Amral"
    ],
    "wof:name":"Amral",
    "wof:placetype":"locality",
    "wof:population":1643
},
  "geometry": {"coordinates":[87.308205,23.15395],"type":"Point"}
}