{
  "type": "Feature",
  "properties": {
    "gn:admin1_code":"12.0",
    "gn:admin2_code":"19.0",
    "gn:asciiname":"Palhetar",
    "gn:country_code":"IN",
    "gn:dem":1936,
    "gn:feature_class":"P",
    "gn:feature_code":"PPL",
    "gn:name":"Palhetar",
    "gn:population":0,
    "gn:timezone":"Asia/Kolkata",
    "iso:country":"IN",
    "wof:name":"Palhetar",
    "wof:placetype":"locality"
},
  "geometry": {"coordinates":[75.06283000000001,33.02855],"type":"Point"}
}