{
  "type": "Feature",
  "properties": {
    "gn:admin1_code":"11",
    "gn:admin2_code":"23.0",
    "gn:asciiname":"Khapdara Adwar",
    "gn:country_code":"IN",
    "gn:dem":2029,
    "gn:feature_class":"P",
    "gn:feature_code":"PPL",
    "gn:name":"Kh\u0101pdara Adw\u0101r",
    "gn:population":0,
    "gn:timezone":"Asia/Kolkata",
    "iso:country":"IN",
    "wof:name":"Khapdara Adwar",
    "wof:placetype":"locality"
},
  "geometry": {"coordinates":[76.03657,32.75141],"type":"Point"}
}