{
  "type": "Feature",
  "properties": {
    "iso:country":"IN",
    "ks:ks_name":"Tadkachhla",
    "ks:ks_pop":0,
    "ks:ks_type":"VILLAGE",
    "name:eng_x_preferred":[
        "Tadkachhla"
    ],
    "wof:name":"Tadkachhla",
    "wof:placetype":"locality",
    "wof:population":0
},
  "geometry": {"coordinates":[73.75388599999999,22.051793],"type":"Point"}
}