{
  "type": "Feature",
  "properties": {
    "iso:country":"IN",
    "ks:ks_name":"Saintara",
    "ks:ks_pop":1096,
    "ks:ks_type":"VILLAGE",
    "name:eng_x_preferred":[
        "Saintara"
    ],
    "wof:name":"Saintara",
    "wof:placetype":"locality",
    "wof:population":1096
},
  "geometry": {"coordinates":[87.542126,23.044686],"type":"Point"}
}