{
  "type": "Feature",
  "properties": {
    "iso:country":"IN",
    "ks:ks_name":"Suthar Faliya",
    "ks:ks_pop":550,
    "ks:ks_type":"HABITATION",
    "name:eng_x_preferred":[
        "Suthar Faliya"
    ],
    "wof:name":"Suthar Faliya",
    "wof:placetype":"locality",
    "wof:population":550
},
  "geometry": {"coordinates":[73.83108300000001,22.886639],"type":"Point"}
}