{
  "type": "Feature",
  "properties": {
    "iso:country":"IN",
    "ks:ks_name":"Nichchalsa",
    "ks:ks_pop":3027,
    "ks:ks_type":"VILLAGE",
    "name:eng_x_preferred":[
        "Nichchalsa"
    ],
    "wof:name":"Nichchalsa",
    "wof:placetype":"locality",
    "wof:population":3027
},
  "geometry": {"coordinates":[88.744767,26.793406],"type":"Point"}
}