{
  "type": "Feature",
  "properties": {
    "iso:country":"IN",
    "ks:ks_name":"Karupukuruchi",
    "ks:ks_pop":102,
    "ks:ks_type":"HABITATION",
    "name:eng_x_preferred":[
        "Karupukuruchi"
    ],
    "wof:name":"Karupukuruchi",
    "wof:placetype":"locality",
    "wof:population":102
},
  "geometry": {"coordinates":[79.09540800000001,10.067579],"type":"Point"}
}