{
  "type": "Feature",
  "properties": {
    "iso:country":"IN",
    "ks:ks_name":"Chhotaghagri2",
    "ks:ks_pop":80,
    "ks:ks_type":"HABITATION",
    "name:eng_x_preferred":[
        "Chhotaghagri2"
    ],
    "wof:name":"Chhotaghagri2",
    "wof:placetype":"locality",
    "wof:population":80
},
  "geometry": {"coordinates":[87.531656,24.690901],"type":"Point"}
}