{
  "type": "Feature",
  "properties": {
    "iso:country":"IN",
    "ks:ks_name":"Battaha Tola",
    "ks:ks_pop":35,
    "ks:ks_type":"HABITATION",
    "name:eng_x_preferred":[
        "Battaha Tola"
    ],
    "wof:name":"Battaha Tola",
    "wof:placetype":"locality",
    "wof:population":35
},
  "geometry": {"coordinates":[83.400606,27.1795],"type":"Point"}
}