{
  "type": "Feature",
  "properties": {
    "gn:admin1_code":"2.0",
    "gn:admin2_code":"553.0",
    "gn:asciiname":"Sugalapenta",
    "gn:country_code":"IN",
    "gn:dem":375,
    "gn:feature_class":"P",
    "gn:feature_code":"PPL",
    "gn:name":"Sug\u0101lapenta",
    "gn:population":0,
    "gn:timezone":"Asia/Kolkata",
    "iso:country":"IN",
    "wof:name":"Sugalapenta",
    "wof:placetype":"locality"
},
  "geometry": {"coordinates":[78.36249000000002,14.16977],"type":"Point"}
}