{
  "type": "Feature",
  "properties": {
    "gn:admin1_code":"10",
    "gn:admin2_code":"82.0",
    "gn:asciiname":"Sampla",
    "gn:country_code":"IN",
    "gn:dem":220,
    "gn:feature_class":"P",
    "gn:feature_code":"PPL",
    "gn:name":"S\u0101mpla",
    "gn:population":0,
    "gn:timezone":"Asia/Kolkata",
    "iso:country":"IN",
    "ks:ks_name":"Sampla",
    "ks:ks_pop":6449,
    "ks:ks_type":"URBAN",
    "ks:ks_uagg_main":0,
    "name:eng_x_preferred":[
        "Sampla"
    ],
    "wof:name":"Sampla",
    "wof:placetype":"neighbourhood",
    "wof:population":6449
},
  "geometry": {"coordinates":[76.77597400000001,28.771503],"type":"Point"}
}