{
  "type": "Feature",
  "properties": {
    "iso:country":"IN",
    "ks:ks_name":"Majandhe",
    "ks:ks_pop":90,
    "ks:ks_type":"HABITATION",
    "name:eng_x_preferred":[
        "Majandhe"
    ],
    "wof:name":"Majandhe",
    "wof:placetype":"locality",
    "wof:population":90
},
  "geometry": {"coordinates":[74.790515,13.715552],"type":"Point"}
}