{
  "type": "Feature",
  "properties": {
    "gn:admin1_code":"12",
    "gn:admin2_code":"13.0",
    "gn:asciiname":"Sangran",
    "gn:country_code":"IN",
    "gn:dem":1897,
    "gn:feature_class":"P",
    "gn:feature_code":"PPL",
    "gn:name":"S\u0101ngran",
    "gn:population":0,
    "gn:timezone":"Asia/Kolkata",
    "iso:country":"IN",
    "wof:name":"Sangran",
    "wof:placetype":"locality"
},
  "geometry": {"coordinates":[74.90931999999999,33.73284],"type":"Point"}
}