{
  "type": "Feature",
  "properties": {
    "iso:country":"IN",
    "ks:ks_name":"Ramjodi",
    "ks:ks_pop":235,
    "ks:ks_type":"VILLAGE",
    "name:eng_x_preferred":[
        "Ramjodi"
    ],
    "wof:name":"Ramjodi",
    "wof:placetype":"locality",
    "wof:population":235
},
  "geometry": {"coordinates":[86.19265799999999,21.790429],"type":"Point"}
}