{
  "type": "Feature",
  "properties": {
    "gn:admin1_code":"36",
    "gn:admin2_code":"155.0",
    "gn:asciiname":"Pathan Khera",
    "gn:country_code":"IN",
    "gn:dem":139,
    "gn:feature_class":"P",
    "gn:feature_code":"PPL",
    "gn:name":"Path\u0101n Khera",
    "gn:population":0,
    "gn:timezone":"Asia/Kolkata",
    "iso:country":"IN",
    "wof:name":"Pathan Khera",
    "wof:placetype":"locality"
},
  "geometry": {"coordinates":[80.62130999999999,27.17739000000001],"type":"Point"}
}