{
  "type": "Feature",
  "properties": {
    "iso:country":"IN",
    "ks:ks_alt_nam":"Manjhi tola",
    "ks:ks_name":"Manjhi Tola",
    "ks:ks_pop":195,
    "ks:ks_type":"HABITATION",
    "ks:ks_uagg_main":0,
    "name:eng_x_preferred":[
        "Manjhi Tola"
    ],
    "wof:name":"Manjhi Tola",
    "wof:placetype":"neighbourhood",
    "wof:population":195
},
  "geometry": {"coordinates":[86.27595100000001,24.959846],"type":"Point"}
}