{
  "type": "Feature",
  "properties": {
    "gn:admin1_code":"36",
    "gn:admin2_code":"142.0",
    "gn:asciiname":"Biharghat",
    "gn:country_code":"IN",
    "gn:dem":182,
    "gn:feature_class":"P",
    "gn:feature_code":"PPL",
    "gn:name":"Bihargh\u0101t",
    "gn:population":0,
    "gn:timezone":"Asia/Kolkata",
    "iso:country":"IN",
    "wof:name":"Biharghat",
    "wof:placetype":"locality"
},
  "geometry": {"coordinates":[78.36102,28.23473],"type":"Point"}
}