{
  "type": "Feature",
  "properties": {
    "iso:country":"IN",
    "ks:ks_name":"Mujangavu",
    "ks:ks_pop":4038,
    "ks:ks_type":"HABITATION",
    "name:eng_x_preferred":[
        "Mujangavu"
    ],
    "wof:name":"Mujangavu",
    "wof:placetype":"locality",
    "wof:population":4038
},
  "geometry": {"coordinates":[74.98070300000001,12.595656],"type":"Point"}
}