{
  "type": "Feature",
  "properties": {
    "iso:country":"IN",
    "ks:ks_name":"Amrutamonahipatana",
    "ks:ks_pop":420,
    "ks:ks_type":"VILLAGE",
    "ks:ks_uagg_main":0,
    "name:eng_x_preferred":[
        "Amrutamonahipatana"
    ],
    "wof:name":"Amrutamonahipatana",
    "wof:placetype":"neighbourhood",
    "wof:population":420
},
  "geometry": {"coordinates":[85.601877,20.525971],"type":"Point"}
}