{
  "type": "Feature",
  "properties": {
    "iso:country":"IN",
    "ks:ks_name":"Moolachira",
    "ks:ks_pop":1144,
    "ks:ks_type":"HABITATION",
    "ks:ks_uagg_main":0,
    "name:eng_x_preferred":[
        "Moolachira"
    ],
    "wof:name":"Moolachira",
    "wof:placetype":"neighbourhood",
    "wof:population":1144
},
  "geometry": {"coordinates":[76.43075399999999,9.436],"type":"Point"}
}