{
  "type": "Feature",
  "properties": {
    "iso:country":"IN",
    "ks:ks_name":"Prem Sagar Chawaniyo Ki Dhani",
    "ks:ks_pop":150,
    "ks:ks_type":"HABITATION",
    "name:eng_x_preferred":[
        "Prem Sagar Chawaniyo Ki Dhani"
    ],
    "wof:name":"Prem Sagar Chawaniyo Ki Dhani",
    "wof:placetype":"locality",
    "wof:population":150
},
  "geometry": {"coordinates":[71.621189,25.723747],"type":"Point"}
}