{
  "type": "Feature",
  "properties": {
    "iso:country":"IN",
    "ks:ks_name":"Ughaon",
    "ks:ks_pop":373,
    "ks:ks_type":"VILLAGE",
    "name:eng_x_preferred":[
        "Ughaon"
    ],
    "wof:name":"Ughaon",
    "wof:placetype":"locality",
    "wof:population":373
},
  "geometry": {"coordinates":[82.490838,23.701101],"type":"Point"}
}