{
  "type": "Feature",
  "properties": {
    "gn:admin1_code":"36",
    "gn:admin2_code":"202.0",
    "gn:asciiname":"Nagla Taresath",
    "gn:country_code":"IN",
    "gn:dem":167,
    "gn:feature_class":"P",
    "gn:feature_code":"PPL",
    "gn:name":"Nagla Taresath",
    "gn:population":0,
    "gn:timezone":"Asia/Kolkata",
    "iso:country":"IN",
    "wof:name":"Nagla Taresath",
    "wof:placetype":"locality"
},
  "geometry": {"coordinates":[78.70319000000001,27.72299000000001],"type":"Point"}
}