{
  "type": "Feature",
  "properties": {
    "gn:admin1_code":"39.0",
    "gn:admin2_code":"66.0",
    "gn:asciiname":"Shiblaipur Joshi",
    "gn:country_code":"IN",
    "gn:dem":351,
    "gn:feature_class":"P",
    "gn:feature_code":"PPL",
    "gn:name":"Shibl\u0101ipur Joshi",
    "gn:population":0,
    "gn:timezone":"Asia/Kolkata",
    "iso:country":"IN",
    "wof:name":"Shiblaipur Joshi",
    "wof:placetype":"locality"
},
  "geometry": {"coordinates":[79.22529,29.31046],"type":"Point"}
}