{
  "type": "Feature",
  "properties": {
    "gn:admin1_code":"39.0",
    "gn:admin2_code":"64.0",
    "gn:asciiname":"Jaicholi",
    "gn:country_code":"IN",
    "gn:dem":1403,
    "gn:feature_class":"P",
    "gn:feature_code":"PPL",
    "gn:name":"Jaicholi",
    "gn:population":0,
    "gn:timezone":"Asia/Kolkata",
    "iso:country":"IN",
    "ks:ks_name":"Jaicholi",
    "ks:ks_pop":611,
    "ks:ks_type":"VILLAGE",
    "name:eng_x_preferred":[
        "Jaicholi"
    ],
    "wof:name":"Jaicholi",
    "wof:placetype":"locality",
    "wof:population":611
},
  "geometry": {"coordinates":[79.59653900000001,29.7783],"type":"Point"}
}