{
  "type": "Feature",
  "properties": {
    "gn:admin1_code":"39.0",
    "gn:admin2_code":"64.0",
    "gn:asciiname":"Jaicholi",
    "gn:country_code":"IN",
    "gn:dem":1403,
    "gn:feature_class":"P",
    "gn:feature_code":"PPL",
    "gn:name":"Jaicholi",
    "gn:population":0,
    "gn:timezone":"Asia/Kolkata",
    "iso:country":"IN",
    "wof:name":"Jaicholi",
    "wof:placetype":"locality"
},
  "geometry": {"coordinates":[79.59718000000002,29.78195],"type":"Point"}
}