{
  "type": "Feature",
  "properties": {
    "gn:admin1_code":"20",
    "gn:admin2_code":"270.0",
    "gn:asciiname":"Lazami",
    "gn:country_code":"IN",
    "gn:dem":1329,
    "gn:feature_class":"P",
    "gn:feature_code":"PPL",
    "gn:name":"Lazami",
    "gn:population":0,
    "gn:timezone":"Asia/Kolkata",
    "iso:country":"IN",
    "name:und_x_variant":[
        "Lozema",
        "Lazami"
    ],
    "wof:name":"Lazami",
    "wof:placetype":"locality"
},
  "geometry": {"coordinates":[94.24930000000001,25.8569],"type":"Point"}
}