{
  "type": "Feature",
  "properties": {
    "iso:country":"IN",
    "ks:ks_name":"Kumarakottai",
    "ks:ks_pop":411,
    "ks:ks_type":"HABITATION",
    "name:eng_x_preferred":[
        "Kumarakottai"
    ],
    "wof:name":"Kumarakottai",
    "wof:placetype":"locality",
    "wof:population":411
},
  "geometry": {"coordinates":[79.267729,10.782354],"type":"Point"}
}