{
  "type": "Feature",
  "properties": {
    "iso:country":"IN",
    "ks:ks_name":"Paswan Tola-1",
    "ks:ks_pop":250,
    "ks:ks_type":"HABITATION",
    "name:eng_x_preferred":[
        "Paswan Tola-1"
    ],
    "wof:name":"Paswan Tola-1",
    "wof:placetype":"locality",
    "wof:population":250
},
  "geometry": {"coordinates":[86.97407699999999,26.514917],"type":"Point"}
}