{
  "type": "Feature",
  "properties": {
    "iso:country":"IN",
    "ks:ks_name":"Belgaon",
    "ks:ks_pop":553,
    "ks:ks_type":"VILLAGE",
    "name:eng_x_preferred":[
        "Belgaon"
    ],
    "wof:name":"Belgaon",
    "wof:placetype":"locality",
    "wof:population":553
},
  "geometry": {"coordinates":[82.109925,24.567786],"type":"Point"}
}