{
  "type": "Feature",
  "properties": {
    "gn:admin1_code":"36.0",
    "gn:admin2_code":"166.0",
    "gn:asciiname":"Bhagwantpura",
    "gn:country_code":"IN",
    "gn:dem":165,
    "gn:feature_class":"P",
    "gn:feature_code":"PPL",
    "gn:name":"Bhagwantpura",
    "gn:population":0,
    "gn:timezone":"Asia/Kolkata",
    "iso:country":"IN",
    "wof:name":"Bhagwantpura",
    "wof:placetype":"locality"
},
  "geometry": {"coordinates":[79.24056,25.53068],"type":"Point"}
}