{
  "type": "Feature",
  "properties": {
    "iso:country":"IN",
    "ks:ks_name":"Tanti Tola",
    "ks:ks_pop":480,
    "ks:ks_type":"HABITATION",
    "name:eng_x_preferred":[
        "Tanti Tola"
    ],
    "wof:name":"Tanti Tola",
    "wof:placetype":"locality",
    "wof:population":480
},
  "geometry": {"coordinates":[86.981621,25.105377],"type":"Point"}
}