{
  "type": "Feature",
  "properties": {
    "iso:country":"IN",
    "ks:ks_name":"N. Bari",
    "ks:ks_pop":207,
    "ks:ks_type":"HABITATION",
    "name:eng_x_preferred":[
        "N. Bari"
    ],
    "wof:name":"N. Bari",
    "wof:placetype":"locality",
    "wof:population":207
},
  "geometry": {"coordinates":[78.771201,27.087298],"type":"Point"}
}