{
  "type": "Feature",
  "properties": {
    "gn:admin1_code":"37.0",
    "gn:admin2_code":"416.0",
    "gn:asciiname":"Silger",
    "gn:country_code":"IN",
    "gn:dem":191,
    "gn:feature_class":"P",
    "gn:feature_code":"PPL",
    "gn:name":"Silger",
    "gn:population":0,
    "gn:timezone":"Asia/Kolkata",
    "iso:country":"IN",
    "ks:ks_name":"Silger",
    "ks:ks_pop":523,
    "ks:ks_type":"VILLAGE",
    "name:eng_x_preferred":[
        "Silger"
    ],
    "name:und_x_variant":[
        "Chillangarh"
    ],
    "wof:name":"Silger",
    "wof:placetype":"locality",
    "wof:population":523
},
  "geometry": {"coordinates":[81.044349,18.479729],"type":"Point"}
}