{
  "type": "Feature",
  "properties": {
    "gn:admin1_code":"36.0",
    "gn:admin2_code":"183.0",
    "gn:asciiname":"Piprahwa",
    "gn:country_code":"IN",
    "gn:dem":106,
    "gn:feature_class":"P",
    "gn:feature_code":"PPL",
    "gn:name":"Piprahwa",
    "gn:population":0,
    "gn:timezone":"Asia/Kolkata",
    "iso:country":"IN",
    "name:deu_x_preferred":[
        "Piprahwa"
    ],
    "name:fra_x_preferred":[
        "Pipr\u00e2w\u00e2"
    ],
    "name:por_x_preferred":[
        "P\u00edprava"
    ],
    "name:sqi_x_preferred":[
        "Piprahwa"
    ],
    "name:tam_x_preferred":[
        "\u0baa\u0bbf\u0baa\u0bcd\u0bb0\u0bb5\u0bbe"
    ],
    "name:tha_x_preferred":[
        "\u0e2b\u0e21\u0e39\u0e48\u0e1a\u0e49\u0e32\u0e19\u0e1b\u0e34\u0e1b\u0e23\u0e32\u0e2b\u0e4c\u0e27\u0e32"
    ],
    "name:vie_x_preferred":[
        "Piprahwa"
    ],
    "name:zho_x_preferred":[
        "\u6bd4\u666e\u7f85\u74e6"
    ],
    "wof:name":"Piprahwa",
    "wof:placetype":"locality"
},
  "geometry": {"coordinates":[82.17025,27.13414],"type":"Point"}
}