{
  "type": "Feature",
  "properties": {
    "iso:country":"IN",
    "ks:ks_name":"Badkaranjia",
    "ks:ks_pop":541,
    "ks:ks_type":"VILLAGE",
    "name:eng_x_preferred":[
        "Badkaranjia"
    ],
    "wof:name":"Badkaranjia",
    "wof:placetype":"locality",
    "wof:population":541
},
  "geometry": {"coordinates":[86.606076,21.733863],"type":"Point"}
}