{
  "type": "Feature",
  "properties": {
    "iso:country":"IN",
    "ks:ks_name":"Raghorampattmafi",
    "ks:ks_pop":275,
    "ks:ks_type":"HABITATION",
    "name:eng_x_preferred":[
        "Raghorampattmafi"
    ],
    "wof:name":"Raghorampattmafi",
    "wof:placetype":"locality",
    "wof:population":275
},
  "geometry": {"coordinates":[82.58996,25.476484],"type":"Point"}
}