{
  "type": "Feature",
  "properties": {
    "iso:country":"IN",
    "ks:ks_name":"Brahamantal",
    "ks:ks_pop":302,
    "ks:ks_type":"VILLAGE",
    "name:eng_x_preferred":[
        "Brahamantal"
    ],
    "wof:name":"Brahamantal",
    "wof:placetype":"locality",
    "wof:population":302
},
  "geometry": {"coordinates":[82.768258,20.822578],"type":"Point"}
}