{
  "type": "Feature",
  "properties": {
    "gn:admin1_code":"35.0",
    "gn:admin2_code":"444",
    "gn:asciiname":"Garha Kalan",
    "gn:country_code":"IN",
    "gn:dem":490,
    "gn:feature_class":"P",
    "gn:feature_code":"PPL",
    "gn:name":"Garha Kal\u0101n",
    "gn:population":0,
    "gn:timezone":"Asia/Kolkata",
    "iso:country":"IN",
    "name:und_x_variant":[
        "Garha",
        "Garha Kal\u0101n"
    ],
    "wof:name":"Garha Kalan",
    "wof:placetype":"locality"
},
  "geometry": {"coordinates":[77.33956999999999,23.74513],"type":"Point"}
}