{
  "type": "Feature",
  "properties": {
    "iso:country":"IN",
    "ks:ks_name":"Semariya",
    "ks:ks_pop":413,
    "ks:ks_type":"VILLAGE",
    "name:eng_x_preferred":[
        "Semariya"
    ],
    "wof:name":"Semariya",
    "wof:placetype":"locality",
    "wof:population":413
},
  "geometry": {"coordinates":[84.736853,22.497786],"type":"Point"}
}