{
  "type": "Feature",
  "properties": {
    "iso:country":"IN",
    "ks:ks_name":"Rungurnguba",
    "ks:ks_pop":246,
    "ks:ks_type":"VILLAGE",
    "name:eng_x_preferred":[
        "Rungurnguba"
    ],
    "wof:name":"Rungurnguba",
    "wof:placetype":"locality",
    "wof:population":246
},
  "geometry": {"coordinates":[84.039002,19.039185],"type":"Point"}
}