{
  "type": "Feature",
  "properties": {
    "gn:admin1_code":"12.0",
    "gn:admin2_code":"12.0",
    "gn:asciiname":"Dogom",
    "gn:country_code":"IN",
    "gn:dem":1595,
    "gn:feature_class":"P",
    "gn:feature_code":"PPL",
    "gn:name":"Dogom",
    "gn:population":0,
    "gn:timezone":"Asia/Kolkata",
    "iso:country":"IN",
    "wof:name":"Dogom",
    "wof:placetype":"locality"
},
  "geometry": {"coordinates":[74.93789,33.93121],"type":"Point"}
}