{
  "type": "Feature",
  "properties": {
    "iso:country":"IN",
    "ks:ks_name":"Rajuguttatanda",
    "ks:ks_pop":89,
    "ks:ks_type":"HABITATION",
    "name:eng_x_preferred":[
        "Rajuguttatanda"
    ],
    "wof:name":"Rajuguttatanda",
    "wof:placetype":"locality",
    "wof:population":89
},
  "geometry": {"coordinates":[77.553325,16.978378],"type":"Point"}
}