{
  "type": "Feature",
  "properties": {
    "iso:country":"IN",
    "ks:ks_alt_nam":"Bazarghat FV",
    "ks:ks_name":"Bazarghat Fv",
    "ks:ks_pop":975,
    "ks:ks_type":"HABITATION",
    "ks:ks_uagg_main":0,
    "name:eng_x_preferred":[
        "Bazarghat Fv"
    ],
    "wof:name":"Bazarghat Fv",
    "wof:placetype":"neighbourhood",
    "wof:population":975
},
  "geometry": {"coordinates":[92.29389500000001,24.358588],"type":"Point"}
}