{
  "type": "Feature",
  "properties": {
    "iso:country":"IN",
    "ks:ks_name":"Mundavara",
    "ks:ks_pop":200,
    "ks:ks_type":"HABITATION",
    "name:eng_x_preferred":[
        "Mundavara"
    ],
    "wof:name":"Mundavara",
    "wof:placetype":"locality",
    "wof:population":200
},
  "geometry": {"coordinates":[76.177334,11.631226],"type":"Point"}
}