{
  "type": "Feature",
  "properties": {
    "iso:country":"IN",
    "ks:ks_name":"Bodila",
    "ks:ks_pop":310,
    "ks:ks_type":"VILLAGE",
    "name:eng_x_preferred":[
        "Bodila"
    ],
    "wof:name":"Bodila",
    "wof:placetype":"locality",
    "wof:population":310
},
  "geometry": {"coordinates":[81.613196,23.377373],"type":"Point"}
}