{
  "type": "Feature",
  "properties": {
    "iso:country":"IN",
    "ks:ks_name":"Banekarwadi",
    "ks:ks_pop":168,
    "ks:ks_type":"HABITATION",
    "name:eng_x_preferred":[
        "Banekarwadi"
    ],
    "wof:name":"Banekarwadi",
    "wof:placetype":"locality",
    "wof:population":168
},
  "geometry": {"coordinates":[73.903181,16.935839],"type":"Point"}
}