{
  "type": "Feature",
  "properties": {
    "iso:country":"IN",
    "ks:ks_name":"Mori Parasi",
    "ks:ks_type":"VILLAGE",
    "name:eng_x_preferred":[
        "Mori Parasi"
    ],
    "wof:name":"Mori Parasi",
    "wof:placetype":"locality"
},
  "geometry": {"coordinates":[82.715864,26.973316],"type":"Point"}
}