{
  "type": "Feature",
  "properties": {
    "iso:country":"IN",
    "ks:ks_name":"Dangra",
    "ks:ks_pop":326,
    "ks:ks_type":"VILLAGE",
    "ks:ks_uagg_main":0,
    "name:eng_x_preferred":[
        "Dangra"
    ],
    "wof:name":"Dangra",
    "wof:placetype":"neighbourhood",
    "wof:population":326
},
  "geometry": {"coordinates":[86.575373,22.458842],"type":"Point"}
}