{
  "type": "Feature",
  "properties": {
    "iso:country":"IN",
    "ks:ks_name":"Sakripadar",
    "ks:ks_pop":145,
    "ks:ks_type":"VILLAGE",
    "name:eng_x_preferred":[
        "Sakripadar"
    ],
    "wof:name":"Sakripadar",
    "wof:placetype":"locality",
    "wof:population":145
},
  "geometry": {"coordinates":[83.72634100000001,20.020866],"type":"Point"}
}