{
  "type": "Feature",
  "properties": {
    "iso:country":"IN",
    "ks:ks_name":"Lekrakhanda",
    "ks:ks_pop":58,
    "ks:ks_type":"VILLAGE",
    "name:eng_x_preferred":[
        "Lekrakhanda"
    ],
    "wof:name":"Lekrakhanda",
    "wof:placetype":"locality",
    "wof:population":58
},
  "geometry": {"coordinates":[86.635823,23.106602],"type":"Point"}
}