{
  "type": "Feature",
  "properties": {
    "iso:country":"IN",
    "ks:ks_name":"Barabanki",
    "ks:ks_pop":161,
    "ks:ks_type":"HABITATION",
    "name:eng_x_preferred":[
        "Barabanki"
    ],
    "wof:name":"Barabanki",
    "wof:placetype":"locality",
    "wof:population":161
},
  "geometry": {"coordinates":[85.961568,21.040304],"type":"Point"}
}