{
  "type": "Feature",
  "properties": {
    "gn:admin1_code":"35",
    "gn:admin2_code":"426.0",
    "gn:asciiname":"Gurji",
    "gn:country_code":"IN",
    "gn:dem":475,
    "gn:feature_class":"P",
    "gn:feature_code":"PPL",
    "gn:name":"Gurji",
    "gn:population":0,
    "gn:timezone":"Asia/Kolkata",
    "iso:country":"IN",
    "wof:name":"Gurji",
    "wof:placetype":"locality"
},
  "geometry": {"coordinates":[80.45623000000001,24.23964],"type":"Point"}
}