{
  "type": "Feature",
  "properties": {
    "iso:country":"IN",
    "ks:ks_name":"Oridipur",
    "ks:ks_pop":2106,
    "ks:ks_type":"HABITATION",
    "name:eng_x_preferred":[
        "Oridipur"
    ],
    "wof:name":"Oridipur",
    "wof:placetype":"locality",
    "wof:population":2106
},
  "geometry": {"coordinates":[82.93512699999999,26.04434],"type":"Point"}
}