{
  "type": "Feature",
  "properties": {
    "iso:country":"IN",
    "ks:ks_alt_nam":"PAtel faliya",
    "ks:ks_name":"Patel Faliya",
    "ks:ks_pop":247,
    "ks:ks_type":"HABITATION",
    "name:eng_x_preferred":[
        "Patel Faliya"
    ],
    "wof:name":"Patel Faliya",
    "wof:placetype":"locality",
    "wof:population":247
},
  "geometry": {"coordinates":[73.408306,20.604583],"type":"Point"}
}