{
  "type": "Feature",
  "properties": {
    "gn:admin1_code":"36.0",
    "gn:admin2_code":"154.0",
    "gn:asciiname":"Khiria",
    "gn:country_code":"IN",
    "gn:dem":137,
    "gn:feature_class":"P",
    "gn:feature_code":"PPL",
    "gn:name":"Khiria",
    "gn:population":0,
    "gn:timezone":"Asia/Kolkata",
    "iso:country":"IN",
    "name:tam_x_preferred":[
        "\u0b95\u0bc0\u0bb0\u0bbf\u0baf\u0bbe"
    ],
    "wof:name":"Khiria",
    "wof:placetype":"neighbourhood"
},
  "geometry": {"coordinates":[80.70737,27.35624],"type":"Point"}
}