{
  "type": "Feature",
  "properties": {
    "gn:admin1_code":"19.0",
    "gn:admin2_code":"571.0",
    "gn:asciiname":"Jampenahalli",
    "gn:country_code":"IN",
    "gn:dem":782,
    "gn:feature_class":"P",
    "gn:feature_code":"PPL",
    "gn:name":"Jampenahalli",
    "gn:population":0,
    "gn:timezone":"Asia/Kolkata",
    "iso:country":"IN",
    "wof:name":"Jampenahalli",
    "wof:placetype":"locality"
},
  "geometry": {"coordinates":[77.21043,13.50707],"type":"Point"}
}