{
  "type": "Feature",
  "properties": {
    "iso:country":"IN",
    "ks:ks_name":"Ayyankoilpatti",
    "ks:ks_pop":247,
    "ks:ks_type":"HABITATION",
    "name:eng_x_preferred":[
        "Ayyankoilpatti"
    ],
    "wof:name":"Ayyankoilpatti",
    "wof:placetype":"locality",
    "wof:population":247
},
  "geometry": {"coordinates":[78.348465,9.410508],"type":"Point"}
}