{
  "type": "Feature",
  "properties": {
    "iso:country":"IN",
    "ks:ks_name":"Nagzari",
    "ks:ks_pop":465,
    "ks:ks_type":"VILLAGE",
    "name:eng_x_preferred":[
        "Nagzari"
    ],
    "wof:name":"Nagzari",
    "wof:placetype":"locality",
    "wof:population":465
},
  "geometry": {"coordinates":[76.66608600000001,20.100704],"type":"Point"}
}