{
  "type": "Feature",
  "properties": {
    "iso:country":"IN",
    "ks:ks_name":"Sri Krishan Nagar",
    "ks:ks_pop":604,
    "ks:ks_type":"HABITATION",
    "name:eng_x_preferred":[
        "Sri Krishan Nagar"
    ],
    "wof:name":"Sri Krishan Nagar",
    "wof:placetype":"locality",
    "wof:population":604
},
  "geometry": {"coordinates":[73.27175800000001,26.624025],"type":"Point"}
}