{
  "type": "Feature",
  "properties": {
    "iso:country":"IN",
    "ks:ks_name":"Swarooppura",
    "ks:ks_pop":632,
    "ks:ks_type":"HABITATION",
    "name:eng_x_preferred":[
        "Swarooppura"
    ],
    "wof:name":"Swarooppura",
    "wof:placetype":"locality",
    "wof:population":632
},
  "geometry": {"coordinates":[76.159417,26.708881],"type":"Point"}
}