{
  "type": "Feature",
  "properties": {
    "iso:country":"IN",
    "ks:ks_name":"Fatehpur",
    "ks:ks_pop":0,
    "ks:ks_type":"VILLAGE",
    "ks:ks_uagg_main":0,
    "name:eng_x_preferred":[
        "Fatehpur"
    ],
    "wof:name":"Fatehpur",
    "wof:placetype":"neighbourhood",
    "wof:population":0
},
  "geometry": {"coordinates":[86.037313,25.717453],"type":"Point"}
}