{
  "type": "Feature",
  "properties": {
    "gn:admin1_code":"35",
    "gn:admin2_code":"451.0",
    "gn:asciiname":"Sukha",
    "gn:country_code":"IN",
    "gn:dem":388,
    "gn:feature_class":"P",
    "gn:feature_code":"PPL",
    "gn:name":"S\u016bkha",
    "gn:population":0,
    "gn:timezone":"Asia/Kolkata",
    "iso:country":"IN",
    "name:fra_x_preferred":[
        "Sukha"
    ],
    "name:hin_x_preferred":[
        "\u0938\u0941\u0916"
    ],
    "name:srp_x_preferred":[
        "Sre\u0107a"
    ],
    "name:zho_x_preferred":[
        "\u6a02"
    ],
    "wof:name":"Sukha",
    "wof:placetype":"locality"
},
  "geometry": {"coordinates":[79.86454000000001,23.20907],"type":"Point"}
}