{
  "type": "Feature",
  "properties": {
    "iso:country":"IN",
    "ks:ks_name":"Putrimahul",
    "ks:ks_pop":415,
    "ks:ks_type":"VILLAGE",
    "name:eng_x_preferred":[
        "Putrimahul"
    ],
    "wof:name":"Putrimahul",
    "wof:placetype":"locality",
    "wof:population":415
},
  "geometry": {"coordinates":[83.660775,20.118417],"type":"Point"}
}