{
  "type": "Feature",
  "properties": {
    "iso:country":"IN",
    "ks:ks_name":"Ramainagar",
    "ks:ks_pop":56,
    "ks:ks_type":"HABITATION",
    "name:eng_x_preferred":[
        "Ramainagar"
    ],
    "wof:name":"Ramainagar",
    "wof:placetype":"locality",
    "wof:population":56
},
  "geometry": {"coordinates":[73.69202799999999,16.07202],"type":"Point"}
}