{
  "type": "Feature",
  "properties": {
    "gn:admin1_code":"36.0",
    "gn:admin2_code":"155.0",
    "gn:asciiname":"Chanda Purwa",
    "gn:country_code":"IN",
    "gn:dem":152,
    "gn:feature_class":"P",
    "gn:feature_code":"PPL",
    "gn:name":"Chanda Purwa",
    "gn:population":0,
    "gn:timezone":"Asia/Kolkata",
    "iso:country":"IN",
    "ks:ks_name":"Chandra Purwa",
    "ks:ks_pop":129,
    "ks:ks_type":"HABITATION",
    "name:eng_x_preferred":[
        "Chandra Purwa"
    ],
    "name:eng_x_variant":[
        "Chanda Purwa"
    ],
    "wof:name":"Chandra Purwa",
    "wof:placetype":"locality",
    "wof:population":129
},
  "geometry": {"coordinates":[80.174892,27.6414],"type":"Point"}
}