{
  "type": "Feature",
  "properties": {
    "iso:country":"IN",
    "ks:ks_name":"Muhpada",
    "ks:ks_pop":56,
    "ks:ks_type":"HABITATION",
    "name:eng_x_preferred":[
        "Muhpada"
    ],
    "wof:name":"Muhpada",
    "wof:placetype":"locality",
    "wof:population":56
},
  "geometry": {"coordinates":[73.20654399999999,19.738262],"type":"Point"}
}