{
  "type": "Feature",
  "properties": {
    "gn:admin1_code":"39.0",
    "gn:admin2_code":"66.0",
    "gn:asciiname":"Bagaur",
    "gn:country_code":"IN",
    "gn:dem":1507,
    "gn:feature_class":"P",
    "gn:feature_code":"PPL",
    "gn:name":"Bagaur",
    "gn:population":0,
    "gn:timezone":"Asia/Kolkata",
    "iso:country":"IN",
    "ks:ks_name":"Bagaur",
    "ks:ks_pop":110,
    "ks:ks_type":"VILLAGE",
    "name:eng_x_preferred":[
        "Bagaur"
    ],
    "wof:name":"Bagaur",
    "wof:placetype":"locality",
    "wof:population":110
},
  "geometry": {"coordinates":[79.88396299999999,29.361597],"type":"Point"}
}