{
  "type": "Feature",
  "properties": {
    "iso:country":"IN",
    "ks:ks_name":"Rangiriguda",
    "ks:ks_pop":44,
    "ks:ks_type":"HABITATION",
    "name:eng_x_preferred":[
        "Rangiriguda"
    ],
    "wof:name":"Rangiriguda",
    "wof:placetype":"locality",
    "wof:population":44
},
  "geometry": {"coordinates":[82.10058600000001,18.386314],"type":"Point"}
}