{
  "type": "Feature",
  "properties": {
    "gn:admin1_code":"36",
    "gn:admin2_code":"183.0",
    "gn:asciiname":"Mardan",
    "gn:country_code":"IN",
    "gn:dem":108,
    "gn:feature_class":"P",
    "gn:feature_code":"PPL",
    "gn:name":"Mard\u0101n",
    "gn:population":0,
    "gn:timezone":"Asia/Kolkata",
    "iso:country":"IN",
    "name:ara_x_preferred":[
        "\u0645\u0631\u062f\u0627\u0646"
    ],
    "name:azb_x_preferred":[
        "\u0645\u0631\u062f\u0627\u0646"
    ],
    "name:ceb_x_preferred":[
        "Mardan"
    ],
    "name:dan_x_preferred":[
        "Mardan"
    ],
    "name:deu_x_preferred":[
        "Mardan"
    ],
    "name:fas_x_preferred":[
        "\u0645\u0631\u062f\u0627\u0646"
    ],
    "name:fin_x_preferred":[
        "Mardan"
    ],
    "name:fra_x_preferred":[
        "Mardan"
    ],
    "name:hin_x_preferred":[
        "\u092e\u0930\u0926\u093e\u0928"
    ],
    "name:ita_x_preferred":[
        "Mardan"
    ],
    "name:jpn_x_preferred":[
        "\u30de\u30eb\u30c0\u30f3"
    ],
    "name:kor_x_preferred":[
        "\ub9c8\ub974\ub2e8"
    ],
    "name:lit_x_preferred":[
        "Mardanas"
    ],
    "name:msa_x_preferred":[
        "Mardan"
    ],
    "name:nep_x_preferred":[
        "\u092e\u0930\u0926\u093e\u0928"
    ],
    "name:nor_x_preferred":[
        "Mardan"
    ],
    "name:pnb_x_preferred":[
        "\u0645\u0631\u062f\u0627\u0646"
    ],
    "name:pol_x_preferred":[
        "Mardan"
    ],
    "name:por_x_preferred":[
        "Mardan"
    ],
    "name:pus_x_preferred":[
        "\u0645\u0631\u062f\u0627\u0646"
    ],
    "name:rus_x_preferred":[
        "\u041c\u0430\u0440\u0434\u0430\u043d"
    ],
    "name:spa_x_preferred":[
        "Mardan"
    ],
    "name:srp_x_preferred":[
        "\u041c\u0430\u0440\u0434\u0430\u043d"
    ],
    "name:swe_x_preferred":[
        "Mardan"
    ],
    "name:urd_x_preferred":[
        "\u0645\u0631\u062f\u0627\u0646"
    ],
    "name:vie_x_preferred":[
        "Mardan"
    ],
    "name:war_x_preferred":[
        "Mardan"
    ],
    "name:xmf_x_preferred":[
        "\u10db\u10d0\u10e0\u10d3\u10d0\u10dc\u10d8"
    ],
    "name:zho_x_preferred":[
        "\u99ac\u723e\u4e39"
    ],
    "wof:name":"Mardan",
    "wof:placetype":"locality"
},
  "geometry": {"coordinates":[81.86787,27.0831],"type":"Point"}
}