{
  "type": "Feature",
  "properties": {
    "gn:admin1_code":"25.0",
    "gn:admin2_code":"608.0",
    "gn:asciiname":"Ervadi",
    "gn:country_code":"IN",
    "gn:dem":347,
    "gn:feature_class":"P",
    "gn:feature_code":"PPL",
    "gn:name":"Erv\u0101di",
    "gn:population":0,
    "gn:timezone":"Asia/Kolkata",
    "iso:country":"IN",
    "ks:ks_name":"Erwadi",
    "ks:ks_pop":406,
    "ks:ks_type":"HABITATION",
    "ks:ks_uagg_main":0,
    "name:eng_x_preferred":[
        "Erwadi"
    ],
    "wof:name":"Erwadi",
    "wof:placetype":"neighbourhood",
    "wof:population":406
},
  "geometry": {"coordinates":[77.909361,11.818281],"type":"Point"}
}