{
  "type": "Feature",
  "properties": {
    "iso:country":"IN",
    "ks:ks_name":"Mavadukurichi East",
    "ks:ks_pop":1964,
    "ks:ks_type":"VILLAGE",
    "ks:ks_uagg_main":0,
    "name:eng_x_preferred":[
        "Mavadukurichi East"
    ],
    "wof:name":"Mavadukurichi East",
    "wof:placetype":"locality",
    "wof:population":1964
},
  "geometry": {"coordinates":[79.210307,10.300302],"type":"Point"}
}