{
  "type": "Feature",
  "properties": {
    "iso:country":"IN",
    "ks:ks_name":"19 AMS",
    "ks:ks_pop":109,
    "ks:ks_type":"VILLAGE",
    "name:eng_x_preferred":[
        "19 AMS"
    ],
    "wof:name":"19 AMS",
    "wof:placetype":"locality",
    "wof:population":109
},
  "geometry": {"coordinates":[75.191506,29.185892],"type":"Point"}
}