{
  "type": "Feature",
  "properties": {
    "gn:admin1_code":"23",
    "gn:admin2_code":"39.0",
    "gn:asciiname":"Jandiala",
    "gn:country_code":"IN",
    "gn:dem":249,
    "gn:feature_class":"P",
    "gn:feature_code":"PPL",
    "gn:name":"Jandi\u0101l\u0101",
    "gn:population":0,
    "gn:timezone":"Asia/Kolkata",
    "iso:country":"IN",
    "name:ben_x_preferred":[
        "\u099c\u09be\u09a8\u09cd\u09a6\u09bf\u09af\u09bc\u09be\u09b2\u09be"
    ],
    "name:bpy_x_preferred":[
        "\u099c\u09be\u09a8\u09cd\u09a6\u09bf\u09af\u09bc\u09be\u09b2\u09be"
    ],
    "name:ceb_x_preferred":[
        "Jandi\u0101la"
    ],
    "name:ita_x_preferred":[
        "Jandiala"
    ],
    "name:jpn_x_preferred":[
        "\u30b8\u30e3\u30f3\u30c7\u30a3\u30a2\u30fc\u30e9"
    ],
    "name:msa_x_preferred":[
        "Jandiala"
    ],
    "name:new_x_preferred":[
        "\u091c\u0928\u094d\u0926\u093f\u092f\u093e\u0932\u093e"
    ],
    "name:nld_x_preferred":[
        "Jandiala"
    ],
    "name:pan_x_preferred":[
        "\u0a1c\u0a70\u0a21\u0a3f\u0a06\u0a32\u0a3e"
    ],
    "name:por_x_preferred":[
        "Jandiala"
    ],
    "name:swe_x_preferred":[
        "Jandi\u0101la"
    ],
    "name:urd_x_preferred":[
        "\u062c\u0646\u0688\u06cc\u0627\u0644\u06c1"
    ],
    "name:vie_x_preferred":[
        "Jandiala"
    ],
    "name:zho_x_preferred":[
        "\u8a79\u8fea\u4e9a\u62c9"
    ],
    "wof:name":"Jandiala",
    "wof:placetype":"locality"
},
  "geometry": {"coordinates":[75.95721999999998,31.2262],"type":"Point"}
}