{
  "type": "Feature",
  "properties": {
    "gn:admin1_code":"36",
    "gn:admin2_code":"185.0",
    "gn:asciiname":"Amlia Mahipat Singh",
    "gn:country_code":"IN",
    "gn:dem":91,
    "gn:feature_class":"P",
    "gn:feature_code":"PPL",
    "gn:name":"Amlia Mahipat Singh",
    "gn:population":0,
    "gn:timezone":"Asia/Kolkata",
    "iso:country":"IN",
    "name:und_x_variant":[
        "Co.\u2019s Sec"
    ],
    "wof:name":"Amlia Mahipat Singh",
    "wof:placetype":"locality"
},
  "geometry": {"coordinates":[82.64279999999999,26.88497000000001],"type":"Point"}
}