{
  "type": "Feature",
  "properties": {
    "iso:country":"IN",
    "ks:ks_name":"Patharemala",
    "ks:ks_pop":210,
    "ks:ks_type":"HABITATION",
    "name:eng_x_preferred":[
        "Patharemala"
    ],
    "wof:name":"Patharemala",
    "wof:placetype":"locality",
    "wof:population":210
},
  "geometry": {"coordinates":[74.491316,18.725499],"type":"Point"}
}