{
  "type": "Feature",
  "properties": {
    "gn:admin1_code":"24",
    "gn:admin2_code":"105.0",
    "gn:asciiname":"Gillidanda",
    "gn:country_code":"IN",
    "gn:dem":185,
    "gn:feature_class":"P",
    "gn:feature_code":"PPL",
    "gn:name":"Gill\u012bdanda",
    "gn:population":0,
    "gn:timezone":"Asia/Kolkata",
    "iso:country":"IN",
    "name:asm_x_preferred":[
        "\u09ad\u099f\u09be-\u0997\u09c1\u099f\u09bf"
    ],
    "name:aze_x_preferred":[
        "\u00c7ilinga\u011fac"
    ],
    "name:ben_x_preferred":[
        "\u09a1\u09be\u0982\u0997\u09c1\u09b2\u09bf"
    ],
    "name:cat_x_preferred":[
        "B\u00f2lit"
    ],
    "name:deu_x_preferred":[
        "Guli Danda"
    ],
    "name:epo_x_preferred":[
        "Paliset-ludo"
    ],
    "name:fas_x_preferred":[
        "\u0627\u0644\u06a9 \u062f\u0648\u0644\u06a9"
    ],
    "name:glg_x_preferred":[
        "Billarda"
    ],
    "name:hin_x_preferred":[
        "\u0917\u093f\u0932\u094d\u0932\u0940 \u0921\u0902\u0921\u093e"
    ],
    "name:ita_x_preferred":[
        "Lippa"
    ],
    "name:kan_x_preferred":[
        "\u0c9a\u0cbf\u0ca8\u0ccd\u0ca8\u0cbf \u0ca6\u0cbe\u0c82\u0ca1\u0cc1"
    ],
    "name:mkd_x_preferred":[
        "\u0427\u0435\u043b\u0438\u043a-\u0447\u043e\u043c\u0430\u043a"
    ],
    "name:nld_x_preferred":[
        "Gilli-danda"
    ],
    "name:nno_x_preferred":[
        "Gilli-danda"
    ],
    "name:pan_x_preferred":[
        "\u0a17\u0a41\u0a71\u0a32\u0a40 \u0a21\u0a70\u0a21\u0a3e"
    ],
    "name:pnb_x_preferred":[
        "\u06af\u0644\u06cc \u0688\u0646\u0688\u0627"
    ],
    "name:pol_x_preferred":[
        "Klipa"
    ],
    "name:sat_x_preferred":[
        "\u1c74\u1c64\u1c68"
    ],
    "name:snd_x_preferred":[
        "\u0627\u067d\u064a \u068f\u06aa\u0631"
    ],
    "name:tam_x_preferred":[
        "\u0b95\u0bbf\u0b9f\u0bcd\u0b9f\u0bbf\u0baa\u0bcd \u0baa\u0bc1\u0bb3\u0bcd\u0bb3\u0bc1"
    ],
    "name:tcy_x_preferred":[
        "\u0c95\u0cc1\u0c9f\u0ccd\u0c9f\u0cbf\u0ca6\u0cca\u0ca3\u0ccd\u0ca3\u0cc6"
    ],
    "name:tur_x_preferred":[
        "\u00c7elik\u00e7omak"
    ],
    "name:urd_x_preferred":[
        "\u06af\u0644\u06cc \u0688\u0646\u0688\u0627"
    ],
    "wof:name":"Gillidanda",
    "wof:placetype":"locality"
},
  "geometry": {"coordinates":[77.60256,26.98355],"type":"Point"}
}