{
  "type": "Feature",
  "properties": {
    "iso:country":"IN",
    "ks:ks_alt_nam":"Panbari no 1",
    "ks:ks_name":"Panbari No 1",
    "ks:ks_pop":935,
    "ks:ks_type":"HABITATION",
    "name:eng_x_preferred":[
        "Panbari No 1"
    ],
    "wof:name":"Panbari No 1",
    "wof:placetype":"locality",
    "wof:population":935
},
  "geometry": {"coordinates":[92.462031,26.425633],"type":"Point"}
}