{
  "type": "Feature",
  "properties": {
    "gn:admin1_code":"24.0",
    "gn:admin2_code":"109.0",
    "gn:asciiname":"Dhyania ki Patti",
    "gn:country_code":"IN",
    "gn:dem":279,
    "gn:feature_class":"P",
    "gn:feature_code":"PPL",
    "gn:name":"Dhy\u0101nia ki Patti",
    "gn:population":0,
    "gn:timezone":"Asia/Kolkata",
    "iso:country":"IN",
    "wof:name":"Dhyania ki Patti",
    "wof:placetype":"locality"
},
  "geometry": {"coordinates":[76.39614,26.49571],"type":"Point"}
}