{
  "type": "Feature",
  "properties": {
    "gn:admin1_code":"19.0",
    "gn:admin2_code":"565.0",
    "gn:asciiname":"Anandevanahalli",
    "gn:country_code":"IN",
    "gn:dem":492,
    "gn:feature_class":"P",
    "gn:feature_code":"PPL",
    "gn:name":"\u0100nandevanahalli",
    "gn:population":0,
    "gn:timezone":"Asia/Kolkata",
    "iso:country":"IN",
    "ks:ks_alt_nam":"\u0100nandevanahalli",
    "ks:ks_name":"Anandevanahalli",
    "ks:ks_type":"VILLAGE",
    "name:eng_x_preferred":[
        "Anandevanahalli"
    ],
    "name:eng_x_variant":[
        "\u0100nandevanahalli"
    ],
    "wof:name":"Anandevanahalli",
    "wof:placetype":"locality"
},
  "geometry": {"coordinates":[76.218548,15.164908],"type":"Point"}
}