{
  "type": "Feature",
  "properties": {
    "iso:country":"IN",
    "ks:ks_name":"Nimagrewasti",
    "ks:ks_pop":518,
    "ks:ks_type":"HABITATION",
    "name:eng_x_preferred":[
        "Nimagrewasti"
    ],
    "wof:name":"Nimagrewasti",
    "wof:placetype":"locality",
    "wof:population":518
},
  "geometry": {"coordinates":[75.256441,17.346315],"type":"Point"}
}