{
  "type": "Feature",
  "properties": {
    "gn:admin1_code":"12.0",
    "gn:admin2_code":"7.0",
    "gn:asciiname":"Gangi",
    "gn:country_code":"IN",
    "gn:dem":503,
    "gn:feature_class":"P",
    "gn:feature_code":"PPL",
    "gn:name":"G\u0101ngi",
    "gn:population":0,
    "gn:timezone":"Asia/Kolkata",
    "iso:country":"IN",
    "name:ceb_x_preferred":[
        "Gangi"
    ],
    "name:ita_x_preferred":[
        "Gangi"
    ],
    "name:scn_x_preferred":[
        "Gangi"
    ],
    "name:sco_x_preferred":[
        "Gangi"
    ],
    "name:swe_x_preferred":[
        "Gangi"
    ],
    "wof:name":"Gangi",
    "wof:placetype":"locality"
},
  "geometry": {"coordinates":[75.70076,32.48018],"type":"Point"}
}