{
  "type": "Feature",
  "properties": {
    "iso:country":"IN",
    "ks:ks_alt_nam":"Sirk\u0101pi",
    "ks:ks_name":"Sirkapi",
    "ks:ks_type":"VILLAGE",
    "name:eng_x_preferred":[
        "Sirkapi"
    ],
    "name:eng_x_variant":[
        "Sirk\u0101pi"
    ],
    "wof:name":"Sirkapi",
    "wof:placetype":"locality"
},
  "geometry": {"coordinates":[85.629284,22.595493],"type":"Point"}
}