{
  "type": "Feature",
  "properties": {
    "iso:country":"IN",
    "ks:ks_name":"Bokkaltaggu",
    "ks:ks_pop":7,
    "ks:ks_type":"HABITATION",
    "name:eng_x_preferred":[
        "Bokkaltaggu"
    ],
    "wof:name":"Bokkaltaggu",
    "wof:placetype":"locality",
    "wof:population":7
},
  "geometry": {"coordinates":[74.715012,14.890134],"type":"Point"}
}