{
  "type": "Feature",
  "properties": {
    "iso:country":"IN",
    "ks:ks_name":"Padaljhonsa",
    "ks:ks_pop":673,
    "ks:ks_type":"VILLAGE",
    "name:eng_x_preferred":[
        "Padaljhonsa"
    ],
    "wof:name":"Padaljhonsa",
    "wof:placetype":"locality",
    "wof:population":673
},
  "geometry": {"coordinates":[74.454915,22.757974],"type":"Point"}
}