{
  "type": "Feature",
  "properties": {
    "iso:country":"IN",
    "ks:ks_name":"Jenumule",
    "ks:ks_pop":16,
    "ks:ks_type":"HABITATION",
    "name:eng_x_preferred":[
        "Jenumule"
    ],
    "wof:name":"Jenumule",
    "wof:placetype":"locality",
    "wof:population":16
},
  "geometry": {"coordinates":[74.76505899999999,14.91896],"type":"Point"}
}