{
  "type": "Feature",
  "properties": {
    "iso:country":"IN",
    "ks:ks_name":"Korti",
    "ks:ks_pop":808,
    "ks:ks_type":"VILLAGE",
    "name:eng_x_preferred":[
        "Korti"
    ],
    "wof:name":"Korti",
    "wof:placetype":"locality",
    "wof:population":808
},
  "geometry": {"coordinates":[75.651584,16.405333],"type":"Point"}
}