{
  "type": "Feature",
  "properties": {
    "iso:country":"IN",
    "ks:ks_name":"Ghola",
    "ks:ks_pop":1826,
    "ks:ks_type":"VILLAGE",
    "name:eng_x_preferred":[
        "Ghola"
    ],
    "wof:name":"Ghola",
    "wof:placetype":"locality",
    "wof:population":1826
},
  "geometry": {"coordinates":[88.569862,22.334154],"type":"Point"}
}