{
  "type": "Feature",
  "properties": {
    "iso:country":"IN",
    "ks:ks_name":"Mahmoodpur Mazra Raipur",
    "ks:ks_pop":3323,
    "ks:ks_type":"VILLAGE",
    "name:eng_x_preferred":[
        "Mahmoodpur Mazra Raipur"
    ],
    "wof:name":"Mahmoodpur Mazra Raipur",
    "wof:placetype":"locality",
    "wof:population":3323
},
  "geometry": {"coordinates":[77.612835,30.261092],"type":"Point"}
}