{
  "type": "Feature",
  "properties": {
    "iso:country":"IN",
    "ks:ks_name":"Ponniamman Nagar",
    "ks:ks_pop":310,
    "ks:ks_type":"HABITATION",
    "name:eng_x_preferred":[
        "Ponniamman Nagar"
    ],
    "wof:name":"Ponniamman Nagar",
    "wof:placetype":"locality",
    "wof:population":310
},
  "geometry": {"coordinates":[79.26226800000001,12.5888],"type":"Point"}
}