{
  "type": "Feature",
  "properties": {
    "gn:admin1_code":"19.0",
    "gn:admin2_code":"568.0",
    "gn:asciiname":"Aralikoppa",
    "gn:country_code":"IN",
    "gn:dem":596,
    "gn:feature_class":"P",
    "gn:feature_code":"PPL",
    "gn:name":"\u0100ralikoppa",
    "gn:population":0,
    "gn:timezone":"Asia/Kolkata",
    "iso:country":"IN",
    "ks:ks_name":"Aralikoppa",
    "ks:ks_pop":575,
    "ks:ks_type":"HABITATION",
    "name:eng_x_preferred":[
        "Aralikoppa"
    ],
    "wof:name":"Aralikoppa",
    "wof:placetype":"locality",
    "wof:population":575
},
  "geometry": {"coordinates":[75.08843299999999,13.935284],"type":"Point"}
}