{
  "type": "Feature",
  "properties": {
    "iso:country":"IN",
    "ks:ks_name":"Kusumapadar",
    "ks:ks_pop":0,
    "ks:ks_type":"VILLAGE",
    "name:eng_x_preferred":[
        "Kusumapadar"
    ],
    "wof:name":"Kusumapadar",
    "wof:placetype":"locality",
    "wof:population":0
},
  "geometry": {"coordinates":[83.727664,19.19505],"type":"Point"}
}