{
  "type": "Feature",
  "properties": {
    "iso:country":"IN",
    "ks:ks_name":"Champaboni",
    "ks:ks_pop":194,
    "ks:ks_type":"HABITATION",
    "ks:ks_uagg_main":0,
    "name:eng_x_preferred":[
        "Champaboni"
    ],
    "wof:name":"Champaboni",
    "wof:placetype":"neighbourhood",
    "wof:population":194
},
  "geometry": {"coordinates":[86.915335,22.56211],"type":"Point"}
}