{
  "type": "Feature",
  "properties": {
    "iso:country":"IN",
    "ks:ks_name":"Manewadi",
    "ks:ks_pop":119,
    "ks:ks_type":"HABITATION",
    "name:eng_x_preferred":[
        "Manewadi"
    ],
    "wof:name":"Manewadi",
    "wof:placetype":"locality",
    "wof:population":119
},
  "geometry": {"coordinates":[73.171136,17.66175],"type":"Point"}
}