{
  "type": "Feature",
  "properties": {
    "gn:admin1_code":"11",
    "gn:admin2_code":"23.0",
    "gn:asciiname":"Salon",
    "gn:country_code":"IN",
    "gn:dem":1825,
    "gn:feature_class":"P",
    "gn:feature_code":"PPL",
    "gn:name":"Salon",
    "gn:population":0,
    "gn:timezone":"Asia/Kolkata",
    "iso:country":"IN",
    "name:bpy_x_preferred":[
        "\u09b8\u09be\u09b2\u09cb\u09a8"
    ],
    "name:cat_x_preferred":[
        "Sal\u00f3"
    ],
    "name:ceb_x_preferred":[
        "Salon"
    ],
    "name:ces_x_preferred":[
        "Salon"
    ],
    "name:deu_x_preferred":[
        "Salon"
    ],
    "name:fra_x_preferred":[
        "Salon"
    ],
    "name:heb_x_preferred":[
        "\u05e1\u05dc\u05d5\u05df"
    ],
    "name:ita_x_preferred":[
        "Salon"
    ],
    "name:jpn_x_preferred":[
        "\u30b5\u30ed\u30f3"
    ],
    "name:msa_x_preferred":[
        "Salon"
    ],
    "name:nds_x_preferred":[
        "Salon"
    ],
    "name:nld_x_preferred":[
        "Salon"
    ],
    "name:oci_x_preferred":[
        "Salon"
    ],
    "name:pms_x_preferred":[
        "Salon"
    ],
    "name:pol_x_preferred":[
        "Salon"
    ],
    "name:ron_x_preferred":[
        "Salon"
    ],
    "name:rus_x_preferred":[
        "\u0421\u0430\u043b\u043e\u043d"
    ],
    "name:slk_x_preferred":[
        "Salon"
    ],
    "name:spa_x_preferred":[
        "Salon"
    ],
    "name:swe_x_preferred":[
        "Salon"
    ],
    "name:tur_x_preferred":[
        "Salon"
    ],
    "name:ukr_x_preferred":[
        "\u0421\u0430\u043b\u043e\u043d"
    ],
    "wof:name":"Salon",
    "wof:placetype":"locality"
},
  "geometry": {"coordinates":[76.53671999999997,32.34461],"type":"Point"}
}