{
  "type": "Feature",
  "properties": {
    "iso:country":"IN",
    "ks:ks_name":"Kashitola",
    "ks:ks_pop":903,
    "ks:ks_type":"HABITATION",
    "ks:ks_uagg_main":0,
    "name:eng_x_preferred":[
        "Kashitola"
    ],
    "wof:name":"Kashitola",
    "wof:placetype":"neighbourhood",
    "wof:population":903
},
  "geometry": {"coordinates":[85.19234299999999,23.513903],"type":"Point"}
}