{
  "type": "Feature",
  "properties": {
    "iso:country":"IN",
    "ks:ks_alt_nam":"Aam ki Sar",
    "ks:ks_name":"Aam Ki Sar",
    "ks:ks_pop":39,
    "ks:ks_type":"HABITATION",
    "name:eng_x_preferred":[
        "Aam Ki Sar"
    ],
    "wof:name":"Aam Ki Sar",
    "wof:placetype":"locality",
    "wof:population":39
},
  "geometry": {"coordinates":[79.38483100000001,29.546876],"type":"Point"}
}