{
  "type": "Feature",
  "properties": {
    "iso:country":"IN",
    "ks:ks_name":"Raginguda",
    "ks:ks_pop":171,
    "ks:ks_type":"HABITATION",
    "name:eng_x_preferred":[
        "Raginguda"
    ],
    "wof:name":"Raginguda",
    "wof:placetype":"locality",
    "wof:population":171
},
  "geometry": {"coordinates":[82.248822,18.17496],"type":"Point"}
}