{
  "type": "Feature",
  "properties": {
    "iso:country":"IN",
    "ks:ks_name":"Kochilabedi",
    "ks:ks_pop":311,
    "ks:ks_type":"VILLAGE",
    "name:eng_x_preferred":[
        "Kochilabedi"
    ],
    "wof:name":"Kochilabedi",
    "wof:placetype":"locality",
    "wof:population":311
},
  "geometry": {"coordinates":[86.44532,20.172836],"type":"Point"}
}