{
  "type": "Feature",
  "properties": {
    "gn:admin1_code":"24.0",
    "gn:admin2_code":"128.0",
    "gn:asciiname":"Chhichhroni ki Tapri",
    "gn:country_code":"IN",
    "gn:dem":342,
    "gn:feature_class":"P",
    "gn:feature_code":"PPL",
    "gn:name":"Chhichhroni ki Tapri",
    "gn:population":0,
    "gn:timezone":"Asia/Kolkata",
    "iso:country":"IN",
    "wof:name":"Chhichhroni ki Tapri",
    "wof:placetype":"locality"
},
  "geometry": {"coordinates":[76.89006999999999,25.16976],"type":"Point"}
}