{
  "type": "Feature",
  "properties": {
    "iso:country":"IN",
    "ks:ks_name":"Kanjirattanam",
    "ks:ks_pop":2946,
    "ks:ks_type":"HABITATION",
    "name:eng_x_preferred":[
        "Kanjirattanam"
    ],
    "wof:name":"Kanjirattanam",
    "wof:placetype":"locality",
    "wof:population":2946
},
  "geometry": {"coordinates":[76.527162,9.745073],"type":"Point"}
}