{
  "type": "Feature",
  "properties": {
    "iso:country":"IN",
    "ks:ks_name":"Varlebena",
    "ks:ks_pop":60,
    "ks:ks_type":"HABITATION",
    "name:eng_x_preferred":[
        "Varlebena"
    ],
    "wof:name":"Varlebena",
    "wof:placetype":"locality",
    "wof:population":60
},
  "geometry": {"coordinates":[74.322036,14.757955],"type":"Point"}
}