{
  "type": "Feature",
  "properties": {
    "iso:country":"IN",
    "ks:ks_alt_nam":"ARAKONA",
    "ks:ks_name":"Arakona",
    "ks:ks_pop":248,
    "ks:ks_type":"HABITATION",
    "name:eng_x_preferred":[
        "Arakona"
    ],
    "wof:name":"Arakona",
    "wof:placetype":"locality",
    "wof:population":248
},
  "geometry": {"coordinates":[83.98099999999999,23.027697],"type":"Point"}
}