{
  "type": "Feature",
  "properties": {
    "iso:country":"IN",
    "ks:ks_name":"Dasanakere",
    "ks:ks_pop":53,
    "ks:ks_type":"HABITATION",
    "name:eng_x_preferred":[
        "Dasanakere"
    ],
    "wof:name":"Dasanakere",
    "wof:placetype":"locality",
    "wof:population":53
},
  "geometry": {"coordinates":[75.276527,14.042553],"type":"Point"}
}