{
  "type": "Feature",
  "properties": {
    "gn:admin1_code":"16",
    "gn:admin2_code":"508.0",
    "gn:asciiname":"Bhatgaon",
    "gn:country_code":"IN",
    "gn:dem":397,
    "gn:feature_class":"P",
    "gn:feature_code":"PPL",
    "gn:name":"Bhatgaon",
    "gn:population":0,
    "gn:timezone":"Asia/Kolkata",
    "iso:country":"IN",
    "ks:ks_name":"Bhatgaon",
    "ks:ks_pop":136,
    "ks:ks_type":"VILLAGE",
    "name:cat_x_preferred":[
        "Bhatgaon"
    ],
    "name:eng_x_preferred":[
        "Bhatgaon"
    ],
    "wof:name":"Bhatgaon",
    "wof:placetype":"locality",
    "wof:population":136
},
  "geometry": {"coordinates":[80.58104299999999,20.580603],"type":"Point"}
}