{
  "type": "Feature",
  "properties": {
    "gn:admin1_code":"36.0",
    "gn:admin2_code":"150.0",
    "gn:asciiname":"Pempur",
    "gn:country_code":"IN",
    "gn:dem":177,
    "gn:feature_class":"P",
    "gn:feature_code":"PPL",
    "gn:name":"Pempur",
    "gn:population":0,
    "gn:timezone":"Asia/Kolkata",
    "iso:country":"IN",
    "ks:ks_name":"Pempur",
    "ks:ks_type":"VILLAGE",
    "name:eng_x_preferred":[
        "Pempur"
    ],
    "wof:name":"Pempur",
    "wof:placetype":"locality"
},
  "geometry": {"coordinates":[79.610163,28.460468],"type":"Point"}
}