{
  "type": "Feature",
  "properties": {
    "iso:country":"IN",
    "ks:ks_name":"Papayapeta",
    "ks:ks_pop":383,
    "ks:ks_type":"VILLAGE",
    "name:eng_x_preferred":[
        "Papayapeta"
    ],
    "wof:name":"Papayapeta",
    "wof:placetype":"locality",
    "wof:population":383
},
  "geometry": {"coordinates":[83.916657,18.861921],"type":"Point"}
}