{
  "type": "Feature",
  "properties": {
    "gn:admin1_code":"12",
    "gn:asciiname":"Banali",
    "gn:country_code":"IN",
    "gn:dem":1963,
    "gn:feature_class":"P",
    "gn:feature_code":"PPL",
    "gn:name":"Ban\u0101li",
    "gn:population":0,
    "gn:timezone":"Asia/Kolkata",
    "iso:country":"IN",
    "wof:name":"Banali",
    "wof:placetype":"locality"
},
  "geometry": {"coordinates":[74.2122,34.09650999999999],"type":"Point"}
}