{
  "type": "Feature",
  "properties": {
    "iso:country":"IN",
    "ks:ks_alt_nam":"DHANIYA TOL",
    "ks:ks_name":"Dhaniya Tol",
    "ks:ks_pop":229,
    "ks:ks_type":"HABITATION",
    "ks:ks_uagg_main":0,
    "name:eng_x_preferred":[
        "Dhaniya Tol"
    ],
    "wof:name":"Dhaniya Tol",
    "wof:placetype":"neighbourhood",
    "wof:population":229
},
  "geometry": {"coordinates":[86.379524,26.049095],"type":"Point"}
}