{
  "type": "Feature",
  "properties": {
    "iso:country":"IN",
    "ks:ks_name":"Chaugain",
    "ks:ks_pop":0,
    "ks:ks_type":"VILLAGE",
    "name:eng_x_preferred":[
        "Chaugain"
    ],
    "wof:name":"Chaugain",
    "wof:placetype":"locality",
    "wof:population":0
},
  "geometry": {"coordinates":[84.196658,24.153107],"type":"Point"}
}