{
  "type": "Feature",
  "properties": {
    "iso:country":"IN",
    "ks:ks_name":"Hatiya Pur",
    "ks:ks_pop":50,
    "ks:ks_type":"HABITATION",
    "name:eng_x_preferred":[
        "Hatiya Pur"
    ],
    "wof:name":"Hatiya Pur",
    "wof:placetype":"locality",
    "wof:population":50
},
  "geometry": {"coordinates":[74.108889,23.416111],"type":"Point"}
}