{
  "type": "Feature",
  "properties": {
    "iso:country":"IN",
    "ks:ks_name":"Karbi Suba",
    "ks:ks_pop":966,
    "ks:ks_type":"HABITATION",
    "name:eng_x_preferred":[
        "Karbi Suba"
    ],
    "wof:name":"Karbi Suba",
    "wof:placetype":"locality",
    "wof:population":966
},
  "geometry": {"coordinates":[91.986619,26.114646],"type":"Point"}
}