{
  "type": "Feature",
  "properties": {
    "iso:country":"IN",
    "ks:ks_alt_nam":"DEB PARA",
    "ks:ks_name":"Deb Para",
    "ks:ks_pop":655,
    "ks:ks_type":"HABITATION",
    "name:eng_x_preferred":[
        "Deb Para"
    ],
    "wof:name":"Deb Para",
    "wof:placetype":"locality",
    "wof:population":655
},
  "geometry": {"coordinates":[91.35728400000001,23.486785],"type":"Point"}
}