{
  "type": "Feature",
  "properties": {
    "gn:admin1_code":"40.0",
    "gn:admin2_code":"541.0",
    "gn:asciiname":"Vagottigudem",
    "gn:country_code":"IN",
    "gn:dem":127,
    "gn:feature_class":"P",
    "gn:feature_code":"PPL",
    "gn:name":"Vagottig\u016bdem",
    "gn:population":0,
    "gn:timezone":"Asia/Kolkata",
    "iso:country":"IN",
    "wof:name":"Vagottigudem",
    "wof:placetype":"locality"
},
  "geometry": {"coordinates":[81.18524000000002,17.33859],"type":"Point"}
}