{
  "type": "Feature",
  "properties": {
    "iso:country":"IN",
    "ks:ks_name":"Avalapalle",
    "ks:ks_pop":20,
    "ks:ks_type":"HABITATION",
    "name:eng_x_preferred":[
        "Avalapalle"
    ],
    "wof:name":"Avalapalle",
    "wof:placetype":"locality",
    "wof:population":20
},
  "geometry": {"coordinates":[79.03429300000001,13.436647],"type":"Point"}
}