{
  "type": "Feature",
  "properties": {
    "iso:country":"IN",
    "ks:ks_name":"Mohitewadi",
    "ks:ks_pop":59,
    "ks:ks_type":"HABITATION",
    "name:eng_x_preferred":[
        "Mohitewadi"
    ],
    "wof:name":"Mohitewadi",
    "wof:placetype":"locality",
    "wof:population":59
},
  "geometry": {"coordinates":[73.382936,17.697711],"type":"Point"}
}