{
  "type": "Feature",
  "properties": {
    "iso:country":"IN",
    "ks:ks_name":"Chapaldihi",
    "ks:ks_pop":325,
    "ks:ks_type":"VILLAGE",
    "name:eng_x_preferred":[
        "Chapaldihi"
    ],
    "wof:name":"Chapaldihi",
    "wof:placetype":"locality",
    "wof:population":325
},
  "geometry": {"coordinates":[86.554401,21.752543],"type":"Point"}
}