{
  "type": "Feature",
  "properties": {
    "iso:country":"IN",
    "ks:ks_name":"Patel",
    "ks:ks_pop":100,
    "ks:ks_type":"HABITATION",
    "name:eng_x_preferred":[
        "Patel"
    ],
    "wof:name":"Patel",
    "wof:placetype":"locality",
    "wof:population":100
},
  "geometry": {"coordinates":[74.4041,23.120525],"type":"Point"}
}