{
  "type": "Feature",
  "properties": {
    "gn:admin1_code":"25.0",
    "gn:admin2_code":"610.0",
    "gn:asciiname":"Anantampalaiyam",
    "gn:country_code":"IN",
    "gn:dem":175,
    "gn:feature_class":"P",
    "gn:feature_code":"PPL",
    "gn:name":"Anantamp\u0101laiyam",
    "gn:population":0,
    "gn:timezone":"Asia/Kolkata",
    "iso:country":"IN",
    "wof:name":"Anantampalaiyam",
    "wof:placetype":"locality"
},
  "geometry": {"coordinates":[77.79924,11.20883],"type":"Point"}
}