{
  "type": "Feature",
  "properties": {
    "iso:country":"IN",
    "ks:ks_name":"Bavi",
    "ks:ks_pop":220,
    "ks:ks_type":"HABITATION",
    "name:eng_x_preferred":[
        "Bavi"
    ],
    "wof:name":"Bavi",
    "wof:placetype":"locality",
    "wof:population":220
},
  "geometry": {"coordinates":[75.724166,18.734411],"type":"Point"}
}