{
  "type": "Feature",
  "properties": {
    "iso:country":"IN",
    "ks:ks_alt_nam":"Dumarg\u0101ri",
    "ks:ks_name":"Dumargari",
    "ks:ks_pop":900,
    "ks:ks_type":"VILLAGE",
    "name:eng_x_preferred":[
        "Dumargari"
    ],
    "name:eng_x_variant":[
        "Dumarg\u0101ri"
    ],
    "wof:name":"Dumargari",
    "wof:placetype":"locality",
    "wof:population":900
},
  "geometry": {"coordinates":[85.080313,23.21779],"type":"Point"}
}