{
  "type": "Feature",
  "properties": {
    "iso:country":"IN",
    "ks:ks_name":"Samyaknagar",
    "ks:ks_pop":265,
    "ks:ks_type":"HABITATION",
    "name:eng_x_preferred":[
        "Samyaknagar"
    ],
    "wof:name":"Samyaknagar",
    "wof:placetype":"locality",
    "wof:population":265
},
  "geometry": {"coordinates":[73.61263599999999,16.554982],"type":"Point"}
}