{
  "type": "Feature",
  "properties": {
    "gn:admin1_code":"10.0",
    "gn:admin2_code":"077",
    "gn:asciiname":"Kinana",
    "gn:country_code":"IN",
    "gn:dem":231,
    "gn:feature_class":"P",
    "gn:feature_code":"PPL",
    "gn:name":"Kin\u0101na",
    "gn:population":0,
    "gn:timezone":"Asia/Kolkata",
    "iso:country":"IN",
    "wof:name":"Kinana",
    "wof:placetype":"locality"
},
  "geometry": {"coordinates":[76.33919,29.23987],"type":"Point"}
}