{
  "type": "Feature",
  "properties": {
    "iso:country":"IN",
    "ks:ks_name":"Dornadulapalle Madigapalle",
    "ks:ks_pop":63,
    "ks:ks_type":"HABITATION",
    "name:eng_x_preferred":[
        "Dornadulapalle Madigapalle"
    ],
    "wof:name":"Dornadulapalle Madigapalle",
    "wof:placetype":"locality",
    "wof:population":63
},
  "geometry": {"coordinates":[78.92329700000001,13.88743],"type":"Point"}
}