{
  "type": "Feature",
  "properties": {
    "iso:country":"IN",
    "ks:ks_name":"Odisingi",
    "ks:ks_pop":333,
    "ks:ks_type":"HABITATION",
    "name:eng_x_preferred":[
        "Odisingi"
    ],
    "wof:name":"Odisingi",
    "wof:placetype":"locality",
    "wof:population":333
},
  "geometry": {"coordinates":[84.115061,18.908836],"type":"Point"}
}