{
  "type": "Feature",
  "properties": {
    "iso:country":"IN",
    "ks:ks_name":"Narainpur",
    "ks:ks_pop":0,
    "ks:ks_type":"VILLAGE",
    "name:eng_x_preferred":[
        "Narainpur"
    ],
    "wof:name":"Narainpur",
    "wof:placetype":"locality",
    "wof:population":0
},
  "geometry": {"coordinates":[85.853471,25.020146],"type":"Point"}
}