{
  "type": "Feature",
  "properties": {
    "iso:country":"IN",
    "ks:ks_name":"Uttar Gopalpur",
    "ks:ks_pop":1474,
    "ks:ks_type":"VILLAGE",
    "ks:ks_uagg_main":0,
    "name:eng_x_preferred":[
        "Uttar Gopalpur"
    ],
    "wof:name":"Uttar Gopalpur",
    "wof:placetype":"neighbourhood",
    "wof:population":1474
},
  "geometry": {"coordinates":[87.99185799999999,25.472065],"type":"Point"}
}