{
  "type": "Feature",
  "properties": {
    "gn:admin1_code":"36",
    "gn:admin2_code":"158.0",
    "gn:asciiname":"Haibatmau",
    "gn:country_code":"IN",
    "gn:dem":115,
    "gn:feature_class":"P",
    "gn:feature_code":"PPL",
    "gn:name":"Haibatmau",
    "gn:population":0,
    "gn:timezone":"Asia/Kolkata",
    "iso:country":"IN",
    "ks:ks_name":"Haibatmau",
    "ks:ks_pop":714,
    "ks:ks_type":"VILLAGE",
    "ks:ks_uagg_main":0,
    "name:eng_x_preferred":[
        "Haibatmau"
    ],
    "wof:name":"Haibatmau",
    "wof:placetype":"locality",
    "wof:population":714
},
  "geometry": {"coordinates":[81.32017,26.245968],"type":"Point"}
}