{
  "type": "Feature",
  "properties": {
    "gn:admin1_code":"38.0",
    "gn:admin2_code":"347.0",
    "gn:asciiname":"Malakdiha",
    "gn:country_code":"IN",
    "gn:dem":396,
    "gn:feature_class":"P",
    "gn:feature_code":"PPL",
    "gn:name":"Malakdih\u0101",
    "gn:population":0,
    "gn:timezone":"Asia/Kolkata",
    "iso:country":"IN",
    "ks:ks_alt_nam":"Malakdih\u0101",
    "ks:ks_name":"Malakdiha",
    "ks:ks_pop":159,
    "ks:ks_type":"VILLAGE",
    "name:eng_x_preferred":[
        "Malakdiha"
    ],
    "name:eng_x_variant":[
        "Malakdih\u0101"
    ],
    "wof:name":"Malakdiha",
    "wof:placetype":"locality",
    "wof:population":159
},
  "geometry": {"coordinates":[85.231831,24.335591],"type":"Point"}
}