{
  "type": "Feature",
  "properties": {
    "iso:country":"IN",
    "ks:ks_name":"Bundura Duba",
    "ks:ks_pop":870,
    "ks:ks_type":"VILLAGE",
    "name:eng_x_preferred":[
        "Bundura Duba"
    ],
    "wof:name":"Bundura Duba",
    "wof:placetype":"locality",
    "wof:population":870
},
  "geometry": {"coordinates":[92.511178,26.173854],"type":"Point"}
}