{
  "type": "Feature",
  "properties": {
    "iso:country":"IN",
    "ks:ks_alt_nam":"MUSHAHARI",
    "ks:ks_name":"Mushahari",
    "ks:ks_pop":254,
    "ks:ks_type":"HABITATION",
    "ks:ks_uagg_main":0,
    "name:eng_x_preferred":[
        "Mushahari"
    ],
    "wof:name":"Mushahari",
    "wof:placetype":"neighbourhood",
    "wof:population":254
},
  "geometry": {"coordinates":[87.357823,25.894506],"type":"Point"}
}