{
  "type": "Feature",
  "properties": {
    "gn:admin1_code":"39",
    "gn:admin2_code":"56.0",
    "gn:asciiname":"Bagi",
    "gn:country_code":"IN",
    "gn:dem":2147,
    "gn:feature_class":"P",
    "gn:feature_code":"PPL",
    "gn:name":"B\u0101gi",
    "gn:population":0,
    "gn:timezone":"Asia/Kolkata",
    "iso:country":"IN",
    "name:ceb_x_preferred":[
        "Bagi"
    ],
    "name:deu_x_preferred":[
        "Bagi"
    ],
    "name:swe_x_preferred":[
        "Bagi"
    ],
    "wof:name":"Bagi",
    "wof:placetype":"locality"
},
  "geometry": {"coordinates":[77.80304,30.95454],"type":"Point"}
}