{
  "type": "Feature",
  "properties": {
    "gn:admin1_code":"36",
    "gn:admin2_code":"177.0",
    "gn:asciiname":"Madna",
    "gn:country_code":"IN",
    "gn:dem":97,
    "gn:feature_class":"P",
    "gn:feature_code":"PPL",
    "gn:name":"Madna",
    "gn:population":0,
    "gn:timezone":"Asia/Kolkata",
    "iso:country":"IN",
    "name:ara_x_preferred":[
        "\u0645\u0627\u062f\u0646\u0629"
    ],
    "name:azb_x_preferred":[
        "\u0645\u0627\u062f\u0646\u0647"
    ],
    "name:fas_x_preferred":[
        "\u0645\u0627\u062f\u0646\u0647"
    ],
    "name:fra_x_preferred":[
        "Madna"
    ],
    "name:ita_x_preferred":[
        "Madna"
    ],
    "name:kab_x_preferred":[
        "Madna"
    ],
    "name:msa_x_preferred":[
        "Madna"
    ],
    "name:por_x_preferred":[
        "Madna"
    ],
    "name:ron_x_preferred":[
        "Madna"
    ],
    "name:spa_x_preferred":[
        "Madna"
    ],
    "name:urd_x_preferred":[
        "\u0645\u06cc\u0688\u0646\u0627"
    ],
    "name:vie_x_preferred":[
        "Madna"
    ],
    "name:zho_x_preferred":[
        "\u99ac\u5fb7\u7d0d"
    ],
    "wof:name":"Madna",
    "wof:placetype":"neighbourhood"
},
  "geometry": {"coordinates":[82.29564000000001,26.69897],"type":"Point"}
}