{
  "type": "Feature",
  "properties": {
    "iso:country":"IN",
    "ks:ks_name":"Muqimpur",
    "ks:ks_pop":5223,
    "ks:ks_type":"VILLAGE",
    "ks:ks_uagg_main":0,
    "name:eng_x_preferred":[
        "Muqimpur"
    ],
    "wof:name":"Muqimpur",
    "wof:placetype":"neighbourhood",
    "wof:population":5223
},
  "geometry": {"coordinates":[84.845825,25.833687],"type":"Point"}
}