{
  "type": "Feature",
  "properties": {
    "iso:country":"IN",
    "ks:ks_alt_nam":"GANGTIA",
    "ks:ks_name":"Gangtia",
    "ks:ks_pop":171,
    "ks:ks_type":"HABITATION",
    "name:eng_x_preferred":[
        "Gangtia"
    ],
    "wof:name":"Gangtia",
    "wof:placetype":"locality",
    "wof:population":171
},
  "geometry": {"coordinates":[86.345376,24.97193],"type":"Point"}
}