{
  "type": "Feature",
  "properties": {
    "iso:country":"IN",
    "ks:ks_name":"Kath Ganga (m)",
    "ks:ks_pop":591,
    "ks:ks_type":"HABITATION",
    "name:eng_x_preferred":[
        "Kath Ganga (m)"
    ],
    "wof:name":"Kath Ganga (m)",
    "wof:placetype":"locality",
    "wof:population":591
},
  "geometry": {"coordinates":[82.950547,26.793246],"type":"Point"}
}