{
  "type": "Feature",
  "properties": {
    "iso:country":"IN",
    "ks:ks_name":"Atariya Ryt",
    "ks:ks_pop":636,
    "ks:ks_type":"HABITATION",
    "name:eng_x_preferred":[
        "Atariya Ryt"
    ],
    "wof:name":"Atariya Ryt",
    "wof:placetype":"locality",
    "wof:population":636
},
  "geometry": {"coordinates":[81.354178,22.798392],"type":"Point"}
}