{
  "type": "Feature",
  "properties": {
    "iso:country":"IN",
    "ks:ks_alt_nam":"Baraf pada",
    "ks:ks_name":"Baraf Pada",
    "ks:ks_pop":52,
    "ks:ks_type":"HABITATION",
    "name:eng_x_preferred":[
        "Baraf Pada"
    ],
    "wof:name":"Baraf Pada",
    "wof:placetype":"locality",
    "wof:population":52
},
  "geometry": {"coordinates":[73.148482,19.84856],"type":"Point"}
}