{
  "type": "Feature",
  "properties": {
    "iso:country":"IN",
    "ks:ks_name":"Kurmel",
    "ks:ks_pop":718,
    "ks:ks_type":"VILLAGE",
    "name:eng_x_preferred":[
        "Kurmel"
    ],
    "wof:name":"Kurmel",
    "wof:placetype":"locality",
    "wof:population":718
},
  "geometry": {"coordinates":[83.428969,20.072621],"type":"Point"}
}