{
  "type": "Feature",
  "properties": {
    "iso:country":"IN",
    "ks:ks_name":"Bommanalli",
    "ks:ks_pop":85,
    "ks:ks_type":"HABITATION",
    "name:eng_x_preferred":[
        "Bommanalli"
    ],
    "wof:name":"Bommanalli",
    "wof:placetype":"locality",
    "wof:population":85
},
  "geometry": {"coordinates":[74.91848299999999,14.639894],"type":"Point"}
}