{
  "type": "Feature",
  "properties": {
    "gn:admin1_code":"36",
    "gn:admin2_code":"201.0",
    "gn:asciiname":"Subhan",
    "gn:country_code":"IN",
    "gn:dem":164,
    "gn:feature_class":"P",
    "gn:feature_code":"PPL",
    "gn:name":"Subh\u0101n",
    "gn:population":0,
    "gn:timezone":"Asia/Kolkata",
    "iso:country":"IN",
    "wof:name":"Subhan",
    "wof:placetype":"locality"
},
  "geometry": {"coordinates":[79.12893000000003,27.51349],"type":"Point"}
}