{
  "type": "Feature",
  "properties": {
    "iso:country":"IN",
    "ks:ks_name":"Kalchipodadihi",
    "ks:ks_pop":321,
    "ks:ks_type":"VILLAGE",
    "name:eng_x_preferred":[
        "Kalchipodadihi"
    ],
    "wof:name":"Kalchipodadihi",
    "wof:placetype":"locality",
    "wof:population":321
},
  "geometry": {"coordinates":[84.422186,21.470046],"type":"Point"}
}