{
  "type": "Feature",
  "properties": {
    "iso:country":"IN",
    "ks:ks_alt_nam":"MIYA TOLA",
    "ks:ks_name":"Miya Tola",
    "ks:ks_pop":364,
    "ks:ks_type":"HABITATION",
    "name:eng_x_preferred":[
        "Miya Tola"
    ],
    "wof:name":"Miya Tola",
    "wof:placetype":"locality",
    "wof:population":364
},
  "geometry": {"coordinates":[86.55927699999999,26.224072],"type":"Point"}
}