{
  "type": "Feature",
  "properties": {
    "iso:country":"IN",
    "ks:ks_name":"Raidang Bongali Gaon",
    "ks:ks_pop":296,
    "ks:ks_type":"VILLAGE",
    "ks:ks_uagg_main":0,
    "name:eng_x_preferred":[
        "Raidang Bongali Gaon"
    ],
    "wof:name":"Raidang Bongali Gaon",
    "wof:placetype":"neighbourhood",
    "wof:population":296
},
  "geometry": {"coordinates":[95.5625,27.4836],"type":"Point"}
}