{
  "type": "Feature",
  "properties": {
    "iso:country":"IN",
    "ks:ks_name":"Gohalbura",
    "ks:ks_pop":519,
    "ks:ks_type":"HABITATION",
    "name:eng_x_preferred":[
        "Gohalbura"
    ],
    "wof:name":"Gohalbura",
    "wof:placetype":"locality",
    "wof:population":519
},
  "geometry": {"coordinates":[86.771108,22.157223],"type":"Point"}
}