{
  "type": "Feature",
  "properties": {
    "gn:admin1_code":"38.0",
    "gn:admin2_code":"353.0",
    "gn:asciiname":"Dalahi",
    "gn:country_code":"IN",
    "gn:dem":113,
    "gn:feature_class":"P",
    "gn:feature_code":"PPL",
    "gn:name":"Dal\u0101hi",
    "gn:population":0,
    "gn:timezone":"Asia/Kolkata",
    "iso:country":"IN",
    "ks:ks_name":"Dalahi",
    "ks:ks_pop":236,
    "ks:ks_type":"VILLAGE",
    "name:eng_x_preferred":[
        "Dalahi"
    ],
    "wof:name":"Dalahi",
    "wof:placetype":"locality",
    "wof:population":236
},
  "geometry": {"coordinates":[87.570363,24.441169],"type":"Point"}
}