{
  "type": "Feature",
  "properties": {
    "gn:admin1_code":"36",
    "gn:admin2_code":"198.0",
    "gn:asciiname":"Tulapur",
    "gn:country_code":"IN",
    "gn:dem":90,
    "gn:feature_class":"P",
    "gn:feature_code":"PPL",
    "gn:name":"Tul\u0101pur",
    "gn:population":0,
    "gn:timezone":"Asia/Kolkata",
    "iso:country":"IN",
    "name:jpn_x_preferred":[
        "\u30c8\u30a5\u30e9\u30fc\u30d7\u30eb"
    ],
    "name:mar_x_preferred":[
        "\u0924\u0941\u0933\u093e\u092a\u0942\u0930"
    ],
    "wof:name":"Tulapur",
    "wof:placetype":"locality"
},
  "geometry": {"coordinates":[82.35613000000002,25.38669],"type":"Point"}
}