{
  "type": "Feature",
  "properties": {
    "gn:admin1_code":"10.0",
    "gn:admin2_code":"081",
    "gn:asciiname":"Dhani Bhakran",
    "gn:country_code":"IN",
    "gn:dem":226,
    "gn:feature_class":"P",
    "gn:feature_code":"PPL",
    "gn:name":"Dh\u0101ni Bh\u0101kr\u0101n",
    "gn:population":0,
    "gn:timezone":"Asia/Kolkata",
    "iso:country":"IN",
    "wof:name":"Dhani Bhakran",
    "wof:placetype":"locality"
},
  "geometry": {"coordinates":[75.56366,28.76599],"type":"Point"}
}