{
  "type": "Feature",
  "properties": {
    "gn:admin1_code":"10.0",
    "gn:admin2_code":"081",
    "gn:asciiname":"Dhani Bhakran",
    "gn:country_code":"IN",
    "gn:dem":226,
    "gn:feature_class":"P",
    "gn:feature_code":"PPL",
    "gn:name":"Dh\u0101ni Bh\u0101kr\u0101n",
    "gn:population":0,
    "gn:timezone":"Asia/Kolkata",
    "iso:country":"IN",
    "ks:ks_alt_nam":"Dh\u0101ni Bh\u0101kr\u0101n Minor",
    "ks:ks_alt_nam_2":"Dhani Bhakran Minor",
    "ks:ks_name":"Dhani Bhakran",
    "ks:ks_pop":2202,
    "ks:ks_type":"VILLAGE",
    "name:eng_x_preferred":[
        "Dhani Bhakran"
    ],
    "name:eng_x_variant":[
        "Dh\u0101ni Bh\u0101kr\u0101n Minor",
        "Dhani Bhakran Minor"
    ],
    "wof:name":"Dhani Bhakran",
    "wof:placetype":"locality",
    "wof:population":2202
},
  "geometry": {"coordinates":[75.56619999999999,28.7582],"type":"Point"}
}