{
  "type": "Feature",
  "properties": {
    "iso:country":"IN",
    "ks:ks_alt_nam":"SUKHUPUR",
    "ks:ks_name":"Sukhupur",
    "ks:ks_pop":3,
    "ks:ks_type":"HABITATION",
    "name:eng_x_preferred":[
        "Sukhupur"
    ],
    "wof:name":"Sukhupur",
    "wof:placetype":"locality",
    "wof:population":3
},
  "geometry": {"coordinates":[82.46213400000001,26.196585],"type":"Point"}
}