{
  "type": "Feature",
  "properties": {
    "iso:country":"IN",
    "ks:ks_name":"Gholap Girame Wasti",
    "ks:ks_pop":430,
    "ks:ks_type":"HABITATION",
    "name:eng_x_preferred":[
        "Gholap Girame Wasti"
    ],
    "wof:name":"Gholap Girame Wasti",
    "wof:placetype":"locality",
    "wof:population":430
},
  "geometry": {"coordinates":[74.996,17.977],"type":"Point"}
}