{
  "type": "Feature",
  "properties": {
    "iso:country":"IN",
    "ks:ks_name":"Barchapahi",
    "ks:ks_pop":14,
    "ks:ks_type":"VILLAGE",
    "name:eng_x_preferred":[
        "Barchapahi"
    ],
    "wof:name":"Barchapahi",
    "wof:placetype":"locality",
    "wof:population":14
},
  "geometry": {"coordinates":[91.919139,26.243572],"type":"Point"}
}