{
  "type": "Feature",
  "properties": {
    "gn:admin1_code":"37.0",
    "gn:admin2_code":"416.0",
    "gn:asciiname":"Pujaripara",
    "gn:country_code":"IN",
    "gn:dem":548,
    "gn:feature_class":"P",
    "gn:feature_code":"PPL",
    "gn:name":"P\u016bj\u0101rip\u0101ra",
    "gn:population":0,
    "gn:timezone":"Asia/Kolkata",
    "iso:country":"IN",
    "wof:name":"Pujaripara",
    "wof:placetype":"locality"
},
  "geometry": {"coordinates":[81.32519000000001,18.53409],"type":"Point"}
}