{
  "type": "Feature",
  "properties": {
    "iso:country":"IN",
    "ks:ks_name":"Giridharipur",
    "ks:ks_pop":1578,
    "ks:ks_type":"VILLAGE",
    "ks:ks_uagg_main":0,
    "name:eng_x_preferred":[
        "Giridharipur"
    ],
    "wof:name":"Giridharipur",
    "wof:placetype":"neighbourhood",
    "wof:population":1578
},
  "geometry": {"coordinates":[88.211664,23.948699],"type":"Point"}
}