{
  "type": "Feature",
  "properties": {
    "gn:admin1_code":"2.0",
    "gn:admin2_code":"554.0",
    "gn:asciiname":"Ragimanipalle",
    "gn:country_code":"IN",
    "gn:dem":597,
    "gn:feature_class":"P",
    "gn:feature_code":"PPL",
    "gn:name":"Ragimanipalle",
    "gn:population":0,
    "gn:timezone":"Asia/Kolkata",
    "iso:country":"IN",
    "ks:ks_name":"Ragimanupalle",
    "ks:ks_pop":334,
    "ks:ks_type":"HABITATION",
    "ks:ks_uagg_main":0,
    "name:eng_x_preferred":[
        "Ragimanupalle"
    ],
    "wof:name":"Ragimanupalle",
    "wof:placetype":"neighbourhood",
    "wof:population":334
},
  "geometry": {"coordinates":[78.26920200000001,13.799265],"type":"Point"}
}