{
  "type": "Feature",
  "properties": {
    "gn:admin1_code":"36.0",
    "gn:admin2_code":"155.0",
    "gn:asciiname":"Sanp Khera",
    "gn:country_code":"IN",
    "gn:dem":131,
    "gn:feature_class":"P",
    "gn:feature_code":"PPL",
    "gn:name":"S\u0101np Khera",
    "gn:population":0,
    "gn:timezone":"Asia/Kolkata",
    "iso:country":"IN",
    "ks:ks_alt_nam":"S\u0101np Khera",
    "ks:ks_name":"Sanp Khera",
    "ks:ks_pop":724,
    "ks:ks_type":"VILLAGE",
    "name:eng_x_preferred":[
        "Sanp Khera"
    ],
    "name:eng_x_variant":[
        "S\u0101np Khera"
    ],
    "wof:name":"Sanp Khera",
    "wof:placetype":"locality",
    "wof:population":724
},
  "geometry": {"coordinates":[80.011585,27.109287],"type":"Point"}
}