{
  "type": "Feature",
  "properties": {
    "gn:admin1_code":"11.0",
    "gn:admin2_code":"31.0",
    "gn:asciiname":"Kheri",
    "gn:country_code":"IN",
    "gn:dem":1549,
    "gn:feature_class":"P",
    "gn:feature_code":"PPL",
    "gn:name":"Kheri",
    "gn:population":0,
    "gn:timezone":"Asia/Kolkata",
    "iso:country":"IN",
    "name:ara_x_preferred":[
        "\u062e\u064a\u0631\u064a"
    ],
    "name:ben_bn_x_preferred":[
        "\u0996\u09c7\u09b0\u09bf"
    ],
    "name:ben_in_x_preferred":[
        "\u0996\u09c7\u09b0\u09bf"
    ],
    "name:bih_x_preferred":[
        "\u0916\u0940\u0930\u0940"
    ],
    "name:cat_x_preferred":[
        "Kheri"
    ],
    "name:ceb_x_preferred":[
        "Kheri"
    ],
    "name:guj_x_preferred":[
        "\u0a96\u0ac7\u0ab0\u0ac0"
    ],
    "name:hin_x_preferred":[
        "\u0916\u0947\u0930\u0940"
    ],
    "name:hin_x_variant":[
        "\u0916\u0940\u0930\u0940"
    ],
    "name:ita_x_preferred":[
        "Kheri"
    ],
    "name:kan_x_preferred":[
        "\u0c96\u0cc7\u0cb0\u0cbf"
    ],
    "name:mal_x_preferred":[
        "\u0d16\u0d47\u0d30\u0d3f"
    ],
    "name:mar_x_preferred":[
        "\u0916\u0947\u0930\u0940"
    ],
    "name:mlg_x_preferred":[
        "Kheri"
    ],
    "name:msa_x_preferred":[
        "Kheri"
    ],
    "name:new_x_preferred":[
        "\u0916\u0947\u0930\u0940"
    ],
    "name:nld_x_preferred":[
        "Lakhimpur Kheri"
    ],
    "name:pan_x_preferred":[
        "\u0a16\u0a47\u0a5c\u0a40"
    ],
    "name:pol_x_preferred":[
        "Kheri"
    ],
    "name:san_x_preferred":[
        "\u0916\u0940\u0930\u0940"
    ],
    "name:swe_x_preferred":[
        "Kheri"
    ],
    "name:tam_x_preferred":[
        "\u0b95\u0bc7\u0bb0\u0bbf"
    ],
    "name:tel_x_preferred":[
        "\u0c16\u0c46\u0c30\u0c3f"
    ],
    "name:urd_x_preferred":[
        "\u06a9\u06be\u06cc\u0631\u06cc"
    ],
    "name:vie_x_preferred":[
        "Kheri"
    ],
    "wof:name":"Kheri",
    "wof:placetype":"locality"
},
  "geometry": {"coordinates":[77.0887,30.99176],"type":"Point"}
}