{
  "type": "Feature",
  "properties": {
    "iso:country":"IN",
    "ks:ks_name":"Mednipur Mustahakam",
    "ks:ks_pop":2135,
    "ks:ks_type":"VILLAGE",
    "ks:ks_uagg_main":0,
    "name:eng_x_preferred":[
        "Mednipur Mustahakam"
    ],
    "wof:name":"Mednipur Mustahakam",
    "wof:placetype":"neighbourhood",
    "wof:population":2135
},
  "geometry": {"coordinates":[83.62647200000001,25.567803],"type":"Point"}
}