{
  "type": "Feature",
  "properties": {
    "gn:admin1_code":"19",
    "gn:admin2_code":"582.0",
    "gn:asciiname":"Motamakalahalli",
    "gn:country_code":"IN",
    "gn:dem":737,
    "gn:feature_class":"P",
    "gn:feature_code":"PPL",
    "gn:name":"Motam\u0101kalahalli",
    "gn:population":0,
    "gn:timezone":"Asia/Kolkata",
    "iso:country":"IN",
    "wof:name":"Motamakalahalli",
    "wof:placetype":"locality"
},
  "geometry": {"coordinates":[78.07156999999999,13.59761],"type":"Point"}
}