{
  "type": "Feature",
  "properties": {
    "gn:admin1_code":"12.0",
    "gn:admin2_code":"18.0",
    "gn:asciiname":"Amretpur",
    "gn:country_code":"IN",
    "gn:dem":2388,
    "gn:feature_class":"P",
    "gn:feature_code":"PPL",
    "gn:name":"Amretpur",
    "gn:population":0,
    "gn:timezone":"Asia/Kolkata",
    "iso:country":"IN",
    "wof:name":"Amretpur",
    "wof:placetype":"locality"
},
  "geometry": {"coordinates":[75.93231999999998,33.08092],"type":"Point"}
}