{
  "type": "Feature",
  "properties": {
    "iso:country":"IN",
    "ks:ks_alt_nam":"BAGULAGARH-2",
    "ks:ks_name":"Bagulagarh-2",
    "ks:ks_pop":724,
    "ks:ks_type":"HABITATION",
    "name:eng_x_preferred":[
        "Bagulagarh-2"
    ],
    "wof:name":"Bagulagarh-2",
    "wof:placetype":"locality",
    "wof:population":724
},
  "geometry": {"coordinates":[87.73715799999999,25.391384],"type":"Point"}
}