{
  "type": "Feature",
  "properties": {
    "iso:country":"IN",
    "ks:ks_name":"Side",
    "ks:ks_pop":253,
    "ks:ks_type":"HABITATION",
    "name:eng_x_preferred":[
        "Side"
    ],
    "wof:name":"Side",
    "wof:placetype":"locality",
    "wof:population":253
},
  "geometry": {"coordinates":[86.68838100000001,24.692358],"type":"Point"}
}