{
  "type": "Feature",
  "properties": {
    "gn:admin1_code":"24.0",
    "gn:admin2_code":"110",
    "gn:asciiname":"Kishanpura",
    "gn:country_code":"IN",
    "gn:dem":359,
    "gn:feature_class":"P",
    "gn:feature_code":"PPL",
    "gn:name":"Kishanpura",
    "gn:population":0,
    "gn:timezone":"Asia/Kolkata",
    "iso:country":"IN",
    "name:und_x_variant":[
        "Kh\u0101t\u012bpura",
        "Kishanpura",
        "Kh\u0101tipura"
    ],
    "wof:name":"Kishanpura",
    "wof:placetype":"locality"
},
  "geometry": {"coordinates":[75.68935999999999,26.76728],"type":"Point"}
}