{
  "type": "Feature",
  "properties": {
    "gn:admin1_code":"25.0",
    "gn:admin2_code":"619.0",
    "gn:asciiname":"Maharajapuram",
    "gn:country_code":"IN",
    "gn:dem":12,
    "gn:feature_class":"P",
    "gn:feature_code":"PPL",
    "gn:name":"Mah\u0101r\u0101japuram",
    "gn:population":0,
    "gn:timezone":"Asia/Kolkata",
    "iso:country":"IN",
    "name:msa_x_preferred":[
        "Maharajapuram"
    ],
    "name:tam_x_preferred":[
        "\u0bae\u0b95\u0bbe\u0bb0\u0bbe\u0b9c\u0baa\u0bc1\u0bb0\u0bae\u0bcd \u0b8a\u0bb0\u0bbe\u0b9f\u0bcd\u0b9a\u0bbf"
    ],
    "wof:name":"Maharajapuram",
    "wof:placetype":"neighbourhood"
},
  "geometry": {"coordinates":[79.46191,10.53079],"type":"Point"}
}