{
  "type": "Feature",
  "properties": {
    "gn:admin1_code":"24.0",
    "gn:admin2_code":"125.0",
    "gn:asciiname":"Borkhabar",
    "gn:country_code":"IN",
    "gn:dem":398,
    "gn:feature_class":"P",
    "gn:feature_code":"PPL",
    "gn:name":"Borkh\u0101bar",
    "gn:population":0,
    "gn:timezone":"Asia/Kolkata",
    "iso:country":"IN",
    "ks:ks_name":"Borkhabar",
    "ks:ks_pop":1854,
    "ks:ks_type":"VILLAGE",
    "name:eng_x_preferred":[
        "Borkhabar"
    ],
    "wof:name":"Borkhabar",
    "wof:placetype":"locality",
    "wof:population":1854
},
  "geometry": {"coordinates":[74.45885,23.385942],"type":"Point"}
}