{
  "type": "Feature",
  "properties": {
    "iso:country":"IN",
    "ks:ks_alt_nam":"HOSAKOPPA",
    "ks:ks_name":"Hosakoppa",
    "ks:ks_pop":15,
    "ks:ks_type":"HABITATION",
    "name:eng_x_preferred":[
        "Hosakoppa"
    ],
    "wof:name":"Hosakoppa",
    "wof:placetype":"locality",
    "wof:population":15
},
  "geometry": {"coordinates":[75.15655,13.787785],"type":"Point"}
}