{
  "type": "Feature",
  "properties": {
    "iso:country":"IN",
    "ks:ks_name":"Ajabpur",
    "ks:ks_pop":23,
    "ks:ks_type":"HABITATION",
    "name:eng_x_preferred":[
        "Ajabpur"
    ],
    "wof:name":"Ajabpur",
    "wof:placetype":"locality",
    "wof:population":23
},
  "geometry": {"coordinates":[78.831253,30.037402],"type":"Point"}
}