{
  "type": "Feature",
  "properties": {
    "iso:country":"IN",
    "ks:ks_name":"Karjyamani North",
    "ks:ks_pop":322,
    "ks:ks_type":"HABITATION",
    "name:eng_x_preferred":[
        "Karjyamani North"
    ],
    "wof:name":"Karjyamani North",
    "wof:placetype":"locality",
    "wof:population":322
},
  "geometry": {"coordinates":[91.40370900000001,23.459743],"type":"Point"}
}