{
  "type": "Feature",
  "properties": {
    "gn:admin1_code":"36",
    "gn:admin2_code":"166.0",
    "gn:asciiname":"Bhandra Buzurg",
    "gn:country_code":"IN",
    "gn:dem":296,
    "gn:feature_class":"P",
    "gn:feature_code":"PPL",
    "gn:name":"Bhandra Buzurg",
    "gn:population":0,
    "gn:timezone":"Asia/Kolkata",
    "iso:country":"IN",
    "ks:ks_name":"Bhandra Buzurg",
    "ks:ks_type":"VILLAGE",
    "name:eng_x_preferred":[
        "Bhandra Buzurg"
    ],
    "wof:name":"Bhandra Buzurg",
    "wof:placetype":"locality"
},
  "geometry": {"coordinates":[78.397037,25.315122],"type":"Point"}
}