{
  "type": "Feature",
  "properties": {
    "gn:admin1_code":"38.0",
    "gn:admin2_code":"360.0",
    "gn:asciiname":"Kajra",
    "gn:country_code":"IN",
    "gn:dem":397,
    "gn:feature_class":"P",
    "gn:feature_code":"PPL",
    "gn:name":"Kajr\u0101",
    "gn:population":0,
    "gn:timezone":"Asia/Kolkata",
    "iso:country":"IN",
    "ks:ks_alt_nam":"Kajr\u0101",
    "ks:ks_name":"Kajra",
    "ks:ks_pop":315,
    "ks:ks_type":"VILLAGE",
    "name:eng_x_preferred":[
        "Kajra"
    ],
    "name:eng_x_variant":[
        "Kajr\u0101"
    ],
    "wof:name":"Kajra",
    "wof:placetype":"locality",
    "wof:population":315
},
  "geometry": {"coordinates":[85.37494,24.27327],"type":"Point"}
}