{
  "type": "Feature",
  "properties": {
    "iso:country":"IN",
    "ks:ks_name":"Simberi",
    "ks:ks_pop":10,
    "ks:ks_type":"VILLAGE",
    "name:eng_x_preferred":[
        "Simberi"
    ],
    "wof:name":"Simberi",
    "wof:placetype":"locality",
    "wof:population":10
},
  "geometry": {"coordinates":[87.714927,24.957573],"type":"Point"}
}