{
  "type": "Feature",
  "properties": {
    "iso:country":"IN",
    "ks:ks_alt_nam":"WAKHIRAI PARA",
    "ks:ks_name":"Wakhirai Para",
    "ks:ks_pop":196,
    "ks:ks_type":"HABITATION",
    "name:eng_x_preferred":[
        "Wakhirai Para"
    ],
    "wof:name":"Wakhirai Para",
    "wof:placetype":"locality",
    "wof:population":196
},
  "geometry": {"coordinates":[91.40972499999999,23.615421],"type":"Point"}
}