{
  "type": "Feature",
  "properties": {
    "iso:country":"IN",
    "ks:ks_name":"Navalodai Colony",
    "ks:ks_pop":374,
    "ks:ks_type":"HABITATION",
    "name:eng_x_preferred":[
        "Navalodai Colony"
    ],
    "wof:name":"Navalodai Colony",
    "wof:placetype":"locality",
    "wof:population":374
},
  "geometry": {"coordinates":[77.314369,10.433776],"type":"Point"}
}