{
  "type": "Feature",
  "properties": {
    "iso:country":"IN",
    "ks:ks_name":"Seethampeta",
    "ks:ks_pop":32,
    "ks:ks_type":"VILLAGE",
    "name:eng_x_preferred":[
        "Seethampeta"
    ],
    "wof:name":"Seethampeta",
    "wof:placetype":"locality",
    "wof:population":32
},
  "geometry": {"coordinates":[81.283936,17.545683],"type":"Point"}
}