{
  "type": "Feature",
  "properties": {
    "iso:country":"IN",
    "ks:ks_name":"Avarangampalayam",
    "ks:ks_pop":980,
    "ks:ks_type":"VILLAGE",
    "ks:ks_uagg_main":0,
    "name:eng_x_preferred":[
        "Avarangampalayam"
    ],
    "wof:name":"Avarangampalayam",
    "wof:placetype":"locality",
    "wof:population":980
},
  "geometry": {"coordinates":[77.901421,11.4952],"type":"Point"}
}