{
  "type": "Feature",
  "properties": {
    "iso:country":"IN",
    "ks:ks_name":"Nemmanapettai",
    "ks:ks_pop":153,
    "ks:ks_type":"HABITATION",
    "ks:ks_uagg_main":0,
    "name:eng_x_preferred":[
        "Nemmanapettai"
    ],
    "wof:name":"Nemmanapettai",
    "wof:placetype":"neighbourhood",
    "wof:population":153
},
  "geometry": {"coordinates":[79.093857,12.835033],"type":"Point"}
}