{
  "type": "Feature",
  "properties": {
    "gn:admin1_code":"9.0",
    "gn:admin2_code":"484.0",
    "gn:asciiname":"Kureta",
    "gn:country_code":"IN",
    "gn:dem":160,
    "gn:feature_class":"P",
    "gn:feature_code":"PPL",
    "gn:name":"Kureta",
    "gn:population":0,
    "gn:timezone":"Asia/Kolkata",
    "iso:country":"IN",
    "ks:ks_name":"Kureta",
    "ks:ks_pop":2497,
    "ks:ks_type":"VILLAGE",
    "name:eng_x_preferred":[
        "Kureta"
    ],
    "wof:name":"Kureta",
    "wof:placetype":"locality",
    "wof:population":2497
},
  "geometry": {"coordinates":[73.87180600000001,23.243],"type":"Point"}
}