{
  "type": "Feature",
  "properties": {
    "gn:admin1_code":"19.0",
    "gn:admin2_code":"581.0",
    "gn:asciiname":"Kalahastipura",
    "gn:country_code":"IN",
    "gn:dem":816,
    "gn:feature_class":"P",
    "gn:feature_code":"PPL",
    "gn:name":"K\u0101lahastipura",
    "gn:population":0,
    "gn:timezone":"Asia/Kolkata",
    "iso:country":"IN",
    "wof:name":"Kalahastipura",
    "wof:placetype":"locality"
},
  "geometry": {"coordinates":[78.1897,13.12836],"type":"Point"}
}