{
  "type": "Feature",
  "properties": {
    "gn:admin1_code":"19",
    "gn:admin2_code":"579.0",
    "gn:asciiname":"Gudewadi",
    "gn:country_code":"IN",
    "gn:dem":413,
    "gn:feature_class":"P",
    "gn:feature_code":"PPL",
    "gn:name":"Gudew\u0101di",
    "gn:population":0,
    "gn:timezone":"Asia/Kolkata",
    "iso:country":"IN",
    "ks:ks_name":"Guddewadi",
    "ks:ks_pop":512,
    "ks:ks_type":"VILLAGE",
    "name:eng_x_preferred":[
        "Guddewadi"
    ],
    "name:eng_x_variant":[
        "Gudewadi"
    ],
    "wof:name":"Guddewadi",
    "wof:placetype":"locality",
    "wof:population":512
},
  "geometry": {"coordinates":[76.435211,17.140381],"type":"Point"}
}