{
  "type": "Feature",
  "properties": {
    "iso:country":"IN",
    "ks:ks_name":"Babhani",
    "ks:ks_pop":404,
    "ks:ks_type":"HABITATION",
    "name:eng_x_preferred":[
        "Babhani"
    ],
    "wof:name":"Babhani",
    "wof:placetype":"locality",
    "wof:population":404
},
  "geometry": {"coordinates":[82.942798,27.15735],"type":"Point"}
}