{
  "type": "Feature",
  "properties": {
    "iso:country":"IN",
    "ks:ks_name":"Kamargram Pt II",
    "ks:ks_pop":926,
    "ks:ks_type":"VILLAGE",
    "name:eng_x_preferred":[
        "Kamargram Pt II"
    ],
    "wof:name":"Kamargram Pt II",
    "wof:placetype":"locality",
    "wof:population":926
},
  "geometry": {"coordinates":[92.40925,24.809229],"type":"Point"}
}