{
  "type": "Feature",
  "properties": {
    "gn:admin1_code":"11",
    "gn:admin2_code":"33.0",
    "gn:asciiname":"Moir Dogri",
    "gn:country_code":"IN",
    "gn:dem":1620,
    "gn:feature_class":"P",
    "gn:feature_code":"PPL",
    "gn:name":"Mo\u00efr Dogri",
    "gn:population":0,
    "gn:timezone":"Asia/Kolkata",
    "iso:country":"IN",
    "wof:name":"Moir Dogri",
    "wof:placetype":"locality"
},
  "geometry": {"coordinates":[77.78309,31.10519],"type":"Point"}
}