{
  "type": "Feature",
  "properties": {
    "iso:country":"IN",
    "ks:ks_name":"Digagaradapalli",
    "ks:ks_pop":64,
    "ks:ks_type":"HABITATION",
    "name:eng_x_preferred":[
        "Digagaradapalli"
    ],
    "wof:name":"Digagaradapalli",
    "wof:placetype":"locality",
    "wof:population":64
},
  "geometry": {"coordinates":[82.78426,18.097118],"type":"Point"}
}