{
  "type": "Feature",
  "properties": {
    "iso:country":"IN",
    "ks:ks_alt_nam":"gamharia",
    "ks:ks_name":"Gamharia",
    "ks:ks_pop":733,
    "ks:ks_type":"HABITATION",
    "name:eng_x_preferred":[
        "Gamharia"
    ],
    "wof:name":"Gamharia",
    "wof:placetype":"locality",
    "wof:population":733
},
  "geometry": {"coordinates":[85.361056,22.429706],"type":"Point"}
}