{
  "type": "Feature",
  "properties": {
    "gn:admin1_code":"39.0",
    "gn:admin2_code":"061",
    "gn:asciiname":"Pataguni",
    "gn:country_code":"IN",
    "gn:dem":1121,
    "gn:feature_class":"P",
    "gn:feature_code":"PPL",
    "gn:name":"Pat\u0101guni",
    "gn:population":0,
    "gn:timezone":"Asia/Kolkata",
    "iso:country":"IN",
    "ks:ks_name":"Pataguni",
    "ks:ks_pop":78,
    "ks:ks_type":"HABITATION",
    "name:eng_x_preferred":[
        "Pataguni"
    ],
    "wof:name":"Pataguni",
    "wof:placetype":"locality",
    "wof:population":78
},
  "geometry": {"coordinates":[78.662104,29.827975],"type":"Point"}
}