{
  "type": "Feature",
  "properties": {
    "iso:country":"IN",
    "ks:ks_name":"Tikai Bigha",
    "ks:ks_pop":190,
    "ks:ks_type":"HABITATION",
    "name:eng_x_preferred":[
        "Tikai Bigha"
    ],
    "wof:name":"Tikai Bigha",
    "wof:placetype":"locality",
    "wof:population":190
},
  "geometry": {"coordinates":[85.21962600000001,25.182721],"type":"Point"}
}