{
  "type": "Feature",
  "properties": {
    "iso:country":"IN",
    "ks:ks_name":"Chandrapar",
    "ks:ks_pop":3,
    "ks:ks_type":"VILLAGE",
    "name:eng_x_preferred":[
        "Chandrapar"
    ],
    "wof:name":"Chandrapar",
    "wof:placetype":"locality",
    "wof:population":3
},
  "geometry": {"coordinates":[70.02909099999999,22.959118],"type":"Point"}
}