{
  "type": "Feature",
  "properties": {
    "iso:country":"IN",
    "ks:ks_name":"Chahalapada",
    "ks:ks_pop":207,
    "ks:ks_type":"VILLAGE",
    "name:eng_x_preferred":[
        "Chahalapada"
    ],
    "wof:name":"Chahalapada",
    "wof:placetype":"locality",
    "wof:population":207
},
  "geometry": {"coordinates":[86.96989499999999,21.727803],"type":"Point"}
}