{
  "type": "Feature",
  "properties": {
    "iso:country":"IN",
    "ks:ks_name":"Ugaliya Kathayat",
    "ks:ks_pop":31,
    "ks:ks_type":"VILLAGE",
    "name:eng_x_preferred":[
        "Ugaliya Kathayat"
    ],
    "wof:name":"Ugaliya Kathayat",
    "wof:placetype":"locality",
    "wof:population":31
},
  "geometry": {"coordinates":[79.29497600000001,29.627598],"type":"Point"}
}