{
  "type": "Feature",
  "properties": {
    "iso:country":"IN",
    "ks:ks_name":"Kesharganj",
    "ks:ks_pop":273,
    "ks:ks_type":"HABITATION",
    "name:eng_x_preferred":[
        "Kesharganj"
    ],
    "wof:name":"Kesharganj",
    "wof:placetype":"locality",
    "wof:population":273
},
  "geometry": {"coordinates":[82.269728,27.669307],"type":"Point"}
}