{
  "type": "Feature",
  "properties": {
    "iso:country":"IN",
    "ks:ks_name":"Zadi",
    "ks:ks_pop":252,
    "ks:ks_type":"HABITATION",
    "name:eng_x_preferred":[
        "Zadi"
    ],
    "wof:name":"Zadi",
    "wof:placetype":"locality",
    "wof:population":252
},
  "geometry": {"coordinates":[73.44202799999999,21.03375],"type":"Point"}
}