{
  "type": "Feature",
  "properties": {
    "iso:country":"IN",
    "ks:ks_name":"Anu. Basti",
    "ks:ks_pop":231,
    "ks:ks_type":"HABITATION",
    "name:eng_x_preferred":[
        "Anu. Basti"
    ],
    "wof:name":"Anu. Basti",
    "wof:placetype":"locality",
    "wof:population":231
},
  "geometry": {"coordinates":[82.768406,25.385718],"type":"Point"}
}