{
  "type": "Feature",
  "properties": {
    "gn:admin1_code":"39.0",
    "gn:admin2_code":"63.0",
    "gn:asciiname":"Bhatgaon",
    "gn:country_code":"IN",
    "gn:dem":1337,
    "gn:feature_class":"P",
    "gn:feature_code":"PPL",
    "gn:name":"Bhatgaon",
    "gn:population":0,
    "gn:timezone":"Asia/Kolkata",
    "iso:country":"IN",
    "name:cat_x_preferred":[
        "Bhatgaon"
    ],
    "wof:name":"Bhatgaon",
    "wof:placetype":"locality"
},
  "geometry": {"coordinates":[79.90264999999999,29.86012],"type":"Point"}
}