{
  "type": "Feature",
  "properties": {
    "gn:admin1_code":"39.0",
    "gn:admin2_code":"63.0",
    "gn:asciiname":"Bhatgaon",
    "gn:country_code":"IN",
    "gn:dem":1337,
    "gn:feature_class":"P",
    "gn:feature_code":"PPL",
    "gn:name":"Bhatgaon",
    "gn:population":0,
    "gn:timezone":"Asia/Kolkata",
    "iso:country":"IN",
    "ks:ks_name":"Bhatgaon",
    "ks:ks_type":"VILLAGE",
    "name:cat_x_preferred":[
        "Bhatgaon"
    ],
    "name:eng_x_preferred":[
        "Bhatgaon"
    ],
    "wof:name":"Bhatgaon",
    "wof:placetype":"locality"
},
  "geometry": {"coordinates":[79.898549,29.85616],"type":"Point"}
}