{
  "type": "Feature",
  "properties": {
    "iso:country":"IN",
    "ks:ks_name":"Badagarh",
    "ks:ks_pop":1552,
    "ks:ks_type":"VILLAGE",
    "name:eng_x_preferred":[
        "Badagarh"
    ],
    "wof:name":"Badagarh",
    "wof:placetype":"locality",
    "wof:population":1552
},
  "geometry": {"coordinates":[84.60910199999999,19.548305],"type":"Point"}
}