{
  "type": "Feature",
  "properties": {
    "gn:admin1_code":"39.0",
    "gn:admin2_code":"64.0",
    "gn:asciiname":"Kapoli",
    "gn:country_code":"IN",
    "gn:dem":1636,
    "gn:feature_class":"P",
    "gn:feature_code":"PPL",
    "gn:name":"Kapoli",
    "gn:population":0,
    "gn:timezone":"Asia/Kolkata",
    "iso:country":"IN",
    "ks:ks_name":"Kapkoli",
    "ks:ks_pop":137,
    "ks:ks_type":"VILLAGE",
    "name:eng_x_preferred":[
        "Kapkoli"
    ],
    "name:eng_x_variant":[
        "Kapoli"
    ],
    "wof:name":"Kapkoli",
    "wof:placetype":"locality",
    "wof:population":137
},
  "geometry": {"coordinates":[79.90167599999999,29.640965],"type":"Point"}
}