{
  "type": "Feature",
  "properties": {
    "iso:country":"IN",
    "ks:ks_name":"Tipu",
    "ks:ks_pop":422,
    "ks:ks_type":"HABITATION",
    "name:eng_x_preferred":[
        "Tipu"
    ],
    "wof:name":"Tipu",
    "wof:placetype":"locality",
    "wof:population":422
},
  "geometry": {"coordinates":[79.958189,26.52916],"type":"Point"}
}