{
  "type": "Feature",
  "properties": {
    "iso:country":"IN",
    "ks:ks_name":"Khendraposh",
    "ks:ks_pop":211,
    "ks:ks_type":"VILLAGE",
    "name:eng_x_preferred":[
        "Khendraposh"
    ],
    "wof:name":"Khendraposh",
    "wof:placetype":"locality",
    "wof:population":211
},
  "geometry": {"coordinates":[84.988754,21.832957],"type":"Point"}
}