{
  "type": "Feature",
  "properties": {
    "gn:admin1_code":"35",
    "gn:admin2_code":"446.0",
    "gn:asciiname":"Silari",
    "gn:country_code":"IN",
    "gn:dem":443,
    "gn:feature_class":"P",
    "gn:feature_code":"PPL",
    "gn:name":"Sil\u0101ri",
    "gn:population":0,
    "gn:timezone":"Asia/Kolkata",
    "iso:country":"IN",
    "ks:ks_alt_nam":"Sil\u0101ri",
    "ks:ks_name":"Silari",
    "ks:ks_pop":756,
    "ks:ks_type":"VILLAGE",
    "name:eng_x_preferred":[
        "Silari"
    ],
    "name:eng_x_variant":[
        "Sil\u0101ri"
    ],
    "wof:name":"Silari",
    "wof:placetype":"locality",
    "wof:population":756
},
  "geometry": {"coordinates":[78.01987800000001,23.269391],"type":"Point"}
}