{
  "type": "Feature",
  "properties": {
    "iso:country":"IN",
    "ks:ks_name":"Koliwada",
    "ks:ks_pop":139,
    "ks:ks_type":"HABITATION",
    "name:eng_x_preferred":[
        "Koliwada"
    ],
    "wof:name":"Koliwada",
    "wof:placetype":"locality",
    "wof:population":139
},
  "geometry": {"coordinates":[73.04574599999999,18.971426],"type":"Point"}
}