{
  "type": "Feature",
  "properties": {
    "iso:country":"IN",
    "ks:ks_name":"Chibli",
    "ks:ks_pop":54,
    "ks:ks_type":"HABITATION",
    "name:eng_x_preferred":[
        "Chibli"
    ],
    "wof:name":"Chibli",
    "wof:placetype":"locality",
    "wof:population":54
},
  "geometry": {"coordinates":[75.31279499999999,13.956628],"type":"Point"}
}