{
  "type": "Feature",
  "properties": {
    "gn:admin1_code":"34.0",
    "gn:admin2_code":"220.0",
    "gn:asciiname":"Muhammadpur Sihan",
    "gn:country_code":"IN",
    "gn:dem":55,
    "gn:feature_class":"P",
    "gn:feature_code":"PPL",
    "gn:name":"Muhammadpur Sih\u0101n",
    "gn:population":0,
    "gn:timezone":"Asia/Kolkata",
    "iso:country":"IN",
    "wof:name":"Muhammadpur Sihan",
    "wof:placetype":"locality"
},
  "geometry": {"coordinates":[85.43356,25.89406],"type":"Point"}
}