{
  "type": "Feature",
  "properties": {
    "gn:admin1_code":"35",
    "gn:admin2_code":"456.0",
    "gn:asciiname":"Bhurkalkhapa",
    "gn:country_code":"IN",
    "gn:dem":581,
    "gn:feature_class":"P",
    "gn:feature_code":"PPL",
    "gn:name":"Bhurkalkh\u0101pa",
    "gn:population":0,
    "gn:timezone":"Asia/Kolkata",
    "iso:country":"IN",
    "wof:name":"Bhurkalkhapa",
    "wof:placetype":"locality"
},
  "geometry": {"coordinates":[79.62998,22.09188],"type":"Point"}
}