{
  "type": "Feature",
  "properties": {
    "gn:admin1_code":"35",
    "gn:admin2_code":"456.0",
    "gn:asciiname":"Bhurkalkhapa",
    "gn:country_code":"IN",
    "gn:dem":581,
    "gn:feature_class":"P",
    "gn:feature_code":"PPL",
    "gn:name":"Bhurkalkh\u0101pa",
    "gn:population":0,
    "gn:timezone":"Asia/Kolkata",
    "iso:country":"IN",
    "ks:ks_alt_nam":"Bhurkalkh\u0101pa",
    "ks:ks_name":"Bhurkalkhapa",
    "ks:ks_pop":708,
    "ks:ks_type":"VILLAGE",
    "name:eng_x_preferred":[
        "Bhurkalkhapa"
    ],
    "name:eng_x_variant":[
        "Bhurkalkh\u0101pa"
    ],
    "wof:name":"Bhurkalkhapa",
    "wof:placetype":"locality",
    "wof:population":708
},
  "geometry": {"coordinates":[79.631868,22.091941],"type":"Point"}
}