{
  "type": "Feature",
  "properties": {
    "iso:country":"IN",
    "ks:ks_name":"Mithadka",
    "ks:ks_pop":1718,
    "ks:ks_type":"HABITATION",
    "name:eng_x_preferred":[
        "Mithadka"
    ],
    "wof:name":"Mithadka",
    "wof:placetype":"locality",
    "wof:population":1718
},
  "geometry": {"coordinates":[74.975748,12.665202],"type":"Point"}
}