{
  "type": "Feature",
  "properties": {
    "iso:country":"IN",
    "ks:ks_name":"Ram Nagar",
    "ks:ks_pop":524,
    "ks:ks_type":"HABITATION",
    "name:eng_x_preferred":[
        "Ram Nagar"
    ],
    "wof:name":"Ram Nagar",
    "wof:placetype":"locality",
    "wof:population":524
},
  "geometry": {"coordinates":[85.357158,26.608345],"type":"Point"}
}