{
  "type": "Feature",
  "properties": {
    "gn:admin1_code":"34.0",
    "gn:admin2_code":"221.0",
    "gn:asciiname":"Bulakipur",
    "gn:country_code":"IN",
    "gn:dem":51,
    "gn:feature_class":"P",
    "gn:feature_code":"PPL",
    "gn:name":"Bul\u0101kipur",
    "gn:population":0,
    "gn:timezone":"Asia/Kolkata",
    "iso:country":"IN",
    "ks:ks_alt_nam":"Bul\u0101kipur",
    "ks:ks_name":"Bulakipur",
    "ks:ks_pop":3594,
    "ks:ks_type":"VILLAGE",
    "name:eng_x_preferred":[
        "Bulakipur"
    ],
    "name:eng_x_variant":[
        "Bul\u0101kipur"
    ],
    "wof:name":"Bulakipur",
    "wof:placetype":"locality",
    "wof:population":3594
},
  "geometry": {"coordinates":[85.856793,25.705491],"type":"Point"}
}