{
  "type": "Feature",
  "properties": {
    "iso:country":"IN",
    "ks:ks_name":"Kanchan Tala",
    "ks:ks_pop":1545,
    "ks:ks_type":"VILLAGE",
    "name:eng_x_preferred":[
        "Kanchan Tala"
    ],
    "wof:name":"Kanchan Tala",
    "wof:placetype":"locality",
    "wof:population":1545
},
  "geometry": {"coordinates":[87.56277900000001,22.531868],"type":"Point"}
}