{
  "type": "Feature",
  "properties": {
    "iso:country":"IN",
    "ks:ks_name":"Hindusthan Cables Town",
    "ks:ks_pop":22154,
    "ks:ks_type":"VILLAGE",
    "name:eng_x_preferred":[
        "Hindusthan Cables Town"
    ],
    "wof:name":"Hindusthan Cables Town",
    "wof:placetype":"locality",
    "wof:population":22154
},
  "geometry": {"coordinates":[86.901732,23.825302],"type":"Point"}
}