{
  "type": "Feature",
  "properties": {
    "iso:country":"IN",
    "ks:ks_name":"Mulidhar Grant",
    "ks:ks_pop":1157,
    "ks:ks_type":"HABITATION",
    "name:eng_x_preferred":[
        "Mulidhar Grant"
    ],
    "wof:name":"Mulidhar Grant",
    "wof:placetype":"locality",
    "wof:population":1157
},
  "geometry": {"coordinates":[92.804331,24.911197],"type":"Point"}
}