{
  "type": "Feature",
  "properties": {
    "gn:admin1_code":"36",
    "gn:admin2_code":"163.0",
    "gn:asciiname":"Pur",
    "gn:country_code":"IN",
    "gn:dem":137,
    "gn:feature_class":"P",
    "gn:feature_code":"PPL",
    "gn:name":"Pur",
    "gn:population":0,
    "gn:timezone":"Asia/Kolkata",
    "iso:country":"IN",
    "name:ceb_x_preferred":[
        "Pur"
    ],
    "name:deu_x_preferred":[
        "Pur"
    ],
    "name:fas_x_preferred":[
        "\u067e\u0648\u0631"
    ],
    "name:hun_x_preferred":[
        "Pur"
    ],
    "name:swe_x_preferred":[
        "Pur"
    ],
    "wof:name":"Pur",
    "wof:placetype":"locality"
},
  "geometry": {"coordinates":[79.91896,26.43311],"type":"Point"}
}