{
  "type": "Feature",
  "properties": {
    "iso:country":"IN",
    "ks:ks_name":"Uppalikanahalli",
    "ks:ks_pop":67,
    "ks:ks_type":"HABITATION",
    "name:eng_x_preferred":[
        "Uppalikanahalli"
    ],
    "wof:name":"Uppalikanahalli",
    "wof:placetype":"locality",
    "wof:population":67
},
  "geometry": {"coordinates":[76.60348500000001,13.505505],"type":"Point"}
}