{
  "type": "Feature",
  "properties": {
    "iso:country":"IN",
    "ks:ks_name":"Kasera",
    "ks:ks_type":"VILLAGE",
    "name:eng_x_preferred":[
        "Kasera"
    ],
    "wof:name":"Kasera",
    "wof:placetype":"locality"
},
  "geometry": {"coordinates":[83.523188,25.447604],"type":"Point"}
}