{
  "type": "Feature",
  "properties": {
    "iso:country":"IN",
    "ks:ks_name":"North Haripur",
    "ks:ks_pop":512,
    "ks:ks_type":"HABITATION",
    "name:eng_x_preferred":[
        "North Haripur"
    ],
    "wof:name":"North Haripur",
    "wof:placetype":"locality",
    "wof:population":512
},
  "geometry": {"coordinates":[89.39154600000001,26.449755],"type":"Point"}
}