{
  "type": "Feature",
  "properties": {
    "iso:country":"IN",
    "ks:ks_name":"Majura Kundi",
    "ks:ks_pop":350,
    "ks:ks_type":"VILLAGE",
    "name:eng_x_preferred":[
        "Majura Kundi"
    ],
    "wof:name":"Majura Kundi",
    "wof:placetype":"locality",
    "wof:population":350
},
  "geometry": {"coordinates":[86.997716,23.473525],"type":"Point"}
}