{
  "type": "Feature",
  "properties": {
    "gn:admin1_code":"24.0",
    "gn:admin2_code":"104.0",
    "gn:asciiname":"Nagla Singalka",
    "gn:country_code":"IN",
    "gn:dem":340,
    "gn:feature_class":"P",
    "gn:feature_code":"PPL",
    "gn:name":"N\u0101gla Singalka",
    "gn:population":0,
    "gn:timezone":"Asia/Kolkata",
    "iso:country":"IN",
    "ks:ks_alt_nam":"N\u0101gla Singalka",
    "ks:ks_name":"Nagla Singalka",
    "ks:ks_type":"VILLAGE",
    "name:eng_x_preferred":[
        "Nagla Singalka"
    ],
    "name:eng_x_variant":[
        "N\u0101gla Singalka"
    ],
    "wof:name":"Nagla Singalka",
    "wof:placetype":"locality"
},
  "geometry": {"coordinates":[76.52189799999999,27.696851],"type":"Point"}
}