{
  "type": "Feature",
  "properties": {
    "iso:country":"IN",
    "ks:ks_name":"Sunnang Vatasal Sannakere",
    "ks:ks_pop":380,
    "ks:ks_type":"HABITATION",
    "name:eng_x_preferred":[
        "Sunnang Vatasal Sannakere"
    ],
    "wof:name":"Sunnang Vatasal Sannakere",
    "wof:placetype":"locality",
    "wof:population":380
},
  "geometry": {"coordinates":[74.92881,13.421601],"type":"Point"}
}