{
  "type": "Feature",
  "properties": {
    "iso:country":"IN",
    "ks:ks_name":"Mapanthi",
    "ks:ks_pop":5,
    "ks:ks_type":"HABITATION",
    "name:eng_x_preferred":[
        "Mapanthi"
    ],
    "wof:name":"Mapanthi",
    "wof:placetype":"locality",
    "wof:population":5
},
  "geometry": {"coordinates":[74.713477,14.059311],"type":"Point"}
}