{
  "type": "Feature",
  "properties": {
    "iso:country":"IN",
    "ks:ks_name":"Satemari Pub",
    "ks:ks_pop":1121,
    "ks:ks_type":"HABITATION",
    "name:eng_x_preferred":[
        "Satemari Pub"
    ],
    "wof:name":"Satemari Pub",
    "wof:placetype":"locality",
    "wof:population":1121
},
  "geometry": {"coordinates":[91.407785,26.281478],"type":"Point"}
}