{
  "type": "Feature",
  "properties": {
    "iso:country":"IN",
    "ks:ks_name":"Medari",
    "ks:ks_pop":110,
    "ks:ks_type":"HABITATION",
    "name:eng_x_preferred":[
        "Medari"
    ],
    "wof:name":"Medari",
    "wof:placetype":"locality",
    "wof:population":110
},
  "geometry": {"coordinates":[79.097598,29.611214],"type":"Point"}
}