{
  "type": "Feature",
  "properties": {
    "iso:country":"IN",
    "ks:ks_name":"Padugeri",
    "ks:ks_pop":285,
    "ks:ks_type":"HABITATION",
    "name:eng_x_preferred":[
        "Padugeri"
    ],
    "wof:name":"Padugeri",
    "wof:placetype":"locality",
    "wof:population":285
},
  "geometry": {"coordinates":[74.46581999999999,14.64929],"type":"Point"}
}