{
  "type": "Feature",
  "properties": {
    "iso:country":"IN",
    "ks:ks_name":"Harohithlu",
    "ks:ks_pop":880,
    "ks:ks_type":"VILLAGE",
    "name:eng_x_preferred":[
        "Harohithlu"
    ],
    "wof:name":"Harohithlu",
    "wof:placetype":"locality",
    "wof:population":880
},
  "geometry": {"coordinates":[75.33547299999999,13.979876],"type":"Point"}
}