{
  "type": "Feature",
  "properties": {
    "iso:country":"IN",
    "ks:ks_name":"Bollaje",
    "ks:ks_pop":610,
    "ks:ks_type":"HABITATION",
    "name:eng_x_preferred":[
        "Bollaje"
    ],
    "wof:name":"Bollaje",
    "wof:placetype":"locality",
    "wof:population":610
},
  "geometry": {"coordinates":[75.46257199999999,12.692267],"type":"Point"}
}