{
  "type": "Feature",
  "properties": {
    "iso:country":"IN",
    "ks:ks_name":"Nagra",
    "ks:ks_pop":29,
    "ks:ks_type":"HABITATION",
    "name:eng_x_preferred":[
        "Nagra"
    ],
    "wof:name":"Nagra",
    "wof:placetype":"locality",
    "wof:population":29
},
  "geometry": {"coordinates":[78.33526000000001,26.927296],"type":"Point"}
}