{
  "type": "Feature",
  "properties": {
    "iso:country":"IN",
    "ks:ks_name":"Kottormukku",
    "ks:ks_pop":729,
    "ks:ks_type":"HABITATION",
    "name:eng_x_preferred":[
        "Kottormukku"
    ],
    "wof:name":"Kottormukku",
    "wof:placetype":"locality",
    "wof:population":729
},
  "geometry": {"coordinates":[76.593097,9.013974],"type":"Point"}
}