{
  "type": "Feature",
  "properties": {
    "gn:admin1_code":"25.0",
    "gn:admin2_code":"611.0",
    "gn:asciiname":"Bagalkodumund",
    "gn:country_code":"IN",
    "gn:dem":2168,
    "gn:feature_class":"P",
    "gn:feature_code":"PPL",
    "gn:name":"Bagalkodumund",
    "gn:population":0,
    "gn:timezone":"Asia/Kolkata",
    "iso:country":"IN",
    "wof:name":"Bagalkodumund",
    "wof:placetype":"locality"
},
  "geometry": {"coordinates":[76.62014000000001,11.4437],"type":"Point"}
}