{
  "type": "Feature",
  "properties": {
    "gn:admin1_code":"2",
    "gn:admin2_code":"544.0",
    "gn:asciiname":"Dalimput",
    "gn:country_code":"IN",
    "gn:dem":1278,
    "gn:feature_class":"P",
    "gn:feature_code":"PPL",
    "gn:name":"Dalimput",
    "gn:population":0,
    "gn:timezone":"Asia/Kolkata",
    "iso:country":"IN",
    "wof:name":"Dalimput",
    "wof:placetype":"locality"
},
  "geometry": {"coordinates":[82.82744,18.17175],"type":"Point"}
}