{
  "type": "Feature",
  "properties": {
    "gn:admin1_code":"11",
    "gn:admin2_code":"25.0",
    "gn:asciiname":"Namu",
    "gn:country_code":"IN",
    "gn:dem":2764,
    "gn:feature_class":"P",
    "gn:feature_code":"PPL",
    "gn:name":"N\u0101mu",
    "gn:population":0,
    "gn:timezone":"Asia/Kolkata",
    "iso:country":"IN",
    "name:ceb_x_preferred":[
        "Namu"
    ],
    "name:swe_x_preferred":[
        "Namu"
    ],
    "wof:name":"Namu",
    "wof:placetype":"locality"
},
  "geometry": {"coordinates":[76.63415999999999,32.74529],"type":"Point"}
}