{
  "type": "Feature",
  "properties": {
    "iso:country":"IN",
    "ks:ks_name":"Kodamtola",
    "ks:ks_pop":430,
    "ks:ks_type":"HABITATION",
    "name:eng_x_preferred":[
        "Kodamtola"
    ],
    "wof:name":"Kodamtola",
    "wof:placetype":"locality",
    "wof:population":430
},
  "geometry": {"coordinates":[90.184783,26.052095],"type":"Point"}
}