{
  "type": "Feature",
  "properties": {
    "iso:country":"IN",
    "ks:ks_name":"Belwa",
    "ks:ks_pop":5050,
    "ks:ks_type":"VILLAGE",
    "ks:ks_uagg_main":0,
    "name:eng_x_preferred":[
        "Belwa"
    ],
    "wof:name":"Belwa",
    "wof:placetype":"neighbourhood",
    "wof:population":5050
},
  "geometry": {"coordinates":[85.003765,26.864046],"type":"Point"}
}