{
  "type": "Feature",
  "properties": {
    "iso:country":"IN",
    "name:eng_x_preferred":[
        "Jawahar Nagar"
    ],
    "name:urd_x_preferred":[
        "\u062c\u0648\u0627\u06c1\u0631 \u0646\u06af\u0627\u0631"
    ],
    "qs:gn_adm0_cc":"IN",
    "qs:gn_local":1277333,
    "qs:gn_nam_loc":"Bangalore, Bangalore, Karnataka, IN",
    "qs:gn_namadm1":"19",
    "qs:local_max":7342,
    "qs:local_sum":38996,
    "qs:localhoods":89,
    "qs:name":"Jawahar Nagar",
    "qs:name_adm0":"India",
    "qs:name_adm1":"Karnataka",
    "qs:name_adm2":"Bangalore",
    "qs:name_local":"Bangalore",
    "qs:photo_max":16,
    "qs:photo_sum":25,
    "qs:placetype":"Suburb",
    "qs:quad_count":5,
    "qs:woe_adm0":23424848,
    "qs:woe_adm1":2345753,
    "qs:woe_adm2":12586572,
    "qs:woe_lau":0,
    "qs:woe_local":2295420,
    "qs:woe_ver":"7.10.0",
    "wd:wordcount":37,
    "wof:lang":[
        "eng"
    ],
    "wof:name":"Jawahar Nagar",
    "wof:placetype":"neighbourhood"
},
  "geometry": {"coordinates":[77.68890500000001,12.951129],"type":"Point"}
}