{
  "type": "Feature",
  "properties": {
    "iso:country":"IN",
    "ks:ks_name":"Gopalpur",
    "ks:ks_pop":2460,
    "ks:ks_type":"VILLAGE",
    "name:eng_x_preferred":[
        "Gopalpur"
    ],
    "wof:name":"Gopalpur",
    "wof:placetype":"locality",
    "wof:population":2460
},
  "geometry": {"coordinates":[87.962124,22.182489],"type":"Point"}
}