{
  "type": "Feature",
  "properties": {
    "iso:country":"IN",
    "ks:ks_name":"Raniban Khasmahal",
    "ks:ks_pop":18,
    "ks:ks_type":"HABITATION",
    "name:eng_x_preferred":[
        "Raniban Khasmahal"
    ],
    "wof:name":"Raniban Khasmahal",
    "wof:placetype":"locality",
    "wof:population":18
},
  "geometry": {"coordinates":[88.245987,27.061723],"type":"Point"}
}