{
  "type": "Feature",
  "properties": {
    "iso:country":"IN",
    "ks:ks_alt_nam":"kanahamanji",
    "ks:ks_name":"Kanahamanji",
    "ks:ks_pop":35,
    "ks:ks_type":"HABITATION",
    "name:eng_x_preferred":[
        "Kanahamanji"
    ],
    "wof:name":"Kanahamanji",
    "wof:placetype":"locality",
    "wof:population":35
},
  "geometry": {"coordinates":[77.40652799999999,10.110667],"type":"Point"}
}