{
  "type": "Feature",
  "properties": {
    "gn:admin1_code":"11",
    "gn:admin2_code":"34.0",
    "gn:asciiname":"Jhayangpu Thach",
    "gn:country_code":"IN",
    "gn:dem":3878,
    "gn:feature_class":"P",
    "gn:feature_code":"PPL",
    "gn:name":"Jh\u0101yangpu Th\u0101ch",
    "gn:population":0,
    "gn:timezone":"Asia/Kolkata",
    "iso:country":"IN",
    "wof:name":"Jhayangpu Thach",
    "wof:placetype":"locality"
},
  "geometry": {"coordinates":[78.41799,31.7062],"type":"Point"}
}