{
  "type": "Feature",
  "properties": {
    "iso:country":"IN",
    "ks:ks_name":"Katelpara",
    "ks:ks_pop":135,
    "ks:ks_type":"HABITATION",
    "name:eng_x_preferred":[
        "Katelpara"
    ],
    "wof:name":"Katelpara",
    "wof:placetype":"locality",
    "wof:population":135
},
  "geometry": {"coordinates":[83.106813,22.375078],"type":"Point"}
}