{
  "type": "Feature",
  "properties": {
    "gn:admin1_code":"11.0",
    "gn:admin2_code":"33.0",
    "gn:asciiname":"Huli",
    "gn:country_code":"IN",
    "gn:dem":1466,
    "gn:feature_class":"P",
    "gn:feature_code":"PPL",
    "gn:name":"Huli",
    "gn:population":0,
    "gn:timezone":"Asia/Kolkata",
    "iso:country":"IN",
    "name:ceb_x_preferred":[
        "Huli"
    ],
    "name:deu_x_preferred":[
        "Huli"
    ],
    "name:fra_x_preferred":[
        "Huli"
    ],
    "name:rus_x_preferred":[
        "\u0425\u0443\u043b\u0438"
    ],
    "name:swe_x_preferred":[
        "Huli"
    ],
    "name:tur_x_preferred":[
        "Huli"
    ],
    "wof:name":"Huli",
    "wof:placetype":"locality"
},
  "geometry": {"coordinates":[77.46679,31.11302],"type":"Point"}
}