{
  "type": "Feature",
  "properties": {
    "iso:country":"IN",
    "ks:ks_name":"Gheepura",
    "ks:ks_pop":102,
    "ks:ks_type":"VILLAGE",
    "name:eng_x_preferred":[
        "Gheepura"
    ],
    "wof:name":"Gheepura",
    "wof:placetype":"locality",
    "wof:population":102
},
  "geometry": {"coordinates":[86.517239,21.556465],"type":"Point"}
}