{
  "type": "Feature",
  "properties": {
    "iso:country":"IN",
    "ks:ks_name":"Lamla",
    "ks:ks_pop":200,
    "ks:ks_type":"HABITATION",
    "name:eng_x_preferred":[
        "Lamla"
    ],
    "wof:name":"Lamla",
    "wof:placetype":"locality",
    "wof:population":200
},
  "geometry": {"coordinates":[74.883769,13.240881],"type":"Point"}
}