{
  "type": "Feature",
  "properties": {
    "iso:country":"IN",
    "ks:ks_name":"Gopiapur",
    "ks:ks_pop":174,
    "ks:ks_type":"HABITATION",
    "name:eng_x_preferred":[
        "Gopiapur"
    ],
    "wof:name":"Gopiapur",
    "wof:placetype":"locality",
    "wof:population":174
},
  "geometry": {"coordinates":[79.484388,26.679267],"type":"Point"}
}