{
  "type": "Feature",
  "properties": {
    "gn:admin1_code":"21",
    "gn:admin2_code":"388.0",
    "gn:asciiname":"Rombha",
    "gn:country_code":"IN",
    "gn:dem":178,
    "gn:feature_class":"P",
    "gn:feature_code":"PPL",
    "gn:name":"Rombha",
    "gn:population":0,
    "gn:timezone":"Asia/Kolkata",
    "iso:country":"IN",
    "wof:name":"Rombha",
    "wof:placetype":"locality"
},
  "geometry": {"coordinates":[84.48461999999998,20.08564],"type":"Point"}
}