{
  "type": "Feature",
  "properties": {
    "iso:country":"IN",
    "ks:ks_name":"Stitigar",
    "ks:ks_pop":68,
    "ks:ks_type":"HABITATION",
    "name:eng_x_preferred":[
        "Stitigar"
    ],
    "wof:name":"Stitigar",
    "wof:placetype":"locality",
    "wof:population":68
},
  "geometry": {"coordinates":[74.51998399999999,14.30902],"type":"Point"}
}