{
  "type": "Feature",
  "properties": {
    "iso:country":"IN",
    "ks:ks_name":"Mata Ji Ka Seegpuriya",
    "ks:ks_pop":87,
    "ks:ks_type":"VILLAGE",
    "name:eng_x_preferred":[
        "Mata Ji Ka Seegpuriya"
    ],
    "wof:name":"Mata Ji Ka Seegpuriya",
    "wof:placetype":"locality",
    "wof:population":87
},
  "geometry": {"coordinates":[74.849575,23.843858],"type":"Point"}
}