{
  "type": "Feature",
  "properties": {
    "iso:country":"IN",
    "ks:ks_name":"Shembewadi",
    "ks:ks_pop":92,
    "ks:ks_type":"HABITATION",
    "name:eng_x_preferred":[
        "Shembewadi"
    ],
    "wof:name":"Shembewadi",
    "wof:placetype":"locality",
    "wof:population":92
},
  "geometry": {"coordinates":[73.561375,17.034542],"type":"Point"}
}