{
  "type": "Feature",
  "properties": {
    "iso:country":"IN",
    "ks:ks_alt_nam":"THUMMALAGUNTA MW",
    "ks:ks_name":"Thummalagunta Mw",
    "ks:ks_pop":187,
    "ks:ks_type":"HABITATION",
    "name:eng_x_preferred":[
        "Thummalagunta Mw"
    ],
    "wof:name":"Thummalagunta Mw",
    "wof:placetype":"locality",
    "wof:population":187
},
  "geometry": {"coordinates":[79.38066000000001,13.613233],"type":"Point"}
}