{
  "type": "Feature",
  "properties": {
    "iso:country":"IN",
    "ks:ks_name":"Ramchandraji Ka Khera",
    "ks:ks_pop":212,
    "ks:ks_type":"HABITATION",
    "name:eng_x_preferred":[
        "Ramchandraji Ka Khera"
    ],
    "wof:name":"Ramchandraji Ka Khera",
    "wof:placetype":"locality",
    "wof:population":212
},
  "geometry": {"coordinates":[75.345613,25.296973],"type":"Point"}
}