{
  "type": "Feature",
  "properties": {
    "iso:country":"IN",
    "ks:ks_name":"Kunnikada",
    "ks:ks_pop":789,
    "ks:ks_type":"HABITATION",
    "name:eng_x_preferred":[
        "Kunnikada"
    ],
    "wof:name":"Kunnikada",
    "wof:placetype":"locality",
    "wof:population":789
},
  "geometry": {"coordinates":[76.933657,8.807343],"type":"Point"}
}