{
  "type": "Feature",
  "properties": {
    "iso:country":"IN",
    "ks:ks_name":"Shanakattu",
    "ks:ks_pop":90,
    "ks:ks_type":"HABITATION",
    "name:eng_x_preferred":[
        "Shanakattu"
    ],
    "wof:name":"Shanakattu",
    "wof:placetype":"locality",
    "wof:population":90
},
  "geometry": {"coordinates":[74.851179,13.639976],"type":"Point"}
}