{
  "type": "Feature",
  "properties": {
    "iso:country":"IN",
    "ks:ks_name":"Dhobani W",
    "ks:ks_pop":122,
    "ks:ks_type":"HABITATION",
    "name:eng_x_preferred":[
        "Dhobani W"
    ],
    "wof:name":"Dhobani W",
    "wof:placetype":"locality",
    "wof:population":122
},
  "geometry": {"coordinates":[83.53497,24.15775],"type":"Point"}
}