{
  "type": "Feature",
  "properties": {
    "gn:admin1_code":"3.0",
    "gn:asciiname":"Bilkhawtlir",
    "gn:country_code":"IN",
    "gn:dem":473,
    "gn:feature_class":"P",
    "gn:feature_code":"PPL",
    "gn:name":"Bilkhawtlir",
    "gn:population":0,
    "gn:timezone":"Asia/Kolkata",
    "iso:country":"IN",
    "wof:name":"Bilkhawtlir",
    "wof:placetype":"locality"
},
  "geometry": {"coordinates":[92.69392999999999,24.29197000000001],"type":"Point"}
}