{
  "type": "Feature",
  "properties": {
    "gn:admin1_code":"40.0",
    "gn:admin2_code":"534.0",
    "gn:asciiname":"Chimalapet",
    "gn:country_code":"IN",
    "gn:dem":275,
    "gn:feature_class":"P",
    "gn:feature_code":"PPL",
    "gn:name":"Chimalapet",
    "gn:population":0,
    "gn:timezone":"Asia/Kolkata",
    "iso:country":"IN",
    "wof:name":"Chimalapet",
    "wof:placetype":"locality"
},
  "geometry": {"coordinates":[79.23250999999998,18.58286],"type":"Point"}
}