{
  "type": "Feature",
  "properties": {
    "iso:country":"IN",
    "ks:ks_name":"Anjunem",
    "ks:ks_pop":0,
    "ks:ks_type":"VILLAGE",
    "name:eng_x_preferred":[
        "Anjunem"
    ],
    "wof:name":"Anjunem",
    "wof:placetype":"locality",
    "wof:population":0
},
  "geometry": {"coordinates":[74.08735299999999,15.626694],"type":"Point"}
}