{
  "type": "Feature",
  "properties": {
    "gn:admin1_code":"29",
    "gn:admin2_code":"244.0",
    "gn:asciiname":"Zeluk",
    "gn:country_code":"IN",
    "gn:dem":2883,
    "gn:feature_class":"P",
    "gn:feature_code":"PPL",
    "gn:name":"Zeluk",
    "gn:population":0,
    "gn:timezone":"Asia/Kolkata",
    "iso:country":"IN",
    "wof:name":"Zeluk",
    "wof:placetype":"locality"
},
  "geometry": {"coordinates":[88.7826,27.25137],"type":"Point"}
}