{
  "type": "Feature",
  "properties": {
    "iso:country":"IN",
    "ks:ks_name":"Ghutulpara",
    "ks:ks_pop":161,
    "ks:ks_type":"HABITATION",
    "name:eng_x_preferred":[
        "Ghutulpara"
    ],
    "wof:name":"Ghutulpara",
    "wof:placetype":"locality",
    "wof:population":161
},
  "geometry": {"coordinates":[81.343309,19.61615],"type":"Point"}
}