{
  "type": "Feature",
  "properties": {
    "gn:admin1_code":"36",
    "gn:admin2_code":"178.0",
    "gn:asciiname":"Sisara",
    "gn:country_code":"IN",
    "gn:dem":91,
    "gn:feature_class":"P",
    "gn:feature_code":"PPL",
    "gn:name":"Sis\u0101ra",
    "gn:population":0,
    "gn:timezone":"Asia/Kolkata",
    "iso:country":"IN",
    "name:deu_x_preferred":[
        "Sisara"
    ],
    "name:fas_x_preferred":[
        "\u0633\u06cc\u200c\u0633\u0631\u0627"
    ],
    "wof:name":"Sisara",
    "wof:placetype":"locality"
},
  "geometry": {"coordinates":[82.71661,26.43862],"type":"Point"}
}