{
  "type": "Feature",
  "properties": {
    "gn:admin1_code":"36",
    "gn:admin2_code":"191.0",
    "gn:asciiname":"Jiwanpur",
    "gn:country_code":"IN",
    "gn:dem":81,
    "gn:feature_class":"P",
    "gn:feature_code":"PPL",
    "gn:name":"J\u012bwanpur",
    "gn:population":0,
    "gn:timezone":"Asia/Kolkata",
    "iso:country":"IN",
    "name:ceb_x_preferred":[
        "Jeewanpur"
    ],
    "name:msa_x_preferred":[
        "Jeewanpur"
    ],
    "name:new_x_preferred":[
        "\u091c\u0940\u0935\u0928\u092a\u0941\u0930"
    ],
    "name:pol_x_preferred":[
        "Jeewanpur"
    ],
    "wof:name":"Jiwanpur",
    "wof:placetype":"locality"
},
  "geometry": {"coordinates":[83.13203,25.79592],"type":"Point"}
}