{
  "type": "Feature",
  "properties": {
    "iso:country":"IN",
    "ks:ks_name":"Sompura",
    "ks:ks_pop":484,
    "ks:ks_type":"VILLAGE",
    "name:eng_x_preferred":[
        "Sompura"
    ],
    "wof:name":"Sompura",
    "wof:placetype":"locality",
    "wof:population":484
},
  "geometry": {"coordinates":[77.806231,13.097007],"type":"Point"}
}