{
  "type": "Feature",
  "properties": {
    "iso:country":"IN",
    "ks:ks_name":"Pattigaon",
    "ks:ks_pop":89,
    "ks:ks_type":"VILLAGE",
    "name:eng_x_preferred":[
        "Pattigaon"
    ],
    "wof:name":"Pattigaon",
    "wof:placetype":"locality",
    "wof:population":89
},
  "geometry": {"coordinates":[80.158691,19.3015],"type":"Point"}
}