{
  "type": "Feature",
  "properties": {
    "gn:admin1_code":"25.0",
    "gn:admin2_code":"608.0",
    "gn:asciiname":"Kaminayakkanpatti",
    "gn:country_code":"IN",
    "gn:dem":283,
    "gn:feature_class":"P",
    "gn:feature_code":"PPL",
    "gn:name":"K\u0101min\u0101yakkanpatti",
    "gn:population":0,
    "gn:timezone":"Asia/Kolkata",
    "iso:country":"IN",
    "wof:name":"Kaminayakkanpatti",
    "wof:placetype":"locality"
},
  "geometry": {"coordinates":[77.89156,11.8769],"type":"Point"}
}