{
  "type": "Feature",
  "properties": {
    "gn:admin1_code":"25.0",
    "gn:admin2_code":"608.0",
    "gn:asciiname":"Kaminayakkanpatti",
    "gn:country_code":"IN",
    "gn:dem":283,
    "gn:feature_class":"P",
    "gn:feature_code":"PPL",
    "gn:name":"K\u0101min\u0101yakkanpatti",
    "gn:population":0,
    "gn:timezone":"Asia/Kolkata",
    "iso:country":"IN",
    "ks:ks_name":"Kaminaickenpatti",
    "ks:ks_pop":296,
    "ks:ks_type":"HABITATION",
    "name:eng_x_preferred":[
        "Kaminaickenpatti"
    ],
    "name:eng_x_variant":[
        "Kaminayakkanpatti"
    ],
    "wof:name":"Kaminaickenpatti",
    "wof:placetype":"locality",
    "wof:population":296
},
  "geometry": {"coordinates":[77.89233,11.874466],"type":"Point"}
}