{
  "type": "Feature",
  "properties": {
    "iso:country":"IN",
    "ks:ks_alt_nam":"HARIJAN TOL",
    "ks:ks_name":"Harijan Tol",
    "ks:ks_pop":271,
    "ks:ks_type":"HABITATION",
    "ks:ks_uagg_main":0,
    "name:eng_x_preferred":[
        "Harijan Tol"
    ],
    "wof:name":"Harijan Tol",
    "wof:placetype":"neighbourhood",
    "wof:population":271
},
  "geometry": {"coordinates":[86.21211,25.987165],"type":"Point"}
}