{
  "type": "Feature",
  "properties": {
    "iso:country":"IN",
    "ks:ks_name":"Kuntekuli",
    "ks:ks_pop":12,
    "ks:ks_type":"HABITATION",
    "name:eng_x_preferred":[
        "Kuntekuli"
    ],
    "wof:name":"Kuntekuli",
    "wof:placetype":"locality",
    "wof:population":12
},
  "geometry": {"coordinates":[74.668654,14.3855],"type":"Point"}
}