{
  "type": "Feature",
  "properties": {
    "gn:country":"IN",
    "gn:fcode":"PPL",
    "gn:pop":18738,
    "iso:country":"IN",
    "name:bpy_x_preferred":[
        "\u09a8\u09be\u09a8\u09cc\u09a4\u09be"
    ],
    "name:bul_x_preferred":[
        "\u041d\u0430\u043d\u0430\u0443\u0442\u0430"
    ],
    "name:chi_x_preferred":[
        "\u7eb3\u7459\u5854"
    ],
    "name:dut_x_preferred":[
        "Nanauta"
    ],
    "name:eng_x_preferred":[
        "Nanauta"
    ],
    "name:ita_x_preferred":[
        "Nanauta"
    ],
    "name:may_x_preferred":[
        "Nanauta"
    ],
    "name:mlg_x_preferred":[
        "Nanauta"
    ],
    "name:nan_x_preferred":[
        "Nanauta"
    ],
    "name:new_x_preferred":[
        "\u0928\u0928\u094c\u0924\u093e"
    ],
    "name:pol_x_preferred":[
        "Nanauta"
    ],
    "name:por_x_preferred":[
        "Nanauta"
    ],
    "name:swe_x_preferred":[
        "Nanauta"
    ],
    "name:unk_x_variant":[
        "Phuta Shahr"
    ],
    "name:urd_x_preferred":[
        "\u0646\u0627\u0646\u0648\u062a\u06c1"
    ],
    "name:vie_x_preferred":[
        "Nanauta"
    ],
    "qs:name":"Nanauta",
    "qs:name_adm0":"India",
    "qs:name_adm1":"Uttar Pradesh",
    "qs:photos_9r":0,
    "qs:photos_sr":0,
    "qs:placetype":"Town",
    "qs:pop_sr":"6",
    "wd:wordcount":153,
    "wof:name":"Nanauta",
    "wof:placetype":"locality",
    "wof:population":18738
},
  "geometry": {"coordinates":[77.4174,29.71256],"type":"Point"}
}