{
  "type": "Feature",
  "properties": {
    "iso:country":"IN",
    "ks:ks_name":"Uperpada",
    "ks:ks_pop":57,
    "ks:ks_type":"HABITATION",
    "name:eng_x_preferred":[
        "Uperpada"
    ],
    "wof:name":"Uperpada",
    "wof:placetype":"locality",
    "wof:population":57
},
  "geometry": {"coordinates":[83.303597,19.785647],"type":"Point"}
}