{
  "type": "Feature",
  "properties": {
    "iso:country":"IN",
    "ks:ks_name":"Chandanpur",
    "ks:ks_pop":2640,
    "ks:ks_type":"HABITATION",
    "name:eng_x_preferred":[
        "Chandanpur"
    ],
    "wof:name":"Chandanpur",
    "wof:placetype":"locality",
    "wof:population":2640
},
  "geometry": {"coordinates":[88.128075,25.427603],"type":"Point"}
}