{
  "type": "Feature",
  "properties": {
    "iso:country":"IN",
    "ks:ks_name":"Malbhoomwadi",
    "ks:ks_pop":72,
    "ks:ks_type":"HABITATION",
    "name:eng_x_preferred":[
        "Malbhoomwadi"
    ],
    "wof:name":"Malbhoomwadi",
    "wof:placetype":"locality",
    "wof:population":72
},
  "geometry": {"coordinates":[73.144887,18.842445],"type":"Point"}
}