{
  "type": "Feature",
  "properties": {
    "iso:country":"IN",
    "ks:ks_name":"Koshtyewadi",
    "ks:ks_pop":41,
    "ks:ks_type":"HABITATION",
    "name:eng_x_preferred":[
        "Koshtyewadi"
    ],
    "wof:name":"Koshtyewadi",
    "wof:placetype":"locality",
    "wof:population":41
},
  "geometry": {"coordinates":[73.54454699999999,16.572944],"type":"Point"}
}