{
  "type": "Feature",
  "properties": {
    "gn:admin1_code":"34.0",
    "gn:admin2_code":"221.0",
    "gn:asciiname":"Purnahi",
    "gn:country_code":"IN",
    "gn:dem":50,
    "gn:feature_class":"P",
    "gn:feature_code":"PPL",
    "gn:name":"Purn\u0101hi",
    "gn:population":0,
    "gn:timezone":"Asia/Kolkata",
    "iso:country":"IN",
    "ks:ks_alt_nam":"Purn\u0101hi",
    "ks:ks_name":"Purnahi",
    "ks:ks_pop":2925,
    "ks:ks_type":"VILLAGE",
    "name:eng_x_preferred":[
        "Purnahi"
    ],
    "name:eng_x_variant":[
        "Purn\u0101hi"
    ],
    "wof:name":"Purnahi",
    "wof:placetype":"locality",
    "wof:population":2925
},
  "geometry": {"coordinates":[85.875585,25.903071],"type":"Point"}
}