{
  "type": "Feature",
  "properties": {
    "gn:admin1_code":"39.0",
    "gn:admin2_code":"63.0",
    "gn:asciiname":"Dhalle Chhani",
    "gn:country_code":"IN",
    "gn:dem":1218,
    "gn:feature_class":"P",
    "gn:feature_code":"PPL",
    "gn:name":"Dhalle Chh\u0101ni",
    "gn:population":0,
    "gn:timezone":"Asia/Kolkata",
    "iso:country":"IN",
    "wof:name":"Dhalle Chhani",
    "wof:placetype":"locality"
},
  "geometry": {"coordinates":[79.79985000000001,29.70488],"type":"Point"}
}