{
  "type": "Feature",
  "properties": {
    "iso:country":"IN",
    "ks:ks_alt_nam":"Desyagani tanda",
    "ks:ks_name":"Desyagani Tanda",
    "ks:ks_pop":92,
    "ks:ks_type":"HABITATION",
    "name:eng_x_preferred":[
        "Desyagani Tanda"
    ],
    "wof:name":"Desyagani Tanda",
    "wof:placetype":"locality",
    "wof:population":92
},
  "geometry": {"coordinates":[78.46245500000001,16.812049],"type":"Point"}
}