{
  "type": "Feature",
  "properties": {
    "iso:country":"IN",
    "ks:ks_name":"Patratoli",
    "ks:ks_pop":111,
    "ks:ks_type":"HABITATION",
    "name:eng_x_preferred":[
        "Patratoli"
    ],
    "wof:name":"Patratoli",
    "wof:placetype":"locality",
    "wof:population":111
},
  "geometry": {"coordinates":[84.96426599999999,23.035006],"type":"Point"}
}