{
  "type": "Feature",
  "properties": {
    "iso:country":"IN",
    "qs:name":"Bachenahatti",
    "qs:name_adm0":"India",
    "qs:name_adm1":"Karnataka",
    "qs:photos":38,
    "qs:photos_1k":8,
    "qs:photos_9k":1,
    "qs:photos_9r":2,
    "qs:photos_all":38,
    "qs:photos_sr":2,
    "qs:placetype":"Town",
    "qs:pop_sr":"0",
    "wof:name":"Bachenahatti",
    "wof:placetype":"locality"
},
  "geometry": {"coordinates":[77.30392399999999,12.926101],"type":"Point"}
}