{
  "type": "Feature",
  "properties": {
    "iso:country":"IN",
    "ks:ks_name":"Vishwanathapura",
    "ks:ks_pop":20,
    "ks:ks_type":"HABITATION",
    "name:eng_x_preferred":[
        "Vishwanathapura"
    ],
    "wof:name":"Vishwanathapura",
    "wof:placetype":"locality",
    "wof:population":20
},
  "geometry": {"coordinates":[75.319113,13.444418],"type":"Point"}
}