{
  "type": "Feature",
  "properties": {
    "iso:country":"IN",
    "ks:ks_alt_nam":"Thoray kadavu",
    "ks:ks_name":"Thoray Kadavu",
    "ks:ks_pop":450,
    "ks:ks_type":"HABITATION",
    "name:eng_x_preferred":[
        "Thoray Kadavu"
    ],
    "wof:name":"Thoray Kadavu",
    "wof:placetype":"locality",
    "wof:population":450
},
  "geometry": {"coordinates":[75.747917,11.409277],"type":"Point"}
}