{
  "type": "Feature",
  "properties": {
    "gn:admin1_code":"19",
    "gn:admin2_code":"563.0",
    "gn:asciiname":"Itguli",
    "gn:country_code":"IN",
    "gn:dem":519,
    "gn:feature_class":"P",
    "gn:feature_code":"PPL",
    "gn:name":"Itguli",
    "gn:population":0,
    "gn:timezone":"Asia/Kolkata",
    "iso:country":"IN",
    "ks:ks_name":"Itaguli",
    "ks:ks_pop":123,
    "ks:ks_type":"VILLAGE",
    "name:eng_x_preferred":[
        "Itaguli"
    ],
    "name:eng_x_variant":[
        "Itguli"
    ],
    "wof:name":"Itaguli",
    "wof:placetype":"locality",
    "wof:population":123
},
  "geometry": {"coordinates":[74.796474,14.657976],"type":"Point"}
}