{
  "type": "Feature",
  "properties": {
    "iso:country":"IN",
    "ks:ks_name":"Bhanera Faliya",
    "ks:ks_pop":320,
    "ks:ks_type":"HABITATION",
    "name:eng_x_preferred":[
        "Bhanera Faliya"
    ],
    "wof:name":"Bhanera Faliya",
    "wof:placetype":"locality",
    "wof:population":320
},
  "geometry": {"coordinates":[73.68388899999999,23.444611],"type":"Point"}
}