{
  "type": "Feature",
  "properties": {
    "gn:admin1_code":"2.0",
    "gn:admin2_code":"554.0",
    "gn:asciiname":"Nagirivandlapalli",
    "gn:country_code":"IN",
    "gn:dem":547,
    "gn:feature_class":"P",
    "gn:feature_code":"PPL",
    "gn:name":"Nagiriv\u0101ndlapalli",
    "gn:population":0,
    "gn:timezone":"Asia/Kolkata",
    "iso:country":"IN",
    "wof:name":"Nagirivandlapalli",
    "wof:placetype":"neighbourhood"
},
  "geometry": {"coordinates":[79.09694,13.63583],"type":"Point"}
}