{
  "type": "Feature",
  "properties": {
    "iso:country":"IN",
    "ks:ks_alt_nam":"SAWAKAR PANAND",
    "ks:ks_name":"Sawakar Panand",
    "ks:ks_pop":105,
    "ks:ks_type":"HABITATION",
    "name:eng_x_preferred":[
        "Sawakar Panand"
    ],
    "wof:name":"Sawakar Panand",
    "wof:placetype":"locality",
    "wof:population":105
},
  "geometry": {"coordinates":[74.307255,16.89322],"type":"Point"}
}