{
  "type": "Feature",
  "properties": {
    "iso:country":"IN",
    "ks:ks_name":"Deogarh",
    "ks:ks_pop":1639,
    "ks:ks_type":"HABITATION",
    "name:eng_x_preferred":[
        "Deogarh"
    ],
    "wof:name":"Deogarh",
    "wof:placetype":"locality",
    "wof:population":1639
},
  "geometry": {"coordinates":[72.605092,26.509725],"type":"Point"}
}