{
  "type": "Feature",
  "properties": {
    "iso:country":"IN",
    "ks:ks_name":"Nachhipur",
    "ks:ks_pop":609,
    "ks:ks_type":"HABITATION",
    "name:eng_x_preferred":[
        "Nachhipur"
    ],
    "wof:name":"Nachhipur",
    "wof:placetype":"locality",
    "wof:population":609
},
  "geometry": {"coordinates":[87.580377,22.350577],"type":"Point"}
}