{
  "type": "Feature",
  "properties": {
    "gn:admin1_code":"12.0",
    "gn:admin2_code":"021",
    "gn:asciiname":"Maheshpur",
    "gn:country_code":"IN",
    "gn:dem":355,
    "gn:feature_class":"P",
    "gn:feature_code":"PPL",
    "gn:name":"Maheshpur",
    "gn:population":0,
    "gn:timezone":"Asia/Kolkata",
    "iso:country":"IN",
    "name:ara_x_preferred":[
        "\u0645\u0627\u0647\u064a\u0634\u0628\u0648\u0631"
    ],
    "name:ben_bn_x_preferred":[
        "\u09ae\u09b9\u09c7\u09b6\u09aa\u09c1\u09b0"
    ],
    "name:ben_in_x_preferred":[
        "\u09ae\u09b9\u09c7\u09b6\u09aa\u09c1\u09b0"
    ],
    "name:ceb_x_preferred":[
        "Maheshpur"
    ],
    "name:fra_x_preferred":[
        "Maheshpur"
    ],
    "name:guj_x_preferred":[
        "\u0aae\u0ab9\u0ac7\u0ab6\u0aaa\u0ac1\u0ab0"
    ],
    "name:hin_x_preferred":[
        "\u092e\u0939\u0947\u0936\u092a\u0941\u0930"
    ],
    "name:hin_x_variant":[
        "\u092e\u0939\u0947\u0936\u092a\u0941\u0930 \u0968"
    ],
    "name:kan_x_preferred":[
        "\u0cae\u0cb9\u0cc7\u0cb6\u0ccd"
    ],
    "name:mal_x_preferred":[
        "\u0d2e\u0d39\u0d47\u0d37\u0d4d\u0d2a\u0d42\u0d7c"
    ],
    "name:mar_x_preferred":[
        "\u092e\u0939\u0947\u0936\u092a\u0942\u0930"
    ],
    "name:new_x_preferred":[
        "\u092e\u0939\u0947\u0936\u092a\u0941\u0930 \u0917\u093e\u0935\u093f\u0938"
    ],
    "name:pan_x_preferred":[
        "\u0a2e\u0a39\u0a47\u0a36\u0a2a\u0a41\u0a30"
    ],
    "name:pol_x_preferred":[
        "Maheshpur"
    ],
    "name:swe_x_preferred":[
        "Maheshpur"
    ],
    "name:tam_x_preferred":[
        "\u0bae\u0bb9\u0bc7\u0bb7\u0bcd\u0baa\u0bc2\u0bb0\u0bcd"
    ],
    "name:tel_x_preferred":[
        "\u0c2e\u0c39\u0c47\u0c37\u0c4d"
    ],
    "name:urd_x_preferred":[
        "\u0645\u06c1\u06cc\u0633 \u067e\u0648\u0631"
    ],
    "wof:name":"Maheshpur",
    "wof:placetype":"locality"
},
  "geometry": {"coordinates":[74.85833000000002,32.73889],"type":"Point"}
}