{
  "type": "Feature",
  "properties": {
    "iso:country":"IN",
    "ks:ks_name":"Nagla Miththu",
    "ks:ks_pop":35,
    "ks:ks_type":"HABITATION",
    "name:eng_x_preferred":[
        "Nagla Miththu"
    ],
    "wof:name":"Nagla Miththu",
    "wof:placetype":"locality",
    "wof:population":35
},
  "geometry": {"coordinates":[78.772729,27.152517],"type":"Point"}
}