{
  "type": "Feature",
  "properties": {
    "iso:country":"IN",
    "ks:ks_name":"Hasan Alipur Muthra",
    "ks:ks_pop":483,
    "ks:ks_type":"VILLAGE",
    "name:eng_x_preferred":[
        "Hasan Alipur Muthra"
    ],
    "wof:name":"Hasan Alipur Muthra",
    "wof:placetype":"locality",
    "wof:population":483
},
  "geometry": {"coordinates":[78.463804,29.47118],"type":"Point"}
}