{
  "type": "Feature",
  "properties": {
    "iso:country":"IN",
    "ks:ks_alt_nam":"SHIVECHAMALA",
    "ks:ks_name":"Shivechamala",
    "ks:ks_pop":76,
    "ks:ks_type":"HABITATION",
    "name:eng_x_preferred":[
        "Shivechamala"
    ],
    "wof:name":"Shivechamala",
    "wof:placetype":"locality",
    "wof:population":76
},
  "geometry": {"coordinates":[74.90732,17.476302],"type":"Point"}
}