{
  "type": "Feature",
  "properties": {
    "iso:country":"IN",
    "ks:ks_name":"Dakkhin Kalbari",
    "ks:ks_pop":344,
    "ks:ks_type":"HABITATION",
    "name:eng_x_preferred":[
        "Dakkhin Kalbari"
    ],
    "wof:name":"Dakkhin Kalbari",
    "wof:placetype":"locality",
    "wof:population":344
},
  "geometry": {"coordinates":[90.828445,26.49325],"type":"Point"}
}