{
  "type": "Feature",
  "properties": {
    "gn:admin1_code":"39.0",
    "gn:admin2_code":"60.0",
    "gn:asciiname":"Bungoti",
    "gn:country_code":"IN",
    "gn:dem":1482,
    "gn:feature_class":"P",
    "gn:feature_code":"PPL",
    "gn:name":"Bungoti",
    "gn:population":0,
    "gn:timezone":"Asia/Kolkata",
    "iso:country":"IN",
    "ks:ks_name":"Bangoti",
    "ks:ks_pop":237,
    "ks:ks_type":"VILLAGE",
    "name:eng_x_preferred":[
        "Bangoti"
    ],
    "name:eng_x_variant":[
        "Bungoti"
    ],
    "wof:name":"Bangoti",
    "wof:placetype":"locality",
    "wof:population":237
},
  "geometry": {"coordinates":[77.93381100000001,30.698967],"type":"Point"}
}