{
  "type": "Feature",
  "properties": {
    "iso:country":"IN",
    "ks:ks_name":"Parande Mala",
    "ks:ks_pop":209,
    "ks:ks_type":"HABITATION",
    "ks:ks_uagg_main":0,
    "name:eng_x_preferred":[
        "Parande Mala"
    ],
    "wof:name":"Parande Mala",
    "wof:placetype":"neighbourhood",
    "wof:population":209
},
  "geometry": {"coordinates":[74.3561,18.162],"type":"Point"}
}