{
  "type": "Feature",
  "properties": {
    "iso:country":"IN",
    "ks:ks_name":"Pamurelli",
    "ks:ks_pop":12,
    "ks:ks_type":"VILLAGE",
    "name:eng_x_preferred":[
        "Pamurelli"
    ],
    "wof:name":"Pamurelli",
    "wof:placetype":"locality",
    "wof:population":12
},
  "geometry": {"coordinates":[82.63763899999999,18.120469],"type":"Point"}
}