{
  "type": "Feature",
  "properties": {
    "iso:country":"IN",
    "ks:ks_name":"Tanta Gaon Roto",
    "ks:ks_pop":163,
    "ks:ks_type":"HABITATION",
    "name:eng_x_preferred":[
        "Tanta Gaon Roto"
    ],
    "wof:name":"Tanta Gaon Roto",
    "wof:placetype":"locality",
    "wof:population":163
},
  "geometry": {"coordinates":[80.614689,29.980715],"type":"Point"}
}