{
  "type": "Feature",
  "properties": {
    "iso:country":"IN",
    "ks:ks_name":"Sindhvaipura",
    "ks:ks_pop":270,
    "ks:ks_type":"HABITATION",
    "name:eng_x_preferred":[
        "Sindhvaipura"
    ],
    "wof:name":"Sindhvaipura",
    "wof:placetype":"locality",
    "wof:population":270
},
  "geometry": {"coordinates":[71.75207399999999,24.2846],"type":"Point"}
}