{
  "type": "Feature",
  "properties": {
    "iso:country":"IN",
    "ks:ks_name":"Balwa",
    "ks:ks_pop":100,
    "ks:ks_type":"HABITATION",
    "name:eng_x_preferred":[
        "Balwa"
    ],
    "wof:name":"Balwa",
    "wof:placetype":"locality",
    "wof:population":100
},
  "geometry": {"coordinates":[84.931168,25.222607],"type":"Point"}
}