{
  "type": "Feature",
  "properties": {
    "iso:country":"IN",
    "ks:ks_name":"Marattipalayam",
    "ks:ks_pop":300,
    "ks:ks_type":"HABITATION",
    "name:eng_x_preferred":[
        "Marattipalayam"
    ],
    "wof:name":"Marattipalayam",
    "wof:placetype":"locality",
    "wof:population":300
},
  "geometry": {"coordinates":[78.69792700000001,12.645427],"type":"Point"}
}