{
  "type": "Feature",
  "properties": {
    "iso:country":"IN",
    "ks:ks_alt_nam":"Atiraj ka pura",
    "ks:ks_name":"Atiraj Ka Pura",
    "ks:ks_pop":102,
    "ks:ks_type":"HABITATION",
    "name:eng_x_preferred":[
        "Atiraj Ka Pura"
    ],
    "wof:name":"Atiraj Ka Pura",
    "wof:placetype":"locality",
    "wof:population":102
},
  "geometry": {"coordinates":[77.68814399999999,26.699683],"type":"Point"}
}