{
  "type": "Feature",
  "properties": {
    "gn:admin1_code":"21",
    "gn:admin2_code":"370.0",
    "gn:asciiname":"Larambha",
    "gn:country_code":"IN",
    "gn:dem":154,
    "gn:feature_class":"P",
    "gn:feature_code":"PPL",
    "gn:name":"Larambha",
    "gn:population":0,
    "gn:timezone":"Asia/Kolkata",
    "iso:country":"IN",
    "ks:ks_name":"Larambha",
    "ks:ks_pop":1567,
    "ks:ks_type":"VILLAGE",
    "ks:ks_uagg_main":0,
    "name:eng_x_preferred":[
        "Larambha"
    ],
    "wof:name":"Larambha",
    "wof:placetype":"neighbourhood",
    "wof:population":1567
},
  "geometry": {"coordinates":[83.83378399999999,21.350739],"type":"Point"}
}