{
  "type": "Feature",
  "properties": {
    "iso:country":"IN",
    "ks:ks_name":"Semalkhedi",
    "ks:ks_pop":325,
    "ks:ks_type":"HABITATION",
    "name:eng_x_preferred":[
        "Semalkhedi"
    ],
    "wof:name":"Semalkhedi",
    "wof:placetype":"locality",
    "wof:population":325
},
  "geometry": {"coordinates":[74.72451700000001,22.783437],"type":"Point"}
}