{
  "type": "Feature",
  "properties": {
    "iso:country":"IN",
    "ks:ks_name":"Nagla Kundan",
    "ks:ks_pop":281,
    "ks:ks_type":"HABITATION",
    "name:eng_x_preferred":[
        "Nagla Kundan"
    ],
    "wof:name":"Nagla Kundan",
    "wof:placetype":"locality",
    "wof:population":281
},
  "geometry": {"coordinates":[78.477791,27.910766],"type":"Point"}
}