{
  "type": "Feature",
  "properties": {
    "gn:admin1_code":"21.0",
    "gn:admin2_code":"382",
    "gn:asciiname":"Bairi",
    "gn:country_code":"IN",
    "gn:dem":32,
    "gn:feature_class":"P",
    "gn:feature_code":"PPL",
    "gn:name":"Bairi",
    "gn:population":0,
    "gn:timezone":"Asia/Kolkata",
    "iso:country":"IN",
    "wof:name":"Bairi",
    "wof:placetype":"neighbourhood"
},
  "geometry": {"coordinates":[86.03467000000001,20.63377],"type":"Point"}
}