{
  "type": "Feature",
  "properties": {
    "iso:country":"IN",
    "ks:ks_name":"Gonditola Pau",
    "ks:ks_pop":216,
    "ks:ks_type":"HABITATION",
    "name:eng_x_preferred":[
        "Gonditola Pau"
    ],
    "wof:name":"Gonditola Pau",
    "wof:placetype":"locality",
    "wof:population":216
},
  "geometry": {"coordinates":[80.507991,21.339638],"type":"Point"}
}