{
  "type": "Feature",
  "properties": {
    "gn:admin1_code":"21.0",
    "gn:admin2_code":"390",
    "gn:asciiname":"Budhaguda",
    "gn:country_code":"IN",
    "gn:dem":782,
    "gn:feature_class":"P",
    "gn:feature_code":"PPL",
    "gn:name":"Budh\u0101guda",
    "gn:population":0,
    "gn:timezone":"Asia/Kolkata",
    "iso:country":"IN",
    "name:und_x_variant":[
        "Budaguda",
        "Budagud",
        "Burhagurha",
        "Budh\u0101guda"
    ],
    "wof:name":"Budhaguda",
    "wof:placetype":"locality"
},
  "geometry": {"coordinates":[83.94225,20.00295],"type":"Point"}
}