{
  "type": "Feature",
  "properties": {
    "iso:country":"IN",
    "ks:ks_name":"Mulesal",
    "ks:ks_pop":17,
    "ks:ks_type":"HABITATION",
    "name:eng_x_preferred":[
        "Mulesal"
    ],
    "wof:name":"Mulesal",
    "wof:placetype":"locality",
    "wof:population":17
},
  "geometry": {"coordinates":[74.685191,14.877547],"type":"Point"}
}