{
  "type": "Feature",
  "properties": {
    "iso:country":"IN",
    "ks:ks_name":"Vagadadi",
    "ks:ks_pop":728,
    "ks:ks_type":"VILLAGE",
    "name:eng_x_preferred":[
        "Vagadadi"
    ],
    "wof:name":"Vagadadi",
    "wof:placetype":"locality",
    "wof:population":728
},
  "geometry": {"coordinates":[72.680933,24.160886],"type":"Point"}
}