{
  "type": "Feature",
  "properties": {
    "gn:admin1_code":"11",
    "gn:admin2_code":"25.0",
    "gn:asciiname":"Shiling",
    "gn:country_code":"IN",
    "gn:dem":3035,
    "gn:feature_class":"P",
    "gn:feature_code":"PPL",
    "gn:name":"Shiling",
    "gn:population":0,
    "gn:timezone":"Asia/Kolkata",
    "iso:country":"IN",
    "wof:name":"Shiling",
    "wof:placetype":"locality"
},
  "geometry": {"coordinates":[76.72684,32.79679],"type":"Point"}
}