{
  "type": "Feature",
  "properties": {
    "iso:country":"IN",
    "ks:ks_alt_nam":"Kovil theru",
    "ks:ks_name":"Kovil Theru",
    "ks:ks_pop":40,
    "ks:ks_type":"HABITATION",
    "name:eng_x_preferred":[
        "Kovil Theru"
    ],
    "wof:name":"Kovil Theru",
    "wof:placetype":"locality",
    "wof:population":40
},
  "geometry": {"coordinates":[79.775432,10.675647],"type":"Point"}
}