{
  "type": "Feature",
  "properties": {
    "gn:admin1_code":"11",
    "gn:admin2_code":"29.0",
    "gn:asciiname":"Tita",
    "gn:country_code":"IN",
    "gn:dem":565,
    "gn:feature_class":"P",
    "gn:feature_code":"PPL",
    "gn:name":"Tita",
    "gn:population":0,
    "gn:timezone":"Asia/Kolkata",
    "iso:country":"IN",
    "name:ara_x_preferred":[
        "\u062a\u064a\u062a\u0627"
    ],
    "name:azb_x_preferred":[
        "\u062a\u06cc\u062a\u0627"
    ],
    "name:deu_x_preferred":[
        "Tita"
    ],
    "name:fas_x_preferred":[
        "\u062a\u06cc\u062a\u0627"
    ],
    "name:fra_x_preferred":[
        "Tita"
    ],
    "name:hun_x_preferred":[
        "Tita"
    ],
    "name:ind_x_preferred":[
        "Tita"
    ],
    "name:ita_x_preferred":[
        "Tita"
    ],
    "name:jpn_x_preferred":[
        "\u30df\u30a6\u30c8\u30f3\u30fb\u30b1\u30a4\u30ed\u30b9\u30fb\u30c0\u30fb\u30d1\u30a4\u30b7\u30e7\u30f3"
    ],
    "name:kor_x_preferred":[
        "\uce58\ud0c0"
    ],
    "name:msa_x_preferred":[
        "Tita"
    ],
    "name:nor_x_preferred":[
        "Tita"
    ],
    "name:pol_x_preferred":[
        "Tita"
    ],
    "name:por_x_preferred":[
        "Tita"
    ],
    "name:rus_x_preferred":[
        "\u0422\u0438\u0442\u0430"
    ],
    "name:spa_x_preferred":[
        "Tita"
    ],
    "name:sqi_x_preferred":[
        "Tita"
    ],
    "name:srp_x_preferred":[
        "\u0422\u0438\u0442\u0430"
    ],
    "name:tgk_x_preferred":[
        "\u0422\u0438\u0442\u0430"
    ],
    "name:ukr_x_preferred":[
        "\u0422\u0456\u0442\u0430"
    ],
    "name:vie_x_preferred":[
        "Tita"
    ],
    "wof:name":"Tita",
    "wof:placetype":"locality"
},
  "geometry": {"coordinates":[75.99082,31.77714000000001],"type":"Point"}
}