{
  "type": "Feature",
  "properties": {
    "iso:country":"IN",
    "ks:ks_alt_nam":"CHATRA GHAT",
    "ks:ks_name":"Chatra Ghat",
    "ks:ks_pop":582,
    "ks:ks_type":"HABITATION",
    "name:eng_x_preferred":[
        "Chatra Ghat"
    ],
    "wof:name":"Chatra Ghat",
    "wof:placetype":"locality",
    "wof:population":582
},
  "geometry": {"coordinates":[87.3942,25.8453],"type":"Point"}
}