{
  "type": "Feature",
  "properties": {
    "iso:country":"IN",
    "ks:ks_name":"Kukkottu",
    "ks:ks_pop":76,
    "ks:ks_type":"HABITATION",
    "name:eng_x_preferred":[
        "Kukkottu"
    ],
    "wof:name":"Kukkottu",
    "wof:placetype":"locality",
    "wof:population":76
},
  "geometry": {"coordinates":[74.903379,13.181595],"type":"Point"}
}