{
  "type": "Feature",
  "properties": {
    "iso:country":"IN",
    "ks:ks_name":"Kudauli",
    "ks:ks_pop":730,
    "ks:ks_type":"HABITATION",
    "name:eng_x_preferred":[
        "Kudauli"
    ],
    "wof:name":"Kudauli",
    "wof:placetype":"locality",
    "wof:population":730
},
  "geometry": {"coordinates":[79.624593,27.69972],"type":"Point"}
}