{
  "type": "Feature",
  "properties": {
    "gn:admin1_code":"36",
    "gn:admin2_code":"154.0",
    "gn:asciiname":"Makka Gadaria Purwa",
    "gn:country_code":"IN",
    "gn:dem":115,
    "gn:feature_class":"P",
    "gn:feature_code":"PPL",
    "gn:name":"Makka Gadari\u0101 Purwa",
    "gn:population":0,
    "gn:timezone":"Asia/Kolkata",
    "iso:country":"IN",
    "wof:name":"Makka Gadaria Purwa",
    "wof:placetype":"locality"
},
  "geometry": {"coordinates":[81.30400999999998,27.48196],"type":"Point"}
}