{
  "type": "Feature",
  "properties": {
    "iso:country":"IN",
    "ks:ks_name":"Bhagelguda",
    "ks:ks_pop":511,
    "ks:ks_type":"HABITATION",
    "name:eng_x_preferred":[
        "Bhagelguda"
    ],
    "wof:name":"Bhagelguda",
    "wof:placetype":"locality",
    "wof:population":511
},
  "geometry": {"coordinates":[82.556725,19.456409],"type":"Point"}
}