{
  "type": "Feature",
  "properties": {
    "gn:admin1_code":"39.0",
    "gn:admin2_code":"64.0",
    "gn:asciiname":"Mayal Bakhal",
    "gn:country_code":"IN",
    "gn:dem":1238,
    "gn:feature_class":"P",
    "gn:feature_code":"PPL",
    "gn:name":"May\u0101l B\u0101khal",
    "gn:population":0,
    "gn:timezone":"Asia/Kolkata",
    "iso:country":"IN",
    "ks:ks_alt_nam":"May\u0101l B\u0101khal",
    "ks:ks_name":"Mayal Bakhal",
    "ks:ks_pop":97,
    "ks:ks_type":"VILLAGE",
    "name:eng_x_preferred":[
        "Mayal Bakhal"
    ],
    "name:eng_x_variant":[
        "May\u0101l B\u0101khal"
    ],
    "wof:name":"Mayal Bakhal",
    "wof:placetype":"locality",
    "wof:population":97
},
  "geometry": {"coordinates":[79.145607,29.683939],"type":"Point"}
}