{
  "type": "Feature",
  "properties": {
    "gn:admin1_code":"39.0",
    "gn:admin2_code":"64.0",
    "gn:asciiname":"Mayal Bakhal",
    "gn:country_code":"IN",
    "gn:dem":1238,
    "gn:feature_class":"P",
    "gn:feature_code":"PPL",
    "gn:name":"May\u0101l B\u0101khal",
    "gn:population":0,
    "gn:timezone":"Asia/Kolkata",
    "iso:country":"IN",
    "wof:name":"Mayal Bakhal",
    "wof:placetype":"locality"
},
  "geometry": {"coordinates":[79.14718000000001,29.68402],"type":"Point"}
}