{
  "type": "Feature",
  "properties": {
    "iso:country":"IN",
    "ks:ks_name":"Pahadtola",
    "ks:ks_pop":488,
    "ks:ks_type":"HABITATION",
    "name:eng_x_preferred":[
        "Pahadtola"
    ],
    "wof:name":"Pahadtola",
    "wof:placetype":"locality",
    "wof:population":488
},
  "geometry": {"coordinates":[84.862801,21.728795],"type":"Point"}
}