{
  "type": "Feature",
  "properties": {
    "gn:admin1_code":"19.0",
    "gn:admin2_code":"570.0",
    "gn:asciiname":"Gurige",
    "gn:country_code":"IN",
    "gn:dem":715,
    "gn:feature_class":"P",
    "gn:feature_code":"PPL",
    "gn:name":"Gurige",
    "gn:population":0,
    "gn:timezone":"Asia/Kolkata",
    "iso:country":"IN",
    "ks:ks_name":"Gurige",
    "ks:ks_pop":78,
    "ks:ks_type":"HABITATION",
    "name:eng_x_preferred":[
        "Gurige"
    ],
    "wof:name":"Gurige",
    "wof:placetype":"locality",
    "wof:population":78
},
  "geometry": {"coordinates":[75.192894,13.282817],"type":"Point"}
}