{
  "type": "Feature",
  "properties": {
    "gn:admin1_code":"11.0",
    "gn:admin2_code":"029",
    "gn:asciiname":"Basi",
    "gn:country_code":"IN",
    "gn:dem":419,
    "gn:feature_class":"P",
    "gn:feature_code":"PPL",
    "gn:name":"Basi",
    "gn:population":0,
    "gn:timezone":"Asia/Kolkata",
    "iso:country":"IN",
    "name:eng_x_preferred":[
        "Basi"
    ],
    "name:und_x_variant":[
        "B\u0101si"
    ],
    "wof:name":"Basi",
    "wof:placetype":"locality"
},
  "geometry": {"coordinates":[76.15318000000001,31.50252],"type":"Point"}
}