{
  "type": "Feature",
  "properties": {
    "iso:country":"IN",
    "ks:ks_name":"Ahiran Ka Purwa",
    "ks:ks_pop":495,
    "ks:ks_type":"HABITATION",
    "name:eng_x_preferred":[
        "Ahiran Ka Purwa"
    ],
    "wof:name":"Ahiran Ka Purwa",
    "wof:placetype":"locality",
    "wof:population":495
},
  "geometry": {"coordinates":[81.54083,25.50216],"type":"Point"}
}