{
  "type": "Feature",
  "properties": {
    "iso:country":"IN",
    "ks:ks_name":"Honnahatti",
    "ks:ks_pop":70,
    "ks:ks_type":"HABITATION",
    "name:eng_x_preferred":[
        "Honnahatti"
    ],
    "wof:name":"Honnahatti",
    "wof:placetype":"locality",
    "wof:population":70
},
  "geometry": {"coordinates":[75.868064,12.919111],"type":"Point"}
}