{
  "type": "Feature",
  "properties": {
    "iso:country":"IN",
    "ks:ks_name":"Rajbansi Tola",
    "ks:ks_pop":248,
    "ks:ks_type":"HABITATION",
    "name:eng_x_preferred":[
        "Rajbansi Tola"
    ],
    "wof:name":"Rajbansi Tola",
    "wof:placetype":"locality",
    "wof:population":248
},
  "geometry": {"coordinates":[87.702957,26.275125],"type":"Point"}
}