{
  "type": "Feature",
  "properties": {
    "iso:country":"IN",
    "ks:ks_name":"Navi Vasahat Faliya",
    "ks:ks_pop":680,
    "ks:ks_type":"HABITATION",
    "name:eng_x_preferred":[
        "Navi Vasahat Faliya"
    ],
    "wof:name":"Navi Vasahat Faliya",
    "wof:placetype":"locality",
    "wof:population":680
},
  "geometry": {"coordinates":[73.863056,23.034111],"type":"Point"}
}