{
  "type": "Feature",
  "properties": {
    "iso:country":"IN",
    "ks:ks_name":"Chandangar",
    "ks:ks_pop":80,
    "ks:ks_type":"VILLAGE",
    "name:eng_x_preferred":[
        "Chandangar"
    ],
    "wof:name":"Chandangar",
    "wof:placetype":"locality",
    "wof:population":80
},
  "geometry": {"coordinates":[88.131315,24.867616],"type":"Point"}
}