{
  "type": "Feature",
  "properties": {
    "gn:admin1_code":"36",
    "gn:admin2_code":"175.0",
    "gn:asciiname":"Khudaganj",
    "gn:country_code":"IN",
    "gn:dem":114,
    "gn:feature_class":"P",
    "gn:feature_code":"PPL",
    "gn:name":"Khud\u0101ganj",
    "gn:population":0,
    "gn:timezone":"Asia/Kolkata",
    "iso:country":"IN",
    "name:bpy_x_preferred":[
        "\u0996\u09c1\u09a6\u09be\u0997\u099e\u09cd\u099c"
    ],
    "name:ceb_x_preferred":[
        "Khud\u0101ganj"
    ],
    "name:ita_x_preferred":[
        "Khudaganj"
    ],
    "name:mlg_x_preferred":[
        "Khudaganj"
    ],
    "name:msa_x_preferred":[
        "Khudaganj"
    ],
    "name:new_x_preferred":[
        "\u0916\u0941\u0926\u093e\u0917\u091e\u094d\u091c"
    ],
    "name:nld_x_preferred":[
        "Khudaganj"
    ],
    "name:pol_x_preferred":[
        "Khudaganj"
    ],
    "name:por_x_preferred":[
        "Khudaganj"
    ],
    "name:urd_x_preferred":[
        "\u062e\u062f\u0627\u06af\u0646\u062c"
    ],
    "name:vie_x_preferred":[
        "Khudaganj"
    ],
    "name:zho_x_preferred":[
        "\u5e93\u8fbe\u7518\u6770"
    ],
    "wof:name":"Khudaganj",
    "wof:placetype":"locality"
},
  "geometry": {"coordinates":[81.95260999999998,24.97805],"type":"Point"}
}