{
  "type": "Feature",
  "properties": {
    "iso:country":"IN",
    "ks:ks_name":"Pui",
    "ks:ks_pop":139,
    "ks:ks_type":"VILLAGE",
    "name:eng_x_preferred":[
        "Pui"
    ],
    "wof:name":"Pui",
    "wof:placetype":"locality",
    "wof:population":139
},
  "geometry": {"coordinates":[73.26141200000001,18.535676],"type":"Point"}
}