{
  "type": "Feature",
  "properties": {
    "iso:country":"IN",
    "ks:ks_name":"Lathi",
    "ks:ks_pop":386,
    "ks:ks_type":"VILLAGE",
    "name:eng_x_preferred":[
        "Lathi"
    ],
    "wof:name":"Lathi",
    "wof:placetype":"locality",
    "wof:population":386
},
  "geometry": {"coordinates":[80.069581,29.927379],"type":"Point"}
}