{
  "type": "Feature",
  "properties": {
    "gn:admin1_code":"2.0",
    "gn:admin2_code":"554.0",
    "gn:asciiname":"Damodaramaharajupuram",
    "gn:country_code":"IN",
    "gn:dem":206,
    "gn:feature_class":"P",
    "gn:feature_code":"PPL",
    "gn:name":"D\u0101modaramah\u0101r\u0101jupuram",
    "gn:population":0,
    "gn:timezone":"Asia/Kolkata",
    "iso:country":"IN",
    "wof:name":"Damodaramaharajupuram",
    "wof:placetype":"locality"
},
  "geometry": {"coordinates":[79.47289000000001,13.39032],"type":"Point"}
}