{
  "type": "Feature",
  "properties": {
    "iso:country":"IN",
    "ks:ks_name":"Kooraparthivaripalle",
    "ks:ks_pop":59,
    "ks:ks_type":"HABITATION",
    "name:eng_x_preferred":[
        "Kooraparthivaripalle"
    ],
    "wof:name":"Kooraparthivaripalle",
    "wof:placetype":"locality",
    "wof:population":59
},
  "geometry": {"coordinates":[79.05624400000001,13.695901],"type":"Point"}
}