{
  "type": "Feature",
  "properties": {
    "iso:country":"IN",
    "ks:ks_alt_nam":"Vil\u0101chcheri",
    "ks:ks_name":"Vilachcheri",
    "ks:ks_type":"VILLAGE",
    "ks:ks_uagg_main":0,
    "name:eng_x_preferred":[
        "Vilachcheri"
    ],
    "name:eng_x_variant":[
        "Vil\u0101chcheri"
    ],
    "wof:name":"Vilachcheri",
    "wof:placetype":"locality"
},
  "geometry": {"coordinates":[78.06034099999999,9.893685],"type":"Point"}
}