{
  "type": "Feature",
  "properties": {
    "iso:country":"IN",
    "ks:ks_name":"Alubavikothur",
    "ks:ks_pop":196,
    "ks:ks_type":"HABITATION",
    "name:eng_x_preferred":[
        "Alubavikothur"
    ],
    "wof:name":"Alubavikothur",
    "wof:placetype":"locality",
    "wof:population":196
},
  "geometry": {"coordinates":[78.019098,12.999701],"type":"Point"}
}