{
  "type": "Feature",
  "properties": {
    "iso:country":"IN",
    "ks:ks_name":"Khawadkarwadi",
    "ks:ks_pop":369,
    "ks:ks_type":"HABITATION",
    "name:eng_x_preferred":[
        "Khawadkarwadi"
    ],
    "wof:name":"Khawadkarwadi",
    "wof:placetype":"locality",
    "wof:population":369
},
  "geometry": {"coordinates":[73.563056,16.840556],"type":"Point"}
}