{
  "type": "Feature",
  "properties": {
    "gn:admin1_code":"36.0",
    "gn:admin2_code":"183.0",
    "gn:asciiname":"Manahna",
    "gn:country_code":"IN",
    "gn:dem":103,
    "gn:feature_class":"P",
    "gn:feature_code":"PPL",
    "gn:name":"Man\u0101hna",
    "gn:population":0,
    "gn:timezone":"Asia/Kolkata",
    "iso:country":"IN",
    "ks:ks_alt_nam":"Man\u0101hna",
    "ks:ks_name":"Manahna",
    "ks:ks_pop":265,
    "ks:ks_type":"VILLAGE",
    "ks:ks_uagg_main":0,
    "name:eng_x_preferred":[
        "Manahna"
    ],
    "name:eng_x_variant":[
        "Man\u0101hna"
    ],
    "wof:name":"Manahna",
    "wof:placetype":"neighbourhood",
    "wof:population":265
},
  "geometry": {"coordinates":[81.963617,26.900375],"type":"Point"}
}