{
  "type": "Feature",
  "properties": {
    "gn:admin1_code":"34.0",
    "gn:admin2_code":"203.0",
    "gn:asciiname":"Kataha",
    "gn:country_code":"IN",
    "gn:dem":89,
    "gn:feature_class":"P",
    "gn:feature_code":"PPL",
    "gn:name":"Katah\u0101",
    "gn:population":0,
    "gn:timezone":"Asia/Kolkata",
    "iso:country":"IN",
    "ks:ks_name":"Kataha",
    "ks:ks_pop":8495,
    "ks:ks_type":"VILLAGE",
    "name:eng_x_preferred":[
        "Kataha"
    ],
    "wof:name":"Kataha",
    "wof:placetype":"locality",
    "wof:population":8495
},
  "geometry": {"coordinates":[84.117881,26.932107],"type":"Point"}
}