{
  "type": "Feature",
  "properties": {
    "iso:country":"IN",
    "ks:ks_name":"Otiya",
    "ks:ks_pop":1914,
    "ks:ks_type":"VILLAGE",
    "name:eng_x_preferred":[
        "Otiya"
    ],
    "wof:name":"Otiya",
    "wof:placetype":"locality",
    "wof:population":1914
},
  "geometry": {"coordinates":[81.5057,26.484],"type":"Point"}
}