{
  "type": "Feature",
  "properties": {
    "iso:country":"IN",
    "ks:ks_name":"Hatisalbeda",
    "ks:ks_pop":253,
    "ks:ks_type":"VILLAGE",
    "name:eng_x_preferred":[
        "Hatisalbeda"
    ],
    "wof:name":"Hatisalbeda",
    "wof:placetype":"locality",
    "wof:population":253
},
  "geometry": {"coordinates":[86.069125,21.745207],"type":"Point"}
}