{
  "type": "Feature",
  "properties": {
    "iso:country":"IN",
    "name:ben_x_preferred":[
        "\u09a5\u09be\u0987\u0995\u09cd\u0995\u09a6"
    ],
    "name:bpy_x_preferred":[
        "\u09a5\u09be\u0987\u0995\u09cd\u0995\u09a6"
    ],
    "name:chi_x_preferred":[
        "\u6cf0\u514b\u5361\u5fb7"
    ],
    "name:dut_x_preferred":[
        "Thaikkad"
    ],
    "name:eng_x_preferred":[
        "Thaikkad"
    ],
    "name:fre_x_preferred":[
        "Thaikkad"
    ],
    "name:ita_x_preferred":[
        "Thaikkad"
    ],
    "name:may_x_preferred":[
        "Thaikkad"
    ],
    "name:nan_x_preferred":[
        "Thaikkad"
    ],
    "name:por_x_preferred":[
        "Thaikkad"
    ],
    "name:vie_x_preferred":[
        "Thaikkad"
    ],
    "qs:name":"Thaikkad",
    "qs:name_adm0":"India",
    "qs:name_adm1":"Kerala",
    "qs:photos":18,
    "qs:photos_1k":4,
    "qs:photos_9k":1,
    "qs:photos_9r":1,
    "qs:photos_all":18,
    "qs:photos_sr":1,
    "qs:placetype":"Town",
    "qs:pop_sr":"0",
    "wd:wordcount":103,
    "wof:name":"Thaikkad",
    "wof:placetype":"locality"
},
  "geometry": {"coordinates":[76.068443,10.586059],"type":"Point"}
}