{
  "type": "Feature",
  "properties": {
    "iso:country":"IN",
    "ks:ks_name":"Jhitikiara",
    "ks:ks_pop":123,
    "ks:ks_type":"HABITATION",
    "name:eng_x_preferred":[
        "Jhitikiara"
    ],
    "wof:name":"Jhitikiara",
    "wof:placetype":"locality",
    "wof:population":123
},
  "geometry": {"coordinates":[84.771056,22.356418],"type":"Point"}
}