{
  "type": "Feature",
  "properties": {
    "iso:country":"IN",
    "name:eng_x_preferred":[
        "Pimple Saudagar"
    ],
    "wof:name":"Pimple Saudagar",
    "wof:placetype":"neighbourhood"
},
  "geometry": {"coordinates":[73.79738153087636,18.59836840510482],"type":"Point"}
}