{
  "type": "Feature",
  "properties": {
    "iso:country":"IN",
    "name:ara_x_preferred":[
        "\u0628\u064a\u0645\u0628\u0644 \u0633\u0627\u0648\u062f\u0627\u062c\u0627\u0631"
    ],
    "name:ben_bn_x_preferred":[
        "\u09aa\u09bf\u09ae\u09cd\u09aa\u09b2\u09c7 \u09b8\u0993\u09a6\u09be\u0997\u09b0"
    ],
    "name:ben_in_x_preferred":[
        "\u09aa\u09bf\u09ae\u09cd\u09aa\u09b2\u09c7 \u09b8\u0993\u09a6\u09be\u0997\u09b0"
    ],
    "name:eng_x_preferred":[
        "Pimple Saudagar"
    ],
    "name:guj_x_preferred":[
        "\u0aaa\u0abf\u0aae\u0aaa\u0ab2 \u0ab8\u0acc\u0aa6\u0abe\u0a97\u0ab0"
    ],
    "name:hin_x_preferred":[
        "\u092a\u093f\u092e\u094d\u092a\u0932 \u0938\u094c\u0926\u093e\u0917\u0930"
    ],
    "name:kan_x_preferred":[
        "\u0caa\u0cbf\u0c82\u0caa\u0ccd\u0cb2\u0cc6 \u0cb8\u0ccc\u0ca6\u0cbe\u0c97\u0cb0\u0ccd"
    ],
    "name:mal_x_preferred":[
        "\u0d2e\u0d41\u0d16\u0d15\u0d4d\u0d15\u0d41\u0d30\u0d41 \u0d38\u0d57\u0d26\u0d3e\u0d17\u0d7c"
    ],
    "name:mar_x_preferred":[
        "\u092a\u093f\u0902\u092a\u0933\u0947 \u0938\u094c\u0926\u093e\u0917\u0930"
    ],
    "name:pan_x_preferred":[
        "\u0a2a\u0a3f\u0a70\u0a2a\u0a32 \u0a38\u0a4c\u0a26\u0a3e\u0a17\u0a30"
    ],
    "name:tam_x_preferred":[
        "\u0baa\u0bbf\u0bae\u0bcd\u0baa\u0bbf\u0bb3\u0bcd \u0b9a\u0bcc\u0ba4\u0bbe\u0b95\u0bb0\u0bcd"
    ],
    "name:tel_x_preferred":[
        "\u0c2a\u0c3f\u0c02\u0c2a\u0c41\u0c32\u0c4d \u0c38\u0c4c\u0c26\u0c3e\u0c17\u0c30\u0c4d"
    ],
    "name:urd_x_preferred":[
        "\u067e\u0645\u067e\u0644 \u0633\u0648\u062f\u0627\u06af\u0631"
    ],
    "wof:name":"Pimple Saudagar",
    "wof:placetype":"neighbourhood"
},
  "geometry": {"coordinates":[73.79738153087636,18.59836840510482],"type":"Point"}
}