{
  "type": "Feature",
  "properties": {
    "gn:admin1_code":"21.0",
    "gn:admin2_code":"396.0",
    "gn:asciiname":"Opaka",
    "gn:country_code":"IN",
    "gn:dem":469,
    "gn:feature_class":"P",
    "gn:feature_code":"PPL",
    "gn:name":"Opaka",
    "gn:population":0,
    "gn:timezone":"Asia/Kolkata",
    "iso:country":"IN",
    "name:azb_x_preferred":[
        "\u0648\u067e\u0627\u06a9\u0627"
    ],
    "name:bul_x_preferred":[
        "\u041e\u043f\u0430\u043a\u0430"
    ],
    "name:ceb_x_preferred":[
        "Opaka"
    ],
    "name:ckb_x_preferred":[
        "\u0626\u06c6\u067e\u0627\u06a9\u0627"
    ],
    "name:fas_x_preferred":[
        "\u0627\u0648\u067e\u0627\u06a9\u0627"
    ],
    "name:heb_x_preferred":[
        "\u05d0\u05d5\u05e4\u05d0\u05e7\u05d4"
    ],
    "name:kaz_x_preferred":[
        "\u041e\u043f\u0430\u043a\u0430"
    ],
    "name:nld_x_preferred":[
        "Opaka"
    ],
    "name:pol_x_preferred":[
        "Opaka"
    ],
    "name:por_x_preferred":[
        "Opaka"
    ],
    "name:ron_x_preferred":[
        "Opaka"
    ],
    "name:rus_x_preferred":[
        "\u041e\u043f\u0430\u043a\u0430"
    ],
    "name:spa_x_preferred":[
        "Opaka"
    ],
    "name:srp_x_preferred":[
        "\u041e\u043f\u0430\u043a\u0430"
    ],
    "name:tur_x_preferred":[
        "Hac\u0131y\u00fcr\u00fck"
    ],
    "name:ukr_x_preferred":[
        "\u041e\u043f\u0430\u043a\u0430"
    ],
    "name:vie_x_preferred":[
        "Opaka"
    ],
    "name:war_x_preferred":[
        "Opaka"
    ],
    "name:zho_x_preferred":[
        "\u5967\u5e15\u5361"
    ],
    "wof:name":"Opaka",
    "wof:placetype":"locality"
},
  "geometry": {"coordinates":[83.53466999999998,19.11625],"type":"Point"}
}