{
  "type": "Feature",
  "properties": {
    "gn:admin1_code":"36.0",
    "gn:admin2_code":"165.0",
    "gn:asciiname":"Hinauli Diwara",
    "gn:country_code":"IN",
    "gn:dem":121,
    "gn:feature_class":"P",
    "gn:feature_code":"PPL",
    "gn:name":"Hinauli Diw\u0101ra",
    "gn:population":0,
    "gn:timezone":"Asia/Kolkata",
    "iso:country":"IN",
    "ks:ks_name":"Hinnauli Diwara",
    "ks:ks_pop":13,
    "ks:ks_type":"HABITATION",
    "name:eng_x_preferred":[
        "Hinnauli Diwara"
    ],
    "name:eng_x_variant":[
        "Hinauli Diwara"
    ],
    "wof:name":"Hinnauli Diwara",
    "wof:placetype":"locality",
    "wof:population":13
},
  "geometry": {"coordinates":[79.473653,26.392155],"type":"Point"}
}