{
  "type": "Feature",
  "properties": {
    "iso:country":"IN",
    "ks:ks_name":"Kayaradka",
    "ks:ks_pop":210,
    "ks:ks_type":"HABITATION",
    "name:eng_x_preferred":[
        "Kayaradka"
    ],
    "wof:name":"Kayaradka",
    "wof:placetype":"locality",
    "wof:population":210
},
  "geometry": {"coordinates":[75.10892200000001,12.844336],"type":"Point"}
}