{
  "type": "Feature",
  "properties": {
    "iso:country":"IN",
    "ks:ks_name":"Sansarpura",
    "ks:ks_pop":23,
    "ks:ks_type":"VILLAGE",
    "name:eng_x_preferred":[
        "Sansarpura"
    ],
    "wof:name":"Sansarpura",
    "wof:placetype":"locality",
    "wof:population":23
},
  "geometry": {"coordinates":[75.809971,30.097792],"type":"Point"}
}