{
  "type": "Feature",
  "properties": {
    "iso:country":"IN",
    "ks:ks_name":"Kunda Falia",
    "ks:ks_pop":506,
    "ks:ks_type":"HABITATION",
    "name:eng_x_preferred":[
        "Kunda Falia"
    ],
    "wof:name":"Kunda Falia",
    "wof:placetype":"locality",
    "wof:population":506
},
  "geometry": {"coordinates":[73.883028,22.708028],"type":"Point"}
}