{
  "type": "Feature",
  "properties": {
    "iso:country":"IN",
    "ks:ks_name":"Ojhipur",
    "ks:ks_pop":97,
    "ks:ks_type":"VILLAGE",
    "ks:ks_uagg_main":0,
    "name:eng_x_preferred":[
        "Ojhipur"
    ],
    "wof:name":"Ojhipur",
    "wof:placetype":"locality",
    "wof:population":97
},
  "geometry": {"coordinates":[80.64964999999999,27.586351],"type":"Point"}
}