{
  "type": "Feature",
  "properties": {
    "iso:country":"IN",
    "ks:ks_name":"38 PTP",
    "ks:ks_pop":4,
    "ks:ks_type":"VILLAGE",
    "name:eng_x_preferred":[
        "38 PTP"
    ],
    "wof:name":"38 PTP",
    "wof:placetype":"locality",
    "wof:population":4
},
  "geometry": {"coordinates":[74.150419,29.799622],"type":"Point"}
}