{
  "type": "Feature",
  "properties": {
    "iso:country":"IN",
    "ks:ks_alt_nam":"kodakaloor",
    "ks:ks_name":"Kodakaloor",
    "ks:ks_pop":378,
    "ks:ks_type":"HABITATION",
    "name:eng_x_preferred":[
        "Kodakaloor"
    ],
    "wof:name":"Kodakaloor",
    "wof:placetype":"locality",
    "wof:population":378
},
  "geometry": {"coordinates":[75.814745,11.552288],"type":"Point"}
}