{
  "type": "Feature",
  "properties": {
    "iso:country":"IN",
    "ks:ks_name":"Kallampirambu",
    "ks:ks_pop":364,
    "ks:ks_type":"HABITATION",
    "ks:ks_uagg_main":0,
    "name:eng_x_preferred":[
        "Kallampirambu"
    ],
    "wof:name":"Kallampirambu",
    "wof:placetype":"neighbourhood",
    "wof:population":364
},
  "geometry": {"coordinates":[78.17137200000001,9.588071],"type":"Point"}
}