{
  "type": "Feature",
  "properties": {
    "iso:country":"IN",
    "ks:ks_name":"Vadnal",
    "ks:ks_pop":352,
    "ks:ks_type":"VILLAGE",
    "name:eng_x_preferred":[
        "Vadnal"
    ],
    "wof:name":"Vadnal",
    "wof:placetype":"locality",
    "wof:population":352
},
  "geometry": {"coordinates":[73.021145,24.266813],"type":"Point"}
}