{
  "type": "Feature",
  "properties": {
    "iso:country":"IN",
    "ks:ks_name":"Holi Faliya",
    "ks:ks_pop":515,
    "ks:ks_type":"HABITATION",
    "name:eng_x_preferred":[
        "Holi Faliya"
    ],
    "wof:name":"Holi Faliya",
    "wof:placetype":"locality",
    "wof:population":515
},
  "geometry": {"coordinates":[73.95399999999999,23.056194],"type":"Point"}
}