{
  "type": "Feature",
  "properties": {
    "iso:country":"IN",
    "ks:ks_name":"Shantipur",
    "ks:ks_pop":8299,
    "ks:ks_type":"VILLAGE",
    "name:eng_x_preferred":[
        "Shantipur"
    ],
    "wof:name":"Shantipur",
    "wof:placetype":"locality",
    "wof:population":8299
},
  "geometry": {"coordinates":[87.867102,22.405927],"type":"Point"}
}