{
  "type": "Feature",
  "properties": {
    "iso:country":"IN",
    "ks:ks_name":"13 AG",
    "ks:ks_pop":100,
    "ks:ks_type":"VILLAGE",
    "name:eng_x_preferred":[
        "13 AG"
    ],
    "wof:name":"13 AG",
    "wof:placetype":"locality",
    "wof:population":100
},
  "geometry": {"coordinates":[74.504064,29.3238],"type":"Point"}
}