{
  "type": "Feature",
  "properties": {
    "iso:country":"IN",
    "ks:ks_name":"Makkimane",
    "ks:ks_pop":51,
    "ks:ks_type":"HABITATION",
    "name:eng_x_preferred":[
        "Makkimane"
    ],
    "wof:name":"Makkimane",
    "wof:placetype":"locality",
    "wof:population":51
},
  "geometry": {"coordinates":[75.298153,13.337081],"type":"Point"}
}