{
  "type": "Feature",
  "properties": {
    "gn:admin1_code":"35.0",
    "gn:admin2_code":"456",
    "gn:asciiname":"Dhutera",
    "gn:country_code":"IN",
    "gn:dem":479,
    "gn:feature_class":"P",
    "gn:feature_code":"PPL",
    "gn:name":"Dhutera",
    "gn:population":0,
    "gn:timezone":"Asia/Kolkata",
    "iso:country":"IN",
    "wof:name":"Dhutera",
    "wof:placetype":"locality"
},
  "geometry": {"coordinates":[79.88288,22.26047],"type":"Point"}
}