{
  "type": "Feature",
  "properties": {
    "gn:country":"IN",
    "gn:fcode":"PPL",
    "gn:population":34649,
    "iso:country":"IN",
    "name:ceb_x_preferred":[
        "Shik\u0101rpur"
    ],
    "name:eng_x_preferred":[
        "Shikarpur"
    ],
    "name:fas_x_preferred":[
        "\u0634\u06cc\u06a9\u0627\u0631\u067e\u0648\u0631"
    ],
    "name:hin_x_preferred":[
        "\u0936\u093f\u0915\u093e\u0930\u092a\u0941\u0930"
    ],
    "name:ita_x_preferred":[
        "Shikarpur"
    ],
    "name:msa_x_preferred":[
        "Shikarpur"
    ],
    "name:nld_x_preferred":[
        "Shikarpur"
    ],
    "name:ori_x_preferred":[
        "\u0b36\u0b3f\u0b15\u0b3e\u0b30\u0b2a\u0b41\u0b30"
    ],
    "name:pnb_x_preferred":[
        "\u0634\u06a9\u0627\u0631\u067e\u0648\u0631\u060c \u0628\u0644\u0646\u062f\u0634\u06c1\u0631"
    ],
    "name:pnb_x_variant":[
        "\u0634\u06a9\u0627\u0631\u067e\u0648\u0631"
    ],
    "name:pol_x_preferred":[
        "Shikarpur"
    ],
    "name:swe_x_preferred":[
        "Shik\u0101rpur"
    ],
    "name:urd_x_preferred":[
        "\u0634\u06a9\u0627\u0631\u067e\u0648\u0631\u060c \u0628\u0644\u0646\u062f\u0634\u06c1\u0631"
    ],
    "name:urd_x_variant":[
        "\u0634\u06a9\u0627\u0631\u067e\u0648\u0631"
    ],
    "name:vie_x_preferred":[
        "Shikarpur"
    ],
    "qs:name":"Shikarpur",
    "qs:name_adm0":"India",
    "qs:name_adm1":"Haryana",
    "qs:photos_9r":0,
    "qs:photos_sr":0,
    "qs:placetype":"Town",
    "qs:pop_sr":"7",
    "wd:wordcount":71,
    "wof:name":"Shikarpur",
    "wof:placetype":"locality",
    "wof:population":34649
},
  "geometry": {"coordinates":[78.01111,28.28178],"type":"Point"}
}