{
  "type": "Feature",
  "properties": {
    "gn:admin1_code":"2",
    "gn:admin2_code":"544.0",
    "gn:asciiname":"Kommanuru",
    "gn:country_code":"IN",
    "gn:dem":679,
    "gn:feature_class":"P",
    "gn:feature_code":"PPL",
    "gn:name":"Komman\u016bru",
    "gn:population":0,
    "gn:timezone":"Asia/Kolkata",
    "iso:country":"IN",
    "ks:ks_alt_nam":"Komman\u016bru",
    "ks:ks_name":"Kommanuru",
    "ks:ks_type":"VILLAGE",
    "name:eng_x_preferred":[
        "Kommanuru"
    ],
    "name:eng_x_variant":[
        "Komman\u016bru"
    ],
    "wof:name":"Kommanuru",
    "wof:placetype":"locality"
},
  "geometry": {"coordinates":[81.94044700000001,17.804357],"type":"Point"}
}