{
  "type": "Feature",
  "properties": {
    "iso:country":"IN",
    "ks:ks_name":"Jotiyali",
    "ks:ks_pop":311,
    "ks:ks_type":"HABITATION",
    "name:eng_x_preferred":[
        "Jotiyali"
    ],
    "wof:name":"Jotiyali",
    "wof:placetype":"locality",
    "wof:population":311
},
  "geometry": {"coordinates":[72.692933,24.280764],"type":"Point"}
}