{
  "type": "Feature",
  "properties": {
    "iso:country":"IN",
    "ks:ks_name":"Baghabaspur",
    "ks:ks_pop":302,
    "ks:ks_type":"VILLAGE",
    "name:eng_x_preferred":[
        "Baghabaspur"
    ],
    "wof:name":"Baghabaspur",
    "wof:placetype":"locality",
    "wof:population":302
},
  "geometry": {"coordinates":[85.049155,20.999474],"type":"Point"}
}