{
  "type": "Feature",
  "properties": {
    "iso:country":"IN",
    "ks:ks_name":"Hansapur",
    "ks:ks_pop":3493,
    "ks:ks_type":"VILLAGE",
    "name:eng_x_preferred":[
        "Hansapur"
    ],
    "wof:name":"Hansapur",
    "wof:placetype":"locality",
    "wof:population":3493
},
  "geometry": {"coordinates":[72.166387,23.855602],"type":"Point"}
}