{
  "type": "Feature",
  "properties": {
    "iso:country":"IN",
    "ks:ks_name":"Manikapur Kham",
    "ks:ks_pop":0,
    "ks:ks_type":"VILLAGE",
    "name:eng_x_preferred":[
        "Manikapur Kham"
    ],
    "wof:name":"Manikapur Kham",
    "wof:placetype":"locality",
    "wof:population":0
},
  "geometry": {"coordinates":[78.883973,27.896308],"type":"Point"}
}