{
  "type": "Feature",
  "properties": {
    "gn:admin1_code":"35",
    "gn:admin2_code":"448.0",
    "gn:asciiname":"Dudhkachachh",
    "gn:country_code":"IN",
    "gn:dem":307,
    "gn:feature_class":"P",
    "gn:feature_code":"PPL",
    "gn:name":"Dudhkachachh",
    "gn:population":0,
    "gn:timezone":"Asia/Kolkata",
    "iso:country":"IN",
    "wof:name":"Dudhkachachh",
    "wof:placetype":"locality"
},
  "geometry": {"coordinates":[77.21013000000001,22.28741],"type":"Point"}
}