{
  "type": "Feature",
  "properties": {
    "gn:admin1_code":"19.0",
    "gn:admin2_code":"566.0",
    "gn:asciiname":"Kittadahatti",
    "gn:country_code":"IN",
    "gn:dem":717,
    "gn:feature_class":"P",
    "gn:feature_code":"PPL",
    "gn:name":"Kittadahatti",
    "gn:population":0,
    "gn:timezone":"Asia/Kolkata",
    "iso:country":"IN",
    "ks:ks_name":"Kittadahatty",
    "ks:ks_pop":249,
    "ks:ks_type":"HABITATION",
    "name:eng_x_preferred":[
        "Kittadahatty"
    ],
    "name:eng_x_variant":[
        "Kittadahatti"
    ],
    "wof:name":"Kittadahatty",
    "wof:placetype":"locality",
    "wof:population":249
},
  "geometry": {"coordinates":[76.27658599999999,14.282214],"type":"Point"}
}