{
  "type": "Feature",
  "properties": {
    "gn:admin1_code":"19.0",
    "gn:admin2_code":"566.0",
    "gn:asciiname":"Kittadahatti",
    "gn:country_code":"IN",
    "gn:dem":717,
    "gn:feature_class":"P",
    "gn:feature_code":"PPL",
    "gn:name":"Kittadahatti",
    "gn:population":0,
    "gn:timezone":"Asia/Kolkata",
    "iso:country":"IN",
    "wof:name":"Kittadahatti",
    "wof:placetype":"locality"
},
  "geometry": {"coordinates":[76.27436,14.28356],"type":"Point"}
}