{
  "type": "Feature",
  "properties": {
    "iso:country":"IN",
    "ks:ks_name":"Vadakken Vellinezhi",
    "ks:ks_pop":1301,
    "ks:ks_type":"HABITATION",
    "name:eng_x_preferred":[
        "Vadakken Vellinezhi"
    ],
    "wof:name":"Vadakken Vellinezhi",
    "wof:placetype":"locality",
    "wof:population":1301
},
  "geometry": {"coordinates":[76.353548,10.910223],"type":"Point"}
}