{
  "type": "Feature",
  "properties": {
    "gn:admin1_code":"19.0",
    "gn:admin2_code":"568.0",
    "gn:asciiname":"Bintala",
    "gn:country_code":"IN",
    "gn:dem":626,
    "gn:feature_class":"P",
    "gn:feature_code":"PPL",
    "gn:name":"Bintala",
    "gn:population":0,
    "gn:timezone":"Asia/Kolkata",
    "iso:country":"IN",
    "ks:ks_name":"Bintala",
    "ks:ks_type":"VILLAGE",
    "name:eng_x_preferred":[
        "Bintala"
    ],
    "wof:name":"Bintala",
    "wof:placetype":"locality"
},
  "geometry": {"coordinates":[75.205112,13.687372],"type":"Point"}
}