{
  "type": "Feature",
  "properties": {
    "iso:country":"IN",
    "ks:ks_name":"Kottampallam",
    "ks:ks_pop":316,
    "ks:ks_type":"HABITATION",
    "name:eng_x_preferred":[
        "Kottampallam"
    ],
    "wof:name":"Kottampallam",
    "wof:placetype":"locality",
    "wof:population":316
},
  "geometry": {"coordinates":[77.885082,11.952201],"type":"Point"}
}