{
  "type": "Feature",
  "properties": {
    "iso:country":"IN",
    "ks:ks_name":"Bairipur",
    "ks:ks_pop":859,
    "ks:ks_type":"VILLAGE",
    "ks:ks_uagg_main":0,
    "name:eng_x_preferred":[
        "Bairipur"
    ],
    "wof:name":"Bairipur",
    "wof:placetype":"neighbourhood",
    "wof:population":859
},
  "geometry": {"coordinates":[85.973843,19.910498],"type":"Point"}
}