{
  "type": "Feature",
  "properties": {
    "iso:country":"IN",
    "ks:ks_alt_nam":"Tipuk T.E. 100 Fs.",
    "ks:ks_name":"Tipuk T.e. 100 Fs.",
    "ks:ks_pop":317,
    "ks:ks_type":"HABITATION",
    "name:eng_x_preferred":[
        "Tipuk T.e. 100 Fs."
    ],
    "wof:name":"Tipuk T.e. 100 Fs.",
    "wof:placetype":"locality",
    "wof:population":317
},
  "geometry": {"coordinates":[95.536631,27.625272],"type":"Point"}
}