{
  "type": "Feature",
  "properties": {
    "iso:country":"IN",
    "ks:ks_name":"Morafalia Gadria",
    "ks:ks_pop":672,
    "ks:ks_type":"HABITATION",
    "name:eng_x_preferred":[
        "Morafalia Gadria"
    ],
    "wof:name":"Morafalia Gadria",
    "wof:placetype":"locality",
    "wof:population":672
},
  "geometry": {"coordinates":[73.009028,20.555083],"type":"Point"}
}