{
  "type": "Feature",
  "properties": {
    "iso:country":"IN",
    "ks:ks_name":"Pungankulam",
    "ks:ks_pop":191,
    "ks:ks_type":"HABITATION",
    "name:eng_x_preferred":[
        "Pungankulam"
    ],
    "wof:name":"Pungankulam",
    "wof:placetype":"locality",
    "wof:population":191
},
  "geometry": {"coordinates":[78.251958,10.352421],"type":"Point"}
}