{
  "type": "Feature",
  "properties": {
    "iso:country":"IN",
    "ks:ks_name":"Kodi",
    "ks:ks_pop":50,
    "ks:ks_type":"HABITATION",
    "name:eng_x_preferred":[
        "Kodi"
    ],
    "wof:name":"Kodi",
    "wof:placetype":"locality",
    "wof:population":50
},
  "geometry": {"coordinates":[75.5125,12.371111],"type":"Point"}
}