{
  "type": "Feature",
  "properties": {
    "iso:country":"IN",
    "ks:ks_alt_nam":"Kailigunth Shri Poornagiri_Poorangiri Mafi",
    "ks:ks_name":"Kailigunth Shri Poornagiri_poorangiri Mafi",
    "ks:ks_pop":92,
    "ks:ks_type":"HABITATION",
    "name:eng_x_preferred":[
        "Kailigunth Shri Poornagiri_poorangiri Mafi"
    ],
    "wof:name":"Kailigunth Shri Poornagiri_poorangiri Mafi",
    "wof:placetype":"locality",
    "wof:population":92
},
  "geometry": {"coordinates":[80.188784,29.154568],"type":"Point"}
}