{
  "type": "Feature",
  "properties": {
    "iso:country":"IN",
    "ks:ks_name":"Jumman Purwa",
    "ks:ks_pop":109,
    "ks:ks_type":"HABITATION",
    "name:eng_x_preferred":[
        "Jumman Purwa"
    ],
    "wof:name":"Jumman Purwa",
    "wof:placetype":"locality",
    "wof:population":109
},
  "geometry": {"coordinates":[82.19151599999999,27.287979],"type":"Point"}
}