{
  "type": "Feature",
  "properties": {
    "gn:admin1_code":"36",
    "gn:admin2_code":"154.0",
    "gn:asciiname":"Panchampur",
    "gn:country_code":"IN",
    "gn:dem":130,
    "gn:feature_class":"P",
    "gn:feature_code":"PPL",
    "gn:name":"Panchampur",
    "gn:population":0,
    "gn:timezone":"Asia/Kolkata",
    "iso:country":"IN",
    "ks:ks_name":"Panchampurwa",
    "ks:ks_pop":30,
    "ks:ks_type":"HABITATION",
    "name:eng_x_preferred":[
        "Panchampurwa"
    ],
    "name:eng_x_variant":[
        "Panchampur"
    ],
    "wof:name":"Panchampurwa",
    "wof:placetype":"locality",
    "wof:population":30
},
  "geometry": {"coordinates":[80.779106,27.304495],"type":"Point"}
}