{
  "type": "Feature",
  "properties": {
    "iso:country":"IN",
    "ks:ks_name":"Sehnaj Pura",
    "ks:ks_pop":344,
    "ks:ks_type":"VILLAGE",
    "name:eng_x_preferred":[
        "Sehnaj Pura"
    ],
    "wof:name":"Sehnaj Pura",
    "wof:placetype":"locality",
    "wof:population":344
},
  "geometry": {"coordinates":[75.86821399999999,21.882329],"type":"Point"}
}