{
  "type": "Feature",
  "properties": {
    "gn:admin1_code":"36.0",
    "gn:admin2_code":"165",
    "gn:asciiname":"Ramhetpura",
    "gn:country_code":"IN",
    "gn:dem":147,
    "gn:feature_class":"P",
    "gn:feature_code":"PPL",
    "gn:name":"R\u0101mhetpura",
    "gn:population":0,
    "gn:timezone":"Asia/Kolkata",
    "iso:country":"IN",
    "ks:ks_name":"Ramhetpura",
    "ks:ks_pop":1047,
    "ks:ks_type":"HABITATION",
    "name:eng_x_preferred":[
        "Ramhetpura"
    ],
    "wof:name":"Ramhetpura",
    "wof:placetype":"locality",
    "wof:population":1047
},
  "geometry": {"coordinates":[79.197171,26.290499],"type":"Point"}
}