{
  "type": "Feature",
  "properties": {
    "gn:admin1_code":"2",
    "gn:admin2_code":"548.0",
    "gn:asciiname":"Peddivaripalem",
    "gn:country_code":"IN",
    "gn:dem":15,
    "gn:feature_class":"P",
    "gn:feature_code":"PPL",
    "gn:name":"Peddiv\u0101rip\u0101lem",
    "gn:population":0,
    "gn:timezone":"Asia/Kolkata",
    "iso:country":"IN",
    "wof:name":"Peddivaripalem",
    "wof:placetype":"locality"
},
  "geometry": {"coordinates":[80.36433000000002,16.0586],"type":"Point"}
}