{
  "type": "Feature",
  "properties": {
    "iso:country":"IN",
    "ks:ks_name":"Khairasol",
    "ks:ks_pop":0,
    "ks:ks_type":"VILLAGE",
    "name:eng_x_preferred":[
        "Khairasol"
    ],
    "wof:name":"Khairasol",
    "wof:placetype":"locality",
    "wof:population":0
},
  "geometry": {"coordinates":[87.677188,25.160195],"type":"Point"}
}