{
  "type": "Feature",
  "properties": {
    "iso:country":"IN",
    "ks:ks_name":"Antras",
    "ks:ks_pop":239,
    "ks:ks_type":"VILLAGE",
    "name:eng_x_preferred":[
        "Antras"
    ],
    "wof:name":"Antras",
    "wof:placetype":"locality",
    "wof:population":239
},
  "geometry": {"coordinates":[73.96033300000001,21.899528],"type":"Point"}
}