{
  "type": "Feature",
  "properties": {
    "iso:country":"IN",
    "ks:ks_name":"Rejarguda",
    "ks:ks_pop":61,
    "ks:ks_type":"HABITATION",
    "name:eng_x_preferred":[
        "Rejarguda"
    ],
    "wof:name":"Rejarguda",
    "wof:placetype":"locality",
    "wof:population":61
},
  "geometry": {"coordinates":[81.811612,18.371615],"type":"Point"}
}