{
  "type": "Feature",
  "properties": {
    "iso:country":"IN",
    "ks:ks_name":"Dhanwani Mafi",
    "ks:ks_pop":1047,
    "ks:ks_type":"VILLAGE",
    "name:eng_x_preferred":[
        "Dhanwani Mafi"
    ],
    "wof:name":"Dhanwani Mafi",
    "wof:placetype":"locality",
    "wof:population":1047
},
  "geometry": {"coordinates":[76.698199,22.203218],"type":"Point"}
}