{
  "type": "Feature",
  "properties": {
    "gn:admin1_code":"19.0",
    "gn:admin2_code":"581.0",
    "gn:asciiname":"Mel Yayilur",
    "gn:country_code":"IN",
    "gn:dem":798,
    "gn:feature_class":"P",
    "gn:feature_code":"PPL",
    "gn:name":"Mel Y\u0101yil\u016br",
    "gn:population":0,
    "gn:timezone":"Asia/Kolkata",
    "iso:country":"IN",
    "wof:name":"Mel Yayilur",
    "wof:placetype":"locality"
},
  "geometry": {"coordinates":[78.40651,13.07437],"type":"Point"}
}