{
  "type": "Feature",
  "properties": {
    "gn:admin1_code":"34",
    "gn:admin2_code":"234.0",
    "gn:asciiname":"Isharpura",
    "gn:country_code":"IN",
    "gn:dem":95,
    "gn:feature_class":"P",
    "gn:feature_code":"PPL",
    "gn:name":"Isharpura",
    "gn:population":0,
    "gn:timezone":"Asia/Kolkata",
    "iso:country":"IN",
    "ks:ks_name":"Isharpura",
    "ks:ks_type":"VILLAGE",
    "name:eng_x_preferred":[
        "Isharpura"
    ],
    "wof:name":"Isharpura",
    "wof:placetype":"locality"
},
  "geometry": {"coordinates":[83.908305,24.941133],"type":"Point"}
}