{
  "type": "Feature",
  "properties": {
    "iso:country":"IN",
    "ks:ks_name":"Kundal",
    "ks:ks_pop":479,
    "ks:ks_type":"VILLAGE",
    "name:eng_x_preferred":[
        "Kundal"
    ],
    "wof:name":"Kundal",
    "wof:placetype":"locality",
    "wof:population":479
},
  "geometry": {"coordinates":[74.54288699999999,23.316686],"type":"Point"}
}