{
  "type": "Feature",
  "properties": {
    "iso:country":"IN",
    "ks:ks_name":"Teli Bhitta",
    "ks:ks_pop":166,
    "ks:ks_type":"HABITATION",
    "name:eng_x_preferred":[
        "Teli Bhitta"
    ],
    "wof:name":"Teli Bhitta",
    "wof:placetype":"locality",
    "wof:population":166
},
  "geometry": {"coordinates":[87.90195199999999,26.428557],"type":"Point"}
}