{
  "type": "Feature",
  "properties": {
    "gn:country":"IN",
    "gn:fcode":"PPL",
    "gn:population":39124,
    "iso:country":"IN",
    "name:bpy_x_preferred":[
        "\u0986\u09ae\u09be\u09a6\u09b2\u09be\u09f1\u09b2\u09b8\u09be"
    ],
    "name:ceb_x_preferred":[
        "Amud\u0101lavalasa"
    ],
    "name:eng_x_preferred":[
        "Amudalavalasa"
    ],
    "name:fas_x_preferred":[
        "\u0627\u0645\u0648\u062f\u0627\u0644\u0627\u0648\u0627\u0644\u0627\u0633\u0627"
    ],
    "name:ita_x_preferred":[
        "Amadalavalasa"
    ],
    "name:min_x_preferred":[
        "Amadalavalasa"
    ],
    "name:msa_x_preferred":[
        "Amadalavalasa"
    ],
    "name:nan_x_preferred":[
        "Amadalavalasa"
    ],
    "name:new_x_preferred":[
        "\u0905\u092e\u0926\u0932\u092d\u0932\u0938\u093e"
    ],
    "name:nld_x_preferred":[
        "Amadalavalasa"
    ],
    "name:pnb_x_preferred":[
        "\u0627\u0645\u0648\u062f\u0627\u0644\u0627\u0648\u0627\u0644\u0627\u0633\u0627"
    ],
    "name:por_x_preferred":[
        "Amadalavalasa"
    ],
    "name:swe_x_preferred":[
        "Amud\u0101lavalasa"
    ],
    "name:tel_x_colloquial":[
        "\u0c06\u0c2e\u0c41\u0c26\u0c3e\u0c32\u0c35\u0c32\u0c38"
    ],
    "name:tel_x_historical":[
        "\u0c06\u0c2e\u0c41\u0c26\u0c3e\u0c32\u0c35\u0c32\u0c38"
    ],
    "name:tel_x_preferred":[
        "\u0c06\u0c2e\u0c41\u0c26\u0c3e\u0c32\u0c35\u0c32\u0c38"
    ],
    "name:tel_x_variant":[
        "\u0c06\u0c2e\u0c26\u0c3e\u0c32\u0c35\u0c32\u0c38"
    ],
    "name:vie_x_preferred":[
        "Amadalavalasa"
    ],
    "name:zho_x_preferred":[
        "\u963f\u9a6c\u8fbe\u62c9\u74e6\u62c9\u8428"
    ],
    "qs:name":"Ramuduvalasa",
    "qs:name_adm0":"India",
    "qs:name_adm1":"Andhra Pradesh",
    "qs:photos_9r":0,
    "qs:photos_sr":0,
    "qs:placetype":"Town",
    "qs:pop_sr":"7",
    "wof:name":"Ramuduvalasa",
    "wof:placetype":"locality",
    "wof:population":39124
},
  "geometry": {"coordinates":[83.90243,18.41062],"type":"Point"}
}