{
  "type": "Feature",
  "properties": {
    "gn:admin1_code":"23",
    "gn:admin2_code":"51.0",
    "gn:asciiname":"Nawlakha",
    "gn:country_code":"IN",
    "gn:dem":283,
    "gn:feature_class":"P",
    "gn:feature_code":"PPL",
    "gn:name":"Nawlakha",
    "gn:population":0,
    "gn:timezone":"Asia/Kolkata",
    "iso:country":"IN",
    "ks:ks_name":"Naulakha",
    "ks:ks_pop":148,
    "ks:ks_type":"VILLAGE",
    "name:eng_x_preferred":[
        "Naulakha"
    ],
    "name:eng_x_variant":[
        "Nawlakha"
    ],
    "wof:name":"Naulakha",
    "wof:placetype":"locality",
    "wof:population":148
},
  "geometry": {"coordinates":[76.565781,31.160275],"type":"Point"}
}