{
  "type": "Feature",
  "properties": {
    "gn:admin1_code":"37",
    "gn:admin2_code":"413.0",
    "gn:asciiname":"Chingnar",
    "gn:country_code":"IN",
    "gn:dem":408,
    "gn:feature_class":"P",
    "gn:feature_code":"PPL",
    "gn:name":"Chingn\u0101r",
    "gn:population":0,
    "gn:timezone":"Asia/Kolkata",
    "iso:country":"IN",
    "ks:ks_alt_nam":"Chingn\u0101r",
    "ks:ks_name":"Chingnar",
    "ks:ks_type":"VILLAGE",
    "name:eng_x_preferred":[
        "Chingnar"
    ],
    "name:eng_x_variant":[
        "Chingn\u0101r"
    ],
    "wof:name":"Chingnar",
    "wof:placetype":"locality"
},
  "geometry": {"coordinates":[81.214681,20.017798],"type":"Point"}
}