{
  "type": "Feature",
  "properties": {
    "gn:admin1_code":"34.0",
    "gn:admin2_code":"203.0",
    "gn:asciiname":"Meghwal",
    "gn:country_code":"IN",
    "gn:dem":116,
    "gn:feature_class":"P",
    "gn:feature_code":"PPL",
    "gn:name":"Meghwal",
    "gn:population":0,
    "gn:timezone":"Asia/Kolkata",
    "iso:country":"IN",
    "name:hin_x_preferred":[
        "\u092e\u0947\u0918\u0935\u093e\u0932"
    ],
    "name:snd_x_preferred":[
        "\u0645\u064a\u0646\u06af\u0647\u0648\u0627\u0699"
    ],
    "wof:name":"Meghwal",
    "wof:placetype":"locality"
},
  "geometry": {"coordinates":[84.34841999999998,27.24146],"type":"Point"}
}