{
  "type": "Feature",
  "properties": {
    "gn:admin1_code":"19.0",
    "gn:admin2_code":"581.0",
    "gn:asciiname":"Achattanhalli",
    "gn:country_code":"IN",
    "gn:dem":891,
    "gn:feature_class":"P",
    "gn:feature_code":"PPL",
    "gn:name":"Achattanhalli",
    "gn:population":0,
    "gn:timezone":"Asia/Kolkata",
    "iso:country":"IN",
    "ks:ks_name":"Achatnahalli",
    "ks:ks_pop":457,
    "ks:ks_type":"VILLAGE",
    "ks:ks_uagg_main":0,
    "name:eng_x_preferred":[
        "Achatnahalli"
    ],
    "wof:name":"Achatnahalli",
    "wof:placetype":"neighbourhood",
    "wof:population":457
},
  "geometry": {"coordinates":[77.991838,13.104967],"type":"Point"}
}