{
  "type": "Feature",
  "properties": {
    "iso:country":"IN",
    "ks:ks_alt_nam":"DAKSHIN PAITHAPARA N",
    "ks:ks_name":"Dakshin Paithapara N",
    "ks:ks_pop":451,
    "ks:ks_type":"HABITATION",
    "name:eng_x_preferred":[
        "Dakshin Paithapara N"
    ],
    "wof:name":"Dakshin Paithapara N",
    "wof:placetype":"locality",
    "wof:population":451
},
  "geometry": {"coordinates":[89.289894,26.541392],"type":"Point"}
}