{
  "type": "Feature",
  "properties": {
    "gn:admin1_code":"19.0",
    "gn:admin2_code":"577.0",
    "gn:asciiname":"Anamala",
    "gn:country_code":"IN",
    "gn:dem":708,
    "gn:feature_class":"P",
    "gn:feature_code":"PPL",
    "gn:name":"An\u0101m\u0101la",
    "gn:population":0,
    "gn:timezone":"Asia/Kolkata",
    "iso:country":"IN",
    "ks:ks_name":"Anemala",
    "ks:ks_pop":776,
    "ks:ks_type":"VILLAGE",
    "name:eng_x_preferred":[
        "Anemala"
    ],
    "name:eng_x_variant":[
        "Anamala"
    ],
    "wof:name":"Anemala",
    "wof:placetype":"locality",
    "wof:population":776
},
  "geometry": {"coordinates":[76.16,11.87194],"type":"Point"}
}