{
  "type": "Feature",
  "properties": {
    "iso:country":"IN",
    "ks:ks_name":"Uttar Chhangong",
    "ks:ks_pop":585,
    "ks:ks_type":"VILLAGE",
    "name:eng_x_preferred":[
        "Uttar Chhangong"
    ],
    "wof:name":"Uttar Chhangong",
    "wof:placetype":"locality",
    "wof:population":585
},
  "geometry": {"coordinates":[91.61359899999999,23.644031],"type":"Point"}
}