{
  "type": "Feature",
  "properties": {
    "gn:admin1_code":"11",
    "gn:admin2_code":"27.0",
    "gn:asciiname":"Alag",
    "gn:country_code":"IN",
    "gn:dem":1196,
    "gn:feature_class":"P",
    "gn:feature_code":"PPL",
    "gn:name":"Alag",
    "gn:population":0,
    "gn:timezone":"Asia/Kolkata",
    "iso:country":"IN",
    "name:ben_x_preferred":[
        "\u0986\u09b2\u09be\u0997"
    ],
    "name:deu_x_preferred":[
        "Alag"
    ],
    "name:fas_x_preferred":[
        "\u0645\u062a\u0641\u0627\u0648\u062a"
    ],
    "name:fra_x_preferred":[
        "Alag"
    ],
    "name:ind_x_preferred":[
        "Alag"
    ],
    "name:ita_x_preferred":[
        "Alag"
    ],
    "name:new_x_preferred":[
        "\u0905\u0932\u0917"
    ],
    "name:pol_x_preferred":[
        "Alag"
    ],
    "wof:name":"Alag",
    "wof:placetype":"locality"
},
  "geometry": {"coordinates":[76.86273,31.79509],"type":"Point"}
}