{
  "type": "Feature",
  "properties": {
    "iso:country":"IN",
    "ks:ks_alt_nam":"Govinda camp",
    "ks:ks_name":"Govinda Camp",
    "ks:ks_pop":217,
    "ks:ks_type":"HABITATION",
    "name:eng_x_preferred":[
        "Govinda Camp"
    ],
    "wof:name":"Govinda Camp",
    "wof:placetype":"locality",
    "wof:population":217
},
  "geometry": {"coordinates":[76.647808,15.440677],"type":"Point"}
}