{
  "type": "Feature",
  "properties": {
    "iso:country":"IN",
    "ks:ks_name":"Bambarwadi",
    "ks:ks_pop":171,
    "ks:ks_type":"HABITATION",
    "name:eng_x_preferred":[
        "Bambarwadi"
    ],
    "wof:name":"Bambarwadi",
    "wof:placetype":"locality",
    "wof:population":171
},
  "geometry": {"coordinates":[73.73755,16.47437],"type":"Point"}
}