{
  "type": "Feature",
  "properties": {
    "iso:country":"IN",
    "ks:ks_name":"Agawali",
    "ks:ks_pop":553,
    "ks:ks_type":"VILLAGE",
    "name:eng_x_preferred":[
        "Agawali"
    ],
    "wof:name":"Agawali",
    "wof:placetype":"locality",
    "wof:population":553
},
  "geometry": {"coordinates":[76.553967,27.132664],"type":"Point"}
}