{
  "type": "Feature",
  "properties": {
    "iso:country":"IN",
    "ks:ks_alt_nam":"15 GM",
    "ks:ks_name":"15 Gm",
    "ks:ks_pop":66,
    "ks:ks_type":"HABITATION",
    "name:eng_x_preferred":[
        "15 Gm"
    ],
    "wof:name":"15 Gm",
    "wof:placetype":"locality",
    "wof:population":66
},
  "geometry": {"coordinates":[73.438333,29.073056],"type":"Point"}
}