{
  "type": "Feature",
  "properties": {
    "gn:admin1_code":"21",
    "gn:admin2_code":"399.0",
    "gn:asciiname":"Aringiguda",
    "gn:country_code":"IN",
    "gn:dem":263,
    "gn:feature_class":"P",
    "gn:feature_code":"PPL",
    "gn:name":"Aringiguda",
    "gn:population":0,
    "gn:timezone":"Asia/Kolkata",
    "iso:country":"IN",
    "wof:name":"Aringiguda",
    "wof:placetype":"locality"
},
  "geometry": {"coordinates":[82.01900999999999,18.45673],"type":"Point"}
}