{
  "type": "Feature",
  "properties": {
    "iso:country":"IN",
    "ks:ks_name":"Pathadi Jn",
    "ks:ks_pop":478,
    "ks:ks_type":"HABITATION",
    "name:eng_x_preferred":[
        "Pathadi Jn"
    ],
    "wof:name":"Pathadi Jn",
    "wof:placetype":"neighbourhood",
    "wof:population":478
},
  "geometry": {"coordinates":[76.76054600000001,9.017016],"type":"Point"}
}