{
  "type": "Feature",
  "properties": {
    "iso:country":"IN",
    "ks:ks_name":"Devitori",
    "ks:ks_pop":738,
    "ks:ks_type":"VILLAGE",
    "name:eng_x_preferred":[
        "Devitori"
    ],
    "wof:name":"Devitori",
    "wof:placetype":"locality",
    "wof:population":738
},
  "geometry": {"coordinates":[77.580566,24.102802],"type":"Point"}
}