{
  "type": "Feature",
  "properties": {
    "iso:country":"IN",
    "ks:ks_alt_nam":"Salig purwa",
    "ks:ks_name":"Salig Purwa",
    "ks:ks_pop":271,
    "ks:ks_type":"HABITATION",
    "ks:ks_uagg_main":0,
    "name:eng_x_preferred":[
        "Salig Purwa"
    ],
    "wof:name":"Salig Purwa",
    "wof:placetype":"neighbourhood",
    "wof:population":271
},
  "geometry": {"coordinates":[81.42800800000001,27.973778],"type":"Point"}
}