{
  "type": "Feature",
  "properties": {
    "iso:country":"IN",
    "ks:ks_name":"Sunehra",
    "ks:ks_pop":8125,
    "ks:ks_type":"VILLAGE",
    "ks:ks_uagg_main":1,
    "name:eng_x_preferred":[
        "Sunehra"
    ],
    "wof:name":"Sunehra",
    "wof:placetype":"neighbourhood",
    "wof:population":8125
},
  "geometry": {"coordinates":[77.871503,29.868271],"type":"Point"}
}