{
  "type": "Feature",
  "properties": {
    "gn:admin1_code":"36",
    "gn:admin2_code":"163.0",
    "gn:asciiname":"Arsun",
    "gn:country_code":"IN",
    "gn:dem":138,
    "gn:feature_class":"P",
    "gn:feature_code":"PPL",
    "gn:name":"Arsun",
    "gn:population":0,
    "gn:timezone":"Asia/Kolkata",
    "iso:country":"IN",
    "name:ceb_x_preferred":[
        "\u0100rs\u016bn"
    ],
    "name:fas_x_preferred":[
        "\u0627\u0631\u0633\u0648\u0646"
    ],
    "name:msa_x_preferred":[
        "Arsun"
    ],
    "name:swe_x_preferred":[
        "\u0100rs\u016bn"
    ],
    "wof:name":"Arsun",
    "wof:placetype":"locality"
},
  "geometry": {"coordinates":[79.54592,26.30025],"type":"Point"}
}