{
  "type": "Feature",
  "properties": {
    "iso:country":"IN",
    "ks:ks_alt_nam":"Madam ADC",
    "ks:ks_name":"Madam Adc",
    "ks:ks_pop":112,
    "ks:ks_type":"HABITATION",
    "ks:ks_uagg_main":0,
    "name:eng_x_preferred":[
        "Madam Adc"
    ],
    "wof:name":"Madam Adc",
    "wof:placetype":"neighbourhood",
    "wof:population":112
},
  "geometry": {"coordinates":[79.60406500000001,12.38682],"type":"Point"}
}