{
  "type": "Feature",
  "properties": {
    "gn:admin1_code":"19.0",
    "gn:admin2_code":"568.0",
    "gn:asciiname":"Melina Sampalli",
    "gn:country_code":"IN",
    "gn:dem":595,
    "gn:feature_class":"P",
    "gn:feature_code":"PPL",
    "gn:name":"Melina Sampalli",
    "gn:population":0,
    "gn:timezone":"Asia/Kolkata",
    "iso:country":"IN",
    "ks:ks_name":"Melina Sampalli",
    "ks:ks_pop":470,
    "ks:ks_type":"VILLAGE",
    "name:eng_x_preferred":[
        "Melina Sampalli"
    ],
    "wof:name":"Melina Sampalli",
    "wof:placetype":"locality",
    "wof:population":470
},
  "geometry": {"coordinates":[75.090121,14.007023],"type":"Point"}
}