{
  "type": "Feature",
  "properties": {
    "iso:country":"IN",
    "ks:ks_name":"Jualibhanga",
    "ks:ks_pop":434,
    "ks:ks_type":"VILLAGE",
    "name:eng_x_preferred":[
        "Jualibhanga"
    ],
    "wof:name":"Jualibhanga",
    "wof:placetype":"locality",
    "wof:population":434
},
  "geometry": {"coordinates":[86.919318,21.780143],"type":"Point"}
}