{
  "type": "Feature",
  "properties": {
    "iso:country":"IN",
    "ks:ks_name":"Bahrampur",
    "ks:ks_pop":250,
    "ks:ks_type":"VILLAGE",
    "name:eng_x_preferred":[
        "Bahrampur"
    ],
    "wof:name":"Bahrampur",
    "wof:placetype":"locality",
    "wof:population":250
},
  "geometry": {"coordinates":[76.133528,27.471436],"type":"Point"}
}