{
  "type": "Feature",
  "properties": {
    "iso:country":"IN",
    "ks:ks_name":"Arazi Nainha",
    "ks:ks_pop":497,
    "ks:ks_type":"VILLAGE",
    "name:eng_x_preferred":[
        "Arazi Nainha"
    ],
    "wof:name":"Arazi Nainha",
    "wof:placetype":"locality",
    "wof:population":497
},
  "geometry": {"coordinates":[85.293768,25.74912],"type":"Point"}
}