{
  "type": "Feature",
  "properties": {
    "gn:country":"IN",
    "gn:fcode":"PPL",
    "gn:pop":56110,
    "iso:country":"IN",
    "name:bpy_x_preferred":[
        "\u0993\u09ac\u09b0\u09be"
    ],
    "name:deu_x_preferred":[
        "Obra"
    ],
    "name:eng_x_preferred":[
        "Obra"
    ],
    "name:hin_x_preferred":[
        "\u0913\u092c\u0930\u093e"
    ],
    "name:ita_x_preferred":[
        "Obra"
    ],
    "name:nan_x_preferred":[
        "Obra"
    ],
    "name:nld_x_preferred":[
        "Obra"
    ],
    "name:ori_x_preferred":[
        "\u0b13\u0b2c\u0b4d\u0b30\u0b3e"
    ],
    "name:pnb_x_preferred":[
        "\u0627\u0648\u0628\u0631\u0627\u060c \u0627\u062a\u0631\u067e\u0631\u062f\u06cc\u0634"
    ],
    "name:pol_x_preferred":[
        "Obra"
    ],
    "name:swe_x_preferred":[
        "Obra"
    ],
    "name:urd_x_preferred":[
        "\u0627\u0648\u0628\u0631\u0627\u060c \u0627\u062a\u0631\u067e\u0631\u062f\u06cc\u0634"
    ],
    "qs:name":"Obra",
    "qs:photos_9r":0,
    "qs:photos_sr":0,
    "qs:pop_sr":"8",
    "wd:wordcount":117,
    "wof:name":"Obra",
    "wof:placetype":"locality",
    "wof:population":56110
},
  "geometry": {"coordinates":[82.9859,24.41656],"type":"Point"}
}