{
  "type": "Feature",
  "properties": {
    "gn:admin1_code":"19.0",
    "gn:admin2_code":"575.0",
    "gn:asciiname":"Aikala",
    "gn:country_code":"IN",
    "gn:dem":74,
    "gn:feature_class":"P",
    "gn:feature_code":"PPL",
    "gn:name":"Aikala",
    "gn:population":0,
    "gn:timezone":"Asia/Kolkata",
    "iso:country":"IN",
    "name:fas_x_preferred":[
        "\u0627\u06cc\u06a9\u0627\u0644\u0627"
    ],
    "wof:name":"Aikala",
    "wof:placetype":"locality"
},
  "geometry": {"coordinates":[74.86078000000001,13.07471],"type":"Point"}
}