{
  "type": "Feature",
  "properties": {
    "gn:admin1_code":"34.0",
    "gn:admin2_code":"203.0",
    "gn:asciiname":"Matia",
    "gn:country_code":"IN",
    "gn:dem":74,
    "gn:feature_class":"P",
    "gn:feature_code":"PPL",
    "gn:name":"Mati\u0101",
    "gn:population":0,
    "gn:timezone":"Asia/Kolkata",
    "iso:country":"IN",
    "name:ceb_x_preferred":[
        "Matia"
    ],
    "name:swe_x_preferred":[
        "Matia"
    ],
    "wof:name":"Matia",
    "wof:placetype":"neighbourhood"
},
  "geometry": {"coordinates":[84.52885000000001,26.6654],"type":"Point"}
}