{
  "type": "Feature",
  "properties": {
    "iso:country":"IN",
    "ks:ks_name":"Baghorgaon",
    "ks:ks_pop":70,
    "ks:ks_type":"HABITATION",
    "ks:ks_uagg_main":0,
    "name:eng_x_preferred":[
        "Baghorgaon"
    ],
    "wof:name":"Baghorgaon",
    "wof:placetype":"neighbourhood",
    "wof:population":70
},
  "geometry": {"coordinates":[94.056135,26.64828],"type":"Point"}
}