{
  "type": "Feature",
  "properties": {
    "iso:country":"IN",
    "ks:ks_name":"Bariarpur",
    "ks:ks_pop":67,
    "ks:ks_type":"VILLAGE",
    "name:eng_x_preferred":[
        "Bariarpur"
    ],
    "wof:name":"Bariarpur",
    "wof:placetype":"locality",
    "wof:population":67
},
  "geometry": {"coordinates":[85.31394299999999,26.18498],"type":"Point"}
}