{
  "type": "Feature",
  "properties": {
    "gn:admin1_code":"11",
    "gn:admin2_code":"23.0",
    "gn:asciiname":"Julas",
    "gn:country_code":"IN",
    "gn:dem":2588,
    "gn:feature_class":"P",
    "gn:feature_code":"PPL",
    "gn:name":"Julas",
    "gn:population":0,
    "gn:timezone":"Asia/Kolkata",
    "iso:country":"IN",
    "wof:name":"Julas",
    "wof:placetype":"locality"
},
  "geometry": {"coordinates":[76.38869,33.09224],"type":"Point"}
}