{
  "type": "Feature",
  "properties": {
    "iso:country":"IN",
    "ks:ks_name":"Kewtahi",
    "ks:ks_pop":100,
    "ks:ks_type":"HABITATION",
    "ks:ks_uagg_main":0,
    "name:eng_x_preferred":[
        "Kewtahi"
    ],
    "wof:name":"Kewtahi",
    "wof:placetype":"neighbourhood",
    "wof:population":100
},
  "geometry": {"coordinates":[82.514954,26.313869],"type":"Point"}
}