{
  "type": "Feature",
  "properties": {
    "gn:admin1_code":"35",
    "gn:admin2_code":"461.0",
    "gn:asciiname":"Parsaupri",
    "gn:country_code":"IN",
    "gn:dem":806,
    "gn:feature_class":"P",
    "gn:feature_code":"PPL",
    "gn:name":"Parsaupri",
    "gn:population":0,
    "gn:timezone":"Asia/Kolkata",
    "iso:country":"IN",
    "wof:name":"Parsaupri",
    "wof:placetype":"locality"
},
  "geometry": {"coordinates":[81.45138,22.96954],"type":"Point"}
}