{
  "type": "Feature",
  "properties": {
    "gn:admin1_code":"36.0",
    "gn:admin2_code":"140.0",
    "gn:asciiname":"Garhmukteshwar",
    "gn:country_code":"IN",
    "gn:dem":217,
    "gn:elevation":"0.0",
    "gn:feature_class":"P",
    "gn:feature_code":"PPL",
    "gn:name":"Garhmukteshwar",
    "gn:population":0,
    "gn:timezone":"Asia/Kolkata",
    "iso:country":"IN",
    "name:bpy_x_preferred":[
        "\u0997\u09a1\u09bc\u09ae\u09c1\u0995\u09cd\u09a4\u09c7\u09b6\u09cd\u09ac\u09b0"
    ],
    "name:deu_x_preferred":[
        "Garhmukteshwar"
    ],
    "name:hin_x_preferred":[
        "\u0917\u0922\u093c \u092e\u0941\u0915\u094d\u0924\u0947\u0936\u094d\u0935\u0930"
    ],
    "name:ita_x_preferred":[
        "Garhmukteshwar"
    ],
    "name:msa_x_preferred":[
        "Garhmukteshwar"
    ],
    "name:new_x_preferred":[
        "\u0917\u0930\u094d\u0939\u094d\u092e\u0941\u0915\u094d\u0924\u0947\u0936\u094d\u0935\u0930"
    ],
    "name:nld_x_preferred":[
        "Garhmukteshwar"
    ],
    "name:pan_x_preferred":[
        "\u0a17\u0a5c\u0a2e\u0a41\u0a15\u0a24\u0a47\u0a38\u0a3c\u0a35\u0a30"
    ],
    "name:pol_x_preferred":[
        "Garhmukteshwar"
    ],
    "name:por_x_preferred":[
        "Garhmukteshwar"
    ],
    "name:spa_x_preferred":[
        "Garhmukteshwar"
    ],
    "name:vie_x_preferred":[
        "Garhmukteshwar"
    ],
    "name:zho_x_preferred":[
        "\u52a0\u5c14\u8d6b\u7a46\u514b\u6cf0\u65af\u8d6b\u74e6\u5c14"
    ],
    "wof:name":"Garhmukteshwar",
    "wof:placetype":"neighbourhood"
},
  "geometry": {"coordinates":[78.08159999999999,28.78933],"type":"Point"}
}