{
  "type": "Feature",
  "properties": {
    "iso:country":"IN",
    "ks:ks_alt_nam":"CHORGHARA",
    "ks:ks_name":"Chorghara",
    "ks:ks_pop":3746,
    "ks:ks_type":"HABITATION",
    "name:eng_x_preferred":[
        "Chorghara"
    ],
    "wof:name":"Chorghara",
    "wof:placetype":"locality",
    "wof:population":3746
},
  "geometry": {"coordinates":[85.38708,23.641321],"type":"Point"}
}