{
  "type": "Feature",
  "properties": {
    "gn:country":"IN",
    "gn:fcode":"PPL",
    "gn:pop":29797,
    "iso:country":"IN",
    "name:ben_x_preferred":[
        "\u09b8\u09cb\u09b0\u09cb"
    ],
    "name:eng_x_preferred":[
        "Soro"
    ],
    "name:ind_x_preferred":[
        "Soro"
    ],
    "name:ita_x_preferred":[
        "Soro"
    ],
    "name:nan_x_preferred":[
        "Soro"
    ],
    "name:nld_x_preferred":[
        "Soro"
    ],
    "name:ori_x_preferred":[
        "\u0b38\u0b4b\u0b30"
    ],
    "name:tam_x_preferred":[
        "\u0b9a\u0bcb\u0bb0\u0bbe"
    ],
    "qs:name":"Soro",
    "qs:name_adm0":"India",
    "qs:name_adm1":"Orissa",
    "qs:photos_9k":1,
    "qs:photos_9r":1,
    "qs:photos_all":1,
    "qs:photos_sr":0,
    "qs:placetype":"Town",
    "qs:pop_sr":"7",
    "wd:wordcount":54,
    "wof:name":"Soro",
    "wof:placetype":"locality",
    "wof:population":29797
},
  "geometry": {"coordinates":[86.68832999999999,21.27851],"type":"Point"}
}