{
  "type": "Feature",
  "properties": {
    "iso:country":"IN",
    "ks:ks_name":"Chikkaresme Colony",
    "ks:ks_pop":53,
    "ks:ks_type":"HABITATION",
    "name:eng_x_preferred":[
        "Chikkaresme Colony"
    ],
    "wof:name":"Chikkaresme Colony",
    "wof:placetype":"locality",
    "wof:population":53
},
  "geometry": {"coordinates":[75.973333,12.261944],"type":"Point"}
}