{
  "type": "Feature",
  "properties": {
    "gn:admin1_code":"21.0",
    "gn:admin2_code":"398.0",
    "gn:asciiname":"Kottaguda",
    "gn:country_code":"IN",
    "gn:dem":664,
    "gn:feature_class":"P",
    "gn:feature_code":"PPL",
    "gn:name":"Kottag\u016bda",
    "gn:population":0,
    "gn:timezone":"Asia/Kolkata",
    "iso:country":"IN",
    "ks:ks_name":"Kataguda",
    "ks:ks_pop":37,
    "ks:ks_type":"HABITATION",
    "name:eng_x_preferred":[
        "Kataguda"
    ],
    "name:eng_x_variant":[
        "Kottaguda"
    ],
    "wof:name":"Kataguda",
    "wof:placetype":"locality",
    "wof:population":37
},
  "geometry": {"coordinates":[83.06482099999999,18.811593],"type":"Point"}
}