{
  "type": "Feature",
  "properties": {
    "iso:country":"IN",
    "ks:ks_name":"Bamhanidwar",
    "ks:ks_pop":67,
    "ks:ks_type":"VILLAGE",
    "name:eng_x_preferred":[
        "Bamhanidwar"
    ],
    "wof:name":"Bamhanidwar",
    "wof:placetype":"locality",
    "wof:population":67
},
  "geometry": {"coordinates":[83.17058,21.170021],"type":"Point"}
}