{
  "type": "Feature",
  "properties": {
    "iso:country":"IN",
    "ks:ks_name":"Pinnayur East",
    "ks:ks_pop":2203,
    "ks:ks_type":"VILLAGE",
    "name:eng_x_preferred":[
        "Pinnayur East"
    ],
    "wof:name":"Pinnayur East",
    "wof:placetype":"locality",
    "wof:population":2203
},
  "geometry": {"coordinates":[79.222691,10.589665],"type":"Point"}
}