{
  "type": "Feature",
  "properties": {
    "iso:country":"IN",
    "ks:ks_name":"East Joypur",
    "ks:ks_pop":620,
    "ks:ks_type":"HABITATION",
    "name:eng_x_preferred":[
        "East Joypur"
    ],
    "wof:name":"East Joypur",
    "wof:placetype":"locality",
    "wof:population":620
},
  "geometry": {"coordinates":[91.53613799999999,23.06905],"type":"Point"}
}