{
  "type": "Feature",
  "properties": {
    "iso:country":"IN",
    "ks:ks_name":"Goptira",
    "ks:ks_pop":1267,
    "ks:ks_type":"VILLAGE",
    "name:eng_x_preferred":[
        "Goptira"
    ],
    "wof:name":"Goptira",
    "wof:placetype":"locality",
    "wof:population":1267
},
  "geometry": {"coordinates":[86.659341,20.56036],"type":"Point"}
}