{
  "type": "Feature",
  "properties": {
    "iso:country":"IN",
    "ks:ks_name":"Boothinathamkottai",
    "ks:ks_pop":209,
    "ks:ks_type":"HABITATION",
    "ks:ks_uagg_main":0,
    "name:eng_x_preferred":[
        "Boothinathamkottai"
    ],
    "wof:name":"Boothinathamkottai",
    "wof:placetype":"neighbourhood",
    "wof:population":209
},
  "geometry": {"coordinates":[78.011387,12.256573],"type":"Point"}
}