{
  "type": "Feature",
  "properties": {
    "iso:country":"IN",
    "ks:ks_name":"Dhapsipada",
    "ks:ks_pop":93,
    "ks:ks_type":"HABITATION",
    "name:eng_x_preferred":[
        "Dhapsipada"
    ],
    "wof:name":"Dhapsipada",
    "wof:placetype":"locality",
    "wof:population":93
},
  "geometry": {"coordinates":[72.89789,19.762104],"type":"Point"}
}