{
  "type": "Feature",
  "properties": {
    "iso:country":"IN",
    "ks:ks_name":"Sagnal",
    "ks:ks_pop":268,
    "ks:ks_type":"VILLAGE",
    "name:eng_x_preferred":[
        "Sagnal"
    ],
    "wof:name":"Sagnal",
    "wof:placetype":"locality",
    "wof:population":268
},
  "geometry": {"coordinates":[84.694309,21.287516],"type":"Point"}
}