{
  "type": "Feature",
  "properties": {
    "gn:admin1_code":"36",
    "gn:admin2_code":"187.0",
    "gn:asciiname":"Maunahia",
    "gn:country_code":"IN",
    "gn:dem":89,
    "gn:feature_class":"P",
    "gn:feature_code":"PPL",
    "gn:name":"Maunahia",
    "gn:population":0,
    "gn:timezone":"Asia/Kolkata",
    "iso:country":"IN",
    "ks:ks_name":"Maunhiya",
    "ks:ks_pop":389,
    "ks:ks_type":"HABITATION",
    "name:eng_x_preferred":[
        "Maunhiya"
    ],
    "name:eng_x_variant":[
        "Maunahia"
    ],
    "wof:name":"Maunhiya",
    "wof:placetype":"locality",
    "wof:population":389
},
  "geometry": {"coordinates":[83.589883,26.950244],"type":"Point"}
}