{
  "type": "Feature",
  "properties": {
    "gn:admin1_code":"11",
    "gn:admin2_code":"27.0",
    "gn:asciiname":"Basi",
    "gn:country_code":"IN",
    "gn:dem":1037,
    "gn:feature_class":"P",
    "gn:feature_code":"PPL",
    "gn:name":"B\u0101si",
    "gn:population":0,
    "gn:timezone":"Asia/Kolkata",
    "iso:country":"IN",
    "name:cat_x_preferred":[
        "Basi"
    ],
    "name:ilo_x_preferred":[
        "Basi"
    ],
    "name:ita_x_preferred":[
        "Basi"
    ],
    "name:lit_x_preferred":[
        "Basis"
    ],
    "name:spa_x_preferred":[
        "Basi"
    ],
    "wof:name":"Basi",
    "wof:placetype":"locality"
},
  "geometry": {"coordinates":[76.80403000000003,31.95508],"type":"Point"}
}