{
  "type": "Feature",
  "properties": {
    "gn:admin1_code":"37",
    "gn:admin2_code":"408.0",
    "gn:asciiname":"Bharritola",
    "gn:country_code":"IN",
    "gn:dem":326,
    "gn:feature_class":"P",
    "gn:feature_code":"PPL",
    "gn:name":"Bharr\u012btola",
    "gn:population":0,
    "gn:timezone":"Asia/Kolkata",
    "iso:country":"IN",
    "ks:ks_alt_nam":"Bharr\u012btola",
    "ks:ks_name":"Bharritola",
    "ks:ks_type":"VILLAGE",
    "name:eng_x_preferred":[
        "Bharritola"
    ],
    "name:eng_x_variant":[
        "Bharr\u012btola"
    ],
    "wof:name":"Bharritola",
    "wof:placetype":"locality"
},
  "geometry": {"coordinates":[80.803719,20.824483],"type":"Point"}
}