{
  "type": "Feature",
  "properties": {
    "gn:admin1_code":"28.0",
    "gn:admin2_code":"327.0",
    "gn:asciiname":"Barbatia",
    "gn:country_code":"IN",
    "gn:dem":1528,
    "gn:feature_class":"P",
    "gn:feature_code":"PPL",
    "gn:name":"Barbatia",
    "gn:population":0,
    "gn:timezone":"Asia/Kolkata",
    "iso:country":"IN",
    "name:ceb_x_preferred":[
        "Barbatia"
    ],
    "name:deu_x_preferred":[
        "Barbatia"
    ],
    "name:nld_x_preferred":[
        "Barbatia"
    ],
    "name:pol_x_preferred":[
        "Barbatia"
    ],
    "name:swe_x_preferred":[
        "Barbatia"
    ],
    "name:war_x_preferred":[
        "Barbatia"
    ],
    "name:zho_x_preferred":[
        "\u9b0d\u9b41\u86e4\u5c6c"
    ],
    "wof:name":"Barbatia",
    "wof:placetype":"locality"
},
  "geometry": {"coordinates":[88.22981,27.02668],"type":"Point"}
}