{
  "type": "Feature",
  "properties": {
    "iso:country":"IN",
    "ks:ks_alt_nam":"SOUTH TOL",
    "ks:ks_name":"South Tol",
    "ks:ks_pop":816,
    "ks:ks_type":"HABITATION",
    "name:eng_x_preferred":[
        "South Tol"
    ],
    "wof:name":"South Tol",
    "wof:placetype":"locality",
    "wof:population":816
},
  "geometry": {"coordinates":[86.398436,26.143528],"type":"Point"}
}