{
  "type": "Feature",
  "properties": {
    "iso:country":"IN",
    "ks:ks_name":"Dehurisahi",
    "ks:ks_pop":268,
    "ks:ks_type":"HABITATION",
    "name:eng_x_preferred":[
        "Dehurisahi"
    ],
    "wof:name":"Dehurisahi",
    "wof:placetype":"locality",
    "wof:population":268
},
  "geometry": {"coordinates":[86.00657200000001,21.429156],"type":"Point"}
}