{
  "type": "Feature",
  "properties": {
    "gn:admin1_code":"35",
    "gn:admin2_code":"463.0",
    "gn:asciiname":"Garahara",
    "gn:country_code":"IN",
    "gn:dem":282,
    "gn:feature_class":"P",
    "gn:feature_code":"PPL",
    "gn:name":"Garahara",
    "gn:population":0,
    "gn:timezone":"Asia/Kolkata",
    "iso:country":"IN",
    "ks:ks_name":"Gadahara",
    "ks:ks_pop":1115,
    "ks:ks_type":"VILLAGE",
    "ks:ks_uagg_main":0,
    "name:eng_x_preferred":[
        "Gadahara"
    ],
    "wof:name":"Gadahara",
    "wof:placetype":"neighbourhood",
    "wof:population":1115
},
  "geometry": {"coordinates":[82.621754,24.00866],"type":"Point"}
}