{
  "type": "Feature",
  "properties": {
    "gn:admin1_code":"37",
    "gn:admin2_code":"400.0",
    "gn:asciiname":"Parsamunda",
    "gn:country_code":"IN",
    "gn:dem":452,
    "gn:feature_class":"P",
    "gn:feature_code":"PPL",
    "gn:name":"Parsamunda",
    "gn:population":0,
    "gn:timezone":"Asia/Kolkata",
    "iso:country":"IN",
    "wof:name":"Parsamunda",
    "wof:placetype":"locality"
},
  "geometry": {"coordinates":[82.24131,22.96226],"type":"Point"}
}