{
  "type": "Feature",
  "properties": {
    "gn:admin1_code":"37",
    "gn:admin2_code":"400.0",
    "gn:asciiname":"Parsamunda",
    "gn:country_code":"IN",
    "gn:dem":452,
    "gn:feature_class":"P",
    "gn:feature_code":"PPL",
    "gn:name":"Parsamunda",
    "gn:population":0,
    "gn:timezone":"Asia/Kolkata",
    "iso:country":"IN",
    "ks:ks_name":"Parsamuda",
    "ks:ks_pop":309,
    "ks:ks_type":"VILLAGE",
    "name:eng_x_preferred":[
        "Parsamuda"
    ],
    "name:eng_x_variant":[
        "Parsamunda"
    ],
    "wof:name":"Parsamuda",
    "wof:placetype":"locality",
    "wof:population":309
},
  "geometry": {"coordinates":[82.240543,22.958164],"type":"Point"}
}