{
  "type": "Feature",
  "properties": {
    "iso:country":"IN",
    "ks:ks_alt_nam":"Devi ka pura",
    "ks:ks_name":"Devi Ka Pura",
    "ks:ks_pop":733,
    "ks:ks_type":"HABITATION",
    "name:eng_x_preferred":[
        "Devi Ka Pura"
    ],
    "wof:name":"Devi Ka Pura",
    "wof:placetype":"locality",
    "wof:population":733
},
  "geometry": {"coordinates":[83.803568,26.104721],"type":"Point"}
}