{
  "type": "Feature",
  "properties": {
    "iso:country":"IN",
    "ks:ks_alt_nam":"Het\u012bm Chak",
    "ks:ks_name":"Hetim Chak",
    "ks:ks_type":"VILLAGE",
    "ks:ks_uagg_main":0,
    "name:eng_x_preferred":[
        "Hetim Chak"
    ],
    "name:eng_x_variant":[
        "Het\u012bm Chak"
    ],
    "wof:name":"Hetim Chak",
    "wof:placetype":"neighbourhood"
},
  "geometry": {"coordinates":[83.703602,25.725533],"type":"Point"}
}