{
  "type": "Feature",
  "properties": {
    "gn:admin1_code":"25.0",
    "gn:admin2_code":"631.0",
    "gn:asciiname":"Chinnappanayakkanur",
    "gn:country_code":"IN",
    "gn:dem":341,
    "gn:feature_class":"P",
    "gn:feature_code":"PPL",
    "gn:name":"Chinnappan\u0101yakkan\u016br",
    "gn:population":0,
    "gn:timezone":"Asia/Kolkata",
    "iso:country":"IN",
    "wof:name":"Chinnappanayakkanur",
    "wof:placetype":"locality"
},
  "geometry": {"coordinates":[78.54673000000003,12.25871],"type":"Point"}
}