{
  "type": "Feature",
  "properties": {
    "iso:country":"IN",
    "ks:ks_name":"Mundla",
    "ks:ks_pop":396,
    "ks:ks_type":"VILLAGE",
    "name:eng_x_preferred":[
        "Mundla"
    ],
    "wof:name":"Mundla",
    "wof:placetype":"locality",
    "wof:population":396
},
  "geometry": {"coordinates":[75.233496,24.014999],"type":"Point"}
}