{
  "type": "Feature",
  "properties": {
    "iso:country":"IN",
    "ks:ks_name":"Suluki",
    "ks:ks_pop":16,
    "ks:ks_type":"VILLAGE",
    "name:eng_x_preferred":[
        "Suluki"
    ],
    "wof:name":"Suluki",
    "wof:placetype":"locality",
    "wof:population":16
},
  "geometry": {"coordinates":[84.09231200000001,20.028263],"type":"Point"}
}