{
  "type": "Feature",
  "properties": {
    "gn:admin1_code":"11.0",
    "gn:admin2_code":"27.0",
    "gn:asciiname":"Ranot",
    "gn:country_code":"IN",
    "gn:dem":1432,
    "gn:feature_class":"P",
    "gn:feature_code":"PPL",
    "gn:name":"Ranot",
    "gn:population":0,
    "gn:timezone":"Asia/Kolkata",
    "iso:country":"IN",
    "wof:name":"Ranot",
    "wof:placetype":"locality"
},
  "geometry": {"coordinates":[77.20406,31.39227],"type":"Point"}
}