{
  "type": "Feature",
  "properties": {
    "iso:country":"IN",
    "ks:ks_name":"Palodi",
    "ks:ks_pop":311,
    "ks:ks_type":"HABITATION",
    "name:eng_x_preferred":[
        "Palodi"
    ],
    "wof:name":"Palodi",
    "wof:placetype":"locality",
    "wof:population":311
},
  "geometry": {"coordinates":[78.285625,27.493164],"type":"Point"}
}