{
  "type": "Feature",
  "properties": {
    "iso:country":"IN",
    "ks:ks_name":"Chikantargangi",
    "ks:ks_pop":5,
    "ks:ks_type":"HABITATION",
    "name:eng_x_preferred":[
        "Chikantargangi"
    ],
    "wof:name":"Chikantargangi",
    "wof:placetype":"locality",
    "wof:population":5
},
  "geometry": {"coordinates":[76.58172999999999,15.928205],"type":"Point"}
}