{
  "type": "Feature",
  "properties": {
    "iso:country":"IN",
    "ks:ks_name":"Paschim Kawoimari",
    "ks:ks_pop":715,
    "ks:ks_type":"HABITATION",
    "name:eng_x_preferred":[
        "Paschim Kawoimari"
    ],
    "wof:name":"Paschim Kawoimari",
    "wof:placetype":"locality",
    "wof:population":715
},
  "geometry": {"coordinates":[91.659587,26.510212],"type":"Point"}
}