{
  "type": "Feature",
  "properties": {
    "gn:admin1_code":"10.0",
    "gn:admin2_code":"75.0",
    "gn:asciiname":"Budhanpur",
    "gn:country_code":"IN",
    "gn:dem":224,
    "gn:feature_class":"P",
    "gn:feature_code":"PPL",
    "gn:name":"Budhanpur",
    "gn:population":0,
    "gn:timezone":"Asia/Kolkata",
    "iso:country":"IN",
    "wof:name":"Budhanpur",
    "wof:placetype":"locality"
},
  "geometry": {"coordinates":[77.1157,29.17246],"type":"Point"}
}