{
  "type": "Feature",
  "properties": {
    "iso:country":"IN",
    "ks:ks_name":"Sawantwada",
    "ks:ks_pop":244,
    "ks:ks_type":"HABITATION",
    "name:eng_x_preferred":[
        "Sawantwada"
    ],
    "wof:name":"Sawantwada",
    "wof:placetype":"locality",
    "wof:population":244
},
  "geometry": {"coordinates":[73.662522,15.853034],"type":"Point"}
}