{
  "type": "Feature",
  "properties": {
    "iso:country":"IN",
    "ks:ks_name":"Aeirakkanni",
    "ks:ks_pop":1080,
    "ks:ks_type":"HABITATION",
    "name:eng_x_preferred":[
        "Aeirakkanni"
    ],
    "wof:name":"Aeirakkanni",
    "wof:placetype":"locality",
    "wof:population":1080
},
  "geometry": {"coordinates":[79.507974,10.416815],"type":"Point"}
}