{
  "type": "Feature",
  "properties": {
    "gn:admin1_code":"11.0",
    "gn:admin2_code":"33.0",
    "gn:asciiname":"Kun",
    "gn:country_code":"IN",
    "gn:dem":1731,
    "gn:feature_class":"P",
    "gn:feature_code":"PPL",
    "gn:name":"K\u016bn",
    "gn:population":0,
    "gn:timezone":"Asia/Kolkata",
    "iso:country":"IN",
    "name:ceb_x_preferred":[
        "Kun"
    ],
    "name:deu_x_preferred":[
        "Kun"
    ],
    "name:est_x_preferred":[
        "Kun"
    ],
    "name:fra_x_preferred":[
        "Kun"
    ],
    "name:hun_x_preferred":[
        "Kun"
    ],
    "name:spa_x_preferred":[
        "Kun"
    ],
    "name:swe_x_preferred":[
        "Kun"
    ],
    "wof:name":"Kun",
    "wof:placetype":"locality"
},
  "geometry": {"coordinates":[77.40260000000001,31.10555],"type":"Point"}
}