{
  "type": "Feature",
  "properties": {
    "gn:admin1_code":"19.0",
    "gn:admin2_code":"582.0",
    "gn:asciiname":"Dogarnaikanhalli",
    "gn:country_code":"IN",
    "gn:dem":906,
    "gn:feature_class":"P",
    "gn:feature_code":"PPL",
    "gn:name":"Dogarn\u0101ikanhalli",
    "gn:population":0,
    "gn:timezone":"Asia/Kolkata",
    "iso:country":"IN",
    "wof:name":"Dogarnaikanhalli",
    "wof:placetype":"locality"
},
  "geometry": {"coordinates":[77.90923000000002,13.43891],"type":"Point"}
}