{
  "type": "Feature",
  "properties": {
    "gn:admin1_code":"36",
    "gn:admin2_code":"152.0",
    "gn:asciiname":"Rajputpur",
    "gn:country_code":"IN",
    "gn:dem":158,
    "gn:feature_class":"P",
    "gn:feature_code":"PPL",
    "gn:name":"R\u0101jp\u016btpur",
    "gn:population":0,
    "gn:timezone":"Asia/Kolkata",
    "iso:country":"IN",
    "name:und_x_variant":[
        "R\u0101jp\u016btpur",
        "Chitt\u012b"
    ],
    "wof:name":"Rajputpur",
    "wof:placetype":"locality"
},
  "geometry": {"coordinates":[79.6283,27.88298],"type":"Point"}
}