{
  "type": "Feature",
  "properties": {
    "iso:country":"IN",
    "ks:ks_name":"Bavadi Kheda Khurd",
    "ks:ks_pop":332,
    "ks:ks_type":"VILLAGE",
    "name:eng_x_preferred":[
        "Bavadi Kheda Khurd"
    ],
    "wof:name":"Bavadi Kheda Khurd",
    "wof:placetype":"locality",
    "wof:population":332
},
  "geometry": {"coordinates":[74.811969,23.533315],"type":"Point"}
}