{
  "type": "Feature",
  "properties": {
    "iso:country":"IN",
    "ks:ks_name":"Kommulavaripalem",
    "ks:ks_pop":125,
    "ks:ks_type":"HABITATION",
    "name:eng_x_preferred":[
        "Kommulavaripalem"
    ],
    "wof:name":"Kommulavaripalem",
    "wof:placetype":"locality",
    "wof:population":125
},
  "geometry": {"coordinates":[81.920914,16.556269],"type":"Point"}
}