{
  "type": "Feature",
  "properties": {
    "gn:admin1_code":"19.0",
    "gn:admin2_code":"573.0",
    "gn:asciiname":"Kirugavalu",
    "gn:country_code":"IN",
    "gn:dem":680,
    "gn:feature_class":"P",
    "gn:feature_code":"PPL",
    "gn:name":"Kirug\u0101valu",
    "gn:population":0,
    "gn:timezone":"Asia/Kolkata",
    "iso:country":"IN",
    "name:kan_x_preferred":[
        "\u0c95\u0cbf\u0cb0\u0cc1\u0c97\u0cbe\u0cb5\u0cb2\u0cc1"
    ],
    "wof:name":"Kirugavalu",
    "wof:placetype":"locality"
},
  "geometry": {"coordinates":[76.94800000000002,12.37349],"type":"Point"}
}