{
  "type": "Feature",
  "properties": {
    "iso:country":"IN",
    "ks:ks_alt_nam":"PUROHITO KI DHANI",
    "ks:ks_name":"Purohito Ki Dhani",
    "ks:ks_pop":55,
    "ks:ks_type":"HABITATION",
    "name:eng_x_preferred":[
        "Purohito Ki Dhani"
    ],
    "wof:name":"Purohito Ki Dhani",
    "wof:placetype":"locality",
    "wof:population":55
},
  "geometry": {"coordinates":[71.195222,26.099972],"type":"Point"}
}