{
  "type": "Feature",
  "properties": {
    "iso:country":"IN",
    "ks:ks_alt_nam":"dubara khera",
    "ks:ks_name":"Dubara Khera",
    "ks:ks_pop":175,
    "ks:ks_type":"HABITATION",
    "name:eng_x_preferred":[
        "Dubara Khera"
    ],
    "wof:name":"Dubara Khera",
    "wof:placetype":"locality",
    "wof:population":175
},
  "geometry": {"coordinates":[80.620014,26.435406],"type":"Point"}
}