{
  "type": "Feature",
  "properties": {
    "gn:admin1_code":"12.0",
    "gn:admin2_code":"2.0",
    "gn:asciiname":"Karalaniu",
    "gn:country_code":"IN",
    "gn:dem":2039,
    "gn:feature_class":"P",
    "gn:feature_code":"PPL",
    "gn:name":"Kar\u0101laniu",
    "gn:population":0,
    "gn:timezone":"Asia/Kolkata",
    "iso:country":"IN",
    "wof:name":"Karalaniu",
    "wof:placetype":"locality"
},
  "geometry": {"coordinates":[74.61839999999999,33.95793],"type":"Point"}
}