{
  "type": "Feature",
  "properties": {
    "iso:country":"IN",
    "ks:ks_name":"Majhiladih",
    "ks:ks_pop":64,
    "ks:ks_type":"VILLAGE",
    "name:eng_x_preferred":[
        "Majhiladih"
    ],
    "wof:name":"Majhiladih",
    "wof:placetype":"locality",
    "wof:population":64
},
  "geometry": {"coordinates":[86.59172,24.371581],"type":"Point"}
}