{
  "type": "Feature",
  "properties": {
    "gn:admin1_code":"24.0",
    "gn:admin2_code":"105",
    "gn:asciiname":"Ballabgarh",
    "gn:country_code":"IN",
    "gn:dem":267,
    "gn:feature_class":"P",
    "gn:feature_code":"PPL",
    "gn:name":"Ballabgarh",
    "gn:population":0,
    "gn:timezone":"Asia/Kolkata",
    "iso:country":"IN",
    "name:ara_x_preferred":[
        "\u0628\u0627\u0644\u0627\u0628\u062c\u0627\u0631\u0647"
    ],
    "name:ben_bn_x_preferred":[
        "\u09ac\u09b2\u09cd\u09b2\u09ad\u0997\u09dc"
    ],
    "name:ben_in_x_preferred":[
        "\u09ac\u09b2\u09cd\u09b2\u09ad\u0997\u09dc"
    ],
    "name:guj_x_preferred":[
        "\u0aac\u0ab2\u0acd\u0ab2\u0a97\u0aa2"
    ],
    "name:hin_x_preferred":[
        "\u092c\u0932\u094d\u0932\u092d\u0917\u095d"
    ],
    "name:kan_x_preferred":[
        "\u0cac\u0cb2\u0ccd\u0cb2\u0cad\u0ccd"
    ],
    "name:mal_x_preferred":[
        "\u0d2c\u0d32\u0d4d\u0d32\u0d2c\u0d4d\u0d17\u0d21\u0d4d"
    ],
    "name:mar_x_preferred":[
        "\u092c\u0932\u094d\u0932\u092d\u0917\u0922"
    ],
    "name:pan_x_preferred":[
        "\u0a2c\u0a71\u0a32\u0a2c\u0a17\u0a5c\u0a4d\u0a39"
    ],
    "name:tam_x_preferred":[
        "\u0baa\u0bb2\u0baa\u0bcd\u0b95\u0bb0\u0bcd"
    ],
    "name:tel_x_preferred":[
        "\u0c2c\u0c32\u0c4d\u0c32\u0c2c\u0c4d"
    ],
    "name:urd_x_preferred":[
        "\u0628\u0644\u0628\u06be \u06af\u0691\u06be"
    ],
    "wof:name":"Ballabgarh",
    "wof:placetype":"locality"
},
  "geometry": {"coordinates":[77.08259,26.96638],"type":"Point"}
}