{
  "type": "Feature",
  "properties": {
    "gn:admin1_code":"24.0",
    "gn:admin2_code":"105",
    "gn:asciiname":"Ballabgarh",
    "gn:country_code":"IN",
    "gn:dem":267,
    "gn:feature_class":"P",
    "gn:feature_code":"PPL",
    "gn:name":"Ballabgarh",
    "gn:population":0,
    "gn:timezone":"Asia/Kolkata",
    "iso:country":"IN",
    "wof:name":"Ballabgarh",
    "wof:placetype":"locality"
},
  "geometry": {"coordinates":[77.08259,26.96638],"type":"Point"}
}