{
  "type": "Feature",
  "properties": {
    "iso:country":"IN",
    "ks:ks_alt_nam":"Christian keri",
    "ks:ks_name":"Christian Keri",
    "ks:ks_pop":86,
    "ks:ks_type":"HABITATION",
    "name:eng_x_preferred":[
        "Christian Keri"
    ],
    "wof:name":"Christian Keri",
    "wof:placetype":"locality",
    "wof:population":86
},
  "geometry": {"coordinates":[74.438025,14.372443],"type":"Point"}
}