{
  "type": "Feature",
  "properties": {
    "iso:country":"IN",
    "ks:ks_alt_nam":"6 GGM",
    "ks:ks_name":"6 Ggm",
    "ks:ks_pop":3,
    "ks:ks_type":"HABITATION",
    "name:eng_x_preferred":[
        "6 Ggm"
    ],
    "wof:name":"6 Ggm",
    "wof:placetype":"locality",
    "wof:population":3
},
  "geometry": {"coordinates":[75.03915600000001,29.112094],"type":"Point"}
}