{
  "type": "Feature",
  "properties": {
    "iso:country":"IN",
    "ks:ks_name":"Merudihi",
    "ks:ks_pop":299,
    "ks:ks_type":"VILLAGE",
    "name:eng_x_preferred":[
        "Merudihi"
    ],
    "wof:name":"Merudihi",
    "wof:placetype":"locality",
    "wof:population":299
},
  "geometry": {"coordinates":[86.34877299999999,22.274888],"type":"Point"}
}