{
  "type": "Feature",
  "properties": {
    "gn:admin1_code":"11.0",
    "gn:admin2_code":"33.0",
    "gn:asciiname":"Kotadhar",
    "gn:country_code":"IN",
    "gn:dem":1888,
    "gn:feature_class":"P",
    "gn:feature_code":"PPL",
    "gn:name":"Kot\u0101dh\u0101r",
    "gn:population":0,
    "gn:timezone":"Asia/Kolkata",
    "iso:country":"IN",
    "wof:name":"Kotadhar",
    "wof:placetype":"locality"
},
  "geometry": {"coordinates":[77.55407,31.28858],"type":"Point"}
}