{
  "type": "Feature",
  "properties": {
    "iso:country":"IN",
    "ks:ks_name":"Tantipara",
    "ks:ks_pop":98,
    "ks:ks_type":"HABITATION",
    "ks:ks_uagg_main":0,
    "name:eng_x_preferred":[
        "Tantipara"
    ],
    "wof:name":"Tantipara",
    "wof:placetype":"neighbourhood",
    "wof:population":98
},
  "geometry": {"coordinates":[88.227833,22.65642],"type":"Point"}
}