{
  "type": "Feature",
  "properties": {
    "iso:country":"IN",
    "ks:ks_name":"Kanda",
    "ks:ks_pop":96,
    "ks:ks_type":"VILLAGE",
    "name:eng_x_preferred":[
        "Kanda"
    ],
    "wof:name":"Kanda",
    "wof:placetype":"locality",
    "wof:population":96
},
  "geometry": {"coordinates":[79.531887,29.460375],"type":"Point"}
}