{
  "type": "Feature",
  "properties": {
    "iso:country":"IN",
    "ks:ks_name":"Tikaura",
    "ks:ks_pop":0,
    "ks:ks_type":"VILLAGE",
    "name:eng_x_preferred":[
        "Tikaura"
    ],
    "wof:name":"Tikaura",
    "wof:placetype":"locality",
    "wof:population":0
},
  "geometry": {"coordinates":[83.95809300000001,25.427176],"type":"Point"}
}