{
  "type": "Feature",
  "properties": {
    "gn:admin1_code":"36",
    "gn:admin2_code":"155.0",
    "gn:asciiname":"Chandupur",
    "gn:country_code":"IN",
    "gn:dem":140,
    "gn:feature_class":"P",
    "gn:feature_code":"PPL",
    "gn:name":"Chand\u016bpur",
    "gn:population":0,
    "gn:timezone":"Asia/Kolkata",
    "iso:country":"IN",
    "ks:ks_name":"Chand Pur",
    "ks:ks_pop":153,
    "ks:ks_type":"HABITATION",
    "name:eng_x_preferred":[
        "Chand Pur"
    ],
    "name:eng_x_variant":[
        "Chandupur"
    ],
    "wof:name":"Chand Pur",
    "wof:placetype":"locality",
    "wof:population":153
},
  "geometry": {"coordinates":[79.93755299999999,27.53108],"type":"Point"}
}