{
  "type": "Feature",
  "properties": {
    "gn:admin1_code":"24",
    "gn:admin2_code":"112.0",
    "gn:asciiname":"Sankhwas",
    "gn:country_code":"IN",
    "gn:dem":333,
    "gn:feature_class":"P",
    "gn:feature_code":"PPL",
    "gn:name":"Sankhw\u0101s",
    "gn:population":0,
    "gn:timezone":"Asia/Kolkata",
    "iso:country":"IN",
    "name:und_x_variant":[
        "Sankhw\u0101i",
        "Sankhw\u0101s"
    ],
    "wof:name":"Sankhwas",
    "wof:placetype":"locality"
},
  "geometry": {"coordinates":[73.67829,26.92416],"type":"Point"}
}