{
  "type": "Feature",
  "properties": {
    "gn:admin1_code":"34.0",
    "gn:admin2_code":"212.0",
    "gn:asciiname":"Binji",
    "gn:country_code":"IN",
    "gn:dem":37,
    "gn:feature_class":"P",
    "gn:feature_code":"PPL",
    "gn:name":"Binji",
    "gn:population":0,
    "gn:timezone":"Asia/Kolkata",
    "iso:country":"IN",
    "ks:ks_name":"Binji",
    "ks:ks_pop":2912,
    "ks:ks_type":"VILLAGE",
    "ks:ks_uagg_main":0,
    "name:ceb_x_preferred":[
        "Binji"
    ],
    "name:eng_x_preferred":[
        "Binji"
    ],
    "name:fra_x_preferred":[
        "Binji"
    ],
    "name:hau_x_preferred":[
        "Binji"
    ],
    "name:ita_x_preferred":[
        "Binji"
    ],
    "name:por_x_preferred":[
        "Binji"
    ],
    "name:rus_x_preferred":[
        "\u0411\u0438\u043d\u0434\u0436\u0438"
    ],
    "name:spa_x_preferred":[
        "Binji"
    ],
    "wof:name":"Binji",
    "wof:placetype":"neighbourhood",
    "wof:population":2912
},
  "geometry": {"coordinates":[87.42500099999999,25.544795],"type":"Point"}
}