{
  "type": "Feature",
  "properties": {
    "iso:country":"IN",
    "ks:ks_name":"Tumballi Pura",
    "ks:ks_pop":190,
    "ks:ks_type":"HABITATION",
    "name:eng_x_preferred":[
        "Tumballi Pura"
    ],
    "wof:name":"Tumballi Pura",
    "wof:placetype":"locality",
    "wof:population":190
},
  "geometry": {"coordinates":[75.562828,13.327797],"type":"Point"}
}