{
  "type": "Feature",
  "properties": {
    "iso:country":"IN",
    "ks:ks_name":"Haledanivasa",
    "ks:ks_pop":75,
    "ks:ks_type":"HABITATION",
    "name:eng_x_preferred":[
        "Haledanivasa"
    ],
    "wof:name":"Haledanivasa",
    "wof:placetype":"locality",
    "wof:population":75
},
  "geometry": {"coordinates":[75.53448,13.659504],"type":"Point"}
}