{
  "type": "Feature",
  "properties": {
    "iso:country":"IN",
    "ks:ks_name":"Dauvrihar",
    "ks:ks_pop":432,
    "ks:ks_type":"HABITATION",
    "name:eng_x_preferred":[
        "Dauvrihar"
    ],
    "wof:name":"Dauvrihar",
    "wof:placetype":"locality",
    "wof:population":432
},
  "geometry": {"coordinates":[82.988962,27.048341],"type":"Point"}
}