{
  "type": "Feature",
  "properties": {
    "gn:admin1_code":"36",
    "gn:admin2_code":"165.0",
    "gn:asciiname":"Para",
    "gn:country_code":"IN",
    "gn:dem":126,
    "gn:feature_class":"P",
    "gn:feature_code":"PPL",
    "gn:name":"Para",
    "gn:population":0,
    "gn:timezone":"Asia/Kolkata",
    "iso:country":"IN",
    "wof:name":"Para",
    "wof:placetype":"locality"
},
  "geometry": {"coordinates":[79.58471999999998,26.09073],"type":"Point"}
}