{
  "type": "Feature",
  "properties": {
    "iso:country":"IN",
    "ks:ks_name":"Dusadh Tola 2",
    "ks:ks_pop":585,
    "ks:ks_type":"HABITATION",
    "name:eng_x_preferred":[
        "Dusadh Tola 2"
    ],
    "wof:name":"Dusadh Tola 2",
    "wof:placetype":"locality",
    "wof:population":585
},
  "geometry": {"coordinates":[84.412352,26.385584],"type":"Point"}
}