{
  "type": "Feature",
  "properties": {
    "iso:country":"IN",
    "ks:ks_name":"Dengapakana",
    "ks:ks_pop":155,
    "ks:ks_type":"HABITATION",
    "name:eng_x_preferred":[
        "Dengapakana"
    ],
    "wof:name":"Dengapakana",
    "wof:placetype":"locality",
    "wof:population":155
},
  "geometry": {"coordinates":[82.315236,18.7554],"type":"Point"}
}