{
  "type": "Feature",
  "properties": {
    "iso:country":"IN",
    "ks:ks_name":"Kodai",
    "ks:ks_pop":198,
    "ks:ks_type":"VILLAGE",
    "ks:ks_uagg_main":0,
    "name:eng_x_preferred":[
        "Kodai"
    ],
    "wof:name":"Kodai",
    "wof:placetype":"neighbourhood",
    "wof:population":198
},
  "geometry": {"coordinates":[86.78316599999999,24.429219],"type":"Point"}
}