{
  "type": "Feature",
  "properties": {
    "gn:admin1_code":"37.0",
    "gn:admin2_code":"400.0",
    "gn:asciiname":"Patpartola",
    "gn:country_code":"IN",
    "gn:dem":581,
    "gn:feature_class":"P",
    "gn:feature_code":"PPL",
    "gn:name":"Patpartola",
    "gn:population":0,
    "gn:timezone":"Asia/Kolkata",
    "iso:country":"IN",
    "wof:name":"Patpartola",
    "wof:placetype":"locality"
},
  "geometry": {"coordinates":[81.64187,23.55619],"type":"Point"}
}