{
  "type": "Feature",
  "properties": {
    "gn:admin1_code":"37.0",
    "gn:admin2_code":"400.0",
    "gn:asciiname":"Patpartola",
    "gn:country_code":"IN",
    "gn:dem":581,
    "gn:feature_class":"P",
    "gn:feature_code":"PPL",
    "gn:name":"Patpartola",
    "gn:population":0,
    "gn:timezone":"Asia/Kolkata",
    "iso:country":"IN",
    "ks:ks_name":"Patpartola",
    "ks:ks_pop":395,
    "ks:ks_type":"VILLAGE",
    "name:eng_x_preferred":[
        "Patpartola"
    ],
    "wof:name":"Patpartola",
    "wof:placetype":"locality",
    "wof:population":395
},
  "geometry": {"coordinates":[81.648017,23.541732],"type":"Point"}
}