{
  "type": "Feature",
  "properties": {
    "gn:admin1_code":"19.0",
    "gn:admin2_code":"573.0",
    "gn:asciiname":"Chikharohalli",
    "gn:country_code":"IN",
    "gn:dem":716,
    "gn:feature_class":"P",
    "gn:feature_code":"PPL",
    "gn:name":"Chikh\u0101rohalli",
    "gn:population":0,
    "gn:timezone":"Asia/Kolkata",
    "iso:country":"IN",
    "wof:name":"Chikharohalli",
    "wof:placetype":"locality"
},
  "geometry": {"coordinates":[76.84045,12.43529],"type":"Point"}
}