{
  "type": "Feature",
  "properties": {
    "gn:admin1_code":"12.0",
    "gn:admin2_code":"16.0",
    "gn:asciiname":"Himoti",
    "gn:country_code":"IN",
    "gn:dem":2044,
    "gn:feature_class":"P",
    "gn:feature_code":"PPL",
    "gn:name":"Himoti",
    "gn:population":0,
    "gn:timezone":"Asia/Kolkata",
    "iso:country":"IN",
    "wof:name":"Himoti",
    "wof:placetype":"locality"
},
  "geometry": {"coordinates":[75.68716999999999,33.06272],"type":"Point"}
}