{
  "type": "Feature",
  "properties": {
    "iso:country":"IN",
    "ks:ks_name":"Chaudhari Chakala",
    "ks:ks_pop":402,
    "ks:ks_type":"VILLAGE",
    "name:eng_x_preferred":[
        "Chaudhari Chakala"
    ],
    "wof:name":"Chaudhari Chakala",
    "wof:placetype":"locality",
    "wof:population":402
},
  "geometry": {"coordinates":[87.289383,25.516721],"type":"Point"}
}