{
  "type": "Feature",
  "properties": {
    "iso:country":"IN",
    "ks:ks_name":"Char Kaludiar",
    "ks:ks_pop":0,
    "ks:ks_type":"VILLAGE",
    "name:eng_x_preferred":[
        "Char Kaludiar"
    ],
    "wof:name":"Char Kaludiar",
    "wof:placetype":"locality",
    "wof:population":0
},
  "geometry": {"coordinates":[88.489339,24.085862],"type":"Point"}
}