{
  "type": "Feature",
  "properties": {
    "iso:country":"IN",
    "ks:ks_name":"Vanganpada",
    "ks:ks_pop":34,
    "ks:ks_type":"HABITATION",
    "name:eng_x_preferred":[
        "Vanganpada"
    ],
    "wof:name":"Vanganpada",
    "wof:placetype":"locality",
    "wof:population":34
},
  "geometry": {"coordinates":[73.42595,20.442049],"type":"Point"}
}