{
  "type": "Feature",
  "properties": {
    "gn:admin1_code":"36.0",
    "gn:admin2_code":"133",
    "gn:asciiname":"Bhukarheri",
    "gn:country_code":"IN",
    "gn:dem":250,
    "gn:feature_class":"P",
    "gn:feature_code":"PPL",
    "gn:name":"Bh\u016bkarheri",
    "gn:population":0,
    "gn:timezone":"Asia/Kolkata",
    "iso:country":"IN",
    "name:und_x_variant":[
        "Bh\u016bkaher\u012b",
        "Bh\u016bkarher\u012b",
        "Bh\u016bkarheri"
    ],
    "wof:name":"Bhukarheri",
    "wof:placetype":"locality"
},
  "geometry": {"coordinates":[77.93803,29.50682],"type":"Point"}
}