{
  "type": "Feature",
  "properties": {
    "iso:country":"IN",
    "ks:ks_alt_nam":"Roy para",
    "ks:ks_name":"Roy Para",
    "ks:ks_pop":190,
    "ks:ks_type":"HABITATION",
    "name:eng_x_preferred":[
        "Roy Para"
    ],
    "wof:name":"Roy Para",
    "wof:placetype":"locality",
    "wof:population":190
},
  "geometry": {"coordinates":[87.89803499999999,22.786317],"type":"Point"}
}