{
  "type": "Feature",
  "properties": {
    "iso:country":"IN",
    "ks:ks_name":"Kulia",
    "ks:ks_pop":502,
    "ks:ks_type":"HABITATION",
    "ks:ks_uagg_main":0,
    "name:eng_x_preferred":[
        "Kulia"
    ],
    "wof:name":"Kulia",
    "wof:placetype":"neighbourhood",
    "wof:population":502
},
  "geometry": {"coordinates":[90.68634400000001,26.053158],"type":"Point"}
}