{
  "type": "Feature",
  "properties": {
    "iso:country":"IN",
    "ks:ks_name":"Hurkakuchi",
    "ks:ks_pop":300,
    "ks:ks_type":"VILLAGE",
    "ks:ks_uagg_main":0,
    "name:eng_x_preferred":[
        "Hurkakuchi"
    ],
    "wof:name":"Hurkakuchi",
    "wof:placetype":"locality",
    "wof:population":300
},
  "geometry": {"coordinates":[90.589786,26.186713],"type":"Point"}
}