{
  "type": "Feature",
  "properties": {
    "iso:country":"IN",
    "ks:ks_name":"Cheruppancodu",
    "ks:ks_pop":428,
    "ks:ks_type":"HABITATION",
    "ks:ks_uagg_main":0,
    "name:eng_x_preferred":[
        "Cheruppancodu"
    ],
    "wof:name":"Cheruppancodu",
    "wof:placetype":"neighbourhood",
    "wof:population":428
},
  "geometry": {"coordinates":[77.347644,8.192748],"type":"Point"}
}