{
  "type": "Feature",
  "properties": {
    "gn:admin1_code":"34.0",
    "gn:admin2_code":"236.0",
    "gn:asciiname":"Adai",
    "gn:country_code":"IN",
    "gn:dem":106,
    "gn:feature_class":"P",
    "gn:feature_code":"PPL",
    "gn:name":"Ad\u0101i",
    "gn:population":0,
    "gn:timezone":"Asia/Kolkata",
    "iso:country":"IN",
    "name:ceb_x_preferred":[
        "Adai"
    ],
    "name:fra_x_preferred":[
        "Adai"
    ],
    "name:glg_x_preferred":[
        "Adai"
    ],
    "name:swe_x_preferred":[
        "Adai"
    ],
    "name:tel_x_preferred":[
        "\u0c05\u0c21\u0c48"
    ],
    "wof:name":"Adai",
    "wof:placetype":"locality"
},
  "geometry": {"coordinates":[84.76813,24.87506],"type":"Point"}
}