{
  "type": "Feature",
  "properties": {
    "gn:admin1_code":"19.0",
    "gn:asciiname":"Gollapuram",
    "gn:country_code":"IN",
    "gn:dem":658,
    "gn:feature_class":"P",
    "gn:feature_code":"PPL",
    "gn:name":"Goll\u0101puram",
    "gn:population":0,
    "gn:timezone":"Asia/Kolkata",
    "iso:country":"IN",
    "wof:name":"Gollapuram",
    "wof:placetype":"locality"
},
  "geometry": {"coordinates":[77.52571,13.72932],"type":"Point"}
}