{
  "type": "Feature",
  "properties": {
    "iso:country":"IN",
    "ks:ks_name":"Padukalthur",
    "ks:ks_pop":238,
    "ks:ks_type":"HABITATION",
    "name:eng_x_preferred":[
        "Padukalthur"
    ],
    "wof:name":"Padukalthur",
    "wof:placetype":"locality",
    "wof:population":238
},
  "geometry": {"coordinates":[74.80222500000001,13.207889],"type":"Point"}
}