{
  "type": "Feature",
  "properties": {
    "iso:country":"IN",
    "ks:ks_name":"Harijanvas",
    "ks:ks_pop":207,
    "ks:ks_type":"HABITATION",
    "name:eng_x_preferred":[
        "Harijanvas"
    ],
    "wof:name":"Harijanvas",
    "wof:placetype":"locality",
    "wof:population":207
},
  "geometry": {"coordinates":[72.744972,20.236556],"type":"Point"}
}