{
  "type": "Feature",
  "properties": {
    "gn:admin1_code":"35",
    "gn:admin2_code":"425.0",
    "gn:asciiname":"Bharator",
    "gn:country_code":"IN",
    "gn:dem":451,
    "gn:feature_class":"P",
    "gn:feature_code":"PPL",
    "gn:name":"Bhar\u0101tor",
    "gn:population":0,
    "gn:timezone":"Asia/Kolkata",
    "iso:country":"IN",
    "wof:name":"Bharator",
    "wof:placetype":"locality"
},
  "geometry": {"coordinates":[79.2401,24.29306],"type":"Point"}
}