{
  "type": "Feature",
  "properties": {
    "iso:country":"IN",
    "ks:ks_name":"Kuruvadi",
    "ks:ks_pop":526,
    "ks:ks_type":"VILLAGE",
    "ks:ks_uagg_main":0,
    "name:eng_x_preferred":[
        "Kuruvadi"
    ],
    "wof:name":"Kuruvadi",
    "wof:placetype":"neighbourhood",
    "wof:population":526
},
  "geometry": {"coordinates":[79.730681,10.879091],"type":"Point"}
}