{
  "type": "Feature",
  "properties": {
    "gn:admin1_code":"24.0",
    "gn:admin2_code":"130.0",
    "gn:asciiname":"Nandbel",
    "gn:country_code":"IN",
    "gn:dem":619,
    "gn:feature_class":"P",
    "gn:feature_code":"PPL",
    "gn:name":"N\u0101ndbel",
    "gn:population":0,
    "gn:timezone":"Asia/Kolkata",
    "iso:country":"IN",
    "ks:ks_name":"Nandvel",
    "ks:ks_pop":1006,
    "ks:ks_type":"VILLAGE",
    "name:eng_x_preferred":[
        "Nandvel"
    ],
    "name:eng_x_variant":[
        "Nandbel"
    ],
    "wof:name":"Nandvel",
    "wof:placetype":"locality",
    "wof:population":1006
},
  "geometry": {"coordinates":[73.509381,24.525453],"type":"Point"}
}