{
  "type": "Feature",
  "properties": {
    "gn:admin1_code":"9.0",
    "gn:admin2_code":"476",
    "gn:asciiname":"Bagathala",
    "gn:country_code":"IN",
    "gn:dem":42,
    "gn:feature_class":"P",
    "gn:feature_code":"PPL",
    "gn:name":"Bagathala",
    "gn:population":0,
    "gn:timezone":"Asia/Kolkata",
    "iso:country":"IN",
    "name:und_x_variant":[
        "Bagathla",
        "Bagathala"
    ],
    "wof:name":"Bagathala",
    "wof:placetype":"locality"
},
  "geometry": {"coordinates":[70.72096999999999,22.85356],"type":"Point"}
}