{
  "type": "Feature",
  "properties": {
    "iso:country":"IN",
    "ks:ks_name":"Baghamunda",
    "ks:ks_pop":81,
    "ks:ks_type":"HABITATION",
    "name:eng_x_preferred":[
        "Baghamunda"
    ],
    "wof:name":"Baghamunda",
    "wof:placetype":"locality",
    "wof:population":81
},
  "geometry": {"coordinates":[84.535912,21.408987],"type":"Point"}
}