{
  "type": "Feature",
  "properties": {
    "iso:country":"IN",
    "ks:ks_name":"Kansarulu",
    "ks:ks_pop":185,
    "ks:ks_type":"HABITATION",
    "name:eng_x_preferred":[
        "Kansarulu"
    ],
    "wof:name":"Kansarulu",
    "wof:placetype":"locality",
    "wof:population":185
},
  "geometry": {"coordinates":[83.362587,19.542771],"type":"Point"}
}