{
  "type": "Feature",
  "properties": {
    "iso:country":"IN",
    "ks:ks_name":"Baghadih",
    "ks:ks_pop":865,
    "ks:ks_type":"VILLAGE",
    "ks:ks_uagg_main":0,
    "name:eng_x_preferred":[
        "Baghadih"
    ],
    "wof:name":"Baghadih",
    "wof:placetype":"neighbourhood",
    "wof:population":865
},
  "geometry": {"coordinates":[86.237585,23.090049],"type":"Point"}
}