{
  "type": "Feature",
  "properties": {
    "iso:country":"IN",
    "ks:ks_name":"Khairi",
    "ks:ks_pop":949,
    "ks:ks_type":"VILLAGE",
    "name:eng_x_preferred":[
        "Khairi"
    ],
    "wof:name":"Khairi",
    "wof:placetype":"locality",
    "wof:population":949
},
  "geometry": {"coordinates":[81.50873300000001,23.413109],"type":"Point"}
}