{
  "type": "Feature",
  "properties": {
    "iso:country":"IN",
    "ks:ks_name":"Srinagar",
    "ks:ks_pop":133,
    "ks:ks_type":"HABITATION",
    "name:eng_x_preferred":[
        "Srinagar"
    ],
    "wof:name":"Srinagar",
    "wof:placetype":"locality",
    "wof:population":133
},
  "geometry": {"coordinates":[82.941844,27.273107],"type":"Point"}
}