{
  "type": "Feature",
  "properties": {
    "iso:country":"IN",
    "ks:ks_name":"Srinagar",
    "ks:ks_pop":133,
    "ks:ks_type":"HABITATION",
    "name:eng_x_preferred":[
        "Srinagar"
    ],
    "name:hin_x_preferred":[
        "\u0936\u094d\u0930\u0940\u0928\u0917\u0930"
    ],
    "name:urd_x_preferred":[
        "\u0633\u0631\u06cc \u0646\u06af\u0631"
    ],
    "wof:name":"Srinagar",
    "wof:placetype":"locality",
    "wof:population":133
},
  "geometry": {"coordinates":[82.941844,27.273107],"type":"Point"}
}