{
  "type": "Feature",
  "properties": {
    "gn:admin1_code":"36",
    "gn:admin2_code":"143.0",
    "gn:asciiname":"Moraina",
    "gn:country_code":"IN",
    "gn:dem":189,
    "gn:feature_class":"P",
    "gn:feature_code":"PPL",
    "gn:name":"Moraina",
    "gn:population":0,
    "gn:timezone":"Asia/Kolkata",
    "iso:country":"IN",
    "wof:name":"Moraina",
    "wof:placetype":"locality"
},
  "geometry": {"coordinates":[77.98885,28.05886],"type":"Point"}
}