{
  "type": "Feature",
  "properties": {
    "gn:admin1_code":"21.0",
    "gn:admin2_code":"398.0",
    "gn:asciiname":"Jongomuguda",
    "gn:country_code":"IN",
    "gn:dem":897,
    "gn:feature_class":"P",
    "gn:feature_code":"PPL",
    "gn:name":"Jongomuguda",
    "gn:population":0,
    "gn:timezone":"Asia/Kolkata",
    "iso:country":"IN",
    "wof:name":"Jongomuguda",
    "wof:placetype":"neighbourhood"
},
  "geometry": {"coordinates":[82.83344,18.66317],"type":"Point"}
}