{
  "type": "Feature",
  "properties": {
    "gn:admin1_code":"36",
    "gn:admin2_code":"193.0",
    "gn:asciiname":"Mahatwar",
    "gn:country_code":"IN",
    "gn:dem":71,
    "gn:feature_class":"P",
    "gn:feature_code":"PPL",
    "gn:name":"Mahatw\u0101r",
    "gn:population":0,
    "gn:timezone":"Asia/Kolkata",
    "iso:country":"IN",
    "ks:ks_name":"Mahatwar",
    "ks:ks_pop":1160,
    "ks:ks_type":"VILLAGE",
    "name:eng_x_preferred":[
        "Mahatwar"
    ],
    "wof:name":"Mahatwar",
    "wof:placetype":"locality",
    "wof:population":1160
},
  "geometry": {"coordinates":[83.811525,25.887772],"type":"Point"}
}