{
  "type": "Feature",
  "properties": {
    "iso:country":"IN",
    "ks:ks_name":"Benehallada Kaval",
    "ks:ks_pop":40,
    "ks:ks_type":"HABITATION",
    "name:eng_x_preferred":[
        "Benehallada Kaval"
    ],
    "wof:name":"Benehallada Kaval",
    "wof:placetype":"locality",
    "wof:population":40
},
  "geometry": {"coordinates":[76.713221,13.318571],"type":"Point"}
}