{
  "type": "Feature",
  "properties": {
    "iso:country":"IN",
    "ks:ks_name":"Manasya",
    "ks:ks_pop":582,
    "ks:ks_type":"VILLAGE",
    "name:eng_x_preferred":[
        "Manasya"
    ],
    "wof:name":"Manasya",
    "wof:placetype":"locality",
    "wof:population":582
},
  "geometry": {"coordinates":[74.880684,22.985753],"type":"Point"}
}