{
  "type": "Feature",
  "properties": {
    "iso:country":"IN",
    "ks:ks_alt_nam":"Kamathi T parali",
    "ks:ks_name":"Kamathi T Parali",
    "ks:ks_pop":231,
    "ks:ks_type":"HABITATION",
    "ks:ks_uagg_main":0,
    "name:eng_x_preferred":[
        "Kamathi T Parali"
    ],
    "wof:name":"Kamathi T Parali",
    "wof:placetype":"neighbourhood",
    "wof:population":231
},
  "geometry": {"coordinates":[74.453744,17.441802],"type":"Point"}
}