{
  "type": "Feature",
  "properties": {
    "iso:country":"IN",
    "ks:ks_name":"Harchi Ali",
    "ks:ks_pop":284,
    "ks:ks_type":"HABITATION",
    "ks:ks_uagg_main":0,
    "name:eng_x_preferred":[
        "Harchi Ali"
    ],
    "wof:name":"Harchi Ali",
    "wof:placetype":"neighbourhood",
    "wof:population":284
},
  "geometry": {"coordinates":[93.392529,26.025789],"type":"Point"}
}