{
  "type": "Feature",
  "properties": {
    "gn:admin1_code":"19.0",
    "gn:admin2_code":"566.0",
    "gn:asciiname":"Madhure",
    "gn:country_code":"IN",
    "gn:dem":731,
    "gn:feature_class":"P",
    "gn:feature_code":"PPL",
    "gn:name":"Madhure",
    "gn:population":0,
    "gn:timezone":"Asia/Kolkata",
    "iso:country":"IN",
    "wof:name":"Madhure",
    "wof:placetype":"locality"
},
  "geometry": {"coordinates":[76.23305000000001,13.8362],"type":"Point"}
}