{
  "type": "Feature",
  "properties": {
    "gn:admin1_code":"36",
    "gn:admin2_code":"180.0",
    "gn:asciiname":"Saida",
    "gn:country_code":"IN",
    "gn:dem":130,
    "gn:feature_class":"P",
    "gn:feature_code":"PPL",
    "gn:name":"Saida",
    "gn:population":0,
    "gn:timezone":"Asia/Kolkata",
    "iso:country":"IN",
    "ks:ks_name":"Saida",
    "ks:ks_pop":172,
    "ks:ks_type":"HABITATION",
    "ks:ks_uagg_main":0,
    "name:ceb_x_preferred":[
        "Saida"
    ],
    "name:deu_x_preferred":[
        "Saida"
    ],
    "name:eng_x_preferred":[
        "Saida"
    ],
    "name:fas_x_preferred":[
        "\u0633\u0639\u06cc\u062f\u0647"
    ],
    "name:heb_x_preferred":[
        "\u05e1\u05d9\u05d9\u05d3\u05d0"
    ],
    "name:hin_x_preferred":[
        "\u0938\u093e\u0907\u0926\u093e"
    ],
    "name:ind_x_preferred":[
        "Saida"
    ],
    "name:kor_x_preferred":[
        "\uc0ac\uc774\ub2e4"
    ],
    "name:lit_x_preferred":[
        "Saida"
    ],
    "name:nld_x_preferred":[
        "Saida"
    ],
    "name:por_x_preferred":[
        "Sa\u00edda"
    ],
    "name:ron_x_preferred":[
        "Saida"
    ],
    "name:rus_x_preferred":[
        "\u0421\u0430\u0438\u0434\u0430"
    ],
    "name:swe_x_preferred":[
        "Saida"
    ],
    "name:vie_x_preferred":[
        "Saida"
    ],
    "wof:name":"Saida",
    "wof:placetype":"neighbourhood",
    "wof:population":172
},
  "geometry": {"coordinates":[81.561987,27.696363],"type":"Point"}
}