{
  "type": "Feature",
  "properties": {
    "iso:country":"IN",
    "ks:ks_name":"Halasinahalli",
    "ks:ks_pop":95,
    "ks:ks_type":"HABITATION",
    "name:eng_x_preferred":[
        "Halasinahalli"
    ],
    "wof:name":"Halasinahalli",
    "wof:placetype":"locality",
    "wof:population":95
},
  "geometry": {"coordinates":[76.38677800000001,13.055921],"type":"Point"}
}