{
  "type": "Feature",
  "properties": {
    "gn:admin1_code":"39",
    "gn:asciiname":"Kurara Khera",
    "gn:country_code":"IN",
    "gn:dem":1497,
    "gn:feature_class":"P",
    "gn:feature_code":"PPL",
    "gn:name":"Kur\u0101ra Khera",
    "gn:population":0,
    "gn:timezone":"Asia/Kolkata",
    "iso:country":"IN",
    "wof:name":"Kurara Khera",
    "wof:placetype":"locality"
},
  "geometry": {"coordinates":[77.79174999999999,30.88676],"type":"Point"}
}