{
  "type": "Feature",
  "properties": {
    "iso:country":"IN",
    "ks:ks_name":"Bijenagar",
    "ks:ks_pop":50,
    "ks:ks_type":"VILLAGE",
    "name:eng_x_preferred":[
        "Bijenagar"
    ],
    "wof:name":"Bijenagar",
    "wof:placetype":"locality",
    "wof:population":50
},
  "geometry": {"coordinates":[84.83277699999999,20.308508],"type":"Point"}
}