{
  "type": "Feature",
  "properties": {
    "gn:admin1_code":"23",
    "gn:admin2_code":"38.0",
    "gn:asciiname":"Mirpur",
    "gn:country_code":"IN",
    "gn:dem":245,
    "gn:feature_class":"P",
    "gn:feature_code":"PPL",
    "gn:name":"M\u012brpur",
    "gn:population":0,
    "gn:timezone":"Asia/Kolkata",
    "iso:country":"IN",
    "ks:ks_alt_nam":"M\u012brpur",
    "ks:ks_name":"Mirpur",
    "ks:ks_type":"VILLAGE",
    "name:ben_x_preferred":[
        "\u09ae\u09bf\u09b0\u09aa\u09c1\u09b0"
    ],
    "name:eng_x_preferred":[
        "Mirpur"
    ],
    "name:eng_x_variant":[
        "M\u012brpur"
    ],
    "name:ita_x_preferred":[
        "Mirpur"
    ],
    "name:sco_x_preferred":[
        "Mirpur"
    ],
    "name:snd_x_preferred":[
        "\u0645\u064a\u0631\u067e\u0648\u0631"
    ],
    "wof:name":"Mirpur",
    "wof:placetype":"locality"
},
  "geometry": {"coordinates":[75.547383,31.917408],"type":"Point"}
}