{
  "type": "Feature",
  "properties": {
    "gn:admin1_code":"35.0",
    "gn:admin2_code":"447.0",
    "gn:asciiname":"Jhirikhapa",
    "gn:country_code":"IN",
    "gn:dem":801,
    "gn:feature_class":"P",
    "gn:feature_code":"PPL",
    "gn:name":"Jhir\u012bkh\u0101pa",
    "gn:population":0,
    "gn:timezone":"Asia/Kolkata",
    "iso:country":"IN",
    "wof:name":"Jhirikhapa",
    "wof:placetype":"locality"
},
  "geometry": {"coordinates":[78.1258,21.86571],"type":"Point"}
}