{
  "type": "Feature",
  "properties": {
    "iso:country":"IN",
    "ks:ks_alt_nam":"MADA PUR",
    "ks:ks_name":"Mada Pur",
    "ks:ks_pop":343,
    "ks:ks_type":"HABITATION",
    "name:eng_x_preferred":[
        "Mada Pur"
    ],
    "wof:name":"Mada Pur",
    "wof:placetype":"locality",
    "wof:population":343
},
  "geometry": {"coordinates":[82.027529,26.0761],"type":"Point"}
}