{
  "type": "Feature",
  "properties": {
    "iso:country":"IN",
    "ks:ks_name":"Uttar Sibrampur",
    "ks:ks_pop":1207,
    "ks:ks_type":"VILLAGE",
    "name:eng_x_preferred":[
        "Uttar Sibrampur"
    ],
    "wof:name":"Uttar Sibrampur",
    "wof:placetype":"locality",
    "wof:population":1207
},
  "geometry": {"coordinates":[87.904493,25.956907],"type":"Point"}
}