{
  "type": "Feature",
  "properties": {
    "iso:country":"IN",
    "ks:ks_name":"Maruguda",
    "ks:ks_pop":46,
    "ks:ks_type":"HABITATION",
    "name:eng_x_preferred":[
        "Maruguda"
    ],
    "wof:name":"Maruguda",
    "wof:placetype":"locality",
    "wof:population":46
},
  "geometry": {"coordinates":[78.90673099999999,19.360451],"type":"Point"}
}