{
  "type": "Feature",
  "properties": {
    "iso:country":"IN",
    "ks:ks_name":"Maruthangal Jn",
    "ks:ks_pop":817,
    "ks:ks_type":"HABITATION",
    "ks:ks_uagg_main":0,
    "name:eng_x_preferred":[
        "Maruthangal Jn"
    ],
    "wof:name":"Maruthangal Jn",
    "wof:placetype":"neighbourhood",
    "wof:population":817
},
  "geometry": {"coordinates":[76.321388,11.22714],"type":"Point"}
}