{
  "type": "Feature",
  "properties": {
    "gn:admin1_code":"12.0",
    "gn:admin2_code":"18.0",
    "gn:asciiname":"Her Tsainyar",
    "gn:country_code":"IN",
    "gn:dem":2233,
    "gn:feature_class":"P",
    "gn:feature_code":"PPL",
    "gn:name":"Her Tsainyar",
    "gn:population":0,
    "gn:timezone":"Asia/Kolkata",
    "iso:country":"IN",
    "wof:name":"Her Tsainyar",
    "wof:placetype":"locality"
},
  "geometry": {"coordinates":[75.70276,33.61964],"type":"Point"}
}