{
  "type": "Feature",
  "properties": {
    "gn:admin1_code":"25",
    "gn:admin2_code":"610.0",
    "gn:asciiname":"Vairamangalam",
    "gn:country_code":"IN",
    "gn:dem":175,
    "gn:feature_class":"P",
    "gn:feature_code":"PPL",
    "gn:name":"Vairamangalam",
    "gn:population":0,
    "gn:timezone":"Asia/Kolkata",
    "iso:country":"IN",
    "wof:name":"Vairamangalam",
    "wof:placetype":"locality"
},
  "geometry": {"coordinates":[77.6156,11.45544],"type":"Point"}
}