{
  "type": "Feature",
  "properties": {
    "gn:admin1_code":"23.0",
    "gn:admin2_code":"36.0",
    "gn:asciiname":"Georgepur",
    "gn:country_code":"IN",
    "gn:dem":213,
    "gn:feature_class":"P",
    "gn:feature_code":"PPL",
    "gn:name":"Georgepur",
    "gn:population":0,
    "gn:timezone":"Asia/Kolkata",
    "iso:country":"IN",
    "name:und_x_variant":[
        "N\u0101nak B\u0101ra"
    ],
    "wof:name":"Georgepur",
    "wof:placetype":"neighbourhood"
},
  "geometry": {"coordinates":[75.24018,31.2675],"type":"Point"}
}