{
  "type": "Feature",
  "properties": {
    "iso:country":"IN",
    "name:ara_x_preferred":[
        "\u0643\u0627\u0645\u062a\u064a"
    ],
    "name:arz_x_preferred":[
        "\u0643\u0627\u0645\u062a\u0649"
    ],
    "name:ben_x_preferred":[
        "\u0995\u09be\u09ae\u09cd\u09aa\u099f\u09c7"
    ],
    "name:bpy_x_preferred":[
        "\u0995\u09be\u09ae\u09cd\u09aa\u099f\u09c7"
    ],
    "name:cat_x_preferred":[
        "Kamthi"
    ],
    "name:ceb_x_preferred":[
        "K\u0101mthi"
    ],
    "name:deu_x_preferred":[
        "Kamptee"
    ],
    "name:eng_x_preferred":[
        "Kamptee"
    ],
    "name:hin_x_preferred":[
        "\u0915\u093e\u092e\u0920\u0940"
    ],
    "name:ind_x_preferred":[
        "Kamptee"
    ],
    "name:ita_x_preferred":[
        "Kamptee"
    ],
    "name:mar_x_preferred":[
        "\u0915\u093e\u092e\u0920\u0940"
    ],
    "name:msa_x_preferred":[
        "Kamptee"
    ],
    "name:nan_x_preferred":[
        "Kamptee"
    ],
    "name:new_x_preferred":[
        "\u0915\u092e\u094d\u092a\u094d\u091f\u0940"
    ],
    "name:nld_x_preferred":[
        "Kamptee"
    ],
    "name:pnb_x_preferred":[
        "\u06a9\u0627\u0645\u0679\u06cc"
    ],
    "name:rus_x_preferred":[
        "\u041a\u0430\u043c\u043f\u0442\u0438"
    ],
    "name:spa_x_preferred":[
        "Kamptee"
    ],
    "name:swe_x_preferred":[
        "Kamptee"
    ],
    "name:tam_x_preferred":[
        "\u0b95\u0bbe\u0bae\u0bcd\u0b9f\u0bcd\u0b9f\u0bbf"
    ],
    "name:tha_x_preferred":[
        "\u0e01\u0e31\u0e21\u0e1b\u0e15\u0e35"
    ],
    "name:urd_x_preferred":[
        "\u06a9\u0627\u0645\u0679\u06cc"
    ],
    "name:vie_x_preferred":[
        "Kamptee"
    ],
    "name:war_x_preferred":[
        "Kamptee"
    ],
    "name:zho_x_preferred":[
        "\u5361\u59c6\u666e\u6cf0\u57c3"
    ],
    "qs:name":"Kamptee",
    "qs:name_adm0":"India",
    "qs:name_adm1":"Maharashtra",
    "qs:photos":29,
    "qs:photos_1k":6,
    "qs:photos_9k":1,
    "qs:photos_9r":2,
    "qs:photos_all":29,
    "qs:photos_sr":2,
    "qs:placetype":"Town",
    "qs:pop_sr":"0",
    "wd:wordcount":1459,
    "wof:name":"Kamptee",
    "wof:placetype":"neighbourhood"
},
  "geometry": {"coordinates":[79.203363,21.208195],"type":"Point"}
}