{
  "type": "Feature",
  "properties": {
    "gn:admin1_code":"36.0",
    "gn:admin2_code":"186.0",
    "gn:asciiname":"Mahdewa",
    "gn:country_code":"IN",
    "gn:dem":89,
    "gn:feature_class":"P",
    "gn:feature_code":"PPL",
    "gn:name":"M\u0101hdewa",
    "gn:population":0,
    "gn:timezone":"Asia/Kolkata",
    "iso:country":"IN",
    "wof:name":"Mahdewa",
    "wof:placetype":"locality"
},
  "geometry": {"coordinates":[82.98279000000002,27.00776],"type":"Point"}
}