{
  "type": "Feature",
  "properties": {
    "iso:country":"IN",
    "ks:ks_name":"Gangapur",
    "ks:ks_pop":463,
    "ks:ks_type":"HABITATION",
    "name:eng_x_preferred":[
        "Gangapur"
    ],
    "name:hin_x_preferred":[
        "\u0917\u0902\u0917\u093e\u092a\u0941\u0930"
    ],
    "wof:name":"Gangapur",
    "wof:placetype":"locality",
    "wof:population":463
},
  "geometry": {"coordinates":[80.995203,28.199792],"type":"Point"}
}