{
  "type": "Feature",
  "properties": {
    "gn:admin1_code":"39.0",
    "gn:admin2_code":"67.0",
    "gn:asciiname":"Hempur Ismail",
    "gn:country_code":"IN",
    "gn:dem":227,
    "gn:feature_class":"P",
    "gn:feature_code":"PPL",
    "gn:name":"Hempur Isma\u012bl",
    "gn:population":0,
    "gn:timezone":"Asia/Kolkata",
    "iso:country":"IN",
    "ks:ks_name":"Hempur Ismail",
    "ks:ks_pop":4832,
    "ks:ks_type":"VILLAGE",
    "ks:ks_uagg_main":0,
    "name:eng_x_preferred":[
        "Hempur Ismail"
    ],
    "wof:name":"Hempur Ismail",
    "wof:placetype":"locality",
    "wof:population":4832
},
  "geometry": {"coordinates":[78.998265,29.184133],"type":"Point"}
}