{
  "type": "Feature",
  "properties": {
    "iso:country":"IN",
    "ks:ks_name":"Ghujadih",
    "ks:ks_pop":490,
    "ks:ks_type":"VILLAGE",
    "ks:ks_uagg_main":0,
    "name:eng_x_preferred":[
        "Ghujadih"
    ],
    "wof:name":"Ghujadih",
    "wof:placetype":"neighbourhood",
    "wof:population":490
},
  "geometry": {"coordinates":[85.993224,24.002271],"type":"Point"}
}