{
  "type": "Feature",
  "properties": {
    "iso:country":"IN",
    "ks:ks_name":"Ogalasandha",
    "ks:ks_pop":8,
    "ks:ks_type":"HABITATION",
    "name:eng_x_preferred":[
        "Ogalasandha"
    ],
    "wof:name":"Ogalasandha",
    "wof:placetype":"locality",
    "wof:population":8
},
  "geometry": {"coordinates":[86.802633,20.596108],"type":"Point"}
}