{
  "type": "Feature",
  "properties": {
    "iso:country":"IN",
    "ks:ks_name":"Abhanga",
    "ks:ks_pop":4706,
    "ks:ks_type":"VILLAGE",
    "name:eng_x_preferred":[
        "Abhanga"
    ],
    "wof:name":"Abhanga",
    "wof:placetype":"locality",
    "wof:population":4706
},
  "geometry": {"coordinates":[91.81580099999999,24.052262],"type":"Point"}
}