{
  "type": "Feature",
  "properties": {
    "iso:country":"IN",
    "ks:ks_name":"Hanumantapura",
    "ks:ks_pop":102,
    "ks:ks_type":"VILLAGE",
    "name:eng_x_preferred":[
        "Hanumantapura"
    ],
    "wof:name":"Hanumantapura",
    "wof:placetype":"locality",
    "wof:population":102
},
  "geometry": {"coordinates":[76.951286,13.148189],"type":"Point"}
}