{
  "type": "Feature",
  "properties": {
    "iso:country":"IN",
    "ks:ks_name":"Hariharpura",
    "ks:ks_pop":150,
    "ks:ks_type":"VILLAGE",
    "name:eng_x_preferred":[
        "Hariharpura"
    ],
    "wof:name":"Hariharpura",
    "wof:placetype":"locality",
    "wof:population":150
},
  "geometry": {"coordinates":[76.42925700000001,11.92568],"type":"Point"}
}