{
  "type": "Feature",
  "properties": {
    "gn:admin1_code":"19",
    "gn:admin2_code":"568.0",
    "gn:asciiname":"Joladagudde",
    "gn:country_code":"IN",
    "gn:dem":565,
    "gn:feature_class":"P",
    "gn:feature_code":"PPL",
    "gn:name":"Joladagudde",
    "gn:population":0,
    "gn:timezone":"Asia/Kolkata",
    "iso:country":"IN",
    "ks:ks_name":"Joladagudde",
    "ks:ks_pop":12,
    "ks:ks_type":"HABITATION",
    "name:eng_x_preferred":[
        "Joladagudde"
    ],
    "wof:name":"Joladagudde",
    "wof:placetype":"locality",
    "wof:population":12
},
  "geometry": {"coordinates":[74.96744700000001,14.418963],"type":"Point"}
}