{
  "type": "Feature",
  "properties": {
    "gn:admin1_code":"36",
    "gn:admin2_code":"194.0",
    "gn:asciiname":"Chandapur",
    "gn:country_code":"IN",
    "gn:dem":93,
    "gn:feature_class":"P",
    "gn:feature_code":"PPL",
    "gn:name":"Chand\u0101pur",
    "gn:population":0,
    "gn:timezone":"Asia/Kolkata",
    "iso:country":"IN",
    "name:ben_x_preferred":[
        "\u099a\u09be\u09a8\u09cd\u09a6\u09be\u09aa\u09c1\u09b0"
    ],
    "name:bpy_x_preferred":[
        "\u099a\u09be\u09a8\u09cd\u09a6\u09be\u09aa\u09c1\u09b0"
    ],
    "name:ita_x_preferred":[
        "Chandapur"
    ],
    "name:msa_x_preferred":[
        "Chandapur"
    ],
    "name:new_x_preferred":[
        "\u091a\u0928\u094d\u0926\u093e\u092a\u0941\u0930"
    ],
    "name:nld_x_preferred":[
        "Chandapur"
    ],
    "name:por_x_preferred":[
        "Chandapur"
    ],
    "name:vie_x_preferred":[
        "Chandapur"
    ],
    "name:zho_x_preferred":[
        "\u94b1\u8fbe\u666e\u5c14"
    ],
    "wof:name":"Chandapur",
    "wof:placetype":"locality"
},
  "geometry": {"coordinates":[82.49209,25.94032],"type":"Point"}
}