{
  "type": "Feature",
  "properties": {
    "iso:country":"IN",
    "ks:ks_name":"Jatiagara",
    "ks:ks_pop":1410,
    "ks:ks_type":"VILLAGE",
    "name:eng_x_preferred":[
        "Jatiagara"
    ],
    "wof:name":"Jatiagara",
    "wof:placetype":"locality",
    "wof:population":1410
},
  "geometry": {"coordinates":[89.367321,26.090337],"type":"Point"}
}