{
  "type": "Feature",
  "properties": {
    "gn:admin1_code":"2.0",
    "gn:admin2_code":"543.0",
    "gn:asciiname":"Gadipallevalasa",
    "gn:country_code":"IN",
    "gn:dem":173,
    "gn:feature_class":"P",
    "gn:feature_code":"PPL",
    "gn:name":"G\u0101dipallevalasa",
    "gn:population":0,
    "gn:timezone":"Asia/Kolkata",
    "iso:country":"IN",
    "ks:ks_name":"Gadipellavalasa",
    "ks:ks_pop":64,
    "ks:ks_type":"HABITATION",
    "name:eng_x_preferred":[
        "Gadipellavalasa"
    ],
    "name:eng_x_variant":[
        "Gadipallevalasa"
    ],
    "wof:name":"Gadipellavalasa",
    "wof:placetype":"locality",
    "wof:population":64
},
  "geometry": {"coordinates":[83.17180500000001,18.664191],"type":"Point"}
}