{
  "type": "Feature",
  "properties": {
    "iso:country":"IN",
    "ks:ks_name":"Badabahal",
    "ks:ks_pop":243,
    "ks:ks_type":"VILLAGE",
    "name:eng_x_preferred":[
        "Badabahal"
    ],
    "wof:name":"Badabahal",
    "wof:placetype":"locality",
    "wof:population":243
},
  "geometry": {"coordinates":[83.724856,20.574007],"type":"Point"}
}