{
  "type": "Feature",
  "properties": {
    "iso:country":"IN",
    "ks:ks_alt_nam":"KORKAL GONDGUDA UP",
    "ks:ks_name":"Korkal Gondguda Up",
    "ks:ks_pop":265,
    "ks:ks_type":"HABITATION",
    "name:eng_x_preferred":[
        "Korkal Gondguda Up"
    ],
    "wof:name":"Korkal Gondguda Up",
    "wof:placetype":"locality",
    "wof:population":265
},
  "geometry": {"coordinates":[78.54500400000001,19.224377],"type":"Point"}
}