{
  "type": "Feature",
  "properties": {
    "iso:country":"IN",
    "ks:ks_name":"Reddypalem",
    "ks:ks_pop":103,
    "ks:ks_type":"HABITATION",
    "name:eng_x_preferred":[
        "Reddypalem"
    ],
    "wof:name":"Reddypalem",
    "wof:placetype":"locality",
    "wof:population":103
},
  "geometry": {"coordinates":[79.412826,15.363069],"type":"Point"}
}