{
  "type": "Feature",
  "properties": {
    "iso:country":"IN",
    "ks:ks_name":"Pirapader",
    "ks:ks_pop":43,
    "ks:ks_type":"HABITATION",
    "name:eng_x_preferred":[
        "Pirapader"
    ],
    "wof:name":"Pirapader",
    "wof:placetype":"locality",
    "wof:population":43
},
  "geometry": {"coordinates":[83.46662999999999,19.960609],"type":"Point"}
}