{
  "type": "Feature",
  "properties": {
    "iso:country":"IN",
    "ks:ks_name":"Isapur",
    "ks:ks_pop":1274,
    "ks:ks_type":"VILLAGE",
    "name:eng_x_preferred":[
        "Isapur"
    ],
    "wof:name":"Isapur",
    "wof:placetype":"locality",
    "wof:population":1274
},
  "geometry": {"coordinates":[77.147918,27.239113],"type":"Point"}
}