{
  "type": "Feature",
  "properties": {
    "iso:country":"IN",
    "ks:ks_name":"Baharmandpur",
    "ks:ks_pop":540,
    "ks:ks_type":"HABITATION",
    "name:eng_x_preferred":[
        "Baharmandpur"
    ],
    "wof:name":"Baharmandpur",
    "wof:placetype":"locality",
    "wof:population":540
},
  "geometry": {"coordinates":[77.49940100000001,30.184059],"type":"Point"}
}