{
  "type": "Feature",
  "properties": {
    "iso:country":"IN",
    "ks:ks_name":"Immanur",
    "ks:ks_pop":60,
    "ks:ks_type":"HABITATION",
    "ks:ks_uagg_main":0,
    "name:eng_x_preferred":[
        "Immanur"
    ],
    "wof:name":"Immanur",
    "wof:placetype":"neighbourhood",
    "wof:population":60
},
  "geometry": {"coordinates":[79.206976,14.120877],"type":"Point"}
}