{
  "type": "Feature",
  "properties": {
    "gn:admin1_code":"36",
    "gn:admin2_code":"191.0",
    "gn:asciiname":"Marufpur Hadi Ali",
    "gn:country_code":"IN",
    "gn:dem":84,
    "gn:feature_class":"P",
    "gn:feature_code":"PPL",
    "gn:name":"M\u0101r\u016bfpur H\u0101di Ali",
    "gn:population":0,
    "gn:timezone":"Asia/Kolkata",
    "iso:country":"IN",
    "wof:name":"Marufpur Hadi Ali",
    "wof:placetype":"locality"
},
  "geometry": {"coordinates":[83.06581,26.03245],"type":"Point"}
}