{
  "type": "Feature",
  "properties": {
    "iso:country":"IN",
    "ks:ks_name":"Moharda",
    "ks:ks_pop":359,
    "ks:ks_type":"VILLAGE",
    "name:eng_x_preferred":[
        "Moharda"
    ],
    "wof:name":"Moharda",
    "wof:placetype":"locality",
    "wof:population":359
},
  "geometry": {"coordinates":[75.18048899999999,20.268181],"type":"Point"}
}