{
  "type": "Feature",
  "properties": {
    "iso:country":"IN",
    "ks:ks_alt_nam":"VIJAY NAGAR",
    "ks:ks_name":"Vijay Nagar",
    "ks:ks_pop":150,
    "ks:ks_type":"HABITATION",
    "name:eng_x_preferred":[
        "Vijay Nagar"
    ],
    "wof:name":"Vijay Nagar",
    "wof:placetype":"locality",
    "wof:population":150
},
  "geometry": {"coordinates":[85.655213,24.913753],"type":"Point"}
}