{
  "type": "Feature",
  "properties": {
    "iso:country":"IN",
    "ks:ks_name":"Tetalia",
    "ks:ks_pop":2025,
    "ks:ks_type":"VILLAGE",
    "name:eng_x_preferred":[
        "Tetalia"
    ],
    "wof:name":"Tetalia",
    "wof:placetype":"locality",
    "wof:population":2025
},
  "geometry": {"coordinates":[87.803815,25.701999],"type":"Point"}
}