{
  "type": "Feature",
  "properties": {
    "gn:admin1_code":"34.0",
    "gn:admin2_code":"216.0",
    "gn:asciiname":"Malpur Agrail",
    "gn:country_code":"IN",
    "gn:dem":55,
    "gn:feature_class":"P",
    "gn:feature_code":"PPL",
    "gn:name":"M\u0101lpur Agrail",
    "gn:population":0,
    "gn:timezone":"Asia/Kolkata",
    "iso:country":"IN",
    "ks:ks_alt_nam":"M\u0101lpur Agrail",
    "ks:ks_name":"Malpur Agrail",
    "ks:ks_pop":1202,
    "ks:ks_type":"VILLAGE",
    "name:eng_x_preferred":[
        "Malpur Agrail"
    ],
    "name:eng_x_variant":[
        "M\u0101lpur Agrail"
    ],
    "wof:name":"Malpur Agrail",
    "wof:placetype":"locality",
    "wof:population":1202
},
  "geometry": {"coordinates":[85.616891,25.971976],"type":"Point"}
}