{
  "type": "Feature",
  "properties": {
    "iso:country":"IN",
    "ks:ks_name":"Marthanadi",
    "ks:ks_pop":350,
    "ks:ks_type":"HABITATION",
    "name:eng_x_preferred":[
        "Marthanadi"
    ],
    "wof:name":"Marthanadi",
    "wof:placetype":"locality",
    "wof:population":350
},
  "geometry": {"coordinates":[75.04524600000001,12.73206],"type":"Point"}
}