{
  "type": "Feature",
  "properties": {
    "iso:country":"IN",
    "ks:ks_name":"Vankamaddi",
    "ks:ks_pop":190,
    "ks:ks_type":"VILLAGE",
    "name:eng_x_preferred":[
        "Vankamaddi"
    ],
    "wof:name":"Vankamaddi",
    "wof:placetype":"locality",
    "wof:population":190
},
  "geometry": {"coordinates":[78.986953,19.27654],"type":"Point"}
}