{
  "type": "Feature",
  "properties": {
    "iso:country":"IN",
    "ks:ks_name":"Gularia",
    "ks:ks_pop":245,
    "ks:ks_type":"HABITATION",
    "name:eng_x_preferred":[
        "Gularia"
    ],
    "wof:name":"Gularia",
    "wof:placetype":"locality",
    "wof:population":245
},
  "geometry": {"coordinates":[78.54836,27.87626],"type":"Point"}
}