{
  "type": "Feature",
  "properties": {
    "gn:admin1_code":"23.0",
    "gn:admin2_code":"50.0",
    "gn:asciiname":"Deo",
    "gn:country_code":"IN",
    "gn:dem":231,
    "gn:feature_class":"P",
    "gn:feature_code":"PPL",
    "gn:name":"Deo",
    "gn:population":0,
    "gn:timezone":"Asia/Kolkata",
    "iso:country":"IN",
    "name:ceb_x_preferred":[
        "Deo"
    ],
    "name:deu_x_preferred":[
        "Deo"
    ],
    "name:nld_x_preferred":[
        "Deo"
    ],
    "name:swe_x_preferred":[
        "Deo"
    ],
    "wof:name":"Deo",
    "wof:placetype":"locality"
},
  "geometry": {"coordinates":[75.01319000000002,31.48727],"type":"Point"}
}