{
  "type": "Feature",
  "properties": {
    "iso:country":"IN",
    "ks:ks_alt_nam":"Ragunath Depha para",
    "ks:ks_name":"Ragunath Depha Para",
    "ks:ks_pop":173,
    "ks:ks_type":"HABITATION",
    "name:eng_x_preferred":[
        "Ragunath Depha Para"
    ],
    "wof:name":"Ragunath Depha Para",
    "wof:placetype":"locality",
    "wof:population":173
},
  "geometry": {"coordinates":[91.403559,23.399359],"type":"Point"}
}