{
  "type": "Feature",
  "properties": {
    "iso:country":"IN",
    "ks:ks_name":"Sc Colony",
    "ks:ks_pop":532,
    "ks:ks_type":"HABITATION",
    "name:eng_x_preferred":[
        "Sc Colony"
    ],
    "wof:name":"Sc Colony",
    "wof:placetype":"locality",
    "wof:population":532
},
  "geometry": {"coordinates":[76.88456100000001,9.083617],"type":"Point"}
}