{
  "type": "Feature",
  "properties": {
    "gn:admin1_code":"12",
    "gn:admin2_code":"14.0",
    "gn:asciiname":"Chithi Paibug",
    "gn:country_code":"IN",
    "gn:dem":1630,
    "gn:feature_class":"P",
    "gn:feature_code":"PPL",
    "gn:name":"Chithi P\u0101ibug",
    "gn:population":0,
    "gn:timezone":"Asia/Kolkata",
    "iso:country":"IN",
    "wof:name":"Chithi Paibug",
    "wof:placetype":"locality"
},
  "geometry": {"coordinates":[75.19933,33.7509],"type":"Point"}
}