{
  "type": "Feature",
  "properties": {
    "iso:country":"IN",
    "ks:ks_name":"Bheta Dhanik",
    "ks:ks_pop":50,
    "ks:ks_type":"VILLAGE",
    "name:eng_x_preferred":[
        "Bheta Dhanik"
    ],
    "wof:name":"Bheta Dhanik",
    "wof:placetype":"locality",
    "wof:population":50
},
  "geometry": {"coordinates":[80.247557,29.65599],"type":"Point"}
}