{
  "type": "Feature",
  "properties": {
    "iso:country":"IN",
    "ks:ks_name":"Hinjalgaria",
    "ks:ks_pop":221,
    "ks:ks_type":"VILLAGE",
    "name:eng_x_preferred":[
        "Hinjalgaria"
    ],
    "wof:name":"Hinjalgaria",
    "wof:placetype":"locality",
    "wof:population":221
},
  "geometry": {"coordinates":[86.653604,21.840966],"type":"Point"}
}