{
  "type": "Feature",
  "properties": {
    "iso:country":"IN",
    "ks:ks_name":"Shri Dawkhrwasti",
    "ks:ks_pop":333,
    "ks:ks_type":"HABITATION",
    "name:eng_x_preferred":[
        "Shri Dawkhrwasti"
    ],
    "wof:name":"Shri Dawkhrwasti",
    "wof:placetype":"locality",
    "wof:population":333
},
  "geometry": {"coordinates":[74.139143,19.189928],"type":"Point"}
}