{
  "type": "Feature",
  "properties": {
    "iso:country":"IN",
    "ks:ks_name":"Sindarpada Falia",
    "ks:ks_pop":280,
    "ks:ks_type":"HABITATION",
    "name:eng_x_preferred":[
        "Sindarpada Falia"
    ],
    "wof:name":"Sindarpada Falia",
    "wof:placetype":"locality",
    "wof:population":280
},
  "geometry": {"coordinates":[73.213111,20.272028],"type":"Point"}
}