{
  "type": "Feature",
  "properties": {
    "iso:country":"IN",
    "ks:ks_alt_nam":"Pitth\u016bw\u0101la",
    "ks:ks_name":"Pitthuwala",
    "ks:ks_pop":800,
    "ks:ks_type":"VILLAGE",
    "ks:ks_uagg_main":0,
    "name:eng_x_preferred":[
        "Pitthuwala"
    ],
    "name:eng_x_variant":[
        "Pitth\u016bw\u0101la"
    ],
    "wof:name":"Pitthuwala",
    "wof:placetype":"neighbourhood",
    "wof:population":800
},
  "geometry": {"coordinates":[77.98987,30.299614],"type":"Point"}
}