{
  "type": "Feature",
  "properties": {
    "gn:admin1_code":"13.0",
    "gn:admin2_code":"590.0",
    "gn:asciiname":"Valluvati",
    "gn:country_code":"IN",
    "gn:dem":890,
    "gn:feature_class":"P",
    "gn:feature_code":"PPL",
    "gn:name":"Valluv\u0101ti",
    "gn:population":0,
    "gn:timezone":"Asia/Kolkata",
    "iso:country":"IN",
    "wof:name":"Valluvati",
    "wof:placetype":"locality"
},
  "geometry": {"coordinates":[76.29973000000003,11.71212],"type":"Point"}
}