{
  "type": "Feature",
  "properties": {
    "iso:country":"IN",
    "ks:ks_name":"Badhai Tola",
    "ks:ks_pop":250,
    "ks:ks_type":"HABITATION",
    "name:eng_x_preferred":[
        "Badhai Tola"
    ],
    "wof:name":"Badhai Tola",
    "wof:placetype":"locality",
    "wof:population":250
},
  "geometry": {"coordinates":[83.76366899999999,26.949465],"type":"Point"}
}