{
  "type": "Feature",
  "properties": {
    "gn:admin1_code":"35.0",
    "gn:admin2_code":"456.0",
    "gn:asciiname":"Patan",
    "gn:country_code":"IN",
    "gn:dem":580,
    "gn:feature_class":"P",
    "gn:feature_code":"PPL",
    "gn:name":"P\u0101tan",
    "gn:population":0,
    "gn:timezone":"Asia/Kolkata",
    "iso:country":"IN",
    "name:ara_x_preferred":[
        "\u0628\u0627\u062a\u0627\u0646"
    ],
    "name:ben_bn_x_preferred":[
        "\u09aa\u09a4\u09a8"
    ],
    "name:ben_in_x_preferred":[
        "\u09aa\u09a4\u09a8"
    ],
    "name:bpy_x_preferred":[
        "\u09aa\u09be\u09a4\u09be\u09a8"
    ],
    "name:cat_x_preferred":[
        "Patan"
    ],
    "name:ceb_x_preferred":[
        "Patan"
    ],
    "name:ces_x_preferred":[
        "P\u00e1tan"
    ],
    "name:deu_x_preferred":[
        "Patan"
    ],
    "name:fin_x_preferred":[
        "Patan"
    ],
    "name:fra_x_preferred":[
        "Patan"
    ],
    "name:guj_x_preferred":[
        "\u0aaa\u0abe\u0a9f\u0aa3"
    ],
    "name:hin_x_preferred":[
        "\u092a\u093e\u091f\u0928"
    ],
    "name:ita_x_preferred":[
        "Patan"
    ],
    "name:kan_x_preferred":[
        "\u0caa\u0c9f\u0ca8\u0ccd"
    ],
    "name:mal_x_preferred":[
        "\u0d2a\u0d24\u0d4d\u0d24\u0d3e\u0d7b"
    ],
    "name:mar_x_preferred":[
        "\u092a\u093e\u091f\u0928"
    ],
    "name:new_x_preferred":[
        "\u092a\u093e\u091f\u0928"
    ],
    "name:nld_x_preferred":[
        "Patan"
    ],
    "name:pan_x_preferred":[
        "\u0a2a\u0a24\u0a23"
    ],
    "name:pol_x_preferred":[
        "Patan"
    ],
    "name:por_x_preferred":[
        "Patan"
    ],
    "name:spa_x_preferred":[
        "Patan"
    ],
    "name:swe_x_preferred":[
        "Patan"
    ],
    "name:tam_x_preferred":[
        "\u0baa\u0b9f\u0bbe\u0ba9\u0bcd"
    ],
    "name:tel_x_preferred":[
        "\u0c2a\u0c3e\u0c1f\u0c28\u0c4d"
    ],
    "name:urd_x_preferred":[
        "\u067e\u0679\u0646"
    ],
    "wof:name":"Patan",
    "wof:placetype":"locality"
},
  "geometry": {"coordinates":[80.19794,22.69944],"type":"Point"}
}