{
  "type": "Feature",
  "properties": {
    "iso:country":"IN",
    "ks:ks_name":"Jeedimanipalle",
    "ks:ks_pop":171,
    "ks:ks_type":"HABITATION",
    "name:eng_x_preferred":[
        "Jeedimanipalle"
    ],
    "wof:name":"Jeedimanipalle",
    "wof:placetype":"locality",
    "wof:population":171
},
  "geometry": {"coordinates":[78.40779499999999,12.8489],"type":"Point"}
}