{
  "type": "Feature",
  "properties": {
    "gn:admin1_code":"36",
    "gn:admin2_code":"191.0",
    "gn:asciiname":"Mahipalpur",
    "gn:country_code":"IN",
    "gn:dem":86,
    "gn:feature_class":"P",
    "gn:feature_code":"PPL",
    "gn:name":"Mahip\u0101lpur",
    "gn:population":0,
    "gn:timezone":"Asia/Kolkata",
    "iso:country":"IN",
    "name:ara_x_preferred":[
        "\u0645\u0627\u0647\u064a\u0628\u0627\u0644\u0628\u0648\u0631"
    ],
    "name:ben_bn_x_preferred":[
        "\u09ae\u09b9\u09bf\u09aa\u09be\u09b2\u09aa\u09c1\u09b0"
    ],
    "name:ben_in_x_preferred":[
        "\u09ae\u09b9\u09bf\u09aa\u09be\u09b2\u09aa\u09c1\u09b0"
    ],
    "name:guj_x_preferred":[
        "\u0aae\u0ab9\u0abf\u0aaa\u0abe\u0ab2\u0aaa\u0ac1\u0ab0"
    ],
    "name:hin_x_preferred":[
        "\u092e\u0939\u093f\u092a\u093e\u0932\u092a\u0941\u0930"
    ],
    "name:kan_x_preferred":[
        "\u0cae\u0cb9\u0cbf\u0caa\u0cbe\u0cb2\u0ccd"
    ],
    "name:mal_x_preferred":[
        "\u0d2e\u0d39\u0d3f\u0d2a\u0d3e\u0d7d\u0d2a\u0d42\u0d7c"
    ],
    "name:mar_x_preferred":[
        "\u092e\u0939\u093f\u092a\u093e\u0932\u092a\u0942\u0930"
    ],
    "name:pan_x_preferred":[
        "\u0a2e\u0a39\u0a40\u0a2a\u0a3e\u0a32\u0a2a\u0a41\u0a30"
    ],
    "name:tam_x_preferred":[
        "\u0bae\u0bb9\u0bbf\u0baa\u0bbe\u0bb2\u0bcd\u0baa\u0bc2\u0bb0\u0bcd"
    ],
    "name:tel_x_preferred":[
        "\u0c2e\u0c39\u0c3f\u0c2a\u0c3e\u0c32\u0c4d\u0c2a\u0c42\u0c30\u0c4d"
    ],
    "name:urd_x_preferred":[
        "\u0645\u06c1\u06cc\u067e\u0627\u0644 \u067e\u0648\u0631"
    ],
    "wof:name":"Mahipalpur",
    "wof:placetype":"neighbourhood"
},
  "geometry": {"coordinates":[82.94302,26.16627],"type":"Point"}
}