{
  "type": "Feature",
  "properties": {
    "iso:country":"IN",
    "ks:ks_name":"No.1 Uttar Kathani",
    "ks:ks_pop":467,
    "ks:ks_type":"VILLAGE",
    "name:eng_x_preferred":[
        "No.1 Uttar Kathani"
    ],
    "wof:name":"No.1 Uttar Kathani",
    "wof:placetype":"locality",
    "wof:population":467
},
  "geometry": {"coordinates":[93.79192,26.935135],"type":"Point"}
}