{
  "type": "Feature",
  "properties": {
    "gn:admin1_code":"2",
    "gn:admin2_code":"545.0",
    "gn:asciiname":"Tankalgadda",
    "gn:country_code":"IN",
    "gn:dem":600,
    "gn:feature_class":"P",
    "gn:feature_code":"PPL",
    "gn:name":"Tankalgadda",
    "gn:population":0,
    "gn:timezone":"Asia/Kolkata",
    "iso:country":"IN",
    "wof:name":"Tankalgadda",
    "wof:placetype":"locality"
},
  "geometry": {"coordinates":[81.78945,17.65446],"type":"Point"}
}