{
  "type": "Feature",
  "properties": {
    "iso:country":"IN",
    "ks:ks_name":"Miroli",
    "ks:ks_pop":39,
    "ks:ks_type":"VILLAGE",
    "name:eng_x_preferred":[
        "Miroli"
    ],
    "wof:name":"Miroli",
    "wof:placetype":"locality",
    "wof:population":39
},
  "geometry": {"coordinates":[79.2067,30.165335],"type":"Point"}
}