{
  "type": "Feature",
  "properties": {
    "iso:country":"IN",
    "ks:ks_name":"Simri Khurd",
    "ks:ks_pop":225,
    "ks:ks_type":"HABITATION",
    "name:eng_x_preferred":[
        "Simri Khurd"
    ],
    "wof:name":"Simri Khurd",
    "wof:placetype":"locality",
    "wof:population":225
},
  "geometry": {"coordinates":[79.896508,24.168166],"type":"Point"}
}