{
  "type": "Feature",
  "properties": {
    "iso:country":"IN",
    "ks:ks_name":"Bhbhutinath",
    "ks:ks_pop":15,
    "ks:ks_type":"HABITATION",
    "name:eng_x_preferred":[
        "Bhbhutinath"
    ],
    "wof:name":"Bhbhutinath",
    "wof:placetype":"locality",
    "wof:population":15
},
  "geometry": {"coordinates":[82.054461,27.618274],"type":"Point"}
}