{
  "type": "Feature",
  "properties": {
    "gn:admin1_code":"36.0",
    "gn:admin2_code":"192.0",
    "gn:asciiname":"Babu Lal",
    "gn:country_code":"IN",
    "gn:dem":76,
    "gn:feature_class":"P",
    "gn:feature_code":"PPL",
    "gn:name":"Babu Lal",
    "gn:population":0,
    "gn:timezone":"Asia/Kolkata",
    "iso:country":"IN",
    "wof:name":"Babu Lal",
    "wof:placetype":"locality"
},
  "geometry": {"coordinates":[83.72211999999998,26.2335],"type":"Point"}
}