{
  "type": "Feature",
  "properties": {
    "iso:country":"IN",
    "ks:ks_name":"Bahera 1",
    "ks:ks_pop":864,
    "ks:ks_type":"HABITATION",
    "name:eng_x_preferred":[
        "Bahera 1"
    ],
    "wof:name":"Bahera 1",
    "wof:placetype":"locality",
    "wof:population":864
},
  "geometry": {"coordinates":[82.850505,24.798426],"type":"Point"}
}