{
  "type": "Feature",
  "properties": {
    "gn:admin1_code":"28.0",
    "gn:admin2_code":"334.0",
    "gn:asciiname":"Raypur",
    "gn:country_code":"IN",
    "gn:dem":33,
    "gn:feature_class":"P",
    "gn:feature_code":"PPL",
    "gn:name":"R\u0101ypur",
    "gn:population":0,
    "gn:timezone":"Asia/Kolkata",
    "iso:country":"IN",
    "wof:name":"Raypur",
    "wof:placetype":"locality"
},
  "geometry": {"coordinates":[87.95189000000001,24.24601],"type":"Point"}
}