{
  "type": "Feature",
  "properties": {
    "gn:admin1_code":"2",
    "gn:admin2_code":"545.0",
    "gn:asciiname":"Palagondi",
    "gn:country_code":"IN",
    "gn:dem":822,
    "gn:feature_class":"P",
    "gn:feature_code":"PPL",
    "gn:name":"P\u0101lagondi",
    "gn:population":0,
    "gn:timezone":"Asia/Kolkata",
    "iso:country":"IN",
    "wof:name":"Palagondi",
    "wof:placetype":"locality"
},
  "geometry": {"coordinates":[81.93814999999999,17.90038999999999],"type":"Point"}
}