{
  "type": "Feature",
  "properties": {
    "iso:country":"IN",
    "ks:ks_name":"Kashibari",
    "ks:ks_pop":562,
    "ks:ks_type":"HABITATION",
    "name:eng_x_preferred":[
        "Kashibari"
    ],
    "wof:name":"Kashibari",
    "wof:placetype":"locality",
    "wof:population":562
},
  "geometry": {"coordinates":[90.287791,26.423597],"type":"Point"}
}