{
  "type": "Feature",
  "properties": {
    "iso:country":"IN",
    "ks:ks_name":"Kutenpani R.F",
    "ks:ks_pop":79,
    "ks:ks_type":"VILLAGE",
    "name:eng_x_preferred":[
        "Kutenpani R.F"
    ],
    "wof:name":"Kutenpani R.F",
    "wof:placetype":"locality",
    "wof:population":79
},
  "geometry": {"coordinates":[83.950909,22.189127],"type":"Point"}
}