{
  "type": "Feature",
  "properties": {
    "gn:admin1_code":"35.0",
    "gn:admin2_code":"419.0",
    "gn:asciiname":"Theha",
    "gn:country_code":"IN",
    "gn:dem":205,
    "gn:feature_class":"P",
    "gn:feature_code":"PPL",
    "gn:name":"Theha",
    "gn:population":0,
    "gn:timezone":"Asia/Kolkata",
    "iso:country":"IN",
    "ks:ks_name":"Theha",
    "ks:ks_type":"VILLAGE",
    "name:eng_x_preferred":[
        "Theha"
    ],
    "wof:name":"Theha",
    "wof:placetype":"locality"
},
  "geometry": {"coordinates":[77.90675,26.296169],"type":"Point"}
}