{
  "type": "Feature",
  "properties": {
    "iso:country":"IN",
    "ks:ks_name":"Harehole",
    "ks:ks_pop":295,
    "ks:ks_type":"HABITATION",
    "name:eng_x_preferred":[
        "Harehole"
    ],
    "wof:name":"Harehole",
    "wof:placetype":"locality",
    "wof:population":295
},
  "geometry": {"coordinates":[75.880556,12.508889],"type":"Point"}
}