{
  "type": "Feature",
  "properties": {
    "iso:country":"IN",
    "ks:ks_name":"Kattudevadur",
    "ks:ks_pop":500,
    "ks:ks_type":"HABITATION",
    "name:eng_x_preferred":[
        "Kattudevadur"
    ],
    "wof:name":"Kattudevadur",
    "wof:placetype":"locality",
    "wof:population":500
},
  "geometry": {"coordinates":[79.934089,12.416731],"type":"Point"}
}