{
  "type": "Feature",
  "properties": {
    "gn:admin1_code":"35.0",
    "gn:admin2_code":"426.0",
    "gn:asciiname":"Mahilwara",
    "gn:country_code":"IN",
    "gn:dem":407,
    "gn:feature_class":"P",
    "gn:feature_code":"PPL",
    "gn:name":"Mahilw\u0101ra",
    "gn:population":0,
    "gn:timezone":"Asia/Kolkata",
    "iso:country":"IN",
    "wof:name":"Mahilwara",
    "wof:placetype":"locality"
},
  "geometry": {"coordinates":[80.24739,23.96032],"type":"Point"}
}