{
  "type": "Feature",
  "properties": {
    "gn:admin1_code":"13",
    "gn:admin2_code":"592.0",
    "gn:asciiname":"Kulattur",
    "gn:country_code":"IN",
    "gn:dem":38,
    "gn:feature_class":"P",
    "gn:feature_code":"PPL",
    "gn:name":"Kulatt\u016br",
    "gn:population":0,
    "gn:timezone":"Asia/Kolkata",
    "iso:country":"IN",
    "wof:name":"Kulattur",
    "wof:placetype":"neighbourhood"
},
  "geometry": {"coordinates":[76.14605,10.94124],"type":"Point"}
}