{
  "type": "Feature",
  "properties": {
    "iso:country":"IN",
    "ks:ks_name":"Burbuda",
    "ks:ks_pop":180,
    "ks:ks_type":"VILLAGE",
    "name:eng_x_preferred":[
        "Burbuda"
    ],
    "wof:name":"Burbuda",
    "wof:placetype":"locality",
    "wof:population":180
},
  "geometry": {"coordinates":[84.71672,21.345135],"type":"Point"}
}