{
  "type": "Feature",
  "properties": {
    "iso:country":"IN",
    "ks:ks_alt_nam":"BHUIYANTOLA",
    "ks:ks_name":"Bhuiyantola",
    "ks:ks_pop":591,
    "ks:ks_type":"HABITATION",
    "ks:ks_uagg_main":0,
    "name:eng_x_preferred":[
        "Bhuiyantola"
    ],
    "wof:name":"Bhuiyantola",
    "wof:placetype":"neighbourhood",
    "wof:population":591
},
  "geometry": {"coordinates":[85.22348100000001,24.362228],"type":"Point"}
}