{
  "type": "Feature",
  "properties": {
    "iso:country":"IN",
    "ks:ks_name":"Mase Nakhawa",
    "ks:ks_pop":231,
    "ks:ks_type":"HABITATION",
    "name:eng_x_preferred":[
        "Mase Nakhawa"
    ],
    "wof:name":"Mase Nakhawa",
    "wof:placetype":"locality",
    "wof:population":231
},
  "geometry": {"coordinates":[91.09496300000001,26.014129],"type":"Point"}
}