{
  "type": "Feature",
  "properties": {
    "iso:country":"IN",
    "ks:ks_name":"Gautia Bairamnagar",
    "ks:ks_pop":318,
    "ks:ks_type":"HABITATION",
    "name:eng_x_preferred":[
        "Gautia Bairamnagar"
    ],
    "wof:name":"Gautia Bairamnagar",
    "wof:placetype":"locality",
    "wof:population":318
},
  "geometry": {"coordinates":[79.322028,28.651685],"type":"Point"}
}