{
  "type": "Feature",
  "properties": {
    "iso:country":"IN",
    "ks:ks_name":"Kendua",
    "ks:ks_pop":112,
    "ks:ks_type":"VILLAGE",
    "name:eng_x_preferred":[
        "Kendua"
    ],
    "wof:name":"Kendua",
    "wof:placetype":"locality",
    "wof:population":112
},
  "geometry": {"coordinates":[86.339386,22.222874],"type":"Point"}
}