{
  "type": "Feature",
  "properties": {
    "iso:country":"IN",
    "ks:ks_name":"Sosidal",
    "ks:ks_pop":344,
    "ks:ks_type":"HABITATION",
    "name:eng_x_preferred":[
        "Sosidal"
    ],
    "wof:name":"Sosidal",
    "wof:placetype":"locality",
    "wof:population":344
},
  "geometry": {"coordinates":[86.766541,24.861382],"type":"Point"}
}