{
  "type": "Feature",
  "properties": {
    "gn:admin1_code":"35",
    "gn:admin2_code":"456.0",
    "gn:asciiname":"Dhuria",
    "gn:country_code":"IN",
    "gn:dem":543,
    "gn:feature_class":"P",
    "gn:feature_code":"PPL",
    "gn:name":"Dhuria",
    "gn:population":0,
    "gn:timezone":"Asia/Kolkata",
    "iso:country":"IN",
    "wof:name":"Dhuria",
    "wof:placetype":"neighbourhood"
},
  "geometry": {"coordinates":[79.55641,22.52286],"type":"Point"}
}