{
  "type": "Feature",
  "properties": {
    "iso:country":"IN",
    "ks:ks_name":"Mangaon",
    "ks:ks_pop":305,
    "ks:ks_type":"VILLAGE",
    "name:eng_x_preferred":[
        "Mangaon"
    ],
    "wof:name":"Mangaon",
    "wof:placetype":"locality",
    "wof:population":305
},
  "geometry": {"coordinates":[73.50547400000001,18.325768],"type":"Point"}
}