{
  "type": "Feature",
  "properties": {
    "iso:country":"IN",
    "ks:ks_name":"Chamthar Gaon",
    "ks:ks_pop":92,
    "ks:ks_type":"VILLAGE",
    "name:eng_x_preferred":[
        "Chamthar Gaon"
    ],
    "wof:name":"Chamthar Gaon",
    "wof:placetype":"locality",
    "wof:population":92
},
  "geometry": {"coordinates":[78.337098,30.348727],"type":"Point"}
}