{
  "type": "Feature",
  "properties": {
    "iso:country":"IN",
    "ks:ks_name":"Ramgadewadi",
    "ks:ks_pop":102,
    "ks:ks_type":"HABITATION",
    "name:eng_x_preferred":[
        "Ramgadewadi"
    ],
    "wof:name":"Ramgadewadi",
    "wof:placetype":"locality",
    "wof:population":102
},
  "geometry": {"coordinates":[73.288939,17.331897],"type":"Point"}
}