{
  "type": "Feature",
  "properties": {
    "iso:country":"IN",
    "ks:ks_name":"Hati Khali No.2",
    "ks:ks_pop":187,
    "ks:ks_type":"HABITATION",
    "name:eng_x_preferred":[
        "Hati Khali No.2"
    ],
    "wof:name":"Hati Khali No.2",
    "wof:placetype":"locality",
    "wof:population":187
},
  "geometry": {"coordinates":[93.13650800000001,25.771399],"type":"Point"}
}