{
  "type": "Feature",
  "properties": {
    "iso:country":"IN",
    "ks:ks_name":"Dhuansahi",
    "ks:ks_pop":429,
    "ks:ks_type":"VILLAGE",
    "name:eng_x_preferred":[
        "Dhuansahi"
    ],
    "wof:name":"Dhuansahi",
    "wof:placetype":"locality",
    "wof:population":429
},
  "geometry": {"coordinates":[86.42202,20.23559],"type":"Point"}
}