{
  "type": "Feature",
  "properties": {
    "gn:admin1_code":"12.0",
    "gn:admin2_code":"005",
    "gn:asciiname":"Bagiot Dora",
    "gn:country_code":"IN",
    "gn:dem":1301,
    "gn:feature_class":"P",
    "gn:feature_code":"PPL",
    "gn:name":"Bagiot Dora",
    "gn:population":0,
    "gn:timezone":"Asia/Kolkata",
    "iso:country":"IN",
    "name:und_x_variant":[
        "Bagi\u0101l Dara"
    ],
    "wof:name":"Bagiot Dora",
    "wof:placetype":"locality"
},
  "geometry": {"coordinates":[74.09773,33.81279],"type":"Point"}
}