{
  "type": "Feature",
  "properties": {
    "iso:country":"IN",
    "ks:ks_name":"Nazareth",
    "ks:ks_pop":58,
    "ks:ks_type":"HABITATION",
    "name:eng_x_preferred":[
        "Nazareth"
    ],
    "wof:name":"Nazareth",
    "wof:placetype":"locality",
    "wof:population":58
},
  "geometry": {"coordinates":[93.633128,26.109551],"type":"Point"}
}