{
  "type": "Feature",
  "properties": {
    "gn:admin1_code":"11",
    "gn:admin2_code":"30.0",
    "gn:asciiname":"Sehri",
    "gn:country_code":"IN",
    "gn:dem":1099,
    "gn:feature_class":"P",
    "gn:feature_code":"PPL",
    "gn:name":"Sehri",
    "gn:population":0,
    "gn:timezone":"Asia/Kolkata",
    "iso:country":"IN",
    "name:ara_x_preferred":[
        "\u0633\u062d\u0631\u064a"
    ],
    "name:fas_x_preferred":[
        "\u0633\u0647\u0631\u06cc"
    ],
    "name:mzn_x_preferred":[
        "\u0633\u0647\u0631\u06cc"
    ],
    "name:ukr_x_preferred":[
        "\u0421\u0435\u0433\u0440\u0456"
    ],
    "wof:name":"Sehri",
    "wof:placetype":"locality"
},
  "geometry": {"coordinates":[76.80341,31.34527000000001],"type":"Point"}
}