{
  "type": "Feature",
  "properties": {
    "gn:admin1_code":"36",
    "gn:admin2_code":"135.0",
    "gn:asciiname":"Rajaura Kannar Deo",
    "gn:country_code":"IN",
    "gn:dem":187,
    "gn:feature_class":"P",
    "gn:feature_code":"PPL",
    "gn:name":"Rajaura Kannar Deo",
    "gn:population":0,
    "gn:timezone":"Asia/Kolkata",
    "iso:country":"IN",
    "ks:ks_name":"Rajaura Kannar Deo",
    "ks:ks_type":"VILLAGE",
    "name:eng_x_preferred":[
        "Rajaura Kannar Deo"
    ],
    "wof:name":"Rajaura Kannar Deo",
    "wof:placetype":"locality"
},
  "geometry": {"coordinates":[78.938289,28.763996],"type":"Point"}
}