{
  "type": "Feature",
  "properties": {
    "iso:country":"IN",
    "ks:ks_name":"Budhikutuni",
    "ks:ks_pop":351,
    "ks:ks_type":"VILLAGE",
    "name:eng_x_preferred":[
        "Budhikutuni"
    ],
    "wof:name":"Budhikutuni",
    "wof:placetype":"locality",
    "wof:population":351
},
  "geometry": {"coordinates":[84.218643,21.416052],"type":"Point"}
}