{
  "type": "Feature",
  "properties": {
    "iso:country":"IN",
    "ks:ks_name":"Kelaginamoodkani",
    "ks:ks_pop":40,
    "ks:ks_type":"HABITATION",
    "name:eng_x_preferred":[
        "Kelaginamoodkani"
    ],
    "wof:name":"Kelaginamoodkani",
    "wof:placetype":"locality",
    "wof:population":40
},
  "geometry": {"coordinates":[74.541473,14.238733],"type":"Point"}
}