{
  "type": "Feature",
  "properties": {
    "iso:country":"IN",
    "ks:ks_name":"Fansapur",
    "ks:ks_pop":450,
    "ks:ks_type":"HABITATION",
    "ks:ks_uagg_main":0,
    "name:eng_x_preferred":[
        "Fansapur"
    ],
    "wof:name":"Fansapur",
    "wof:placetype":"neighbourhood",
    "wof:population":450
},
  "geometry": {"coordinates":[72.98185100000001,18.563395],"type":"Point"}
}