{
  "type": "Feature",
  "properties": {
    "iso:country":"IN",
    "ks:ks_name":"Lingdoba",
    "ks:ks_pop":752,
    "ks:ks_type":"VILLAGE",
    "name:eng_x_preferred":[
        "Lingdoba"
    ],
    "wof:name":"Lingdoba",
    "wof:placetype":"locality",
    "wof:population":752
},
  "geometry": {"coordinates":[90.448148,26.354101],"type":"Point"}
}