{
  "type": "Feature",
  "properties": {
    "iso:country":"IN",
    "ks:ks_name":"Rajgarh",
    "ks:ks_pop":256,
    "ks:ks_type":"HABITATION",
    "name:eng_x_preferred":[
        "Rajgarh"
    ],
    "name:hin_x_preferred":[
        "\u0930\u093e\u091c\u0917\u0922\u093c"
    ],
    "wof:name":"Rajgarh",
    "wof:placetype":"locality",
    "wof:population":256
},
  "geometry": {"coordinates":[72.567239,26.414569],"type":"Point"}
}