{
  "type": "Feature",
  "properties": {
    "gn:admin1_code":"35.0",
    "gn:admin2_code":"457.0",
    "gn:asciiname":"Chillod",
    "gn:country_code":"IN",
    "gn:dem":310,
    "gn:feature_class":"P",
    "gn:feature_code":"PPL",
    "gn:name":"Chillod",
    "gn:population":0,
    "gn:timezone":"Asia/Kolkata",
    "iso:country":"IN",
    "ks:ks_name":"Chillod",
    "ks:ks_pop":2311,
    "ks:ks_type":"VILLAGE",
    "name:eng_x_preferred":[
        "Chillod"
    ],
    "wof:name":"Chillod",
    "wof:placetype":"locality",
    "wof:population":2311
},
  "geometry": {"coordinates":[80.08217999999999,21.8291],"type":"Point"}
}