{
  "type": "Feature",
  "properties": {
    "iso:country":"IN",
    "ks:ks_name":"Pure Kunjal",
    "ks:ks_pop":143,
    "ks:ks_type":"HABITATION",
    "ks:ks_uagg_main":0,
    "name:eng_x_preferred":[
        "Pure Kunjal"
    ],
    "wof:name":"Pure Kunjal",
    "wof:placetype":"neighbourhood",
    "wof:population":143
},
  "geometry": {"coordinates":[81.41596699999999,26.157947],"type":"Point"}
}