{
  "type": "Feature",
  "properties": {
    "iso:country":"IN",
    "ks:ks_name":"Udiadihi",
    "ks:ks_pop":165,
    "ks:ks_type":"HABITATION",
    "name:eng_x_preferred":[
        "Udiadihi"
    ],
    "wof:name":"Udiadihi",
    "wof:placetype":"locality",
    "wof:population":165
},
  "geometry": {"coordinates":[84.143224,22.235916],"type":"Point"}
}