{
  "type": "Feature",
  "properties": {
    "iso:country":"IN",
    "ks:ks_name":"Ekalamasni",
    "ks:ks_pop":578,
    "ks:ks_type":"HABITATION",
    "name:eng_x_preferred":[
        "Ekalamasni"
    ],
    "wof:name":"Ekalamasni",
    "wof:placetype":"locality",
    "wof:population":578
},
  "geometry": {"coordinates":[78.42740999999999,22.251121],"type":"Point"}
}