{
  "type": "Feature",
  "properties": {
    "iso:country":"IN",
    "ks:ks_name":"Gareeya",
    "ks:ks_pop":152,
    "ks:ks_type":"VILLAGE",
    "name:eng_x_preferred":[
        "Gareeya"
    ],
    "wof:name":"Gareeya",
    "wof:placetype":"locality",
    "wof:population":152
},
  "geometry": {"coordinates":[74.008499,23.500724],"type":"Point"}
}