{
  "type": "Feature",
  "properties": {
    "iso:country":"IN",
    "ks:ks_name":"Punghat Kala",
    "ks:ks_pop":465,
    "ks:ks_type":"HABITATION",
    "name:eng_x_preferred":[
        "Punghat Kala"
    ],
    "wof:name":"Punghat Kala",
    "wof:placetype":"locality",
    "wof:population":465
},
  "geometry": {"coordinates":[76.775272,22.307883],"type":"Point"}
}