{
  "type": "Feature",
  "properties": {
    "iso:country":"IN",
    "ks:ks_name":"Sundartaila",
    "ks:ks_pop":105,
    "ks:ks_type":"HABITATION",
    "name:eng_x_preferred":[
        "Sundartaila"
    ],
    "wof:name":"Sundartaila",
    "wof:placetype":"locality",
    "wof:population":105
},
  "geometry": {"coordinates":[84.758504,20.246448],"type":"Point"}
}