{
  "type": "Feature",
  "properties": {
    "iso:country":"IN",
    "ks:ks_name":"Dakhin Mahiakhat",
    "ks:ks_pop":323,
    "ks:ks_type":"HABITATION",
    "ks:ks_uagg_main":0,
    "name:eng_x_preferred":[
        "Dakhin Mahiakhat"
    ],
    "wof:name":"Dakhin Mahiakhat",
    "wof:placetype":"neighbourhood",
    "wof:population":323
},
  "geometry": {"coordinates":[91.828063,26.619539],"type":"Point"}
}