{
  "type": "Feature",
  "properties": {
    "gn:admin1_code":"35.0",
    "gn:admin2_code":"431.0",
    "gn:asciiname":"Tikura Kathai",
    "gn:country_code":"IN",
    "gn:dem":480,
    "gn:feature_class":"P",
    "gn:feature_code":"PPL",
    "gn:name":"Tikura Kathai",
    "gn:population":0,
    "gn:timezone":"Asia/Kolkata",
    "iso:country":"IN",
    "ks:ks_name":"Tikura Kathai",
    "ks:ks_pop":361,
    "ks:ks_type":"VILLAGE",
    "name:eng_x_preferred":[
        "Tikura Kathai"
    ],
    "wof:name":"Tikura Kathai",
    "wof:placetype":"locality",
    "wof:population":361
},
  "geometry": {"coordinates":[80.727874,23.532713],"type":"Point"}
}