{
  "type": "Feature",
  "properties": {
    "gn:admin1_code":"35.0",
    "gn:admin2_code":"431.0",
    "gn:asciiname":"Tikura Kathai",
    "gn:country_code":"IN",
    "gn:dem":480,
    "gn:feature_class":"P",
    "gn:feature_code":"PPL",
    "gn:name":"Tikura Kathai",
    "gn:population":0,
    "gn:timezone":"Asia/Kolkata",
    "iso:country":"IN",
    "wof:name":"Tikura Kathai",
    "wof:placetype":"locality"
},
  "geometry": {"coordinates":[80.72829,23.53276],"type":"Point"}
}