{
  "type": "Feature",
  "properties": {
    "iso:country":"IN",
    "ks:ks_name":"Ghogopadar",
    "ks:ks_pop":187,
    "ks:ks_type":"VILLAGE",
    "name:eng_x_preferred":[
        "Ghogopadar"
    ],
    "wof:name":"Ghogopadar",
    "wof:placetype":"locality",
    "wof:population":187
},
  "geometry": {"coordinates":[83.644633,19.59241],"type":"Point"}
}