{
  "type": "Feature",
  "properties": {
    "gn:admin1_code":"36",
    "gn:admin2_code":"161.0",
    "gn:asciiname":"Dabha",
    "gn:country_code":"IN",
    "gn:dem":151,
    "gn:feature_class":"P",
    "gn:feature_code":"PPL",
    "gn:name":"Dabha",
    "gn:population":0,
    "gn:timezone":"Asia/Kolkata",
    "iso:country":"IN",
    "wof:name":"Dabha",
    "wof:placetype":"neighbourhood"
},
  "geometry": {"coordinates":[78.97624,26.72144],"type":"Point"}
}