{
  "type": "Feature",
  "properties": {
    "iso:country":"IN",
    "ks:ks_name":"Rampur",
    "ks:ks_pop":6700,
    "ks:ks_type":"HABITATION",
    "ks:ks_uagg_main":0,
    "name:eng_x_preferred":[
        "Rampur"
    ],
    "wof:name":"Rampur",
    "wof:placetype":"neighbourhood",
    "wof:population":6700
},
  "geometry": {"coordinates":[85.51983,26.25574],"type":"Point"}
}