{
  "type": "Feature",
  "properties": {
    "gn:admin1_code":"10.0",
    "gn:admin2_code":"082",
    "gn:asciiname":"Garhi Sampla",
    "gn:country_code":"IN",
    "gn:dem":220,
    "gn:feature_class":"P",
    "gn:feature_code":"PPL",
    "gn:name":"Garhi S\u0101mpla",
    "gn:population":0,
    "gn:timezone":"Asia/Kolkata",
    "iso:country":"IN",
    "wof:name":"Garhi Sampla",
    "wof:placetype":"locality"
},
  "geometry": {"coordinates":[76.77186,28.76084],"type":"Point"}
}