{
  "type": "Feature",
  "properties": {
    "gn:admin1_code":"12.0",
    "gn:asciiname":"Dalori",
    "gn:country_code":"IN",
    "gn:dem":599,
    "gn:feature_class":"P",
    "gn:feature_code":"PPL",
    "gn:name":"Dalori",
    "gn:population":0,
    "gn:timezone":"Asia/Kolkata",
    "iso:country":"IN",
    "name:hau_x_preferred":[
        "Dalori"
    ],
    "wof:name":"Dalori",
    "wof:placetype":"locality"
},
  "geometry": {"coordinates":[74.20591,33.14775],"type":"Point"}
}