{
  "type": "Feature",
  "properties": {
    "iso:country":"IN",
    "ks:ks_name":"Alijad",
    "ks:ks_pop":338,
    "ks:ks_type":"HABITATION",
    "name:eng_x_preferred":[
        "Alijad"
    ],
    "wof:name":"Alijad",
    "wof:placetype":"locality",
    "wof:population":338
},
  "geometry": {"coordinates":[76.258116,10.917107],"type":"Point"}
}