{
  "type": "Feature",
  "properties": {
    "iso:country":"IN",
    "ks:ks_name":"Selmapali",
    "ks:ks_pop":140,
    "ks:ks_type":"VILLAGE",
    "name:eng_x_preferred":[
        "Selmapali"
    ],
    "wof:name":"Selmapali",
    "wof:placetype":"locality",
    "wof:population":140
},
  "geometry": {"coordinates":[83.734123,20.587219],"type":"Point"}
}