{
  "type": "Feature",
  "properties": {
    "iso:country":"IN",
    "ks:ks_name":"Bommenahalli",
    "ks:ks_pop":159,
    "ks:ks_type":"VILLAGE",
    "ks:ks_uagg_main":0,
    "name:eng_x_preferred":[
        "Bommenahalli"
    ],
    "wof:name":"Bommenahalli",
    "wof:placetype":"neighbourhood",
    "wof:population":159
},
  "geometry": {"coordinates":[76.535989,13.278131],"type":"Point"}
}