{
  "type": "Feature",
  "properties": {
    "iso:country":"IN",
    "name:ara_x_preferred":[
        "\u0641\u0648\u0644 \u0628\u0627\u062c"
    ],
    "name:ben_bn_x_preferred":[
        "\u09ab\u09c1\u09b2 \u09ac\u09be\u0997"
    ],
    "name:ben_in_x_preferred":[
        "\u09ab\u09c1\u09b2 \u09ac\u09be\u0997"
    ],
    "name:eng_x_preferred":[
        "Phool Bagh"
    ],
    "name:guj_x_preferred":[
        "\u0aab\u0ac2\u0ab2 \u0aac\u0abe\u0a97"
    ],
    "name:hin_x_preferred":[
        "\u092b\u0942\u0932 \u092c\u093e\u0917"
    ],
    "name:kan_x_preferred":[
        "\u0cab\u0cc2\u0cb2\u0ccd"
    ],
    "name:mal_x_preferred":[
        "\u0d2b\u0d42\u0d7e \u0d2c\u0d3e\u0d17\u0d4d"
    ],
    "name:mar_x_preferred":[
        "\u092b\u0942\u0932 \u092c\u093e\u0917"
    ],
    "name:pan_x_preferred":[
        "\u0a2b\u0a42\u0a32 \u0a2c\u0a3e\u0a17"
    ],
    "name:tam_x_preferred":[
        "\u0b83\u0baa\u0bc2\u0bb2\u0bcd \u0baa\u0bbe\u0b95\u0bcd"
    ],
    "name:tel_x_preferred":[
        "\u0c2b\u0c42\u0c32\u0c4d \u0c2c\u0c3e\u0c17\u0c4d"
    ],
    "name:urd_x_preferred":[
        "\u067e\u06be\u0648\u0644 \u0628\u0627\u063a"
    ],
    "qs:gn_adm0_cc":"IN",
    "qs:gn_local":1261033,
    "qs:gn_nam_loc":"orchha",
    "qs:gn_namadm1":"36",
    "qs:local_max":1418,
    "qs:local_sum":1992,
    "qs:localhoods":4,
    "qs:name":"Phool Bagh",
    "qs:name_adm0":"India",
    "qs:name_adm1":"Madhya Pradesh",
    "qs:name_adm2":"Tikamgarh",
    "qs:name_local":"Orchha",
    "qs:photo_max":507,
    "qs:photo_sum":1418,
    "qs:placetype":"Suburb",
    "qs:quad_count":26,
    "qs:woe_adm0":23424848,
    "qs:woe_adm1":2345749,
    "qs:woe_adm2":12586521,
    "qs:woe_lau":0,
    "qs:woe_local":2291413,
    "qs:woe_ver":"7.10.0",
    "wd:wordcount":543,
    "wof:lang":[
        "eng"
    ],
    "wof:name":"Phool Bagh",
    "wof:placetype":"neighbourhood"
},
  "geometry": {"coordinates":[78.63686,25.353019],"type":"Point"}
}