{
  "type": "Feature",
  "properties": {
    "iso:country":"IN",
    "name:eng_x_preferred":[
        "Phool Bagh"
    ],
    "name:unk_x_variant":[
        "Phool Bagh"
    ],
    "qs:gn_adm0_cc":"IN",
    "qs:gn_local":1261033,
    "qs:gn_nam_loc":"orchha",
    "qs:gn_namadm1":"36",
    "qs:local_max":1418,
    "qs:local_sum":1992,
    "qs:localhoods":4,
    "qs:name":"Phool Bagh",
    "qs:name_adm0":"India",
    "qs:name_adm1":"Madhya Pradesh",
    "qs:name_adm2":"Tikamgarh",
    "qs:name_local":"Orchha",
    "qs:photo_max":507,
    "qs:photo_sum":1418,
    "qs:placetype":"Suburb",
    "qs:quad_count":26,
    "qs:woe_adm0":23424848,
    "qs:woe_adm1":2345749,
    "qs:woe_adm2":12586521,
    "qs:woe_lau":0,
    "qs:woe_local":2291413,
    "qs:woe_ver":"7.10.0",
    "wd:wordcount":543,
    "wof:lang":[
        "eng"
    ],
    "wof:name":"Phool Bagh",
    "wof:placetype":"neighbourhood"
},
  "geometry": {"coordinates":[78.63686,25.353019],"type":"Point"}
}