{
  "type": "Feature",
  "properties": {
    "gn:admin1_code":"35.0",
    "gn:admin2_code":"438.0",
    "gn:asciiname":"Karki",
    "gn:country_code":"IN",
    "gn:dem":372,
    "gn:feature_class":"P",
    "gn:feature_code":"PPL",
    "gn:name":"Karki",
    "gn:population":0,
    "gn:timezone":"Asia/Kolkata",
    "iso:country":"IN",
    "name:fra_x_preferred":[
        "Karki"
    ],
    "name:ita_x_preferred":[
        "Karki"
    ],
    "name:nld_x_preferred":[
        "Karki"
    ],
    "name:por_x_preferred":[
        "Karki"
    ],
    "name:rus_x_preferred":[
        "\u041a\u044f\u0440\u043a\u0438"
    ],
    "wof:name":"Karki",
    "wof:placetype":"locality"
},
  "geometry": {"coordinates":[74.9239,22.44755],"type":"Point"}
}