{
  "type": "Feature",
  "properties": {
    "gn:admin1_code":"35",
    "gn:admin2_code":"423.0",
    "gn:asciiname":"Kharoh",
    "gn:country_code":"IN",
    "gn:dem":401,
    "gn:feature_class":"P",
    "gn:feature_code":"PPL",
    "gn:name":"Kharoh",
    "gn:population":0,
    "gn:timezone":"Asia/Kolkata",
    "iso:country":"IN",
    "wof:name":"Kharoh",
    "wof:placetype":"locality"
},
  "geometry": {"coordinates":[78.00633000000001,25.14998],"type":"Point"}
}