{
  "type": "Feature",
  "properties": {
    "iso:country":"IN",
    "ks:ks_name":"Keremundinakaval",
    "ks:ks_pop":55,
    "ks:ks_type":"VILLAGE",
    "name:eng_x_preferred":[
        "Keremundinakaval"
    ],
    "wof:name":"Keremundinakaval",
    "wof:placetype":"locality",
    "wof:population":55
},
  "geometry": {"coordinates":[76.327888,13.504767],"type":"Point"}
}