{
  "type": "Feature",
  "properties": {
    "iso:country":"IN",
    "ks:ks_name":"Jawli Ki Barh",
    "ks:ks_pop":1477,
    "ks:ks_type":"VILLAGE",
    "name:eng_x_preferred":[
        "Jawli Ki Barh"
    ],
    "wof:name":"Jawli Ki Barh",
    "wof:placetype":"locality",
    "wof:population":1477
},
  "geometry": {"coordinates":[76.56978100000001,27.16675],"type":"Point"}
}