{
  "type": "Feature",
  "properties": {
    "iso:country":"IN",
    "ks:ks_name":"Singhia Sundar",
    "ks:ks_pop":2522,
    "ks:ks_type":"VILLAGE",
    "name:eng_x_preferred":[
        "Singhia Sundar"
    ],
    "wof:name":"Singhia Sundar",
    "wof:placetype":"locality",
    "wof:population":2522
},
  "geometry": {"coordinates":[87.163641,25.643186],"type":"Point"}
}