{
  "type": "Feature",
  "properties": {
    "gn:admin1_code":"23.0",
    "gn:admin2_code":"41.0",
    "gn:asciiname":"Hadia",
    "gn:country_code":"IN",
    "gn:dem":249,
    "gn:feature_class":"P",
    "gn:feature_code":"PPL",
    "gn:name":"H\u0101dia",
    "gn:population":0,
    "gn:timezone":"Asia/Kolkata",
    "iso:country":"IN",
    "ks:ks_alt_nam":"H\u0101dia",
    "ks:ks_name":"Hadia",
    "ks:ks_type":"VILLAGE",
    "ks:ks_uagg_main":0,
    "name:deu_x_preferred":[
        "Hadia"
    ],
    "name:eng_x_preferred":[
        "Hadia"
    ],
    "name:eng_x_variant":[
        "H\u0101dia"
    ],
    "wof:name":"Hadia",
    "wof:placetype":"neighbourhood"
},
  "geometry": {"coordinates":[76.132941,30.911315],"type":"Point"}
}