{
  "type": "Feature",
  "properties": {
    "iso:country":"IN",
    "ks:ks_name":"Khajurpara",
    "ks:ks_pop":98,
    "ks:ks_type":"HABITATION",
    "name:eng_x_preferred":[
        "Khajurpara"
    ],
    "wof:name":"Khajurpara",
    "wof:placetype":"locality",
    "wof:population":98
},
  "geometry": {"coordinates":[84.210571,22.278769],"type":"Point"}
}