{
  "type": "Feature",
  "properties": {
    "gn:admin1_code":"34.0",
    "gn:admin2_code":"235.0",
    "gn:asciiname":"Amarpura",
    "gn:country_code":"IN",
    "gn:dem":95,
    "gn:feature_class":"P",
    "gn:feature_code":"PPL",
    "gn:name":"Amarpura",
    "gn:population":0,
    "gn:timezone":"Asia/Kolkata",
    "iso:country":"IN",
    "name:fas_x_preferred":[
        "\u0627\u0645\u0627\u0631\u067e\u0648\u0631\u0627"
    ],
    "name:urd_x_preferred":[
        "\u0627\u0645\u0631\u067e\u0648\u0631\u06c1"
    ],
    "wof:name":"Amarpura",
    "wof:placetype":"locality"
},
  "geometry": {"coordinates":[84.50869,24.82914],"type":"Point"}
}