{
  "type": "Feature",
  "properties": {
    "iso:country":"IN",
    "ks:ks_alt_nam":"PTR colony",
    "ks:ks_name":"Ptr Colony",
    "ks:ks_pop":280,
    "ks:ks_type":"HABITATION",
    "ks:ks_uagg_main":0,
    "name:eng_x_preferred":[
        "Ptr Colony"
    ],
    "wof:name":"Ptr Colony",
    "wof:placetype":"neighbourhood",
    "wof:population":280
},
  "geometry": {"coordinates":[78.19081199999999,9.900979],"type":"Point"}
}