{
  "type": "Feature",
  "properties": {
    "iso:country":"IN",
    "ks:ks_name":"Gairua",
    "ks:ks_pop":3200,
    "ks:ks_type":"VILLAGE",
    "name:eng_x_preferred":[
        "Gairua"
    ],
    "wof:name":"Gairua",
    "wof:placetype":"locality",
    "wof:population":3200
},
  "geometry": {"coordinates":[82.26754800000001,24.580361],"type":"Point"}
}