{
  "type": "Feature",
  "properties": {
    "iso:country":"IN",
    "ks:ks_alt_nam":"College padi",
    "ks:ks_name":"College Padi",
    "ks:ks_pop":846,
    "ks:ks_type":"HABITATION",
    "name:eng_x_preferred":[
        "College Padi"
    ],
    "wof:name":"College Padi",
    "wof:placetype":"locality",
    "wof:population":846
},
  "geometry": {"coordinates":[76.085166,11.130102],"type":"Point"}
}