{
  "type": "Feature",
  "properties": {
    "iso:country":"IN",
    "ks:ks_name":"K Shettahally",
    "ks:ks_pop":173,
    "ks:ks_type":"HABITATION",
    "name:eng_x_preferred":[
        "K Shettahally"
    ],
    "wof:name":"K Shettahally",
    "wof:placetype":"locality",
    "wof:population":173
},
  "geometry": {"coordinates":[76.157073,12.222796],"type":"Point"}
}