{
  "type": "Feature",
  "properties": {
    "gn:admin1_code":"24",
    "gn:admin2_code":"123.0",
    "gn:asciiname":"Rawan ka Khera",
    "gn:country_code":"IN",
    "gn:dem":527,
    "gn:feature_class":"P",
    "gn:feature_code":"PPL",
    "gn:name":"R\u0101w\u0101n ka Khera",
    "gn:population":0,
    "gn:timezone":"Asia/Kolkata",
    "iso:country":"IN",
    "ks:ks_name":"Rawon Ka Khera",
    "ks:ks_pop":519,
    "ks:ks_type":"VILLAGE",
    "name:eng_x_preferred":[
        "Rawon Ka Khera"
    ],
    "name:eng_x_variant":[
        "Rawan ka Khera"
    ],
    "wof:name":"Rawon Ka Khera",
    "wof:placetype":"locality",
    "wof:population":519
},
  "geometry": {"coordinates":[73.99889899999999,25.103586],"type":"Point"}
}