{
  "type": "Feature",
  "properties": {
    "iso:country":"IN",
    "ks:ks_alt_nam":"COLONY",
    "ks:ks_name":"Colony",
    "ks:ks_pop":37,
    "ks:ks_type":"HABITATION",
    "name:eng_x_preferred":[
        "Colony"
    ],
    "wof:name":"Colony",
    "wof:placetype":"locality",
    "wof:population":37
},
  "geometry": {"coordinates":[91.591385,23.854692],"type":"Point"}
}