{
  "type": "Feature",
  "properties": {
    "gn:admin1_code":"36",
    "gn:admin2_code":"137.0",
    "gn:asciiname":"Pathwari",
    "gn:country_code":"IN",
    "gn:dem":224,
    "gn:feature_class":"P",
    "gn:feature_code":"PPL",
    "gn:name":"Pathw\u0101ri",
    "gn:population":0,
    "gn:timezone":"Asia/Kolkata",
    "iso:country":"IN",
    "ks:ks_alt_nam":"Pathw\u0101ri",
    "ks:ks_name":"Pathwari",
    "ks:ks_type":"VILLAGE",
    "ks:ks_uagg_main":0,
    "name:eng_x_preferred":[
        "Pathwari"
    ],
    "name:eng_x_variant":[
        "Pathw\u0101ri"
    ],
    "wof:name":"Pathwari",
    "wof:placetype":"neighbourhood"
},
  "geometry": {"coordinates":[78.49297,29.059498],"type":"Point"}
}