{
  "type": "Feature",
  "properties": {
    "iso:country":"IN",
    "ks:ks_name":"Haleballi",
    "ks:ks_pop":9,
    "ks:ks_type":"HABITATION",
    "name:eng_x_preferred":[
        "Haleballi"
    ],
    "wof:name":"Haleballi",
    "wof:placetype":"locality",
    "wof:population":9
},
  "geometry": {"coordinates":[74.79320300000001,14.113359],"type":"Point"}
}