{
  "type": "Feature",
  "properties": {
    "iso:country":"IN",
    "ks:ks_name":"Patuli",
    "ks:ks_pop":920,
    "ks:ks_type":"VILLAGE",
    "ks:ks_uagg_main":0,
    "name:eng_x_preferred":[
        "Patuli"
    ],
    "wof:name":"Patuli",
    "wof:placetype":"neighbourhood",
    "wof:population":920
},
  "geometry": {"coordinates":[86.726124,20.780957],"type":"Point"}
}