{
  "type": "Feature",
  "properties": {
    "iso:country":"IN",
    "ks:ks_alt_nam":"deevarkeri",
    "ks:ks_name":"Deevarkeri",
    "ks:ks_pop":80,
    "ks:ks_type":"HABITATION",
    "name:eng_x_preferred":[
        "Deevarkeri"
    ],
    "wof:name":"Deevarkeri",
    "wof:placetype":"locality",
    "wof:population":80
},
  "geometry": {"coordinates":[74.707724,14.468797],"type":"Point"}
}