{
  "type": "Feature",
  "properties": {
    "iso:country":"IN",
    "ks:ks_name":"Khairan",
    "ks:ks_pop":227,
    "ks:ks_type":"HABITATION",
    "ks:ks_uagg_main":0,
    "name:eng_x_preferred":[
        "Khairan"
    ],
    "wof:name":"Khairan",
    "wof:placetype":"neighbourhood",
    "wof:population":227
},
  "geometry": {"coordinates":[86.407552,24.869901],"type":"Point"}
}