{
  "type": "Feature",
  "properties": {
    "gn:admin1_code":"38",
    "gn:admin2_code":"346.0",
    "gn:asciiname":"Karcha",
    "gn:country_code":"IN",
    "gn:dem":237,
    "gn:feature_class":"P",
    "gn:feature_code":"PPL",
    "gn:name":"Karcha",
    "gn:population":0,
    "gn:timezone":"Asia/Kolkata",
    "iso:country":"IN",
    "ks:ks_name":"Karcha",
    "ks:ks_pop":1056,
    "ks:ks_type":"VILLAGE",
    "name:eng_x_preferred":[
        "Karcha"
    ],
    "wof:name":"Karcha",
    "wof:placetype":"locality",
    "wof:population":1056
},
  "geometry": {"coordinates":[83.58274299999999,24.251766],"type":"Point"}
}