{
  "type": "Feature",
  "properties": {
    "iso:country":"IN",
    "ks:ks_name":"Sandha",
    "ks:ks_pop":534,
    "ks:ks_type":"VILLAGE",
    "ks:ks_uagg_main":0,
    "name:eng_x_preferred":[
        "Sandha"
    ],
    "wof:name":"Sandha",
    "wof:placetype":"neighbourhood",
    "wof:population":534
},
  "geometry": {"coordinates":[85.90929199999999,24.629449],"type":"Point"}
}