{
  "type": "Feature",
  "properties": {
    "iso:country":"IN",
    "ks:ks_alt_nam":"Tarajuli TE 1",
    "ks:ks_name":"Tarajuli Te 1",
    "ks:ks_pop":1960,
    "ks:ks_type":"HABITATION",
    "ks:ks_uagg_main":0,
    "name:eng_x_preferred":[
        "Tarajuli Te 1"
    ],
    "wof:name":"Tarajuli Te 1",
    "wof:placetype":"neighbourhood",
    "wof:population":1960
},
  "geometry": {"coordinates":[92.63307,26.868708],"type":"Point"}
}