{
  "type": "Feature",
  "properties": {
    "gn:admin1_code":"36.0",
    "gn:admin2_code":"150.0",
    "gn:asciiname":"Rath",
    "gn:country_code":"IN",
    "gn:dem":189,
    "gn:feature_class":"P",
    "gn:feature_code":"PPL",
    "gn:name":"R\u0101th",
    "gn:population":0,
    "gn:timezone":"Asia/Kolkata",
    "iso:country":"IN",
    "name:bpy_x_preferred":[
        "\u09b0\u09be\u09a5"
    ],
    "name:ceb_x_preferred":[
        "Rath"
    ],
    "name:ces_x_preferred":[
        "Rath"
    ],
    "name:deu_x_preferred":[
        "Rath"
    ],
    "name:fra_x_preferred":[
        "Rath"
    ],
    "name:hun_x_preferred":[
        "R\u00e1th"
    ],
    "name:ita_x_preferred":[
        "Rath"
    ],
    "name:nld_x_preferred":[
        "Rath"
    ],
    "name:pol_x_preferred":[
        "Rath"
    ],
    "name:swe_x_preferred":[
        "Rath"
    ],
    "name:vie_x_preferred":[
        "Rath"
    ],
    "wof:name":"Rath",
    "wof:placetype":"locality"
},
  "geometry": {"coordinates":[79.39905,28.79208],"type":"Point"}
}