{
  "type": "Feature",
  "properties": {
    "iso:country":"IN",
    "ks:ks_name":"7 F",
    "ks:ks_pop":627,
    "ks:ks_type":"HABITATION",
    "name:eng_x_preferred":[
        "7 F"
    ],
    "wof:name":"7 F",
    "wof:placetype":"locality",
    "wof:population":627
},
  "geometry": {"coordinates":[73.81787799999999,29.992764],"type":"Point"}
}