{
  "type": "Feature",
  "properties": {
    "iso:country":"IN",
    "ks:ks_name":"Draka",
    "ks:ks_pop":1937,
    "ks:ks_type":"VILLAGE",
    "ks:ks_uagg_main":0,
    "name:eng_x_preferred":[
        "Draka"
    ],
    "wof:name":"Draka",
    "wof:placetype":"neighbourhood",
    "wof:population":1937
},
  "geometry": {"coordinates":[75.342462,30.308094],"type":"Point"}
}