{
  "type": "Feature",
  "properties": {
    "iso:country":"IN",
    "ks:ks_name":"Batadula Paschimpara",
    "ks:ks_pop":594,
    "ks:ks_type":"HABITATION",
    "name:eng_x_preferred":[
        "Batadula Paschimpara"
    ],
    "wof:name":"Batadula Paschimpara",
    "wof:placetype":"locality",
    "wof:population":594
},
  "geometry": {"coordinates":[91.21831,23.540422],"type":"Point"}
}