{
  "type": "Feature",
  "properties": {
    "gn:admin1_code":"24.0",
    "gn:admin2_code":"118.0",
    "gn:asciiname":"Jaitsingh ka Gudha",
    "gn:country_code":"IN",
    "gn:dem":283,
    "gn:feature_class":"P",
    "gn:feature_code":"PPL",
    "gn:name":"Jaitsingh ka G\u016bdha",
    "gn:population":0,
    "gn:timezone":"Asia/Kolkata",
    "iso:country":"IN",
    "wof:name":"Jaitsingh ka Gudha",
    "wof:placetype":"neighbourhood"
},
  "geometry": {"coordinates":[73.50482,25.52028],"type":"Point"}
}