{
  "type": "Feature",
  "properties": {
    "iso:country":"IN",
    "ks:ks_name":"Vachu Thanda",
    "ks:ks_pop":92,
    "ks:ks_type":"HABITATION",
    "name:eng_x_preferred":[
        "Vachu Thanda"
    ],
    "wof:name":"Vachu Thanda",
    "wof:placetype":"locality",
    "wof:population":92
},
  "geometry": {"coordinates":[77.644019,18.234538],"type":"Point"}
}