{
  "type": "Feature",
  "properties": {
    "iso:country":"IN",
    "ks:ks_name":"Lupungi",
    "ks:ks_pop":878,
    "ks:ks_type":"HABITATION",
    "name:eng_x_preferred":[
        "Lupungi"
    ],
    "wof:name":"Lupungi",
    "wof:placetype":"locality",
    "wof:population":878
},
  "geometry": {"coordinates":[85.74507,22.204854],"type":"Point"}
}