{
  "type": "Feature",
  "properties": {
    "gn:admin1_code":"12.0",
    "gn:admin2_code":"005",
    "gn:asciiname":"Damel",
    "gn:country_code":"IN",
    "gn:dem":2372,
    "gn:feature_class":"P",
    "gn:feature_code":"PPL",
    "gn:name":"Damel",
    "gn:population":0,
    "gn:timezone":"Asia/Kolkata",
    "iso:country":"IN",
    "name:deu_x_preferred":[
        "Damel"
    ],
    "name:fra_x_preferred":[
        "Damel"
    ],
    "wof:name":"Damel",
    "wof:placetype":"locality"
},
  "geometry": {"coordinates":[74.33649,33.86239],"type":"Point"}
}