{
  "type": "Feature",
  "properties": {
    "iso:country":"IN",
    "ks:ks_name":"Gothasabalia",
    "ks:ks_pop":63,
    "ks:ks_type":"VILLAGE",
    "ks:ks_uagg_main":0,
    "name:eng_x_preferred":[
        "Gothasabalia"
    ],
    "wof:name":"Gothasabalia",
    "wof:placetype":"neighbourhood",
    "wof:population":63
},
  "geometry": {"coordinates":[85.926202,20.210789],"type":"Point"}
}