{
  "type": "Feature",
  "properties": {
    "iso:country":"IN",
    "ks:ks_name":"13 KWM",
    "ks:ks_pop":88,
    "ks:ks_type":"VILLAGE",
    "name:eng_x_preferred":[
        "13 KWM"
    ],
    "wof:name":"13 KWM",
    "wof:placetype":"locality",
    "wof:population":88
},
  "geometry": {"coordinates":[73.107445,28.865581],"type":"Point"}
}