{
  "type": "Feature",
  "properties": {
    "gn:admin1_code":"03",
    "gn:admin2_code":"306.0",
    "gn:asciiname":"Singlijan",
    "gn:country_code":"IN",
    "gn:dem":114,
    "gn:feature_class":"P",
    "gn:feature_code":"PPL",
    "gn:name":"Singlij\u0101n",
    "gn:population":0,
    "gn:timezone":"Asia/Kolkata",
    "iso:country":"IN",
    "name:und_x_variant":[
        "Singlij\u0101n Basti",
        "Singlij\u0101n"
    ],
    "wof:name":"Singlijan",
    "wof:placetype":"locality"
},
  "geometry": {"coordinates":[93.46337,26.92533],"type":"Point"}
}