{
  "type": "Feature",
  "properties": {
    "iso:country":"IN",
    "ks:ks_name":"Karimabad",
    "ks:ks_pop":1250,
    "ks:ks_type":"VILLAGE",
    "ks:ks_uagg_main":0,
    "name:eng_x_preferred":[
        "Karimabad"
    ],
    "wof:name":"Karimabad",
    "wof:placetype":"neighbourhood",
    "wof:population":1250
},
  "geometry": {"coordinates":[80.78385,26.836187],"type":"Point"}
}