{
  "type": "Feature",
  "properties": {
    "gn:admin1_code":"35.0",
    "gn:admin2_code":"457.0",
    "gn:asciiname":"Alna",
    "gn:country_code":"IN",
    "gn:dem":650,
    "gn:feature_class":"P",
    "gn:feature_code":"PPL",
    "gn:name":"Aln\u0101",
    "gn:population":0,
    "gn:timezone":"Asia/Kolkata",
    "iso:country":"IN",
    "name:bar_x_preferred":[
        "Alna"
    ],
    "name:ceb_x_preferred":[
        "Alna District"
    ],
    "name:dan_x_preferred":[
        "Alna"
    ],
    "name:deu_x_preferred":[
        "Alna"
    ],
    "name:est_x_preferred":[
        "Alna linnaosa"
    ],
    "name:fas_x_preferred":[
        "\u0627\u0644\u0646\u0627"
    ],
    "name:fin_x_preferred":[
        "Alna"
    ],
    "name:fra_x_preferred":[
        "Alna"
    ],
    "name:nld_x_preferred":[
        "Alna"
    ],
    "name:nno_x_preferred":[
        "Oslobydelen Alna"
    ],
    "name:nor_x_preferred":[
        "Bydel Alna"
    ],
    "name:pol_x_preferred":[
        "Alna"
    ],
    "name:spa_x_preferred":[
        "Alna"
    ],
    "name:swe_x_preferred":[
        "Alna"
    ],
    "name:zho_x_preferred":[
        "\u963f\u723e\u7d0d"
    ],
    "wof:name":"Alna",
    "wof:placetype":"locality"
},
  "geometry": {"coordinates":[80.79939,22.30955],"type":"Point"}
}