{
  "type": "Feature",
  "properties": {
    "iso:country":"IN",
    "ks:ks_name":"Subkara",
    "ks:ks_pop":1038,
    "ks:ks_type":"VILLAGE",
    "name:eng_x_preferred":[
        "Subkara"
    ],
    "wof:name":"Subkara",
    "wof:placetype":"locality",
    "wof:population":1038
},
  "geometry": {"coordinates":[76.679118,25.353585],"type":"Point"}
}