{
  "type": "Feature",
  "properties": {
    "iso:country":"IN",
    "ks:ks_name":"Duhia Diliya",
    "ks:ks_pop":331,
    "ks:ks_type":"VILLAGE",
    "name:eng_x_preferred":[
        "Duhia Diliya"
    ],
    "wof:name":"Duhia Diliya",
    "wof:placetype":"locality",
    "wof:population":331
},
  "geometry": {"coordinates":[83.58382899999999,26.242611],"type":"Point"}
}