{
  "type": "Feature",
  "properties": {
    "gn:admin1_code":"16.0",
    "gn:admin2_code":"524",
    "gn:asciiname":"Ambalga Buzurg",
    "gn:country_code":"IN",
    "gn:dem":598,
    "gn:feature_class":"P",
    "gn:feature_code":"PPL",
    "gn:name":"Ambalga Buzurg",
    "gn:population":0,
    "gn:timezone":"Asia/Kolkata",
    "iso:country":"IN",
    "name:und_x_variant":[
        "Amb\u0101lga",
        "Ambalga Buzurg"
    ],
    "wof:name":"Ambalga Buzurg",
    "wof:placetype":"neighbourhood"
},
  "geometry": {"coordinates":[76.86516,18.16334],"type":"Point"}
}