{
  "type": "Feature",
  "properties": {
    "iso:country":"IN",
    "ks:ks_name":"Chak Jogi",
    "ks:ks_pop":12,
    "ks:ks_type":"VILLAGE",
    "name:eng_x_preferred":[
        "Chak Jogi"
    ],
    "wof:name":"Chak Jogi",
    "wof:placetype":"locality",
    "wof:population":12
},
  "geometry": {"coordinates":[87.56958299999999,22.043982],"type":"Point"}
}