{
  "type": "Feature",
  "properties": {
    "iso:country":"IN",
    "ks:ks_name":"Musalamma Camp",
    "ks:ks_pop":135,
    "ks:ks_type":"HABITATION",
    "name:eng_x_preferred":[
        "Musalamma Camp"
    ],
    "wof:name":"Musalamma Camp",
    "wof:placetype":"locality",
    "wof:population":135
},
  "geometry": {"coordinates":[76.37,15.28],"type":"Point"}
}