{
  "type": "Feature",
  "properties": {
    "iso:country":"IN",
    "ks:ks_alt_nam":"Mam mati gaon",
    "ks:ks_name":"Mam Mati Gaon",
    "ks:ks_pop":450,
    "ks:ks_type":"HABITATION",
    "ks:ks_uagg_main":0,
    "name:eng_x_preferred":[
        "Mam Mati Gaon"
    ],
    "wof:name":"Mam Mati Gaon",
    "wof:placetype":"neighbourhood",
    "wof:population":450
},
  "geometry": {"coordinates":[94.730113,26.853329],"type":"Point"}
}