{
  "type": "Feature",
  "properties": {
    "gn:admin1_code":"37",
    "gn:admin2_code":"406.0",
    "gn:asciiname":"Ainthi",
    "gn:country_code":"IN",
    "gn:dem":561,
    "gn:feature_class":"P",
    "gn:feature_code":"PPL",
    "gn:name":"Ainthi",
    "gn:population":0,
    "gn:timezone":"Asia/Kolkata",
    "iso:country":"IN",
    "wof:name":"Ainthi",
    "wof:placetype":"locality"
},
  "geometry": {"coordinates":[81.97344,22.98681],"type":"Point"}
}