{
  "type": "Feature",
  "properties": {
    "gn:admin1_code":"39.0",
    "gn:admin2_code":"61.0",
    "gn:asciiname":"Bawansa Malla",
    "gn:country_code":"IN",
    "gn:dem":1460,
    "gn:feature_class":"P",
    "gn:feature_code":"PPL",
    "gn:name":"Baw\u0101nsa Malla",
    "gn:population":0,
    "gn:timezone":"Asia/Kolkata",
    "iso:country":"IN",
    "wof:name":"Bawansa Malla",
    "wof:placetype":"locality"
},
  "geometry": {"coordinates":[79.07040000000001,29.81724],"type":"Point"}
}