{
  "type": "Feature",
  "properties": {
    "gn:admin1_code":"39.0",
    "gn:admin2_code":"61.0",
    "gn:asciiname":"Bawansa Malla",
    "gn:country_code":"IN",
    "gn:dem":1460,
    "gn:feature_class":"P",
    "gn:feature_code":"PPL",
    "gn:name":"Baw\u0101nsa Malla",
    "gn:population":0,
    "gn:timezone":"Asia/Kolkata",
    "iso:country":"IN",
    "ks:ks_name":"Bawasa Malla",
    "ks:ks_pop":299,
    "ks:ks_type":"VILLAGE",
    "name:eng_x_preferred":[
        "Bawasa Malla"
    ],
    "name:eng_x_variant":[
        "Bawansa Malla"
    ],
    "wof:name":"Bawasa Malla",
    "wof:placetype":"locality",
    "wof:population":299
},
  "geometry": {"coordinates":[79.06924100000001,29.816895],"type":"Point"}
}