{
  "type": "Feature",
  "properties": {
    "iso:country":"IN",
    "ks:ks_name":"Harijanawada",
    "ks:ks_pop":265,
    "ks:ks_type":"HABITATION",
    "name:eng_x_preferred":[
        "Harijanawada"
    ],
    "wof:name":"Harijanawada",
    "wof:placetype":"locality",
    "wof:population":265
},
  "geometry": {"coordinates":[79.627413,13.658856],"type":"Point"}
}