{
  "type": "Feature",
  "properties": {
    "iso:country":"IN",
    "ks:ks_name":"Kaleigaon",
    "ks:ks_pop":749,
    "ks:ks_type":"VILLAGE",
    "ks:ks_uagg_main":0,
    "name:eng_x_preferred":[
        "Kaleigaon"
    ],
    "wof:name":"Kaleigaon",
    "wof:placetype":"neighbourhood",
    "wof:population":749
},
  "geometry": {"coordinates":[82.973906,19.839565],"type":"Point"}
}