{
  "type": "Feature",
  "properties": {
    "iso:country":"IN",
    "ks:ks_name":"Tangara",
    "ks:ks_pop":0,
    "ks:ks_type":"VILLAGE",
    "name:eng_x_preferred":[
        "Tangara"
    ],
    "wof:name":"Tangara",
    "wof:placetype":"locality",
    "wof:population":0
},
  "geometry": {"coordinates":[85.129412,20.055466],"type":"Point"}
}