{
  "type": "Feature",
  "properties": {
    "iso:country":"IN",
    "ks:ks_name":"Bilokhar Tola",
    "ks:ks_pop":62,
    "ks:ks_type":"HABITATION",
    "name:eng_x_preferred":[
        "Bilokhar Tola"
    ],
    "wof:name":"Bilokhar Tola",
    "wof:placetype":"locality",
    "wof:population":62
},
  "geometry": {"coordinates":[86.4825,25.251779],"type":"Point"}
}