{
  "type": "Feature",
  "properties": {
    "gn:admin1_code":"19.0",
    "gn:admin2_code":"574.0",
    "gn:asciiname":"Hirihalli",
    "gn:country_code":"IN",
    "gn:dem":843,
    "gn:feature_class":"P",
    "gn:feature_code":"PPL",
    "gn:name":"Hirihalli",
    "gn:population":0,
    "gn:timezone":"Asia/Kolkata",
    "iso:country":"IN",
    "ks:ks_name":"Hirehalli",
    "ks:ks_pop":1448,
    "ks:ks_type":"VILLAGE",
    "name:eng_x_preferred":[
        "Hirehalli"
    ],
    "name:eng_x_variant":[
        "Hirihalli"
    ],
    "wof:name":"Hirehalli",
    "wof:placetype":"locality",
    "wof:population":1448
},
  "geometry": {"coordinates":[76.068533,12.637385],"type":"Point"}
}