{
  "type": "Feature",
  "properties": {
    "iso:country":"IN",
    "ks:ks_name":"Manikjhara",
    "ks:ks_pop":281,
    "ks:ks_type":"HABITATION",
    "name:eng_x_preferred":[
        "Manikjhara"
    ],
    "wof:name":"Manikjhara",
    "wof:placetype":"locality",
    "wof:population":281
},
  "geometry": {"coordinates":[90.54456,26.275648],"type":"Point"}
}