{
  "type": "Feature",
  "properties": {
    "iso:country":"IN",
    "ks:ks_name":"Timikinala",
    "ks:ks_pop":20,
    "ks:ks_type":"VILLAGE",
    "name:eng_x_preferred":[
        "Timikinala"
    ],
    "wof:name":"Timikinala",
    "wof:placetype":"locality",
    "wof:population":20
},
  "geometry": {"coordinates":[83.637007,22.189443],"type":"Point"}
}