{
  "type": "Feature",
  "properties": {
    "iso:country":"IN",
    "ks:ks_name":"Mahengra",
    "ks:ks_pop":665,
    "ks:ks_type":"HABITATION",
    "name:eng_x_preferred":[
        "Mahengra"
    ],
    "wof:name":"Mahengra",
    "wof:placetype":"locality",
    "wof:population":665
},
  "geometry": {"coordinates":[86.00549599999999,24.84319],"type":"Point"}
}