{
  "type": "Feature",
  "properties": {
    "iso:country":"IN",
    "ks:ks_alt_nam":"Koodapetty colani Road",
    "ks:ks_name":"Koodapetty Colani Road",
    "ks:ks_pop":623,
    "ks:ks_type":"HABITATION",
    "name:eng_x_preferred":[
        "Koodapetty Colani Road"
    ],
    "wof:name":"Koodapetty Colani Road",
    "wof:placetype":"locality",
    "wof:population":623
},
  "geometry": {"coordinates":[76.207053,11.343993],"type":"Point"}
}