{
  "type": "Feature",
  "properties": {
    "gn:admin1_code":"34.0",
    "gn:admin2_code":"224.0",
    "gn:asciiname":"Lakhanpur",
    "gn:country_code":"IN",
    "gn:dem":53,
    "gn:feature_class":"P",
    "gn:feature_code":"PPL",
    "gn:name":"Lakhanpur",
    "gn:population":0,
    "gn:timezone":"Asia/Kolkata",
    "iso:country":"IN",
    "name:ara_x_preferred":[
        "\u0644\u0627\u0643\u0647\u0646\u0628\u0648\u0631"
    ],
    "name:ben_bn_x_preferred":[
        "\u09b2\u09be\u0996\u09be\u09a8\u09aa\u09c1\u09b0"
    ],
    "name:ben_in_x_preferred":[
        "\u09b2\u09be\u0996\u09be\u09a8\u09aa\u09c1\u09b0"
    ],
    "name:fra_x_preferred":[
        "Lakhanpur"
    ],
    "name:guj_x_preferred":[
        "\u0ab2\u0a96\u0aa8\u0a95\u0aaa\u0ac1\u0ab0"
    ],
    "name:hin_x_preferred":[
        "\u0932\u0916\u0928\u092a\u0941\u0930"
    ],
    "name:kan_x_preferred":[
        "\u0cb2\u0c96\u0ca8\u0ccd"
    ],
    "name:mal_x_preferred":[
        "\u0d32\u0d16\u0d3e\u0d7b\u0d2a\u0d42\u0d7c"
    ],
    "name:mar_x_preferred":[
        "\u0932\u093e\u0916\u0928\u092a\u0941\u0930\u093e"
    ],
    "name:pan_x_preferred":[
        "\u0a32\u0a16\u0a28\u0a2a\u0a41\u0a30"
    ],
    "name:pol_x_preferred":[
        "Lakhanpur"
    ],
    "name:tam_x_preferred":[
        "\u0bb2\u0b95\u0bbe\u0ba9\u0bcd\u0baa\u0bc2\u0bb0\u0bcd"
    ],
    "name:tel_x_preferred":[
        "\u0c32\u0c16\u0c3e\u0c28\u0c4d"
    ],
    "name:urd_x_preferred":[
        "\u0644\u06a9\u06be\u0646 \u067e\u0648\u0631"
    ],
    "wof:name":"Lakhanpur",
    "wof:placetype":"locality"
},
  "geometry": {"coordinates":[86.6816,25.13254],"type":"Point"}
}