{
  "type": "Feature",
  "properties": {
    "iso:country":"IN",
    "ks:ks_name":"Gochati Dakshinpara",
    "ks:ks_pop":1155,
    "ks:ks_type":"HABITATION",
    "name:eng_x_preferred":[
        "Gochati Dakshinpara"
    ],
    "wof:name":"Gochati Dakshinpara",
    "wof:placetype":"locality",
    "wof:population":1155
},
  "geometry": {"coordinates":[87.780817,22.536501],"type":"Point"}
}