{
  "type": "Feature",
  "properties": {
    "gn:admin1_code":"19.0",
    "gn:admin2_code":"574.0",
    "gn:asciiname":"Madihalli",
    "gn:country_code":"IN",
    "gn:dem":924,
    "gn:feature_class":"P",
    "gn:feature_code":"PPL",
    "gn:name":"M\u0101dihalli",
    "gn:population":0,
    "gn:timezone":"Asia/Kolkata",
    "iso:country":"IN",
    "name:urd_x_preferred":[
        "\u0645\u06cc\u0688\u06cc\u06c1\u0627\u0644\u06cc"
    ],
    "wof:name":"Madihalli",
    "wof:placetype":"locality"
},
  "geometry": {"coordinates":[76.08533,12.7278],"type":"Point"}
}