{
  "type": "Feature",
  "properties": {
    "gn:admin1_code":"36.0",
    "gn:admin2_code":"139.0",
    "gn:asciiname":"Hasanpur Jakhera",
    "gn:country_code":"IN",
    "gn:dem":226,
    "gn:feature_class":"P",
    "gn:feature_code":"PPL",
    "gn:name":"Hasanpur Jakhera",
    "gn:population":0,
    "gn:timezone":"Asia/Kolkata",
    "iso:country":"IN",
    "ks:ks_name":"Hasanpur Jakhera",
    "ks:ks_type":"VILLAGE",
    "name:eng_x_preferred":[
        "Hasanpur Jakhera"
    ],
    "wof:name":"Hasanpur Jakhera",
    "wof:placetype":"locality"
},
  "geometry": {"coordinates":[77.25109500000001,29.033066],"type":"Point"}
}