{
  "type": "Feature",
  "properties": {
    "iso:country":"IN",
    "ks:ks_name":"Honnenahalli",
    "ks:ks_type":"VILLAGE",
    "name:eng_x_preferred":[
        "Honnenahalli"
    ],
    "wof:name":"Honnenahalli",
    "wof:placetype":"locality"
},
  "geometry": {"coordinates":[76.90897,13.524436],"type":"Point"}
}