{
  "type": "Feature",
  "properties": {
    "iso:country":"IN",
    "ks:ks_alt_nam":"Rajak tola",
    "ks:ks_name":"Rajak Tola",
    "ks:ks_pop":145,
    "ks:ks_type":"HABITATION",
    "name:eng_x_preferred":[
        "Rajak Tola"
    ],
    "wof:name":"Rajak Tola",
    "wof:placetype":"locality",
    "wof:population":145
},
  "geometry": {"coordinates":[86.495575,26.031824],"type":"Point"}
}