{
  "type": "Feature",
  "properties": {
    "gn:admin1_code":"36",
    "gn:admin2_code":"195.0",
    "gn:asciiname":"Sarai Murad Ali",
    "gn:country_code":"IN",
    "gn:dem":73,
    "gn:feature_class":"P",
    "gn:feature_code":"PPL",
    "gn:name":"Sar\u0101i Mur\u0101d Ali",
    "gn:population":0,
    "gn:timezone":"Asia/Kolkata",
    "iso:country":"IN",
    "ks:ks_alt_nam":"Sar\u0101i Mur\u0101d Ali",
    "ks:ks_name":"Sarai Murad Ali",
    "ks:ks_type":"VILLAGE",
    "ks:ks_uagg_main":0,
    "name:eng_x_preferred":[
        "Sarai Murad Ali"
    ],
    "name:eng_x_variant":[
        "Sar\u0101i Mur\u0101d Ali"
    ],
    "wof:name":"Sarai Murad Ali",
    "wof:placetype":"neighbourhood"
},
  "geometry": {"coordinates":[83.56923999999999,25.420971],"type":"Point"}
}