{
  "type": "Feature",
  "properties": {
    "gn:admin1_code":"11",
    "gn:admin2_code":"24.0",
    "gn:asciiname":"Nari",
    "gn:country_code":"IN",
    "gn:dem":636,
    "gn:feature_class":"P",
    "gn:feature_code":"PPL",
    "gn:name":"N\u0101ri",
    "gn:population":0,
    "gn:timezone":"Asia/Kolkata",
    "iso:country":"IN",
    "name:ceb_x_preferred":[
        "Nari"
    ],
    "name:deu_x_preferred":[
        "Nari"
    ],
    "name:swe_x_preferred":[
        "Nari"
    ],
    "name:ukr_x_preferred":[
        "\u041d\u0430\u0440\u0456"
    ],
    "wof:name":"Nari",
    "wof:placetype":"locality"
},
  "geometry": {"coordinates":[76.24133,31.7838],"type":"Point"}
}