{
  "type": "Feature",
  "properties": {
    "gn:admin1_code":"24.0",
    "gn:admin2_code":"130.0",
    "gn:asciiname":"Munawara",
    "gn:country_code":"IN",
    "gn:dem":314,
    "gn:feature_class":"P",
    "gn:feature_code":"PPL",
    "gn:name":"M\u016bnaw\u0101ra",
    "gn:population":0,
    "gn:timezone":"Asia/Kolkata",
    "iso:country":"IN",
    "ks:ks_name":"Mundwara",
    "ks:ks_pop":431,
    "ks:ks_type":"VILLAGE",
    "name:eng_x_preferred":[
        "Mundwara"
    ],
    "name:eng_x_variant":[
        "Munawara"
    ],
    "wof:name":"Mundwara",
    "wof:placetype":"locality",
    "wof:population":431
},
  "geometry": {"coordinates":[73.62181699999999,24.019593],"type":"Point"}
}