{
  "type": "Feature",
  "properties": {
    "gn:admin1_code":"24.0",
    "gn:admin2_code":"130.0",
    "gn:asciiname":"Munawara",
    "gn:country_code":"IN",
    "gn:dem":314,
    "gn:feature_class":"P",
    "gn:feature_code":"PPL",
    "gn:name":"M\u016bnaw\u0101ra",
    "gn:population":0,
    "gn:timezone":"Asia/Kolkata",
    "iso:country":"IN",
    "wof:name":"Munawara",
    "wof:placetype":"locality"
},
  "geometry": {"coordinates":[73.61838,24.01657],"type":"Point"}
}