{
  "type": "Feature",
  "properties": {
    "gn:admin1_code":"36",
    "gn:admin2_code":"185.0",
    "gn:asciiname":"Kakrahia",
    "gn:country_code":"IN",
    "gn:dem":92,
    "gn:feature_class":"P",
    "gn:feature_code":"PPL",
    "gn:name":"Kakrahia",
    "gn:population":0,
    "gn:timezone":"Asia/Kolkata",
    "iso:country":"IN",
    "ks:ks_name":"Kakrahia",
    "ks:ks_pop":545,
    "ks:ks_type":"VILLAGE",
    "ks:ks_uagg_main":0,
    "name:eng_x_preferred":[
        "Kakrahia"
    ],
    "wof:name":"Kakrahia",
    "wof:placetype":"neighbourhood",
    "wof:population":545
},
  "geometry": {"coordinates":[82.73072999999999,26.929159],"type":"Point"}
}