{
  "type": "Feature",
  "properties": {
    "gn:admin1_code":"36",
    "gn:admin2_code":"179.0",
    "gn:asciiname":"Purwa Gadarian",
    "gn:country_code":"IN",
    "gn:dem":102,
    "gn:feature_class":"P",
    "gn:feature_code":"PPL",
    "gn:name":"Purwa Gadarian",
    "gn:population":0,
    "gn:timezone":"Asia/Kolkata",
    "iso:country":"IN",
    "ks:ks_name":"Pure Gadarian",
    "ks:ks_pop":117,
    "ks:ks_type":"HABITATION",
    "name:eng_x_preferred":[
        "Pure Gadarian"
    ],
    "name:eng_x_variant":[
        "Purwa Gadarian"
    ],
    "wof:name":"Pure Gadarian",
    "wof:placetype":"locality",
    "wof:population":117
},
  "geometry": {"coordinates":[82.103093,26.335599],"type":"Point"}
}