{
  "type": "Feature",
  "properties": {
    "iso:country":"IN",
    "ks:ks_name":"3 BWSM",
    "ks:ks_pop":26,
    "ks:ks_type":"VILLAGE",
    "name:eng_x_preferred":[
        "3 BWSM"
    ],
    "wof:name":"3 BWSM",
    "wof:placetype":"locality",
    "wof:population":26
},
  "geometry": {"coordinates":[73.210184,29.422515],"type":"Point"}
}