{
  "type": "Feature",
  "properties": {
    "iso:country":"IN",
    "ks:ks_name":"Udi Road",
    "ks:ks_pop":260,
    "ks:ks_type":"HABITATION",
    "name:eng_x_preferred":[
        "Udi Road"
    ],
    "wof:name":"Udi Road",
    "wof:placetype":"locality",
    "wof:population":260
},
  "geometry": {"coordinates":[85.583742,23.713622],"type":"Point"}
}