{
  "type": "Feature",
  "properties": {
    "iso:country":"IN",
    "ks:ks_name":"Jagsahaipura",
    "ks:ks_pop":467,
    "ks:ks_type":"VILLAGE",
    "name:eng_x_preferred":[
        "Jagsahaipura"
    ],
    "wof:name":"Jagsahaipura",
    "wof:placetype":"locality",
    "wof:population":467
},
  "geometry": {"coordinates":[76.23503599999999,26.723719],"type":"Point"}
}