{
  "type": "Feature",
  "properties": {
    "iso:country":"IN",
    "ks:ks_name":"Pareda Chak No. 1",
    "ks:ks_pop":253,
    "ks:ks_type":"HABITATION",
    "name:eng_x_preferred":[
        "Pareda Chak No. 1"
    ],
    "wof:name":"Pareda Chak No. 1",
    "wof:placetype":"locality",
    "wof:population":253
},
  "geometry": {"coordinates":[73.59239700000001,24.175477],"type":"Point"}
}