{
  "type": "Feature",
  "properties": {
    "gn:admin1_code":"19.0",
    "gn:admin2_code":"577.0",
    "gn:asciiname":"Mannehundi",
    "gn:country_code":"IN",
    "gn:dem":667,
    "gn:feature_class":"P",
    "gn:feature_code":"PPL",
    "gn:name":"Mannehundi",
    "gn:population":0,
    "gn:timezone":"Asia/Kolkata",
    "iso:country":"IN",
    "wof:name":"Mannehundi",
    "wof:placetype":"locality"
},
  "geometry": {"coordinates":[76.86360999999999,12.22371],"type":"Point"}
}