{
  "type": "Feature",
  "properties": {
    "iso:country":"IN",
    "ks:ks_alt_nam":"\u0100mbadar",
    "ks:ks_name":"Ambadar",
    "ks:ks_type":"VILLAGE",
    "name:eng_x_preferred":[
        "Ambadar"
    ],
    "name:eng_x_variant":[
        "\u0100mbadar"
    ],
    "wof:name":"Ambadar",
    "wof:placetype":"locality"
},
  "geometry": {"coordinates":[84.62684,20.850212],"type":"Point"}
}