{
  "type": "Feature",
  "properties": {
    "iso:country":"IN",
    "ks:ks_name":"Budegebai",
    "ks:ks_pop":154,
    "ks:ks_type":"HABITATION",
    "name:eng_x_preferred":[
        "Budegebai"
    ],
    "wof:name":"Budegebai",
    "wof:placetype":"locality",
    "wof:population":154
},
  "geometry": {"coordinates":[79.031738,17.440323],"type":"Point"}
}