{
  "type": "Feature",
  "properties": {
    "iso:country":"IN",
    "ks:ks_name":"Purbba Haripur",
    "ks:ks_pop":202,
    "ks:ks_type":"VILLAGE",
    "ks:ks_uagg_main":0,
    "name:eng_x_preferred":[
        "Purbba Haripur"
    ],
    "wof:name":"Purbba Haripur",
    "wof:placetype":"neighbourhood",
    "wof:population":202
},
  "geometry": {"coordinates":[87.92819799999999,23.814526],"type":"Point"}
}