{
  "type": "Feature",
  "properties": {
    "gn:country":"IN",
    "gn:fcode":"PPL",
    "gn:pop":8247,
    "iso:country":"IN",
    "name:bpy_x_preferred":[
        "\u09a6\u09c8\u09f1\u09be\u09b2\u09be"
    ],
    "name:ceb_x_preferred":[
        "Doiw\u0101la"
    ],
    "name:eng_x_preferred":[
        "Doiwala"
    ],
    "name:ita_x_preferred":[
        "Doiwala"
    ],
    "name:mlg_x_preferred":[
        "Doiwala"
    ],
    "name:msa_x_preferred":[
        "Doiwala"
    ],
    "name:nan_x_preferred":[
        "Doiwala"
    ],
    "name:new_x_preferred":[
        "\u0926\u094b\u0907\u0935\u093e\u0932\u093e"
    ],
    "name:nld_x_preferred":[
        "Doiwala"
    ],
    "name:pol_x_preferred":[
        "Doiwala"
    ],
    "name:por_x_preferred":[
        "Doiwala"
    ],
    "name:swe_x_preferred":[
        "Doiw\u0101la"
    ],
    "name:urd_x_preferred":[
        "\u062f\u0648\u0626\u06cc \u0648\u0627\u0644\u0627"
    ],
    "name:vie_x_preferred":[
        "Doiwala"
    ],
    "name:zho_x_preferred":[
        "\u591a\u4f0a\u74e6\u62c9"
    ],
    "qs:name":"Doiw\u0101la",
    "qs:photos_9r":0,
    "qs:photos_sr":0,
    "qs:pop_sr":"5",
    "wd:wordcount":843,
    "wof:name":"Doiw\u0101la",
    "wof:placetype":"locality",
    "wof:population":8247
},
  "geometry": {"coordinates":[78.11784,30.17895],"type":"Point"}
}