{
  "type": "Feature",
  "properties": {
    "iso:country":"IN",
    "ks:ks_name":"Mambapalli",
    "ks:ks_pop":2920,
    "ks:ks_type":"HABITATION",
    "name:eng_x_preferred":[
        "Mambapalli"
    ],
    "wof:name":"Mambapalli",
    "wof:placetype":"locality",
    "wof:population":2920
},
  "geometry": {"coordinates":[75.48288599999999,11.885549],"type":"Point"}
}