{
  "type": "Feature",
  "properties": {
    "iso:country":"IN",
    "ks:ks_name":"Lingwana",
    "ks:ks_pop":151,
    "ks:ks_type":"HABITATION",
    "name:eng_x_preferred":[
        "Lingwana"
    ],
    "wof:name":"Lingwana",
    "wof:placetype":"locality",
    "wof:population":151
},
  "geometry": {"coordinates":[78.640636,30.272812],"type":"Point"}
}