{
  "type": "Feature",
  "properties": {
    "iso:country":"IN",
    "ks:ks_name":"Uliya",
    "ks:ks_pop":208,
    "ks:ks_type":"HABITATION",
    "name:eng_x_preferred":[
        "Uliya"
    ],
    "wof:name":"Uliya",
    "wof:placetype":"locality",
    "wof:population":208
},
  "geometry": {"coordinates":[75.29268399999999,12.86824],"type":"Point"}
}