{
  "type": "Feature",
  "properties": {
    "iso:country":"IN",
    "ks:ks_name":"Dengapuchi",
    "ks:ks_pop":251,
    "ks:ks_type":"VILLAGE",
    "name:eng_x_preferred":[
        "Dengapuchi"
    ],
    "wof:name":"Dengapuchi",
    "wof:placetype":"locality",
    "wof:population":251
},
  "geometry": {"coordinates":[84.02797,19.439155],"type":"Point"}
}