{
  "type": "Feature",
  "properties": {
    "iso:country":"IN",
    "ks:ks_alt_nam":"nelliatumalcolony",
    "ks:ks_name":"Nelliatumalcolony",
    "ks:ks_pop":896,
    "ks:ks_type":"HABITATION",
    "name:eng_x_preferred":[
        "Nelliatumalcolony"
    ],
    "wof:name":"Nelliatumalcolony",
    "wof:placetype":"locality",
    "wof:population":896
},
  "geometry": {"coordinates":[75.68880299999999,11.540137],"type":"Point"}
}