{
  "type": "Feature",
  "properties": {
    "iso:country":"IN",
    "ks:ks_name":"Bokhari",
    "ks:ks_pop":1534,
    "ks:ks_type":"VILLAGE",
    "ks:ks_uagg_main":0,
    "name:eng_x_preferred":[
        "Bokhari"
    ],
    "wof:name":"Bokhari",
    "wof:placetype":"neighbourhood",
    "wof:population":1534
},
  "geometry": {"coordinates":[85.520293,26.690117],"type":"Point"}
}