{
  "type": "Feature",
  "properties": {
    "gn:admin1_code":"37.0",
    "gn:admin2_code":"416.0",
    "gn:asciiname":"Mahima",
    "gn:country_code":"IN",
    "gn:dem":284,
    "gn:feature_class":"P",
    "gn:feature_code":"PPL",
    "gn:name":"Mahima",
    "gn:population":0,
    "gn:timezone":"Asia/Kolkata",
    "iso:country":"IN",
    "ks:ks_name":"Mahima",
    "ks:ks_pop":173,
    "ks:ks_type":"VILLAGE",
    "name:eng_x_preferred":[
        "Mahima"
    ],
    "wof:name":"Mahima",
    "wof:placetype":"locality",
    "wof:population":173
},
  "geometry": {"coordinates":[81.703968,18.609635],"type":"Point"}
}