{
  "type": "Feature",
  "properties": {
    "iso:country":"IN",
    "ks:ks_name":"Ghasipada",
    "ks:ks_pop":177,
    "ks:ks_type":"VILLAGE",
    "name:eng_x_preferred":[
        "Ghasipada"
    ],
    "wof:name":"Ghasipada",
    "wof:placetype":"locality",
    "wof:population":177
},
  "geometry": {"coordinates":[84.394457,19.772894],"type":"Point"}
}