{
  "type": "Feature",
  "properties": {
    "iso:country":"IN",
    "ks:ks_alt_nam":"vadakkethotty",
    "ks:ks_name":"Vadakkethotty",
    "ks:ks_pop":350,
    "ks:ks_type":"HABITATION",
    "name:eng_x_preferred":[
        "Vadakkethotty"
    ],
    "wof:name":"Vadakkethotty",
    "wof:placetype":"locality",
    "wof:population":350
},
  "geometry": {"coordinates":[76.71576,9.94052],"type":"Point"}
}