{
  "type": "Feature",
  "properties": {
    "iso:country":"IN",
    "ks:ks_name":"Tantgore",
    "ks:ks_pop":465,
    "ks:ks_type":"HABITATION",
    "name:eng_x_preferred":[
        "Tantgore"
    ],
    "wof:name":"Tantgore",
    "wof:placetype":"locality",
    "wof:population":465
},
  "geometry": {"coordinates":[87.610344,23.664342],"type":"Point"}
}