{
  "type": "Feature",
  "properties": {
    "iso:country":"IN",
    "ks:ks_name":"Jogyari",
    "ks:ks_pop":440,
    "ks:ks_type":"HABITATION",
    "name:eng_x_preferred":[
        "Jogyari"
    ],
    "wof:name":"Jogyari",
    "wof:placetype":"locality",
    "wof:population":440
},
  "geometry": {"coordinates":[79.484247,29.57013],"type":"Point"}
}