{
  "type": "Feature",
  "properties": {
    "gn:admin1_code":"19.0",
    "gn:admin2_code":"582.0",
    "gn:asciiname":"Palligutta",
    "gn:country_code":"IN",
    "gn:dem":779,
    "gn:feature_class":"P",
    "gn:feature_code":"PPL",
    "gn:name":"Palligutta",
    "gn:population":0,
    "gn:timezone":"Asia/Kolkata",
    "iso:country":"IN",
    "ks:ks_name":"Pillagutta",
    "ks:ks_pop":190,
    "ks:ks_type":"HABITATION",
    "name:eng_x_preferred":[
        "Pillagutta"
    ],
    "name:eng_x_variant":[
        "Palligutta"
    ],
    "wof:name":"Pillagutta",
    "wof:placetype":"locality",
    "wof:population":190
},
  "geometry": {"coordinates":[77.84910499999999,13.702733],"type":"Point"}
}