{
  "type": "Feature",
  "properties": {
    "gn:admin1_code":"36",
    "gn:admin2_code":"196.0",
    "gn:asciiname":"Makwa",
    "gn:country_code":"IN",
    "gn:dem":80,
    "gn:feature_class":"P",
    "gn:feature_code":"PPL",
    "gn:name":"Makwa",
    "gn:population":0,
    "gn:timezone":"Asia/Kolkata",
    "iso:country":"IN",
    "name:ceb_x_preferred":[
        "Makwa"
    ],
    "name:swe_x_preferred":[
        "Makwa"
    ],
    "wof:name":"Makwa",
    "wof:placetype":"neighbourhood"
},
  "geometry": {"coordinates":[83.18941,25.23407],"type":"Point"}
}