{
  "type": "Feature",
  "properties": {
    "gn:admin1_code":"36.0",
    "gn:admin2_code":"178.0",
    "gn:asciiname":"Manjha Kamharia",
    "gn:country_code":"IN",
    "gn:dem":80,
    "gn:feature_class":"P",
    "gn:feature_code":"PPL",
    "gn:name":"M\u0101njha Kamharia",
    "gn:population":0,
    "gn:timezone":"Asia/Kolkata",
    "iso:country":"IN",
    "wof:name":"Manjha Kamharia",
    "wof:placetype":"locality"
},
  "geometry": {"coordinates":[83.09738,26.37447],"type":"Point"}
}