{
  "type": "Feature",
  "properties": {
    "gn:country":"IN",
    "gn:fcode":"PPL",
    "gn:population":0,
    "iso:country":"IN",
    "name:ceb_x_preferred":[
        "Nandgaon"
    ],
    "name:pol_x_preferred":[
        "Nandgaon"
    ],
    "name:swe_x_preferred":[
        "Nandgaon"
    ],
    "name:und_x_variant":[
        "N\u0101ndgaon"
    ],
    "qs:name":"Nandgaon",
    "qs:name_adm0":"India",
    "qs:name_adm1":"Maharashtra",
    "qs:photos":40,
    "qs:photos_1k":8,
    "qs:photos_9k":1,
    "qs:photos_9r":2,
    "qs:photos_all":40,
    "qs:photos_sr":2,
    "qs:placetype":"Town",
    "qs:pop_sr":"0",
    "wd:wordcount":78,
    "wof:name":"Nandgaon",
    "wof:placetype":"locality",
    "wof:population":0
},
  "geometry": {"coordinates":[72.92983,18.37918],"type":"Point"}
}