{
  "type": "Feature",
  "properties": {
    "gn:admin1_code":"10.0",
    "gn:admin2_code":"072",
    "gn:asciiname":"Banarsidas ka Plot",
    "gn:country_code":"IN",
    "gn:dem":246,
    "gn:feature_class":"P",
    "gn:feature_code":"PPL",
    "gn:name":"Ban\u0101rs\u012bd\u0101s ka Plot",
    "gn:population":0,
    "gn:timezone":"Asia/Kolkata",
    "iso:country":"IN",
    "wof:name":"Banarsidas ka Plot",
    "wof:placetype":"locality"
},
  "geometry": {"coordinates":[76.52984000000002,30.0433],"type":"Point"}
}