{
  "type": "Feature",
  "properties": {
    "iso:country":"IN",
    "ks:ks_name":"Volbailu",
    "ks:ks_pop":192,
    "ks:ks_type":"HABITATION",
    "name:eng_x_preferred":[
        "Volbailu"
    ],
    "wof:name":"Volbailu",
    "wof:placetype":"locality",
    "wof:population":192
},
  "geometry": {"coordinates":[74.679879,13.710967],"type":"Point"}
}