{
  "type": "Feature",
  "properties": {
    "gn:admin1_code":"35",
    "gn:admin2_code":"461.0",
    "gn:asciiname":"Bijapuri",
    "gn:country_code":"IN",
    "gn:dem":760,
    "gn:feature_class":"P",
    "gn:feature_code":"PPL",
    "gn:name":"Bij\u0101puri",
    "gn:population":0,
    "gn:timezone":"Asia/Kolkata",
    "iso:country":"IN",
    "ks:ks_alt_nam":"Bij\u0101puri",
    "ks:ks_name":"Bijapuri",
    "ks:ks_pop":1107,
    "ks:ks_type":"VILLAGE",
    "name:eng_x_preferred":[
        "Bijapuri"
    ],
    "name:eng_x_variant":[
        "Bij\u0101puri"
    ],
    "wof:name":"Bijapuri",
    "wof:placetype":"locality",
    "wof:population":1107
},
  "geometry": {"coordinates":[81.361597,22.996849],"type":"Point"}
}