{
  "type": "Feature",
  "properties": {
    "iso:country":"IN",
    "ks:ks_name":"Gavaliwadi",
    "ks:ks_pop":61,
    "ks:ks_type":"HABITATION",
    "name:eng_x_preferred":[
        "Gavaliwadi"
    ],
    "wof:name":"Gavaliwadi",
    "wof:placetype":"locality",
    "wof:population":61
},
  "geometry": {"coordinates":[73.538675,17.112436],"type":"Point"}
}