{
  "type": "Feature",
  "properties": {
    "gn:country":"IN",
    "gn:fcode":"PPL",
    "gn:population":39243,
    "iso:country":"IN",
    "name:ast_x_preferred":[
        "Giddarbaha"
    ],
    "name:ben_x_preferred":[
        "\u0997\u09bf\u09a6\u09cd\u09a6\u09c7\u09b0\u09ac\u09be\u09b9\u09be"
    ],
    "name:bpy_x_preferred":[
        "\u0997\u09bf\u09a6\u09cd\u09a6\u09c7\u09b0\u09ac\u09be\u09b9\u09be"
    ],
    "name:ceb_x_preferred":[
        "Giddarb\u0101ha"
    ],
    "name:eng_x_preferred":[
        "Giddarbaha"
    ],
    "name:hin_x_preferred":[
        "\u0917\u093f\u0926\u094d\u0926\u0921\u093c\u092c\u093e\u0939\u093e"
    ],
    "name:ita_x_preferred":[
        "Giddarbaha"
    ],
    "name:msa_x_preferred":[
        "Gidderbaha"
    ],
    "name:nan_x_preferred":[
        "Gidderbaha"
    ],
    "name:new_x_preferred":[
        "\u0917\u093f\u0921\u094d\u0921\u0947\u0930\u092c\u0939\u093e"
    ],
    "name:nld_x_preferred":[
        "Gidderbaha"
    ],
    "name:pan_x_preferred":[
        "\u0a17\u0a3f\u0a71\u0a26\u0a5c\u0a2c\u0a3e\u0a39\u0a3e"
    ],
    "name:pnb_x_preferred":[
        "\u06af\u0650\u062f\u0691\u0628\u0627\u06c1\u0627"
    ],
    "name:por_x_preferred":[
        "Gidderbaha"
    ],
    "name:spa_x_preferred":[
        "Giddarbaha"
    ],
    "name:swe_x_preferred":[
        "Giddarb\u0101ha"
    ],
    "name:vie_x_preferred":[
        "Gidderbaha"
    ],
    "name:zho_x_preferred":[
        "\u5409\u5fb7\u5c14\u5df4\u54c8"
    ],
    "qs:name":"Giddarbaha",
    "qs:name_adm0":"India",
    "qs:name_adm1":"Punjab",
    "qs:photos_9k":1,
    "qs:photos_9r":1,
    "qs:photos_all":2,
    "qs:photos_sr":0,
    "qs:placetype":"Town",
    "qs:pop_sr":"7",
    "wd:elevation":189.0,
    "wd:wordcount":1058,
    "wof:name":"Giddarbaha",
    "wof:placetype":"locality",
    "wof:population":39243
},
  "geometry": {"coordinates":[74.66318,30.2023],"type":"Point"}
}