{
  "type": "Feature",
  "properties": {
    "iso:country":"IN",
    "ks:ks_alt_nam":"Narsimha thanda",
    "ks:ks_name":"Narsimha Thanda",
    "ks:ks_pop":73,
    "ks:ks_type":"HABITATION",
    "ks:ks_uagg_main":0,
    "name:eng_x_preferred":[
        "Narsimha Thanda"
    ],
    "wof:name":"Narsimha Thanda",
    "wof:placetype":"neighbourhood",
    "wof:population":73
},
  "geometry": {"coordinates":[79.77030000000001,17.748268],"type":"Point"}
}