{
  "type": "Feature",
  "properties": {
    "iso:country":"IN",
    "ks:ks_name":"Chakir Bhitha E",
    "ks:ks_pop":352,
    "ks:ks_type":"HABITATION",
    "name:eng_x_preferred":[
        "Chakir Bhitha E"
    ],
    "wof:name":"Chakir Bhitha E",
    "wof:placetype":"locality",
    "wof:population":352
},
  "geometry": {"coordinates":[91.055829,26.385224],"type":"Point"}
}