{
  "type": "Feature",
  "properties": {
    "gn:admin1_code":"16",
    "gn:admin2_code":"501.0",
    "gn:asciiname":"Aliabad",
    "gn:country_code":"IN",
    "gn:dem":287,
    "gn:feature_class":"P",
    "gn:feature_code":"PPL",
    "gn:name":"\u0100li\u0101b\u0101d",
    "gn:population":0,
    "gn:timezone":"Asia/Kolkata",
    "iso:country":"IN",
    "name:azb_x_preferred":[
        "\u0639\u0644\u06cc\u200c\u0622\u0628\u0627\u062f"
    ],
    "name:aze_x_preferred":[
        "\u018fliabad"
    ],
    "name:fas_x_preferred":[
        "\u0639\u0644\u06cc\u200c\u0622\u0628\u0627\u062f"
    ],
    "name:hin_x_preferred":[
        "\u0906\u0932\u093f\u092f\u093e\u092c\u093e\u0926"
    ],
    "name:ita_x_preferred":[
        "Aliabad"
    ],
    "name:kat_x_preferred":[
        "\u10d0\u10da\u10d8\u10d0\u10d1\u10d0\u10d3\u10d8"
    ],
    "name:mzn_x_preferred":[
        "\u0639\u0644\u06cc\u200c\u0622\u0628\u0627\u062f"
    ],
    "name:nld_x_preferred":[
        "Aliabad"
    ],
    "name:pol_x_preferred":[
        "Aliabad"
    ],
    "name:tur_x_preferred":[
        "Aliabad"
    ],
    "wof:name":"Aliabad",
    "wof:placetype":"locality"
},
  "geometry": {"coordinates":[77.05698000000002,20.74628],"type":"Point"}
}