{
  "type": "Feature",
  "properties": {
    "iso:country":"IN",
    "ks:ks_name":"Mohan Baba Tola",
    "ks:ks_pop":247,
    "ks:ks_type":"HABITATION",
    "name:eng_x_preferred":[
        "Mohan Baba Tola"
    ],
    "wof:name":"Mohan Baba Tola",
    "wof:placetype":"locality",
    "wof:population":247
},
  "geometry": {"coordinates":[83.985292,26.927152],"type":"Point"}
}