{
  "type": "Feature",
  "properties": {
    "iso:country":"IN",
    "ks:ks_name":"Duldulva",
    "ks:ks_pop":160,
    "ks:ks_type":"HABITATION",
    "name:eng_x_preferred":[
        "Duldulva"
    ],
    "wof:name":"Duldulva",
    "wof:placetype":"locality",
    "wof:population":160
},
  "geometry": {"coordinates":[82.281111,26.519636],"type":"Point"}
}