{
  "type": "Feature",
  "properties": {
    "gn:admin1_code":"13.0",
    "gn:admin2_code":"593.0",
    "gn:asciiname":"Bhagavatikshetram",
    "gn:country_code":"IN",
    "gn:dem":54,
    "gn:feature_class":"P",
    "gn:feature_code":"PPL",
    "gn:name":"Bhagavatiksh\u0113tram",
    "gn:population":0,
    "gn:timezone":"Asia/Kolkata",
    "iso:country":"IN",
    "wof:name":"Bhagavatikshetram",
    "wof:placetype":"locality"
},
  "geometry": {"coordinates":[76.42633000000002,10.97094],"type":"Point"}
}