{
  "type": "Feature",
  "properties": {
    "iso:country":"IN",
    "ks:ks_name":"Brahmanwadi",
    "ks:ks_pop":57,
    "ks:ks_type":"HABITATION",
    "name:eng_x_preferred":[
        "Brahmanwadi"
    ],
    "wof:name":"Brahmanwadi",
    "wof:placetype":"locality",
    "wof:population":57
},
  "geometry": {"coordinates":[73.294522,17.206153],"type":"Point"}
}