{
  "type": "Feature",
  "properties": {
    "iso:country":"IN",
    "ks:ks_name":"Aswari Banjaria",
    "ks:ks_pop":1250,
    "ks:ks_type":"VILLAGE",
    "ks:ks_uagg_main":0,
    "name:eng_x_preferred":[
        "Aswari Banjaria"
    ],
    "wof:name":"Aswari Banjaria",
    "wof:placetype":"neighbourhood",
    "wof:population":1250
},
  "geometry": {"coordinates":[85.145464,26.183517],"type":"Point"}
}