{
  "type": "Feature",
  "properties": {
    "gn:admin1_code":"11",
    "gn:asciiname":"Tibi",
    "gn:country_code":"IN",
    "gn:dem":710,
    "gn:feature_class":"P",
    "gn:feature_code":"PPL",
    "gn:name":"Tibi",
    "gn:population":0,
    "gn:timezone":"Asia/Kolkata",
    "iso:country":"IN",
    "name:ceb_x_preferred":[
        "Tibi"
    ],
    "name:deu_x_preferred":[
        "Tibi"
    ],
    "name:heb_x_preferred":[
        "\u05d8\u05d9\u05d1\u05d9"
    ],
    "name:rus_x_preferred":[
        "\u0422\u0438\u0431\u0438"
    ],
    "name:swe_x_preferred":[
        "Tibi"
    ],
    "name:tgl_x_preferred":[
        "Tibi"
    ],
    "name:ukr_x_preferred":[
        "\u0422\u0456\u0431\u0456"
    ],
    "wof:name":"Tibi",
    "wof:placetype":"locality"
},
  "geometry": {"coordinates":[76.99171,30.77936],"type":"Point"}
}