{
  "type": "Feature",
  "properties": {
    "gn:admin1_code":"11",
    "gn:asciiname":"Tibi",
    "gn:country_code":"IN",
    "gn:dem":710,
    "gn:feature_class":"P",
    "gn:feature_code":"PPL",
    "gn:name":"Tibi",
    "gn:population":0,
    "gn:timezone":"Asia/Kolkata",
    "iso:country":"IN",
    "wof:name":"Tibi",
    "wof:placetype":"locality"
},
  "geometry": {"coordinates":[76.99171,30.77936],"type":"Point"}
}