{
  "type": "Feature",
  "properties": {
    "iso:country":"IN",
    "ks:ks_alt_nam":"Rothia",
    "ks:ks_name":"Rotiha",
    "ks:ks_pop":190,
    "ks:ks_type":"VILLAGE",
    "ks:ks_uagg_main":0,
    "name:eng_x_preferred":[
        "Rotiha"
    ],
    "name:eng_x_variant":[
        "Rothia"
    ],
    "wof:name":"Rotiha",
    "wof:placetype":"neighbourhood",
    "wof:population":190
},
  "geometry": {"coordinates":[81.140041,27.812361],"type":"Point"}
}