{
  "type": "Feature",
  "properties": {
    "iso:country":"IN",
    "ks:ks_name":"Gundikhan",
    "ks:ks_pop":708,
    "ks:ks_type":"VILLAGE",
    "name:eng_x_preferred":[
        "Gundikhan"
    ],
    "wof:name":"Gundikhan",
    "wof:placetype":"locality",
    "wof:population":708
},
  "geometry": {"coordinates":[73.047861,24.374056],"type":"Point"}
}