{
  "type": "Feature",
  "properties": {
    "iso:country":"IN",
    "ks:ks_name":"Gangtal",
    "ks:ks_pop":169,
    "ks:ks_type":"VILLAGE",
    "name:eng_x_preferred":[
        "Gangtal"
    ],
    "wof:name":"Gangtal",
    "wof:placetype":"locality",
    "wof:population":169
},
  "geometry": {"coordinates":[79.000187,30.373942],"type":"Point"}
}