{
  "type": "Feature",
  "properties": {
    "iso:country":"IN",
    "ks:ks_name":"Jaffrabad",
    "ks:ks_pop":4500,
    "ks:ks_type":"VILLAGE",
    "ks:ks_uagg_main":0,
    "name:eng_x_preferred":[
        "Jaffrabad"
    ],
    "wof:name":"Jaffrabad",
    "wof:placetype":"locality",
    "wof:population":4500
},
  "geometry": {"coordinates":[78.607268,12.69073],"type":"Point"}
}