{
  "type": "Feature",
  "properties": {
    "gn:admin1_code":"24.0",
    "gn:admin2_code":"110.0",
    "gn:asciiname":"Sirohi",
    "gn:country_code":"IN",
    "gn:dem":461,
    "gn:feature_class":"P",
    "gn:feature_code":"PPL",
    "gn:name":"Sirohi",
    "gn:population":0,
    "gn:timezone":"Asia/Kolkata",
    "iso:country":"IN",
    "name:ben_x_preferred":[
        "\u09b8\u09bf\u09b0\u09cb\u09b9\u09bf"
    ],
    "name:bpy_x_preferred":[
        "\u09b8\u09bf\u09b0\u09cb\u09b9\u09bf"
    ],
    "name:cat_x_preferred":[
        "Sirohi"
    ],
    "name:ceb_x_preferred":[
        "Sirohi"
    ],
    "name:deu_x_preferred":[
        "Sirohi"
    ],
    "name:fra_x_preferred":[
        "Sirohi"
    ],
    "name:guj_x_preferred":[
        "\u0ab8\u0abf\u0ab0\u0acb\u0ab9\u0ac0"
    ],
    "name:hif_x_preferred":[
        "Sirohi"
    ],
    "name:hin_x_preferred":[
        "\u0938\u093f\u0930\u094b\u0939\u0940"
    ],
    "name:ita_x_preferred":[
        "Sirohi"
    ],
    "name:jpn_x_preferred":[
        "\u30b7\u30ed\u30fc\u30d2\u30fc"
    ],
    "name:mar_x_preferred":[
        "\u0938\u093f\u0930\u094b\u0939\u0940"
    ],
    "name:mlg_x_preferred":[
        "Sirohi"
    ],
    "name:msa_x_preferred":[
        "Sirohi"
    ],
    "name:nep_x_preferred":[
        "\u0938\u093f\u0930\u094b\u0939\u0940"
    ],
    "name:nor_x_preferred":[
        "Sirohi"
    ],
    "name:ori_x_preferred":[
        "\u0b38\u0b3f\u0b30\u0b4b\u0b39\u0b3f"
    ],
    "name:pam_x_preferred":[
        "Sirohi"
    ],
    "name:pol_x_preferred":[
        "Sirohi"
    ],
    "name:rus_x_preferred":[
        "\u0421\u0438\u0440\u043e\u0445\u0438"
    ],
    "name:san_x_preferred":[
        "\u0938\u093f\u0930\u094b\u0939\u0940"
    ],
    "name:swe_x_preferred":[
        "Sirohi"
    ],
    "name:urd_x_preferred":[
        "\u0633\u0631\u0648\u06c1\u06cc"
    ],
    "name:vie_x_preferred":[
        "Sirohi"
    ],
    "name:xmf_x_preferred":[
        "\u10e1\u10d8\u10e0\u10dd\u10f0\u10d8"
    ],
    "name:zho_x_preferred":[
        "\u897f\u7f57\u5e0c"
    ],
    "wof:name":"Sirohi",
    "wof:placetype":"locality"
},
  "geometry": {"coordinates":[75.90071999999998,27.23063],"type":"Point"}
}