{
  "type": "Feature",
  "properties": {
    "gn:admin1_code":"35.0",
    "gn:admin2_code":"450.0",
    "gn:asciiname":"Kharkhari",
    "gn:country_code":"IN",
    "gn:dem":411,
    "gn:feature_class":"P",
    "gn:feature_code":"PPL",
    "gn:name":"Kharkhari",
    "gn:population":0,
    "gn:timezone":"Asia/Kolkata",
    "iso:country":"IN",
    "name:bpy_x_preferred":[
        "\u0996\u09be\u0996\u09be\u09b0\u09bf"
    ],
    "name:ita_x_preferred":[
        "Kharkhari"
    ],
    "name:msa_x_preferred":[
        "Kharkhari"
    ],
    "name:new_x_preferred":[
        "\u0916\u0930\u094d\u0916\u0930\u0940"
    ],
    "name:por_x_preferred":[
        "Kharkhari"
    ],
    "name:vie_x_preferred":[
        "Kharkhari"
    ],
    "name:zho_x_preferred":[
        "\u5361\u5c14\u5361\u91cc"
    ],
    "wof:name":"Kharkhari",
    "wof:placetype":"locality"
},
  "geometry": {"coordinates":[80.2538,23.72864],"type":"Point"}
}