{
  "type": "Feature",
  "properties": {
    "gn:admin1_code":"35.0",
    "gn:admin2_code":"450.0",
    "gn:asciiname":"Kharkhari",
    "gn:country_code":"IN",
    "gn:dem":411,
    "gn:feature_class":"P",
    "gn:feature_code":"PPL",
    "gn:name":"Kharkhari",
    "gn:population":0,
    "gn:timezone":"Asia/Kolkata",
    "iso:country":"IN",
    "wof:name":"Kharkhari",
    "wof:placetype":"locality"
},
  "geometry": {"coordinates":[80.2538,23.72864],"type":"Point"}
}