{
  "type": "Feature",
  "properties": {
    "iso:country":"IN",
    "ks:ks_name":"Chauraha Manguradila",
    "ks:ks_pop":350,
    "ks:ks_type":"HABITATION",
    "name:eng_x_preferred":[
        "Chauraha Manguradila"
    ],
    "wof:name":"Chauraha Manguradila",
    "wof:placetype":"locality",
    "wof:population":350
},
  "geometry": {"coordinates":[82.74462,26.390001],"type":"Point"}
}