{
  "type": "Feature",
  "properties": {
    "iso:country":"IN",
    "ks:ks_alt_nam":"JITEN AKHRA",
    "ks:ks_name":"Jiten Akhra",
    "ks:ks_pop":275,
    "ks:ks_type":"HABITATION",
    "name:eng_x_preferred":[
        "Jiten Akhra"
    ],
    "wof:name":"Jiten Akhra",
    "wof:placetype":"locality",
    "wof:population":275
},
  "geometry": {"coordinates":[91.69475199999999,24.111035],"type":"Point"}
}