{
  "type": "Feature",
  "properties": {
    "gn:admin1_code":"16.0",
    "gn:admin2_code":"508.0",
    "gn:asciiname":"Makkepalli",
    "gn:country_code":"IN",
    "gn:dem":269,
    "gn:feature_class":"P",
    "gn:feature_code":"PPL",
    "gn:name":"Makkepalli",
    "gn:population":0,
    "gn:timezone":"Asia/Kolkata",
    "iso:country":"IN",
    "ks:ks_name":"Makkepalli",
    "ks:ks_type":"VILLAGE",
    "name:eng_x_preferred":[
        "Makkepalli"
    ],
    "wof:name":"Makkepalli",
    "wof:placetype":"locality"
},
  "geometry": {"coordinates":[80.17348699999999,19.669421],"type":"Point"}
}