{
  "type": "Feature",
  "properties": {
    "iso:country":"IN",
    "ks:ks_name":"Maharaj Nagar",
    "ks:ks_pop":699,
    "ks:ks_type":"HABITATION",
    "name:eng_x_preferred":[
        "Maharaj Nagar"
    ],
    "wof:name":"Maharaj Nagar",
    "wof:placetype":"locality",
    "wof:population":699
},
  "geometry": {"coordinates":[80.108333,26.620278],"type":"Point"}
}