{
  "type": "Feature",
  "properties": {
    "gn:admin1_code":"19.0",
    "gn:admin2_code":"577.0",
    "gn:asciiname":"Bhogval-Vadiyanpur",
    "gn:country_code":"IN",
    "gn:dem":762,
    "gn:feature_class":"P",
    "gn:feature_code":"PPL",
    "gn:name":"Bh\u014dgv\u0101l-Vadiyanp\u016br",
    "gn:population":0,
    "gn:timezone":"Asia/Kolkata",
    "iso:country":"IN",
    "wof:name":"Bhogval-Vadiyanpur",
    "wof:placetype":"locality"
},
  "geometry": {"coordinates":[76.55638,11.9431],"type":"Point"}
}