{
  "type": "Feature",
  "properties": {
    "gn:admin1_code":"36",
    "gn:admin2_code":"188.0",
    "gn:asciiname":"Rakauli",
    "gn:country_code":"IN",
    "gn:dem":79,
    "gn:feature_class":"P",
    "gn:feature_code":"PPL",
    "gn:name":"Rakauli",
    "gn:population":0,
    "gn:timezone":"Asia/Kolkata",
    "iso:country":"IN",
    "ks:ks_name":"Rakauli",
    "ks:ks_pop":645,
    "ks:ks_type":"VILLAGE",
    "ks:ks_uagg_main":0,
    "name:eng_x_preferred":[
        "Rakauli"
    ],
    "wof:name":"Rakauli",
    "wof:placetype":"neighbourhood",
    "wof:population":645
},
  "geometry": {"coordinates":[83.32094600000001,26.362923],"type":"Point"}
}