{
  "type": "Feature",
  "properties": {
    "iso:country":"IN",
    "ks:ks_name":"Adargolli",
    "ks:ks_pop":472,
    "ks:ks_type":"HABITATION",
    "name:eng_x_preferred":[
        "Adargolli"
    ],
    "wof:name":"Adargolli",
    "wof:placetype":"locality",
    "wof:population":472
},
  "geometry": {"coordinates":[74.63054200000001,13.77384],"type":"Point"}
}