{
  "type": "Feature",
  "properties": {
    "gn:admin1_code":"35",
    "gn:admin2_code":"420.0",
    "gn:asciiname":"Nepalsingh ka Pura",
    "gn:country_code":"IN",
    "gn:dem":163,
    "gn:feature_class":"P",
    "gn:feature_code":"PPL",
    "gn:name":"Nep\u0101lsingh ka Pura",
    "gn:population":0,
    "gn:timezone":"Asia/Kolkata",
    "iso:country":"IN",
    "wof:name":"Nepalsingh ka Pura",
    "wof:placetype":"locality"
},
  "geometry": {"coordinates":[78.40886999999999,26.50778],"type":"Point"}
}