{
  "type": "Feature",
  "properties": {
    "gn:admin1_code":"36.0",
    "gn:admin2_code":"162.0",
    "gn:asciiname":"Purwa Gaja",
    "gn:country_code":"IN",
    "gn:dem":143,
    "gn:feature_class":"P",
    "gn:feature_code":"PPL",
    "gn:name":"Purwa Gaja",
    "gn:population":0,
    "gn:timezone":"Asia/Kolkata",
    "iso:country":"IN",
    "ks:ks_name":"Purwa Gaja",
    "ks:ks_pop":375,
    "ks:ks_type":"HABITATION",
    "name:eng_x_preferred":[
        "Purwa Gaja"
    ],
    "wof:name":"Purwa Gaja",
    "wof:placetype":"locality",
    "wof:population":375
},
  "geometry": {"coordinates":[79.73286299999999,26.768],"type":"Point"}
}