{
  "type": "Feature",
  "properties": {
    "iso:country":"IN",
    "ks:ks_name":"Chakdarbaru",
    "ks:ks_pop":154,
    "ks:ks_type":"VILLAGE",
    "ks:ks_uagg_main":0,
    "name:eng_x_preferred":[
        "Chakdarbaru"
    ],
    "wof:name":"Chakdarbaru",
    "wof:placetype":"neighbourhood",
    "wof:population":154
},
  "geometry": {"coordinates":[88.38378299999999,25.455758],"type":"Point"}
}