{
  "type": "Feature",
  "properties": {
    "iso:country":"IN",
    "ks:ks_name":"Palaiyapura",
    "ks:ks_pop":381,
    "ks:ks_type":"HABITATION",
    "name:eng_x_preferred":[
        "Palaiyapura"
    ],
    "wof:name":"Palaiyapura",
    "wof:placetype":"locality",
    "wof:population":381
},
  "geometry": {"coordinates":[72.759472,22.581639],"type":"Point"}
}