{
  "type": "Feature",
  "properties": {
    "gn:admin1_code":"34.0",
    "gn:admin2_code":"216.0",
    "gn:asciiname":"Sadullahpur Bhergara",
    "gn:country_code":"IN",
    "gn:dem":55,
    "gn:feature_class":"P",
    "gn:feature_code":"PPL",
    "gn:name":"S\u0101dull\u0101hpur Bhergara",
    "gn:population":0,
    "gn:timezone":"Asia/Kolkata",
    "iso:country":"IN",
    "wof:name":"Sadullahpur Bhergara",
    "wof:placetype":"locality"
},
  "geometry": {"coordinates":[85.59737,25.94869],"type":"Point"}
}