{
  "type": "Feature",
  "properties": {
    "iso:country":"IN",
    "ks:ks_name":"Amaura",
    "ks:ks_pop":592,
    "ks:ks_type":"HABITATION",
    "name:eng_x_preferred":[
        "Amaura"
    ],
    "wof:name":"Amaura",
    "wof:placetype":"locality",
    "wof:population":592
},
  "geometry": {"coordinates":[81.43400200000001,25.471375],"type":"Point"}
}