{
  "type": "Feature",
  "properties": {
    "iso:country":"IN",
    "ks:ks_name":"Gramchuk",
    "ks:ks_pop":253,
    "ks:ks_type":"HABITATION",
    "name:eng_x_preferred":[
        "Gramchuk"
    ],
    "wof:name":"Gramchuk",
    "wof:placetype":"locality",
    "wof:population":253
},
  "geometry": {"coordinates":[94.232016,27.147931],"type":"Point"}
}