{
  "type": "Feature",
  "properties": {
    "iso:country":"IN",
    "ks:ks_name":"Masjid Tola",
    "ks:ks_pop":250,
    "ks:ks_type":"HABITATION",
    "name:eng_x_preferred":[
        "Masjid Tola"
    ],
    "wof:name":"Masjid Tola",
    "wof:placetype":"locality",
    "wof:population":250
},
  "geometry": {"coordinates":[87.500181,25.984978],"type":"Point"}
}