{
  "type": "Feature",
  "properties": {
    "iso:country":"IN",
    "ks:ks_name":"Dobra",
    "ks:ks_pop":64,
    "ks:ks_type":"VILLAGE",
    "name:eng_x_preferred":[
        "Dobra"
    ],
    "wof:name":"Dobra",
    "wof:placetype":"locality",
    "wof:population":64
},
  "geometry": {"coordinates":[78.574234,30.20707],"type":"Point"}
}