{
  "type": "Feature",
  "properties": {
    "iso:country":"IN",
    "ks:ks_alt_nam":"Pudur AD Colony",
    "ks:ks_name":"Pudur Ad Colony",
    "ks:ks_pop":408,
    "ks:ks_type":"HABITATION",
    "ks:ks_uagg_main":0,
    "name:eng_x_preferred":[
        "Pudur Ad Colony"
    ],
    "wof:name":"Pudur Ad Colony",
    "wof:placetype":"neighbourhood",
    "wof:population":408
},
  "geometry": {"coordinates":[78.679418,10.445472],"type":"Point"}
}