{
  "type": "Feature",
  "properties": {
    "iso:country":"IN",
    "ks:ks_name":"Khehoi",
    "ks:ks_pop":651,
    "ks:ks_type":"HABITATION",
    "ks:ks_uagg_main":0,
    "name:eng_x_preferred":[
        "Khehoi"
    ],
    "wof:name":"Khehoi",
    "wof:placetype":"neighbourhood",
    "wof:population":651
},
  "geometry": {"coordinates":[93.969283,25.928593],"type":"Point"}
}