{
  "type": "Feature",
  "properties": {
    "iso:country":"IN",
    "ks:ks_alt_nam":"KEBAT BIGHA",
    "ks:ks_name":"Kebat Bigha",
    "ks:ks_pop":180,
    "ks:ks_type":"HABITATION",
    "name:eng_x_preferred":[
        "Kebat Bigha"
    ],
    "wof:name":"Kebat Bigha",
    "wof:placetype":"locality",
    "wof:population":180
},
  "geometry": {"coordinates":[84.880216,25.221147],"type":"Point"}
}