{
  "type": "Feature",
  "properties": {
    "iso:country":"IN",
    "ks:ks_alt_nam":"GHATGE WASTI",
    "ks:ks_name":"Ghatge Wasti",
    "ks:ks_pop":78,
    "ks:ks_type":"HABITATION",
    "name:eng_x_preferred":[
        "Ghatge Wasti"
    ],
    "wof:name":"Ghatge Wasti",
    "wof:placetype":"locality",
    "wof:population":78
},
  "geometry": {"coordinates":[74.43536400000001,17.349426],"type":"Point"}
}