{
  "type": "Feature",
  "properties": {
    "iso:country":"IN",
    "ks:ks_name":"Bar Puri",
    "ks:ks_pop":444,
    "ks:ks_type":"VILLAGE",
    "name:eng_x_preferred":[
        "Bar Puri"
    ],
    "wof:name":"Bar Puri",
    "wof:placetype":"locality",
    "wof:population":444
},
  "geometry": {"coordinates":[87.58718,22.315099],"type":"Point"}
}