{
  "type": "Feature",
  "properties": {
    "iso:country":"IN",
    "ks:ks_name":"Kajarekond",
    "ks:ks_pop":216,
    "ks:ks_type":"HABITATION",
    "name:eng_x_preferred":[
        "Kajarekond"
    ],
    "wof:name":"Kajarekond",
    "wof:placetype":"locality",
    "wof:population":216
},
  "geometry": {"coordinates":[73.444278,17.068832],"type":"Point"}
}