{
  "type": "Feature",
  "properties": {
    "iso:country":"IN",
    "ks:ks_name":"Jaipanga",
    "ks:ks_pop":238,
    "ks:ks_type":"VILLAGE",
    "name:eng_x_preferred":[
        "Jaipanga"
    ],
    "wof:name":"Jaipanga",
    "wof:placetype":"locality",
    "wof:population":238
},
  "geometry": {"coordinates":[83.707741,19.293711],"type":"Point"}
}