{
  "type": "Feature",
  "properties": {
    "iso:country":"IN",
    "ks:ks_name":"Adda Lidhuara",
    "ks:ks_pop":60,
    "ks:ks_type":"HABITATION",
    "name:eng_x_preferred":[
        "Adda Lidhuara"
    ],
    "wof:name":"Adda Lidhuara",
    "wof:placetype":"locality",
    "wof:population":60
},
  "geometry": {"coordinates":[79.34704600000001,26.688152],"type":"Point"}
}