{
  "type": "Feature",
  "properties": {
    "iso:country":"IN",
    "ks:ks_name":"Pahadpur",
    "ks:ks_pop":511,
    "ks:ks_type":"VILLAGE",
    "name:eng_x_preferred":[
        "Pahadpur"
    ],
    "wof:name":"Pahadpur",
    "wof:placetype":"locality",
    "wof:population":511
},
  "geometry": {"coordinates":[86.594178,22.219052],"type":"Point"}
}