{
  "type": "Feature",
  "properties": {
    "gn:admin1_code":"16.0",
    "gn:admin2_code":"521",
    "gn:asciiname":"Katphal",
    "gn:country_code":"IN",
    "gn:dem":581,
    "gn:feature_class":"P",
    "gn:feature_code":"PPL",
    "gn:name":"Katphal",
    "gn:population":0,
    "gn:timezone":"Asia/Kolkata",
    "iso:country":"IN",
    "wof:name":"Katphal",
    "wof:placetype":"locality"
},
  "geometry": {"coordinates":[74.61521,18.23981],"type":"Point"}
}