{
  "type": "Feature",
  "properties": {
    "iso:country":"IN",
    "ks:ks_name":"Simrakita",
    "ks:ks_pop":61,
    "ks:ks_type":"HABITATION",
    "name:eng_x_preferred":[
        "Simrakita"
    ],
    "wof:name":"Simrakita",
    "wof:placetype":"locality",
    "wof:population":61
},
  "geometry": {"coordinates":[87.12559400000001,24.710935],"type":"Point"}
}