{
  "type": "Feature",
  "properties": {
    "gn:admin1_code":"36.0",
    "gn:admin2_code":"133.0",
    "gn:asciiname":"Muhammadpur Mafi",
    "gn:country_code":"IN",
    "gn:dem":237,
    "gn:feature_class":"P",
    "gn:feature_code":"PPL",
    "gn:name":"Muhammadpur Mafi",
    "gn:population":0,
    "gn:timezone":"Asia/Kolkata",
    "iso:country":"IN",
    "ks:ks_name":"Mohammadpur Mafi",
    "ks:ks_pop":1182,
    "ks:ks_type":"VILLAGE",
    "ks:ks_uagg_main":0,
    "name:eng_x_preferred":[
        "Mohammadpur Mafi"
    ],
    "wof:name":"Mohammadpur Mafi",
    "wof:placetype":"neighbourhood",
    "wof:population":1182
},
  "geometry": {"coordinates":[77.689014,29.249348],"type":"Point"}
}