{
  "type": "Feature",
  "properties": {
    "iso:country":"IN",
    "ks:ks_name":"Banamali A",
    "ks:ks_pop":509,
    "ks:ks_type":"HABITATION",
    "name:eng_x_preferred":[
        "Banamali A"
    ],
    "wof:name":"Banamali A",
    "wof:placetype":"locality",
    "wof:population":509
},
  "geometry": {"coordinates":[92.30615299999999,24.885236],"type":"Point"}
}