{
  "type": "Feature",
  "properties": {
    "gn:admin1_code":"35",
    "gn:admin2_code":"447.0",
    "gn:asciiname":"Dabhori",
    "gn:country_code":"IN",
    "gn:dem":640,
    "gn:feature_class":"P",
    "gn:feature_code":"PPL",
    "gn:name":"Dabhori",
    "gn:population":0,
    "gn:timezone":"Asia/Kolkata",
    "iso:country":"IN",
    "wof:name":"Dabhori",
    "wof:placetype":"locality"
},
  "geometry": {"coordinates":[77.84126999999999,21.84952],"type":"Point"}
}