{
  "type": "Feature",
  "properties": {
    "iso:country":"IN",
    "ks:ks_name":"Sangra Nadi",
    "ks:ks_pop":1219,
    "ks:ks_type":"VILLAGE",
    "name:eng_x_preferred":[
        "Sangra Nadi"
    ],
    "wof:name":"Sangra Nadi",
    "wof:placetype":"locality",
    "wof:population":1219
},
  "geometry": {"coordinates":[72.2659,26.133069],"type":"Point"}
}