{
  "type": "Feature",
  "properties": {
    "iso:country":"IN",
    "ks:ks_name":"Salarbona",
    "ks:ks_pop":157,
    "ks:ks_type":"HABITATION",
    "name:eng_x_preferred":[
        "Salarbona"
    ],
    "wof:name":"Salarbona",
    "wof:placetype":"locality",
    "wof:population":157
},
  "geometry": {"coordinates":[86.98545300000001,24.656454],"type":"Point"}
}