{
  "type": "Feature",
  "properties": {
    "iso:country":"IN",
    "name:eng_x_preferred":[
        "Nayarambalam"
    ],
    "name:mal_x_preferred":[
        "\u0d28\u0d3e\u0d2f\u0d30\u0d2e\u0d4d\u0d2a\u0d32\u0d02"
    ],
    "name:nld_x_preferred":[
        "Nayarambalam"
    ],
    "qs:name":"Nayarambalam",
    "qs:name_adm0":"India",
    "qs:name_adm1":"Kerala",
    "qs:photos":84,
    "qs:photos_1k":17,
    "qs:photos_9k":1,
    "qs:photos_9r":3,
    "qs:photos_all":84,
    "qs:photos_sr":3,
    "qs:placetype":"Town",
    "qs:pop_sr":"0",
    "wd:wordcount":1196,
    "wof:name":"Nayarambalam",
    "wof:placetype":"locality"
},
  "geometry": {"coordinates":[76.211471,10.081431],"type":"Point"}
}