{
  "type": "Feature",
  "properties": {
    "iso:country":"IN",
    "ks:ks_alt_nam":"Madakunnu school padi",
    "ks:ks_name":"Madakunnu School Padi",
    "ks:ks_pop":537,
    "ks:ks_type":"HABITATION",
    "name:eng_x_preferred":[
        "Madakunnu School Padi"
    ],
    "wof:name":"Madakunnu School Padi",
    "wof:placetype":"locality",
    "wof:population":537
},
  "geometry": {"coordinates":[76.020263,11.650983],"type":"Point"}
}