{
  "type": "Feature",
  "properties": {
    "gn:admin1_code":"24.0",
    "gn:admin2_code":"100",
    "gn:asciiname":"Fattehgarh",
    "gn:country_code":"IN",
    "gn:dem":183,
    "gn:feature_class":"P",
    "gn:feature_code":"PPL",
    "gn:name":"Fattehgarh",
    "gn:population":0,
    "gn:timezone":"Asia/Kolkata",
    "iso:country":"IN",
    "name:und_x_variant":[
        "Fatehgarh",
        "Fattehgarh"
    ],
    "wof:name":"Fattehgarh",
    "wof:placetype":"locality"
},
  "geometry": {"coordinates":[74.24384999999999,29.51001],"type":"Point"}
}