{
  "type": "Feature",
  "properties": {
    "iso:country":"IN",
    "ks:ks_name":"Nikhral",
    "ks:ks_pop":2048,
    "ks:ks_type":"VILLAGE",
    "ks:ks_uagg_main":0,
    "name:eng_x_preferred":[
        "Nikhral"
    ],
    "wof:name":"Nikhral",
    "wof:placetype":"neighbourhood",
    "wof:population":2048
},
  "geometry": {"coordinates":[88.02586100000001,25.482358],"type":"Point"}
}