{
  "type": "Feature",
  "properties": {
    "iso:country":"IN",
    "ks:ks_name":"East Shriram Dewari",
    "ks:ks_pop":383,
    "ks:ks_type":"HABITATION",
    "ks:ks_uagg_main":0,
    "name:eng_x_preferred":[
        "East Shriram Dewari"
    ],
    "wof:name":"East Shriram Dewari",
    "wof:placetype":"neighbourhood",
    "wof:population":383
},
  "geometry": {"coordinates":[94.332605,27.048252],"type":"Point"}
}