{
  "type": "Feature",
  "properties": {
    "iso:country":"IN",
    "ks:ks_name":"Vaddinakoppa",
    "ks:ks_pop":203,
    "ks:ks_type":"HABITATION",
    "name:eng_x_preferred":[
        "Vaddinakoppa"
    ],
    "wof:name":"Vaddinakoppa",
    "wof:placetype":"locality",
    "wof:population":203
},
  "geometry": {"coordinates":[74.946968,14.59107],"type":"Point"}
}