{
  "type": "Feature",
  "properties": {
    "iso:country":"IN",
    "ks:ks_name":"Shekatawadi",
    "ks:ks_pop":315,
    "ks:ks_type":"HABITATION",
    "name:eng_x_preferred":[
        "Shekatawadi"
    ],
    "wof:name":"Shekatawadi",
    "wof:placetype":"locality",
    "wof:population":315
},
  "geometry": {"coordinates":[73.617988,19.517582],"type":"Point"}
}