{
  "type": "Feature",
  "properties": {
    "gn:admin1_code":"35",
    "gn:admin2_code":"426.0",
    "gn:asciiname":"Ranipur",
    "gn:country_code":"IN",
    "gn:dem":340,
    "gn:feature_class":"P",
    "gn:feature_code":"PPL",
    "gn:name":"R\u0101nipur",
    "gn:population":0,
    "gn:timezone":"Asia/Kolkata",
    "iso:country":"IN",
    "name:ara_x_preferred":[
        "\u0631\u0627\u0646\u064a\u0628\u0648\u0631"
    ],
    "name:ben_bn_x_preferred":[
        "\u09b0\u09be\u09a8\u09c0\u09aa\u09c1\u09b0"
    ],
    "name:ben_in_x_preferred":[
        "\u09b0\u09be\u09a8\u09c0\u09aa\u09c1\u09b0"
    ],
    "name:guj_x_preferred":[
        "\u0ab0\u0abe\u0aa8\u0ac0\u0aaa\u0ac1\u0ab0"
    ],
    "name:hin_x_preferred":[
        "\u0930\u093e\u0928\u0940\u092a\u0941\u0930"
    ],
    "name:kan_x_preferred":[
        "\u0cb0\u0cbe\u0ca3\u0cbf\u0caa\u0cc1\u0cb0"
    ],
    "name:mal_x_preferred":[
        "\u0d31\u0d3e\u0d23\u0d3f\u0d2a\u0d42\u0d7c"
    ],
    "name:mar_x_preferred":[
        "\u0930\u093e\u0928\u0940\u092a\u0942\u0930"
    ],
    "name:pan_x_preferred":[
        "\u0a30\u0a3e\u0a23\u0a40\u0a2a\u0a41\u0a30"
    ],
    "name:pol_x_preferred":[
        "Ranipur"
    ],
    "name:snd_x_preferred":[
        "\u0631\u0627\u06bb\u064a \u067e\u0648\u0631"
    ],
    "name:tam_x_preferred":[
        "\u0bb0\u0bbe\u0ba3\u0bbf\u0baa\u0bcd\u0baa\u0bc2\u0bb0\u0bcd"
    ],
    "name:tel_x_preferred":[
        "\u0c30\u0c3e\u0c23\u0c3f\u0c2a\u0c42\u0c30\u0c4d"
    ],
    "name:urd_x_preferred":[
        "\u0631\u0627\u0646\u06cc \u067e\u0648\u0631"
    ],
    "wof:name":"Ranipur",
    "wof:placetype":"locality"
},
  "geometry": {"coordinates":[80.28223,24.57973],"type":"Point"}
}