{
  "type": "Feature",
  "properties": {
    "iso:country":"IN",
    "ks:ks_name":"Harizan Tola",
    "ks:ks_pop":286,
    "ks:ks_type":"HABITATION",
    "name:eng_x_preferred":[
        "Harizan Tola"
    ],
    "wof:name":"Harizan Tola",
    "wof:placetype":"locality",
    "wof:population":286
},
  "geometry": {"coordinates":[86.20669100000001,24.137486],"type":"Point"}
}