{
  "type": "Feature",
  "properties": {
    "iso:country":"IN",
    "ks:ks_name":"Chotakanshirada",
    "ks:ks_pop":265,
    "ks:ks_type":"HABITATION",
    "name:eng_x_preferred":[
        "Chotakanshirada"
    ],
    "wof:name":"Chotakanshirada",
    "wof:placetype":"locality",
    "wof:population":265
},
  "geometry": {"coordinates":[74.736914,15.194683],"type":"Point"}
}