{
  "type": "Feature",
  "properties": {
    "iso:country":"IN",
    "ks:ks_name":"Mahendhrapuram",
    "ks:ks_pop":520,
    "ks:ks_type":"HABITATION",
    "name:eng_x_preferred":[
        "Mahendhrapuram"
    ],
    "wof:name":"Mahendhrapuram",
    "wof:placetype":"locality",
    "wof:population":520
},
  "geometry": {"coordinates":[84.412863,18.856537],"type":"Point"}
}