{
  "type": "Feature",
  "properties": {
    "iso:country":"IN",
    "ks:ks_name":"Pharka",
    "ks:ks_pop":0,
    "ks:ks_type":"VILLAGE",
    "name:eng_x_preferred":[
        "Pharka"
    ],
    "wof:name":"Pharka",
    "wof:placetype":"locality",
    "wof:population":0
},
  "geometry": {"coordinates":[85.679554,24.745905],"type":"Point"}
}