{
  "type": "Feature",
  "properties": {
    "iso:country":"IN",
    "ks:ks_name":"Girana Sakhar Karkhana",
    "ks:ks_pop":1150,
    "ks:ks_type":"HABITATION",
    "name:eng_x_preferred":[
        "Girana Sakhar Karkhana"
    ],
    "wof:name":"Girana Sakhar Karkhana",
    "wof:placetype":"neighbourhood",
    "wof:population":1150
},
  "geometry": {"coordinates":[74.465498,20.559065],"type":"Point"}
}