{
  "type": "Feature",
  "properties": {
    "iso:country":"IN",
    "ks:ks_alt_nam":"KALLYI  RD",
    "ks:ks_name":"Kallyi Rd",
    "ks:ks_pop":681,
    "ks:ks_type":"HABITATION",
    "name:eng_x_preferred":[
        "Kallyi Rd"
    ],
    "name:eng_x_variant":[
        "KALLYI  RD"
    ],
    "wof:name":"Kallyi Rd",
    "wof:placetype":"locality",
    "wof:population":681
},
  "geometry": {"coordinates":[76.033753,10.581047],"type":"Point"}
}