{
  "type": "Feature",
  "properties": {
    "iso:country":"IN",
    "ks:ks_name":"Rackkampatti",
    "ks:ks_pop":506,
    "ks:ks_type":"HABITATION",
    "name:eng_x_preferred":[
        "Rackkampatti"
    ],
    "wof:name":"Rackkampatti",
    "wof:placetype":"locality",
    "wof:population":506
},
  "geometry": {"coordinates":[78.302662,10.695616],"type":"Point"}
}