{
  "type": "Feature",
  "properties": {
    "gn:admin1_code":"35",
    "gn:admin2_code":"449.0",
    "gn:asciiname":"Bisoni Khurd",
    "gn:country_code":"IN",
    "gn:dem":301,
    "gn:feature_class":"P",
    "gn:feature_code":"PPL",
    "gn:name":"Bisoni Khurd",
    "gn:population":0,
    "gn:timezone":"Asia/Kolkata",
    "iso:country":"IN",
    "wof:name":"Bisoni Khurd",
    "wof:placetype":"locality"
},
  "geometry": {"coordinates":[77.32007,22.48039],"type":"Point"}
}