{
  "type": "Feature",
  "properties": {
    "gn:country":"IN",
    "gn:fcode":"PPL",
    "gn:population":0,
    "iso:country":"IN",
    "name:ara_x_preferred":[
        "\u0645\u0648\u0631\u0641\u0627\u062f\u064a"
    ],
    "name:ben_bn_x_preferred":[
        "\u09ae\u09cb\u09b0\u0993\u09df\u09be\u09dc\u09bf"
    ],
    "name:ben_in_x_preferred":[
        "\u09ae\u09cb\u09b0\u0993\u09df\u09be\u09dc\u09bf"
    ],
    "name:guj_x_preferred":[
        "\u0aae\u0acb\u0ab0\u0ab5\u0abe\u0aa1\u0abe"
    ],
    "name:hin_x_preferred":[
        "\u092e\u094b\u0930\u0935\u093e\u095c\u0940"
    ],
    "name:kan_x_preferred":[
        "\u0cae\u0cca\u0cb0\u0ccd\u0cb5\u0cbe\u0ca1\u0cbf"
    ],
    "name:mal_x_preferred":[
        "\u0d2e\u0d4b\u0d7c\u0d35\u0d3e\u0d21\u0d3f"
    ],
    "name:mar_x_preferred":[
        "\u092e\u094b\u0930\u0935\u093e\u0921\u0940"
    ],
    "name:pan_x_preferred":[
        "\u0a2e\u0a4c\u0a30\u0a35\u0a3e\u0a5c\u0a40"
    ],
    "name:tam_x_preferred":[
        "\u0bae\u0bcb\u0bb0\u0bcd\u0bb5\u0bbe\u0b9f\u0bbf"
    ],
    "name:tel_x_preferred":[
        "\u0c2e\u0c4b\u0c30\u0c4d\u0c35\u0c3e\u0c21\u0c40"
    ],
    "name:urd_x_preferred":[
        "\u0645\u0648\u0631\u0648\u0627\u0691\u06cc"
    ],
    "qs:name":"Morwadi",
    "qs:name_adm0":"India",
    "qs:name_adm1":"Maharashtra",
    "qs:photos":1,
    "qs:photos_1k":1,
    "qs:photos_9k":1,
    "qs:photos_9r":1,
    "qs:photos_all":1,
    "qs:photos_sr":1,
    "qs:placetype":"Suburb",
    "qs:pop_sr":"0",
    "wof:name":"Morwadi",
    "wof:placetype":"neighbourhood",
    "wof:population":0
},
  "geometry": {"coordinates":[73.80441,18.63256],"type":"Point"}
}