{
  "type": "Feature",
  "properties": {
    "iso:country":"IN",
    "ks:ks_name":"Dehurisahi",
    "ks:ks_pop":66,
    "ks:ks_type":"VILLAGE",
    "ks:ks_uagg_main":0,
    "name:eng_x_preferred":[
        "Dehurisahi"
    ],
    "wof:name":"Dehurisahi",
    "wof:placetype":"neighbourhood",
    "wof:population":66
},
  "geometry": {"coordinates":[84.200317,20.436552],"type":"Point"}
}