{
  "type": "Feature",
  "properties": {
    "iso:country":"IN",
    "ks:ks_name":"Padrahwa",
    "ks:ks_pop":30,
    "ks:ks_type":"HABITATION",
    "name:eng_x_preferred":[
        "Padrahwa"
    ],
    "wof:name":"Padrahwa",
    "wof:placetype":"locality",
    "wof:population":30
},
  "geometry": {"coordinates":[82.998913,27.218504],"type":"Point"}
}