{
  "type": "Feature",
  "properties": {
    "iso:country":"IN",
    "ks:ks_alt_nam":"Rehald\u0101g",
    "ks:ks_name":"Rehaldag",
    "ks:ks_pop":731,
    "ks:ks_type":"VILLAGE",
    "name:eng_x_preferred":[
        "Rehaldag"
    ],
    "name:eng_x_variant":[
        "Rehald\u0101g"
    ],
    "wof:name":"Rehaldag",
    "wof:placetype":"locality",
    "wof:population":731
},
  "geometry": {"coordinates":[84.381739,23.484154],"type":"Point"}
}