{
  "type": "Feature",
  "properties": {
    "gn:admin1_code":"36",
    "gn:admin2_code":"177.0",
    "gn:asciiname":"Purwa Samar",
    "gn:country_code":"IN",
    "gn:dem":102,
    "gn:feature_class":"P",
    "gn:feature_code":"PPL",
    "gn:name":"Purwa Samar",
    "gn:population":0,
    "gn:timezone":"Asia/Kolkata",
    "iso:country":"IN",
    "wof:name":"Purwa Samar",
    "wof:placetype":"neighbourhood"
},
  "geometry": {"coordinates":[82.17377999999999,26.42699],"type":"Point"}
}