{
  "type": "Feature",
  "properties": {
    "iso:country":"IN",
    "ks:ks_name":"Pentapadu",
    "ks:ks_pop":12970,
    "ks:ks_type":"VILLAGE",
    "ks:ks_uagg_main":0,
    "name:eng_x_preferred":[
        "Pentapadu"
    ],
    "wof:name":"Pentapadu",
    "wof:placetype":"locality",
    "wof:population":12970
},
  "geometry": {"coordinates":[81.525291,16.784302],"type":"Point"}
}