{
  "type": "Feature",
  "properties": {
    "iso:country":"IN",
    "ks:ks_name":"Bhool Garhi",
    "ks:ks_pop":4141,
    "ks:ks_type":"HABITATION",
    "ks:ks_uagg_main":0,
    "name:eng_x_preferred":[
        "Bhool Garhi"
    ],
    "wof:name":"Bhool Garhi",
    "wof:placetype":"neighbourhood",
    "wof:population":4141
},
  "geometry": {"coordinates":[77.541332,28.671795],"type":"Point"}
}