{
  "type": "Feature",
  "properties": {
    "gn:admin1_code":"13.0",
    "gn:admin2_code":"595.0",
    "gn:asciiname":"Pattanam",
    "gn:country_code":"IN",
    "gn:dem":10,
    "gn:feature_class":"P",
    "gn:feature_code":"PPL",
    "gn:name":"Pattanam",
    "gn:population":0,
    "gn:timezone":"Asia/Kolkata",
    "iso:country":"IN",
    "name:mal_x_preferred":[
        "\u0d2a\u0d1f\u0d4d\u0d1f\u0d23\u0d02"
    ],
    "wof:name":"Pattanam",
    "wof:placetype":"locality"
},
  "geometry": {"coordinates":[76.20860999999999,10.15588],"type":"Point"}
}