{
  "type": "Feature",
  "properties": {
    "iso:country":"IN",
    "ks:ks_alt_nam":"Malr\u0101jankuppam",
    "ks:ks_alt_nam_2":"Malrajankuppam",
    "ks:ks_name":"Malarajamkuppam",
    "ks:ks_pop":635,
    "ks:ks_type":"VILLAGE",
    "ks:ks_uagg_main":0,
    "name:eng_x_preferred":[
        "Malarajamkuppam"
    ],
    "name:eng_x_variant":[
        "Malr\u0101jankuppam",
        "Malrajankuppam"
    ],
    "wof:name":"Malarajamkuppam",
    "wof:placetype":"neighbourhood",
    "wof:population":635
},
  "geometry": {"coordinates":[79.60166700000001,11.926091],"type":"Point"}
}