{
  "type": "Feature",
  "properties": {
    "gn:admin1_code":"19.0",
    "gn:admin2_code":"573.0",
    "gn:asciiname":"Bommadihalli",
    "gn:country_code":"IN",
    "gn:dem":798,
    "gn:feature_class":"P",
    "gn:feature_code":"PPL",
    "gn:name":"Bommadihalli",
    "gn:population":0,
    "gn:timezone":"Asia/Kolkata",
    "iso:country":"IN",
    "wof:name":"Bommadihalli",
    "wof:placetype":"locality"
},
  "geometry": {"coordinates":[76.72977,12.75324],"type":"Point"}
}