{
  "type": "Feature",
  "properties": {
    "gn:admin1_code":"39.0",
    "gn:admin2_code":"60.0",
    "gn:asciiname":"Samog",
    "gn:country_code":"IN",
    "gn:dem":1795,
    "gn:feature_class":"P",
    "gn:feature_code":"PPL",
    "gn:name":"Samog",
    "gn:population":0,
    "gn:timezone":"Asia/Kolkata",
    "iso:country":"IN",
    "ks:ks_name":"Samog",
    "ks:ks_pop":308,
    "ks:ks_type":"VILLAGE",
    "name:eng_x_preferred":[
        "Samog"
    ],
    "wof:name":"Samog",
    "wof:placetype":"locality",
    "wof:population":308
},
  "geometry": {"coordinates":[77.93497499999999,30.720908],"type":"Point"}
}