{
  "type": "Feature",
  "properties": {
    "iso:country":"IN",
    "name:ara_x_preferred":[
        "\u062c\u0648\u0643\u064a\u0641\u0627\u0631\u064a"
    ],
    "name:ben_bn_x_preferred":[
        "\u0997\u09cb\u0996\u09bf\u09ad\u09be\u09b0\u09c7"
    ],
    "name:ben_in_x_preferred":[
        "\u0997\u09cb\u0996\u09bf\u09ad\u09be\u09b0\u09c7"
    ],
    "name:ben_x_preferred":[
        "\u0997\u09cb\u0996\u09bf\u0993\u09af\u09bc\u09be\u09b0\u09c7"
    ],
    "name:bpy_x_preferred":[
        "\u0997\u09cb\u0996\u09bf\u09f1\u09b0\u09c7"
    ],
    "name:eng_x_preferred":[
        "Gokhivare"
    ],
    "name:fra_x_preferred":[
        "Gokhivare"
    ],
    "name:guj_x_preferred":[
        "\u0a97\u0acb\u0a96\u0ac0\u0ab5\u0abe\u0ab0\u0ac7"
    ],
    "name:hin_x_preferred":[
        "\u0917\u094b\u0916\u0940\u0935\u093e\u0930\u0947"
    ],
    "name:ita_x_preferred":[
        "Gokhivare"
    ],
    "name:kan_x_preferred":[
        "\u0c97\u0ccb\u0c96\u0cbf\u0cb5\u0cb0\u0cc6"
    ],
    "name:mal_x_preferred":[
        "\u0d17\u0d4b\u0d16\u0d3f\u0d35\u0d3e\u0d30\u0d46"
    ],
    "name:mar_x_preferred":[
        "\u0917\u094b\u0916\u093f\u0935\u0930\u0947"
    ],
    "name:msa_x_preferred":[
        "Gokhivare"
    ],
    "name:nan_x_preferred":[
        "Gokhivare"
    ],
    "name:new_x_preferred":[
        "\u0917\u094b\u0916\u093f\u092d\u0930\u0947"
    ],
    "name:nld_x_preferred":[
        "Gokhivare"
    ],
    "name:pan_x_preferred":[
        "\u0a17\u0a4b\u0a16\u0a40\u0a35\u0a3e\u0a30\u0a47"
    ],
    "name:por_x_preferred":[
        "Gokhivare"
    ],
    "name:tam_x_preferred":[
        "\u0b95\u0bcb\u0b95\u0bbf\u0bb5\u0bb0\u0bc6"
    ],
    "name:tel_x_preferred":[
        "\u0c17\u0c4a\u0c15\u0c3f\u0c35\u0c3e\u0c30\u0c46"
    ],
    "name:urd_x_preferred":[
        "\u06af\u0648\u06a9\u06be\u06cc\u0648\u0627\u0691\u06cc"
    ],
    "name:urd_x_variant":[
        "\u06af\u0648\u06a9\u06be\u06cc\u0648\u0627\u0691\u06d2"
    ],
    "name:vie_x_preferred":[
        "Gokhivare"
    ],
    "name:zho_min_nan_x_preferred":[
        "Gokhivare"
    ],
    "name:zho_x_preferred":[
        "\u6208\u57fa\u74e6\u96f7"
    ],
    "qs:gn_adm0_cc":"IN",
    "qs:gn_local":1253133,
    "qs:gn_nam_loc":"virar",
    "qs:gn_namadm1":"16",
    "qs:local_max":371,
    "qs:local_sum":377,
    "qs:localhoods":2,
    "qs:name":"Gokhivare",
    "qs:name_adm0":"India",
    "qs:name_adm1":"Maharashtra",
    "qs:name_adm2":"Thane",
    "qs:name_local":"Virar",
    "qs:photo_max":4,
    "qs:photo_sum":6,
    "qs:placetype":"Suburb",
    "qs:quad_count":3,
    "qs:woe_adm0":23424848,
    "qs:woe_adm1":2345750,
    "qs:woe_adm2":12586551,
    "qs:woe_lau":0,
    "qs:woe_local":2292747,
    "qs:woe_ver":"7.10.0",
    "wd:wordcount":113,
    "wof:lang":[
        "eng"
    ],
    "wof:name":"Gokhivare",
    "wof:placetype":"neighbourhood"
},
  "geometry": {"coordinates":[72.844849,19.403567],"type":"Point"}
}