{
  "type": "Feature",
  "properties": {
    "iso:country":"IN",
    "name:ben_x_preferred":[
        "\u0997\u09cb\u0996\u09bf\u0993\u09af\u09bc\u09be\u09b0\u09c7"
    ],
    "name:bpy_x_preferred":[
        "\u0997\u09cb\u0996\u09bf\u09f1\u09b0\u09c7"
    ],
    "name:eng_x_preferred":[
        "Gokhivare"
    ],
    "name:ita_x_preferred":[
        "Gokhivare"
    ],
    "name:msa_x_preferred":[
        "Gokhivare"
    ],
    "name:new_x_preferred":[
        "\u0917\u094b\u0916\u093f\u092d\u0930\u0947"
    ],
    "name:nld_x_preferred":[
        "Gokhivare"
    ],
    "name:por_x_preferred":[
        "Gokhivare"
    ],
    "name:unk_x_variant":[
        "Gokhivare"
    ],
    "name:urd_x_preferred":[
        "\u06af\u0648\u06a9\u06be\u06cc\u0648\u0627\u0691\u06d2"
    ],
    "name:vie_x_preferred":[
        "Gokhivare"
    ],
    "name:zho_min_nan_x_preferred":[
        "Gokhivare"
    ],
    "name:zho_x_preferred":[
        "\u6208\u57fa\u74e6\u96f7"
    ],
    "qs:gn_adm0_cc":"IN",
    "qs:gn_local":1253133,
    "qs:gn_nam_loc":"virar",
    "qs:gn_namadm1":"16",
    "qs:local_max":371,
    "qs:local_sum":377,
    "qs:localhoods":2,
    "qs:name":"Gokhivare",
    "qs:name_adm0":"India",
    "qs:name_adm1":"Maharashtra",
    "qs:name_adm2":"Thane",
    "qs:name_local":"Virar",
    "qs:photo_max":4,
    "qs:photo_sum":6,
    "qs:placetype":"Suburb",
    "qs:quad_count":3,
    "qs:woe_adm0":23424848,
    "qs:woe_adm1":2345750,
    "qs:woe_adm2":12586551,
    "qs:woe_lau":0,
    "qs:woe_local":2292747,
    "qs:woe_ver":"7.10.0",
    "wd:wordcount":113,
    "wof:lang":[
        "eng"
    ],
    "wof:name":"Gokhivare",
    "wof:placetype":"neighbourhood"
},
  "geometry": {"coordinates":[72.844849,19.403567],"type":"Point"}
}