{
  "type": "Feature",
  "properties": {
    "gn:admin1_code":"36",
    "gn:admin2_code":"179.0",
    "gn:asciiname":"Jaria",
    "gn:country_code":"IN",
    "gn:dem":90,
    "gn:feature_class":"P",
    "gn:feature_code":"PPL",
    "gn:name":"Jaria",
    "gn:population":0,
    "gn:timezone":"Asia/Kolkata",
    "iso:country":"IN",
    "name:ceb_x_preferred":[
        "Jar\u012b\u0101"
    ],
    "name:fas_x_preferred":[
        "\u062c\u0631\u06cc\u0627"
    ],
    "name:msa_x_preferred":[
        "Jaria"
    ],
    "name:swe_x_preferred":[
        "Jar\u012b\u0101"
    ],
    "name:urd_x_preferred":[
        "\u062c\u0631\u06cc\u0627"
    ],
    "wof:name":"Jaria",
    "wof:placetype":"neighbourhood"
},
  "geometry": {"coordinates":[82.52157,26.20943],"type":"Point"}
}