{
  "type": "Feature",
  "properties": {
    "gn:admin1_code":"2.0",
    "gn:admin2_code":"554.0",
    "gn:asciiname":"Basireddipalle",
    "gn:country_code":"IN",
    "gn:dem":674,
    "gn:feature_class":"P",
    "gn:feature_code":"PPL",
    "gn:name":"Basireddipalle",
    "gn:population":0,
    "gn:timezone":"Asia/Kolkata",
    "iso:country":"IN",
    "name:tel_x_preferred":[
        "\u0c2c\u0c38\u0c3f\u0c30\u0c46\u0c21\u0c4d\u0c21\u0c3f\u0c2a\u0c32\u0c4d\u0c32\u0c3f"
    ],
    "wof:name":"Basireddipalle",
    "wof:placetype":"locality"
},
  "geometry": {"coordinates":[78.40888000000002,13.76631],"type":"Point"}
}