{
  "type": "Feature",
  "properties": {
    "iso:country":"IN",
    "ks:ks_name":"Lodh Purwa",
    "ks:ks_pop":465,
    "ks:ks_type":"HABITATION",
    "name:eng_x_preferred":[
        "Lodh Purwa"
    ],
    "wof:name":"Lodh Purwa",
    "wof:placetype":"locality",
    "wof:population":465
},
  "geometry": {"coordinates":[83.03119599999999,27.299317],"type":"Point"}
}