{
  "type": "Feature",
  "properties": {
    "iso:country":"IN",
    "ks:ks_name":"Kudhur",
    "ks:ks_pop":959,
    "ks:ks_type":"VILLAGE",
    "name:eng_x_preferred":[
        "Kudhur"
    ],
    "wof:name":"Kudhur",
    "wof:placetype":"locality",
    "wof:population":959
},
  "geometry": {"coordinates":[81.53236699999999,19.231287],"type":"Point"}
}