{
  "type": "Feature",
  "properties": {
    "gn:admin1_code":"25.0",
    "gn:admin2_code":"606.0",
    "gn:asciiname":"Kalkkalantangal",
    "gn:country_code":"IN",
    "gn:dem":160,
    "gn:feature_class":"P",
    "gn:feature_code":"PPL",
    "gn:name":"Kalkkalant\u0101ngal",
    "gn:population":0,
    "gn:timezone":"Asia/Kolkata",
    "iso:country":"IN",
    "wof:name":"Kalkkalantangal",
    "wof:placetype":"locality"
},
  "geometry": {"coordinates":[79.23633000000002,12.66105],"type":"Point"}
}