{
  "type": "Feature",
  "properties": {
    "iso:country":"IN",
    "ks:ks_name":"Kherad",
    "ks:ks_pop":383,
    "ks:ks_type":"VILLAGE",
    "name:eng_x_preferred":[
        "Kherad"
    ],
    "wof:name":"Kherad",
    "wof:placetype":"locality",
    "wof:population":383
},
  "geometry": {"coordinates":[73.332553,24.246131],"type":"Point"}
}