{
  "type": "Feature",
  "properties": {
    "iso:country":"IN",
    "ks:ks_name":"Dahirpur",
    "ks:ks_pop":365,
    "ks:ks_type":"VILLAGE",
    "ks:ks_uagg_main":0,
    "name:eng_x_preferred":[
        "Dahirpur"
    ],
    "wof:name":"Dahirpur",
    "wof:placetype":"neighbourhood",
    "wof:population":365
},
  "geometry": {"coordinates":[82.57762200000001,26.468799],"type":"Point"}
}