{
  "type": "Feature",
  "properties": {
    "gn:admin1_code":"2",
    "gn:admin2_code":"545.0",
    "gn:asciiname":"Chidipalem",
    "gn:country_code":"IN",
    "gn:dem":250,
    "gn:feature_class":"P",
    "gn:feature_code":"PPL",
    "gn:name":"Ch\u012bdip\u0101lem",
    "gn:population":0,
    "gn:timezone":"Asia/Kolkata",
    "iso:country":"IN",
    "ks:ks_alt_nam":"Ch\u012bdip\u0101lem",
    "ks:ks_name":"Chidipalem",
    "ks:ks_type":"VILLAGE",
    "name:eng_x_preferred":[
        "Chidipalem"
    ],
    "name:eng_x_variant":[
        "Ch\u012bdip\u0101lem"
    ],
    "wof:name":"Chidipalem",
    "wof:placetype":"locality"
},
  "geometry": {"coordinates":[81.959951,17.435904],"type":"Point"}
}