{
  "type": "Feature",
  "properties": {
    "gn:admin1_code":"10.0",
    "gn:admin2_code":"72.0",
    "gn:asciiname":"Mangauli Rangharan",
    "gn:country_code":"IN",
    "gn:dem":272,
    "gn:feature_class":"P",
    "gn:feature_code":"PPL",
    "gn:name":"Mangauli R\u0101nghar\u0101n",
    "gn:population":0,
    "gn:timezone":"Asia/Kolkata",
    "iso:country":"IN",
    "wof:name":"Mangauli Rangharan",
    "wof:placetype":"locality"
},
  "geometry": {"coordinates":[77.01515000000001,30.13562],"type":"Point"}
}