{
  "type": "Feature",
  "properties": {
    "iso:country":"IN",
    "ks:ks_name":"Dhanshri Bazar",
    "ks:ks_pop":717,
    "ks:ks_type":"HABITATION",
    "ks:ks_uagg_main":0,
    "name:eng_x_preferred":[
        "Dhanshri Bazar"
    ],
    "wof:name":"Dhanshri Bazar",
    "wof:placetype":"neighbourhood",
    "wof:population":717
},
  "geometry": {"coordinates":[93.601722,25.809758],"type":"Point"}
}