{
  "type": "Feature",
  "properties": {
    "iso:country":"IN",
    "ks:ks_alt_nam":"KANTHARIYA PEEPALIYA",
    "ks:ks_name":"Kanthariya Peepaliya",
    "ks:ks_pop":153,
    "ks:ks_type":"HABITATION",
    "name:eng_x_preferred":[
        "Kanthariya Peepaliya"
    ],
    "wof:name":"Kanthariya Peepaliya",
    "wof:placetype":"locality",
    "wof:population":153
},
  "geometry": {"coordinates":[74.70870499999999,23.854577],"type":"Point"}
}