{
  "type": "Feature",
  "properties": {
    "iso:country":"IN",
    "ks:ks_name":"Shivnagri",
    "ks:ks_pop":1437,
    "ks:ks_type":"VILLAGE",
    "name:eng_x_preferred":[
        "Shivnagri"
    ],
    "wof:name":"Shivnagri",
    "wof:placetype":"locality",
    "wof:population":1437
},
  "geometry": {"coordinates":[72.682739,26.182169],"type":"Point"}
}