{
  "type": "Feature",
  "properties": {
    "iso:country":"IN",
    "ks:ks_name":"Khaspur Mustkil",
    "ks:ks_pop":2189,
    "ks:ks_type":"VILLAGE",
    "name:eng_x_preferred":[
        "Khaspur Mustkil"
    ],
    "wof:name":"Khaspur Mustkil",
    "wof:placetype":"neighbourhood",
    "wof:population":2189
},
  "geometry": {"coordinates":[78.02454899999999,27.244886],"type":"Point"}
}