{
  "type": "Feature",
  "properties": {
    "gn:admin1_code":"35.0",
    "gn:admin2_code":"450.0",
    "gn:asciiname":"Jbuli",
    "gn:country_code":"IN",
    "gn:dem":382,
    "gn:feature_class":"P",
    "gn:feature_code":"PPL",
    "gn:name":"Jbuli",
    "gn:population":0,
    "gn:timezone":"Asia/Kolkata",
    "iso:country":"IN",
    "wof:name":"Jbuli",
    "wof:placetype":"neighbourhood"
},
  "geometry": {"coordinates":[80.44535,23.85218],"type":"Point"}
}