{
  "type": "Feature",
  "properties": {
    "iso:country":"IN",
    "ks:ks_name":"Darshana",
    "ks:ks_type":"VILLAGE",
    "name:eng_x_preferred":[
        "Darshana"
    ],
    "wof:name":"Darshana",
    "wof:placetype":"locality"
},
  "geometry": {"coordinates":[83.921819,24.834486],"type":"Point"}
}