{
  "type": "Feature",
  "properties": {
    "gn:admin1_code":"36.0",
    "gn:admin2_code":"134.0",
    "gn:asciiname":"Aminpur",
    "gn:country_code":"IN",
    "gn:dem":236,
    "gn:feature_class":"P",
    "gn:feature_code":"PPL",
    "gn:name":"Am\u012bnpur",
    "gn:population":0,
    "gn:timezone":"Asia/Kolkata",
    "iso:country":"IN",
    "name:fas_x_preferred":[
        "\u0627\u0645\u06cc\u0646\u200c\u067e\u0648\u0631"
    ],
    "name:rus_x_preferred":[
        "\u0410\u043c\u0438\u043d\u043f\u0443\u0440"
    ],
    "name:und_x_variant":[
        "Am\u012bnpur",
        "N\u0101r\u0101yanpur"
    ],
    "name:urd_x_preferred":[
        "\u0627\u0645\u06cc\u0646 \u067e\u0648\u0631"
    ],
    "wof:name":"Aminpur",
    "wof:placetype":"locality"
},
  "geometry": {"coordinates":[78.0809,29.56872000000001],"type":"Point"}
}