{
  "type": "Feature",
  "properties": {
    "gn:admin1_code":"11",
    "gn:admin2_code":"23.0",
    "gn:asciiname":"Diwan Khaha",
    "gn:country_code":"IN",
    "gn:dem":1494,
    "gn:feature_class":"P",
    "gn:feature_code":"PPL",
    "gn:name":"Diw\u0101n Kh\u0101ha",
    "gn:population":0,
    "gn:timezone":"Asia/Kolkata",
    "iso:country":"IN",
    "wof:name":"Diwan Khaha",
    "wof:placetype":"locality"
},
  "geometry": {"coordinates":[76.13775,32.58827],"type":"Point"}
}