{
  "type": "Feature",
  "properties": {
    "iso:country":"IN",
    "ks:ks_name":"Khadara",
    "ks:ks_pop":96,
    "ks:ks_type":"HABITATION",
    "name:eng_x_preferred":[
        "Khadara"
    ],
    "wof:name":"Khadara",
    "wof:placetype":"locality",
    "wof:population":96
},
  "geometry": {"coordinates":[78.45497400000001,26.940724],"type":"Point"}
}