{
  "type": "Feature",
  "properties": {
    "iso:country":"IN",
    "ks:ks_name":"Belechandi",
    "ks:ks_pop":2368,
    "ks:ks_type":"VILLAGE",
    "ks:ks_uagg_main":0,
    "name:eng_x_preferred":[
        "Belechandi"
    ],
    "wof:name":"Belechandi",
    "wof:placetype":"neighbourhood",
    "wof:population":2368
},
  "geometry": {"coordinates":[88.452478,22.271701],"type":"Point"}
}