{
  "type": "Feature",
  "properties": {
    "iso:country":"IN",
    "ks:ks_name":"Dhamnichua",
    "ks:ks_pop":87,
    "ks:ks_type":"VILLAGE",
    "name:eng_x_preferred":[
        "Dhamnichua"
    ],
    "wof:name":"Dhamnichua",
    "wof:placetype":"locality",
    "wof:population":87
},
  "geometry": {"coordinates":[87.43286000000001,24.550917],"type":"Point"}
}