{
  "type": "Feature",
  "properties": {
    "iso:country":"IN",
    "ks:ks_name":"Laxmanpur",
    "ks:ks_pop":268,
    "ks:ks_type":"HABITATION",
    "name:eng_x_preferred":[
        "Laxmanpur"
    ],
    "wof:name":"Laxmanpur",
    "wof:placetype":"locality",
    "wof:population":268
},
  "geometry": {"coordinates":[80.393075,26.301793],"type":"Point"}
}