{
  "type": "Feature",
  "properties": {
    "iso:country":"IN",
    "ks:ks_name":"Kharigara",
    "ks:ks_pop":678,
    "ks:ks_type":"VILLAGE",
    "name:eng_x_preferred":[
        "Kharigara"
    ],
    "wof:name":"Kharigara",
    "wof:placetype":"locality",
    "wof:population":678
},
  "geometry": {"coordinates":[87.17353900000001,23.273959],"type":"Point"}
}