{
  "type": "Feature",
  "properties": {
    "iso:country":"IN",
    "ks:ks_name":"Badenigochha",
    "ks:ks_pop":14,
    "ks:ks_type":"VILLAGE",
    "name:eng_x_preferred":[
        "Badenigochha"
    ],
    "wof:name":"Badenigochha",
    "wof:placetype":"locality",
    "wof:population":14
},
  "geometry": {"coordinates":[84.376272,20.59614],"type":"Point"}
}