{
  "type": "Feature",
  "properties": {
    "iso:country":"IN",
    "ks:ks_name":"Tapopada",
    "ks:ks_pop":89,
    "ks:ks_type":"HABITATION",
    "name:eng_x_preferred":[
        "Tapopada"
    ],
    "wof:name":"Tapopada",
    "wof:placetype":"locality",
    "wof:population":89
},
  "geometry": {"coordinates":[84.11586800000001,21.38876],"type":"Point"}
}