{
  "type": "Feature",
  "properties": {
    "iso:country":"IN",
    "ks:ks_alt_nam":"anjukandy",
    "ks:ks_name":"Anjukandy",
    "ks:ks_pop":880,
    "ks:ks_type":"HABITATION",
    "name:eng_x_preferred":[
        "Anjukandy"
    ],
    "wof:name":"Anjukandy",
    "wof:placetype":"locality",
    "wof:population":880
},
  "geometry": {"coordinates":[75.64619,11.645729],"type":"Point"}
}