{
  "type": "Feature",
  "properties": {
    "gn:admin1_code":"34.0",
    "gn:admin2_code":"221",
    "gn:asciiname":"Desri",
    "gn:country_code":"IN",
    "gn:dem":53,
    "gn:feature_class":"P",
    "gn:feature_code":"PPL",
    "gn:name":"Desri",
    "gn:population":0,
    "gn:timezone":"Asia/Kolkata",
    "iso:country":"IN",
    "name:und_x_variant":[
        "Sh\u0101hjah\u0101npur"
    ],
    "wof:name":"Desri",
    "wof:placetype":"locality"
},
  "geometry": {"coordinates":[86.00955999999999,25.61193],"type":"Point"}
}