{
  "type": "Feature",
  "properties": {
    "iso:country":"IN",
    "ks:ks_name":"Jolaguda",
    "ks:ks_pop":195,
    "ks:ks_type":"HABITATION",
    "name:eng_x_preferred":[
        "Jolaguda"
    ],
    "wof:name":"Jolaguda",
    "wof:placetype":"locality",
    "wof:population":195
},
  "geometry": {"coordinates":[82.99965,18.689711],"type":"Point"}
}