{
  "type": "Feature",
  "properties": {
    "iso:country":"IN",
    "ks:ks_name":"Kheshab Chak",
    "ks:ks_pop":1144,
    "ks:ks_type":"VILLAGE",
    "name:eng_x_preferred":[
        "Kheshab Chak"
    ],
    "wof:name":"Kheshab Chak",
    "wof:placetype":"locality",
    "wof:population":1144
},
  "geometry": {"coordinates":[87.87544,21.913453],"type":"Point"}
}