{
  "type": "Feature",
  "properties": {
    "gn:admin1_code":"35.0",
    "gn:admin2_code":"440.0",
    "gn:asciiname":"Karond",
    "gn:country_code":"IN",
    "gn:dem":190,
    "gn:feature_class":"P",
    "gn:feature_code":"PPL",
    "gn:name":"Karond",
    "gn:population":0,
    "gn:timezone":"Asia/Kolkata",
    "iso:country":"IN",
    "ks:ks_name":"Karond",
    "ks:ks_type":"VILLAGE",
    "ks:ks_uagg_main":0,
    "name:eng_x_preferred":[
        "Karond"
    ],
    "wof:name":"Karond",
    "wof:placetype":"neighbourhood"
},
  "geometry": {"coordinates":[75.97385800000001,22.242254],"type":"Point"}
}