{
  "type": "Feature",
  "properties": {
    "gn:admin1_code":"28.0",
    "gn:admin2_code":"341.0",
    "gn:asciiname":"Bikihakola",
    "gn:country_code":"IN",
    "gn:dem":12,
    "gn:feature_class":"P",
    "gn:feature_code":"PPL",
    "gn:name":"Bikihakola",
    "gn:population":0,
    "gn:timezone":"Asia/Kolkata",
    "iso:country":"IN",
    "wof:name":"Bikihakola",
    "wof:placetype":"locality"
},
  "geometry": {"coordinates":[88.1567,22.55814],"type":"Point"}
}