{
  "type": "Feature",
  "properties": {
    "iso:country":"IN",
    "ks:ks_name":"Yashawantnagar",
    "ks:ks_pop":11602,
    "ks:ks_type":"VILLAGE",
    "name:eng_x_preferred":[
        "Yashawantnagar"
    ],
    "wof:name":"Yashawantnagar",
    "wof:placetype":"locality",
    "wof:population":11602
},
  "geometry": {"coordinates":[75.011386,17.868196],"type":"Point"}
}