{
  "type": "Feature",
  "properties": {
    "iso:country":"IN",
    "ks:ks_alt_nam":"S\u012bla Talla",
    "ks:ks_alt_nam_2":"Sila Talla",
    "ks:ks_name":"Sila",
    "ks:ks_type":"VILLAGE",
    "name:eng_x_preferred":[
        "Sila"
    ],
    "name:eng_x_variant":[
        "S\u012bla Talla",
        "Sila Talla"
    ],
    "wof:name":"Sila",
    "wof:placetype":"locality"
},
  "geometry": {"coordinates":[78.866844,29.973103],"type":"Point"}
}