{
  "type": "Feature",
  "properties": {
    "iso:country":"IN",
    "ks:ks_name":"Jedkiya",
    "ks:ks_pop":252,
    "ks:ks_type":"HABITATION",
    "name:eng_x_preferred":[
        "Jedkiya"
    ],
    "wof:name":"Jedkiya",
    "wof:placetype":"locality",
    "wof:population":252
},
  "geometry": {"coordinates":[72.84866700000001,23.311667],"type":"Point"}
}