{
  "type": "Feature",
  "properties": {
    "iso:country":"IN",
    "ks:ks_name":"Malhari Ryt.",
    "ks:ks_pop":6,
    "ks:ks_type":"VILLAGE",
    "name:eng_x_preferred":[
        "Malhari Ryt."
    ],
    "wof:name":"Malhari Ryt.",
    "wof:placetype":"locality",
    "wof:population":6
},
  "geometry": {"coordinates":[80.370222,23.059701],"type":"Point"}
}