{
  "type": "Feature",
  "properties": {
    "iso:country":"IN",
    "ks:ks_name":"Athiyalil",
    "ks:ks_pop":755,
    "ks:ks_type":"HABITATION",
    "name:eng_x_preferred":[
        "Athiyalil"
    ],
    "wof:name":"Athiyalil",
    "wof:placetype":"locality",
    "wof:population":755
},
  "geometry": {"coordinates":[76.724788,9.436617],"type":"Point"}
}