{
  "type": "Feature",
  "properties": {
    "iso:country":"IN",
    "ks:ks_name":"Matapada Suwarpada",
    "ks:ks_pop":500,
    "ks:ks_type":"HABITATION",
    "name:eng_x_preferred":[
        "Matapada Suwarpada"
    ],
    "wof:name":"Matapada Suwarpada",
    "wof:placetype":"locality",
    "wof:population":500
},
  "geometry": {"coordinates":[74.814144,22.968603],"type":"Point"}
}