{
  "type": "Feature",
  "properties": {
    "iso:country":"IN",
    "ks:ks_name":"Tola Pidron",
    "ks:ks_pop":22,
    "ks:ks_type":"VILLAGE",
    "name:eng_x_preferred":[
        "Tola Pidron"
    ],
    "wof:name":"Tola Pidron",
    "wof:placetype":"locality",
    "wof:population":22
},
  "geometry": {"coordinates":[86.42641399999999,24.769499],"type":"Point"}
}