{
  "type": "Feature",
  "properties": {
    "gn:admin1_code":"11.0",
    "gn:admin2_code":"32.0",
    "gn:asciiname":"Leo",
    "gn:country_code":"IN",
    "gn:dem":1748,
    "gn:feature_class":"P",
    "gn:feature_code":"PPL",
    "gn:name":"Leo",
    "gn:population":0,
    "gn:timezone":"Asia/Kolkata",
    "iso:country":"IN",
    "name:bre_x_preferred":[
        "Leo"
    ],
    "name:bul_x_preferred":[
        "\u041b\u044a\u0432"
    ],
    "name:cat_x_preferred":[
        "Leo"
    ],
    "name:ceb_x_preferred":[
        "Leo"
    ],
    "name:ces_x_preferred":[
        "Leo"
    ],
    "name:deu_x_preferred":[
        "Leo"
    ],
    "name:epo_x_preferred":[
        "Leo"
    ],
    "name:eus_x_preferred":[
        "Leo"
    ],
    "name:fas_x_preferred":[
        "\u0644\u0626\u0648"
    ],
    "name:fin_x_preferred":[
        "Leo"
    ],
    "name:heb_x_preferred":[
        "\u05d0\u05e8\u05d9\u05d4"
    ],
    "name:ita_x_preferred":[
        "Leo"
    ],
    "name:lat_x_preferred":[
        "Leo"
    ],
    "name:lav_x_preferred":[
        "Leo"
    ],
    "name:ltz_x_preferred":[
        "Leo"
    ],
    "name:msa_x_preferred":[
        "Leo"
    ],
    "name:nld_x_preferred":[
        "Leo"
    ],
    "name:pol_x_preferred":[
        "Leo"
    ],
    "name:por_x_preferred":[
        "Leo"
    ],
    "name:rus_x_preferred":[
        "\u041b\u0435\u043e"
    ],
    "name:slk_x_preferred":[
        "Leo"
    ],
    "name:spa_x_preferred":[
        "Leo"
    ],
    "name:swe_x_preferred":[
        "Leo"
    ],
    "name:tur_x_preferred":[
        "Leo"
    ],
    "name:vie_x_preferred":[
        "S\u01b0 T\u1eed"
    ],
    "wof:name":"Leo",
    "wof:placetype":"locality"
},
  "geometry": {"coordinates":[77.35613000000002,30.97125],"type":"Point"}
}