{
  "type": "Feature",
  "properties": {
    "iso:country":"IN",
    "ks:ks_name":"Changmai Gaon",
    "ks:ks_pop":573,
    "ks:ks_type":"HABITATION",
    "name:eng_x_preferred":[
        "Changmai Gaon"
    ],
    "wof:name":"Changmai Gaon",
    "wof:placetype":"locality",
    "wof:population":573
},
  "geometry": {"coordinates":[94.903828,27.077651],"type":"Point"}
}