{
  "type": "Feature",
  "properties": {
    "iso:country":"IN",
    "ks:ks_name":"Kudikadu",
    "ks:ks_pop":49,
    "ks:ks_type":"HABITATION",
    "name:eng_x_preferred":[
        "Kudikadu"
    ],
    "wof:name":"Kudikadu",
    "wof:placetype":"locality",
    "wof:population":49
},
  "geometry": {"coordinates":[78.910301,9.998973],"type":"Point"}
}