{
  "type": "Feature",
  "properties": {
    "iso:country":"IN",
    "ks:ks_name":"Sultanpur",
    "ks:ks_pop":4206,
    "ks:ks_type":"VILLAGE",
    "name:eng_x_preferred":[
        "Sultanpur"
    ],
    "wof:name":"Sultanpur",
    "wof:placetype":"locality",
    "wof:population":4206
},
  "geometry": {"coordinates":[87.709711,22.774389],"type":"Point"}
}