{
  "type": "Feature",
  "properties": {
    "iso:country":"IN",
    "ks:ks_name":"Bhitaramarichamala",
    "ks:ks_pop":345,
    "ks:ks_type":"VILLAGE",
    "name:eng_x_preferred":[
        "Bhitaramarichamala"
    ],
    "wof:name":"Bhitaramarichamala",
    "wof:placetype":"locality",
    "wof:population":345
},
  "geometry": {"coordinates":[82.988563,18.837161],"type":"Point"}
}