{
  "type": "Feature",
  "properties": {
    "gn:admin1_code":"19.0",
    "gn:admin2_code":"577.0",
    "gn:asciiname":"Vaddrapalya",
    "gn:country_code":"IN",
    "gn:dem":885,
    "gn:feature_class":"P",
    "gn:feature_code":"PPL",
    "gn:name":"Vaddrapalya",
    "gn:population":0,
    "gn:timezone":"Asia/Kolkata",
    "iso:country":"IN",
    "wof:name":"Vaddrapalya",
    "wof:placetype":"locality"
},
  "geometry": {"coordinates":[76.11931,12.42128],"type":"Point"}
}