{
  "type": "Feature",
  "properties": {
    "iso:country":"IN",
    "ks:ks_alt_nam":"9 SKM-B",
    "ks:ks_name":"9 Skm-b",
    "ks:ks_pop":52,
    "ks:ks_type":"HABITATION",
    "name:eng_x_preferred":[
        "9 Skm-b"
    ],
    "wof:name":"9 Skm-b",
    "wof:placetype":"locality",
    "wof:population":52
},
  "geometry": {"coordinates":[72.807214,28.958383],"type":"Point"}
}