{
  "type": "Feature",
  "properties": {
    "iso:country":"IN",
    "ks:ks_name":"Bachhubigha",
    "ks:ks_pop":160,
    "ks:ks_type":"HABITATION",
    "name:eng_x_preferred":[
        "Bachhubigha"
    ],
    "wof:name":"Bachhubigha",
    "wof:placetype":"locality",
    "wof:population":160
},
  "geometry": {"coordinates":[85.173737,25.10038],"type":"Point"}
}