{
  "type": "Feature",
  "properties": {
    "gn:admin1_code":"09",
    "gn:admin2_code":"469.0",
    "gn:asciiname":"Tharad",
    "gn:country_code":"IN",
    "gn:dem":24,
    "gn:feature_class":"P",
    "gn:feature_code":"PPL",
    "gn:name":"Thar\u0101d",
    "gn:population":0,
    "gn:timezone":"Asia/Kolkata",
    "iso:country":"IN",
    "name:guj_x_preferred":[
        "\u0aae\u0acb\u0ab0\u0ab5\u0abe\u0aa1\u0abe"
    ],
    "name:und_x_variant":[
        "Morv\u0101da",
        "Thar\u0101d"
    ],
    "wof:name":"Tharad",
    "wof:placetype":"neighbourhood"
},
  "geometry": {"coordinates":[71.42127000000001,24.03593],"type":"Point"}
}