{
  "type": "Feature",
  "properties": {
    "gn:country":"IN",
    "gn:fcode":"PPL",
    "gn:pop":9478,
    "iso:country":"IN",
    "name:bpy_x_preferred":[
        "\u09b9\u09c7\u09b0\u09ac\u09be\u09b0\u09cd\u099f\u09aa\u09c1\u09b0"
    ],
    "name:bul_x_preferred":[
        "\u0425\u0430\u0440\u0431\u0430\u0442\u043f\u0443\u0440"
    ],
    "name:ceb_x_preferred":[
        "Harbatpur"
    ],
    "name:eng_x_preferred":[
        "Herbertpur"
    ],
    "name:fra_x_preferred":[
        "Herbertpur"
    ],
    "name:ita_x_preferred":[
        "Herbertpur"
    ],
    "name:mlg_x_preferred":[
        "Herbertpur"
    ],
    "name:msa_x_preferred":[
        "Herbertpur"
    ],
    "name:nan_x_preferred":[
        "Herbertpur"
    ],
    "name:new_x_preferred":[
        "\u0939\u0930\u094d\u092c\u0930\u094d\u091f\u092a\u0941\u0930"
    ],
    "name:nld_x_preferred":[
        "Herbertpur"
    ],
    "name:pol_x_preferred":[
        "Herbertpur"
    ],
    "name:por_x_preferred":[
        "Herbertpur"
    ],
    "name:swe_x_preferred":[
        "Harbatpur"
    ],
    "name:unk_x_variant":[
        "Harbatpur"
    ],
    "name:vie_x_preferred":[
        "Herbertpur"
    ],
    "name:zho_x_preferred":[
        "\u8d6b\u5c14\u8d1d\u5c14\u7279\u666e\u5c14"
    ],
    "qs:name":"Herbertpur",
    "qs:name_adm0":"India",
    "qs:name_adm1":"Uttarakhand",
    "qs:photos":11,
    "qs:photos_1k":2,
    "qs:photos_9k":1,
    "qs:photos_9r":1,
    "qs:photos_all":12,
    "qs:photos_sr":1,
    "qs:placetype":"Town",
    "qs:pop_sr":"5",
    "wd:wordcount":577,
    "wof:name":"Herbertpur",
    "wof:placetype":"locality",
    "wof:population":9478
},
  "geometry": {"coordinates":[77.73461,30.43909],"type":"Point"}
}