{
  "type": "Feature",
  "properties": {
    "iso:country":"IN",
    "ks:ks_name":"2 No. Kachari",
    "ks:ks_pop":167,
    "ks:ks_type":"HABITATION",
    "name:eng_x_preferred":[
        "2 No. Kachari"
    ],
    "wof:name":"2 No. Kachari",
    "wof:placetype":"locality",
    "wof:population":167
},
  "geometry": {"coordinates":[94.03641,26.486959],"type":"Point"}
}