{
  "type": "Feature",
  "properties": {
    "gn:admin1_code":"36",
    "gn:admin2_code":"161.0",
    "gn:asciiname":"Tirkara Badu",
    "gn:country_code":"IN",
    "gn:dem":153,
    "gn:feature_class":"P",
    "gn:feature_code":"PPL",
    "gn:name":"Tirk\u0101ra B\u0101du",
    "gn:population":0,
    "gn:timezone":"Asia/Kolkata",
    "iso:country":"IN",
    "wof:name":"Tirkara Badu",
    "wof:placetype":"locality"
},
  "geometry": {"coordinates":[78.94866999999998,26.94681],"type":"Point"}
}