{
  "type": "Feature",
  "properties": {
    "gn:admin1_code":"34.0",
    "gn:admin2_code":"207.0",
    "gn:asciiname":"Sukhwasi",
    "gn:country_code":"IN",
    "gn:dem":68,
    "gn:feature_class":"P",
    "gn:feature_code":"PPL",
    "gn:name":"Sukhw\u0101si",
    "gn:population":0,
    "gn:timezone":"Asia/Kolkata",
    "iso:country":"IN",
    "wof:name":"Sukhwasi",
    "wof:placetype":"locality"
},
  "geometry": {"coordinates":[85.97187,26.55608],"type":"Point"}
}