{
  "type": "Feature",
  "properties": {
    "gn:admin1_code":"39.0",
    "gn:admin2_code":"66.0",
    "gn:asciiname":"Dolmar",
    "gn:country_code":"IN",
    "gn:dem":1123,
    "gn:feature_class":"P",
    "gn:feature_code":"PPL",
    "gn:name":"Dolm\u0101r",
    "gn:population":0,
    "gn:timezone":"Asia/Kolkata",
    "iso:country":"IN",
    "name:fra_x_preferred":[
        "Dolmar"
    ],
    "name:ita_x_preferred":[
        "Dolmar"
    ],
    "name:nld_x_preferred":[
        "Dolmar"
    ],
    "name:nno_x_preferred":[
        "Dolmar GmbH"
    ],
    "name:swe_x_preferred":[
        "Dolmar GmbH"
    ],
    "wof:name":"Dolmar",
    "wof:placetype":"locality"
},
  "geometry": {"coordinates":[79.50609,29.31732],"type":"Point"}
}