{
  "type": "Feature",
  "properties": {
    "iso:country":"IN",
    "ks:ks_alt_nam":"KAMA",
    "ks:ks_name":"Kama",
    "ks:ks_pop":705,
    "ks:ks_type":"HABITATION",
    "name:eng_x_preferred":[
        "Kama"
    ],
    "wof:name":"Kama",
    "wof:placetype":"locality",
    "wof:population":705
},
  "geometry": {"coordinates":[83.665423,25.01907],"type":"Point"}
}