{
  "type": "Feature",
  "properties": {
    "gn:admin1_code":"36",
    "gn:admin2_code":"188.0",
    "gn:asciiname":"Pakwaria",
    "gn:country_code":"IN",
    "gn:dem":85,
    "gn:feature_class":"P",
    "gn:feature_code":"PPL",
    "gn:name":"Pakwaria",
    "gn:population":0,
    "gn:timezone":"Asia/Kolkata",
    "iso:country":"IN",
    "wof:name":"Pakwaria",
    "wof:placetype":"locality"
},
  "geometry": {"coordinates":[83.60786,26.72719],"type":"Point"}
}