{
  "type": "Feature",
  "properties": {
    "iso:country":"IN",
    "ks:ks_alt_nam":"KUTTEWASTI THABDEWADI",
    "ks:ks_name":"Kuttewasti Thabdewadi",
    "ks:ks_pop":101,
    "ks:ks_type":"HABITATION",
    "name:eng_x_preferred":[
        "Kuttewasti Thabdewadi"
    ],
    "wof:name":"Kuttewasti Thabdewadi",
    "wof:placetype":"locality",
    "wof:population":101
},
  "geometry": {"coordinates":[74.89492,17.030772],"type":"Point"}
}