{
  "type": "Feature",
  "properties": {
    "iso:country":"IN",
    "ks:ks_name":"Dhodhagaon Thethetanger",
    "ks:ks_pop":395,
    "ks:ks_type":"HABITATION",
    "name:eng_x_preferred":[
        "Dhodhagaon Thethetanger"
    ],
    "wof:name":"Dhodhagaon Thethetanger",
    "wof:placetype":"locality",
    "wof:population":395
},
  "geometry": {"coordinates":[83.604607,22.675982],"type":"Point"}
}