{
  "type": "Feature",
  "properties": {
    "iso:country":"IN",
    "ks:ks_name":"Mundia Pistor",
    "ks:ks_pop":572,
    "ks:ks_type":"VILLAGE",
    "ks:ks_uagg_main":0,
    "name:eng_x_preferred":[
        "Mundia Pistor"
    ],
    "wof:name":"Mundia Pistor",
    "wof:placetype":"neighbourhood",
    "wof:population":572
},
  "geometry": {"coordinates":[79.14453,29.149589],"type":"Point"}
}