{
  "type": "Feature",
  "properties": {
    "iso:country":"IN",
    "ks:ks_name":"Toera",
    "ks:ks_pop":387,
    "ks:ks_type":"VILLAGE",
    "name:eng_x_preferred":[
        "Toera"
    ],
    "wof:name":"Toera",
    "wof:placetype":"locality",
    "wof:population":387
},
  "geometry": {"coordinates":[85.586084,22.757058],"type":"Point"}
}