{
  "type": "Feature",
  "properties": {
    "gn:admin1_code":"16",
    "gn:admin2_code":"509.0",
    "gn:asciiname":"Shivsagar Tukum",
    "gn:country_code":"IN",
    "gn:dem":251,
    "gn:feature_class":"P",
    "gn:feature_code":"PPL",
    "gn:name":"Shivs\u0101gar Tukum",
    "gn:population":0,
    "gn:timezone":"Asia/Kolkata",
    "iso:country":"IN",
    "wof:name":"Shivsagar Tukum",
    "wof:placetype":"locality"
},
  "geometry": {"coordinates":[79.79631999999999,20.45846],"type":"Point"}
}