{
  "type": "Feature",
  "properties": {
    "iso:country":"IN",
    "ks:ks_name":"West Kholabhuyan No 2",
    "ks:ks_pop":63,
    "ks:ks_type":"HABITATION",
    "ks:ks_uagg_main":0,
    "name:eng_x_preferred":[
        "West Kholabhuyan No 2"
    ],
    "wof:name":"West Kholabhuyan No 2",
    "wof:placetype":"neighbourhood",
    "wof:population":63
},
  "geometry": {"coordinates":[92.09149499999999,26.235361],"type":"Point"}
}