{
  "type": "Feature",
  "properties": {
    "iso:country":"IN",
    "ks:ks_name":"Chhota Daikiari",
    "ks:ks_pop":153,
    "ks:ks_type":"VILLAGE",
    "name:eng_x_preferred":[
        "Chhota Daikiari"
    ],
    "wof:name":"Chhota Daikiari",
    "wof:placetype":"locality",
    "wof:population":153
},
  "geometry": {"coordinates":[86.692367,23.453549],"type":"Point"}
}