{
  "type": "Feature",
  "properties": {
    "gn:admin1_code":"35.0",
    "gn:admin2_code":"428",
    "gn:asciiname":"Ghatera",
    "gn:country_code":"IN",
    "gn:dem":333,
    "gn:feature_class":"P",
    "gn:feature_code":"PPL",
    "gn:name":"Ghatera",
    "gn:population":0,
    "gn:timezone":"Asia/Kolkata",
    "iso:country":"IN",
    "name:und_x_variant":[
        "Ghater\u0101"
    ],
    "wof:name":"Ghatera",
    "wof:placetype":"locality"
},
  "geometry": {"coordinates":[79.66925999999999,23.82779],"type":"Point"}
}