{
  "type": "Feature",
  "properties": {
    "iso:country":"IN",
    "ks:ks_name":"Mahikaramnath Pattiy.b",
    "ks:ks_pop":752,
    "ks:ks_type":"HABITATION",
    "name:eng_x_preferred":[
        "Mahikaramnath Pattiy.b"
    ],
    "wof:name":"Mahikaramnath Pattiy.b",
    "wof:placetype":"locality",
    "wof:population":752
},
  "geometry": {"coordinates":[83.255129,26.2573],"type":"Point"}
}