{
  "type": "Feature",
  "properties": {
    "iso:country":"IN",
    "ks:ks_name":"Pharainda",
    "ks:ks_pop":40,
    "ks:ks_type":"HABITATION",
    "name:eng_x_preferred":[
        "Pharainda"
    ],
    "wof:name":"Pharainda",
    "wof:placetype":"locality",
    "wof:population":40
},
  "geometry": {"coordinates":[80.873439,27.572776],"type":"Point"}
}