{
  "type": "Feature",
  "properties": {
    "gn:admin1_code":"09",
    "gn:admin2_code":"481.0",
    "gn:asciiname":"Ranigam",
    "gn:country_code":"IN",
    "gn:dem":65,
    "gn:feature_class":"P",
    "gn:feature_code":"PPL",
    "gn:name":"R\u0101n\u012bg\u0101m",
    "gn:population":0,
    "gn:timezone":"Asia/Kolkata",
    "iso:country":"IN",
    "wof:name":"Ranigam",
    "wof:placetype":"locality"
},
  "geometry": {"coordinates":[71.62732,21.42081],"type":"Point"}
}