{
  "type": "Feature",
  "properties": {
    "iso:country":"IN",
    "ks:ks_name":"Raghavwadi",
    "ks:ks_pop":70,
    "ks:ks_type":"HABITATION",
    "name:eng_x_preferred":[
        "Raghavwadi"
    ],
    "wof:name":"Raghavwadi",
    "wof:placetype":"locality",
    "wof:population":70
},
  "geometry": {"coordinates":[73.56361099999999,16.666389],"type":"Point"}
}