{
  "type": "Feature",
  "properties": {
    "iso:country":"IN",
    "ks:ks_alt_nam":"PURE GEHARVAR",
    "ks:ks_name":"Pure Geharvar",
    "ks:ks_pop":208,
    "ks:ks_type":"HABITATION",
    "name:eng_x_preferred":[
        "Pure Geharvar"
    ],
    "wof:name":"Pure Geharvar",
    "wof:placetype":"locality",
    "wof:population":208
},
  "geometry": {"coordinates":[81.47750000000001,26.287],"type":"Point"}
}