{
  "type": "Feature",
  "properties": {
    "gn:admin1_code":"34.0",
    "gn:admin2_code":"221.0",
    "gn:asciiname":"Rahimpur Peare",
    "gn:country_code":"IN",
    "gn:dem":50,
    "gn:feature_class":"P",
    "gn:feature_code":"PPL",
    "gn:name":"Rahimpur Pe\u0101re",
    "gn:population":0,
    "gn:timezone":"Asia/Kolkata",
    "iso:country":"IN",
    "ks:ks_alt_nam":"Rahimpur Pe\u0101re",
    "ks:ks_name":"Rahimpur Peare",
    "ks:ks_pop":2512,
    "ks:ks_type":"VILLAGE",
    "name:eng_x_preferred":[
        "Rahimpur Peare"
    ],
    "name:eng_x_variant":[
        "Rahimpur Pe\u0101re"
    ],
    "wof:name":"Rahimpur Peare",
    "wof:placetype":"locality",
    "wof:population":2512
},
  "geometry": {"coordinates":[85.774378,25.659545],"type":"Point"}
}