{
  "type": "Feature",
  "properties": {
    "iso:country":"IN",
    "ks:ks_name":"Upparagudem",
    "ks:ks_pop":291,
    "ks:ks_type":"HABITATION",
    "name:eng_x_preferred":[
        "Upparagudem"
    ],
    "wof:name":"Upparagudem",
    "wof:placetype":"locality",
    "wof:population":291
},
  "geometry": {"coordinates":[81.577169,16.477685],"type":"Point"}
}