{
  "type": "Feature",
  "properties": {
    "iso:country":"IN",
    "ks:ks_name":"Kurubanapalli",
    "ks:ks_pop":174,
    "ks:ks_type":"HABITATION",
    "name:eng_x_preferred":[
        "Kurubanapalli"
    ],
    "wof:name":"Kurubanapalli",
    "wof:placetype":"locality",
    "wof:population":174
},
  "geometry": {"coordinates":[77.661705,12.512],"type":"Point"}
}