{
  "type": "Feature",
  "properties": {
    "iso:country":"IN",
    "ks:ks_name":"Laxmipura",
    "ks:ks_pop":925,
    "ks:ks_type":"HABITATION",
    "name:eng_x_preferred":[
        "Laxmipura"
    ],
    "wof:name":"Laxmipura",
    "wof:placetype":"locality",
    "wof:population":925
},
  "geometry": {"coordinates":[73.590428,24.045986],"type":"Point"}
}