{
  "type": "Feature",
  "properties": {
    "iso:country":"IN",
    "ks:ks_name":"Nath Para",
    "ks:ks_pop":14,
    "ks:ks_type":"HABITATION",
    "name:eng_x_preferred":[
        "Nath Para"
    ],
    "wof:name":"Nath Para",
    "wof:placetype":"locality",
    "wof:population":14
},
  "geometry": {"coordinates":[91.60937199999999,23.288022],"type":"Point"}
}