{
  "type": "Feature",
  "properties": {
    "iso:country":"IN",
    "ks:ks_name":"Kamalpura Urf Rasulpur Patti",
    "ks:ks_pop":1225,
    "ks:ks_type":"VILLAGE",
    "name:eng_x_preferred":[
        "Kamalpura Urf Rasulpur Patti"
    ],
    "wof:name":"Kamalpura Urf Rasulpur Patti",
    "wof:placetype":"locality",
    "wof:population":1225
},
  "geometry": {"coordinates":[85.41033400000001,25.882249],"type":"Point"}
}