{
  "type": "Feature",
  "properties": {
    "gn:admin1_code":"24.0",
    "gn:admin2_code":"130.0",
    "gn:asciiname":"Talaupur",
    "gn:country_code":"IN",
    "gn:dem":258,
    "gn:feature_class":"P",
    "gn:feature_code":"PPL",
    "gn:name":"Talaupur",
    "gn:population":0,
    "gn:timezone":"Asia/Kolkata",
    "iso:country":"IN",
    "ks:ks_name":"Talapur",
    "ks:ks_pop":405,
    "ks:ks_type":"VILLAGE",
    "name:eng_x_preferred":[
        "Talapur"
    ],
    "name:eng_x_variant":[
        "Talaupur"
    ],
    "wof:name":"Talapur",
    "wof:placetype":"locality",
    "wof:population":405
},
  "geometry": {"coordinates":[74.273764,24.030947],"type":"Point"}
}