{
  "type": "Feature",
  "properties": {
    "iso:country":"IN",
    "name:eng_x_preferred":[
        "Naukuchiatal"
    ],
    "qs:name":"Naukuchiatal",
    "qs:name_adm0":"India",
    "qs:name_adm1":"Uttarakhand",
    "qs:photos":133,
    "qs:photos_1k":27,
    "qs:photos_9k":1,
    "qs:photos_9r":3,
    "qs:photos_all":133,
    "qs:photos_sr":3,
    "qs:placetype":"Town",
    "qs:pop_sr":"0",
    "wd:wordcount":947,
    "wof:name":"Naukuchiatal",
    "wof:placetype":"locality"
},
  "geometry": {"coordinates":[79.644184,29.386512],"type":"Point"}
}