{
  "type": "Feature",
  "properties": {
    "iso:country":"IN",
    "ks:ks_alt_nam":"YADAV TOL",
    "ks:ks_name":"Yadav Tol",
    "ks:ks_pop":2125,
    "ks:ks_type":"HABITATION",
    "ks:ks_uagg_main":0,
    "name:eng_x_preferred":[
        "Yadav Tol"
    ],
    "wof:name":"Yadav Tol",
    "wof:placetype":"neighbourhood",
    "wof:population":2125
},
  "geometry": {"coordinates":[86.37994999999999,26.051645],"type":"Point"}
}