{
  "type": "Feature",
  "properties": {
    "iso:country":"IN",
    "ks:ks_alt_nam":"Kamas kunta",
    "ks:ks_name":"Kamas Kunta",
    "ks:ks_pop":56,
    "ks:ks_type":"HABITATION",
    "name:eng_x_preferred":[
        "Kamas Kunta"
    ],
    "wof:name":"Kamas Kunta",
    "wof:placetype":"locality",
    "wof:population":56
},
  "geometry": {"coordinates":[77.780844,16.905341],"type":"Point"}
}