{
  "type": "Feature",
  "properties": {
    "iso:country":"IN",
    "ks:ks_name":"Besthapalayam",
    "ks:ks_pop":250,
    "ks:ks_type":"HABITATION",
    "name:eng_x_preferred":[
        "Besthapalayam"
    ],
    "wof:name":"Besthapalayam",
    "wof:placetype":"locality",
    "wof:population":250
},
  "geometry": {"coordinates":[80.14098,13.259873],"type":"Point"}
}