{
  "type": "Feature",
  "properties": {
    "gn:admin1_code":"24.0",
    "gn:admin2_code":"110.0",
    "gn:asciiname":"Rupawas ki Dhani",
    "gn:country_code":"IN",
    "gn:dem":470,
    "gn:feature_class":"P",
    "gn:feature_code":"PPL",
    "gn:name":"R\u016bp\u0101w\u0101s ki Dh\u0101ni",
    "gn:population":0,
    "gn:timezone":"Asia/Kolkata",
    "iso:country":"IN",
    "wof:name":"Rupawas ki Dhani",
    "wof:placetype":"neighbourhood"
},
  "geometry": {"coordinates":[75.69634000000001,27.16956],"type":"Point"}
}