{
  "type": "Feature",
  "properties": {
    "gn:admin1_code":"36.0",
    "gn:admin2_code":"175.0",
    "gn:asciiname":"Tulapur Taluka",
    "gn:country_code":"IN",
    "gn:dem":101,
    "gn:feature_class":"P",
    "gn:feature_code":"PPL",
    "gn:name":"Tul\u0101pur T\u0101luka",
    "gn:population":0,
    "gn:timezone":"Asia/Kolkata",
    "iso:country":"IN",
    "name:und_x_variant":[
        "Tul\u0101pur T\u0101luka",
        "Abd\u0101lpur"
    ],
    "wof:name":"Tulapur Taluka",
    "wof:placetype":"locality"
},
  "geometry": {"coordinates":[81.87049,25.59181],"type":"Point"}
}