{
  "type": "Feature",
  "properties": {
    "gn:admin1_code":"19.0",
    "gn:admin2_code":"563.0",
    "gn:asciiname":"Handiyani Math",
    "gn:country_code":"IN",
    "gn:dem":524,
    "gn:feature_class":"P",
    "gn:feature_code":"PPL",
    "gn:name":"Handiy\u0101ni Math",
    "gn:population":0,
    "gn:timezone":"Asia/Kolkata",
    "iso:country":"IN",
    "ks:ks_name":"Handyanematha",
    "ks:ks_pop":25,
    "ks:ks_type":"HABITATION",
    "name:eng_x_preferred":[
        "Handyanematha"
    ],
    "name:eng_x_variant":[
        "Handiyani Math"
    ],
    "wof:name":"Handyanematha",
    "wof:placetype":"locality",
    "wof:population":25
},
  "geometry": {"coordinates":[74.71024300000001,14.423764],"type":"Point"}
}