{
  "type": "Feature",
  "properties": {
    "gn:admin1_code":"23.0",
    "gn:admin2_code":"35.0",
    "gn:asciiname":"Narainpur",
    "gn:country_code":"IN",
    "gn:dem":261,
    "gn:feature_class":"P",
    "gn:feature_code":"PPL",
    "gn:name":"Nar\u0101inpur",
    "gn:population":0,
    "gn:timezone":"Asia/Kolkata",
    "iso:country":"IN",
    "ks:ks_alt_nam":"Nar\u0101inpur",
    "ks:ks_name":"Narainpur",
    "ks:ks_type":"VILLAGE",
    "name:eng_x_preferred":[
        "Narainpur"
    ],
    "name:eng_x_variant":[
        "Nar\u0101inpur"
    ],
    "wof:name":"Narainpur",
    "wof:placetype":"locality"
},
  "geometry": {"coordinates":[75.445971,32.213118],"type":"Point"}
}