{
  "type": "Feature",
  "properties": {
    "gn:admin1_code":"36.0",
    "gn:admin2_code":"181.0",
    "gn:asciiname":"Lunian Purwa",
    "gn:country_code":"IN",
    "gn:dem":121,
    "gn:feature_class":"P",
    "gn:feature_code":"PPL",
    "gn:name":"Lunian Purwa",
    "gn:population":0,
    "gn:timezone":"Asia/Kolkata",
    "iso:country":"IN",
    "ks:ks_alt_nam":"loniyan purwa",
    "ks:ks_name":"Loniyan Purwa",
    "ks:ks_pop":40,
    "ks:ks_type":"HABITATION",
    "name:eng_x_preferred":[
        "Loniyan Purwa"
    ],
    "name:eng_x_variant":[
        "Lunian Purwa"
    ],
    "wof:name":"Loniyan Purwa",
    "wof:placetype":"locality",
    "wof:population":40
},
  "geometry": {"coordinates":[81.816537,27.417807],"type":"Point"}
}