{
  "type": "Feature",
  "properties": {
    "gn:admin1_code":"37",
    "gn:admin2_code":"405.0",
    "gn:asciiname":"Murpar",
    "gn:country_code":"IN",
    "gn:dem":232,
    "gn:feature_class":"P",
    "gn:feature_code":"PPL",
    "gn:name":"Murp\u0101r",
    "gn:population":0,
    "gn:timezone":"Asia/Kolkata",
    "iso:country":"IN",
    "wof:name":"Murpar",
    "wof:placetype":"neighbourhood"
},
  "geometry": {"coordinates":[82.65091,21.73893],"type":"Point"}
}