{
  "type": "Feature",
  "properties": {
    "iso:country":"IN",
    "ks:ks_name":"Kauwajor",
    "ks:ks_pop":186,
    "ks:ks_type":"VILLAGE",
    "name:eng_x_preferred":[
        "Kauwajor"
    ],
    "wof:name":"Kauwajor",
    "wof:placetype":"locality",
    "wof:population":186
},
  "geometry": {"coordinates":[84.91151499999999,22.714067],"type":"Point"}
}