{
  "type": "Feature",
  "properties": {
    "iso:country":"IN",
    "ks:ks_name":"Tala Naranga",
    "ks:ks_pop":235,
    "ks:ks_type":"HABITATION",
    "name:eng_x_preferred":[
        "Tala Naranga"
    ],
    "wof:name":"Tala Naranga",
    "wof:placetype":"locality",
    "wof:population":235
},
  "geometry": {"coordinates":[82.81312699999999,18.871093],"type":"Point"}
}