{
  "type": "Feature",
  "properties": {
    "gn:admin1_code":"36",
    "gn:admin2_code":"179.0",
    "gn:asciiname":"Misrane",
    "gn:country_code":"IN",
    "gn:dem":106,
    "gn:feature_class":"P",
    "gn:feature_code":"PPL",
    "gn:name":"Misr\u0101ne",
    "gn:population":0,
    "gn:timezone":"Asia/Kolkata",
    "iso:country":"IN",
    "name:und_x_variant":[
        "Misr\u0101ne",
        "Purwa Jodhan"
    ],
    "wof:name":"Misrane",
    "wof:placetype":"neighbourhood"
},
  "geometry": {"coordinates":[82.13722,26.36257],"type":"Point"}
}