{
  "type": "Feature",
  "properties": {
    "iso:country":"IN",
    "ks:ks_name":"Karvanjewadi",
    "ks:ks_pop":130,
    "ks:ks_type":"HABITATION",
    "name:eng_x_preferred":[
        "Karvanjewadi"
    ],
    "wof:name":"Karvanjewadi",
    "wof:placetype":"locality",
    "wof:population":130
},
  "geometry": {"coordinates":[73.59,17.01],"type":"Point"}
}