{
  "type": "Feature",
  "properties": {
    "iso:country":"IN",
    "ks:ks_name":"Kempadommasandra",
    "ks:ks_pop":355,
    "ks:ks_type":"HABITATION",
    "name:eng_x_preferred":[
        "Kempadommasandra"
    ],
    "wof:name":"Kempadommasandra",
    "wof:placetype":"locality",
    "wof:population":355
},
  "geometry": {"coordinates":[77.70617,12.67125],"type":"Point"}
}