{
  "type": "Feature",
  "properties": {
    "gn:admin1_code":"11.0",
    "gn:admin2_code":"31.0",
    "gn:asciiname":"Ghalhut",
    "gn:country_code":"IN",
    "gn:dem":1744,
    "gn:feature_class":"P",
    "gn:feature_code":"PPL",
    "gn:name":"Ghalh\u016bt",
    "gn:population":0,
    "gn:timezone":"Asia/Kolkata",
    "iso:country":"IN",
    "wof:name":"Ghalhut",
    "wof:placetype":"locality"
},
  "geometry": {"coordinates":[77.11976,30.93257],"type":"Point"}
}