{
  "type": "Feature",
  "properties": {
    "iso:country":"IN",
    "ks:ks_alt_nam":"Barkhet\u0101",
    "ks:ks_name":"Barkheta",
    "ks:ks_pop":707,
    "ks:ks_type":"VILLAGE",
    "name:eng_x_preferred":[
        "Barkheta"
    ],
    "name:eng_x_variant":[
        "Barkhet\u0101"
    ],
    "wof:name":"Barkheta",
    "wof:placetype":"locality",
    "wof:population":707
},
  "geometry": {"coordinates":[84.150389,23.715099],"type":"Point"}
}