{
  "type": "Feature",
  "properties": {
    "gn:admin1_code":"40.0",
    "gn:admin2_code":"539",
    "gn:asciiname":"Advi Devalpalli",
    "gn:country_code":"IN",
    "gn:dem":90,
    "gn:feature_class":"P",
    "gn:feature_code":"PPL",
    "gn:name":"Advi Devalpalli",
    "gn:population":0,
    "gn:timezone":"Asia/Kolkata",
    "iso:country":"IN",
    "wof:name":"Advi Devalpalli",
    "wof:placetype":"neighbourhood"
},
  "geometry": {"coordinates":[79.51344,16.6622],"type":"Point"}
}