{
  "type": "Feature",
  "properties": {
    "iso:country":"IN",
    "ks:ks_name":"Devendra Para",
    "ks:ks_pop":155,
    "ks:ks_type":"HABITATION",
    "name:eng_x_preferred":[
        "Devendra Para"
    ],
    "wof:name":"Devendra Para",
    "wof:placetype":"locality",
    "wof:population":155
},
  "geometry": {"coordinates":[91.731694,23.365776],"type":"Point"}
}