{
  "type": "Feature",
  "properties": {
    "iso:country":"IN",
    "ks:ks_name":"Bichla Tola",
    "ks:ks_pop":489,
    "ks:ks_type":"HABITATION",
    "name:eng_x_preferred":[
        "Bichla Tola"
    ],
    "wof:name":"Bichla Tola",
    "wof:placetype":"locality",
    "wof:population":489
},
  "geometry": {"coordinates":[83.526735,24.121892],"type":"Point"}
}