{
  "type": "Feature",
  "properties": {
    "iso:country":"IN",
    "name:ara_x_preferred":[
        "\u0646\u0635\u0628 \u062a\u0634\u064a\u0646\u064a \u0643\u0627 \u0631\u0648\u0632\u0627"
    ],
    "name:ben_bn_x_preferred":[
        "\u099a\u09bf\u09a8\u09bf \u0995\u09be \u09b0\u09be\u0989\u099c\u09be"
    ],
    "name:ben_in_x_preferred":[
        "\u099a\u09bf\u09a8\u09bf \u0995\u09be \u09b0\u09be\u0989\u099c\u09be"
    ],
    "name:eng_x_preferred":[
        "Chini Ka Rauza"
    ],
    "name:guj_x_preferred":[
        "\u0a9a\u0abf\u0aa8\u0ac0 \u0a95\u0abe \u0ab0\u0acc\u0a9d\u0abe"
    ],
    "name:hin_x_preferred":[
        "\u091a\u0940\u0928\u0940 \u0915\u093e \u0930\u094c\u095b\u093e"
    ],
    "name:kan_x_preferred":[
        "\u0c9a\u0cbf\u0ca8\u0cbf \u0c95\u0cbe \u0cb0\u0ccc\u0c9c\u0cbe"
    ],
    "name:mal_x_preferred":[
        "\u0d1a\u0d3f\u0d28\u0d3f \u0d15\u0d3e \u0d31\u0d57\u0d38"
    ],
    "name:mar_x_preferred":[
        "\u091a\u093f\u0928\u0940 \u0915\u093e \u0930\u094c\u091d\u093e"
    ],
    "name:pan_x_preferred":[
        "\u0a1a\u0a3f\u0a28\u0a40 \u0a15\u0a3e \u0a30\u0a4b\u0a1c\u0a3c\u0a3e"
    ],
    "name:sqi_x_preferred":[
        "Chini Ka Rauza"
    ],
    "name:tam_x_preferred":[
        "\u0b9a\u0bc0\u0ba9\u0bbf \u0b95\u0bbe \u0bb0\u0bcc\u0b9c\u0bbe"
    ],
    "name:tel_x_preferred":[
        "\u0c1a\u0c3f\u0c28\u0c4d\u0c28\u0c3f \u0c15\u0c3e \u0c30\u0c4c\u0c1c\u0c3e"
    ],
    "name:urd_x_preferred":[
        "\u0686\u06cc\u0646\u06cc \u06a9\u0627 \u0631\u0648\u0636\u06c1"
    ],
    "qs:gn_adm0_cc":"IN",
    "qs:gn_local":1279259,
    "qs:gn_nam_loc":"Agra, Agra, Uttar Pradesh, IN",
    "qs:gn_namadm1":"36",
    "qs:local_max":10925,
    "qs:local_sum":42779,
    "qs:localhoods":21,
    "qs:name":"Chini Ka Rauza",
    "qs:name_adm0":"India",
    "qs:name_adm1":"Uttar Pradesh",
    "qs:name_adm2":"Agra",
    "qs:name_local":"Agra",
    "qs:photo_max":18,
    "qs:photo_sum":39,
    "qs:placetype":"Suburb",
    "qs:quad_count":5,
    "qs:woe_adm0":23424848,
    "qs:woe_adm1":2345760,
    "qs:woe_adm2":12586712,
    "qs:woe_lau":0,
    "qs:woe_local":2295399,
    "qs:woe_ver":"7.10.0",
    "wd:wordcount":298,
    "wof:lang":[
        "eng"
    ],
    "wof:name":"Chini Ka Rauza",
    "wof:placetype":"neighbourhood"
},
  "geometry": {"coordinates":[78.035994,27.205504],"type":"Point"}
}