{
  "type": "Feature",
  "properties": {
    "iso:country":"IN",
    "ks:ks_name":"Kukada Kotar",
    "ks:ks_pop":223,
    "ks:ks_type":"HABITATION",
    "name:eng_x_preferred":[
        "Kukada Kotar"
    ],
    "wof:name":"Kukada Kotar",
    "wof:placetype":"locality",
    "wof:population":223
},
  "geometry": {"coordinates":[73.407167,21.661167],"type":"Point"}
}