{
  "type": "Feature",
  "properties": {
    "iso:country":"IN",
    "ks:ks_name":"Bariya Fala",
    "ks:ks_pop":1854,
    "ks:ks_type":"HABITATION",
    "name:eng_x_preferred":[
        "Bariya Fala"
    ],
    "wof:name":"Bariya Fala",
    "wof:placetype":"locality",
    "wof:population":1854
},
  "geometry": {"coordinates":[74.31953300000001,23.079444],"type":"Point"}
}