{
  "type": "Feature",
  "properties": {
    "iso:country":"IN",
    "ks:ks_name":"Rohal",
    "ks:ks_pop":1030,
    "ks:ks_type":"VILLAGE",
    "name:eng_x_preferred":[
        "Rohal"
    ],
    "wof:name":"Rohal",
    "wof:placetype":"locality",
    "wof:population":1030
},
  "geometry": {"coordinates":[74.295179,23.548367],"type":"Point"}
}