{
  "type": "Feature",
  "properties": {
    "gn:admin1_code":"33.0",
    "gn:admin2_code":"586",
    "gn:asciiname":"Assolna",
    "gn:country_code":"IN",
    "gn:dem":11,
    "gn:feature_class":"P",
    "gn:feature_code":"PPL",
    "gn:name":"Assolna",
    "gn:population":0,
    "gn:timezone":"Asia/Kolkata",
    "iso:country":"IN",
    "wof:name":"Assolna",
    "wof:placetype":"locality"
},
  "geometry": {"coordinates":[73.97117,15.18067],"type":"Point"}
}