{
  "type": "Feature",
  "properties": {
    "gn:admin1_code":"36.0",
    "gn:admin2_code":"192.0",
    "gn:asciiname":"Pardaha Zamin Pardaha",
    "gn:country_code":"IN",
    "gn:dem":77,
    "gn:feature_class":"P",
    "gn:feature_code":"PPL",
    "gn:name":"Pardaha Zam\u012bn Pardaha",
    "gn:population":0,
    "gn:timezone":"Asia/Kolkata",
    "iso:country":"IN",
    "wof:name":"Pardaha Zamin Pardaha",
    "wof:placetype":"neighbourhood"
},
  "geometry": {"coordinates":[83.65237999999999,26.09169],"type":"Point"}
}