{
  "type": "Feature",
  "properties": {
    "gn:admin1_code":"19.0",
    "gn:admin2_code":"568.0",
    "gn:asciiname":"Billesvara",
    "gn:country_code":"IN",
    "gn:dem":706,
    "gn:feature_class":"P",
    "gn:feature_code":"PPL",
    "gn:name":"Billesvara",
    "gn:population":0,
    "gn:timezone":"Asia/Kolkata",
    "iso:country":"IN",
    "ks:ks_name":"Billeshwara",
    "ks:ks_pop":565,
    "ks:ks_type":"HABITATION",
    "name:eng_x_preferred":[
        "Billeshwara"
    ],
    "name:eng_x_variant":[
        "Billesvara"
    ],
    "wof:name":"Billeshwara",
    "wof:placetype":"locality",
    "wof:population":565
},
  "geometry": {"coordinates":[75.203334,13.853053],"type":"Point"}
}