{
  "type": "Feature",
  "properties": {
    "iso:country":"IN",
    "ks:ks_name":"Faridpur",
    "ks:ks_pop":536,
    "ks:ks_type":"VILLAGE",
    "ks:ks_uagg_main":0,
    "name:eng_x_preferred":[
        "Faridpur"
    ],
    "wof:name":"Faridpur",
    "wof:placetype":"neighbourhood",
    "wof:population":536
},
  "geometry": {"coordinates":[88.11037,23.018574],"type":"Point"}
}