{
  "type": "Feature",
  "properties": {
    "iso:country":"IN",
    "ks:ks_name":"Doodhwat",
    "ks:ks_pop":1027,
    "ks:ks_type":"VILLAGE",
    "name:eng_x_preferred":[
        "Doodhwat"
    ],
    "wof:name":"Doodhwat",
    "wof:placetype":"locality",
    "wof:population":1027
},
  "geometry": {"coordinates":[72.19479699999999,24.794336],"type":"Point"}
}