{
  "type": "Feature",
  "properties": {
    "gn:admin1_code":"37",
    "gn:admin2_code":"410.0",
    "gn:asciiname":"Lawan",
    "gn:country_code":"IN",
    "gn:dem":255,
    "gn:feature_class":"P",
    "gn:feature_code":"PPL",
    "gn:name":"Lawan",
    "gn:population":0,
    "gn:timezone":"Asia/Kolkata",
    "iso:country":"IN",
    "name:ceb_x_preferred":[
        "Lawan"
    ],
    "name:jpn_x_preferred":[
        "\u30e9\u30ef\u30f3"
    ],
    "name:swe_x_preferred":[
        "Lawan"
    ],
    "wof:name":"Lawan",
    "wof:placetype":"locality"
},
  "geometry": {"coordinates":[82.34123000000002,21.64137],"type":"Point"}
}