{
  "type": "Feature",
  "properties": {
    "iso:country":"IN",
    "ks:ks_name":"Nai Basti",
    "ks:ks_pop":383,
    "ks:ks_type":"HABITATION",
    "name:eng_x_preferred":[
        "Nai Basti"
    ],
    "wof:name":"Nai Basti",
    "wof:placetype":"locality",
    "wof:population":383
},
  "geometry": {"coordinates":[74.29013399999999,23.90447],"type":"Point"}
}