{
  "type": "Feature",
  "properties": {
    "gn:admin1_code":"25.0",
    "gn:admin2_code":"605.0",
    "gn:asciiname":"Kattarikuppam",
    "gn:country_code":"IN",
    "gn:dem":295,
    "gn:feature_class":"P",
    "gn:feature_code":"PPL",
    "gn:name":"Katt\u0101rikuppam",
    "gn:population":0,
    "gn:timezone":"Asia/Kolkata",
    "iso:country":"IN",
    "ks:ks_name":"Kathadikuppam",
    "ks:ks_pop":320,
    "ks:ks_type":"VILLAGE",
    "name:eng_x_preferred":[
        "Kathadikuppam"
    ],
    "name:eng_x_variant":[
        "Kattarikuppam"
    ],
    "wof:name":"Kathadikuppam",
    "wof:placetype":"locality",
    "wof:population":320
},
  "geometry": {"coordinates":[78.853696,12.966866],"type":"Point"}
}