{
  "type": "Feature",
  "properties": {
    "gn:admin1_code":"19",
    "gn:admin2_code":"579.0",
    "gn:asciiname":"Aurad",
    "gn:country_code":"IN",
    "gn:dem":433,
    "gn:feature_class":"P",
    "gn:feature_code":"PPL",
    "gn:name":"Aur\u0101d",
    "gn:population":0,
    "gn:timezone":"Asia/Kolkata",
    "iso:country":"IN",
    "name:ben_x_preferred":[
        "\u0994\u09b0\u09a6"
    ],
    "name:bpy_x_preferred":[
        "\u0986\u0989\u09b0\u09a6"
    ],
    "name:cat_x_preferred":[
        "Aurad"
    ],
    "name:ceb_x_preferred":[
        "Aur\u0101d"
    ],
    "name:ita_x_preferred":[
        "Aurad"
    ],
    "name:kan_x_preferred":[
        "\u0c94\u0cb0\u0cbe\u0ca6"
    ],
    "name:mlg_x_preferred":[
        "Aurad"
    ],
    "name:msa_x_preferred":[
        "Aurad"
    ],
    "name:new_x_preferred":[
        "\u0914\u0930\u0926"
    ],
    "name:nld_x_preferred":[
        "Aurad"
    ],
    "name:por_x_preferred":[
        "Aurad"
    ],
    "name:san_x_preferred":[
        "\u0914\u0930\u093e\u0926"
    ],
    "name:swe_x_preferred":[
        "Aur\u0101d"
    ],
    "name:vie_x_preferred":[
        "Aurad"
    ],
    "name:zho_x_preferred":[
        "\u5965\u62c9\u5fb7"
    ],
    "wof:name":"Aurad",
    "wof:placetype":"locality"
},
  "geometry": {"coordinates":[76.7615,16.97155],"type":"Point"}
}