{
  "type": "Feature",
  "properties": {
    "iso:country":"IN",
    "ks:ks_name":"Kandala",
    "ks:ks_pop":22,
    "ks:ks_type":"HABITATION",
    "name:eng_x_preferred":[
        "Kandala"
    ],
    "wof:name":"Kandala",
    "wof:placetype":"locality",
    "wof:population":22
},
  "geometry": {"coordinates":[82.11071,18.29924],"type":"Point"}
}