{
  "type": "Feature",
  "properties": {
    "iso:country":"IN",
    "ks:ks_name":"Nai Khet",
    "ks:ks_type":"VILLAGE",
    "name:eng_x_preferred":[
        "Nai Khet"
    ],
    "wof:name":"Nai Khet",
    "wof:placetype":"locality"
},
  "geometry": {"coordinates":[78.847965,30.215034],"type":"Point"}
}