{
  "type": "Feature",
  "properties": {
    "iso:country":"IN",
    "ks:ks_name":"Reta",
    "ks:ks_pop":516,
    "ks:ks_type":"HABITATION",
    "ks:ks_uagg_main":0,
    "name:eng_x_preferred":[
        "Reta"
    ],
    "wof:name":"Reta",
    "wof:placetype":"neighbourhood",
    "wof:population":516
},
  "geometry": {"coordinates":[84.18603,27.0639],"type":"Point"}
}