{
  "type": "Feature",
  "properties": {
    "gn:admin1_code":"24.0",
    "gn:admin2_code":"130.0",
    "gn:asciiname":"Kupachoki",
    "gn:country_code":"IN",
    "gn:dem":557,
    "gn:feature_class":"P",
    "gn:feature_code":"PPL",
    "gn:name":"Kupachoki",
    "gn:population":0,
    "gn:timezone":"Asia/Kolkata",
    "iso:country":"IN",
    "ks:ks_name":"Kupa Chaoki",
    "ks:ks_pop":41,
    "ks:ks_type":"VILLAGE",
    "name:eng_x_preferred":[
        "Kupa Chaoki"
    ],
    "name:eng_x_variant":[
        "Kupachoki"
    ],
    "wof:name":"Kupa Chaoki",
    "wof:placetype":"locality",
    "wof:population":41
},
  "geometry": {"coordinates":[73.501983,24.393367],"type":"Point"}
}