{
  "type": "Feature",
  "properties": {
    "gn:admin1_code":"36.0",
    "gn:admin2_code":"193.0",
    "gn:asciiname":"Sultanpur",
    "gn:country_code":"IN",
    "gn:dem":69,
    "gn:feature_class":"P",
    "gn:feature_code":"PPL",
    "gn:name":"Sult\u0101npur",
    "gn:population":0,
    "gn:timezone":"Asia/Kolkata",
    "iso:country":"IN",
    "wof:name":"Sultanpur",
    "wof:placetype":"locality"
},
  "geometry": {"coordinates":[84.10664,25.86663],"type":"Point"}
}