{
  "type": "Feature",
  "properties": {
    "iso:country":"IN",
    "ks:ks_name":"Nangal Bani",
    "ks:ks_pop":2229,
    "ks:ks_type":"VILLAGE",
    "name:eng_x_preferred":[
        "Nangal Bani"
    ],
    "wof:name":"Nangal Bani",
    "wof:placetype":"locality",
    "wof:population":2229
},
  "geometry": {"coordinates":[76.22444400000001,27.358056],"type":"Point"}
}