{
  "type": "Feature",
  "properties": {
    "iso:country":"IN",
    "ks:ks_name":"Naduthota",
    "ks:ks_pop":189,
    "ks:ks_type":"HABITATION",
    "name:eng_x_preferred":[
        "Naduthota"
    ],
    "wof:name":"Naduthota",
    "wof:placetype":"locality",
    "wof:population":189
},
  "geometry": {"coordinates":[75.16591099999999,12.643573],"type":"Point"}
}