{
  "type": "Feature",
  "properties": {
    "iso:country":"IN",
    "ks:ks_name":"Magani",
    "ks:ks_pop":67,
    "ks:ks_type":"HABITATION",
    "name:eng_x_preferred":[
        "Magani"
    ],
    "wof:name":"Magani",
    "wof:placetype":"locality",
    "wof:population":67
},
  "geometry": {"coordinates":[74.861301,14.429073],"type":"Point"}
}