{
  "type": "Feature",
  "properties": {
    "gn:admin1_code":"36",
    "gn:admin2_code":"158.0",
    "gn:asciiname":"Jagatpur",
    "gn:country_code":"IN",
    "gn:dem":121,
    "gn:feature_class":"P",
    "gn:feature_code":"PPL",
    "gn:name":"Jagatpur",
    "gn:population":0,
    "gn:timezone":"Asia/Kolkata",
    "iso:country":"IN",
    "name:ceb_x_preferred":[
        "Jagatpur"
    ],
    "name:pol_x_preferred":[
        "Jagatpur"
    ],
    "name:swe_x_preferred":[
        "Jagatpur"
    ],
    "name:und_x_variant":[
        "R\u0101mgarhi"
    ],
    "wof:name":"Jagatpur",
    "wof:placetype":"locality"
},
  "geometry": {"coordinates":[80.94113,26.2303],"type":"Point"}
}