{
  "type": "Feature",
  "properties": {
    "iso:country":"IN",
    "ks:ks_name":"Karanjpada",
    "ks:ks_pop":222,
    "ks:ks_type":"VILLAGE",
    "name:eng_x_preferred":[
        "Karanjpada"
    ],
    "wof:name":"Karanjpada",
    "wof:placetype":"locality",
    "wof:population":222
},
  "geometry": {"coordinates":[73.837694,20.901806],"type":"Point"}
}