{
  "type": "Feature",
  "properties": {
    "iso:country":"IN",
    "ks:ks_alt_nam":"Korian purwa",
    "ks:ks_name":"Korian Purwa",
    "ks:ks_pop":106,
    "ks:ks_type":"HABITATION",
    "name:eng_x_preferred":[
        "Korian Purwa"
    ],
    "wof:name":"Korian Purwa",
    "wof:placetype":"locality",
    "wof:population":106
},
  "geometry": {"coordinates":[81.31113499999999,27.315053],"type":"Point"}
}