{
  "type": "Feature",
  "properties": {
    "iso:country":"IN",
    "ks:ks_name":"Sardarsai",
    "ks:ks_pop":61,
    "ks:ks_type":"HABITATION",
    "name:eng_x_preferred":[
        "Sardarsai"
    ],
    "wof:name":"Sardarsai",
    "wof:placetype":"locality",
    "wof:population":61
},
  "geometry": {"coordinates":[85.954888,22.161223],"type":"Point"}
}