{
  "type": "Feature",
  "properties": {
    "gn:admin1_code":"34.0",
    "gn:admin2_code":"237.0",
    "gn:asciiname":"Akhra",
    "gn:country_code":"IN",
    "gn:dem":109,
    "gn:feature_class":"P",
    "gn:feature_code":"PPL",
    "gn:name":"Akhra",
    "gn:population":0,
    "gn:timezone":"Asia/Kolkata",
    "iso:country":"IN",
    "ks:ks_name":"Akhra",
    "ks:ks_type":"VILLAGE",
    "name:eng_x_preferred":[
        "Akhra"
    ],
    "wof:name":"Akhra",
    "wof:placetype":"locality"
},
  "geometry": {"coordinates":[85.413358,24.785919],"type":"Point"}
}