{
  "type": "Feature",
  "properties": {
    "iso:country":"IN",
    "ks:ks_name":"Adottukaya",
    "ks:ks_pop":1474,
    "ks:ks_type":"HABITATION",
    "name:eng_x_preferred":[
        "Adottukaya"
    ],
    "wof:name":"Adottukaya",
    "wof:placetype":"locality",
    "wof:population":1474
},
  "geometry": {"coordinates":[75.28726,12.425758],"type":"Point"}
}