{
  "type": "Feature",
  "properties": {
    "gn:admin1_code":"24",
    "gn:admin2_code":"123.0",
    "gn:asciiname":"Pokaria",
    "gn:country_code":"IN",
    "gn:dem":665,
    "gn:feature_class":"P",
    "gn:feature_code":"PPL",
    "gn:name":"Pok\u0101ria",
    "gn:population":0,
    "gn:timezone":"Asia/Kolkata",
    "iso:country":"IN",
    "wof:name":"Pokaria",
    "wof:placetype":"neighbourhood"
},
  "geometry": {"coordinates":[73.90416,25.64114],"type":"Point"}
}