{
  "type": "Feature",
  "properties": {
    "gn:admin1_code":"36",
    "gn:admin2_code":"166.0",
    "gn:asciiname":"Tal Ramanna",
    "gn:country_code":"IN",
    "gn:dem":229,
    "gn:feature_class":"P",
    "gn:feature_code":"PPL",
    "gn:name":"T\u0101l Ramanna",
    "gn:population":0,
    "gn:timezone":"Asia/Kolkata",
    "iso:country":"IN",
    "wof:name":"Tal Ramanna",
    "wof:placetype":"locality"
},
  "geometry": {"coordinates":[78.73394999999999,25.36651],"type":"Point"}
}