{
  "type": "Feature",
  "properties": {
    "iso:country":"IN",
    "ks:ks_name":"Adhouri Bigha",
    "ks:ks_pop":155,
    "ks:ks_type":"HABITATION",
    "name:eng_x_preferred":[
        "Adhouri Bigha"
    ],
    "wof:name":"Adhouri Bigha",
    "wof:placetype":"locality",
    "wof:population":155
},
  "geometry": {"coordinates":[84.862995,24.887873],"type":"Point"}
}