{
  "type": "Feature",
  "properties": {
    "iso:country":"IN",
    "ks:ks_name":"Ashwinpur",
    "ks:ks_pop":351,
    "ks:ks_type":"VILLAGE",
    "name:eng_x_preferred":[
        "Ashwinpur"
    ],
    "wof:name":"Ashwinpur",
    "wof:placetype":"locality",
    "wof:population":351
},
  "geometry": {"coordinates":[87.66678899999999,23.097567],"type":"Point"}
}