{
  "type": "Feature",
  "properties": {
    "gn:admin1_code":"36.0",
    "gn:admin2_code":"160",
    "gn:asciiname":"Nagla Bari",
    "gn:country_code":"IN",
    "gn:dem":152,
    "gn:feature_class":"P",
    "gn:feature_code":"PPL",
    "gn:name":"Nagla Bari",
    "gn:population":0,
    "gn:timezone":"Asia/Kolkata",
    "iso:country":"IN",
    "wof:name":"Nagla Bari",
    "wof:placetype":"locality"
},
  "geometry": {"coordinates":[79.40319000000002,27.09962],"type":"Point"}
}