{
  "type": "Feature",
  "properties": {
    "iso:country":"IN",
    "ks:ks_name":"Ranewala",
    "ks:ks_pop":656,
    "ks:ks_type":"VILLAGE",
    "name:eng_x_preferred":[
        "Ranewala"
    ],
    "wof:name":"Ranewala",
    "wof:placetype":"locality",
    "wof:population":656
},
  "geometry": {"coordinates":[72.85391300000001,28.640799],"type":"Point"}
}