{
  "type": "Feature",
  "properties": {
    "iso:country":"IN",
    "ks:ks_name":"Chennaipally No-2",
    "ks:ks_pop":148,
    "ks:ks_type":"HABITATION",
    "name:eng_x_preferred":[
        "Chennaipally No-2"
    ],
    "wof:name":"Chennaipally No-2",
    "wof:placetype":"locality",
    "wof:population":148
},
  "geometry": {"coordinates":[77.80206099999999,16.940916],"type":"Point"}
}