{
  "type": "Feature",
  "properties": {
    "gn:admin1_code":"24",
    "gn:admin2_code":"125.0",
    "gn:asciiname":"Bawripara",
    "gn:country_code":"IN",
    "gn:dem":252,
    "gn:feature_class":"P",
    "gn:feature_code":"PPL",
    "gn:name":"B\u0101wr\u012bp\u0101ra",
    "gn:population":0,
    "gn:timezone":"Asia/Kolkata",
    "iso:country":"IN",
    "ks:ks_name":"Baori-Para",
    "ks:ks_type":"VILLAGE",
    "name:eng_x_preferred":[
        "Baori-Para"
    ],
    "name:eng_x_variant":[
        "Bawripara"
    ],
    "wof:name":"Baori-Para",
    "wof:placetype":"locality"
},
  "geometry": {"coordinates":[74.324596,23.158471],"type":"Point"}
}