{
  "type": "Feature",
  "properties": {
    "iso:country":"IN",
    "ks:ks_name":"Chaukipada",
    "ks:ks_pop":627,
    "ks:ks_type":"HABITATION",
    "name:eng_x_preferred":[
        "Chaukipada"
    ],
    "wof:name":"Chaukipada",
    "wof:placetype":"locality",
    "wof:population":627
},
  "geometry": {"coordinates":[73.261833,20.071387],"type":"Point"}
}