{
  "type": "Feature",
  "properties": {
    "iso:country":"IN",
    "ks:ks_name":"Mysoreppanadoddi",
    "ks:ks_pop":618,
    "ks:ks_type":"HABITATION",
    "name:eng_x_preferred":[
        "Mysoreppanadoddi"
    ],
    "wof:name":"Mysoreppanadoddi",
    "wof:placetype":"locality",
    "wof:population":618
},
  "geometry": {"coordinates":[77.264822,11.909895],"type":"Point"}
}