{
  "type": "Feature",
  "properties": {
    "gn:admin1_code":"36",
    "gn:admin2_code":"168.0",
    "gn:asciiname":"Singran",
    "gn:country_code":"IN",
    "gn:dem":153,
    "gn:feature_class":"P",
    "gn:feature_code":"PPL",
    "gn:name":"Singr\u0101n",
    "gn:population":0,
    "gn:timezone":"Asia/Kolkata",
    "iso:country":"IN",
    "ks:ks_alt_nam":"Singr\u0101n",
    "ks:ks_name":"Singran",
    "ks:ks_type":"VILLAGE",
    "name:eng_x_preferred":[
        "Singran"
    ],
    "name:eng_x_variant":[
        "Singr\u0101n"
    ],
    "wof:name":"Singran",
    "wof:placetype":"locality"
},
  "geometry": {"coordinates":[79.615589,25.697177],"type":"Point"}
}