{
  "type": "Feature",
  "properties": {
    "iso:country":"IN",
    "ks:ks_alt_nam":"K.Kunnuru",
    "ks:ks_name":"K.kunnuru",
    "ks:ks_pop":82,
    "ks:ks_type":"HABITATION",
    "name:eng_x_preferred":[
        "K.kunnuru"
    ],
    "wof:name":"K.kunnuru",
    "wof:placetype":"locality",
    "wof:population":82
},
  "geometry": {"coordinates":[75.182176,13.916367],"type":"Point"}
}