{
  "type": "Feature",
  "properties": {
    "gn:admin1_code":"2.0",
    "gn:admin2_code":"543",
    "gn:asciiname":"Chemudu",
    "gn:country_code":"IN",
    "gn:dem":151,
    "gn:feature_class":"P",
    "gn:feature_code":"PPL",
    "gn:name":"Chemudu",
    "gn:population":0,
    "gn:timezone":"Asia/Kolkata",
    "iso:country":"IN",
    "wof:name":"Chemudu",
    "wof:placetype":"locality"
},
  "geometry": {"coordinates":[83.22915999999999,18.64157],"type":"Point"}
}