{
  "type": "Feature",
  "properties": {
    "iso:country":"IN",
    "ks:ks_name":"No.2 Sivaguri",
    "ks:ks_pop":72,
    "ks:ks_type":"HABITATION",
    "name:eng_x_preferred":[
        "No.2 Sivaguri"
    ],
    "wof:name":"No.2 Sivaguri",
    "wof:placetype":"locality",
    "wof:population":72
},
  "geometry": {"coordinates":[95.300527,27.85036],"type":"Point"}
}