{
  "type": "Feature",
  "properties": {
    "iso:country":"IN",
    "ks:ks_name":"Yerakarajupuram",
    "ks:ks_pop":113,
    "ks:ks_type":"HABITATION",
    "name:eng_x_preferred":[
        "Yerakarajupuram"
    ],
    "wof:name":"Yerakarajupuram",
    "wof:placetype":"locality",
    "wof:population":113
},
  "geometry": {"coordinates":[83.73322,18.637415],"type":"Point"}
}