{
  "type": "Feature",
  "properties": {
    "iso:country":"IN",
    "ks:ks_name":"Kurinjankottai",
    "ks:ks_pop":336,
    "ks:ks_type":"HABITATION",
    "name:eng_x_preferred":[
        "Kurinjankottai"
    ],
    "wof:name":"Kurinjankottai",
    "wof:placetype":"locality",
    "wof:population":336
},
  "geometry": {"coordinates":[79.134664,10.171387],"type":"Point"}
}