{
  "type": "Feature",
  "properties": {
    "iso:country":"IN",
    "ks:ks_name":"Painthar",
    "ks:ks_pop":374,
    "ks:ks_type":"VILLAGE",
    "name:eng_x_preferred":[
        "Painthar"
    ],
    "wof:name":"Painthar",
    "wof:placetype":"locality",
    "wof:population":374
},
  "geometry": {"coordinates":[78.310751,30.6795],"type":"Point"}
}