{
  "type": "Feature",
  "properties": {
    "iso:country":"IN",
    "ks:ks_alt_nam":"HULLE PLOT",
    "ks:ks_name":"Hulle Plot",
    "ks:ks_pop":1518,
    "ks:ks_type":"HABITATION",
    "ks:ks_uagg_main":0,
    "name:eng_x_preferred":[
        "Hulle Plot"
    ],
    "wof:name":"Hulle Plot",
    "wof:placetype":"neighbourhood",
    "wof:population":1518
},
  "geometry": {"coordinates":[74.683763,16.842993],"type":"Point"}
}