{
  "type": "Feature",
  "properties": {
    "iso:country":"IN",
    "ks:ks_alt_nam":"Loniyan purwa",
    "ks:ks_name":"Loniyan Purwa",
    "ks:ks_pop":187,
    "ks:ks_type":"HABITATION",
    "name:eng_x_preferred":[
        "Loniyan Purwa"
    ],
    "wof:name":"Loniyan Purwa",
    "wof:placetype":"locality",
    "wof:population":187
},
  "geometry": {"coordinates":[81.76594299999999,27.413808],"type":"Point"}
}