{
  "type": "Feature",
  "properties": {
    "gn:admin1_code":"9.0",
    "gn:admin2_code":"473.0",
    "gn:asciiname":"Sabolo",
    "gn:country_code":"IN",
    "gn:dem":76,
    "gn:feature_class":"P",
    "gn:feature_code":"PPL",
    "gn:name":"S\u0101bolo",
    "gn:population":0,
    "gn:timezone":"Asia/Kolkata",
    "iso:country":"IN",
    "wof:name":"Sabolo",
    "wof:placetype":"locality"
},
  "geometry": {"coordinates":[73.00001999999998,23.13566],"type":"Point"}
}