{
  "type": "Feature",
  "properties": {
    "gn:admin1_code":"39",
    "gn:admin2_code":"60.0",
    "gn:asciiname":"Kudoli",
    "gn:country_code":"IN",
    "gn:dem":915,
    "gn:feature_class":"P",
    "gn:feature_code":"PPL",
    "gn:name":"Kudoli",
    "gn:population":0,
    "gn:timezone":"Asia/Kolkata",
    "iso:country":"IN",
    "wof:name":"Kudoli",
    "wof:placetype":"locality"
},
  "geometry": {"coordinates":[77.8325,30.87476],"type":"Point"}
}