{
  "type": "Feature",
  "properties": {
    "iso:country":"IN",
    "ks:ks_name":"Charing Kaiborto",
    "ks:ks_pop":802,
    "ks:ks_type":"HABITATION",
    "name:eng_x_preferred":[
        "Charing Kaiborto"
    ],
    "wof:name":"Charing Kaiborto",
    "wof:placetype":"locality",
    "wof:population":802
},
  "geometry": {"coordinates":[94.546201,26.888691],"type":"Point"}
}