{
  "type": "Feature",
  "properties": {
    "iso:country":"IN",
    "ks:ks_name":"Rathourpur",
    "ks:ks_pop":680,
    "ks:ks_type":"VILLAGE",
    "ks:ks_uagg_main":0,
    "name:eng_x_preferred":[
        "Rathourpur"
    ],
    "wof:name":"Rathourpur",
    "wof:placetype":"neighbourhood",
    "wof:population":680
},
  "geometry": {"coordinates":[80.641448,27.41788],"type":"Point"}
}