{
  "type": "Feature",
  "properties": {
    "gn:admin1_code":"35.0",
    "gn:admin2_code":"437.0",
    "gn:asciiname":"Barkhera",
    "gn:country_code":"IN",
    "gn:dem":513,
    "gn:feature_class":"P",
    "gn:feature_code":"PPL",
    "gn:name":"Barkhera",
    "gn:population":0,
    "gn:timezone":"Asia/Kolkata",
    "iso:country":"IN",
    "name:bpy_x_preferred":[
        "\u09ac\u09be\u09b0\u0996\u09c7\u09b0\u09be"
    ],
    "name:ceb_x_preferred":[
        "Barkhera"
    ],
    "name:ita_x_preferred":[
        "Barkhera"
    ],
    "name:mlg_x_preferred":[
        "Barkhera"
    ],
    "name:msa_x_preferred":[
        "Barkhera"
    ],
    "name:new_x_preferred":[
        "\u092c\u0930\u094d\u0916\u0947\u0930\u093e"
    ],
    "name:nld_x_preferred":[
        "Barkhera"
    ],
    "name:pol_x_preferred":[
        "Barkhera"
    ],
    "name:por_x_preferred":[
        "Barkhera"
    ],
    "name:swe_x_preferred":[
        "Barkhera"
    ],
    "name:urd_x_preferred":[
        "\u0628\u0631\u06a9\u06be\u06cc\u0691\u0627"
    ],
    "name:vie_x_preferred":[
        "Barkhera"
    ],
    "name:zho_x_preferred":[
        "\u5df4\u5c14\u51ef\u62c9"
    ],
    "wof:name":"Barkhera",
    "wof:placetype":"locality"
},
  "geometry": {"coordinates":[76.13077,23.16244],"type":"Point"}
}