{
  "type": "Feature",
  "properties": {
    "iso:country":"IN",
    "ks:ks_name":"Tutiha",
    "ks:ks_pop":166,
    "ks:ks_type":"HABITATION",
    "name:eng_x_preferred":[
        "Tutiha"
    ],
    "wof:name":"Tutiha",
    "wof:placetype":"locality",
    "wof:population":166
},
  "geometry": {"coordinates":[81.91332300000001,27.493103],"type":"Point"}
}