{
  "type": "Feature",
  "properties": {
    "gn:admin1_code":"21",
    "gn:admin2_code":"390.0",
    "gn:asciiname":"Madaguda",
    "gn:country_code":"IN",
    "gn:dem":378,
    "gn:feature_class":"P",
    "gn:feature_code":"PPL",
    "gn:name":"M\u0101daguda",
    "gn:population":0,
    "gn:timezone":"Asia/Kolkata",
    "iso:country":"IN",
    "wof:name":"Madaguda",
    "wof:placetype":"locality"
},
  "geometry": {"coordinates":[83.74415999999999,19.90212],"type":"Point"}
}