{
  "type": "Feature",
  "properties": {
    "iso:country":"IN",
    "ks:ks_name":"Unchageri",
    "ks:ks_pop":159,
    "ks:ks_type":"HABITATION",
    "name:eng_x_preferred":[
        "Unchageri"
    ],
    "wof:name":"Unchageri",
    "wof:placetype":"locality",
    "wof:population":159
},
  "geometry": {"coordinates":[74.476871,14.343111],"type":"Point"}
}