{
  "type": "Feature",
  "properties": {
    "iso:country":"IN",
    "ks:ks_name":"Kudwari",
    "ks:ks_pop":852,
    "ks:ks_type":"VILLAGE",
    "name:eng_x_preferred":[
        "Kudwari"
    ],
    "wof:name":"Kudwari",
    "wof:placetype":"locality",
    "wof:population":852
},
  "geometry": {"coordinates":[80.994877,23.165847],"type":"Point"}
}