{
  "type": "Feature",
  "properties": {
    "iso:country":"IN",
    "ks:ks_alt_nam":"Raigung pada",
    "ks:ks_name":"Raigung Pada",
    "ks:ks_pop":260,
    "ks:ks_type":"HABITATION",
    "name:eng_x_preferred":[
        "Raigung Pada"
    ],
    "wof:name":"Raigung Pada",
    "wof:placetype":"locality",
    "wof:population":260
},
  "geometry": {"coordinates":[73.001583,19.745872],"type":"Point"}
}