{
  "type": "Feature",
  "properties": {
    "gn:admin1_code":"36",
    "gn:admin2_code":"180.0",
    "gn:asciiname":"Ratahia",
    "gn:country_code":"IN",
    "gn:dem":125,
    "gn:feature_class":"P",
    "gn:feature_code":"PPL",
    "gn:name":"Ratahia",
    "gn:population":0,
    "gn:timezone":"Asia/Kolkata",
    "iso:country":"IN",
    "name:und_x_variant":[
        "Kalw\u0101ran Purwa"
    ],
    "wof:name":"Ratahia",
    "wof:placetype":"locality"
},
  "geometry": {"coordinates":[81.72719000000002,27.56182],"type":"Point"}
}