{
  "type": "Feature",
  "properties": {
    "iso:country":"IN",
    "ks:ks_name":"Ramaguda",
    "ks:ks_pop":358,
    "ks:ks_type":"HABITATION",
    "name:eng_x_preferred":[
        "Ramaguda"
    ],
    "wof:name":"Ramaguda",
    "wof:placetype":"locality",
    "wof:population":358
},
  "geometry": {"coordinates":[82.02282599999999,18.484508],"type":"Point"}
}