{
  "type": "Feature",
  "properties": {
    "gn:admin1_code":"36",
    "gn:admin2_code":"160.0",
    "gn:asciiname":"Mura",
    "gn:country_code":"IN",
    "gn:dem":138,
    "gn:feature_class":"P",
    "gn:feature_code":"PPL",
    "gn:name":"Mura",
    "gn:population":0,
    "gn:timezone":"Asia/Kolkata",
    "iso:country":"IN",
    "name:bel_x_preferred":[
        "\u041c\u0443\u0440\u0430"
    ],
    "name:bul_x_preferred":[
        "\u041c\u0443\u0440\u0430"
    ],
    "name:ceb_x_preferred":[
        "Mura"
    ],
    "name:ces_x_preferred":[
        "Mura"
    ],
    "name:deu_x_preferred":[
        "Mura"
    ],
    "name:est_x_preferred":[
        "Mura"
    ],
    "name:eus_x_preferred":[
        "Mura"
    ],
    "name:fra_x_preferred":[
        "Mura"
    ],
    "name:hun_x_preferred":[
        "Mura"
    ],
    "name:ita_x_preferred":[
        "Mura"
    ],
    "name:msa_x_preferred":[
        "Mura"
    ],
    "name:nld_x_preferred":[
        "Mura"
    ],
    "name:pol_x_preferred":[
        "Mura"
    ],
    "name:por_x_preferred":[
        "Mura"
    ],
    "name:rus_x_preferred":[
        "\u041c\u0443\u0440\u0430"
    ],
    "name:sco_x_preferred":[
        "Mura"
    ],
    "name:slk_x_preferred":[
        "Mura"
    ],
    "name:slv_x_preferred":[
        "Mura"
    ],
    "name:spa_x_preferred":[
        "Mura"
    ],
    "name:srp_x_preferred":[
        "Mura"
    ],
    "name:swe_x_preferred":[
        "Mura"
    ],
    "name:tgl_x_preferred":[
        "Mura"
    ],
    "name:ukr_x_preferred":[
        "\u041c\u0443\u0440\u0430"
    ],
    "name:vie_x_preferred":[
        "Mura"
    ],
    "name:war_x_preferred":[
        "Mura"
    ],
    "wof:name":"Mura",
    "wof:placetype":"locality"
},
  "geometry": {"coordinates":[79.72309,27.1786],"type":"Point"}
}