{
  "type": "Feature",
  "properties": {
    "iso:country":"IN",
    "ks:ks_name":"Gundumalai",
    "ks:ks_pop":612,
    "ks:ks_type":"HABITATION",
    "ks:ks_uagg_main":0,
    "name:eng_x_preferred":[
        "Gundumalai"
    ],
    "wof:name":"Gundumalai",
    "wof:placetype":"neighbourhood",
    "wof:population":612
},
  "geometry": {"coordinates":[77.186916,10.05457],"type":"Point"}
}