{
  "type": "Feature",
  "properties": {
    "gn:admin1_code":"11",
    "gn:admin2_code":"31.0",
    "gn:asciiname":"Ner",
    "gn:country_code":"IN",
    "gn:dem":1355,
    "gn:feature_class":"P",
    "gn:feature_code":"PPL",
    "gn:name":"Ner",
    "gn:population":0,
    "gn:timezone":"Asia/Kolkata",
    "iso:country":"IN",
    "name:cat_x_preferred":[
        "Ner"
    ],
    "name:ceb_x_preferred":[
        "Ner"
    ],
    "name:deu_x_preferred":[
        "Ner"
    ],
    "name:fin_x_preferred":[
        "Ner"
    ],
    "name:fra_x_preferred":[
        "Ner"
    ],
    "name:ita_x_preferred":[
        "Ner"
    ],
    "name:nno_x_preferred":[
        "Ner"
    ],
    "name:pol_x_preferred":[
        "Ner"
    ],
    "name:spa_x_preferred":[
        "Ner"
    ],
    "name:swe_x_preferred":[
        "Ner"
    ],
    "name:ukr_x_preferred":[
        "\u041d\u0435\u0440"
    ],
    "wof:name":"Ner",
    "wof:placetype":"locality"
},
  "geometry": {"coordinates":[76.94404,31.27297],"type":"Point"}
}