{
  "type": "Feature",
  "properties": {
    "iso:country":"IN",
    "ks:ks_name":"Madaiya Chamaran",
    "ks:ks_pop":133,
    "ks:ks_type":"HABITATION",
    "ks:ks_uagg_main":0,
    "name:eng_x_preferred":[
        "Madaiya Chamaran"
    ],
    "wof:name":"Madaiya Chamaran",
    "wof:placetype":"neighbourhood",
    "wof:population":133
},
  "geometry": {"coordinates":[79.561876,26.57001],"type":"Point"}
}