{
  "type": "Feature",
  "properties": {
    "iso:country":"IN",
    "ks:ks_name":"Satabahani",
    "ks:ks_pop":1033,
    "ks:ks_type":"VILLAGE",
    "name:eng_x_preferred":[
        "Satabahani"
    ],
    "wof:name":"Satabahani",
    "wof:placetype":"locality",
    "wof:population":1033
},
  "geometry": {"coordinates":[83.03155599999999,23.928692],"type":"Point"}
}