{
  "type": "Feature",
  "properties": {
    "iso:country":"IN",
    "ks:ks_alt_nam":"Kaul\u012b",
    "ks:ks_name":"Kauli",
    "ks:ks_type":"VILLAGE",
    "name:eng_x_preferred":[
        "Kauli"
    ],
    "name:eng_x_variant":[
        "Kaul\u012b"
    ],
    "wof:name":"Kauli",
    "wof:placetype":"locality"
},
  "geometry": {"coordinates":[80.194227,29.174121],"type":"Point"}
}