{
  "type": "Feature",
  "properties": {
    "gn:admin1_code":"34.0",
    "gn:admin2_code":"236.0",
    "gn:asciiname":"Jalpa",
    "gn:country_code":"IN",
    "gn:dem":138,
    "gn:feature_class":"P",
    "gn:feature_code":"PPL",
    "gn:name":"Jalpa",
    "gn:population":0,
    "gn:timezone":"Asia/Kolkata",
    "iso:country":"IN",
    "ks:ks_name":"Jalpa",
    "ks:ks_type":"VILLAGE",
    "ks:ks_uagg_main":0,
    "name:ceb_x_preferred":[
        "Jalpa"
    ],
    "name:deu_x_preferred":[
        "Jalpa"
    ],
    "name:eng_x_preferred":[
        "Jalpa"
    ],
    "name:rus_x_preferred":[
        "\u0425\u0430\u043b\u044c\u043f\u0430"
    ],
    "name:swe_x_preferred":[
        "Jalpa"
    ],
    "name:vie_x_preferred":[
        "Jalpa"
    ],
    "wof:name":"Jalpa",
    "wof:placetype":"neighbourhood"
},
  "geometry": {"coordinates":[84.71810600000001,24.636],"type":"Point"}
}