{
  "type": "Feature",
  "properties": {
    "gn:admin1_code":"12.0",
    "gn:admin2_code":"18.0",
    "gn:asciiname":"Marg",
    "gn:country_code":"IN",
    "gn:dem":3478,
    "gn:feature_class":"P",
    "gn:feature_code":"PPL",
    "gn:name":"Marg",
    "gn:population":0,
    "gn:timezone":"Asia/Kolkata",
    "iso:country":"IN",
    "name:deu_x_preferred":[
        "Marg"
    ],
    "name:fra_x_preferred":[
        "Marg"
    ],
    "name:nor_x_preferred":[
        "Marg"
    ],
    "wof:name":"Marg",
    "wof:placetype":"locality"
},
  "geometry": {"coordinates":[75.66918000000003,33.52793],"type":"Point"}
}