{
  "type": "Feature",
  "properties": {
    "iso:country":"IN",
    "ks:ks_name":"Leda",
    "ks:ks_pop":75,
    "ks:ks_type":"HABITATION",
    "name:eng_x_preferred":[
        "Leda"
    ],
    "wof:name":"Leda",
    "wof:placetype":"locality",
    "wof:population":75
},
  "geometry": {"coordinates":[83.960251,18.917006],"type":"Point"}
}