{
  "type": "Feature",
  "properties": {
    "iso:country":"IN",
    "ks:ks_name":"Butani Chuk",
    "ks:ks_pop":300,
    "ks:ks_type":"HABITATION",
    "ks:ks_uagg_main":0,
    "name:eng_x_preferred":[
        "Butani Chuk"
    ],
    "wof:name":"Butani Chuk",
    "wof:placetype":"neighbourhood",
    "wof:population":300
},
  "geometry": {"coordinates":[94.411227,26.690209],"type":"Point"}
}