{
  "type": "Feature",
  "properties": {
    "iso:country":"IN",
    "ks:ks_name":"Kottiyode",
    "ks:ks_pop":1298,
    "ks:ks_type":"HABITATION",
    "name:eng_x_preferred":[
        "Kottiyode"
    ],
    "wof:name":"Kottiyode",
    "wof:placetype":"locality",
    "wof:population":1298
},
  "geometry": {"coordinates":[76.516828,10.915469],"type":"Point"}
}