{
  "type": "Feature",
  "properties": {
    "iso:country":"IN",
    "ks:ks_name":"Dhana Kachhar",
    "ks:ks_pop":265,
    "ks:ks_type":"VILLAGE",
    "name:eng_x_preferred":[
        "Dhana Kachhar"
    ],
    "wof:name":"Dhana Kachhar",
    "wof:placetype":"locality",
    "wof:population":265
},
  "geometry": {"coordinates":[83.386769,22.451396],"type":"Point"}
}