{
  "type": "Feature",
  "properties": {
    "iso:country":"IN",
    "ks:ks_name":"Lahangpatti",
    "ks:ks_type":"VILLAGE",
    "name:eng_x_preferred":[
        "Lahangpatti"
    ],
    "wof:name":"Lahangpatti",
    "wof:placetype":"locality"
},
  "geometry": {"coordinates":[83.85386200000001,25.302543],"type":"Point"}
}