{
  "type": "Feature",
  "properties": {
    "iso:country":"IN",
    "ks:ks_alt_nam":"NAI BASTI",
    "ks:ks_name":"Nai Basti",
    "ks:ks_pop":244,
    "ks:ks_type":"HABITATION",
    "name:eng_x_preferred":[
        "Nai Basti"
    ],
    "wof:name":"Nai Basti",
    "wof:placetype":"locality",
    "wof:population":244
},
  "geometry": {"coordinates":[83.077842,25.050381],"type":"Point"}
}