{
  "type": "Feature",
  "properties": {
    "iso:country":"IN",
    "ks:ks_name":"Oler\t",
    "ks:ks_pop":392,
    "ks:ks_type":"VILLAGE",
    "name:eng_x_preferred":[
        "Oler\t"
    ],
    "wof:name":"Oler\t",
    "wof:placetype":"locality",
    "wof:population":392
},
  "geometry": {"coordinates":[81.952791,18.595004],"type":"Point"}
}