{
  "type": "Feature",
  "properties": {
    "iso:country":"IN",
    "ks:ks_name":"Kudrepadavu",
    "ks:ks_pop":502,
    "ks:ks_type":"HABITATION",
    "name:eng_x_preferred":[
        "Kudrepadavu"
    ],
    "wof:name":"Kudrepadavu",
    "wof:placetype":"locality",
    "wof:population":502
},
  "geometry": {"coordinates":[74.89224900000001,13.081744],"type":"Point"}
}