{
  "type": "Feature",
  "properties": {
    "iso:country":"IN",
    "ks:ks_name":"Kotethotta",
    "ks:ks_pop":106,
    "ks:ks_type":"HABITATION",
    "name:eng_x_preferred":[
        "Kotethotta"
    ],
    "wof:name":"Kotethotta",
    "wof:placetype":"locality",
    "wof:population":106
},
  "geometry": {"coordinates":[75.337577,13.34667],"type":"Point"}
}