{
  "type": "Feature",
  "properties": {
    "gn:admin1_code":"10.0",
    "gn:admin2_code":"81.0",
    "gn:asciiname":"Kasni Khurd",
    "gn:country_code":"IN",
    "gn:dem":243,
    "gn:feature_class":"P",
    "gn:feature_code":"PPL",
    "gn:name":"K\u0101sni Khurd",
    "gn:population":0,
    "gn:timezone":"Asia/Kolkata",
    "iso:country":"IN",
    "ks:ks_name":"Kasni Khurd",
    "ks:ks_pop":644,
    "ks:ks_type":"VILLAGE",
    "name:eng_x_preferred":[
        "Kasni Khurd"
    ],
    "wof:name":"Kasni Khurd",
    "wof:placetype":"locality",
    "wof:population":644
},
  "geometry": {"coordinates":[75.685109,28.656558],"type":"Point"}
}