{
  "type": "Feature",
  "properties": {
    "gn:admin1_code":"25.0",
    "gn:admin2_code":"633",
    "gn:asciiname":"Karattoluvu",
    "gn:country_code":"IN",
    "gn:dem":283,
    "gn:feature_class":"P",
    "gn:feature_code":"PPL",
    "gn:name":"K\u0101rattoluvu",
    "gn:population":0,
    "gn:timezone":"Asia/Kolkata",
    "iso:country":"IN",
    "name:und_x_variant":[
        "Karatholuvu",
        "K\u0101rattoluvu"
    ],
    "wof:name":"Karattoluvu",
    "wof:placetype":"locality"
},
  "geometry": {"coordinates":[77.37841999999998,10.62447],"type":"Point"}
}