{
  "type": "Feature",
  "properties": {
    "iso:country":"IN",
    "ks:ks_name":"Mohammadpur Faridpur",
    "ks:ks_pop":928,
    "ks:ks_type":"HABITATION",
    "name:eng_x_preferred":[
        "Mohammadpur Faridpur"
    ],
    "wof:name":"Mohammadpur Faridpur",
    "wof:placetype":"locality",
    "wof:population":928
},
  "geometry": {"coordinates":[82.919286,26.481482],"type":"Point"}
}