{
  "type": "Feature",
  "properties": {
    "gn:admin1_code":"24",
    "gn:admin2_code":"125.0",
    "gn:asciiname":"Surajkund",
    "gn:country_code":"IN",
    "gn:dem":360,
    "gn:feature_class":"P",
    "gn:feature_code":"PPL",
    "gn:name":"S\u016brajkund",
    "gn:population":0,
    "gn:timezone":"Asia/Kolkata",
    "iso:country":"IN",
    "name:hin_x_preferred":[
        "\u0938\u0942\u0930\u091c\u0915\u0941\u0923\u094d\u0921"
    ],
    "name:mai_x_preferred":[
        "\u0938\u0942\u0930\u091c\u0915\u0941\u0923\u094d\u0921"
    ],
    "name:pan_x_preferred":[
        "\u0a38\u0a42\u0a30\u0a1c\u0a15\u0a41\u0a70\u0a21"
    ],
    "wof:name":"Surajkund",
    "wof:placetype":"locality"
},
  "geometry": {"coordinates":[74.47131,23.24764],"type":"Point"}
}