{
  "type": "Feature",
  "properties": {
    "gn:admin1_code":"36",
    "gn:admin2_code":"154.0",
    "gn:asciiname":"Sirsa",
    "gn:country_code":"IN",
    "gn:dem":122,
    "gn:feature_class":"P",
    "gn:feature_code":"PPL",
    "gn:name":"Sirsa",
    "gn:population":0,
    "gn:timezone":"Asia/Kolkata",
    "iso:country":"IN",
    "name:ara_x_preferred":[
        "\u0633\u0631\u0633\u0627"
    ],
    "name:ben_bn_x_preferred":[
        "\u09b8\u09bf\u09b0\u09b8\u09be"
    ],
    "name:ben_in_x_preferred":[
        "\u09b8\u09bf\u09b0\u09b8\u09be"
    ],
    "name:bih_x_preferred":[
        "\u0938\u093f\u0930\u0938\u093e"
    ],
    "name:cat_x_preferred":[
        "Sirsa"
    ],
    "name:ceb_x_preferred":[
        "Sirsa"
    ],
    "name:deu_x_preferred":[
        "Sirsa"
    ],
    "name:fas_x_preferred":[
        "\u0633\u06cc\u0631\u0633\u0627"
    ],
    "name:fra_x_preferred":[
        "Sirsa"
    ],
    "name:guj_x_preferred":[
        "\u0ab8\u0abf\u0ab0\u0ab8\u0abe"
    ],
    "name:hin_x_preferred":[
        "\u0938\u093f\u0930\u0938\u093e"
    ],
    "name:ita_x_preferred":[
        "Sirsa"
    ],
    "name:kan_x_preferred":[
        "\u0cb8\u0cbf\u0cb0\u0ccd\u0cb8\u0cbe"
    ],
    "name:mal_x_preferred":[
        "\u0d38\u0d3f\u0d7c\u0d38"
    ],
    "name:mar_x_preferred":[
        "\u0938\u093f\u0930\u0938\u093e"
    ],
    "name:msa_x_preferred":[
        "Sirsa"
    ],
    "name:nor_x_preferred":[
        "Sirsa"
    ],
    "name:ori_x_preferred":[
        "\u0b38\u0b3f\u0b30\u0b4d\u0b38\u0b3e"
    ],
    "name:pan_x_preferred":[
        "\u0a38\u0a3f\u0a30\u0a38\u0a3e"
    ],
    "name:pnb_x_preferred":[
        "\u0636\u0644\u0639 \u0633\u0631\u0633\u06c1"
    ],
    "name:pol_x_preferred":[
        "Sirsa"
    ],
    "name:rus_x_preferred":[
        "\u0421\u0438\u0440\u0441\u0430"
    ],
    "name:san_x_preferred":[
        "\u0938\u093f\u0930\u0938\u093e,\u0939\u0930\u093f\u092f\u093e\u0923\u093e"
    ],
    "name:spa_x_preferred":[
        "Sirsa"
    ],
    "name:swe_x_preferred":[
        "Sirsa"
    ],
    "name:tam_x_preferred":[
        "\u0b9a\u0bbf\u0bb0\u0bcd\u0b9a\u0bbe"
    ],
    "name:tel_x_preferred":[
        "\u0c38\u0c3f\u0c30\u0c4d\u0c38\u0c3e"
    ],
    "name:urd_x_preferred":[
        "\u0633\u0631\u0633\u0627"
    ],
    "name:vie_x_preferred":[
        "Sirsa"
    ],
    "name:war_x_preferred":[
        "Sirsa"
    ],
    "name:zho_x_preferred":[
        "\u897f\u5c14\u8428"
    ],
    "wof:name":"Sirsa",
    "wof:placetype":"locality"
},
  "geometry": {"coordinates":[81.24061999999998,27.63111],"type":"Point"}
}