{
  "type": "Feature",
  "properties": {
    "iso:country":"IN",
    "ks:ks_name":"Kundol",
    "ks:ks_pop":0,
    "ks:ks_type":"VILLAGE",
    "name:eng_x_preferred":[
        "Kundol"
    ],
    "wof:name":"Kundol",
    "wof:placetype":"locality",
    "wof:population":0
},
  "geometry": {"coordinates":[72.88622599999999,23.547575],"type":"Point"}
}