{
  "type": "Feature",
  "properties": {
    "iso:country":"IN",
    "ks:ks_name":"Kalipara",
    "ks:ks_pop":550,
    "ks:ks_type":"HABITATION",
    "name:eng_x_preferred":[
        "Kalipara"
    ],
    "wof:name":"Kalipara",
    "wof:placetype":"locality",
    "wof:population":550
},
  "geometry": {"coordinates":[81.891353,19.853336],"type":"Point"}
}