{
  "type": "Feature",
  "properties": {
    "iso:country":"IN",
    "ks:ks_alt_nam":"PuraniBasti",
    "ks:ks_name":"Puranibasti",
    "ks:ks_pop":289,
    "ks:ks_type":"HABITATION",
    "name:eng_x_preferred":[
        "Puranibasti"
    ],
    "wof:name":"Puranibasti",
    "wof:placetype":"locality",
    "wof:population":289
},
  "geometry": {"coordinates":[81.678792,20.583093],"type":"Point"}
}