{
  "type": "Feature",
  "properties": {
    "gn:admin1_code":"11.0",
    "gn:admin2_code":"27.0",
    "gn:asciiname":"Kandi",
    "gn:country_code":"IN",
    "gn:dem":1749,
    "gn:feature_class":"P",
    "gn:feature_code":"PPL",
    "gn:name":"K\u0101ndi",
    "gn:population":0,
    "gn:timezone":"Asia/Kolkata",
    "iso:country":"IN",
    "name:ben_x_preferred":[
        "\u0995\u09be\u09a8\u09cd\u09a6\u09bf"
    ],
    "name:ceb_x_preferred":[
        "Kandi"
    ],
    "name:deu_x_preferred":[
        "Kandi"
    ],
    "name:fin_x_preferred":[
        "Kandi"
    ],
    "name:fra_x_preferred":[
        "Kandi"
    ],
    "name:heb_x_preferred":[
        "\u05e7\u05e0\u05d3\u05d9"
    ],
    "name:hin_x_preferred":[
        "\u0915\u0902\u0921\u0940"
    ],
    "name:hin_x_variant":[
        "\u0915\u093e\u0902\u0921\u0940"
    ],
    "name:hun_x_preferred":[
        "Kandi"
    ],
    "name:swe_x_preferred":[
        "Kandi"
    ],
    "name:tur_x_preferred":[
        "Kandi"
    ],
    "wof:name":"Kandi",
    "wof:placetype":"locality"
},
  "geometry": {"coordinates":[77.0813,31.51092],"type":"Point"}
}