{
  "type": "Feature",
  "properties": {
    "gn:admin1_code":"11.0",
    "gn:admin2_code":"27.0",
    "gn:asciiname":"Kandi",
    "gn:country_code":"IN",
    "gn:dem":1749,
    "gn:feature_class":"P",
    "gn:feature_code":"PPL",
    "gn:name":"K\u0101ndi",
    "gn:population":0,
    "gn:timezone":"Asia/Kolkata",
    "iso:country":"IN",
    "name:ceb_x_preferred":[
        "Kandi"
    ],
    "name:deu_x_preferred":[
        "Kandi"
    ],
    "name:fin_x_preferred":[
        "Kandi"
    ],
    "name:fra_x_preferred":[
        "Kandi"
    ],
    "name:hun_x_preferred":[
        "Kandi"
    ],
    "name:swe_x_preferred":[
        "Kandi"
    ],
    "wof:name":"Kandi",
    "wof:placetype":"locality"
},
  "geometry": {"coordinates":[77.0813,31.51092],"type":"Point"}
}