{
  "type": "Feature",
  "properties": {
    "gn:admin1_code":"11",
    "gn:admin2_code":"23.0",
    "gn:asciiname":"Kaliana",
    "gn:country_code":"IN",
    "gn:dem":964,
    "gn:feature_class":"P",
    "gn:feature_code":"PPL",
    "gn:name":"Kali\u0101na",
    "gn:population":0,
    "gn:timezone":"Asia/Kolkata",
    "iso:country":"IN",
    "name:ceb_x_preferred":[
        "Kali\u00e1na"
    ],
    "name:ell_x_preferred":[
        "\u039a\u03b1\u03bb\u03b9\u03ac\u03bd\u03b1"
    ],
    "name:pol_x_preferred":[
        "Kaliana"
    ],
    "name:swe_x_preferred":[
        "Kali\u00e1na"
    ],
    "name:urd_x_preferred":[
        "\u06a9\u0627\u0644\u06cc\u0627\u0646\u0627"
    ],
    "wof:name":"Kaliana",
    "wof:placetype":"locality"
},
  "geometry": {"coordinates":[76.08346999999998,32.33029000000001],"type":"Point"}
}