{
  "type": "Feature",
  "properties": {
    "gn:admin1_code":"21",
    "gn:admin2_code":"391.0",
    "gn:asciiname":"Manamunda",
    "gn:cc2":"IN",
    "gn:country_code":"IN",
    "gn:dem":114,
    "gn:feature_class":"P",
    "gn:feature_code":"PPL",
    "gn:name":"Manamunda",
    "gn:population":0,
    "gn:timezone":"Asia/Kolkata",
    "iso:country":"IN",
    "name:und_x_variant":[
        "Manomonda",
        "Manamunda"
    ],
    "wof:name":"Manamunda",
    "wof:placetype":"locality"
},
  "geometry": {"coordinates":[83.91667,20.81667],"type":"Point"}
}