{
  "type": "Feature",
  "properties": {
    "iso:country":"IN",
    "ks:ks_name":"Kashitanr",
    "ks:ks_pop":504,
    "ks:ks_type":"VILLAGE",
    "name:eng_x_preferred":[
        "Kashitanr"
    ],
    "wof:name":"Kashitanr",
    "wof:placetype":"locality",
    "wof:population":504
},
  "geometry": {"coordinates":[86.51849199999999,23.948648],"type":"Point"}
}