{
  "type": "Feature",
  "properties": {
    "iso:country":"IN",
    "ks:ks_name":"Eguvakiridivalasa",
    "ks:ks_pop":4,
    "ks:ks_type":"HABITATION",
    "name:eng_x_preferred":[
        "Eguvakiridivalasa"
    ],
    "wof:name":"Eguvakiridivalasa",
    "wof:placetype":"locality",
    "wof:population":4
},
  "geometry": {"coordinates":[83.88606,18.661486],"type":"Point"}
}