{
  "type": "Feature",
  "properties": {
    "iso:country":"IN",
    "ks:ks_name":"Molalgutta",
    "ks:ks_pop":103,
    "ks:ks_type":"HABITATION",
    "name:eng_x_preferred":[
        "Molalgutta"
    ],
    "wof:name":"Molalgutta",
    "wof:placetype":"locality",
    "wof:population":103
},
  "geometry": {"coordinates":[78.67463499999999,19.587451],"type":"Point"}
}