{
  "type": "Feature",
  "properties": {
    "iso:country":"IN",
    "qs:name":"Law College",
    "qs:name_adm0":"India",
    "qs:name_adm1":"Maharashtra",
    "qs:photos":33,
    "qs:photos_1k":7,
    "qs:photos_9k":1,
    "qs:photos_9r":2,
    "qs:photos_all":33,
    "qs:photos_sr":2,
    "qs:placetype":"Suburb",
    "qs:pop_sr":"0",
    "wof:name":"Law College",
    "wof:placetype":"neighbourhood"
},
  "geometry": {"coordinates":[73.826322,18.511478],"type":"Point"}
}