{
  "type": "Feature",
  "properties": {
    "gn:admin1_code":"19.0",
    "gn:admin2_code":"575.0",
    "gn:asciiname":"Ichlampadi",
    "gn:country_code":"IN",
    "gn:dem":108,
    "gn:feature_class":"P",
    "gn:feature_code":"PPLL",
    "gn:name":"Ichlamp\u0101di",
    "gn:population":0,
    "gn:timezone":"Asia/Kolkata",
    "iso:country":"IN",
    "wof:name":"Ichlampadi",
    "wof:placetype":"locality"
},
  "geometry": {"coordinates":[75.45376,12.80376],"type":"Point"}
}