{
  "type": "Feature",
  "properties": {
    "iso:country":"IN",
    "ks:ks_alt_nam":"Ettukuttai kadu",
    "ks:ks_name":"Ettukuttai Kadu",
    "ks:ks_pop":250,
    "ks:ks_type":"HABITATION",
    "name:eng_x_preferred":[
        "Ettukuttai Kadu"
    ],
    "wof:name":"Ettukuttai Kadu",
    "wof:placetype":"locality",
    "wof:population":250
},
  "geometry": {"coordinates":[77.76423200000001,11.574142],"type":"Point"}
}