{
  "type": "Feature",
  "properties": {
    "gn:admin1_code":"36",
    "gn:admin2_code":"197.0",
    "gn:asciiname":"Chhitauni",
    "gn:country_code":"IN",
    "gn:dem":83,
    "gn:feature_class":"P",
    "gn:feature_code":"PPL",
    "gn:name":"Chhitauni",
    "gn:population":0,
    "gn:timezone":"Asia/Kolkata",
    "iso:country":"IN",
    "ks:ks_name":"Chhitauni",
    "ks:ks_pop":1422,
    "ks:ks_type":"VILLAGE",
    "wof:name":"Chhitauni",
    "wof:placetype":"neighbourhood"
},
  "geometry": {"coordinates":[82.94192,25.22311],"type":"Point"}
}