{
  "type": "Feature",
  "properties": {
    "gn:admin1_code":"10.0",
    "gn:admin2_code":"79.0",
    "gn:asciiname":"Gushaiyana",
    "gn:country_code":"IN",
    "gn:dem":201,
    "gn:feature_class":"P",
    "gn:feature_code":"PPL",
    "gn:name":"Gushaiy\u0101na",
    "gn:population":0,
    "gn:timezone":"Asia/Kolkata",
    "iso:country":"IN",
    "wof:name":"Gushaiyana",
    "wof:placetype":"locality"
},
  "geometry": {"coordinates":[75.08686,29.25151],"type":"Point"}
}