{
  "type": "Feature",
  "properties": {
    "gn:admin1_code":"39.0",
    "gn:admin2_code":"64.0",
    "gn:asciiname":"Pinkot",
    "gn:country_code":"IN",
    "gn:dem":752,
    "gn:feature_class":"P",
    "gn:feature_code":"PPL",
    "gn:name":"Pinkot",
    "gn:population":0,
    "gn:timezone":"Asia/Kolkata",
    "iso:country":"IN",
    "ks:ks_name":"Pina Kot",
    "ks:ks_pop":585,
    "ks:ks_type":"VILLAGE",
    "name:eng_x_preferred":[
        "Pina Kot"
    ],
    "name:eng_x_variant":[
        "Pinkot"
    ],
    "wof:name":"Pina Kot",
    "wof:placetype":"locality",
    "wof:population":585
},
  "geometry": {"coordinates":[79.170858,29.610158],"type":"Point"}
}