{
  "type": "Feature",
  "properties": {
    "gn:admin1_code":"21.0",
    "gn:admin2_code":"398.0",
    "gn:asciiname":"Pentapadu",
    "gn:country_code":"IN",
    "gn:dem":870,
    "gn:feature_class":"P",
    "gn:feature_code":"PPL",
    "gn:name":"Pentapadu",
    "gn:population":0,
    "gn:timezone":"Asia/Kolkata",
    "iso:country":"IN",
    "name:new_x_preferred":[
        "\u092a\u0947\u0902\u091f\u092a\u093e\u0921\u0941 \u092e\u0923\u094d\u0921\u0932"
    ],
    "name:tam_x_preferred":[
        "\u0baa\u0bc6\u0ba3\u0bcd\u0b9f\u0baa\u0bbe\u0b9f\u0bc1"
    ],
    "name:tel_x_preferred":[
        "\u0c2a\u0c46\u0c02\u0c1f\u0c2a\u0c3e\u0c21\u0c41"
    ],
    "name:urd_x_preferred":[
        "\u067e\u06cc\u0646\u0679\u0627\u067e\u0627\u0691\u0648"
    ],
    "wof:name":"Pentapadu",
    "wof:placetype":"locality"
},
  "geometry": {"coordinates":[82.56004,18.61805],"type":"Point"}
}