{
  "type": "Feature",
  "properties": {
    "gn:admin1_code":"24.0",
    "gn:admin2_code":"107",
    "gn:asciiname":"Bhankri",
    "gn:country_code":"IN",
    "gn:dem":331,
    "gn:feature_class":"P",
    "gn:feature_code":"PPL",
    "gn:name":"Bh\u0101nkri",
    "gn:population":0,
    "gn:timezone":"Asia/Kolkata",
    "iso:country":"IN",
    "name:und_x_variant":[
        "Bh\u0101nkri",
        "Bh\u0101nkr\u012b"
    ],
    "wof:name":"Bhankri",
    "wof:placetype":"locality"
},
  "geometry": {"coordinates":[77.14819,26.45308],"type":"Point"}
}