{
  "type": "Feature",
  "properties": {
    "iso:country":"IN",
    "ks:ks_name":"Alampatti",
    "ks:ks_pop":230,
    "ks:ks_type":"HABITATION",
    "name:eng_x_preferred":[
        "Alampatti"
    ],
    "wof:name":"Alampatti",
    "wof:placetype":"locality",
    "wof:population":230
},
  "geometry": {"coordinates":[78.938903,10.186617],"type":"Point"}
}