{
  "type": "Feature",
  "properties": {
    "gn:admin1_code":"2",
    "gn:admin2_code":"545.0",
    "gn:asciiname":"Sitaram",
    "gn:country_code":"IN",
    "gn:dem":41,
    "gn:feature_class":"P",
    "gn:feature_code":"PPL",
    "gn:name":"S\u012bt\u0101ram",
    "gn:population":0,
    "gn:timezone":"Asia/Kolkata",
    "iso:country":"IN",
    "name:tel_x_preferred":[
        "\u0c38\u0c40\u0c24\u0c3e\u0c30\u0c3e\u0c02"
    ],
    "wof:name":"Sitaram",
    "wof:placetype":"locality"
},
  "geometry": {"coordinates":[81.70048,17.33521],"type":"Point"}
}