{
  "type": "Feature",
  "properties": {
    "gn:country":"IN",
    "gn:fcode":"PPL",
    "gn:population":6705,
    "iso:country":"IN",
    "name:bpy_x_preferred":[
        "\u09b6\u09bf\u09ac\u09b0\u09be\u099c\u09aa\u09c1\u09b0"
    ],
    "name:ita_x_preferred":[
        "Shivrajpur"
    ],
    "name:msa_x_preferred":[
        "Shivrajpur"
    ],
    "name:nld_x_preferred":[
        "Shivrajpur"
    ],
    "name:pol_x_preferred":[
        "Shivrajpur"
    ],
    "name:por_x_preferred":[
        "Shivrajpur"
    ],
    "name:urd_x_preferred":[
        "\u0634\u06cc\u0648\u0631\u0627\u062c \u067e\u0648\u0631"
    ],
    "name:vie_x_preferred":[
        "Shivrajpur"
    ],
    "name:zho_x_preferred":[
        "\u65af\u5e0c\u6c83\u62c9\u6770\u666e\u5c14"
    ],
    "qs:name":"Shivrajpur",
    "qs:name_adm0":"India",
    "qs:name_adm1":"Gujarat",
    "qs:photos_9r":0,
    "qs:photos_sr":0,
    "qs:placetype":"Town",
    "qs:pop_sr":"5",
    "wd:wordcount":211,
    "wof:name":"Shivrajpur",
    "wof:placetype":"locality",
    "wof:population":6705
},
  "geometry": {"coordinates":[73.60865,22.42319],"type":"Point"}
}