{
  "type": "Feature",
  "properties": {
    "gn:country":"IN",
    "gn:fcode":"PPL",
    "gn:pop":6705,
    "iso:country":"IN",
    "qs:name":"Shivrajpur",
    "qs:name_adm0":"India",
    "qs:name_adm1":"Gujarat",
    "qs:photos_9r":0,
    "qs:photos_sr":0,
    "qs:placetype":"Town",
    "qs:pop_sr":"5",
    "wd:wordcount":211,
    "wof:name":"Shivrajpur",
    "wof:placetype":"locality",
    "wof:population":6705
},
  "geometry": {"coordinates":[73.60865,22.42319],"type":"Point"}
}