{
  "type": "Feature",
  "properties": {
    "iso:country":"IN",
    "ks:ks_name":"Tharechavas",
    "ks:ks_pop":210,
    "ks:ks_type":"HABITATION",
    "name:eng_x_preferred":[
        "Tharechavas"
    ],
    "wof:name":"Tharechavas",
    "wof:placetype":"locality",
    "wof:population":210
},
  "geometry": {"coordinates":[71.964083,24.055179],"type":"Point"}
}