{
  "type": "Feature",
  "properties": {
    "iso:country":"IN",
    "ks:ks_name":"Chandoswadi",
    "ks:ks_pop":220,
    "ks:ks_type":"HABITATION",
    "name:eng_x_preferred":[
        "Chandoswadi"
    ],
    "wof:name":"Chandoswadi",
    "wof:placetype":"locality",
    "wof:population":220
},
  "geometry": {"coordinates":[73.634305,15.998683],"type":"Point"}
}