{
  "type": "Feature",
  "properties": {
    "gn:admin1_code":"19.0",
    "gn:admin2_code":"583.0",
    "gn:asciiname":"Devarahoshalli",
    "gn:country_code":"IN",
    "gn:dem":877,
    "gn:feature_class":"P",
    "gn:feature_code":"PPL",
    "gn:name":"Devar\u0101hoshalli",
    "gn:population":0,
    "gn:timezone":"Asia/Kolkata",
    "iso:country":"IN",
    "wof:name":"Devarahoshalli",
    "wof:placetype":"locality"
},
  "geometry": {"coordinates":[77.19266999999998,13.26199],"type":"Point"}
}