{
  "type": "Feature",
  "properties": {
    "iso:country":"IN",
    "ks:ks_name":"Aam Karia",
    "ks:ks_pop":126,
    "ks:ks_type":"VILLAGE",
    "name:eng_x_preferred":[
        "Aam Karia"
    ],
    "wof:name":"Aam Karia",
    "wof:placetype":"locality",
    "wof:population":126
},
  "geometry": {"coordinates":[80.015694,29.290929],"type":"Point"}
}