{
  "type": "Feature",
  "properties": {
    "iso:country":"IN",
    "ks:ks_name":"Bukanagundi",
    "ks:ks_pop":249,
    "ks:ks_type":"HABITATION",
    "name:eng_x_preferred":[
        "Bukanagundi"
    ],
    "wof:name":"Bukanagundi",
    "wof:placetype":"locality",
    "wof:population":249
},
  "geometry": {"coordinates":[76.161007,13.602323],"type":"Point"}
}