{
  "type": "Feature",
  "properties": {
    "iso:country":"IN",
    "ks:ks_name":"Dayakhol",
    "ks:ks_pop":68,
    "ks:ks_type":"VILLAGE",
    "name:eng_x_preferred":[
        "Dayakhol"
    ],
    "wof:name":"Dayakhol",
    "wof:placetype":"locality",
    "wof:population":68
},
  "geometry": {"coordinates":[84.688278,21.603713],"type":"Point"}
}