{
  "type": "Feature",
  "properties": {
    "iso:country":"IN",
    "ks:ks_name":"Purwa Jhabra",
    "ks:ks_type":"VILLAGE",
    "name:eng_x_preferred":[
        "Purwa Jhabra"
    ],
    "wof:name":"Purwa Jhabra",
    "wof:placetype":"locality"
},
  "geometry": {"coordinates":[79.479851,26.74634],"type":"Point"}
}