{
  "type": "Feature",
  "properties": {
    "iso:country":"IN",
    "ks:ks_name":"Mulajjamu",
    "ks:ks_pop":232,
    "ks:ks_type":"HABITATION",
    "name:eng_x_preferred":[
        "Mulajjamu"
    ],
    "wof:name":"Mulajjamu",
    "wof:placetype":"locality",
    "wof:population":232
},
  "geometry": {"coordinates":[83.601921,19.021155],"type":"Point"}
}