{
  "type": "Feature",
  "properties": {
    "iso:country":"IN",
    "ks:ks_name":"Ayanachegalu",
    "ks:ks_pop":64,
    "ks:ks_type":"HABITATION",
    "name:eng_x_preferred":[
        "Ayanachegalu"
    ],
    "wof:name":"Ayanachegalu",
    "wof:placetype":"locality",
    "wof:population":64
},
  "geometry": {"coordinates":[73.856627,15.945775],"type":"Point"}
}