{
  "type": "Feature",
  "properties": {
    "iso:country":"IN",
    "ks:ks_name":"Nagla Mahmood",
    "ks:ks_pop":48,
    "ks:ks_type":"VILLAGE",
    "ks:ks_uagg_main":0,
    "name:eng_x_preferred":[
        "Nagla Mahmood"
    ],
    "wof:name":"Nagla Mahmood",
    "wof:placetype":"neighbourhood",
    "wof:population":48
},
  "geometry": {"coordinates":[77.29570699999999,29.876529],"type":"Point"}
}