{
  "type": "Feature",
  "properties": {
    "iso:country":"IN",
    "ks:ks_name":"Signal Basti",
    "ks:ks_pop":702,
    "ks:ks_type":"HABITATION",
    "ks:ks_uagg_main":0,
    "name:eng_x_preferred":[
        "Signal Basti"
    ],
    "wof:name":"Signal Basti",
    "wof:placetype":"neighbourhood",
    "wof:population":702
},
  "geometry": {"coordinates":[94.757887,27.071862],"type":"Point"}
}