{
  "type": "Feature",
  "properties": {
    "gn:admin1_code":"34.0",
    "gn:admin2_code":"203.0",
    "gn:asciiname":"Gajna",
    "gn:country_code":"IN",
    "gn:dem":80,
    "gn:feature_class":"P",
    "gn:feature_code":"PPL",
    "gn:name":"Gajna",
    "gn:population":0,
    "gn:timezone":"Asia/Kolkata",
    "iso:country":"IN",
    "name:hif_x_preferred":[
        "Gajna"
    ],
    "wof:name":"Gajna",
    "wof:placetype":"neighbourhood"
},
  "geometry": {"coordinates":[84.31838999999999,26.85416],"type":"Point"}
}