{
  "type": "Feature",
  "properties": {
    "gn:admin1_code":"13.0",
    "gn:admin2_code":"588.0",
    "gn:asciiname":"Bandadka",
    "gn:country_code":"IN",
    "gn:dem":173,
    "gn:feature_class":"P",
    "gn:feature_code":"PPLL",
    "gn:name":"Bandadka",
    "gn:population":0,
    "gn:timezone":"Asia/Kolkata",
    "iso:country":"IN",
    "name:mal_x_preferred":[
        "\u0d2c\u0d28\u0d4d\u0d24\u0d1f\u0d41\u0d15\u0d4d\u0d15"
    ],
    "wof:name":"Bandadka",
    "wof:placetype":"locality"
},
  "geometry": {"coordinates":[75.27285999999999,12.48372],"type":"Point"}
}