{
  "type": "Feature",
  "properties": {
    "iso:country":"IN",
    "ks:ks_name":"Boudhwadi",
    "ks:ks_pop":49,
    "ks:ks_type":"HABITATION",
    "name:eng_x_preferred":[
        "Boudhwadi"
    ],
    "wof:name":"Boudhwadi",
    "wof:placetype":"locality",
    "wof:population":49
},
  "geometry": {"coordinates":[73.86353699999999,16.172137],"type":"Point"}
}