{
  "type": "Feature",
  "properties": {
    "iso:country":"IN",
    "ks:ks_name":"Ghisingbeda",
    "ks:ks_pop":375,
    "ks:ks_type":"HABITATION",
    "name:eng_x_preferred":[
        "Ghisingbeda"
    ],
    "wof:name":"Ghisingbeda",
    "wof:placetype":"locality",
    "wof:population":375
},
  "geometry": {"coordinates":[81.941693,17.996916],"type":"Point"}
}