{
  "type": "Feature",
  "properties": {
    "iso:country":"IN",
    "ks:ks_name":"Konagundi",
    "ks:ks_pop":17,
    "ks:ks_type":"HABITATION",
    "name:eng_x_preferred":[
        "Konagundi"
    ],
    "wof:name":"Konagundi",
    "wof:placetype":"locality",
    "wof:population":17
},
  "geometry": {"coordinates":[75.489788,12.505608],"type":"Point"}
}