{
  "type": "Feature",
  "properties": {
    "iso:country":"IN",
    "ks:ks_alt_nam":"Ky\u0101tanahalli",
    "ks:ks_name":"Kyatanahalli",
    "ks:ks_type":"VILLAGE",
    "name:eng_x_preferred":[
        "Kyatanahalli"
    ],
    "name:eng_x_variant":[
        "Ky\u0101tanahalli"
    ],
    "wof:name":"Kyatanahalli",
    "wof:placetype":"locality"
},
  "geometry": {"coordinates":[76.056489,12.849785],"type":"Point"}
}