{
  "type": "Feature",
  "properties": {
    "gn:admin1_code":"36",
    "gn:admin2_code":"200.0",
    "gn:asciiname":"Nisogi",
    "gn:country_code":"IN",
    "gn:dem":324,
    "gn:feature_class":"P",
    "gn:feature_code":"PPL",
    "gn:name":"Nisogi",
    "gn:population":0,
    "gn:timezone":"Asia/Kolkata",
    "iso:country":"IN",
    "ks:ks_name":"Nisogi",
    "ks:ks_type":"VILLAGE",
    "name:eng_x_preferred":[
        "Nisogi"
    ],
    "wof:name":"Nisogi",
    "wof:placetype":"locality"
},
  "geometry": {"coordinates":[83.142853,24.616748],"type":"Point"}
}