{
  "type": "Feature",
  "properties": {
    "iso:country":"IN",
    "ks:ks_name":"Naya Thotha Para",
    "ks:ks_pop":33,
    "ks:ks_type":"HABITATION",
    "name:eng_x_preferred":[
        "Naya Thotha Para"
    ],
    "wof:name":"Naya Thotha Para",
    "wof:placetype":"locality",
    "wof:population":33
},
  "geometry": {"coordinates":[82.12735600000001,19.169458],"type":"Point"}
}