{
  "type": "Feature",
  "properties": {
    "gn:admin1_code":"25.0",
    "gn:admin2_code":"619.0",
    "gn:asciiname":"Kattimodu",
    "gn:country_code":"IN",
    "gn:dem":6,
    "gn:feature_class":"P",
    "gn:feature_code":"PPL",
    "gn:name":"Kattimodu",
    "gn:population":0,
    "gn:timezone":"Asia/Kolkata",
    "iso:country":"IN",
    "ks:ks_name":"Kattimedu",
    "ks:ks_pop":2458,
    "ks:ks_type":"VILLAGE",
    "ks:ks_uagg_main":0,
    "name:eng_x_preferred":[
        "Kattimedu"
    ],
    "wof:name":"Kattimedu",
    "wof:placetype":"neighbourhood",
    "wof:population":2458
},
  "geometry": {"coordinates":[79.66221899999999,10.498945],"type":"Point"}
}