{
  "type": "Feature",
  "properties": {
    "iso:country":"IN",
    "ks:ks_name":"Bara Purwa",
    "ks:ks_pop":1370,
    "ks:ks_type":"HABITATION",
    "name:eng_x_preferred":[
        "Bara Purwa"
    ],
    "wof:name":"Bara Purwa",
    "wof:placetype":"locality",
    "wof:population":1370
},
  "geometry": {"coordinates":[82.99818399999999,27.088683],"type":"Point"}
}