{
  "type": "Feature",
  "properties": {
    "iso:country":"IN",
    "ks:ks_name":"Limbarpada Falia",
    "ks:ks_pop":580,
    "ks:ks_type":"HABITATION",
    "name:eng_x_preferred":[
        "Limbarpada Falia"
    ],
    "wof:name":"Limbarpada Falia",
    "wof:placetype":"locality",
    "wof:population":580
},
  "geometry": {"coordinates":[73.43825,20.720472],"type":"Point"}
}