{
  "type": "Feature",
  "properties": {
    "gn:admin1_code":"36",
    "gn:admin2_code":"164.0",
    "gn:asciiname":"Purwa Bamba",
    "gn:country_code":"IN",
    "gn:dem":139,
    "gn:feature_class":"P",
    "gn:feature_code":"PPL",
    "gn:name":"Purwa Bamba",
    "gn:population":0,
    "gn:timezone":"Asia/Kolkata",
    "iso:country":"IN",
    "wof:name":"Purwa Bamba",
    "wof:placetype":"neighbourhood"
},
  "geometry": {"coordinates":[79.96847,26.88711],"type":"Point"}
}