{
  "type": "Feature",
  "properties": {
    "gn:admin1_code":"39.0",
    "gn:admin2_code":"67.0",
    "gn:asciiname":"Bhawani",
    "gn:country_code":"IN",
    "gn:dem":204,
    "gn:feature_class":"P",
    "gn:feature_code":"PPL",
    "gn:name":"Bhaw\u0101ni",
    "gn:population":0,
    "gn:timezone":"Asia/Kolkata",
    "iso:country":"IN",
    "name:ceb_x_preferred":[
        "Bhawani"
    ],
    "name:mai_x_preferred":[
        "\u092d\u0935\u093e\u0928\u093f"
    ],
    "name:msa_x_preferred":[
        "Bhawani"
    ],
    "name:nep_x_preferred":[
        "\u092d\u0935\u093e\u0928\u093f"
    ],
    "name:new_x_preferred":[
        "\u092d\u0935\u093e\u0928\u0940 \u0917\u093e\u0935\u093f\u0938"
    ],
    "name:pol_x_preferred":[
        "Bhawani"
    ],
    "wof:name":"Bhawani",
    "wof:placetype":"locality"
},
  "geometry": {"coordinates":[79.4507,28.91521],"type":"Point"}
}