{
  "type": "Feature",
  "properties": {
    "gn:admin1_code":"39.0",
    "gn:admin2_code":"67.0",
    "gn:asciiname":"Bhawani",
    "gn:country_code":"IN",
    "gn:dem":204,
    "gn:feature_class":"P",
    "gn:feature_code":"PPL",
    "gn:name":"Bhaw\u0101ni",
    "gn:population":0,
    "gn:timezone":"Asia/Kolkata",
    "iso:country":"IN",
    "wof:name":"Bhawani",
    "wof:placetype":"locality"
},
  "geometry": {"coordinates":[79.4507,28.91521],"type":"Point"}
}