{
  "type": "Feature",
  "properties": {
    "iso:country":"IN",
    "ks:ks_name":"Kurrichuan",
    "ks:ks_pop":106,
    "ks:ks_type":"HABITATION",
    "name:eng_x_preferred":[
        "Kurrichuan"
    ],
    "wof:name":"Kurrichuan",
    "wof:placetype":"locality",
    "wof:population":106
},
  "geometry": {"coordinates":[82.94265900000001,21.044383],"type":"Point"}
}