{
  "type": "Feature",
  "properties": {
    "iso:country":"IN",
    "ks:ks_name":"Kadappa",
    "ks:ks_pop":37,
    "ks:ks_type":"HABITATION",
    "name:eng_x_preferred":[
        "Kadappa"
    ],
    "wof:name":"Kadappa",
    "wof:placetype":"locality",
    "wof:population":37
},
  "geometry": {"coordinates":[73.243049,18.672378],"type":"Point"}
}