{
  "type": "Feature",
  "properties": {
    "iso:country":"IN",
    "ks:ks_name":"Inchathotty",
    "ks:ks_pop":426,
    "ks:ks_type":"HABITATION",
    "name:eng_x_preferred":[
        "Inchathotty"
    ],
    "wof:name":"Inchathotty",
    "wof:placetype":"locality",
    "wof:population":426
},
  "geometry": {"coordinates":[76.761861,10.087581],"type":"Point"}
}