{
  "type": "Feature",
  "properties": {
    "iso:country":"IN",
    "ks:ks_name":"Yenkapalli",
    "ks:ks_pop":421,
    "ks:ks_type":"HABITATION",
    "name:eng_x_preferred":[
        "Yenkapalli"
    ],
    "wof:name":"Yenkapalli",
    "wof:placetype":"locality",
    "wof:population":421
},
  "geometry": {"coordinates":[80.03855900000001,19.422535],"type":"Point"}
}