{
  "type": "Feature",
  "properties": {
    "gn:admin1_code":"37",
    "gn:admin2_code":"409.0",
    "gn:asciiname":"Jeortara",
    "gn:country_code":"IN",
    "gn:dem":305,
    "gn:feature_class":"P",
    "gn:feature_code":"PPL",
    "gn:name":"Jeortara",
    "gn:population":0,
    "gn:timezone":"Asia/Kolkata",
    "iso:country":"IN",
    "wof:name":"Jeortara",
    "wof:placetype":"neighbourhood"
},
  "geometry": {"coordinates":[81.10113,20.98655],"type":"Point"}
}