{
  "type": "Feature",
  "properties": {
    "iso:country":"IN",
    "ks:ks_name":"Chambethota",
    "ks:ks_pop":103,
    "ks:ks_type":"HABITATION",
    "name:eng_x_preferred":[
        "Chambethota"
    ],
    "wof:name":"Chambethota",
    "wof:placetype":"locality",
    "wof:population":103
},
  "geometry": {"coordinates":[74.93562900000001,12.802762],"type":"Point"}
}