{
  "type": "Feature",
  "properties": {
    "gn:admin1_code":"35",
    "gn:admin2_code":"443.0",
    "gn:asciiname":"Harganakheri",
    "gn:country_code":"IN",
    "gn:dem":510,
    "gn:feature_class":"P",
    "gn:feature_code":"PPL",
    "gn:name":"Hargan\u0101kheri",
    "gn:population":0,
    "gn:timezone":"Asia/Kolkata",
    "iso:country":"IN",
    "ks:ks_name":"Hargana Khedi",
    "ks:ks_pop":72,
    "ks:ks_type":"VILLAGE",
    "name:eng_x_preferred":[
        "Hargana Khedi"
    ],
    "name:eng_x_variant":[
        "Harganakheri"
    ],
    "wof:name":"Hargana Khedi",
    "wof:placetype":"locality",
    "wof:population":72
},
  "geometry": {"coordinates":[77.532392,24.227461],"type":"Point"}
}