{
  "type": "Feature",
  "properties": {
    "iso:country":"IN",
    "ks:ks_name":"Thumbare",
    "ks:ks_pop":34,
    "ks:ks_type":"HABITATION",
    "name:eng_x_preferred":[
        "Thumbare"
    ],
    "wof:name":"Thumbare",
    "wof:placetype":"locality",
    "wof:population":34
},
  "geometry": {"coordinates":[75.29652,13.549892],"type":"Point"}
}