{
  "type": "Feature",
  "properties": {
    "gn:admin1_code":"21.0",
    "gn:admin2_code":"396.0",
    "gn:asciiname":"Rungudu",
    "gn:country_code":"IN",
    "gn:dem":308,
    "gn:feature_class":"P",
    "gn:feature_code":"PPL",
    "gn:name":"Rungudu",
    "gn:population":0,
    "gn:timezone":"Asia/Kolkata",
    "iso:country":"IN",
    "ks:ks_name":"Rungudi",
    "ks:ks_pop":269,
    "ks:ks_type":"VILLAGE",
    "name:eng_x_preferred":[
        "Rungudi"
    ],
    "name:eng_x_variant":[
        "Rungudu"
    ],
    "wof:name":"Rungudi",
    "wof:placetype":"locality",
    "wof:population":269
},
  "geometry": {"coordinates":[83.780395,19.491978],"type":"Point"}
}