{
  "type": "Feature",
  "properties": {
    "iso:country":"IN",
    "ks:ks_name":"Bitisingi",
    "ks:ks_pop":121,
    "ks:ks_type":"VILLAGE",
    "name:eng_x_preferred":[
        "Bitisingi"
    ],
    "wof:name":"Bitisingi",
    "wof:placetype":"locality",
    "wof:population":121
},
  "geometry": {"coordinates":[84.128229,18.849154],"type":"Point"}
}