{
  "type": "Feature",
  "properties": {
    "gn:admin1_code":"10.0",
    "gn:admin2_code":"81.0",
    "gn:asciiname":"Barsana",
    "gn:country_code":"IN",
    "gn:dem":227,
    "gn:feature_class":"P",
    "gn:feature_code":"PPL",
    "gn:name":"Bars\u0101na",
    "gn:population":0,
    "gn:timezone":"Asia/Kolkata",
    "iso:country":"IN",
    "name:bih_x_preferred":[
        "\u092c\u0930\u0938\u093e\u0928\u093e"
    ],
    "name:bpy_x_preferred":[
        "\u09ac\u09b0\u09b8\u09be\u09a8\u09be"
    ],
    "name:ceb_x_preferred":[
        "Bars\u0101na"
    ],
    "name:fra_x_preferred":[
        "Barsana"
    ],
    "name:hin_x_preferred":[
        "\u092c\u0930\u0938\u093e\u0928\u093e"
    ],
    "name:ita_x_preferred":[
        "Barsana"
    ],
    "name:msa_x_preferred":[
        "Barsana"
    ],
    "name:new_x_preferred":[
        "\u092c\u0930\u094d\u0938\u0928\u093e"
    ],
    "name:nld_x_preferred":[
        "Barsana"
    ],
    "name:pol_x_preferred":[
        "Barsana"
    ],
    "name:ron_x_preferred":[
        "Barsana"
    ],
    "name:rus_x_preferred":[
        "\u0411\u0430\u0440\u0441\u0430\u043d\u0430"
    ],
    "name:swe_x_preferred":[
        "Bars\u0101na"
    ],
    "name:urd_x_preferred":[
        "\u0628\u0631\u0633\u0627\u0646\u0627"
    ],
    "name:vie_x_preferred":[
        "Barsana"
    ],
    "name:zho_x_preferred":[
        "\u5df4\u5c14\u8428\u7eb3"
    ],
    "wof:name":"Barsana",
    "wof:placetype":"locality"
},
  "geometry": {"coordinates":[76.11983000000002,28.58911],"type":"Point"}
}