{
  "type": "Feature",
  "properties": {
    "iso:country":"IN",
    "ks:ks_name":"Shantikere",
    "ks:ks_pop":182,
    "ks:ks_type":"VILLAGE",
    "name:eng_x_preferred":[
        "Shantikere"
    ],
    "wof:name":"Shantikere",
    "wof:placetype":"locality",
    "wof:population":182
},
  "geometry": {"coordinates":[75.332503,14.028194],"type":"Point"}
}