{
  "type": "Feature",
  "properties": {
    "gn:admin1_code":"36.0",
    "gn:admin2_code":"184.0",
    "gn:asciiname":"Amghati",
    "gn:country_code":"IN",
    "gn:dem":96,
    "gn:feature_class":"P",
    "gn:feature_code":"PPL",
    "gn:name":"Amghati",
    "gn:population":0,
    "gn:timezone":"Asia/Kolkata",
    "iso:country":"IN",
    "ks:ks_name":"Amghati",
    "ks:ks_pop":407,
    "ks:ks_type":"VILLAGE",
    "name:eng_x_preferred":[
        "Amghati"
    ],
    "wof:name":"Amghati",
    "wof:placetype":"locality",
    "wof:population":407
},
  "geometry": {"coordinates":[82.829611,27.188032],"type":"Point"}
}