{
  "type": "Feature",
  "properties": {
    "gn:admin1_code":"19.0",
    "gn:admin2_code":"555.0",
    "gn:asciiname":"Kagdhal",
    "gn:country_code":"IN",
    "gn:dem":605,
    "gn:feature_class":"P",
    "gn:feature_code":"PPL",
    "gn:name":"K\u0101gdh\u0101l",
    "gn:population":0,
    "gn:timezone":"Asia/Kolkata",
    "iso:country":"IN",
    "wof:name":"Kagdhal",
    "wof:placetype":"neighbourhood"
},
  "geometry": {"coordinates":[75.29635,15.78332],"type":"Point"}
}