{
  "type": "Feature",
  "properties": {
    "iso:country":"IN",
    "ks:ks_alt_nam":"Malakadevar hatti",
    "ks:ks_name":"Malakadevar Hatti",
    "ks:ks_pop":499,
    "ks:ks_type":"HABITATION",
    "name:eng_x_preferred":[
        "Malakadevar Hatti"
    ],
    "wof:name":"Malakadevar Hatti",
    "wof:placetype":"locality",
    "wof:population":499
},
  "geometry": {"coordinates":[75.536968,16.915262],"type":"Point"}
}