{
  "type": "Feature",
  "properties": {
    "iso:country":"IN",
    "ks:ks_alt_nam":"JADHAV VASTI",
    "ks:ks_name":"Jadhav Vasti",
    "ks:ks_pop":263,
    "ks:ks_type":"HABITATION",
    "name:eng_x_preferred":[
        "Jadhav Vasti"
    ],
    "wof:name":"Jadhav Vasti",
    "wof:placetype":"locality",
    "wof:population":263
},
  "geometry": {"coordinates":[74.72809599999999,16.799962],"type":"Point"}
}