{
  "type": "Feature",
  "properties": {
    "gn:admin1_code":"25.0",
    "gn:admin2_code":"631.0",
    "gn:asciiname":"Pedda Matagoudapalli Jagir",
    "gn:country_code":"IN",
    "gn:dem":921,
    "gn:feature_class":"P",
    "gn:feature_code":"PPL",
    "gn:name":"Pedda Matagoudapalli J\u0101gir",
    "gn:population":0,
    "gn:timezone":"Asia/Kolkata",
    "iso:country":"IN",
    "wof:name":"Pedda Matagoudapalli Jagir",
    "wof:placetype":"neighbourhood"
},
  "geometry": {"coordinates":[77.72811,12.63546],"type":"Point"}
}