{
  "type": "Feature",
  "properties": {
    "gn:admin1_code":"19.0",
    "gn:admin2_code":"572.0",
    "gn:asciiname":"Vaderhalli",
    "gn:country_code":"IN",
    "gn:dem":908,
    "gn:feature_class":"P",
    "gn:feature_code":"PPL",
    "gn:name":"Vad\u0113rhalli",
    "gn:population":0,
    "gn:timezone":"Asia/Kolkata",
    "iso:country":"IN",
    "wof:name":"Vaderhalli",
    "wof:placetype":"locality"
},
  "geometry": {"coordinates":[77.69766,12.72994],"type":"Point"}
}