{
  "type": "Feature",
  "properties": {
    "iso:country":"IN",
    "ks:ks_name":"Tintara",
    "ks:ks_pop":222,
    "ks:ks_type":"VILLAGE",
    "ks:ks_uagg_main":0,
    "name:eng_x_preferred":[
        "Tintara"
    ],
    "wof:name":"Tintara",
    "wof:placetype":"locality",
    "wof:population":222
},
  "geometry": {"coordinates":[85.607896,24.46423],"type":"Point"}
}