{
  "type": "Feature",
  "properties": {
    "iso:country":"IN",
    "ks:ks_alt_nam":"12 APD",
    "ks:ks_name":"12 Apd",
    "ks:ks_pop":105,
    "ks:ks_type":"HABITATION",
    "name:eng_x_preferred":[
        "12 Apd"
    ],
    "wof:name":"12 Apd",
    "wof:placetype":"locality",
    "wof:population":105
},
  "geometry": {"coordinates":[73.344444,29.286944],"type":"Point"}
}