{
  "type": "Feature",
  "properties": {
    "iso:country":"IN",
    "ks:ks_name":"Rajendranagar",
    "ks:ks_pop":49,
    "ks:ks_type":"HABITATION",
    "ks:ks_uagg_main":0,
    "name:eng_x_preferred":[
        "Rajendranagar"
    ],
    "wof:name":"Rajendranagar",
    "wof:placetype":"neighbourhood",
    "wof:population":49
},
  "geometry": {"coordinates":[80.58415599999999,17.587159],"type":"Point"}
}