{
  "type": "Feature",
  "properties": {
    "iso:country":"IN",
    "ks:ks_name":"Olarbindha",
    "ks:ks_pop":147,
    "ks:ks_type":"VILLAGE",
    "ks:ks_uagg_main":0,
    "name:eng_x_preferred":[
        "Olarbindha"
    ],
    "wof:name":"Olarbindha",
    "wof:placetype":"neighbourhood",
    "wof:population":147
},
  "geometry": {"coordinates":[85.965479,20.245955],"type":"Point"}
}