{
  "type": "Feature",
  "properties": {
    "gn:admin1_code":"10.0",
    "gn:admin2_code":"71.0",
    "gn:asciiname":"Chikan",
    "gn:country_code":"IN",
    "gn:dem":361,
    "gn:feature_class":"P",
    "gn:feature_code":"PPL",
    "gn:name":"Chikan",
    "gn:population":0,
    "gn:timezone":"Asia/Kolkata",
    "iso:country":"IN",
    "name:ceb_x_preferred":[
        "Chikan"
    ],
    "name:deu_x_preferred":[
        "Chikan"
    ],
    "name:fra_x_preferred":[
        "Chikan"
    ],
    "name:spa_x_preferred":[
        "Chikan"
    ],
    "wof:name":"Chikan",
    "wof:placetype":"locality"
},
  "geometry": {"coordinates":[77.4802,30.36953],"type":"Point"}
}