{
  "type": "Feature",
  "properties": {
    "gn:admin1_code":"19.0",
    "gn:admin2_code":"563.0",
    "gn:asciiname":"Magod",
    "gn:country_code":"IN",
    "gn:dem":484,
    "gn:feature_class":"P",
    "gn:feature_code":"PPL",
    "gn:name":"M\u0101god",
    "gn:population":0,
    "gn:timezone":"Asia/Kolkata",
    "iso:country":"IN",
    "ks:ks_alt_nam":"M\u0101god",
    "ks:ks_name":"Magod",
    "ks:ks_pop":41,
    "ks:ks_type":"VILLAGE",
    "name:eng_x_preferred":[
        "Magod"
    ],
    "name:eng_x_variant":[
        "M\u0101god"
    ],
    "wof:name":"Magod",
    "wof:placetype":"locality",
    "wof:population":41
},
  "geometry": {"coordinates":[74.7189,14.862452],"type":"Point"}
}