{
  "type": "Feature",
  "properties": {
    "iso:country":"IN",
    "ks:ks_name":"Dusadh Tol",
    "ks:ks_pop":334,
    "ks:ks_type":"HABITATION",
    "name:eng_x_preferred":[
        "Dusadh Tol"
    ],
    "wof:name":"Dusadh Tol",
    "wof:placetype":"locality",
    "wof:population":334
},
  "geometry": {"coordinates":[86.36011000000001,26.319828],"type":"Point"}
}