{
  "type": "Feature",
  "properties": {
    "gn:admin1_code":"25.0",
    "gn:admin2_code":"608.0",
    "gn:asciiname":"Palaiyakalikavundanur",
    "gn:country_code":"IN",
    "gn:dem":304,
    "gn:feature_class":"P",
    "gn:feature_code":"PPL",
    "gn:name":"Palaiyak\u0101likavundan\u016br",
    "gn:population":0,
    "gn:timezone":"Asia/Kolkata",
    "iso:country":"IN",
    "wof:name":"Palaiyakalikavundanur",
    "wof:placetype":"neighbourhood"
},
  "geometry": {"coordinates":[77.96914,11.88464],"type":"Point"}
}