{
  "type": "Feature",
  "properties": {
    "gn:admin1_code":"25.0",
    "gn:admin2_code":"622.0",
    "gn:asciiname":"Okkur",
    "gn:country_code":"IN",
    "gn:dem":96,
    "gn:feature_class":"P",
    "gn:feature_code":"PPL",
    "gn:name":"Okk\u016br",
    "gn:population":0,
    "gn:timezone":"Asia/Kolkata",
    "iso:country":"IN",
    "wof:name":"Okkur",
    "wof:placetype":"locality"
},
  "geometry": {"coordinates":[78.52191999999999,9.94524],"type":"Point"}
}