{
  "type": "Feature",
  "properties": {
    "gn:admin1_code":"36",
    "gn:admin2_code":"153.0",
    "gn:asciiname":"Dhamaura",
    "gn:country_code":"IN",
    "gn:dem":148,
    "gn:feature_class":"P",
    "gn:feature_code":"PPL",
    "gn:name":"Dhamaura",
    "gn:population":0,
    "gn:timezone":"Asia/Kolkata",
    "iso:country":"IN",
    "name:bih_x_preferred":[
        "\u0927\u092e\u094c\u0930\u093e"
    ],
    "name:ceb_x_preferred":[
        "Dhamaura"
    ],
    "name:fra_x_preferred":[
        "Dhamaura"
    ],
    "name:mai_x_preferred":[
        "\u0927\u092e\u094c\u0930\u093e"
    ],
    "name:msa_x_preferred":[
        "Dhamaura"
    ],
    "name:nep_x_preferred":[
        "\u0927\u092e\u094c\u0930\u093e"
    ],
    "name:new_x_preferred":[
        "\u0927\u092e\u094c\u0930\u093e"
    ],
    "name:pol_x_preferred":[
        "Dhamaura"
    ],
    "wof:name":"Dhamaura",
    "wof:placetype":"neighbourhood"
},
  "geometry": {"coordinates":[80.76408000000001,27.89551],"type":"Point"}
}