{
  "type": "Feature",
  "properties": {
    "gn:admin1_code":"10.0",
    "gn:admin2_code":"85.0",
    "gn:asciiname":"Ladhuwas Ahir",
    "gn:country_code":"IN",
    "gn:dem":247,
    "gn:feature_class":"P",
    "gn:feature_code":"PPL",
    "gn:name":"L\u0101dh\u016bw\u0101s Ah\u012br",
    "gn:population":0,
    "gn:timezone":"Asia/Kolkata",
    "iso:country":"IN",
    "name:und_x_variant":[
        "L\u0101dh\u016bw\u0101s Ah\u012br"
    ],
    "wof:name":"Ladhuwas Ahir",
    "wof:placetype":"locality"
},
  "geometry": {"coordinates":[76.55909,28.20611],"type":"Point"}
}