{
  "type": "Feature",
  "properties": {
    "gn:admin1_code":"36.0",
    "gn:admin2_code":"163.0",
    "gn:asciiname":"Makrandpur",
    "gn:country_code":"IN",
    "gn:dem":137,
    "gn:feature_class":"P",
    "gn:feature_code":"PPL",
    "gn:name":"Makrandpur",
    "gn:population":0,
    "gn:timezone":"Asia/Kolkata",
    "iso:country":"IN",
    "name:und_x_variant":[
        "Marahmat\u0101b\u0101d",
        "Makrandpur"
    ],
    "wof:name":"Makrandpur",
    "wof:placetype":"locality"
},
  "geometry": {"coordinates":[79.97354,26.5719],"type":"Point"}
}