{
  "type": "Feature",
  "properties": {
    "iso:country":"IN",
    "ks:ks_alt_nam":"Mehr\u0101b\u0101d",
    "ks:ks_name":"Mehrabad",
    "ks:ks_type":"VILLAGE",
    "ks:ks_uagg_main":0,
    "name:eng_x_preferred":[
        "Mehrabad"
    ],
    "name:eng_x_variant":[
        "Mehr\u0101b\u0101d"
    ],
    "wof:name":"Mehrabad",
    "wof:placetype":"neighbourhood"
},
  "geometry": {"coordinates":[78.57840899999999,27.092939],"type":"Point"}
}