{
  "type": "Feature",
  "properties": {
    "iso:country":"IN",
    "ks:ks_name":"Kuila",
    "ks:ks_pop":120,
    "ks:ks_type":"HABITATION",
    "name:eng_x_preferred":[
        "Kuila"
    ],
    "wof:name":"Kuila",
    "wof:placetype":"locality",
    "wof:population":120
},
  "geometry": {"coordinates":[86.93038,22.629787],"type":"Point"}
}