{
  "type": "Feature",
  "properties": {
    "iso:country":"IN",
    "ks:ks_name":"Belbahra",
    "ks:ks_pop":1208,
    "ks:ks_type":"VILLAGE",
    "name:eng_x_preferred":[
        "Belbahra"
    ],
    "wof:name":"Belbahra",
    "wof:placetype":"locality",
    "wof:population":1208
},
  "geometry": {"coordinates":[82.21299500000001,23.018829],"type":"Point"}
}