{
  "type": "Feature",
  "properties": {
    "iso:country":"IN",
    "ks:ks_alt_nam":"kidukatti",
    "ks:ks_name":"Kidukatti",
    "ks:ks_pop":255,
    "ks:ks_type":"HABITATION",
    "name:eng_x_preferred":[
        "Kidukatti"
    ],
    "wof:name":"Kidukatti",
    "wof:placetype":"locality",
    "wof:population":255
},
  "geometry": {"coordinates":[78.866488,9.879009],"type":"Point"}
}