{
  "type": "Feature",
  "properties": {
    "gn:admin1_code":"33.0",
    "gn:admin2_code":"585",
    "gn:asciiname":"Colombi",
    "gn:cc2":"IN",
    "gn:country_code":"IN",
    "gn:dem":13,
    "gn:feature_class":"P",
    "gn:feature_code":"PPL",
    "gn:name":"Colombi",
    "gn:population":0,
    "gn:timezone":"Asia/Kolkata",
    "iso:country":"IN",
    "name:und_x_variant":[
        "Cotombi",
        "Colombi"
    ],
    "wof:name":"Colombi",
    "wof:placetype":"locality"
},
  "geometry": {"coordinates":[74.03333000000001,15.46667],"type":"Point"}
}