{
  "type": "Feature",
  "properties": {
    "iso:country":"IN",
    "ks:ks_name":"Dhadkidi",
    "ks:ks_pop":214,
    "ks:ks_type":"VILLAGE",
    "ks:ks_uagg_main":0,
    "name:eng_x_preferred":[
        "Dhadkidi"
    ],
    "wof:name":"Dhadkidi",
    "wof:placetype":"neighbourhood",
    "wof:population":214
},
  "geometry": {"coordinates":[86.70682499999999,23.789038],"type":"Point"}
}