{
  "type": "Feature",
  "properties": {
    "iso:country":"IN",
    "ks:ks_name":"Titingapada",
    "ks:ks_pop":697,
    "ks:ks_type":"VILLAGE",
    "name:eng_x_preferred":[
        "Titingapada"
    ],
    "wof:name":"Titingapada",
    "wof:placetype":"locality",
    "wof:population":697
},
  "geometry": {"coordinates":[86.121543,20.031471],"type":"Point"}
}