{
  "type": "Feature",
  "properties": {
    "iso:country":"IN",
    "ks:ks_name":"Kanksol",
    "ks:ks_pop":0,
    "ks:ks_type":"VILLAGE",
    "name:eng_x_preferred":[
        "Kanksol"
    ],
    "wof:name":"Kanksol",
    "wof:placetype":"locality",
    "wof:population":0
},
  "geometry": {"coordinates":[87.358634,22.53581],"type":"Point"}
}