{
  "type": "Feature",
  "properties": {
    "iso:country":"IN",
    "ks:ks_alt_nam":"1 MC BARANI",
    "ks:ks_name":"1 Mc Barani",
    "ks:ks_pop":13,
    "ks:ks_type":"HABITATION",
    "name:eng_x_preferred":[
        "1 Mc Barani"
    ],
    "wof:name":"1 Mc Barani",
    "wof:placetype":"locality",
    "wof:population":13
},
  "geometry": {"coordinates":[73.94039100000001,29.179474],"type":"Point"}
}