{
  "type": "Feature",
  "properties": {
    "iso:country":"IN",
    "ks:ks_name":"Paraspur Bejhawniya",
    "ks:ks_pop":180,
    "ks:ks_type":"VILLAGE",
    "name:eng_x_preferred":[
        "Paraspur Bejhawniya"
    ],
    "wof:name":"Paraspur Bejhawniya",
    "wof:placetype":"locality",
    "wof:population":180
},
  "geometry": {"coordinates":[82.566174,25.431474],"type":"Point"}
}