{
  "type": "Feature",
  "properties": {
    "gn:admin1_code":"36",
    "gn:admin2_code":"156.0",
    "gn:asciiname":"Basant Khera",
    "gn:country_code":"IN",
    "gn:dem":119,
    "gn:feature_class":"P",
    "gn:feature_code":"PPL",
    "gn:name":"Basant Khera",
    "gn:population":0,
    "gn:timezone":"Asia/Kolkata",
    "iso:country":"IN",
    "wof:name":"Basant Khera",
    "wof:placetype":"locality"
},
  "geometry": {"coordinates":[80.82624,26.26231],"type":"Point"}
}