{
  "type": "Feature",
  "properties": {
    "iso:country":"IN",
    "ks:ks_name":"Mota Ghed",
    "ks:ks_pop":13,
    "ks:ks_type":"VILLAGE",
    "name:eng_x_preferred":[
        "Mota Ghed"
    ],
    "wof:name":"Mota Ghed",
    "wof:placetype":"locality",
    "wof:population":13
},
  "geometry": {"coordinates":[69.96005599999999,21.421667],"type":"Point"}
}