{
  "type": "Feature",
  "properties": {
    "gn:admin1_code":"34.0",
    "gn:admin2_code":"221.0",
    "gn:asciiname":"Manpura",
    "gn:country_code":"IN",
    "gn:dem":54,
    "gn:feature_class":"P",
    "gn:feature_code":"PPL",
    "gn:name":"M\u0101npura",
    "gn:population":0,
    "gn:timezone":"Asia/Kolkata",
    "iso:country":"IN",
    "ks:ks_name":"Manpura",
    "ks:ks_pop":599,
    "ks:ks_type":"VILLAGE",
    "name:eng_x_preferred":[
        "Manpura"
    ],
    "wof:name":"Manpura",
    "wof:placetype":"locality",
    "wof:population":599
},
  "geometry": {"coordinates":[85.63875299999999,25.836301],"type":"Point"}
}