{
  "type": "Feature",
  "properties": {
    "iso:country":"IN",
    "ks:ks_name":"Koothandam Palaiya Colony",
    "ks:ks_pop":250,
    "ks:ks_type":"HABITATION",
    "ks:ks_uagg_main":0,
    "name:eng_x_preferred":[
        "Koothandam Palaiya Colony"
    ],
    "wof:name":"Koothandam Palaiya Colony",
    "wof:placetype":"neighbourhood",
    "wof:population":250
},
  "geometry": {"coordinates":[78.49471200000001,9.832563],"type":"Point"}
}