{
  "type": "Feature",
  "properties": {
    "iso:country":"IN",
    "ks:ks_alt_nam":"Pattiyandal ADC",
    "ks:ks_name":"Pattiyandal Adc",
    "ks:ks_pop":163,
    "ks:ks_type":"HABITATION",
    "name:eng_x_preferred":[
        "Pattiyandal Adc"
    ],
    "wof:name":"Pattiyandal Adc",
    "wof:placetype":"locality",
    "wof:population":163
},
  "geometry": {"coordinates":[78.932772,12.450605],"type":"Point"}
}