{
  "type": "Feature",
  "properties": {
    "gn:admin1_code":"21.0",
    "gn:admin2_code":"398.0",
    "gn:asciiname":"Gunjalipadu",
    "gn:country_code":"IN",
    "gn:dem":876,
    "gn:feature_class":"P",
    "gn:feature_code":"PPL",
    "gn:name":"Gunjalip\u0101du",
    "gn:population":0,
    "gn:timezone":"Asia/Kolkata",
    "iso:country":"IN",
    "ks:ks_name":"Gunjilpadu",
    "ks:ks_pop":36,
    "ks:ks_type":"HABITATION",
    "name:eng_x_preferred":[
        "Gunjilpadu"
    ],
    "name:eng_x_variant":[
        "Gunjalipadu"
    ],
    "wof:name":"Gunjilpadu",
    "wof:placetype":"locality",
    "wof:population":36
},
  "geometry": {"coordinates":[83.023816,18.543764],"type":"Point"}
}