{
  "type": "Feature",
  "properties": {
    "iso:country":"IN",
    "ks:ks_name":"3 R",
    "ks:ks_pop":49,
    "ks:ks_type":"VILLAGE",
    "ks:ks_uagg_main":0,
    "name:eng_x_preferred":[
        "3 R"
    ],
    "wof:name":"3 R",
    "wof:placetype":"neighbourhood",
    "wof:population":49
},
  "geometry": {"coordinates":[73.671761,30.003707],"type":"Point"}
}