{
  "type": "Feature",
  "properties": {
    "gn:admin1_code":"36",
    "gn:admin2_code":"179.0",
    "gn:asciiname":"Purwa Bhikai",
    "gn:country_code":"IN",
    "gn:dem":94,
    "gn:feature_class":"P",
    "gn:feature_code":"PPL",
    "gn:name":"Purwa Bhikai",
    "gn:population":0,
    "gn:timezone":"Asia/Kolkata",
    "iso:country":"IN",
    "wof:name":"Purwa Bhikai",
    "wof:placetype":"neighbourhood"
},
  "geometry": {"coordinates":[82.11279999999999,26.28764],"type":"Point"}
}