{
  "type": "Feature",
  "properties": {
    "gn:admin1_code":"16",
    "gn:admin2_code":"505.0",
    "gn:asciiname":"Bori",
    "gn:country_code":"IN",
    "gn:dem":306,
    "gn:feature_class":"P",
    "gn:feature_code":"PPL",
    "gn:name":"Bori",
    "gn:population":0,
    "gn:timezone":"Asia/Kolkata",
    "iso:country":"IN",
    "name:ceb_x_preferred":[
        "Bori"
    ],
    "name:deu_x_preferred":[
        "Bori"
    ],
    "name:fra_x_preferred":[
        "Bori"
    ],
    "name:hun_x_preferred":[
        "Bori"
    ],
    "name:ita_x_preferred":[
        "Bori"
    ],
    "name:kor_x_preferred":[
        "\ubcf4\ub9ac"
    ],
    "name:por_x_preferred":[
        "Bori"
    ],
    "name:swe_x_preferred":[
        "Bori"
    ],
    "name:vie_x_preferred":[
        "Bori"
    ],
    "wof:name":"Bori",
    "wof:placetype":"locality"
},
  "geometry": {"coordinates":[79.40533000000001,21.36665],"type":"Point"}
}