{
  "type": "Feature",
  "properties": {
    "gn:admin1_code":"35",
    "gn:admin2_code":"456.0",
    "gn:asciiname":"Murgahi",
    "gn:country_code":"IN",
    "gn:dem":539,
    "gn:feature_class":"P",
    "gn:feature_code":"PPL",
    "gn:name":"M\u016brg\u0101h\u012b",
    "gn:population":0,
    "gn:timezone":"Asia/Kolkata",
    "iso:country":"IN",
    "wof:name":"Murgahi",
    "wof:placetype":"locality"
},
  "geometry": {"coordinates":[79.92574,22.57639],"type":"Point"}
}