{
  "type": "Feature",
  "properties": {
    "iso:country":"IN",
    "ks:ks_name":"Mandapathankadu",
    "ks:ks_pop":250,
    "ks:ks_type":"HABITATION",
    "name:eng_x_preferred":[
        "Mandapathankadu"
    ],
    "wof:name":"Mandapathankadu",
    "wof:placetype":"locality",
    "wof:population":250
},
  "geometry": {"coordinates":[77.86443199999999,11.490432],"type":"Point"}
}