{
  "type": "Feature",
  "properties": {
    "iso:country":"IN",
    "ks:ks_name":"Adivasipada",
    "ks:ks_pop":201,
    "ks:ks_type":"HABITATION",
    "name:eng_x_preferred":[
        "Adivasipada"
    ],
    "wof:name":"Adivasipada",
    "wof:placetype":"locality",
    "wof:population":201
},
  "geometry": {"coordinates":[73.106651,19.442612],"type":"Point"}
}