{
  "type": "Feature",
  "properties": {
    "gn:admin1_code":"37",
    "gn:admin2_code":"417.0",
    "gn:asciiname":"Pulpa Madugu",
    "gn:country_code":"IN",
    "gn:dem":550,
    "gn:feature_class":"P",
    "gn:feature_code":"PPL",
    "gn:name":"Pulpa Madugu",
    "gn:population":0,
    "gn:timezone":"Asia/Kolkata",
    "iso:country":"IN",
    "wof:name":"Pulpa Madugu",
    "wof:placetype":"locality"
},
  "geometry": {"coordinates":[80.75227,18.38629],"type":"Point"}
}