{
  "type": "Feature",
  "properties": {
    "gn:admin1_code":"25.0",
    "gn:admin2_code":"630.0",
    "gn:asciiname":"Sinnaganahalli",
    "gn:country_code":"IN",
    "gn:dem":467,
    "gn:feature_class":"P",
    "gn:feature_code":"PPL",
    "gn:name":"Sinn\u0101ganahalli",
    "gn:population":0,
    "gn:timezone":"Asia/Kolkata",
    "iso:country":"IN",
    "wof:name":"Sinnaganahalli",
    "wof:placetype":"neighbourhood"
},
  "geometry": {"coordinates":[77.97629999999999,12.09217],"type":"Point"}
}