{
  "type": "Feature",
  "properties": {
    "iso:country":"IN",
    "ks:ks_name":"Raghunathapur",
    "ks:ks_pop":336,
    "ks:ks_type":"HABITATION",
    "name:eng_x_preferred":[
        "Raghunathapur"
    ],
    "wof:name":"Raghunathapur",
    "wof:placetype":"locality",
    "wof:population":336
},
  "geometry": {"coordinates":[86.961055,21.680344],"type":"Point"}
}