{
  "type": "Feature",
  "properties": {
    "gn:admin1_code":"10.0",
    "gn:admin2_code":"084",
    "gn:asciiname":"Kanwariyabas",
    "gn:country_code":"IN",
    "gn:dem":330,
    "gn:feature_class":"P",
    "gn:feature_code":"PPL",
    "gn:name":"Kanwariy\u0101b\u0101s",
    "gn:population":0,
    "gn:timezone":"Asia/Kolkata",
    "iso:country":"IN",
    "wof:name":"Kanwariyabas",
    "wof:placetype":"locality"
},
  "geometry": {"coordinates":[76.04069,28.03117],"type":"Point"}
}