{
  "type": "Feature",
  "properties": {
    "gn:admin1_code":"36",
    "gn:admin2_code":"194.0",
    "gn:asciiname":"Khemapur",
    "gn:country_code":"IN",
    "gn:dem":89,
    "gn:feature_class":"P",
    "gn:feature_code":"PPL",
    "gn:name":"Khemapur",
    "gn:population":0,
    "gn:timezone":"Asia/Kolkata",
    "iso:country":"IN",
    "ks:ks_name":"Khemapur",
    "ks:ks_pop":679,
    "ks:ks_type":"VILLAGE",
    "ks:ks_uagg_main":0,
    "name:eng_x_preferred":[
        "Khemapur"
    ],
    "wof:name":"Khemapur",
    "wof:placetype":"neighbourhood",
    "wof:population":679
},
  "geometry": {"coordinates":[82.53466899999999,25.444436],"type":"Point"}
}