{
  "type": "Feature",
  "properties": {
    "gn:admin1_code":"23.0",
    "gn:admin2_code":"42.0",
    "gn:asciiname":"Amargarh Bandian",
    "gn:country_code":"IN",
    "gn:dem":214,
    "gn:feature_class":"P",
    "gn:feature_code":"PPL",
    "gn:name":"Amargarh B\u0101ndi\u0101n",
    "gn:population":0,
    "gn:timezone":"Asia/Kolkata",
    "iso:country":"IN",
    "wof:name":"Amargarh Bandian",
    "wof:placetype":"locality"
},
  "geometry": {"coordinates":[75.08811,31.00935],"type":"Point"}
}