{
  "type": "Feature",
  "properties": {
    "iso:country":"IN",
    "ks:ks_name":"Borokona",
    "ks:ks_type":"VILLAGE",
    "name:eng_x_preferred":[
        "Borokona"
    ],
    "wof:name":"Borokona",
    "wof:placetype":"locality"
},
  "geometry": {"coordinates":[84.057265,22.900202],"type":"Point"}
}