{
  "type": "Feature",
  "properties": {
    "iso:country":"IN",
    "ks:ks_name":"Dumbari",
    "ks:ks_pop":0,
    "ks:ks_type":"VILLAGE",
    "name:eng_x_preferred":[
        "Dumbari"
    ],
    "wof:name":"Dumbari",
    "wof:placetype":"locality",
    "wof:population":0
},
  "geometry": {"coordinates":[87.50368899999999,25.052637],"type":"Point"}
}