{
  "type": "Feature",
  "properties": {
    "iso:country":"IN",
    "ks:ks_name":"Vylipura",
    "ks:ks_type":"VILLAGE",
    "name:eng_x_preferred":[
        "Vylipura"
    ],
    "wof:name":"Vylipura",
    "wof:placetype":"locality"
},
  "geometry": {"coordinates":[75.827529,14.171896],"type":"Point"}
}