{
  "type": "Feature",
  "properties": {
    "gn:admin1_code":"10.0",
    "gn:admin2_code":"069",
    "gn:asciiname":"Kotian",
    "gn:country_code":"IN",
    "gn:dem":420,
    "gn:feature_class":"P",
    "gn:feature_code":"PPL",
    "gn:name":"Koti\u0101n",
    "gn:population":0,
    "gn:timezone":"Asia/Kolkata",
    "iso:country":"IN",
    "ks:ks_alt_nam":"Koti\u0101n",
    "ks:ks_name":"Kotian",
    "ks:ks_pop":1997,
    "ks:ks_type":"VILLAGE",
    "ks:ks_uagg_main":0,
    "name:eng_x_preferred":[
        "Kotian"
    ],
    "name:eng_x_variant":[
        "Koti\u0101n"
    ],
    "wof:name":"Kotian",
    "wof:placetype":"neighbourhood",
    "wof:population":1997
},
  "geometry": {"coordinates":[76.926215,30.740262],"type":"Point"}
}