{
  "type": "Feature",
  "properties": {
    "iso:country":"IN",
    "ks:ks_name":"Sarakallu",
    "ks:ks_pop":989,
    "ks:ks_type":"HABITATION",
    "name:eng_x_preferred":[
        "Sarakallu"
    ],
    "wof:name":"Sarakallu",
    "wof:placetype":"locality",
    "wof:population":989
},
  "geometry": {"coordinates":[74.76132,13.756739],"type":"Point"}
}