{
  "type": "Feature",
  "properties": {
    "iso:country":"IN",
    "ks:ks_name":"Radha Krishnapur",
    "ks:ks_pop":857,
    "ks:ks_type":"VILLAGE",
    "name:eng_x_preferred":[
        "Radha Krishnapur"
    ],
    "wof:name":"Radha Krishnapur",
    "wof:placetype":"locality",
    "wof:population":857
},
  "geometry": {"coordinates":[87.15801500000001,23.348876],"type":"Point"}
}