{
  "type": "Feature",
  "properties": {
    "iso:country":"IN",
    "ks:ks_alt_nam":"Heroes Nagar Rd end",
    "ks:ks_name":"Heroes Nagar Rd End",
    "ks:ks_pop":1021,
    "ks:ks_type":"HABITATION",
    "name:eng_x_preferred":[
        "Heroes Nagar Rd End"
    ],
    "wof:name":"Heroes Nagar Rd End",
    "wof:placetype":"locality",
    "wof:population":1021
},
  "geometry": {"coordinates":[75.83279,11.125265],"type":"Point"}
}