{
  "type": "Feature",
  "properties": {
    "gn:admin1_code":"19.0",
    "gn:admin2_code":"581.0",
    "gn:asciiname":"Pujenahalli",
    "gn:country_code":"IN",
    "gn:dem":763,
    "gn:feature_class":"P",
    "gn:feature_code":"PPL",
    "gn:name":"P\u016bjenahalli",
    "gn:population":0,
    "gn:timezone":"Asia/Kolkata",
    "iso:country":"IN",
    "wof:name":"Pujenahalli",
    "wof:placetype":"locality"
},
  "geometry": {"coordinates":[78.47875999999999,13.2416],"type":"Point"}
}