{
  "type": "Feature",
  "properties": {
    "gn:admin1_code":"35",
    "gn:admin2_code":"462.0",
    "gn:asciiname":"Path",
    "gn:country_code":"IN",
    "gn:dem":432,
    "gn:feature_class":"P",
    "gn:feature_code":"PPL",
    "gn:name":"P\u0101th",
    "gn:population":0,
    "gn:timezone":"Asia/Kolkata",
    "iso:country":"IN",
    "ks:ks_alt_nam":"P\u0101th",
    "ks:ks_name":"Path",
    "ks:ks_pop":227,
    "ks:ks_type":"VILLAGE",
    "name:ara_x_preferred":[
        "\u0645\u0633\u0627\u0631"
    ],
    "name:ces_x_preferred":[
        "Path"
    ],
    "name:deu_x_preferred":[
        "Pfad"
    ],
    "name:eng_x_preferred":[
        "Path"
    ],
    "name:eng_x_variant":[
        "P\u0101th"
    ],
    "name:fas_x_preferred":[
        "\u0645\u0633\u06cc\u0631"
    ],
    "name:fra_x_preferred":[
        "Path"
    ],
    "name:glg_x_preferred":[
        "Cami\u00f1o"
    ],
    "name:por_x_preferred":[
        "Caminho"
    ],
    "name:spa_x_preferred":[
        "Path"
    ],
    "wof:name":"Path",
    "wof:placetype":"locality",
    "wof:population":227
},
  "geometry": {"coordinates":[81.93456399999999,24.554056],"type":"Point"}
}