{
  "type": "Feature",
  "properties": {
    "iso:country":"IN",
    "ks:ks_name":"Mohamadpur",
    "ks:ks_pop":285,
    "ks:ks_type":"HABITATION",
    "name:eng_x_preferred":[
        "Mohamadpur"
    ],
    "wof:name":"Mohamadpur",
    "wof:placetype":"locality",
    "wof:population":285
},
  "geometry": {"coordinates":[80.660438,27.869881],"type":"Point"}
}