{
  "type": "Feature",
  "properties": {
    "gn:admin1_code":"36",
    "gn:admin2_code":"180.0",
    "gn:asciiname":"Malal Purwa",
    "gn:country_code":"IN",
    "gn:dem":117,
    "gn:feature_class":"P",
    "gn:feature_code":"PPL",
    "gn:name":"Mal\u0101l Purwa",
    "gn:population":0,
    "gn:timezone":"Asia/Kolkata",
    "iso:country":"IN",
    "ks:ks_name":"Malang Purwa",
    "ks:ks_pop":72,
    "ks:ks_type":"HABITATION",
    "ks:ks_uagg_main":0,
    "name:eng_x_preferred":[
        "Malang Purwa"
    ],
    "wof:name":"Malang Purwa",
    "wof:placetype":"neighbourhood",
    "wof:population":72
},
  "geometry": {"coordinates":[81.49633300000001,27.439747],"type":"Point"}
}