{
  "type": "Feature",
  "properties": {
    "gn:admin1_code":"19.0",
    "gn:admin2_code":"562.0",
    "gn:asciiname":"Bendalgatti",
    "gn:country_code":"IN",
    "gn:dem":627,
    "gn:feature_class":"P",
    "gn:feature_code":"PPL",
    "gn:name":"Bendalgatti",
    "gn:population":0,
    "gn:timezone":"Asia/Kolkata",
    "iso:country":"IN",
    "name:vie_x_preferred":[
        "Bendalgatti"
    ],
    "wof:name":"Bendalgatti",
    "wof:placetype":"locality"
},
  "geometry": {"coordinates":[75.07026,15.09871],"type":"Point"}
}