{
  "type": "Feature",
  "properties": {
    "gn:admin1_code":"24.0",
    "gn:admin2_code":"130",
    "gn:asciiname":"Dhol",
    "gn:country_code":"IN",
    "gn:dem":850,
    "gn:feature_class":"P",
    "gn:feature_code":"PPL",
    "gn:name":"Dhol",
    "gn:population":0,
    "gn:timezone":"Asia/Kolkata",
    "iso:country":"IN",
    "name:asm_x_preferred":[
        "\u09a2\u09cb\u09b2"
    ],
    "name:aze_x_preferred":[
        "Dol"
    ],
    "name:ben_x_preferred":[
        "\u09a2\u09cb\u09b2"
    ],
    "name:bih_x_preferred":[
        "\u0922\u094b\u0932"
    ],
    "name:deu_x_preferred":[
        "Dhol"
    ],
    "name:fas_x_preferred":[
        "\u062f\u0647\u0644"
    ],
    "name:fra_x_preferred":[
        "Dohol"
    ],
    "name:guj_x_preferred":[
        "\u0aa2\u0acb\u0ab2"
    ],
    "name:hye_x_preferred":[
        "\u0534\u0570\u0578\u056c"
    ],
    "name:hyw_x_preferred":[
        "\u054f\u0570\u0578\u056c"
    ],
    "name:ind_x_preferred":[
        "Marawis"
    ],
    "name:ita_x_preferred":[
        "Dhol"
    ],
    "name:mal_x_preferred":[
        "\u0d22\u0d4b\u0d7d"
    ],
    "name:mar_x_preferred":[
        "\u0922\u094b\u0932"
    ],
    "name:nep_x_preferred":[
        "\u0922\u094b\u0932"
    ],
    "name:nld_x_preferred":[
        "Dhol"
    ],
    "name:nno_x_preferred":[
        "Dhol"
    ],
    "name:pol_x_preferred":[
        "Dhol"
    ],
    "name:por_x_preferred":[
        "Mirwas"
    ],
    "name:rus_x_preferred":[
        "\u0414\u0445\u043e\u043b"
    ],
    "name:spa_x_preferred":[
        "Dhol"
    ],
    "name:sun_x_preferred":[
        "Marawis"
    ],
    "wof:name":"Dhol",
    "wof:placetype":"locality"
},
  "geometry": {"coordinates":[73.44003000000002,24.86849],"type":"Point"}
}