{
  "type": "Feature",
  "properties": {
    "gn:admin1_code":"24.0",
    "gn:admin2_code":"130",
    "gn:asciiname":"Dhol",
    "gn:country_code":"IN",
    "gn:dem":850,
    "gn:feature_class":"P",
    "gn:feature_code":"PPL",
    "gn:name":"Dhol",
    "gn:population":0,
    "gn:timezone":"Asia/Kolkata",
    "iso:country":"IN",
    "wof:name":"Dhol",
    "wof:placetype":"locality"
},
  "geometry": {"coordinates":[73.44003000000002,24.86849],"type":"Point"}
}