{
  "type": "Feature",
  "properties": {
    "iso:country":"IN",
    "ks:ks_alt_nam":"Gaddaguda thanda",
    "ks:ks_name":"Gaddaguda Thanda",
    "ks:ks_pop":392,
    "ks:ks_type":"HABITATION",
    "name:eng_x_preferred":[
        "Gaddaguda Thanda"
    ],
    "wof:name":"Gaddaguda Thanda",
    "wof:placetype":"locality",
    "wof:population":392
},
  "geometry": {"coordinates":[77.84282,18.228414],"type":"Point"}
}