{
  "type": "Feature",
  "properties": {
    "iso:country":"IN",
    "ks:ks_name":"Talyachiwadi",
    "ks:ks_pop":308,
    "ks:ks_type":"HABITATION",
    "name:eng_x_preferred":[
        "Talyachiwadi"
    ],
    "wof:name":"Talyachiwadi",
    "wof:placetype":"locality",
    "wof:population":308
},
  "geometry": {"coordinates":[73.064378,19.439898],"type":"Point"}
}