{
  "type": "Feature",
  "properties": {
    "iso:country":"IN",
    "ks:ks_name":"Kochariya",
    "ks:ks_pop":51,
    "ks:ks_type":"HABITATION",
    "name:eng_x_preferred":[
        "Kochariya"
    ],
    "wof:name":"Kochariya",
    "wof:placetype":"locality",
    "wof:population":51
},
  "geometry": {"coordinates":[73.338447,24.275617],"type":"Point"}
}