{
  "type": "Feature",
  "properties": {
    "iso:country":"IN",
    "ks:ks_name":"Kaliyam",
    "ks:ks_pop":318,
    "ks:ks_type":"VILLAGE",
    "name:eng_x_preferred":[
        "Kaliyam"
    ],
    "wof:name":"Kaliyam",
    "wof:placetype":"locality",
    "wof:population":318
},
  "geometry": {"coordinates":[86.448913,22.359754],"type":"Point"}
}