{
  "type": "Feature",
  "properties": {
    "gn:country":"IN",
    "gn:fcode":"PPL",
    "gn:pop":17403,
    "iso:country":"IN",
    "name:ben_x_preferred":[
        "\u09a8\u09b0\u09c7\u0997\u09be\u09b2"
    ],
    "name:bpy_x_preferred":[
        "\u09a8\u09b0\u09c7\u0997\u09be\u09b2"
    ],
    "name:bul_x_preferred":[
        "\u041d\u0430\u0440\u0435\u0433\u0430\u043b"
    ],
    "name:chi_x_preferred":[
        "\u7eb3\u96f7\u52a0\u5c14"
    ],
    "name:dut_x_preferred":[
        "Naregal"
    ],
    "name:eng_x_preferred":[
        "Naregal"
    ],
    "name:fre_x_preferred":[
        "Naregal"
    ],
    "name:ita_x_preferred":[
        "Naregal"
    ],
    "name:nan_x_preferred":[
        "Naregal"
    ],
    "name:new_x_preferred":[
        "\u0928\u0930\u0947\u0917\u093e\u0932"
    ],
    "name:por_x_preferred":[
        "Naregal"
    ],
    "name:swe_x_preferred":[
        "Naregal"
    ],
    "name:vie_x_preferred":[
        "Naregal"
    ],
    "qs:name":"Naregal",
    "qs:name_adm0":"India",
    "qs:name_adm1":"Karnataka",
    "qs:photos_9r":0,
    "qs:photos_sr":0,
    "qs:placetype":"Town",
    "qs:pop_sr":"6",
    "wd:wordcount":31,
    "wof:name":"Naregal",
    "wof:placetype":"locality",
    "wof:population":17403
},
  "geometry": {"coordinates":[75.80804000000001,15.57316],"type":"Point"}
}