{
  "type": "Feature",
  "properties": {
    "gn:admin1_code":"35",
    "gn:admin2_code":"447.0",
    "gn:asciiname":"Chillaur",
    "gn:country_code":"IN",
    "gn:dem":385,
    "gn:feature_class":"P",
    "gn:feature_code":"PPL",
    "gn:name":"Chillaur",
    "gn:population":0,
    "gn:timezone":"Asia/Kolkata",
    "iso:country":"IN",
    "wof:name":"Chillaur",
    "wof:placetype":"neighbourhood"
},
  "geometry": {"coordinates":[77.31504,21.84049],"type":"Point"}
}