{
  "type": "Feature",
  "properties": {
    "gn:admin1_code":"2",
    "gn:admin2_code":"549.0",
    "gn:asciiname":"Samarapadu",
    "gn:country_code":"IN",
    "gn:dem":59,
    "gn:feature_class":"P",
    "gn:feature_code":"PPL",
    "gn:name":"Samar\u0101p\u0101du",
    "gn:population":0,
    "gn:timezone":"Asia/Kolkata",
    "iso:country":"IN",
    "wof:name":"Samarapadu",
    "wof:placetype":"locality"
},
  "geometry": {"coordinates":[80.02531,16.05287],"type":"Point"}
}