{
  "type": "Feature",
  "properties": {
    "iso:country":"IN",
    "ks:ks_name":"Chak Bhikan",
    "ks:ks_pop":520,
    "ks:ks_type":"VILLAGE",
    "name:eng_x_preferred":[
        "Chak Bhikan"
    ],
    "wof:name":"Chak Bhikan",
    "wof:placetype":"locality",
    "wof:population":520
},
  "geometry": {"coordinates":[88.787612,25.190656],"type":"Point"}
}