{
  "type": "Feature",
  "properties": {
    "iso:country":"IN",
    "ks:ks_name":"Malia",
    "ks:ks_pop":2223,
    "ks:ks_type":"VILLAGE",
    "ks:ks_uagg_main":0,
    "name:eng_x_preferred":[
        "Malia"
    ],
    "wof:name":"Malia",
    "wof:placetype":"neighbourhood",
    "wof:population":2223
},
  "geometry": {"coordinates":[87.912722,22.528932],"type":"Point"}
}