{
  "type": "Feature",
  "properties": {
    "iso:country":"IN",
    "ks:ks_alt_nam":"Pipal faliya",
    "ks:ks_name":"Pipal Faliya",
    "ks:ks_pop":225,
    "ks:ks_type":"HABITATION",
    "name:eng_x_preferred":[
        "Pipal Faliya"
    ],
    "wof:name":"Pipal Faliya",
    "wof:placetype":"locality",
    "wof:population":225
},
  "geometry": {"coordinates":[73.275423,20.475627],"type":"Point"}
}