{
  "type": "Feature",
  "properties": {
    "iso:country":"IN",
    "ks:ks_name":"Dakshin Kalayanpur",
    "ks:ks_pop":643,
    "ks:ks_type":"VILLAGE",
    "name:eng_x_preferred":[
        "Dakshin Kalayanpur"
    ],
    "wof:name":"Dakshin Kalayanpur",
    "wof:placetype":"locality",
    "wof:population":643
},
  "geometry": {"coordinates":[87.650668,21.734647],"type":"Point"}
}