{
  "type": "Feature",
  "properties": {
    "iso:country":"IN",
    "ks:ks_name":"Purwa - Ram Sudh",
    "ks:ks_pop":315,
    "ks:ks_type":"HABITATION",
    "name:eng_x_preferred":[
        "Purwa - Ram Sudh"
    ],
    "wof:name":"Purwa - Ram Sudh",
    "wof:placetype":"locality",
    "wof:population":315
},
  "geometry": {"coordinates":[82.188975,27.375026],"type":"Point"}
}