{
  "type": "Feature",
  "properties": {
    "iso:country":"IN",
    "ks:ks_name":"Uyyalavada",
    "ks:ks_pop":122,
    "ks:ks_type":"HABITATION",
    "name:eng_x_preferred":[
        "Uyyalavada"
    ],
    "wof:name":"Uyyalavada",
    "wof:placetype":"locality",
    "wof:population":122
},
  "geometry": {"coordinates":[80.649238,17.624847],"type":"Point"}
}