{
  "type": "Feature",
  "properties": {
    "iso:country":"IN",
    "ks:ks_name":"3 K",
    "ks:ks_pop":339,
    "ks:ks_type":"HABITATION",
    "name:eng_x_preferred":[
        "3 K"
    ],
    "wof:name":"3 K",
    "wof:placetype":"locality",
    "wof:population":339
},
  "geometry": {"coordinates":[73.79926399999999,29.946122],"type":"Point"}
}