{
  "type": "Feature",
  "properties": {
    "iso:country":"IN",
    "ks:ks_name":"Chokiyapati",
    "ks:ks_pop":90,
    "ks:ks_type":"VILLAGE",
    "name:eng_x_preferred":[
        "Chokiyapati"
    ],
    "wof:name":"Chokiyapati",
    "wof:placetype":"locality",
    "wof:population":90
},
  "geometry": {"coordinates":[71.79005600000001,21.392833],"type":"Point"}
}