{
  "type": "Feature",
  "properties": {
    "iso:country":"IN",
    "ks:ks_alt_nam":"K\u0101dirpur",
    "ks:ks_alt_nam_2":"Kadirpur",
    "ks:ks_name":"Chak Harbansh",
    "ks:ks_pop":0,
    "ks:ks_type":"VILLAGE",
    "name:eng_x_preferred":[
        "Chak Harbansh"
    ],
    "name:eng_x_variant":[
        "K\u0101dirpur",
        "Kadirpur"
    ],
    "wof:name":"Chak Harbansh",
    "wof:placetype":"locality",
    "wof:population":0
},
  "geometry": {"coordinates":[83.623941,25.372233],"type":"Point"}
}