{
  "type": "Feature",
  "properties": {
    "iso:country":"IN",
    "ks:ks_name":"Jumbulingampettai",
    "ks:ks_pop":250,
    "ks:ks_type":"HABITATION",
    "ks:ks_uagg_main":0,
    "name:eng_x_preferred":[
        "Jumbulingampettai"
    ],
    "wof:name":"Jumbulingampettai",
    "wof:placetype":"neighbourhood",
    "wof:population":250
},
  "geometry": {"coordinates":[79.66483599999999,11.648701],"type":"Point"}
}