{
  "type": "Feature",
  "properties": {
    "gn:admin1_code":"35.0",
    "gn:admin2_code":"452.0",
    "gn:asciiname":"Chiria",
    "gn:country_code":"IN",
    "gn:dem":348,
    "gn:feature_class":"P",
    "gn:feature_code":"PPL",
    "gn:name":"Chiria",
    "gn:population":0,
    "gn:timezone":"Asia/Kolkata",
    "iso:country":"IN",
    "wof:name":"Chiria",
    "wof:placetype":"locality"
},
  "geometry": {"coordinates":[78.84338000000002,22.95697],"type":"Point"}
}