{
  "type": "Feature",
  "properties": {
    "gn:admin1_code":"35",
    "gn:admin2_code":"439.0",
    "gn:asciiname":"Manpura",
    "gn:country_code":"IN",
    "gn:dem":526,
    "gn:feature_class":"P",
    "gn:feature_code":"PPL",
    "gn:name":"M\u0101npura",
    "gn:population":0,
    "gn:timezone":"Asia/Kolkata",
    "iso:country":"IN",
    "wof:name":"Manpura",
    "wof:placetype":"locality"
},
  "geometry": {"coordinates":[75.51756999999998,22.68707],"type":"Point"}
}