{
  "type": "Feature",
  "properties": {
    "iso:country":"IN",
    "ks:ks_name":"Kiroli",
    "ks:ks_pop":229,
    "ks:ks_type":"VILLAGE",
    "name:eng_x_preferred":[
        "Kiroli"
    ],
    "wof:name":"Kiroli",
    "wof:placetype":"locality",
    "wof:population":229
},
  "geometry": {"coordinates":[79.931656,29.964945],"type":"Point"}
}