{
  "type": "Feature",
  "properties": {
    "gn:admin1_code":"16",
    "gn:admin2_code":"507.0",
    "gn:asciiname":"Umarpaili",
    "gn:country_code":"IN",
    "gn:dem":273,
    "gn:feature_class":"P",
    "gn:feature_code":"PPL",
    "gn:name":"Umarpaili",
    "gn:population":0,
    "gn:timezone":"Asia/Kolkata",
    "iso:country":"IN",
    "ks:ks_name":"Umarpayali",
    "ks:ks_pop":127,
    "ks:ks_type":"HABITATION",
    "name:eng_x_preferred":[
        "Umarpayali"
    ],
    "name:eng_x_variant":[
        "Umarpaili"
    ],
    "wof:name":"Umarpayali",
    "wof:placetype":"locality",
    "wof:population":127
},
  "geometry": {"coordinates":[80.209587,20.752478],"type":"Point"}
}