{
  "type": "Feature",
  "properties": {
    "gn:admin1_code":"36",
    "gn:admin2_code":"181.0",
    "gn:asciiname":"Rehli",
    "gn:country_code":"IN",
    "gn:dem":118,
    "gn:feature_class":"P",
    "gn:feature_code":"PPL",
    "gn:name":"Rehli",
    "gn:population":0,
    "gn:timezone":"Asia/Kolkata",
    "iso:country":"IN",
    "name:ben_x_preferred":[
        "\u09b0\u09c7\u09b9\u09b2\u09bf"
    ],
    "name:bpy_x_preferred":[
        "\u09b0\u09c7\u09b9\u09b2\u09bf"
    ],
    "name:ceb_x_preferred":[
        "Rehl\u012b"
    ],
    "name:hif_x_preferred":[
        "Rehli"
    ],
    "name:ita_x_preferred":[
        "Rehli"
    ],
    "name:msa_x_preferred":[
        "Rehli"
    ],
    "name:ori_x_preferred":[
        "\u0b30\u0b47\u0b39\u0b32\u0b3f"
    ],
    "name:por_x_preferred":[
        "Rehli"
    ],
    "name:spa_x_preferred":[
        "Rehli"
    ],
    "name:swe_x_preferred":[
        "Rehl\u012b"
    ],
    "name:vie_x_preferred":[
        "Rehli"
    ],
    "name:zho_x_preferred":[
        "\u96f7\u8d6b\u5229"
    ],
    "wof:name":"Rehli",
    "wof:placetype":"locality"
},
  "geometry": {"coordinates":[81.97329000000001,27.67114],"type":"Point"}
}