{
  "type": "Feature",
  "properties": {
    "iso:country":"IN",
    "ks:ks_alt_nam":"p dukaling",
    "ks:ks_name":"p Dukaling",
    "ks:ks_pop":79,
    "ks:ks_type":"HABITATION",
    "name:eng_x_preferred":[
        "p Dukaling"
    ],
    "wof:name":"p Dukaling",
    "wof:placetype":"locality",
    "wof:population":79
},
  "geometry": {"coordinates":[93.201679,25.283092],"type":"Point"}
}