{
  "type": "Feature",
  "properties": {
    "gn:admin1_code":"35",
    "gn:admin2_code":"420.0",
    "gn:asciiname":"Ranjitsingh ka Pura",
    "gn:country_code":"IN",
    "gn:dem":162,
    "gn:feature_class":"P",
    "gn:feature_code":"PPL",
    "gn:name":"Ranj\u012btsingh ka Pura",
    "gn:population":0,
    "gn:timezone":"Asia/Kolkata",
    "iso:country":"IN",
    "wof:name":"Ranjitsingh ka Pura",
    "wof:placetype":"locality"
},
  "geometry": {"coordinates":[78.51526,26.52213],"type":"Point"}
}