{
  "type": "Feature",
  "properties": {
    "iso:country":"IN",
    "ks:ks_name":"Lakshmiwada",
    "ks:ks_pop":1067,
    "ks:ks_type":"VILLAGE",
    "name:eng_x_preferred":[
        "Lakshmiwada"
    ],
    "wof:name":"Lakshmiwada",
    "wof:placetype":"locality",
    "wof:population":1067
},
  "geometry": {"coordinates":[82.107721,16.57963],"type":"Point"}
}