{
  "type": "Feature",
  "properties": {
    "iso:country":"IN",
    "ks:ks_name":"Baladia",
    "ks:ks_pop":238,
    "ks:ks_type":"VILLAGE",
    "ks:ks_uagg_main":0,
    "name:eng_x_preferred":[
        "Baladia"
    ],
    "wof:name":"Baladia",
    "wof:placetype":"neighbourhood",
    "wof:population":238
},
  "geometry": {"coordinates":[86.644142,21.279341],"type":"Point"}
}