{
  "type": "Feature",
  "properties": {
    "iso:country":"IN",
    "ks:ks_name":"Bhoiwadi",
    "ks:ks_pop":74,
    "ks:ks_type":"HABITATION",
    "name:eng_x_preferred":[
        "Bhoiwadi"
    ],
    "wof:name":"Bhoiwadi",
    "wof:placetype":"locality",
    "wof:population":74
},
  "geometry": {"coordinates":[73.405681,17.609264],"type":"Point"}
}