{
  "type": "Feature",
  "properties": {
    "gn:admin1_code":"36",
    "gn:admin2_code":"134.0",
    "gn:asciiname":"Narayanpur",
    "gn:country_code":"IN",
    "gn:dem":237,
    "gn:feature_class":"P",
    "gn:feature_code":"PPL",
    "gn:name":"N\u0101r\u0101yanpur",
    "gn:population":0,
    "gn:timezone":"Asia/Kolkata",
    "iso:country":"IN",
    "name:und_x_variant":[
        "N\u0101r\u0101yanpur",
        "Rustampur Sher"
    ],
    "wof:name":"Narayanpur",
    "wof:placetype":"locality"
},
  "geometry": {"coordinates":[78.32835,29.32884],"type":"Point"}
}