{
  "type": "Feature",
  "properties": {
    "iso:country":"IN",
    "ks:ks_name":"Padra",
    "ks:ks_pop":279,
    "ks:ks_type":"VILLAGE",
    "name:eng_x_preferred":[
        "Padra"
    ],
    "wof:name":"Padra",
    "wof:placetype":"locality",
    "wof:population":279
},
  "geometry": {"coordinates":[74.448725,23.749803],"type":"Point"}
}