{
  "type": "Feature",
  "properties": {
    "iso:country":"IN",
    "ks:ks_name":"Talwadi",
    "ks:ks_pop":91,
    "ks:ks_type":"HABITATION",
    "name:eng_x_preferred":[
        "Talwadi"
    ],
    "wof:name":"Talwadi",
    "wof:placetype":"locality",
    "wof:population":91
},
  "geometry": {"coordinates":[73.602154,16.780281],"type":"Point"}
}