{
  "type": "Feature",
  "properties": {
    "iso:country":"IN",
    "ks:ks_alt_nam":"upper tola",
    "ks:ks_name":"Upper Tola",
    "ks:ks_pop":200,
    "ks:ks_type":"HABITATION",
    "name:eng_x_preferred":[
        "Upper Tola"
    ],
    "wof:name":"Upper Tola",
    "wof:placetype":"locality",
    "wof:population":200
},
  "geometry": {"coordinates":[86.400392,24.605603],"type":"Point"}
}