{
  "type": "Feature",
  "properties": {
    "iso:country":"IN",
    "ks:ks_name":"Mandau",
    "ks:ks_pop":1010,
    "ks:ks_type":"HABITATION",
    "name:eng_x_preferred":[
        "Mandau"
    ],
    "wof:name":"Mandau",
    "wof:placetype":"locality",
    "wof:population":1010
},
  "geometry": {"coordinates":[71.08213499999999,27.224188],"type":"Point"}
}