{
  "type": "Feature",
  "properties": {
    "gn:admin1_code":"21.0",
    "gn:admin2_code":"398.0",
    "gn:asciiname":"Maliguda",
    "gn:country_code":"IN",
    "gn:dem":858,
    "gn:feature_class":"P",
    "gn:feature_code":"PPL",
    "gn:name":"Maliguda",
    "gn:population":0,
    "gn:timezone":"Asia/Kolkata",
    "iso:country":"IN",
    "ks:ks_name":"Baliguda",
    "ks:ks_pop":79,
    "ks:ks_type":"HABITATION",
    "name:eng_x_preferred":[
        "Baliguda"
    ],
    "name:eng_x_variant":[
        "Maliguda"
    ],
    "wof:name":"Baliguda",
    "wof:placetype":"locality",
    "wof:population":79
},
  "geometry": {"coordinates":[82.858559,18.838395],"type":"Point"}
}