{
  "type": "Feature",
  "properties": {
    "gn:admin1_code":"21.0",
    "gn:admin2_code":"398.0",
    "gn:asciiname":"Maliguda",
    "gn:country_code":"IN",
    "gn:dem":858,
    "gn:feature_class":"P",
    "gn:feature_code":"PPL",
    "gn:name":"Maliguda",
    "gn:population":0,
    "gn:timezone":"Asia/Kolkata",
    "iso:country":"IN",
    "wof:name":"Maliguda",
    "wof:placetype":"locality"
},
  "geometry": {"coordinates":[82.85328,18.8499],"type":"Point"}
}