{
  "type": "Feature",
  "properties": {
    "iso:country":"IN",
    "ks:ks_name":"Thoratwasti",
    "ks:ks_pop":167,
    "ks:ks_type":"HABITATION",
    "name:eng_x_preferred":[
        "Thoratwasti"
    ],
    "wof:name":"Thoratwasti",
    "wof:placetype":"locality",
    "wof:population":167
},
  "geometry": {"coordinates":[74.586016,18.908168],"type":"Point"}
}