{
  "type": "Feature",
  "properties": {
    "iso:country":"IN",
    "ks:ks_name":"Monkala",
    "ks:ks_pop":145,
    "ks:ks_type":"VILLAGE",
    "name:eng_x_preferred":[
        "Monkala"
    ],
    "wof:name":"Monkala",
    "wof:placetype":"locality",
    "wof:population":145
},
  "geometry": {"coordinates":[90.228099,26.072196],"type":"Point"}
}