{
  "type": "Feature",
  "properties": {
    "iso:country":"IN",
    "ks:ks_name":"Singi Khasmahal",
    "ks:ks_pop":1463,
    "ks:ks_type":"VILLAGE",
    "name:eng_x_preferred":[
        "Singi Khasmahal"
    ],
    "wof:name":"Singi Khasmahal",
    "wof:placetype":"locality",
    "wof:population":1463
},
  "geometry": {"coordinates":[88.51076399999999,26.998571],"type":"Point"}
}