{
  "type": "Feature",
  "properties": {
    "iso:country":"IN",
    "ks:ks_name":"Madauka",
    "ks:ks_pop":139,
    "ks:ks_type":"VILLAGE",
    "ks:ks_uagg_main":0,
    "name:eng_x_preferred":[
        "Madauka"
    ],
    "wof:name":"Madauka",
    "wof:placetype":"neighbourhood",
    "wof:population":139
},
  "geometry": {"coordinates":[86.929062,21.954504],"type":"Point"}
}