{
  "type": "Feature",
  "properties": {
    "iso:country":"IN",
    "ks:ks_name":"Dhangulai Pathar",
    "ks:ks_pop":492,
    "ks:ks_type":"VILLAGE",
    "ks:ks_uagg_main":0,
    "name:eng_x_preferred":[
        "Dhangulai Pathar"
    ],
    "wof:name":"Dhangulai Pathar",
    "wof:placetype":"neighbourhood",
    "wof:population":492
},
  "geometry": {"coordinates":[93.90708100000001,26.937896],"type":"Point"}
}