{
  "type": "Feature",
  "properties": {
    "iso:country":"IN",
    "ks:ks_name":"S C Para",
    "ks:ks_pop":472,
    "ks:ks_type":"HABITATION",
    "name:eng_x_preferred":[
        "S C Para"
    ],
    "wof:name":"S C Para",
    "wof:placetype":"locality",
    "wof:population":472
},
  "geometry": {"coordinates":[91.97446100000001,24.137166],"type":"Point"}
}