{
  "type": "Feature",
  "properties": {
    "iso:country":"IN",
    "ks:ks_name":"Bharat Pura",
    "ks:ks_pop":368,
    "ks:ks_type":"VILLAGE",
    "name:eng_x_preferred":[
        "Bharat Pura"
    ],
    "wof:name":"Bharat Pura",
    "wof:placetype":"locality",
    "wof:population":368
},
  "geometry": {"coordinates":[78.09819299999999,24.434589],"type":"Point"}
}