{
  "type": "Feature",
  "properties": {
    "gn:admin1_code":"11",
    "gn:admin2_code":"27.0",
    "gn:asciiname":"Nosa",
    "gn:country_code":"IN",
    "gn:dem":1386,
    "gn:feature_class":"P",
    "gn:feature_code":"PPL",
    "gn:name":"Nosa",
    "gn:population":0,
    "gn:timezone":"Asia/Kolkata",
    "iso:country":"IN",
    "name:ceb_x_preferred":[
        "Nosa"
    ],
    "wof:name":"Nosa",
    "wof:placetype":"locality"
},
  "geometry": {"coordinates":[76.86839999999999,31.93367000000001],"type":"Point"}
}