{
  "type": "Feature",
  "properties": {
    "gn:admin1_code":"36",
    "gn:admin2_code":"173.0",
    "gn:asciiname":"Birahimpur",
    "gn:country_code":"IN",
    "gn:dem":105,
    "gn:feature_class":"P",
    "gn:feature_code":"PPL",
    "gn:name":"Bir\u0101himpur",
    "gn:population":0,
    "gn:timezone":"Asia/Kolkata",
    "iso:country":"IN",
    "name:und_x_variant":[
        "Bir\u0101himpur",
        "Sar\u0101i B\u0101rmati"
    ],
    "wof:name":"Birahimpur",
    "wof:placetype":"neighbourhood"
},
  "geometry": {"coordinates":[81.66907,25.91964],"type":"Point"}
}