{
  "type": "Feature",
  "properties": {
    "iso:country":"IN",
    "ks:ks_name":"Hamir Bhadha",
    "ks:ks_pop":535,
    "ks:ks_type":"HABITATION",
    "name:eng_x_preferred":[
        "Hamir Bhadha"
    ],
    "wof:name":"Hamir Bhadha",
    "wof:placetype":"locality",
    "wof:population":535
},
  "geometry": {"coordinates":[70.87478900000001,23.519908],"type":"Point"}
}