{
  "type": "Feature",
  "properties": {
    "iso:country":"IN",
    "ks:ks_name":"Katia Chapari",
    "ks:ks_pop":328,
    "ks:ks_type":"VILLAGE",
    "name:eng_x_preferred":[
        "Katia Chapari"
    ],
    "wof:name":"Katia Chapari",
    "wof:placetype":"locality",
    "wof:population":328
},
  "geometry": {"coordinates":[92.889054,26.570215],"type":"Point"}
}