{
  "type": "Feature",
  "properties": {
    "iso:country":"IN",
    "ks:ks_name":"Matewadi",
    "ks:ks_pop":701,
    "ks:ks_type":"HABITATION",
    "name:eng_x_preferred":[
        "Matewadi"
    ],
    "wof:name":"Matewadi",
    "wof:placetype":"locality",
    "wof:population":701
},
  "geometry": {"coordinates":[75.122934,20.093681],"type":"Point"}
}