{
  "type": "Feature",
  "properties": {
    "iso:country":"IN",
    "ks:ks_name":"Dakhin Tola",
    "ks:ks_pop":240,
    "ks:ks_type":"HABITATION",
    "name:eng_x_preferred":[
        "Dakhin Tola"
    ],
    "wof:name":"Dakhin Tola",
    "wof:placetype":"locality",
    "wof:population":240
},
  "geometry": {"coordinates":[84.161591,26.150373],"type":"Point"}
}