{
  "type": "Feature",
  "properties": {
    "iso:country":"IN",
    "ks:ks_name":"Katansalaiya",
    "ks:ks_pop":86,
    "ks:ks_type":"VILLAGE",
    "name:eng_x_preferred":[
        "Katansalaiya"
    ],
    "wof:name":"Katansalaiya",
    "wof:placetype":"locality",
    "wof:population":86
},
  "geometry": {"coordinates":[82.05174,24.805141],"type":"Point"}
}