{
  "type": "Feature",
  "properties": {
    "iso:country":"IN",
    "ks:ks_alt_nam":"D\u0101r\u0101pur",
    "ks:ks_name":"Darapur",
    "ks:ks_type":"VILLAGE",
    "name:eng_x_preferred":[
        "Darapur"
    ],
    "name:eng_x_variant":[
        "D\u0101r\u0101pur"
    ],
    "wof:name":"Darapur",
    "wof:placetype":"locality"
},
  "geometry": {"coordinates":[77.47130300000001,21.241411],"type":"Point"}
}