{
  "type": "Feature",
  "properties": {
    "gn:admin1_code":"25.0",
    "gn:admin2_code":"629.0",
    "gn:asciiname":"Alanchi",
    "gn:country_code":"IN",
    "gn:dem":64,
    "gn:feature_class":"P",
    "gn:feature_code":"PPL",
    "gn:name":"Alanchi",
    "gn:population":0,
    "gn:timezone":"Asia/Kolkata",
    "iso:country":"IN",
    "name:fas_x_preferred":[
        "\u0627\u0644\u0627\u0646\u0686\u06cc"
    ],
    "name:tam_x_preferred":[
        "\u0b86\u0bb2\u0b9e\u0bcd\u0b9a\u0bbf"
    ],
    "name:und_x_variant":[
        "Alanchy"
    ],
    "wof:name":"Alanchi",
    "wof:placetype":"locality"
},
  "geometry": {"coordinates":[77.23577,8.19722],"type":"Point"}
}