{
  "type": "Feature",
  "properties": {
    "gn:admin1_code":"19.0",
    "gn:admin2_code":"582.0",
    "gn:asciiname":"Bandarlahalli",
    "gn:country_code":"IN",
    "gn:dem":772,
    "gn:feature_class":"P",
    "gn:feature_code":"PPL",
    "gn:name":"Bandarlahalli",
    "gn:population":0,
    "gn:timezone":"Asia/Kolkata",
    "iso:country":"IN",
    "wof:name":"Bandarlahalli",
    "wof:placetype":"neighbourhood"
},
  "geometry": {"coordinates":[77.51721000000001,13.45435],"type":"Point"}
}