{
  "type": "Feature",
  "properties": {
    "gn:admin1_code":"16",
    "gn:admin2_code":"525.0",
    "gn:asciiname":"Thair",
    "gn:country_code":"IN",
    "gn:dem":651,
    "gn:feature_class":"P",
    "gn:feature_code":"PPL",
    "gn:name":"Thair",
    "gn:population":0,
    "gn:timezone":"Asia/Kolkata",
    "iso:country":"IN",
    "name:und_x_variant":[
        "Ter",
        "Tair",
        "Ther",
        "Thair"
    ],
    "wof:name":"Thair",
    "wof:placetype":"neighbourhood"
},
  "geometry": {"coordinates":[76.14100999999999,18.31996],"type":"Point"}
}