{
  "type": "Feature",
  "properties": {
    "iso:country":"IN",
    "ks:ks_name":"Wagjainagar",
    "ks:ks_pop":102,
    "ks:ks_type":"HABITATION",
    "name:eng_x_preferred":[
        "Wagjainagar"
    ],
    "wof:name":"Wagjainagar",
    "wof:placetype":"locality",
    "wof:population":102
},
  "geometry": {"coordinates":[73.844544,18.1338],"type":"Point"}
}