{
  "type": "Feature",
  "properties": {
    "iso:country":"IN",
    "ks:ks_name":"Chanvai Fa",
    "ks:ks_pop":808,
    "ks:ks_type":"HABITATION",
    "name:eng_x_preferred":[
        "Chanvai Fa"
    ],
    "wof:name":"Chanvai Fa",
    "wof:placetype":"locality",
    "wof:population":808
},
  "geometry": {"coordinates":[72.937917,20.447278],"type":"Point"}
}