{
  "type": "Feature",
  "properties": {
    "gn:admin1_code":"2.0",
    "gn:admin2_code":"551.0",
    "gn:asciiname":"Diguvakonetivandlapalle",
    "gn:country_code":"IN",
    "gn:dem":316,
    "gn:feature_class":"P",
    "gn:feature_code":"PPL",
    "gn:name":"Diguvakonetiv\u0101ndlapalle",
    "gn:population":0,
    "gn:timezone":"Asia/Kolkata",
    "iso:country":"IN",
    "wof:name":"Diguvakonetivandlapalle",
    "wof:placetype":"neighbourhood"
},
  "geometry": {"coordinates":[78.88256,14.10681],"type":"Point"}
}