{
  "type": "Feature",
  "properties": {
    "iso:country":"IN",
    "ks:ks_alt_nam":"Lew\u0101banwaria",
    "ks:ks_name":"Lewabanwaria",
    "ks:ks_pop":196,
    "ks:ks_type":"VILLAGE",
    "name:eng_x_preferred":[
        "Lewabanwaria"
    ],
    "name:eng_x_variant":[
        "Lew\u0101banwaria"
    ],
    "wof:name":"Lewabanwaria",
    "wof:placetype":"locality",
    "wof:population":196
},
  "geometry": {"coordinates":[86.10100799999999,24.662962],"type":"Point"}
}