{
  "type": "Feature",
  "properties": {
    "iso:country":"IN",
    "ks:ks_name":"Machhethira Family",
    "ks:ks_pop":32,
    "ks:ks_type":"HABITATION",
    "name:eng_x_preferred":[
        "Machhethira Family"
    ],
    "wof:name":"Machhethira Family",
    "wof:placetype":"locality",
    "wof:population":32
},
  "geometry": {"coordinates":[75.801389,12.268889],"type":"Point"}
}