{
  "type": "Feature",
  "properties": {
    "iso:country":"IN",
    "ks:ks_name":"Patewa Tola",
    "ks:ks_pop":101,
    "ks:ks_type":"HABITATION",
    "name:eng_x_preferred":[
        "Patewa Tola"
    ],
    "wof:name":"Patewa Tola",
    "wof:placetype":"locality",
    "wof:population":101
},
  "geometry": {"coordinates":[87.63185300000001,26.207785],"type":"Point"}
}