{
  "type": "Feature",
  "properties": {
    "gn:admin1_code":"36",
    "gn:admin2_code":"191.0",
    "gn:asciiname":"Yahiapur",
    "gn:country_code":"IN",
    "gn:dem":85,
    "gn:feature_class":"P",
    "gn:feature_code":"PPL",
    "gn:name":"Yahi\u0101pur",
    "gn:population":0,
    "gn:timezone":"Asia/Kolkata",
    "iso:country":"IN",
    "ks:ks_alt_nam":"Yahi\u0101pur",
    "ks:ks_name":"Yahiapur",
    "ks:ks_type":"VILLAGE",
    "ks:ks_uagg_main":0,
    "name:eng_x_preferred":[
        "Yahiapur"
    ],
    "name:eng_x_variant":[
        "Yahi\u0101pur"
    ],
    "wof:name":"Yahiapur",
    "wof:placetype":"neighbourhood"
},
  "geometry": {"coordinates":[83.06544599999999,26.041682],"type":"Point"}
}