{
  "type": "Feature",
  "properties": {
    "iso:country":"IN",
    "ks:ks_name":"Waghbil",
    "ks:ks_pop":32,
    "ks:ks_type":"HABITATION",
    "name:eng_x_preferred":[
        "Waghbil"
    ],
    "wof:name":"Waghbil",
    "wof:placetype":"locality",
    "wof:population":32
},
  "geometry": {"coordinates":[73.446158,16.337403],"type":"Point"}
}