{
  "type": "Feature",
  "properties": {
    "iso:country":"IN",
    "ks:ks_name":"Benipali",
    "ks:ks_pop":100,
    "ks:ks_type":"VILLAGE",
    "name:eng_x_preferred":[
        "Benipali"
    ],
    "wof:name":"Benipali",
    "wof:placetype":"locality",
    "wof:population":100
},
  "geometry": {"coordinates":[83.395954,20.763474],"type":"Point"}
}