{
  "type": "Feature",
  "properties": {
    "gn:admin1_code":"23.0",
    "gn:admin2_code":"053",
    "gn:asciiname":"Rurki Khurd",
    "gn:country_code":"IN",
    "gn:dem":257,
    "gn:feature_class":"P",
    "gn:feature_code":"PPL",
    "gn:name":"R\u016brki Khurd",
    "gn:population":0,
    "gn:timezone":"Asia/Kolkata",
    "iso:country":"IN",
    "wof:name":"Rurki Khurd",
    "wof:placetype":"locality"
},
  "geometry": {"coordinates":[76.04644999999999,30.55146],"type":"Point"}
}