{
  "type": "Feature",
  "properties": {
    "iso:country":"IN",
    "ks:ks_name":"Ghar",
    "ks:ks_pop":4160,
    "ks:ks_type":"VILLAGE",
    "name:eng_x_preferred":[
        "Ghar"
    ],
    "wof:name":"Ghar",
    "wof:placetype":"locality",
    "wof:population":4160
},
  "geometry": {"coordinates":[75.688056,25.865986],"type":"Point"}
}