{
  "type": "Feature",
  "properties": {
    "iso:country":"IN",
    "ks:ks_name":"Arenoor",
    "ks:ks_pop":306,
    "ks:ks_type":"VILLAGE",
    "name:eng_x_preferred":[
        "Arenoor"
    ],
    "wof:name":"Arenoor",
    "wof:placetype":"locality",
    "wof:population":306
},
  "geometry": {"coordinates":[75.60324,13.281226],"type":"Point"}
}