{
  "type": "Feature",
  "properties": {
    "gn:admin1_code":"2",
    "gn:admin2_code":"545.0",
    "gn:asciiname":"Kumkamamidi",
    "gn:country_code":"IN",
    "gn:dem":700,
    "gn:feature_class":"P",
    "gn:feature_code":"PPL",
    "gn:name":"Kumkam\u0101midi",
    "gn:population":0,
    "gn:timezone":"Asia/Kolkata",
    "iso:country":"IN",
    "ks:ks_name":"Kunkumamidi",
    "ks:ks_pop":13,
    "ks:ks_type":"HABITATION",
    "name:eng_x_preferred":[
        "Kunkumamidi"
    ],
    "name:eng_x_variant":[
        "Kumkamamidi"
    ],
    "wof:name":"Kunkumamidi",
    "wof:placetype":"locality",
    "wof:population":13
},
  "geometry": {"coordinates":[81.840712,17.70585],"type":"Point"}
}