{
  "type": "Feature",
  "properties": {
    "gn:admin1_code":"36.0",
    "gn:admin2_code":"190.0",
    "gn:asciiname":"Pipra Bandh",
    "gn:country_code":"IN",
    "gn:dem":73,
    "gn:feature_class":"P",
    "gn:feature_code":"PPL",
    "gn:name":"Pipra Bandh",
    "gn:population":0,
    "gn:timezone":"Asia/Kolkata",
    "iso:country":"IN",
    "wof:name":"Pipra Bandh",
    "wof:placetype":"locality"
},
  "geometry": {"coordinates":[83.88020999999998,26.22148],"type":"Point"}
}