{
  "type": "Feature",
  "properties": {
    "gn:admin1_code":"34.0",
    "gn:admin2_code":"236.0",
    "gn:asciiname":"Kadirganj",
    "gn:country_code":"IN",
    "gn:dem":199,
    "gn:feature_class":"P",
    "gn:feature_code":"PPL",
    "gn:name":"K\u0101dirganj",
    "gn:population":0,
    "gn:timezone":"Asia/Kolkata",
    "iso:country":"IN",
    "ks:ks_name":"Kadirganj",
    "ks:ks_pop":1025,
    "ks:ks_type":"HABITATION",
    "name:eng_x_preferred":[
        "Kadirganj"
    ],
    "wof:name":"Kadirganj",
    "wof:placetype":"locality",
    "wof:population":1025
},
  "geometry": {"coordinates":[84.548821,24.467243],"type":"Point"}
}