{
  "type": "Feature",
  "properties": {
    "iso:country":"IN",
    "ks:ks_name":"Bhutkudar",
    "ks:ks_pop":390,
    "ks:ks_type":"HABITATION",
    "name:eng_x_preferred":[
        "Bhutkudar"
    ],
    "wof:name":"Bhutkudar",
    "wof:placetype":"locality",
    "wof:population":390
},
  "geometry": {"coordinates":[84.366612,22.437447],"type":"Point"}
}