{
  "type": "Feature",
  "properties": {
    "iso:country":"IN",
    "ks:ks_name":"Bhurkul",
    "ks:ks_pop":654,
    "ks:ks_type":"VILLAGE",
    "ks:ks_uagg_main":0,
    "name:eng_x_preferred":[
        "Bhurkul"
    ],
    "wof:name":"Bhurkul",
    "wof:placetype":"locality",
    "wof:population":654
},
  "geometry": {"coordinates":[88.460446,22.386521],"type":"Point"}
}