{
  "type": "Feature",
  "properties": {
    "gn:admin1_code":"10",
    "gn:admin2_code":"84.0",
    "gn:asciiname":"Suretimawarena",
    "gn:country_code":"IN",
    "gn:dem":301,
    "gn:feature_class":"P",
    "gn:feature_code":"PPL",
    "gn:name":"Suret\u012bmawarena",
    "gn:population":0,
    "gn:timezone":"Asia/Kolkata",
    "iso:country":"IN",
    "wof:name":"Suretimawarena",
    "wof:placetype":"locality"
},
  "geometry": {"coordinates":[75.95318,28.34016],"type":"Point"}
}