{
  "type": "Feature",
  "properties": {
    "iso:country":"IN",
    "ks:ks_name":"Kobbaiguda",
    "ks:ks_pop":60,
    "ks:ks_type":"HABITATION",
    "name:eng_x_preferred":[
        "Kobbaiguda"
    ],
    "wof:name":"Kobbaiguda",
    "wof:placetype":"locality",
    "wof:population":60
},
  "geometry": {"coordinates":[78.602408,19.501962],"type":"Point"}
}