{
  "type": "Feature",
  "properties": {
    "iso:country":"IN",
    "ks:ks_name":"Kebbodi",
    "ks:ks_pop":130,
    "ks:ks_type":"HABITATION",
    "name:eng_x_preferred":[
        "Kebbodi"
    ],
    "wof:name":"Kebbodi",
    "wof:placetype":"locality",
    "wof:population":130
},
  "geometry": {"coordinates":[75.560464,12.691382],"type":"Point"}
}