{
  "type": "Feature",
  "properties": {
    "iso:country":"IN",
    "ks:ks_name":"Rajjanpur",
    "ks:ks_pop":198,
    "ks:ks_type":"VILLAGE",
    "name:eng_x_preferred":[
        "Rajjanpur"
    ],
    "wof:name":"Rajjanpur",
    "wof:placetype":"locality",
    "wof:population":198
},
  "geometry": {"coordinates":[83.49811099999999,25.977693],"type":"Point"}
}