{
  "type": "Feature",
  "properties": {
    "iso:country":"IN",
    "ks:ks_alt_nam":"SHANKERPUR",
    "ks:ks_name":"Shankerpur",
    "ks:ks_pop":181,
    "ks:ks_type":"HABITATION",
    "name:eng_x_preferred":[
        "Shankerpur"
    ],
    "wof:name":"Shankerpur",
    "wof:placetype":"locality",
    "wof:population":181
},
  "geometry": {"coordinates":[85.952567,26.084248],"type":"Point"}
}