{
  "type": "Feature",
  "properties": {
    "iso:country":"IN",
    "ks:ks_name":"Kalikapur Machhamartola",
    "ks:ks_pop":1127,
    "ks:ks_type":"HABITATION",
    "name:eng_x_preferred":[
        "Kalikapur Machhamartola"
    ],
    "wof:name":"Kalikapur Machhamartola",
    "wof:placetype":"locality",
    "wof:population":1127
},
  "geometry": {"coordinates":[83.518676,23.940066],"type":"Point"}
}