{
  "type": "Feature",
  "properties": {
    "iso:country":"IN",
    "ks:ks_alt_nam":"Karu keelatheru",
    "ks:ks_name":"Karu Keelatheru",
    "ks:ks_pop":360,
    "ks:ks_type":"HABITATION",
    "name:eng_x_preferred":[
        "Karu Keelatheru"
    ],
    "wof:name":"Karu Keelatheru",
    "wof:placetype":"locality",
    "wof:population":360
},
  "geometry": {"coordinates":[79.125541,10.390461],"type":"Point"}
}