{
  "type": "Feature",
  "properties": {
    "gn:admin1_code":"36",
    "gn:admin2_code":"191.0",
    "gn:asciiname":"Jafarpur Kathkan",
    "gn:country_code":"IN",
    "gn:dem":88,
    "gn:feature_class":"P",
    "gn:feature_code":"PPL",
    "gn:name":"J\u0101farpur Kathk\u0101n",
    "gn:population":0,
    "gn:timezone":"Asia/Kolkata",
    "iso:country":"IN",
    "ks:ks_name":"Jafarpur Kathakan",
    "ks:ks_pop":955,
    "ks:ks_type":"VILLAGE",
    "ks:ks_uagg_main":0,
    "name:eng_x_preferred":[
        "Jafarpur Kathakan"
    ],
    "wof:name":"Jafarpur Kathakan",
    "wof:placetype":"neighbourhood",
    "wof:population":955
},
  "geometry": {"coordinates":[82.724619,26.105433],"type":"Point"}
}