{
  "type": "Feature",
  "properties": {
    "iso:country":"IN",
    "ks:ks_alt_nam":"BARKI BARA TAR",
    "ks:ks_name":"Barki Bara Tar",
    "ks:ks_pop":300,
    "ks:ks_type":"HABITATION",
    "name:eng_x_preferred":[
        "Barki Bara Tar"
    ],
    "wof:name":"Barki Bara Tar",
    "wof:placetype":"locality",
    "wof:population":300
},
  "geometry": {"coordinates":[85.671181,24.637594],"type":"Point"}
}