{
  "type": "Feature",
  "properties": {
    "iso:country":"IN",
    "ks:ks_name":"Luhurenpali",
    "ks:ks_pop":80,
    "ks:ks_type":"HABITATION",
    "name:eng_x_preferred":[
        "Luhurenpali"
    ],
    "wof:name":"Luhurenpali",
    "wof:placetype":"locality",
    "wof:population":80
},
  "geometry": {"coordinates":[83.61529400000001,20.630111],"type":"Point"}
}