{
  "type": "Feature",
  "properties": {
    "iso:country":"IN",
    "ks:ks_name":"Iswarpur",
    "ks:ks_pop":885,
    "ks:ks_type":"VILLAGE",
    "ks:ks_uagg_main":0,
    "name:eng_x_preferred":[
        "Iswarpur"
    ],
    "wof:name":"Iswarpur",
    "wof:placetype":"neighbourhood",
    "wof:population":885
},
  "geometry": {"coordinates":[86.810777,20.696925],"type":"Point"}
}