{
  "type": "Feature",
  "properties": {
    "iso:country":"IN",
    "ks:ks_name":"Gahirjor",
    "ks:ks_pop":165,
    "ks:ks_type":"VILLAGE",
    "name:eng_x_preferred":[
        "Gahirjor"
    ],
    "wof:name":"Gahirjor",
    "wof:placetype":"locality",
    "wof:population":165
},
  "geometry": {"coordinates":[86.37942099999999,24.302569],"type":"Point"}
}