{
  "type": "Feature",
  "properties": {
    "gn:admin1_code":"36",
    "gn:admin2_code":"202.0",
    "gn:asciiname":"Shekhpura",
    "gn:country_code":"IN",
    "gn:dem":167,
    "gn:feature_class":"P",
    "gn:feature_code":"PPL",
    "gn:name":"Shekhpura",
    "gn:population":0,
    "gn:timezone":"Asia/Kolkata",
    "iso:country":"IN",
    "name:ben_x_preferred":[
        "\u09b6\u09c7\u0996\u09b0\u09aa\u09c1\u09b0\u09be"
    ],
    "name:bpy_x_preferred":[
        "\u09b6\u09c7\u0996\u09b0\u09aa\u09c1\u09b0\u09be"
    ],
    "name:ita_x_preferred":[
        "Shekhpura"
    ],
    "name:msa_x_preferred":[
        "Shekhpura"
    ],
    "name:nld_x_preferred":[
        "Shekhpura"
    ],
    "name:por_x_preferred":[
        "Shekhpura"
    ],
    "name:vie_x_preferred":[
        "Shekhpura"
    ],
    "name:zho_x_preferred":[
        "\u65af\u8d6b\u514b\u666e\u62c9"
    ],
    "wof:name":"Shekhpura",
    "wof:placetype":"locality"
},
  "geometry": {"coordinates":[78.94571999999999,27.63086],"type":"Point"}
}