{
  "type": "Feature",
  "properties": {
    "gn:admin1_code":"36",
    "gn:admin2_code":"134.0",
    "gn:asciiname":"Rashidpur",
    "gn:country_code":"IN",
    "gn:dem":226,
    "gn:feature_class":"P",
    "gn:feature_code":"PPL",
    "gn:name":"Rash\u012bdpur",
    "gn:population":0,
    "gn:timezone":"Asia/Kolkata",
    "iso:country":"IN",
    "ks:ks_alt_nam":"Rash\u012bdpur",
    "ks:ks_name":"Rashidpur",
    "ks:ks_type":"VILLAGE",
    "ks:ks_uagg_main":0,
    "name:eng_x_preferred":[
        "Rashidpur"
    ],
    "name:eng_x_variant":[
        "Rash\u012bdpur"
    ],
    "wof:name":"Rashidpur",
    "wof:placetype":"neighbourhood"
},
  "geometry": {"coordinates":[78.532751,29.186814],"type":"Point"}
}