{
  "type": "Feature",
  "properties": {
    "iso:country":"IN",
    "ks:ks_name":"Kansar",
    "ks:ks_pop":417,
    "ks:ks_type":"VILLAGE",
    "name:eng_x_preferred":[
        "Kansar"
    ],
    "wof:name":"Kansar",
    "wof:placetype":"locality",
    "wof:population":417
},
  "geometry": {"coordinates":[85.361484,21.197009],"type":"Point"}
}