{
  "type": "Feature",
  "properties": {
    "iso:country":"IN",
    "ks:ks_name":"Chhemuan",
    "ks:ks_pop":0,
    "ks:ks_type":"VILLAGE",
    "name:eng_x_preferred":[
        "Chhemuan"
    ],
    "wof:name":"Chhemuan",
    "wof:placetype":"locality",
    "wof:population":0
},
  "geometry": {"coordinates":[84.220766,24.967782],"type":"Point"}
}