{
  "type": "Feature",
  "properties": {
    "iso:country":"IN",
    "ks:ks_name":"Bagulamari",
    "ks:ks_pop":2400,
    "ks:ks_type":"VILLAGE",
    "ks:ks_uagg_main":0,
    "name:eng_x_preferred":[
        "Bagulamari"
    ],
    "wof:name":"Bagulamari",
    "wof:placetype":"neighbourhood",
    "wof:population":2400
},
  "geometry": {"coordinates":[89.96987300000001,26.022142],"type":"Point"}
}