{
  "type": "Feature",
  "properties": {
    "gn:admin1_code":"34.0",
    "gn:admin2_code":"234.0",
    "gn:asciiname":"Mohaddiganj",
    "gn:country_code":"IN",
    "gn:dem":106,
    "gn:feature_class":"P",
    "gn:feature_code":"PPL",
    "gn:name":"Mohaddiganj",
    "gn:population":0,
    "gn:timezone":"Asia/Kolkata",
    "iso:country":"IN",
    "ks:ks_name":"Mohaddi Ganj",
    "ks:ks_pop":2388,
    "ks:ks_type":"VILLAGE",
    "name:eng_x_preferred":[
        "Mohaddi Ganj"
    ],
    "name:eng_x_variant":[
        "Mohaddiganj"
    ],
    "wof:name":"Mohaddi Ganj",
    "wof:placetype":"locality",
    "wof:population":2388
},
  "geometry": {"coordinates":[84.024777,24.961668],"type":"Point"}
}