{
  "type": "Feature",
  "properties": {
    "iso:country":"IN",
    "ks:ks_name":"Madhupali",
    "ks:ks_pop":16,
    "ks:ks_type":"VILLAGE",
    "name:eng_x_preferred":[
        "Madhupali"
    ],
    "wof:name":"Madhupali",
    "wof:placetype":"locality",
    "wof:population":16
},
  "geometry": {"coordinates":[84.678059,21.389541],"type":"Point"}
}