{
  "type": "Feature",
  "properties": {
    "gn:admin1_code":"36",
    "gn:admin2_code":"191.0",
    "gn:asciiname":"Babhangawan",
    "gn:country_code":"IN",
    "gn:dem":85,
    "gn:feature_class":"P",
    "gn:feature_code":"PPL",
    "gn:name":"Babhang\u0101w\u0101n",
    "gn:population":0,
    "gn:timezone":"Asia/Kolkata",
    "iso:country":"IN",
    "name:und_x_variant":[
        "Babhang\u0101w\u0101n",
        "Rew\u0101n"
    ],
    "wof:name":"Babhangawan",
    "wof:placetype":"locality"
},
  "geometry": {"coordinates":[82.96169,25.98451],"type":"Point"}
}