{
  "type": "Feature",
  "properties": {
    "gn:admin1_code":"36",
    "gn:admin2_code":"158.0",
    "gn:asciiname":"Pura Jafar Ali Kumedan",
    "gn:country_code":"IN",
    "gn:dem":119,
    "gn:feature_class":"P",
    "gn:feature_code":"PPL",
    "gn:name":"Pura J\u0101far Ali Kumed\u0101n",
    "gn:population":0,
    "gn:timezone":"Asia/Kolkata",
    "iso:country":"IN",
    "wof:name":"Pura Jafar Ali Kumedan",
    "wof:placetype":"neighbourhood"
},
  "geometry": {"coordinates":[81.20829000000001,26.41616],"type":"Point"}
}