{
  "type": "Feature",
  "properties": {
    "iso:country":"IN",
    "ks:ks_name":"Jaradih",
    "ks:ks_pop":134,
    "ks:ks_type":"HABITATION",
    "name:eng_x_preferred":[
        "Jaradih"
    ],
    "wof:name":"Jaradih",
    "wof:placetype":"locality",
    "wof:population":134
},
  "geometry": {"coordinates":[85.70270499999999,23.336109],"type":"Point"}
}