{
  "type": "Feature",
  "properties": {
    "iso:country":"IN",
    "ks:ks_name":"Kalli Vattam",
    "ks:ks_pop":141,
    "ks:ks_type":"HABITATION",
    "name:eng_x_preferred":[
        "Kalli Vattam"
    ],
    "wof:name":"Kalli Vattam",
    "wof:placetype":"locality",
    "wof:population":141
},
  "geometry": {"coordinates":[78.230248,11.70351],"type":"Point"}
}