{
  "type": "Feature",
  "properties": {
    "iso:country":"IN",
    "ks:ks_name":"Venkatathippa",
    "ks:ks_pop":221,
    "ks:ks_type":"HABITATION",
    "name:eng_x_preferred":[
        "Venkatathippa"
    ],
    "wof:name":"Venkatathippa",
    "wof:placetype":"locality",
    "wof:population":221
},
  "geometry": {"coordinates":[81.56922900000001,16.446489],"type":"Point"}
}