{
  "type": "Feature",
  "properties": {
    "gn:admin1_code":"36.0",
    "gn:admin2_code":"160",
    "gn:asciiname":"Maushampur Maurara",
    "gn:country_code":"IN",
    "gn:dem":142,
    "gn:feature_class":"P",
    "gn:feature_code":"PPL",
    "gn:name":"Maushampur Maur\u0101ra",
    "gn:population":0,
    "gn:timezone":"Asia/Kolkata",
    "iso:country":"IN",
    "ks:ks_alt_nam":"Maushampur Maur\u0101ra",
    "ks:ks_name":"Maushampur Maurara",
    "ks:ks_type":"VILLAGE",
    "ks:ks_uagg_main":0,
    "wof:name":"Maushampur Maurara",
    "wof:placetype":"neighbourhood"
},
  "geometry": {"coordinates":[79.90356,27.04337],"type":"Point"}
}