{
  "type": "Feature",
  "properties": {
    "iso:country":"IN",
    "ks:ks_name":"Dablee",
    "ks:ks_pop":1757,
    "ks:ks_type":"HABITATION",
    "name:eng_x_preferred":[
        "Dablee"
    ],
    "wof:name":"Dablee",
    "wof:placetype":"locality",
    "wof:population":1757
},
  "geometry": {"coordinates":[72.02377799999999,25.427469],"type":"Point"}
}