{
  "type": "Feature",
  "properties": {
    "gn:admin1_code":"10",
    "gn:admin2_code":"85.0",
    "gn:asciiname":"Bhurthal Thethar",
    "gn:country_code":"IN",
    "gn:dem":235,
    "gn:feature_class":"P",
    "gn:feature_code":"PPL",
    "gn:name":"Bhurthal Thethar",
    "gn:population":0,
    "gn:timezone":"Asia/Kolkata",
    "iso:country":"IN",
    "wof:name":"Bhurthal Thethar",
    "wof:placetype":"locality"
},
  "geometry": {"coordinates":[76.64860999999998,28.26323],"type":"Point"}
}