{
  "type": "Feature",
  "properties": {
    "gn:admin1_code":"10.0",
    "gn:admin2_code":"87.0",
    "gn:asciiname":"Bilakpur",
    "gn:country_code":"IN",
    "gn:dem":210,
    "gn:feature_class":"P",
    "gn:feature_code":"PPL",
    "gn:name":"Bil\u0101kpur",
    "gn:population":0,
    "gn:timezone":"Asia/Kolkata",
    "iso:country":"IN",
    "name:und_x_variant":[
        "Bil\u0101kpur",
        "Sidhr\u0101wat"
    ],
    "wof:name":"Bilakpur",
    "wof:placetype":"locality"
},
  "geometry": {"coordinates":[76.95316,27.76942],"type":"Point"}
}