{
  "type": "Feature",
  "properties": {
    "iso:country":"IN",
    "ks:ks_name":"Bhaler Bhodar",
    "ks:ks_pop":1369,
    "ks:ks_type":"VILLAGE",
    "name:eng_x_preferred":[
        "Bhaler Bhodar"
    ],
    "wof:name":"Bhaler Bhodar",
    "wof:placetype":"locality",
    "wof:population":1369
},
  "geometry": {"coordinates":[74.163889,23.363333],"type":"Point"}
}