{
  "type": "Feature",
  "properties": {
    "gn:country":"IN",
    "gn:fcode":"PPL",
    "gn:population":0,
    "iso:country":"IN",
    "name:ast_x_preferred":[
        "Dammaiguda"
    ],
    "name:eng_x_preferred":[
        "Dammaiguda"
    ],
    "name:nld_x_preferred":[
        "Dammaiguda"
    ],
    "qs:name":"Dammaiguda",
    "qs:name_adm0":"India",
    "qs:name_adm1":"Andhra Pradesh",
    "qs:photos":1,
    "qs:photos_1k":1,
    "qs:photos_9k":1,
    "qs:photos_9r":1,
    "qs:photos_all":1,
    "qs:photos_sr":1,
    "qs:placetype":"Suburb",
    "qs:pop_sr":"0",
    "wd:elevation":533.0,
    "wd:wordcount":560,
    "wof:name":"Dammaiguda",
    "wof:placetype":"neighbourhood",
    "wof:population":0
},
  "geometry": {"coordinates":[78.58986,17.50314],"type":"Point"}
}