{
  "type": "Feature",
  "properties": {
    "gn:country":"IN",
    "gn:fcode":"PPL",
    "gn:population":0,
    "iso:country":"IN",
    "name:ara_x_preferred":[
        "\u062f\u0627\u0645\u0627\u064a \u062c\u0648\u062f\u0627"
    ],
    "name:ast_x_preferred":[
        "Dammaiguda"
    ],
    "name:ben_bn_x_preferred":[
        "\u09a6\u09be\u09ae\u09cd\u09ae\u09be\u0987\u0997\u09c1\u09a1\u09be"
    ],
    "name:ben_in_x_preferred":[
        "\u09a6\u09be\u09ae\u09cd\u09ae\u09be\u0987\u0997\u09c1\u09a1\u09be"
    ],
    "name:eng_x_preferred":[
        "Dammaiguda"
    ],
    "name:guj_x_preferred":[
        "\u0aa6\u0aae\u0acd\u0aae\u0abe\u0a87\u0a97\u0ac1\u0aa1\u0abe"
    ],
    "name:hin_x_preferred":[
        "\u0926\u092e\u094d\u092e\u0948\u0917\u0941\u0921\u093e"
    ],
    "name:kan_x_preferred":[
        "\u0ca6\u0cae\u0ccd\u0cae\u0cc8\u0c97\u0cc1\u0ca1"
    ],
    "name:mal_x_preferred":[
        "\u0d21\u0d2e\u0d4d\u0d2e\u0d48\u0d17\u0d41\u0d21"
    ],
    "name:mar_x_preferred":[
        "\u0926\u093e\u092e\u092e\u093e\u092f\u0917\u0941\u0921\u093e"
    ],
    "name:nld_x_preferred":[
        "Dammaiguda"
    ],
    "name:pan_x_preferred":[
        "\u0a26\u0a2e\u0a3e\u0a07\u0a17\u0a41\u0a5c\u0a3e"
    ],
    "name:tam_x_preferred":[
        "\u0b9f\u0bae\u0bcd\u0bae\u0bbe\u0baf\u0bcd\u0b95\u0bc1\u0b9f\u0bbe"
    ],
    "name:tel_x_preferred":[
        "\u0c26\u0c2e\u0c4d\u0c2e\u0c48\u0c17\u0c42\u0c21"
    ],
    "name:urd_x_preferred":[
        "\u062f\u0645\u0651\u0627\u0626\u06cc \u06af\u0648\u0688\u0627"
    ],
    "qs:name":"Dammaiguda",
    "qs:name_adm0":"India",
    "qs:name_adm1":"Andhra Pradesh",
    "qs:photos":1,
    "qs:photos_1k":1,
    "qs:photos_9k":1,
    "qs:photos_9r":1,
    "qs:photos_all":1,
    "qs:photos_sr":1,
    "qs:placetype":"Suburb",
    "qs:pop_sr":"0",
    "wd:elevation":533.0,
    "wd:wordcount":560,
    "wof:name":"Dammaiguda",
    "wof:placetype":"neighbourhood",
    "wof:population":0
},
  "geometry": {"coordinates":[78.58986,17.50314],"type":"Point"}
}