{
  "type": "Feature",
  "properties": {
    "iso:country":"IN",
    "ks:ks_name":"Baridih",
    "ks:ks_pop":51,
    "ks:ks_type":"VILLAGE",
    "name:eng_x_preferred":[
        "Baridih"
    ],
    "wof:name":"Baridih",
    "wof:placetype":"locality",
    "wof:population":51
},
  "geometry": {"coordinates":[87.54455,25.059191],"type":"Point"}
}