{
  "type": "Feature",
  "properties": {
    "iso:country":"IN",
    "ks:ks_name":"Nevuwarya",
    "ks:ks_pop":212,
    "ks:ks_type":"HABITATION",
    "name:eng_x_preferred":[
        "Nevuwarya"
    ],
    "wof:name":"Nevuwarya",
    "wof:placetype":"locality",
    "wof:population":212
},
  "geometry": {"coordinates":[82.682875,25.453776],"type":"Point"}
}