{
  "type": "Feature",
  "properties": {
    "iso:country":"IN",
    "ks:ks_name":"Bar Dhanara No.2",
    "ks:ks_pop":16,
    "ks:ks_type":"VILLAGE",
    "ks:ks_uagg_main":0,
    "name:eng_x_preferred":[
        "Bar Dhanara No.2"
    ],
    "wof:name":"Bar Dhanara No.2",
    "wof:placetype":"neighbourhood",
    "wof:population":16
},
  "geometry": {"coordinates":[91.521096,26.39156],"type":"Point"}
}