{
  "type": "Feature",
  "properties": {
    "iso:country":"IN",
    "ks:ks_alt_nam":"halyachawada",
    "ks:ks_name":"Halyachawada",
    "ks:ks_pop":110,
    "ks:ks_type":"HABITATION",
    "name:eng_x_preferred":[
        "Halyachawada"
    ],
    "wof:name":"Halyachawada",
    "wof:placetype":"locality",
    "wof:population":110
},
  "geometry": {"coordinates":[74.057817,16.291928],"type":"Point"}
}