{
  "type": "Feature",
  "properties": {
    "iso:country":"IN",
    "ks:ks_name":"Burjiguda",
    "ks:ks_pop":56,
    "ks:ks_type":"HABITATION",
    "name:eng_x_preferred":[
        "Burjiguda"
    ],
    "wof:name":"Burjiguda",
    "wof:placetype":"locality",
    "wof:population":56
},
  "geometry": {"coordinates":[84.02843300000001,18.77093],"type":"Point"}
}