{
  "type": "Feature",
  "properties": {
    "gn:admin1_code":"24.0",
    "gn:admin2_code":"129.0",
    "gn:asciiname":"Budhwara",
    "gn:country_code":"IN",
    "gn:dem":358,
    "gn:feature_class":"P",
    "gn:feature_code":"PPL",
    "gn:name":"Budhw\u0101ra",
    "gn:population":0,
    "gn:timezone":"Asia/Kolkata",
    "iso:country":"IN",
    "wof:name":"Budhwara",
    "wof:placetype":"locality"
},
  "geometry": {"coordinates":[76.82458000000003,24.27376],"type":"Point"}
}