{
  "type": "Feature",
  "properties": {
    "iso:country":"IN",
    "ks:ks_name":"Pakdi Kol",
    "ks:ks_pop":0,
    "ks:ks_type":"VILLAGE",
    "name:eng_x_preferred":[
        "Pakdi Kol"
    ],
    "wof:name":"Pakdi Kol",
    "wof:placetype":"locality",
    "wof:population":0
},
  "geometry": {"coordinates":[83.70070200000001,25.918503],"type":"Point"}
}