{
  "type": "Feature",
  "properties": {
    "iso:country":"IN",
    "ks:ks_name":"West Vadugambadi",
    "ks:ks_pop":320,
    "ks:ks_type":"HABITATION",
    "name:eng_x_preferred":[
        "West Vadugambadi"
    ],
    "wof:name":"West Vadugambadi",
    "wof:placetype":"locality",
    "wof:population":320
},
  "geometry": {"coordinates":[78.086901,10.626586],"type":"Point"}
}