{
  "type": "Feature",
  "properties": {
    "iso:country":"IN",
    "ks:ks_name":"Potturajulapalle",
    "ks:ks_pop":73,
    "ks:ks_type":"HABITATION",
    "name:eng_x_preferred":[
        "Potturajulapalle"
    ],
    "wof:name":"Potturajulapalle",
    "wof:placetype":"locality",
    "wof:population":73
},
  "geometry": {"coordinates":[79.171334,13.150117],"type":"Point"}
}