{
  "type": "Feature",
  "properties": {
    "iso:country":"IN",
    "ks:ks_name":"Bhawanand Tilaia Bahiar",
    "ks:ks_pop":519,
    "ks:ks_type":"VILLAGE",
    "name:eng_x_preferred":[
        "Bhawanand Tilaia Bahiar"
    ],
    "wof:name":"Bhawanand Tilaia Bahiar",
    "wof:placetype":"locality",
    "wof:population":519
},
  "geometry": {"coordinates":[86.074893,24.107455],"type":"Point"}
}