{
  "type": "Feature",
  "properties": {
    "gn:admin1_code":"34.0",
    "gn:admin2_code":"228.0",
    "gn:asciiname":"Madhepur",
    "gn:country_code":"IN",
    "gn:dem":57,
    "gn:feature_class":"P",
    "gn:feature_code":"PPL",
    "gn:name":"M\u0101dhepur",
    "gn:population":0,
    "gn:timezone":"Asia/Kolkata",
    "iso:country":"IN",
    "name:ceb_x_preferred":[
        "Madhepur"
    ],
    "name:spa_x_preferred":[
        "Madhepur"
    ],
    "name:swe_x_preferred":[
        "Madhepur"
    ],
    "wof:name":"Madhepur",
    "wof:placetype":"neighbourhood"
},
  "geometry": {"coordinates":[85.74099,25.1592],"type":"Point"}
}