{
  "type": "Feature",
  "properties": {
    "iso:country":"IN",
    "ks:ks_name":"Sonamoha Para",
    "ks:ks_pop":210,
    "ks:ks_type":"HABITATION",
    "name:eng_x_preferred":[
        "Sonamoha Para"
    ],
    "wof:name":"Sonamoha Para",
    "wof:placetype":"locality",
    "wof:population":210
},
  "geometry": {"coordinates":[91.59746800000001,23.116344],"type":"Point"}
}