{
  "type": "Feature",
  "properties": {
    "iso:country":"IN",
    "ks:ks_name":"Zuzamwadi",
    "ks:ks_pop":77,
    "ks:ks_type":"HABITATION",
    "name:eng_x_preferred":[
        "Zuzamwadi"
    ],
    "wof:name":"Zuzamwadi",
    "wof:placetype":"locality",
    "wof:population":77
},
  "geometry": {"coordinates":[73.643964,17.526878],"type":"Point"}
}