{
  "type": "Feature",
  "properties": {
    "iso:country":"IN",
    "ks:ks_name":"Uttar Gobindapur",
    "ks:ks_pop":402,
    "ks:ks_type":"VILLAGE",
    "ks:ks_uagg_main":0,
    "name:eng_x_preferred":[
        "Uttar Gobindapur"
    ],
    "wof:name":"Uttar Gobindapur",
    "wof:placetype":"neighbourhood",
    "wof:population":402
},
  "geometry": {"coordinates":[88.366525,25.620142],"type":"Point"}
}