{
  "type": "Feature",
  "properties": {
    "gn:admin1_code":"28.0",
    "gn:admin2_code":"341.0",
    "gn:asciiname":"Bikihakola",
    "gn:country_code":"IN",
    "gn:dem":12,
    "gn:feature_class":"P",
    "gn:feature_code":"PPL",
    "gn:name":"Bikihakola",
    "gn:population":0,
    "gn:timezone":"Asia/Kolkata",
    "iso:country":"IN",
    "ks:ks_name":"Bikihakola",
    "ks:ks_pop":11900,
    "ks:ks_type":"URBAN",
    "ks:ks_uagg_main":0,
    "name:ben_x_preferred":[
        "\u09ac\u09bf\u0995\u09bf\u09b9\u09be\u0995\u09cb\u09b2\u09be"
    ],
    "name:bpy_x_preferred":[
        "\u09ac\u09bf\u0995\u09bf\u09b9\u09be\u0995\u09cb\u09b2\u09be"
    ],
    "name:eng_x_preferred":[
        "Bikihakola"
    ],
    "name:ita_x_preferred":[
        "Bikihakola"
    ],
    "name:msa_x_preferred":[
        "Bikihakola"
    ],
    "name:new_x_preferred":[
        "\u092c\u093f\u0915\u093f\u0939\u093e\u0915\u094b\u0932\u093e"
    ],
    "name:nld_x_preferred":[
        "Bikihakola"
    ],
    "name:por_x_preferred":[
        "Bikihakola"
    ],
    "name:vie_x_preferred":[
        "Bikihakola"
    ],
    "name:zho_x_preferred":[
        "\u6bd4\u57fa\u54c8\u79d1\u62c9"
    ],
    "wof:name":"Bikihakola",
    "wof:placetype":"locality",
    "wof:population":11900
},
  "geometry": {"coordinates":[88.149815,22.557116],"type":"Point"}
}