{
  "type": "Feature",
  "properties": {
    "iso:country":"IN",
    "ks:ks_name":"Kannanperuchira Junction",
    "ks:ks_pop":1548,
    "ks:ks_type":"HABITATION",
    "name:eng_x_preferred":[
        "Kannanperuchira Junction"
    ],
    "wof:name":"Kannanperuchira Junction",
    "wof:placetype":"locality",
    "wof:population":1548
},
  "geometry": {"coordinates":[76.522755,9.471671],"type":"Point"}
}