{
  "type": "Feature",
  "properties": {
    "iso:country":"IN",
    "ks:ks_name":"Firojpur",
    "ks:ks_pop":387,
    "ks:ks_type":"VILLAGE",
    "ks:ks_uagg_main":0,
    "name:eng_x_preferred":[
        "Firojpur"
    ],
    "wof:name":"Firojpur",
    "wof:placetype":"neighbourhood",
    "wof:population":387
},
  "geometry": {"coordinates":[88.42032500000001,24.202743],"type":"Point"}
}