{
  "type": "Feature",
  "properties": {
    "iso:country":"IN",
    "ks:ks_name":"Sarabaria",
    "ks:ks_pop":0,
    "ks:ks_type":"VILLAGE",
    "name:eng_x_preferred":[
        "Sarabaria"
    ],
    "wof:name":"Sarabaria",
    "wof:placetype":"locality",
    "wof:population":0
},
  "geometry": {"coordinates":[88.722803,22.571062],"type":"Point"}
}