{
  "type": "Feature",
  "properties": {
    "iso:country":"IN",
    "ks:ks_name":"Hukkalukai",
    "ks:ks_pop":47,
    "ks:ks_type":"HABITATION",
    "name:eng_x_preferred":[
        "Hukkalukai"
    ],
    "wof:name":"Hukkalukai",
    "wof:placetype":"locality",
    "wof:population":47
},
  "geometry": {"coordinates":[75.02517,14.098177],"type":"Point"}
}