{
  "type": "Feature",
  "properties": {
    "gn:admin1_code":"16",
    "gn:admin2_code":"502.0",
    "gn:asciiname":"Bhoyat",
    "gn:country_code":"IN",
    "gn:dem":498,
    "gn:feature_class":"P",
    "gn:feature_code":"PPL",
    "gn:name":"Bhoyat",
    "gn:population":0,
    "gn:timezone":"Asia/Kolkata",
    "iso:country":"IN",
    "wof:name":"Bhoyat",
    "wof:placetype":"locality"
},
  "geometry": {"coordinates":[77.19718,20.27339],"type":"Point"}
}