{
  "type": "Feature",
  "properties": {
    "iso:country":"IN",
    "ks:ks_name":"Kanchan Pur Tola",
    "ks:ks_pop":516,
    "ks:ks_type":"HABITATION",
    "name:eng_x_preferred":[
        "Kanchan Pur Tola"
    ],
    "wof:name":"Kanchan Pur Tola",
    "wof:placetype":"locality",
    "wof:population":516
},
  "geometry": {"coordinates":[83.639415,27.135281],"type":"Point"}
}