{
  "type": "Feature",
  "properties": {
    "iso:country":"IN",
    "ks:ks_name":"Taunkri",
    "ks:ks_type":"VILLAGE",
    "name:eng_x_preferred":[
        "Taunkri"
    ],
    "wof:name":"Taunkri",
    "wof:placetype":"locality"
},
  "geometry": {"coordinates":[76.35350699999999,24.417094],"type":"Point"}
}