{
  "type": "Feature",
  "properties": {
    "gn:admin1_code":"36.0",
    "gn:admin2_code":"175.0",
    "gn:asciiname":"Dharauta",
    "gn:country_code":"IN",
    "gn:dem":100,
    "gn:feature_class":"P",
    "gn:feature_code":"PPL",
    "gn:name":"Dharauta",
    "gn:population":0,
    "gn:timezone":"Asia/Kolkata",
    "iso:country":"IN",
    "ks:ks_name":"Dharauta",
    "ks:ks_pop":704,
    "ks:ks_type":"VILLAGE",
    "ks:ks_uagg_main":0,
    "name:eng_x_preferred":[
        "Dharauta"
    ],
    "name:und_x_variant":[
        "Bor\u012bpur"
    ],
    "wof:name":"Dharauta",
    "wof:placetype":"neighbourhood",
    "wof:population":704
},
  "geometry": {"coordinates":[81.976096,25.721345],"type":"Point"}
}