{
  "type": "Feature",
  "properties": {
    "iso:country":"IN",
    "ks:ks_name":"Raghunath Chak",
    "ks:ks_pop":319,
    "ks:ks_type":"VILLAGE",
    "name:eng_x_preferred":[
        "Raghunath Chak"
    ],
    "wof:name":"Raghunath Chak",
    "wof:placetype":"locality",
    "wof:population":319
},
  "geometry": {"coordinates":[87.341886,22.088674],"type":"Point"}
}