{
  "type": "Feature",
  "properties": {
    "iso:country":"IN",
    "ks:ks_name":"Maredupalle",
    "ks:ks_pop":1164,
    "ks:ks_type":"VILLAGE",
    "ks:ks_uagg_main":0,
    "name:eng_x_preferred":[
        "Maredupalle"
    ],
    "wof:name":"Maredupalle",
    "wof:placetype":"neighbourhood",
    "wof:population":1164
},
  "geometry": {"coordinates":[79.276093,18.769324],"type":"Point"}
}