{
  "type": "Feature",
  "properties": {
    "iso:country":"IN",
    "ks:ks_name":"Asanbani",
    "ks:ks_pop":168,
    "ks:ks_type":"VILLAGE",
    "name:eng_x_preferred":[
        "Asanbani"
    ],
    "wof:name":"Asanbani",
    "wof:placetype":"locality",
    "wof:population":168
},
  "geometry": {"coordinates":[87.430683,24.382794],"type":"Point"}
}