{
  "type": "Feature",
  "properties": {
    "iso:country":"IN",
    "ks:ks_alt_nam":"KELAKOPPA",
    "ks:ks_name":"Kelakoppa",
    "ks:ks_pop":84,
    "ks:ks_type":"HABITATION",
    "name:eng_x_preferred":[
        "Kelakoppa"
    ],
    "wof:name":"Kelakoppa",
    "wof:placetype":"locality",
    "wof:population":84
},
  "geometry": {"coordinates":[75.17355499999999,13.604028],"type":"Point"}
}