{
  "type": "Feature",
  "properties": {
    "iso:country":"IN",
    "ks:ks_name":"Banamalipur",
    "ks:ks_pop":21,
    "ks:ks_type":"VILLAGE",
    "name:eng_x_preferred":[
        "Banamalipur"
    ],
    "wof:name":"Banamalipur",
    "wof:placetype":"locality",
    "wof:population":21
},
  "geometry": {"coordinates":[85.82227399999999,20.511534],"type":"Point"}
}