{
  "type": "Feature",
  "properties": {
    "iso:country":"IN",
    "ks:ks_name":"Yadavar Kollakottai",
    "ks:ks_pop":300,
    "ks:ks_type":"HABITATION",
    "name:eng_x_preferred":[
        "Yadavar Kollakottai"
    ],
    "wof:name":"Yadavar Kollakottai",
    "wof:placetype":"locality",
    "wof:population":300
},
  "geometry": {"coordinates":[78.652055,12.760998],"type":"Point"}
}