{
  "type": "Feature",
  "properties": {
    "gn:admin1_code":"2",
    "gn:admin2_code":"544.0",
    "gn:asciiname":"Soraniguda",
    "gn:country_code":"IN",
    "gn:dem":995,
    "gn:feature_class":"P",
    "gn:feature_code":"PPL",
    "gn:name":"Soranig\u016bda",
    "gn:population":0,
    "gn:timezone":"Asia/Kolkata",
    "iso:country":"IN",
    "wof:name":"Soraniguda",
    "wof:placetype":"locality"
},
  "geometry": {"coordinates":[82.94856999999998,18.29991],"type":"Point"}
}