{
  "type": "Feature",
  "properties": {
    "gn:admin1_code":"2",
    "gn:admin2_code":"544.0",
    "gn:asciiname":"Soraniguda",
    "gn:country_code":"IN",
    "gn:dem":995,
    "gn:feature_class":"P",
    "gn:feature_code":"PPL",
    "gn:name":"Soranig\u016bda",
    "gn:population":0,
    "gn:timezone":"Asia/Kolkata",
    "iso:country":"IN",
    "ks:ks_name":"Soraiguda",
    "ks:ks_pop":82,
    "ks:ks_type":"HABITATION",
    "name:eng_x_preferred":[
        "Soraiguda"
    ],
    "name:eng_x_variant":[
        "Soraniguda"
    ],
    "wof:name":"Soraiguda",
    "wof:placetype":"locality",
    "wof:population":82
},
  "geometry": {"coordinates":[82.948998,18.299725],"type":"Point"}
}