{
  "type": "Feature",
  "properties": {
    "gn:admin1_code":"36",
    "gn:admin2_code":"191.0",
    "gn:asciiname":"Chak Shah Kafi",
    "gn:country_code":"IN",
    "gn:dem":88,
    "gn:feature_class":"P",
    "gn:feature_code":"PPL",
    "gn:name":"Chak Shah Kafi",
    "gn:population":0,
    "gn:timezone":"Asia/Kolkata",
    "iso:country":"IN",
    "ks:ks_name":"Chak Shah Kafi",
    "ks:ks_pop":455,
    "ks:ks_type":"VILLAGE",
    "name:eng_x_preferred":[
        "Chak Shah Kafi"
    ],
    "wof:name":"Chak Shah Kafi",
    "wof:placetype":"locality",
    "wof:population":455
},
  "geometry": {"coordinates":[82.879655,26.131558],"type":"Point"}
}