{
  "type": "Feature",
  "properties": {
    "iso:country":"IN",
    "ks:ks_name":"Birendra Para",
    "ks:ks_pop":64,
    "ks:ks_type":"HABITATION",
    "name:eng_x_preferred":[
        "Birendra Para"
    ],
    "wof:name":"Birendra Para",
    "wof:placetype":"locality",
    "wof:population":64
},
  "geometry": {"coordinates":[91.436627,24.043119],"type":"Point"}
}