{
  "type": "Feature",
  "properties": {
    "iso:country":"IN",
    "ks:ks_name":"Luadi",
    "ks:ks_pop":658,
    "ks:ks_type":"VILLAGE",
    "ks:ks_uagg_main":0,
    "name:eng_x_preferred":[
        "Luadi"
    ],
    "wof:name":"Luadi",
    "wof:placetype":"neighbourhood",
    "wof:population":658
},
  "geometry": {"coordinates":[86.669622,23.822922],"type":"Point"}
}