{
  "type": "Feature",
  "properties": {
    "iso:country":"IN",
    "ks:ks_name":"Kachahar",
    "ks:ks_pop":1144,
    "ks:ks_type":"VILLAGE",
    "name:eng_x_preferred":[
        "Kachahar"
    ],
    "wof:name":"Kachahar",
    "wof:placetype":"locality",
    "wof:population":1144
},
  "geometry": {"coordinates":[81.671097,23.416501],"type":"Point"}
}