{
  "type": "Feature",
  "properties": {
    "iso:country":"IN",
    "ks:ks_name":"Petha",
    "ks:ks_pop":520,
    "ks:ks_type":"VILLAGE",
    "name:eng_x_preferred":[
        "Petha"
    ],
    "wof:name":"Petha",
    "wof:placetype":"locality",
    "wof:population":520
},
  "geometry": {"coordinates":[80.308679,19.634725],"type":"Point"}
}