{
  "type": "Feature",
  "properties": {
    "iso:country":"IN",
    "ks:ks_name":"Kotha Donabandathanda",
    "ks:ks_pop":564,
    "ks:ks_type":"HABITATION",
    "ks:ks_uagg_main":0,
    "name:eng_x_preferred":[
        "Kotha Donabandathanda"
    ],
    "wof:name":"Kotha Donabandathanda",
    "wof:placetype":"neighbourhood",
    "wof:population":564
},
  "geometry": {"coordinates":[79.82253,16.792555],"type":"Point"}
}