{
  "type": "Feature",
  "properties": {
    "iso:country":"IN",
    "ks:ks_alt_nam":"DONGARI DEVALAY",
    "ks:ks_name":"Dongari Devalay",
    "ks:ks_pop":50,
    "ks:ks_type":"HABITATION",
    "name:eng_x_preferred":[
        "Dongari Devalay"
    ],
    "wof:name":"Dongari Devalay",
    "wof:placetype":"locality",
    "wof:population":50
},
  "geometry": {"coordinates":[74.330078,17.269488],"type":"Point"}
}