{
  "type": "Feature",
  "properties": {
    "gn:admin1_code":"23.0",
    "gn:admin2_code":"41.0",
    "gn:asciiname":"Bhagwanpur",
    "gn:country_code":"IN",
    "gn:dem":262,
    "gn:feature_class":"P",
    "gn:feature_code":"PPL",
    "gn:name":"Bhagw\u0101npur",
    "gn:population":0,
    "gn:timezone":"Asia/Kolkata",
    "iso:country":"IN",
    "name:ara_x_preferred":[
        "\u0628\u0627\u062c\u0648\u0627\u0646\u0628\u0648\u0631"
    ],
    "name:ben_bn_x_preferred":[
        "\u09ad\u0997\u09ac\u09be\u09a8\u09aa\u09c1\u09b0"
    ],
    "name:ben_in_x_preferred":[
        "\u09ad\u0997\u09ac\u09be\u09a8\u09aa\u09c1\u09b0"
    ],
    "name:fra_x_preferred":[
        "Bhagwanpur"
    ],
    "name:guj_x_preferred":[
        "\u0aad\u0a97\u0ab5\u0abe\u0aa8\u0aaa\u0ac1\u0ab0"
    ],
    "name:hin_x_preferred":[
        "\u092d\u0917\u0935\u093e\u0928\u092a\u0941\u0930"
    ],
    "name:kan_x_preferred":[
        "\u0cad\u0c97\u0cb5\u0cbe\u0ca8\u0ccd"
    ],
    "name:mal_x_preferred":[
        "\u0d2d\u0d17\u0d35\u0d3e\u0d7b\u0d2a\u0d42\u0d7c"
    ],
    "name:mar_x_preferred":[
        "\u092d\u0917\u0935\u093e\u0928\u092a\u0941\u0930"
    ],
    "name:pan_x_preferred":[
        "\u0a2d\u0a17\u0a35\u0a3e\u0a28\u0a2a\u0a41\u0a30"
    ],
    "name:pol_x_preferred":[
        "Bhagwanpur"
    ],
    "name:tam_x_preferred":[
        "\u0baa\u0b95\u0bb5\u0bbe\u0ba9\u0bcd\u0baa\u0bc2\u0bb0\u0bcd"
    ],
    "name:tel_x_preferred":[
        "\u0c2d\u0c17\u0c4d"
    ],
    "name:urd_x_preferred":[
        "\u0628\u06be\u06af\u0648\u0627\u0646 \u067e\u0648\u0631"
    ],
    "wof:name":"Bhagwanpur",
    "wof:placetype":"locality"
},
  "geometry": {"coordinates":[75.94453,30.78827],"type":"Point"}
}