{
  "type": "Feature",
  "properties": {
    "gn:admin1_code":"36.0",
    "gn:admin2_code":"180.0",
    "gn:asciiname":"Huzurpur",
    "gn:country_code":"IN",
    "gn:dem":112,
    "gn:feature_class":"P",
    "gn:feature_code":"PPL",
    "gn:name":"Huz\u016brpur",
    "gn:population":0,
    "gn:timezone":"Asia/Kolkata",
    "iso:country":"IN",
    "name:und_x_variant":[
        "Huz\u016brpur",
        "Haz\u016brpur"
    ],
    "wof:name":"Huzurpur",
    "wof:placetype":"locality"
},
  "geometry": {"coordinates":[81.6627,27.35093],"type":"Point"}
}