{
  "type": "Feature",
  "properties": {
    "gn:admin1_code":"34.0",
    "gn:admin2_code":"220.0",
    "gn:asciiname":"Basanta Jahanabad",
    "gn:country_code":"IN",
    "gn:dem":56,
    "gn:feature_class":"P",
    "gn:feature_code":"PPL",
    "gn:name":"Basanta Jah\u0101n\u0101b\u0101d",
    "gn:population":0,
    "gn:timezone":"Asia/Kolkata",
    "iso:country":"IN",
    "wof:name":"Basanta Jahanabad",
    "wof:placetype":"locality"
},
  "geometry": {"coordinates":[85.16973,25.83718],"type":"Point"}
}