{
  "type": "Feature",
  "properties": {
    "gn:admin1_code":"34.0",
    "gn:admin2_code":"220.0",
    "gn:asciiname":"Basanta Jahanabad",
    "gn:country_code":"IN",
    "gn:dem":56,
    "gn:feature_class":"P",
    "gn:feature_code":"PPL",
    "gn:name":"Basanta Jah\u0101n\u0101b\u0101d",
    "gn:population":0,
    "gn:timezone":"Asia/Kolkata",
    "iso:country":"IN",
    "ks:ks_name":"Basant Jahanabad",
    "ks:ks_pop":5081,
    "ks:ks_type":"VILLAGE",
    "name:eng_x_preferred":[
        "Basant Jahanabad"
    ],
    "name:eng_x_variant":[
        "Basanta Jahanabad"
    ],
    "wof:name":"Basant Jahanabad",
    "wof:placetype":"locality",
    "wof:population":5081
},
  "geometry": {"coordinates":[85.169337,25.838038],"type":"Point"}
}