{
  "type": "Feature",
  "properties": {
    "iso:country":"IN",
    "ks:ks_name":"Ajeetmana",
    "ks:ks_pop":1073,
    "ks:ks_type":"VILLAGE",
    "name:eng_x_preferred":[
        "Ajeetmana"
    ],
    "wof:name":"Ajeetmana",
    "wof:placetype":"locality",
    "wof:population":1073
},
  "geometry": {"coordinates":[73.388542,28.570703],"type":"Point"}
}