{
  "type": "Feature",
  "properties": {
    "gn:admin1_code":"24.0",
    "gn:admin2_code":"107.0",
    "gn:asciiname":"Puranpura",
    "gn:country_code":"IN",
    "gn:dem":234,
    "gn:feature_class":"P",
    "gn:feature_code":"PPL",
    "gn:name":"P\u016branpura",
    "gn:population":0,
    "gn:timezone":"Asia/Kolkata",
    "iso:country":"IN",
    "wof:name":"Puranpura",
    "wof:placetype":"locality"
},
  "geometry": {"coordinates":[76.64023,26.30505],"type":"Point"}
}