{
  "type": "Feature",
  "properties": {
    "iso:country":"IN",
    "ks:ks_name":"Chinthalapadu",
    "ks:ks_pop":92,
    "ks:ks_type":"HABITATION",
    "name:eng_x_preferred":[
        "Chinthalapadu"
    ],
    "wof:name":"Chinthalapadu",
    "wof:placetype":"locality",
    "wof:population":92
},
  "geometry": {"coordinates":[82.502538,17.886044],"type":"Point"}
}