{
  "type": "Feature",
  "properties": {
    "gn:admin1_code":"34.0",
    "gn:admin2_code":"236.0",
    "gn:asciiname":"Shukurdih",
    "gn:country_code":"IN",
    "gn:dem":156,
    "gn:feature_class":"P",
    "gn:feature_code":"PPL",
    "gn:name":"Shukurdih",
    "gn:population":0,
    "gn:timezone":"Asia/Kolkata",
    "iso:country":"IN",
    "wof:name":"Shukurdih",
    "wof:placetype":"neighbourhood"
},
  "geometry": {"coordinates":[84.62179999999999,24.60674],"type":"Point"}
}