{
  "type": "Feature",
  "properties": {
    "iso:country":"IN",
    "ks:ks_name":"Kusumsahi",
    "ks:ks_pop":52,
    "ks:ks_type":"VILLAGE",
    "name:eng_x_preferred":[
        "Kusumsahi"
    ],
    "wof:name":"Kusumsahi",
    "wof:placetype":"locality",
    "wof:population":52
},
  "geometry": {"coordinates":[84.281251,20.650538],"type":"Point"}
}