{
  "type": "Feature",
  "properties": {
    "gn:admin1_code":"03",
    "gn:asciiname":"Phaikulum",
    "gn:country_code":"IN",
    "gn:dem":545,
    "gn:feature_class":"P",
    "gn:feature_code":"PPL",
    "gn:name":"Phaikulum",
    "gn:population":0,
    "gn:timezone":"Asia/Kolkata",
    "iso:country":"IN",
    "wof:name":"Phaikulum",
    "wof:placetype":"locality"
},
  "geometry": {"coordinates":[93.45207000000001,25.4753],"type":"Point"}
}