{
  "type": "Feature",
  "properties": {
    "iso:country":"IN",
    "ks:ks_name":"Turukdiha",
    "ks:ks_type":"VILLAGE",
    "ks:ks_uagg_main":0,
    "name:eng_x_preferred":[
        "Turukdiha"
    ],
    "wof:name":"Turukdiha",
    "wof:placetype":"locality"
},
  "geometry": {"coordinates":[86.345866,24.142411],"type":"Point"}
}