{
  "type": "Feature",
  "properties": {
    "iso:country":"IN",
    "ks:ks_name":"7 RWD",
    "ks:ks_pop":44,
    "ks:ks_type":"VILLAGE",
    "name:eng_x_preferred":[
        "7 RWD"
    ],
    "wof:name":"7 RWD",
    "wof:placetype":"locality",
    "wof:population":44
},
  "geometry": {"coordinates":[74.56082499999999,29.377832],"type":"Point"}
}