{
  "type": "Feature",
  "properties": {
    "gn:admin1_code":"34.0",
    "gn:admin2_code":"220.0",
    "gn:asciiname":"Lachhmi Narayanpur",
    "gn:country_code":"IN",
    "gn:dem":55,
    "gn:feature_class":"P",
    "gn:feature_code":"PPL",
    "gn:name":"Lachhmi N\u0101r\u0101yanpur",
    "gn:population":0,
    "gn:timezone":"Asia/Kolkata",
    "iso:country":"IN",
    "ks:ks_name":"Lacchminarayanpur",
    "ks:ks_pop":1112,
    "ks:ks_type":"VILLAGE",
    "name:eng_x_preferred":[
        "Lacchminarayanpur"
    ],
    "name:eng_x_variant":[
        "Lachhmi Narayanpur"
    ],
    "wof:name":"Lacchminarayanpur",
    "wof:placetype":"locality",
    "wof:population":1112
},
  "geometry": {"coordinates":[85.207902,25.858907],"type":"Point"}
}