{
  "type": "Feature",
  "properties": {
    "iso:country":"IN",
    "ks:ks_alt_nam":"CHAUTHIYALI",
    "ks:ks_name":"Chauthiyali",
    "ks:ks_pop":279,
    "ks:ks_type":"HABITATION",
    "name:eng_x_preferred":[
        "Chauthiyali"
    ],
    "wof:name":"Chauthiyali",
    "wof:placetype":"locality",
    "wof:population":279
},
  "geometry": {"coordinates":[70.384333,25.868894],"type":"Point"}
}