{
  "type": "Feature",
  "properties": {
    "iso:country":"IN",
    "ks:ks_name":"Kushhi Nagar",
    "ks:ks_pop":88,
    "ks:ks_type":"HABITATION",
    "name:eng_x_preferred":[
        "Kushhi Nagar"
    ],
    "wof:name":"Kushhi Nagar",
    "wof:placetype":"locality",
    "wof:population":88
},
  "geometry": {"coordinates":[80.857133,26.642345],"type":"Point"}
}