{
  "type": "Feature",
  "properties": {
    "iso:country":"IN",
    "ks:ks_alt_nam":"Kul\u0101buru",
    "ks:ks_name":"Kulaburu",
    "ks:ks_pop":1510,
    "ks:ks_type":"VILLAGE",
    "name:eng_x_preferred":[
        "Kulaburu"
    ],
    "name:eng_x_variant":[
        "Kul\u0101buru"
    ],
    "wof:name":"Kulaburu",
    "wof:placetype":"locality",
    "wof:population":1510
},
  "geometry": {"coordinates":[85.764071,22.174505],"type":"Point"}
}