{
  "type": "Feature",
  "properties": {
    "gn:admin1_code":"23.0",
    "gn:admin2_code":"43.0",
    "gn:asciiname":"Waryam Khera",
    "gn:country_code":"IN",
    "gn:dem":185,
    "gn:feature_class":"P",
    "gn:feature_code":"PPL",
    "gn:name":"Wary\u0101m Khera",
    "gn:population":0,
    "gn:timezone":"Asia/Kolkata",
    "iso:country":"IN",
    "name:und_x_variant":[
        "Wary\u0101m Khera"
    ],
    "wof:name":"Waryam Khera",
    "wof:placetype":"locality"
},
  "geometry": {"coordinates":[74.08287,30.02353],"type":"Point"}
}