{
  "type": "Feature",
  "properties": {
    "gn:admin1_code":"35.0",
    "gn:admin2_code":"455.0",
    "gn:asciiname":"Machighat",
    "gn:country_code":"IN",
    "gn:dem":710,
    "gn:feature_class":"P",
    "gn:feature_code":"PPL",
    "gn:name":"Machigh\u0101t",
    "gn:population":0,
    "gn:timezone":"Asia/Kolkata",
    "iso:country":"IN",
    "ks:ks_alt_nam":"Machigh\u0101t",
    "ks:ks_name":"Machighat",
    "ks:ks_type":"VILLAGE",
    "name:eng_x_preferred":[
        "Machighat"
    ],
    "name:eng_x_variant":[
        "Machigh\u0101t"
    ],
    "wof:name":"Machighat",
    "wof:placetype":"locality"
},
  "geometry": {"coordinates":[78.559263,22.083192],"type":"Point"}
}