{
  "type": "Feature",
  "properties": {
    "iso:country":"IN",
    "ks:ks_name":"Lakshmi Kandar",
    "ks:ks_pop":408,
    "ks:ks_type":"VILLAGE",
    "name:eng_x_preferred":[
        "Lakshmi Kandar"
    ],
    "wof:name":"Lakshmi Kandar",
    "wof:placetype":"locality",
    "wof:population":408
},
  "geometry": {"coordinates":[88.10958599999999,25.095615],"type":"Point"}
}