{
  "type": "Feature",
  "properties": {
    "iso:country":"IN",
    "ks:ks_name":"Gundrevaripalle",
    "ks:ks_pop":17,
    "ks:ks_type":"HABITATION",
    "name:eng_x_preferred":[
        "Gundrevaripalle"
    ],
    "wof:name":"Gundrevaripalle",
    "wof:placetype":"locality",
    "wof:population":17
},
  "geometry": {"coordinates":[79.010223,13.871312],"type":"Point"}
}