{
  "type": "Feature",
  "properties": {
    "gn:admin1_code":"25.0",
    "gn:admin2_code":"607.0",
    "gn:asciiname":"Vanambattu",
    "gn:country_code":"IN",
    "gn:dem":57,
    "gn:feature_class":"P",
    "gn:feature_code":"PPL",
    "gn:name":"V\u0101n\u0101mbattu",
    "gn:population":0,
    "gn:timezone":"Asia/Kolkata",
    "iso:country":"IN",
    "ks:ks_name":"Vannampattu",
    "ks:ks_pop":687,
    "ks:ks_type":"VILLAGE",
    "ks:ks_uagg_main":0,
    "name:eng_x_preferred":[
        "Vannampattu"
    ],
    "wof:name":"Vannampattu",
    "wof:placetype":"neighbourhood",
    "wof:population":687
},
  "geometry": {"coordinates":[79.402565,11.694431],"type":"Point"}
}