{
  "type": "Feature",
  "properties": {
    "gn:admin1_code":"2.0",
    "gn:admin2_code":"554.0",
    "gn:asciiname":"Kuruvapalle",
    "gn:country_code":"IN",
    "gn:dem":704,
    "gn:feature_class":"P",
    "gn:feature_code":"PPL",
    "gn:name":"Kuruvapalle",
    "gn:population":0,
    "gn:timezone":"Asia/Kolkata",
    "iso:country":"IN",
    "wof:name":"Kuruvapalle",
    "wof:placetype":"neighbourhood"
},
  "geometry": {"coordinates":[78.41934999999999,13.68337],"type":"Point"}
}