{
  "type": "Feature",
  "properties": {
    "iso:country":"IN",
    "ks:ks_name":"Vechupathy",
    "ks:ks_pop":349,
    "ks:ks_type":"HABITATION",
    "name:eng_x_preferred":[
        "Vechupathy"
    ],
    "wof:name":"Vechupathy",
    "wof:placetype":"locality",
    "wof:population":349
},
  "geometry": {"coordinates":[76.72643600000001,11.059493],"type":"Point"}
}