{
  "type": "Feature",
  "properties": {
    "iso:country":"IN",
    "ks:ks_name":"Boudhwadi",
    "ks:ks_pop":75,
    "ks:ks_type":"HABITATION",
    "name:eng_x_preferred":[
        "Boudhwadi"
    ],
    "wof:name":"Boudhwadi",
    "wof:placetype":"locality",
    "wof:population":75
},
  "geometry": {"coordinates":[73.53782,16.38152],"type":"Point"}
}