{
  "type": "Feature",
  "properties": {
    "gn:admin1_code":"36",
    "gn:admin2_code":"175.0",
    "gn:asciiname":"Jaswan",
    "gn:country_code":"IN",
    "gn:dem":97,
    "gn:feature_class":"P",
    "gn:feature_code":"PPL",
    "gn:name":"Jasw\u0101n",
    "gn:population":0,
    "gn:timezone":"Asia/Kolkata",
    "iso:country":"IN",
    "name:cat_x_preferred":[
        "Jaswan"
    ],
    "name:ita_x_preferred":[
        "Jaswan"
    ],
    "name:ori_x_preferred":[
        "\u0b1c\u0b38\u0b4d\u0b71\u0b3e\u0b28 \u0b30\u0b3e\u0b1c\u0b4d\u0b5f"
    ],
    "wof:name":"Jaswan",
    "wof:placetype":"locality"
},
  "geometry": {"coordinates":[82.25216,25.30759],"type":"Point"}
}