{
  "type": "Feature",
  "properties": {
    "iso:country":"IN",
    "ks:ks_name":"Ng. Harzu",
    "ks:ks_pop":198,
    "ks:ks_type":"HABITATION",
    "ks:ks_uagg_main":0,
    "name:eng_x_preferred":[
        "Ng. Harzu"
    ],
    "wof:name":"Ng. Harzu",
    "wof:placetype":"neighbourhood",
    "wof:population":198
},
  "geometry": {"coordinates":[79.084963,27.523842],"type":"Point"}
}