{
  "type": "Feature",
  "properties": {
    "iso:country":"IN",
    "ks:ks_name":"Gandhi Nagar",
    "ks:ks_pop":238,
    "ks:ks_type":"HABITATION",
    "name:eng_x_preferred":[
        "Gandhi Nagar"
    ],
    "wof:name":"Gandhi Nagar",
    "wof:placetype":"locality",
    "wof:population":238
},
  "geometry": {"coordinates":[78.591945,12.219817],"type":"Point"}
}