{
  "type": "Feature",
  "properties": {
    "gn:admin1_code":"12.0",
    "gn:admin2_code":"1.0",
    "gn:asciiname":"Bhurjhali",
    "gn:country_code":"IN",
    "gn:dem":3056,
    "gn:feature_class":"P",
    "gn:feature_code":"PPL",
    "gn:name":"Bhurjh\u0101li",
    "gn:population":0,
    "gn:timezone":"Asia/Kolkata",
    "iso:country":"IN",
    "wof:name":"Bhurjhali",
    "wof:placetype":"locality"
},
  "geometry": {"coordinates":[74.04384,34.57128],"type":"Point"}
}