{
  "type": "Feature",
  "properties": {
    "gn:admin1_code":"38.0",
    "gn:admin2_code":"347.0",
    "gn:asciiname":"Jori",
    "gn:country_code":"IN",
    "gn:dem":517,
    "gn:feature_class":"P",
    "gn:feature_code":"PPL",
    "gn:name":"Jori",
    "gn:population":0,
    "gn:timezone":"Asia/Kolkata",
    "iso:country":"IN",
    "ks:ks_name":"Jori",
    "ks:ks_pop":656,
    "ks:ks_type":"VILLAGE",
    "name:eng_x_preferred":[
        "Jori"
    ],
    "name:ita_x_preferred":[
        "Jori"
    ],
    "wof:name":"Jori",
    "wof:placetype":"locality",
    "wof:population":656
},
  "geometry": {"coordinates":[85.174201,24.079609],"type":"Point"}
}