{
  "type": "Feature",
  "properties": {
    "gn:admin1_code":"28.0",
    "gn:admin2_code":"344.0",
    "gn:asciiname":"Dinapur",
    "gn:country_code":"IN",
    "gn:dem":20,
    "gn:feature_class":"P",
    "gn:feature_code":"PPL",
    "gn:name":"Dinapur",
    "gn:population":0,
    "gn:timezone":"Asia/Kolkata",
    "iso:country":"IN",
    "wof:name":"Dinapur",
    "wof:placetype":"locality"
},
  "geometry": {"coordinates":[87.53588000000001,22.45067],"type":"Point"}
}