{
  "type": "Feature",
  "properties": {
    "iso:country":"IN",
    "ks:ks_name":"Guddegadde",
    "ks:ks_pop":27,
    "ks:ks_type":"HABITATION",
    "name:eng_x_preferred":[
        "Guddegadde"
    ],
    "wof:name":"Guddegadde",
    "wof:placetype":"locality",
    "wof:population":27
},
  "geometry": {"coordinates":[74.611109,14.94973],"type":"Point"}
}