{
  "type": "Feature",
  "properties": {
    "iso:country":"IN",
    "ks:ks_alt_nam":"Kinyalagury HC",
    "ks:ks_name":"Kinyalagury Hc",
    "ks:ks_pop":132,
    "ks:ks_type":"HABITATION",
    "name:eng_x_preferred":[
        "Kinyalagury Hc"
    ],
    "wof:name":"Kinyalagury Hc",
    "wof:placetype":"locality",
    "wof:population":132
},
  "geometry": {"coordinates":[75.048174,13.150395],"type":"Point"}
}