{
  "type": "Feature",
  "properties": {
    "iso:country":"IN",
    "ks:ks_name":"Nadupadugai",
    "ks:ks_pop":90,
    "ks:ks_type":"HABITATION",
    "name:eng_x_preferred":[
        "Nadupadugai"
    ],
    "wof:name":"Nadupadugai",
    "wof:placetype":"locality",
    "wof:population":90
},
  "geometry": {"coordinates":[78.97117299999999,10.860573],"type":"Point"}
}