{
  "type": "Feature",
  "properties": {
    "iso:country":"IN",
    "ks:ks_name":"Khairasi",
    "ks:ks_pop":22,
    "ks:ks_type":"HABITATION",
    "name:eng_x_preferred":[
        "Khairasi"
    ],
    "wof:name":"Khairasi",
    "wof:placetype":"locality",
    "wof:population":22
},
  "geometry": {"coordinates":[76.220431,24.569328],"type":"Point"}
}