{
  "type": "Feature",
  "properties": {
    "gn:admin1_code":"35",
    "gn:admin2_code":"443.0",
    "gn:asciiname":"Raikheri",
    "gn:country_code":"IN",
    "gn:dem":420,
    "gn:feature_class":"P",
    "gn:feature_code":"PPL",
    "gn:name":"R\u0101ikheri",
    "gn:population":0,
    "gn:timezone":"Asia/Kolkata",
    "iso:country":"IN",
    "ks:ks_name":"Raikhedi",
    "ks:ks_pop":135,
    "ks:ks_type":"VILLAGE",
    "name:eng_x_preferred":[
        "Raikhedi"
    ],
    "name:eng_x_variant":[
        "Raikheri"
    ],
    "wof:name":"Raikhedi",
    "wof:placetype":"locality",
    "wof:population":135
},
  "geometry": {"coordinates":[77.86535000000001,24.025479],"type":"Point"}
}