{
  "type": "Feature",
  "properties": {
    "iso:country":"IN",
    "ks:ks_alt_nam":"Chinna Nagapudi AC",
    "ks:ks_name":"Chinna Nagapudi Ac",
    "ks:ks_pop":100,
    "ks:ks_type":"HABITATION",
    "ks:ks_uagg_main":0,
    "name:eng_x_preferred":[
        "Chinna Nagapudi Ac"
    ],
    "wof:name":"Chinna Nagapudi Ac",
    "wof:placetype":"neighbourhood",
    "wof:population":100
},
  "geometry": {"coordinates":[79.370829,13.113566],"type":"Point"}
}