{
  "type": "Feature",
  "properties": {
    "iso:country":"IN",
    "ks:ks_alt_nam":"GHATAWALI KHERI",
    "ks:ks_name":"Ghatawali Kheri",
    "ks:ks_pop":17,
    "ks:ks_type":"HABITATION",
    "name:eng_x_preferred":[
        "Ghatawali Kheri"
    ],
    "wof:name":"Ghatawali Kheri",
    "wof:placetype":"locality",
    "wof:population":17
},
  "geometry": {"coordinates":[74.633911,23.920083],"type":"Point"}
}