{
  "type": "Feature",
  "properties": {
    "gn:admin1_code":"34.0",
    "gn:admin2_code":"229.0",
    "gn:asciiname":"Narainpur",
    "gn:country_code":"IN",
    "gn:dem":68,
    "gn:feature_class":"P",
    "gn:feature_code":"PPL",
    "gn:name":"Nar\u0101inpur",
    "gn:population":0,
    "gn:timezone":"Asia/Kolkata",
    "iso:country":"IN",
    "ks:ks_name":"Narainpur",
    "ks:ks_pop":2378,
    "ks:ks_type":"VILLAGE",
    "name:eng_x_preferred":[
        "Narainpur"
    ],
    "wof:name":"Narainpur",
    "wof:placetype":"locality",
    "wof:population":2378
},
  "geometry": {"coordinates":[85.204334,25.207873],"type":"Point"}
}