{
  "type": "Feature",
  "properties": {
    "iso:country":"IN",
    "ks:ks_name":"Ladian Khurd",
    "ks:ks_pop":1058,
    "ks:ks_type":"VILLAGE",
    "name:eng_x_preferred":[
        "Ladian Khurd"
    ],
    "wof:name":"Ladian Khurd",
    "wof:placetype":"neighbourhood",
    "wof:population":1058
},
  "geometry": {"coordinates":[75.788392,30.949588],"type":"Point"}
}