{
  "type": "Feature",
  "properties": {
    "iso:country":"IN",
    "ks:ks_name":"Chigaraiahgarimitta",
    "ks:ks_pop":55,
    "ks:ks_type":"HABITATION",
    "name:eng_x_preferred":[
        "Chigaraiahgarimitta"
    ],
    "wof:name":"Chigaraiahgarimitta",
    "wof:placetype":"locality",
    "wof:population":55
},
  "geometry": {"coordinates":[79.045936,13.41552],"type":"Point"}
}