{
  "type": "Feature",
  "properties": {
    "gn:admin1_code":"19.0",
    "gn:admin2_code":"580",
    "gn:asciiname":"Gugi",
    "gn:country_code":"IN",
    "gn:dem":450,
    "gn:feature_class":"P",
    "gn:feature_code":"PPL",
    "gn:name":"G\u016bgi",
    "gn:population":0,
    "gn:timezone":"Asia/Kolkata",
    "iso:country":"IN",
    "name:fas_x_preferred":[
        "\u06af\u0648\u06af\u06cc"
    ],
    "name:msa_x_preferred":[
        "Gugi"
    ],
    "wof:name":"Gugi",
    "wof:placetype":"locality"
},
  "geometry": {"coordinates":[76.74581999999999,16.7313],"type":"Point"}
}