{
  "type": "Feature",
  "properties": {
    "iso:country":"IN",
    "ks:ks_name":"Talothe",
    "ks:ks_pop":574,
    "ks:ks_type":"VILLAGE",
    "name:eng_x_preferred":[
        "Talothe"
    ],
    "wof:name":"Talothe",
    "wof:placetype":"locality",
    "wof:population":574
},
  "geometry": {"coordinates":[72.89348099999999,20.03485],"type":"Point"}
}