{
  "type": "Feature",
  "properties": {
    "iso:country":"IN",
    "ks:ks_name":"Devada",
    "ks:ks_pop":8227,
    "ks:ks_type":"VILLAGE",
    "name:eng_x_preferred":[
        "Devada"
    ],
    "wof:name":"Devada",
    "wof:placetype":"neighbourhood",
    "wof:population":8227
},
  "geometry": {"coordinates":[83.139837,17.585997],"type":"Point"}
}