{
  "type": "Feature",
  "properties": {
    "iso:country":"IN",
    "ks:ks_name":"Dina Gaon",
    "ks:ks_pop":506,
    "ks:ks_type":"HABITATION",
    "name:eng_x_preferred":[
        "Dina Gaon"
    ],
    "wof:name":"Dina Gaon",
    "wof:placetype":"locality",
    "wof:population":506
},
  "geometry": {"coordinates":[94.29334299999999,26.683365],"type":"Point"}
}