{
  "type": "Feature",
  "properties": {
    "gn:admin1_code":"24.0",
    "gn:admin2_code":"111",
    "gn:asciiname":"Dhod",
    "gn:country_code":"IN",
    "gn:dem":425,
    "gn:feature_class":"P",
    "gn:feature_code":"PPL",
    "gn:name":"Dhod",
    "gn:population":0,
    "gn:timezone":"Asia/Kolkata",
    "iso:country":"IN",
    "name:und_x_variant":[
        "Dhaod"
    ],
    "wof:name":"Dhod",
    "wof:placetype":"locality"
},
  "geometry": {"coordinates":[74.98588000000002,27.49376],"type":"Point"}
}