{
  "type": "Feature",
  "properties": {
    "gn:admin1_code":"35.0",
    "gn:admin2_code":"464.0",
    "gn:asciiname":"Simrol",
    "gn:country_code":"IN",
    "gn:dem":500,
    "gn:feature_class":"P",
    "gn:feature_code":"PPL",
    "gn:name":"Simrol",
    "gn:population":0,
    "gn:timezone":"Asia/Kolkata",
    "iso:country":"IN",
    "wof:name":"Simrol",
    "wof:placetype":"locality"
},
  "geometry": {"coordinates":[74.89416,22.87049],"type":"Point"}
}