{
  "type": "Feature",
  "properties": {
    "iso:country":"IN",
    "ks:ks_name":"Mahishamuri",
    "ks:ks_pop":0,
    "ks:ks_type":"VILLAGE",
    "name:eng_x_preferred":[
        "Mahishamuri"
    ],
    "wof:name":"Mahishamuri",
    "wof:placetype":"locality",
    "wof:population":0
},
  "geometry": {"coordinates":[87.340273,22.524516],"type":"Point"}
}