{
  "type": "Feature",
  "properties": {
    "gn:admin1_code":"36",
    "gn:admin2_code":"177.0",
    "gn:asciiname":"Sukhipur",
    "gn:country_code":"IN",
    "gn:dem":112,
    "gn:feature_class":"P",
    "gn:feature_code":"PPL",
    "gn:name":"Sukh\u012bpur",
    "gn:population":0,
    "gn:timezone":"Asia/Kolkata",
    "iso:country":"IN",
    "name:bih_x_preferred":[
        "\u0938\u0941\u0916\u0940\u092a\u0941\u0930"
    ],
    "name:ceb_x_preferred":[
        "Sukhipur"
    ],
    "name:deu_x_preferred":[
        "Sukhipur"
    ],
    "name:dty_x_preferred":[
        "\u0938\u0941\u0916\u093f\u092a\u0941\u0930 \u0928\u0917\u0930\u092a\u093e\u0932\u093f\u0915\u093e"
    ],
    "name:mai_x_preferred":[
        "\u0938\u0941\u0916\u093f\u092a\u0941\u0930 \u0928\u0917\u0930\u092a\u093e\u0932\u093f\u0915\u093e"
    ],
    "name:msa_x_preferred":[
        "Sukhipur"
    ],
    "name:nep_x_preferred":[
        "\u0938\u0941\u0916\u093f\u092a\u0941\u0930 \u0928\u0917\u0930\u092a\u093e\u0932\u093f\u0915\u093e"
    ],
    "name:new_x_preferred":[
        "\u0938\u0941\u0916\u093f\u092a\u0941\u0930"
    ],
    "name:pol_x_preferred":[
        "Sukhipur"
    ],
    "wof:name":"Sukhipur",
    "wof:placetype":"locality"
},
  "geometry": {"coordinates":[81.68568,26.87383],"type":"Point"}
}