{
  "type": "Feature",
  "properties": {
    "iso:country":"IN",
    "ks:ks_name":"Baria Faliya",
    "ks:ks_pop":400,
    "ks:ks_type":"HABITATION",
    "name:eng_x_preferred":[
        "Baria Faliya"
    ],
    "wof:name":"Baria Faliya",
    "wof:placetype":"locality",
    "wof:population":400
},
  "geometry": {"coordinates":[73.83236100000001,22.889861],"type":"Point"}
}