{
  "type": "Feature",
  "properties": {
    "iso:country":"IN",
    "ks:ks_alt_nam":"BHELWA GOSAI",
    "ks:ks_name":"Bhelwa Gosai",
    "ks:ks_pop":152,
    "ks:ks_type":"HABITATION",
    "name:eng_x_preferred":[
        "Bhelwa Gosai"
    ],
    "wof:name":"Bhelwa Gosai",
    "wof:placetype":"locality",
    "wof:population":152
},
  "geometry": {"coordinates":[85.279438,23.894057],"type":"Point"}
}