{
  "type": "Feature",
  "properties": {
    "iso:country":"IN",
    "ks:ks_name":"Kachh Purwa",
    "ks:ks_pop":319,
    "ks:ks_type":"HABITATION",
    "ks:ks_uagg_main":0,
    "name:eng_x_preferred":[
        "Kachh Purwa"
    ],
    "wof:name":"Kachh Purwa",
    "wof:placetype":"neighbourhood",
    "wof:population":319
},
  "geometry": {"coordinates":[79.844249,26.69623],"type":"Point"}
}