{
  "type": "Feature",
  "properties": {
    "gn:admin1_code":"10",
    "gn:admin2_code":"70.0",
    "gn:asciiname":"Khera",
    "gn:country_code":"IN",
    "gn:dem":300,
    "gn:feature_class":"P",
    "gn:feature_code":"PPL",
    "gn:name":"Khera",
    "gn:population":0,
    "gn:timezone":"Asia/Kolkata",
    "iso:country":"IN",
    "name:und_x_variant":[
        "Ghanni"
    ],
    "wof:name":"Khera",
    "wof:placetype":"locality"
},
  "geometry": {"coordinates":[76.94292,30.47628],"type":"Point"}
}