{
  "type": "Feature",
  "properties": {
    "iso:country":"IN",
    "ks:ks_alt_nam":"Telekar-Zurungewasti",
    "ks:ks_name":"Telekar-zurungewasti",
    "ks:ks_pop":475,
    "ks:ks_type":"HABITATION",
    "name:eng_x_preferred":[
        "Telekar-zurungewasti"
    ],
    "wof:name":"Telekar-zurungewasti",
    "wof:placetype":"locality",
    "wof:population":475
},
  "geometry": {"coordinates":[74.22878,18.59762],"type":"Point"}
}