{
  "type": "Feature",
  "properties": {
    "iso:country":"IN",
    "ks:ks_name":"Kashidih",
    "ks:ks_pop":237,
    "ks:ks_type":"VILLAGE",
    "name:eng_x_preferred":[
        "Kashidih"
    ],
    "wof:name":"Kashidih",
    "wof:placetype":"locality",
    "wof:population":237
},
  "geometry": {"coordinates":[85.86026699999999,22.795733],"type":"Point"}
}