{
  "type": "Feature",
  "properties": {
    "iso:country":"IN",
    "ks:ks_name":"Kolimakki",
    "ks:ks_pop":187,
    "ks:ks_type":"HABITATION",
    "name:eng_x_preferred":[
        "Kolimakki"
    ],
    "wof:name":"Kolimakki",
    "wof:placetype":"locality",
    "wof:population":187
},
  "geometry": {"coordinates":[74.566806,14.426754],"type":"Point"}
}