{
  "type": "Feature",
  "properties": {
    "gn:admin1_code":"16",
    "gn:admin2_code":"509.0",
    "gn:asciiname":"Chaugaon",
    "gn:country_code":"IN",
    "gn:dem":226,
    "gn:feature_class":"P",
    "gn:feature_code":"PPL",
    "gn:name":"Chaugaon",
    "gn:population":0,
    "gn:timezone":"Asia/Kolkata",
    "iso:country":"IN",
    "name:mar_x_preferred":[
        "\u091a\u094c\u0917\u093e\u0935"
    ],
    "wof:name":"Chaugaon",
    "wof:placetype":"locality"
},
  "geometry": {"coordinates":[79.87984,20.5444],"type":"Point"}
}