{
  "type": "Feature",
  "properties": {
    "gn:admin1_code":"35.0",
    "gn:admin2_code":"464.0",
    "gn:asciiname":"Sujapura",
    "gn:country_code":"IN",
    "gn:dem":349,
    "gn:feature_class":"P",
    "gn:feature_code":"PPL",
    "gn:name":"Sujapura",
    "gn:population":0,
    "gn:timezone":"Asia/Kolkata",
    "iso:country":"IN",
    "ks:ks_name":"Sujapura",
    "ks:ks_pop":1716,
    "ks:ks_type":"VILLAGE",
    "name:eng_x_preferred":[
        "Sujapura"
    ],
    "wof:name":"Sujapura",
    "wof:placetype":"locality",
    "wof:population":1716
},
  "geometry": {"coordinates":[74.646002,23.059983],"type":"Point"}
}