{
  "type": "Feature",
  "properties": {
    "iso:country":"IN",
    "ks:ks_name":"Vellipatti",
    "ks:ks_pop":910,
    "ks:ks_type":"VILLAGE",
    "ks:ks_uagg_main":0,
    "name:eng_x_preferred":[
        "Vellipatti"
    ],
    "wof:name":"Vellipatti",
    "wof:placetype":"neighbourhood",
    "wof:population":910
},
  "geometry": {"coordinates":[78.910167,10.142155],"type":"Point"}
}