{
  "type": "Feature",
  "properties": {
    "iso:country":"IN",
    "ks:ks_name":"Ayodhyanagar",
    "ks:ks_pop":764,
    "ks:ks_type":"HABITATION",
    "name:eng_x_preferred":[
        "Ayodhyanagar"
    ],
    "wof:name":"Ayodhyanagar",
    "wof:placetype":"locality",
    "wof:population":764
},
  "geometry": {"coordinates":[77.803376,16.865706],"type":"Point"}
}