{
  "type": "Feature",
  "properties": {
    "gn:admin1_code":"36.0",
    "gn:admin2_code":"136.0",
    "gn:asciiname":"Parghambarpur",
    "gn:country_code":"IN",
    "gn:dem":193,
    "gn:feature_class":"P",
    "gn:feature_code":"PPL",
    "gn:name":"Parghambarpur",
    "gn:population":0,
    "gn:timezone":"Asia/Kolkata",
    "iso:country":"IN",
    "wof:name":"Parghambarpur",
    "wof:placetype":"locality"
},
  "geometry": {"coordinates":[79.28783,28.86986],"type":"Point"}
}