{
  "type": "Feature",
  "properties": {
    "iso:country":"IN",
    "ks:ks_name":"Malawada",
    "ks:ks_pop":165,
    "ks:ks_type":"HABITATION",
    "name:eng_x_preferred":[
        "Malawada"
    ],
    "wof:name":"Malawada",
    "wof:placetype":"locality",
    "wof:population":165
},
  "geometry": {"coordinates":[78.687533,14.481887],"type":"Point"}
}