{
  "type": "Feature",
  "properties": {
    "gn:admin1_code":"37",
    "gn:admin2_code":"403.0",
    "gn:asciiname":"Chandai",
    "gn:country_code":"IN",
    "gn:dem":236,
    "gn:feature_class":"P",
    "gn:feature_code":"PPL",
    "gn:name":"Chandai",
    "gn:population":0,
    "gn:timezone":"Asia/Kolkata",
    "iso:country":"IN",
    "name:cat_x_preferred":[
        "Chandai"
    ],
    "name:ceb_x_preferred":[
        "Chandai"
    ],
    "name:deu_x_preferred":[
        "Chandai"
    ],
    "name:eus_x_preferred":[
        "Chandai"
    ],
    "name:fra_x_preferred":[
        "Chandai"
    ],
    "name:hun_x_preferred":[
        "Chandai"
    ],
    "name:ind_x_preferred":[
        "Chandai"
    ],
    "name:ita_x_preferred":[
        "Chandai"
    ],
    "name:kaz_x_preferred":[
        "\u0428\u0430\u043d\u0434\u0435"
    ],
    "name:lat_x_preferred":[
        "Chandai"
    ],
    "name:mlg_x_preferred":[
        "Chandai"
    ],
    "name:msa_x_preferred":[
        "Chandai"
    ],
    "name:nld_x_preferred":[
        "Chandai"
    ],
    "name:oci_x_preferred":[
        "Chandai"
    ],
    "name:pms_x_preferred":[
        "Chandai"
    ],
    "name:pol_x_preferred":[
        "Chandai"
    ],
    "name:por_x_preferred":[
        "Chandai"
    ],
    "name:ron_x_preferred":[
        "Chandai"
    ],
    "name:slk_x_preferred":[
        "Chandai"
    ],
    "name:spa_x_preferred":[
        "Chandai"
    ],
    "name:srp_x_preferred":[
        "\u0428\u0430\u043d\u0434\u0435"
    ],
    "name:swe_x_preferred":[
        "Chandai"
    ],
    "name:ukr_x_preferred":[
        "\u0428\u0430\u043d\u0434\u0435"
    ],
    "name:uzb_x_preferred":[
        "Chandai"
    ],
    "name:vie_x_preferred":[
        "Chandai"
    ],
    "name:vol_x_preferred":[
        "Chandai"
    ],
    "name:war_x_preferred":[
        "Chandai"
    ],
    "wof:name":"Chandai",
    "wof:placetype":"locality"
},
  "geometry": {"coordinates":[83.03865999999999,21.59429],"type":"Point"}
}