{
  "type": "Feature",
  "properties": {
    "iso:country":"IN",
    "ks:ks_name":"Nerella",
    "ks:ks_pop":55,
    "ks:ks_type":"HABITATION",
    "name:eng_x_preferred":[
        "Nerella"
    ],
    "wof:name":"Nerella",
    "wof:placetype":"locality",
    "wof:population":55
},
  "geometry": {"coordinates":[82.81334699999999,18.036349],"type":"Point"}
}