{
  "type": "Feature",
  "properties": {
    "gn:admin1_code":"25.0",
    "gn:admin2_code":"607.0",
    "gn:asciiname":"Tandavasamudram",
    "gn:country_code":"IN",
    "gn:dem":131,
    "gn:feature_class":"P",
    "gn:feature_code":"PPL",
    "gn:name":"T\u0101ndavasamudram",
    "gn:population":0,
    "gn:timezone":"Asia/Kolkata",
    "iso:country":"IN",
    "wof:name":"Tandavasamudram",
    "wof:placetype":"locality"
},
  "geometry": {"coordinates":[79.34690000000001,12.1565],"type":"Point"}
}