{
  "type": "Feature",
  "properties": {
    "iso:country":"IN",
    "ks:ks_name":"Sarkaniya",
    "ks:ks_pop":328,
    "ks:ks_type":"HABITATION",
    "name:eng_x_preferred":[
        "Sarkaniya"
    ],
    "wof:name":"Sarkaniya",
    "wof:placetype":"locality",
    "wof:population":328
},
  "geometry": {"coordinates":[82.002791,24.408444],"type":"Point"}
}