{
  "type": "Feature",
  "properties": {
    "gn:admin1_code":"12.0",
    "gn:admin2_code":"1.0",
    "gn:asciiname":"Shada Baihk",
    "gn:country_code":"IN",
    "gn:dem":2773,
    "gn:feature_class":"P",
    "gn:feature_code":"PPL",
    "gn:name":"Shada Baihk",
    "gn:population":0,
    "gn:timezone":"Asia/Kolkata",
    "iso:country":"IN",
    "wof:name":"Shada Baihk",
    "wof:placetype":"locality"
},
  "geometry": {"coordinates":[74.01924,34.50642],"type":"Point"}
}