{
  "type": "Feature",
  "properties": {
    "gn:admin1_code":"16",
    "gn:admin2_code":"498.0",
    "gn:asciiname":"Mohadi",
    "gn:country_code":"IN",
    "gn:dem":226,
    "gn:feature_class":"P",
    "gn:feature_code":"PPL",
    "gn:name":"Moh\u0101di",
    "gn:population":0,
    "gn:timezone":"Asia/Kolkata",
    "iso:country":"IN",
    "name:und_x_variant":[
        "Moh\u0101di"
    ],
    "wof:name":"Mohadi",
    "wof:placetype":"locality"
},
  "geometry": {"coordinates":[74.89742,21.01486],"type":"Point"}
}