{
  "type": "Feature",
  "properties": {
    "iso:country":"IN",
    "ks:ks_name":"Rupnagar",
    "ks:ks_pop":156,
    "ks:ks_type":"HABITATION",
    "ks:ks_uagg_main":0,
    "name:eng_x_preferred":[
        "Rupnagar"
    ],
    "wof:name":"Rupnagar",
    "wof:placetype":"neighbourhood",
    "wof:population":156
},
  "geometry": {"coordinates":[89.320787,26.573437],"type":"Point"}
}