{
  "type": "Feature",
  "properties": {
    "iso:country":"IN",
    "ks:ks_name":"Postamara",
    "ks:ks_pop":11,
    "ks:ks_type":"VILLAGE",
    "name:eng_x_preferred":[
        "Postamara"
    ],
    "wof:name":"Postamara",
    "wof:placetype":"locality",
    "wof:population":11
},
  "geometry": {"coordinates":[86.540966,24.491895],"type":"Point"}
}