{
  "type": "Feature",
  "properties": {
    "iso:country":"IN",
    "ks:ks_name":"Nagala Dalip",
    "ks:ks_pop":255,
    "ks:ks_type":"HABITATION",
    "ks:ks_uagg_main":0,
    "name:eng_x_preferred":[
        "Nagala Dalip"
    ],
    "wof:name":"Nagala Dalip",
    "wof:placetype":"neighbourhood",
    "wof:population":255
},
  "geometry": {"coordinates":[78.517877,27.480665],"type":"Point"}
}