{
  "type": "Feature",
  "properties": {
    "iso:country":"IN",
    "ks:ks_name":"Pathan Dihwa",
    "ks:ks_pop":107,
    "ks:ks_type":"HABITATION",
    "name:eng_x_preferred":[
        "Pathan Dihwa"
    ],
    "wof:name":"Pathan Dihwa",
    "wof:placetype":"locality",
    "wof:population":107
},
  "geometry": {"coordinates":[83.23443,27.398487],"type":"Point"}
}