{
  "type": "Feature",
  "properties": {
    "gn:admin1_code":"34.0",
    "gn:admin2_code":"240.0",
    "gn:asciiname":"Khushdihra",
    "gn:country_code":"IN",
    "gn:dem":87,
    "gn:feature_class":"P",
    "gn:feature_code":"PPL",
    "gn:name":"Khushdihra",
    "gn:population":0,
    "gn:timezone":"Asia/Kolkata",
    "iso:country":"IN",
    "wof:name":"Khushdihra",
    "wof:placetype":"locality"
},
  "geometry": {"coordinates":[84.54348,25.16601],"type":"Point"}
}