{
  "type": "Feature",
  "properties": {
    "iso:country":"IN",
    "ks:ks_name":"Madigapalli",
    "ks:ks_pop":120,
    "ks:ks_type":"HABITATION",
    "name:eng_x_preferred":[
        "Madigapalli"
    ],
    "wof:name":"Madigapalli",
    "wof:placetype":"locality",
    "wof:population":120
},
  "geometry": {"coordinates":[78.307385,14.191953],"type":"Point"}
}