{
  "type": "Feature",
  "properties": {
    "gn:admin1_code":"16.0",
    "gn:admin2_code":"509",
    "gn:asciiname":"Dighori",
    "gn:country_code":"IN",
    "gn:dem":233,
    "gn:feature_class":"P",
    "gn:feature_code":"PPL",
    "gn:name":"Dighori",
    "gn:population":0,
    "gn:timezone":"Asia/Kolkata",
    "iso:country":"IN",
    "name:mar_x_preferred":[
        "\u0926\u093f\u0918\u094b\u0930\u0940"
    ],
    "name:urd_x_preferred":[
        "\u062f\u06af\u06be\u0648\u0631\u06cc"
    ],
    "wof:name":"Dighori",
    "wof:placetype":"locality"
},
  "geometry": {"coordinates":[79.81281,20.67624],"type":"Point"}
}