{
  "type": "Feature",
  "properties": {
    "iso:country":"IN",
    "ks:ks_alt_nam":"KELVANWADI",
    "ks:ks_name":"Kelvanwadi",
    "ks:ks_pop":195,
    "ks:ks_type":"HABITATION",
    "name:eng_x_preferred":[
        "Kelvanwadi"
    ],
    "wof:name":"Kelvanwadi",
    "wof:placetype":"locality",
    "wof:population":195
},
  "geometry": {"coordinates":[73.425749,16.719702],"type":"Point"}
}