{
  "type": "Feature",
  "properties": {
    "iso:country":"IN",
    "ks:ks_name":"Golana",
    "ks:ks_pop":313,
    "ks:ks_type":"VILLAGE",
    "name:eng_x_preferred":[
        "Golana"
    ],
    "wof:name":"Golana",
    "wof:placetype":"locality",
    "wof:population":313
},
  "geometry": {"coordinates":[79.837422,29.914235],"type":"Point"}
}