{
  "type": "Feature",
  "properties": {
    "iso:country":"IN",
    "ks:ks_name":"Adargeria",
    "ks:ks_pop":375,
    "ks:ks_type":"HABITATION",
    "name:eng_x_preferred":[
        "Adargeria"
    ],
    "wof:name":"Adargeria",
    "wof:placetype":"locality",
    "wof:population":375
},
  "geometry": {"coordinates":[86.676474,22.708762],"type":"Point"}
}