{
  "type": "Feature",
  "properties": {
    "gn:admin1_code":"34.0",
    "gn:admin2_code":"222.0",
    "gn:asciiname":"Bindpur",
    "gn:country_code":"IN",
    "gn:dem":46,
    "gn:feature_class":"P",
    "gn:feature_code":"PPL",
    "gn:name":"Bindpur",
    "gn:population":0,
    "gn:timezone":"Asia/Kolkata",
    "iso:country":"IN",
    "ks:ks_name":"Bindpur",
    "ks:ks_pop":3222,
    "ks:ks_type":"VILLAGE",
    "ks:ks_uagg_main":0,
    "name:eng_x_preferred":[
        "Bindpur"
    ],
    "wof:name":"Bindpur",
    "wof:placetype":"neighbourhood",
    "wof:population":3222
},
  "geometry": {"coordinates":[86.09494100000001,25.447532],"type":"Point"}
}