{
  "type": "Feature",
  "properties": {
    "gn:admin1_code":"2.0",
    "gn:admin2_code":"546",
    "gn:asciiname":"Devarapalle",
    "gn:cc2":"IN",
    "gn:country_code":"IN",
    "gn:dem":59,
    "gn:feature_class":"P",
    "gn:feature_code":"PPL",
    "gn:name":"Devarapalle",
    "gn:population":0,
    "gn:timezone":"Asia/Kolkata",
    "iso:country":"IN",
    "name:und_x_variant":[
        "Derarapalle",
        "Devarapalle"
    ],
    "wof:name":"Devarapalle",
    "wof:placetype":"locality"
},
  "geometry": {"coordinates":[81.55,17.03333],"type":"Point"}
}