{
  "type": "Feature",
  "properties": {
    "iso:country":"IN",
    "ks:ks_name":"Tajpur",
    "ks:ks_pop":851,
    "ks:ks_type":"VILLAGE",
    "name:eng_x_preferred":[
        "Tajpur"
    ],
    "wof:name":"Tajpur",
    "wof:placetype":"locality",
    "wof:population":851
},
  "geometry": {"coordinates":[72.99205499999999,18.545736],"type":"Point"}
}