{
  "type": "Feature",
  "properties": {
    "gn:admin1_code":"35.0",
    "gn:admin2_code":"439.0",
    "gn:asciiname":"Dakachya",
    "gn:country_code":"IN",
    "gn:dem":523,
    "gn:feature_class":"P",
    "gn:feature_code":"PPL",
    "gn:name":"Dak\u0101chya",
    "gn:population":0,
    "gn:timezone":"Asia/Kolkata",
    "iso:country":"IN",
    "wof:name":"Dakachya",
    "wof:placetype":"locality"
},
  "geometry": {"coordinates":[75.96694000000002,22.85727],"type":"Point"}
}