{
  "type": "Feature",
  "properties": {
    "iso:country":"IN",
    "ks:ks_name":"Harori",
    "ks:ks_pop":102,
    "ks:ks_type":"VILLAGE",
    "name:eng_x_preferred":[
        "Harori"
    ],
    "wof:name":"Harori",
    "wof:placetype":"locality",
    "wof:population":102
},
  "geometry": {"coordinates":[80.022892,29.405703],"type":"Point"}
}