{
  "type": "Feature",
  "properties": {
    "iso:country":"IN",
    "ks:ks_name":"Peeladka",
    "ks:ks_pop":204,
    "ks:ks_type":"HABITATION",
    "name:eng_x_preferred":[
        "Peeladka"
    ],
    "wof:name":"Peeladka",
    "wof:placetype":"locality",
    "wof:population":204
},
  "geometry": {"coordinates":[75.04156500000001,12.79698],"type":"Point"}
}