{
  "type": "Feature",
  "properties": {
    "iso:country":"IN",
    "ks:ks_name":"Bherupada",
    "ks:ks_pop":799,
    "ks:ks_type":"HABITATION",
    "name:eng_x_preferred":[
        "Bherupada"
    ],
    "wof:name":"Bherupada",
    "wof:placetype":"locality",
    "wof:population":799
},
  "geometry": {"coordinates":[74.79909600000001,22.604343],"type":"Point"}
}