{
  "type": "Feature",
  "properties": {
    "iso:country":"IN",
    "ks:ks_alt_nam":"REDLAPALEM",
    "ks:ks_name":"Redlapalem",
    "ks:ks_pop":328,
    "ks:ks_type":"HABITATION",
    "ks:ks_uagg_main":0,
    "name:eng_x_preferred":[
        "Redlapalem"
    ],
    "wof:name":"Redlapalem",
    "wof:placetype":"neighbourhood",
    "wof:population":328
},
  "geometry": {"coordinates":[80.673089,15.993855],"type":"Point"}
}