{
  "type": "Feature",
  "properties": {
    "iso:country":"IN",
    "ks:ks_name":"Bakaliya Tola",
    "ks:ks_pop":260,
    "ks:ks_type":"HABITATION",
    "name:eng_x_preferred":[
        "Bakaliya Tola"
    ],
    "wof:name":"Bakaliya Tola",
    "wof:placetype":"locality",
    "wof:population":260
},
  "geometry": {"coordinates":[83.17196,24.014419],"type":"Point"}
}