{
  "type": "Feature",
  "properties": {
    "iso:country":"IN",
    "ks:ks_name":"Nakhat Sonowal",
    "ks:ks_pop":250,
    "ks:ks_type":"VILLAGE",
    "name:eng_x_preferred":[
        "Nakhat Sonowal"
    ],
    "wof:name":"Nakhat Sonowal",
    "wof:placetype":"locality",
    "wof:population":250
},
  "geometry": {"coordinates":[95.002582,27.306321],"type":"Point"}
}