{
  "type": "Feature",
  "properties": {
    "gn:admin1_code":"25.0",
    "gn:admin2_code":"610.0",
    "gn:asciiname":"Vadakkuppalaiyam",
    "gn:country_code":"IN",
    "gn:dem":167,
    "gn:feature_class":"P",
    "gn:feature_code":"PPL",
    "gn:name":"Vadakkupp\u0101laiyam",
    "gn:population":0,
    "gn:timezone":"Asia/Kolkata",
    "iso:country":"IN",
    "ks:ks_name":"Vadakkupalayam",
    "ks:ks_pop":515,
    "ks:ks_type":"HABITATION",
    "name:eng_x_preferred":[
        "Vadakkupalayam"
    ],
    "name:eng_x_variant":[
        "Vadakkuppalaiyam"
    ],
    "wof:name":"Vadakkupalayam",
    "wof:placetype":"locality",
    "wof:population":515
},
  "geometry": {"coordinates":[77.833152,11.15073],"type":"Point"}
}