{
  "type": "Feature",
  "properties": {
    "iso:country":"IN",
    "ks:ks_name":"Hulukatunda",
    "ks:ks_pop":362,
    "ks:ks_type":"VILLAGE",
    "name:eng_x_preferred":[
        "Hulukatunda"
    ],
    "wof:name":"Hulukatunda",
    "wof:placetype":"locality",
    "wof:population":362
},
  "geometry": {"coordinates":[83.25420800000001,19.051615],"type":"Point"}
}