{
  "type": "Feature",
  "properties": {
    "gn:admin1_code":"36",
    "gn:admin2_code":"180.0",
    "gn:asciiname":"Sasna",
    "gn:country_code":"IN",
    "gn:dem":115,
    "gn:feature_class":"P",
    "gn:feature_code":"PPL",
    "gn:name":"Sasna",
    "gn:population":0,
    "gn:timezone":"Asia/Kolkata",
    "iso:country":"IN",
    "ks:ks_name":"Sasna",
    "ks:ks_pop":433,
    "ks:ks_type":"VILLAGE",
    "ks:ks_uagg_main":0,
    "name:deu_x_preferred":[
        "Sassen"
    ],
    "name:eng_x_preferred":[
        "Sasna"
    ],
    "name:fra_x_preferred":[
        "Sasna"
    ],
    "name:lit_x_preferred":[
        "Sasna"
    ],
    "name:pol_x_preferred":[
        "Ziemia Sasin\u00f3w"
    ],
    "name:rus_x_preferred":[
        "\u0421\u0430\u0441\u0441\u043e\u0432\u0438\u044f"
    ],
    "name:ukr_x_preferred":[
        "\u0421\u0430\u0441\u0441\u0456\u044f"
    ],
    "wof:name":"Sasna",
    "wof:placetype":"neighbourhood",
    "wof:population":433
},
  "geometry": {"coordinates":[81.593913,27.400607],"type":"Point"}
}