{
  "type": "Feature",
  "properties": {
    "gn:admin1_code":"35",
    "gn:admin2_code":"456.0",
    "gn:asciiname":"Bagdari",
    "gn:country_code":"IN",
    "gn:dem":419,
    "gn:feature_class":"P",
    "gn:feature_code":"PPL",
    "gn:name":"Bagd\u0101ri",
    "gn:population":0,
    "gn:timezone":"Asia/Kolkata",
    "iso:country":"IN",
    "ks:ks_alt_nam":"Bagd\u0101ri",
    "ks:ks_name":"Bagdari",
    "ks:ks_pop":554,
    "ks:ks_type":"VILLAGE",
    "name:eng_x_preferred":[
        "Bagdari"
    ],
    "name:eng_x_variant":[
        "Bagd\u0101ri"
    ],
    "wof:name":"Bagdari",
    "wof:placetype":"locality",
    "wof:population":554
},
  "geometry": {"coordinates":[79.962844,22.801995],"type":"Point"}
}