{
  "type": "Feature",
  "properties": {
    "iso:country":"IN",
    "ks:ks_alt_nam":"Lukumai bill",
    "ks:ks_name":"Lukumai Bill",
    "ks:ks_pop":490,
    "ks:ks_type":"HABITATION",
    "ks:ks_uagg_main":0,
    "name:eng_x_preferred":[
        "Lukumai Bill"
    ],
    "wof:name":"Lukumai Bill",
    "wof:placetype":"neighbourhood",
    "wof:population":490
},
  "geometry": {"coordinates":[94.845828,27.205596],"type":"Point"}
}