{
  "type": "Feature",
  "properties": {
    "iso:country":"IN",
    "ks:ks_name":"Tamoli",
    "ks:ks_pop":747,
    "ks:ks_type":"VILLAGE",
    "name:eng_x_preferred":[
        "Tamoli"
    ],
    "wof:name":"Tamoli",
    "wof:placetype":"locality",
    "wof:population":747
},
  "geometry": {"coordinates":[84.069033,23.514254],"type":"Point"}
}