{
  "type": "Feature",
  "properties": {
    "iso:country":"IN",
    "ks:ks_alt_nam":"ZaminBudur Colony",
    "ks:ks_name":"Zaminbudur Colony",
    "ks:ks_pop":600,
    "ks:ks_type":"HABITATION",
    "name:eng_x_preferred":[
        "Zaminbudur Colony"
    ],
    "wof:name":"Zaminbudur Colony",
    "wof:placetype":"locality",
    "wof:population":600
},
  "geometry": {"coordinates":[79.962333,12.342609],"type":"Point"}
}