{
  "type": "Feature",
  "properties": {
    "iso:country":"IN",
    "ks:ks_name":"Khal Gaon",
    "ks:ks_pop":245,
    "ks:ks_type":"HABITATION",
    "name:eng_x_preferred":[
        "Khal Gaon"
    ],
    "wof:name":"Khal Gaon",
    "wof:placetype":"locality",
    "wof:population":245
},
  "geometry": {"coordinates":[75.463565,24.848409],"type":"Point"}
}