{
  "type": "Feature",
  "properties": {
    "gn:admin1_code":"35",
    "gn:admin2_code":"429.0",
    "gn:asciiname":"Kudra",
    "gn:country_code":"IN",
    "gn:dem":368,
    "gn:feature_class":"P",
    "gn:feature_code":"PPL",
    "gn:name":"Kudra",
    "gn:population":0,
    "gn:timezone":"Asia/Kolkata",
    "iso:country":"IN",
    "name:urd_x_preferred":[
        "\u06a9\u062f\u0631\u0627"
    ],
    "wof:name":"Kudra",
    "wof:placetype":"locality"
},
  "geometry": {"coordinates":[80.64662,24.19976],"type":"Point"}
}