{
  "type": "Feature",
  "properties": {
    "iso:country":"IN",
    "ks:ks_name":"Thirukalyanapuram",
    "ks:ks_pop":136,
    "ks:ks_type":"HABITATION",
    "name:eng_x_preferred":[
        "Thirukalyanapuram"
    ],
    "wof:name":"Thirukalyanapuram",
    "wof:placetype":"locality",
    "wof:population":136
},
  "geometry": {"coordinates":[79.008848,9.927303],"type":"Point"}
}