{
  "type": "Feature",
  "properties": {
    "gn:admin1_code":"37.0",
    "gn:admin2_code":"417.0",
    "gn:asciiname":"Tarmendri",
    "gn:country_code":"IN",
    "gn:dem":313,
    "gn:feature_class":"P",
    "gn:feature_code":"PPL",
    "gn:name":"T\u0101rmendri",
    "gn:population":0,
    "gn:timezone":"Asia/Kolkata",
    "iso:country":"IN",
    "ks:ks_alt_nam":"T\u0101rmendri",
    "ks:ks_name":"Tarmendri",
    "ks:ks_type":"VILLAGE",
    "name:eng_x_preferred":[
        "Tarmendri"
    ],
    "name:eng_x_variant":[
        "T\u0101rmendri"
    ],
    "wof:name":"Tarmendri",
    "wof:placetype":"locality"
},
  "geometry": {"coordinates":[80.65668700000001,19.120298],"type":"Point"}
}