{
  "type": "Feature",
  "properties": {
    "gn:admin1_code":"39.0",
    "gn:admin2_code":"64.0",
    "gn:asciiname":"Banasi",
    "gn:country_code":"IN",
    "gn:dem":636,
    "gn:feature_class":"P",
    "gn:feature_code":"PPL",
    "gn:name":"Ban\u0101si",
    "gn:population":0,
    "gn:timezone":"Asia/Kolkata",
    "iso:country":"IN",
    "wof:name":"Banasi",
    "wof:placetype":"locality"
},
  "geometry": {"coordinates":[79.06973000000001,29.60843],"type":"Point"}
}