{
  "type": "Feature",
  "properties": {
    "gn:admin1_code":"39.0",
    "gn:admin2_code":"64.0",
    "gn:asciiname":"Banasi",
    "gn:country_code":"IN",
    "gn:dem":636,
    "gn:feature_class":"P",
    "gn:feature_code":"PPL",
    "gn:name":"Ban\u0101si",
    "gn:population":0,
    "gn:timezone":"Asia/Kolkata",
    "iso:country":"IN",
    "ks:ks_alt_nam":"Ban\u0101si",
    "ks:ks_name":"Banasi",
    "ks:ks_type":"VILLAGE",
    "name:eng_x_preferred":[
        "Banasi"
    ],
    "name:eng_x_variant":[
        "Ban\u0101si"
    ],
    "wof:name":"Banasi",
    "wof:placetype":"locality"
},
  "geometry": {"coordinates":[79.06973499999999,29.608427],"type":"Point"}
}