{
  "type": "Feature",
  "properties": {
    "iso:country":"IN",
    "ks:ks_name":"Raikishun Pati Naubarar",
    "ks:ks_pop":0,
    "ks:ks_type":"VILLAGE",
    "name:eng_x_preferred":[
        "Raikishun Pati Naubarar"
    ],
    "wof:name":"Raikishun Pati Naubarar",
    "wof:placetype":"locality",
    "wof:population":0
},
  "geometry": {"coordinates":[84.014475,25.631275],"type":"Point"}
}