{
  "type": "Feature",
  "properties": {
    "gn:country":"IN",
    "gn:fcode":"PPL",
    "gn:population":0,
    "iso:country":"IN",
    "name:ben_x_preferred":[
        "\u09a8\u09c1\u09b0\u09aa\u09c1\u09b0"
    ],
    "name:bpy_x_preferred":[
        "\u09a8\u09c1\u09b0\u09aa\u09c1\u09b0"
    ],
    "name:cat_x_preferred":[
        "Nurpur"
    ],
    "name:deu_x_preferred":[
        "Nurpur"
    ],
    "name:eng_x_preferred":[
        "Nurpur"
    ],
    "name:fra_x_preferred":[
        "Nurpur"
    ],
    "name:guj_x_preferred":[
        "\u0aa8\u0ac2\u0ab0\u0aaa\u0ac1\u0ab0"
    ],
    "name:hin_x_preferred":[
        "\u0928\u0942\u0930\u092a\u0941\u0930"
    ],
    "name:ita_x_preferred":[
        "Nurpur"
    ],
    "name:jpn_x_preferred":[
        "\u30cc\u30eb\u30d7\u30fc\u30eb"
    ],
    "name:kan_x_preferred":[
        "\u0ca8\u0cc2\u0cb0\u0ccd\u0caa\u0cc1\u0cb0\u0ccd"
    ],
    "name:kor_x_preferred":[
        "\ub204\ub974\ud478\ub974"
    ],
    "name:msa_x_preferred":[
        "Nurpur"
    ],
    "name:nan_x_preferred":[
        "Nurpur"
    ],
    "name:new_x_preferred":[
        "\u0928\u0941\u0930\u092a\u0941\u0930"
    ],
    "name:nld_x_preferred":[
        "Nurpur"
    ],
    "name:pol_x_preferred":[
        "Nurpur"
    ],
    "name:por_x_preferred":[
        "Nurpur"
    ],
    "name:rus_x_preferred":[
        "\u041d\u0443\u0440\u043f\u0443\u0440"
    ],
    "name:spa_x_preferred":[
        "Nurpur"
    ],
    "name:tam_x_preferred":[
        "\u0ba8\u0bc2\u0bb1\u0bcd\u0baa\u0bc1\u0bb0\u0bcd"
    ],
    "name:tel_x_preferred":[
        "\u0c28\u0c42\u0c30\u0c4d\u0c2a\u0c42\u0c30\u0c4d"
    ],
    "name:und_x_variant":[
        "N\u016brpur"
    ],
    "name:urd_x_preferred":[
        "\u0646\u0648\u0631\u067e\u0648\u0631"
    ],
    "name:vie_x_preferred":[
        "Nurpur"
    ],
    "name:zho_x_preferred":[
        "\u52aa\u5c14\u666e\u5c14"
    ],
    "qs:name":"Nurpur",
    "qs:name_adm0":"India",
    "qs:name_adm1":"Himachal Pradesh",
    "qs:photos":19,
    "qs:photos_1k":4,
    "qs:photos_9k":1,
    "qs:photos_9r":1,
    "qs:photos_all":19,
    "qs:photos_sr":1,
    "qs:placetype":"Town",
    "qs:pop_sr":"4",
    "wd:wordcount":67,
    "wof:name":"Nurpur",
    "wof:placetype":"locality",
    "wof:population":0
},
  "geometry": {"coordinates":[75.88526,32.29923],"type":"Point"}
}