{
  "type": "Feature",
  "properties": {
    "gn:admin1_code":"25.0",
    "gn:admin2_code":"605.0",
    "gn:asciiname":"Kovilandur",
    "gn:country_code":"IN",
    "gn:dem":611,
    "gn:feature_class":"P",
    "gn:feature_code":"PPL",
    "gn:name":"Koviland\u016br",
    "gn:population":0,
    "gn:timezone":"Asia/Kolkata",
    "iso:country":"IN",
    "ks:ks_name":"Kovilendur",
    "ks:ks_pop":215,
    "ks:ks_type":"HABITATION",
    "name:eng_x_preferred":[
        "Kovilendur"
    ],
    "name:eng_x_variant":[
        "Kovilandur"
    ],
    "wof:name":"Kovilendur",
    "wof:placetype":"locality",
    "wof:population":215
},
  "geometry": {"coordinates":[78.97785500000001,12.663358],"type":"Point"}
}