{
  "type": "Feature",
  "properties": {
    "gn:admin1_code":"36",
    "gn:admin2_code":"146.0",
    "gn:asciiname":"Shahpur Tula",
    "gn:country_code":"IN",
    "gn:dem":165,
    "gn:feature_class":"P",
    "gn:feature_code":"PPL",
    "gn:name":"Sh\u0101hpur Tula",
    "gn:population":0,
    "gn:timezone":"Asia/Kolkata",
    "iso:country":"IN",
    "wof:name":"Shahpur Tula",
    "wof:placetype":"locality"
},
  "geometry": {"coordinates":[78.13448000000002,26.96723],"type":"Point"}
}