{
  "type": "Feature",
  "properties": {
    "iso:country":"IN",
    "ks:ks_name":"Usri",
    "ks:ks_pop":683,
    "ks:ks_type":"HABITATION",
    "name:eng_x_preferred":[
        "Usri"
    ],
    "wof:name":"Usri",
    "wof:placetype":"locality",
    "wof:population":683
},
  "geometry": {"coordinates":[81.598878,26.519224],"type":"Point"}
}