{
  "type": "Feature",
  "properties": {
    "iso:country":"IN",
    "ks:ks_name":"Tagi",
    "ks:ks_pop":378,
    "ks:ks_type":"VILLAGE",
    "name:eng_x_preferred":[
        "Tagi"
    ],
    "wof:name":"Tagi",
    "wof:placetype":"locality",
    "wof:population":378
},
  "geometry": {"coordinates":[80.71091300000001,24.866202],"type":"Point"}
}