{
  "type": "Feature",
  "properties": {
    "gn:admin1_code":"21.0",
    "gn:admin2_code":"375",
    "gn:asciiname":"Horomoto",
    "gn:country_code":"IN",
    "gn:dem":519,
    "gn:feature_class":"P",
    "gn:feature_code":"PPL",
    "gn:name":"Horomoto",
    "gn:population":0,
    "gn:timezone":"Asia/Kolkata",
    "iso:country":"IN",
    "name:und_x_variant":[
        "Haromoto",
        "Horomutu",
        "Horomoto"
    ],
    "wof:name":"Horomoto",
    "wof:placetype":"locality"
},
  "geometry": {"coordinates":[85.29053,22.05404],"type":"Point"}
}