{
  "type": "Feature",
  "properties": {
    "iso:country":"IN",
    "ks:ks_name":"Villiyar Colony",
    "ks:ks_pop":44,
    "ks:ks_type":"HABITATION",
    "ks:ks_uagg_main":0,
    "name:eng_x_preferred":[
        "Villiyar Colony"
    ],
    "wof:name":"Villiyar Colony",
    "wof:placetype":"neighbourhood",
    "wof:population":44
},
  "geometry": {"coordinates":[79.854518,12.739959],"type":"Point"}
}