{
  "type": "Feature",
  "properties": {
    "gn:admin1_code":"36",
    "gn:admin2_code":"199.0",
    "gn:asciiname":"Riksa Khurd",
    "gn:country_code":"IN",
    "gn:dem":231,
    "gn:feature_class":"P",
    "gn:feature_code":"PPL",
    "gn:name":"Riksa Khurd",
    "gn:population":0,
    "gn:timezone":"Asia/Kolkata",
    "iso:country":"IN",
    "wof:name":"Riksa Khurd",
    "wof:placetype":"neighbourhood"
},
  "geometry": {"coordinates":[82.57917999999999,24.89204],"type":"Point"}
}