{
  "type": "Feature",
  "properties": {
    "iso:country":"IN",
    "ks:ks_name":"Mondaltola",
    "ks:ks_pop":1627,
    "ks:ks_type":"HABITATION",
    "name:eng_x_preferred":[
        "Mondaltola"
    ],
    "wof:name":"Mondaltola",
    "wof:placetype":"locality",
    "wof:population":1627
},
  "geometry": {"coordinates":[86.090418,24.315491],"type":"Point"}
}