{
  "type": "Feature",
  "properties": {
    "gn:admin1_code":"19.0",
    "gn:admin2_code":"574.0",
    "gn:asciiname":"Narandhalli",
    "gn:country_code":"IN",
    "gn:dem":904,
    "gn:feature_class":"P",
    "gn:feature_code":"PPL",
    "gn:name":"Narandhalli",
    "gn:population":0,
    "gn:timezone":"Asia/Kolkata",
    "iso:country":"IN",
    "wof:name":"Narandhalli",
    "wof:placetype":"locality"
},
  "geometry": {"coordinates":[75.74663000000002,12.84712],"type":"Point"}
}