{
  "type": "Feature",
  "properties": {
    "iso:country":"IN",
    "ks:ks_name":"Bilawala Mustahkam",
    "ks:ks_pop":1907,
    "ks:ks_type":"VILLAGE",
    "name:eng_x_preferred":[
        "Bilawala Mustahkam"
    ],
    "wof:name":"Bilawala Mustahkam",
    "wof:placetype":"locality",
    "wof:population":1907
},
  "geometry": {"coordinates":[78.908699,29.085903],"type":"Point"}
}