{
  "type": "Feature",
  "properties": {
    "iso:country":"IN",
    "ks:ks_name":"Kana Kolar",
    "ks:ks_pop":845,
    "ks:ks_type":"VILLAGE",
    "name:eng_x_preferred":[
        "Kana Kolar"
    ],
    "wof:name":"Kana Kolar",
    "wof:placetype":"locality",
    "wof:population":845
},
  "geometry": {"coordinates":[73.09376899999999,25.051431],"type":"Point"}
}