{
  "type": "Feature",
  "properties": {
    "iso:country":"IN",
    "ks:ks_name":"Hamankhudi",
    "ks:ks_pop":1,
    "ks:ks_type":"VILLAGE",
    "name:eng_x_preferred":[
        "Hamankhudi"
    ],
    "wof:name":"Hamankhudi",
    "wof:placetype":"locality",
    "wof:population":1
},
  "geometry": {"coordinates":[68.555217,23.597997],"type":"Point"}
}