{
  "type": "Feature",
  "properties": {
    "iso:country":"IN",
    "ks:ks_name":"Yogambalpuram",
    "ks:ks_pop":260,
    "ks:ks_type":"HABITATION",
    "name:eng_x_preferred":[
        "Yogambalpuram"
    ],
    "wof:name":"Yogambalpuram",
    "wof:placetype":"locality",
    "wof:population":260
},
  "geometry": {"coordinates":[78.936978,10.19314],"type":"Point"}
}