{
  "type": "Feature",
  "properties": {
    "iso:country":"IN",
    "ks:ks_name":"Boraianapalya",
    "ks:ks_pop":90,
    "ks:ks_type":"HABITATION",
    "name:eng_x_preferred":[
        "Boraianapalya"
    ],
    "wof:name":"Boraianapalya",
    "wof:placetype":"locality",
    "wof:population":90
},
  "geometry": {"coordinates":[76.936634,13.012414],"type":"Point"}
}