{
  "type": "Feature",
  "properties": {
    "iso:country":"IN",
    "ks:ks_alt_nam":"PURE BEDIEN",
    "ks:ks_name":"Pure Bedien",
    "ks:ks_pop":126,
    "ks:ks_type":"HABITATION",
    "name:eng_x_preferred":[
        "Pure Bedien"
    ],
    "wof:name":"Pure Bedien",
    "wof:placetype":"locality",
    "wof:population":126
},
  "geometry": {"coordinates":[81.782535,26.038732],"type":"Point"}
}