{
  "type": "Feature",
  "properties": {
    "gn:admin1_code":"40",
    "gn:admin2_code":"537.0",
    "gn:asciiname":"Dargah",
    "gn:country_code":"IN",
    "gn:dem":575,
    "gn:feature_class":"P",
    "gn:feature_code":"PPL",
    "gn:name":"Darg\u0101h",
    "gn:population":0,
    "gn:timezone":"Asia/Kolkata",
    "iso:country":"IN",
    "name:ara_x_preferred":[
        "\u062f\u0631\u0642\u0627\u0639\u0629"
    ],
    "name:fra_x_preferred":[
        "Dargah"
    ],
    "name:hin_x_preferred":[
        "\u0926\u0930\u0917\u093e\u0939"
    ],
    "name:ind_x_preferred":[
        "Dorgah"
    ],
    "name:ita_x_preferred":[
        "Dargah"
    ],
    "name:mal_x_preferred":[
        "\u0d26\u0d7c\u0d17\u0d4d\u0d17"
    ],
    "name:pan_x_preferred":[
        "\u0a26\u0a30\u0a17\u0a3e\u0a39"
    ],
    "name:pol_x_preferred":[
        "Dargah"
    ],
    "name:por_x_preferred":[
        "Dargah"
    ],
    "name:tam_x_preferred":[
        "\u0ba4\u0bb0\u0bcd\u0b95\u0bbe"
    ],
    "name:tel_x_preferred":[
        "\u0c26\u0c30\u0c4d\u0c17\u0c3e\u0c39\u0c4d"
    ],
    "name:urd_x_preferred":[
        "\u062f\u0631\u06af\u0627\u0647"
    ],
    "wof:name":"Dargah",
    "wof:placetype":"neighbourhood"
},
  "geometry": {"coordinates":[78.27654,17.32858],"type":"Point"}
}