{
  "type": "Feature",
  "properties": {
    "iso:country":"IN",
    "ks:ks_alt_nam":"BHOSALE WASTI",
    "ks:ks_name":"Bhosale Wasti",
    "ks:ks_pop":80,
    "ks:ks_type":"HABITATION",
    "name:eng_x_preferred":[
        "Bhosale Wasti"
    ],
    "wof:name":"Bhosale Wasti",
    "wof:placetype":"locality",
    "wof:population":80
},
  "geometry": {"coordinates":[75.07966999999999,17.090307],"type":"Point"}
}