{
  "type": "Feature",
  "properties": {
    "iso:country":"IN",
    "ks:ks_name":"Bagadiha",
    "ks:ks_pop":6,
    "ks:ks_type":"VILLAGE",
    "name:eng_x_preferred":[
        "Bagadiha"
    ],
    "wof:name":"Bagadiha",
    "wof:placetype":"locality",
    "wof:population":6
},
  "geometry": {"coordinates":[84.872242,20.410243],"type":"Point"}
}