{
  "type": "Feature",
  "properties": {
    "gn:admin1_code":"12.0",
    "gn:admin2_code":"16.0",
    "gn:asciiname":"Brahmapur",
    "gn:country_code":"IN",
    "gn:dem":1749,
    "gn:feature_class":"P",
    "gn:feature_code":"PPL",
    "gn:name":"Brahmapur",
    "gn:population":0,
    "gn:timezone":"Asia/Kolkata",
    "iso:country":"IN",
    "name:ceb_x_preferred":[
        "Brahmapur"
    ],
    "name:swe_x_preferred":[
        "Brahmapur"
    ],
    "wof:name":"Brahmapur",
    "wof:placetype":"locality"
},
  "geometry": {"coordinates":[75.61478000000002,33.08286],"type":"Point"}
}