{
  "type": "Feature",
  "properties": {
    "gn:admin1_code":"12.0",
    "gn:admin2_code":"16.0",
    "gn:asciiname":"Brahmapur",
    "gn:country_code":"IN",
    "gn:dem":1749,
    "gn:feature_class":"P",
    "gn:feature_code":"PPL",
    "gn:name":"Brahmapur",
    "gn:population":0,
    "gn:timezone":"Asia/Kolkata",
    "iso:country":"IN",
    "name:ceb_x_preferred":[
        "Brahmapur"
    ],
    "name:heb_x_preferred":[
        "\u05d1\u05e8\u05d4\u05de\u05e4\u05d5\u05e8"
    ],
    "name:hin_x_preferred":[
        "\u092c\u094d\u0930\u0939\u094d\u092e\u092a\u0941\u0930"
    ],
    "name:hun_x_preferred":[
        "Brahmapur"
    ],
    "name:swe_x_preferred":[
        "Brahmapur"
    ],
    "wof:name":"Brahmapur",
    "wof:placetype":"locality"
},
  "geometry": {"coordinates":[75.61478,33.08286],"type":"Point"}
}