{
  "type": "Feature",
  "properties": {
    "iso:country":"IN",
    "ks:ks_name":"Mirganj",
    "ks:ks_pop":0,
    "ks:ks_type":"VILLAGE",
    "name:eng_x_preferred":[
        "Mirganj"
    ],
    "wof:name":"Mirganj",
    "wof:placetype":"locality",
    "wof:population":0
},
  "geometry": {"coordinates":[87.65594299999999,25.35068],"type":"Point"}
}