{
  "type": "Feature",
  "properties": {
    "gn:admin1_code":"35",
    "gn:admin2_code":"452.0",
    "gn:asciiname":"Katangi",
    "gn:country_code":"IN",
    "gn:dem":339,
    "gn:feature_class":"P",
    "gn:feature_code":"PPL",
    "gn:name":"Katangi",
    "gn:population":0,
    "gn:timezone":"Asia/Kolkata",
    "iso:country":"IN",
    "name:ben_x_preferred":[
        "\u0995\u09be\u099f\u09be\u0999\u09cd\u0997\u09bf"
    ],
    "name:bpy_x_preferred":[
        "\u0995\u09be\u099f\u09be\u0999\u09cd\u0997\u09bf"
    ],
    "name:cat_x_preferred":[
        "Katangi"
    ],
    "name:ceb_x_preferred":[
        "Kat\u0101ngi"
    ],
    "name:fra_x_preferred":[
        "Katangi"
    ],
    "name:ita_x_preferred":[
        "Katangi"
    ],
    "name:msa_x_preferred":[
        "Katangi"
    ],
    "name:new_x_preferred":[
        "\u0915\u0924\u0902\u0917\u0940"
    ],
    "name:nld_x_preferred":[
        "Katangi"
    ],
    "name:por_x_preferred":[
        "Katangi"
    ],
    "name:spa_x_preferred":[
        "Katangi"
    ],
    "name:swe_x_preferred":[
        "Kat\u0101ngi"
    ],
    "name:vie_x_preferred":[
        "Katangi"
    ],
    "name:zho_x_preferred":[
        "\u5361\u5510\u683c\u4f0a"
    ],
    "wof:name":"Katangi",
    "wof:placetype":"locality"
},
  "geometry": {"coordinates":[79.05671,23.02039],"type":"Point"}
}