{
  "type": "Feature",
  "properties": {
    "iso:country":"IN",
    "ks:ks_name":"Gutuhatu",
    "ks:ks_pop":1258,
    "ks:ks_type":"VILLAGE",
    "name:eng_x_preferred":[
        "Gutuhatu"
    ],
    "wof:name":"Gutuhatu",
    "wof:placetype":"locality",
    "wof:population":1258
},
  "geometry": {"coordinates":[85.413736,23.055699],"type":"Point"}
}