{
  "type": "Feature",
  "properties": {
    "gn:admin1_code":"24",
    "gn:admin2_code":"117.0",
    "gn:asciiname":"Mundwara",
    "gn:country_code":"IN",
    "gn:dem":291,
    "gn:feature_class":"P",
    "gn:feature_code":"PPL",
    "gn:name":"Mundw\u0101ra",
    "gn:population":0,
    "gn:timezone":"Asia/Kolkata",
    "iso:country":"IN",
    "name:und_x_variant":[
        "M\u0101ndw\u0101ra",
        "Mundw\u0101ra"
    ],
    "wof:name":"Mundwara",
    "wof:placetype":"neighbourhood"
},
  "geometry": {"coordinates":[72.55265,24.8295],"type":"Point"}
}