{
  "type": "Feature",
  "properties": {
    "iso:country":"IN",
    "ks:ks_name":"Bansapti",
    "ks:ks_pop":0,
    "ks:ks_type":"VILLAGE",
    "name:eng_x_preferred":[
        "Bansapti"
    ],
    "wof:name":"Bansapti",
    "wof:placetype":"locality",
    "wof:population":0
},
  "geometry": {"coordinates":[83.92771999999999,27.306846],"type":"Point"}
}