{
  "type": "Feature",
  "properties": {
    "gn:admin1_code":"11",
    "gn:admin2_code":"27.0",
    "gn:asciiname":"Galu",
    "gn:country_code":"IN",
    "gn:dem":993,
    "gn:feature_class":"P",
    "gn:feature_code":"PPL",
    "gn:name":"G\u0101lu",
    "gn:population":0,
    "gn:timezone":"Asia/Kolkata",
    "iso:country":"IN",
    "name:ceb_x_preferred":[
        "Galu"
    ],
    "name:fas_x_preferred":[
        "\u06af\u0644\u0648"
    ],
    "name:ron_x_preferred":[
        "Galu"
    ],
    "name:swe_x_preferred":[
        "Galu"
    ],
    "wof:name":"Galu",
    "wof:placetype":"locality"
},
  "geometry": {"coordinates":[76.86303000000002,31.8616],"type":"Point"}
}