{
  "type": "Feature",
  "properties": {
    "iso:country":"IN",
    "ks:ks_name":"Arjunapura",
    "ks:ks_pop":56,
    "ks:ks_type":"VILLAGE",
    "name:eng_x_preferred":[
        "Arjunapura"
    ],
    "wof:name":"Arjunapura",
    "wof:placetype":"locality",
    "wof:population":56
},
  "geometry": {"coordinates":[83.608131,20.099308],"type":"Point"}
}