{
  "type": "Feature",
  "properties": {
    "iso:country":"IN",
    "ks:ks_alt_nam":"Jeegutta tanda",
    "ks:ks_name":"Jeegutta Tanda",
    "ks:ks_pop":98,
    "ks:ks_type":"HABITATION",
    "name:eng_x_preferred":[
        "Jeegutta Tanda"
    ],
    "wof:name":"Jeegutta Tanda",
    "wof:placetype":"locality",
    "wof:population":98
},
  "geometry": {"coordinates":[78.26069099999999,16.591641],"type":"Point"}
}