{
  "type": "Feature",
  "properties": {
    "iso:country":"IN",
    "ks:ks_alt_nam":"Junm\u0101ni",
    "ks:ks_name":"Junmani",
    "ks:ks_type":"VILLAGE",
    "name:eng_x_preferred":[
        "Junmani"
    ],
    "name:eng_x_variant":[
        "Junm\u0101ni"
    ],
    "wof:name":"Junmani",
    "wof:placetype":"locality"
},
  "geometry": {"coordinates":[77.358255,28.956676],"type":"Point"}
}