{
  "type": "Feature",
  "properties": {
    "gn:admin1_code":"35.0",
    "gn:admin2_code":"436.0",
    "gn:asciiname":"Dhabla Husainpur",
    "gn:country_code":"IN",
    "gn:dem":478,
    "gn:feature_class":"P",
    "gn:feature_code":"PPL",
    "gn:name":"Dhabla Husainpur",
    "gn:population":0,
    "gn:timezone":"Asia/Kolkata",
    "iso:country":"IN",
    "wof:name":"Dhabla Husainpur",
    "wof:placetype":"locality"
},
  "geometry": {"coordinates":[76.80871999999999,23.27837],"type":"Point"}
}