{
  "type": "Feature",
  "properties": {
    "iso:country":"IN",
    "ks:ks_name":"Karukakkadavu- Methuk Road",
    "ks:ks_pop":351,
    "ks:ks_type":"HABITATION",
    "ks:ks_uagg_main":0,
    "name:eng_x_preferred":[
        "Karukakkadavu- Methuk Road"
    ],
    "wof:name":"Karukakkadavu- Methuk Road",
    "wof:placetype":"neighbourhood",
    "wof:population":351
},
  "geometry": {"coordinates":[76.352211,10.718671],"type":"Point"}
}