{
  "type": "Feature",
  "properties": {
    "gn:admin1_code":"23.0",
    "gn:admin2_code":"53.0",
    "gn:asciiname":"Mahan Singhwala",
    "gn:country_code":"IN",
    "gn:dem":230,
    "gn:feature_class":"P",
    "gn:feature_code":"PPL",
    "gn:name":"Mah\u0101n Singhw\u0101la",
    "gn:population":0,
    "gn:timezone":"Asia/Kolkata",
    "iso:country":"IN",
    "name:und_x_variant":[
        "Mah\u0101n Singhw\u0101la",
        "Gobindgarh"
    ],
    "wof:name":"Mahan Singhwala",
    "wof:placetype":"neighbourhood"
},
  "geometry": {"coordinates":[75.98295,29.74508],"type":"Point"}
}