{
  "type": "Feature",
  "properties": {
    "iso:country":"IN",
    "ks:ks_name":"Foolpur",
    "ks:ks_pop":503,
    "ks:ks_type":"VILLAGE",
    "ks:ks_uagg_main":0,
    "name:eng_x_preferred":[
        "Foolpur"
    ],
    "wof:name":"Foolpur",
    "wof:placetype":"locality",
    "wof:population":503
},
  "geometry": {"coordinates":[83.60430599999999,25.589203],"type":"Point"}
}