{
  "type": "Feature",
  "properties": {
    "iso:country":"IN",
    "ks:ks_alt_nam":"mali bigha",
    "ks:ks_name":"Mali Bigha",
    "ks:ks_pop":149,
    "ks:ks_type":"HABITATION",
    "name:eng_x_preferred":[
        "Mali Bigha"
    ],
    "wof:name":"Mali Bigha",
    "wof:placetype":"locality",
    "wof:population":149
},
  "geometry": {"coordinates":[84.957643,25.099743],"type":"Point"}
}