{
  "type": "Feature",
  "properties": {
    "gn:admin1_code":"12",
    "gn:admin2_code":"12.0",
    "gn:asciiname":"Kawain",
    "gn:country_code":"IN",
    "gn:dem":1600,
    "gn:feature_class":"P",
    "gn:feature_code":"PPL",
    "gn:name":"K\u0101wain",
    "gn:population":0,
    "gn:timezone":"Asia/Kolkata",
    "iso:country":"IN",
    "wof:name":"Kawain",
    "wof:placetype":"locality"
},
  "geometry": {"coordinates":[75.05946999999998,33.8392],"type":"Point"}
}