{
  "type": "Feature",
  "properties": {
    "gn:admin1_code":"12.0",
    "gn:admin2_code":"010",
    "gn:asciiname":"Chhandna Deh Nauabad",
    "gn:country_code":"IN",
    "gn:dem":1587,
    "gn:feature_class":"P",
    "gn:feature_code":"PPL",
    "gn:name":"Chhandna Deh Nau\u0101b\u0101d",
    "gn:population":0,
    "gn:timezone":"Asia/Kolkata",
    "iso:country":"IN",
    "wof:name":"Chhandna Deh Nauabad",
    "wof:placetype":"locality"
},
  "geometry": {"coordinates":[74.72476999999998,34.17401],"type":"Point"}
}