{
  "type": "Feature",
  "properties": {
    "iso:country":"IN",
    "ks:ks_name":"Handewasti",
    "ks:ks_pop":108,
    "ks:ks_type":"HABITATION",
    "name:eng_x_preferred":[
        "Handewasti"
    ],
    "wof:name":"Handewasti",
    "wof:placetype":"locality",
    "wof:population":108
},
  "geometry": {"coordinates":[74.270291,18.379959],"type":"Point"}
}