{
  "type": "Feature",
  "properties": {
    "gn:admin1_code":"35.0",
    "gn:admin2_code":"446.0",
    "gn:asciiname":"Saliwara",
    "gn:country_code":"IN",
    "gn:dem":517,
    "gn:feature_class":"P",
    "gn:feature_code":"PPL",
    "gn:name":"S\u0101l\u012bw\u0101ra",
    "gn:population":0,
    "gn:timezone":"Asia/Kolkata",
    "iso:country":"IN",
    "ks:ks_alt_nam":"S\u0101l\u012bw\u0101ra",
    "ks:ks_name":"Saliwara",
    "ks:ks_type":"VILLAGE",
    "name:eng_x_preferred":[
        "Saliwara"
    ],
    "name:eng_x_variant":[
        "S\u0101l\u012bw\u0101ra"
    ],
    "wof:name":"Saliwara",
    "wof:placetype":"locality"
},
  "geometry": {"coordinates":[78.264093,23.578727],"type":"Point"}
}