{
  "type": "Feature",
  "properties": {
    "gn:admin1_code":"25.0",
    "gn:admin2_code":"616.0",
    "gn:asciiname":"Idaiyankudikkadu",
    "gn:country_code":"IN",
    "gn:dem":35,
    "gn:feature_class":"P",
    "gn:feature_code":"PPL",
    "gn:name":"Idaiyankudikk\u0101du",
    "gn:population":0,
    "gn:timezone":"Asia/Kolkata",
    "iso:country":"IN",
    "wof:name":"Idaiyankudikkadu",
    "wof:placetype":"locality"
},
  "geometry": {"coordinates":[79.45125999999998,11.23711],"type":"Point"}
}