{
  "type": "Feature",
  "properties": {
    "iso:country":"IN",
    "ks:ks_name":"Bhanawatawala",
    "ks:ks_pop":338,
    "ks:ks_type":"VILLAGE",
    "name:eng_x_preferred":[
        "Bhanawatawala"
    ],
    "wof:name":"Bhanawatawala",
    "wof:placetype":"locality",
    "wof:population":338
},
  "geometry": {"coordinates":[72.995188,28.371167],"type":"Point"}
}