{
  "type": "Feature",
  "properties": {
    "gn:admin1_code":"12.0",
    "gn:admin2_code":"1.0",
    "gn:asciiname":"Birindur Nar",
    "gn:country_code":"IN",
    "gn:dem":1724,
    "gn:feature_class":"P",
    "gn:feature_code":"PPL",
    "gn:name":"Birindur N\u0101r",
    "gn:population":0,
    "gn:timezone":"Asia/Kolkata",
    "iso:country":"IN",
    "wof:name":"Birindur Nar",
    "wof:placetype":"locality"
},
  "geometry": {"coordinates":[74.26461,34.56987],"type":"Point"}
}