{
  "type": "Feature",
  "properties": {
    "iso:country":"IN",
    "ks:ks_name":"Vijapura Forest",
    "ks:ks_pop":1640,
    "ks:ks_type":"VILLAGE",
    "name:eng_x_preferred":[
        "Vijapura Forest"
    ],
    "wof:name":"Vijapura Forest",
    "wof:placetype":"locality",
    "wof:population":1640
},
  "geometry": {"coordinates":[76.006351,12.761609],"type":"Point"}
}