{
  "type": "Feature",
  "properties": {
    "iso:country":"IN",
    "ks:ks_name":"Singhaberi",
    "ks:ks_pop":110,
    "ks:ks_type":"HABITATION",
    "ks:ks_uagg_main":0,
    "name:eng_x_preferred":[
        "Singhaberi"
    ],
    "wof:name":"Singhaberi",
    "wof:placetype":"locality",
    "wof:population":110
},
  "geometry": {"coordinates":[88.23423699999999,22.825822],"type":"Point"}
}