{
  "type": "Feature",
  "properties": {
    "gn:admin1_code":"25.0",
    "gn:admin2_code":"631.0",
    "gn:asciiname":"Yaragondanahalli",
    "gn:country_code":"IN",
    "gn:dem":907,
    "gn:feature_class":"P",
    "gn:feature_code":"PPL",
    "gn:name":"Yaragondanahalli",
    "gn:population":0,
    "gn:timezone":"Asia/Kolkata",
    "iso:country":"IN",
    "wof:name":"Yaragondanahalli",
    "wof:placetype":"locality"
},
  "geometry": {"coordinates":[77.69328,12.61006],"type":"Point"}
}