{
  "type": "Feature",
  "properties": {
    "iso:country":"IN",
    "ks:ks_name":"Pokharia",
    "ks:ks_pop":787,
    "ks:ks_type":"VILLAGE",
    "ks:ks_uagg_main":0,
    "name:eng_x_preferred":[
        "Pokharia"
    ],
    "wof:name":"Pokharia",
    "wof:placetype":"neighbourhood",
    "wof:population":787
},
  "geometry": {"coordinates":[86.555796,20.892551],"type":"Point"}
}