{
  "type": "Feature",
  "properties": {
    "iso:country":"IN",
    "ks:ks_name":"Haldar Para",
    "ks:ks_pop":703,
    "ks:ks_type":"HABITATION",
    "ks:ks_uagg_main":0,
    "name:eng_x_preferred":[
        "Haldar Para"
    ],
    "wof:name":"Haldar Para",
    "wof:placetype":"neighbourhood",
    "wof:population":703
},
  "geometry": {"coordinates":[88.328929,22.101002],"type":"Point"}
}