{
  "type": "Feature",
  "properties": {
    "iso:country":"IN",
    "ks:ks_name":"Kolengimaru-1",
    "ks:ks_pop":250,
    "ks:ks_type":"HABITATION",
    "name:eng_x_preferred":[
        "Kolengimaru-1"
    ],
    "wof:name":"Kolengimaru-1",
    "wof:placetype":"locality",
    "wof:population":250
},
  "geometry": {"coordinates":[75.094562,12.728991],"type":"Point"}
}