{
  "type": "Feature",
  "properties": {
    "iso:country":"IN",
    "ks:ks_name":"Machu Tanda",
    "ks:ks_pop":150,
    "ks:ks_type":"HABITATION",
    "name:eng_x_preferred":[
        "Machu Tanda"
    ],
    "wof:name":"Machu Tanda",
    "wof:placetype":"locality",
    "wof:population":150
},
  "geometry": {"coordinates":[77.26836,18.494589],"type":"Point"}
}