{
  "type": "Feature",
  "properties": {
    "iso:country":"IN",
    "ks:ks_name":"Medapalli S",
    "ks:ks_pop":422,
    "ks:ks_type":"VILLAGE",
    "name:eng_x_preferred":[
        "Medapalli S"
    ],
    "wof:name":"Medapalli S",
    "wof:placetype":"locality",
    "wof:population":422
},
  "geometry": {"coordinates":[80.22146499999999,19.400521],"type":"Point"}
}