{
  "type": "Feature",
  "properties": {
    "iso:country":"IN",
    "ks:ks_name":"Ganga Kher",
    "ks:ks_pop":231,
    "ks:ks_type":"HABITATION",
    "name:eng_x_preferred":[
        "Ganga Kher"
    ],
    "wof:name":"Ganga Kher",
    "wof:placetype":"locality",
    "wof:population":231
},
  "geometry": {"coordinates":[80.433397,27.118708],"type":"Point"}
}