{
  "type": "Feature",
  "properties": {
    "gn:admin1_code":"12",
    "gn:admin2_code":"18.0",
    "gn:asciiname":"Mat",
    "gn:country_code":"IN",
    "gn:dem":1810,
    "gn:feature_class":"P",
    "gn:feature_code":"PPL",
    "gn:name":"Mat",
    "gn:population":0,
    "gn:timezone":"Asia/Kolkata",
    "iso:country":"IN",
    "name:ben_x_preferred":[
        "\u09ae\u09be\u09a6\u09c1\u09b0"
    ],
    "name:bre_x_preferred":[
        "Torch-treid"
    ],
    "name:ces_x_preferred":[
        "Roho\u017eka"
    ],
    "name:dan_x_preferred":[
        "M\u00e5tte"
    ],
    "name:deu_x_preferred":[
        "Fu\u00dfmatte"
    ],
    "name:ell_x_preferred":[
        "\u03a0\u03b1\u03c4\u03ac\u03ba\u03b9"
    ],
    "name:epo_x_preferred":[
        "Mato"
    ],
    "name:eus_x_preferred":[
        "Lanpas"
    ],
    "name:fas_x_preferred":[
        "\u067e\u0627\u062f\u0631\u06cc"
    ],
    "name:fra_x_preferred":[
        "Paillasson"
    ],
    "name:hun_x_preferred":[
        "L\u00e1bt\u00f6rl\u0151"
    ],
    "name:ind_x_preferred":[
        "Keset"
    ],
    "name:ita_x_preferred":[
        "Zerbino"
    ],
    "name:jav_x_preferred":[
        "K\u00e9s\u00e8t"
    ],
    "name:jpn_x_preferred":[
        "\u30de\u30c3\u30c8"
    ],
    "name:lin_x_preferred":[
        "Etok\u00f3"
    ],
    "name:lit_x_preferred":[
        "Demblys"
    ],
    "name:msa_x_preferred":[
        "Tikar"
    ],
    "name:nep_x_preferred":[
        "\u091a\u0915\u091f\u0940"
    ],
    "name:nld_x_preferred":[
        "Deurmat"
    ],
    "name:nno_x_preferred":[
        "Matte"
    ],
    "name:nor_x_preferred":[
        "Matte"
    ],
    "name:pol_x_preferred":[
        "Wycieraczka"
    ],
    "name:por_x_preferred":[
        "Esteira"
    ],
    "name:rus_x_preferred":[
        "\u041f\u043e\u043b\u043e\u0432\u0438\u043a"
    ],
    "name:slk_x_preferred":[
        "Roho\u017eka"
    ],
    "name:spa_x_preferred":[
        "Felpudo"
    ],
    "name:srp_x_preferred":[
        "\u041f\u043e\u0434\u043c\u0435\u0442\u0430\u0447"
    ],
    "name:sun_x_preferred":[
        "K\u00e9k\u00e9s\u00e9d"
    ],
    "name:swa_x_preferred":[
        "Mkeka"
    ],
    "name:swe_x_preferred":[
        "D\u00f6rrmatta"
    ],
    "name:tcy_x_preferred":[
        "\u0caa\u0c9c\u0cc6"
    ],
    "name:tel_x_preferred":[
        "\u0c1a\u0c3e\u0c2a"
    ],
    "name:tgl_x_preferred":[
        "Pamalisan"
    ],
    "name:ukr_x_preferred":[
        "\u041f\u043e\u0441\u0442\u0456\u043b\u043a\u0430"
    ],
    "wof:name":"Mat",
    "wof:placetype":"locality"
},
  "geometry": {"coordinates":[76.17151,33.27183],"type":"Point"}
}