{
  "type": "Feature",
  "properties": {
    "iso:country":"IN",
    "ks:ks_name":"Mekeri",
    "ks:ks_pop":858,
    "ks:ks_type":"HABITATION",
    "name:eng_x_preferred":[
        "Mekeri"
    ],
    "wof:name":"Mekeri",
    "wof:placetype":"locality",
    "wof:population":858
},
  "geometry": {"coordinates":[75.752703,12.395414],"type":"Point"}
}