{
  "type": "Feature",
  "properties": {
    "iso:country":"IN",
    "ks:ks_name":"Kunu",
    "ks:ks_pop":85,
    "ks:ks_type":"VILLAGE",
    "name:eng_x_preferred":[
        "Kunu"
    ],
    "wof:name":"Kunu",
    "wof:placetype":"locality",
    "wof:population":85
},
  "geometry": {"coordinates":[85.16130699999999,21.645775],"type":"Point"}
}