{
  "type": "Feature",
  "properties": {
    "iso:country":"IN",
    "ks:ks_alt_nam":"Dakhin Bari toli",
    "ks:ks_name":"Dakhin Bari Toli",
    "ks:ks_pop":125,
    "ks:ks_type":"HABITATION",
    "name:eng_x_preferred":[
        "Dakhin Bari Toli"
    ],
    "wof:name":"Dakhin Bari Toli",
    "wof:placetype":"locality",
    "wof:population":125
},
  "geometry": {"coordinates":[84.463785,27.165225],"type":"Point"}
}