{
  "type": "Feature",
  "properties": {
    "gn:admin1_code":"19.0",
    "gn:admin2_code":"575.0",
    "gn:asciiname":"Pilathadka",
    "gn:country_code":"IN",
    "gn:dem":119,
    "gn:feature_class":"P",
    "gn:feature_code":"PPL",
    "gn:name":"Pilathadka",
    "gn:population":0,
    "gn:timezone":"Asia/Kolkata",
    "iso:country":"IN",
    "ks:ks_name":"Pilithadka",
    "ks:ks_pop":158,
    "ks:ks_type":"HABITATION",
    "name:eng_x_preferred":[
        "Pilithadka"
    ],
    "name:eng_x_variant":[
        "Pilathadka"
    ],
    "wof:name":"Pilithadka",
    "wof:placetype":"locality",
    "wof:population":158
},
  "geometry": {"coordinates":[75.379255,13.013228],"type":"Point"}
}