{
  "type": "Feature",
  "properties": {
    "gn:admin1_code":"35.0",
    "gn:admin2_code":"441.0",
    "gn:asciiname":"Chippakhedi",
    "gn:country_code":"IN",
    "gn:dem":156,
    "gn:feature_class":"P",
    "gn:feature_code":"PPL",
    "gn:name":"Chippakhedi",
    "gn:population":0,
    "gn:timezone":"Asia/Kolkata",
    "iso:country":"IN",
    "ks:ks_alt_nam":"ChipaKhedi",
    "ks:ks_name":"Chipakhedi",
    "ks:ks_pop":1027,
    "ks:ks_type":"HABITATION",
    "name:eng_x_preferred":[
        "Chipakhedi"
    ],
    "name:eng_x_variant":[
        "Chippakhedi"
    ],
    "wof:name":"Chipakhedi",
    "wof:placetype":"locality",
    "wof:population":1027
},
  "geometry": {"coordinates":[74.769149,22.024474],"type":"Point"}
}