{
  "type": "Feature",
  "properties": {
    "iso:country":"IN",
    "ks:ks_alt_nam":"Shyamkrishna para",
    "ks:ks_name":"Shyamkrishna Para",
    "ks:ks_pop":53,
    "ks:ks_type":"HABITATION",
    "name:eng_x_preferred":[
        "Shyamkrishna Para"
    ],
    "wof:name":"Shyamkrishna Para",
    "wof:placetype":"locality",
    "wof:population":53
},
  "geometry": {"coordinates":[91.753232,23.329678],"type":"Point"}
}