{
  "type": "Feature",
  "properties": {
    "gn:admin1_code":"35",
    "gn:admin2_code":"423.0",
    "gn:asciiname":"Amraudi",
    "gn:country_code":"IN",
    "gn:dem":413,
    "gn:feature_class":"P",
    "gn:feature_code":"PPL",
    "gn:name":"Amraudi",
    "gn:population":0,
    "gn:timezone":"Asia/Kolkata",
    "iso:country":"IN",
    "ks:ks_name":"Amrauda",
    "ks:ks_type":"VILLAGE",
    "name:eng_x_preferred":[
        "Amrauda"
    ],
    "name:eng_x_variant":[
        "Amraudi"
    ],
    "wof:name":"Amrauda",
    "wof:placetype":"locality"
},
  "geometry": {"coordinates":[77.440513,25.669463],"type":"Point"}
}