{
  "type": "Feature",
  "properties": {
    "gn:admin1_code":"35.0",
    "gn:admin2_code":"421.0",
    "gn:asciiname":"Kartar ka Tapra",
    "gn:country_code":"IN",
    "gn:dem":208,
    "gn:feature_class":"P",
    "gn:feature_code":"PPL",
    "gn:name":"Kart\u0101r ka Tapra",
    "gn:population":0,
    "gn:timezone":"Asia/Kolkata",
    "iso:country":"IN",
    "wof:name":"Kartar ka Tapra",
    "wof:placetype":"locality"
},
  "geometry": {"coordinates":[78.36426999999998,25.97421],"type":"Point"}
}