{
  "type": "Feature",
  "properties": {
    "iso:country":"IN",
    "ks:ks_name":"Gotabenoor",
    "ks:ks_pop":275,
    "ks:ks_type":"HABITATION",
    "name:eng_x_preferred":[
        "Gotabenoor"
    ],
    "wof:name":"Gotabenoor",
    "wof:placetype":"locality",
    "wof:population":275
},
  "geometry": {"coordinates":[81.29647799999999,19.606241],"type":"Point"}
}