{
  "type": "Feature",
  "properties": {
    "iso:country":"IN",
    "ks:ks_alt_nam":"konyewadi",
    "ks:ks_name":"Konyewadi",
    "ks:ks_pop":50,
    "ks:ks_type":"HABITATION",
    "name:eng_x_preferred":[
        "Konyewadi"
    ],
    "wof:name":"Konyewadi",
    "wof:placetype":"locality",
    "wof:population":50
},
  "geometry": {"coordinates":[73.567717,16.596551],"type":"Point"}
}