{
  "type": "Feature",
  "properties": {
    "iso:country":"IN",
    "ks:ks_name":"Kasim Aligarh",
    "ks:ks_pop":1228,
    "ks:ks_type":"HABITATION",
    "name:eng_x_preferred":[
        "Kasim Aligarh"
    ],
    "wof:name":"Kasim Aligarh",
    "wof:placetype":"locality",
    "wof:population":1228
},
  "geometry": {"coordinates":[88.30010900000001,22.978485],"type":"Point"}
}