{
  "type": "Feature",
  "properties": {
    "iso:country":"IN",
    "ks:ks_name":"Jorhadabari",
    "ks:ks_pop":1390,
    "ks:ks_type":"HABITATION",
    "name:eng_x_preferred":[
        "Jorhadabari"
    ],
    "wof:name":"Jorhadabari",
    "wof:placetype":"locality",
    "wof:population":1390
},
  "geometry": {"coordinates":[82.498665,22.25152],"type":"Point"}
}