{
  "type": "Feature",
  "properties": {
    "iso:country":"IN",
    "ks:ks_alt_nam":"lokhande pada",
    "ks:ks_name":"Lokhande Pada",
    "ks:ks_pop":36,
    "ks:ks_type":"HABITATION",
    "name:eng_x_preferred":[
        "Lokhande Pada"
    ],
    "wof:name":"Lokhande Pada",
    "wof:placetype":"locality",
    "wof:population":36
},
  "geometry": {"coordinates":[73.061688,19.732233],"type":"Point"}
}