{
  "type": "Feature",
  "properties": {
    "gn:admin1_code":"39.0",
    "gn:admin2_code":"061",
    "gn:asciiname":"Kolargaon",
    "gn:country_code":"IN",
    "gn:dem":1251,
    "gn:feature_class":"P",
    "gn:feature_code":"PPL",
    "gn:name":"Kol\u0101rgaon",
    "gn:population":0,
    "gn:timezone":"Asia/Kolkata",
    "iso:country":"IN",
    "wof:name":"Kolargaon",
    "wof:placetype":"locality"
},
  "geometry": {"coordinates":[78.69358000000003,29.92011],"type":"Point"}
}