{
  "type": "Feature",
  "properties": {
    "gn:admin1_code":"12.0",
    "gn:admin2_code":"003",
    "gn:asciiname":"Erad",
    "gn:country_code":"IN",
    "gn:dem":4141,
    "gn:feature_class":"P",
    "gn:feature_code":"PPL",
    "gn:name":"Erad",
    "gn:population":0,
    "gn:timezone":"Asia/Kolkata",
    "iso:country":"IN",
    "wof:name":"Erad",
    "wof:placetype":"locality"
},
  "geometry": {"coordinates":[78.19741999999999,33.95705],"type":"Point"}
}