{
  "type": "Feature",
  "properties": {
    "iso:country":"IN",
    "ks:ks_name":"Pabnashini",
    "ks:ks_pop":0,
    "ks:ks_type":"VILLAGE",
    "name:eng_x_preferred":[
        "Pabnashini"
    ],
    "wof:name":"Pabnashini",
    "wof:placetype":"locality",
    "wof:population":0
},
  "geometry": {"coordinates":[87.188889,22.73972],"type":"Point"}
}