{
  "type": "Feature",
  "properties": {
    "iso:country":"IN",
    "ks:ks_alt_nam":"Jhelarov FV",
    "ks:ks_name":"Jhelarov Fv",
    "ks:ks_pop":68,
    "ks:ks_type":"HABITATION",
    "name:eng_x_preferred":[
        "Jhelarov Fv"
    ],
    "wof:name":"Jhelarov Fv",
    "wof:placetype":"locality",
    "wof:population":68
},
  "geometry": {"coordinates":[82.028341,20.030048],"type":"Point"}
}