{
  "type": "Feature",
  "properties": {
    "iso:country":"IN",
    "ks:ks_name":"Balaji Tanda",
    "ks:ks_pop":845,
    "ks:ks_type":"HABITATION",
    "name:eng_x_preferred":[
        "Balaji Tanda"
    ],
    "wof:name":"Balaji Tanda",
    "wof:placetype":"locality",
    "wof:population":845
},
  "geometry": {"coordinates":[77.25860299999999,18.591098],"type":"Point"}
}