{
  "type": "Feature",
  "properties": {
    "iso:country":"IN",
    "ks:ks_name":"Burjamanuguda",
    "ks:ks_pop":88,
    "ks:ks_type":"HABITATION",
    "name:eng_x_preferred":[
        "Burjamanuguda"
    ],
    "wof:name":"Burjamanuguda",
    "wof:placetype":"locality",
    "wof:population":88
},
  "geometry": {"coordinates":[83.846243,18.761186],"type":"Point"}
}