{
  "type": "Feature",
  "properties": {
    "iso:country":"IN",
    "ks:ks_name":"Khubulla Chak",
    "ks:ks_pop":228,
    "ks:ks_type":"HABITATION",
    "name:eng_x_preferred":[
        "Khubulla Chak"
    ],
    "wof:name":"Khubulla Chak",
    "wof:placetype":"locality",
    "wof:population":228
},
  "geometry": {"coordinates":[82.987944,25.913969],"type":"Point"}
}