{
  "type": "Feature",
  "properties": {
    "iso:country":"IN",
    "ks:ks_name":"Neemrana",
    "ks:ks_pop":4217,
    "ks:ks_type":"URBAN",
    "ks:ks_uagg_main":0,
    "name:ast_x_preferred":[
        "Neemrana"
    ],
    "name:cat_x_preferred":[
        "Nimrana"
    ],
    "name:deu_x_preferred":[
        "Neemrana"
    ],
    "name:eng_x_preferred":[
        "Neemrana"
    ],
    "name:fra_x_preferred":[
        "Neemrana"
    ],
    "name:hin_x_preferred":[
        "\u0928\u0940\u092e\u0930\u093e\u0928\u093e"
    ],
    "name:jpn_x_preferred":[
        "\u30cb\u30e0\u30e9\u30ca"
    ],
    "name:nep_x_preferred":[
        "NIIT \u0935\u093f\u0936\u094d\u0935\u0935\u093f\u0926\u094d\u092f\u093e\u0932\u092f"
    ],
    "name:nld_x_preferred":[
        "Neemrana"
    ],
    "name:tam_x_preferred":[
        "\u0ba8\u0bc0\u0bae\u0bcd\u0bb0\u0bbe\u0ba9\u0bbe"
    ],
    "qs:name":"Neemrana",
    "qs:name_adm0":"India",
    "qs:name_adm1":"Rajasthan",
    "qs:photos":308,
    "qs:photos_1k":62,
    "qs:photos_9k":1,
    "qs:photos_9r":5,
    "qs:photos_all":308,
    "qs:photos_sr":5,
    "qs:placetype":"Town",
    "qs:pop_sr":"0",
    "wof:name":"Neemrana",
    "wof:placetype":"neighbourhood",
    "wof:population":4217
},
  "geometry": {"coordinates":[76.38499899999999,27.992469],"type":"Point"}
}