{
  "type": "Feature",
  "properties": {
    "iso:country":"IN",
    "ks:ks_name":"Biswalmunda",
    "ks:ks_pop":102,
    "ks:ks_type":"VILLAGE",
    "name:eng_x_preferred":[
        "Biswalmunda"
    ],
    "wof:name":"Biswalmunda",
    "wof:placetype":"locality",
    "wof:population":102
},
  "geometry": {"coordinates":[84.94837099999999,21.220103],"type":"Point"}
}