{
  "type": "Feature",
  "properties": {
    "iso:country":"IN",
    "ks:ks_name":"Bhagan",
    "ks:ks_pop":243,
    "ks:ks_type":"VILLAGE",
    "name:eng_x_preferred":[
        "Bhagan"
    ],
    "wof:name":"Bhagan",
    "wof:placetype":"locality",
    "wof:population":243
},
  "geometry": {"coordinates":[87.054213,24.48456],"type":"Point"}
}