{
  "type": "Feature",
  "properties": {
    "gn:admin1_code":"36",
    "gn:admin2_code":"158.0",
    "gn:asciiname":"Kunwarapur Gaura",
    "gn:country_code":"IN",
    "gn:dem":115,
    "gn:feature_class":"P",
    "gn:feature_code":"PPL",
    "gn:name":"Kunwar\u0101pur Gaura",
    "gn:population":0,
    "gn:timezone":"Asia/Kolkata",
    "iso:country":"IN",
    "wof:name":"Kunwarapur Gaura",
    "wof:placetype":"locality"
},
  "geometry": {"coordinates":[81.39565,26.14383],"type":"Point"}
}