{
  "type": "Feature",
  "properties": {
    "iso:country":"IN",
    "ks:ks_name":"Talramsagar",
    "ks:ks_pop":384,
    "ks:ks_type":"VILLAGE",
    "name:eng_x_preferred":[
        "Talramsagar"
    ],
    "wof:name":"Talramsagar",
    "wof:placetype":"locality",
    "wof:population":384
},
  "geometry": {"coordinates":[77.589896,26.58453],"type":"Point"}
}