{
  "type": "Feature",
  "properties": {
    "gn:admin1_code":"10.0",
    "gn:admin2_code":"102",
    "gn:asciiname":"Dhanauthi",
    "gn:country_code":"IN",
    "gn:dem":212,
    "gn:feature_class":"P",
    "gn:feature_code":"PPL",
    "gn:name":"Dhanauthi",
    "gn:population":0,
    "gn:timezone":"Asia/Kolkata",
    "iso:country":"IN",
    "name:und_x_variant":[
        "Dhanauthi Bari"
    ],
    "wof:name":"Dhanauthi",
    "wof:placetype":"locality"
},
  "geometry": {"coordinates":[75.49136,28.86829],"type":"Point"}
}