{
  "type": "Feature",
  "properties": {
    "iso:country":"IN",
    "ks:ks_name":"Meluguddehalla",
    "ks:ks_pop":80,
    "ks:ks_type":"HABITATION",
    "name:eng_x_preferred":[
        "Meluguddehalla"
    ],
    "wof:name":"Meluguddehalla",
    "wof:placetype":"locality",
    "wof:population":80
},
  "geometry": {"coordinates":[75.443218,13.51901],"type":"Point"}
}