{
  "type": "Feature",
  "properties": {
    "iso:country":"IN",
    "ks:ks_name":"Garaiguri Village",
    "ks:ks_pop":114,
    "ks:ks_type":"HABITATION",
    "ks:ks_uagg_main":0,
    "name:eng_x_preferred":[
        "Garaiguri Village"
    ],
    "wof:name":"Garaiguri Village",
    "wof:placetype":"neighbourhood",
    "wof:population":114
},
  "geometry": {"coordinates":[93.19362599999999,26.20773],"type":"Point"}
}