{
  "type": "Feature",
  "properties": {
    "iso:country":"IN",
    "ks:ks_name":"Mulapur",
    "ks:ks_pop":105,
    "ks:ks_type":"HABITATION",
    "name:eng_x_preferred":[
        "Mulapur"
    ],
    "wof:name":"Mulapur",
    "wof:placetype":"locality",
    "wof:population":105
},
  "geometry": {"coordinates":[73.43752499999999,18.579094],"type":"Point"}
}