{
  "type": "Feature",
  "properties": {
    "gn:admin1_code":"12.0",
    "gn:admin2_code":"006",
    "gn:asciiname":"Harir ka Nakka",
    "gn:country_code":"IN",
    "gn:dem":883,
    "gn:feature_class":"P",
    "gn:feature_code":"PPL",
    "gn:name":"Har\u012br ka Nakka",
    "gn:population":0,
    "gn:timezone":"Asia/Kolkata",
    "iso:country":"IN",
    "wof:name":"Harir ka Nakka",
    "wof:placetype":"locality"
},
  "geometry": {"coordinates":[74.47806,33.11907],"type":"Point"}
}