{
  "type": "Feature",
  "properties": {
    "gn:admin1_code":"25.0",
    "gn:admin2_code":"620.0",
    "gn:asciiname":"Sunarapperumalkovil",
    "gn:country_code":"IN",
    "gn:dem":38,
    "gn:feature_class":"P",
    "gn:feature_code":"PPL",
    "gn:name":"Sunarapperum\u0101lkovil",
    "gn:population":0,
    "gn:timezone":"Asia/Kolkata",
    "iso:country":"IN",
    "wof:name":"Sunarapperumalkovil",
    "wof:placetype":"neighbourhood"
},
  "geometry": {"coordinates":[79.30692999999999,10.93775],"type":"Point"}
}