{
  "type": "Feature",
  "properties": {
    "iso:country":"IN",
    "ks:ks_alt_nam":"Pattakaran kattuvalavu",
    "ks:ks_name":"Pattakaran Kattuvalavu",
    "ks:ks_pop":242,
    "ks:ks_type":"HABITATION",
    "name:eng_x_preferred":[
        "Pattakaran Kattuvalavu"
    ],
    "wof:name":"Pattakaran Kattuvalavu",
    "wof:placetype":"locality",
    "wof:population":242
},
  "geometry": {"coordinates":[77.662341,11.82619],"type":"Point"}
}