{
  "type": "Feature",
  "properties": {
    "iso:country":"IN",
    "ks:ks_name":"Sonpur",
    "ks:ks_pop":667,
    "ks:ks_type":"VILLAGE",
    "name:eng_x_preferred":[
        "Sonpur"
    ],
    "wof:name":"Sonpur",
    "wof:placetype":"locality",
    "wof:population":667
},
  "geometry": {"coordinates":[84.891104,24.141917],"type":"Point"}
}