{
  "type": "Feature",
  "properties": {
    "gn:admin1_code":"34.0",
    "gn:admin2_code":"203.0",
    "gn:asciiname":"Bharwalia",
    "gn:country_code":"IN",
    "gn:dem":92,
    "gn:feature_class":"P",
    "gn:feature_code":"PPL",
    "gn:name":"Bharwali\u0101",
    "gn:population":0,
    "gn:timezone":"Asia/Kolkata",
    "iso:country":"IN",
    "wof:name":"Bharwalia",
    "wof:placetype":"locality"
},
  "geometry": {"coordinates":[84.61620000000001,27.10218],"type":"Point"}
}