{
  "type": "Feature",
  "properties": {
    "gn:admin1_code":"16",
    "gn:admin2_code":"501.0",
    "gn:asciiname":"Paranda",
    "gn:country_code":"IN",
    "gn:dem":347,
    "gn:feature_class":"P",
    "gn:feature_code":"PPL",
    "gn:name":"Paranda",
    "gn:population":0,
    "gn:timezone":"Asia/Kolkata",
    "iso:country":"IN",
    "name:ben_x_preferred":[
        "\u09aa\u09be\u09b0\u09be\u09a8\u09cd\u09a6\u09be"
    ],
    "name:bpy_x_preferred":[
        "\u09aa\u09be\u09b0\u09be\u09a8\u09cd\u09a6\u09be"
    ],
    "name:ita_x_preferred":[
        "Paranda"
    ],
    "name:msa_x_preferred":[
        "Paranda"
    ],
    "name:nld_x_preferred":[
        "Paranda"
    ],
    "name:por_x_preferred":[
        "Paranda"
    ],
    "name:urd_x_preferred":[
        "\u067e\u0631\u0627\u0646\u0688\u0627"
    ],
    "name:vie_x_preferred":[
        "Paranda"
    ],
    "name:zho_x_preferred":[
        "\u5e15\u5170\u8fbe"
    ],
    "wof:name":"Paranda",
    "wof:placetype":"locality"
},
  "geometry": {"coordinates":[77.12495,20.61175],"type":"Point"}
}