{
  "type": "Feature",
  "properties": {
    "gn:admin1_code":"16",
    "gn:admin2_code":"500.0",
    "gn:asciiname":"Gandhari",
    "gn:country_code":"IN",
    "gn:dem":514,
    "gn:feature_class":"P",
    "gn:feature_code":"PPL",
    "gn:name":"G\u0101ndhari",
    "gn:population":0,
    "gn:timezone":"Asia/Kolkata",
    "iso:country":"IN",
    "name:fra_x_preferred":[
        "G\u0101ndh\u0101r\u012b"
    ],
    "name:hin_x_preferred":[
        "\u0917\u093e\u0902\u0927\u093e\u0930\u0940"
    ],
    "name:rus_x_preferred":[
        "\u0413\u0430\u043d\u0434\u0445\u0430\u0440\u0438"
    ],
    "wof:name":"Gandhari",
    "wof:placetype":"locality"
},
  "geometry": {"coordinates":[76.60706999999999,19.87926],"type":"Point"}
}