{
  "type": "Feature",
  "properties": {
    "gn:admin1_code":"12.0",
    "gn:admin2_code":"021",
    "gn:asciiname":"Jaralan da Chak",
    "gn:country_code":"IN",
    "gn:dem":304,
    "gn:feature_class":"P",
    "gn:feature_code":"PPL",
    "gn:name":"Jar\u0101l\u0101n da Chak",
    "gn:population":0,
    "gn:timezone":"Asia/Kolkata",
    "iso:country":"IN",
    "name:und_x_variant":[
        "Jar\u0101l\u0101n da Chak",
        "Jar\u0101le Chak"
    ],
    "wof:name":"Jaralan da Chak",
    "wof:placetype":"locality"
},
  "geometry": {"coordinates":[74.88053000000002,32.644],"type":"Point"}
}