{
  "type": "Feature",
  "properties": {
    "gn:admin1_code":"38",
    "gn:admin2_code":"367.0",
    "gn:asciiname":"Serubatoli",
    "gn:country_code":"IN",
    "gn:dem":280,
    "gn:feature_class":"P",
    "gn:feature_code":"PPL",
    "gn:name":"Serub\u0101toli",
    "gn:population":0,
    "gn:timezone":"Asia/Kolkata",
    "iso:country":"IN",
    "wof:name":"Serubatoli",
    "wof:placetype":"locality"
},
  "geometry": {"coordinates":[85.06888000000002,22.56998],"type":"Point"}
}