{
  "type": "Feature",
  "properties": {
    "iso:country":"IN",
    "ks:ks_name":"Dharampur",
    "ks:ks_pop":1847,
    "ks:ks_type":"VILLAGE",
    "name:eng_x_preferred":[
        "Dharampur"
    ],
    "wof:name":"Dharampur",
    "wof:placetype":"locality",
    "wof:population":1847
},
  "geometry": {"coordinates":[84.19091,27.130561],"type":"Point"}
}