{
  "type": "Feature",
  "properties": {
    "iso:country":"IN",
    "ks:ks_name":"Melpathy",
    "ks:ks_pop":312,
    "ks:ks_type":"HABITATION",
    "name:eng_x_preferred":[
        "Melpathy"
    ],
    "wof:name":"Melpathy",
    "wof:placetype":"locality",
    "wof:population":312
},
  "geometry": {"coordinates":[79.403092,10.921667],"type":"Point"}
}