{
  "type": "Feature",
  "properties": {
    "iso:country":"IN",
    "ks:ks_name":"Dakhin Tola.",
    "ks:ks_pop":187,
    "ks:ks_type":"HABITATION",
    "ks:ks_uagg_main":0,
    "name:eng_x_preferred":[
        "Dakhin Tola."
    ],
    "wof:name":"Dakhin Tola.",
    "wof:placetype":"neighbourhood",
    "wof:population":187
},
  "geometry": {"coordinates":[83.996045,27.031125],"type":"Point"}
}