{
  "type": "Feature",
  "properties": {
    "iso:country":"IN",
    "ks:ks_name":"Raighati",
    "ks:ks_pop":222,
    "ks:ks_type":"HABITATION",
    "name:eng_x_preferred":[
        "Raighati"
    ],
    "wof:name":"Raighati",
    "wof:placetype":"locality",
    "wof:population":222
},
  "geometry": {"coordinates":[85.876267,21.068496],"type":"Point"}
}