{
  "type": "Feature",
  "properties": {
    "iso:country":"IN",
    "ks:ks_name":"Amtereng",
    "ks:ks_pop":478,
    "ks:ks_type":"HABITATION",
    "name:eng_x_preferred":[
        "Amtereng"
    ],
    "wof:name":"Amtereng",
    "wof:placetype":"locality",
    "wof:population":478
},
  "geometry": {"coordinates":[92.500237,25.990012],"type":"Point"}
}