{
  "type": "Feature",
  "properties": {
    "iso:country":"IN",
    "ks:ks_alt_nam":"NORTH TOLA",
    "ks:ks_name":"North Tola",
    "ks:ks_pop":133,
    "ks:ks_type":"HABITATION",
    "ks:ks_uagg_main":0,
    "name:eng_x_preferred":[
        "North Tola"
    ],
    "wof:name":"North Tola",
    "wof:placetype":"neighbourhood",
    "wof:population":133
},
  "geometry": {"coordinates":[85.832076,26.211095],"type":"Point"}
}