{
  "type": "Feature",
  "properties": {
    "iso:country":"IN",
    "ks:ks_name":"Batugudde",
    "ks:ks_pop":990,
    "ks:ks_type":"HABITATION",
    "name:eng_x_preferred":[
        "Batugudde"
    ],
    "wof:name":"Batugudde",
    "wof:placetype":"locality",
    "wof:population":990
},
  "geometry": {"coordinates":[75.259238,12.984483],"type":"Point"}
}