{
  "type": "Feature",
  "properties": {
    "iso:country":"IN",
    "ks:ks_name":"Hanumangarhi(581)",
    "ks:ks_pop":1,
    "ks:ks_type":"HABITATION",
    "name:eng_x_preferred":[
        "Hanumangarhi(581)"
    ],
    "wof:name":"Hanumangarhi(581)",
    "wof:placetype":"locality",
    "wof:population":1
},
  "geometry": {"coordinates":[81.623847,24.947304],"type":"Point"}
}