{
  "type": "Feature",
  "properties": {
    "gn:admin1_code":"39.0",
    "gn:admin2_code":"61.0",
    "gn:asciiname":"Kaphlekh",
    "gn:country_code":"IN",
    "gn:dem":1661,
    "gn:feature_class":"P",
    "gn:feature_code":"PPL",
    "gn:name":"Kaphlekh",
    "gn:population":0,
    "gn:timezone":"Asia/Kolkata",
    "iso:country":"IN",
    "wof:name":"Kaphlekh",
    "wof:placetype":"locality"
},
  "geometry": {"coordinates":[79.14749,29.98863],"type":"Point"}
}