{
  "type": "Feature",
  "properties": {
    "gn:admin1_code":"2.0",
    "gn:admin2_code":"552.0",
    "gn:asciiname":"Dharmapuram",
    "gn:country_code":"IN",
    "gn:dem":529,
    "gn:feature_class":"P",
    "gn:feature_code":"PPL",
    "gn:name":"Dharm\u0101puram",
    "gn:population":0,
    "gn:timezone":"Asia/Kolkata",
    "iso:country":"IN",
    "name:tel_x_preferred":[
        "\u0c27\u0c30\u0c4d\u0c2e\u0c2a\u0c41\u0c30\u0c02"
    ],
    "wof:name":"Dharmapuram",
    "wof:placetype":"neighbourhood"
},
  "geometry": {"coordinates":[77.75597,15.29734],"type":"Point"}
}