{
  "type": "Feature",
  "properties": {
    "iso:country":"IN",
    "ks:ks_name":"Kothe Machaki Khurd",
    "ks:ks_pop":290,
    "ks:ks_type":"HABITATION",
    "name:eng_x_preferred":[
        "Kothe Machaki Khurd"
    ],
    "wof:name":"Kothe Machaki Khurd",
    "wof:placetype":"locality",
    "wof:population":290
},
  "geometry": {"coordinates":[74.66588400000001,30.700943],"type":"Point"}
}