{
  "type": "Feature",
  "properties": {
    "iso:country":"IN",
    "ks:ks_name":"Putiaguda",
    "ks:ks_pop":504,
    "ks:ks_type":"HABITATION",
    "name:eng_x_preferred":[
        "Putiaguda"
    ],
    "wof:name":"Putiaguda",
    "wof:placetype":"locality",
    "wof:population":504
},
  "geometry": {"coordinates":[82.08849600000001,18.403358],"type":"Point"}
}