{
  "type": "Feature",
  "properties": {
    "gn:admin1_code":"25.0",
    "gn:admin2_code":"604.0",
    "gn:asciiname":"Kunnavakkam",
    "gn:country_code":"IN",
    "gn:dem":36,
    "gn:feature_class":"P",
    "gn:feature_code":"PPL",
    "gn:name":"Kunnav\u0101kkam",
    "gn:population":0,
    "gn:timezone":"Asia/Kolkata",
    "iso:country":"IN",
    "ks:ks_alt_nam":"Kunnav\u0101kkam",
    "ks:ks_name":"Kunnavakkam",
    "ks:ks_pop":160,
    "ks:ks_type":"VILLAGE",
    "name:eng_x_preferred":[
        "Kunnavakkam"
    ],
    "name:eng_x_variant":[
        "Kunnav\u0101kkam"
    ],
    "wof:name":"Kunnavakkam",
    "wof:placetype":"locality",
    "wof:population":160
},
  "geometry": {"coordinates":[79.865054,12.537971],"type":"Point"}
}