{
  "type": "Feature",
  "properties": {
    "iso:country":"IN",
    "ks:ks_name":"Narangi Jiunath",
    "ks:ks_pop":2437,
    "ks:ks_type":"VILLAGE",
    "ks:ks_uagg_main":0,
    "name:eng_x_preferred":[
        "Narangi Jiunath"
    ],
    "wof:name":"Narangi Jiunath",
    "wof:placetype":"neighbourhood",
    "wof:population":2437
},
  "geometry": {"coordinates":[85.170462,26.132022],"type":"Point"}
}