{
  "type": "Feature",
  "properties": {
    "gn:admin1_code":"2.0",
    "gn:admin2_code":"553.0",
    "gn:asciiname":"Chikirevulapalle",
    "gn:country_code":"IN",
    "gn:dem":667,
    "gn:feature_class":"P",
    "gn:feature_code":"PPL",
    "gn:name":"Ch\u012bkirevulapalle",
    "gn:population":0,
    "gn:timezone":"Asia/Kolkata",
    "iso:country":"IN",
    "wof:name":"Chikirevulapalle",
    "wof:placetype":"locality"
},
  "geometry": {"coordinates":[78.03464,13.87635],"type":"Point"}
}