{
  "type": "Feature",
  "properties": {
    "iso:country":"IN",
    "ks:ks_name":"Langtuk Tokbi",
    "ks:ks_pop":85,
    "ks:ks_type":"HABITATION",
    "name:eng_x_preferred":[
        "Langtuk Tokbi"
    ],
    "wof:name":"Langtuk Tokbi",
    "wof:placetype":"locality",
    "wof:population":85
},
  "geometry": {"coordinates":[93.51191900000001,26.508606],"type":"Point"}
}