{
  "type": "Feature",
  "properties": {
    "iso:country":"IN",
    "ks:ks_alt_nam":"Pakhana toli",
    "ks:ks_name":"Pakhana Toli",
    "ks:ks_pop":126,
    "ks:ks_type":"HABITATION",
    "name:eng_x_preferred":[
        "Pakhana Toli"
    ],
    "wof:name":"Pakhana Toli",
    "wof:placetype":"locality",
    "wof:population":126
},
  "geometry": {"coordinates":[84.031733,23.253173],"type":"Point"}
}