{
  "type": "Feature",
  "properties": {
    "iso:country":"IN",
    "ks:ks_name":"Ambalima",
    "ks:ks_pop":166,
    "ks:ks_type":"VILLAGE",
    "name:eng_x_preferred":[
        "Ambalima"
    ],
    "wof:name":"Ambalima",
    "wof:placetype":"locality",
    "wof:population":166
},
  "geometry": {"coordinates":[83.833702,19.658073],"type":"Point"}
}