{
  "type": "Feature",
  "properties": {
    "gn:admin1_code":"36.0",
    "gn:admin2_code":"161",
    "gn:asciiname":"Kalandra",
    "gn:country_code":"IN",
    "gn:dem":149,
    "gn:feature_class":"P",
    "gn:feature_code":"PPL",
    "gn:name":"Kalandra",
    "gn:population":0,
    "gn:timezone":"Asia/Kolkata",
    "iso:country":"IN",
    "name:bul_x_preferred":[
        "\u041a\u0430\u043b\u0430\u043d\u0434\u0440\u0430"
    ],
    "name:ceb_x_preferred":[
        "Kal\u00e1ndra"
    ],
    "name:ell_x_preferred":[
        "\u039a\u03b1\u03bb\u03ac\u03bd\u03b4\u03c1\u03b1 \u03a7\u03b1\u03bb\u03ba\u03b9\u03b4\u03b9\u03ba\u03ae\u03c2"
    ],
    "name:mkd_x_preferred":[
        "\u041a\u0430\u043b\u0430\u043d\u0434\u0440\u0430"
    ],
    "name:swe_x_preferred":[
        "Kal\u00e1ndra"
    ],
    "wof:name":"Kalandra",
    "wof:placetype":"locality"
},
  "geometry": {"coordinates":[79.24365999999998,26.84879],"type":"Point"}
}