{
  "type": "Feature",
  "properties": {
    "iso:country":"IN",
    "ks:ks_name":"Vachetavadi",
    "ks:ks_pop":115,
    "ks:ks_type":"HABITATION",
    "name:eng_x_preferred":[
        "Vachetavadi"
    ],
    "wof:name":"Vachetavadi",
    "wof:placetype":"locality",
    "wof:population":115
},
  "geometry": {"coordinates":[76.77300200000001,9.331752],"type":"Point"}
}