{
  "type": "Feature",
  "properties": {
    "gn:admin1_code":"21.0",
    "gn:admin2_code":"389.0",
    "gn:asciiname":"Jodur",
    "gn:country_code":"IN",
    "gn:dem":593,
    "gn:feature_class":"P",
    "gn:feature_code":"PPL",
    "gn:name":"Jodur",
    "gn:population":0,
    "gn:timezone":"Asia/Kolkata",
    "iso:country":"IN",
    "wof:name":"Jodur",
    "wof:placetype":"locality"
},
  "geometry": {"coordinates":[83.99044000000001,18.89939],"type":"Point"}
}