{
  "type": "Feature",
  "properties": {
    "gn:admin1_code":"36",
    "gn:admin2_code":"180.0",
    "gn:asciiname":"Pura Hata",
    "gn:country_code":"IN",
    "gn:dem":116,
    "gn:feature_class":"P",
    "gn:feature_code":"PPL",
    "gn:name":"Pura H\u0101ta",
    "gn:population":0,
    "gn:timezone":"Asia/Kolkata",
    "iso:country":"IN",
    "wof:name":"Pura Hata",
    "wof:placetype":"neighbourhood"
},
  "geometry": {"coordinates":[81.67386999999999,27.34015],"type":"Point"}
}