{
  "type": "Feature",
  "properties": {
    "gn:admin1_code":"21",
    "gn:admin2_code":"396.0",
    "gn:asciiname":"Dongarabari",
    "gn:country_code":"IN",
    "gn:dem":435,
    "gn:feature_class":"P",
    "gn:feature_code":"PPL",
    "gn:name":"Dongarab\u0101ri",
    "gn:population":0,
    "gn:timezone":"Asia/Kolkata",
    "iso:country":"IN",
    "ks:ks_alt_nam":"Dongarab\u0101ri",
    "ks:ks_name":"Dongarabari",
    "ks:ks_type":"VILLAGE",
    "name:eng_x_preferred":[
        "Dongarabari"
    ],
    "name:eng_x_variant":[
        "Dongarab\u0101ri"
    ],
    "wof:name":"Dongarabari",
    "wof:placetype":"locality"
},
  "geometry": {"coordinates":[83.490909,19.824651],"type":"Point"}
}