{
  "type": "Feature",
  "properties": {
    "iso:country":"IN",
    "ks:ks_name":"Passian Purwa",
    "ks:ks_pop":93,
    "ks:ks_type":"HABITATION",
    "name:eng_x_preferred":[
        "Passian Purwa"
    ],
    "wof:name":"Passian Purwa",
    "wof:placetype":"locality",
    "wof:population":93
},
  "geometry": {"coordinates":[82.25952700000001,27.313917],"type":"Point"}
}