{
  "type": "Feature",
  "properties": {
    "gn:admin1_code":"25.0",
    "gn:admin2_code":"611.0",
    "gn:asciiname":"Nalagiri",
    "gn:country_code":"IN",
    "gn:dem":1743,
    "gn:feature_class":"P",
    "gn:feature_code":"PPL",
    "gn:name":"Nalagiri",
    "gn:population":0,
    "gn:timezone":"Asia/Kolkata",
    "iso:country":"IN",
    "wof:name":"Nalagiri",
    "wof:placetype":"locality"
},
  "geometry": {"coordinates":[76.84619000000001,11.468],"type":"Point"}
}