{
  "type": "Feature",
  "properties": {
    "iso:country":"IN",
    "ks:ks_name":"Saraiya",
    "ks:ks_type":"VILLAGE",
    "name:eng_x_preferred":[
        "Saraiya"
    ],
    "wof:name":"Saraiya",
    "wof:placetype":"locality"
},
  "geometry": {"coordinates":[82.773692,25.716628],"type":"Point"}
}