{
  "type": "Feature",
  "properties": {
    "iso:country":"IN",
    "ks:ks_name":"Tara Hadia",
    "ks:ks_pop":1211,
    "ks:ks_type":"VILLAGE",
    "ks:ks_uagg_main":0,
    "name:eng_x_preferred":[
        "Tara Hadia"
    ],
    "wof:name":"Tara Hadia",
    "wof:placetype":"neighbourhood",
    "wof:population":1211
},
  "geometry": {"coordinates":[88.542449,22.568547],"type":"Point"}
}