{
  "type": "Feature",
  "properties": {
    "gn:admin1_code":"36",
    "gn:admin2_code":"146.0",
    "gn:asciiname":"Barara",
    "gn:country_code":"IN",
    "gn:dem":173,
    "gn:feature_class":"P",
    "gn:feature_code":"PPL",
    "gn:name":"Bar\u0101ra",
    "gn:population":0,
    "gn:timezone":"Asia/Kolkata",
    "iso:country":"IN",
    "name:hin_x_preferred":[
        "\u092c\u0930\u093e\u0921\u093c\u093e"
    ],
    "wof:name":"Barara",
    "wof:placetype":"locality"
},
  "geometry": {"coordinates":[77.90066,27.13328],"type":"Point"}
}