{
  "type": "Feature",
  "properties": {
    "iso:country":"IN",
    "ks:ks_name":"Enjal",
    "ks:ks_pop":507,
    "ks:ks_type":"HABITATION",
    "name:eng_x_preferred":[
        "Enjal"
    ],
    "wof:name":"Enjal",
    "wof:placetype":"locality",
    "wof:population":507
},
  "geometry": {"coordinates":[79.638063,10.6795],"type":"Point"}
}