{
  "type": "Feature",
  "properties": {
    "iso:country":"IN",
    "ks:ks_name":"Dhuvadkhar",
    "ks:ks_pop":100,
    "ks:ks_type":"HABITATION",
    "name:eng_x_preferred":[
        "Dhuvadkhar"
    ],
    "wof:name":"Dhuvadkhar",
    "wof:placetype":"locality",
    "wof:population":100
},
  "geometry": {"coordinates":[73.014535,18.684581],"type":"Point"}
}