{
  "type": "Feature",
  "properties": {
    "gn:admin1_code":"38.0",
    "gn:admin2_code":"348.0",
    "gn:asciiname":"Birhorwa",
    "gn:country_code":"IN",
    "gn:dem":307,
    "gn:feature_class":"P",
    "gn:feature_code":"PPL",
    "gn:name":"Birhorw\u0101",
    "gn:population":0,
    "gn:timezone":"Asia/Kolkata",
    "iso:country":"IN",
    "ks:ks_alt_nam":"Birhorw\u0101",
    "ks:ks_name":"Birhorwa",
    "ks:ks_pop":0,
    "ks:ks_type":"VILLAGE",
    "name:eng_x_preferred":[
        "Birhorwa"
    ],
    "name:eng_x_variant":[
        "Birhorw\u0101"
    ],
    "wof:name":"Birhorwa",
    "wof:placetype":"locality",
    "wof:population":0
},
  "geometry": {"coordinates":[85.39411200000001,24.530248],"type":"Point"}
}