{
  "type": "Feature",
  "properties": {
    "iso:country":"IN",
    "ks:ks_name":"Ranisahii",
    "ks:ks_pop":836,
    "ks:ks_type":"HABITATION",
    "name:eng_x_preferred":[
        "Ranisahii"
    ],
    "wof:name":"Ranisahii",
    "wof:placetype":"locality",
    "wof:population":836
},
  "geometry": {"coordinates":[84.652269,20.447034],"type":"Point"}
}