{
  "type": "Feature",
  "properties": {
    "iso:country":"IN",
    "ks:ks_name":"Khirberwa",
    "ks:ks_pop":719,
    "ks:ks_type":"HABITATION",
    "name:eng_x_preferred":[
        "Khirberwa"
    ],
    "wof:name":"Khirberwa",
    "wof:placetype":"locality",
    "wof:population":719
},
  "geometry": {"coordinates":[85.496871,23.835621],"type":"Point"}
}