{
  "type": "Feature",
  "properties": {
    "iso:country":"IN",
    "ks:ks_name":"Tembwadi",
    "ks:ks_pop":39,
    "ks:ks_type":"HABITATION",
    "name:eng_x_preferred":[
        "Tembwadi"
    ],
    "wof:name":"Tembwadi",
    "wof:placetype":"locality",
    "wof:population":39
},
  "geometry": {"coordinates":[73.631905,16.114963],"type":"Point"}
}