{
  "type": "Feature",
  "properties": {
    "gn:admin1_code":"34.0",
    "gn:admin2_code":"218.0",
    "gn:asciiname":"Sherpur",
    "gn:country_code":"IN",
    "gn:dem":65,
    "gn:feature_class":"P",
    "gn:feature_code":"PPL",
    "gn:name":"Sherpur",
    "gn:population":0,
    "gn:timezone":"Asia/Kolkata",
    "iso:country":"IN",
    "name:ara_x_preferred":[
        "\u0634\u064a\u0631\u0628\u0648\u0631"
    ],
    "name:ben_bn_x_preferred":[
        "\u09b6\u09c7\u09b0\u09aa\u09c1\u09b0"
    ],
    "name:ben_in_x_preferred":[
        "\u09b6\u09c7\u09b0\u09aa\u09c1\u09b0"
    ],
    "name:ceb_x_preferred":[
        "Sherpur"
    ],
    "name:guj_x_preferred":[
        "\u0ab6\u0ac7\u0ab0\u0aaa\u0ac1\u0ab0"
    ],
    "name:hin_x_preferred":[
        "\u0936\u0947\u0930\u092a\u0941\u0930"
    ],
    "name:kan_x_preferred":[
        "\u0cb6\u0cc7\u0cb0\u0ccd"
    ],
    "name:mal_x_preferred":[
        "\u0d37\u0d46\u0d7c\u0d2a\u0d42\u0d7c"
    ],
    "name:mar_x_preferred":[
        "\u0936\u0947\u0930\u092a\u0942\u0930"
    ],
    "name:nld_x_preferred":[
        "Sherpur"
    ],
    "name:pan_x_preferred":[
        "\u0a36\u0a47\u0a30\u0a2a\u0a41\u0a30"
    ],
    "name:rus_x_preferred":[
        "\u0428\u0435\u0440\u043f\u0443\u0440"
    ],
    "name:swe_x_preferred":[
        "Sherpur"
    ],
    "name:tam_x_preferred":[
        "\u0bb7\u0bc7\u0bb0\u0bcd\u0baa\u0bc2\u0bb0\u0bcd"
    ],
    "name:tel_x_preferred":[
        "\u0c37\u0c47\u0c30\u0c4d"
    ],
    "name:urd_x_preferred":[
        "\u0634\u06cc\u0631\u067e\u0648\u0631"
    ],
    "wof:name":"Sherpur",
    "wof:placetype":"locality"
},
  "geometry": {"coordinates":[84.59659000000001,26.22287],"type":"Point"}
}