{
  "type": "Feature",
  "properties": {
    "iso:country":"IN",
    "ks:ks_name":"Raipur",
    "ks:ks_pop":1526,
    "ks:ks_type":"VILLAGE",
    "name:eng_x_preferred":[
        "Raipur"
    ],
    "wof:name":"Raipur",
    "wof:placetype":"locality",
    "wof:population":1526
},
  "geometry": {"coordinates":[77.84071900000001,25.562886],"type":"Point"}
}