{
  "type": "Feature",
  "properties": {
    "iso:country":"IN",
    "ks:ks_name":"Andukhal",
    "ks:ks_pop":4,
    "ks:ks_type":"HABITATION",
    "name:eng_x_preferred":[
        "Andukhal"
    ],
    "wof:name":"Andukhal",
    "wof:placetype":"locality",
    "wof:population":4
},
  "geometry": {"coordinates":[83.192768,19.389457],"type":"Point"}
}