{
  "type": "Feature",
  "properties": {
    "gn:country":"IN",
    "iso:country":"IN",
    "qs:name":"Sernabatim",
    "qs:name_adm0":"India",
    "qs:name_adm1":"Goa",
    "qs:photos":304,
    "qs:photos_1k":62,
    "qs:photos_9k":1,
    "qs:photos_9r":5,
    "qs:photos_all":304,
    "qs:photos_sr":5,
    "qs:placetype":"Town",
    "qs:pop_sr":"0",
    "wof:name":"Sernabatim",
    "wof:placetype":"locality"
},
  "geometry": {"coordinates":[73.924083,15.222659],"type":"Point"}
}