{
  "type": "Feature",
  "properties": {
    "gn:admin1_code":"24.0",
    "gn:admin2_code":"100.0",
    "gn:asciiname":"Shoratada",
    "gn:country_code":"IN",
    "gn:dem":204,
    "gn:feature_class":"P",
    "gn:feature_code":"PPL",
    "gn:name":"Shor\u0101t\u0101da",
    "gn:population":0,
    "gn:timezone":"Asia/Kolkata",
    "iso:country":"IN",
    "wof:name":"Shoratada",
    "wof:placetype":"locality"
},
  "geometry": {"coordinates":[75.14523,28.88534000000001],"type":"Point"}
}