{
  "type": "Feature",
  "properties": {
    "gn:admin1_code":"39.0",
    "gn:admin2_code":"62.0",
    "gn:asciiname":"Bajar",
    "gn:country_code":"IN",
    "gn:dem":1312,
    "gn:feature_class":"P",
    "gn:feature_code":"PPL",
    "gn:name":"B\u0101jar",
    "gn:population":0,
    "gn:timezone":"Asia/Kolkata",
    "iso:country":"IN",
    "ks:ks_alt_nam":"B\u0101jar",
    "ks:ks_name":"Bajar",
    "ks:ks_pop":226,
    "ks:ks_type":"VILLAGE",
    "name:eng_x_preferred":[
        "Bajar"
    ],
    "name:eng_x_variant":[
        "B\u0101jar"
    ],
    "wof:name":"Bajar",
    "wof:placetype":"locality",
    "wof:population":226
},
  "geometry": {"coordinates":[79.91887199999999,29.78548],"type":"Point"}
}