{
  "type": "Feature",
  "properties": {
    "iso:country":"IN",
    "ks:ks_name":"Abadi Chan Chak",
    "ks:ks_pop":550,
    "ks:ks_type":"HABITATION",
    "name:eng_x_preferred":[
        "Abadi Chan Chak"
    ],
    "wof:name":"Abadi Chan Chak",
    "wof:placetype":"locality",
    "wof:population":550
},
  "geometry": {"coordinates":[74.727205,31.19116],"type":"Point"}
}