{
  "type": "Feature",
  "properties": {
    "iso:country":"IN",
    "ks:ks_name":"Mannandiyur",
    "ks:ks_pop":195,
    "ks:ks_type":"HABITATION",
    "name:eng_x_preferred":[
        "Mannandiyur"
    ],
    "wof:name":"Mannandiyur",
    "wof:placetype":"locality",
    "wof:population":195
},
  "geometry": {"coordinates":[78.53749500000001,12.292115],"type":"Point"}
}