{
  "type": "Feature",
  "properties": {
    "gn:admin1_code":"37.0",
    "gn:admin2_code":"404.0",
    "gn:asciiname":"Nawapara",
    "gn:country_code":"IN",
    "gn:dem":323,
    "gn:feature_class":"P",
    "gn:feature_code":"PPL",
    "gn:name":"Nawapara",
    "gn:population":0,
    "gn:timezone":"Asia/Kolkata",
    "iso:country":"IN",
    "wof:name":"Nawapara",
    "wof:placetype":"locality"
},
  "geometry": {"coordinates":[82.29363000000002,22.41517],"type":"Point"}
}