{
  "type": "Feature",
  "properties": {
    "gn:admin1_code":"34.0",
    "gn:admin2_code":"217.0",
    "gn:asciiname":"Banjaria",
    "gn:country_code":"IN",
    "gn:dem":77,
    "gn:feature_class":"P",
    "gn:feature_code":"PPL",
    "gn:name":"Banjaria",
    "gn:population":0,
    "gn:timezone":"Asia/Kolkata",
    "iso:country":"IN",
    "ks:ks_name":"Banjaria",
    "ks:ks_pop":2047,
    "ks:ks_type":"VILLAGE",
    "name:eng_x_preferred":[
        "Banjaria"
    ],
    "wof:name":"Banjaria",
    "wof:placetype":"locality",
    "wof:population":2047
},
  "geometry": {"coordinates":[84.2509,26.57633],"type":"Point"}
}