{
  "type": "Feature",
  "properties": {
    "gn:admin1_code":"36",
    "gn:admin2_code":"159.0",
    "gn:asciiname":"Baura",
    "gn:country_code":"IN",
    "gn:dem":150,
    "gn:feature_class":"P",
    "gn:feature_code":"PPL",
    "gn:name":"Baura",
    "gn:population":0,
    "gn:timezone":"Asia/Kolkata",
    "iso:country":"IN",
    "name:mal_x_preferred":[
        "\u0d2c\u0d57\u0d31"
    ],
    "name:pan_x_preferred":[
        "\u0a2d\u0a4c\u0a30\u0a3e"
    ],
    "wof:name":"Baura",
    "wof:placetype":"locality"
},
  "geometry": {"coordinates":[79.24703000000002,27.65878],"type":"Point"}
}