{
  "type": "Feature",
  "properties": {
    "iso:country":"IN",
    "ks:ks_name":"Bhogapur",
    "ks:ks_pop":79,
    "ks:ks_type":"VILLAGE",
    "name:eng_x_preferred":[
        "Bhogapur"
    ],
    "wof:name":"Bhogapur",
    "wof:placetype":"locality",
    "wof:population":79
},
  "geometry": {"coordinates":[86.223967,20.243508],"type":"Point"}
}