{
  "type": "Feature",
  "properties": {
    "iso:country":"IN",
    "ks:ks_name":"Kiadingiri",
    "ks:ks_pop":456,
    "ks:ks_type":"HABITATION",
    "name:eng_x_preferred":[
        "Kiadingiri"
    ],
    "wof:name":"Kiadingiri",
    "wof:placetype":"locality",
    "wof:population":456
},
  "geometry": {"coordinates":[86.44047500000001,20.258785],"type":"Point"}
}