{
  "type": "Feature",
  "properties": {
    "iso:country":"IN",
    "ks:ks_name":"Dukhisukhi II",
    "ks:ks_pop":510,
    "ks:ks_type":"VILLAGE",
    "name:eng_x_preferred":[
        "Dukhisukhi II"
    ],
    "wof:name":"Dukhisukhi II",
    "wof:placetype":"locality",
    "wof:population":510
},
  "geometry": {"coordinates":[89.870637,26.179741],"type":"Point"}
}