{
  "type": "Feature",
  "properties": {
    "gn:admin1_code":"35.0",
    "gn:admin2_code":"424",
    "gn:asciiname":"Tindari",
    "gn:country_code":"IN",
    "gn:dem":361,
    "gn:feature_class":"P",
    "gn:feature_code":"PPL",
    "gn:name":"Tind\u0101ri",
    "gn:population":0,
    "gn:timezone":"Asia/Kolkata",
    "iso:country":"IN",
    "name:cat_x_preferred":[
        "Tindaris"
    ],
    "name:deu_x_preferred":[
        "Tindari"
    ],
    "name:ell_x_preferred":[
        "\u03a4\u03af\u03bd\u03c4\u03b1\u03c1\u03b9"
    ],
    "name:eus_x_preferred":[
        "Tindaris"
    ],
    "name:fas_x_preferred":[
        "\u062a\u06cc\u0646\u062f\u0627\u0631\u06cc"
    ],
    "name:fin_x_preferred":[
        "Tyndaris"
    ],
    "name:fra_x_preferred":[
        "Tyndaris"
    ],
    "name:ita_x_preferred":[
        "Tindari"
    ],
    "name:kat_x_preferred":[
        "\u10e2\u10d8\u10dc\u10d3\u10d0\u10e0\u10d8"
    ],
    "name:lat_x_preferred":[
        "Tyndaris"
    ],
    "name:nld_x_preferred":[
        "Tindari"
    ],
    "name:por_x_preferred":[
        "Tindari"
    ],
    "name:scn_x_preferred":[
        "Lu T\u00ecnnaru"
    ],
    "name:spa_x_preferred":[
        "T\u00edndaris"
    ],
    "name:srp_x_preferred":[
        "\u0422\u0438\u043d\u0434\u0430\u0440\u0438"
    ],
    "name:swe_x_preferred":[
        "Tyndaris"
    ],
    "wof:name":"Tindari",
    "wof:placetype":"locality"
},
  "geometry": {"coordinates":[78.78465,24.62711],"type":"Point"}
}