{
  "type": "Feature",
  "properties": {
    "iso:country":"IN",
    "ks:ks_alt_nam":"PURE LALLU PANDEY",
    "ks:ks_name":"Pure Lallu Pandey",
    "ks:ks_pop":93,
    "ks:ks_type":"HABITATION",
    "ks:ks_uagg_main":0,
    "name:eng_x_preferred":[
        "Pure Lallu Pandey"
    ],
    "wof:name":"Pure Lallu Pandey",
    "wof:placetype":"neighbourhood",
    "wof:population":93
},
  "geometry": {"coordinates":[81.58280600000001,26.375503],"type":"Point"}
}