{
  "type": "Feature",
  "properties": {
    "iso:country":"IN",
    "ks:ks_name":"Chandera",
    "ks:ks_pop":2,
    "ks:ks_type":"HABITATION",
    "name:eng_x_preferred":[
        "Chandera"
    ],
    "wof:name":"Chandera",
    "wof:placetype":"locality",
    "wof:population":2
},
  "geometry": {"coordinates":[78.187922,24.098303],"type":"Point"}
}