{
  "type": "Feature",
  "properties": {
    "iso:country":"IN",
    "ks:ks_alt_nam":"PUKHRAJAM",
    "ks:ks_name":"Pukhrajam",
    "ks:ks_pop":135,
    "ks:ks_type":"HABITATION",
    "ks:ks_uagg_main":0,
    "name:eng_x_preferred":[
        "Pukhrajam"
    ],
    "wof:name":"Pukhrajam",
    "wof:placetype":"neighbourhood",
    "wof:population":135
},
  "geometry": {"coordinates":[83.0545,25.354623],"type":"Point"}
}