{
  "type": "Feature",
  "properties": {
    "iso:country":"IN",
    "ks:ks_name":"Mudwani",
    "ks:ks_pop":56,
    "ks:ks_type":"VILLAGE",
    "name:eng_x_preferred":[
        "Mudwani"
    ],
    "wof:name":"Mudwani",
    "wof:placetype":"locality",
    "wof:population":56
},
  "geometry": {"coordinates":[82.16855700000001,24.455946],"type":"Point"}
}