{
  "type": "Feature",
  "properties": {
    "gn:admin1_code":"16",
    "gn:admin2_code":"503.0",
    "gn:asciiname":"Gavandgaon Khurd",
    "gn:country_code":"IN",
    "gn:dem":311,
    "gn:feature_class":"P",
    "gn:feature_code":"PPL",
    "gn:name":"G\u0101vandgaon Khurd",
    "gn:population":0,
    "gn:timezone":"Asia/Kolkata",
    "iso:country":"IN",
    "ks:ks_alt_nam":"G\u0101vandgaon Khurd",
    "ks:ks_alt_nam_2":"Gavandgaon Khurd",
    "ks:ks_name":"Gavandgaon Kh",
    "ks:ks_pop":319,
    "ks:ks_type":"VILLAGE",
    "ks:ks_uagg_main":0,
    "name:eng_x_preferred":[
        "Gavandgaon Kh"
    ],
    "name:eng_x_variant":[
        "G\u0101vandgaon Khurd",
        "Gavandgaon Khurd"
    ],
    "wof:name":"Gavandgaon Kh",
    "wof:placetype":"neighbourhood",
    "wof:population":319
},
  "geometry": {"coordinates":[77.218418,21.092551],"type":"Point"}
}