{
  "type": "Feature",
  "properties": {
    "iso:country":"IN",
    "ks:ks_alt_nam":"DUKHA KARIU KA TOLA",
    "ks:ks_name":"Dukha Kariu Ka Tola",
    "ks:ks_pop":294,
    "ks:ks_type":"HABITATION",
    "ks:ks_uagg_main":0,
    "name:eng_x_preferred":[
        "Dukha Kariu Ka Tola"
    ],
    "wof:name":"Dukha Kariu Ka Tola",
    "wof:placetype":"neighbourhood",
    "wof:population":294
},
  "geometry": {"coordinates":[84.300391,25.861642],"type":"Point"}
}