{
  "type": "Feature",
  "properties": {
    "iso:country":"IN",
    "ks:ks_name":"Suhagpura",
    "ks:ks_pop":231,
    "ks:ks_type":"HABITATION",
    "name:eng_x_preferred":[
        "Suhagpura"
    ],
    "wof:name":"Suhagpura",
    "wof:placetype":"locality",
    "wof:population":231
},
  "geometry": {"coordinates":[86.720454,21.695686],"type":"Point"}
}