{
  "type": "Feature",
  "properties": {
    "gn:admin1_code":"34.0",
    "gn:admin2_code":"220.0",
    "gn:asciiname":"Saidpur Bijuli",
    "gn:country_code":"IN",
    "gn:dem":56,
    "gn:feature_class":"P",
    "gn:feature_code":"PPL",
    "gn:name":"Saidpur Bijuli",
    "gn:population":0,
    "gn:timezone":"Asia/Kolkata",
    "iso:country":"IN",
    "ks:ks_name":"Saidpur Bijuli",
    "ks:ks_pop":815,
    "ks:ks_type":"VILLAGE",
    "name:eng_x_preferred":[
        "Saidpur Bijuli"
    ],
    "wof:name":"Saidpur Bijuli",
    "wof:placetype":"locality",
    "wof:population":815
},
  "geometry": {"coordinates":[85.29473,25.850934],"type":"Point"}
}