{
  "type": "Feature",
  "properties": {
    "iso:country":"IN",
    "ks:ks_name":"Holewasti",
    "ks:ks_pop":743,
    "ks:ks_type":"HABITATION",
    "name:eng_x_preferred":[
        "Holewasti"
    ],
    "wof:name":"Holewasti",
    "wof:placetype":"locality",
    "wof:population":743
},
  "geometry": {"coordinates":[73.93913999999999,18.441206],"type":"Point"}
}