{
  "type": "Feature",
  "properties": {
    "iso:country":"IN",
    "ks:ks_alt_nam":"Noonegundlapalli alias",
    "ks:ks_name":"Noonegundlapalli Alias",
    "ks:ks_pop":294,
    "ks:ks_type":"HABITATION",
    "ks:ks_uagg_main":0,
    "name:eng_x_preferred":[
        "Noonegundlapalli Alias"
    ],
    "wof:name":"Noonegundlapalli Alias",
    "wof:placetype":"neighbourhood",
    "wof:population":294
},
  "geometry": {"coordinates":[78.998949,13.197447],"type":"Point"}
}