{
  "type": "Feature",
  "properties": {
    "gn:admin1_code":"09",
    "gn:admin2_code":"477.0",
    "gn:asciiname":"Sidsar",
    "gn:country_code":"IN",
    "gn:dem":75,
    "gn:feature_class":"P",
    "gn:feature_code":"PPL",
    "gn:name":"Sidsar",
    "gn:population":0,
    "gn:timezone":"Asia/Kolkata",
    "iso:country":"IN",
    "wof:name":"Sidsar",
    "wof:placetype":"locality"
},
  "geometry": {"coordinates":[70.10589,21.87545],"type":"Point"}
}