{
  "type": "Feature",
  "properties": {
    "gn:admin1_code":"36",
    "gn:admin2_code":"158.0",
    "gn:asciiname":"Pura Parshad Upadhia",
    "gn:country_code":"IN",
    "gn:dem":114,
    "gn:feature_class":"P",
    "gn:feature_code":"PPL",
    "gn:name":"Pura Parsh\u0101d Upadhia",
    "gn:population":0,
    "gn:timezone":"Asia/Kolkata",
    "iso:country":"IN",
    "wof:name":"Pura Parshad Upadhia",
    "wof:placetype":"neighbourhood"
},
  "geometry": {"coordinates":[81.47620000000001,26.1689],"type":"Point"}
}