{
  "type": "Feature",
  "properties": {
    "gn:admin1_code":"36",
    "gn:admin2_code":"197.0",
    "gn:asciiname":"Baren",
    "gn:country_code":"IN",
    "gn:dem":87,
    "gn:feature_class":"P",
    "gn:feature_code":"PPL",
    "gn:name":"Baren",
    "gn:population":0,
    "gn:timezone":"Asia/Kolkata",
    "iso:country":"IN",
    "name:ceb_x_preferred":[
        "Baren"
    ],
    "name:deu_x_preferred":[
        "Baren"
    ],
    "name:fra_x_preferred":[
        "Baren"
    ],
    "name:srp_x_preferred":[
        "\u0411\u0430\u0440\u0430\u043d"
    ],
    "wof:name":"Baren",
    "wof:placetype":"neighbourhood"
},
  "geometry": {"coordinates":[82.75996000000001,25.48424],"type":"Point"}
}