{
  "type": "Feature",
  "properties": {
    "iso:country":"IN",
    "ks:ks_name":"Bandathanda",
    "ks:ks_pop":16,
    "ks:ks_type":"HABITATION",
    "name:eng_x_preferred":[
        "Bandathanda"
    ],
    "wof:name":"Bandathanda",
    "wof:placetype":"locality",
    "wof:population":16
},
  "geometry": {"coordinates":[79.193237,17.988388],"type":"Point"}
}