{
  "type": "Feature",
  "properties": {
    "iso:country":"IN",
    "ks:ks_name":"Ummathur",
    "ks:ks_pop":515,
    "ks:ks_type":"VILLAGE",
    "name:eng_x_preferred":[
        "Ummathur"
    ],
    "wof:name":"Ummathur",
    "wof:placetype":"locality",
    "wof:population":515
},
  "geometry": {"coordinates":[75.79789100000001,12.844331],"type":"Point"}
}