{
  "type": "Feature",
  "properties": {
    "iso:country":"IN",
    "ks:ks_name":"Kilatheru",
    "ks:ks_pop":1246,
    "ks:ks_type":"VILLAGE",
    "name:eng_x_preferred":[
        "Kilatheru"
    ],
    "wof:name":"Kilatheru",
    "wof:placetype":"locality",
    "wof:population":1246
},
  "geometry": {"coordinates":[79.124358,10.387681],"type":"Point"}
}