{
  "type": "Feature",
  "properties": {
    "iso:country":"IN",
    "ks:ks_alt_nam":"Pothapola indlu",
    "ks:ks_name":"Pothapola Indlu",
    "ks:ks_pop":114,
    "ks:ks_type":"HABITATION",
    "name:eng_x_preferred":[
        "Pothapola Indlu"
    ],
    "wof:name":"Pothapola Indlu",
    "wof:placetype":"locality",
    "wof:population":114
},
  "geometry": {"coordinates":[78.955738,13.402855],"type":"Point"}
}