{
  "type": "Feature",
  "properties": {
    "gn:admin1_code":"35",
    "gn:admin2_code":"449.0",
    "gn:asciiname":"Gadariya",
    "gn:country_code":"IN",
    "gn:dem":306,
    "gn:feature_class":"P",
    "gn:feature_code":"PPL",
    "gn:name":"G\u0101dariya",
    "gn:population":0,
    "gn:timezone":"Asia/Kolkata",
    "iso:country":"IN",
    "name:ceb_x_preferred":[
        "Gadariya"
    ],
    "name:dty_x_preferred":[
        "\u0917\u0926\u0930\u093f\u092f\u093e"
    ],
    "name:mai_x_preferred":[
        "\u0917\u0926\u0930\u093f\u092f\u093e"
    ],
    "name:msa_x_preferred":[
        "Gadariya"
    ],
    "name:nep_x_preferred":[
        "\u0917\u0926\u0930\u093f\u092f\u093e"
    ],
    "name:pol_x_preferred":[
        "Gadariya"
    ],
    "wof:name":"Gadariya",
    "wof:placetype":"locality"
},
  "geometry": {"coordinates":[77.42338000000002,22.52043],"type":"Point"}
}