{
  "type": "Feature",
  "properties": {
    "iso:country":"IN",
    "ks:ks_name":"Bagcherra Punjee",
    "ks:ks_pop":1450,
    "ks:ks_type":"HABITATION",
    "name:eng_x_preferred":[
        "Bagcherra Punjee"
    ],
    "wof:name":"Bagcherra Punjee",
    "wof:placetype":"locality",
    "wof:population":1450
},
  "geometry": {"coordinates":[92.452383,24.203934],"type":"Point"}
}