{
  "type": "Feature",
  "properties": {
    "gn:admin1_code":"23.0",
    "gn:admin2_code":"45.0",
    "gn:asciiname":"Sikhanwala",
    "gn:country_code":"IN",
    "gn:dem":208,
    "gn:feature_class":"P",
    "gn:feature_code":"PPL",
    "gn:name":"Sikh\u0101nw\u0101la",
    "gn:population":0,
    "gn:timezone":"Asia/Kolkata",
    "iso:country":"IN",
    "name:fas_x_preferred":[
        "\u0633\u06a9\u0647\u0627\u0646\u200c\u0648\u0627\u0644\u0647"
    ],
    "name:urd_x_preferred":[
        "\u0633\u06a9\u06be\u0627\u0646\u0648\u0627\u0644\u06c1"
    ],
    "wof:name":"Sikhanwala",
    "wof:placetype":"locality"
},
  "geometry": {"coordinates":[74.83178000000002,30.63844000000001],"type":"Point"}
}