{
  "type": "Feature",
  "properties": {
    "iso:country":"IN",
    "ks:ks_name":"Kutrughati",
    "ks:ks_pop":40,
    "ks:ks_type":"HABITATION",
    "name:eng_x_preferred":[
        "Kutrughati"
    ],
    "wof:name":"Kutrughati",
    "wof:placetype":"locality",
    "wof:population":40
},
  "geometry": {"coordinates":[83.371217,19.893821],"type":"Point"}
}