{
  "type": "Feature",
  "properties": {
    "iso:country":"IN",
    "ks:ks_name":"Beerappa Nagar",
    "ks:ks_pop":400,
    "ks:ks_type":"HABITATION",
    "name:eng_x_preferred":[
        "Beerappa Nagar"
    ],
    "wof:name":"Beerappa Nagar",
    "wof:placetype":"locality",
    "wof:population":400
},
  "geometry": {"coordinates":[75.892405,17.185094],"type":"Point"}
}