{
  "type": "Feature",
  "properties": {
    "iso:country":"IN",
    "ks:ks_name":"Nundrubadi",
    "ks:ks_pop":28,
    "ks:ks_type":"HABITATION",
    "name:eng_x_preferred":[
        "Nundrubadi"
    ],
    "wof:name":"Nundrubadi",
    "wof:placetype":"locality",
    "wof:population":28
},
  "geometry": {"coordinates":[83.564701,19.83311],"type":"Point"}
}