{
  "type": "Feature",
  "properties": {
    "gn:admin1_code":"36.0",
    "gn:admin2_code":"173.0",
    "gn:asciiname":"Parasrampur Khurd",
    "gn:country_code":"IN",
    "gn:dem":108,
    "gn:feature_class":"P",
    "gn:feature_code":"PPL",
    "gn:name":"Parasr\u0101mpur Khurd",
    "gn:population":0,
    "gn:timezone":"Asia/Kolkata",
    "iso:country":"IN",
    "ks:ks_alt_nam":"Parasr\u0101mpur Khurd",
    "ks:ks_name":"Parasrampur Khurd",
    "ks:ks_type":"VILLAGE",
    "ks:ks_uagg_main":0,
    "name:eng_x_preferred":[
        "Parasrampur Khurd"
    ],
    "name:eng_x_variant":[
        "Parasr\u0101mpur Khurd"
    ],
    "wof:name":"Parasrampur Khurd",
    "wof:placetype":"neighbourhood"
},
  "geometry": {"coordinates":[81.858124,25.757322],"type":"Point"}
}