{
  "type": "Feature",
  "properties": {
    "iso:country":"IN",
    "ks:ks_name":"Jalu",
    "ks:ks_pop":256,
    "ks:ks_type":"VILLAGE",
    "name:eng_x_preferred":[
        "Jalu"
    ],
    "wof:name":"Jalu",
    "wof:placetype":"locality",
    "wof:population":256
},
  "geometry": {"coordinates":[69.34662,23.500472],"type":"Point"}
}