{
  "type": "Feature",
  "properties": {
    "iso:country":"IN",
    "ks:ks_name":"T Poigaipatty",
    "ks:ks_pop":435,
    "ks:ks_type":"HABITATION",
    "name:eng_x_preferred":[
        "T Poigaipatty"
    ],
    "wof:name":"T Poigaipatty",
    "wof:placetype":"locality",
    "wof:population":435
},
  "geometry": {"coordinates":[78.39952,10.556557],"type":"Point"}
}