{
  "type": "Feature",
  "properties": {
    "iso:country":"IN",
    "ks:ks_name":"Bahadurpura",
    "ks:ks_pop":9,
    "ks:ks_type":"VILLAGE",
    "name:eng_x_preferred":[
        "Bahadurpura"
    ],
    "wof:name":"Bahadurpura",
    "wof:placetype":"locality",
    "wof:population":9
},
  "geometry": {"coordinates":[77.239732,22.328054],"type":"Point"}
}