{
  "type": "Feature",
  "properties": {
    "iso:country":"IN",
    "ks:ks_name":"Jhaljhali",
    "ks:ks_pop":3770,
    "ks:ks_type":"VILLAGE",
    "name:eng_x_preferred":[
        "Jhaljhali"
    ],
    "wof:name":"Jhaljhali",
    "wof:placetype":"locality",
    "wof:population":3770
},
  "geometry": {"coordinates":[89.64027,26.249053],"type":"Point"}
}