{
  "type": "Feature",
  "properties": {
    "gn:admin1_code":"19.0",
    "gn:admin2_code":"581.0",
    "gn:asciiname":"Chikka Bandahalli",
    "gn:country_code":"IN",
    "gn:dem":800,
    "gn:feature_class":"P",
    "gn:feature_code":"PPL",
    "gn:name":"Chikka Bandahalli",
    "gn:population":0,
    "gn:timezone":"Asia/Kolkata",
    "iso:country":"IN",
    "wof:name":"Chikka Bandahalli",
    "wof:placetype":"locality"
},
  "geometry": {"coordinates":[78.43609000000002,13.1696],"type":"Point"}
}