{
  "type": "Feature",
  "properties": {
    "iso:country":"IN",
    "ks:ks_alt_nam":"Khiriya (Sirsi)",
    "ks:ks_name":"Khiriya (sirsi)",
    "ks:ks_pop":192,
    "ks:ks_type":"HABITATION",
    "name:eng_x_preferred":[
        "Khiriya (sirsi)"
    ],
    "wof:name":"Khiriya (sirsi)",
    "wof:placetype":"locality",
    "wof:population":192
},
  "geometry": {"coordinates":[77.281533,24.94505],"type":"Point"}
}