{
  "type": "Feature",
  "properties": {
    "iso:country":"IN",
    "ks:ks_name":"Mehagwan Padarivakala",
    "ks:ks_pop":49,
    "ks:ks_type":"HABITATION",
    "name:eng_x_preferred":[
        "Mehagwan Padarivakala"
    ],
    "wof:name":"Mehagwan Padarivakala",
    "wof:placetype":"locality",
    "wof:population":49
},
  "geometry": {"coordinates":[80.05795000000001,23.368682],"type":"Point"}
}