{
  "type": "Feature",
  "properties": {
    "gn:admin1_code":"36",
    "gn:admin2_code":"188.0",
    "gn:asciiname":"Parsia Nisfi Shukul",
    "gn:country_code":"IN",
    "gn:dem":80,
    "gn:feature_class":"P",
    "gn:feature_code":"PPL",
    "gn:name":"Parsia Nisfi Shukul",
    "gn:population":0,
    "gn:timezone":"Asia/Kolkata",
    "iso:country":"IN",
    "wof:name":"Parsia Nisfi Shukul",
    "wof:placetype":"locality"
},
  "geometry": {"coordinates":[83.31938000000002,26.40374000000001],"type":"Point"}
}