{
  "type": "Feature",
  "properties": {
    "iso:country":"IN",
    "ks:ks_name":"Thadaperumbakkam",
    "ks:ks_pop":3205,
    "ks:ks_type":"VILLAGE",
    "ks:ks_uagg_main":0,
    "name:eng_x_preferred":[
        "Thadaperumbakkam"
    ],
    "wof:name":"Thadaperumbakkam",
    "wof:placetype":"neighbourhood",
    "wof:population":3205
},
  "geometry": {"coordinates":[80.195311,13.32026],"type":"Point"}
}