{
  "type": "Feature",
  "properties": {
    "iso:country":"IN",
    "ks:ks_name":"Bitalipurwa",
    "ks:ks_pop":1069,
    "ks:ks_type":"HABITATION",
    "name:eng_x_preferred":[
        "Bitalipurwa"
    ],
    "wof:name":"Bitalipurwa",
    "wof:placetype":"locality",
    "wof:population":1069
},
  "geometry": {"coordinates":[79.98871200000001,25.226265],"type":"Point"}
}