{
  "type": "Feature",
  "properties": {
    "iso:country":"IN",
    "ks:ks_alt_nam":"HESALGUTU",
    "ks:ks_name":"Hesalgutu",
    "ks:ks_pop":116,
    "ks:ks_type":"HABITATION",
    "name:eng_x_preferred":[
        "Hesalgutu"
    ],
    "wof:name":"Hesalgutu",
    "wof:placetype":"locality",
    "wof:population":116
},
  "geometry": {"coordinates":[85.521035,22.245532],"type":"Point"}
}