{
  "type": "Feature",
  "properties": {
    "gn:admin1_code":"40.0",
    "gn:admin2_code":"538",
    "gn:asciiname":"Mahadeopur",
    "gn:country_code":"IN",
    "gn:dem":662,
    "gn:feature_class":"P",
    "gn:feature_code":"PPL",
    "gn:name":"Mahadeopur",
    "gn:population":0,
    "gn:timezone":"Asia/Kolkata",
    "iso:country":"IN",
    "wof:name":"Mahadeopur",
    "wof:placetype":"neighbourhood"
},
  "geometry": {"coordinates":[78.06905999999999,17.09998],"type":"Point"}
}