{
  "type": "Feature",
  "properties": {
    "iso:country":"IN",
    "ks:ks_name":"Duldulia",
    "ks:ks_pop":1554,
    "ks:ks_type":"VILLAGE",
    "ks:ks_uagg_main":0,
    "name:eng_x_preferred":[
        "Duldulia"
    ],
    "wof:name":"Duldulia",
    "wof:placetype":"locality",
    "wof:population":1554
},
  "geometry": {"coordinates":[84.48818900000001,26.42743],"type":"Point"}
}