{
  "type": "Feature",
  "properties": {
    "gn:admin1_code":"19.0",
    "gn:admin2_code":"575.0",
    "gn:asciiname":"Bilanile",
    "gn:country_code":"IN",
    "gn:dem":139,
    "gn:feature_class":"P",
    "gn:feature_code":"PPL",
    "gn:name":"Bilanile",
    "gn:population":0,
    "gn:timezone":"Asia/Kolkata",
    "iso:country":"IN",
    "ks:ks_name":"Bilinele",
    "ks:ks_pop":499,
    "ks:ks_type":"VILLAGE",
    "name:eng_x_preferred":[
        "Bilinele"
    ],
    "name:eng_x_variant":[
        "Bilanile"
    ],
    "wof:name":"Bilinele",
    "wof:placetype":"locality",
    "wof:population":499
},
  "geometry": {"coordinates":[75.576142,12.727366],"type":"Point"}
}