{
  "type": "Feature",
  "properties": {
    "gn:admin1_code":"2.0",
    "gn:admin2_code":"553.0",
    "gn:asciiname":"Ragimakulapalle",
    "gn:country_code":"IN",
    "gn:dem":589,
    "gn:feature_class":"P",
    "gn:feature_code":"PPL",
    "gn:name":"R\u0101gim\u0101kulapalle",
    "gn:population":0,
    "gn:timezone":"Asia/Kolkata",
    "iso:country":"IN",
    "wof:name":"Ragimakulapalle",
    "wof:placetype":"locality"
},
  "geometry": {"coordinates":[77.4704,14.14548],"type":"Point"}
}