{
  "type": "Feature",
  "properties": {
    "iso:country":"IN",
    "ks:ks_name":"Chorhiyapur",
    "ks:ks_pop":250,
    "ks:ks_type":"HABITATION",
    "name:eng_x_preferred":[
        "Chorhiyapur"
    ],
    "wof:name":"Chorhiyapur",
    "wof:placetype":"locality",
    "wof:population":250
},
  "geometry": {"coordinates":[81.022852,26.24066],"type":"Point"}
}