{
  "type": "Feature",
  "properties": {
    "iso:country":"IN",
    "ks:ks_name":"Garad Wasti",
    "ks:ks_pop":265,
    "ks:ks_type":"HABITATION",
    "name:eng_x_preferred":[
        "Garad Wasti"
    ],
    "wof:name":"Garad Wasti",
    "wof:placetype":"locality",
    "wof:population":265
},
  "geometry": {"coordinates":[75.30706499999999,17.968833],"type":"Point"}
}