{
  "type": "Feature",
  "properties": {
    "gn:admin1_code":"36",
    "gn:admin2_code":"158.0",
    "gn:asciiname":"Pura Shiudin Kurmi",
    "gn:country_code":"IN",
    "gn:dem":109,
    "gn:feature_class":"P",
    "gn:feature_code":"PPL",
    "gn:name":"Pura Shiud\u012bn Kurmi",
    "gn:population":0,
    "gn:timezone":"Asia/Kolkata",
    "iso:country":"IN",
    "wof:name":"Pura Shiudin Kurmi",
    "wof:placetype":"locality"
},
  "geometry": {"coordinates":[81.56099,26.01028],"type":"Point"}
}