{
  "type": "Feature",
  "properties": {
    "iso:country":"IN",
    "ks:ks_name":"Mathegujar",
    "ks:ks_pop":365,
    "ks:ks_type":"VILLAGE",
    "name:eng_x_preferred":[
        "Mathegujar"
    ],
    "wof:name":"Mathegujar",
    "wof:placetype":"locality",
    "wof:population":365
},
  "geometry": {"coordinates":[73.22102700000001,17.660541],"type":"Point"}
}