{
  "type": "Feature",
  "properties": {
    "iso:country":"IN",
    "ks:ks_name":"Sialinalijungle",
    "ks:ks_pop":1184,
    "ks:ks_type":"VILLAGE",
    "name:eng_x_preferred":[
        "Sialinalijungle"
    ],
    "wof:name":"Sialinalijungle",
    "wof:placetype":"locality",
    "wof:population":1184
},
  "geometry": {"coordinates":[83.672551,21.049224],"type":"Point"}
}