{
  "type": "Feature",
  "properties": {
    "iso:country":"IN",
    "ks:ks_name":"Malegadde Camp",
    "ks:ks_pop":500,
    "ks:ks_type":"HABITATION",
    "name:eng_x_preferred":[
        "Malegadde Camp"
    ],
    "wof:name":"Malegadde Camp",
    "wof:placetype":"locality",
    "wof:population":500
},
  "geometry": {"coordinates":[77.02529,15.058758],"type":"Point"}
}