{
  "type": "Feature",
  "properties": {
    "iso:country":"IN",
    "ks:ks_alt_nam":"Kuttanellur Bypass Junction Bus Stop rd",
    "ks:ks_name":"Kuttanellur Bypass Junction Bus Stop Rd",
    "ks:ks_pop":636,
    "ks:ks_type":"HABITATION",
    "name:eng_x_preferred":[
        "Kuttanellur Bypass Junction Bus Stop Rd"
    ],
    "wof:name":"Kuttanellur Bypass Junction Bus Stop Rd",
    "wof:placetype":"locality",
    "wof:population":636
},
  "geometry": {"coordinates":[76.26181800000001,10.496904],"type":"Point"}
}