{
  "type": "Feature",
  "properties": {
    "iso:country":"IN",
    "ks:ks_alt_nam":"SHITAL TALI",
    "ks:ks_name":"Shital Tali",
    "ks:ks_pop":173,
    "ks:ks_type":"HABITATION",
    "name:eng_x_preferred":[
        "Shital Tali"
    ],
    "wof:name":"Shital Tali",
    "wof:placetype":"locality",
    "wof:population":173
},
  "geometry": {"coordinates":[91.24280899999999,23.771499],"type":"Point"}
}