{
  "type": "Feature",
  "properties": {
    "gn:admin1_code":"21",
    "gn:admin2_code":"396.0",
    "gn:asciiname":"Padaliguda",
    "gn:country_code":"IN",
    "gn:dem":405,
    "gn:feature_class":"P",
    "gn:feature_code":"PPL",
    "gn:name":"Padaliguda",
    "gn:population":0,
    "gn:timezone":"Asia/Kolkata",
    "iso:country":"IN",
    "ks:ks_name":"Padulaguda",
    "ks:ks_pop":88,
    "ks:ks_type":"VILLAGE",
    "name:eng_x_preferred":[
        "Padulaguda"
    ],
    "name:eng_x_variant":[
        "Padaliguda"
    ],
    "wof:name":"Padulaguda",
    "wof:placetype":"locality",
    "wof:population":88
},
  "geometry": {"coordinates":[83.30819099999999,19.580223],"type":"Point"}
}