{
  "type": "Feature",
  "properties": {
    "gn:admin1_code":"21",
    "gn:admin2_code":"395.0",
    "gn:asciiname":"Kumbharbaru",
    "gn:country_code":"IN",
    "gn:dem":598,
    "gn:feature_class":"P",
    "gn:feature_code":"PPL",
    "gn:name":"Kumbharb\u0101ru",
    "gn:population":0,
    "gn:timezone":"Asia/Kolkata",
    "iso:country":"IN",
    "wof:name":"Kumbharbaru",
    "wof:placetype":"locality"
},
  "geometry": {"coordinates":[83.37021999999997,19.85162],"type":"Point"}
}