{
  "type": "Feature",
  "properties": {
    "gn:admin1_code":"21",
    "gn:admin2_code":"395.0",
    "gn:asciiname":"Kumbharbaru",
    "gn:country_code":"IN",
    "gn:dem":598,
    "gn:feature_class":"P",
    "gn:feature_code":"PPL",
    "gn:name":"Kumbharb\u0101ru",
    "gn:population":0,
    "gn:timezone":"Asia/Kolkata",
    "iso:country":"IN",
    "ks:ks_alt_nam":"Kumbharb\u0101ru",
    "ks:ks_name":"Kumbharbaru",
    "ks:ks_pop":99,
    "ks:ks_type":"VILLAGE",
    "name:eng_x_preferred":[
        "Kumbharbaru"
    ],
    "name:eng_x_variant":[
        "Kumbharb\u0101ru"
    ],
    "wof:name":"Kumbharbaru",
    "wof:placetype":"locality",
    "wof:population":99
},
  "geometry": {"coordinates":[83.37030900000001,19.851606],"type":"Point"}
}