{
  "type": "Feature",
  "properties": {
    "iso:country":"IN",
    "ks:ks_name":"Tighara",
    "ks:ks_pop":4,
    "ks:ks_type":"HABITATION",
    "name:eng_x_preferred":[
        "Tighara"
    ],
    "wof:name":"Tighara",
    "wof:placetype":"locality",
    "wof:population":4
},
  "geometry": {"coordinates":[77.354321,26.197938],"type":"Point"}
}