{
  "type": "Feature",
  "properties": {
    "gn:admin1_code":"19.0",
    "gn:admin2_code":"575.0",
    "gn:asciiname":"Kompadavu",
    "gn:country_code":"IN",
    "gn:dem":85,
    "gn:feature_class":"P",
    "gn:feature_code":"PPLL",
    "gn:name":"Kompadavu",
    "gn:population":0,
    "gn:timezone":"Asia/Kolkata",
    "iso:country":"IN",
    "ks:ks_name":"Kompadavu",
    "ks:ks_pop":2333,
    "ks:ks_type":"VILLAGE",
    "name:eng_x_preferred":[
        "Kompadavu"
    ],
    "wof:name":"Kompadavu",
    "wof:placetype":"locality",
    "wof:population":2333
},
  "geometry": {"coordinates":[74.919578,13.006113],"type":"Point"}
}