{
  "type": "Feature",
  "properties": {
    "gn:admin1_code":"35.0",
    "gn:admin2_code":"455.0",
    "gn:asciiname":"Thuniyaudna",
    "gn:country_code":"IN",
    "gn:dem":688,
    "gn:feature_class":"P",
    "gn:feature_code":"PPL",
    "gn:name":"Thuniy\u0101udna",
    "gn:population":0,
    "gn:timezone":"Asia/Kolkata",
    "iso:country":"IN",
    "wof:name":"Thuniyaudna",
    "wof:placetype":"locality"
},
  "geometry": {"coordinates":[78.87120999999998,22.03927],"type":"Point"}
}