{
  "type": "Feature",
  "properties": {
    "gn:admin1_code":"35",
    "gn:admin2_code":"456.0",
    "gn:asciiname":"Barela",
    "gn:country_code":"IN",
    "gn:dem":601,
    "gn:feature_class":"P",
    "gn:feature_code":"PPL",
    "gn:name":"Barel\u0101",
    "gn:population":0,
    "gn:timezone":"Asia/Kolkata",
    "iso:country":"IN",
    "name:ben_x_preferred":[
        "\u09ac\u09b0\u09c7\u09b2\u09be"
    ],
    "name:bpy_x_preferred":[
        "\u09ac\u09b0\u09c7\u09b2\u09be"
    ],
    "name:ceb_x_preferred":[
        "Barel\u0101"
    ],
    "name:ita_x_preferred":[
        "Barela"
    ],
    "name:msa_x_preferred":[
        "Barela"
    ],
    "name:new_x_preferred":[
        "\u092c\u0930\u0947\u0932"
    ],
    "name:nld_x_preferred":[
        "Barela"
    ],
    "name:por_x_preferred":[
        "Barela"
    ],
    "name:swe_x_preferred":[
        "Barel\u0101"
    ],
    "name:vie_x_preferred":[
        "Barela"
    ],
    "name:zho_x_preferred":[
        "\u5df4\u96f7\u62c9"
    ],
    "wof:name":"Barela",
    "wof:placetype":"locality"
},
  "geometry": {"coordinates":[79.76093,22.5589],"type":"Point"}
}