{
  "type": "Feature",
  "properties": {
    "iso:country":"IN",
    "ks:ks_name":"Bijaini",
    "ks:ks_pop":331,
    "ks:ks_type":"HABITATION",
    "name:eng_x_preferred":[
        "Bijaini"
    ],
    "wof:name":"Bijaini",
    "wof:placetype":"locality",
    "wof:population":331
},
  "geometry": {"coordinates":[84.551704,24.47522],"type":"Point"}
}