{
  "type": "Feature",
  "properties": {
    "gn:admin1_code":"36.0",
    "gn:admin2_code":"149.0",
    "gn:asciiname":"Rahimuddinnagar",
    "gn:country_code":"IN",
    "gn:dem":173,
    "gn:feature_class":"P",
    "gn:feature_code":"PPL",
    "gn:name":"Rah\u012bmudd\u012bnnagar",
    "gn:population":0,
    "gn:timezone":"Asia/Kolkata",
    "iso:country":"IN",
    "wof:name":"Rahimuddinnagar",
    "wof:placetype":"locality"
},
  "geometry": {"coordinates":[79.09124,28.00246],"type":"Point"}
}