{
  "type": "Feature",
  "properties": {
    "iso:country":"IN",
    "ks:ks_name":"Isukavari Palli",
    "ks:ks_pop":20,
    "ks:ks_type":"HABITATION",
    "name:eng_x_preferred":[
        "Isukavari Palli"
    ],
    "wof:name":"Isukavari Palli",
    "wof:placetype":"locality",
    "wof:population":20
},
  "geometry": {"coordinates":[78.254796,13.908232],"type":"Point"}
}