{
  "type": "Feature",
  "properties": {
    "gn:admin1_code":"11",
    "gn:admin2_code":"24.0",
    "gn:asciiname":"Baghaur",
    "gn:country_code":"IN",
    "gn:dem":510,
    "gn:feature_class":"P",
    "gn:feature_code":"PPL",
    "gn:name":"Baghaur",
    "gn:population":0,
    "gn:timezone":"Asia/Kolkata",
    "iso:country":"IN",
    "wof:name":"Baghaur",
    "wof:placetype":"locality"
},
  "geometry": {"coordinates":[76.25875000000001,31.8453],"type":"Point"}
}