{
  "type": "Feature",
  "properties": {
    "gn:admin1_code":"2.0",
    "gn:admin2_code":"542.0",
    "gn:asciiname":"Goyiguda",
    "gn:country_code":"IN",
    "gn:dem":334,
    "gn:feature_class":"P",
    "gn:feature_code":"PPL",
    "gn:name":"Goyig\u016bda",
    "gn:population":0,
    "gn:timezone":"Asia/Kolkata",
    "iso:country":"IN",
    "wof:name":"Goyiguda",
    "wof:placetype":"locality"
},
  "geometry": {"coordinates":[83.78907,18.89394],"type":"Point"}
}