{
  "type": "Feature",
  "properties": {
    "iso:country":"IN",
    "ks:ks_name":"Kadiya",
    "ks:ks_type":"VILLAGE",
    "ks:ks_uagg_main":0,
    "name:eng_x_preferred":[
        "Kadiya"
    ],
    "wof:name":"Kadiya",
    "wof:placetype":"neighbourhood"
},
  "geometry": {"coordinates":[87.044926,24.543316],"type":"Point"}
}