{
  "type": "Feature",
  "properties": {
    "gn:admin1_code":"35",
    "gn:admin2_code":"422.0",
    "gn:asciiname":"Jaura",
    "gn:country_code":"IN",
    "gn:dem":174,
    "gn:feature_class":"P",
    "gn:feature_code":"PPL",
    "gn:name":"Jaura",
    "gn:population":0,
    "gn:timezone":"Asia/Kolkata",
    "iso:country":"IN",
    "wof:name":"Jaura",
    "wof:placetype":"locality"
},
  "geometry": {"coordinates":[78.65035999999998,25.79584],"type":"Point"}
}