{
  "type": "Feature",
  "properties": {
    "gn:admin1_code":"34.0",
    "gn:admin2_code":"220.0",
    "gn:asciiname":"Bhagwanpur Kaiju",
    "gn:country_code":"IN",
    "gn:dem":53,
    "gn:feature_class":"P",
    "gn:feature_code":"PPL",
    "gn:name":"Bhagw\u0101npur Kaiju",
    "gn:population":0,
    "gn:timezone":"Asia/Kolkata",
    "iso:country":"IN",
    "ks:ks_alt_nam":"Bhagw\u0101npur Kaiju",
    "ks:ks_name":"Bhagwanpur Kaiju",
    "ks:ks_pop":1451,
    "ks:ks_type":"VILLAGE",
    "name:eng_x_preferred":[
        "Bhagwanpur Kaiju"
    ],
    "name:eng_x_variant":[
        "Bhagw\u0101npur Kaiju"
    ],
    "wof:name":"Bhagwanpur Kaiju",
    "wof:placetype":"locality",
    "wof:population":1451
},
  "geometry": {"coordinates":[85.60641200000001,25.834574],"type":"Point"}
}