{
  "type": "Feature",
  "properties": {
    "iso:country":"IN",
    "ks:ks_name":"Vadakkanmarainadu",
    "ks:ks_pop":228,
    "ks:ks_type":"HABITATION",
    "ks:ks_uagg_main":0,
    "name:eng_x_preferred":[
        "Vadakkanmarainadu"
    ],
    "wof:name":"Vadakkanmarainadu",
    "wof:placetype":"neighbourhood",
    "wof:population":228
},
  "geometry": {"coordinates":[77.708235,9.297941],"type":"Point"}
}