{
  "type": "Feature",
  "properties": {
    "iso:country":"IN",
    "ks:ks_name":"Pralhadpur",
    "ks:ks_pop":2146,
    "ks:ks_type":"VILLAGE",
    "ks:ks_uagg_main":0,
    "name:eng_x_preferred":[
        "Pralhadpur"
    ],
    "wof:name":"Pralhadpur",
    "wof:placetype":"neighbourhood",
    "wof:population":2146
},
  "geometry": {"coordinates":[77.748869,21.231197],"type":"Point"}
}