{
  "type": "Feature",
  "properties": {
    "gn:country":"IN",
    "gn:fcode":"PPL",
    "gn:pop":45921,
    "iso:country":"IN",
    "name:ara_x_preferred":[
        "\u0645\u062d\u0645\u0648\u062f \u0622\u0628\u0627\u062f"
    ],
    "name:cat_x_preferred":[
        "Mahmudabad"
    ],
    "name:ceb_x_preferred":[
        "Mahm\u016bd\u0101b\u0101d"
    ],
    "name:eng_x_preferred":[
        "Mahmudabad"
    ],
    "name:fra_x_preferred":[
        "Mahmudabad"
    ],
    "name:hin_x_preferred":[
        "\u092e\u0939\u092e\u0942\u0926\u093e\u092c\u093e\u0926"
    ],
    "name:ita_x_preferred":[
        "Mahmudabad"
    ],
    "name:msa_x_preferred":[
        "Mahmudabad"
    ],
    "name:nan_x_preferred":[
        "Mahmudabad"
    ],
    "name:nld_x_preferred":[
        "Mahmudabad"
    ],
    "name:pol_x_preferred":[
        "Mahmudabad"
    ],
    "name:swe_x_preferred":[
        "Mahm\u016bd\u0101b\u0101d"
    ],
    "name:unk_x_variant":[
        "Mahmud\u0101b\u0101d"
    ],
    "name:urd_x_preferred":[
        "\u0645\u062d\u0645\u0648\u062f \u0622\u0628\u0627\u062f\u060c \u0628\u06be\u0627\u0631\u062a"
    ],
    "name:urd_x_variant":[
        "\u0645\u062d\u0645\u0648\u062f \u0622\u0628\u0627\u062f"
    ],
    "name:vie_x_preferred":[
        "Mahmudabad"
    ],
    "name:zho_x_preferred":[
        "\u9a6c\u8d6b\u7a46\u8fbe\u5df4\u5fb7"
    ],
    "qs:name":"Mahm\u016bd\u0101b\u0101d",
    "qs:photos_9r":0,
    "qs:photos_sr":0,
    "qs:pop_sr":"7",
    "wof:name":"Mahm\u016bd\u0101b\u0101d",
    "wof:placetype":"locality",
    "wof:population":45921
},
  "geometry": {"coordinates":[81.12399000000001,27.2976],"type":"Point"}
}