{
  "type": "Feature",
  "properties": {
    "iso:country":"IN",
    "ks:ks_alt_nam":"2 RBM",
    "ks:ks_name":"2 Rbm",
    "ks:ks_pop":66,
    "ks:ks_type":"HABITATION",
    "name:eng_x_preferred":[
        "2 Rbm"
    ],
    "wof:name":"2 Rbm",
    "wof:placetype":"locality",
    "wof:population":66
},
  "geometry": {"coordinates":[73.41500000000001,29.200278],"type":"Point"}
}