{
  "type": "Feature",
  "properties": {
    "gn:admin1_code":"19.0",
    "gn:admin2_code":"571.0",
    "gn:asciiname":"Kanivepalya",
    "gn:country_code":"IN",
    "gn:dem":877,
    "gn:feature_class":"P",
    "gn:feature_code":"PPL",
    "gn:name":"Kanivep\u0101lya",
    "gn:population":0,
    "gn:timezone":"Asia/Kolkata",
    "iso:country":"IN",
    "wof:name":"Kanivepalya",
    "wof:placetype":"locality"
},
  "geometry": {"coordinates":[77.13760000000001,12.93152],"type":"Point"}
}