{
  "type": "Feature",
  "properties": {
    "gn:admin1_code":"10",
    "gn:admin2_code":"69.0",
    "gn:asciiname":"Manakpur Devilat",
    "gn:country_code":"IN",
    "gn:dem":520,
    "gn:feature_class":"P",
    "gn:feature_code":"PPL",
    "gn:name":"M\u0101nakpur Devil\u0101t",
    "gn:population":0,
    "gn:timezone":"Asia/Kolkata",
    "iso:country":"IN",
    "wof:name":"Manakpur Devilat",
    "wof:placetype":"locality"
},
  "geometry": {"coordinates":[76.90348,30.79557],"type":"Point"}
}