{
  "type": "Feature",
  "properties": {
    "iso:country":"IN",
    "ks:ks_name":"Choura Ryt",
    "ks:ks_pop":640,
    "ks:ks_type":"HABITATION",
    "name:eng_x_preferred":[
        "Choura Ryt"
    ],
    "wof:name":"Choura Ryt",
    "wof:placetype":"locality",
    "wof:population":640
},
  "geometry": {"coordinates":[80.686289,23.282813],"type":"Point"}
}