{
  "type": "Feature",
  "properties": {
    "iso:country":"IN",
    "ks:ks_name":"Andavarkoil",
    "ks:ks_pop":200,
    "ks:ks_type":"HABITATION",
    "name:eng_x_preferred":[
        "Andavarkoil"
    ],
    "wof:name":"Andavarkoil",
    "wof:placetype":"locality",
    "wof:population":200
},
  "geometry": {"coordinates":[78.43076000000001,10.625996],"type":"Point"}
}