{
  "type": "Feature",
  "properties": {
    "iso:country":"IN",
    "ks:ks_name":"Tikrigora",
    "ks:ks_pop":67,
    "ks:ks_type":"VILLAGE",
    "name:eng_x_preferred":[
        "Tikrigora"
    ],
    "wof:name":"Tikrigora",
    "wof:placetype":"locality",
    "wof:population":67
},
  "geometry": {"coordinates":[87.425867,24.888847],"type":"Point"}
}