{
  "type": "Feature",
  "properties": {
    "gn:admin1_code":"19.0",
    "gn:admin2_code":"568.0",
    "gn:asciiname":"Vatigaru",
    "gn:country_code":"IN",
    "gn:dem":637,
    "gn:feature_class":"P",
    "gn:feature_code":"PPL",
    "gn:name":"Vatig\u0101ru",
    "gn:population":0,
    "gn:timezone":"Asia/Kolkata",
    "iso:country":"IN",
    "ks:ks_name":"Vatagaru",
    "ks:ks_pop":625,
    "ks:ks_type":"VILLAGE",
    "name:eng_x_preferred":[
        "Vatagaru"
    ],
    "name:eng_x_variant":[
        "Vatigaru"
    ],
    "wof:name":"Vatagaru",
    "wof:placetype":"locality",
    "wof:population":625
},
  "geometry": {"coordinates":[75.287486,13.619181],"type":"Point"}
}