{
  "type": "Feature",
  "properties": {
    "gn:admin1_code":"19.0",
    "gn:admin2_code":"568.0",
    "gn:asciiname":"Vatigaru",
    "gn:country_code":"IN",
    "gn:dem":637,
    "gn:feature_class":"P",
    "gn:feature_code":"PPL",
    "gn:name":"Vatig\u0101ru",
    "gn:population":0,
    "gn:timezone":"Asia/Kolkata",
    "iso:country":"IN",
    "wof:name":"Vatigaru",
    "wof:placetype":"locality"
},
  "geometry": {"coordinates":[75.28879000000001,13.61596],"type":"Point"}
}