{
  "type": "Feature",
  "properties": {
    "gn:admin1_code":"35",
    "gn:admin2_code":"429.0",
    "gn:asciiname":"Mantola",
    "gn:country_code":"IN",
    "gn:dem":340,
    "gn:feature_class":"P",
    "gn:feature_code":"PPL",
    "gn:name":"Mantola",
    "gn:population":0,
    "gn:timezone":"Asia/Kolkata",
    "iso:country":"IN",
    "name:ara_x_preferred":[
        "\u0645\u0627\u0646\u062a\u0648\u0644\u0627"
    ],
    "name:ben_bn_x_preferred":[
        "\u09ae\u09be\u09a8\u09a4\u09b2\u09be"
    ],
    "name:ben_in_x_preferred":[
        "\u09ae\u09be\u09a8\u09a4\u09b2\u09be"
    ],
    "name:guj_x_preferred":[
        "\u0aae\u0acb\u0aa8\u0acd\u0a9f\u0acb\u0ab2\u0abe"
    ],
    "name:hin_x_preferred":[
        "\u092e\u0902\u091f\u094b\u0932\u093e"
    ],
    "name:kan_x_preferred":[
        "\u0cae\u0c82\u0ca4\u0ccb\u0cb2\u0cbe"
    ],
    "name:mal_x_preferred":[
        "\u0d2e\u0d28\u0d4d\u0d24\u0d4b\u0d33"
    ],
    "name:mar_x_preferred":[
        "\u092e\u0902\u091f\u094b\u0932\u093e"
    ],
    "name:pan_x_preferred":[
        "\u0a2e\u0a28\u0a1f\u0a4c\u0a32\u0a3e"
    ],
    "name:tam_x_preferred":[
        "\u0bae\u0ba9\u0bcd\u0b9f\u0bcb\u0bb2\u0bbe"
    ],
    "name:tel_x_preferred":[
        "\u0c2e\u0c02\u0c1f\u0c4b\u0c32\u0c3e"
    ],
    "name:urd_x_preferred":[
        "\u0645\u0627\u0646 \u0679\u0648\u0644\u06c1"
    ],
    "wof:name":"Mantola",
    "wof:placetype":"locality"
},
  "geometry": {"coordinates":[80.89124,24.33471],"type":"Point"}
}