{
  "type": "Feature",
  "properties": {
    "gn:admin1_code":"36.0",
    "gn:admin2_code":"183.0",
    "gn:asciiname":"Tilokpur",
    "gn:country_code":"IN",
    "gn:dem":103,
    "gn:feature_class":"P",
    "gn:feature_code":"PPL",
    "gn:name":"Tilokpur",
    "gn:population":0,
    "gn:timezone":"Asia/Kolkata",
    "iso:country":"IN",
    "ks:ks_name":"Tilokpur",
    "ks:ks_type":"VILLAGE",
    "name:eng_x_preferred":[
        "Tilokpur"
    ],
    "name:hin_x_preferred":[
        "\u0924\u093f\u0932\u094b\u0915\u092a\u0941\u0930"
    ],
    "wof:name":"Tilokpur",
    "wof:placetype":"locality"
},
  "geometry": {"coordinates":[82.152607,27.245127],"type":"Point"}
}