{
  "type": "Feature",
  "properties": {
    "iso:country":"IN",
    "ks:ks_name":"Manikpura",
    "ks:ks_pop":462,
    "ks:ks_type":"VILLAGE",
    "name:eng_x_preferred":[
        "Manikpura"
    ],
    "wof:name":"Manikpura",
    "wof:placetype":"locality",
    "wof:population":462
},
  "geometry": {"coordinates":[87.174104,21.714129],"type":"Point"}
}