{
  "type": "Feature",
  "properties": {
    "gn:admin1_code":"36",
    "gn:admin2_code":"134.0",
    "gn:asciiname":"Haizarpur",
    "gn:country_code":"IN",
    "gn:dem":252,
    "gn:feature_class":"P",
    "gn:feature_code":"PPL",
    "gn:name":"Haizarpur",
    "gn:population":0,
    "gn:timezone":"Asia/Kolkata",
    "iso:country":"IN",
    "name:und_x_variant":[
        "Jah\u0101ng\u012brpur Kh\u0101s"
    ],
    "wof:name":"Haizarpur",
    "wof:placetype":"locality"
},
  "geometry": {"coordinates":[78.41771,29.49671],"type":"Point"}
}