{
  "type": "Feature",
  "properties": {
    "gn:admin1_code":"28.0",
    "gn:admin2_code":"343",
    "gn:asciiname":"Bodra",
    "gn:country_code":"IN",
    "gn:dem":8,
    "gn:feature_class":"P",
    "gn:feature_code":"PPL",
    "gn:name":"Bodra",
    "gn:population":0,
    "gn:timezone":"Asia/Kolkata",
    "iso:country":"IN",
    "ks:ks_name":"Bodra",
    "ks:ks_pop":4459,
    "ks:ks_type":"VILLAGE",
    "name:eng_x_preferred":[
        "Bodra"
    ],
    "wof:name":"Bodra",
    "wof:placetype":"locality",
    "wof:population":4459
},
  "geometry": {"coordinates":[88.615368,22.447068],"type":"Point"}
}