{
  "type": "Feature",
  "properties": {
    "iso:country":"IN",
    "ks:ks_name":"Chhata Tala",
    "ks:ks_pop":486,
    "ks:ks_type":"VILLAGE",
    "name:eng_x_preferred":[
        "Chhata Tala"
    ],
    "wof:name":"Chhata Tala",
    "wof:placetype":"locality",
    "wof:population":486
},
  "geometry": {"coordinates":[86.96292200000001,23.384819],"type":"Point"}
}