{
  "type": "Feature",
  "properties": {
    "iso:country":"IN",
    "ks:ks_name":"Pedalanka",
    "ks:ks_pop":75,
    "ks:ks_type":"HABITATION",
    "name:eng_x_preferred":[
        "Pedalanka"
    ],
    "wof:name":"Pedalanka",
    "wof:placetype":"locality",
    "wof:population":75
},
  "geometry": {"coordinates":[82.52134700000001,18.00807],"type":"Point"}
}