{
  "type": "Feature",
  "properties": {
    "gn:admin1_code":"36",
    "gn:admin2_code":"179.0",
    "gn:asciiname":"Pura Lalai",
    "gn:country_code":"IN",
    "gn:dem":91,
    "gn:feature_class":"P",
    "gn:feature_code":"PPL",
    "gn:name":"Pura Lalai",
    "gn:population":0,
    "gn:timezone":"Asia/Kolkata",
    "iso:country":"IN",
    "wof:name":"Pura Lalai",
    "wof:placetype":"locality"
},
  "geometry": {"coordinates":[82.52206,26.23338],"type":"Point"}
}