{
  "type": "Feature",
  "properties": {
    "iso:country":"IN",
    "ks:ks_name":"Sultanpur Hariprasad",
    "ks:ks_pop":913,
    "ks:ks_type":"HABITATION",
    "name:eng_x_preferred":[
        "Sultanpur Hariprasad"
    ],
    "wof:name":"Sultanpur Hariprasad",
    "wof:placetype":"locality",
    "wof:population":913
},
  "geometry": {"coordinates":[80.919481,27.620899],"type":"Point"}
}