{
  "type": "Feature",
  "properties": {
    "iso:country":"IN",
    "ks:ks_name":"Kothuru",
    "ks:ks_pop":102,
    "ks:ks_type":"VILLAGE",
    "name:eng_x_preferred":[
        "Kothuru"
    ],
    "wof:name":"Kothuru",
    "wof:placetype":"locality",
    "wof:population":102
},
  "geometry": {"coordinates":[82.781581,17.968438],"type":"Point"}
}