{
  "type": "Feature",
  "properties": {
    "iso:country":"IN",
    "ks:ks_name":"Kadachala",
    "ks:ks_pop":696,
    "ks:ks_type":"VILLAGE",
    "ks:ks_uagg_main":0,
    "name:eng_x_preferred":[
        "Kadachala"
    ],
    "wof:name":"Kadachala",
    "wof:placetype":"neighbourhood",
    "wof:population":696
},
  "geometry": {"coordinates":[73.46025,22.401567],"type":"Point"}
}