{
  "type": "Feature",
  "properties": {
    "iso:country":"IN",
    "ks:ks_name":"Kakarapadu",
    "ks:ks_pop":79,
    "ks:ks_type":"HABITATION",
    "name:eng_x_preferred":[
        "Kakarapadu"
    ],
    "wof:name":"Kakarapadu",
    "wof:placetype":"locality",
    "wof:population":79
},
  "geometry": {"coordinates":[82.256229,17.91611],"type":"Point"}
}