{
  "type": "Feature",
  "properties": {
    "gn:admin1_code":"09",
    "gn:admin2_code":"475.0",
    "gn:asciiname":"Pansina",
    "gn:country_code":"IN",
    "gn:dem":24,
    "gn:feature_class":"P",
    "gn:feature_code":"PPL",
    "gn:name":"P\u0101nsina",
    "gn:population":0,
    "gn:timezone":"Asia/Kolkata",
    "iso:country":"IN",
    "wof:name":"Pansina",
    "wof:placetype":"locality"
},
  "geometry": {"coordinates":[71.9692,22.55025],"type":"Point"}
}