{
  "type": "Feature",
  "properties": {
    "iso:country":"IN",
    "ks:ks_name":"Pipar Panti",
    "ks:ks_pop":621,
    "ks:ks_type":"VILLAGE",
    "ks:ks_uagg_main":0,
    "name:eng_x_preferred":[
        "Pipar Panti"
    ],
    "wof:name":"Pipar Panti",
    "wof:placetype":"neighbourhood",
    "wof:population":621
},
  "geometry": {"coordinates":[84.25717400000001,26.327755],"type":"Point"}
}