{
  "type": "Feature",
  "properties": {
    "iso:country":"IN",
    "ks:ks_name":"Tadwayli",
    "ks:ks_pop":263,
    "ks:ks_type":"VILLAGE",
    "name:eng_x_preferred":[
        "Tadwayli"
    ],
    "wof:name":"Tadwayli",
    "wof:placetype":"locality",
    "wof:population":263
},
  "geometry": {"coordinates":[80.601032,19.746041],"type":"Point"}
}