{
  "type": "Feature",
  "properties": {
    "iso:country":"IN",
    "ks:ks_name":"Razapur",
    "ks:ks_pop":914,
    "ks:ks_type":"VILLAGE",
    "ks:ks_uagg_main":0,
    "name:eng_x_preferred":[
        "Razapur"
    ],
    "wof:name":"Razapur",
    "wof:placetype":"neighbourhood",
    "wof:population":914
},
  "geometry": {"coordinates":[76.90891000000001,30.375668],"type":"Point"}
}