{
  "type": "Feature",
  "properties": {
    "iso:country":"IN",
    "ks:ks_name":"Manjura",
    "ks:ks_pop":0,
    "ks:ks_type":"VILLAGE",
    "ks:ks_uagg_main":0,
    "name:eng_x_preferred":[
        "Manjura"
    ],
    "wof:name":"Manjura",
    "wof:placetype":"locality",
    "wof:population":0
},
  "geometry": {"coordinates":[86.21996900000001,24.900279],"type":"Point"}
}