{
  "type": "Feature",
  "properties": {
    "iso:country":"IN",
    "ks:ks_name":"Chak Mushlia",
    "ks:ks_pop":0,
    "ks:ks_type":"VILLAGE",
    "name:eng_x_preferred":[
        "Chak Mushlia"
    ],
    "wof:name":"Chak Mushlia",
    "wof:placetype":"locality",
    "wof:population":0
},
  "geometry": {"coordinates":[87.035167,23.523971],"type":"Point"}
}