{
  "type": "Feature",
  "properties": {
    "iso:country":"IN",
    "ks:ks_name":"Gauri Chaubey",
    "ks:ks_pop":483,
    "ks:ks_type":"HABITATION",
    "ks:ks_uagg_main":0,
    "name:eng_x_preferred":[
        "Gauri Chaubey"
    ],
    "wof:name":"Gauri Chaubey",
    "wof:placetype":"neighbourhood",
    "wof:population":483
},
  "geometry": {"coordinates":[80.18943299999999,26.619378],"type":"Point"}
}