{
  "type": "Feature",
  "properties": {
    "iso:country":"IN",
    "ks:ks_name":"Pushp Tali Purv",
    "ks:ks_pop":190,
    "ks:ks_type":"HABITATION",
    "ks:ks_uagg_main":0,
    "name:eng_x_preferred":[
        "Pushp Tali Purv"
    ],
    "wof:name":"Pushp Tali Purv",
    "wof:placetype":"neighbourhood",
    "wof:population":190
},
  "geometry": {"coordinates":[80.293351,27.390615],"type":"Point"}
}