{
  "type": "Feature",
  "properties": {
    "gn:admin1_code":"24",
    "gn:admin2_code":"104.0",
    "gn:asciiname":"Nangal",
    "gn:country_code":"IN",
    "gn:dem":318,
    "gn:feature_class":"P",
    "gn:feature_code":"PPL",
    "gn:name":"Nangal",
    "gn:population":0,
    "gn:timezone":"Asia/Kolkata",
    "iso:country":"IN",
    "wof:name":"Nangal",
    "wof:placetype":"locality"
},
  "geometry": {"coordinates":[76.25189,27.94501],"type":"Point"}
}