{
  "type": "Feature",
  "properties": {
    "gn:admin1_code":"00",
    "gn:asciiname":"Manhiala",
    "gn:country_code":"IN",
    "gn:dem":221,
    "gn:feature_class":"P",
    "gn:feature_code":"PPL",
    "gn:name":"Manhi\u0101la",
    "gn:population":0,
    "gn:timezone":"Asia/Karachi",
    "iso:country":"IN",
    "name:und_x_variant":[
        "Manhi\u0101la",
        "Manhi\u0101la Khurd",
        "Manhi\u0101la Kal\u0101n",
        "Kal\u0101n",
        "Khurd"
    ],
    "wof:name":"Manhiala",
    "wof:placetype":"locality"
},
  "geometry": {"coordinates":[74.54563,31.53058],"type":"Point"}
}