{
  "type": "Feature",
  "properties": {
    "gn:admin1_code":"2.0",
    "gn:admin2_code":"542",
    "gn:asciiname":"Gara",
    "gn:country_code":"IN",
    "gn:dem":11,
    "gn:feature_class":"P",
    "gn:feature_code":"PPL",
    "gn:name":"G\u0101ra",
    "gn:population":0,
    "gn:timezone":"Asia/Kolkata",
    "iso:country":"IN",
    "name:arg_x_preferred":[
        "Gara"
    ],
    "name:cat_x_preferred":[
        "Gara"
    ],
    "name:deu_x_preferred":[
        "Gara"
    ],
    "name:eus_x_preferred":[
        "Gara"
    ],
    "name:fra_x_preferred":[
        "Gara"
    ],
    "name:glg_x_preferred":[
        "Gara"
    ],
    "name:jpn_x_preferred":[
        "\u30ac\u30e9"
    ],
    "name:ltz_x_preferred":[
        "Gara"
    ],
    "name:nor_x_preferred":[
        "Gara"
    ],
    "name:spa_x_preferred":[
        "Gara"
    ],
    "name:swe_x_preferred":[
        "Gara"
    ],
    "wof:name":"Gara",
    "wof:placetype":"locality"
},
  "geometry": {"coordinates":[84.06870000000001,18.32261],"type":"Point"}
}