{
  "type": "Feature",
  "properties": {
    "iso:country":"IN",
    "ks:ks_name":"Mahua Deeh",
    "ks:ks_pop":163,
    "ks:ks_type":"HABITATION",
    "name:eng_x_preferred":[
        "Mahua Deeh"
    ],
    "wof:name":"Mahua Deeh",
    "wof:placetype":"locality",
    "wof:population":163
},
  "geometry": {"coordinates":[83.106691,27.338491],"type":"Point"}
}