{
  "type": "Feature",
  "properties": {
    "iso:country":"IN",
    "ks:ks_name":"Belalanadla",
    "ks:ks_pop":21,
    "ks:ks_type":"HABITATION",
    "name:eng_x_preferred":[
        "Belalanadla"
    ],
    "wof:name":"Belalanadla",
    "wof:placetype":"locality",
    "wof:population":21
},
  "geometry": {"coordinates":[75.031629,13.663688],"type":"Point"}
}