{
  "type": "Feature",
  "properties": {
    "gn:admin1_code":"38.0",
    "gn:admin2_code":"352.0",
    "gn:asciiname":"Lilatanr",
    "gn:country_code":"IN",
    "gn:dem":127,
    "gn:feature_class":"P",
    "gn:feature_code":"PPL",
    "gn:name":"Lil\u0101t\u0101nr",
    "gn:population":0,
    "gn:timezone":"Asia/Kolkata",
    "iso:country":"IN",
    "ks:ks_alt_nam":"Lil\u0101t\u0101nr",
    "ks:ks_name":"Lilatanr",
    "ks:ks_pop":88,
    "ks:ks_type":"VILLAGE",
    "name:eng_x_preferred":[
        "Lilatanr"
    ],
    "name:eng_x_variant":[
        "Lil\u0101t\u0101nr"
    ],
    "wof:name":"Lilatanr",
    "wof:placetype":"locality",
    "wof:population":88
},
  "geometry": {"coordinates":[87.555848,25.003931],"type":"Point"}
}