{
  "type": "Feature",
  "properties": {
    "gn:admin1_code":"34.0",
    "gn:admin2_code":"220.0",
    "gn:asciiname":"Gopalpur Palwaia",
    "gn:country_code":"IN",
    "gn:dem":48,
    "gn:feature_class":"P",
    "gn:feature_code":"PPL",
    "gn:name":"Gop\u0101lpur Palwaia",
    "gn:population":0,
    "gn:timezone":"Asia/Kolkata",
    "iso:country":"IN",
    "ks:ks_alt_nam":"Gop\u0101lpur Palwaia",
    "ks:ks_name":"Gopalpur Palwaia",
    "ks:ks_pop":0,
    "ks:ks_type":"VILLAGE",
    "name:eng_x_preferred":[
        "Gopalpur Palwaia"
    ],
    "name:eng_x_variant":[
        "Gop\u0101lpur Palwaia"
    ],
    "wof:name":"Gopalpur Palwaia",
    "wof:placetype":"locality",
    "wof:population":0
},
  "geometry": {"coordinates":[85.533638,25.560658],"type":"Point"}
}