{
  "type": "Feature",
  "properties": {
    "gn:admin1_code":"34.0",
    "gn:admin2_code":"220.0",
    "gn:asciiname":"Gopalpur Palwaia",
    "gn:country_code":"IN",
    "gn:dem":48,
    "gn:feature_class":"P",
    "gn:feature_code":"PPL",
    "gn:name":"Gop\u0101lpur Palwaia",
    "gn:population":0,
    "gn:timezone":"Asia/Kolkata",
    "iso:country":"IN",
    "name:eng_x_preferred":[
        "Gop\u0101lpur Palwaia"
    ],
    "wof:name":"Gopalpur Palwaia",
    "wof:placetype":"locality"
},
  "geometry": {"coordinates":[85.53364000000001,25.56066],"type":"Point"}
}