{
  "type": "Feature",
  "properties": {
    "gn:admin1_code":"11.0",
    "gn:admin2_code":"33.0",
    "gn:asciiname":"Nahal",
    "gn:country_code":"IN",
    "gn:dem":1632,
    "gn:feature_class":"P",
    "gn:feature_code":"PPL",
    "gn:name":"N\u0101hal",
    "gn:population":0,
    "gn:timezone":"Asia/Kolkata",
    "iso:country":"IN",
    "name:deu_x_preferred":[
        "Nachal"
    ],
    "name:fra_x_preferred":[
        "Nahal"
    ],
    "name:por_x_preferred":[
        "Nahal"
    ],
    "wof:name":"Nahal",
    "wof:placetype":"locality"
},
  "geometry": {"coordinates":[77.43086,31.31882],"type":"Point"}
}