{
  "type": "Feature",
  "properties": {
    "gn:admin1_code":"40.0",
    "gn:admin2_code":"541.0",
    "gn:asciiname":"Vissapuram",
    "gn:country_code":"IN",
    "gn:dem":61,
    "gn:feature_class":"P",
    "gn:feature_code":"PPL",
    "gn:name":"Viss\u0101puram",
    "gn:population":0,
    "gn:timezone":"Asia/Kolkata",
    "iso:country":"IN",
    "ks:ks_name":"Viswapuram",
    "ks:ks_pop":354,
    "ks:ks_type":"VILLAGE",
    "name:eng_x_preferred":[
        "Viswapuram"
    ],
    "name:eng_x_variant":[
        "Vissapuram"
    ],
    "wof:name":"Viswapuram",
    "wof:placetype":"locality",
    "wof:population":354
},
  "geometry": {"coordinates":[81.09777099999999,17.692862],"type":"Point"}
}