{
  "type": "Feature",
  "properties": {
    "iso:country":"IN",
    "ks:ks_name":"Vadolepada",
    "ks:ks_pop":25,
    "ks:ks_type":"HABITATION",
    "name:eng_x_preferred":[
        "Vadolepada"
    ],
    "wof:name":"Vadolepada",
    "wof:placetype":"locality",
    "wof:population":25
},
  "geometry": {"coordinates":[73.154736,19.721826],"type":"Point"}
}