{
  "type": "Feature",
  "properties": {
    "iso:country":"IN",
    "ks:ks_name":"Kusa Brat",
    "ks:ks_pop":180,
    "ks:ks_type":"HABITATION",
    "name:eng_x_preferred":[
        "Kusa Brat"
    ],
    "wof:name":"Kusa Brat",
    "wof:placetype":"locality",
    "wof:population":180
},
  "geometry": {"coordinates":[80.68682800000001,27.242814],"type":"Point"}
}