{
  "type": "Feature",
  "properties": {
    "iso:country":"IN",
    "ks:ks_name":"Sujawalpur",
    "ks:ks_pop":745,
    "ks:ks_type":"HABITATION",
    "name:eng_x_preferred":[
        "Sujawalpur"
    ],
    "wof:name":"Sujawalpur",
    "wof:placetype":"locality",
    "wof:population":745
},
  "geometry": {"coordinates":[81.018045,27.815833],"type":"Point"}
}