{
  "type": "Feature",
  "properties": {
    "iso:country":"IN",
    "ks:ks_alt_nam":"gopalwadi",
    "ks:ks_name":"Gopalwadi",
    "ks:ks_pop":100,
    "ks:ks_type":"HABITATION",
    "name:eng_x_preferred":[
        "Gopalwadi"
    ],
    "wof:name":"Gopalwadi",
    "wof:placetype":"locality",
    "wof:population":100
},
  "geometry": {"coordinates":[73.54679400000001,17.225325],"type":"Point"}
}