{
  "type": "Feature",
  "properties": {
    "gn:admin1_code":"36",
    "gn:admin2_code":"191.0",
    "gn:asciiname":"Badokhar",
    "gn:country_code":"IN",
    "gn:dem":82,
    "gn:feature_class":"P",
    "gn:feature_code":"PPL",
    "gn:name":"Badokhar",
    "gn:population":0,
    "gn:timezone":"Asia/Kolkata",
    "iso:country":"IN",
    "ks:ks_name":"Barokhar",
    "ks:ks_pop":187,
    "ks:ks_type":"HABITATION",
    "name:eng_x_preferred":[
        "Barokhar"
    ],
    "name:eng_x_variant":[
        "Badokhar"
    ],
    "wof:name":"Barokhar",
    "wof:placetype":"locality",
    "wof:population":187
},
  "geometry": {"coordinates":[83.226088,26.147368],"type":"Point"}
}