{
  "type": "Feature",
  "properties": {
    "iso:country":"IN",
    "ks:ks_alt_nam":"Esmilekhan ki dhani",
    "ks:ks_name":"Esmilekhan Ki Dhani",
    "ks:ks_pop":27,
    "ks:ks_type":"HABITATION",
    "name:eng_x_preferred":[
        "Esmilekhan Ki Dhani"
    ],
    "wof:name":"Esmilekhan Ki Dhani",
    "wof:placetype":"locality",
    "wof:population":27
},
  "geometry": {"coordinates":[72.01351099999999,27.3553],"type":"Point"}
}