{
  "type": "Feature",
  "properties": {
    "iso:country":"IN",
    "ks:ks_name":"Khushal Ganj",
    "ks:ks_pop":3496,
    "ks:ks_type":"VILLAGE",
    "ks:ks_uagg_main":0,
    "name:eng_x_preferred":[
        "Khushal Ganj"
    ],
    "wof:name":"Khushal Ganj",
    "wof:placetype":"locality",
    "wof:population":3496
},
  "geometry": {"coordinates":[80.802474,26.824632],"type":"Point"}
}