{
  "type": "Feature",
  "properties": {
    "iso:country":"IN",
    "ks:ks_name":"Madho",
    "ks:ks_pop":161,
    "ks:ks_type":"HABITATION",
    "name:eng_x_preferred":[
        "Madho"
    ],
    "wof:name":"Madho",
    "wof:placetype":"locality",
    "wof:population":161
},
  "geometry": {"coordinates":[79.029813,23.506156],"type":"Point"}
}