{
  "type": "Feature",
  "properties": {
    "gn:admin1_code":"39.0",
    "gn:admin2_code":"67.0",
    "gn:asciiname":"Totawali Beria",
    "gn:country_code":"IN",
    "gn:dem":232,
    "gn:feature_class":"P",
    "gn:feature_code":"PPL",
    "gn:name":"Tot\u0101w\u0101l\u012b Beri\u0101",
    "gn:population":0,
    "gn:timezone":"Asia/Kolkata",
    "iso:country":"IN",
    "wof:name":"Totawali Beria",
    "wof:placetype":"locality"
},
  "geometry": {"coordinates":[79.24124999999999,29.14709],"type":"Point"}
}