{
  "type": "Feature",
  "properties": {
    "gn:admin1_code":"36.0",
    "gn:admin2_code":"166.0",
    "gn:asciiname":"Ranyara",
    "gn:country_code":"IN",
    "gn:dem":199,
    "gn:feature_class":"P",
    "gn:feature_code":"PPL",
    "gn:name":"Rany\u0101ra",
    "gn:population":0,
    "gn:timezone":"Asia/Kolkata",
    "iso:country":"IN",
    "wof:name":"Ranyara",
    "wof:placetype":"locality"
},
  "geometry": {"coordinates":[79.04925,25.52171],"type":"Point"}
}