{
  "type": "Feature",
  "properties": {
    "iso:country":"IN",
    "ks:ks_name":"Sandanagkadu",
    "ks:ks_pop":255,
    "ks:ks_type":"HABITATION",
    "name:eng_x_preferred":[
        "Sandanagkadu"
    ],
    "wof:name":"Sandanagkadu",
    "wof:placetype":"locality",
    "wof:population":255
},
  "geometry": {"coordinates":[79.698646,10.400295],"type":"Point"}
}