{
  "type": "Feature",
  "properties": {
    "gn:admin1_code":"36.0",
    "gn:admin2_code":"164.0",
    "gn:asciiname":"Kakori",
    "gn:country_code":"IN",
    "gn:dem":128,
    "gn:feature_class":"P",
    "gn:feature_code":"PPL",
    "gn:name":"Kakori",
    "gn:population":0,
    "gn:timezone":"Asia/Kolkata",
    "iso:country":"IN",
    "name:bih_x_preferred":[
        "\u0915\u093e\u0915\u094b\u0930\u0940"
    ],
    "name:bpy_x_preferred":[
        "\u0995\u09be\u0995\u09cb\u09b0\u09bf"
    ],
    "name:ceb_x_preferred":[
        "K\u0101kori"
    ],
    "name:hin_x_preferred":[
        "\u0915\u093e\u0915\u094b\u0930\u0940"
    ],
    "name:ita_x_preferred":[
        "Kakori"
    ],
    "name:mlg_x_preferred":[
        "Kakori"
    ],
    "name:msa_x_preferred":[
        "Kakori"
    ],
    "name:new_x_preferred":[
        "\u0915\u093e\u0915\u094b\u0930\u0940"
    ],
    "name:nld_x_preferred":[
        "Kakori"
    ],
    "name:pol_x_preferred":[
        "Kakori"
    ],
    "name:sco_x_preferred":[
        "Kakori"
    ],
    "name:swe_x_preferred":[
        "K\u0101kori"
    ],
    "name:urd_x_preferred":[
        "\u06a9\u0627\u06a9\u0648\u0631\u06cc"
    ],
    "name:vie_x_preferred":[
        "Kakori"
    ],
    "name:zho_x_preferred":[
        "\u5361\u79d1\u91cc"
    ],
    "wof:name":"Kakori",
    "wof:placetype":"locality"
},
  "geometry": {"coordinates":[80.28350999999998,26.29823],"type":"Point"}
}