{
  "type": "Feature",
  "properties": {
    "gn:admin1_code":"12.0",
    "gn:admin2_code":"002",
    "gn:asciiname":"Churpur",
    "gn:country_code":"IN",
    "gn:dem":1588,
    "gn:feature_class":"P",
    "gn:feature_code":"PPL",
    "gn:name":"Churpur",
    "gn:population":0,
    "gn:timezone":"Asia/Kolkata",
    "iso:country":"IN",
    "wof:name":"Churpur",
    "wof:placetype":"neighbourhood"
},
  "geometry": {"coordinates":[74.7978,34.04114],"type":"Point"}
}