{
  "type": "Feature",
  "properties": {
    "gn:admin1_code":"23.0",
    "gn:admin2_code":"49.0",
    "gn:asciiname":"Kotli Kadirabad",
    "gn:country_code":"IN",
    "gn:dem":242,
    "gn:feature_class":"P",
    "gn:feature_code":"PPL",
    "gn:name":"Kotli Kad\u012br\u0101b\u0101d",
    "gn:population":0,
    "gn:timezone":"Asia/Kolkata",
    "iso:country":"IN",
    "wof:name":"Kotli Kadirabad",
    "wof:placetype":"locality"
},
  "geometry": {"coordinates":[75.12368000000002,31.75226],"type":"Point"}
}