{
  "type": "Feature",
  "properties": {
    "iso:country":"IN",
    "ks:ks_name":"Kalkapur",
    "ks:ks_pop":312,
    "ks:ks_type":"VILLAGE",
    "name:eng_x_preferred":[
        "Kalkapur"
    ],
    "wof:name":"Kalkapur",
    "wof:placetype":"locality",
    "wof:population":312
},
  "geometry": {"coordinates":[87.238572,23.97305],"type":"Point"}
}