{
  "type": "Feature",
  "properties": {
    "iso:country":"IN",
    "ks:ks_name":"Gair",
    "ks:ks_pop":381,
    "ks:ks_type":"VILLAGE",
    "name:eng_x_preferred":[
        "Gair"
    ],
    "wof:name":"Gair",
    "wof:placetype":"locality",
    "wof:population":381
},
  "geometry": {"coordinates":[79.13622599999999,30.541695],"type":"Point"}
}