{
  "type": "Feature",
  "properties": {
    "iso:country":"IN",
    "ks:ks_name":"Kongera",
    "ks:ks_pop":303,
    "ks:ks_type":"VILLAGE",
    "name:eng_x_preferred":[
        "Kongera"
    ],
    "wof:name":"Kongera",
    "wof:placetype":"locality",
    "wof:population":303
},
  "geometry": {"coordinates":[81.352408,19.856746],"type":"Point"}
}