{
  "type": "Feature",
  "properties": {
    "gn:admin1_code":"19.0",
    "gn:admin2_code":"571.0",
    "gn:asciiname":"Lingadahalli",
    "gn:country_code":"IN",
    "gn:dem":743,
    "gn:feature_class":"P",
    "gn:feature_code":"PPL",
    "gn:name":"Lingadahalli",
    "gn:population":0,
    "gn:timezone":"Asia/Kolkata",
    "iso:country":"IN",
    "name:san_x_preferred":[
        "\u0932\u093f\u0919\u094d\u0917\u0926\u0939\u0933\u094d\u0933\u0940"
    ],
    "wof:name":"Lingadahalli",
    "wof:placetype":"locality"
},
  "geometry": {"coordinates":[76.48364000000002,13.5065],"type":"Point"}
}