{
  "type": "Feature",
  "properties": {
    "gn:admin1_code":"36.0",
    "gn:admin2_code":"139.0",
    "gn:asciiname":"Rustampur",
    "gn:country_code":"IN",
    "gn:dem":228,
    "gn:feature_class":"P",
    "gn:feature_code":"PPL",
    "gn:name":"Rustampur",
    "gn:population":0,
    "gn:timezone":"Asia/Kolkata",
    "iso:country":"IN",
    "ks:ks_name":"Rustampur",
    "ks:ks_pop":2074,
    "ks:ks_type":"VILLAGE",
    "name:eng_x_preferred":[
        "Rustampur"
    ],
    "wof:name":"Rustampur",
    "wof:placetype":"locality",
    "wof:population":2074
},
  "geometry": {"coordinates":[77.263408,29.133747],"type":"Point"}
}