{
  "type": "Feature",
  "properties": {
    "iso:country":"IN",
    "ks:ks_name":"Chedi Asthan",
    "ks:ks_pop":442,
    "ks:ks_type":"HABITATION",
    "name:eng_x_preferred":[
        "Chedi Asthan"
    ],
    "wof:name":"Chedi Asthan",
    "wof:placetype":"locality",
    "wof:population":442
},
  "geometry": {"coordinates":[84.54658999999999,24.467621],"type":"Point"}
}