{
  "type": "Feature",
  "properties": {
    "iso:country":"IN",
    "ks:ks_name":"Korar Chak",
    "ks:ks_pop":0,
    "ks:ks_type":"VILLAGE",
    "name:eng_x_preferred":[
        "Korar Chak"
    ],
    "wof:name":"Korar Chak",
    "wof:placetype":"locality",
    "wof:population":0
},
  "geometry": {"coordinates":[87.95551399999999,23.259044],"type":"Point"}
}