{
  "type": "Feature",
  "properties": {
    "iso:country":"IN",
    "ks:ks_alt_nam":"BELATPARA",
    "ks:ks_name":"Belatpara",
    "ks:ks_pop":618,
    "ks:ks_type":"HABITATION",
    "name:eng_x_preferred":[
        "Belatpara"
    ],
    "wof:name":"Belatpara",
    "wof:placetype":"locality",
    "wof:population":618
},
  "geometry": {"coordinates":[81.93643400000001,22.562406],"type":"Point"}
}