{
  "type": "Feature",
  "properties": {
    "gn:admin1_code":"36",
    "gn:admin2_code":"194.0",
    "gn:asciiname":"Bhualapatti",
    "gn:country_code":"IN",
    "gn:dem":86,
    "gn:feature_class":"P",
    "gn:feature_code":"PPL",
    "gn:name":"Bhu\u0101l\u0101patti",
    "gn:population":0,
    "gn:timezone":"Asia/Kolkata",
    "iso:country":"IN",
    "ks:ks_alt_nam":"Bhu\u0101l\u0101patti",
    "ks:ks_name":"Bhualapatti",
    "ks:ks_type":"VILLAGE",
    "ks:ks_uagg_main":0,
    "name:eng_x_preferred":[
        "Bhualapatti"
    ],
    "name:eng_x_variant":[
        "Bhu\u0101l\u0101patti"
    ],
    "wof:name":"Bhualapatti",
    "wof:placetype":"neighbourhood"
},
  "geometry": {"coordinates":[82.69527600000001,25.715178],"type":"Point"}
}