{
  "type": "Feature",
  "properties": {
    "gn:admin1_code":"34.0",
    "gn:admin2_code":"230.0",
    "gn:asciiname":"Dhanuki",
    "gn:country_code":"IN",
    "gn:dem":60,
    "gn:feature_class":"P",
    "gn:feature_code":"PPL",
    "gn:name":"Dhanuki",
    "gn:population":0,
    "gn:timezone":"Asia/Kolkata",
    "iso:country":"IN",
    "ks:ks_name":"Dhanuki",
    "ks:ks_pop":881,
    "ks:ks_type":"HABITATION",
    "name:eng_x_preferred":[
        "Dhanuki"
    ],
    "wof:name":"Dhanuki",
    "wof:placetype":"locality",
    "wof:population":881
},
  "geometry": {"coordinates":[85.067583,25.438052],"type":"Point"}
}