{
  "type": "Feature",
  "properties": {
    "gn:admin1_code":"12.0",
    "gn:admin2_code":"7.0",
    "gn:asciiname":"Ser",
    "gn:country_code":"IN",
    "gn:dem":1208,
    "gn:feature_class":"P",
    "gn:feature_code":"PPL",
    "gn:name":"Ser",
    "gn:population":0,
    "gn:timezone":"Asia/Kolkata",
    "iso:country":"IN",
    "name:ceb_x_preferred":[
        "Ser"
    ],
    "name:fra_x_preferred":[
        "Ser"
    ],
    "name:glg_x_preferred":[
        "Ser"
    ],
    "name:hrv_x_preferred":[
        "Ser"
    ],
    "name:lav_x_preferred":[
        "Ser"
    ],
    "name:pol_x_preferred":[
        "Ser"
    ],
    "name:rus_x_preferred":[
        "\u0421\u0435\u0440"
    ],
    "name:spa_x_preferred":[
        "Ser"
    ],
    "name:srp_x_preferred":[
        "\u0421\u0435\u0440"
    ],
    "name:swe_x_preferred":[
        "Ser"
    ],
    "name:ukr_x_preferred":[
        "\u0421\u0435\u0440"
    ],
    "wof:name":"Ser",
    "wof:placetype":"locality"
},
  "geometry": {"coordinates":[75.67524,32.61972],"type":"Point"}
}