{
  "type": "Feature",
  "properties": {
    "iso:country":"IN",
    "ks:ks_name":"Padumalle",
    "ks:ks_pop":179,
    "ks:ks_type":"HABITATION",
    "name:eng_x_preferred":[
        "Padumalle"
    ],
    "wof:name":"Padumalle",
    "wof:placetype":"locality",
    "wof:population":179
},
  "geometry": {"coordinates":[74.78185999999999,13.251673],"type":"Point"}
}