{
  "type": "Feature",
  "properties": {
    "iso:country":"IN",
    "ks:ks_alt_nam":"NARAINPUR",
    "ks:ks_name":"Narainpur",
    "ks:ks_pop":40,
    "ks:ks_type":"HABITATION",
    "name:eng_x_preferred":[
        "Narainpur"
    ],
    "wof:name":"Narainpur",
    "wof:placetype":"locality",
    "wof:population":40
},
  "geometry": {"coordinates":[86.921841,25.172301],"type":"Point"}
}