{
  "type": "Feature",
  "properties": {
    "iso:country":"IN",
    "ks:ks_name":"Thar Ramcharan",
    "ks:ks_pop":57,
    "ks:ks_type":"HABITATION",
    "name:eng_x_preferred":[
        "Thar Ramcharan"
    ],
    "wof:name":"Thar Ramcharan",
    "wof:placetype":"locality",
    "wof:population":57
},
  "geometry": {"coordinates":[78.28701599999999,27.122217],"type":"Point"}
}