{
  "type": "Feature",
  "properties": {
    "gn:admin1_code":"36",
    "gn:admin2_code":"176.0",
    "gn:asciiname":"Dhanauli",
    "gn:country_code":"IN",
    "gn:dem":116,
    "gn:feature_class":"P",
    "gn:feature_code":"PPL",
    "gn:name":"Dhanauli",
    "gn:population":0,
    "gn:timezone":"Asia/Kolkata",
    "iso:country":"IN",
    "name:bpy_x_preferred":[
        "\u09a7\u09be\u09a8\u09cc\u09b2\u09bf\u09af\u09bc\u09be"
    ],
    "name:ita_x_preferred":[
        "Dhanauli"
    ],
    "name:msa_x_preferred":[
        "Dhanauli"
    ],
    "name:new_x_preferred":[
        "\u0927\u0928\u094c\u0932\u0940"
    ],
    "name:nld_x_preferred":[
        "Dhanauli"
    ],
    "name:pol_x_preferred":[
        "Dhanauli"
    ],
    "name:por_x_preferred":[
        "Dhanauli"
    ],
    "name:urd_x_preferred":[
        "\u062f\u06be\u0646\u0627\u0624\u0644\u06cc"
    ],
    "name:vie_x_preferred":[
        "Dhanauli"
    ],
    "name:zho_x_preferred":[
        "\u8fbe\u7459\u5229"
    ],
    "wof:name":"Dhanauli",
    "wof:placetype":"locality"
},
  "geometry": {"coordinates":[81.49781,26.79712],"type":"Point"}
}