{
  "type": "Feature",
  "properties": {
    "gn:admin1_code":"16",
    "gn:admin2_code":"504.0",
    "gn:asciiname":"Vagholi",
    "gn:country_code":"IN",
    "gn:dem":222,
    "gn:feature_class":"P",
    "gn:feature_code":"PPL",
    "gn:name":"V\u0101gholi",
    "gn:population":0,
    "gn:timezone":"Asia/Kolkata",
    "iso:country":"IN",
    "wof:name":"Vagholi",
    "wof:placetype":"locality"
},
  "geometry": {"coordinates":[78.80469000000002,20.59013],"type":"Point"}
}