{
  "type": "Feature",
  "properties": {
    "iso:country":"IN",
    "ks:ks_name":"Malakoppa",
    "ks:ks_pop":26,
    "ks:ks_type":"HABITATION",
    "name:eng_x_preferred":[
        "Malakoppa"
    ],
    "wof:name":"Malakoppa",
    "wof:placetype":"locality",
    "wof:population":26
},
  "geometry": {"coordinates":[74.890135,13.890356],"type":"Point"}
}