{
  "type": "Feature",
  "properties": {
    "gn:admin1_code":"10",
    "gn:admin2_code":"69.0",
    "gn:asciiname":"Miranpur Bakhskiwale",
    "gn:country_code":"IN",
    "gn:dem":489,
    "gn:feature_class":"P",
    "gn:feature_code":"PPL",
    "gn:name":"Mir\u0101npur Bakhskiw\u0101le",
    "gn:population":0,
    "gn:timezone":"Asia/Kolkata",
    "iso:country":"IN",
    "ks:ks_name":"Miranpur Bakhshiwala",
    "ks:ks_pop":1300,
    "ks:ks_type":"VILLAGE",
    "ks:ks_uagg_main":0,
    "name:eng_x_preferred":[
        "Miranpur Bakhshiwala"
    ],
    "wof:name":"Miranpur Bakhshiwala",
    "wof:placetype":"locality",
    "wof:population":1300
},
  "geometry": {"coordinates":[76.933347,30.769089],"type":"Point"}
}