{
  "type": "Feature",
  "properties": {
    "iso:country":"IN",
    "ks:ks_alt_nam":"HAJAM TOLI",
    "ks:ks_name":"Hajam Toli",
    "ks:ks_pop":246,
    "ks:ks_type":"HABITATION",
    "name:eng_x_preferred":[
        "Hajam Toli"
    ],
    "wof:name":"Hajam Toli",
    "wof:placetype":"locality",
    "wof:population":246
},
  "geometry": {"coordinates":[83.923573,25.408561],"type":"Point"}
}