{
  "type": "Feature",
  "properties": {
    "gn:admin1_code":"35",
    "gn:admin2_code":"430.0",
    "gn:asciiname":"Kaduawan",
    "gn:country_code":"IN",
    "gn:dem":312,
    "gn:feature_class":"P",
    "gn:feature_code":"PPL",
    "gn:name":"Kadu\u0101wan",
    "gn:population":0,
    "gn:timezone":"Asia/Kolkata",
    "iso:country":"IN",
    "ks:ks_alt_nam":"Kadu\u0101wan",
    "ks:ks_name":"Kaduawan",
    "ks:ks_type":"VILLAGE",
    "name:eng_x_preferred":[
        "Kaduawan"
    ],
    "name:eng_x_variant":[
        "Kadu\u0101wan"
    ],
    "wof:name":"Kaduawan",
    "wof:placetype":"locality"
},
  "geometry": {"coordinates":[81.789998,24.532105],"type":"Point"}
}