{
  "type": "Feature",
  "properties": {
    "iso:country":"IN",
    "ks:ks_name":"Chaupara",
    "ks:ks_pop":756,
    "ks:ks_type":"VILLAGE",
    "ks:ks_uagg_main":0,
    "name:eng_x_preferred":[
        "Chaupara"
    ],
    "wof:name":"Chaupara",
    "wof:placetype":"neighbourhood",
    "wof:population":756
},
  "geometry": {"coordinates":[86.002978,20.296272],"type":"Point"}
}