{
  "type": "Feature",
  "properties": {
    "iso:country":"IN",
    "ks:ks_name":"Mahadebpur",
    "ks:ks_pop":625,
    "ks:ks_type":"VILLAGE",
    "ks:ks_uagg_main":0,
    "name:eng_x_preferred":[
        "Mahadebpur"
    ],
    "wof:name":"Mahadebpur",
    "wof:placetype":"neighbourhood",
    "wof:population":625
},
  "geometry": {"coordinates":[87.92936899999999,25.215039],"type":"Point"}
}