{
  "type": "Feature",
  "properties": {
    "iso:country":"IN",
    "ks:ks_name":"Ramaguda",
    "ks:ks_pop":300,
    "ks:ks_type":"VILLAGE",
    "name:eng_x_preferred":[
        "Ramaguda"
    ],
    "wof:name":"Ramaguda",
    "wof:placetype":"locality",
    "wof:population":300
},
  "geometry": {"coordinates":[82.275812,18.305893],"type":"Point"}
}