{
  "type": "Feature",
  "properties": {
    "iso:country":"IN",
    "ks:ks_name":"Vankachinta Rf",
    "ks:ks_pop":94,
    "ks:ks_type":"HABITATION",
    "name:eng_x_preferred":[
        "Vankachinta Rf"
    ],
    "wof:name":"Vankachinta Rf",
    "wof:placetype":"locality",
    "wof:population":94
},
  "geometry": {"coordinates":[82.718992,18.020494],"type":"Point"}
}