{
  "type": "Feature",
  "properties": {
    "iso:country":"IN",
    "ks:ks_alt_nam":"Johadhed falia",
    "ks:ks_name":"Johadhed Falia",
    "ks:ks_pop":1230,
    "ks:ks_type":"HABITATION",
    "name:eng_x_preferred":[
        "Johadhed Falia"
    ],
    "wof:name":"Johadhed Falia",
    "wof:placetype":"locality",
    "wof:population":1230
},
  "geometry": {"coordinates":[74.31994400000001,22.675583],"type":"Point"}
}