{
  "type": "Feature",
  "properties": {
    "iso:country":"IN",
    "ks:ks_name":"Ekalgharia",
    "ks:ks_pop":1710,
    "ks:ks_type":"HABITATION",
    "name:eng_x_preferred":[
        "Ekalgharia"
    ],
    "wof:name":"Ekalgharia",
    "wof:placetype":"locality",
    "wof:population":1710
},
  "geometry": {"coordinates":[75.563489,22.103283],"type":"Point"}
}