{
  "type": "Feature",
  "properties": {
    "iso:country":"IN",
    "ks:ks_name":"Aggeri",
    "ks:ks_pop":255,
    "ks:ks_type":"HABITATION",
    "name:eng_x_preferred":[
        "Aggeri"
    ],
    "wof:name":"Aggeri",
    "wof:placetype":"locality",
    "wof:population":255
},
  "geometry": {"coordinates":[74.815865,14.4009],"type":"Point"}
}