{
  "type": "Feature",
  "properties": {
    "iso:country":"IN",
    "ks:ks_name":"Nuatola",
    "ks:ks_pop":100,
    "ks:ks_type":"HABITATION",
    "name:eng_x_preferred":[
        "Nuatola"
    ],
    "wof:name":"Nuatola",
    "wof:placetype":"locality",
    "wof:population":100
},
  "geometry": {"coordinates":[84.92501,22.27147],"type":"Point"}
}