{
  "type": "Feature",
  "properties": {
    "gn:admin1_code":"35",
    "gn:admin2_code":"437.0",
    "gn:asciiname":"Naranpura",
    "gn:country_code":"IN",
    "gn:dem":269,
    "gn:feature_class":"P",
    "gn:feature_code":"PPL",
    "gn:name":"Nar\u0101npura",
    "gn:population":0,
    "gn:timezone":"Asia/Kolkata",
    "iso:country":"IN",
    "ks:ks_name":"Narayanpura",
    "ks:ks_pop":1216,
    "ks:ks_type":"HABITATION",
    "name:eng_x_preferred":[
        "Narayanpura"
    ],
    "name:eng_x_variant":[
        "Naranpura"
    ],
    "wof:name":"Narayanpura",
    "wof:placetype":"locality",
    "wof:population":1216
},
  "geometry": {"coordinates":[76.760143,22.446246],"type":"Point"}
}