{
  "type": "Feature",
  "properties": {
    "iso:country":"IN",
    "ks:ks_name":"Khankari Gunth",
    "ks:ks_pop":493,
    "ks:ks_type":"VILLAGE",
    "name:eng_x_preferred":[
        "Khankari Gunth"
    ],
    "wof:name":"Khankari Gunth",
    "wof:placetype":"locality",
    "wof:population":493
},
  "geometry": {"coordinates":[79.8222,29.683063],"type":"Point"}
}