{
  "type": "Feature",
  "properties": {
    "iso:country":"IN",
    "ks:ks_name":"Harijan Basti Nai Dunia",
    "ks:ks_pop":160,
    "ks:ks_type":"HABITATION",
    "name:eng_x_preferred":[
        "Harijan Basti Nai Dunia"
    ],
    "wof:name":"Harijan Basti Nai Dunia",
    "wof:placetype":"locality",
    "wof:population":160
},
  "geometry": {"coordinates":[80.93464,25.545853],"type":"Point"}
}