{
  "type": "Feature",
  "properties": {
    "gn:admin1_code":"19",
    "gn:admin2_code":"563.0",
    "gn:asciiname":"Sampkeri",
    "gn:country_code":"IN",
    "gn:dem":595,
    "gn:feature_class":"P",
    "gn:feature_code":"PPL",
    "gn:name":"Sampkeri",
    "gn:population":0,
    "gn:timezone":"Asia/Kolkata",
    "iso:country":"IN",
    "ks:ks_name":"Sampekeri",
    "ks:ks_pop":150,
    "ks:ks_type":"HABITATION",
    "name:eng_x_preferred":[
        "Sampekeri"
    ],
    "name:eng_x_variant":[
        "Sampkeri"
    ],
    "wof:name":"Sampekeri",
    "wof:placetype":"locality",
    "wof:population":150
},
  "geometry": {"coordinates":[74.900389,14.316777],"type":"Point"}
}