{
  "type": "Feature",
  "properties": {
    "iso:country":"IN",
    "ks:ks_name":"Tembwadi",
    "ks:ks_pop":92,
    "ks:ks_type":"HABITATION",
    "name:eng_x_preferred":[
        "Tembwadi"
    ],
    "wof:name":"Tembwadi",
    "wof:placetype":"locality",
    "wof:population":92
},
  "geometry": {"coordinates":[73.546921,16.08317],"type":"Point"}
}