{
  "type": "Feature",
  "properties": {
    "gn:admin1_code":"35",
    "gn:admin2_code":"427.0",
    "gn:asciiname":"Badora",
    "gn:country_code":"IN",
    "gn:dem":500,
    "gn:feature_class":"P",
    "gn:feature_code":"PPL",
    "gn:name":"Badora",
    "gn:population":0,
    "gn:timezone":"Asia/Kolkata",
    "iso:country":"IN",
    "wof:name":"Badora",
    "wof:placetype":"locality"
},
  "geometry": {"coordinates":[78.61086,23.88889],"type":"Point"}
}