{
  "type": "Feature",
  "properties": {
    "gn:admin1_code":"10.0",
    "gn:admin2_code":"070",
    "gn:asciiname":"Dubli",
    "gn:country_code":"IN",
    "gn:dem":270,
    "gn:feature_class":"P",
    "gn:feature_code":"PPL",
    "gn:name":"D\u016bbli",
    "gn:population":0,
    "gn:timezone":"Asia/Kolkata",
    "iso:country":"IN",
    "ks:ks_name":"Dubli",
    "ks:ks_pop":1207,
    "ks:ks_type":"VILLAGE",
    "name:eng_x_preferred":[
        "Dubli"
    ],
    "wof:name":"Dubli",
    "wof:placetype":"locality",
    "wof:population":1207
},
  "geometry": {"coordinates":[76.880185,30.247842],"type":"Point"}
}