{
  "type": "Feature",
  "properties": {
    "iso:country":"IN",
    "ks:ks_name":"Gonditikra",
    "ks:ks_pop":253,
    "ks:ks_type":"HABITATION",
    "name:eng_x_preferred":[
        "Gonditikra"
    ],
    "wof:name":"Gonditikra",
    "wof:placetype":"locality",
    "wof:population":253
},
  "geometry": {"coordinates":[81.789355,18.748792],"type":"Point"}
}