{
  "type": "Feature",
  "properties": {
    "iso:country":"IN",
    "ks:ks_name":"Govindpur",
    "ks:ks_pop":286,
    "ks:ks_type":"HABITATION",
    "name:eng_x_preferred":[
        "Govindpur"
    ],
    "wof:name":"Govindpur",
    "wof:placetype":"locality",
    "wof:population":286
},
  "geometry": {"coordinates":[80.321377,24.691578],"type":"Point"}
}