{
  "type": "Feature",
  "properties": {
    "iso:country":"IN",
    "ks:ks_alt_nam":"SUKRAMPUR",
    "ks:ks_name":"Sukrampur",
    "ks:ks_pop":1123,
    "ks:ks_type":"HABITATION",
    "name:eng_x_preferred":[
        "Sukrampur"
    ],
    "wof:name":"Sukrampur",
    "wof:placetype":"locality",
    "wof:population":1123
},
  "geometry": {"coordinates":[89.177162,26.691215],"type":"Point"}
}