{
  "type": "Feature",
  "properties": {
    "iso:country":"IN",
    "ks:ks_name":"Barijhola",
    "ks:ks_pop":84,
    "ks:ks_type":"HABITATION",
    "name:eng_x_preferred":[
        "Barijhola"
    ],
    "wof:name":"Barijhola",
    "wof:placetype":"locality",
    "wof:population":84
},
  "geometry": {"coordinates":[82.957753,19.132542],"type":"Point"}
}