{
  "type": "Feature",
  "properties": {
    "iso:country":"IN",
    "ks:ks_name":"Kewatpara 1 Seoni",
    "ks:ks_pop":214,
    "ks:ks_type":"HABITATION",
    "name:eng_x_preferred":[
        "Kewatpara 1 Seoni"
    ],
    "wof:name":"Kewatpara 1 Seoni",
    "wof:placetype":"locality",
    "wof:population":214
},
  "geometry": {"coordinates":[81.804761,19.262628],"type":"Point"}
}