{
  "type": "Feature",
  "properties": {
    "iso:country":"IN",
    "ks:ks_name":"Patha Koyagudem",
    "ks:ks_pop":95,
    "ks:ks_type":"HABITATION",
    "name:eng_x_preferred":[
        "Patha Koyagudem"
    ],
    "wof:name":"Patha Koyagudem",
    "wof:placetype":"locality",
    "wof:population":95
},
  "geometry": {"coordinates":[81.188828,17.531114],"type":"Point"}
}