{
  "type": "Feature",
  "properties": {
    "iso:country":"IN",
    "ks:ks_name":"Kumbarakottige1",
    "ks:ks_pop":47,
    "ks:ks_type":"HABITATION",
    "name:eng_x_preferred":[
        "Kumbarakottige1"
    ],
    "wof:name":"Kumbarakottige1",
    "wof:placetype":"locality",
    "wof:population":47
},
  "geometry": {"coordinates":[75.49201100000001,13.326339],"type":"Point"}
}