{
  "type": "Feature",
  "properties": {
    "iso:country":"IN",
    "ks:ks_name":"Pure Arjun Singh",
    "ks:ks_pop":112,
    "ks:ks_type":"VILLAGE",
    "ks:ks_uagg_main":0,
    "name:eng_x_preferred":[
        "Pure Arjun Singh"
    ],
    "wof:name":"Pure Arjun Singh",
    "wof:placetype":"neighbourhood",
    "wof:population":112
},
  "geometry": {"coordinates":[81.35732899999999,27.592733],"type":"Point"}
}