{
  "type": "Feature",
  "properties": {
    "iso:country":"IN",
    "ks:ks_name":"Belapada",
    "ks:ks_pop":678,
    "ks:ks_type":"VILLAGE",
    "name:eng_x_preferred":[
        "Belapada"
    ],
    "wof:name":"Belapada",
    "wof:placetype":"locality",
    "wof:population":678
},
  "geometry": {"coordinates":[85.40407999999999,20.412277],"type":"Point"}
}