{
  "type": "Feature",
  "properties": {
    "iso:country":"IN",
    "ks:ks_name":"Dhusuri",
    "ks:ks_pop":2666,
    "ks:ks_type":"VILLAGE",
    "ks:ks_uagg_main":0,
    "name:eng_x_preferred":[
        "Dhusuri"
    ],
    "wof:name":"Dhusuri",
    "wof:placetype":"neighbourhood",
    "wof:population":2666
},
  "geometry": {"coordinates":[86.553226,20.892469],"type":"Point"}
}