{
  "type": "Feature",
  "properties": {
    "iso:country":"IN",
    "ks:ks_name":"N. Pal Vishun",
    "ks:ks_pop":80,
    "ks:ks_type":"HABITATION",
    "ks:ks_uagg_main":0,
    "name:eng_x_preferred":[
        "N. Pal Vishun"
    ],
    "wof:name":"N. Pal Vishun",
    "wof:placetype":"neighbourhood",
    "wof:population":80
},
  "geometry": {"coordinates":[78.836744,26.975916],"type":"Point"}
}