{
  "type": "Feature",
  "properties": {
    "gn:admin1_code":"11.0",
    "gn:admin2_code":"31.0",
    "gn:asciiname":"Mahi",
    "gn:country_code":"IN",
    "gn:dem":1414,
    "gn:feature_class":"P",
    "gn:feature_code":"PPL",
    "gn:name":"Mahi",
    "gn:population":0,
    "gn:timezone":"Asia/Kolkata",
    "iso:country":"IN",
    "name:ara_x_preferred":[
        "\u0645\u0627\u0647\u064a"
    ],
    "name:ceb_x_preferred":[
        "Mahi"
    ],
    "name:deu_x_preferred":[
        "Mahi"
    ],
    "name:ell_x_preferred":[
        "\u039c\u03ac\u03c7\u03b9"
    ],
    "name:fas_x_preferred":[
        "\u0645\u0627\u0647\u06cc"
    ],
    "name:fra_x_preferred":[
        "Mahi"
    ],
    "name:heb_x_preferred":[
        "\u05de\u05d0\u05d9\u05e7\u05d5\u05e8\u05d5"
    ],
    "name:hun_x_preferred":[
        "Mahi"
    ],
    "name:ind_x_preferred":[
        "Mahi"
    ],
    "name:ita_x_preferred":[
        "Mahi"
    ],
    "name:kor_x_preferred":[
        "\ub9c8\ud788"
    ],
    "name:pol_x_preferred":[
        "Mahi"
    ],
    "name:por_x_preferred":[
        "Mahi"
    ],
    "name:swe_x_preferred":[
        "Mahi"
    ],
    "name:tur_x_preferred":[
        "Mahi"
    ],
    "name:ukr_x_preferred":[
        "\u041c\u0430\u0445\u0456"
    ],
    "name:vie_x_preferred":[
        "S\u00f4ng Mahi"
    ],
    "wof:name":"Mahi",
    "wof:placetype":"locality"
},
  "geometry": {"coordinates":[77.11125,30.95734],"type":"Point"}
}