{
  "type": "Feature",
  "properties": {
    "iso:country":"IN",
    "ks:ks_name":"Baraddih Khurd",
    "ks:ks_pop":181,
    "ks:ks_type":"VILLAGE",
    "name:eng_x_preferred":[
        "Baraddih Khurd"
    ],
    "wof:name":"Baraddih Khurd",
    "wof:placetype":"locality",
    "wof:population":181
},
  "geometry": {"coordinates":[86.18991,23.978849],"type":"Point"}
}