{
  "type": "Feature",
  "properties": {
    "iso:country":"IN",
    "ks:ks_name":"Harijanpada",
    "ks:ks_pop":16,
    "ks:ks_type":"HABITATION",
    "name:eng_x_preferred":[
        "Harijanpada"
    ],
    "wof:name":"Harijanpada",
    "wof:placetype":"locality",
    "wof:population":16
},
  "geometry": {"coordinates":[72.863974,19.74394],"type":"Point"}
}