{
  "type": "Feature",
  "properties": {
    "iso:country":"IN",
    "ks:ks_name":"Prahlad Dera",
    "ks:ks_pop":350,
    "ks:ks_type":"HABITATION",
    "name:eng_x_preferred":[
        "Prahlad Dera"
    ],
    "wof:name":"Prahlad Dera",
    "wof:placetype":"locality",
    "wof:population":350
},
  "geometry": {"coordinates":[80.41588900000001,25.923556],"type":"Point"}
}