{
  "type": "Feature",
  "properties": {
    "gn:admin1_code":"34.0",
    "gn:admin2_code":"216.0",
    "gn:asciiname":"Dubauli",
    "gn:country_code":"IN",
    "gn:dem":66,
    "gn:feature_class":"P",
    "gn:feature_code":"PPL",
    "gn:name":"Dubauli",
    "gn:population":0,
    "gn:timezone":"Asia/Kolkata",
    "iso:country":"IN",
    "ks:ks_name":"Dubauli",
    "ks:ks_type":"VILLAGE",
    "name:eng_x_preferred":[
        "Dubauli"
    ],
    "wof:name":"Dubauli",
    "wof:placetype":"locality"
},
  "geometry": {"coordinates":[84.969577,26.179553],"type":"Point"}
}