{
  "type": "Feature",
  "properties": {
    "iso:country":"IN",
    "ks:ks_name":"Basmangi Kaval",
    "ks:ks_pop":409,
    "ks:ks_type":"VILLAGE",
    "name:eng_x_preferred":[
        "Basmangi Kaval"
    ],
    "wof:name":"Basmangi Kaval",
    "wof:placetype":"locality",
    "wof:population":409
},
  "geometry": {"coordinates":[77.022357,13.747753],"type":"Point"}
}