{
  "type": "Feature",
  "properties": {
    "iso:country":"IN",
    "ks:ks_name":"Beteli Bagan No 5",
    "ks:ks_pop":692,
    "ks:ks_type":"HABITATION",
    "ks:ks_uagg_main":0,
    "name:eng_x_preferred":[
        "Beteli Bagan No 5"
    ],
    "wof:name":"Beteli Bagan No 5",
    "wof:placetype":"neighbourhood",
    "wof:population":692
},
  "geometry": {"coordinates":[92.26141800000001,26.770381],"type":"Point"}
}