{
  "type": "Feature",
  "properties": {
    "gn:admin1_code":"39.0",
    "gn:admin2_code":"64.0",
    "gn:asciiname":"Korni",
    "gn:country_code":"IN",
    "gn:dem":1117,
    "gn:feature_class":"P",
    "gn:feature_code":"PPL",
    "gn:name":"Korni",
    "gn:population":0,
    "gn:timezone":"Asia/Kolkata",
    "iso:country":"IN",
    "name:ita_x_preferred":[
        "Korni"
    ],
    "name:rus_x_preferred":[
        "\u041a\u043e\u0440\u043d\u0438"
    ],
    "name:ukr_x_preferred":[
        "\u041a\u043e\u0440\u043d\u0456"
    ],
    "wof:name":"Korni",
    "wof:placetype":"locality"
},
  "geometry": {"coordinates":[79.40883000000002,29.91396],"type":"Point"}
}