{
  "type": "Feature",
  "properties": {
    "iso:country":"IN",
    "ks:ks_name":"Purbba Keshabpur",
    "ks:ks_pop":657,
    "ks:ks_type":"VILLAGE",
    "ks:ks_uagg_main":0,
    "name:eng_x_preferred":[
        "Purbba Keshabpur"
    ],
    "wof:name":"Purbba Keshabpur",
    "wof:placetype":"neighbourhood",
    "wof:population":657
},
  "geometry": {"coordinates":[88.14527,22.903208],"type":"Point"}
}