{
  "type": "Feature",
  "properties": {
    "iso:country":"IN",
    "ks:ks_alt_nam":"PURE DUHAKI",
    "ks:ks_name":"Pure Duhaki",
    "ks:ks_pop":78,
    "ks:ks_type":"HABITATION",
    "ks:ks_uagg_main":0,
    "name:eng_x_preferred":[
        "Pure Duhaki"
    ],
    "wof:name":"Pure Duhaki",
    "wof:placetype":"neighbourhood",
    "wof:population":78
},
  "geometry": {"coordinates":[81.344877,26.118491],"type":"Point"}
}