{
  "type": "Feature",
  "properties": {
    "iso:country":"IN",
    "ks:ks_name":"Dabalubil",
    "ks:ks_pop":512,
    "ks:ks_type":"VILLAGE",
    "ks:ks_uagg_main":0,
    "name:eng_x_preferred":[
        "Dabalubil"
    ],
    "wof:name":"Dabalubil",
    "wof:placetype":"neighbourhood",
    "wof:population":512
},
  "geometry": {"coordinates":[92.57795900000001,26.218601],"type":"Point"}
}