{
  "type": "Feature",
  "properties": {
    "iso:country":"IN",
    "ks:ks_name":"Vaderahally",
    "ks:ks_pop":770,
    "ks:ks_type":"VILLAGE",
    "ks:ks_uagg_main":0,
    "name:eng_x_preferred":[
        "Vaderahally"
    ],
    "wof:name":"Vaderahally",
    "wof:placetype":"neighbourhood",
    "wof:population":770
},
  "geometry": {"coordinates":[77.697824,13.287094],"type":"Point"}
}