{
  "type": "Feature",
  "properties": {
    "gn:admin1_code":"19.0",
    "gn:admin2_code":"574.0",
    "gn:asciiname":"Bukkanpur",
    "gn:country_code":"IN",
    "gn:dem":978,
    "gn:feature_class":"P",
    "gn:feature_code":"PPL",
    "gn:name":"Bukkanpur",
    "gn:population":0,
    "gn:timezone":"Asia/Kolkata",
    "iso:country":"IN",
    "wof:name":"Bukkanpur",
    "wof:placetype":"locality"
},
  "geometry": {"coordinates":[75.85209,12.97687],"type":"Point"}
}