{
  "type": "Feature",
  "properties": {
    "iso:country":"IN",
    "ks:ks_name":"Kakorikata",
    "ks:ks_pop":1000,
    "ks:ks_type":"VILLAGE",
    "name:eng_x_preferred":[
        "Kakorikata"
    ],
    "wof:name":"Kakorikata",
    "wof:placetype":"locality",
    "wof:population":1000
},
  "geometry": {"coordinates":[94.08549499999999,26.911403],"type":"Point"}
}