{
  "type": "Feature",
  "properties": {
    "iso:country":"IN",
    "ks:ks_name":"Amlifalia",
    "ks:ks_pop":671,
    "ks:ks_type":"HABITATION",
    "name:eng_x_preferred":[
        "Amlifalia"
    ],
    "wof:name":"Amlifalia",
    "wof:placetype":"locality",
    "wof:population":671
},
  "geometry": {"coordinates":[73.00538899999999,20.659972],"type":"Point"}
}