{
  "type": "Feature",
  "properties": {
    "gn:admin1_code":"37.0",
    "gn:admin2_code":"414.0",
    "gn:asciiname":"Sadra",
    "gn:country_code":"IN",
    "gn:dem":665,
    "gn:feature_class":"P",
    "gn:feature_code":"PPLL",
    "gn:name":"Sadra",
    "gn:population":0,
    "gn:timezone":"Asia/Kolkata",
    "iso:country":"IN",
    "name:hrv_x_preferred":[
        "Sadra"
    ],
    "wof:name":"Sadra",
    "wof:placetype":"locality"
},
  "geometry": {"coordinates":[81.64289000000002,18.89509],"type":"Point"}
}