{
  "type": "Feature",
  "properties": {
    "iso:country":"IN",
    "ks:ks_name":"Salapatada",
    "ks:ks_pop":43,
    "ks:ks_type":"VILLAGE",
    "name:eng_x_preferred":[
        "Salapatada"
    ],
    "wof:name":"Salapatada",
    "wof:placetype":"locality",
    "wof:population":43
},
  "geometry": {"coordinates":[86.673924,21.709661],"type":"Point"}
}