{
  "type": "Feature",
  "properties": {
    "iso:country":"IN",
    "ks:ks_name":"Pawai S.c. Basti",
    "ks:ks_pop":349,
    "ks:ks_type":"HABITATION",
    "ks:ks_uagg_main":0,
    "name:eng_x_preferred":[
        "Pawai S.c. Basti"
    ],
    "wof:name":"Pawai S.c. Basti",
    "wof:placetype":"neighbourhood",
    "wof:population":349
},
  "geometry": {"coordinates":[82.73128199999999,26.168092],"type":"Point"}
}