{
  "type": "Feature",
  "properties": {
    "iso:country":"IN",
    "ks:ks_name":"Rajanepada",
    "ks:ks_pop":56,
    "ks:ks_type":"HABITATION",
    "name:eng_x_preferred":[
        "Rajanepada"
    ],
    "wof:name":"Rajanepada",
    "wof:placetype":"locality",
    "wof:population":56
},
  "geometry": {"coordinates":[73.63249999999999,19.466667],"type":"Point"}
}