{
  "type": "Feature",
  "properties": {
    "iso:country":"IN",
    "ks:ks_name":"Gamadi",
    "ks:ks_pop":704,
    "ks:ks_type":"HABITATION",
    "name:eng_x_preferred":[
        "Gamadi"
    ],
    "wof:name":"Gamadi",
    "wof:placetype":"locality",
    "wof:population":704
},
  "geometry": {"coordinates":[73.726778,23.088556],"type":"Point"}
}