{
  "type": "Feature",
  "properties": {
    "iso:country":"IN",
    "ks:ks_name":"12 MD-A",
    "ks:ks_pop":220,
    "ks:ks_type":"VILLAGE",
    "name:eng_x_preferred":[
        "12 MD-A"
    ],
    "wof:name":"12 MD-A",
    "wof:placetype":"locality",
    "wof:population":220
},
  "geometry": {"coordinates":[73.09564399999999,29.061158],"type":"Point"}
}