{
  "type": "Feature",
  "properties": {
    "gn:admin1_code":"36",
    "gn:admin2_code":"176.0",
    "gn:asciiname":"Kuti Baijnath Das",
    "gn:country_code":"IN",
    "gn:dem":116,
    "gn:feature_class":"P",
    "gn:feature_code":"PPL",
    "gn:name":"Kuti Baijn\u0101th D\u0101s",
    "gn:population":0,
    "gn:timezone":"Asia/Kolkata",
    "iso:country":"IN",
    "wof:name":"Kuti Baijnath Das",
    "wof:placetype":"locality"
},
  "geometry": {"coordinates":[81.41632,26.61525],"type":"Point"}
}