{
  "type": "Feature",
  "properties": {
    "gn:admin1_code":"10.0",
    "gn:admin2_code":"076",
    "gn:asciiname":"Hasanyarpur Tihara Kalan",
    "gn:country_code":"IN",
    "gn:dem":228,
    "gn:feature_class":"P",
    "gn:feature_code":"PPL",
    "gn:name":"Hasany\u0101rpur Tih\u0101ra Kal\u0101n",
    "gn:population":0,
    "gn:timezone":"Asia/Kolkata",
    "iso:country":"IN",
    "wof:name":"Hasanyarpur Tihara Kalan",
    "wof:placetype":"locality"
},
  "geometry": {"coordinates":[76.92379,28.98293],"type":"Point"}
}