{
  "type": "Feature",
  "properties": {
    "gn:admin1_code":"10.0",
    "gn:admin2_code":"076",
    "gn:asciiname":"Hasanyarpur Tihara Kalan",
    "gn:country_code":"IN",
    "gn:dem":228,
    "gn:feature_class":"P",
    "gn:feature_code":"PPL",
    "gn:name":"Hasany\u0101rpur Tih\u0101ra Kal\u0101n",
    "gn:population":0,
    "gn:timezone":"Asia/Kolkata",
    "iso:country":"IN",
    "ks:ks_alt_nam":"Hasany\u0101rpur Tih\u0101ra Kal\u0101n",
    "ks:ks_name":"Hasanyarpur Tihara Kalan",
    "ks:ks_pop":1491,
    "ks:ks_type":"VILLAGE",
    "name:eng_x_preferred":[
        "Hasanyarpur Tihara Kalan"
    ],
    "name:eng_x_variant":[
        "Hasany\u0101rpur Tih\u0101ra Kal\u0101n"
    ],
    "wof:name":"Hasanyarpur Tihara Kalan",
    "wof:placetype":"locality",
    "wof:population":1491
},
  "geometry": {"coordinates":[76.90958500000001,28.974293],"type":"Point"}
}