{
  "type": "Feature",
  "properties": {
    "iso:country":"IN",
    "ks:ks_name":"Puttegowdanapalya",
    "ks:ks_pop":128,
    "ks:ks_type":"HABITATION",
    "name:eng_x_preferred":[
        "Puttegowdanapalya"
    ],
    "wof:name":"Puttegowdanapalya",
    "wof:placetype":"locality",
    "wof:population":128
},
  "geometry": {"coordinates":[77.077405,13.096064],"type":"Point"}
}