{
  "type": "Feature",
  "properties": {
    "gn:admin1_code":"16.0",
    "gn:admin2_code":"505.0",
    "gn:asciiname":"Selu",
    "gn:country_code":"IN",
    "gn:dem":355,
    "gn:feature_class":"P",
    "gn:feature_code":"PPL",
    "gn:name":"Selu",
    "gn:population":0,
    "gn:timezone":"Asia/Kolkata",
    "iso:country":"IN",
    "name:ceb_x_preferred":[
        "Selu"
    ],
    "name:deu_x_preferred":[
        "Selu"
    ],
    "name:swe_x_preferred":[
        "Selu"
    ],
    "wof:name":"Selu",
    "wof:placetype":"locality"
},
  "geometry": {"coordinates":[78.89797,21.20543],"type":"Point"}
}