{
  "type": "Feature",
  "properties": {
    "iso:country":"IN",
    "ks:ks_name":"Bamankuli",
    "ks:ks_pop":1675,
    "ks:ks_type":"VILLAGE",
    "ks:ks_uagg_main":0,
    "name:eng_x_preferred":[
        "Bamankuli"
    ],
    "wof:name":"Bamankuli",
    "wof:placetype":"neighbourhood",
    "wof:population":1675
},
  "geometry": {"coordinates":[86.966724,23.30861],"type":"Point"}
}