{
  "type": "Feature",
  "properties": {
    "iso:country":"IN",
    "ks:ks_name":"Itimari",
    "ks:ks_pop":32,
    "ks:ks_type":"HABITATION",
    "name:eng_x_preferred":[
        "Itimari"
    ],
    "wof:name":"Itimari",
    "wof:placetype":"locality",
    "wof:population":32
},
  "geometry": {"coordinates":[83.03666,18.783786],"type":"Point"}
}