{
  "type": "Feature",
  "properties": {
    "gn:admin1_code":"24.0",
    "gn:admin2_code":"102",
    "gn:asciiname":"Bhairusar",
    "gn:country_code":"IN",
    "gn:dem":267,
    "gn:feature_class":"P",
    "gn:feature_code":"PPL",
    "gn:name":"Bhair\u016bsar",
    "gn:population":0,
    "gn:timezone":"Asia/Kolkata",
    "iso:country":"IN",
    "name:und_x_variant":[
        "Bharusar",
        "Bhair\u016bsar"
    ],
    "wof:name":"Bhairusar",
    "wof:placetype":"locality"
},
  "geometry": {"coordinates":[74.97694,28.46548],"type":"Point"}
}