{
  "type": "Feature",
  "properties": {
    "gn:admin1_code":"39.0",
    "gn:admin2_code":"68.0",
    "gn:asciiname":"Bagowali",
    "gn:country_code":"IN",
    "gn:dem":236,
    "gn:feature_class":"P",
    "gn:feature_code":"PPL",
    "gn:name":"B\u0101gow\u0101li",
    "gn:population":0,
    "gn:timezone":"Asia/Kolkata",
    "iso:country":"IN",
    "wof:name":"Bagowali",
    "wof:placetype":"locality"
},
  "geometry": {"coordinates":[78.02110999999999,29.70103],"type":"Point"}
}