{
  "type": "Feature",
  "properties": {
    "gn:admin1_code":"12.0",
    "gn:admin2_code":"19.0",
    "gn:asciiname":"Putal",
    "gn:country_code":"IN",
    "gn:dem":1588,
    "gn:feature_class":"P",
    "gn:feature_code":"PPL",
    "gn:name":"Putal",
    "gn:population":0,
    "gn:timezone":"Asia/Kolkata",
    "iso:country":"IN",
    "name:und_x_variant":[
        "Patwal"
    ],
    "wof:name":"Putal",
    "wof:placetype":"locality"
},
  "geometry": {"coordinates":[75.52030999999999,32.74768],"type":"Point"}
}