{
  "type": "Feature",
  "properties": {
    "iso:country":"IN",
    "ks:ks_alt_nam":"21 KD",
    "ks:ks_name":"21 Kd",
    "ks:ks_pop":103,
    "ks:ks_type":"HABITATION",
    "name:eng_x_preferred":[
        "21 Kd"
    ],
    "wof:name":"21 Kd",
    "wof:placetype":"locality",
    "wof:population":103
},
  "geometry": {"coordinates":[72.753753,28.917989],"type":"Point"}
}