{
  "type": "Feature",
  "properties": {
    "gn:admin1_code":"24.0",
    "gn:admin2_code":"110",
    "gn:asciiname":"Renwal",
    "gn:country_code":"IN",
    "gn:dem":405,
    "gn:feature_class":"P",
    "gn:feature_code":"PPL",
    "gn:name":"Renw\u0101l",
    "gn:population":0,
    "gn:timezone":"Asia/Kolkata",
    "iso:country":"IN",
    "name:und_x_variant":[
        "Renw\u0101l",
        "Kishangarh"
    ],
    "wof:name":"Renwal",
    "wof:placetype":"locality"
},
  "geometry": {"coordinates":[75.35808,27.15767],"type":"Point"}
}