{
  "type": "Feature",
  "properties": {
    "iso:country":"IN",
    "ks:ks_name":"Awalepathar",
    "ks:ks_pop":284,
    "ks:ks_type":"HABITATION",
    "name:eng_x_preferred":[
        "Awalepathar"
    ],
    "wof:name":"Awalepathar",
    "wof:placetype":"locality",
    "wof:population":284
},
  "geometry": {"coordinates":[74.351339,17.825277],"type":"Point"}
}