{
  "type": "Feature",
  "properties": {
    "iso:country":"IN",
    "ks:ks_name":"Mathu Mog Para",
    "ks:ks_pop":175,
    "ks:ks_type":"HABITATION",
    "name:eng_x_preferred":[
        "Mathu Mog Para"
    ],
    "wof:name":"Mathu Mog Para",
    "wof:placetype":"locality",
    "wof:population":175
},
  "geometry": {"coordinates":[91.65641599999999,23.243954],"type":"Point"}
}