{
  "type": "Feature",
  "properties": {
    "iso:country":"IN",
    "ks:ks_name":"Aremane",
    "ks:ks_pop":70,
    "ks:ks_type":"HABITATION",
    "name:eng_x_preferred":[
        "Aremane"
    ],
    "wof:name":"Aremane",
    "wof:placetype":"locality",
    "wof:population":70
},
  "geometry": {"coordinates":[75.476601,13.4385],"type":"Point"}
}