{
  "type": "Feature",
  "properties": {
    "iso:country":"IN",
    "ks:ks_name":"Chiruan",
    "ks:ks_pop":403,
    "ks:ks_type":"VILLAGE",
    "ks:ks_uagg_main":0,
    "name:eng_x_preferred":[
        "Chiruan"
    ],
    "wof:name":"Chiruan",
    "wof:placetype":"neighbourhood",
    "wof:population":403
},
  "geometry": {"coordinates":[85.56053300000001,24.001657],"type":"Point"}
}