{
  "type": "Feature",
  "properties": {
    "iso:country":"IN",
    "ks:ks_alt_nam":"PAWARWASTI",
    "ks:ks_name":"Pawarwasti",
    "ks:ks_pop":124,
    "ks:ks_type":"HABITATION",
    "name:eng_x_preferred":[
        "Pawarwasti"
    ],
    "wof:name":"Pawarwasti",
    "wof:placetype":"locality",
    "wof:population":124
},
  "geometry": {"coordinates":[74.773667,17.137018],"type":"Point"}
}