{
  "type": "Feature",
  "properties": {
    "iso:country":"IN",
    "ks:ks_name":"Gulu",
    "ks:ks_pop":164,
    "ks:ks_type":"VILLAGE",
    "name:eng_x_preferred":[
        "Gulu"
    ],
    "wof:name":"Gulu",
    "wof:placetype":"locality",
    "wof:population":164
},
  "geometry": {"coordinates":[83.678921,24.659071],"type":"Point"}
}