{
  "type": "Feature",
  "properties": {
    "gn:admin1_code":"13.0",
    "gn:admin2_code":"589",
    "gn:asciiname":"Kariyad",
    "gn:country_code":"IN",
    "gn:dem":10,
    "gn:feature_class":"P",
    "gn:feature_code":"PPLL",
    "gn:name":"Kariyad",
    "gn:population":0,
    "gn:timezone":"Asia/Kolkata",
    "iso:country":"IN",
    "wof:name":"Kariyad",
    "wof:placetype":"locality"
},
  "geometry": {"coordinates":[75.57743000000001,11.6878],"type":"Point"}
}