{
  "type": "Feature",
  "properties": {
    "gn:admin1_code":"39.0",
    "gn:admin2_code":"61.0",
    "gn:asciiname":"Lajkhil",
    "gn:country_code":"IN",
    "gn:dem":1467,
    "gn:feature_class":"P",
    "gn:feature_code":"PPL",
    "gn:name":"L\u0101jkhil",
    "gn:population":0,
    "gn:timezone":"Asia/Kolkata",
    "iso:country":"IN",
    "wof:name":"Lajkhil",
    "wof:placetype":"locality"
},
  "geometry": {"coordinates":[79.03137,29.89895],"type":"Point"}
}