{
  "type": "Feature",
  "properties": {
    "gn:admin1_code":"36.0",
    "gn:admin2_code":"136.0",
    "gn:asciiname":"Milak Nai Bihi",
    "gn:country_code":"IN",
    "gn:dem":203,
    "gn:feature_class":"P",
    "gn:feature_code":"PPL",
    "gn:name":"Milak Na\u012b B\u012bh\u012b",
    "gn:population":0,
    "gn:timezone":"Asia/Kolkata",
    "iso:country":"IN",
    "ks:ks_alt_nam":"Milak Na\u012b B\u012bh\u012b",
    "ks:ks_name":"Milak Nai Bihi",
    "ks:ks_type":"VILLAGE",
    "name:eng_x_preferred":[
        "Milak Nai Bihi"
    ],
    "name:eng_x_variant":[
        "Milak Na\u012b B\u012bh\u012b"
    ],
    "wof:name":"Milak Nai Bihi",
    "wof:placetype":"locality"
},
  "geometry": {"coordinates":[79.001097,28.964674],"type":"Point"}
}