{
  "type": "Feature",
  "properties": {
    "gn:admin1_code":"13.0",
    "gn:admin2_code":"588.0",
    "gn:asciiname":"Badaje",
    "gn:country_code":"IN",
    "gn:dem":21,
    "gn:feature_class":"P",
    "gn:feature_code":"PPLL",
    "gn:name":"Bad\u0101je",
    "gn:population":0,
    "gn:timezone":"Asia/Kolkata",
    "iso:country":"IN",
    "name:mal_x_preferred":[
        "\u0d2c\u0d21\u0d3e\u0d1c\u0d46"
    ],
    "wof:name":"Badaje",
    "wof:placetype":"locality"
},
  "geometry": {"coordinates":[74.91152,12.72341],"type":"Point"}
}