{
  "type": "Feature",
  "properties": {
    "gn:admin1_code":"13.0",
    "gn:admin2_code":"588.0",
    "gn:asciiname":"Badaje",
    "gn:country_code":"IN",
    "gn:dem":21,
    "gn:feature_class":"P",
    "gn:feature_code":"PPLL",
    "gn:name":"Bad\u0101je",
    "gn:population":0,
    "gn:timezone":"Asia/Kolkata",
    "iso:country":"IN",
    "ks:ks_name":"Badaje",
    "ks:ks_pop":893,
    "ks:ks_type":"HABITATION",
    "name:eng_x_preferred":[
        "Badaje"
    ],
    "name:mal_x_preferred":[
        "\u0d2c\u0d21\u0d3e\u0d1c\u0d46"
    ],
    "wof:name":"Badaje",
    "wof:placetype":"locality",
    "wof:population":893
},
  "geometry": {"coordinates":[74.900826,12.725428],"type":"Point"}
}