{
  "type": "Feature",
  "properties": {
    "gn:admin1_code":"36.0",
    "gn:admin2_code":"154.0",
    "gn:asciiname":"Rampur",
    "gn:country_code":"IN",
    "gn:dem":138,
    "gn:feature_class":"P",
    "gn:feature_code":"PPL",
    "gn:name":"R\u0101mpur",
    "gn:population":0,
    "gn:timezone":"Asia/Kolkata",
    "iso:country":"IN",
    "name:ara_x_preferred":[
        "\u0631\u0627\u0645\u0628\u0648\u0631"
    ],
    "name:ben_bn_x_preferred":[
        "\u09b0\u09be\u09ae\u09aa\u09c1\u09b0"
    ],
    "name:ben_in_x_preferred":[
        "\u09b0\u09be\u09ae\u09aa\u09c1\u09b0"
    ],
    "name:ben_x_preferred":[
        "\u09b0\u09be\u09ae\u09aa\u09c1\u09b0"
    ],
    "name:bih_x_preferred":[
        "\u0930\u093e\u092e\u092a\u0941\u0930"
    ],
    "name:bpy_x_preferred":[
        "\u09b0\u09be\u09ae\u09aa\u09c1\u09b0"
    ],
    "name:cat_x_preferred":[
        "Rampur"
    ],
    "name:ceb_x_preferred":[
        "Rampur"
    ],
    "name:deu_x_preferred":[
        "Rampur"
    ],
    "name:fra_x_preferred":[
        "Rampur"
    ],
    "name:guj_x_preferred":[
        "\u0ab0\u0abe\u0aae\u0aaa\u0ac1\u0ab0"
    ],
    "name:hin_x_preferred":[
        "\u0930\u093e\u092e\u092a\u0941\u0930"
    ],
    "name:ita_x_preferred":[
        "Rampur"
    ],
    "name:kan_x_preferred":[
        "\u0cb0\u0cbe\u0cae\u0ccd"
    ],
    "name:mal_x_preferred":[
        "\u0d30\u0d3e\u0d02\u0d2a\u0d42\u0d7c"
    ],
    "name:mar_x_preferred":[
        "\u0930\u093e\u092e\u092a\u0941\u0930"
    ],
    "name:new_x_preferred":[
        "\u0930\u093e\u092e\u092a\u0941\u0930"
    ],
    "name:nld_x_preferred":[
        "Rampur"
    ],
    "name:pan_x_preferred":[
        "\u0a30\u0a3e\u0a2e\u0a2a\u0a41\u0a30"
    ],
    "name:pnb_x_preferred":[
        "\u0631\u0627\u0645 \u067e\u0648\u0631"
    ],
    "name:pol_x_preferred":[
        "Rampur"
    ],
    "name:rus_x_preferred":[
        "\u0420\u0430\u043c\u043f\u0443\u0440"
    ],
    "name:snd_x_preferred":[
        "\u0631\u0627\u0645 \u067e\u0648\u0631"
    ],
    "name:swe_x_preferred":[
        "Rampur"
    ],
    "name:tam_x_preferred":[
        "\u0bb0\u0bbe\u0bae\u0bcd\u0baa\u0bc2\u0bb0\u0bcd"
    ],
    "name:tel_x_preferred":[
        "\u0c30\u0c3e\u0c02\u0c2a\u0c42\u0c30\u0c4d"
    ],
    "name:urd_x_preferred":[
        "\u0631\u0627\u0645\u067e\u0648\u0631"
    ],
    "name:urd_x_variant":[
        "\u0631\u0627\u0645 \u067e\u0648\u0631"
    ],
    "wof:name":"Rampur",
    "wof:placetype":"locality"
},
  "geometry": {"coordinates":[80.65179999999999,27.33409],"type":"Point"}
}