{
  "type": "Feature",
  "properties": {
    "gn:admin1_code":"39.0",
    "gn:admin2_code":"61.0",
    "gn:asciiname":"Maniyargaon",
    "gn:country_code":"IN",
    "gn:dem":1515,
    "gn:feature_class":"P",
    "gn:feature_code":"PPL",
    "gn:name":"Maniy\u0101rgaon",
    "gn:population":0,
    "gn:timezone":"Asia/Kolkata",
    "iso:country":"IN",
    "wof:name":"Maniyargaon",
    "wof:placetype":"locality"
},
  "geometry": {"coordinates":[79.14816999999999,29.9311],"type":"Point"}
}