{
  "type": "Feature",
  "properties": {
    "gn:admin1_code":"39.0",
    "gn:admin2_code":"61.0",
    "gn:asciiname":"Maniyargaon",
    "gn:country_code":"IN",
    "gn:dem":1515,
    "gn:feature_class":"P",
    "gn:feature_code":"PPL",
    "gn:name":"Maniy\u0101rgaon",
    "gn:population":0,
    "gn:timezone":"Asia/Kolkata",
    "iso:country":"IN",
    "ks:ks_name":"Maniyar Gaon",
    "ks:ks_pop":367,
    "ks:ks_type":"VILLAGE",
    "name:eng_x_preferred":[
        "Maniyar Gaon"
    ],
    "name:eng_x_variant":[
        "Maniyargaon"
    ],
    "wof:name":"Maniyar Gaon",
    "wof:placetype":"locality",
    "wof:population":367
},
  "geometry": {"coordinates":[79.14613799999999,29.93055],"type":"Point"}
}