{
  "type": "Feature",
  "properties": {
    "iso:country":"IN",
    "ks:ks_name":"Kiringloya",
    "ks:ks_pop":77,
    "ks:ks_type":"VILLAGE",
    "ks:ks_uagg_main":0,
    "name:eng_x_preferred":[
        "Kiringloya"
    ],
    "wof:name":"Kiringloya",
    "wof:placetype":"neighbourhood",
    "wof:population":77
},
  "geometry": {"coordinates":[84.77051899999999,22.973022],"type":"Point"}
}