{
  "type": "Feature",
  "properties": {
    "iso:country":"IN",
    "ks:ks_alt_nam":"sadhar khera",
    "ks:ks_name":"Sadhar Khera",
    "ks:ks_pop":165,
    "ks:ks_type":"HABITATION",
    "name:eng_x_preferred":[
        "Sadhar Khera"
    ],
    "wof:name":"Sadhar Khera",
    "wof:placetype":"locality",
    "wof:population":165
},
  "geometry": {"coordinates":[80.807114,26.245364],"type":"Point"}
}