{
  "type": "Feature",
  "properties": {
    "iso:country":"IN",
    "ks:ks_name":"Saru Amri",
    "ks:ks_pop":189,
    "ks:ks_type":"VILLAGE",
    "ks:ks_uagg_main":0,
    "name:eng_x_preferred":[
        "Saru Amri"
    ],
    "wof:name":"Saru Amri",
    "wof:placetype":"neighbourhood",
    "wof:population":189
},
  "geometry": {"coordinates":[92.52592799999999,26.111815],"type":"Point"}
}