{
  "type": "Feature",
  "properties": {
    "iso:country":"IN",
    "ks:ks_name":"1 MSR",
    "ks:ks_pop":274,
    "ks:ks_type":"VILLAGE",
    "name:eng_x_preferred":[
        "1 MSR"
    ],
    "wof:name":"1 MSR",
    "wof:placetype":"locality",
    "wof:population":274
},
  "geometry": {"coordinates":[75.128953,29.183756],"type":"Point"}
}