{
  "type": "Feature",
  "properties": {
    "iso:country":"IN",
    "ks:ks_name":"Therkupatti",
    "ks:ks_pop":420,
    "ks:ks_type":"HABITATION",
    "ks:ks_uagg_main":0,
    "name:eng_x_preferred":[
        "Therkupatti"
    ],
    "wof:name":"Therkupatti",
    "wof:placetype":"neighbourhood",
    "wof:population":420
},
  "geometry": {"coordinates":[79.089579,10.464995],"type":"Point"}
}