{
  "type": "Feature",
  "properties": {
    "gn:admin1_code":"35",
    "gn:admin2_code":"429.0",
    "gn:asciiname":"Chinda",
    "gn:country_code":"IN",
    "gn:dem":319,
    "gn:feature_class":"P",
    "gn:feature_code":"PPL",
    "gn:name":"Chinda",
    "gn:population":0,
    "gn:timezone":"Asia/Kolkata",
    "iso:country":"IN",
    "name:fra_x_preferred":[
        "Chinda"
    ],
    "name:ita_x_preferred":[
        "Chinda"
    ],
    "name:nld_x_preferred":[
        "Chinda"
    ],
    "name:por_x_preferred":[
        "Chinda"
    ],
    "name:spa_x_preferred":[
        "Chinda"
    ],
    "wof:name":"Chinda",
    "wof:placetype":"locality"
},
  "geometry": {"coordinates":[80.71239,24.59943],"type":"Point"}
}