{
  "type": "Feature",
  "properties": {
    "iso:country":"IN",
    "ks:ks_name":"Jalakadhole",
    "ks:ks_pop":21,
    "ks:ks_type":"HABITATION",
    "name:eng_x_preferred":[
        "Jalakadhole"
    ],
    "wof:name":"Jalakadhole",
    "wof:placetype":"locality",
    "wof:population":21
},
  "geometry": {"coordinates":[75.478374,12.666981],"type":"Point"}
}