{
  "type": "Feature",
  "properties": {
    "iso:country":"IN",
    "ks:ks_name":"Afatpura",
    "ks:ks_pop":100,
    "ks:ks_type":"HABITATION",
    "name:eng_x_preferred":[
        "Afatpura"
    ],
    "wof:name":"Afatpura",
    "wof:placetype":"locality",
    "wof:population":100
},
  "geometry": {"coordinates":[79.690248,25.870108],"type":"Point"}
}