{
  "type": "Feature",
  "properties": {
    "iso:country":"IN",
    "ks:ks_name":"Dobri",
    "ks:ks_pop":168,
    "ks:ks_type":"VILLAGE",
    "name:eng_x_preferred":[
        "Dobri"
    ],
    "wof:name":"Dobri",
    "wof:placetype":"locality",
    "wof:population":168
},
  "geometry": {"coordinates":[79.08240000000001,30.208494],"type":"Point"}
}