{
  "type": "Feature",
  "properties": {
    "gn:admin1_code":"19.0",
    "gn:admin2_code":"576.0",
    "gn:asciiname":"Iggodlu",
    "gn:country_code":"IN",
    "gn:dem":960,
    "gn:feature_class":"P",
    "gn:feature_code":"PPL",
    "gn:name":"Iggodlu",
    "gn:population":0,
    "gn:timezone":"Asia/Kolkata",
    "iso:country":"IN",
    "ks:ks_name":"Iggodlu",
    "ks:ks_pop":372,
    "ks:ks_type":"HABITATION",
    "name:eng_x_preferred":[
        "Iggodlu"
    ],
    "wof:name":"Iggodlu",
    "wof:placetype":"locality",
    "wof:population":372
},
  "geometry": {"coordinates":[75.796944,12.505],"type":"Point"}
}