{
  "type": "Feature",
  "properties": {
    "gn:admin1_code":"19.0",
    "gn:admin2_code":"576.0",
    "gn:asciiname":"Iggodlu",
    "gn:country_code":"IN",
    "gn:dem":960,
    "gn:feature_class":"P",
    "gn:feature_code":"PPL",
    "gn:name":"Iggodlu",
    "gn:population":0,
    "gn:timezone":"Asia/Kolkata",
    "iso:country":"IN",
    "wof:name":"Iggodlu",
    "wof:placetype":"locality"
},
  "geometry": {"coordinates":[75.79371,12.51158],"type":"Point"}
}