{
  "type": "Feature",
  "properties": {
    "iso:country":"IN",
    "ks:ks_name":"Suryavanshiwasti",
    "ks:ks_pop":100,
    "ks:ks_type":"HABITATION",
    "name:eng_x_preferred":[
        "Suryavanshiwasti"
    ],
    "wof:name":"Suryavanshiwasti",
    "wof:placetype":"locality",
    "wof:population":100
},
  "geometry": {"coordinates":[75.40178,17.294208],"type":"Point"}
}