{
  "type": "Feature",
  "properties": {
    "iso:country":"IN",
    "ks:ks_alt_nam":"Khari Samn\u0101pur",
    "ks:ks_name":"Khari Samnapur",
    "ks:ks_type":"VILLAGE",
    "name:eng_x_preferred":[
        "Khari Samnapur"
    ],
    "name:eng_x_variant":[
        "Khari Samn\u0101pur"
    ],
    "wof:name":"Khari Samnapur",
    "wof:placetype":"locality"
},
  "geometry": {"coordinates":[78.00505099999999,23.09709],"type":"Point"}
}