{
  "type": "Feature",
  "properties": {
    "gn:admin1_code":"11",
    "gn:admin2_code":"30.0",
    "gn:asciiname":"Chari",
    "gn:country_code":"IN",
    "gn:dem":1079,
    "gn:feature_class":"P",
    "gn:feature_code":"PPL",
    "gn:name":"Chari",
    "gn:population":0,
    "gn:timezone":"Asia/Kolkata",
    "iso:country":"IN",
    "name:ben_x_preferred":[
        "\u099a\u09be\u09b0\u09bf"
    ],
    "name:ceb_x_preferred":[
        "Chari"
    ],
    "name:fin_x_preferred":[
        "Chari"
    ],
    "name:hin_x_preferred":[
        "\u091a\u0930\u0940"
    ],
    "name:ita_x_preferred":[
        "Chari"
    ],
    "name:urd_x_preferred":[
        "\u0686\u0627\u0631\u06cc"
    ],
    "wof:name":"Chari",
    "wof:placetype":"locality"
},
  "geometry": {"coordinates":[76.7962,31.30917],"type":"Point"}
}