{
  "type": "Feature",
  "properties": {
    "iso:country":"IN",
    "ks:ks_name":"Mancodu",
    "ks:ks_pop":1150,
    "ks:ks_type":"HABITATION",
    "ks:ks_uagg_main":0,
    "name:eng_x_preferred":[
        "Mancodu"
    ],
    "wof:name":"Mancodu",
    "wof:placetype":"neighbourhood",
    "wof:population":1150
},
  "geometry": {"coordinates":[76.89204700000001,9.125088],"type":"Point"}
}