{
  "type": "Feature",
  "properties": {
    "gn:admin1_code":"36.0",
    "gn:admin2_code":"161",
    "gn:asciiname":"Bhadai",
    "gn:country_code":"IN",
    "gn:dem":154,
    "gn:feature_class":"P",
    "gn:feature_code":"PPL",
    "gn:name":"Bhadai",
    "gn:population":0,
    "gn:timezone":"Asia/Kolkata",
    "iso:country":"IN",
    "name:und_x_variant":[
        "Bhadei K\u0101sh\u012bpur"
    ],
    "wof:name":"Bhadai",
    "wof:placetype":"neighbourhood"
},
  "geometry": {"coordinates":[79.03452,26.89946],"type":"Point"}
}