{
  "type": "Feature",
  "properties": {
    "iso:country":"IN",
    "ks:ks_name":"Gharwadi",
    "ks:ks_pop":161,
    "ks:ks_type":"HABITATION",
    "name:eng_x_preferred":[
        "Gharwadi"
    ],
    "wof:name":"Gharwadi",
    "wof:placetype":"locality",
    "wof:population":161
},
  "geometry": {"coordinates":[73.57481300000001,17.585512],"type":"Point"}
}