{
  "type": "Feature",
  "properties": {
    "iso:country":"IN",
    "ks:ks_name":"Khilaguda",
    "ks:ks_pop":304,
    "ks:ks_type":"VILLAGE",
    "name:eng_x_preferred":[
        "Khilaguda"
    ],
    "wof:name":"Khilaguda",
    "wof:placetype":"locality",
    "wof:population":304
},
  "geometry": {"coordinates":[82.36394199999999,18.450133],"type":"Point"}
}