{
  "type": "Feature",
  "properties": {
    "iso:country":"IN",
    "ks:ks_name":"Patalipada",
    "ks:ks_pop":193,
    "ks:ks_type":"HABITATION",
    "name:eng_x_preferred":[
        "Patalipada"
    ],
    "wof:name":"Patalipada",
    "wof:placetype":"locality",
    "wof:population":193
},
  "geometry": {"coordinates":[84.159965,20.687561],"type":"Point"}
}