{
  "type": "Feature",
  "properties": {
    "iso:country":"IN",
    "ks:ks_name":"Inakidu H P",
    "ks:ks_pop":45,
    "ks:ks_type":"HABITATION",
    "name:eng_x_preferred":[
        "Inakidu H P"
    ],
    "wof:name":"Inakidu H P",
    "wof:placetype":"locality",
    "wof:population":45
},
  "geometry": {"coordinates":[75.613162,12.627827],"type":"Point"}
}