{
  "type": "Feature",
  "properties": {
    "iso:country":"IN",
    "ks:ks_alt_nam":"Gharmuha tola",
    "ks:ks_name":"Gharmuha Tola",
    "ks:ks_pop":511,
    "ks:ks_type":"HABITATION",
    "name:eng_x_preferred":[
        "Gharmuha Tola"
    ],
    "wof:name":"Gharmuha Tola",
    "wof:placetype":"locality",
    "wof:population":511
},
  "geometry": {"coordinates":[86.533522,25.788776],"type":"Point"}
}