{
  "type": "Feature",
  "properties": {
    "gn:admin1_code":"36",
    "gn:admin2_code":"201.0",
    "gn:asciiname":"Banwaripur",
    "gn:country_code":"IN",
    "gn:dem":169,
    "gn:feature_class":"P",
    "gn:feature_code":"PPL",
    "gn:name":"Banw\u0101ripur",
    "gn:population":0,
    "gn:timezone":"Asia/Kolkata",
    "iso:country":"IN",
    "name:und_x_variant":[
        "Banw\u0101ripur",
        "Nagla Lukia"
    ],
    "wof:name":"Banwaripur",
    "wof:placetype":"locality"
},
  "geometry": {"coordinates":[78.70624000000002,27.62826],"type":"Point"}
}