{
  "type": "Feature",
  "properties": {
    "gn:admin1_code":"34",
    "gn:admin2_code":"233.0",
    "gn:asciiname":"Narotapur",
    "gn:country_code":"IN",
    "gn:dem":81,
    "gn:feature_class":"P",
    "gn:feature_code":"PPL",
    "gn:name":"Narot\u0101pur",
    "gn:population":0,
    "gn:timezone":"Asia/Kolkata",
    "iso:country":"IN",
    "ks:ks_name":"Narotapur",
    "ks:ks_pop":783,
    "ks:ks_type":"VILLAGE",
    "name:eng_x_preferred":[
        "Narotapur"
    ],
    "wof:name":"Narotapur",
    "wof:placetype":"locality",
    "wof:population":783
},
  "geometry": {"coordinates":[83.518581,25.139259],"type":"Point"}
}