{
  "type": "Feature",
  "properties": {
    "gn:admin1_code":"13.0",
    "gn:admin2_code":"598.0",
    "gn:asciiname":"Tumboli",
    "gn:country_code":"IN",
    "gn:dem":11,
    "gn:feature_class":"P",
    "gn:feature_code":"PPL",
    "gn:name":"Tumboli",
    "gn:population":0,
    "gn:timezone":"Asia/Kolkata",
    "iso:country":"IN",
    "wof:name":"Tumboli",
    "wof:placetype":"locality"
},
  "geometry": {"coordinates":[76.31926999999997,9.51326],"type":"Point"}
}