{
  "type": "Feature",
  "properties": {
    "iso:country":"IN",
    "ks:ks_name":"Pipalya Khurd",
    "ks:ks_pop":165,
    "ks:ks_type":"VILLAGE",
    "name:eng_x_preferred":[
        "Pipalya Khurd"
    ],
    "wof:name":"Pipalya Khurd",
    "wof:placetype":"locality",
    "wof:population":165
},
  "geometry": {"coordinates":[75.151357,22.361154],"type":"Point"}
}