{
  "type": "Feature",
  "properties": {
    "iso:country":"IN",
    "ks:ks_name":"Ben",
    "ks:ks_pop":1142,
    "ks:ks_type":"HABITATION",
    "name:eng_x_preferred":[
        "Ben"
    ],
    "wof:name":"Ben",
    "wof:placetype":"locality",
    "wof:population":1142
},
  "geometry": {"coordinates":[73.89796200000001,23.787827],"type":"Point"}
}