{
  "type": "Feature",
  "properties": {
    "iso:country":"IN",
    "ks:ks_name":"Dateeyar",
    "ks:ks_pop":931,
    "ks:ks_type":"VILLAGE",
    "name:eng_x_preferred":[
        "Dateeyar"
    ],
    "wof:name":"Dateeyar",
    "wof:placetype":"locality",
    "wof:population":931
},
  "geometry": {"coordinates":[74.565724,23.875399],"type":"Point"}
}