{
  "type": "Feature",
  "properties": {
    "gn:admin1_code":"16.0",
    "gn:admin2_code":"497.0",
    "gn:asciiname":"Pada",
    "gn:country_code":"IN",
    "gn:dem":209,
    "gn:feature_class":"P",
    "gn:feature_code":"PPL",
    "gn:name":"P\u0101da",
    "gn:population":0,
    "gn:timezone":"Asia/Kolkata",
    "iso:country":"IN",
    "name:cat_x_preferred":[
        "Pada"
    ],
    "name:ceb_x_preferred":[
        "Pada"
    ],
    "name:nor_x_preferred":[
        "Pada"
    ],
    "name:swe_x_preferred":[
        "Pada"
    ],
    "wof:name":"Pada",
    "wof:placetype":"locality"
},
  "geometry": {"coordinates":[74.02346999999997,21.25952],"type":"Point"}
}