{
  "type": "Feature",
  "properties": {
    "iso:country":"IN",
    "ks:ks_name":"Haurburi",
    "ks:ks_pop":236,
    "ks:ks_type":"VILLAGE",
    "name:eng_x_preferred":[
        "Haurburi"
    ],
    "wof:name":"Haurburi",
    "wof:placetype":"locality",
    "wof:population":236
},
  "geometry": {"coordinates":[87.684414,21.700299],"type":"Point"}
}