{
  "type": "Feature",
  "properties": {
    "iso:country":"IN",
    "ks:ks_name":"Ganagara Gudde",
    "ks:ks_pop":48,
    "ks:ks_type":"HABITATION",
    "name:eng_x_preferred":[
        "Ganagara Gudde"
    ],
    "wof:name":"Ganagara Gudde",
    "wof:placetype":"locality",
    "wof:population":48
},
  "geometry": {"coordinates":[75.980833,12.135556],"type":"Point"}
}