{
  "type": "Feature",
  "properties": {
    "iso:country":"IN",
    "ks:ks_alt_nam":"Marchanda C.P.Estate",
    "ks:ks_name":"Marchanda C.p.estate",
    "ks:ks_pop":62,
    "ks:ks_type":"HABITATION",
    "name:eng_x_preferred":[
        "Marchanda C.p.estate"
    ],
    "wof:name":"Marchanda C.p.estate",
    "wof:placetype":"locality",
    "wof:population":62
},
  "geometry": {"coordinates":[75.679722,12.225278],"type":"Point"}
}