{
  "type": "Feature",
  "properties": {
    "iso:country":"IN",
    "ks:ks_name":"Kaharia",
    "ks:ks_pop":1509,
    "ks:ks_type":"VILLAGE",
    "name:eng_x_preferred":[
        "Kaharia"
    ],
    "wof:name":"Kaharia",
    "wof:placetype":"locality",
    "wof:population":1509
},
  "geometry": {"coordinates":[85.829464,26.212464],"type":"Point"}
}