{
  "type": "Feature",
  "properties": {
    "iso:country":"IN",
    "ks:ks_alt_nam":"Kakr\u0101la",
    "ks:ks_name":"Kakrala",
    "ks:ks_type":"VILLAGE",
    "ks:ks_uagg_main":0,
    "name:eng_x_preferred":[
        "Kakrala"
    ],
    "name:eng_x_variant":[
        "Kakr\u0101la"
    ],
    "wof:name":"Kakrala",
    "wof:placetype":"neighbourhood"
},
  "geometry": {"coordinates":[77.411787,28.550566],"type":"Point"}
}