{
  "type": "Feature",
  "properties": {
    "gn:admin1_code":"35.0",
    "gn:admin2_code":"455",
    "gn:asciiname":"Ankhawari",
    "gn:country_code":"IN",
    "gn:dem":761,
    "gn:feature_class":"P",
    "gn:feature_code":"PPL",
    "gn:name":"Ankh\u0101w\u0101ri",
    "gn:population":0,
    "gn:timezone":"Asia/Kolkata",
    "iso:country":"IN",
    "ks:ks_name":"Ankhawadi",
    "ks:ks_pop":761,
    "ks:ks_type":"VILLAGE",
    "name:eng_x_preferred":[
        "Ankhawadi"
    ],
    "name:eng_x_variant":[
        "Ankhawari"
    ],
    "wof:name":"Ankhawadi",
    "wof:placetype":"locality",
    "wof:population":761
},
  "geometry": {"coordinates":[78.852372,22.494816],"type":"Point"}
}