{
  "type": "Feature",
  "properties": {
    "gn:admin1_code":"35.0",
    "gn:admin2_code":"455",
    "gn:asciiname":"Ankhawari",
    "gn:country_code":"IN",
    "gn:dem":761,
    "gn:feature_class":"P",
    "gn:feature_code":"PPL",
    "gn:name":"Ankh\u0101w\u0101ri",
    "gn:population":0,
    "gn:timezone":"Asia/Kolkata",
    "iso:country":"IN",
    "wof:name":"Ankhawari",
    "wof:placetype":"locality"
},
  "geometry": {"coordinates":[78.84793000000001,22.48684],"type":"Point"}
}