{
  "type": "Feature",
  "properties": {
    "iso:country":"IN",
    "ks:ks_alt_nam":"Kanchavaram thanda",
    "ks:ks_name":"Kanchavaram Thanda",
    "ks:ks_pop":93,
    "ks:ks_type":"HABITATION",
    "ks:ks_uagg_main":0,
    "name:eng_x_preferred":[
        "Kanchavaram Thanda"
    ],
    "wof:name":"Kanchavaram Thanda",
    "wof:placetype":"neighbourhood",
    "wof:population":93
},
  "geometry": {"coordinates":[78.672121,16.862038],"type":"Point"}
}