{
  "type": "Feature",
  "properties": {
    "iso:country":"IN",
    "ks:ks_name":"Kondawadi",
    "ks:ks_pop":170,
    "ks:ks_type":"HABITATION",
    "name:eng_x_preferred":[
        "Kondawadi"
    ],
    "wof:name":"Kondawadi",
    "wof:placetype":"locality",
    "wof:population":170
},
  "geometry": {"coordinates":[73.35440800000001,17.578214],"type":"Point"}
}