{
  "type": "Feature",
  "properties": {
    "gn:admin1_code":"19",
    "gn:admin2_code":"580.0",
    "gn:asciiname":"Hadanur",
    "gn:country_code":"IN",
    "gn:dem":459,
    "gn:feature_class":"P",
    "gn:feature_code":"PPL",
    "gn:name":"Hadan\u016br",
    "gn:population":0,
    "gn:timezone":"Asia/Kolkata",
    "iso:country":"IN",
    "wof:name":"Hadanur",
    "wof:placetype":"neighbourhood"
},
  "geometry": {"coordinates":[76.54003,16.73491],"type":"Point"}
}