{
  "type": "Feature",
  "properties": {
    "iso:country":"IN",
    "ks:ks_name":"Rupshi Pt.iii",
    "ks:ks_pop":701,
    "ks:ks_type":"VILLAGE",
    "name:eng_x_preferred":[
        "Rupshi Pt.iii"
    ],
    "wof:name":"Rupshi Pt.iii",
    "wof:placetype":"locality",
    "wof:population":701
},
  "geometry": {"coordinates":[89.918435,26.138551],"type":"Point"}
}