{
  "type": "Feature",
  "properties": {
    "gn:admin1_code":"10.0",
    "gn:admin2_code":"87.0",
    "gn:asciiname":"Subasheri",
    "gn:country_code":"IN",
    "gn:dem":267,
    "gn:feature_class":"P",
    "gn:feature_code":"PPL",
    "gn:name":"Sub\u0101sheri",
    "gn:population":0,
    "gn:timezone":"Asia/Kolkata",
    "iso:country":"IN",
    "wof:name":"Subasheri",
    "wof:placetype":"locality"
},
  "geometry": {"coordinates":[76.90698,28.17885],"type":"Point"}
}