{
  "type": "Feature",
  "properties": {
    "iso:country":"IN",
    "ks:ks_name":"Bandipara",
    "ks:ks_pop":121,
    "ks:ks_type":"HABITATION",
    "name:eng_x_preferred":[
        "Bandipara"
    ],
    "wof:name":"Bandipara",
    "wof:placetype":"locality",
    "wof:population":121
},
  "geometry": {"coordinates":[81.295242,18.494603],"type":"Point"}
}