{
  "type": "Feature",
  "properties": {
    "iso:country":"IN",
    "ks:ks_name":"Hirpur Ganura",
    "ks:ks_pop":859,
    "ks:ks_type":"VILLAGE",
    "name:eng_x_preferred":[
        "Hirpur Ganura"
    ],
    "wof:name":"Hirpur Ganura",
    "wof:placetype":"locality",
    "wof:population":859
},
  "geometry": {"coordinates":[76.40027000000001,31.206998],"type":"Point"}
}