{
  "type": "Feature",
  "properties": {
    "iso:country":"IN",
    "ks:ks_name":"Barahi Purwa",
    "ks:ks_pop":100,
    "ks:ks_type":"HABITATION",
    "name:eng_x_preferred":[
        "Barahi Purwa"
    ],
    "wof:name":"Barahi Purwa",
    "wof:placetype":"locality",
    "wof:population":100
},
  "geometry": {"coordinates":[81.847795,27.036113],"type":"Point"}
}