{
  "type": "Feature",
  "properties": {
    "gn:admin1_code":"37.0",
    "gn:admin2_code":"409.0",
    "gn:asciiname":"Biranpur",
    "gn:country_code":"IN",
    "gn:dem":312,
    "gn:feature_class":"P",
    "gn:feature_code":"PPL",
    "gn:name":"B\u012branpur",
    "gn:population":0,
    "gn:timezone":"Asia/Kolkata",
    "iso:country":"IN",
    "name:eng_x_preferred":[
        "B\u012branpur"
    ],
    "wof:name":"Biranpur",
    "wof:placetype":"locality"
},
  "geometry": {"coordinates":[81.19298000000001,21.70003],"type":"Point"}
}