{
  "type": "Feature",
  "properties": {
    "iso:country":"IN",
    "ks:ks_name":"Lewatand",
    "ks:ks_pop":602,
    "ks:ks_type":"HABITATION",
    "name:eng_x_preferred":[
        "Lewatand"
    ],
    "wof:name":"Lewatand",
    "wof:placetype":"locality",
    "wof:population":602
},
  "geometry": {"coordinates":[85.758813,23.594013],"type":"Point"}
}