{
  "type": "Feature",
  "properties": {
    "gn:admin1_code":"13.0",
    "gn:admin2_code":"595.0",
    "gn:asciiname":"Kolenchery",
    "gn:country_code":"IN",
    "gn:dem":34,
    "gn:feature_class":"P",
    "gn:feature_code":"PPL",
    "gn:name":"Kolenchery",
    "gn:population":0,
    "gn:timezone":"Asia/Kolkata",
    "iso:country":"IN",
    "ks:ks_name":"Kolenchery",
    "ks:ks_pop":1603,
    "ks:ks_type":"HABITATION",
    "name:eng_x_preferred":[
        "Kolenchery"
    ],
    "name:mal_x_preferred":[
        "\u0d15\u0d4b\u0d32\u0d1e\u0d4d\u0d1a\u0d47\u0d30\u0d3f"
    ],
    "wof:name":"Kolenchery",
    "wof:placetype":"locality",
    "wof:population":1603
},
  "geometry": {"coordinates":[76.47621100000001,9.981976],"type":"Point"}
}