{
  "type": "Feature",
  "properties": {
    "iso:country":"IN",
    "ks:ks_alt_nam":"dhangarwada",
    "ks:ks_name":"Dhangarwada",
    "ks:ks_pop":200,
    "ks:ks_type":"HABITATION",
    "ks:ks_uagg_main":0,
    "name:eng_x_preferred":[
        "Dhangarwada"
    ],
    "wof:name":"Dhangarwada",
    "wof:placetype":"neighbourhood",
    "wof:population":200
},
  "geometry": {"coordinates":[74.16211699999999,15.988522],"type":"Point"}
}