{
  "type": "Feature",
  "properties": {
    "gn:admin1_code":"35.0",
    "gn:admin2_code":"431.0",
    "gn:asciiname":"Aganhuri",
    "gn:country_code":"IN",
    "gn:dem":529,
    "gn:feature_class":"P",
    "gn:feature_code":"PPL",
    "gn:name":"Aganhuri",
    "gn:population":0,
    "gn:timezone":"Asia/Kolkata",
    "iso:country":"IN",
    "wof:name":"Aganhuri",
    "wof:placetype":"locality"
},
  "geometry": {"coordinates":[80.84186,23.46117000000001],"type":"Point"}
}