{
  "type": "Feature",
  "properties": {
    "gn:admin1_code":"35.0",
    "gn:admin2_code":"463.0",
    "gn:asciiname":"Baghari",
    "gn:country_code":"IN",
    "gn:dem":330,
    "gn:feature_class":"P",
    "gn:feature_code":"PPL",
    "gn:name":"Baghari",
    "gn:population":0,
    "gn:timezone":"Asia/Kolkata",
    "iso:country":"IN",
    "wof:name":"Baghari",
    "wof:placetype":"locality"
},
  "geometry": {"coordinates":[82.71956999999998,24.32061],"type":"Point"}
}