{
  "type": "Feature",
  "properties": {
    "gn:admin1_code":"36.0",
    "gn:admin2_code":"161",
    "gn:asciiname":"Phuphai",
    "gn:country_code":"IN",
    "gn:dem":152,
    "gn:feature_class":"P",
    "gn:feature_code":"PPL",
    "gn:name":"Phuphai",
    "gn:population":0,
    "gn:timezone":"Asia/Kolkata",
    "iso:country":"IN",
    "name:und_x_variant":[
        "Ph\u016bphal"
    ],
    "wof:name":"Phuphai",
    "wof:placetype":"locality"
},
  "geometry": {"coordinates":[79.08140999999998,26.75568],"type":"Point"}
}