{
  "type": "Feature",
  "properties": {
    "iso:country":"IN",
    "ks:ks_name":"Hembru",
    "ks:ks_pop":200,
    "ks:ks_type":"VILLAGE",
    "name:eng_x_preferred":[
        "Hembru"
    ],
    "wof:name":"Hembru",
    "wof:placetype":"locality",
    "wof:population":200
},
  "geometry": {"coordinates":[83.613542,19.576981],"type":"Point"}
}