{
  "type": "Feature",
  "properties": {
    "iso:country":"IN",
    "ks:ks_alt_nam":"S.S.Puram",
    "ks:ks_name":"S.s.puram",
    "ks:ks_pop":126,
    "ks:ks_type":"HABITATION",
    "name:eng_x_preferred":[
        "S.s.puram"
    ],
    "wof:name":"S.s.puram",
    "wof:placetype":"locality",
    "wof:population":126
},
  "geometry": {"coordinates":[77.642529,9.838314],"type":"Point"}
}