{
  "type": "Feature",
  "properties": {
    "gn:admin1_code":"39.0",
    "gn:admin2_code":"64.0",
    "gn:asciiname":"Sarson",
    "gn:country_code":"IN",
    "gn:dem":1422,
    "gn:feature_class":"P",
    "gn:feature_code":"PPL",
    "gn:name":"Sarson",
    "gn:population":0,
    "gn:timezone":"Asia/Kolkata",
    "iso:country":"IN",
    "ks:ks_name":"Sarso",
    "ks:ks_pop":1329,
    "ks:ks_type":"VILLAGE",
    "ks:ks_uagg_main":0,
    "name:eng_x_preferred":[
        "Sarso"
    ],
    "wof:name":"Sarso",
    "wof:placetype":"neighbourhood",
    "wof:population":1329
},
  "geometry": {"coordinates":[79.66136299999999,29.592675],"type":"Point"}
}