{
  "type": "Feature",
  "properties": {
    "iso:country":"IN",
    "ks:ks_alt_nam":"ChankiBigha",
    "ks:ks_name":"Chankibigha",
    "ks:ks_pop":294,
    "ks:ks_type":"HABITATION",
    "name:eng_x_preferred":[
        "Chankibigha"
    ],
    "wof:name":"Chankibigha",
    "wof:placetype":"locality",
    "wof:population":294
},
  "geometry": {"coordinates":[84.74570199999999,24.907539],"type":"Point"}
}