{
  "type": "Feature",
  "properties": {
    "gn:admin1_code":"37",
    "gn:admin2_code":"412.0",
    "gn:asciiname":"Bakori",
    "gn:country_code":"IN",
    "gn:dem":328,
    "gn:feature_class":"P",
    "gn:feature_code":"PPL",
    "gn:name":"Bakori",
    "gn:population":0,
    "gn:timezone":"Asia/Kolkata",
    "iso:country":"IN",
    "name:ceb_x_preferred":[
        "Bakori"
    ],
    "name:fra_x_preferred":[
        "Bakori"
    ],
    "name:hau_x_preferred":[
        "Bakori"
    ],
    "name:ita_x_preferred":[
        "Bakori"
    ],
    "name:spa_x_preferred":[
        "Bakori"
    ],
    "wof:name":"Bakori",
    "wof:placetype":"locality"
},
  "geometry": {"coordinates":[81.86239,20.70163],"type":"Point"}
}