{
  "type": "Feature",
  "properties": {
    "gn:admin1_code":"2.0",
    "gn:admin2_code":"542.0",
    "gn:asciiname":"Pubbada",
    "gn:country_code":"IN",
    "gn:dem":497,
    "gn:feature_class":"P",
    "gn:feature_code":"PPL",
    "gn:name":"Pubb\u0101da",
    "gn:population":0,
    "gn:timezone":"Asia/Kolkata",
    "iso:country":"IN",
    "ks:ks_alt_nam":"Pubb\u0101da",
    "ks:ks_name":"Pubbada",
    "ks:ks_pop":267,
    "ks:ks_type":"VILLAGE",
    "name:eng_x_preferred":[
        "Pubbada"
    ],
    "name:eng_x_variant":[
        "Pubb\u0101da"
    ],
    "wof:name":"Pubbada",
    "wof:placetype":"locality",
    "wof:population":267
},
  "geometry": {"coordinates":[83.72668899999999,18.73089],"type":"Point"}
}