{
  "type": "Feature",
  "properties": {
    "iso:country":"IN",
    "ks:ks_name":"Devalayakoppa",
    "ks:ks_pop":24,
    "ks:ks_type":"HABITATION",
    "name:eng_x_preferred":[
        "Devalayakoppa"
    ],
    "wof:name":"Devalayakoppa",
    "wof:placetype":"locality",
    "wof:population":24
},
  "geometry": {"coordinates":[75.265773,13.479316],"type":"Point"}
}