{
  "type": "Feature",
  "properties": {
    "gn:country":"IN",
    "gn:fcode":"PPL",
    "gn:pop":0,
    "iso:country":"IN",
    "name:eng_x_preferred":[
        "Ramagondanahalli"
    ],
    "qs:name":"Ramagondanahalli",
    "qs:name_adm0":"India",
    "qs:name_adm1":"Karnataka",
    "qs:photos":228,
    "qs:photos_1k":46,
    "qs:photos_9k":1,
    "qs:photos_9r":4,
    "qs:photos_all":228,
    "qs:photos_sr":4,
    "qs:placetype":"Town",
    "qs:pop_sr":"0",
    "wd:wordcount":185,
    "wof:name":"Ramagondanahalli",
    "wof:placetype":"locality",
    "wof:population":0
},
  "geometry": {"coordinates":[77.6245,13.01861],"type":"Point"}
}