{
  "type": "Feature",
  "properties": {
    "iso:country":"IN",
    "ks:ks_alt_nam":"janusilusipur",
    "ks:ks_name":"Janusilusipur",
    "ks:ks_pop":158,
    "ks:ks_type":"HABITATION",
    "name:eng_x_preferred":[
        "Janusilusipur"
    ],
    "wof:name":"Janusilusipur",
    "wof:placetype":"locality",
    "wof:population":158
},
  "geometry": {"coordinates":[85.958535,21.017061],"type":"Point"}
}