{
  "type": "Feature",
  "properties": {
    "iso:country":"IN",
    "ks:ks_alt_nam":"Murkat\u012b",
    "ks:ks_name":"Murkati",
    "ks:ks_type":"VILLAGE",
    "name:eng_x_preferred":[
        "Murkati"
    ],
    "name:eng_x_variant":[
        "Murkat\u012b"
    ],
    "wof:name":"Murkati",
    "wof:placetype":"locality"
},
  "geometry": {"coordinates":[82.190112,25.286223],"type":"Point"}
}