{
  "type": "Feature",
  "properties": {
    "iso:country":"IN",
    "ks:ks_name":"Kottadamane",
    "ks:ks_pop":42,
    "ks:ks_type":"HABITATION",
    "name:eng_x_preferred":[
        "Kottadamane"
    ],
    "wof:name":"Kottadamane",
    "wof:placetype":"locality",
    "wof:population":42
},
  "geometry": {"coordinates":[75.377747,13.655261],"type":"Point"}
}