{
  "type": "Feature",
  "properties": {
    "iso:country":"IN",
    "ks:ks_name":"Lesariwala",
    "ks:ks_pop":1972,
    "ks:ks_type":"VILLAGE",
    "name:eng_x_preferred":[
        "Lesariwala"
    ],
    "wof:name":"Lesariwala",
    "wof:placetype":"locality",
    "wof:population":1972
},
  "geometry": {"coordinates":[75.663594,31.424461],"type":"Point"}
}