{
  "type": "Feature",
  "properties": {
    "iso:country":"IN",
    "ks:ks_name":"Mugalpura",
    "ks:ks_pop":467,
    "ks:ks_type":"HABITATION",
    "name:eng_x_preferred":[
        "Mugalpura"
    ],
    "wof:name":"Mugalpura",
    "wof:placetype":"locality",
    "wof:population":467
},
  "geometry": {"coordinates":[77.689931,26.557352],"type":"Point"}
}