{
  "type": "Feature",
  "properties": {
    "gn:admin1_code":"36.0",
    "gn:admin2_code":"139.0",
    "gn:asciiname":"Binahpur",
    "gn:country_code":"IN",
    "gn:dem":220,
    "gn:feature_class":"P",
    "gn:feature_code":"PPL",
    "gn:name":"B\u012bnahpur",
    "gn:population":0,
    "gn:timezone":"Asia/Kolkata",
    "iso:country":"IN",
    "wof:name":"Binahpur",
    "wof:placetype":"neighbourhood"
},
  "geometry": {"coordinates":[77.35126,28.81757],"type":"Point"}
}