{
  "type": "Feature",
  "properties": {
    "iso:country":"IN",
    "ks:ks_name":"Relakunta",
    "ks:ks_pop":1919,
    "ks:ks_type":"VILLAGE",
    "ks:ks_uagg_main":0,
    "name:eng_x_preferred":[
        "Relakunta"
    ],
    "wof:name":"Relakunta",
    "wof:placetype":"neighbourhood",
    "wof:population":1919
},
  "geometry": {"coordinates":[79.82004999999999,18.077983],"type":"Point"}
}