{
  "type": "Feature",
  "properties": {
    "iso:country":"IN",
    "ks:ks_alt_nam":"YADAVA BASTI",
    "ks:ks_name":"Yadava Basti",
    "ks:ks_pop":167,
    "ks:ks_type":"HABITATION",
    "ks:ks_uagg_main":0,
    "name:eng_x_preferred":[
        "Yadava Basti"
    ],
    "wof:name":"Yadava Basti",
    "wof:placetype":"neighbourhood",
    "wof:population":167
},
  "geometry": {"coordinates":[82.09292499999999,25.5238],"type":"Point"}
}