{
  "type": "Feature",
  "properties": {
    "iso:country":"IN",
    "ks:ks_alt_nam":"Th\u0101ndi\u0101n",
    "ks:ks_name":"Thandian",
    "ks:ks_type":"VILLAGE",
    "name:eng_x_preferred":[
        "Thandian"
    ],
    "name:eng_x_variant":[
        "Th\u0101ndi\u0101n"
    ],
    "wof:name":"Thandian",
    "wof:placetype":"neighbourhood"
},
  "geometry": {"coordinates":[76.021963,31.181363],"type":"Point"}
}