{
  "type": "Feature",
  "properties": {
    "iso:country":"IN",
    "ks:ks_name":"Potharajugaripalli",
    "ks:ks_pop":63,
    "ks:ks_type":"HABITATION",
    "name:eng_x_preferred":[
        "Potharajugaripalli"
    ],
    "wof:name":"Potharajugaripalli",
    "wof:placetype":"locality",
    "wof:population":63
},
  "geometry": {"coordinates":[78.930125,14.19524],"type":"Point"}
}