{
  "type": "Feature",
  "properties": {
    "gn:admin1_code":"38",
    "gn:admin2_code":"362.0",
    "gn:asciiname":"Sareya",
    "gn:country_code":"IN",
    "gn:dem":206,
    "gn:feature_class":"P",
    "gn:feature_code":"PPL",
    "gn:name":"Sareya",
    "gn:population":0,
    "gn:timezone":"Asia/Kolkata",
    "iso:country":"IN",
    "wof:name":"Sareya",
    "wof:placetype":"neighbourhood"
},
  "geometry": {"coordinates":[87.01982,24.57117],"type":"Point"}
}