{
  "type": "Feature",
  "properties": {
    "iso:country":"IN",
    "ks:ks_name":"Panalu",
    "ks:ks_pop":172,
    "ks:ks_type":"HABITATION",
    "name:eng_x_preferred":[
        "Panalu"
    ],
    "wof:name":"Panalu",
    "wof:placetype":"locality",
    "wof:population":172
},
  "geometry": {"coordinates":[75.151741,13.096867],"type":"Point"}
}