{
  "type": "Feature",
  "properties": {
    "iso:country":"IN",
    "ks:ks_name":"Shejavali",
    "ks:ks_pop":564,
    "ks:ks_type":"VILLAGE",
    "name:eng_x_preferred":[
        "Shejavali"
    ],
    "wof:name":"Shejavali",
    "wof:placetype":"locality",
    "wof:population":564
},
  "geometry": {"coordinates":[73.602368,16.552231],"type":"Point"}
}