{
  "type": "Feature",
  "properties": {
    "gn:admin1_code":"11",
    "gn:admin2_code":"24.0",
    "gn:asciiname":"Ghati Bilwari",
    "gn:country_code":"IN",
    "gn:dem":412,
    "gn:feature_class":"P",
    "gn:feature_code":"PPL",
    "gn:name":"Gh\u0101ti Bilw\u0101ri",
    "gn:population":0,
    "gn:timezone":"Asia/Kolkata",
    "iso:country":"IN",
    "wof:name":"Ghati Bilwari",
    "wof:placetype":"locality"
},
  "geometry": {"coordinates":[75.93784000000002,31.93995],"type":"Point"}
}