{
  "type": "Feature",
  "properties": {
    "iso:country":"IN",
    "ks:ks_alt_nam":"DEEN KA PURVA",
    "ks:ks_name":"Deen Ka Purva",
    "ks:ks_pop":1010,
    "ks:ks_type":"HABITATION",
    "name:eng_x_preferred":[
        "Deen Ka Purva"
    ],
    "wof:name":"Deen Ka Purva",
    "wof:placetype":"locality",
    "wof:population":1010
},
  "geometry": {"coordinates":[81.79414800000001,26.108208],"type":"Point"}
}