{
  "type": "Feature",
  "properties": {
    "gn:admin1_code":"12.0",
    "gn:admin2_code":"1.0",
    "gn:asciiname":"Gattiali Forest",
    "gn:country_code":"IN",
    "gn:dem":1899,
    "gn:feature_class":"P",
    "gn:feature_code":"PPL",
    "gn:name":"Gatti\u0101li Forest",
    "gn:population":0,
    "gn:timezone":"Asia/Kolkata",
    "iso:country":"IN",
    "wof:name":"Gattiali Forest",
    "wof:placetype":"locality"
},
  "geometry": {"coordinates":[74.41223000000002,34.55168],"type":"Point"}
}