{
  "type": "Feature",
  "properties": {
    "iso:country":"IN",
    "ks:ks_name":"Ghasibara",
    "ks:ks_pop":538,
    "ks:ks_type":"VILLAGE",
    "name:eng_x_preferred":[
        "Ghasibara"
    ],
    "wof:name":"Ghasibara",
    "wof:placetype":"locality",
    "wof:population":538
},
  "geometry": {"coordinates":[86.099234,20.830453],"type":"Point"}
}