{
  "type": "Feature",
  "properties": {
    "iso:country":"IN",
    "ks:ks_name":"Pat Gaon Malla",
    "ks:ks_pop":178,
    "ks:ks_type":"VILLAGE",
    "name:eng_x_preferred":[
        "Pat Gaon Malla"
    ],
    "wof:name":"Pat Gaon Malla",
    "wof:placetype":"locality",
    "wof:population":178
},
  "geometry": {"coordinates":[79.062922,29.740303],"type":"Point"}
}