{
  "type": "Feature",
  "properties": {
    "gn:admin1_code":"12",
    "gn:admin2_code":"10.0",
    "gn:asciiname":"Pharao",
    "gn:country_code":"IN",
    "gn:dem":2095,
    "gn:feature_class":"P",
    "gn:feature_code":"PPL",
    "gn:name":"Ph\u0101r\u0101o",
    "gn:population":0,
    "gn:timezone":"Asia/Kolkata",
    "iso:country":"IN",
    "name:bul_x_preferred":[
        "\u0424\u0430\u0440\u0430\u043e"
    ],
    "name:deu_x_preferred":[
        "Pharao"
    ],
    "name:fin_x_preferred":[
        "Pharao"
    ],
    "name:fra_x_preferred":[
        "Pharao"
    ],
    "name:hun_x_preferred":[
        "Pharao"
    ],
    "name:pol_x_preferred":[
        "Pharao"
    ],
    "name:rus_x_preferred":[
        "Pharao"
    ],
    "name:swe_x_preferred":[
        "Pharao"
    ],
    "name:ukr_x_preferred":[
        "Pharao"
    ],
    "wof:name":"Pharao",
    "wof:placetype":"locality"
},
  "geometry": {"coordinates":[75.06166,34.2452],"type":"Point"}
}