{
  "type": "Feature",
  "properties": {
    "iso:country":"IN",
    "ks:ks_name":"Bhouwapur Khurd",
    "ks:ks_pop":664,
    "ks:ks_type":"HABITATION",
    "name:eng_x_preferred":[
        "Bhouwapur Khurd"
    ],
    "wof:name":"Bhouwapur Khurd",
    "wof:placetype":"locality",
    "wof:population":664
},
  "geometry": {"coordinates":[81.065219,27.991157],"type":"Point"}
}