{
  "type": "Feature",
  "properties": {
    "iso:country":"IN",
    "ks:ks_alt_nam":"M\u0101lni",
    "ks:ks_name":"Malni",
    "ks:ks_type":"VILLAGE",
    "name:eng_x_preferred":[
        "Malni"
    ],
    "name:eng_x_variant":[
        "M\u0101lni"
    ],
    "wof:name":"Malni",
    "wof:placetype":"locality"
},
  "geometry": {"coordinates":[78.64561399999999,28.604159],"type":"Point"}
}