{
  "type": "Feature",
  "properties": {
    "iso:country":"IN",
    "ks:ks_alt_nam":"Bagavathikavu st colony",
    "ks:ks_name":"Bagavathikavu St Colony",
    "ks:ks_pop":718,
    "ks:ks_type":"HABITATION",
    "name:eng_x_preferred":[
        "Bagavathikavu St Colony"
    ],
    "wof:name":"Bagavathikavu St Colony",
    "wof:placetype":"locality",
    "wof:population":718
},
  "geometry": {"coordinates":[76.025733,11.297892],"type":"Point"}
}