{
  "type": "Feature",
  "properties": {
    "iso:country":"IN",
    "ks:ks_name":"Polkhand",
    "ks:ks_pop":38,
    "ks:ks_type":"HABITATION",
    "name:eng_x_preferred":[
        "Polkhand"
    ],
    "wof:name":"Polkhand",
    "wof:placetype":"locality",
    "wof:population":38
},
  "geometry": {"coordinates":[78.58084599999999,30.297408],"type":"Point"}
}