{
  "type": "Feature",
  "properties": {
    "iso:country":"IN",
    "ks:ks_name":"Teju Tola",
    "ks:ks_pop":600,
    "ks:ks_type":"HABITATION",
    "name:eng_x_preferred":[
        "Teju Tola"
    ],
    "wof:name":"Teju Tola",
    "wof:placetype":"locality",
    "wof:population":600
},
  "geometry": {"coordinates":[84.285006,26.731119],"type":"Point"}
}