{
  "type": "Feature",
  "properties": {
    "iso:country":"IN",
    "ks:ks_name":"Kalidaha",
    "ks:ks_pop":1232,
    "ks:ks_type":"HABITATION",
    "ks:ks_uagg_main":0,
    "name:eng_x_preferred":[
        "Kalidaha"
    ],
    "wof:name":"Kalidaha",
    "wof:placetype":"neighbourhood",
    "wof:population":1232
},
  "geometry": {"coordinates":[88.459328,23.986863],"type":"Point"}
}