{
  "type": "Feature",
  "properties": {
    "iso:country":"IN",
    "ks:ks_name":"Aivaphai",
    "ks:ks_pop":144,
    "ks:ks_type":"HABITATION",
    "ks:ks_uagg_main":0,
    "name:eng_x_preferred":[
        "Aivaphai"
    ],
    "wof:name":"Aivaphai",
    "wof:placetype":"neighbourhood",
    "wof:population":144
},
  "geometry": {"coordinates":[92.79892100000001,25.100439],"type":"Point"}
}