{
  "type": "Feature",
  "properties": {
    "iso:country":"IN",
    "ks:ks_name":"Ramgarh",
    "ks:ks_pop":1514,
    "ks:ks_type":"HABITATION",
    "name:eng_x_preferred":[
        "Ramgarh"
    ],
    "name:hin_x_preferred":[
        "\u0930\u093e\u092e\u0917\u0922\u093c"
    ],
    "wof:name":"Ramgarh",
    "wof:placetype":"locality",
    "wof:population":1514
},
  "geometry": {"coordinates":[81.722915,24.343584],"type":"Point"}
}