{
  "type": "Feature",
  "properties": {
    "iso:country":"IN",
    "ks:ks_name":"Majhi Para",
    "ks:ks_pop":743,
    "ks:ks_type":"HABITATION",
    "name:eng_x_preferred":[
        "Majhi Para"
    ],
    "wof:name":"Majhi Para",
    "wof:placetype":"locality",
    "wof:population":743
},
  "geometry": {"coordinates":[88.740595,22.286342],"type":"Point"}
}