{
  "type": "Feature",
  "properties": {
    "iso:country":"IN",
    "ks:ks_name":"Madi",
    "ks:ks_pop":142,
    "ks:ks_type":"VILLAGE",
    "name:eng_x_preferred":[
        "Madi"
    ],
    "wof:name":"Madi",
    "wof:placetype":"locality",
    "wof:population":142
},
  "geometry": {"coordinates":[77.486335,25.199526],"type":"Point"}
}