{
  "type": "Feature",
  "properties": {
    "iso:country":"IN",
    "ks:ks_name":"Bellamane",
    "ks:ks_pop":38,
    "ks:ks_type":"HABITATION",
    "name:eng_x_preferred":[
        "Bellamane"
    ],
    "wof:name":"Bellamane",
    "wof:placetype":"locality",
    "wof:population":38
},
  "geometry": {"coordinates":[74.754345,14.469768],"type":"Point"}
}