{
  "type": "Feature",
  "properties": {
    "iso:country":"IN",
    "ks:ks_alt_nam":"CHORPARA",
    "ks:ks_name":"Chorpara",
    "ks:ks_pop":158,
    "ks:ks_type":"HABITATION",
    "name:eng_x_preferred":[
        "Chorpara"
    ],
    "wof:name":"Chorpara",
    "wof:placetype":"locality",
    "wof:population":158
},
  "geometry": {"coordinates":[82.082534,22.548211],"type":"Point"}
}