{
  "type": "Feature",
  "properties": {
    "iso:country":"IN",
    "ks:ks_alt_nam":"MARUGUTU",
    "ks:ks_name":"Marugutu",
    "ks:ks_pop":219,
    "ks:ks_type":"HABITATION",
    "name:eng_x_preferred":[
        "Marugutu"
    ],
    "wof:name":"Marugutu",
    "wof:placetype":"locality",
    "wof:population":219
},
  "geometry": {"coordinates":[85.92077500000001,22.410189],"type":"Point"}
}