{
  "type": "Feature",
  "properties": {
    "gn:admin1_code":"25.0",
    "gn:admin2_code":"631.0",
    "gn:asciiname":"Konapalli",
    "gn:country_code":"IN",
    "gn:dem":728,
    "gn:feature_class":"P",
    "gn:feature_code":"PPL",
    "gn:name":"K\u014dnapalli",
    "gn:population":0,
    "gn:timezone":"Asia/Kolkata",
    "iso:country":"IN",
    "wof:name":"Konapalli",
    "wof:placetype":"neighbourhood"
},
  "geometry": {"coordinates":[77.9851,12.54845],"type":"Point"}
}