{
  "type": "Feature",
  "properties": {
    "gn:admin1_code":"36",
    "gn:admin2_code":"160.0",
    "gn:asciiname":"Barai",
    "gn:country_code":"IN",
    "gn:dem":146,
    "gn:feature_class":"P",
    "gn:feature_code":"PPL",
    "gn:name":"Barai",
    "gn:population":0,
    "gn:timezone":"Asia/Kolkata",
    "iso:country":"IN",
    "name:ceb_x_preferred":[
        "Barai"
    ],
    "name:ita_x_preferred":[
        "Barai"
    ],
    "name:mai_x_preferred":[
        "\u092c\u0930\u094d\u0930\u0947"
    ],
    "name:msa_x_preferred":[
        "Barai"
    ],
    "name:pol_x_preferred":[
        "Barai"
    ],
    "wof:name":"Barai",
    "wof:placetype":"locality"
},
  "geometry": {"coordinates":[79.63114,27.00513],"type":"Point"}
}