{
  "type": "Feature",
  "properties": {
    "iso:country":"IN",
    "ks:ks_alt_nam":"Seethyanaik thanda",
    "ks:ks_name":"Seethyanaik Thanda",
    "ks:ks_pop":109,
    "ks:ks_type":"HABITATION",
    "name:eng_x_preferred":[
        "Seethyanaik Thanda"
    ],
    "wof:name":"Seethyanaik Thanda",
    "wof:placetype":"locality",
    "wof:population":109
},
  "geometry": {"coordinates":[77.747362,17.107828],"type":"Point"}
}