{
  "type": "Feature",
  "properties": {
    "gn:admin1_code":"36",
    "gn:admin2_code":"163.0",
    "gn:asciiname":"Surajpura",
    "gn:country_code":"IN",
    "gn:dem":133,
    "gn:feature_class":"P",
    "gn:feature_code":"PPL",
    "gn:name":"S\u016brajpura",
    "gn:population":0,
    "gn:timezone":"Asia/Kolkata",
    "iso:country":"IN",
    "name:und_x_variant":[
        "S\u016brajpura",
        "Himmath\u0101r"
    ],
    "wof:name":"Surajpura",
    "wof:placetype":"locality"
},
  "geometry": {"coordinates":[79.86575000000001,26.28421],"type":"Point"}
}