{
  "type": "Feature",
  "properties": {
    "iso:country":"IN",
    "ks:ks_name":"Gaji Gudana",
    "ks:ks_pop":420,
    "ks:ks_type":"VILLAGE",
    "name:eng_x_preferred":[
        "Gaji Gudana"
    ],
    "wof:name":"Gaji Gudana",
    "wof:placetype":"locality",
    "wof:population":420
},
  "geometry": {"coordinates":[75.35963700000001,31.497125],"type":"Point"}
}