{
  "type": "Feature",
  "properties": {
    "gn:admin1_code":"36.0",
    "gn:admin2_code":"175.0",
    "gn:asciiname":"Birsinghpur",
    "gn:country_code":"IN",
    "gn:dem":104,
    "gn:feature_class":"P",
    "gn:feature_code":"PPL",
    "gn:name":"B\u012brsinghpur",
    "gn:population":0,
    "gn:timezone":"Asia/Kolkata",
    "iso:country":"IN",
    "name:und_x_variant":[
        "B\u012brsinghpur",
        "R\u0101mgarh"
    ],
    "wof:name":"Birsinghpur",
    "wof:placetype":"locality"
},
  "geometry": {"coordinates":[81.80283,25.68426],"type":"Point"}
}