{
  "type": "Feature",
  "properties": {
    "iso:country":"IN",
    "ks:ks_name":"Lamadhar",
    "ks:ks_pop":86,
    "ks:ks_type":"VILLAGE",
    "name:eng_x_preferred":[
        "Lamadhar"
    ],
    "wof:name":"Lamadhar",
    "wof:placetype":"locality",
    "wof:population":86
},
  "geometry": {"coordinates":[80.097185,29.916245],"type":"Point"}
}