{
  "type": "Feature",
  "properties": {
    "gn:admin1_code":"39.0",
    "gn:admin2_code":"64.0",
    "gn:asciiname":"Jalna",
    "gn:country_code":"IN",
    "gn:dem":1939,
    "gn:feature_class":"P",
    "gn:feature_code":"PPL",
    "gn:name":"Jalna",
    "gn:population":0,
    "gn:timezone":"Asia/Kolkata",
    "iso:country":"IN",
    "name:ara_x_preferred":[
        "\u062c\u0627\u0644\u0646\u0627"
    ],
    "name:ben_bn_x_preferred":[
        "\u099c\u09be\u09b2\u09a8\u09be"
    ],
    "name:ben_in_x_preferred":[
        "\u099c\u09be\u09b2\u09a8\u09be"
    ],
    "name:ben_x_preferred":[
        "\u099c\u09be\u09b2\u09a8\u09be"
    ],
    "name:bih_x_preferred":[
        "\u091c\u093e\u0932\u0928\u093e"
    ],
    "name:bpy_x_preferred":[
        "\u099c\u09be\u09b2\u09a8\u09be"
    ],
    "name:cat_x_preferred":[
        "Jalna"
    ],
    "name:ceb_x_preferred":[
        "Jalna"
    ],
    "name:guj_x_preferred":[
        "\u0a9c\u0abe\u0ab2\u0acd\u0aa8\u0abe"
    ],
    "name:hin_x_preferred":[
        "\u091c\u0932\u0928\u093e"
    ],
    "name:kan_x_preferred":[
        "\u0c9c\u0cb2\u0ccd\u0ca8\u0cbe"
    ],
    "name:mal_x_preferred":[
        "\u0d1c\u0d7d\u0d28"
    ],
    "name:mar_x_preferred":[
        "\u091c\u093e\u0932\u0928\u093e"
    ],
    "name:msa_x_preferred":[
        "Jalna"
    ],
    "name:new_x_preferred":[
        "\u091c\u093e\u0932\u0928\u093e"
    ],
    "name:nld_x_preferred":[
        "Jalna"
    ],
    "name:pan_x_preferred":[
        "\u0a1c\u0a3e\u0a32\u0a28\u0a3e"
    ],
    "name:san_x_preferred":[
        "\u091c\u093e\u0932\u0928\u093e"
    ],
    "name:swe_x_preferred":[
        "Jalna"
    ],
    "name:tam_x_preferred":[
        "\u0b9c\u0bb2\u0bcd\u0ba9\u0bbe"
    ],
    "name:tel_x_preferred":[
        "\u0c1c\u0c3e\u0c32\u0c4d\u0c28\u0c3e"
    ],
    "name:urd_x_preferred":[
        "\u062c\u0627\u0644\u0646\u0627"
    ],
    "wof:name":"Jalna",
    "wof:placetype":"locality"
},
  "geometry": {"coordinates":[79.72303000000002,29.54947],"type":"Point"}
}