{
  "type": "Feature",
  "properties": {
    "gn:admin1_code":"24.0",
    "gn:admin2_code":"125.0",
    "gn:asciiname":"Mandli",
    "gn:country_code":"IN",
    "gn:dem":215,
    "gn:feature_class":"P",
    "gn:feature_code":"PPL",
    "gn:name":"Mandli",
    "gn:population":0,
    "gn:timezone":"Asia/Kolkata",
    "iso:country":"IN",
    "name:ara_x_preferred":[
        "\u0645\u0627\u0646\u062f\u0644\u064a"
    ],
    "name:ben_bn_x_preferred":[
        "\u09ae\u09a8\u09cd\u09a1\u09b2\u09c0"
    ],
    "name:ben_in_x_preferred":[
        "\u09ae\u09a8\u09cd\u09a1\u09b2\u09c0"
    ],
    "name:guj_x_preferred":[
        "\u0aae\u0a82\u0aa1\u0ab2\u0ac0"
    ],
    "name:hin_x_preferred":[
        "\u092e\u0902\u0921\u0932\u0940"
    ],
    "name:kan_x_preferred":[
        "\u0cae\u0c82\u0ca1\u0ccd\u0cb2\u0cbf"
    ],
    "name:mal_x_preferred":[
        "\u0d2e\u0d3e\u0d23\u0d4d\u0d21\u0d32\u0d3f"
    ],
    "name:mar_x_preferred":[
        "\u092e\u093e\u0902\u0921\u0932\u0940"
    ],
    "name:pan_x_preferred":[
        "\u0a2e\u0a70\u0a21\u0a32\u0a40"
    ],
    "name:tam_x_preferred":[
        "\u0bae\u0ba9\u0bcd\u0b9f\u0bcd\u0bb2\u0bbf"
    ],
    "name:tel_x_preferred":[
        "\u0c2e\u0c02\u0c21\u0c4d\u0c32\u0c3f"
    ],
    "name:urd_x_preferred":[
        "\u0645\u0627\u0646\u0688\u0644\u06cc"
    ],
    "wof:name":"Mandli",
    "wof:placetype":"locality"
},
  "geometry": {"coordinates":[74.22244999999999,23.2742],"type":"Point"}
}