{
  "type": "Feature",
  "properties": {
    "iso:country":"IN",
    "ks:ks_alt_nam":"RODGO",
    "ks:ks_name":"Rodgo",
    "ks:ks_pop":440,
    "ks:ks_type":"HABITATION",
    "name:eng_x_preferred":[
        "Rodgo"
    ],
    "wof:name":"Rodgo",
    "wof:placetype":"locality",
    "wof:population":440
},
  "geometry": {"coordinates":[87.614853,24.702748],"type":"Point"}
}