{
  "type": "Feature",
  "properties": {
    "gn:admin1_code":"34.0",
    "gn:admin2_code":"221.0",
    "gn:asciiname":"Deorhi",
    "gn:country_code":"IN",
    "gn:dem":42,
    "gn:feature_class":"P",
    "gn:feature_code":"PPL",
    "gn:name":"Deorhi",
    "gn:population":0,
    "gn:timezone":"Asia/Kolkata",
    "iso:country":"IN",
    "ks:ks_name":"Deorhi",
    "ks:ks_pop":2061,
    "ks:ks_type":"VILLAGE",
    "ks:ks_uagg_main":0,
    "name:eng_x_preferred":[
        "Deorhi"
    ],
    "wof:name":"Deorhi",
    "wof:placetype":"neighbourhood",
    "wof:population":2061
},
  "geometry": {"coordinates":[86.20281900000001,25.717425],"type":"Point"}
}