{
  "type": "Feature",
  "properties": {
    "gn:admin1_code":"13.0",
    "gn:admin2_code":"591.0",
    "gn:asciiname":"Koduvalli",
    "gn:country_code":"IN",
    "gn:dem":48,
    "gn:feature_class":"P",
    "gn:feature_code":"PPL",
    "gn:name":"Koduvalli",
    "gn:population":0,
    "gn:timezone":"Asia/Kolkata",
    "iso:country":"IN",
    "ks:ks_name":"Koduvalli",
    "ks:ks_type":"VILLAGE",
    "name:eng_x_preferred":[
        "Koduvalli"
    ],
    "wof:name":"Koduvalli",
    "wof:placetype":"locality"
},
  "geometry": {"coordinates":[75.90183399999999,11.34642],"type":"Point"}
}