{
  "type": "Feature",
  "properties": {
    "gn:admin1_code":"16",
    "gn:admin2_code":"501.0",
    "gn:asciiname":"Kharab Buzurg",
    "gn:country_code":"IN",
    "gn:dem":276,
    "gn:feature_class":"P",
    "gn:feature_code":"PPL",
    "gn:name":"Kharab Buzurg",
    "gn:population":0,
    "gn:timezone":"Asia/Kolkata",
    "iso:country":"IN",
    "wof:name":"Kharab Buzurg",
    "wof:placetype":"locality"
},
  "geometry": {"coordinates":[77.02531,20.73699],"type":"Point"}
}