{
  "type": "Feature",
  "properties": {
    "iso:country":"IN",
    "ks:ks_name":"Dahupani",
    "ks:ks_pop":188,
    "ks:ks_type":"VILLAGE",
    "name:eng_x_preferred":[
        "Dahupani"
    ],
    "wof:name":"Dahupani",
    "wof:placetype":"locality",
    "wof:population":188
},
  "geometry": {"coordinates":[86.316883,22.36978],"type":"Point"}
}