{
  "type": "Feature",
  "properties": {
    "gn:admin1_code":"12",
    "gn:admin2_code":"17.0",
    "gn:asciiname":"Danhar",
    "gn:country_code":"IN",
    "gn:dem":2062,
    "gn:feature_class":"P",
    "gn:feature_code":"PPL",
    "gn:name":"Danh\u0101r",
    "gn:population":0,
    "gn:timezone":"Asia/Kolkata",
    "iso:country":"IN",
    "wof:name":"Danhar",
    "wof:placetype":"locality"
},
  "geometry": {"coordinates":[75.16539,33.50402],"type":"Point"}
}