{
  "type": "Feature",
  "properties": {
    "iso:country":"IN",
    "ks:ks_name":"Gadiyasheelam",
    "ks:ks_pop":2516,
    "ks:ks_type":"VILLAGE",
    "name:eng_x_preferred":[
        "Gadiyasheelam"
    ],
    "wof:name":"Gadiyasheelam",
    "wof:placetype":"locality",
    "wof:population":2516
},
  "geometry": {"coordinates":[78.876937,27.4806],"type":"Point"}
}