{
  "type": "Feature",
  "properties": {
    "gn:admin1_code":"13.0",
    "gn:admin2_code":"589.0",
    "gn:asciiname":"Eruvatti",
    "gn:country_code":"IN",
    "gn:dem":37,
    "gn:feature_class":"P",
    "gn:feature_code":"PPL",
    "gn:name":"Eruvatti",
    "gn:population":0,
    "gn:timezone":"Asia/Kolkata",
    "iso:country":"IN",
    "ks:ks_name":"Eruvatti",
    "ks:ks_pop":15444,
    "ks:ks_type":"VILLAGE",
    "name:eng_x_preferred":[
        "Eruvatti"
    ],
    "wof:name":"Eruvatti",
    "wof:placetype":"locality",
    "wof:population":15444
},
  "geometry": {"coordinates":[75.53023,11.806205],"type":"Point"}
}