{
  "type": "Feature",
  "properties": {
    "iso:country":"IN",
    "ks:ks_name":"Naharhabi Grant No.83",
    "ks:ks_pop":89,
    "ks:ks_type":"VILLAGE",
    "name:eng_x_preferred":[
        "Naharhabi Grant No.83"
    ],
    "wof:name":"Naharhabi Grant No.83",
    "wof:placetype":"locality",
    "wof:population":89
},
  "geometry": {"coordinates":[94.84165900000001,26.983834],"type":"Point"}
}