{
  "type": "Feature",
  "properties": {
    "iso:country":"IN",
    "ks:ks_name":"Goregadde",
    "ks:ks_pop":86,
    "ks:ks_type":"HABITATION",
    "name:eng_x_preferred":[
        "Goregadde"
    ],
    "wof:name":"Goregadde",
    "wof:placetype":"locality",
    "wof:population":86
},
  "geometry": {"coordinates":[74.77457099999999,14.565468],"type":"Point"}
}