{
  "type": "Feature",
  "properties": {
    "iso:country":"IN",
    "ks:ks_alt_nam":"Makh\u0101ni",
    "ks:ks_alt_nam_2":"Makhani",
    "ks:ks_name":"Mukhani",
    "ks:ks_pop":5959,
    "ks:ks_type":"VILLAGE",
    "ks:ks_uagg_main":0,
    "name:eng_x_preferred":[
        "Mukhani"
    ],
    "name:eng_x_variant":[
        "Makh\u0101ni",
        "Makhani"
    ],
    "wof:name":"Mukhani",
    "wof:placetype":"neighbourhood",
    "wof:population":5959
},
  "geometry": {"coordinates":[79.507683,29.212279],"type":"Point"}
}