{
  "type": "Feature",
  "properties": {
    "gn:admin1_code":"36",
    "gn:admin2_code":"202.0",
    "gn:asciiname":"Bankner",
    "gn:country_code":"IN",
    "gn:dem":173,
    "gn:feature_class":"P",
    "gn:feature_code":"PPL",
    "gn:name":"B\u0101nkner",
    "gn:population":0,
    "gn:timezone":"Asia/Kolkata",
    "iso:country":"IN",
    "name:ara_x_preferred":[
        "\u0628\u0627\u0646\u0643\u0646\u064a\u0631"
    ],
    "name:ben_bn_x_preferred":[
        "\u09ac\u09be\u0999\u09cd\u0995\u09a8\u09c7\u09b0"
    ],
    "name:ben_in_x_preferred":[
        "\u09ac\u09be\u0999\u09cd\u0995\u09a8\u09c7\u09b0"
    ],
    "name:ben_x_preferred":[
        "\u09ac\u09be\u0999\u09cd\u0995\u09a8\u09c7\u09b0"
    ],
    "name:bpy_x_preferred":[
        "\u09ac\u09be\u0999\u09cd\u0995\u09a8\u09c7\u09b0"
    ],
    "name:guj_x_preferred":[
        "\u0aac\u0ac7\u0a82\u0a95\u0ab0"
    ],
    "name:hin_x_preferred":[
        "\u092c\u0902\u0915\u0928\u0947\u0930"
    ],
    "name:ita_x_preferred":[
        "Bankner"
    ],
    "name:kan_x_preferred":[
        "\u0cac\u0c82\u0c95\u0cbe\u0ca8\u0cc7\u0cb0\u0ccd"
    ],
    "name:mal_x_preferred":[
        "\u0d2c\u0d3e\u0d19\u0d4d\u0d15\u0d7c"
    ],
    "name:mar_x_preferred":[
        "\u092c\u0901\u0915\u0928\u0947\u0930"
    ],
    "name:msa_x_preferred":[
        "Bankner"
    ],
    "name:new_x_preferred":[
        "\u092c\u0902\u0915\u094d\u0928\u0947\u0930"
    ],
    "name:nld_x_preferred":[
        "Bankner"
    ],
    "name:pan_x_preferred":[
        "\u0a2c\u0a70\u0a15\u0a28\u0a47\u0a30"
    ],
    "name:por_x_preferred":[
        "Bankner"
    ],
    "name:tam_x_preferred":[
        "\u0baa\u0ba9\u0bcd\u0b95\u0bcd\u0ba9\u0bc6\u0bb0\u0bcd"
    ],
    "name:tel_x_preferred":[
        "\u0c2c\u0c4d\u0c2f\u0c3e\u0c02\u0c15\u0c4d"
    ],
    "name:urd_x_preferred":[
        "\u0628\u0627\u0646\u06a9\u06cc\u0631"
    ],
    "name:vie_x_preferred":[
        "Bankner"
    ],
    "name:zho_x_preferred":[
        "\u73ed\u514b\u5185\u5c14"
    ],
    "wof:name":"Bankner",
    "wof:placetype":"neighbourhood"
},
  "geometry": {"coordinates":[78.63072,27.79514],"type":"Point"}
}