{
  "type": "Feature",
  "properties": {
    "gn:admin1_code":"40",
    "gn:admin2_code":"537.0",
    "gn:asciiname":"Puppalguda",
    "gn:country_code":"IN",
    "gn:dem":537,
    "gn:feature_class":"P",
    "gn:feature_code":"PPL",
    "gn:name":"Pupp\u0101lg\u016bda",
    "gn:population":0,
    "gn:timezone":"Asia/Kolkata",
    "iso:country":"IN",
    "ks:ks_alt_nam":"Pupp\u0101lg\u016bda",
    "ks:ks_name":"Puppalguda",
    "ks:ks_pop":2108,
    "ks:ks_type":"VILLAGE",
    "ks:ks_uagg_main":0,
    "name:eng_x_preferred":[
        "Puppalguda"
    ],
    "name:eng_x_variant":[
        "Pupp\u0101lg\u016bda"
    ],
    "wof:name":"Puppalguda",
    "wof:placetype":"locality",
    "wof:population":2108
},
  "geometry": {"coordinates":[78.37480499999999,17.398191],"type":"Point"}
}