{
  "type": "Feature",
  "properties": {
    "iso:country":"IN",
    "ks:ks_alt_nam":"Hes\u0101long",
    "ks:ks_name":"Hesalong",
    "ks:ks_pop":221,
    "ks:ks_type":"VILLAGE",
    "name:eng_x_preferred":[
        "Hesalong"
    ],
    "name:eng_x_variant":[
        "Hes\u0101long"
    ],
    "wof:name":"Hesalong",
    "wof:placetype":"locality",
    "wof:population":221
},
  "geometry": {"coordinates":[84.865503,23.595406],"type":"Point"}
}