{
  "type": "Feature",
  "properties": {
    "iso:country":"IN",
    "ks:ks_name":"Ramprasadpur",
    "ks:ks_pop":2505,
    "ks:ks_type":"VILLAGE",
    "ks:ks_uagg_main":0,
    "name:eng_x_preferred":[
        "Ramprasadpur"
    ],
    "wof:name":"Ramprasadpur",
    "wof:placetype":"locality",
    "wof:population":2505
},
  "geometry": {"coordinates":[87.192009,23.566688],"type":"Point"}
}