{
  "type": "Feature",
  "properties": {
    "gn:admin1_code":"24",
    "gn:admin2_code":"122.0",
    "gn:asciiname":"Barapal-ki-Jhonpria",
    "gn:country_code":"IN",
    "gn:dem":366,
    "gn:feature_class":"P",
    "gn:feature_code":"PPL",
    "gn:name":"B\u0101rap\u0101l-ki-Jhonpria",
    "gn:population":0,
    "gn:timezone":"Asia/Kolkata",
    "iso:country":"IN",
    "wof:name":"Barapal-ki-Jhonpria",
    "wof:placetype":"locality"
},
  "geometry": {"coordinates":[75.31444,25.58674],"type":"Point"}
}