{
  "type": "Feature",
  "properties": {
    "iso:country":"IN",
    "ks:ks_name":"Chotto Sahebkhali",
    "ks:ks_pop":2183,
    "ks:ks_type":"HABITATION",
    "name:eng_x_preferred":[
        "Chotto Sahebkhali"
    ],
    "wof:name":"Chotto Sahebkhali",
    "wof:placetype":"locality",
    "wof:population":2183
},
  "geometry": {"coordinates":[88.952325,22.327058],"type":"Point"}
}