{
  "type": "Feature",
  "properties": {
    "iso:country":"IN",
    "ks:ks_name":"Jaintar",
    "ks:ks_pop":3086,
    "ks:ks_type":"VILLAGE",
    "name:eng_x_preferred":[
        "Jaintar"
    ],
    "wof:name":"Jaintar",
    "wof:placetype":"locality",
    "wof:population":3086
},
  "geometry": {"coordinates":[86.459873,20.839936],"type":"Point"}
}