{
  "type": "Feature",
  "properties": {
    "gn:admin1_code":"2",
    "gn:admin2_code":"548.0",
    "gn:asciiname":"Rangaraopeta",
    "gn:country_code":"IN",
    "gn:dem":12,
    "gn:feature_class":"P",
    "gn:feature_code":"PPL",
    "gn:name":"Rangaraopeta",
    "gn:population":0,
    "gn:timezone":"Asia/Kolkata",
    "iso:country":"IN",
    "wof:name":"Rangaraopeta",
    "wof:placetype":"locality"
},
  "geometry": {"coordinates":[80.38893,16.02447],"type":"Point"}
}