{
  "type": "Feature",
  "properties": {
    "iso:country":"IN",
    "ks:ks_name":"Mulagadde",
    "ks:ks_pop":129,
    "ks:ks_type":"HABITATION",
    "name:eng_x_preferred":[
        "Mulagadde"
    ],
    "wof:name":"Mulagadde",
    "wof:placetype":"locality",
    "wof:population":129
},
  "geometry": {"coordinates":[75.094528,13.983886],"type":"Point"}
}