{
  "type": "Feature",
  "properties": {
    "iso:country":"IN",
    "ks:ks_name":"Primeda",
    "ks:ks_pop":559,
    "ks:ks_type":"HABITATION",
    "name:eng_x_preferred":[
        "Primeda"
    ],
    "wof:name":"Primeda",
    "wof:placetype":"locality",
    "wof:population":559
},
  "geometry": {"coordinates":[79.91266400000001,19.080819],"type":"Point"}
}