{
  "type": "Feature",
  "properties": {
    "iso:country":"IN",
    "ks:ks_name":"Halkara Khurd",
    "ks:ks_pop":197,
    "ks:ks_type":"VILLAGE",
    "name:eng_x_preferred":[
        "Halkara Khurd"
    ],
    "wof:name":"Halkara Khurd",
    "wof:placetype":"locality",
    "wof:population":197
},
  "geometry": {"coordinates":[74.547432,23.291829],"type":"Point"}
}