{
  "type": "Feature",
  "properties": {
    "iso:country":"IN",
    "ks:ks_name":"Balatari",
    "ks:ks_pop":574,
    "ks:ks_type":"VILLAGE",
    "name:eng_x_preferred":[
        "Balatari"
    ],
    "wof:name":"Balatari",
    "wof:placetype":"locality",
    "wof:population":574
},
  "geometry": {"coordinates":[79.945542,29.336257],"type":"Point"}
}