{
  "type": "Feature",
  "properties": {
    "iso:country":"IN",
    "name:eng_x_preferred":[
        "Kamakshya"
    ],
    "name:tel_x_preferred":[
        "\u0c15\u0c3e\u0c2e\u0c3e\u0c16\u0c4d\u0c2f\u0c3e\u0c26\u0c47\u0c35\u0c3f"
    ],
    "name:unk_x_variant":[
        "Kamakshya"
    ],
    "qs:gn_adm0_cc":"IN",
    "qs:gn_local":1261186,
    "qs:gn_nam_loc":"North Guwahati",
    "qs:gn_namadm1":"03",
    "qs:local_max":112,
    "qs:local_sum":175,
    "qs:localhoods":3,
    "qs:name":"Kamakshya",
    "qs:name_adm0":"India",
    "qs:name_adm1":"Assam",
    "qs:name_adm2":"Kamrup",
    "qs:name_local":"Guwahati",
    "qs:photo_max":29,
    "qs:photo_sum":57,
    "qs:placetype":"Suburb",
    "qs:quad_count":9,
    "qs:woe_adm0":23424848,
    "qs:woe_adm1":2345741,
    "qs:woe_adm2":12586360,
    "qs:woe_lau":0,
    "qs:woe_local":2277394,
    "qs:woe_ver":"7.10.0",
    "wd:wordcount":1048,
    "wof:lang":[
        "eng"
    ],
    "wof:name":"Kamakshya",
    "wof:placetype":"neighbourhood"
},
  "geometry": {"coordinates":[91.705843,26.16865],"type":"Point"}
}