{
  "type": "Feature",
  "properties": {
    "iso:country":"IN",
    "name:ara_x_preferred":[
        "\u0643\u0627\u0645\u0643\u0634\u064a"
    ],
    "name:ben_bn_x_preferred":[
        "\u0995\u09be\u09ae\u09be\u0995\u09cd\u09b7\u09cd\u09af\u09be"
    ],
    "name:ben_in_x_preferred":[
        "\u0995\u09be\u09ae\u09be\u0995\u09cd\u09b7\u09cd\u09af\u09be"
    ],
    "name:eng_x_preferred":[
        "Kamakshya"
    ],
    "name:eng_x_variant":[
        "Kamakhya"
    ],
    "name:guj_x_preferred":[
        "\u0a95\u0abe\u0aae\u0abe\u0a95\u0acd\u0ab7\u0acd\u0aaf"
    ],
    "name:hin_x_preferred":[
        "\u0915\u093e\u092e\u093e\u0915\u094d\u0937\u094d\u092f"
    ],
    "name:kan_x_preferred":[
        "\u0c95\u0cbe\u0cae\u0cbe\u0c95\u0ccd\u0cb7\u0ccd\u0caf"
    ],
    "name:mal_x_preferred":[
        "\u0d15\u0d3e\u0d2e\u0d3e\u0d15\u0d4d\u0d37\u0d4d\u0d2f"
    ],
    "name:mar_x_preferred":[
        "\u0915\u093e\u092e\u093e\u0915\u094d\u0937\u094d\u092f\u093e"
    ],
    "name:pan_x_preferred":[
        "\u0a15\u0a3e\u0a2e\u0a15\u0a36\u0a3f\u0a06"
    ],
    "name:pan_x_variant":[
        "\u0a15\u0a3e\u0a2e\u0a3e\u0a16\u0a3f\u0a06"
    ],
    "name:tam_x_preferred":[
        "\u0b95\u0bbe\u0bae\u0bbe\u0b95\u0bcd"
    ],
    "name:tel_x_preferred":[
        "\u0c15\u0c3e\u0c2e\u0c3e\u0c15\u0c4d\u0c37\u0c4d\u0c2f"
    ],
    "name:tel_x_variant":[
        "\u0c15\u0c3e\u0c2e\u0c3e\u0c16\u0c4d\u0c2f\u0c3e\u0c26\u0c47\u0c35\u0c3f"
    ],
    "name:urd_x_preferred":[
        "\u06a9\u0627\u0645\u0627\u06a9\u06be\u06cc\u0627"
    ],
    "qs:gn_adm0_cc":"IN",
    "qs:gn_local":1261186,
    "qs:gn_nam_loc":"North Guwahati",
    "qs:gn_namadm1":"03",
    "qs:local_max":112,
    "qs:local_sum":175,
    "qs:localhoods":3,
    "qs:name":"Kamakshya",
    "qs:name_adm0":"India",
    "qs:name_adm1":"Assam",
    "qs:name_adm2":"Kamrup",
    "qs:name_local":"Guwahati",
    "qs:photo_max":29,
    "qs:photo_sum":57,
    "qs:placetype":"Suburb",
    "qs:quad_count":9,
    "qs:woe_adm0":23424848,
    "qs:woe_adm1":2345741,
    "qs:woe_adm2":12586360,
    "qs:woe_lau":0,
    "qs:woe_local":2277394,
    "qs:woe_ver":"7.10.0",
    "wd:wordcount":1048,
    "wof:lang":[
        "eng"
    ],
    "wof:name":"Kamakshya",
    "wof:placetype":"neighbourhood"
},
  "geometry": {"coordinates":[91.705843,26.16865],"type":"Point"}
}