{
  "type": "Feature",
  "properties": {
    "gn:admin1_code":"35",
    "gn:admin2_code":"426.0",
    "gn:asciiname":"Rachhapar",
    "gn:country_code":"IN",
    "gn:dem":501,
    "gn:feature_class":"P",
    "gn:feature_code":"PPL",
    "gn:name":"Rachhap\u0101r",
    "gn:population":0,
    "gn:timezone":"Asia/Kolkata",
    "iso:country":"IN",
    "ks:ks_name":"Rachhapur",
    "ks:ks_pop":65,
    "ks:ks_type":"HABITATION",
    "name:eng_x_preferred":[
        "Rachhapur"
    ],
    "name:eng_x_variant":[
        "Rachhapar"
    ],
    "wof:name":"Rachhapur",
    "wof:placetype":"locality",
    "wof:population":65
},
  "geometry": {"coordinates":[80.46938299999999,24.208688],"type":"Point"}
}