{
  "type": "Feature",
  "properties": {
    "iso:country":"IN",
    "ks:ks_name":"27 MD",
    "ks:ks_pop":7,
    "ks:ks_type":"VILLAGE",
    "name:eng_x_preferred":[
        "27 MD"
    ],
    "wof:name":"27 MD",
    "wof:placetype":"locality",
    "wof:population":7
},
  "geometry": {"coordinates":[72.95246400000001,29.011234],"type":"Point"}
}