{
  "type": "Feature",
  "properties": {
    "iso:country":"IN",
    "ks:ks_name":"Mandi",
    "ks:ks_pop":898,
    "ks:ks_type":"VILLAGE",
    "name:eng_x_preferred":[
        "Mandi"
    ],
    "wof:name":"Mandi",
    "wof:placetype":"locality",
    "wof:population":898
},
  "geometry": {"coordinates":[87.264562,22.972106],"type":"Point"}
}