{
  "type": "Feature",
  "properties": {
    "iso:country":"IN",
    "ks:ks_name":"Amlagura",
    "ks:ks_pop":675,
    "ks:ks_type":"VILLAGE",
    "name:eng_x_preferred":[
        "Amlagura"
    ],
    "wof:name":"Amlagura",
    "wof:placetype":"locality",
    "wof:population":675
},
  "geometry": {"coordinates":[87.024946,23.114618],"type":"Point"}
}