{
  "type": "Feature",
  "properties": {
    "iso:country":"IN",
    "ks:ks_name":"Daler",
    "ks:ks_pop":405,
    "ks:ks_type":"VILLAGE",
    "name:eng_x_preferred":[
        "Daler"
    ],
    "wof:name":"Daler",
    "wof:placetype":"locality",
    "wof:population":405
},
  "geometry": {"coordinates":[81.043013,19.067862],"type":"Point"}
}