{
  "type": "Feature",
  "properties": {
    "iso:country":"IN",
    "ks:ks_name":"Manawas",
    "ks:ks_pop":340,
    "ks:ks_type":"VILLAGE",
    "name:eng_x_preferred":[
        "Manawas"
    ],
    "wof:name":"Manawas",
    "wof:placetype":"locality",
    "wof:population":340
},
  "geometry": {"coordinates":[71.98944400000001,25.678578],"type":"Point"}
}