{
  "type": "Feature",
  "properties": {
    "gn:admin1_code":"21",
    "gn:admin2_code":"370.0",
    "gn:asciiname":"Kulunda",
    "gn:country_code":"IN",
    "gn:dem":166,
    "gn:feature_class":"P",
    "gn:feature_code":"PPL",
    "gn:name":"Kulunda",
    "gn:population":0,
    "gn:timezone":"Asia/Kolkata",
    "iso:country":"IN",
    "name:bel_x_preferred":[
        "\u041a\u0443\u043b\u0443\u043d\u0434\u0430"
    ],
    "name:ben_x_preferred":[
        "\u0995\u09c1\u09b2\u09c1\u09a8\u09cd\u09a6\u09be"
    ],
    "name:ceb_x_preferred":[
        "Kulunda"
    ],
    "name:che_x_preferred":[
        "\u041a\u0443\u043b\u0443\u043d\u0434\u0430"
    ],
    "name:deu_x_preferred":[
        "Kulunda"
    ],
    "name:ell_x_preferred":[
        "\u039a\u03bf\u03c5\u03bb\u03bf\u03cd\u03bd\u03c4\u03b1"
    ],
    "name:fas_x_preferred":[
        "\u06a9\u0648\u0644\u0648\u0646\u062f\u0627"
    ],
    "name:fra_x_preferred":[
        "Kulunda"
    ],
    "name:heb_x_preferred":[
        "\u05e7\u05d5\u05dc\u05d5\u05e0\u05d3\u05d4"
    ],
    "name:hin_x_preferred":[
        "\u0915\u0941\u0932\u0941\u0902\u0926\u093e"
    ],
    "name:ind_x_preferred":[
        "Kulunda"
    ],
    "name:ita_x_preferred":[
        "Kulunda"
    ],
    "name:jpn_x_preferred":[
        "\u30af\u30eb\u30f3\u30c0"
    ],
    "name:kor_x_preferred":[
        "\ucfe8\ub8ec\ub2e4"
    ],
    "name:lit_x_preferred":[
        "Kulunda"
    ],
    "name:pol_x_preferred":[
        "Ku\u0142unda"
    ],
    "name:rus_x_preferred":[
        "\u041a\u0443\u043b\u0443\u043d\u0434\u0430"
    ],
    "name:swe_x_preferred":[
        "Kulunda"
    ],
    "name:tur_x_preferred":[
        "Kulunda"
    ],
    "name:ukr_x_preferred":[
        "\u041a\u0443\u043b\u0443\u043d\u0434\u0430"
    ],
    "name:urd_x_preferred":[
        "\u06a9\u0648\u0644\u0648\u0646\u062f\u0627"
    ],
    "name:vie_x_preferred":[
        "Kulunda"
    ],
    "wof:name":"Kulunda",
    "wof:placetype":"locality"
},
  "geometry": {"coordinates":[83.78180999999999,21.34472],"type":"Point"}
}