{
  "type": "Feature",
  "properties": {
    "gn:admin1_code":"21",
    "gn:admin2_code":"370.0",
    "gn:asciiname":"Kulunda",
    "gn:country_code":"IN",
    "gn:dem":166,
    "gn:feature_class":"P",
    "gn:feature_code":"PPL",
    "gn:name":"Kulunda",
    "gn:population":0,
    "gn:timezone":"Asia/Kolkata",
    "iso:country":"IN",
    "name:bel_x_preferred":[
        "\u041a\u0443\u043b\u0443\u043d\u0434\u0430"
    ],
    "name:ceb_x_preferred":[
        "Kulunda"
    ],
    "name:che_x_preferred":[
        "\u041a\u0443\u043b\u0443\u043d\u0434\u0430"
    ],
    "name:deu_x_preferred":[
        "Kulunda"
    ],
    "name:ita_x_preferred":[
        "Kulunda"
    ],
    "name:lit_x_preferred":[
        "Kulunda"
    ],
    "name:pol_x_preferred":[
        "Ku\u0142unda"
    ],
    "name:rus_x_preferred":[
        "\u041a\u0443\u043b\u0443\u043d\u0434\u0430"
    ],
    "wof:name":"Kulunda",
    "wof:placetype":"locality"
},
  "geometry": {"coordinates":[83.78180999999999,21.34472],"type":"Point"}
}