{
  "type": "Feature",
  "properties": {
    "iso:country":"IN",
    "ks:ks_alt_nam":"Nas\u012brpur",
    "ks:ks_name":"Nasirpur",
    "ks:ks_pop":136,
    "ks:ks_type":"VILLAGE",
    "ks:ks_uagg_main":0,
    "name:eng_x_preferred":[
        "Nasirpur"
    ],
    "name:eng_x_variant":[
        "Nas\u012brpur"
    ],
    "wof:name":"Nasirpur",
    "wof:placetype":"neighbourhood",
    "wof:population":136
},
  "geometry": {"coordinates":[83.53592,25.611509],"type":"Point"}
}