{
  "type": "Feature",
  "properties": {
    "gn:admin1_code":"39.0",
    "gn:admin2_code":"60.0",
    "gn:asciiname":"Koti",
    "gn:country_code":"IN",
    "gn:dem":778,
    "gn:feature_class":"P",
    "gn:feature_code":"PPL",
    "gn:name":"Koti",
    "gn:population":0,
    "gn:timezone":"Asia/Kolkata",
    "iso:country":"IN",
    "name:ceb_x_preferred":[
        "Koti"
    ],
    "name:deu_x_preferred":[
        "Koti"
    ],
    "name:fra_x_preferred":[
        "Koti"
    ],
    "name:new_x_preferred":[
        "\u0915\u094b\u091f\u0940"
    ],
    "name:sco_x_preferred":[
        "Koti"
    ],
    "name:swe_x_preferred":[
        "Koti"
    ],
    "wof:name":"Koti",
    "wof:placetype":"locality"
},
  "geometry": {"coordinates":[77.78198,30.61015],"type":"Point"}
}