{
  "type": "Feature",
  "properties": {
    "iso:country":"IN",
    "ks:ks_name":"Kalagin Kabgal",
    "ks:ks_pop":91,
    "ks:ks_type":"HABITATION",
    "name:eng_x_preferred":[
        "Kalagin Kabgal"
    ],
    "wof:name":"Kalagin Kabgal",
    "wof:placetype":"locality",
    "wof:population":91
},
  "geometry": {"coordinates":[74.47134800000001,14.565045],"type":"Point"}
}