{
  "type": "Feature",
  "properties": {
    "gn:admin1_code":"36.0",
    "gn:admin2_code":"162.0",
    "gn:asciiname":"Gopiapur",
    "gn:country_code":"IN",
    "gn:dem":148,
    "gn:feature_class":"P",
    "gn:feature_code":"PPL",
    "gn:name":"Gopi\u0101pur",
    "gn:population":0,
    "gn:timezone":"Asia/Kolkata",
    "iso:country":"IN",
    "wof:name":"Gopiapur",
    "wof:placetype":"neighbourhood"
},
  "geometry": {"coordinates":[79.37273999999999,26.86131],"type":"Point"}
}