{
  "type": "Feature",
  "properties": {
    "iso:country":"IN",
    "ks:ks_alt_nam":"EAST TOLA",
    "ks:ks_name":"East Tola",
    "ks:ks_pop":1005,
    "ks:ks_type":"HABITATION",
    "name:eng_x_preferred":[
        "East Tola"
    ],
    "wof:name":"East Tola",
    "wof:placetype":"locality",
    "wof:population":1005
},
  "geometry": {"coordinates":[84.82971000000001,25.87392],"type":"Point"}
}