{
  "type": "Feature",
  "properties": {
    "gn:admin1_code":"39",
    "gn:admin2_code":"60.0",
    "gn:asciiname":"Khadra",
    "gn:country_code":"IN",
    "gn:dem":2126,
    "gn:feature_class":"P",
    "gn:feature_code":"PPL",
    "gn:name":"Kh\u0101dra",
    "gn:population":0,
    "gn:timezone":"Asia/Kolkata",
    "iso:country":"IN",
    "wof:name":"Khadra",
    "wof:placetype":"locality"
},
  "geometry": {"coordinates":[77.93934,30.84253],"type":"Point"}
}