{
  "type": "Feature",
  "properties": {
    "gn:admin1_code":"10.0",
    "gn:admin2_code":"71.0",
    "gn:asciiname":"Salempur",
    "gn:country_code":"IN",
    "gn:dem":292,
    "gn:feature_class":"P",
    "gn:feature_code":"PPL",
    "gn:name":"Salempur",
    "gn:population":0,
    "gn:timezone":"Asia/Kolkata",
    "iso:country":"IN",
    "name:ceb_x_preferred":[
        "Salempur"
    ],
    "name:pol_x_preferred":[
        "Salempur"
    ],
    "name:swe_x_preferred":[
        "Salempur"
    ],
    "wof:name":"Salempur",
    "wof:placetype":"locality"
},
  "geometry": {"coordinates":[77.31780999999999,30.23626],"type":"Point"}
}