{
  "type": "Feature",
  "properties": {
    "gn:admin1_code":"34",
    "gn:admin2_code":"209.0",
    "gn:asciiname":"Pategna",
    "gn:country_code":"IN",
    "gn:dem":62,
    "gn:feature_class":"P",
    "gn:feature_code":"PPL",
    "gn:name":"Pategna",
    "gn:population":0,
    "gn:timezone":"Asia/Kolkata",
    "iso:country":"IN",
    "wof:name":"Pategna",
    "wof:placetype":"locality"
},
  "geometry": {"coordinates":[87.46035000000001,26.25262],"type":"Point"}
}