{
  "type": "Feature",
  "properties": {
    "iso:country":"IN",
    "ks:ks_name":"Jaigaon Jatoli",
    "ks:ks_pop":343,
    "ks:ks_type":"VILLAGE",
    "name:eng_x_preferred":[
        "Jaigaon Jatoli"
    ],
    "wof:name":"Jaigaon Jatoli",
    "wof:placetype":"locality",
    "wof:population":343
},
  "geometry": {"coordinates":[80.068603,29.296658],"type":"Point"}
}