{
  "type": "Feature",
  "properties": {
    "gn:admin1_code":"36.0",
    "gn:admin2_code":"184.0",
    "gn:asciiname":"Madhwapur",
    "gn:country_code":"IN",
    "gn:dem":89,
    "gn:feature_class":"P",
    "gn:feature_code":"PPL",
    "gn:name":"Madhw\u0101pur",
    "gn:population":0,
    "gn:timezone":"Asia/Kolkata",
    "iso:country":"IN",
    "name:hin_x_preferred":[
        "\u092e\u0927\u0935\u093e\u092a\u0941\u0930 \u092a\u094d\u0930\u0916\u0923\u094d\u0921"
    ],
    "wof:name":"Madhwapur",
    "wof:placetype":"locality"
},
  "geometry": {"coordinates":[82.98698,27.16463],"type":"Point"}
}