{
  "type": "Feature",
  "properties": {
    "iso:country":"IN",
    "ks:ks_name":"Rajgarh",
    "ks:ks_pop":1051,
    "ks:ks_type":"VILLAGE",
    "ks:ks_uagg_main":0,
    "name:eng_x_preferred":[
        "Rajgarh"
    ],
    "wof:name":"Rajgarh",
    "wof:placetype":"neighbourhood",
    "wof:population":1051
},
  "geometry": {"coordinates":[92.85424500000001,26.791282],"type":"Point"}
}