{
  "type": "Feature",
  "properties": {
    "gn:admin1_code":"31.0",
    "gn:admin2_code":"284",
    "gn:asciiname":"Khawbung",
    "gn:country_code":"IN",
    "gn:dem":1309,
    "gn:feature_class":"P",
    "gn:feature_code":"PPL",
    "gn:name":"Khawbung",
    "gn:population":0,
    "gn:timezone":"Asia/Kolkata",
    "iso:country":"IN",
    "wof:name":"Khawbung",
    "wof:placetype":"locality"
},
  "geometry": {"coordinates":[93.21995,23.17163],"type":"Point"}
}