{
  "type": "Feature",
  "properties": {
    "iso:country":"IN",
    "ks:ks_alt_nam":"It\u0101r",
    "ks:ks_name":"Itar",
    "ks:ks_pop":942,
    "ks:ks_type":"VILLAGE",
    "name:eng_x_preferred":[
        "Itar"
    ],
    "name:eng_x_variant":[
        "It\u0101r"
    ],
    "wof:name":"Itar",
    "wof:placetype":"locality",
    "wof:population":942
},
  "geometry": {"coordinates":[85.86361100000001,22.140962],"type":"Point"}
}