{
  "type": "Feature",
  "properties": {
    "iso:country":"IN",
    "ks:ks_name":"Maina M.mahua",
    "ks:ks_pop":300,
    "ks:ks_type":"HABITATION",
    "name:eng_x_preferred":[
        "Maina M.mahua"
    ],
    "wof:name":"Maina M.mahua",
    "wof:placetype":"locality",
    "wof:population":300
},
  "geometry": {"coordinates":[80.23875700000001,28.275726],"type":"Point"}
}