{
  "type": "Feature",
  "properties": {
    "iso:country":"IN",
    "ks:ks_name":"Patelpara Pondgaon",
    "ks:ks_pop":1060,
    "ks:ks_type":"HABITATION",
    "name:eng_x_preferred":[
        "Patelpara Pondgaon"
    ],
    "wof:name":"Patelpara Pondgaon",
    "wof:placetype":"locality",
    "wof:population":1060
},
  "geometry": {"coordinates":[81.147111,20.16036],"type":"Point"}
}