{
  "type": "Feature",
  "properties": {
    "iso:country":"IN",
    "ks:ks_name":"Abedkarbeedi",
    "ks:ks_pop":30,
    "ks:ks_type":"HABITATION",
    "name:eng_x_preferred":[
        "Abedkarbeedi"
    ],
    "wof:name":"Abedkarbeedi",
    "wof:placetype":"locality",
    "wof:population":30
},
  "geometry": {"coordinates":[74.540662,14.86836],"type":"Point"}
}