{
  "type": "Feature",
  "properties": {
    "iso:country":"IN",
    "ks:ks_name":"Idoor",
    "ks:ks_pop":168,
    "ks:ks_type":"HABITATION",
    "name:eng_x_preferred":[
        "Idoor"
    ],
    "wof:name":"Idoor",
    "wof:placetype":"locality",
    "wof:population":168
},
  "geometry": {"coordinates":[74.177347,14.76319],"type":"Point"}
}