{
  "type": "Feature",
  "properties": {
    "iso:country":"IN",
    "ks:ks_name":"Simble",
    "ks:ks_pop":101,
    "ks:ks_type":"HABITATION",
    "name:eng_x_preferred":[
        "Simble"
    ],
    "wof:name":"Simble",
    "wof:placetype":"locality",
    "wof:population":101
},
  "geometry": {"coordinates":[75.330547,32.299887],"type":"Point"}
}