{
  "type": "Feature",
  "properties": {
    "iso:country":"IN",
    "ks:ks_name":"Hilkome",
    "ks:ks_pop":240,
    "ks:ks_type":"HABITATION",
    "name:eng_x_preferred":[
        "Hilkome"
    ],
    "wof:name":"Hilkome",
    "wof:placetype":"locality",
    "wof:population":240
},
  "geometry": {"coordinates":[74.769469,13.597777],"type":"Point"}
}