{
  "type": "Feature",
  "properties": {
    "iso:country":"IN",
    "ks:ks_name":"Kancharapadu",
    "ks:ks_pop":161,
    "ks:ks_type":"HABITATION",
    "name:eng_x_preferred":[
        "Kancharapadu"
    ],
    "wof:name":"Kancharapadu",
    "wof:placetype":"locality",
    "wof:population":161
},
  "geometry": {"coordinates":[83.407455,18.860429],"type":"Point"}
}