{
  "type": "Feature",
  "properties": {
    "iso:country":"IN",
    "ks:ks_name":"Y. Plantation",
    "ks:ks_pop":31,
    "ks:ks_type":"HABITATION",
    "name:eng_x_preferred":[
        "Y. Plantation"
    ],
    "wof:name":"Y. Plantation",
    "wof:placetype":"locality",
    "wof:population":31
},
  "geometry": {"coordinates":[77.876671,13.294543],"type":"Point"}
}