{
  "type": "Feature",
  "properties": {
    "iso:country":"IN",
    "ks:ks_alt_nam":"mundatola",
    "ks:ks_name":"Mundatola",
    "ks:ks_pop":186,
    "ks:ks_type":"HABITATION",
    "name:eng_x_preferred":[
        "Mundatola"
    ],
    "wof:name":"Mundatola",
    "wof:placetype":"locality",
    "wof:population":186
},
  "geometry": {"coordinates":[85.270099,22.443208],"type":"Point"}
}