{
  "type": "Feature",
  "properties": {
    "gn:admin1_code":"2",
    "gn:admin2_code":"545.0",
    "gn:asciiname":"Rajupalem",
    "gn:country_code":"IN",
    "gn:dem":64,
    "gn:feature_class":"P",
    "gn:feature_code":"PPL",
    "gn:name":"R\u0101jup\u0101lem",
    "gn:population":0,
    "gn:timezone":"Asia/Kolkata",
    "iso:country":"IN",
    "name:vie_x_preferred":[
        "Rajupalem"
    ],
    "wof:name":"Rajupalem",
    "wof:placetype":"locality"
},
  "geometry": {"coordinates":[81.86968,17.27734],"type":"Point"}
}