{
  "type": "Feature",
  "properties": {
    "gn:admin1_code":"38.0",
    "gn:admin2_code":"363",
    "gn:asciiname":"Chaparia",
    "gn:country_code":"IN",
    "gn:dem":218,
    "gn:feature_class":"P",
    "gn:feature_code":"PPL",
    "gn:name":"Chaparia",
    "gn:population":0,
    "gn:timezone":"Asia/Kolkata",
    "iso:country":"IN",
    "name:und_x_variant":[
        "Shaparia",
        "Chaparia"
    ],
    "wof:name":"Chaparia",
    "wof:placetype":"locality"
},
  "geometry": {"coordinates":[86.8954,24.06053],"type":"Point"}
}