{
  "type": "Feature",
  "properties": {
    "gn:admin1_code":"19.0",
    "gn:admin2_code":"581.0",
    "gn:asciiname":"Tavarikere",
    "gn:country_code":"IN",
    "gn:dem":830,
    "gn:feature_class":"P",
    "gn:feature_code":"PPL",
    "gn:name":"Tavarikere",
    "gn:population":0,
    "gn:timezone":"Asia/Kolkata",
    "iso:country":"IN",
    "wof:name":"Tavarikere",
    "wof:placetype":"locality"
},
  "geometry": {"coordinates":[78.22801,12.89514],"type":"Point"}
}