{
  "type": "Feature",
  "properties": {
    "gn:admin1_code":"24",
    "gn:admin2_code":"102.0",
    "gn:asciiname":"Sandwa",
    "gn:country_code":"IN",
    "gn:dem":316,
    "gn:feature_class":"P",
    "gn:feature_code":"PPL",
    "gn:name":"S\u0101ndwa",
    "gn:population":0,
    "gn:timezone":"Asia/Kolkata",
    "iso:country":"IN",
    "name:ceb_x_preferred":[
        "S\u0101ndwa"
    ],
    "name:hin_x_preferred":[
        "\u0938\u093e\u0902\u0921\u0935\u093e"
    ],
    "name:swe_x_preferred":[
        "S\u0101ndwa"
    ],
    "name:und_x_variant":[
        "S\u0101ndwa"
    ],
    "wof:name":"Sandwa",
    "wof:placetype":"locality"
},
  "geometry": {"coordinates":[74.16842,27.75249],"type":"Point"}
}