{
  "type": "Feature",
  "properties": {
    "gn:admin1_code":"10.0",
    "gn:admin2_code":"76.0",
    "gn:asciiname":"Kheri Gujar",
    "gn:country_code":"IN",
    "gn:dem":230,
    "gn:feature_class":"P",
    "gn:feature_code":"PPL",
    "gn:name":"Kheri G\u016bjar",
    "gn:population":0,
    "gn:timezone":"Asia/Kolkata",
    "iso:country":"IN",
    "wof:name":"Kheri Gujar",
    "wof:placetype":"locality"
},
  "geometry": {"coordinates":[76.97261999999998,29.16478],"type":"Point"}
}