{
  "type": "Feature",
  "properties": {
    "iso:country":"IN",
    "ks:ks_name":"Kuroli",
    "ks:ks_pop":125,
    "ks:ks_type":"VILLAGE",
    "name:eng_x_preferred":[
        "Kuroli"
    ],
    "wof:name":"Kuroli",
    "wof:placetype":"locality",
    "wof:population":125
},
  "geometry": {"coordinates":[78.984213,26.6445],"type":"Point"}
}