{
  "type": "Feature",
  "properties": {
    "iso:country":"IN",
    "ks:ks_alt_nam":"SHEJALWASTI",
    "ks:ks_name":"Shejalwasti",
    "ks:ks_pop":234,
    "ks:ks_type":"HABITATION",
    "name:eng_x_preferred":[
        "Shejalwasti"
    ],
    "wof:name":"Shejalwasti",
    "wof:placetype":"locality",
    "wof:population":234
},
  "geometry": {"coordinates":[74.957815,17.010948],"type":"Point"}
}