{
  "type": "Feature",
  "properties": {
    "iso:country":"IN",
    "ks:ks_alt_nam":"Salaiya maneri",
    "ks:ks_name":"Salaiya Maneri",
    "ks:ks_pop":143,
    "ks:ks_type":"HABITATION",
    "name:eng_x_preferred":[
        "Salaiya Maneri"
    ],
    "wof:name":"Salaiya Maneri",
    "wof:placetype":"locality",
    "wof:population":143
},
  "geometry": {"coordinates":[79.984193,22.85187],"type":"Point"}
}