{
  "type": "Feature",
  "properties": {
    "gn:admin1_code":"34.0",
    "gn:admin2_code":"235.0",
    "gn:asciiname":"Rampur Khaira",
    "gn:country_code":"IN",
    "gn:dem":142,
    "gn:feature_class":"P",
    "gn:feature_code":"PPL",
    "gn:name":"R\u0101mpur Khair\u0101",
    "gn:population":0,
    "gn:timezone":"Asia/Kolkata",
    "iso:country":"IN",
    "ks:ks_alt_nam":"R\u0101mpur Khair\u0101",
    "ks:ks_name":"Rampur Khaira",
    "ks:ks_pop":152,
    "ks:ks_type":"VILLAGE",
    "name:eng_x_preferred":[
        "Rampur Khaira"
    ],
    "name:eng_x_variant":[
        "R\u0101mpur Khair\u0101"
    ],
    "wof:name":"Rampur Khaira",
    "wof:placetype":"locality",
    "wof:population":152
},
  "geometry": {"coordinates":[84.208101,24.606423],"type":"Point"}
}