{
  "type": "Feature",
  "properties": {
    "iso:country":"IN",
    "ks:ks_name":"Vanagaram",
    "ks:ks_pop":1212,
    "ks:ks_type":"VILLAGE",
    "ks:ks_uagg_main":0,
    "name:eng_x_preferred":[
        "Vanagaram"
    ],
    "wof:name":"Vanagaram",
    "wof:placetype":"locality",
    "wof:population":1212
},
  "geometry": {"coordinates":[80.156588,13.060785],"type":"Point"}
}