{
  "type": "Feature",
  "properties": {
    "iso:country":"IN",
    "ks:ks_name":"Shettappana Halli",
    "ks:ks_pop":34,
    "ks:ks_type":"HABITATION",
    "name:eng_x_preferred":[
        "Shettappana Halli"
    ],
    "wof:name":"Shettappana Halli",
    "wof:placetype":"locality",
    "wof:population":34
},
  "geometry": {"coordinates":[77.02208,13.232757],"type":"Point"}
}