{
  "type": "Feature",
  "properties": {
    "iso:country":"IN",
    "ks:ks_name":"Vaderamanchanahalli",
    "ks:ks_pop":717,
    "ks:ks_type":"VILLAGE",
    "ks:ks_uagg_main":0,
    "name:eng_x_preferred":[
        "Vaderamanchanahalli"
    ],
    "wof:name":"Vaderamanchanahalli",
    "wof:placetype":"locality",
    "wof:population":717
},
  "geometry": {"coordinates":[77.63055,12.768713],"type":"Point"}
}