{
  "type": "Feature",
  "properties": {
    "iso:country":"IN",
    "ks:ks_name":"Gara Gachha",
    "ks:ks_pop":1101,
    "ks:ks_type":"VILLAGE",
    "name:eng_x_preferred":[
        "Gara Gachha"
    ],
    "wof:name":"Gara Gachha",
    "wof:placetype":"locality",
    "wof:population":1101
},
  "geometry": {"coordinates":[88.606534,22.582603],"type":"Point"}
}