{
  "type": "Feature",
  "properties": {
    "iso:country":"IN",
    "ks:ks_name":"Kottavur",
    "ks:ks_pop":424,
    "ks:ks_type":"HABITATION",
    "ks:ks_uagg_main":0,
    "name:eng_x_preferred":[
        "Kottavur"
    ],
    "wof:name":"Kottavur",
    "wof:placetype":"neighbourhood",
    "wof:population":424
},
  "geometry": {"coordinates":[78.326227,12.270162],"type":"Point"}
}