{
  "type": "Feature",
  "properties": {
    "iso:country":"IN",
    "ks:ks_name":"M Ammappatti",
    "ks:ks_pop":325,
    "ks:ks_type":"HABITATION",
    "name:eng_x_preferred":[
        "M Ammappatti"
    ],
    "wof:name":"M Ammappatti",
    "wof:placetype":"locality",
    "wof:population":325
},
  "geometry": {"coordinates":[78.459182,10.391445],"type":"Point"}
}