{
  "type": "Feature",
  "properties": {
    "gn:admin1_code":"11.0",
    "gn:admin2_code":"26.0",
    "gn:asciiname":"Pakora",
    "gn:country_code":"IN",
    "gn:dem":2485,
    "gn:feature_class":"P",
    "gn:feature_code":"PPL",
    "gn:name":"Pakora",
    "gn:population":0,
    "gn:timezone":"Asia/Kolkata",
    "iso:country":"IN",
    "name:ben_x_preferred":[
        "\u09aa\u09be\u0995\u09cb\u09a1\u09bc\u09be"
    ],
    "name:cat_x_preferred":[
        "Pakora"
    ],
    "name:ceb_x_preferred":[
        "Pako\u1e5b\u0101"
    ],
    "name:deu_x_preferred":[
        "Pakora"
    ],
    "name:epo_x_preferred":[
        "Pakoro"
    ],
    "name:fas_x_preferred":[
        "\u067e\u0627\u06a9\u0648\u0631\u0647"
    ],
    "name:fra_x_preferred":[
        "Pakora"
    ],
    "name:guj_x_preferred":[
        "\u0aaa\u0a95\u0acb\u0aa1\u0ac0"
    ],
    "name:heb_x_preferred":[
        "\u05e4\u05e7\u05d5\u05e8\u05d4"
    ],
    "name:hin_x_preferred":[
        "\u092a\u0915\u094b\u0921\u093c\u093e"
    ],
    "name:ita_x_preferred":[
        "Pakora"
    ],
    "name:jpn_x_preferred":[
        "\u30d1\u30b3\u30e9"
    ],
    "name:kan_x_preferred":[
        "\u0caa\u0c95\u0ccb\u0ca1\u0cbe"
    ],
    "name:kor_x_preferred":[
        "\ud30c\ucf54\ub77c"
    ],
    "name:lit_x_preferred":[
        "Pakora"
    ],
    "name:mal_x_preferred":[
        "\u0d2a\u0d15\u0d4b\u0d21"
    ],
    "name:nld_x_preferred":[
        "Pakora"
    ],
    "name:nno_x_preferred":[
        "Pakora"
    ],
    "name:nor_x_preferred":[
        "Pakora"
    ],
    "name:ori_x_preferred":[
        "\u0b2a\u0b15\u0b4b\u0b21\u0b3c\u0b3e"
    ],
    "name:pan_x_preferred":[
        "\u0a2a\u0a24\u0a4c\u0a5c"
    ],
    "name:pnb_x_preferred":[
        "\u067e\u06a9\u0648\u0691\u0627"
    ],
    "name:pol_x_preferred":[
        "Pakora"
    ],
    "name:por_x_preferred":[
        "Pakora"
    ],
    "name:ron_x_preferred":[
        "Pakora"
    ],
    "name:sat_x_preferred":[
        "\u1c6f\u1c5a\u1c60\u1c73\u1c72\u1c5f"
    ],
    "name:sco_x_preferred":[
        "Pakora"
    ],
    "name:snd_x_preferred":[
        "\u067e\u06aa\u0648\u0699\u0648"
    ],
    "name:spa_x_preferred":[
        "Pakora"
    ],
    "name:tam_x_preferred":[
        "\u0baa\u0b95\u0bcd\u0b95\u0bcb\u0bb0\u0bbe"
    ],
    "name:tel_x_preferred":[
        "\u0c2a\u0c15\u0c4b\u0c21\u0c40"
    ],
    "name:urd_x_preferred":[
        "\u067e\u06a9\u0648\u0691\u0627"
    ],
    "name:vie_x_preferred":[
        "Pakora"
    ],
    "wof:name":"Pakora",
    "wof:placetype":"locality"
},
  "geometry": {"coordinates":[77.58824,31.5043],"type":"Point"}
}