{
  "type": "Feature",
  "properties": {
    "iso:country":"IN",
    "ks:ks_name":"Bouserkuti",
    "ks:ks_pop":1545,
    "ks:ks_type":"VILLAGE",
    "name:eng_x_preferred":[
        "Bouserkuti"
    ],
    "wof:name":"Bouserkuti",
    "wof:placetype":"locality",
    "wof:population":1545
},
  "geometry": {"coordinates":[89.71260700000001,26.257623],"type":"Point"}
}