{
  "type": "Feature",
  "properties": {
    "iso:country":"IN",
    "ks:ks_alt_nam":"Basveshwar nagar",
    "ks:ks_name":"Basveshwar Nagar",
    "ks:ks_pop":145,
    "ks:ks_type":"HABITATION",
    "name:eng_x_preferred":[
        "Basveshwar Nagar"
    ],
    "wof:name":"Basveshwar Nagar",
    "wof:placetype":"locality",
    "wof:population":145
},
  "geometry": {"coordinates":[76.273352,17.623306],"type":"Point"}
}