{
  "type": "Feature",
  "properties": {
    "iso:country":"IN",
    "ks:ks_name":"Machakulam",
    "ks:ks_pop":812,
    "ks:ks_type":"HABITATION",
    "ks:ks_uagg_main":0,
    "name:eng_x_preferred":[
        "Machakulam"
    ],
    "wof:name":"Machakulam",
    "wof:placetype":"neighbourhood",
    "wof:population":812
},
  "geometry": {"coordinates":[75.848139,11.335653],"type":"Point"}
}