{
  "type": "Feature",
  "properties": {
    "iso:country":"IN",
    "ks:ks_name":"Bhauratoli",
    "ks:ks_pop":100,
    "ks:ks_type":"HABITATION",
    "name:eng_x_preferred":[
        "Bhauratoli"
    ],
    "wof:name":"Bhauratoli",
    "wof:placetype":"locality",
    "wof:population":100
},
  "geometry": {"coordinates":[85.02767,23.125497],"type":"Point"}
}