{
  "type": "Feature",
  "properties": {
    "iso:country":"IN",
    "ks:ks_name":"Hardiha Khurd",
    "ks:ks_pop":60,
    "ks:ks_type":"VILLAGE",
    "name:eng_x_preferred":[
        "Hardiha Khurd"
    ],
    "wof:name":"Hardiha Khurd",
    "wof:placetype":"locality",
    "wof:population":60
},
  "geometry": {"coordinates":[81.40479000000001,23.50883],"type":"Point"}
}