{
  "type": "Feature",
  "properties": {
    "iso:country":"IN",
    "name:bpy_x_preferred":[
        "\u0993 \u09ad\u09c7\u09b2\u09c0"
    ],
    "name:chi_x_preferred":[
        "\u5965\u74e6\u83b1\u4f0a"
    ],
    "name:dut_x_preferred":[
        "O' Valley"
    ],
    "name:eng_x_preferred":[
        "O' Valley"
    ],
    "name:ita_x_preferred":[
        "O' Valley"
    ],
    "name:may_x_preferred":[
        "O' Valley"
    ],
    "name:mlg_x_preferred":[
        "O' Valley"
    ],
    "name:nan_x_preferred":[
        "O' Valley"
    ],
    "name:ori_x_preferred":[
        "\u0b13' \u0b2d\u0b4d\u0b5f\u0b3e\u0b32\u0b3f"
    ],
    "name:por_x_preferred":[
        "O' Valley"
    ],
    "name:tam_x_preferred":[
        "\u0b93.\u0bb5\u0bc7\u0bb2\u0bbf"
    ],
    "name:urd_x_preferred":[
        "\u0627\u0648 \u0648\u06cc\u0644\u06cc"
    ],
    "name:vie_x_preferred":[
        "O' Valley"
    ],
    "qs:name":"O' Valley",
    "qs:name_adm0":"India",
    "qs:name_adm1":"Tamil Nadu",
    "qs:photos":31,
    "qs:photos_1k":6,
    "qs:photos_9k":1,
    "qs:photos_9r":2,
    "qs:photos_all":31,
    "qs:photos_sr":2,
    "qs:placetype":"Town",
    "qs:pop_sr":"0",
    "wd:wordcount":121,
    "wof:name":"O' Valley",
    "wof:placetype":"locality"
},
  "geometry": {"coordinates":[76.392059,11.662323],"type":"Point"}
}