{
  "type": "Feature",
  "properties": {
    "iso:country":"IN",
    "ks:ks_name":"Chandrwani Khalsa",
    "ks:ks_pop":1213,
    "ks:ks_type":"VILLAGE",
    "ks:ks_uagg_main":0,
    "name:eng_x_preferred":[
        "Chandrwani Khalsa"
    ],
    "wof:name":"Chandrwani Khalsa",
    "wof:placetype":"locality",
    "wof:population":1213
},
  "geometry": {"coordinates":[77.98475000000001,30.285769],"type":"Point"}
}