{
  "type": "Feature",
  "properties": {
    "iso:country":"IN",
    "ks:ks_name":"Bhabhor Falia",
    "ks:ks_pop":327,
    "ks:ks_type":"HABITATION",
    "name:eng_x_preferred":[
        "Bhabhor Falia"
    ],
    "wof:name":"Bhabhor Falia",
    "wof:placetype":"locality",
    "wof:population":327
},
  "geometry": {"coordinates":[74.086778,23.217694],"type":"Point"}
}