{
  "type": "Feature",
  "properties": {
    "iso:country":"IN",
    "ks:ks_alt_nam":"tavilkoppa",
    "ks:ks_name":"Tavilkoppa",
    "ks:ks_pop":112,
    "ks:ks_type":"HABITATION",
    "name:eng_x_preferred":[
        "Tavilkoppa"
    ],
    "wof:name":"Tavilkoppa",
    "wof:placetype":"locality",
    "wof:population":112
},
  "geometry": {"coordinates":[74.966483,14.719165],"type":"Point"}
}