{
  "type": "Feature",
  "properties": {
    "iso:country":"IN",
    "ks:ks_name":"Mamillagudem",
    "ks:ks_pop":324,
    "ks:ks_type":"HABITATION",
    "name:eng_x_preferred":[
        "Mamillagudem"
    ],
    "wof:name":"Mamillagudem",
    "wof:placetype":"locality",
    "wof:population":324
},
  "geometry": {"coordinates":[80.780244,17.443358],"type":"Point"}
}