{
  "type": "Feature",
  "properties": {
    "iso:country":"IN",
    "ks:ks_alt_nam":"NAWATOLI",
    "ks:ks_name":"Nawatoli",
    "ks:ks_pop":256,
    "ks:ks_type":"HABITATION",
    "name:eng_x_preferred":[
        "Nawatoli"
    ],
    "wof:name":"Nawatoli",
    "wof:placetype":"locality",
    "wof:population":256
},
  "geometry": {"coordinates":[83.74996,22.735347],"type":"Point"}
}