{
  "type": "Feature",
  "properties": {
    "iso:country":"IN",
    "ks:ks_name":"Karadkhaman",
    "ks:ks_pop":46,
    "ks:ks_type":"HABITATION",
    "name:eng_x_preferred":[
        "Karadkhaman"
    ],
    "wof:name":"Karadkhaman",
    "wof:placetype":"locality",
    "wof:population":46
},
  "geometry": {"coordinates":[85.205731,21.111247],"type":"Point"}
}