{
  "type": "Feature",
  "properties": {
    "iso:country":"IN",
    "ks:ks_alt_nam":"RangappagariPalle",
    "ks:ks_name":"Rangappagaripalle",
    "ks:ks_pop":40,
    "ks:ks_type":"HABITATION",
    "name:eng_x_preferred":[
        "Rangappagaripalle"
    ],
    "wof:name":"Rangappagaripalle",
    "wof:placetype":"locality",
    "wof:population":40
},
  "geometry": {"coordinates":[78.72581,13.872683],"type":"Point"}
}