{
  "type": "Feature",
  "properties": {
    "gn:admin1_code":"39.0",
    "gn:admin2_code":"57.0",
    "gn:asciiname":"Bosrakhet",
    "gn:country_code":"IN",
    "gn:dem":1404,
    "gn:feature_class":"P",
    "gn:feature_code":"PPL",
    "gn:name":"Bosr\u0101khet",
    "gn:population":0,
    "gn:timezone":"Asia/Kolkata",
    "iso:country":"IN",
    "ks:ks_alt_nam":"Bosr\u0101khet",
    "ks:ks_name":"Bosrakhet",
    "ks:ks_pop":173,
    "ks:ks_type":"VILLAGE",
    "name:eng_x_preferred":[
        "Bosrakhet"
    ],
    "name:eng_x_variant":[
        "Bosr\u0101khet"
    ],
    "wof:name":"Bosrakhet",
    "wof:placetype":"locality",
    "wof:population":173
},
  "geometry": {"coordinates":[79.321111,29.997472],"type":"Point"}
}