{
  "type": "Feature",
  "properties": {
    "gn:admin1_code":"10.0",
    "gn:admin2_code":"072",
    "gn:asciiname":"Partapgarh",
    "gn:country_code":"IN",
    "gn:dem":258,
    "gn:feature_class":"P",
    "gn:feature_code":"PPL",
    "gn:name":"Partapgarh",
    "gn:population":0,
    "gn:timezone":"Asia/Kolkata",
    "iso:country":"IN",
    "name:und_x_variant":[
        "Part\u0101pgart"
    ],
    "wof:name":"Partapgarh",
    "wof:placetype":"locality"
},
  "geometry": {"coordinates":[76.87536,29.99048],"type":"Point"}
}