{
  "type": "Feature",
  "properties": {
    "gn:admin1_code":"12.0",
    "gn:admin2_code":"2.0",
    "gn:asciiname":"Hajan",
    "gn:country_code":"IN",
    "gn:dem":2302,
    "gn:feature_class":"P",
    "gn:feature_code":"PPL",
    "gn:name":"Hajan",
    "gn:population":0,
    "gn:timezone":"Asia/Kolkata",
    "iso:country":"IN",
    "name:bpy_x_preferred":[
        "\u09b9\u09be\u099c\u09a8"
    ],
    "name:ceb_x_preferred":[
        "H\u0101jan"
    ],
    "name:ita_x_preferred":[
        "Hajan"
    ],
    "name:mlg_x_preferred":[
        "Hajan"
    ],
    "name:msa_x_preferred":[
        "Hajan"
    ],
    "name:new_x_preferred":[
        "\u0939\u091c\u0928"
    ],
    "name:nld_x_preferred":[
        "Hajan"
    ],
    "name:por_x_preferred":[
        "Hajan"
    ],
    "name:spa_x_preferred":[
        "Hajan"
    ],
    "name:swe_x_preferred":[
        "H\u0101jan"
    ],
    "name:vie_x_preferred":[
        "Hajan"
    ],
    "wof:name":"Hajan",
    "wof:placetype":"locality"
},
  "geometry": {"coordinates":[74.64981999999998,33.85774],"type":"Point"}
}