{
  "type": "Feature",
  "properties": {
    "iso:country":"IN",
    "ks:ks_alt_nam":"Harijan Tola ravidas tola",
    "ks:ks_name":"Harijan Tola Ravidas Tola",
    "ks:ks_pop":231,
    "ks:ks_type":"HABITATION",
    "name:eng_x_preferred":[
        "Harijan Tola Ravidas Tola"
    ],
    "wof:name":"Harijan Tola Ravidas Tola",
    "wof:placetype":"locality",
    "wof:population":231
},
  "geometry": {"coordinates":[85.31513699999999,24.375384],"type":"Point"}
}