{
  "type": "Feature",
  "properties": {
    "iso:country":"IN",
    "ks:ks_name":"Godasar",
    "ks:ks_pop":73,
    "ks:ks_type":"VILLAGE",
    "name:eng_x_preferred":[
        "Godasar"
    ],
    "wof:name":"Godasar",
    "wof:placetype":"locality",
    "wof:population":73
},
  "geometry": {"coordinates":[72.538662,26.283138],"type":"Point"}
}