{
  "type": "Feature",
  "properties": {
    "iso:country":"IN",
    "ks:ks_name":"Partapur",
    "ks:ks_pop":1012,
    "ks:ks_type":"VILLAGE",
    "ks:ks_uagg_main":0,
    "name:eng_x_preferred":[
        "Partapur"
    ],
    "wof:name":"Partapur",
    "wof:placetype":"neighbourhood",
    "wof:population":1012
},
  "geometry": {"coordinates":[85.441874,26.449571],"type":"Point"}
}