{
  "type": "Feature",
  "properties": {
    "iso:country":"IN",
    "ks:ks_name":"Station Falia",
    "ks:ks_pop":150,
    "ks:ks_type":"HABITATION",
    "name:eng_x_preferred":[
        "Station Falia"
    ],
    "wof:name":"Station Falia",
    "wof:placetype":"locality",
    "wof:population":150
},
  "geometry": {"coordinates":[73.412611,20.807694],"type":"Point"}
}