{
  "type": "Feature",
  "properties": {
    "iso:country":"IN",
    "ks:ks_alt_nam":"Jagan purwa",
    "ks:ks_name":"Jagan Purwa",
    "ks:ks_pop":135,
    "ks:ks_type":"HABITATION",
    "name:eng_x_preferred":[
        "Jagan Purwa"
    ],
    "wof:name":"Jagan Purwa",
    "wof:placetype":"locality",
    "wof:population":135
},
  "geometry": {"coordinates":[81.482473,27.314225],"type":"Point"}
}