{
  "type": "Feature",
  "properties": {
    "iso:country":"IN",
    "ks:ks_name":"Loonkhan",
    "ks:ks_pop":993,
    "ks:ks_type":"VILLAGE",
    "name:eng_x_preferred":[
        "Loonkhan"
    ],
    "wof:name":"Loonkhan",
    "wof:placetype":"locality",
    "wof:population":993
},
  "geometry": {"coordinates":[72.945886,28.672986],"type":"Point"}
}