{
  "type": "Feature",
  "properties": {
    "gn:admin1_code":"35",
    "gn:admin2_code":"456.0",
    "gn:asciiname":"Dhenki",
    "gn:country_code":"IN",
    "gn:dem":615,
    "gn:feature_class":"P",
    "gn:feature_code":"PPL",
    "gn:name":"Dhenki",
    "gn:population":0,
    "gn:timezone":"Asia/Kolkata",
    "iso:country":"IN",
    "name:ori_x_preferred":[
        "\u0b22\u0b3f\u0b19\u0b4d\u0b15\u0b3f"
    ],
    "name:sat_x_preferred":[
        "\u1c70\u1c77\u1c64\u1c5d\u1c60\u1c64"
    ],
    "wof:name":"Dhenki",
    "wof:placetype":"locality"
},
  "geometry": {"coordinates":[79.49914,22.12153],"type":"Point"}
}