{
  "type": "Feature",
  "properties": {
    "iso:country":"IN",
    "ks:ks_name":"Maningeri",
    "ks:ks_pop":115,
    "ks:ks_type":"HABITATION",
    "name:eng_x_preferred":[
        "Maningeri"
    ],
    "wof:name":"Maningeri",
    "wof:placetype":"locality",
    "wof:population":115
},
  "geometry": {"coordinates":[75.41256799999999,12.927335],"type":"Point"}
}