{
  "type": "Feature",
  "properties": {
    "iso:country":"IN",
    "ks:ks_name":"Mawali Guda Para",
    "ks:ks_pop":563,
    "ks:ks_type":"HABITATION",
    "ks:ks_uagg_main":0,
    "name:eng_x_preferred":[
        "Mawali Guda Para"
    ],
    "wof:name":"Mawali Guda Para",
    "wof:placetype":"neighbourhood",
    "wof:population":563
},
  "geometry": {"coordinates":[81.828003,19.361728],"type":"Point"}
}