{
  "type": "Feature",
  "properties": {
    "gn:admin1_code":"35.0",
    "gn:admin2_code":"442.0",
    "gn:asciiname":"Lasurli",
    "gn:country_code":"IN",
    "gn:dem":433,
    "gn:feature_class":"P",
    "gn:feature_code":"PPL",
    "gn:name":"Las\u016brli",
    "gn:population":0,
    "gn:timezone":"Asia/Kolkata",
    "iso:country":"IN",
    "wof:name":"Lasurli",
    "wof:placetype":"locality"
},
  "geometry": {"coordinates":[76.96498000000003,23.80771],"type":"Point"}
}