{
  "type": "Feature",
  "properties": {
    "gn:admin1_code":"38.0",
    "gn:admin2_code":"348.0",
    "gn:asciiname":"Arapagar",
    "gn:country_code":"IN",
    "gn:dem":391,
    "gn:feature_class":"P",
    "gn:feature_code":"PPL",
    "gn:name":"Arapag\u0101r",
    "gn:population":0,
    "gn:timezone":"Asia/Kolkata",
    "iso:country":"IN",
    "wof:name":"Arapagar",
    "wof:placetype":"locality"
},
  "geometry": {"coordinates":[85.33389,24.35106],"type":"Point"}
}