{
  "type": "Feature",
  "properties": {
    "gn:admin1_code":"35.0",
    "gn:admin2_code":"425.0",
    "gn:asciiname":"Bandha",
    "gn:country_code":"IN",
    "gn:dem":329,
    "gn:feature_class":"P",
    "gn:feature_code":"PPL",
    "gn:name":"Bandha",
    "gn:population":0,
    "gn:timezone":"Asia/Kolkata",
    "iso:country":"IN",
    "ks:ks_name":"Bandha",
    "ks:ks_pop":2308,
    "ks:ks_type":"VILLAGE",
    "name:eng_x_preferred":[
        "Bandha"
    ],
    "wof:name":"Bandha",
    "wof:placetype":"locality",
    "wof:population":2308
},
  "geometry": {"coordinates":[79.103403,24.55331],"type":"Point"}
}