{
  "type": "Feature",
  "properties": {
    "iso:country":"IN",
    "ks:ks_name":"Gondiguda",
    "ks:ks_pop":114,
    "ks:ks_type":"HABITATION",
    "name:eng_x_preferred":[
        "Gondiguda"
    ],
    "wof:name":"Gondiguda",
    "wof:placetype":"locality",
    "wof:population":114
},
  "geometry": {"coordinates":[82.73044,18.286086],"type":"Point"}
}