{
  "type": "Feature",
  "properties": {
    "iso:country":"IN",
    "ks:ks_name":"Karkapara",
    "ks:ks_pop":133,
    "ks:ks_type":"HABITATION",
    "name:eng_x_preferred":[
        "Karkapara"
    ],
    "wof:name":"Karkapara",
    "wof:placetype":"locality",
    "wof:population":133
},
  "geometry": {"coordinates":[81.103346,18.5229],"type":"Point"}
}