{
  "type": "Feature",
  "properties": {
    "iso:country":"IN",
    "ks:ks_name":"25 MJD",
    "ks:ks_pop":148,
    "ks:ks_type":"VILLAGE",
    "name:eng_x_preferred":[
        "25 MJD"
    ],
    "wof:name":"25 MJD",
    "wof:placetype":"locality",
    "wof:population":148
},
  "geometry": {"coordinates":[74.178308,29.779069],"type":"Point"}
}