{
  "type": "Feature",
  "properties": {
    "iso:country":"IN",
    "ks:ks_name":"Unda",
    "ks:ks_pop":166,
    "ks:ks_type":"HABITATION",
    "name:eng_x_preferred":[
        "Unda"
    ],
    "wof:name":"Unda",
    "wof:placetype":"locality",
    "wof:population":166
},
  "geometry": {"coordinates":[82.357597,20.399723],"type":"Point"}
}