{
  "type": "Feature",
  "properties": {
    "gn:admin1_code":"36",
    "gn:admin2_code":"154.0",
    "gn:asciiname":"Purwa Manu Singh",
    "gn:country_code":"IN",
    "gn:dem":120,
    "gn:feature_class":"P",
    "gn:feature_code":"PPL",
    "gn:name":"Purwa Manu Singh",
    "gn:population":0,
    "gn:timezone":"Asia/Kolkata",
    "iso:country":"IN",
    "wof:name":"Purwa Manu Singh",
    "wof:placetype":"neighbourhood"
},
  "geometry": {"coordinates":[81.25839999999999,27.54754],"type":"Point"}
}