{
  "type": "Feature",
  "properties": {
    "gn:admin1_code":"25.0",
    "gn:admin2_code":"604.0",
    "gn:asciiname":"Tenambakkam",
    "gn:country_code":"IN",
    "gn:dem":79,
    "gn:feature_class":"P",
    "gn:feature_code":"PPL",
    "gn:name":"Tenamb\u0101kkam",
    "gn:population":0,
    "gn:timezone":"Asia/Kolkata",
    "iso:country":"IN",
    "ks:ks_alt_nam":"Tenamb\u0101kkam",
    "ks:ks_name":"Tenambakkam",
    "ks:ks_type":"VILLAGE",
    "ks:ks_uagg_main":0,
    "name:eng_x_preferred":[
        "Tenambakkam"
    ],
    "name:eng_x_variant":[
        "Tenamb\u0101kkam"
    ],
    "wof:name":"Tenambakkam",
    "wof:placetype":"neighbourhood"
},
  "geometry": {"coordinates":[79.734104,12.810221],"type":"Point"}
}