{
  "type": "Feature",
  "properties": {
    "iso:country":"IN",
    "ks:ks_name":"Burkapara",
    "ks:ks_pop":150,
    "ks:ks_type":"HABITATION",
    "name:eng_x_preferred":[
        "Burkapara"
    ],
    "wof:name":"Burkapara",
    "wof:placetype":"locality",
    "wof:population":150
},
  "geometry": {"coordinates":[81.489512,18.910557],"type":"Point"}
}