{
  "type": "Feature",
  "properties": {
    "gn:admin1_code":"28.0",
    "gn:admin2_code":"341.0",
    "gn:asciiname":"Paschimpara",
    "gn:country_code":"IN",
    "gn:dem":7,
    "gn:feature_class":"P",
    "gn:feature_code":"PPL",
    "gn:name":"Paschimpara",
    "gn:population":0,
    "gn:timezone":"Asia/Kolkata",
    "iso:country":"IN",
    "wof:name":"Paschimpara",
    "wof:placetype":"neighbourhood"
},
  "geometry": {"coordinates":[88.22908000000002,22.54164],"type":"Point"}
}