{
  "type": "Feature",
  "properties": {
    "iso:country":"IN",
    "ks:ks_name":"Bantar",
    "ks:ks_pop":143,
    "ks:ks_type":"HABITATION",
    "name:eng_x_preferred":[
        "Bantar"
    ],
    "wof:name":"Bantar",
    "wof:placetype":"locality",
    "wof:population":143
},
  "geometry": {"coordinates":[81.603651,24.846534],"type":"Point"}
}