{
  "type": "Feature",
  "properties": {
    "gn:admin1_code":"34.0",
    "gn:admin2_code":"211.0",
    "gn:asciiname":"Dhokardhara",
    "gn:country_code":"IN",
    "gn:dem":49,
    "gn:feature_class":"P",
    "gn:feature_code":"PPL",
    "gn:name":"Dhokardh\u0101ra",
    "gn:population":0,
    "gn:timezone":"Asia/Kolkata",
    "iso:country":"IN",
    "ks:ks_name":"Dhokardhara",
    "ks:ks_pop":801,
    "ks:ks_type":"VILLAGE",
    "name:eng_x_preferred":[
        "Dhokardhara"
    ],
    "wof:name":"Dhokardhara",
    "wof:placetype":"locality",
    "wof:population":801
},
  "geometry": {"coordinates":[87.203965,25.881509],"type":"Point"}
}