{
  "type": "Feature",
  "properties": {
    "iso:country":"IN",
    "ks:ks_name":"Jamdahi",
    "ks:ks_pop":1328,
    "ks:ks_type":"VILLAGE",
    "name:eng_x_preferred":[
        "Jamdahi"
    ],
    "wof:name":"Jamdahi",
    "wof:placetype":"locality",
    "wof:population":1328
},
  "geometry": {"coordinates":[86.972204,23.948828],"type":"Point"}
}