{
  "type": "Feature",
  "properties": {
    "gn:admin1_code":"19.0",
    "gn:admin2_code":"568.0",
    "gn:asciiname":"Malur",
    "gn:country_code":"IN",
    "gn:dem":587,
    "gn:feature_class":"P",
    "gn:feature_code":"PPL",
    "gn:name":"Mal\u016br",
    "gn:population":0,
    "gn:timezone":"Asia/Kolkata",
    "iso:country":"IN",
    "ks:ks_name":"Maluru",
    "ks:ks_pop":53,
    "ks:ks_type":"VILLAGE",
    "name:ben_x_preferred":[
        "\u09ae\u09be\u09b2\u09c1\u09b0"
    ],
    "name:bpy_x_preferred":[
        "\u09ae\u09be\u09b2\u09c1\u09b0"
    ],
    "name:ceb_x_preferred":[
        "M\u0101l\u016br"
    ],
    "name:eng_x_preferred":[
        "Maluru"
    ],
    "name:eng_x_variant":[
        "Malur"
    ],
    "name:ita_x_preferred":[
        "Malur"
    ],
    "name:kan_x_preferred":[
        "\u0cae\u0cbe\u0cb2\u0cc2\u0cb0\u0cc1"
    ],
    "name:mlg_x_preferred":[
        "Malur"
    ],
    "name:msa_x_preferred":[
        "Malur"
    ],
    "name:new_x_preferred":[
        "\u092e\u0932\u0941\u0930"
    ],
    "name:nld_x_preferred":[
        "Malur"
    ],
    "name:ori_x_preferred":[
        "\u0b2e\u0b3e\u0b32\u0b41\u0b30\u0b4d"
    ],
    "name:spa_x_preferred":[
        "Malur"
    ],
    "name:swe_x_preferred":[
        "M\u0101l\u016br"
    ],
    "name:urd_x_preferred":[
        "\u0645\u0644\u0648\u0631"
    ],
    "name:vie_x_preferred":[
        "Malur"
    ],
    "name:zho_x_preferred":[
        "\u9a6c\u5362\u5c14"
    ],
    "wof:name":"Maluru",
    "wof:placetype":"locality",
    "wof:population":53
},
  "geometry": {"coordinates":[74.83959900000001,13.963951],"type":"Point"}
}