{
  "type": "Feature",
  "properties": {
    "gn:admin1_code":"36",
    "gn:admin2_code":"173.0",
    "gn:asciiname":"Fatehshahpur",
    "gn:country_code":"IN",
    "gn:dem":110,
    "gn:feature_class":"P",
    "gn:feature_code":"PPL",
    "gn:name":"Fatehshahpur",
    "gn:population":0,
    "gn:timezone":"Asia/Kolkata",
    "iso:country":"IN",
    "wof:name":"Fatehshahpur",
    "wof:placetype":"locality"
},
  "geometry": {"coordinates":[81.5264,25.83234],"type":"Point"}
}