{
  "type": "Feature",
  "properties": {
    "gn:admin1_code":"36",
    "gn:admin2_code":"173.0",
    "gn:asciiname":"Fatehshahpur",
    "gn:country_code":"IN",
    "gn:dem":110,
    "gn:feature_class":"P",
    "gn:feature_code":"PPL",
    "gn:name":"Fatehshahpur",
    "gn:population":0,
    "gn:timezone":"Asia/Kolkata",
    "iso:country":"IN",
    "ks:ks_name":"Fatte Shahpur",
    "ks:ks_pop":481,
    "ks:ks_type":"VILLAGE",
    "name:eng_x_preferred":[
        "Fatte Shahpur"
    ],
    "name:eng_x_variant":[
        "Fatehshahpur"
    ],
    "wof:name":"Fatte Shahpur",
    "wof:placetype":"locality",
    "wof:population":481
},
  "geometry": {"coordinates":[81.530096,25.83139],"type":"Point"}
}