{
  "type": "Feature",
  "properties": {
    "iso:country":"IN",
    "ks:ks_alt_nam":"NAGREMALA",
    "ks:ks_name":"Nagremala",
    "ks:ks_pop":67,
    "ks:ks_type":"HABITATION",
    "name:eng_x_preferred":[
        "Nagremala"
    ],
    "wof:name":"Nagremala",
    "wof:placetype":"locality",
    "wof:population":67
},
  "geometry": {"coordinates":[74.822012,17.116148],"type":"Point"}
}