{
  "type": "Feature",
  "properties": {
    "gn:admin1_code":"39",
    "gn:admin2_code":"61.0",
    "gn:asciiname":"Molkhandi",
    "gn:country_code":"IN",
    "gn:dem":1199,
    "gn:feature_class":"P",
    "gn:feature_code":"PPL",
    "gn:name":"Molkhandi",
    "gn:population":0,
    "gn:timezone":"Asia/Kolkata",
    "iso:country":"IN",
    "wof:name":"Molkhandi",
    "wof:placetype":"locality"
},
  "geometry": {"coordinates":[78.76403000000001,30.17238],"type":"Point"}
}