{
  "type": "Feature",
  "properties": {
    "iso:country":"IN",
    "ks:ks_alt_nam":"MALIPARA",
    "ks:ks_name":"Malipara",
    "ks:ks_pop":649,
    "ks:ks_type":"HABITATION",
    "name:eng_x_preferred":[
        "Malipara"
    ],
    "wof:name":"Malipara",
    "wof:placetype":"locality",
    "wof:population":649
},
  "geometry": {"coordinates":[88.803979,26.477434],"type":"Point"}
}