{
  "type": "Feature",
  "properties": {
    "iso:country":"IN",
    "ks:ks_name":"Kothagadda",
    "ks:ks_pop":82,
    "ks:ks_type":"HABITATION",
    "name:eng_x_preferred":[
        "Kothagadda"
    ],
    "wof:name":"Kothagadda",
    "wof:placetype":"locality",
    "wof:population":82
},
  "geometry": {"coordinates":[78.364355,13.441854],"type":"Point"}
}