{
  "type": "Feature",
  "properties": {
    "gn:admin1_code":"10.0",
    "gn:admin2_code":"72.0",
    "gn:asciiname":"Samalka",
    "gn:country_code":"IN",
    "gn:dem":263,
    "gn:feature_class":"P",
    "gn:feature_code":"PPL",
    "gn:name":"Sam\u0101lka",
    "gn:population":0,
    "gn:timezone":"Asia/Kolkata",
    "iso:country":"IN",
    "wof:name":"Samalka",
    "wof:placetype":"locality"
},
  "geometry": {"coordinates":[77.07141,30.00868],"type":"Point"}
}