{
  "type": "Feature",
  "properties": {
    "iso:country":"IN",
    "ks:ks_name":"Balakatta Moodukodi",
    "ks:ks_pop":234,
    "ks:ks_type":"HABITATION",
    "name:eng_x_preferred":[
        "Balakatta Moodukodi"
    ],
    "wof:name":"Balakatta Moodukodi",
    "wof:placetype":"locality",
    "wof:population":234
},
  "geometry": {"coordinates":[74.814261,13.328181],"type":"Point"}
}