{
  "type": "Feature",
  "properties": {
    "gn:admin1_code":"11",
    "gn:admin2_code":"23.0",
    "gn:asciiname":"Patanghala",
    "gn:country_code":"IN",
    "gn:dem":2052,
    "gn:feature_class":"P",
    "gn:feature_code":"PPL",
    "gn:name":"Patangh\u0101la",
    "gn:population":0,
    "gn:timezone":"Asia/Kolkata",
    "iso:country":"IN",
    "wof:name":"Patanghala",
    "wof:placetype":"locality"
},
  "geometry": {"coordinates":[76.58036,32.44893],"type":"Point"}
}