{
  "type": "Feature",
  "properties": {
    "iso:country":"IN",
    "ks:ks_name":"Bhatatambedi",
    "ks:ks_pop":197,
    "ks:ks_type":"VILLAGE",
    "name:eng_x_preferred":[
        "Bhatatambedi"
    ],
    "wof:name":"Bhatatambedi",
    "wof:placetype":"locality",
    "wof:population":197
},
  "geometry": {"coordinates":[83.309327,19.034879],"type":"Point"}
}