{
  "type": "Feature",
  "properties": {
    "iso:country":"IN",
    "ks:ks_name":"Dattawadi",
    "ks:ks_pop":246,
    "ks:ks_type":"HABITATION",
    "name:eng_x_preferred":[
        "Dattawadi"
    ],
    "wof:name":"Dattawadi",
    "wof:placetype":"locality",
    "wof:population":246
},
  "geometry": {"coordinates":[73.533576,17.468264],"type":"Point"}
}