{
  "type": "Feature",
  "properties": {
    "gn:admin1_code":"34.0",
    "gn:admin2_code":"212.0",
    "gn:asciiname":"Lalia",
    "gn:country_code":"IN",
    "gn:dem":37,
    "gn:feature_class":"P",
    "gn:feature_code":"PPL",
    "gn:name":"Lalia",
    "gn:population":0,
    "gn:timezone":"Asia/Kolkata",
    "iso:country":"IN",
    "name:ceb_x_preferred":[
        "Lalia"
    ],
    "name:deu_x_preferred":[
        "Lalia"
    ],
    "wof:name":"Lalia",
    "wof:placetype":"neighbourhood"
},
  "geometry": {"coordinates":[87.34344,25.58171],"type":"Point"}
}