{
  "type": "Feature",
  "properties": {
    "iso:country":"IN",
    "ks:ks_name":"Kerethotta",
    "ks:ks_pop":60,
    "ks:ks_type":"HABITATION",
    "name:eng_x_preferred":[
        "Kerethotta"
    ],
    "wof:name":"Kerethotta",
    "wof:placetype":"locality",
    "wof:population":60
},
  "geometry": {"coordinates":[75.305969,13.39396],"type":"Point"}
}