{
  "type": "Feature",
  "properties": {
    "iso:country":"IN",
    "ks:ks_name":"Nelliyaarlcolony",
    "ks:ks_pop":15,
    "ks:ks_type":"HABITATION",
    "name:eng_x_preferred":[
        "Nelliyaarlcolony"
    ],
    "wof:name":"Nelliyaarlcolony",
    "wof:placetype":"locality",
    "wof:population":15
},
  "geometry": {"coordinates":[75.416006,12.702376],"type":"Point"}
}