{
  "type": "Feature",
  "properties": {
    "gn:country":"IN",
    "gn:fcode":"PPL",
    "gn:pop":21213,
    "iso:country":"IN",
    "name:unk_x_variant":[
        "Jangaon"
    ],
    "qs:name":"Asifabad",
    "qs:name_adm0":"India",
    "qs:name_adm1":"Andhra Pradesh",
    "qs:photos_9k":1,
    "qs:photos_9r":1,
    "qs:photos_all":1,
    "qs:photos_sr":0,
    "qs:placetype":"Town",
    "qs:pop_sr":"7",
    "wd:wordcount":8,
    "wof:name":"Asifabad",
    "wof:placetype":"locality",
    "wof:population":21213
},
  "geometry": {"coordinates":[79.28415,19.35851],"type":"Point"}
}