{
  "type": "Feature",
  "properties": {
    "iso:country":"IN",
    "ks:ks_name":"Kutama",
    "ks:ks_pop":218,
    "ks:ks_type":"VILLAGE",
    "name:eng_x_preferred":[
        "Kutama"
    ],
    "wof:name":"Kutama",
    "wof:placetype":"locality",
    "wof:population":218
},
  "geometry": {"coordinates":[84.20584100000001,19.565166],"type":"Point"}
}