{
  "type": "Feature",
  "properties": {
    "iso:country":"IN",
    "ks:ks_name":"Dhani Sher Singh",
    "ks:ks_pop":2913,
    "ks:ks_type":"HABITATION",
    "name:eng_x_preferred":[
        "Dhani Sher Singh"
    ],
    "wof:name":"Dhani Sher Singh",
    "wof:placetype":"locality",
    "wof:population":2913
},
  "geometry": {"coordinates":[74.160224,30.619971],"type":"Point"}
}