{
  "type": "Feature",
  "properties": {
    "gn:admin1_code":"11",
    "gn:admin2_code":"23.0",
    "gn:asciiname":"Kutehr",
    "gn:country_code":"IN",
    "gn:dem":1455,
    "gn:feature_class":"P",
    "gn:feature_code":"PPL",
    "gn:name":"Kutehr",
    "gn:population":0,
    "gn:timezone":"Asia/Kolkata",
    "iso:country":"IN",
    "wof:name":"Kutehr",
    "wof:placetype":"locality"
},
  "geometry": {"coordinates":[76.14076,32.87083],"type":"Point"}
}