{
  "type": "Feature",
  "properties": {
    "iso:country":"IN",
    "ks:ks_name":"Magawne",
    "ks:ks_pop":269,
    "ks:ks_type":"HABITATION",
    "name:eng_x_preferred":[
        "Magawne"
    ],
    "wof:name":"Magawne",
    "wof:placetype":"locality",
    "wof:population":269
},
  "geometry": {"coordinates":[73.50567100000001,16.161716],"type":"Point"}
}