{
  "type": "Feature",
  "properties": {
    "gn:admin1_code":"24.0",
    "gn:admin2_code":"102",
    "gn:asciiname":"Rajasar Chodiya",
    "gn:country_code":"IN",
    "gn:dem":215,
    "gn:feature_class":"P",
    "gn:feature_code":"PPL",
    "gn:name":"R\u0101j\u0101sar Chodiya",
    "gn:population":0,
    "gn:timezone":"Asia/Kolkata",
    "iso:country":"IN",
    "name:und_x_variant":[
        "R\u0101j\u0101sar Chodiya",
        "Chodia"
    ],
    "wof:name":"Rajasar Chodiya",
    "wof:placetype":"locality"
},
  "geometry": {"coordinates":[74.22696999999999,28.6345],"type":"Point"}
}