{
  "type": "Feature",
  "properties": {
    "iso:country":"IN",
    "ks:ks_name":"Banshkhal",
    "ks:ks_pop":648,
    "ks:ks_type":"VILLAGE",
    "name:eng_x_preferred":[
        "Banshkhal"
    ],
    "wof:name":"Banshkhal",
    "wof:placetype":"locality",
    "wof:population":648
},
  "geometry": {"coordinates":[87.735933,22.537558],"type":"Point"}
}