{
  "type": "Feature",
  "properties": {
    "iso:country":"IN",
    "ks:ks_name":"Dattmandir",
    "ks:ks_pop":58,
    "ks:ks_type":"HABITATION",
    "name:eng_x_preferred":[
        "Dattmandir"
    ],
    "wof:name":"Dattmandir",
    "wof:placetype":"locality",
    "wof:population":58
},
  "geometry": {"coordinates":[73.54963600000001,16.488683],"type":"Point"}
}