{
  "type": "Feature",
  "properties": {
    "iso:country":"IN",
    "ks:ks_name":"Bilamalbandha",
    "ks:ks_pop":0,
    "ks:ks_type":"VILLAGE",
    "name:eng_x_preferred":[
        "Bilamalbandha"
    ],
    "wof:name":"Bilamalbandha",
    "wof:placetype":"locality",
    "wof:population":0
},
  "geometry": {"coordinates":[88.093645,24.036725],"type":"Point"}
}