{
  "type": "Feature",
  "properties": {
    "iso:country":"IN",
    "ks:ks_name":"Ringichiwadi",
    "ks:ks_pop":89,
    "ks:ks_type":"HABITATION",
    "name:eng_x_preferred":[
        "Ringichiwadi"
    ],
    "wof:name":"Ringichiwadi",
    "wof:placetype":"locality",
    "wof:population":89
},
  "geometry": {"coordinates":[73.380515,17.197721],"type":"Point"}
}