{
  "type": "Feature",
  "properties": {
    "iso:country":"IN",
    "ks:ks_name":"Nigrora",
    "ks:ks_pop":167,
    "ks:ks_type":"HABITATION",
    "name:eng_x_preferred":[
        "Nigrora"
    ],
    "wof:name":"Nigrora",
    "wof:placetype":"locality",
    "wof:population":167
},
  "geometry": {"coordinates":[78.381953,24.964901],"type":"Point"}
}