{
  "type": "Feature",
  "properties": {
    "gn:admin1_code":"21",
    "gn:admin2_code":"395.0",
    "gn:asciiname":"Ramana",
    "gn:country_code":"IN",
    "gn:dem":498,
    "gn:feature_class":"P",
    "gn:feature_code":"PPL",
    "gn:name":"Ramana",
    "gn:population":0,
    "gn:timezone":"Asia/Kolkata",
    "iso:country":"IN",
    "name:aze_x_preferred":[
        "Ramana"
    ],
    "name:rus_x_preferred":[
        "\u0420\u0430\u043c\u0430\u043d\u0430"
    ],
    "wof:name":"Ramana",
    "wof:placetype":"locality"
},
  "geometry": {"coordinates":[83.30535999999999,19.8432],"type":"Point"}
}