{
  "type": "Feature",
  "properties": {
    "gn:admin1_code":"37",
    "gn:admin2_code":"404.0",
    "gn:asciiname":"Jamnipali",
    "gn:country_code":"IN",
    "gn:dem":265,
    "gn:feature_class":"P",
    "gn:feature_code":"PPL",
    "gn:name":"Jamn\u012bp\u0101li",
    "gn:population":0,
    "gn:timezone":"Asia/Kolkata",
    "iso:country":"IN",
    "wof:name":"Jamnipali",
    "wof:placetype":"locality"
},
  "geometry": {"coordinates":[82.70045999999998,22.11321],"type":"Point"}
}