{
  "type": "Feature",
  "properties": {
    "iso:country":"IN",
    "ks:ks_name":"East Garlabari",
    "ks:ks_pop":183,
    "ks:ks_type":"HABITATION",
    "name:eng_x_preferred":[
        "East Garlabari"
    ],
    "wof:name":"East Garlabari",
    "wof:placetype":"locality",
    "wof:population":183
},
  "geometry": {"coordinates":[90.440516,26.597137],"type":"Point"}
}