{
  "type": "Feature",
  "properties": {
    "gn:admin1_code":"36.0",
    "gn:admin2_code":"185.0",
    "gn:asciiname":"Kapia Kalan",
    "gn:country_code":"IN",
    "gn:dem":89,
    "gn:feature_class":"P",
    "gn:feature_code":"PPL",
    "gn:name":"Kapia Kal\u0101n",
    "gn:population":0,
    "gn:timezone":"Asia/Kolkata",
    "iso:country":"IN",
    "ks:ks_alt_nam":"Kapia Kal\u0101n",
    "ks:ks_name":"Kapia Kalan",
    "ks:ks_type":"VILLAGE",
    "name:eng_x_preferred":[
        "Kapia Kalan"
    ],
    "name:eng_x_variant":[
        "Kapia Kal\u0101n"
    ],
    "wof:name":"Kapia Kalan",
    "wof:placetype":"locality"
},
  "geometry": {"coordinates":[82.83910400000001,27.053188],"type":"Point"}
}