{
  "type": "Feature",
  "properties": {
    "iso:country":"IN",
    "ks:ks_name":"Chandipur",
    "ks:ks_pop":1141,
    "ks:ks_type":"VILLAGE",
    "name:eng_x_preferred":[
        "Chandipur"
    ],
    "wof:name":"Chandipur",
    "wof:placetype":"locality",
    "wof:population":1141
},
  "geometry": {"coordinates":[92.509484,24.999462],"type":"Point"}
}