{
  "type": "Feature",
  "properties": {
    "gn:admin1_code":"25.0",
    "gn:admin2_code":"604.0",
    "gn:asciiname":"Kodamanallur",
    "gn:country_code":"IN",
    "gn:dem":72,
    "gn:feature_class":"P",
    "gn:feature_code":"PPL",
    "gn:name":"Kodamanall\u016br",
    "gn:population":0,
    "gn:timezone":"Asia/Kolkata",
    "iso:country":"IN",
    "ks:ks_alt_nam":"Kodamanall\u016br",
    "ks:ks_name":"Kodamanallur",
    "ks:ks_pop":212,
    "ks:ks_type":"VILLAGE",
    "name:eng_x_preferred":[
        "Kodamanallur"
    ],
    "name:eng_x_variant":[
        "Kodamanall\u016br"
    ],
    "wof:name":"Kodamanallur",
    "wof:placetype":"locality",
    "wof:population":212
},
  "geometry": {"coordinates":[79.796076,12.95135],"type":"Point"}
}