{
  "type": "Feature",
  "properties": {
    "iso:country":"IN",
    "ks:ks_name":"Darra",
    "ks:ks_pop":1688,
    "ks:ks_type":"VILLAGE",
    "name:eng_x_preferred":[
        "Darra"
    ],
    "wof:name":"Darra",
    "wof:placetype":"locality",
    "wof:population":1688
},
  "geometry": {"coordinates":[87.592422,22.307649],"type":"Point"}
}