{
  "type": "Feature",
  "properties": {
    "iso:country":"IN",
    "ks:ks_name":"Sankinipara",
    "ks:ks_pop":0,
    "ks:ks_type":"VILLAGE",
    "name:eng_x_preferred":[
        "Sankinipara"
    ],
    "wof:name":"Sankinipara",
    "wof:placetype":"locality",
    "wof:population":0
},
  "geometry": {"coordinates":[88.82013999999999,25.230277],"type":"Point"}
}