{
  "type": "Feature",
  "properties": {
    "iso:country":"IN",
    "ks:ks_alt_nam":"Varmangia falia",
    "ks:ks_name":"Varmangia Falia",
    "ks:ks_pop":494,
    "ks:ks_type":"HABITATION",
    "ks:ks_uagg_main":0,
    "name:eng_x_preferred":[
        "Varmangia Falia"
    ],
    "wof:name":"Varmangia Falia",
    "wof:placetype":"neighbourhood",
    "wof:population":494
},
  "geometry": {"coordinates":[74.24211099999999,22.730056],"type":"Point"}
}