{
  "type": "Feature",
  "properties": {
    "iso:country":"IN",
    "ks:ks_name":"Dheevar Pura",
    "ks:ks_pop":100,
    "ks:ks_type":"HABITATION",
    "name:eng_x_preferred":[
        "Dheevar Pura"
    ],
    "wof:name":"Dheevar Pura",
    "wof:placetype":"locality",
    "wof:population":100
},
  "geometry": {"coordinates":[78.47404400000001,25.388161],"type":"Point"}
}