{
  "type": "Feature",
  "properties": {
    "iso:country":"IN",
    "ks:ks_name":"Barokhar",
    "ks:ks_pop":0,
    "ks:ks_type":"VILLAGE",
    "name:eng_x_preferred":[
        "Barokhar"
    ],
    "wof:name":"Barokhar",
    "wof:placetype":"locality",
    "wof:population":0
},
  "geometry": {"coordinates":[85.863646,25.030354],"type":"Point"}
}