{
  "type": "Feature",
  "properties": {
    "gn:admin1_code":"07",
    "gn:admin2_code":"90.0",
    "gn:asciiname":"Shakurpur",
    "gn:country_code":"IN",
    "gn:dem":220,
    "gn:feature_class":"P",
    "gn:feature_code":"PPL",
    "gn:name":"Shak\u016brpur",
    "gn:population":0,
    "gn:timezone":"Asia/Kolkata",
    "iso:country":"IN",
    "wof:name":"Shakurpur",
    "wof:placetype":"locality"
},
  "geometry": {"coordinates":[77.14338000000002,28.68379],"type":"Point"}
}