{
  "type": "Feature",
  "properties": {
    "iso:country":"IN",
    "ks:ks_alt_nam":"soladewadi",
    "ks:ks_name":"Soladewadi",
    "ks:ks_pop":72,
    "ks:ks_type":"HABITATION",
    "ks:ks_uagg_main":0,
    "name:eng_x_preferred":[
        "Soladewadi"
    ],
    "wof:name":"Soladewadi",
    "wof:placetype":"neighbourhood",
    "wof:population":72
},
  "geometry": {"coordinates":[73.972583,15.685556],"type":"Point"}
}