{
  "type": "Feature",
  "properties": {
    "iso:country":"IN",
    "ks:ks_alt_nam":"chaudharipada",
    "ks:ks_name":"Chaudharipada",
    "ks:ks_pop":32,
    "ks:ks_type":"HABITATION",
    "name:eng_x_preferred":[
        "Chaudharipada"
    ],
    "wof:name":"Chaudharipada",
    "wof:placetype":"locality",
    "wof:population":32
},
  "geometry": {"coordinates":[73.104445,19.685604],"type":"Point"}
}