{
  "type": "Feature",
  "properties": {
    "gn:admin1_code":"24.0",
    "gn:admin2_code":"103.0",
    "gn:asciiname":"Meharadasi",
    "gn:country_code":"IN",
    "gn:dem":325,
    "gn:feature_class":"P",
    "gn:feature_code":"PPL",
    "gn:name":"Mehar\u0101d\u0101si",
    "gn:population":0,
    "gn:timezone":"Asia/Kolkata",
    "iso:country":"IN",
    "wof:name":"Meharadasi",
    "wof:placetype":"locality"
},
  "geometry": {"coordinates":[75.17166,28.1137],"type":"Point"}
}