{
  "type": "Feature",
  "properties": {
    "iso:country":"IN",
    "ks:ks_name":"Uttar Radhanagar",
    "ks:ks_pop":0,
    "ks:ks_type":"VILLAGE",
    "name:eng_x_preferred":[
        "Uttar Radhanagar"
    ],
    "wof:name":"Uttar Radhanagar",
    "wof:placetype":"locality",
    "wof:population":0
},
  "geometry": {"coordinates":[87.668514,23.643443],"type":"Point"}
}