{
  "type": "Feature",
  "properties": {
    "iso:country":"IN",
    "ks:ks_name":"Purbba Daripattani",
    "ks:ks_pop":209,
    "ks:ks_type":"VILLAGE",
    "name:eng_x_preferred":[
        "Purbba Daripattani"
    ],
    "wof:name":"Purbba Daripattani",
    "wof:placetype":"locality",
    "wof:population":209
},
  "geometry": {"coordinates":[88.913042,26.293457],"type":"Point"}
}