{
  "type": "Feature",
  "properties": {
    "gn:admin1_code":"36",
    "gn:admin2_code":"193.0",
    "gn:asciiname":"Tari Baragaon",
    "gn:country_code":"IN",
    "gn:dem":77,
    "gn:feature_class":"P",
    "gn:feature_code":"PPL",
    "gn:name":"T\u0101r\u012b Bar\u0101gaon",
    "gn:population":0,
    "gn:timezone":"Asia/Kolkata",
    "iso:country":"IN",
    "name:und_x_variant":[
        "T\u0101r\u012b Bar\u0101gaon",
        "T\u0101ri Bar\u0101gaon"
    ],
    "wof:name":"Tari Baragaon",
    "wof:placetype":"locality"
},
  "geometry": {"coordinates":[83.83126999999998,25.9901],"type":"Point"}
}