{
  "type": "Feature",
  "properties": {
    "iso:country":"IN",
    "ks:ks_name":"Hakam",
    "ks:ks_pop":72,
    "ks:ks_type":"VILLAGE",
    "ks:ks_uagg_main":0,
    "name:eng_x_preferred":[
        "Hakam"
    ],
    "wof:name":"Hakam",
    "wof:placetype":"neighbourhood",
    "wof:population":72
},
  "geometry": {"coordinates":[84.80858000000001,25.898927],"type":"Point"}
}