{
  "type": "Feature",
  "properties": {
    "iso:country":"IN",
    "ks:ks_name":"Dhuanpari",
    "ks:ks_pop":1105,
    "ks:ks_type":"VILLAGE",
    "ks:ks_uagg_main":0,
    "name:eng_x_preferred":[
        "Dhuanpari"
    ],
    "wof:name":"Dhuanpari",
    "wof:placetype":"neighbourhood",
    "wof:population":1105
},
  "geometry": {"coordinates":[86.2358,20.277204],"type":"Point"}
}