{
  "type": "Feature",
  "properties": {
    "gn:admin1_code":"25.0",
    "gn:admin2_code":"618.0",
    "gn:asciiname":"Kurichchi",
    "gn:country_code":"IN",
    "gn:dem":3,
    "gn:feature_class":"P",
    "gn:feature_code":"PPL",
    "gn:name":"Kurichchi",
    "gn:population":0,
    "gn:timezone":"Asia/Kolkata",
    "iso:country":"IN",
    "wof:name":"Kurichchi",
    "wof:placetype":"locality"
},
  "geometry": {"coordinates":[79.80263000000002,10.69351],"type":"Point"}
}