{
  "type": "Feature",
  "properties": {
    "iso:country":"IN",
    "ks:ks_name":"Sunpeda",
    "ks:ks_pop":2569,
    "ks:ks_type":"HABITATION",
    "name:eng_x_preferred":[
        "Sunpeda"
    ],
    "wof:name":"Sunpeda",
    "wof:placetype":"locality",
    "wof:population":2569
},
  "geometry": {"coordinates":[77.713615,28.35368],"type":"Point"}
}