{
  "type": "Feature",
  "properties": {
    "iso:country":"IN",
    "ks:ks_name":"Narayan Ronghang",
    "ks:ks_pop":30,
    "ks:ks_type":"HABITATION",
    "name:eng_x_preferred":[
        "Narayan Ronghang"
    ],
    "wof:name":"Narayan Ronghang",
    "wof:placetype":"locality",
    "wof:population":30
},
  "geometry": {"coordinates":[93.299575,26.326406],"type":"Point"}
}