{
  "type": "Feature",
  "properties": {
    "iso:country":"IN",
    "ks:ks_name":"Lingalagattu",
    "ks:ks_pop":1833,
    "ks:ks_type":"HABITATION",
    "name:eng_x_preferred":[
        "Lingalagattu"
    ],
    "wof:name":"Lingalagattu",
    "wof:placetype":"locality",
    "wof:population":1833
},
  "geometry": {"coordinates":[78.901321,16.050883],"type":"Point"}
}