{
  "type": "Feature",
  "properties": {
    "gn:admin1_code":"31.0",
    "gn:admin2_code":"281.0",
    "gn:asciiname":"Tuidam",
    "gn:country_code":"IN",
    "gn:dem":698,
    "gn:feature_class":"P",
    "gn:feature_code":"PPL",
    "gn:name":"Tuidam",
    "gn:population":0,
    "gn:timezone":"Asia/Kolkata",
    "iso:country":"IN",
    "wof:name":"Tuidam",
    "wof:placetype":"locality"
},
  "geometry": {"coordinates":[92.36897,23.92652],"type":"Point"}
}