{
  "type": "Feature",
  "properties": {
    "iso:country":"IN",
    "ks:ks_name":"Kaudiapur",
    "ks:ks_pop":189,
    "ks:ks_type":"HABITATION",
    "name:eng_x_preferred":[
        "Kaudiapur"
    ],
    "wof:name":"Kaudiapur",
    "wof:placetype":"locality",
    "wof:population":189
},
  "geometry": {"coordinates":[85.612481,19.968357],"type":"Point"}
}