{
  "type": "Feature",
  "properties": {
    "iso:country":"IN",
    "ks:ks_name":"Budhandol Alias Chhatadar",
    "ks:ks_pop":0,
    "ks:ks_type":"VILLAGE",
    "name:eng_x_preferred":[
        "Budhandol Alias Chhatadar"
    ],
    "wof:name":"Budhandol Alias Chhatadar",
    "wof:placetype":"locality",
    "wof:population":0
},
  "geometry": {"coordinates":[81.712875,23.93973],"type":"Point"}
}