{
  "type": "Feature",
  "properties": {
    "iso:country":"IN",
    "ks:ks_name":"Madigapeta",
    "ks:ks_pop":192,
    "ks:ks_type":"HABITATION",
    "ks:ks_uagg_main":0,
    "name:eng_x_preferred":[
        "Madigapeta"
    ],
    "wof:name":"Madigapeta",
    "wof:placetype":"neighbourhood",
    "wof:population":192
},
  "geometry": {"coordinates":[83.882378,18.358141],"type":"Point"}
}