{
  "type": "Feature",
  "properties": {
    "gn:admin1_code":"19.0",
    "gn:admin2_code":"566.0",
    "gn:asciiname":"Chikka Kabbigere",
    "gn:country_code":"IN",
    "gn:dem":681,
    "gn:feature_class":"P",
    "gn:feature_code":"PPL",
    "gn:name":"Chikka Kabbigere",
    "gn:population":0,
    "gn:timezone":"Asia/Kolkata",
    "iso:country":"IN",
    "wof:name":"Chikka Kabbigere",
    "wof:placetype":"locality"
},
  "geometry": {"coordinates":[76.30129000000002,14.35261],"type":"Point"}
}