{
  "type": "Feature",
  "properties": {
    "gn:admin1_code":"36.0",
    "gn:admin2_code":"175.0",
    "gn:asciiname":"Chak Afzal",
    "gn:country_code":"IN",
    "gn:dem":104,
    "gn:feature_class":"P",
    "gn:feature_code":"PPL",
    "gn:name":"Chak Afzal",
    "gn:population":0,
    "gn:timezone":"Asia/Kolkata",
    "iso:country":"IN",
    "name:und_x_variant":[
        "Pure L\u012bla"
    ],
    "wof:name":"Chak Afzal",
    "wof:placetype":"neighbourhood"
},
  "geometry": {"coordinates":[81.96019,25.67453],"type":"Point"}
}