{
  "type": "Feature",
  "properties": {
    "iso:country":"IN",
    "ks:ks_name":"Rasoolpur",
    "ks:ks_pop":39,
    "ks:ks_type":"VILLAGE",
    "ks:ks_uagg_main":0,
    "name:eng_x_preferred":[
        "Rasoolpur"
    ],
    "wof:name":"Rasoolpur",
    "wof:placetype":"neighbourhood",
    "wof:population":39
},
  "geometry": {"coordinates":[78.634064,28.18569],"type":"Point"}
}