{
  "type": "Feature",
  "properties": {
    "iso:country":"IN",
    "name:eng_x_preferred":[
        "Gulzar House"
    ],
    "name:eng_x_variant":[
        "Gulzar Houz"
    ],
    "name:tel_x_preferred":[
        "\u0c17\u0c41\u0c32\u0c4d\u0c1c\u0c3e\u0c30\u0c4d \u0c39\u0c4c\u0c1c\u0c4d"
    ],
    "qs:gn_adm0_cc":"IN",
    "qs:gn_local":1269843,
    "qs:local_max":1198,
    "qs:local_sum":10545,
    "qs:localhoods":56,
    "qs:name":"Gulzar House",
    "qs:name_adm0":"India",
    "qs:name_adm1":"Andhra Pradesh",
    "qs:name_adm2":"Hyderabad",
    "qs:name_local":"Hyderabad",
    "qs:photo_max":29,
    "qs:photo_sum":70,
    "qs:placetype":"Suburb",
    "qs:quad_count":5,
    "qs:woe_adm0":23424848,
    "qs:woe_adm1":2345740,
    "qs:woe_adm2":24527543,
    "qs:woe_lau":0,
    "qs:woe_local":2295414,
    "qs:woe_ver":"7.10.0",
    "wd:wordcount":134,
    "wof:lang":[
        "eng"
    ],
    "wof:name":"Gulzar House",
    "wof:placetype":"neighbourhood"
},
  "geometry": {"coordinates":[78.47510200000001,17.367296],"type":"Point"}
}