{
  "type": "Feature",
  "properties": {
    "iso:country":"IN",
    "ks:ks_alt_nam":"BEEDGHAS",
    "ks:ks_name":"Beedghas",
    "ks:ks_pop":1712,
    "ks:ks_type":"HABITATION",
    "name:eng_x_preferred":[
        "Beedghas"
    ],
    "wof:name":"Beedghas",
    "wof:placetype":"locality",
    "wof:population":1712
},
  "geometry": {"coordinates":[74.01647699999999,24.801086],"type":"Point"}
}