{
  "type": "Feature",
  "properties": {
    "iso:country":"IN",
    "ks:ks_alt_nam":"ME School suba",
    "ks:ks_name":"Me School Suba",
    "ks:ks_pop":600,
    "ks:ks_type":"HABITATION",
    "name:eng_x_preferred":[
        "Me School Suba"
    ],
    "wof:name":"Me School Suba",
    "wof:placetype":"locality",
    "wof:population":600
},
  "geometry": {"coordinates":[91.560703,26.503255],"type":"Point"}
}