{
  "type": "Feature",
  "properties": {
    "iso:country":"IN",
    "qs:name":"Nawab Purwa",
    "qs:name_adm0":"India",
    "qs:name_adm1":"Uttar Pradesh",
    "qs:photos":25,
    "qs:photos_1k":5,
    "qs:photos_9k":1,
    "qs:photos_9r":1,
    "qs:photos_all":25,
    "qs:photos_sr":1,
    "qs:placetype":"Suburb",
    "qs:pop_sr":"0",
    "wof:name":"Nawab Purwa",
    "wof:placetype":"neighbourhood"
},
  "geometry": {"coordinates":[81.00228300000001,26.855958],"type":"Point"}
}