{
  "type": "Feature",
  "properties": {
    "gn:admin1_code":"23.0",
    "gn:admin2_code":"35.0",
    "gn:asciiname":"Khan Piyara",
    "gn:country_code":"IN",
    "gn:dem":253,
    "gn:feature_class":"P",
    "gn:feature_code":"PPL",
    "gn:name":"Kh\u0101n Piy\u0101r\u0101",
    "gn:population":0,
    "gn:timezone":"Asia/Kolkata",
    "iso:country":"IN",
    "ks:ks_alt_nam":"Kh\u0101n Piy\u0101r\u0101",
    "ks:ks_name":"Khan Piyara",
    "ks:ks_pop":1328,
    "ks:ks_type":"VILLAGE",
    "name:eng_x_preferred":[
        "Khan Piyara"
    ],
    "name:eng_x_variant":[
        "Kh\u0101n Piy\u0101r\u0101"
    ],
    "wof:name":"Khan Piyara",
    "wof:placetype":"locality",
    "wof:population":1328
},
  "geometry": {"coordinates":[75.31939300000001,31.875757],"type":"Point"}
}