{
  "type": "Feature",
  "properties": {
    "gn:admin1_code":"23.0",
    "gn:admin2_code":"35.0",
    "gn:asciiname":"Khan Piyara",
    "gn:country_code":"IN",
    "gn:dem":253,
    "gn:feature_class":"P",
    "gn:feature_code":"PPL",
    "gn:name":"Kh\u0101n Piy\u0101r\u0101",
    "gn:population":0,
    "gn:timezone":"Asia/Kolkata",
    "iso:country":"IN",
    "wof:name":"Khan Piyara",
    "wof:placetype":"locality"
},
  "geometry": {"coordinates":[75.31939,31.87576],"type":"Point"}
}