{
  "type": "Feature",
  "properties": {
    "gn:admin1_code":"38.0",
    "gn:admin2_code":"353.0",
    "gn:asciiname":"Garopahari",
    "gn:country_code":"IN",
    "gn:dem":65,
    "gn:feature_class":"P",
    "gn:feature_code":"PPL",
    "gn:name":"G\u0101ropah\u0101ri",
    "gn:population":0,
    "gn:timezone":"Asia/Kolkata",
    "iso:country":"IN",
    "ks:ks_name":"Ganropahari",
    "ks:ks_pop":573,
    "ks:ks_type":"VILLAGE",
    "name:eng_x_preferred":[
        "Ganropahari"
    ],
    "name:eng_x_variant":[
        "Garopahari"
    ],
    "wof:name":"Ganropahari",
    "wof:placetype":"locality",
    "wof:population":573
},
  "geometry": {"coordinates":[87.66020399999999,24.612359],"type":"Point"}
}