{
  "type": "Feature",
  "properties": {
    "gn:admin1_code":"38.0",
    "gn:admin2_code":"360.0",
    "gn:asciiname":"Chhaoni",
    "gn:country_code":"IN",
    "gn:dem":596,
    "gn:feature_class":"P",
    "gn:feature_code":"PPL",
    "gn:name":"Chh\u0101oni",
    "gn:population":0,
    "gn:timezone":"Asia/Kolkata",
    "iso:country":"IN",
    "ks:ks_alt_nam":"Chh\u0101oni",
    "ks:ks_name":"Chhaoni",
    "ks:ks_pop":356,
    "ks:ks_type":"VILLAGE",
    "ks:ks_uagg_main":0,
    "name:eng_x_preferred":[
        "Chhaoni"
    ],
    "name:eng_x_variant":[
        "Chh\u0101oni"
    ],
    "wof:name":"Chhaoni",
    "wof:placetype":"neighbourhood",
    "wof:population":356
},
  "geometry": {"coordinates":[85.430145,24.078257],"type":"Point"}
}