{
  "type": "Feature",
  "properties": {
    "gn:admin1_code":"36",
    "gn:admin2_code":"162.0",
    "gn:asciiname":"Belupur",
    "gn:country_code":"IN",
    "gn:dem":142,
    "gn:feature_class":"P",
    "gn:feature_code":"PPL",
    "gn:name":"Bel\u016bpur",
    "gn:population":0,
    "gn:timezone":"Asia/Kolkata",
    "iso:country":"IN",
    "ks:ks_alt_nam":"Bel\u016bpur",
    "ks:ks_name":"Belupur",
    "ks:ks_type":"VILLAGE",
    "name:eng_x_preferred":[
        "Belupur"
    ],
    "name:eng_x_variant":[
        "Bel\u016bpur"
    ],
    "wof:name":"Belupur",
    "wof:placetype":"locality"
},
  "geometry": {"coordinates":[79.682608,26.639885],"type":"Point"}
}