{
  "type": "Feature",
  "properties": {
    "iso:country":"IN",
    "ks:ks_name":"Harijanpada",
    "ks:ks_pop":186,
    "ks:ks_type":"HABITATION",
    "name:eng_x_preferred":[
        "Harijanpada"
    ],
    "wof:name":"Harijanpada",
    "wof:placetype":"locality",
    "wof:population":186
},
  "geometry": {"coordinates":[83.083578,19.569296],"type":"Point"}
}