{
  "type": "Feature",
  "properties": {
    "iso:country":"IN",
    "ks:ks_name":"Jamuposi",
    "ks:ks_pop":352,
    "ks:ks_type":"HABITATION",
    "name:eng_x_preferred":[
        "Jamuposi"
    ],
    "wof:name":"Jamuposi",
    "wof:placetype":"locality",
    "wof:population":352
},
  "geometry": {"coordinates":[85.85871400000001,21.302717],"type":"Point"}
}