{
  "type": "Feature",
  "properties": {
    "gn:admin1_code":"37.0",
    "gn:admin2_code":"401.0",
    "gn:asciiname":"Khopa",
    "gn:country_code":"IN",
    "gn:dem":526,
    "gn:feature_class":"P",
    "gn:feature_code":"PPL",
    "gn:name":"Khopa",
    "gn:population":0,
    "gn:timezone":"Asia/Kolkata",
    "iso:country":"IN",
    "ks:ks_name":"Khopa",
    "ks:ks_type":"VILLAGE",
    "name:eng_x_preferred":[
        "Khopa"
    ],
    "wof:name":"Khopa",
    "wof:placetype":"locality"
},
  "geometry": {"coordinates":[82.919355,23.318061],"type":"Point"}
}