{
  "type": "Feature",
  "properties": {
    "gn:admin1_code":"37.0",
    "gn:admin2_code":"401.0",
    "gn:asciiname":"Khopa",
    "gn:country_code":"IN",
    "gn:dem":526,
    "gn:feature_class":"P",
    "gn:feature_code":"PPL",
    "gn:name":"Khopa",
    "gn:population":0,
    "gn:timezone":"Asia/Kolkata",
    "iso:country":"IN",
    "wof:name":"Khopa",
    "wof:placetype":"locality"
},
  "geometry": {"coordinates":[82.91934999999999,23.31806],"type":"Point"}
}