{
  "type": "Feature",
  "properties": {
    "iso:country":"IN",
    "ks:ks_name":"Bagraguda",
    "ks:ks_pop":176,
    "ks:ks_type":"HABITATION",
    "name:eng_x_preferred":[
        "Bagraguda"
    ],
    "wof:name":"Bagraguda",
    "wof:placetype":"locality",
    "wof:population":176
},
  "geometry": {"coordinates":[82.67309299999999,18.953649],"type":"Point"}
}