{
  "type": "Feature",
  "properties": {
    "iso:country":"IN",
    "ks:ks_name":"Garhi Kishan",
    "ks:ks_pop":975,
    "ks:ks_type":"HABITATION",
    "name:eng_x_preferred":[
        "Garhi Kishan"
    ],
    "wof:name":"Garhi Kishan",
    "wof:placetype":"locality",
    "wof:population":975
},
  "geometry": {"coordinates":[78.21606300000001,27.052546],"type":"Point"}
}