{
  "type": "Feature",
  "properties": {
    "iso:country":"IN",
    "ks:ks_name":"Chhechhi Manjhar",
    "ks:ks_pop":76,
    "ks:ks_type":"VILLAGE",
    "ks:ks_uagg_main":0,
    "name:eng_x_preferred":[
        "Chhechhi Manjhar"
    ],
    "wof:name":"Chhechhi Manjhar",
    "wof:placetype":"neighbourhood",
    "wof:population":76
},
  "geometry": {"coordinates":[84.828171,24.451505],"type":"Point"}
}