{
  "type": "Feature",
  "properties": {
    "gn:admin1_code":"09",
    "gn:admin2_code":"476.0",
    "gn:asciiname":"Kuvadra",
    "gn:country_code":"IN",
    "gn:dem":175,
    "gn:feature_class":"P",
    "gn:feature_code":"PPL",
    "gn:name":"Kuv\u0101dra",
    "gn:population":0,
    "gn:timezone":"Asia/Kolkata",
    "iso:country":"IN",
    "name:und_x_variant":[
        "Kuvada",
        "Kuv\u0101rva",
        "Kuv\u0101dra"
    ],
    "wof:name":"Kuvadra",
    "wof:placetype":"locality"
},
  "geometry": {"coordinates":[70.94503,22.35949],"type":"Point"}
}