{
  "type": "Feature",
  "properties": {
    "iso:country":"IN",
    "ks:ks_alt_nam":"ICHAKUTI",
    "ks:ks_name":"Ichakuti",
    "ks:ks_pop":150,
    "ks:ks_type":"HABITATION",
    "name:eng_x_preferred":[
        "Ichakuti"
    ],
    "wof:name":"Ichakuti",
    "wof:placetype":"locality",
    "wof:population":150
},
  "geometry": {"coordinates":[85.650873,22.372244],"type":"Point"}
}