{
  "type": "Feature",
  "properties": {
    "iso:country":"IN",
    "ks:ks_name":"Bharuhia",
    "ks:ks_pop":96,
    "ks:ks_type":"VILLAGE",
    "name:eng_x_preferred":[
        "Bharuhia"
    ],
    "wof:name":"Bharuhia",
    "wof:placetype":"locality",
    "wof:population":96
},
  "geometry": {"coordinates":[82.714716,25.123722],"type":"Point"}
}