{
  "type": "Feature",
  "properties": {
    "iso:country":"IN",
    "ks:ks_alt_nam":"GASABAND",
    "ks:ks_name":"Gasaband",
    "ks:ks_pop":275,
    "ks:ks_type":"HABITATION",
    "name:eng_x_preferred":[
        "Gasaband"
    ],
    "wof:name":"Gasaband",
    "wof:placetype":"locality",
    "wof:population":275
},
  "geometry": {"coordinates":[83.636962,23.168767],"type":"Point"}
}