{
  "type": "Feature",
  "properties": {
    "iso:country":"IN",
    "ks:ks_name":"Dhangol",
    "ks:ks_pop":170,
    "ks:ks_type":"VILLAGE",
    "name:eng_x_preferred":[
        "Dhangol"
    ],
    "wof:name":"Dhangol",
    "wof:placetype":"locality",
    "wof:population":170
},
  "geometry": {"coordinates":[80.52185799999999,18.815303],"type":"Point"}
}