{
  "type": "Feature",
  "properties": {
    "iso:country":"IN",
    "ks:ks_name":"Ramachandra Nagar",
    "ks:ks_pop":368,
    "ks:ks_type":"HABITATION",
    "ks:ks_uagg_main":0,
    "name:eng_x_preferred":[
        "Ramachandra Nagar"
    ],
    "wof:name":"Ramachandra Nagar",
    "wof:placetype":"locality",
    "wof:population":368
},
  "geometry": {"coordinates":[78.70239599999999,12.824052],"type":"Point"}
}