{
  "type": "Feature",
  "properties": {
    "iso:country":"IN",
    "ks:ks_name":"Rampur Thana Amanat Sarkar",
    "ks:ks_pop":0,
    "ks:ks_type":"VILLAGE",
    "name:eng_x_preferred":[
        "Rampur Thana Amanat Sarkar"
    ],
    "wof:name":"Rampur Thana Amanat Sarkar",
    "wof:placetype":"locality",
    "wof:population":0
},
  "geometry": {"coordinates":[86.171026,25.177064],"type":"Point"}
}