{
  "type": "Feature",
  "properties": {
    "gn:admin1_code":"2.0",
    "gn:admin2_code":"551.0",
    "gn:asciiname":"Rajupeta",
    "gn:country_code":"IN",
    "gn:dem":141,
    "gn:feature_class":"P",
    "gn:feature_code":"PPL",
    "gn:name":"R\u0101jupeta",
    "gn:population":0,
    "gn:timezone":"Asia/Kolkata",
    "iso:country":"IN",
    "ks:ks_name":"Rajupet",
    "ks:ks_pop":133,
    "ks:ks_type":"HABITATION",
    "name:eng_x_preferred":[
        "Rajupet"
    ],
    "name:eng_x_variant":[
        "Rajupeta"
    ],
    "wof:name":"Rajupet",
    "wof:placetype":"locality",
    "wof:population":133
},
  "geometry": {"coordinates":[79.14919999999999,14.690737],"type":"Point"}
}