{
  "type": "Feature",
  "properties": {
    "iso:country":"IN",
    "ks:ks_name":"Murchbana",
    "ks:ks_pop":129,
    "ks:ks_type":"VILLAGE",
    "name:eng_x_preferred":[
        "Murchbana"
    ],
    "wof:name":"Murchbana",
    "wof:placetype":"locality",
    "wof:population":129
},
  "geometry": {"coordinates":[68.876332,23.513301],"type":"Point"}
}