{
  "type": "Feature",
  "properties": {
    "iso:country":"IN",
    "ks:ks_name":"Dattanagar",
    "ks:ks_pop":64,
    "ks:ks_type":"HABITATION",
    "name:eng_x_preferred":[
        "Dattanagar"
    ],
    "wof:name":"Dattanagar",
    "wof:placetype":"locality",
    "wof:population":64
},
  "geometry": {"coordinates":[73.419061,16.588897],"type":"Point"}
}