{
  "type": "Feature",
  "properties": {
    "gn:admin1_code":"11.0",
    "gn:admin2_code":"27.0",
    "gn:asciiname":"Daklehr",
    "gn:country_code":"IN",
    "gn:dem":3163,
    "gn:feature_class":"P",
    "gn:feature_code":"PPL",
    "gn:name":"Daklehr",
    "gn:population":0,
    "gn:timezone":"Asia/Kolkata",
    "iso:country":"IN",
    "wof:name":"Daklehr",
    "wof:placetype":"locality"
},
  "geometry": {"coordinates":[77.17758000000001,31.48201],"type":"Point"}
}