{
  "type": "Feature",
  "properties": {
    "iso:country":"IN",
    "ks:ks_name":"Agraharam",
    "ks:ks_pop":2548,
    "ks:ks_type":"VILLAGE",
    "ks:ks_uagg_main":0,
    "name:eng_x_preferred":[
        "Agraharam"
    ],
    "wof:name":"Agraharam",
    "wof:placetype":"neighbourhood",
    "wof:population":2548
},
  "geometry": {"coordinates":[82.25819300000001,17.129324],"type":"Point"}
}