{
  "type": "Feature",
  "properties": {
    "iso:country":"IN",
    "ks:ks_name":"Kusgyache Galu",
    "ks:ks_pop":270,
    "ks:ks_type":"HABITATION",
    "name:eng_x_preferred":[
        "Kusgyache Galu"
    ],
    "wof:name":"Kusgyache Galu",
    "wof:placetype":"locality",
    "wof:population":270
},
  "geometry": {"coordinates":[73.85735,16.037026],"type":"Point"}
}