{
  "type": "Feature",
  "properties": {
    "iso:country":"IN",
    "ks:ks_name":"Iswarpali",
    "ks:ks_pop":273,
    "ks:ks_type":"HABITATION",
    "name:eng_x_preferred":[
        "Iswarpali"
    ],
    "wof:name":"Iswarpali",
    "wof:placetype":"locality",
    "wof:population":273
},
  "geometry": {"coordinates":[84.689583,21.448285],"type":"Point"}
}