{
  "type": "Feature",
  "properties": {
    "iso:country":"IN",
    "ks:ks_name":"Vellani",
    "ks:ks_pop":1246,
    "ks:ks_type":"HABITATION",
    "name:eng_x_preferred":[
        "Vellani"
    ],
    "wof:name":"Vellani",
    "wof:placetype":"locality",
    "wof:population":1246
},
  "geometry": {"coordinates":[76.86916600000001,9.712301],"type":"Point"}
}