{
  "type": "Feature",
  "properties": {
    "iso:country":"IN",
    "ks:ks_name":"Alakapai",
    "ks:ks_pop":64,
    "ks:ks_type":"HABITATION",
    "name:eng_x_preferred":[
        "Alakapai"
    ],
    "wof:name":"Alakapai",
    "wof:placetype":"locality",
    "wof:population":64
},
  "geometry": {"coordinates":[83.174285,18.842325],"type":"Point"}
}