{
  "type": "Feature",
  "properties": {
    "iso:country":"IN",
    "ks:ks_name":"Tigdda",
    "ks:ks_pop":241,
    "ks:ks_type":"HABITATION",
    "name:eng_x_preferred":[
        "Tigdda"
    ],
    "wof:name":"Tigdda",
    "wof:placetype":"locality",
    "wof:population":241
},
  "geometry": {"coordinates":[78.487263,25.088734],"type":"Point"}
}