{
  "type": "Feature",
  "properties": {
    "gn:admin1_code":"2",
    "gn:admin2_code":"548.0",
    "gn:asciiname":"Balijepalle",
    "gn:country_code":"IN",
    "gn:dem":90,
    "gn:feature_class":"P",
    "gn:feature_code":"PPL",
    "gn:name":"Balijepalle",
    "gn:population":0,
    "gn:timezone":"Asia/Kolkata",
    "iso:country":"IN",
    "wof:name":"Balijepalle",
    "wof:placetype":"locality"
},
  "geometry": {"coordinates":[80.03049,16.40148],"type":"Point"}
}