{
  "type": "Feature",
  "properties": {
    "gn:admin1_code":"37.0",
    "gn:admin2_code":"414.0",
    "gn:asciiname":"Kumharpara",
    "gn:country_code":"IN",
    "gn:dem":652,
    "gn:feature_class":"P",
    "gn:feature_code":"PPL",
    "gn:name":"Kumh\u0101rp\u0101ra",
    "gn:population":0,
    "gn:timezone":"Asia/Kolkata",
    "iso:country":"IN",
    "ks:ks_name":"Kumharsadra",
    "ks:ks_pop":1111,
    "ks:ks_type":"VILLAGE",
    "name:eng_x_preferred":[
        "Kumharsadra"
    ],
    "name:eng_x_variant":[
        "Kumharpara"
    ],
    "wof:name":"Kumharsadra",
    "wof:placetype":"locality",
    "wof:population":1111
},
  "geometry": {"coordinates":[81.650825,18.929724],"type":"Point"}
}