{
  "type": "Feature",
  "properties": {
    "iso:country":"IN",
    "ks:ks_name":"Gamar Kurya",
    "ks:ks_type":"VILLAGE",
    "name:eng_x_preferred":[
        "Gamar Kurya"
    ],
    "wof:name":"Gamar Kurya",
    "wof:placetype":"locality"
},
  "geometry": {"coordinates":[87.474301,22.667306],"type":"Point"}
}