{
  "type": "Feature",
  "properties": {
    "gn:admin1_code":"35",
    "gn:admin2_code":"421.0",
    "gn:asciiname":"Hansapur",
    "gn:country_code":"IN",
    "gn:dem":182,
    "gn:feature_class":"P",
    "gn:feature_code":"PPL",
    "gn:name":"Hans\u0101pur",
    "gn:population":0,
    "gn:timezone":"Asia/Kolkata",
    "iso:country":"IN",
    "name:fra_x_preferred":[
        "Hansapur"
    ],
    "name:new_x_preferred":[
        "\u0939\u0902\u0936\u092a\u0941\u0930"
    ],
    "name:pol_x_preferred":[
        "Hansapur"
    ],
    "wof:name":"Hansapur",
    "wof:placetype":"neighbourhood"
},
  "geometry": {"coordinates":[78.75815,25.71381],"type":"Point"}
}