{
  "type": "Feature",
  "properties": {
    "gn:admin1_code":"34.0",
    "gn:admin2_code":"219.0",
    "gn:asciiname":"Nandlal Chhapra",
    "gn:country_code":"IN",
    "gn:dem":57,
    "gn:feature_class":"P",
    "gn:feature_code":"PPL",
    "gn:name":"Nandl\u0101l Chhapra",
    "gn:population":0,
    "gn:timezone":"Asia/Kolkata",
    "iso:country":"IN",
    "ks:ks_alt_nam":"Nandl\u0101l Chhapra",
    "ks:ks_name":"Nandlal Chhapra",
    "ks:ks_type":"VILLAGE",
    "ks:ks_uagg_main":0,
    "name:eng_x_preferred":[
        "Nandlal Chhapra"
    ],
    "name:eng_x_variant":[
        "Nandl\u0101l Chhapra"
    ],
    "wof:name":"Nandlal Chhapra",
    "wof:placetype":"neighbourhood"
},
  "geometry": {"coordinates":[84.753923,25.844839],"type":"Point"}
}