{
  "type": "Feature",
  "properties": {
    "iso:country":"IN",
    "ks:ks_name":"Kalikapur",
    "ks:ks_pop":553,
    "ks:ks_type":"VILLAGE",
    "ks:ks_uagg_main":0,
    "name:eng_x_preferred":[
        "Kalikapur"
    ],
    "wof:name":"Kalikapur",
    "wof:placetype":"neighbourhood",
    "wof:population":553
},
  "geometry": {"coordinates":[87.636876,21.686558],"type":"Point"}
}