{
  "type": "Feature",
  "properties": {
    "iso:country":"IN",
    "ks:ks_name":"Hapasar",
    "ks:ks_pop":296,
    "ks:ks_type":"HABITATION",
    "name:eng_x_preferred":[
        "Hapasar"
    ],
    "wof:name":"Hapasar",
    "wof:placetype":"locality",
    "wof:population":296
},
  "geometry": {"coordinates":[72.41889999999999,26.636256],"type":"Point"}
}