{
  "type": "Feature",
  "properties": {
    "iso:country":"IN",
    "ks:ks_name":"Nachania",
    "ks:ks_pop":463,
    "ks:ks_type":"VILLAGE",
    "name:eng_x_preferred":[
        "Nachania"
    ],
    "wof:name":"Nachania",
    "wof:placetype":"locality",
    "wof:population":463
},
  "geometry": {"coordinates":[84.240498,25.076516],"type":"Point"}
}