{
  "type": "Feature",
  "properties": {
    "gn:admin1_code":"39",
    "gn:admin2_code":"60.0",
    "gn:asciiname":"Gobindwala",
    "gn:country_code":"IN",
    "gn:dem":747,
    "gn:feature_class":"P",
    "gn:feature_code":"PPL",
    "gn:name":"Gobindw\u0101la",
    "gn:population":0,
    "gn:timezone":"Asia/Kolkata",
    "iso:country":"IN",
    "ks:ks_alt_nam":"Gobindw\u0101la",
    "ks:ks_name":"Gobindwala",
    "ks:ks_type":"VILLAGE",
    "ks:ks_uagg_main":0,
    "name:eng_x_preferred":[
        "Gobindwala"
    ],
    "name:eng_x_variant":[
        "Gobindw\u0101la"
    ],
    "wof:name":"Gobindwala",
    "wof:placetype":"neighbourhood"
},
  "geometry": {"coordinates":[78.234174,30.203022],"type":"Point"}
}