{
  "type": "Feature",
  "properties": {
    "iso:country":"IN",
    "ks:ks_name":"Sarangpore",
    "ks:ks_pop":12531,
    "ks:ks_type":"VILLAGE",
    "ks:ks_uagg_main":0,
    "name:eng_x_preferred":[
        "Sarangpore"
    ],
    "wof:name":"Sarangpore",
    "wof:placetype":"neighbourhood",
    "wof:population":12531
},
  "geometry": {"coordinates":[73.045744,21.630636],"type":"Point"}
}