{
  "type": "Feature",
  "properties": {
    "gn:country":"IN",
    "gn:fcode":"PPL",
    "gn:pop":0,
    "iso:country":"IN",
    "name:eng_x_preferred":[
        "Singanamane"
    ],
    "name:nld_x_preferred":[
        "Singanamane"
    ],
    "name:unk_x_variant":[
        "Singanamana"
    ],
    "qs:name":"Singanamane",
    "qs:name_adm0":"India",
    "qs:name_adm1":"Karnataka",
    "qs:photos":37,
    "qs:photos_1k":7,
    "qs:photos_9k":1,
    "qs:photos_9r":2,
    "qs:photos_all":37,
    "qs:photos_sr":2,
    "qs:placetype":"Town",
    "qs:pop_sr":"0",
    "wd:wordcount":96,
    "wof:name":"Singanamane",
    "wof:placetype":"locality",
    "wof:population":0
},
  "geometry": {"coordinates":[75.63636,13.71618],"type":"Point"}
}