{
  "type": "Feature",
  "properties": {
    "iso:country":"IN",
    "ks:ks_name":"Adivasipada",
    "ks:ks_pop":96,
    "ks:ks_type":"HABITATION",
    "name:eng_x_preferred":[
        "Adivasipada"
    ],
    "wof:name":"Adivasipada",
    "wof:placetype":"locality",
    "wof:population":96
},
  "geometry": {"coordinates":[73.171098,19.46925],"type":"Point"}
}