{
  "type": "Feature",
  "properties": {
    "iso:country":"IN",
    "ks:ks_name":"Maddi Vasti",
    "ks:ks_pop":250,
    "ks:ks_type":"HABITATION",
    "name:eng_x_preferred":[
        "Maddi Vasti"
    ],
    "wof:name":"Maddi Vasti",
    "wof:placetype":"locality",
    "wof:population":250
},
  "geometry": {"coordinates":[75.81146099999999,17.184582],"type":"Point"}
}