{
  "type": "Feature",
  "properties": {
    "iso:country":"IN",
    "ks:ks_name":"Khatna Binpara",
    "ks:ks_pop":784,
    "ks:ks_type":"HABITATION",
    "name:eng_x_preferred":[
        "Khatna Binpara"
    ],
    "wof:name":"Khatna Binpara",
    "wof:placetype":"locality",
    "wof:population":784
},
  "geometry": {"coordinates":[87.851675,25.417092],"type":"Point"}
}