{
  "type": "Feature",
  "properties": {
    "iso:country":"IN",
    "ks:ks_name":"Muttinakeri",
    "ks:ks_pop":159,
    "ks:ks_type":"HABITATION",
    "name:eng_x_preferred":[
        "Muttinakeri"
    ],
    "wof:name":"Muttinakeri",
    "wof:placetype":"locality",
    "wof:population":159
},
  "geometry": {"coordinates":[74.822029,14.452835],"type":"Point"}
}