{
  "type": "Feature",
  "properties": {
    "iso:country":"IN",
    "ks:ks_name":"Karam Ghati",
    "ks:ks_pop":887,
    "ks:ks_type":"HABITATION",
    "name:eng_x_preferred":[
        "Karam Ghati"
    ],
    "wof:name":"Karam Ghati",
    "wof:placetype":"locality",
    "wof:population":887
},
  "geometry": {"coordinates":[82.952888,23.919964],"type":"Point"}
}