{
  "type": "Feature",
  "properties": {
    "iso:country":"IN",
    "ks:ks_name":"Nivati",
    "ks:ks_pop":85,
    "ks:ks_type":"HABITATION",
    "name:eng_x_preferred":[
        "Nivati"
    ],
    "wof:name":"Nivati",
    "wof:placetype":"locality",
    "wof:population":85
},
  "geometry": {"coordinates":[73.631816,15.909055],"type":"Point"}
}