{
  "type": "Feature",
  "properties": {
    "gn:admin1_code":"35",
    "gn:admin2_code":"455.0",
    "gn:asciiname":"Dhodakhapa",
    "gn:country_code":"IN",
    "gn:dem":531,
    "gn:feature_class":"P",
    "gn:feature_code":"PPL",
    "gn:name":"Dhod\u0101kh\u0101pa",
    "gn:population":0,
    "gn:timezone":"Asia/Kolkata",
    "iso:country":"IN",
    "ks:ks_alt_nam":"Dhod\u0101kh\u0101pa",
    "ks:ks_name":"Dhodakhapa",
    "ks:ks_pop":285,
    "ks:ks_type":"VILLAGE",
    "name:eng_x_preferred":[
        "Dhodakhapa"
    ],
    "name:eng_x_variant":[
        "Dhod\u0101kh\u0101pa"
    ],
    "wof:name":"Dhodakhapa",
    "wof:placetype":"locality",
    "wof:population":285
},
  "geometry": {"coordinates":[79.04157499999999,21.758155],"type":"Point"}
}