{
  "type": "Feature",
  "properties": {
    "iso:country":"IN",
    "ks:ks_name":"Jajoosan",
    "ks:ks_pop":1482,
    "ks:ks_type":"VILLAGE",
    "name:eng_x_preferred":[
        "Jajoosan"
    ],
    "wof:name":"Jajoosan",
    "wof:placetype":"locality",
    "wof:population":1482
},
  "geometry": {"coordinates":[71.802904,24.754495],"type":"Point"}
}