{
  "type": "Feature",
  "properties": {
    "gn:admin1_code":"24.0",
    "gn:admin2_code":"115",
    "gn:asciiname":"Koslu",
    "gn:country_code":"IN",
    "gn:dem":77,
    "gn:feature_class":"P",
    "gn:feature_code":"PPL",
    "gn:name":"Koslu",
    "gn:population":0,
    "gn:timezone":"Asia/Kolkata",
    "iso:country":"IN",
    "wof:name":"Koslu",
    "wof:placetype":"locality"
},
  "geometry": {"coordinates":[71.76815000000001,25.48953],"type":"Point"}
}