{
  "type": "Feature",
  "properties": {
    "gn:admin1_code":"21.0",
    "gn:admin2_code":"398.0",
    "gn:asciiname":"Chonda",
    "gn:country_code":"IN",
    "gn:dem":888,
    "gn:feature_class":"P",
    "gn:feature_code":"PPL",
    "gn:name":"Chonda",
    "gn:population":0,
    "gn:timezone":"Asia/Kolkata",
    "iso:country":"IN",
    "wof:name":"Chonda",
    "wof:placetype":"locality"
},
  "geometry": {"coordinates":[82.61960999999999,18.72325],"type":"Point"}
}