{
  "type": "Feature",
  "properties": {
    "iso:country":"IN",
    "ks:ks_name":"Malkariputtu",
    "ks:ks_pop":86,
    "ks:ks_type":"HABITATION",
    "name:eng_x_preferred":[
        "Malkariputtu"
    ],
    "wof:name":"Malkariputtu",
    "wof:placetype":"locality",
    "wof:population":86
},
  "geometry": {"coordinates":[82.524058,18.307182],"type":"Point"}
}