{
  "type": "Feature",
  "properties": {
    "iso:country":"IN",
    "ks:ks_name":"Guachopi",
    "ks:ks_pop":281,
    "ks:ks_type":"VILLAGE",
    "ks:ks_uagg_main":0,
    "name:eng_x_preferred":[
        "Guachopi"
    ],
    "wof:name":"Guachopi",
    "wof:placetype":"neighbourhood",
    "wof:population":281
},
  "geometry": {"coordinates":[87.13611899999999,21.726716],"type":"Point"}
}