{
  "type": "Feature",
  "properties": {
    "iso:country":"IN",
    "ks:ks_alt_nam":"chamrabad",
    "ks:ks_name":"Chamrabad",
    "ks:ks_pop":425,
    "ks:ks_type":"HABITATION",
    "ks:ks_uagg_main":0,
    "name:eng_x_preferred":[
        "Chamrabad"
    ],
    "wof:name":"Chamrabad",
    "wof:placetype":"neighbourhood",
    "wof:population":425
},
  "geometry": {"coordinates":[86.32825699999999,23.586208],"type":"Point"}
}