{
  "type": "Feature",
  "properties": {
    "iso:country":"IN",
    "ks:ks_name":"Bhelsharh",
    "ks:ks_pop":983,
    "ks:ks_type":"VILLAGE",
    "name:eng_x_preferred":[
        "Bhelsharh"
    ],
    "wof:name":"Bhelsharh",
    "wof:placetype":"locality",
    "wof:population":983
},
  "geometry": {"coordinates":[84.241381,25.7361],"type":"Point"}
}