{
  "type": "Feature",
  "properties": {
    "iso:country":"IN",
    "ks:ks_name":"Purusotampur",
    "ks:ks_pop":1216,
    "ks:ks_type":"VILLAGE",
    "name:eng_x_preferred":[
        "Purusotampur"
    ],
    "wof:name":"Purusotampur",
    "wof:placetype":"locality",
    "wof:population":1216
},
  "geometry": {"coordinates":[85.849056,20.864498],"type":"Point"}
}