{
  "type": "Feature",
  "properties": {
    "iso:country":"IN",
    "ks:ks_name":"Muniya",
    "ks:ks_pop":180,
    "ks:ks_type":"HABITATION",
    "name:eng_x_preferred":[
        "Muniya"
    ],
    "wof:name":"Muniya",
    "wof:placetype":"locality",
    "wof:population":180
},
  "geometry": {"coordinates":[74.561939,23.194644],"type":"Point"}
}