{
  "type": "Feature",
  "properties": {
    "gn:admin1_code":"34.0",
    "gn:admin2_code":"236.0",
    "gn:asciiname":"Kabar",
    "gn:country_code":"IN",
    "gn:dem":105,
    "gn:feature_class":"P",
    "gn:feature_code":"PPL",
    "gn:name":"K\u0101bar",
    "gn:population":0,
    "gn:timezone":"Asia/Kolkata",
    "iso:country":"IN",
    "name:aze_x_preferred":[
        "K\u0259b\u0259rl\u0259r"
    ],
    "name:bul_x_preferred":[
        "\u041a\u0430\u0431\u0430\u0440\u0438"
    ],
    "name:chv_x_preferred":[
        "\u041a\u0430\u0432\u0430\u0440\u0441\u0435\u043c"
    ],
    "name:deu_x_preferred":[
        "Kabaren"
    ],
    "name:fra_x_preferred":[
        "Kabars"
    ],
    "name:heb_x_preferred":[
        "\u05e7\u05d0\u05d1\u05d0\u05e8\u05d9\u05dd"
    ],
    "name:hun_x_preferred":[
        "Kavarok"
    ],
    "name:pol_x_preferred":[
        "Kabarowie"
    ],
    "name:ron_x_preferred":[
        "Kavari"
    ],
    "name:rus_x_preferred":[
        "\u041a\u0430\u0432\u0430\u0440\u044b"
    ],
    "name:spa_x_preferred":[
        "Kabar"
    ],
    "name:srp_x_preferred":[
        "\u041a\u0430\u0431\u0430\u0440\u0438"
    ],
    "name:tur_x_preferred":[
        "Kabarlar"
    ],
    "name:ukr_x_preferred":[
        "\u041a\u0430\u0432\u0430\u0440\u0438"
    ],
    "name:zho_x_preferred":[
        "\u5361\u5df4\u723e\u4eba"
    ],
    "wof:name":"Kabar",
    "wof:placetype":"locality"
},
  "geometry": {"coordinates":[84.74037,24.88388],"type":"Point"}
}