{
  "type": "Feature",
  "properties": {
    "iso:country":"IN",
    "ks:ks_name":"Tembwadi",
    "ks:ks_pop":107,
    "ks:ks_type":"HABITATION",
    "name:eng_x_preferred":[
        "Tembwadi"
    ],
    "wof:name":"Tembwadi",
    "wof:placetype":"locality",
    "wof:population":107
},
  "geometry": {"coordinates":[73.75042000000001,16.226088],"type":"Point"}
}