{
  "type": "Feature",
  "properties": {
    "gn:admin1_code":"34.0",
    "gn:admin2_code":"231.0",
    "gn:asciiname":"Semariya",
    "gn:country_code":"IN",
    "gn:dem":63,
    "gn:feature_class":"P",
    "gn:feature_code":"PPL",
    "gn:name":"Semariya",
    "gn:population":0,
    "gn:timezone":"Asia/Kolkata",
    "iso:country":"IN",
    "ks:ks_name":"Semariya",
    "ks:ks_type":"VILLAGE",
    "ks:ks_uagg_main":0,
    "name:eng_x_preferred":[
        "Semariya"
    ],
    "name:und_x_variant":[
        "Patti Ojha"
    ],
    "wof:name":"Semariya",
    "wof:placetype":"neighbourhood"
},
  "geometry": {"coordinates":[84.437904,25.632975],"type":"Point"}
}