{
  "type": "Feature",
  "properties": {
    "iso:country":"IN",
    "ks:ks_name":"Chakbagi",
    "ks:ks_pop":1831,
    "ks:ks_type":"VILLAGE",
    "ks:ks_uagg_main":0,
    "name:eng_x_preferred":[
        "Chakbagi"
    ],
    "wof:name":"Chakbagi",
    "wof:placetype":"locality",
    "wof:population":1831
},
  "geometry": {"coordinates":[88.275541,22.386229],"type":"Point"}
}