{
  "type": "Feature",
  "properties": {
    "iso:country":"IN",
    "ks:ks_name":"Kewtahi Ahiran Purwa",
    "ks:ks_pop":200,
    "ks:ks_type":"HABITATION",
    "ks:ks_uagg_main":0,
    "name:eng_x_preferred":[
        "Kewtahi Ahiran Purwa"
    ],
    "wof:name":"Kewtahi Ahiran Purwa",
    "wof:placetype":"neighbourhood",
    "wof:population":200
},
  "geometry": {"coordinates":[81.83991899999999,26.940036],"type":"Point"}
}