{
  "type": "Feature",
  "properties": {
    "gn:admin1_code":"19.0",
    "gn:admin2_code":"569.0",
    "gn:asciiname":"Abbanabettu",
    "gn:country_code":"IN",
    "gn:dem":87,
    "gn:feature_class":"P",
    "gn:feature_code":"PPL",
    "gn:name":"Abbanabettu",
    "gn:population":0,
    "gn:timezone":"Asia/Kolkata",
    "iso:country":"IN",
    "ks:ks_alt_nam":"Abbanabettu HC",
    "ks:ks_name":"Abbanabettu Hc",
    "ks:ks_pop":180,
    "ks:ks_type":"HABITATION",
    "name:eng_x_preferred":[
        "Abbanabettu Hc"
    ],
    "name:eng_x_variant":[
        "Abbanabettu"
    ],
    "wof:name":"Abbanabettu Hc",
    "wof:placetype":"locality",
    "wof:population":180
},
  "geometry": {"coordinates":[75.055164,13.209325],"type":"Point"}
}