{
  "type": "Feature",
  "properties": {
    "iso:country":"IN",
    "ks:ks_name":"Chodapalli",
    "ks:ks_pop":261,
    "ks:ks_type":"VILLAGE",
    "name:eng_x_preferred":[
        "Chodapalli"
    ],
    "wof:name":"Chodapalli",
    "wof:placetype":"locality",
    "wof:population":261
},
  "geometry": {"coordinates":[82.717583,17.985678],"type":"Point"}
}