{
  "type": "Feature",
  "properties": {
    "iso:country":"IN",
    "ks:ks_alt_nam":"Tand\u0101padar",
    "ks:ks_name":"Tandapadar",
    "ks:ks_type":"VILLAGE",
    "name:eng_x_preferred":[
        "Tandapadar"
    ],
    "name:eng_x_variant":[
        "Tand\u0101padar"
    ],
    "wof:name":"Tandapadar",
    "wof:placetype":"locality"
},
  "geometry": {"coordinates":[84.079291,20.640808],"type":"Point"}
}