{
  "type": "Feature",
  "properties": {
    "iso:country":"IN",
    "ks:ks_name":"Serawa",
    "ks:ks_pop":538,
    "ks:ks_type":"VILLAGE",
    "name:eng_x_preferred":[
        "Serawa"
    ],
    "wof:name":"Serawa",
    "wof:placetype":"locality",
    "wof:population":538
},
  "geometry": {"coordinates":[70.599372,27.216622],"type":"Point"}
}