{
  "type": "Feature",
  "properties": {
    "iso:country":"IN",
    "ks:ks_alt_nam":"NAIK MALI VASTI",
    "ks:ks_name":"Naik Mali Vasti",
    "ks:ks_pop":202,
    "ks:ks_type":"HABITATION",
    "name:eng_x_preferred":[
        "Naik Mali Vasti"
    ],
    "wof:name":"Naik Mali Vasti",
    "wof:placetype":"locality",
    "wof:population":202
},
  "geometry": {"coordinates":[74.822582,16.777618],"type":"Point"}
}