{
  "type": "Feature",
  "properties": {
    "iso:country":"IN",
    "ks:ks_name":"Maharikala",
    "ks:ks_pop":1451,
    "ks:ks_type":"HABITATION",
    "name:eng_x_preferred":[
        "Maharikala"
    ],
    "wof:name":"Maharikala",
    "wof:placetype":"locality",
    "wof:population":1451
},
  "geometry": {"coordinates":[82.933849,24.043894],"type":"Point"}
}