{
  "type": "Feature",
  "properties": {
    "gn:admin1_code":"21.0",
    "gn:admin2_code":"386",
    "gn:asciiname":"Haladia",
    "gn:country_code":"IN",
    "gn:dem":42,
    "gn:feature_class":"P",
    "gn:feature_code":"PPL",
    "gn:name":"Haladia",
    "gn:population":0,
    "gn:timezone":"Asia/Kolkata",
    "iso:country":"IN",
    "wof:name":"Haladia",
    "wof:placetype":"locality"
},
  "geometry": {"coordinates":[85.56667,20.26667],"type":"Point"}
}