{
  "type": "Feature",
  "properties": {
    "iso:country":"IN",
    "ks:ks_alt_nam":"6 KD",
    "ks:ks_name":"6 Kd",
    "ks:ks_pop":209,
    "ks:ks_type":"HABITATION",
    "name:eng_x_preferred":[
        "6 Kd"
    ],
    "wof:name":"6 Kd",
    "wof:placetype":"locality",
    "wof:population":209
},
  "geometry": {"coordinates":[72.9211,28.903286],"type":"Point"}
}