{
  "type": "Feature",
  "properties": {
    "iso:country":"IN",
    "ks:ks_name":"Kondawahi",
    "ks:ks_pop":441,
    "ks:ks_type":"HABITATION",
    "name:eng_x_preferred":[
        "Kondawahi"
    ],
    "wof:name":"Kondawahi",
    "wof:placetype":"locality",
    "wof:population":441
},
  "geometry": {"coordinates":[80.292255,20.08837],"type":"Point"}
}