{
  "type": "Feature",
  "properties": {
    "gn:admin1_code":"36",
    "gn:admin2_code":"178.0",
    "gn:asciiname":"Bibipur",
    "gn:country_code":"IN",
    "gn:dem":93,
    "gn:feature_class":"P",
    "gn:feature_code":"PPL",
    "gn:name":"B\u012bb\u012bpur",
    "gn:population":0,
    "gn:timezone":"Asia/Kolkata",
    "iso:country":"IN",
    "ks:ks_alt_nam":"B\u012bb\u012bpur",
    "ks:ks_name":"Bibipur",
    "ks:ks_pop":514,
    "ks:ks_type":"VILLAGE",
    "ks:ks_uagg_main":0,
    "name:eng_x_preferred":[
        "Bibipur"
    ],
    "name:eng_x_variant":[
        "B\u012bb\u012bpur"
    ],
    "wof:name":"Bibipur",
    "wof:placetype":"neighbourhood",
    "wof:population":514
},
  "geometry": {"coordinates":[82.581445,26.283656],"type":"Point"}
}