{
  "type": "Feature",
  "properties": {
    "iso:country":"IN",
    "ks:ks_name":"Bazar Para",
    "ks:ks_pop":1000,
    "ks:ks_type":"HABITATION",
    "name:eng_x_preferred":[
        "Bazar Para"
    ],
    "wof:name":"Bazar Para",
    "wof:placetype":"locality",
    "wof:population":1000
},
  "geometry": {"coordinates":[88.704798,22.195635],"type":"Point"}
}