{
  "type": "Feature",
  "properties": {
    "iso:country":"IN",
    "ks:ks_name":"Nothiyarupadi",
    "ks:ks_pop":328,
    "ks:ks_type":"HABITATION",
    "name:eng_x_preferred":[
        "Nothiyarupadi"
    ],
    "wof:name":"Nothiyarupadi",
    "wof:placetype":"locality",
    "wof:population":328
},
  "geometry": {"coordinates":[76.29758200000001,10.956479],"type":"Point"}
}