{
  "type": "Feature",
  "properties": {
    "iso:country":"IN",
    "ks:ks_name":"Vanjarwadi",
    "ks:ks_pop":192,
    "ks:ks_type":"HABITATION",
    "name:eng_x_preferred":[
        "Vanjarwadi"
    ],
    "wof:name":"Vanjarwadi",
    "wof:placetype":"locality",
    "wof:population":192
},
  "geometry": {"coordinates":[76.122934,19.070881],"type":"Point"}
}