{
  "type": "Feature",
  "properties": {
    "iso:country":"IN",
    "ks:ks_name":"Kaparwal",
    "ks:ks_pop":851,
    "ks:ks_type":"HABITATION",
    "name:eng_x_preferred":[
        "Kaparwal"
    ],
    "wof:name":"Kaparwal",
    "wof:placetype":"locality",
    "wof:population":851
},
  "geometry": {"coordinates":[81.386005,27.48712],"type":"Point"}
}