{
  "type": "Feature",
  "properties": {
    "gn:admin1_code":"12.0",
    "gn:admin2_code":"008",
    "gn:asciiname":"Thukarpur",
    "gn:country_code":"IN",
    "gn:dem":1597,
    "gn:feature_class":"P",
    "gn:feature_code":"PPL",
    "gn:name":"Thukarpur",
    "gn:population":0,
    "gn:timezone":"Asia/Kolkata",
    "iso:country":"IN",
    "name:und_x_variant":[
        "Thukatpur"
    ],
    "wof:name":"Thukarpur",
    "wof:placetype":"locality"
},
  "geometry": {"coordinates":[74.35862,34.34546],"type":"Point"}
}