{
  "type": "Feature",
  "properties": {
    "gn:admin1_code":"19.0",
    "gn:admin2_code":"573.0",
    "gn:asciiname":"Mangravalli",
    "gn:country_code":"IN",
    "gn:dem":894,
    "gn:feature_class":"P",
    "gn:feature_code":"PPL",
    "gn:name":"Mangravalli",
    "gn:population":0,
    "gn:timezone":"Asia/Kolkata",
    "iso:country":"IN",
    "wof:name":"Mangravalli",
    "wof:placetype":"locality"
},
  "geometry": {"coordinates":[76.61179,12.89693],"type":"Point"}
}