{
  "type": "Feature",
  "properties": {
    "iso:country":"IN",
    "ks:ks_name":"Lakshmi Nagar",
    "ks:ks_pop":342,
    "ks:ks_type":"HABITATION",
    "ks:ks_uagg_main":0,
    "name:eng_x_preferred":[
        "Lakshmi Nagar"
    ],
    "wof:name":"Lakshmi Nagar",
    "wof:placetype":"locality",
    "wof:population":342
},
  "geometry": {"coordinates":[79.993088,12.744198],"type":"Point"}
}