{
  "type": "Feature",
  "properties": {
    "iso:country":"IN",
    "ks:ks_name":"Rekameta",
    "ks:ks_pop":176,
    "ks:ks_type":"VILLAGE",
    "name:eng_x_preferred":[
        "Rekameta"
    ],
    "wof:name":"Rekameta",
    "wof:placetype":"locality",
    "wof:population":176
},
  "geometry": {"coordinates":[80.57222299999999,19.717472],"type":"Point"}
}