{
  "type": "Feature",
  "properties": {
    "gn:admin1_code":"36",
    "gn:admin2_code":"169.0",
    "gn:asciiname":"Gauhari",
    "gn:country_code":"IN",
    "gn:dem":168,
    "gn:feature_class":"P",
    "gn:feature_code":"PPL",
    "gn:name":"Gauh\u0101ri",
    "gn:population":0,
    "gn:timezone":"Asia/Kolkata",
    "iso:country":"IN",
    "name:eng_x_preferred":[
        "Gauh\u0101ri"
    ],
    "wof:name":"Gauhari",
    "wof:placetype":"neighbourhood"
},
  "geometry": {"coordinates":[80.00490000000001,25.40255],"type":"Point"}
}