{
  "type": "Feature",
  "properties": {
    "iso:country":"IN",
    "ks:ks_name":"Sitalbasa",
    "ks:ks_pop":536,
    "ks:ks_type":"HABITATION",
    "name:eng_x_preferred":[
        "Sitalbasa"
    ],
    "wof:name":"Sitalbasa",
    "wof:placetype":"locality",
    "wof:population":536
},
  "geometry": {"coordinates":[85.708502,20.9725],"type":"Point"}
}