{
  "type": "Feature",
  "properties": {
    "gn:admin1_code":"35",
    "gn:admin2_code":"422.0",
    "gn:asciiname":"Bajera",
    "gn:country_code":"IN",
    "gn:dem":194,
    "gn:feature_class":"P",
    "gn:feature_code":"PPL",
    "gn:name":"Bajera",
    "gn:population":0,
    "gn:timezone":"Asia/Kolkata",
    "iso:country":"IN",
    "name:und_x_variant":[
        "Barjorpura"
    ],
    "wof:name":"Bajera",
    "wof:placetype":"neighbourhood"
},
  "geometry": {"coordinates":[78.49814000000001,25.87677],"type":"Point"}
}