{
  "type": "Feature",
  "properties": {
    "iso:country":"IN",
    "ks:ks_name":"Machhalawa",
    "ks:ks_pop":152,
    "ks:ks_type":"VILLAGE",
    "name:eng_x_preferred":[
        "Machhalawa"
    ],
    "wof:name":"Machhalawa",
    "wof:placetype":"locality",
    "wof:population":152
},
  "geometry": {"coordinates":[82.97371,24.781672],"type":"Point"}
}