{
  "type": "Feature",
  "properties": {
    "iso:country":"IN",
    "ks:ks_name":"Naguguda",
    "ks:ks_pop":134,
    "ks:ks_type":"HABITATION",
    "name:eng_x_preferred":[
        "Naguguda"
    ],
    "wof:name":"Naguguda",
    "wof:placetype":"locality",
    "wof:population":134
},
  "geometry": {"coordinates":[79.13292199999999,19.208762],"type":"Point"}
}