{
  "type": "Feature",
  "properties": {
    "iso:country":"IN",
    "ks:ks_name":"Chandmari",
    "ks:ks_pop":1871,
    "ks:ks_type":"VILLAGE",
    "ks:ks_uagg_main":0,
    "name:eng_x_preferred":[
        "Chandmari"
    ],
    "wof:name":"Chandmari",
    "wof:placetype":"locality",
    "wof:population":1871
},
  "geometry": {"coordinates":[94.084316,27.278586],"type":"Point"}
}