{
  "type": "Feature",
  "properties": {
    "gn:country":"IN",
    "gn:fcode":"PPLX",
    "gn:population":0,
    "iso:country":"IN",
    "name:eng_x_preferred":[
        "Trustpuram"
    ],
    "name:fas_x_preferred":[
        "\u062a\u0631\u0627\u0633\u062a\u200c\u067e\u0648\u0631\u0627\u0645"
    ],
    "name:tam_x_preferred":[
        "\u0b9f\u0bbf\u0bb0\u0bb8\u0bcd\u0b9f\u0bcd \u0baa\u0bc1\u0bb0\u0bae\u0bcd"
    ],
    "name:urd_x_preferred":[
        "\u062a\u0631\u0633\u062a \u067e\u0648\u0631\u0645"
    ],
    "qs:name":"Trustpuram",
    "qs:name_adm0":"India",
    "qs:name_adm1":"Tamil Nadu",
    "qs:photos":1,
    "qs:photos_1k":1,
    "qs:photos_9k":1,
    "qs:photos_9r":1,
    "qs:photos_all":1,
    "qs:photos_sr":1,
    "qs:placetype":"Suburb",
    "qs:pop_sr":"0",
    "wd:wordcount":108,
    "wof:name":"Trustpuram",
    "wof:placetype":"neighbourhood",
    "wof:population":0
},
  "geometry": {"coordinates":[80.22528,13.05444],"type":"Point"}
}