{
  "type": "Feature",
  "properties": {
    "iso:country":"IN",
    "ks:ks_name":"Sarai",
    "ks:ks_pop":960,
    "ks:ks_type":"VILLAGE",
    "ks:ks_uagg_main":0,
    "name:eng_x_preferred":[
        "Sarai"
    ],
    "wof:name":"Sarai",
    "wof:placetype":"neighbourhood",
    "wof:population":960
},
  "geometry": {"coordinates":[80.278858,28.308109],"type":"Point"}
}