{
  "type": "Feature",
  "properties": {
    "gn:admin1_code":"21.0",
    "gn:admin2_code":"396.0",
    "gn:asciiname":"Puvalaguda",
    "gn:country_code":"IN",
    "gn:dem":356,
    "gn:feature_class":"P",
    "gn:feature_code":"PPL",
    "gn:name":"Puvalaguda",
    "gn:population":0,
    "gn:timezone":"Asia/Kolkata",
    "iso:country":"IN",
    "ks:ks_name":"Phulaguda",
    "ks:ks_pop":220,
    "ks:ks_type":"VILLAGE",
    "name:eng_x_preferred":[
        "Phulaguda"
    ],
    "name:eng_x_variant":[
        "Puvalaguda"
    ],
    "wof:name":"Phulaguda",
    "wof:placetype":"locality",
    "wof:population":220
},
  "geometry": {"coordinates":[83.539618,19.381833],"type":"Point"}
}