{
  "type": "Feature",
  "properties": {
    "iso:country":"IN",
    "ks:ks_name":"Haripura",
    "ks:ks_pop":0,
    "ks:ks_type":"VILLAGE",
    "name:eng_x_preferred":[
        "Haripura"
    ],
    "wof:name":"Haripura",
    "wof:placetype":"locality",
    "wof:population":0
},
  "geometry": {"coordinates":[75.782141,24.254665],"type":"Point"}
}