{
  "type": "Feature",
  "properties": {
    "iso:country":"IN",
    "ks:ks_name":"Sahadapalli",
    "ks:ks_pop":4,
    "ks:ks_type":"VILLAGE",
    "ks:ks_uagg_main":0,
    "name:eng_x_preferred":[
        "Sahadapalli"
    ],
    "wof:name":"Sahadapalli",
    "wof:placetype":"neighbourhood",
    "wof:population":4
},
  "geometry": {"coordinates":[85.395589,19.920351],"type":"Point"}
}