{
  "type": "Feature",
  "properties": {
    "iso:country":"IN",
    "ks:ks_name":"Dhebulmala",
    "ks:ks_pop":3580,
    "ks:ks_type":"HABITATION",
    "name:eng_x_preferred":[
        "Dhebulmala"
    ],
    "wof:name":"Dhebulmala",
    "wof:placetype":"locality",
    "wof:population":3580
},
  "geometry": {"coordinates":[74.15840300000001,20.440196],"type":"Point"}
}