{
  "type": "Feature",
  "properties": {
    "iso:country":"IN",
    "ks:ks_name":"Gurlabahal",
    "ks:ks_pop":0,
    "ks:ks_type":"VILLAGE",
    "name:eng_x_preferred":[
        "Gurlabahal"
    ],
    "wof:name":"Gurlabahal",
    "wof:placetype":"locality",
    "wof:population":0
},
  "geometry": {"coordinates":[84.202898,21.918067],"type":"Point"}
}