{
  "type": "Feature",
  "properties": {
    "gn:admin1_code":"24.0",
    "gn:admin2_code":"129.0",
    "gn:asciiname":"Gobardhanpura",
    "gn:country_code":"IN",
    "gn:dem":359,
    "gn:feature_class":"P",
    "gn:feature_code":"PPL",
    "gn:name":"Gobardhanpura",
    "gn:population":0,
    "gn:timezone":"Asia/Kolkata",
    "iso:country":"IN",
    "wof:name":"Gobardhanpura",
    "wof:placetype":"locality"
},
  "geometry": {"coordinates":[76.35443000000002,24.35125],"type":"Point"}
}