{
  "type": "Feature",
  "properties": {
    "iso:country":"IN",
    "ks:ks_name":"Sarada",
    "ks:ks_pop":206,
    "ks:ks_type":"HABITATION",
    "name:eng_x_preferred":[
        "Sarada"
    ],
    "wof:name":"Sarada",
    "wof:placetype":"locality",
    "wof:population":206
},
  "geometry": {"coordinates":[85.646647,21.192177],"type":"Point"}
}