{
  "type": "Feature",
  "properties": {
    "gn:admin1_code":"12.0",
    "gn:admin2_code":"1.0",
    "gn:asciiname":"Zimindarkhan",
    "gn:country_code":"IN",
    "gn:dem":1648,
    "gn:feature_class":"P",
    "gn:feature_code":"PPL",
    "gn:name":"Zimind\u0101rkhan",
    "gn:population":0,
    "gn:timezone":"Asia/Kolkata",
    "iso:country":"IN",
    "wof:name":"Zimindarkhan",
    "wof:placetype":"locality"
},
  "geometry": {"coordinates":[74.25529,34.53909],"type":"Point"}
}