{
  "type": "Feature",
  "properties": {
    "gn:admin1_code":"34.0",
    "gn:admin2_code":"225.0",
    "gn:asciiname":"Kachmachia",
    "gn:country_code":"IN",
    "gn:dem":85,
    "gn:feature_class":"P",
    "gn:feature_code":"PPL",
    "gn:name":"Kachmachia",
    "gn:population":0,
    "gn:timezone":"Asia/Kolkata",
    "iso:country":"IN",
    "ks:ks_name":"Kachmachia",
    "ks:ks_pop":1152,
    "ks:ks_type":"VILLAGE",
    "name:eng_x_preferred":[
        "Kachmachia"
    ],
    "wof:name":"Kachmachia",
    "wof:placetype":"locality",
    "wof:population":1152
},
  "geometry": {"coordinates":[87.08448,24.848063],"type":"Point"}
}