{
  "type": "Feature",
  "properties": {
    "iso:country":"IN",
    "ks:ks_name":"Durgapur Road",
    "ks:ks_pop":369,
    "ks:ks_type":"HABITATION",
    "name:eng_x_preferred":[
        "Durgapur Road"
    ],
    "wof:name":"Durgapur Road",
    "wof:placetype":"locality",
    "wof:population":369
},
  "geometry": {"coordinates":[74.419318,19.570639],"type":"Point"}
}