{
  "type": "Feature",
  "properties": {
    "iso:country":"IN",
    "ks:ks_name":"Venukonda",
    "ks:ks_pop":52,
    "ks:ks_type":"HABITATION",
    "name:eng_x_preferred":[
        "Venukonda"
    ],
    "wof:name":"Venukonda",
    "wof:placetype":"locality",
    "wof:population":52
},
  "geometry": {"coordinates":[83.028609,18.199031],"type":"Point"}
}