{
  "type": "Feature",
  "properties": {
    "gn:admin1_code":"36.0",
    "gn:admin2_code":"177.0",
    "gn:asciiname":"Ahrauli",
    "gn:country_code":"IN",
    "gn:dem":93,
    "gn:feature_class":"P",
    "gn:feature_code":"PPL",
    "gn:name":"Ahrauli",
    "gn:population":0,
    "gn:timezone":"Asia/Kolkata",
    "iso:country":"IN",
    "ks:ks_name":"Aharauli",
    "ks:ks_pop":474,
    "ks:ks_type":"VILLAGE",
    "name:eng_x_preferred":[
        "Aharauli"
    ],
    "name:eng_x_variant":[
        "Ahrauli"
    ],
    "wof:name":"Aharauli",
    "wof:placetype":"locality",
    "wof:population":474
},
  "geometry": {"coordinates":[81.768604,26.851923],"type":"Point"}
}