{
  "type": "Feature",
  "properties": {
    "gn:admin1_code":"34.0",
    "gn:admin2_code":"219.0",
    "gn:asciiname":"Balua Mardan",
    "gn:country_code":"IN",
    "gn:dem":60,
    "gn:feature_class":"P",
    "gn:feature_code":"PPL",
    "gn:name":"Balua Mardan",
    "gn:population":0,
    "gn:timezone":"Asia/Kolkata",
    "iso:country":"IN",
    "ks:ks_name":"Balua Mardan",
    "ks:ks_pop":261,
    "ks:ks_type":"VILLAGE",
    "name:eng_x_preferred":[
        "Balua Mardan"
    ],
    "wof:name":"Balua Mardan",
    "wof:placetype":"locality",
    "wof:population":261
},
  "geometry": {"coordinates":[84.904101,26.047773],"type":"Point"}
}