{
  "type": "Feature",
  "properties": {
    "iso:country":"IN",
    "ks:ks_name":"Chunki Ka Dera",
    "ks:ks_pop":124,
    "ks:ks_type":"HABITATION",
    "name:eng_x_preferred":[
        "Chunki Ka Dera"
    ],
    "wof:name":"Chunki Ka Dera",
    "wof:placetype":"locality",
    "wof:population":124
},
  "geometry": {"coordinates":[80.323246,25.884059],"type":"Point"}
}