{
  "type": "Feature",
  "properties": {
    "iso:country":"IN",
    "ks:ks_name":"Abdullapuram",
    "ks:ks_pop":1361,
    "ks:ks_type":"VILLAGE",
    "ks:ks_uagg_main":0,
    "name:eng_x_preferred":[
        "Abdullapuram"
    ],
    "wof:name":"Abdullapuram",
    "wof:placetype":"locality",
    "wof:population":1361
},
  "geometry": {"coordinates":[79.08521500000001,12.913945],"type":"Point"}
}