{
  "type": "Feature",
  "properties": {
    "gn:admin1_code":"36",
    "gn:admin2_code":"198.0",
    "gn:asciiname":"Chak Jura",
    "gn:country_code":"IN",
    "gn:dem":90,
    "gn:feature_class":"P",
    "gn:feature_code":"PPL",
    "gn:name":"Chak J\u016bra",
    "gn:population":0,
    "gn:timezone":"Asia/Kolkata",
    "iso:country":"IN",
    "wof:name":"Chak Jura",
    "wof:placetype":"locality"
},
  "geometry": {"coordinates":[82.44019,25.39421],"type":"Point"}
}