{
  "type": "Feature",
  "properties": {
    "gn:admin1_code":"37.0",
    "gn:admin2_code":"400",
    "gn:asciiname":"Dewadand",
    "gn:country_code":"IN",
    "gn:dem":401,
    "gn:feature_class":"P",
    "gn:feature_code":"PPL",
    "gn:name":"Dewadand",
    "gn:population":0,
    "gn:timezone":"Asia/Kolkata",
    "iso:country":"IN",
    "wof:name":"Dewadand",
    "wof:placetype":"locality"
},
  "geometry": {"coordinates":[82.30296,23.03154],"type":"Point"}
}