{
  "type": "Feature",
  "properties": {
    "iso:country":"IN",
    "ks:ks_name":"Bandimut",
    "ks:ks_pop":80,
    "ks:ks_type":"HABITATION",
    "name:eng_x_preferred":[
        "Bandimut"
    ],
    "wof:name":"Bandimut",
    "wof:placetype":"locality",
    "wof:population":80
},
  "geometry": {"coordinates":[75.063106,13.489693],"type":"Point"}
}