{
  "type": "Feature",
  "properties": {
    "iso:country":"IN",
    "ks:ks_alt_nam":"V Nagaram colony",
    "ks:ks_name":"V Nagaram Colony",
    "ks:ks_pop":200,
    "ks:ks_type":"HABITATION",
    "name:eng_x_preferred":[
        "V Nagaram Colony"
    ],
    "wof:name":"V Nagaram Colony",
    "wof:placetype":"locality",
    "wof:population":200
},
  "geometry": {"coordinates":[82.489062,17.438449],"type":"Point"}
}