{
  "type": "Feature",
  "properties": {
    "gn:admin1_code":"37",
    "gn:admin2_code":"406.0",
    "gn:asciiname":"Dhelwa",
    "gn:country_code":"IN",
    "gn:dem":588,
    "gn:feature_class":"P",
    "gn:feature_code":"PPL",
    "gn:name":"Dhelwa",
    "gn:population":0,
    "gn:timezone":"Asia/Kolkata",
    "iso:country":"IN",
    "wof:name":"Dhelwa",
    "wof:placetype":"locality"
},
  "geometry": {"coordinates":[82.15689999999999,22.73696],"type":"Point"}
}