{
  "type": "Feature",
  "properties": {
    "gn:admin1_code":"21",
    "gn:admin2_code":"395.0",
    "gn:asciiname":"Semelguda",
    "gn:country_code":"IN",
    "gn:dem":808,
    "gn:feature_class":"P",
    "gn:feature_code":"PPL",
    "gn:name":"Semelguda",
    "gn:population":0,
    "gn:timezone":"Asia/Kolkata",
    "iso:country":"IN",
    "ks:ks_name":"Semelguda",
    "ks:ks_type":"VILLAGE",
    "name:eng_x_preferred":[
        "Semelguda"
    ],
    "wof:name":"Semelguda",
    "wof:placetype":"locality"
},
  "geometry": {"coordinates":[83.17853599999999,19.67867],"type":"Point"}
}