{
  "type": "Feature",
  "properties": {
    "gn:admin1_code":"2",
    "gn:admin2_code":"547.0",
    "gn:asciiname":"Mandapadu",
    "gn:country_code":"IN",
    "gn:dem":8,
    "gn:feature_class":"P",
    "gn:feature_code":"PPL",
    "gn:name":"Mandap\u0101du",
    "gn:population":0,
    "gn:timezone":"Asia/Kolkata",
    "iso:country":"IN",
    "ks:ks_name":"Mandapadu",
    "ks:ks_pop":644,
    "ks:ks_type":"HABITATION",
    "ks:ks_uagg_main":0,
    "name:eng_x_preferred":[
        "Mandapadu"
    ],
    "wof:name":"Mandapadu",
    "wof:placetype":"neighbourhood",
    "wof:population":644
},
  "geometry": {"coordinates":[81.34729799999999,16.561686],"type":"Point"}
}