{
  "type": "Feature",
  "properties": {
    "gn:country":"IN",
    "gn:fcode":"PPL",
    "gn:pop":32504,
    "iso:country":"IN",
    "name:ben_x_preferred":[
        "\u09ae\u09be\u09b9\u09c7\u09ae\u09a6\u09be\u09ad\u09be\u09a6"
    ],
    "name:bpy_x_preferred":[
        "\u09ae\u09be\u09b9\u09be\u09ae\u09c7\u09a6\u09be\u09ac\u09be\u09a6"
    ],
    "name:deu_x_preferred":[
        "Mahemdavad"
    ],
    "name:eng_x_preferred":[
        "Mahemdavad"
    ],
    "name:fra_x_preferred":[
        "Mahemdavad"
    ],
    "name:guj_x_preferred":[
        "\u0aae\u0ab9\u0ac7\u0aae\u0aa6\u0abe\u0ab5\u0abe\u0aa6"
    ],
    "name:ita_x_preferred":[
        "Mahemdavad"
    ],
    "name:jpn_x_preferred":[
        "\u30de\u30d8\u30f3\u30c0\u30f4\u30a1\u30c3\u30c9"
    ],
    "name:kan_x_preferred":[
        "\u0cae\u0cb9\u0cc7\u0c82\u0ca6\u0cbe\u0cb5\u0cbe\u0ca6\u0ccd"
    ],
    "name:kor_x_preferred":[
        "\ub9c8\ud5e8\ub4dc\ubc14\ub4dc"
    ],
    "name:msa_x_preferred":[
        "Mahemdavad"
    ],
    "name:new_x_preferred":[
        "\u092e\u0939\u0947\u092e\u094d\u0926\u093e\u0935\u093e\u0926"
    ],
    "name:nld_x_preferred":[
        "Mahemdavad"
    ],
    "name:ori_x_preferred":[
        "\u0b2e\u0b39\u0b47\u0b2e\u0b26\u0b3e\u0b2c\u0b3e\u0b26\u0b4d"
    ],
    "name:pnb_x_preferred":[
        "\u0645\u06c1\u0645\u062f \u0622\u0628\u0627\u062f"
    ],
    "name:por_x_preferred":[
        "Mahemdavad"
    ],
    "name:rus_x_preferred":[
        "\u041c\u0430\u0445\u0435\u043c\u0434\u0430\u0432\u0430\u0434"
    ],
    "name:spa_x_preferred":[
        "Mahemdavad"
    ],
    "name:swe_x_preferred":[
        "Mahemd\u0101v\u0101d"
    ],
    "name:tam_x_preferred":[
        "\u0bae\u0bb9\u0bc0\u0bae\u0bcd\u0b9f\u0bc7\u0bb5\u0bbf\u0b9f\u0bcd"
    ],
    "name:tel_x_preferred":[
        "\u0c2e\u0c39\u0c47\u0c26\u0c4d\u0c35\u0c3e\u0c26\u0c4d"
    ],
    "name:unk_x_variant":[
        "Mehmad\u0101b\u0101d"
    ],
    "name:urd_x_preferred":[
        "\u0645\u06c1\u0645\u062f \u0622\u0628\u0627\u062f"
    ],
    "name:vie_x_preferred":[
        "Mahemdavad"
    ],
    "name:zho_x_preferred":[
        "\u9a6c\u8d6b\u59c6\u8fbe\u74e6\u5fb7"
    ],
    "qs:name":"Mahemd\u0101v\u0101d",
    "qs:photos_9r":0,
    "qs:photos_sr":0,
    "qs:pop_sr":"7",
    "wd:wordcount":832,
    "wof:name":"Mahemd\u0101v\u0101d",
    "wof:placetype":"locality",
    "wof:population":32504
},
  "geometry": {"coordinates":[72.75551,22.82359],"type":"Point"}
}