{
  "type": "Feature",
  "properties": {
    "gn:admin1_code":"25.0",
    "gn:admin2_code":"631.0",
    "gn:asciiname":"Palalyakottai",
    "gn:country_code":"IN",
    "gn:dem":398,
    "gn:feature_class":"P",
    "gn:feature_code":"PPL",
    "gn:name":"Palalyakottai",
    "gn:population":0,
    "gn:timezone":"Asia/Kolkata",
    "iso:country":"IN",
    "wof:name":"Palalyakottai",
    "wof:placetype":"locality"
},
  "geometry": {"coordinates":[78.4353,12.23737],"type":"Point"}
}