{
  "type": "Feature",
  "properties": {
    "iso:country":"IN",
    "ks:ks_alt_nam":"KAKARARA",
    "ks:ks_name":"Kakarara",
    "ks:ks_pop":78,
    "ks:ks_type":"HABITATION",
    "name:eng_x_preferred":[
        "Kakarara"
    ],
    "wof:name":"Kakarara",
    "wof:placetype":"locality",
    "wof:population":78
},
  "geometry": {"coordinates":[80.2689,26.731404],"type":"Point"}
}