{
  "type": "Feature",
  "properties": {
    "iso:country":"IN",
    "ks:ks_alt_nam":"Musa khoh Ryt",
    "ks:ks_name":"Musa Khoh Ryt",
    "ks:ks_pop":299,
    "ks:ks_type":"HABITATION",
    "name:eng_x_preferred":[
        "Musa Khoh Ryt"
    ],
    "wof:name":"Musa Khoh Ryt",
    "wof:placetype":"locality",
    "wof:population":299
},
  "geometry": {"coordinates":[80.02499,22.957414],"type":"Point"}
}