{
  "type": "Feature",
  "properties": {
    "iso:country":"IN",
    "ks:ks_name":"Kolekar Wasti",
    "ks:ks_pop":163,
    "ks:ks_type":"HABITATION",
    "name:eng_x_preferred":[
        "Kolekar Wasti"
    ],
    "wof:name":"Kolekar Wasti",
    "wof:placetype":"locality",
    "wof:population":163
},
  "geometry": {"coordinates":[75.510291,18.302775],"type":"Point"}
}