{
  "type": "Feature",
  "properties": {
    "gn:admin1_code":"25.0",
    "gn:admin2_code":"620.0",
    "gn:asciiname":"Selvanayakkanpatnam",
    "gn:country_code":"IN",
    "gn:dem":7,
    "gn:feature_class":"P",
    "gn:feature_code":"PPL",
    "gn:name":"Selvan\u0101yakkanpatnam",
    "gn:population":0,
    "gn:timezone":"Asia/Kolkata",
    "iso:country":"IN",
    "wof:name":"Selvanayakkanpatnam",
    "wof:placetype":"locality"
},
  "geometry": {"coordinates":[79.30436,10.27644],"type":"Point"}
}