{
  "type": "Feature",
  "properties": {
    "iso:country":"IN",
    "ks:ks_name":"Puthia",
    "ks:ks_pop":857,
    "ks:ks_type":"HABITATION",
    "name:eng_x_preferred":[
        "Puthia"
    ],
    "wof:name":"Puthia",
    "wof:placetype":"locality",
    "wof:population":857
},
  "geometry": {"coordinates":[90.142734,26.039124],"type":"Point"}
}