{
  "type": "Feature",
  "properties": {
    "gn:admin1_code":"39.0",
    "gn:admin2_code":"64.0",
    "gn:asciiname":"Basai Talli",
    "gn:country_code":"IN",
    "gn:dem":1083,
    "gn:feature_class":"P",
    "gn:feature_code":"PPL",
    "gn:name":"Basai Talli",
    "gn:population":0,
    "gn:timezone":"Asia/Kolkata",
    "iso:country":"IN",
    "wof:name":"Basai Talli",
    "wof:placetype":"locality"
},
  "geometry": {"coordinates":[79.1829,29.85946],"type":"Point"}
}