{
  "type": "Feature",
  "properties": {
    "iso:country":"IN",
    "ks:ks_alt_nam":"B\u0101re\u0101tu",
    "ks:ks_name":"Bareatu",
    "ks:ks_pop":1465,
    "ks:ks_type":"VILLAGE",
    "ks:ks_uagg_main":0,
    "name:eng_x_preferred":[
        "Bareatu"
    ],
    "name:eng_x_variant":[
        "B\u0101re\u0101tu"
    ],
    "wof:name":"Bareatu",
    "wof:placetype":"neighbourhood",
    "wof:population":1465
},
  "geometry": {"coordinates":[85.16859100000001,23.894347],"type":"Point"}
}