{
  "type": "Feature",
  "properties": {
    "gn:admin1_code":"34.0",
    "gn:admin2_code":"203.0",
    "gn:asciiname":"Barbiro",
    "gn:country_code":"IN",
    "gn:dem":88,
    "gn:feature_class":"P",
    "gn:feature_code":"PPL",
    "gn:name":"Barb\u012bro",
    "gn:population":0,
    "gn:timezone":"Asia/Kolkata",
    "iso:country":"IN",
    "ks:ks_alt_nam":"Barb\u012bro",
    "ks:ks_name":"Barbiro",
    "ks:ks_pop":660,
    "ks:ks_type":"VILLAGE",
    "ks:ks_uagg_main":0,
    "name:eng_x_preferred":[
        "Barbiro"
    ],
    "name:eng_x_variant":[
        "Barb\u012bro"
    ],
    "wof:name":"Barbiro",
    "wof:placetype":"neighbourhood",
    "wof:population":660
},
  "geometry": {"coordinates":[84.364548,27.04583],"type":"Point"}
}