{
  "type": "Feature",
  "properties": {
    "iso:country":"IN",
    "ks:ks_name":"Bhltwani Palli",
    "ks:ks_pop":99,
    "ks:ks_type":"HABITATION",
    "name:eng_x_preferred":[
        "Bhltwani Palli"
    ],
    "wof:name":"Bhltwani Palli",
    "wof:placetype":"locality",
    "wof:population":99
},
  "geometry": {"coordinates":[79.289699,29.908201],"type":"Point"}
}