{
  "type": "Feature",
  "properties": {
    "gn:admin1_code":"24",
    "gn:admin2_code":"123.0",
    "gn:asciiname":"Sadra",
    "gn:country_code":"IN",
    "gn:dem":565,
    "gn:feature_class":"P",
    "gn:feature_code":"PPL",
    "gn:name":"S\u0101dra",
    "gn:population":0,
    "gn:timezone":"Asia/Kolkata",
    "iso:country":"IN",
    "name:hrv_x_preferred":[
        "Sadra"
    ],
    "wof:name":"Sadra",
    "wof:placetype":"locality"
},
  "geometry": {"coordinates":[73.92385999999998,25.13326],"type":"Point"}
}