{
  "type": "Feature",
  "properties": {
    "iso:country":"IN",
    "ks:ks_name":"Lagania Purwa",
    "ks:ks_pop":275,
    "ks:ks_type":"HABITATION",
    "name:eng_x_preferred":[
        "Lagania Purwa"
    ],
    "wof:name":"Lagania Purwa",
    "wof:placetype":"locality",
    "wof:population":275
},
  "geometry": {"coordinates":[80.706997,27.268688],"type":"Point"}
}