{
  "type": "Feature",
  "properties": {
    "iso:country":"IN",
    "ks:ks_alt_nam":"Sui\u0101mb\u0101",
    "ks:ks_name":"Suiamba",
    "ks:ks_pop":891,
    "ks:ks_type":"VILLAGE",
    "name:eng_x_preferred":[
        "Suiamba"
    ],
    "name:eng_x_variant":[
        "Sui\u0101mb\u0101"
    ],
    "wof:name":"Suiamba",
    "wof:placetype":"locality",
    "wof:population":891
},
  "geometry": {"coordinates":[85.596887,22.438774],"type":"Point"}
}