{
  "type": "Feature",
  "properties": {
    "iso:country":"IN",
    "ks:ks_name":"Totadamane",
    "ks:ks_pop":50,
    "ks:ks_type":"HABITATION",
    "name:eng_x_preferred":[
        "Totadamane"
    ],
    "wof:name":"Totadamane",
    "wof:placetype":"locality",
    "wof:population":50
},
  "geometry": {"coordinates":[74.736166,14.710473],"type":"Point"}
}