{
  "type": "Feature",
  "properties": {
    "iso:country":"IN",
    "ks:ks_name":"Morki",
    "ks:ks_pop":1309,
    "ks:ks_type":"VILLAGE",
    "name:eng_x_preferred":[
        "Morki"
    ],
    "wof:name":"Morki",
    "wof:placetype":"locality",
    "wof:population":1309
},
  "geometry": {"coordinates":[75.747455,27.935244],"type":"Point"}
}