{
  "type": "Feature",
  "properties": {
    "gn:admin1_code":"36.0",
    "gn:admin2_code":"175.0",
    "gn:asciiname":"Singarpur",
    "gn:country_code":"IN",
    "gn:dem":101,
    "gn:feature_class":"P",
    "gn:feature_code":"PPL",
    "gn:name":"Sing\u0101rpur",
    "gn:population":0,
    "gn:timezone":"Asia/Kolkata",
    "iso:country":"IN",
    "ks:ks_alt_nam":"Sing\u0101rpur",
    "ks:ks_name":"Singarpur",
    "ks:ks_type":"VILLAGE",
    "ks:ks_uagg_main":0,
    "name:eng_x_preferred":[
        "Singarpur"
    ],
    "name:eng_x_variant":[
        "Sing\u0101rpur"
    ],
    "name:msa_x_preferred":[
        "Singarpur"
    ],
    "wof:name":"Singarpur",
    "wof:placetype":"neighbourhood"
},
  "geometry": {"coordinates":[81.843198,25.541118],"type":"Point"}
}