{
  "type": "Feature",
  "properties": {
    "iso:country":"IN",
    "ks:ks_alt_nam":"AURAJHARIYA",
    "ks:ks_name":"Aurajhariya",
    "ks:ks_pop":177,
    "ks:ks_type":"HABITATION",
    "name:eng_x_preferred":[
        "Aurajhariya"
    ],
    "wof:name":"Aurajhariya",
    "wof:placetype":"locality",
    "wof:population":177
},
  "geometry": {"coordinates":[83.969506,22.719157],"type":"Point"}
}