{
  "type": "Feature",
  "properties": {
    "iso:country":"IN",
    "ks:ks_alt_nam":"thakurwadi",
    "ks:ks_name":"Thakurwadi",
    "ks:ks_pop":95,
    "ks:ks_type":"HABITATION",
    "name:eng_x_preferred":[
        "Thakurwadi"
    ],
    "wof:name":"Thakurwadi",
    "wof:placetype":"locality",
    "wof:population":95
},
  "geometry": {"coordinates":[74.2047,19.234823],"type":"Point"}
}