{
  "type": "Feature",
  "properties": {
    "iso:country":"IN",
    "ks:ks_name":"P Meenachipuram",
    "ks:ks_pop":481,
    "ks:ks_type":"HABITATION",
    "name:eng_x_preferred":[
        "P Meenachipuram"
    ],
    "wof:name":"P Meenachipuram",
    "wof:placetype":"locality",
    "wof:population":481
},
  "geometry": {"coordinates":[78.232804,9.16221],"type":"Point"}
}