{
  "type": "Feature",
  "properties": {
    "gn:admin1_code":"28.0",
    "gn:admin2_code":"327.0",
    "gn:asciiname":"Tungsung Basti",
    "gn:country_code":"IN",
    "gn:dem":2137,
    "gn:feature_class":"P",
    "gn:feature_code":"PPL",
    "gn:name":"Tungsung Basti",
    "gn:population":0,
    "gn:timezone":"Asia/Kolkata",
    "iso:country":"IN",
    "wof:name":"Tungsung Basti",
    "wof:placetype":"locality"
},
  "geometry": {"coordinates":[88.26777,27.0383],"type":"Point"}
}