{
  "type": "Feature",
  "properties": {
    "iso:country":"IN",
    "ks:ks_name":"Ran Bania",
    "ks:ks_pop":202,
    "ks:ks_type":"VILLAGE",
    "name:eng_x_preferred":[
        "Ran Bania"
    ],
    "wof:name":"Ran Bania",
    "wof:placetype":"locality",
    "wof:population":202
},
  "geometry": {"coordinates":[87.187792,22.179423],"type":"Point"}
}