{
  "type": "Feature",
  "properties": {
    "iso:country":"IN",
    "ks:ks_name":"Khudimirkhi",
    "ks:ks_pop":716,
    "ks:ks_type":"HABITATION",
    "name:eng_x_preferred":[
        "Khudimirkhi"
    ],
    "wof:name":"Khudimirkhi",
    "wof:placetype":"locality",
    "wof:population":716
},
  "geometry": {"coordinates":[87.303129,24.452511],"type":"Point"}
}