{
  "type": "Feature",
  "properties": {
    "iso:country":"IN",
    "ks:ks_alt_nam":"cherussery",
    "ks:ks_name":"Cherussery",
    "ks:ks_pop":1426,
    "ks:ks_type":"HABITATION",
    "name:eng_x_preferred":[
        "Cherussery"
    ],
    "wof:name":"Cherussery",
    "wof:placetype":"locality",
    "wof:population":1426
},
  "geometry": {"coordinates":[76.05798,11.424876],"type":"Point"}
}