{
  "type": "Feature",
  "properties": {
    "gn:admin1_code":"36",
    "gn:admin2_code":"163.0",
    "gn:asciiname":"Aurangabad Jhara",
    "gn:country_code":"IN",
    "gn:dem":140,
    "gn:feature_class":"P",
    "gn:feature_code":"PPL",
    "gn:name":"Aurang\u0101b\u0101d Jhara",
    "gn:population":0,
    "gn:timezone":"Asia/Kolkata",
    "iso:country":"IN",
    "wof:name":"Aurangabad Jhara",
    "wof:placetype":"locality"
},
  "geometry": {"coordinates":[79.67811,26.52986],"type":"Point"}
}