{
  "type": "Feature",
  "properties": {
    "gn:admin1_code":"16",
    "gn:admin2_code":"505.0",
    "gn:asciiname":"Lakhapur",
    "gn:country_code":"IN",
    "gn:dem":370,
    "gn:feature_class":"P",
    "gn:feature_code":"PPL",
    "gn:name":"Lakh\u0101pur",
    "gn:population":0,
    "gn:timezone":"Asia/Kolkata",
    "iso:country":"IN",
    "ks:ks_alt_nam":"Lakh\u0101pur",
    "ks:ks_name":"Lakhapur",
    "ks:ks_pop":177,
    "ks:ks_type":"VILLAGE",
    "name:eng_x_preferred":[
        "Lakhapur"
    ],
    "name:eng_x_variant":[
        "Lakh\u0101pur"
    ],
    "wof:name":"Lakhapur",
    "wof:placetype":"locality",
    "wof:population":177
},
  "geometry": {"coordinates":[79.43180099999999,21.562507],"type":"Point"}
}