{
  "type": "Feature",
  "properties": {
    "gn:admin1_code":"35.0",
    "gn:admin2_code":"457.0",
    "gn:asciiname":"Pusu Tola",
    "gn:country_code":"IN",
    "gn:dem":313,
    "gn:feature_class":"P",
    "gn:feature_code":"PPL",
    "gn:name":"Pus\u016b Tol\u0101",
    "gn:population":0,
    "gn:timezone":"Asia/Kolkata",
    "iso:country":"IN",
    "wof:name":"Pusu Tola",
    "wof:placetype":"locality"
},
  "geometry": {"coordinates":[80.13593,21.77766],"type":"Point"}
}