{
  "type": "Feature",
  "properties": {
    "gn:admin1_code":"19.0",
    "gn:admin2_code":"584.0",
    "gn:asciiname":"Iyanurdoddi",
    "gn:country_code":"IN",
    "gn:dem":737,
    "gn:feature_class":"P",
    "gn:feature_code":"PPL",
    "gn:name":"Iy\u0101nurdoddi",
    "gn:population":0,
    "gn:timezone":"Asia/Kolkata",
    "iso:country":"IN",
    "ks:ks_name":"Iyyanordoddi",
    "ks:ks_pop":68,
    "ks:ks_type":"HABITATION",
    "name:eng_x_preferred":[
        "Iyyanordoddi"
    ],
    "name:eng_x_variant":[
        "Iyanurdoddi"
    ],
    "wof:name":"Iyyanordoddi",
    "wof:placetype":"locality",
    "wof:population":68
},
  "geometry": {"coordinates":[77.33525400000001,12.552918],"type":"Point"}
}