{
  "type": "Feature",
  "properties": {
    "iso:country":"IN",
    "ks:ks_alt_nam":"HARIZAN TOLA",
    "ks:ks_name":"Harizan Tola",
    "ks:ks_pop":1070,
    "ks:ks_type":"HABITATION",
    "name:eng_x_preferred":[
        "Harizan Tola"
    ],
    "wof:name":"Harizan Tola",
    "wof:placetype":"locality",
    "wof:population":1070
},
  "geometry": {"coordinates":[86.757638,25.340326],"type":"Point"}
}