{
  "type": "Feature",
  "properties": {
    "gn:admin1_code":"34",
    "gn:admin2_code":"233.0",
    "gn:asciiname":"Dadra",
    "gn:country_code":"IN",
    "gn:dem":84,
    "gn:feature_class":"P",
    "gn:feature_code":"PPL",
    "gn:name":"Dadra",
    "gn:population":0,
    "gn:timezone":"Asia/Kolkata",
    "iso:country":"IN",
    "name:deu_x_preferred":[
        "Dadra"
    ],
    "name:hin_x_preferred":[
        "\u0926\u093e\u0926\u0930\u093e"
    ],
    "name:mar_x_preferred":[
        "\u0926\u093e\u0926\u0930\u093e"
    ],
    "name:new_x_preferred":[
        "\u0926\u093e\u0926\u0930\u093e \u0924\u093e\u0932"
    ],
    "name:urd_x_preferred":[
        "\u062f\u0627\u062f\u0631\u0627"
    ],
    "wof:name":"Dadra",
    "wof:placetype":"locality"
},
  "geometry": {"coordinates":[83.62697,25.01299],"type":"Point"}
}