{
  "type": "Feature",
  "properties": {
    "gn:admin1_code":"34.0",
    "gn:admin2_code":"216.0",
    "gn:asciiname":"Sangopatti",
    "gn:country_code":"IN",
    "gn:dem":52,
    "gn:feature_class":"P",
    "gn:feature_code":"PPL",
    "gn:name":"Sangopatti",
    "gn:population":0,
    "gn:timezone":"Asia/Kolkata",
    "iso:country":"IN",
    "ks:ks_name":"Sangopatti",
    "ks:ks_pop":890,
    "ks:ks_type":"VILLAGE",
    "name:eng_x_preferred":[
        "Sangopatti"
    ],
    "wof:name":"Sangopatti",
    "wof:placetype":"locality",
    "wof:population":890
},
  "geometry": {"coordinates":[85.489925,25.989152],"type":"Point"}
}