{
  "type": "Feature",
  "properties": {
    "iso:country":"IN",
    "ks:ks_name":"Wad Pod",
    "ks:ks_pop":25,
    "ks:ks_type":"HABITATION",
    "name:eng_x_preferred":[
        "Wad Pod"
    ],
    "wof:name":"Wad Pod",
    "wof:placetype":"locality",
    "wof:population":25
},
  "geometry": {"coordinates":[78.14045,20.015833],"type":"Point"}
}