{
  "type": "Feature",
  "properties": {
    "iso:country":"IN",
    "ks:ks_name":"Thitewadi",
    "ks:ks_pop":59,
    "ks:ks_type":"HABITATION",
    "name:eng_x_preferred":[
        "Thitewadi"
    ],
    "wof:name":"Thitewadi",
    "wof:placetype":"locality",
    "wof:population":59
},
  "geometry": {"coordinates":[73.506615,18.021375],"type":"Point"}
}