{
  "type": "Feature",
  "properties": {
    "iso:country":"IN",
    "ks:ks_name":"Vadakkapuram",
    "ks:ks_pop":1127,
    "ks:ks_type":"HABITATION",
    "name:eng_x_preferred":[
        "Vadakkapuram"
    ],
    "wof:name":"Vadakkapuram",
    "wof:placetype":"locality",
    "wof:population":1127
},
  "geometry": {"coordinates":[76.83630100000001,9.279185],"type":"Point"}
}