{
  "type": "Feature",
  "properties": {
    "iso:country":"IN",
    "ks:ks_name":"Siberalga",
    "ks:ks_pop":1116,
    "ks:ks_type":"VILLAGE",
    "name:eng_x_preferred":[
        "Siberalga"
    ],
    "wof:name":"Siberalga",
    "wof:placetype":"locality",
    "wof:population":1116
},
  "geometry": {"coordinates":[90.070283,26.088818],"type":"Point"}
}