{
  "type": "Feature",
  "properties": {
    "gn:admin1_code":"23.0",
    "gn:admin2_code":"50.0",
    "gn:asciiname":"Burj",
    "gn:country_code":"IN",
    "gn:dem":225,
    "gn:feature_class":"P",
    "gn:feature_code":"PPL",
    "gn:name":"Burj",
    "gn:population":0,
    "gn:timezone":"Asia/Kolkata",
    "iso:country":"IN",
    "name:ceb_x_preferred":[
        "Burj"
    ],
    "name:deu_x_preferred":[
        "Burj"
    ],
    "name:fra_x_preferred":[
        "Burj"
    ],
    "name:heb_x_preferred":[
        "\u05d1\u05d5\u05e8\u05d2'"
    ],
    "name:hin_x_preferred":[
        "\u092c\u0941\u0930\u094d\u091c"
    ],
    "name:swe_x_preferred":[
        "Burj"
    ],
    "name:uzb_x_preferred":[
        "Burj"
    ],
    "wof:name":"Burj",
    "wof:placetype":"locality"
},
  "geometry": {"coordinates":[74.7641,31.47113],"type":"Point"}
}