{
  "type": "Feature",
  "properties": {
    "gn:admin1_code":"2",
    "gn:admin2_code":"544.0",
    "gn:asciiname":"Kaliaguda",
    "gn:country_code":"IN",
    "gn:dem":875,
    "gn:feature_class":"P",
    "gn:feature_code":"PPL",
    "gn:name":"Kaliag\u016bda",
    "gn:population":0,
    "gn:timezone":"Asia/Kolkata",
    "iso:country":"IN",
    "wof:name":"Kaliaguda",
    "wof:placetype":"locality"
},
  "geometry": {"coordinates":[82.99813,18.29801],"type":"Point"}
}