{
  "type": "Feature",
  "properties": {
    "iso:country":"IN",
    "ks:ks_name":"Be Chhapri",
    "ks:ks_pop":97,
    "ks:ks_type":"VILLAGE",
    "ks:ks_uagg_main":0,
    "name:eng_x_preferred":[
        "Be Chhapri"
    ],
    "wof:name":"Be Chhapri",
    "wof:placetype":"neighbourhood",
    "wof:population":97
},
  "geometry": {"coordinates":[84.51232400000001,25.996582],"type":"Point"}
}