{
  "type": "Feature",
  "properties": {
    "iso:country":"IN",
    "ks:ks_name":"Baijalpur",
    "ks:ks_pop":12,
    "ks:ks_type":"VILLAGE",
    "name:eng_x_preferred":[
        "Baijalpur"
    ],
    "wof:name":"Baijalpur",
    "wof:placetype":"locality",
    "wof:population":12
},
  "geometry": {"coordinates":[86.60773399999999,25.137743],"type":"Point"}
}