{
  "type": "Feature",
  "properties": {
    "gn:admin1_code":"24.0",
    "gn:admin2_code":"102.0",
    "gn:asciiname":"Dhadar",
    "gn:country_code":"IN",
    "gn:dem":287,
    "gn:feature_class":"P",
    "gn:feature_code":"PPL",
    "gn:name":"Dh\u0101dar",
    "gn:population":0,
    "gn:timezone":"Asia/Kolkata",
    "iso:country":"IN",
    "name:ceb_x_preferred":[
        "D\u0101dhar"
    ],
    "name:fas_x_preferred":[
        "\u062f\u0647\u0627\u062f\u0631"
    ],
    "name:msa_x_preferred":[
        "Dhadar"
    ],
    "name:pnb_x_preferred":[
        "\u062f\u06be\u0627\u062f\u0631"
    ],
    "name:por_x_preferred":[
        "Dhadar"
    ],
    "name:rus_x_preferred":[
        "\u0414\u0445\u0430\u0434\u0430\u0440"
    ],
    "name:spa_x_preferred":[
        "Dhadar"
    ],
    "name:swe_x_preferred":[
        "Dhadar"
    ],
    "name:urd_x_preferred":[
        "\u062f\u06be\u0627\u062f\u0631"
    ],
    "wof:name":"Dhadar",
    "wof:placetype":"locality"
},
  "geometry": {"coordinates":[75.06379,28.33011],"type":"Point"}
}