{
  "type": "Feature",
  "properties": {
    "gn:admin1_code":"16.0",
    "gn:admin2_code":"510.0",
    "gn:asciiname":"Patharwadi",
    "gn:country_code":"IN",
    "gn:dem":398,
    "gn:feature_class":"P",
    "gn:feature_code":"PPL",
    "gn:name":"Path\u0101rw\u0101di",
    "gn:population":0,
    "gn:timezone":"Asia/Kolkata",
    "iso:country":"IN",
    "wof:name":"Patharwadi",
    "wof:placetype":"locality"
},
  "geometry": {"coordinates":[77.60883000000003,19.72664],"type":"Point"}
}