{
  "type": "Feature",
  "properties": {
    "gn:admin1_code":"23",
    "gn:admin2_code":"39.0",
    "gn:asciiname":"Chandpur Rurki",
    "gn:country_code":"IN",
    "gn:dem":321,
    "gn:feature_class":"P",
    "gn:feature_code":"PPL",
    "gn:name":"Ch\u0101ndpur Rurki",
    "gn:population":0,
    "gn:timezone":"Asia/Kolkata",
    "iso:country":"IN",
    "name:por_x_preferred":[
        "Chandpur Rurki"
    ],
    "wof:name":"Chandpur Rurki",
    "wof:placetype":"locality"
},
  "geometry": {"coordinates":[76.24194,31.21261],"type":"Point"}
}