{
  "type": "Feature",
  "properties": {
    "iso:country":"IN",
    "ks:ks_name":"Belia",
    "ks:ks_pop":768,
    "ks:ks_type":"VILLAGE",
    "name:eng_x_preferred":[
        "Belia"
    ],
    "wof:name":"Belia",
    "wof:placetype":"locality",
    "wof:population":768
},
  "geometry": {"coordinates":[87.172983,22.451895],"type":"Point"}
}