{
  "type": "Feature",
  "properties": {
    "iso:country":"IN",
    "ks:ks_name":"Kamalpur Mu.Jaipatti",
    "ks:ks_pop":305,
    "ks:ks_type":"VILLAGE",
    "ks:ks_uagg_main":0,
    "name:eng_x_preferred":[
        "Kamalpur Mu.Jaipatti"
    ],
    "wof:name":"Kamalpur Mu.Jaipatti",
    "wof:placetype":"neighbourhood",
    "wof:population":305
},
  "geometry": {"coordinates":[83.03099400000001,25.158808],"type":"Point"}
}