{
  "type": "Feature",
  "properties": {
    "iso:country":"IN",
    "ks:ks_name":"Girli Kitpal",
    "ks:ks_pop":102,
    "ks:ks_type":"VILLAGE",
    "name:eng_x_preferred":[
        "Girli Kitpal"
    ],
    "wof:name":"Girli Kitpal",
    "wof:placetype":"locality",
    "wof:population":102
},
  "geometry": {"coordinates":[71.916792,25.772725],"type":"Point"}
}