{
  "type": "Feature",
  "properties": {
    "gn:admin1_code":"36.0",
    "gn:admin2_code":"179.0",
    "gn:asciiname":"Lingri",
    "gn:country_code":"IN",
    "gn:dem":106,
    "gn:feature_class":"P",
    "gn:feature_code":"PPL",
    "gn:name":"Lingri",
    "gn:population":0,
    "gn:timezone":"Asia/Kolkata",
    "iso:country":"IN",
    "wof:name":"Lingri",
    "wof:placetype":"neighbourhood"
},
  "geometry": {"coordinates":[81.88272000000001,26.30634],"type":"Point"}
}