{
  "type": "Feature",
  "properties": {
    "iso:country":"IN",
    "ks:ks_name":"Rowmari",
    "ks:ks_pop":2676,
    "ks:ks_type":"HABITATION",
    "name:eng_x_preferred":[
        "Rowmari"
    ],
    "wof:name":"Rowmari",
    "wof:placetype":"locality",
    "wof:population":2676
},
  "geometry": {"coordinates":[92.471087,26.386974],"type":"Point"}
}