{
  "type": "Feature",
  "properties": {
    "gn:admin1_code":"34.0",
    "gn:admin2_code":"220.0",
    "gn:asciiname":"Pachrukhi",
    "gn:country_code":"IN",
    "gn:dem":58,
    "gn:feature_class":"P",
    "gn:feature_code":"PPL",
    "gn:name":"Pachrukhi",
    "gn:population":0,
    "gn:timezone":"Asia/Kolkata",
    "iso:country":"IN",
    "wof:name":"Pachrukhi",
    "wof:placetype":"locality"
},
  "geometry": {"coordinates":[85.2302,25.89926],"type":"Point"}
}