{
  "type": "Feature",
  "properties": {
    "gn:admin1_code":"34.0",
    "gn:admin2_code":"220.0",
    "gn:asciiname":"Pachrukhi",
    "gn:country_code":"IN",
    "gn:dem":58,
    "gn:feature_class":"P",
    "gn:feature_code":"PPL",
    "gn:name":"Pachrukhi",
    "gn:population":0,
    "gn:timezone":"Asia/Kolkata",
    "iso:country":"IN",
    "ks:ks_name":"Pachrukhi",
    "ks:ks_pop":321,
    "ks:ks_type":"VILLAGE",
    "name:eng_x_preferred":[
        "Pachrukhi"
    ],
    "wof:name":"Pachrukhi",
    "wof:placetype":"locality",
    "wof:population":321
},
  "geometry": {"coordinates":[85.22684700000001,25.901766],"type":"Point"}
}