{
  "type": "Feature",
  "properties": {
    "iso:country":"IN",
    "ks:ks_name":"Kodaria Nizamuddin",
    "ks:ks_pop":178,
    "ks:ks_type":"VILLAGE",
    "name:eng_x_preferred":[
        "Kodaria Nizamuddin"
    ],
    "wof:name":"Kodaria Nizamuddin",
    "wof:placetype":"locality",
    "wof:population":178
},
  "geometry": {"coordinates":[85.285371,26.119123],"type":"Point"}
}