{
  "type": "Feature",
  "properties": {
    "gn:admin1_code":"11.0",
    "gn:admin2_code":"31.0",
    "gn:asciiname":"Anji",
    "gn:country_code":"IN",
    "gn:dem":1454,
    "gn:feature_class":"P",
    "gn:feature_code":"PPL",
    "gn:name":"Anji",
    "gn:population":0,
    "gn:timezone":"Asia/Kolkata",
    "iso:country":"IN",
    "name:ceb_x_preferred":[
        "Anji"
    ],
    "name:deu_x_preferred":[
        "Anji"
    ],
    "wof:name":"Anji",
    "wof:placetype":"locality"
},
  "geometry": {"coordinates":[77.09413000000001,30.8945],"type":"Point"}
}