{
  "type": "Feature",
  "properties": {
    "iso:country":"IN",
    "ks:ks_alt_nam":"Jal\u0101l\u0101b\u0101d",
    "ks:ks_name":"Jalalabad",
    "ks:ks_type":"VILLAGE",
    "ks:ks_uagg_main":0,
    "name:eng_x_preferred":[
        "Jalalabad"
    ],
    "name:eng_x_variant":[
        "Jal\u0101l\u0101b\u0101d"
    ],
    "wof:name":"Jalalabad",
    "wof:placetype":"neighbourhood"
},
  "geometry": {"coordinates":[78.316689,29.596999],"type":"Point"}
}