{
  "type": "Feature",
  "properties": {
    "iso:country":"IN",
    "ks:ks_alt_nam":"M\u0101dakkottai",
    "ks:ks_name":"Madakkottai",
    "ks:ks_pop":566,
    "ks:ks_type":"VILLAGE",
    "name:eng_x_preferred":[
        "Madakkottai"
    ],
    "name:eng_x_variant":[
        "M\u0101dakkottai"
    ],
    "wof:name":"Madakkottai",
    "wof:placetype":"locality",
    "wof:population":566
},
  "geometry": {"coordinates":[78.89680799999999,9.964619],"type":"Point"}
}