{
  "type": "Feature",
  "properties": {
    "iso:country":"IN",
    "ks:ks_name":"Shirigere",
    "ks:ks_pop":990,
    "ks:ks_type":"VILLAGE",
    "name:eng_x_preferred":[
        "Shirigere"
    ],
    "wof:name":"Shirigere",
    "wof:placetype":"locality",
    "wof:population":990
},
  "geometry": {"coordinates":[75.418211,13.953047],"type":"Point"}
}