{
  "type": "Feature",
  "properties": {
    "gn:admin1_code":"25.0",
    "gn:admin2_code":"631.0",
    "gn:asciiname":"Semmandapatti",
    "gn:country_code":"IN",
    "gn:dem":430,
    "gn:feature_class":"P",
    "gn:feature_code":"PPL",
    "gn:name":"Semmandapatti",
    "gn:population":0,
    "gn:timezone":"Asia/Kolkata",
    "iso:country":"IN",
    "wof:name":"Semmandapatti",
    "wof:placetype":"locality"
},
  "geometry": {"coordinates":[78.28137,12.28433],"type":"Point"}
}