{
  "type": "Feature",
  "properties": {
    "gn:admin1_code":"19.0",
    "gn:admin2_code":"577.0",
    "gn:asciiname":"Dallal",
    "gn:country_code":"IN",
    "gn:dem":821,
    "gn:feature_class":"P",
    "gn:feature_code":"PPL",
    "gn:name":"Dall\u0101l",
    "gn:population":0,
    "gn:timezone":"Asia/Kolkata",
    "iso:country":"IN",
    "wof:name":"Dallal",
    "wof:placetype":"locality"
},
  "geometry": {"coordinates":[76.45115,12.31455],"type":"Point"}
}