{
  "type": "Feature",
  "properties": {
    "iso:country":"IN",
    "ks:ks_alt_nam":"Auhammadpur M\u0101jri",
    "ks:ks_name":"Auhammadpur Majri",
    "ks:ks_type":"VILLAGE",
    "ks:ks_uagg_main":0,
    "name:eng_x_preferred":[
        "Auhammadpur Majri"
    ],
    "name:eng_x_variant":[
        "Auhammadpur M\u0101jri"
    ],
    "wof:name":"Auhammadpur Majri",
    "wof:placetype":"neighbourhood"
},
  "geometry": {"coordinates":[77.038273,28.729219],"type":"Point"}
}