{
  "type": "Feature",
  "properties": {
    "gn:admin1_code":"12",
    "gn:asciiname":"Mohri Baihk",
    "gn:country_code":"IN",
    "gn:dem":2935,
    "gn:feature_class":"P",
    "gn:feature_code":"PPL",
    "gn:name":"Mohri Baihk",
    "gn:population":0,
    "gn:timezone":"Asia/Kolkata",
    "iso:country":"IN",
    "wof:name":"Mohri Baihk",
    "wof:placetype":"locality"
},
  "geometry": {"coordinates":[74.09483,34.22562],"type":"Point"}
}