{
  "type": "Feature",
  "properties": {
    "gn:admin1_code":"36",
    "gn:admin2_code":"166.0",
    "gn:asciiname":"Karura",
    "gn:country_code":"IN",
    "gn:dem":174,
    "gn:feature_class":"P",
    "gn:feature_code":"PPL",
    "gn:name":"Kar\u016bra",
    "gn:population":0,
    "gn:timezone":"Asia/Kolkata",
    "iso:country":"IN",
    "name:fra_x_preferred":[
        "Karura"
    ],
    "name:hin_x_preferred":[
        "\u0917\u0930\u0941\u0921\u093c"
    ],
    "name:hrv_x_preferred":[
        "Karura"
    ],
    "name:ind_x_preferred":[
        "Karura"
    ],
    "name:ita_x_preferred":[
        "Karura"
    ],
    "name:jpn_x_preferred":[
        "\u8fe6\u697c\u7f85\u5929"
    ],
    "name:nor_x_preferred":[
        "Karura"
    ],
    "name:rus_x_preferred":[
        "\u041a\u0430\u0440\u0443\u0440\u0430"
    ],
    "name:spa_x_preferred":[
        "Karura"
    ],
    "name:tam_x_preferred":[
        "\u0b95\u0bb0\u0bc2\u0bb0\u0bbe"
    ],
    "name:zho_x_preferred":[
        "\u8fe6\u6a13\u7f85"
    ],
    "wof:name":"Karura",
    "wof:placetype":"locality"
},
  "geometry": {"coordinates":[78.94682,25.80946],"type":"Point"}
}