{
  "type": "Feature",
  "properties": {
    "iso:country":"IN",
    "ks:ks_name":"Bogamukh No.7",
    "ks:ks_pop":1940,
    "ks:ks_type":"VILLAGE",
    "ks:ks_uagg_main":0,
    "name:eng_x_preferred":[
        "Bogamukh No.7"
    ],
    "wof:name":"Bogamukh No.7",
    "wof:placetype":"neighbourhood",
    "wof:population":1940
},
  "geometry": {"coordinates":[92.76217,26.523311],"type":"Point"}
}