{
  "type": "Feature",
  "properties": {
    "iso:country":"IN",
    "ks:ks_name":"Humbarnewadi",
    "ks:ks_pop":503,
    "ks:ks_type":"HABITATION",
    "name:eng_x_preferred":[
        "Humbarnewadi"
    ],
    "wof:name":"Humbarnewadi",
    "wof:placetype":"locality",
    "wof:population":503
},
  "geometry": {"coordinates":[73.646604,16.290827],"type":"Point"}
}