{
  "type": "Feature",
  "properties": {
    "iso:country":"IN",
    "ks:ks_name":"Chheratangar",
    "ks:ks_pop":540,
    "ks:ks_type":"VILLAGE",
    "name:eng_x_preferred":[
        "Chheratangar"
    ],
    "wof:name":"Chheratangar",
    "wof:placetype":"locality",
    "wof:population":540
},
  "geometry": {"coordinates":[86.13161599999999,21.629073],"type":"Point"}
}