{
  "type": "Feature",
  "properties": {
    "iso:country":"IN",
    "ks:ks_name":"Painchimania",
    "ks:ks_pop":0,
    "ks:ks_type":"VILLAGE",
    "ks:ks_uagg_main":0,
    "name:eng_x_preferred":[
        "Painchimania"
    ],
    "wof:name":"Painchimania",
    "wof:placetype":"neighbourhood",
    "wof:population":0
},
  "geometry": {"coordinates":[86.514382,20.216677],"type":"Point"}
}