{
  "type": "Feature",
  "properties": {
    "gn:admin1_code":"37",
    "gn:admin2_code":"401.0",
    "gn:asciiname":"Semli",
    "gn:country_code":"IN",
    "gn:dem":529,
    "gn:feature_class":"P",
    "gn:feature_code":"PPL",
    "gn:name":"Seml\u012b",
    "gn:population":0,
    "gn:timezone":"Asia/Kolkata",
    "iso:country":"IN",
    "wof:name":"Semli",
    "wof:placetype":"locality"
},
  "geometry": {"coordinates":[83.64771999999998,23.62024],"type":"Point"}
}