{
  "type": "Feature",
  "properties": {
    "iso:country":"IN",
    "ks:ks_name":"Barwi",
    "ks:ks_pop":1093,
    "ks:ks_type":"HABITATION",
    "name:eng_x_preferred":[
        "Barwi"
    ],
    "wof:name":"Barwi",
    "wof:placetype":"locality",
    "wof:population":1093
},
  "geometry": {"coordinates":[74.38868100000001,23.579464],"type":"Point"}
}