{
  "type": "Feature",
  "properties": {
    "gn:admin1_code":"24.0",
    "gn:admin2_code":"110.0",
    "gn:asciiname":"Tadas",
    "gn:country_code":"IN",
    "gn:dem":434,
    "gn:feature_class":"P",
    "gn:feature_code":"PPL",
    "gn:name":"T\u0101d\u0101s",
    "gn:population":0,
    "gn:timezone":"Asia/Kolkata",
    "iso:country":"IN",
    "name:ceb_x_preferred":[
        "Tadas"
    ],
    "name:swe_x_preferred":[
        "Tadas"
    ],
    "wof:name":"Tadas",
    "wof:placetype":"locality"
},
  "geometry": {"coordinates":[75.55098000000002,27.13133],"type":"Point"}
}