{
  "type": "Feature",
  "properties": {
    "iso:country":"IN",
    "ks:ks_alt_nam":"khadura",
    "ks:ks_name":"Khadura",
    "ks:ks_pop":480,
    "ks:ks_type":"HABITATION",
    "name:eng_x_preferred":[
        "Khadura"
    ],
    "wof:name":"Khadura",
    "wof:placetype":"locality",
    "wof:population":480
},
  "geometry": {"coordinates":[82.83211900000001,25.246273],"type":"Point"}
}