{
  "type": "Feature",
  "properties": {
    "iso:country":"IN",
    "ks:ks_name":"Manaje",
    "ks:ks_pop":300,
    "ks:ks_type":"HABITATION",
    "name:eng_x_preferred":[
        "Manaje"
    ],
    "wof:name":"Manaje",
    "wof:placetype":"locality",
    "wof:population":300
},
  "geometry": {"coordinates":[74.906194,13.703281],"type":"Point"}
}