{
  "type": "Feature",
  "properties": {
    "iso:country":"IN",
    "ks:ks_name":"Munsirvita",
    "ks:ks_pop":227,
    "ks:ks_type":"VILLAGE",
    "name:eng_x_preferred":[
        "Munsirvita"
    ],
    "wof:name":"Munsirvita",
    "wof:placetype":"locality",
    "wof:population":227
},
  "geometry": {"coordinates":[90.503249,26.160225],"type":"Point"}
}