{
  "type": "Feature",
  "properties": {
    "iso:country":"IN",
    "ks:ks_alt_nam":"Hos\u016br Agrah\u0101r",
    "ks:ks_alt_nam_2":"Hosur Agrahar",
    "ks:ks_name":"Hosur",
    "ks:ks_type":"VILLAGE",
    "name:eng_x_preferred":[
        "Hosur"
    ],
    "name:eng_x_variant":[
        "Hos\u016br Agrah\u0101r",
        "Hosur Agrahar"
    ],
    "wof:name":"Hosur",
    "wof:placetype":"locality"
},
  "geometry": {"coordinates":[75.01506500000001,14.476883],"type":"Point"}
}