{
  "type": "Feature",
  "properties": {
    "gn:admin1_code":"21",
    "gn:admin2_code":"398.0",
    "gn:asciiname":"Majhiguda",
    "gn:country_code":"IN",
    "gn:dem":552,
    "gn:feature_class":"P",
    "gn:feature_code":"PPL",
    "gn:name":"M\u0101jhiguda",
    "gn:population":0,
    "gn:timezone":"Asia/Kolkata",
    "iso:country":"IN",
    "ks:ks_name":"Majhiguda",
    "ks:ks_pop":438,
    "ks:ks_type":"HABITATION",
    "name:eng_x_preferred":[
        "Majhiguda"
    ],
    "wof:name":"Majhiguda",
    "wof:placetype":"locality",
    "wof:population":438
},
  "geometry": {"coordinates":[82.240469,19.105475],"type":"Point"}
}