{
  "type": "Feature",
  "properties": {
    "iso:country":"IN",
    "ks:ks_alt_nam":"mhavlankarwadi",
    "ks:ks_name":"Mhavlankarwadi",
    "ks:ks_pop":67,
    "ks:ks_type":"HABITATION",
    "name:eng_x_preferred":[
        "Mhavlankarwadi"
    ],
    "wof:name":"Mhavlankarwadi",
    "wof:placetype":"locality",
    "wof:population":67
},
  "geometry": {"coordinates":[74.0265,15.628806],"type":"Point"}
}