{
  "type": "Feature",
  "properties": {
    "iso:country":"IN",
    "ks:ks_name":"Chakia",
    "ks:ks_pop":514,
    "ks:ks_type":"VILLAGE",
    "name:eng_x_preferred":[
        "Chakia"
    ],
    "wof:name":"Chakia",
    "wof:placetype":"locality",
    "wof:population":514
},
  "geometry": {"coordinates":[86.712354,23.181889],"type":"Point"}
}