{
  "type": "Feature",
  "properties": {
    "iso:country":"IN",
    "ks:ks_name":"Digawari Kalan",
    "ks:ks_pop":874,
    "ks:ks_type":"VILLAGE",
    "name:eng_x_preferred":[
        "Digawari Kalan"
    ],
    "wof:name":"Digawari Kalan",
    "wof:placetype":"locality",
    "wof:population":874
},
  "geometry": {"coordinates":[73.23230599999999,24.436536],"type":"Point"}
}