{
  "type": "Feature",
  "properties": {
    "iso:country":"IN",
    "ks:ks_name":"Nabbe Begha",
    "ks:ks_pop":602,
    "ks:ks_type":"HABITATION",
    "name:eng_x_preferred":[
        "Nabbe Begha"
    ],
    "wof:name":"Nabbe Begha",
    "wof:placetype":"locality",
    "wof:population":602
},
  "geometry": {"coordinates":[78.40598,27.094392],"type":"Point"}
}