{
  "type": "Feature",
  "properties": {
    "gn:admin1_code":"36",
    "gn:admin2_code":"188.0",
    "gn:asciiname":"Kursa",
    "gn:country_code":"IN",
    "gn:dem":85,
    "gn:feature_class":"P",
    "gn:feature_code":"PPL",
    "gn:name":"Kursa",
    "gn:population":0,
    "gn:timezone":"Asia/Kolkata",
    "iso:country":"IN",
    "name:lav_x_preferred":[
        "Kursa"
    ],
    "wof:name":"Kursa",
    "wof:placetype":"locality"
},
  "geometry": {"coordinates":[83.16452,26.6733],"type":"Point"}
}