{
  "type": "Feature",
  "properties": {
    "gn:admin1_code":"12.0",
    "gn:asciiname":"Makri",
    "gn:country_code":"IN",
    "gn:dem":1005,
    "gn:feature_class":"P",
    "gn:feature_code":"PPL",
    "gn:name":"Makri",
    "gn:population":0,
    "gn:timezone":"Asia/Kolkata",
    "iso:country":"IN",
    "name:fra_x_preferred":[
        "Makri"
    ],
    "wof:name":"Makri",
    "wof:placetype":"locality"
},
  "geometry": {"coordinates":[74.05034000000001,33.22438],"type":"Point"}
}