{
  "type": "Feature",
  "properties": {
    "gn:admin1_code":"35",
    "gn:admin2_code":"426.0",
    "gn:asciiname":"Sili",
    "gn:country_code":"IN",
    "gn:dem":356,
    "gn:feature_class":"P",
    "gn:feature_code":"PPL",
    "gn:name":"Sili",
    "gn:population":0,
    "gn:timezone":"Asia/Kolkata",
    "iso:country":"IN",
    "ks:ks_name":"Sili",
    "ks:ks_pop":2098,
    "ks:ks_type":"VILLAGE",
    "ks:ks_uagg_main":0,
    "name:cat_x_preferred":[
        "Sili"
    ],
    "name:ceb_x_preferred":[
        "Sili"
    ],
    "name:eng_x_preferred":[
        "Sili"
    ],
    "name:swe_x_preferred":[
        "Sili"
    ],
    "wof:name":"Sili",
    "wof:placetype":"neighbourhood",
    "wof:population":2098
},
  "geometry": {"coordinates":[80.24635000000001,24.471717],"type":"Point"}
}