{
  "type": "Feature",
  "properties": {
    "iso:country":"IN",
    "ks:ks_name":"Dungar Pada",
    "ks:ks_pop":98,
    "ks:ks_type":"HABITATION",
    "name:eng_x_preferred":[
        "Dungar Pada"
    ],
    "wof:name":"Dungar Pada",
    "wof:placetype":"locality",
    "wof:population":98
},
  "geometry": {"coordinates":[73.3425,20.308472],"type":"Point"}
}