{
  "type": "Feature",
  "properties": {
    "iso:country":"IN",
    "ks:ks_alt_nam":"Bara tola",
    "ks:ks_name":"Bara Tola",
    "ks:ks_pop":811,
    "ks:ks_type":"HABITATION",
    "name:eng_x_preferred":[
        "Bara Tola"
    ],
    "wof:name":"Bara Tola",
    "wof:placetype":"locality",
    "wof:population":811
},
  "geometry": {"coordinates":[87.56453,26.049725],"type":"Point"}
}