{
  "type": "Feature",
  "properties": {
    "gn:admin1_code":"16.0",
    "gn:admin2_code":"505.0",
    "gn:asciiname":"Nayegaon",
    "gn:country_code":"IN",
    "gn:dem":389,
    "gn:feature_class":"P",
    "gn:feature_code":"PPL",
    "gn:name":"Nayegaon",
    "gn:population":0,
    "gn:timezone":"Asia/Kolkata",
    "iso:country":"IN",
    "ks:ks_name":"Naigaon",
    "ks:ks_pop":253,
    "ks:ks_type":"VILLAGE",
    "name:eng_x_preferred":[
        "Naigaon"
    ],
    "name:eng_x_variant":[
        "Nayegaon"
    ],
    "wof:name":"Naigaon",
    "wof:placetype":"locality",
    "wof:population":253
},
  "geometry": {"coordinates":[78.50268199999999,21.341563],"type":"Point"}
}