{
  "type": "Feature",
  "properties": {
    "gn:admin1_code":"12.0",
    "gn:admin2_code":"16.0",
    "gn:asciiname":"Rokali",
    "gn:country_code":"IN",
    "gn:dem":2017,
    "gn:feature_class":"P",
    "gn:feature_code":"PPL",
    "gn:name":"Rokali",
    "gn:population":0,
    "gn:timezone":"Asia/Kolkata",
    "iso:country":"IN",
    "wof:name":"Rokali",
    "wof:placetype":"locality"
},
  "geometry": {"coordinates":[75.71391,33.109],"type":"Point"}
}