{
  "type": "Feature",
  "properties": {
    "iso:country":"IN",
    "ks:ks_name":"Khocharewadi",
    "ks:ks_pop":85,
    "ks:ks_type":"HABITATION",
    "name:eng_x_preferred":[
        "Khocharewadi"
    ],
    "wof:name":"Khocharewadi",
    "wof:placetype":"locality",
    "wof:population":85
},
  "geometry": {"coordinates":[73.863252,16.183801],"type":"Point"}
}