{
  "type": "Feature",
  "properties": {
    "iso:country":"IN",
    "ks:ks_name":"Nathamkodiyur",
    "ks:ks_pop":505,
    "ks:ks_type":"HABITATION",
    "ks:ks_uagg_main":0,
    "name:eng_x_preferred":[
        "Nathamkodiyur"
    ],
    "wof:name":"Nathamkodiyur",
    "wof:placetype":"neighbourhood",
    "wof:population":505
},
  "geometry": {"coordinates":[78.20053299999999,12.210927],"type":"Point"}
}