{
  "type": "Feature",
  "properties": {
    "iso:country":"IN",
    "ks:ks_name":"Anjumala Junction",
    "ks:ks_pop":1897,
    "ks:ks_type":"HABITATION",
    "name:eng_x_preferred":[
        "Anjumala Junction"
    ],
    "wof:name":"Anjumala Junction",
    "wof:placetype":"locality",
    "wof:population":1897
},
  "geometry": {"coordinates":[76.78264799999999,9.762361],"type":"Point"}
}