{
  "type": "Feature",
  "properties": {
    "iso:country":"IN",
    "ks:ks_name":"Vailal",
    "ks:ks_pop":66,
    "ks:ks_type":"HABITATION",
    "name:eng_x_preferred":[
        "Vailal"
    ],
    "wof:name":"Vailal",
    "wof:placetype":"locality",
    "wof:population":66
},
  "geometry": {"coordinates":[74.484785,15.19361],"type":"Point"}
}