{
  "type": "Feature",
  "properties": {
    "iso:country":"IN",
    "ks:ks_name":"Ray Na Muvada",
    "ks:ks_pop":160,
    "ks:ks_type":"HABITATION",
    "name:eng_x_preferred":[
        "Ray Na Muvada"
    ],
    "wof:name":"Ray Na Muvada",
    "wof:placetype":"locality",
    "wof:population":160
},
  "geometry": {"coordinates":[73.19838900000001,23.149333],"type":"Point"}
}