{
  "type": "Feature",
  "properties": {
    "gn:admin1_code":"23",
    "gn:admin2_code":"38.0",
    "gn:asciiname":"Nangarain",
    "gn:country_code":"IN",
    "gn:dem":291,
    "gn:feature_class":"P",
    "gn:feature_code":"PPL",
    "gn:name":"Nangarain",
    "gn:population":0,
    "gn:timezone":"Asia/Kolkata",
    "iso:country":"IN",
    "ks:ks_name":"Naugarain",
    "ks:ks_pop":300,
    "ks:ks_type":"VILLAGE",
    "name:eng_x_preferred":[
        "Naugarain"
    ],
    "name:eng_x_variant":[
        "Nangarain"
    ],
    "wof:name":"Naugarain",
    "wof:placetype":"locality",
    "wof:population":300
},
  "geometry": {"coordinates":[75.935962,31.472604],"type":"Point"}
}