{
  "type": "Feature",
  "properties": {
    "gn:admin1_code":"23",
    "gn:admin2_code":"38.0",
    "gn:asciiname":"Nangarain",
    "gn:country_code":"IN",
    "gn:dem":291,
    "gn:feature_class":"P",
    "gn:feature_code":"PPL",
    "gn:name":"Nangarain",
    "gn:population":0,
    "gn:timezone":"Asia/Kolkata",
    "iso:country":"IN",
    "wof:name":"Nangarain",
    "wof:placetype":"locality"
},
  "geometry": {"coordinates":[75.93371999999999,31.47475],"type":"Point"}
}