{
  "type": "Feature",
  "properties": {
    "gn:admin1_code":"36",
    "gn:admin2_code":"154.0",
    "gn:asciiname":"Sukhipur",
    "gn:country_code":"IN",
    "gn:dem":129,
    "gn:feature_class":"P",
    "gn:feature_code":"PPL",
    "gn:name":"Sukhipur",
    "gn:population":0,
    "gn:timezone":"Asia/Kolkata",
    "iso:country":"IN",
    "ks:ks_name":"Sukaipur",
    "ks:ks_pop":390,
    "ks:ks_type":"VILLAGE",
    "ks:ks_uagg_main":0,
    "name:bih_x_preferred":[
        "\u0938\u0941\u0916\u0940\u092a\u0941\u0930"
    ],
    "name:ceb_x_preferred":[
        "Sukhipur"
    ],
    "name:deu_x_preferred":[
        "Sukhipur"
    ],
    "name:dty_x_preferred":[
        "\u0938\u0941\u0916\u093f\u092a\u0941\u0930 \u0928\u0917\u0930\u092a\u093e\u0932\u093f\u0915\u093e"
    ],
    "name:eng_x_preferred":[
        "Sukaipur"
    ],
    "name:mai_x_preferred":[
        "\u0938\u0941\u0916\u093f\u092a\u0941\u0930 \u0928\u0917\u0930\u092a\u093e\u0932\u093f\u0915\u093e"
    ],
    "name:msa_x_preferred":[
        "Sukhipur"
    ],
    "name:nep_x_preferred":[
        "\u0938\u0941\u0916\u093f\u092a\u0941\u0930 \u0928\u0917\u0930\u092a\u093e\u0932\u093f\u0915\u093e"
    ],
    "name:new_x_preferred":[
        "\u0938\u0941\u0916\u093f\u092a\u0941\u0930"
    ],
    "name:pol_x_preferred":[
        "Sukhipur"
    ],
    "wof:name":"Sukaipur",
    "wof:placetype":"neighbourhood",
    "wof:population":390
},
  "geometry": {"coordinates":[81.09195,27.303957],"type":"Point"}
}