{
  "type": "Feature",
  "properties": {
    "gn:admin1_code":"36.0",
    "gn:admin2_code":"186.0",
    "gn:asciiname":"Amra Koel",
    "gn:country_code":"IN",
    "gn:dem":83,
    "gn:feature_class":"P",
    "gn:feature_code":"PPL",
    "gn:name":"Amra Koel",
    "gn:population":0,
    "gn:timezone":"Asia/Kolkata",
    "iso:country":"IN",
    "ks:ks_name":"Amra Koel",
    "ks:ks_pop":393,
    "ks:ks_type":"VILLAGE",
    "name:eng_x_preferred":[
        "Amra Koel"
    ],
    "wof:name":"Amra Koel",
    "wof:placetype":"locality",
    "wof:population":393
},
  "geometry": {"coordinates":[82.941664,27.014456],"type":"Point"}
}