{
  "type": "Feature",
  "properties": {
    "iso:country":"IN",
    "ks:ks_name":"Pakri Pathan",
    "ks:ks_pop":603,
    "ks:ks_type":"HABITATION",
    "name:eng_x_preferred":[
        "Pakri Pathan"
    ],
    "wof:name":"Pakri Pathan",
    "wof:placetype":"locality",
    "wof:population":603
},
  "geometry": {"coordinates":[82.62948799999999,27.343294],"type":"Point"}
}