{
  "type": "Feature",
  "properties": {
    "iso:country":"IN",
    "ks:ks_alt_nam":"1 FM",
    "ks:ks_name":"1 Fm",
    "ks:ks_pop":100,
    "ks:ks_type":"HABITATION",
    "name:eng_x_preferred":[
        "1 Fm"
    ],
    "wof:name":"1 Fm",
    "wof:placetype":"locality",
    "wof:population":100
},
  "geometry": {"coordinates":[73.13098100000001,28.955167],"type":"Point"}
}