{
  "type": "Feature",
  "properties": {
    "iso:country":"IN",
    "ks:ks_name":"Bhaw Sihwan Shivrajpur",
    "ks:ks_pop":212,
    "ks:ks_type":"HABITATION",
    "ks:ks_uagg_main":0,
    "name:eng_x_preferred":[
        "Bhaw Sihwan Shivrajpur"
    ],
    "wof:name":"Bhaw Sihwan Shivrajpur",
    "wof:placetype":"neighbourhood",
    "wof:population":212
},
  "geometry": {"coordinates":[81.924722,25.968289],"type":"Point"}
}