{
  "type": "Feature",
  "properties": {
    "iso:country":"IN",
    "ks:ks_name":"Bhaibancherra",
    "ks:ks_pop":162,
    "ks:ks_type":"HABITATION",
    "name:eng_x_preferred":[
        "Bhaibancherra"
    ],
    "wof:name":"Bhaibancherra",
    "wof:placetype":"locality",
    "wof:population":162
},
  "geometry": {"coordinates":[92.17800800000001,24.02719],"type":"Point"}
}