{
  "type": "Feature",
  "properties": {
    "iso:country":"IN",
    "ks:ks_name":"Purba Pipla",
    "ks:ks_pop":1152,
    "ks:ks_type":"VILLAGE",
    "ks:ks_uagg_main":0,
    "name:eng_x_preferred":[
        "Purba Pipla"
    ],
    "wof:name":"Purba Pipla",
    "wof:placetype":"neighbourhood",
    "wof:population":1152
},
  "geometry": {"coordinates":[88.03265500000001,25.795232],"type":"Point"}
}