{
  "type": "Feature",
  "properties": {
    "iso:country":"IN",
    "ks:ks_name":"Dalkyari",
    "ks:ks_pop":126,
    "ks:ks_type":"HABITATION",
    "name:eng_x_preferred":[
        "Dalkyari"
    ],
    "wof:name":"Dalkyari",
    "wof:placetype":"locality",
    "wof:population":126
},
  "geometry": {"coordinates":[78.69812,30.344681],"type":"Point"}
}