{
  "type": "Feature",
  "properties": {
    "iso:country":"IN",
    "ks:ks_alt_nam":"TALAB KHERA",
    "ks:ks_name":"Talab Khera",
    "ks:ks_pop":113,
    "ks:ks_type":"HABITATION",
    "name:eng_x_preferred":[
        "Talab Khera"
    ],
    "wof:name":"Talab Khera",
    "wof:placetype":"locality",
    "wof:population":113
},
  "geometry": {"coordinates":[74.770184,23.958883],"type":"Point"}
}