{
  "type": "Feature",
  "properties": {
    "iso:country":"IN",
    "ks:ks_name":"Rampurawas Deoliya",
    "ks:ks_pop":380,
    "ks:ks_type":"VILLAGE",
    "ks:ks_uagg_main":0,
    "name:eng_x_preferred":[
        "Rampurawas Deoliya"
    ],
    "wof:name":"Rampurawas Deoliya",
    "wof:placetype":"neighbourhood",
    "wof:population":380
},
  "geometry": {"coordinates":[75.602341,26.826128],"type":"Point"}
}