{
  "type": "Feature",
  "properties": {
    "iso:country":"IN",
    "ks:ks_name":"Kharimakki",
    "ks:ks_pop":141,
    "ks:ks_type":"HABITATION",
    "name:eng_x_preferred":[
        "Kharimakki"
    ],
    "wof:name":"Kharimakki",
    "wof:placetype":"locality",
    "wof:population":141
},
  "geometry": {"coordinates":[74.22943600000001,14.771271],"type":"Point"}
}