{
  "type": "Feature",
  "properties": {
    "iso:country":"IN",
    "ks:ks_name":"Bakarshal Pt II",
    "ks:ks_pop":2810,
    "ks:ks_type":"VILLAGE",
    "ks:ks_uagg_main":0,
    "name:eng_x_preferred":[
        "Bakarshal Pt II"
    ],
    "wof:name":"Bakarshal Pt II",
    "wof:placetype":"locality",
    "wof:population":2810
},
  "geometry": {"coordinates":[92.398943,24.842863],"type":"Point"}
}