{
  "type": "Feature",
  "properties": {
    "iso:country":"IN",
    "ks:ks_name":"Rabangora",
    "ks:ks_pop":100,
    "ks:ks_type":"VILLAGE",
    "name:eng_x_preferred":[
        "Rabangora"
    ],
    "wof:name":"Rabangora",
    "wof:placetype":"locality",
    "wof:population":100
},
  "geometry": {"coordinates":[83.61699900000001,20.503659],"type":"Point"}
}