{
  "type": "Feature",
  "properties": {
    "iso:country":"IN",
    "ks:ks_name":"Uttar Roypur",
    "ks:ks_pop":2085,
    "ks:ks_type":"VILLAGE",
    "ks:ks_uagg_main":0,
    "name:eng_x_preferred":[
        "Uttar Roypur"
    ],
    "wof:name":"Uttar Roypur",
    "wof:placetype":"neighbourhood",
    "wof:population":2085
},
  "geometry": {"coordinates":[88.768591,25.338518],"type":"Point"}
}