{
  "type": "Feature",
  "properties": {
    "gn:admin1_code":"39.0",
    "gn:admin2_code":"60.0",
    "gn:asciiname":"Joliyon",
    "gn:country_code":"IN",
    "gn:dem":990,
    "gn:feature_class":"P",
    "gn:feature_code":"PPL",
    "gn:name":"Joliyon",
    "gn:population":0,
    "gn:timezone":"Asia/Kolkata",
    "iso:country":"IN",
    "wof:name":"Joliyon",
    "wof:placetype":"locality"
},
  "geometry": {"coordinates":[78.15716,30.30715],"type":"Point"}
}