{
  "type": "Feature",
  "properties": {
    "iso:country":"IN",
    "ks:ks_name":"Manipada",
    "ks:ks_pop":443,
    "ks:ks_type":"HABITATION",
    "name:eng_x_preferred":[
        "Manipada"
    ],
    "wof:name":"Manipada",
    "wof:placetype":"locality",
    "wof:population":443
},
  "geometry": {"coordinates":[72.840954,19.871079],"type":"Point"}
}