{
  "type": "Feature",
  "properties": {
    "iso:country":"IN",
    "ks:ks_name":"Dadarpali",
    "ks:ks_pop":336,
    "ks:ks_type":"VILLAGE",
    "name:eng_x_preferred":[
        "Dadarpali"
    ],
    "wof:name":"Dadarpali",
    "wof:placetype":"locality",
    "wof:population":336
},
  "geometry": {"coordinates":[84.047878,21.020674],"type":"Point"}
}