{
  "type": "Feature",
  "properties": {
    "gn:admin1_code":"36",
    "gn:admin2_code":"137.0",
    "gn:asciiname":"Tanda",
    "gn:country_code":"IN",
    "gn:dem":222,
    "gn:feature_class":"P",
    "gn:feature_code":"PPL",
    "gn:name":"T\u0101nda",
    "gn:population":0,
    "gn:timezone":"Asia/Kolkata",
    "iso:country":"IN",
    "ks:ks_alt_nam":"T\u0101nda",
    "ks:ks_name":"Tanda",
    "ks:ks_pop":113,
    "ks:ks_type":"VILLAGE",
    "ks:ks_uagg_main":0,
    "name:bpy_x_preferred":[
        "\u09a4\u09be\u09a8\u09cd\u09a6\u09be"
    ],
    "name:ceb_x_preferred":[
        "Tanda"
    ],
    "name:deu_x_preferred":[
        "Tanda"
    ],
    "name:eng_x_preferred":[
        "Tanda"
    ],
    "name:eng_x_variant":[
        "T\u0101nda"
    ],
    "name:fra_x_preferred":[
        "Tanda"
    ],
    "name:ita_x_preferred":[
        "Tanda"
    ],
    "name:nld_x_preferred":[
        "Tanda"
    ],
    "name:pol_x_preferred":[
        "Tanda"
    ],
    "name:swa_x_preferred":[
        "Tanda"
    ],
    "name:swe_x_preferred":[
        "Tanda"
    ],
    "wof:name":"Tanda",
    "wof:placetype":"neighbourhood",
    "wof:population":113
},
  "geometry": {"coordinates":[78.308932,29.037424],"type":"Point"}
}