{
  "type": "Feature",
  "properties": {
    "gn:admin1_code":"16",
    "gn:admin2_code":"504.0",
    "gn:asciiname":"Kalamner",
    "gn:country_code":"IN",
    "gn:dem":232,
    "gn:feature_class":"P",
    "gn:feature_code":"PPL",
    "gn:name":"Kalamner",
    "gn:population":0,
    "gn:timezone":"Asia/Kolkata",
    "iso:country":"IN",
    "wof:name":"Kalamner",
    "wof:placetype":"locality"
},
  "geometry": {"coordinates":[78.57479000000002,20.43249],"type":"Point"}
}