{
  "type": "Feature",
  "properties": {
    "gn:admin1_code":"33",
    "gn:admin2_code":"585.0",
    "gn:asciiname":"Latambarcem",
    "gn:country_code":"IN",
    "gn:dem":26,
    "gn:feature_class":"P",
    "gn:feature_code":"PPL",
    "gn:name":"Latambarcem",
    "gn:population":0,
    "gn:timezone":"Asia/Kolkata",
    "iso:country":"IN",
    "name:hin_x_preferred":[
        "\u0932\u093e\u0924\u092e\u094d\u092c\u0930\u0938\u0947\u092e"
    ],
    "name:und_x_variant":[
        "Latembarcem",
        "Latambarcem"
    ],
    "wof:name":"Latambarcem",
    "wof:placetype":"locality"
},
  "geometry": {"coordinates":[73.93643,15.65096],"type":"Point"}
}