{
  "type": "Feature",
  "properties": {
    "gn:admin1_code":"36",
    "gn:admin2_code":"173.0",
    "gn:asciiname":"Saruppur",
    "gn:country_code":"IN",
    "gn:dem":98,
    "gn:feature_class":"P",
    "gn:feature_code":"PPL",
    "gn:name":"Sar\u016bppur",
    "gn:population":0,
    "gn:timezone":"Asia/Kolkata",
    "iso:country":"IN",
    "name:und_x_variant":[
        "Sar\u016bppur",
        "Naurera"
    ],
    "wof:name":"Saruppur",
    "wof:placetype":"locality"
},
  "geometry": {"coordinates":[82.15177,25.72742],"type":"Point"}
}