{
  "type": "Feature",
  "properties": {
    "iso:country":"IN",
    "ks:ks_name":"Nagla Khera",
    "ks:ks_pop":817,
    "ks:ks_type":"HABITATION",
    "ks:ks_uagg_main":0,
    "name:eng_x_preferred":[
        "Nagla Khera"
    ],
    "wof:name":"Nagla Khera",
    "wof:placetype":"neighbourhood",
    "wof:population":817
},
  "geometry": {"coordinates":[77.885079,27.491923],"type":"Point"}
}