{
  "type": "Feature",
  "properties": {
    "gn:admin1_code":"19.0",
    "gn:admin2_code":"574.0",
    "gn:asciiname":"Magallu",
    "gn:country_code":"IN",
    "gn:dem":921,
    "gn:feature_class":"P",
    "gn:feature_code":"PPL",
    "gn:name":"Magallu",
    "gn:population":0,
    "gn:timezone":"Asia/Kolkata",
    "iso:country":"IN",
    "name:hin_x_preferred":[
        "\u092e\u0917\u0932\u0941"
    ],
    "name:new_x_preferred":[
        "\u092e\u0917\u0932\u0941"
    ],
    "name:tel_x_preferred":[
        "\u0c2e\u0c3e\u0c17\u0c32\u0c4d\u0c32\u0c41"
    ],
    "wof:name":"Magallu",
    "wof:placetype":"locality"
},
  "geometry": {"coordinates":[75.84893000000002,12.82561],"type":"Point"}
}