{
  "type": "Feature",
  "properties": {
    "iso:country":"IN",
    "ks:ks_name":"Bommandahalli",
    "ks:ks_pop":651,
    "ks:ks_type":"VILLAGE",
    "ks:ks_uagg_main":0,
    "name:eng_x_preferred":[
        "Bommandahalli"
    ],
    "wof:name":"Bommandahalli",
    "wof:placetype":"locality",
    "wof:population":651
},
  "geometry": {"coordinates":[77.638944,12.753568],"type":"Point"}
}