{
  "type": "Feature",
  "properties": {
    "gn:admin1_code":"36.0",
    "gn:admin2_code":"150.0",
    "gn:asciiname":"Kuiyan Ram Sahai",
    "gn:country_code":"IN",
    "gn:dem":175,
    "gn:feature_class":"P",
    "gn:feature_code":"PPL",
    "gn:name":"Kuiy\u0101n R\u0101m Sah\u0101i",
    "gn:population":0,
    "gn:timezone":"Asia/Kolkata",
    "iso:country":"IN",
    "wof:name":"Kuiyan Ram Sahai",
    "wof:placetype":"locality"
},
  "geometry": {"coordinates":[79.69681,28.37358],"type":"Point"}
}