{
  "type": "Feature",
  "properties": {
    "iso:country":"IN",
    "ks:ks_name":"Phalyati",
    "ks:ks_pop":123,
    "ks:ks_type":"HABITATION",
    "name:eng_x_preferred":[
        "Phalyati"
    ],
    "wof:name":"Phalyati",
    "wof:placetype":"locality",
    "wof:population":123
},
  "geometry": {"coordinates":[80.150076,29.898378],"type":"Point"}
}