{
  "type": "Feature",
  "properties": {
    "iso:country":"IN",
    "ks:ks_name":"Banjapadar",
    "ks:ks_pop":130,
    "ks:ks_type":"HABITATION",
    "name:eng_x_preferred":[
        "Banjapadar"
    ],
    "wof:name":"Banjapadar",
    "wof:placetype":"locality",
    "wof:population":130
},
  "geometry": {"coordinates":[82.873519,18.843753],"type":"Point"}
}