{
  "type": "Feature",
  "properties": {
    "iso:country":"IN",
    "ks:ks_alt_nam":"Ng.Chita",
    "ks:ks_name":"Ng.chita",
    "ks:ks_pop":34,
    "ks:ks_type":"HABITATION",
    "name:eng_x_preferred":[
        "Ng.chita"
    ],
    "wof:name":"Ng.chita",
    "wof:placetype":"locality",
    "wof:population":34
},
  "geometry": {"coordinates":[79.062727,27.757736],"type":"Point"}
}