{
  "type": "Feature",
  "properties": {
    "iso:country":"IN",
    "ks:ks_alt_nam":"T\u0101t\u0101",
    "ks:ks_name":"Tata",
    "ks:ks_pop":89,
    "ks:ks_type":"VILLAGE",
    "name:eng_x_preferred":[
        "Tata"
    ],
    "name:eng_x_variant":[
        "T\u0101t\u0101"
    ],
    "wof:name":"Tata",
    "wof:placetype":"locality",
    "wof:population":89
},
  "geometry": {"coordinates":[84.872349,23.547113],"type":"Point"}
}