{
  "type": "Feature",
  "properties": {
    "iso:country":"IN",
    "ks:ks_name":"Siddipura",
    "ks:ks_pop":814,
    "ks:ks_type":"HABITATION",
    "name:eng_x_preferred":[
        "Siddipura"
    ],
    "wof:name":"Siddipura",
    "wof:placetype":"locality",
    "wof:population":814
},
  "geometry": {"coordinates":[75.97211,13.78753],"type":"Point"}
}