{
  "type": "Feature",
  "properties": {
    "gn:admin1_code":"35",
    "gn:admin2_code":"423.0",
    "gn:asciiname":"Samuha",
    "gn:country_code":"IN",
    "gn:dem":252,
    "gn:feature_class":"P",
    "gn:feature_code":"PPL",
    "gn:name":"Samuha",
    "gn:population":0,
    "gn:timezone":"Asia/Kolkata",
    "iso:country":"IN",
    "name:cat_x_preferred":[
        "Samuha"
    ],
    "name:deu_x_preferred":[
        "\u0160amu\u1e2ba"
    ],
    "name:eus_x_preferred":[
        "Samuha"
    ],
    "name:fra_x_preferred":[
        "Samuha"
    ],
    "name:glg_x_preferred":[
        "Samuha"
    ],
    "name:hun_x_preferred":[
        "Szamuha"
    ],
    "name:ita_x_preferred":[
        "Samuha"
    ],
    "name:kat_x_preferred":[
        "\u10e1\u10d0\u10db\u10e3\u10ee\u10d0"
    ],
    "name:spa_x_preferred":[
        "Samuha"
    ],
    "wof:name":"Samuha",
    "wof:placetype":"locality"
},
  "geometry": {"coordinates":[78.19325000000001,25.57024],"type":"Point"}
}