{
  "type": "Feature",
  "properties": {
    "iso:country":"IN",
    "ks:ks_name":"Bandi Falia",
    "ks:ks_pop":377,
    "ks:ks_type":"HABITATION",
    "name:eng_x_preferred":[
        "Bandi Falia"
    ],
    "wof:name":"Bandi Falia",
    "wof:placetype":"locality",
    "wof:population":377
},
  "geometry": {"coordinates":[74.279556,23.114583],"type":"Point"}
}