{
  "type": "Feature",
  "properties": {
    "iso:country":"IN",
    "ks:ks_name":"Melekipara",
    "ks:ks_pop":202,
    "ks:ks_type":"HABITATION",
    "ks:ks_uagg_main":0,
    "name:eng_x_preferred":[
        "Melekipara"
    ],
    "wof:name":"Melekipara",
    "wof:placetype":"locality",
    "wof:population":202
},
  "geometry": {"coordinates":[91.475973,26.104089],"type":"Point"}
}