{
  "type": "Feature",
  "properties": {
    "gn:admin1_code":"12.0",
    "gn:admin2_code":"1.0",
    "gn:asciiname":"Gichhpur",
    "gn:country_code":"IN",
    "gn:dem":1941,
    "gn:feature_class":"P",
    "gn:feature_code":"PPL",
    "gn:name":"Gichhpur",
    "gn:population":0,
    "gn:timezone":"Asia/Kolkata",
    "iso:country":"IN",
    "wof:name":"Gichhpur",
    "wof:placetype":"locality"
},
  "geometry": {"coordinates":[74.24339000000001,34.59811],"type":"Point"}
}