{
  "type": "Feature",
  "properties": {
    "gn:country":"IN",
    "gn:fcode":"PPL",
    "gn:population":20923,
    "iso:country":"IN",
    "name:ara_x_preferred":[
        "\u0645\u0646\u0637\u0642\u0629 \u0628\u0627\u0631\u0627\u0628\u0627\u0646\u0643\u064a"
    ],
    "name:bih_x_preferred":[
        "\u092c\u093e\u0930\u093e\u092c\u0902\u0915\u0940 \u091c\u093f\u0932\u093e"
    ],
    "name:dan_x_preferred":[
        "Barabanki"
    ],
    "name:deu_x_preferred":[
        "Barabanki"
    ],
    "name:fas_x_preferred":[
        "\u0628\u062e\u0634 \u0628\u0627\u0631\u0647\u200c\u0628\u0646\u06a9\u06cc"
    ],
    "name:hin_x_preferred":[
        "\u092c\u093e\u0930\u093e\u092c\u0902\u0915\u0940 \u091c\u093f\u0932\u093e"
    ],
    "name:mar_x_preferred":[
        "\u092c\u093e\u0930\u093e\u092c\u0902\u0915\u0940 \u091c\u093f\u0932\u094d\u0939\u093e"
    ],
    "name:msa_x_preferred":[
        "Banki"
    ],
    "name:nep_x_preferred":[
        "\u092c\u093e\u0930\u093e\u092c\u0902\u0915\u0940 \u091c\u093f\u0932\u094d\u0932\u093e"
    ],
    "name:new_x_preferred":[
        "\u092c\u093e\u0930\u093e\u092c\u0902\u0915\u0940 \u091c\u093f\u0932\u094d\u0932\u093e"
    ],
    "name:nld_x_preferred":[
        "Barabanki"
    ],
    "name:nor_x_preferred":[
        "Barabanki"
    ],
    "name:ori_x_preferred":[
        "\u0b2c\u0b3e\u0b30\u0b3e\u0b2c\u0b19\u0b4d\u0b15\u0b40 \u0b1c\u0b3f\u0b32\u0b4d\u0b32\u0b3e"
    ],
    "name:pnb_x_preferred":[
        "\u0636\u0644\u0639 \u0628\u0627\u0631\u0627\u0628\u0646\u06a9\u06cc"
    ],
    "name:rus_x_preferred":[
        "\u0411\u0430\u0440\u0430\u0431\u0430\u043d\u043a\u0438"
    ],
    "name:san_x_preferred":[
        "\u092c\u093e\u0930\u093e\u092c\u0919\u094d\u0915\u0940\u092e\u0923\u094d\u0921\u0932\u092e\u094d"
    ],
    "name:swe_x_preferred":[
        "Nawabganj"
    ],
    "name:tam_x_preferred":[
        "\u0baa\u0bbe\u0bb0\u0bbe\u0baa\u0b99\u0bcd\u0b95\u0bbf \u0bae\u0bbe\u0bb5\u0b9f\u0bcd\u0b9f\u0bae\u0bcd"
    ],
    "name:tel_x_preferred":[
        "\u0c2c\u0c3e\u0c30\u0c3e\u0c2c\u0c02\u0c15\u0c3f"
    ],
    "name:und_x_variant":[
        "Saranli"
    ],
    "name:vie_x_preferred":[
        "Barabanki"
    ],
    "name:zho_x_preferred":[
        "\u5df4\u62c9\u73ed\u57fa\u7e23"
    ],
    "qs:name":"Sandauli",
    "qs:name_adm0":"India",
    "qs:name_adm1":"Uttar Pradesh",
    "qs:photos_9r":0,
    "qs:photos_sr":0,
    "qs:placetype":"Town",
    "qs:pop_sr":"7",
    "wd:wordcount":9049,
    "wof:name":"Sandauli",
    "wof:placetype":"locality",
    "wof:population":20923
},
  "geometry": {"coordinates":[79.09139999999999,28.4929],"type":"Point"}
}