{
  "type": "Feature",
  "properties": {
    "gn:country":"IN",
    "gn:fcode":"PPL",
    "gn:pop":20923,
    "iso:country":"IN",
    "name:unk_x_variant":[
        "Saranli"
    ],
    "qs:name":"Sandauli",
    "qs:name_adm0":"India",
    "qs:name_adm1":"Uttar Pradesh",
    "qs:photos_9r":0,
    "qs:photos_sr":0,
    "qs:placetype":"Town",
    "qs:pop_sr":"7",
    "wd:wordcount":9049,
    "wof:name":"Sandauli",
    "wof:placetype":"locality",
    "wof:population":20923
},
  "geometry": {"coordinates":[79.09139999999999,28.4929],"type":"Point"}
}