{
  "type": "Feature",
  "properties": {
    "iso:country":"IN",
    "ks:ks_name":"Musarlanka",
    "ks:ks_pop":61,
    "ks:ks_type":"HABITATION",
    "name:eng_x_preferred":[
        "Musarlanka"
    ],
    "wof:name":"Musarlanka",
    "wof:placetype":"locality",
    "wof:population":61
},
  "geometry": {"coordinates":[82.69905300000001,18.303566],"type":"Point"}
}