{
  "type": "Feature",
  "properties": {
    "iso:country":"IN",
    "ks:ks_name":"Rangapura",
    "ks:ks_type":"VILLAGE",
    "name:eng_x_preferred":[
        "Rangapura"
    ],
    "wof:name":"Rangapura",
    "wof:placetype":"locality"
},
  "geometry": {"coordinates":[75.876454,13.89365],"type":"Point"}
}