{
  "type": "Feature",
  "properties": {
    "gn:admin1_code":"16.0",
    "gn:admin2_code":"523.0",
    "gn:asciiname":"Kesapuri",
    "gn:country_code":"IN",
    "gn:dem":437,
    "gn:feature_class":"P",
    "gn:feature_code":"PPL",
    "gn:name":"Kes\u0101puri",
    "gn:population":0,
    "gn:timezone":"Asia/Kolkata",
    "iso:country":"IN",
    "ks:ks_alt_nam":"Kes\u0101puri",
    "ks:ks_name":"Kesapuri",
    "ks:ks_pop":5362,
    "ks:ks_type":"VILLAGE",
    "ks:ks_uagg_main":0,
    "name:eng_x_preferred":[
        "Kesapuri"
    ],
    "name:eng_x_variant":[
        "Kes\u0101puri"
    ],
    "wof:name":"Kesapuri",
    "wof:placetype":"neighbourhood",
    "wof:population":5362
},
  "geometry": {"coordinates":[76.192752,19.179671],"type":"Point"}
}