{
  "type": "Feature",
  "properties": {
    "iso:country":"IN",
    "ks:ks_alt_nam":"MOOLAYIL",
    "ks:ks_name":"Moolayil",
    "ks:ks_pop":2070,
    "ks:ks_type":"HABITATION",
    "name:eng_x_preferred":[
        "Moolayil"
    ],
    "wof:name":"Moolayil",
    "wof:placetype":"locality",
    "wof:population":2070
},
  "geometry": {"coordinates":[76.331056,10.831508],"type":"Point"}
}