{
  "type": "Feature",
  "properties": {
    "iso:country":"IN",
    "ks:ks_name":"Koti",
    "ks:ks_pop":51,
    "ks:ks_type":"HABITATION",
    "name:eng_x_preferred":[
        "Koti"
    ],
    "wof:name":"Koti",
    "wof:placetype":"locality",
    "wof:population":51
},
  "geometry": {"coordinates":[81.589195,24.805298],"type":"Point"}
}