{
  "type": "Feature",
  "properties": {
    "iso:country":"IN",
    "ks:ks_alt_nam":"MANWARDIPA",
    "ks:ks_name":"Manwardipa",
    "ks:ks_pop":365,
    "ks:ks_type":"HABITATION",
    "name:eng_x_preferred":[
        "Manwardipa"
    ],
    "wof:name":"Manwardipa",
    "wof:placetype":"locality",
    "wof:population":365
},
  "geometry": {"coordinates":[83.767933,22.59693],"type":"Point"}
}