{
  "type": "Feature",
  "properties": {
    "gn:admin1_code":"11.0",
    "gn:admin2_code":"26.0",
    "gn:asciiname":"Panasha ka Dir",
    "gn:country_code":"IN",
    "gn:dem":1561,
    "gn:feature_class":"P",
    "gn:feature_code":"PPL",
    "gn:name":"Pan\u0101sha ka Dir",
    "gn:population":0,
    "gn:timezone":"Asia/Kolkata",
    "iso:country":"IN",
    "wof:name":"Panasha ka Dir",
    "wof:placetype":"locality"
},
  "geometry": {"coordinates":[77.6142,31.44669],"type":"Point"}
}