{
  "type": "Feature",
  "properties": {
    "gn:admin1_code":"36",
    "gn:admin2_code":"176.0",
    "gn:asciiname":"Jahanabad",
    "gn:country_code":"IN",
    "gn:dem":119,
    "gn:feature_class":"P",
    "gn:feature_code":"PPL",
    "gn:name":"Jah\u0101n\u0101b\u0101d",
    "gn:population":0,
    "gn:timezone":"Asia/Kolkata",
    "iso:country":"IN",
    "name:ceb_x_preferred":[
        "Jahanabad"
    ],
    "name:fas_x_preferred":[
        "\u062c\u0647\u0627\u0646\u200c\u0622\u0628\u0627\u062f"
    ],
    "name:rus_x_preferred":[
        "\u0414\u0436\u0435\u0445\u0430\u043d\u0430\u0431\u0430\u0434"
    ],
    "name:swe_x_preferred":[
        "Jahanabad"
    ],
    "wof:name":"Jahanabad",
    "wof:placetype":"locality"
},
  "geometry": {"coordinates":[81.31041,26.75714],"type":"Point"}
}