{
  "type": "Feature",
  "properties": {
    "iso:country":"IN",
    "ks:ks_name":"Baradharia",
    "ks:ks_pop":184,
    "ks:ks_type":"HABITATION",
    "name:eng_x_preferred":[
        "Baradharia"
    ],
    "wof:name":"Baradharia",
    "wof:placetype":"locality",
    "wof:population":184
},
  "geometry": {"coordinates":[86.384727,21.051106],"type":"Point"}
}