{
  "type": "Feature",
  "properties": {
    "iso:country":"IN",
    "ks:ks_name":"Mylachal",
    "ks:ks_pop":1733,
    "ks:ks_type":"HABITATION",
    "name:eng_x_preferred":[
        "Mylachal"
    ],
    "wof:name":"Mylachal",
    "wof:placetype":"locality",
    "wof:population":1733
},
  "geometry": {"coordinates":[77.135262,8.466118],"type":"Point"}
}