{
  "type": "Feature",
  "properties": {
    "iso:country":"IN",
    "ks:ks_name":"Machcha",
    "ks:ks_pop":1508,
    "ks:ks_type":"HABITATION",
    "ks:ks_uagg_main":0,
    "name:eng_x_preferred":[
        "Machcha"
    ],
    "wof:name":"Machcha",
    "wof:placetype":"neighbourhood",
    "wof:population":1508
},
  "geometry": {"coordinates":[85.889599,26.285738],"type":"Point"}
}