{
  "type": "Feature",
  "properties": {
    "gn:admin1_code":"11",
    "gn:admin2_code":"23.0",
    "gn:asciiname":"Bilpar",
    "gn:country_code":"IN",
    "gn:dem":1214,
    "gn:feature_class":"P",
    "gn:feature_code":"PPL",
    "gn:name":"Bilpar",
    "gn:population":0,
    "gn:timezone":"Asia/Kolkata",
    "iso:country":"IN",
    "name:und_x_variant":[
        "Bittar"
    ],
    "wof:name":"Bilpar",
    "wof:placetype":"locality"
},
  "geometry": {"coordinates":[76.09564,32.33651],"type":"Point"}
}