{
  "type": "Feature",
  "properties": {
    "iso:country":"IN",
    "ks:ks_name":"Mali Mala",
    "ks:ks_pop":516,
    "ks:ks_type":"HABITATION",
    "name:eng_x_preferred":[
        "Mali Mala"
    ],
    "wof:name":"Mali Mala",
    "wof:placetype":"locality",
    "wof:population":516
},
  "geometry": {"coordinates":[75.066703,17.333804],"type":"Point"}
}