{
  "type": "Feature",
  "properties": {
    "gn:admin1_code":"2.0",
    "gn:admin2_code":"545.0",
    "gn:asciiname":"Egayalasa",
    "gn:country_code":"IN",
    "gn:dem":617,
    "gn:feature_class":"P",
    "gn:feature_code":"PPL",
    "gn:name":"Egayalasa",
    "gn:population":0,
    "gn:timezone":"Asia/Kolkata",
    "iso:country":"IN",
    "ks:ks_name":"Egavalasa",
    "ks:ks_pop":110,
    "ks:ks_type":"HABITATION",
    "name:eng_x_preferred":[
        "Egavalasa"
    ],
    "name:eng_x_variant":[
        "Egayalasa"
    ],
    "wof:name":"Egavalasa",
    "wof:placetype":"locality",
    "wof:population":110
},
  "geometry": {"coordinates":[81.74953600000001,17.771436],"type":"Point"}
}