{
  "type": "Feature",
  "properties": {
    "iso:country":"IN",
    "ks:ks_name":"Singona",
    "ks:ks_pop":7,
    "ks:ks_type":"VILLAGE",
    "name:eng_x_preferred":[
        "Singona"
    ],
    "wof:name":"Singona",
    "wof:placetype":"locality",
    "wof:population":7
},
  "geometry": {"coordinates":[78.18873499999999,20.999202],"type":"Point"}
}