{
  "type": "Feature",
  "properties": {
    "iso:country":"IN",
    "ks:ks_name":"Kewtali Mahadewpara",
    "ks:ks_pop":491,
    "ks:ks_type":"HABITATION",
    "name:eng_x_preferred":[
        "Kewtali Mahadewpara"
    ],
    "wof:name":"Kewtali Mahadewpara",
    "wof:placetype":"locality",
    "wof:population":491
},
  "geometry": {"coordinates":[82.91194,23.366514],"type":"Point"}
}