{
  "type": "Feature",
  "properties": {
    "iso:country":"IN",
    "ks:ks_name":"Bramhanwadi",
    "ks:ks_pop":94,
    "ks:ks_type":"HABITATION",
    "name:eng_x_preferred":[
        "Bramhanwadi"
    ],
    "wof:name":"Bramhanwadi",
    "wof:placetype":"locality",
    "wof:population":94
},
  "geometry": {"coordinates":[73.50311000000001,16.982076],"type":"Point"}
}