{
  "type": "Feature",
  "properties": {
    "iso:country":"IN",
    "ks:ks_name":"K Narasapuram",
    "ks:ks_pop":180,
    "ks:ks_type":"HABITATION",
    "name:eng_x_preferred":[
        "K Narasapuram"
    ],
    "wof:name":"K Narasapuram",
    "wof:placetype":"locality",
    "wof:population":180
},
  "geometry": {"coordinates":[77.412818,13.892799],"type":"Point"}
}