{
  "type": "Feature",
  "properties": {
    "gn:admin1_code":"35.0",
    "gn:admin2_code":"449.0",
    "gn:asciiname":"Parrai",
    "gn:country_code":"IN",
    "gn:dem":372,
    "gn:feature_class":"P",
    "gn:feature_code":"PPL",
    "gn:name":"Parrai",
    "gn:population":0,
    "gn:timezone":"Asia/Kolkata",
    "iso:country":"IN",
    "ks:ks_name":"Parrai",
    "ks:ks_type":"VILLAGE",
    "name:eng_x_preferred":[
        "Parrai"
    ],
    "wof:name":"Parrai",
    "wof:placetype":"locality"
},
  "geometry": {"coordinates":[78.476161,22.698962],"type":"Point"}
}