{
  "type": "Feature",
  "properties": {
    "iso:country":"IN",
    "ks:ks_alt_nam":"Nazr\u0101b\u0101d",
    "ks:ks_name":"Nazrabad",
    "ks:ks_type":"VILLAGE",
    "name:eng_x_preferred":[
        "Nazrabad"
    ],
    "name:eng_x_variant":[
        "Nazr\u0101b\u0101d"
    ],
    "wof:name":"Nazrabad",
    "wof:placetype":"locality"
},
  "geometry": {"coordinates":[83.679568,25.072085],"type":"Point"}
}