{
  "type": "Feature",
  "properties": {
    "gn:admin1_code":"19.0",
    "gn:admin2_code":"578.0",
    "gn:asciiname":"Berambadi",
    "gn:country_code":"IN",
    "gn:dem":911,
    "gn:feature_class":"P",
    "gn:feature_code":"PPL",
    "gn:name":"B\u0113ramb\u0101di",
    "gn:population":0,
    "gn:timezone":"Asia/Kolkata",
    "iso:country":"IN",
    "wof:name":"Berambadi",
    "wof:placetype":"locality"
},
  "geometry": {"coordinates":[76.56749000000001,11.7612],"type":"Point"}
}