{
  "type": "Feature",
  "properties": {
    "iso:country":"IN",
    "ks:ks_name":"Karanjamal",
    "ks:ks_pop":22,
    "ks:ks_type":"HABITATION",
    "name:eng_x_preferred":[
        "Karanjamal"
    ],
    "wof:name":"Karanjamal",
    "wof:placetype":"locality",
    "wof:population":22
},
  "geometry": {"coordinates":[86.52293,20.980817],"type":"Point"}
}