{
  "type": "Feature",
  "properties": {
    "gn:admin1_code":"16",
    "gn:admin2_code":"515.0",
    "gn:asciiname":"Khamgaon",
    "gn:country_code":"IN",
    "gn:dem":572,
    "gn:feature_class":"P",
    "gn:feature_code":"PPL",
    "gn:name":"Kh\u0101mgaon",
    "gn:population":0,
    "gn:timezone":"Asia/Kolkata",
    "iso:country":"IN",
    "wof:name":"Khamgaon",
    "wof:placetype":"locality"
},
  "geometry": {"coordinates":[74.94898000000001,20.14834],"type":"Point"}
}