{
  "type": "Feature",
  "properties": {
    "iso:country":"IN",
    "ks:ks_name":"Dhauha",
    "ks:ks_pop":30,
    "ks:ks_type":"HABITATION",
    "name:eng_x_preferred":[
        "Dhauha"
    ],
    "wof:name":"Dhauha",
    "wof:placetype":"locality",
    "wof:population":30
},
  "geometry": {"coordinates":[81.959791,24.516777],"type":"Point"}
}