{
  "type": "Feature",
  "properties": {
    "iso:country":"IN",
    "ks:ks_alt_nam":"Long-E-Pi",
    "ks:ks_name":"Long-e-pi",
    "ks:ks_pop":53,
    "ks:ks_type":"HABITATION",
    "name:eng_x_preferred":[
        "Long-e-pi"
    ],
    "wof:name":"Long-e-pi",
    "wof:placetype":"locality",
    "wof:population":53
},
  "geometry": {"coordinates":[92.638285,25.907479],"type":"Point"}
}