{
  "type": "Feature",
  "properties": {
    "gn:admin1_code":"23",
    "gn:admin2_code":"37.0",
    "gn:asciiname":"Sichewali",
    "gn:country_code":"IN",
    "gn:dem":222,
    "gn:feature_class":"P",
    "gn:feature_code":"PPL",
    "gn:name":"Sichew\u0101li",
    "gn:population":0,
    "gn:timezone":"Asia/Kolkata",
    "iso:country":"IN",
    "wof:name":"Sichewali",
    "wof:placetype":"locality"
},
  "geometry": {"coordinates":[75.30499,31.15733],"type":"Point"}
}