{
  "type": "Feature",
  "properties": {
    "iso:country":"IN",
    "ks:ks_name":"Baudhwadi",
    "ks:ks_pop":60,
    "ks:ks_type":"HABITATION",
    "name:eng_x_preferred":[
        "Baudhwadi"
    ],
    "wof:name":"Baudhwadi",
    "wof:placetype":"locality",
    "wof:population":60
},
  "geometry": {"coordinates":[73.324572,17.592033],"type":"Point"}
}