{
  "type": "Feature",
  "properties": {
    "iso:country":"IN",
    "ks:ks_name":"Kudaiya",
    "ks:ks_pop":13,
    "ks:ks_type":"HABITATION",
    "name:eng_x_preferred":[
        "Kudaiya"
    ],
    "wof:name":"Kudaiya",
    "wof:placetype":"locality",
    "wof:population":13
},
  "geometry": {"coordinates":[77.216328,24.412642],"type":"Point"}
}