{
  "type": "Feature",
  "properties": {
    "iso:country":"IN",
    "ks:ks_name":"Bhendri",
    "ks:ks_pop":612,
    "ks:ks_type":"VILLAGE",
    "name:eng_x_preferred":[
        "Bhendri"
    ],
    "wof:name":"Bhendri",
    "wof:placetype":"locality",
    "wof:population":612
},
  "geometry": {"coordinates":[83.346323,23.49381],"type":"Point"}
}