{
  "type": "Feature",
  "properties": {
    "gn:admin1_code":"36",
    "gn:admin2_code":"169.0",
    "gn:asciiname":"Lataura",
    "gn:country_code":"IN",
    "gn:dem":150,
    "gn:feature_class":"P",
    "gn:feature_code":"PPL",
    "gn:name":"Lataura",
    "gn:population":0,
    "gn:timezone":"Asia/Kolkata",
    "iso:country":"IN",
    "ks:ks_name":"Lataura",
    "ks:ks_type":"VILLAGE",
    "name:eng_x_preferred":[
        "Lataura"
    ],
    "wof:name":"Lataura",
    "wof:placetype":"locality"
},
  "geometry": {"coordinates":[79.73702,25.516563],"type":"Point"}
}