{
  "type": "Feature",
  "properties": {
    "iso:country":"IN",
    "ks:ks_name":"Dewkura",
    "ks:ks_pop":481,
    "ks:ks_type":"VILLAGE",
    "ks:ks_uagg_main":0,
    "name:eng_x_preferred":[
        "Dewkura"
    ],
    "wof:name":"Dewkura",
    "wof:placetype":"neighbourhood",
    "wof:population":481
},
  "geometry": {"coordinates":[90.86755100000001,26.380958],"type":"Point"}
}