{
  "type": "Feature",
  "properties": {
    "iso:country":"IN",
    "ks:ks_name":"Gajarakumpa",
    "ks:ks_pop":222,
    "ks:ks_type":"VILLAGE",
    "name:eng_x_preferred":[
        "Gajarakumpa"
    ],
    "wof:name":"Gajarakumpa",
    "wof:placetype":"locality",
    "wof:population":222
},
  "geometry": {"coordinates":[84.382172,19.595077],"type":"Point"}
}