{
  "type": "Feature",
  "properties": {
    "gn:admin1_code":"16",
    "gn:admin2_code":"508.0",
    "gn:asciiname":"Satputi",
    "gn:country_code":"IN",
    "gn:dem":396,
    "gn:feature_class":"P",
    "gn:feature_code":"PPL",
    "gn:name":"S\u0101tputi",
    "gn:population":0,
    "gn:timezone":"Asia/Kolkata",
    "iso:country":"IN",
    "ks:ks_alt_nam":"S\u0101tputi",
    "ks:ks_name":"Satputi",
    "ks:ks_pop":251,
    "ks:ks_type":"VILLAGE",
    "name:eng_x_preferred":[
        "Satputi"
    ],
    "name:eng_x_variant":[
        "S\u0101tputi"
    ],
    "wof:name":"Satputi",
    "wof:placetype":"locality",
    "wof:population":251
},
  "geometry": {"coordinates":[80.50322799999999,20.690219],"type":"Point"}
}