{
  "type": "Feature",
  "properties": {
    "iso:country":"IN",
    "ks:ks_name":"Mattavaripalli",
    "ks:ks_pop":39,
    "ks:ks_type":"HABITATION",
    "name:eng_x_preferred":[
        "Mattavaripalli"
    ],
    "wof:name":"Mattavaripalli",
    "wof:placetype":"locality",
    "wof:population":39
},
  "geometry": {"coordinates":[77.961043,13.836738],"type":"Point"}
}