{
  "type": "Feature",
  "properties": {
    "iso:country":"IN",
    "ks:ks_name":"Uttar Sunseri",
    "ks:ks_pop":620,
    "ks:ks_type":"HABITATION",
    "name:eng_x_preferred":[
        "Uttar Sunseri"
    ],
    "wof:name":"Uttar Sunseri",
    "wof:placetype":"locality",
    "wof:population":620
},
  "geometry": {"coordinates":[92.48459,26.483669],"type":"Point"}
}