{
  "type": "Feature",
  "properties": {
    "iso:country":"IN",
    "ks:ks_name":"Bhalekerawadi",
    "ks:ks_pop":311,
    "ks:ks_type":"HABITATION",
    "name:eng_x_preferred":[
        "Bhalekerawadi"
    ],
    "wof:name":"Bhalekerawadi",
    "wof:placetype":"locality",
    "wof:population":311
},
  "geometry": {"coordinates":[73.936229,17.284615],"type":"Point"}
}