{
  "type": "Feature",
  "properties": {
    "gn:admin1_code":"11",
    "gn:admin2_code":"25.0",
    "gn:asciiname":"Bima",
    "gn:country_code":"IN",
    "gn:dem":2815,
    "gn:feature_class":"P",
    "gn:feature_code":"PPL",
    "gn:name":"B\u012bma",
    "gn:population":0,
    "gn:timezone":"Asia/Kolkata",
    "iso:country":"IN",
    "name:ara_x_preferred":[
        "\u0628\u064a\u0645\u0627"
    ],
    "name:ceb_x_preferred":[
        "Bima"
    ],
    "name:deu_x_preferred":[
        "Bima"
    ],
    "name:fra_x_preferred":[
        "Bima"
    ],
    "name:ind_x_preferred":[
        "Kota Bima"
    ],
    "name:ita_x_preferred":[
        "Bima"
    ],
    "name:jav_x_preferred":[
        "Kutha Bima"
    ],
    "name:mlg_x_preferred":[
        "Kota Bima"
    ],
    "name:msa_x_preferred":[
        "Kota Bima"
    ],
    "name:new_x_preferred":[
        "\u092c\u093f\u092e\u093e"
    ],
    "name:nld_x_preferred":[
        "Bima"
    ],
    "name:pol_x_preferred":[
        "Bima"
    ],
    "name:por_x_preferred":[
        "Bima"
    ],
    "name:spa_x_preferred":[
        "Bima"
    ],
    "name:sqi_x_preferred":[
        "Bima"
    ],
    "name:swe_x_preferred":[
        "Bima"
    ],
    "name:ukr_x_preferred":[
        "\u0411\u0456\u043c\u0430"
    ],
    "name:urd_x_preferred":[
        "\u0628\u06cc\u0645\u0627"
    ],
    "wof:name":"Bima",
    "wof:placetype":"locality"
},
  "geometry": {"coordinates":[76.72936,32.66749],"type":"Point"}
}