{
  "type": "Feature",
  "properties": {
    "gn:admin1_code":"11",
    "gn:admin2_code":"25.0",
    "gn:asciiname":"Bima",
    "gn:country_code":"IN",
    "gn:dem":2815,
    "gn:feature_class":"P",
    "gn:feature_code":"PPL",
    "gn:name":"B\u012bma",
    "gn:population":0,
    "gn:timezone":"Asia/Kolkata",
    "iso:country":"IN",
    "wof:name":"Bima",
    "wof:placetype":"locality"
},
  "geometry": {"coordinates":[76.72936,32.66749],"type":"Point"}
}