{
  "type": "Feature",
  "properties": {
    "gn:admin1_code":"13.0",
    "gn:admin2_code":"593.0",
    "gn:asciiname":"Kappur",
    "gn:country_code":"IN",
    "gn:dem":33,
    "gn:feature_class":"P",
    "gn:feature_code":"PPL",
    "gn:name":"Kapp\u016br",
    "gn:population":0,
    "gn:timezone":"Asia/Kolkata",
    "iso:country":"IN",
    "name:tam_x_preferred":[
        "\u0b95\u0baa\u0bcd\u0baa\u0bc2\u0bb0\u0bcd \u0b8a\u0bb0\u0bbe\u0b9f\u0bcd\u0b9a\u0bbf"
    ],
    "wof:name":"Kappur",
    "wof:placetype":"locality"
},
  "geometry": {"coordinates":[76.06341999999999,10.76613],"type":"Point"}
}