{
  "type": "Feature",
  "properties": {
    "gn:admin1_code":"11",
    "gn:admin2_code":"31.0",
    "gn:asciiname":"Roura",
    "gn:country_code":"IN",
    "gn:dem":1438,
    "gn:feature_class":"P",
    "gn:feature_code":"PPL",
    "gn:name":"Roura",
    "gn:population":0,
    "gn:timezone":"Asia/Kolkata",
    "iso:country":"IN",
    "wof:name":"Roura",
    "wof:placetype":"locality"
},
  "geometry": {"coordinates":[77.14570000000001,31.00377000000001],"type":"Point"}
}