{
  "type": "Feature",
  "properties": {
    "gn:admin1_code":"11",
    "gn:admin2_code":"31.0",
    "gn:asciiname":"Roura",
    "gn:country_code":"IN",
    "gn:dem":1438,
    "gn:feature_class":"P",
    "gn:feature_code":"PPL",
    "gn:name":"Roura",
    "gn:population":0,
    "gn:timezone":"Asia/Kolkata",
    "iso:country":"IN",
    "name:ara_x_preferred":[
        "\u0631\u0648\u0631\u0627"
    ],
    "name:cat_x_preferred":[
        "Roura"
    ],
    "name:ceb_x_preferred":[
        "Roura"
    ],
    "name:deu_x_preferred":[
        "Roura"
    ],
    "name:fra_x_preferred":[
        "Roura"
    ],
    "name:ind_x_preferred":[
        "Roura"
    ],
    "name:ita_x_preferred":[
        "Roura"
    ],
    "name:lat_x_preferred":[
        "Roura"
    ],
    "name:msa_x_preferred":[
        "Roura"
    ],
    "name:nld_x_preferred":[
        "Roura"
    ],
    "name:oci_x_preferred":[
        "Roura"
    ],
    "name:pms_x_preferred":[
        "Roura"
    ],
    "name:pol_x_preferred":[
        "Roura"
    ],
    "name:por_x_preferred":[
        "Roura"
    ],
    "name:rus_x_preferred":[
        "\u0420\u0443\u0440\u0430"
    ],
    "name:slk_x_preferred":[
        "Roura"
    ],
    "name:spa_x_preferred":[
        "Roura"
    ],
    "name:swe_x_preferred":[
        "Roura"
    ],
    "name:ukr_x_preferred":[
        "\u0420\u0443\u0440\u0430"
    ],
    "name:vie_x_preferred":[
        "Roura"
    ],
    "name:war_x_preferred":[
        "Roura"
    ],
    "wof:name":"Roura",
    "wof:placetype":"locality"
},
  "geometry": {"coordinates":[77.14570000000001,31.00377000000001],"type":"Point"}
}