{
  "type": "Feature",
  "properties": {
    "gn:admin1_code":"28.0",
    "gn:admin2_code":"344",
    "gn:asciiname":"Debra",
    "gn:country_code":"IN",
    "gn:dem":19,
    "gn:feature_class":"P",
    "gn:feature_code":"PPL",
    "gn:name":"Debra",
    "gn:population":0,
    "gn:timezone":"Asia/Kolkata",
    "iso:country":"IN",
    "ks:ks_name":"Debra",
    "ks:ks_pop":1974,
    "ks:ks_type":"VILLAGE",
    "ks:ks_uagg_main":0,
    "name:deu_x_preferred":[
        "Debra"
    ],
    "name:eng_x_preferred":[
        "Debra"
    ],
    "name:jpn_x_preferred":[
        "\u30c7\u30d6\u30e9"
    ],
    "name:swe_x_preferred":[
        "Debra"
    ],
    "wof:name":"Debra",
    "wof:placetype":"neighbourhood",
    "wof:population":1974
},
  "geometry": {"coordinates":[87.563289,22.399993],"type":"Point"}
}