{
  "type": "Feature",
  "properties": {
    "iso:country":"IN",
    "ks:ks_name":"Talkerikop",
    "ks:ks_type":"VILLAGE",
    "name:eng_x_preferred":[
        "Talkerikop"
    ],
    "wof:name":"Talkerikop",
    "wof:placetype":"locality"
},
  "geometry": {"coordinates":[75.147232,14.856793],"type":"Point"}
}