{
  "type": "Feature",
  "properties": {
    "gn:admin1_code":"35.0",
    "gn:admin2_code":"422",
    "gn:asciiname":"Indargarh",
    "gn:country_code":"IN",
    "gn:dem":188,
    "gn:feature_class":"P",
    "gn:feature_code":"PPL",
    "gn:name":"Indargarh",
    "gn:population":0,
    "gn:timezone":"Asia/Kolkata",
    "iso:country":"IN",
    "wof:name":"Indargarh",
    "wof:placetype":"locality"
},
  "geometry": {"coordinates":[78.56193,25.9109],"type":"Point"}
}