{
  "type": "Feature",
  "properties": {
    "iso:country":"IN",
    "ks:ks_name":"Madyanwadvi",
    "ks:ks_pop":168,
    "ks:ks_type":"HABITATION",
    "name:eng_x_preferred":[
        "Madyanwadvi"
    ],
    "wof:name":"Madyanwadvi",
    "wof:placetype":"locality",
    "wof:population":168
},
  "geometry": {"coordinates":[80.626019,20.542835],"type":"Point"}
}