{
  "type": "Feature",
  "properties": {
    "gn:admin1_code":"37",
    "gn:admin2_code":"408.0",
    "gn:asciiname":"Nandia",
    "gn:country_code":"IN",
    "gn:dem":320,
    "gn:feature_class":"P",
    "gn:feature_code":"PPL",
    "gn:name":"N\u0101ndia",
    "gn:population":0,
    "gn:timezone":"Asia/Kolkata",
    "iso:country":"IN",
    "ks:ks_name":"Nadia",
    "ks:ks_pop":688,
    "ks:ks_type":"HABITATION",
    "name:eng_x_preferred":[
        "Nadia"
    ],
    "name:eng_x_variant":[
        "Nandia"
    ],
    "wof:name":"Nadia",
    "wof:placetype":"locality",
    "wof:population":688
},
  "geometry": {"coordinates":[80.79841399999999,20.842181],"type":"Point"}
}