{
  "type": "Feature",
  "properties": {
    "iso:country":"IN",
    "ks:ks_name":"Basakpara",
    "ks:ks_pop":1100,
    "ks:ks_type":"HABITATION",
    "name:eng_x_preferred":[
        "Basakpara"
    ],
    "wof:name":"Basakpara",
    "wof:placetype":"locality",
    "wof:population":1100
},
  "geometry": {"coordinates":[88.285777,26.315167],"type":"Point"}
}