{
  "type": "Feature",
  "properties": {
    "iso:country":"IN",
    "ks:ks_name":"Indra Nagar",
    "ks:ks_pop":1942,
    "ks:ks_type":"HABITATION",
    "ks:ks_uagg_main":0,
    "name:eng_x_preferred":[
        "Indra Nagar"
    ],
    "wof:name":"Indra Nagar",
    "wof:placetype":"neighbourhood",
    "wof:population":1942
},
  "geometry": {"coordinates":[84.63328,26.757417],"type":"Point"}
}