{
  "type": "Feature",
  "properties": {
    "gn:admin1_code":"13.0",
    "gn:admin2_code":"589.0",
    "gn:asciiname":"Parapuram",
    "gn:country_code":"IN",
    "gn:dem":15,
    "gn:feature_class":"P",
    "gn:feature_code":"PPL",
    "gn:name":"Parapuram",
    "gn:population":0,
    "gn:timezone":"Asia/Kolkata",
    "iso:country":"IN",
    "ks:ks_name":"Parapram",
    "ks:ks_pop":1566,
    "ks:ks_type":"HABITATION",
    "name:eng_x_preferred":[
        "Parapram"
    ],
    "name:eng_x_variant":[
        "Parapuram"
    ],
    "wof:name":"Parapram",
    "wof:placetype":"locality",
    "wof:population":1566
},
  "geometry": {"coordinates":[75.47994199999999,11.811661],"type":"Point"}
}