{
  "type": "Feature",
  "properties": {
    "iso:country":"IN",
    "ks:ks_alt_nam":"West kollaimedu",
    "ks:ks_name":"West Kollaimedu",
    "ks:ks_pop":422,
    "ks:ks_type":"HABITATION",
    "name:eng_x_preferred":[
        "West Kollaimedu"
    ],
    "wof:name":"West Kollaimedu",
    "wof:placetype":"locality",
    "wof:population":422
},
  "geometry": {"coordinates":[79.02723,12.86417],"type":"Point"}
}