{
  "type": "Feature",
  "properties": {
    "iso:country":"IN",
    "ks:ks_name":"Nagoriya",
    "ks:ks_pop":95,
    "ks:ks_type":"VILLAGE",
    "name:eng_x_preferred":[
        "Nagoriya"
    ],
    "wof:name":"Nagoriya",
    "wof:placetype":"locality",
    "wof:population":95
},
  "geometry": {"coordinates":[79.596598,29.733435],"type":"Point"}
}