{
  "type": "Feature",
  "properties": {
    "gn:admin1_code":"24.0",
    "gn:admin2_code":"120",
    "gn:asciiname":"Ajaipal ka Dungri",
    "gn:country_code":"IN",
    "gn:dem":327,
    "gn:feature_class":"P",
    "gn:feature_code":"PPL",
    "gn:name":"Ajaip\u0101l ka D\u016bngri",
    "gn:population":0,
    "gn:timezone":"Asia/Kolkata",
    "iso:country":"IN",
    "wof:name":"Ajaipal ka Dungri",
    "wof:placetype":"locality"
},
  "geometry": {"coordinates":[75.64364999999999,25.72648],"type":"Point"}
}