{
  "type": "Feature",
  "properties": {
    "iso:country":"IN",
    "ks:ks_name":"Sohan Singh Ki Dhani",
    "ks:ks_pop":8,
    "ks:ks_type":"HABITATION",
    "name:eng_x_preferred":[
        "Sohan Singh Ki Dhani"
    ],
    "wof:name":"Sohan Singh Ki Dhani",
    "wof:placetype":"locality",
    "wof:population":8
},
  "geometry": {"coordinates":[74.311505,29.856889],"type":"Point"}
}