{
  "type": "Feature",
  "properties": {
    "iso:country":"IN",
    "ks:ks_name":"Cheruguda",
    "ks:ks_pop":147,
    "ks:ks_type":"HABITATION",
    "name:eng_x_preferred":[
        "Cheruguda"
    ],
    "wof:name":"Cheruguda",
    "wof:placetype":"locality",
    "wof:population":147
},
  "geometry": {"coordinates":[78.831299,19.323486],"type":"Point"}
}