{
  "type": "Feature",
  "properties": {
    "iso:country":"IN",
    "ks:ks_alt_nam":"CHOUKHALA UTTAR PARA",
    "ks:ks_name":"Choukhala Uttar Para",
    "ks:ks_pop":418,
    "ks:ks_type":"HABITATION",
    "name:eng_x_preferred":[
        "Choukhala Uttar Para"
    ],
    "wof:name":"Choukhala Uttar Para",
    "wof:placetype":"locality",
    "wof:population":418
},
  "geometry": {"coordinates":[91.28553700000001,23.744968],"type":"Point"}
}