{
  "type": "Feature",
  "properties": {
    "gn:admin1_code":"24.0",
    "gn:admin2_code":"118.0",
    "gn:asciiname":"Khar",
    "gn:country_code":"IN",
    "gn:dem":370,
    "gn:feature_class":"P",
    "gn:feature_code":"PPL",
    "gn:name":"Khar",
    "gn:population":0,
    "gn:timezone":"Asia/Kolkata",
    "iso:country":"IN",
    "name:ceb_x_preferred":[
        "Khar"
    ],
    "name:deu_x_preferred":[
        "Khar"
    ],
    "name:swe_x_preferred":[
        "Khar"
    ],
    "wof:name":"Khar",
    "wof:placetype":"neighbourhood"
},
  "geometry": {"coordinates":[74.16545000000001,26.16574],"type":"Point"}
}