{
  "type": "Feature",
  "properties": {
    "iso:country":"IN",
    "ks:ks_name":"Jawahri",
    "ks:ks_type":"VILLAGE",
    "ks:ks_uagg_main":0,
    "name:eng_x_preferred":[
        "Jawahri"
    ],
    "wof:name":"Jawahri",
    "wof:placetype":"neighbourhood"
},
  "geometry": {"coordinates":[76.99096400000001,29.027393],"type":"Point"}
}