{
  "type": "Feature",
  "properties": {
    "iso:country":"IN",
    "ks:ks_name":"Akewada",
    "ks:ks_pop":15,
    "ks:ks_type":"VILLAGE",
    "name:eng_x_preferred":[
        "Akewada"
    ],
    "wof:name":"Akewada",
    "wof:placetype":"locality",
    "wof:population":15
},
  "geometry": {"coordinates":[78.71442999999999,21.122645],"type":"Point"}
}