{
  "type": "Feature",
  "properties": {
    "iso:country":"IN",
    "ks:ks_name":"Bhagat Tola",
    "ks:ks_pop":241,
    "ks:ks_type":"HABITATION",
    "name:eng_x_preferred":[
        "Bhagat Tola"
    ],
    "wof:name":"Bhagat Tola",
    "wof:placetype":"locality",
    "wof:population":241
},
  "geometry": {"coordinates":[83.853934,26.881984],"type":"Point"}
}