{
  "type": "Feature",
  "properties": {
    "iso:country":"IN",
    "ks:ks_alt_nam":"MANDAL TOLA",
    "ks:ks_name":"Mandal Tola",
    "ks:ks_pop":281,
    "ks:ks_type":"HABITATION",
    "name:eng_x_preferred":[
        "Mandal Tola"
    ],
    "wof:name":"Mandal Tola",
    "wof:placetype":"locality",
    "wof:population":281
},
  "geometry": {"coordinates":[85.917481,26.277274],"type":"Point"}
}