{
  "type": "Feature",
  "properties": {
    "iso:country":"IN",
    "ks:ks_alt_nam":"Deopura",
    "ks:ks_name":"Deopur",
    "ks:ks_type":"VILLAGE",
    "name:eng_x_preferred":[
        "Deopur"
    ],
    "name:eng_x_variant":[
        "Deopura"
    ],
    "wof:name":"Deopur",
    "wof:placetype":"locality"
},
  "geometry": {"coordinates":[76.719122,22.827832],"type":"Point"}
}