{
  "type": "Feature",
  "properties": {
    "gn:admin1_code":"3.0",
    "gn:admin2_code":"301.0",
    "gn:asciiname":"Paglahat",
    "gn:country_code":"IN",
    "gn:dem":37,
    "gn:feature_class":"P",
    "gn:feature_code":"PPL",
    "gn:name":"Paglahat",
    "gn:population":0,
    "gn:timezone":"Asia/Kolkata",
    "iso:country":"IN",
    "wof:name":"Paglahat",
    "wof:placetype":"locality"
},
  "geometry": {"coordinates":[89.86395999999998,26.21046],"type":"Point"}
}