{
  "type": "Feature",
  "properties": {
    "iso:country":"IN",
    "ks:ks_name":"Thikankond",
    "ks:ks_pop":82,
    "ks:ks_type":"VILLAGE",
    "name:eng_x_preferred":[
        "Thikankond"
    ],
    "wof:name":"Thikankond",
    "wof:placetype":"locality",
    "wof:population":82
},
  "geometry": {"coordinates":[73.632778,16.690036],"type":"Point"}
}