{
  "type": "Feature",
  "properties": {
    "gn:admin1_code":"36.0",
    "gn:admin2_code":"166",
    "gn:asciiname":"Bijauli",
    "gn:country_code":"IN",
    "gn:dem":263,
    "gn:feature_class":"P",
    "gn:feature_code":"PPL",
    "gn:name":"Bijauli",
    "gn:population":0,
    "gn:timezone":"Asia/Kolkata",
    "iso:country":"IN",
    "name:und_x_variant":[
        "Bijoli"
    ],
    "wof:name":"Bijauli",
    "wof:placetype":"locality"
},
  "geometry": {"coordinates":[78.545,25.37314],"type":"Point"}
}