{
  "type": "Feature",
  "properties": {
    "iso:country":"IN",
    "ks:ks_name":"Anwar Khera",
    "ks:ks_pop":376,
    "ks:ks_type":"HABITATION",
    "name:eng_x_preferred":[
        "Anwar Khera"
    ],
    "wof:name":"Anwar Khera",
    "wof:placetype":"locality",
    "wof:population":376
},
  "geometry": {"coordinates":[80.292824,27.280377],"type":"Point"}
}