{
  "type": "Feature",
  "properties": {
    "iso:country":"IN",
    "ks:ks_name":"Thomas Nagar",
    "ks:ks_pop":892,
    "ks:ks_type":"HABITATION",
    "name:eng_x_preferred":[
        "Thomas Nagar"
    ],
    "wof:name":"Thomas Nagar",
    "wof:placetype":"locality",
    "wof:population":892
},
  "geometry": {"coordinates":[78.34464800000001,10.573842],"type":"Point"}
}