{
  "type": "Feature",
  "properties": {
    "iso:country":"IN",
    "ks:ks_name":"Sannasomandoddi",
    "ks:ks_pop":119,
    "ks:ks_type":"HABITATION",
    "name:eng_x_preferred":[
        "Sannasomandoddi"
    ],
    "wof:name":"Sannasomandoddi",
    "wof:placetype":"locality",
    "wof:population":119
},
  "geometry": {"coordinates":[76.589124,16.303615],"type":"Point"}
}