{
  "type": "Feature",
  "properties": {
    "iso:country":"IN",
    "ks:ks_name":"Kaharkola",
    "ks:ks_pop":1097,
    "ks:ks_type":"VILLAGE",
    "name:eng_x_preferred":[
        "Kaharkola"
    ],
    "wof:name":"Kaharkola",
    "wof:placetype":"locality",
    "wof:population":1097
},
  "geometry": {"coordinates":[79.86075099999999,27.562846],"type":"Point"}
}