{
  "type": "Feature",
  "properties": {
    "gn:admin1_code":"35",
    "gn:admin2_code":"455.0",
    "gn:asciiname":"Charkhera",
    "gn:country_code":"IN",
    "gn:dem":721,
    "gn:feature_class":"P",
    "gn:feature_code":"PPL",
    "gn:name":"Ch\u0101rkhera",
    "gn:population":0,
    "gn:timezone":"Asia/Kolkata",
    "iso:country":"IN",
    "ks:ks_name":"Charkheda",
    "ks:ks_pop":570,
    "ks:ks_type":"HABITATION",
    "name:eng_x_preferred":[
        "Charkheda"
    ],
    "name:eng_x_variant":[
        "Charkhera"
    ],
    "wof:name":"Charkheda",
    "wof:placetype":"locality",
    "wof:population":570
},
  "geometry": {"coordinates":[78.41636099999999,22.341558],"type":"Point"}
}