{
  "type": "Feature",
  "properties": {
    "iso:country":"IN",
    "ks:ks_name":"Melakdi",
    "ks:ks_pop":180,
    "ks:ks_type":"HABITATION",
    "name:eng_x_preferred":[
        "Melakdi"
    ],
    "wof:name":"Melakdi",
    "wof:placetype":"locality",
    "wof:population":180
},
  "geometry": {"coordinates":[72.108583,21.57575],"type":"Point"}
}