{
  "type": "Feature",
  "properties": {
    "iso:country":"IN",
    "ks:ks_name":"Khaas",
    "ks:ks_pop":384,
    "ks:ks_type":"HABITATION",
    "name:eng_x_preferred":[
        "Khaas"
    ],
    "wof:name":"Khaas",
    "wof:placetype":"locality",
    "wof:population":384
},
  "geometry": {"coordinates":[83.77774700000001,26.73271],"type":"Point"}
}