{
  "type": "Feature",
  "properties": {
    "gn:admin1_code":"09",
    "gn:admin2_code":"481.0",
    "gn:asciiname":"Ranghola",
    "gn:country_code":"IN",
    "gn:dem":57,
    "gn:feature_class":"P",
    "gn:feature_code":"PPL",
    "gn:name":"Ranghola",
    "gn:population":0,
    "gn:timezone":"Asia/Kolkata",
    "iso:country":"IN",
    "wof:name":"Ranghola",
    "wof:placetype":"locality"
},
  "geometry": {"coordinates":[71.67586,21.76386],"type":"Point"}
}