{
  "type": "Feature",
  "properties": {
    "gn:admin1_code":"39.0",
    "gn:admin2_code":"67.0",
    "gn:asciiname":"Ludhpura",
    "gn:country_code":"IN",
    "gn:dem":228,
    "gn:feature_class":"P",
    "gn:feature_code":"PPL",
    "gn:name":"Ludhpura",
    "gn:population":0,
    "gn:timezone":"Asia/Kolkata",
    "iso:country":"IN",
    "ks:ks_name":"Ludhpura",
    "ks:ks_type":"VILLAGE",
    "name:eng_x_preferred":[
        "Ludhpura"
    ],
    "wof:name":"Ludhpura",
    "wof:placetype":"locality"
},
  "geometry": {"coordinates":[79.10112700000001,29.1722],"type":"Point"}
}