{
  "type": "Feature",
  "properties": {
    "iso:country":"IN",
    "ks:ks_name":"Naraharipur",
    "ks:ks_pop":205,
    "ks:ks_type":"VILLAGE",
    "name:eng_x_preferred":[
        "Naraharipur"
    ],
    "wof:name":"Naraharipur",
    "wof:placetype":"locality",
    "wof:population":205
},
  "geometry": {"coordinates":[84.22139,18.835421],"type":"Point"}
}