{
  "type": "Feature",
  "properties": {
    "iso:country":"IN",
    "ks:ks_name":"Shukulauporwa",
    "ks:ks_type":"VILLAGE",
    "name:eng_x_preferred":[
        "Shukulauporwa"
    ],
    "wof:name":"Shukulauporwa",
    "wof:placetype":"locality"
},
  "geometry": {"coordinates":[81.362506,27.385883],"type":"Point"}
}