{
  "type": "Feature",
  "properties": {
    "iso:country":"IN",
    "ks:ks_name":"Sunhera",
    "ks:ks_type":"VILLAGE",
    "name:eng_x_preferred":[
        "Sunhera"
    ],
    "wof:name":"Sunhera",
    "wof:placetype":"locality"
},
  "geometry": {"coordinates":[78.411727,23.598289],"type":"Point"}
}