{
  "type": "Feature",
  "properties": {
    "gn:admin1_code":"36",
    "gn:admin2_code":"194.0",
    "gn:asciiname":"Durgapatti",
    "gn:country_code":"IN",
    "gn:dem":88,
    "gn:feature_class":"P",
    "gn:feature_code":"PPL",
    "gn:name":"Durg\u0101patti",
    "gn:population":0,
    "gn:timezone":"Asia/Kolkata",
    "iso:country":"IN",
    "ks:ks_name":"Durgapatti",
    "ks:ks_pop":530,
    "ks:ks_type":"VILLAGE",
    "name:eng_x_preferred":[
        "Durgapatti"
    ],
    "wof:name":"Durgapatti",
    "wof:placetype":"locality",
    "wof:population":530
},
  "geometry": {"coordinates":[82.543441,25.88295],"type":"Point"}
}