{
  "type": "Feature",
  "properties": {
    "iso:country":"IN",
    "ks:ks_name":"Kerehadi B Colony",
    "ks:ks_pop":108,
    "ks:ks_type":"HABITATION",
    "name:eng_x_preferred":[
        "Kerehadi B Colony"
    ],
    "wof:name":"Kerehadi B Colony",
    "wof:placetype":"locality",
    "wof:population":108
},
  "geometry": {"coordinates":[76.224108,11.936316],"type":"Point"}
}