{
  "type": "Feature",
  "properties": {
    "iso:country":"IN",
    "ks:ks_alt_nam":"Rat\u016bpura",
    "ks:ks_name":"Ratupura",
    "ks:ks_type":"VILLAGE",
    "name:eng_x_preferred":[
        "Ratupura"
    ],
    "name:eng_x_variant":[
        "Rat\u016bpura"
    ],
    "wof:name":"Ratupura",
    "wof:placetype":"locality"
},
  "geometry": {"coordinates":[78.84087700000001,29.01498],"type":"Point"}
}