{
  "type": "Feature",
  "properties": {
    "gn:admin1_code":"36.0",
    "gn:admin2_code":"172.0",
    "gn:asciiname":"Bushahra",
    "gn:country_code":"IN",
    "gn:dem":113,
    "gn:feature_class":"P",
    "gn:feature_code":"PPL",
    "gn:name":"Bushahra",
    "gn:population":0,
    "gn:timezone":"Asia/Kolkata",
    "iso:country":"IN",
    "wof:name":"Bushahra",
    "wof:placetype":"locality"
},
  "geometry": {"coordinates":[81.05138000000002,25.86817000000001],"type":"Point"}
}