{
  "type": "Feature",
  "properties": {
    "iso:country":"IN",
    "ks:ks_name":"Manani",
    "ks:ks_pop":258,
    "ks:ks_type":"HABITATION",
    "name:eng_x_preferred":[
        "Manani"
    ],
    "wof:name":"Manani",
    "wof:placetype":"locality",
    "wof:population":258
},
  "geometry": {"coordinates":[74.55235500000001,21.817076],"type":"Point"}
}