{
  "type": "Feature",
  "properties": {
    "iso:country":"IN",
    "ks:ks_name":"Patratoli",
    "ks:ks_pop":276,
    "ks:ks_type":"HABITATION",
    "name:eng_x_preferred":[
        "Patratoli"
    ],
    "wof:name":"Patratoli",
    "wof:placetype":"locality",
    "wof:population":276
},
  "geometry": {"coordinates":[84.68675,23.138796],"type":"Point"}
}