{
  "type": "Feature",
  "properties": {
    "iso:country":"IN",
    "ks:ks_name":"Moodu Mangatha Thanda",
    "ks:ks_pop":55,
    "ks:ks_type":"HABITATION",
    "name:eng_x_preferred":[
        "Moodu Mangatha Thanda"
    ],
    "wof:name":"Moodu Mangatha Thanda",
    "wof:placetype":"locality",
    "wof:population":55
},
  "geometry": {"coordinates":[79.686531,17.730942],"type":"Point"}
}