{
  "type": "Feature",
  "properties": {
    "iso:country":"IN",
    "ks:ks_name":"Ronsuyan",
    "ks:ks_pop":430,
    "ks:ks_type":"HABITATION",
    "name:eng_x_preferred":[
        "Ronsuyan"
    ],
    "wof:name":"Ronsuyan",
    "wof:placetype":"locality",
    "wof:population":430
},
  "geometry": {"coordinates":[93.94367699999999,26.031851],"type":"Point"}
}