{
  "type": "Feature",
  "properties": {
    "gn:admin1_code":"39.0",
    "gn:admin2_code":"63.0",
    "gn:asciiname":"Phanyari",
    "gn:country_code":"IN",
    "gn:dem":1336,
    "gn:feature_class":"P",
    "gn:feature_code":"PPL",
    "gn:name":"Phany\u0101ri",
    "gn:population":0,
    "gn:timezone":"Asia/Kolkata",
    "iso:country":"IN",
    "wof:name":"Phanyari",
    "wof:placetype":"locality"
},
  "geometry": {"coordinates":[79.80960999999998,29.85264],"type":"Point"}
}