{
  "type": "Feature",
  "properties": {
    "iso:country":"IN",
    "ks:ks_name":"Talawada",
    "ks:ks_pop":2214,
    "ks:ks_type":"VILLAGE",
    "name:eng_x_preferred":[
        "Talawada"
    ],
    "wof:name":"Talawada",
    "wof:placetype":"locality",
    "wof:population":2214
},
  "geometry": {"coordinates":[74.756102,23.22616],"type":"Point"}
}