{
  "type": "Feature",
  "properties": {
    "gn:admin1_code":"19",
    "gn:admin2_code":"563.0",
    "gn:asciiname":"Harigar",
    "gn:country_code":"IN",
    "gn:dem":524,
    "gn:feature_class":"P",
    "gn:feature_code":"PPL",
    "gn:name":"Harig\u0101r",
    "gn:population":0,
    "gn:timezone":"Asia/Kolkata",
    "iso:country":"IN",
    "ks:ks_alt_nam":"Harig\u0101r",
    "ks:ks_name":"Harigar",
    "ks:ks_pop":48,
    "ks:ks_type":"VILLAGE",
    "name:eng_x_preferred":[
        "Harigar"
    ],
    "name:eng_x_variant":[
        "Harig\u0101r"
    ],
    "wof:name":"Harigar",
    "wof:placetype":"locality",
    "wof:population":48
},
  "geometry": {"coordinates":[74.761825,14.429834],"type":"Point"}
}