{
  "type": "Feature",
  "properties": {
    "iso:country":"IN",
    "qs:name":"Kadakampally",
    "qs:name_adm0":"India",
    "qs:name_adm1":"Kerala",
    "qs:photos":130,
    "qs:photos_1k":26,
    "qs:photos_9k":1,
    "qs:photos_9r":3,
    "qs:photos_all":130,
    "qs:photos_sr":3,
    "qs:placetype":"Town",
    "qs:pop_sr":"0",
    "wof:name":"Kadakampally",
    "wof:placetype":"neighbourhood"
},
  "geometry": {"coordinates":[76.885049,8.516132],"type":"Point"}
}