{
  "type": "Feature",
  "properties": {
    "gn:admin1_code":"23.0",
    "gn:admin2_code":"41.0",
    "gn:asciiname":"Mor Karima",
    "gn:country_code":"IN",
    "gn:dem":242,
    "gn:feature_class":"P",
    "gn:feature_code":"PPL",
    "gn:name":"Mor Kar\u012bma",
    "gn:population":0,
    "gn:timezone":"Asia/Kolkata",
    "iso:country":"IN",
    "name:und_x_variant":[
        "Mor Kar\u012bma"
    ],
    "wof:name":"Mor Karima",
    "wof:placetype":"locality"
},
  "geometry": {"coordinates":[75.60836,30.83574],"type":"Point"}
}