{
  "type": "Feature",
  "properties": {
    "iso:country":"IN",
    "ks:ks_name":"Gorti Kanda",
    "ks:ks_pop":579,
    "ks:ks_type":"HABITATION",
    "name:eng_x_preferred":[
        "Gorti Kanda"
    ],
    "wof:name":"Gorti Kanda",
    "wof:placetype":"locality",
    "wof:population":579
},
  "geometry": {"coordinates":[78.592271,30.159377],"type":"Point"}
}