{
  "type": "Feature",
  "properties": {
    "iso:country":"IN",
    "ks:ks_name":"Dumarkola",
    "ks:ks_pop":363,
    "ks:ks_type":"VILLAGE",
    "name:eng_x_preferred":[
        "Dumarkola"
    ],
    "wof:name":"Dumarkola",
    "wof:placetype":"locality",
    "wof:population":363
},
  "geometry": {"coordinates":[86.614012,24.654367],"type":"Point"}
}