{
  "type": "Feature",
  "properties": {
    "gn:admin1_code":"19.0",
    "gn:admin2_code":"584.0",
    "gn:asciiname":"Tirmalapur",
    "gn:country_code":"IN",
    "gn:dem":871,
    "gn:feature_class":"P",
    "gn:feature_code":"PPL",
    "gn:name":"Tirmalapur",
    "gn:population":0,
    "gn:timezone":"Asia/Kolkata",
    "iso:country":"IN",
    "wof:name":"Tirmalapur",
    "wof:placetype":"locality"
},
  "geometry": {"coordinates":[77.29380999999999,13.02057],"type":"Point"}
}