{
  "type": "Feature",
  "properties": {
    "gn:admin1_code":"10.0",
    "gn:admin2_code":"85.0",
    "gn:asciiname":"Bidawas",
    "gn:country_code":"IN",
    "gn:dem":268,
    "gn:feature_class":"P",
    "gn:feature_code":"PPL",
    "gn:name":"Bid\u0101w\u0101s",
    "gn:population":0,
    "gn:timezone":"Asia/Kolkata",
    "iso:country":"IN",
    "wof:name":"Bidawas",
    "wof:placetype":"locality"
},
  "geometry": {"coordinates":[76.63175,28.03504],"type":"Point"}
}