{
  "type": "Feature",
  "properties": {
    "iso:country":"IN",
    "ks:ks_name":"Ali Chak",
    "ks:ks_pop":2006,
    "ks:ks_type":"VILLAGE",
    "name:eng_x_preferred":[
        "Ali Chak"
    ],
    "wof:name":"Ali Chak",
    "wof:placetype":"locality",
    "wof:population":2006
},
  "geometry": {"coordinates":[87.84238000000001,21.909752],"type":"Point"}
}