{
  "type": "Feature",
  "properties": {
    "gn:admin1_code":"11",
    "gn:admin2_code":"24.0",
    "gn:asciiname":"Sihoti",
    "gn:country_code":"IN",
    "gn:dem":532,
    "gn:feature_class":"P",
    "gn:feature_code":"PPL",
    "gn:name":"Sihoti",
    "gn:population":0,
    "gn:timezone":"Asia/Kolkata",
    "iso:country":"IN",
    "wof:name":"Sihoti",
    "wof:placetype":"locality"
},
  "geometry": {"coordinates":[76.3402,31.79961],"type":"Point"}
}