{
  "type": "Feature",
  "properties": {
    "iso:country":"IN",
    "ks:ks_name":"Ranjanewadi",
    "ks:ks_pop":127,
    "ks:ks_type":"HABITATION",
    "name:eng_x_preferred":[
        "Ranjanewadi"
    ],
    "wof:name":"Ranjanewadi",
    "wof:placetype":"locality",
    "wof:population":127
},
  "geometry": {"coordinates":[73.49333300000001,17.264444],"type":"Point"}
}