{
  "type": "Feature",
  "properties": {
    "iso:country":"IN",
    "ks:ks_name":"Thakurwadi",
    "ks:ks_pop":243,
    "ks:ks_type":"HABITATION",
    "name:eng_x_preferred":[
        "Thakurwadi"
    ],
    "wof:name":"Thakurwadi",
    "wof:placetype":"locality",
    "wof:population":243
},
  "geometry": {"coordinates":[73.277181,19.122468],"type":"Point"}
}