{
  "type": "Feature",
  "properties": {
    "iso:country":"IN",
    "ks:ks_name":"Kanchanahalli",
    "ks:ks_pop":1922,
    "ks:ks_type":"VILLAGE",
    "name:eng_x_preferred":[
        "Kanchanahalli"
    ],
    "wof:name":"Kanchanahalli",
    "wof:placetype":"locality",
    "wof:population":1922
},
  "geometry": {"coordinates":[74.831558,15.115993],"type":"Point"}
}