{
  "type": "Feature",
  "properties": {
    "gn:admin1_code":"39.0",
    "gn:admin2_code":"64.0",
    "gn:asciiname":"Kalaun",
    "gn:country_code":"IN",
    "gn:dem":1547,
    "gn:feature_class":"P",
    "gn:feature_code":"PPL",
    "gn:name":"Kalaun",
    "gn:population":0,
    "gn:timezone":"Asia/Kolkata",
    "iso:country":"IN",
    "ks:ks_name":"Kalaun",
    "ks:ks_type":"VILLAGE",
    "name:eng_x_preferred":[
        "Kalaun"
    ],
    "wof:name":"Kalaun",
    "wof:placetype":"locality"
},
  "geometry": {"coordinates":[79.774782,29.666907],"type":"Point"}
}