{
  "type": "Feature",
  "properties": {
    "iso:country":"IN",
    "ks:ks_name":"Khambhla",
    "ks:ks_pop":359,
    "ks:ks_type":"VILLAGE",
    "name:eng_x_preferred":[
        "Khambhla"
    ],
    "wof:name":"Khambhla",
    "wof:placetype":"locality",
    "wof:population":359
},
  "geometry": {"coordinates":[73.234363,21.082403],"type":"Point"}
}