{
  "type": "Feature",
  "properties": {
    "iso:country":"IN",
    "ks:ks_name":"Katghara Patti",
    "ks:ks_pop":3919,
    "ks:ks_type":"VILLAGE",
    "name:eng_x_preferred":[
        "Katghara Patti"
    ],
    "wof:name":"Katghara Patti",
    "wof:placetype":"locality",
    "wof:population":3919
},
  "geometry": {"coordinates":[82.448432,26.224418],"type":"Point"}
}