{
  "type": "Feature",
  "properties": {
    "iso:country":"IN",
    "ks:ks_name":"Soonthi",
    "ks:ks_pop":116,
    "ks:ks_type":"HABITATION",
    "name:eng_x_preferred":[
        "Soonthi"
    ],
    "wof:name":"Soonthi",
    "wof:placetype":"locality",
    "wof:population":116
},
  "geometry": {"coordinates":[75.372777,25.197175],"type":"Point"}
}