{
  "type": "Feature",
  "properties": {
    "iso:country":"IN",
    "ks:ks_name":"Laxmanapur",
    "ks:ks_pop":475,
    "ks:ks_type":"VILLAGE",
    "name:eng_x_preferred":[
        "Laxmanapur"
    ],
    "wof:name":"Laxmanapur",
    "wof:placetype":"locality",
    "wof:population":475
},
  "geometry": {"coordinates":[86.28869899999999,20.892467],"type":"Point"}
}