{
  "type": "Feature",
  "properties": {
    "gn:admin1_code":"20",
    "gn:admin2_code":"263.0",
    "gn:asciiname":"Sakhalu",
    "gn:country_code":"IN",
    "gn:dem":1745,
    "gn:feature_class":"P",
    "gn:feature_code":"PPL",
    "gn:name":"Sakh\u0101lu",
    "gn:population":0,
    "gn:timezone":"Asia/Kolkata",
    "iso:country":"IN",
    "wof:name":"Sakhalu",
    "wof:placetype":"locality"
},
  "geometry": {"coordinates":[94.51257,25.97512],"type":"Point"}
}