{
  "type": "Feature",
  "properties": {
    "gn:admin1_code":"36",
    "gn:admin2_code":"179.0",
    "gn:asciiname":"Manapur",
    "gn:country_code":"IN",
    "gn:dem":92,
    "gn:feature_class":"P",
    "gn:feature_code":"PPL",
    "gn:name":"M\u0101napur",
    "gn:population":0,
    "gn:timezone":"Asia/Kolkata",
    "iso:country":"IN",
    "ks:ks_alt_nam":"M\u0101napur",
    "ks:ks_name":"Manapur",
    "ks:ks_type":"VILLAGE",
    "ks:ks_uagg_main":0,
    "name:eng_x_preferred":[
        "Manapur"
    ],
    "name:eng_x_variant":[
        "M\u0101napur"
    ],
    "wof:name":"Manapur",
    "wof:placetype":"neighbourhood"
},
  "geometry": {"coordinates":[82.296404,26.076619],"type":"Point"}
}