{
  "type": "Feature",
  "properties": {
    "iso:country":"IN",
    "ks:ks_name":"Taktauwa",
    "ks:ks_pop":397,
    "ks:ks_type":"VILLAGE",
    "name:eng_x_preferred":[
        "Taktauwa"
    ],
    "wof:name":"Taktauwa",
    "wof:placetype":"locality",
    "wof:population":397
},
  "geometry": {"coordinates":[80.649877,22.425863],"type":"Point"}
}