{
  "type": "Feature",
  "properties": {
    "iso:country":"IN",
    "ks:ks_name":"Nemmeli",
    "ks:ks_pop":3055,
    "ks:ks_type":"VILLAGE",
    "ks:ks_uagg_main":0,
    "name:ast_x_preferred":[
        "Nemmeli"
    ],
    "name:eng_x_preferred":[
        "Nemmeli"
    ],
    "name:nld_x_preferred":[
        "Nemmeli"
    ],
    "qs:name":"Nemmeli",
    "qs:name_adm0":"India",
    "qs:name_adm1":"Tamil Nadu",
    "qs:photos":97,
    "qs:photos_1k":20,
    "qs:photos_9k":1,
    "qs:photos_9r":3,
    "qs:photos_all":97,
    "qs:photos_sr":3,
    "qs:placetype":"Town",
    "qs:pop_sr":"0",
    "wof:name":"Nemmeli",
    "wof:placetype":"neighbourhood",
    "wof:population":3055
},
  "geometry": {"coordinates":[80.21962000000001,12.714483],"type":"Point"}
}