{
  "type": "Feature",
  "properties": {
    "gn:admin1_code":"16",
    "gn:admin2_code":"500.0",
    "gn:asciiname":"Nimgaon",
    "gn:country_code":"IN",
    "gn:dem":258,
    "gn:feature_class":"P",
    "gn:feature_code":"PPL",
    "gn:name":"Nimgaon",
    "gn:population":0,
    "gn:timezone":"Asia/Kolkata",
    "iso:country":"IN",
    "wof:name":"Nimgaon",
    "wof:placetype":"locality"
},
  "geometry": {"coordinates":[76.48002,20.86503],"type":"Point"}
}