{
  "type": "Feature",
  "properties": {
    "iso:country":"IN",
    "ks:ks_name":"Amali Phalan",
    "ks:ks_pop":372,
    "ks:ks_type":"HABITATION",
    "name:eng_x_preferred":[
        "Amali Phalan"
    ],
    "wof:name":"Amali Phalan",
    "wof:placetype":"locality",
    "wof:population":372
},
  "geometry": {"coordinates":[74.451386,23.890683],"type":"Point"}
}