{
  "type": "Feature",
  "properties": {
    "iso:country":"IN",
    "ks:ks_name":"Loona Kalan",
    "ks:ks_pop":1526,
    "ks:ks_type":"VILLAGE",
    "name:eng_x_preferred":[
        "Loona Kalan"
    ],
    "wof:name":"Loona Kalan",
    "wof:placetype":"locality",
    "wof:population":1526
},
  "geometry": {"coordinates":[71.98476700000001,25.455244],"type":"Point"}
}