{
  "type": "Feature",
  "properties": {
    "gn:admin1_code":"19.0",
    "gn:admin2_code":"584.0",
    "gn:asciiname":"Gangaiyandoddi",
    "gn:country_code":"IN",
    "gn:dem":651,
    "gn:feature_class":"P",
    "gn:feature_code":"PPL",
    "gn:name":"Gangaiyandoddi",
    "gn:population":0,
    "gn:timezone":"Asia/Kolkata",
    "iso:country":"IN",
    "wof:name":"Gangaiyandoddi",
    "wof:placetype":"locality"
},
  "geometry": {"coordinates":[77.39657,12.48943],"type":"Point"}
}