{
  "type": "Feature",
  "properties": {
    "iso:country":"IN",
    "ks:ks_name":"Manjhipara",
    "ks:ks_pop":443,
    "ks:ks_type":"HABITATION",
    "name:eng_x_preferred":[
        "Manjhipara"
    ],
    "wof:name":"Manjhipara",
    "wof:placetype":"locality",
    "wof:population":443
},
  "geometry": {"coordinates":[81.83756,19.484975],"type":"Point"}
}