{
  "type": "Feature",
  "properties": {
    "iso:country":"IN",
    "ks:ks_name":"Alavandarmedu",
    "ks:ks_pop":357,
    "ks:ks_type":"VILLAGE",
    "name:eng_x_preferred":[
        "Alavandarmedu"
    ],
    "wof:name":"Alavandarmedu",
    "wof:placetype":"locality",
    "wof:population":357
},
  "geometry": {"coordinates":[79.63526299999999,12.82293],"type":"Point"}
}