{
  "type": "Feature",
  "properties": {
    "iso:country":"IN",
    "ks:ks_name":"Debidia",
    "ks:ks_pop":1156,
    "ks:ks_type":"VILLAGE",
    "name:eng_x_preferred":[
        "Debidia"
    ],
    "wof:name":"Debidia",
    "wof:placetype":"locality",
    "wof:population":1156
},
  "geometry": {"coordinates":[86.84616200000001,23.099972],"type":"Point"}
}