{
  "type": "Feature",
  "properties": {
    "gn:admin1_code":"40",
    "gn:admin2_code":"534.0",
    "gn:asciiname":"Chintalur",
    "gn:country_code":"IN",
    "gn:dem":226,
    "gn:feature_class":"P",
    "gn:feature_code":"PPL",
    "gn:name":"Chintal\u016br",
    "gn:population":0,
    "gn:timezone":"Asia/Kolkata",
    "iso:country":"IN",
    "wof:name":"Chintalur",
    "wof:placetype":"locality"
},
  "geometry": {"coordinates":[78.83255,18.97911],"type":"Point"}
}