{
  "type": "Feature",
  "properties": {
    "iso:country":"IN",
    "ks:ks_name":"Mohammadpur Urf Pehmi Mohammad",
    "ks:ks_pop":1147,
    "ks:ks_type":"VILLAGE",
    "name:eng_x_preferred":[
        "Mohammadpur Urf Pehmi Mohammad"
    ],
    "wof:name":"Mohammadpur Urf Pehmi Mohammad",
    "wof:placetype":"locality",
    "wof:population":1147
},
  "geometry": {"coordinates":[85.431477,25.769784],"type":"Point"}
}