{
  "type": "Feature",
  "properties": {
    "gn:admin1_code":"36.0",
    "gn:admin2_code":"158.0",
    "gn:asciiname":"Chilaula Bhangria",
    "gn:country_code":"IN",
    "gn:dem":115,
    "gn:feature_class":"P",
    "gn:feature_code":"PPL",
    "gn:name":"Chilaul\u0101 Bhangria",
    "gn:population":0,
    "gn:timezone":"Asia/Kolkata",
    "iso:country":"IN",
    "wof:name":"Chilaula Bhangria",
    "wof:placetype":"locality"
},
  "geometry": {"coordinates":[81.13665999999998,26.18742],"type":"Point"}
}