{
  "type": "Feature",
  "properties": {
    "iso:country":"IN",
    "ks:ks_name":"Tamajor",
    "ks:ks_pop":1000,
    "ks:ks_type":"VILLAGE",
    "name:eng_x_preferred":[
        "Tamajor"
    ],
    "wof:name":"Tamajor",
    "wof:placetype":"locality",
    "wof:population":1000
},
  "geometry": {"coordinates":[86.85977699999999,24.009846],"type":"Point"}
}