{
  "type": "Feature",
  "properties": {
    "gn:admin1_code":"9.0",
    "gn:admin2_code":"480",
    "gn:asciiname":"Dedan",
    "gn:country_code":"IN",
    "gn:dem":115,
    "gn:feature_class":"P",
    "gn:feature_code":"PPL",
    "gn:name":"Ded\u0101n",
    "gn:population":0,
    "gn:timezone":"Asia/Kolkata",
    "iso:country":"IN",
    "name:cat_x_preferred":[
        "Dedan"
    ],
    "name:ell_x_preferred":[
        "\u039d\u03c4\u03b5\u03bd\u03c4\u03ac\u03bd"
    ],
    "name:spa_x_preferred":[
        "Dedan"
    ],
    "wof:name":"Dedan",
    "wof:placetype":"locality"
},
  "geometry": {"coordinates":[71.28049,21.05033],"type":"Point"}
}