{
  "type": "Feature",
  "properties": {
    "iso:country":"IN",
    "ks:ks_name":"Hatgechhe Dakshin",
    "ks:ks_pop":1652,
    "ks:ks_type":"VILLAGE",
    "name:eng_x_preferred":[
        "Hatgechhe Dakshin"
    ],
    "wof:name":"Hatgechhe Dakshin",
    "wof:placetype":"locality",
    "wof:population":1652
},
  "geometry": {"coordinates":[87.88747100000001,22.210792],"type":"Point"}
}