{
  "type": "Feature",
  "properties": {
    "iso:country":"IN",
    "ks:ks_name":"Dhakual Gaon",
    "ks:ks_pop":520,
    "ks:ks_type":"VILLAGE",
    "name:eng_x_preferred":[
        "Dhakual Gaon"
    ],
    "wof:name":"Dhakual Gaon",
    "wof:placetype":"locality",
    "wof:population":520
},
  "geometry": {"coordinates":[95.377511,27.54807],"type":"Point"}
}