{
  "type": "Feature",
  "properties": {
    "iso:country":"IN",
    "ks:ks_name":"Nau Ka Purwa",
    "ks:ks_pop":125,
    "ks:ks_type":"HABITATION",
    "ks:ks_uagg_main":0,
    "name:eng_x_preferred":[
        "Nau Ka Purwa"
    ],
    "wof:name":"Nau Ka Purwa",
    "wof:placetype":"neighbourhood",
    "wof:population":125
},
  "geometry": {"coordinates":[82.108283,26.70696],"type":"Point"}
}