{
  "type": "Feature",
  "properties": {
    "iso:country":"IN",
    "ks:ks_alt_nam":"KHARTOLI",
    "ks:ks_name":"Khartoli",
    "ks:ks_pop":111,
    "ks:ks_type":"HABITATION",
    "name:eng_x_preferred":[
        "Khartoli"
    ],
    "wof:name":"Khartoli",
    "wof:placetype":"locality",
    "wof:population":111
},
  "geometry": {"coordinates":[83.733428,23.213045],"type":"Point"}
}