{
  "type": "Feature",
  "properties": {
    "iso:country":"IN",
    "ks:ks_name":"Dewda",
    "ks:ks_pop":76,
    "ks:ks_type":"VILLAGE",
    "name:eng_x_preferred":[
        "Dewda"
    ],
    "wof:name":"Dewda",
    "wof:placetype":"locality",
    "wof:population":76
},
  "geometry": {"coordinates":[80.138628,19.982272],"type":"Point"}
}