{
  "type": "Feature",
  "properties": {
    "gn:admin1_code":"28.0",
    "gn:admin2_code":"344.0",
    "gn:asciiname":"Chakadoba",
    "gn:country_code":"IN",
    "gn:dem":239,
    "gn:feature_class":"P",
    "gn:feature_code":"PPL",
    "gn:name":"Chakadoba",
    "gn:population":0,
    "gn:timezone":"Asia/Kolkata",
    "iso:country":"IN",
    "wof:name":"Chakadoba",
    "wof:placetype":"locality"
},
  "geometry": {"coordinates":[86.65859,22.76681],"type":"Point"}
}