{
  "type": "Feature",
  "properties": {
    "iso:country":"IN",
    "ks:ks_alt_nam":"Korakh\u0101p",
    "ks:ks_name":"Korakhap",
    "ks:ks_type":"VILLAGE",
    "name:eng_x_preferred":[
        "Korakhap"
    ],
    "name:eng_x_variant":[
        "Korakh\u0101p"
    ],
    "wof:name":"Korakhap",
    "wof:placetype":"locality"
},
  "geometry": {"coordinates":[84.434834,26.241772],"type":"Point"}
}