{
  "type": "Feature",
  "properties": {
    "iso:country":"IN",
    "ks:ks_name":"Monabari T.E.P.P.No.1",
    "ks:ks_pop":1300,
    "ks:ks_type":"VILLAGE",
    "ks:ks_uagg_main":0,
    "name:eng_x_preferred":[
        "Monabari T.E.P.P.No.1"
    ],
    "wof:name":"Monabari T.E.P.P.No.1",
    "wof:placetype":"neighbourhood",
    "wof:population":1300
},
  "geometry": {"coordinates":[93.27117,26.770015],"type":"Point"}
}