{
  "type": "Feature",
  "properties": {
    "gn:admin1_code":"2.0",
    "gn:admin2_code":"543.0",
    "gn:asciiname":"Kotta Ajjada",
    "gn:country_code":"IN",
    "gn:dem":85,
    "gn:feature_class":"P",
    "gn:feature_code":"PPL",
    "gn:name":"Kotta Ajj\u0101da",
    "gn:population":0,
    "gn:timezone":"Asia/Kolkata",
    "iso:country":"IN",
    "wof:name":"Kotta Ajjada",
    "wof:placetype":"locality"
},
  "geometry": {"coordinates":[83.48879000000002,18.67396],"type":"Point"}
}