{
  "type": "Feature",
  "properties": {
    "iso:country":"IN",
    "ks:ks_name":"Kallannirappu",
    "ks:ks_pop":897,
    "ks:ks_type":"HABITATION",
    "ks:ks_uagg_main":0,
    "name:eng_x_preferred":[
        "Kallannirappu"
    ],
    "wof:name":"Kallannirappu",
    "wof:placetype":"neighbourhood",
    "wof:population":897
},
  "geometry": {"coordinates":[76.34153999999999,10.478012],"type":"Point"}
}