{
  "type": "Feature",
  "properties": {
    "gn:admin1_code":"34.0",
    "gn:admin2_code":"221.0",
    "gn:asciiname":"Nagar Basti",
    "gn:country_code":"IN",
    "gn:dem":54,
    "gn:feature_class":"P",
    "gn:feature_code":"PPL",
    "gn:name":"Nagar Basti",
    "gn:population":0,
    "gn:timezone":"Asia/Kolkata",
    "iso:country":"IN",
    "ks:ks_name":"Nagar Basti",
    "ks:ks_pop":1910,
    "ks:ks_type":"VILLAGE",
    "name:eng_x_preferred":[
        "Nagar Basti"
    ],
    "wof:name":"Nagar Basti",
    "wof:placetype":"locality",
    "wof:population":1910
},
  "geometry": {"coordinates":[85.82181,25.869003],"type":"Point"}
}