{
  "type": "Feature",
  "properties": {
    "gn:admin1_code":"36",
    "gn:admin2_code":"143.0",
    "gn:asciiname":"Lachhampur",
    "gn:country_code":"IN",
    "gn:dem":177,
    "gn:feature_class":"P",
    "gn:feature_code":"PPL",
    "gn:name":"Lachhampur",
    "gn:population":0,
    "gn:timezone":"Asia/Kolkata",
    "iso:country":"IN",
    "wof:name":"Lachhampur",
    "wof:placetype":"locality"
},
  "geometry": {"coordinates":[78.42301999999999,27.8269],"type":"Point"}
}