{
  "type": "Feature",
  "properties": {
    "gn:admin1_code":"23.0",
    "gn:admin2_code":"46.0",
    "gn:asciiname":"Lahra Muhabbat",
    "gn:country_code":"IN",
    "gn:dem":217,
    "gn:feature_class":"P",
    "gn:feature_code":"PPL",
    "gn:name":"Lahra Muhabbat",
    "gn:population":0,
    "gn:timezone":"Asia/Kolkata",
    "iso:country":"IN",
    "wof:name":"Lahra Muhabbat",
    "wof:placetype":"locality"
},
  "geometry": {"coordinates":[75.16660999999998,30.24206],"type":"Point"}
}