{
  "type": "Feature",
  "properties": {
    "gn:admin1_code":"21",
    "gn:admin2_code":"398.0",
    "gn:asciiname":"Jonkarguda",
    "gn:country_code":"IN",
    "gn:dem":917,
    "gn:feature_class":"P",
    "gn:feature_code":"PPL",
    "gn:name":"Jonkarg\u016bda",
    "gn:population":0,
    "gn:timezone":"Asia/Kolkata",
    "iso:country":"IN",
    "wof:name":"Jonkarguda",
    "wof:placetype":"locality"
},
  "geometry": {"coordinates":[82.93285999999998,18.42226],"type":"Point"}
}