{
  "type": "Feature",
  "properties": {
    "iso:country":"IN",
    "ks:ks_name":"Kiyakuli",
    "ks:ks_pop":821,
    "ks:ks_type":"VILLAGE",
    "name:eng_x_preferred":[
        "Kiyakuli"
    ],
    "wof:name":"Kiyakuli",
    "wof:placetype":"locality",
    "wof:population":821
},
  "geometry": {"coordinates":[87.471977,21.669301],"type":"Point"}
}