{
  "type": "Feature",
  "properties": {
    "iso:country":"IN",
    "ks:ks_name":"Guddanaikanahalli",
    "ks:ks_type":"VILLAGE",
    "name:eng_x_preferred":[
        "Guddanaikanahalli"
    ],
    "wof:name":"Guddanaikanahalli",
    "wof:placetype":"locality"
},
  "geometry": {"coordinates":[76.172849,14.607473],"type":"Point"}
}