{
  "type": "Feature",
  "properties": {
    "gn:admin1_code":"21.0",
    "gn:admin2_code":"398.0",
    "gn:asciiname":"Kinchop",
    "gn:country_code":"IN",
    "gn:dem":830,
    "gn:feature_class":"P",
    "gn:feature_code":"PPL",
    "gn:name":"Kinchop",
    "gn:population":0,
    "gn:timezone":"Asia/Kolkata",
    "iso:country":"IN",
    "wof:name":"Kinchop",
    "wof:placetype":"neighbourhood"
},
  "geometry": {"coordinates":[82.49054,18.52978],"type":"Point"}
}