{
  "type": "Feature",
  "properties": {
    "iso:country":"IN",
    "ks:ks_name":"Gobardhana",
    "ks:ks_pop":2291,
    "ks:ks_type":"VILLAGE",
    "ks:ks_uagg_main":0,
    "name:eng_x_preferred":[
        "Gobardhana"
    ],
    "wof:name":"Gobardhana",
    "wof:placetype":"neighbourhood",
    "wof:population":2291
},
  "geometry": {"coordinates":[90.98478900000001,26.575889],"type":"Point"}
}