{
  "type": "Feature",
  "properties": {
    "gn:admin1_code":"19.0",
    "gn:admin2_code":"571.0",
    "gn:asciiname":"Gyaragatta",
    "gn:country_code":"IN",
    "gn:dem":827,
    "gn:feature_class":"P",
    "gn:feature_code":"PPL",
    "gn:name":"Gyaragatta",
    "gn:population":0,
    "gn:timezone":"Asia/Kolkata",
    "iso:country":"IN",
    "wof:name":"Gyaragatta",
    "wof:placetype":"locality"
},
  "geometry": {"coordinates":[76.36923,13.32943],"type":"Point"}
}