{
  "type": "Feature",
  "properties": {
    "gn:country":"IN",
    "gn:fcode":"PPL",
    "gn:population":20518,
    "iso:country":"IN",
    "ks:ks_name":"Chillupar",
    "ks:ks_pop":176,
    "ks:ks_type":"VILLAGE",
    "ks:ks_uagg_main":0,
    "name:bpy_x_preferred":[
        "\u09ac\u09be\u09b0\u09b9\u09be\u09b2\u0997\u099e\u09cd\u099c"
    ],
    "name:ceb_x_preferred":[
        "Chill\u016bp\u0101r"
    ],
    "name:eng_x_preferred":[
        "Barhalganj"
    ],
    "name:fra_x_preferred":[
        "Barhalganj"
    ],
    "name:hin_x_preferred":[
        "\u092c\u0921\u093c\u0939\u0932\u0917\u0902\u091c"
    ],
    "name:ita_x_preferred":[
        "Barhalganj"
    ],
    "name:msa_x_preferred":[
        "Barhalganj"
    ],
    "name:nan_x_preferred":[
        "Barhalganj"
    ],
    "name:new_x_preferred":[
        "\u092c\u0930\u094d\u0932\u0939\u0932\u0917\u091e\u094d\u091c"
    ],
    "name:nld_x_preferred":[
        "Barhalganj"
    ],
    "name:pol_x_preferred":[
        "Barhalganj"
    ],
    "name:por_x_preferred":[
        "Barhalganj"
    ],
    "name:swe_x_preferred":[
        "Chill\u016bp\u0101r"
    ],
    "name:urd_x_preferred":[
        "\u0628\u0631\u06c1\u0644 \u06af\u0646\u062c"
    ],
    "name:vie_x_preferred":[
        "Barhalganj"
    ],
    "name:zho_x_preferred":[
        "\u5df4\u5c14\u54c8\u5c14\u7518\u6770"
    ],
    "qs:name":"Chill\u016bp\u0101r",
    "qs:photos_9r":0,
    "qs:photos_sr":0,
    "qs:pop_sr":"7",
    "wof:name":"Chillupar",
    "wof:placetype":"neighbourhood",
    "wof:population":176
},
  "geometry": {"coordinates":[83.510992,26.283346],"type":"Point"}
}