{
  "type": "Feature",
  "properties": {
    "iso:country":"IN",
    "ks:ks_name":"Kita",
    "ks:ks_pop":172,
    "ks:ks_type":"VILLAGE",
    "name:eng_x_preferred":[
        "Kita"
    ],
    "wof:name":"Kita",
    "wof:placetype":"locality",
    "wof:population":172
},
  "geometry": {"coordinates":[85.27943,22.808291],"type":"Point"}
}