{
  "type": "Feature",
  "properties": {
    "iso:country":"IN",
    "ks:ks_name":"Mokhawa Khurd",
    "ks:ks_pop":1232,
    "ks:ks_type":"VILLAGE",
    "name:eng_x_preferred":[
        "Mokhawa Khurd"
    ],
    "wof:name":"Mokhawa Khurd",
    "wof:placetype":"locality",
    "wof:population":1232
},
  "geometry": {"coordinates":[71.633814,25.275139],"type":"Point"}
}