{
  "type": "Feature",
  "properties": {
    "gn:admin1_code":"12.0",
    "gn:admin2_code":"7.0",
    "gn:asciiname":"Kapai",
    "gn:country_code":"IN",
    "gn:dem":600,
    "gn:feature_class":"P",
    "gn:feature_code":"PPL",
    "gn:name":"Kapai",
    "gn:population":0,
    "gn:timezone":"Asia/Kolkata",
    "iso:country":"IN",
    "name:bcl_x_preferred":[
        "Kapai"
    ],
    "name:ceb_x_preferred":[
        "Kapai"
    ],
    "name:deu_x_preferred":[
        "Kapai"
    ],
    "name:fra_x_preferred":[
        "Kapai"
    ],
    "name:ilo_x_preferred":[
        "Kapai"
    ],
    "name:ind_x_preferred":[
        "Kapai"
    ],
    "name:ita_x_preferred":[
        "Kapai"
    ],
    "name:nld_x_preferred":[
        "Kapai"
    ],
    "name:pag_x_preferred":[
        "Kapai"
    ],
    "name:pam_x_preferred":[
        "Kapai"
    ],
    "name:spa_x_preferred":[
        "Kapai"
    ],
    "name:swe_x_preferred":[
        "Kapai"
    ],
    "name:tgl_x_preferred":[
        "Kapai"
    ],
    "name:urd_x_preferred":[
        "\u06a9\u0627\u067e\u0627\u06cc"
    ],
    "name:vie_x_preferred":[
        "Kapai"
    ],
    "name:war_x_preferred":[
        "Kapai"
    ],
    "wof:name":"Kapai",
    "wof:placetype":"locality"
},
  "geometry": {"coordinates":[75.66643000000001,32.51553],"type":"Point"}
}