{
  "type": "Feature",
  "properties": {
    "iso:country":"IN",
    "ks:ks_name":"Bengali Suba",
    "ks:ks_pop":456,
    "ks:ks_type":"HABITATION",
    "name:eng_x_preferred":[
        "Bengali Suba"
    ],
    "wof:name":"Bengali Suba",
    "wof:placetype":"locality",
    "wof:population":456
},
  "geometry": {"coordinates":[91.93115,26.046181],"type":"Point"}
}