{
  "type": "Feature",
  "properties": {
    "gn:admin1_code":"21",
    "gn:admin2_code":"391.0",
    "gn:asciiname":"Telibandh",
    "gn:country_code":"IN",
    "gn:dem":116,
    "gn:feature_class":"P",
    "gn:feature_code":"PPL",
    "gn:name":"Telib\u0101ndh",
    "gn:population":0,
    "gn:timezone":"Asia/Kolkata",
    "iso:country":"IN",
    "wof:name":"Telibandh",
    "wof:placetype":"locality"
},
  "geometry": {"coordinates":[84.18774000000001,20.8473],"type":"Point"}
}