{
  "type": "Feature",
  "properties": {
    "gn:admin1_code":"11",
    "gn:admin2_code":"24.0",
    "gn:asciiname":"Balu",
    "gn:country_code":"IN",
    "gn:dem":627,
    "gn:feature_class":"P",
    "gn:feature_code":"PPL",
    "gn:name":"B\u0101lu",
    "gn:population":0,
    "gn:timezone":"Asia/Kolkata",
    "iso:country":"IN",
    "name:ceb_x_preferred":[
        "Balu"
    ],
    "name:deu_x_preferred":[
        "Balu"
    ],
    "name:rus_x_preferred":[
        "\u0411\u0430\u043b\u0443"
    ],
    "name:swe_x_preferred":[
        "Balu"
    ],
    "wof:name":"Balu",
    "wof:placetype":"locality"
},
  "geometry": {"coordinates":[76.27710999999999,32.02425],"type":"Point"}
}