{
  "type": "Feature",
  "properties": {
    "iso:country":"IN",
    "ks:ks_name":"Belchauri",
    "ks:ks_pop":141,
    "ks:ks_type":"HABITATION",
    "ks:ks_uagg_main":0,
    "name:eng_x_preferred":[
        "Belchauri"
    ],
    "wof:name":"Belchauri",
    "wof:placetype":"neighbourhood",
    "wof:population":141
},
  "geometry": {"coordinates":[81.124421,27.807655],"type":"Point"}
}