{
  "type": "Feature",
  "properties": {
    "iso:country":"IN",
    "ks:ks_name":"Sana Trilochanpur",
    "ks:ks_pop":581,
    "ks:ks_type":"VILLAGE",
    "ks:ks_uagg_main":0,
    "name:eng_x_preferred":[
        "Sana Trilochanpur"
    ],
    "wof:name":"Sana Trilochanpur",
    "wof:placetype":"neighbourhood",
    "wof:population":581
},
  "geometry": {"coordinates":[86.29704700000001,20.840506],"type":"Point"}
}