{
  "type": "Feature",
  "properties": {
    "iso:country":"IN",
    "ks:ks_name":"Raulidia",
    "ks:ks_pop":351,
    "ks:ks_type":"VILLAGE",
    "ks:ks_uagg_main":0,
    "name:eng_x_preferred":[
        "Raulidia"
    ],
    "wof:name":"Raulidia",
    "wof:placetype":"neighbourhood",
    "wof:population":351
},
  "geometry": {"coordinates":[86.45784500000001,20.653496],"type":"Point"}
}