{
  "type": "Feature",
  "properties": {
    "gn:admin1_code":"36",
    "gn:admin2_code":"187.0",
    "gn:asciiname":"Nandabhar",
    "gn:country_code":"IN",
    "gn:dem":97,
    "gn:feature_class":"P",
    "gn:feature_code":"PPL",
    "gn:name":"Nandabhar",
    "gn:population":0,
    "gn:timezone":"Asia/Kolkata",
    "iso:country":"IN",
    "wof:name":"Nandabhar",
    "wof:placetype":"locality"
},
  "geometry": {"coordinates":[83.60566999999998,27.22235],"type":"Point"}
}