{
  "type": "Feature",
  "properties": {
    "iso:country":"IN",
    "ks:ks_name":"Kambampadu",
    "ks:ks_pop":755,
    "ks:ks_type":"HABITATION",
    "name:eng_x_preferred":[
        "Kambampadu"
    ],
    "wof:name":"Kambampadu",
    "wof:placetype":"locality",
    "wof:population":755
},
  "geometry": {"coordinates":[81.97830500000001,16.624998],"type":"Point"}
}