{
  "type": "Feature",
  "properties": {
    "iso:country":"IN",
    "ks:ks_name":"Railway Gate Road",
    "ks:ks_pop":255,
    "ks:ks_type":"HABITATION",
    "name:eng_x_preferred":[
        "Railway Gate Road"
    ],
    "wof:name":"Railway Gate Road",
    "wof:placetype":"locality",
    "wof:population":255
},
  "geometry": {"coordinates":[76.21821799999999,11.006946],"type":"Point"}
}