{
  "type": "Feature",
  "properties": {
    "gn:admin1_code":"34.0",
    "gn:admin2_code":"219.0",
    "gn:asciiname":"Natha Chhapra",
    "gn:country_code":"IN",
    "gn:dem":55,
    "gn:feature_class":"P",
    "gn:feature_code":"PPL",
    "gn:name":"Natha Chhapra",
    "gn:population":0,
    "gn:timezone":"Asia/Kolkata",
    "iso:country":"IN",
    "ks:ks_name":"Natha Chhapra",
    "ks:ks_pop":1659,
    "ks:ks_type":"VILLAGE",
    "name:eng_x_preferred":[
        "Natha Chhapra"
    ],
    "wof:name":"Natha Chhapra",
    "wof:placetype":"locality",
    "wof:population":1659
},
  "geometry": {"coordinates":[85.024855,25.858259],"type":"Point"}
}