{
  "type": "Feature",
  "properties": {
    "iso:country":"IN",
    "ks:ks_name":"Diguva Bodagattu",
    "ks:ks_pop":142,
    "ks:ks_type":"HABITATION",
    "name:eng_x_preferred":[
        "Diguva Bodagattu"
    ],
    "wof:name":"Diguva Bodagattu",
    "wof:placetype":"locality",
    "wof:population":142
},
  "geometry": {"coordinates":[78.38647899999999,12.637282],"type":"Point"}
}