{
  "type": "Feature",
  "properties": {
    "gn:admin1_code":"23",
    "gn:admin2_code":"38.0",
    "gn:asciiname":"Bahera",
    "gn:country_code":"IN",
    "gn:dem":513,
    "gn:feature_class":"P",
    "gn:feature_code":"PPL",
    "gn:name":"Bahera",
    "gn:population":0,
    "gn:timezone":"Asia/Kolkata",
    "iso:country":"IN",
    "name:mal_x_preferred":[
        "\u0d2c\u0d39\u0d47\u0d31"
    ],
    "wof:name":"Bahera",
    "wof:placetype":"locality"
},
  "geometry": {"coordinates":[75.95045999999998,31.75461],"type":"Point"}
}