{
  "type": "Feature",
  "properties": {
    "gn:admin1_code":"23",
    "gn:admin2_code":"38.0",
    "gn:asciiname":"Bahera",
    "gn:country_code":"IN",
    "gn:dem":513,
    "gn:feature_class":"P",
    "gn:feature_code":"PPL",
    "gn:name":"Bahera",
    "gn:population":0,
    "gn:timezone":"Asia/Kolkata",
    "iso:country":"IN",
    "ks:ks_name":"Bahera",
    "ks:ks_pop":569,
    "ks:ks_type":"VILLAGE",
    "name:eng_x_preferred":[
        "Bahera"
    ],
    "name:mal_x_preferred":[
        "\u0d2c\u0d39\u0d47\u0d31"
    ],
    "wof:name":"Bahera",
    "wof:placetype":"locality",
    "wof:population":569
},
  "geometry": {"coordinates":[75.950456,31.754612],"type":"Point"}
}