{
  "type": "Feature",
  "properties": {
    "iso:country":"IN",
    "ks:ks_name":"Kohalitola Koy",
    "ks:ks_pop":235,
    "ks:ks_type":"HABITATION",
    "name:eng_x_preferred":[
        "Kohalitola Koy"
    ],
    "wof:name":"Kohalitola Koy",
    "wof:placetype":"locality",
    "wof:population":235
},
  "geometry": {"coordinates":[80.247636,21.093549],"type":"Point"}
}