{
  "type": "Feature",
  "properties": {
    "iso:country":"IN",
    "ks:ks_alt_nam":"Kautaibari II",
    "ks:ks_name":"Kautaibari Ii",
    "ks:ks_pop":326,
    "ks:ks_type":"HABITATION",
    "name:eng_x_preferred":[
        "Kautaibari Ii"
    ],
    "wof:name":"Kautaibari Ii",
    "wof:placetype":"locality",
    "wof:population":326
},
  "geometry": {"coordinates":[93.34715199999999,25.414787],"type":"Point"}
}