{
  "type": "Feature",
  "properties": {
    "iso:country":"IN",
    "ks:ks_name":"Sudingpadar",
    "ks:ks_pop":197,
    "ks:ks_type":"VILLAGE",
    "name:eng_x_preferred":[
        "Sudingpadar"
    ],
    "wof:name":"Sudingpadar",
    "wof:placetype":"locality",
    "wof:population":197
},
  "geometry": {"coordinates":[83.359967,20.226273],"type":"Point"}
}