{
  "type": "Feature",
  "properties": {
    "iso:country":"IN",
    "ks:ks_name":"Tikirasahi",
    "ks:ks_pop":104,
    "ks:ks_type":"HABITATION",
    "name:eng_x_preferred":[
        "Tikirasahi"
    ],
    "wof:name":"Tikirasahi",
    "wof:placetype":"locality",
    "wof:population":104
},
  "geometry": {"coordinates":[82.984482,19.384286],"type":"Point"}
}