{
  "type": "Feature",
  "properties": {
    "gn:admin1_code":"37",
    "gn:admin2_code":"406.0",
    "gn:asciiname":"Pithampur",
    "gn:country_code":"IN",
    "gn:dem":288,
    "gn:feature_class":"P",
    "gn:feature_code":"PPL",
    "gn:name":"Pithampur",
    "gn:population":0,
    "gn:timezone":"Asia/Kolkata",
    "iso:country":"IN",
    "name:ben_x_preferred":[
        "\u09aa\u09bf\u09a5\u09ae\u09aa\u09c1\u09b0"
    ],
    "name:bih_x_preferred":[
        "\u092a\u0940\u0925\u092e\u092a\u0941\u0930"
    ],
    "name:bpy_x_preferred":[
        "\u09aa\u09bf\u09a5\u09ae\u09aa\u09c1\u09b0"
    ],
    "name:ceb_x_preferred":[
        "Pithampur"
    ],
    "name:hif_x_preferred":[
        "Pithampur"
    ],
    "name:hin_x_preferred":[
        "\u092a\u0940\u0925\u092e\u092a\u0941\u0930"
    ],
    "name:ita_x_preferred":[
        "Pithampur"
    ],
    "name:mlg_x_preferred":[
        "Pithampur"
    ],
    "name:msa_x_preferred":[
        "Pithampur"
    ],
    "name:nld_x_preferred":[
        "Pithampur"
    ],
    "name:ori_x_preferred":[
        "\u0b2a\u0b3f\u0b25\u0b3e\u0b2e\u0b2a\u0b41\u0b30"
    ],
    "name:por_x_preferred":[
        "Pithampur"
    ],
    "name:spa_x_preferred":[
        "Pithampur"
    ],
    "name:swe_x_preferred":[
        "Pithampur"
    ],
    "name:vie_x_preferred":[
        "Pithampur"
    ],
    "name:zho_x_preferred":[
        "\u76ae\u5854\u59c6\u666e\u5c14"
    ],
    "wof:name":"Pithampur",
    "wof:placetype":"locality"
},
  "geometry": {"coordinates":[81.74999,22.11917],"type":"Point"}
}