{
  "type": "Feature",
  "properties": {
    "gn:admin1_code":"35",
    "gn:admin2_code":"456.0",
    "gn:asciiname":"Khirki",
    "gn:country_code":"IN",
    "gn:dem":361,
    "gn:feature_class":"P",
    "gn:feature_code":"PPL",
    "gn:name":"Khirki",
    "gn:population":0,
    "gn:timezone":"Asia/Kolkata",
    "iso:country":"IN",
    "ks:ks_name":"Khidki",
    "ks:ks_pop":15,
    "ks:ks_type":"VILLAGE",
    "name:eng_x_preferred":[
        "Khidki"
    ],
    "name:eng_x_variant":[
        "Khirki"
    ],
    "wof:name":"Khidki",
    "wof:placetype":"locality",
    "wof:population":15
},
  "geometry": {"coordinates":[79.62213199999999,21.717404],"type":"Point"}
}