{
  "type": "Feature",
  "properties": {
    "iso:country":"IN",
    "ks:ks_name":"Rangamatiasahi",
    "ks:ks_pop":125,
    "ks:ks_type":"HABITATION",
    "name:eng_x_preferred":[
        "Rangamatiasahi"
    ],
    "wof:name":"Rangamatiasahi",
    "wof:placetype":"locality",
    "wof:population":125
},
  "geometry": {"coordinates":[85.757874,21.18849],"type":"Point"}
}