{
  "type": "Feature",
  "properties": {
    "iso:country":"IN",
    "ks:ks_alt_nam":"DURJOY NAGAR",
    "ks:ks_name":"Durjoy Nagar",
    "ks:ks_pop":765,
    "ks:ks_type":"HABITATION",
    "ks:ks_uagg_main":0,
    "name:eng_x_preferred":[
        "Durjoy Nagar"
    ],
    "wof:name":"Durjoy Nagar",
    "wof:placetype":"locality",
    "wof:population":765
},
  "geometry": {"coordinates":[91.26775000000001,23.876406],"type":"Point"}
}