{
  "type": "Feature",
  "properties": {
    "iso:country":"IN",
    "ks:ks_name":"Paleregadi",
    "ks:ks_pop":85,
    "ks:ks_type":"HABITATION",
    "name:eng_x_preferred":[
        "Paleregadi"
    ],
    "wof:name":"Paleregadi",
    "wof:placetype":"locality",
    "wof:population":85
},
  "geometry": {"coordinates":[78.719622,19.225428],"type":"Point"}
}