{
  "type": "Feature",
  "properties": {
    "iso:country":"IN",
    "ks:ks_name":"Shamjot",
    "ks:ks_pop":168,
    "ks:ks_type":"VILLAGE",
    "name:eng_x_preferred":[
        "Shamjot"
    ],
    "wof:name":"Shamjot",
    "wof:placetype":"locality",
    "wof:population":168
},
  "geometry": {"coordinates":[87.835278,24.793499],"type":"Point"}
}