{
  "type": "Feature",
  "properties": {
    "gn:admin1_code":"37",
    "gn:admin2_code":"415.0",
    "gn:asciiname":"Chargaon",
    "gn:country_code":"IN",
    "gn:dem":340,
    "gn:feature_class":"P",
    "gn:feature_code":"PPL",
    "gn:name":"Ch\u0101rgaon",
    "gn:population":0,
    "gn:timezone":"Asia/Kolkata",
    "iso:country":"IN",
    "ks:ks_alt_nam":"Ch\u0101rgaon",
    "ks:ks_name":"Chargaon",
    "ks:ks_type":"VILLAGE",
    "name:eng_x_preferred":[
        "Chargaon"
    ],
    "name:eng_x_variant":[
        "Ch\u0101rgaon"
    ],
    "wof:name":"Chargaon",
    "wof:placetype":"locality"
},
  "geometry": {"coordinates":[81.008487,20.035619],"type":"Point"}
}