{
  "type": "Feature",
  "properties": {
    "gn:admin1_code":"37",
    "gn:admin2_code":"415.0",
    "gn:asciiname":"Chargaon",
    "gn:country_code":"IN",
    "gn:dem":340,
    "gn:feature_class":"P",
    "gn:feature_code":"PPL",
    "gn:name":"Ch\u0101rgaon",
    "gn:population":0,
    "gn:timezone":"Asia/Kolkata",
    "iso:country":"IN",
    "wof:name":"Chargaon",
    "wof:placetype":"locality"
},
  "geometry": {"coordinates":[81.00849000000002,20.03562],"type":"Point"}
}