{
  "type": "Feature",
  "properties": {
    "gn:admin1_code":"36.0",
    "gn:admin2_code":"150.0",
    "gn:asciiname":"Naugawan",
    "gn:country_code":"IN",
    "gn:dem":176,
    "gn:feature_class":"P",
    "gn:feature_code":"PPL",
    "gn:name":"Naugaw\u0101n",
    "gn:population":0,
    "gn:timezone":"Asia/Kolkata",
    "iso:country":"IN",
    "ks:ks_alt_nam":"Naugaw\u0101n",
    "ks:ks_name":"Naugawan",
    "ks:ks_type":"VILLAGE",
    "name:eng_x_preferred":[
        "Naugawan"
    ],
    "name:eng_x_variant":[
        "Naugaw\u0101n"
    ],
    "wof:name":"Naugawan",
    "wof:placetype":"locality"
},
  "geometry": {"coordinates":[79.508951,28.442451],"type":"Point"}
}