{
  "type": "Feature",
  "properties": {
    "iso:country":"IN",
    "ks:ks_name":"Charigharia",
    "ks:ks_pop":280,
    "ks:ks_type":"VILLAGE",
    "name:eng_x_preferred":[
        "Charigharia"
    ],
    "wof:name":"Charigharia",
    "wof:placetype":"locality",
    "wof:population":280
},
  "geometry": {"coordinates":[86.35597199999999,21.04221],"type":"Point"}
}