{
  "type": "Feature",
  "properties": {
    "iso:country":"IN",
    "ks:ks_name":"Dadkee",
    "ks:ks_pop":1499,
    "ks:ks_type":"HABITATION",
    "name:eng_x_preferred":[
        "Dadkee"
    ],
    "wof:name":"Dadkee",
    "wof:placetype":"locality",
    "wof:population":1499
},
  "geometry": {"coordinates":[77.724363,26.901339],"type":"Point"}
}