{
  "type": "Feature",
  "properties": {
    "gn:admin1_code":"11.0",
    "gn:admin2_code":"32.0",
    "gn:asciiname":"Kalab",
    "gn:country_code":"IN",
    "gn:dem":2536,
    "gn:feature_class":"P",
    "gn:feature_code":"PPL",
    "gn:name":"K\u0101lab",
    "gn:population":0,
    "gn:timezone":"Asia/Kolkata",
    "iso:country":"IN",
    "name:fas_x_preferred":[
        "\u06a9\u0644\u0627\u0628"
    ],
    "wof:name":"Kalab",
    "wof:placetype":"locality"
},
  "geometry": {"coordinates":[77.39709000000001,30.95183],"type":"Point"}
}