{
  "type": "Feature",
  "properties": {
    "iso:country":"IN",
    "ks:ks_name":"Dharmagatpur",
    "ks:ks_pop":19,
    "ks:ks_type":"VILLAGE",
    "name:eng_x_preferred":[
        "Dharmagatpur"
    ],
    "wof:name":"Dharmagatpur",
    "wof:placetype":"locality",
    "wof:population":19
},
  "geometry": {"coordinates":[83.916124,25.298916],"type":"Point"}
}