{
  "type": "Feature",
  "properties": {
    "iso:country":"IN",
    "ks:ks_name":"Honnikuppe",
    "ks:ks_pop":90,
    "ks:ks_type":"HABITATION",
    "name:eng_x_preferred":[
        "Honnikuppe"
    ],
    "wof:name":"Honnikuppe",
    "wof:placetype":"locality",
    "wof:population":90
},
  "geometry": {"coordinates":[75.97361100000001,12.150278],"type":"Point"}
}