{
  "type": "Feature",
  "properties": {
    "iso:country":"IN",
    "ks:ks_name":"Doddahirekai",
    "ks:ks_pop":54,
    "ks:ks_type":"HABITATION",
    "name:eng_x_preferred":[
        "Doddahirekai"
    ],
    "wof:name":"Doddahirekai",
    "wof:placetype":"locality",
    "wof:population":54
},
  "geometry": {"coordinates":[74.69333899999999,14.416594],"type":"Point"}
}