{
  "type": "Feature",
  "properties": {
    "iso:country":"IN",
    "ks:ks_name":"School Tola",
    "ks:ks_pop":206,
    "ks:ks_type":"HABITATION",
    "ks:ks_uagg_main":0,
    "name:eng_x_preferred":[
        "School Tola"
    ],
    "wof:name":"School Tola",
    "wof:placetype":"neighbourhood",
    "wof:population":206
},
  "geometry": {"coordinates":[83.41830899999999,26.964929],"type":"Point"}
}