{
  "type": "Feature",
  "properties": {
    "iso:country":"IN",
    "ks:ks_name":"Andabylu",
    "ks:ks_pop":884,
    "ks:ks_type":"HABITATION",
    "name:eng_x_preferred":[
        "Andabylu"
    ],
    "wof:name":"Andabylu",
    "wof:placetype":"locality",
    "wof:population":884
},
  "geometry": {"coordinates":[75.167547,13.696342],"type":"Point"}
}