{
  "type": "Feature",
  "properties": {
    "iso:country":"IN",
    "ks:ks_name":"Sedara",
    "ks:ks_pop":1396,
    "ks:ks_type":"VILLAGE",
    "name:eng_x_preferred":[
        "Sedara"
    ],
    "wof:name":"Sedara",
    "wof:placetype":"locality",
    "wof:population":1396
},
  "geometry": {"coordinates":[79.3172,24.08014],"type":"Point"}
}