{
  "type": "Feature",
  "properties": {
    "gn:admin1_code":"39.0",
    "gn:admin2_code":"66.0",
    "gn:asciiname":"Riya",
    "gn:country_code":"IN",
    "gn:dem":1225,
    "gn:feature_class":"P",
    "gn:feature_code":"PPL",
    "gn:name":"Riya",
    "gn:population":0,
    "gn:timezone":"Asia/Kolkata",
    "iso:country":"IN",
    "name:deu_x_preferred":[
        "Riya"
    ],
    "name:fra_x_preferred":[
        "Riya"
    ],
    "name:ind_x_preferred":[
        "Riya"
    ],
    "name:ita_x_preferred":[
        "Riya"
    ],
    "name:jpn_x_preferred":[
        "Riya"
    ],
    "name:tgl_x_preferred":[
        "Riya"
    ],
    "name:vie_x_preferred":[
        "Riya"
    ],
    "name:zho_x_preferred":[
        "Riya"
    ],
    "wof:name":"Riya",
    "wof:placetype":"locality"
},
  "geometry": {"coordinates":[79.29142,29.4474],"type":"Point"}
}