{
  "type": "Feature",
  "properties": {
    "iso:country":"IN",
    "ks:ks_name":"Idayankudi",
    "ks:ks_pop":1050,
    "ks:ks_type":"HABITATION",
    "ks:ks_uagg_main":0,
    "name:eng_x_preferred":[
        "Idayankudi"
    ],
    "wof:name":"Idayankudi",
    "wof:placetype":"neighbourhood",
    "wof:population":1050
},
  "geometry": {"coordinates":[77.881891,8.309571],"type":"Point"}
}