{
  "type": "Feature",
  "properties": {
    "iso:country":"IN",
    "ks:ks_name":"Bansjori",
    "ks:ks_pop":379,
    "ks:ks_type":"HABITATION",
    "name:eng_x_preferred":[
        "Bansjori"
    ],
    "wof:name":"Bansjori",
    "wof:placetype":"locality",
    "wof:population":379
},
  "geometry": {"coordinates":[87.617192,24.919388],"type":"Point"}
}