{
  "type": "Feature",
  "properties": {
    "iso:country":"IN",
    "ks:ks_name":"Thailapara Pt I",
    "ks:ks_pop":203,
    "ks:ks_type":"HABITATION",
    "name:eng_x_preferred":[
        "Thailapara Pt I"
    ],
    "wof:name":"Thailapara Pt I",
    "wof:placetype":"locality",
    "wof:population":203
},
  "geometry": {"coordinates":[90.35004600000001,26.126506],"type":"Point"}
}