{
  "type": "Feature",
  "properties": {
    "iso:country":"IN",
    "ks:ks_name":"Pudur - Rawthankuppam",
    "ks:ks_pop":360,
    "ks:ks_type":"HABITATION",
    "name:eng_x_preferred":[
        "Pudur - Rawthankuppam"
    ],
    "wof:name":"Pudur - Rawthankuppam",
    "wof:placetype":"locality",
    "wof:population":360
},
  "geometry": {"coordinates":[79.767594,12.016259],"type":"Point"}
}