{
  "type": "Feature",
  "properties": {
    "gn:admin1_code":"24.0",
    "gn:admin2_code":"104.0",
    "gn:asciiname":"Hajipur",
    "gn:country_code":"IN",
    "gn:dem":259,
    "gn:feature_class":"P",
    "gn:feature_code":"PPL",
    "gn:name":"H\u0101jipur",
    "gn:population":0,
    "gn:timezone":"Asia/Kolkata",
    "iso:country":"IN",
    "wof:name":"Hajipur",
    "wof:placetype":"locality"
},
  "geometry": {"coordinates":[76.67449000000001,28.08782],"type":"Point"}
}