{
  "type": "Feature",
  "properties": {
    "iso:country":"IN",
    "ks:ks_name":"Bihadi Pod",
    "ks:ks_pop":195,
    "ks:ks_type":"HABITATION",
    "name:eng_x_preferred":[
        "Bihadi Pod"
    ],
    "wof:name":"Bihadi Pod",
    "wof:placetype":"locality",
    "wof:population":195
},
  "geometry": {"coordinates":[78.705618,20.148455],"type":"Point"}
}