{
  "type": "Feature",
  "properties": {
    "iso:country":"IN",
    "ks:ks_name":"Bihawal",
    "ks:ks_pop":318,
    "ks:ks_type":"VILLAGE",
    "name:eng_x_preferred":[
        "Bihawal"
    ],
    "wof:name":"Bihawal",
    "wof:placetype":"locality",
    "wof:population":318
},
  "geometry": {"coordinates":[83.820189,22.606307],"type":"Point"}
}