{
  "type": "Feature",
  "properties": {
    "iso:country":"IN",
    "ks:ks_name":"Ranipukhuri",
    "ks:ks_pop":2326,
    "ks:ks_type":"VILLAGE",
    "ks:ks_uagg_main":0,
    "name:eng_x_preferred":[
        "Ranipukhuri"
    ],
    "wof:name":"Ranipukhuri",
    "wof:placetype":"locality",
    "wof:population":2326
},
  "geometry": {"coordinates":[92.963303,25.944654],"type":"Point"}
}