{
  "type": "Feature",
  "properties": {
    "gn:admin1_code":"25.0",
    "gn:admin2_code":"609.0",
    "gn:asciiname":"Aruvappuliyur",
    "gn:country_code":"IN",
    "gn:dem":220,
    "gn:feature_class":"P",
    "gn:feature_code":"PPL",
    "gn:name":"Aruv\u0101ppuliy\u016br",
    "gn:population":0,
    "gn:timezone":"Asia/Kolkata",
    "iso:country":"IN",
    "wof:name":"Aruvappuliyur",
    "wof:placetype":"locality"
},
  "geometry": {"coordinates":[77.79691,11.43911],"type":"Point"}
}