{
  "type": "Feature",
  "properties": {
    "gn:admin1_code":"28.0",
    "gn:admin2_code":"344.0",
    "gn:asciiname":"Nayapukur",
    "gn:country_code":"IN",
    "gn:dem":34,
    "gn:feature_class":"P",
    "gn:feature_code":"PPL",
    "gn:name":"Nayapukur",
    "gn:population":0,
    "gn:timezone":"Asia/Kolkata",
    "iso:country":"IN",
    "wof:name":"Nayapukur",
    "wof:placetype":"locality"
},
  "geometry": {"coordinates":[87.31404000000001,22.20146],"type":"Point"}
}