{
  "type": "Feature",
  "properties": {
    "iso:country":"IN",
    "ks:ks_name":"Thar Goberdhan",
    "ks:ks_pop":300,
    "ks:ks_type":"HABITATION",
    "name:eng_x_preferred":[
        "Thar Goberdhan"
    ],
    "wof:name":"Thar Goberdhan",
    "wof:placetype":"locality",
    "wof:population":300
},
  "geometry": {"coordinates":[78.39088599999999,27.094343],"type":"Point"}
}