{
  "type": "Feature",
  "properties": {
    "iso:country":"IN",
    "ks:ks_name":"Chandanpur",
    "ks:ks_pop":0,
    "ks:ks_type":"VILLAGE",
    "name:eng_x_preferred":[
        "Chandanpur"
    ],
    "wof:name":"Chandanpur",
    "wof:placetype":"locality",
    "wof:population":0
},
  "geometry": {"coordinates":[80.312242,28.314897],"type":"Point"}
}