{
  "type": "Feature",
  "properties": {
    "iso:country":"IN",
    "ks:ks_name":"Nalilu",
    "ks:ks_pop":462,
    "ks:ks_type":"HABITATION",
    "name:eng_x_preferred":[
        "Nalilu"
    ],
    "wof:name":"Nalilu",
    "wof:placetype":"locality",
    "wof:population":462
},
  "geometry": {"coordinates":[75.33687999999999,12.667131],"type":"Point"}
}