{
  "type": "Feature",
  "properties": {
    "iso:country":"IN",
    "ks:ks_name":"Palasdanga Hamidpur Durulya",
    "ks:ks_pop":230,
    "ks:ks_type":"VILLAGE",
    "name:eng_x_preferred":[
        "Palasdanga Hamidpur Durulya"
    ],
    "wof:name":"Palasdanga Hamidpur Durulya",
    "wof:placetype":"locality",
    "wof:population":230
},
  "geometry": {"coordinates":[87.409414,24.037261],"type":"Point"}
}