{
  "type": "Feature",
  "properties": {
    "iso:country":"IN",
    "ks:ks_alt_nam":"Kaggod LT",
    "ks:ks_name":"Kaggod Lt",
    "ks:ks_pop":270,
    "ks:ks_type":"HABITATION",
    "name:eng_x_preferred":[
        "Kaggod Lt"
    ],
    "wof:name":"Kaggod Lt",
    "wof:placetype":"locality",
    "wof:population":270
},
  "geometry": {"coordinates":[75.91463400000001,16.821544],"type":"Point"}
}