{
  "type": "Feature",
  "properties": {
    "iso:country":"IN",
    "ks:ks_name":"Sukhampur",
    "ks:ks_pop":185,
    "ks:ks_type":"HABITATION",
    "name:eng_x_preferred":[
        "Sukhampur"
    ],
    "wof:name":"Sukhampur",
    "wof:placetype":"locality",
    "wof:population":185
},
  "geometry": {"coordinates":[79.54497499999999,26.739786],"type":"Point"}
}