{
  "type": "Feature",
  "properties": {
    "iso:country":"IN",
    "ks:ks_alt_nam":"Ampuram",
    "ks:ks_name":"Ampur",
    "ks:ks_type":"VILLAGE",
    "name:eng_x_preferred":[
        "Ampur"
    ],
    "name:eng_x_variant":[
        "Ampuram"
    ],
    "wof:name":"Ampur",
    "wof:placetype":"locality"
},
  "geometry": {"coordinates":[80.936825,18.201069],"type":"Point"}
}