{
  "type": "Feature",
  "properties": {
    "gn:admin1_code":"2.0",
    "gn:admin2_code":"546",
    "gn:asciiname":"Ganapavaram",
    "gn:country_code":"IN",
    "gn:dem":16,
    "gn:feature_class":"P",
    "gn:feature_code":"PPL",
    "gn:name":"Ganapavaram",
    "gn:population":0,
    "gn:timezone":"Asia/Kolkata",
    "iso:country":"IN",
    "wof:name":"Ganapavaram",
    "wof:placetype":"locality"
},
  "geometry": {"coordinates":[81.46297,16.70007],"type":"Point"}
}