{
  "type": "Feature",
  "properties": {
    "gn:admin1_code":"12.0",
    "gn:admin2_code":"9.0",
    "gn:asciiname":"Buth",
    "gn:country_code":"IN",
    "gn:dem":2203,
    "gn:feature_class":"P",
    "gn:feature_code":"PPL",
    "gn:name":"B\u016bth",
    "gn:population":0,
    "gn:timezone":"Asia/Kolkata",
    "iso:country":"IN",
    "name:eng_x_preferred":[
        "B\u016bth"
    ],
    "wof:name":"Buth",
    "wof:placetype":"locality"
},
  "geometry": {"coordinates":[74.68871999999998,34.44584],"type":"Point"}
}