{
  "type": "Feature",
  "properties": {
    "iso:country":"IN",
    "ks:ks_name":"Dibyasinghprasad",
    "ks:ks_pop":801,
    "ks:ks_type":"HABITATION",
    "name:eng_x_preferred":[
        "Dibyasinghprasad"
    ],
    "wof:name":"Dibyasinghprasad",
    "wof:placetype":"locality",
    "wof:population":801
},
  "geometry": {"coordinates":[85.56659500000001,20.235495],"type":"Point"}
}