{
  "type": "Feature",
  "properties": {
    "gn:admin1_code":"25.0",
    "gn:admin2_code":"631.0",
    "gn:asciiname":"Ganjinayakkampaptti",
    "gn:country_code":"IN",
    "gn:dem":411,
    "gn:feature_class":"P",
    "gn:feature_code":"PPL",
    "gn:name":"Ganjin\u0101yakkampaptti",
    "gn:population":0,
    "gn:timezone":"Asia/Kolkata",
    "iso:country":"IN",
    "wof:name":"Ganjinayakkampaptti",
    "wof:placetype":"neighbourhood"
},
  "geometry": {"coordinates":[78.38454,12.34134],"type":"Point"}
}