{
  "type": "Feature",
  "properties": {
    "iso:country":"IN",
    "ks:ks_name":"Shata Chak",
    "ks:ks_pop":279,
    "ks:ks_type":"VILLAGE",
    "name:eng_x_preferred":[
        "Shata Chak"
    ],
    "wof:name":"Shata Chak",
    "wof:placetype":"locality",
    "wof:population":279
},
  "geometry": {"coordinates":[87.501418,22.497737],"type":"Point"}
}