{
  "type": "Feature",
  "properties": {
    "gn:admin1_code":"12.0",
    "gn:admin2_code":"6.0",
    "gn:asciiname":"Bina",
    "gn:country_code":"IN",
    "gn:dem":1412,
    "gn:feature_class":"P",
    "gn:feature_code":"PPL",
    "gn:name":"Bina",
    "gn:population":0,
    "gn:timezone":"Asia/Kolkata",
    "iso:country":"IN",
    "wof:name":"Bina",
    "wof:placetype":"locality"
},
  "geometry": {"coordinates":[74.4905,33.29804],"type":"Point"}
}