{
  "type": "Feature",
  "properties": {
    "gn:admin1_code":"37",
    "gn:admin2_code":"400.0",
    "gn:asciiname":"Mero",
    "gn:country_code":"IN",
    "gn:dem":449,
    "gn:feature_class":"P",
    "gn:feature_code":"PPL",
    "gn:name":"Mero",
    "gn:population":0,
    "gn:timezone":"Asia/Kolkata",
    "iso:country":"IN",
    "ks:ks_name":"Mero",
    "ks:ks_pop":1087,
    "ks:ks_type":"VILLAGE",
    "name:ceb_x_preferred":[
        "Mero"
    ],
    "name:deu_x_preferred":[
        "Mero"
    ],
    "name:eng_x_preferred":[
        "Mero"
    ],
    "name:fra_x_preferred":[
        "M\u00e9ro"
    ],
    "name:glg_x_preferred":[
        "Mero"
    ],
    "name:por_x_preferred":[
        "Mero"
    ],
    "name:swe_x_preferred":[
        "Mero"
    ],
    "wof:name":"Mero",
    "wof:placetype":"locality",
    "wof:population":1087
},
  "geometry": {"coordinates":[82.26038699999999,23.135087],"type":"Point"}
}