{
  "type": "Feature",
  "properties": {
    "iso:country":"IN",
    "ks:ks_alt_nam":"kamathe foujdarwadi",
    "ks:ks_name":"Kamathe Foujdarwadi",
    "ks:ks_pop":100,
    "ks:ks_type":"HABITATION",
    "name:eng_x_preferred":[
        "Kamathe Foujdarwadi"
    ],
    "wof:name":"Kamathe Foujdarwadi",
    "wof:placetype":"locality",
    "wof:population":100
},
  "geometry": {"coordinates":[73.606235,18.037453],"type":"Point"}
}