{
  "type": "Feature",
  "properties": {
    "iso:country":"IN",
    "ks:ks_name":"Piteipur",
    "ks:ks_pop":1479,
    "ks:ks_type":"VILLAGE",
    "name:eng_x_preferred":[
        "Piteipur"
    ],
    "wof:name":"Piteipur",
    "wof:placetype":"locality",
    "wof:population":1479
},
  "geometry": {"coordinates":[86.451425,20.845918],"type":"Point"}
}