{
  "type": "Feature",
  "properties": {
    "iso:country":"IN",
    "ks:ks_name":"E Chekkavari Palli",
    "ks:ks_pop":23,
    "ks:ks_type":"HABITATION",
    "name:eng_x_preferred":[
        "E Chekkavari Palli"
    ],
    "wof:name":"E Chekkavari Palli",
    "wof:placetype":"locality",
    "wof:population":23
},
  "geometry": {"coordinates":[78.247597,13.961756],"type":"Point"}
}