{
  "type": "Feature",
  "properties": {
    "iso:country":"IN",
    "ks:ks_name":"Rajwadi",
    "ks:ks_pop":25,
    "ks:ks_type":"HABITATION",
    "name:eng_x_preferred":[
        "Rajwadi"
    ],
    "wof:name":"Rajwadi",
    "wof:placetype":"locality",
    "wof:population":25
},
  "geometry": {"coordinates":[73.494659,19.705131],"type":"Point"}
}