{
  "type": "Feature",
  "properties": {
    "iso:country":"IN",
    "ks:ks_name":"Kayrabani",
    "ks:ks_pop":235,
    "ks:ks_type":"VILLAGE",
    "name:eng_x_preferred":[
        "Kayrabani"
    ],
    "wof:name":"Kayrabani",
    "wof:placetype":"locality",
    "wof:population":235
},
  "geometry": {"coordinates":[87.305711,24.289919],"type":"Point"}
}