{
  "type": "Feature",
  "properties": {
    "iso:country":"IN",
    "ks:ks_alt_nam":"M\u0101hpur",
    "ks:ks_name":"Mahpur",
    "ks:ks_type":"VILLAGE",
    "name:eng_x_preferred":[
        "Mahpur"
    ],
    "name:eng_x_variant":[
        "M\u0101hpur"
    ],
    "wof:name":"Mahpur",
    "wof:placetype":"locality"
},
  "geometry": {"coordinates":[84.31647700000001,26.107319],"type":"Point"}
}