{
  "type": "Feature",
  "properties": {
    "iso:country":"IN",
    "ks:ks_name":"Ravidoddipeta",
    "ks:ks_pop":432,
    "ks:ks_type":"HABITATION",
    "name:eng_x_preferred":[
        "Ravidoddipeta"
    ],
    "wof:name":"Ravidoddipeta",
    "wof:placetype":"locality",
    "wof:population":432
},
  "geometry": {"coordinates":[82.121813,16.728872],"type":"Point"}
}