{
  "type": "Feature",
  "properties": {
    "iso:country":"IN",
    "ks:ks_name":"Bhairopur Nizamat",
    "ks:ks_pop":1933,
    "ks:ks_type":"VILLAGE",
    "ks:ks_uagg_main":0,
    "name:eng_x_preferred":[
        "Bhairopur Nizamat"
    ],
    "wof:name":"Bhairopur Nizamat",
    "wof:placetype":"locality",
    "wof:population":1933
},
  "geometry": {"coordinates":[84.832047,25.734695],"type":"Point"}
}