{
  "type": "Feature",
  "properties": {
    "iso:country":"IN",
    "ks:ks_name":"Puchabettu",
    "ks:ks_pop":110,
    "ks:ks_type":"HABITATION",
    "name:eng_x_preferred":[
        "Puchabettu"
    ],
    "wof:name":"Puchabettu",
    "wof:placetype":"locality",
    "wof:population":110
},
  "geometry": {"coordinates":[75.101266,13.168574],"type":"Point"}
}