{
  "type": "Feature",
  "properties": {
    "iso:country":"IN",
    "ks:ks_name":"Taratikar",
    "ks:ks_pop":398,
    "ks:ks_type":"VILLAGE",
    "ks:ks_uagg_main":0,
    "name:eng_x_preferred":[
        "Taratikar"
    ],
    "wof:name":"Taratikar",
    "wof:placetype":"neighbourhood",
    "wof:population":398
},
  "geometry": {"coordinates":[87.23849,24.928836],"type":"Point"}
}