{
  "type": "Feature",
  "properties": {
    "gn:admin1_code":"36.0",
    "gn:admin2_code":"169.0",
    "gn:asciiname":"Thalaura",
    "gn:country_code":"IN",
    "gn:dem":186,
    "gn:feature_class":"P",
    "gn:feature_code":"PPL",
    "gn:name":"Thalaura",
    "gn:population":0,
    "gn:timezone":"Asia/Kolkata",
    "iso:country":"IN",
    "wof:name":"Thalaura",
    "wof:placetype":"locality"
},
  "geometry": {"coordinates":[79.40928000000002,25.35781],"type":"Point"}
}