{
  "type": "Feature",
  "properties": {
    "gn:admin1_code":"35.0",
    "gn:admin2_code":"463.0",
    "gn:asciiname":"Ghinhagaon",
    "gn:country_code":"IN",
    "gn:dem":429,
    "gn:feature_class":"P",
    "gn:feature_code":"PPL",
    "gn:name":"Ghinh\u0101gaon",
    "gn:population":0,
    "gn:timezone":"Asia/Kolkata",
    "iso:country":"IN",
    "ks:ks_alt_nam":"Ghinh\u0101gaon",
    "ks:ks_name":"Ghinhagaon",
    "ks:ks_pop":1843,
    "ks:ks_type":"VILLAGE",
    "name:eng_x_preferred":[
        "Ghinhagaon"
    ],
    "name:eng_x_variant":[
        "Ghinh\u0101gaon"
    ],
    "wof:name":"Ghinhagaon",
    "wof:placetype":"locality",
    "wof:population":1843
},
  "geometry": {"coordinates":[82.50030599999999,24.268207],"type":"Point"}
}