{
  "type": "Feature",
  "properties": {
    "gn:admin1_code":"35.0",
    "gn:admin2_code":"463.0",
    "gn:asciiname":"Ghinhagaon",
    "gn:country_code":"IN",
    "gn:dem":429,
    "gn:feature_class":"P",
    "gn:feature_code":"PPL",
    "gn:name":"Ghinh\u0101gaon",
    "gn:population":0,
    "gn:timezone":"Asia/Kolkata",
    "iso:country":"IN",
    "wof:name":"Ghinhagaon",
    "wof:placetype":"locality"
},
  "geometry": {"coordinates":[82.50579999999999,24.26819],"type":"Point"}
}