{
  "type": "Feature",
  "properties": {
    "iso:country":"IN",
    "ks:ks_name":"Balanagar",
    "ks:ks_pop":376,
    "ks:ks_type":"HABITATION",
    "name:eng_x_preferred":[
        "Balanagar"
    ],
    "wof:name":"Balanagar",
    "wof:placetype":"locality",
    "wof:population":376
},
  "geometry": {"coordinates":[72.266092,26.44395],"type":"Point"}
}