{
  "type": "Feature",
  "properties": {
    "gn:admin1_code":"16.0",
    "gn:admin2_code":"526.0",
    "gn:asciiname":"Guruwadi",
    "gn:country_code":"IN",
    "gn:dem":468,
    "gn:feature_class":"P",
    "gn:feature_code":"PPL",
    "gn:name":"Guruw\u0101di",
    "gn:population":0,
    "gn:timezone":"Asia/Kolkata",
    "iso:country":"IN",
    "wof:name":"Guruwadi",
    "wof:placetype":"locality"
},
  "geometry": {"coordinates":[76.17246999999998,17.43048],"type":"Point"}
}