{
  "type": "Feature",
  "properties": {
    "gn:admin1_code":"24.0",
    "gn:admin2_code":"103",
    "gn:asciiname":"Neta ki Dhani",
    "gn:country_code":"IN",
    "gn:dem":331,
    "gn:feature_class":"P",
    "gn:feature_code":"PPL",
    "gn:name":"Neta ki Dh\u0101ni",
    "gn:population":0,
    "gn:timezone":"Asia/Kolkata",
    "iso:country":"IN",
    "wof:name":"Neta ki Dhani",
    "wof:placetype":"locality"
},
  "geometry": {"coordinates":[75.41609,28.11937],"type":"Point"}
}