{
  "type": "Feature",
  "properties": {
    "iso:country":"IN",
    "ks:ks_name":"Athani Poomala Road Jn",
    "ks:ks_pop":1314,
    "ks:ks_type":"HABITATION",
    "ks:ks_uagg_main":0,
    "name:eng_x_preferred":[
        "Athani Poomala Road Jn"
    ],
    "wof:name":"Athani Poomala Road Jn",
    "wof:placetype":"locality",
    "wof:population":1314
},
  "geometry": {"coordinates":[76.216785,10.619946],"type":"Point"}
}