{
  "type": "Feature",
  "properties": {
    "iso:country":"IN",
    "ks:ks_name":"Sapmundi",
    "ks:ks_pop":462,
    "ks:ks_type":"VILLAGE",
    "name:eng_x_preferred":[
        "Sapmundi"
    ],
    "wof:name":"Sapmundi",
    "wof:placetype":"locality",
    "wof:population":462
},
  "geometry": {"coordinates":[83.047359,19.73595],"type":"Point"}
}