{
  "type": "Feature",
  "properties": {
    "gn:admin1_code":"24.0",
    "gn:admin2_code":"124.0",
    "gn:asciiname":"Satu",
    "gn:country_code":"IN",
    "gn:dem":252,
    "gn:feature_class":"P",
    "gn:feature_code":"PPL",
    "gn:name":"Satu",
    "gn:population":0,
    "gn:timezone":"Asia/Kolkata",
    "iso:country":"IN",
    "name:fin_x_preferred":[
        "Satu"
    ],
    "name:ind_x_preferred":[
        "Satu"
    ],
    "name:jpn_x_preferred":[
        "\u30b5\u30c8\u30a5"
    ],
    "name:ron_x_preferred":[
        "Satu"
    ],
    "wof:name":"Satu",
    "wof:placetype":"locality"
},
  "geometry": {"coordinates":[73.90838000000002,23.91136],"type":"Point"}
}