{
  "type": "Feature",
  "properties": {
    "iso:country":"IN",
    "ks:ks_name":"Dabaliapara N",
    "ks:ks_pop":509,
    "ks:ks_type":"HABITATION",
    "name:eng_x_preferred":[
        "Dabaliapara N"
    ],
    "wof:name":"Dabaliapara N",
    "wof:placetype":"locality",
    "wof:population":509
},
  "geometry": {"coordinates":[90.96881999999999,26.397277],"type":"Point"}
}