{
  "type": "Feature",
  "properties": {
    "iso:country":"IN",
    "ks:ks_name":"Dhanuk Tola",
    "ks:ks_pop":393,
    "ks:ks_type":"HABITATION",
    "name:eng_x_preferred":[
        "Dhanuk Tola"
    ],
    "wof:name":"Dhanuk Tola",
    "wof:placetype":"locality",
    "wof:population":393
},
  "geometry": {"coordinates":[86.792474,26.089332],"type":"Point"}
}