{
  "type": "Feature",
  "properties": {
    "gn:admin1_code":"19.0",
    "gn:admin2_code":"568.0",
    "gn:asciiname":"Indavalli",
    "gn:country_code":"IN",
    "gn:dem":568,
    "gn:feature_class":"P",
    "gn:feature_code":"PPL",
    "gn:name":"Indavalli",
    "gn:population":0,
    "gn:timezone":"Asia/Kolkata",
    "iso:country":"IN",
    "ks:ks_name":"Induvalli",
    "ks:ks_pop":32,
    "ks:ks_type":"VILLAGE",
    "name:eng_x_preferred":[
        "Induvalli"
    ],
    "name:eng_x_variant":[
        "Indavalli"
    ],
    "wof:name":"Induvalli",
    "wof:placetype":"locality",
    "wof:population":32
},
  "geometry": {"coordinates":[75.06667299999999,14.044654],"type":"Point"}
}