{
  "type": "Feature",
  "properties": {
    "iso:country":"IN",
    "ks:ks_name":"Chinthakayalapalle",
    "ks:ks_pop":124,
    "ks:ks_type":"HABITATION",
    "name:eng_x_preferred":[
        "Chinthakayalapalle"
    ],
    "wof:name":"Chinthakayalapalle",
    "wof:placetype":"locality",
    "wof:population":124
},
  "geometry": {"coordinates":[79.195871,14.362623],"type":"Point"}
}