{
  "type": "Feature",
  "properties": {
    "iso:country":"IN",
    "ks:ks_name":"Seyyanam",
    "ks:ks_pop":1085,
    "ks:ks_type":"VILLAGE",
    "ks:ks_uagg_main":0,
    "name:eng_x_preferred":[
        "Seyyanam"
    ],
    "wof:name":"Seyyanam",
    "wof:placetype":"neighbourhood",
    "wof:population":1085
},
  "geometry": {"coordinates":[79.15052,9.931689],"type":"Point"}
}