{
  "type": "Feature",
  "properties": {
    "gn:admin1_code":"24",
    "gn:admin2_code":"105.0",
    "gn:asciiname":"Begpahari",
    "gn:country_code":"IN",
    "gn:dem":208,
    "gn:feature_class":"P",
    "gn:feature_code":"PPL",
    "gn:name":"Begpah\u0101ri",
    "gn:population":0,
    "gn:timezone":"Asia/Kolkata",
    "iso:country":"IN",
    "ks:ks_name":"Beg Pahari",
    "ks:ks_pop":453,
    "ks:ks_type":"VILLAGE",
    "ks:ks_uagg_main":0,
    "name:eng_x_preferred":[
        "Beg Pahari"
    ],
    "wof:name":"Beg Pahari",
    "wof:placetype":"neighbourhood",
    "wof:population":453
},
  "geometry": {"coordinates":[77.145094,27.549501],"type":"Point"}
}