{
  "type": "Feature",
  "properties": {
    "iso:country":"IN",
    "ks:ks_name":"Nallankulam",
    "ks:ks_pop":148,
    "ks:ks_type":"HABITATION",
    "name:eng_x_preferred":[
        "Nallankulam"
    ],
    "wof:name":"Nallankulam",
    "wof:placetype":"locality",
    "wof:population":148
},
  "geometry": {"coordinates":[78.49220800000001,9.424512],"type":"Point"}
}