{
  "type": "Feature",
  "properties": {
    "iso:country":"IN",
    "ks:ks_name":"Mudhon Ka Tala",
    "ks:ks_pop":203,
    "ks:ks_type":"VILLAGE",
    "name:eng_x_preferred":[
        "Mudhon Ka Tala"
    ],
    "wof:name":"Mudhon Ka Tala",
    "wof:placetype":"locality",
    "wof:population":203
},
  "geometry": {"coordinates":[71.232389,25.596275],"type":"Point"}
}