{
  "type": "Feature",
  "properties": {
    "iso:country":"IN",
    "ks:ks_alt_nam":"VELMUGANKUDIYIRUPPU",
    "ks:ks_name":"Velmugankudiyiruppu",
    "ks:ks_pop":302,
    "ks:ks_type":"HABITATION",
    "name:eng_x_preferred":[
        "Velmugankudiyiruppu"
    ],
    "wof:name":"Velmugankudiyiruppu",
    "wof:placetype":"locality",
    "wof:population":302
},
  "geometry": {"coordinates":[78.81643699999999,10.051394],"type":"Point"}
}