{
  "type": "Feature",
  "properties": {
    "iso:country":"IN",
    "ks:ks_name":"Radhanagar",
    "ks:ks_pop":81,
    "ks:ks_type":"VILLAGE",
    "name:eng_x_preferred":[
        "Radhanagar"
    ],
    "wof:name":"Radhanagar",
    "wof:placetype":"locality",
    "wof:population":81
},
  "geometry": {"coordinates":[88.05807900000001,24.144472],"type":"Point"}
}