{
  "type": "Feature",
  "properties": {
    "iso:country":"IN",
    "ks:ks_name":"Tatara",
    "ks:ks_pop":434,
    "ks:ks_type":"HABITATION",
    "name:eng_x_preferred":[
        "Tatara"
    ],
    "wof:name":"Tatara",
    "wof:placetype":"locality",
    "wof:population":434
},
  "geometry": {"coordinates":[78.527011,22.939249],"type":"Point"}
}