{
  "type": "Feature",
  "properties": {
    "gn:admin1_code":"30.0",
    "gn:admin2_code":"247",
    "gn:asciiname":"Kafi",
    "gn:country_code":"IN",
    "gn:dem":708,
    "gn:feature_class":"P",
    "gn:feature_code":"PPL",
    "gn:name":"Kafi",
    "gn:population":0,
    "gn:timezone":"Asia/Kolkata",
    "iso:country":"IN",
    "wof:name":"Kafi",
    "wof:placetype":"locality"
},
  "geometry": {"coordinates":[93.09999999999999,27.43333],"type":"Point"}
}