{
  "type": "Feature",
  "properties": {
    "iso:country":"IN",
    "ks:ks_name":"Workshop Jn",
    "ks:ks_pop":750,
    "ks:ks_type":"HABITATION",
    "name:eng_x_preferred":[
        "Workshop Jn"
    ],
    "wof:name":"Workshop Jn",
    "wof:placetype":"locality",
    "wof:population":750
},
  "geometry": {"coordinates":[76.855081,9.085165],"type":"Point"}
}