{
  "type": "Feature",
  "properties": {
    "iso:country":"IN",
    "ks:ks_name":"Nayakguda",
    "ks:ks_pop":255,
    "ks:ks_type":"HABITATION",
    "ks:ks_uagg_main":0,
    "name:eng_x_preferred":[
        "Nayakguda"
    ],
    "wof:name":"Nayakguda",
    "wof:placetype":"neighbourhood",
    "wof:population":255
},
  "geometry": {"coordinates":[82.649351,19.267748],"type":"Point"}
}