{
  "type": "Feature",
  "properties": {
    "iso:country":"IN",
    "ks:ks_name":"Putulingi",
    "ks:ks_pop":22,
    "ks:ks_type":"VILLAGE",
    "name:eng_x_preferred":[
        "Putulingi"
    ],
    "wof:name":"Putulingi",
    "wof:placetype":"locality",
    "wof:population":22
},
  "geometry": {"coordinates":[84.94359,19.745775],"type":"Point"}
}