{
  "type": "Feature",
  "properties": {
    "gn:admin1_code":"16.0",
    "gn:admin2_code":"501",
    "gn:asciiname":"Chani",
    "gn:country_code":"IN",
    "gn:dem":335,
    "gn:feature_class":"P",
    "gn:feature_code":"PPL",
    "gn:name":"Ch\u0101ni",
    "gn:population":0,
    "gn:timezone":"Asia/Kolkata",
    "iso:country":"IN",
    "name:bul_x_preferred":[
        "\u0427\u0430\u043d\u0438"
    ],
    "name:fra_x_preferred":[
        "Chani"
    ],
    "name:ita_x_preferred":[
        "Chani Kynes"
    ],
    "name:rus_x_preferred":[
        "\u0427\u0430\u043d\u0438"
    ],
    "name:spa_x_preferred":[
        "Chani"
    ],
    "name:und_x_variant":[
        "Chanyi",
        "Ch\u0101ni"
    ],
    "wof:name":"Chani",
    "wof:placetype":"locality"
},
  "geometry": {"coordinates":[76.77105999999998,20.46117000000001],"type":"Point"}
}