{
  "type": "Feature",
  "properties": {
    "iso:country":"IN",
    "ks:ks_name":"Shemiya",
    "ks:ks_pop":711,
    "ks:ks_type":"HABITATION",
    "name:eng_x_preferred":[
        "Shemiya"
    ],
    "wof:name":"Shemiya",
    "wof:placetype":"locality",
    "wof:population":711
},
  "geometry": {"coordinates":[82.845834,24.600713],"type":"Point"}
}