{
  "type": "Feature",
  "properties": {
    "gn:admin1_code":"35",
    "gn:admin2_code":"426.0",
    "gn:asciiname":"Jamuni",
    "gn:country_code":"IN",
    "gn:dem":364,
    "gn:feature_class":"P",
    "gn:feature_code":"PPL",
    "gn:name":"Jamuni",
    "gn:population":0,
    "gn:timezone":"Asia/Kolkata",
    "iso:country":"IN",
    "name:ceb_x_preferred":[
        "Jamuni"
    ],
    "name:fra_x_preferred":[
        "Jamuni"
    ],
    "name:mai_x_preferred":[
        "\u091c\u092e\u0941\u0928\u0940"
    ],
    "name:msa_x_preferred":[
        "Jamuni"
    ],
    "name:nep_x_preferred":[
        "\u091c\u092e\u0941\u0928\u0940"
    ],
    "name:new_x_preferred":[
        "\u091c\u092e\u0941\u0928\u0940"
    ],
    "name:pol_x_preferred":[
        "Jamuni"
    ],
    "name:urd_x_preferred":[
        "\u062c\u0645\u0646\u06cc"
    ],
    "wof:name":"Jamuni",
    "wof:placetype":"neighbourhood"
},
  "geometry": {"coordinates":[80.56833,24.85132],"type":"Point"}
}