{
  "type": "Feature",
  "properties": {
    "iso:country":"IN",
    "ks:ks_name":"Kurriha",
    "ks:ks_pop":925,
    "ks:ks_type":"HABITATION",
    "name:eng_x_preferred":[
        "Kurriha"
    ],
    "wof:name":"Kurriha",
    "wof:placetype":"locality",
    "wof:population":925
},
  "geometry": {"coordinates":[80.923402,23.317394],"type":"Point"}
}