{
  "type": "Feature",
  "properties": {
    "gn:admin1_code":"36",
    "gn:admin2_code":"191.0",
    "gn:asciiname":"Kalan",
    "gn:country_code":"IN",
    "gn:dem":95,
    "gn:feature_class":"P",
    "gn:feature_code":"PPL",
    "gn:name":"Kal\u0101n",
    "gn:population":0,
    "gn:timezone":"Asia/Kolkata",
    "iso:country":"IN",
    "ks:ks_alt_nam":"Kal\u0101n",
    "ks:ks_name":"Kalan",
    "ks:ks_type":"VILLAGE",
    "ks:ks_uagg_main":0,
    "name:ceb_x_preferred":[
        "Kalan"
    ],
    "name:deu_x_preferred":[
        "Kalan"
    ],
    "name:eng_x_preferred":[
        "Kalan"
    ],
    "name:eng_x_variant":[
        "Kal\u0101n"
    ],
    "name:fas_x_preferred":[
        "\u06a9\u0644\u0627\u0646"
    ],
    "name:fra_x_preferred":[
        "Kalan"
    ],
    "name:hrv_x_preferred":[
        "Kalan"
    ],
    "name:nld_x_preferred":[
        "Kalan"
    ],
    "name:rus_x_preferred":[
        "\u041a\u0430\u043b\u0430\u043d"
    ],
    "name:slv_x_preferred":[
        "Kalan"
    ],
    "name:swe_x_preferred":[
        "Kalan"
    ],
    "name:ukr_x_preferred":[
        "\u041a\u0430\u043b\u0430\u043d"
    ],
    "wof:name":"Kalan",
    "wof:placetype":"neighbourhood"
},
  "geometry": {"coordinates":[82.73902,26.215306],"type":"Point"}
}