{
  "type": "Feature",
  "properties": {
    "iso:country":"IN",
    "ks:ks_name":"Vaddinakoppa",
    "ks:ks_pop":65,
    "ks:ks_type":"HABITATION",
    "name:eng_x_preferred":[
        "Vaddinakoppa"
    ],
    "wof:name":"Vaddinakoppa",
    "wof:placetype":"locality",
    "wof:population":65
},
  "geometry": {"coordinates":[74.96516699999999,14.607013],"type":"Point"}
}