{
  "type": "Feature",
  "properties": {
    "iso:country":"IN",
    "ks:ks_alt_nam":"BARKI BARIZAN BASTI",
    "ks:ks_name":"Barki Barizan Basti",
    "ks:ks_pop":450,
    "ks:ks_type":"HABITATION",
    "name:eng_x_preferred":[
        "Barki Barizan Basti"
    ],
    "wof:name":"Barki Barizan Basti",
    "wof:placetype":"locality",
    "wof:population":450
},
  "geometry": {"coordinates":[83.87665800000001,26.077941],"type":"Point"}
}