{
  "type": "Feature",
  "properties": {
    "iso:country":"IN",
    "ks:ks_name":"Chaura Ama",
    "ks:ks_pop":653,
    "ks:ks_type":"VILLAGE",
    "name:eng_x_preferred":[
        "Chaura Ama"
    ],
    "wof:name":"Chaura Ama",
    "wof:placetype":"locality",
    "wof:population":653
},
  "geometry": {"coordinates":[83.56392099999999,22.585439],"type":"Point"}
}