{
  "type": "Feature",
  "properties": {
    "iso:country":"IN",
    "ks:ks_name":"Jhanjarpur",
    "ks:ks_pop":451,
    "ks:ks_type":"VILLAGE",
    "name:eng_x_preferred":[
        "Jhanjarpur"
    ],
    "wof:name":"Jhanjarpur",
    "wof:placetype":"locality",
    "wof:population":451
},
  "geometry": {"coordinates":[74.64581699999999,31.61176],"type":"Point"}
}