{
  "type": "Feature",
  "properties": {
    "iso:country":"IN",
    "ks:ks_name":"Kurlardoddi -1",
    "ks:ks_pop":130,
    "ks:ks_type":"HABITATION",
    "ks:ks_uagg_main":0,
    "name:eng_x_preferred":[
        "Kurlardoddi -1"
    ],
    "wof:name":"Kurlardoddi -1",
    "wof:placetype":"neighbourhood",
    "wof:population":130
},
  "geometry": {"coordinates":[76.945617,16.206921],"type":"Point"}
}