{
  "type": "Feature",
  "properties": {
    "iso:country":"IN",
    "ks:ks_name":"Nizbargaon",
    "ks:ks_pop":592,
    "ks:ks_type":"VILLAGE",
    "ks:ks_uagg_main":0,
    "name:eng_x_preferred":[
        "Nizbargaon"
    ],
    "wof:name":"Nizbargaon",
    "wof:placetype":"neighbourhood",
    "wof:population":592
},
  "geometry": {"coordinates":[92.571483,26.665272],"type":"Point"}
}