{
  "type": "Feature",
  "properties": {
    "iso:country":"IN",
    "ks:ks_alt_nam":"kunjalankunnu",
    "ks:ks_name":"Kunjalankunnu",
    "ks:ks_pop":130,
    "ks:ks_type":"HABITATION",
    "name:eng_x_preferred":[
        "Kunjalankunnu"
    ],
    "wof:name":"Kunjalankunnu",
    "wof:placetype":"locality",
    "wof:population":130
},
  "geometry": {"coordinates":[76.36394,11.540186],"type":"Point"}
}