{
  "type": "Feature",
  "properties": {
    "gn:admin1_code":"23.0",
    "gn:admin2_code":"43.0",
    "gn:asciiname":"Rukan Shahwala",
    "gn:country_code":"IN",
    "gn:dem":202,
    "gn:feature_class":"P",
    "gn:feature_code":"PPL",
    "gn:name":"Rukan Sh\u0101hw\u0101la",
    "gn:population":0,
    "gn:timezone":"Asia/Kolkata",
    "iso:country":"IN",
    "name:und_x_variant":[
        "Rukan Sh\u0101hw\u0101la",
        "Saiyid\u0101nw\u0101la"
    ],
    "wof:name":"Rukan Shahwala",
    "wof:placetype":"locality"
},
  "geometry": {"coordinates":[74.75828,30.96692],"type":"Point"}
}