{
  "type": "Feature",
  "properties": {
    "gn:admin1_code":"11",
    "gn:admin2_code":"23.0",
    "gn:asciiname":"Kor Rei",
    "gn:country_code":"IN",
    "gn:dem":2897,
    "gn:feature_class":"P",
    "gn:feature_code":"PPL",
    "gn:name":"Kor Rei",
    "gn:population":0,
    "gn:timezone":"Asia/Kolkata",
    "iso:country":"IN",
    "wof:name":"Kor Rei",
    "wof:placetype":"locality"
},
  "geometry": {"coordinates":[76.46111999999999,32.95556],"type":"Point"}
}