{
  "type": "Feature",
  "properties": {
    "gn:admin1_code":"37",
    "gn:admin2_code":"414.0",
    "gn:asciiname":"Dandargarh",
    "gn:country_code":"IN",
    "gn:dem":473,
    "gn:feature_class":"P",
    "gn:feature_code":"PPL",
    "gn:name":"D\u0101ndargarh",
    "gn:population":0,
    "gn:timezone":"Asia/Kolkata",
    "iso:country":"IN",
    "ks:ks_name":"Dadargarh",
    "ks:ks_pop":146,
    "ks:ks_type":"VILLAGE",
    "name:eng_x_preferred":[
        "Dadargarh"
    ],
    "name:eng_x_variant":[
        "Dandargarh"
    ],
    "wof:name":"Dadargarh",
    "wof:placetype":"locality",
    "wof:population":146
},
  "geometry": {"coordinates":[81.560158,20.127912],"type":"Point"}
}