{
  "type": "Feature",
  "properties": {
    "iso:country":"IN",
    "ks:ks_name":"Katuru",
    "ks:ks_pop":246,
    "ks:ks_type":"VILLAGE",
    "name:eng_x_preferred":[
        "Katuru"
    ],
    "wof:name":"Katuru",
    "wof:placetype":"locality",
    "wof:population":246
},
  "geometry": {"coordinates":[83.951267,18.833761],"type":"Point"}
}