{
  "type": "Feature",
  "properties": {
    "iso:country":"IN",
    "ks:ks_name":"Daldala",
    "ks:ks_pop":494,
    "ks:ks_type":"VILLAGE",
    "ks:ks_uagg_main":0,
    "name:eng_x_preferred":[
        "Daldala"
    ],
    "wof:name":"Daldala",
    "wof:placetype":"neighbourhood",
    "wof:population":494
},
  "geometry": {"coordinates":[86.617124,24.047972],"type":"Point"}
}