{
  "type": "Feature",
  "properties": {
    "gn:admin1_code":"13.0",
    "gn:admin2_code":"590.0",
    "gn:asciiname":"Ollancheri",
    "gn:country_code":"IN",
    "gn:dem":755,
    "gn:feature_class":"P",
    "gn:feature_code":"PPL",
    "gn:name":"Ollanch\u0113ri",
    "gn:population":0,
    "gn:timezone":"Asia/Kolkata",
    "iso:country":"IN",
    "wof:name":"Ollancheri",
    "wof:placetype":"locality"
},
  "geometry": {"coordinates":[76.05391,11.86104],"type":"Point"}
}