{
  "type": "Feature",
  "properties": {
    "gn:country":"IN",
    "gn:fcode":"PPL",
    "gn:pop":40113,
    "iso:country":"IN",
    "name:ben_x_preferred":[
        "\u099f\u09be\u0995\u09bf"
    ],
    "name:bpy_x_preferred":[
        "\u099f\u09be\u0995\u09c0"
    ],
    "name:eng_x_preferred":[
        "Taki"
    ],
    "name:fra_x_preferred":[
        "Taki"
    ],
    "name:ita_x_preferred":[
        "Taki"
    ],
    "name:nld_x_preferred":[
        "Taki"
    ],
    "name:ori_x_preferred":[
        "\u0b24\u0b3e\u0b15\u0b3f"
    ],
    "name:rus_x_preferred":[
        "\u0422\u0430\u043a\u043e\u0439"
    ],
    "name:spa_x_preferred":[
        "Taki"
    ],
    "name:swe_x_preferred":[
        "T\u0101ki"
    ],
    "name:unk_x_variant":[
        "T\u0101ki"
    ],
    "name:urd_x_preferred":[
        "\u062a\u0627\u06a9\u06cc"
    ],
    "qs:name":"Taki",
    "qs:name_adm0":"India",
    "qs:name_adm1":"West Bengal",
    "qs:photos":59,
    "qs:photos_1k":12,
    "qs:photos_9k":1,
    "qs:photos_9r":2,
    "qs:photos_all":59,
    "qs:photos_sr":2,
    "qs:placetype":"Town",
    "qs:pop_sr":"7",
    "wd:wordcount":167,
    "wof:name":"Taki",
    "wof:placetype":"locality",
    "wof:population":40113
},
  "geometry": {"coordinates":[88.93253,22.58868],"type":"Point"}
}