{
  "type": "Feature",
  "properties": {
    "iso:country":"IN",
    "ks:ks_name":"Gajulapalle",
    "ks:ks_pop":69,
    "ks:ks_type":"HABITATION",
    "name:eng_x_preferred":[
        "Gajulapalle"
    ],
    "wof:name":"Gajulapalle",
    "wof:placetype":"locality",
    "wof:population":69
},
  "geometry": {"coordinates":[78.54301700000001,13.963952],"type":"Point"}
}