{
  "type": "Feature",
  "properties": {
    "iso:country":"IN",
    "ks:ks_name":"Haladiaguna",
    "ks:ks_pop":289,
    "ks:ks_type":"VILLAGE",
    "ks:ks_uagg_main":0,
    "name:eng_x_preferred":[
        "Haladiaguna"
    ],
    "wof:name":"Haladiaguna",
    "wof:placetype":"neighbourhood",
    "wof:population":289
},
  "geometry": {"coordinates":[85.58663199999999,21.763758],"type":"Point"}
}