{
  "type": "Feature",
  "properties": {
    "iso:country":"IN",
    "ks:ks_name":"Kusbana",
    "ks:ks_pop":386,
    "ks:ks_type":"VILLAGE",
    "name:eng_x_preferred":[
        "Kusbana"
    ],
    "wof:name":"Kusbana",
    "wof:placetype":"locality",
    "wof:population":386
},
  "geometry": {"coordinates":[87.326452,24.504429],"type":"Point"}
}