{
  "type": "Feature",
  "properties": {
    "iso:country":"IN",
    "ks:ks_name":"Hundyapada",
    "ks:ks_pop":1536,
    "ks:ks_type":"HABITATION",
    "name:eng_x_preferred":[
        "Hundyapada"
    ],
    "wof:name":"Hundyapada",
    "wof:placetype":"locality",
    "wof:population":1536
},
  "geometry": {"coordinates":[74.14546900000001,21.895001],"type":"Point"}
}