{
  "type": "Feature",
  "properties": {
    "iso:country":"IN",
    "ks:ks_alt_nam":"Kanyana HSC Hebri",
    "ks:ks_name":"Kanyana Hsc Hebri",
    "ks:ks_pop":149,
    "ks:ks_type":"HABITATION",
    "name:eng_x_preferred":[
        "Kanyana Hsc Hebri"
    ],
    "wof:name":"Kanyana Hsc Hebri",
    "wof:placetype":"locality",
    "wof:population":149
},
  "geometry": {"coordinates":[74.975239,13.449805],"type":"Point"}
}