{
  "type": "Feature",
  "properties": {
    "iso:country":"IN",
    "ks:ks_name":"Sutarwadi",
    "ks:ks_pop":21,
    "ks:ks_type":"HABITATION",
    "name:eng_x_preferred":[
        "Sutarwadi"
    ],
    "wof:name":"Sutarwadi",
    "wof:placetype":"locality",
    "wof:population":21
},
  "geometry": {"coordinates":[73.595513,16.032177],"type":"Point"}
}