{
  "type": "Feature",
  "properties": {
    "gn:admin1_code":"36.0",
    "gn:admin2_code":"149.0",
    "gn:asciiname":"Khera Buzurg",
    "gn:country_code":"IN",
    "gn:dem":174,
    "gn:feature_class":"P",
    "gn:feature_code":"PPL",
    "gn:name":"Khera Buzurg",
    "gn:population":0,
    "gn:timezone":"Asia/Kolkata",
    "iso:country":"IN",
    "wof:name":"Khera Buzurg",
    "wof:placetype":"locality"
},
  "geometry": {"coordinates":[79.13785,28.0517],"type":"Point"}
}