{
  "type": "Feature",
  "properties": {
    "gn:admin1_code":"23.0",
    "gn:admin2_code":"48.0",
    "gn:asciiname":"Rajgarh",
    "gn:country_code":"IN",
    "gn:dem":249,
    "gn:feature_class":"P",
    "gn:feature_code":"PPL",
    "gn:name":"R\u0101jgarh",
    "gn:population":0,
    "gn:timezone":"Asia/Kolkata",
    "iso:country":"IN",
    "name:ara_x_preferred":[
        "\u0631\u0627\u062c \u062c\u0627\u0631\u0647"
    ],
    "name:ben_bn_x_preferred":[
        "\u09b0\u09be\u099c\u0997\u09a1\u09bc"
    ],
    "name:ben_in_x_preferred":[
        "\u09b0\u09be\u099c\u0997\u09a1\u09bc"
    ],
    "name:deu_x_preferred":[
        "Rajgarh"
    ],
    "name:guj_x_preferred":[
        "\u0ab0\u0abe\u0a9c\u0a97\u0aa2"
    ],
    "name:hin_x_preferred":[
        "\u0930\u093e\u091c\u0917\u095d"
    ],
    "name:ita_x_preferred":[
        "Rajgarh"
    ],
    "name:kan_x_preferred":[
        "\u0cb0\u0cbe\u0c9c\u0ccd"
    ],
    "name:mal_x_preferred":[
        "\u0d30\u0d3e\u0d1c\u0d4d\u0d17\u0d21\u0d4d"
    ],
    "name:mar_x_preferred":[
        "\u0930\u093e\u091c\u0917\u0921"
    ],
    "name:nld_x_preferred":[
        "Rajgarh"
    ],
    "name:pan_x_preferred":[
        "\u0a30\u0a3e\u0a1c\u0a17\u0a5c\u0a4d\u0a39"
    ],
    "name:pol_x_preferred":[
        "Rajgarh"
    ],
    "name:por_x_preferred":[
        "Rajgarh"
    ],
    "name:tam_x_preferred":[
        "\u0bb0\u0bbe\u0b9c\u0bcd\u0b95\u0bb0\u0bcd"
    ],
    "name:tel_x_preferred":[
        "\u0c30\u0c3e\u0c1c\u0c4d"
    ],
    "name:urd_x_preferred":[
        "\u0631\u0627\u062c \u06af\u0691\u06be"
    ],
    "name:urd_x_variant":[
        "\u0631\u0627\u062c\u06af\u0691\u06be"
    ],
    "wof:name":"Rajgarh",
    "wof:placetype":"locality"
},
  "geometry": {"coordinates":[76.13712,30.4401],"type":"Point"}
}