{
  "type": "Feature",
  "properties": {
    "gn:admin1_code":"40.0",
    "gn:admin2_code":"532.0",
    "gn:asciiname":"Bambaigura",
    "gn:country_code":"IN",
    "gn:dem":143,
    "gn:feature_class":"P",
    "gn:feature_code":"PPL",
    "gn:name":"Bambaigura",
    "gn:population":0,
    "gn:timezone":"Asia/Kolkata",
    "iso:country":"IN",
    "ks:ks_alt_nam":"Bambaigura",
    "ks:ks_name":"Bombaiguda",
    "ks:ks_pop":1188,
    "ks:ks_type":"VILLAGE",
    "name:eng_x_preferred":[
        "Bombaiguda"
    ],
    "name:eng_x_variant":[
        "Bambaigura"
    ],
    "wof:name":"Bombaiguda",
    "wof:placetype":"locality",
    "wof:population":1188
},
  "geometry": {"coordinates":[79.722015,19.280308],"type":"Point"}
}