{
  "type": "Feature",
  "properties": {
    "gn:admin1_code":"39.0",
    "gn:admin2_code":"60.0",
    "gn:asciiname":"Kwarna",
    "gn:country_code":"IN",
    "gn:dem":1132,
    "gn:feature_class":"P",
    "gn:feature_code":"PPL",
    "gn:name":"Kw\u0101rna",
    "gn:population":0,
    "gn:timezone":"Asia/Kolkata",
    "iso:country":"IN",
    "wof:name":"Kwarna",
    "wof:placetype":"locality"
},
  "geometry": {"coordinates":[77.7894,30.68927],"type":"Point"}
}