{
  "type": "Feature",
  "properties": {
    "iso:country":"IN",
    "ks:ks_name":"Dhelua",
    "ks:ks_pop":476,
    "ks:ks_type":"VILLAGE",
    "name:eng_x_preferred":[
        "Dhelua"
    ],
    "wof:name":"Dhelua",
    "wof:placetype":"locality",
    "wof:population":476
},
  "geometry": {"coordinates":[83.938532,23.869971],"type":"Point"}
}