{
  "type": "Feature",
  "properties": {
    "gn:admin1_code":"25.0",
    "gn:admin2_code":"633.0",
    "gn:asciiname":"Rangakavundanpalaiyam",
    "gn:country_code":"IN",
    "gn:dem":326,
    "gn:feature_class":"P",
    "gn:feature_code":"PPL",
    "gn:name":"Rangakavundanp\u0101laiyam",
    "gn:population":0,
    "gn:timezone":"Asia/Kolkata",
    "iso:country":"IN",
    "wof:name":"Rangakavundanpalaiyam",
    "wof:placetype":"locality"
},
  "geometry": {"coordinates":[77.39574,11.06871],"type":"Point"}
}