{
  "type": "Feature",
  "properties": {
    "gn:admin1_code":"34.0",
    "gn:admin2_code":"207.0",
    "gn:asciiname":"Barhi",
    "gn:country_code":"IN",
    "gn:dem":67,
    "gn:feature_class":"P",
    "gn:feature_code":"PPL",
    "gn:name":"Barhi",
    "gn:population":0,
    "gn:timezone":"Asia/Kolkata",
    "iso:country":"IN",
    "name:nld_x_preferred":[
        "Barhi"
    ],
    "wof:name":"Barhi",
    "wof:placetype":"neighbourhood"
},
  "geometry": {"coordinates":[85.92973000000001,26.55866],"type":"Point"}
}