{
  "type": "Feature",
  "properties": {
    "iso:country":"IN",
    "ks:ks_alt_nam":"Andavar\u0101yapuram",
    "ks:ks_name":"Andavarayapuram",
    "ks:ks_pop":430,
    "ks:ks_type":"VILLAGE",
    "name:eng_x_preferred":[
        "Andavarayapuram"
    ],
    "name:eng_x_variant":[
        "Andavar\u0101yapuram"
    ],
    "wof:name":"Andavarayapuram",
    "wof:placetype":"locality",
    "wof:population":430
},
  "geometry": {"coordinates":[79.108298,10.355733],"type":"Point"}
}