{
  "type": "Feature",
  "properties": {
    "gn:admin1_code":"09",
    "gn:admin2_code":"468.0",
    "gn:asciiname":"Matanomadh",
    "gn:country_code":"IN",
    "gn:dem":96,
    "gn:feature_class":"P",
    "gn:feature_code":"PPL",
    "gn:name":"M\u0101t\u0101nomadh",
    "gn:population":0,
    "gn:timezone":"Asia/Kolkata",
    "iso:country":"IN",
    "wof:name":"Matanomadh",
    "wof:placetype":"locality"
},
  "geometry": {"coordinates":[68.94884,23.54261],"type":"Point"}
}