{
  "type": "Feature",
  "properties": {
    "iso:country":"IN",
    "ks:ks_name":"Addagadde",
    "ks:ks_pop":788,
    "ks:ks_type":"VILLAGE",
    "name:eng_x_preferred":[
        "Addagadde"
    ],
    "wof:name":"Addagadde",
    "wof:placetype":"locality",
    "wof:population":788
},
  "geometry": {"coordinates":[75.306855,13.456574],"type":"Point"}
}