{
  "type": "Feature",
  "properties": {
    "gn:admin1_code":"13.0",
    "gn:admin2_code":"599.0",
    "gn:asciiname":"Omallur",
    "gn:country_code":"IN",
    "gn:dem":23,
    "gn:feature_class":"P",
    "gn:feature_code":"PPL",
    "gn:name":"Omall\u016br",
    "gn:population":0,
    "gn:timezone":"Asia/Kolkata",
    "iso:country":"IN",
    "name:mal_x_preferred":[
        "\u0d13\u0d2e\u0d32\u0d4d\u0d32\u0d42\u0d7c"
    ],
    "wof:name":"Omallur",
    "wof:placetype":"locality"
},
  "geometry": {"coordinates":[76.7577,9.2474],"type":"Point"}
}