{
  "type": "Feature",
  "properties": {
    "iso:country":"IN",
    "ks:ks_name":"Keteki",
    "ks:ks_pop":50,
    "ks:ks_type":"HABITATION",
    "name:eng_x_preferred":[
        "Keteki"
    ],
    "wof:name":"Keteki",
    "wof:placetype":"locality",
    "wof:population":50
},
  "geometry": {"coordinates":[91.10875900000001,26.24376],"type":"Point"}
}