{
  "type": "Feature",
  "properties": {
    "iso:country":"IN",
    "ks:ks_name":"Ganjaguda",
    "ks:ks_pop":236,
    "ks:ks_type":"VILLAGE",
    "name:eng_x_preferred":[
        "Ganjaguda"
    ],
    "wof:name":"Ganjaguda",
    "wof:placetype":"locality",
    "wof:population":236
},
  "geometry": {"coordinates":[83.160884,21.094327],"type":"Point"}
}