{
  "type": "Feature",
  "properties": {
    "iso:country":"IN",
    "ks:ks_name":"Kaklaibari",
    "ks:ks_pop":248,
    "ks:ks_type":"HABITATION",
    "name:eng_x_preferred":[
        "Kaklaibari"
    ],
    "wof:name":"Kaklaibari",
    "wof:placetype":"locality",
    "wof:population":248
},
  "geometry": {"coordinates":[91.60405,23.435175],"type":"Point"}
}