{
  "type": "Feature",
  "properties": {
    "iso:country":"IN",
    "ks:ks_name":"Papoli",
    "ks:ks_pop":558,
    "ks:ks_type":"VILLAGE",
    "name:eng_x_preferred":[
        "Papoli"
    ],
    "wof:name":"Papoli",
    "wof:placetype":"locality",
    "wof:population":558
},
  "geometry": {"coordinates":[80.014079,29.532636],"type":"Point"}
}