{
  "type": "Feature",
  "properties": {
    "gn:admin1_code":"11.0",
    "gn:admin2_code":"33.0",
    "gn:asciiname":"Nohan",
    "gn:country_code":"IN",
    "gn:dem":1168,
    "gn:feature_class":"P",
    "gn:feature_code":"PPL",
    "gn:name":"Nohan",
    "gn:population":0,
    "gn:timezone":"Asia/Kolkata",
    "iso:country":"IN",
    "wof:name":"Nohan",
    "wof:placetype":"locality"
},
  "geometry": {"coordinates":[77.26963000000001,30.94757],"type":"Point"}
}