{
  "type": "Feature",
  "properties": {
    "iso:country":"IN",
    "ks:ks_name":"Hajari Gurha",
    "ks:ks_pop":2702,
    "ks:ks_type":"HABITATION",
    "name:eng_x_preferred":[
        "Hajari Gurha"
    ],
    "wof:name":"Hajari Gurha",
    "wof:placetype":"locality",
    "wof:population":2702
},
  "geometry": {"coordinates":[74.483064,23.938228],"type":"Point"}
}