{
  "type": "Feature",
  "properties": {
    "iso:country":"IN",
    "ks:ks_name":"Kariyampali",
    "ks:ks_pop":169,
    "ks:ks_type":"VILLAGE",
    "name:eng_x_preferred":[
        "Kariyampali"
    ],
    "wof:name":"Kariyampali",
    "wof:placetype":"locality",
    "wof:population":169
},
  "geometry": {"coordinates":[74.668356,15.235939],"type":"Point"}
}