{
  "type": "Feature",
  "properties": {
    "iso:country":"IN",
    "ks:ks_name":"Thoke",
    "ks:ks_pop":243,
    "ks:ks_type":"HABITATION",
    "name:eng_x_preferred":[
        "Thoke"
    ],
    "wof:name":"Thoke",
    "wof:placetype":"locality",
    "wof:population":243
},
  "geometry": {"coordinates":[74.78601,13.122568],"type":"Point"}
}