{
  "type": "Feature",
  "properties": {
    "iso:country":"IN",
    "ks:ks_alt_nam":"SutarJadhav",
    "ks:ks_name":"Sutarjadhav",
    "ks:ks_pop":64,
    "ks:ks_type":"HABITATION",
    "name:eng_x_preferred":[
        "Sutarjadhav"
    ],
    "wof:name":"Sutarjadhav",
    "wof:placetype":"locality",
    "wof:population":64
},
  "geometry": {"coordinates":[75.744902,18.508006],"type":"Point"}
}