{
  "type": "Feature",
  "properties": {
    "iso:country":"IN",
    "ks:ks_name":"Gonerchak",
    "ks:ks_pop":864,
    "ks:ks_type":"HABITATION",
    "name:eng_x_preferred":[
        "Gonerchak"
    ],
    "wof:name":"Gonerchak",
    "wof:placetype":"locality",
    "wof:population":864
},
  "geometry": {"coordinates":[87.151383,25.031016],"type":"Point"}
}