{
  "type": "Feature",
  "properties": {
    "iso:country":"IN",
    "ks:ks_name":"Arbettu",
    "ks:ks_pop":61,
    "ks:ks_type":"HABITATION",
    "name:eng_x_preferred":[
        "Arbettu"
    ],
    "wof:name":"Arbettu",
    "wof:placetype":"locality",
    "wof:population":61
},
  "geometry": {"coordinates":[74.776516,13.239734],"type":"Point"}
}