{
  "type": "Feature",
  "properties": {
    "iso:country":"IN",
    "ks:ks_name":"Dubbathanda",
    "ks:ks_pop":145,
    "ks:ks_type":"HABITATION",
    "name:eng_x_preferred":[
        "Dubbathanda"
    ],
    "wof:name":"Dubbathanda",
    "wof:placetype":"locality",
    "wof:population":145
},
  "geometry": {"coordinates":[79.56393,17.456184],"type":"Point"}
}