{
  "type": "Feature",
  "properties": {
    "iso:country":"IN",
    "ks:ks_name":"Saharapara",
    "ks:ks_pop":330,
    "ks:ks_type":"VILLAGE",
    "name:eng_x_preferred":[
        "Saharapara"
    ],
    "wof:name":"Saharapara",
    "wof:placetype":"locality",
    "wof:population":330
},
  "geometry": {"coordinates":[87.262107,21.836917],"type":"Point"}
}