{
  "type": "Feature",
  "properties": {
    "gn:country":"IN",
    "gn:fcode":"PPL",
    "gn:population":15422,
    "iso:country":"IN",
    "name:ben_x_preferred":[
        "\u09a4\u09c0\u09b0\u09cd\u09a5\u09b9\u09be\u09b2\u09cd\u09b2\u09bf"
    ],
    "name:bpy_x_preferred":[
        "\u09a4\u09c0\u09b0\u09cd\u09a5\u09b9\u09be\u09b2\u09cd\u09b2\u09bf"
    ],
    "name:ceb_x_preferred":[
        "T\u012brthahalli"
    ],
    "name:eng_x_preferred":[
        "Thirthahalli"
    ],
    "name:ita_x_preferred":[
        "Tirthahalli"
    ],
    "name:jpn_x_preferred":[
        "\u30c6\u30a3\u30eb\u30bf\u30cf\u30ea"
    ],
    "name:kan_x_preferred":[
        "\u0ca4\u0cc0\u0cb0\u0ccd\u0ca5\u0cb9\u0cb3\u0ccd\u0cb3\u0cbf"
    ],
    "name:msa_x_preferred":[
        "Tirthahalli"
    ],
    "name:nan_x_preferred":[
        "Tirthahalli"
    ],
    "name:nld_x_preferred":[
        "Tirthahalli"
    ],
    "name:pam_x_preferred":[
        "Thirthahalli"
    ],
    "name:por_x_preferred":[
        "Tirthahalli"
    ],
    "name:san_x_preferred":[
        "\u0924\u0940\u0930\u094d\u0925\u0939\u0933\u094d\u0933\u0940"
    ],
    "name:swe_x_preferred":[
        "T\u012brthahalli"
    ],
    "name:tcy_x_preferred":[
        "\u0ca4\u0cc0\u0cb0\u0ccd\u0ca5\u0cb9\u0cb3\u0ccd\u0cb3\u0cbf"
    ],
    "name:vie_x_preferred":[
        "Tirthahalli"
    ],
    "name:zho_x_preferred":[
        "\u8482\u5c14\u5854\u54c8\u5c14\u5229"
    ],
    "qs:name":"T\u012brthahalli",
    "qs:photos_9r":0,
    "qs:photos_sr":0,
    "qs:pop_sr":"6",
    "wd:wordcount":1825,
    "wof:name":"T\u012brthahalli",
    "wof:placetype":"locality",
    "wof:population":15422
},
  "geometry": {"coordinates":[75.24548,13.68835],"type":"Point"}
}