{
  "type": "Feature",
  "properties": {
    "gn:admin1_code":"25.0",
    "gn:admin2_code":"619.0",
    "gn:asciiname":"Kiralattur",
    "gn:country_code":"IN",
    "gn:dem":8,
    "gn:feature_class":"P",
    "gn:feature_code":"PPL",
    "gn:name":"K\u012br\u0101latt\u016br",
    "gn:population":0,
    "gn:timezone":"Asia/Kolkata",
    "iso:country":"IN",
    "wof:name":"Kiralattur",
    "wof:placetype":"locality"
},
  "geometry": {"coordinates":[79.62406,10.64254],"type":"Point"}
}