{
  "type": "Feature",
  "properties": {
    "iso:country":"IN",
    "ks:ks_name":"Bagijhola",
    "ks:ks_pop":120,
    "ks:ks_type":"HABITATION",
    "name:eng_x_preferred":[
        "Bagijhola"
    ],
    "wof:name":"Bagijhola",
    "wof:placetype":"locality",
    "wof:population":120
},
  "geometry": {"coordinates":[82.026979,18.533774],"type":"Point"}
}