{
  "type": "Feature",
  "properties": {
    "iso:country":"IN",
    "ks:ks_alt_nam":"D\u016bja Ghewara",
    "ks:ks_alt_nam_2":"Duja Ghewara",
    "ks:ks_name":"Duja Ghewra",
    "ks:ks_pop":0,
    "ks:ks_type":"VILLAGE",
    "name:eng_x_preferred":[
        "Duja Ghewra"
    ],
    "name:eng_x_variant":[
        "D\u016bja Ghewara",
        "Duja Ghewara"
    ],
    "wof:name":"Duja Ghewra",
    "wof:placetype":"locality",
    "wof:population":0
},
  "geometry": {"coordinates":[83.948719,25.218623],"type":"Point"}
}