{
  "type": "Feature",
  "properties": {
    "iso:country":"IN",
    "ks:ks_name":"Barjasar",
    "ks:ks_pop":912,
    "ks:ks_type":"VILLAGE",
    "name:eng_x_preferred":[
        "Barjasar"
    ],
    "wof:name":"Barjasar",
    "wof:placetype":"locality",
    "wof:population":912
},
  "geometry": {"coordinates":[72.76276900000001,27.163219],"type":"Point"}
}