{
  "type": "Feature",
  "properties": {
    "iso:country":"IN",
    "ks:ks_name":"Mahabuang",
    "ks:ks_pop":624,
    "ks:ks_type":"HABITATION",
    "name:eng_x_preferred":[
        "Mahabuang"
    ],
    "wof:name":"Mahabuang",
    "wof:placetype":"locality",
    "wof:population":624
},
  "geometry": {"coordinates":[84.963702,22.730511],"type":"Point"}
}