{
  "type": "Feature",
  "properties": {
    "iso:country":"IN",
    "ks:ks_name":"Matia",
    "ks:ks_pop":279,
    "ks:ks_type":"HABITATION",
    "name:eng_x_preferred":[
        "Matia"
    ],
    "wof:name":"Matia",
    "wof:placetype":"locality",
    "wof:population":279
},
  "geometry": {"coordinates":[79.032759,22.639531],"type":"Point"}
}