{
  "type": "Feature",
  "properties": {
    "iso:country":"IN",
    "ks:ks_name":"Kuwarelwadi",
    "ks:ks_pop":67,
    "ks:ks_type":"HABITATION",
    "name:eng_x_preferred":[
        "Kuwarelwadi"
    ],
    "wof:name":"Kuwarelwadi",
    "wof:placetype":"locality",
    "wof:population":67
},
  "geometry": {"coordinates":[73.59999999999999,17.14],"type":"Point"}
}