{
  "type": "Feature",
  "properties": {
    "gn:admin1_code":"36",
    "gn:admin2_code":"193.0",
    "gn:asciiname":"Kaithi Khurd",
    "gn:country_code":"IN",
    "gn:dem":71,
    "gn:feature_class":"P",
    "gn:feature_code":"PPL",
    "gn:name":"Kaith\u012b Khurd",
    "gn:population":0,
    "gn:timezone":"Asia/Kolkata",
    "iso:country":"IN",
    "ks:ks_alt_nam":"Kaith\u012b Khurd",
    "ks:ks_name":"Kaithi Khurd",
    "ks:ks_type":"VILLAGE",
    "name:eng_x_preferred":[
        "Kaithi Khurd"
    ],
    "name:eng_x_variant":[
        "Kaith\u012b Khurd"
    ],
    "wof:name":"Kaithi Khurd",
    "wof:placetype":"locality"
},
  "geometry": {"coordinates":[83.90504,25.903524],"type":"Point"}
}