{
  "type": "Feature",
  "properties": {
    "iso:country":"IN",
    "ks:ks_name":"Naranpura",
    "ks:ks_pop":1149,
    "ks:ks_type":"HABITATION",
    "name:eng_x_preferred":[
        "Naranpura"
    ],
    "wof:name":"Naranpura",
    "wof:placetype":"locality",
    "wof:population":1149
},
  "geometry": {"coordinates":[71.9798,23.764388],"type":"Point"}
}