{
  "type": "Feature",
  "properties": {
    "gn:admin1_code":"36.0",
    "gn:admin2_code":"183.0",
    "gn:asciiname":"Purwa Suraj Bakhsh Singh",
    "gn:country_code":"IN",
    "gn:dem":99,
    "gn:feature_class":"P",
    "gn:feature_code":"PPL",
    "gn:name":"Purwa Suraj Bakhsh Singh",
    "gn:population":0,
    "gn:timezone":"Asia/Kolkata",
    "iso:country":"IN",
    "wof:name":"Purwa Suraj Bakhsh Singh",
    "wof:placetype":"neighbourhood"
},
  "geometry": {"coordinates":[82.20182,26.89223],"type":"Point"}
}