{
  "type": "Feature",
  "properties": {
    "iso:country":"IN",
    "ks:ks_name":"Siuri",
    "ks:ks_pop":163,
    "ks:ks_type":"VILLAGE",
    "ks:ks_uagg_main":0,
    "name:ben_x_preferred":[
        "\u09b8\u09bf\u0989\u09b0\u09bf"
    ],
    "name:eng_x_preferred":[
        "Siuri"
    ],
    "name:hin_x_preferred":[
        "\u0938\u093f\u0909\u0930\u0940"
    ],
    "wof:name":"Siuri",
    "wof:placetype":"neighbourhood",
    "wof:population":163
},
  "geometry": {"coordinates":[83.741478,26.333521],"type":"Point"}
}