{
  "type": "Feature",
  "properties": {
    "iso:country":"IN",
    "ks:ks_name":"Siuri",
    "ks:ks_pop":163,
    "ks:ks_type":"VILLAGE",
    "ks:ks_uagg_main":0,
    "name:eng_x_preferred":[
        "Siuri"
    ],
    "wof:name":"Siuri",
    "wof:placetype":"neighbourhood",
    "wof:population":163
},
  "geometry": {"coordinates":[83.741478,26.333521],"type":"Point"}
}