{
  "type": "Feature",
  "properties": {
    "iso:country":"IN",
    "ks:ks_name":"Dharapara",
    "ks:ks_pop":719,
    "ks:ks_type":"HABITATION",
    "ks:ks_uagg_main":0,
    "name:eng_x_preferred":[
        "Dharapara"
    ],
    "wof:name":"Dharapara",
    "wof:placetype":"neighbourhood",
    "wof:population":719
},
  "geometry": {"coordinates":[88.030801,22.411586],"type":"Point"}
}