{
  "type": "Feature",
  "properties": {
    "gn:admin1_code":"24.0",
    "gn:admin2_code":"115.0",
    "gn:asciiname":"Bhilon ki Dhani",
    "gn:country_code":"IN",
    "gn:dem":170,
    "gn:feature_class":"P",
    "gn:feature_code":"PPL",
    "gn:name":"Bhilon ki Dhani",
    "gn:population":0,
    "gn:timezone":"Asia/Karachi",
    "iso:country":"IN",
    "wof:name":"Bhilon ki Dhani",
    "wof:placetype":"locality"
},
  "geometry": {"coordinates":[70.61877,25.71611],"type":"Point"}
}