{
  "type": "Feature",
  "properties": {
    "gn:admin1_code":"19.0",
    "gn:admin2_code":"573.0",
    "gn:asciiname":"Haluvadi",
    "gn:country_code":"IN",
    "gn:dem":679,
    "gn:feature_class":"P",
    "gn:feature_code":"PPL",
    "gn:name":"Haluv\u0101di",
    "gn:population":0,
    "gn:timezone":"Asia/Kolkata",
    "iso:country":"IN",
    "wof:name":"Haluvadi",
    "wof:placetype":"locality"
},
  "geometry": {"coordinates":[76.90249,12.48952],"type":"Point"}
}