{
  "type": "Feature",
  "properties": {
    "iso:country":"IN",
    "ks:ks_name":"Bibitalapara",
    "ks:ks_pop":744,
    "ks:ks_type":"HABITATION",
    "ks:ks_uagg_main":0,
    "name:eng_x_preferred":[
        "Bibitalapara"
    ],
    "wof:name":"Bibitalapara",
    "wof:placetype":"locality",
    "wof:population":744
},
  "geometry": {"coordinates":[88.180971,22.528836],"type":"Point"}
}