{
  "type": "Feature",
  "properties": {
    "iso:country":"IN",
    "ks:ks_name":"Lanka",
    "ks:ks_pop":342,
    "ks:ks_type":"HABITATION",
    "name:eng_x_preferred":[
        "Lanka"
    ],
    "wof:name":"Lanka",
    "wof:placetype":"locality",
    "wof:population":342
},
  "geometry": {"coordinates":[81.175163,19.332745],"type":"Point"}
}