{
  "type": "Feature",
  "properties": {
    "iso:country":"IN",
    "ks:ks_name":"Kattupuram",
    "ks:ks_pop":265,
    "ks:ks_type":"HABITATION",
    "ks:ks_uagg_main":0,
    "name:eng_x_preferred":[
        "Kattupuram"
    ],
    "wof:name":"Kattupuram",
    "wof:placetype":"neighbourhood",
    "wof:population":265
},
  "geometry": {"coordinates":[76.33883299999999,9.850436],"type":"Point"}
}