{
  "type": "Feature",
  "properties": {
    "iso:country":"IN",
    "ks:ks_name":"Nava Mayurnagar",
    "ks:ks_pop":160,
    "ks:ks_type":"HABITATION",
    "name:eng_x_preferred":[
        "Nava Mayurnagar"
    ],
    "wof:name":"Nava Mayurnagar",
    "wof:placetype":"locality",
    "wof:population":160
},
  "geometry": {"coordinates":[71.084598,23.068803],"type":"Point"}
}