{
  "type": "Feature",
  "properties": {
    "iso:country":"IN",
    "ks:ks_name":"Rahir",
    "ks:ks_pop":1067,
    "ks:ks_type":"VILLAGE",
    "name:eng_x_preferred":[
        "Rahir"
    ],
    "wof:name":"Rahir",
    "wof:placetype":"locality",
    "wof:population":1067
},
  "geometry": {"coordinates":[77.00725799999999,26.269282],"type":"Point"}
}