{
  "type": "Feature",
  "properties": {
    "iso:country":"IN",
    "ks:ks_name":"Kuwadih",
    "ks:ks_pop":161,
    "ks:ks_type":"HABITATION",
    "name:eng_x_preferred":[
        "Kuwadih"
    ],
    "wof:name":"Kuwadih",
    "wof:placetype":"locality",
    "wof:population":161
},
  "geometry": {"coordinates":[85.608327,23.15175],"type":"Point"}
}