{
  "type": "Feature",
  "properties": {
    "iso:country":"IN",
    "ks:ks_name":"Kothaagarampalle",
    "ks:ks_pop":62,
    "ks:ks_type":"HABITATION",
    "name:eng_x_preferred":[
        "Kothaagarampalle"
    ],
    "wof:name":"Kothaagarampalle",
    "wof:placetype":"locality",
    "wof:population":62
},
  "geometry": {"coordinates":[79.039202,13.299744],"type":"Point"}
}