{
  "type": "Feature",
  "properties": {
    "iso:country":"IN",
    "ks:ks_name":"Sajatola",
    "ks:ks_pop":254,
    "ks:ks_type":"VILLAGE",
    "name:eng_x_preferred":[
        "Sajatola"
    ],
    "wof:name":"Sajatola",
    "wof:placetype":"locality",
    "wof:population":254
},
  "geometry": {"coordinates":[81.119759,22.398581],"type":"Point"}
}