{
  "type": "Feature",
  "properties": {
    "gn:admin1_code":"2.0",
    "gn:admin2_code":"544.0",
    "gn:asciiname":"Sidimettu",
    "gn:country_code":"IN",
    "gn:dem":958,
    "gn:feature_class":"P",
    "gn:feature_code":"PPL",
    "gn:name":"Sidimettu",
    "gn:population":0,
    "gn:timezone":"Asia/Kolkata",
    "iso:country":"IN",
    "wof:name":"Sidimettu",
    "wof:placetype":"locality"
},
  "geometry": {"coordinates":[82.64726,18.11012],"type":"Point"}
}