{
  "type": "Feature",
  "properties": {
    "gn:admin1_code":"34.0",
    "gn:admin2_code":"237.0",
    "gn:asciiname":"Koriyauna",
    "gn:country_code":"IN",
    "gn:dem":116,
    "gn:feature_class":"P",
    "gn:feature_code":"PPL",
    "gn:name":"Koriyauna",
    "gn:population":0,
    "gn:timezone":"Asia/Kolkata",
    "iso:country":"IN",
    "ks:ks_name":"Koriyauna",
    "ks:ks_pop":850,
    "ks:ks_type":"VILLAGE",
    "ks:ks_uagg_main":0,
    "name:eng_x_preferred":[
        "Koriyauna"
    ],
    "wof:name":"Koriyauna",
    "wof:placetype":"neighbourhood",
    "wof:population":850
},
  "geometry": {"coordinates":[85.608963,24.75062],"type":"Point"}
}