{
  "type": "Feature",
  "properties": {
    "gn:admin1_code":"19.0",
    "gn:admin2_code":"582.0",
    "gn:asciiname":"Hulikunte",
    "gn:country_code":"IN",
    "gn:dem":696,
    "gn:feature_class":"P",
    "gn:feature_code":"PPL",
    "gn:name":"Hulikunte",
    "gn:population":0,
    "gn:timezone":"Asia/Kolkata",
    "iso:country":"IN",
    "wof:name":"Hulikunte",
    "wof:placetype":"locality"
},
  "geometry": {"coordinates":[77.62204,13.68009],"type":"Point"}
}