{
  "type": "Feature",
  "properties": {
    "gn:admin1_code":"36.0",
    "gn:admin2_code":"184.0",
    "gn:asciiname":"Paraspur",
    "gn:country_code":"IN",
    "gn:dem":91,
    "gn:feature_class":"P",
    "gn:feature_code":"PPL",
    "gn:name":"Paraspur",
    "gn:population":0,
    "gn:timezone":"Asia/Kolkata",
    "iso:country":"IN",
    "name:new_x_preferred":[
        "\u092a\u093e\u0930\u0938\u092a\u0941\u0930"
    ],
    "wof:name":"Paraspur",
    "wof:placetype":"locality"
},
  "geometry": {"coordinates":[82.84886,27.24713],"type":"Point"}
}