{
  "type": "Feature",
  "properties": {
    "iso:country":"IN",
    "ks:ks_name":"Sangirle",
    "ks:ks_pop":176,
    "ks:ks_type":"HABITATION",
    "name:eng_x_preferred":[
        "Sangirle"
    ],
    "wof:name":"Sangirle",
    "wof:placetype":"locality",
    "wof:population":176
},
  "geometry": {"coordinates":[74.606244,15.144257],"type":"Point"}
}