{
  "type": "Feature",
  "properties": {
    "gn:admin1_code":"39.0",
    "gn:admin2_code":"64.0",
    "gn:asciiname":"Kurchaun",
    "gn:country_code":"IN",
    "gn:dem":1439,
    "gn:feature_class":"P",
    "gn:feature_code":"PPL",
    "gn:name":"Kurchaun",
    "gn:population":0,
    "gn:timezone":"Asia/Kolkata",
    "iso:country":"IN",
    "ks:ks_name":"Kurchoun",
    "ks:ks_pop":376,
    "ks:ks_type":"VILLAGE",
    "name:eng_x_preferred":[
        "Kurchoun"
    ],
    "name:eng_x_variant":[
        "Kurchaun"
    ],
    "wof:name":"Kurchoun",
    "wof:placetype":"locality",
    "wof:population":376
},
  "geometry": {"coordinates":[79.56008300000001,29.637164],"type":"Point"}
}