{
  "type": "Feature",
  "properties": {
    "gn:admin1_code":"24",
    "gn:admin2_code":"106.0",
    "gn:asciiname":"Tharwa",
    "gn:country_code":"IN",
    "gn:dem":238,
    "gn:feature_class":"P",
    "gn:feature_code":"PPL",
    "gn:name":"Tharwa",
    "gn:population":0,
    "gn:timezone":"Asia/Kolkata",
    "iso:country":"IN",
    "ks:ks_name":"Tarwa",
    "ks:ks_pop":665,
    "ks:ks_type":"HABITATION",
    "name:eng_x_preferred":[
        "Tarwa"
    ],
    "name:eng_x_variant":[
        "Tharwa"
    ],
    "wof:name":"Tarwa",
    "wof:placetype":"locality",
    "wof:population":665
},
  "geometry": {"coordinates":[77.460616,26.585215],"type":"Point"}
}