{
  "type": "Feature",
  "properties": {
    "gn:admin1_code":"24.0",
    "gn:admin2_code":"126.0",
    "gn:asciiname":"Darba",
    "gn:country_code":"IN",
    "gn:dem":451,
    "gn:feature_class":"P",
    "gn:feature_code":"PPL",
    "gn:name":"Darba",
    "gn:population":0,
    "gn:timezone":"Asia/Kolkata",
    "iso:country":"IN",
    "wof:name":"Darba",
    "wof:placetype":"locality"
},
  "geometry": {"coordinates":[74.51165999999998,25.11189],"type":"Point"}
}