{
  "type": "Feature",
  "properties": {
    "gn:admin1_code":"24.0",
    "gn:admin2_code":"102.0",
    "gn:asciiname":"Bhiyansar",
    "gn:country_code":"IN",
    "gn:dem":218,
    "gn:feature_class":"P",
    "gn:feature_code":"PPL",
    "gn:name":"Bhiy\u0101nsar",
    "gn:population":0,
    "gn:timezone":"Asia/Kolkata",
    "iso:country":"IN",
    "name:und_x_variant":[
        "Bhiy\u0101nsar",
        "Bh\u012by\u0101nsar"
    ],
    "wof:name":"Bhiyansar",
    "wof:placetype":"locality"
},
  "geometry": {"coordinates":[74.2854,28.66213],"type":"Point"}
}