{
  "type": "Feature",
  "properties": {
    "gn:admin1_code":"11",
    "gn:admin2_code":"27.0",
    "gn:asciiname":"Kharalang",
    "gn:country_code":"IN",
    "gn:dem":1929,
    "gn:feature_class":"P",
    "gn:feature_code":"PPL",
    "gn:name":"Khar\u0101lang",
    "gn:population":0,
    "gn:timezone":"Asia/Kolkata",
    "iso:country":"IN",
    "wof:name":"Kharalang",
    "wof:placetype":"locality"
},
  "geometry": {"coordinates":[76.95151,31.92077],"type":"Point"}
}