{
  "type": "Feature",
  "properties": {
    "gn:admin1_code":"36",
    "gn:admin2_code":"137.0",
    "gn:asciiname":"Bakaina Milak",
    "gn:country_code":"IN",
    "gn:dem":219,
    "gn:feature_class":"P",
    "gn:feature_code":"PPL",
    "gn:name":"Bakaina Milak",
    "gn:population":0,
    "gn:timezone":"Asia/Kolkata",
    "iso:country":"IN",
    "wof:name":"Bakaina Milak",
    "wof:placetype":"locality"
},
  "geometry": {"coordinates":[78.49769000000001,29.04173],"type":"Point"}
}