{
  "type": "Feature",
  "properties": {
    "iso:country":"IN",
    "ks:ks_name":"Heggadde",
    "ks:ks_pop":5,
    "ks:ks_type":"VILLAGE",
    "name:eng_x_preferred":[
        "Heggadde"
    ],
    "wof:name":"Heggadde",
    "wof:placetype":"locality",
    "wof:population":5
},
  "geometry": {"coordinates":[75.241103,13.52237],"type":"Point"}
}