{
  "type": "Feature",
  "properties": {
    "iso:country":"IN",
    "ks:ks_name":"Wayapari Tola",
    "ks:ks_pop":320,
    "ks:ks_type":"HABITATION",
    "name:eng_x_preferred":[
        "Wayapari Tola"
    ],
    "wof:name":"Wayapari Tola",
    "wof:placetype":"locality",
    "wof:population":320
},
  "geometry": {"coordinates":[83.926259,27.065845],"type":"Point"}
}