{
  "type": "Feature",
  "properties": {
    "iso:country":"IN",
    "ks:ks_name":"Hardi Bahara",
    "ks:ks_pop":1057,
    "ks:ks_type":"VILLAGE",
    "name:eng_x_preferred":[
        "Hardi Bahara"
    ],
    "wof:name":"Hardi Bahara",
    "wof:placetype":"locality",
    "wof:population":1057
},
  "geometry": {"coordinates":[82.790229,23.902383],"type":"Point"}
}