{
  "type": "Feature",
  "properties": {
    "iso:country":"IN",
    "ks:ks_alt_nam":"KHAIMAINARAMPUR",
    "ks:ks_name":"Khaimainarampur",
    "ks:ks_pop":900,
    "ks:ks_type":"HABITATION",
    "name:eng_x_preferred":[
        "Khaimainarampur"
    ],
    "wof:name":"Khaimainarampur",
    "wof:placetype":"locality",
    "wof:population":900
},
  "geometry": {"coordinates":[82.81483299999999,25.319245],"type":"Point"}
}