{
  "type": "Feature",
  "properties": {
    "iso:country":"IN",
    "ks:ks_name":"Muslimpara",
    "ks:ks_pop":281,
    "ks:ks_type":"HABITATION",
    "ks:ks_uagg_main":0,
    "name:eng_x_preferred":[
        "Muslimpara"
    ],
    "wof:name":"Muslimpara",
    "wof:placetype":"locality",
    "wof:population":281
},
  "geometry": {"coordinates":[91.49372700000001,26.113067],"type":"Point"}
}