{
  "type": "Feature",
  "properties": {
    "iso:country":"IN",
    "ks:ks_name":"Bhuska Falia",
    "ks:ks_pop":1259,
    "ks:ks_type":"HABITATION",
    "name:eng_x_preferred":[
        "Bhuska Falia"
    ],
    "wof:name":"Bhuska Falia",
    "wof:placetype":"locality",
    "wof:population":1259
},
  "geometry": {"coordinates":[74.13208299999999,22.749222],"type":"Point"}
}