{
  "type": "Feature",
  "properties": {
    "iso:country":"IN",
    "ks:ks_name":"Panjai Gaon",
    "ks:ks_pop":115,
    "ks:ks_type":"VILLAGE",
    "name:eng_x_preferred":[
        "Panjai Gaon"
    ],
    "wof:name":"Panjai Gaon",
    "wof:placetype":"locality",
    "wof:population":115
},
  "geometry": {"coordinates":[78.498165,29.979144],"type":"Point"}
}