{
  "type": "Feature",
  "properties": {
    "gn:admin1_code":"25.0",
    "gn:admin2_code":"605.0",
    "gn:asciiname":"Sankarapuram",
    "gn:country_code":"IN",
    "gn:dem":362,
    "gn:feature_class":"P",
    "gn:feature_code":"PPL",
    "gn:name":"Sankarapuram",
    "gn:population":0,
    "gn:timezone":"Asia/Kolkata",
    "iso:country":"IN",
    "name:bpy_x_preferred":[
        "\u09b6\u0999\u09cd\u0995\u09b0\u09be\u09aa\u09c1\u09b0\u09ae"
    ],
    "name:ita_x_preferred":[
        "Sankarapuram"
    ],
    "name:msa_x_preferred":[
        "Sankarapuram"
    ],
    "name:nld_x_preferred":[
        "Sankarapuram"
    ],
    "name:por_x_preferred":[
        "Sankarapuram"
    ],
    "name:tam_x_preferred":[
        "\u0b9a\u0b99\u0bcd\u0b95\u0bb0\u0bbe\u0baa\u0bc1\u0bb0\u0bae\u0bcd"
    ],
    "name:vie_x_preferred":[
        "Sankarapuram"
    ],
    "name:zho_x_preferred":[
        "\u6851\u5361\u62c9\u666e\u62c9\u59c6"
    ],
    "wof:name":"Sankarapuram",
    "wof:placetype":"neighbourhood"
},
  "geometry": {"coordinates":[78.57783999999999,12.67784],"type":"Point"}
}