{
  "type": "Feature",
  "properties": {
    "iso:country":"IN",
    "ks:ks_name":"Taladih",
    "ks:ks_pop":484,
    "ks:ks_type":"VILLAGE",
    "name:eng_x_preferred":[
        "Taladih"
    ],
    "wof:name":"Taladih",
    "wof:placetype":"locality",
    "wof:population":484
},
  "geometry": {"coordinates":[85.609143,22.948499],"type":"Point"}
}