{
  "type": "Feature",
  "properties": {
    "iso:country":"IN",
    "ks:ks_alt_nam":"PURE BARGADIN",
    "ks:ks_name":"Pure Bargadin",
    "ks:ks_pop":135,
    "ks:ks_type":"HABITATION",
    "name:eng_x_preferred":[
        "Pure Bargadin"
    ],
    "wof:name":"Pure Bargadin",
    "wof:placetype":"locality",
    "wof:population":135
},
  "geometry": {"coordinates":[81.732997,26.233959],"type":"Point"}
}