{
  "type": "Feature",
  "properties": {
    "iso:country":"IN",
    "ks:ks_name":"Pipri",
    "ks:ks_pop":225,
    "ks:ks_type":"HABITATION",
    "name:eng_x_preferred":[
        "Pipri"
    ],
    "wof:name":"Pipri",
    "wof:placetype":"locality",
    "wof:population":225
},
  "geometry": {"coordinates":[77.702996,23.728696],"type":"Point"}
}