{
  "type": "Feature",
  "properties": {
    "iso:country":"IN",
    "ks:ks_name":"K Pudur",
    "ks:ks_pop":175,
    "ks:ks_type":"HABITATION",
    "name:eng_x_preferred":[
        "K Pudur"
    ],
    "wof:name":"K Pudur",
    "wof:placetype":"locality",
    "wof:population":175
},
  "geometry": {"coordinates":[78.118694,10.393952],"type":"Point"}
}