{
  "type": "Feature",
  "properties": {
    "iso:country":"IN",
    "ks:ks_name":"Damdarsai",
    "ks:ks_pop":369,
    "ks:ks_type":"VILLAGE",
    "name:eng_x_preferred":[
        "Damdarsai"
    ],
    "wof:name":"Damdarsai",
    "wof:placetype":"locality",
    "wof:population":369
},
  "geometry": {"coordinates":[85.814352,22.067502],"type":"Point"}
}