{
  "type": "Feature",
  "properties": {
    "iso:country":"IN",
    "ks:ks_name":"Gosaindih",
    "ks:ks_pop":192,
    "ks:ks_type":"VILLAGE",
    "ks:ks_uagg_main":0,
    "name:eng_x_preferred":[
        "Gosaindih"
    ],
    "wof:name":"Gosaindih",
    "wof:placetype":"neighbourhood",
    "wof:population":192
},
  "geometry": {"coordinates":[85.180549,24.333025],"type":"Point"}
}