{
  "type": "Feature",
  "properties": {
    "iso:country":"IN",
    "ks:ks_name":"Sonaichari",
    "ks:ks_pop":235,
    "ks:ks_type":"HABITATION",
    "name:eng_x_preferred":[
        "Sonaichari"
    ],
    "wof:name":"Sonaichari",
    "wof:placetype":"locality",
    "wof:population":235
},
  "geometry": {"coordinates":[91.518974,23.486021],"type":"Point"}
}