{
  "type": "Feature",
  "properties": {
    "gn:admin1_code":"11",
    "gn:admin2_code":"23.0",
    "gn:asciiname":"Angriala",
    "gn:country_code":"IN",
    "gn:dem":1941,
    "gn:feature_class":"P",
    "gn:feature_code":"PPL",
    "gn:name":"Angri\u0101la",
    "gn:population":0,
    "gn:timezone":"Asia/Kolkata",
    "iso:country":"IN",
    "wof:name":"Angriala",
    "wof:placetype":"locality"
},
  "geometry": {"coordinates":[76.21321999999998,32.89667],"type":"Point"}
}