{
  "type": "Feature",
  "properties": {
    "gn:admin1_code":"24",
    "gn:admin2_code":"123.0",
    "gn:asciiname":"Morchina",
    "gn:country_code":"IN",
    "gn:dem":572,
    "gn:feature_class":"P",
    "gn:feature_code":"PPL",
    "gn:name":"Morchina",
    "gn:population":0,
    "gn:timezone":"Asia/Kolkata",
    "iso:country":"IN",
    "ks:ks_name":"Morchana",
    "ks:ks_pop":1699,
    "ks:ks_type":"VILLAGE",
    "ks:ks_uagg_main":0,
    "name:eng_x_preferred":[
        "Morchana"
    ],
    "wof:name":"Morchana",
    "wof:placetype":"neighbourhood",
    "wof:population":1699
},
  "geometry": {"coordinates":[73.862753,25.102483],"type":"Point"}
}