{
  "type": "Feature",
  "properties": {
    "iso:country":"IN",
    "ks:ks_name":"Mohanria",
    "ks:ks_pop":157,
    "ks:ks_type":"VILLAGE",
    "name:eng_x_preferred":[
        "Mohanria"
    ],
    "wof:name":"Mohanria",
    "wof:placetype":"locality",
    "wof:population":157
},
  "geometry": {"coordinates":[85.779308,24.705395],"type":"Point"}
}