{
  "type": "Feature",
  "properties": {
    "iso:country":"IN",
    "ks:ks_alt_nam":"radaodisa",
    "ks:ks_name":"Radaodisa",
    "ks:ks_pop":78,
    "ks:ks_type":"HABITATION",
    "name:eng_x_preferred":[
        "Radaodisa"
    ],
    "wof:name":"Radaodisa",
    "wof:placetype":"locality",
    "wof:population":78
},
  "geometry": {"coordinates":[93.130354,25.679773],"type":"Point"}
}