{
  "type": "Feature",
  "properties": {
    "iso:country":"IN",
    "ks:ks_name":"Chatti",
    "ks:ks_pop":297,
    "ks:ks_type":"VILLAGE",
    "ks:ks_uagg_main":0,
    "name:eng_x_preferred":[
        "Chatti"
    ],
    "wof:name":"Chatti",
    "wof:placetype":"neighbourhood",
    "wof:population":297
},
  "geometry": {"coordinates":[84.482472,23.280416],"type":"Point"}
}