{
  "type": "Feature",
  "properties": {
    "iso:country":"IN",
    "ks:ks_name":"Bairagarh",
    "ks:ks_pop":22,
    "ks:ks_type":"HABITATION",
    "ks:ks_uagg_main":0,
    "name:eng_x_preferred":[
        "Bairagarh"
    ],
    "wof:name":"Bairagarh",
    "wof:placetype":"neighbourhood",
    "wof:population":22
},
  "geometry": {"coordinates":[77.57986099999999,29.901291],"type":"Point"}
}