{
  "type": "Feature",
  "properties": {
    "iso:country":"IN",
    "ks:ks_name":"Gaonkarkeri",
    "ks:ks_pop":161,
    "ks:ks_type":"HABITATION",
    "name:eng_x_preferred":[
        "Gaonkarkeri"
    ],
    "wof:name":"Gaonkarkeri",
    "wof:placetype":"locality",
    "wof:population":161
},
  "geometry": {"coordinates":[74.277804,14.705552],"type":"Point"}
}