{
  "type": "Feature",
  "properties": {
    "gn:admin1_code":"24.0",
    "gn:admin2_code":"115.0",
    "gn:asciiname":"Jojar sing ji Dhani",
    "gn:country_code":"IN",
    "gn:dem":121,
    "gn:feature_class":"P",
    "gn:feature_code":"PPL",
    "gn:name":"Joj\u0101r sing ji Dh\u0101ni",
    "gn:population":0,
    "gn:timezone":"Asia/Kolkata",
    "iso:country":"IN",
    "wof:name":"Jojar sing ji Dhani",
    "wof:placetype":"locality"
},
  "geometry": {"coordinates":[70.91795999999999,25.1135],"type":"Point"}
}