{
  "type": "Feature",
  "properties": {
    "iso:country":"IN",
    "ks:ks_name":"Kakarlaputtuga",
    "ks:ks_pop":403,
    "ks:ks_type":"HABITATION",
    "name:eng_x_preferred":[
        "Kakarlaputtuga"
    ],
    "wof:name":"Kakarlaputtuga",
    "wof:placetype":"locality",
    "wof:population":403
},
  "geometry": {"coordinates":[84.62603900000001,18.966618],"type":"Point"}
}