{
  "type": "Feature",
  "properties": {
    "iso:country":"IN",
    "ks:ks_alt_nam":"ENERGY COLONY",
    "ks:ks_name":"Energy Colony",
    "ks:ks_pop":264,
    "ks:ks_type":"HABITATION",
    "name:eng_x_preferred":[
        "Energy Colony"
    ],
    "wof:name":"Energy Colony",
    "wof:placetype":"locality",
    "wof:population":264
},
  "geometry": {"coordinates":[91.17898700000001,23.734759],"type":"Point"}
}