{
  "type": "Feature",
  "properties": {
    "gn:admin1_code":"19.0",
    "gn:admin2_code":"584.0",
    "gn:asciiname":"Virapura",
    "gn:country_code":"IN",
    "gn:dem":744,
    "gn:feature_class":"P",
    "gn:feature_code":"PPL",
    "gn:name":"Vir\u0101pura",
    "gn:population":0,
    "gn:timezone":"Asia/Kolkata",
    "iso:country":"IN",
    "ks:ks_name":"Veerapura",
    "ks:ks_pop":110,
    "ks:ks_type":"VILLAGE",
    "name:eng_x_preferred":[
        "Veerapura"
    ],
    "name:eng_x_variant":[
        "Virapura"
    ],
    "wof:name":"Veerapura",
    "wof:placetype":"locality",
    "wof:population":110
},
  "geometry": {"coordinates":[77.32187999999999,12.914971],"type":"Point"}
}