{
  "type": "Feature",
  "properties": {
    "iso:country":"IN",
    "ks:ks_name":"Medharaganda",
    "ks:ks_pop":300,
    "ks:ks_type":"HABITATION",
    "name:eng_x_preferred":[
        "Medharaganda"
    ],
    "wof:name":"Medharaganda",
    "wof:placetype":"locality",
    "wof:population":300
},
  "geometry": {"coordinates":[83.582534,18.92459],"type":"Point"}
}