{
  "type": "Feature",
  "properties": {
    "gn:admin1_code":"36",
    "gn:admin2_code":"146.0",
    "gn:asciiname":"Mahgauli",
    "gn:country_code":"IN",
    "gn:dem":152,
    "gn:feature_class":"P",
    "gn:feature_code":"PPL",
    "gn:name":"Mahgauli",
    "gn:population":0,
    "gn:timezone":"Asia/Kolkata",
    "iso:country":"IN",
    "ks:ks_name":"Mahgauli",
    "ks:ks_type":"VILLAGE",
    "name:eng_x_preferred":[
        "Mahgauli"
    ],
    "wof:name":"Mahgauli",
    "wof:placetype":"locality"
},
  "geometry": {"coordinates":[78.31562,26.88696],"type":"Point"}
}