{
  "type": "Feature",
  "properties": {
    "iso:country":"IN",
    "ks:ks_name":"Hanijanakeri",
    "ks:ks_pop":230,
    "ks:ks_type":"HABITATION",
    "name:eng_x_preferred":[
        "Hanijanakeri"
    ],
    "wof:name":"Hanijanakeri",
    "wof:placetype":"locality",
    "wof:population":230
},
  "geometry": {"coordinates":[75.02628,14.53724],"type":"Point"}
}