{
  "type": "Feature",
  "properties": {
    "iso:country":"IN",
    "ks:ks_name":"D S Palya",
    "ks:ks_pop":476,
    "ks:ks_type":"HABITATION",
    "name:eng_x_preferred":[
        "D S Palya"
    ],
    "wof:name":"D S Palya",
    "wof:placetype":"locality",
    "wof:population":476
},
  "geometry": {"coordinates":[76.989738,13.191863],"type":"Point"}
}