{
  "type": "Feature",
  "properties": {
    "iso:country":"IN",
    "ks:ks_name":"Methyali",
    "ks:ks_pop":2464,
    "ks:ks_type":"VILLAGE",
    "ks:ks_uagg_main":0,
    "name:eng_x_preferred":[
        "Methyali"
    ],
    "wof:name":"Methyali",
    "wof:placetype":"neighbourhood",
    "wof:population":2464
},
  "geometry": {"coordinates":[87.27432,23.47716],"type":"Point"}
}