{
  "type": "Feature",
  "properties": {
    "gn:admin1_code":"3.0",
    "gn:admin2_code":"300.0",
    "gn:asciiname":"Hauriajhora",
    "gn:country_code":"IN",
    "gn:dem":43,
    "gn:feature_class":"P",
    "gn:feature_code":"PPL",
    "gn:name":"Hauriajhora",
    "gn:population":0,
    "gn:timezone":"Asia/Kolkata",
    "iso:country":"IN",
    "ks:ks_name":"Hawrijhora",
    "ks:ks_pop":199,
    "ks:ks_type":"HABITATION",
    "name:eng_x_preferred":[
        "Hawrijhora"
    ],
    "name:eng_x_variant":[
        "Hauriajhora"
    ],
    "wof:name":"Hawrijhora",
    "wof:placetype":"locality",
    "wof:population":199
},
  "geometry": {"coordinates":[89.976979,26.247172],"type":"Point"}
}