{
  "type": "Feature",
  "properties": {
    "iso:country":"IN",
    "ks:ks_alt_nam":"Kotyanaik tanda",
    "ks:ks_name":"Kotyanaik Tanda",
    "ks:ks_pop":62,
    "ks:ks_type":"HABITATION",
    "name:eng_x_preferred":[
        "Kotyanaik Tanda"
    ],
    "wof:name":"Kotyanaik Tanda",
    "wof:placetype":"locality",
    "wof:population":62
},
  "geometry": {"coordinates":[78.28170900000001,16.959339],"type":"Point"}
}