{
  "type": "Feature",
  "properties": {
    "gn:admin1_code":"36",
    "gn:admin2_code":"186.0",
    "gn:asciiname":"Parsa Kalan",
    "gn:country_code":"IN",
    "gn:dem":85,
    "gn:feature_class":"P",
    "gn:feature_code":"PPL",
    "gn:name":"Parsa Kal\u0101n",
    "gn:population":0,
    "gn:timezone":"Asia/Kolkata",
    "iso:country":"IN",
    "ks:ks_alt_nam":"Parsa Kal\u0101n",
    "ks:ks_name":"Parsa Kalan",
    "ks:ks_type":"VILLAGE",
    "ks:ks_uagg_main":0,
    "name:eng_x_preferred":[
        "Parsa Kalan"
    ],
    "name:eng_x_variant":[
        "Parsa Kal\u0101n"
    ],
    "wof:name":"Parsa Kalan",
    "wof:placetype":"neighbourhood"
},
  "geometry": {"coordinates":[83.017319,26.562324],"type":"Point"}
}