{
  "type": "Feature",
  "properties": {
    "gn:admin1_code":"19.0",
    "gn:admin2_code":"584.0",
    "gn:asciiname":"Banavasi",
    "gn:country_code":"IN",
    "gn:dem":712,
    "gn:feature_class":"P",
    "gn:feature_code":"PPL",
    "gn:name":"Banavasi",
    "gn:population":0,
    "gn:timezone":"Asia/Kolkata",
    "iso:country":"IN",
    "name:bar_x_preferred":[
        "Banavasi"
    ],
    "name:cat_x_preferred":[
        "Banavasi"
    ],
    "name:ceb_x_preferred":[
        "Banav\u0101si"
    ],
    "name:deu_x_preferred":[
        "Banavasi"
    ],
    "name:hin_x_preferred":[
        "\u092c\u0928\u0935\u093e\u0938\u0940"
    ],
    "name:ind_x_preferred":[
        "Banavasi"
    ],
    "name:kan_x_preferred":[
        "\u0cac\u0ca8\u0cb5\u0cbe\u0cb8\u0cbf"
    ],
    "name:kat_x_preferred":[
        "\u10d1\u10d0\u10dc\u10d0\u10d5\u10d0\u10e1\u10d8"
    ],
    "name:mar_x_preferred":[
        "\u092c\u0928\u0935\u093e\u0938\u0940"
    ],
    "name:rus_x_preferred":[
        "\u0411\u0430\u043d\u0430\u0432\u0430\u0441\u0438"
    ],
    "name:san_x_preferred":[
        "\u092c\u0928\u0935\u093e\u0938\u0940"
    ],
    "name:swe_x_preferred":[
        "Banav\u0101si"
    ],
    "name:tam_x_preferred":[
        "\u0baa\u0ba9\u0bb5\u0bbe\u0b9a\u0bbf"
    ],
    "name:ukr_x_preferred":[
        "\u0411\u0430\u043d\u0430\u0432\u0430\u0441\u0456"
    ],
    "name:vie_x_preferred":[
        "Banavasi"
    ],
    "wof:name":"Banavasi",
    "wof:placetype":"locality"
},
  "geometry": {"coordinates":[77.54588000000003,12.64149],"type":"Point"}
}