{
  "type": "Feature",
  "properties": {
    "gn:country":"IN",
    "gn:fcode":"PPL",
    "gn:population":23405,
    "iso:country":"IN",
    "name:ben_x_preferred":[
        "\u0996\u09be\u09a4\u09c7\u0997\u09be\u0981\u0993"
    ],
    "name:bpy_x_preferred":[
        "\u0996\u09be\u09a4\u09c7\u0997\u09be\u0981\u0993"
    ],
    "name:ceb_x_preferred":[
        "Kh\u0101tegaon"
    ],
    "name:deu_x_preferred":[
        "Khategaon"
    ],
    "name:eng_x_preferred":[
        "Khategaon"
    ],
    "name:fra_x_preferred":[
        "Khategaon"
    ],
    "name:guj_x_preferred":[
        "\u0a96\u0abe\u0aa4\u0ac7\u0a97\u0abe\u0a82\u0ab5"
    ],
    "name:hin_x_preferred":[
        "\u0916\u093e\u0924\u0947\u0917\u093e\u0902\u0935"
    ],
    "name:ita_x_preferred":[
        "Khategaon"
    ],
    "name:jpn_x_preferred":[
        "\u30ab\u30fc\u30c6\u30ac\u30aa\u30f3"
    ],
    "name:kan_x_preferred":[
        "\u0c96\u0cbe\u0ca4\u0cc6\u0c97\u0cbe\u0cb5\u0ccd"
    ],
    "name:kor_x_preferred":[
        "\uce74\ud14c\uac00\uc628"
    ],
    "name:mlg_x_preferred":[
        "Khategaon"
    ],
    "name:msa_x_preferred":[
        "Khategaon"
    ],
    "name:nan_x_preferred":[
        "Khategaon"
    ],
    "name:new_x_preferred":[
        "\u0916\u0924\u0947\u0917\u093e\u0902\u0935"
    ],
    "name:nld_x_preferred":[
        "Khategaon"
    ],
    "name:por_x_preferred":[
        "Khategaon"
    ],
    "name:rus_x_preferred":[
        "\u041a\u0445\u0430\u0442\u0435\u0433\u0430\u043e\u043d"
    ],
    "name:spa_x_preferred":[
        "Khategaon"
    ],
    "name:swe_x_preferred":[
        "Kh\u0101tegaon"
    ],
    "name:tam_x_preferred":[
        "\u0b95\u0bbe\u0b9f\u0bc6\u0b95\u0bcd\u0b95\u0ba9\u0bcd"
    ],
    "name:tel_x_preferred":[
        "\u0c16\u0c1f\u0c47\u0c17\u0c3e\u0c35\u0c4d"
    ],
    "name:urd_x_preferred":[
        "\u062e\u0627\u062a\u06cc\u062c\u0627\u0648\u0646"
    ],
    "name:vie_x_preferred":[
        "Khategaon"
    ],
    "name:zho_x_preferred":[
        "\u5361\u6cf0\u52a0\u5965\u6069"
    ],
    "qs:name":"Khategaon",
    "qs:name_adm0":"India",
    "qs:name_adm1":"Madhya Pradesh",
    "qs:photos_9k":1,
    "qs:photos_9r":1,
    "qs:photos_all":1,
    "qs:photos_sr":0,
    "qs:placetype":"Town",
    "qs:pop_sr":"7",
    "wd:wordcount":93,
    "wof:name":"Khategaon",
    "wof:placetype":"locality",
    "wof:population":23405
},
  "geometry": {"coordinates":[76.91363,22.5957],"type":"Point"}
}