{
  "type": "Feature",
  "properties": {
    "iso:country":"IN",
    "ks:ks_name":"Andipatti",
    "ks:ks_pop":1182,
    "ks:ks_type":"HABITATION",
    "name:eng_x_preferred":[
        "Andipatti"
    ],
    "wof:name":"Andipatti",
    "wof:placetype":"locality",
    "wof:population":1182
},
  "geometry": {"coordinates":[87.058986,25.996192],"type":"Point"}
}