{
  "type": "Feature",
  "properties": {
    "gn:admin1_code":"36",
    "gn:admin2_code":"185.0",
    "gn:asciiname":"Bhagwandin",
    "gn:country_code":"IN",
    "gn:dem":94,
    "gn:feature_class":"P",
    "gn:feature_code":"PPL",
    "gn:name":"Bhagw\u0101nd\u012bn",
    "gn:population":0,
    "gn:timezone":"Asia/Kolkata",
    "iso:country":"IN",
    "wof:name":"Bhagwandin",
    "wof:placetype":"neighbourhood"
},
  "geometry": {"coordinates":[82.57204,26.80501],"type":"Point"}
}