{
  "type": "Feature",
  "properties": {
    "iso:country":"IN",
    "ks:ks_name":"Vanaj",
    "ks:ks_pop":446,
    "ks:ks_type":"VILLAGE",
    "name:eng_x_preferred":[
        "Vanaj"
    ],
    "wof:name":"Vanaj",
    "wof:placetype":"locality",
    "wof:population":446
},
  "geometry": {"coordinates":[73.2945,23.973139],"type":"Point"}
}