{
  "type": "Feature",
  "properties": {
    "gn:admin1_code":"36",
    "gn:admin2_code":"176.0",
    "gn:asciiname":"Gangapur",
    "gn:country_code":"IN",
    "gn:dem":116,
    "gn:feature_class":"P",
    "gn:feature_code":"PPL",
    "gn:name":"Gang\u0101pur",
    "gn:population":0,
    "gn:timezone":"Asia/Kolkata",
    "iso:country":"IN",
    "ks:ks_name":"Ganga Pur",
    "ks:ks_pop":552,
    "ks:ks_type":"VILLAGE",
    "ks:ks_uagg_main":0,
    "name:bih_x_preferred":[
        "\u0917\u0902\u0917\u093e\u092a\u0941\u0930"
    ],
    "name:ceb_x_preferred":[
        "Gangapur"
    ],
    "name:eng_x_preferred":[
        "Ganga Pur"
    ],
    "name:ita_x_preferred":[
        "Gangapur"
    ],
    "name:pol_x_preferred":[
        "Gangapur"
    ],
    "name:swe_x_preferred":[
        "Gangapur"
    ],
    "name:vie_x_preferred":[
        "Gangapur"
    ],
    "wof:name":"Ganga Pur",
    "wof:placetype":"neighbourhood",
    "wof:population":552
},
  "geometry": {"coordinates":[81.24648500000001,26.675857],"type":"Point"}
}