{
  "type": "Feature",
  "properties": {
    "iso:country":"IN",
    "ks:ks_name":"Korant",
    "ks:ks_pop":1932,
    "ks:ks_type":"VILLAGE",
    "ks:ks_uagg_main":0,
    "name:eng_x_preferred":[
        "Korant"
    ],
    "wof:name":"Korant",
    "wof:placetype":"locality",
    "wof:population":1932
},
  "geometry": {"coordinates":[86.461072,21.066568],"type":"Point"}
}