{
  "type": "Feature",
  "properties": {
    "iso:country":"IN",
    "ks:ks_name":"Kalleii Palam",
    "ks:ks_pop":45,
    "ks:ks_type":"HABITATION",
    "name:eng_x_preferred":[
        "Kalleii Palam"
    ],
    "wof:name":"Kalleii Palam",
    "wof:placetype":"locality",
    "wof:population":45
},
  "geometry": {"coordinates":[76.828998,9.169475],"type":"Point"}
}