{
  "type": "Feature",
  "properties": {
    "iso:country":"IN",
    "ks:ks_alt_nam":"GORE -AHIR TOLA",
    "ks:ks_name":"Gore -ahir Tola",
    "ks:ks_pop":320,
    "ks:ks_type":"HABITATION",
    "name:eng_x_preferred":[
        "Gore -ahir Tola"
    ],
    "wof:name":"Gore -ahir Tola",
    "wof:placetype":"locality",
    "wof:population":320
},
  "geometry": {"coordinates":[83.958777,23.979893],"type":"Point"}
}