{
  "type": "Feature",
  "properties": {
    "iso:country":"IN",
    "ks:ks_name":"Dampur Pt.-ii",
    "ks:ks_pop":1509,
    "ks:ks_type":"VILLAGE",
    "ks:ks_uagg_main":0,
    "name:eng_x_preferred":[
        "Dampur Pt.-ii"
    ],
    "wof:name":"Dampur Pt.-ii",
    "wof:placetype":"neighbourhood",
    "wof:population":1509
},
  "geometry": {"coordinates":[90.01753600000001,26.124712],"type":"Point"}
}