{
  "type": "Feature",
  "properties": {
    "iso:country":"IN",
    "ks:ks_name":"Ontipalya",
    "ks:ks_pop":31,
    "ks:ks_type":"HABITATION",
    "name:eng_x_preferred":[
        "Ontipalya"
    ],
    "wof:name":"Ontipalya",
    "wof:placetype":"locality",
    "wof:population":31
},
  "geometry": {"coordinates":[76.795694,13.264024],"type":"Point"}
}