{
  "type": "Feature",
  "properties": {
    "gn:admin1_code":"21.0",
    "gn:admin2_code":"389.0",
    "gn:asciiname":"Garabandh",
    "gn:country_code":"IN",
    "gn:dem":621,
    "gn:feature_class":"P",
    "gn:feature_code":"PPL",
    "gn:name":"Garabandh",
    "gn:population":0,
    "gn:timezone":"Asia/Kolkata",
    "iso:country":"IN",
    "wof:name":"Garabandh",
    "wof:placetype":"locality"
},
  "geometry": {"coordinates":[83.96581,19.05884],"type":"Point"}
}