{
  "type": "Feature",
  "properties": {
    "iso:country":"IN",
    "ks:ks_name":"Jhajhara",
    "ks:ks_pop":0,
    "ks:ks_type":"VILLAGE",
    "name:eng_x_preferred":[
        "Jhajhara"
    ],
    "wof:name":"Jhajhara",
    "wof:placetype":"locality",
    "wof:population":0
},
  "geometry": {"coordinates":[84.047031,24.84828],"type":"Point"}
}