{
  "type": "Feature",
  "properties": {
    "iso:country":"IN",
    "ks:ks_alt_nam":"BHUIYAN TOLI",
    "ks:ks_name":"Bhuiyan Toli",
    "ks:ks_pop":258,
    "ks:ks_type":"HABITATION",
    "name:eng_x_preferred":[
        "Bhuiyan Toli"
    ],
    "wof:name":"Bhuiyan Toli",
    "wof:placetype":"locality",
    "wof:population":258
},
  "geometry": {"coordinates":[84.88592,24.357517],"type":"Point"}
}