{
  "type": "Feature",
  "properties": {
    "iso:country":"IN",
    "ks:ks_name":"No. 2 Moha Ranipur",
    "ks:ks_pop":767,
    "ks:ks_type":"HABITATION",
    "name:eng_x_preferred":[
        "No. 2 Moha Ranipur"
    ],
    "wof:name":"No. 2 Moha Ranipur",
    "wof:placetype":"locality",
    "wof:population":767
},
  "geometry": {"coordinates":[94.80055400000001,27.603031],"type":"Point"}
}