{
  "type": "Feature",
  "properties": {
    "iso:country":"IN",
    "ks:ks_name":"Tent Gaon",
    "ks:ks_pop":56,
    "ks:ks_type":"VILLAGE",
    "name:eng_x_preferred":[
        "Tent Gaon"
    ],
    "wof:name":"Tent Gaon",
    "wof:placetype":"locality",
    "wof:population":56
},
  "geometry": {"coordinates":[79.014797,29.664111],"type":"Point"}
}