{
  "type": "Feature",
  "properties": {
    "gn:admin1_code":"38.0",
    "gn:admin2_code":"347.0",
    "gn:asciiname":"Amin",
    "gn:country_code":"IN",
    "gn:dem":430,
    "gn:feature_class":"P",
    "gn:feature_code":"PPL",
    "gn:name":"\u0100min",
    "gn:population":0,
    "gn:timezone":"Asia/Kolkata",
    "iso:country":"IN",
    "ks:ks_name":"Amin",
    "ks:ks_pop":405,
    "ks:ks_type":"VILLAGE",
    "name:dan_x_preferred":[
        "Amin"
    ],
    "name:deu_x_preferred":[
        "Amin"
    ],
    "name:eng_x_preferred":[
        "Amin"
    ],
    "name:fin_x_preferred":[
        "Amin"
    ],
    "name:fra_x_preferred":[
        "Amin"
    ],
    "name:ind_x_preferred":[
        "Amin"
    ],
    "name:ita_x_preferred":[
        "Amin"
    ],
    "name:jpn_x_preferred":[
        "\u30a2\u30df\u30f3"
    ],
    "name:nld_x_preferred":[
        "Amin"
    ],
    "name:pol_x_preferred":[
        "Amin"
    ],
    "name:por_x_preferred":[
        "Amin"
    ],
    "name:rus_x_preferred":[
        "\u0410\u043c\u0438\u043d"
    ],
    "name:slv_x_preferred":[
        "Amin"
    ],
    "name:srp_x_preferred":[
        "\u0410\u043c\u0438\u043d"
    ],
    "name:swe_x_preferred":[
        "Amin"
    ],
    "name:tur_x_preferred":[
        "Amin"
    ],
    "name:vie_x_preferred":[
        "Amin"
    ],
    "wof:name":"Amin",
    "wof:placetype":"locality",
    "wof:population":405
},
  "geometry": {"coordinates":[85.016206,24.232416],"type":"Point"}
}