{
  "type": "Feature",
  "properties": {
    "iso:country":"IN",
    "ks:ks_name":"Daulatpur",
    "ks:ks_pop":315,
    "ks:ks_type":"HABITATION",
    "name:eng_x_preferred":[
        "Daulatpur"
    ],
    "wof:name":"Daulatpur",
    "wof:placetype":"locality",
    "wof:population":315
},
  "geometry": {"coordinates":[83.277743,25.567541],"type":"Point"}
}