{
  "type": "Feature",
  "properties": {
    "gn:admin1_code":"30.0",
    "gn:admin2_code":"258",
    "gn:asciiname":"Bomjur",
    "gn:country_code":"IN",
    "gn:dem":189,
    "gn:feature_class":"P",
    "gn:feature_code":"PPL",
    "gn:name":"Bomjur",
    "gn:population":0,
    "gn:timezone":"Asia/Kolkata",
    "iso:country":"IN",
    "wof:name":"Bomjur",
    "wof:placetype":"locality"
},
  "geometry": {"coordinates":[95.69262000000001,28.11433],"type":"Point"}
}