{
  "type": "Feature",
  "properties": {
    "gn:admin1_code":"19.0",
    "gn:admin2_code":"577.0",
    "gn:asciiname":"Maragaudanahalli",
    "gn:country_code":"IN",
    "gn:dem":836,
    "gn:feature_class":"P",
    "gn:feature_code":"PPL",
    "gn:name":"M\u0101ragaudanahalli",
    "gn:population":0,
    "gn:timezone":"Asia/Kolkata",
    "iso:country":"IN",
    "wof:name":"Maragaudanahalli",
    "wof:placetype":"locality"
},
  "geometry": {"coordinates":[76.29825,12.42335],"type":"Point"}
}