{
  "type": "Feature",
  "properties": {
    "gn:admin1_code":"11",
    "gn:admin2_code":"24.0",
    "gn:asciiname":"Dhumlar",
    "gn:country_code":"IN",
    "gn:dem":1538,
    "gn:feature_class":"P",
    "gn:feature_code":"PPL",
    "gn:name":"Dhuml\u0101r",
    "gn:population":0,
    "gn:timezone":"Asia/Kolkata",
    "iso:country":"IN",
    "wof:name":"Dhumlar",
    "wof:placetype":"locality"
},
  "geometry": {"coordinates":[76.28305999999998,32.26827],"type":"Point"}
}