{
  "type": "Feature",
  "properties": {
    "iso:country":"IN",
    "ks:ks_name":"Berenga Pt IV",
    "ks:ks_pop":1254,
    "ks:ks_type":"VILLAGE",
    "ks:ks_uagg_main":0,
    "name:eng_x_preferred":[
        "Berenga Pt IV"
    ],
    "wof:name":"Berenga Pt IV",
    "wof:placetype":"neighbourhood",
    "wof:population":1254
},
  "geometry": {"coordinates":[92.81334099999999,24.833748],"type":"Point"}
}