{
  "type": "Feature",
  "properties": {
    "iso:country":"IN",
    "ks:ks_name":"Andarjoda",
    "ks:ks_pop":71,
    "ks:ks_type":"VILLAGE",
    "name:eng_x_preferred":[
        "Andarjoda"
    ],
    "wof:name":"Andarjoda",
    "wof:placetype":"locality",
    "wof:population":71
},
  "geometry": {"coordinates":[86.80378,22.055293],"type":"Point"}
}