{
  "type": "Feature",
  "properties": {
    "iso:country":"IN",
    "ks:ks_name":"Simar",
    "ks:ks_pop":72,
    "ks:ks_type":"VILLAGE",
    "name:eng_x_preferred":[
        "Simar"
    ],
    "wof:name":"Simar",
    "wof:placetype":"locality",
    "wof:population":72
},
  "geometry": {"coordinates":[80.036574,29.304553],"type":"Point"}
}