{
  "type": "Feature",
  "properties": {
    "iso:country":"IN",
    "ks:ks_name":"Udayabhanpur",
    "ks:ks_pop":0,
    "ks:ks_type":"VILLAGE",
    "name:eng_x_preferred":[
        "Udayabhanpur"
    ],
    "wof:name":"Udayabhanpur",
    "wof:placetype":"locality",
    "wof:population":0
},
  "geometry": {"coordinates":[84.144451,25.231768],"type":"Point"}
}