{
  "type": "Feature",
  "properties": {
    "gn:country":"IN",
    "gn:fcode":"PPL",
    "gn:pop":25494,
    "iso:country":"IN",
    "qs:name":"Koelw\u0101r",
    "qs:photos_9r":0,
    "qs:photos_sr":0,
    "qs:pop_sr":"7",
    "wd:wordcount":225,
    "wof:name":"Koelw\u0101r",
    "wof:placetype":"locality",
    "wof:population":25494
},
  "geometry": {"coordinates":[84.79631999999999,25.5811],"type":"Point"}
}