{
  "type": "Feature",
  "properties": {
    "gn:country":"IN",
    "gn:fcode":"PPL",
    "gn:pop":25494,
    "iso:country":"IN",
    "name:ben_x_preferred":[
        "\u0995\u09cb\u0987\u09b2\u0993\u09af\u09bc\u09be\u09b0"
    ],
    "name:bpy_x_preferred":[
        "\u0995\u09cb\u0987\u09b2\u09f1\u09be\u09b0"
    ],
    "name:eng_x_preferred":[
        "Koilwar"
    ],
    "name:ita_x_preferred":[
        "Koilwar"
    ],
    "name:msa_x_preferred":[
        "Koilwar"
    ],
    "name:nan_x_preferred":[
        "Koilwar"
    ],
    "name:new_x_preferred":[
        "\u0915\u094b\u0907\u0932\u0935\u093e\u0930"
    ],
    "name:nld_x_preferred":[
        "Koilwar"
    ],
    "name:por_x_preferred":[
        "Koilwar"
    ],
    "name:spa_x_preferred":[
        "Koilwar"
    ],
    "name:urd_x_preferred":[
        "\u06a9\u0648\u0644\u0648\u0631"
    ],
    "name:vie_x_preferred":[
        "Koilwar"
    ],
    "name:zho_x_preferred":[
        "\u79d1\u4f0a\u5c14\u74e6\u5c14"
    ],
    "qs:name":"Koelw\u0101r",
    "qs:photos_9r":0,
    "qs:photos_sr":0,
    "qs:pop_sr":"7",
    "wd:wordcount":225,
    "wof:name":"Koelw\u0101r",
    "wof:placetype":"locality",
    "wof:population":25494
},
  "geometry": {"coordinates":[84.79631999999999,25.5811],"type":"Point"}
}