{
  "type": "Feature",
  "properties": {
    "gn:admin1_code":"34.0",
    "gn:admin2_code":"226.0",
    "gn:asciiname":"Qasba",
    "gn:country_code":"IN",
    "gn:dem":56,
    "gn:feature_class":"P",
    "gn:feature_code":"PPL",
    "gn:name":"Qasba",
    "gn:population":0,
    "gn:timezone":"Asia/Kolkata",
    "iso:country":"IN",
    "wof:name":"Qasba",
    "wof:placetype":"neighbourhood"
},
  "geometry": {"coordinates":[86.66357000000001,25.11987],"type":"Point"}
}