{
  "type": "Feature",
  "properties": {
    "iso:country":"IN",
    "ks:ks_name":"Kannarasilpa",
    "ks:ks_pop":65,
    "ks:ks_type":"HABITATION",
    "name:eng_x_preferred":[
        "Kannarasilpa"
    ],
    "wof:name":"Kannarasilpa",
    "wof:placetype":"locality",
    "wof:population":65
},
  "geometry": {"coordinates":[82.279606,17.953531],"type":"Point"}
}