{
  "type": "Feature",
  "properties": {
    "iso:country":"IN",
    "ks:ks_alt_nam":"VADACHAMALA",
    "ks:ks_name":"Vadachamala",
    "ks:ks_pop":200,
    "ks:ks_type":"HABITATION",
    "name:eng_x_preferred":[
        "Vadachamala"
    ],
    "wof:name":"Vadachamala",
    "wof:placetype":"locality",
    "wof:population":200
},
  "geometry": {"coordinates":[74.801681,17.14712],"type":"Point"}
}