{
  "type": "Feature",
  "properties": {
    "gn:admin1_code":"19",
    "gn:admin2_code":"559.0",
    "gn:asciiname":"Sunknur",
    "gn:country_code":"IN",
    "gn:dem":410,
    "gn:feature_class":"P",
    "gn:feature_code":"PPL",
    "gn:name":"Sunkn\u016br",
    "gn:population":0,
    "gn:timezone":"Asia/Kolkata",
    "iso:country":"IN",
    "wof:name":"Sunknur",
    "wof:placetype":"locality"
},
  "geometry": {"coordinates":[76.81178,16.00381],"type":"Point"}
}