{
  "type": "Feature",
  "properties": {
    "iso:country":"IN",
    "ks:ks_name":"Periyankalam",
    "ks:ks_pop":188,
    "ks:ks_type":"HABITATION",
    "ks:ks_uagg_main":0,
    "name:eng_x_preferred":[
        "Periyankalam"
    ],
    "wof:name":"Periyankalam",
    "wof:placetype":"neighbourhood",
    "wof:population":188
},
  "geometry": {"coordinates":[78.508944,10.251798],"type":"Point"}
}