{
  "type": "Feature",
  "properties": {
    "iso:country":"IN",
    "ks:ks_alt_nam":"Nerale hosur",
    "ks:ks_name":"Nerale Hosur",
    "ks:ks_pop":246,
    "ks:ks_type":"HABITATION",
    "name:eng_x_preferred":[
        "Nerale Hosur"
    ],
    "wof:name":"Nerale Hosur",
    "wof:placetype":"locality",
    "wof:population":246
},
  "geometry": {"coordinates":[76.32987199999999,12.004982],"type":"Point"}
}