{
  "type": "Feature",
  "properties": {
    "gn:admin1_code":"19.0",
    "gn:admin2_code":"575.0",
    "gn:asciiname":"Nettana",
    "gn:country_code":"IN",
    "gn:dem":129,
    "gn:feature_class":"P",
    "gn:feature_code":"PPL",
    "gn:name":"Nettana",
    "gn:population":0,
    "gn:timezone":"Asia/Kolkata",
    "iso:country":"IN",
    "ks:ks_name":"Nettana",
    "ks:ks_pop":210,
    "ks:ks_type":"HABITATION",
    "name:eng_x_preferred":[
        "Nettana"
    ],
    "wof:name":"Nettana",
    "wof:placetype":"locality",
    "wof:population":210
},
  "geometry": {"coordinates":[75.561307,12.729847],"type":"Point"}
}