{
  "type": "Feature",
  "properties": {
    "iso:country":"IN",
    "ks:ks_name":"Borbam",
    "ks:ks_pop":210,
    "ks:ks_type":"HABITATION",
    "name:eng_x_preferred":[
        "Borbam"
    ],
    "wof:name":"Borbam",
    "wof:placetype":"locality",
    "wof:population":210
},
  "geometry": {"coordinates":[94.79976000000001,27.099145],"type":"Point"}
}