{
  "type": "Feature",
  "properties": {
    "iso:country":"IN",
    "ks:ks_name":"Olatpur",
    "ks:ks_pop":1351,
    "ks:ks_type":"VILLAGE",
    "name:eng_x_preferred":[
        "Olatpur"
    ],
    "wof:name":"Olatpur",
    "wof:placetype":"locality",
    "wof:population":1351
},
  "geometry": {"coordinates":[85.993841,20.230424],"type":"Point"}
}