{
  "type": "Feature",
  "properties": {
    "iso:country":"IN",
    "ks:ks_name":"Kalkar",
    "ks:ks_pop":204,
    "ks:ks_type":"HABITATION",
    "name:eng_x_preferred":[
        "Kalkar"
    ],
    "wof:name":"Kalkar",
    "wof:placetype":"locality",
    "wof:population":204
},
  "geometry": {"coordinates":[75.019299,12.736892],"type":"Point"}
}