{
  "type": "Feature",
  "properties": {
    "iso:country":"IN",
    "ks:ks_name":"Boro Chakiachhara",
    "ks:ks_pop":973,
    "ks:ks_type":"HABITATION",
    "name:eng_x_preferred":[
        "Boro Chakiachhara"
    ],
    "wof:name":"Boro Chakiachhara",
    "wof:placetype":"locality",
    "wof:population":973
},
  "geometry": {"coordinates":[89.26126499999999,26.388953],"type":"Point"}
}