{
  "type": "Feature",
  "properties": {
    "gn:admin1_code":"2.0",
    "gn:admin2_code":"553.0",
    "gn:asciiname":"Kottapalle",
    "gn:country_code":"IN",
    "gn:dem":330,
    "gn:feature_class":"P",
    "gn:feature_code":"PPL",
    "gn:name":"Kottapalle",
    "gn:population":0,
    "gn:timezone":"Asia/Kolkata",
    "iso:country":"IN",
    "wof:name":"Kottapalle",
    "wof:placetype":"neighbourhood"
},
  "geometry": {"coordinates":[77.59871,14.78487],"type":"Point"}
}