{
  "type": "Feature",
  "properties": {
    "iso:country":"IN",
    "ks:ks_name":"Guthi",
    "ks:ks_pop":448,
    "ks:ks_type":"VILLAGE",
    "name:eng_x_preferred":[
        "Guthi"
    ],
    "wof:name":"Guthi",
    "wof:placetype":"locality",
    "wof:population":448
},
  "geometry": {"coordinates":[80.25251799999999,29.928465],"type":"Point"}
}