{
  "type": "Feature",
  "properties": {
    "iso:country":"IN",
    "ks:ks_name":"Beechalapura",
    "ks:ks_pop":3,
    "ks:ks_type":"VILLAGE",
    "name:eng_x_preferred":[
        "Beechalapura"
    ],
    "wof:name":"Beechalapura",
    "wof:placetype":"locality",
    "wof:population":3
},
  "geometry": {"coordinates":[75.93825699999999,12.981798],"type":"Point"}
}