{
  "type": "Feature",
  "properties": {
    "gn:admin1_code":"36",
    "gn:admin2_code":"173.0",
    "gn:asciiname":"Narai",
    "gn:country_code":"IN",
    "gn:dem":110,
    "gn:feature_class":"P",
    "gn:feature_code":"PPL",
    "gn:name":"Narai",
    "gn:population":0,
    "gn:timezone":"Asia/Kolkata",
    "iso:country":"IN",
    "wof:name":"Narai",
    "wof:placetype":"locality"
},
  "geometry": {"coordinates":[81.53220999999998,25.89132],"type":"Point"}
}