{
  "type": "Feature",
  "properties": {
    "iso:country":"IN",
    "ks:ks_name":"Banagarya",
    "ks:ks_pop":346,
    "ks:ks_type":"VILLAGE",
    "name:eng_x_preferred":[
        "Banagarya"
    ],
    "wof:name":"Banagarya",
    "wof:placetype":"locality",
    "wof:population":346
},
  "geometry": {"coordinates":[86.8554,23.058685],"type":"Point"}
}