{
  "type": "Feature",
  "properties": {
    "gn:admin1_code":"35",
    "gn:admin2_code":"455.0",
    "gn:asciiname":"Kalapatha",
    "gn:country_code":"IN",
    "gn:dem":527,
    "gn:feature_class":"P",
    "gn:feature_code":"PPL",
    "gn:name":"K\u0101l\u0101p\u0101tha",
    "gn:population":0,
    "gn:timezone":"Asia/Kolkata",
    "iso:country":"IN",
    "ks:ks_alt_nam":"K\u0101l\u0101p\u0101tha",
    "ks:ks_name":"Kalapatha",
    "ks:ks_pop":314,
    "ks:ks_type":"VILLAGE",
    "name:eng_x_preferred":[
        "Kalapatha"
    ],
    "name:eng_x_variant":[
        "K\u0101l\u0101p\u0101tha"
    ],
    "wof:name":"Kalapatha",
    "wof:placetype":"locality",
    "wof:population":314
},
  "geometry": {"coordinates":[78.573033,21.665481],"type":"Point"}
}