{
  "type": "Feature",
  "properties": {
    "gn:admin1_code":"12.0",
    "gn:asciiname":"Kathlala",
    "gn:country_code":"IN",
    "gn:dem":988,
    "gn:feature_class":"P",
    "gn:feature_code":"PPL",
    "gn:name":"Kathl\u0101la",
    "gn:population":0,
    "gn:timezone":"Asia/Kolkata",
    "iso:country":"IN",
    "name:und_x_variant":[
        "Kathl\u0101la",
        "Kathi\u0101la"
    ],
    "wof:name":"Kathlala",
    "wof:placetype":"locality"
},
  "geometry": {"coordinates":[74.02725,33.23089],"type":"Point"}
}