{
  "type": "Feature",
  "properties": {
    "iso:country":"IN",
    "ks:ks_name":"Amalner",
    "ks:ks_pop":694,
    "ks:ks_type":"VILLAGE",
    "name:eng_x_preferred":[
        "Amalner"
    ],
    "wof:name":"Amalner",
    "wof:placetype":"locality",
    "wof:population":694
},
  "geometry": {"coordinates":[74.619398,19.541332],"type":"Point"}
}