{
  "type": "Feature",
  "properties": {
    "gn:admin1_code":"40.0",
    "gn:admin2_code":"534.0",
    "gn:asciiname":"Shamsabad",
    "gn:country_code":"IN",
    "gn:dem":268,
    "gn:feature_class":"P",
    "gn:feature_code":"PPL",
    "gn:name":"Shams\u0101b\u0101d",
    "gn:population":0,
    "gn:timezone":"Asia/Kolkata",
    "iso:country":"IN",
    "name:bpy_x_preferred":[
        "\u09b6\u09be\u09ae\u09b8\u09be\u09ac\u09be\u09a6"
    ],
    "name:ceb_x_preferred":[
        "Shamsabad"
    ],
    "name:fas_x_preferred":[
        "\u0634\u0645\u0633\u200c\u0622\u0628\u0627\u062f"
    ],
    "name:ita_x_preferred":[
        "Shamsabad"
    ],
    "name:nld_x_preferred":[
        "Shamsabad"
    ],
    "name:pol_x_preferred":[
        "Shamsabad"
    ],
    "name:swe_x_preferred":[
        "Shamsabad"
    ],
    "wof:name":"Shamsabad",
    "wof:placetype":"locality"
},
  "geometry": {"coordinates":[79.26836,18.33295],"type":"Point"}
}