{
  "type": "Feature",
  "properties": {
    "gn:admin1_code":"36",
    "gn:admin2_code":"153.0",
    "gn:asciiname":"Purwa Hira Lal",
    "gn:country_code":"IN",
    "gn:dem":134,
    "gn:feature_class":"P",
    "gn:feature_code":"PPL",
    "gn:name":"Purwa H\u012br\u0101 L\u0101l",
    "gn:population":0,
    "gn:timezone":"Asia/Kolkata",
    "iso:country":"IN",
    "wof:name":"Purwa Hira Lal",
    "wof:placetype":"neighbourhood"
},
  "geometry": {"coordinates":[81.09533,27.90083],"type":"Point"}
}