{
  "type": "Feature",
  "properties": {
    "gn:admin1_code":"36.0",
    "gn:admin2_code":"133",
    "gn:asciiname":"Ambahta Rindan",
    "gn:country_code":"IN",
    "gn:dem":254,
    "gn:feature_class":"P",
    "gn:feature_code":"PPL",
    "gn:name":"Ambahta Rind\u0101n",
    "gn:population":0,
    "gn:timezone":"Asia/Kolkata",
    "iso:country":"IN",
    "wof:name":"Ambahta Rindan",
    "wof:placetype":"locality"
},
  "geometry": {"coordinates":[77.28699999999998,29.56384000000001],"type":"Point"}
}