{
  "type": "Feature",
  "properties": {
    "gn:admin1_code":"23.0",
    "gn:admin2_code":"38.0",
    "gn:asciiname":"Sukhia",
    "gn:country_code":"IN",
    "gn:dem":306,
    "gn:feature_class":"P",
    "gn:feature_code":"PPL",
    "gn:name":"Sukhia",
    "gn:population":0,
    "gn:timezone":"Asia/Kolkata",
    "iso:country":"IN",
    "wof:name":"Sukhia",
    "wof:placetype":"locality"
},
  "geometry": {"coordinates":[75.91488000000003,31.54276],"type":"Point"}
}