{
  "type": "Feature",
  "properties": {
    "iso:country":"IN",
    "ks:ks_name":"Dakwal",
    "ks:ks_pop":326,
    "ks:ks_type":"HABITATION",
    "name:eng_x_preferred":[
        "Dakwal"
    ],
    "wof:name":"Dakwal",
    "wof:placetype":"locality",
    "wof:population":326
},
  "geometry": {"coordinates":[79.91426300000001,26.709621],"type":"Point"}
}