{
  "type": "Feature",
  "properties": {
    "iso:country":"IN",
    "ks:ks_name":"Vadupada",
    "ks:ks_pop":159,
    "ks:ks_type":"HABITATION",
    "name:eng_x_preferred":[
        "Vadupada"
    ],
    "wof:name":"Vadupada",
    "wof:placetype":"locality",
    "wof:population":159
},
  "geometry": {"coordinates":[73.03543000000001,19.771223],"type":"Point"}
}