{
  "type": "Feature",
  "properties": {
    "iso:country":"IN",
    "ks:ks_name":"Sughar Tola",
    "ks:ks_pop":214,
    "ks:ks_type":"VILLAGE",
    "name:eng_x_preferred":[
        "Sughar Tola"
    ],
    "wof:name":"Sughar Tola",
    "wof:placetype":"locality",
    "wof:population":214
},
  "geometry": {"coordinates":[84.406167,26.423346],"type":"Point"}
}