{
  "type": "Feature",
  "properties": {
    "iso:country":"IN",
    "ks:ks_alt_nam":"Venkat\u0101puram",
    "ks:ks_alt_nam_2":"Venkatapuram",
    "ks:ks_name":"B.venkatapuram",
    "ks:ks_pop":0,
    "ks:ks_type":"VILLAGE",
    "name:eng_x_preferred":[
        "B.venkatapuram"
    ],
    "name:eng_x_variant":[
        "Venkat\u0101puram",
        "Venkatapuram"
    ],
    "wof:name":"B.venkatapuram",
    "wof:placetype":"locality",
    "wof:population":0
},
  "geometry": {"coordinates":[78.42788400000001,14.97941],"type":"Point"}
}