{
  "type": "Feature",
  "properties": {
    "gn:admin1_code":"16.0",
    "gn:admin2_code":"508.0",
    "gn:asciiname":"Khandala",
    "gn:country_code":"IN",
    "gn:dem":193,
    "gn:feature_class":"P",
    "gn:feature_code":"PPL",
    "gn:name":"Khand\u0101la",
    "gn:population":0,
    "gn:timezone":"Asia/Kolkata",
    "iso:country":"IN",
    "name:guj_x_preferred":[
        "\u0a96\u0a82\u0aa1\u0abe\u0ab2\u0abe"
    ],
    "name:hin_x_preferred":[
        "\u0916\u0902\u0921\u093e\u0932\u093e"
    ],
    "name:kan_x_preferred":[
        "\u0c96\u0c82\u0ca1\u0cbe\u0cb3\u0cbe"
    ],
    "name:mal_x_preferred":[
        "\u0d16\u0d23\u0d4d\u0d1f\u0d3e\u0d32"
    ],
    "name:san_x_preferred":[
        "\u0916\u0923\u094d\u0921\u093e\u0933\u093e"
    ],
    "wof:name":"Khandala",
    "wof:placetype":"locality"
},
  "geometry": {"coordinates":[79.81079,19.99218],"type":"Point"}
}