{
  "type": "Feature",
  "properties": {
    "gn:admin1_code":"34.0",
    "gn:admin2_code":"220.0",
    "gn:asciiname":"Adampur",
    "gn:country_code":"IN",
    "gn:dem":59,
    "gn:feature_class":"P",
    "gn:feature_code":"PPL",
    "gn:name":"\u0100dampur",
    "gn:population":0,
    "gn:timezone":"Asia/Kolkata",
    "iso:country":"IN",
    "name:ara_x_preferred":[
        "\u0623\u062f\u0645 \u0628\u0648\u0631"
    ],
    "name:ben_bn_x_preferred":[
        "\u0986\u09a6\u09ae\u09aa\u09c1\u09b0"
    ],
    "name:ben_in_x_preferred":[
        "\u0986\u09a6\u09ae\u09aa\u09c1\u09b0"
    ],
    "name:ben_x_preferred":[
        "\u0986\u09a6\u09ae\u09aa\u09c1\u09b0"
    ],
    "name:bpy_x_preferred":[
        "\u0986\u09a6\u09ae\u09aa\u09c1\u09b0"
    ],
    "name:fas_x_preferred":[
        "\u0627\u062f\u0627\u0645\u067e\u0648\u0631"
    ],
    "name:guj_x_preferred":[
        "\u0a86\u0aa6\u0aae\u0aaa\u0ac1\u0ab0"
    ],
    "name:hin_x_preferred":[
        "\u0906\u0926\u092e\u092a\u0941\u0930"
    ],
    "name:ita_x_preferred":[
        "Adampur"
    ],
    "name:kan_x_preferred":[
        "\u0c86\u0ca6\u0cae\u0ccd"
    ],
    "name:mal_x_preferred":[
        "\u0d05\u0d26\u0d3e\u0d02\u0d2a\u0d42\u0d7c"
    ],
    "name:mar_x_preferred":[
        "\u0906\u0926\u092e\u092a\u0942\u0930"
    ],
    "name:min_x_preferred":[
        "Adampur"
    ],
    "name:mlg_x_preferred":[
        "Adampur"
    ],
    "name:msa_x_preferred":[
        "Adampur"
    ],
    "name:new_x_preferred":[
        "\u0906\u0926\u092e\u092a\u0941\u0930"
    ],
    "name:nld_x_preferred":[
        "Adampur"
    ],
    "name:pan_x_preferred":[
        "\u0a06\u0a26\u0a2e\u0a2a\u0a41\u0a30"
    ],
    "name:por_x_preferred":[
        "Adampur"
    ],
    "name:spa_x_preferred":[
        "Adampur"
    ],
    "name:tam_x_preferred":[
        "\u0b86\u0ba4\u0bae\u0bcd\u0baa\u0bc2\u0bb0\u0bcd"
    ],
    "name:tel_x_preferred":[
        "\u0c06\u0c21\u0c02\u0c2a\u0c42\u0c30\u0c4d"
    ],
    "name:urd_x_preferred":[
        "\u0622\u062f\u0645 \u067e\u0648\u0631"
    ],
    "name:vie_x_preferred":[
        "Adampur"
    ],
    "name:zho_x_preferred":[
        "\u963f\u8fbe\u59c6\u666e\u5c14"
    ],
    "wof:name":"Adampur",
    "wof:placetype":"locality"
},
  "geometry": {"coordinates":[85.30733000000002,25.90638],"type":"Point"}
}