{
  "type": "Feature",
  "properties": {
    "gn:admin1_code":"12.0",
    "gn:admin2_code":"2.0",
    "gn:asciiname":"Ganj Lalbur",
    "gn:country_code":"IN",
    "gn:dem":1948,
    "gn:feature_class":"P",
    "gn:feature_code":"PPL",
    "gn:name":"Ganj L\u0101lbur",
    "gn:population":0,
    "gn:timezone":"Asia/Kolkata",
    "iso:country":"IN",
    "wof:name":"Ganj Lalbur",
    "wof:placetype":"locality"
},
  "geometry": {"coordinates":[74.60343,33.97381],"type":"Point"}
}