{
  "type": "Feature",
  "properties": {
    "gn:admin1_code":"2",
    "gn:admin2_code":"544.0",
    "gn:asciiname":"Vakapalle",
    "gn:country_code":"IN",
    "gn:dem":150,
    "gn:feature_class":"P",
    "gn:feature_code":"PPL",
    "gn:name":"V\u0101kapalle",
    "gn:population":0,
    "gn:timezone":"Asia/Kolkata",
    "iso:country":"IN",
    "ks:ks_name":"Vakapalli",
    "ks:ks_pop":101,
    "ks:ks_type":"HABITATION",
    "name:eng_x_preferred":[
        "Vakapalli"
    ],
    "name:eng_x_variant":[
        "Vakapalle"
    ],
    "wof:name":"Vakapalli",
    "wof:placetype":"locality",
    "wof:population":101
},
  "geometry": {"coordinates":[82.848919,17.985165],"type":"Point"}
}