{
  "type": "Feature",
  "properties": {
    "gn:admin1_code":"11.0",
    "gn:admin2_code":"32.0",
    "gn:asciiname":"Mal",
    "gn:country_code":"IN",
    "gn:dem":1851,
    "gn:feature_class":"P",
    "gn:feature_code":"PPL",
    "gn:name":"M\u0101l",
    "gn:population":0,
    "gn:timezone":"Asia/Kolkata",
    "iso:country":"IN",
    "name:hin_x_preferred":[
        "\u092e\u0932"
    ],
    "wof:name":"Mal",
    "wof:placetype":"locality"
},
  "geometry": {"coordinates":[77.34894,30.95261],"type":"Point"}
}