{
  "type": "Feature",
  "properties": {
    "iso:country":"IN",
    "ks:ks_name":"Hanchihalli Colony",
    "ks:ks_pop":345,
    "ks:ks_type":"HABITATION",
    "name:eng_x_preferred":[
        "Hanchihalli Colony"
    ],
    "wof:name":"Hanchihalli Colony",
    "wof:placetype":"locality",
    "wof:population":345
},
  "geometry": {"coordinates":[77.083416,13.412717],"type":"Point"}
}