{
  "type": "Feature",
  "properties": {
    "gn:admin1_code":"36",
    "gn:admin2_code":"201.0",
    "gn:asciiname":"Deonan Kalan",
    "gn:country_code":"IN",
    "gn:dem":162,
    "gn:feature_class":"P",
    "gn:feature_code":"PPL",
    "gn:name":"Deon\u0101n Kal\u0101n",
    "gn:population":0,
    "gn:timezone":"Asia/Kolkata",
    "iso:country":"IN",
    "wof:name":"Deonan Kalan",
    "wof:placetype":"locality"
},
  "geometry": {"coordinates":[79.05237,27.55813],"type":"Point"}
}