{
  "type": "Feature",
  "properties": {
    "iso:country":"IN",
    "ks:ks_name":"Madhu Chapra",
    "ks:ks_pop":1420,
    "ks:ks_type":"VILLAGE",
    "ks:ks_uagg_main":0,
    "name:eng_x_preferred":[
        "Madhu Chapra"
    ],
    "wof:name":"Madhu Chapra",
    "wof:placetype":"neighbourhood",
    "wof:population":1420
},
  "geometry": {"coordinates":[85.23816600000001,26.665983],"type":"Point"}
}