{
  "type": "Feature",
  "properties": {
    "iso:country":"IN",
    "ks:ks_name":"Eachampoond",
    "ks:ks_pop":760,
    "ks:ks_type":"HABITATION",
    "name:eng_x_preferred":[
        "Eachampoond"
    ],
    "wof:name":"Eachampoond",
    "wof:placetype":"locality",
    "wof:population":760
},
  "geometry": {"coordinates":[79.500265,11.197824],"type":"Point"}
}