{
  "type": "Feature",
  "properties": {
    "iso:country":"IN",
    "ks:ks_name":"Vahagaon",
    "ks:ks_pop":3662,
    "ks:ks_type":"HABITATION",
    "name:eng_x_preferred":[
        "Vahagaon"
    ],
    "wof:name":"Vahagaon",
    "wof:placetype":"locality",
    "wof:population":3662
},
  "geometry": {"coordinates":[74.23978099999999,17.232926],"type":"Point"}
}