{
  "type": "Feature",
  "properties": {
    "iso:country":"IN",
    "ks:ks_name":"Kalibari",
    "ks:ks_pop":157,
    "ks:ks_type":"HABITATION",
    "name:eng_x_preferred":[
        "Kalibari"
    ],
    "wof:name":"Kalibari",
    "wof:placetype":"locality",
    "wof:population":157
},
  "geometry": {"coordinates":[91.349137,23.224787],"type":"Point"}
}