{
  "type": "Feature",
  "properties": {
    "iso:country":"IN",
    "ks:ks_alt_nam":"FAKUYA BARI",
    "ks:ks_name":"Fakuya Bari",
    "ks:ks_pop":139,
    "ks:ks_type":"HABITATION",
    "name:eng_x_preferred":[
        "Fakuya Bari"
    ],
    "wof:name":"Fakuya Bari",
    "wof:placetype":"locality",
    "wof:population":139
},
  "geometry": {"coordinates":[91.56422000000001,23.942363],"type":"Point"}
}