{
  "type": "Feature",
  "properties": {
    "iso:country":"IN",
    "ks:ks_alt_nam":"RanapadaII",
    "ks:ks_name":"Ranapadaii",
    "ks:ks_pop":94,
    "ks:ks_type":"HABITATION",
    "name:eng_x_preferred":[
        "Ranapadaii"
    ],
    "wof:name":"Ranapadaii",
    "wof:placetype":"locality",
    "wof:population":94
},
  "geometry": {"coordinates":[82.646638,19.5883],"type":"Point"}
}