{
  "type": "Feature",
  "properties": {
    "gn:admin1_code":"34.0",
    "gn:admin2_code":"229.0",
    "gn:asciiname":"Rajwa",
    "gn:country_code":"IN",
    "gn:dem":59,
    "gn:feature_class":"P",
    "gn:feature_code":"PPL",
    "gn:name":"Rajwa",
    "gn:population":0,
    "gn:timezone":"Asia/Kolkata",
    "iso:country":"IN",
    "ks:ks_name":"Rajwa",
    "ks:ks_pop":570,
    "ks:ks_type":"VILLAGE",
    "name:eng_x_preferred":[
        "Rajwa"
    ],
    "wof:name":"Rajwa",
    "wof:placetype":"locality",
    "wof:population":570
},
  "geometry": {"coordinates":[85.332295,25.252251],"type":"Point"}
}