{
  "type": "Feature",
  "properties": {
    "iso:country":"IN",
    "ks:ks_alt_nam":"MANJHALADIH",
    "ks:ks_name":"Manjhaladih",
    "ks:ks_pop":150,
    "ks:ks_type":"HABITATION",
    "name:eng_x_preferred":[
        "Manjhaladih"
    ],
    "wof:name":"Manjhaladih",
    "wof:placetype":"locality",
    "wof:population":150
},
  "geometry": {"coordinates":[85.655558,24.63259],"type":"Point"}
}