{
  "type": "Feature",
  "properties": {
    "iso:country":"IN",
    "ks:ks_name":"Naugawan No.3",
    "ks:ks_pop":18,
    "ks:ks_type":"VILLAGE",
    "name:eng_x_preferred":[
        "Naugawan No.3"
    ],
    "wof:name":"Naugawan No.3",
    "wof:placetype":"locality",
    "wof:population":18
},
  "geometry": {"coordinates":[81.22711099999999,24.244182],"type":"Point"}
}