{
  "type": "Feature",
  "properties": {
    "iso:country":"IN",
    "ks:ks_name":"Sahni Tola",
    "ks:ks_pop":595,
    "ks:ks_type":"HABITATION",
    "ks:ks_uagg_main":0,
    "name:eng_x_preferred":[
        "Sahni Tola"
    ],
    "wof:name":"Sahni Tola",
    "wof:placetype":"neighbourhood",
    "wof:population":595
},
  "geometry": {"coordinates":[86.078216,25.676027],"type":"Point"}
}