{
  "type": "Feature",
  "properties": {
    "gn:admin1_code":"37",
    "gn:admin2_code":"404.0",
    "gn:asciiname":"Ratkhandi",
    "gn:country_code":"IN",
    "gn:dem":412,
    "gn:feature_class":"P",
    "gn:feature_code":"PPL",
    "gn:name":"Ratkhandi",
    "gn:population":0,
    "gn:timezone":"Asia/Kolkata",
    "iso:country":"IN",
    "ks:ks_name":"Ratkhandi",
    "ks:ks_pop":1443,
    "ks:ks_type":"VILLAGE",
    "name:eng_x_preferred":[
        "Ratkhandi"
    ],
    "wof:name":"Ratkhandi",
    "wof:placetype":"locality",
    "wof:population":1443
},
  "geometry": {"coordinates":[82.22673500000001,22.569083],"type":"Point"}
}