{
  "type": "Feature",
  "properties": {
    "iso:country":"IN",
    "ks:ks_name":"Telageri",
    "ks:ks_pop":80,
    "ks:ks_type":"HABITATION",
    "name:eng_x_preferred":[
        "Telageri"
    ],
    "wof:name":"Telageri",
    "wof:placetype":"locality",
    "wof:population":80
},
  "geometry": {"coordinates":[74.739344,15.005054],"type":"Point"}
}