{
  "type": "Feature",
  "properties": {
    "iso:country":"IN",
    "ks:ks_name":"Durjantaila",
    "ks:ks_pop":306,
    "ks:ks_type":"VILLAGE",
    "name:eng_x_preferred":[
        "Durjantaila"
    ],
    "wof:name":"Durjantaila",
    "wof:placetype":"locality",
    "wof:population":306
},
  "geometry": {"coordinates":[84.028052,21.041186],"type":"Point"}
}