{
  "type": "Feature",
  "properties": {
    "gn:admin1_code":"16.0",
    "gn:admin2_code":"513.0",
    "gn:asciiname":"Jaithapurwadi",
    "gn:country_code":"IN",
    "gn:dem":416,
    "gn:feature_class":"P",
    "gn:feature_code":"PPL",
    "gn:name":"Jaith\u0101purw\u0101di",
    "gn:population":0,
    "gn:timezone":"Asia/Kolkata",
    "iso:country":"IN",
    "wof:name":"Jaithapurwadi",
    "wof:placetype":"locality"
},
  "geometry": {"coordinates":[76.40697,19.21908],"type":"Point"}
}