{
  "type": "Feature",
  "properties": {
    "iso:country":"IN",
    "ks:ks_name":"Bhumiheen Colony W 5",
    "ks:ks_pop":584,
    "ks:ks_type":"HABITATION",
    "name:eng_x_preferred":[
        "Bhumiheen Colony W 5"
    ],
    "wof:name":"Bhumiheen Colony W 5",
    "wof:placetype":"locality",
    "wof:population":584
},
  "geometry": {"coordinates":[92.18292,24.311623],"type":"Point"}
}