{
  "type": "Feature",
  "properties": {
    "iso:country":"IN",
    "ks:ks_name":"Kamra",
    "ks:ks_pop":53,
    "ks:ks_type":"VILLAGE",
    "name:eng_x_preferred":[
        "Kamra"
    ],
    "wof:name":"Kamra",
    "wof:placetype":"locality",
    "wof:population":53
},
  "geometry": {"coordinates":[78.12084299999999,31.040311],"type":"Point"}
}