{
  "type": "Feature",
  "properties": {
    "iso:country":"IN",
    "ks:ks_name":"Tiarasahi",
    "ks:ks_pop":529,
    "ks:ks_type":"VILLAGE",
    "ks:ks_uagg_main":0,
    "name:eng_x_preferred":[
        "Tiarasahi"
    ],
    "wof:name":"Tiarasahi",
    "wof:placetype":"neighbourhood",
    "wof:population":529
},
  "geometry": {"coordinates":[85.46794,20.334348],"type":"Point"}
}