{
  "type": "Feature",
  "properties": {
    "iso:country":"IN",
    "ks:ks_name":"Karballa Purwa",
    "ks:ks_pop":66,
    "ks:ks_type":"HABITATION",
    "name:eng_x_preferred":[
        "Karballa Purwa"
    ],
    "wof:name":"Karballa Purwa",
    "wof:placetype":"locality",
    "wof:population":66
},
  "geometry": {"coordinates":[81.530788,27.082925],"type":"Point"}
}