{
  "type": "Feature",
  "properties": {
    "iso:country":"IN",
    "ks:ks_name":"Chatakpur",
    "ks:ks_pop":237,
    "ks:ks_type":"HABITATION",
    "name:eng_x_preferred":[
        "Chatakpur"
    ],
    "wof:name":"Chatakpur",
    "wof:placetype":"locality",
    "wof:population":237
},
  "geometry": {"coordinates":[84.688928,22.933002],"type":"Point"}
}