{
  "type": "Feature",
  "properties": {
    "iso:country":"IN",
    "ks:ks_alt_nam":"Jarnagar II",
    "ks:ks_name":"Jarnagar Ii",
    "ks:ks_pop":250,
    "ks:ks_type":"HABITATION",
    "name:eng_x_preferred":[
        "Jarnagar Ii"
    ],
    "wof:name":"Jarnagar Ii",
    "wof:placetype":"locality",
    "wof:population":250
},
  "geometry": {"coordinates":[90.335559,26.284589],"type":"Point"}
}