{
  "type": "Feature",
  "properties": {
    "iso:country":"IN",
    "ks:ks_alt_nam":"School Rd junction",
    "ks:ks_name":"School Rd Junction",
    "ks:ks_pop":1292,
    "ks:ks_type":"HABITATION",
    "ks:ks_uagg_main":0,
    "name:eng_x_preferred":[
        "School Rd Junction"
    ],
    "wof:name":"School Rd Junction",
    "wof:placetype":"neighbourhood",
    "wof:population":1292
},
  "geometry": {"coordinates":[75.889961,10.902992],"type":"Point"}
}