{
  "type": "Feature",
  "properties": {
    "iso:country":"IN",
    "ks:ks_name":"Meesalamane",
    "ks:ks_pop":80,
    "ks:ks_type":"HABITATION",
    "name:eng_x_preferred":[
        "Meesalamane"
    ],
    "wof:name":"Meesalamane",
    "wof:placetype":"locality",
    "wof:population":80
},
  "geometry": {"coordinates":[75.711134,12.90613],"type":"Point"}
}