{
  "type": "Feature",
  "properties": {
    "iso:country":"IN",
    "ks:ks_name":"Dhaktewadi",
    "ks:ks_pop":422,
    "ks:ks_type":"HABITATION",
    "name:eng_x_preferred":[
        "Dhaktewadi"
    ],
    "wof:name":"Dhaktewadi",
    "wof:placetype":"locality",
    "wof:population":422
},
  "geometry": {"coordinates":[76.97736999999999,18.658483],"type":"Point"}
}