{
  "type": "Feature",
  "properties": {
    "iso:country":"IN",
    "ks:ks_name":"Mahadikwadi",
    "ks:ks_pop":62,
    "ks:ks_type":"HABITATION",
    "name:eng_x_preferred":[
        "Mahadikwadi"
    ],
    "wof:name":"Mahadikwadi",
    "wof:placetype":"locality",
    "wof:population":62
},
  "geometry": {"coordinates":[73.401844,17.6445],"type":"Point"}
}