{
  "type": "Feature",
  "properties": {
    "gn:admin1_code":"35",
    "gn:admin2_code":"451.0",
    "gn:asciiname":"Akona",
    "gn:country_code":"IN",
    "gn:dem":367,
    "gn:feature_class":"P",
    "gn:feature_code":"PPL",
    "gn:name":"Akona",
    "gn:population":0,
    "gn:timezone":"Asia/Kolkata",
    "iso:country":"IN",
    "name:fas_x_preferred":[
        "\u0627\u06a9\u0648\u0646\u0627"
    ],
    "name:hin_x_preferred":[
        "\u0905\u0915\u094c\u0928\u093e"
    ],
    "wof:name":"Akona",
    "wof:placetype":"locality"
},
  "geometry": {"coordinates":[79.75711,23.41617],"type":"Point"}
}