{
  "type": "Feature",
  "properties": {
    "gn:admin1_code":"11",
    "gn:admin2_code":"24.0",
    "gn:asciiname":"Bhalotha",
    "gn:country_code":"IN",
    "gn:dem":1664,
    "gn:feature_class":"P",
    "gn:feature_code":"PPL",
    "gn:name":"Bhalotha",
    "gn:population":0,
    "gn:timezone":"Asia/Kolkata",
    "iso:country":"IN",
    "wof:name":"Bhalotha",
    "wof:placetype":"locality"
},
  "geometry": {"coordinates":[76.26198000000002,32.25482],"type":"Point"}
}