{
  "type": "Feature",
  "properties": {
    "iso:country":"IN",
    "ks:ks_alt_nam":"S\u012bkera",
    "ks:ks_name":"Sikera",
    "ks:ks_pop":1092,
    "ks:ks_type":"VILLAGE",
    "ks:ks_uagg_main":0,
    "name:eng_x_preferred":[
        "Sikera"
    ],
    "name:eng_x_variant":[
        "S\u012bkera"
    ],
    "wof:name":"Sikera",
    "wof:placetype":"neighbourhood",
    "wof:population":1092
},
  "geometry": {"coordinates":[78.253167,29.415016],"type":"Point"}
}