{
  "type": "Feature",
  "properties": {
    "iso:country":"IN",
    "ks:ks_name":"Paik Bheri",
    "ks:ks_pop":1000,
    "ks:ks_type":"VILLAGE",
    "name:eng_x_preferred":[
        "Paik Bheri"
    ],
    "wof:name":"Paik Bheri",
    "wof:placetype":"locality",
    "wof:population":1000
},
  "geometry": {"coordinates":[87.725706,22.100909],"type":"Point"}
}