{
  "type": "Feature",
  "properties": {
    "gn:admin1_code":"21.0",
    "gn:admin2_code":"388",
    "gn:asciiname":"Gazalbarhi",
    "gn:country_code":"IN",
    "gn:dem":196,
    "gn:feature_class":"P",
    "gn:feature_code":"PPL",
    "gn:name":"Gazalb\u0101rhi",
    "gn:population":0,
    "gn:timezone":"Asia/Kolkata",
    "iso:country":"IN",
    "name:und_x_variant":[
        "G\u0101dulab\u0101di",
        "Gazalb\u0101rhi"
    ],
    "wof:name":"Gazalbarhi",
    "wof:placetype":"locality"
},
  "geometry": {"coordinates":[84.28333000000001,19.84741],"type":"Point"}
}