{
  "type": "Feature",
  "properties": {
    "iso:country":"IN",
    "ks:ks_name":"Moyampara",
    "ks:ks_pop":302,
    "ks:ks_type":"HABITATION",
    "name:eng_x_preferred":[
        "Moyampara"
    ],
    "wof:name":"Moyampara",
    "wof:placetype":"locality",
    "wof:population":302
},
  "geometry": {"coordinates":[80.578818,18.741636],"type":"Point"}
}