{
  "type": "Feature",
  "properties": {
    "gn:country":"IN",
    "gn:fcode":"PPL",
    "gn:pop":12886,
    "iso:country":"IN",
    "name:ben_x_preferred":[
        "\u09ae\u09be\u0996\u09c1"
    ],
    "name:bpy_x_preferred":[
        "\u09ae\u09be\u0996\u09c1"
    ],
    "name:ceb_x_preferred":[
        "Makhu"
    ],
    "name:eng_x_preferred":[
        "Makhu"
    ],
    "name:fra_x_preferred":[
        "Makhu"
    ],
    "name:ita_x_preferred":[
        "Makhu"
    ],
    "name:mlg_x_preferred":[
        "Makhu"
    ],
    "name:msa_x_preferred":[
        "Makhu"
    ],
    "name:nan_x_preferred":[
        "Makhu"
    ],
    "name:new_x_preferred":[
        "\u092e\u0916\u0941"
    ],
    "name:nld_x_preferred":[
        "Makhu"
    ],
    "name:por_x_preferred":[
        "Makhu"
    ],
    "name:spa_x_preferred":[
        "Makhu"
    ],
    "name:swe_x_preferred":[
        "Makhu"
    ],
    "name:vie_x_preferred":[
        "Makhu"
    ],
    "name:zho_x_preferred":[
        "\u9a6c\u5e93"
    ],
    "qs:name":"Makhu",
    "qs:name_adm0":"India",
    "qs:name_adm1":"Punjab",
    "qs:photos":11,
    "qs:photos_1k":2,
    "qs:photos_9k":1,
    "qs:photos_9r":1,
    "qs:photos_all":11,
    "qs:photos_sr":1,
    "qs:placetype":"Town",
    "qs:pop_sr":"6",
    "wd:wordcount":228,
    "wof:name":"Makhu",
    "wof:placetype":"locality",
    "wof:population":12886
},
  "geometry": {"coordinates":[74.9969,31.1023],"type":"Point"}
}