{
  "type": "Feature",
  "properties": {
    "gn:admin1_code":"38",
    "gn:admin2_code":"346.0",
    "gn:asciiname":"Baghwar",
    "gn:country_code":"IN",
    "gn:dem":445,
    "gn:feature_class":"P",
    "gn:feature_code":"PPL",
    "gn:name":"B\u0101ghw\u0101r",
    "gn:population":0,
    "gn:timezone":"Asia/Kolkata",
    "iso:country":"IN",
    "ks:ks_alt_nam":"B\u0101ghw\u0101r",
    "ks:ks_name":"Baghwar",
    "ks:ks_pop":2379,
    "ks:ks_type":"VILLAGE",
    "name:eng_x_preferred":[
        "Baghwar"
    ],
    "name:eng_x_variant":[
        "B\u0101ghw\u0101r"
    ],
    "wof:name":"Baghwar",
    "wof:placetype":"locality",
    "wof:population":2379
},
  "geometry": {"coordinates":[83.75199600000001,23.719334],"type":"Point"}
}