{
  "type": "Feature",
  "properties": {
    "iso:country":"IN",
    "ks:ks_name":"Udheni",
    "ks:ks_pop":180,
    "ks:ks_type":"VILLAGE",
    "name:eng_x_preferred":[
        "Udheni"
    ],
    "wof:name":"Udheni",
    "wof:placetype":"locality",
    "wof:population":180
},
  "geometry": {"coordinates":[82.46791,23.731295],"type":"Point"}
}