{
  "type": "Feature",
  "properties": {
    "gn:admin1_code":"35.0",
    "gn:admin2_code":"453.0",
    "gn:asciiname":"Tikra Maheshpuri",
    "gn:country_code":"IN",
    "gn:dem":783,
    "gn:feature_class":"P",
    "gn:feature_code":"PPL",
    "gn:name":"Tikra Maheshpuri",
    "gn:population":0,
    "gn:timezone":"Asia/Kolkata",
    "iso:country":"IN",
    "ks:ks_name":"Tikra Maheshpuri",
    "ks:ks_type":"VILLAGE",
    "name:eng_x_preferred":[
        "Tikra Maheshpuri"
    ],
    "wof:name":"Tikra Maheshpuri",
    "wof:placetype":"locality"
},
  "geometry": {"coordinates":[80.75440999999999,23.070164],"type":"Point"}
}