{
  "type": "Feature",
  "properties": {
    "iso:country":"IN",
    "ks:ks_name":"Venkatappana Doddi",
    "ks:ks_pop":12,
    "ks:ks_type":"HABITATION",
    "name:eng_x_preferred":[
        "Venkatappana Doddi"
    ],
    "wof:name":"Venkatappana Doddi",
    "wof:placetype":"locality",
    "wof:population":12
},
  "geometry": {"coordinates":[77.29277999999999,12.521053],"type":"Point"}
}