{
  "type": "Feature",
  "properties": {
    "iso:country":"IN",
    "ks:ks_name":"Sadika",
    "ks:ks_pop":139,
    "ks:ks_type":"VILLAGE",
    "name:eng_x_preferred":[
        "Sadika"
    ],
    "wof:name":"Sadika",
    "wof:placetype":"locality",
    "wof:population":139
},
  "geometry": {"coordinates":[82.41294000000001,17.841137],"type":"Point"}
}