{
  "type": "Feature",
  "properties": {
    "iso:country":"IN",
    "ks:ks_name":"Gadekoppa",
    "ks:ks_pop":62,
    "ks:ks_type":"HABITATION",
    "name:eng_x_preferred":[
        "Gadekoppa"
    ],
    "wof:name":"Gadekoppa",
    "wof:placetype":"locality",
    "wof:population":62
},
  "geometry": {"coordinates":[74.99882700000001,14.050887],"type":"Point"}
}