{
  "type": "Feature",
  "properties": {
    "iso:country":"IN",
    "ks:ks_name":"Illupuli",
    "ks:ks_pop":1231,
    "ks:ks_type":"VILLAGE",
    "name:eng_x_preferred":[
        "Illupuli"
    ],
    "wof:name":"Illupuli",
    "wof:placetype":"locality",
    "wof:population":1231
},
  "geometry": {"coordinates":[78.01832899999999,11.356934],"type":"Point"}
}