{
  "type": "Feature",
  "properties": {
    "iso:country":"IN",
    "ks:ks_name":"Chhatramandal",
    "ks:ks_pop":377,
    "ks:ks_type":"VILLAGE",
    "name:eng_x_preferred":[
        "Chhatramandal"
    ],
    "wof:name":"Chhatramandal",
    "wof:placetype":"locality",
    "wof:population":377
},
  "geometry": {"coordinates":[86.32207,22.318973],"type":"Point"}
}