{
  "type": "Feature",
  "properties": {
    "iso:country":"IN",
    "ks:ks_name":"Betbari No.1",
    "ks:ks_pop":867,
    "ks:ks_type":"VILLAGE",
    "name:eng_x_preferred":[
        "Betbari No.1"
    ],
    "wof:name":"Betbari No.1",
    "wof:placetype":"locality",
    "wof:population":867
},
  "geometry": {"coordinates":[90.789778,26.563129],"type":"Point"}
}