{
  "type": "Feature",
  "properties": {
    "iso:country":"IN",
    "ks:ks_name":"Shelgaon",
    "ks:ks_pop":593,
    "ks:ks_type":"HABITATION",
    "name:eng_x_preferred":[
        "Shelgaon"
    ],
    "wof:name":"Shelgaon",
    "wof:placetype":"locality",
    "wof:population":593
},
  "geometry": {"coordinates":[76.58654199999999,20.721002],"type":"Point"}
}