{
  "type": "Feature",
  "properties": {
    "iso:country":"IN",
    "ks:ks_name":"Madia",
    "ks:ks_pop":157,
    "ks:ks_type":"HABITATION",
    "name:eng_x_preferred":[
        "Madia"
    ],
    "wof:name":"Madia",
    "wof:placetype":"locality",
    "wof:population":157
},
  "geometry": {"coordinates":[80.69323199999999,27.180561],"type":"Point"}
}