{
  "type": "Feature",
  "properties": {
    "gn:admin1_code":"35",
    "gn:admin2_code":"451.0",
    "gn:asciiname":"Beohari",
    "gn:country_code":"IN",
    "gn:dem":378,
    "gn:feature_class":"P",
    "gn:feature_code":"PPL",
    "gn:name":"Beoh\u0101ri",
    "gn:population":0,
    "gn:timezone":"Asia/Kolkata",
    "iso:country":"IN",
    "name:ben_x_preferred":[
        "\u09ac\u09c7\u0993\u09b9\u09be\u09b0\u09bf"
    ],
    "name:bpy_x_preferred":[
        "\u09ac\u09c7\u0993\u09b9\u09be\u09b0\u09bf"
    ],
    "name:ceb_x_preferred":[
        "Beoh\u0101ri"
    ],
    "name:ind_x_preferred":[
        "Beohari"
    ],
    "name:ita_x_preferred":[
        "Beohari"
    ],
    "name:mlg_x_preferred":[
        "Beohari"
    ],
    "name:msa_x_preferred":[
        "Beohari"
    ],
    "name:new_x_preferred":[
        "\u092c\u0947\u0913\u0939\u093e\u0930\u0940"
    ],
    "name:nld_x_preferred":[
        "Beohari"
    ],
    "name:por_x_preferred":[
        "Beohari"
    ],
    "name:spa_x_preferred":[
        "Beohari"
    ],
    "name:swe_x_preferred":[
        "Beoh\u0101ri"
    ],
    "name:vie_x_preferred":[
        "Beohari"
    ],
    "name:zho_x_preferred":[
        "\u8d1d\u5965\u54c8\u91cc"
    ],
    "wof:name":"Beohari",
    "wof:placetype":"locality"
},
  "geometry": {"coordinates":[79.76561,23.3259],"type":"Point"}
}