{
  "type": "Feature",
  "properties": {
    "iso:country":"IN",
    "ks:ks_name":"Panjikallu",
    "ks:ks_pop":276,
    "ks:ks_type":"HABITATION",
    "name:eng_x_preferred":[
        "Panjikallu"
    ],
    "wof:name":"Panjikallu",
    "wof:placetype":"locality",
    "wof:population":276
},
  "geometry": {"coordinates":[75.123023,12.693052],"type":"Point"}
}