{
  "type": "Feature",
  "properties": {
    "iso:country":"IN",
    "ks:ks_name":"Marbattola",
    "ks:ks_pop":28,
    "ks:ks_type":"HABITATION",
    "name:eng_x_preferred":[
        "Marbattola"
    ],
    "wof:name":"Marbattola",
    "wof:placetype":"locality",
    "wof:population":28
},
  "geometry": {"coordinates":[80.336112,21.056157],"type":"Point"}
}