{
  "type": "Feature",
  "properties": {
    "iso:country":"IN",
    "ks:ks_name":"Digha Danri",
    "ks:ks_pop":773,
    "ks:ks_type":"VILLAGE",
    "name:eng_x_preferred":[
        "Digha Danri"
    ],
    "wof:name":"Digha Danri",
    "wof:placetype":"locality",
    "wof:population":773
},
  "geometry": {"coordinates":[87.720253,21.940258],"type":"Point"}
}