{
  "type": "Feature",
  "properties": {
    "iso:country":"IN",
    "ks:ks_name":"Pandey Ka Pura",
    "ks:ks_pop":125,
    "ks:ks_type":"HABITATION",
    "name:eng_x_preferred":[
        "Pandey Ka Pura"
    ],
    "wof:name":"Pandey Ka Pura",
    "wof:placetype":"locality",
    "wof:population":125
},
  "geometry": {"coordinates":[82.495758,26.451154],"type":"Point"}
}