{
  "type": "Feature",
  "properties": {
    "iso:country":"IN",
    "ks:ks_name":"Melinakeri",
    "ks:ks_pop":55,
    "ks:ks_type":"HABITATION",
    "name:eng_x_preferred":[
        "Melinakeri"
    ],
    "wof:name":"Melinakeri",
    "wof:placetype":"locality",
    "wof:population":55
},
  "geometry": {"coordinates":[74.419642,14.309281],"type":"Point"}
}