{
  "type": "Feature",
  "properties": {
    "iso:country":"IN",
    "ks:ks_name":"Patrauwa",
    "ks:ks_pop":2771,
    "ks:ks_type":"VILLAGE",
    "name:eng_x_preferred":[
        "Patrauwa"
    ],
    "wof:name":"Patrauwa",
    "wof:placetype":"neighbourhood",
    "wof:population":2771
},
  "geometry": {"coordinates":[78.764645,28.443611],"type":"Point"}
}