{
  "type": "Feature",
  "properties": {
    "gn:admin1_code":"25.0",
    "gn:admin2_code":"610.0",
    "gn:asciiname":"Nattanayakkampalaiyam",
    "gn:country_code":"IN",
    "gn:dem":231,
    "gn:feature_class":"P",
    "gn:feature_code":"PPL",
    "gn:name":"Nattan\u0101yakkamp\u0101laiyam",
    "gn:population":0,
    "gn:timezone":"Asia/Kolkata",
    "iso:country":"IN",
    "wof:name":"Nattanayakkampalaiyam",
    "wof:placetype":"locality"
},
  "geometry": {"coordinates":[77.65855999999999,11.28232],"type":"Point"}
}