{
  "type": "Feature",
  "properties": {
    "gn:admin1_code":"25.0",
    "gn:admin2_code":"619.0",
    "gn:asciiname":"Mullaivasal",
    "gn:country_code":"IN",
    "gn:dem":25,
    "gn:feature_class":"P",
    "gn:feature_code":"PPL",
    "gn:name":"Mullaiv\u0101sal",
    "gn:population":0,
    "gn:timezone":"Asia/Kolkata",
    "iso:country":"IN",
    "ks:ks_name":"Mullaivasal",
    "ks:ks_pop":626,
    "ks:ks_type":"HABITATION",
    "name:eng_x_preferred":[
        "Mullaivasal"
    ],
    "wof:name":"Mullaivasal",
    "wof:placetype":"locality",
    "wof:population":626
},
  "geometry": {"coordinates":[79.42412299999999,10.756627],"type":"Point"}
}