{
  "type": "Feature",
  "properties": {
    "gn:admin1_code":"35",
    "gn:admin2_code":"466.0",
    "gn:asciiname":"Khar",
    "gn:country_code":"IN",
    "gn:dem":321,
    "gn:feature_class":"P",
    "gn:feature_code":"PPL",
    "gn:name":"Khar",
    "gn:population":0,
    "gn:timezone":"Asia/Kolkata",
    "iso:country":"IN",
    "name:ceb_x_preferred":[
        "Khar"
    ],
    "name:deu_x_preferred":[
        "Khar"
    ],
    "name:swe_x_preferred":[
        "Khar"
    ],
    "wof:name":"Khar",
    "wof:placetype":"locality"
},
  "geometry": {"coordinates":[76.62886999999998,21.77202],"type":"Point"}
}