{
  "type": "Feature",
  "properties": {
    "iso:country":"IN",
    "ks:ks_name":"Luhasa",
    "ks:ks_pop":986,
    "ks:ks_type":"VILLAGE",
    "name:eng_x_preferred":[
        "Luhasa"
    ],
    "wof:name":"Luhasa",
    "wof:placetype":"locality",
    "wof:population":986
},
  "geometry": {"coordinates":[77.22426299999999,27.022601],"type":"Point"}
}