{
  "type": "Feature",
  "properties": {
    "iso:country":"IN",
    "ks:ks_name":"Narikkudi",
    "ks:ks_pop":210,
    "ks:ks_type":"HABITATION",
    "name:eng_x_preferred":[
        "Narikkudi"
    ],
    "wof:name":"Narikkudi",
    "wof:placetype":"locality",
    "wof:population":210
},
  "geometry": {"coordinates":[79.040299,10.038361],"type":"Point"}
}