{
  "type": "Feature",
  "properties": {
    "iso:country":"IN",
    "ks:ks_name":"Chuto Kandoli 2",
    "ks:ks_pop":373,
    "ks:ks_type":"HABITATION",
    "ks:ks_uagg_main":0,
    "name:eng_x_preferred":[
        "Chuto Kandoli 2"
    ],
    "wof:name":"Chuto Kandoli 2",
    "wof:placetype":"neighbourhood",
    "wof:population":373
},
  "geometry": {"coordinates":[92.787561,26.258663],"type":"Point"}
}