{
  "type": "Feature",
  "properties": {
    "iso:country":"IN",
    "ks:ks_alt_nam":"Patn\u0101",
    "ks:ks_name":"Patna",
    "ks:ks_pop":717,
    "ks:ks_type":"VILLAGE",
    "name:eng_x_preferred":[
        "Patna"
    ],
    "name:eng_x_variant":[
        "Patn\u0101"
    ],
    "wof:name":"Patna",
    "wof:placetype":"locality",
    "wof:population":717
},
  "geometry": {"coordinates":[84.34497,23.92542],"type":"Point"}
}