{
  "type": "Feature",
  "properties": {
    "gn:admin1_code":"36",
    "gn:admin2_code":"186.0",
    "gn:asciiname":"Manguwa",
    "gn:country_code":"IN",
    "gn:dem":89,
    "gn:feature_class":"P",
    "gn:feature_code":"PPL",
    "gn:name":"Manguwa",
    "gn:population":0,
    "gn:timezone":"Asia/Kolkata",
    "iso:country":"IN",
    "ks:ks_name":"Manguwa",
    "ks:ks_pop":517,
    "ks:ks_type":"VILLAGE",
    "ks:ks_uagg_main":0,
    "name:eng_x_preferred":[
        "Manguwa"
    ],
    "wof:name":"Manguwa",
    "wof:placetype":"neighbourhood",
    "wof:population":517
},
  "geometry": {"coordinates":[82.91992,26.917295],"type":"Point"}
}