{
  "type": "Feature",
  "properties": {
    "iso:country":"IN",
    "ks:ks_alt_nam":"Nagla T\u0101shi Q\u0101simpur",
    "ks:ks_name":"Nagla Tashi Qasimpur",
    "ks:ks_type":"VILLAGE",
    "ks:ks_uagg_main":0,
    "name:eng_x_preferred":[
        "Nagla Tashi Qasimpur"
    ],
    "name:eng_x_variant":[
        "Nagla T\u0101shi Q\u0101simpur"
    ],
    "wof:name":"Nagla Tashi Qasimpur",
    "wof:placetype":"neighbourhood"
},
  "geometry": {"coordinates":[77.66767,29.03166],"type":"Point"}
}