{
  "type": "Feature",
  "properties": {
    "gn:admin1_code":"39.0",
    "gn:admin2_code":"68.0",
    "gn:asciiname":"Dandheri Khwajgipur",
    "gn:country_code":"IN",
    "gn:dem":257,
    "gn:feature_class":"P",
    "gn:feature_code":"PPL",
    "gn:name":"Dandheri Khw\u0101jg\u012bpur",
    "gn:population":0,
    "gn:timezone":"Asia/Kolkata",
    "iso:country":"IN",
    "wof:name":"Dandheri Khwajgipur",
    "wof:placetype":"locality"
},
  "geometry": {"coordinates":[77.95524,29.86838],"type":"Point"}
}