{
  "type": "Feature",
  "properties": {
    "iso:country":"IN",
    "ks:ks_name":"Ghumatwasti",
    "ks:ks_pop":200,
    "ks:ks_type":"HABITATION",
    "name:eng_x_preferred":[
        "Ghumatwasti"
    ],
    "wof:name":"Ghumatwasti",
    "wof:placetype":"locality",
    "wof:population":200
},
  "geometry": {"coordinates":[74.638678,17.718335],"type":"Point"}
}