{
  "type": "Feature",
  "properties": {
    "iso:country":"IN",
    "ks:ks_name":"Barplai",
    "ks:ks_pop":57,
    "ks:ks_type":"HABITATION",
    "name:eng_x_preferred":[
        "Barplai"
    ],
    "wof:name":"Barplai",
    "wof:placetype":"locality",
    "wof:population":57
},
  "geometry": {"coordinates":[83.30538199999999,22.206422],"type":"Point"}
}