{
  "type": "Feature",
  "properties": {
    "iso:country":"IN",
    "ks:ks_name":"Ng. Panchee",
    "ks:ks_pop":480,
    "ks:ks_type":"HABITATION",
    "name:eng_x_preferred":[
        "Ng. Panchee"
    ],
    "wof:name":"Ng. Panchee",
    "wof:placetype":"locality",
    "wof:population":480
},
  "geometry": {"coordinates":[78.76804799999999,27.443284],"type":"Point"}
}