{
  "type": "Feature",
  "properties": {
    "gn:admin1_code":"36",
    "gn:admin2_code":"134.0",
    "gn:asciiname":"Badhawa",
    "gn:country_code":"IN",
    "gn:dem":237,
    "gn:feature_class":"P",
    "gn:feature_code":"PPL",
    "gn:name":"Badh\u0101wa",
    "gn:population":0,
    "gn:timezone":"Asia/Kolkata",
    "iso:country":"IN",
    "name:und_x_variant":[
        "Badh\u0101wa",
        "Tirkampur Hafiz"
    ],
    "wof:name":"Badhawa",
    "wof:placetype":"neighbourhood"
},
  "geometry": {"coordinates":[78.31088,29.35103],"type":"Point"}
}