{
  "type": "Feature",
  "properties": {
    "iso:country":"IN",
    "ks:ks_alt_nam":"MOTI PIRKHIND MARG",
    "ks:ks_name":"Moti Pirkhind Marg",
    "ks:ks_pop":128,
    "ks:ks_type":"HABITATION",
    "name:eng_x_preferred":[
        "Moti Pirkhind Marg"
    ],
    "wof:name":"Moti Pirkhind Marg",
    "wof:placetype":"locality",
    "wof:population":128
},
  "geometry": {"coordinates":[74.793403,16.927752],"type":"Point"}
}