{
  "type": "Feature",
  "properties": {
    "iso:country":"IN",
    "ks:ks_name":"Chamruti",
    "ks:ks_pop":566,
    "ks:ks_type":"HABITATION",
    "name:eng_x_preferred":[
        "Chamruti"
    ],
    "wof:name":"Chamruti",
    "wof:placetype":"locality",
    "wof:population":566
},
  "geometry": {"coordinates":[82.17119,25.34265],"type":"Point"}
}