{
  "type": "Feature",
  "properties": {
    "iso:country":"IN",
    "ks:ks_alt_nam":"NITABASA",
    "ks:ks_name":"Nitabasa",
    "ks:ks_pop":116,
    "ks:ks_type":"HABITATION",
    "name:eng_x_preferred":[
        "Nitabasa"
    ],
    "wof:name":"Nitabasa",
    "wof:placetype":"locality",
    "wof:population":116
},
  "geometry": {"coordinates":[85.90337100000001,22.33338],"type":"Point"}
}