{
  "type": "Feature",
  "properties": {
    "iso:country":"IN",
    "ks:ks_name":"Barali",
    "ks:ks_pop":49,
    "ks:ks_type":"HABITATION",
    "name:eng_x_preferred":[
        "Barali"
    ],
    "wof:name":"Barali",
    "wof:placetype":"locality",
    "wof:population":49
},
  "geometry": {"coordinates":[79.362815,30.330305],"type":"Point"}
}