{
  "type": "Feature",
  "properties": {
    "gn:admin1_code":"12",
    "gn:admin2_code":"18.0",
    "gn:asciiname":"Muthal",
    "gn:country_code":"IN",
    "gn:dem":3068,
    "gn:feature_class":"P",
    "gn:feature_code":"PPL",
    "gn:name":"Muthal",
    "gn:population":0,
    "gn:timezone":"Asia/Kolkata",
    "iso:country":"IN",
    "wof:name":"Muthal",
    "wof:placetype":"locality"
},
  "geometry": {"coordinates":[76.36414000000001,33.18744],"type":"Point"}
}