{
  "type": "Feature",
  "properties": {
    "iso:country":"IN",
    "ks:ks_name":"Murugan Kovil Vattam",
    "ks:ks_pop":360,
    "ks:ks_type":"HABITATION",
    "name:eng_x_preferred":[
        "Murugan Kovil Vattam"
    ],
    "wof:name":"Murugan Kovil Vattam",
    "wof:placetype":"locality",
    "wof:population":360
},
  "geometry": {"coordinates":[78.72547299999999,12.612777],"type":"Point"}
}