{
  "type": "Feature",
  "properties": {
    "gn:admin1_code":"21.0",
    "gn:admin2_code":"398.0",
    "gn:asciiname":"Nallochuvva",
    "gn:country_code":"IN",
    "gn:dem":882,
    "gn:feature_class":"P",
    "gn:feature_code":"PPL",
    "gn:name":"Nallochuvva",
    "gn:population":0,
    "gn:timezone":"Asia/Kolkata",
    "iso:country":"IN",
    "wof:name":"Nallochuvva",
    "wof:placetype":"neighbourhood"
},
  "geometry": {"coordinates":[82.59952,18.64533],"type":"Point"}
}