{
  "type": "Feature",
  "properties": {
    "gn:admin1_code":"25.0",
    "gn:admin2_code":"620.0",
    "gn:asciiname":"Srinivasanallur",
    "gn:country_code":"IN",
    "gn:dem":31,
    "gn:feature_class":"P",
    "gn:feature_code":"PPL",
    "gn:name":"Sr\u012bniv\u0101sanall\u016br",
    "gn:population":0,
    "gn:timezone":"Asia/Kolkata",
    "iso:country":"IN",
    "ks:ks_name":"Srinivasanallur",
    "ks:ks_pop":1263,
    "ks:ks_type":"VILLAGE",
    "ks:ks_uagg_main":0,
    "name:eng_x_preferred":[
        "Srinivasanallur"
    ],
    "wof:name":"Srinivasanallur",
    "wof:placetype":"locality",
    "wof:population":1263
},
  "geometry": {"coordinates":[79.423146,10.959501],"type":"Point"}
}