{
  "type": "Feature",
  "properties": {
    "gn:admin1_code":"24.0",
    "gn:admin2_code":"125.0",
    "gn:asciiname":"Piplod",
    "gn:country_code":"IN",
    "gn:dem":225,
    "gn:feature_class":"P",
    "gn:feature_code":"PPL",
    "gn:name":"Piplod",
    "gn:population":0,
    "gn:timezone":"Asia/Kolkata",
    "iso:country":"IN",
    "wof:name":"Piplod",
    "wof:placetype":"locality"
},
  "geometry": {"coordinates":[74.31189000000001,23.39355],"type":"Point"}
}