{
  "type": "Feature",
  "properties": {
    "iso:country":"IN",
    "ks:ks_name":"Sainkul",
    "ks:ks_pop":1051,
    "ks:ks_type":"VILLAGE",
    "ks:ks_uagg_main":0,
    "name:eng_x_preferred":[
        "Sainkul"
    ],
    "wof:name":"Sainkul",
    "wof:placetype":"neighbourhood",
    "wof:population":1051
},
  "geometry": {"coordinates":[86.40292700000001,20.790075],"type":"Point"}
}