{
  "type": "Feature",
  "properties": {
    "iso:country":"IN",
    "name:ben_x_preferred":[
        "\u09a4\u09bf\u09b0\u09c1\u09ad\u09be\u09b0\u09c1\u09b0"
    ],
    "name:bpy_x_preferred":[
        "\u09a5\u09b0\u09c1\u09ac\u09be\u09b2\u09cd\u09b2\u09c1\u09b0"
    ],
    "name:bul_x_preferred":[
        "\u0422\u0438\u0440\u0443\u0432\u0430\u043b\u0443\u0440"
    ],
    "name:cat_x_preferred":[
        "Tiruvallur"
    ],
    "name:ceb_x_preferred":[
        "Tiruvallur"
    ],
    "name:deu_x_preferred":[
        "Tiruvallur"
    ],
    "name:eng_x_preferred":[
        "Tiruvallur"
    ],
    "name:fra_x_preferred":[
        "Tiruvallur"
    ],
    "name:guj_x_preferred":[
        "\u0aa4\u0abf\u0ab0\u0ac1\u0ab5\u0ab2\u0acd\u0ab2\u0ac1\u0ab0"
    ],
    "name:hin_x_preferred":[
        "\u0924\u093f\u0930\u0941\u0935\u0932\u094d\u0932\u0941\u0930"
    ],
    "name:ita_x_preferred":[
        "Tiruvallur"
    ],
    "name:jpn_x_preferred":[
        "\u30c6\u30a3\u30eb\u30f4\u30a1\u30c3\u30eb\u30fc\u30eb"
    ],
    "name:kan_x_preferred":[
        "\u0ca4\u0cbf\u0cb0\u0cc1\u0cb5\u0cb2\u0ccd\u0cb2\u0cc2\u0cb0\u0cc1"
    ],
    "name:kor_x_preferred":[
        "\ud2f0\ub8e8\ubc1c\ub8e8\ub974"
    ],
    "name:mar_x_preferred":[
        "\u0924\u093f\u0930\u0941\u0935\u0932\u094d\u0932\u0941\u0930"
    ],
    "name:mlg_x_preferred":[
        "Tiruvallur"
    ],
    "name:msa_x_preferred":[
        "Thiruvallur"
    ],
    "name:nld_x_preferred":[
        "Tiruvallur"
    ],
    "name:pam_x_preferred":[
        "Tiruvallur"
    ],
    "name:por_x_preferred":[
        "Tiruvallur"
    ],
    "name:rus_x_preferred":[
        "\u0422\u0438\u0440\u0443\u0432\u0430\u043b\u043b\u0443\u0440"
    ],
    "name:san_x_preferred":[
        "\u0924\u093f\u0930\u0941\u0935\u0933\u094d\u0933\u0942\u0930\u0941"
    ],
    "name:spa_x_preferred":[
        "Tiruvallur"
    ],
    "name:swe_x_preferred":[
        "Tiruvallur"
    ],
    "name:tam_x_preferred":[
        "\u0ba4\u0bbf\u0bb0\u0bc1\u0bb5\u0bb3\u0bcd\u0bb3\u0bc2\u0bb0\u0bcd"
    ],
    "name:tel_x_preferred":[
        "\u0c24\u0c3f\u0c30\u0c41\u0c35\u0c33\u0c4d\u0c33\u0c42\u0c30\u0c41"
    ],
    "name:urd_x_preferred":[
        "\u062a\u06cc\u0631\u0648\u0648\u0627\u0644\u0648\u0631"
    ],
    "name:vie_x_preferred":[
        "Thiruvallur"
    ],
    "name:zho_x_preferred":[
        "\u8482\u9c81\u74e6\u5362\u5c14"
    ],
    "qs:name":"Thiruvallur",
    "qs:name_adm0":"India",
    "qs:name_adm1":"Tamil Nadu",
    "qs:photos":275,
    "qs:photos_1k":56,
    "qs:photos_9k":1,
    "qs:photos_9r":4,
    "qs:photos_all":275,
    "qs:photos_sr":5,
    "qs:placetype":"Town",
    "qs:pop_sr":"0",
    "wd:wordcount":2529,
    "wof:name":"Thiruvallur",
    "wof:placetype":"locality"
},
  "geometry": {"coordinates":[79.93652299999999,13.115268],"type":"Point"}
}