{
  "type": "Feature",
  "properties": {
    "gn:admin1_code":"13.0",
    "gn:admin2_code":"588.0",
    "gn:asciiname":"Keloth",
    "gn:country_code":"IN",
    "gn:dem":26,
    "gn:feature_class":"P",
    "gn:feature_code":"PPL",
    "gn:name":"Keloth",
    "gn:population":0,
    "gn:timezone":"Asia/Kolkata",
    "iso:country":"IN",
    "ks:ks_name":"Keloth",
    "ks:ks_pop":1048,
    "ks:ks_type":"HABITATION",
    "name:eng_x_preferred":[
        "Keloth"
    ],
    "wof:name":"Keloth",
    "wof:placetype":"locality",
    "wof:population":1048
},
  "geometry": {"coordinates":[75.103481,12.375223],"type":"Point"}
}