{
  "type": "Feature",
  "properties": {
    "iso:country":"IN",
    "ks:ks_name":"Khasjhika",
    "ks:ks_pop":1935,
    "ks:ks_type":"VILLAGE",
    "ks:ks_uagg_main":0,
    "name:eng_x_preferred":[
        "Khasjhika"
    ],
    "wof:name":"Khasjhika",
    "wof:placetype":"locality",
    "wof:population":1935
},
  "geometry": {"coordinates":[88.206519,22.389345],"type":"Point"}
}