{
  "type": "Feature",
  "properties": {
    "iso:country":"IN",
    "ks:ks_name":"Madiyapar",
    "ks:ks_pop":12,
    "ks:ks_type":"HABITATION",
    "name:eng_x_preferred":[
        "Madiyapar"
    ],
    "wof:name":"Madiyapar",
    "wof:placetype":"locality",
    "wof:population":12
},
  "geometry": {"coordinates":[80.722086,21.605716],"type":"Point"}
}