{
  "type": "Feature",
  "properties": {
    "iso:country":"IN",
    "ks:ks_name":"Baulapurpatana",
    "ks:ks_pop":1304,
    "ks:ks_type":"VILLAGE",
    "name:eng_x_preferred":[
        "Baulapurpatana"
    ],
    "wof:name":"Baulapurpatana",
    "wof:placetype":"locality",
    "wof:population":1304
},
  "geometry": {"coordinates":[85.527064,20.744349],"type":"Point"}
}