{
  "type": "Feature",
  "properties": {
    "gn:admin1_code":"11.0",
    "gn:admin2_code":"31.0",
    "gn:asciiname":"Bamanhol",
    "gn:country_code":"IN",
    "gn:dem":1353,
    "gn:feature_class":"P",
    "gn:feature_code":"PPL",
    "gn:name":"Bamanhol",
    "gn:population":0,
    "gn:timezone":"Asia/Kolkata",
    "iso:country":"IN",
    "wof:name":"Bamanhol",
    "wof:placetype":"locality"
},
  "geometry": {"coordinates":[77.02654,30.91033],"type":"Point"}
}