{
  "type": "Feature",
  "properties": {
    "iso:country":"IN",
    "ks:ks_name":"Belkuba",
    "ks:ks_pop":616,
    "ks:ks_type":"VILLAGE",
    "name:eng_x_preferred":[
        "Belkuba"
    ],
    "wof:name":"Belkuba",
    "wof:placetype":"locality",
    "wof:population":616
},
  "geometry": {"coordinates":[84.207836,22.397557],"type":"Point"}
}