{
  "type": "Feature",
  "properties": {
    "iso:country":"IN",
    "ks:ks_name":"Bindaura Paraspur",
    "ks:ks_pop":377,
    "ks:ks_type":"VILLAGE",
    "ks:ks_uagg_main":0,
    "name:eng_x_preferred":[
        "Bindaura Paraspur"
    ],
    "wof:name":"Bindaura Paraspur",
    "wof:placetype":"neighbourhood",
    "wof:population":377
},
  "geometry": {"coordinates":[81.424449,27.1473],"type":"Point"}
}