{
  "type": "Feature",
  "properties": {
    "gn:admin1_code":"35",
    "gn:admin2_code":"452.0",
    "gn:asciiname":"Panjra",
    "gn:country_code":"IN",
    "gn:dem":452,
    "gn:feature_class":"P",
    "gn:feature_code":"PPL",
    "gn:name":"P\u0101njra",
    "gn:population":0,
    "gn:timezone":"Asia/Kolkata",
    "iso:country":"IN",
    "ks:ks_alt_nam":"P\u0101njra",
    "ks:ks_name":"Panjra",
    "ks:ks_pop":502,
    "ks:ks_type":"VILLAGE",
    "name:eng_x_preferred":[
        "Panjra"
    ],
    "name:eng_x_variant":[
        "P\u0101njra"
    ],
    "wof:name":"Panjra",
    "wof:placetype":"locality",
    "wof:population":502
},
  "geometry": {"coordinates":[79.40093299999999,22.788273],"type":"Point"}
}