{
  "type": "Feature",
  "properties": {
    "iso:country":"IN",
    "ks:ks_name":"Hahapur",
    "ks:ks_pop":0,
    "ks:ks_type":"VILLAGE",
    "name:eng_x_preferred":[
        "Hahapur"
    ],
    "wof:name":"Hahapur",
    "wof:placetype":"locality",
    "wof:population":0
},
  "geometry": {"coordinates":[83.61295200000001,25.088501],"type":"Point"}
}