{
  "type": "Feature",
  "properties": {
    "gn:admin1_code":"25.0",
    "gn:admin2_code":"626",
    "gn:asciiname":"Kadaladi",
    "gn:country_code":"IN",
    "gn:dem":16,
    "gn:feature_class":"P",
    "gn:feature_code":"PPL",
    "gn:name":"Kadal\u0101di",
    "gn:population":0,
    "gn:timezone":"Asia/Kolkata",
    "iso:country":"IN",
    "name:und_x_variant":[
        "Kadal\u0101di"
    ],
    "wof:name":"Kadaladi",
    "wof:placetype":"locality"
},
  "geometry": {"coordinates":[78.49663000000002,9.22327],"type":"Point"}
}