{
  "type": "Feature",
  "properties": {
    "iso:country":"IN",
    "ks:ks_name":"R D Kopplu",
    "ks:ks_pop":817,
    "ks:ks_type":"HABITATION",
    "name:eng_x_preferred":[
        "R D Kopplu"
    ],
    "wof:name":"R D Kopplu",
    "wof:placetype":"locality",
    "wof:population":817
},
  "geometry": {"coordinates":[76.18722200000001,12.444722],"type":"Point"}
}