{
  "type": "Feature",
  "properties": {
    "gn:admin1_code":"12.0",
    "gn:admin2_code":"1.0",
    "gn:asciiname":"Sonapind Gali",
    "gn:country_code":"IN",
    "gn:dem":2376,
    "gn:feature_class":"P",
    "gn:feature_code":"PPL",
    "gn:name":"Sonapind Gali",
    "gn:population":0,
    "gn:timezone":"Asia/Kolkata",
    "iso:country":"IN",
    "wof:name":"Sonapind Gali",
    "wof:placetype":"locality"
},
  "geometry": {"coordinates":[74.47261,34.58839],"type":"Point"}
}