{
  "type": "Feature",
  "properties": {
    "iso:country":"IN",
    "ks:ks_alt_nam":"Lohar tola",
    "ks:ks_name":"Lohar Tola",
    "ks:ks_pop":249,
    "ks:ks_type":"HABITATION",
    "name:eng_x_preferred":[
        "Lohar Tola"
    ],
    "wof:name":"Lohar Tola",
    "wof:placetype":"locality",
    "wof:population":249
},
  "geometry": {"coordinates":[83.795317,25.230115],"type":"Point"}
}