{
  "type": "Feature",
  "properties": {
    "gn:admin1_code":"11.0",
    "gn:admin2_code":"26.0",
    "gn:asciiname":"Bagash",
    "gn:country_code":"IN",
    "gn:dem":1866,
    "gn:feature_class":"P",
    "gn:feature_code":"PPL",
    "gn:name":"Bag\u0101sh",
    "gn:population":0,
    "gn:timezone":"Asia/Kolkata",
    "iso:country":"IN",
    "wof:name":"Bagash",
    "wof:placetype":"locality"
},
  "geometry": {"coordinates":[77.39655999999999,31.44161],"type":"Point"}
}