{
  "type": "Feature",
  "properties": {
    "gn:admin1_code":"36.0",
    "gn:admin2_code":"150.0",
    "gn:asciiname":"Para Bahauddinpur",
    "gn:country_code":"IN",
    "gn:dem":165,
    "gn:feature_class":"P",
    "gn:feature_code":"PPL",
    "gn:name":"P\u0101ra Bah\u0101uddinpur",
    "gn:population":0,
    "gn:timezone":"Asia/Kolkata",
    "iso:country":"IN",
    "wof:name":"Para Bahauddinpur",
    "wof:placetype":"locality"
},
  "geometry": {"coordinates":[79.30116,28.27113],"type":"Point"}
}