{
  "type": "Feature",
  "properties": {
    "gn:admin1_code":"36.0",
    "gn:admin2_code":"150.0",
    "gn:asciiname":"Para Bahauddinpur",
    "gn:country_code":"IN",
    "gn:dem":165,
    "gn:feature_class":"P",
    "gn:feature_code":"PPL",
    "gn:name":"P\u0101ra Bah\u0101uddinpur",
    "gn:population":0,
    "gn:timezone":"Asia/Kolkata",
    "iso:country":"IN",
    "ks:ks_alt_nam":"P\u0101ra Bah\u0101uddinpur",
    "ks:ks_name":"Para Bahauddinpur",
    "ks:ks_type":"VILLAGE",
    "name:eng_x_preferred":[
        "Para Bahauddinpur"
    ],
    "name:eng_x_variant":[
        "P\u0101ra Bah\u0101uddinpur"
    ],
    "wof:name":"Para Bahauddinpur",
    "wof:placetype":"locality"
},
  "geometry": {"coordinates":[79.301157,28.271126],"type":"Point"}
}