{
  "type": "Feature",
  "properties": {
    "iso:country":"IN",
    "ks:ks_name":"Lilawaran",
    "ks:ks_pop":325,
    "ks:ks_type":"HABITATION",
    "name:eng_x_preferred":[
        "Lilawaran"
    ],
    "wof:name":"Lilawaran",
    "wof:placetype":"locality",
    "wof:population":325
},
  "geometry": {"coordinates":[86.853191,24.878208],"type":"Point"}
}