{
  "type": "Feature",
  "properties": {
    "gn:admin1_code":"19.0",
    "gn:admin2_code":"561.0",
    "gn:asciiname":"Hire Kop",
    "gn:country_code":"IN",
    "gn:dem":631,
    "gn:feature_class":"P",
    "gn:feature_code":"PPL",
    "gn:name":"Hire Kop",
    "gn:population":0,
    "gn:timezone":"Asia/Kolkata",
    "iso:country":"IN",
    "wof:name":"Hire Kop",
    "wof:placetype":"locality"
},
  "geometry": {"coordinates":[75.65208,15.47851],"type":"Point"}
}