{
  "type": "Feature",
  "properties": {
    "iso:country":"IN",
    "ks:ks_name":"Hilapurkhu",
    "ks:ks_pop":506,
    "ks:ks_type":"HABITATION",
    "name:eng_x_preferred":[
        "Hilapurkhu"
    ],
    "wof:name":"Hilapurkhu",
    "wof:placetype":"locality",
    "wof:population":506
},
  "geometry": {"coordinates":[80.936722,27.6414],"type":"Point"}
}