{
  "type": "Feature",
  "properties": {
    "iso:country":"IN",
    "ks:ks_name":"Kaikadiwasti",
    "ks:ks_pop":168,
    "ks:ks_type":"HABITATION",
    "name:eng_x_preferred":[
        "Kaikadiwasti"
    ],
    "wof:name":"Kaikadiwasti",
    "wof:placetype":"locality",
    "wof:population":168
},
  "geometry": {"coordinates":[74.39854,17.9671],"type":"Point"}
}