{
  "type": "Feature",
  "properties": {
    "iso:country":"IN",
    "ks:ks_alt_nam":"chamruti",
    "ks:ks_name":"Chamruti",
    "ks:ks_pop":150,
    "ks:ks_type":"HABITATION",
    "name:eng_x_preferred":[
        "Chamruti"
    ],
    "wof:name":"Chamruti",
    "wof:placetype":"locality",
    "wof:population":150
},
  "geometry": {"coordinates":[81.87488,25.5425],"type":"Point"}
}