{
  "type": "Feature",
  "properties": {
    "iso:country":"IN",
    "ks:ks_name":"Thokara",
    "ks:ks_pop":410,
    "ks:ks_type":"VILLAGE",
    "name:eng_x_preferred":[
        "Thokara"
    ],
    "wof:name":"Thokara",
    "wof:placetype":"locality",
    "wof:population":410
},
  "geometry": {"coordinates":[86.699665,20.784466],"type":"Point"}
}