{
  "type": "Feature",
  "properties": {
    "iso:country":"IN",
    "ks:ks_name":"Murakhada",
    "ks:ks_pop":638,
    "ks:ks_type":"VILLAGE",
    "name:eng_x_preferred":[
        "Murakhada"
    ],
    "wof:name":"Murakhada",
    "wof:placetype":"locality",
    "wof:population":638
},
  "geometry": {"coordinates":[70.23282500000001,21.732288],"type":"Point"}
}