{
  "type": "Feature",
  "properties": {
    "gn:admin1_code":"36",
    "gn:admin2_code":"200.0",
    "gn:asciiname":"Misri",
    "gn:country_code":"IN",
    "gn:dem":205,
    "gn:feature_class":"P",
    "gn:feature_code":"PPL",
    "gn:name":"Misri",
    "gn:population":0,
    "gn:timezone":"Asia/Kolkata",
    "iso:country":"IN",
    "name:pan_x_preferred":[
        "\u0a2e\u0a3f\u0a38\u0a30\u0a40"
    ],
    "wof:name":"Misri",
    "wof:placetype":"locality"
},
  "geometry": {"coordinates":[83.37304,24.4475],"type":"Point"}
}