{
  "type": "Feature",
  "properties": {
    "gn:admin1_code":"36",
    "gn:admin2_code":"200.0",
    "gn:asciiname":"Misri",
    "gn:country_code":"IN",
    "gn:dem":205,
    "gn:feature_class":"P",
    "gn:feature_code":"PPL",
    "gn:name":"Misri",
    "gn:population":0,
    "gn:timezone":"Asia/Kolkata",
    "iso:country":"IN",
    "ks:ks_name":"Misari",
    "ks:ks_pop":634,
    "ks:ks_type":"VILLAGE",
    "name:eng_x_preferred":[
        "Misari"
    ],
    "name:eng_x_variant":[
        "Misri"
    ],
    "name:pan_x_preferred":[
        "\u0a2e\u0a3f\u0a38\u0a30\u0a40"
    ],
    "wof:name":"Misari",
    "wof:placetype":"locality",
    "wof:population":634
},
  "geometry": {"coordinates":[83.36557999999999,24.44718],"type":"Point"}
}