{
  "type": "Feature",
  "properties": {
    "iso:country":"IN",
    "ks:ks_name":"Gangadharpur",
    "ks:ks_pop":299,
    "ks:ks_type":"VILLAGE",
    "ks:ks_uagg_main":1,
    "name:eng_x_preferred":[
        "Gangadharpur"
    ],
    "wof:name":"Gangadharpur",
    "wof:placetype":"neighbourhood",
    "wof:population":299
},
  "geometry": {"coordinates":[87.542753,21.631151],"type":"Point"}
}