{
  "type": "Feature",
  "properties": {
    "gn:admin1_code":"36",
    "gn:admin2_code":"180.0",
    "gn:asciiname":"Biswan",
    "gn:country_code":"IN",
    "gn:dem":119,
    "gn:feature_class":"P",
    "gn:feature_code":"PPL",
    "gn:name":"Bisw\u0101n",
    "gn:population":0,
    "gn:timezone":"Asia/Kolkata",
    "iso:country":"IN",
    "name:bpy_x_preferred":[
        "\u09ac\u09bf\u09b8\u09f1\u09be\u09a8"
    ],
    "name:ceb_x_preferred":[
        "Bisw\u0101n"
    ],
    "name:hin_x_preferred":[
        "\u092c\u093f\u0938\u0935\u093e\u0901"
    ],
    "name:ita_x_preferred":[
        "Biswan"
    ],
    "name:mlg_x_preferred":[
        "Biswan"
    ],
    "name:msa_x_preferred":[
        "Biswan"
    ],
    "name:new_x_preferred":[
        "\u092c\u093f\u0938\u094d\u0935\u093e\u0928"
    ],
    "name:nld_x_preferred":[
        "Biswan"
    ],
    "name:pol_x_preferred":[
        "Biswan"
    ],
    "name:por_x_preferred":[
        "Biswan"
    ],
    "name:swe_x_preferred":[
        "Bisw\u0101n"
    ],
    "name:urd_x_preferred":[
        "\u0628\u0633\u0648\u0627\u06ba"
    ],
    "name:vie_x_preferred":[
        "Biswan"
    ],
    "name:zho_x_preferred":[
        "\u6bd4\u65af\u4e07"
    ],
    "wof:name":"Biswan",
    "wof:placetype":"locality"
},
  "geometry": {"coordinates":[81.43529000000002,27.41086],"type":"Point"}
}