{
  "type": "Feature",
  "properties": {
    "gn:admin1_code":"10",
    "gn:admin2_code":"70.0",
    "gn:asciiname":"Bhorangpur",
    "gn:country_code":"IN",
    "gn:dem":255,
    "gn:feature_class":"P",
    "gn:feature_code":"PPL",
    "gn:name":"Bhorangpur",
    "gn:population":0,
    "gn:timezone":"Asia/Kolkata",
    "iso:country":"IN",
    "ks:ks_name":"Bhorangpur",
    "ks:ks_pop":1371,
    "ks:ks_type":"VILLAGE",
    "ks:ks_uagg_main":0,
    "name:eng_x_preferred":[
        "Bhorangpur"
    ],
    "wof:name":"Bhorangpur",
    "wof:placetype":"neighbourhood",
    "wof:population":1371
},
  "geometry": {"coordinates":[76.636827,30.271185],"type":"Point"}
}