{
  "type": "Feature",
  "properties": {
    "iso:country":"IN",
    "ks:ks_alt_nam":"polpal",
    "ks:ks_name":"Polpal",
    "ks:ks_pop":509,
    "ks:ks_type":"HABITATION",
    "name:eng_x_preferred":[
        "Polpal"
    ],
    "wof:name":"Polpal",
    "wof:placetype":"locality",
    "wof:population":509
},
  "geometry": {"coordinates":[84.257384,23.32407],"type":"Point"}
}