{
  "type": "Feature",
  "properties": {
    "iso:country":"IN",
    "ks:ks_name":"Patgaon Talla",
    "ks:ks_pop":192,
    "ks:ks_type":"VILLAGE",
    "name:eng_x_preferred":[
        "Patgaon Talla"
    ],
    "wof:name":"Patgaon Talla",
    "wof:placetype":"locality",
    "wof:population":192
},
  "geometry": {"coordinates":[79.06562,29.741428],"type":"Point"}
}