{
  "type": "Feature",
  "properties": {
    "gn:admin1_code":"36.0",
    "gn:admin2_code":"148",
    "gn:asciiname":"Khadra",
    "gn:country_code":"IN",
    "gn:dem":149,
    "gn:feature_class":"P",
    "gn:feature_code":"PPL",
    "gn:name":"Khadra",
    "gn:population":0,
    "gn:timezone":"Asia/Kolkata",
    "iso:country":"IN",
    "name:ara_x_preferred":[
        "\u062e\u0636\u0631\u0629"
    ],
    "name:azb_x_preferred":[
        "\u062e\u0636\u0631\u0647"
    ],
    "name:fas_x_preferred":[
        "\u062e\u0636\u0631\u0647"
    ],
    "name:fra_x_preferred":[
        "Khadra"
    ],
    "name:ita_x_preferred":[
        "Khadra"
    ],
    "name:kab_x_preferred":[
        "Xe\u1e0dra"
    ],
    "name:msa_x_preferred":[
        "Khadra"
    ],
    "name:por_x_preferred":[
        "Khadra"
    ],
    "name:ron_x_preferred":[
        "Khadra"
    ],
    "name:spa_x_preferred":[
        "Khadra"
    ],
    "name:vie_x_preferred":[
        "Khadra"
    ],
    "wof:name":"Khadra",
    "wof:placetype":"locality"
},
  "geometry": {"coordinates":[79.31359999999999,27.10023],"type":"Point"}
}