{
  "type": "Feature",
  "properties": {
    "gn:admin1_code":"11",
    "gn:admin2_code":"33.0",
    "gn:asciiname":"Dewin",
    "gn:country_code":"IN",
    "gn:dem":1347,
    "gn:feature_class":"P",
    "gn:feature_code":"PPL",
    "gn:name":"Dew\u012bn",
    "gn:population":0,
    "gn:timezone":"Asia/Kolkata",
    "iso:country":"IN",
    "name:deu_x_preferred":[
        "Dewin"
    ],
    "wof:name":"Dewin",
    "wof:placetype":"locality"
},
  "geometry": {"coordinates":[77.04159,31.07766],"type":"Point"}
}