{
  "type": "Feature",
  "properties": {
    "gn:admin1_code":"34.0",
    "gn:admin2_code":"207.0",
    "gn:asciiname":"Bhatgawan",
    "gn:country_code":"IN",
    "gn:dem":66,
    "gn:feature_class":"P",
    "gn:feature_code":"PPL",
    "gn:name":"Bhatg\u0101w\u0101n",
    "gn:population":0,
    "gn:timezone":"Asia/Kolkata",
    "iso:country":"IN",
    "ks:ks_alt_nam":"Bhatg\u0101w\u0101n",
    "ks:ks_name":"Bhatgawan",
    "ks:ks_pop":2704,
    "ks:ks_type":"VILLAGE",
    "name:eng_x_preferred":[
        "Bhatgawan"
    ],
    "name:eng_x_variant":[
        "Bhatg\u0101w\u0101n"
    ],
    "wof:name":"Bhatgawan",
    "wof:placetype":"locality",
    "wof:population":2704
},
  "geometry": {"coordinates":[86.233003,26.428137],"type":"Point"}
}