{
  "type": "Feature",
  "properties": {
    "iso:country":"IN",
    "ks:ks_name":"Gaddekumbri",
    "ks:ks_pop":62,
    "ks:ks_type":"HABITATION",
    "name:eng_x_preferred":[
        "Gaddekumbri"
    ],
    "wof:name":"Gaddekumbri",
    "wof:placetype":"locality",
    "wof:population":62
},
  "geometry": {"coordinates":[74.55264699999999,14.902035],"type":"Point"}
}