{
  "type": "Feature",
  "properties": {
    "iso:country":"IN",
    "ks:ks_name":"Garhi Bagampur",
    "ks:ks_type":"VILLAGE",
    "name:eng_x_preferred":[
        "Garhi Bagampur"
    ],
    "wof:name":"Garhi Bagampur",
    "wof:placetype":"locality"
},
  "geometry": {"coordinates":[77.486777,28.348858],"type":"Point"}
}