{
  "type": "Feature",
  "properties": {
    "iso:country":"IN",
    "ks:ks_name":"Tajpur Laga Kandai",
    "ks:ks_pop":440,
    "ks:ks_type":"VILLAGE",
    "name:eng_x_preferred":[
        "Tajpur Laga Kandai"
    ],
    "wof:name":"Tajpur Laga Kandai",
    "wof:placetype":"locality",
    "wof:population":440
},
  "geometry": {"coordinates":[79.59430399999999,30.093732],"type":"Point"}
}