{
  "type": "Feature",
  "properties": {
    "gn:admin1_code":"19.0",
    "gn:admin2_code":"576.0",
    "gn:asciiname":"Appasethali",
    "gn:country_code":"IN",
    "gn:dem":965,
    "gn:feature_class":"P",
    "gn:feature_code":"PPL",
    "gn:name":"Appasethali",
    "gn:population":0,
    "gn:timezone":"Asia/Kolkata",
    "iso:country":"IN",
    "wof:name":"Appasethali",
    "wof:placetype":"locality"
},
  "geometry": {"coordinates":[75.87747,12.71157],"type":"Point"}
}