{
  "type": "Feature",
  "properties": {
    "iso:country":"IN",
    "ks:ks_name":"26 PTD",
    "ks:ks_pop":45,
    "ks:ks_type":"VILLAGE",
    "ks:ks_uagg_main":0,
    "name:eng_x_preferred":[
        "26 PTD"
    ],
    "wof:name":"26 PTD",
    "wof:placetype":"neighbourhood",
    "wof:population":45
},
  "geometry": {"coordinates":[73.195396,29.374059],"type":"Point"}
}