{
  "type": "Feature",
  "properties": {
    "gn:admin1_code":"36",
    "gn:admin2_code":"185.0",
    "gn:asciiname":"Pipri",
    "gn:country_code":"IN",
    "gn:dem":92,
    "gn:feature_class":"P",
    "gn:feature_code":"PPL",
    "gn:name":"Pipri",
    "gn:population":0,
    "gn:timezone":"Asia/Kolkata",
    "iso:country":"IN",
    "name:bpy_x_preferred":[
        "\u09aa\u09bf\u09aa\u09b0\u09bf"
    ],
    "name:ceb_x_preferred":[
        "Pipri"
    ],
    "name:ita_x_preferred":[
        "Pipri"
    ],
    "name:mlg_x_preferred":[
        "Pipri"
    ],
    "name:msa_x_preferred":[
        "Pipri"
    ],
    "name:nld_x_preferred":[
        "Pipri"
    ],
    "name:pol_x_preferred":[
        "Pipri"
    ],
    "name:por_x_preferred":[
        "Pipri"
    ],
    "name:swe_x_preferred":[
        "Pipri"
    ],
    "name:urd_x_preferred":[
        "\u067e\u06cc\u067e\u0631\u06cc"
    ],
    "name:vie_x_preferred":[
        "Pipri"
    ],
    "name:zho_x_preferred":[
        "\u76ae\u666e\u91cc"
    ],
    "wof:name":"Pipri",
    "wof:placetype":"neighbourhood"
},
  "geometry": {"coordinates":[82.78751,26.8429],"type":"Point"}
}