{
  "type": "Feature",
  "properties": {
    "gn:admin1_code":"21.0",
    "gn:admin2_code":"382",
    "gn:asciiname":"Barenderi",
    "gn:country_code":"IN",
    "gn:dem":30,
    "gn:feature_class":"P",
    "gn:feature_code":"PPL",
    "gn:name":"Barenderi",
    "gn:population":0,
    "gn:timezone":"Asia/Kolkata",
    "iso:country":"IN",
    "wof:name":"Barenderi",
    "wof:placetype":"locality"
},
  "geometry": {"coordinates":[86.22704,20.9922],"type":"Point"}
}