{
  "type": "Feature",
  "properties": {
    "iso:country":"IN",
    "ks:ks_name":"Suruda",
    "ks:ks_pop":7,
    "ks:ks_type":"VILLAGE",
    "name:eng_x_preferred":[
        "Suruda"
    ],
    "wof:name":"Suruda",
    "wof:placetype":"locality",
    "wof:population":7
},
  "geometry": {"coordinates":[83.510744,19.98976],"type":"Point"}
}