{
  "type": "Feature",
  "properties": {
    "iso:country":"IN",
    "ks:ks_alt_nam":"7   a II",
    "ks:ks_name":"7 a Ii",
    "ks:ks_pop":378,
    "ks:ks_type":"HABITATION",
    "name:eng_x_preferred":[
        "7 a Ii"
    ],
    "name:eng_x_variant":[
        "7   a II"
    ],
    "wof:name":"7 a Ii",
    "wof:placetype":"locality",
    "wof:population":378
},
  "geometry": {"coordinates":[73.85807800000001,29.880344],"type":"Point"}
}