{
  "type": "Feature",
  "properties": {
    "iso:country":"IN",
    "ks:ks_alt_nam":"Chantaiah Palli thanda",
    "ks:ks_name":"Chantaiah Palli Thanda",
    "ks:ks_pop":100,
    "ks:ks_type":"HABITATION",
    "name:eng_x_preferred":[
        "Chantaiah Palli Thanda"
    ],
    "wof:name":"Chantaiah Palli Thanda",
    "wof:placetype":"locality",
    "wof:population":100
},
  "geometry": {"coordinates":[79.32204400000001,18.027793],"type":"Point"}
}