{
  "type": "Feature",
  "properties": {
    "gn:admin1_code":"28.0",
    "gn:admin2_code":"343",
    "gn:asciiname":"Dhanyaghata",
    "gn:country_code":"IN",
    "gn:dem":8,
    "gn:feature_class":"P",
    "gn:feature_code":"PPL",
    "gn:name":"Dh\u0101nyagh\u0101ta",
    "gn:population":0,
    "gn:timezone":"Asia/Kolkata",
    "iso:country":"IN",
    "wof:name":"Dhanyaghata",
    "wof:placetype":"locality"
},
  "geometry": {"coordinates":[88.33553000000001,22.18849],"type":"Point"}
}