{
  "type": "Feature",
  "properties": {
    "iso:country":"IN",
    "ks:ks_name":"Kanmule",
    "ks:ks_pop":46,
    "ks:ks_type":"HABITATION",
    "name:eng_x_preferred":[
        "Kanmule"
    ],
    "wof:name":"Kanmule",
    "wof:placetype":"locality",
    "wof:population":46
},
  "geometry": {"coordinates":[74.399756,14.552585],"type":"Point"}
}