{
  "type": "Feature",
  "properties": {
    "iso:country":"IN",
    "ks:ks_name":"Chukhapur",
    "ks:ks_pop":608,
    "ks:ks_type":"HABITATION",
    "name:eng_x_preferred":[
        "Chukhapur"
    ],
    "wof:name":"Chukhapur",
    "wof:placetype":"locality",
    "wof:population":608
},
  "geometry": {"coordinates":[78.315443,29.634284],"type":"Point"}
}