{
  "type": "Feature",
  "properties": {
    "iso:country":"IN",
    "ks:ks_name":"Dhamankonta",
    "ks:ks_pop":480,
    "ks:ks_type":"HABITATION",
    "name:eng_x_preferred":[
        "Dhamankonta"
    ],
    "wof:name":"Dhamankonta",
    "wof:placetype":"locality",
    "wof:population":480
},
  "geometry": {"coordinates":[81.891795,18.735961],"type":"Point"}
}