{
  "type": "Feature",
  "properties": {
    "iso:country":"IN",
    "ks:ks_alt_nam":"Naki ka pura",
    "ks:ks_name":"Naki Ka Pura",
    "ks:ks_pop":400,
    "ks:ks_type":"HABITATION",
    "name:eng_x_preferred":[
        "Naki Ka Pura"
    ],
    "wof:name":"Naki Ka Pura",
    "wof:placetype":"locality",
    "wof:population":400
},
  "geometry": {"coordinates":[81.936566,25.184303],"type":"Point"}
}