{
  "type": "Feature",
  "properties": {
    "gn:admin1_code":"23.0",
    "gn:admin2_code":"40.0",
    "gn:asciiname":"Ditupur Faqiran",
    "gn:country_code":"IN",
    "gn:dem":258,
    "gn:feature_class":"P",
    "gn:feature_code":"PPL",
    "gn:name":"D\u012bt\u016bpur Faq\u012br\u0101n",
    "gn:population":0,
    "gn:timezone":"Asia/Kolkata",
    "iso:country":"IN",
    "ks:ks_name":"Ditupur Fakiran",
    "ks:ks_pop":326,
    "ks:ks_type":"VILLAGE",
    "name:eng_x_preferred":[
        "Ditupur Fakiran"
    ],
    "name:eng_x_variant":[
        "Ditupur Faqiran"
    ],
    "wof:name":"Ditupur Fakiran",
    "wof:placetype":"locality",
    "wof:population":326
},
  "geometry": {"coordinates":[76.46043899999999,30.445507],"type":"Point"}
}