{
  "type": "Feature",
  "properties": {
    "iso:country":"IN",
    "ks:ks_name":"Uttar Bilpar Dhumkar",
    "ks:ks_pop":939,
    "ks:ks_type":"HABITATION",
    "name:eng_x_preferred":[
        "Uttar Bilpar Dhumkar"
    ],
    "wof:name":"Uttar Bilpar Dhumkar",
    "wof:placetype":"locality",
    "wof:population":939
},
  "geometry": {"coordinates":[92.579337,24.699276],"type":"Point"}
}