{
  "type": "Feature",
  "properties": {
    "iso:country":"IN",
    "ks:ks_name":"Goddibanda",
    "ks:ks_pop":12,
    "ks:ks_type":"HABITATION",
    "name:eng_x_preferred":[
        "Goddibanda"
    ],
    "wof:name":"Goddibanda",
    "wof:placetype":"locality",
    "wof:population":12
},
  "geometry": {"coordinates":[82.44828800000001,17.929852],"type":"Point"}
}