{
  "type": "Feature",
  "properties": {
    "iso:country":"IN",
    "ks:ks_name":"Nayapurwa",
    "ks:ks_pop":500,
    "ks:ks_type":"HABITATION",
    "name:eng_x_preferred":[
        "Nayapurwa"
    ],
    "wof:name":"Nayapurwa",
    "wof:placetype":"locality",
    "wof:population":500
},
  "geometry": {"coordinates":[81.219391,25.789543],"type":"Point"}
}