{
  "type": "Feature",
  "properties": {
    "iso:country":"IN",
    "ks:ks_alt_nam":"H\u0101lekote",
    "ks:ks_name":"Halekote",
    "ks:ks_type":"VILLAGE",
    "name:eng_x_preferred":[
        "Halekote"
    ],
    "name:eng_x_variant":[
        "H\u0101lekote"
    ],
    "wof:name":"Halekote",
    "wof:placetype":"locality"
},
  "geometry": {"coordinates":[76.93765500000001,15.733715],"type":"Point"}
}