{
  "type": "Feature",
  "properties": {
    "iso:country":"IN",
    "ks:ks_name":"Mumanpara",
    "ks:ks_pop":265,
    "ks:ks_type":"HABITATION",
    "name:eng_x_preferred":[
        "Mumanpara"
    ],
    "wof:name":"Mumanpara",
    "wof:placetype":"locality",
    "wof:population":265
},
  "geometry": {"coordinates":[72.10955199999999,23.987798],"type":"Point"}
}