{
  "type": "Feature",
  "properties": {
    "iso:country":"IN",
    "ks:ks_name":"Baidya Mohalla",
    "ks:ks_pop":492,
    "ks:ks_type":"HABITATION",
    "name:eng_x_preferred":[
        "Baidya Mohalla"
    ],
    "wof:name":"Baidya Mohalla",
    "wof:placetype":"locality",
    "wof:population":492
},
  "geometry": {"coordinates":[85.16301,23.52384],"type":"Point"}
}