{
  "type": "Feature",
  "properties": {
    "iso:country":"IN",
    "ks:ks_name":"Bheluatikira",
    "ks:ks_pop":143,
    "ks:ks_type":"VILLAGE",
    "name:eng_x_preferred":[
        "Bheluatikira"
    ],
    "wof:name":"Bheluatikira",
    "wof:placetype":"locality",
    "wof:population":143
},
  "geometry": {"coordinates":[83.78247500000001,21.890079],"type":"Point"}
}