{
  "type": "Feature",
  "properties": {
    "gn:admin1_code":"35",
    "gn:admin2_code":"425.0",
    "gn:asciiname":"Sareri",
    "gn:country_code":"IN",
    "gn:dem":258,
    "gn:feature_class":"P",
    "gn:feature_code":"PPL",
    "gn:name":"Sareri",
    "gn:population":0,
    "gn:timezone":"Asia/Kolkata",
    "iso:country":"IN",
    "wof:name":"Sareri",
    "wof:placetype":"locality"
},
  "geometry": {"coordinates":[79.53029000000002,25.0414],"type":"Point"}
}