{
  "type": "Feature",
  "properties": {
    "gn:admin1_code":"35",
    "gn:admin2_code":"425.0",
    "gn:asciiname":"Sareri",
    "gn:country_code":"IN",
    "gn:dem":258,
    "gn:feature_class":"P",
    "gn:feature_code":"PPL",
    "gn:name":"Sareri",
    "gn:population":0,
    "gn:timezone":"Asia/Kolkata",
    "iso:country":"IN",
    "ks:ks_name":"Saderi",
    "ks:ks_pop":1017,
    "ks:ks_type":"HABITATION",
    "name:eng_x_preferred":[
        "Saderi"
    ],
    "name:eng_x_variant":[
        "Sareri"
    ],
    "wof:name":"Saderi",
    "wof:placetype":"locality",
    "wof:population":1017
},
  "geometry": {"coordinates":[79.527503,25.043046],"type":"Point"}
}