{
  "type": "Feature",
  "properties": {
    "iso:country":"IN",
    "ks:ks_name":"Barai",
    "ks:ks_pop":929,
    "ks:ks_type":"VILLAGE",
    "name:eng_x_preferred":[
        "Barai"
    ],
    "wof:name":"Barai",
    "wof:placetype":"locality",
    "wof:population":929
},
  "geometry": {"coordinates":[81.79699100000001,26.839258],"type":"Point"}
}