{
  "type": "Feature",
  "properties": {
    "gn:admin1_code":"2.0",
    "gn:admin2_code":"553.0",
    "gn:asciiname":"Vengampeta",
    "gn:country_code":"IN",
    "gn:dem":333,
    "gn:feature_class":"P",
    "gn:feature_code":"PPL",
    "gn:name":"Vengampeta",
    "gn:population":0,
    "gn:timezone":"Asia/Kolkata",
    "iso:country":"IN",
    "wof:name":"Vengampeta",
    "wof:placetype":"locality"
},
  "geometry": {"coordinates":[77.82679,14.76918],"type":"Point"}
}