{
  "type": "Feature",
  "properties": {
    "iso:country":"IN",
    "ks:ks_name":"Simaldahi",
    "ks:ks_pop":531,
    "ks:ks_type":"VILLAGE",
    "name:eng_x_preferred":[
        "Simaldahi"
    ],
    "wof:name":"Simaldahi",
    "wof:placetype":"locality",
    "wof:population":531
},
  "geometry": {"coordinates":[87.670338,24.446402],"type":"Point"}
}