{
  "type": "Feature",
  "properties": {
    "iso:country":"IN",
    "ks:ks_name":"Tangabani",
    "ks:ks_pop":233,
    "ks:ks_type":"VILLAGE",
    "name:eng_x_preferred":[
        "Tangabani"
    ],
    "wof:name":"Tangabani",
    "wof:placetype":"locality",
    "wof:population":233
},
  "geometry": {"coordinates":[87.51576,21.67695],"type":"Point"}
}