{
  "type": "Feature",
  "properties": {
    "iso:country":"IN",
    "ks:ks_name":"Karkhiya",
    "ks:ks_pop":1000,
    "ks:ks_type":"HABITATION",
    "ks:ks_uagg_main":0,
    "name:eng_x_preferred":[
        "Karkhiya"
    ],
    "wof:name":"Karkhiya",
    "wof:placetype":"neighbourhood",
    "wof:population":1000
},
  "geometry": {"coordinates":[84.37989,25.554315],"type":"Point"}
}