{
  "type": "Feature",
  "properties": {
    "iso:country":"IN",
    "ks:ks_name":"Patoradadar",
    "ks:ks_pop":429,
    "ks:ks_type":"VILLAGE",
    "name:eng_x_preferred":[
        "Patoradadar"
    ],
    "wof:name":"Patoradadar",
    "wof:placetype":"locality",
    "wof:population":429
},
  "geometry": {"coordinates":[82.232601,20.526292],"type":"Point"}
}