{
  "type": "Feature",
  "properties": {
    "gn:admin1_code":"11.0",
    "gn:admin2_code":"32.0",
    "gn:asciiname":"Achhoti",
    "gn:country_code":"IN",
    "gn:dem":1399,
    "gn:feature_class":"P",
    "gn:feature_code":"PPL",
    "gn:name":"Achhoti",
    "gn:population":0,
    "gn:timezone":"Asia/Kolkata",
    "iso:country":"IN",
    "wof:name":"Achhoti",
    "wof:placetype":"locality"
},
  "geometry": {"coordinates":[77.70135999999999,30.66563],"type":"Point"}
}