{
  "type": "Feature",
  "properties": {
    "iso:country":"IN",
    "ks:ks_name":"Samanya Basti",
    "ks:ks_pop":95,
    "ks:ks_type":"HABITATION",
    "name:eng_x_preferred":[
        "Samanya Basti"
    ],
    "wof:name":"Samanya Basti",
    "wof:placetype":"locality",
    "wof:population":95
},
  "geometry": {"coordinates":[82.712154,25.286854],"type":"Point"}
}