{
  "type": "Feature",
  "properties": {
    "gn:admin1_code":"36",
    "gn:admin2_code":"169.0",
    "gn:asciiname":"Kamalpura",
    "gn:country_code":"IN",
    "gn:dem":202,
    "gn:feature_class":"P",
    "gn:feature_code":"PPL",
    "gn:name":"Kam\u0101lpura",
    "gn:population":0,
    "gn:timezone":"Asia/Kolkata",
    "iso:country":"IN",
    "wof:name":"Kamalpura",
    "wof:placetype":"locality"
},
  "geometry": {"coordinates":[79.69865,25.2972],"type":"Point"}
}