{
  "type": "Feature",
  "properties": {
    "iso:country":"IN",
    "ks:ks_name":"Mechak",
    "ks:ks_pop":0,
    "ks:ks_type":"VILLAGE",
    "name:eng_x_preferred":[
        "Mechak"
    ],
    "wof:name":"Mechak",
    "wof:placetype":"locality",
    "wof:population":0
},
  "geometry": {"coordinates":[87.05052999999999,21.666952],"type":"Point"}
}