{
  "type": "Feature",
  "properties": {
    "iso:country":"IN",
    "ks:ks_alt_nam":"Par\u0101chh\u0101t",
    "ks:ks_name":"Parachhat",
    "ks:ks_pop":1217,
    "ks:ks_type":"VILLAGE",
    "name:eng_x_preferred":[
        "Parachhat"
    ],
    "name:eng_x_variant":[
        "Par\u0101chh\u0101t"
    ],
    "wof:name":"Parachhat",
    "wof:placetype":"locality",
    "wof:population":1217
},
  "geometry": {"coordinates":[85.150312,21.207282],"type":"Point"}
}