{
  "type": "Feature",
  "properties": {
    "gn:admin1_code":"34.0",
    "gn:admin2_code":"220.0",
    "gn:asciiname":"Bahadurpur",
    "gn:country_code":"IN",
    "gn:dem":55,
    "gn:feature_class":"P",
    "gn:feature_code":"PPL",
    "gn:name":"Bah\u0101durpur",
    "gn:population":0,
    "gn:timezone":"Asia/Kolkata",
    "iso:country":"IN",
    "name:fra_x_preferred":[
        "Bahadurpur"
    ],
    "name:pol_x_preferred":[
        "Bahadurpur"
    ],
    "name:und_x_variant":[
        "Bah\u0101durpur",
        "Bhu\u0101lpur"
    ],
    "wof:name":"Bahadurpur",
    "wof:placetype":"locality"
},
  "geometry": {"coordinates":[85.34623000000001,25.93959],"type":"Point"}
}