{
  "type": "Feature",
  "properties": {
    "iso:country":"IN",
    "ks:ks_name":"Paina",
    "ks:ks_pop":8,
    "ks:ks_type":"HABITATION",
    "name:eng_x_preferred":[
        "Paina"
    ],
    "wof:name":"Paina",
    "wof:placetype":"locality",
    "wof:population":8
},
  "geometry": {"coordinates":[79.338314,30.178619],"type":"Point"}
}