{
  "type": "Feature",
  "properties": {
    "iso:country":"IN",
    "ks:ks_name":"Saindanakodlu",
    "ks:ks_pop":192,
    "ks:ks_type":"HABITATION",
    "name:eng_x_preferred":[
        "Saindanakodlu"
    ],
    "wof:name":"Saindanakodlu",
    "wof:placetype":"locality",
    "wof:population":192
},
  "geometry": {"coordinates":[74.794276,13.740431],"type":"Point"}
}