{
  "type": "Feature",
  "properties": {
    "gn:admin1_code":"24",
    "gn:admin2_code":"113.0",
    "gn:asciiname":"Lohawat",
    "gn:country_code":"IN",
    "gn:dem":300,
    "gn:feature_class":"P",
    "gn:feature_code":"PPL",
    "gn:name":"Loh\u0101wat",
    "gn:population":0,
    "gn:timezone":"Asia/Kolkata",
    "iso:country":"IN",
    "name:hin_x_preferred":[
        "\u0932\u094b\u0939\u093e\u0935\u091f"
    ],
    "wof:name":"Lohawat",
    "wof:placetype":"locality"
},
  "geometry": {"coordinates":[72.57991,26.98214],"type":"Point"}
}