{
  "type": "Feature",
  "properties": {
    "iso:country":"IN",
    "ks:ks_name":"Padyana",
    "ks:ks_pop":554,
    "ks:ks_type":"HABITATION",
    "name:eng_x_preferred":[
        "Padyana"
    ],
    "wof:name":"Padyana",
    "wof:placetype":"locality",
    "wof:population":554
},
  "geometry": {"coordinates":[75.011081,12.720516],"type":"Point"}
}