{
  "type": "Feature",
  "properties": {
    "iso:country":"IN",
    "ks:ks_name":"Chakosa",
    "ks:ks_pop":306,
    "ks:ks_type":"VILLAGE",
    "name:eng_x_preferred":[
        "Chakosa"
    ],
    "wof:name":"Chakosa",
    "wof:placetype":"locality",
    "wof:population":306
},
  "geometry": {"coordinates":[72.914541,28.390254],"type":"Point"}
}