{
  "type": "Feature",
  "properties": {
    "gn:admin1_code":"19",
    "gn:admin2_code":"563.0",
    "gn:asciiname":"Melin Targod",
    "gn:country_code":"IN",
    "gn:dem":546,
    "gn:feature_class":"P",
    "gn:feature_code":"PPL",
    "gn:name":"Melin T\u0101rgod",
    "gn:population":0,
    "gn:timezone":"Asia/Kolkata",
    "iso:country":"IN",
    "ks:ks_name":"Melin Targod",
    "ks:ks_pop":76,
    "ks:ks_type":"HABITATION",
    "name:eng_x_preferred":[
        "Melin Targod"
    ],
    "wof:name":"Melin Targod",
    "wof:placetype":"locality",
    "wof:population":76
},
  "geometry": {"coordinates":[74.839105,14.671228],"type":"Point"}
}