{
  "type": "Feature",
  "properties": {
    "gn:admin1_code":"19",
    "gn:admin2_code":"563.0",
    "gn:asciiname":"Melin Targod",
    "gn:country_code":"IN",
    "gn:dem":546,
    "gn:feature_class":"P",
    "gn:feature_code":"PPL",
    "gn:name":"Melin T\u0101rgod",
    "gn:population":0,
    "gn:timezone":"Asia/Kolkata",
    "iso:country":"IN",
    "wof:name":"Melin Targod",
    "wof:placetype":"locality"
},
  "geometry": {"coordinates":[74.83551999999997,14.66921],"type":"Point"}
}