{
  "type": "Feature",
  "properties": {
    "gn:admin1_code":"36",
    "gn:admin2_code":"175.0",
    "gn:asciiname":"Nimi",
    "gn:country_code":"IN",
    "gn:dem":97,
    "gn:feature_class":"P",
    "gn:feature_code":"PPL",
    "gn:name":"N\u012bm\u012b",
    "gn:population":0,
    "gn:timezone":"Asia/Kolkata",
    "iso:country":"IN",
    "name:ceb_x_preferred":[
        "Nimi"
    ],
    "name:swe_x_preferred":[
        "Nimi"
    ],
    "wof:name":"Nimi",
    "wof:placetype":"locality"
},
  "geometry": {"coordinates":[82.15016999999997,25.43417],"type":"Point"}
}