{
  "type": "Feature",
  "properties": {
    "gn:admin1_code":"39.0",
    "gn:admin2_code":"64.0",
    "gn:asciiname":"Mairi",
    "gn:country_code":"IN",
    "gn:dem":1326,
    "gn:feature_class":"P",
    "gn:feature_code":"PPL",
    "gn:name":"Mairi",
    "gn:population":0,
    "gn:timezone":"Asia/Kolkata",
    "iso:country":"IN",
    "name:ceb_x_preferred":[
        "Mairi"
    ],
    "name:fra_x_preferred":[
        "Mairi"
    ],
    "name:swe_x_preferred":[
        "Mairi"
    ],
    "wof:name":"Mairi",
    "wof:placetype":"locality"
},
  "geometry": {"coordinates":[79.52588,29.72481],"type":"Point"}
}