{
  "type": "Feature",
  "properties": {
    "gn:admin1_code":"21.0",
    "gn:admin2_code":"396.0",
    "gn:asciiname":"Dharapuram",
    "gn:country_code":"IN",
    "gn:dem":119,
    "gn:feature_class":"P",
    "gn:feature_code":"PPL",
    "gn:name":"Dharapuram",
    "gn:population":0,
    "gn:timezone":"Asia/Kolkata",
    "iso:country":"IN",
    "name:bpy_x_preferred":[
        "\u09a7\u09be\u09b0\u09be\u09aa\u09c1\u09b0\u09ae"
    ],
    "name:ceb_x_preferred":[
        "Dharapuram"
    ],
    "name:ind_x_preferred":[
        "Dharapuram"
    ],
    "name:ita_x_preferred":[
        "Dharapuram"
    ],
    "name:msa_x_preferred":[
        "Dharapuram"
    ],
    "name:new_x_preferred":[
        "\u0927\u093e\u0930\u093e\u092a\u0941\u0930\u092e"
    ],
    "name:por_x_preferred":[
        "Dharapuram"
    ],
    "name:spa_x_preferred":[
        "Dharapuram"
    ],
    "name:swe_x_preferred":[
        "Dharapuram"
    ],
    "name:tam_x_preferred":[
        "\u0ba4\u0bbe\u0bb0\u0bbe\u0baa\u0bc1\u0bb0\u0bae\u0bcd"
    ],
    "name:vie_x_preferred":[
        "Dharapuram"
    ],
    "name:zho_x_preferred":[
        "\u8fbe\u62c9\u666e\u62c9\u59c6"
    ],
    "wof:name":"Dharapuram",
    "wof:placetype":"locality"
},
  "geometry": {"coordinates":[83.78508000000002,19.24584],"type":"Point"}
}