{
  "type": "Feature",
  "properties": {
    "iso:country":"IN",
    "ks:ks_name":"Marulnaickanpatty",
    "ks:ks_pop":230,
    "ks:ks_type":"HABITATION",
    "name:eng_x_preferred":[
        "Marulnaickanpatty"
    ],
    "wof:name":"Marulnaickanpatty",
    "wof:placetype":"locality",
    "wof:population":230
},
  "geometry": {"coordinates":[78.51496299999999,10.633597],"type":"Point"}
}