{
  "type": "Feature",
  "properties": {
    "iso:country":"IN",
    "ks:ks_alt_nam":"MITHILANAGARAM",
    "ks:ks_name":"Mithilanagaram",
    "ks:ks_pop":89,
    "ks:ks_type":"HABITATION",
    "ks:ks_uagg_main":0,
    "name:eng_x_preferred":[
        "Mithilanagaram"
    ],
    "wof:name":"Mithilanagaram",
    "wof:placetype":"neighbourhood",
    "wof:population":89
},
  "geometry": {"coordinates":[79.13722300000001,13.130472],"type":"Point"}
}