{
  "type": "Feature",
  "properties": {
    "gn:admin1_code":"35.0",
    "gn:admin2_code":"439.0",
    "gn:asciiname":"Lasurdya Parmar",
    "gn:country_code":"IN",
    "gn:dem":527,
    "gn:feature_class":"P",
    "gn:feature_code":"PPL",
    "gn:name":"Lasurdya Parm\u0101r",
    "gn:population":0,
    "gn:timezone":"Asia/Kolkata",
    "iso:country":"IN",
    "ks:ks_name":"Lasudiya Parmar",
    "ks:ks_pop":1630,
    "ks:ks_type":"VILLAGE",
    "ks:ks_uagg_main":0,
    "name:eng_x_preferred":[
        "Lasudiya Parmar"
    ],
    "wof:name":"Lasudiya Parmar",
    "wof:placetype":"neighbourhood",
    "wof:population":1630
},
  "geometry": {"coordinates":[75.957392,22.849618],"type":"Point"}
}