{
  "type": "Feature",
  "properties": {
    "iso:country":"IN",
    "ks:ks_name":"Babanagar",
    "ks:ks_pop":253,
    "ks:ks_type":"HABITATION",
    "name:eng_x_preferred":[
        "Babanagar"
    ],
    "wof:name":"Babanagar",
    "wof:placetype":"locality",
    "wof:population":253
},
  "geometry": {"coordinates":[82.049296,16.51166],"type":"Point"}
}