{
  "type": "Feature",
  "properties": {
    "gn:admin1_code":"36.0",
    "gn:admin2_code":"151.0",
    "gn:asciiname":"Parsandi",
    "gn:country_code":"IN",
    "gn:dem":173,
    "gn:feature_class":"P",
    "gn:feature_code":"PPL",
    "gn:name":"Parsandi",
    "gn:population":0,
    "gn:timezone":"Asia/Kolkata",
    "iso:country":"IN",
    "ks:ks_name":"Parsandi",
    "ks:ks_type":"VILLAGE",
    "name:eng_x_preferred":[
        "Parsandi"
    ],
    "wof:name":"Parsandi",
    "wof:placetype":"locality"
},
  "geometry": {"coordinates":[79.866062,28.321988],"type":"Point"}
}