{
  "type": "Feature",
  "properties": {
    "gn:admin1_code":"12.0",
    "gn:admin2_code":"5.0",
    "gn:asciiname":"Nar",
    "gn:country_code":"IN",
    "gn:dem":2014,
    "gn:feature_class":"P",
    "gn:feature_code":"PPL",
    "gn:name":"N\u0101r",
    "gn:population":0,
    "gn:timezone":"Asia/Kolkata",
    "iso:country":"IN",
    "wof:name":"Nar",
    "wof:placetype":"locality"
},
  "geometry": {"coordinates":[74.32888,33.63602],"type":"Point"}
}