{
  "type": "Feature",
  "properties": {
    "iso:country":"IN",
    "ks:ks_name":"Boshawa Tola",
    "ks:ks_pop":132,
    "ks:ks_type":"HABITATION",
    "name:eng_x_preferred":[
        "Boshawa Tola"
    ],
    "wof:name":"Boshawa Tola",
    "wof:placetype":"locality",
    "wof:population":132
},
  "geometry": {"coordinates":[83.51485,27.272252],"type":"Point"}
}