{
  "type": "Feature",
  "properties": {
    "gn:admin1_code":"2.0",
    "gn:admin2_code":"550",
    "gn:asciiname":"Kaligiri",
    "gn:country_code":"IN",
    "gn:dem":68,
    "gn:feature_class":"P",
    "gn:feature_code":"PPL",
    "gn:name":"Kaligiri",
    "gn:population":0,
    "gn:timezone":"Asia/Kolkata",
    "iso:country":"IN",
    "name:new_x_preferred":[
        "\u0915\u0932\u093f\u0917\u093f\u0930\u093f \u092e\u0923\u094d\u0921\u0932"
    ],
    "name:tam_x_preferred":[
        "\u0b95\u0bb2\u0bbf\u0b95\u0bbf\u0bb0\u0bbf"
    ],
    "name:tel_x_preferred":[
        "\u0c15\u0c32\u0c3f\u0c17\u0c3f\u0c30\u0c3f"
    ],
    "wof:name":"Kaligiri",
    "wof:placetype":"locality"
},
  "geometry": {"coordinates":[79.69073,14.82844],"type":"Point"}
}