{
  "type": "Feature",
  "properties": {
    "iso:country":"IN",
    "ks:ks_alt_nam":"JagaNaik Thanda",
    "ks:ks_name":"Jaganaik Thanda",
    "ks:ks_pop":109,
    "ks:ks_type":"HABITATION",
    "name:eng_x_preferred":[
        "Jaganaik Thanda"
    ],
    "wof:name":"Jaganaik Thanda",
    "wof:placetype":"locality",
    "wof:population":109
},
  "geometry": {"coordinates":[77.38170700000001,18.252506],"type":"Point"}
}