{
  "type": "Feature",
  "properties": {
    "iso:country":"IN",
    "ks:ks_name":"Bhadidar",
    "ks:ks_pop":321,
    "ks:ks_type":"HABITATION",
    "name:eng_x_preferred":[
        "Bhadidar"
    ],
    "wof:name":"Bhadidar",
    "wof:placetype":"locality",
    "wof:population":321
},
  "geometry": {"coordinates":[84.23316,21.055311],"type":"Point"}
}