{
  "type": "Feature",
  "properties": {
    "iso:country":"IN",
    "ks:ks_alt_nam":"15  LNP-11B",
    "ks:ks_name":"15 Lnp-11b",
    "ks:ks_pop":31,
    "ks:ks_type":"HABITATION",
    "name:eng_x_preferred":[
        "15 Lnp-11b"
    ],
    "name:eng_x_variant":[
        "15  LNP-11B"
    ],
    "wof:name":"15 Lnp-11b",
    "wof:placetype":"locality",
    "wof:population":31
},
  "geometry": {"coordinates":[73.997694,29.809008],"type":"Point"}
}