{
  "type": "Feature",
  "properties": {
    "iso:country":"IN",
    "ks:ks_name":"Veerakanchipuram",
    "ks:ks_pop":120,
    "ks:ks_type":"HABITATION",
    "name:eng_x_preferred":[
        "Veerakanchipuram"
    ],
    "wof:name":"Veerakanchipuram",
    "wof:placetype":"locality",
    "wof:population":120
},
  "geometry": {"coordinates":[78.267076,9.10911],"type":"Point"}
}