{
  "type": "Feature",
  "properties": {
    "iso:country":"IN",
    "ks:ks_name":"Amatekoppa",
    "ks:ks_pop":104,
    "ks:ks_type":"HABITATION",
    "name:eng_x_preferred":[
        "Amatekoppa"
    ],
    "wof:name":"Amatekoppa",
    "wof:placetype":"locality",
    "wof:population":104
},
  "geometry": {"coordinates":[75.067711,14.128698],"type":"Point"}
}