{
  "type": "Feature",
  "properties": {
    "iso:country":"IN",
    "ks:ks_name":"Huladevanasar",
    "ks:ks_pop":168,
    "ks:ks_type":"HABITATION",
    "name:eng_x_preferred":[
        "Huladevanasar"
    ],
    "wof:name":"Huladevanasar",
    "wof:placetype":"locality",
    "wof:population":168
},
  "geometry": {"coordinates":[74.79594,14.732675],"type":"Point"}
}