{
  "type": "Feature",
  "properties": {
    "gn:admin1_code":"36",
    "gn:admin2_code":"170.0",
    "gn:asciiname":"Naurangabad",
    "gn:country_code":"IN",
    "gn:dem":139,
    "gn:feature_class":"P",
    "gn:feature_code":"PPL",
    "gn:name":"Naurang\u0101b\u0101d",
    "gn:population":0,
    "gn:timezone":"Asia/Kolkata",
    "iso:country":"IN",
    "name:tat_x_preferred":[
        "\u041d\u0430\u0443\u0440\u0430\u043d\u0433\u0430\u0431\u0430\u0434"
    ],
    "wof:name":"Naurangabad",
    "wof:placetype":"locality"
},
  "geometry": {"coordinates":[80.33504000000001,25.30686],"type":"Point"}
}