{
  "type": "Feature",
  "properties": {
    "iso:country":"IN",
    "ks:ks_name":"Seepur",
    "ks:ks_pop":196,
    "ks:ks_type":"HABITATION",
    "name:eng_x_preferred":[
        "Seepur"
    ],
    "wof:name":"Seepur",
    "wof:placetype":"locality",
    "wof:population":196
},
  "geometry": {"coordinates":[84.913764,21.283249],"type":"Point"}
}