{
  "type": "Feature",
  "properties": {
    "iso:country":"IN",
    "ks:ks_name":"Nauka Tola",
    "ks:ks_pop":861,
    "ks:ks_type":"HABITATION",
    "ks:ks_uagg_main":0,
    "name:eng_x_preferred":[
        "Nauka Tola"
    ],
    "wof:name":"Nauka Tola",
    "wof:placetype":"neighbourhood",
    "wof:population":861
},
  "geometry": {"coordinates":[83.791141,27.381159],"type":"Point"}
}