{
  "type": "Feature",
  "properties": {
    "iso:country":"IN",
    "ks:ks_name":"Barait",
    "ks:ks_pop":167,
    "ks:ks_type":"VILLAGE",
    "name:eng_x_preferred":[
        "Barait"
    ],
    "wof:name":"Barait",
    "wof:placetype":"locality",
    "wof:population":167
},
  "geometry": {"coordinates":[79.945624,29.363245],"type":"Point"}
}