{
  "type": "Feature",
  "properties": {
    "gn:admin1_code":"36",
    "gn:admin2_code":"173.0",
    "gn:asciiname":"Khushiyali ka Pura",
    "gn:country_code":"IN",
    "gn:dem":97,
    "gn:feature_class":"P",
    "gn:feature_code":"PPL",
    "gn:name":"Khushiy\u0101li ka Pura",
    "gn:population":0,
    "gn:timezone":"Asia/Kolkata",
    "iso:country":"IN",
    "wof:name":"Khushiyali ka Pura",
    "wof:placetype":"neighbourhood"
},
  "geometry": {"coordinates":[82.07012,25.67825],"type":"Point"}
}