{
  "type": "Feature",
  "properties": {
    "iso:country":"IN",
    "ks:ks_name":"Hulliyamballi",
    "ks:ks_pop":42,
    "ks:ks_type":"HABITATION",
    "name:eng_x_preferred":[
        "Hulliyamballi"
    ],
    "wof:name":"Hulliyamballi",
    "wof:placetype":"locality",
    "wof:population":42
},
  "geometry": {"coordinates":[75.973889,11.999722],"type":"Point"}
}