{
  "type": "Feature",
  "properties": {
    "iso:country":"IN",
    "ks:ks_name":"Tal Dohar",
    "ks:ks_pop":96,
    "ks:ks_type":"VILLAGE",
    "name:eng_x_preferred":[
        "Tal Dohar"
    ],
    "wof:name":"Tal Dohar",
    "wof:placetype":"locality",
    "wof:population":96
},
  "geometry": {"coordinates":[83.459766,26.501622],"type":"Point"}
}