{
  "type": "Feature",
  "properties": {
    "iso:country":"IN",
    "ks:ks_name":"Chak Chauhani",
    "ks:ks_pop":1936,
    "ks:ks_type":"VILLAGE",
    "ks:ks_uagg_main":0,
    "name:eng_x_preferred":[
        "Chak Chauhani"
    ],
    "wof:name":"Chak Chauhani",
    "wof:placetype":"neighbourhood",
    "wof:population":1936
},
  "geometry": {"coordinates":[85.138121,26.395859],"type":"Point"}
}