{
  "type": "Feature",
  "properties": {
    "iso:country":"IN",
    "ks:ks_name":"Hoigegudde",
    "ks:ks_pop":260,
    "ks:ks_type":"HABITATION",
    "name:eng_x_preferred":[
        "Hoigegudde"
    ],
    "wof:name":"Hoigegudde",
    "wof:placetype":"locality",
    "wof:population":260
},
  "geometry": {"coordinates":[74.85053499999999,12.831118],"type":"Point"}
}