{
  "type": "Feature",
  "properties": {
    "iso:country":"IN",
    "ks:ks_name":"Sah Tola",
    "ks:ks_pop":78,
    "ks:ks_type":"HABITATION",
    "name:eng_x_preferred":[
        "Sah Tola"
    ],
    "wof:name":"Sah Tola",
    "wof:placetype":"locality",
    "wof:population":78
},
  "geometry": {"coordinates":[84.48506500000001,26.486017],"type":"Point"}
}