{
  "type": "Feature",
  "properties": {
    "iso:country":"IN",
    "ks:ks_alt_nam":"L\u0101lpur Khadra",
    "ks:ks_name":"Lalpur Khadra",
    "ks:ks_type":"VILLAGE",
    "name:eng_x_preferred":[
        "Lalpur Khadra"
    ],
    "name:eng_x_variant":[
        "L\u0101lpur Khadra"
    ],
    "wof:name":"Lalpur Khadra",
    "wof:placetype":"locality"
},
  "geometry": {"coordinates":[81.951013,27.566927],"type":"Point"}
}