{
  "type": "Feature",
  "properties": {
    "gn:admin1_code":"2",
    "gn:admin2_code":"545.0",
    "gn:asciiname":"Sevadikota",
    "gn:country_code":"IN",
    "gn:dem":868,
    "gn:feature_class":"P",
    "gn:feature_code":"PPL",
    "gn:name":"Sevadikota",
    "gn:population":0,
    "gn:timezone":"Asia/Kolkata",
    "iso:country":"IN",
    "wof:name":"Sevadikota",
    "wof:placetype":"locality"
},
  "geometry": {"coordinates":[81.86001999999998,17.78092000000001],"type":"Point"}
}