{
  "type": "Feature",
  "properties": {
    "iso:country":"IN",
    "ks:ks_name":"Khajoori",
    "ks:ks_pop":1038,
    "ks:ks_type":"HABITATION",
    "name:eng_x_preferred":[
        "Khajoori"
    ],
    "wof:name":"Khajoori",
    "wof:placetype":"locality",
    "wof:population":1038
},
  "geometry": {"coordinates":[74.19606400000001,24.214761],"type":"Point"}
}