{
  "type": "Feature",
  "properties": {
    "gn:admin1_code":"39.0",
    "gn:admin2_code":"61.0",
    "gn:asciiname":"Lachhi",
    "gn:country_code":"IN",
    "gn:dem":1485,
    "gn:feature_class":"P",
    "gn:feature_code":"PPL",
    "gn:name":"L\u0101chhi",
    "gn:population":0,
    "gn:timezone":"Asia/Kolkata",
    "iso:country":"IN",
    "ks:ks_alt_nam":"L\u0101chhi",
    "ks:ks_name":"Lachhi",
    "ks:ks_type":"VILLAGE",
    "name:eng_x_preferred":[
        "Lachhi"
    ],
    "name:eng_x_variant":[
        "L\u0101chhi"
    ],
    "wof:name":"Lachhi",
    "wof:placetype":"locality"
},
  "geometry": {"coordinates":[79.041616,29.905545],"type":"Point"}
}