{
  "type": "Feature",
  "properties": {
    "iso:country":"IN",
    "ks:ks_name":"Chaq Kewat Ali Gair Abad",
    "ks:ks_pop":0,
    "ks:ks_type":"VILLAGE",
    "name:eng_x_preferred":[
        "Chaq Kewat Ali Gair Abad"
    ],
    "wof:name":"Chaq Kewat Ali Gair Abad",
    "wof:placetype":"locality",
    "wof:population":0
},
  "geometry": {"coordinates":[81.93883,25.510822],"type":"Point"}
}