{
  "type": "Feature",
  "properties": {
    "iso:country":"IN",
    "ks:ks_name":"Khango",
    "ks:ks_pop":332,
    "ks:ks_type":"HABITATION",
    "name:eng_x_preferred":[
        "Khango"
    ],
    "wof:name":"Khango",
    "wof:placetype":"locality",
    "wof:population":332
},
  "geometry": {"coordinates":[79.886623,23.548559],"type":"Point"}
}