{
  "type": "Feature",
  "properties": {
    "iso:country":"IN",
    "ks:ks_name":"Hatigarh 1",
    "ks:ks_pop":221,
    "ks:ks_type":"HABITATION",
    "name:eng_x_preferred":[
        "Hatigarh 1"
    ],
    "wof:name":"Hatigarh 1",
    "wof:placetype":"locality",
    "wof:population":221
},
  "geometry": {"coordinates":[92.543091,26.11042],"type":"Point"}
}