{
  "type": "Feature",
  "properties": {
    "gn:admin1_code":"36.0",
    "gn:admin2_code":"189.0",
    "gn:asciiname":"Loharpatti",
    "gn:country_code":"IN",
    "gn:dem":89,
    "gn:feature_class":"P",
    "gn:feature_code":"PPL",
    "gn:name":"Loharpatti",
    "gn:population":0,
    "gn:timezone":"Asia/Kolkata",
    "iso:country":"IN",
    "ks:ks_name":"Lohar Patti",
    "ks:ks_pop":313,
    "ks:ks_type":"VILLAGE",
    "name:bih_x_preferred":[
        "\u0932\u094b\u0939\u093e\u0930\u092a\u091f\u094d\u091f\u0940"
    ],
    "name:ceb_x_preferred":[
        "Loharpatti"
    ],
    "name:eng_x_preferred":[
        "Lohar Patti"
    ],
    "name:eng_x_variant":[
        "Loharpatti"
    ],
    "name:mai_x_preferred":[
        "\u0932\u094b\u0939\u093e\u0930\u092a\u091f\u094d\u091f\u0940"
    ],
    "name:msa_x_preferred":[
        "Loharpatti"
    ],
    "name:nep_x_preferred":[
        "\u0932\u094b\u0939\u093e\u0930\u092a\u091f\u094d\u091f\u0940"
    ],
    "name:new_x_preferred":[
        "\u0932\u094b\u0939\u093e\u0930\u092a\u091f\u094d\u091f\u0940"
    ],
    "name:pol_x_preferred":[
        "Loharpatti"
    ],
    "wof:name":"Lohar Patti",
    "wof:placetype":"locality",
    "wof:population":313
},
  "geometry": {"coordinates":[84.120324,26.816428],"type":"Point"}
}