{
  "type": "Feature",
  "properties": {
    "gn:admin1_code":"19",
    "gn:admin2_code":"563.0",
    "gn:asciiname":"Uplekop",
    "gn:country_code":"IN",
    "gn:dem":595,
    "gn:feature_class":"P",
    "gn:feature_code":"PPL",
    "gn:name":"Uplekop",
    "gn:population":0,
    "gn:timezone":"Asia/Kolkata",
    "iso:country":"IN",
    "ks:ks_name":"Uplekop",
    "ks:ks_type":"VILLAGE",
    "name:eng_x_preferred":[
        "Uplekop"
    ],
    "wof:name":"Uplekop",
    "wof:placetype":"locality"
},
  "geometry": {"coordinates":[74.899587,14.564696],"type":"Point"}
}