{
  "type": "Feature",
  "properties": {
    "gn:admin1_code":"40",
    "gn:admin2_code":"538.0",
    "gn:asciiname":"Inayatkhanguda",
    "gn:country_code":"IN",
    "gn:dem":637,
    "gn:feature_class":"P",
    "gn:feature_code":"PPL",
    "gn:name":"In\u0101yatkh\u0101nguda",
    "gn:population":0,
    "gn:timezone":"Asia/Kolkata",
    "iso:country":"IN",
    "wof:name":"Inayatkhanguda",
    "wof:placetype":"locality"
},
  "geometry": {"coordinates":[78.21429000000001,17.04407999999999],"type":"Point"}
}