{
  "type": "Feature",
  "properties": {
    "gn:admin1_code":"39.0",
    "gn:admin2_code":"59.0",
    "gn:asciiname":"Siyagaon",
    "gn:country_code":"IN",
    "gn:dem":1550,
    "gn:feature_class":"P",
    "gn:feature_code":"PPL",
    "gn:name":"Siy\u0101gaon",
    "gn:population":0,
    "gn:timezone":"Asia/Kolkata",
    "iso:country":"IN",
    "name:ara_x_preferred":[
        "\u0633\u064a\u0627\u062c\u0648\u0646"
    ],
    "name:ben_bn_x_preferred":[
        "\u09b8\u09bf\u09df\u09be\u0997\u09be\u0981\u0993"
    ],
    "name:ben_in_x_preferred":[
        "\u09b8\u09bf\u09df\u09be\u0997\u09be\u0981\u0993"
    ],
    "name:guj_x_preferred":[
        "\u0ab8\u0abf\u0aaf\u0abe\u0a97\u0abe\u0a82\u0ab5"
    ],
    "name:hin_x_preferred":[
        "\u0938\u093f\u092f\u093e\u0917\u093e\u0902\u0935"
    ],
    "name:kan_x_preferred":[
        "\u0cb8\u0cbf\u0caf\u0cbe\u0c97\u0cbe\u0c82\u0cb5\u0ccd"
    ],
    "name:mal_x_preferred":[
        "\u0d38\u0d3f\u0d2f\u0d3e\u0d17\u0d4b\u0d7a"
    ],
    "name:mar_x_preferred":[
        "\u0938\u093f\u092f\u093e\u0917\u093e\u0935"
    ],
    "name:pan_x_preferred":[
        "\u0a38\u0a3f\u0a06\u0a17\u0a3e\u0a13\u0a02"
    ],
    "name:tam_x_preferred":[
        "\u0b9a\u0bbf\u0baf\u0bbe\u0b95\u0bbe\u0bb5\u0bcd\u0ba9\u0bcd"
    ],
    "name:tel_x_preferred":[
        "\u0c38\u0c3f\u0c2f\u0c3e\u0c17\u0c3e\u0c02\u0c35\u0c4d"
    ],
    "name:urd_x_preferred":[
        "\u0633\u06cc\u0627 \u06af\u0627\u0624\u0646"
    ],
    "wof:name":"Siyagaon",
    "wof:placetype":"locality"
},
  "geometry": {"coordinates":[78.04720999999998,30.4845],"type":"Point"}
}