{
  "type": "Feature",
  "properties": {
    "iso:country":"IN",
    "ks:ks_name":"Chippada",
    "ks:ks_pop":1155,
    "ks:ks_type":"VILLAGE",
    "name:eng_x_preferred":[
        "Chippada"
    ],
    "wof:name":"Chippada",
    "wof:placetype":"locality",
    "wof:population":1155
},
  "geometry": {"coordinates":[83.011679,17.524011],"type":"Point"}
}