{
  "type": "Feature",
  "properties": {
    "iso:country":"IN",
    "ks:ks_name":"Saunkhola",
    "ks:ks_pop":351,
    "ks:ks_type":"VILLAGE",
    "name:eng_x_preferred":[
        "Saunkhola"
    ],
    "wof:name":"Saunkhola",
    "wof:placetype":"locality",
    "wof:population":351
},
  "geometry": {"coordinates":[79.359528,29.623377],"type":"Point"}
}