{
  "type": "Feature",
  "properties": {
    "iso:country":"IN",
    "ks:ks_name":"Gameerpura Hameera",
    "ks:ks_pop":234,
    "ks:ks_type":"HABITATION",
    "name:eng_x_preferred":[
        "Gameerpura Hameera"
    ],
    "wof:name":"Gameerpura Hameera",
    "wof:placetype":"locality",
    "wof:population":234
},
  "geometry": {"coordinates":[74.181208,23.432019],"type":"Point"}
}