{
  "type": "Feature",
  "properties": {
    "gn:admin1_code":"34.0",
    "gn:admin2_code":"209.0",
    "gn:asciiname":"Amgachhi",
    "gn:country_code":"IN",
    "gn:dem":59,
    "gn:feature_class":"P",
    "gn:feature_code":"PPL",
    "gn:name":"\u0100mg\u0101chhi",
    "gn:population":0,
    "gn:timezone":"Asia/Kolkata",
    "iso:country":"IN",
    "ks:ks_name":"Aamgachhi",
    "ks:ks_pop":577,
    "ks:ks_type":"HABITATION",
    "name:ceb_x_preferred":[
        "Amgachhi"
    ],
    "name:eng_x_preferred":[
        "Aamgachhi"
    ],
    "name:eng_x_variant":[
        "Amgachhi"
    ],
    "name:fas_x_preferred":[
        "\u0627\u0645\u06af\u0627\u0686\u06cc"
    ],
    "name:msa_x_preferred":[
        "Amgachhi"
    ],
    "name:new_x_preferred":[
        "\u0906\u092e\u0917\u093e\u091b\u0940"
    ],
    "name:pol_x_preferred":[
        "Amgachhi"
    ],
    "wof:name":"Aamgachhi",
    "wof:placetype":"locality",
    "wof:population":577
},
  "geometry": {"coordinates":[87.521795,26.252964],"type":"Point"}
}