{
  "type": "Feature",
  "properties": {
    "iso:country":"IN",
    "ks:ks_name":"Laibri Para",
    "ks:ks_pop":1422,
    "ks:ks_type":"HABITATION",
    "name:eng_x_preferred":[
        "Laibri Para"
    ],
    "wof:name":"Laibri Para",
    "wof:placetype":"locality",
    "wof:population":1422
},
  "geometry": {"coordinates":[88.294372,21.796976],"type":"Point"}
}