{
  "type": "Feature",
  "properties": {
    "gn:admin1_code":"19.0",
    "gn:admin2_code":"584.0",
    "gn:asciiname":"Bijhalli",
    "gn:country_code":"IN",
    "gn:dem":690,
    "gn:feature_class":"P",
    "gn:feature_code":"PPL",
    "gn:name":"Bijhalli",
    "gn:population":0,
    "gn:timezone":"Asia/Kolkata",
    "iso:country":"IN",
    "wof:name":"Bijhalli",
    "wof:placetype":"locality"
},
  "geometry": {"coordinates":[77.54382,12.44985],"type":"Point"}
}