{
  "type": "Feature",
  "properties": {
    "gn:admin1_code":"35.0",
    "gn:admin2_code":"457.0",
    "gn:asciiname":"Bhiri",
    "gn:country_code":"IN",
    "gn:dem":595,
    "gn:feature_class":"P",
    "gn:feature_code":"PPL",
    "gn:name":"Bh\u012bri",
    "gn:population":0,
    "gn:timezone":"Asia/Kolkata",
    "iso:country":"IN",
    "wof:name":"Bhiri",
    "wof:placetype":"locality"
},
  "geometry": {"coordinates":[80.34936999999999,22.142],"type":"Point"}
}