{
  "type": "Feature",
  "properties": {
    "iso:country":"IN",
    "ks:ks_name":"Manappakkam",
    "ks:ks_type":"VILLAGE",
    "ks:ks_uagg_main":0,
    "name:eng_x_preferred":[
        "Manappakkam"
    ],
    "wof:name":"Manappakkam",
    "wof:placetype":"neighbourhood"
},
  "geometry": {"coordinates":[80.168611,13.010833],"type":"Point"}
}