{
  "type": "Feature",
  "properties": {
    "gn:admin1_code":"12.0",
    "gn:admin2_code":"14.0",
    "gn:asciiname":"Badaran",
    "gn:country_code":"IN",
    "gn:dem":1778,
    "gn:feature_class":"P",
    "gn:feature_code":"PPL",
    "gn:name":"Bad\u0101ran",
    "gn:population":0,
    "gn:timezone":"Asia/Kolkata",
    "iso:country":"IN",
    "wof:name":"Badaran",
    "wof:placetype":"locality"
},
  "geometry": {"coordinates":[75.26793000000001,33.8461],"type":"Point"}
}