{
  "type": "Feature",
  "properties": {
    "gn:admin1_code":"25.0",
    "gn:admin2_code":"611.0",
    "gn:asciiname":"Bikkekandi",
    "gn:country_code":"IN",
    "gn:dem":1870,
    "gn:feature_class":"P",
    "gn:feature_code":"PPL",
    "gn:name":"Bikkekandi",
    "gn:population":0,
    "gn:timezone":"Asia/Kolkata",
    "iso:country":"IN",
    "wof:name":"Bikkekandi",
    "wof:placetype":"locality"
},
  "geometry": {"coordinates":[76.66096999999998,11.48194],"type":"Point"}
}