{
  "type": "Feature",
  "properties": {
    "iso:country":"IN",
    "ks:ks_name":"Shibpur",
    "ks:ks_pop":585,
    "ks:ks_type":"VILLAGE",
    "ks:ks_uagg_main":0,
    "name:eng_x_preferred":[
        "Shibpur"
    ],
    "wof:name":"Shibpur",
    "wof:placetype":"neighbourhood",
    "wof:population":585
},
  "geometry": {"coordinates":[88.19414399999999,25.715548],"type":"Point"}
}