{
  "type": "Feature",
  "properties": {
    "iso:country":"IN",
    "ks:ks_name":"Jaddupur",
    "ks:ks_pop":105,
    "ks:ks_type":"HABITATION",
    "name:eng_x_preferred":[
        "Jaddupur"
    ],
    "wof:name":"Jaddupur",
    "wof:placetype":"locality",
    "wof:population":105
},
  "geometry": {"coordinates":[82.83366100000001,25.463243],"type":"Point"}
}