{
  "type": "Feature",
  "properties": {
    "gn:admin1_code":"24.0",
    "gn:admin2_code":"117.0",
    "gn:asciiname":"Dhanari",
    "gn:country_code":"IN",
    "gn:dem":329,
    "gn:feature_class":"P",
    "gn:feature_code":"PPL",
    "gn:name":"Dhan\u0101ri",
    "gn:population":0,
    "gn:timezone":"Asia/Kolkata",
    "iso:country":"IN",
    "wof:name":"Dhanari",
    "wof:placetype":"locality"
},
  "geometry": {"coordinates":[72.92740000000001,24.68388],"type":"Point"}
}