{
  "type": "Feature",
  "properties": {
    "iso:country":"IN",
    "ks:ks_name":"43rd Mile",
    "ks:ks_pop":251,
    "ks:ks_type":"HABITATION",
    "name:eng_x_preferred":[
        "43rd Mile"
    ],
    "wof:name":"43rd Mile",
    "wof:placetype":"locality",
    "wof:population":251
},
  "geometry": {"coordinates":[75.926738,11.83799],"type":"Point"}
}