{
  "type": "Feature",
  "properties": {
    "iso:country":"IN",
    "ks:ks_name":"Hanwant Nagar",
    "ks:ks_pop":355,
    "ks:ks_type":"HABITATION",
    "name:eng_x_preferred":[
        "Hanwant Nagar"
    ],
    "wof:name":"Hanwant Nagar",
    "wof:placetype":"locality",
    "wof:population":355
},
  "geometry": {"coordinates":[72.22861899999999,27.424878],"type":"Point"}
}