{
  "type": "Feature",
  "properties": {
    "gn:admin1_code":"34.0",
    "gn:admin2_code":"221.0",
    "gn:asciiname":"Waina",
    "gn:country_code":"IN",
    "gn:dem":49,
    "gn:feature_class":"P",
    "gn:feature_code":"PPL",
    "gn:name":"Waina",
    "gn:population":0,
    "gn:timezone":"Asia/Kolkata",
    "iso:country":"IN",
    "ks:ks_name":"Waina",
    "ks:ks_type":"VILLAGE",
    "name:eng_x_preferred":[
        "Waina"
    ],
    "wof:name":"Waina",
    "wof:placetype":"locality"
},
  "geometry": {"coordinates":[85.66479,25.758008],"type":"Point"}
}