{
  "type": "Feature",
  "properties": {
    "iso:country":"IN",
    "ks:ks_alt_nam":"hakkalamane",
    "ks:ks_name":"Hakkalamane",
    "ks:ks_pop":81,
    "ks:ks_type":"HABITATION",
    "name:eng_x_preferred":[
        "Hakkalamane"
    ],
    "wof:name":"Hakkalamane",
    "wof:placetype":"locality",
    "wof:population":81
},
  "geometry": {"coordinates":[74.577651,13.970316],"type":"Point"}
}