{
  "type": "Feature",
  "properties": {
    "iso:country":"IN",
    "ks:ks_name":"Tayab Chak",
    "ks:ks_pop":475,
    "ks:ks_type":"VILLAGE",
    "name:eng_x_preferred":[
        "Tayab Chak"
    ],
    "wof:name":"Tayab Chak",
    "wof:placetype":"locality",
    "wof:population":475
},
  "geometry": {"coordinates":[85.20904,25.93119],"type":"Point"}
}