{
  "type": "Feature",
  "properties": {
    "iso:country":"IN",
    "ks:ks_name":"Kandhabundar",
    "ks:ks_pop":4,
    "ks:ks_type":"HABITATION",
    "name:eng_x_preferred":[
        "Kandhabundar"
    ],
    "wof:name":"Kandhabundar",
    "wof:placetype":"locality",
    "wof:population":4
},
  "geometry": {"coordinates":[84.549976,20.221912],"type":"Point"}
}