{
  "type": "Feature",
  "properties": {
    "iso:country":"IN",
    "ks:ks_name":"Arashigod",
    "ks:ks_pop":150,
    "ks:ks_type":"HABITATION",
    "name:eng_x_preferred":[
        "Arashigod"
    ],
    "wof:name":"Arashigod",
    "wof:placetype":"locality",
    "wof:population":150
},
  "geometry": {"coordinates":[74.828361,14.423292],"type":"Point"}
}