{
  "type": "Feature",
  "properties": {
    "gn:admin1_code":"35.0",
    "gn:admin2_code":"418.0",
    "gn:asciiname":"Danglipura",
    "gn:country_code":"IN",
    "gn:dem":188,
    "gn:feature_class":"P",
    "gn:feature_code":"PPL",
    "gn:name":"Dangl\u012bpura",
    "gn:population":0,
    "gn:timezone":"Asia/Kolkata",
    "iso:country":"IN",
    "wof:name":"Danglipura",
    "wof:placetype":"locality"
},
  "geometry": {"coordinates":[76.88686,26.03691],"type":"Point"}
}