{
  "type": "Feature",
  "properties": {
    "iso:country":"IN",
    "ks:ks_name":"Mashidwadi",
    "ks:ks_pop":142,
    "ks:ks_type":"VILLAGE",
    "name:eng_x_preferred":[
        "Mashidwadi"
    ],
    "wof:name":"Mashidwadi",
    "wof:placetype":"locality",
    "wof:population":142
},
  "geometry": {"coordinates":[73.350914,18.309206],"type":"Point"}
}