{
  "type": "Feature",
  "properties": {
    "iso:country":"IN",
    "ks:ks_name":"Dihi Palsya",
    "ks:ks_pop":306,
    "ks:ks_type":"VILLAGE",
    "ks:ks_uagg_main":0,
    "name:eng_x_preferred":[
        "Dihi Palsya"
    ],
    "wof:name":"Dihi Palsya",
    "wof:placetype":"neighbourhood",
    "wof:population":306
},
  "geometry": {"coordinates":[87.566118,22.195334],"type":"Point"}
}