{
  "type": "Feature",
  "properties": {
    "gn:admin1_code":"35",
    "gn:admin2_code":"447.0",
    "gn:asciiname":"Kharwar",
    "gn:country_code":"IN",
    "gn:dem":472,
    "gn:feature_class":"P",
    "gn:feature_code":"PPL",
    "gn:name":"Kharw\u0101r",
    "gn:population":0,
    "gn:timezone":"Asia/Kolkata",
    "iso:country":"IN",
    "name:hin_x_preferred":[
        "\u0916\u0930\u0935\u093e\u0930"
    ],
    "wof:name":"Kharwar",
    "wof:placetype":"locality"
},
  "geometry": {"coordinates":[77.66509000000001,22.25004],"type":"Point"}
}