{
  "type": "Feature",
  "properties": {
    "iso:country":"IN",
    "ks:ks_name":"Pure Ram Avtar",
    "ks:ks_pop":26,
    "ks:ks_type":"HABITATION",
    "name:eng_x_preferred":[
        "Pure Ram Avtar"
    ],
    "wof:name":"Pure Ram Avtar",
    "wof:placetype":"locality",
    "wof:population":26
},
  "geometry": {"coordinates":[81.803515,26.392557],"type":"Point"}
}