{
  "type": "Feature",
  "properties": {
    "gn:admin1_code":"12",
    "gn:admin2_code":"18.0",
    "gn:asciiname":"Miagot",
    "gn:country_code":"IN",
    "gn:dem":3437,
    "gn:feature_class":"P",
    "gn:feature_code":"PPL",
    "gn:name":"Mi\u0101g\u014dt",
    "gn:population":0,
    "gn:timezone":"Asia/Kolkata",
    "iso:country":"IN",
    "wof:name":"Miagot",
    "wof:placetype":"locality"
},
  "geometry": {"coordinates":[76.22515,33.37873],"type":"Point"}
}