{
  "type": "Feature",
  "properties": {
    "gn:admin1_code":"2.0",
    "gn:admin2_code":"554.0",
    "gn:asciiname":"Gutturu",
    "gn:country_code":"IN",
    "gn:dem":711,
    "gn:feature_class":"P",
    "gn:feature_code":"PPL",
    "gn:name":"Gutt\u016bru",
    "gn:population":0,
    "gn:timezone":"Asia/Kolkata",
    "iso:country":"IN",
    "ks:ks_name":"Gutturu",
    "ks:ks_pop":64,
    "ks:ks_type":"HABITATION",
    "name:eng_x_preferred":[
        "Gutturu"
    ],
    "wof:name":"Gutturu",
    "wof:placetype":"locality",
    "wof:population":64
},
  "geometry": {"coordinates":[78.293972,13.615399],"type":"Point"}
}