{
  "type": "Feature",
  "properties": {
    "gn:admin1_code":"37",
    "gn:admin2_code":"401.0",
    "gn:asciiname":"Chakeri",
    "gn:country_code":"IN",
    "gn:dem":556,
    "gn:feature_class":"P",
    "gn:feature_code":"PPL",
    "gn:name":"Chakeri",
    "gn:population":0,
    "gn:timezone":"Asia/Kolkata",
    "iso:country":"IN",
    "name:bpy_x_preferred":[
        "\u099a\u0995\u09c7\u09b0\u09bf"
    ],
    "name:ita_x_preferred":[
        "Chakeri"
    ],
    "name:mlg_x_preferred":[
        "Chakeri"
    ],
    "name:msa_x_preferred":[
        "Chakeri"
    ],
    "name:new_x_preferred":[
        "\u091a\u0915\u0947\u0930\u0940"
    ],
    "name:nld_x_preferred":[
        "Chakeri"
    ],
    "name:pol_x_preferred":[
        "Chakeri"
    ],
    "name:por_x_preferred":[
        "Chakeri"
    ],
    "name:urd_x_preferred":[
        "\u0686\u06a9\u06cc\u0631\u06cc"
    ],
    "name:vie_x_preferred":[
        "Chakeri"
    ],
    "name:zho_x_preferred":[
        "\u6070\u51ef\u91cc"
    ],
    "wof:name":"Chakeri",
    "wof:placetype":"locality"
},
  "geometry": {"coordinates":[82.90653,22.84834],"type":"Point"}
}