{
  "type": "Feature",
  "properties": {
    "gn:admin1_code":"37",
    "gn:admin2_code":"414.0",
    "gn:asciiname":"Ataraguda",
    "gn:country_code":"IN",
    "gn:dem":562,
    "gn:feature_class":"P",
    "gn:feature_code":"PPL",
    "gn:name":"Atar\u0101guda",
    "gn:population":0,
    "gn:timezone":"Asia/Kolkata",
    "iso:country":"IN",
    "wof:name":"Ataraguda",
    "wof:placetype":"locality"
},
  "geometry": {"coordinates":[82.00766999999998,19.28462],"type":"Point"}
}