{
  "type": "Feature",
  "properties": {
    "gn:admin1_code":"24.0",
    "gn:admin2_code":"103",
    "gn:asciiname":"Pandasi",
    "gn:country_code":"IN",
    "gn:dem":284,
    "gn:feature_class":"P",
    "gn:feature_code":"PPL",
    "gn:name":"P\u0101nd\u0101si",
    "gn:population":0,
    "gn:timezone":"Asia/Kolkata",
    "iso:country":"IN",
    "ks:ks_alt_nam":"P\u0101nd\u0101si",
    "ks:ks_name":"Pandasi",
    "ks:ks_pop":627,
    "ks:ks_type":"VILLAGE",
    "name:eng_x_preferred":[
        "Pandasi"
    ],
    "name:eng_x_variant":[
        "P\u0101nd\u0101si"
    ],
    "wof:name":"Pandasi",
    "wof:placetype":"locality",
    "wof:population":627
},
  "geometry": {"coordinates":[75.33497199999999,28.348444],"type":"Point"}
}