{
  "type": "Feature",
  "properties": {
    "iso:country":"IN",
    "ks:ks_name":"Hiragapura",
    "ks:ks_pop":1135,
    "ks:ks_type":"VILLAGE",
    "name:eng_x_preferred":[
        "Hiragapura"
    ],
    "wof:name":"Hiragapura",
    "wof:placetype":"locality",
    "wof:population":1135
},
  "geometry": {"coordinates":[75.690651,13.68642],"type":"Point"}
}