{
  "type": "Feature",
  "properties": {
    "gn:admin1_code":"36",
    "gn:admin2_code":"154.0",
    "gn:asciiname":"Gopalapur",
    "gn:country_code":"IN",
    "gn:dem":137,
    "gn:feature_class":"P",
    "gn:feature_code":"PPL",
    "gn:name":"Gop\u0101l\u0101pur",
    "gn:population":0,
    "gn:timezone":"Asia/Kolkata",
    "iso:country":"IN",
    "name:ara_x_preferred":[
        "\u062c\u0648\u0628\u0627\u0644\u0627\u0628\u0648\u0631"
    ],
    "name:ben_bn_x_preferred":[
        "\u0997\u09cb\u09aa\u09be\u09b2\u09be\u09aa\u09c1\u09b0"
    ],
    "name:ben_in_x_preferred":[
        "\u0997\u09cb\u09aa\u09be\u09b2\u09aa\u09c1\u09b0"
    ],
    "name:guj_x_preferred":[
        "\u0a97\u0acb\u0aaa\u0abe\u0ab2\u0aaa\u0ac1\u0ab0"
    ],
    "name:hin_x_preferred":[
        "\u0917\u094b\u092a\u093e\u0932\u092a\u0941\u0930"
    ],
    "name:kan_x_preferred":[
        "\u0c97\u0ccb\u0caa\u0cbe\u0cb2\u0caa\u0cc1\u0cb0"
    ],
    "name:mal_x_preferred":[
        "\u0d17\u0d4b\u0d2a\u0d3e\u0d32\u0d3e\u0d2a\u0d42\u0d7c"
    ],
    "name:mar_x_preferred":[
        "\u0917\u094b\u092a\u093e\u0933\u092a\u0942\u0930"
    ],
    "name:pan_x_preferred":[
        "\u0a17\u0a4b\u0a2a\u0a3e\u0a32\u0a3e\u0a2a\u0a41\u0a30"
    ],
    "name:tam_x_preferred":[
        "\u0b95\u0bcb\u0baa\u0bbe\u0bb2\u0baa\u0bc2\u0bb0\u0bcd"
    ],
    "name:tel_x_preferred":[
        "\u0c17\u0c4b\u0c2a\u0c3e\u0c32\u0c2a\u0c42\u0c30\u0c4d"
    ],
    "name:urd_x_preferred":[
        "\u06af\u0648\u067e\u0627\u0644 \u067e\u0648\u0631"
    ],
    "wof:name":"Gopalapur",
    "wof:placetype":"locality"
},
  "geometry": {"coordinates":[80.96758,27.42478],"type":"Point"}
}