{
  "type": "Feature",
  "properties": {
    "iso:country":"IN",
    "ks:ks_name":"Chambanthara",
    "ks:ks_pop":509,
    "ks:ks_type":"HABITATION",
    "name:eng_x_preferred":[
        "Chambanthara"
    ],
    "wof:name":"Chambanthara",
    "wof:placetype":"locality",
    "wof:population":509
},
  "geometry": {"coordinates":[76.345932,9.640211],"type":"Point"}
}