{
  "type": "Feature",
  "properties": {
    "iso:country":"IN",
    "ks:ks_name":"Vazarwadi",
    "ks:ks_pop":202,
    "ks:ks_type":"HABITATION",
    "name:eng_x_preferred":[
        "Vazarwadi"
    ],
    "wof:name":"Vazarwadi",
    "wof:placetype":"locality",
    "wof:population":202
},
  "geometry": {"coordinates":[73.86838899999999,15.847861],"type":"Point"}
}