{
  "type": "Feature",
  "properties": {
    "iso:country":"IN",
    "ks:ks_name":"Madpha Mal",
    "ks:ks_pop":392,
    "ks:ks_type":"HABITATION",
    "name:eng_x_preferred":[
        "Madpha Mal"
    ],
    "wof:name":"Madpha Mal",
    "wof:placetype":"locality",
    "wof:population":392
},
  "geometry": {"coordinates":[81.136681,22.56386],"type":"Point"}
}