{
  "type": "Feature",
  "properties": {
    "iso:country":"IN",
    "ks:ks_name":"Manakunnam",
    "ks:ks_pop":711,
    "ks:ks_type":"HABITATION",
    "ks:ks_uagg_main":0,
    "name:eng_x_preferred":[
        "Manakunnam"
    ],
    "wof:name":"Manakunnam",
    "wof:placetype":"neighbourhood",
    "wof:population":711
},
  "geometry": {"coordinates":[79.47376300000001,11.138231],"type":"Point"}
}