{
  "type": "Feature",
  "properties": {
    "gn:country":"IN",
    "gn:fcode":"PPL",
    "gn:pop":11444,
    "iso:country":"IN",
    "name:ben_x_preferred":[
        "\u09ae\u09c7\u0987\u09a8\u09a6\u09be\u09b0\u0997\u09bf"
    ],
    "name:bpy_x_preferred":[
        "\u09ae\u09c7\u0987\u09a8\u09a6\u09be\u09b0\u0997\u09bf"
    ],
    "name:bul_x_preferred":[
        "\u041c\u0430\u0438\u043d\u0434\u0430\u0440\u0433\u0438"
    ],
    "name:chi_x_preferred":[
        "\u8fc8\u6069\u8fbe\u5c14\u5409"
    ],
    "name:dut_x_preferred":[
        "Maindargi"
    ],
    "name:eng_x_preferred":[
        "Maindargi"
    ],
    "name:fre_x_preferred":[
        "Maindargi"
    ],
    "name:ita_x_preferred":[
        "Maindargi"
    ],
    "name:may_x_preferred":[
        "Maindargi"
    ],
    "name:nan_x_preferred":[
        "Maindargi"
    ],
    "name:new_x_preferred":[
        "\u092e\u0948\u0928\u094d\u0926\u0930\u094d\u0917\u0940"
    ],
    "name:por_x_preferred":[
        "Maindargi"
    ],
    "name:swe_x_preferred":[
        "Maindargi"
    ],
    "name:urd_x_preferred":[
        "\u0645\u06cc\u0646\u062f\u0627\u0631\u06af\u06cc"
    ],
    "name:vie_x_preferred":[
        "Maindargi"
    ],
    "qs:name":"Maindargi",
    "qs:photos_9r":0,
    "qs:photos_sr":0,
    "qs:pop_sr":"6",
    "wd:wordcount":173,
    "wof:name":"Maindargi",
    "wof:placetype":"locality",
    "wof:population":11444
},
  "geometry": {"coordinates":[76.29306,17.45758],"type":"Point"}
}