{
  "type": "Feature",
  "properties": {
    "gn:admin1_code":"13.0",
    "gn:admin2_code":"601.0",
    "gn:asciiname":"Amboori",
    "gn:country_code":"IN",
    "gn:dem":92,
    "gn:feature_class":"P",
    "gn:feature_code":"PPL",
    "gn:name":"Amboori",
    "gn:population":0,
    "gn:timezone":"Asia/Kolkata",
    "iso:country":"IN",
    "name:fas_x_preferred":[
        "\u0627\u0645\u0628\u0648\u0631\u06cc"
    ],
    "name:mal_x_preferred":[
        "\u0d05\u0d2e\u0d4d\u0d2a\u0d42\u0d30\u0d3f"
    ],
    "wof:name":"Amboori",
    "wof:placetype":"locality"
},
  "geometry": {"coordinates":[77.19,8.47],"type":"Point"}
}