{
  "type": "Feature",
  "properties": {
    "iso:country":"IN",
    "ks:ks_name":"Anakkunnu",
    "ks:ks_pop":1103,
    "ks:ks_type":"HABITATION",
    "name:eng_x_preferred":[
        "Anakkunnu"
    ],
    "wof:name":"Anakkunnu",
    "wof:placetype":"locality",
    "wof:population":1103
},
  "geometry": {"coordinates":[76.147398,11.607272],"type":"Point"}
}