{
  "type": "Feature",
  "properties": {
    "iso:country":"IN",
    "ks:ks_alt_nam":"B\u0101lidih",
    "ks:ks_name":"Balidih",
    "ks:ks_pop":432,
    "ks:ks_type":"VILLAGE",
    "name:eng_x_preferred":[
        "Balidih"
    ],
    "name:eng_x_variant":[
        "B\u0101lidih"
    ],
    "wof:name":"Balidih",
    "wof:placetype":"locality",
    "wof:population":432
},
  "geometry": {"coordinates":[85.912899,22.533688],"type":"Point"}
}