{
  "type": "Feature",
  "properties": {
    "iso:country":"IN",
    "ks:ks_name":"Gumabil",
    "ks:ks_pop":424,
    "ks:ks_type":"HABITATION",
    "name:eng_x_preferred":[
        "Gumabil"
    ],
    "wof:name":"Gumabil",
    "wof:placetype":"locality",
    "wof:population":424
},
  "geometry": {"coordinates":[90.123036,26.528645],"type":"Point"}
}