{
  "type": "Feature",
  "properties": {
    "gn:admin1_code":"23.0",
    "gn:admin2_code":"35.0",
    "gn:asciiname":"Kotli Dhadian",
    "gn:country_code":"IN",
    "gn:dem":241,
    "gn:feature_class":"P",
    "gn:feature_code":"PPL",
    "gn:name":"Kotli Dh\u0101di\u0101n",
    "gn:population":0,
    "gn:timezone":"Asia/Kolkata",
    "iso:country":"IN",
    "ks:ks_alt_nam":"Kotli Dh\u0101di\u0101n",
    "ks:ks_name":"Kotli Dhadian",
    "ks:ks_pop":910,
    "ks:ks_type":"VILLAGE",
    "ks:ks_uagg_main":0,
    "name:eng_x_preferred":[
        "Kotli Dhadian"
    ],
    "name:eng_x_variant":[
        "Kotli Dh\u0101di\u0101n"
    ],
    "wof:name":"Kotli Dhadian",
    "wof:placetype":"neighbourhood",
    "wof:population":910
},
  "geometry": {"coordinates":[75.039699,31.829882],"type":"Point"}
}