{
  "type": "Feature",
  "properties": {
    "iso:country":"IN",
    "ks:ks_alt_nam":"PIPARA DAHA",
    "ks:ks_name":"Pipara Daha",
    "ks:ks_pop":506,
    "ks:ks_type":"HABITATION",
    "name:eng_x_preferred":[
        "Pipara Daha"
    ],
    "wof:name":"Pipara Daha",
    "wof:placetype":"locality",
    "wof:population":506
},
  "geometry": {"coordinates":[85.17083700000001,24.509469],"type":"Point"}
}