{
  "type": "Feature",
  "properties": {
    "gn:country":"IN",
    "gn:fcode":"PPL",
    "gn:population":22486,
    "iso:country":"IN",
    "name:ara_x_preferred":[
        "\u062a\u0648\u0644\u0633\u0628\u0648\u0631"
    ],
    "name:ben_bn_x_preferred":[
        "\u09a4\u09c1\u09b2\u09b8\u09c0\u09aa\u09c1\u09b0"
    ],
    "name:ben_in_x_preferred":[
        "\u09a4\u09c1\u09b2\u09b8\u09c0\u09aa\u09c1\u09b0"
    ],
    "name:bho_x_preferred":[
        "\u0924\u0941\u0932\u0938\u0940\u092a\u0941\u0930"
    ],
    "name:bpy_x_preferred":[
        "\u09a4\u09c1\u09b2\u09b8\u09bf\u09aa\u09c1\u09b0"
    ],
    "name:ceb_x_preferred":[
        "Tuls\u012bpur"
    ],
    "name:deu_x_preferred":[
        "Tulsipur"
    ],
    "name:eng_x_preferred":[
        "Tulsipur"
    ],
    "name:fra_x_preferred":[
        "Tulsipur"
    ],
    "name:guj_x_preferred":[
        "\u0aa4\u0ac1\u0ab2\u0ab8\u0ac0\u0aaa\u0ac1\u0ab0"
    ],
    "name:hin_x_preferred":[
        "\u0924\u0941\u0932\u0938\u0940\u092a\u0941\u0930"
    ],
    "name:ita_x_preferred":[
        "Tulsipur"
    ],
    "name:jpn_x_preferred":[
        "\u30c8\u30a5\u30eb\u30b7\u30d7\u30eb"
    ],
    "name:kan_x_preferred":[
        "\u0ca4\u0cc1\u0cb3\u0cb8\u0cc0\u0caa\u0cc1\u0cb0"
    ],
    "name:mal_x_preferred":[
        "\u0d24\u0d41\u0d33\u0d38\u0d3f\u0d2a\u0d42\u0d7c"
    ],
    "name:mar_x_preferred":[
        "\u0924\u0941\u0933\u0936\u0940\u092a\u0942\u0930"
    ],
    "name:mlg_x_preferred":[
        "Tulsipur"
    ],
    "name:msa_x_preferred":[
        "Tulsipur"
    ],
    "name:nan_x_preferred":[
        "Tulsipur"
    ],
    "name:new_x_preferred":[
        "\u0924\u0941\u0932\u094d\u0938\u0940\u092a\u0941\u0930"
    ],
    "name:nld_x_preferred":[
        "Tulsipur"
    ],
    "name:pan_x_preferred":[
        "\u0a24\u0a41\u0a32\u0a38\u0a40\u0a2a\u0a41\u0a30"
    ],
    "name:pnb_x_preferred":[
        "\u062a\u0644\u0633\u06cc \u067e\u0648\u0631"
    ],
    "name:pol_x_preferred":[
        "Tulsipur"
    ],
    "name:por_x_preferred":[
        "Tulsipur"
    ],
    "name:swe_x_preferred":[
        "Tuls\u012bpur"
    ],
    "name:tam_x_preferred":[
        "\u0ba4\u0bc1\u0bb3\u0b9a\u0bbf\u0baa\u0bcd\u0baa\u0bc2\u0bb0\u0bcd"
    ],
    "name:tam_x_variant":[
        "\u0ba4\u0bc1\u0bb3\u0b9a\u0bbf\u0baa\u0bc2\u0bb0\u0bcd"
    ],
    "name:tel_x_preferred":[
        "\u0c24\u0c41\u0c32\u0c4d\u0c38\u0c3f\u0c2a\u0c42\u0c30\u0c4d"
    ],
    "name:urd_x_preferred":[
        "\u062a\u0644\u0633\u06cc \u067e\u0648\u0631"
    ],
    "name:vie_x_preferred":[
        "Tulsipur"
    ],
    "name:zho_x_preferred":[
        "\u56fe\u5c14\u897f\u666e\u5c14"
    ],
    "qs:name":"Tulsipur",
    "qs:name_adm0":"India",
    "qs:name_adm1":"Uttar Pradesh",
    "qs:photos_9r":0,
    "qs:photos_sr":0,
    "qs:placetype":"Town",
    "qs:pop_sr":"7",
    "wd:wordcount":745,
    "wof:name":"Tulsipur",
    "wof:placetype":"locality",
    "wof:population":22486
},
  "geometry": {"coordinates":[82.41652999999999,27.5337],"type":"Point"}
}