{
  "type": "Feature",
  "properties": {
    "gn:country":"IN",
    "gn:fcode":"PPL",
    "gn:pop":22486,
    "iso:country":"IN",
    "name:bho_x_preferred":[
        "\u0924\u0941\u0932\u0938\u0940\u092a\u0941\u0930"
    ],
    "name:bpy_x_preferred":[
        "\u09a4\u09c1\u09b2\u09b8\u09bf\u09aa\u09c1\u09b0"
    ],
    "name:ceb_x_preferred":[
        "Tuls\u012bpur"
    ],
    "name:deu_x_preferred":[
        "Tulsipur"
    ],
    "name:eng_x_preferred":[
        "Tulsipur"
    ],
    "name:fra_x_preferred":[
        "Tulsipur"
    ],
    "name:hin_x_preferred":[
        "\u0924\u0941\u0932\u0938\u0940\u092a\u0941\u0930"
    ],
    "name:ita_x_preferred":[
        "Tulsipur"
    ],
    "name:jpn_x_preferred":[
        "\u30c8\u30a5\u30eb\u30b7\u30d7\u30eb"
    ],
    "name:mlg_x_preferred":[
        "Tulsipur"
    ],
    "name:msa_x_preferred":[
        "Tulsipur"
    ],
    "name:nan_x_preferred":[
        "Tulsipur"
    ],
    "name:new_x_preferred":[
        "\u0924\u0941\u0932\u094d\u0938\u0940\u092a\u0941\u0930"
    ],
    "name:nld_x_preferred":[
        "Tulsipur"
    ],
    "name:pnb_x_preferred":[
        "\u062a\u0644\u0633\u06cc \u067e\u0648\u0631"
    ],
    "name:pol_x_preferred":[
        "Tulsipur"
    ],
    "name:por_x_preferred":[
        "Tulsipur"
    ],
    "name:swe_x_preferred":[
        "Tuls\u012bpur"
    ],
    "name:tam_x_preferred":[
        "\u0ba4\u0bc1\u0bb3\u0b9a\u0bbf\u0baa\u0bc2\u0bb0\u0bcd"
    ],
    "name:unk_x_variant":[
        "Tuls\u012bpur"
    ],
    "name:urd_x_preferred":[
        "\u062a\u0644\u0633\u06cc \u067e\u0648\u0631"
    ],
    "name:vie_x_preferred":[
        "Tulsipur"
    ],
    "name:zho_x_preferred":[
        "\u56fe\u5c14\u897f\u666e\u5c14"
    ],
    "qs:name":"Tulsipur",
    "qs:name_adm0":"India",
    "qs:name_adm1":"Uttar Pradesh",
    "qs:photos_9r":0,
    "qs:photos_sr":0,
    "qs:placetype":"Town",
    "qs:pop_sr":"7",
    "wd:wordcount":745,
    "wof:name":"Tulsipur",
    "wof:placetype":"locality",
    "wof:population":22486
},
  "geometry": {"coordinates":[82.41652999999999,27.5337],"type":"Point"}
}