{
  "type": "Feature",
  "properties": {
    "gn:country":"IN",
    "gn:fcode":"PPL",
    "gn:pop":22486,
    "iso:country":"IN",
    "name:unk_x_variant":[
        "Tuls\u012bpur"
    ],
    "qs:name":"Tulsipur",
    "qs:name_adm0":"India",
    "qs:name_adm1":"Uttar Pradesh",
    "qs:photos_9r":0,
    "qs:photos_sr":0,
    "qs:placetype":"Town",
    "qs:pop_sr":"7",
    "wd:wordcount":745,
    "wof:name":"Tulsipur",
    "wof:placetype":"locality",
    "wof:population":22486
},
  "geometry": {"coordinates":[82.41652999999999,27.5337],"type":"Point"}
}