{
  "type": "Feature",
  "properties": {
    "iso:country":"IN",
    "ks:ks_name":"6 Z",
    "ks:ks_pop":146,
    "ks:ks_type":"VILLAGE",
    "ks:ks_uagg_main":0,
    "name:eng_x_preferred":[
        "6 Z"
    ],
    "wof:name":"6 Z",
    "wof:placetype":"neighbourhood",
    "wof:population":146
},
  "geometry": {"coordinates":[73.868369,29.922436],"type":"Point"}
}