{
  "type": "Feature",
  "properties": {
    "gn:admin1_code":"12.0",
    "gn:admin2_code":"008",
    "gn:asciiname":"Lahikot",
    "gn:country_code":"IN",
    "gn:dem":1969,
    "gn:feature_class":"P",
    "gn:feature_code":"PPL",
    "gn:name":"Lahikot",
    "gn:population":0,
    "gn:timezone":"Asia/Kolkata",
    "iso:country":"IN",
    "wof:name":"Lahikot",
    "wof:placetype":"locality"
},
  "geometry": {"coordinates":[74.18233000000002,34.30915],"type":"Point"}
}