{
  "type": "Feature",
  "properties": {
    "gn:admin1_code":"38",
    "gn:admin2_code":"346.0",
    "gn:asciiname":"Adhauri",
    "gn:country_code":"IN",
    "gn:dem":248,
    "gn:feature_class":"P",
    "gn:feature_code":"PPL",
    "gn:name":"Adhauri",
    "gn:population":0,
    "gn:timezone":"Asia/Kolkata",
    "iso:country":"IN",
    "ks:ks_name":"Adhauri",
    "ks:ks_pop":735,
    "ks:ks_type":"VILLAGE",
    "name:eng_x_preferred":[
        "Adhauri"
    ],
    "wof:name":"Adhauri",
    "wof:placetype":"locality",
    "wof:population":735
},
  "geometry": {"coordinates":[83.517769,24.262522],"type":"Point"}
}