{
  "type": "Feature",
  "properties": {
    "gn:admin1_code":"16.0",
    "gn:admin2_code":"498",
    "gn:asciiname":"Dondvada",
    "gn:country_code":"IN",
    "gn:dem":327,
    "gn:feature_class":"P",
    "gn:feature_code":"PPL",
    "gn:name":"Dondv\u0101da",
    "gn:population":0,
    "gn:timezone":"Asia/Kolkata",
    "iso:country":"IN",
    "name:und_x_variant":[
        "Donovada",
        "Dondv\u0101da"
    ],
    "wof:name":"Dondvada",
    "wof:placetype":"locality"
},
  "geometry": {"coordinates":[74.84501,20.72208],"type":"Point"}
}