{
  "type": "Feature",
  "properties": {
    "iso:country":"IN",
    "ks:ks_name":"Girigoyyapalem",
    "ks:ks_pop":44,
    "ks:ks_type":"HABITATION",
    "name:eng_x_preferred":[
        "Girigoyyapalem"
    ],
    "wof:name":"Girigoyyapalem",
    "wof:placetype":"locality",
    "wof:population":44
},
  "geometry": {"coordinates":[82.50465800000001,17.970221],"type":"Point"}
}