{
  "type": "Feature",
  "properties": {
    "iso:country":"IN",
    "ks:ks_name":"Darbaripur",
    "ks:ks_pop":1438,
    "ks:ks_type":"VILLAGE",
    "ks:ks_uagg_main":0,
    "name:eng_x_preferred":[
        "Darbaripur"
    ],
    "wof:name":"Darbaripur",
    "wof:placetype":"neighbourhood",
    "wof:population":1438
},
  "geometry": {"coordinates":[77.01113100000001,28.391311],"type":"Point"}
}