{
  "type": "Feature",
  "properties": {
    "gn:admin1_code":"25.0",
    "gn:admin2_code":"604.0",
    "gn:asciiname":"Vadakal",
    "gn:country_code":"IN",
    "gn:dem":48,
    "gn:feature_class":"P",
    "gn:feature_code":"PPL",
    "gn:name":"Vadak\u0101l",
    "gn:population":0,
    "gn:timezone":"Asia/Kolkata",
    "iso:country":"IN",
    "ks:ks_alt_nam":"Vadak\u0101l",
    "ks:ks_name":"Vadakal",
    "ks:ks_type":"VILLAGE",
    "ks:ks_uagg_main":0,
    "name:eng_x_preferred":[
        "Vadakal"
    ],
    "name:eng_x_variant":[
        "Vadak\u0101l"
    ],
    "wof:name":"Vadakal",
    "wof:placetype":"neighbourhood"
},
  "geometry": {"coordinates":[79.934055,12.904214],"type":"Point"}
}