{
  "type": "Feature",
  "properties": {
    "iso:country":"IN",
    "ks:ks_name":"Srinivasapuram",
    "ks:ks_pop":5,
    "ks:ks_type":"HABITATION",
    "name:eng_x_preferred":[
        "Srinivasapuram"
    ],
    "wof:name":"Srinivasapuram",
    "wof:placetype":"locality",
    "wof:population":5
},
  "geometry": {"coordinates":[83.19475300000001,17.955639],"type":"Point"}
}