{
  "type": "Feature",
  "properties": {
    "iso:country":"IN",
    "ks:ks_alt_nam":"DHOBI TOLA",
    "ks:ks_name":"Dhobi Tola",
    "ks:ks_pop":402,
    "ks:ks_type":"HABITATION",
    "name:eng_x_preferred":[
        "Dhobi Tola"
    ],
    "wof:name":"Dhobi Tola",
    "wof:placetype":"locality",
    "wof:population":402
},
  "geometry": {"coordinates":[83.535661,25.020122],"type":"Point"}
}