{
  "type": "Feature",
  "properties": {
    "iso:country":"IN",
    "ks:ks_name":"Damerikia",
    "ks:ks_pop":427,
    "ks:ks_type":"VILLAGE",
    "name:eng_x_preferred":[
        "Damerikia"
    ],
    "wof:name":"Damerikia",
    "wof:placetype":"locality",
    "wof:population":427
},
  "geometry": {"coordinates":[84.053776,20.158537],"type":"Point"}
}