{
  "type": "Feature",
  "properties": {
    "iso:country":"IN",
    "ks:ks_name":"Hosanela",
    "ks:ks_pop":41,
    "ks:ks_type":"HABITATION",
    "name:eng_x_preferred":[
        "Hosanela"
    ],
    "wof:name":"Hosanela",
    "wof:placetype":"locality",
    "wof:population":41
},
  "geometry": {"coordinates":[75.33077299999999,13.381089],"type":"Point"}
}