{
  "type": "Feature",
  "properties": {
    "iso:country":"IN",
    "ks:ks_alt_nam":"GHODAK VASTI",
    "ks:ks_name":"Ghodak Vasti",
    "ks:ks_pop":102,
    "ks:ks_type":"HABITATION",
    "name:eng_x_preferred":[
        "Ghodak Vasti"
    ],
    "wof:name":"Ghodak Vasti",
    "wof:placetype":"locality",
    "wof:population":102
},
  "geometry": {"coordinates":[74.89058300000001,16.830617],"type":"Point"}
}