{
  "type": "Feature",
  "properties": {
    "iso:country":"IN",
    "ks:ks_name":"Palkhedi",
    "ks:ks_pop":662,
    "ks:ks_type":"VILLAGE",
    "name:eng_x_preferred":[
        "Palkhedi"
    ],
    "wof:name":"Palkhedi",
    "wof:placetype":"locality",
    "wof:population":662
},
  "geometry": {"coordinates":[75.752206,23.120589],"type":"Point"}
}