{
  "type": "Feature",
  "properties": {
    "iso:country":"IN",
    "ks:ks_name":"Kamsali Thanda",
    "ks:ks_pop":89,
    "ks:ks_type":"HABITATION",
    "name:eng_x_preferred":[
        "Kamsali Thanda"
    ],
    "wof:name":"Kamsali Thanda",
    "wof:placetype":"locality",
    "wof:population":89
},
  "geometry": {"coordinates":[80.124207,17.482793],"type":"Point"}
}