{
  "type": "Feature",
  "properties": {
    "gn:admin1_code":"38.0",
    "gn:admin2_code":"361",
    "gn:asciiname":"Gola",
    "gn:country_code":"IN",
    "gn:dem":342,
    "gn:feature_class":"P",
    "gn:feature_code":"PPL",
    "gn:name":"Gola",
    "gn:population":0,
    "gn:timezone":"Asia/Kolkata",
    "iso:country":"IN",
    "name:und_x_variant":[
        "Rol\u0101"
    ],
    "wof:name":"Gola",
    "wof:placetype":"locality"
},
  "geometry": {"coordinates":[85.71719,23.53354],"type":"Point"}
}