{
  "type": "Feature",
  "properties": {
    "iso:country":"IN",
    "ks:ks_name":"Champat Niwada",
    "ks:ks_pop":570,
    "ks:ks_type":"HABITATION",
    "name:eng_x_preferred":[
        "Champat Niwada"
    ],
    "wof:name":"Champat Niwada",
    "wof:placetype":"locality",
    "wof:population":570
},
  "geometry": {"coordinates":[79.985,26.793889],"type":"Point"}
}