{
  "type": "Feature",
  "properties": {
    "iso:country":"IN",
    "ks:ks_name":"Jasnath Nagar",
    "ks:ks_pop":768,
    "ks:ks_type":"HABITATION",
    "name:eng_x_preferred":[
        "Jasnath Nagar"
    ],
    "wof:name":"Jasnath Nagar",
    "wof:placetype":"locality",
    "wof:population":768
},
  "geometry": {"coordinates":[72.760051,26.335715],"type":"Point"}
}