{
  "type": "Feature",
  "properties": {
    "iso:country":"IN",
    "ks:ks_name":"Kotha Palle",
    "ks:ks_pop":52,
    "ks:ks_type":"HABITATION",
    "name:eng_x_preferred":[
        "Kotha Palle"
    ],
    "wof:name":"Kotha Palle",
    "wof:placetype":"locality",
    "wof:population":52
},
  "geometry": {"coordinates":[78.594916,13.99433],"type":"Point"}
}