{
  "type": "Feature",
  "properties": {
    "gn:admin1_code":"19.0",
    "gn:admin2_code":"570.0",
    "gn:asciiname":"Devarahalli",
    "gn:country_code":"IN",
    "gn:dem":964,
    "gn:feature_class":"P",
    "gn:feature_code":"PPL",
    "gn:name":"Devarahalli",
    "gn:population":0,
    "gn:timezone":"Asia/Kolkata",
    "iso:country":"IN",
    "ks:ks_name":"Devarahalli",
    "ks:ks_pop":198,
    "ks:ks_type":"VILLAGE",
    "name:eng_x_preferred":[
        "Devarahalli"
    ],
    "wof:name":"Devarahalli",
    "wof:placetype":"locality",
    "wof:population":198
},
  "geometry": {"coordinates":[75.619861,13.298536],"type":"Point"}
}