{
  "type": "Feature",
  "properties": {
    "iso:country":"IN",
    "ks:ks_name":"No.2 Balupara",
    "ks:ks_pop":136,
    "ks:ks_type":"HABITATION",
    "name:eng_x_preferred":[
        "No.2 Balupara"
    ],
    "wof:name":"No.2 Balupara",
    "wof:placetype":"locality",
    "wof:population":136
},
  "geometry": {"coordinates":[95.340495,27.53657],"type":"Point"}
}