{
  "type": "Feature",
  "properties": {
    "gn:admin1_code":"19",
    "gn:admin2_code":"563.0",
    "gn:asciiname":"Benpalgadde",
    "gn:country_code":"IN",
    "gn:dem":530,
    "gn:feature_class":"P",
    "gn:feature_code":"PPL",
    "gn:name":"Benp\u0101lgadde",
    "gn:population":0,
    "gn:timezone":"Asia/Kolkata",
    "iso:country":"IN",
    "ks:ks_name":"Benbalgaddde",
    "ks:ks_pop":22,
    "ks:ks_type":"HABITATION",
    "name:eng_x_preferred":[
        "Benbalgaddde"
    ],
    "name:eng_x_variant":[
        "Benpalgadde"
    ],
    "wof:name":"Benbalgaddde",
    "wof:placetype":"locality",
    "wof:population":22
},
  "geometry": {"coordinates":[74.73808,14.938468],"type":"Point"}
}