{
  "type": "Feature",
  "properties": {
    "iso:country":"IN",
    "ks:ks_name":"Chechpur",
    "ks:ks_pop":217,
    "ks:ks_type":"VILLAGE",
    "name:eng_x_preferred":[
        "Chechpur"
    ],
    "wof:name":"Chechpur",
    "wof:placetype":"locality",
    "wof:population":217
},
  "geometry": {"coordinates":[81.18138500000001,23.576625],"type":"Point"}
}