{
  "type": "Feature",
  "properties": {
    "gn:admin1_code":"34.0",
    "gn:admin2_code":"226.0",
    "gn:asciiname":"Khirodharpur",
    "gn:country_code":"IN",
    "gn:dem":49,
    "gn:feature_class":"P",
    "gn:feature_code":"PPL",
    "gn:name":"Khirodharpur",
    "gn:population":0,
    "gn:timezone":"Asia/Kolkata",
    "iso:country":"IN",
    "ks:ks_name":"Khirodharpur",
    "ks:ks_pop":888,
    "ks:ks_type":"VILLAGE",
    "ks:ks_uagg_main":0,
    "name:eng_x_preferred":[
        "Khirodharpur"
    ],
    "wof:name":"Khirodharpur",
    "wof:placetype":"neighbourhood",
    "wof:population":888
},
  "geometry": {"coordinates":[86.480661,25.279951],"type":"Point"}
}