{
  "type": "Feature",
  "properties": {
    "gn:admin1_code":"40",
    "gn:admin2_code":"540.0",
    "gn:asciiname":"Purushottamgudam",
    "gn:country_code":"IN",
    "gn:dem":163,
    "gn:feature_class":"P",
    "gn:feature_code":"PPL",
    "gn:name":"Purushottamgudam",
    "gn:population":0,
    "gn:timezone":"Asia/Kolkata",
    "iso:country":"IN",
    "name:eng_x_preferred":[
        "Purushottamgudam"
    ],
    "wof:name":"Purushottamgudam",
    "wof:placetype":"locality"
},
  "geometry": {"coordinates":[79.95035,17.40533],"type":"Point"}
}