{
  "type": "Feature",
  "properties": {
    "iso:country":"IN",
    "ks:ks_alt_nam":"BONI GANJ",
    "ks:ks_name":"Boni Ganj",
    "ks:ks_pop":300,
    "ks:ks_type":"HABITATION",
    "name:eng_x_preferred":[
        "Boni Ganj"
    ],
    "wof:name":"Boni Ganj",
    "wof:placetype":"locality",
    "wof:population":300
},
  "geometry": {"coordinates":[84.508002,25.00174],"type":"Point"}
}