{
  "type": "Feature",
  "properties": {
    "iso:country":"IN",
    "ks:ks_alt_nam":"DUMARIATAND",
    "ks:ks_name":"Dumariatand",
    "ks:ks_pop":339,
    "ks:ks_type":"HABITATION",
    "name:eng_x_preferred":[
        "Dumariatand"
    ],
    "wof:name":"Dumariatand",
    "wof:placetype":"locality",
    "wof:population":339
},
  "geometry": {"coordinates":[85.657512,24.204896],"type":"Point"}
}