{
  "type": "Feature",
  "properties": {
    "gn:admin1_code":"19.0",
    "gn:admin2_code":"567.0",
    "gn:asciiname":"Nelagondanahalli",
    "gn:country_code":"IN",
    "gn:dem":624,
    "gn:feature_class":"P",
    "gn:feature_code":"PPL",
    "gn:name":"Nelagondanahalli",
    "gn:population":0,
    "gn:timezone":"Asia/Kolkata",
    "iso:country":"IN",
    "ks:ks_name":"Nelagondanahalli",
    "ks:ks_pop":371,
    "ks:ks_type":"HABITATION",
    "name:eng_x_preferred":[
        "Nelagondanahalli"
    ],
    "wof:name":"Nelagondanahalli",
    "wof:placetype":"locality",
    "wof:population":371
},
  "geometry": {"coordinates":[76.05,14.641],"type":"Point"}
}