{
  "type": "Feature",
  "properties": {
    "gn:admin1_code":"21.0",
    "gn:admin2_code":"398.0",
    "gn:asciiname":"Gotanoputtu",
    "gn:country_code":"IN",
    "gn:dem":884,
    "gn:feature_class":"P",
    "gn:feature_code":"PPL",
    "gn:name":"Gotanoputtu",
    "gn:population":0,
    "gn:timezone":"Asia/Kolkata",
    "iso:country":"IN",
    "wof:name":"Gotanoputtu",
    "wof:placetype":"neighbourhood"
},
  "geometry": {"coordinates":[82.75842,18.64455],"type":"Point"}
}