{
  "type": "Feature",
  "properties": {
    "iso:country":"IN",
    "ks:ks_name":"Kapindapur",
    "ks:ks_pop":976,
    "ks:ks_type":"VILLAGE",
    "ks:ks_uagg_main":0,
    "name:eng_x_preferred":[
        "Kapindapur"
    ],
    "wof:name":"Kapindapur",
    "wof:placetype":"locality",
    "wof:population":976
},
  "geometry": {"coordinates":[88.44896,22.376592],"type":"Point"}
}