{
  "type": "Feature",
  "properties": {
    "iso:country":"IN",
    "ks:ks_name":"Pindra Kuli",
    "ks:ks_pop":317,
    "ks:ks_type":"VILLAGE",
    "name:eng_x_preferred":[
        "Pindra Kuli"
    ],
    "wof:name":"Pindra Kuli",
    "wof:placetype":"locality",
    "wof:population":317
},
  "geometry": {"coordinates":[86.947497,22.298137],"type":"Point"}
}