{
  "type": "Feature",
  "properties": {
    "iso:country":"IN",
    "ks:ks_name":"Musapadar",
    "ks:ks_pop":668,
    "ks:ks_type":"VILLAGE",
    "name:eng_x_preferred":[
        "Musapadar"
    ],
    "wof:name":"Musapadar",
    "wof:placetype":"locality",
    "wof:population":668
},
  "geometry": {"coordinates":[83.798179,19.405928],"type":"Point"}
}