{
  "type": "Feature",
  "properties": {
    "iso:country":"IN",
    "ks:ks_alt_nam":"SCARTED",
    "ks:ks_name":"Scarted",
    "ks:ks_pop":20,
    "ks:ks_type":"HABITATION",
    "name:eng_x_preferred":[
        "Scarted"
    ],
    "wof:name":"Scarted",
    "wof:placetype":"locality",
    "wof:population":20
},
  "geometry": {"coordinates":[74.071814,29.75775],"type":"Point"}
}