{
  "type": "Feature",
  "properties": {
    "iso:country":"IN",
    "ks:ks_name":"Adauri",
    "ks:ks_pop":4134,
    "ks:ks_type":"VILLAGE",
    "name:eng_x_preferred":[
        "Adauri"
    ],
    "wof:name":"Adauri",
    "wof:placetype":"locality",
    "wof:population":4134
},
  "geometry": {"coordinates":[85.28554800000001,26.631961],"type":"Point"}
}