{
  "type": "Feature",
  "properties": {
    "gn:admin1_code":"37.0",
    "gn:admin2_code":"407.0",
    "gn:asciiname":"Larbakki",
    "gn:country_code":"IN",
    "gn:dem":571,
    "gn:feature_class":"P",
    "gn:feature_code":"PPL",
    "gn:name":"Larbakki",
    "gn:population":0,
    "gn:timezone":"Asia/Kolkata",
    "iso:country":"IN",
    "ks:ks_name":"Larbakki",
    "ks:ks_type":"VILLAGE",
    "name:eng_x_preferred":[
        "Larbakki"
    ],
    "wof:name":"Larbakki",
    "wof:placetype":"locality"
},
  "geometry": {"coordinates":[81.175425,22.33941],"type":"Point"}
}