{
  "type": "Feature",
  "properties": {
    "iso:country":"IN",
    "ks:ks_alt_nam":"Bakarw\u0101la",
    "ks:ks_name":"Bakarwala",
    "ks:ks_type":"VILLAGE",
    "ks:ks_uagg_main":0,
    "name:eng_x_preferred":[
        "Bakarwala"
    ],
    "name:eng_x_variant":[
        "Bakarw\u0101la"
    ],
    "wof:name":"Bakarwala",
    "wof:placetype":"neighbourhood"
},
  "geometry": {"coordinates":[77.02011400000001,28.667803],"type":"Point"}
}