{
  "type": "Feature",
  "properties": {
    "iso:country":"IN",
    "ks:ks_name":"20 PTD",
    "ks:ks_pop":235,
    "ks:ks_type":"VILLAGE",
    "name:eng_x_preferred":[
        "20 PTD"
    ],
    "wof:name":"20 PTD",
    "wof:placetype":"locality",
    "wof:population":235
},
  "geometry": {"coordinates":[73.23845799999999,29.384325],"type":"Point"}
}