{
  "type": "Feature",
  "properties": {
    "iso:country":"IN",
    "ks:ks_name":"Umbasoo",
    "ks:ks_pop":155,
    "ks:ks_type":"HABITATION",
    "name:eng_x_preferred":[
        "Umbasoo"
    ],
    "wof:name":"Umbasoo",
    "wof:placetype":"locality",
    "wof:population":155
},
  "geometry": {"coordinates":[92.49677800000001,25.743006],"type":"Point"}
}