{
  "type": "Feature",
  "properties": {
    "iso:country":"IN",
    "ks:ks_name":"Vachattinkara",
    "ks:ks_pop":500,
    "ks:ks_type":"HABITATION",
    "name:eng_x_preferred":[
        "Vachattinkara"
    ],
    "wof:name":"Vachattinkara",
    "wof:placetype":"locality",
    "wof:population":500
},
  "geometry": {"coordinates":[76.896773,8.786936],"type":"Point"}
}