{
  "type": "Feature",
  "properties": {
    "gn:admin1_code":"34.0",
    "gn:admin2_code":"207.0",
    "gn:asciiname":"Rakbe Pauni",
    "gn:country_code":"IN",
    "gn:dem":53,
    "gn:feature_class":"P",
    "gn:feature_code":"PPL",
    "gn:name":"Rakbe Pauni",
    "gn:population":0,
    "gn:timezone":"Asia/Kolkata",
    "iso:country":"IN",
    "ks:ks_name":"Az Rakbe Pauni",
    "ks:ks_pop":1578,
    "ks:ks_type":"VILLAGE",
    "name:eng_x_preferred":[
        "Az Rakbe Pauni"
    ],
    "name:eng_x_variant":[
        "Rakbe Pauni"
    ],
    "wof:name":"Az Rakbe Pauni",
    "wof:placetype":"locality",
    "wof:population":1578
},
  "geometry": {"coordinates":[86.415859,26.235092],"type":"Point"}
}