{
  "type": "Feature",
  "properties": {
    "gn:admin1_code":"19.0",
    "gn:admin2_code":"570.0",
    "gn:asciiname":"Varkati",
    "gn:country_code":"IN",
    "gn:dem":692,
    "gn:feature_class":"P",
    "gn:feature_code":"PPL",
    "gn:name":"Varkati",
    "gn:population":0,
    "gn:timezone":"Asia/Kolkata",
    "iso:country":"IN",
    "ks:ks_name":"Varkate",
    "ks:ks_pop":184,
    "ks:ks_type":"VILLAGE",
    "name:eng_x_preferred":[
        "Varkate"
    ],
    "name:eng_x_variant":[
        "Varkati"
    ],
    "wof:name":"Varkate",
    "wof:placetype":"locality",
    "wof:population":184
},
  "geometry": {"coordinates":[75.51349999999999,13.570039],"type":"Point"}
}