{
  "type": "Feature",
  "properties": {
    "gn:admin1_code":"19.0",
    "gn:admin2_code":"584.0",
    "gn:asciiname":"Gantaganadoddi",
    "gn:country_code":"IN",
    "gn:dem":708,
    "gn:feature_class":"P",
    "gn:feature_code":"PPL",
    "gn:name":"Gantaganadoddi",
    "gn:population":0,
    "gn:timezone":"Asia/Kolkata",
    "iso:country":"IN",
    "ks:ks_name":"Gantakanadoddi",
    "ks:ks_pop":169,
    "ks:ks_type":"HABITATION",
    "ks:ks_uagg_main":0,
    "name:eng_x_preferred":[
        "Gantakanadoddi"
    ],
    "wof:name":"Gantakanadoddi",
    "wof:placetype":"neighbourhood",
    "wof:population":169
},
  "geometry": {"coordinates":[77.487893,12.740635],"type":"Point"}
}