{
  "type": "Feature",
  "properties": {
    "iso:country":"IN",
    "ks:ks_name":"6 MRN",
    "ks:ks_pop":51,
    "ks:ks_type":"VILLAGE",
    "name:eng_x_preferred":[
        "6 MRN"
    ],
    "wof:name":"6 MRN",
    "wof:placetype":"locality",
    "wof:population":51
},
  "geometry": {"coordinates":[75.32039399999999,29.245797],"type":"Point"}
}