{
  "type": "Feature",
  "properties": {
    "gn:admin1_code":"9.0",
    "gn:admin2_code":"472.0",
    "gn:asciiname":"Parthipura",
    "gn:country_code":"IN",
    "gn:dem":159,
    "gn:feature_class":"P",
    "gn:feature_code":"PPL",
    "gn:name":"Parthipura",
    "gn:population":0,
    "gn:timezone":"Asia/Kolkata",
    "iso:country":"IN",
    "wof:name":"Parthipura",
    "wof:placetype":"locality"
},
  "geometry": {"coordinates":[73.50306999999999,23.47029],"type":"Point"}
}