{
  "type": "Feature",
  "properties": {
    "iso:country":"IN",
    "ks:ks_name":"Rambhakta Para",
    "ks:ks_pop":341,
    "ks:ks_type":"HABITATION",
    "name:eng_x_preferred":[
        "Rambhakta Para"
    ],
    "wof:name":"Rambhakta Para",
    "wof:placetype":"locality",
    "wof:population":341
},
  "geometry": {"coordinates":[91.670979,23.720909],"type":"Point"}
}