{
  "type": "Feature",
  "properties": {
    "iso:country":"IN",
    "ks:ks_name":"Dhobenpada",
    "ks:ks_pop":370,
    "ks:ks_type":"HABITATION",
    "name:eng_x_preferred":[
        "Dhobenpada"
    ],
    "wof:name":"Dhobenpada",
    "wof:placetype":"locality",
    "wof:population":370
},
  "geometry": {"coordinates":[82.608739,19.661074],"type":"Point"}
}