{
  "type": "Feature",
  "properties": {
    "iso:country":"IN",
    "ks:ks_name":"Kollathankurichi",
    "ks:ks_pop":235,
    "ks:ks_type":"HABITATION",
    "name:eng_x_preferred":[
        "Kollathankurichi"
    ],
    "wof:name":"Kollathankurichi",
    "wof:placetype":"locality",
    "wof:population":235
},
  "geometry": {"coordinates":[79.32785199999999,11.466353],"type":"Point"}
}