{
  "type": "Feature",
  "properties": {
    "gn:admin1_code":"2.0",
    "gn:admin2_code":"553.0",
    "gn:asciiname":"Bichchalavandlapalle",
    "gn:country_code":"IN",
    "gn:dem":644,
    "gn:feature_class":"P",
    "gn:feature_code":"PPL",
    "gn:name":"Bichchalav\u0101ndlapalle",
    "gn:population":0,
    "gn:timezone":"Asia/Kolkata",
    "iso:country":"IN",
    "wof:name":"Bichchalavandlapalle",
    "wof:placetype":"neighbourhood"
},
  "geometry": {"coordinates":[78.10119,13.88826],"type":"Point"}
}