{
  "type": "Feature",
  "properties": {
    "iso:country":"IN",
    "ks:ks_name":"Kadamwadi",
    "ks:ks_pop":122,
    "ks:ks_type":"HABITATION",
    "name:eng_x_preferred":[
        "Kadamwadi"
    ],
    "wof:name":"Kadamwadi",
    "wof:placetype":"locality",
    "wof:population":122
},
  "geometry": {"coordinates":[73.609289,17.498889],"type":"Point"}
}