{
  "type": "Feature",
  "properties": {
    "iso:country":"IN",
    "ks:ks_name":"Fish Market Road",
    "ks:ks_pop":591,
    "ks:ks_type":"HABITATION",
    "name:eng_x_preferred":[
        "Fish Market Road"
    ],
    "wof:name":"Fish Market Road",
    "wof:placetype":"locality",
    "wof:population":591
},
  "geometry": {"coordinates":[76.114436,10.39844],"type":"Point"}
}