{
  "type": "Feature",
  "properties": {
    "iso:country":"IN",
    "ks:ks_alt_nam":"Kumbhar sahi",
    "ks:ks_name":"Kumbhar Sahi",
    "ks:ks_pop":209,
    "ks:ks_type":"HABITATION",
    "name:eng_x_preferred":[
        "Kumbhar Sahi"
    ],
    "wof:name":"Kumbhar Sahi",
    "wof:placetype":"locality",
    "wof:population":209
},
  "geometry": {"coordinates":[86.147362,22.266019],"type":"Point"}
}