{
  "type": "Feature",
  "properties": {
    "iso:country":"IN",
    "ks:ks_name":"Nischanta",
    "ks:ks_pop":970,
    "ks:ks_type":"VILLAGE",
    "ks:ks_uagg_main":0,
    "name:eng_x_preferred":[
        "Nischanta"
    ],
    "wof:name":"Nischanta",
    "wof:placetype":"neighbourhood",
    "wof:population":970
},
  "geometry": {"coordinates":[86.75724200000001,20.807981],"type":"Point"}
}