{
  "type": "Feature",
  "properties": {
    "iso:country":"IN",
    "ks:ks_name":"Palakkal",
    "ks:ks_pop":126,
    "ks:ks_type":"HABITATION",
    "name:eng_x_preferred":[
        "Palakkal"
    ],
    "wof:name":"Palakkal",
    "wof:placetype":"locality",
    "wof:population":126
},
  "geometry": {"coordinates":[76.949307,8.832978],"type":"Point"}
}