{
  "type": "Feature",
  "properties": {
    "gn:admin1_code":"11.0",
    "gn:admin2_code":"33.0",
    "gn:asciiname":"Jagrichauki",
    "gn:country_code":"IN",
    "gn:dem":2329,
    "gn:feature_class":"P",
    "gn:feature_code":"PPL",
    "gn:name":"Jagrichauki",
    "gn:population":0,
    "gn:timezone":"Asia/Kolkata",
    "iso:country":"IN",
    "wof:name":"Jagrichauki",
    "wof:placetype":"locality"
},
  "geometry": {"coordinates":[77.34855,31.22942],"type":"Point"}
}