{
  "type": "Feature",
  "properties": {
    "iso:country":"IN",
    "ks:ks_name":"Achhutadaspur",
    "ks:ks_pop":508,
    "ks:ks_type":"VILLAGE",
    "ks:ks_uagg_main":0,
    "name:eng_x_preferred":[
        "Achhutadaspur"
    ],
    "wof:name":"Achhutadaspur",
    "wof:placetype":"neighbourhood",
    "wof:population":508
},
  "geometry": {"coordinates":[86.43571900000001,20.21549],"type":"Point"}
}