{
  "type": "Feature",
  "properties": {
    "iso:country":"IN",
    "ks:ks_name":"Basdiha Pachhimtola",
    "ks:ks_pop":172,
    "ks:ks_type":"VILLAGE",
    "name:eng_x_preferred":[
        "Basdiha Pachhimtola"
    ],
    "wof:name":"Basdiha Pachhimtola",
    "wof:placetype":"locality",
    "wof:population":172
},
  "geometry": {"coordinates":[87.26194,24.589614],"type":"Point"}
}