{
  "type": "Feature",
  "properties": {
    "iso:country":"IN",
    "ks:ks_name":"Devakar",
    "ks:ks_pop":177,
    "ks:ks_type":"VILLAGE",
    "name:eng_x_preferred":[
        "Devakar"
    ],
    "wof:name":"Devakar",
    "wof:placetype":"locality",
    "wof:population":177
},
  "geometry": {"coordinates":[74.490312,14.858105],"type":"Point"}
}