{
  "type": "Feature",
  "properties": {
    "iso:country":"IN",
    "ks:ks_name":"Mallpada",
    "ks:ks_pop":31,
    "ks:ks_type":"HABITATION",
    "name:eng_x_preferred":[
        "Mallpada"
    ],
    "wof:name":"Mallpada",
    "wof:placetype":"locality",
    "wof:population":31
},
  "geometry": {"coordinates":[73.016543,19.966543],"type":"Point"}
}