{
  "type": "Feature",
  "properties": {
    "iso:country":"IN",
    "ks:ks_name":"Negadiya",
    "ks:ks_pop":281,
    "ks:ks_type":"VILLAGE",
    "name:eng_x_preferred":[
        "Negadiya"
    ],
    "wof:name":"Negadiya",
    "wof:placetype":"locality",
    "wof:population":281
},
  "geometry": {"coordinates":[74.541642,24.372172],"type":"Point"}
}