{
  "type": "Feature",
  "properties": {
    "gn:admin1_code":"16.0",
    "gn:admin2_code":"520.0",
    "gn:asciiname":"Ratwad",
    "gn:country_code":"IN",
    "gn:dem":61,
    "gn:feature_class":"P",
    "gn:feature_code":"PPL",
    "gn:name":"Ratwad",
    "gn:population":0,
    "gn:timezone":"Asia/Kolkata",
    "iso:country":"IN",
    "wof:name":"Ratwad",
    "wof:placetype":"locality"
},
  "geometry": {"coordinates":[73.23125999999998,18.35423],"type":"Point"}
}