{
  "type": "Feature",
  "properties": {
    "iso:country":"IN",
    "ks:ks_name":"Boravkarwasti",
    "ks:ks_pop":28,
    "ks:ks_type":"HABITATION",
    "ks:ks_uagg_main":0,
    "name:eng_x_preferred":[
        "Boravkarwasti"
    ],
    "wof:name":"Boravkarwasti",
    "wof:placetype":"neighbourhood",
    "wof:population":28
},
  "geometry": {"coordinates":[74.58526000000001,18.42447],"type":"Point"}
}