{
  "type": "Feature",
  "properties": {
    "iso:country":"IN",
    "ks:ks_name":"Daulatabad",
    "ks:ks_pop":1098,
    "ks:ks_type":"VILLAGE",
    "ks:ks_uagg_main":0,
    "name:eng_x_preferred":[
        "Daulatabad"
    ],
    "wof:name":"Daulatabad",
    "wof:placetype":"neighbourhood",
    "wof:population":1098
},
  "geometry": {"coordinates":[88.381677,24.143342],"type":"Point"}
}