{
  "type": "Feature",
  "properties": {
    "iso:country":"IN",
    "ks:ks_name":"Pandarapita",
    "ks:ks_pop":285,
    "ks:ks_type":"VILLAGE",
    "name:eng_x_preferred":[
        "Pandarapita"
    ],
    "wof:name":"Pandarapita",
    "wof:placetype":"locality",
    "wof:population":285
},
  "geometry": {"coordinates":[83.734393,20.522087],"type":"Point"}
}