{
  "type": "Feature",
  "properties": {
    "iso:country":"IN",
    "ks:ks_alt_nam":"kakkur thanda",
    "ks:ks_name":"Kakkur Thanda",
    "ks:ks_pop":915,
    "ks:ks_type":"HABITATION",
    "name:eng_x_preferred":[
        "Kakkur Thanda"
    ],
    "wof:name":"Kakkur Thanda",
    "wof:placetype":"locality",
    "wof:population":915
},
  "geometry": {"coordinates":[75.923762,15.158802],"type":"Point"}
}