{
  "type": "Feature",
  "properties": {
    "iso:country":"IN",
    "ks:ks_name":"Ramthi Forest",
    "ks:ks_pop":0,
    "ks:ks_type":"VILLAGE",
    "name:eng_x_preferred":[
        "Ramthi Forest"
    ],
    "wof:name":"Ramthi Forest",
    "wof:placetype":"locality",
    "wof:population":0
},
  "geometry": {"coordinates":[88.59934699999999,26.917509],"type":"Point"}
}