{
  "type": "Feature",
  "properties": {
    "iso:country":"IN",
    "ks:ks_alt_nam":"Nagathanpara colony",
    "ks:ks_name":"Nagathanpara Colony",
    "ks:ks_pop":450,
    "ks:ks_type":"HABITATION",
    "name:eng_x_preferred":[
        "Nagathanpara Colony"
    ],
    "wof:name":"Nagathanpara Colony",
    "wof:placetype":"locality",
    "wof:population":450
},
  "geometry": {"coordinates":[76.55889999999999,10.305202],"type":"Point"}
}