{
  "type": "Feature",
  "properties": {
    "iso:country":"IN",
    "ks:ks_name":"Naraikinaru",
    "ks:ks_pop":1519,
    "ks:ks_type":"HABITATION",
    "name:eng_x_preferred":[
        "Naraikinaru"
    ],
    "wof:name":"Naraikinaru",
    "wof:placetype":"locality",
    "wof:population":1519
},
  "geometry": {"coordinates":[78.391293,11.478635],"type":"Point"}
}