{
  "type": "Feature",
  "properties": {
    "gn:admin1_code":"16.0",
    "gn:admin2_code":"522",
    "gn:asciiname":"Karjat",
    "gn:country_code":"IN",
    "gn:dem":593,
    "gn:feature_class":"P",
    "gn:feature_code":"PPL",
    "gn:name":"Karjat",
    "gn:population":0,
    "gn:timezone":"Asia/Kolkata",
    "iso:country":"IN",
    "name:ben_x_preferred":[
        "\u0995\u09be\u09b0\u099c\u09be\u09a4"
    ],
    "name:bpy_x_preferred":[
        "\u0995\u09be\u09b0\u099c\u09be\u09a4"
    ],
    "name:ceb_x_preferred":[
        "Karjat"
    ],
    "name:ita_x_preferred":[
        "Karjat"
    ],
    "name:mar_x_preferred":[
        "\u0915\u0930\u094d\u091c\u0924"
    ],
    "name:mlg_x_preferred":[
        "Karjat"
    ],
    "name:msa_x_preferred":[
        "Karjat"
    ],
    "name:new_x_preferred":[
        "\u0915\u0930\u094d\u091c\u0924"
    ],
    "name:nld_x_preferred":[
        "Karjat"
    ],
    "name:ori_x_preferred":[
        "\u0b15\u0b3e\u0b30\u0b4d\u0b1c\u0b3e\u0b24"
    ],
    "name:pam_x_preferred":[
        "Karjat"
    ],
    "name:swe_x_preferred":[
        "Karjat"
    ],
    "name:tam_x_preferred":[
        "\u0b95\u0bb0\u0bcd\u0b9c\u0ba4\u0bcd"
    ],
    "name:urd_x_preferred":[
        "\u06a9\u0631\u062c\u062a"
    ],
    "name:vie_x_preferred":[
        "Karjat"
    ],
    "name:war_x_preferred":[
        "Karjat"
    ],
    "name:zho_x_preferred":[
        "\u5361\u5c14\u8d3e\u7279"
    ],
    "wof:name":"Karjat",
    "wof:placetype":"locality"
},
  "geometry": {"coordinates":[75.01051,18.55121],"type":"Point"}
}