{
  "type": "Feature",
  "properties": {
    "gn:admin1_code":"40.0",
    "gn:admin2_code":"535.0",
    "gn:asciiname":"Dandapalli",
    "gn:country_code":"IN",
    "gn:dem":564,
    "gn:feature_class":"P",
    "gn:feature_code":"PPL",
    "gn:name":"Dandapalli",
    "gn:population":0,
    "gn:timezone":"Asia/Kolkata",
    "iso:country":"IN",
    "wof:name":"Dandapalli",
    "wof:placetype":"locality"
},
  "geometry": {"coordinates":[78.57313000000001,17.82906000000001],"type":"Point"}
}