{
  "type": "Feature",
  "properties": {
    "gn:admin1_code":"19.0",
    "gn:admin2_code":"573.0",
    "gn:asciiname":"Avverahalli",
    "gn:country_code":"IN",
    "gn:dem":732,
    "gn:feature_class":"P",
    "gn:feature_code":"PPL",
    "gn:name":"Avverahalli",
    "gn:population":0,
    "gn:timezone":"Asia/Kolkata",
    "iso:country":"IN",
    "wof:name":"Avverahalli",
    "wof:placetype":"locality"
},
  "geometry": {"coordinates":[76.80982,12.5163],"type":"Point"}
}