{
  "type": "Feature",
  "properties": {
    "gn:admin1_code":"34.0",
    "gn:admin2_code":"203.0",
    "gn:asciiname":"Pokharia Babu",
    "gn:country_code":"IN",
    "gn:dem":79,
    "gn:feature_class":"P",
    "gn:feature_code":"PPL",
    "gn:name":"Pokharia B\u0101bu",
    "gn:population":0,
    "gn:timezone":"Asia/Kolkata",
    "iso:country":"IN",
    "name:und_x_variant":[
        "Pokharia B\u0101bu",
        "Ekrahi\u0101"
    ],
    "wof:name":"Pokharia Babu",
    "wof:placetype":"neighbourhood"
},
  "geometry": {"coordinates":[84.4738,26.89205],"type":"Point"}
}