{
  "type": "Feature",
  "properties": {
    "iso:country":"IN",
    "ks:ks_name":"Dhakundi Jamboni",
    "ks:ks_pop":329,
    "ks:ks_type":"HABITATION",
    "name:eng_x_preferred":[
        "Dhakundi Jamboni"
    ],
    "wof:name":"Dhakundi Jamboni",
    "wof:placetype":"locality",
    "wof:population":329
},
  "geometry": {"coordinates":[86.903333,22.181],"type":"Point"}
}