{
  "type": "Feature",
  "properties": {
    "iso:country":"IN",
    "ks:ks_name":"Teghari",
    "ks:ks_pop":1059,
    "ks:ks_type":"VILLAGE",
    "ks:ks_uagg_main":0,
    "name:eng_x_preferred":[
        "Teghari"
    ],
    "wof:name":"Teghari",
    "wof:placetype":"locality",
    "wof:population":1059
},
  "geometry": {"coordinates":[87.807806,22.88028],"type":"Point"}
}