{
  "type": "Feature",
  "properties": {
    "iso:country":"IN",
    "ks:ks_name":"Bariya Na Muvada",
    "ks:ks_pop":246,
    "ks:ks_type":"HABITATION",
    "name:eng_x_preferred":[
        "Bariya Na Muvada"
    ],
    "wof:name":"Bariya Na Muvada",
    "wof:placetype":"locality",
    "wof:population":246
},
  "geometry": {"coordinates":[73.44152800000001,23.403306],"type":"Point"}
}