{
  "type": "Feature",
  "properties": {
    "iso:country":"IN",
    "ks:ks_name":"Sarwani",
    "ks:ks_pop":1184,
    "ks:ks_type":"HABITATION",
    "name:eng_x_preferred":[
        "Sarwani"
    ],
    "wof:name":"Sarwani",
    "wof:placetype":"locality",
    "wof:population":1184
},
  "geometry": {"coordinates":[74.14166899999999,24.117319],"type":"Point"}
}