{
  "type": "Feature",
  "properties": {
    "iso:country":"IN",
    "ks:ks_name":"Alampur Tangia",
    "ks:ks_pop":116,
    "ks:ks_type":"VILLAGE",
    "name:eng_x_preferred":[
        "Alampur Tangia"
    ],
    "wof:name":"Alampur Tangia",
    "wof:placetype":"locality",
    "wof:population":116
},
  "geometry": {"coordinates":[79.192342,24.228754],"type":"Point"}
}