{
  "type": "Feature",
  "properties": {
    "gn:admin1_code":"24.0",
    "gn:admin2_code":"116",
    "gn:asciiname":"Ahor",
    "gn:country_code":"IN",
    "gn:dem":187,
    "gn:feature_class":"P",
    "gn:feature_code":"PPL",
    "gn:name":"Ahor",
    "gn:population":0,
    "gn:timezone":"Asia/Kolkata",
    "iso:country":"IN",
    "name:cat_x_preferred":[
        "Ahor"
    ],
    "name:ceb_x_preferred":[
        "Ahor"
    ],
    "name:fas_x_preferred":[
        "\u0627\u0647\u0648\u0631"
    ],
    "name:hin_x_preferred":[
        "\u0906\u0939\u094b\u0930"
    ],
    "name:swe_x_preferred":[
        "Ahor"
    ],
    "wof:name":"Ahor",
    "wof:placetype":"locality"
},
  "geometry": {"coordinates":[72.78038000000002,25.3687],"type":"Point"}
}