{
  "type": "Feature",
  "properties": {
    "iso:country":"IN",
    "ks:ks_alt_nam":"Mannarpuram AD Colony",
    "ks:ks_name":"Mannarpuram Ad Colony",
    "ks:ks_pop":210,
    "ks:ks_type":"HABITATION",
    "ks:ks_uagg_main":0,
    "name:eng_x_preferred":[
        "Mannarpuram Ad Colony"
    ],
    "wof:name":"Mannarpuram Ad Colony",
    "wof:placetype":"neighbourhood",
    "wof:population":210
},
  "geometry": {"coordinates":[77.807429,8.367204],"type":"Point"}
}