{
  "type": "Feature",
  "properties": {
    "iso:country":"IN",
    "ks:ks_name":"Balahara",
    "ks:ks_pop":6,
    "ks:ks_type":"VILLAGE",
    "name:eng_x_preferred":[
        "Balahara"
    ],
    "wof:name":"Balahara",
    "wof:placetype":"locality",
    "wof:population":6
},
  "geometry": {"coordinates":[81.44806699999999,24.815297],"type":"Point"}
}