{
  "type": "Feature",
  "properties": {
    "iso:country":"IN",
    "ks:ks_name":"Siddegowdanahalli",
    "ks:ks_pop":9,
    "ks:ks_type":"VILLAGE",
    "name:eng_x_preferred":[
        "Siddegowdanahalli"
    ],
    "wof:name":"Siddegowdanahalli",
    "wof:placetype":"locality",
    "wof:population":9
},
  "geometry": {"coordinates":[76.09124799999999,13.695022],"type":"Point"}
}