{
  "type": "Feature",
  "properties": {
    "iso:country":"IN",
    "ks:ks_name":"Siriapal",
    "ks:ks_pop":1178,
    "ks:ks_type":"VILLAGE",
    "name:eng_x_preferred":[
        "Siriapal"
    ],
    "wof:name":"Siriapal",
    "wof:placetype":"locality",
    "wof:population":1178
},
  "geometry": {"coordinates":[86.403705,21.401583],"type":"Point"}
}