{
  "type": "Feature",
  "properties": {
    "gn:admin1_code":"35",
    "gn:admin2_code":"461.0",
    "gn:asciiname":"Paladigwar",
    "gn:country_code":"IN",
    "gn:dem":764,
    "gn:feature_class":"P",
    "gn:feature_code":"PPL",
    "gn:name":"Pal\u0101digw\u0101r",
    "gn:population":0,
    "gn:timezone":"Asia/Kolkata",
    "iso:country":"IN",
    "name:und_x_variant":[
        "Pal\u0101digw\u0101r",
        "Nang\u0101tola"
    ],
    "wof:name":"Paladigwar",
    "wof:placetype":"locality"
},
  "geometry": {"coordinates":[81.31545,22.92208],"type":"Point"}
}