{
  "type": "Feature",
  "properties": {
    "iso:country":"IN",
    "ks:ks_name":"Chenoor",
    "ks:ks_pop":487,
    "ks:ks_type":"HABITATION",
    "name:eng_x_preferred":[
        "Chenoor"
    ],
    "wof:name":"Chenoor",
    "wof:placetype":"locality",
    "wof:population":487
},
  "geometry": {"coordinates":[78.53633499999999,12.395893],"type":"Point"}
}