{
  "type": "Feature",
  "properties": {
    "gn:admin1_code":"11",
    "gn:admin2_code":"23.0",
    "gn:asciiname":"Man Masi",
    "gn:country_code":"IN",
    "gn:dem":1585,
    "gn:feature_class":"P",
    "gn:feature_code":"PPL",
    "gn:name":"Man Masi",
    "gn:population":0,
    "gn:timezone":"Asia/Kolkata",
    "iso:country":"IN",
    "wof:name":"Man Masi",
    "wof:placetype":"locality"
},
  "geometry": {"coordinates":[76.1113,32.32223],"type":"Point"}
}