{
  "type": "Feature",
  "properties": {
    "gn:admin1_code":"13.0",
    "gn:admin2_code":"591.0",
    "gn:asciiname":"Eramala",
    "gn:country_code":"IN",
    "gn:dem":17,
    "gn:feature_class":"P",
    "gn:feature_code":"PPL",
    "gn:name":"Er\u0101mala",
    "gn:population":0,
    "gn:timezone":"Asia/Kolkata",
    "iso:country":"IN",
    "ks:ks_name":"Eramala",
    "ks:ks_pop":1892,
    "ks:ks_type":"VILLAGE",
    "name:eng_x_preferred":[
        "Eramala"
    ],
    "name:mal_x_preferred":[
        "\u0d0f\u0d31\u0d3e\u0d2e\u0d32 \u0d17\u0d4d\u0d30\u0d3e\u0d2e\u0d2a\u0d1e\u0d4d\u0d1a\u0d3e\u0d2f\u0d24\u0d4d\u0d24\u0d4d"
    ],
    "wof:name":"Eramala",
    "wof:placetype":"locality",
    "wof:population":1892
},
  "geometry": {"coordinates":[75.590205,11.67963],"type":"Point"}
}