{
  "type": "Feature",
  "properties": {
    "iso:country":"IN",
    "ks:ks_name":"Kurtab Dewtali",
    "ks:ks_pop":1083,
    "ks:ks_type":"VILLAGE",
    "name:eng_x_preferred":[
        "Kurtab Dewtali"
    ],
    "wof:name":"Kurtab Dewtali",
    "wof:placetype":"locality",
    "wof:population":1083
},
  "geometry": {"coordinates":[92.285149,24.800808],"type":"Point"}
}