{
  "type": "Feature",
  "properties": {
    "iso:country":"IN",
    "ks:ks_name":"Gondari",
    "ks:ks_pop":150,
    "ks:ks_type":"HABITATION",
    "name:eng_x_preferred":[
        "Gondari"
    ],
    "wof:name":"Gondari",
    "wof:placetype":"locality",
    "wof:population":150
},
  "geometry": {"coordinates":[81.628579,25.336031],"type":"Point"}
}