{
  "type": "Feature",
  "properties": {
    "iso:country":"IN",
    "ks:ks_name":"Konetigattu",
    "ks:ks_pop":217,
    "ks:ks_type":"HABITATION",
    "name:eng_x_preferred":[
        "Konetigattu"
    ],
    "wof:name":"Konetigattu",
    "wof:placetype":"locality",
    "wof:population":217
},
  "geometry": {"coordinates":[81.820768,16.546707],"type":"Point"}
}