{
  "type": "Feature",
  "properties": {
    "gn:admin1_code":"12",
    "gn:admin2_code":"20.0",
    "gn:asciiname":"Barhma Dhar",
    "gn:country_code":"IN",
    "gn:dem":2305,
    "gn:feature_class":"P",
    "gn:feature_code":"PPL",
    "gn:name":"Barhm\u0101 Dh\u0101r",
    "gn:population":0,
    "gn:timezone":"Asia/Kolkata",
    "iso:country":"IN",
    "wof:name":"Barhma Dhar",
    "wof:placetype":"locality"
},
  "geometry": {"coordinates":[74.87791,33.41164000000001],"type":"Point"}
}