{
  "type": "Feature",
  "properties": {
    "iso:country":"IN",
    "ks:ks_name":"Chitwakonha",
    "ks:ks_pop":13,
    "ks:ks_type":"HABITATION",
    "name:eng_x_preferred":[
        "Chitwakonha"
    ],
    "wof:name":"Chitwakonha",
    "wof:placetype":"locality",
    "wof:population":13
},
  "geometry": {"coordinates":[80.919237,20.862421],"type":"Point"}
}