{
  "type": "Feature",
  "properties": {
    "gn:admin1_code":"34.0",
    "gn:admin2_code":"221.0",
    "gn:asciiname":"Sajanpur",
    "gn:country_code":"IN",
    "gn:dem":52,
    "gn:feature_class":"P",
    "gn:feature_code":"PPL",
    "gn:name":"S\u0101janpur",
    "gn:population":0,
    "gn:timezone":"Asia/Kolkata",
    "iso:country":"IN",
    "ks:ks_name":"Sajanpur",
    "ks:ks_pop":1292,
    "ks:ks_type":"VILLAGE",
    "name:eng_x_preferred":[
        "Sajanpur"
    ],
    "wof:name":"Sajanpur",
    "wof:placetype":"locality",
    "wof:population":1292
},
  "geometry": {"coordinates":[85.826358,25.956339],"type":"Point"}
}