{
  "type": "Feature",
  "properties": {
    "gn:admin1_code":"19.0",
    "gn:admin2_code":"575.0",
    "gn:asciiname":"Alankaru",
    "gn:country_code":"IN",
    "gn:dem":113,
    "gn:feature_class":"P",
    "gn:feature_code":"PPLL",
    "gn:name":"Alank\u0101ru",
    "gn:population":0,
    "gn:timezone":"Asia/Kolkata",
    "iso:country":"IN",
    "ks:ks_alt_nam":"Alank\u0101ru",
    "ks:ks_name":"Alankaru",
    "ks:ks_pop":3787,
    "ks:ks_type":"VILLAGE",
    "name:eng_x_preferred":[
        "Alankaru"
    ],
    "name:eng_x_variant":[
        "Alank\u0101ru"
    ],
    "wof:name":"Alankaru",
    "wof:placetype":"locality",
    "wof:population":3787
},
  "geometry": {"coordinates":[75.346446,12.765353],"type":"Point"}
}