{
  "type": "Feature",
  "properties": {
    "iso:country":"IN",
    "ks:ks_name":"Guriginjala Palle",
    "ks:ks_pop":56,
    "ks:ks_type":"HABITATION",
    "name:eng_x_preferred":[
        "Guriginjala Palle"
    ],
    "wof:name":"Guriginjala Palle",
    "wof:placetype":"locality",
    "wof:population":56
},
  "geometry": {"coordinates":[78.318926,13.707071],"type":"Point"}
}