{
  "type": "Feature",
  "properties": {
    "gn:admin1_code":"36",
    "gn:admin2_code":"193.0",
    "gn:asciiname":"Nadauli",
    "gn:country_code":"IN",
    "gn:dem":72,
    "gn:feature_class":"P",
    "gn:feature_code":"PPL",
    "gn:name":"Nadaul\u012b",
    "gn:population":0,
    "gn:timezone":"Asia/Kolkata",
    "iso:country":"IN",
    "ks:ks_alt_nam":"Nadaul\u012b",
    "ks:ks_name":"Nadauli",
    "ks:ks_pop":1233,
    "ks:ks_type":"VILLAGE",
    "ks:ks_uagg_main":0,
    "name:eng_x_preferred":[
        "Nadauli"
    ],
    "name:eng_x_variant":[
        "Nadaul\u012b"
    ],
    "wof:name":"Nadauli",
    "wof:placetype":"neighbourhood",
    "wof:population":1233
},
  "geometry": {"coordinates":[83.772693,25.893259],"type":"Point"}
}