{
  "type": "Feature",
  "properties": {
    "gn:admin1_code":"36.0",
    "gn:admin2_code":"154.0",
    "gn:asciiname":"Ram Sala",
    "gn:country_code":"IN",
    "gn:dem":137,
    "gn:feature_class":"P",
    "gn:feature_code":"PPL",
    "gn:name":"R\u0101m S\u0101la",
    "gn:population":0,
    "gn:timezone":"Asia/Kolkata",
    "iso:country":"IN",
    "wof:name":"Ram Sala",
    "wof:placetype":"locality"
},
  "geometry": {"coordinates":[80.74942,27.44754],"type":"Point"}
}