{
  "type": "Feature",
  "properties": {
    "iso:country":"IN",
    "ks:ks_name":"Kavalagi",
    "ks:ks_pop":50,
    "ks:ks_type":"HABITATION",
    "name:eng_x_preferred":[
        "Kavalagi"
    ],
    "wof:name":"Kavalagi",
    "wof:placetype":"locality",
    "wof:population":50
},
  "geometry": {"coordinates":[74.934957,14.91415],"type":"Point"}
}