{
  "type": "Feature",
  "properties": {
    "iso:country":"IN",
    "ks:ks_name":"Pandripani",
    "ks:ks_pop":176,
    "ks:ks_type":"HABITATION",
    "name:eng_x_preferred":[
        "Pandripani"
    ],
    "wof:name":"Pandripani",
    "wof:placetype":"locality",
    "wof:population":176
},
  "geometry": {"coordinates":[82.235596,22.889148],"type":"Point"}
}