{
  "type": "Feature",
  "properties": {
    "iso:country":"IN",
    "ks:ks_name":"Uthamagoundanur",
    "ks:ks_pop":478,
    "ks:ks_type":"HABITATION",
    "name:eng_x_preferred":[
        "Uthamagoundanur"
    ],
    "wof:name":"Uthamagoundanur",
    "wof:placetype":"locality",
    "wof:population":478
},
  "geometry": {"coordinates":[78.247134,10.646407],"type":"Point"}
}