{
  "type": "Feature",
  "properties": {
    "iso:country":"IN",
    "ks:ks_name":"Beda Ka Bagar",
    "ks:ks_pop":76,
    "ks:ks_type":"VILLAGE",
    "name:eng_x_preferred":[
        "Beda Ka Bagar"
    ],
    "wof:name":"Beda Ka Bagar",
    "wof:placetype":"locality",
    "wof:population":76
},
  "geometry": {"coordinates":[78.851152,30.087509],"type":"Point"}
}