{
  "type": "Feature",
  "properties": {
    "gn:admin1_code":"25.0",
    "gn:admin2_code":"606.0",
    "gn:asciiname":"Vellankuppam",
    "gn:country_code":"IN",
    "gn:dem":715,
    "gn:feature_class":"P",
    "gn:feature_code":"PPL",
    "gn:name":"Vellankuppam",
    "gn:population":0,
    "gn:timezone":"Asia/Kolkata",
    "iso:country":"IN",
    "ks:ks_name":"Vilangkuppam",
    "ks:ks_pop":120,
    "ks:ks_type":"HABITATION",
    "name:eng_x_preferred":[
        "Vilangkuppam"
    ],
    "name:eng_x_variant":[
        "Vellankuppam"
    ],
    "wof:name":"Vilangkuppam",
    "wof:placetype":"locality",
    "wof:population":120
},
  "geometry": {"coordinates":[78.910522,12.626863],"type":"Point"}
}