{
  "type": "Feature",
  "properties": {
    "gn:admin1_code":"36",
    "gn:admin2_code":"196.0",
    "gn:asciiname":"Bataspur",
    "gn:country_code":"IN",
    "gn:dem":341,
    "gn:feature_class":"P",
    "gn:feature_code":"PPL",
    "gn:name":"Bat\u0101spur",
    "gn:population":0,
    "gn:timezone":"Asia/Kolkata",
    "iso:country":"IN",
    "ks:ks_alt_nam":"Bat\u0101spur",
    "ks:ks_name":"Bataspur",
    "ks:ks_type":"VILLAGE",
    "name:eng_x_preferred":[
        "Bataspur"
    ],
    "name:eng_x_variant":[
        "Bat\u0101spur"
    ],
    "wof:name":"Bataspur",
    "wof:placetype":"locality"
},
  "geometry": {"coordinates":[83.364628,24.799701],"type":"Point"}
}