{
  "type": "Feature",
  "properties": {
    "iso:country":"IN",
    "ks:ks_name":"Sanawal Harijantola",
    "ks:ks_pop":335,
    "ks:ks_type":"HABITATION",
    "name:eng_x_preferred":[
        "Sanawal Harijantola"
    ],
    "wof:name":"Sanawal Harijantola",
    "wof:placetype":"locality",
    "wof:population":335
},
  "geometry": {"coordinates":[83.36724700000001,24.036598],"type":"Point"}
}