{
  "type": "Feature",
  "properties": {
    "iso:country":"IN",
    "ks:ks_alt_nam":"Thumkal padi",
    "ks:ks_name":"Thumkal Padi",
    "ks:ks_pop":921,
    "ks:ks_type":"HABITATION",
    "name:eng_x_preferred":[
        "Thumkal Padi"
    ],
    "wof:name":"Thumkal Padi",
    "wof:placetype":"locality",
    "wof:population":921
},
  "geometry": {"coordinates":[76.805795,9.362657],"type":"Point"}
}