{
  "type": "Feature",
  "properties": {
    "iso:country":"IN",
    "ks:ks_name":"Nibia Khera",
    "ks:ks_pop":945,
    "ks:ks_type":"HABITATION",
    "name:eng_x_preferred":[
        "Nibia Khera"
    ],
    "wof:name":"Nibia Khera",
    "wof:placetype":"locality",
    "wof:population":945
},
  "geometry": {"coordinates":[80.271389,26.101111],"type":"Point"}
}