{
  "type": "Feature",
  "properties": {
    "gn:admin1_code":"12.0",
    "gn:admin2_code":"18.0",
    "gn:asciiname":"Sananan",
    "gn:country_code":"IN",
    "gn:dem":2701,
    "gn:feature_class":"P",
    "gn:feature_code":"PPL",
    "gn:name":"San\u0101nan",
    "gn:population":0,
    "gn:timezone":"Asia/Kolkata",
    "iso:country":"IN",
    "wof:name":"Sananan",
    "wof:placetype":"locality"
},
  "geometry": {"coordinates":[75.93436,33.31912],"type":"Point"}
}