{
  "type": "Feature",
  "properties": {
    "iso:country":"IN",
    "ks:ks_name":"Balabhadrapur",
    "ks:ks_pop":263,
    "ks:ks_type":"VILLAGE",
    "name:eng_x_preferred":[
        "Balabhadrapur"
    ],
    "wof:name":"Balabhadrapur",
    "wof:placetype":"locality",
    "wof:population":263
},
  "geometry": {"coordinates":[86.387373,20.122283],"type":"Point"}
}