{
  "type": "Feature",
  "properties": {
    "gn:admin1_code":"11.0",
    "gn:admin2_code":"27.0",
    "gn:asciiname":"Hej",
    "gn:country_code":"IN",
    "gn:dem":2856,
    "gn:feature_class":"P",
    "gn:feature_code":"PPL",
    "gn:name":"Hej",
    "gn:population":0,
    "gn:timezone":"Asia/Kolkata",
    "iso:country":"IN",
    "name:swe_x_preferred":[
        "Hej"
    ],
    "wof:name":"Hej",
    "wof:placetype":"locality"
},
  "geometry": {"coordinates":[77.11999,31.45444],"type":"Point"}
}