{
  "type": "Feature",
  "properties": {
    "gn:admin1_code":"13.0",
    "gn:admin2_code":"593.0",
    "gn:asciiname":"Vandithavalam",
    "gn:country_code":"IN",
    "gn:dem":156,
    "gn:feature_class":"P",
    "gn:feature_code":"PPL",
    "gn:name":"Vandithavalam",
    "gn:population":0,
    "gn:timezone":"Asia/Kolkata",
    "iso:country":"IN",
    "name:ara_x_preferred":[
        "\u0641\u0627\u0646\u062f\u064a\u062b\u0627\u0641\u0627\u0644\u0627\u0645"
    ],
    "name:fas_x_preferred":[
        "\u0648\u0646\u062f\u06cc\u062a\u0647\u0648\u0644\u0645"
    ],
    "name:mal_x_preferred":[
        "\u0d35\u0d23\u0d4d\u0d1f\u0d3f\u0d24\u0d4d\u0d24\u0d3e\u0d35\u0d33\u0d02"
    ],
    "wof:name":"Vandithavalam",
    "wof:placetype":"locality"
},
  "geometry": {"coordinates":[76.74259000000001,10.65898],"type":"Point"}
}