{
  "type": "Feature",
  "properties": {
    "iso:country":"IN",
    "ks:ks_name":"Samda",
    "ks:ks_type":"VILLAGE",
    "name:eng_x_preferred":[
        "Samda"
    ],
    "wof:name":"Samda",
    "wof:placetype":"locality"
},
  "geometry": {"coordinates":[87.51286500000001,25.400711],"type":"Point"}
}