{
  "type": "Feature",
  "properties": {
    "iso:country":"IN",
    "ks:ks_name":"Bada Bagaicha",
    "ks:ks_pop":542,
    "ks:ks_type":"HABITATION",
    "name:eng_x_preferred":[
        "Bada Bagaicha"
    ],
    "wof:name":"Bada Bagaicha",
    "wof:placetype":"locality",
    "wof:population":542
},
  "geometry": {"coordinates":[82.300252,25.235924],"type":"Point"}
}