{
  "type": "Feature",
  "properties": {
    "iso:country":"IN",
    "ks:ks_name":"Kerrakachhar",
    "ks:ks_pop":54,
    "ks:ks_type":"HABITATION",
    "name:eng_x_preferred":[
        "Kerrakachhar"
    ],
    "wof:name":"Kerrakachhar",
    "wof:placetype":"locality",
    "wof:population":54
},
  "geometry": {"coordinates":[84.115235,22.598259],"type":"Point"}
}