{
  "type": "Feature",
  "properties": {
    "iso:country":"IN",
    "ks:ks_name":"Attalipparambu",
    "ks:ks_pop":702,
    "ks:ks_type":"HABITATION",
    "name:eng_x_preferred":[
        "Attalipparambu"
    ],
    "wof:name":"Attalipparambu",
    "wof:placetype":"locality",
    "wof:population":702
},
  "geometry": {"coordinates":[76.11919899999999,10.930335],"type":"Point"}
}