{
  "type": "Feature",
  "properties": {
    "iso:country":"IN",
    "ks:ks_name":"Nagankas",
    "ks:ks_pop":349,
    "ks:ks_type":"HABITATION",
    "name:eng_x_preferred":[
        "Nagankas"
    ],
    "wof:name":"Nagankas",
    "wof:placetype":"locality",
    "wof:population":349
},
  "geometry": {"coordinates":[72.765114,20.072561],"type":"Point"}
}