{
  "type": "Feature",
  "properties": {
    "iso:country":"IN",
    "ks:ks_name":"Mahes Khapuri",
    "ks:ks_pop":216,
    "ks:ks_type":"VILLAGE",
    "name:eng_x_preferred":[
        "Mahes Khapuri"
    ],
    "wof:name":"Mahes Khapuri",
    "wof:placetype":"locality",
    "wof:population":216
},
  "geometry": {"coordinates":[86.816928,23.308642],"type":"Point"}
}