{
  "type": "Feature",
  "properties": {
    "iso:country":"IN",
    "ks:ks_name":"Patelpara",
    "ks:ks_pop":344,
    "ks:ks_type":"HABITATION",
    "name:eng_x_preferred":[
        "Patelpara"
    ],
    "wof:name":"Patelpara",
    "wof:placetype":"locality",
    "wof:population":344
},
  "geometry": {"coordinates":[81.34523299999999,19.017414],"type":"Point"}
}