{
  "type": "Feature",
  "properties": {
    "iso:country":"IN",
    "ks:ks_name":"Ghugharmal",
    "ks:ks_pop":215,
    "ks:ks_type":"HABITATION",
    "name:eng_x_preferred":[
        "Ghugharmal"
    ],
    "wof:name":"Ghugharmal",
    "wof:placetype":"locality",
    "wof:population":215
},
  "geometry": {"coordinates":[72.894459,24.147664],"type":"Point"}
}