{
  "type": "Feature",
  "properties": {
    "iso:country":"IN",
    "ks:ks_name":"Shidhpura",
    "ks:ks_pop":185,
    "ks:ks_type":"HABITATION",
    "name:eng_x_preferred":[
        "Shidhpura"
    ],
    "wof:name":"Shidhpura",
    "wof:placetype":"locality",
    "wof:population":185
},
  "geometry": {"coordinates":[78.56655600000001,24.811863],"type":"Point"}
}