{
  "type": "Feature",
  "properties": {
    "iso:country":"IN",
    "ks:ks_name":"Bungkulung",
    "ks:ks_pop":898,
    "ks:ks_type":"HABITATION",
    "name:eng_x_preferred":[
        "Bungkulung"
    ],
    "wof:name":"Bungkulung",
    "wof:placetype":"locality",
    "wof:population":898
},
  "geometry": {"coordinates":[88.224812,26.875434],"type":"Point"}
}