{
  "type": "Feature",
  "properties": {
    "iso:country":"IN",
    "ks:ks_name":"Chhotashalgeria",
    "ks:ks_pop":107,
    "ks:ks_type":"VILLAGE",
    "ks:ks_uagg_main":0,
    "name:eng_x_preferred":[
        "Chhotashalgeria"
    ],
    "wof:name":"Chhotashalgeria",
    "wof:placetype":"neighbourhood",
    "wof:population":107
},
  "geometry": {"coordinates":[87.177469,22.875123],"type":"Point"}
}