{
  "type": "Feature",
  "properties": {
    "iso:country":"IN",
    "ks:ks_name":"Bedapada",
    "ks:ks_pop":475,
    "ks:ks_type":"VILLAGE",
    "name:eng_x_preferred":[
        "Bedapada"
    ],
    "wof:name":"Bedapada",
    "wof:placetype":"locality",
    "wof:population":475
},
  "geometry": {"coordinates":[86.12701199999999,20.806178],"type":"Point"}
}