{
  "type": "Feature",
  "properties": {
    "iso:country":"IN",
    "ks:ks_name":"Tanr Par",
    "ks:ks_pop":253,
    "ks:ks_type":"HABITATION",
    "name:eng_x_preferred":[
        "Tanr Par"
    ],
    "wof:name":"Tanr Par",
    "wof:placetype":"locality",
    "wof:population":253
},
  "geometry": {"coordinates":[85.538774,25.151026],"type":"Point"}
}