{
  "type": "Feature",
  "properties": {
    "gn:admin1_code":"2.0",
    "gn:admin2_code":"552.0",
    "gn:asciiname":"Krishnapuram",
    "gn:country_code":"IN",
    "gn:dem":358,
    "gn:feature_class":"P",
    "gn:feature_code":"PPL",
    "gn:name":"Krishn\u0101puram",
    "gn:population":0,
    "gn:timezone":"Asia/Kolkata",
    "iso:country":"IN",
    "wof:name":"Krishnapuram",
    "wof:placetype":"locality"
},
  "geometry": {"coordinates":[77.76999000000001,15.64517],"type":"Point"}
}