{
  "type": "Feature",
  "properties": {
    "gn:admin1_code":"19.0",
    "gn:admin2_code":"583.0",
    "gn:asciiname":"Somatanhalli",
    "gn:country_code":"IN",
    "gn:dem":883,
    "gn:feature_class":"P",
    "gn:feature_code":"PPL",
    "gn:name":"Somatanhalli",
    "gn:population":0,
    "gn:timezone":"Asia/Kolkata",
    "iso:country":"IN",
    "wof:name":"Somatanhalli",
    "wof:placetype":"locality"
},
  "geometry": {"coordinates":[77.76860000000001,13.1694],"type":"Point"}
}