{
  "type": "Feature",
  "properties": {
    "iso:country":"IN",
    "ks:ks_name":"18 RJD",
    "ks:ks_pop":210,
    "ks:ks_type":"VILLAGE",
    "name:eng_x_preferred":[
        "18 RJD"
    ],
    "wof:name":"18 RJD",
    "wof:placetype":"locality",
    "wof:population":210
},
  "geometry": {"coordinates":[73.02204999999999,28.741876],"type":"Point"}
}