{
  "type": "Feature",
  "properties": {
    "iso:country":"IN",
    "ks:ks_name":"Surkumi",
    "ks:ks_pop":959,
    "ks:ks_type":"VILLAGE",
    "name:eng_x_preferred":[
        "Surkumi"
    ],
    "wof:name":"Surkumi",
    "wof:placetype":"locality",
    "wof:population":959
},
  "geometry": {"coordinates":[84.188047,23.64755],"type":"Point"}
}