{
  "type": "Feature",
  "properties": {
    "gn:admin1_code":"19.0",
    "gn:admin2_code":"574.0",
    "gn:asciiname":"Ibbane",
    "gn:country_code":"IN",
    "gn:dem":990,
    "gn:feature_class":"P",
    "gn:feature_code":"PPL",
    "gn:name":"Ibb\u0101ne",
    "gn:population":0,
    "gn:timezone":"Asia/Kolkata",
    "iso:country":"IN",
    "wof:name":"Ibbane",
    "wof:placetype":"locality"
},
  "geometry": {"coordinates":[76.05261,13.0703],"type":"Point"}
}