{
  "type": "Feature",
  "properties": {
    "iso:country":"IN",
    "ks:ks_name":"Sonar Tola",
    "ks:ks_pop":230,
    "ks:ks_type":"HABITATION",
    "name:eng_x_preferred":[
        "Sonar Tola"
    ],
    "wof:name":"Sonar Tola",
    "wof:placetype":"locality",
    "wof:population":230
},
  "geometry": {"coordinates":[84.743324,25.871555],"type":"Point"}
}