{
  "type": "Feature",
  "properties": {
    "iso:country":"IN",
    "ks:ks_name":"Hogrehalli",
    "ks:ks_pop":1863,
    "ks:ks_type":"VILLAGE",
    "name:eng_x_preferred":[
        "Hogrehalli"
    ],
    "wof:name":"Hogrehalli",
    "wof:placetype":"locality",
    "wof:population":1863
},
  "geometry": {"coordinates":[75.888161,13.584195],"type":"Point"}
}