{
  "type": "Feature",
  "properties": {
    "iso:country":"IN",
    "ks:ks_name":"Pulinkunnu",
    "ks:ks_pop":16795,
    "ks:ks_type":"VILLAGE",
    "name:eng_x_preferred":[
        "Pulinkunnu"
    ],
    "wof:name":"Pulinkunnu",
    "wof:placetype":"locality",
    "wof:population":16795
},
  "geometry": {"coordinates":[76.40912,9.483648],"type":"Point"}
}