{
  "type": "Feature",
  "properties": {
    "iso:country":"IN",
    "ks:ks_name":"Damodarpur",
    "ks:ks_pop":1110,
    "ks:ks_type":"VILLAGE",
    "ks:ks_uagg_main":0,
    "name:eng_x_preferred":[
        "Damodarpur"
    ],
    "wof:name":"Damodarpur",
    "wof:placetype":"neighbourhood",
    "wof:population":1110
},
  "geometry": {"coordinates":[87.44932799999999,21.999202],"type":"Point"}
}