{
  "type": "Feature",
  "properties": {
    "iso:country":"IN",
    "ks:ks_alt_nam":"J\u0101mdih",
    "ks:ks_name":"Jamdih",
    "ks:ks_type":"VILLAGE",
    "name:eng_x_preferred":[
        "Jamdih"
    ],
    "name:eng_x_variant":[
        "J\u0101mdih"
    ],
    "wof:name":"Jamdih",
    "wof:placetype":"locality"
},
  "geometry": {"coordinates":[84.549909,23.645166],"type":"Point"}
}