{
  "type": "Feature",
  "properties": {
    "iso:country":"IN",
    "ks:ks_name":"Jharboni",
    "ks:ks_pop":2534,
    "ks:ks_type":"VILLAGE",
    "ks:ks_uagg_main":0,
    "name:eng_x_preferred":[
        "Jharboni"
    ],
    "wof:name":"Jharboni",
    "wof:placetype":"neighbourhood",
    "wof:population":2534
},
  "geometry": {"coordinates":[87.30793,22.846205],"type":"Point"}
}