{
  "type": "Feature",
  "properties": {
    "iso:country":"IN",
    "ks:ks_name":"Akhasar",
    "ks:ks_pop":931,
    "ks:ks_type":"VILLAGE",
    "name:eng_x_preferred":[
        "Akhasar"
    ],
    "wof:name":"Akhasar",
    "wof:placetype":"locality",
    "wof:population":931
},
  "geometry": {"coordinates":[73.188061,27.181867],"type":"Point"}
}