{
  "type": "Feature",
  "properties": {
    "iso:country":"IN",
    "ks:ks_name":"Palgabhan",
    "ks:ks_pop":2576,
    "ks:ks_type":"VILLAGE",
    "name:eng_x_preferred":[
        "Palgabhan"
    ],
    "wof:name":"Palgabhan",
    "wof:placetype":"locality",
    "wof:population":2576
},
  "geometry": {"coordinates":[73.312134,20.826459],"type":"Point"}
}