{
  "type": "Feature",
  "properties": {
    "iso:country":"IN",
    "ks:ks_alt_nam":"Posari theru",
    "ks:ks_name":"Posari Theru",
    "ks:ks_pop":130,
    "ks:ks_type":"HABITATION",
    "name:eng_x_preferred":[
        "Posari Theru"
    ],
    "wof:name":"Posari Theru",
    "wof:placetype":"locality",
    "wof:population":130
},
  "geometry": {"coordinates":[78.884753,10.810753],"type":"Point"}
}