{
  "type": "Feature",
  "properties": {
    "iso:country":"IN",
    "ks:ks_name":"Kuduvaiyur",
    "ks:ks_pop":101,
    "ks:ks_type":"HABITATION",
    "name:eng_x_preferred":[
        "Kuduvaiyur"
    ],
    "wof:name":"Kuduvaiyur",
    "wof:placetype":"locality",
    "wof:population":101
},
  "geometry": {"coordinates":[79.10243800000001,10.037432],"type":"Point"}
}