{
  "type": "Feature",
  "properties": {
    "gn:country":"IN",
    "gn:fcode":"PPL",
    "gn:population":0,
    "iso:country":"IN",
    "name:ara_x_preferred":[
        "\u0625\u0646\u062f\u0631\u064a\u0634\u0627\u0645"
    ],
    "name:ben_bn_x_preferred":[
        "\u0987\u09a6\u09cd\u09b0\u09c7\u09b6\u09be\u09ae"
    ],
    "name:ben_in_x_preferred":[
        "\u0987\u09a6\u09cd\u09b0\u09c7\u09b6\u09be\u09ae"
    ],
    "name:guj_x_preferred":[
        "\u0a87\u0aa8\u0acd\u0aa6\u0acd\u0ab0\u0ab6\u0ac7\u0aae"
    ],
    "name:hin_x_preferred":[
        "\u0907\u0902\u0926\u094d\u0930\u0947\u0936\u092e"
    ],
    "name:kan_x_preferred":[
        "\u0c87\u0c82\u0ca6\u0ccd\u0cb0\u0cc7\u0cb6\u0cae\u0ccd"
    ],
    "name:mal_x_preferred":[
        "\u0d07\u0d28\u0d4d\u0d26\u0d4d\u0d30\u0d47\u0d37\u0d02"
    ],
    "name:mar_x_preferred":[
        "\u0907\u0902\u0926\u094d\u0930\u0947\u0936\u092e"
    ],
    "name:pan_x_preferred":[
        "\u0a07\u0a70\u0a26\u0a30\u0a47\u0a36\u0a2e"
    ],
    "name:tam_x_preferred":[
        "\u0b87\u0ba8\u0bcd\u0ba4\u0bbf\u0bb0\u0bc7\u0bb7\u0bae\u0bcd"
    ],
    "name:tel_x_preferred":[
        "\u0c07\u0c02\u0c26\u0c4d\u0c30\u0c46\u0c37\u0c3e\u0c2e\u0c4d"
    ],
    "name:urd_x_preferred":[
        "\u0627\u0646\u062f\u0631\u06cc\u0634\u0645"
    ],
    "qs:name":"Indresham",
    "qs:name_adm0":"India",
    "qs:name_adm1":"Andhra Pradesh",
    "qs:photos":1,
    "qs:photos_1k":1,
    "qs:photos_9k":1,
    "qs:photos_9r":1,
    "qs:photos_all":1,
    "qs:photos_sr":1,
    "qs:placetype":"Suburb",
    "qs:pop_sr":"0",
    "wof:name":"Indresham",
    "wof:placetype":"neighbourhood",
    "wof:population":0
},
  "geometry": {"coordinates":[78.26111,17.56667],"type":"Point"}
}