{
  "type": "Feature",
  "properties": {
    "iso:country":"IN",
    "ks:ks_alt_nam":"EVR Nagar",
    "ks:ks_name":"Evr Nagar",
    "ks:ks_pop":102,
    "ks:ks_type":"HABITATION",
    "name:eng_x_preferred":[
        "Evr Nagar"
    ],
    "wof:name":"Evr Nagar",
    "wof:placetype":"locality",
    "wof:population":102
},
  "geometry": {"coordinates":[79.105591,10.208013],"type":"Point"}
}