{
  "type": "Feature",
  "properties": {
    "gn:admin1_code":"37",
    "gn:admin2_code":"409.0",
    "gn:asciiname":"Pitora",
    "gn:country_code":"IN",
    "gn:dem":285,
    "gn:feature_class":"P",
    "gn:feature_code":"PPL",
    "gn:name":"Pitora",
    "gn:population":0,
    "gn:timezone":"Asia/Kolkata",
    "iso:country":"IN",
    "wof:name":"Pitora",
    "wof:placetype":"locality"
},
  "geometry": {"coordinates":[81.40916,21.39022000000001],"type":"Point"}
}