{
  "type": "Feature",
  "properties": {
    "iso:country":"IN",
    "ks:ks_name":"Bamjakachhar",
    "ks:ks_pop":125,
    "ks:ks_type":"HABITATION",
    "name:eng_x_preferred":[
        "Bamjakachhar"
    ],
    "wof:name":"Bamjakachhar",
    "wof:placetype":"locality",
    "wof:population":125
},
  "geometry": {"coordinates":[83.704987,22.126283],"type":"Point"}
}