{
  "type": "Feature",
  "properties": {
    "gn:admin1_code":"37",
    "gn:admin2_code":"410.0",
    "gn:asciiname":"Bagar",
    "gn:country_code":"IN",
    "gn:dem":244,
    "gn:feature_class":"P",
    "gn:feature_code":"PPL",
    "gn:name":"Bag\u0101r",
    "gn:population":0,
    "gn:timezone":"Asia/Kolkata",
    "iso:country":"IN",
    "name:ceb_x_preferred":[
        "Bagar"
    ],
    "name:slv_x_preferred":[
        "Bagar"
    ],
    "name:swe_x_preferred":[
        "Bagar"
    ],
    "wof:name":"Bagar",
    "wof:placetype":"locality"
},
  "geometry": {"coordinates":[82.37826,21.56584],"type":"Point"}
}