{
  "type": "Feature",
  "properties": {
    "gn:admin1_code":"11.0",
    "gn:admin2_code":"32.0",
    "gn:asciiname":"Boral",
    "gn:country_code":"IN",
    "gn:dem":1527,
    "gn:feature_class":"P",
    "gn:feature_code":"PPL",
    "gn:name":"Bor\u0101l",
    "gn:population":0,
    "gn:timezone":"Asia/Kolkata",
    "iso:country":"IN",
    "wof:name":"Boral",
    "wof:placetype":"locality"
},
  "geometry": {"coordinates":[77.56986999999999,30.73294000000001],"type":"Point"}
}