{
  "type": "Feature",
  "properties": {
    "gn:admin1_code":"36",
    "gn:admin2_code":"178.0",
    "gn:asciiname":"Chamrauti Bibi Talia",
    "gn:country_code":"IN",
    "gn:dem":94,
    "gn:feature_class":"P",
    "gn:feature_code":"PPL",
    "gn:name":"Chamrauti B\u012bbi Talia",
    "gn:population":0,
    "gn:timezone":"Asia/Kolkata",
    "iso:country":"IN",
    "wof:name":"Chamrauti Bibi Talia",
    "wof:placetype":"locality"
},
  "geometry": {"coordinates":[82.60505999999999,26.38129],"type":"Point"}
}