{
  "type": "Feature",
  "properties": {
    "iso:country":"IN",
    "ks:ks_name":"Khedi Manawar",
    "ks:ks_pop":232,
    "ks:ks_type":"HABITATION",
    "name:eng_x_preferred":[
        "Khedi Manawar"
    ],
    "wof:name":"Khedi Manawar",
    "wof:placetype":"locality",
    "wof:population":232
},
  "geometry": {"coordinates":[75.09741099999999,22.20939],"type":"Point"}
}