{
  "type": "Feature",
  "properties": {
    "iso:country":"IN",
    "ks:ks_name":"Sodat",
    "ks:ks_pop":490,
    "ks:ks_type":"VILLAGE",
    "ks:ks_uagg_main":0,
    "name:eng_x_preferred":[
        "Sodat"
    ],
    "wof:name":"Sodat",
    "wof:placetype":"neighbourhood",
    "wof:population":490
},
  "geometry": {"coordinates":[73.730306,22.051722],"type":"Point"}
}