{
  "type": "Feature",
  "properties": {
    "gn:admin1_code":"40.0",
    "gn:admin2_code":"534.0",
    "gn:asciiname":"Mayedam Banda",
    "gn:country_code":"IN",
    "gn:dem":185,
    "gn:feature_class":"P",
    "gn:feature_code":"PPL",
    "gn:name":"Mayedam Banda",
    "gn:population":0,
    "gn:timezone":"Asia/Kolkata",
    "iso:country":"IN",
    "wof:name":"Mayedam Banda",
    "wof:placetype":"locality"
},
  "geometry": {"coordinates":[79.60179000000002,18.54763],"type":"Point"}
}