{
  "type": "Feature",
  "properties": {
    "gn:admin1_code":"28.0",
    "gn:admin2_code":"327.0",
    "gn:asciiname":"Pringtam",
    "gn:country_code":"IN",
    "gn:dem":584,
    "gn:feature_class":"P",
    "gn:feature_code":"PPL",
    "gn:name":"Pringt\u0101m",
    "gn:population":0,
    "gn:timezone":"Asia/Kolkata",
    "iso:country":"IN",
    "wof:name":"Pringtam",
    "wof:placetype":"locality"
},
  "geometry": {"coordinates":[88.50354,27.04618],"type":"Point"}
}