{
  "type": "Feature",
  "properties": {
    "gn:admin1_code":"36",
    "gn:admin2_code":"194.0",
    "gn:asciiname":"Bhatauli",
    "gn:country_code":"IN",
    "gn:dem":85,
    "gn:feature_class":"P",
    "gn:feature_code":"PPL",
    "gn:name":"Bhatauli",
    "gn:population":0,
    "gn:timezone":"Asia/Kolkata",
    "iso:country":"IN",
    "wof:name":"Bhatauli",
    "wof:placetype":"locality"
},
  "geometry": {"coordinates":[82.67693,25.64237],"type":"Point"}
}