{
  "type": "Feature",
  "properties": {
    "gn:admin1_code":"36.0",
    "gn:admin2_code":"150.0",
    "gn:asciiname":"Kair Shadi",
    "gn:country_code":"IN",
    "gn:dem":165,
    "gn:feature_class":"P",
    "gn:feature_code":"PPL",
    "gn:name":"Kair Sh\u0101di",
    "gn:population":0,
    "gn:timezone":"Asia/Kolkata",
    "iso:country":"IN",
    "ks:ks_alt_nam":"Kair Sh\u0101di",
    "ks:ks_name":"Kair Shadi",
    "ks:ks_type":"VILLAGE",
    "name:eng_x_preferred":[
        "Kair Shadi"
    ],
    "name:eng_x_variant":[
        "Kair Sh\u0101di"
    ],
    "wof:name":"Kair Shadi",
    "wof:placetype":"locality"
},
  "geometry": {"coordinates":[79.59377000000001,28.221549],"type":"Point"}
}