{
  "type": "Feature",
  "properties": {
    "iso:country":"IN",
    "ks:ks_name":"Edathuruthy Boundary",
    "ks:ks_pop":320,
    "ks:ks_type":"HABITATION",
    "name:eng_x_preferred":[
        "Edathuruthy Boundary"
    ],
    "wof:name":"Edathuruthy Boundary",
    "wof:placetype":"locality",
    "wof:population":320
},
  "geometry": {"coordinates":[76.121201,10.350032],"type":"Point"}
}