{
  "type": "Feature",
  "properties": {
    "gn:admin1_code":"19.0",
    "gn:admin2_code":"573.0",
    "gn:asciiname":"Habbadamaranahalli",
    "gn:country_code":"IN",
    "gn:dem":727,
    "gn:feature_class":"P",
    "gn:feature_code":"PPL",
    "gn:name":"Habbadam\u0101ranahalli",
    "gn:population":0,
    "gn:timezone":"Asia/Kolkata",
    "iso:country":"IN",
    "wof:name":"Habbadamaranahalli",
    "wof:placetype":"locality"
},
  "geometry": {"coordinates":[76.83763,12.63677],"type":"Point"}
}