{
  "type": "Feature",
  "properties": {
    "iso:country":"IN",
    "ks:ks_name":"Uttarasasan",
    "ks:ks_pop":1432,
    "ks:ks_type":"VILLAGE",
    "ks:ks_uagg_main":0,
    "name:eng_x_preferred":[
        "Uttarasasan"
    ],
    "qs:name":"Uttarasasan",
    "qs:name_adm0":"India",
    "qs:name_adm1":"Orissa",
    "qs:photos":29,
    "qs:photos_1k":6,
    "qs:photos_9k":1,
    "qs:photos_9r":2,
    "qs:photos_all":29,
    "qs:photos_sr":2,
    "qs:placetype":"Town",
    "qs:pop_sr":"0",
    "wof:name":"Uttarasasan",
    "wof:placetype":"neighbourhood",
    "wof:population":1432
},
  "geometry": {"coordinates":[85.855479,20.196591],"type":"Point"}
}