{
  "type": "Feature",
  "properties": {
    "iso:country":"IN",
    "ks:ks_name":"Tholka",
    "ks:ks_pop":213,
    "ks:ks_type":"VILLAGE",
    "name:eng_x_preferred":[
        "Tholka"
    ],
    "wof:name":"Tholka",
    "wof:placetype":"locality",
    "wof:population":213
},
  "geometry": {"coordinates":[85.87079900000001,22.649048],"type":"Point"}
}