{
  "type": "Feature",
  "properties": {
    "iso:country":"IN",
    "ks:ks_name":"Malaichiwadi",
    "ks:ks_pop":269,
    "ks:ks_type":"HABITATION",
    "name:eng_x_preferred":[
        "Malaichiwadi"
    ],
    "wof:name":"Malaichiwadi",
    "wof:placetype":"locality",
    "wof:population":269
},
  "geometry": {"coordinates":[73.974568,17.258479],"type":"Point"}
}