{
  "type": "Feature",
  "properties": {
    "gn:admin1_code":"2.0",
    "gn:admin2_code":"543.0",
    "gn:asciiname":"Bayyada",
    "gn:country_code":"IN",
    "gn:dem":674,
    "gn:feature_class":"P",
    "gn:feature_code":"PPL",
    "gn:name":"Bayyada",
    "gn:population":0,
    "gn:timezone":"Asia/Kolkata",
    "iso:country":"IN",
    "ks:ks_name":"Bayyada",
    "ks:ks_pop":369,
    "ks:ks_type":"HABITATION",
    "name:eng_x_preferred":[
        "Bayyada"
    ],
    "wof:name":"Bayyada",
    "wof:placetype":"locality",
    "wof:population":369
},
  "geometry": {"coordinates":[83.56652,18.988977],"type":"Point"}
}