{
  "type": "Feature",
  "properties": {
    "gn:admin1_code":"2.0",
    "gn:admin2_code":"543.0",
    "gn:asciiname":"Bayyada",
    "gn:country_code":"IN",
    "gn:dem":674,
    "gn:feature_class":"P",
    "gn:feature_code":"PPL",
    "gn:name":"Bayyada",
    "gn:population":0,
    "gn:timezone":"Asia/Kolkata",
    "iso:country":"IN",
    "wof:name":"Bayyada",
    "wof:placetype":"locality"
},
  "geometry": {"coordinates":[83.56645,18.98936],"type":"Point"}
}