{
  "type": "Feature",
  "properties": {
    "gn:admin1_code":"36",
    "gn:admin2_code":"156.0",
    "gn:asciiname":"Mushkabad",
    "gn:country_code":"IN",
    "gn:dem":118,
    "gn:feature_class":"P",
    "gn:feature_code":"PPL",
    "gn:name":"Mushk\u0101b\u0101d",
    "gn:population":0,
    "gn:timezone":"Asia/Kolkata",
    "iso:country":"IN",
    "ks:ks_alt_nam":"Mushk\u0101b\u0101d",
    "ks:ks_name":"Mushkabad",
    "ks:ks_type":"VILLAGE",
    "name:eng_x_preferred":[
        "Mushkabad"
    ],
    "name:eng_x_variant":[
        "Mushk\u0101b\u0101d"
    ],
    "wof:name":"Mushkabad",
    "wof:placetype":"locality"
},
  "geometry": {"coordinates":[80.79731200000001,26.246334],"type":"Point"}
}