{
  "type": "Feature",
  "properties": {
    "gn:admin1_code":"21.0",
    "gn:admin2_code":"385",
    "gn:asciiname":"Barkola",
    "gn:country_code":"IN",
    "gn:dem":190,
    "gn:feature_class":"P",
    "gn:feature_code":"PPL",
    "gn:name":"Barkola",
    "gn:population":0,
    "gn:timezone":"Asia/Kolkata",
    "iso:country":"IN",
    "ks:ks_name":"Barkola",
    "ks:ks_pop":557,
    "ks:ks_type":"VILLAGE",
    "name:eng_x_preferred":[
        "Barkola"
    ],
    "wof:name":"Barkola",
    "wof:placetype":"locality",
    "wof:population":557
},
  "geometry": {"coordinates":[84.84826200000001,20.164106],"type":"Point"}
}