{
  "type": "Feature",
  "properties": {
    "iso:country":"IN",
    "ks:ks_name":"Ghoramara Pt II",
    "ks:ks_pop":1634,
    "ks:ks_type":"VILLAGE",
    "name:eng_x_preferred":[
        "Ghoramara Pt II"
    ],
    "wof:name":"Ghoramara Pt II",
    "wof:placetype":"locality",
    "wof:population":1634
},
  "geometry": {"coordinates":[92.430533,24.813658],"type":"Point"}
}