{
  "type": "Feature",
  "properties": {
    "gn:admin1_code":"36",
    "gn:admin2_code":"195.0",
    "gn:asciiname":"Sera",
    "gn:country_code":"IN",
    "gn:dem":71,
    "gn:feature_class":"P",
    "gn:feature_code":"PPL",
    "gn:name":"Sera",
    "gn:population":0,
    "gn:timezone":"Asia/Kolkata",
    "iso:country":"IN",
    "ks:ks_name":"Sera",
    "ks:ks_type":"VILLAGE",
    "name:bul_x_preferred":[
        "\u0421\u0435\u0440\u0430"
    ],
    "name:ceb_x_preferred":[
        "Sera"
    ],
    "name:deu_x_preferred":[
        "Sera"
    ],
    "name:eng_x_preferred":[
        "Sera"
    ],
    "name:fin_x_preferred":[
        "Sera"
    ],
    "name:fra_x_preferred":[
        "Sera"
    ],
    "name:ita_x_preferred":[
        "Sera"
    ],
    "name:nld_x_preferred":[
        "Sera"
    ],
    "name:rus_x_preferred":[
        "\u0421\u0435\u0440\u0430"
    ],
    "name:srp_x_preferred":[
        "\u0421\u0435\u0440\u0430"
    ],
    "name:swe_x_preferred":[
        "Sera"
    ],
    "name:ukr_x_preferred":[
        "\u0421\u0435\u0440\u0430"
    ],
    "wof:name":"Sera",
    "wof:placetype":"locality"
},
  "geometry": {"coordinates":[83.629732,25.374492],"type":"Point"}
}