{
  "type": "Feature",
  "properties": {
    "gn:admin1_code":"16.0",
    "gn:admin2_code":"507.0",
    "gn:asciiname":"Saongitola",
    "gn:country_code":"IN",
    "gn:dem":260,
    "gn:feature_class":"P",
    "gn:feature_code":"PPL",
    "gn:name":"Saong\u012btol\u0101",
    "gn:population":0,
    "gn:timezone":"Asia/Kolkata",
    "iso:country":"IN",
    "wof:name":"Saongitola",
    "wof:placetype":"locality"
},
  "geometry": {"coordinates":[80.11901999999998,21.09079],"type":"Point"}
}