{
  "type": "Feature",
  "properties": {
    "iso:country":"IN",
    "ks:ks_name":"Bhati",
    "ks:ks_pop":587,
    "ks:ks_type":"HABITATION",
    "name:eng_x_preferred":[
        "Bhati"
    ],
    "wof:name":"Bhati",
    "wof:placetype":"locality",
    "wof:population":587
},
  "geometry": {"coordinates":[73.206389,17.387222],"type":"Point"}
}