{
  "type": "Feature",
  "properties": {
    "iso:country":"IN",
    "ks:ks_name":"15 NRD",
    "ks:ks_pop":259,
    "ks:ks_type":"VILLAGE",
    "name:eng_x_preferred":[
        "15 NRD"
    ],
    "wof:name":"15 NRD",
    "wof:placetype":"locality",
    "wof:population":259
},
  "geometry": {"coordinates":[73.662086,29.476382],"type":"Point"}
}