{
  "type": "Feature",
  "properties": {
    "iso:country":"IN",
    "ks:ks_name":"Pind Per",
    "ks:ks_pop":144,
    "ks:ks_type":"HABITATION",
    "name:eng_x_preferred":[
        "Pind Per"
    ],
    "wof:name":"Pind Per",
    "wof:placetype":"locality",
    "wof:population":144
},
  "geometry": {"coordinates":[85.63385599999999,25.183693],"type":"Point"}
}