{
  "type": "Feature",
  "properties": {
    "iso:country":"IN",
    "ks:ks_name":"Salika Dhanichak",
    "ks:ks_pop":1647,
    "ks:ks_type":"VILLAGE",
    "ks:ks_uagg_main":0,
    "name:eng_x_preferred":[
        "Salika Dhanichak"
    ],
    "wof:name":"Salika Dhanichak",
    "wof:placetype":"neighbourhood",
    "wof:population":1647
},
  "geometry": {"coordinates":[87.80918800000001,22.302207],"type":"Point"}
}