{
  "type": "Feature",
  "properties": {
    "gn:admin1_code":"36",
    "gn:admin2_code":"186.0",
    "gn:asciiname":"Sheopur",
    "gn:country_code":"IN",
    "gn:dem":83,
    "gn:feature_class":"P",
    "gn:feature_code":"PPL",
    "gn:name":"Sheopur",
    "gn:population":0,
    "gn:timezone":"Asia/Kolkata",
    "iso:country":"IN",
    "name:ara_x_preferred":[
        "\u0634\u064a\u0628\u0648\u0631"
    ],
    "name:ben_bn_x_preferred":[
        "\u09b6\u09c7\u0993\u09aa\u09c1\u09b0"
    ],
    "name:ben_in_x_preferred":[
        "\u09b6\u09c7\u0993\u09aa\u09c1\u09b0"
    ],
    "name:ben_x_preferred":[
        "\u09b6\u09c7\u0993\u09aa\u09c1\u09b0"
    ],
    "name:bpy_x_preferred":[
        "\u09b6\u09c7\u09f1\u09aa\u09c1\u09b0"
    ],
    "name:cat_x_preferred":[
        "Sheopur"
    ],
    "name:ceb_x_preferred":[
        "Sheopur"
    ],
    "name:fra_x_preferred":[
        "Sheopur"
    ],
    "name:guj_x_preferred":[
        "\u0ab6\u0ac0\u0a93\u0aaa\u0ac1\u0ab0"
    ],
    "name:guj_x_variant":[
        "\u0ab6\u0acd\u0aaf\u0acb\u0aaa\u0ac1\u0ab0"
    ],
    "name:hif_x_preferred":[
        "Sheopur"
    ],
    "name:hin_x_preferred":[
        "\u0936\u0947\u0913\u092a\u0941\u0930"
    ],
    "name:hin_x_variant":[
        "\u0936\u094d\u092f\u094b\u092a\u0941\u0930"
    ],
    "name:ita_x_preferred":[
        "Sheopur"
    ],
    "name:kan_x_preferred":[
        "\u0cb6\u0ccd\u0caf\u0cc2\u0caa\u0cc1\u0cb0"
    ],
    "name:mal_x_preferred":[
        "\u0d37\u0d3f\u0d2f\u0d4b\u0d2a\u0d42\u0d7c"
    ],
    "name:mar_x_preferred":[
        "\u0936\u094d\u092f\u094b\u092a\u0941\u0930"
    ],
    "name:mlg_x_preferred":[
        "Sheopur"
    ],
    "name:msa_x_preferred":[
        "Sheopur"
    ],
    "name:ori_x_preferred":[
        "\u0b36\u0b47\u0b13\u0b2a\u0b41\u0b30"
    ],
    "name:pam_x_preferred":[
        "Sheopur"
    ],
    "name:pan_x_preferred":[
        "\u0a36\u0a40\u0a13\u0a2a\u0a41\u0a30"
    ],
    "name:por_x_preferred":[
        "Sheopur"
    ],
    "name:san_x_preferred":[
        "\u0936\u094d\u092f\u094b\u092a\u0941\u0930\u092e\u094d"
    ],
    "name:spa_x_preferred":[
        "Sheopur"
    ],
    "name:swe_x_preferred":[
        "Sheopur"
    ],
    "name:tam_x_preferred":[
        "\u0bb7\u0bcd\u0baf\u0bcb\u0baa\u0bc2\u0bb0\u0bcd"
    ],
    "name:tel_x_preferred":[
        "\u0c37\u0c3f\u0c2f\u0c4b\u0c2a\u0c42\u0c30\u0c4d"
    ],
    "name:urd_x_preferred":[
        "\u0634\u06cc\u0648\u067e\u0648\u0631"
    ],
    "name:urd_x_variant":[
        "\u0634\u0648\u067e\u0648\u0631"
    ],
    "name:vie_x_preferred":[
        "Sheopur"
    ],
    "name:zho_x_preferred":[
        "\u65af\u8d6b\u5965\u666e\u5c14"
    ],
    "wof:name":"Sheopur",
    "wof:placetype":"locality"
},
  "geometry": {"coordinates":[83.08391,26.45766],"type":"Point"}
}