{
  "type": "Feature",
  "properties": {
    "iso:country":"IN",
    "ks:ks_name":"Otisar",
    "ks:ks_pop":31,
    "ks:ks_type":"HABITATION",
    "name:eng_x_preferred":[
        "Otisar"
    ],
    "wof:name":"Otisar",
    "wof:placetype":"locality",
    "wof:population":31
},
  "geometry": {"coordinates":[74.775402,14.839028],"type":"Point"}
}