{
  "type": "Feature",
  "properties": {
    "iso:country":"IN",
    "ks:ks_name":"Bhajaput",
    "ks:ks_pop":256,
    "ks:ks_type":"HABITATION",
    "name:eng_x_preferred":[
        "Bhajaput"
    ],
    "wof:name":"Bhajaput",
    "wof:placetype":"locality",
    "wof:population":256
},
  "geometry": {"coordinates":[83.004212,18.844752],"type":"Point"}
}