{
  "type": "Feature",
  "properties": {
    "iso:country":"IN",
    "ks:ks_name":"Chavanwasti",
    "ks:ks_pop":357,
    "ks:ks_type":"HABITATION",
    "name:eng_x_preferred":[
        "Chavanwasti"
    ],
    "wof:name":"Chavanwasti",
    "wof:placetype":"locality",
    "wof:population":357
},
  "geometry": {"coordinates":[75.310593,18.562679],"type":"Point"}
}