{
  "type": "Feature",
  "properties": {
    "iso:country":"IN",
    "ks:ks_name":"Gollapalle",
    "ks:ks_pop":307,
    "ks:ks_type":"HABITATION",
    "name:eng_x_preferred":[
        "Gollapalle"
    ],
    "wof:name":"Gollapalle",
    "wof:placetype":"locality",
    "wof:population":307
},
  "geometry": {"coordinates":[79.089776,14.610539],"type":"Point"}
}