{
  "type": "Feature",
  "properties": {
    "iso:country":"IN",
    "ks:ks_name":"Mukkerjal",
    "ks:ks_pop":100,
    "ks:ks_type":"HABITATION",
    "name:eng_x_preferred":[
        "Mukkerjal"
    ],
    "wof:name":"Mukkerjal",
    "wof:placetype":"locality",
    "wof:population":100
},
  "geometry": {"coordinates":[75.316022,12.909492],"type":"Point"}
}