{
  "type": "Feature",
  "properties": {
    "iso:country":"IN",
    "ks:ks_name":"Sabbapada",
    "ks:ks_pop":28,
    "ks:ks_type":"HABITATION",
    "name:eng_x_preferred":[
        "Sabbapada"
    ],
    "wof:name":"Sabbapada",
    "wof:placetype":"locality",
    "wof:population":28
},
  "geometry": {"coordinates":[74.940082,23.014898],"type":"Point"}
}