{
  "type": "Feature",
  "properties": {
    "iso:country":"IN",
    "ks:ks_name":"Ganesh Nagar",
    "ks:ks_pop":106,
    "ks:ks_type":"HABITATION",
    "name:eng_x_preferred":[
        "Ganesh Nagar"
    ],
    "wof:name":"Ganesh Nagar",
    "wof:placetype":"locality",
    "wof:population":106
},
  "geometry": {"coordinates":[75.57832500000001,16.93886],"type":"Point"}
}