{
  "type": "Feature",
  "properties": {
    "iso:country":"IN",
    "ks:ks_name":"Bansdubia",
    "ks:ks_pop":177,
    "ks:ks_type":"VILLAGE",
    "ks:ks_uagg_main":0,
    "name:eng_x_preferred":[
        "Bansdubia"
    ],
    "wof:name":"Bansdubia",
    "wof:placetype":"neighbourhood",
    "wof:population":177
},
  "geometry": {"coordinates":[85.868392,24.442344],"type":"Point"}
}