{
  "type": "Feature",
  "properties": {
    "iso:country":"IN",
    "ks:ks_alt_nam":"DOMDERA",
    "ks:ks_name":"Domdera",
    "ks:ks_pop":176,
    "ks:ks_type":"HABITATION",
    "name:eng_x_preferred":[
        "Domdera"
    ],
    "wof:name":"Domdera",
    "wof:placetype":"locality",
    "wof:population":176
},
  "geometry": {"coordinates":[83.745148,26.010943],"type":"Point"}
}