{
  "type": "Feature",
  "properties": {
    "gn:admin1_code":"19.0",
    "gn:admin2_code":"573.0",
    "gn:asciiname":"Muddanahallikoppal",
    "gn:country_code":"IN",
    "gn:dem":847,
    "gn:feature_class":"P",
    "gn:feature_code":"PPL",
    "gn:name":"Muddanahallikoppal",
    "gn:population":0,
    "gn:timezone":"Asia/Kolkata",
    "iso:country":"IN",
    "wof:name":"Muddanahallikoppal",
    "wof:placetype":"locality"
},
  "geometry": {"coordinates":[76.56286,12.54284],"type":"Point"}
}