{
  "type": "Feature",
  "properties": {
    "gn:admin1_code":"36",
    "gn:admin2_code":"199.0",
    "gn:asciiname":"Tikhor",
    "gn:country_code":"IN",
    "gn:dem":160,
    "gn:feature_class":"P",
    "gn:feature_code":"PPL",
    "gn:name":"Tikhor",
    "gn:population":0,
    "gn:timezone":"Asia/Kolkata",
    "iso:country":"IN",
    "name:ara_x_preferred":[
        "\u0637\u064a\u062e\u0648\u0631"
    ],
    "name:ceb_x_preferred":[
        "\u0162\u012bkhor"
    ],
    "name:fas_x_preferred":[
        "\u0637\u06cc\u062e\u0648\u0631"
    ],
    "name:swe_x_preferred":[
        "\u0162\u012bkhor"
    ],
    "wof:name":"Tikhor",
    "wof:placetype":"locality"
},
  "geometry": {"coordinates":[82.33351,25.06418],"type":"Point"}
}