{
  "type": "Feature",
  "properties": {
    "iso:country":"IN",
    "ks:ks_name":"Bhandarisul",
    "ks:ks_pop":279,
    "ks:ks_type":"VILLAGE",
    "name:eng_x_preferred":[
        "Bhandarisul"
    ],
    "wof:name":"Bhandarisul",
    "wof:placetype":"locality",
    "wof:population":279
},
  "geometry": {"coordinates":[86.971052,22.028282],"type":"Point"}
}