{
  "type": "Feature",
  "properties": {
    "iso:country":"IN",
    "ks:ks_name":"Bilekal",
    "ks:ks_pop":46,
    "ks:ks_type":"HABITATION",
    "name:eng_x_preferred":[
        "Bilekal"
    ],
    "name:hin_x_preferred":[
        "\u092c\u093f\u0932\u0947\u0915\u0932"
    ],
    "name:kan_x_preferred":[
        "\u0cac\u0cbf\u0cb3\u0cc6\u0c95\u0cb2\u0ccd"
    ],
    "wof:name":"Bilekal",
    "wof:placetype":"locality",
    "wof:population":46
},
  "geometry": {"coordinates":[74.709681,14.503332],"type":"Point"}
}