{
  "type": "Feature",
  "properties": {
    "iso:country":"IN",
    "ks:ks_name":"Khalachiwadi",
    "ks:ks_pop":88,
    "ks:ks_type":"HABITATION",
    "name:eng_x_preferred":[
        "Khalachiwadi"
    ],
    "wof:name":"Khalachiwadi",
    "wof:placetype":"locality",
    "wof:population":88
},
  "geometry": {"coordinates":[73.727222,16.20108],"type":"Point"}
}