{
  "type": "Feature",
  "properties": {
    "iso:country":"IN",
    "ks:ks_name":"Palash",
    "ks:ks_pop":1525,
    "ks:ks_type":"VILLAGE",
    "ks:ks_uagg_main":0,
    "name:eng_x_preferred":[
        "Palash"
    ],
    "wof:name":"Palash",
    "wof:placetype":"neighbourhood",
    "wof:population":1525
},
  "geometry": {"coordinates":[88.435964,26.758936],"type":"Point"}
}