{
  "type": "Feature",
  "properties": {
    "iso:country":"IN",
    "ks:ks_name":"Sathanapara",
    "ks:ks_pop":365,
    "ks:ks_type":"HABITATION",
    "name:eng_x_preferred":[
        "Sathanapara"
    ],
    "wof:name":"Sathanapara",
    "wof:placetype":"locality",
    "wof:population":365
},
  "geometry": {"coordinates":[76.98133799999999,9.88967],"type":"Point"}
}