{
  "type": "Feature",
  "properties": {
    "iso:country":"IN",
    "ks:ks_alt_nam":"BINOBA NAGAR",
    "ks:ks_name":"Binoba Nagar",
    "ks:ks_pop":178,
    "ks:ks_type":"HABITATION",
    "name:eng_x_preferred":[
        "Binoba Nagar"
    ],
    "wof:name":"Binoba Nagar",
    "wof:placetype":"locality",
    "wof:population":178
},
  "geometry": {"coordinates":[83.642779,24.869403],"type":"Point"}
}