{
  "type": "Feature",
  "properties": {
    "iso:country":"IN",
    "ks:ks_name":"Bagarsangan",
    "ks:ks_pop":2549,
    "ks:ks_type":"VILLAGE",
    "ks:ks_uagg_main":0,
    "name:eng_x_preferred":[
        "Bagarsangan"
    ],
    "wof:name":"Bagarsangan",
    "wof:placetype":"neighbourhood",
    "wof:population":2549
},
  "geometry": {"coordinates":[92.299983,24.901422],"type":"Point"}
}