{
  "type": "Feature",
  "properties": {
    "iso:country":"IN",
    "ks:ks_alt_nam":"6 FFB",
    "ks:ks_name":"6 Ffb",
    "ks:ks_pop":31,
    "ks:ks_type":"HABITATION",
    "name:eng_x_preferred":[
        "6 Ffb"
    ],
    "wof:name":"6 Ffb",
    "wof:placetype":"locality",
    "wof:population":31
},
  "geometry": {"coordinates":[73.340074,29.65249],"type":"Point"}
}