{
  "type": "Feature",
  "properties": {
    "gn:admin1_code":"35",
    "gn:admin2_code":"451.0",
    "gn:asciiname":"Dhangawan",
    "gn:country_code":"IN",
    "gn:dem":391,
    "gn:feature_class":"P",
    "gn:feature_code":"PPL",
    "gn:name":"Dhangaw\u0101n",
    "gn:population":0,
    "gn:timezone":"Asia/Kolkata",
    "iso:country":"IN",
    "name:und_x_variant":[
        "Dhangaw\u0101n",
        "Mauw\u0101khera"
    ],
    "wof:name":"Dhangawan",
    "wof:placetype":"locality"
},
  "geometry": {"coordinates":[79.98608,23.54224],"type":"Point"}
}