{
  "type": "Feature",
  "properties": {
    "iso:country":"IN",
    "ks:ks_name":"Temha",
    "ks:ks_pop":77,
    "ks:ks_type":"VILLAGE",
    "ks:ks_uagg_main":0,
    "name:eng_x_preferred":[
        "Temha"
    ],
    "wof:name":"Temha",
    "wof:placetype":"neighbourhood",
    "wof:population":77
},
  "geometry": {"coordinates":[83.426485,26.597337],"type":"Point"}
}