{
  "type": "Feature",
  "properties": {
    "gn:admin1_code":"11.0",
    "gn:admin2_code":"31.0",
    "gn:asciiname":"Gog",
    "gn:country_code":"IN",
    "gn:dem":1238,
    "gn:feature_class":"P",
    "gn:feature_code":"PPL",
    "gn:name":"Gog",
    "gn:population":0,
    "gn:timezone":"Asia/Kolkata",
    "iso:country":"IN",
    "name:ceb_x_preferred":[
        "Gog"
    ],
    "name:cym_x_preferred":[
        "Gog"
    ],
    "name:deu_x_preferred":[
        "Gog"
    ],
    "name:fra_x_preferred":[
        "Gog"
    ],
    "name:ind_x_preferred":[
        "Gog"
    ],
    "name:pol_x_preferred":[
        "Gog"
    ],
    "name:por_x_preferred":[
        "Gog"
    ],
    "name:ron_x_preferred":[
        "Gog"
    ],
    "name:spa_x_preferred":[
        "Gog"
    ],
    "name:swe_x_preferred":[
        "Gog"
    ],
    "name:tgl_x_preferred":[
        "Gog"
    ],
    "wof:name":"Gog",
    "wof:placetype":"locality"
},
  "geometry": {"coordinates":[77.07394000000002,30.98529000000001],"type":"Point"}
}