{
  "type": "Feature",
  "properties": {
    "iso:country":"IN",
    "ks:ks_name":"Devarahalli",
    "ks:ks_pop":90,
    "ks:ks_type":"HABITATION",
    "name:eng_x_preferred":[
        "Devarahalli"
    ],
    "wof:name":"Devarahalli",
    "wof:placetype":"locality",
    "wof:population":90
},
  "geometry": {"coordinates":[77.02120499999999,13.496755],"type":"Point"}
}