{
  "type": "Feature",
  "properties": {
    "iso:country":"IN",
    "ks:ks_name":"Velani",
    "ks:ks_pop":210,
    "ks:ks_type":"HABITATION",
    "name:eng_x_preferred":[
        "Velani"
    ],
    "wof:name":"Velani",
    "wof:placetype":"locality",
    "wof:population":210
},
  "geometry": {"coordinates":[78.548343,9.667925],"type":"Point"}
}