{
  "type": "Feature",
  "properties": {
    "iso:country":"IN",
    "ks:ks_name":"Musukuli",
    "ks:ks_pop":176,
    "ks:ks_type":"VILLAGE",
    "name:eng_x_preferred":[
        "Musukuli"
    ],
    "wof:name":"Musukuli",
    "wof:placetype":"locality",
    "wof:population":176
},
  "geometry": {"coordinates":[83.88918700000001,20.211667],"type":"Point"}
}