{
  "type": "Feature",
  "properties": {
    "iso:country":"IN",
    "ks:ks_name":"Kakar Khurd",
    "ks:ks_pop":6,
    "ks:ks_type":"VILLAGE",
    "name:eng_x_preferred":[
        "Kakar Khurd"
    ],
    "wof:name":"Kakar Khurd",
    "wof:placetype":"locality",
    "wof:population":6
},
  "geometry": {"coordinates":[75.20918899999999,31.108809],"type":"Point"}
}