{
  "type": "Feature",
  "properties": {
    "iso:country":"IN",
    "ks:ks_alt_nam":"Mallah tola",
    "ks:ks_name":"Mallah Tola",
    "ks:ks_pop":704,
    "ks:ks_type":"HABITATION",
    "name:eng_x_preferred":[
        "Mallah Tola"
    ],
    "wof:name":"Mallah Tola",
    "wof:placetype":"locality",
    "wof:population":704
},
  "geometry": {"coordinates":[83.79316900000001,25.028501],"type":"Point"}
}