{
  "type": "Feature",
  "properties": {
    "gn:admin1_code":"35.0",
    "gn:admin2_code":"450.0",
    "gn:asciiname":"Pondi",
    "gn:country_code":"IN",
    "gn:dem":430,
    "gn:feature_class":"P",
    "gn:feature_code":"PPL",
    "gn:name":"Pondi",
    "gn:population":0,
    "gn:timezone":"Asia/Kolkata",
    "iso:country":"IN",
    "name:ceb_x_preferred":[
        "Pondi"
    ],
    "name:swe_x_preferred":[
        "Pondi"
    ],
    "wof:name":"Pondi",
    "wof:placetype":"locality"
},
  "geometry": {"coordinates":[80.42496,23.67071],"type":"Point"}
}