{
  "type": "Feature",
  "properties": {
    "iso:country":"IN",
    "ks:ks_name":"Illigaradoddi",
    "ks:ks_pop":174,
    "ks:ks_type":"HABITATION",
    "name:eng_x_preferred":[
        "Illigaradoddi"
    ],
    "wof:name":"Illigaradoddi",
    "wof:placetype":"locality",
    "wof:population":174
},
  "geometry": {"coordinates":[77.249898,12.867305],"type":"Point"}
}