{
  "type": "Feature",
  "properties": {
    "gn:admin1_code":"36.0",
    "gn:admin2_code":"189.0",
    "gn:asciiname":"Dumhi",
    "gn:country_code":"IN",
    "gn:dem":83,
    "gn:feature_class":"P",
    "gn:feature_code":"PPL",
    "gn:name":"Dumhi",
    "gn:population":0,
    "gn:timezone":"Asia/Kolkata",
    "iso:country":"IN",
    "ks:ks_name":"Dumhi",
    "ks:ks_type":"VILLAGE",
    "name:eng_x_preferred":[
        "Dumhi"
    ],
    "wof:name":"Dumhi",
    "wof:placetype":"locality"
},
  "geometry": {"coordinates":[84.157115,26.74748],"type":"Point"}
}