{
  "type": "Feature",
  "properties": {
    "iso:country":"IN",
    "ks:ks_name":"Basavangudi",
    "ks:ks_pop":36,
    "ks:ks_type":"HABITATION",
    "name:eng_x_preferred":[
        "Basavangudi"
    ],
    "wof:name":"Basavangudi",
    "wof:placetype":"locality",
    "wof:population":36
},
  "geometry": {"coordinates":[74.873265,14.89839],"type":"Point"}
}