{
  "type": "Feature",
  "properties": {
    "iso:country":"IN",
    "ks:ks_alt_nam":"Palyanayakan tanda",
    "ks:ks_name":"Palyanayakan Tanda",
    "ks:ks_pop":80,
    "ks:ks_type":"HABITATION",
    "name:eng_x_preferred":[
        "Palyanayakan Tanda"
    ],
    "wof:name":"Palyanayakan Tanda",
    "wof:placetype":"locality",
    "wof:population":80
},
  "geometry": {"coordinates":[76.939071,16.219089],"type":"Point"}
}