{
  "type": "Feature",
  "properties": {
    "gn:admin1_code":"3.0",
    "gn:admin2_code":"320.0",
    "gn:asciiname":"Chhatibargaon",
    "gn:country_code":"IN",
    "gn:dem":69,
    "gn:feature_class":"P",
    "gn:feature_code":"PPL",
    "gn:name":"Chh\u0101tibargaon",
    "gn:population":0,
    "gn:timezone":"Asia/Kolkata",
    "iso:country":"IN",
    "wof:name":"Chhatibargaon",
    "wof:placetype":"locality"
},
  "geometry": {"coordinates":[90.51766000000001,26.54421],"type":"Point"}
}