{
  "type": "Feature",
  "properties": {
    "iso:country":"IN",
    "name:eng_x_preferred":[
        "Jalahalli"
    ],
    "name:eng_x_variant":[
        "Jalhalli"
    ],
    "name:kan_x_preferred":[
        "\u0c9c\u0cbe\u0cb2\u0cb9\u0cb3\u0ccd\u0cb3\u0cbf"
    ],
    "name:nld_x_preferred":[
        "Jalahalli"
    ],
    "name:tam_x_preferred":[
        "\u0b9a\u0bb2\u0bbe\u0bb3\u0bbf"
    ],
    "name:und_x_preferred":[
        "J\u0101lahalli"
    ],
    "name:unk_x_variant":[
        "Jalhalli",
        "Jalahalli"
    ],
    "name:urd_x_preferred":[
        "\u062c\u0644\u06c1\u0627\u0644\u0644\u06cc"
    ],
    "name:zho_x_preferred":[
        "\u52a0\u62c9\u54c8\u7acb"
    ],
    "qs:gn_adm0_cc":"IN",
    "qs:gn_fcode":"PPL",
    "qs:gn_local":1277333,
    "qs:gn_nam_loc":"Bangalore, Bangalore, Karnataka, IN",
    "qs:gn_namadm1":"19",
    "qs:gn_name":"J\u0101lahalli",
    "qs:local_max":7342,
    "qs:local_sum":38996,
    "qs:localhoods":89,
    "qs:name":"Jalahalli",
    "qs:name_adm0":"India",
    "qs:name_adm1":"Karnataka",
    "qs:name_adm2":"Bangalore",
    "qs:name_local":"Bangalore",
    "qs:photo_max":38,
    "qs:photo_sum":66,
    "qs:placetype":"Suburb",
    "qs:quad_count":9,
    "qs:woe_adm0":23424848,
    "qs:woe_adm1":2345753,
    "qs:woe_adm2":12586572,
    "qs:woe_lau":0,
    "qs:woe_local":2295420,
    "qs:woe_ver":"7.10.0",
    "wd:wordcount":1002,
    "wof:lang":[
        "eng"
    ],
    "wof:name":"Jalahalli",
    "wof:placetype":"neighbourhood"
},
  "geometry": {"coordinates":[77.542877,13.053088],"type":"Point"}
}