{
  "type": "Feature",
  "properties": {
    "iso:country":"IN",
    "ks:ks_name":"Majnu Tola",
    "ks:ks_pop":100,
    "ks:ks_type":"HABITATION",
    "ks:ks_uagg_main":0,
    "name:eng_x_preferred":[
        "Majnu Tola"
    ],
    "wof:name":"Majnu Tola",
    "wof:placetype":"neighbourhood",
    "wof:population":100
},
  "geometry": {"coordinates":[83.33639700000001,27.039408],"type":"Point"}
}