{
  "type": "Feature",
  "properties": {
    "iso:country":"IN",
    "ks:ks_name":"Jamalapur",
    "ks:ks_pop":301,
    "ks:ks_type":"VILLAGE",
    "ks:ks_uagg_main":0,
    "name:eng_x_preferred":[
        "Jamalapur"
    ],
    "wof:name":"Jamalapur",
    "wof:placetype":"neighbourhood",
    "wof:population":301
},
  "geometry": {"coordinates":[85.83500600000001,20.061069],"type":"Point"}
}