{
  "type": "Feature",
  "properties": {
    "iso:country":"IN",
    "ks:ks_name":"Danardanpali",
    "ks:ks_pop":430,
    "ks:ks_type":"VILLAGE",
    "name:eng_x_preferred":[
        "Danardanpali"
    ],
    "wof:name":"Danardanpali",
    "wof:placetype":"locality",
    "wof:population":430
},
  "geometry": {"coordinates":[84.773369,21.444005],"type":"Point"}
}