{
  "type": "Feature",
  "properties": {
    "iso:country":"IN",
    "ks:ks_name":"Gondrabhatha Patelpara",
    "ks:ks_pop":320,
    "ks:ks_type":"HABITATION",
    "name:eng_x_preferred":[
        "Gondrabhatha Patelpara"
    ],
    "wof:name":"Gondrabhatha Patelpara",
    "wof:placetype":"locality",
    "wof:population":320
},
  "geometry": {"coordinates":[82.664366,22.271498],"type":"Point"}
}