{
  "type": "Feature",
  "properties": {
    "iso:country":"IN",
    "ks:ks_alt_nam":"HARAHI",
    "ks:ks_name":"Harahi",
    "ks:ks_pop":412,
    "ks:ks_type":"HABITATION",
    "ks:ks_uagg_main":0,
    "name:eng_x_preferred":[
        "Harahi"
    ],
    "wof:name":"Harahi",
    "wof:placetype":"neighbourhood",
    "wof:population":412
},
  "geometry": {"coordinates":[82.118882,26.24493],"type":"Point"}
}