{
  "type": "Feature",
  "properties": {
    "gn:admin1_code":"36",
    "gn:admin2_code":"167.0",
    "gn:asciiname":"Bareja",
    "gn:country_code":"IN",
    "gn:dem":400,
    "gn:feature_class":"P",
    "gn:feature_code":"PPL",
    "gn:name":"Bareja",
    "gn:population":0,
    "gn:timezone":"Asia/Kolkata",
    "iso:country":"IN",
    "wof:name":"Bareja",
    "wof:placetype":"locality"
},
  "geometry": {"coordinates":[78.61034000000002,24.38924],"type":"Point"}
}