{
  "type": "Feature",
  "properties": {
    "gn:admin1_code":"36",
    "gn:admin2_code":"156.0",
    "gn:asciiname":"Ram Das Khera Kalan",
    "gn:country_code":"IN",
    "gn:dem":122,
    "gn:feature_class":"P",
    "gn:feature_code":"PPL",
    "gn:name":"R\u0101m D\u0101s Khera Kal\u0101n",
    "gn:population":0,
    "gn:timezone":"Asia/Kolkata",
    "iso:country":"IN",
    "wof:name":"Ram Das Khera Kalan",
    "wof:placetype":"locality"
},
  "geometry": {"coordinates":[80.91079999999999,26.42832000000001],"type":"Point"}
}