{
  "type": "Feature",
  "properties": {
    "iso:country":"IN",
    "ks:ks_name":"Salaiya Maharhai",
    "ks:ks_pop":71,
    "ks:ks_type":"HABITATION",
    "name:eng_x_preferred":[
        "Salaiya Maharhai"
    ],
    "wof:name":"Salaiya Maharhai",
    "wof:placetype":"locality",
    "wof:population":71
},
  "geometry": {"coordinates":[80.48833,23.945237],"type":"Point"}
}