{
  "type": "Feature",
  "properties": {
    "iso:country":"IN",
    "ks:ks_name":"Kadikadu",
    "ks:ks_pop":140,
    "ks:ks_type":"VILLAGE",
    "name:eng_x_preferred":[
        "Kadikadu"
    ],
    "wof:name":"Kadikadu",
    "wof:placetype":"locality",
    "wof:population":140
},
  "geometry": {"coordinates":[84.565493,20.201379],"type":"Point"}
}