{
  "type": "Feature",
  "properties": {
    "iso:country":"IN",
    "ks:ks_name":"Ojagaon No 2 A",
    "ks:ks_pop":345,
    "ks:ks_type":"HABITATION",
    "name:eng_x_preferred":[
        "Ojagaon No 2 A"
    ],
    "wof:name":"Ojagaon No 2 A",
    "wof:placetype":"locality",
    "wof:population":345
},
  "geometry": {"coordinates":[92.252554,26.820405],"type":"Point"}
}