{
  "type": "Feature",
  "properties": {
    "iso:country":"IN",
    "ks:ks_alt_nam":"Lothikunta thanda",
    "ks:ks_name":"Lothikunta Thanda",
    "ks:ks_pop":160,
    "ks:ks_type":"HABITATION",
    "name:eng_x_preferred":[
        "Lothikunta Thanda"
    ],
    "wof:name":"Lothikunta Thanda",
    "wof:placetype":"locality",
    "wof:population":160
},
  "geometry": {"coordinates":[77.76162100000001,17.172276],"type":"Point"}
}