{
  "type": "Feature",
  "properties": {
    "gn:admin1_code":"25.0",
    "gn:admin2_code":"616.0",
    "gn:asciiname":"Panniyadi",
    "gn:country_code":"IN",
    "gn:dem":37,
    "gn:feature_class":"P",
    "gn:feature_code":"PPL",
    "gn:name":"Panniy\u0101di",
    "gn:population":0,
    "gn:timezone":"Asia/Kolkata",
    "iso:country":"IN",
    "ks:ks_name":"Panayadi",
    "ks:ks_pop":379,
    "ks:ks_type":"HABITATION",
    "name:eng_x_preferred":[
        "Panayadi"
    ],
    "name:eng_x_variant":[
        "Panniyadi"
    ],
    "wof:name":"Panayadi",
    "wof:placetype":"locality",
    "wof:population":379
},
  "geometry": {"coordinates":[79.36407,11.114288],"type":"Point"}
}