{
  "type": "Feature",
  "properties": {
    "iso:country":"IN",
    "ks:ks_name":"Tola Banpur",
    "ks:ks_pop":128,
    "ks:ks_type":"VILLAGE",
    "name:eng_x_preferred":[
        "Tola Banpur"
    ],
    "wof:name":"Tola Banpur",
    "wof:placetype":"locality",
    "wof:population":128
},
  "geometry": {"coordinates":[86.913918,24.708128],"type":"Point"}
}