{
  "type": "Feature",
  "properties": {
    "iso:country":"IN",
    "ks:ks_name":"Dungri Falia",
    "ks:ks_pop":699,
    "ks:ks_type":"HABITATION",
    "name:eng_x_preferred":[
        "Dungri Falia"
    ],
    "wof:name":"Dungri Falia",
    "wof:placetype":"locality",
    "wof:population":699
},
  "geometry": {"coordinates":[73.146833,20.435083],"type":"Point"}
}