{
  "type": "Feature",
  "properties": {
    "iso:country":"IN",
    "ks:ks_name":"Hebbarmane",
    "ks:ks_pop":11,
    "ks:ks_type":"HABITATION",
    "name:eng_x_preferred":[
        "Hebbarmane"
    ],
    "wof:name":"Hebbarmane",
    "wof:placetype":"locality",
    "wof:population":11
},
  "geometry": {"coordinates":[74.678059,14.926637],"type":"Point"}
}