{
  "type": "Feature",
  "properties": {
    "iso:country":"IN",
    "ks:ks_name":"Kummarikunta",
    "ks:ks_pop":85,
    "ks:ks_type":"HABITATION",
    "name:eng_x_preferred":[
        "Kummarikunta"
    ],
    "wof:name":"Kummarikunta",
    "wof:placetype":"locality",
    "wof:population":85
},
  "geometry": {"coordinates":[78.794252,19.321359],"type":"Point"}
}