{
  "type": "Feature",
  "properties": {
    "gn:admin1_code":"40.0",
    "gn:admin2_code":"535",
    "gn:asciiname":"Raikanapalli",
    "gn:country_code":"IN",
    "gn:dem":511,
    "gn:feature_class":"P",
    "gn:feature_code":"PPL",
    "gn:name":"Raikanapalli",
    "gn:population":0,
    "gn:timezone":"Asia/Kolkata",
    "iso:country":"IN",
    "wof:name":"Raikanapalli",
    "wof:placetype":"neighbourhood"
},
  "geometry": {"coordinates":[78.14906000000001,17.85337],"type":"Point"}
}