{
  "type": "Feature",
  "properties": {
    "iso:country":"IN",
    "ks:ks_alt_nam":"Thotagunta Yanadi colony",
    "ks:ks_name":"Thotagunta Yanadi Colony",
    "ks:ks_pop":91,
    "ks:ks_type":"HABITATION",
    "name:eng_x_preferred":[
        "Thotagunta Yanadi Colony"
    ],
    "wof:name":"Thotagunta Yanadi Colony",
    "wof:placetype":"locality",
    "wof:population":91
},
  "geometry": {"coordinates":[80.09551999999999,15.352636],"type":"Point"}
}