{
  "type": "Feature",
  "properties": {
    "gn:admin1_code":"21",
    "gn:admin2_code":"394.0",
    "gn:asciiname":"Talakot",
    "gn:country_code":"IN",
    "gn:dem":326,
    "gn:feature_class":"P",
    "gn:feature_code":"PPL",
    "gn:name":"Tal\u0101kot",
    "gn:population":0,
    "gn:timezone":"Asia/Kolkata",
    "iso:country":"IN",
    "ks:ks_alt_nam":"Tal\u0101kot",
    "ks:ks_name":"Talakot",
    "ks:ks_type":"VILLAGE",
    "name:eng_x_preferred":[
        "Talakot"
    ],
    "name:eng_x_variant":[
        "Tal\u0101kot"
    ],
    "wof:name":"Talakot",
    "wof:placetype":"locality"
},
  "geometry": {"coordinates":[82.417098,20.078253],"type":"Point"}
}