{
  "type": "Feature",
  "properties": {
    "gn:admin1_code":"9.0",
    "gn:admin2_code":"483.0",
    "gn:asciiname":"Mekhari Muwara",
    "gn:country_code":"IN",
    "gn:dem":104,
    "gn:feature_class":"P",
    "gn:feature_code":"PPL",
    "gn:name":"Mekhari Muwara",
    "gn:population":0,
    "gn:timezone":"Asia/Kolkata",
    "iso:country":"IN",
    "wof:name":"Mekhari Muwara",
    "wof:placetype":"neighbourhood"
},
  "geometry": {"coordinates":[73.42104999999999,23.09606],"type":"Point"}
}