{
  "type": "Feature",
  "properties": {
    "iso:country":"IN",
    "ks:ks_name":"Birjewadi",
    "ks:ks_pop":153,
    "ks:ks_type":"HABITATION",
    "name:eng_x_preferred":[
        "Birjewadi"
    ],
    "wof:name":"Birjewadi",
    "wof:placetype":"locality",
    "wof:population":153
},
  "geometry": {"coordinates":[73.344972,16.823632],"type":"Point"}
}