{
  "type": "Feature",
  "properties": {
    "iso:country":"IN",
    "ks:ks_alt_nam":"TUNGRI TOLI",
    "ks:ks_name":"Tungri Toli",
    "ks:ks_pop":200,
    "ks:ks_type":"HABITATION",
    "name:eng_x_preferred":[
        "Tungri Toli"
    ],
    "wof:name":"Tungri Toli",
    "wof:placetype":"locality",
    "wof:population":200
},
  "geometry": {"coordinates":[84.937471,22.902273],"type":"Point"}
}