{
  "type": "Feature",
  "properties": {
    "iso:country":"IN",
    "ks:ks_alt_nam":"Boroi TE Grant 319 505",
    "ks:ks_name":"Boroi Te Grant 319 505",
    "ks:ks_pop":418,
    "ks:ks_type":"HABITATION",
    "name:eng_x_preferred":[
        "Boroi Te Grant 319 505"
    ],
    "wof:name":"Boroi Te Grant 319 505",
    "wof:placetype":"locality",
    "wof:population":418
},
  "geometry": {"coordinates":[93.509776,26.928601],"type":"Point"}
}