{
  "type": "Feature",
  "properties": {
    "iso:country":"IN",
    "ks:ks_name":"Badhurkha Para",
    "ks:ks_pop":814,
    "ks:ks_type":"HABITATION",
    "name:eng_x_preferred":[
        "Badhurkha Para"
    ],
    "wof:name":"Badhurkha Para",
    "wof:placetype":"locality",
    "wof:population":814
},
  "geometry": {"coordinates":[91.80365,24.096656],"type":"Point"}
}