{
  "type": "Feature",
  "properties": {
    "iso:country":"IN",
    "ks:ks_name":"Chinchua",
    "ks:ks_pop":217,
    "ks:ks_type":"HABITATION",
    "name:eng_x_preferred":[
        "Chinchua"
    ],
    "wof:name":"Chinchua",
    "wof:placetype":"locality",
    "wof:population":217
},
  "geometry": {"coordinates":[82.663962,20.943763],"type":"Point"}
}