{
  "type": "Feature",
  "properties": {
    "iso:country":"IN",
    "ks:ks_name":"Rampur Kamata Prasad",
    "ks:ks_pop":772,
    "ks:ks_type":"VILLAGE",
    "name:eng_x_preferred":[
        "Rampur Kamata Prasad"
    ],
    "wof:name":"Rampur Kamata Prasad",
    "wof:placetype":"locality",
    "wof:population":772
},
  "geometry": {"coordinates":[82.36167399999999,24.965161],"type":"Point"}
}