{
  "type": "Feature",
  "properties": {
    "gn:admin1_code":"35.0",
    "gn:admin2_code":"464.0",
    "gn:asciiname":"Gadwara",
    "gn:country_code":"IN",
    "gn:dem":328,
    "gn:feature_class":"P",
    "gn:feature_code":"PPL",
    "gn:name":"Gadwara",
    "gn:population":0,
    "gn:timezone":"Asia/Kolkata",
    "iso:country":"IN",
    "wof:name":"Gadwara",
    "wof:placetype":"locality"
},
  "geometry": {"coordinates":[74.61561999999998,22.76337],"type":"Point"}
}