{
  "type": "Feature",
  "properties": {
    "gn:admin1_code":"3.0",
    "gn:admin2_code":"323.0",
    "gn:asciiname":"Meruattari",
    "gn:country_code":"IN",
    "gn:dem":46,
    "gn:feature_class":"P",
    "gn:feature_code":"PPL",
    "gn:name":"Meruattari",
    "gn:population":0,
    "gn:timezone":"Asia/Kolkata",
    "iso:country":"IN",
    "wof:name":"Meruattari",
    "wof:placetype":"locality"
},
  "geometry": {"coordinates":[91.37832,26.30359],"type":"Point"}
}