{
  "type": "Feature",
  "properties": {
    "iso:country":"IN",
    "ks:ks_name":"Halkanhar",
    "ks:ks_pop":94,
    "ks:ks_type":"VILLAGE",
    "name:eng_x_preferred":[
        "Halkanhar"
    ],
    "wof:name":"Halkanhar",
    "wof:placetype":"locality",
    "wof:population":94
},
  "geometry": {"coordinates":[80.500342,20.116336],"type":"Point"}
}