{
  "type": "Feature",
  "properties": {
    "iso:country":"IN",
    "ks:ks_name":"Soso",
    "ks:ks_pop":501,
    "ks:ks_type":"HABITATION",
    "name:eng_x_preferred":[
        "Soso"
    ],
    "wof:name":"Soso",
    "wof:placetype":"locality",
    "wof:population":501
},
  "geometry": {"coordinates":[85.67369600000001,23.333963],"type":"Point"}
}