{
  "type": "Feature",
  "properties": {
    "iso:country":"IN",
    "ks:ks_name":"Neerige",
    "ks:ks_pop":30,
    "ks:ks_type":"HABITATION",
    "name:eng_x_preferred":[
        "Neerige"
    ],
    "wof:name":"Neerige",
    "wof:placetype":"locality",
    "wof:population":30
},
  "geometry": {"coordinates":[74.882569,13.928103],"type":"Point"}
}