{
  "type": "Feature",
  "properties": {
    "gn:admin1_code":"19.0",
    "gn:admin2_code":"571.0",
    "gn:asciiname":"Buddamarenahalli",
    "gn:country_code":"IN",
    "gn:dem":736,
    "gn:feature_class":"P",
    "gn:feature_code":"PPL",
    "gn:name":"Buddam\u0101renahalli",
    "gn:population":0,
    "gn:timezone":"Asia/Kolkata",
    "iso:country":"IN",
    "wof:name":"Buddamarenahalli",
    "wof:placetype":"locality"
},
  "geometry": {"coordinates":[77.31614999999999,13.50645],"type":"Point"}
}