{
  "type": "Feature",
  "properties": {
    "iso:country":"IN",
    "ks:ks_name":"Varikwadi",
    "ks:ks_pop":251,
    "ks:ks_type":"HABITATION",
    "name:eng_x_preferred":[
        "Varikwadi"
    ],
    "wof:name":"Varikwadi",
    "wof:placetype":"locality",
    "wof:population":251
},
  "geometry": {"coordinates":[73.418091,16.440779],"type":"Point"}
}