{
  "type": "Feature",
  "properties": {
    "iso:country":"IN",
    "ks:ks_name":"Kutumsukri",
    "ks:ks_pop":2619,
    "ks:ks_type":"VILLAGE",
    "ks:ks_uagg_main":0,
    "name:eng_x_preferred":[
        "Kutumsukri"
    ],
    "wof:name":"Kutumsukri",
    "wof:placetype":"neighbourhood",
    "wof:population":2619
},
  "geometry": {"coordinates":[85.432671,24.084149],"type":"Point"}
}