{
  "type": "Feature",
  "properties": {
    "gn:admin1_code":"19.0",
    "gn:admin2_code":"584.0",
    "gn:asciiname":"Hoskoti",
    "gn:country_code":"IN",
    "gn:dem":685,
    "gn:feature_class":"P",
    "gn:feature_code":"PPL",
    "gn:name":"Hoskoti",
    "gn:population":0,
    "gn:timezone":"Asia/Kolkata",
    "iso:country":"IN",
    "wof:name":"Hoskoti",
    "wof:placetype":"locality"
},
  "geometry": {"coordinates":[77.53061,12.48382],"type":"Point"}
}