{
  "type": "Feature",
  "properties": {
    "iso:country":"IN",
    "ks:ks_name":"Limoti",
    "ks:ks_pop":571,
    "ks:ks_type":"HABITATION",
    "name:eng_x_preferred":[
        "Limoti"
    ],
    "wof:name":"Limoti",
    "wof:placetype":"locality",
    "wof:population":571
},
  "geometry": {"coordinates":[80.597206,21.878707],"type":"Point"}
}