{
  "type": "Feature",
  "properties": {
    "iso:country":"IN",
    "ks:ks_name":"Kuchilargool II",
    "ks:ks_pop":204,
    "ks:ks_type":"VILLAGE",
    "name:eng_x_preferred":[
        "Kuchilargool II"
    ],
    "wof:name":"Kuchilargool II",
    "wof:placetype":"locality",
    "wof:population":204
},
  "geometry": {"coordinates":[92.498713,24.777683],"type":"Point"}
}