{
  "type": "Feature",
  "properties": {
    "iso:country":"IN",
    "ks:ks_name":"Jutai",
    "ks:ks_pop":175,
    "ks:ks_type":"VILLAGE",
    "name:eng_x_preferred":[
        "Jutai"
    ],
    "wof:name":"Jutai",
    "wof:placetype":"locality",
    "wof:population":175
},
  "geometry": {"coordinates":[78.955209,30.20234],"type":"Point"}
}