{
  "type": "Feature",
  "properties": {
    "iso:country":"IN",
    "ks:ks_name":"K N Podur",
    "ks:ks_pop":526,
    "ks:ks_type":"HABITATION",
    "name:eng_x_preferred":[
        "K N Podur"
    ],
    "wof:name":"K N Podur",
    "wof:placetype":"locality",
    "wof:population":526
},
  "geometry": {"coordinates":[78.100967,12.774949],"type":"Point"}
}