{
  "type": "Feature",
  "properties": {
    "gn:admin1_code":"2.0",
    "gn:admin2_code":"543.0",
    "gn:asciiname":"Rudrapalem",
    "gn:country_code":"IN",
    "gn:dem":82,
    "gn:feature_class":"P",
    "gn:feature_code":"PPL",
    "gn:name":"Rudrap\u0101lem",
    "gn:population":0,
    "gn:timezone":"Asia/Kolkata",
    "iso:country":"IN",
    "ks:ks_name":"Rudrapalem",
    "ks:ks_pop":342,
    "ks:ks_type":"HABITATION",
    "name:eng_x_preferred":[
        "Rudrapalem"
    ],
    "wof:name":"Rudrapalem",
    "wof:placetype":"locality",
    "wof:population":342
},
  "geometry": {"coordinates":[83.286484,18.231508],"type":"Point"}
}