{
  "type": "Feature",
  "properties": {
    "gn:admin1_code":"35",
    "gn:admin2_code":"430.0",
    "gn:asciiname":"Pidariya",
    "gn:country_code":"IN",
    "gn:dem":380,
    "gn:feature_class":"P",
    "gn:feature_code":"PPL",
    "gn:name":"Pidariya",
    "gn:population":0,
    "gn:timezone":"Asia/Kolkata",
    "iso:country":"IN",
    "name:fra_x_preferred":[
        "Pidariya"
    ],
    "name:mai_x_preferred":[
        "\u092a\u0930\u0921\u0940\u092f\u093e"
    ],
    "name:new_x_preferred":[
        "\u092a\u093f\u0921\u093e\u0930\u093f\u092f\u093e"
    ],
    "name:pol_x_preferred":[
        "Pidariya"
    ],
    "wof:name":"Pidariya",
    "wof:placetype":"locality"
},
  "geometry": {"coordinates":[82.03098,24.71502000000001],"type":"Point"}
}