{
  "type": "Feature",
  "properties": {
    "gn:country":"IN",
    "gn:fcode":"PPL",
    "gn:population":0,
    "iso:country":"IN",
    "name:bpy_x_preferred":[
        "\u09aa\u09be\u09b0\u09be\u09ac\u09be\u0987"
    ],
    "name:eng_x_preferred":[
        "Paravai"
    ],
    "name:fra_x_preferred":[
        "Paravai"
    ],
    "name:ita_x_preferred":[
        "Paravai"
    ],
    "name:msa_x_preferred":[
        "Paravai"
    ],
    "name:nan_x_preferred":[
        "Paravai"
    ],
    "name:nld_x_preferred":[
        "Paravai"
    ],
    "name:por_x_preferred":[
        "Paravai"
    ],
    "name:tam_x_preferred":[
        "paravai"
    ],
    "name:und_x_variant":[
        "Chinna Varavani"
    ],
    "name:vie_x_preferred":[
        "Paravai"
    ],
    "name:zho_x_preferred":[
        "\u5e15\u62c9\u74e6\u4f0a"
    ],
    "qs:name":"Paravai",
    "qs:name_adm0":"India",
    "qs:name_adm1":"Tamil Nadu",
    "qs:photos":13,
    "qs:photos_1k":3,
    "qs:photos_9k":1,
    "qs:photos_9r":1,
    "qs:photos_all":13,
    "qs:photos_sr":1,
    "qs:placetype":"Town",
    "qs:pop_sr":"0",
    "wd:wordcount":112,
    "wof:name":"Paravai",
    "wof:placetype":"locality",
    "wof:population":0
},
  "geometry": {"coordinates":[78.78852000000001,9.63213],"type":"Point"}
}