{
  "type": "Feature",
  "properties": {
    "iso:country":"IN",
    "ks:ks_name":"Monirchar Boidergaon",
    "ks:ks_pop":1167,
    "ks:ks_type":"VILLAGE",
    "name:eng_x_preferred":[
        "Monirchar Boidergaon"
    ],
    "wof:name":"Monirchar Boidergaon",
    "wof:placetype":"locality",
    "wof:population":1167
},
  "geometry": {"coordinates":[89.97402700000001,25.86591],"type":"Point"}
}