{
  "type": "Feature",
  "properties": {
    "iso:country":"IN",
    "ks:ks_name":"Chuinposi",
    "ks:ks_pop":546,
    "ks:ks_type":"VILLAGE",
    "name:eng_x_preferred":[
        "Chuinposi"
    ],
    "wof:name":"Chuinposi",
    "wof:placetype":"locality",
    "wof:population":546
},
  "geometry": {"coordinates":[86.47915999999999,21.522247],"type":"Point"}
}