{
  "type": "Feature",
  "properties": {
    "iso:country":"IN",
    "ks:ks_name":"Kinthuda",
    "ks:ks_pop":496,
    "ks:ks_type":"VILLAGE",
    "name:eng_x_preferred":[
        "Kinthuda"
    ],
    "wof:name":"Kinthuda",
    "wof:placetype":"locality",
    "wof:population":496
},
  "geometry": {"coordinates":[83.960043,19.038929],"type":"Point"}
}