{
  "type": "Feature",
  "properties": {
    "gn:admin1_code":"2.0",
    "gn:admin2_code":"554.0",
    "gn:asciiname":"Dumukumakanampalli",
    "gn:country_code":"IN",
    "gn:dem":749,
    "gn:feature_class":"P",
    "gn:feature_code":"PPL",
    "gn:name":"Dumukumakanampalli",
    "gn:population":0,
    "gn:timezone":"Asia/Kolkata",
    "iso:country":"IN",
    "wof:name":"Dumukumakanampalli",
    "wof:placetype":"locality"
},
  "geometry": {"coordinates":[78.39268,12.85694],"type":"Point"}
}