{
  "type": "Feature",
  "properties": {
    "iso:country":"IN",
    "ks:ks_name":"Dadwa",
    "ks:ks_pop":208,
    "ks:ks_type":"HABITATION",
    "ks:ks_uagg_main":0,
    "name:eng_x_preferred":[
        "Dadwa"
    ],
    "wof:name":"Dadwa",
    "wof:placetype":"neighbourhood",
    "wof:population":208
},
  "geometry": {"coordinates":[82.169715,26.601778],"type":"Point"}
}