{
  "type": "Feature",
  "properties": {
    "iso:country":"IN",
    "ks:ks_name":"Sahoowas",
    "ks:ks_pop":132,
    "ks:ks_type":"VILLAGE",
    "name:eng_x_preferred":[
        "Sahoowas"
    ],
    "wof:name":"Sahoowas",
    "wof:placetype":"locality",
    "wof:population":132
},
  "geometry": {"coordinates":[76.71544400000001,27.860656],"type":"Point"}
}