{
  "type": "Feature",
  "properties": {
    "iso:country":"IN",
    "ks:ks_name":"Poha Bhata",
    "ks:ks_pop":65,
    "ks:ks_type":"HABITATION",
    "name:eng_x_preferred":[
        "Poha Bhata"
    ],
    "wof:name":"Poha Bhata",
    "wof:placetype":"locality",
    "wof:population":65
},
  "geometry": {"coordinates":[78.77463400000001,25.329304],"type":"Point"}
}