{
  "type": "Feature",
  "properties": {
    "gn:admin1_code":"36",
    "gn:admin2_code":"154.0",
    "gn:asciiname":"Kharahra",
    "gn:country_code":"IN",
    "gn:dem":122,
    "gn:feature_class":"P",
    "gn:feature_code":"PPL",
    "gn:name":"Kharahra",
    "gn:population":0,
    "gn:timezone":"Asia/Kolkata",
    "iso:country":"IN",
    "wof:name":"Kharahra",
    "wof:placetype":"neighbourhood"
},
  "geometry": {"coordinates":[81.21362999999999,27.3346],"type":"Point"}
}