{
  "type": "Feature",
  "properties": {
    "gn:admin1_code":"11.0",
    "gn:admin2_code":"33.0",
    "gn:asciiname":"Patsaribasa",
    "gn:country_code":"IN",
    "gn:dem":1435,
    "gn:feature_class":"P",
    "gn:feature_code":"PPL",
    "gn:name":"Pats\u0101rib\u0101sa",
    "gn:population":0,
    "gn:timezone":"Asia/Kolkata",
    "iso:country":"IN",
    "wof:name":"Patsaribasa",
    "wof:placetype":"locality"
},
  "geometry": {"coordinates":[77.73788,31.15403],"type":"Point"}
}