{
  "type": "Feature",
  "properties": {
    "iso:country":"IN",
    "ks:ks_name":"Baharar",
    "ks:ks_pop":1396,
    "ks:ks_type":"VILLAGE",
    "ks:ks_uagg_main":0,
    "name:eng_x_preferred":[
        "Baharar"
    ],
    "wof:name":"Baharar",
    "wof:placetype":"neighbourhood",
    "wof:population":1396
},
  "geometry": {"coordinates":[83.757482,25.823245],"type":"Point"}
}