{
  "type": "Feature",
  "properties": {
    "gn:country":"IN",
    "gn:fcode":"PPL",
    "gn:pop":46788,
    "iso:country":"IN",
    "name:ben_x_preferred":[
        "\u09ab\u09be\u09b2\u09cb\u09a6\u09bf"
    ],
    "name:bpy_x_preferred":[
        "\u09ab\u09be\u09b2\u09cb\u09a6\u09bf"
    ],
    "name:bul_x_preferred":[
        "\u041f\u0445\u0430\u043b\u043e\u0434\u0438"
    ],
    "name:chi_x_preferred":[
        "\u5e15\u6d1b\u8fea"
    ],
    "name:dut_x_preferred":[
        "Phalodi"
    ],
    "name:eng_x_preferred":[
        "Phalodi"
    ],
    "name:fre_x_preferred":[
        "Phalodi"
    ],
    "name:ger_x_preferred":[
        "Phalodi"
    ],
    "name:guj_x_preferred":[
        "\u0aab\u0ab2\u0acb\u0aa6\u0ac0"
    ],
    "name:hin_x_preferred":[
        "\u092b\u0932\u094b\u0926\u0940"
    ],
    "name:ita_x_preferred":[
        "Phalodi"
    ],
    "name:jpn_x_preferred":[
        "\u30d5\u30a1\u30ed\u30fc\u30c7\u30a3"
    ],
    "name:kan_x_preferred":[
        "\u0cab\u0cb2\u0ccb\u0ca6\u0cbf"
    ],
    "name:kor_x_preferred":[
        "\ud314\ub85c\ub514"
    ],
    "name:may_x_preferred":[
        "Phalodi"
    ],
    "name:mlg_x_preferred":[
        "Phalodi"
    ],
    "name:ori_x_preferred":[
        "\u0b2b\u0b3e\u0b32\u0b4b\u0b21\u0b3c\u0b3f"
    ],
    "name:por_x_preferred":[
        "Phalodi"
    ],
    "name:rus_x_preferred":[
        "\u041f\u0445\u0430\u043b\u043e\u0434\u0438"
    ],
    "name:spa_x_preferred":[
        "Phalodi"
    ],
    "name:swe_x_preferred":[
        "Phalodi"
    ],
    "name:tam_x_preferred":[
        "\u0baa\u0bbe\u0bb2\u0bcb\u0b9f\u0bbf"
    ],
    "name:tel_x_preferred":[
        "\u0c2b\u0c32\u0c4b\u0c21\u0c3f"
    ],
    "name:urd_x_preferred":[
        "\u067e\u06be\u0627\u0644\u0648\u062f\u06cc"
    ],
    "name:vie_x_preferred":[
        "Phalodi"
    ],
    "qs:name":"Phalodi",
    "qs:photos_9r":0,
    "qs:photos_sr":0,
    "qs:pop_sr":"7",
    "wd:wordcount":968,
    "wof:name":"Phalodi",
    "wof:placetype":"locality",
    "wof:population":46788
},
  "geometry": {"coordinates":[72.36826000000001,27.13102],"type":"Point"}
}