{
  "type": "Feature",
  "properties": {
    "iso:country":"IN",
    "ks:ks_name":"Doodhiya Talab",
    "ks:ks_pop":584,
    "ks:ks_type":"HABITATION",
    "name:eng_x_preferred":[
        "Doodhiya Talab"
    ],
    "wof:name":"Doodhiya Talab",
    "wof:placetype":"locality",
    "wof:population":584
},
  "geometry": {"coordinates":[74.82698000000001,23.714696],"type":"Point"}
}