{
  "type": "Feature",
  "properties": {
    "iso:country":"IN",
    "ks:ks_name":"Baitwadi",
    "ks:ks_pop":160,
    "ks:ks_type":"HABITATION",
    "name:eng_x_preferred":[
        "Baitwadi"
    ],
    "wof:name":"Baitwadi",
    "wof:placetype":"locality",
    "wof:population":160
},
  "geometry": {"coordinates":[73.51777800000001,17.022778],"type":"Point"}
}