{
  "type": "Feature",
  "properties": {
    "iso:country":"IN",
    "ks:ks_name":"Jashara",
    "ks:ks_pop":328,
    "ks:ks_type":"VILLAGE",
    "ks:ks_uagg_main":0,
    "name:eng_x_preferred":[
        "Jashara"
    ],
    "wof:name":"Jashara",
    "wof:placetype":"neighbourhood",
    "wof:population":328
},
  "geometry": {"coordinates":[87.72364,22.488081],"type":"Point"}
}