{
  "type": "Feature",
  "properties": {
    "gn:admin1_code":"35.0",
    "gn:admin2_code":"420",
    "gn:asciiname":"Nawalpura",
    "gn:country_code":"IN",
    "gn:dem":149,
    "gn:feature_class":"P",
    "gn:feature_code":"PPL",
    "gn:name":"Nawalpura",
    "gn:population":0,
    "gn:timezone":"Asia/Kolkata",
    "iso:country":"IN",
    "wof:name":"Nawalpura",
    "wof:placetype":"locality"
},
  "geometry": {"coordinates":[79.01098,26.35177],"type":"Point"}
}