{
  "type": "Feature",
  "properties": {
    "gn:admin1_code":"35.0",
    "gn:admin2_code":"420",
    "gn:asciiname":"Nawalpura",
    "gn:country_code":"IN",
    "gn:dem":149,
    "gn:feature_class":"P",
    "gn:feature_code":"PPL",
    "gn:name":"Nawalpura",
    "gn:population":0,
    "gn:timezone":"Asia/Kolkata",
    "iso:country":"IN",
    "ks:ks_name":"Nawal Pura",
    "ks:ks_pop":401,
    "ks:ks_type":"HABITATION",
    "name:eng_x_preferred":[
        "Nawal Pura"
    ],
    "name:eng_x_variant":[
        "Nawalpura"
    ],
    "wof:name":"Nawal Pura",
    "wof:placetype":"locality",
    "wof:population":401
},
  "geometry": {"coordinates":[79.012536,26.351211],"type":"Point"}
}