{
  "type": "Feature",
  "properties": {
    "iso:country":"IN",
    "ks:ks_name":"Bhelampur Reserved Forest",
    "ks:ks_type":"VILLAGE",
    "name:eng_x_preferred":[
        "Bhelampur Reserved Forest"
    ],
    "wof:name":"Bhelampur Reserved Forest",
    "wof:placetype":"locality"
},
  "geometry": {"coordinates":[83.41233699999999,26.95008],"type":"Point"}
}