{
  "type": "Feature",
  "properties": {
    "iso:country":"IN",
    "ks:ks_name":"Chhatakhama",
    "ks:ks_pop":12,
    "ks:ks_type":"VILLAGE",
    "name:eng_x_preferred":[
        "Chhatakhama"
    ],
    "wof:name":"Chhatakhama",
    "wof:placetype":"locality",
    "wof:population":12
},
  "geometry": {"coordinates":[85.839562,20.917743],"type":"Point"}
}