{
  "type": "Feature",
  "properties": {
    "gn:admin1_code":"12.0",
    "gn:admin2_code":"1.0",
    "gn:asciiname":"Gund Baihk",
    "gn:country_code":"IN",
    "gn:dem":1704,
    "gn:feature_class":"P",
    "gn:feature_code":"PPL",
    "gn:name":"Gund Baihk",
    "gn:population":0,
    "gn:timezone":"Asia/Kolkata",
    "iso:country":"IN",
    "wof:name":"Gund Baihk",
    "wof:placetype":"locality"
},
  "geometry": {"coordinates":[74.32082,34.55687],"type":"Point"}
}