{
  "type": "Feature",
  "properties": {
    "iso:country":"IN",
    "ks:ks_alt_nam":"chamaranpurwa",
    "ks:ks_name":"Chamaranpurwa",
    "ks:ks_pop":81,
    "ks:ks_type":"HABITATION",
    "name:eng_x_preferred":[
        "Chamaranpurwa"
    ],
    "wof:name":"Chamaranpurwa",
    "wof:placetype":"locality",
    "wof:population":81
},
  "geometry": {"coordinates":[81.875282,27.447393],"type":"Point"}
}