{
  "type": "Feature",
  "properties": {
    "iso:country":"IN",
    "ks:ks_alt_nam":"Mandal tola",
    "ks:ks_name":"Mandal Tola",
    "ks:ks_pop":310,
    "ks:ks_type":"HABITATION",
    "name:eng_x_preferred":[
        "Mandal Tola"
    ],
    "wof:name":"Mandal Tola",
    "wof:placetype":"locality",
    "wof:population":310
},
  "geometry": {"coordinates":[86.902067,25.173733],"type":"Point"}
}