{
  "type": "Feature",
  "properties": {
    "gn:admin1_code":"37",
    "gn:admin2_code":"406.0",
    "gn:asciiname":"Murmur",
    "gn:country_code":"IN",
    "gn:dem":612,
    "gn:feature_class":"P",
    "gn:feature_code":"PPL",
    "gn:name":"Murmur",
    "gn:population":0,
    "gn:timezone":"Asia/Kolkata",
    "iso:country":"IN",
    "ks:ks_name":"Murmur",
    "ks:ks_pop":2057,
    "ks:ks_type":"VILLAGE",
    "name:ara_x_preferred":[
        "\u0646\u0641\u062e\u0629"
    ],
    "name:ces_x_preferred":[
        "Murmur"
    ],
    "name:dan_x_preferred":[
        "Murmur"
    ],
    "name:eng_x_preferred":[
        "Murmur"
    ],
    "name:est_x_preferred":[
        "Murmur"
    ],
    "name:ita_x_preferred":[
        "Murmur"
    ],
    "name:pol_x_preferred":[
        "Murmur"
    ],
    "name:por_x_preferred":[
        "Murmur"
    ],
    "wof:name":"Murmur",
    "wof:placetype":"locality",
    "wof:population":2057
},
  "geometry": {"coordinates":[82.083977,22.698748],"type":"Point"}
}