{
  "type": "Feature",
  "properties": {
    "iso:country":"IN",
    "ks:ks_name":"Mudugudiselathanda",
    "ks:ks_pop":91,
    "ks:ks_type":"HABITATION",
    "name:eng_x_preferred":[
        "Mudugudiselathanda"
    ],
    "wof:name":"Mudugudiselathanda",
    "wof:placetype":"locality",
    "wof:population":91
},
  "geometry": {"coordinates":[78.38281000000001,18.652741],"type":"Point"}
}