{
  "type": "Feature",
  "properties": {
    "iso:country":"IN",
    "ks:ks_name":"Chatiya Mal.",
    "ks:ks_pop":299,
    "ks:ks_type":"VILLAGE",
    "name:eng_x_preferred":[
        "Chatiya Mal."
    ],
    "wof:name":"Chatiya Mal.",
    "wof:placetype":"locality",
    "wof:population":299
},
  "geometry": {"coordinates":[80.98491199999999,23.067231],"type":"Point"}
}