{
  "type": "Feature",
  "properties": {
    "iso:country":"IN",
    "ks:ks_name":"Mudapara",
    "ks:ks_pop":168,
    "ks:ks_type":"HABITATION",
    "name:eng_x_preferred":[
        "Mudapara"
    ],
    "wof:name":"Mudapara",
    "wof:placetype":"locality",
    "wof:population":168
},
  "geometry": {"coordinates":[81.78841199999999,18.924676],"type":"Point"}
}