{
  "type": "Feature",
  "properties": {
    "gn:admin1_code":"36.0",
    "gn:admin2_code":"188.0",
    "gn:asciiname":"Konrar Tiwari",
    "gn:country_code":"IN",
    "gn:dem":70,
    "gn:feature_class":"P",
    "gn:feature_code":"PPL",
    "gn:name":"Konr\u0101r Tiw\u0101ri",
    "gn:population":0,
    "gn:timezone":"Asia/Kolkata",
    "iso:country":"IN",
    "wof:name":"Konrar Tiwari",
    "wof:placetype":"locality"
},
  "geometry": {"coordinates":[83.55873000000003,26.34771],"type":"Point"}
}