{
  "type": "Feature",
  "properties": {
    "iso:country":"IN",
    "ks:ks_name":"Kevalapur",
    "ks:ks_pop":84,
    "ks:ks_type":"VILLAGE",
    "name:eng_x_preferred":[
        "Kevalapur"
    ],
    "wof:name":"Kevalapur",
    "wof:placetype":"locality",
    "wof:population":84
},
  "geometry": {"coordinates":[82.534046,25.461207],"type":"Point"}
}