{
  "type": "Feature",
  "properties": {
    "iso:country":"IN",
    "ks:ks_name":"Muttakeri",
    "ks:ks_pop":189,
    "ks:ks_type":"HABITATION",
    "name:eng_x_preferred":[
        "Muttakeri"
    ],
    "wof:name":"Muttakeri",
    "wof:placetype":"locality",
    "wof:population":189
},
  "geometry": {"coordinates":[74.52845499999999,14.303206],"type":"Point"}
}