{
  "type": "Feature",
  "properties": {
    "iso:country":"IN",
    "ks:ks_alt_nam":"Adhl\u0101r",
    "ks:ks_name":"Adhlar",
    "ks:ks_pop":270,
    "ks:ks_type":"VILLAGE",
    "ks:ks_uagg_main":0,
    "name:eng_x_preferred":[
        "Adhlar"
    ],
    "name:eng_x_variant":[
        "Adhl\u0101r"
    ],
    "wof:name":"Adhlar",
    "wof:placetype":"neighbourhood",
    "wof:population":270
},
  "geometry": {"coordinates":[86.31101200000001,25.892827],"type":"Point"}
}