{
  "type": "Feature",
  "properties": {
    "gn:admin1_code":"34.0",
    "gn:admin2_code":"219.0",
    "gn:asciiname":"Langarpura",
    "gn:country_code":"IN",
    "gn:dem":58,
    "gn:feature_class":"P",
    "gn:feature_code":"PPL",
    "gn:name":"Langarpura",
    "gn:population":0,
    "gn:timezone":"Asia/Kolkata",
    "iso:country":"IN",
    "ks:ks_name":"Langarpura",
    "ks:ks_pop":1608,
    "ks:ks_type":"VILLAGE",
    "name:eng_x_preferred":[
        "Langarpura"
    ],
    "wof:name":"Langarpura",
    "wof:placetype":"locality",
    "wof:population":1608
},
  "geometry": {"coordinates":[84.959692,25.891358],"type":"Point"}
}