{
  "type": "Feature",
  "properties": {
    "gn:admin1_code":"19.0",
    "gn:admin2_code":"564.0",
    "gn:asciiname":"Bailval",
    "gn:country_code":"IN",
    "gn:dem":597,
    "gn:feature_class":"P",
    "gn:feature_code":"PPL",
    "gn:name":"Bailv\u0101l",
    "gn:population":0,
    "gn:timezone":"Asia/Kolkata",
    "iso:country":"IN",
    "ks:ks_name":"Bailwal",
    "ks:ks_pop":1308,
    "ks:ks_type":"VILLAGE",
    "name:eng_x_preferred":[
        "Bailwal"
    ],
    "name:eng_x_variant":[
        "Bailval"
    ],
    "wof:name":"Bailwal",
    "wof:placetype":"locality",
    "wof:population":1308
},
  "geometry": {"coordinates":[75.109488,14.881387],"type":"Point"}
}