{
  "type": "Feature",
  "properties": {
    "gn:admin1_code":"37.0",
    "gn:admin2_code":"416.0",
    "gn:asciiname":"Chinna Bodkel",
    "gn:country_code":"IN",
    "gn:dem":164,
    "gn:feature_class":"P",
    "gn:feature_code":"PPL",
    "gn:name":"Chinna Bodkel",
    "gn:population":0,
    "gn:timezone":"Asia/Kolkata",
    "iso:country":"IN",
    "ks:ks_name":"Chinnabodkel",
    "ks:ks_pop":184,
    "ks:ks_type":"VILLAGE",
    "name:eng_x_preferred":[
        "Chinnabodkel"
    ],
    "name:eng_x_variant":[
        "Chinna Bodkel"
    ],
    "wof:name":"Chinnabodkel",
    "wof:placetype":"locality",
    "wof:population":184
},
  "geometry": {"coordinates":[81.058458,18.352728],"type":"Point"}
}