{
  "type": "Feature",
  "properties": {
    "iso:country":"IN",
    "ks:ks_name":"Amodghata",
    "ks:ks_pop":6865,
    "ks:ks_type":"VILLAGE",
    "ks:ks_uagg_main":0,
    "name:eng_x_preferred":[
        "Amodghata"
    ],
    "wof:name":"Amodghata",
    "wof:placetype":"locality",
    "wof:population":6865
},
  "geometry": {"coordinates":[88.379927,22.985511],"type":"Point"}
}