{
  "type": "Feature",
  "properties": {
    "iso:country":"IN",
    "ks:ks_name":"Thotakurapalem",
    "ks:ks_pop":241,
    "ks:ks_type":"HABITATION",
    "name:eng_x_preferred":[
        "Thotakurapalem"
    ],
    "wof:name":"Thotakurapalem",
    "wof:placetype":"locality",
    "wof:population":241
},
  "geometry": {"coordinates":[81.98860999999999,17.625272],"type":"Point"}
}