{
  "type": "Feature",
  "properties": {
    "iso:country":"IN",
    "ks:ks_name":"Budania Ki Dhani",
    "ks:ks_pop":20,
    "ks:ks_type":"HABITATION",
    "name:eng_x_preferred":[
        "Budania Ki Dhani"
    ],
    "wof:name":"Budania Ki Dhani",
    "wof:placetype":"locality",
    "wof:population":20
},
  "geometry": {"coordinates":[75.327361,28.226],"type":"Point"}
}