{
  "type": "Feature",
  "properties": {
    "gn:admin1_code":"36",
    "gn:admin2_code":"191.0",
    "gn:asciiname":"Dakhingawan",
    "gn:country_code":"IN",
    "gn:dem":86,
    "gn:feature_class":"P",
    "gn:feature_code":"PPL",
    "gn:name":"Dakhingaw\u0101n",
    "gn:population":0,
    "gn:timezone":"Asia/Kolkata",
    "iso:country":"IN",
    "ks:ks_alt_nam":"Dakhingaw\u0101n",
    "ks:ks_name":"Dakhingawan",
    "ks:ks_type":"VILLAGE",
    "ks:ks_uagg_main":0,
    "name:eng_x_preferred":[
        "Dakhingawan"
    ],
    "name:eng_x_variant":[
        "Dakhingaw\u0101n"
    ],
    "wof:name":"Dakhingawan",
    "wof:placetype":"neighbourhood"
},
  "geometry": {"coordinates":[82.80734699999999,26.119428],"type":"Point"}
}