{
  "type": "Feature",
  "properties": {
    "gn:admin1_code":"38.0",
    "gn:admin2_code":"358.0",
    "gn:asciiname":"Khaira",
    "gn:country_code":"IN",
    "gn:dem":341,
    "gn:feature_class":"P",
    "gn:feature_code":"PPL",
    "gn:name":"Khaira",
    "gn:population":0,
    "gn:timezone":"Asia/Kolkata",
    "iso:country":"IN",
    "ks:ks_name":"Khaira",
    "ks:ks_pop":156,
    "ks:ks_type":"VILLAGE",
    "name:eng_x_preferred":[
        "Khaira"
    ],
    "name:hin_x_preferred":[
        "\u0916\u0948\u0930\u093e"
    ],
    "name:new_x_preferred":[
        "\u0916\u0948\u0930\u093e"
    ],
    "wof:name":"Khaira",
    "wof:placetype":"locality",
    "wof:population":156
},
  "geometry": {"coordinates":[84.42040900000001,24.21765],"type":"Point"}
}