{
  "type": "Feature",
  "properties": {
    "gn:admin1_code":"24.0",
    "gn:admin2_code":"125",
    "gn:asciiname":"Arthuna",
    "gn:country_code":"IN",
    "gn:dem":156,
    "gn:feature_class":"P",
    "gn:feature_code":"PPL",
    "gn:name":"Arthuna",
    "gn:population":0,
    "gn:timezone":"Asia/Kolkata",
    "iso:country":"IN",
    "name:hin_x_preferred":[
        "\u0905\u0930\u0925\u0941\u0928\u093e"
    ],
    "wof:name":"Arthuna",
    "wof:placetype":"neighbourhood"
},
  "geometry": {"coordinates":[74.09609,23.49954],"type":"Point"}
}