{
  "type": "Feature",
  "properties": {
    "gn:admin1_code":"10.0",
    "gn:admin2_code":"70.0",
    "gn:asciiname":"Salawala",
    "gn:country_code":"IN",
    "gn:dem":306,
    "gn:feature_class":"P",
    "gn:feature_code":"PPL",
    "gn:name":"Sal\u0101w\u0101la",
    "gn:population":0,
    "gn:timezone":"Asia/Kolkata",
    "iso:country":"IN",
    "wof:name":"Salawala",
    "wof:placetype":"locality"
},
  "geometry": {"coordinates":[77.05840999999999,30.41605],"type":"Point"}
}