{
  "type": "Feature",
  "properties": {
    "iso:country":"IN",
    "ks:ks_alt_nam":"BARKHANDI",
    "ks:ks_name":"Barkhandi",
    "ks:ks_pop":95,
    "ks:ks_type":"HABITATION",
    "ks:ks_uagg_main":0,
    "name:eng_x_preferred":[
        "Barkhandi"
    ],
    "wof:name":"Barkhandi",
    "wof:placetype":"neighbourhood",
    "wof:population":95
},
  "geometry": {"coordinates":[86.440896,25.474129],"type":"Point"}
}