{
  "type": "Feature",
  "properties": {
    "iso:country":"IN",
    "ks:ks_name":"Harizan Tola",
    "ks:ks_pop":62,
    "ks:ks_type":"HABITATION",
    "name:eng_x_preferred":[
        "Harizan Tola"
    ],
    "wof:name":"Harizan Tola",
    "wof:placetype":"locality",
    "wof:population":62
},
  "geometry": {"coordinates":[84.146863,26.614638],"type":"Point"}
}