{
  "type": "Feature",
  "properties": {
    "gn:admin1_code":"25.0",
    "gn:admin2_code":"608.0",
    "gn:asciiname":"Tirumalur",
    "gn:country_code":"IN",
    "gn:dem":247,
    "gn:feature_class":"P",
    "gn:feature_code":"PPL",
    "gn:name":"Tirum\u0101l\u016br",
    "gn:population":0,
    "gn:timezone":"Asia/Kolkata",
    "iso:country":"IN",
    "ks:ks_name":"Thirumalur",
    "ks:ks_pop":720,
    "ks:ks_type":"HABITATION",
    "name:eng_x_preferred":[
        "Thirumalur"
    ],
    "name:eng_x_variant":[
        "Tirumalur"
    ],
    "wof:name":"Thirumalur",
    "wof:placetype":"locality",
    "wof:population":720
},
  "geometry": {"coordinates":[77.878204,11.654818],"type":"Point"}
}