{
  "type": "Feature",
  "properties": {
    "iso:country":"IN",
    "ks:ks_name":"Palada",
    "ks:ks_pop":2831,
    "ks:ks_type":"VILLAGE",
    "name:eng_x_preferred":[
        "Palada"
    ],
    "wof:name":"Palada",
    "wof:placetype":"locality",
    "wof:population":2831
},
  "geometry": {"coordinates":[86.40104700000001,20.826948],"type":"Point"}
}