{
  "type": "Feature",
  "properties": {
    "gn:admin1_code":"17",
    "gn:admin2_code":"274.0",
    "gn:asciiname":"Munpi",
    "gn:country_code":"IN",
    "gn:dem":1248,
    "gn:feature_class":"P",
    "gn:feature_code":"PPL",
    "gn:name":"Munpi",
    "gn:population":0,
    "gn:timezone":"Asia/Kolkata",
    "iso:country":"IN",
    "wof:name":"Munpi",
    "wof:placetype":"locality"
},
  "geometry": {"coordinates":[93.50826000000001,24.32025],"type":"Point"}
}