{
  "type": "Feature",
  "properties": {
    "iso:country":"IN",
    "ks:ks_name":"Kalibagwasti",
    "ks:ks_pop":803,
    "ks:ks_type":"HABITATION",
    "name:eng_x_preferred":[
        "Kalibagwasti"
    ],
    "wof:name":"Kalibagwasti",
    "wof:placetype":"locality",
    "wof:population":803
},
  "geometry": {"coordinates":[75.51652799999999,17.444529],"type":"Point"}
}