{
  "type": "Feature",
  "properties": {
    "iso:country":"IN",
    "ks:ks_name":"Kalamanekeri",
    "ks:ks_pop":84,
    "ks:ks_type":"HABITATION",
    "name:eng_x_preferred":[
        "Kalamanekeri"
    ],
    "wof:name":"Kalamanekeri",
    "wof:placetype":"locality",
    "wof:population":84
},
  "geometry": {"coordinates":[74.54266200000001,14.247402],"type":"Point"}
}