{
  "type": "Feature",
  "properties": {
    "gn:admin1_code":"36.0",
    "gn:admin2_code":"182.0",
    "gn:asciiname":"Motinagar",
    "gn:country_code":"IN",
    "gn:dem":106,
    "gn:feature_class":"P",
    "gn:feature_code":"PPL",
    "gn:name":"Mot\u012bnagar",
    "gn:population":0,
    "gn:timezone":"Asia/Kolkata",
    "iso:country":"IN",
    "ks:ks_alt_nam":"Mot\u012bnagar",
    "ks:ks_name":"Motinagar",
    "ks:ks_pop":1126,
    "ks:ks_type":"VILLAGE",
    "ks:ks_uagg_main":0,
    "name:eng_x_preferred":[
        "Motinagar"
    ],
    "name:eng_x_variant":[
        "Mot\u012bnagar"
    ],
    "name:und_x_variant":[
        "Mot\u012bnagar",
        "Moti D\u012bh"
    ],
    "wof:name":"Motinagar",
    "wof:placetype":"neighbourhood",
    "wof:population":1126
},
  "geometry": {"coordinates":[82.662993,27.501737],"type":"Point"}
}