{
  "type": "Feature",
  "properties": {
    "iso:country":"IN",
    "ks:ks_name":"Karanjdi",
    "ks:ks_pop":538,
    "ks:ks_type":"VILLAGE",
    "name:eng_x_preferred":[
        "Karanjdi"
    ],
    "wof:name":"Karanjdi",
    "wof:placetype":"locality",
    "wof:population":538
},
  "geometry": {"coordinates":[73.859216,20.781475],"type":"Point"}
}