{
  "type": "Feature",
  "properties": {
    "iso:country":"IN",
    "ks:ks_name":"Bettupuram",
    "ks:ks_pop":66,
    "ks:ks_type":"HABITATION",
    "name:eng_x_preferred":[
        "Bettupuram"
    ],
    "wof:name":"Bettupuram",
    "wof:placetype":"locality",
    "wof:population":66
},
  "geometry": {"coordinates":[83.7985,18.644083],"type":"Point"}
}