{
  "type": "Feature",
  "properties": {
    "iso:country":"IN",
    "ks:ks_name":"Ganpatichiwadi",
    "ks:ks_pop":104,
    "ks:ks_type":"HABITATION",
    "name:eng_x_preferred":[
        "Ganpatichiwadi"
    ],
    "wof:name":"Ganpatichiwadi",
    "wof:placetype":"locality",
    "wof:population":104
},
  "geometry": {"coordinates":[73.706823,16.296825],"type":"Point"}
}