{
  "type": "Feature",
  "properties": {
    "gn:admin1_code":"2.0",
    "gn:admin2_code":"551.0",
    "gn:asciiname":"Jotivaripalle",
    "gn:country_code":"IN",
    "gn:dem":185,
    "gn:feature_class":"P",
    "gn:feature_code":"PPL",
    "gn:name":"Jotiv\u0101ripalle",
    "gn:population":0,
    "gn:timezone":"Asia/Kolkata",
    "iso:country":"IN",
    "wof:name":"Jotivaripalle",
    "wof:placetype":"locality"
},
  "geometry": {"coordinates":[78.99387,15.03785],"type":"Point"}
}