{
  "type": "Feature",
  "properties": {
    "iso:country":"IN",
    "ks:ks_name":"Lonthar",
    "ks:ks_pop":88,
    "ks:ks_type":"VILLAGE",
    "ks:ks_uagg_main":0,
    "name:eng_x_preferred":[
        "Lonthar"
    ],
    "wof:name":"Lonthar",
    "wof:placetype":"neighbourhood",
    "wof:population":88
},
  "geometry": {"coordinates":[78.563737,30.320113],"type":"Point"}
}