{
  "type": "Feature",
  "properties": {
    "gn:admin1_code":"13.0",
    "gn:admin2_code":"600.0",
    "gn:asciiname":"Padirikkal",
    "gn:country_code":"IN",
    "gn:dem":22,
    "gn:feature_class":"P",
    "gn:feature_code":"PPL",
    "gn:name":"P\u0101dirikkal",
    "gn:population":0,
    "gn:timezone":"Asia/Kolkata",
    "iso:country":"IN",
    "wof:name":"Padirikkal",
    "wof:placetype":"locality"
},
  "geometry": {"coordinates":[76.61673,9.11425],"type":"Point"}
}