{
  "type": "Feature",
  "properties": {
    "gn:admin1_code":"36.0",
    "gn:admin2_code":"138.0",
    "gn:asciiname":"Jataula",
    "gn:country_code":"IN",
    "gn:dem":226,
    "gn:feature_class":"P",
    "gn:feature_code":"PPL",
    "gn:name":"Jataula",
    "gn:population":0,
    "gn:timezone":"Asia/Kolkata",
    "iso:country":"IN",
    "ks:ks_name":"Jataula",
    "ks:ks_pop":1256,
    "ks:ks_type":"VILLAGE",
    "ks:ks_uagg_main":0,
    "name:eng_x_preferred":[
        "Jataula"
    ],
    "wof:name":"Jataula",
    "wof:placetype":"neighbourhood",
    "wof:population":1256
},
  "geometry": {"coordinates":[77.474305,29.055281],"type":"Point"}
}