{
  "type": "Feature",
  "properties": {
    "iso:country":"IN",
    "ks:ks_name":"Rampura Asangaon",
    "ks:ks_pop":451,
    "ks:ks_type":"HABITATION",
    "name:eng_x_preferred":[
        "Rampura Asangaon"
    ],
    "wof:name":"Rampura Asangaon",
    "wof:placetype":"locality",
    "wof:population":451
},
  "geometry": {"coordinates":[75.574916,21.899821],"type":"Point"}
}