{
  "type": "Feature",
  "properties": {
    "iso:country":"IN",
    "ks:ks_name":"Lahangepada",
    "ks:ks_pop":145,
    "ks:ks_type":"HABITATION",
    "name:eng_x_preferred":[
        "Lahangepada"
    ],
    "wof:name":"Lahangepada",
    "wof:placetype":"locality",
    "wof:population":145
},
  "geometry": {"coordinates":[72.840165,19.888155],"type":"Point"}
}