{
  "type": "Feature",
  "properties": {
    "iso:country":"IN",
    "ks:ks_name":"1 DM",
    "ks:ks_pop":56,
    "ks:ks_type":"VILLAGE",
    "name:eng_x_preferred":[
        "1 DM"
    ],
    "wof:name":"1 DM",
    "wof:placetype":"locality",
    "wof:population":56
},
  "geometry": {"coordinates":[73.364722,29.043611],"type":"Point"}
}