{
  "type": "Feature",
  "properties": {
    "gn:admin1_code":"11",
    "gn:admin2_code":"24.0",
    "gn:asciiname":"Nauri Uparli",
    "gn:country_code":"IN",
    "gn:dem":1044,
    "gn:feature_class":"P",
    "gn:feature_code":"PPL",
    "gn:name":"Nauri Uparli",
    "gn:population":0,
    "gn:timezone":"Asia/Kolkata",
    "iso:country":"IN",
    "wof:name":"Nauri Uparli",
    "wof:placetype":"locality"
},
  "geometry": {"coordinates":[76.60356,32.06409],"type":"Point"}
}