{
  "type": "Feature",
  "properties": {
    "iso:country":"IN",
    "ks:ks_name":"Badimamidilanka",
    "ks:ks_pop":24,
    "ks:ks_type":"HABITATION",
    "name:eng_x_preferred":[
        "Badimamidilanka"
    ],
    "wof:name":"Badimamidilanka",
    "wof:placetype":"locality",
    "wof:population":24
},
  "geometry": {"coordinates":[81.888768,17.771677],"type":"Point"}
}