{
  "type": "Feature",
  "properties": {
    "iso:country":"IN",
    "ks:ks_name":"Bhaktanpur",
    "ks:ks_pop":61,
    "ks:ks_type":"HABITATION",
    "name:eng_x_preferred":[
        "Bhaktanpur"
    ],
    "wof:name":"Bhaktanpur",
    "wof:placetype":"locality",
    "wof:population":61
},
  "geometry": {"coordinates":[80.83555200000001,27.372233],"type":"Point"}
}