{
  "type": "Feature",
  "properties": {
    "iso:country":"IN",
    "ks:ks_name":"Vamaniya Wara",
    "ks:ks_pop":1186,
    "ks:ks_type":"HABITATION",
    "name:eng_x_preferred":[
        "Vamaniya Wara"
    ],
    "wof:name":"Vamaniya Wara",
    "wof:placetype":"locality",
    "wof:population":1186
},
  "geometry": {"coordinates":[73.95666199999999,23.488063],"type":"Point"}
}