{
  "type": "Feature",
  "properties": {
    "gn:admin1_code":"37",
    "gn:admin2_code":"409.0",
    "gn:asciiname":"Kuagaon",
    "gn:country_code":"IN",
    "gn:dem":320,
    "gn:feature_class":"P",
    "gn:feature_code":"PPL",
    "gn:name":"K\u016b\u0101gaon",
    "gn:population":0,
    "gn:timezone":"Asia/Kolkata",
    "iso:country":"IN",
    "wof:name":"Kuagaon",
    "wof:placetype":"locality"
},
  "geometry": {"coordinates":[80.98774,20.93561],"type":"Point"}
}