{
  "type": "Feature",
  "properties": {
    "iso:country":"IN",
    "ks:ks_name":"Tal Badohi",
    "ks:ks_pop":0,
    "ks:ks_type":"VILLAGE",
    "name:eng_x_preferred":[
        "Tal Badohi"
    ],
    "wof:name":"Tal Badohi",
    "wof:placetype":"locality",
    "wof:population":0
},
  "geometry": {"coordinates":[83.472902,26.423673],"type":"Point"}
}