{
  "type": "Feature",
  "properties": {
    "iso:country":"IN",
    "ks:ks_name":"Mankatena",
    "ks:ks_pop":231,
    "ks:ks_type":"HABITATION",
    "name:eng_x_preferred":[
        "Mankatena"
    ],
    "wof:name":"Mankatena",
    "wof:placetype":"locality",
    "wof:population":231
},
  "geometry": {"coordinates":[81.647907,27.92241],"type":"Point"}
}