{
  "type": "Feature",
  "properties": {
    "iso:country":"IN",
    "ks:ks_name":"Baralisia",
    "ks:ks_pop":1319,
    "ks:ks_type":"VILLAGE",
    "name:eng_x_preferred":[
        "Baralisia"
    ],
    "wof:name":"Baralisia",
    "wof:placetype":"locality",
    "wof:population":1319
},
  "geometry": {"coordinates":[85.735398,22.38678],"type":"Point"}
}