{
  "type": "Feature",
  "properties": {
    "gn:country":"IN",
    "gn:fcode":"PPL",
    "gn:pop":14302,
    "iso:country":"IN",
    "name:asm_x_preferred":[
        "\u09a8\u09be\u099c\u09bf\u09f0\u09be"
    ],
    "name:bpy_x_preferred":[
        "\u09a8\u09be\u099c\u09bf\u09b0\u09be"
    ],
    "name:ceb_x_preferred":[
        "N\u0101zir\u0101"
    ],
    "name:eng_x_preferred":[
        "Nazira"
    ],
    "name:fra_x_preferred":[
        "Nazira"
    ],
    "name:ita_x_preferred":[
        "Nazira"
    ],
    "name:msa_x_preferred":[
        "Nazira"
    ],
    "name:nan_x_preferred":[
        "Nazira"
    ],
    "name:new_x_preferred":[
        "\u0928\u091c\u093f\u0930\u093e"
    ],
    "name:nld_x_preferred":[
        "Nazira"
    ],
    "name:por_x_preferred":[
        "Nazira"
    ],
    "name:swe_x_preferred":[
        "N\u0101zir\u0101"
    ],
    "name:unk_x_variant":[
        "N\u0101zir\u0101"
    ],
    "name:vie_x_preferred":[
        "Nazira"
    ],
    "name:zho_x_preferred":[
        "\u7eb3\u9f50\u62c9"
    ],
    "qs:name":"Nazira",
    "qs:name_adm0":"India",
    "qs:name_adm1":"Assam",
    "qs:photos_9k":1,
    "qs:photos_9r":1,
    "qs:photos_all":1,
    "qs:photos_sr":0,
    "qs:placetype":"Town",
    "qs:pop_sr":"6",
    "wd:wordcount":1249,
    "wof:name":"Nazira",
    "wof:placetype":"locality",
    "wof:population":14302
},
  "geometry": {"coordinates":[94.73611,26.91649],"type":"Point"}
}