{
  "type": "Feature",
  "properties": {
    "iso:country":"IN",
    "ks:ks_name":"Cholampundi",
    "ks:ks_pop":1282,
    "ks:ks_type":"VILLAGE",
    "ks:ks_uagg_main":0,
    "name:eng_x_preferred":[
        "Cholampundi"
    ],
    "wof:name":"Cholampundi",
    "wof:placetype":"neighbourhood",
    "wof:population":1282
},
  "geometry": {"coordinates":[79.46135700000001,11.97028],"type":"Point"}
}