{
  "type": "Feature",
  "properties": {
    "gn:admin1_code":"36",
    "gn:admin2_code":"138.0",
    "gn:asciiname":"Santpur",
    "gn:country_code":"IN",
    "gn:dem":214,
    "gn:feature_class":"P",
    "gn:feature_code":"PPL",
    "gn:name":"Santpur",
    "gn:population":0,
    "gn:timezone":"Asia/Kolkata",
    "iso:country":"IN",
    "name:msa_x_preferred":[
        "Santpur"
    ],
    "name:pol_x_preferred":[
        "Santpur"
    ],
    "wof:name":"Santpur",
    "wof:placetype":"locality"
},
  "geometry": {"coordinates":[78.04266,29.17617000000001],"type":"Point"}
}