{
  "type": "Feature",
  "properties": {
    "iso:country":"IN",
    "ks:ks_name":"Keramuda",
    "ks:ks_pop":115,
    "ks:ks_type":"HABITATION",
    "name:eng_x_preferred":[
        "Keramuda"
    ],
    "wof:name":"Keramuda",
    "wof:placetype":"locality",
    "wof:population":115
},
  "geometry": {"coordinates":[83.651824,22.260137],"type":"Point"}
}