{
  "type": "Feature",
  "properties": {
    "iso:country":"IN",
    "ks:ks_name":"Kadavu End",
    "ks:ks_pop":21,
    "ks:ks_type":"HABITATION",
    "name:eng_x_preferred":[
        "Kadavu End"
    ],
    "wof:name":"Kadavu End",
    "wof:placetype":"locality",
    "wof:population":21
},
  "geometry": {"coordinates":[76.30765700000001,10.263629],"type":"Point"}
}