{
  "type": "Feature",
  "properties": {
    "gn:admin1_code":"36",
    "gn:admin2_code":"176.0",
    "gn:asciiname":"Taspur",
    "gn:country_code":"IN",
    "gn:dem":124,
    "gn:feature_class":"P",
    "gn:feature_code":"PPL",
    "gn:name":"T\u0101spur",
    "gn:population":0,
    "gn:timezone":"Asia/Kolkata",
    "iso:country":"IN",
    "wof:name":"Taspur",
    "wof:placetype":"locality"
},
  "geometry": {"coordinates":[81.15810999999999,27.04772],"type":"Point"}
}