{
  "type": "Feature",
  "properties": {
    "gn:admin1_code":"36.0",
    "gn:admin2_code":"175.0",
    "gn:asciiname":"Shadmanpur",
    "gn:country_code":"IN",
    "gn:dem":94,
    "gn:feature_class":"P",
    "gn:feature_code":"PPL",
    "gn:name":"Sh\u0101dm\u0101npur",
    "gn:population":0,
    "gn:timezone":"Asia/Kolkata",
    "iso:country":"IN",
    "wof:name":"Shadmanpur",
    "wof:placetype":"locality"
},
  "geometry": {"coordinates":[81.97678000000001,25.48429],"type":"Point"}
}