{
  "type": "Feature",
  "properties": {
    "gn:admin1_code":"37.0",
    "gn:admin2_code":"409.0",
    "gn:asciiname":"Bendarchi",
    "gn:country_code":"IN",
    "gn:dem":320,
    "gn:feature_class":"P",
    "gn:feature_code":"PPL",
    "gn:name":"Bendarchi",
    "gn:population":0,
    "gn:timezone":"Asia/Kolkata",
    "iso:country":"IN",
    "name:eng_x_preferred":[
        "Bendarchi"
    ],
    "wof:name":"Bendarchi",
    "wof:placetype":"locality"
},
  "geometry": {"coordinates":[81.23950000000001,21.74916],"type":"Point"}
}