{
  "type": "Feature",
  "properties": {
    "gn:admin1_code":"21.0",
    "gn:admin2_code":"398.0",
    "gn:asciiname":"Tamba",
    "gn:country_code":"IN",
    "gn:dem":891,
    "gn:feature_class":"P",
    "gn:feature_code":"PPL",
    "gn:name":"Tamba",
    "gn:population":0,
    "gn:timezone":"Asia/Kolkata",
    "iso:country":"IN",
    "name:ceb_x_preferred":[
        "Tamba"
    ],
    "name:cym_x_preferred":[
        "Tamba"
    ],
    "name:deu_x_preferred":[
        "Tamba"
    ],
    "name:fra_x_preferred":[
        "Tamba"
    ],
    "name:ind_x_preferred":[
        "Tamba"
    ],
    "name:nld_x_preferred":[
        "Tamba"
    ],
    "name:swe_x_preferred":[
        "Tamba"
    ],
    "wof:name":"Tamba",
    "wof:placetype":"locality"
},
  "geometry": {"coordinates":[82.89291,18.58856],"type":"Point"}
}