{
  "type": "Feature",
  "properties": {
    "iso:country":"IN",
    "ks:ks_alt_nam":"sadakpada",
    "ks:ks_name":"Sadakpada",
    "ks:ks_pop":110,
    "ks:ks_type":"HABITATION",
    "name:eng_x_preferred":[
        "Sadakpada"
    ],
    "wof:name":"Sadakpada",
    "wof:placetype":"locality",
    "wof:population":110
},
  "geometry": {"coordinates":[73.18958499999999,19.850536],"type":"Point"}
}