{
  "type": "Feature",
  "properties": {
    "gn:country":"IN",
    "gn:fcode":"PPL",
    "gn:population":0,
    "iso:country":"IN",
    "name:ara_x_preferred":[
        "\u0647\u0631\u062f\u064a \u0628\u0648\u0631"
    ],
    "name:ben_bn_x_preferred":[
        "\u09b9\u09b0\u09bf\u09a6\u09c7\u09ac\u09aa\u09c1\u09b0"
    ],
    "name:ben_in_x_preferred":[
        "\u09b9\u09b0\u09bf\u09a6\u09c7\u09ac\u09aa\u09c1\u09b0"
    ],
    "name:guj_x_preferred":[
        "\u0ab9\u0ab0\u0abf\u0aa6\u0ac7\u0aac\u0aaa\u0ac1\u0ab0"
    ],
    "name:hin_x_preferred":[
        "\u0939\u0930\u093f\u0926\u0947\u092c\u092a\u0941\u0930"
    ],
    "name:kan_x_preferred":[
        "\u0cb9\u0cb0\u0cbf\u0ca6\u0cc7\u0cac\u0ccd"
    ],
    "name:mal_x_preferred":[
        "\u0d39\u0d30\u0d3f\u0d26\u0d46\u0d2a\u0d42\u0d7c"
    ],
    "name:mar_x_preferred":[
        "\u0939\u0930\u093f\u0926\u0947\u092c\u092a\u0942\u0930"
    ],
    "name:pan_x_preferred":[
        "\u0a39\u0a30\u0a40\u0a26\u0a47\u0a2c\u0a2a\u0a41\u0a30"
    ],
    "name:tam_x_preferred":[
        "\u0bb9\u0bb0\u0bbf\u0b9f\u0bc7\u0baa\u0bcd\u0baa\u0bc2\u0bb0\u0bcd"
    ],
    "name:tel_x_preferred":[
        "\u0c39\u0c30\u0c3f\u0c26\u0c47\u0c2c\u0c4d"
    ],
    "name:urd_x_preferred":[
        "\u06c1\u0631\u06cc\u062f\u06cc\u0628 \u067e\u0648\u0631"
    ],
    "qs:name":"Haridebpur",
    "qs:name_adm0":"India",
    "qs:name_adm1":"West Bengal",
    "qs:photos":1,
    "qs:photos_1k":1,
    "qs:photos_9k":1,
    "qs:photos_9r":1,
    "qs:photos_all":1,
    "qs:photos_sr":1,
    "qs:placetype":"Suburb",
    "qs:pop_sr":"0",
    "wof:name":"Haridebpur",
    "wof:placetype":"neighbourhood",
    "wof:population":0
},
  "geometry": {"coordinates":[88.27321999999999,22.78586],"type":"Point"}
}