{
  "type": "Feature",
  "properties": {
    "gn:admin1_code":"25",
    "gn:admin2_code":"626.0",
    "gn:asciiname":"Ramaswamipatti",
    "gn:country_code":"IN",
    "gn:dem":65,
    "gn:feature_class":"P",
    "gn:feature_code":"PPL",
    "gn:name":"R\u0101masw\u0101mipatti",
    "gn:population":0,
    "gn:timezone":"Asia/Kolkata",
    "iso:country":"IN",
    "wof:name":"Ramaswamipatti",
    "wof:placetype":"locality"
},
  "geometry": {"coordinates":[78.26560000000001,9.39049],"type":"Point"}
}