{
  "type": "Feature",
  "properties": {
    "iso:country":"IN",
    "ks:ks_alt_nam":"Peda HPeta",
    "ks:ks_name":"Peda Hpeta",
    "ks:ks_pop":718,
    "ks:ks_type":"HABITATION",
    "name:eng_x_preferred":[
        "Peda Hpeta"
    ],
    "wof:name":"Peda Hpeta",
    "wof:placetype":"locality",
    "wof:population":718
},
  "geometry": {"coordinates":[82.03099,16.519714],"type":"Point"}
}