{
  "type": "Feature",
  "properties": {
    "iso:country":"IN",
    "ks:ks_name":"Anandnagar N V",
    "ks:ks_pop":604,
    "ks:ks_type":"HABITATION",
    "name:eng_x_preferred":[
        "Anandnagar N V"
    ],
    "wof:name":"Anandnagar N V",
    "wof:placetype":"locality",
    "wof:population":604
},
  "geometry": {"coordinates":[73.337222,19.33],"type":"Point"}
}