{
  "type": "Feature",
  "properties": {
    "gn:admin1_code":"37",
    "gn:admin2_code":"407.0",
    "gn:asciiname":"Bhaisabod",
    "gn:country_code":"IN",
    "gn:dem":329,
    "gn:feature_class":"P",
    "gn:feature_code":"PPL",
    "gn:name":"Bhais\u0101bod",
    "gn:population":0,
    "gn:timezone":"Asia/Kolkata",
    "iso:country":"IN",
    "wof:name":"Bhaisabod",
    "wof:placetype":"locality"
},
  "geometry": {"coordinates":[81.49556,22.17451],"type":"Point"}
}