{
  "type": "Feature",
  "properties": {
    "iso:country":"IN",
    "ks:ks_name":"Jungle Kurmaul",
    "ks:ks_pop":2944,
    "ks:ks_type":"VILLAGE",
    "name:eng_x_preferred":[
        "Jungle Kurmaul"
    ],
    "wof:name":"Jungle Kurmaul",
    "wof:placetype":"locality",
    "wof:population":2944
},
  "geometry": {"coordinates":[83.98570100000001,26.942193],"type":"Point"}
}