{
  "type": "Feature",
  "properties": {
    "iso:country":"IN",
    "ks:ks_name":"Kuppapatty",
    "ks:ks_pop":212,
    "ks:ks_type":"HABITATION",
    "ks:ks_uagg_main":0,
    "name:eng_x_preferred":[
        "Kuppapatty"
    ],
    "wof:name":"Kuppapatty",
    "wof:placetype":"neighbourhood",
    "wof:population":212
},
  "geometry": {"coordinates":[78.323502,10.28786],"type":"Point"}
}