{
  "type": "Feature",
  "properties": {
    "iso:country":"IN",
    "ks:ks_name":"Atraulia",
    "ks:ks_pop":1007,
    "ks:ks_type":"VILLAGE",
    "name:eng_x_preferred":[
        "Atraulia"
    ],
    "wof:name":"Atraulia",
    "wof:placetype":"locality",
    "wof:population":1007
},
  "geometry": {"coordinates":[85.17439400000001,26.031117],"type":"Point"}
}