{
  "type": "Feature",
  "properties": {
    "gn:admin1_code":"36",
    "gn:admin2_code":"200.0",
    "gn:asciiname":"Tiara",
    "gn:country_code":"IN",
    "gn:dem":308,
    "gn:feature_class":"P",
    "gn:feature_code":"PPL",
    "gn:name":"Tiara",
    "gn:population":0,
    "gn:timezone":"Asia/Kolkata",
    "iso:country":"IN",
    "name:ara_x_preferred":[
        "\u062a\u0627\u062c \u0645\u0631\u0635\u0639"
    ],
    "name:azb_x_preferred":[
        "\u06cc\u0627\u0631\u06cc\u0645\u200c\u062a\u0627\u062c"
    ],
    "name:bjn_x_preferred":[
        "Katopong"
    ],
    "name:cat_x_preferred":[
        "Tiara"
    ],
    "name:ces_x_preferred":[
        "Ti\u00e1ra"
    ],
    "name:dan_x_preferred":[
        "Tiara"
    ],
    "name:deu_x_preferred":[
        "Tiara"
    ],
    "name:epo_x_preferred":[
        "Tiaro"
    ],
    "name:est_x_preferred":[
        "Tiaara"
    ],
    "name:eus_x_preferred":[
        "Tiara"
    ],
    "name:fas_x_preferred":[
        "\u0646\u06cc\u0645\u200c\u062a\u0627\u062c"
    ],
    "name:fin_x_preferred":[
        "Tiara"
    ],
    "name:fra_x_preferred":[
        "Tiare"
    ],
    "name:heb_x_preferred":[
        "\u05e0\u05d6\u05e8"
    ],
    "name:hun_x_preferred":[
        "Tiara"
    ],
    "name:ido_x_preferred":[
        "Tiaro"
    ],
    "name:ind_x_preferred":[
        "Tiara"
    ],
    "name:ita_x_preferred":[
        "Tiara"
    ],
    "name:jav_x_preferred":[
        "Tiara"
    ],
    "name:jpn_x_preferred":[
        "\u30c6\u30a3\u30a2\u30e9"
    ],
    "name:kor_x_preferred":[
        "\ud2f0\uc544\ub77c"
    ],
    "name:lat_x_preferred":[
        "Tiara"
    ],
    "name:nld_x_preferred":[
        "Tiara"
    ],
    "name:nno_x_preferred":[
        "Tiara"
    ],
    "name:nor_x_preferred":[
        "Tiara"
    ],
    "name:rus_x_preferred":[
        "\u0422\u0438\u0430\u0440\u0430"
    ],
    "name:spa_x_preferred":[
        "Tiara"
    ],
    "name:swe_x_preferred":[
        "Tiara"
    ],
    "name:tha_x_preferred":[
        "\u0e40\u0e17\u0e23\u0e34\u0e14"
    ],
    "name:tur_x_preferred":[
        "Tiara"
    ],
    "wof:name":"Tiara",
    "wof:placetype":"locality"
},
  "geometry": {"coordinates":[83.06095000000001,24.70725],"type":"Point"}
}