{
  "type": "Feature",
  "properties": {
    "gn:admin1_code":"36.0",
    "gn:admin2_code":"150.0",
    "gn:asciiname":"Sudhanpur",
    "gn:country_code":"IN",
    "gn:dem":172,
    "gn:feature_class":"P",
    "gn:feature_code":"PPL",
    "gn:name":"Sudhanpur",
    "gn:population":0,
    "gn:timezone":"Asia/Kolkata",
    "iso:country":"IN",
    "wof:name":"Sudhanpur",
    "wof:placetype":"locality"
},
  "geometry": {"coordinates":[79.2842,28.37003],"type":"Point"}
}