{
  "type": "Feature",
  "properties": {
    "gn:admin1_code":"39",
    "gn:admin2_code":"61.0",
    "gn:asciiname":"Rikhera",
    "gn:country_code":"IN",
    "gn:dem":1250,
    "gn:feature_class":"P",
    "gn:feature_code":"PPL",
    "gn:name":"Rikhera",
    "gn:population":0,
    "gn:timezone":"Asia/Kolkata",
    "iso:country":"IN",
    "wof:name":"Rikhera",
    "wof:placetype":"locality"
},
  "geometry": {"coordinates":[78.49061999999998,29.94844],"type":"Point"}
}