{
  "type": "Feature",
  "properties": {
    "gn:admin1_code":"11",
    "gn:admin2_code":"24.0",
    "gn:asciiname":"Majhetli Buhli",
    "gn:country_code":"IN",
    "gn:dem":972,
    "gn:feature_class":"P",
    "gn:feature_code":"PPL",
    "gn:name":"Majhetli B\u016bhli",
    "gn:population":0,
    "gn:timezone":"Asia/Kolkata",
    "iso:country":"IN",
    "wof:name":"Majhetli Buhli",
    "wof:placetype":"locality"
},
  "geometry": {"coordinates":[76.42121999999998,32.1196],"type":"Point"}
}