{
  "type": "Feature",
  "properties": {
    "iso:country":"IN",
    "ks:ks_alt_nam":"thalakulam",
    "ks:ks_name":"Thalakulam",
    "ks:ks_pop":2430,
    "ks:ks_type":"HABITATION",
    "name:eng_x_preferred":[
        "Thalakulam"
    ],
    "wof:name":"Thalakulam",
    "wof:placetype":"locality",
    "wof:population":2430
},
  "geometry": {"coordinates":[77.06329100000001,9.981488],"type":"Point"}
}