{
  "type": "Feature",
  "properties": {
    "iso:country":"IN",
    "ks:ks_alt_nam":"LALA TOLA",
    "ks:ks_name":"Lala Tola",
    "ks:ks_pop":207,
    "ks:ks_type":"HABITATION",
    "name:eng_x_preferred":[
        "Lala Tola"
    ],
    "wof:name":"Lala Tola",
    "wof:placetype":"locality",
    "wof:population":207
},
  "geometry": {"coordinates":[85.12869999999999,24.134519],"type":"Point"}
}