{
  "type": "Feature",
  "properties": {
    "iso:country":"IN",
    "ks:ks_name":"Govinadinni",
    "ks:ks_pop":249,
    "ks:ks_type":"HABITATION",
    "name:eng_x_preferred":[
        "Govinadinni"
    ],
    "wof:name":"Govinadinni",
    "wof:placetype":"locality",
    "wof:population":249
},
  "geometry": {"coordinates":[75.72954300000001,16.326355],"type":"Point"}
}