{
  "type": "Feature",
  "properties": {
    "iso:country":"IN",
    "ks:ks_name":"Talav Falia",
    "ks:ks_pop":886,
    "ks:ks_type":"HABITATION",
    "name:eng_x_preferred":[
        "Talav Falia"
    ],
    "wof:name":"Talav Falia",
    "wof:placetype":"locality",
    "wof:population":886
},
  "geometry": {"coordinates":[73.878139,22.789583],"type":"Point"}
}