{
  "type": "Feature",
  "properties": {
    "iso:country":"IN",
    "ks:ks_name":"Rellalapalem",
    "ks:ks_pop":42,
    "ks:ks_type":"HABITATION",
    "name:eng_x_preferred":[
        "Rellalapalem"
    ],
    "wof:name":"Rellalapalem",
    "wof:placetype":"locality",
    "wof:population":42
},
  "geometry": {"coordinates":[82.890578,17.9815],"type":"Point"}
}