{
  "type": "Feature",
  "properties": {
    "iso:country":"IN",
    "ks:ks_name":"Akna-1",
    "ks:ks_pop":442,
    "ks:ks_type":"HABITATION",
    "name:eng_x_preferred":[
        "Akna-1"
    ],
    "wof:name":"Akna-1",
    "wof:placetype":"locality",
    "wof:population":442
},
  "geometry": {"coordinates":[86.82020199999999,22.252697],"type":"Point"}
}