{
  "type": "Feature",
  "properties": {
    "iso:country":"IN",
    "ks:ks_alt_nam":"AHIRAUTI",
    "ks:ks_name":"Ahirauti",
    "ks:ks_pop":171,
    "ks:ks_type":"HABITATION",
    "name:eng_x_preferred":[
        "Ahirauti"
    ],
    "wof:name":"Ahirauti",
    "wof:placetype":"locality",
    "wof:population":171
},
  "geometry": {"coordinates":[82.159993,26.248766],"type":"Point"}
}