{
  "type": "Feature",
  "properties": {
    "iso:country":"IN",
    "ks:ks_name":"Kalikamerya",
    "ks:ks_pop":117,
    "ks:ks_type":"VILLAGE",
    "name:eng_x_preferred":[
        "Kalikamerya"
    ],
    "wof:name":"Kalikamerya",
    "wof:placetype":"locality",
    "wof:population":117
},
  "geometry": {"coordinates":[88.198713,22.244014],"type":"Point"}
}