{
  "type": "Feature",
  "properties": {
    "gn:admin1_code":"19.0",
    "gn:admin2_code":"563.0",
    "gn:asciiname":"Chandavar",
    "gn:country_code":"IN",
    "gn:dem":20,
    "gn:feature_class":"P",
    "gn:feature_code":"PPL",
    "gn:name":"Chandavar",
    "gn:population":0,
    "gn:timezone":"Asia/Kolkata",
    "iso:country":"IN",
    "ks:ks_name":"Chandavar",
    "ks:ks_pop":301,
    "ks:ks_type":"VILLAGE",
    "name:eng_x_preferred":[
        "Chandavar"
    ],
    "wof:name":"Chandavar",
    "wof:placetype":"locality",
    "wof:population":301
},
  "geometry": {"coordinates":[74.478201,14.38698],"type":"Point"}
}