{
  "type": "Feature",
  "properties": {
    "iso:country":"IN",
    "ks:ks_name":"Kilingar",
    "ks:ks_pop":4001,
    "ks:ks_type":"HABITATION",
    "name:eng_x_preferred":[
        "Kilingar"
    ],
    "wof:name":"Kilingar",
    "wof:placetype":"locality",
    "wof:population":4001
},
  "geometry": {"coordinates":[75.021638,12.595716],"type":"Point"}
}