{
  "type": "Feature",
  "properties": {
    "iso:country":"IN",
    "ks:ks_name":"Jhumar",
    "ks:ks_pop":134,
    "ks:ks_type":"VILLAGE",
    "name:eng_x_preferred":[
        "Jhumar"
    ],
    "wof:name":"Jhumar",
    "wof:placetype":"locality",
    "wof:population":134
},
  "geometry": {"coordinates":[80.04306099999999,25.160505],"type":"Point"}
}