{
  "type": "Feature",
  "properties": {
    "iso:country":"IN",
    "ks:ks_name":"Rusikulyaguda",
    "ks:ks_pop":84,
    "ks:ks_type":"HABITATION",
    "name:eng_x_preferred":[
        "Rusikulyaguda"
    ],
    "wof:name":"Rusikulyaguda",
    "wof:placetype":"locality",
    "wof:population":84
},
  "geometry": {"coordinates":[83.798883,19.439019],"type":"Point"}
}