{
  "type": "Feature",
  "properties": {
    "gn:admin1_code":"38.0",
    "gn:admin2_code":"360.0",
    "gn:asciiname":"Doi",
    "gn:country_code":"IN",
    "gn:dem":587,
    "gn:feature_class":"P",
    "gn:feature_code":"PPL",
    "gn:name":"Doi",
    "gn:population":0,
    "gn:timezone":"Asia/Kolkata",
    "iso:country":"IN",
    "ks:ks_name":"Doi",
    "ks:ks_pop":522,
    "ks:ks_type":"VILLAGE",
    "ks:ks_uagg_main":0,
    "name:eng_x_preferred":[
        "Doi"
    ],
    "wof:name":"Doi",
    "wof:placetype":"neighbourhood",
    "wof:population":522
},
  "geometry": {"coordinates":[85.483469,24.106778],"type":"Point"}
}