{
  "type": "Feature",
  "properties": {
    "iso:country":"IN",
    "ks:ks_name":"Vahdi Vadheya Harijan Faliya",
    "ks:ks_pop":709,
    "ks:ks_type":"HABITATION",
    "name:eng_x_preferred":[
        "Vahdi Vadheya Harijan Faliya"
    ],
    "wof:name":"Vahdi Vadheya Harijan Faliya",
    "wof:placetype":"locality",
    "wof:population":709
},
  "geometry": {"coordinates":[73.833944,22.837611],"type":"Point"}
}