{
  "type": "Feature",
  "properties": {
    "iso:country":"IN",
    "ks:ks_name":"Puritola",
    "ks:ks_pop":567,
    "ks:ks_type":"HABITATION",
    "name:eng_x_preferred":[
        "Puritola"
    ],
    "wof:name":"Puritola",
    "wof:placetype":"locality",
    "wof:population":567
},
  "geometry": {"coordinates":[85.63716100000001,23.370662],"type":"Point"}
}