{
  "type": "Feature",
  "properties": {
    "gn:admin1_code":"39.0",
    "gn:admin2_code":"64.0",
    "gn:asciiname":"Harara",
    "gn:country_code":"IN",
    "gn:dem":1157,
    "gn:feature_class":"P",
    "gn:feature_code":"PPL",
    "gn:name":"Harara",
    "gn:population":0,
    "gn:timezone":"Asia/Kolkata",
    "iso:country":"IN",
    "ks:ks_name":"Harara",
    "ks:ks_type":"VILLAGE",
    "name:eng_x_preferred":[
        "Harara"
    ],
    "wof:name":"Harara",
    "wof:placetype":"locality"
},
  "geometry": {"coordinates":[79.94895699999999,29.658505],"type":"Point"}
}