{
  "type": "Feature",
  "properties": {
    "iso:country":"IN",
    "ks:ks_name":"Seenikuppam",
    "ks:ks_pop":84,
    "ks:ks_type":"HABITATION",
    "ks:ks_uagg_main":0,
    "name:eng_x_preferred":[
        "Seenikuppam"
    ],
    "wof:name":"Seenikuppam",
    "wof:placetype":"neighbourhood",
    "wof:population":84
},
  "geometry": {"coordinates":[79.958158,13.334107],"type":"Point"}
}