{
  "type": "Feature",
  "properties": {
    "iso:country":"IN",
    "ks:ks_name":"Nuji Periyotty",
    "ks:ks_pop":250,
    "ks:ks_type":"HABITATION",
    "name:eng_x_preferred":[
        "Nuji Periyotty"
    ],
    "wof:name":"Nuji Periyotty",
    "wof:placetype":"locality",
    "wof:population":250
},
  "geometry": {"coordinates":[75.212143,13.08996],"type":"Point"}
}