{
  "type": "Feature",
  "properties": {
    "iso:country":"IN",
    "ks:ks_name":"Chuttugondi",
    "ks:ks_pop":198,
    "ks:ks_type":"HABITATION",
    "name:eng_x_preferred":[
        "Chuttugondi"
    ],
    "wof:name":"Chuttugondi",
    "wof:placetype":"locality",
    "wof:population":198
},
  "geometry": {"coordinates":[82.395302,18.320129],"type":"Point"}
}