{
  "type": "Feature",
  "properties": {
    "iso:country":"IN",
    "ks:ks_name":"Babhnauti Urf Shahar Golafaj",
    "ks:ks_pop":177,
    "ks:ks_type":"VILLAGE",
    "name:eng_x_preferred":[
        "Babhnauti Urf Shahar Golafaj"
    ],
    "wof:name":"Babhnauti Urf Shahar Golafaj",
    "wof:placetype":"locality",
    "wof:population":177
},
  "geometry": {"coordinates":[81.390473,27.480265],"type":"Point"}
}