{
  "type": "Feature",
  "properties": {
    "gn:admin1_code":"36.0",
    "gn:admin2_code":"183.0",
    "gn:asciiname":"Bhawaniapur Upadhia",
    "gn:country_code":"IN",
    "gn:dem":112,
    "gn:feature_class":"P",
    "gn:feature_code":"PPL",
    "gn:name":"Bhawani\u0101pur Upadhia",
    "gn:population":0,
    "gn:timezone":"Asia/Kolkata",
    "iso:country":"IN",
    "wof:name":"Bhawaniapur Upadhia",
    "wof:placetype":"neighbourhood"
},
  "geometry": {"coordinates":[82.00682,27.33287],"type":"Point"}
}