{
  "type": "Feature",
  "properties": {
    "iso:country":"IN",
    "ks:ks_name":"Khutwar",
    "ks:ks_pop":8,
    "ks:ks_type":"HABITATION",
    "name:eng_x_preferred":[
        "Khutwar"
    ],
    "wof:name":"Khutwar",
    "wof:placetype":"locality",
    "wof:population":8
},
  "geometry": {"coordinates":[85.664497,23.984275],"type":"Point"}
}