{
  "type": "Feature",
  "properties": {
    "iso:country":"IN",
    "ks:ks_alt_nam":"KANDELVA",
    "ks:ks_name":"Kandelva",
    "ks:ks_pop":120,
    "ks:ks_type":"HABITATION",
    "name:eng_x_preferred":[
        "Kandelva"
    ],
    "wof:name":"Kandelva",
    "wof:placetype":"locality",
    "wof:population":120
},
  "geometry": {"coordinates":[81.148627,26.979607],"type":"Point"}
}