{
  "type": "Feature",
  "properties": {
    "gn:admin1_code":"35.0",
    "gn:admin2_code":"442.0",
    "gn:asciiname":"Gulkheri Kalan",
    "gn:country_code":"IN",
    "gn:dem":428,
    "gn:feature_class":"P",
    "gn:feature_code":"PPL",
    "gn:name":"Gulkheri Kal\u0101n",
    "gn:population":0,
    "gn:timezone":"Asia/Kolkata",
    "iso:country":"IN",
    "wof:name":"Gulkheri Kalan",
    "wof:placetype":"locality"
},
  "geometry": {"coordinates":[76.66856999999997,23.70286],"type":"Point"}
}