{
  "type": "Feature",
  "properties": {
    "iso:country":"IN",
    "ks:ks_name":"Ragunadhapuram",
    "ks:ks_pop":15,
    "ks:ks_type":"HABITATION",
    "name:eng_x_preferred":[
        "Ragunadhapuram"
    ],
    "wof:name":"Ragunadhapuram",
    "wof:placetype":"locality",
    "wof:population":15
},
  "geometry": {"coordinates":[84.434214,18.902927],"type":"Point"}
}