{
  "type": "Feature",
  "properties": {
    "gn:admin1_code":"36",
    "gn:admin2_code":"172.0",
    "gn:asciiname":"Udairajpur",
    "gn:country_code":"IN",
    "gn:dem":121,
    "gn:feature_class":"P",
    "gn:feature_code":"PPL",
    "gn:name":"Udair\u0101jpur",
    "gn:population":0,
    "gn:timezone":"Asia/Kolkata",
    "iso:country":"IN",
    "ks:ks_name":"Udaiy Rajpur",
    "ks:ks_pop":326,
    "ks:ks_type":"VILLAGE",
    "name:eng_x_preferred":[
        "Udaiy Rajpur"
    ],
    "name:eng_x_variant":[
        "Udairajpur"
    ],
    "wof:name":"Udaiy Rajpur",
    "wof:placetype":"locality",
    "wof:population":326
},
  "geometry": {"coordinates":[80.68598299999999,25.963335],"type":"Point"}
}