{
  "type": "Feature",
  "properties": {
    "iso:country":"IN",
    "ks:ks_name":"Upari Ratgaon Chak",
    "ks:ks_pop":1244,
    "ks:ks_type":"HABITATION",
    "name:eng_x_preferred":[
        "Upari Ratgaon Chak"
    ],
    "wof:name":"Upari Ratgaon Chak",
    "wof:placetype":"locality",
    "wof:population":1244
},
  "geometry": {"coordinates":[79.54856100000001,30.136344],"type":"Point"}
}