{
  "type": "Feature",
  "properties": {
    "iso:country":"IN",
    "ks:ks_name":"K Mala",
    "ks:ks_pop":41,
    "ks:ks_type":"HABITATION",
    "name:eng_x_preferred":[
        "K Mala"
    ],
    "wof:name":"K Mala",
    "wof:placetype":"locality",
    "wof:population":41
},
  "geometry": {"coordinates":[84.434415,19.009859],"type":"Point"}
}