{
  "type": "Feature",
  "properties": {
    "iso:country":"IN",
    "ks:ks_name":"Damuku Rai",
    "ks:ks_pop":34,
    "ks:ks_type":"HABITATION",
    "name:eng_x_preferred":[
        "Damuku Rai"
    ],
    "wof:name":"Damuku Rai",
    "wof:placetype":"locality",
    "wof:population":34
},
  "geometry": {"coordinates":[82.973491,18.185202],"type":"Point"}
}