{
  "type": "Feature",
  "properties": {
    "iso:country":"IN",
    "ks:ks_name":"Anandipur",
    "ks:ks_pop":59,
    "ks:ks_type":"HABITATION",
    "name:eng_x_preferred":[
        "Anandipur"
    ],
    "wof:name":"Anandipur",
    "wof:placetype":"locality",
    "wof:population":59
},
  "geometry": {"coordinates":[78.116924,29.577072],"type":"Point"}
}