{
  "type": "Feature",
  "properties": {
    "iso:country":"IN",
    "ks:ks_name":"Gaswa",
    "ks:ks_pop":765,
    "ks:ks_type":"HABITATION",
    "ks:ks_uagg_main":0,
    "name:eng_x_preferred":[
        "Gaswa"
    ],
    "wof:name":"Gaswa",
    "wof:placetype":"neighbourhood",
    "wof:population":765
},
  "geometry": {"coordinates":[86.22031,26.06142],"type":"Point"}
}