{
  "type": "Feature",
  "properties": {
    "iso:country":"IN",
    "ks:ks_alt_nam":"M\u0101npur",
    "ks:ks_name":"Manpur",
    "ks:ks_pop":2541,
    "ks:ks_type":"VILLAGE",
    "ks:ks_uagg_main":0,
    "name:eng_x_preferred":[
        "Manpur"
    ],
    "name:eng_x_variant":[
        "M\u0101npur"
    ],
    "wof:name":"Manpur",
    "wof:placetype":"neighbourhood",
    "wof:population":2541
},
  "geometry": {"coordinates":[85.925589,24.932975],"type":"Point"}
}