{
  "type": "Feature",
  "properties": {
    "iso:country":"IN",
    "ks:ks_name":"Suli",
    "ks:ks_type":"VILLAGE",
    "name:eng_x_preferred":[
        "Suli"
    ],
    "wof:name":"Suli",
    "wof:placetype":"locality"
},
  "geometry": {"coordinates":[84.066912,20.524303],"type":"Point"}
}