{
  "type": "Feature",
  "properties": {
    "iso:country":"IN",
    "ks:ks_name":"Dhuchaniyafali",
    "ks:ks_pop":301,
    "ks:ks_type":"HABITATION",
    "name:eng_x_preferred":[
        "Dhuchaniyafali"
    ],
    "wof:name":"Dhuchaniyafali",
    "wof:placetype":"locality",
    "wof:population":301
},
  "geometry": {"coordinates":[72.800797,24.282977],"type":"Point"}
}