{
  "type": "Feature",
  "properties": {
    "iso:country":"IN",
    "ks:ks_name":"Dapadanga",
    "ks:ks_pop":96,
    "ks:ks_type":"VILLAGE",
    "name:eng_x_preferred":[
        "Dapadanga"
    ],
    "wof:name":"Dapadanga",
    "wof:placetype":"locality",
    "wof:population":96
},
  "geometry": {"coordinates":[83.812748,20.21087],"type":"Point"}
}