{
  "type": "Feature",
  "properties": {
    "iso:country":"IN",
    "ks:ks_name":"Purnapani",
    "ks:ks_pop":142,
    "ks:ks_type":"HABITATION",
    "name:eng_x_preferred":[
        "Purnapani"
    ],
    "wof:name":"Purnapani",
    "wof:placetype":"locality",
    "wof:population":142
},
  "geometry": {"coordinates":[87.086533,22.570754],"type":"Point"}
}