{
  "type": "Feature",
  "properties": {
    "iso:country":"IN",
    "ks:ks_name":"Gobro",
    "ks:ks_pop":164,
    "ks:ks_type":"HABITATION",
    "name:eng_x_preferred":[
        "Gobro"
    ],
    "wof:name":"Gobro",
    "wof:placetype":"locality",
    "wof:population":164
},
  "geometry": {"coordinates":[86.35619,24.757089],"type":"Point"}
}