{
  "type": "Feature",
  "properties": {
    "iso:country":"IN",
    "ks:ks_name":"Limboda",
    "ks:ks_pop":1115,
    "ks:ks_type":"VILLAGE",
    "name:eng_x_preferred":[
        "Limboda"
    ],
    "wof:name":"Limboda",
    "wof:placetype":"locality",
    "wof:population":1115
},
  "geometry": {"coordinates":[74.66570400000001,23.778882],"type":"Point"}
}