{
  "type": "Feature",
  "properties": {
    "iso:country":"IN",
    "ks:ks_name":"Gharkarepada",
    "ks:ks_pop":6,
    "ks:ks_type":"HABITATION",
    "name:eng_x_preferred":[
        "Gharkarepada"
    ],
    "wof:name":"Gharkarepada",
    "wof:placetype":"locality",
    "wof:population":6
},
  "geometry": {"coordinates":[73.122074,19.683884],"type":"Point"}
}