{
  "type": "Feature",
  "properties": {
    "gn:admin1_code":"35",
    "gn:admin2_code":"463.0",
    "gn:asciiname":"Nawanagar",
    "gn:country_code":"IN",
    "gn:dem":444,
    "gn:feature_class":"P",
    "gn:feature_code":"PPL",
    "gn:name":"Naw\u0101nagar",
    "gn:population":0,
    "gn:timezone":"Asia/Kolkata",
    "iso:country":"IN",
    "ks:ks_alt_nam":"Naw\u0101nagar",
    "ks:ks_name":"Nawanagar",
    "ks:ks_type":"VILLAGE",
    "name:eng_x_preferred":[
        "Nawanagar"
    ],
    "name:eng_x_variant":[
        "Naw\u0101nagar"
    ],
    "name:hin_x_preferred":[
        "\u0928\u0935\u093e\u0928\u0917\u0930"
    ],
    "name:und_x_variant":[
        "Naw\u0101nagar",
        "Now\u0101naghar"
    ],
    "wof:name":"Nawanagar",
    "wof:placetype":"locality"
},
  "geometry": {"coordinates":[82.53234999999999,24.316226],"type":"Point"}
}