{
  "type": "Feature",
  "properties": {
    "iso:country":"IN",
    "ks:ks_name":"Veilukandapuram",
    "ks:ks_pop":105,
    "ks:ks_type":"HABITATION",
    "name:eng_x_preferred":[
        "Veilukandapuram"
    ],
    "wof:name":"Veilukandapuram",
    "wof:placetype":"locality",
    "wof:population":105
},
  "geometry": {"coordinates":[77.686016,9.068539],"type":"Point"}
}