{
  "type": "Feature",
  "properties": {
    "iso:country":"IN",
    "ks:ks_name":"Dubaulia Khas",
    "ks:ks_pop":1687,
    "ks:ks_type":"VILLAGE",
    "name:eng_x_preferred":[
        "Dubaulia Khas"
    ],
    "wof:name":"Dubaulia Khas",
    "wof:placetype":"locality",
    "wof:population":1687
},
  "geometry": {"coordinates":[82.506038,26.699741],"type":"Point"}
}