{
  "type": "Feature",
  "properties": {
    "iso:country":"IN",
    "ks:ks_alt_nam":"kmanimane",
    "ks:ks_name":"Kmanimane",
    "ks:ks_pop":49,
    "ks:ks_type":"HABITATION",
    "name:eng_x_preferred":[
        "Kmanimane"
    ],
    "wof:name":"Kmanimane",
    "wof:placetype":"locality",
    "wof:population":49
},
  "geometry": {"coordinates":[74.867059,14.369809],"type":"Point"}
}