{
  "type": "Feature",
  "properties": {
    "gn:admin1_code":"38.0",
    "gn:admin2_code":"347.0",
    "gn:asciiname":"Tulsi",
    "gn:country_code":"IN",
    "gn:dem":381,
    "gn:feature_class":"P",
    "gn:feature_code":"PPL",
    "gn:name":"Tuls\u012b",
    "gn:population":0,
    "gn:timezone":"Asia/Kolkata",
    "iso:country":"IN",
    "name:ara_x_preferred":[
        "\u062a\u0648\u0644\u0633\u064a"
    ],
    "name:ben_bn_x_preferred":[
        "\u09a4\u09c1\u09b2\u09b8\u09c0"
    ],
    "name:ben_in_x_preferred":[
        "\u09a4\u09c1\u09b2\u09b8\u09c0"
    ],
    "name:guj_x_preferred":[
        "\u0aa4\u0ac1\u0ab2\u0ab8\u0ac0"
    ],
    "name:hin_x_preferred":[
        "\u0924\u0941\u0932\u0938\u0940"
    ],
    "name:kan_x_preferred":[
        "\u0ca4\u0cc1\u0cb3\u0cb8\u0cbf"
    ],
    "name:mal_x_preferred":[
        "\u0d24\u0d41\u0d33\u0d4d\u200d\u0d38\u0d3f"
    ],
    "name:mar_x_preferred":[
        "\u0924\u0941\u0933\u0936\u0940"
    ],
    "name:pan_x_preferred":[
        "\u0a24\u0a41\u0a32\u0a38\u0a40"
    ],
    "name:tam_x_preferred":[
        "\u0ba4\u0bc1\u0bb3\u0bcd\u0b9a\u0bbf"
    ],
    "name:tel_x_preferred":[
        "\u0c24\u0c41\u0c32\u0c4d\u0c38\u0c40"
    ],
    "name:urd_x_preferred":[
        "\u062a\u0644\u0633\u06cc"
    ],
    "wof:name":"Tulsi",
    "wof:placetype":"locality"
},
  "geometry": {"coordinates":[84.64279000000001,24.21604],"type":"Point"}
}