{
  "type": "Feature",
  "properties": {
    "gn:admin1_code":"37",
    "gn:admin2_code":"404.0",
    "gn:asciiname":"Thitholi",
    "gn:country_code":"IN",
    "gn:dem":260,
    "gn:feature_class":"P",
    "gn:feature_code":"PPL",
    "gn:name":"Thithol\u012b",
    "gn:population":0,
    "gn:timezone":"Asia/Kolkata",
    "iso:country":"IN",
    "ks:ks_alt_nam":"Thithol\u012b",
    "ks:ks_name":"Thitholi",
    "ks:ks_type":"VILLAGE",
    "name:eng_x_preferred":[
        "Thitholi"
    ],
    "name:eng_x_variant":[
        "Thithol\u012b"
    ],
    "wof:name":"Thitholi",
    "wof:placetype":"locality"
},
  "geometry": {"coordinates":[82.641109,22.128513],"type":"Point"}
}