{
  "type": "Feature",
  "properties": {
    "iso:country":"IN",
    "ks:ks_name":"Deodand",
    "ks:ks_pop":669,
    "ks:ks_type":"VILLAGE",
    "name:eng_x_preferred":[
        "Deodand"
    ],
    "wof:name":"Deodand",
    "wof:placetype":"locality",
    "wof:population":669
},
  "geometry": {"coordinates":[83.581413,23.027728],"type":"Point"}
}