{
  "type": "Feature",
  "properties": {
    "iso:country":"IN",
    "ks:ks_name":"Niche Tonka",
    "ks:ks_pop":165,
    "ks:ks_type":"VILLAGE",
    "name:eng_x_preferred":[
        "Niche Tonka"
    ],
    "wof:name":"Niche Tonka",
    "wof:placetype":"locality",
    "wof:population":165
},
  "geometry": {"coordinates":[81.250936,20.210597],"type":"Point"}
}