{
  "type": "Feature",
  "properties": {
    "iso:country":"IN",
    "ks:ks_name":"Chamghati",
    "ks:ks_pop":55,
    "ks:ks_type":"HABITATION",
    "name:eng_x_preferred":[
        "Chamghati"
    ],
    "wof:name":"Chamghati",
    "wof:placetype":"locality",
    "wof:population":55
},
  "geometry": {"coordinates":[85.56141,23.380059],"type":"Point"}
}