{
  "type": "Feature",
  "properties": {
    "iso:country":"IN",
    "ks:ks_name":"Keshawapur",
    "ks:ks_pop":1154,
    "ks:ks_type":"VILLAGE",
    "ks:ks_uagg_main":0,
    "name:eng_x_preferred":[
        "Keshawapur"
    ],
    "wof:name":"Keshawapur",
    "wof:placetype":"neighbourhood",
    "wof:population":1154
},
  "geometry": {"coordinates":[82.258202,26.837464],"type":"Point"}
}