{
  "type": "Feature",
  "properties": {
    "gn:admin1_code":"24",
    "gn:admin2_code":"119.0",
    "gn:asciiname":"Kailu",
    "gn:country_code":"IN",
    "gn:dem":435,
    "gn:feature_class":"P",
    "gn:feature_code":"PPL",
    "gn:name":"Kailu",
    "gn:population":0,
    "gn:timezone":"Asia/Kolkata",
    "iso:country":"IN",
    "name:ara_x_preferred":[
        "\u0643\u0627\u064a\u0644\u0648"
    ],
    "name:ben_x_preferred":[
        "\u0995\u09be\u0987\u09b2\u09c1"
    ],
    "name:deu_x_preferred":[
        "Kailu"
    ],
    "name:ell_x_preferred":[
        "\u039a\u03b1\u03ca\u03bb\u03bf\u03cd"
    ],
    "name:eng_x_preferred":[
        "Kailu"
    ],
    "name:fas_x_preferred":[
        "\u06a9\u0627\u06cc\u0644\u0648"
    ],
    "name:fra_x_preferred":[
        "Kailu"
    ],
    "name:heb_x_preferred":[
        "\u05e7\u05d0\u05d9\u05dc\u05d5"
    ],
    "name:hin_x_preferred":[
        "\u0915\u093e\u0907\u0932\u0942"
    ],
    "name:hun_x_preferred":[
        "Kailu"
    ],
    "name:ind_x_preferred":[
        "Kailu"
    ],
    "name:ita_x_preferred":[
        "Kailu"
    ],
    "name:jpn_x_preferred":[
        "\u958b\u9b6f"
    ],
    "name:kor_x_preferred":[
        "\uce74\uc77c\ub8e8"
    ],
    "name:nld_x_preferred":[
        "Kailu"
    ],
    "name:pol_x_preferred":[
        "Kailu"
    ],
    "name:por_x_preferred":[
        "Kailu"
    ],
    "name:rus_x_preferred":[
        "\u041a\u0430\u0439\u043b\u0443"
    ],
    "name:spa_x_preferred":[
        "Kailu"
    ],
    "name:swe_x_preferred":[
        "Kailu"
    ],
    "name:tur_x_preferred":[
        "Kailu"
    ],
    "name:ukr_x_preferred":[
        "\u041a\u0430\u0439\u043b\u0443"
    ],
    "name:urd_x_preferred":[
        "\u06a9\u06cc\u0644\u0648"
    ],
    "name:vie_x_preferred":[
        "Khai L\u1ed7"
    ],
    "name:zho_cn_x_preferred":[
        "\u5f00\u9c81\u53bf"
    ],
    "name:zho_tw_x_preferred":[
        "\u958b\u9b6f"
    ],
    "wof:name":"Kailu",
    "wof:placetype":"locality"
},
  "geometry": {"coordinates":[74.52571,26.00307],"type":"Point"}
}