{
  "type": "Feature",
  "properties": {
    "iso:country":"IN",
    "ks:ks_name":"Bakcha",
    "ks:ks_pop":306,
    "ks:ks_type":"VILLAGE",
    "ks:ks_uagg_main":0,
    "name:eng_x_preferred":[
        "Bakcha"
    ],
    "wof:name":"Bakcha",
    "wof:placetype":"neighbourhood",
    "wof:population":306
},
  "geometry": {"coordinates":[87.620062,22.825618],"type":"Point"}
}