{
  "type": "Feature",
  "properties": {
    "iso:country":"IN",
    "ks:ks_name":"Kumshet",
    "ks:ks_pop":631,
    "ks:ks_type":"VILLAGE",
    "name:eng_x_preferred":[
        "Kumshet"
    ],
    "wof:name":"Kumshet",
    "wof:placetype":"locality",
    "wof:population":631
},
  "geometry": {"coordinates":[73.712812,19.454902],"type":"Point"}
}