{
  "type": "Feature",
  "properties": {
    "iso:country":"IN",
    "ks:ks_name":"Balijan",
    "ks:ks_pop":519,
    "ks:ks_type":"VILLAGE",
    "name:eng_x_preferred":[
        "Balijan"
    ],
    "wof:name":"Balijan",
    "wof:placetype":"locality",
    "wof:population":519
},
  "geometry": {"coordinates":[94.70213699999999,27.614223],"type":"Point"}
}