{
  "type": "Feature",
  "properties": {
    "gn:admin1_code":"35",
    "gn:admin2_code":"463.0",
    "gn:asciiname":"Kanhaiyadah",
    "gn:country_code":"IN",
    "gn:dem":414,
    "gn:feature_class":"P",
    "gn:feature_code":"PPL",
    "gn:name":"Kanhaiy\u0101dah",
    "gn:population":0,
    "gn:timezone":"Asia/Kolkata",
    "iso:country":"IN",
    "ks:ks_alt_nam":"Kanhaiy\u0101dah",
    "ks:ks_name":"Kanhaiyadah",
    "ks:ks_pop":451,
    "ks:ks_type":"VILLAGE",
    "name:eng_x_preferred":[
        "Kanhaiyadah"
    ],
    "name:eng_x_variant":[
        "Kanhaiy\u0101dah"
    ],
    "wof:name":"Kanhaiyadah",
    "wof:placetype":"locality",
    "wof:population":451
},
  "geometry": {"coordinates":[82.26025199999999,24.095646],"type":"Point"}
}