{
  "type": "Feature",
  "properties": {
    "iso:country":"IN",
    "ks:ks_name":"Uparbesra",
    "ks:ks_pop":233,
    "ks:ks_type":"VILLAGE",
    "name:eng_x_preferred":[
        "Uparbesra"
    ],
    "wof:name":"Uparbesra",
    "wof:placetype":"locality",
    "wof:population":233
},
  "geometry": {"coordinates":[84.56310999999999,23.785642],"type":"Point"}
}