{
  "type": "Feature",
  "properties": {
    "iso:country":"IN",
    "ks:ks_name":"Yaladamakki",
    "ks:ks_pop":37,
    "ks:ks_type":"HABITATION",
    "name:eng_x_preferred":[
        "Yaladamakki"
    ],
    "wof:name":"Yaladamakki",
    "wof:placetype":"locality",
    "wof:population":37
},
  "geometry": {"coordinates":[74.796278,13.97417],"type":"Point"}
}