{
  "type": "Feature",
  "properties": {
    "gn:admin1_code":"21",
    "gn:admin2_code":"395.0",
    "gn:asciiname":"Sikerkupa",
    "gn:country_code":"IN",
    "gn:dem":318,
    "gn:feature_class":"P",
    "gn:feature_code":"PPL",
    "gn:name":"Sikerkupa",
    "gn:population":0,
    "gn:timezone":"Asia/Kolkata",
    "iso:country":"IN",
    "ks:ks_name":"Sikarakupa",
    "ks:ks_pop":220,
    "ks:ks_type":"VILLAGE",
    "name:eng_x_preferred":[
        "Sikarakupa"
    ],
    "name:eng_x_variant":[
        "Sikerkupa"
    ],
    "wof:name":"Sikarakupa",
    "wof:placetype":"locality",
    "wof:population":220
},
  "geometry": {"coordinates":[83.401495,19.923938],"type":"Point"}
}