{
  "type": "Feature",
  "properties": {
    "gn:admin1_code":"38.0",
    "gn:admin2_code":"358.0",
    "gn:asciiname":"Pathra",
    "gn:country_code":"IN",
    "gn:dem":229,
    "gn:feature_class":"P",
    "gn:feature_code":"PPL",
    "gn:name":"Pathr\u0101",
    "gn:population":0,
    "gn:timezone":"Asia/Kolkata",
    "iso:country":"IN",
    "name:und_x_variant":[
        "Pathr\u0101",
        "Narsinh\u0101pur"
    ],
    "wof:name":"Pathra",
    "wof:placetype":"locality"
},
  "geometry": {"coordinates":[84.01600999999999,24.08448],"type":"Point"}
}