{
  "type": "Feature",
  "properties": {
    "iso:country":"IN",
    "ks:ks_name":"Pratappada",
    "ks:ks_pop":415,
    "ks:ks_type":"VILLAGE",
    "ks:ks_uagg_main":0,
    "name:eng_x_preferred":[
        "Pratappada"
    ],
    "wof:name":"Pratappada",
    "wof:placetype":"neighbourhood",
    "wof:population":415
},
  "geometry": {"coordinates":[86.775946,21.425595],"type":"Point"}
}