{
  "type": "Feature",
  "properties": {
    "iso:country":"IN",
    "ks:ks_name":"Duntakna",
    "ks:ks_pop":724,
    "ks:ks_type":"HABITATION",
    "name:eng_x_preferred":[
        "Duntakna"
    ],
    "wof:name":"Duntakna",
    "wof:placetype":"locality",
    "wof:population":724
},
  "geometry": {"coordinates":[88.561592,27.064143],"type":"Point"}
}