{
  "type": "Feature",
  "properties": {
    "iso:country":"IN",
    "ks:ks_name":"Patilpada",
    "ks:ks_pop":97,
    "ks:ks_type":"HABITATION",
    "name:eng_x_preferred":[
        "Patilpada"
    ],
    "wof:name":"Patilpada",
    "wof:placetype":"locality",
    "wof:population":97
},
  "geometry": {"coordinates":[73.14982500000001,19.722051],"type":"Point"}
}