{
  "type": "Feature",
  "properties": {
    "gn:admin1_code":"19.0",
    "gn:admin2_code":"574.0",
    "gn:asciiname":"Bommahalli",
    "gn:country_code":"IN",
    "gn:dem":975,
    "gn:feature_class":"P",
    "gn:feature_code":"PPL",
    "gn:name":"Bommahalli",
    "gn:population":0,
    "gn:timezone":"Asia/Kolkata",
    "iso:country":"IN",
    "ks:ks_name":"Bommadihalli",
    "ks:ks_pop":199,
    "ks:ks_type":"VILLAGE",
    "name:eng_x_preferred":[
        "Bommadihalli"
    ],
    "name:eng_x_variant":[
        "Bommahalli"
    ],
    "wof:name":"Bommadihalli",
    "wof:placetype":"locality",
    "wof:population":199
},
  "geometry": {"coordinates":[75.835178,13.193519],"type":"Point"}
}