{
  "type": "Feature",
  "properties": {
    "iso:country":"IN",
    "ks:ks_alt_nam":"Madan pur",
    "ks:ks_name":"Madan Pur",
    "ks:ks_pop":1238,
    "ks:ks_type":"HABITATION",
    "name:eng_x_preferred":[
        "Madan Pur"
    ],
    "wof:name":"Madan Pur",
    "wof:placetype":"locality",
    "wof:population":1238
},
  "geometry": {"coordinates":[76.979433,29.648888],"type":"Point"}
}