{
  "type": "Feature",
  "properties": {
    "iso:country":"IN",
    "ks:ks_name":"Purwa Mohan",
    "ks:ks_pop":270,
    "ks:ks_type":"HABITATION",
    "ks:ks_uagg_main":0,
    "name:eng_x_preferred":[
        "Purwa Mohan"
    ],
    "wof:name":"Purwa Mohan",
    "wof:placetype":"neighbourhood",
    "wof:population":270
},
  "geometry": {"coordinates":[79.459279,26.772801],"type":"Point"}
}