{
  "type": "Feature",
  "properties": {
    "gn:admin1_code":"34.0",
    "gn:admin2_code":"221.0",
    "gn:asciiname":"Sobhan",
    "gn:country_code":"IN",
    "gn:dem":52,
    "gn:feature_class":"P",
    "gn:feature_code":"PPL",
    "gn:name":"Sobhan",
    "gn:population":0,
    "gn:timezone":"Asia/Kolkata",
    "iso:country":"IN",
    "name:tel_x_preferred":[
        "\u0c36\u0c4b\u0c2d\u0c28\u0c4d"
    ],
    "wof:name":"Sobhan",
    "wof:placetype":"locality"
},
  "geometry": {"coordinates":[85.91481,25.8491],"type":"Point"}
}