{
  "type": "Feature",
  "properties": {
    "iso:country":"IN",
    "ks:ks_name":"Haratoli",
    "ks:ks_pop":60,
    "ks:ks_type":"HABITATION",
    "name:eng_x_preferred":[
        "Haratoli"
    ],
    "wof:name":"Haratoli",
    "wof:placetype":"locality",
    "wof:population":60
},
  "geometry": {"coordinates":[85.489558,22.807306],"type":"Point"}
}