{
  "type": "Feature",
  "properties": {
    "iso:country":"IN",
    "ks:ks_name":"Sottabapanna Guda",
    "ks:ks_pop":89,
    "ks:ks_type":"HABITATION",
    "name:eng_x_preferred":[
        "Sottabapanna Guda"
    ],
    "wof:name":"Sottabapanna Guda",
    "wof:placetype":"locality",
    "wof:population":89
},
  "geometry": {"coordinates":[83.69004700000001,18.796028],"type":"Point"}
}