{
  "type": "Feature",
  "properties": {
    "gn:admin1_code":"25.0",
    "gn:admin2_code":"612",
    "gn:asciiname":"Eriyodu",
    "gn:country_code":"IN",
    "gn:dem":265,
    "gn:feature_class":"P",
    "gn:feature_code":"PPL",
    "gn:name":"Eriyodu",
    "gn:population":0,
    "gn:timezone":"Asia/Kolkata",
    "iso:country":"IN",
    "name:bpy_x_preferred":[
        "\u098f\u09b0\u09bf\u0993\u09a1\u09c1"
    ],
    "name:ceb_x_preferred":[
        "Eriyodu"
    ],
    "name:ita_x_preferred":[
        "Eriodu"
    ],
    "name:msa_x_preferred":[
        "Eriodu"
    ],
    "name:new_x_preferred":[
        "\u0907\u0930\u093f\u0913\u0921\u0941"
    ],
    "name:nld_x_preferred":[
        "Eriodu"
    ],
    "name:por_x_preferred":[
        "Eriodu"
    ],
    "name:swe_x_preferred":[
        "Eriyodu"
    ],
    "name:tam_x_preferred":[
        "\u0b8e\u0bb0\u0bbf\u0baf\u0bcb\u0b9f\u0bc1"
    ],
    "name:und_x_variant":[
        "Eriyodi"
    ],
    "name:vie_x_preferred":[
        "Eriodu"
    ],
    "name:zho_x_preferred":[
        "\u57c3\u91cc\u5965\u675c"
    ],
    "wof:name":"Eriyodu",
    "wof:placetype":"locality"
},
  "geometry": {"coordinates":[78.06268,10.51724],"type":"Point"}
}