{
  "type": "Feature",
  "properties": {
    "gn:admin1_code":"25.0",
    "gn:admin2_code":"633.0",
    "gn:asciiname":"Devarayampalaiyam",
    "gn:country_code":"IN",
    "gn:dem":359,
    "gn:feature_class":"P",
    "gn:feature_code":"PPL",
    "gn:name":"Devar\u0101yamp\u0101laiyam",
    "gn:population":0,
    "gn:timezone":"Asia/Kolkata",
    "iso:country":"IN",
    "ks:ks_name":"Devarayanpalayam",
    "ks:ks_pop":1225,
    "ks:ks_type":"HABITATION",
    "ks:ks_uagg_main":0,
    "name:eng_x_preferred":[
        "Devarayanpalayam"
    ],
    "wof:name":"Devarayanpalayam",
    "wof:placetype":"locality",
    "wof:population":1225
},
  "geometry": {"coordinates":[77.180432,11.050469],"type":"Point"}
}