{
  "type": "Feature",
  "properties": {
    "iso:country":"IN",
    "ks:ks_name":"Baskheda",
    "ks:ks_pop":167,
    "ks:ks_type":"HABITATION",
    "name:eng_x_preferred":[
        "Baskheda"
    ],
    "wof:name":"Baskheda",
    "wof:placetype":"locality",
    "wof:population":167
},
  "geometry": {"coordinates":[79.090878,22.948638],"type":"Point"}
}