{
  "type": "Feature",
  "properties": {
    "iso:country":"IN",
    "ks:ks_name":"Khaspara",
    "ks:ks_pop":7,
    "ks:ks_type":"HABITATION",
    "name:eng_x_preferred":[
        "Khaspara"
    ],
    "wof:name":"Khaspara",
    "wof:placetype":"locality",
    "wof:population":7
},
  "geometry": {"coordinates":[81.402019,19.640956],"type":"Point"}
}