{
  "type": "Feature",
  "properties": {
    "gn:admin1_code":"21",
    "gn:admin2_code":"399.0",
    "gn:asciiname":"Bandhuguda",
    "gn:country_code":"IN",
    "gn:dem":260,
    "gn:feature_class":"P",
    "gn:feature_code":"PPL",
    "gn:name":"Bandhuguda",
    "gn:population":0,
    "gn:timezone":"Asia/Kolkata",
    "iso:country":"IN",
    "wof:name":"Bandhuguda",
    "wof:placetype":"locality"
},
  "geometry": {"coordinates":[82.16276999999999,18.48081],"type":"Point"}
}