{
  "type": "Feature",
  "properties": {
    "gn:admin1_code":"36.0",
    "gn:admin2_code":"183.0",
    "gn:asciiname":"Kasturi",
    "gn:country_code":"IN",
    "gn:dem":111,
    "gn:feature_class":"P",
    "gn:feature_code":"PPL",
    "gn:name":"Kasturi",
    "gn:population":0,
    "gn:timezone":"Asia/Kolkata",
    "iso:country":"IN",
    "name:nld_x_preferred":[
        "Kasturi"
    ],
    "name:tel_x_preferred":[
        "\u0c15\u0c38\u0c4d\u0c24\u0c42\u0c30\u0c3f"
    ],
    "wof:name":"Kasturi",
    "wof:placetype":"locality"
},
  "geometry": {"coordinates":[81.74083,27.13962],"type":"Point"}
}