{
  "type": "Feature",
  "properties": {
    "gn:admin1_code":"25.0",
    "gn:admin2_code":"620.0",
    "gn:asciiname":"Vastachavadi",
    "gn:country_code":"IN",
    "gn:dem":80,
    "gn:feature_class":"P",
    "gn:feature_code":"PPL",
    "gn:name":"Vast\u0101ch\u0101vadi",
    "gn:population":0,
    "gn:timezone":"Asia/Kolkata",
    "iso:country":"IN",
    "wof:name":"Vastachavadi",
    "wof:placetype":"neighbourhood"
},
  "geometry": {"coordinates":[79.10577000000001,10.73445],"type":"Point"}
}