{
  "type": "Feature",
  "properties": {
    "iso:country":"IN",
    "ks:ks_name":"Sasipalu",
    "ks:ks_pop":40,
    "ks:ks_type":"HABITATION",
    "name:eng_x_preferred":[
        "Sasipalu"
    ],
    "wof:name":"Sasipalu",
    "wof:placetype":"locality",
    "wof:population":40
},
  "geometry": {"coordinates":[75.063542,13.720543],"type":"Point"}
}