{
  "type": "Feature",
  "properties": {
    "iso:country":"IN",
    "ks:ks_name":"Chiku Dih",
    "ks:ks_pop":174,
    "ks:ks_type":"HABITATION",
    "ks:ks_uagg_main":0,
    "name:eng_x_preferred":[
        "Chiku Dih"
    ],
    "wof:name":"Chiku Dih",
    "wof:placetype":"neighbourhood",
    "wof:population":174
},
  "geometry": {"coordinates":[82.27448800000001,27.314115],"type":"Point"}
}