{
  "type": "Feature",
  "properties": {
    "iso:country":"IN",
    "ks:ks_name":"Amba Khorea N",
    "ks:ks_pop":317,
    "ks:ks_type":"HABITATION",
    "name:eng_x_preferred":[
        "Amba Khorea N"
    ],
    "wof:name":"Amba Khorea N",
    "wof:placetype":"locality",
    "wof:population":317
},
  "geometry": {"coordinates":[83.49955799999999,24.076464],"type":"Point"}
}