{
  "type": "Feature",
  "properties": {
    "iso:country":"IN",
    "ks:ks_name":"Narkelpara",
    "ks:ks_pop":512,
    "ks:ks_type":"HABITATION",
    "name:eng_x_preferred":[
        "Narkelpara"
    ],
    "wof:name":"Narkelpara",
    "wof:placetype":"locality",
    "wof:population":512
},
  "geometry": {"coordinates":[89.52073300000001,26.350985],"type":"Point"}
}