{
  "type": "Feature",
  "properties": {
    "iso:country":"IN",
    "ks:ks_name":"Pure Ram Sawar",
    "ks:ks_pop":105,
    "ks:ks_type":"HABITATION",
    "name:eng_x_preferred":[
        "Pure Ram Sawar"
    ],
    "wof:name":"Pure Ram Sawar",
    "wof:placetype":"locality",
    "wof:population":105
},
  "geometry": {"coordinates":[81.95887500000001,26.741436],"type":"Point"}
}