{
  "type": "Feature",
  "properties": {
    "iso:country":"IN",
    "ks:ks_name":"Gurgu Alias Irgu",
    "ks:ks_pop":734,
    "ks:ks_type":"HABITATION",
    "name:eng_x_preferred":[
        "Gurgu Alias Irgu"
    ],
    "wof:name":"Gurgu Alias Irgu",
    "wof:placetype":"locality",
    "wof:population":734
},
  "geometry": {"coordinates":[84.433464,23.713615],"type":"Point"}
}