{
  "type": "Feature",
  "properties": {
    "iso:country":"IN",
    "ks:ks_name":"Layaradasarahalli",
    "ks:ks_pop":249,
    "ks:ks_type":"VILLAGE",
    "name:eng_x_preferred":[
        "Layaradasarahalli"
    ],
    "wof:name":"Layaradasarahalli",
    "wof:placetype":"locality",
    "wof:population":249
},
  "geometry": {"coordinates":[76.631027,13.794255],"type":"Point"}
}