{
  "type": "Feature",
  "properties": {
    "iso:country":"IN",
    "ks:ks_alt_nam":"Thannan thoppu colony",
    "ks:ks_name":"Thannan Thoppu Colony",
    "ks:ks_pop":321,
    "ks:ks_type":"HABITATION",
    "name:eng_x_preferred":[
        "Thannan Thoppu Colony"
    ],
    "wof:name":"Thannan Thoppu Colony",
    "wof:placetype":"locality",
    "wof:population":321
},
  "geometry": {"coordinates":[79.96305599999999,12.62168],"type":"Point"}
}