{
  "type": "Feature",
  "properties": {
    "iso:country":"IN",
    "ks:ks_name":"Hanuman Purwa",
    "ks:ks_pop":347,
    "ks:ks_type":"HABITATION",
    "name:eng_x_preferred":[
        "Hanuman Purwa"
    ],
    "wof:name":"Hanuman Purwa",
    "wof:placetype":"locality",
    "wof:population":347
},
  "geometry": {"coordinates":[82.34416400000001,27.11658],"type":"Point"}
}