{
  "type": "Feature",
  "properties": {
    "iso:country":"IN",
    "ks:ks_name":"Pipalguda",
    "ks:ks_pop":131,
    "ks:ks_type":"VILLAGE",
    "name:eng_x_preferred":[
        "Pipalguda"
    ],
    "wof:name":"Pipalguda",
    "wof:placetype":"locality",
    "wof:population":131
},
  "geometry": {"coordinates":[83.340616,19.443215],"type":"Point"}
}