{
  "type": "Feature",
  "properties": {
    "gn:admin1_code":"24",
    "gn:admin2_code":"125.0",
    "gn:asciiname":"Mal",
    "gn:country_code":"IN",
    "gn:dem":308,
    "gn:feature_class":"P",
    "gn:feature_code":"PPL",
    "gn:name":"M\u0101l",
    "gn:population":0,
    "gn:timezone":"Asia/Kolkata",
    "iso:country":"IN",
    "ks:ks_alt_nam":"M\u0101l",
    "ks:ks_name":"Mal",
    "ks:ks_type":"VILLAGE",
    "name:eng_x_preferred":[
        "Mal"
    ],
    "name:eng_x_variant":[
        "M\u0101l"
    ],
    "wof:name":"Mal",
    "wof:placetype":"locality"
},
  "geometry": {"coordinates":[74.469577,23.226389],"type":"Point"}
}