{
  "type": "Feature",
  "properties": {
    "gn:admin1_code":"36",
    "gn:admin2_code":"136.0",
    "gn:asciiname":"Tanda",
    "gn:country_code":"IN",
    "gn:dem":208,
    "gn:feature_class":"P",
    "gn:feature_code":"PPL",
    "gn:name":"T\u0101nda",
    "gn:population":44822,
    "gn:timezone":"Asia/Kolkata",
    "iso:country":"IN",
    "name:hin_x_preferred":[
        "\u091f\u093e\u0902\u0921\u093e"
    ],
    "name:ita_x_preferred":[
        "Tanda"
    ],
    "name:msa_x_preferred":[
        "Tanda"
    ],
    "name:nld_x_preferred":[
        "Tanda"
    ],
    "name:pol_x_preferred":[
        "Tanda"
    ],
    "name:und_x_variant":[
        "T\u0101nda"
    ],
    "name:urd_x_preferred":[
        "\u0679\u0627\u0646\u0688\u0627"
    ],
    "name:vie_x_preferred":[
        "Tanda"
    ],
    "wof:name":"Tanda",
    "wof:placetype":"locality",
    "wof:population":44822
},
  "geometry": {"coordinates":[78.94186999999999,28.97621],"type":"Point"}
}