{
  "type": "Feature",
  "properties": {
    "gn:admin1_code":"36",
    "gn:admin2_code":"136.0",
    "gn:asciiname":"Tanda",
    "gn:country_code":"IN",
    "gn:dem":208,
    "gn:feature_class":"P",
    "gn:feature_code":"PPL",
    "gn:name":"T\u0101nda",
    "gn:population":44822,
    "gn:timezone":"Asia/Kolkata",
    "iso:country":"IN",
    "name:und_x_variant":[
        "T\u0101nda"
    ],
    "wof:name":"Tanda",
    "wof:placetype":"locality",
    "wof:population":44822
},
  "geometry": {"coordinates":[78.94186999999999,28.97621],"type":"Point"}
}