{
  "type": "Feature",
  "properties": {
    "iso:country":"IN",
    "ks:ks_alt_nam":"Nagena agrahara",
    "ks:ks_name":"Nagena Agrahara",
    "ks:ks_pop":4,
    "ks:ks_type":"HABITATION",
    "name:eng_x_preferred":[
        "Nagena Agrahara"
    ],
    "wof:name":"Nagena Agrahara",
    "wof:placetype":"locality",
    "wof:population":4
},
  "geometry": {"coordinates":[77.778802,12.906863],"type":"Point"}
}