{
  "type": "Feature",
  "properties": {
    "gn:admin1_code":"34.0",
    "gn:admin2_code":"212.0",
    "gn:asciiname":"Pinda",
    "gn:country_code":"IN",
    "gn:dem":31,
    "gn:feature_class":"P",
    "gn:feature_code":"PPL",
    "gn:name":"Pinda",
    "gn:population":0,
    "gn:timezone":"Asia/Kolkata",
    "iso:country":"IN",
    "name:ceb_x_preferred":[
        "Pinda"
    ],
    "name:pol_x_preferred":[
        "Pinda"
    ],
    "name:por_x_preferred":[
        "Pinda"
    ],
    "name:swe_x_preferred":[
        "Pinda"
    ],
    "wof:name":"Pinda",
    "wof:placetype":"locality"
},
  "geometry": {"coordinates":[87.64052,25.50223],"type":"Point"}
}