{
  "type": "Feature",
  "properties": {
    "gn:admin1_code":"36",
    "gn:admin2_code":"163.0",
    "gn:asciiname":"Banjara",
    "gn:country_code":"IN",
    "gn:dem":133,
    "gn:feature_class":"P",
    "gn:feature_code":"PPL",
    "gn:name":"Banj\u0101ra",
    "gn:population":0,
    "gn:timezone":"Asia/Kolkata",
    "iso:country":"IN",
    "name:bel_x_preferred":[
        "\u0411\u0430\u043d\u0434\u0436\u0430\u0440\u0430"
    ],
    "name:bih_x_preferred":[
        "\u092c\u0902\u091c\u093e\u0930\u093e"
    ],
    "name:cat_x_preferred":[
        "Lambadi"
    ],
    "name:hin_x_preferred":[
        "\u0932\u0902\u092c\u093e\u0923\u0940"
    ],
    "name:hun_x_preferred":[
        "Bandzs\u00e1r\u00e1k"
    ],
    "name:kan_x_preferred":[
        "\u0cac\u0c82\u0c9c\u0cbe\u0cb0\u0ccd"
    ],
    "name:lit_x_preferred":[
        "Band\u017earai"
    ],
    "name:mal_x_preferred":[
        "\u0d32\u0d02\u0d2c\u0d3e\u0d1f\u0d3f"
    ],
    "name:mar_x_preferred":[
        "\u092c\u0902\u091c\u093e\u0930\u093e"
    ],
    "name:nor_x_preferred":[
        "Lambadier"
    ],
    "name:pan_x_preferred":[
        "\u0a2c\u0a23\u0a1c\u0a3e\u0a30\u0a3e"
    ],
    "name:pol_x_preferred":[
        "Band\u017cara"
    ],
    "name:rmy_x_preferred":[
        "Banjara"
    ],
    "name:rus_x_preferred":[
        "\u0411\u0430\u043d\u0434\u0436\u0430\u0440\u044b"
    ],
    "name:san_x_preferred":[
        "\u0932\u092e\u094d\u092c\u093e\u0923\u093f\u091c\u0928\u093e\u0919\u094d\u0917\u0903"
    ],
    "name:tam_x_preferred":[
        "\u0bb2\u0bae\u0bcd\u0baa\u0bbe\u0b9f\u0bbf"
    ],
    "name:tel_x_preferred":[
        "\u0c32\u0c02\u0c2c\u0c3e\u0c21\u0c3f"
    ],
    "wof:name":"Banjara",
    "wof:placetype":"locality"
},
  "geometry": {"coordinates":[79.84845,26.41793],"type":"Point"}
}