{
  "type": "Feature",
  "properties": {
    "iso:country":"IN",
    "ks:ks_name":"Ghateha",
    "ks:ks_pop":2569,
    "ks:ks_type":"VILLAGE",
    "name:eng_x_preferred":[
        "Ghateha"
    ],
    "wof:name":"Ghateha",
    "wof:placetype":"locality",
    "wof:population":2569
},
  "geometry": {"coordinates":[81.516707,25.129951],"type":"Point"}
}