{
  "type": "Feature",
  "properties": {
    "gn:admin1_code":"19.0",
    "gn:admin2_code":"573.0",
    "gn:asciiname":"Annur",
    "gn:country_code":"IN",
    "gn:dem":639,
    "gn:feature_class":"P",
    "gn:feature_code":"PPL",
    "gn:name":"Ann\u016br",
    "gn:population":0,
    "gn:timezone":"Asia/Kolkata",
    "iso:country":"IN",
    "ks:ks_alt_nam":"Ann\u016br",
    "ks:ks_name":"Annur",
    "ks:ks_pop":3528,
    "ks:ks_type":"VILLAGE",
    "ks:ks_uagg_main":0,
    "name:bpy_x_preferred":[
        "\u0986\u09a8\u09cd\u09a8\u09c1\u09b0"
    ],
    "name:ceb_x_preferred":[
        "Annur"
    ],
    "name:eng_x_preferred":[
        "Annur"
    ],
    "name:eng_x_variant":[
        "Ann\u016br"
    ],
    "name:ita_x_preferred":[
        "Annur"
    ],
    "name:msa_x_preferred":[
        "Annur"
    ],
    "name:new_x_preferred":[
        "\u0905\u0928\u094d\u0928\u0941\u0930"
    ],
    "name:nld_x_preferred":[
        "Annur"
    ],
    "name:por_x_preferred":[
        "Annur"
    ],
    "name:swe_x_preferred":[
        "Annur"
    ],
    "name:tam_x_preferred":[
        "\u0b85\u0ba9\u0bcd\u0ba9\u0bc2\u0bb0\u0bcd"
    ],
    "name:urd_x_preferred":[
        "\u0627\u0646\u0648\u0631 \u062a\u0639\u0642\u0644\u06c1"
    ],
    "name:vie_x_preferred":[
        "Annur"
    ],
    "wof:name":"Annur",
    "wof:placetype":"neighbourhood",
    "wof:population":3528
},
  "geometry": {"coordinates":[77.046115,12.480312],"type":"Point"}
}