{
  "type": "Feature",
  "properties": {
    "gn:admin1_code":"36",
    "gn:admin2_code":"137.0",
    "gn:asciiname":"Malipura",
    "gn:country_code":"IN",
    "gn:dem":194,
    "gn:feature_class":"P",
    "gn:feature_code":"PPL",
    "gn:name":"M\u0101lipura",
    "gn:population":0,
    "gn:timezone":"Asia/Kolkata",
    "iso:country":"IN",
    "name:hin_x_preferred":[
        "\u092e\u093e\u0932\u0940\u092a\u0941\u0930\u093e"
    ],
    "wof:name":"Malipura",
    "wof:placetype":"locality"
},
  "geometry": {"coordinates":[78.24833000000002,28.54112000000001],"type":"Point"}
}