{
  "type": "Feature",
  "properties": {
    "iso:country":"IN",
    "ks:ks_name":"Madanpur",
    "ks:ks_type":"VILLAGE",
    "name:eng_x_preferred":[
        "Madanpur"
    ],
    "wof:name":"Madanpur",
    "wof:placetype":"neighbourhood"
},
  "geometry": {"coordinates":[78.16372699999999,26.303172],"type":"Point"}
}