{
  "type": "Feature",
  "properties": {
    "iso:country":"IN",
    "ks:ks_name":"Pandabbil",
    "ks:ks_pop":166,
    "ks:ks_type":"VILLAGE",
    "name:eng_x_preferred":[
        "Pandabbil"
    ],
    "wof:name":"Pandabbil",
    "wof:placetype":"locality",
    "wof:population":166
},
  "geometry": {"coordinates":[88.368315,25.67359],"type":"Point"}
}