{
  "type": "Feature",
  "properties": {
    "gn:admin1_code":"3.0",
    "gn:admin2_code":"314.0",
    "gn:asciiname":"Inglinggaon",
    "gn:country_code":"IN",
    "gn:dem":676,
    "gn:feature_class":"P",
    "gn:feature_code":"PPL",
    "gn:name":"Inglingg\u0101on",
    "gn:population":0,
    "gn:timezone":"Asia/Kolkata",
    "iso:country":"IN",
    "wof:name":"Inglinggaon",
    "wof:placetype":"locality"
},
  "geometry": {"coordinates":[93.34198000000001,26.19154],"type":"Point"}
}