{
  "type": "Feature",
  "properties": {
    "gn:admin1_code":"2.0",
    "gn:admin2_code":"550.0",
    "gn:asciiname":"Toguruvandlapalem",
    "gn:country_code":"IN",
    "gn:dem":67,
    "gn:feature_class":"P",
    "gn:feature_code":"PPL",
    "gn:name":"Tog\u016bruv\u0101ndlap\u0101lem",
    "gn:population":0,
    "gn:timezone":"Asia/Kolkata",
    "iso:country":"IN",
    "wof:name":"Toguruvandlapalem",
    "wof:placetype":"locality"
},
  "geometry": {"coordinates":[79.68369,14.89567],"type":"Point"}
}