{
  "type": "Feature",
  "properties": {
    "iso:country":"IN",
    "ks:ks_alt_nam":"Sevya thanda",
    "ks:ks_name":"Sevya Thanda",
    "ks:ks_pop":103,
    "ks:ks_type":"HABITATION",
    "name:eng_x_preferred":[
        "Sevya Thanda"
    ],
    "wof:name":"Sevya Thanda",
    "wof:placetype":"locality",
    "wof:population":103
},
  "geometry": {"coordinates":[78.822317,16.716828],"type":"Point"}
}