{
  "type": "Feature",
  "properties": {
    "iso:country":"IN",
    "ks:ks_name":"Chautanga",
    "ks:ks_pop":64,
    "ks:ks_type":"HABITATION",
    "name:eng_x_preferred":[
        "Chautanga"
    ],
    "wof:name":"Chautanga",
    "wof:placetype":"locality",
    "wof:population":64
},
  "geometry": {"coordinates":[85.24845500000001,23.224409],"type":"Point"}
}