{
  "type": "Feature",
  "properties": {
    "iso:country":"IN",
    "ks:ks_name":"Singhpur",
    "ks:ks_type":"VILLAGE",
    "name:eng_x_preferred":[
        "Singhpur"
    ],
    "wof:name":"Singhpur",
    "wof:placetype":"locality"
},
  "geometry": {"coordinates":[84.20956700000001,23.103644],"type":"Point"}
}