{
  "type": "Feature",
  "properties": {
    "gn:admin1_code":"24.0",
    "gn:admin2_code":"128.0",
    "gn:asciiname":"Sunda",
    "gn:country_code":"IN",
    "gn:dem":327,
    "gn:feature_class":"P",
    "gn:feature_code":"PPL",
    "gn:name":"S\u016bnda",
    "gn:population":0,
    "gn:timezone":"Asia/Kolkata",
    "iso:country":"IN",
    "name:cat_x_preferred":[
        "Sonda"
    ],
    "name:ceb_x_preferred":[
        "Sunda"
    ],
    "name:deu_x_preferred":[
        "Sunda"
    ],
    "name:fin_x_preferred":[
        "Sunda"
    ],
    "name:fra_x_preferred":[
        "Sunda"
    ],
    "name:heb_x_preferred":[
        "\u05e1\u05d5\u05e0\u05d3\u05d4"
    ],
    "name:hin_x_preferred":[
        "\u0938\u0941\u0928\u094d\u0926"
    ],
    "name:ind_x_preferred":[
        "Sunda"
    ],
    "name:jav_x_preferred":[
        "Sundha"
    ],
    "name:jpn_x_preferred":[
        "\u30b9\u30f3\u30c0\u5217\u5cf6"
    ],
    "name:lit_x_preferred":[
        "Sunda"
    ],
    "name:nld_x_preferred":[
        "Sunda"
    ],
    "name:sun_x_preferred":[
        "Sunda"
    ],
    "name:swe_x_preferred":[
        "Sunda"
    ],
    "name:tgl_x_preferred":[
        "Sunda"
    ],
    "name:tha_x_preferred":[
        "\u0e0b\u0e38\u0e19\u0e14\u0e32"
    ],
    "name:ukr_x_preferred":[
        "\u0421\u0443\u043d\u0434\u0430"
    ],
    "wof:name":"Sunda",
    "wof:placetype":"locality"
},
  "geometry": {"coordinates":[76.84265000000001,25.17567],"type":"Point"}
}