{
  "type": "Feature",
  "properties": {
    "iso:country":"IN",
    "qs:name":"Da Gaon",
    "qs:name_adm0":"India",
    "qs:name_adm1":"Assam",
    "qs:photos":6,
    "qs:photos_1k":1,
    "qs:photos_9k":1,
    "qs:photos_9r":1,
    "qs:photos_all":6,
    "qs:photos_sr":1,
    "qs:placetype":"Town",
    "qs:pop_sr":"0",
    "wof:name":"Da Gaon",
    "wof:placetype":"locality"
},
  "geometry": {"coordinates":[94.7037785,27.0215125],"type":"Point"}
}