{
  "type": "Feature",
  "properties": {
    "iso:country":"IN",
    "ks:ks_name":"Nagdha",
    "ks:ks_pop":24,
    "ks:ks_type":"HABITATION",
    "name:eng_x_preferred":[
        "Nagdha"
    ],
    "wof:name":"Nagdha",
    "wof:placetype":"locality",
    "wof:population":24
},
  "geometry": {"coordinates":[77.94991400000001,26.19296],"type":"Point"}
}