{
  "type": "Feature",
  "properties": {
    "iso:country":"IN",
    "ks:ks_name":"Kulum",
    "ks:ks_pop":421,
    "ks:ks_type":"VILLAGE",
    "name:eng_x_preferred":[
        "Kulum"
    ],
    "wof:name":"Kulum",
    "wof:placetype":"locality",
    "wof:population":421
},
  "geometry": {"coordinates":[85.26777300000001,22.828579],"type":"Point"}
}