{
  "type": "Feature",
  "properties": {
    "gn:admin1_code":"36",
    "gn:admin2_code":"146.0",
    "gn:asciiname":"Izzatnagar",
    "gn:country_code":"IN",
    "gn:dem":169,
    "gn:feature_class":"P",
    "gn:feature_code":"PPL",
    "gn:name":"Izzatnagar",
    "gn:population":0,
    "gn:timezone":"Asia/Kolkata",
    "iso:country":"IN",
    "name:fas_x_preferred":[
        "\u0639\u0632\u062a\u200c\u0646\u06af\u0631"
    ],
    "name:hin_x_preferred":[
        "\u0907\u091c\u094d\u091c\u0924 \u0928\u0917\u0930"
    ],
    "name:mar_x_preferred":[
        "\u0907\u091c\u094d\u091c\u0924\u0928\u0917\u0930"
    ],
    "wof:name":"Izzatnagar",
    "wof:placetype":"locality"
},
  "geometry": {"coordinates":[78.00971,27.04928],"type":"Point"}
}