{
  "type": "Feature",
  "properties": {
    "gn:admin1_code":"13.0",
    "gn:admin2_code":"600.0",
    "gn:asciiname":"Chakkuvarakal",
    "gn:country_code":"IN",
    "gn:dem":54,
    "gn:feature_class":"P",
    "gn:feature_code":"PPL",
    "gn:name":"Chakkuvarakal",
    "gn:population":0,
    "gn:timezone":"Asia/Kolkata",
    "iso:country":"IN",
    "ks:ks_name":"Chakkuvarakkal",
    "ks:ks_pop":243,
    "ks:ks_type":"VILLAGE",
    "name:eng_x_preferred":[
        "Chakkuvarakkal"
    ],
    "name:eng_x_variant":[
        "Chakkuvarakal"
    ],
    "wof:name":"Chakkuvarakkal",
    "wof:placetype":"locality",
    "wof:population":243
},
  "geometry": {"coordinates":[76.86681900000001,8.994881],"type":"Point"}
}