{
  "type": "Feature",
  "properties": {
    "iso:country":"IN",
    "ks:ks_name":"Paching",
    "ks:ks_pop":306,
    "ks:ks_type":"VILLAGE",
    "name:eng_x_preferred":[
        "Paching"
    ],
    "wof:name":"Paching",
    "wof:placetype":"locality",
    "wof:population":306
},
  "geometry": {"coordinates":[83.181049,18.855743],"type":"Point"}
}