{
  "type": "Feature",
  "properties": {
    "gn:admin1_code":"23.0",
    "gn:admin2_code":"42.0",
    "gn:asciiname":"Jhatra",
    "gn:country_code":"IN",
    "gn:dem":212,
    "gn:feature_class":"P",
    "gn:feature_code":"PPL",
    "gn:name":"Jhatra",
    "gn:population":0,
    "gn:timezone":"Asia/Kolkata",
    "iso:country":"IN",
    "wof:name":"Jhatra",
    "wof:placetype":"locality"
},
  "geometry": {"coordinates":[75.04012,30.93581],"type":"Point"}
}