{
  "type": "Feature",
  "properties": {
    "iso:country":"IN",
    "ks:ks_name":"Badebodal",
    "ks:ks_pop":583,
    "ks:ks_type":"VILLAGE",
    "name:eng_x_preferred":[
        "Badebodal"
    ],
    "wof:name":"Badebodal",
    "wof:placetype":"locality",
    "wof:population":583
},
  "geometry": {"coordinates":[81.999797,18.933034],"type":"Point"}
}