{
  "type": "Feature",
  "properties": {
    "iso:country":"IN",
    "ks:ks_name":"Mavlatwadi",
    "ks:ks_pop":125,
    "ks:ks_type":"HABITATION",
    "name:eng_x_preferred":[
        "Mavlatwadi"
    ],
    "wof:name":"Mavlatwadi",
    "wof:placetype":"locality",
    "wof:population":125
},
  "geometry": {"coordinates":[73.60083299999999,17.107778],"type":"Point"}
}