{
  "type": "Feature",
  "properties": {
    "iso:country":"IN",
    "ks:ks_name":"Naiyon Ki Dhani",
    "ks:ks_pop":882,
    "ks:ks_type":"HABITATION",
    "name:eng_x_preferred":[
        "Naiyon Ki Dhani"
    ],
    "wof:name":"Naiyon Ki Dhani",
    "wof:placetype":"locality",
    "wof:population":882
},
  "geometry": {"coordinates":[71.691413,24.949468],"type":"Point"}
}