{
  "type": "Feature",
  "properties": {
    "iso:country":"IN",
    "ks:ks_name":"Dhanwar",
    "ks:ks_pop":75,
    "ks:ks_type":"VILLAGE",
    "name:eng_x_preferred":[
        "Dhanwar"
    ],
    "wof:name":"Dhanwar",
    "wof:placetype":"locality",
    "wof:population":75
},
  "geometry": {"coordinates":[83.45682600000001,23.942515],"type":"Point"}
}