{
  "type": "Feature",
  "properties": {
    "iso:country":"IN",
    "ks:ks_name":"Brahman Basti",
    "ks:ks_pop":170,
    "ks:ks_type":"HABITATION",
    "name:eng_x_preferred":[
        "Brahman Basti"
    ],
    "wof:name":"Brahman Basti",
    "wof:placetype":"locality",
    "wof:population":170
},
  "geometry": {"coordinates":[82.278553,25.81088],"type":"Point"}
}