{
  "type": "Feature",
  "properties": {
    "iso:country":"IN",
    "ks:ks_name":"Deesa",
    "ks:ks_pop":1167,
    "ks:ks_type":"VILLAGE",
    "name:eng_x_preferred":[
        "Deesa"
    ],
    "wof:name":"Deesa",
    "wof:placetype":"locality",
    "wof:population":1167
},
  "geometry": {"coordinates":[75.43620199999999,27.191254],"type":"Point"}
}