{
  "type": "Feature",
  "properties": {
    "iso:country":"IN",
    "ks:ks_name":"Kanikot Lagga Chora Guth",
    "ks:ks_pop":154,
    "ks:ks_type":"HABITATION",
    "name:eng_x_preferred":[
        "Kanikot Lagga Chora Guth"
    ],
    "wof:name":"Kanikot Lagga Chora Guth",
    "wof:placetype":"locality",
    "wof:population":154
},
  "geometry": {"coordinates":[79.892583,29.479315],"type":"Point"}
}