{
  "type": "Feature",
  "properties": {
    "iso:country":"IN",
    "ks:ks_alt_nam":"Kota FV",
    "ks:ks_name":"Kota Fv",
    "ks:ks_pop":121,
    "ks:ks_type":"HABITATION",
    "name:eng_x_preferred":[
        "Kota Fv"
    ],
    "wof:name":"Kota Fv",
    "wof:placetype":"locality",
    "wof:population":121
},
  "geometry": {"coordinates":[80.16340700000001,22.332285],"type":"Point"}
}