{
  "type": "Feature",
  "properties": {
    "iso:country":"IN",
    "ks:ks_name":"Odalumane",
    "ks:ks_pop":52,
    "ks:ks_type":"HABITATION",
    "name:eng_x_preferred":[
        "Odalumane"
    ],
    "wof:name":"Odalumane",
    "wof:placetype":"locality",
    "wof:population":52
},
  "geometry": {"coordinates":[75.263502,13.713272],"type":"Point"}
}