{
  "type": "Feature",
  "properties": {
    "gn:admin1_code":"35",
    "gn:admin2_code":"429.0",
    "gn:asciiname":"Gora",
    "gn:country_code":"IN",
    "gn:dem":345,
    "gn:feature_class":"P",
    "gn:feature_code":"PPL",
    "gn:name":"Gora",
    "gn:population":0,
    "gn:timezone":"Asia/Kolkata",
    "iso:country":"IN",
    "name:bos_x_preferred":[
        "Gora"
    ],
    "name:bul_x_preferred":[
        "\u0413\u043e\u0440\u0430"
    ],
    "name:ceb_x_preferred":[
        "Gora"
    ],
    "name:deu_x_preferred":[
        "Gora"
    ],
    "name:fin_x_preferred":[
        "Gora"
    ],
    "name:fra_x_preferred":[
        "Gora"
    ],
    "name:heb_x_preferred":[
        "\u05d2\u05d5\u05e8\u05d4"
    ],
    "name:hrv_x_preferred":[
        "Gora"
    ],
    "name:hun_x_preferred":[
        "Gora"
    ],
    "name:ind_x_preferred":[
        "Gora"
    ],
    "name:ita_x_preferred":[
        "Gora"
    ],
    "name:nld_x_preferred":[
        "Gora"
    ],
    "name:rue_x_preferred":[
        "\u0413\u043e\u0440\u0430"
    ],
    "name:rus_x_preferred":[
        "\u0413\u043e\u0440\u0430"
    ],
    "name:slv_x_preferred":[
        "Gora"
    ],
    "name:sna_x_preferred":[
        "Gora"
    ],
    "name:srp_x_preferred":[
        "\u0413\u043e\u0440\u0430"
    ],
    "name:swe_x_preferred":[
        "Gora"
    ],
    "name:tur_x_preferred":[
        "Gora"
    ],
    "name:ukr_x_preferred":[
        "\u0413\u043e\u0440\u0430"
    ],
    "wof:name":"Gora",
    "wof:placetype":"locality"
},
  "geometry": {"coordinates":[81.08355,24.33241],"type":"Point"}
}