{
  "type": "Feature",
  "properties": {
    "iso:country":"IN",
    "ks:ks_name":"Yerrinagipalle",
    "ks:ks_pop":745,
    "ks:ks_type":"HABITATION",
    "ks:ks_uagg_main":0,
    "name:eng_x_preferred":[
        "Yerrinagipalle"
    ],
    "wof:name":"Yerrinagipalle",
    "wof:placetype":"neighbourhood",
    "wof:population":745
},
  "geometry": {"coordinates":[78.492895,12.983257],"type":"Point"}
}