{
  "type": "Feature",
  "properties": {
    "gn:admin1_code":"23.0",
    "gn:admin2_code":"36.0",
    "gn:asciiname":"Bhaini Harse Khan",
    "gn:country_code":"IN",
    "gn:dem":214,
    "gn:feature_class":"P",
    "gn:feature_code":"PPL",
    "gn:name":"Bhaini Harse Kh\u0101n",
    "gn:population":0,
    "gn:timezone":"Asia/Kolkata",
    "iso:country":"IN",
    "wof:name":"Bhaini Harse Khan",
    "wof:placetype":"locality"
},
  "geometry": {"coordinates":[75.13868000000002,31.30245],"type":"Point"}
}