{
  "type": "Feature",
  "properties": {
    "iso:country":"IN",
    "ks:ks_name":"Hirnabara",
    "ks:ks_pop":230,
    "ks:ks_type":"VILLAGE",
    "name:eng_x_preferred":[
        "Hirnabara"
    ],
    "wof:name":"Hirnabara",
    "wof:placetype":"locality",
    "wof:population":230
},
  "geometry": {"coordinates":[86.95534600000001,24.4039],"type":"Point"}
}