{
  "type": "Feature",
  "properties": {
    "gn:admin1_code":"38.0",
    "gn:admin2_code":"368",
    "gn:asciiname":"Jalasar",
    "gn:country_code":"IN",
    "gn:dem":307,
    "gn:feature_class":"P",
    "gn:feature_code":"PPL",
    "gn:name":"Jal\u0101s\u0101r",
    "gn:population":0,
    "gn:timezone":"Asia/Kolkata",
    "iso:country":"IN",
    "ks:ks_alt_nam":"Jal\u0101s\u0101r",
    "ks:ks_name":"Jalasar",
    "ks:ks_pop":740,
    "ks:ks_type":"VILLAGE",
    "name:eng_x_preferred":[
        "Jalasar"
    ],
    "name:eng_x_variant":[
        "Jal\u0101s\u0101r"
    ],
    "wof:name":"Jalasar",
    "wof:placetype":"locality",
    "wof:population":740
},
  "geometry": {"coordinates":[85.16798300000001,22.789054],"type":"Point"}
}