{
  "type": "Feature",
  "properties": {
    "iso:country":"IN",
    "ks:ks_name":"Navagadh",
    "ks:ks_type":"VILLAGE",
    "ks:ks_uagg_main":0,
    "name:eng_x_preferred":[
        "Navagadh"
    ],
    "wof:name":"Navagadh",
    "wof:placetype":"neighbourhood"
},
  "geometry": {"coordinates":[70.62276,21.767791],"type":"Point"}
}