{
  "type": "Feature",
  "properties": {
    "gn:admin1_code":"36",
    "gn:admin2_code":"147.0",
    "gn:asciiname":"Gadalpura",
    "gn:country_code":"IN",
    "gn:dem":164,
    "gn:feature_class":"P",
    "gn:feature_code":"PPL",
    "gn:name":"Gadalpura",
    "gn:population":0,
    "gn:timezone":"Asia/Kolkata",
    "iso:country":"IN",
    "ks:ks_alt_nam":"GADALPURA",
    "ks:ks_name":"Gadalpura",
    "ks:ks_pop":727,
    "ks:ks_type":"HABITATION",
    "ks:ks_uagg_main":0,
    "name:eng_x_preferred":[
        "Gadalpura"
    ],
    "wof:name":"Gadalpura",
    "wof:placetype":"neighbourhood",
    "wof:population":727
},
  "geometry": {"coordinates":[78.220741,27.134706],"type":"Point"}
}