{
  "type": "Feature",
  "properties": {
    "gn:admin1_code":"39.0",
    "gn:admin2_code":"66.0",
    "gn:asciiname":"Bhalaun",
    "gn:country_code":"IN",
    "gn:dem":851,
    "gn:feature_class":"P",
    "gn:feature_code":"PPL",
    "gn:name":"Bhalaun",
    "gn:population":0,
    "gn:timezone":"Asia/Kolkata",
    "iso:country":"IN",
    "wof:name":"Bhalaun",
    "wof:placetype":"locality"
},
  "geometry": {"coordinates":[79.25116,29.46666],"type":"Point"}
}