{
  "type": "Feature",
  "properties": {
    "gn:admin1_code":"35.0",
    "gn:admin2_code":"452.0",
    "gn:asciiname":"Kaneri",
    "gn:country_code":"IN",
    "gn:dem":345,
    "gn:feature_class":"P",
    "gn:feature_code":"PPL",
    "gn:name":"Kaneri",
    "gn:population":0,
    "gn:timezone":"Asia/Kolkata",
    "iso:country":"IN",
    "name:guj_x_preferred":[
        "\u0a95\u0abe\u0aa8\u0ac7\u0ab0\u0ac0"
    ],
    "wof:name":"Kaneri",
    "wof:placetype":"locality"
},
  "geometry": {"coordinates":[78.91741,23.15543],"type":"Point"}
}