{
  "type": "Feature",
  "properties": {
    "iso:country":"IN",
    "ks:ks_name":"Kuldanga",
    "ks:ks_pop":6991,
    "ks:ks_type":"URBAN",
    "ks:ks_uagg_main":0,
    "name:eng_x_preferred":[
        "Kuldanga"
    ],
    "wof:name":"Kuldanga",
    "wof:placetype":"locality",
    "wof:population":6991
},
  "geometry": {"coordinates":[88.137693,22.604248],"type":"Point"}
}