{
  "type": "Feature",
  "properties": {
    "iso:country":"IN",
    "ks:ks_name":"Routara Bari",
    "ks:ks_pop":1284,
    "ks:ks_type":"VILLAGE",
    "name:eng_x_preferred":[
        "Routara Bari"
    ],
    "wof:name":"Routara Bari",
    "wof:placetype":"locality",
    "wof:population":1284
},
  "geometry": {"coordinates":[87.54723799999999,22.087535],"type":"Point"}
}