{
  "type": "Feature",
  "properties": {
    "iso:country":"IN",
    "ks:ks_name":"Ratansenpur Gaunti",
    "ks:ks_pop":729,
    "ks:ks_type":"VILLAGE",
    "ks:ks_uagg_main":0,
    "name:eng_x_preferred":[
        "Ratansenpur Gaunti"
    ],
    "wof:name":"Ratansenpur Gaunti",
    "wof:placetype":"neighbourhood",
    "wof:population":729
},
  "geometry": {"coordinates":[81.270081,25.821901],"type":"Point"}
}