{
  "type": "Feature",
  "properties": {
    "iso:country":"IN",
    "ks:ks_name":"Hadpatiwas",
    "ks:ks_pop":314,
    "ks:ks_type":"HABITATION",
    "name:eng_x_preferred":[
        "Hadpatiwas"
    ],
    "wof:name":"Hadpatiwas",
    "wof:placetype":"locality",
    "wof:population":314
},
  "geometry": {"coordinates":[73.046306,20.54425],"type":"Point"}
}