{
  "type": "Feature",
  "properties": {
    "iso:country":"IN",
    "ks:ks_name":"Annaparra",
    "ks:ks_pop":102,
    "ks:ks_type":"HABITATION",
    "name:eng_x_preferred":[
        "Annaparra"
    ],
    "wof:name":"Annaparra",
    "wof:placetype":"locality",
    "wof:population":102
},
  "geometry": {"coordinates":[76.878454,9.338602],"type":"Point"}
}