{
  "type": "Feature",
  "properties": {
    "gn:admin1_code":"19.0",
    "gn:admin2_code":"581.0",
    "gn:asciiname":"Ramanatapura",
    "gn:country_code":"IN",
    "gn:dem":814,
    "gn:feature_class":"P",
    "gn:feature_code":"PPL",
    "gn:name":"R\u0101man\u0101tap\u016bra",
    "gn:population":0,
    "gn:timezone":"Asia/Kolkata",
    "iso:country":"IN",
    "wof:name":"Ramanatapura",
    "wof:placetype":"neighbourhood"
},
  "geometry": {"coordinates":[78.30804000000001,13.10854],"type":"Point"}
}