{
  "type": "Feature",
  "properties": {
    "gn:admin1_code":"25.0",
    "gn:admin2_code":"606.0",
    "gn:asciiname":"Tellarampattu",
    "gn:country_code":"IN",
    "gn:dem":132,
    "gn:feature_class":"P",
    "gn:feature_code":"PPL",
    "gn:name":"Tell\u0101rampattu",
    "gn:population":0,
    "gn:timezone":"Asia/Kolkata",
    "iso:country":"IN",
    "ks:ks_name":"Thellarampattu",
    "ks:ks_pop":203,
    "ks:ks_type":"VILLAGE",
    "ks:ks_uagg_main":0,
    "name:eng_x_preferred":[
        "Thellarampattu"
    ],
    "wof:name":"Thellarampattu",
    "wof:placetype":"neighbourhood",
    "wof:population":203
},
  "geometry": {"coordinates":[79.377664,12.539894],"type":"Point"}
}