{
  "type": "Feature",
  "properties": {
    "iso:country":"IN",
    "ks:ks_name":"Bas Agaria",
    "ks:ks_pop":678,
    "ks:ks_type":"HABITATION",
    "name:eng_x_preferred":[
        "Bas Agaria"
    ],
    "wof:name":"Bas Agaria",
    "wof:placetype":"neighbourhood",
    "wof:population":678
},
  "geometry": {"coordinates":[78.07015800000001,27.265181],"type":"Point"}
}