{
  "type": "Feature",
  "properties": {
    "iso:country":"IN",
    "ks:ks_name":"Motinara",
    "ks:ks_pop":163,
    "ks:ks_type":"HABITATION",
    "name:eng_x_preferred":[
        "Motinara"
    ],
    "wof:name":"Motinara",
    "wof:placetype":"locality",
    "wof:population":163
},
  "geometry": {"coordinates":[71.414264,26.179733],"type":"Point"}
}