{
  "type": "Feature",
  "properties": {
    "iso:country":"IN",
    "ks:ks_name":"Chakbila",
    "ks:ks_pop":415,
    "ks:ks_type":"VILLAGE",
    "name:eng_x_preferred":[
        "Chakbila"
    ],
    "wof:name":"Chakbila",
    "wof:placetype":"locality",
    "wof:population":415
},
  "geometry": {"coordinates":[87.167303,22.110045],"type":"Point"}
}