{
  "type": "Feature",
  "properties": {
    "iso:country":"IN",
    "ks:ks_name":"Mukudupali",
    "ks:ks_pop":266,
    "ks:ks_type":"VILLAGE",
    "name:eng_x_preferred":[
        "Mukudupali"
    ],
    "wof:name":"Mukudupali",
    "wof:placetype":"locality",
    "wof:population":266
},
  "geometry": {"coordinates":[82.32174000000001,18.282972],"type":"Point"}
}