{
  "type": "Feature",
  "properties": {
    "gn:admin1_code":"10.0",
    "gn:admin2_code":"88.0",
    "gn:asciiname":"Imamuddinpur",
    "gn:country_code":"IN",
    "gn:dem":201,
    "gn:feature_class":"P",
    "gn:feature_code":"PPL",
    "gn:name":"Im\u0101m\u016bdd\u012bnpur",
    "gn:population":0,
    "gn:timezone":"Asia/Kolkata",
    "iso:country":"IN",
    "ks:ks_name":"Imamuddinpur",
    "ks:ks_pop":935,
    "ks:ks_type":"VILLAGE",
    "ks:ks_uagg_main":0,
    "name:eng_x_preferred":[
        "Imamuddinpur"
    ],
    "wof:name":"Imamuddinpur",
    "wof:placetype":"neighbourhood",
    "wof:population":935
},
  "geometry": {"coordinates":[77.463514,28.322961],"type":"Point"}
}