{
  "type": "Feature",
  "properties": {
    "iso:country":"IN",
    "ks:ks_name":"Usribera",
    "ks:ks_pop":561,
    "ks:ks_type":"HABITATION",
    "name:eng_x_preferred":[
        "Usribera"
    ],
    "wof:name":"Usribera",
    "wof:placetype":"locality",
    "wof:population":561
},
  "geometry": {"coordinates":[81.716246,19.715271],"type":"Point"}
}