{
  "type": "Feature",
  "properties": {
    "iso:country":"IN",
    "ks:ks_name":"Palasa",
    "ks:ks_pop":1034,
    "ks:ks_type":"VILLAGE",
    "name:eng_x_preferred":[
        "Palasa"
    ],
    "wof:name":"Palasa",
    "wof:placetype":"locality",
    "wof:population":1034
},
  "geometry": {"coordinates":[86.371588,21.103456],"type":"Point"}
}