{
  "type": "Feature",
  "properties": {
    "iso:country":"IN",
    "ks:ks_name":"Palasa",
    "ks:ks_pop":1034,
    "ks:ks_type":"VILLAGE",
    "name:eng_x_preferred":[
        "Palasa"
    ],
    "name:hin_x_preferred":[
        "\u092a\u0932\u093e\u0938\u093e"
    ],
    "name:tel_x_preferred":[
        "\u0c2a\u0c32\u0c3e\u0c38"
    ],
    "name:urd_x_preferred":[
        "\u067e\u0627\u0644\u0627\u0633\u0627"
    ],
    "wof:name":"Palasa",
    "wof:placetype":"locality",
    "wof:population":1034
},
  "geometry": {"coordinates":[86.371588,21.103456],"type":"Point"}
}