{
  "type": "Feature",
  "properties": {
    "gn:country":"IN",
    "gn:fcode":"PPL",
    "gn:pop":9098,
    "iso:country":"IN",
    "name:eng_x_preferred":[
        "Pali"
    ],
    "name:hin_x_preferred":[
        "\u092a\u093e\u0932\u0940"
    ],
    "name:ita_x_preferred":[
        "Pali"
    ],
    "name:msa_x_preferred":[
        "Pali"
    ],
    "name:nld_x_preferred":[
        "Pali"
    ],
    "name:pol_x_preferred":[
        "Pali"
    ],
    "name:unk_x_variant":[
        "P\u0101li"
    ],
    "name:urd_x_preferred":[
        "\u067e\u0627\u0644\u06cc\u060c \u0644\u0644\u062a \u067e\u0648\u0631"
    ],
    "name:urd_x_variant":[
        "\u067e\u0627\u0644\u06cc"
    ],
    "qs:name":"Pali",
    "qs:name_adm0":"India",
    "qs:name_adm1":"Uttar Pradesh",
    "qs:photos_9r":0,
    "qs:photos_sr":0,
    "qs:placetype":"Town",
    "qs:pop_sr":"5",
    "wd:wordcount":6873,
    "wof:name":"Pali",
    "wof:placetype":"locality",
    "wof:population":9098
},
  "geometry": {"coordinates":[78.41654,24.49277],"type":"Point"}
}