{
  "type": "Feature",
  "properties": {
    "iso:country":"IN",
    "ks:ks_name":"Khiron",
    "ks:ks_pop":132,
    "ks:ks_type":"VILLAGE",
    "name:eng_x_preferred":[
        "Khiron"
    ],
    "wof:name":"Khiron",
    "wof:placetype":"locality",
    "wof:population":132
},
  "geometry": {"coordinates":[79.48264399999999,30.686187],"type":"Point"}
}