{
  "type": "Feature",
  "properties": {
    "iso:country":"IN",
    "ks:ks_name":"Valiyamaruthu",
    "ks:ks_pop":1514,
    "ks:ks_type":"HABITATION",
    "name:eng_x_preferred":[
        "Valiyamaruthu"
    ],
    "wof:name":"Valiyamaruthu",
    "wof:placetype":"locality",
    "wof:population":1514
},
  "geometry": {"coordinates":[76.581166,9.738136],"type":"Point"}
}