{
  "type": "Feature",
  "properties": {
    "gn:admin1_code":"38.0",
    "gn:admin2_code":"360.0",
    "gn:asciiname":"Gobarbandha",
    "gn:country_code":"IN",
    "gn:dem":597,
    "gn:feature_class":"P",
    "gn:feature_code":"PPL",
    "gn:name":"Gobarbandh\u0101",
    "gn:population":0,
    "gn:timezone":"Asia/Kolkata",
    "iso:country":"IN",
    "ks:ks_alt_nam":"Gobarbandh\u0101",
    "ks:ks_name":"Gobarbandha",
    "ks:ks_pop":1189,
    "ks:ks_type":"VILLAGE",
    "ks:ks_uagg_main":0,
    "name:eng_x_preferred":[
        "Gobarbandha"
    ],
    "name:eng_x_variant":[
        "Gobarbandh\u0101"
    ],
    "wof:name":"Gobarbandha",
    "wof:placetype":"neighbourhood",
    "wof:population":1189
},
  "geometry": {"coordinates":[85.397122,24.084427],"type":"Point"}
}