{
  "type": "Feature",
  "properties": {
    "iso:country":"IN",
    "ks:ks_name":"Sivpur Diyar Numbari",
    "ks:ks_pop":10012,
    "ks:ks_type":"HABITATION",
    "ks:ks_uagg_main":0,
    "name:eng_x_preferred":[
        "Sivpur Diyar Numbari"
    ],
    "wof:name":"Sivpur Diyar Numbari",
    "wof:placetype":"neighbourhood",
    "wof:population":10012
},
  "geometry": {"coordinates":[84.21187,25.759169],"type":"Point"}
}