{
  "type": "Feature",
  "properties": {
    "gn:admin1_code":"09",
    "gn:admin2_code":"485.0",
    "gn:asciiname":"Malwasi",
    "gn:country_code":"IN",
    "gn:dem":289,
    "gn:feature_class":"P",
    "gn:feature_code":"PPL",
    "gn:name":"Malw\u0101si",
    "gn:population":0,
    "gn:timezone":"Asia/Kolkata",
    "iso:country":"IN",
    "wof:name":"Malwasi",
    "wof:placetype":"locality"
},
  "geometry": {"coordinates":[74.23031999999998,23.01365],"type":"Point"}
}