{
  "type": "Feature",
  "properties": {
    "iso:country":"IN",
    "ks:ks_name":"Barajuli Pathar",
    "ks:ks_pop":286,
    "ks:ks_type":"VILLAGE",
    "ks:ks_uagg_main":0,
    "name:eng_x_preferred":[
        "Barajuli Pathar"
    ],
    "wof:name":"Barajuli Pathar",
    "wof:placetype":"neighbourhood",
    "wof:population":286
},
  "geometry": {"coordinates":[93.417101,26.859616],"type":"Point"}
}