{
  "type": "Feature",
  "properties": {
    "gn:admin1_code":"36.0",
    "gn:admin2_code":"170.0",
    "gn:asciiname":"Bajrangpur",
    "gn:country_code":"IN",
    "gn:dem":168,
    "gn:feature_class":"P",
    "gn:feature_code":"PPL",
    "gn:name":"Bajrangpur",
    "gn:population":0,
    "gn:timezone":"Asia/Kolkata",
    "iso:country":"IN",
    "ks:ks_name":"Bajarangpur",
    "ks:ks_pop":332,
    "ks:ks_type":"HABITATION",
    "ks:ks_uagg_main":0,
    "name:eng_x_preferred":[
        "Bajarangpur"
    ],
    "wof:name":"Bajarangpur",
    "wof:placetype":"neighbourhood",
    "wof:population":332
},
  "geometry": {"coordinates":[80.671992,25.098804],"type":"Point"}
}