{
  "type": "Feature",
  "properties": {
    "iso:country":"IN",
    "ks:ks_alt_nam":"MAGARAJHI",
    "ks:ks_name":"Magarajhi",
    "ks:ks_pop":451,
    "ks:ks_type":"HABITATION",
    "name:eng_x_preferred":[
        "Magarajhi"
    ],
    "wof:name":"Magarajhi",
    "wof:placetype":"locality",
    "wof:population":451
},
  "geometry": {"coordinates":[84.567532,24.64973],"type":"Point"}
}