{
  "type": "Feature",
  "properties": {
    "gn:admin1_code":"34.0",
    "gn:admin2_code":"221.0",
    "gn:asciiname":"Jarahi",
    "gn:country_code":"IN",
    "gn:dem":48,
    "gn:feature_class":"P",
    "gn:feature_code":"PPL",
    "gn:name":"Jar\u0101hi",
    "gn:population":0,
    "gn:timezone":"Asia/Kolkata",
    "iso:country":"IN",
    "ks:ks_alt_nam":"Jar\u0101hi",
    "ks:ks_name":"Jarahi",
    "ks:ks_type":"VILLAGE",
    "ks:ks_uagg_main":0,
    "name:eng_x_preferred":[
        "Jarahi"
    ],
    "name:eng_x_variant":[
        "Jar\u0101hi"
    ],
    "name:kur_x_preferred":[
        "Kurdistan"
    ],
    "wof:name":"Jarahi",
    "wof:placetype":"neighbourhood"
},
  "geometry": {"coordinates":[86.0348,25.773331],"type":"Point"}
}