{
  "type": "Feature",
  "properties": {
    "iso:country":"IN",
    "ks:ks_name":"Kakaral Palli",
    "ks:ks_pop":160,
    "ks:ks_type":"HABITATION",
    "name:eng_x_preferred":[
        "Kakaral Palli"
    ],
    "wof:name":"Kakaral Palli",
    "wof:placetype":"locality",
    "wof:population":160
},
  "geometry": {"coordinates":[78.398225,12.844102],"type":"Point"}
}