{
  "type": "Feature",
  "properties": {
    "iso:country":"IN",
    "ks:ks_name":"Birmamath Urf Harnathpur Harna",
    "ks:ks_pop":1042,
    "ks:ks_type":"VILLAGE",
    "name:eng_x_preferred":[
        "Birmamath Urf Harnathpur Harna"
    ],
    "wof:name":"Birmamath Urf Harnathpur Harna",
    "wof:placetype":"locality",
    "wof:population":1042
},
  "geometry": {"coordinates":[85.28692700000001,25.976297],"type":"Point"}
}