{
  "type": "Feature",
  "properties": {
    "iso:country":"IN",
    "ks:ks_name":"M.Domalapalle",
    "ks:ks_pop":1425,
    "ks:ks_type":"VILLAGE",
    "name:eng_x_preferred":[
        "M.Domalapalle"
    ],
    "wof:name":"M.Domalapalle",
    "wof:placetype":"locality",
    "wof:population":1425
},
  "geometry": {"coordinates":[79.125353,17.062055],"type":"Point"}
}