{
  "type": "Feature",
  "properties": {
    "gn:admin1_code":"21.0",
    "gn:admin2_code":"377.0",
    "gn:asciiname":"Oupada",
    "gn:country_code":"IN",
    "gn:dem":14,
    "gn:feature_class":"P",
    "gn:feature_code":"PPL",
    "gn:name":"Oupada",
    "gn:population":0,
    "gn:timezone":"Asia/Kolkata",
    "iso:country":"IN",
    "wof:name":"Oupada",
    "wof:placetype":"locality"
},
  "geometry": {"coordinates":[86.94838,21.49141],"type":"Point"}
}