{
  "type": "Feature",
  "properties": {
    "iso:country":"IN",
    "ks:ks_alt_nam":"Hariharm\u0101ti",
    "ks:ks_name":"Hariharmati",
    "ks:ks_type":"VILLAGE",
    "name:eng_x_preferred":[
        "Hariharmati"
    ],
    "name:eng_x_variant":[
        "Hariharm\u0101ti"
    ],
    "wof:name":"Hariharmati",
    "wof:placetype":"locality"
},
  "geometry": {"coordinates":[86.828523,24.123954],"type":"Point"}
}