{
  "type": "Feature",
  "properties": {
    "iso:country":"IN",
    "ks:ks_alt_nam":"27 NP-A",
    "ks:ks_name":"27 Np-a",
    "ks:ks_pop":24,
    "ks:ks_type":"HABITATION",
    "name:eng_x_preferred":[
        "27 Np-a"
    ],
    "wof:name":"27 Np-a",
    "wof:placetype":"locality",
    "wof:population":24
},
  "geometry": {"coordinates":[73.241378,29.394374],"type":"Point"}
}