{
  "type": "Feature",
  "properties": {
    "iso:country":"IN",
    "ks:ks_name":"Ichhanagari",
    "ks:ks_pop":3732,
    "ks:ks_type":"VILLAGE",
    "ks:ks_uagg_main":0,
    "name:eng_x_preferred":[
        "Ichhanagari"
    ],
    "wof:name":"Ichhanagari",
    "wof:placetype":"neighbourhood",
    "wof:population":3732
},
  "geometry": {"coordinates":[88.100652,22.687157],"type":"Point"}
}