{
  "type": "Feature",
  "properties": {
    "iso:country":"IN",
    "ks:ks_alt_nam":"BHARAT SARDAR PARA",
    "ks:ks_name":"Bharat Sardar Para",
    "ks:ks_pop":159,
    "ks:ks_type":"HABITATION",
    "name:eng_x_preferred":[
        "Bharat Sardar Para"
    ],
    "wof:name":"Bharat Sardar Para",
    "wof:placetype":"locality",
    "wof:population":159
},
  "geometry": {"coordinates":[91.335655,23.783026],"type":"Point"}
}