{
  "type": "Feature",
  "properties": {
    "iso:country":"IN",
    "ks:ks_name":"Rangamati",
    "ks:ks_pop":402,
    "ks:ks_type":"HABITATION",
    "name:eng_x_preferred":[
        "Rangamati"
    ],
    "wof:name":"Rangamati",
    "wof:placetype":"locality",
    "wof:population":402
},
  "geometry": {"coordinates":[85.732077,23.293437],"type":"Point"}
}