{
  "type": "Feature",
  "properties": {
    "gn:admin1_code":"34.0",
    "gn:admin2_code":"217.0",
    "gn:asciiname":"Bhatwa",
    "gn:country_code":"IN",
    "gn:dem":80,
    "gn:feature_class":"P",
    "gn:feature_code":"PPL",
    "gn:name":"Bhatw\u0101",
    "gn:population":0,
    "gn:timezone":"Asia/Kolkata",
    "iso:country":"IN",
    "ks:ks_alt_nam":"Bhatw\u0101",
    "ks:ks_name":"Bhatwa",
    "ks:ks_type":"VILLAGE",
    "name:eng_x_preferred":[
        "Bhatwa"
    ],
    "name:eng_x_variant":[
        "Bhatw\u0101"
    ],
    "wof:name":"Bhatwa",
    "wof:placetype":"locality"
},
  "geometry": {"coordinates":[84.160504,26.566201],"type":"Point"}
}