{
  "type": "Feature",
  "properties": {
    "iso:country":"IN",
    "ks:ks_name":"Mathiabhanga",
    "ks:ks_pop":398,
    "ks:ks_type":"VILLAGE",
    "name:eng_x_preferred":[
        "Mathiabhanga"
    ],
    "wof:name":"Mathiabhanga",
    "wof:placetype":"locality",
    "wof:population":398
},
  "geometry": {"coordinates":[86.57558,21.688278],"type":"Point"}
}