{
  "type": "Feature",
  "properties": {
    "iso:country":"IN",
    "ks:ks_name":"Bakkadi",
    "ks:ks_pop":105,
    "ks:ks_type":"HABITATION",
    "name:eng_x_preferred":[
        "Bakkadi"
    ],
    "wof:name":"Bakkadi",
    "wof:placetype":"locality",
    "wof:population":105
},
  "geometry": {"coordinates":[75.666878,13.022289],"type":"Point"}
}