{
  "type": "Feature",
  "properties": {
    "gn:admin1_code":"33.0",
    "gn:admin2_code":"586.0",
    "gn:asciiname":"Sadolasem",
    "gn:country_code":"IN",
    "gn:dem":18,
    "gn:feature_class":"P",
    "gn:feature_code":"PPL",
    "gn:name":"S\u0101dolasem",
    "gn:population":0,
    "gn:timezone":"Asia/Kolkata",
    "iso:country":"IN",
    "wof:name":"Sadolasem",
    "wof:placetype":"locality"
},
  "geometry": {"coordinates":[74.06535,14.99281],"type":"Point"}
}