{
  "type": "Feature",
  "properties": {
    "gn:admin1_code":"25.0",
    "gn:admin2_code":"619.0",
    "gn:asciiname":"Karuvakkurichchi",
    "gn:country_code":"IN",
    "gn:dem":30,
    "gn:feature_class":"P",
    "gn:feature_code":"PPL",
    "gn:name":"Karuv\u0101kkurichchi",
    "gn:population":0,
    "gn:timezone":"Asia/Kolkata",
    "iso:country":"IN",
    "wof:name":"Karuvakkurichchi",
    "wof:placetype":"neighbourhood"
},
  "geometry": {"coordinates":[79.36528,10.61371],"type":"Point"}
}