{
  "type": "Feature",
  "properties": {
    "iso:country":"IN",
    "ks:ks_name":"Badaolama",
    "ks:ks_pop":1861,
    "ks:ks_type":"HABITATION",
    "name:eng_x_preferred":[
        "Badaolama"
    ],
    "wof:name":"Badaolama",
    "wof:placetype":"locality",
    "wof:population":1861
},
  "geometry": {"coordinates":[82.367445,19.398314],"type":"Point"}
}