{
  "type": "Feature",
  "properties": {
    "iso:country":"IN",
    "ks:ks_name":"Teli Tola",
    "ks:ks_pop":78,
    "ks:ks_type":"HABITATION",
    "name:eng_x_preferred":[
        "Teli Tola"
    ],
    "wof:name":"Teli Tola",
    "wof:placetype":"locality",
    "wof:population":78
},
  "geometry": {"coordinates":[83.550225,24.316089],"type":"Point"}
}