{
  "type": "Feature",
  "properties": {
    "iso:country":"IN",
    "ks:ks_name":"Chotegangulawa",
    "ks:ks_pop":147,
    "ks:ks_type":"HABITATION",
    "name:eng_x_preferred":[
        "Chotegangulawa"
    ],
    "wof:name":"Chotegangulawa",
    "wof:placetype":"locality",
    "wof:population":147
},
  "geometry": {"coordinates":[81.28744,18.335828],"type":"Point"}
}