{
  "type": "Feature",
  "properties": {
    "gn:admin1_code":"39.0",
    "gn:admin2_code":"63.0",
    "gn:asciiname":"Lingurta",
    "gn:country_code":"IN",
    "gn:dem":961,
    "gn:feature_class":"P",
    "gn:feature_code":"PPL",
    "gn:name":"Lingurta",
    "gn:population":0,
    "gn:timezone":"Asia/Kolkata",
    "iso:country":"IN",
    "wof:name":"Lingurta",
    "wof:placetype":"locality"
},
  "geometry": {"coordinates":[79.84109000000002,29.70249],"type":"Point"}
}