{
  "type": "Feature",
  "properties": {
    "iso:country":"IN",
    "ks:ks_name":"Kodija",
    "ks:ks_pop":981,
    "ks:ks_type":"VILLAGE",
    "ks:ks_uagg_main":0,
    "name:eng_x_preferred":[
        "Kodija"
    ],
    "wof:name":"Kodija",
    "wof:placetype":"neighbourhood",
    "wof:population":981
},
  "geometry": {"coordinates":[75.87943300000001,25.401558],"type":"Point"}
}