{
  "type": "Feature",
  "properties": {
    "gn:admin1_code":"19.0",
    "gn:admin2_code":"575.0",
    "gn:asciiname":"Kamarkaje",
    "gn:country_code":"IN",
    "gn:dem":135,
    "gn:feature_class":"P",
    "gn:feature_code":"PPL",
    "gn:name":"Kamark\u0101je",
    "gn:population":0,
    "gn:timezone":"Asia/Kolkata",
    "iso:country":"IN",
    "ks:ks_name":"Kamarkaje",
    "ks:ks_pop":104,
    "ks:ks_type":"HABITATION",
    "name:eng_x_preferred":[
        "Kamarkaje"
    ],
    "wof:name":"Kamarkaje",
    "wof:placetype":"locality",
    "wof:population":104
},
  "geometry": {"coordinates":[75.54664200000001,12.772056],"type":"Point"}
}