{
  "type": "Feature",
  "properties": {
    "gn:admin1_code":"39.0",
    "gn:admin2_code":"60.0",
    "gn:asciiname":"Balawala",
    "gn:country_code":"IN",
    "gn:dem":601,
    "gn:feature_class":"P",
    "gn:feature_code":"PPL",
    "gn:name":"B\u0101l\u0101w\u0101la",
    "gn:population":0,
    "gn:timezone":"Asia/Kolkata",
    "iso:country":"IN",
    "ks:ks_alt_nam":"B\u0101l\u0101w\u0101la",
    "ks:ks_name":"Balawala",
    "ks:ks_pop":7381,
    "ks:ks_type":"VILLAGE",
    "ks:ks_uagg_main":0,
    "name:eng_x_preferred":[
        "Balawala"
    ],
    "name:eng_x_variant":[
        "B\u0101l\u0101w\u0101la"
    ],
    "wof:name":"Balawala",
    "wof:placetype":"locality",
    "wof:population":7381
},
  "geometry": {"coordinates":[78.11417400000001,30.257642],"type":"Point"}
}