{
  "type": "Feature",
  "properties": {
    "gn:admin1_code":"36",
    "gn:admin2_code":"194.0",
    "gn:asciiname":"Satwa",
    "gn:country_code":"IN",
    "gn:dem":94,
    "gn:feature_class":"P",
    "gn:feature_code":"PPL",
    "gn:name":"Satwa",
    "gn:population":0,
    "gn:timezone":"Asia/Kolkata",
    "iso:country":"IN",
    "name:und_x_variant":[
        "Goraiya D\u012bh"
    ],
    "wof:name":"Satwa",
    "wof:placetype":"neighbourhood"
},
  "geometry": {"coordinates":[82.19726,25.66968],"type":"Point"}
}