{
  "type": "Feature",
  "properties": {
    "gn:admin1_code":"19.0",
    "gn:admin2_code":"573.0",
    "gn:asciiname":"Chuchchalakyaranahalli",
    "gn:country_code":"IN",
    "gn:dem":817,
    "gn:feature_class":"P",
    "gn:feature_code":"PPL",
    "gn:name":"Chuchchalaky\u0101ranahalli",
    "gn:population":0,
    "gn:timezone":"Asia/Kolkata",
    "iso:country":"IN",
    "wof:name":"Chuchchalakyaranahalli",
    "wof:placetype":"neighbourhood"
},
  "geometry": {"coordinates":[76.39886,12.74934],"type":"Point"}
}