{
  "type": "Feature",
  "properties": {
    "gn:admin1_code":"21",
    "gn:admin2_code":"396.0",
    "gn:asciiname":"Dhanimaska",
    "gn:country_code":"IN",
    "gn:dem":496,
    "gn:feature_class":"P",
    "gn:feature_code":"PPL",
    "gn:name":"Dhanimaska",
    "gn:population":0,
    "gn:timezone":"Asia/Kolkata",
    "iso:country":"IN",
    "ks:ks_name":"Dharnimaska",
    "ks:ks_pop":38,
    "ks:ks_type":"VILLAGE",
    "name:eng_x_preferred":[
        "Dharnimaska"
    ],
    "name:eng_x_variant":[
        "Dhanimaska"
    ],
    "wof:name":"Dharnimaska",
    "wof:placetype":"locality",
    "wof:population":38
},
  "geometry": {"coordinates":[83.54132199999999,19.850248],"type":"Point"}
}