{
  "type": "Feature",
  "properties": {
    "iso:country":"IN",
    "ks:ks_name":"Amroli",
    "ks:ks_type":"VILLAGE",
    "ks:ks_uagg_main":0,
    "name:eng_x_preferred":[
        "Amroli"
    ],
    "wof:name":"Amroli",
    "wof:placetype":"neighbourhood"
},
  "geometry": {"coordinates":[72.85030399999999,21.236575],"type":"Point"}
}