{
  "type": "Feature",
  "properties": {
    "gn:admin1_code":"19.0",
    "gn:admin2_code":"572",
    "gn:asciiname":"Cox Town",
    "gn:country_code":"IN",
    "gn:dem":910,
    "gn:feature_class":"P",
    "gn:feature_code":"PPL",
    "gn:name":"Cox Town",
    "gn:population":0,
    "gn:timezone":"Asia/Kolkata",
    "iso:country":"IN",
    "wof:name":"Cox Town",
    "wof:placetype":"locality"
},
  "geometry": {"coordinates":[77.62064000000002,12.99636],"type":"Point"}
}