{
  "type": "Feature",
  "properties": {
    "iso:country":"IN",
    "ks:ks_name":"Udpura",
    "ks:ks_pop":4,
    "ks:ks_type":"HABITATION",
    "name:eng_x_preferred":[
        "Udpura"
    ],
    "wof:name":"Udpura",
    "wof:placetype":"locality",
    "wof:population":4
},
  "geometry": {"coordinates":[75.787921,24.913913],"type":"Point"}
}