{
  "type": "Feature",
  "properties": {
    "iso:country":"IN",
    "ks:ks_name":"Sadishta",
    "ks:ks_pop":811,
    "ks:ks_type":"VILLAGE",
    "name:eng_x_preferred":[
        "Sadishta"
    ],
    "wof:name":"Sadishta",
    "wof:placetype":"locality",
    "wof:population":811
},
  "geometry": {"coordinates":[87.180952,23.153688],"type":"Point"}
}