{
  "type": "Feature",
  "properties": {
    "gn:admin1_code":"36",
    "gn:admin2_code":"180.0",
    "gn:asciiname":"Renda",
    "gn:country_code":"IN",
    "gn:dem":122,
    "gn:feature_class":"P",
    "gn:feature_code":"PPL",
    "gn:name":"Renda",
    "gn:population":0,
    "gn:timezone":"Asia/Kolkata",
    "iso:country":"IN",
    "name:ita_x_preferred":[
        "Renda"
    ],
    "name:por_x_preferred":[
        "Renda"
    ],
    "wof:name":"Renda",
    "wof:placetype":"locality"
},
  "geometry": {"coordinates":[81.72296999999998,27.51136],"type":"Point"}
}