{
  "type": "Feature",
  "properties": {
    "gn:admin1_code":"19.0",
    "gn:admin2_code":"573.0",
    "gn:asciiname":"Hallikoppal",
    "gn:country_code":"IN",
    "gn:dem":906,
    "gn:feature_class":"P",
    "gn:feature_code":"PPL",
    "gn:name":"Hallikoppal",
    "gn:population":0,
    "gn:timezone":"Asia/Kolkata",
    "iso:country":"IN",
    "wof:name":"Hallikoppal",
    "wof:placetype":"locality"
},
  "geometry": {"coordinates":[76.67364000000001,12.72816],"type":"Point"}
}