{
  "type": "Feature",
  "properties": {
    "gn:admin1_code":"13.0",
    "gn:admin2_code":"601.0",
    "gn:asciiname":"Chavarodu",
    "gn:country_code":"IN",
    "gn:dem":58,
    "gn:feature_class":"P",
    "gn:feature_code":"PPL",
    "gn:name":"Ch\u0101varodu",
    "gn:population":0,
    "gn:timezone":"Asia/Kolkata",
    "iso:country":"IN",
    "wof:name":"Chavarodu",
    "wof:placetype":"locality"
},
  "geometry": {"coordinates":[76.76878000000001,8.79143],"type":"Point"}
}