{
  "type": "Feature",
  "properties": {
    "iso:country":"IN",
    "ks:ks_name":"Mumru Ronghang 2",
    "ks:ks_pop":652,
    "ks:ks_type":"HABITATION",
    "name:eng_x_preferred":[
        "Mumru Ronghang 2"
    ],
    "wof:name":"Mumru Ronghang 2",
    "wof:placetype":"locality",
    "wof:population":652
},
  "geometry": {"coordinates":[93.15512099999999,26.02765],"type":"Point"}
}