{
  "type": "Feature",
  "properties": {
    "iso:country":"IN",
    "ks:ks_name":"Karremarka",
    "ks:ks_pop":72,
    "ks:ks_type":"HABITATION",
    "name:eng_x_preferred":[
        "Karremarka"
    ],
    "wof:name":"Karremarka",
    "wof:placetype":"locality",
    "wof:population":72
},
  "geometry": {"coordinates":[80.807106,20.02281],"type":"Point"}
}