{
  "type": "Feature",
  "properties": {
    "iso:country":"IN",
    "ks:ks_name":"Deoria Urf Tenghriha Babu",
    "ks:ks_pop":241,
    "ks:ks_type":"VILLAGE",
    "name:eng_x_preferred":[
        "Deoria Urf Tenghriha Babu"
    ],
    "wof:name":"Deoria Urf Tenghriha Babu",
    "wof:placetype":"locality",
    "wof:population":241
},
  "geometry": {"coordinates":[82.80133499999999,26.595143],"type":"Point"}
}