{
  "type": "Feature",
  "properties": {
    "iso:country":"IN",
    "ks:ks_name":"Keshopur",
    "ks:ks_pop":915,
    "ks:ks_type":"VILLAGE",
    "ks:ks_uagg_main":0,
    "name:eng_x_preferred":[
        "Keshopur"
    ],
    "wof:name":"Keshopur",
    "wof:placetype":"neighbourhood",
    "wof:population":915
},
  "geometry": {"coordinates":[86.52922599999999,25.352422],"type":"Point"}
}