{
  "type": "Feature",
  "properties": {
    "iso:country":"IN",
    "ks:ks_name":"Maripalya",
    "ks:ks_pop":168,
    "ks:ks_type":"HABITATION",
    "name:eng_x_preferred":[
        "Maripalya"
    ],
    "wof:name":"Maripalya",
    "wof:placetype":"locality",
    "wof:population":168
},
  "geometry": {"coordinates":[77.134321,13.577384],"type":"Point"}
}