{
  "type": "Feature",
  "properties": {
    "iso:country":"IN",
    "ks:ks_name":"Patkhauli Raja",
    "ks:ks_pop":139,
    "ks:ks_type":"HABITATION",
    "ks:ks_uagg_main":0,
    "name:eng_x_preferred":[
        "Patkhauli Raja"
    ],
    "wof:name":"Patkhauli Raja",
    "wof:placetype":"neighbourhood",
    "wof:population":139
},
  "geometry": {"coordinates":[82.650503,26.792693],"type":"Point"}
}