{
  "type": "Feature",
  "properties": {
    "iso:country":"IN",
    "ks:ks_name":"Khuna",
    "ks:ks_pop":93,
    "ks:ks_type":"HABITATION",
    "name:eng_x_preferred":[
        "Khuna"
    ],
    "wof:name":"Khuna",
    "wof:placetype":"locality",
    "wof:population":93
},
  "geometry": {"coordinates":[79.28671,29.610423],"type":"Point"}
}