{
  "type": "Feature",
  "properties": {
    "gn:admin1_code":"19.0",
    "gn:admin2_code":"570.0",
    "gn:asciiname":"Kumbargod",
    "gn:country_code":"IN",
    "gn:dem":646,
    "gn:feature_class":"P",
    "gn:feature_code":"PPL",
    "gn:name":"Kumbargod",
    "gn:population":0,
    "gn:timezone":"Asia/Kolkata",
    "iso:country":"IN",
    "ks:ks_name":"Kumbargodu",
    "ks:ks_pop":58,
    "ks:ks_type":"HABITATION",
    "name:eng_x_preferred":[
        "Kumbargodu"
    ],
    "name:eng_x_variant":[
        "Kumbargod"
    ],
    "wof:name":"Kumbargodu",
    "wof:placetype":"locality",
    "wof:population":58
},
  "geometry": {"coordinates":[75.20452899999999,13.490455],"type":"Point"}
}