{
  "type": "Feature",
  "properties": {
    "iso:country":"IN",
    "ks:ks_name":"Keezhattingal",
    "ks:ks_pop":124,
    "ks:ks_type":"VILLAGE",
    "name:eng_x_preferred":[
        "Keezhattingal"
    ],
    "wof:name":"Keezhattingal",
    "wof:placetype":"locality",
    "wof:population":124
},
  "geometry": {"coordinates":[76.785651,8.701847],"type":"Point"}
}