{
  "type": "Feature",
  "properties": {
    "iso:country":"IN",
    "ks:ks_name":"Jhilitanr",
    "ks:ks_pop":62,
    "ks:ks_type":"HABITATION",
    "name:eng_x_preferred":[
        "Jhilitanr"
    ],
    "wof:name":"Jhilitanr",
    "wof:placetype":"locality",
    "wof:population":62
},
  "geometry": {"coordinates":[86.054968,24.785693],"type":"Point"}
}