{
  "type": "Feature",
  "properties": {
    "iso:country":"IN",
    "ks:ks_name":"Kolanda",
    "ks:ks_pop":1299,
    "ks:ks_type":"VILLAGE",
    "name:eng_x_preferred":[
        "Kolanda"
    ],
    "wof:name":"Kolanda",
    "wof:placetype":"locality",
    "wof:population":1299
},
  "geometry": {"coordinates":[87.52436,22.094348],"type":"Point"}
}