{
  "type": "Feature",
  "properties": {
    "gn:admin1_code":"36",
    "gn:admin2_code":"191.0",
    "gn:asciiname":"Santi",
    "gn:country_code":"IN",
    "gn:dem":82,
    "gn:feature_class":"P",
    "gn:feature_code":"PPL",
    "gn:name":"S\u0101nti",
    "gn:population":0,
    "gn:timezone":"Asia/Kolkata",
    "iso:country":"IN",
    "ks:ks_alt_nam":"S\u0101nti",
    "ks:ks_name":"Santi",
    "ks:ks_type":"VILLAGE",
    "ks:ks_uagg_main":0,
    "name:bre_x_preferred":[
        "Santi"
    ],
    "name:ceb_x_preferred":[
        "Santi"
    ],
    "name:deu_x_preferred":[
        "Santi"
    ],
    "name:eng_x_preferred":[
        "Santi"
    ],
    "name:eng_x_variant":[
        "S\u0101nti"
    ],
    "name:fra_x_preferred":[
        "Santi"
    ],
    "name:ita_x_preferred":[
        "Santi"
    ],
    "name:jpn_x_preferred":[
        "\u30b5\u30f3\u30c6\u30a3"
    ],
    "name:por_x_preferred":[
        "Santi"
    ],
    "name:srp_x_preferred":[
        "Santi"
    ],
    "name:swe_x_preferred":[
        "Santi"
    ],
    "wof:name":"Santi",
    "wof:placetype":"neighbourhood"
},
  "geometry": {"coordinates":[83.105868,26.151059],"type":"Point"}
}