{
  "type": "Feature",
  "properties": {
    "iso:country":"IN",
    "ks:ks_alt_nam":"MS Cheru Thanda",
    "ks:ks_name":"Ms Cheru Thanda",
    "ks:ks_pop":190,
    "ks:ks_type":"HABITATION",
    "name:eng_x_preferred":[
        "Ms Cheru Thanda"
    ],
    "wof:name":"Ms Cheru Thanda",
    "wof:placetype":"locality",
    "wof:population":190
},
  "geometry": {"coordinates":[78.529223,18.386645],"type":"Point"}
}