{
  "type": "Feature",
  "properties": {
    "iso:country":"IN",
    "ks:ks_name":"Allipur",
    "ks:ks_pop":1456,
    "ks:ks_type":"VILLAGE",
    "ks:ks_uagg_main":0,
    "name:eng_x_preferred":[
        "Allipur"
    ],
    "wof:name":"Allipur",
    "wof:placetype":"locality",
    "wof:population":1456
},
  "geometry": {"coordinates":[79.569344,17.924233],"type":"Point"}
}