{
  "type": "Feature",
  "properties": {
    "iso:country":"IN",
    "ks:ks_name":"Khadagada",
    "ks:ks_pop":2422,
    "ks:ks_type":"VILLAGE",
    "name:eng_x_preferred":[
        "Khadagada"
    ],
    "wof:name":"Khadagada",
    "wof:placetype":"locality",
    "wof:population":2422
},
  "geometry": {"coordinates":[73.81316099999999,21.860852],"type":"Point"}
}