{
  "type": "Feature",
  "properties": {
    "iso:country":"IN",
    "ks:ks_name":"Kalaliyakad",
    "ks:ks_pop":415,
    "ks:ks_type":"VILLAGE",
    "name:eng_x_preferred":[
        "Kalaliyakad"
    ],
    "wof:name":"Kalaliyakad",
    "wof:placetype":"locality",
    "wof:population":415
},
  "geometry": {"coordinates":[73.682283,24.146853],"type":"Point"}
}