{
  "type": "Feature",
  "properties": {
    "iso:country":"IN",
    "ks:ks_name":"Manjali",
    "ks:ks_pop":425,
    "ks:ks_type":"HABITATION",
    "name:eng_x_preferred":[
        "Manjali"
    ],
    "wof:name":"Manjali",
    "wof:placetype":"locality",
    "wof:population":425
},
  "geometry": {"coordinates":[76.325878,10.239725],"type":"Point"}
}