{
  "type": "Feature",
  "properties": {
    "iso:country":"IN",
    "ks:ks_alt_nam":"RABIA CHOW. PARA",
    "ks:ks_name":"Rabia Chow. Para",
    "ks:ks_pop":73,
    "ks:ks_type":"HABITATION",
    "name:eng_x_preferred":[
        "Rabia Chow. Para"
    ],
    "wof:name":"Rabia Chow. Para",
    "wof:placetype":"locality",
    "wof:population":73
},
  "geometry": {"coordinates":[91.481584,23.910523],"type":"Point"}
}