{
  "type": "Feature",
  "properties": {
    "gn:admin1_code":"35",
    "gn:admin2_code":"439.0",
    "gn:asciiname":"Dongargaon",
    "gn:country_code":"IN",
    "gn:dem":598,
    "gn:feature_class":"P",
    "gn:feature_code":"PPL",
    "gn:name":"Dongargaon",
    "gn:population":0,
    "gn:timezone":"Asia/Kolkata",
    "iso:country":"IN",
    "wof:name":"Dongargaon",
    "wof:placetype":"locality"
},
  "geometry": {"coordinates":[75.74158,22.54319],"type":"Point"}
}