{
  "type": "Feature",
  "properties": {
    "iso:country":"IN",
    "ks:ks_name":"Lakhipur Grant",
    "ks:ks_pop":2222,
    "ks:ks_type":"VILLAGE",
    "ks:ks_uagg_main":0,
    "name:eng_x_preferred":[
        "Lakhipur Grant"
    ],
    "wof:name":"Lakhipur Grant",
    "wof:placetype":"neighbourhood",
    "wof:population":2222
},
  "geometry": {"coordinates":[93.003331,24.787709],"type":"Point"}
}