{
  "type": "Feature",
  "properties": {
    "iso:country":"IN",
    "ks:ks_name":"Piproli",
    "ks:ks_pop":997,
    "ks:ks_type":"HABITATION",
    "name:eng_x_preferred":[
        "Piproli"
    ],
    "wof:name":"Piproli",
    "wof:placetype":"locality",
    "wof:population":997
},
  "geometry": {"coordinates":[78.16296,26.134809],"type":"Point"}
}