{
  "type": "Feature",
  "properties": {
    "gn:admin1_code":"16.0",
    "gn:admin2_code":"527.0",
    "gn:asciiname":"Puklewadi",
    "gn:country_code":"IN",
    "gn:dem":766,
    "gn:feature_class":"P",
    "gn:feature_code":"PPL",
    "gn:name":"Puklewadi",
    "gn:population":0,
    "gn:timezone":"Asia/Kolkata",
    "iso:country":"IN",
    "wof:name":"Puklewadi",
    "wof:placetype":"locality"
},
  "geometry": {"coordinates":[74.66338,17.53286],"type":"Point"}
}