{
  "type": "Feature",
  "properties": {
    "iso:country":"IN",
    "ks:ks_name":"Barangaya",
    "ks:ks_pop":17,
    "ks:ks_type":"HABITATION",
    "name:eng_x_preferred":[
        "Barangaya"
    ],
    "wof:name":"Barangaya",
    "wof:placetype":"locality",
    "wof:population":17
},
  "geometry": {"coordinates":[75.546566,12.575699],"type":"Point"}
}