{
  "type": "Feature",
  "properties": {
    "gn:admin1_code":"24",
    "gn:admin2_code":"102.0",
    "gn:asciiname":"Sawar",
    "gn:country_code":"IN",
    "gn:dem":212,
    "gn:feature_class":"P",
    "gn:feature_code":"PPL",
    "gn:name":"S\u0101war",
    "gn:population":0,
    "gn:timezone":"Asia/Kolkata",
    "iso:country":"IN",
    "name:und_x_variant":[
        "S\u0101rwar",
        "S\u0101war"
    ],
    "wof:name":"Sawar",
    "wof:placetype":"locality"
},
  "geometry": {"coordinates":[74.33775,28.76898],"type":"Point"}
}