{
  "type": "Feature",
  "properties": {
    "iso:country":"IN",
    "ks:ks_alt_nam":"Avinasi KV",
    "ks:ks_name":"Avinasi Kv",
    "ks:ks_pop":410,
    "ks:ks_type":"HABITATION",
    "ks:ks_uagg_main":0,
    "name:eng_x_preferred":[
        "Avinasi Kv"
    ],
    "wof:name":"Avinasi Kv",
    "wof:placetype":"neighbourhood",
    "wof:population":410
},
  "geometry": {"coordinates":[77.919839,11.608494],"type":"Point"}
}