{
  "type": "Feature",
  "properties": {
    "iso:country":"IN",
    "ks:ks_name":"Sundardihi",
    "ks:ks_pop":204,
    "ks:ks_type":"VILLAGE",
    "name:eng_x_preferred":[
        "Sundardihi"
    ],
    "wof:name":"Sundardihi",
    "wof:placetype":"locality",
    "wof:population":204
},
  "geometry": {"coordinates":[86.697766,21.877079],"type":"Point"}
}