{
  "type": "Feature",
  "properties": {
    "gn:admin1_code":"10.0",
    "gn:admin2_code":"83.0",
    "gn:asciiname":"Pahladpur",
    "gn:country_code":"IN",
    "gn:dem":219,
    "gn:feature_class":"P",
    "gn:feature_code":"PPL",
    "gn:name":"Pahl\u0101dpur",
    "gn:population":0,
    "gn:timezone":"Asia/Kolkata",
    "iso:country":"IN",
    "wof:name":"Pahladpur",
    "wof:placetype":"locality"
},
  "geometry": {"coordinates":[76.90796,28.81038],"type":"Point"}
}