{
  "type": "Feature",
  "properties": {
    "iso:country":"IN",
    "ks:ks_name":"Kutubpur",
    "ks:ks_pop":568,
    "ks:ks_type":"HABITATION",
    "name:eng_x_preferred":[
        "Kutubpur"
    ],
    "wof:name":"Kutubpur",
    "wof:placetype":"locality",
    "wof:population":568
},
  "geometry": {"coordinates":[82.51629699999999,26.614261],"type":"Point"}
}