{
  "type": "Feature",
  "properties": {
    "iso:country":"IN",
    "ks:ks_name":"Loohar Tola",
    "ks:ks_pop":189,
    "ks:ks_type":"HABITATION",
    "name:eng_x_preferred":[
        "Loohar Tola"
    ],
    "wof:name":"Loohar Tola",
    "wof:placetype":"locality",
    "wof:population":189
},
  "geometry": {"coordinates":[85.152056,25.743639],"type":"Point"}
}