{
  "type": "Feature",
  "properties": {
    "gn:admin1_code":"23",
    "gn:admin2_code":"40.0",
    "gn:asciiname":"Talanian",
    "gn:country_code":"IN",
    "gn:dem":271,
    "gn:feature_class":"P",
    "gn:feature_code":"PPL",
    "gn:name":"Tal\u0101ni\u0101n",
    "gn:population":0,
    "gn:timezone":"Asia/Kolkata",
    "iso:country":"IN",
    "ks:ks_alt_nam":"Tal\u0101ni\u0101n",
    "ks:ks_name":"Talanian",
    "ks:ks_pop":254,
    "ks:ks_type":"VILLAGE",
    "ks:ks_uagg_main":0,
    "name:eng_x_preferred":[
        "Talanian"
    ],
    "name:eng_x_variant":[
        "Tal\u0101ni\u0101n"
    ],
    "wof:name":"Talanian",
    "wof:placetype":"locality",
    "wof:population":254
},
  "geometry": {"coordinates":[76.38591099999999,30.664175],"type":"Point"}
}