{
  "type": "Feature",
  "properties": {
    "iso:country":"IN",
    "ks:ks_name":"Siroli",
    "ks:ks_pop":2243,
    "ks:ks_type":"VILLAGE",
    "name:eng_x_preferred":[
        "Siroli"
    ],
    "wof:name":"Siroli",
    "wof:placetype":"neighbourhood",
    "wof:population":2243
},
  "geometry": {"coordinates":[77.960302,27.115999],"type":"Point"}
}