{
  "type": "Feature",
  "properties": {
    "iso:country":"IN",
    "ks:ks_name":"Gopalpur",
    "ks:ks_pop":244,
    "ks:ks_type":"VILLAGE",
    "ks:ks_uagg_main":0,
    "name:eng_x_preferred":[
        "Gopalpur"
    ],
    "wof:name":"Gopalpur",
    "wof:placetype":"neighbourhood",
    "wof:population":244
},
  "geometry": {"coordinates":[84.297344,26.365934],"type":"Point"}
}