{
  "type": "Feature",
  "properties": {
    "gn:admin1_code":"34.0",
    "gn:admin2_code":"221.0",
    "gn:asciiname":"Bishunpur Kawa",
    "gn:country_code":"IN",
    "gn:dem":53,
    "gn:feature_class":"P",
    "gn:feature_code":"PPL",
    "gn:name":"Bishunpur K\u0101wa",
    "gn:population":0,
    "gn:timezone":"Asia/Kolkata",
    "iso:country":"IN",
    "ks:ks_alt_nam":"Bishunpur K\u0101wa",
    "ks:ks_name":"Bishunpur Kawa",
    "ks:ks_pop":1459,
    "ks:ks_type":"VILLAGE",
    "name:eng_x_preferred":[
        "Bishunpur Kawa"
    ],
    "name:eng_x_variant":[
        "Bishunpur K\u0101wa"
    ],
    "wof:name":"Bishunpur Kawa",
    "wof:placetype":"locality",
    "wof:population":1459
},
  "geometry": {"coordinates":[85.640957,25.915255],"type":"Point"}
}