{
  "type": "Feature",
  "properties": {
    "iso:country":"IN",
    "ks:ks_name":"Varsale",
    "ks:ks_pop":314,
    "ks:ks_type":"VILLAGE",
    "name:eng_x_preferred":[
        "Varsale"
    ],
    "wof:name":"Varsale",
    "wof:placetype":"locality",
    "wof:population":314
},
  "geometry": {"coordinates":[73.253288,19.727113],"type":"Point"}
}