{
  "type": "Feature",
  "properties": {
    "gn:admin1_code":"11",
    "gn:admin2_code":"23.0",
    "gn:asciiname":"Chanalon",
    "gn:country_code":"IN",
    "gn:dem":1940,
    "gn:feature_class":"P",
    "gn:feature_code":"PPL",
    "gn:name":"Chan\u0101lon",
    "gn:population":0,
    "gn:timezone":"Asia/Kolkata",
    "iso:country":"IN",
    "wof:name":"Chanalon",
    "wof:placetype":"locality"
},
  "geometry": {"coordinates":[76.09220000000001,32.83763],"type":"Point"}
}