{
  "type": "Feature",
  "properties": {
    "iso:country":"IN",
    "ks:ks_name":"Buxa Hill Forest",
    "ks:ks_pop":3144,
    "ks:ks_type":"VILLAGE",
    "name:eng_x_preferred":[
        "Buxa Hill Forest"
    ],
    "wof:name":"Buxa Hill Forest",
    "wof:placetype":"locality",
    "wof:population":3144
},
  "geometry": {"coordinates":[89.580811,26.75629],"type":"Point"}
}