{
  "type": "Feature",
  "properties": {
    "iso:country":"IN",
    "ks:ks_name":"Sibpur",
    "ks:ks_pop":0,
    "ks:ks_type":"VILLAGE",
    "name:eng_x_preferred":[
        "Sibpur"
    ],
    "wof:name":"Sibpur",
    "wof:placetype":"locality",
    "wof:population":0
},
  "geometry": {"coordinates":[86.70734,25.159317],"type":"Point"}
}