{
  "type": "Feature",
  "properties": {
    "gn:admin1_code":"35.0",
    "gn:admin2_code":"458.0",
    "gn:asciiname":"Biroli",
    "gn:country_code":"IN",
    "gn:dem":363,
    "gn:feature_class":"P",
    "gn:feature_code":"PPL",
    "gn:name":"Biroli",
    "gn:population":0,
    "gn:timezone":"Asia/Kolkata",
    "iso:country":"IN",
    "ks:ks_name":"Viroli",
    "ks:ks_pop":382,
    "ks:ks_type":"HABITATION",
    "name:eng_x_preferred":[
        "Viroli"
    ],
    "name:eng_x_variant":[
        "Biroli"
    ],
    "wof:name":"Viroli",
    "wof:placetype":"locality",
    "wof:population":382
},
  "geometry": {"coordinates":[76.88256800000001,24.97437],"type":"Point"}
}