{
  "type": "Feature",
  "properties": {
    "iso:country":"IN",
    "ks:ks_name":"Dev Dih",
    "ks:ks_pop":2532,
    "ks:ks_type":"VILLAGE",
    "ks:ks_uagg_main":0,
    "name:eng_x_preferred":[
        "Dev Dih"
    ],
    "wof:name":"Dev Dih",
    "wof:placetype":"neighbourhood",
    "wof:population":2532
},
  "geometry": {"coordinates":[84.202471,25.888338],"type":"Point"}
}