{
  "type": "Feature",
  "properties": {
    "iso:country":"IN",
    "ks:ks_name":"Gadkhol",
    "ks:ks_pop":1078,
    "ks:ks_type":"VILLAGE",
    "ks:ks_uagg_main":0,
    "name:eng_x_preferred":[
        "Gadkhol"
    ],
    "wof:name":"Gadkhol",
    "wof:placetype":"neighbourhood",
    "wof:population":1078
},
  "geometry": {"coordinates":[73.020618,21.638368],"type":"Point"}
}