{
  "type": "Feature",
  "properties": {
    "iso:country":"IN",
    "ks:ks_name":"Gosmanekelginawada",
    "ks:ks_pop":24,
    "ks:ks_type":"HABITATION",
    "name:eng_x_preferred":[
        "Gosmanekelginawada"
    ],
    "wof:name":"Gosmanekelginawada",
    "wof:placetype":"locality",
    "wof:population":24
},
  "geometry": {"coordinates":[74.70214199999999,15.027733],"type":"Point"}
}