{
  "type": "Feature",
  "properties": {
    "iso:country":"IN",
    "ks:ks_name":"Chavanwasti",
    "ks:ks_pop":560,
    "ks:ks_type":"HABITATION",
    "name:eng_x_preferred":[
        "Chavanwasti"
    ],
    "wof:name":"Chavanwasti",
    "wof:placetype":"locality",
    "wof:population":560
},
  "geometry": {"coordinates":[75.056432,17.767808],"type":"Point"}
}