{
  "type": "Feature",
  "properties": {
    "iso:country":"IN",
    "ks:ks_alt_nam":"Jagarn\u0101thpur",
    "ks:ks_name":"Jagarnathpur",
    "ks:ks_type":"VILLAGE",
    "ks:ks_uagg_main":0,
    "name:eng_x_preferred":[
        "Jagarnathpur"
    ],
    "name:eng_x_variant":[
        "Jagarn\u0101thpur"
    ],
    "wof:name":"Jagarnathpur",
    "wof:placetype":"neighbourhood"
},
  "geometry": {"coordinates":[85.286106,23.316281],"type":"Point"}
}