{
  "type": "Feature",
  "properties": {
    "gn:admin1_code":"25.0",
    "gn:admin2_code":"631.0",
    "gn:asciiname":"Vepasandiram",
    "gn:country_code":"IN",
    "gn:dem":919,
    "gn:feature_class":"P",
    "gn:feature_code":"PPL",
    "gn:name":"V\u0113pasandiram",
    "gn:population":0,
    "gn:timezone":"Asia/Kolkata",
    "iso:country":"IN",
    "wof:name":"Vepasandiram",
    "wof:placetype":"neighbourhood"
},
  "geometry": {"coordinates":[77.84952,12.4118],"type":"Point"}
}