{
  "type": "Feature",
  "properties": {
    "iso:country":"IN",
    "ks:ks_name":"Peddamasanpally",
    "ks:ks_pop":1655,
    "ks:ks_type":"HABITATION",
    "name:eng_x_preferred":[
        "Peddamasanpally"
    ],
    "wof:name":"Peddamasanpally",
    "wof:placetype":"locality",
    "wof:population":1655
},
  "geometry": {"coordinates":[78.805949,18.010258],"type":"Point"}
}