{
  "type": "Feature",
  "properties": {
    "gn:country":"IN",
    "gn:fcode":"PPL",
    "gn:population":0,
    "iso:country":"IN",
    "name:ara_x_preferred":[
        "\u0644\u0627\u0645"
    ],
    "name:ben_bn_x_preferred":[
        "\u09b2\u09be\u09ae"
    ],
    "name:ben_in_x_preferred":[
        "\u09b2\u09be\u09ae"
    ],
    "name:ceb_x_preferred":[
        "Lam"
    ],
    "name:dan_x_preferred":[
        "Lam"
    ],
    "name:fra_x_preferred":[
        "Lam"
    ],
    "name:guj_x_preferred":[
        "\u0ab2\u0abe\u0aae"
    ],
    "name:hin_x_preferred":[
        "\u0932\u093e\u092e"
    ],
    "name:kan_x_preferred":[
        "\u0cb2\u0ccd\u0caf\u0cbe\u0cae\u0ccd"
    ],
    "name:mal_x_preferred":[
        "\u0d32\u0d3e\u0d02"
    ],
    "name:mar_x_preferred":[
        "\u0932\u0945\u092e"
    ],
    "name:nld_x_preferred":[
        "Lam"
    ],
    "name:nor_x_preferred":[
        "Lam"
    ],
    "name:pan_x_preferred":[
        "\u0a32\u0a48\u0a2e"
    ],
    "name:pol_x_preferred":[
        "Lam"
    ],
    "name:por_x_preferred":[
        "Lam"
    ],
    "name:swe_x_preferred":[
        "Lam"
    ],
    "name:tam_x_preferred":[
        "\u0bb2\u0bbe\u0bae\u0bcd"
    ],
    "name:tel_x_preferred":[
        "\u0c32\u0c3e\u0c2e\u0c4d"
    ],
    "name:urd_x_preferred":[
        "\u0644\u0627\u0645"
    ],
    "name:vie_x_preferred":[
        "Lam"
    ],
    "qs:name":"Lam",
    "qs:name_adm0":"India",
    "qs:name_adm1":"Jammu and Kashmir",
    "qs:photos":26,
    "qs:photos_1k":5,
    "qs:photos_9k":1,
    "qs:photos_9r":2,
    "qs:photos_all":26,
    "qs:photos_sr":2,
    "qs:placetype":"Suburb",
    "qs:pop_sr":"0",
    "wd:wordcount":1117,
    "wof:name":"Lam",
    "wof:placetype":"neighbourhood",
    "wof:population":0
},
  "geometry": {"coordinates":[74.88153,34.11634],"type":"Point"}
}