{
  "type": "Feature",
  "properties": {
    "gn:country":"IN",
    "gn:fcode":"PPL",
    "gn:pop":0,
    "iso:country":"IN",
    "name:ceb_x_preferred":[
        "Lam"
    ],
    "name:dan_x_preferred":[
        "Lam"
    ],
    "name:fra_x_preferred":[
        "Lam"
    ],
    "name:nld_x_preferred":[
        "Lam"
    ],
    "name:nor_x_preferred":[
        "Lam"
    ],
    "name:pol_x_preferred":[
        "Lam"
    ],
    "name:por_x_preferred":[
        "Lam"
    ],
    "name:swe_x_preferred":[
        "Lam"
    ],
    "name:vie_x_preferred":[
        "Lam"
    ],
    "qs:name":"Lam",
    "qs:name_adm0":"India",
    "qs:name_adm1":"Jammu and Kashmir",
    "qs:photos":26,
    "qs:photos_1k":5,
    "qs:photos_9k":1,
    "qs:photos_9r":2,
    "qs:photos_all":26,
    "qs:photos_sr":2,
    "qs:placetype":"Suburb",
    "qs:pop_sr":"0",
    "wd:wordcount":1117,
    "wof:name":"Lam",
    "wof:placetype":"neighbourhood",
    "wof:population":0
},
  "geometry": {"coordinates":[74.88153,34.11634],"type":"Point"}
}