{
  "type": "Feature",
  "properties": {
    "gn:admin1_code":"03",
    "gn:admin2_code":"314.0",
    "gn:asciiname":"Longkamgaon",
    "gn:country_code":"IN",
    "gn:dem":559,
    "gn:feature_class":"P",
    "gn:feature_code":"PPL",
    "gn:name":"Longk\u0101mgaon",
    "gn:population":0,
    "gn:timezone":"Asia/Kolkata",
    "iso:country":"IN",
    "wof:name":"Longkamgaon",
    "wof:placetype":"locality"
},
  "geometry": {"coordinates":[93.37482,26.187],"type":"Point"}
}