{
  "type": "Feature",
  "properties": {
    "gn:admin1_code":"03",
    "gn:admin2_code":"314.0",
    "gn:asciiname":"Longkamgaon",
    "gn:country_code":"IN",
    "gn:dem":559,
    "gn:feature_class":"P",
    "gn:feature_code":"PPL",
    "gn:name":"Longk\u0101mgaon",
    "gn:population":0,
    "gn:timezone":"Asia/Kolkata",
    "iso:country":"IN",
    "ks:ks_alt_nam":"Longk\u0101mgaon",
    "ks:ks_name":"Longkamgaon",
    "ks:ks_type":"VILLAGE",
    "name:eng_x_preferred":[
        "Longkamgaon"
    ],
    "name:eng_x_variant":[
        "Longk\u0101mgaon"
    ],
    "wof:name":"Longkamgaon",
    "wof:placetype":"locality"
},
  "geometry": {"coordinates":[93.374821,26.186998],"type":"Point"}
}