{
  "type": "Feature",
  "properties": {
    "iso:country":"IN",
    "ks:ks_name":"Bhitar Amda",
    "ks:ks_pop":702,
    "ks:ks_type":"VILLAGE",
    "name:eng_x_preferred":[
        "Bhitar Amda"
    ],
    "wof:name":"Bhitar Amda",
    "wof:placetype":"locality",
    "wof:population":702
},
  "geometry": {"coordinates":[86.33378,22.41347],"type":"Point"}
}