{
  "type": "Feature",
  "properties": {
    "iso:country":"IN",
    "ks:ks_name":"Padmapur I",
    "ks:ks_pop":30,
    "ks:ks_type":"HABITATION",
    "name:eng_x_preferred":[
        "Padmapur I"
    ],
    "wof:name":"Padmapur I",
    "wof:placetype":"locality",
    "wof:population":30
},
  "geometry": {"coordinates":[84.417376,19.30945],"type":"Point"}
}