{
  "type": "Feature",
  "properties": {
    "iso:country":"IN",
    "ks:ks_name":"Borora Gaon",
    "ks:ks_pop":640,
    "ks:ks_type":"VILLAGE",
    "ks:ks_uagg_main":0,
    "name:eng_x_preferred":[
        "Borora Gaon"
    ],
    "wof:name":"Borora Gaon",
    "wof:placetype":"neighbourhood",
    "wof:population":640
},
  "geometry": {"coordinates":[91.856155,26.54579],"type":"Point"}
}