{
  "type": "Feature",
  "properties": {
    "gn:admin1_code":"34.0",
    "gn:admin2_code":"208.0",
    "gn:asciiname":"Bhawanipur",
    "gn:country_code":"IN",
    "gn:dem":75,
    "gn:feature_class":"P",
    "gn:feature_code":"PPL",
    "gn:name":"Bhawanipur",
    "gn:population":27000,
    "gn:timezone":"Asia/Kolkata",
    "iso:country":"IN",
    "name:ceb_x_preferred":[
        "Bhawanipur"
    ],
    "name:spa_x_preferred":[
        "Bhawanipur"
    ],
    "name:swe_x_preferred":[
        "Bhawanipur"
    ],
    "wof:name":"Bhawanipur",
    "wof:placetype":"locality",
    "wof:population":27000
},
  "geometry": {"coordinates":[87.02744,26.45352],"type":"Point"}
}