{
  "type": "Feature",
  "properties": {
    "iso:country":"IN",
    "ks:ks_name":"Bhalluguda",
    "ks:ks_pop":87,
    "ks:ks_type":"HABITATION",
    "name:eng_x_preferred":[
        "Bhalluguda"
    ],
    "wof:name":"Bhalluguda",
    "wof:placetype":"locality",
    "wof:population":87
},
  "geometry": {"coordinates":[82.85496999999999,18.348705],"type":"Point"}
}