{
  "type": "Feature",
  "properties": {
    "iso:country":"IN",
    "ks:ks_alt_nam":"ChingiPurwa",
    "ks:ks_name":"Chingipurwa",
    "ks:ks_pop":76,
    "ks:ks_type":"HABITATION",
    "name:eng_x_preferred":[
        "Chingipurwa"
    ],
    "wof:name":"Chingipurwa",
    "wof:placetype":"locality",
    "wof:population":76
},
  "geometry": {"coordinates":[81.520554,27.969631],"type":"Point"}
}