{
  "type": "Feature",
  "properties": {
    "iso:country":"IN",
    "ks:ks_name":"Alagapuri",
    "ks:ks_pop":67,
    "ks:ks_type":"HABITATION",
    "name:eng_x_preferred":[
        "Alagapuri"
    ],
    "wof:name":"Alagapuri",
    "wof:placetype":"locality",
    "wof:population":67
},
  "geometry": {"coordinates":[78.78693800000001,9.731],"type":"Point"}
}