{
  "type": "Feature",
  "properties": {
    "gn:admin1_code":"36",
    "gn:admin2_code":"191.0",
    "gn:asciiname":"Khalifatpur",
    "gn:country_code":"IN",
    "gn:dem":85,
    "gn:feature_class":"P",
    "gn:feature_code":"PPL",
    "gn:name":"Khal\u012bfatpur",
    "gn:population":0,
    "gn:timezone":"Asia/Kolkata",
    "iso:country":"IN",
    "ks:ks_alt_nam":"Khal\u012bfatpur",
    "ks:ks_name":"Khalifatpur",
    "ks:ks_pop":622,
    "ks:ks_type":"VILLAGE",
    "ks:ks_uagg_main":0,
    "wof:name":"Khalifatpur",
    "wof:placetype":"neighbourhood"
},
  "geometry": {"coordinates":[83.03139,26.15524],"type":"Point"}
}