{
  "type": "Feature",
  "properties": {
    "gn:admin1_code":"2.0",
    "gn:admin2_code":"543.0",
    "gn:asciiname":"Chorapalle",
    "gn:country_code":"IN",
    "gn:dem":482,
    "gn:feature_class":"P",
    "gn:feature_code":"PPL",
    "gn:name":"Chorapalle",
    "gn:population":0,
    "gn:timezone":"Asia/Kolkata",
    "iso:country":"IN",
    "wof:name":"Chorapalle",
    "wof:placetype":"locality"
},
  "geometry": {"coordinates":[83.49688,18.97689],"type":"Point"}
}