{
  "type": "Feature",
  "properties": {
    "gn:admin1_code":"2.0",
    "gn:admin2_code":"543.0",
    "gn:asciiname":"Chorapalle",
    "gn:country_code":"IN",
    "gn:dem":482,
    "gn:feature_class":"P",
    "gn:feature_code":"PPL",
    "gn:name":"Chorapalle",
    "gn:population":0,
    "gn:timezone":"Asia/Kolkata",
    "iso:country":"IN",
    "ks:ks_name":"Chorupalle",
    "ks:ks_pop":150,
    "ks:ks_type":"HABITATION",
    "name:eng_x_preferred":[
        "Chorupalle"
    ],
    "name:eng_x_variant":[
        "Chorapalle"
    ],
    "wof:name":"Chorupalle",
    "wof:placetype":"locality",
    "wof:population":150
},
  "geometry": {"coordinates":[83.500134,18.972972],"type":"Point"}
}