{
  "type": "Feature",
  "properties": {
    "gn:admin1_code":"21.0",
    "gn:admin2_code":"399.0",
    "gn:asciiname":"Nilguda",
    "gn:country_code":"IN",
    "gn:dem":160,
    "gn:feature_class":"P",
    "gn:feature_code":"PPL",
    "gn:name":"Nilg\u016bda",
    "gn:population":0,
    "gn:timezone":"Asia/Kolkata",
    "iso:country":"IN",
    "ks:ks_name":"Nilaguda",
    "ks:ks_pop":343,
    "ks:ks_type":"HABITATION",
    "name:eng_x_preferred":[
        "Nilaguda"
    ],
    "name:eng_x_variant":[
        "Nilguda"
    ],
    "wof:name":"Nilaguda",
    "wof:placetype":"locality",
    "wof:population":343
},
  "geometry": {"coordinates":[81.537164,18.235423],"type":"Point"}
}