{
  "type": "Feature",
  "properties": {
    "gn:admin1_code":"40",
    "gn:admin2_code":"539.0",
    "gn:asciiname":"Regalgadda Tanda",
    "gn:country_code":"IN",
    "gn:dem":68,
    "gn:feature_class":"P",
    "gn:feature_code":"PPL",
    "gn:name":"Regalgadda T\u0101nda",
    "gn:population":0,
    "gn:timezone":"Asia/Kolkata",
    "iso:country":"IN",
    "wof:name":"Regalgadda Tanda",
    "wof:placetype":"locality"
},
  "geometry": {"coordinates":[79.45886,16.63181],"type":"Point"}
}