{
  "type": "Feature",
  "properties": {
    "gn:admin1_code":"36",
    "gn:admin2_code":"180.0",
    "gn:asciiname":"Jhingha",
    "gn:country_code":"IN",
    "gn:dem":119,
    "gn:feature_class":"P",
    "gn:feature_code":"PPL",
    "gn:name":"Jhingha",
    "gn:population":0,
    "gn:timezone":"Asia/Kolkata",
    "iso:country":"IN",
    "ks:ks_name":"Jhingha",
    "ks:ks_pop":2753,
    "ks:ks_type":"VILLAGE",
    "ks:ks_uagg_main":0,
    "name:eng_x_preferred":[
        "Jhingha"
    ],
    "wof:name":"Jhingha",
    "wof:placetype":"neighbourhood",
    "wof:population":2753
},
  "geometry": {"coordinates":[81.551734,27.579214],"type":"Point"}
}