{
  "type": "Feature",
  "properties": {
    "iso:country":"IN",
    "ks:ks_name":"Ambadahara",
    "ks:ks_pop":431,
    "ks:ks_type":"VILLAGE",
    "name:eng_x_preferred":[
        "Ambadahara"
    ],
    "wof:name":"Ambadahara",
    "wof:placetype":"locality",
    "wof:population":431
},
  "geometry": {"coordinates":[85.548513,21.635373],"type":"Point"}
}