{
  "type": "Feature",
  "properties": {
    "gn:admin1_code":"19",
    "gn:admin2_code":"580.0",
    "gn:asciiname":"Sanur",
    "gn:country_code":"IN",
    "gn:dem":384,
    "gn:feature_class":"P",
    "gn:feature_code":"PPL",
    "gn:name":"S\u0101n\u016br",
    "gn:population":0,
    "gn:timezone":"Asia/Kolkata",
    "iso:country":"IN",
    "name:ceb_x_preferred":[
        "Sanur"
    ],
    "name:dan_x_preferred":[
        "Sanur"
    ],
    "name:nld_x_preferred":[
        "Sanur"
    ],
    "name:swe_x_preferred":[
        "Sanur"
    ],
    "wof:name":"Sanur",
    "wof:placetype":"locality"
},
  "geometry": {"coordinates":[76.86849000000002,16.56179],"type":"Point"}
}