{
  "type": "Feature",
  "properties": {
    "gn:admin1_code":"35.0",
    "gn:admin2_code":"457.0",
    "gn:asciiname":"Bhamodi",
    "gn:country_code":"IN",
    "gn:dem":585,
    "gn:feature_class":"P",
    "gn:feature_code":"PPL",
    "gn:name":"Bhamod\u012b",
    "gn:population":0,
    "gn:timezone":"Asia/Kolkata",
    "iso:country":"IN",
    "name:ben_x_preferred":[
        "\u09ad\u09be\u09ae\u09cb\u09a6\u09bf"
    ],
    "name:bpy_x_preferred":[
        "\u09ad\u09be\u09ae\u09cb\u09a6\u09bf"
    ],
    "name:ita_x_preferred":[
        "Bhamodi"
    ],
    "name:msa_x_preferred":[
        "Bhamodi"
    ],
    "name:new_x_preferred":[
        "\u092d\u092e\u094b\u0926\u0940"
    ],
    "name:nld_x_preferred":[
        "Bhamodi"
    ],
    "name:por_x_preferred":[
        "Bhamodi"
    ],
    "name:spa_x_preferred":[
        "Bhamodi"
    ],
    "name:und_x_variant":[
        "Bhamod\u012b"
    ],
    "name:vie_x_preferred":[
        "Bhamodi"
    ],
    "name:zho_x_preferred":[
        "\u5df4\u83ab\u8fea"
    ],
    "wof:name":"Bhamodi",
    "wof:placetype":"locality"
},
  "geometry": {"coordinates":[80.3583,22.20371],"type":"Point"}
}