{
  "type": "Feature",
  "properties": {
    "gn:admin1_code":"12",
    "gn:admin2_code":"15.0",
    "gn:asciiname":"Nanyibug",
    "gn:country_code":"IN",
    "gn:dem":1672,
    "gn:feature_class":"P",
    "gn:feature_code":"PPL",
    "gn:name":"Nanyibug",
    "gn:population":0,
    "gn:timezone":"Asia/Kolkata",
    "iso:country":"IN",
    "wof:name":"Nanyibug",
    "wof:placetype":"locality"
},
  "geometry": {"coordinates":[75.04219999999999,33.68227],"type":"Point"}
}