{
  "type": "Feature",
  "properties": {
    "iso:country":"IN",
    "ks:ks_name":"Jhaliapara",
    "ks:ks_pop":334,
    "ks:ks_type":"VILLAGE",
    "name:eng_x_preferred":[
        "Jhaliapara"
    ],
    "wof:name":"Jhaliapara",
    "wof:placetype":"locality",
    "wof:population":334
},
  "geometry": {"coordinates":[82.539805,19.878548],"type":"Point"}
}