{
  "type": "Feature",
  "properties": {
    "iso:country":"IN",
    "ks:ks_name":"Kalamwadi",
    "ks:ks_pop":335,
    "ks:ks_type":"HABITATION",
    "name:eng_x_preferred":[
        "Kalamwadi"
    ],
    "wof:name":"Kalamwadi",
    "wof:placetype":"locality",
    "wof:population":335
},
  "geometry": {"coordinates":[73.40006,19.880982],"type":"Point"}
}