{
  "type": "Feature",
  "properties": {
    "iso:country":"IN",
    "ks:ks_name":"Punkedadi",
    "ks:ks_pop":1454,
    "ks:ks_type":"HABITATION",
    "name:eng_x_preferred":[
        "Punkedadi"
    ],
    "wof:name":"Punkedadi",
    "wof:placetype":"locality",
    "wof:population":1454
},
  "geometry": {"coordinates":[74.92106800000001,12.898784],"type":"Point"}
}