{
  "type": "Feature",
  "properties": {
    "gn:admin1_code":"16.0",
    "gn:admin2_code":"497.0",
    "gn:asciiname":"Pimpalpada",
    "gn:country_code":"IN",
    "gn:dem":647,
    "gn:feature_class":"P",
    "gn:feature_code":"PPL",
    "gn:name":"Pimpalp\u0101da",
    "gn:population":0,
    "gn:timezone":"Asia/Kolkata",
    "iso:country":"IN",
    "ks:ks_alt_nam":"Pimpalp\u0101da",
    "ks:ks_name":"Pimpalpada",
    "ks:ks_type":"VILLAGE",
    "name:eng_x_preferred":[
        "Pimpalpada"
    ],
    "name:eng_x_variant":[
        "Pimpalp\u0101da"
    ],
    "wof:name":"Pimpalpada",
    "wof:placetype":"locality"
},
  "geometry": {"coordinates":[74.206653,21.71133],"type":"Point"}
}