{
  "type": "Feature",
  "properties": {
    "gn:admin1_code":"25.0",
    "gn:admin2_code":"629.0",
    "gn:asciiname":"Palliyadi",
    "gn:country_code":"IN",
    "gn:dem":58,
    "gn:feature_class":"P",
    "gn:feature_code":"PPL",
    "gn:name":"Palliyadi",
    "gn:population":0,
    "gn:timezone":"Asia/Kolkata",
    "iso:country":"IN",
    "wof:name":"Palliyadi",
    "wof:placetype":"locality"
},
  "geometry": {"coordinates":[77.25131,8.26827],"type":"Point"}
}