{
  "type": "Feature",
  "properties": {
    "iso:country":"IN",
    "ks:ks_alt_nam":"MILKIYAN BASTI",
    "ks:ks_name":"Milkiyan Basti",
    "ks:ks_pop":73,
    "ks:ks_type":"HABITATION",
    "ks:ks_uagg_main":0,
    "name:eng_x_preferred":[
        "Milkiyan Basti"
    ],
    "wof:name":"Milkiyan Basti",
    "wof:placetype":"neighbourhood",
    "wof:population":73
},
  "geometry": {"coordinates":[82.2484,26.058079],"type":"Point"}
}