{
  "type": "Feature",
  "properties": {
    "iso:country":"IN",
    "ks:ks_name":"Agarewadi",
    "ks:ks_pop":157,
    "ks:ks_type":"HABITATION",
    "name:eng_x_preferred":[
        "Agarewadi"
    ],
    "wof:name":"Agarewadi",
    "wof:placetype":"locality",
    "wof:population":157
},
  "geometry": {"coordinates":[73.560272,17.508056],"type":"Point"}
}