{
  "type": "Feature",
  "properties": {
    "iso:country":"IN",
    "ks:ks_name":"Dhaneswarpur",
    "ks:ks_pop":861,
    "ks:ks_type":"VILLAGE",
    "name:eng_x_preferred":[
        "Dhaneswarpur"
    ],
    "wof:name":"Dhaneswarpur",
    "wof:placetype":"locality",
    "wof:population":861
},
  "geometry": {"coordinates":[86.69216299999999,20.650309],"type":"Point"}
}