{
  "type": "Feature",
  "properties": {
    "gn:admin1_code":"16",
    "gn:admin2_code":"509.0",
    "gn:asciiname":"Shegaon",
    "gn:country_code":"IN",
    "gn:dem":237,
    "gn:feature_class":"P",
    "gn:feature_code":"PPL",
    "gn:name":"Shegaon",
    "gn:population":0,
    "gn:timezone":"Asia/Kolkata",
    "iso:country":"IN",
    "name:ben_x_preferred":[
        "\u09b6\u09c7\u0997\u09be\u0981\u0993"
    ],
    "name:bpy_x_preferred":[
        "\u09b6\u09c7\u0997\u09be\u0981\u0993"
    ],
    "name:ceb_x_preferred":[
        "Shegaon"
    ],
    "name:ita_x_preferred":[
        "Shegaon"
    ],
    "name:mar_x_preferred":[
        "\u0936\u0947\u0917\u093e\u0902\u0935"
    ],
    "name:mlg_x_preferred":[
        "Shegaon"
    ],
    "name:msa_x_preferred":[
        "Shegaon"
    ],
    "name:nld_x_preferred":[
        "Shegaon"
    ],
    "name:ori_x_preferred":[
        "\u0b36\u0b47\u200c\u200c\u0b17\u0b3e\u0b13\u0b01"
    ],
    "name:pam_x_preferred":[
        "Shegaon"
    ],
    "name:swe_x_preferred":[
        "Shegaon"
    ],
    "name:und_x_variant":[
        "Shegaon Buzurg"
    ],
    "name:urd_x_preferred":[
        "\u0634\u06d2 \u06af\u0627\u0624\u06ba"
    ],
    "name:vie_x_preferred":[
        "Shegaon"
    ],
    "name:zho_x_preferred":[
        "\u65af\u8d6b\u52a0\u5965\u6069"
    ],
    "wof:name":"Shegaon",
    "wof:placetype":"locality"
},
  "geometry": {"coordinates":[79.15004999999999,20.32965],"type":"Point"}
}