{
  "type": "Feature",
  "properties": {
    "gn:admin1_code":"16",
    "gn:admin2_code":"509.0",
    "gn:asciiname":"Shegaon",
    "gn:country_code":"IN",
    "gn:dem":237,
    "gn:feature_class":"P",
    "gn:feature_code":"PPL",
    "gn:name":"Shegaon",
    "gn:population":0,
    "gn:timezone":"Asia/Kolkata",
    "iso:country":"IN",
    "name:und_x_variant":[
        "Shegaon Buzurg"
    ],
    "wof:name":"Shegaon",
    "wof:placetype":"locality"
},
  "geometry": {"coordinates":[79.15004999999999,20.32965],"type":"Point"}
}