{
  "type": "Feature",
  "properties": {
    "iso:country":"IN",
    "ks:ks_name":"Majhauli",
    "ks:ks_pop":1086,
    "ks:ks_type":"VILLAGE",
    "ks:ks_uagg_main":0,
    "name:eng_x_preferred":[
        "Majhauli"
    ],
    "wof:name":"Majhauli",
    "wof:placetype":"neighbourhood",
    "wof:population":1086
},
  "geometry": {"coordinates":[83.610795,26.429545],"type":"Point"}
}