{
  "type": "Feature",
  "properties": {
    "iso:country":"IN",
    "ks:ks_name":"Inammaniyachi",
    "ks:ks_pop":4008,
    "ks:ks_type":"VILLAGE",
    "ks:ks_uagg_main":0,
    "name:eng_x_preferred":[
        "Inammaniyachi"
    ],
    "wof:name":"Inammaniyachi",
    "wof:placetype":"neighbourhood",
    "wof:population":4008
},
  "geometry": {"coordinates":[77.84954,9.169532],"type":"Point"}
}