{
  "type": "Feature",
  "properties": {
    "iso:country":"IN",
    "ks:ks_name":"Sainj",
    "ks:ks_pop":388,
    "ks:ks_type":"HABITATION",
    "name:eng_x_preferred":[
        "Sainj"
    ],
    "wof:name":"Sainj",
    "wof:placetype":"locality",
    "wof:population":388
},
  "geometry": {"coordinates":[79.794842,29.7211],"type":"Point"}
}