{
  "type": "Feature",
  "properties": {
    "iso:country":"IN",
    "ks:ks_name":"Sarcargachher Chhat",
    "ks:ks_pop":32,
    "ks:ks_type":"VILLAGE",
    "name:eng_x_preferred":[
        "Sarcargachher Chhat"
    ],
    "wof:name":"Sarcargachher Chhat",
    "wof:placetype":"locality",
    "wof:population":32
},
  "geometry": {"coordinates":[88.31576200000001,26.641305],"type":"Point"}
}