{
  "type": "Feature",
  "properties": {
    "gn:admin1_code":"02",
    "gn:admin2_code":"552.0",
    "gn:asciiname":"Parumanchala",
    "gn:country_code":"IN",
    "gn:dem":291,
    "gn:feature_class":"P",
    "gn:feature_code":"PPL",
    "gn:name":"P\u0101rumanch\u0101la",
    "gn:population":0,
    "gn:timezone":"Asia/Kolkata",
    "iso:country":"IN",
    "wof:name":"Parumanchala",
    "wof:placetype":"locality"
},
  "geometry": {"coordinates":[78.40187,15.79754],"type":"Point"}
}