{
  "type": "Feature",
  "properties": {
    "gn:admin1_code":"35.0",
    "gn:admin2_code":"441.0",
    "gn:asciiname":"Barwani Khurd",
    "gn:country_code":"IN",
    "gn:dem":216,
    "gn:feature_class":"P",
    "gn:feature_code":"PPL",
    "gn:name":"Barw\u0101ni Khurd",
    "gn:population":0,
    "gn:timezone":"Asia/Kolkata",
    "iso:country":"IN",
    "ks:ks_name":"Barwani Khurd",
    "ks:ks_pop":1326,
    "ks:ks_type":"HABITATION",
    "name:eng_x_preferred":[
        "Barwani Khurd"
    ],
    "wof:name":"Barwani Khurd",
    "wof:placetype":"locality",
    "wof:population":1326
},
  "geometry": {"coordinates":[74.87774899999999,22.020802],"type":"Point"}
}