{
  "type": "Feature",
  "properties": {
    "iso:country":"IN",
    "ks:ks_name":"Rampara",
    "ks:ks_pop":2624,
    "ks:ks_type":"VILLAGE",
    "ks:ks_uagg_main":0,
    "name:eng_x_preferred":[
        "Rampara"
    ],
    "wof:name":"Rampara",
    "wof:placetype":"neighbourhood",
    "wof:population":2624
},
  "geometry": {"coordinates":[88.327668,23.981609],"type":"Point"}
}