{
  "type": "Feature",
  "properties": {
    "gn:admin1_code":"39.0",
    "gn:admin2_code":"60.0",
    "gn:asciiname":"Bhitarli Bari",
    "gn:country_code":"IN",
    "gn:dem":1098,
    "gn:feature_class":"P",
    "gn:feature_code":"PPL",
    "gn:name":"Bhitarli Bari",
    "gn:population":0,
    "gn:timezone":"Asia/Kolkata",
    "iso:country":"IN",
    "wof:name":"Bhitarli Bari",
    "wof:placetype":"locality"
},
  "geometry": {"coordinates":[78.04772,30.42718],"type":"Point"}
}