{
  "type": "Feature",
  "properties": {
    "iso:country":"IN",
    "ks:ks_name":"Bhimkhole",
    "ks:ks_pop":67,
    "ks:ks_type":"HABITATION",
    "name:eng_x_preferred":[
        "Bhimkhole"
    ],
    "wof:name":"Bhimkhole",
    "wof:placetype":"locality",
    "wof:population":67
},
  "geometry": {"coordinates":[84.389692,20.580202],"type":"Point"}
}