{
  "type": "Feature",
  "properties": {
    "iso:country":"IN",
    "ks:ks_name":"Bhemarpally",
    "ks:ks_pop":336,
    "ks:ks_type":"HABITATION",
    "ks:ks_uagg_main":0,
    "name:eng_x_preferred":[
        "Bhemarpally"
    ],
    "wof:name":"Bhemarpally",
    "wof:placetype":"neighbourhood",
    "wof:population":336
},
  "geometry": {"coordinates":[79.479159,18.450957],"type":"Point"}
}