{
  "type": "Feature",
  "properties": {
    "iso:country":"IN",
    "ks:ks_name":"Pura Malkhan Singh",
    "ks:ks_pop":50,
    "ks:ks_type":"HABITATION",
    "name:eng_x_preferred":[
        "Pura Malkhan Singh"
    ],
    "wof:name":"Pura Malkhan Singh",
    "wof:placetype":"locality",
    "wof:population":50
},
  "geometry": {"coordinates":[78.055358,26.967804],"type":"Point"}
}