{
  "type": "Feature",
  "properties": {
    "iso:country":"IN",
    "ks:ks_name":"Ramdevnagar",
    "ks:ks_pop":380,
    "ks:ks_type":"HABITATION",
    "name:eng_x_preferred":[
        "Ramdevnagar"
    ],
    "wof:name":"Ramdevnagar",
    "wof:placetype":"locality",
    "wof:population":380
},
  "geometry": {"coordinates":[72.377803,26.83205],"type":"Point"}
}