{
  "type": "Feature",
  "properties": {
    "iso:country":"IN",
    "ks:ks_alt_nam":"AVULAVARIPALEM",
    "ks:ks_name":"Avulavaripalem",
    "ks:ks_pop":378,
    "ks:ks_type":"HABITATION",
    "name:eng_x_preferred":[
        "Avulavaripalem"
    ],
    "wof:name":"Avulavaripalem",
    "wof:placetype":"locality",
    "wof:population":378
},
  "geometry": {"coordinates":[80.712548,16.02929],"type":"Point"}
}