{
  "type": "Feature",
  "properties": {
    "iso:country":"IN",
    "ks:ks_name":"Holi Falia",
    "ks:ks_pop":149,
    "ks:ks_type":"HABITATION",
    "name:eng_x_preferred":[
        "Holi Falia"
    ],
    "wof:name":"Holi Falia",
    "wof:placetype":"locality",
    "wof:population":149
},
  "geometry": {"coordinates":[74.401861,22.81775],"type":"Point"}
}