{
  "type": "Feature",
  "properties": {
    "iso:country":"IN",
    "ks:ks_alt_nam":"CHIRDARKUNDE MALA",
    "ks:ks_name":"Chirdarkunde Mala",
    "ks:ks_pop":83,
    "ks:ks_type":"HABITATION",
    "name:eng_x_preferred":[
        "Chirdarkunde Mala"
    ],
    "wof:name":"Chirdarkunde Mala",
    "wof:placetype":"locality",
    "wof:population":83
},
  "geometry": {"coordinates":[74.64811,18.861297],"type":"Point"}
}