{
  "type": "Feature",
  "properties": {
    "iso:country":"IN",
    "ks:ks_name":"Dosimapara",
    "ks:ks_pop":644,
    "ks:ks_type":"VILLAGE",
    "ks:ks_uagg_main":0,
    "name:eng_x_preferred":[
        "Dosimapara"
    ],
    "wof:name":"Dosimapara",
    "wof:placetype":"neighbourhood",
    "wof:population":644
},
  "geometry": {"coordinates":[90.53225399999999,26.452687],"type":"Point"}
}