{
  "type": "Feature",
  "properties": {
    "iso:country":"IN",
    "ks:ks_name":"Machwai",
    "ks:ks_pop":68,
    "ks:ks_type":"HABITATION",
    "name:eng_x_preferred":[
        "Machwai"
    ],
    "wof:name":"Machwai",
    "wof:placetype":"locality",
    "wof:population":68
},
  "geometry": {"coordinates":[73.307108,17.260669],"type":"Point"}
}