{
  "type": "Feature",
  "properties": {
    "iso:country":"IN",
    "ks:ks_name":"Pub-Dairang",
    "ks:ks_pop":1629,
    "ks:ks_type":"VILLAGE",
    "name:eng_x_preferred":[
        "Pub-Dairang"
    ],
    "wof:name":"Pub-Dairang",
    "wof:placetype":"locality",
    "wof:population":1629
},
  "geometry": {"coordinates":[90.643452,25.98547],"type":"Point"}
}