{
  "type": "Feature",
  "properties": {
    "iso:country":"IN",
    "ks:ks_name":"Oinawa",
    "ks:ks_pop":990,
    "ks:ks_type":"VILLAGE",
    "ks:ks_uagg_main":0,
    "name:eng_x_preferred":[
        "Oinawa"
    ],
    "wof:name":"Oinawa",
    "wof:placetype":"neighbourhood",
    "wof:population":990
},
  "geometry": {"coordinates":[83.11873300000001,25.163713],"type":"Point"}
}