{
  "type": "Feature",
  "properties": {
    "iso:country":"IN",
    "ks:ks_alt_nam":"B\u0101ndu",
    "ks:ks_name":"Bandu",
    "ks:ks_pop":894,
    "ks:ks_type":"VILLAGE",
    "name:eng_x_preferred":[
        "Bandu"
    ],
    "name:eng_x_variant":[
        "B\u0101ndu"
    ],
    "wof:name":"Bandu",
    "wof:placetype":"locality",
    "wof:population":894
},
  "geometry": {"coordinates":[85.135919,22.678146],"type":"Point"}
}