{
  "type": "Feature",
  "properties": {
    "iso:country":"IN",
    "ks:ks_name":"Kandi Khal Lagga Selur",
    "ks:ks_pop":168,
    "ks:ks_type":"HABITATION",
    "name:eng_x_preferred":[
        "Kandi Khal Lagga Selur"
    ],
    "wof:name":"Kandi Khal Lagga Selur",
    "wof:placetype":"locality",
    "wof:population":168
},
  "geometry": {"coordinates":[78.390468,30.432345],"type":"Point"}
}