{
  "type": "Feature",
  "properties": {
    "iso:country":"IN",
    "ks:ks_name":"Kursamari FV",
    "ks:ks_pop":246,
    "ks:ks_type":"VILLAGE",
    "name:eng_x_preferred":[
        "Kursamari FV"
    ],
    "wof:name":"Kursamari FV",
    "wof:placetype":"locality",
    "wof:population":246
},
  "geometry": {"coordinates":[90.09217200000001,26.429503],"type":"Point"}
}