{
  "type": "Feature",
  "properties": {
    "gn:admin1_code":"24.0",
    "gn:admin2_code":"102.0",
    "gn:asciiname":"Biran",
    "gn:country_code":"IN",
    "gn:dem":254,
    "gn:feature_class":"P",
    "gn:feature_code":"PPL",
    "gn:name":"B\u012br\u0101n",
    "gn:population":0,
    "gn:timezone":"Asia/Kolkata",
    "iso:country":"IN",
    "name:ceb_x_preferred":[
        "Biran"
    ],
    "name:deu_x_preferred":[
        "Biran"
    ],
    "name:fra_x_preferred":[
        "Biran"
    ],
    "name:heb_x_preferred":[
        "\u05d1\u05d9\u05e8\u05df"
    ],
    "name:nld_x_preferred":[
        "Biran"
    ],
    "name:oci_x_preferred":[
        "Biran"
    ],
    "name:pol_x_preferred":[
        "Biran"
    ],
    "name:rus_x_preferred":[
        "\u0411\u0438\u0440\u0430\u043d"
    ],
    "name:srp_x_preferred":[
        "\u0411\u0438\u0440\u0430\u043d"
    ],
    "name:swe_x_preferred":[
        "Biran"
    ],
    "wof:name":"Biran",
    "wof:placetype":"neighbourhood"
},
  "geometry": {"coordinates":[75.58906,28.58284],"type":"Point"}
}