{
  "type": "Feature",
  "properties": {
    "iso:country":"IN",
    "ks:ks_name":"Jot Silam",
    "ks:ks_pop":358,
    "ks:ks_type":"VILLAGE",
    "ks:ks_uagg_main":0,
    "name:eng_x_preferred":[
        "Jot Silam"
    ],
    "wof:name":"Jot Silam",
    "wof:placetype":"neighbourhood",
    "wof:population":358
},
  "geometry": {"coordinates":[87.881047,23.18023],"type":"Point"}
}