{
  "type": "Feature",
  "properties": {
    "gn:admin1_code":"35",
    "gn:admin2_code":"423.0",
    "gn:asciiname":"Deopura",
    "gn:country_code":"IN",
    "gn:dem":421,
    "gn:feature_class":"P",
    "gn:feature_code":"PPL",
    "gn:name":"Deopura",
    "gn:population":0,
    "gn:timezone":"Asia/Kolkata",
    "iso:country":"IN",
    "wof:name":"Deopura",
    "wof:placetype":"locality"
},
  "geometry": {"coordinates":[77.40346,25.73156],"type":"Point"}
}