{
  "type": "Feature",
  "properties": {
    "gn:admin1_code":"35",
    "gn:admin2_code":"462.0",
    "gn:asciiname":"Chakraur",
    "gn:country_code":"IN",
    "gn:dem":392,
    "gn:feature_class":"P",
    "gn:feature_code":"PPL",
    "gn:name":"Chakraur",
    "gn:population":0,
    "gn:timezone":"Asia/Kolkata",
    "iso:country":"IN",
    "ks:ks_name":"Chakdaur",
    "ks:ks_pop":4052,
    "ks:ks_type":"VILLAGE",
    "name:eng_x_preferred":[
        "Chakdaur"
    ],
    "name:eng_x_variant":[
        "Chakraur"
    ],
    "wof:name":"Chakdaur",
    "wof:placetype":"locality",
    "wof:population":4052
},
  "geometry": {"coordinates":[81.67013900000001,24.309991],"type":"Point"}
}