{
  "type": "Feature",
  "properties": {
    "iso:country":"IN",
    "ks:ks_name":"Kappejaddi",
    "ks:ks_pop":13,
    "ks:ks_type":"HABITATION",
    "name:eng_x_preferred":[
        "Kappejaddi"
    ],
    "wof:name":"Kappejaddi",
    "wof:placetype":"locality",
    "wof:population":13
},
  "geometry": {"coordinates":[74.71651900000001,14.346498],"type":"Point"}
}