{
  "type": "Feature",
  "properties": {
    "iso:country":"IN",
    "ks:ks_name":"Paran Patti Sauth",
    "ks:ks_pop":618,
    "ks:ks_type":"HABITATION",
    "name:eng_x_preferred":[
        "Paran Patti Sauth"
    ],
    "wof:name":"Paran Patti Sauth",
    "wof:placetype":"locality",
    "wof:population":618
},
  "geometry": {"coordinates":[87.306157,25.964149],"type":"Point"}
}