{
  "type": "Feature",
  "properties": {
    "iso:country":"IN",
    "ks:ks_name":"Jagjeet",
    "ks:ks_pop":200,
    "ks:ks_type":"HABITATION",
    "name:eng_x_preferred":[
        "Jagjeet"
    ],
    "wof:name":"Jagjeet",
    "wof:placetype":"locality",
    "wof:population":200
},
  "geometry": {"coordinates":[80.870504,27.706643],"type":"Point"}
}