{
  "type": "Feature",
  "properties": {
    "iso:country":"IN",
    "ks:ks_name":"Chitra Pahari",
    "ks:ks_pop":27,
    "ks:ks_type":"VILLAGE",
    "name:eng_x_preferred":[
        "Chitra Pahari"
    ],
    "wof:name":"Chitra Pahari",
    "wof:placetype":"locality",
    "wof:population":27
},
  "geometry": {"coordinates":[86.251034,24.327173],"type":"Point"}
}