{
  "type": "Feature",
  "properties": {
    "iso:country":"IN",
    "ks:ks_name":"Amman Nagar",
    "ks:ks_pop":266,
    "ks:ks_type":"HABITATION",
    "ks:ks_uagg_main":0,
    "name:eng_x_preferred":[
        "Amman Nagar"
    ],
    "wof:name":"Amman Nagar",
    "wof:placetype":"neighbourhood",
    "wof:population":266
},
  "geometry": {"coordinates":[78.017383,12.251598],"type":"Point"}
}