{
  "type": "Feature",
  "properties": {
    "gn:admin1_code":"16",
    "gn:admin2_code":"503.0",
    "gn:asciiname":"Kund",
    "gn:country_code":"IN",
    "gn:dem":351,
    "gn:feature_class":"P",
    "gn:feature_code":"PPL",
    "gn:name":"Kund",
    "gn:population":0,
    "gn:timezone":"Asia/Kolkata",
    "iso:country":"IN",
    "ks:ks_name":"Kund",
    "ks:ks_pop":173,
    "ks:ks_type":"HABITATION",
    "name:eng_x_preferred":[
        "Kund"
    ],
    "name:fas_x_preferred":[
        "\u06a9\u0646\u062f"
    ],
    "name:urd_x_preferred":[
        "\u06a9\u0646\u0688"
    ],
    "wof:name":"Kund",
    "wof:placetype":"locality",
    "wof:population":173
},
  "geometry": {"coordinates":[77.180803,21.721454],"type":"Point"}
}