{
  "type": "Feature",
  "properties": {
    "iso:country":"IN",
    "ks:ks_name":"Kasaipali",
    "ks:ks_pop":1016,
    "ks:ks_type":"VILLAGE",
    "name:eng_x_preferred":[
        "Kasaipali"
    ],
    "wof:name":"Kasaipali",
    "wof:placetype":"locality",
    "wof:population":1016
},
  "geometry": {"coordinates":[82.55958699999999,22.390409],"type":"Point"}
}