{
  "type": "Feature",
  "properties": {
    "gn:admin1_code":"36.0",
    "gn:admin2_code":"133.0",
    "gn:asciiname":"Daulatpur",
    "gn:country_code":"IN",
    "gn:dem":249,
    "gn:feature_class":"P",
    "gn:feature_code":"PPL",
    "gn:name":"Daulatpur",
    "gn:population":0,
    "gn:timezone":"Asia/Kolkata",
    "iso:country":"IN",
    "wof:name":"Daulatpur",
    "wof:placetype":"locality"
},
  "geometry": {"coordinates":[77.92998,29.42389],"type":"Point"}
}