{
  "type": "Feature",
  "properties": {
    "gn:admin1_code":"35",
    "gn:admin2_code":"450.0",
    "gn:asciiname":"Shikarpur",
    "gn:country_code":"IN",
    "gn:dem":509,
    "gn:feature_class":"P",
    "gn:feature_code":"PPL",
    "gn:name":"Shik\u0101rpur",
    "gn:population":0,
    "gn:timezone":"Asia/Kolkata",
    "iso:country":"IN",
    "ks:ks_name":"Shikarpura",
    "ks:ks_pop":257,
    "ks:ks_type":"VILLAGE",
    "name:ceb_x_preferred":[
        "Shikarpur"
    ],
    "name:eng_x_preferred":[
        "Shikarpura"
    ],
    "name:eng_x_variant":[
        "Shikarpur"
    ],
    "name:pol_x_preferred":[
        "Shikarpur"
    ],
    "name:pus_x_preferred":[
        "\u0634\u06a9\u0627\u0631\u067e\u0648\u0631"
    ],
    "name:swe_x_preferred":[
        "Shikarpur"
    ],
    "name:urd_x_preferred":[
        "\u0634\u06a9\u0627\u0631\u067e\u0648\u0631"
    ],
    "name:vie_x_preferred":[
        "Shikarpur"
    ],
    "wof:name":"Shikarpura",
    "wof:placetype":"locality",
    "wof:population":257
},
  "geometry": {"coordinates":[79.85656299999999,23.768601],"type":"Point"}
}