{
  "type": "Feature",
  "properties": {
    "gn:admin1_code":"19.0",
    "gn:admin2_code":"573.0",
    "gn:asciiname":"Mole",
    "gn:country_code":"IN",
    "gn:dem":703,
    "gn:feature_class":"P",
    "gn:feature_code":"PPL",
    "gn:name":"Mole",
    "gn:population":0,
    "gn:timezone":"Asia/Kolkata",
    "iso:country":"IN",
    "name:ceb_x_preferred":[
        "Mole"
    ],
    "name:deu_x_preferred":[
        "Mole"
    ],
    "name:ell_x_preferred":[
        "Mole"
    ],
    "name:fin_x_preferred":[
        "Myyr\u00e4"
    ],
    "name:fra_x_preferred":[
        "Mole"
    ],
    "name:ita_x_preferred":[
        "Mole"
    ],
    "name:jpn_x_preferred":[
        "\u3082\u3050\u3089"
    ],
    "name:nld_x_preferred":[
        "Mole"
    ],
    "name:nor_x_preferred":[
        "Mole"
    ],
    "name:pol_x_preferred":[
        "Mole"
    ],
    "name:por_x_preferred":[
        "Mole"
    ],
    "name:spa_x_preferred":[
        "Mole"
    ],
    "name:swe_x_preferred":[
        "Mole"
    ],
    "wof:name":"Mole",
    "wof:placetype":"neighbourhood"
},
  "geometry": {"coordinates":[76.91649,12.64963],"type":"Point"}
}