{
  "type": "Feature",
  "properties": {
    "iso:country":"IN",
    "ks:ks_name":"Surja Pur",
    "ks:ks_pop":895,
    "ks:ks_type":"VILLAGE",
    "name:eng_x_preferred":[
        "Surja Pur"
    ],
    "wof:name":"Surja Pur",
    "wof:placetype":"locality",
    "wof:population":895
},
  "geometry": {"coordinates":[80.731346,26.551792],"type":"Point"}
}