{
  "type": "Feature",
  "properties": {
    "gn:admin1_code":"3.0",
    "gn:admin2_code":"311.0",
    "gn:asciiname":"Bhadra",
    "gn:country_code":"IN",
    "gn:dem":95,
    "gn:feature_class":"P",
    "gn:feature_code":"PPL",
    "gn:name":"Bhadr\u0101",
    "gn:population":0,
    "gn:timezone":"Asia/Kolkata",
    "iso:country":"IN",
    "wof:name":"Bhadra",
    "wof:placetype":"locality"
},
  "geometry": {"coordinates":[94.82846000000001,27.03733],"type":"Point"}
}