{
  "type": "Feature",
  "properties": {
    "gn:admin1_code":"36",
    "gn:admin2_code":"134.0",
    "gn:asciiname":"Paitia",
    "gn:country_code":"IN",
    "gn:dem":223,
    "gn:feature_class":"P",
    "gn:feature_code":"PPL",
    "gn:name":"Paitia",
    "gn:population":0,
    "gn:timezone":"Asia/Kolkata",
    "iso:country":"IN",
    "name:und_x_variant":[
        "Khw\u0101ja Ahmadpur"
    ],
    "wof:name":"Paitia",
    "wof:placetype":"neighbourhood"
},
  "geometry": {"coordinates":[78.51593,29.1255],"type":"Point"}
}