{
  "type": "Feature",
  "properties": {
    "iso:country":"IN",
    "ks:ks_name":"Konnakadu",
    "ks:ks_pop":945,
    "ks:ks_type":"HABITATION",
    "name:eng_x_preferred":[
        "Konnakadu"
    ],
    "wof:name":"Konnakadu",
    "wof:placetype":"locality",
    "wof:population":945
},
  "geometry": {"coordinates":[79.07248300000001,10.195202],"type":"Point"}
}