{
  "type": "Feature",
  "properties": {
    "iso:country":"IN",
    "ks:ks_name":"Abbannakudru",
    "ks:ks_pop":439,
    "ks:ks_type":"HABITATION",
    "name:eng_x_preferred":[
        "Abbannakudru"
    ],
    "wof:name":"Abbannakudru",
    "wof:placetype":"locality",
    "wof:population":439
},
  "geometry": {"coordinates":[74.75214099999999,13.377431],"type":"Point"}
}