{
  "type": "Feature",
  "properties": {
    "iso:country":"IN",
    "ks:ks_alt_nam":"5 MOD",
    "ks:ks_name":"5 Mod",
    "ks:ks_pop":26,
    "ks:ks_type":"HABITATION",
    "name:eng_x_preferred":[
        "5 Mod"
    ],
    "wof:name":"5 Mod",
    "wof:placetype":"locality",
    "wof:population":26
},
  "geometry": {"coordinates":[74.174261,29.582769],"type":"Point"}
}