{
  "type": "Feature",
  "properties": {
    "iso:country":"IN",
    "ks:ks_name":"Udaipur",
    "ks:ks_pop":374,
    "ks:ks_type":"VILLAGE",
    "name:eng_x_preferred":[
        "Udaipur"
    ],
    "wof:name":"Udaipur",
    "wof:placetype":"locality",
    "wof:population":374
},
  "geometry": {"coordinates":[85.21987900000001,23.968744],"type":"Point"}
}