{
  "type": "Feature",
  "properties": {
    "gn:admin1_code":"12",
    "gn:asciiname":"Mehnda",
    "gn:country_code":"IN",
    "gn:dem":3126,
    "gn:feature_class":"P",
    "gn:feature_code":"PPL",
    "gn:name":"Mehnda",
    "gn:population":0,
    "gn:timezone":"Asia/Kolkata",
    "iso:country":"IN",
    "wof:name":"Mehnda",
    "wof:placetype":"locality"
},
  "geometry": {"coordinates":[74.24786999999998,34.01531],"type":"Point"}
}