{
  "type": "Feature",
  "properties": {
    "iso:country":"IN",
    "ks:ks_name":"Shiv Lal Purwa",
    "ks:ks_pop":268,
    "ks:ks_type":"HABITATION",
    "name:eng_x_preferred":[
        "Shiv Lal Purwa"
    ],
    "wof:name":"Shiv Lal Purwa",
    "wof:placetype":"locality",
    "wof:population":268
},
  "geometry": {"coordinates":[81.79960800000001,27.178676],"type":"Point"}
}