{
  "type": "Feature",
  "properties": {
    "iso:country":"IN",
    "ks:ks_name":"Shhirwadi",
    "ks:ks_pop":209,
    "ks:ks_type":"HABITATION",
    "name:eng_x_preferred":[
        "Shhirwadi"
    ],
    "wof:name":"Shhirwadi",
    "wof:placetype":"locality",
    "wof:population":209
},
  "geometry": {"coordinates":[73.97456699999999,16.982962],"type":"Point"}
}