{
  "type": "Feature",
  "properties": {
    "iso:country":"IN",
    "ks:ks_name":"Lodhan Purwa",
    "ks:ks_pop":301,
    "ks:ks_type":"HABITATION",
    "ks:ks_uagg_main":0,
    "name:eng_x_preferred":[
        "Lodhan Purwa"
    ],
    "wof:name":"Lodhan Purwa",
    "wof:placetype":"neighbourhood",
    "wof:population":301
},
  "geometry": {"coordinates":[81.39986,27.890287],"type":"Point"}
}