{
  "type": "Feature",
  "properties": {
    "gn:admin1_code":"23",
    "gn:admin2_code":"39.0",
    "gn:asciiname":"Pandrawal",
    "gn:country_code":"IN",
    "gn:dem":241,
    "gn:feature_class":"P",
    "gn:feature_code":"PPL",
    "gn:name":"Pandraw\u0101l",
    "gn:population":0,
    "gn:timezone":"Asia/Kolkata",
    "iso:country":"IN",
    "ks:ks_alt_nam":"Pandraw\u0101l",
    "ks:ks_name":"Pandrawal",
    "ks:ks_pop":671,
    "ks:ks_type":"VILLAGE",
    "name:eng_x_preferred":[
        "Pandrawal"
    ],
    "name:eng_x_variant":[
        "Pandraw\u0101l"
    ],
    "name:por_x_preferred":[
        "Pandrawal"
    ],
    "wof:name":"Pandrawal",
    "wof:placetype":"locality",
    "wof:population":671
},
  "geometry": {"coordinates":[75.958071,31.024406],"type":"Point"}
}