{
  "type": "Feature",
  "properties": {
    "iso:country":"IN",
    "ks:ks_name":"Gudloor 1",
    "ks:ks_pop":79,
    "ks:ks_type":"HABITATION",
    "name:eng_x_preferred":[
        "Gudloor 1"
    ],
    "wof:name":"Gudloor 1",
    "wof:placetype":"locality",
    "wof:population":79
},
  "geometry": {"coordinates":[75.95138900000001,12.300833],"type":"Point"}
}