{
  "type": "Feature",
  "properties": {
    "iso:country":"IN",
    "ks:ks_name":"Panda",
    "ks:ks_pop":578,
    "ks:ks_type":"VILLAGE",
    "ks:ks_uagg_main":0,
    "name:eng_x_preferred":[
        "Panda"
    ],
    "wof:name":"Panda",
    "wof:placetype":"neighbourhood",
    "wof:population":578
},
  "geometry": {"coordinates":[80.23461399999999,29.604385],"type":"Point"}
}