{
  "type": "Feature",
  "properties": {
    "iso:country":"IN",
    "ks:ks_name":"Madho Math",
    "ks:ks_pop":710,
    "ks:ks_type":"VILLAGE",
    "name:eng_x_preferred":[
        "Madho Math"
    ],
    "wof:name":"Madho Math",
    "wof:placetype":"locality",
    "wof:population":710
},
  "geometry": {"coordinates":[84.257614,26.495853],"type":"Point"}
}