{
  "type": "Feature",
  "properties": {
    "iso:country":"IN",
    "ks:ks_alt_nam":"Thayil palam",
    "ks:ks_name":"Thayil Palam",
    "ks:ks_pop":287,
    "ks:ks_type":"HABITATION",
    "name:eng_x_preferred":[
        "Thayil Palam"
    ],
    "wof:name":"Thayil Palam",
    "wof:placetype":"locality",
    "wof:population":287
},
  "geometry": {"coordinates":[75.606004,11.671632],"type":"Point"}
}