{
  "type": "Feature",
  "properties": {
    "gn:admin1_code":"36",
    "gn:admin2_code":"176.0",
    "gn:asciiname":"Ashrafpur",
    "gn:country_code":"IN",
    "gn:dem":111,
    "gn:feature_class":"P",
    "gn:feature_code":"PPL",
    "gn:name":"Ashrafpur",
    "gn:population":0,
    "gn:timezone":"Asia/Kolkata",
    "iso:country":"IN",
    "ks:ks_name":"Ashrafpur",
    "ks:ks_type":"VILLAGE",
    "name:eng_x_preferred":[
        "Ashrafpur"
    ],
    "wof:name":"Ashrafpur",
    "wof:placetype":"locality"
},
  "geometry": {"coordinates":[81.429666,27.274425],"type":"Point"}
}