{
  "type": "Feature",
  "properties": {
    "iso:country":"IN",
    "ks:ks_name":"Maradi",
    "ks:ks_pop":57,
    "ks:ks_type":"HABITATION",
    "name:eng_x_preferred":[
        "Maradi"
    ],
    "wof:name":"Maradi",
    "wof:placetype":"locality",
    "wof:population":57
},
  "geometry": {"coordinates":[75.619719,13.303309],"type":"Point"}
}