{
  "type": "Feature",
  "properties": {
    "gn:admin1_code":"2",
    "gn:admin2_code":"544.0",
    "gn:asciiname":"Ginjangi",
    "gn:country_code":"IN",
    "gn:dem":849,
    "gn:feature_class":"P",
    "gn:feature_code":"PPL",
    "gn:name":"Ginjangi",
    "gn:population":0,
    "gn:timezone":"Asia/Kolkata",
    "iso:country":"IN",
    "ks:ks_name":"Ginjangi",
    "ks:ks_type":"VILLAGE",
    "name:eng_x_preferred":[
        "Ginjangi"
    ],
    "wof:name":"Ginjangi",
    "wof:placetype":"locality"
},
  "geometry": {"coordinates":[82.34502500000001,17.956321],"type":"Point"}
}