{
  "type": "Feature",
  "properties": {
    "iso:country":"IN",
    "ks:ks_name":"Keneli",
    "ks:ks_pop":279,
    "ks:ks_type":"HABITATION",
    "name:eng_x_preferred":[
        "Keneli"
    ],
    "wof:name":"Keneli",
    "wof:placetype":"locality",
    "wof:population":279
},
  "geometry": {"coordinates":[83.82307400000001,19.555329],"type":"Point"}
}