{
  "type": "Feature",
  "properties": {
    "gn:admin1_code":"36",
    "gn:admin2_code":"155.0",
    "gn:asciiname":"Pariyal",
    "gn:country_code":"IN",
    "gn:dem":147,
    "gn:feature_class":"P",
    "gn:feature_code":"PPL",
    "gn:name":"Par\u012byal",
    "gn:population":0,
    "gn:timezone":"Asia/Kolkata",
    "iso:country":"IN",
    "wof:name":"Pariyal",
    "wof:placetype":"locality"
},
  "geometry": {"coordinates":[79.89644,27.69388],"type":"Point"}
}