{
  "type": "Feature",
  "properties": {
    "iso:country":"IN",
    "ks:ks_name":"Pipra Khas",
    "ks:ks_pop":2049,
    "ks:ks_type":"HABITATION",
    "name:eng_x_preferred":[
        "Pipra Khas"
    ],
    "wof:name":"Pipra Khas",
    "wof:placetype":"locality",
    "wof:population":2049
},
  "geometry": {"coordinates":[83.697774,26.791785],"type":"Point"}
}