{
  "type": "Feature",
  "properties": {
    "iso:country":"IN",
    "ks:ks_name":"Ichadih",
    "ks:ks_pop":469,
    "ks:ks_type":"VILLAGE",
    "ks:ks_uagg_main":0,
    "name:eng_x_preferred":[
        "Ichadih"
    ],
    "wof:name":"Ichadih",
    "wof:placetype":"neighbourhood",
    "wof:population":469
},
  "geometry": {"coordinates":[86.417519,22.43811],"type":"Point"}
}