{
  "type": "Feature",
  "properties": {
    "gn:admin1_code":"36",
    "gn:admin2_code":"145.0",
    "gn:asciiname":"Nagla Hemraj",
    "gn:country_code":"IN",
    "gn:dem":185,
    "gn:feature_class":"P",
    "gn:feature_code":"PPL",
    "gn:name":"Nagla Hemr\u0101j",
    "gn:population":0,
    "gn:timezone":"Asia/Kolkata",
    "iso:country":"IN",
    "ks:ks_name":"Nagla Hemraj",
    "ks:ks_pop":288,
    "ks:ks_type":"HABITATION",
    "ks:ks_uagg_main":0,
    "name:eng_x_preferred":[
        "Nagla Hemraj"
    ],
    "wof:name":"Nagla Hemraj",
    "wof:placetype":"neighbourhood",
    "wof:population":288
},
  "geometry": {"coordinates":[77.56841300000001,27.567587],"type":"Point"}
}