{
  "type": "Feature",
  "properties": {
    "iso:country":"IN",
    "ks:ks_name":"Natham",
    "ks:ks_pop":288,
    "ks:ks_type":"HABITATION",
    "name:eng_x_preferred":[
        "Natham"
    ],
    "wof:name":"Natham",
    "wof:placetype":"locality",
    "wof:population":288
},
  "geometry": {"coordinates":[79.71056900000001,11.053113],"type":"Point"}
}