{
  "type": "Feature",
  "properties": {
    "gn:admin1_code":"21",
    "gn:admin2_code":"393.0",
    "gn:asciiname":"Luisinga",
    "gn:cc2":"IN",
    "gn:country_code":"IN",
    "gn:dem":155,
    "gn:feature_class":"P",
    "gn:feature_code":"PPL",
    "gn:name":"Luisinga",
    "gn:population":0,
    "gn:timezone":"Asia/Kolkata",
    "iso:country":"IN",
    "name:und_x_variant":[
        "Loisinga",
        "Loisingha",
        "Luisinga"
    ],
    "wof:name":"Luisinga",
    "wof:placetype":"locality"
},
  "geometry": {"coordinates":[83.51666999999998,20.86667000000001],"type":"Point"}
}