{
  "type": "Feature",
  "properties": {
    "gn:country":"IN",
    "gn:fcode":"PPL",
    "gn:pop":0,
    "iso:country":"IN",
    "qs:name":"Kammasandra",
    "qs:name_adm0":"India",
    "qs:name_adm1":"Karnataka",
    "qs:photos":17,
    "qs:photos_1k":3,
    "qs:photos_9k":1,
    "qs:photos_9r":1,
    "qs:photos_all":17,
    "qs:photos_sr":1,
    "qs:placetype":"Town",
    "qs:pop_sr":"0",
    "wof:name":"Kammasandra",
    "wof:placetype":"locality",
    "wof:population":0
},
  "geometry": {"coordinates":[78.19962,12.87664],"type":"Point"}
}