{
  "type": "Feature",
  "properties": {
    "iso:country":"IN",
    "ks:ks_name":"Nurupur-3",
    "ks:ks_pop":523,
    "ks:ks_type":"VILLAGE",
    "name:eng_x_preferred":[
        "Nurupur-3"
    ],
    "wof:name":"Nurupur-3",
    "wof:placetype":"locality",
    "wof:population":523
},
  "geometry": {"coordinates":[86.276557,20.719869],"type":"Point"}
}