{
  "type": "Feature",
  "properties": {
    "iso:country":"IN",
    "ks:ks_name":"Kairagora",
    "ks:ks_pop":201,
    "ks:ks_type":"VILLAGE",
    "name:eng_x_preferred":[
        "Kairagora"
    ],
    "wof:name":"Kairagora",
    "wof:placetype":"locality",
    "wof:population":201
},
  "geometry": {"coordinates":[87.50824900000001,24.953831],"type":"Point"}
}