{
  "type": "Feature",
  "properties": {
    "iso:country":"IN",
    "ks:ks_name":"Puranwala",
    "ks:ks_pop":135,
    "ks:ks_type":"VILLAGE",
    "name:eng_x_preferred":[
        "Puranwala"
    ],
    "wof:name":"Puranwala",
    "wof:placetype":"locality",
    "wof:population":135
},
  "geometry": {"coordinates":[72.494393,27.992697],"type":"Point"}
}