{
  "type": "Feature",
  "properties": {
    "iso:country":"IN",
    "ks:ks_name":"Kashiya Chak",
    "ks:ks_pop":184,
    "ks:ks_type":"VILLAGE",
    "ks:ks_uagg_main":0,
    "name:eng_x_preferred":[
        "Kashiya Chak"
    ],
    "wof:name":"Kashiya Chak",
    "wof:placetype":"neighbourhood",
    "wof:population":184
},
  "geometry": {"coordinates":[85.02643,24.586011],"type":"Point"}
}