{
  "type": "Feature",
  "properties": {
    "iso:country":"IN",
    "ks:ks_name":"Shahgupur Khas",
    "ks:ks_pop":779,
    "ks:ks_type":"HABITATION",
    "name:eng_x_preferred":[
        "Shahgupur Khas"
    ],
    "wof:name":"Shahgupur Khas",
    "wof:placetype":"locality",
    "wof:population":779
},
  "geometry": {"coordinates":[82.76727,26.269002],"type":"Point"}
}