{
  "type": "Feature",
  "properties": {
    "gn:admin1_code":"35.0",
    "gn:admin2_code":"423",
    "gn:asciiname":"Tapariyan",
    "gn:country_code":"IN",
    "gn:dem":342,
    "gn:feature_class":"P",
    "gn:feature_code":"PPL",
    "gn:name":"Tapariyan",
    "gn:population":0,
    "gn:timezone":"Asia/Kolkata",
    "iso:country":"IN",
    "wof:name":"Tapariyan",
    "wof:placetype":"locality"
},
  "geometry": {"coordinates":[78.24991,24.96621],"type":"Point"}
}