{
  "type": "Feature",
  "properties": {
    "iso:country":"IN",
    "ks:ks_name":"Periyakukkundi",
    "ks:ks_pop":865,
    "ks:ks_type":"HABITATION",
    "name:eng_x_preferred":[
        "Periyakukkundi"
    ],
    "wof:name":"Periyakukkundi",
    "wof:placetype":"locality",
    "wof:population":865
},
  "geometry": {"coordinates":[79.37647200000001,12.861165],"type":"Point"}
}