{
  "type": "Feature",
  "properties": {
    "gn:admin1_code":"36",
    "gn:admin2_code":"188.0",
    "gn:asciiname":"Marautia",
    "gn:country_code":"IN",
    "gn:dem":82,
    "gn:feature_class":"P",
    "gn:feature_code":"PPL",
    "gn:name":"Marautia",
    "gn:population":0,
    "gn:timezone":"Asia/Kolkata",
    "iso:country":"IN",
    "ks:ks_alt_nam":"Marw\u0101tia",
    "ks:ks_name":"Marwatia",
    "ks:ks_type":"VILLAGE",
    "ks:ks_uagg_main":0,
    "name:eng_x_preferred":[
        "Marwatia"
    ],
    "name:eng_x_variant":[
        "Marw\u0101tia"
    ],
    "wof:name":"Marwatia",
    "wof:placetype":"neighbourhood"
},
  "geometry": {"coordinates":[83.27179099999999,26.430528],"type":"Point"}
}