{
  "type": "Feature",
  "properties": {
    "iso:country":"IN",
    "ks:ks_alt_nam":"Karhum\u0101",
    "ks:ks_name":"Karhuma",
    "ks:ks_pop":792,
    "ks:ks_type":"VILLAGE",
    "name:eng_x_preferred":[
        "Karhuma"
    ],
    "name:eng_x_variant":[
        "Karhum\u0101"
    ],
    "wof:name":"Karhuma",
    "wof:placetype":"locality",
    "wof:population":792
},
  "geometry": {"coordinates":[84.56077500000001,23.764722],"type":"Point"}
}