{
  "type": "Feature",
  "properties": {
    "gn:admin1_code":"37.0",
    "gn:admin2_code":"408.0",
    "gn:asciiname":"Pendarwani",
    "gn:country_code":"IN",
    "gn:dem":321,
    "gn:feature_class":"P",
    "gn:feature_code":"PPL",
    "gn:name":"Pendarw\u0101ni",
    "gn:population":0,
    "gn:timezone":"Asia/Kolkata",
    "iso:country":"IN",
    "name:eng_x_preferred":[
        "Pendarw\u0101ni"
    ],
    "wof:name":"Pendarwani",
    "wof:placetype":"locality"
},
  "geometry": {"coordinates":[81.14872,21.69468],"type":"Point"}
}