{
  "type": "Feature",
  "properties": {
    "iso:country":"IN",
    "ks:ks_name":"Sanbadapasi",
    "ks:ks_pop":679,
    "ks:ks_type":"VILLAGE",
    "name:eng_x_preferred":[
        "Sanbadapasi"
    ],
    "wof:name":"Sanbadapasi",
    "wof:placetype":"locality",
    "wof:population":679
},
  "geometry": {"coordinates":[85.966735,21.82519],"type":"Point"}
}