{
  "type": "Feature",
  "properties": {
    "gn:admin1_code":"35",
    "gn:admin2_code":"428.0",
    "gn:asciiname":"Khitarpur",
    "gn:country_code":"IN",
    "gn:dem":353,
    "gn:feature_class":"P",
    "gn:feature_code":"PPL",
    "gn:name":"Khit\u0101rpur",
    "gn:population":0,
    "gn:timezone":"Asia/Kolkata",
    "iso:country":"IN",
    "ks:ks_alt_nam":"Khit\u0101rpur",
    "ks:ks_name":"Khitarpur",
    "ks:ks_type":"VILLAGE",
    "name:eng_x_preferred":[
        "Khitarpur"
    ],
    "name:eng_x_variant":[
        "Khit\u0101rpur"
    ],
    "wof:name":"Khitarpur",
    "wof:placetype":"locality"
},
  "geometry": {"coordinates":[79.428078,24.024469],"type":"Point"}
}