{
  "type": "Feature",
  "properties": {
    "gn:admin1_code":"36.0",
    "gn:admin2_code":"148.0",
    "gn:asciiname":"Khuria",
    "gn:country_code":"IN",
    "gn:dem":163,
    "gn:feature_class":"P",
    "gn:feature_code":"PPL",
    "gn:name":"Khuria",
    "gn:population":0,
    "gn:timezone":"Asia/Kolkata",
    "iso:country":"IN",
    "ks:ks_name":"Khuria",
    "ks:ks_type":"VILLAGE",
    "name:eng_x_preferred":[
        "Khuria"
    ],
    "name:und_x_variant":[
        "Khori\u0101"
    ],
    "wof:name":"Khuria",
    "wof:placetype":"locality"
},
  "geometry": {"coordinates":[78.933449,27.301373],"type":"Point"}
}