{
  "type": "Feature",
  "properties": {
    "gn:admin1_code":"36.0",
    "gn:admin2_code":"148.0",
    "gn:asciiname":"Khuria",
    "gn:country_code":"IN",
    "gn:dem":163,
    "gn:feature_class":"P",
    "gn:feature_code":"PPL",
    "gn:name":"Khuria",
    "gn:population":0,
    "gn:timezone":"Asia/Kolkata",
    "iso:country":"IN",
    "name:und_x_variant":[
        "Khori\u0101"
    ],
    "wof:name":"Khuria",
    "wof:placetype":"locality"
},
  "geometry": {"coordinates":[78.93344999999999,27.30137],"type":"Point"}
}