{
  "type": "Feature",
  "properties": {
    "iso:country":"IN",
    "ks:ks_name":"Balapara",
    "ks:ks_pop":398,
    "ks:ks_type":"VILLAGE",
    "name:eng_x_preferred":[
        "Balapara"
    ],
    "wof:name":"Balapara",
    "wof:placetype":"locality",
    "wof:population":398
},
  "geometry": {"coordinates":[91.08426300000001,26.249193],"type":"Point"}
}