{
  "type": "Feature",
  "properties": {
    "iso:country":"IN",
    "ks:ks_alt_nam":"Suryanaik tanda",
    "ks:ks_name":"Suryanaik Tanda",
    "ks:ks_pop":63,
    "ks:ks_type":"HABITATION",
    "name:eng_x_preferred":[
        "Suryanaik Tanda"
    ],
    "wof:name":"Suryanaik Tanda",
    "wof:placetype":"locality",
    "wof:population":63
},
  "geometry": {"coordinates":[77.816945,17.020969],"type":"Point"}
}