{
  "type": "Feature",
  "properties": {
    "iso:country":"IN",
    "ks:ks_name":"Koravakuzhi",
    "ks:ks_pop":133,
    "ks:ks_type":"HABITATION",
    "name:eng_x_preferred":[
        "Koravakuzhi"
    ],
    "wof:name":"Koravakuzhi",
    "wof:placetype":"locality",
    "wof:population":133
},
  "geometry": {"coordinates":[77.315213,8.426347],"type":"Point"}
}