{
  "type": "Feature",
  "properties": {
    "gn:admin1_code":"37",
    "gn:admin2_code":"408.0",
    "gn:asciiname":"Panehur",
    "gn:country_code":"IN",
    "gn:dem":399,
    "gn:feature_class":"P",
    "gn:feature_code":"PPL",
    "gn:name":"Paneh\u016br",
    "gn:population":0,
    "gn:timezone":"Asia/Kolkata",
    "iso:country":"IN",
    "ks:ks_name":"Panahur",
    "ks:ks_pop":110,
    "ks:ks_type":"VILLAGE",
    "name:eng_x_preferred":[
        "Panahur"
    ],
    "name:eng_x_variant":[
        "Panehur"
    ],
    "wof:name":"Panahur",
    "wof:placetype":"locality",
    "wof:population":110
},
  "geometry": {"coordinates":[80.65208800000001,20.244735],"type":"Point"}
}