{
  "type": "Feature",
  "properties": {
    "gn:admin1_code":"37",
    "gn:admin2_code":"408.0",
    "gn:asciiname":"Panehur",
    "gn:country_code":"IN",
    "gn:dem":399,
    "gn:feature_class":"P",
    "gn:feature_code":"PPL",
    "gn:name":"Paneh\u016br",
    "gn:population":0,
    "gn:timezone":"Asia/Kolkata",
    "iso:country":"IN",
    "wof:name":"Panehur",
    "wof:placetype":"locality"
},
  "geometry": {"coordinates":[80.65225,20.24482],"type":"Point"}
}