{
  "type": "Feature",
  "properties": {
    "iso:country":"IN",
    "ks:ks_name":"Dandwa (bhairos Pura)",
    "ks:ks_pop":167,
    "ks:ks_type":"HABITATION",
    "ks:ks_uagg_main":0,
    "name:eng_x_preferred":[
        "Dandwa (bhairos Pura)"
    ],
    "wof:name":"Dandwa (bhairos Pura)",
    "wof:placetype":"neighbourhood",
    "wof:population":167
},
  "geometry": {"coordinates":[82.867439,26.266495],"type":"Point"}
}