{
  "type": "Feature",
  "properties": {
    "gn:admin1_code":"35",
    "gn:admin2_code":"435.0",
    "gn:asciiname":"Manasa",
    "gn:country_code":"IN",
    "gn:dem":435,
    "gn:feature_class":"P",
    "gn:feature_code":"PPL",
    "gn:name":"Man\u0101sa",
    "gn:population":0,
    "gn:timezone":"Asia/Kolkata",
    "iso:country":"IN",
    "name:asm_x_preferred":[
        "\u09ae\u09a8\u09b8\u09be"
    ],
    "name:ben_x_preferred":[
        "\u09ae\u09a8\u09b8\u09be"
    ],
    "name:deu_x_preferred":[
        "Manasa"
    ],
    "name:fra_x_preferred":[
        "Manasa"
    ],
    "name:hin_x_preferred":[
        "\u092e\u0928\u0938\u093e \u0926\u0947\u0935\u0940"
    ],
    "name:jpn_x_preferred":[
        "\u30de\u30ca\u30b5\u30fc"
    ],
    "name:kan_x_preferred":[
        "\u0cae\u0cbe\u0ca8\u0cb8 \u0ca6\u0cc7\u0cb5\u0cbf"
    ],
    "name:mai_x_preferred":[
        "\u092e\u0928\u0938\u093e \u0926\u0947\u0935\u0940"
    ],
    "name:new_x_preferred":[
        "\u092e\u0928\u0938\u093e"
    ],
    "name:nld_x_preferred":[
        "Manasa"
    ],
    "name:pan_x_preferred":[
        "\u0a2e\u0a28\u0a38\u0a3e"
    ],
    "name:pol_x_preferred":[
        "Manasa"
    ],
    "name:rus_x_preferred":[
        "\u041c\u0430\u043d\u0430\u0441\u0430"
    ],
    "name:slv_x_preferred":[
        "Manasa"
    ],
    "name:spa_x_preferred":[
        "Manas\u00e1"
    ],
    "name:tam_x_preferred":[
        "\u0bae\u0bbe\u0ba9\u0b9a\u0bbe \u0ba4\u0bc7\u0bb5\u0bbf"
    ],
    "name:tha_x_preferred":[
        "\u0e1e\u0e23\u0e30\u0e41\u0e21\u0e48\u0e21\u0e19\u0e2a\u0e32\u0e40\u0e17\u0e27\u0e35"
    ],
    "name:vie_x_preferred":[
        "Manasa"
    ],
    "name:zho_x_preferred":[
        "\u6469\u7eb3\u5a11"
    ],
    "wof:name":"Manasa",
    "wof:placetype":"locality"
},
  "geometry": {"coordinates":[76.15645000000001,23.55649],"type":"Point"}
}