{
  "type": "Feature",
  "properties": {
    "iso:country":"IN",
    "ks:ks_name":"Khamaria J. Gunha",
    "ks:ks_pop":67,
    "ks:ks_type":"HABITATION",
    "name:eng_x_preferred":[
        "Khamaria J. Gunha"
    ],
    "wof:name":"Khamaria J. Gunha",
    "wof:placetype":"locality",
    "wof:population":67
},
  "geometry": {"coordinates":[80.09819,28.199757],"type":"Point"}
}