{
  "type": "Feature",
  "properties": {
    "iso:country":"IN",
    "ks:ks_name":"Dubedih",
    "ks:ks_pop":1080,
    "ks:ks_type":"HABITATION",
    "name:eng_x_preferred":[
        "Dubedih"
    ],
    "wof:name":"Dubedih",
    "wof:placetype":"locality",
    "wof:population":1080
},
  "geometry": {"coordinates":[86.259951,24.753014],"type":"Point"}
}