{
  "type": "Feature",
  "properties": {
    "iso:country":"IN",
    "ks:ks_name":"Nimapalli",
    "ks:ks_pop":35,
    "ks:ks_type":"VILLAGE",
    "name:eng_x_preferred":[
        "Nimapalli"
    ],
    "wof:name":"Nimapalli",
    "wof:placetype":"locality",
    "wof:population":35
},
  "geometry": {"coordinates":[84.56429799999999,19.727211],"type":"Point"}
}