{
  "type": "Feature",
  "properties": {
    "gn:admin1_code":"2.0",
    "gn:admin2_code":"552.0",
    "gn:asciiname":"Madarisupalle",
    "gn:country_code":"IN",
    "gn:dem":245,
    "gn:feature_class":"P",
    "gn:feature_code":"PPL",
    "gn:name":"Madarisupalle",
    "gn:population":0,
    "gn:timezone":"Asia/Kolkata",
    "iso:country":"IN",
    "ks:ks_name":"Madasupalle",
    "ks:ks_pop":264,
    "ks:ks_type":"HABITATION",
    "name:eng_x_preferred":[
        "Madasupalle"
    ],
    "name:eng_x_variant":[
        "Madarisupalle"
    ],
    "wof:name":"Madasupalle",
    "wof:placetype":"locality",
    "wof:population":264
},
  "geometry": {"coordinates":[78.172,15.326827],"type":"Point"}
}