{
  "type": "Feature",
  "properties": {
    "iso:country":"IN",
    "ks:ks_name":"6 STB-C",
    "ks:ks_pop":148,
    "ks:ks_type":"VILLAGE",
    "name:eng_x_preferred":[
        "6 STB-C"
    ],
    "wof:name":"6 STB-C",
    "wof:placetype":"locality",
    "wof:population":148
},
  "geometry": {"coordinates":[73.429716,29.348095],"type":"Point"}
}