{
  "type": "Feature",
  "properties": {
    "gn:admin1_code":"2.0",
    "gn:asciiname":"Poleshiammankulam",
    "gn:country_code":"IN",
    "gn:dem":7,
    "gn:feature_class":"P",
    "gn:feature_code":"PPL",
    "gn:name":"Poleshiammankulam",
    "gn:population":0,
    "gn:timezone":"Asia/Kolkata",
    "iso:country":"IN",
    "wof:name":"Poleshiammankulam",
    "wof:placetype":"neighbourhood"
},
  "geometry": {"coordinates":[80.28351000000001,13.40531],"type":"Point"}
}