{
  "type": "Feature",
  "properties": {
    "gn:admin1_code":"40.0",
    "gn:admin2_code":"541.0",
    "gn:asciiname":"Bandalagudem",
    "gn:country_code":"IN",
    "gn:dem":47,
    "gn:feature_class":"P",
    "gn:feature_code":"PPL",
    "gn:name":"Bandalag\u016bdem",
    "gn:population":0,
    "gn:timezone":"Asia/Kolkata",
    "iso:country":"IN",
    "ks:ks_name":"Bandarigudem",
    "ks:ks_pop":35,
    "ks:ks_type":"HABITATION",
    "name:eng_x_preferred":[
        "Bandarigudem"
    ],
    "name:eng_x_variant":[
        "Bandalagudem"
    ],
    "wof:name":"Bandarigudem",
    "wof:placetype":"locality",
    "wof:population":35
},
  "geometry": {"coordinates":[81.40024,17.732987],"type":"Point"}
}