{
  "type": "Feature",
  "properties": {
    "gn:admin1_code":"2.0",
    "gn:admin2_code":"549.0",
    "gn:asciiname":"Burepalle",
    "gn:country_code":"IN",
    "gn:dem":31,
    "gn:feature_class":"P",
    "gn:feature_code":"PPL",
    "gn:name":"Burepalle",
    "gn:population":0,
    "gn:timezone":"Asia/Kolkata",
    "iso:country":"IN",
    "ks:ks_name":"Burepalli",
    "ks:ks_pop":388,
    "ks:ks_type":"HABITATION",
    "name:eng_x_preferred":[
        "Burepalli"
    ],
    "name:eng_x_variant":[
        "Burepalle"
    ],
    "wof:name":"Burepalli",
    "wof:placetype":"locality",
    "wof:population":388
},
  "geometry": {"coordinates":[79.986126,15.684336],"type":"Point"}
}