{
  "type": "Feature",
  "properties": {
    "iso:country":"IN",
    "ks:ks_name":"Gorakhpara",
    "ks:ks_pop":380,
    "ks:ks_type":"HABITATION",
    "name:eng_x_preferred":[
        "Gorakhpara"
    ],
    "wof:name":"Gorakhpara",
    "wof:placetype":"locality",
    "wof:population":380
},
  "geometry": {"coordinates":[70.709778,21.325111],"type":"Point"}
}