{
  "type": "Feature",
  "properties": {
    "iso:country":"IN",
    "ks:ks_name":"Syam Chak",
    "ks:ks_pop":0,
    "ks:ks_type":"VILLAGE",
    "name:eng_x_preferred":[
        "Syam Chak"
    ],
    "wof:name":"Syam Chak",
    "wof:placetype":"locality",
    "wof:population":0
},
  "geometry": {"coordinates":[87.403797,22.229218],"type":"Point"}
}