{
  "type": "Feature",
  "properties": {
    "iso:country":"IN",
    "ks:ks_name":"Jamusara",
    "ks:ks_pop":277,
    "ks:ks_type":"VILLAGE",
    "name:eng_x_preferred":[
        "Jamusara"
    ],
    "wof:name":"Jamusara",
    "wof:placetype":"locality",
    "wof:population":277
},
  "geometry": {"coordinates":[85.722785,20.773488],"type":"Point"}
}