{
  "type": "Feature",
  "properties": {
    "gn:admin1_code":"39.0",
    "gn:admin2_code":"063",
    "gn:asciiname":"Kapkot",
    "gn:country_code":"IN",
    "gn:dem":1075,
    "gn:feature_class":"P",
    "gn:feature_code":"PPL",
    "gn:name":"Kapkot",
    "gn:population":0,
    "gn:timezone":"Asia/Kolkata",
    "iso:country":"IN",
    "name:und_x_variant":[
        "Kapkote",
        "Kapkot"
    ],
    "wof:name":"Kapkot",
    "wof:placetype":"locality"
},
  "geometry": {"coordinates":[79.90016999999997,29.94949],"type":"Point"}
}