{
  "type": "Feature",
  "properties": {
    "gn:admin1_code":"19.0",
    "gn:admin2_code":"582.0",
    "gn:asciiname":"Badaguvarahalli",
    "gn:country_code":"IN",
    "gn:dem":867,
    "gn:feature_class":"P",
    "gn:feature_code":"PPL",
    "gn:name":"Badaguv\u0101rahalli",
    "gn:population":0,
    "gn:timezone":"Asia/Kolkata",
    "iso:country":"IN",
    "wof:name":"Badaguvarahalli",
    "wof:placetype":"locality"
},
  "geometry": {"coordinates":[78.07324,13.42226],"type":"Point"}
}