{
  "type": "Feature",
  "properties": {
    "iso:country":"IN",
    "name:ben_x_preferred":[
        "\u099c\u09cb\u09a1\u09bc\u09be\u09b8\u09be\u0981\u0995\u09cb"
    ],
    "name:eng_x_preferred":[
        "Jorasanko"
    ],
    "name:fra_x_preferred":[
        "Jorasanko"
    ],
    "name:hin_x_preferred":[
        "\u091c\u094b\u0930\u093e\u0938\u093e\u0902\u0915\u094b"
    ],
    "qs:name":"Jorasanko",
    "qs:name_adm0":"India",
    "qs:name_adm1":"West Bengal",
    "qs:photos":23,
    "qs:photos_1k":5,
    "qs:photos_9k":1,
    "qs:photos_9r":1,
    "qs:photos_all":23,
    "qs:photos_sr":1,
    "qs:placetype":"Suburb",
    "qs:pop_sr":"0",
    "wd:wordcount":901,
    "wof:name":"Jorasanko",
    "wof:placetype":"neighbourhood"
},
  "geometry": {"coordinates":[88.35642199999999,22.583209],"type":"Point"}
}