{
  "type": "Feature",
  "properties": {
    "iso:country":"IN",
    "qs:name":"Jorasanko",
    "qs:name_adm0":"India",
    "qs:name_adm1":"West Bengal",
    "qs:photos":23,
    "qs:photos_1k":5,
    "qs:photos_9k":1,
    "qs:photos_9r":1,
    "qs:photos_all":23,
    "qs:photos_sr":1,
    "qs:placetype":"Suburb",
    "qs:pop_sr":"0",
    "wd:wordcount":901,
    "wof:name":"Jorasanko",
    "wof:placetype":"neighbourhood"
},
  "geometry": {"coordinates":[88.35642199999999,22.583209],"type":"Point"}
}