{
  "type": "Feature",
  "properties": {
    "iso:country":"IN",
    "ks:ks_name":"Phulwapati",
    "ks:ks_pop":632,
    "ks:ks_type":"VILLAGE",
    "ks:ks_uagg_main":0,
    "name:eng_x_preferred":[
        "Phulwapati"
    ],
    "wof:name":"Phulwapati",
    "wof:placetype":"neighbourhood",
    "wof:population":632
},
  "geometry": {"coordinates":[83.97736999999999,26.682709],"type":"Point"}
}