{
  "type": "Feature",
  "properties": {
    "iso:country":"IN",
    "ks:ks_name":"Bankat",
    "ks:ks_pop":264,
    "ks:ks_type":"VILLAGE",
    "name:eng_x_preferred":[
        "Bankat"
    ],
    "wof:name":"Bankat",
    "wof:placetype":"locality",
    "wof:population":264
},
  "geometry": {"coordinates":[85.046618,24.595657],"type":"Point"}
}