{
  "type": "Feature",
  "properties": {
    "iso:country":"IN",
    "ks:ks_name":"Kharahwatanr",
    "ks:ks_pop":0,
    "ks:ks_type":"VILLAGE",
    "name:eng_x_preferred":[
        "Kharahwatanr"
    ],
    "wof:name":"Kharahwatanr",
    "wof:placetype":"locality",
    "wof:population":0
},
  "geometry": {"coordinates":[85.52883,24.553106],"type":"Point"}
}