{
  "type": "Feature",
  "properties": {
    "gn:admin1_code":"34.0",
    "gn:admin2_code":"236.0",
    "gn:asciiname":"Khawaspur",
    "gn:country_code":"IN",
    "gn:dem":110,
    "gn:feature_class":"P",
    "gn:feature_code":"PPL",
    "gn:name":"Khaw\u0101spur",
    "gn:population":0,
    "gn:timezone":"Asia/Kolkata",
    "iso:country":"IN",
    "name:urd_x_preferred":[
        "\u062e\u0648\u0627\u0635 \u067e\u0648\u0631"
    ],
    "wof:name":"Khawaspur",
    "wof:placetype":"locality"
},
  "geometry": {"coordinates":[84.72537,24.8455],"type":"Point"}
}