{
  "type": "Feature",
  "properties": {
    "gn:admin1_code":"34.0",
    "gn:admin2_code":"223.0",
    "gn:asciiname":"Ahuna Siswa",
    "gn:country_code":"IN",
    "gn:dem":43,
    "gn:feature_class":"P",
    "gn:feature_code":"PPL",
    "gn:name":"Ahuna Siswa",
    "gn:population":0,
    "gn:timezone":"Asia/Kolkata",
    "iso:country":"IN",
    "ks:ks_name":"Ahunasiswa",
    "ks:ks_pop":732,
    "ks:ks_type":"VILLAGE",
    "name:eng_x_preferred":[
        "Ahunasiswa"
    ],
    "name:eng_x_variant":[
        "Ahuna Siswa"
    ],
    "wof:name":"Ahunasiswa",
    "wof:placetype":"locality",
    "wof:population":732
},
  "geometry": {"coordinates":[86.3926,25.561681],"type":"Point"}
}