{
  "type": "Feature",
  "properties": {
    "gn:admin1_code":"23.0",
    "gn:admin2_code":"53.0",
    "gn:asciiname":"Ratangarh",
    "gn:country_code":"IN",
    "gn:dem":224,
    "gn:feature_class":"P",
    "gn:feature_code":"PPL",
    "gn:name":"Ratangarh",
    "gn:population":0,
    "gn:timezone":"Asia/Kolkata",
    "iso:country":"IN",
    "name:ben_x_preferred":[
        "\u09b0\u09a4\u09a8\u0997\u09a1\u09bc"
    ],
    "name:bpy_x_preferred":[
        "\u09b0\u09a4\u09a8\u0997\u09a1\u09bc"
    ],
    "name:ceb_x_preferred":[
        "Ratangarh"
    ],
    "name:deu_x_preferred":[
        "Ratangarh"
    ],
    "name:por_x_preferred":[
        "Ratangarh"
    ],
    "name:swe_x_preferred":[
        "Ratangarh"
    ],
    "name:und_x_variant":[
        "Pat\u0101nw\u0101li"
    ],
    "wof:name":"Ratangarh",
    "wof:placetype":"locality"
},
  "geometry": {"coordinates":[75.69333,30.03707],"type":"Point"}
}