{
  "type": "Feature",
  "properties": {
    "iso:country":"IN",
    "ks:ks_name":"Badhulipur",
    "ks:ks_pop":331,
    "ks:ks_type":"VILLAGE",
    "name:eng_x_preferred":[
        "Badhulipur"
    ],
    "wof:name":"Badhulipur",
    "wof:placetype":"locality",
    "wof:population":331
},
  "geometry": {"coordinates":[84.878478,20.067623],"type":"Point"}
}