{
  "type": "Feature",
  "properties": {
    "gn:admin1_code":"38.0",
    "gn:admin2_code":"351.0",
    "gn:asciiname":"Mangra",
    "gn:country_code":"IN",
    "gn:dem":81,
    "gn:feature_class":"P",
    "gn:feature_code":"PPL",
    "gn:name":"Mangra",
    "gn:population":0,
    "gn:timezone":"Asia/Kolkata",
    "iso:country":"IN",
    "ks:ks_name":"Mangra",
    "ks:ks_pop":1123,
    "ks:ks_type":"VILLAGE",
    "name:eng_x_preferred":[
        "Mangra"
    ],
    "name:msa_x_preferred":[
        "Mangra"
    ],
    "name:zho_x_preferred":[
        "\u832b\u62c9\u4e61"
    ],
    "wof:name":"Mangra",
    "wof:placetype":"locality",
    "wof:population":1123
},
  "geometry": {"coordinates":[87.47080800000001,25.047702],"type":"Point"}
}