{
  "type": "Feature",
  "properties": {
    "iso:country":"IN",
    "ks:ks_name":"Adasingi",
    "ks:ks_pop":330,
    "ks:ks_type":"VILLAGE",
    "name:eng_x_preferred":[
        "Adasingi"
    ],
    "wof:name":"Adasingi",
    "wof:placetype":"locality",
    "wof:population":330
},
  "geometry": {"coordinates":[84.20724199999999,18.865968],"type":"Point"}
}