{
  "type": "Feature",
  "properties": {
    "iso:country":"IN",
    "ks:ks_name":"Thekkinkanam",
    "ks:ks_pop":598,
    "ks:ks_type":"HABITATION",
    "name:eng_x_preferred":[
        "Thekkinkanam"
    ],
    "wof:name":"Thekkinkanam",
    "wof:placetype":"locality",
    "wof:population":598
},
  "geometry": {"coordinates":[77.06428099999999,9.986355],"type":"Point"}
}