{
  "type": "Feature",
  "properties": {
    "iso:country":"IN",
    "ks:ks_name":"Baghmari",
    "ks:ks_pop":56,
    "ks:ks_type":"HABITATION",
    "name:eng_x_preferred":[
        "Baghmari"
    ],
    "wof:name":"Baghmari",
    "wof:placetype":"locality",
    "wof:population":56
},
  "geometry": {"coordinates":[86.156294,24.049364],"type":"Point"}
}