{
  "type": "Feature",
  "properties": {
    "iso:country":"IN",
    "ks:ks_name":"Pripeketa",
    "ks:ks_pop":13,
    "ks:ks_type":"VILLAGE",
    "name:eng_x_preferred":[
        "Pripeketa"
    ],
    "wof:name":"Pripeketa",
    "wof:placetype":"locality",
    "wof:population":13
},
  "geometry": {"coordinates":[84.014785,20.201436],"type":"Point"}
}