{
  "type": "Feature",
  "properties": {
    "iso:country":"IN",
    "ks:ks_name":"Arjunaposi",
    "ks:ks_pop":244,
    "ks:ks_type":"HABITATION",
    "name:eng_x_preferred":[
        "Arjunaposi"
    ],
    "wof:name":"Arjunaposi",
    "wof:placetype":"locality",
    "wof:population":244
},
  "geometry": {"coordinates":[85.85217799999999,21.788594],"type":"Point"}
}