{
  "type": "Feature",
  "properties": {
    "gn:country":"IN",
    "gn:fcode":"PPL",
    "gn:population":13343,
    "iso:country":"IN",
    "name:ben_x_preferred":[
        "\u09ae\u09be\u09b2\u0995\u09be\u09aa\u09c1\u09b0"
    ],
    "name:eng_x_preferred":[
        "Malkapur"
    ],
    "name:fra_x_preferred":[
        "Malkapur"
    ],
    "name:ita_x_preferred":[
        "Malkapur"
    ],
    "name:msa_x_preferred":[
        "Malkapur"
    ],
    "name:nld_x_preferred":[
        "Malkapur"
    ],
    "name:und_x_variant":[
        "Malk\u0101pur"
    ],
    "name:urd_x_preferred":[
        "\u0645\u0644\u06a9\u0627\u067e\u0648\u0631\u060c \u06a9\u0648\u0644\u06c1\u0627\u067e\u0648\u0631"
    ],
    "name:urd_x_variant":[
        "\u0645\u0644\u06a9\u0627\u067e\u0648\u0631"
    ],
    "qs:name":"Malkapur",
    "qs:name_adm0":"India",
    "qs:name_adm1":"Maharashtra",
    "qs:photos_9k":1,
    "qs:photos_9r":1,
    "qs:photos_all":1,
    "qs:photos_sr":0,
    "qs:placetype":"Town",
    "qs:pop_sr":"6",
    "wd:wordcount":29,
    "wof:name":"Malkapur",
    "wof:placetype":"locality",
    "wof:population":13343
},
  "geometry": {"coordinates":[73.93470000000001,16.91999],"type":"Point"}
}