{
  "type": "Feature",
  "properties": {
    "gn:admin1_code":"16",
    "gn:admin2_code":"530.0",
    "gn:asciiname":"Malkapur",
    "gn:country":"IN",
    "gn:country_code":"IN",
    "gn:dem":576,
    "gn:fcode":"PPL",
    "gn:feature_class":"P",
    "gn:feature_code":"PPL",
    "gn:name":"Malk\u0101pur",
    "gn:population":13343,
    "gn:timezone":"Asia/Kolkata",
    "iso:country":"IN",
    "ks:ks_alt_nam":"Malk\u0101pur",
    "ks:ks_name":"Malkapur",
    "ks:ks_pop":5504,
    "ks:ks_type":"VILLAGE",
    "name:ben_x_preferred":[
        "\u09ae\u09be\u09b2\u0995\u09be\u09aa\u09c1\u09b0"
    ],
    "name:bpy_x_preferred":[
        "\u09ae\u09be\u09b2\u0995\u09be\u09aa\u09c1\u09b0"
    ],
    "name:ceb_x_preferred":[
        "Malk\u0101pur"
    ],
    "name:eng_x_preferred":[
        "Malkapur"
    ],
    "name:eng_x_variant":[
        "Malk\u0101pur"
    ],
    "name:fra_x_preferred":[
        "Malkapur"
    ],
    "name:hin_x_preferred":[
        "\u092e\u0932\u094d\u0915\u093e\u092a\u0941\u0930"
    ],
    "name:hin_x_variant":[
        "\u092e\u0932\u0915\u093e\u092a\u0941\u0930"
    ],
    "name:ita_x_preferred":[
        "Malkapur"
    ],
    "name:mar_x_preferred":[
        "\u092e\u0932\u0915\u093e\u092a\u0942\u0930"
    ],
    "name:msa_x_preferred":[
        "Malkapur"
    ],
    "name:nld_x_preferred":[
        "Malkapur"
    ],
    "name:spa_x_preferred":[
        "Malkapur"
    ],
    "name:swe_x_preferred":[
        "Malk\u0101pur"
    ],
    "name:und_x_variant":[
        "Malk\u0101pur"
    ],
    "name:urd_x_preferred":[
        "\u0645\u0644\u06a9\u0627\u067e\u0648\u0631\u060c \u06a9\u0648\u0644\u06c1\u0627\u067e\u0648\u0631"
    ],
    "name:urd_x_variant":[
        "\u0645\u0644\u06a9\u0627\u067e\u0648\u0631"
    ],
    "qs:name":"Malkapur",
    "qs:name_adm0":"India",
    "qs:name_adm1":"Maharashtra",
    "qs:photos_9k":1,
    "qs:photos_9r":1,
    "qs:photos_all":1,
    "qs:photos_sr":0,
    "qs:placetype":"Town",
    "qs:pop_sr":"6",
    "wd:wordcount":29,
    "wof:name":"Malkapur",
    "wof:placetype":"locality",
    "wof:population":13343
},
  "geometry": {"coordinates":[73.93470000000001,16.91999],"type":"Point"}
}