{
  "type": "Feature",
  "properties": {
    "iso:country":"IN",
    "ks:ks_name":"Tendui",
    "ks:ks_type":"VILLAGE",
    "name:eng_x_preferred":[
        "Tendui"
    ],
    "wof:name":"Tendui",
    "wof:placetype":"locality"
},
  "geometry": {"coordinates":[83.286674,25.152662],"type":"Point"}
}