{
  "type": "Feature",
  "properties": {
    "iso:country":"IN",
    "ks:ks_alt_nam":"KEBAT TOLA",
    "ks:ks_name":"Kebat Tola",
    "ks:ks_pop":428,
    "ks:ks_type":"HABITATION",
    "ks:ks_uagg_main":0,
    "name:eng_x_preferred":[
        "Kebat Tola"
    ],
    "wof:name":"Kebat Tola",
    "wof:placetype":"neighbourhood",
    "wof:population":428
},
  "geometry": {"coordinates":[86.60215599999999,26.305301],"type":"Point"}
}