{
  "type": "Feature",
  "properties": {
    "iso:country":"IN",
    "ks:ks_name":"Simkuna Faras Upper Faras Devithan",
    "ks:ks_pop":806,
    "ks:ks_type":"HABITATION",
    "name:eng_x_preferred":[
        "Simkuna Faras Upper Faras Devithan"
    ],
    "wof:name":"Simkuna Faras Upper Faras Devithan",
    "wof:placetype":"locality",
    "wof:population":806
},
  "geometry": {"coordinates":[88.250184,26.929207],"type":"Point"}
}