{
  "type": "Feature",
  "properties": {
    "iso:country":"IN",
    "ks:ks_alt_nam":"HB",
    "ks:ks_name":"Hb",
    "ks:ks_pop":282,
    "ks:ks_type":"HABITATION",
    "ks:ks_uagg_main":0,
    "name:eng_x_preferred":[
        "Hb"
    ],
    "wof:name":"Hb",
    "wof:placetype":"neighbourhood",
    "wof:population":282
},
  "geometry": {"coordinates":[82.817263,25.830917],"type":"Point"}
}