{
  "type": "Feature",
  "properties": {
    "iso:country":"IN",
    "ks:ks_alt_nam":"D\u0101rid\u0101g",
    "ks:ks_name":"Daridag",
    "ks:ks_pop":400,
    "ks:ks_type":"VILLAGE",
    "name:eng_x_preferred":[
        "Daridag"
    ],
    "name:eng_x_variant":[
        "D\u0101rid\u0101g"
    ],
    "wof:name":"Daridag",
    "wof:placetype":"locality",
    "wof:population":400
},
  "geometry": {"coordinates":[85.794217,23.826676],"type":"Point"}
}