{
  "type": "Feature",
  "properties": {
    "iso:country":"IN",
    "ks:ks_name":"Arangabad",
    "ks:ks_pop":2526,
    "ks:ks_type":"VILLAGE",
    "name:eng_x_preferred":[
        "Arangabad"
    ],
    "wof:name":"Arangabad",
    "wof:placetype":"locality",
    "wof:population":2526
},
  "geometry": {"coordinates":[86.204594,20.72335],"type":"Point"}
}