{
  "type": "Feature",
  "properties": {
    "gn:admin1_code":"2.0",
    "gn:admin2_code":"553.0",
    "gn:asciiname":"Budiligaddapalle",
    "gn:country_code":"IN",
    "gn:dem":647,
    "gn:feature_class":"P",
    "gn:feature_code":"PPL",
    "gn:name":"B\u016bdiligaddapalle",
    "gn:population":0,
    "gn:timezone":"Asia/Kolkata",
    "iso:country":"IN",
    "wof:name":"Budiligaddapalle",
    "wof:placetype":"locality"
},
  "geometry": {"coordinates":[77.74547,13.95987],"type":"Point"}
}