{
  "type": "Feature",
  "properties": {
    "gn:admin1_code":"19.0",
    "gn:admin2_code":"562.0",
    "gn:asciiname":"Pale",
    "gn:country_code":"IN",
    "gn:dem":602,
    "gn:feature_class":"P",
    "gn:feature_code":"PPL",
    "gn:name":"P\u0101le",
    "gn:population":0,
    "gn:timezone":"Asia/Kolkata",
    "iso:country":"IN",
    "name:ara_x_preferred":[
        "\u0628\u0627\u0644\u064a"
    ],
    "name:ben_bn_x_preferred":[
        "\u09aa\u09be\u09b2\u09c7"
    ],
    "name:ben_in_x_preferred":[
        "\u09aa\u09be\u09b2\u09c7"
    ],
    "name:bos_x_preferred":[
        "Pale"
    ],
    "name:cat_x_preferred":[
        "Pale"
    ],
    "name:ceb_x_preferred":[
        "Pale"
    ],
    "name:deu_x_preferred":[
        "Pale"
    ],
    "name:fin_x_preferred":[
        "Pale"
    ],
    "name:fra_x_preferred":[
        "Pale"
    ],
    "name:guj_x_preferred":[
        "\u0aaa\u0ac7\u0ab2\u0ac7"
    ],
    "name:hin_x_preferred":[
        "\u092a\u093e\u0932\u0947"
    ],
    "name:hrv_x_preferred":[
        "Pale"
    ],
    "name:ita_x_preferred":[
        "Pale"
    ],
    "name:kan_x_preferred":[
        "\u0caa\u0cbe\u0cb2\u0cc6"
    ],
    "name:mal_x_preferred":[
        "\u0d2a\u0d32\u0d46"
    ],
    "name:mar_x_preferred":[
        "\u092a\u093e\u0932\u0947"
    ],
    "name:nld_x_preferred":[
        "Pale"
    ],
    "name:pan_x_preferred":[
        "\u0a2a\u0a47\u0a32"
    ],
    "name:por_x_preferred":[
        "Pale"
    ],
    "name:rus_x_preferred":[
        "\u041f\u044d\u0439\u043b"
    ],
    "name:swe_x_preferred":[
        "Pale"
    ],
    "name:tam_x_preferred":[
        "\u0baa\u0bbe\u0bb2\u0bc6"
    ],
    "name:tel_x_preferred":[
        "\u0c2a\u0c3e\u0c32\u0c46"
    ],
    "name:ukr_x_preferred":[
        "\u041f\u0430\u043b\u0435"
    ],
    "name:urd_x_preferred":[
        "\u067e\u0627\u0644\u06cc"
    ],
    "name:wln_x_preferred":[
        "P\u00e5le"
    ],
    "wof:name":"Pale",
    "wof:placetype":"locality"
},
  "geometry": {"coordinates":[75.14627,15.24618],"type":"Point"}
}