{
  "type": "Feature",
  "properties": {
    "iso:country":"IN",
    "ks:ks_name":"Haribabawasti",
    "ks:ks_pop":395,
    "ks:ks_type":"HABITATION",
    "name:eng_x_preferred":[
        "Haribabawasti"
    ],
    "wof:name":"Haribabawasti",
    "wof:placetype":"locality",
    "wof:population":395
},
  "geometry": {"coordinates":[74.16921499999999,19.580363],"type":"Point"}
}