{
  "type": "Feature",
  "properties": {
    "gn:admin1_code":"12.0",
    "gn:admin2_code":"008",
    "gn:asciiname":"Kutur Naribal",
    "gn:country_code":"IN",
    "gn:dem":1988,
    "gn:feature_class":"P",
    "gn:feature_code":"PPL",
    "gn:name":"Kutur N\u0101ribal",
    "gn:population":0,
    "gn:timezone":"Asia/Kolkata",
    "iso:country":"IN",
    "wof:name":"Kutur Naribal",
    "wof:placetype":"locality"
},
  "geometry": {"coordinates":[74.26125,34.25884],"type":"Point"}
}