{
  "type": "Feature",
  "properties": {
    "gn:admin1_code":"16",
    "gn:admin2_code":"509.0",
    "gn:asciiname":"Bond",
    "gn:country_code":"IN",
    "gn:dem":264,
    "gn:feature_class":"P",
    "gn:feature_code":"PPL",
    "gn:name":"Bond",
    "gn:population":0,
    "gn:timezone":"Asia/Kolkata",
    "iso:country":"IN",
    "name:ceb_x_preferred":[
        "Bond"
    ],
    "name:cym_x_preferred":[
        "Bond"
    ],
    "name:deu_x_preferred":[
        "Bond"
    ],
    "name:ell_x_preferred":[
        "\u039c\u03c0\u03bf\u03bd\u03c4"
    ],
    "name:est_x_preferred":[
        "Bond"
    ],
    "name:fas_x_preferred":[
        "\u0628\u0627\u0646\u062f"
    ],
    "name:fin_x_preferred":[
        "Bond"
    ],
    "name:fra_x_preferred":[
        "Bond"
    ],
    "name:heb_x_preferred":[
        "\u05d1\u05d5\u05e0\u05d3"
    ],
    "name:ita_x_preferred":[
        "Bond"
    ],
    "name:jpn_x_preferred":[
        "\u30dc\u30f3\u30c9"
    ],
    "name:lmo_x_preferred":[
        "Bond"
    ],
    "name:nld_x_preferred":[
        "Bond"
    ],
    "name:nor_x_preferred":[
        "Bond"
    ],
    "name:pol_x_preferred":[
        "Bond"
    ],
    "name:por_x_preferred":[
        "Bond"
    ],
    "name:rus_x_preferred":[
        "\u0411\u043e\u043d\u0434"
    ],
    "name:slk_x_preferred":[
        "Bond"
    ],
    "name:slv_x_preferred":[
        "Bond"
    ],
    "name:spa_x_preferred":[
        "Bond"
    ],
    "name:srp_x_preferred":[
        "\u0411\u043e\u043d\u0434"
    ],
    "name:swe_x_preferred":[
        "Bond"
    ],
    "name:tha_x_preferred":[
        "\u0e1a\u0e2d\u0e19\u0e14\u0e4c"
    ],
    "name:tur_x_preferred":[
        "Bond"
    ],
    "name:ukr_x_preferred":[
        "\u0411\u043e\u043d\u0434"
    ],
    "wof:name":"Bond",
    "wof:placetype":"locality"
},
  "geometry": {"coordinates":[79.74263000000001,20.48948],"type":"Point"}
}