{
  "type": "Feature",
  "properties": {
    "gn:admin1_code":"11.0",
    "gn:admin2_code":"33.0",
    "gn:asciiname":"Bhog",
    "gn:country_code":"IN",
    "gn:dem":2185,
    "gn:feature_class":"P",
    "gn:feature_code":"PPL",
    "gn:name":"Bhog",
    "gn:population":0,
    "gn:timezone":"Asia/Kolkata",
    "iso:country":"IN",
    "name:fra_x_preferred":[
        "Bhog"
    ],
    "name:guj_x_preferred":[
        "\u0aad\u0acb\u0a97"
    ],
    "wof:name":"Bhog",
    "wof:placetype":"locality"
},
  "geometry": {"coordinates":[77.52318000000002,31.08771],"type":"Point"}
}