{
  "type": "Feature",
  "properties": {
    "gn:admin1_code":"23.0",
    "gn:admin2_code":"35.0",
    "gn:asciiname":"Mathola",
    "gn:country_code":"IN",
    "gn:dem":254,
    "gn:feature_class":"P",
    "gn:feature_code":"PPL",
    "gn:name":"Mathola",
    "gn:population":0,
    "gn:timezone":"Asia/Kolkata",
    "iso:country":"IN",
    "wof:name":"Mathola",
    "wof:placetype":"locality"
},
  "geometry": {"coordinates":[75.44171999999998,31.74578],"type":"Point"}
}