{
  "type": "Feature",
  "properties": {
    "iso:country":"IN",
    "ks:ks_name":"Chougalewadi Sangavad",
    "ks:ks_pop":1241,
    "ks:ks_type":"HABITATION",
    "name:eng_x_preferred":[
        "Chougalewadi Sangavad"
    ],
    "wof:name":"Chougalewadi Sangavad",
    "wof:placetype":"locality",
    "wof:population":1241
},
  "geometry": {"coordinates":[73.98331,17.336936],"type":"Point"}
}