{
  "type": "Feature",
  "properties": {
    "gn:admin1_code":"35",
    "gn:admin2_code":"430.0",
    "gn:asciiname":"Ghuma",
    "gn:country_code":"IN",
    "gn:dem":340,
    "gn:feature_class":"P",
    "gn:feature_code":"PPL",
    "gn:name":"Gh\u016bma",
    "gn:population":0,
    "gn:timezone":"Asia/Kolkata",
    "iso:country":"IN",
    "wof:name":"Ghuma",
    "wof:placetype":"locality"
},
  "geometry": {"coordinates":[81.67591,24.90662],"type":"Point"}
}