{
  "type": "Feature",
  "properties": {
    "iso:country":"IN",
    "ks:ks_name":"Paboosari",
    "ks:ks_pop":737,
    "ks:ks_type":"HABITATION",
    "name:eng_x_preferred":[
        "Paboosari"
    ],
    "wof:name":"Paboosari",
    "wof:placetype":"locality",
    "wof:population":737
},
  "geometry": {"coordinates":[70.544342,25.856969],"type":"Point"}
}