{
  "type": "Feature",
  "properties": {
    "gn:admin1_code":"25.0",
    "gn:admin2_code":"633.0",
    "gn:asciiname":"Pundi",
    "gn:country_code":"IN",
    "gn:dem":1061,
    "gn:feature_class":"P",
    "gn:feature_code":"PPL",
    "gn:name":"P\u016bndi",
    "gn:population":0,
    "gn:timezone":"Asia/Kolkata",
    "iso:country":"IN",
    "name:tcy_x_preferred":[
        "\u0caa\u0cc1\u0c82\u0ca1\u0cbf"
    ],
    "wof:name":"Pundi",
    "wof:placetype":"locality"
},
  "geometry": {"coordinates":[77.09787,10.42217],"type":"Point"}
}