{
  "type": "Feature",
  "properties": {
    "gn:admin1_code":"16",
    "gn:admin2_code":"502.0",
    "gn:asciiname":"Chandhai",
    "gn:country_code":"IN",
    "gn:dem":455,
    "gn:feature_class":"P",
    "gn:feature_code":"PPL",
    "gn:name":"Ch\u0101ndhai",
    "gn:population":0,
    "gn:timezone":"Asia/Kolkata",
    "iso:country":"IN",
    "wof:name":"Chandhai",
    "wof:placetype":"locality"
},
  "geometry": {"coordinates":[77.40465,20.28746],"type":"Point"}
}