{
  "type": "Feature",
  "properties": {
    "iso:country":"IN",
    "ks:ks_name":"Seujia Pathar Gohain",
    "ks:ks_pop":299,
    "ks:ks_type":"HABITATION",
    "ks:ks_uagg_main":0,
    "name:eng_x_preferred":[
        "Seujia Pathar Gohain"
    ],
    "wof:name":"Seujia Pathar Gohain",
    "wof:placetype":"neighbourhood",
    "wof:population":299
},
  "geometry": {"coordinates":[94.580377,27.339233],"type":"Point"}
}