{
  "type": "Feature",
  "properties": {
    "iso:country":"IN",
    "ks:ks_name":"Hadikal",
    "ks:ks_pop":191,
    "ks:ks_type":"VILLAGE",
    "name:eng_x_preferred":[
        "Hadikal"
    ],
    "wof:name":"Hadikal",
    "wof:placetype":"locality",
    "wof:population":191
},
  "geometry": {"coordinates":[74.542233,14.17381],"type":"Point"}
}