{
  "type": "Feature",
  "properties": {
    "iso:country":"IN",
    "ks:ks_name":"Majeti",
    "ks:ks_pop":19,
    "ks:ks_type":"VILLAGE",
    "name:eng_x_preferred":[
        "Majeti"
    ],
    "wof:name":"Majeti",
    "wof:placetype":"locality",
    "wof:population":19
},
  "geometry": {"coordinates":[75.009663,24.056109],"type":"Point"}
}