{
  "type": "Feature",
  "properties": {
    "iso:country":"IN",
    "ks:ks_name":"Dumuribeda",
    "ks:ks_pop":170,
    "ks:ks_type":"VILLAGE",
    "ks:ks_uagg_main":0,
    "name:eng_x_preferred":[
        "Dumuribeda"
    ],
    "wof:name":"Dumuribeda",
    "wof:placetype":"neighbourhood",
    "wof:population":170
},
  "geometry": {"coordinates":[84.215991,20.882005],"type":"Point"}
}