{
  "type": "Feature",
  "properties": {
    "gn:admin1_code":"10.0",
    "gn:admin2_code":"74.0",
    "gn:asciiname":"Goli",
    "gn:country_code":"IN",
    "gn:dem":239,
    "gn:feature_class":"P",
    "gn:feature_code":"PPL",
    "gn:name":"Goli",
    "gn:population":0,
    "gn:timezone":"Asia/Kolkata",
    "iso:country":"IN",
    "name:ceb_x_preferred":[
        "Goli"
    ],
    "name:deu_x_preferred":[
        "Goli"
    ],
    "name:swe_x_preferred":[
        "Goli"
    ],
    "name:ukr_x_preferred":[
        "\u0413\u043e\u043b\u0456"
    ],
    "wof:name":"Goli",
    "wof:placetype":"locality"
},
  "geometry": {"coordinates":[76.75961,29.48364],"type":"Point"}
}