{
  "type": "Feature",
  "properties": {
    "iso:country":"IN",
    "ks:ks_alt_nam":"BHUKRANSAR",
    "ks:ks_name":"Bhukransar",
    "ks:ks_pop":611,
    "ks:ks_type":"HABITATION",
    "name:eng_x_preferred":[
        "Bhukransar"
    ],
    "wof:name":"Bhukransar",
    "wof:placetype":"locality",
    "wof:population":611
},
  "geometry": {"coordinates":[71.329967,25.430444],"type":"Point"}
}