{
  "type": "Feature",
  "properties": {
    "gn:admin1_code":"36.0",
    "gn:admin2_code":"162.0",
    "gn:asciiname":"Sheopur",
    "gn:country_code":"IN",
    "gn:dem":146,
    "gn:feature_class":"P",
    "gn:feature_code":"PPL",
    "gn:name":"Sheopur",
    "gn:population":0,
    "gn:timezone":"Asia/Kolkata",
    "iso:country":"IN",
    "name:ben_x_preferred":[
        "\u09b6\u09c7\u0993\u09aa\u09c1\u09b0"
    ],
    "name:bpy_x_preferred":[
        "\u09b6\u09c7\u09f1\u09aa\u09c1\u09b0"
    ],
    "name:cat_x_preferred":[
        "Sheopur"
    ],
    "name:ceb_x_preferred":[
        "Sheopur"
    ],
    "name:fra_x_preferred":[
        "Sheopur"
    ],
    "name:guj_x_preferred":[
        "\u0ab6\u0acd\u0aaf\u0acb\u0aaa\u0ac1\u0ab0"
    ],
    "name:hif_x_preferred":[
        "Sheopur"
    ],
    "name:hin_x_preferred":[
        "\u0936\u094d\u092f\u094b\u092a\u0941\u0930"
    ],
    "name:ita_x_preferred":[
        "Sheopur"
    ],
    "name:mlg_x_preferred":[
        "Sheopur"
    ],
    "name:msa_x_preferred":[
        "Sheopur"
    ],
    "name:ori_x_preferred":[
        "\u0b36\u0b47\u0b13\u0b2a\u0b41\u0b30"
    ],
    "name:pam_x_preferred":[
        "Sheopur"
    ],
    "name:por_x_preferred":[
        "Sheopur"
    ],
    "name:san_x_preferred":[
        "\u0936\u094d\u092f\u094b\u092a\u0941\u0930\u092e\u094d"
    ],
    "name:spa_x_preferred":[
        "Sheopur"
    ],
    "name:swe_x_preferred":[
        "Sheopur"
    ],
    "name:urd_x_preferred":[
        "\u0634\u0648\u067e\u0648\u0631"
    ],
    "name:vie_x_preferred":[
        "Sheopur"
    ],
    "name:zho_x_preferred":[
        "\u65af\u8d6b\u5965\u666e\u5c14"
    ],
    "wof:name":"Sheopur",
    "wof:placetype":"locality"
},
  "geometry": {"coordinates":[79.4271,26.67531],"type":"Point"}
}