{
  "type": "Feature",
  "properties": {
    "gn:admin1_code":"2.0",
    "gn:admin2_code":"554.0",
    "gn:asciiname":"Nadimpalli",
    "gn:country_code":"IN",
    "gn:dem":398,
    "gn:feature_class":"P",
    "gn:feature_code":"PPL",
    "gn:name":"Nadimpalli",
    "gn:population":0,
    "gn:timezone":"Asia/Kolkata",
    "iso:country":"IN",
    "ks:ks_name":"Nadimpalle",
    "ks:ks_pop":51,
    "ks:ks_type":"VILLAGE",
    "name:eng_x_preferred":[
        "Nadimpalle"
    ],
    "name:eng_x_variant":[
        "Nadimpalli"
    ],
    "wof:name":"Nadimpalle",
    "wof:placetype":"locality",
    "wof:population":51
},
  "geometry": {"coordinates":[79.012832,13.102053],"type":"Point"}
}