{
  "type": "Feature",
  "properties": {
    "gn:admin1_code":"19.0",
    "gn:admin2_code":"576.0",
    "gn:asciiname":"Kodhalli",
    "gn:country_code":"IN",
    "gn:dem":1013,
    "gn:feature_class":"P",
    "gn:feature_code":"PPL",
    "gn:name":"Kodhalli",
    "gn:population":0,
    "gn:timezone":"Asia/Kolkata",
    "iso:country":"IN",
    "ks:ks_name":"Kodalli",
    "ks:ks_pop":14,
    "ks:ks_type":"HABITATION",
    "name:eng_x_preferred":[
        "Kodalli"
    ],
    "name:eng_x_variant":[
        "Kodhalli"
    ],
    "wof:name":"Kodalli",
    "wof:placetype":"locality",
    "wof:population":14
},
  "geometry": {"coordinates":[75.745278,12.674722],"type":"Point"}
}