{
  "type": "Feature",
  "properties": {
    "iso:country":"IN",
    "ks:ks_name":"Sandelerbil",
    "ks:ks_pop":9132,
    "ks:ks_type":"VILLAGE",
    "name:eng_x_preferred":[
        "Sandelerbil"
    ],
    "wof:name":"Sandelerbil",
    "wof:placetype":"locality",
    "wof:population":9132
},
  "geometry": {"coordinates":[88.967534,22.439678],"type":"Point"}
}