{
  "type": "Feature",
  "properties": {
    "iso:country":"IN",
    "ks:ks_name":"Tutumsing",
    "ks:ks_pop":356,
    "ks:ks_type":"VILLAGE",
    "name:eng_x_preferred":[
        "Tutumsing"
    ],
    "wof:name":"Tutumsing",
    "wof:placetype":"locality",
    "wof:population":356
},
  "geometry": {"coordinates":[84.22971099999999,20.687842],"type":"Point"}
}