{
  "type": "Feature",
  "properties": {
    "iso:country":"IN",
    "ks:ks_alt_nam":"abbas wasti",
    "ks:ks_name":"Abbas Wasti",
    "ks:ks_pop":440,
    "ks:ks_type":"HABITATION",
    "name:eng_x_preferred":[
        "Abbas Wasti"
    ],
    "wof:name":"Abbas Wasti",
    "wof:placetype":"locality",
    "wof:population":440
},
  "geometry": {"coordinates":[76.14852,17.712737],"type":"Point"}
}