{
  "type": "Feature",
  "properties": {
    "iso:country":"IN",
    "ks:ks_name":"Sahotra",
    "ks:ks_pop":45,
    "ks:ks_type":"VILLAGE",
    "name:eng_x_preferred":[
        "Sahotra"
    ],
    "wof:name":"Sahotra",
    "wof:placetype":"locality",
    "wof:population":45
},
  "geometry": {"coordinates":[84.965935,24.316945],"type":"Point"}
}