{
  "type": "Feature",
  "properties": {
    "iso:country":"IN",
    "ks:ks_name":"Khori Falia",
    "ks:ks_pop":78,
    "ks:ks_type":"HABITATION",
    "name:eng_x_preferred":[
        "Khori Falia"
    ],
    "wof:name":"Khori Falia",
    "wof:placetype":"locality",
    "wof:population":78
},
  "geometry": {"coordinates":[73.114806,20.346889],"type":"Point"}
}