{
  "type": "Feature",
  "properties": {
    "iso:country":"IN",
    "ks:ks_name":"Ichauli",
    "ks:ks_pop":700,
    "ks:ks_type":"VILLAGE",
    "name:eng_x_preferred":[
        "Ichauli"
    ],
    "wof:name":"Ichauli",
    "wof:placetype":"locality",
    "wof:population":700
},
  "geometry": {"coordinates":[81.40255999999999,25.555608],"type":"Point"}
}