{
  "type": "Feature",
  "properties": {
    "iso:country":"IN",
    "ks:ks_name":"Karanpur",
    "ks:ks_pop":794,
    "ks:ks_type":"VILLAGE",
    "name:eng_x_preferred":[
        "Karanpur"
    ],
    "wof:name":"Karanpur",
    "wof:placetype":"locality",
    "wof:population":794
},
  "geometry": {"coordinates":[82.488765,26.898269],"type":"Point"}
}