{
  "type": "Feature",
  "properties": {
    "iso:country":"IN",
    "ks:ks_name":"Khan Mondal Para",
    "ks:ks_pop":2000,
    "ks:ks_type":"HABITATION",
    "name:eng_x_preferred":[
        "Khan Mondal Para"
    ],
    "wof:name":"Khan Mondal Para",
    "wof:placetype":"locality",
    "wof:population":2000
},
  "geometry": {"coordinates":[88.334566,22.331676],"type":"Point"}
}