{
  "type": "Feature",
  "properties": {
    "iso:country":"IN",
    "ks:ks_name":"Kanchan Purwa",
    "ks:ks_pop":100,
    "ks:ks_type":"HABITATION",
    "name:eng_x_preferred":[
        "Kanchan Purwa"
    ],
    "wof:name":"Kanchan Purwa",
    "wof:placetype":"locality",
    "wof:population":100
},
  "geometry": {"coordinates":[81.74526400000001,27.291706],"type":"Point"}
}