{
  "type": "Feature",
  "properties": {
    "gn:admin1_code":"13.0",
    "gn:admin2_code":"593.0",
    "gn:asciiname":"Kulamaniyenon Challai",
    "gn:country_code":"IN",
    "gn:dem":183,
    "gn:feature_class":"P",
    "gn:feature_code":"PPL",
    "gn:name":"Kulamaniyenon Ch\u0101llai",
    "gn:population":0,
    "gn:timezone":"Asia/Kolkata",
    "iso:country":"IN",
    "wof:name":"Kulamaniyenon Challai",
    "wof:placetype":"neighbourhood"
},
  "geometry": {"coordinates":[76.85308000000001,10.7818],"type":"Point"}
}