{
  "type": "Feature",
  "properties": {
    "gn:admin1_code":"38.0",
    "gn:admin2_code":"347.0",
    "gn:asciiname":"Bajrahi",
    "gn:country_code":"IN",
    "gn:dem":383,
    "gn:feature_class":"P",
    "gn:feature_code":"PPL",
    "gn:name":"Bajr\u0101h\u012b",
    "gn:population":0,
    "gn:timezone":"Asia/Kolkata",
    "iso:country":"IN",
    "ks:ks_alt_nam":"Bajr\u0101h\u012b",
    "ks:ks_name":"Bajrahi",
    "ks:ks_pop":65,
    "ks:ks_type":"VILLAGE",
    "name:eng_x_preferred":[
        "Bajrahi"
    ],
    "name:eng_x_variant":[
        "Bajr\u0101h\u012b"
    ],
    "wof:name":"Bajrahi",
    "wof:placetype":"locality",
    "wof:population":65
},
  "geometry": {"coordinates":[84.646541,24.160789],"type":"Point"}
}