{
  "type": "Feature",
  "properties": {
    "gn:admin1_code":"38.0",
    "gn:admin2_code":"347.0",
    "gn:asciiname":"Bajrahi",
    "gn:country_code":"IN",
    "gn:dem":383,
    "gn:feature_class":"P",
    "gn:feature_code":"PPL",
    "gn:name":"Bajr\u0101h\u012b",
    "gn:population":0,
    "gn:timezone":"Asia/Kolkata",
    "iso:country":"IN",
    "wof:name":"Bajrahi",
    "wof:placetype":"locality"
},
  "geometry": {"coordinates":[84.64654,24.16079],"type":"Point"}
}