{
  "type": "Feature",
  "properties": {
    "gn:admin1_code":"34.0",
    "gn:admin2_code":"235.0",
    "gn:asciiname":"Kakan",
    "gn:country_code":"IN",
    "gn:dem":114,
    "gn:feature_class":"P",
    "gn:feature_code":"PPL",
    "gn:name":"K\u0101kan",
    "gn:population":0,
    "gn:timezone":"Asia/Kolkata",
    "iso:country":"IN",
    "name:ceb_x_preferred":[
        "Kakan"
    ],
    "name:swe_x_preferred":[
        "Kakan"
    ],
    "wof:name":"Kakan",
    "wof:placetype":"locality"
},
  "geometry": {"coordinates":[84.57316,24.73834],"type":"Point"}
}