{
  "type": "Feature",
  "properties": {
    "iso:country":"IN",
    "ks:ks_name":"Dhamai",
    "ks:ks_pop":878,
    "ks:ks_type":"VILLAGE",
    "name:eng_x_preferred":[
        "Dhamai"
    ],
    "wof:name":"Dhamai",
    "wof:placetype":"locality",
    "wof:population":878
},
  "geometry": {"coordinates":[87.727324,21.869751],"type":"Point"}
}