{
  "type": "Feature",
  "properties": {
    "iso:country":"IN",
    "ks:ks_name":"Karumbulipatty",
    "ks:ks_pop":682,
    "ks:ks_type":"HABITATION",
    "name:eng_x_preferred":[
        "Karumbulipatty"
    ],
    "wof:name":"Karumbulipatty",
    "wof:placetype":"locality",
    "wof:population":682
},
  "geometry": {"coordinates":[78.400293,10.653377],"type":"Point"}
}