{
  "type": "Feature",
  "properties": {
    "iso:country":"IN",
    "ks:ks_name":"Modokona",
    "ks:ks_pop":1021,
    "ks:ks_type":"HABITATION",
    "name:eng_x_preferred":[
        "Modokona"
    ],
    "wof:name":"Modokona",
    "wof:placetype":"locality",
    "wof:population":1021
},
  "geometry": {"coordinates":[90.145611,26.033981],"type":"Point"}
}