{
  "type": "Feature",
  "properties": {
    "gn:admin1_code":"35",
    "gn:admin2_code":"443.0",
    "gn:asciiname":"Besra",
    "gn:country_code":"IN",
    "gn:dem":500,
    "gn:feature_class":"P",
    "gn:feature_code":"PPL",
    "gn:name":"Besra",
    "gn:population":0,
    "gn:timezone":"Asia/Kolkata",
    "iso:country":"IN",
    "name:ara_x_preferred":[
        "\u0628\u0627\u0634\u0642 \u0628\u0633\u0631\u0649"
    ],
    "name:ast_x_preferred":[
        "Accipiter virgatus"
    ],
    "name:ava_x_preferred":[
        "\u0413\u044c\u0438\u0442\u04c0\u0438\u043d\u0430\u0431 \u0445\u044a\u0435\u0440\u0433\u044a\u0443"
    ],
    "name:aze_x_preferred":[
        "Ki\u00e7ik bildir\u00e7in\u00e7alan"
    ],
    "name:ceb_x_preferred":[
        "Accipiter virgatus"
    ],
    "name:che_x_preferred":[
        "\u041a\u044a\u043e\u0440\u0437\u0430 \u043a\u0443\u044c\u0439\u0440\u0430"
    ],
    "name:cym_x_preferred":[
        "Gwalch Besra"
    ],
    "name:epo_x_preferred":[
        "Besro"
    ],
    "name:eus_x_preferred":[
        "Accipiter virgatus"
    ],
    "name:fin_x_preferred":[
        "Ruostevarpushaukka"
    ],
    "name:fra_x_preferred":[
        "\u00c9pervier besra"
    ],
    "name:ind_x_preferred":[
        "Elang-alap besra"
    ],
    "name:ita_x_preferred":[
        "Accipiter virgatus"
    ],
    "name:mal_x_preferred":[
        "\u0d2c\u0d46\u0d38\u0d4d\u0d30 \u0d2a\u0d4d\u0d30\u0d3e\u0d2a\u0d4d\u0d2a\u0d3f\u0d1f\u0d3f\u0d2f\u0d7b"
    ],
    "name:nep_x_preferred":[
        "\u092c\u0947\u0938\u0930\u093e"
    ],
    "name:nld_x_preferred":[
        "Besrasperwer"
    ],
    "name:pnb_x_preferred":[
        "\u0628\u0633\u0631\u0627"
    ],
    "name:pol_x_preferred":[
        "Krogulec orientalny"
    ],
    "name:rus_x_preferred":[
        "\u0418\u043d\u0434\u0438\u0439\u0441\u043a\u0438\u0439 \u043f\u0435\u0440\u0435\u043f\u0435\u043b\u044f\u0442\u043d\u0438\u043a"
    ],
    "name:spa_x_preferred":[
        "Accipiter virgatus"
    ],
    "name:sun_x_preferred":[
        "Alap-alap"
    ],
    "name:swe_x_preferred":[
        "Besra"
    ],
    "name:tam_x_preferred":[
        "\u0b9a\u0bbf\u0ba9\u0bcd\u0ba9 \u0bb5\u0bb2\u0bcd\u0bb2\u0bc2\u0bb1\u0bc1"
    ],
    "name:war_x_preferred":[
        "Accipiter virgatus"
    ],
    "name:zho_x_preferred":[
        "\u677e\u96c0\u9e70"
    ],
    "wof:name":"Besra",
    "wof:placetype":"neighbourhood"
},
  "geometry": {"coordinates":[77.50095,24.25201],"type":"Point"}
}