{
  "type": "Feature",
  "properties": {
    "iso:country":"IN",
    "ks:ks_name":"Golikatta",
    "ks:ks_pop":119,
    "ks:ks_type":"HABITATION",
    "name:eng_x_preferred":[
        "Golikatta"
    ],
    "wof:name":"Golikatta",
    "wof:placetype":"locality",
    "wof:population":119
},
  "geometry": {"coordinates":[74.94327199999999,14.558538],"type":"Point"}
}