{
  "type": "Feature",
  "properties": {
    "iso:country":"IN",
    "ks:ks_name":"Majra Haldau",
    "ks:ks_pop":250,
    "ks:ks_type":"HABITATION",
    "name:eng_x_preferred":[
        "Majra Haldau"
    ],
    "wof:name":"Majra Haldau",
    "wof:placetype":"locality",
    "wof:population":250
},
  "geometry": {"coordinates":[79.347145,28.790729],"type":"Point"}
}