{
  "type": "Feature",
  "properties": {
    "gn:admin1_code":"23",
    "gn:admin2_code":"37.0",
    "gn:asciiname":"Budhanwal",
    "gn:country_code":"IN",
    "gn:dem":223,
    "gn:feature_class":"P",
    "gn:feature_code":"PPL",
    "gn:name":"Budhanw\u0101l",
    "gn:population":0,
    "gn:timezone":"Asia/Kolkata",
    "iso:country":"IN",
    "wof:name":"Budhanwal",
    "wof:placetype":"locality"
},
  "geometry": {"coordinates":[75.34336,31.05208],"type":"Point"}
}