{
  "type": "Feature",
  "properties": {
    "iso:country":"IN",
    "ks:ks_name":"Dhobin Purwa",
    "ks:ks_pop":147,
    "ks:ks_type":"HABITATION",
    "name:eng_x_preferred":[
        "Dhobin Purwa"
    ],
    "wof:name":"Dhobin Purwa",
    "wof:placetype":"locality",
    "wof:population":147
},
  "geometry": {"coordinates":[81.00318900000001,25.334029],"type":"Point"}
}