{
  "type": "Feature",
  "properties": {
    "iso:country":"IN",
    "ks:ks_name":"Baki",
    "ks:ks_pop":22,
    "ks:ks_type":"HABITATION",
    "name:eng_x_preferred":[
        "Baki"
    ],
    "wof:name":"Baki",
    "wof:placetype":"locality",
    "wof:population":22
},
  "geometry": {"coordinates":[74.364305,15.01629],"type":"Point"}
}