{
  "type": "Feature",
  "properties": {
    "iso:country":"IN",
    "ks:ks_name":"Pookulam",
    "ks:ks_pop":380,
    "ks:ks_type":"HABITATION",
    "name:eng_x_preferred":[
        "Pookulam"
    ],
    "wof:name":"Pookulam",
    "wof:placetype":"locality",
    "wof:population":380
},
  "geometry": {"coordinates":[77.050049,9.67444],"type":"Point"}
}