{
  "type": "Feature",
  "properties": {
    "iso:country":"IN",
    "ks:ks_name":"Chamariya",
    "ks:ks_pop":2,
    "ks:ks_type":"HABITATION",
    "name:eng_x_preferred":[
        "Chamariya"
    ],
    "wof:name":"Chamariya",
    "wof:placetype":"locality",
    "wof:population":2
},
  "geometry": {"coordinates":[81.117696,24.816879],"type":"Point"}
}