{
  "type": "Feature",
  "properties": {
    "iso:country":"IN",
    "ks:ks_alt_nam":"7 SHPD-B",
    "ks:ks_name":"7 Shpd-b",
    "ks:ks_pop":93,
    "ks:ks_type":"HABITATION",
    "name:eng_x_preferred":[
        "7 Shpd-b"
    ],
    "wof:name":"7 Shpd-b",
    "wof:placetype":"locality",
    "wof:population":93
},
  "geometry": {"coordinates":[73.786028,29.376619],"type":"Point"}
}