{
  "type": "Feature",
  "properties": {
    "gn:admin1_code":"21",
    "gn:admin2_code":"397.0",
    "gn:asciiname":"Killoli",
    "gn:country_code":"IN",
    "gn:dem":649,
    "gn:feature_class":"P",
    "gn:feature_code":"PPL",
    "gn:name":"Killoli",
    "gn:population":0,
    "gn:timezone":"Asia/Kolkata",
    "iso:country":"IN",
    "wof:name":"Killoli",
    "wof:placetype":"neighbourhood"
},
  "geometry": {"coordinates":[81.91146000000001,20.05446],"type":"Point"}
}