{
  "type": "Feature",
  "properties": {
    "iso:country":"IN",
    "ks:ks_name":"Sindhibandaguda",
    "ks:ks_pop":98,
    "ks:ks_type":"HABITATION",
    "name:eng_x_preferred":[
        "Sindhibandaguda"
    ],
    "wof:name":"Sindhibandaguda",
    "wof:placetype":"locality",
    "wof:population":98
},
  "geometry": {"coordinates":[82.214553,18.520211],"type":"Point"}
}