{
  "type": "Feature",
  "properties": {
    "iso:country":"IN",
    "ks:ks_name":"Dhanirampur",
    "ks:ks_pop":165,
    "ks:ks_type":"VILLAGE",
    "name:eng_x_preferred":[
        "Dhanirampur"
    ],
    "wof:name":"Dhanirampur",
    "wof:placetype":"locality",
    "wof:population":165
},
  "geometry": {"coordinates":[85.74433500000001,25.633967],"type":"Point"}
}