{
  "type": "Feature",
  "properties": {
    "iso:country":"IN",
    "ks:ks_alt_nam":"Lalpani FV",
    "ks:ks_name":"Lalpani Fv",
    "ks:ks_pop":3775,
    "ks:ks_type":"HABITATION",
    "name:eng_x_preferred":[
        "Lalpani Fv"
    ],
    "wof:name":"Lalpani Fv",
    "wof:placetype":"locality",
    "wof:population":3775
},
  "geometry": {"coordinates":[92.712884,24.538771],"type":"Point"}
}