{
  "type": "Feature",
  "properties": {
    "iso:country":"IN",
    "ks:ks_name":"Navneetpura",
    "ks:ks_pop":264,
    "ks:ks_type":"HABITATION",
    "name:eng_x_preferred":[
        "Navneetpura"
    ],
    "wof:name":"Navneetpura",
    "wof:placetype":"locality",
    "wof:population":264
},
  "geometry": {"coordinates":[72.46837499999999,27.418442],"type":"Point"}
}