{
  "type": "Feature",
  "properties": {
    "iso:country":"IN",
    "ks:ks_name":"Athampalayam",
    "ks:ks_pop":299,
    "ks:ks_type":"HABITATION",
    "name:eng_x_preferred":[
        "Athampalayam"
    ],
    "wof:name":"Athampalayam",
    "wof:placetype":"locality",
    "wof:population":299
},
  "geometry": {"coordinates":[77.657365,10.956607],"type":"Point"}
}