{
  "type": "Feature",
  "properties": {
    "gn:admin1_code":"36.0",
    "gn:admin2_code":"183.0",
    "gn:asciiname":"Chiraiya Nabi Bakhsh",
    "gn:country_code":"IN",
    "gn:dem":99,
    "gn:feature_class":"P",
    "gn:feature_code":"PPL",
    "gn:name":"Chiraiya Nabi Bakhsh",
    "gn:population":0,
    "gn:timezone":"Asia/Kolkata",
    "iso:country":"IN",
    "wof:name":"Chiraiya Nabi Bakhsh",
    "wof:placetype":"locality"
},
  "geometry": {"coordinates":[82.21039,27.03665],"type":"Point"}
}