{
  "type": "Feature",
  "properties": {
    "iso:country":"IN",
    "ks:ks_name":"Duspaiha Para",
    "ks:ks_pop":114,
    "ks:ks_type":"HABITATION",
    "name:eng_x_preferred":[
        "Duspaiha Para"
    ],
    "wof:name":"Duspaiha Para",
    "wof:placetype":"locality",
    "wof:population":114
},
  "geometry": {"coordinates":[91.620965,23.338779],"type":"Point"}
}