{
  "type": "Feature",
  "properties": {
    "iso:country":"IN",
    "ks:ks_name":"Eramam",
    "ks:ks_pop":1548,
    "ks:ks_type":"VILLAGE",
    "name:eng_x_preferred":[
        "Eramam"
    ],
    "wof:name":"Eramam",
    "wof:placetype":"locality",
    "wof:population":1548
},
  "geometry": {"coordinates":[75.271034,12.177678],"type":"Point"}
}