{
  "type": "Feature",
  "properties": {
    "iso:country":"IN",
    "ks:ks_name":"Sisawa Buzurg",
    "ks:ks_pop":822,
    "ks:ks_type":"VILLAGE",
    "name:eng_x_preferred":[
        "Sisawa Buzurg"
    ],
    "wof:name":"Sisawa Buzurg",
    "wof:placetype":"locality",
    "wof:population":822
},
  "geometry": {"coordinates":[83.025282,27.282534],"type":"Point"}
}