{
  "type": "Feature",
  "properties": {
    "gn:admin1_code":"34",
    "gn:admin2_code":"233.0",
    "gn:asciiname":"Diwas Dihra",
    "gn:country_code":"IN",
    "gn:dem":80,
    "gn:feature_class":"P",
    "gn:feature_code":"PPL",
    "gn:name":"Diw\u0101s D\u012bhra",
    "gn:population":0,
    "gn:timezone":"Asia/Kolkata",
    "iso:country":"IN",
    "ks:ks_name":"Dewasdehra",
    "ks:ks_pop":544,
    "ks:ks_type":"VILLAGE",
    "ks:ks_uagg_main":0,
    "name:eng_x_preferred":[
        "Dewasdehra"
    ],
    "wof:name":"Dewasdehra",
    "wof:placetype":"neighbourhood",
    "wof:population":544
},
  "geometry": {"coordinates":[83.78664499999999,25.192396],"type":"Point"}
}