{
  "type": "Feature",
  "properties": {
    "iso:country":"IN",
    "ks:ks_alt_nam":"Nayak falia",
    "ks:ks_name":"Nayak Falia",
    "ks:ks_pop":230,
    "ks:ks_type":"HABITATION",
    "name:eng_x_preferred":[
        "Nayak Falia"
    ],
    "wof:name":"Nayak Falia",
    "wof:placetype":"locality",
    "wof:population":230
},
  "geometry": {"coordinates":[73.5776,22.89075],"type":"Point"}
}