{
  "type": "Feature",
  "properties": {
    "gn:admin1_code":"36.0",
    "gn:admin2_code":"137.0",
    "gn:asciiname":"Hashimpur",
    "gn:country_code":"IN",
    "gn:dem":217,
    "gn:feature_class":"P",
    "gn:feature_code":"PPL",
    "gn:name":"H\u0101shimpur",
    "gn:population":0,
    "gn:timezone":"Asia/Kolkata",
    "iso:country":"IN",
    "ks:ks_alt_nam":"H\u0101shimpur",
    "ks:ks_name":"Hashimpur",
    "ks:ks_type":"VILLAGE",
    "ks:ks_uagg_main":0,
    "name:eng_x_preferred":[
        "Hashimpur"
    ],
    "name:eng_x_variant":[
        "H\u0101shimpur"
    ],
    "wof:name":"Hashimpur",
    "wof:placetype":"neighbourhood"
},
  "geometry": {"coordinates":[78.288642,28.904204],"type":"Point"}
}