{
  "type": "Feature",
  "properties": {
    "iso:country":"IN",
    "ks:ks_name":"Sato Peet",
    "ks:ks_pop":1926,
    "ks:ks_type":"VILLAGE",
    "ks:ks_uagg_main":0,
    "name:eng_x_preferred":[
        "Sato Peet"
    ],
    "wof:name":"Sato Peet",
    "wof:placetype":"neighbourhood",
    "wof:population":1926
},
  "geometry": {"coordinates":[80.985608,25.770585],"type":"Point"}
}