{
  "type": "Feature",
  "properties": {
    "gn:admin1_code":"35",
    "gn:admin2_code":"458.0",
    "gn:asciiname":"Dhirdeh",
    "gn:country_code":"IN",
    "gn:dem":453,
    "gn:feature_class":"P",
    "gn:feature_code":"PPL",
    "gn:name":"Dh\u012brdeh",
    "gn:population":0,
    "gn:timezone":"Asia/Kolkata",
    "iso:country":"IN",
    "ks:ks_alt_nam":"Dh\u012brdeh",
    "ks:ks_name":"Dhirdeh",
    "ks:ks_pop":168,
    "ks:ks_type":"VILLAGE",
    "name:eng_x_preferred":[
        "Dhirdeh"
    ],
    "name:eng_x_variant":[
        "Dh\u012brdeh"
    ],
    "wof:name":"Dhirdeh",
    "wof:placetype":"locality",
    "wof:population":168
},
  "geometry": {"coordinates":[77.254965,24.487053],"type":"Point"}
}