{
  "type": "Feature",
  "properties": {
    "iso:country":"IN",
    "ks:ks_alt_nam":"5 NO. TILLA",
    "ks:ks_name":"5 No. Tilla",
    "ks:ks_pop":664,
    "ks:ks_type":"HABITATION",
    "name:eng_x_preferred":[
        "5 No. Tilla"
    ],
    "wof:name":"5 No. Tilla",
    "wof:placetype":"locality",
    "wof:population":664
},
  "geometry": {"coordinates":[91.16710999999999,23.732824],"type":"Point"}
}