{
  "type": "Feature",
  "properties": {
    "gn:admin1_code":"36",
    "gn:admin2_code":"178.0",
    "gn:asciiname":"Malikpur",
    "gn:country_code":"IN",
    "gn:dem":94,
    "gn:feature_class":"P",
    "gn:feature_code":"PPL",
    "gn:name":"Malikpur",
    "gn:population":0,
    "gn:timezone":"Asia/Kolkata",
    "iso:country":"IN",
    "name:fas_x_preferred":[
        "\u0645\u0644\u06a9\u200c\u067e\u0648\u0631"
    ],
    "name:msa_x_preferred":[
        "Malikpur"
    ],
    "wof:name":"Malikpur",
    "wof:placetype":"locality"
},
  "geometry": {"coordinates":[82.64731,26.51883],"type":"Point"}
}