{
  "type": "Feature",
  "properties": {
    "iso:country":"IN",
    "ks:ks_name":"Shalchura",
    "ks:ks_pop":195,
    "ks:ks_type":"VILLAGE",
    "name:eng_x_preferred":[
        "Shalchura"
    ],
    "wof:name":"Shalchura",
    "wof:placetype":"locality",
    "wof:population":195
},
  "geometry": {"coordinates":[86.733723,23.673216],"type":"Point"}
}