{
  "type": "Feature",
  "properties": {
    "iso:country":"IN",
    "ks:ks_name":"Varikkamuthan",
    "ks:ks_pop":445,
    "ks:ks_type":"HABITATION",
    "name:eng_x_preferred":[
        "Varikkamuthan"
    ],
    "wof:name":"Varikkamuthan",
    "wof:placetype":"locality",
    "wof:population":445
},
  "geometry": {"coordinates":[76.886987,9.980021],"type":"Point"}
}