{
  "type": "Feature",
  "properties": {
    "iso:country":"IN",
    "ks:ks_name":"Mirza Chak",
    "ks:ks_pop":20,
    "ks:ks_type":"HABITATION",
    "name:eng_x_preferred":[
        "Mirza Chak"
    ],
    "wof:name":"Mirza Chak",
    "wof:placetype":"locality",
    "wof:population":20
},
  "geometry": {"coordinates":[87.254752,24.94419],"type":"Point"}
}