{
  "type": "Feature",
  "properties": {
    "iso:country":"IN",
    "ks:ks_name":"Chanangarh",
    "ks:ks_pop":262,
    "ks:ks_type":"HABITATION",
    "name:eng_x_preferred":[
        "Chanangarh"
    ],
    "wof:name":"Chanangarh",
    "wof:placetype":"locality",
    "wof:population":262
},
  "geometry": {"coordinates":[70.714664,26.369967],"type":"Point"}
}