{
  "type": "Feature",
  "properties": {
    "iso:country":"IN",
    "ks:ks_name":"Asta",
    "ks:ks_pop":0,
    "ks:ks_type":"VILLAGE",
    "name:eng_x_preferred":[
        "Asta"
    ],
    "wof:name":"Asta",
    "wof:placetype":"locality",
    "wof:population":0
},
  "geometry": {"coordinates":[86.886183,24.366172],"type":"Point"}
}