{
  "type": "Feature",
  "properties": {
    "gn:admin1_code":"34.0",
    "gn:admin2_code":"219.0",
    "gn:asciiname":"Deuria",
    "gn:country_code":"IN",
    "gn:dem":59,
    "gn:feature_class":"P",
    "gn:feature_code":"PPL",
    "gn:name":"Deuria",
    "gn:population":0,
    "gn:timezone":"Asia/Kolkata",
    "iso:country":"IN",
    "ks:ks_name":"Deuria",
    "ks:ks_pop":1190,
    "ks:ks_type":"VILLAGE",
    "name:eng_x_preferred":[
        "Deuria"
    ],
    "wof:name":"Deuria",
    "wof:placetype":"locality",
    "wof:population":1190
},
  "geometry": {"coordinates":[84.94000699999999,25.775248],"type":"Point"}
}