{
  "type": "Feature",
  "properties": {
    "gn:admin1_code":"38.0",
    "gn:admin2_code":"358.0",
    "gn:asciiname":"Rabda",
    "gn:country_code":"IN",
    "gn:dem":243,
    "gn:feature_class":"P",
    "gn:feature_code":"PPL",
    "gn:name":"Rabd\u0101",
    "gn:population":0,
    "gn:timezone":"Asia/Kolkata",
    "iso:country":"IN",
    "name:ara_x_preferred":[
        "\u0631\u0628\u062f\u0629"
    ],
    "name:fas_x_preferred":[
        "\u0631\u0628\u062f\u0647"
    ],
    "name:pol_x_preferred":[
        "Rabda"
    ],
    "name:vie_x_preferred":[
        "Rabda"
    ],
    "wof:name":"Rabda",
    "wof:placetype":"locality"
},
  "geometry": {"coordinates":[84.07954000000002,24.22176],"type":"Point"}
}