{
  "type": "Feature",
  "properties": {
    "iso:country":"IN",
    "ks:ks_name":"Balabari",
    "ks:ks_pop":257,
    "ks:ks_type":"HABITATION",
    "ks:ks_uagg_main":0,
    "name:eng_x_preferred":[
        "Balabari"
    ],
    "wof:name":"Balabari",
    "wof:placetype":"neighbourhood",
    "wof:population":257
},
  "geometry": {"coordinates":[91.385773,26.720433],"type":"Point"}
}