{
  "type": "Feature",
  "properties": {
    "iso:country":"IN",
    "ks:ks_name":"Dhavadewadi",
    "ks:ks_pop":45,
    "ks:ks_type":"HABITATION",
    "name:eng_x_preferred":[
        "Dhavadewadi"
    ],
    "wof:name":"Dhavadewadi",
    "wof:placetype":"locality",
    "wof:population":45
},
  "geometry": {"coordinates":[73.438675,17.7629],"type":"Point"}
}