{
  "type": "Feature",
  "properties": {
    "iso:country":"IN",
    "ks:ks_name":"Chandpura",
    "ks:ks_pop":15,
    "ks:ks_type":"VILLAGE",
    "name:eng_x_preferred":[
        "Chandpura"
    ],
    "wof:name":"Chandpura",
    "wof:placetype":"locality",
    "wof:population":15
},
  "geometry": {"coordinates":[76.10704200000001,26.74015],"type":"Point"}
}