{
  "type": "Feature",
  "properties": {
    "iso:country":"IN",
    "ks:ks_name":"Mukandpur",
    "ks:ks_type":"VILLAGE",
    "name:eng_x_preferred":[
        "Mukandpur"
    ],
    "wof:name":"Mukandpur",
    "wof:placetype":"locality"
},
  "geometry": {"coordinates":[77.99283,29.826984],"type":"Point"}
}