{
  "type": "Feature",
  "properties": {
    "iso:country":"IN",
    "ks:ks_name":"Bhakatgaon",
    "ks:ks_pop":1200,
    "ks:ks_type":"VILLAGE",
    "ks:ks_uagg_main":0,
    "name:eng_x_preferred":[
        "Bhakatgaon"
    ],
    "wof:name":"Bhakatgaon",
    "wof:placetype":"neighbourhood",
    "wof:population":1200
},
  "geometry": {"coordinates":[92.450461,26.228268],"type":"Point"}
}