{
  "type": "Feature",
  "properties": {
    "gn:admin1_code":"11",
    "gn:admin2_code":"24.0",
    "gn:asciiname":"Nag Dramman",
    "gn:country_code":"IN",
    "gn:dem":697,
    "gn:feature_class":"P",
    "gn:feature_code":"PPL",
    "gn:name":"N\u0101g Dramman",
    "gn:population":0,
    "gn:timezone":"Asia/Kolkata",
    "iso:country":"IN",
    "wof:name":"Nag Dramman",
    "wof:placetype":"locality"
},
  "geometry": {"coordinates":[76.10033,32.23252],"type":"Point"}
}