{
  "type": "Feature",
  "properties": {
    "iso:country":"IN",
    "ks:ks_name":"Fanaswadi",
    "ks:ks_pop":77,
    "ks:ks_type":"HABITATION",
    "name:eng_x_preferred":[
        "Fanaswadi"
    ],
    "wof:name":"Fanaswadi",
    "wof:placetype":"locality",
    "wof:population":77
},
  "geometry": {"coordinates":[73.241669,17.908794],"type":"Point"}
}