{
  "type": "Feature",
  "properties": {
    "iso:country":"IN",
    "ks:ks_name":"Jaitpur",
    "ks:ks_pop":595,
    "ks:ks_type":"HABITATION",
    "name:eng_x_preferred":[
        "Jaitpur"
    ],
    "wof:name":"Jaitpur",
    "wof:placetype":"locality",
    "wof:population":595
},
  "geometry": {"coordinates":[77.916663,23.032954],"type":"Point"}
}