{
  "type": "Feature",
  "properties": {
    "gn:admin1_code":"36",
    "gn:admin2_code":"197.0",
    "gn:asciiname":"Kansraipur",
    "gn:country_code":"IN",
    "gn:dem":84,
    "gn:feature_class":"P",
    "gn:feature_code":"PPL",
    "gn:name":"Kansr\u0101ipur",
    "gn:population":0,
    "gn:timezone":"Asia/Kolkata",
    "iso:country":"IN",
    "ks:ks_name":"Kansraipur",
    "ks:ks_pop":505,
    "ks:ks_type":"HABITATION",
    "ks:ks_uagg_main":0,
    "name:eng_x_preferred":[
        "Kansraipur"
    ],
    "wof:name":"Kansraipur",
    "wof:placetype":"neighbourhood",
    "wof:population":505
},
  "geometry": {"coordinates":[82.762038,25.303739],"type":"Point"}
}