{
  "type": "Feature",
  "properties": {
    "iso:country":"IN",
    "ks:ks_name":"Balarampur",
    "ks:ks_pop":742,
    "ks:ks_type":"VILLAGE",
    "name:eng_x_preferred":[
        "Balarampur"
    ],
    "wof:name":"Balarampur",
    "wof:placetype":"locality",
    "wof:population":742
},
  "geometry": {"coordinates":[87.739221,22.746915],"type":"Point"}
}