{
  "type": "Feature",
  "properties": {
    "iso:country":"IN",
    "ks:ks_name":"Randhali Gaon",
    "ks:ks_pop":502,
    "ks:ks_type":"VILLAGE",
    "name:eng_x_preferred":[
        "Randhali Gaon"
    ],
    "wof:name":"Randhali Gaon",
    "wof:placetype":"locality",
    "wof:population":502
},
  "geometry": {"coordinates":[94.01625199999999,26.622869],"type":"Point"}
}