{
  "type": "Feature",
  "properties": {
    "iso:country":"IN",
    "ks:ks_name":"Hernimani",
    "ks:ks_pop":71,
    "ks:ks_type":"HABITATION",
    "name:eng_x_preferred":[
        "Hernimani"
    ],
    "wof:name":"Hernimani",
    "wof:placetype":"locality",
    "wof:population":71
},
  "geometry": {"coordinates":[74.356911,14.789154],"type":"Point"}
}