{
  "type": "Feature",
  "properties": {
    "iso:country":"IN",
    "ks:ks_name":"Badouli Tola",
    "ks:ks_pop":574,
    "ks:ks_type":"HABITATION",
    "ks:ks_uagg_main":0,
    "name:eng_x_preferred":[
        "Badouli Tola"
    ],
    "wof:name":"Badouli Tola",
    "wof:placetype":"neighbourhood",
    "wof:population":574
},
  "geometry": {"coordinates":[83.400093,27.087452],"type":"Point"}
}