{
  "type": "Feature",
  "properties": {
    "iso:country":"IN",
    "ks:ks_name":"Faridanpur",
    "ks:ks_type":"VILLAGE",
    "name:eng_x_preferred":[
        "Faridanpur"
    ],
    "wof:name":"Faridanpur",
    "wof:placetype":"locality"
},
  "geometry": {"coordinates":[84.90722,26.079229],"type":"Point"}
}