{
  "type": "Feature",
  "properties": {
    "iso:country":"IN",
    "ks:ks_name":"Lalsahab Kheda",
    "ks:ks_pop":387,
    "ks:ks_type":"HABITATION",
    "name:eng_x_preferred":[
        "Lalsahab Kheda"
    ],
    "wof:name":"Lalsahab Kheda",
    "wof:placetype":"locality",
    "wof:population":387
},
  "geometry": {"coordinates":[81.011206,26.38476],"type":"Point"}
}