{
  "type": "Feature",
  "properties": {
    "gn:admin1_code":"12",
    "gn:admin2_code":"14.0",
    "gn:asciiname":"Duratyar",
    "gn:country_code":"IN",
    "gn:dem":1638,
    "gn:feature_class":"P",
    "gn:feature_code":"PPL",
    "gn:name":"Duraty\u0101r",
    "gn:population":0,
    "gn:timezone":"Asia/Kolkata",
    "iso:country":"IN",
    "wof:name":"Duratyar",
    "wof:placetype":"locality"
},
  "geometry": {"coordinates":[75.13164999999999,33.79735],"type":"Point"}
}