{
  "type": "Feature",
  "properties": {
    "gn:admin1_code":"35",
    "gn:admin2_code":"443.0",
    "gn:asciiname":"Khejra",
    "gn:country_code":"IN",
    "gn:dem":432,
    "gn:feature_class":"P",
    "gn:feature_code":"PPL",
    "gn:name":"Khejra",
    "gn:population":0,
    "gn:timezone":"Asia/Kolkata",
    "iso:country":"IN",
    "wof:name":"Khejra",
    "wof:placetype":"locality"
},
  "geometry": {"coordinates":[77.98435000000001,23.56113],"type":"Point"}
}