{
  "type": "Feature",
  "properties": {
    "iso:country":"IN",
    "ks:ks_name":"Behanhgi",
    "ks:ks_pop":1459,
    "ks:ks_type":"HABITATION",
    "name:eng_x_preferred":[
        "Behanhgi"
    ],
    "wof:name":"Behanhgi",
    "wof:placetype":"locality",
    "wof:population":1459
},
  "geometry": {"coordinates":[87.530801,26.186238],"type":"Point"}
}