{
  "type": "Feature",
  "properties": {
    "iso:country":"IN",
    "ks:ks_name":"Kumardiha",
    "ks:ks_pop":523,
    "ks:ks_type":"HABITATION",
    "name:eng_x_preferred":[
        "Kumardiha"
    ],
    "wof:name":"Kumardiha",
    "wof:placetype":"locality",
    "wof:population":523
},
  "geometry": {"coordinates":[86.94718899999999,22.782452],"type":"Point"}
}