{
  "type": "Feature",
  "properties": {
    "iso:country":"IN",
    "ks:ks_name":"Gopalpur",
    "ks:ks_pop":3958,
    "ks:ks_type":"HABITATION",
    "name:eng_x_preferred":[
        "Gopalpur"
    ],
    "wof:name":"Gopalpur",
    "wof:placetype":"locality",
    "wof:population":3958
},
  "geometry": {"coordinates":[88.213408,21.862211],"type":"Point"}
}