{
  "type": "Feature",
  "properties": {
    "iso:country":"IN",
    "ks:ks_alt_nam":"Dangarp\u0101l",
    "ks:ks_name":"Dangarpal",
    "ks:ks_type":"VILLAGE",
    "name:eng_x_preferred":[
        "Dangarpal"
    ],
    "name:eng_x_variant":[
        "Dangarp\u0101l"
    ],
    "wof:name":"Dangarpal",
    "wof:placetype":"locality"
},
  "geometry": {"coordinates":[85.220911,21.175677],"type":"Point"}
}