{
  "type": "Feature",
  "properties": {
    "gn:admin1_code":"19.0",
    "gn:admin2_code":"568.0",
    "gn:asciiname":"Nandigod",
    "gn:country_code":"IN",
    "gn:dem":625,
    "gn:feature_class":"P",
    "gn:feature_code":"PPL",
    "gn:name":"Nandigod",
    "gn:population":0,
    "gn:timezone":"Asia/Kolkata",
    "iso:country":"IN",
    "ks:ks_name":"Nandigodu",
    "ks:ks_pop":231,
    "ks:ks_type":"VILLAGE",
    "name:eng_x_preferred":[
        "Nandigodu"
    ],
    "name:eng_x_variant":[
        "Nandigod"
    ],
    "wof:name":"Nandigodu",
    "wof:placetype":"locality",
    "wof:population":231
},
  "geometry": {"coordinates":[75.17571700000001,13.767669],"type":"Point"}
}