{
  "type": "Feature",
  "properties": {
    "gn:admin1_code":"36",
    "gn:admin2_code":"200.0",
    "gn:asciiname":"Dhobi",
    "gn:country_code":"IN",
    "gn:dem":376,
    "gn:feature_class":"P",
    "gn:feature_code":"PPL",
    "gn:name":"Dhobi",
    "gn:population":0,
    "gn:timezone":"Asia/Kolkata",
    "iso:country":"IN",
    "name:guj_x_preferred":[
        "\u0aa7\u0acb\u0aac\u0ac0"
    ],
    "name:hin_x_preferred":[
        "\u0927\u094b\u092c\u0940"
    ],
    "name:kan_x_preferred":[
        "\u0ca7\u0ccb\u0cac\u0cbf"
    ],
    "name:nep_x_preferred":[
        "\u0927\u094b\u092c\u0940"
    ],
    "name:rus_x_preferred":[
        "\u0414\u0445\u043e\u0431\u0438"
    ],
    "name:urd_x_preferred":[
        "\u062f\u06be\u0648\u0628\u06cc"
    ],
    "wof:name":"Dhobi",
    "wof:placetype":"locality"
},
  "geometry": {"coordinates":[83.46061,24.7012],"type":"Point"}
}