{
  "type": "Feature",
  "properties": {
    "gn:admin1_code":"36.0",
    "gn:admin2_code":"174.0",
    "gn:asciiname":"Kosam Inam",
    "gn:country_code":"IN",
    "gn:dem":104,
    "gn:feature_class":"P",
    "gn:feature_code":"PPL",
    "gn:name":"Kosam In\u0101m",
    "gn:population":0,
    "gn:timezone":"Asia/Kolkata",
    "iso:country":"IN",
    "name:und_x_variant":[
        "Kosam In\u0101m",
        "Uparh\u0101r"
    ],
    "wof:name":"Kosam Inam",
    "wof:placetype":"locality"
},
  "geometry": {"coordinates":[81.3716,25.34458],"type":"Point"}
}