{
  "type": "Feature",
  "properties": {
    "iso:country":"IN",
    "ks:ks_name":"Naini",
    "ks:ks_pop":136,
    "ks:ks_type":"VILLAGE",
    "name:eng_x_preferred":[
        "Naini"
    ],
    "wof:name":"Naini",
    "wof:placetype":"locality",
    "wof:population":136
},
  "geometry": {"coordinates":[80.03642000000001,29.56694],"type":"Point"}
}