{
  "type": "Feature",
  "properties": {
    "iso:country":"IN",
    "ks:ks_name":"Gokula Tola Bhalua Badar",
    "ks:ks_pop":353,
    "ks:ks_type":"VILLAGE",
    "name:eng_x_preferred":[
        "Gokula Tola Bhalua Badar"
    ],
    "wof:name":"Gokula Tola Bhalua Badar",
    "wof:placetype":"locality",
    "wof:population":353
},
  "geometry": {"coordinates":[86.985838,24.731161],"type":"Point"}
}