{
  "type": "Feature",
  "properties": {
    "gn:admin1_code":"24.0",
    "gn:admin2_code":"122.0",
    "gn:asciiname":"Debipura",
    "gn:country_code":"IN",
    "gn:dem":368,
    "gn:feature_class":"P",
    "gn:feature_code":"PPL",
    "gn:name":"Deb\u012bpura",
    "gn:population":0,
    "gn:timezone":"Asia/Kolkata",
    "iso:country":"IN",
    "name:und_x_variant":[
        "Deb\u012bpura",
        "M\u0101t\u0101ji ka Khera"
    ],
    "wof:name":"Debipura",
    "wof:placetype":"locality"
},
  "geometry": {"coordinates":[74.92726,25.19647],"type":"Point"}
}