{
  "type": "Feature",
  "properties": {
    "iso:country":"IN",
    "ks:ks_name":"Neemkuhi",
    "ks:ks_pop":597,
    "ks:ks_type":"HABITATION",
    "name:eng_x_preferred":[
        "Neemkuhi"
    ],
    "wof:name":"Neemkuhi",
    "wof:placetype":"locality",
    "wof:population":597
},
  "geometry": {"coordinates":[78.68553300000001,22.051574],"type":"Point"}
}