{
  "type": "Feature",
  "properties": {
    "gn:admin1_code":"38",
    "gn:admin2_code":"346.0",
    "gn:asciiname":"Jhotar",
    "gn:country_code":"IN",
    "gn:dem":250,
    "gn:feature_class":"P",
    "gn:feature_code":"PPL",
    "gn:name":"Jhotar",
    "gn:population":0,
    "gn:timezone":"Asia/Kolkata",
    "iso:country":"IN",
    "ks:ks_alt_nam":"JHOTAR",
    "ks:ks_name":"Jhotar",
    "ks:ks_pop":3337,
    "ks:ks_type":"HABITATION",
    "name:eng_x_preferred":[
        "Jhotar"
    ],
    "wof:name":"Jhotar",
    "wof:placetype":"locality",
    "wof:population":3337
},
  "geometry": {"coordinates":[83.67993300000001,24.115832],"type":"Point"}
}