{
  "type": "Feature",
  "properties": {
    "iso:country":"IN",
    "ks:ks_name":"Makarampur",
    "ks:ks_pop":93,
    "ks:ks_type":"VILLAGE",
    "name:eng_x_preferred":[
        "Makarampur"
    ],
    "wof:name":"Makarampur",
    "wof:placetype":"locality",
    "wof:population":93
},
  "geometry": {"coordinates":[86.16459,20.297643],"type":"Point"}
}