{
  "type": "Feature",
  "properties": {
    "iso:country":"IN",
    "ks:ks_name":"Krishnanagar",
    "ks:ks_pop":213,
    "ks:ks_type":"VILLAGE",
    "ks:ks_uagg_main":0,
    "name:eng_x_preferred":[
        "Krishnanagar"
    ],
    "wof:name":"Krishnanagar",
    "wof:placetype":"neighbourhood",
    "wof:population":213
},
  "geometry": {"coordinates":[87.027822,23.210899],"type":"Point"}
}