{
  "type": "Feature",
  "properties": {
    "iso:country":"IN",
    "ks:ks_name":"Parbatta Diara",
    "ks:ks_pop":550,
    "ks:ks_type":"HABITATION",
    "name:eng_x_preferred":[
        "Parbatta Diara"
    ],
    "wof:name":"Parbatta Diara",
    "wof:placetype":"locality",
    "wof:population":550
},
  "geometry": {"coordinates":[87.046395,25.304184],"type":"Point"}
}