{
  "type": "Feature",
  "properties": {
    "gn:admin1_code":"38",
    "gn:admin2_code":"346.0",
    "gn:asciiname":"Marchaiya",
    "gn:country_code":"IN",
    "gn:dem":357,
    "gn:feature_class":"P",
    "gn:feature_code":"PPL",
    "gn:name":"March\u0101iya",
    "gn:population":0,
    "gn:timezone":"Asia/Kolkata",
    "iso:country":"IN",
    "ks:ks_name":"Marchai",
    "ks:ks_pop":2066,
    "ks:ks_type":"VILLAGE",
    "name:eng_x_preferred":[
        "Marchai"
    ],
    "name:eng_x_variant":[
        "Marchaiya"
    ],
    "wof:name":"Marchai",
    "wof:placetype":"locality",
    "wof:population":2066
},
  "geometry": {"coordinates":[83.493971,24.128822],"type":"Point"}
}