{
  "type": "Feature",
  "properties": {
    "gn:admin1_code":"36",
    "gn:admin2_code":"180.0",
    "gn:asciiname":"Rehwa Mansur",
    "gn:country_code":"IN",
    "gn:dem":121,
    "gn:feature_class":"P",
    "gn:feature_code":"PPL",
    "gn:name":"Rehwa Mans\u016br",
    "gn:population":0,
    "gn:timezone":"Asia/Kolkata",
    "iso:country":"IN",
    "ks:ks_name":"Rehuya Mansur",
    "ks:ks_pop":3148,
    "ks:ks_type":"VILLAGE",
    "name:eng_x_preferred":[
        "Rehuya Mansur"
    ],
    "name:eng_x_variant":[
        "Rehwa Mansur"
    ],
    "wof:name":"Rehuya Mansur",
    "wof:placetype":"locality",
    "wof:population":3148
},
  "geometry": {"coordinates":[81.450512,27.622963],"type":"Point"}
}