{
  "type": "Feature",
  "properties": {
    "iso:country":"IN",
    "ks:ks_name":"Wadala",
    "ks:ks_pop":19,
    "ks:ks_type":"VILLAGE",
    "name:eng_x_preferred":[
        "Wadala"
    ],
    "wof:name":"Wadala",
    "wof:placetype":"locality",
    "wof:population":19
},
  "geometry": {"coordinates":[77.10063700000001,20.580347],"type":"Point"}
}