{
  "type": "Feature",
  "properties": {
    "iso:country":"IN",
    "ks:ks_name":"Eturu Malawada",
    "ks:ks_pop":193,
    "ks:ks_type":"HABITATION",
    "name:eng_x_preferred":[
        "Eturu Malawada"
    ],
    "wof:name":"Eturu Malawada",
    "wof:placetype":"locality",
    "wof:population":193
},
  "geometry": {"coordinates":[78.69818600000001,14.633622],"type":"Point"}
}