{
  "type": "Feature",
  "properties": {
    "iso:country":"IN",
    "ks:ks_name":"Ambyachapada",
    "ks:ks_pop":225,
    "ks:ks_type":"HABITATION",
    "name:eng_x_preferred":[
        "Ambyachapada"
    ],
    "wof:name":"Ambyachapada",
    "wof:placetype":"locality",
    "wof:population":225
},
  "geometry": {"coordinates":[73.131477,19.943037],"type":"Point"}
}