{
  "type": "Feature",
  "properties": {
    "gn:admin1_code":"35.0",
    "gn:admin2_code":"418.0",
    "gn:asciiname":"Dhoti",
    "gn:country_code":"IN",
    "gn:dem":232,
    "gn:feature_class":"P",
    "gn:feature_code":"PPL",
    "gn:name":"Dhoti",
    "gn:population":0,
    "gn:timezone":"Asia/Kolkata",
    "iso:country":"IN",
    "name:ben_x_preferred":[
        "\u09a7\u09c1\u09a4\u09bf"
    ],
    "name:deu_x_preferred":[
        "Dhoti"
    ],
    "name:dsb_x_preferred":[
        "Dhoti"
    ],
    "name:eus_x_preferred":[
        "Dhoti"
    ],
    "name:fra_x_preferred":[
        "Dhoti"
    ],
    "name:guj_x_preferred":[
        "\u0aa7\u0acb\u0aa4\u0ac0\u0aaf\u0ac1\u0a82"
    ],
    "name:hin_x_preferred":[
        "\u0927\u094b\u0924\u0940"
    ],
    "name:ind_x_preferred":[
        "Dhoti"
    ],
    "name:ita_x_preferred":[
        "Dhoti"
    ],
    "name:jpn_x_preferred":[
        "\u30c9\u30a6\u30c6\u30a3"
    ],
    "name:kat_x_preferred":[
        "\u10d3\u10f0\u10dd\u10e2\u10d8"
    ],
    "name:lit_x_preferred":[
        "Dhotis"
    ],
    "name:mar_x_preferred":[
        "\u0927\u094b\u0924\u0930"
    ],
    "name:msa_x_preferred":[
        "Dhoti"
    ],
    "name:nld_x_preferred":[
        "Dhoti"
    ],
    "name:nno_x_preferred":[
        "Dhoti"
    ],
    "name:nor_x_preferred":[
        "Dhoti"
    ],
    "name:ori_x_preferred":[
        "\u0b27\u0b4b\u0b24\u0b3f"
    ],
    "name:pol_x_preferred":[
        "Dhoti"
    ],
    "name:por_x_preferred":[
        "Dhoti"
    ],
    "name:rus_x_preferred":[
        "\u0414\u0445\u043e\u0442\u0438"
    ],
    "name:spa_x_preferred":[
        "Dhoti"
    ],
    "name:swe_x_preferred":[
        "Dhoti"
    ],
    "name:tam_x_preferred":[
        "\u0bb5\u0bc7\u0b9f\u0bcd\u0b9f\u0bbf"
    ],
    "name:tel_x_preferred":[
        "\u0c2a\u0c02\u0c1a\u0c46"
    ],
    "name:ukr_x_preferred":[
        "\u0414\u0445\u043e\u0442\u0456"
    ],
    "name:urd_x_preferred":[
        "\u062f\u06be\u0648\u062a\u06cc"
    ],
    "name:vie_x_preferred":[
        "Dhoti"
    ],
    "name:xmf_x_preferred":[
        "\u10d3\u10f0\u10dd\u10e2\u10d8"
    ],
    "wof:name":"Dhoti",
    "wof:placetype":"locality"
},
  "geometry": {"coordinates":[76.59241999999998,25.66829],"type":"Point"}
}