{
  "type": "Feature",
  "properties": {
    "iso:country":"IN",
    "ks:ks_name":"Faial Rubber Estate Rd",
    "ks:ks_pop":475,
    "ks:ks_type":"HABITATION",
    "name:eng_x_preferred":[
        "Faial Rubber Estate Rd"
    ],
    "wof:name":"Faial Rubber Estate Rd",
    "wof:placetype":"locality",
    "wof:population":475
},
  "geometry": {"coordinates":[76.454576,10.70285],"type":"Point"}
}