{
  "type": "Feature",
  "properties": {
    "iso:country":"IN",
    "ks:ks_name":"Mathna Malik Urf Mathna Bhim",
    "ks:ks_pop":4239,
    "ks:ks_type":"VILLAGE",
    "name:eng_x_preferred":[
        "Mathna Malik Urf Mathna Bhim"
    ],
    "wof:name":"Mathna Malik Urf Mathna Bhim",
    "wof:placetype":"locality",
    "wof:population":4239
},
  "geometry": {"coordinates":[85.42650500000001,25.933324],"type":"Point"}
}