{
  "type": "Feature",
  "properties": {
    "iso:country":"IN",
    "ks:ks_name":"Raniatari",
    "ks:ks_pop":226,
    "ks:ks_type":"HABITATION",
    "name:eng_x_preferred":[
        "Raniatari"
    ],
    "wof:name":"Raniatari",
    "wof:placetype":"locality",
    "wof:population":226
},
  "geometry": {"coordinates":[82.27053100000001,22.832859],"type":"Point"}
}