{
  "type": "Feature",
  "properties": {
    "gn:admin1_code":"36",
    "gn:admin2_code":"179.0",
    "gn:asciiname":"Faridipur",
    "gn:country_code":"IN",
    "gn:dem":101,
    "gn:feature_class":"P",
    "gn:feature_code":"PPL",
    "gn:name":"Far\u012bdipur",
    "gn:population":0,
    "gn:timezone":"Asia/Kolkata",
    "iso:country":"IN",
    "ks:ks_alt_nam":"Far\u012bdipur",
    "ks:ks_name":"Faridipur",
    "ks:ks_type":"VILLAGE",
    "ks:ks_uagg_main":0,
    "name:eng_x_preferred":[
        "Faridipur"
    ],
    "name:eng_x_variant":[
        "Far\u012bdipur"
    ],
    "wof:name":"Faridipur",
    "wof:placetype":"neighbourhood"
},
  "geometry": {"coordinates":[82.12707,26.310107],"type":"Point"}
}