{
  "type": "Feature",
  "properties": {
    "gn:admin1_code":"2.0",
    "gn:admin2_code":"554.0",
    "gn:asciiname":"Sriramapuram",
    "gn:country_code":"IN",
    "gn:dem":91,
    "gn:feature_class":"P",
    "gn:feature_code":"PPL",
    "gn:name":"Sr\u012br\u0101m\u0101puram",
    "gn:population":0,
    "gn:timezone":"Asia/Kolkata",
    "iso:country":"IN",
    "name:bpy_x_preferred":[
        "\u09b6\u09cd\u09b0\u09c0\u09b0\u09be\u09ae\u09aa\u09c1\u09b0\u09ae"
    ],
    "name:ita_x_preferred":[
        "Sriramapuram"
    ],
    "name:msa_x_preferred":[
        "Sriramapuram"
    ],
    "name:nld_x_preferred":[
        "Sriramapuram"
    ],
    "name:por_x_preferred":[
        "Sriramapuram"
    ],
    "name:tam_x_preferred":[
        "\u0bb8\u0bcd\u0bb0\u0bc0\u0bb0\u0bbe\u0bae\u0baa\u0bc1\u0bb0\u0bae\u0bcd"
    ],
    "name:vie_x_preferred":[
        "Sriramapuram"
    ],
    "name:zho_x_preferred":[
        "\u65af\u91cc\u62c9\u9a6c\u666e\u62c9\u59c6"
    ],
    "wof:name":"Sriramapuram",
    "wof:placetype":"locality"
},
  "geometry": {"coordinates":[79.71023000000002,13.42088],"type":"Point"}
}