{
  "type": "Feature",
  "properties": {
    "iso:country":"IN",
    "qs:name":"Hiramanpur",
    "qs:name_adm0":"India",
    "qs:name_adm1":"Uttar Pradesh",
    "qs:photos":122,
    "qs:photos_1k":25,
    "qs:photos_9k":1,
    "qs:photos_9r":3,
    "qs:photos_all":122,
    "qs:photos_sr":3,
    "qs:placetype":"Town",
    "qs:pop_sr":"0",
    "wof:name":"Hiramanpur",
    "wof:placetype":"neighbourhood"
},
  "geometry": {"coordinates":[83.024389,25.380827],"type":"Point"}
}