{
  "type": "Feature",
  "properties": {
    "gn:admin1_code":"23",
    "gn:admin2_code":"38.0",
    "gn:asciiname":"Mahal",
    "gn:country_code":"IN",
    "gn:dem":260,
    "gn:feature_class":"P",
    "gn:feature_code":"PPL",
    "gn:name":"Mahal",
    "gn:population":0,
    "gn:timezone":"Asia/Kolkata",
    "iso:country":"IN",
    "name:ceb_x_preferred":[
        "Mahal"
    ],
    "name:deu_x_preferred":[
        "Mahal"
    ],
    "name:fra_x_preferred":[
        "Mahal"
    ],
    "name:ita_x_preferred":[
        "Mahal"
    ],
    "name:jpn_x_preferred":[
        "\u30de\u30cf\u30eb"
    ],
    "name:swe_x_preferred":[
        "Mahal"
    ],
    "wof:name":"Mahal",
    "wof:placetype":"locality"
},
  "geometry": {"coordinates":[75.9387,31.33252],"type":"Point"}
}