{
  "type": "Feature",
  "properties": {
    "iso:country":"IN",
    "ks:ks_name":"Kotwar Para",
    "ks:ks_pop":90,
    "ks:ks_type":"HABITATION",
    "name:eng_x_preferred":[
        "Kotwar Para"
    ],
    "wof:name":"Kotwar Para",
    "wof:placetype":"locality",
    "wof:population":90
},
  "geometry": {"coordinates":[81.428758,19.383683],"type":"Point"}
}