{
  "type": "Feature",
  "properties": {
    "gn:admin1_code":"10.0",
    "gn:admin2_code":"084",
    "gn:asciiname":"Kharkhari",
    "gn:country_code":"IN",
    "gn:dem":301,
    "gn:feature_class":"P",
    "gn:feature_code":"PPL",
    "gn:name":"Kharkhari",
    "gn:population":0,
    "gn:timezone":"Asia/Kolkata",
    "iso:country":"IN",
    "wof:name":"Kharkhari",
    "wof:placetype":"locality"
},
  "geometry": {"coordinates":[76.00906999999999,28.38339],"type":"Point"}
}