{
  "type": "Feature",
  "properties": {
    "iso:country":"IN",
    "ks:ks_name":"Amragohal",
    "ks:ks_pop":2488,
    "ks:ks_type":"HABITATION",
    "name:eng_x_preferred":[
        "Amragohal"
    ],
    "wof:name":"Amragohal",
    "wof:placetype":"locality",
    "wof:population":2488
},
  "geometry": {"coordinates":[87.751231,22.36663],"type":"Point"}
}