{
  "type": "Feature",
  "properties": {
    "iso:country":"IN",
    "ks:ks_name":"Chouka Beragi",
    "ks:ks_pop":5,
    "ks:ks_type":"VILLAGE",
    "name:eng_x_preferred":[
        "Chouka Beragi"
    ],
    "wof:name":"Chouka Beragi",
    "wof:placetype":"locality",
    "wof:population":5
},
  "geometry": {"coordinates":[78.417856,23.471106],"type":"Point"}
}