{
  "type": "Feature",
  "properties": {
    "iso:country":"IN",
    "ks:ks_name":"Lakshmipura",
    "ks:ks_pop":250,
    "ks:ks_type":"HABITATION",
    "name:eng_x_preferred":[
        "Lakshmipura"
    ],
    "wof:name":"Lakshmipura",
    "wof:placetype":"locality",
    "wof:population":250
},
  "geometry": {"coordinates":[76.56028999999999,12.845483],"type":"Point"}
}