{
  "type": "Feature",
  "properties": {
    "iso:country":"IN",
    "ks:ks_name":"Debnath Para",
    "ks:ks_pop":825,
    "ks:ks_type":"HABITATION",
    "ks:ks_uagg_main":0,
    "name:eng_x_preferred":[
        "Debnath Para"
    ],
    "wof:name":"Debnath Para",
    "wof:placetype":"neighbourhood",
    "wof:population":825
},
  "geometry": {"coordinates":[89.487345,26.230994],"type":"Point"}
}