{
  "type": "Feature",
  "properties": {
    "iso:country":"IN",
    "ks:ks_name":"Nawali",
    "ks:ks_pop":5,
    "ks:ks_type":"VILLAGE",
    "name:eng_x_preferred":[
        "Nawali"
    ],
    "wof:name":"Nawali",
    "wof:placetype":"locality",
    "wof:population":5
},
  "geometry": {"coordinates":[79.630242,29.781775],"type":"Point"}
}