{
  "type": "Feature",
  "properties": {
    "gn:admin1_code":"34.0",
    "gn:admin2_code":"238",
    "gn:asciiname":"Dulampur",
    "gn:country_code":"IN",
    "gn:dem":319,
    "gn:feature_class":"P",
    "gn:feature_code":"PPL",
    "gn:name":"Dulampur",
    "gn:population":0,
    "gn:timezone":"Asia/Kolkata",
    "iso:country":"IN",
    "ks:ks_alt_nam":"dulampur",
    "ks:ks_name":"Dulampur",
    "ks:ks_pop":900,
    "ks:ks_type":"HABITATION",
    "name:eng_x_preferred":[
        "Dulampur"
    ],
    "wof:name":"Dulampur",
    "wof:placetype":"locality",
    "wof:population":900
},
  "geometry": {"coordinates":[86.43973699999999,24.412224],"type":"Point"}
}