{
  "type": "Feature",
  "properties": {
    "gn:admin1_code":"11.0",
    "gn:admin2_code":"32.0",
    "gn:asciiname":"Lafyog Tikri",
    "gn:country_code":"IN",
    "gn:dem":965,
    "gn:feature_class":"P",
    "gn:feature_code":"PPL",
    "gn:name":"Lafyog Tikri",
    "gn:population":0,
    "gn:timezone":"Asia/Kolkata",
    "iso:country":"IN",
    "wof:name":"Lafyog Tikri",
    "wof:placetype":"locality"
},
  "geometry": {"coordinates":[77.11214,30.74941],"type":"Point"}
}