{
  "type": "Feature",
  "properties": {
    "gn:admin1_code":"19.0",
    "gn:admin2_code":"576.0",
    "gn:asciiname":"Hosuru",
    "gn:country_code":"IN",
    "gn:dem":932,
    "gn:feature_class":"P",
    "gn:feature_code":"PPLL",
    "gn:name":"Hosuru",
    "gn:population":0,
    "gn:timezone":"Asia/Kolkata",
    "iso:country":"IN",
    "wof:name":"Hosuru",
    "wof:placetype":"locality"
},
  "geometry": {"coordinates":[75.91498,12.21949],"type":"Point"}
}