{
  "type": "Feature",
  "properties": {
    "iso:country":"IN",
    "ks:ks_name":"Mena Faliya",
    "ks:ks_pop":896,
    "ks:ks_type":"HABITATION",
    "name:eng_x_preferred":[
        "Mena Faliya"
    ],
    "wof:name":"Mena Faliya",
    "wof:placetype":"locality",
    "wof:population":896
},
  "geometry": {"coordinates":[73.98608299999999,23.242472],"type":"Point"}
}