{
  "type": "Feature",
  "properties": {
    "gn:admin1_code":"35",
    "gn:admin2_code":"463.0",
    "gn:asciiname":"Diyagarai",
    "gn:country_code":"IN",
    "gn:dem":416,
    "gn:feature_class":"P",
    "gn:feature_code":"PPL",
    "gn:name":"Diy\u0101garai",
    "gn:population":0,
    "gn:timezone":"Asia/Kolkata",
    "iso:country":"IN",
    "ks:ks_name":"Diyagadai",
    "ks:ks_pop":1476,
    "ks:ks_type":"VILLAGE",
    "name:eng_x_preferred":[
        "Diyagadai"
    ],
    "name:eng_x_variant":[
        "Diyagarai"
    ],
    "wof:name":"Diyagadai",
    "wof:placetype":"locality",
    "wof:population":1476
},
  "geometry": {"coordinates":[82.24446500000001,24.08072],"type":"Point"}
}