{
  "type": "Feature",
  "properties": {
    "iso:country":"IN",
    "ks:ks_name":"Ajmpat Nes",
    "ks:ks_pop":220,
    "ks:ks_type":"HABITATION",
    "name:eng_x_preferred":[
        "Ajmpat Nes"
    ],
    "wof:name":"Ajmpat Nes",
    "wof:placetype":"locality",
    "wof:population":220
},
  "geometry": {"coordinates":[69.742639,21.811056],"type":"Point"}
}