{
  "type": "Feature",
  "properties": {
    "iso:country":"IN",
    "ks:ks_name":"Siswara",
    "ks:ks_pop":381,
    "ks:ks_type":"HABITATION",
    "name:eng_x_preferred":[
        "Siswara"
    ],
    "wof:name":"Siswara",
    "wof:placetype":"locality",
    "wof:population":381
},
  "geometry": {"coordinates":[81.90402,27.570527],"type":"Point"}
}