{
  "type": "Feature",
  "properties": {
    "gn:admin1_code":"11.0",
    "gn:admin2_code":"32.0",
    "gn:asciiname":"Chiyanra",
    "gn:country_code":"IN",
    "gn:dem":1559,
    "gn:feature_class":"P",
    "gn:feature_code":"PPL",
    "gn:name":"Chiy\u0101nra",
    "gn:population":0,
    "gn:timezone":"Asia/Kolkata",
    "iso:country":"IN",
    "wof:name":"Chiyanra",
    "wof:placetype":"locality"
},
  "geometry": {"coordinates":[77.43439000000002,30.66187],"type":"Point"}
}