{
  "type": "Feature",
  "properties": {
    "gn:admin1_code":"19.0",
    "gn:admin2_code":"569.0",
    "gn:asciiname":"Mulladka",
    "gn:country_code":"IN",
    "gn:dem":39,
    "gn:feature_class":"P",
    "gn:feature_code":"PPLL",
    "gn:name":"Mulladka",
    "gn:population":0,
    "gn:timezone":"Asia/Kolkata",
    "iso:country":"IN",
    "ks:ks_name":"Mulladka",
    "ks:ks_pop":369,
    "ks:ks_type":"VILLAGE",
    "name:eng_x_preferred":[
        "Mulladka"
    ],
    "wof:name":"Mulladka",
    "wof:placetype":"locality",
    "wof:population":369
},
  "geometry": {"coordinates":[74.868167,13.143334],"type":"Point"}
}