{
  "type": "Feature",
  "properties": {
    "iso:country":"IN",
    "ks:ks_name":"Karkona",
    "ks:ks_pop":86,
    "ks:ks_type":"VILLAGE",
    "name:eng_x_preferred":[
        "Karkona"
    ],
    "wof:name":"Karkona",
    "wof:placetype":"locality",
    "wof:population":86
},
  "geometry": {"coordinates":[83.41367200000001,19.453588],"type":"Point"}
}