{
  "type": "Feature",
  "properties": {
    "gn:admin1_code":"23.0",
    "gn:admin2_code":"40.0",
    "gn:asciiname":"Sangatpura",
    "gn:country_code":"IN",
    "gn:dem":268,
    "gn:feature_class":"P",
    "gn:feature_code":"PPL",
    "gn:name":"Sangatpura",
    "gn:population":0,
    "gn:timezone":"Asia/Kolkata",
    "iso:country":"IN",
    "wof:name":"Sangatpura",
    "wof:placetype":"locality"
},
  "geometry": {"coordinates":[76.25966,30.805],"type":"Point"}
}