{
  "type": "Feature",
  "properties": {
    "iso:country":"IN",
    "ks:ks_name":"Tapor Pathar Gaon",
    "ks:ks_pop":349,
    "ks:ks_type":"HABITATION",
    "name:eng_x_preferred":[
        "Tapor Pathar Gaon"
    ],
    "wof:name":"Tapor Pathar Gaon",
    "wof:placetype":"locality",
    "wof:population":349
},
  "geometry": {"coordinates":[94.82425600000001,27.392474],"type":"Point"}
}