{
  "type": "Feature",
  "properties": {
    "gn:country":"IN",
    "gn:fcode":"LCTY",
    "gn:pop":10000,
    "iso:country":"IN",
    "qs:name":"Rajapuri",
    "qs:photos_9r":0,
    "qs:photos_sr":0,
    "qs:pop_sr":"5",
    "wof:name":"Rajapuri",
    "wof:placetype":"locality",
    "wof:population":10000
},
  "geometry": {"coordinates":[77.05982,28.60683],"type":"Point"}
}