{
  "type": "Feature",
  "properties": {
    "iso:country":"IN",
    "ks:ks_name":"Karinakuri",
    "ks:ks_pop":536,
    "ks:ks_type":"HABITATION",
    "name:eng_x_preferred":[
        "Karinakuri"
    ],
    "wof:name":"Karinakuri",
    "wof:placetype":"locality",
    "wof:population":536
},
  "geometry": {"coordinates":[76.727301,9.459478],"type":"Point"}
}