{
  "type": "Feature",
  "properties": {
    "iso:country":"IN",
    "ks:ks_name":"Valifaliya",
    "ks:ks_pop":299,
    "ks:ks_type":"HABITATION",
    "name:eng_x_preferred":[
        "Valifaliya"
    ],
    "wof:name":"Valifaliya",
    "wof:placetype":"locality",
    "wof:population":299
},
  "geometry": {"coordinates":[73.36659,20.453572],"type":"Point"}
}