{
  "type": "Feature",
  "properties": {
    "iso:country":"IN",
    "ks:ks_name":"Purbo Hafanirgool",
    "ks:ks_pop":324,
    "ks:ks_type":"HABITATION",
    "name:eng_x_preferred":[
        "Purbo Hafanirgool"
    ],
    "wof:name":"Purbo Hafanirgool",
    "wof:placetype":"locality",
    "wof:population":324
},
  "geometry": {"coordinates":[92.31904400000001,24.668578],"type":"Point"}
}