{
  "type": "Feature",
  "properties": {
    "iso:country":"IN",
    "ks:ks_name":"Swarka",
    "ks:ks_type":"VILLAGE",
    "name:eng_x_preferred":[
        "Swarka"
    ],
    "wof:name":"Swarka",
    "wof:placetype":"locality"
},
  "geometry": {"coordinates":[79.254122,30.273589],"type":"Point"}
}