{
  "type": "Feature",
  "properties": {
    "gn:admin1_code":"39.0",
    "gn:admin2_code":"065",
    "gn:asciiname":"Devidhura",
    "gn:country_code":"IN",
    "gn:dem":1947,
    "gn:feature_class":"P",
    "gn:feature_code":"PPL",
    "gn:name":"Devidhura",
    "gn:population":0,
    "gn:timezone":"Asia/Kolkata",
    "iso:country":"IN",
    "ks:ks_name":"Devidhura",
    "ks:ks_type":"VILLAGE",
    "name:eng_x_preferred":[
        "Devidhura"
    ],
    "name:und_x_variant":[
        "Devi Dhura"
    ],
    "wof:name":"Devidhura",
    "wof:placetype":"locality"
},
  "geometry": {"coordinates":[79.86344099999999,29.415843],"type":"Point"}
}