{
  "type": "Feature",
  "properties": {
    "iso:country":"IN",
    "ks:ks_name":"Valiyaparambu Jn",
    "ks:ks_pop":1146,
    "ks:ks_type":"HABITATION",
    "name:eng_x_preferred":[
        "Valiyaparambu Jn"
    ],
    "wof:name":"Valiyaparambu Jn",
    "wof:placetype":"locality",
    "wof:population":1146
},
  "geometry": {"coordinates":[75.948909,11.178259],"type":"Point"}
}