{
  "type": "Feature",
  "properties": {
    "iso:country":"IN",
    "ks:ks_name":"Amli",
    "ks:ks_pop":605,
    "ks:ks_type":"VILLAGE",
    "name:eng_x_preferred":[
        "Amli"
    ],
    "wof:name":"Amli",
    "wof:placetype":"locality",
    "wof:population":605
},
  "geometry": {"coordinates":[73.47324999999999,21.756056],"type":"Point"}
}