{
  "type": "Feature",
  "properties": {
    "iso:country":"IN",
    "ks:ks_name":"Ghanekarwadi",
    "ks:ks_pop":252,
    "ks:ks_type":"HABITATION",
    "name:eng_x_preferred":[
        "Ghanekarwadi"
    ],
    "wof:name":"Ghanekarwadi",
    "wof:placetype":"locality",
    "wof:population":252
},
  "geometry": {"coordinates":[73.493889,17.270833],"type":"Point"}
}