{
  "type": "Feature",
  "properties": {
    "iso:country":"IN",
    "ks:ks_name":"Baron Ka Sher",
    "ks:ks_pop":554,
    "ks:ks_type":"VILLAGE",
    "name:eng_x_preferred":[
        "Baron Ka Sher"
    ],
    "wof:name":"Baron Ka Sher",
    "wof:placetype":"locality",
    "wof:population":554
},
  "geometry": {"coordinates":[73.61657700000001,23.949122],"type":"Point"}
}