{
  "type": "Feature",
  "properties": {
    "iso:country":"IN",
    "ks:ks_name":"Kuidbusu",
    "ks:ks_pop":667,
    "ks:ks_type":"VILLAGE",
    "name:eng_x_preferred":[
        "Kuidbusu"
    ],
    "wof:name":"Kuidbusu",
    "wof:placetype":"locality",
    "wof:population":667
},
  "geometry": {"coordinates":[85.852852,22.505805],"type":"Point"}
}