{
  "type": "Feature",
  "properties": {
    "iso:country":"IN",
    "ks:ks_alt_nam":"CHAMPABARI",
    "ks:ks_name":"Champabari",
    "ks:ks_pop":844,
    "ks:ks_type":"HABITATION",
    "name:eng_x_preferred":[
        "Champabari"
    ],
    "wof:name":"Champabari",
    "wof:placetype":"locality",
    "wof:population":844
},
  "geometry": {"coordinates":[92.246634,24.527703],"type":"Point"}
}