{
  "type": "Feature",
  "properties": {
    "gn:admin1_code":"11",
    "gn:admin2_code":"27.0",
    "gn:asciiname":"Chhanwar",
    "gn:country_code":"IN",
    "gn:dem":1145,
    "gn:feature_class":"P",
    "gn:feature_code":"PPL",
    "gn:name":"Chhanw\u0101r",
    "gn:population":0,
    "gn:timezone":"Asia/Kolkata",
    "iso:country":"IN",
    "wof:name":"Chhanwar",
    "wof:placetype":"locality"
},
  "geometry": {"coordinates":[76.93448000000002,31.66823],"type":"Point"}
}