{
  "type": "Feature",
  "properties": {
    "iso:country":"IN",
    "ks:ks_alt_nam":"Changbanda pt II",
    "ks:ks_name":"Changbanda Pt Ii",
    "ks:ks_pop":364,
    "ks:ks_type":"HABITATION",
    "name:eng_x_preferred":[
        "Changbanda Pt Ii"
    ],
    "wof:name":"Changbanda Pt Ii",
    "wof:placetype":"locality",
    "wof:population":364
},
  "geometry": {"coordinates":[90.04948400000001,26.259496],"type":"Point"}
}