{
  "type": "Feature",
  "properties": {
    "gn:admin1_code":"35.0",
    "gn:admin2_code":"447",
    "gn:asciiname":"Kalmesura",
    "gn:country_code":"IN",
    "gn:dem":753,
    "gn:feature_class":"P",
    "gn:feature_code":"PPL",
    "gn:name":"Kalmesura",
    "gn:population":0,
    "gn:timezone":"Asia/Kolkata",
    "iso:country":"IN",
    "wof:name":"Kalmesura",
    "wof:placetype":"neighbourhood"
},
  "geometry": {"coordinates":[78.30568,22.04323],"type":"Point"}
}