{
  "type": "Feature",
  "properties": {
    "iso:country":"IN",
    "ks:ks_name":"Barpukhuri",
    "ks:ks_pop":1670,
    "ks:ks_type":"VILLAGE",
    "ks:ks_uagg_main":0,
    "name:eng_x_preferred":[
        "Barpukhuri"
    ],
    "wof:name":"Barpukhuri",
    "wof:placetype":"locality",
    "wof:population":1670
},
  "geometry": {"coordinates":[92.954024,25.959503],"type":"Point"}
}