{
  "type": "Feature",
  "properties": {
    "iso:country":"IN",
    "ks:ks_name":"Nezampur",
    "ks:ks_pop":422,
    "ks:ks_type":"VILLAGE",
    "ks:ks_uagg_main":0,
    "name:eng_x_preferred":[
        "Nezampur"
    ],
    "wof:name":"Nezampur",
    "wof:placetype":"neighbourhood",
    "wof:population":422
},
  "geometry": {"coordinates":[88.308044,22.884158],"type":"Point"}
}