{
  "type": "Feature",
  "properties": {
    "gn:admin1_code":"37.0",
    "gn:admin2_code":"416",
    "gn:asciiname":"Gogonda",
    "gn:country_code":"IN",
    "gn:dem":659,
    "gn:feature_class":"P",
    "gn:feature_code":"PPL",
    "gn:name":"Gogonda",
    "gn:population":0,
    "gn:timezone":"Asia/Kolkata",
    "iso:country":"IN",
    "ks:ks_name":"Gogunda",
    "ks:ks_pop":359,
    "ks:ks_type":"VILLAGE",
    "name:eng_x_preferred":[
        "Gogunda"
    ],
    "name:eng_x_variant":[
        "Gogonda"
    ],
    "wof:name":"Gogunda",
    "wof:placetype":"locality",
    "wof:population":359
},
  "geometry": {"coordinates":[81.378703,18.374407],"type":"Point"}
}