{
  "type": "Feature",
  "properties": {
    "gn:admin1_code":"37.0",
    "gn:admin2_code":"416",
    "gn:asciiname":"Gogonda",
    "gn:country_code":"IN",
    "gn:dem":659,
    "gn:feature_class":"P",
    "gn:feature_code":"PPL",
    "gn:name":"Gogonda",
    "gn:population":0,
    "gn:timezone":"Asia/Kolkata",
    "iso:country":"IN",
    "wof:name":"Gogonda",
    "wof:placetype":"locality"
},
  "geometry": {"coordinates":[81.37323000000001,18.37497],"type":"Point"}
}