{
  "type": "Feature",
  "properties": {
    "iso:country":"IN",
    "ks:ks_name":"Malahi Chak",
    "ks:ks_pop":85,
    "ks:ks_type":"VILLAGE",
    "ks:ks_uagg_main":0,
    "name:eng_x_preferred":[
        "Malahi Chak"
    ],
    "wof:name":"Malahi Chak",
    "wof:placetype":"neighbourhood",
    "wof:population":85
},
  "geometry": {"coordinates":[84.21403100000001,25.948593],"type":"Point"}
}