{
  "type": "Feature",
  "properties": {
    "gn:admin1_code":"37",
    "gn:admin2_code":"408.0",
    "gn:asciiname":"Badhiatola",
    "gn:country_code":"IN",
    "gn:dem":347,
    "gn:feature_class":"P",
    "gn:feature_code":"PPL",
    "gn:name":"Badhi\u0101tol\u0101",
    "gn:population":0,
    "gn:timezone":"Asia/Kolkata",
    "iso:country":"IN",
    "ks:ks_alt_nam":"Badhi\u0101tol\u0101",
    "ks:ks_name":"Badhiatola",
    "ks:ks_type":"VILLAGE",
    "ks:ks_uagg_main":0,
    "name:eng_x_preferred":[
        "Badhiatola"
    ],
    "name:eng_x_variant":[
        "Badhi\u0101tol\u0101"
    ],
    "wof:name":"Badhiatola",
    "wof:placetype":"neighbourhood"
},
  "geometry": {"coordinates":[80.766638,21.179118],"type":"Point"}
}