{
  "type": "Feature",
  "properties": {
    "iso:country":"IN",
    "ks:ks_alt_nam":"Ch\u0101ndpur Kal\u0101n",
    "ks:ks_name":"Chandpur Kalan",
    "ks:ks_type":"VILLAGE",
    "name:eng_x_preferred":[
        "Chandpur Kalan"
    ],
    "name:eng_x_variant":[
        "Ch\u0101ndpur Kal\u0101n"
    ],
    "wof:name":"Chandpur Kalan",
    "wof:placetype":"neighbourhood"
},
  "geometry": {"coordinates":[77.008095,28.752392],"type":"Point"}
}