{
  "type": "Feature",
  "properties": {
    "iso:country":"IN",
    "ks:ks_name":"Siju",
    "ks:ks_pop":1531,
    "ks:ks_type":"VILLAGE",
    "ks:ks_uagg_main":0,
    "name:eng_x_preferred":[
        "Siju"
    ],
    "wof:name":"Siju",
    "wof:placetype":"neighbourhood",
    "wof:population":1531
},
  "geometry": {"coordinates":[86.585757,20.286624],"type":"Point"}
}