{
  "type": "Feature",
  "properties": {
    "gn:admin1_code":"39.0",
    "gn:admin2_code":"57.0",
    "gn:asciiname":"Jhali Kharak",
    "gn:country_code":"IN",
    "gn:dem":2382,
    "gn:feature_class":"P",
    "gn:feature_code":"PPL",
    "gn:name":"Jh\u0101li Kharak",
    "gn:population":0,
    "gn:timezone":"Asia/Kolkata",
    "iso:country":"IN",
    "wof:name":"Jhali Kharak",
    "wof:placetype":"locality"
},
  "geometry": {"coordinates":[79.50558000000002,30.343],"type":"Point"}
}