{
  "type": "Feature",
  "properties": {
    "gn:admin1_code":"35.0",
    "gn:admin2_code":"456.0",
    "gn:asciiname":"Kondra",
    "gn:country_code":"IN",
    "gn:dem":593,
    "gn:feature_class":"P",
    "gn:feature_code":"PPL",
    "gn:name":"Kondra",
    "gn:population":0,
    "gn:timezone":"Asia/Kolkata",
    "iso:country":"IN",
    "ks:ks_name":"Kodra",
    "ks:ks_pop":445,
    "ks:ks_type":"VILLAGE",
    "name:eng_x_preferred":[
        "Kodra"
    ],
    "name:eng_x_variant":[
        "Kondra"
    ],
    "wof:name":"Kodra",
    "wof:placetype":"locality",
    "wof:population":445
},
  "geometry": {"coordinates":[79.394971,22.355769],"type":"Point"}
}