{
  "type": "Feature",
  "properties": {
    "iso:country":"IN",
    "ks:ks_name":"Plotpada",
    "ks:ks_pop":25,
    "ks:ks_type":"HABITATION",
    "name:eng_x_preferred":[
        "Plotpada"
    ],
    "wof:name":"Plotpada",
    "wof:placetype":"locality",
    "wof:population":25
},
  "geometry": {"coordinates":[73.153527,19.710996],"type":"Point"}
}