{
  "type": "Feature",
  "properties": {
    "gn:admin1_code":"35.0",
    "gn:admin2_code":"431.0",
    "gn:asciiname":"Chargawan",
    "gn:country_code":"IN",
    "gn:dem":570,
    "gn:feature_class":"P",
    "gn:feature_code":"PPL",
    "gn:name":"Chargaw\u0101n",
    "gn:population":0,
    "gn:timezone":"Asia/Kolkata",
    "iso:country":"IN",
    "wof:name":"Chargawan",
    "wof:placetype":"locality"
},
  "geometry": {"coordinates":[80.82648,23.28785],"type":"Point"}
}