{
  "type": "Feature",
  "properties": {
    "iso:country":"IN",
    "ks:ks_name":"Foujdarwadi",
    "ks:ks_pop":100,
    "ks:ks_type":"HABITATION",
    "name:eng_x_preferred":[
        "Foujdarwadi"
    ],
    "wof:name":"Foujdarwadi",
    "wof:placetype":"locality",
    "wof:population":100
},
  "geometry": {"coordinates":[73.55098099999999,17.787286],"type":"Point"}
}