{
  "type": "Feature",
  "properties": {
    "iso:country":"IN",
    "ks:ks_name":"Mundasahi",
    "ks:ks_pop":37,
    "ks:ks_type":"VILLAGE",
    "name:eng_x_preferred":[
        "Mundasahi"
    ],
    "wof:name":"Mundasahi",
    "wof:placetype":"locality",
    "wof:population":37
},
  "geometry": {"coordinates":[85.61110100000001,21.153809],"type":"Point"}
}