{
  "type": "Feature",
  "properties": {
    "gn:admin1_code":"34.0",
    "gn:admin2_code":"229.0",
    "gn:asciiname":"Asta",
    "gn:country_code":"IN",
    "gn:dem":57,
    "gn:feature_class":"P",
    "gn:feature_code":"PPL",
    "gn:name":"Asta",
    "gn:population":0,
    "gn:timezone":"Asia/Kolkata",
    "iso:country":"IN",
    "name:deu_x_preferred":[
        "Asta"
    ],
    "name:ita_x_preferred":[
        "Asta"
    ],
    "name:jpn_x_preferred":[
        "\u30a2\u30b9\u30bf"
    ],
    "name:lat_x_preferred":[
        "Asta"
    ],
    "name:nld_x_preferred":[
        "Asta"
    ],
    "name:pol_x_preferred":[
        "Asta"
    ],
    "name:por_x_preferred":[
        "Asta"
    ],
    "name:spa_x_preferred":[
        "Asta"
    ],
    "wof:name":"Asta",
    "wof:placetype":"locality"
},
  "geometry": {"coordinates":[85.41079999999999,25.27842],"type":"Point"}
}