{
  "type": "Feature",
  "properties": {
    "iso:country":"IN",
    "ks:ks_name":"Sekh Tola",
    "ks:ks_pop":925,
    "ks:ks_type":"HABITATION",
    "name:eng_x_preferred":[
        "Sekh Tola"
    ],
    "wof:name":"Sekh Tola",
    "wof:placetype":"locality",
    "wof:population":925
},
  "geometry": {"coordinates":[85.20298,26.496902],"type":"Point"}
}