{
  "type": "Feature",
  "properties": {
    "gn:admin1_code":"12.0",
    "gn:admin2_code":"010",
    "gn:asciiname":"Thuru",
    "gn:country_code":"IN",
    "gn:dem":1594,
    "gn:feature_class":"P",
    "gn:feature_code":"PPL",
    "gn:name":"Th\u016bru",
    "gn:population":0,
    "gn:timezone":"Asia/Kolkata",
    "iso:country":"IN",
    "name:zho_x_preferred":[
        "\u6258\u7f85\u5c71"
    ],
    "wof:name":"Thuru",
    "wof:placetype":"locality"
},
  "geometry": {"coordinates":[74.75176999999999,34.23207],"type":"Point"}
}