{
  "type": "Feature",
  "properties": {
    "gn:admin1_code":"25.0",
    "gn:admin2_code":"608.0",
    "gn:asciiname":"Gudalur",
    "gn:country_code":"IN",
    "gn:dem":237,
    "gn:feature_class":"P",
    "gn:feature_code":"PPL",
    "gn:name":"Gudal\u016br",
    "gn:population":0,
    "gn:timezone":"Asia/Kolkata",
    "iso:country":"IN",
    "ks:ks_alt_nam":"Gudal\u016br",
    "ks:ks_name":"Gudalur",
    "ks:ks_pop":5004,
    "ks:ks_type":"VILLAGE",
    "ks:ks_uagg_main":0,
    "name:bpy_x_preferred":[
        "\u0997\u09c1\u09a6\u09be\u09b2\u09c1\u09b0"
    ],
    "name:ceb_x_preferred":[
        "Gudalur"
    ],
    "name:eng_x_preferred":[
        "Gudalur"
    ],
    "name:eng_x_variant":[
        "Gudal\u016br"
    ],
    "name:ita_x_preferred":[
        "Gudalur"
    ],
    "name:swe_x_preferred":[
        "Gudalur"
    ],
    "wof:name":"Gudalur",
    "wof:placetype":"locality",
    "wof:population":5004
},
  "geometry": {"coordinates":[77.993385,11.535099],"type":"Point"}
}