{
  "type": "Feature",
  "properties": {
    "iso:country":"IN",
    "ks:ks_name":"Mohanpura",
    "ks:ks_pop":157,
    "ks:ks_type":"HABITATION",
    "name:eng_x_preferred":[
        "Mohanpura"
    ],
    "wof:name":"Mohanpura",
    "wof:placetype":"locality",
    "wof:population":157
},
  "geometry": {"coordinates":[73.122573,23.767254],"type":"Point"}
}