{
  "type": "Feature",
  "properties": {
    "gn:admin1_code":"23.0",
    "gn:admin2_code":"45.0",
    "gn:asciiname":"Mandwala",
    "gn:country_code":"IN",
    "gn:dem":211,
    "gn:feature_class":"P",
    "gn:feature_code":"PPL",
    "gn:name":"Mandw\u0101la",
    "gn:population":0,
    "gn:timezone":"Asia/Kolkata",
    "iso:country":"IN",
    "name:ceb_x_preferred":[
        "M\u0101ndavla"
    ],
    "name:swe_x_preferred":[
        "M\u0101ndavla"
    ],
    "wof:name":"Mandwala",
    "wof:placetype":"locality"
},
  "geometry": {"coordinates":[74.86464000000002,30.72588],"type":"Point"}
}