{
  "type": "Feature",
  "properties": {
    "gn:admin1_code":"34.0",
    "gn:admin2_code":"231.0",
    "gn:asciiname":"Tiwaridih",
    "gn:country_code":"IN",
    "gn:dem":82,
    "gn:feature_class":"P",
    "gn:feature_code":"PPL",
    "gn:name":"Tiw\u0101r\u012bdih",
    "gn:population":0,
    "gn:timezone":"Asia/Kolkata",
    "iso:country":"IN",
    "wof:name":"Tiwaridih",
    "wof:placetype":"locality"
},
  "geometry": {"coordinates":[84.36291,25.33392000000001],"type":"Point"}
}