{
  "type": "Feature",
  "properties": {
    "gn:admin1_code":"35",
    "gn:admin2_code":"462.0",
    "gn:asciiname":"Jamua",
    "gn:country_code":"IN",
    "gn:dem":374,
    "gn:feature_class":"P",
    "gn:feature_code":"PPL",
    "gn:name":"Jamua",
    "gn:population":0,
    "gn:timezone":"Asia/Kolkata",
    "iso:country":"IN",
    "ks:ks_name":"Jamua",
    "ks:ks_pop":2586,
    "ks:ks_type":"VILLAGE",
    "name:eng_x_preferred":[
        "Jamua"
    ],
    "wof:name":"Jamua",
    "wof:placetype":"locality",
    "wof:population":2586
},
  "geometry": {"coordinates":[81.72200599999999,24.150532],"type":"Point"}
}