{
  "type": "Feature",
  "properties": {
    "iso:country":"IN",
    "ks:ks_name":"Rooppuriya",
    "ks:ks_pop":217,
    "ks:ks_type":"VILLAGE",
    "name:eng_x_preferred":[
        "Rooppuriya"
    ],
    "wof:name":"Rooppuriya",
    "wof:placetype":"locality",
    "wof:population":217
},
  "geometry": {"coordinates":[74.76011200000001,23.857674],"type":"Point"}
}