{
  "type": "Feature",
  "properties": {
    "iso:country":"IN",
    "ks:ks_name":"Misran Dera",
    "ks:ks_pop":180,
    "ks:ks_type":"HABITATION",
    "name:eng_x_preferred":[
        "Misran Dera"
    ],
    "wof:name":"Misran Dera",
    "wof:placetype":"locality",
    "wof:population":180
},
  "geometry": {"coordinates":[80.888499,25.707343],"type":"Point"}
}