{
  "type": "Feature",
  "properties": {
    "gn:admin1_code":"36",
    "gn:admin2_code":"156.0",
    "gn:asciiname":"Putua Khera",
    "gn:country_code":"IN",
    "gn:dem":123,
    "gn:feature_class":"P",
    "gn:feature_code":"PPL",
    "gn:name":"Putua Khera",
    "gn:population":0,
    "gn:timezone":"Asia/Kolkata",
    "iso:country":"IN",
    "wof:name":"Putua Khera",
    "wof:placetype":"locality"
},
  "geometry": {"coordinates":[80.76349999999999,26.19127000000001],"type":"Point"}
}