{
  "type": "Feature",
  "properties": {
    "iso:country":"IN",
    "ks:ks_name":"Talabahalunda",
    "ks:ks_pop":905,
    "ks:ks_type":"VILLAGE",
    "ks:ks_uagg_main":0,
    "name:eng_x_preferred":[
        "Talabahalunda"
    ],
    "wof:name":"Talabahalunda",
    "wof:placetype":"neighbourhood",
    "wof:population":905
},
  "geometry": {"coordinates":[85.385947,20.782448],"type":"Point"}
}