{
  "type": "Feature",
  "properties": {
    "iso:country":"IN",
    "ks:ks_name":"Bandagudisalu",
    "ks:ks_pop":11,
    "ks:ks_type":"HABITATION",
    "name:eng_x_preferred":[
        "Bandagudisalu"
    ],
    "wof:name":"Bandagudisalu",
    "wof:placetype":"locality",
    "wof:population":11
},
  "geometry": {"coordinates":[82.410319,18.056565],"type":"Point"}
}