{
  "type": "Feature",
  "properties": {
    "iso:country":"IN",
    "ks:ks_name":"Ballekatte",
    "ks:ks_pop":204,
    "ks:ks_type":"VILLAGE",
    "ks:ks_uagg_main":0,
    "name:eng_x_preferred":[
        "Ballekatte"
    ],
    "wof:name":"Ballekatte",
    "wof:placetype":"neighbourhood",
    "wof:population":204
},
  "geometry": {"coordinates":[76.69319400000001,13.201871],"type":"Point"}
}