{
  "type": "Feature",
  "properties": {
    "iso:country":"IN",
    "ks:ks_alt_nam":"jamua",
    "ks:ks_name":"Jamua",
    "ks:ks_pop":552,
    "ks:ks_type":"HABITATION",
    "name:eng_x_preferred":[
        "Jamua"
    ],
    "wof:name":"Jamua",
    "wof:placetype":"locality",
    "wof:population":552
},
  "geometry": {"coordinates":[86.753394,24.366728],"type":"Point"}
}