{
  "type": "Feature",
  "properties": {
    "iso:country":"IN",
    "ks:ks_name":"Kansemari",
    "ks:ks_pop":0,
    "ks:ks_type":"VILLAGE",
    "name:eng_x_preferred":[
        "Kansemari"
    ],
    "wof:name":"Kansemari",
    "wof:placetype":"locality",
    "wof:population":0
},
  "geometry": {"coordinates":[80.492479,25.582686],"type":"Point"}
}