{
  "type": "Feature",
  "properties": {
    "gn:admin1_code":"34.0",
    "gn:admin2_code":"236.0",
    "gn:asciiname":"Satiar",
    "gn:country_code":"IN",
    "gn:dem":187,
    "gn:feature_class":"P",
    "gn:feature_code":"PPL",
    "gn:name":"Sati\u0101r",
    "gn:population":0,
    "gn:timezone":"Asia/Kolkata",
    "iso:country":"IN",
    "name:ara_x_preferred":[
        "\u0633\u0627\u0637\u064a\u0627\u0631"
    ],
    "name:ckb_x_preferred":[
        "\u0633\u0627\u062a\u06cc\u0627\u0631"
    ],
    "name:fas_x_preferred":[
        "\u0633\u0627\u0637\u06cc\u0627\u0631"
    ],
    "wof:name":"Satiar",
    "wof:placetype":"neighbourhood"
},
  "geometry": {"coordinates":[84.57482,24.47936],"type":"Point"}
}