{
  "type": "Feature",
  "properties": {
    "gn:admin1_code":"35",
    "gn:admin2_code":"443.0",
    "gn:asciiname":"Arnot",
    "gn:country_code":"IN",
    "gn:dem":406,
    "gn:feature_class":"P",
    "gn:feature_code":"PPL",
    "gn:name":"Arnot",
    "gn:population":0,
    "gn:timezone":"Asia/Kolkata",
    "iso:country":"IN",
    "name:ceb_x_preferred":[
        "Arnot"
    ],
    "name:deu_x_preferred":[
        "Arnot"
    ],
    "name:swe_x_preferred":[
        "Arnot"
    ],
    "wof:name":"Arnot",
    "wof:placetype":"locality"
},
  "geometry": {"coordinates":[77.97296,24.00064],"type":"Point"}
}