{
  "type": "Feature",
  "properties": {
    "iso:country":"IN",
    "ks:ks_name":"Kandhabadabhuin",
    "ks:ks_pop":88,
    "ks:ks_type":"VILLAGE",
    "name:eng_x_preferred":[
        "Kandhabadabhuin"
    ],
    "wof:name":"Kandhabadabhuin",
    "wof:placetype":"locality",
    "wof:population":88
},
  "geometry": {"coordinates":[85.155441,20.498195],"type":"Point"}
}