{
  "type": "Feature",
  "properties": {
    "iso:country":"IN",
    "ks:ks_name":"Manpuradev",
    "ks:ks_pop":1250,
    "ks:ks_type":"HABITATION",
    "name:eng_x_preferred":[
        "Manpuradev"
    ],
    "wof:name":"Manpuradev",
    "wof:placetype":"locality",
    "wof:population":1250
},
  "geometry": {"coordinates":[77.083004,23.740605],"type":"Point"}
}