{
  "type": "Feature",
  "properties": {
    "iso:country":"IN",
    "ks:ks_name":"Jyothinagara Nakre",
    "ks:ks_pop":248,
    "ks:ks_type":"HABITATION",
    "name:eng_x_preferred":[
        "Jyothinagara Nakre"
    ],
    "wof:name":"Jyothinagara Nakre",
    "wof:placetype":"locality",
    "wof:population":248
},
  "geometry": {"coordinates":[74.959478,13.236227],"type":"Point"}
}