{
  "type": "Feature",
  "properties": {
    "gn:admin1_code":"36.0",
    "gn:admin2_code":"155.0",
    "gn:asciiname":"Bhikaripur",
    "gn:country_code":"IN",
    "gn:dem":141,
    "gn:feature_class":"P",
    "gn:feature_code":"PPL",
    "gn:name":"Bhik\u0101ripur",
    "gn:population":0,
    "gn:timezone":"Asia/Kolkata",
    "iso:country":"IN",
    "ks:ks_name":"Bhigharipur",
    "ks:ks_pop":346,
    "ks:ks_type":"HABITATION",
    "name:eng_x_preferred":[
        "Bhigharipur"
    ],
    "name:eng_x_variant":[
        "Bhikaripur"
    ],
    "wof:name":"Bhigharipur",
    "wof:placetype":"locality",
    "wof:population":346
},
  "geometry": {"coordinates":[80.127967,27.189331],"type":"Point"}
}