{
  "type": "Feature",
  "properties": {
    "gn:admin1_code":"19.0",
    "gn:admin2_code":"575.0",
    "gn:asciiname":"Kallur",
    "gn:country_code":"IN",
    "gn:dem":211,
    "gn:feature_class":"P",
    "gn:feature_code":"PPL",
    "gn:name":"Kallur",
    "gn:population":0,
    "gn:timezone":"Asia/Kolkata",
    "iso:country":"IN",
    "name:deu_x_preferred":[
        "Kallur"
    ],
    "name:swe_x_preferred":[
        "Kallur"
    ],
    "wof:name":"Kallur",
    "wof:placetype":"locality"
},
  "geometry": {"coordinates":[75.51694999999999,12.79267],"type":"Point"}
}