{
  "type": "Feature",
  "properties": {
    "gn:admin1_code":"16",
    "gn:admin2_code":"502.0",
    "gn:asciiname":"Jamkhel",
    "gn:country_code":"IN",
    "gn:dem":471,
    "gn:feature_class":"P",
    "gn:feature_code":"PPL",
    "gn:name":"J\u0101mkhel",
    "gn:population":0,
    "gn:timezone":"Asia/Kolkata",
    "iso:country":"IN",
    "wof:name":"Jamkhel",
    "wof:placetype":"locality"
},
  "geometry": {"coordinates":[77.08610999999998,20.27674],"type":"Point"}
}