{
  "type": "Feature",
  "properties": {
    "iso:country":"IN",
    "ks:ks_name":"Alojpur",
    "ks:ks_pop":61,
    "ks:ks_type":"HABITATION",
    "name:eng_x_preferred":[
        "Alojpur"
    ],
    "wof:name":"Alojpur",
    "wof:placetype":"locality",
    "wof:population":61
},
  "geometry": {"coordinates":[78.48030799999999,23.345961],"type":"Point"}
}