{
  "type": "Feature",
  "properties": {
    "iso:country":"IN",
    "ks:ks_name":"Baghiya",
    "ks:ks_pop":104,
    "ks:ks_type":"HABITATION",
    "name:eng_x_preferred":[
        "Baghiya"
    ],
    "wof:name":"Baghiya",
    "wof:placetype":"locality",
    "wof:population":104
},
  "geometry": {"coordinates":[83.494542,27.149847],"type":"Point"}
}