{
  "type": "Feature",
  "properties": {
    "iso:country":"IN",
    "ks:ks_name":"Koodige",
    "ks:ks_pop":55,
    "ks:ks_type":"HABITATION",
    "name:eng_x_preferred":[
        "Koodige"
    ],
    "wof:name":"Koodige",
    "wof:placetype":"locality",
    "wof:population":55
},
  "geometry": {"coordinates":[75.319996,13.528417],"type":"Point"}
}