{
  "type": "Feature",
  "properties": {
    "iso:country":"IN",
    "ks:ks_name":"Mul Falia",
    "ks:ks_pop":368,
    "ks:ks_type":"HABITATION",
    "name:eng_x_preferred":[
        "Mul Falia"
    ],
    "wof:name":"Mul Falia",
    "wof:placetype":"locality",
    "wof:population":368
},
  "geometry": {"coordinates":[73.194917,20.305583],"type":"Point"}
}