{
  "type": "Feature",
  "properties": {
    "iso:country":"IN",
    "ks:ks_name":"Vadadala",
    "ks:ks_pop":897,
    "ks:ks_type":"VILLAGE",
    "ks:ks_uagg_main":1,
    "name:eng_x_preferred":[
        "Vadadala"
    ],
    "wof:name":"Vadadala",
    "wof:placetype":"neighbourhood",
    "wof:population":897
},
  "geometry": {"coordinates":[72.961759,21.110552],"type":"Point"}
}