{
  "type": "Feature",
  "properties": {
    "iso:country":"IN",
    "ks:ks_name":"Karanjvera",
    "ks:ks_pop":370,
    "ks:ks_type":"HABITATION",
    "name:eng_x_preferred":[
        "Karanjvera"
    ],
    "wof:name":"Karanjvera",
    "wof:placetype":"locality",
    "wof:population":370
},
  "geometry": {"coordinates":[73.35847200000001,20.260833],"type":"Point"}
}