{
  "type": "Feature",
  "properties": {
    "iso:country":"IN",
    "ks:ks_name":"Romda",
    "ks:ks_pop":96,
    "ks:ks_type":"HABITATION",
    "name:eng_x_preferred":[
        "Romda"
    ],
    "wof:name":"Romda",
    "wof:placetype":"locality",
    "wof:population":96
},
  "geometry": {"coordinates":[85.46203800000001,22.837344],"type":"Point"}
}