{
  "type": "Feature",
  "properties": {
    "gn:admin1_code":"36",
    "gn:admin2_code":"194.0",
    "gn:asciiname":"Pachrukhi Kalikaprasad",
    "gn:country_code":"IN",
    "gn:dem":89,
    "gn:feature_class":"P",
    "gn:feature_code":"PPL",
    "gn:name":"Pachrukhi K\u0101lik\u0101pras\u0101d",
    "gn:population":0,
    "gn:timezone":"Asia/Kolkata",
    "iso:country":"IN",
    "wof:name":"Pachrukhi Kalikaprasad",
    "wof:placetype":"neighbourhood"
},
  "geometry": {"coordinates":[82.53037999999999,25.50033],"type":"Point"}
}