{
  "type": "Feature",
  "properties": {
    "iso:country":"IN",
    "ks:ks_name":"Bhendi Bazar",
    "ks:ks_pop":210,
    "ks:ks_type":"HABITATION",
    "name:eng_x_preferred":[
        "Bhendi Bazar"
    ],
    "wof:name":"Bhendi Bazar",
    "wof:placetype":"locality",
    "wof:population":210
},
  "geometry": {"coordinates":[73.549722,17.181111],"type":"Point"}
}