{
  "type": "Feature",
  "properties": {
    "iso:country":"IN",
    "ks:ks_name":"Chinnamathampalayam",
    "ks:ks_pop":1250,
    "ks:ks_type":"HABITATION",
    "ks:ks_uagg_main":0,
    "name:eng_x_preferred":[
        "Chinnamathampalayam"
    ],
    "wof:name":"Chinnamathampalayam",
    "wof:placetype":"locality",
    "wof:population":1250
},
  "geometry": {"coordinates":[76.96699099999999,11.206833],"type":"Point"}
}