{
  "type": "Feature",
  "properties": {
    "gn:admin1_code":"31.0",
    "gn:admin2_code":"285.0",
    "gn:asciiname":"Buangpui",
    "gn:country_code":"IN",
    "gn:dem":768,
    "gn:feature_class":"P",
    "gn:feature_code":"PPL",
    "gn:name":"Buangpui",
    "gn:population":0,
    "gn:timezone":"Asia/Kolkata",
    "iso:country":"IN",
    "wof:name":"Buangpui",
    "wof:placetype":"locality"
},
  "geometry": {"coordinates":[92.74554999999999,23.23606],"type":"Point"}
}