{
  "type": "Feature",
  "properties": {
    "gn:admin1_code":"35",
    "gn:admin2_code":"425.0",
    "gn:asciiname":"Luharpura",
    "gn:country_code":"IN",
    "gn:dem":338,
    "gn:feature_class":"P",
    "gn:feature_code":"PPL",
    "gn:name":"Luharpura",
    "gn:population":0,
    "gn:timezone":"Asia/Kolkata",
    "iso:country":"IN",
    "ks:ks_name":"Luharpura",
    "ks:ks_pop":509,
    "ks:ks_type":"HABITATION",
    "name:eng_x_preferred":[
        "Luharpura"
    ],
    "wof:name":"Luharpura",
    "wof:placetype":"locality",
    "wof:population":509
},
  "geometry": {"coordinates":[79.55625999999999,24.428017],"type":"Point"}
}