{
  "type": "Feature",
  "properties": {
    "gn:admin1_code":"35",
    "gn:admin2_code":"430.0",
    "gn:asciiname":"Kota",
    "gn:country_code":"IN",
    "gn:dem":154,
    "gn:feature_class":"P",
    "gn:feature_code":"PPL",
    "gn:name":"Kota",
    "gn:population":0,
    "gn:timezone":"Asia/Kolkata",
    "iso:country":"IN",
    "ks:ks_name":"Kota",
    "ks:ks_pop":856,
    "ks:ks_type":"VILLAGE",
    "name:ara_x_preferred":[
        "\u0643\u0648\u062a\u0627"
    ],
    "name:ben_bn_x_preferred":[
        "\u0995\u09cb\u099f\u09be"
    ],
    "name:ben_in_x_preferred":[
        "\u0995\u09cb\u099f\u09be"
    ],
    "name:bih_x_preferred":[
        "\u0915\u094b\u091f\u093e"
    ],
    "name:bpy_x_preferred":[
        "\u0995\u09cb\u09a4\u09be"
    ],
    "name:cat_x_preferred":[
        "Kota"
    ],
    "name:ceb_x_preferred":[
        "Kota"
    ],
    "name:deu_x_preferred":[
        "Kota"
    ],
    "name:eng_x_preferred":[
        "Kota"
    ],
    "name:fas_x_preferred":[
        "\u06a9\u0648\u062a\u0627"
    ],
    "name:fra_x_preferred":[
        "Kota"
    ],
    "name:guj_x_preferred":[
        "\u0a95\u0acb\u0a9f\u0abe"
    ],
    "name:hin_x_preferred":[
        "\u0915\u094b\u091f\u093e"
    ],
    "name:hun_x_preferred":[
        "Kota"
    ],
    "name:ind_x_preferred":[
        "Kota"
    ],
    "name:ita_x_preferred":[
        "Kota"
    ],
    "name:kan_x_preferred":[
        "\u0c95\u0ccb\u0c9f"
    ],
    "name:lav_x_preferred":[
        "Kota"
    ],
    "name:mal_x_preferred":[
        "\u0d15\u0d4b\u0d1f"
    ],
    "name:mar_x_preferred":[
        "\u0915\u094b\u091f\u093e"
    ],
    "name:msa_x_preferred":[
        "Kota"
    ],
    "name:new_x_preferred":[
        "\u0915\u094b\u0924\u093e"
    ],
    "name:nld_x_preferred":[
        "Kota"
    ],
    "name:pan_x_preferred":[
        "\u0a15\u0a4b\u0a1f\u0a3e"
    ],
    "name:pol_x_preferred":[
        "Kota"
    ],
    "name:pus_x_preferred":[
        "\u06a9\u0648\u062a\u0627"
    ],
    "name:rus_x_preferred":[
        "\u041a\u043e\u0442\u0430"
    ],
    "name:spa_x_preferred":[
        "Kota"
    ],
    "name:swe_x_preferred":[
        "Kota"
    ],
    "name:tam_x_preferred":[
        "\u0b95\u0bcb\u0b9f\u0bcd\u0b9f\u0bbe"
    ],
    "name:tel_x_preferred":[
        "\u0c15\u0c4b\u0c1f\u0c3e"
    ],
    "name:ukr_x_preferred":[
        "\u041a\u043e\u0442\u0430"
    ],
    "name:urd_x_preferred":[
        "\u06a9\u0648\u0679\u0627"
    ],
    "name:vie_x_preferred":[
        "Kota"
    ],
    "wof:name":"Kota",
    "wof:placetype":"locality",
    "wof:population":856
},
  "geometry": {"coordinates":[81.348584,25.075506],"type":"Point"}
}