{
  "type": "Feature",
  "properties": {
    "iso:country":"IN",
    "ks:ks_name":"Naskarpur",
    "ks:ks_pop":738,
    "ks:ks_type":"VILLAGE",
    "ks:ks_uagg_main":0,
    "name:eng_x_preferred":[
        "Naskarpur"
    ],
    "wof:name":"Naskarpur",
    "wof:placetype":"locality",
    "wof:population":738
},
  "geometry": {"coordinates":[87.435551,21.631848],"type":"Point"}
}