{
  "type": "Feature",
  "properties": {
    "iso:country":"IN",
    "ks:ks_name":"Guluguddivalasa",
    "ks:ks_pop":76,
    "ks:ks_type":"HABITATION",
    "name:eng_x_preferred":[
        "Guluguddivalasa"
    ],
    "wof:name":"Guluguddivalasa",
    "wof:placetype":"locality",
    "wof:population":76
},
  "geometry": {"coordinates":[83.10509500000001,18.520542],"type":"Point"}
}