{
  "type": "Feature",
  "properties": {
    "iso:country":"IN",
    "ks:ks_name":"Karjamguda",
    "ks:ks_pop":33,
    "ks:ks_type":"HABITATION",
    "name:eng_x_preferred":[
        "Karjamguda"
    ],
    "wof:name":"Karjamguda",
    "wof:placetype":"locality",
    "wof:population":33
},
  "geometry": {"coordinates":[83.723917,18.802886],"type":"Point"}
}