{
  "type": "Feature",
  "properties": {
    "iso:country":"IN",
    "ks:ks_alt_nam":"Genda bharri",
    "ks:ks_name":"Genda Bharri",
    "ks:ks_pop":53,
    "ks:ks_type":"HABITATION",
    "name:eng_x_preferred":[
        "Genda Bharri"
    ],
    "wof:name":"Genda Bharri",
    "wof:placetype":"locality",
    "wof:population":53
},
  "geometry": {"coordinates":[81.976934,20.237055],"type":"Point"}
}