{
  "type": "Feature",
  "properties": {
    "iso:country":"IN",
    "ks:ks_name":"Berhampur",
    "ks:ks_pop":623,
    "ks:ks_type":"VILLAGE",
    "ks:ks_uagg_main":0,
    "name:eng_x_preferred":[
        "Berhampur"
    ],
    "wof:name":"Berhampur",
    "wof:placetype":"neighbourhood",
    "wof:population":623
},
  "geometry": {"coordinates":[85.678253,21.955071],"type":"Point"}
}