{
  "type": "Feature",
  "properties": {
    "iso:country":"IN",
    "ks:ks_alt_nam":"NICCHE TOLA",
    "ks:ks_name":"Nicche Tola",
    "ks:ks_pop":451,
    "ks:ks_type":"HABITATION",
    "name:eng_x_preferred":[
        "Nicche Tola"
    ],
    "wof:name":"Nicche Tola",
    "wof:placetype":"locality",
    "wof:population":451
},
  "geometry": {"coordinates":[85.786299,22.688964],"type":"Point"}
}