{
  "type": "Feature",
  "properties": {
    "gn:admin1_code":"2.0",
    "gn:admin2_code":"553.0",
    "gn:asciiname":"Maralehalli",
    "gn:country_code":"IN",
    "gn:dem":525,
    "gn:feature_class":"P",
    "gn:feature_code":"PPL",
    "gn:name":"M\u0101ralehalli",
    "gn:population":0,
    "gn:timezone":"Asia/Kolkata",
    "iso:country":"IN",
    "wof:name":"Maralehalli",
    "wof:placetype":"neighbourhood"
},
  "geometry": {"coordinates":[77.18206000000001,14.53055],"type":"Point"}
}