{
  "type": "Feature",
  "properties": {
    "iso:country":"IN",
    "ks:ks_name":"Kolebeda Para",
    "ks:ks_pop":218,
    "ks:ks_type":"HABITATION",
    "name:eng_x_preferred":[
        "Kolebeda Para"
    ],
    "wof:name":"Kolebeda Para",
    "wof:placetype":"locality",
    "wof:population":218
},
  "geometry": {"coordinates":[81.639927,19.342051],"type":"Point"}
}