{
  "type": "Feature",
  "properties": {
    "gn:admin1_code":"10.0",
    "gn:admin2_code":"88.0",
    "gn:asciiname":"Jajru",
    "gn:country_code":"IN",
    "gn:dem":202,
    "gn:feature_class":"P",
    "gn:feature_code":"PPL",
    "gn:name":"Jajru",
    "gn:population":0,
    "gn:timezone":"Asia/Kolkata",
    "iso:country":"IN",
    "wof:name":"Jajru",
    "wof:placetype":"locality"
},
  "geometry": {"coordinates":[77.31199000000002,28.29271],"type":"Point"}
}