{
  "type": "Feature",
  "properties": {
    "iso:country":"IN",
    "ks:ks_alt_nam":"Kandauli KA PURWA",
    "ks:ks_name":"Kandauli Ka Purwa",
    "ks:ks_pop":430,
    "ks:ks_type":"HABITATION",
    "name:eng_x_preferred":[
        "Kandauli Ka Purwa"
    ],
    "wof:name":"Kandauli Ka Purwa",
    "wof:placetype":"locality",
    "wof:population":430
},
  "geometry": {"coordinates":[81.931798,24.977962],"type":"Point"}
}