{
  "type": "Feature",
  "properties": {
    "iso:country":"IN",
    "ks:ks_alt_nam":"HANSAPIRA KHAS",
    "ks:ks_name":"Hansapira Khas",
    "ks:ks_pop":754,
    "ks:ks_type":"HABITATION",
    "name:eng_x_preferred":[
        "Hansapira Khas"
    ],
    "wof:name":"Hansapira Khas",
    "wof:placetype":"locality",
    "wof:population":754
},
  "geometry": {"coordinates":[84.812954,26.119621],"type":"Point"}
}