{
  "type": "Feature",
  "properties": {
    "iso:country":"IN",
    "ks:ks_name":"Baukpur",
    "ks:ks_pop":30,
    "ks:ks_type":"VILLAGE",
    "name:eng_x_preferred":[
        "Baukpur"
    ],
    "wof:name":"Baukpur",
    "wof:placetype":"locality",
    "wof:population":30
},
  "geometry": {"coordinates":[87.43942199999999,22.577196],"type":"Point"}
}