{
  "type": "Feature",
  "properties": {
    "iso:country":"IN",
    "ks:ks_name":"Bankati",
    "ks:ks_pop":413,
    "ks:ks_type":"VILLAGE",
    "name:eng_x_preferred":[
        "Bankati"
    ],
    "wof:name":"Bankati",
    "wof:placetype":"locality",
    "wof:population":413
},
  "geometry": {"coordinates":[87.303207,24.605888],"type":"Point"}
}