{
  "type": "Feature",
  "properties": {
    "gn:admin1_code":"1.0",
    "gn:admin2_code":"638",
    "gn:asciiname":"Kola-rue",
    "gn:country_code":"IN",
    "gn:dem":22,
    "gn:feature_class":"P",
    "gn:feature_code":"PPL",
    "gn:name":"Kola-rue",
    "gn:population":0,
    "gn:timezone":"Asia/Kolkata",
    "iso:country":"IN",
    "wof:name":"Kola-rue",
    "wof:placetype":"locality"
},
  "geometry": {"coordinates":[93.16667,8.23333],"type":"Point"}
}