{
  "type": "Feature",
  "properties": {
    "iso:country":"IN",
    "ks:ks_alt_nam":"thanepada",
    "ks:ks_name":"Thanepada",
    "ks:ks_pop":279,
    "ks:ks_type":"HABITATION",
    "ks:ks_uagg_main":0,
    "name:eng_x_preferred":[
        "Thanepada"
    ],
    "wof:name":"Thanepada",
    "wof:placetype":"neighbourhood",
    "wof:population":279
},
  "geometry": {"coordinates":[72.804272,19.573337],"type":"Point"}
}