{
  "type": "Feature",
  "properties": {
    "gn:admin1_code":"11.0",
    "gn:admin2_code":"32.0",
    "gn:asciiname":"Dhamandar",
    "gn:country_code":"IN",
    "gn:dem":1255,
    "gn:feature_class":"P",
    "gn:feature_code":"PPL",
    "gn:name":"Dham\u0101ndar",
    "gn:population":0,
    "gn:timezone":"Asia/Kolkata",
    "iso:country":"IN",
    "wof:name":"Dhamandar",
    "wof:placetype":"locality"
},
  "geometry": {"coordinates":[77.3947,31.00928],"type":"Point"}
}