{
  "type": "Feature",
  "properties": {
    "gn:admin1_code":"36",
    "gn:admin2_code":"191.0",
    "gn:asciiname":"Chak Barwa",
    "gn:country_code":"IN",
    "gn:dem":84,
    "gn:feature_class":"P",
    "gn:feature_code":"PPL",
    "gn:name":"Chak Barwa",
    "gn:population":0,
    "gn:timezone":"Asia/Kolkata",
    "iso:country":"IN",
    "name:und_x_variant":[
        "Ramesargir"
    ],
    "wof:name":"Chak Barwa",
    "wof:placetype":"locality"
},
  "geometry": {"coordinates":[83.03161,25.88493],"type":"Point"}
}