{
  "type": "Feature",
  "properties": {
    "iso:country":"IN",
    "ks:ks_name":"Imaliya Karanpur",
    "ks:ks_pop":3510,
    "ks:ks_type":"HABITATION",
    "name:eng_x_preferred":[
        "Imaliya Karanpur"
    ],
    "wof:name":"Imaliya Karanpur",
    "wof:placetype":"locality",
    "wof:population":3510
},
  "geometry": {"coordinates":[81.692245,27.705184],"type":"Point"}
}