{
  "type": "Feature",
  "properties": {
    "iso:country":"IN",
    "ks:ks_name":"Bhararia",
    "ks:ks_pop":649,
    "ks:ks_type":"HABITATION",
    "ks:ks_uagg_main":0,
    "name:eng_x_preferred":[
        "Bhararia"
    ],
    "wof:name":"Bhararia",
    "wof:placetype":"neighbourhood",
    "wof:population":649
},
  "geometry": {"coordinates":[85.99937799999999,25.853795],"type":"Point"}
}