{
  "type": "Feature",
  "properties": {
    "iso:country":"IN",
    "ks:ks_name":"Kurmi Tola",
    "ks:ks_pop":50,
    "ks:ks_type":"HABITATION",
    "ks:ks_uagg_main":0,
    "name:eng_x_preferred":[
        "Kurmi Tola"
    ],
    "wof:name":"Kurmi Tola",
    "wof:placetype":"neighbourhood",
    "wof:population":50
},
  "geometry": {"coordinates":[83.257688,27.004385],"type":"Point"}
}