{
  "type": "Feature",
  "properties": {
    "iso:country":"IN",
    "ks:ks_name":"Bahirpurwa",
    "ks:ks_pop":210,
    "ks:ks_type":"HABITATION",
    "ks:ks_uagg_main":0,
    "name:eng_x_preferred":[
        "Bahirpurwa"
    ],
    "wof:name":"Bahirpurwa",
    "wof:placetype":"neighbourhood",
    "wof:population":210
},
  "geometry": {"coordinates":[81.299053,27.844562],"type":"Point"}
}