{
  "type": "Feature",
  "properties": {
    "iso:country":"IN",
    "ks:ks_alt_nam":"UTTAR BANAGRAM",
    "ks:ks_name":"Uttar Banagram",
    "ks:ks_pop":594,
    "ks:ks_type":"HABITATION",
    "name:eng_x_preferred":[
        "Uttar Banagram"
    ],
    "wof:name":"Uttar Banagram",
    "wof:placetype":"locality",
    "wof:population":594
},
  "geometry": {"coordinates":[88.46127300000001,23.458614],"type":"Point"}
}