{
  "type": "Feature",
  "properties": {
    "gn:admin1_code":"24",
    "gn:admin2_code":"110.0",
    "gn:asciiname":"Fagoriawala ki Dhani",
    "gn:country_code":"IN",
    "gn:dem":393,
    "gn:feature_class":"P",
    "gn:feature_code":"PPL",
    "gn:name":"Fagori\u0101w\u0101la ki Dh\u0101ni",
    "gn:population":0,
    "gn:timezone":"Asia/Kolkata",
    "iso:country":"IN",
    "wof:name":"Fagoriawala ki Dhani",
    "wof:placetype":"locality"
},
  "geometry": {"coordinates":[75.6275,26.85321],"type":"Point"}
}