{
  "type": "Feature",
  "properties": {
    "gn:admin1_code":"11",
    "gn:admin2_code":"30.0",
    "gn:asciiname":"Ori",
    "gn:country_code":"IN",
    "gn:dem":983,
    "gn:feature_class":"P",
    "gn:feature_code":"PPL",
    "gn:name":"Ori",
    "gn:population":0,
    "gn:timezone":"Asia/Kolkata",
    "iso:country":"IN",
    "name:ceb_x_preferred":[
        "Ori"
    ],
    "name:ces_x_preferred":[
        "Ori"
    ],
    "name:deu_x_preferred":[
        "Ori"
    ],
    "name:est_x_preferred":[
        "Ori"
    ],
    "name:hun_x_preferred":[
        "Ori"
    ],
    "name:kor_x_preferred":[
        "\uc624\ub9ac"
    ],
    "name:nld_x_preferred":[
        "Ori"
    ],
    "name:pol_x_preferred":[
        "Ori"
    ],
    "name:por_x_preferred":[
        "Ori"
    ],
    "name:rus_x_preferred":[
        "Ori"
    ],
    "name:slk_x_preferred":[
        "Ori"
    ],
    "name:spa_x_preferred":[
        "Ori"
    ],
    "name:swe_x_preferred":[
        "Ori"
    ],
    "name:ukr_x_preferred":[
        "\u041e\u0440\u0456"
    ],
    "wof:name":"Ori",
    "wof:placetype":"locality"
},
  "geometry": {"coordinates":[76.85259000000001,31.29717],"type":"Point"}
}