{
  "type": "Feature",
  "properties": {
    "iso:country":"IN",
    "ks:ks_name":"Vallomthitta",
    "ks:ks_pop":536,
    "ks:ks_type":"HABITATION",
    "name:eng_x_preferred":[
        "Vallomthitta"
    ],
    "wof:name":"Vallomthitta",
    "wof:placetype":"locality",
    "wof:population":536
},
  "geometry": {"coordinates":[76.50722399999999,9.315291],"type":"Point"}
}