{
  "type": "Feature",
  "properties": {
    "gn:admin1_code":"35.0",
    "gn:admin2_code":"451.0",
    "gn:asciiname":"Baraha",
    "gn:country_code":"IN",
    "gn:dem":601,
    "gn:feature_class":"P",
    "gn:feature_code":"PPL",
    "gn:name":"Baraha",
    "gn:population":0,
    "gn:timezone":"Asia/Kolkata",
    "iso:country":"IN",
    "wof:name":"Baraha",
    "wof:placetype":"locality"
},
  "geometry": {"coordinates":[80.47294000000002,23.35612],"type":"Point"}
}