{
  "type": "Feature",
  "properties": {
    "gn:admin1_code":"35.0",
    "gn:admin2_code":"451.0",
    "gn:asciiname":"Baraha",
    "gn:country_code":"IN",
    "gn:dem":601,
    "gn:feature_class":"P",
    "gn:feature_code":"PPL",
    "gn:name":"Baraha",
    "gn:population":0,
    "gn:timezone":"Asia/Kolkata",
    "iso:country":"IN",
    "name:hin_x_preferred":[
        "\u092c\u0930\u0939"
    ],
    "name:kan_x_preferred":[
        "\u0cac\u0cb0\u0cb9"
    ],
    "name:mar_x_preferred":[
        "\u092c\u0930\u0939\u093e"
    ],
    "name:tam_x_preferred":[
        "\u0baa\u0bb0\u0bb9\u0bbe"
    ],
    "wof:name":"Baraha",
    "wof:placetype":"locality"
},
  "geometry": {"coordinates":[80.47294000000002,23.35612],"type":"Point"}
}