{
  "type": "Feature",
  "properties": {
    "iso:country":"IN",
    "ks:ks_name":"Chandbati",
    "ks:ks_pop":1056,
    "ks:ks_type":"VILLAGE",
    "name:eng_x_preferred":[
        "Chandbati"
    ],
    "wof:name":"Chandbati",
    "wof:placetype":"locality",
    "wof:population":1056
},
  "geometry": {"coordinates":[88.067773,22.79938],"type":"Point"}
}