{
  "type": "Feature",
  "properties": {
    "gn:admin1_code":"35.0",
    "gn:admin2_code":"455",
    "gn:asciiname":"Jhilmili",
    "gn:country_code":"IN",
    "gn:dem":604,
    "gn:feature_class":"P",
    "gn:feature_code":"PPL",
    "gn:name":"Jhilmili",
    "gn:population":0,
    "gn:timezone":"Asia/Kolkata",
    "iso:country":"IN",
    "name:und_x_variant":[
        "Jhilmill",
        "Jhilmili"
    ],
    "wof:name":"Jhilmili",
    "wof:placetype":"locality"
},
  "geometry": {"coordinates":[79.15434999999999,22.04558],"type":"Point"}
}