{
  "type": "Feature",
  "properties": {
    "iso:country":"IN",
    "ks:ks_name":"Panchar",
    "ks:ks_pop":181,
    "ks:ks_type":"VILLAGE",
    "name:eng_x_preferred":[
        "Panchar"
    ],
    "wof:name":"Panchar",
    "wof:placetype":"locality",
    "wof:population":181
},
  "geometry": {"coordinates":[82.222279,24.629314],"type":"Point"}
}