{
  "type": "Feature",
  "properties": {
    "gn:admin1_code":"19.0",
    "gn:admin2_code":"561.0",
    "gn:asciiname":"Basarkod",
    "gn:country_code":"IN",
    "gn:dem":543,
    "gn:feature_class":"P",
    "gn:feature_code":"PPL",
    "gn:name":"Basarkod",
    "gn:population":0,
    "gn:timezone":"Asia/Kolkata",
    "iso:country":"IN",
    "wof:name":"Basarkod",
    "wof:placetype":"locality"
},
  "geometry": {"coordinates":[75.70170999999998,15.81864],"type":"Point"}
}