{
  "type": "Feature",
  "properties": {
    "iso:country":"IN",
    "ks:ks_name":"Yadagatta Bhovihatti",
    "ks:ks_pop":457,
    "ks:ks_type":"HABITATION",
    "name:eng_x_preferred":[
        "Yadagatta Bhovihatti"
    ],
    "wof:name":"Yadagatta Bhovihatti",
    "wof:placetype":"locality",
    "wof:population":457
},
  "geometry": {"coordinates":[76.642222,13.3375],"type":"Point"}
}