{
  "type": "Feature",
  "properties": {
    "iso:country":"IN",
    "ks:ks_name":"Khandobawasti",
    "ks:ks_pop":214,
    "ks:ks_type":"HABITATION",
    "name:eng_x_preferred":[
        "Khandobawasti"
    ],
    "wof:name":"Khandobawasti",
    "wof:placetype":"locality",
    "wof:population":214
},
  "geometry": {"coordinates":[74.68899999999999,18.169],"type":"Point"}
}