{
  "type": "Feature",
  "properties": {
    "gn:admin1_code":"37.0",
    "gn:admin2_code":"404.0",
    "gn:asciiname":"Jamkachhar",
    "gn:country_code":"IN",
    "gn:dem":412,
    "gn:feature_class":"P",
    "gn:feature_code":"PPL",
    "gn:name":"Jamkachhar",
    "gn:population":0,
    "gn:timezone":"Asia/Kolkata",
    "iso:country":"IN",
    "ks:ks_alt_nam":"J\u0101mkachh\u0101r",
    "ks:ks_name":"Jamkachhar",
    "ks:ks_pop":579,
    "ks:ks_type":"VILLAGE",
    "name:eng_x_preferred":[
        "Jamkachhar"
    ],
    "name:eng_x_variant":[
        "J\u0101mkachh\u0101r"
    ],
    "wof:name":"Jamkachhar",
    "wof:placetype":"locality",
    "wof:population":579
},
  "geometry": {"coordinates":[82.52836499999999,22.927488],"type":"Point"}
}