{
  "type": "Feature",
  "properties": {
    "gn:admin1_code":"37.0",
    "gn:admin2_code":"404.0",
    "gn:asciiname":"Jamkachhar",
    "gn:country_code":"IN",
    "gn:dem":412,
    "gn:feature_class":"P",
    "gn:feature_code":"PPL",
    "gn:name":"Jamkachhar",
    "gn:population":0,
    "gn:timezone":"Asia/Kolkata",
    "iso:country":"IN",
    "wof:name":"Jamkachhar",
    "wof:placetype":"locality"
},
  "geometry": {"coordinates":[82.53482,22.91512],"type":"Point"}
}