{
  "type": "Feature",
  "properties": {
    "iso:country":"IN",
    "ks:ks_name":"Gesuon Ka Wanga",
    "ks:ks_pop":560,
    "ks:ks_type":"HABITATION",
    "name:eng_x_preferred":[
        "Gesuon Ka Wanga"
    ],
    "wof:name":"Gesuon Ka Wanga",
    "wof:placetype":"locality",
    "wof:population":560
},
  "geometry": {"coordinates":[73.652439,23.766089],"type":"Point"}
}