{
  "type": "Feature",
  "properties": {
    "gn:admin1_code":"13.0",
    "gn:admin2_code":"598.0",
    "gn:asciiname":"Kottaikkagam",
    "gn:country_code":"IN",
    "gn:dem":9,
    "gn:feature_class":"P",
    "gn:feature_code":"PPL",
    "gn:name":"Kottaikkagam",
    "gn:population":0,
    "gn:timezone":"Asia/Kolkata",
    "iso:country":"IN",
    "ks:ks_name":"Kottakkakam",
    "ks:ks_pop":175,
    "ks:ks_type":"HABITATION",
    "name:eng_x_preferred":[
        "Kottakkakam"
    ],
    "name:eng_x_variant":[
        "Kottaikkagam"
    ],
    "wof:name":"Kottakkakam",
    "wof:placetype":"locality",
    "wof:population":175
},
  "geometry": {"coordinates":[76.47972300000001,9.254497],"type":"Point"}
}