{
  "type": "Feature",
  "properties": {
    "iso:country":"IN",
    "ks:ks_alt_nam":"JANIYON KI BASTI",
    "ks:ks_name":"Janiyon Ki Basti",
    "ks:ks_pop":60,
    "ks:ks_type":"HABITATION",
    "name:eng_x_preferred":[
        "Janiyon Ki Basti"
    ],
    "wof:name":"Janiyon Ki Basti",
    "wof:placetype":"locality",
    "wof:population":60
},
  "geometry": {"coordinates":[71.090011,25.155442],"type":"Point"}
}