{
  "type": "Feature",
  "properties": {
    "iso:country":"IN",
    "ks:ks_name":"Hesaltanr",
    "ks:ks_pop":65,
    "ks:ks_type":"VILLAGE",
    "name:eng_x_preferred":[
        "Hesaltanr"
    ],
    "wof:name":"Hesaltanr",
    "wof:placetype":"locality",
    "wof:population":65
},
  "geometry": {"coordinates":[87.125484,23.938736],"type":"Point"}
}