{
  "type": "Feature",
  "properties": {
    "iso:country":"IN",
    "ks:ks_name":"Bagbati",
    "ks:ks_pop":754,
    "ks:ks_type":"VILLAGE",
    "ks:ks_uagg_main":0,
    "name:eng_x_preferred":[
        "Bagbati"
    ],
    "wof:name":"Bagbati",
    "wof:placetype":"neighbourhood",
    "wof:population":754
},
  "geometry": {"coordinates":[87.71321399999999,23.58885],"type":"Point"}
}