{
  "type": "Feature",
  "properties": {
    "iso:country":"IN",
    "ks:ks_name":"Sariguda",
    "ks:ks_pop":121,
    "ks:ks_type":"HABITATION",
    "name:eng_x_preferred":[
        "Sariguda"
    ],
    "wof:name":"Sariguda",
    "wof:placetype":"locality",
    "wof:population":121
},
  "geometry": {"coordinates":[82.384702,18.552713],"type":"Point"}
}