{
  "type": "Feature",
  "properties": {
    "gn:admin1_code":"35.0",
    "gn:admin2_code":"443",
    "gn:asciiname":"Kakrawali",
    "gn:country_code":"IN",
    "gn:dem":410,
    "gn:feature_class":"P",
    "gn:feature_code":"PPL",
    "gn:name":"Kakr\u0101wali",
    "gn:population":0,
    "gn:timezone":"Asia/Kolkata",
    "iso:country":"IN",
    "wof:name":"Kakrawali",
    "wof:placetype":"locality"
},
  "geometry": {"coordinates":[78.20463000000002,24.04459],"type":"Point"}
}