{
  "type": "Feature",
  "properties": {
    "iso:country":"IN",
    "ks:ks_name":"Manjhi Para",
    "ks:ks_pop":178,
    "ks:ks_type":"HABITATION",
    "name:eng_x_preferred":[
        "Manjhi Para"
    ],
    "wof:name":"Manjhi Para",
    "wof:placetype":"locality",
    "wof:population":178
},
  "geometry": {"coordinates":[81.660999,19.458452],"type":"Point"}
}