{
  "type": "Feature",
  "properties": {
    "gn:admin1_code":"23.0",
    "gn:admin2_code":"35.0",
    "gn:asciiname":"Dakhla",
    "gn:country_code":"IN",
    "gn:dem":270,
    "gn:feature_class":"P",
    "gn:feature_code":"PPL",
    "gn:name":"D\u0101khla",
    "gn:population":0,
    "gn:timezone":"Asia/Kolkata",
    "iso:country":"IN",
    "name:ara_x_preferred":[
        "\u062f\u0627\u062e\u0644\u0629"
    ],
    "name:ceb_x_preferred":[
        "Dakhla"
    ],
    "name:deu_x_preferred":[
        "Dakhla"
    ],
    "name:hun_x_preferred":[
        "Dakhla"
    ],
    "name:kaz_x_preferred":[
        "\u0414\u0430\u0445\u043b\u0430 \u049b\u0430\u043b\u0430\u0441\u044b"
    ],
    "name:rus_x_preferred":[
        "\u0414\u0430\u0445\u043b\u0430"
    ],
    "name:swe_x_preferred":[
        "Dakhla"
    ],
    "name:ukr_x_preferred":[
        "\u0414\u0430\u0445\u043b\u0430"
    ],
    "wof:name":"Dakhla",
    "wof:placetype":"locality"
},
  "geometry": {"coordinates":[75.47207,32.075],"type":"Point"}
}