{
  "type": "Feature",
  "properties": {
    "gn:admin1_code":"25.0",
    "gn:admin2_code":"631.0",
    "gn:asciiname":"Dheoganpalli",
    "gn:country_code":"IN",
    "gn:dem":911,
    "gn:feature_class":"P",
    "gn:feature_code":"PPL",
    "gn:name":"Dheoganpalli",
    "gn:population":0,
    "gn:timezone":"Asia/Kolkata",
    "iso:country":"IN",
    "wof:name":"Dheoganpalli",
    "wof:placetype":"neighbourhood"
},
  "geometry": {"coordinates":[77.70152,12.61572],"type":"Point"}
}