{
  "type": "Feature",
  "properties": {
    "iso:country":"IN",
    "ks:ks_name":"Vadgaon",
    "ks:ks_type":"VILLAGE",
    "ks:ks_uagg_main":0,
    "name:eng_x_preferred":[
        "Vadgaon"
    ],
    "wof:name":"Vadgaon",
    "wof:placetype":"neighbourhood"
},
  "geometry": {"coordinates":[78.11258100000001,20.375889],"type":"Point"}
}