{
  "type": "Feature",
  "properties": {
    "iso:country":"IN",
    "ks:ks_name":"Badku Ka Purwa",
    "ks:ks_pop":20,
    "ks:ks_type":"HABITATION",
    "name:eng_x_preferred":[
        "Badku Ka Purwa"
    ],
    "wof:name":"Badku Ka Purwa",
    "wof:placetype":"locality",
    "wof:population":20
},
  "geometry": {"coordinates":[80.748676,25.13075],"type":"Point"}
}