{
  "type": "Feature",
  "properties": {
    "gn:admin1_code":"24.0",
    "gn:admin2_code":"119.0",
    "gn:asciiname":"Kalatankhera",
    "gn:country_code":"IN",
    "gn:dem":508,
    "gn:feature_class":"P",
    "gn:feature_code":"PPL",
    "gn:name":"Kalat\u0101nkhera",
    "gn:population":0,
    "gn:timezone":"Asia/Kolkata",
    "iso:country":"IN",
    "ks:ks_name":"Kalat Khera",
    "ks:ks_pop":382,
    "ks:ks_type":"VILLAGE",
    "ks:ks_uagg_main":0,
    "name:eng_x_preferred":[
        "Kalat Khera"
    ],
    "wof:name":"Kalat Khera",
    "wof:placetype":"neighbourhood",
    "wof:population":382
},
  "geometry": {"coordinates":[74.224476,25.953695],"type":"Point"}
}