{
  "type": "Feature",
  "properties": {
    "gn:admin1_code":"35",
    "gn:admin2_code":"449.0",
    "gn:asciiname":"Moriya",
    "gn:country_code":"IN",
    "gn:dem":338,
    "gn:feature_class":"P",
    "gn:feature_code":"PPL",
    "gn:name":"Moriya",
    "gn:population":0,
    "gn:timezone":"Asia/Kolkata",
    "iso:country":"IN",
    "ks:ks_name":"Moriya",
    "ks:ks_pop":182,
    "ks:ks_type":"VILLAGE",
    "name:ceb_x_preferred":[
        "Moriya"
    ],
    "name:eng_x_preferred":[
        "Moriya"
    ],
    "name:swe_x_preferred":[
        "Moriya"
    ],
    "name:tuk_x_preferred":[
        "Moriya"
    ],
    "wof:name":"Moriya",
    "wof:placetype":"locality",
    "wof:population":182
},
  "geometry": {"coordinates":[77.426489,22.336749],"type":"Point"}
}