{
  "type": "Feature",
  "properties": {
    "iso:country":"IN",
    "ks:ks_name":"Donthirallapalle",
    "ks:ks_pop":1,
    "ks:ks_type":"HABITATION",
    "name:eng_x_preferred":[
        "Donthirallapalle"
    ],
    "wof:name":"Donthirallapalle",
    "wof:placetype":"locality",
    "wof:population":1
},
  "geometry": {"coordinates":[78.654212,13.084753],"type":"Point"}
}