{
  "type": "Feature",
  "properties": {
    "iso:country":"IN",
    "ks:ks_name":"Sampangi Puttu",
    "ks:ks_pop":187,
    "ks:ks_type":"HABITATION",
    "name:eng_x_preferred":[
        "Sampangi Puttu"
    ],
    "wof:name":"Sampangi Puttu",
    "wof:placetype":"locality",
    "wof:population":187
},
  "geometry": {"coordinates":[82.83754,18.096054],"type":"Point"}
}