{
  "type": "Feature",
  "properties": {
    "iso:country":"IN",
    "ks:ks_name":"Kadigsar",
    "ks:ks_pop":280,
    "ks:ks_type":"HABITATION",
    "name:eng_x_preferred":[
        "Kadigsar"
    ],
    "wof:name":"Kadigsar",
    "wof:placetype":"locality",
    "wof:population":280
},
  "geometry": {"coordinates":[72.41616399999999,26.729886],"type":"Point"}
}