{
  "type": "Feature",
  "properties": {
    "iso:country":"IN",
    "ks:ks_name":"Gaddibanda",
    "ks:ks_pop":24,
    "ks:ks_type":"VILLAGE",
    "name:eng_x_preferred":[
        "Gaddibanda"
    ],
    "wof:name":"Gaddibanda",
    "wof:placetype":"locality",
    "wof:population":24
},
  "geometry": {"coordinates":[82.821963,18.044871],"type":"Point"}
}