{
  "type": "Feature",
  "properties": {
    "iso:country":"IN",
    "ks:ks_name":"12 DOL-B",
    "ks:ks_pop":1030,
    "ks:ks_type":"VILLAGE",
    "ks:ks_uagg_main":0,
    "name:eng_x_preferred":[
        "12 DOL-B"
    ],
    "wof:name":"12 DOL-B",
    "wof:placetype":"neighbourhood",
    "wof:population":1030
},
  "geometry": {"coordinates":[72.755177,28.830725],"type":"Point"}
}