{
  "type": "Feature",
  "properties": {
    "iso:country":"IN",
    "ks:ks_name":"Kasripara",
    "ks:ks_pop":33,
    "ks:ks_type":"HABITATION",
    "name:eng_x_preferred":[
        "Kasripara"
    ],
    "wof:name":"Kasripara",
    "wof:placetype":"locality",
    "wof:population":33
},
  "geometry": {"coordinates":[87.372343,24.798489],"type":"Point"}
}