{
  "type": "Feature",
  "properties": {
    "gn:admin1_code":"36",
    "gn:admin2_code":"161.0",
    "gn:asciiname":"Madanpur",
    "gn:country_code":"IN",
    "gn:dem":153,
    "gn:feature_class":"P",
    "gn:feature_code":"PPL",
    "gn:name":"Madanpur",
    "gn:population":0,
    "gn:timezone":"Asia/Kolkata",
    "iso:country":"IN",
    "name:ceb_x_preferred":[
        "Madanpur"
    ],
    "name:swe_x_preferred":[
        "Madanpur"
    ],
    "wof:name":"Madanpur",
    "wof:placetype":"locality"
},
  "geometry": {"coordinates":[78.867,26.94606],"type":"Point"}
}