{
  "type": "Feature",
  "properties": {
    "gn:admin1_code":"34.0",
    "gn:admin2_code":"209.0",
    "gn:asciiname":"Maratibpur",
    "gn:country_code":"IN",
    "gn:dem":66,
    "gn:feature_class":"P",
    "gn:feature_code":"PPL",
    "gn:name":"Mar\u0101tibpur",
    "gn:population":0,
    "gn:timezone":"Asia/Kolkata",
    "iso:country":"IN",
    "ks:ks_alt_nam":"Mar\u0101tibpur",
    "ks:ks_name":"Maratibpur",
    "ks:ks_type":"VILLAGE",
    "ks:ks_uagg_main":0,
    "name:eng_x_preferred":[
        "Maratibpur"
    ],
    "name:eng_x_variant":[
        "Mar\u0101tibpur"
    ],
    "wof:name":"Maratibpur",
    "wof:placetype":"neighbourhood"
},
  "geometry": {"coordinates":[87.435017,26.373411],"type":"Point"}
}