{
  "type": "Feature",
  "properties": {
    "iso:country":"IN",
    "ks:ks_name":"Idaikal",
    "ks:ks_pop":2283,
    "ks:ks_type":"VILLAGE",
    "ks:ks_uagg_main":0,
    "name:eng_x_preferred":[
        "Idaikal"
    ],
    "wof:name":"Idaikal",
    "wof:placetype":"locality",
    "wof:population":2283
},
  "geometry": {"coordinates":[77.333957,9.030002],"type":"Point"}
}