{
  "type": "Feature",
  "properties": {
    "iso:country":"IN",
    "ks:ks_name":"Sapekhati Gaon",
    "ks:ks_pop":146,
    "ks:ks_type":"VILLAGE",
    "ks:ks_uagg_main":0,
    "name:eng_x_preferred":[
        "Sapekhati Gaon"
    ],
    "wof:name":"Sapekhati Gaon",
    "wof:placetype":"neighbourhood",
    "wof:population":146
},
  "geometry": {"coordinates":[94.65001700000001,27.578603],"type":"Point"}
}