{
  "type": "Feature",
  "properties": {
    "iso:country":"IN",
    "ks:ks_name":"Jeenapur",
    "ks:ks_pop":962,
    "ks:ks_type":"VILLAGE",
    "ks:ks_uagg_main":0,
    "name:eng_x_preferred":[
        "Jeenapur"
    ],
    "wof:name":"Jeenapur",
    "wof:placetype":"neighbourhood",
    "wof:population":962
},
  "geometry": {"coordinates":[76.33924399999999,26.004839],"type":"Point"}
}