{
  "type": "Feature",
  "properties": {
    "iso:country":"IN",
    "ks:ks_name":"Barhbawanpur",
    "ks:ks_pop":1759,
    "ks:ks_type":"HABITATION",
    "name:eng_x_preferred":[
        "Barhbawanpur"
    ],
    "wof:name":"Barhbawanpur",
    "wof:placetype":"locality",
    "wof:population":1759
},
  "geometry": {"coordinates":[87.731134,22.094208],"type":"Point"}
}