{
  "type": "Feature",
  "properties": {
    "iso:country":"IN",
    "ks:ks_name":"Roshaiya",
    "ks:ks_pop":243,
    "ks:ks_type":"HABITATION",
    "name:eng_x_preferred":[
        "Roshaiya"
    ],
    "wof:name":"Roshaiya",
    "wof:placetype":"locality",
    "wof:population":243
},
  "geometry": {"coordinates":[81.28554099999999,26.023832],"type":"Point"}
}