{
  "type": "Feature",
  "properties": {
    "iso:country":"IN",
    "ks:ks_name":"Purantharan Doddy",
    "ks:ks_pop":76,
    "ks:ks_type":"HABITATION",
    "name:eng_x_preferred":[
        "Purantharan Doddy"
    ],
    "wof:name":"Purantharan Doddy",
    "wof:placetype":"locality",
    "wof:population":76
},
  "geometry": {"coordinates":[77.62962,12.400756],"type":"Point"}
}