{
  "type": "Feature",
  "properties": {
    "iso:country":"IN",
    "ks:ks_alt_nam":"surendra Gowda camp",
    "ks:ks_name":"Surendra Gowda Camp",
    "ks:ks_pop":287,
    "ks:ks_type":"HABITATION",
    "name:eng_x_preferred":[
        "Surendra Gowda Camp"
    ],
    "wof:name":"Surendra Gowda Camp",
    "wof:placetype":"locality",
    "wof:population":287
},
  "geometry": {"coordinates":[75.71343299999999,14.014037],"type":"Point"}
}