{
  "type": "Feature",
  "properties": {
    "iso:country":"IN",
    "ks:ks_name":"Gubbiga",
    "ks:ks_pop":163,
    "ks:ks_type":"HABITATION",
    "name:eng_x_preferred":[
        "Gubbiga"
    ],
    "wof:name":"Gubbiga",
    "wof:placetype":"locality",
    "wof:population":163
},
  "geometry": {"coordinates":[75.449994,13.577085],"type":"Point"}
}