{
  "type": "Feature",
  "properties": {
    "iso:country":"IN",
    "ks:ks_name":"Kenduya",
    "ks:ks_pop":1061,
    "ks:ks_type":"VILLAGE",
    "name:eng_x_preferred":[
        "Kenduya"
    ],
    "wof:name":"Kenduya",
    "wof:placetype":"locality",
    "wof:population":1061
},
  "geometry": {"coordinates":[86.329447,22.43996],"type":"Point"}
}