{
  "type": "Feature",
  "properties": {
    "iso:country":"IN",
    "ks:ks_name":"Chamran",
    "ks:ks_pop":145,
    "ks:ks_type":"HABITATION",
    "name:eng_x_preferred":[
        "Chamran"
    ],
    "wof:name":"Chamran",
    "wof:placetype":"locality",
    "wof:population":145
},
  "geometry": {"coordinates":[82.292075,24.806186],"type":"Point"}
}