{
  "type": "Feature",
  "properties": {
    "iso:country":"IN",
    "ks:ks_name":"Kairasol",
    "ks:ks_pop":8,
    "ks:ks_type":"VILLAGE",
    "name:eng_x_preferred":[
        "Kairasol"
    ],
    "wof:name":"Kairasol",
    "wof:placetype":"locality",
    "wof:population":8
},
  "geometry": {"coordinates":[87.460995,24.448248],"type":"Point"}
}