{
  "type": "Feature",
  "properties": {
    "iso:country":"IN",
    "ks:ks_name":"Pandit Ka Pura",
    "ks:ks_pop":100,
    "ks:ks_type":"HABITATION",
    "name:eng_x_preferred":[
        "Pandit Ka Pura"
    ],
    "wof:name":"Pandit Ka Pura",
    "wof:placetype":"locality",
    "wof:population":100
},
  "geometry": {"coordinates":[82.62890899999999,26.270211],"type":"Point"}
}