{
  "type": "Feature",
  "properties": {
    "iso:country":"IN",
    "ks:ks_name":"Tetariya",
    "ks:ks_pop":0,
    "ks:ks_type":"VILLAGE",
    "name:eng_x_preferred":[
        "Tetariya"
    ],
    "wof:name":"Tetariya",
    "wof:placetype":"locality",
    "wof:population":0
},
  "geometry": {"coordinates":[84.83928400000001,24.47808],"type":"Point"}
}