{
  "type": "Feature",
  "properties": {
    "gn:admin1_code":"11.0",
    "gn:admin2_code":"33.0",
    "gn:asciiname":"Sharamla",
    "gn:country_code":"IN",
    "gn:dem":2171,
    "gn:feature_class":"P",
    "gn:feature_code":"PPL",
    "gn:name":"Sharamla",
    "gn:population":0,
    "gn:timezone":"Asia/Kolkata",
    "iso:country":"IN",
    "wof:name":"Sharamla",
    "wof:placetype":"locality"
},
  "geometry": {"coordinates":[77.45501999999998,31.17661],"type":"Point"}
}