{
  "type": "Feature",
  "properties": {
    "iso:country":"IN",
    "ks:ks_name":"Naladhalia",
    "ks:ks_pop":509,
    "ks:ks_type":"VILLAGE",
    "name:eng_x_preferred":[
        "Naladhalia"
    ],
    "wof:name":"Naladhalia",
    "wof:placetype":"locality",
    "wof:population":509
},
  "geometry": {"coordinates":[86.56481100000001,20.532031],"type":"Point"}
}