{
  "type": "Feature",
  "properties": {
    "iso:country":"IN",
    "ks:ks_name":"Ratanpur",
    "ks:ks_pop":473,
    "ks:ks_type":"VILLAGE",
    "name:eng_x_preferred":[
        "Ratanpur"
    ],
    "wof:name":"Ratanpur",
    "wof:placetype":"locality",
    "wof:population":473
},
  "geometry": {"coordinates":[77.293187,25.028261],"type":"Point"}
}