{
  "type": "Feature",
  "properties": {
    "iso:country":"IN",
    "ks:ks_name":"Shiriramwadi",
    "ks:ks_pop":294,
    "ks:ks_type":"HABITATION",
    "name:eng_x_preferred":[
        "Shiriramwadi"
    ],
    "wof:name":"Shiriramwadi",
    "wof:placetype":"locality",
    "wof:population":294
},
  "geometry": {"coordinates":[74.457843,17.964732],"type":"Point"}
}