{
  "type": "Feature",
  "properties": {
    "iso:country":"IN",
    "ks:ks_name":"Abbanakuppe",
    "ks:ks_pop":1479,
    "ks:ks_type":"VILLAGE",
    "ks:ks_uagg_main":0,
    "name:eng_x_preferred":[
        "Abbanakuppe"
    ],
    "wof:name":"Abbanakuppe",
    "wof:placetype":"locality",
    "wof:population":1479
},
  "geometry": {"coordinates":[77.412992,12.773905],"type":"Point"}
}