{
  "type": "Feature",
  "properties": {
    "iso:country":"IN",
    "ks:ks_name":"Japhlapuram",
    "ks:ks_pop":132,
    "ks:ks_type":"HABITATION",
    "name:eng_x_preferred":[
        "Japhlapuram"
    ],
    "wof:name":"Japhlapuram",
    "wof:placetype":"locality",
    "wof:population":132
},
  "geometry": {"coordinates":[79.58548,15.549609],"type":"Point"}
}