{
  "type": "Feature",
  "properties": {
    "iso:country":"IN",
    "ks:ks_name":"Ng. Ballabh",
    "ks:ks_pop":373,
    "ks:ks_type":"HABITATION",
    "name:eng_x_preferred":[
        "Ng. Ballabh"
    ],
    "wof:name":"Ng. Ballabh",
    "wof:placetype":"locality",
    "wof:population":373
},
  "geometry": {"coordinates":[79.22865400000001,27.379308],"type":"Point"}
}