{
  "type": "Feature",
  "properties": {
    "iso:country":"IN",
    "ks:ks_name":"Musahri",
    "ks:ks_pop":531,
    "ks:ks_type":"HABITATION",
    "name:eng_x_preferred":[
        "Musahri"
    ],
    "wof:name":"Musahri",
    "wof:placetype":"locality",
    "wof:population":531
},
  "geometry": {"coordinates":[86.564938,26.469966],"type":"Point"}
}