{
  "type": "Feature",
  "properties": {
    "gn:admin1_code":"36.0",
    "gn:admin2_code":"162.0",
    "gn:asciiname":"Garhia Gosain",
    "gn:country_code":"IN",
    "gn:dem":146,
    "gn:feature_class":"P",
    "gn:feature_code":"PPL",
    "gn:name":"Garhia Gos\u0101in",
    "gn:population":0,
    "gn:timezone":"Asia/Kolkata",
    "iso:country":"IN",
    "wof:name":"Garhia Gosain",
    "wof:placetype":"locality"
},
  "geometry": {"coordinates":[79.47343000000002,26.85904],"type":"Point"}
}