{
  "type": "Feature",
  "properties": {
    "iso:country":"IN",
    "ks:ks_name":"Nawadih",
    "ks:ks_pop":226,
    "ks:ks_type":"HABITATION",
    "name:eng_x_preferred":[
        "Nawadih"
    ],
    "wof:name":"Nawadih",
    "wof:placetype":"locality",
    "wof:population":226
},
  "geometry": {"coordinates":[83.298924,22.326542],"type":"Point"}
}