{
  "type": "Feature",
  "properties": {
    "iso:country":"IN",
    "ks:ks_name":"Pahartoli",
    "ks:ks_pop":163,
    "ks:ks_type":"HABITATION",
    "name:eng_x_preferred":[
        "Pahartoli"
    ],
    "wof:name":"Pahartoli",
    "wof:placetype":"locality",
    "wof:population":163
},
  "geometry": {"coordinates":[84.534594,22.857922],"type":"Point"}
}