{
  "type": "Feature",
  "properties": {
    "gn:admin1_code":"37.0",
    "gn:admin2_code":"413.0",
    "gn:asciiname":"Charama",
    "gn:country_code":"IN",
    "gn:dem":396,
    "gn:feature_class":"P",
    "gn:feature_code":"PPL",
    "gn:name":"Char\u0101ma",
    "gn:population":0,
    "gn:timezone":"Asia/Kolkata",
    "iso:country":"IN",
    "wof:name":"Charama",
    "wof:placetype":"locality"
},
  "geometry": {"coordinates":[81.49714,20.43234],"type":"Point"}
}