{
  "type": "Feature",
  "properties": {
    "iso:country":"IN",
    "ks:ks_name":"Kaisashi",
    "ks:ks_pop":84,
    "ks:ks_type":"HABITATION",
    "name:eng_x_preferred":[
        "Kaisashi"
    ],
    "wof:name":"Kaisashi",
    "wof:placetype":"locality",
    "wof:population":84
},
  "geometry": {"coordinates":[74.423299,14.335329],"type":"Point"}
}