{
  "type": "Feature",
  "properties": {
    "iso:country":"IN",
    "ks:ks_name":"Ashara Harijan Basti",
    "ks:ks_pop":164,
    "ks:ks_type":"HABITATION",
    "name:eng_x_preferred":[
        "Ashara Harijan Basti"
    ],
    "wof:name":"Ashara Harijan Basti",
    "wof:placetype":"locality",
    "wof:population":164
},
  "geometry": {"coordinates":[83.03307599999999,26.346192],"type":"Point"}
}