{
  "type": "Feature",
  "properties": {
    "gn:admin1_code":"21.0",
    "gn:admin2_code":"399.0",
    "gn:asciiname":"Purunagudemu",
    "gn:country_code":"IN",
    "gn:dem":91,
    "gn:feature_class":"P",
    "gn:feature_code":"PPL",
    "gn:name":"Purun\u0101g\u016bdemu",
    "gn:population":0,
    "gn:timezone":"Asia/Kolkata",
    "iso:country":"IN",
    "wof:name":"Purunagudemu",
    "wof:placetype":"locality"
},
  "geometry": {"coordinates":[81.54366999999998,17.86517000000001],"type":"Point"}
}