{
  "type": "Feature",
  "properties": {
    "iso:country":"IN",
    "ks:ks_name":"Khijalpur Vanto",
    "ks:ks_pop":1404,
    "ks:ks_type":"VILLAGE",
    "name:eng_x_preferred":[
        "Khijalpur Vanto"
    ],
    "wof:name":"Khijalpur Vanto",
    "wof:placetype":"locality",
    "wof:population":1404
},
  "geometry": {"coordinates":[73.09708500000001,22.735701],"type":"Point"}
}