{
  "type": "Feature",
  "properties": {
    "gn:admin1_code":"38",
    "gn:admin2_code":"367.0",
    "gn:asciiname":"Lachragarh",
    "gn:country_code":"IN",
    "gn:dem":442,
    "gn:feature_class":"P",
    "gn:feature_code":"PPL",
    "gn:name":"Lachr\u0101garh",
    "gn:population":0,
    "gn:timezone":"Asia/Kolkata",
    "iso:country":"IN",
    "wof:name":"Lachragarh",
    "wof:placetype":"locality"
},
  "geometry": {"coordinates":[84.86201,22.64409],"type":"Point"}
}