{
  "type": "Feature",
  "properties": {
    "iso:country":"IN",
    "ks:ks_alt_nam":"Vadi faliya",
    "ks:ks_name":"Vadi Faliya",
    "ks:ks_pop":533,
    "ks:ks_type":"HABITATION",
    "name:eng_x_preferred":[
        "Vadi Faliya"
    ],
    "wof:name":"Vadi Faliya",
    "wof:placetype":"locality",
    "wof:population":533
},
  "geometry": {"coordinates":[73.690444,23.284444],"type":"Point"}
}