{
  "type": "Feature",
  "properties": {
    "iso:country":"IN",
    "ks:ks_name":"Burudiput",
    "ks:ks_pop":42,
    "ks:ks_type":"VILLAGE",
    "ks:ks_uagg_main":0,
    "name:eng_x_preferred":[
        "Burudiput"
    ],
    "wof:name":"Burudiput",
    "wof:placetype":"neighbourhood",
    "wof:population":42
},
  "geometry": {"coordinates":[82.49406399999999,18.864272],"type":"Point"}
}