{
  "type": "Feature",
  "properties": {
    "gn:admin1_code":"36",
    "gn:admin2_code":"134.0",
    "gn:asciiname":"Umri Badhi",
    "gn:country_code":"IN",
    "gn:dem":231,
    "gn:feature_class":"P",
    "gn:feature_code":"PPL",
    "gn:name":"Umri Badhi",
    "gn:population":0,
    "gn:timezone":"Asia/Kolkata",
    "iso:country":"IN",
    "ks:ks_name":"Umribarhi",
    "ks:ks_pop":1491,
    "ks:ks_type":"VILLAGE",
    "ks:ks_uagg_main":0,
    "name:eng_x_preferred":[
        "Umribarhi"
    ],
    "wof:name":"Umribarhi",
    "wof:placetype":"neighbourhood",
    "wof:population":1491
},
  "geometry": {"coordinates":[78.346891,29.196383],"type":"Point"}
}