{
  "type": "Feature",
  "properties": {
    "iso:country":"IN",
    "ks:ks_name":"Syamasundarpur",
    "ks:ks_pop":81,
    "ks:ks_type":"HABITATION",
    "name:eng_x_preferred":[
        "Syamasundarpur"
    ],
    "wof:name":"Syamasundarpur",
    "wof:placetype":"locality",
    "wof:population":81
},
  "geometry": {"coordinates":[84.388411,19.45394],"type":"Point"}
}