{
  "type": "Feature",
  "properties": {
    "gn:admin1_code":"36.0",
    "gn:admin2_code":"167",
    "gn:asciiname":"Dharampura",
    "gn:country_code":"IN",
    "gn:dem":364,
    "gn:feature_class":"P",
    "gn:feature_code":"PPL",
    "gn:name":"Dharampura",
    "gn:population":0,
    "gn:timezone":"Asia/Kolkata",
    "iso:country":"IN",
    "name:fas_x_preferred":[
        "\u062f\u0647\u0631\u0645\u200c\u067e\u0648\u0631\u0647"
    ],
    "name:und_x_variant":[
        "B\u0101jna",
        "Dharampura",
        "B\u0101jno"
    ],
    "name:urd_x_preferred":[
        "\u062f\u06be\u0631\u0645 \u067e\u0648\u0631\u06c1"
    ],
    "wof:name":"Dharampura",
    "wof:placetype":"neighbourhood"
},
  "geometry": {"coordinates":[78.38025,24.8445],"type":"Point"}
}