{
  "type": "Feature",
  "properties": {
    "iso:country":"IN",
    "ks:ks_name":"Paighambarpur",
    "ks:ks_pop":599,
    "ks:ks_type":"VILLAGE",
    "name:eng_x_preferred":[
        "Paighambarpur"
    ],
    "wof:name":"Paighambarpur",
    "wof:placetype":"locality",
    "wof:population":599
},
  "geometry": {"coordinates":[85.358574,25.892015],"type":"Point"}
}