{
  "type": "Feature",
  "properties": {
    "iso:country":"IN",
    "ks:ks_name":"Dorko",
    "ks:ks_pop":1293,
    "ks:ks_type":"VILLAGE",
    "name:eng_x_preferred":[
        "Dorko"
    ],
    "wof:name":"Dorko",
    "wof:placetype":"locality",
    "wof:population":1293
},
  "geometry": {"coordinates":[89.691598,26.423409],"type":"Point"}
}