{
  "type": "Feature",
  "properties": {
    "iso:country":"IN",
    "ks:ks_name":"Mushari",
    "ks:ks_pop":314,
    "ks:ks_type":"HABITATION",
    "name:eng_x_preferred":[
        "Mushari"
    ],
    "wof:name":"Mushari",
    "wof:placetype":"locality",
    "wof:population":314
},
  "geometry": {"coordinates":[87.24132899999999,25.665875],"type":"Point"}
}