{
  "type": "Feature",
  "properties": {
    "iso:country":"IN",
    "ks:ks_name":"Bodakmahajib",
    "ks:ks_pop":772,
    "ks:ks_type":"VILLAGE",
    "ks:ks_uagg_main":0,
    "name:eng_x_preferred":[
        "Bodakmahajib"
    ],
    "wof:name":"Bodakmahajib",
    "wof:placetype":"neighbourhood",
    "wof:population":772
},
  "geometry": {"coordinates":[86.395859,21.122285],"type":"Point"}
}