{
  "type": "Feature",
  "properties": {
    "iso:country":"IN",
    "ks:ks_name":"Sharifpur",
    "ks:ks_pop":236,
    "ks:ks_type":"HABITATION",
    "name:eng_x_preferred":[
        "Sharifpur"
    ],
    "wof:name":"Sharifpur",
    "wof:placetype":"locality",
    "wof:population":236
},
  "geometry": {"coordinates":[77.46656,23.932112],"type":"Point"}
}