{
  "type": "Feature",
  "properties": {
    "iso:country":"IN",
    "ks:ks_name":"Garaiya",
    "ks:ks_pop":1001,
    "ks:ks_type":"VILLAGE",
    "name:eng_x_preferred":[
        "Garaiya"
    ],
    "wof:name":"Garaiya",
    "wof:placetype":"locality",
    "wof:population":1001
},
  "geometry": {"coordinates":[80.704499,22.71879],"type":"Point"}
}