{
  "type": "Feature",
  "properties": {
    "iso:country":"IN",
    "ks:ks_name":"Sugginahalli",
    "ks:ks_pop":4069,
    "ks:ks_type":"VILLAGE",
    "name:eng_x_preferred":[
        "Sugginahalli"
    ],
    "wof:name":"Sugginahalli",
    "wof:placetype":"locality",
    "wof:population":4069
},
  "geometry": {"coordinates":[76.71843200000001,15.300099],"type":"Point"}
}