{
  "type": "Feature",
  "properties": {
    "iso:country":"IN",
    "ks:ks_name":"Dagyong Kolbong",
    "ks:ks_pop":773,
    "ks:ks_type":"HABITATION",
    "name:eng_x_preferred":[
        "Dagyong Kolbong"
    ],
    "wof:name":"Dagyong Kolbong",
    "wof:placetype":"locality",
    "wof:population":773
},
  "geometry": {"coordinates":[88.67877300000001,27.10082],"type":"Point"}
}