{
  "type": "Feature",
  "properties": {
    "gn:admin1_code":"36.0",
    "gn:admin2_code":"181.0",
    "gn:asciiname":"Iira",
    "gn:country_code":"IN",
    "gn:dem":117,
    "gn:feature_class":"P",
    "gn:feature_code":"PPL",
    "gn:name":"Iira",
    "gn:population":0,
    "gn:timezone":"Asia/Kolkata",
    "iso:country":"IN",
    "name:ceb_x_preferred":[
        "Ira"
    ],
    "name:est_x_preferred":[
        "Iira"
    ],
    "name:hye_x_preferred":[
        "\u053b\u056b\u057c\u0561"
    ],
    "name:pol_x_preferred":[
        "Iira"
    ],
    "name:sco_x_preferred":[
        "Iira"
    ],
    "name:spa_x_preferred":[
        "Iira"
    ],
    "name:swe_x_preferred":[
        "Iira"
    ],
    "name:vol_x_preferred":[
        "Iira"
    ],
    "wof:name":"Iira",
    "wof:placetype":"locality"
},
  "geometry": {"coordinates":[81.91595,27.47658],"type":"Point"}
}