{
  "type": "Feature",
  "properties": {
    "gn:admin1_code":"35",
    "gn:admin2_code":"421.0",
    "gn:asciiname":"Lakshmangarh",
    "gn:country_code":"IN",
    "gn:dem":182,
    "gn:feature_class":"P",
    "gn:feature_code":"PPL",
    "gn:name":"Lakshmangarh",
    "gn:population":0,
    "gn:timezone":"Asia/Kolkata",
    "iso:country":"IN",
    "name:und_x_variant":[
        "Lachhmangarh"
    ],
    "wof:name":"Lakshmangarh",
    "wof:placetype":"neighbourhood"
},
  "geometry": {"coordinates":[78.25919,26.31027],"type":"Point"}
}