{
  "type": "Feature",
  "properties": {
    "gn:admin1_code":"12",
    "gn:admin2_code":"3.0",
    "gn:asciiname":"Roang",
    "gn:country_code":"IN",
    "gn:dem":4412,
    "gn:feature_class":"P",
    "gn:feature_code":"PPL",
    "gn:name":"Roang",
    "gn:population":0,
    "gn:timezone":"Asia/Kolkata",
    "iso:country":"IN",
    "wof:name":"Roang",
    "wof:placetype":"locality"
},
  "geometry": {"coordinates":[78.14081,33.63723],"type":"Point"}
}