{
  "type": "Feature",
  "properties": {
    "gn:admin1_code":"36",
    "gn:admin2_code":"191.0",
    "gn:asciiname":"Zamin Sakat",
    "gn:country_code":"IN",
    "gn:dem":83,
    "gn:feature_class":"P",
    "gn:feature_code":"PPL",
    "gn:name":"Zam\u012bn Sakat",
    "gn:population":0,
    "gn:timezone":"Asia/Kolkata",
    "iso:country":"IN",
    "ks:ks_name":"Jaminsakat",
    "ks:ks_pop":422,
    "ks:ks_type":"VILLAGE",
    "name:eng_x_preferred":[
        "Jaminsakat"
    ],
    "name:eng_x_variant":[
        "Zamin Sakat"
    ],
    "wof:name":"Jaminsakat",
    "wof:placetype":"locality",
    "wof:population":422
},
  "geometry": {"coordinates":[83.13162199999999,25.669093],"type":"Point"}
}