{
  "type": "Feature",
  "properties": {
    "iso:country":"IN",
    "ks:ks_alt_nam":"Nirapan kadi",
    "ks:ks_name":"Nirapan Kadi",
    "ks:ks_pop":280,
    "ks:ks_type":"HABITATION",
    "name:eng_x_preferred":[
        "Nirapan Kadi"
    ],
    "wof:name":"Nirapan Kadi",
    "wof:placetype":"locality",
    "wof:population":280
},
  "geometry": {"coordinates":[73.23688900000001,20.610944],"type":"Point"}
}