{
  "type": "Feature",
  "properties": {
    "gn:admin1_code":"2.0",
    "gn:admin2_code":"553.0",
    "gn:asciiname":"Payelavaripalle",
    "gn:country_code":"IN",
    "gn:dem":589,
    "gn:feature_class":"P",
    "gn:feature_code":"PPL",
    "gn:name":"Payelav\u0101ripalle",
    "gn:population":0,
    "gn:timezone":"Asia/Kolkata",
    "iso:country":"IN",
    "wof:name":"Payelavaripalle",
    "wof:placetype":"locality"
},
  "geometry": {"coordinates":[78.18353,14.01048],"type":"Point"}
}