{
  "type": "Feature",
  "properties": {
    "gn:admin1_code":"40",
    "gn:admin2_code":"537.0",
    "gn:asciiname":"Shaireddiguda",
    "gn:country_code":"IN",
    "gn:dem":613,
    "gn:feature_class":"P",
    "gn:feature_code":"PPL",
    "gn:name":"Sh\u0101ireddiguda",
    "gn:population":0,
    "gn:timezone":"Asia/Kolkata",
    "iso:country":"IN",
    "wof:name":"Shaireddiguda",
    "wof:placetype":"locality"
},
  "geometry": {"coordinates":[78.19436999999998,17.18648],"type":"Point"}
}