{
  "type": "Feature",
  "properties": {
    "iso:country":"IN",
    "ks:ks_name":"Tongavagu",
    "ks:ks_pop":172,
    "ks:ks_type":"HABITATION",
    "name:eng_x_preferred":[
        "Tongavagu"
    ],
    "wof:name":"Tongavagu",
    "wof:placetype":"locality",
    "wof:population":172
},
  "geometry": {"coordinates":[81.035921,17.975744],"type":"Point"}
}