{
  "type": "Feature",
  "properties": {
    "iso:country":"IN",
    "ks:ks_name":"Lakhanguwan",
    "ks:ks_pop":4420,
    "ks:ks_type":"VILLAGE",
    "name:eng_x_preferred":[
        "Lakhanguwan"
    ],
    "wof:name":"Lakhanguwan",
    "wof:placetype":"locality",
    "wof:population":4420
},
  "geometry": {"coordinates":[79.512038,24.398519],"type":"Point"}
}