{
  "type": "Feature",
  "properties": {
    "gn:admin1_code":"23.0",
    "gn:admin2_code":"50.0",
    "gn:asciiname":"Bahla",
    "gn:country_code":"IN",
    "gn:dem":225,
    "gn:feature_class":"P",
    "gn:feature_code":"PPL",
    "gn:name":"Bahla",
    "gn:population":0,
    "gn:timezone":"Asia/Kolkata",
    "iso:country":"IN",
    "name:ara_x_preferred":[
        "\u0628\u0647\u0644\u0627"
    ],
    "name:bul_x_preferred":[
        "\u0411\u0430\u0445\u043b\u0430"
    ],
    "name:cat_x_preferred":[
        "Bahla"
    ],
    "name:ces_x_preferred":[
        "Bahla"
    ],
    "name:deu_x_preferred":[
        "Bahla"
    ],
    "name:fas_x_preferred":[
        "\u0628\u0647\u0644\u0627\u0621"
    ],
    "name:fra_x_preferred":[
        "Bahla"
    ],
    "name:ita_x_preferred":[
        "Bahla"
    ],
    "name:nld_x_preferred":[
        "Bahla"
    ],
    "name:nno_x_preferred":[
        "Bahla"
    ],
    "name:nor_x_preferred":[
        "Bahla"
    ],
    "name:pol_x_preferred":[
        "Bahla"
    ],
    "name:por_x_preferred":[
        "Bala"
    ],
    "name:rus_x_preferred":[
        "\u0411\u0430\u0445\u043b\u0430"
    ],
    "name:urd_x_preferred":[
        "\u0628\u06c1\u0644\u0627"
    ],
    "wof:name":"Bahla",
    "wof:placetype":"locality"
},
  "geometry": {"coordinates":[74.93533000000002,31.49971],"type":"Point"}
}