{
  "type": "Feature",
  "properties": {
    "iso:country":"IN",
    "ks:ks_name":"Balibaju",
    "ks:ks_pop":82,
    "ks:ks_type":"VILLAGE",
    "name:eng_x_preferred":[
        "Balibaju"
    ],
    "wof:name":"Balibaju",
    "wof:placetype":"locality",
    "wof:population":82
},
  "geometry": {"coordinates":[83.636782,20.19695],"type":"Point"}
}