{
  "type": "Feature",
  "properties": {
    "iso:country":"IN",
    "ks:ks_name":"Bhel Dunga",
    "ks:ks_pop":31,
    "ks:ks_type":"VILLAGE",
    "name:eng_x_preferred":[
        "Bhel Dunga"
    ],
    "wof:name":"Bhel Dunga",
    "wof:placetype":"locality",
    "wof:population":31
},
  "geometry": {"coordinates":[78.369473,30.055522],"type":"Point"}
}