{
  "type": "Feature",
  "properties": {
    "gn:admin1_code":"24.0",
    "gn:admin2_code":"103.0",
    "gn:asciiname":"Navta",
    "gn:country_code":"IN",
    "gn:dem":317,
    "gn:feature_class":"P",
    "gn:feature_code":"PPL",
    "gn:name":"N\u0101vta",
    "gn:population":0,
    "gn:timezone":"Asia/Kolkata",
    "iso:country":"IN",
    "ks:ks_alt_nam":"N\u0101vta",
    "ks:ks_name":"Navta",
    "ks:ks_type":"VILLAGE",
    "ks:ks_uagg_main":0,
    "name:eng_x_preferred":[
        "Navta"
    ],
    "name:eng_x_variant":[
        "N\u0101vta"
    ],
    "wof:name":"Navta",
    "wof:placetype":"neighbourhood"
},
  "geometry": {"coordinates":[75.95093199999999,28.118343],"type":"Point"}
}