{
  "type": "Feature",
  "properties": {
    "iso:country":"IN",
    "ks:ks_name":"Nagla Dhana",
    "ks:ks_pop":950,
    "ks:ks_type":"HABITATION",
    "name:eng_x_preferred":[
        "Nagla Dhana"
    ],
    "wof:name":"Nagla Dhana",
    "wof:placetype":"locality",
    "wof:population":950
},
  "geometry": {"coordinates":[77.92739899999999,27.023968],"type":"Point"}
}