{
  "type": "Feature",
  "properties": {
    "iso:country":"IN",
    "ks:ks_name":"Kadamdohri",
    "ks:ks_pop":498,
    "ks:ks_type":"HABITATION",
    "name:eng_x_preferred":[
        "Kadamdohri"
    ],
    "wof:name":"Kadamdohri",
    "wof:placetype":"locality",
    "wof:population":498
},
  "geometry": {"coordinates":[83.25250800000001,22.680853],"type":"Point"}
}