{
  "type": "Feature",
  "properties": {
    "iso:country":"IN",
    "ks:ks_name":"Barapathari",
    "ks:ks_pop":322,
    "ks:ks_type":"VILLAGE",
    "ks:ks_uagg_main":0,
    "name:eng_x_preferred":[
        "Barapathari"
    ],
    "wof:name":"Barapathari",
    "wof:placetype":"neighbourhood",
    "wof:population":322
},
  "geometry": {"coordinates":[91.405551,23.299492],"type":"Point"}
}