{
  "type": "Feature",
  "properties": {
    "iso:country":"IN",
    "ks:ks_name":"Theethampettai",
    "ks:ks_pop":1146,
    "ks:ks_type":"VILLAGE",
    "name:eng_x_preferred":[
        "Theethampettai"
    ],
    "wof:name":"Theethampettai",
    "wof:placetype":"locality",
    "wof:population":1146
},
  "geometry": {"coordinates":[78.39152799999999,9.711241],"type":"Point"}
}