{
  "type": "Feature",
  "properties": {
    "iso:country":"IN",
    "ks:ks_name":"Mitauli",
    "ks:ks_pop":219,
    "ks:ks_type":"HABITATION",
    "ks:ks_uagg_main":0,
    "name:eng_x_preferred":[
        "Mitauli"
    ],
    "wof:name":"Mitauli",
    "wof:placetype":"neighbourhood",
    "wof:population":219
},
  "geometry": {"coordinates":[78.419195,28.084238],"type":"Point"}
}