{
  "type": "Feature",
  "properties": {
    "iso:country":"IN",
    "ks:ks_name":"Savantwasti",
    "ks:ks_pop":246,
    "ks:ks_type":"HABITATION",
    "name:eng_x_preferred":[
        "Savantwasti"
    ],
    "wof:name":"Savantwasti",
    "wof:placetype":"locality",
    "wof:population":246
},
  "geometry": {"coordinates":[75.28046000000001,17.936684],"type":"Point"}
}