{
  "type": "Feature",
  "properties": {
    "gn:admin1_code":"40.0",
    "gn:admin2_code":"541.0",
    "gn:asciiname":"Buriyalgutta",
    "gn:country_code":"IN",
    "gn:dem":148,
    "gn:feature_class":"P",
    "gn:feature_code":"PPL",
    "gn:name":"Buriy\u0101lgutta",
    "gn:population":0,
    "gn:timezone":"Asia/Kolkata",
    "iso:country":"IN",
    "ks:ks_name":"Boriyalagutta",
    "ks:ks_pop":114,
    "ks:ks_type":"HABITATION",
    "name:eng_x_preferred":[
        "Boriyalagutta"
    ],
    "name:eng_x_variant":[
        "Buriyalgutta"
    ],
    "wof:name":"Boriyalagutta",
    "wof:placetype":"locality",
    "wof:population":114
},
  "geometry": {"coordinates":[81.091249,17.388285],"type":"Point"}
}