{
  "type": "Feature",
  "properties": {
    "gn:admin1_code":"36",
    "gn:admin2_code":"194.0",
    "gn:asciiname":"Chauki Kalan",
    "gn:country_code":"IN",
    "gn:dem":94,
    "gn:feature_class":"P",
    "gn:feature_code":"PPL",
    "gn:name":"Chauk\u012b Kal\u0101n",
    "gn:population":0,
    "gn:timezone":"Asia/Kolkata",
    "iso:country":"IN",
    "wof:name":"Chauki Kalan",
    "wof:placetype":"locality"
},
  "geometry": {"coordinates":[82.33156,25.55914],"type":"Point"}
}