{
  "type": "Feature",
  "properties": {
    "iso:country":"IN",
    "ks:ks_name":"Madhubana",
    "ks:ks_pop":1450,
    "ks:ks_type":"VILLAGE",
    "name:eng_x_preferred":[
        "Madhubana"
    ],
    "wof:name":"Madhubana",
    "wof:placetype":"locality",
    "wof:population":1450
},
  "geometry": {"coordinates":[86.30606400000001,21.265149],"type":"Point"}
}