{
  "type": "Feature",
  "properties": {
    "iso:country":"IN",
    "ks:ks_name":"Gollarahalli",
    "ks:ks_pop":80,
    "ks:ks_type":"HABITATION",
    "name:eng_x_preferred":[
        "Gollarahalli"
    ],
    "wof:name":"Gollarahalli",
    "wof:placetype":"locality",
    "wof:population":80
},
  "geometry": {"coordinates":[75.8028,13.619381],"type":"Point"}
}