{
  "type": "Feature",
  "properties": {
    "gn:admin1_code":"12.0",
    "gn:admin2_code":"004",
    "gn:asciiname":"Yogma",
    "gn:country_code":"IN",
    "gn:dem":2868,
    "gn:feature_class":"P",
    "gn:feature_code":"PPL",
    "gn:name":"Yogma",
    "gn:population":0,
    "gn:timezone":"Asia/Kolkata",
    "iso:country":"IN",
    "wof:name":"Yogma",
    "wof:placetype":"locality"
},
  "geometry": {"coordinates":[76.16110999999999,34.55972],"type":"Point"}
}