{
  "type": "Feature",
  "properties": {
    "iso:country":"IN",
    "ks:ks_name":"Muraliganja",
    "ks:ks_pop":2893,
    "ks:ks_type":"VILLAGE",
    "name:eng_x_preferred":[
        "Muraliganja"
    ],
    "wof:name":"Muraliganja",
    "wof:placetype":"locality",
    "wof:population":2893
},
  "geometry": {"coordinates":[87.49869700000001,22.930564],"type":"Point"}
}