{
  "type": "Feature",
  "properties": {
    "iso:country":"IN",
    "ks:ks_name":"Nagla Khushal",
    "ks:ks_pop":126,
    "ks:ks_type":"HABITATION",
    "ks:ks_uagg_main":0,
    "name:eng_x_preferred":[
        "Nagla Khushal"
    ],
    "wof:name":"Nagla Khushal",
    "wof:placetype":"neighbourhood",
    "wof:population":126
},
  "geometry": {"coordinates":[78.69151100000001,27.348025],"type":"Point"}
}