{
  "type": "Feature",
  "properties": {
    "gn:admin1_code":"2.0",
    "gn:admin2_code":"543.0",
    "gn:asciiname":"Papayyavalasa",
    "gn:country_code":"IN",
    "gn:dem":117,
    "gn:feature_class":"P",
    "gn:feature_code":"PPL",
    "gn:name":"Papayyavalasa",
    "gn:population":0,
    "gn:timezone":"Asia/Kolkata",
    "iso:country":"IN",
    "ks:ks_name":"Papammavalasa",
    "ks:ks_pop":773,
    "ks:ks_type":"VILLAGE",
    "ks:ks_uagg_main":0,
    "name:eng_x_preferred":[
        "Papammavalasa"
    ],
    "wof:name":"Papammavalasa",
    "wof:placetype":"neighbourhood",
    "wof:population":773
},
  "geometry": {"coordinates":[83.399343,18.696886],"type":"Point"}
}