{
  "type": "Feature",
  "properties": {
    "gn:admin1_code":"2.0",
    "gn:admin2_code":"551.0",
    "gn:asciiname":"Kottapeta",
    "gn:country_code":"IN",
    "gn:dem":276,
    "gn:feature_class":"P",
    "gn:feature_code":"PPL",
    "gn:name":"Kottapeta",
    "gn:population":0,
    "gn:timezone":"Asia/Kolkata",
    "iso:country":"IN",
    "wof:name":"Kottapeta",
    "wof:placetype":"locality"
},
  "geometry": {"coordinates":[78.51688,14.20585],"type":"Point"}
}