{
  "type": "Feature",
  "properties": {
    "gn:admin1_code":"35",
    "gn:admin2_code":"455.0",
    "gn:asciiname":"Puntara",
    "gn:country_code":"IN",
    "gn:dem":617,
    "gn:feature_class":"P",
    "gn:feature_code":"PPL",
    "gn:name":"Puntara",
    "gn:population":0,
    "gn:timezone":"Asia/Kolkata",
    "iso:country":"IN",
    "wof:name":"Puntara",
    "wof:placetype":"locality"
},
  "geometry": {"coordinates":[79.09884,21.77717],"type":"Point"}
}