{
  "type": "Feature",
  "properties": {
    "gn:admin1_code":"24.0",
    "gn:admin2_code":"130.0",
    "gn:asciiname":"Panu ka Ghara",
    "gn:country_code":"IN",
    "gn:dem":213,
    "gn:feature_class":"P",
    "gn:feature_code":"PPL",
    "gn:name":"P\u0101nu ka Ghara",
    "gn:population":0,
    "gn:timezone":"Asia/Kolkata",
    "iso:country":"IN",
    "wof:name":"Panu ka Ghara",
    "wof:placetype":"neighbourhood"
},
  "geometry": {"coordinates":[74.04492999999999,24.00185],"type":"Point"}
}