{
  "type": "Feature",
  "properties": {
    "iso:country":"IN",
    "ks:ks_name":"Sadhubir",
    "ks:ks_pop":243,
    "ks:ks_type":"VILLAGE",
    "ks:ks_uagg_main":0,
    "name:eng_x_preferred":[
        "Sadhubir"
    ],
    "wof:name":"Sadhubir",
    "wof:placetype":"neighbourhood",
    "wof:population":243
},
  "geometry": {"coordinates":[86.706986,21.188367],"type":"Point"}
}