{
  "type": "Feature",
  "properties": {
    "iso:country":"IN",
    "ks:ks_name":"Holong",
    "ks:ks_pop":95,
    "ks:ks_type":"VILLAGE",
    "name:eng_x_preferred":[
        "Holong"
    ],
    "wof:name":"Holong",
    "wof:placetype":"locality",
    "wof:population":95
},
  "geometry": {"coordinates":[85.721909,23.380404],"type":"Point"}
}