{
  "type": "Feature",
  "properties": {
    "gn:admin1_code":"24.0",
    "gn:admin2_code":"108.0",
    "gn:asciiname":"Khidarpur",
    "gn:country_code":"IN",
    "gn:dem":220,
    "gn:feature_class":"P",
    "gn:feature_code":"PPL",
    "gn:name":"Khidarpur",
    "gn:population":0,
    "gn:timezone":"Asia/Kolkata",
    "iso:country":"IN",
    "wof:name":"Khidarpur",
    "wof:placetype":"locality"
},
  "geometry": {"coordinates":[76.79167,26.05706],"type":"Point"}
}