{
  "type": "Feature",
  "properties": {
    "iso:country":"IN",
    "ks:ks_name":"Naikara Keri",
    "ks:ks_pop":101,
    "ks:ks_type":"HABITATION",
    "name:eng_x_preferred":[
        "Naikara Keri"
    ],
    "wof:name":"Naikara Keri",
    "wof:placetype":"locality",
    "wof:population":101
},
  "geometry": {"coordinates":[74.47137499999999,14.23456],"type":"Point"}
}