{
  "type": "Feature",
  "properties": {
    "gn:admin1_code":"35",
    "gn:admin2_code":"463.0",
    "gn:asciiname":"Singraul",
    "gn:country_code":"IN",
    "gn:dem":436,
    "gn:feature_class":"P",
    "gn:feature_code":"PPL",
    "gn:name":"Singraul",
    "gn:population":0,
    "gn:timezone":"Asia/Kolkata",
    "iso:country":"IN",
    "name:und_x_variant":[
        "Singradul",
        "Singraul"
    ],
    "wof:name":"Singraul",
    "wof:placetype":"locality"
},
  "geometry": {"coordinates":[82.27445999999998,23.86629],"type":"Point"}
}