{
  "type": "Feature",
  "properties": {
    "iso:country":"IN",
    "ks:ks_name":"Thenginajeddu",
    "ks:ks_pop":240,
    "ks:ks_type":"HABITATION",
    "name:eng_x_preferred":[
        "Thenginajeddu"
    ],
    "wof:name":"Thenginajeddu",
    "wof:placetype":"locality",
    "wof:population":240
},
  "geometry": {"coordinates":[74.836799,13.424829],"type":"Point"}
}