{
  "type": "Feature",
  "properties": {
    "gn:admin1_code":"12",
    "gn:admin2_code":"10.0",
    "gn:asciiname":"shnapad",
    "gn:country_code":"IN",
    "gn:dem":1789,
    "gn:feature_class":"P",
    "gn:feature_code":"PPL",
    "gn:name":"shnap\u0101d",
    "gn:population":0,
    "gn:timezone":"Asia/Kolkata",
    "iso:country":"IN",
    "wof:name":"shnapad",
    "wof:placetype":"locality"
},
  "geometry": {"coordinates":[75.00256,34.02907],"type":"Point"}
}