{
  "type": "Feature",
  "properties": {
    "iso:country":"IN",
    "ks:ks_name":"Jarkat",
    "ks:ks_pop":610,
    "ks:ks_type":"VILLAGE",
    "name:eng_x_preferred":[
        "Jarkat"
    ],
    "wof:name":"Jarkat",
    "wof:placetype":"locality",
    "wof:population":610
},
  "geometry": {"coordinates":[83.26495300000001,22.230543],"type":"Point"}
}