{
  "type": "Feature",
  "properties": {
    "iso:country":"IN",
    "ks:ks_name":"Pakka Pura",
    "ks:ks_pop":270,
    "ks:ks_type":"HABITATION",
    "name:eng_x_preferred":[
        "Pakka Pura"
    ],
    "wof:name":"Pakka Pura",
    "wof:placetype":"locality",
    "wof:population":270
},
  "geometry": {"coordinates":[78.16864200000001,27.006205],"type":"Point"}
}