{
  "type": "Feature",
  "properties": {
    "gn:admin1_code":"24.0",
    "gn:admin2_code":"114",
    "gn:asciiname":"Dudhali Ki Dhani",
    "gn:country_code":"IN",
    "gn:dem":246,
    "gn:feature_class":"P",
    "gn:feature_code":"PPL",
    "gn:name":"Dudhali Ki Dh\u0101ni",
    "gn:population":0,
    "gn:timezone":"Asia/Kolkata",
    "iso:country":"IN",
    "wof:name":"Dudhali Ki Dhani",
    "wof:placetype":"locality"
},
  "geometry": {"coordinates":[71.82380000000001,26.61106],"type":"Point"}
}