{
  "type": "Feature",
  "properties": {
    "gn:admin1_code":"24.0",
    "gn:admin2_code":"114",
    "gn:asciiname":"Dudhali Ki Dhani",
    "gn:country_code":"IN",
    "gn:dem":246,
    "gn:feature_class":"P",
    "gn:feature_code":"PPL",
    "gn:name":"Dudhali Ki Dh\u0101ni",
    "gn:population":0,
    "gn:timezone":"Asia/Kolkata",
    "iso:country":"IN",
    "ks:ks_name":"Doodhli Ki Dhani",
    "ks:ks_pop":160,
    "ks:ks_type":"HABITATION",
    "name:eng_x_preferred":[
        "Doodhli Ki Dhani"
    ],
    "name:eng_x_variant":[
        "Dudhali Ki Dhani"
    ],
    "wof:name":"Doodhli Ki Dhani",
    "wof:placetype":"locality",
    "wof:population":160
},
  "geometry": {"coordinates":[71.822806,26.6146],"type":"Point"}
}