{
  "type": "Feature",
  "properties": {
    "gn:admin1_code":"33.0",
    "gn:admin2_code":"585.0",
    "gn:asciiname":"Arvalem",
    "gn:country_code":"IN",
    "gn:dem":57,
    "gn:feature_class":"P",
    "gn:feature_code":"PPL",
    "gn:name":"Arvalem",
    "gn:population":0,
    "gn:timezone":"Asia/Kolkata",
    "iso:country":"IN",
    "wof:name":"Arvalem",
    "wof:placetype":"locality"
},
  "geometry": {"coordinates":[74.04665,15.56631],"type":"Point"}
}