{
  "type": "Feature",
  "properties": {
    "iso:country":"IN",
    "ks:ks_name":"Jhajharwa Khurd",
    "ks:ks_pop":600,
    "ks:ks_type":"VILLAGE",
    "name:eng_x_preferred":[
        "Jhajharwa Khurd"
    ],
    "wof:name":"Jhajharwa Khurd",
    "wof:placetype":"locality",
    "wof:population":600
},
  "geometry": {"coordinates":[74.182108,23.216336],"type":"Point"}
}