{
  "type": "Feature",
  "properties": {
    "iso:country":"IN",
    "ks:ks_name":"Asoburki",
    "ks:ks_pop":267,
    "ks:ks_type":"HABITATION",
    "name:eng_x_preferred":[
        "Asoburki"
    ],
    "wof:name":"Asoburki",
    "wof:placetype":"locality",
    "wof:population":267
},
  "geometry": {"coordinates":[78.622681,19.558472],"type":"Point"}
}