{
  "type": "Feature",
  "properties": {
    "gn:admin1_code":"36",
    "gn:admin2_code":"140.0",
    "gn:asciiname":"Shekhmir",
    "gn:country_code":"IN",
    "gn:dem":215,
    "gn:feature_class":"P",
    "gn:feature_code":"PPL",
    "gn:name":"Shekhmir",
    "gn:population":0,
    "gn:timezone":"Asia/Kolkata",
    "iso:country":"IN",
    "ks:ks_name":"Shekhmir",
    "ks:ks_type":"VILLAGE",
    "name:eng_x_preferred":[
        "Shekhmir"
    ],
    "wof:name":"Shekhmir",
    "wof:placetype":"locality"
},
  "geometry": {"coordinates":[78.109538,28.693096],"type":"Point"}
}