{
  "type": "Feature",
  "properties": {
    "gn:admin1_code":"36",
    "gn:admin2_code":"140.0",
    "gn:asciiname":"Shekhmir",
    "gn:country_code":"IN",
    "gn:dem":215,
    "gn:feature_class":"P",
    "gn:feature_code":"PPL",
    "gn:name":"Shekhmir",
    "gn:population":0,
    "gn:timezone":"Asia/Kolkata",
    "iso:country":"IN",
    "wof:name":"Shekhmir",
    "wof:placetype":"locality"
},
  "geometry": {"coordinates":[78.10954,28.6931],"type":"Point"}
}