{
  "type": "Feature",
  "properties": {
    "gn:admin1_code":"36.0",
    "gn:admin2_code":"183.0",
    "gn:asciiname":"Kopa",
    "gn:country_code":"IN",
    "gn:dem":106,
    "gn:feature_class":"P",
    "gn:feature_code":"PPL",
    "gn:name":"Kopa",
    "gn:population":0,
    "gn:timezone":"Asia/Kolkata",
    "iso:country":"IN",
    "name:ceb_x_preferred":[
        "Kopa"
    ],
    "name:ces_x_preferred":[
        "Kopa"
    ],
    "name:deu_x_preferred":[
        "Kopa"
    ],
    "name:eus_x_preferred":[
        "Kopa"
    ],
    "name:kaz_x_preferred":[
        "\u049a\u043e\u043f\u0430"
    ],
    "name:lav_x_preferred":[
        "Kopa"
    ],
    "name:lit_x_preferred":[
        "Kopa"
    ],
    "name:pol_x_preferred":[
        "Kopa"
    ],
    "name:rus_x_preferred":[
        "\u041a\u043e\u043f\u0430"
    ],
    "name:slk_x_preferred":[
        "Kopa"
    ],
    "name:swe_x_preferred":[
        "Kopa"
    ],
    "name:tgl_x_preferred":[
        "Kopa"
    ],
    "name:ukr_x_preferred":[
        "\u041a\u043e\u043f\u0430"
    ],
    "wof:name":"Kopa",
    "wof:placetype":"neighbourhood"
},
  "geometry": {"coordinates":[82.20869999999999,27.12079],"type":"Point"}
}