{
  "type": "Feature",
  "properties": {
    "iso:country":"IN",
    "ks:ks_alt_nam":"Bhelw\u0101dih",
    "ks:ks_name":"Bhelwadih",
    "ks:ks_pop":230,
    "ks:ks_type":"VILLAGE",
    "name:eng_x_preferred":[
        "Bhelwadih"
    ],
    "name:eng_x_variant":[
        "Bhelw\u0101dih"
    ],
    "wof:name":"Bhelwadih",
    "wof:placetype":"locality",
    "wof:population":230
},
  "geometry": {"coordinates":[84.41168399999999,23.232166],"type":"Point"}
}