{
  "type": "Feature",
  "properties": {
    "iso:country":"IN",
    "ks:ks_name":"Duttapara",
    "ks:ks_pop":1060,
    "ks:ks_type":"HABITATION",
    "ks:ks_uagg_main":0,
    "name:eng_x_preferred":[
        "Duttapara"
    ],
    "wof:name":"Duttapara",
    "wof:placetype":"locality",
    "wof:population":1060
},
  "geometry": {"coordinates":[88.221278,22.786961],"type":"Point"}
}