{
  "type": "Feature",
  "properties": {
    "iso:country":"IN",
    "ks:ks_name":"Gudakulli",
    "ks:ks_pop":841,
    "ks:ks_type":"HABITATION",
    "name:eng_x_preferred":[
        "Gudakulli"
    ],
    "wof:name":"Gudakulli",
    "wof:placetype":"locality",
    "wof:population":841
},
  "geometry": {"coordinates":[74.41359,14.342339],"type":"Point"}
}