{
  "type": "Feature",
  "properties": {
    "gn:admin1_code":"19.0",
    "gn:admin2_code":"565.0",
    "gn:asciiname":"Nirakallu Basapuram",
    "gn:country_code":"IN",
    "gn:dem":611,
    "gn:feature_class":"P",
    "gn:feature_code":"PPL",
    "gn:name":"N\u012brakallu Bas\u0101puram",
    "gn:population":0,
    "gn:timezone":"Asia/Kolkata",
    "iso:country":"IN",
    "wof:name":"Nirakallu Basapuram",
    "wof:placetype":"locality"
},
  "geometry": {"coordinates":[76.38750999999998,14.94399],"type":"Point"}
}