{
  "type": "Feature",
  "properties": {
    "gn:admin1_code":"36",
    "gn:admin2_code":"199.0",
    "gn:asciiname":"Lalpur Khurd",
    "gn:country_code":"IN",
    "gn:dem":270,
    "gn:feature_class":"P",
    "gn:feature_code":"PPL",
    "gn:name":"L\u0101lpur Khurd",
    "gn:population":0,
    "gn:timezone":"Asia/Kolkata",
    "iso:country":"IN",
    "ks:ks_alt_nam":"L\u0101lpur Khurd",
    "ks:ks_name":"Lalpur Khurd",
    "ks:ks_pop":1333,
    "ks:ks_type":"VILLAGE",
    "name:eng_x_preferred":[
        "Lalpur Khurd"
    ],
    "name:eng_x_variant":[
        "L\u0101lpur Khurd"
    ],
    "wof:name":"Lalpur Khurd",
    "wof:placetype":"locality",
    "wof:population":1333
},
  "geometry": {"coordinates":[82.74114,24.917292],"type":"Point"}
}