{
  "type": "Feature",
  "properties": {
    "iso:country":"IN",
    "ks:ks_name":"Bandgarwadi 2",
    "ks:ks_pop":534,
    "ks:ks_type":"HABITATION",
    "name:eng_x_preferred":[
        "Bandgarwadi 2"
    ],
    "wof:name":"Bandgarwadi 2",
    "wof:placetype":"locality",
    "wof:population":534
},
  "geometry": {"coordinates":[75.049532,17.567916],"type":"Point"}
}