{
  "type": "Feature",
  "properties": {
    "iso:country":"IN",
    "ks:ks_alt_nam":"GROUP HOUSING COLONY",
    "ks:ks_name":"Group Housing Colony",
    "ks:ks_pop":116,
    "ks:ks_type":"HABITATION",
    "name:eng_x_preferred":[
        "Group Housing Colony"
    ],
    "wof:name":"Group Housing Colony",
    "wof:placetype":"locality",
    "wof:population":116
},
  "geometry": {"coordinates":[91.38110500000001,23.730046],"type":"Point"}
}