{
  "type": "Feature",
  "properties": {
    "iso:country":"IN",
    "ks:ks_alt_nam":"garri n",
    "ks:ks_name":"Garri n",
    "ks:ks_pop":430,
    "ks:ks_type":"HABITATION",
    "ks:ks_uagg_main":0,
    "name:eng_x_preferred":[
        "Garri n"
    ],
    "wof:name":"Garri n",
    "wof:placetype":"neighbourhood",
    "wof:population":430
},
  "geometry": {"coordinates":[85.761055,26.398579],"type":"Point"}
}