{
  "type": "Feature",
  "properties": {
    "iso:country":"IN",
    "ks:ks_name":"Malada",
    "ks:ks_pop":793,
    "ks:ks_type":"VILLAGE",
    "name:eng_x_preferred":[
        "Malada"
    ],
    "wof:name":"Malada",
    "wof:placetype":"locality",
    "wof:population":793
},
  "geometry": {"coordinates":[85.471148,21.795895],"type":"Point"}
}