{
  "type": "Feature",
  "properties": {
    "iso:country":"IN",
    "ks:ks_alt_nam":"Kalliyengal jn",
    "ks:ks_name":"Kalliyengal Jn",
    "ks:ks_pop":813,
    "ks:ks_type":"HABITATION",
    "name:eng_x_preferred":[
        "Kalliyengal Jn"
    ],
    "wof:name":"Kalliyengal Jn",
    "wof:placetype":"locality",
    "wof:population":813
},
  "geometry": {"coordinates":[76.03301399999999,11.102521],"type":"Point"}
}