{
  "type": "Feature",
  "properties": {
    "gn:admin1_code":"25.0",
    "gn:admin2_code":"633.0",
    "gn:asciiname":"Pottaiyampalaryam",
    "gn:country_code":"IN",
    "gn:dem":358,
    "gn:feature_class":"P",
    "gn:feature_code":"PPL",
    "gn:name":"Pottaiyamp\u0101laryam",
    "gn:population":0,
    "gn:timezone":"Asia/Kolkata",
    "iso:country":"IN",
    "wof:name":"Pottaiyampalaryam",
    "wof:placetype":"locality"
},
  "geometry": {"coordinates":[77.20193,10.65987],"type":"Point"}
}