{
  "type": "Feature",
  "properties": {
    "iso:country":"IN",
    "ks:ks_name":"Ballighai",
    "ks:ks_pop":377,
    "ks:ks_type":"VILLAGE",
    "name:eng_x_preferred":[
        "Ballighai"
    ],
    "wof:name":"Ballighai",
    "wof:placetype":"locality",
    "wof:population":377
},
  "geometry": {"coordinates":[84.47500700000001,19.298863],"type":"Point"}
}