{
  "type": "Feature",
  "properties": {
    "gn:admin1_code":"2",
    "gn:admin2_code":"544.0",
    "gn:asciiname":"Lusam",
    "gn:country_code":"IN",
    "gn:dem":480,
    "gn:feature_class":"P",
    "gn:feature_code":"PPL",
    "gn:name":"L\u016bs\u0101m",
    "gn:population":0,
    "gn:timezone":"Asia/Kolkata",
    "iso:country":"IN",
    "ks:ks_alt_nam":"L\u016bs\u0101m",
    "ks:ks_name":"Lusam",
    "ks:ks_type":"VILLAGE",
    "name:eng_x_preferred":[
        "Lusam"
    ],
    "name:eng_x_variant":[
        "L\u016bs\u0101m"
    ],
    "wof:name":"Lusam",
    "wof:placetype":"locality"
},
  "geometry": {"coordinates":[82.21308399999999,17.705782],"type":"Point"}
}