{
  "type": "Feature",
  "properties": {
    "gn:admin1_code":"2",
    "gn:admin2_code":"544.0",
    "gn:asciiname":"Lusam",
    "gn:country_code":"IN",
    "gn:dem":480,
    "gn:feature_class":"P",
    "gn:feature_code":"PPL",
    "gn:name":"L\u016bs\u0101m",
    "gn:population":0,
    "gn:timezone":"Asia/Kolkata",
    "iso:country":"IN",
    "wof:name":"Lusam",
    "wof:placetype":"locality"
},
  "geometry": {"coordinates":[82.21308000000001,17.70577999999999],"type":"Point"}
}