{
  "type": "Feature",
  "properties": {
    "iso:country":"IN",
    "ks:ks_name":"Darbarwadi",
    "ks:ks_pop":180,
    "ks:ks_type":"HABITATION",
    "name:eng_x_preferred":[
        "Darbarwadi"
    ],
    "wof:name":"Darbarwadi",
    "wof:placetype":"locality",
    "wof:population":180
},
  "geometry": {"coordinates":[73.005022,18.742485],"type":"Point"}
}