{
  "type": "Feature",
  "properties": {
    "iso:country":"IN",
    "ks:ks_alt_nam":"KATHATDUNDA",
    "ks:ks_name":"Kathatdunda",
    "ks:ks_pop":137,
    "ks:ks_type":"HABITATION",
    "name:eng_x_preferred":[
        "Kathatdunda"
    ],
    "wof:name":"Kathatdunda",
    "wof:placetype":"locality",
    "wof:population":137
},
  "geometry": {"coordinates":[83.859892,22.515853],"type":"Point"}
}