{
  "type": "Feature",
  "properties": {
    "iso:country":"IN",
    "ks:ks_name":"Uskalbag",
    "ks:ks_pop":691,
    "ks:ks_type":"VILLAGE",
    "name:eng_x_preferred":[
        "Uskalbag"
    ],
    "wof:name":"Uskalbag",
    "wof:placetype":"locality",
    "wof:population":691
},
  "geometry": {"coordinates":[81.641296,18.298721],"type":"Point"}
}