{
  "type": "Feature",
  "properties": {
    "iso:country":"IN",
    "ks:ks_name":"Bari Chowa Gaon",
    "ks:ks_pop":1542,
    "ks:ks_type":"VILLAGE",
    "ks:ks_uagg_main":0,
    "name:eng_x_preferred":[
        "Bari Chowa Gaon"
    ],
    "wof:name":"Bari Chowa Gaon",
    "wof:placetype":"neighbourhood",
    "wof:population":1542
},
  "geometry": {"coordinates":[93.94929999999999,26.672119],"type":"Point"}
}