{
  "type": "Feature",
  "properties": {
    "iso:country":"IN",
    "ks:ks_name":"No 1 Lape Bahoiting",
    "ks:ks_pop":135,
    "ks:ks_type":"HABITATION",
    "name:eng_x_preferred":[
        "No 1 Lape Bahoiting"
    ],
    "wof:name":"No 1 Lape Bahoiting",
    "wof:placetype":"locality",
    "wof:population":135
},
  "geometry": {"coordinates":[94.619726,27.573522],"type":"Point"}
}