{
  "type": "Feature",
  "properties": {
    "iso:country":"IN",
    "ks:ks_name":"Balekodlu",
    "ks:ks_pop":45,
    "ks:ks_type":"HABITATION",
    "name:eng_x_preferred":[
        "Balekodlu"
    ],
    "wof:name":"Balekodlu",
    "wof:placetype":"locality",
    "wof:population":45
},
  "geometry": {"coordinates":[74.60599000000001,14.966234],"type":"Point"}
}