{
  "type": "Feature",
  "properties": {
    "gn:admin1_code":"35.0",
    "gn:admin2_code":"455",
    "gn:asciiname":"Alimod",
    "gn:country_code":"IN",
    "gn:dem":874,
    "gn:feature_class":"P",
    "gn:feature_code":"PPL",
    "gn:name":"\u0100limod",
    "gn:population":0,
    "gn:timezone":"Asia/Kolkata",
    "iso:country":"IN",
    "ks:ks_name":"Almod",
    "ks:ks_pop":671,
    "ks:ks_type":"VILLAGE",
    "name:eng_x_preferred":[
        "Almod"
    ],
    "name:eng_x_variant":[
        "Alimod"
    ],
    "wof:name":"Almod",
    "wof:placetype":"locality",
    "wof:population":671
},
  "geometry": {"coordinates":[78.3734,22.394095],"type":"Point"}
}