{
  "type": "Feature",
  "properties": {
    "iso:country":"IN",
    "ks:ks_name":"Sagadra",
    "ks:ks_pop":48,
    "ks:ks_type":"VILLAGE",
    "name:eng_x_preferred":[
        "Sagadra"
    ],
    "wof:name":"Sagadra",
    "wof:placetype":"locality",
    "wof:population":48
},
  "geometry": {"coordinates":[73.87858300000001,22.437278],"type":"Point"}
}