{
  "type": "Feature",
  "properties": {
    "iso:country":"IN",
    "ks:ks_name":"Divalpadu",
    "ks:ks_pop":265,
    "ks:ks_type":"VILLAGE",
    "name:eng_x_preferred":[
        "Divalpadu"
    ],
    "wof:name":"Divalpadu",
    "wof:placetype":"locality",
    "wof:population":265
},
  "geometry": {"coordinates":[83.322971,19.466073],"type":"Point"}
}