{
  "type": "Feature",
  "properties": {
    "iso:country":"IN",
    "ks:ks_name":"Chandalguda",
    "ks:ks_pop":241,
    "ks:ks_type":"HABITATION",
    "name:eng_x_preferred":[
        "Chandalguda"
    ],
    "wof:name":"Chandalguda",
    "wof:placetype":"locality",
    "wof:population":241
},
  "geometry": {"coordinates":[82.11878900000001,18.479899],"type":"Point"}
}