{
  "type": "Feature",
  "properties": {
    "gn:admin1_code":"19.0",
    "gn:admin2_code":"568.0",
    "gn:asciiname":"Avalagere",
    "gn:country_code":"IN",
    "gn:dem":666,
    "gn:feature_class":"P",
    "gn:feature_code":"PPL",
    "gn:name":"\u0100valagere",
    "gn:population":0,
    "gn:timezone":"Asia/Kolkata",
    "iso:country":"IN",
    "wof:name":"Avalagere",
    "wof:placetype":"locality"
},
  "geometry": {"coordinates":[75.34147,13.82225],"type":"Point"}
}