{
  "type": "Feature",
  "properties": {
    "iso:country":"IN",
    "ks:ks_alt_nam":"GOUSA BIGHA",
    "ks:ks_name":"Gousa Bigha",
    "ks:ks_pop":167,
    "ks:ks_type":"HABITATION",
    "name:eng_x_preferred":[
        "Gousa Bigha"
    ],
    "wof:name":"Gousa Bigha",
    "wof:placetype":"locality",
    "wof:population":167
},
  "geometry": {"coordinates":[85.009895,25.281493],"type":"Point"}
}