{
  "type": "Feature",
  "properties": {
    "iso:country":"IN",
    "ks:ks_name":"Bore",
    "ks:ks_pop":66,
    "ks:ks_type":"VILLAGE",
    "name:eng_x_preferred":[
        "Bore"
    ],
    "wof:name":"Bore",
    "wof:placetype":"locality",
    "wof:population":66
},
  "geometry": {"coordinates":[73.57795900000001,21.656214],"type":"Point"}
}