{
  "type": "Feature",
  "properties": {
    "iso:country":"IN",
    "ks:ks_name":"Baligwar",
    "ks:ks_pop":109,
    "ks:ks_type":"HABITATION",
    "name:eng_x_preferred":[
        "Baligwar"
    ],
    "wof:name":"Baligwar",
    "wof:placetype":"locality",
    "wof:population":109
},
  "geometry": {"coordinates":[79.602665,30.268275],"type":"Point"}
}