{
  "type": "Feature",
  "properties": {
    "gn:admin1_code":"19.0",
    "gn:admin2_code":"581.0",
    "gn:asciiname":"Koteramgula",
    "gn:country_code":"IN",
    "gn:dem":776,
    "gn:feature_class":"P",
    "gn:feature_code":"PPL",
    "gn:name":"Koter\u0101mgula",
    "gn:population":0,
    "gn:timezone":"Asia/Kolkata",
    "iso:country":"IN",
    "wof:name":"Koteramgula",
    "wof:placetype":"neighbourhood"
},
  "geometry": {"coordinates":[78.1416,12.87713],"type":"Point"}
}