{
  "type": "Feature",
  "properties": {
    "iso:country":"IN",
    "ks:ks_name":"Basaveshwara Camp",
    "ks:ks_pop":2129,
    "ks:ks_type":"HABITATION",
    "name:eng_x_preferred":[
        "Basaveshwara Camp"
    ],
    "wof:name":"Basaveshwara Camp",
    "wof:placetype":"locality",
    "wof:population":2129
},
  "geometry": {"coordinates":[75.67360499999999,14.453389],"type":"Point"}
}