{
  "type": "Feature",
  "properties": {
    "gn:admin1_code":"39.0",
    "gn:admin2_code":"63.0",
    "gn:asciiname":"Kaphauli",
    "gn:country_code":"IN",
    "gn:dem":1370,
    "gn:feature_class":"P",
    "gn:feature_code":"PPL",
    "gn:name":"Kaphauli",
    "gn:population":0,
    "gn:timezone":"Asia/Kolkata",
    "iso:country":"IN",
    "ks:ks_name":"Kaphauli",
    "ks:ks_type":"VILLAGE",
    "name:eng_x_preferred":[
        "Kaphauli"
    ],
    "wof:name":"Kaphauli",
    "wof:placetype":"locality"
},
  "geometry": {"coordinates":[79.811296,29.922058],"type":"Point"}
}