{
  "type": "Feature",
  "properties": {
    "gn:admin1_code":"09",
    "gn:admin2_code":"479.0",
    "gn:asciiname":"Vanthli",
    "gn:country_code":"IN",
    "gn:dem":44,
    "gn:feature_class":"P",
    "gn:feature_code":"PPL",
    "gn:name":"Vanthli",
    "gn:population":0,
    "gn:timezone":"Asia/Kolkata",
    "iso:country":"IN",
    "wof:name":"Vanthli",
    "wof:placetype":"locality"
},
  "geometry": {"coordinates":[70.33114999999999,21.4774],"type":"Point"}
}