{
  "type": "Feature",
  "properties": {
    "iso:country":"IN",
    "ks:ks_name":"Bhosle Wasti",
    "ks:ks_pop":250,
    "ks:ks_type":"HABITATION",
    "name:eng_x_preferred":[
        "Bhosle Wasti"
    ],
    "wof:name":"Bhosle Wasti",
    "wof:placetype":"locality",
    "wof:population":250
},
  "geometry": {"coordinates":[74.31407900000001,18.624357],"type":"Point"}
}