{
  "type": "Feature",
  "properties": {
    "iso:country":"IN",
    "ks:ks_alt_nam":"PURNA BIGHA",
    "ks:ks_name":"Purna Bigha",
    "ks:ks_pop":78,
    "ks:ks_type":"HABITATION",
    "name:eng_x_preferred":[
        "Purna Bigha"
    ],
    "wof:name":"Purna Bigha",
    "wof:placetype":"locality",
    "wof:population":78
},
  "geometry": {"coordinates":[84.975363,25.10064],"type":"Point"}
}