{
  "type": "Feature",
  "properties": {
    "gn:admin1_code":"11",
    "gn:admin2_code":"23.0",
    "gn:asciiname":"Rauta",
    "gn:country_code":"IN",
    "gn:dem":1882,
    "gn:feature_class":"P",
    "gn:feature_code":"PPL",
    "gn:name":"Rauta",
    "gn:population":0,
    "gn:timezone":"Asia/Kolkata",
    "iso:country":"IN",
    "name:bih_x_preferred":[
        "\u0930\u094c\u0924\u093e"
    ],
    "name:ceb_x_preferred":[
        "Rauta"
    ],
    "name:fra_x_preferred":[
        "Rauta"
    ],
    "name:ita_x_preferred":[
        "Rauta"
    ],
    "name:mai_x_preferred":[
        "\u0930\u094c\u0924\u093e"
    ],
    "name:msa_x_preferred":[
        "Rauta"
    ],
    "name:nep_x_preferred":[
        "\u0930\u094c\u0924\u093e"
    ],
    "name:new_x_preferred":[
        "\u0930\u094c\u0924\u093e"
    ],
    "name:pol_x_preferred":[
        "Rauta"
    ],
    "wof:name":"Rauta",
    "wof:placetype":"locality"
},
  "geometry": {"coordinates":[76.065,32.55785],"type":"Point"}
}