{
  "type": "Feature",
  "properties": {
    "gn:admin1_code":"38.0",
    "gn:admin2_code":"358.0",
    "gn:asciiname":"Nawa",
    "gn:country_code":"IN",
    "gn:dem":355,
    "gn:feature_class":"P",
    "gn:feature_code":"PPL",
    "gn:name":"N\u0101wa",
    "gn:population":0,
    "gn:timezone":"Asia/Kolkata",
    "iso:country":"IN",
    "ks:ks_alt_nam":"N\u0101wa",
    "ks:ks_name":"Nawa",
    "ks:ks_pop":738,
    "ks:ks_type":"VILLAGE",
    "name:ceb_x_preferred":[
        "Nawa"
    ],
    "name:deu_x_preferred":[
        "Nawa"
    ],
    "name:eng_x_preferred":[
        "Nawa"
    ],
    "name:eng_x_variant":[
        "N\u0101wa"
    ],
    "name:ita_x_preferred":[
        "Nawa"
    ],
    "name:pol_x_preferred":[
        "Nawa"
    ],
    "name:rus_x_preferred":[
        "\u041d\u0430\u0432\u0430"
    ],
    "name:swe_x_preferred":[
        "Nawa"
    ],
    "name:ukr_x_preferred":[
        "\u041d\u0430\u0432\u0430"
    ],
    "wof:name":"Nawa",
    "wof:placetype":"locality",
    "wof:population":738
},
  "geometry": {"coordinates":[84.399366,24.244296],"type":"Point"}
}