{
  "type": "Feature",
  "properties": {
    "gn:admin1_code":"35.0",
    "gn:admin2_code":"463.0",
    "gn:asciiname":"Katrihar",
    "gn:country_code":"IN",
    "gn:dem":292,
    "gn:feature_class":"P",
    "gn:feature_code":"PPL",
    "gn:name":"Katrih\u0101r",
    "gn:population":0,
    "gn:timezone":"Asia/Kolkata",
    "iso:country":"IN",
    "ks:ks_alt_nam":"Katrih\u0101r",
    "ks:ks_name":"Katrihar",
    "ks:ks_pop":1546,
    "ks:ks_type":"VILLAGE",
    "name:eng_x_preferred":[
        "Katrihar"
    ],
    "name:eng_x_variant":[
        "Katrih\u0101r"
    ],
    "wof:name":"Katrihar",
    "wof:placetype":"locality",
    "wof:population":1546
},
  "geometry": {"coordinates":[82.722949,24.365431],"type":"Point"}
}