{
  "type": "Feature",
  "properties": {
    "iso:country":"IN",
    "ks:ks_name":"Hirdaya Nagar",
    "ks:ks_pop":404,
    "ks:ks_type":"HABITATION",
    "name:eng_x_preferred":[
        "Hirdaya Nagar"
    ],
    "wof:name":"Hirdaya Nagar",
    "wof:placetype":"locality",
    "wof:population":404
},
  "geometry": {"coordinates":[82.326162,27.435043],"type":"Point"}
}