{
  "type": "Feature",
  "properties": {
    "iso:country":"IN",
    "ks:ks_name":"Bhaduon Ki Dhani",
    "ks:ks_pop":556,
    "ks:ks_type":"HABITATION",
    "name:eng_x_preferred":[
        "Bhaduon Ki Dhani"
    ],
    "wof:name":"Bhaduon Ki Dhani",
    "wof:placetype":"locality",
    "wof:population":556
},
  "geometry": {"coordinates":[72.69159500000001,26.798708],"type":"Point"}
}