{
  "type": "Feature",
  "properties": {
    "gn:admin1_code":"16",
    "gn:admin2_code":"502.0",
    "gn:asciiname":"Medsi",
    "gn:country_code":"IN",
    "gn:dem":461,
    "gn:feature_class":"P",
    "gn:feature_code":"PPL",
    "gn:name":"Medsi",
    "gn:population":0,
    "gn:timezone":"Asia/Kolkata",
    "iso:country":"IN",
    "wof:name":"Medsi",
    "wof:placetype":"locality"
},
  "geometry": {"coordinates":[76.94100999999998,20.32736],"type":"Point"}
}