{
  "type": "Feature",
  "properties": {
    "gn:admin1_code":"2",
    "gn:admin2_code":"546.0",
    "gn:asciiname":"Venkatadri Apparaopuram",
    "gn:country_code":"IN",
    "gn:dem":9,
    "gn:feature_class":"P",
    "gn:feature_code":"PPL",
    "gn:name":"Venkat\u0101dri App\u0101r\u0101opuram",
    "gn:population":0,
    "gn:timezone":"Asia/Kolkata",
    "iso:country":"IN",
    "wof:name":"Venkatadri Apparaopuram",
    "wof:placetype":"locality"
},
  "geometry": {"coordinates":[81.47386,16.76684],"type":"Point"}
}