{
  "type": "Feature",
  "properties": {
    "iso:country":"IN",
    "ks:ks_name":"Bura Tokbi",
    "ks:ks_pop":265,
    "ks:ks_type":"HABITATION",
    "name:eng_x_preferred":[
        "Bura Tokbi"
    ],
    "wof:name":"Bura Tokbi",
    "wof:placetype":"locality",
    "wof:population":265
},
  "geometry": {"coordinates":[93.788398,26.372072],"type":"Point"}
}