{
  "type": "Feature",
  "properties": {
    "iso:country":"IN",
    "ks:ks_name":"Pure Umrao Singh",
    "ks:ks_pop":124,
    "ks:ks_type":"HABITATION",
    "ks:ks_uagg_main":0,
    "name:eng_x_preferred":[
        "Pure Umrao Singh"
    ],
    "wof:name":"Pure Umrao Singh",
    "wof:placetype":"neighbourhood",
    "wof:population":124
},
  "geometry": {"coordinates":[81.695291,26.291779],"type":"Point"}
}