{
  "type": "Feature",
  "properties": {
    "iso:country":"IN",
    "ks:ks_alt_nam":"Mahug\u0101in",
    "ks:ks_name":"Mahugain",
    "ks:ks_type":"VILLAGE",
    "ks:ks_uagg_main":0,
    "name:eng_x_preferred":[
        "Mahugain"
    ],
    "name:eng_x_variant":[
        "Mahug\u0101in"
    ],
    "wof:name":"Mahugain",
    "wof:placetype":"neighbourhood"
},
  "geometry": {"coordinates":[84.947627,24.438465],"type":"Point"}
}