{
  "type": "Feature",
  "properties": {
    "gn:country":"IN",
    "gn:fcode":"PPL",
    "gn:pop":0,
    "iso:country":"IN",
    "name:unk_x_variant":[
        "Pallipuram"
    ],
    "qs:name":"Pallippuram",
    "qs:name_adm0":"India",
    "qs:name_adm1":"Kerala",
    "qs:photos":56,
    "qs:photos_1k":11,
    "qs:photos_9k":1,
    "qs:photos_9r":2,
    "qs:photos_all":56,
    "qs:photos_sr":2,
    "qs:placetype":"Town",
    "qs:pop_sr":"0",
    "wd:wordcount":22,
    "wof:name":"Pallippuram",
    "wof:placetype":"locality",
    "wof:population":0
},
  "geometry": {"coordinates":[76.18333,10.16667],"type":"Point"}
}