{
  "type": "Feature",
  "properties": {
    "gn:admin1_code":"40.0",
    "gn:admin2_code":"534.0",
    "gn:asciiname":"Narasimhalapalli",
    "gn:country_code":"IN",
    "gn:dem":329,
    "gn:feature_class":"P",
    "gn:feature_code":"PPL",
    "gn:name":"Narasimhalapalli",
    "gn:population":0,
    "gn:timezone":"Asia/Kolkata",
    "iso:country":"IN",
    "ks:ks_name":"Narsimhulapally",
    "ks:ks_pop":276,
    "ks:ks_type":"HABITATION",
    "name:eng_x_preferred":[
        "Narsimhulapally"
    ],
    "name:eng_x_variant":[
        "Narasimhalapalli"
    ],
    "wof:name":"Narsimhulapally",
    "wof:placetype":"locality",
    "wof:population":276
},
  "geometry": {"coordinates":[79.029073,18.238405],"type":"Point"}
}