{
  "type": "Feature",
  "properties": {
    "gn:admin1_code":"2.0",
    "gn:admin2_code":"548.0",
    "gn:asciiname":"Govada",
    "gn:country_code":"IN",
    "gn:dem":5,
    "gn:feature_class":"P",
    "gn:feature_code":"PPL",
    "gn:name":"Govada",
    "gn:population":0,
    "gn:timezone":"Asia/Kolkata",
    "iso:country":"IN",
    "wof:name":"Govada",
    "wof:placetype":"locality"
},
  "geometry": {"coordinates":[80.60475,16.03412],"type":"Point"}
}