{
  "type": "Feature",
  "properties": {
    "iso:country":"IN",
    "ks:ks_name":"Appalarajupeta",
    "ks:ks_pop":60,
    "ks:ks_type":"HABITATION",
    "name:eng_x_preferred":[
        "Appalarajupeta"
    ],
    "wof:name":"Appalarajupeta",
    "wof:placetype":"locality",
    "wof:population":60
},
  "geometry": {"coordinates":[82.648702,17.41968],"type":"Point"}
}