{
  "type": "Feature",
  "properties": {
    "gn:admin1_code":"37",
    "gn:admin2_code":"405.0",
    "gn:asciiname":"Jagdalla",
    "gn:country_code":"IN",
    "gn:dem":251,
    "gn:feature_class":"P",
    "gn:feature_code":"PPL",
    "gn:name":"Jagdall\u0101",
    "gn:population":0,
    "gn:timezone":"Asia/Kolkata",
    "iso:country":"IN",
    "wof:name":"Jagdalla",
    "wof:placetype":"locality"
},
  "geometry": {"coordinates":[82.91781,22.08609],"type":"Point"}
}