{
  "type": "Feature",
  "properties": {
    "iso:country":"IN",
    "name:ben_x_preferred":[
        "\u09ac\u09be\u09b2\u09bf\u0997\u099e\u09cd\u099c"
    ],
    "name:eng_x_preferred":[
        "Ballygunge"
    ],
    "name:eng_x_variant":[
        "Calcutta Ballygunge"
    ],
    "name:ind_x_preferred":[
        "Ballygunge"
    ],
    "name:jpn_x_preferred":[
        "\u30d0\u30ea\u30b0\u30f3\u30b8"
    ],
    "name:nld_x_preferred":[
        "Ballygunge"
    ],
    "name:zho_x_preferred":[
        "\u5df4\u5229\u6839\u6208"
    ],
    "qs:gn_adm0_cc":"IN",
    "qs:gn_fcode":"PPLX",
    "qs:gn_local":1275004,
    "qs:gn_nam_loc":"Kolkata, Kolkata, West Bengal, IN",
    "qs:gn_namadm1":"28",
    "qs:gn_name":"Ballygunge",
    "qs:local_max":2678,
    "qs:local_sum":20035,
    "qs:localhoods":53,
    "qs:name":"Ballygunge",
    "qs:name_adm0":"India",
    "qs:name_adm1":"West Bengal",
    "qs:name_adm2":"Kolkata",
    "qs:name_local":"Kolkata",
    "qs:photo_max":61,
    "qs:photo_sum":160,
    "qs:placetype":"Suburb",
    "qs:quad_count":13,
    "qs:woe_adm0":23424848,
    "qs:woe_adm1":2345761,
    "qs:woe_adm2":12586798,
    "qs:woe_lau":0,
    "qs:woe_local":2295386,
    "qs:woe_ver":"7.10.0",
    "wd:wordcount":404,
    "wof:lang":[
        "eng"
    ],
    "wof:name":"Ballygunge",
    "wof:placetype":"neighbourhood"
},
  "geometry": {"coordinates":[88.36582900000001,22.531585],"type":"Point"}
}