{
  "type": "Feature",
  "properties": {
    "iso:country":"IN",
    "ks:ks_name":"Karena Faliya",
    "ks:ks_pop":701,
    "ks:ks_type":"HABITATION",
    "name:eng_x_preferred":[
        "Karena Faliya"
    ],
    "wof:name":"Karena Faliya",
    "wof:placetype":"locality",
    "wof:population":701
},
  "geometry": {"coordinates":[73.46130599999999,23.137778],"type":"Point"}
}