{
  "type": "Feature",
  "properties": {
    "iso:country":"IN",
    "ks:ks_name":"Tarbin Cherra Grant",
    "ks:ks_pop":825,
    "ks:ks_type":"HABITATION",
    "name:eng_x_preferred":[
        "Tarbin Cherra Grant"
    ],
    "wof:name":"Tarbin Cherra Grant",
    "wof:placetype":"locality",
    "wof:population":825
},
  "geometry": {"coordinates":[92.388069,24.387228],"type":"Point"}
}