{
  "type": "Feature",
  "properties": {
    "gn:admin1_code":"34",
    "gn:admin2_code":"232.0",
    "gn:asciiname":"Kachhmipur",
    "gn:country_code":"IN",
    "gn:dem":68,
    "gn:feature_class":"P",
    "gn:feature_code":"PPL",
    "gn:name":"Kachhm\u012bpur",
    "gn:population":0,
    "gn:timezone":"Asia/Kolkata",
    "iso:country":"IN",
    "ks:ks_name":"Lachhmipur",
    "ks:ks_pop":1570,
    "ks:ks_type":"VILLAGE",
    "ks:ks_uagg_main":0,
    "name:eng_x_preferred":[
        "Lachhmipur"
    ],
    "wof:name":"Lachhmipur",
    "wof:placetype":"neighbourhood",
    "wof:population":1570
},
  "geometry": {"coordinates":[83.94049800000001,25.547323],"type":"Point"}
}