{
  "type": "Feature",
  "properties": {
    "iso:country":"IN",
    "ks:ks_name":"Toranmal",
    "ks:ks_pop":375,
    "ks:ks_type":"HABITATION",
    "name:eng_x_preferred":[
        "Toranmal"
    ],
    "wof:name":"Toranmal",
    "wof:placetype":"locality",
    "wof:population":375
},
  "geometry": {"coordinates":[73.54360800000001,20.391657],"type":"Point"}
}