{
  "type": "Feature",
  "properties": {
    "gn:admin1_code":"36",
    "gn:admin2_code":"166.0",
    "gn:asciiname":"Manpur",
    "gn:country_code":"IN",
    "gn:dem":276,
    "gn:feature_class":"P",
    "gn:feature_code":"PPL",
    "gn:name":"Manpur",
    "gn:population":0,
    "gn:timezone":"Asia/Kolkata",
    "iso:country":"IN",
    "name:ceb_x_preferred":[
        "Manpur"
    ],
    "name:fra_x_preferred":[
        "Manpur"
    ],
    "name:pol_x_preferred":[
        "Manpur"
    ],
    "name:swe_x_preferred":[
        "Manpur"
    ],
    "wof:name":"Manpur",
    "wof:placetype":"locality"
},
  "geometry": {"coordinates":[78.49721,25.26714],"type":"Point"}
}