{
  "type": "Feature",
  "properties": {
    "iso:country":"IN",
    "ks:ks_name":"Madhopur",
    "ks:ks_pop":1016,
    "ks:ks_type":"HABITATION",
    "ks:ks_uagg_main":0,
    "name:eng_x_preferred":[
        "Madhopur"
    ],
    "wof:name":"Madhopur",
    "wof:placetype":"neighbourhood",
    "wof:population":1016
},
  "geometry": {"coordinates":[84.556495,26.314419],"type":"Point"}
}