{
  "type": "Feature",
  "properties": {
    "iso:country":"IN",
    "ks:ks_name":"Gheghara",
    "ks:ks_pop":772,
    "ks:ks_type":"VILLAGE",
    "name:eng_x_preferred":[
        "Gheghara"
    ],
    "wof:name":"Gheghara",
    "wof:placetype":"locality",
    "wof:population":772
},
  "geometry": {"coordinates":[73.24098600000001,28.73788],"type":"Point"}
}