{
  "type": "Feature",
  "properties": {
    "gn:admin1_code":"25.0",
    "gn:admin2_code":"619.0",
    "gn:asciiname":"Manalur",
    "gn:country_code":"IN",
    "gn:dem":30,
    "gn:feature_class":"P",
    "gn:feature_code":"PPL",
    "gn:name":"Manal\u016br",
    "gn:population":0,
    "gn:timezone":"Asia/Kolkata",
    "iso:country":"IN",
    "ks:ks_name":"Manalur",
    "ks:ks_pop":1063,
    "ks:ks_type":"HABITATION",
    "name:eng_x_preferred":[
        "Manalur"
    ],
    "wof:name":"Manalur",
    "wof:placetype":"locality",
    "wof:population":1063
},
  "geometry": {"coordinates":[79.371757,10.78756],"type":"Point"}
}