{
  "type": "Feature",
  "properties": {
    "gn:admin1_code":"25",
    "gn:admin2_code":"604.0",
    "gn:asciiname":"Achcharapakkam",
    "gn:country_code":"IN",
    "gn:dem":22,
    "gn:feature_class":"P",
    "gn:feature_code":"PPL",
    "gn:name":"Achcharap\u0101kkam",
    "gn:population":0,
    "gn:timezone":"Asia/Kolkata",
    "iso:country":"IN",
    "wof:name":"Achcharapakkam",
    "wof:placetype":"neighbourhood"
},
  "geometry": {"coordinates":[80.09627,12.59867],"type":"Point"}
}