{
  "type": "Feature",
  "properties": {
    "iso:country":"IN",
    "ks:ks_alt_nam":"MAHA BABHANAUTI",
    "ks:ks_name":"Maha Babhanauti",
    "ks:ks_pop":100,
    "ks:ks_type":"HABITATION",
    "name:eng_x_preferred":[
        "Maha Babhanauti"
    ],
    "wof:name":"Maha Babhanauti",
    "wof:placetype":"locality",
    "wof:population":100
},
  "geometry": {"coordinates":[82.195154,25.542803],"type":"Point"}
}