{
  "type": "Feature",
  "properties": {
    "gn:admin1_code":"13.0",
    "gn:admin2_code":"592.0",
    "gn:asciiname":"Nettikulam",
    "gn:country_code":"IN",
    "gn:dem":52,
    "gn:feature_class":"P",
    "gn:feature_code":"PPL",
    "gn:name":"Nettikulam",
    "gn:population":0,
    "gn:timezone":"Asia/Kolkata",
    "iso:country":"IN",
    "wof:name":"Nettikulam",
    "wof:placetype":"locality"
},
  "geometry": {"coordinates":[76.25364999999999,11.40063],"type":"Point"}
}