{
  "type": "Feature",
  "properties": {
    "iso:country":"IN",
    "ks:ks_name":"Thrikkapallam",
    "ks:ks_pop":626,
    "ks:ks_type":"HABITATION",
    "ks:ks_uagg_main":0,
    "name:eng_x_preferred":[
        "Thrikkapallam"
    ],
    "wof:name":"Thrikkapallam",
    "wof:placetype":"neighbourhood",
    "wof:population":626
},
  "geometry": {"coordinates":[76.116894,10.457913],"type":"Point"}
}