{
  "type": "Feature",
  "properties": {
    "iso:country":"IN",
    "ks:ks_name":"Garhichand Khan",
    "ks:ks_pop":1514,
    "ks:ks_type":"VILLAGE",
    "ks:ks_uagg_main":0,
    "name:eng_x_preferred":[
        "Garhichand Khan"
    ],
    "wof:name":"Garhichand Khan",
    "wof:placetype":"neighbourhood",
    "wof:population":1514
},
  "geometry": {"coordinates":[79.94844000000001,27.606883],"type":"Point"}
}