{
  "type": "Feature",
  "properties": {
    "iso:country":"IN",
    "ks:ks_alt_nam":"Kate\u0101d\u012bh",
    "ks:ks_name":"Kateadih",
    "ks:ks_pop":720,
    "ks:ks_type":"VILLAGE",
    "name:eng_x_preferred":[
        "Kateadih"
    ],
    "name:eng_x_variant":[
        "Kate\u0101d\u012bh"
    ],
    "wof:name":"Kateadih",
    "wof:placetype":"locality",
    "wof:population":720
},
  "geometry": {"coordinates":[85.630116,23.256019],"type":"Point"}
}