{
  "type": "Feature",
  "properties": {
    "gn:admin1_code":"2",
    "gn:admin2_code":"545.0",
    "gn:asciiname":"Siripuram",
    "gn:country_code":"IN",
    "gn:dem":314,
    "gn:feature_class":"P",
    "gn:feature_code":"PPL",
    "gn:name":"Siripuram",
    "gn:population":0,
    "gn:timezone":"Asia/Kolkata",
    "iso:country":"IN",
    "ks:ks_name":"Sripuram",
    "ks:ks_pop":469,
    "ks:ks_type":"HABITATION",
    "name:eng_x_preferred":[
        "Sripuram"
    ],
    "name:eng_x_variant":[
        "Siripuram"
    ],
    "wof:name":"Sripuram",
    "wof:placetype":"locality",
    "wof:population":469
},
  "geometry": {"coordinates":[81.84762000000001,17.534665],"type":"Point"}
}