{
  "type": "Feature",
  "properties": {
    "iso:country":"IN",
    "ks:ks_name":"Hindur M",
    "ks:ks_pop":119,
    "ks:ks_type":"HABITATION",
    "name:eng_x_preferred":[
        "Hindur M"
    ],
    "wof:name":"Hindur M",
    "wof:placetype":"locality",
    "wof:population":119
},
  "geometry": {"coordinates":[80.62904,19.46487],"type":"Point"}
}