{
  "type": "Feature",
  "properties": {
    "iso:country":"IN",
    "ks:ks_name":"Rampur",
    "ks:ks_pop":316,
    "ks:ks_type":"HABITATION",
    "name:eng_x_preferred":[
        "Rampur"
    ],
    "wof:name":"Rampur",
    "wof:placetype":"locality",
    "wof:population":316
},
  "geometry": {"coordinates":[85.455505,25.195957],"type":"Point"}
}