{
  "type": "Feature",
  "properties": {
    "iso:country":"IN",
    "ks:ks_name":"Tiruchanur",
    "ks:ks_pop":12487,
    "ks:ks_type":"VILLAGE",
    "ks:ks_uagg_main":0,
    "name:eng_x_preferred":[
        "Tiruchanur"
    ],
    "wof:name":"Tiruchanur",
    "wof:placetype":"locality",
    "wof:population":12487
},
  "geometry": {"coordinates":[79.45047,13.60824],"type":"Point"}
}