{
  "type": "Feature",
  "properties": {
    "iso:country":"IN",
    "ks:ks_alt_nam":"pero toli",
    "ks:ks_name":"Pero Toli",
    "ks:ks_pop":104,
    "ks:ks_type":"HABITATION",
    "name:eng_x_preferred":[
        "Pero Toli"
    ],
    "wof:name":"Pero Toli",
    "wof:placetype":"locality",
    "wof:population":104
},
  "geometry": {"coordinates":[84.318877,22.539136],"type":"Point"}
}