{
  "type": "Feature",
  "properties": {
    "iso:country":"IN",
    "ks:ks_name":"Malda",
    "ks:ks_pop":1500,
    "ks:ks_type":"HABITATION",
    "name:eng_x_preferred":[
        "Malda"
    ],
    "wof:name":"Malda",
    "wof:placetype":"locality",
    "wof:population":1500
},
  "geometry": {"coordinates":[82.272222,27.54004],"type":"Point"}
}