{
  "type": "Feature",
  "properties": {
    "gn:admin1_code":"16",
    "gn:admin2_code":"503.0",
    "gn:asciiname":"Navthal Buzurg",
    "gn:country_code":"IN",
    "gn:dem":307,
    "gn:feature_class":"P",
    "gn:feature_code":"PPL",
    "gn:name":"Navthal Buzurg",
    "gn:population":0,
    "gn:timezone":"Asia/Kolkata",
    "iso:country":"IN",
    "wof:name":"Navthal Buzurg",
    "wof:placetype":"locality"
},
  "geometry": {"coordinates":[77.57773,20.94592],"type":"Point"}
}