{
  "type": "Feature",
  "properties": {
    "iso:country":"IN",
    "ks:ks_name":"Vellalampatti",
    "ks:ks_pop":274,
    "ks:ks_type":"VILLAGE",
    "name:eng_x_preferred":[
        "Vellalampatti"
    ],
    "wof:name":"Vellalampatti",
    "wof:placetype":"locality",
    "wof:population":274
},
  "geometry": {"coordinates":[78.667424,12.118998],"type":"Point"}
}