{
  "type": "Feature",
  "properties": {
    "gn:admin1_code":"39.0",
    "gn:admin2_code":"66.0",
    "gn:asciiname":"Bhadyun",
    "gn:country_code":"IN",
    "gn:dem":1384,
    "gn:feature_class":"P",
    "gn:feature_code":"PPL",
    "gn:name":"Bhadyun",
    "gn:population":0,
    "gn:timezone":"Asia/Kolkata",
    "iso:country":"IN",
    "ks:ks_name":"Bhadyun",
    "ks:ks_type":"VILLAGE",
    "name:eng_x_preferred":[
        "Bhadyun"
    ],
    "wof:name":"Bhadyun",
    "wof:placetype":"locality"
},
  "geometry": {"coordinates":[79.543685,29.528821],"type":"Point"}
}