{
  "type": "Feature",
  "properties": {
    "gn:admin1_code":"11.0",
    "gn:admin2_code":"033",
    "gn:asciiname":"Chayotha",
    "gn:country_code":"IN",
    "gn:dem":1236,
    "gn:feature_class":"P",
    "gn:feature_code":"PPL",
    "gn:name":"Chayotha",
    "gn:population":0,
    "gn:timezone":"Asia/Kolkata",
    "iso:country":"IN",
    "wof:name":"Chayotha",
    "wof:placetype":"locality"
},
  "geometry": {"coordinates":[77.08750000000001,31.19444],"type":"Point"}
}