{
  "type": "Feature",
  "properties": {
    "gn:admin1_code":"36",
    "gn:admin2_code":"186.0",
    "gn:asciiname":"Kant Ganga",
    "gn:country_code":"IN",
    "gn:dem":87,
    "gn:feature_class":"P",
    "gn:feature_code":"PPL",
    "gn:name":"K\u0101nt Ganga",
    "gn:population":0,
    "gn:timezone":"Asia/Kolkata",
    "iso:country":"IN",
    "ks:ks_alt_nam":"K\u0101nt Ganga",
    "ks:ks_name":"Kant Ganga",
    "ks:ks_type":"VILLAGE",
    "ks:ks_uagg_main":0,
    "name:eng_x_preferred":[
        "Kant Ganga"
    ],
    "name:eng_x_variant":[
        "K\u0101nt Ganga"
    ],
    "wof:name":"Kant Ganga",
    "wof:placetype":"neighbourhood"
},
  "geometry": {"coordinates":[82.952456,26.789677],"type":"Point"}
}