{
  "type": "Feature",
  "properties": {
    "iso:country":"IN",
    "ks:ks_alt_nam":"M\u0101ndvi Reserved Forest",
    "ks:ks_name":"Mandvi Reserved Forest",
    "ks:ks_type":"VILLAGE",
    "name:eng_x_preferred":[
        "Mandvi Reserved Forest"
    ],
    "name:eng_x_variant":[
        "M\u0101ndvi Reserved Forest"
    ],
    "wof:name":"Mandvi Reserved Forest",
    "wof:placetype":"locality"
},
  "geometry": {"coordinates":[78.404864,21.651023],"type":"Point"}
}