{
  "type": "Feature",
  "properties": {
    "iso:country":"IN",
    "ks:ks_name":"Khamesripara Purinbsti",
    "ks:ks_pop":162,
    "ks:ks_type":"HABITATION",
    "name:eng_x_preferred":[
        "Khamesripara Purinbsti"
    ],
    "wof:name":"Khamesripara Purinbsti",
    "wof:placetype":"locality",
    "wof:population":162
},
  "geometry": {"coordinates":[81.568198,20.525544],"type":"Point"}
}