{
  "type": "Feature",
  "properties": {
    "gn:admin1_code":"36.0",
    "gn:admin2_code":"135.0",
    "gn:asciiname":"Daulpuri Bamanian",
    "gn:country_code":"IN",
    "gn:dem":211,
    "gn:feature_class":"P",
    "gn:feature_code":"PPL",
    "gn:name":"Daulpuri Bamani\u0101n",
    "gn:population":0,
    "gn:timezone":"Asia/Kolkata",
    "iso:country":"IN",
    "wof:name":"Daulpuri Bamanian",
    "wof:placetype":"neighbourhood"
},
  "geometry": {"coordinates":[78.87254,29.02885],"type":"Point"}
}