{
  "type": "Feature",
  "properties": {
    "iso:country":"IN",
    "ks:ks_name":"Sonpur",
    "ks:ks_pop":194,
    "ks:ks_type":"VILLAGE",
    "name:eng_x_preferred":[
        "Sonpur"
    ],
    "wof:name":"Sonpur",
    "wof:placetype":"locality",
    "wof:population":194
},
  "geometry": {"coordinates":[78.990827,24.068084],"type":"Point"}
}