{
  "type": "Feature",
  "properties": {
    "iso:country":"IN",
    "ks:ks_alt_nam":"PALLEPALEM",
    "ks:ks_name":"Pallepalem",
    "ks:ks_pop":10,
    "ks:ks_type":"HABITATION",
    "name:eng_x_preferred":[
        "Pallepalem"
    ],
    "wof:name":"Pallepalem",
    "wof:placetype":"locality",
    "wof:population":10
},
  "geometry": {"coordinates":[80.85258,16.014288],"type":"Point"}
}