{
  "type": "Feature",
  "properties": {
    "gn:admin1_code":"16",
    "gn:admin2_code":"509.0",
    "gn:asciiname":"Khatora",
    "gn:country_code":"IN",
    "gn:dem":227,
    "gn:feature_class":"P",
    "gn:feature_code":"PPL",
    "gn:name":"Kh\u0101tora",
    "gn:population":0,
    "gn:timezone":"Asia/Kolkata",
    "iso:country":"IN",
    "wof:name":"Khatora",
    "wof:placetype":"locality"
},
  "geometry": {"coordinates":[79.46693,20.39089],"type":"Point"}
}