{
  "type": "Feature",
  "properties": {
    "gn:admin1_code":"35",
    "gn:admin2_code":"419.0",
    "gn:asciiname":"Rithora",
    "gn:country_code":"IN",
    "gn:dem":170,
    "gn:feature_class":"P",
    "gn:feature_code":"PPL",
    "gn:name":"Rithora",
    "gn:population":0,
    "gn:timezone":"Asia/Kolkata",
    "iso:country":"IN",
    "name:bpy_x_preferred":[
        "\u09b0\u09bf\u09a5\u09cb\u09b0\u09be"
    ],
    "name:ita_x_preferred":[
        "Rithora"
    ],
    "name:msa_x_preferred":[
        "Rithora"
    ],
    "name:nld_x_preferred":[
        "Rithora"
    ],
    "name:pol_x_preferred":[
        "Rithora"
    ],
    "name:por_x_preferred":[
        "Rithora"
    ],
    "name:urd_x_preferred":[
        "\u0631\u0679\u06be\u0648\u0631\u0627"
    ],
    "name:vie_x_preferred":[
        "Rithora"
    ],
    "name:zho_x_preferred":[
        "\u91cc\u6258\u62c9"
    ],
    "wof:name":"Rithora",
    "wof:placetype":"locality"
},
  "geometry": {"coordinates":[78.16880999999999,26.62773],"type":"Point"}
}