{
  "type": "Feature",
  "properties": {
    "iso:country":"IN",
    "ks:ks_alt_nam":"adnalli",
    "ks:ks_name":"Adnalli",
    "ks:ks_pop":84,
    "ks:ks_type":"HABITATION",
    "name:eng_x_preferred":[
        "Adnalli"
    ],
    "wof:name":"Adnalli",
    "wof:placetype":"locality",
    "wof:population":84
},
  "geometry": {"coordinates":[74.907231,14.740257],"type":"Point"}
}