{
  "type": "Feature",
  "properties": {
    "iso:country":"IN",
    "ks:ks_name":"Libupadar",
    "ks:ks_pop":197,
    "ks:ks_type":"HABITATION",
    "name:eng_x_preferred":[
        "Libupadar"
    ],
    "wof:name":"Libupadar",
    "wof:placetype":"locality",
    "wof:population":197
},
  "geometry": {"coordinates":[81.69708799999999,18.448501],"type":"Point"}
}