{
  "type": "Feature",
  "properties": {
    "iso:country":"IN",
    "ks:ks_name":"Janakpur",
    "ks:ks_pop":653,
    "ks:ks_type":"HABITATION",
    "name:eng_x_preferred":[
        "Janakpur"
    ],
    "wof:name":"Janakpur",
    "wof:placetype":"locality",
    "wof:population":653
},
  "geometry": {"coordinates":[86.886376,24.981717],"type":"Point"}
}