{
  "type": "Feature",
  "properties": {
    "iso:country":"IN",
    "ks:ks_name":"Palakakuzhi",
    "ks:ks_pop":327,
    "ks:ks_type":"HABITATION",
    "name:eng_x_preferred":[
        "Palakakuzhi"
    ],
    "wof:name":"Palakakuzhi",
    "wof:placetype":"locality",
    "wof:population":327
},
  "geometry": {"coordinates":[76.228239,11.075588],"type":"Point"}
}