{
  "type": "Feature",
  "properties": {
    "iso:country":"IN",
    "ks:ks_name":"Pattuvam",
    "ks:ks_pop":15003,
    "ks:ks_type":"VILLAGE",
    "ks:ks_uagg_main":0,
    "name:eng_x_preferred":[
        "Pattuvam"
    ],
    "wof:name":"Pattuvam",
    "wof:placetype":"locality",
    "wof:population":15003
},
  "geometry": {"coordinates":[75.33880600000001,12.023521],"type":"Point"}
}