{
  "type": "Feature",
  "properties": {
    "iso:country":"IN",
    "ks:ks_name":"Matohar",
    "ks:ks_pop":30,
    "ks:ks_type":"VILLAGE",
    "name:eng_x_preferred":[
        "Matohar"
    ],
    "wof:name":"Matohar",
    "wof:placetype":"locality",
    "wof:population":30
},
  "geometry": {"coordinates":[81.50901399999999,23.767149],"type":"Point"}
}