{
  "type": "Feature",
  "properties": {
    "iso:country":"IN",
    "ks:ks_name":"Thorlebag",
    "ks:ks_pop":268,
    "ks:ks_type":"HABITATION",
    "name:eng_x_preferred":[
        "Thorlebag"
    ],
    "wof:name":"Thorlebag",
    "wof:placetype":"locality",
    "wof:population":268
},
  "geometry": {"coordinates":[74.138859,14.883566],"type":"Point"}
}