{
  "type": "Feature",
  "properties": {
    "iso:country":"IN",
    "ks:ks_alt_nam":"JJ Nagar",
    "ks:ks_name":"Jj Nagar",
    "ks:ks_pop":1560,
    "ks:ks_type":"HABITATION",
    "ks:ks_uagg_main":0,
    "name:eng_x_preferred":[
        "Jj Nagar"
    ],
    "wof:name":"Jj Nagar",
    "wof:placetype":"locality",
    "wof:population":1560
},
  "geometry": {"coordinates":[77.01182,10.942803],"type":"Point"}
}