{
  "type": "Feature",
  "properties": {
    "iso:country":"IN",
    "ks:ks_name":"Kalardia Top",
    "ks:ks_pop":446,
    "ks:ks_type":"HABITATION",
    "name:eng_x_preferred":[
        "Kalardia Top"
    ],
    "wof:name":"Kalardia Top",
    "wof:placetype":"locality",
    "wof:population":446
},
  "geometry": {"coordinates":[91.308862,26.112958],"type":"Point"}
}