{
  "type": "Feature",
  "properties": {
    "iso:country":"IN",
    "ks:ks_name":"Sonarwadi",
    "ks:ks_pop":36,
    "ks:ks_type":"HABITATION",
    "name:eng_x_preferred":[
        "Sonarwadi"
    ],
    "wof:name":"Sonarwadi",
    "wof:placetype":"locality",
    "wof:population":36
},
  "geometry": {"coordinates":[73.728386,16.591302],"type":"Point"}
}