{
  "type": "Feature",
  "properties": {
    "iso:country":"IN",
    "ks:ks_name":"Barmal",
    "ks:ks_pop":441,
    "ks:ks_type":"HABITATION",
    "name:eng_x_preferred":[
        "Barmal"
    ],
    "wof:name":"Barmal",
    "wof:placetype":"locality",
    "wof:population":441
},
  "geometry": {"coordinates":[84.051102,21.932433],"type":"Point"}
}