{
  "type": "Feature",
  "properties": {
    "iso:country":"IN",
    "ks:ks_name":"Bardogachibatitaki",
    "ks:ks_pop":115,
    "ks:ks_type":"HABITATION",
    "name:eng_x_preferred":[
        "Bardogachibatitaki"
    ],
    "wof:name":"Bardogachibatitaki",
    "wof:placetype":"locality",
    "wof:population":115
},
  "geometry": {"coordinates":[87.44014799999999,22.323883],"type":"Point"}
}