{
  "type": "Feature",
  "properties": {
    "iso:country":"IN",
    "ks:ks_name":"Lakhnia",
    "ks:ks_pop":1763,
    "ks:ks_type":"VILLAGE",
    "ks:ks_uagg_main":0,
    "name:eng_x_preferred":[
        "Lakhnia"
    ],
    "wof:name":"Lakhnia",
    "wof:placetype":"neighbourhood",
    "wof:population":1763
},
  "geometry": {"coordinates":[82.69441,26.354605],"type":"Point"}
}