{
  "type": "Feature",
  "properties": {
    "iso:country":"IN",
    "ks:ks_name":"Sadulaniyon Ka Tala",
    "ks:ks_pop":807,
    "ks:ks_type":"VILLAGE",
    "name:eng_x_preferred":[
        "Sadulaniyon Ka Tala"
    ],
    "wof:name":"Sadulaniyon Ka Tala",
    "wof:placetype":"locality",
    "wof:population":807
},
  "geometry": {"coordinates":[71.444778,25.486367],"type":"Point"}
}