{
  "type": "Feature",
  "properties": {
    "iso:country":"IN",
    "ks:ks_name":"Enaet Chak",
    "ks:ks_pop":0,
    "ks:ks_type":"VILLAGE",
    "name:eng_x_preferred":[
        "Enaet Chak"
    ],
    "wof:name":"Enaet Chak",
    "wof:placetype":"locality",
    "wof:population":0
},
  "geometry": {"coordinates":[85.189311,24.666496],"type":"Point"}
}