{
  "type": "Feature",
  "properties": {
    "iso:country":"IN",
    "ks:ks_name":"Thazheniravil",
    "ks:ks_pop":1378,
    "ks:ks_type":"HABITATION",
    "name:eng_x_preferred":[
        "Thazheniravil"
    ],
    "wof:name":"Thazheniravil",
    "wof:placetype":"locality",
    "wof:population":1378
},
  "geometry": {"coordinates":[75.85566799999999,11.753724],"type":"Point"}
}