{
  "type": "Feature",
  "properties": {
    "iso:country":"IN",
    "ks:ks_name":"Wakalan",
    "ks:ks_pop":1790,
    "ks:ks_type":"HABITATION",
    "name:eng_x_preferred":[
        "Wakalan"
    ],
    "wof:name":"Wakalan",
    "wof:placetype":"neighbourhood",
    "wof:population":1790
},
  "geometry": {"coordinates":[73.095844,19.121299],"type":"Point"}
}