{
  "type": "Feature",
  "properties": {
    "iso:country":"IN",
    "ks:ks_name":"Harizen Tola",
    "ks:ks_pop":82,
    "ks:ks_type":"HABITATION",
    "name:eng_x_preferred":[
        "Harizen Tola"
    ],
    "wof:name":"Harizen Tola",
    "wof:placetype":"locality",
    "wof:population":82
},
  "geometry": {"coordinates":[86.085759,25.407828],"type":"Point"}
}