{
  "type": "Feature",
  "properties": {
    "iso:country":"IN",
    "ks:ks_name":"Yennaikattanpuram",
    "ks:ks_pop":150,
    "ks:ks_type":"HABITATION",
    "name:eng_x_preferred":[
        "Yennaikattanpuram"
    ],
    "wof:name":"Yennaikattanpuram",
    "wof:placetype":"locality",
    "wof:population":150
},
  "geometry": {"coordinates":[79.58225,12.86292],"type":"Point"}
}