{
  "type": "Feature",
  "properties": {
    "iso:country":"IN",
    "ks:ks_name":"Nariapara",
    "ks:ks_pop":26,
    "ks:ks_type":"HABITATION",
    "name:eng_x_preferred":[
        "Nariapara"
    ],
    "wof:name":"Nariapara",
    "wof:placetype":"locality",
    "wof:population":26
},
  "geometry": {"coordinates":[82.530046,19.854631],"type":"Point"}
}