{
  "type": "Feature",
  "properties": {
    "iso:country":"IN",
    "ks:ks_name":"Biljiala",
    "ks:ks_pop":0,
    "ks:ks_type":"VILLAGE",
    "name:eng_x_preferred":[
        "Biljiala"
    ],
    "wof:name":"Biljiala",
    "wof:placetype":"locality",
    "wof:population":0
},
  "geometry": {"coordinates":[88.42994299999999,23.749929],"type":"Point"}
}