{
  "type": "Feature",
  "properties": {
    "iso:country":"IN",
    "qs:name":"Bhilai Nagar",
    "qs:name_adm0":"India",
    "qs:name_adm1":"Chhattisgarh",
    "qs:photos":70,
    "qs:photos_1k":14,
    "qs:photos_9k":1,
    "qs:photos_9r":2,
    "qs:photos_all":70,
    "qs:photos_sr":2,
    "qs:placetype":"Town",
    "qs:pop_sr":"0",
    "wof:name":"Bhilai Nagar",
    "wof:placetype":"locality"
},
  "geometry": {"coordinates":[81.369102,21.1746885],"type":"Point"}
}