{
  "type": "Feature",
  "properties": {
    "gn:admin1_code":"35",
    "gn:admin2_code":"456.0",
    "gn:asciiname":"Sarekhatola",
    "gn:country_code":"IN",
    "gn:dem":517,
    "gn:feature_class":"P",
    "gn:feature_code":"PPL",
    "gn:name":"Sarekh\u0101tola",
    "gn:population":0,
    "gn:timezone":"Asia/Kolkata",
    "iso:country":"IN",
    "wof:name":"Sarekhatola",
    "wof:placetype":"locality"
},
  "geometry": {"coordinates":[79.70877,22.35176],"type":"Point"}
}