{
  "type": "Feature",
  "properties": {
    "iso:country":"IN",
    "ks:ks_name":"Manwadi",
    "ks:ks_pop":145,
    "ks:ks_type":"HABITATION",
    "name:eng_x_preferred":[
        "Manwadi"
    ],
    "wof:name":"Manwadi",
    "wof:placetype":"locality",
    "wof:population":145
},
  "geometry": {"coordinates":[77.603195,19.504522],"type":"Point"}
}