{
  "type": "Feature",
  "properties": {
    "gn:admin1_code":"11.0",
    "gn:admin2_code":"31.0",
    "gn:asciiname":"Dhanechi",
    "gn:country_code":"IN",
    "gn:dem":1799,
    "gn:feature_class":"P",
    "gn:feature_code":"PPL",
    "gn:name":"Dhanechi",
    "gn:population":0,
    "gn:timezone":"Asia/Kolkata",
    "iso:country":"IN",
    "wof:name":"Dhanechi",
    "wof:placetype":"locality"
},
  "geometry": {"coordinates":[77.19450999999999,30.98501],"type":"Point"}
}