{
  "type": "Feature",
  "properties": {
    "iso:country":"IN",
    "ks:ks_name":"Jakha",
    "ks:ks_pop":831,
    "ks:ks_type":"HABITATION",
    "name:eng_x_preferred":[
        "Jakha"
    ],
    "wof:name":"Jakha",
    "wof:placetype":"locality",
    "wof:population":831
},
  "geometry": {"coordinates":[79.605119,27.333463],"type":"Point"}
}