{
  "type": "Feature",
  "properties": {
    "gn:admin1_code":"35.0",
    "gn:admin2_code":"430.0",
    "gn:asciiname":"Khatkhari Chhoti",
    "gn:country_code":"IN",
    "gn:dem":123,
    "gn:feature_class":"P",
    "gn:feature_code":"PPL",
    "gn:name":"Khatkhari Chhoti",
    "gn:population":0,
    "gn:timezone":"Asia/Kolkata",
    "iso:country":"IN",
    "wof:name":"Khatkhari Chhoti",
    "wof:placetype":"neighbourhood"
},
  "geometry": {"coordinates":[81.56395999999999,25.12632],"type":"Point"}
}