{
  "type": "Feature",
  "properties": {
    "gn:admin1_code":"16",
    "gn:admin2_code":"505.0",
    "gn:asciiname":"Kalandri",
    "gn:country_code":"IN",
    "gn:dem":300,
    "gn:feature_class":"P",
    "gn:feature_code":"PPL",
    "gn:name":"Kal\u0101ndri",
    "gn:population":0,
    "gn:timezone":"Asia/Kolkata",
    "iso:country":"IN",
    "ks:ks_alt_nam":"Kal\u0101ndri",
    "ks:ks_name":"Kalandri",
    "ks:ks_pop":413,
    "ks:ks_type":"VILLAGE",
    "ks:ks_uagg_main":0,
    "name:eng_x_preferred":[
        "Kalandri"
    ],
    "name:eng_x_variant":[
        "Kal\u0101ndri"
    ],
    "name:hin_x_preferred":[
        "\u0915\u093e\u0932\u0928\u094d\u0926\u094d\u0930\u0940"
    ],
    "wof:name":"Kalandri",
    "wof:placetype":"neighbourhood",
    "wof:population":413
},
  "geometry": {"coordinates":[79.291876,20.968877],"type":"Point"}
}