{
  "type": "Feature",
  "properties": {
    "gn:admin1_code":"11.0",
    "gn:admin2_code":"27.0",
    "gn:asciiname":"Karnala",
    "gn:country_code":"IN",
    "gn:dem":1599,
    "gn:feature_class":"P",
    "gn:feature_code":"PPL",
    "gn:name":"Karn\u0101la",
    "gn:population":0,
    "gn:timezone":"Asia/Kolkata",
    "iso:country":"IN",
    "wof:name":"Karnala",
    "wof:placetype":"locality"
},
  "geometry": {"coordinates":[77.06050999999999,31.52717],"type":"Point"}
}