{
  "type": "Feature",
  "properties": {
    "iso:country":"IN",
    "ks:ks_alt_nam":"Sal\u0101rpur",
    "ks:ks_name":"Salarpur",
    "ks:ks_pop":0,
    "ks:ks_type":"VILLAGE",
    "name:eng_x_preferred":[
        "Salarpur"
    ],
    "name:eng_x_variant":[
        "Sal\u0101rpur"
    ],
    "wof:name":"Salarpur",
    "wof:placetype":"locality",
    "wof:population":0
},
  "geometry": {"coordinates":[83.908699,25.497086],"type":"Point"}
}