{
  "type": "Feature",
  "properties": {
    "iso:country":"IN",
    "ks:ks_name":"Kosapara",
    "ks:ks_pop":147,
    "ks:ks_type":"HABITATION",
    "name:eng_x_preferred":[
        "Kosapara"
    ],
    "wof:name":"Kosapara",
    "wof:placetype":"locality",
    "wof:population":147
},
  "geometry": {"coordinates":[81.71648999999999,18.945153],"type":"Point"}
}