{
  "type": "Feature",
  "properties": {
    "gn:admin1_code":"20.0",
    "gn:admin2_code":"267.0",
    "gn:asciiname":"Shamtorr",
    "gn:country_code":"IN",
    "gn:dem":1666,
    "gn:feature_class":"P",
    "gn:feature_code":"PPL",
    "gn:name":"Shamtorr",
    "gn:population":0,
    "gn:timezone":"Asia/Kolkata",
    "iso:country":"IN",
    "wof:name":"Shamtorr",
    "wof:placetype":"locality"
},
  "geometry": {"coordinates":[94.87993,26.05954],"type":"Point"}
}