{
  "type": "Feature",
  "properties": {
    "iso:country":"IN",
    "ks:ks_name":"Rajalividuthi",
    "ks:ks_pop":203,
    "ks:ks_type":"HABITATION",
    "ks:ks_uagg_main":0,
    "name:eng_x_preferred":[
        "Rajalividuthi"
    ],
    "wof:name":"Rajalividuthi",
    "wof:placetype":"neighbourhood",
    "wof:population":203
},
  "geometry": {"coordinates":[79.222455,10.469487],"type":"Point"}
}