{
  "type": "Feature",
  "properties": {
    "iso:country":"IN",
    "ks:ks_alt_nam":"BAROBASA",
    "ks:ks_name":"Barobasa",
    "ks:ks_pop":146,
    "ks:ks_type":"HABITATION",
    "name:eng_x_preferred":[
        "Barobasa"
    ],
    "wof:name":"Barobasa",
    "wof:placetype":"locality",
    "wof:population":146
},
  "geometry": {"coordinates":[85.89976299999999,22.421765],"type":"Point"}
}