{
  "type": "Feature",
  "properties": {
    "gn:admin1_code":"19.0",
    "gn:admin2_code":"561.0",
    "gn:asciiname":"Hire Vadvatti",
    "gn:country_code":"IN",
    "gn:dem":604,
    "gn:feature_class":"P",
    "gn:feature_code":"PPL",
    "gn:name":"Hire Vadvatti",
    "gn:population":0,
    "gn:timezone":"Asia/Kolkata",
    "iso:country":"IN",
    "wof:name":"Hire Vadvatti",
    "wof:placetype":"locality"
},
  "geometry": {"coordinates":[75.78305999999998,15.22353],"type":"Point"}
}