{
  "type": "Feature",
  "properties": {
    "iso:country":"IN",
    "ks:ks_name":"Gowariguda",
    "ks:ks_pop":85,
    "ks:ks_type":"HABITATION",
    "name:eng_x_preferred":[
        "Gowariguda"
    ],
    "wof:name":"Gowariguda",
    "wof:placetype":"locality",
    "wof:population":85
},
  "geometry": {"coordinates":[79.27970500000001,19.231791],"type":"Point"}
}