{
  "type": "Feature",
  "properties": {
    "gn:admin1_code":"19.0",
    "gn:admin2_code":"581.0",
    "gn:asciiname":"Gutlur",
    "gn:country_code":"IN",
    "gn:dem":806,
    "gn:feature_class":"P",
    "gn:feature_code":"PPL",
    "gn:name":"Gutl\u016br",
    "gn:population":0,
    "gn:timezone":"Asia/Kolkata",
    "iso:country":"IN",
    "wof:name":"Gutlur",
    "wof:placetype":"locality"
},
  "geometry": {"coordinates":[78.1112,12.88883],"type":"Point"}
}