{
  "type": "Feature",
  "properties": {
    "iso:country":"IN",
    "ks:ks_name":"Niz-Borkhola Pt II",
    "ks:ks_pop":2247,
    "ks:ks_type":"VILLAGE",
    "ks:ks_uagg_main":0,
    "name:eng_x_preferred":[
        "Niz-Borkhola Pt II"
    ],
    "wof:name":"Niz-Borkhola Pt II",
    "wof:placetype":"neighbourhood",
    "wof:population":2247
},
  "geometry": {"coordinates":[92.74303,24.920465],"type":"Point"}
}