{
  "type": "Feature",
  "properties": {
    "iso:country":"IN",
    "ks:ks_name":"Sivanandipatty",
    "ks:ks_pop":165,
    "ks:ks_type":"HABITATION",
    "name:eng_x_preferred":[
        "Sivanandipatty"
    ],
    "wof:name":"Sivanandipatty",
    "wof:placetype":"locality",
    "wof:population":165
},
  "geometry": {"coordinates":[77.677425,9.413757],"type":"Point"}
}