{
  "type": "Feature",
  "properties": {
    "gn:admin1_code":"24.0",
    "gn:admin2_code":"117.0",
    "gn:asciiname":"Laj",
    "gn:country_code":"IN",
    "gn:dem":362,
    "gn:feature_class":"P",
    "gn:feature_code":"PPL",
    "gn:name":"Laj",
    "gn:population":0,
    "gn:timezone":"Asia/Kolkata",
    "iso:country":"IN",
    "name:hat_x_preferred":[
        "Laj"
    ],
    "name:srp_x_preferred":[
        "\u041b\u0430\u0458"
    ],
    "wof:name":"Laj",
    "wof:placetype":"neighbourhood"
},
  "geometry": {"coordinates":[72.95659000000001,24.75014],"type":"Point"}
}