{
  "type": "Feature",
  "properties": {
    "iso:country":"IN",
    "ks:ks_alt_nam":"NAYA NAGAR",
    "ks:ks_name":"Naya Nagar",
    "ks:ks_pop":292,
    "ks:ks_type":"HABITATION",
    "name:eng_x_preferred":[
        "Naya Nagar"
    ],
    "wof:name":"Naya Nagar",
    "wof:placetype":"locality",
    "wof:population":292
},
  "geometry": {"coordinates":[85.643914,25.04881],"type":"Point"}
}