{
  "type": "Feature",
  "properties": {
    "iso:country":"IN",
    "ks:ks_name":"Khohra",
    "ks:ks_pop":233,
    "ks:ks_type":"VILLAGE",
    "name:eng_x_preferred":[
        "Khohra"
    ],
    "wof:name":"Khohra",
    "wof:placetype":"locality",
    "wof:population":233
},
  "geometry": {"coordinates":[82.050472,23.78257],"type":"Point"}
}