{
  "type": "Feature",
  "properties": {
    "gn:admin1_code":"37",
    "gn:admin2_code":"413.0",
    "gn:asciiname":"Latmarka",
    "gn:country_code":"IN",
    "gn:dem":417,
    "gn:feature_class":"P",
    "gn:feature_code":"PPL",
    "gn:name":"L\u0101tmarka",
    "gn:population":0,
    "gn:timezone":"Asia/Kolkata",
    "iso:country":"IN",
    "ks:ks_alt_nam":"L\u0101tmarka",
    "ks:ks_name":"Latmarka",
    "ks:ks_type":"VILLAGE",
    "name:eng_x_preferred":[
        "Latmarka"
    ],
    "name:eng_x_variant":[
        "L\u0101tmarka"
    ],
    "wof:name":"Latmarka",
    "wof:placetype":"locality"
},
  "geometry": {"coordinates":[80.869474,20.107747],"type":"Point"}
}