{
  "type": "Feature",
  "properties": {
    "iso:country":"IN",
    "ks:ks_name":"Marada",
    "ks:ks_pop":60,
    "ks:ks_type":"VILLAGE",
    "name:eng_x_preferred":[
        "Marada"
    ],
    "wof:name":"Marada",
    "wof:placetype":"locality",
    "wof:population":60
},
  "geometry": {"coordinates":[84.78627299999999,20.577618],"type":"Point"}
}