{
  "type": "Feature",
  "properties": {
    "iso:country":"IN",
    "ks:ks_alt_nam":"PATILWASTI",
    "ks:ks_name":"Patilwasti",
    "ks:ks_pop":75,
    "ks:ks_type":"HABITATION",
    "name:eng_x_preferred":[
        "Patilwasti"
    ],
    "wof:name":"Patilwasti",
    "wof:placetype":"locality",
    "wof:population":75
},
  "geometry": {"coordinates":[74.294692,16.978736],"type":"Point"}
}