{
  "type": "Feature",
  "properties": {
    "gn:admin1_code":"36.0",
    "gn:admin2_code":"161",
    "gn:asciiname":"Gadhia",
    "gn:country_code":"IN",
    "gn:dem":148,
    "gn:feature_class":"P",
    "gn:feature_code":"PPL",
    "gn:name":"Gadhia",
    "gn:population":0,
    "gn:timezone":"Asia/Kolkata",
    "iso:country":"IN",
    "name:cat_x_preferred":[
        "Gadhia"
    ],
    "name:und_x_variant":[
        "Garhia H\u0101th\u012bsingh"
    ],
    "wof:name":"Gadhia",
    "wof:placetype":"locality"
},
  "geometry": {"coordinates":[79.20907,26.85065],"type":"Point"}
}