{
  "type": "Feature",
  "properties": {
    "iso:country":"IN",
    "ks:ks_name":"N Gudadahatti",
    "ks:ks_pop":269,
    "ks:ks_type":"HABITATION",
    "name:eng_x_preferred":[
        "N Gudadahatti"
    ],
    "wof:name":"N Gudadahatti",
    "wof:placetype":"locality",
    "wof:population":269
},
  "geometry": {"coordinates":[76.09999999999999,14.34],"type":"Point"}
}