{
  "type": "Feature",
  "properties": {
    "iso:country":"IN",
    "ks:ks_name":"Bhalauri",
    "ks:ks_pop":144,
    "ks:ks_type":"VILLAGE",
    "name:eng_x_preferred":[
        "Bhalauri"
    ],
    "wof:name":"Bhalauri",
    "wof:placetype":"locality",
    "wof:population":144
},
  "geometry": {"coordinates":[80.132515,29.91756],"type":"Point"}
}