{
  "type": "Feature",
  "properties": {
    "iso:country":"IN",
    "ks:ks_alt_nam":"Kamarbandha TE",
    "ks:ks_name":"Kamarbandha Te",
    "ks:ks_pop":1000,
    "ks:ks_type":"HABITATION",
    "name:eng_x_preferred":[
        "Kamarbandha Te"
    ],
    "wof:name":"Kamarbandha Te",
    "wof:placetype":"locality",
    "wof:population":1000
},
  "geometry": {"coordinates":[94.219706,26.689118],"type":"Point"}
}