{
  "type": "Feature",
  "properties": {
    "iso:country":"IN",
    "ks:ks_name":"Koya Khumji",
    "ks:ks_pop":219,
    "ks:ks_type":"HABITATION",
    "name:eng_x_preferred":[
        "Koya Khumji"
    ],
    "wof:name":"Koya Khumji",
    "wof:placetype":"locality",
    "wof:population":219
},
  "geometry": {"coordinates":[73.24244,22.974529],"type":"Point"}
}