{
  "type": "Feature",
  "properties": {
    "iso:country":"IN",
    "ks:ks_name":"Amartal",
    "ks:ks_pop":147,
    "ks:ks_type":"HABITATION",
    "name:eng_x_preferred":[
        "Amartal"
    ],
    "wof:name":"Amartal",
    "wof:placetype":"locality",
    "wof:population":147
},
  "geometry": {"coordinates":[83.0181,22.177545],"type":"Point"}
}