{
  "type": "Feature",
  "properties": {
    "iso:country":"IN",
    "qs:name":"Pulipakkam",
    "qs:name_adm0":"India",
    "qs:name_adm1":"Tamil Nadu",
    "qs:photos":7,
    "qs:photos_1k":1,
    "qs:photos_9k":1,
    "qs:photos_9r":1,
    "qs:photos_all":7,
    "qs:photos_sr":1,
    "qs:placetype":"Town",
    "qs:pop_sr":"0",
    "wof:name":"Pulipakkam",
    "wof:placetype":"locality"
},
  "geometry": {"coordinates":[79.978065,12.710846],"type":"Point"}
}