{
  "type": "Feature",
  "properties": {
    "gn:admin1_code":"24",
    "gn:admin2_code":"101.0",
    "gn:asciiname":"Manna",
    "gn:country_code":"IN",
    "gn:dem":209,
    "gn:feature_class":"P",
    "gn:feature_code":"PPL",
    "gn:name":"M\u0101nna",
    "gn:population":0,
    "gn:timezone":"Asia/Kolkata",
    "iso:country":"IN",
    "name:afr_x_preferred":[
        "Manna"
    ],
    "name:ara_x_preferred":[
        "\u0645\u0646"
    ],
    "name:aze_x_preferred":[
        "S\u0259ma mannas\u0131"
    ],
    "name:bul_x_preferred":[
        "\u041c\u0430\u043d\u043d\u0430 \u043d\u0435\u0431\u0435\u0441\u043d\u0430"
    ],
    "name:cat_x_preferred":[
        "Mann\u00e0"
    ],
    "name:ces_x_preferred":[
        "Mana"
    ],
    "name:ckb_x_preferred":[
        "\u06af\u06d5\u0632\u06c6"
    ],
    "name:deu_x_preferred":[
        "Manna"
    ],
    "name:epo_x_preferred":[
        "Manao"
    ],
    "name:fas_x_preferred":[
        "\u06af\u0632\u0627\u0646\u06af\u0628\u06cc\u0646"
    ],
    "name:fin_x_preferred":[
        "Manna"
    ],
    "name:fra_x_preferred":[
        "Manne"
    ],
    "name:hrv_x_preferred":[
        "Mana"
    ],
    "name:hye_x_preferred":[
        "\u0544\u0561\u0576\u0561\u0576\u0561"
    ],
    "name:ind_x_preferred":[
        "Manna"
    ],
    "name:ita_x_preferred":[
        "Manna"
    ],
    "name:jpn_x_preferred":[
        "\u30de\u30ca"
    ],
    "name:khm_x_preferred":[
        "\u1798\u17c9\u17b6\u178e\u17b6"
    ],
    "name:mal_x_preferred":[
        "\u0d2e\u0d28\u0d4d\u0d28\u0d3e"
    ],
    "name:nld_x_preferred":[
        "Manna"
    ],
    "name:nno_x_preferred":[
        "Manna"
    ],
    "name:nor_x_preferred":[
        "Manna"
    ],
    "name:pol_x_preferred":[
        "Biblijna manna"
    ],
    "name:por_x_preferred":[
        "Man\u00e1"
    ],
    "name:rus_x_preferred":[
        "\u041c\u0430\u043d\u043d\u0430 \u043d\u0435\u0431\u0435\u0441\u043d\u0430\u044f"
    ],
    "name:spa_x_preferred":[
        "Man\u00e1"
    ],
    "name:sqi_x_preferred":[
        "Manna"
    ],
    "name:swa_x_preferred":[
        "Mana"
    ],
    "name:swe_x_preferred":[
        "Manna"
    ],
    "name:tam_x_preferred":[
        "\u0bae\u0ba9\u0bcd\u0ba9\u0bbe"
    ],
    "name:tgl_x_preferred":[
        "Mana"
    ],
    "name:ukr_x_preferred":[
        "\u041c\u0430\u043d\u043d\u0430 \u043d\u0435\u0431\u0435\u0441\u043d\u0430"
    ],
    "wof:name":"Manna",
    "wof:placetype":"locality"
},
  "geometry": {"coordinates":[73.38876999999999,28.56493],"type":"Point"}
}