{
  "type": "Feature",
  "properties": {
    "iso:country":"IN",
    "ks:ks_alt_nam":"Dighaltarang T.E. 120 117",
    "ks:ks_name":"Dighaltarang T.e. 120 117",
    "ks:ks_pop":1431,
    "ks:ks_type":"HABITATION",
    "name:eng_x_preferred":[
        "Dighaltarang T.e. 120 117"
    ],
    "wof:name":"Dighaltarang T.e. 120 117",
    "wof:placetype":"locality",
    "wof:population":1431
},
  "geometry": {"coordinates":[95.43917999999999,27.622119],"type":"Point"}
}