{
  "type": "Feature",
  "properties": {
    "gn:admin1_code":"10.0",
    "gn:admin2_code":"70.0",
    "gn:asciiname":"Mirpur",
    "gn:country_code":"IN",
    "gn:dem":322,
    "gn:feature_class":"P",
    "gn:feature_code":"PPL",
    "gn:name":"M\u012brpur",
    "gn:population":0,
    "gn:timezone":"Asia/Kolkata",
    "iso:country":"IN",
    "wof:name":"Mirpur",
    "wof:placetype":"locality"
},
  "geometry": {"coordinates":[77.09621,30.49164],"type":"Point"}
}