{
  "type": "Feature",
  "properties": {
    "iso:country":"IN",
    "ks:ks_name":"Sulekerekaval",
    "ks:ks_pop":43,
    "ks:ks_type":"VILLAGE",
    "name:eng_x_preferred":[
        "Sulekerekaval"
    ],
    "wof:name":"Sulekerekaval",
    "wof:placetype":"locality",
    "wof:population":43
},
  "geometry": {"coordinates":[76.403898,12.20701],"type":"Point"}
}