{
  "type": "Feature",
  "properties": {
    "iso:country":"IN",
    "ks:ks_name":"Raniya",
    "ks:ks_pop":39,
    "ks:ks_type":"HABITATION",
    "name:eng_x_preferred":[
        "Raniya"
    ],
    "wof:name":"Raniya",
    "wof:placetype":"locality",
    "wof:population":39
},
  "geometry": {"coordinates":[86.25950899999999,24.013408],"type":"Point"}
}