{
  "type": "Feature",
  "properties": {
    "iso:country":"IN",
    "ks:ks_name":"Godiput",
    "ks:ks_pop":57,
    "ks:ks_type":"HABITATION",
    "name:eng_x_preferred":[
        "Godiput"
    ],
    "wof:name":"Godiput",
    "wof:placetype":"locality",
    "wof:population":57
},
  "geometry": {"coordinates":[82.66590600000001,18.370729],"type":"Point"}
}