{
  "type": "Feature",
  "properties": {
    "gn:admin1_code":"10.0",
    "gn:admin2_code":"82.0",
    "gn:asciiname":"Rurki",
    "gn:country_code":"IN",
    "gn:dem":227,
    "gn:feature_class":"P",
    "gn:feature_code":"PPL",
    "gn:name":"Rurki",
    "gn:population":0,
    "gn:timezone":"Asia/Kolkata",
    "iso:country":"IN",
    "wof:name":"Rurki",
    "wof:placetype":"locality"
},
  "geometry": {"coordinates":[76.73953,28.93379],"type":"Point"}
}