{
  "type": "Feature",
  "properties": {
    "iso:country":"IN",
    "ks:ks_name":"Khoni",
    "ks:ks_pop":15115,
    "ks:ks_type":"VILLAGE",
    "ks:ks_uagg_main":0,
    "name:eng_x_preferred":[
        "Khoni"
    ],
    "wof:name":"Khoni",
    "wof:placetype":"neighbourhood",
    "wof:population":15115
},
  "geometry": {"coordinates":[73.05091899999999,19.30415],"type":"Point"}
}