{
  "type": "Feature",
  "properties": {
    "iso:country":"IN",
    "ks:ks_name":"Rajdaha",
    "ks:ks_pop":0,
    "ks:ks_type":"VILLAGE",
    "name:eng_x_preferred":[
        "Rajdaha"
    ],
    "wof:name":"Rajdaha",
    "wof:placetype":"locality",
    "wof:population":0
},
  "geometry": {"coordinates":[86.188509,23.921083],"type":"Point"}
}