{
  "type": "Feature",
  "properties": {
    "iso:country":"IN",
    "ks:ks_name":"Kakrahwa",
    "ks:ks_pop":218,
    "ks:ks_type":"HABITATION",
    "ks:ks_uagg_main":0,
    "name:eng_x_preferred":[
        "Kakrahwa"
    ],
    "wof:name":"Kakrahwa",
    "wof:placetype":"neighbourhood",
    "wof:population":218
},
  "geometry": {"coordinates":[82.44638500000001,26.186128],"type":"Point"}
}