{
  "type": "Feature",
  "properties": {
    "gn:admin1_code":"19.0",
    "gn:admin2_code":"563.0",
    "gn:asciiname":"Virje",
    "gn:country_code":"IN",
    "gn:dem":59,
    "gn:feature_class":"P",
    "gn:feature_code":"PPL",
    "gn:name":"Virje",
    "gn:population":0,
    "gn:timezone":"Asia/Kolkata",
    "iso:country":"IN",
    "name:bos_x_preferred":[
        "Virje"
    ],
    "name:ceb_x_preferred":[
        "Virje"
    ],
    "name:deu_x_preferred":[
        "Virje"
    ],
    "name:fra_x_preferred":[
        "Virje"
    ],
    "name:hrv_x_preferred":[
        "Virje"
    ],
    "name:hun_x_preferred":[
        "Prodav\u00edz"
    ],
    "name:ita_x_preferred":[
        "Virje"
    ],
    "name:nld_x_preferred":[
        "Virje"
    ],
    "name:pol_x_preferred":[
        "Gmina Virje"
    ],
    "name:ron_x_preferred":[
        "Comuna Virje"
    ],
    "name:rus_x_preferred":[
        "\u0412\u0438\u0440\u044c\u0435"
    ],
    "name:slv_x_preferred":[
        "Virje"
    ],
    "name:spa_x_preferred":[
        "Virje"
    ],
    "name:sqi_x_preferred":[
        "Virje"
    ],
    "name:srp_x_preferred":[
        "\u0412\u0438\u0440\u0458\u0435"
    ],
    "name:swe_x_preferred":[
        "Virje"
    ],
    "name:ukr_x_preferred":[
        "\u0412\u0456\u0440'\u0454"
    ],
    "name:war_x_preferred":[
        "Virje"
    ],
    "wof:name":"Virje",
    "wof:placetype":"locality"
},
  "geometry": {"coordinates":[74.35334,14.8797],"type":"Point"}
}