{
  "type": "Feature",
  "properties": {
    "gn:admin1_code":"39.0",
    "gn:admin2_code":"63.0",
    "gn:asciiname":"Gaurigad",
    "gn:country_code":"IN",
    "gn:dem":1226,
    "gn:feature_class":"P",
    "gn:feature_code":"PPL",
    "gn:name":"Gaurigad",
    "gn:population":0,
    "gn:timezone":"Asia/Kolkata",
    "iso:country":"IN",
    "wof:name":"Gaurigad",
    "wof:placetype":"locality"
},
  "geometry": {"coordinates":[79.74370999999999,29.74654],"type":"Point"}
}