{
  "type": "Feature",
  "properties": {
    "gn:admin1_code":"38.0",
    "gn:admin2_code":"348.0",
    "gn:asciiname":"Nawakadih",
    "gn:country_code":"IN",
    "gn:dem":357,
    "gn:feature_class":"P",
    "gn:feature_code":"PPL",
    "gn:name":"N\u0101w\u0101kadih",
    "gn:population":0,
    "gn:timezone":"Asia/Kolkata",
    "iso:country":"IN",
    "wof:name":"Nawakadih",
    "wof:placetype":"locality"
},
  "geometry": {"coordinates":[85.65208,24.34395],"type":"Point"}
}