{
  "type": "Feature",
  "properties": {
    "iso:country":"IN",
    "ks:ks_name":"Hatkhola Para",
    "ks:ks_pop":784,
    "ks:ks_type":"HABITATION",
    "name:eng_x_preferred":[
        "Hatkhola Para"
    ],
    "wof:name":"Hatkhola Para",
    "wof:placetype":"locality",
    "wof:population":784
},
  "geometry": {"coordinates":[88.72274,22.134276],"type":"Point"}
}