{
  "type": "Feature",
  "properties": {
    "gn:admin1_code":"29",
    "gn:admin2_code":"243.0",
    "gn:asciiname":"Pachi",
    "gn:country_code":"IN",
    "gn:dem":1073,
    "gn:feature_class":"P",
    "gn:feature_code":"PPL",
    "gn:name":"Pachi",
    "gn:population":0,
    "gn:timezone":"Asia/Kolkata",
    "iso:country":"IN",
    "name:ceb_x_preferred":[
        "Pachi"
    ],
    "name:swe_x_preferred":[
        "Pachi"
    ],
    "wof:name":"Pachi",
    "wof:placetype":"locality"
},
  "geometry": {"coordinates":[88.46666999999999,27.23333],"type":"Point"}
}