{
  "type": "Feature",
  "properties": {
    "iso:country":"IN",
    "ks:ks_name":"Kamothe",
    "ks:ks_pop":4729,
    "ks:ks_type":"VILLAGE",
    "name:eng_x_preferred":[
        "Kamothe"
    ],
    "wof:name":"Kamothe",
    "wof:placetype":"locality",
    "wof:population":4729
},
  "geometry": {"coordinates":[73.090678,19.016838],"type":"Point"}
}