{
  "type": "Feature",
  "properties": {
    "iso:country":"IN",
    "ks:ks_name":"Dhimaniya",
    "ks:ks_pop":648,
    "ks:ks_type":"HABITATION",
    "name:eng_x_preferred":[
        "Dhimaniya"
    ],
    "wof:name":"Dhimaniya",
    "wof:placetype":"locality",
    "wof:population":648
},
  "geometry": {"coordinates":[76.220877,21.56495],"type":"Point"}
}