{
  "type": "Feature",
  "properties": {
    "iso:country":"IN",
    "ks:ks_name":"Ahir Toli",
    "ks:ks_pop":364,
    "ks:ks_type":"HABITATION",
    "ks:ks_uagg_main":0,
    "name:eng_x_preferred":[
        "Ahir Toli"
    ],
    "wof:name":"Ahir Toli",
    "wof:placetype":"locality",
    "wof:population":364
},
  "geometry": {"coordinates":[84.921736,26.709036],"type":"Point"}
}