{
  "type": "Feature",
  "properties": {
    "iso:country":"IN",
    "ks:ks_name":"Laxmisul",
    "ks:ks_pop":183,
    "ks:ks_type":"VILLAGE",
    "name:eng_x_preferred":[
        "Laxmisul"
    ],
    "wof:name":"Laxmisul",
    "wof:placetype":"locality",
    "wof:population":183
},
  "geometry": {"coordinates":[86.56199700000001,21.346609],"type":"Point"}
}