{
  "type": "Feature",
  "properties": {
    "iso:country":"IN",
    "ks:ks_name":"Lalsagar",
    "ks:ks_pop":657,
    "ks:ks_type":"HABITATION",
    "name:eng_x_preferred":[
        "Lalsagar"
    ],
    "wof:name":"Lalsagar",
    "wof:placetype":"locality",
    "wof:population":657
},
  "geometry": {"coordinates":[72.241725,26.269419],"type":"Point"}
}