{
  "type": "Feature",
  "properties": {
    "iso:country":"IN",
    "ks:ks_name":"Nai Tola",
    "ks:ks_pop":58,
    "ks:ks_type":"HABITATION",
    "name:eng_x_preferred":[
        "Nai Tola"
    ],
    "wof:name":"Nai Tola",
    "wof:placetype":"locality",
    "wof:population":58
},
  "geometry": {"coordinates":[86.047965,24.308371],"type":"Point"}
}