{
  "type": "Feature",
  "properties": {
    "iso:country":"IN",
    "ks:ks_name":"Baturi",
    "ks:ks_pop":76,
    "ks:ks_type":"VILLAGE",
    "name:eng_x_preferred":[
        "Baturi"
    ],
    "wof:name":"Baturi",
    "wof:placetype":"locality",
    "wof:population":76
},
  "geometry": {"coordinates":[83.43564000000001,19.689333],"type":"Point"}
}