{
  "type": "Feature",
  "properties": {
    "gn:admin1_code":"2.0",
    "gn:admin2_code":"546",
    "gn:asciiname":"Dharmajigudem",
    "gn:country_code":"IN",
    "gn:dem":73,
    "gn:feature_class":"P",
    "gn:feature_code":"PPL",
    "gn:name":"Dharm\u0101jig\u016bdem",
    "gn:population":0,
    "gn:timezone":"Asia/Kolkata",
    "iso:country":"IN",
    "name:und_x_variant":[
        "Dharm\u0101jig\u016bdem",
        "Dh\u0101rmajig\u016bdem"
    ],
    "wof:name":"Dharmajigudem",
    "wof:placetype":"locality"
},
  "geometry": {"coordinates":[80.99625,16.89449],"type":"Point"}
}