{
  "type": "Feature",
  "properties": {
    "iso:country":"IN",
    "ks:ks_name":"Kishanpur",
    "ks:ks_pop":584,
    "ks:ks_type":"VILLAGE",
    "ks:ks_uagg_main":0,
    "name:eng_x_preferred":[
        "Kishanpur"
    ],
    "wof:name":"Kishanpur",
    "wof:placetype":"neighbourhood",
    "wof:population":584
},
  "geometry": {"coordinates":[76.554254,27.991267],"type":"Point"}
}