{
  "type": "Feature",
  "properties": {
    "gn:admin1_code":"36.0",
    "gn:admin2_code":"149.0",
    "gn:asciiname":"Bhilaulia",
    "gn:country_code":"IN",
    "gn:dem":182,
    "gn:feature_class":"P",
    "gn:feature_code":"PPL",
    "gn:name":"Bhilaulia",
    "gn:population":0,
    "gn:timezone":"Asia/Kolkata",
    "iso:country":"IN",
    "name:und_x_variant":[
        "Satpura"
    ],
    "wof:name":"Bhilaulia",
    "wof:placetype":"locality"
},
  "geometry": {"coordinates":[78.8878,28.22386],"type":"Point"}
}