{
  "type": "Feature",
  "properties": {
    "iso:country":"IN",
    "ks:ks_name":"Tulasivalsa",
    "ks:ks_pop":139,
    "ks:ks_type":"HABITATION",
    "name:eng_x_preferred":[
        "Tulasivalsa"
    ],
    "wof:name":"Tulasivalsa",
    "wof:placetype":"locality",
    "wof:population":139
},
  "geometry": {"coordinates":[83.250516,19.050534],"type":"Point"}
}