{
  "type": "Feature",
  "properties": {
    "iso:country":"IN",
    "ks:ks_name":"Bankana",
    "ks:ks_pop":753,
    "ks:ks_type":"VILLAGE",
    "name:eng_x_preferred":[
        "Bankana"
    ],
    "wof:name":"Bankana",
    "wof:placetype":"locality",
    "wof:population":753
},
  "geometry": {"coordinates":[70.90684400000001,25.552697],"type":"Point"}
}