{
  "type": "Feature",
  "properties": {
    "iso:country":"IN",
    "ks:ks_name":"Padri",
    "ks:ks_type":"VILLAGE",
    "name:eng_x_preferred":[
        "Padri"
    ],
    "wof:name":"Padri",
    "wof:placetype":"locality"
},
  "geometry": {"coordinates":[83.070539,26.430453],"type":"Point"}
}