{
  "type": "Feature",
  "properties": {
    "iso:country":"IN",
    "ks:ks_name":"Bania Tala Mahanpura",
    "ks:ks_pop":742,
    "ks:ks_type":"VILLAGE",
    "ks:ks_uagg_main":0,
    "name:eng_x_preferred":[
        "Bania Tala Mahanpura"
    ],
    "wof:name":"Bania Tala Mahanpura",
    "wof:placetype":"neighbourhood",
    "wof:population":742
},
  "geometry": {"coordinates":[79.80429100000001,25.299747],"type":"Point"}
}