{
  "type": "Feature",
  "properties": {
    "iso:country":"IN",
    "ks:ks_name":"2 KLD",
    "ks:ks_pop":177,
    "ks:ks_type":"VILLAGE",
    "name:eng_x_preferred":[
        "2 KLD"
    ],
    "wof:name":"2 KLD",
    "wof:placetype":"locality",
    "wof:population":177
},
  "geometry": {"coordinates":[72.758346,28.814789],"type":"Point"}
}