{
  "type": "Feature",
  "properties": {
    "gn:admin1_code":"35.0",
    "gn:admin2_code":"453.0",
    "gn:asciiname":"Mirchatola",
    "gn:country_code":"IN",
    "gn:dem":650,
    "gn:feature_class":"P",
    "gn:feature_code":"PPL",
    "gn:name":"Mirch\u0101tol\u0101",
    "gn:population":0,
    "gn:timezone":"Asia/Kolkata",
    "iso:country":"IN",
    "wof:name":"Mirchatola",
    "wof:placetype":"locality"
},
  "geometry": {"coordinates":[80.97372,22.58983],"type":"Point"}
}