{
  "type": "Feature",
  "properties": {
    "gn:admin1_code":"24.0",
    "gn:admin2_code":"110.0",
    "gn:asciiname":"Jagannathpura",
    "gn:country_code":"IN",
    "gn:dem":487,
    "gn:feature_class":"P",
    "gn:feature_code":"PPL",
    "gn:name":"Jagann\u0101thpura",
    "gn:population":0,
    "gn:timezone":"Asia/Kolkata",
    "iso:country":"IN",
    "ks:ks_name":"Jagnnathpura",
    "ks:ks_pop":1183,
    "ks:ks_type":"VILLAGE",
    "ks:ks_uagg_main":0,
    "name:eng_x_preferred":[
        "Jagnnathpura"
    ],
    "wof:name":"Jagnnathpura",
    "wof:placetype":"locality",
    "wof:population":1183
},
  "geometry": {"coordinates":[75.77209999999999,27.042362],"type":"Point"}
}