{
  "type": "Feature",
  "properties": {
    "gn:admin1_code":"19.0",
    "gn:admin2_code":"582.0",
    "gn:asciiname":"Guilhalli",
    "gn:country_code":"IN",
    "gn:dem":789,
    "gn:feature_class":"P",
    "gn:feature_code":"PPL",
    "gn:name":"Guilhalli",
    "gn:population":0,
    "gn:timezone":"Asia/Kolkata",
    "iso:country":"IN",
    "wof:name":"Guilhalli",
    "wof:placetype":"neighbourhood"
},
  "geometry": {"coordinates":[77.60493,13.45682],"type":"Point"}
}