{
  "type": "Feature",
  "properties": {
    "iso:country":"IN",
    "ks:ks_name":"Ugawa",
    "ks:ks_pop":720,
    "ks:ks_type":"VILLAGE",
    "name:eng_x_preferred":[
        "Ugawa"
    ],
    "wof:name":"Ugawa",
    "wof:placetype":"locality",
    "wof:population":720
},
  "geometry": {"coordinates":[70.959289,26.650197],"type":"Point"}
}