{
  "type": "Feature",
  "properties": {
    "iso:country":"IN",
    "ks:ks_name":"Vandanpara",
    "ks:ks_pop":260,
    "ks:ks_type":"HABITATION",
    "name:eng_x_preferred":[
        "Vandanpara"
    ],
    "wof:name":"Vandanpara",
    "wof:placetype":"locality",
    "wof:population":260
},
  "geometry": {"coordinates":[76.559759,11.059849],"type":"Point"}
}