{
  "type": "Feature",
  "properties": {
    "iso:country":"IN",
    "ks:ks_alt_nam":"Hokaldanga Madhya Para and Uttar Para",
    "ks:ks_name":"Hokaldanga Madhya Para And Uttar Para",
    "ks:ks_pop":1322,
    "ks:ks_type":"HABITATION",
    "name:eng_x_preferred":[
        "Hokaldanga Madhya Para And Uttar Para"
    ],
    "wof:name":"Hokaldanga Madhya Para And Uttar Para",
    "wof:placetype":"locality",
    "wof:population":1322
},
  "geometry": {"coordinates":[88.46208,22.102722],"type":"Point"}
}