{
  "type": "Feature",
  "properties": {
    "iso:country":"IN",
    "ks:ks_alt_nam":"BANDA",
    "ks:ks_name":"Banda",
    "ks:ks_pop":91,
    "ks:ks_type":"HABITATION",
    "name:eng_x_preferred":[
        "Banda"
    ],
    "wof:name":"Banda",
    "wof:placetype":"locality",
    "wof:population":91
},
  "geometry": {"coordinates":[84.97669399999999,24.282477],"type":"Point"}
}