{
  "type": "Feature",
  "properties": {
    "gn:admin1_code":"19.0",
    "gn:admin2_code":"575.0",
    "gn:asciiname":"Auvaranad",
    "gn:country_code":"IN",
    "gn:dem":170,
    "gn:feature_class":"P",
    "gn:feature_code":"PPLL",
    "gn:name":"Auvaran\u0101d",
    "gn:population":0,
    "gn:timezone":"Asia/Kolkata",
    "iso:country":"IN",
    "wof:name":"Auvaranad",
    "wof:placetype":"locality"
},
  "geometry": {"coordinates":[75.38233000000002,12.62118],"type":"Point"}
}