{
  "type": "Feature",
  "properties": {
    "iso:country":"IN",
    "ks:ks_name":"Darhipatti",
    "ks:ks_pop":1702,
    "ks:ks_type":"VILLAGE",
    "name:eng_x_preferred":[
        "Darhipatti"
    ],
    "wof:name":"Darhipatti",
    "wof:placetype":"locality",
    "wof:population":1702
},
  "geometry": {"coordinates":[85.370406,26.236431],"type":"Point"}
}