{
  "type": "Feature",
  "properties": {
    "gn:admin1_code":"35",
    "gn:admin2_code":"463.0",
    "gn:asciiname":"Amilwan",
    "gn:country_code":"IN",
    "gn:dem":329,
    "gn:feature_class":"P",
    "gn:feature_code":"PPL",
    "gn:name":"Amilw\u0101n",
    "gn:population":0,
    "gn:timezone":"Asia/Kolkata",
    "iso:country":"IN",
    "ks:ks_alt_nam":"Amilw\u0101n",
    "ks:ks_name":"Amilwan",
    "ks:ks_pop":1372,
    "ks:ks_type":"VILLAGE",
    "name:eng_x_preferred":[
        "Amilwan"
    ],
    "name:eng_x_variant":[
        "Amilw\u0101n"
    ],
    "wof:name":"Amilwan",
    "wof:placetype":"locality",
    "wof:population":1372
},
  "geometry": {"coordinates":[82.50541200000001,24.044814],"type":"Point"}
}