{
  "type": "Feature",
  "properties": {
    "iso:country":"IN",
    "ks:ks_name":"Garasai",
    "ks:ks_pop":747,
    "ks:ks_type":"HABITATION",
    "name:eng_x_preferred":[
        "Garasai"
    ],
    "wof:name":"Garasai",
    "wof:placetype":"locality",
    "wof:population":747
},
  "geometry": {"coordinates":[85.72744299999999,22.242098],"type":"Point"}
}