{
  "type": "Feature",
  "properties": {
    "iso:country":"IN",
    "ks:ks_name":"Nathu Purwa",
    "ks:ks_pop":230,
    "ks:ks_type":"HABITATION",
    "name:eng_x_preferred":[
        "Nathu Purwa"
    ],
    "wof:name":"Nathu Purwa",
    "wof:placetype":"locality",
    "wof:population":230
},
  "geometry": {"coordinates":[81.12295,25.366022],"type":"Point"}
}