{
  "type": "Feature",
  "properties": {
    "iso:country":"IN",
    "ks:ks_name":"Pudupatti",
    "ks:ks_pop":150,
    "ks:ks_type":"HABITATION",
    "name:eng_x_preferred":[
        "Pudupatti"
    ],
    "wof:name":"Pudupatti",
    "wof:placetype":"locality",
    "wof:population":150
},
  "geometry": {"coordinates":[78.644971,10.276986],"type":"Point"}
}