{
  "type": "Feature",
  "properties": {
    "gn:admin1_code":"11",
    "gn:admin2_code":"33.0",
    "gn:asciiname":"Matranla",
    "gn:country_code":"IN",
    "gn:dem":2233,
    "gn:feature_class":"P",
    "gn:feature_code":"PPL",
    "gn:name":"Matr\u0101nla",
    "gn:population":0,
    "gn:timezone":"Asia/Kolkata",
    "iso:country":"IN",
    "wof:name":"Matranla",
    "wof:placetype":"locality"
},
  "geometry": {"coordinates":[77.6996,30.99722],"type":"Point"}
}