{
  "type": "Feature",
  "properties": {
    "iso:country":"IN",
    "ks:ks_name":"Phuleiguda.",
    "ks:ks_pop":36,
    "ks:ks_type":"HABITATION",
    "name:eng_x_preferred":[
        "Phuleiguda."
    ],
    "wof:name":"Phuleiguda.",
    "wof:placetype":"locality",
    "wof:population":36
},
  "geometry": {"coordinates":[82.099605,19.733483],"type":"Point"}
}