{
  "type": "Feature",
  "properties": {
    "gn:admin1_code":"36",
    "gn:admin2_code":"142.0",
    "gn:asciiname":"Chachrai",
    "gn:country_code":"IN",
    "gn:dem":201,
    "gn:feature_class":"P",
    "gn:feature_code":"PPL",
    "gn:name":"Chachrai",
    "gn:population":0,
    "gn:timezone":"Asia/Kolkata",
    "iso:country":"IN",
    "ks:ks_name":"Chachrai",
    "ks:ks_type":"VILLAGE",
    "name:eng_x_preferred":[
        "Chachrai"
    ],
    "wof:name":"Chachrai",
    "wof:placetype":"locality"
},
  "geometry": {"coordinates":[78.11750499999999,28.409956],"type":"Point"}
}