{
  "type": "Feature",
  "properties": {
    "gn:admin1_code":"19.0",
    "gn:admin2_code":"563.0",
    "gn:asciiname":"Chilmi",
    "gn:country_code":"IN",
    "gn:dem":421,
    "gn:feature_class":"P",
    "gn:feature_code":"PPL",
    "gn:name":"Chilmi",
    "gn:population":0,
    "gn:timezone":"Asia/Kolkata",
    "iso:country":"IN",
    "ks:ks_alt_nam":"chilme",
    "ks:ks_name":"Chilme",
    "ks:ks_pop":16,
    "ks:ks_type":"HABITATION",
    "name:eng_x_preferred":[
        "Chilme"
    ],
    "name:eng_x_variant":[
        "Chilmi"
    ],
    "wof:name":"Chilme",
    "wof:placetype":"locality",
    "wof:population":16
},
  "geometry": {"coordinates":[74.527698,14.993498],"type":"Point"}
}