{
  "type": "Feature",
  "properties": {
    "gn:admin1_code":"36",
    "gn:admin2_code":"174.0",
    "gn:asciiname":"Rampur Basohra",
    "gn:country_code":"IN",
    "gn:dem":108,
    "gn:feature_class":"P",
    "gn:feature_code":"PPL",
    "gn:name":"R\u0101mpur Basohra",
    "gn:population":0,
    "gn:timezone":"Asia/Kolkata",
    "iso:country":"IN",
    "ks:ks_name":"Rampur Basohara",
    "ks:ks_pop":637,
    "ks:ks_type":"VILLAGE",
    "ks:ks_uagg_main":0,
    "name:eng_x_preferred":[
        "Rampur Basohara"
    ],
    "wof:name":"Rampur Basohara",
    "wof:placetype":"neighbourhood",
    "wof:population":637
},
  "geometry": {"coordinates":[81.410206,25.530166],"type":"Point"}
}