{
  "type": "Feature",
  "properties": {
    "iso:country":"IN",
    "ks:ks_name":"Nirbhaypur",
    "ks:ks_pop":1580,
    "ks:ks_type":"VILLAGE",
    "name:eng_x_preferred":[
        "Nirbhaypur"
    ],
    "wof:name":"Nirbhaypur",
    "wof:placetype":"locality",
    "wof:population":1580
},
  "geometry": {"coordinates":[87.895169,22.214169],"type":"Point"}
}