{
  "type": "Feature",
  "properties": {
    "iso:country":"IN",
    "ks:ks_name":"H Basti Bhikhipur",
    "ks:ks_pop":94,
    "ks:ks_type":"HABITATION",
    "name:eng_x_preferred":[
        "H Basti Bhikhipur"
    ],
    "wof:name":"H Basti Bhikhipur",
    "wof:placetype":"locality",
    "wof:population":94
},
  "geometry": {"coordinates":[81.710352,26.347435],"type":"Point"}
}