{
  "type": "Feature",
  "properties": {
    "iso:country":"IN",
    "ks:ks_alt_nam":"pasin purwa",
    "ks:ks_name":"Pasin Purwa",
    "ks:ks_pop":106,
    "ks:ks_type":"HABITATION",
    "ks:ks_uagg_main":0,
    "name:eng_x_preferred":[
        "Pasin Purwa"
    ],
    "wof:name":"Pasin Purwa",
    "wof:placetype":"neighbourhood",
    "wof:population":106
},
  "geometry": {"coordinates":[81.58118,27.414047],"type":"Point"}
}