{
  "type": "Feature",
  "properties": {
    "gn:admin1_code":"35.0",
    "gn:admin2_code":"454.0",
    "gn:asciiname":"Narangi",
    "gn:country_code":"IN",
    "gn:dem":509,
    "gn:feature_class":"P",
    "gn:feature_code":"PPL",
    "gn:name":"N\u0101rang\u012b",
    "gn:population":0,
    "gn:timezone":"Asia/Kolkata",
    "iso:country":"IN",
    "wof:name":"Narangi",
    "wof:placetype":"locality"
},
  "geometry": {"coordinates":[80.52356999999998,22.32291],"type":"Point"}
}