{
  "type": "Feature",
  "properties": {
    "iso:country":"IN",
    "ks:ks_name":"Mundachedu",
    "ks:ks_pop":112,
    "ks:ks_type":"HABITATION",
    "name:eng_x_preferred":[
        "Mundachedu"
    ],
    "wof:name":"Mundachedu",
    "wof:placetype":"locality",
    "wof:population":112
},
  "geometry": {"coordinates":[78.22663300000001,11.857243],"type":"Point"}
}