{
  "type": "Feature",
  "properties": {
    "iso:country":"IN",
    "ks:ks_name":"Manjrol Vadadli Vasahat",
    "ks:ks_pop":167,
    "ks:ks_type":"HABITATION",
    "name:eng_x_preferred":[
        "Manjrol Vadadli Vasahat"
    ],
    "wof:name":"Manjrol Vadadli Vasahat",
    "wof:placetype":"locality",
    "wof:population":167
},
  "geometry": {"coordinates":[73.52175,22.151667],"type":"Point"}
}