{
  "type": "Feature",
  "properties": {
    "iso:country":"IN",
    "ks:ks_name":"Natun Dalalpara",
    "ks:ks_pop":1631,
    "ks:ks_type":"HABITATION",
    "ks:ks_uagg_main":0,
    "name:eng_x_preferred":[
        "Natun Dalalpara"
    ],
    "wof:name":"Natun Dalalpara",
    "wof:placetype":"neighbourhood",
    "wof:population":1631
},
  "geometry": {"coordinates":[88.324167,24.315193],"type":"Point"}
}