{
  "type": "Feature",
  "properties": {
    "gn:admin1_code":"19.0",
    "gn:admin2_code":"578.0",
    "gn:asciiname":"Alattur",
    "gn:country_code":"IN",
    "gn:dem":865,
    "gn:feature_class":"P",
    "gn:feature_code":"PPL",
    "gn:name":"\u0100latt\u016br",
    "gn:population":0,
    "gn:timezone":"Asia/Kolkata",
    "iso:country":"IN",
    "wof:name":"Alattur",
    "wof:placetype":"locality"
},
  "geometry": {"coordinates":[76.59899999999998,11.87352],"type":"Point"}
}