{
  "type": "Feature",
  "properties": {
    "gn:admin1_code":"24",
    "gn:admin2_code":"120.0",
    "gn:asciiname":"Sankhna",
    "gn:country_code":"IN",
    "gn:dem":302,
    "gn:feature_class":"P",
    "gn:feature_code":"PPL",
    "gn:name":"S\u0101nkhna",
    "gn:population":0,
    "gn:timezone":"Asia/Kolkata",
    "iso:country":"IN",
    "name:und_x_variant":[
        "S\u0101kna",
        "S\u0101nkhna"
    ],
    "wof:name":"Sankhna",
    "wof:placetype":"locality"
},
  "geometry": {"coordinates":[75.73900999999999,25.96691],"type":"Point"}
}