{
  "type": "Feature",
  "properties": {
    "gn:admin1_code":"19.0",
    "gn:admin2_code":"582.0",
    "gn:asciiname":"Naduyanahalli",
    "gn:country_code":"IN",
    "gn:dem":824,
    "gn:feature_class":"P",
    "gn:feature_code":"PPL",
    "gn:name":"Naduyanahalli",
    "gn:population":0,
    "gn:timezone":"Asia/Kolkata",
    "iso:country":"IN",
    "wof:name":"Naduyanahalli",
    "wof:placetype":"locality"
},
  "geometry": {"coordinates":[77.74788000000002,13.65659],"type":"Point"}
}