{
  "type": "Feature",
  "properties": {
    "iso:country":"IN",
    "ks:ks_name":"Dongargaonwadi",
    "ks:ks_pop":340,
    "ks:ks_type":"HABITATION",
    "name:eng_x_preferred":[
        "Dongargaonwadi"
    ],
    "wof:name":"Dongargaonwadi",
    "wof:placetype":"locality",
    "wof:population":340
},
  "geometry": {"coordinates":[73.625068,18.725326],"type":"Point"}
}