{
  "type": "Feature",
  "properties": {
    "iso:country":"IN",
    "ks:ks_alt_nam":"Chunnamvukaran kulambu",
    "ks:ks_name":"Chunnamvukaran Kulambu",
    "ks:ks_pop":2115,
    "ks:ks_type":"HABITATION",
    "name:eng_x_preferred":[
        "Chunnamvukaran Kulambu"
    ],
    "wof:name":"Chunnamvukaran Kulambu",
    "wof:placetype":"locality",
    "wof:population":2115
},
  "geometry": {"coordinates":[76.466883,10.541404],"type":"Point"}
}