{
  "type": "Feature",
  "properties": {
    "iso:country":"IN",
    "ks:ks_name":"Lawakera",
    "ks:ks_pop":718,
    "ks:ks_type":"VILLAGE",
    "name:eng_x_preferred":[
        "Lawakera"
    ],
    "wof:name":"Lawakera",
    "wof:placetype":"locality",
    "wof:population":718
},
  "geometry": {"coordinates":[83.985266,22.380317],"type":"Point"}
}