{
  "type": "Feature",
  "properties": {
    "iso:country":"IN",
    "ks:ks_name":"Dhugal Gaon",
    "ks:ks_pop":50,
    "ks:ks_type":"HABITATION",
    "name:eng_x_preferred":[
        "Dhugal Gaon"
    ],
    "wof:name":"Dhugal Gaon",
    "wof:placetype":"locality",
    "wof:population":50
},
  "geometry": {"coordinates":[80.328311,29.746092],"type":"Point"}
}