{
  "type": "Feature",
  "properties": {
    "iso:country":"IN",
    "ks:ks_name":"Halpatiwas",
    "ks:ks_pop":412,
    "ks:ks_type":"HABITATION",
    "ks:ks_uagg_main":0,
    "name:eng_x_preferred":[
        "Halpatiwas"
    ],
    "wof:name":"Halpatiwas",
    "wof:placetype":"neighbourhood",
    "wof:population":412
},
  "geometry": {"coordinates":[73.280056,21.221556],"type":"Point"}
}