{
  "type": "Feature",
  "properties": {
    "iso:country":"IN",
    "ks:ks_name":"Usaripar",
    "ks:ks_pop":9,
    "ks:ks_type":"HABITATION",
    "name:eng_x_preferred":[
        "Usaripar"
    ],
    "wof:name":"Usaripar",
    "wof:placetype":"locality",
    "wof:population":9
},
  "geometry": {"coordinates":[79.816613,21.298422],"type":"Point"}
}