{
  "type": "Feature",
  "properties": {
    "gn:country":"IN",
    "gn:fcode":"PPL",
    "gn:population":8534,
    "iso:country":"IN",
    "name:bpy_x_preferred":[
        "\u0995\u09cb\u09a4\u09cd\u09b0\u09be"
    ],
    "name:ceb_x_preferred":[
        "Kotra"
    ],
    "name:eng_x_preferred":[
        "Kotra"
    ],
    "name:ita_x_preferred":[
        "Kotra"
    ],
    "name:msa_x_preferred":[
        "Kotra"
    ],
    "name:nan_x_preferred":[
        "Kotra"
    ],
    "name:new_x_preferred":[
        "\u0915\u094b\u0924\u094d\u0930\u093e"
    ],
    "name:nld_x_preferred":[
        "Kotra"
    ],
    "name:pol_x_preferred":[
        "Kotra"
    ],
    "name:swe_x_preferred":[
        "Kotra"
    ],
    "name:urd_x_preferred":[
        "\u06a9\u0648\u0679\u0631\u0627\u060c \u0627\u062a\u0631\u067e\u0631\u062f\u06cc\u0634"
    ],
    "name:urd_x_variant":[
        "\u06a9\u0648\u0679\u0631\u0627"
    ],
    "name:vie_x_preferred":[
        "Kotra"
    ],
    "name:zho_x_preferred":[
        "\u79d1\u7279\u62c9"
    ],
    "qs:name":"Kotra",
    "qs:photos_9r":0,
    "qs:photos_sr":0,
    "qs:pop_sr":"5",
    "wof:name":"Kotra",
    "wof:placetype":"locality",
    "wof:population":8534
},
  "geometry": {"coordinates":[79.30882,25.80766],"type":"Point"}
}