{
  "type": "Feature",
  "properties": {
    "gn:country":"IN",
    "gn:fcode":"PPL",
    "gn:population":8534,
    "iso:country":"IN",
    "name:ara_x_preferred":[
        "\u0643\u0648\u062a\u0631\u0627"
    ],
    "name:ben_bn_x_preferred":[
        "\u0995\u09cb\u099f\u09b0\u09be"
    ],
    "name:ben_in_x_preferred":[
        "\u0995\u09cb\u099f\u09b0\u09be"
    ],
    "name:bpy_x_preferred":[
        "\u0995\u09cb\u09a4\u09cd\u09b0\u09be"
    ],
    "name:ceb_x_preferred":[
        "Kotra"
    ],
    "name:eng_x_preferred":[
        "Kotra"
    ],
    "name:guj_x_preferred":[
        "\u0a95\u0acb\u0a9f\u0ab0\u0abe"
    ],
    "name:hin_x_preferred":[
        "\u0915\u094b\u091f\u0930\u093e"
    ],
    "name:ita_x_preferred":[
        "Kotra"
    ],
    "name:kan_x_preferred":[
        "\u0c95\u0ccb\u0ca4\u0ccd\u0cb0\u0cbe"
    ],
    "name:mal_x_preferred":[
        "\u0d15\u0d4b\u0d24\u0d4d\u0d30"
    ],
    "name:mar_x_preferred":[
        "\u0915\u094b\u091f\u094d\u0930\u093e"
    ],
    "name:msa_x_preferred":[
        "Kotra"
    ],
    "name:nan_x_preferred":[
        "Kotra"
    ],
    "name:new_x_preferred":[
        "\u0915\u094b\u0924\u094d\u0930\u093e"
    ],
    "name:nld_x_preferred":[
        "Kotra"
    ],
    "name:pan_x_preferred":[
        "\u0a15\u0a4b\u0a1f\u0a30\u0a3e"
    ],
    "name:pol_x_preferred":[
        "Kotra"
    ],
    "name:swe_x_preferred":[
        "Kotra"
    ],
    "name:tam_x_preferred":[
        "\u0b95\u0bcb\u0b9f\u0bcd\u0bb0\u0bbe"
    ],
    "name:tel_x_preferred":[
        "\u0c15\u0c4a\u0c1f\u0c4d\u0c30\u0c3e"
    ],
    "name:urd_x_preferred":[
        "\u06a9\u0648\u0679\u0631\u0627"
    ],
    "name:urd_x_variant":[
        "\u06a9\u0648\u0679\u0631\u0627\u060c \u0627\u062a\u0631\u067e\u0631\u062f\u06cc\u0634"
    ],
    "name:vie_x_preferred":[
        "Kotra"
    ],
    "name:zho_x_preferred":[
        "\u79d1\u7279\u62c9"
    ],
    "qs:name":"Kotra",
    "qs:photos_9r":0,
    "qs:photos_sr":0,
    "qs:pop_sr":"5",
    "wof:name":"Kotra",
    "wof:placetype":"locality",
    "wof:population":8534
},
  "geometry": {"coordinates":[79.30882,25.80766],"type":"Point"}
}