{
  "type": "Feature",
  "properties": {
    "iso:country":"IN",
    "ks:ks_alt_nam":"MALUKA BURUSAI",
    "ks:ks_name":"Maluka Burusai",
    "ks:ks_pop":152,
    "ks:ks_type":"HABITATION",
    "ks:ks_uagg_main":0,
    "name:eng_x_preferred":[
        "Maluka Burusai"
    ],
    "wof:name":"Maluka Burusai",
    "wof:placetype":"neighbourhood",
    "wof:population":152
},
  "geometry": {"coordinates":[85.69019900000001,22.221102],"type":"Point"}
}