{
  "type": "Feature",
  "properties": {
    "gn:admin1_code":"34.0",
    "gn:admin2_code":"216.0",
    "gn:asciiname":"Anandi Chapra",
    "gn:country_code":"IN",
    "gn:dem":64,
    "gn:feature_class":"P",
    "gn:feature_code":"PPL",
    "gn:name":"Anandi Ch\u0101pra",
    "gn:population":0,
    "gn:timezone":"Asia/Kolkata",
    "iso:country":"IN",
    "ks:ks_name":"Anandi Chhapra",
    "ks:ks_pop":1142,
    "ks:ks_type":"VILLAGE",
    "ks:ks_uagg_main":0,
    "name:eng_x_preferred":[
        "Anandi Chhapra"
    ],
    "wof:name":"Anandi Chhapra",
    "wof:placetype":"neighbourhood",
    "wof:population":1142
},
  "geometry": {"coordinates":[84.98039900000001,26.310958],"type":"Point"}
}