{
  "type": "Feature",
  "properties": {
    "gn:admin1_code":"16.0",
    "gn:admin2_code":"503.0",
    "gn:asciiname":"Isapur",
    "gn:country_code":"IN",
    "gn:dem":306,
    "gn:feature_class":"P",
    "gn:feature_code":"PPL",
    "gn:name":"Is\u0101pur",
    "gn:population":0,
    "gn:timezone":"Asia/Kolkata",
    "iso:country":"IN",
    "name:ara_x_preferred":[
        "\u0633\u062f \u0625\u0633\u0627\u0628\u0648\u0631"
    ],
    "name:ben_bn_x_preferred":[
        "\u0987\u09b8\u09be\u09aa\u09c1\u09b0"
    ],
    "name:ben_in_x_preferred":[
        "\u0987\u09b8\u09be\u09aa\u09c1\u09b0"
    ],
    "name:guj_x_preferred":[
        "\u0a87\u0ab8\u0abe\u0aaa\u0ac1\u0ab0"
    ],
    "name:hin_x_preferred":[
        "\u0908\u0938\u093e\u092a\u0941\u0930"
    ],
    "name:kan_x_preferred":[
        "\u0c87\u0cb8\u0cbe\u0caa\u0cc1\u0cb0"
    ],
    "name:mal_x_preferred":[
        "\u0d07\u0d38\u0d3e\u0d2a\u0d42\u0d7c"
    ],
    "name:mar_x_preferred":[
        "\u0908\u0938\u093e\u092a\u0942\u0930"
    ],
    "name:pan_x_preferred":[
        "\u0a08\u0a38\u0a3e\u0a2a\u0a41\u0a30"
    ],
    "name:tam_x_preferred":[
        "\u0b87\u0b9a\u0bbe\u0baa\u0bc2\u0bb0\u0bcd"
    ],
    "name:tel_x_preferred":[
        "\u0c07\u0c38\u0c3e\u0c2a\u0c42\u0c30\u0c4d"
    ],
    "name:urd_x_preferred":[
        "\u0639\u06cc\u0633\u06cc \u067e\u0648\u0631"
    ],
    "wof:name":"Isapur",
    "wof:placetype":"locality"
},
  "geometry": {"coordinates":[78.12868,21.10813],"type":"Point"}
}