{
  "type": "Feature",
  "properties": {
    "gn:admin1_code":"34.0",
    "gn:admin2_code":"236.0",
    "gn:asciiname":"Kangti",
    "gn:country_code":"IN",
    "gn:dem":143,
    "gn:feature_class":"P",
    "gn:feature_code":"PPL",
    "gn:name":"Kangti",
    "gn:population":0,
    "gn:timezone":"Asia/Kolkata",
    "iso:country":"IN",
    "name:new_x_preferred":[
        "\u0915\u0902\u0917\u093f\u091f\u093f \u092e\u0923\u094d\u0921\u0932"
    ],
    "name:tel_x_preferred":[
        "\u0c15\u0c02\u0c17\u0c4d\u0c1f\u0c3f \u0c2e\u0c02\u0c21\u0c32\u0c02"
    ],
    "wof:name":"Kangti",
    "wof:placetype":"neighbourhood"
},
  "geometry": {"coordinates":[85.08951,24.59247],"type":"Point"}
}