{
  "type": "Feature",
  "properties": {
    "iso:country":"IN",
    "ks:ks_name":"Budhauda",
    "ks:ks_pop":40,
    "ks:ks_type":"HABITATION",
    "name:eng_x_preferred":[
        "Budhauda"
    ],
    "wof:name":"Budhauda",
    "wof:placetype":"locality",
    "wof:population":40
},
  "geometry": {"coordinates":[83.597797,19.430304],"type":"Point"}
}