{
  "type": "Feature",
  "properties": {
    "gn:admin1_code":"23.0",
    "gn:admin2_code":"45.0",
    "gn:asciiname":"Ghanyewala",
    "gn:country_code":"IN",
    "gn:dem":213,
    "gn:feature_class":"P",
    "gn:feature_code":"PPL",
    "gn:name":"Ghanyew\u0101la",
    "gn:population":0,
    "gn:timezone":"Asia/Kolkata",
    "iso:country":"IN",
    "wof:name":"Ghanyewala",
    "wof:placetype":"locality"
},
  "geometry": {"coordinates":[74.93992,30.63324],"type":"Point"}
}