{
  "type": "Feature",
  "properties": {
    "gn:admin1_code":"37",
    "gn:admin2_code":"414.0",
    "gn:asciiname":"Uridgaon",
    "gn:country_code":"IN",
    "gn:dem":646,
    "gn:feature_class":"P",
    "gn:feature_code":"PPL",
    "gn:name":"Uridgaon",
    "gn:population":0,
    "gn:timezone":"Asia/Kolkata",
    "iso:country":"IN",
    "ks:ks_name":"Udidgaon",
    "ks:ks_pop":1113,
    "ks:ks_type":"VILLAGE",
    "name:eng_x_preferred":[
        "Udidgaon"
    ],
    "name:eng_x_variant":[
        "Uridgaon"
    ],
    "wof:name":"Udidgaon",
    "wof:placetype":"locality",
    "wof:population":1113
},
  "geometry": {"coordinates":[81.83318,20.043181],"type":"Point"}
}