{
  "type": "Feature",
  "properties": {
    "iso:country":"IN",
    "ks:ks_name":"Jamdaha",
    "ks:ks_pop":2190,
    "ks:ks_type":"VILLAGE",
    "ks:ks_uagg_main":0,
    "name:eng_x_preferred":[
        "Jamdaha"
    ],
    "wof:name":"Jamdaha",
    "wof:placetype":"neighbourhood",
    "wof:population":2190
},
  "geometry": {"coordinates":[87.98491199999999,23.156656],"type":"Point"}
}