{
  "type": "Feature",
  "properties": {
    "gn:admin1_code":"2.0",
    "gn:admin2_code":"554.0",
    "gn:asciiname":"Bommasamudram",
    "gn:country_code":"IN",
    "gn:dem":253,
    "gn:feature_class":"P",
    "gn:feature_code":"PPL",
    "gn:name":"Bommasamudram",
    "gn:population":0,
    "gn:timezone":"Asia/Kolkata",
    "iso:country":"IN",
    "name:tel_x_preferred":[
        "\u0c2c\u0c4a\u0c2e\u0c4d\u0c2e\u0c38\u0c2e\u0c41\u0c26\u0c4d\u0c30\u0c02"
    ],
    "wof:name":"Bommasamudram",
    "wof:placetype":"locality"
},
  "geometry": {"coordinates":[79.1584,13.04681],"type":"Point"}
}