{
  "type": "Feature",
  "properties": {
    "iso:country":"IN",
    "ks:ks_name":"Kasapada",
    "ks:ks_pop":312,
    "ks:ks_type":"HABITATION",
    "name:eng_x_preferred":[
        "Kasapada"
    ],
    "wof:name":"Kasapada",
    "wof:placetype":"locality",
    "wof:population":312
},
  "geometry": {"coordinates":[72.77298,19.907091],"type":"Point"}
}