{
  "type": "Feature",
  "properties": {
    "iso:country":"IN",
    "name:ara_x_preferred":[
        "\u0641\u064a\u0646\u0627\u064a \u0646\u0627\u062c\u0627\u0631"
    ],
    "name:ben_bn_x_preferred":[
        "\u09ac\u09bf\u09a3\u09df \u09a8\u0997\u09b0"
    ],
    "name:ben_in_x_preferred":[
        "\u09ac\u09bf\u09a3\u09df \u09a8\u0997\u09b0"
    ],
    "name:eng_x_preferred":[
        "Vinay Nagar"
    ],
    "name:guj_x_preferred":[
        "\u0ab5\u0abf\u0a9c\u0aaf \u0aa8\u0a97\u0ab0"
    ],
    "name:hin_x_preferred":[
        "\u0935\u093f\u0928\u092f \u0928\u0917\u0930"
    ],
    "name:kan_x_preferred":[
        "\u0cb5\u0cbf\u0ca8\u0caf\u0ccd"
    ],
    "name:mal_x_preferred":[
        "\u0d35\u0d3f\u0d28\u0d2f\u0d4d \u0d28\u0d17\u0d7c"
    ],
    "name:mar_x_preferred":[
        "\u0935\u093f\u0928\u092f \u0928\u0917\u0930"
    ],
    "name:pan_x_preferred":[
        "\u0a35\u0a3f\u0a1c\u0a47 \u0a28\u0a17\u0a30"
    ],
    "name:tam_x_preferred":[
        "\u0bb5\u0bbf\u0ba9\u0baf\u0bcd \u0ba8\u0b95\u0bb0\u0bcd"
    ],
    "name:tel_x_preferred":[
        "\u0c35\u0c3f\u0c28\u0c2f\u0c4d \u0c28\u0c17\u0c30\u0c4d"
    ],
    "name:urd_x_preferred":[
        "\u0648\u0646\u06d2 \u0646\u06af\u0631"
    ],
    "qs:gn_adm0_cc":"IN",
    "qs:gn_local":1270583,
    "qs:gn_nam_loc":"Gwalior, Gwalior, Madhya Pradesh, IN",
    "qs:gn_namadm1":"35",
    "qs:local_max":192,
    "qs:local_sum":312,
    "qs:localhoods":5,
    "qs:name":"Vinay Nagar",
    "qs:name_adm0":"India",
    "qs:name_adm1":"Madhya Pradesh",
    "qs:name_adm2":"Gwalior",
    "qs:name_local":"Gwalior",
    "qs:photo_max":29,
    "qs:photo_sum":39,
    "qs:placetype":"Suburb",
    "qs:quad_count":3,
    "qs:woe_adm0":23424848,
    "qs:woe_adm1":2345749,
    "qs:woe_adm2":12586494,
    "qs:woe_lau":0,
    "qs:woe_local":2295400,
    "qs:woe_ver":"7.10.0",
    "wof:lang":[
        "eng"
    ],
    "wof:name":"Vinay Nagar",
    "wof:placetype":"neighbourhood"
},
  "geometry": {"coordinates":[78.160858,26.223461],"type":"Point"}
}