{
  "type": "Feature",
  "properties": {
    "iso:country":"IN",
    "name:eng_x_preferred":[
        "Vinay Nagar"
    ],
    "name:unk_x_variant":[
        "Vinay Nagar"
    ],
    "qs:gn_adm0_cc":"IN",
    "qs:gn_local":1270583,
    "qs:gn_nam_loc":"Gwalior, Gwalior, Madhya Pradesh, IN",
    "qs:gn_namadm1":"35",
    "qs:local_max":192,
    "qs:local_sum":312,
    "qs:localhoods":5,
    "qs:name":"Vinay Nagar",
    "qs:name_adm0":"India",
    "qs:name_adm1":"Madhya Pradesh",
    "qs:name_adm2":"Gwalior",
    "qs:name_local":"Gwalior",
    "qs:photo_max":29,
    "qs:photo_sum":39,
    "qs:placetype":"Suburb",
    "qs:quad_count":3,
    "qs:woe_adm0":23424848,
    "qs:woe_adm1":2345749,
    "qs:woe_adm2":12586494,
    "qs:woe_lau":0,
    "qs:woe_local":2295400,
    "qs:woe_ver":"7.10.0",
    "wof:lang":[
        "eng"
    ],
    "wof:name":"Vinay Nagar",
    "wof:placetype":"neighbourhood"
},
  "geometry": {"coordinates":[78.160858,26.223461],"type":"Point"}
}