{
  "type": "Feature",
  "properties": {
    "gn:admin1_code":"24.0",
    "gn:admin2_code":"110",
    "gn:asciiname":"Barh",
    "gn:country_code":"IN",
    "gn:dem":397,
    "gn:feature_class":"P",
    "gn:feature_code":"PPL",
    "gn:name":"B\u0101rh",
    "gn:population":0,
    "gn:timezone":"Asia/Kolkata",
    "iso:country":"IN",
    "name:ben_x_preferred":[
        "\u09ac\u09a1\u09bc\u09b9"
    ],
    "name:bpy_x_preferred":[
        "\u09ac\u09a1\u09bc\u09b9"
    ],
    "name:ceb_x_preferred":[
        "B\u0101rh"
    ],
    "name:fra_x_preferred":[
        "Barh"
    ],
    "name:hif_x_preferred":[
        "Barh"
    ],
    "name:hin_x_preferred":[
        "\u092c\u093e\u0922\u093c"
    ],
    "name:ita_x_preferred":[
        "Barh"
    ],
    "name:mlg_x_preferred":[
        "Barh"
    ],
    "name:msa_x_preferred":[
        "Barh"
    ],
    "name:new_x_preferred":[
        "\u092c\u0930\u094d\u0939\u094d"
    ],
    "name:ori_x_preferred":[
        "\u0b2c\u0b3e\u0b22"
    ],
    "name:pam_x_preferred":[
        "Barh"
    ],
    "name:por_x_preferred":[
        "Barh"
    ],
    "name:spa_x_preferred":[
        "Barh"
    ],
    "name:swe_x_preferred":[
        "B\u0101rh"
    ],
    "name:urd_x_preferred":[
        "\u0628\u0627\u0691\u06be"
    ],
    "name:vie_x_preferred":[
        "Barh"
    ],
    "wof:name":"Barh",
    "wof:placetype":"locality"
},
  "geometry": {"coordinates":[75.5605,26.88262000000001],"type":"Point"}
}