{
  "type": "Feature",
  "properties": {
    "iso:country":"IN",
    "ks:ks_alt_nam":"Dhole wasti",
    "ks:ks_name":"Dhole Wasti",
    "ks:ks_pop":200,
    "ks:ks_type":"HABITATION",
    "name:eng_x_preferred":[
        "Dhole Wasti"
    ],
    "wof:name":"Dhole Wasti",
    "wof:placetype":"locality",
    "wof:population":200
},
  "geometry": {"coordinates":[75.30858000000001,19.19964],"type":"Point"}
}