{
  "type": "Feature",
  "properties": {
    "iso:country":"IN",
    "ks:ks_name":"Gahvad",
    "ks:ks_pop":721,
    "ks:ks_type":"HABITATION",
    "name:eng_x_preferred":[
        "Gahvad"
    ],
    "wof:name":"Gahvad",
    "wof:placetype":"locality",
    "wof:population":721
},
  "geometry": {"coordinates":[73.418111,20.711972],"type":"Point"}
}