{
  "type": "Feature",
  "properties": {
    "iso:country":"IN",
    "ks:ks_alt_nam":"PURNADAS PARA",
    "ks:ks_name":"Purnadas Para",
    "ks:ks_pop":150,
    "ks:ks_type":"HABITATION",
    "name:eng_x_preferred":[
        "Purnadas Para"
    ],
    "wof:name":"Purnadas Para",
    "wof:placetype":"locality",
    "wof:population":150
},
  "geometry": {"coordinates":[91.206773,23.696679],"type":"Point"}
}