{
  "type": "Feature",
  "properties": {
    "gn:admin1_code":"19.0",
    "gn:admin2_code":"570.0",
    "gn:asciiname":"Hemarhalli",
    "gn:country_code":"IN",
    "gn:dem":805,
    "gn:feature_class":"P",
    "gn:feature_code":"PPL",
    "gn:name":"Hem\u0101rhalli",
    "gn:population":0,
    "gn:timezone":"Asia/Kolkata",
    "iso:country":"IN",
    "wof:name":"Hemarhalli",
    "wof:placetype":"locality"
},
  "geometry": {"coordinates":[75.63677,13.42074],"type":"Point"}
}