{
  "type": "Feature",
  "properties": {
    "iso:country":"IN",
    "ks:ks_name":"Khairawa",
    "ks:ks_pop":158,
    "ks:ks_type":"HABITATION",
    "name:eng_x_preferred":[
        "Khairawa"
    ],
    "wof:name":"Khairawa",
    "wof:placetype":"locality",
    "wof:population":158
},
  "geometry": {"coordinates":[82.95632999999999,24.769952],"type":"Point"}
}