{
  "type": "Feature",
  "properties": {
    "iso:country":"IN",
    "ks:ks_alt_nam":"pitambarwadi",
    "ks:ks_name":"Pitambarwadi",
    "ks:ks_pop":149,
    "ks:ks_type":"HABITATION",
    "name:eng_x_preferred":[
        "Pitambarwadi"
    ],
    "wof:name":"Pitambarwadi",
    "wof:placetype":"locality",
    "wof:population":149
},
  "geometry": {"coordinates":[78.249415,19.650839],"type":"Point"}
}