{
  "type": "Feature",
  "properties": {
    "iso:country":"IN",
    "ks:ks_name":"Kumharan Purwa",
    "ks:ks_pop":117,
    "ks:ks_type":"HABITATION",
    "name:eng_x_preferred":[
        "Kumharan Purwa"
    ],
    "wof:name":"Kumharan Purwa",
    "wof:placetype":"locality",
    "wof:population":117
},
  "geometry": {"coordinates":[81.74801100000001,27.320677],"type":"Point"}
}