{
  "type": "Feature",
  "properties": {
    "gn:admin1_code":"36.0",
    "gn:admin2_code":"173.0",
    "gn:asciiname":"Sumerpur",
    "gn:country_code":"IN",
    "gn:dem":102,
    "gn:feature_class":"P",
    "gn:feature_code":"PPL",
    "gn:name":"Sumerpur",
    "gn:population":0,
    "gn:timezone":"Asia/Kolkata",
    "iso:country":"IN",
    "name:ben_x_preferred":[
        "\u09b8\u09c1\u09ae\u09c7\u09b0\u09aa\u09c1\u09b0"
    ],
    "name:bpy_x_preferred":[
        "\u09b8\u09c1\u09ae\u09c7\u09b0\u09aa\u09c1\u09b0"
    ],
    "name:ceb_x_preferred":[
        "Sumerpur"
    ],
    "name:hif_x_preferred":[
        "Sumerpur"
    ],
    "name:hin_x_preferred":[
        "\u0938\u0941\u092e\u0947\u0930\u092a\u0941\u0930"
    ],
    "name:ita_x_preferred":[
        "Sumerpur"
    ],
    "name:msa_x_preferred":[
        "Sumerpur"
    ],
    "name:nld_x_preferred":[
        "Sumerpur"
    ],
    "name:ori_x_preferred":[
        "\u0b38\u0b41\u0b2e\u0b47\u0b30\u0b2a\u0b41\u0b30"
    ],
    "name:swe_x_preferred":[
        "Sumerpur"
    ],
    "name:vie_x_preferred":[
        "Sumerpur"
    ],
    "name:zho_x_preferred":[
        "\u82cf\u6885\u5c14\u666e\u5c14"
    ],
    "wof:name":"Sumerpur",
    "wof:placetype":"locality"
},
  "geometry": {"coordinates":[81.86703,25.73403],"type":"Point"}
}