{
  "type": "Feature",
  "properties": {
    "gn:admin1_code":"28.0",
    "gn:asciiname":"Manoharpur",
    "gn:country_code":"IN",
    "gn:dem":5,
    "gn:feature_class":"P",
    "gn:feature_code":"PPL",
    "gn:name":"Manoharpur",
    "gn:population":0,
    "gn:timezone":"Asia/Kolkata",
    "iso:country":"IN",
    "wof:name":"Manoharpur",
    "wof:placetype":"locality"
},
  "geometry": {"coordinates":[88.21056,22.13361],"type":"Point"}
}