{
  "type": "Feature",
  "properties": {
    "iso:country":"IN",
    "ks:ks_alt_nam":"Naya S\u0101nw\u0101ra",
    "ks:ks_name":"Naya Sanwara",
    "ks:ks_pop":4191,
    "ks:ks_type":"VILLAGE",
    "name:eng_x_preferred":[
        "Naya Sanwara"
    ],
    "name:eng_x_variant":[
        "Naya S\u0101nw\u0101ra"
    ],
    "wof:name":"Naya Sanwara",
    "wof:placetype":"locality",
    "wof:population":4191
},
  "geometry": {"coordinates":[72.940028,24.849236],"type":"Point"}
}