{
  "type": "Feature",
  "properties": {
    "gn:country":"IN",
    "gn:fcode":"PPL",
    "gn:population":11379,
    "iso:country":"IN",
    "name:ast_x_preferred":[
        "Mangalam"
    ],
    "name:bpy_x_preferred":[
        "\u09ae\u0999\u09cd\u0997\u09b2\u09ae"
    ],
    "name:bul_x_preferred":[
        "\u041c\u0430\u043d\u0433\u0430\u043b\u0430\u043c"
    ],
    "name:ceb_x_preferred":[
        "Mangalam"
    ],
    "name:eng_x_preferred":[
        "Mangalam"
    ],
    "name:ita_x_preferred":[
        "Mangalam"
    ],
    "name:msa_x_preferred":[
        "Mangalam"
    ],
    "name:nan_x_preferred":[
        "Mangalam"
    ],
    "name:new_x_preferred":[
        "\u092e\u0902\u0917\u0932\u092e"
    ],
    "name:nld_x_preferred":[
        "Mangalam"
    ],
    "name:swe_x_preferred":[
        "Mangalam"
    ],
    "name:tam_x_preferred":[
        "\u0bae\u0b99\u0bcd\u0b95\u0bb3\u0bae\u0bcd"
    ],
    "name:und_x_variant":[
        "Mungalum"
    ],
    "name:vie_x_preferred":[
        "Mangalam"
    ],
    "name:zho_x_preferred":[
        "\u8292\u683c\u963f\u62c9\u59c6"
    ],
    "qs:name":"Karamangalam",
    "qs:name_adm0":"India",
    "qs:name_adm1":"Tamil Nadu",
    "qs:photos_9r":0,
    "qs:photos_sr":0,
    "qs:placetype":"Town",
    "qs:pop_sr":"6",
    "wd:wordcount":70,
    "wof:name":"Karamangalam",
    "wof:placetype":"locality",
    "wof:population":11379
},
  "geometry": {"coordinates":[78.63969,9.76572],"type":"Point"}
}