{
  "type": "Feature",
  "properties": {
    "iso:country":"IN",
    "ks:ks_name":"Sirser",
    "ks:ks_pop":598,
    "ks:ks_type":"VILLAGE",
    "name:eng_x_preferred":[
        "Sirser"
    ],
    "wof:name":"Sirser",
    "wof:placetype":"locality",
    "wof:population":598
},
  "geometry": {"coordinates":[78.78335800000001,30.288131],"type":"Point"}
}