{
  "type": "Feature",
  "properties": {
    "gn:admin1_code":"36",
    "gn:admin2_code":"202.0",
    "gn:asciiname":"Kanjahar",
    "gn:country_code":"IN",
    "gn:dem":166,
    "gn:feature_class":"P",
    "gn:feature_code":"PPL",
    "gn:name":"Kanj\u0101h\u0101r",
    "gn:population":0,
    "gn:timezone":"Asia/Kolkata",
    "iso:country":"IN",
    "wof:name":"Kanjahar",
    "wof:placetype":"locality"
},
  "geometry": {"coordinates":[78.93549,27.59164],"type":"Point"}
}