{
  "type": "Feature",
  "properties": {
    "gn:admin1_code":"35",
    "gn:admin2_code":"462.0",
    "gn:asciiname":"Goriara",
    "gn:country_code":"IN",
    "gn:dem":334,
    "gn:feature_class":"P",
    "gn:feature_code":"PPL",
    "gn:name":"Goriara",
    "gn:population":0,
    "gn:timezone":"Asia/Kolkata",
    "iso:country":"IN",
    "ks:ks_name":"Goriyara",
    "ks:ks_pop":1323,
    "ks:ks_type":"VILLAGE",
    "name:eng_x_preferred":[
        "Goriyara"
    ],
    "name:eng_x_variant":[
        "Goriara"
    ],
    "wof:name":"Goriyara",
    "wof:placetype":"locality",
    "wof:population":1323
},
  "geometry": {"coordinates":[81.89878299999999,24.362944],"type":"Point"}
}