{
  "type": "Feature",
  "properties": {
    "gn:admin1_code":"25.0",
    "gn:admin2_code":"618.0",
    "gn:asciiname":"Naluvedapati",
    "gn:country_code":"IN",
    "gn:dem":5,
    "gn:feature_class":"P",
    "gn:feature_code":"PPL",
    "gn:name":"N\u0101luvedapati",
    "gn:population":0,
    "gn:timezone":"Asia/Kolkata",
    "iso:country":"IN",
    "ks:ks_name":"Naluvethapathi",
    "ks:ks_pop":2402,
    "ks:ks_type":"VILLAGE",
    "ks:ks_uagg_main":0,
    "name:eng_x_preferred":[
        "Naluvethapathi"
    ],
    "wof:name":"Naluvethapathi",
    "wof:placetype":"neighbourhood",
    "wof:population":2402
},
  "geometry": {"coordinates":[79.84024700000001,10.503641],"type":"Point"}
}