{
  "type": "Feature",
  "properties": {
    "iso:country":"IN",
    "name:ara_x_preferred":[
        "\u062c\u0648\u062f\u0648\u0644\u0628\u064a"
    ],
    "name:ben_bn_x_preferred":[
        "\u0997\u09cb\u09a6\u09cb\u09b2\u09bf\u09df\u09be"
    ],
    "name:ben_in_x_preferred":[
        "\u0997\u09cb\u09a6\u09cb\u09b2\u09bf\u09df\u09be"
    ],
    "name:eng_x_preferred":[
        "Godoliya"
    ],
    "name:guj_x_preferred":[
        "\u0a97\u0acb\u0aa1\u0acb\u0ab2\u0abf\u0aaf\u0abe"
    ],
    "name:hin_x_preferred":[
        "\u0917\u094b\u0921\u094b\u0932\u093f\u092f\u093e"
    ],
    "name:kan_x_preferred":[
        "\u0c97\u0cca\u0ca1\u0cca\u0cb2\u0cbf\u0caf\u0cbe"
    ],
    "name:mal_x_preferred":[
        "\u0d17\u0d4b\u0d26\u0d4b\u0d32\u0d3f\u0d2f"
    ],
    "name:mar_x_preferred":[
        "\u0917\u094b\u0921\u094b\u0932\u093f\u092f\u093e"
    ],
    "name:pan_x_preferred":[
        "\u0a17\u0a4b\u0a21\u0a4b\u0a32\u0a40\u0a06"
    ],
    "name:tam_x_preferred":[
        "\u0b95\u0bca\u0b9f\u0bca\u0bb2\u0bbf\u0baf\u0bbe"
    ],
    "name:tel_x_preferred":[
        "\u0c17\u0c4b\u0c21\u0c4b\u0c32\u0c3f\u0c2f\u0c3e"
    ],
    "name:urd_x_preferred":[
        "\u06af\u0648\u0688\u0648\u0644\u06cc\u0627"
    ],
    "qs:gn_adm0_cc":"IN",
    "qs:gn_local":1253405,
    "qs:gn_nam_loc":"Varanasi, Varanasi, Uttar Pradesh, IN",
    "qs:gn_namadm1":"36",
    "qs:local_max":11649,
    "qs:local_sum":17228,
    "qs:localhoods":15,
    "qs:name":"Godoliya",
    "qs:name_adm0":"India",
    "qs:name_adm1":"Uttar Pradesh",
    "qs:name_adm2":"Varanasi",
    "qs:name_local":"Varanasi",
    "qs:photo_max":3181,
    "qs:photo_sum":11649,
    "qs:placetype":"Suburb",
    "qs:quad_count":49,
    "qs:woe_adm0":23424848,
    "qs:woe_adm1":2345760,
    "qs:woe_adm2":12586794,
    "qs:woe_lau":0,
    "qs:woe_local":2295380,
    "qs:woe_ver":"7.10.0",
    "wof:lang":[
        "eng"
    ],
    "wof:name":"Godoliya",
    "wof:placetype":"neighbourhood"
},
  "geometry": {"coordinates":[83.010813,25.306735],"type":"Point"}
}