{
  "type": "Feature",
  "properties": {
    "gn:admin1_code":"35",
    "gn:admin2_code":"452.0",
    "gn:asciiname":"Babariya",
    "gn:country_code":"IN",
    "gn:dem":390,
    "gn:feature_class":"P",
    "gn:feature_code":"PPL",
    "gn:name":"Babariya",
    "gn:population":0,
    "gn:timezone":"Asia/Kolkata",
    "iso:country":"IN",
    "wof:name":"Babariya",
    "wof:placetype":"locality"
},
  "geometry": {"coordinates":[79.32174999999999,22.87845],"type":"Point"}
}