{
  "type": "Feature",
  "properties": {
    "iso:country":"IN",
    "ks:ks_name":"Kalleppadi Jn1",
    "ks:ks_pop":546,
    "ks:ks_type":"HABITATION",
    "ks:ks_uagg_main":0,
    "name:eng_x_preferred":[
        "Kalleppadi Jn1"
    ],
    "wof:name":"Kalleppadi Jn1",
    "wof:placetype":"locality",
    "wof:population":546
},
  "geometry": {"coordinates":[76.215283,10.597273],"type":"Point"}
}