{
  "type": "Feature",
  "properties": {
    "iso:country":"IN",
    "ks:ks_name":"Gaith Tola",
    "ks:ks_pop":898,
    "ks:ks_type":"HABITATION",
    "name:eng_x_preferred":[
        "Gaith Tola"
    ],
    "wof:name":"Gaith Tola",
    "wof:placetype":"locality",
    "wof:population":898
},
  "geometry": {"coordinates":[86.705055,25.841453],"type":"Point"}
}