{
  "type": "Feature",
  "properties": {
    "iso:country":"IN",
    "ks:ks_name":"Kalta",
    "ks:ks_pop":0,
    "ks:ks_type":"VILLAGE",
    "name:eng_x_preferred":[
        "Kalta"
    ],
    "wof:name":"Kalta",
    "wof:placetype":"locality",
    "wof:population":0
},
  "geometry": {"coordinates":[87.253435,22.127685],"type":"Point"}
}