{
  "type": "Feature",
  "properties": {
    "iso:country":"IN",
    "ks:ks_name":"Moriya Khuna",
    "ks:ks_pop":258,
    "ks:ks_type":"HABITATION",
    "name:eng_x_preferred":[
        "Moriya Khuna"
    ],
    "wof:name":"Moriya Khuna",
    "wof:placetype":"locality",
    "wof:population":258
},
  "geometry": {"coordinates":[73.28832800000001,24.630103],"type":"Point"}
}