{
  "type": "Feature",
  "properties": {
    "gn:admin1_code":"39.0",
    "gn:admin2_code":"64.0",
    "gn:asciiname":"Dhaili",
    "gn:country_code":"IN",
    "gn:dem":1712,
    "gn:feature_class":"P",
    "gn:feature_code":"PPL",
    "gn:name":"Dhaili",
    "gn:population":0,
    "gn:timezone":"Asia/Kolkata",
    "iso:country":"IN",
    "wof:name":"Dhaili",
    "wof:placetype":"locality"
},
  "geometry": {"coordinates":[79.73423000000003,29.56219],"type":"Point"}
}