{
  "type": "Feature",
  "properties": {
    "iso:country":"IN",
    "ks:ks_name":"Jahangirpur Andaur",
    "ks:ks_pop":3168,
    "ks:ks_type":"VILLAGE",
    "name:eng_x_preferred":[
        "Jahangirpur Andaur"
    ],
    "wof:name":"Jahangirpur Andaur",
    "wof:placetype":"locality",
    "wof:population":3168
},
  "geometry": {"coordinates":[85.684158,25.600991],"type":"Point"}
}