{
  "type": "Feature",
  "properties": {
    "iso:country":"IN",
    "ks:ks_name":"Mondkarwadi",
    "ks:ks_pop":55,
    "ks:ks_type":"HABITATION",
    "name:eng_x_preferred":[
        "Mondkarwadi"
    ],
    "wof:name":"Mondkarwadi",
    "wof:placetype":"locality",
    "wof:population":55
},
  "geometry": {"coordinates":[73.61672,16.336],"type":"Point"}
}