{
  "type": "Feature",
  "properties": {
    "iso:country":"IN",
    "ks:ks_name":"Nagla Nimoh",
    "ks:ks_pop":122,
    "ks:ks_type":"HABITATION",
    "name:eng_x_preferred":[
        "Nagla Nimoh"
    ],
    "wof:name":"Nagla Nimoh",
    "wof:placetype":"locality",
    "wof:population":122
},
  "geometry": {"coordinates":[78.64715099999999,27.221523],"type":"Point"}
}