{
  "type": "Feature",
  "properties": {
    "iso:country":"IN",
    "ks:ks_name":"Chotohapjan 114 4 Nlr.",
    "ks:ks_pop":2236,
    "ks:ks_type":"HABITATION",
    "name:eng_x_preferred":[
        "Chotohapjan 114 4 Nlr."
    ],
    "wof:name":"Chotohapjan 114 4 Nlr.",
    "wof:placetype":"locality",
    "wof:population":2236
},
  "geometry": {"coordinates":[95.475131,27.497131],"type":"Point"}
}