{
  "type": "Feature",
  "properties": {
    "iso:country":"IN",
    "ks:ks_name":"Sos",
    "ks:ks_pop":1644,
    "ks:ks_type":"VILLAGE",
    "name:eng_x_preferred":[
        "Sos"
    ],
    "wof:name":"Sos",
    "wof:placetype":"locality",
    "wof:population":1644
},
  "geometry": {"coordinates":[82.519558,23.145371],"type":"Point"}
}