{
  "type": "Feature",
  "properties": {
    "iso:country":"IN",
    "ks:ks_name":"Biripada",
    "ks:ks_pop":38,
    "ks:ks_type":"VILLAGE",
    "name:eng_x_preferred":[
        "Biripada"
    ],
    "wof:name":"Biripada",
    "wof:placetype":"locality",
    "wof:population":38
},
  "geometry": {"coordinates":[84.387415,19.636381],"type":"Point"}
}