{
  "type": "Feature",
  "properties": {
    "gn:admin1_code":"24",
    "gn:admin2_code":"118.0",
    "gn:asciiname":"Lambia",
    "gn:country_code":"IN",
    "gn:dem":319,
    "gn:feature_class":"P",
    "gn:feature_code":"PPL",
    "gn:name":"L\u0101mbia",
    "gn:population":0,
    "gn:timezone":"Asia/Kolkata",
    "iso:country":"IN",
    "name:por_x_preferred":[
        "Lambia"
    ],
    "name:spa_x_preferred":[
        "Lambia"
    ],
    "name:und_x_variant":[
        "L\u0101mbiya",
        "L\u0101mbia"
    ],
    "wof:name":"Lambia",
    "wof:placetype":"locality"
},
  "geometry": {"coordinates":[74.0635,26.395],"type":"Point"}
}