{
  "type": "Feature",
  "properties": {
    "gn:admin1_code":"34.0",
    "gn:admin2_code":"220.0",
    "gn:asciiname":"Mansurpur",
    "gn:country_code":"IN",
    "gn:dem":54,
    "gn:feature_class":"P",
    "gn:feature_code":"PPL",
    "gn:name":"Mans\u016brpur",
    "gn:population":0,
    "gn:timezone":"Asia/Kolkata",
    "iso:country":"IN",
    "ks:ks_name":"Mansurapur",
    "ks:ks_pop":1759,
    "ks:ks_type":"VILLAGE",
    "name:eng_x_preferred":[
        "Mansurapur"
    ],
    "name:eng_x_variant":[
        "Mansurpur"
    ],
    "wof:name":"Mansurapur",
    "wof:placetype":"locality",
    "wof:population":1759
},
  "geometry": {"coordinates":[85.273066,25.775689],"type":"Point"}
}