{
  "type": "Feature",
  "properties": {
    "iso:country":"IN",
    "ks:ks_name":"Palabavi Thanda",
    "ks:ks_pop":32,
    "ks:ks_type":"HABITATION",
    "ks:ks_uagg_main":0,
    "name:eng_x_preferred":[
        "Palabavi Thanda"
    ],
    "wof:name":"Palabavi Thanda",
    "wof:placetype":"neighbourhood",
    "wof:population":32
},
  "geometry": {"coordinates":[78.108402,14.302461],"type":"Point"}
}