{
  "type": "Feature",
  "properties": {
    "iso:country":"IN",
    "ks:ks_name":"Ghoda Tola",
    "ks:ks_pop":271,
    "ks:ks_type":"HABITATION",
    "ks:ks_uagg_main":0,
    "name:eng_x_preferred":[
        "Ghoda Tola"
    ],
    "wof:name":"Ghoda Tola",
    "wof:placetype":"neighbourhood",
    "wof:population":271
},
  "geometry": {"coordinates":[83.776138,27.04187],"type":"Point"}
}