{
  "type": "Feature",
  "properties": {
    "iso:country":"IN",
    "ks:ks_name":"Islampur",
    "ks:ks_pop":67,
    "ks:ks_type":"VILLAGE",
    "name:eng_x_preferred":[
        "Islampur"
    ],
    "wof:name":"Islampur",
    "wof:placetype":"locality",
    "wof:population":67
},
  "geometry": {"coordinates":[79.248215,19.143545],"type":"Point"}
}