{
  "type": "Feature",
  "properties": {
    "iso:country":"IN",
    "ks:ks_name":"Anamel",
    "ks:ks_pop":338,
    "ks:ks_type":"VILLAGE",
    "name:eng_x_preferred":[
        "Anamel"
    ],
    "wof:name":"Anamel",
    "wof:placetype":"locality",
    "wof:population":338
},
  "geometry": {"coordinates":[82.384748,18.512706],"type":"Point"}
}