{
  "type": "Feature",
  "properties": {
    "gn:admin1_code":"19.0",
    "gn:admin2_code":"581.0",
    "gn:asciiname":"Kurubarahalli",
    "gn:country_code":"IN",
    "gn:dem":751,
    "gn:feature_class":"P",
    "gn:feature_code":"PPL",
    "gn:name":"Kurubarahalli",
    "gn:population":0,
    "gn:timezone":"Asia/Kolkata",
    "iso:country":"IN",
    "wof:name":"Kurubarahalli",
    "wof:placetype":"locality"
},
  "geometry": {"coordinates":[78.5064,13.19745],"type":"Point"}
}