{
  "type": "Feature",
  "properties": {
    "iso:country":"IN",
    "ks:ks_alt_nam":"Khor\u0101mpur",
    "ks:ks_name":"Khorampur",
    "ks:ks_pop":0,
    "ks:ks_type":"VILLAGE",
    "ks:ks_uagg_main":0,
    "name:eng_x_preferred":[
        "Khorampur"
    ],
    "name:eng_x_variant":[
        "Khor\u0101mpur"
    ],
    "wof:name":"Khorampur",
    "wof:placetype":"neighbourhood",
    "wof:population":0
},
  "geometry": {"coordinates":[83.878747,25.462159],"type":"Point"}
}