{
  "type": "Feature",
  "properties": {
    "gn:admin1_code":"2",
    "gn:admin2_code":"544.0",
    "gn:asciiname":"Sariya",
    "gn:country_code":"IN",
    "gn:dem":321,
    "gn:feature_class":"P",
    "gn:feature_code":"PPL",
    "gn:name":"Sariya",
    "gn:population":0,
    "gn:timezone":"Asia/Kolkata",
    "iso:country":"IN",
    "ks:ks_name":"Sariya",
    "ks:ks_pop":61,
    "ks:ks_type":"VILLAGE",
    "name:eng_x_preferred":[
        "Sariya"
    ],
    "wof:name":"Sariya",
    "wof:placetype":"locality",
    "wof:population":61
},
  "geometry": {"coordinates":[82.888373,18.037023],"type":"Point"}
}