{
  "type": "Feature",
  "properties": {
    "iso:country":"IN",
    "ks:ks_name":"Temburni",
    "ks:ks_pop":92,
    "ks:ks_type":"HABITATION",
    "name:eng_x_preferred":[
        "Temburni"
    ],
    "wof:name":"Temburni",
    "wof:placetype":"locality",
    "wof:population":92
},
  "geometry": {"coordinates":[78.53328500000001,18.984157],"type":"Point"}
}