{
  "type": "Feature",
  "properties": {
    "gn:admin1_code":"11.0",
    "gn:admin2_code":"32.0",
    "gn:asciiname":"Garahu",
    "gn:country_code":"IN",
    "gn:dem":1069,
    "gn:feature_class":"P",
    "gn:feature_code":"PPL",
    "gn:name":"Gar\u0101hu",
    "gn:population":0,
    "gn:timezone":"Asia/Kolkata",
    "iso:country":"IN",
    "wof:name":"Garahu",
    "wof:placetype":"locality"
},
  "geometry": {"coordinates":[77.34300999999998,30.76771],"type":"Point"}
}