{
  "type": "Feature",
  "properties": {
    "gn:admin1_code":"39.0",
    "gn:admin2_code":"061",
    "gn:asciiname":"Gaula",
    "gn:country_code":"IN",
    "gn:dem":1226,
    "gn:feature_class":"P",
    "gn:feature_code":"PPL",
    "gn:name":"Gaula",
    "gn:population":0,
    "gn:timezone":"Asia/Kolkata",
    "iso:country":"IN",
    "name:ceb_x_preferred":[
        "Gaula"
    ],
    "name:dan_x_preferred":[
        "Gaula"
    ],
    "name:deu_x_preferred":[
        "Gaula"
    ],
    "name:fra_x_preferred":[
        "Gaula"
    ],
    "name:ita_x_preferred":[
        "Gaula"
    ],
    "name:nor_x_preferred":[
        "Gaula"
    ],
    "name:pol_x_preferred":[
        "Gaula"
    ],
    "name:swe_x_preferred":[
        "Gaula"
    ],
    "wof:name":"Gaula",
    "wof:placetype":"locality"
},
  "geometry": {"coordinates":[78.50426,29.90518],"type":"Point"}
}