{
  "type": "Feature",
  "properties": {
    "iso:country":"IN",
    "ks:ks_name":"Chak Kutubpur",
    "ks:ks_pop":806,
    "ks:ks_type":"VILLAGE",
    "name:eng_x_preferred":[
        "Chak Kutubpur"
    ],
    "wof:name":"Chak Kutubpur",
    "wof:placetype":"locality",
    "wof:population":806
},
  "geometry": {"coordinates":[85.18407000000001,25.914732],"type":"Point"}
}