{
  "type": "Feature",
  "properties": {
    "gn:admin1_code":"11",
    "gn:admin2_code":"33.0",
    "gn:asciiname":"Nahera",
    "gn:country_code":"IN",
    "gn:dem":2291,
    "gn:feature_class":"P",
    "gn:feature_code":"PPL",
    "gn:name":"Nahera",
    "gn:population":0,
    "gn:timezone":"Asia/Kolkata",
    "iso:country":"IN",
    "wof:name":"Nahera",
    "wof:placetype":"locality"
},
  "geometry": {"coordinates":[77.24758,31.04141],"type":"Point"}
}