{
  "type": "Feature",
  "properties": {
    "iso:country":"IN",
    "ks:ks_name":"Chevoor North",
    "ks:ks_pop":1225,
    "ks:ks_type":"HABITATION",
    "ks:ks_uagg_main":0,
    "name:eng_x_preferred":[
        "Chevoor North"
    ],
    "wof:name":"Chevoor North",
    "wof:placetype":"locality",
    "wof:population":1225
},
  "geometry": {"coordinates":[76.21629799999999,10.404013],"type":"Point"}
}