{
  "type": "Feature",
  "properties": {
    "iso:country":"IN",
    "ks:ks_name":"Jahri Laga Mathall",
    "ks:ks_pop":13,
    "ks:ks_type":"HABITATION",
    "name:eng_x_preferred":[
        "Jahri Laga Mathall"
    ],
    "wof:name":"Jahri Laga Mathall",
    "wof:placetype":"locality",
    "wof:population":13
},
  "geometry": {"coordinates":[78.76414699999999,29.771652],"type":"Point"}
}