{
  "type": "Feature",
  "properties": {
    "iso:country":"IN",
    "ks:ks_name":"Ghotul Para",
    "ks:ks_pop":249,
    "ks:ks_type":"HABITATION",
    "name:eng_x_preferred":[
        "Ghotul Para"
    ],
    "wof:name":"Ghotul Para",
    "wof:placetype":"locality",
    "wof:population":249
},
  "geometry": {"coordinates":[81.37244800000001,19.687831],"type":"Point"}
}