{
  "type": "Feature",
  "properties": {
    "gn:admin1_code":"37.0",
    "gn:admin2_code":"414.0",
    "gn:asciiname":"Chandragiri",
    "gn:country_code":"IN",
    "gn:dem":721,
    "gn:feature_class":"P",
    "gn:feature_code":"PPL",
    "gn:name":"Chandragiri",
    "gn:population":0,
    "gn:timezone":"Asia/Kolkata",
    "iso:country":"IN",
    "wof:name":"Chandragiri",
    "wof:placetype":"locality"
},
  "geometry": {"coordinates":[81.78234999999999,18.88433],"type":"Point"}
}