{
  "type": "Feature",
  "properties": {
    "gn:admin1_code":"37.0",
    "gn:admin2_code":"414.0",
    "gn:asciiname":"Chandragiri",
    "gn:country_code":"IN",
    "gn:dem":721,
    "gn:feature_class":"P",
    "gn:feature_code":"PPL",
    "gn:name":"Chandragiri",
    "gn:population":0,
    "gn:timezone":"Asia/Kolkata",
    "iso:country":"IN",
    "name:cat_x_preferred":[
        "Chandragiri"
    ],
    "name:fra_x_preferred":[
        "Chandragiri"
    ],
    "name:ita_x_preferred":[
        "Chandragiri"
    ],
    "name:jpn_x_preferred":[
        "\u30c1\u30e3\u30f3\u30c9\u30e9\u30ae\u30ea"
    ],
    "name:new_x_preferred":[
        "\u091a\u0902\u0926\u094d\u0930\u0917\u093f\u0930\u093f \u092e\u0923\u094d\u0921\u0932"
    ],
    "name:pam_x_preferred":[
        "Chandragiri"
    ],
    "name:tam_x_preferred":[
        "\u0b9a\u0ba8\u0bcd\u0ba4\u0bbf\u0bb0\u0b95\u0bbf\u0bb0\u0bbf \u0bae\u0ba3\u0bcd\u0b9f\u0bb2\u0bae\u0bcd"
    ],
    "name:tel_x_preferred":[
        "\u0c1a\u0c02\u0c26\u0c4d\u0c30\u0c17\u0c3f\u0c30\u0c3f"
    ],
    "name:tgl_x_preferred":[
        "Chandragiri"
    ],
    "name:urd_x_preferred":[
        "\u0686\u0646\u062f\u0631\u0627\u06af\u0631\u06cc"
    ],
    "name:vie_x_preferred":[
        "Chandragiri"
    ],
    "wof:name":"Chandragiri",
    "wof:placetype":"locality"
},
  "geometry": {"coordinates":[81.78234999999999,18.88433],"type":"Point"}
}