{
  "type": "Feature",
  "properties": {
    "iso:country":"IN",
    "ks:ks_name":"Petforwa Oraon Tola",
    "ks:ks_pop":100,
    "ks:ks_type":"HABITATION",
    "name:eng_x_preferred":[
        "Petforwa Oraon Tola"
    ],
    "wof:name":"Petforwa Oraon Tola",
    "wof:placetype":"locality",
    "wof:population":100
},
  "geometry": {"coordinates":[83.67379200000001,23.857421],"type":"Point"}
}