{
  "type": "Feature",
  "properties": {
    "gn:admin1_code":"35.0",
    "gn:admin2_code":"456.0",
    "gn:asciiname":"Tendnitola",
    "gn:country_code":"IN",
    "gn:dem":619,
    "gn:feature_class":"P",
    "gn:feature_code":"PPL",
    "gn:name":"Tendn\u012btola",
    "gn:population":0,
    "gn:timezone":"Asia/Kolkata",
    "iso:country":"IN",
    "wof:name":"Tendnitola",
    "wof:placetype":"locality"
},
  "geometry": {"coordinates":[79.41349,22.47261],"type":"Point"}
}