{
  "type": "Feature",
  "properties": {
    "iso:country":"IN",
    "ks:ks_name":"Narholi",
    "ks:ks_pop":3926,
    "ks:ks_type":"VILLAGE",
    "ks:ks_uagg_main":0,
    "name:eng_x_preferred":[
        "Narholi"
    ],
    "wof:name":"Narholi",
    "wof:placetype":"neighbourhood",
    "wof:population":3926
},
  "geometry": {"coordinates":[77.666245,27.458804],"type":"Point"}
}