{
  "type": "Feature",
  "properties": {
    "gn:admin1_code":"34.0",
    "gn:admin2_code":"238.0",
    "gn:asciiname":"Jansinghdih",
    "gn:country_code":"IN",
    "gn:dem":86,
    "gn:feature_class":"P",
    "gn:feature_code":"PPL",
    "gn:name":"Jansinghdih",
    "gn:population":0,
    "gn:timezone":"Asia/Kolkata",
    "iso:country":"IN",
    "ks:ks_name":"Jansinghdih",
    "ks:ks_pop":1041,
    "ks:ks_type":"VILLAGE",
    "name:eng_x_preferred":[
        "Jansinghdih"
    ],
    "wof:name":"Jansinghdih",
    "wof:placetype":"locality",
    "wof:population":1041
},
  "geometry": {"coordinates":[86.024019,24.907075],"type":"Point"}
}