{
  "type": "Feature",
  "properties": {
    "gn:admin1_code":"36.0",
    "gn:admin2_code":"188",
    "gn:asciiname":"Bhaunrabari",
    "gn:country_code":"IN",
    "gn:dem":83,
    "gn:feature_class":"P",
    "gn:feature_code":"PPL",
    "gn:name":"Bhaunrab\u0101ri",
    "gn:population":0,
    "gn:timezone":"Asia/Kolkata",
    "iso:country":"IN",
    "name:und_x_variant":[
        "Bhaunrab\u0101ri",
        "Bhaunrabari"
    ],
    "wof:name":"Bhaunrabari",
    "wof:placetype":"locality"
},
  "geometry": {"coordinates":[83.34683000000003,27.02571],"type":"Point"}
}