{
  "type": "Feature",
  "properties": {
    "iso:country":"IN",
    "ks:ks_name":"Haldibari",
    "ks:ks_pop":278,
    "ks:ks_type":"HABITATION",
    "name:eng_x_preferred":[
        "Haldibari"
    ],
    "wof:name":"Haldibari",
    "wof:placetype":"locality",
    "wof:population":278
},
  "geometry": {"coordinates":[93.61849599999999,26.93593],"type":"Point"}
}