{
  "type": "Feature",
  "properties": {
    "iso:country":"IN",
    "ks:ks_name":"Pradhaniguda",
    "ks:ks_pop":67,
    "ks:ks_type":"HABITATION",
    "name:eng_x_preferred":[
        "Pradhaniguda"
    ],
    "wof:name":"Pradhaniguda",
    "wof:placetype":"locality",
    "wof:population":67
},
  "geometry": {"coordinates":[82.148183,18.600172],"type":"Point"}
}