{
  "type": "Feature",
  "properties": {
    "iso:country":"IN",
    "ks:ks_alt_nam":"Sundarsing colony",
    "ks:ks_name":"Sundarsing Colony",
    "ks:ks_pop":199,
    "ks:ks_type":"HABITATION",
    "name:eng_x_preferred":[
        "Sundarsing Colony"
    ],
    "wof:name":"Sundarsing Colony",
    "wof:placetype":"locality",
    "wof:population":199
},
  "geometry": {"coordinates":[81.952901,16.572831],"type":"Point"}
}