{
  "type": "Feature",
  "properties": {
    "iso:country":"IN",
    "ks:ks_name":"Ram Sewak Ka Purwa",
    "ks:ks_pop":67,
    "ks:ks_type":"HABITATION",
    "name:eng_x_preferred":[
        "Ram Sewak Ka Purwa"
    ],
    "wof:name":"Ram Sewak Ka Purwa",
    "wof:placetype":"locality",
    "wof:population":67
},
  "geometry": {"coordinates":[81.125052,25.274515],"type":"Point"}
}