{
  "type": "Feature",
  "properties": {
    "iso:country":"IN",
    "ks:ks_name":"Nagariya",
    "ks:ks_pop":53,
    "ks:ks_type":"HABITATION",
    "name:eng_x_preferred":[
        "Nagariya"
    ],
    "wof:name":"Nagariya",
    "wof:placetype":"locality",
    "wof:population":53
},
  "geometry": {"coordinates":[79.36878299999999,26.862302],"type":"Point"}
}