{
  "type": "Feature",
  "properties": {
    "iso:country":"IN",
    "ks:ks_alt_nam":"State FarmColony",
    "ks:ks_name":"State Farmcolony",
    "ks:ks_pop":1392,
    "ks:ks_type":"HABITATION",
    "ks:ks_uagg_main":0,
    "name:eng_x_preferred":[
        "State Farmcolony"
    ],
    "wof:name":"State Farmcolony",
    "wof:placetype":"neighbourhood",
    "wof:population":1392
},
  "geometry": {"coordinates":[88.20424,26.272219],"type":"Point"}
}