{
  "type": "Feature",
  "properties": {
    "gn:admin1_code":"19.0",
    "gn:admin2_code":"570.0",
    "gn:asciiname":"Gundagadde",
    "gn:country_code":"IN",
    "gn:dem":658,
    "gn:feature_class":"P",
    "gn:feature_code":"PPL",
    "gn:name":"Gundagadde",
    "gn:population":0,
    "gn:timezone":"Asia/Kolkata",
    "iso:country":"IN",
    "wof:name":"Gundagadde",
    "wof:placetype":"locality"
},
  "geometry": {"coordinates":[75.26334,13.39359],"type":"Point"}
}