{
  "type": "Feature",
  "properties": {
    "gn:admin1_code":"34",
    "gn:asciiname":"Pratappur",
    "gn:country_code":"IN",
    "gn:dem":58,
    "gn:feature_class":"P",
    "gn:feature_code":"PPL",
    "gn:name":"Prat\u0101ppur",
    "gn:population":0,
    "gn:timezone":"Asia/Kolkata",
    "iso:country":"IN",
    "ks:ks_name":"Partappur",
    "ks:ks_pop":0,
    "ks:ks_type":"VILLAGE",
    "name:eng_x_preferred":[
        "Partappur"
    ],
    "name:eng_x_variant":[
        "Pratappur"
    ],
    "wof:name":"Partappur",
    "wof:placetype":"locality",
    "wof:population":0
},
  "geometry": {"coordinates":[83.867446,25.499023],"type":"Point"}
}