{
  "type": "Feature",
  "properties": {
    "gn:admin1_code":"23.0",
    "gn:admin2_code":"43.0",
    "gn:asciiname":"Jamalpura",
    "gn:country_code":"IN",
    "gn:dem":187,
    "gn:feature_class":"P",
    "gn:feature_code":"PPL",
    "gn:name":"Jam\u0101lpura",
    "gn:population":0,
    "gn:timezone":"Asia/Kolkata",
    "iso:country":"IN",
    "name:und_x_variant":[
        "Jam\u0101lpura",
        "Sapp\u0101nw\u0101la"
    ],
    "wof:name":"Jamalpura",
    "wof:placetype":"neighbourhood"
},
  "geometry": {"coordinates":[74.08201,30.09377],"type":"Point"}
}