{
  "type": "Feature",
  "properties": {
    "iso:country":"IN",
    "ks:ks_name":"Gopalpura",
    "ks:ks_pop":462,
    "ks:ks_type":"VILLAGE",
    "name:eng_x_preferred":[
        "Gopalpura"
    ],
    "wof:name":"Gopalpura",
    "wof:placetype":"locality",
    "wof:population":462
},
  "geometry": {"coordinates":[74.37776700000001,24.013919],"type":"Point"}
}