{
  "type": "Feature",
  "properties": {
    "iso:country":"IN",
    "ks:ks_name":"Muruva",
    "ks:ks_pop":196,
    "ks:ks_type":"HABITATION",
    "name:eng_x_preferred":[
        "Muruva"
    ],
    "wof:name":"Muruva",
    "wof:placetype":"locality",
    "wof:population":196
},
  "geometry": {"coordinates":[75.13991,12.817753],"type":"Point"}
}