{
  "type": "Feature",
  "properties": {
    "iso:country":"IN",
    "ks:ks_name":"Prabhupura",
    "ks:ks_pop":339,
    "ks:ks_type":"VILLAGE",
    "name:eng_x_preferred":[
        "Prabhupura"
    ],
    "wof:name":"Prabhupura",
    "wof:placetype":"locality",
    "wof:population":339
},
  "geometry": {"coordinates":[72.063896,26.412639],"type":"Point"}
}