{
  "type": "Feature",
  "properties": {
    "iso:country":"IN",
    "ks:ks_name":"Saidba",
    "ks:ks_type":"VILLAGE",
    "name:eng_x_preferred":[
        "Saidba"
    ],
    "wof:name":"Saidba",
    "wof:placetype":"locality"
},
  "geometry": {"coordinates":[85.342067,22.644731],"type":"Point"}
}