{
  "type": "Feature",
  "properties": {
    "iso:country":"IN",
    "ks:ks_alt_nam":"Kuntavath thanda",
    "ks:ks_name":"Kuntavath Thanda",
    "ks:ks_pop":260,
    "ks:ks_type":"HABITATION",
    "name:eng_x_preferred":[
        "Kuntavath Thanda"
    ],
    "wof:name":"Kuntavath Thanda",
    "wof:placetype":"locality",
    "wof:population":260
},
  "geometry": {"coordinates":[79.38113,17.631831],"type":"Point"}
}