{
  "type": "Feature",
  "properties": {
    "iso:country":"IN",
    "ks:ks_name":"Sulagoda",
    "ks:ks_pop":15,
    "ks:ks_type":"HABITATION",
    "name:eng_x_preferred":[
        "Sulagoda"
    ],
    "wof:name":"Sulagoda",
    "wof:placetype":"locality",
    "wof:population":15
},
  "geometry": {"coordinates":[75.012517,13.870808],"type":"Point"}
}