{
  "type": "Feature",
  "properties": {
    "gn:admin1_code":"12.0",
    "gn:admin2_code":"1.0",
    "gn:asciiname":"Thail",
    "gn:country_code":"IN",
    "gn:dem":2383,
    "gn:feature_class":"P",
    "gn:feature_code":"PPL",
    "gn:name":"Thail",
    "gn:population":0,
    "gn:timezone":"Asia/Kolkata",
    "iso:country":"IN",
    "wof:name":"Thail",
    "wof:placetype":"locality"
},
  "geometry": {"coordinates":[74.42768000000002,34.68352],"type":"Point"}
}