{
  "type": "Feature",
  "properties": {
    "gn:admin1_code":"35",
    "gn:admin2_code":"423.0",
    "gn:asciiname":"Janori",
    "gn:country_code":"IN",
    "gn:dem":246,
    "gn:feature_class":"P",
    "gn:feature_code":"PPL",
    "gn:name":"Janori",
    "gn:population":0,
    "gn:timezone":"Asia/Kolkata",
    "iso:country":"IN",
    "ks:ks_name":"Janori",
    "ks:ks_pop":984,
    "ks:ks_type":"VILLAGE",
    "name:eng_x_preferred":[
        "Janori"
    ],
    "wof:name":"Janori",
    "wof:placetype":"locality",
    "wof:population":984
},
  "geometry": {"coordinates":[78.290795,25.602019],"type":"Point"}
}