{
  "type": "Feature",
  "properties": {
    "iso:country":"IN",
    "ks:ks_alt_nam":"Baher\u0101dol",
    "ks:ks_name":"Baheradol",
    "ks:ks_type":"VILLAGE",
    "name:eng_x_preferred":[
        "Baheradol"
    ],
    "name:eng_x_variant":[
        "Baher\u0101dol"
    ],
    "wof:name":"Baheradol",
    "wof:placetype":"locality"
},
  "geometry": {"coordinates":[83.19017100000001,23.99897],"type":"Point"}
}