{
  "type": "Feature",
  "properties": {
    "gn:admin1_code":"3.0",
    "gn:admin2_code":"301.0",
    "gn:asciiname":"Banjaguri",
    "gn:country_code":"IN",
    "gn:dem":38,
    "gn:feature_class":"P",
    "gn:feature_code":"PPL",
    "gn:name":"Banjaguri",
    "gn:population":0,
    "gn:timezone":"Asia/Kolkata",
    "iso:country":"IN",
    "wof:name":"Banjaguri",
    "wof:placetype":"locality"
},
  "geometry": {"coordinates":[89.79649000000001,26.34972],"type":"Point"}
}