{
  "type": "Feature",
  "properties": {
    "iso:country":"IN",
    "ks:ks_name":"Banthara",
    "ks:ks_pop":345,
    "ks:ks_type":"HABITATION",
    "name:eng_x_preferred":[
        "Banthara"
    ],
    "wof:name":"Banthara",
    "wof:placetype":"locality",
    "wof:population":345
},
  "geometry": {"coordinates":[79.610163,26.810578],"type":"Point"}
}