{
  "type": "Feature",
  "properties": {
    "iso:country":"IN",
    "ks:ks_name":"Adelpur",
    "ks:ks_pop":656,
    "ks:ks_type":"VILLAGE",
    "ks:ks_uagg_main":0,
    "name:eng_x_preferred":[
        "Adelpur"
    ],
    "wof:name":"Adelpur",
    "wof:placetype":"neighbourhood",
    "wof:population":656
},
  "geometry": {"coordinates":[82.786451,26.453015],"type":"Point"}
}