{
  "type": "Feature",
  "properties": {
    "iso:country":"IN",
    "ks:ks_name":"Banduru",
    "ks:ks_pop":213,
    "ks:ks_type":"VILLAGE",
    "name:eng_x_preferred":[
        "Banduru"
    ],
    "wof:name":"Banduru",
    "wof:placetype":"locality",
    "wof:population":213
},
  "geometry": {"coordinates":[83.751245,19.749055],"type":"Point"}
}