{
  "type": "Feature",
  "properties": {
    "gn:admin1_code":"36.0",
    "gn:admin2_code":"179.0",
    "gn:asciiname":"Piro",
    "gn:country_code":"IN",
    "gn:dem":106,
    "gn:feature_class":"P",
    "gn:feature_code":"PPL",
    "gn:name":"P\u012bro",
    "gn:population":0,
    "gn:timezone":"Asia/Kolkata",
    "iso:country":"IN",
    "name:ceb_x_preferred":[
        "Piro"
    ],
    "name:deu_x_preferred":[
        "Piro"
    ],
    "name:hrv_x_preferred":[
        "Piro"
    ],
    "name:ita_x_preferred":[
        "Piro"
    ],
    "name:spa_x_preferred":[
        "Piro"
    ],
    "name:srp_x_preferred":[
        "Piro"
    ],
    "name:swe_x_preferred":[
        "Piro"
    ],
    "wof:name":"Piro",
    "wof:placetype":"neighbourhood"
},
  "geometry": {"coordinates":[81.9755,26.46663],"type":"Point"}
}