{
  "type": "Feature",
  "properties": {
    "iso:country":"IN",
    "ks:ks_name":"Tapna",
    "ks:ks_pop":1141,
    "ks:ks_type":"VILLAGE",
    "ks:ks_uagg_main":0,
    "name:eng_x_preferred":[
        "Tapna"
    ],
    "wof:name":"Tapna",
    "wof:placetype":"neighbourhood",
    "wof:population":1141
},
  "geometry": {"coordinates":[88.081137,22.421876],"type":"Point"}
}