{
  "type": "Feature",
  "properties": {
    "iso:country":"IN",
    "ks:ks_name":"Kalyanpur",
    "ks:ks_pop":620,
    "ks:ks_type":"VILLAGE",
    "name:eng_x_preferred":[
        "Kalyanpur"
    ],
    "wof:name":"Kalyanpur",
    "wof:placetype":"locality",
    "wof:population":620
},
  "geometry": {"coordinates":[88.74497700000001,23.147606],"type":"Point"}
}