{
  "type": "Feature",
  "properties": {
    "iso:country":"IN",
    "ks:ks_alt_nam":"PAHARTOLI",
    "ks:ks_name":"Pahartoli",
    "ks:ks_pop":180,
    "ks:ks_type":"HABITATION",
    "name:eng_x_preferred":[
        "Pahartoli"
    ],
    "wof:name":"Pahartoli",
    "wof:placetype":"locality",
    "wof:population":180
},
  "geometry": {"coordinates":[83.712193,22.818785],"type":"Point"}
}