{
  "type": "Feature",
  "properties": {
    "iso:country":"IN",
    "ks:ks_name":"Kalapadu Thotalu",
    "ks:ks_pop":34,
    "ks:ks_type":"HABITATION",
    "name:eng_x_preferred":[
        "Kalapadu Thotalu"
    ],
    "wof:name":"Kalapadu Thotalu",
    "wof:placetype":"locality",
    "wof:population":34
},
  "geometry": {"coordinates":[79.59237400000001,13.97829],"type":"Point"}
}