{
  "type": "Feature",
  "properties": {
    "iso:country":"IN",
    "ks:ks_name":"Pasi Purwa",
    "ks:ks_pop":64,
    "ks:ks_type":"HABITATION",
    "ks:ks_uagg_main":0,
    "name:eng_x_preferred":[
        "Pasi Purwa"
    ],
    "wof:name":"Pasi Purwa",
    "wof:placetype":"neighbourhood",
    "wof:population":64
},
  "geometry": {"coordinates":[81.99279,27.542299],"type":"Point"}
}