{
  "type": "Feature",
  "properties": {
    "iso:country":"IN",
    "ks:ks_name":"Belsar",
    "ks:ks_pop":664,
    "ks:ks_type":"VILLAGE",
    "name:eng_x_preferred":[
        "Belsar"
    ],
    "wof:name":"Belsar",
    "wof:placetype":"locality",
    "wof:population":664
},
  "geometry": {"coordinates":[83.350202,23.872989],"type":"Point"}
}