{
  "type": "Feature",
  "properties": {
    "iso:country":"IN",
    "ks:ks_name":"Deorihangaon",
    "ks:ks_pop":2579,
    "ks:ks_type":"HABITATION",
    "name:eng_x_preferred":[
        "Deorihangaon"
    ],
    "wof:name":"Deorihangaon",
    "wof:placetype":"locality",
    "wof:population":2579
},
  "geometry": {"coordinates":[81.739698,24.800868],"type":"Point"}
}