{
  "type": "Feature",
  "properties": {
    "iso:country":"IN",
    "ks:ks_alt_nam":"West Bhanukumari Ward No II",
    "ks:ks_name":"West Bhanukumari Ward No Ii",
    "ks:ks_pop":1485,
    "ks:ks_type":"HABITATION",
    "name:eng_x_preferred":[
        "West Bhanukumari Ward No Ii"
    ],
    "wof:name":"West Bhanukumari Ward No Ii",
    "wof:placetype":"locality",
    "wof:population":1485
},
  "geometry": {"coordinates":[89.684597,26.352139],"type":"Point"}
}