{
  "type": "Feature",
  "properties": {
    "gn:admin1_code":"19.0",
    "gn:admin2_code":"574.0",
    "gn:asciiname":"Samudravalli",
    "gn:country_code":"IN",
    "gn:dem":956,
    "gn:feature_class":"P",
    "gn:feature_code":"PPL",
    "gn:name":"Samudravalli",
    "gn:population":0,
    "gn:timezone":"Asia/Kolkata",
    "iso:country":"IN",
    "wof:name":"Samudravalli",
    "wof:placetype":"locality"
},
  "geometry": {"coordinates":[76.11533,12.95924],"type":"Point"}
}