{
  "type": "Feature",
  "properties": {
    "gn:admin1_code":"11.0",
    "gn:admin2_code":"27.0",
    "gn:asciiname":"Magrugarh",
    "gn:country_code":"IN",
    "gn:dem":2829,
    "gn:feature_class":"P",
    "gn:feature_code":"PPL",
    "gn:name":"Magrugarh",
    "gn:population":0,
    "gn:timezone":"Asia/Kolkata",
    "iso:country":"IN",
    "wof:name":"Magrugarh",
    "wof:placetype":"locality"
},
  "geometry": {"coordinates":[77.24889,31.48296],"type":"Point"}
}