{
  "type": "Feature",
  "properties": {
    "iso:country":"IN",
    "ks:ks_name":"Gangewadi",
    "ks:ks_pop":85,
    "ks:ks_type":"HABITATION",
    "name:eng_x_preferred":[
        "Gangewadi"
    ],
    "wof:name":"Gangewadi",
    "wof:placetype":"locality",
    "wof:population":85
},
  "geometry": {"coordinates":[76.638007,13.570625],"type":"Point"}
}