{
  "type": "Feature",
  "properties": {
    "iso:country":"IN",
    "ks:ks_name":"Gujurisul",
    "ks:ks_pop":115,
    "ks:ks_type":"VILLAGE",
    "name:eng_x_preferred":[
        "Gujurisul"
    ],
    "wof:name":"Gujurisul",
    "wof:placetype":"locality",
    "wof:population":115
},
  "geometry": {"coordinates":[87.207421,21.961154],"type":"Point"}
}