{
  "type": "Feature",
  "properties": {
    "iso:country":"IN",
    "ks:ks_name":"Purunapani",
    "ks:ks_pop":42,
    "ks:ks_type":"VILLAGE",
    "name:eng_x_preferred":[
        "Purunapani"
    ],
    "wof:name":"Purunapani",
    "wof:placetype":"locality",
    "wof:population":42
},
  "geometry": {"coordinates":[82.15973099999999,18.274514],"type":"Point"}
}