{
  "type": "Feature",
  "properties": {
    "iso:country":"IN",
    "ks:ks_name":"Karamtoli",
    "ks:ks_pop":920,
    "ks:ks_type":"VILLAGE",
    "name:eng_x_preferred":[
        "Karamtoli"
    ],
    "wof:name":"Karamtoli",
    "wof:placetype":"locality",
    "wof:population":920
},
  "geometry": {"coordinates":[84.214443,22.510735],"type":"Point"}
}