{
  "type": "Feature",
  "properties": {
    "iso:country":"IN",
    "ks:ks_alt_nam":"Adki tanda",
    "ks:ks_name":"Adki Tanda",
    "ks:ks_pop":151,
    "ks:ks_type":"HABITATION",
    "name:eng_x_preferred":[
        "Adki Tanda"
    ],
    "wof:name":"Adki Tanda",
    "wof:placetype":"locality",
    "wof:population":151
},
  "geometry": {"coordinates":[77.39169800000001,17.133829],"type":"Point"}
}