{
  "type": "Feature",
  "properties": {
    "gn:admin1_code":"34.0",
    "gn:admin2_code":"238.0",
    "gn:asciiname":"Karitanr",
    "gn:country_code":"IN",
    "gn:dem":170,
    "gn:feature_class":"P",
    "gn:feature_code":"PPL",
    "gn:name":"Karit\u0101nr",
    "gn:population":0,
    "gn:timezone":"Asia/Kolkata",
    "iso:country":"IN",
    "ks:ks_alt_nam":"Karit\u0101nr",
    "ks:ks_name":"Karitanr",
    "ks:ks_pop":461,
    "ks:ks_type":"VILLAGE",
    "name:eng_x_preferred":[
        "Karitanr"
    ],
    "name:eng_x_variant":[
        "Karit\u0101nr"
    ],
    "wof:name":"Karitanr",
    "wof:placetype":"locality",
    "wof:population":461
},
  "geometry": {"coordinates":[86.063012,24.790255],"type":"Point"}
}