{
  "type": "Feature",
  "properties": {
    "iso:country":"IN",
    "ks:ks_name":"Tozhi",
    "ks:ks_pop":310,
    "ks:ks_type":"HABITATION",
    "name:eng_x_preferred":[
        "Tozhi"
    ],
    "wof:name":"Tozhi",
    "wof:placetype":"locality",
    "wof:population":310
},
  "geometry": {"coordinates":[79.54905100000001,10.468019],"type":"Point"}
}