{
  "type": "Feature",
  "properties": {
    "iso:country":"IN",
    "ks:ks_name":"Malayappapuram",
    "ks:ks_pop":600,
    "ks:ks_type":"HABITATION",
    "ks:ks_uagg_main":0,
    "name:eng_x_preferred":[
        "Malayappapuram"
    ],
    "wof:name":"Malayappapuram",
    "wof:placetype":"neighbourhood",
    "wof:population":600
},
  "geometry": {"coordinates":[78.192059,10.954156],"type":"Point"}
}