{
  "type": "Feature",
  "properties": {
    "iso:country":"IN",
    "ks:ks_name":"Rachaianapalya",
    "ks:ks_pop":269,
    "ks:ks_type":"HABITATION",
    "name:eng_x_preferred":[
        "Rachaianapalya"
    ],
    "wof:name":"Rachaianapalya",
    "wof:placetype":"locality",
    "wof:population":269
},
  "geometry": {"coordinates":[77.10315199999999,13.639027],"type":"Point"}
}