{
  "type": "Feature",
  "properties": {
    "iso:country":"IN",
    "ks:ks_name":"Paschim Chandpur",
    "ks:ks_pop":670,
    "ks:ks_type":"VILLAGE",
    "name:eng_x_preferred":[
        "Paschim Chandpur"
    ],
    "wof:name":"Paschim Chandpur",
    "wof:placetype":"locality",
    "wof:population":670
},
  "geometry": {"coordinates":[88.275695,22.115916],"type":"Point"}
}