{
  "type": "Feature",
  "properties": {
    "gn:admin1_code":"11",
    "gn:admin2_code":"23.0",
    "gn:asciiname":"Drammah Uparla",
    "gn:country_code":"IN",
    "gn:dem":2252,
    "gn:feature_class":"P",
    "gn:feature_code":"PPL",
    "gn:name":"Drammah Uparla",
    "gn:population":0,
    "gn:timezone":"Asia/Kolkata",
    "iso:country":"IN",
    "wof:name":"Drammah Uparla",
    "wof:placetype":"locality"
},
  "geometry": {"coordinates":[76.23714,32.50908],"type":"Point"}
}