{
  "type": "Feature",
  "properties": {
    "iso:country":"IN",
    "ks:ks_alt_nam":"NOHARI KA PURWA",
    "ks:ks_name":"Nohari Ka Purwa",
    "ks:ks_pop":112,
    "ks:ks_type":"HABITATION",
    "ks:ks_uagg_main":0,
    "name:eng_x_preferred":[
        "Nohari Ka Purwa"
    ],
    "wof:name":"Nohari Ka Purwa",
    "wof:placetype":"neighbourhood",
    "wof:population":112
},
  "geometry": {"coordinates":[81.37139999999999,26.4987],"type":"Point"}
}