{
  "type": "Feature",
  "properties": {
    "iso:country":"IN",
    "ks:ks_name":"Nallimala",
    "ks:ks_pop":150,
    "ks:ks_type":"HABITATION",
    "name:eng_x_preferred":[
        "Nallimala"
    ],
    "wof:name":"Nallimala",
    "wof:placetype":"locality",
    "wof:population":150
},
  "geometry": {"coordinates":[76.98033599999999,9.415388],"type":"Point"}
}