{
  "type": "Feature",
  "properties": {
    "iso:country":"IN",
    "ks:ks_name":"Sulemunde",
    "ks:ks_pop":96,
    "ks:ks_type":"HABITATION",
    "name:eng_x_preferred":[
        "Sulemunde"
    ],
    "wof:name":"Sulemunde",
    "wof:placetype":"locality",
    "wof:population":96
},
  "geometry": {"coordinates":[74.758968,13.568695],"type":"Point"}
}