{
  "type": "Feature",
  "properties": {
    "iso:country":"IN",
    "ks:ks_name":"Balapuram",
    "ks:ks_pop":45,
    "ks:ks_type":"HABITATION",
    "name:eng_x_preferred":[
        "Balapuram"
    ],
    "wof:name":"Balapuram",
    "wof:placetype":"locality",
    "wof:population":45
},
  "geometry": {"coordinates":[79.650507,15.750466],"type":"Point"}
}