{
  "type": "Feature",
  "properties": {
    "iso:country":"IN",
    "ks:ks_name":"Dhanapadar",
    "ks:ks_pop":27,
    "ks:ks_type":"VILLAGE",
    "name:eng_x_preferred":[
        "Dhanapadar"
    ],
    "wof:name":"Dhanapadar",
    "wof:placetype":"locality",
    "wof:population":27
},
  "geometry": {"coordinates":[83.35522,19.593],"type":"Point"}
}