{
  "type": "Feature",
  "properties": {
    "gn:admin1_code":"19.0",
    "gn:admin2_code":"569.0",
    "gn:asciiname":"Chittur",
    "gn:country_code":"IN",
    "gn:dem":22,
    "gn:feature_class":"P",
    "gn:feature_code":"PPL",
    "gn:name":"Chitt\u016br",
    "gn:population":0,
    "gn:timezone":"Asia/Kolkata",
    "iso:country":"IN",
    "name:ben_x_preferred":[
        "\u099a\u09bf\u09a4\u09cd\u09a4\u09c1\u09b0-\u09a5\u09be\u09a5\u09ae\u0999\u09cd\u0997\u09b2\u09ae"
    ],
    "name:bpy_x_preferred":[
        "\u099a\u09bf\u09a4\u09cd\u09a4\u09c1\u09b0-\u09a5\u09be\u09a5\u09ae\u0999\u09cd\u0997\u09b2\u09ae"
    ],
    "name:ita_x_preferred":[
        "Chittur"
    ],
    "name:mal_x_preferred":[
        "\u0d1a\u0d3f\u0d31\u0d4d\u0d31\u0d42\u0d7c"
    ],
    "name:mar_x_preferred":[
        "\u091a\u093f\u0924\u094d\u0924\u0942\u0930"
    ],
    "name:new_x_preferred":[
        "\u091a\u093f\u0924\u094d\u0924\u0941\u0930-\u0925\u093e\u0925\u092e\u0919\u094d\u0917\u0932\u092e"
    ],
    "name:por_x_preferred":[
        "Chittur-Thathamangalam"
    ],
    "name:tam_x_preferred":[
        "\u0b9a\u0bbf\u0bb1\u0bcd\u0bb1\u0bc2\u0bb0\u0bcd"
    ],
    "name:urd_x_preferred":[
        "\u0686\u0679\u0648\u0631"
    ],
    "name:vie_x_preferred":[
        "Chittur-Thathamangalam"
    ],
    "wof:name":"Chittur",
    "wof:placetype":"locality"
},
  "geometry": {"coordinates":[74.78369000000001,13.72827],"type":"Point"}
}