{
  "type": "Feature",
  "properties": {
    "gn:admin1_code":"34.0",
    "gn:admin2_code":"220.0",
    "gn:asciiname":"Goriari",
    "gn:country_code":"IN",
    "gn:dem":50,
    "gn:feature_class":"P",
    "gn:feature_code":"PPL",
    "gn:name":"Gori\u0101ri",
    "gn:population":0,
    "gn:timezone":"Asia/Kolkata",
    "iso:country":"IN",
    "ks:ks_name":"Gorari",
    "ks:ks_pop":48,
    "ks:ks_type":"VILLAGE",
    "name:eng_x_preferred":[
        "Gorari"
    ],
    "name:eng_x_variant":[
        "Goriari"
    ],
    "wof:name":"Gorari",
    "wof:placetype":"locality",
    "wof:population":48
},
  "geometry": {"coordinates":[85.336264,25.601391],"type":"Point"}
}