{
  "type": "Feature",
  "properties": {
    "iso:country":"IN",
    "ks:ks_name":"Pipli Mal",
    "ks:ks_pop":470,
    "ks:ks_type":"HABITATION",
    "name:eng_x_preferred":[
        "Pipli Mal"
    ],
    "wof:name":"Pipli Mal",
    "wof:placetype":"locality",
    "wof:population":470
},
  "geometry": {"coordinates":[75.30716700000001,22.400355],"type":"Point"}
}