{
  "type": "Feature",
  "properties": {
    "iso:country":"IN",
    "ks:ks_name":"Kelemaha",
    "ks:ks_pop":231,
    "ks:ks_type":"VILLAGE",
    "ks:ks_uagg_main":0,
    "name:eng_x_preferred":[
        "Kelemaha"
    ],
    "wof:name":"Kelemaha",
    "wof:placetype":"neighbourhood",
    "wof:population":231
},
  "geometry": {"coordinates":[84.199613,20.11813],"type":"Point"}
}