{
  "type": "Feature",
  "properties": {
    "iso:country":"IN",
    "ks:ks_name":"Dhunaguri Borgaya Deori",
    "ks:ks_pop":344,
    "ks:ks_type":"VILLAGE",
    "ks:ks_uagg_main":0,
    "name:eng_x_preferred":[
        "Dhunaguri Borgaya Deori"
    ],
    "wof:name":"Dhunaguri Borgaya Deori",
    "wof:placetype":"neighbourhood",
    "wof:population":344
},
  "geometry": {"coordinates":[94.662076,27.492961],"type":"Point"}
}