{
  "type": "Feature",
  "properties": {
    "gn:admin1_code":"37.0",
    "gn:admin2_code":"405.0",
    "gn:asciiname":"Sonaidih",
    "gn:country_code":"IN",
    "gn:dem":235,
    "gn:feature_class":"P",
    "gn:feature_code":"PPL",
    "gn:name":"Sonaidih",
    "gn:population":0,
    "gn:timezone":"Asia/Kolkata",
    "iso:country":"IN",
    "wof:name":"Sonaidih",
    "wof:placetype":"locality"
},
  "geometry": {"coordinates":[82.72797,21.87674],"type":"Point"}
}