{
  "type": "Feature",
  "properties": {
    "iso:country":"IN",
    "ks:ks_alt_nam":"katalwadi",
    "ks:ks_name":"Katalwadi",
    "ks:ks_pop":255,
    "ks:ks_type":"HABITATION",
    "name:eng_x_preferred":[
        "Katalwadi"
    ],
    "wof:name":"Katalwadi",
    "wof:placetype":"locality",
    "wof:population":255
},
  "geometry": {"coordinates":[73.55247900000001,16.723544],"type":"Point"}
}