{
  "type": "Feature",
  "properties": {
    "gn:admin1_code":"34.0",
    "gn:admin2_code":"216.0",
    "gn:asciiname":"Simra Nankar",
    "gn:country_code":"IN",
    "gn:dem":64,
    "gn:feature_class":"P",
    "gn:feature_code":"PPL",
    "gn:name":"Simra N\u0101nk\u0101r",
    "gn:population":0,
    "gn:timezone":"Asia/Kolkata",
    "iso:country":"IN",
    "ks:ks_name":"Simra Nankar",
    "ks:ks_pop":610,
    "ks:ks_type":"VILLAGE",
    "ks:ks_uagg_main":0,
    "name:eng_x_preferred":[
        "Simra Nankar"
    ],
    "wof:name":"Simra Nankar",
    "wof:placetype":"neighbourhood",
    "wof:population":610
},
  "geometry": {"coordinates":[84.948322,26.23566],"type":"Point"}
}