{
  "type": "Feature",
  "properties": {
    "iso:country":"IN",
    "ks:ks_name":"Nhaviwasti",
    "ks:ks_pop":36,
    "ks:ks_type":"HABITATION",
    "name:eng_x_preferred":[
        "Nhaviwasti"
    ],
    "wof:name":"Nhaviwasti",
    "wof:placetype":"locality",
    "wof:population":36
},
  "geometry": {"coordinates":[73.620698,17.871198],"type":"Point"}
}