{
  "type": "Feature",
  "properties": {
    "iso:country":"IN",
    "ks:ks_name":"Siddankere",
    "ks:ks_pop":54,
    "ks:ks_type":"HABITATION",
    "name:eng_x_preferred":[
        "Siddankere"
    ],
    "wof:name":"Siddankere",
    "wof:placetype":"locality",
    "wof:population":54
},
  "geometry": {"coordinates":[75.784206,13.600844],"type":"Point"}
}