{
  "type": "Feature",
  "properties": {
    "iso:country":"IN",
    "ks:ks_name":"Mharwali",
    "ks:ks_pop":139,
    "ks:ks_type":"HABITATION",
    "name:eng_x_preferred":[
        "Mharwali"
    ],
    "wof:name":"Mharwali",
    "wof:placetype":"locality",
    "wof:population":139
},
  "geometry": {"coordinates":[73.67108,15.951641],"type":"Point"}
}