{
  "type": "Feature",
  "properties": {
    "gn:admin1_code":"36",
    "gn:admin2_code":"200.0",
    "gn:asciiname":"Gulaldih",
    "gn:country_code":"IN",
    "gn:dem":349,
    "gn:feature_class":"P",
    "gn:feature_code":"PPL",
    "gn:name":"Gul\u0101ld\u012bh",
    "gn:population":0,
    "gn:timezone":"Asia/Kolkata",
    "iso:country":"IN",
    "ks:ks_name":"Gulalidih",
    "ks:ks_pop":388,
    "ks:ks_type":"HABITATION",
    "name:eng_x_preferred":[
        "Gulalidih"
    ],
    "name:eng_x_variant":[
        "Gulaldih"
    ],
    "wof:name":"Gulalidih",
    "wof:placetype":"locality",
    "wof:population":388
},
  "geometry": {"coordinates":[82.825209,24.282642],"type":"Point"}
}