{
  "type": "Feature",
  "properties": {
    "iso:country":"IN",
    "ks:ks_name":"Gobardhan Chak",
    "ks:ks_type":"VILLAGE",
    "name:eng_x_preferred":[
        "Gobardhan Chak"
    ],
    "wof:name":"Gobardhan Chak",
    "wof:placetype":"locality"
},
  "geometry": {"coordinates":[83.61119600000001,25.125758],"type":"Point"}
}