{
  "type": "Feature",
  "properties": {
    "iso:country":"IN",
    "ks:ks_name":"Baudhawadi",
    "ks:ks_pop":503,
    "ks:ks_type":"HABITATION",
    "name:eng_x_preferred":[
        "Baudhawadi"
    ],
    "wof:name":"Baudhawadi",
    "wof:placetype":"locality",
    "wof:population":503
},
  "geometry": {"coordinates":[73.53,17.42],"type":"Point"}
}