{
  "type": "Feature",
  "properties": {
    "iso:country":"IN",
    "ks:ks_name":"Chapra Megh Rai",
    "ks:ks_pop":7929,
    "ks:ks_type":"VILLAGE",
    "name:eng_x_preferred":[
        "Chapra Megh Rai"
    ],
    "wof:name":"Chapra Megh Rai",
    "wof:placetype":"locality",
    "wof:population":7929
},
  "geometry": {"coordinates":[85.474965,26.062415],"type":"Point"}
}