{
  "type": "Feature",
  "properties": {
    "iso:country":"IN",
    "ks:ks_name":"Kaiandiha",
    "ks:ks_pop":59,
    "ks:ks_type":"HABITATION",
    "name:eng_x_preferred":[
        "Kaiandiha"
    ],
    "wof:name":"Kaiandiha",
    "wof:placetype":"locality",
    "wof:population":59
},
  "geometry": {"coordinates":[84.761049,20.323058],"type":"Point"}
}