{
  "type": "Feature",
  "properties": {
    "gn:admin1_code":"36",
    "gn:admin2_code":"132.0",
    "gn:asciiname":"Sultanpur Datauli",
    "gn:country_code":"IN",
    "gn:dem":283,
    "gn:feature_class":"P",
    "gn:feature_code":"PPL",
    "gn:name":"Sult\u0101npur Datauli",
    "gn:population":0,
    "gn:timezone":"Asia/Kolkata",
    "iso:country":"IN",
    "name:und_x_variant":[
        "Sult\u0101npur Datauli",
        "R\u0101nghar"
    ],
    "wof:name":"Sultanpur Datauli",
    "wof:placetype":"neighbourhood"
},
  "geometry": {"coordinates":[77.52419,30.02864],"type":"Point"}
}