{
  "type": "Feature",
  "properties": {
    "gn:admin1_code":"36",
    "gn:admin2_code":"136.0",
    "gn:asciiname":"Faizganj",
    "gn:country_code":"IN",
    "gn:dem":194,
    "gn:feature_class":"P",
    "gn:feature_code":"PPL",
    "gn:name":"Faizganj",
    "gn:population":0,
    "gn:timezone":"Asia/Kolkata",
    "iso:country":"IN",
    "ks:ks_name":"Faizganj",
    "ks:ks_type":"VILLAGE",
    "name:bpy_x_preferred":[
        "\u09ab\u09be\u0987\u099c\u0997\u099e\u09cd\u099c"
    ],
    "name:bul_x_preferred":[
        "\u0424\u0430\u0438\u0437\u0433\u0430\u043d"
    ],
    "name:eng_x_preferred":[
        "Faizganj"
    ],
    "name:fas_x_preferred":[
        "\u0641\u06cc\u0636\u200c\u06af\u0646\u062c"
    ],
    "name:ita_x_preferred":[
        "Faizganj"
    ],
    "name:msa_x_preferred":[
        "Faizganj"
    ],
    "name:new_x_preferred":[
        "\u092b\u0948\u091c\u0917\u091e\u094d\u091c"
    ],
    "name:nld_x_preferred":[
        "Faizganj"
    ],
    "name:pol_x_preferred":[
        "Faizganj"
    ],
    "name:por_x_preferred":[
        "Faizganj"
    ],
    "name:urd_x_preferred":[
        "\u0641\u06cc\u0636 \u06af\u0646\u062c"
    ],
    "name:vie_x_preferred":[
        "Faizganj"
    ],
    "name:zho_x_preferred":[
        "\u6cd5\u4f0a\u5179\u7518\u6770"
    ],
    "wof:name":"Faizganj",
    "wof:placetype":"locality"
},
  "geometry": {"coordinates":[78.99833,28.876645],"type":"Point"}
}