{
  "type": "Feature",
  "properties": {
    "iso:country":"IN",
    "ks:ks_name":"Ambav",
    "ks:ks_pop":4344,
    "ks:ks_type":"VILLAGE",
    "ks:ks_uagg_main":0,
    "name:eng_x_preferred":[
        "Ambav"
    ],
    "wof:name":"Ambav",
    "wof:placetype":"neighbourhood",
    "wof:population":4344
},
  "geometry": {"coordinates":[72.98926,22.41813],"type":"Point"}
}