{
  "type": "Feature",
  "properties": {
    "gn:admin1_code":"16",
    "gn:admin2_code":"511.0",
    "gn:asciiname":"Tembhi",
    "gn:country_code":"IN",
    "gn:dem":346,
    "gn:feature_class":"P",
    "gn:feature_code":"PPL",
    "gn:name":"Tembhi",
    "gn:population":0,
    "gn:timezone":"Asia/Kolkata",
    "iso:country":"IN",
    "wof:name":"Tembhi",
    "wof:placetype":"locality"
},
  "geometry": {"coordinates":[78.20836,19.77497],"type":"Point"}
}