{
  "type": "Feature",
  "properties": {
    "iso:country":"IN",
    "ks:ks_alt_nam":"S\u0101rum\u0101ha",
    "ks:ks_name":"Sarumaha",
    "ks:ks_pop":765,
    "ks:ks_type":"VILLAGE",
    "name:eng_x_preferred":[
        "Sarumaha"
    ],
    "name:eng_x_variant":[
        "S\u0101rum\u0101ha"
    ],
    "wof:name":"Sarumaha",
    "wof:placetype":"locality",
    "wof:population":765
},
  "geometry": {"coordinates":[84.214753,20.256203],"type":"Point"}
}