{
  "type": "Feature",
  "properties": {
    "gn:admin1_code":"37.0",
    "gn:admin2_code":"417.0",
    "gn:asciiname":"Korinjed",
    "gn:country_code":"IN",
    "gn:dem":317,
    "gn:feature_class":"P",
    "gn:feature_code":"PPL",
    "gn:name":"Kor\u012bnjed",
    "gn:population":0,
    "gn:timezone":"Asia/Kolkata",
    "iso:country":"IN",
    "ks:ks_alt_nam":"Kor\u012bnjed",
    "ks:ks_name":"Korinjed",
    "ks:ks_type":"VILLAGE",
    "name:eng_x_preferred":[
        "Korinjed"
    ],
    "name:eng_x_variant":[
        "Kor\u012bnjed"
    ],
    "wof:name":"Korinjed",
    "wof:placetype":"locality"
},
  "geometry": {"coordinates":[80.576729,18.89341],"type":"Point"}
}