{
  "type": "Feature",
  "properties": {
    "gn:admin1_code":"24.0",
    "gn:admin2_code":"128.0",
    "gn:asciiname":"Sindni",
    "gn:country_code":"IN",
    "gn:dem":302,
    "gn:feature_class":"P",
    "gn:feature_code":"PPL",
    "gn:name":"S\u012bndni",
    "gn:population":0,
    "gn:timezone":"Asia/Kolkata",
    "iso:country":"IN",
    "wof:name":"Sindni",
    "wof:placetype":"neighbourhood"
},
  "geometry": {"coordinates":[76.70582,24.79136],"type":"Point"}
}