{
  "type": "Feature",
  "properties": {
    "iso:country":"IN",
    "ks:ks_name":"Helna",
    "ks:ks_pop":608,
    "ks:ks_type":"VILLAGE",
    "name:eng_x_preferred":[
        "Helna"
    ],
    "wof:name":"Helna",
    "wof:placetype":"locality",
    "wof:population":608
},
  "geometry": {"coordinates":[87.00762400000001,23.185896],"type":"Point"}
}