{
  "type": "Feature",
  "properties": {
    "iso:country":"IN",
    "ks:ks_name":"Deulwadi",
    "ks:ks_pop":39,
    "ks:ks_type":"HABITATION",
    "name:eng_x_preferred":[
        "Deulwadi"
    ],
    "wof:name":"Deulwadi",
    "wof:placetype":"locality",
    "wof:population":39
},
  "geometry": {"coordinates":[73.172406,17.656389],"type":"Point"}
}