{
  "type": "Feature",
  "properties": {
    "gn:admin1_code":"19",
    "gn:admin2_code":"563.0",
    "gn:asciiname":"Amboli",
    "gn:country_code":"IN",
    "gn:dem":535,
    "gn:feature_class":"P",
    "gn:feature_code":"PPL",
    "gn:name":"Amboli",
    "gn:population":0,
    "gn:timezone":"Asia/Kolkata",
    "iso:country":"IN",
    "ks:ks_name":"Ambolli",
    "ks:ks_pop":41,
    "ks:ks_type":"HABITATION",
    "name:eng_x_preferred":[
        "Ambolli"
    ],
    "name:eng_x_variant":[
        "Amboli"
    ],
    "wof:name":"Ambolli",
    "wof:placetype":"locality",
    "wof:population":41
},
  "geometry": {"coordinates":[74.763378,14.926896],"type":"Point"}
}