{
  "type": "Feature",
  "properties": {
    "gn:admin1_code":"40",
    "gn:admin2_code":"541.0",
    "gn:asciiname":"Takkellapadu",
    "gn:country_code":"IN",
    "gn:dem":62,
    "gn:feature_class":"P",
    "gn:feature_code":"PPL",
    "gn:name":"Takkellap\u0101du",
    "gn:population":0,
    "gn:timezone":"Asia/Kolkata",
    "iso:country":"IN",
    "wof:name":"Takkellapadu",
    "wof:placetype":"locality"
},
  "geometry": {"coordinates":[80.45688,16.88141],"type":"Point"}
}