{
  "type": "Feature",
  "properties": {
    "iso:country":"IN",
    "ks:ks_name":"Ramad Nadmelana",
    "ks:ks_pop":319,
    "ks:ks_type":"HABITATION",
    "name:eng_x_preferred":[
        "Ramad Nadmelana"
    ],
    "wof:name":"Ramad Nadmelana",
    "wof:placetype":"locality",
    "wof:population":319
},
  "geometry": {"coordinates":[73.617763,23.567122],"type":"Point"}
}