{
  "type": "Feature",
  "properties": {
    "gn:admin1_code":"36",
    "gn:admin2_code":"148.0",
    "gn:asciiname":"Amarpur",
    "gn:country_code":"IN",
    "gn:dem":159,
    "gn:feature_class":"P",
    "gn:feature_code":"PPL",
    "gn:name":"Amarpur",
    "gn:population":0,
    "gn:timezone":"Asia/Kolkata",
    "iso:country":"IN",
    "name:ceb_x_preferred":[
        "Amarpur"
    ],
    "name:fra_x_preferred":[
        "Amarpur"
    ],
    "name:new_x_preferred":[
        "\u0905\u092e\u0930\u092a\u0941\u0930 \u0917\u093e\u0935\u093f\u0938"
    ],
    "name:nld_x_preferred":[
        "Amarpur"
    ],
    "name:pol_x_preferred":[
        "Amarpur"
    ],
    "name:swe_x_preferred":[
        "Amarpur"
    ],
    "wof:name":"Amarpur",
    "wof:placetype":"locality"
},
  "geometry": {"coordinates":[78.88648000000001,27.10352],"type":"Point"}
}