{
  "type": "Feature",
  "properties": {
    "gn:admin1_code":"09",
    "gn:admin2_code":"475.0",
    "gn:asciiname":"Palali",
    "gn:country_code":"IN",
    "gn:dem":18,
    "gn:feature_class":"P",
    "gn:feature_code":"PPL",
    "gn:name":"Pal\u0101li",
    "gn:population":0,
    "gn:timezone":"Asia/Kolkata",
    "iso:country":"IN",
    "wof:name":"Palali",
    "wof:placetype":"locality"
},
  "geometry": {"coordinates":[71.97046999999998,22.70388],"type":"Point"}
}