{
  "type": "Feature",
  "properties": {
    "iso:country":"IN",
    "ks:ks_name":"Gugli",
    "ks:ks_pop":6,
    "ks:ks_type":"VILLAGE",
    "name:eng_x_preferred":[
        "Gugli"
    ],
    "wof:name":"Gugli",
    "wof:placetype":"locality",
    "wof:population":6
},
  "geometry": {"coordinates":[78.61344800000001,30.266273],"type":"Point"}
}