{
  "type": "Feature",
  "properties": {
    "gn:admin1_code":"23.0",
    "gn:admin2_code":"37.0",
    "gn:asciiname":"Motipur",
    "gn:country_code":"IN",
    "gn:dem":217,
    "gn:feature_class":"P",
    "gn:feature_code":"PPL",
    "gn:name":"Motipur",
    "gn:population":0,
    "gn:timezone":"Asia/Kolkata",
    "iso:country":"IN",
    "name:fra_x_preferred":[
        "Motipur"
    ],
    "name:pol_x_preferred":[
        "Motipur"
    ],
    "wof:name":"Motipur",
    "wof:placetype":"locality"
},
  "geometry": {"coordinates":[75.27968,31.18216],"type":"Point"}
}