{
  "type": "Feature",
  "properties": {
    "gn:admin1_code":"10.0",
    "gn:admin2_code":"73.0",
    "gn:asciiname":"Kharak",
    "gn:country_code":"IN",
    "gn:dem":237,
    "gn:feature_class":"P",
    "gn:feature_code":"PPL",
    "gn:name":"Kharak",
    "gn:population":0,
    "gn:timezone":"Asia/Kolkata",
    "iso:country":"IN",
    "wof:name":"Kharak",
    "wof:placetype":"locality"
},
  "geometry": {"coordinates":[76.21526999999998,29.9009],"type":"Point"}
}