{
  "type": "Feature",
  "properties": {
    "gn:admin1_code":"36",
    "gn:admin2_code":"200.0",
    "gn:asciiname":"Naugain",
    "gn:country_code":"IN",
    "gn:dem":295,
    "gn:feature_class":"P",
    "gn:feature_code":"PPL",
    "gn:name":"Nauga\u012bn",
    "gn:population":0,
    "gn:timezone":"Asia/Kolkata",
    "iso:country":"IN",
    "ks:ks_name":"Naugai",
    "ks:ks_pop":597,
    "ks:ks_type":"VILLAGE",
    "name:eng_x_preferred":[
        "Naugai"
    ],
    "name:eng_x_variant":[
        "Naugain"
    ],
    "wof:name":"Naugai",
    "wof:placetype":"locality",
    "wof:population":597
},
  "geometry": {"coordinates":[82.75192,24.75446],"type":"Point"}
}