{
  "type": "Feature",
  "properties": {
    "gn:admin1_code":"35",
    "gn:admin2_code":"425.0",
    "gn:asciiname":"Baraichkhera",
    "gn:country_code":"IN",
    "gn:dem":274,
    "gn:feature_class":"P",
    "gn:feature_code":"PPL",
    "gn:name":"Bar\u0101ichkhera",
    "gn:population":0,
    "gn:timezone":"Asia/Kolkata",
    "iso:country":"IN",
    "ks:ks_name":"Barayach Khera",
    "ks:ks_pop":1097,
    "ks:ks_type":"VILLAGE",
    "ks:ks_uagg_main":0,
    "name:eng_x_preferred":[
        "Barayach Khera"
    ],
    "wof:name":"Barayach Khera",
    "wof:placetype":"neighbourhood",
    "wof:population":1097
},
  "geometry": {"coordinates":[79.697487,24.899039],"type":"Point"}
}