{
  "type": "Feature",
  "properties": {
    "iso:country":"IN",
    "ks:ks_name":"Nallanveetupatti",
    "ks:ks_pop":105,
    "ks:ks_type":"HABITATION",
    "name:eng_x_preferred":[
        "Nallanveetupatti"
    ],
    "wof:name":"Nallanveetupatti",
    "wof:placetype":"locality",
    "wof:population":105
},
  "geometry": {"coordinates":[78.821124,12.969508],"type":"Point"}
}