{
  "type": "Feature",
  "properties": {
    "gn:admin1_code":"28.0",
    "gn:admin2_code":"334.0",
    "gn:asciiname":"Madnapur",
    "gn:country_code":"IN",
    "gn:dem":28,
    "gn:feature_class":"P",
    "gn:feature_code":"PPL",
    "gn:name":"Madn\u0101pur",
    "gn:population":0,
    "gn:timezone":"Asia/Kolkata",
    "iso:country":"IN",
    "name:urd_x_preferred":[
        "\u0645\u062f\u0646\u0627\u067e\u0648\u0631"
    ],
    "wof:name":"Madnapur",
    "wof:placetype":"locality"
},
  "geometry": {"coordinates":[87.93200999999998,24.50845],"type":"Point"}
}