{
  "type": "Feature",
  "properties": {
    "gn:admin1_code":"2.0",
    "gn:admin2_code":"549.0",
    "gn:asciiname":"Velamvaripalle",
    "gn:country_code":"IN",
    "gn:dem":121,
    "gn:feature_class":"P",
    "gn:feature_code":"PPL",
    "gn:name":"Velamv\u0101ripalle",
    "gn:population":0,
    "gn:timezone":"Asia/Kolkata",
    "iso:country":"IN",
    "ks:ks_name":"Vellamvaripalli",
    "ks:ks_pop":196,
    "ks:ks_type":"HABITATION",
    "name:eng_x_preferred":[
        "Vellamvaripalli"
    ],
    "name:eng_x_variant":[
        "Velamvaripalle"
    ],
    "wof:name":"Vellamvaripalli",
    "wof:placetype":"locality",
    "wof:population":196
},
  "geometry": {"coordinates":[79.381491,15.256426],"type":"Point"}
}