{
  "type": "Feature",
  "properties": {
    "iso:country":"IN",
    "ks:ks_name":"Shib Pally",
    "ks:ks_pop":1456,
    "ks:ks_type":"HABITATION",
    "name:eng_x_preferred":[
        "Shib Pally"
    ],
    "wof:name":"Shib Pally",
    "wof:placetype":"locality",
    "wof:population":1456
},
  "geometry": {"coordinates":[88.46659099999999,21.871058],"type":"Point"}
}