{
  "type": "Feature",
  "properties": {
    "gn:admin1_code":"36",
    "gn:admin2_code":"188.0",
    "gn:asciiname":"Bath Buzurg",
    "gn:country_code":"IN",
    "gn:dem":80,
    "gn:feature_class":"P",
    "gn:feature_code":"PPL",
    "gn:name":"B\u0101th Buzurg",
    "gn:population":0,
    "gn:timezone":"Asia/Kolkata",
    "iso:country":"IN",
    "ks:ks_name":"Bath Bujurg",
    "ks:ks_pop":1188,
    "ks:ks_type":"VILLAGE",
    "ks:ks_uagg_main":0,
    "name:eng_x_preferred":[
        "Bath Bujurg"
    ],
    "wof:name":"Bath Bujurg",
    "wof:placetype":"neighbourhood",
    "wof:population":1188
},
  "geometry": {"coordinates":[83.30742100000001,26.429133],"type":"Point"}
}