{
  "type": "Feature",
  "properties": {
    "gn:country":"IN",
    "gn:fcode":"PPL",
    "gn:pop":16468,
    "iso:country":"IN",
    "name:bpy_x_preferred":[
        "\u09a5\u09cb\u09a8\u09a1\u09bc\u09bf"
    ],
    "name:chi_x_preferred":[
        "\u901a\u8fea"
    ],
    "name:dut_x_preferred":[
        "Thondi"
    ],
    "name:eng_x_preferred":[
        "Thondi"
    ],
    "name:fre_x_preferred":[
        "Thondi"
    ],
    "name:ita_x_preferred":[
        "Thondi"
    ],
    "name:may_x_preferred":[
        "Thondi"
    ],
    "name:nan_x_preferred":[
        "Thondi"
    ],
    "name:por_x_preferred":[
        "Thondi"
    ],
    "name:tam_x_preferred":[
        "\u0ba4\u0bca\u0ba3\u0bcd\u0b9f\u0bbf"
    ],
    "name:vie_x_preferred":[
        "Thondi"
    ],
    "qs:name":"Thondi",
    "qs:name_adm0":"India",
    "qs:name_adm1":"Tamil Nadu",
    "qs:photos_9k":1,
    "qs:photos_9r":1,
    "qs:photos_all":2,
    "qs:photos_sr":0,
    "qs:placetype":"Town",
    "qs:pop_sr":"6",
    "wd:wordcount":161,
    "wof:name":"Thondi",
    "wof:placetype":"locality",
    "wof:population":16468
},
  "geometry": {"coordinates":[79.01774,9.74172],"type":"Point"}
}