{
  "type": "Feature",
  "properties": {
    "iso:country":"IN",
    "ks:ks_alt_nam":"MUSALMAN TOLA",
    "ks:ks_name":"Musalman Tola",
    "ks:ks_pop":126,
    "ks:ks_type":"HABITATION",
    "name:eng_x_preferred":[
        "Musalman Tola"
    ],
    "wof:name":"Musalman Tola",
    "wof:placetype":"locality",
    "wof:population":126
},
  "geometry": {"coordinates":[87.925612,26.299105],"type":"Point"}
}