{
  "type": "Feature",
  "properties": {
    "iso:country":"IN",
    "ks:ks_name":"Gular Baga Urf Kushum Bathua",
    "ks:ks_pop":493,
    "ks:ks_type":"VILLAGE",
    "ks:ks_uagg_main":0,
    "name:eng_x_preferred":[
        "Gular Baga Urf Kushum Bathua"
    ],
    "wof:name":"Gular Baga Urf Kushum Bathua",
    "wof:placetype":"neighbourhood",
    "wof:population":493
},
  "geometry": {"coordinates":[84.210117,26.460698],"type":"Point"}
}