{
  "type": "Feature",
  "properties": {
    "iso:country":"IN",
    "ks:ks_name":"Manipur Bhagi",
    "ks:ks_pop":973,
    "ks:ks_type":"VILLAGE",
    "name:eng_x_preferred":[
        "Manipur Bhagi"
    ],
    "wof:name":"Manipur Bhagi",
    "wof:placetype":"locality",
    "wof:population":973
},
  "geometry": {"coordinates":[85.805042,25.875061],"type":"Point"}
}