{
  "type": "Feature",
  "properties": {
    "iso:country":"IN",
    "ks:ks_name":"Dhilwabad",
    "ks:ks_pop":15,
    "ks:ks_type":"HABITATION",
    "name:eng_x_preferred":[
        "Dhilwabad"
    ],
    "wof:name":"Dhilwabad",
    "wof:placetype":"locality",
    "wof:population":15
},
  "geometry": {"coordinates":[85.319277,24.383665],"type":"Point"}
}