{
  "type": "Feature",
  "properties": {
    "iso:country":"IN",
    "ks:ks_name":"Hindu Purwa",
    "ks:ks_pop":150,
    "ks:ks_type":"HABITATION",
    "name:eng_x_preferred":[
        "Hindu Purwa"
    ],
    "wof:name":"Hindu Purwa",
    "wof:placetype":"locality",
    "wof:population":150
},
  "geometry": {"coordinates":[79.61554599999999,26.811806],"type":"Point"}
}