{
  "type": "Feature",
  "properties": {
    "iso:country":"IN",
    "ks:ks_name":"Kita Nauakura",
    "ks:ks_pop":513,
    "ks:ks_type":"VILLAGE",
    "name:eng_x_preferred":[
        "Kita Nauakura"
    ],
    "wof:name":"Kita Nauakura",
    "wof:placetype":"locality",
    "wof:population":513
},
  "geometry": {"coordinates":[86.36260799999999,24.840093],"type":"Point"}
}