{
  "type": "Feature",
  "properties": {
    "iso:country":"IN",
    "ks:ks_alt_nam":"Nagli S\u0101kpur",
    "ks:ks_name":"Nagli Sakpur",
    "ks:ks_type":"VILLAGE",
    "ks:ks_uagg_main":0,
    "name:eng_x_preferred":[
        "Nagli Sakpur"
    ],
    "name:eng_x_variant":[
        "Nagli S\u0101kpur"
    ],
    "wof:name":"Nagli Sakpur",
    "wof:placetype":"neighbourhood"
},
  "geometry": {"coordinates":[77.376621,28.501662],"type":"Point"}
}