{
  "type": "Feature",
  "properties": {
    "iso:country":"IN",
    "ks:ks_name":"Chainpur",
    "ks:ks_pop":217,
    "ks:ks_type":"HABITATION",
    "name:eng_x_preferred":[
        "Chainpur"
    ],
    "wof:name":"Chainpur",
    "wof:placetype":"locality",
    "wof:population":217
},
  "geometry": {"coordinates":[84.830389,23.094013],"type":"Point"}
}