{
  "type": "Feature",
  "properties": {
    "iso:country":"IN",
    "ks:ks_alt_nam":"Thellabanda thanda",
    "ks:ks_name":"Thellabanda Thanda",
    "ks:ks_pop":140,
    "ks:ks_type":"HABITATION",
    "ks:ks_uagg_main":0,
    "name:eng_x_preferred":[
        "Thellabanda Thanda"
    ],
    "wof:name":"Thellabanda Thanda",
    "wof:placetype":"neighbourhood",
    "wof:population":140
},
  "geometry": {"coordinates":[80.06281300000001,17.442539],"type":"Point"}
}