{
  "type": "Feature",
  "properties": {
    "gn:admin1_code":"35.0",
    "gn:admin2_code":"431.0",
    "gn:asciiname":"Lahangi",
    "gn:country_code":"IN",
    "gn:dem":489,
    "gn:feature_class":"P",
    "gn:feature_code":"PPL",
    "gn:name":"Lah\u0101ngi",
    "gn:population":0,
    "gn:timezone":"Asia/Kolkata",
    "iso:country":"IN",
    "wof:name":"Lahangi",
    "wof:placetype":"locality"
},
  "geometry": {"coordinates":[80.88351,23.33966],"type":"Point"}
}