{
  "type": "Feature",
  "properties": {
    "iso:country":"IN",
    "ks:ks_name":"Puratbomnalli",
    "ks:ks_pop":16,
    "ks:ks_type":"HABITATION",
    "name:eng_x_preferred":[
        "Puratbomnalli"
    ],
    "wof:name":"Puratbomnalli",
    "wof:placetype":"locality",
    "wof:population":16
},
  "geometry": {"coordinates":[74.91055299999999,14.874779],"type":"Point"}
}