{
  "type": "Feature",
  "properties": {
    "gn:admin1_code":"35.0",
    "gn:admin2_code":"455.0",
    "gn:asciiname":"Sundrehi",
    "gn:country_code":"IN",
    "gn:dem":683,
    "gn:feature_class":"P",
    "gn:feature_code":"PPL",
    "gn:name":"Sundrehi",
    "gn:population":0,
    "gn:timezone":"Asia/Kolkata",
    "iso:country":"IN",
    "wof:name":"Sundrehi",
    "wof:placetype":"locality"
},
  "geometry": {"coordinates":[78.6151,22.06699],"type":"Point"}
}