{
  "type": "Feature",
  "properties": {
    "gn:country":"IN",
    "gn:fcode":"PPL",
    "gn:population":0,
    "iso:country":"IN",
    "name:ara_x_preferred":[
        "\u064a\u0648\u062a\u0627\u0646"
    ],
    "name:ben_bn_x_preferred":[
        "\u0989\u099f\u09be\u09a8"
    ],
    "name:ben_in_x_preferred":[
        "\u0989\u099f\u09be\u09a8"
    ],
    "name:eng_x_preferred":[
        "Utan"
    ],
    "name:guj_x_preferred":[
        "\u0a89\u0aa4\u0abe\u0aa8"
    ],
    "name:hin_x_preferred":[
        "\u0909\u091f\u0928"
    ],
    "name:kan_x_preferred":[
        "\u0c89\u0ca4\u0ca8\u0ccd"
    ],
    "name:mal_x_preferred":[
        "\u0d2f\u0d42\u0d1f\u0d4d\u0d1f\u0d3e\u0d7b"
    ],
    "name:mar_x_preferred":[
        "\u092f\u0941\u091f\u093e\u0928"
    ],
    "name:pan_x_preferred":[
        "\u0a09\u0a24\u0a3e\u0a28"
    ],
    "name:tam_x_preferred":[
        "\u0b89\u0b9f\u0bbe\u0ba9\u0bcd"
    ],
    "name:tel_x_preferred":[
        "\u0c09\u0c1f\u0c3e\u0c28\u0c4d"
    ],
    "name:und_x_variant":[
        "Uttan"
    ],
    "name:urd_x_preferred":[
        "\u0627\u0648\u0679\u0627\u0646"
    ],
    "qs:name":"Utan",
    "qs:name_adm0":"India",
    "qs:name_adm1":"Maharashtra",
    "qs:photos":113,
    "qs:photos_1k":23,
    "qs:photos_9k":1,
    "qs:photos_9r":3,
    "qs:photos_all":113,
    "qs:photos_sr":3,
    "qs:placetype":"Suburb",
    "qs:pop_sr":"0",
    "wd:wordcount":200,
    "wof:name":"Utan",
    "wof:placetype":"neighbourhood",
    "wof:population":0
},
  "geometry": {"coordinates":[72.78572,19.28367],"type":"Point"}
}