{
  "type": "Feature",
  "properties": {
    "gn:admin1_code":"35.0",
    "gn:admin2_code":"453.0",
    "gn:asciiname":"Pindrukhi",
    "gn:country_code":"IN",
    "gn:dem":709,
    "gn:feature_class":"P",
    "gn:feature_code":"PPL",
    "gn:name":"Pindrukh\u012b",
    "gn:population":0,
    "gn:timezone":"Asia/Kolkata",
    "iso:country":"IN",
    "wof:name":"Pindrukhi",
    "wof:placetype":"locality"
},
  "geometry": {"coordinates":[80.93115999999998,22.82269],"type":"Point"}
}