{
  "type": "Feature",
  "properties": {
    "iso:country":"IN",
    "ks:ks_name":"Thar Bhogi",
    "ks:ks_pop":95,
    "ks:ks_type":"HABITATION",
    "name:eng_x_preferred":[
        "Thar Bhogi"
    ],
    "wof:name":"Thar Bhogi",
    "wof:placetype":"locality",
    "wof:population":95
},
  "geometry": {"coordinates":[78.66591200000001,26.925879],"type":"Point"}
}