{
  "type": "Feature",
  "properties": {
    "iso:country":"IN",
    "ks:ks_name":"Durgammaputtuga",
    "ks:ks_pop":241,
    "ks:ks_type":"HABITATION",
    "name:eng_x_preferred":[
        "Durgammaputtuga"
    ],
    "wof:name":"Durgammaputtuga",
    "wof:placetype":"locality",
    "wof:population":241
},
  "geometry": {"coordinates":[84.712172,19.045568],"type":"Point"}
}