{
  "type": "Feature",
  "properties": {
    "iso:country":"IN",
    "ks:ks_name":"Golai Gaon No.3",
    "ks:ks_pop":463,
    "ks:ks_type":"VILLAGE",
    "ks:ks_uagg_main":0,
    "name:eng_x_preferred":[
        "Golai Gaon No.3"
    ],
    "wof:name":"Golai Gaon No.3",
    "wof:placetype":"neighbourhood",
    "wof:population":463
},
  "geometry": {"coordinates":[95.645432,27.374407],"type":"Point"}
}