{
  "type": "Feature",
  "properties": {
    "iso:country":"IN",
    "ks:ks_name":"Sankarmarui",
    "ks:ks_pop":2219,
    "ks:ks_type":"VILLAGE",
    "name:eng_x_preferred":[
        "Sankarmarui"
    ],
    "wof:name":"Sankarmarui",
    "wof:placetype":"locality",
    "wof:population":2219
},
  "geometry": {"coordinates":[88.079615,23.9093],"type":"Point"}
}