{
  "type": "Feature",
  "properties": {
    "iso:country":"IN",
    "ks:ks_name":"Kohalaguda",
    "ks:ks_pop":182,
    "ks:ks_type":"HABITATION",
    "name:eng_x_preferred":[
        "Kohalaguda"
    ],
    "wof:name":"Kohalaguda",
    "wof:placetype":"locality",
    "wof:population":182
},
  "geometry": {"coordinates":[81.743228,18.106117],"type":"Point"}
}