{
  "type": "Feature",
  "properties": {
    "iso:country":"IN",
    "ks:ks_name":"Ghati Falia",
    "ks:ks_pop":639,
    "ks:ks_type":"HABITATION",
    "name:eng_x_preferred":[
        "Ghati Falia"
    ],
    "wof:name":"Ghati Falia",
    "wof:placetype":"locality",
    "wof:population":639
},
  "geometry": {"coordinates":[73.99297199999999,22.695194],"type":"Point"}
}