{
  "type": "Feature",
  "properties": {
    "iso:country":"IN",
    "ks:ks_name":"Badkuwa",
    "ks:ks_pop":409,
    "ks:ks_type":"VILLAGE",
    "name:eng_x_preferred":[
        "Badkuwa"
    ],
    "wof:name":"Badkuwa",
    "wof:placetype":"locality",
    "wof:population":409
},
  "geometry": {"coordinates":[74.57635000000001,22.771996],"type":"Point"}
}