{
  "type": "Feature",
  "properties": {
    "iso:country":"IN",
    "ks:ks_name":"Chura Khark Khet",
    "ks:ks_pop":73,
    "ks:ks_type":"VILLAGE",
    "name:eng_x_preferred":[
        "Chura Khark Khet"
    ],
    "wof:name":"Chura Khark Khet",
    "wof:placetype":"locality",
    "wof:population":73
},
  "geometry": {"coordinates":[80.057309,29.332508],"type":"Point"}
}