{
  "type": "Feature",
  "properties": {
    "iso:country":"IN",
    "ks:ks_name":"Girkabavi Tanda",
    "ks:ks_pop":20,
    "ks:ks_type":"HABITATION",
    "name:eng_x_preferred":[
        "Girkabavi Tanda"
    ],
    "wof:name":"Girkabavi Tanda",
    "wof:placetype":"locality",
    "wof:population":20
},
  "geometry": {"coordinates":[77.674201,17.133295],"type":"Point"}
}