{
  "type": "Feature",
  "properties": {
    "gn:admin1_code":"34.0",
    "gn:admin2_code":"218.0",
    "gn:asciiname":"Kanhauli",
    "gn:country_code":"IN",
    "gn:dem":68,
    "gn:feature_class":"P",
    "gn:feature_code":"PPL",
    "gn:name":"Kanhauli",
    "gn:population":0,
    "gn:timezone":"Asia/Kolkata",
    "iso:country":"IN",
    "ks:ks_name":"Kanhauli",
    "ks:ks_pop":602,
    "ks:ks_type":"VILLAGE",
    "ks:ks_uagg_main":0,
    "name:eng_x_preferred":[
        "Kanhauli"
    ],
    "wof:name":"Kanhauli",
    "wof:placetype":"neighbourhood",
    "wof:population":602
},
  "geometry": {"coordinates":[84.14721900000001,26.147244],"type":"Point"}
}