{
  "type": "Feature",
  "properties": {
    "gn:country":"IN",
    "gn:fcode":"PPL",
    "gn:population":5195,
    "iso:country":"IN",
    "name:ara_x_preferred":[
        "\u0631\u0627\u0645\u0646\u0627\u063a\u0627\u0631"
    ],
    "name:ben_bn_x_preferred":[
        "\u09b0\u09be\u09ae\u09a8\u0997\u09b0"
    ],
    "name:ben_in_x_preferred":[
        "\u09b0\u09be\u09ae\u09a8\u0997\u09b0"
    ],
    "name:ben_x_preferred":[
        "\u09b0\u09be\u09ae\u09a8\u0997\u09b0"
    ],
    "name:cat_x_preferred":[
        "Ramnagar"
    ],
    "name:ceb_x_preferred":[
        "Ramnagar"
    ],
    "name:fra_x_preferred":[
        "Ramnagar"
    ],
    "name:guj_x_preferred":[
        "\u0ab0\u0abe\u0aae\u0aa8\u0a97\u0ab0"
    ],
    "name:hin_x_preferred":[
        "\u0930\u093e\u092e\u0928\u0917\u0930"
    ],
    "name:kan_x_preferred":[
        "\u0cb0\u0cbe\u0cae\u0ca8\u0c97\u0cb0"
    ],
    "name:mal_x_preferred":[
        "\u0d30\u0d3e\u0d02\u0d28\u0d17\u0d30\u0d4d\u200d"
    ],
    "name:mar_x_preferred":[
        "\u0930\u093e\u092e\u0928\u0917\u0930"
    ],
    "name:new_x_preferred":[
        "\u0930\u093e\u092e\u0928\u0917\u0930"
    ],
    "name:nld_x_preferred":[
        "Ramnagar"
    ],
    "name:pan_x_preferred":[
        "\u0a30\u0a3e\u0a2e\u0a28\u0a17\u0a30"
    ],
    "name:pol_x_preferred":[
        "Ramnagar"
    ],
    "name:rus_x_preferred":[
        "\u0420\u0430\u043c\u043d\u0430\u0433\u0430\u0440"
    ],
    "name:swe_x_preferred":[
        "Ramnagar"
    ],
    "name:tam_x_preferred":[
        "\u0bb0\u0bbe\u0bae\u0bcd\u0ba8\u0b95\u0bb0\u0bcd"
    ],
    "name:tel_x_preferred":[
        "\u0c30\u0c3e\u0c02\u0c28\u0c17\u0c30\u0c4d"
    ],
    "name:urd_x_preferred":[
        "\u0631\u0627\u0645 \u0646\u06af\u0631"
    ],
    "qs:name":"Ramnagar",
    "qs:name_adm0":"India",
    "qs:name_adm1":"West Bengal",
    "qs:photos_9r":0,
    "qs:photos_sr":0,
    "qs:placetype":"Town",
    "qs:pop_sr":"5",
    "wd:wordcount":231,
    "wof:name":"Ramnagar",
    "wof:placetype":"locality",
    "wof:population":5195
},
  "geometry": {"coordinates":[88.24639000000001,22.77778],"type":"Point"}
}