{
  "type": "Feature",
  "properties": {
    "gn:country":"IN",
    "gn:fcode":"PPL",
    "gn:pop":5195,
    "iso:country":"IN",
    "name:ben_x_preferred":[
        "\u09b0\u09be\u09ae\u09a8\u0997\u09b0"
    ],
    "name:cat_x_preferred":[
        "Ramnagar"
    ],
    "name:ceb_x_preferred":[
        "Ramnagar"
    ],
    "name:fra_x_preferred":[
        "Ramnagar"
    ],
    "name:hin_x_preferred":[
        "\u0930\u093e\u092e\u0928\u0917\u0930"
    ],
    "name:new_x_preferred":[
        "\u0930\u093e\u092e\u0928\u0917\u0930"
    ],
    "name:nld_x_preferred":[
        "Ramnagar"
    ],
    "name:pol_x_preferred":[
        "Ramnagar"
    ],
    "name:rus_x_preferred":[
        "\u0420\u0430\u043c\u043d\u0430\u0433\u0430\u0440"
    ],
    "name:swe_x_preferred":[
        "Ramnagar"
    ],
    "qs:name":"Ramnagar",
    "qs:name_adm0":"India",
    "qs:name_adm1":"West Bengal",
    "qs:photos_9r":0,
    "qs:photos_sr":0,
    "qs:placetype":"Town",
    "qs:pop_sr":"5",
    "wd:wordcount":231,
    "wof:name":"Ramnagar",
    "wof:placetype":"locality",
    "wof:population":5195
},
  "geometry": {"coordinates":[88.24639000000001,22.77778],"type":"Point"}
}