{
  "type": "Feature",
  "properties": {
    "gn:admin1_code":"35.0",
    "gn:admin2_code":"450.0",
    "gn:asciiname":"Jajnori",
    "gn:country_code":"IN",
    "gn:dem":369,
    "gn:feature_class":"P",
    "gn:feature_code":"PPL",
    "gn:name":"Jajnori",
    "gn:population":0,
    "gn:timezone":"Asia/Kolkata",
    "iso:country":"IN",
    "wof:name":"Jajnori",
    "wof:placetype":"locality"
},
  "geometry": {"coordinates":[80.56028000000001,23.97133],"type":"Point"}
}