{
  "type": "Feature",
  "properties": {
    "iso:country":"IN",
    "ks:ks_name":"N. Lalsingh",
    "ks:ks_pop":30,
    "ks:ks_type":"HABITATION",
    "ks:ks_uagg_main":0,
    "name:eng_x_preferred":[
        "N. Lalsingh"
    ],
    "wof:name":"N. Lalsingh",
    "wof:placetype":"neighbourhood",
    "wof:population":30
},
  "geometry": {"coordinates":[79.313649,27.112886],"type":"Point"}
}