{
  "type": "Feature",
  "properties": {
    "iso:country":"IN",
    "ks:ks_name":"Dadari",
    "ks:ks_pop":11,
    "ks:ks_type":"VILLAGE",
    "name:eng_x_preferred":[
        "Dadari"
    ],
    "wof:name":"Dadari",
    "wof:placetype":"locality",
    "wof:population":11
},
  "geometry": {"coordinates":[85.183164,21.121257],"type":"Point"}
}