{
  "type": "Feature",
  "properties": {
    "iso:country":"IN",
    "ks:ks_name":"Jamdigri",
    "ks:ks_pop":846,
    "ks:ks_type":"VILLAGE",
    "name:eng_x_preferred":[
        "Jamdigri"
    ],
    "wof:name":"Jamdigri",
    "wof:placetype":"locality",
    "wof:population":846
},
  "geometry": {"coordinates":[87.478697,23.068895],"type":"Point"}
}