{
  "type": "Feature",
  "properties": {
    "iso:country":"IN",
    "ks:ks_alt_nam":"neeli kunnu",
    "ks:ks_name":"Neeli Kunnu",
    "ks:ks_pop":256,
    "ks:ks_type":"HABITATION",
    "name:eng_x_preferred":[
        "Neeli Kunnu"
    ],
    "wof:name":"Neeli Kunnu",
    "wof:placetype":"locality",
    "wof:population":256
},
  "geometry": {"coordinates":[75.79676600000001,11.529481],"type":"Point"}
}