{
  "type": "Feature",
  "properties": {
    "iso:country":"IN",
    "ks:ks_alt_nam":"Sundarw\u0101s",
    "ks:ks_name":"Sundarwas",
    "ks:ks_type":"VILLAGE",
    "ks:ks_uagg_main":0,
    "name:eng_x_preferred":[
        "Sundarwas"
    ],
    "name:eng_x_variant":[
        "Sundarw\u0101s"
    ],
    "wof:name":"Sundarwas",
    "wof:placetype":"neighbourhood"
},
  "geometry": {"coordinates":[73.73386499999999,24.586467],"type":"Point"}
}