{
  "type": "Feature",
  "properties": {
    "iso:country":"IN",
    "ks:ks_alt_nam":"KUMHARAN KA PURWA",
    "ks:ks_name":"Kumharan Ka Purwa",
    "ks:ks_pop":212,
    "ks:ks_type":"HABITATION",
    "ks:ks_uagg_main":0,
    "name:eng_x_preferred":[
        "Kumharan Ka Purwa"
    ],
    "wof:name":"Kumharan Ka Purwa",
    "wof:placetype":"neighbourhood",
    "wof:population":212
},
  "geometry": {"coordinates":[82.225043,26.215164],"type":"Point"}
}