{
  "type": "Feature",
  "properties": {
    "iso:country":"IN",
    "ks:ks_name":"Guheswaranahalli",
    "ks:ks_type":"VILLAGE",
    "name:eng_x_preferred":[
        "Guheswaranahalli"
    ],
    "wof:name":"Guheswaranahalli",
    "wof:placetype":"locality"
},
  "geometry": {"coordinates":[76.35425499999999,14.425252],"type":"Point"}
}