{
  "type": "Feature",
  "properties": {
    "iso:country":"IN",
    "ks:ks_name":"Shiravanthe",
    "ks:ks_pop":1119,
    "ks:ks_type":"VILLAGE",
    "name:eng_x_preferred":[
        "Shiravanthe"
    ],
    "wof:name":"Shiravanthe",
    "wof:placetype":"locality",
    "wof:population":1119
},
  "geometry": {"coordinates":[74.96730700000001,14.184157],"type":"Point"}
}