{
  "type": "Feature",
  "properties": {
    "gn:admin1_code":"2",
    "gn:admin2_code":"544.0",
    "gn:asciiname":"Velagalapudi",
    "gn:country_code":"IN",
    "gn:dem":107,
    "gn:feature_class":"P",
    "gn:feature_code":"PPL",
    "gn:name":"Velagalapudi",
    "gn:population":0,
    "gn:timezone":"Asia/Kolkata",
    "iso:country":"IN",
    "ks:ks_name":"Velagalapudi",
    "ks:ks_pop":64,
    "ks:ks_type":"HABITATION",
    "name:eng_x_preferred":[
        "Velagalapudi"
    ],
    "wof:name":"Velagalapudi",
    "wof:placetype":"locality",
    "wof:population":64
},
  "geometry": {"coordinates":[82.56946499999999,17.579356],"type":"Point"}
}