{
  "type": "Feature",
  "properties": {
    "gn:admin1_code":"2",
    "gn:admin2_code":"544.0",
    "gn:asciiname":"Velagalapudi",
    "gn:country_code":"IN",
    "gn:dem":107,
    "gn:feature_class":"P",
    "gn:feature_code":"PPL",
    "gn:name":"Velagalapudi",
    "gn:population":0,
    "gn:timezone":"Asia/Kolkata",
    "iso:country":"IN",
    "wof:name":"Velagalapudi",
    "wof:placetype":"locality"
},
  "geometry": {"coordinates":[82.57854,17.57947],"type":"Point"}
}