{
  "type": "Feature",
  "properties": {
    "iso:country":"IN",
    "ks:ks_name":"Banahata",
    "ks:ks_pop":764,
    "ks:ks_type":"VILLAGE",
    "name:eng_x_preferred":[
        "Banahata"
    ],
    "wof:name":"Banahata",
    "wof:placetype":"locality",
    "wof:population":764
},
  "geometry": {"coordinates":[86.09968499999999,23.387866],"type":"Point"}
}