{
  "type": "Feature",
  "properties": {
    "iso:country":"IN",
    "ks:ks_alt_nam":"DONGARGAON",
    "ks:ks_name":"Dongargaon",
    "ks:ks_pop":90,
    "ks:ks_type":"HABITATION",
    "name:eng_x_preferred":[
        "Dongargaon"
    ],
    "name:hin_x_preferred":[
        "\u0921\u094b\u0902\u0917\u0930\u0917\u093e\u0902\u0935"
    ],
    "wof:name":"Dongargaon",
    "wof:placetype":"locality",
    "wof:population":90
},
  "geometry": {"coordinates":[75.363288,20.207759],"type":"Point"}
}