{
  "type": "Feature",
  "properties": {
    "iso:country":"IN",
    "ks:ks_name":"Punawali",
    "ks:ks_pop":858,
    "ks:ks_type":"VILLAGE",
    "name:eng_x_preferred":[
        "Punawali"
    ],
    "wof:name":"Punawali",
    "wof:placetype":"locality",
    "wof:population":858
},
  "geometry": {"coordinates":[77.96470100000001,25.356758],"type":"Point"}
}