{
  "type": "Feature",
  "properties": {
    "iso:country":"IN",
    "qs:name":"Sukarbar Peth",
    "qs:name_adm0":"India",
    "qs:name_adm1":"Maharashtra",
    "qs:photos":73,
    "qs:photos_1k":15,
    "qs:photos_9k":1,
    "qs:photos_9r":2,
    "qs:photos_all":73,
    "qs:photos_sr":2,
    "qs:placetype":"Suburb",
    "qs:pop_sr":"0",
    "wof:name":"Sukarbar Peth",
    "wof:placetype":"neighbourhood"
},
  "geometry": {"coordinates":[73.85394552243099,18.51151043201381],"type":"Point"}
}