{
  "type": "Feature",
  "properties": {
    "iso:country":"IN",
    "name:ara_x_preferred":[
        "\u0633\u0643\u0631\u0628\u0627\u0631 \u0628\u064a\u062b"
    ],
    "name:ben_bn_x_preferred":[
        "\u09b6\u09c1\u0995\u09b0\u09ac\u09be\u09b0 \u09aa\u09c7\u09a0"
    ],
    "name:ben_in_x_preferred":[
        "\u09b6\u09c1\u0995\u09b0\u09ac\u09be\u09b0 \u09aa\u09c7\u09a0"
    ],
    "name:guj_x_preferred":[
        "\u0ab8\u0ac1\u0a95\u0abe\u0ab0\u0aac\u0abe\u0ab0 \u0aaa\u0ac7\u0aa0"
    ],
    "name:hin_x_preferred":[
        "\u0938\u0941\u0915\u0930\u092c\u093e\u0930 \u092a\u0947\u091f"
    ],
    "name:kan_x_preferred":[
        "\u0cb8\u0cc1\u0c95\u0cb0\u0ccd"
    ],
    "name:mal_x_preferred":[
        "\u0d36\u0d41\u0d15\u0d4d\u0d30\u0d35\u0d7c \u0d2a\u0d46\u0d24\u0d4d\u0d24\u0d4d"
    ],
    "name:mar_x_preferred":[
        "\u0936\u0941\u0915\u094d\u0930\u0935\u093e\u0930 \u092a\u0947\u0920"
    ],
    "name:pan_x_preferred":[
        "\u0a38\u0a41\u0a15\u0a30\u0a2c\u0a30 \u0a2a\u0a47\u0a1f"
    ],
    "name:tam_x_preferred":[
        "\u0b9a\u0bc1\u0b95\u0bb0\u0bcd\u0baa\u0bb0\u0bcd \u0baa\u0bc7\u0ba4\u0bcd"
    ],
    "name:tel_x_preferred":[
        "\u0c38\u0c41\u0c15\u0c3e\u0c30\u0c4d"
    ],
    "name:urd_x_preferred":[
        "\u0633\u06a9\u0631\u0628\u0627\u0631 \u067e\u06cc\u0679\u06be"
    ],
    "qs:name":"Sukarbar Peth",
    "qs:name_adm0":"India",
    "qs:name_adm1":"Maharashtra",
    "qs:photos":73,
    "qs:photos_1k":15,
    "qs:photos_9k":1,
    "qs:photos_9r":2,
    "qs:photos_all":73,
    "qs:photos_sr":2,
    "qs:placetype":"Suburb",
    "qs:pop_sr":"0",
    "wof:name":"Sukarbar Peth",
    "wof:placetype":"neighbourhood"
},
  "geometry": {"coordinates":[73.85394552243099,18.51151043201381],"type":"Point"}
}