{
  "type": "Feature",
  "properties": {
    "iso:country":"IN",
    "ks:ks_name":"Chandi Khera",
    "ks:ks_pop":521,
    "ks:ks_type":"HABITATION",
    "ks:ks_uagg_main":0,
    "name:eng_x_preferred":[
        "Chandi Khera"
    ],
    "wof:name":"Chandi Khera",
    "wof:placetype":"neighbourhood",
    "wof:population":521
},
  "geometry": {"coordinates":[81.108304,26.625522],"type":"Point"}
}