{
  "type": "Feature",
  "properties": {
    "gn:admin1_code":"23.0",
    "gn:admin2_code":"35.0",
    "gn:asciiname":"Kharkhara Tarf Narot",
    "gn:country_code":"IN",
    "gn:dem":280,
    "gn:feature_class":"P",
    "gn:feature_code":"PPL",
    "gn:name":"Kharkhara Tarf Narot",
    "gn:population":0,
    "gn:timezone":"Asia/Kolkata",
    "iso:country":"IN",
    "wof:name":"Kharkhara Tarf Narot",
    "wof:placetype":"locality"
},
  "geometry": {"coordinates":[75.45674,32.29455],"type":"Point"}
}