{
  "type": "Feature",
  "properties": {
    "gn:admin1_code":"34.0",
    "gn:admin2_code":"218.0",
    "gn:asciiname":"Sisahani",
    "gn:country_code":"IN",
    "gn:dem":67,
    "gn:feature_class":"P",
    "gn:feature_code":"PPL",
    "gn:name":"Sisahani",
    "gn:population":0,
    "gn:timezone":"Asia/Kolkata",
    "iso:country":"IN",
    "ks:ks_name":"Sisahani",
    "ks:ks_pop":1359,
    "ks:ks_type":"VILLAGE",
    "ks:ks_uagg_main":0,
    "name:eng_x_preferred":[
        "Sisahani"
    ],
    "wof:name":"Sisahani",
    "wof:placetype":"neighbourhood",
    "wof:population":1359
},
  "geometry": {"coordinates":[84.209188,26.196439],"type":"Point"}
}