{
  "type": "Feature",
  "properties": {
    "gn:admin1_code":"35",
    "gn:admin2_code":"456.0",
    "gn:asciiname":"Tharka",
    "gn:country_code":"IN",
    "gn:dem":606,
    "gn:feature_class":"P",
    "gn:feature_code":"PPL",
    "gn:name":"Thark\u0101",
    "gn:population":0,
    "gn:timezone":"Asia/Kolkata",
    "iso:country":"IN",
    "ks:ks_alt_nam":"Thark\u0101",
    "ks:ks_name":"Tharka",
    "ks:ks_pop":371,
    "ks:ks_type":"VILLAGE",
    "name:eng_x_preferred":[
        "Tharka"
    ],
    "name:eng_x_variant":[
        "Thark\u0101"
    ],
    "wof:name":"Tharka",
    "wof:placetype":"locality",
    "wof:population":371
},
  "geometry": {"coordinates":[79.40636600000001,22.116403],"type":"Point"}
}