{
  "type": "Feature",
  "properties": {
    "iso:country":"IN",
    "ks:ks_name":"Doonga Ka Bas",
    "ks:ks_pop":355,
    "ks:ks_type":"HABITATION",
    "name:eng_x_preferred":[
        "Doonga Ka Bas"
    ],
    "wof:name":"Doonga Ka Bas",
    "wof:placetype":"locality",
    "wof:population":355
},
  "geometry": {"coordinates":[76.332222,27.5425],"type":"Point"}
}