{
  "type": "Feature",
  "properties": {
    "iso:country":"IN",
    "ks:ks_name":"Chaudhary Tola",
    "ks:ks_pop":187,
    "ks:ks_type":"HABITATION",
    "name:eng_x_preferred":[
        "Chaudhary Tola"
    ],
    "wof:name":"Chaudhary Tola",
    "wof:placetype":"locality",
    "wof:population":187
},
  "geometry": {"coordinates":[83.48614999999999,26.83639],"type":"Point"}
}