{
  "type": "Feature",
  "properties": {
    "iso:country":"IN",
    "ks:ks_name":"Chhachhi Beri",
    "ks:ks_pop":1008,
    "ks:ks_type":"VILLAGE",
    "name:eng_x_preferred":[
        "Chhachhi Beri"
    ],
    "wof:name":"Chhachhi Beri",
    "wof:placetype":"locality",
    "wof:population":1008
},
  "geometry": {"coordinates":[71.222269,25.167042],"type":"Point"}
}