{
  "type": "Feature",
  "properties": {
    "iso:country":"IN",
    "ks:ks_name":"5 JRK",
    "ks:ks_pop":67,
    "ks:ks_type":"VILLAGE",
    "name:eng_x_preferred":[
        "5 JRK"
    ],
    "wof:name":"5 JRK",
    "wof:placetype":"locality",
    "wof:population":67
},
  "geometry": {"coordinates":[74.237291,29.629771],"type":"Point"}
}