{
  "type": "Feature",
  "properties": {
    "gn:admin1_code":"34.0",
    "gn:admin2_code":"219.0",
    "gn:asciiname":"Bhaiya Ramki Dhauri",
    "gn:country_code":"IN",
    "gn:dem":61,
    "gn:feature_class":"P",
    "gn:feature_code":"PPL",
    "gn:name":"Bhaiya R\u0101mki Dhauri",
    "gn:population":0,
    "gn:timezone":"Asia/Kolkata",
    "iso:country":"IN",
    "ks:ks_alt_nam":"Bhaiya R\u0101mki Dhauri",
    "ks:ks_name":"Bhaiya Ramki Dhauri",
    "ks:ks_pop":2332,
    "ks:ks_type":"VILLAGE",
    "ks:ks_uagg_main":0,
    "name:eng_x_preferred":[
        "Bhaiya Ramki Dhauri"
    ],
    "name:eng_x_variant":[
        "Bhaiya R\u0101mki Dhauri"
    ],
    "wof:name":"Bhaiya Ramki Dhauri",
    "wof:placetype":"neighbourhood",
    "wof:population":2332
},
  "geometry": {"coordinates":[84.704933,26.062993],"type":"Point"}
}