{
  "type": "Feature",
  "properties": {
    "gn:admin1_code":"24.0",
    "gn:admin2_code":"99.0",
    "gn:asciiname":"Rupnagar",
    "gn:country_code":"IN",
    "gn:dem":180,
    "gn:feature_class":"P",
    "gn:feature_code":"PPL",
    "gn:name":"Rupnagar",
    "gn:population":0,
    "gn:timezone":"Asia/Kolkata",
    "iso:country":"IN",
    "wof:name":"Rupnagar",
    "wof:placetype":"locality"
},
  "geometry": {"coordinates":[74.02290000000001,29.96149],"type":"Point"}
}