{
  "type": "Feature",
  "properties": {
    "iso:country":"IN",
    "ks:ks_name":"Kempena Koppa",
    "ks:ks_pop":5,
    "ks:ks_type":"VILLAGE",
    "name:eng_x_preferred":[
        "Kempena Koppa"
    ],
    "wof:name":"Kempena Koppa",
    "wof:placetype":"locality",
    "wof:population":5
},
  "geometry": {"coordinates":[75.395798,14.073888],"type":"Point"}
}