{
  "type": "Feature",
  "properties": {
    "iso:country":"IN",
    "ks:ks_name":"Kinattintavida",
    "ks:ks_pop":405,
    "ks:ks_type":"HABITATION",
    "ks:ks_uagg_main":0,
    "name:eng_x_preferred":[
        "Kinattintavida"
    ],
    "wof:name":"Kinattintavida",
    "wof:placetype":"neighbourhood",
    "wof:population":405
},
  "geometry": {"coordinates":[75.54490300000001,11.850602],"type":"Point"}
}