{
  "type": "Feature",
  "properties": {
    "iso:country":"IN",
    "ks:ks_name":"Dhaba Bawardi",
    "ks:ks_pop":666,
    "ks:ks_type":"VILLAGE",
    "name:eng_x_preferred":[
        "Dhaba Bawardi"
    ],
    "wof:name":"Dhaba Bawardi",
    "wof:placetype":"locality",
    "wof:population":666
},
  "geometry": {"coordinates":[74.97347600000001,21.968939],"type":"Point"}
}