{
  "type": "Feature",
  "properties": {
    "gn:admin1_code":"36.0",
    "gn:admin2_code":"175.0",
    "gn:asciiname":"Nai Bazar",
    "gn:country_code":"IN",
    "gn:dem":101,
    "gn:feature_class":"P",
    "gn:feature_code":"PPL",
    "gn:name":"Nai B\u0101z\u0101r",
    "gn:population":0,
    "gn:timezone":"Asia/Kolkata",
    "iso:country":"IN",
    "name:bpy_x_preferred":[
        "\u09a8\u09be\u0987 \u09ac\u09be\u099c\u09be\u09b0"
    ],
    "name:fas_x_preferred":[
        "\u0646\u06cc\u200c\u0628\u0627\u0632\u0627\u0631"
    ],
    "name:ita_x_preferred":[
        "Nai Bazar"
    ],
    "name:msa_x_preferred":[
        "Nai Bazar"
    ],
    "name:new_x_preferred":[
        "\u0928\u0908 \u092c\u091c\u093e\u0930"
    ],
    "name:nld_x_preferred":[
        "Nai Bazar"
    ],
    "name:pol_x_preferred":[
        "Nai Bazar"
    ],
    "name:por_x_preferred":[
        "Nai Bazar"
    ],
    "name:und_x_variant":[
        "Nai B\u0101z\u0101r",
        "M\u0101dhopur"
    ],
    "name:urd_x_preferred":[
        "\u0646\u0626\u06cc \u0628\u0627\u0632\u0627\u0631"
    ],
    "name:vie_x_preferred":[
        "Nai Bazar"
    ],
    "name:zho_x_preferred":[
        "\u5948\u5df4\u624e\u5c14"
    ],
    "wof:name":"Nai Bazar",
    "wof:placetype":"locality"
},
  "geometry": {"coordinates":[81.94571999999999,25.67714],"type":"Point"}
}