{
  "type": "Feature",
  "properties": {
    "gn:admin1_code":"36.0",
    "gn:admin2_code":"175.0",
    "gn:asciiname":"Nai Bazar",
    "gn:country_code":"IN",
    "gn:dem":101,
    "gn:feature_class":"P",
    "gn:feature_code":"PPL",
    "gn:name":"Nai B\u0101z\u0101r",
    "gn:population":0,
    "gn:timezone":"Asia/Kolkata",
    "iso:country":"IN",
    "name:und_x_variant":[
        "Nai B\u0101z\u0101r",
        "M\u0101dhopur"
    ],
    "wof:name":"Nai Bazar",
    "wof:placetype":"locality"
},
  "geometry": {"coordinates":[81.94571999999999,25.67714],"type":"Point"}
}