{
  "type": "Feature",
  "properties": {
    "gn:admin1_code":"12",
    "gn:asciiname":"Dudhran",
    "gn:country_code":"IN",
    "gn:dem":2059,
    "gn:feature_class":"P",
    "gn:feature_code":"PPL",
    "gn:name":"D\u016bdhran",
    "gn:population":0,
    "gn:timezone":"Asia/Kolkata",
    "iso:country":"IN",
    "wof:name":"Dudhran",
    "wof:placetype":"locality"
},
  "geometry": {"coordinates":[74.2159,34.07142],"type":"Point"}
}