{
  "type": "Feature",
  "properties": {
    "iso:country":"IN",
    "ks:ks_name":"Sarion",
    "ks:ks_pop":698,
    "ks:ks_type":"VILLAGE",
    "name:eng_x_preferred":[
        "Sarion"
    ],
    "wof:name":"Sarion",
    "wof:placetype":"locality",
    "wof:population":698
},
  "geometry": {"coordinates":[85.672349,21.04248],"type":"Point"}
}