{
  "type": "Feature",
  "properties": {
    "iso:country":"IN",
    "ks:ks_name":"Ruma",
    "ks:ks_pop":155,
    "ks:ks_type":"HABITATION",
    "name:eng_x_preferred":[
        "Ruma"
    ],
    "wof:name":"Ruma",
    "wof:placetype":"locality",
    "wof:population":155
},
  "geometry": {"coordinates":[82.314722,18.180713],"type":"Point"}
}