{
  "type": "Feature",
  "properties": {
    "iso:country":"IN",
    "ks:ks_name":"Deppiguda",
    "ks:ks_pop":32,
    "ks:ks_type":"HABITATION",
    "name:eng_x_preferred":[
        "Deppiguda"
    ],
    "wof:name":"Deppiguda",
    "wof:placetype":"locality",
    "wof:population":32
},
  "geometry": {"coordinates":[83.941632,18.725635],"type":"Point"}
}