{
  "type": "Feature",
  "properties": {
    "iso:country":"IN",
    "ks:ks_alt_nam":"Panch patra Majhipara",
    "ks:ks_name":"Panch Patra Majhipara",
    "ks:ks_pop":807,
    "ks:ks_type":"HABITATION",
    "ks:ks_uagg_main":0,
    "name:eng_x_preferred":[
        "Panch Patra Majhipara"
    ],
    "wof:name":"Panch Patra Majhipara",
    "wof:placetype":"locality",
    "wof:population":807
},
  "geometry": {"coordinates":[88.184034,22.612636],"type":"Point"}
}