{
  "type": "Feature",
  "properties": {
    "gn:admin1_code":"36",
    "gn:admin2_code":"199.0",
    "gn:asciiname":"Arazi Chak Burhia",
    "gn:country_code":"IN",
    "gn:dem":87,
    "gn:feature_class":"P",
    "gn:feature_code":"PPL",
    "gn:name":"Ar\u0101zi Chak Burhia",
    "gn:population":0,
    "gn:timezone":"Asia/Kolkata",
    "iso:country":"IN",
    "wof:name":"Arazi Chak Burhia",
    "wof:placetype":"locality"
},
  "geometry": {"coordinates":[83.07079,25.10203],"type":"Point"}
}