{
  "type": "Feature",
  "properties": {
    "iso:country":"IN",
    "ks:ks_name":"Harijanwasti",
    "ks:ks_pop":430,
    "ks:ks_type":"HABITATION",
    "name:eng_x_preferred":[
        "Harijanwasti"
    ],
    "wof:name":"Harijanwasti",
    "wof:placetype":"locality",
    "wof:population":430
},
  "geometry": {"coordinates":[74.229388,19.550955],"type":"Point"}
}