{
  "type": "Feature",
  "properties": {
    "iso:country":"IN",
    "ks:ks_name":"Jadubati",
    "ks:ks_pop":724,
    "ks:ks_type":"VILLAGE",
    "ks:ks_uagg_main":0,
    "name:eng_x_preferred":[
        "Jadubati"
    ],
    "wof:name":"Jadubati",
    "wof:placetype":"neighbourhood",
    "wof:population":724
},
  "geometry": {"coordinates":[88.596778,25.238444],"type":"Point"}
}