{
  "type": "Feature",
  "properties": {
    "gn:admin1_code":"23.0",
    "gn:admin2_code":"41.0",
    "gn:asciiname":"Bir Akhara",
    "gn:country_code":"IN",
    "gn:dem":232,
    "gn:feature_class":"P",
    "gn:feature_code":"PPL",
    "gn:name":"B\u012br Akh\u0101ra",
    "gn:population":0,
    "gn:timezone":"Asia/Kolkata",
    "iso:country":"IN",
    "wof:name":"Bir Akhara",
    "wof:placetype":"locality"
},
  "geometry": {"coordinates":[75.48246999999998,30.7619],"type":"Point"}
}