{
  "type": "Feature",
  "properties": {
    "iso:country":"IN",
    "ks:ks_name":"Madivalarakeri",
    "ks:ks_pop":177,
    "ks:ks_type":"HABITATION",
    "name:eng_x_preferred":[
        "Madivalarakeri"
    ],
    "wof:name":"Madivalarakeri",
    "wof:placetype":"locality",
    "wof:population":177
},
  "geometry": {"coordinates":[75.684444,12.299722],"type":"Point"}
}