{
  "type": "Feature",
  "properties": {
    "iso:country":"IN",
    "ks:ks_name":"Nagnechinagar",
    "ks:ks_pop":728,
    "ks:ks_type":"HABITATION",
    "name:eng_x_preferred":[
        "Nagnechinagar"
    ],
    "wof:name":"Nagnechinagar",
    "wof:placetype":"locality",
    "wof:population":728
},
  "geometry": {"coordinates":[72.215158,27.078583],"type":"Point"}
}