{
  "type": "Feature",
  "properties": {
    "iso:country":"IN",
    "ks:ks_name":"Basaitha",
    "ks:ks_pop":1381,
    "ks:ks_type":"VILLAGE",
    "name:eng_x_preferred":[
        "Basaitha"
    ],
    "wof:name":"Basaitha",
    "wof:placetype":"locality",
    "wof:population":1381
},
  "geometry": {"coordinates":[85.077662,26.040796],"type":"Point"}
}