{
  "type": "Feature",
  "properties": {
    "iso:country":"IN",
    "ks:ks_name":"Goregadde",
    "ks:ks_pop":36,
    "ks:ks_type":"HABITATION",
    "name:eng_x_preferred":[
        "Goregadde"
    ],
    "wof:name":"Goregadde",
    "wof:placetype":"locality",
    "wof:population":36
},
  "geometry": {"coordinates":[74.787885,14.562726],"type":"Point"}
}