{
  "type": "Feature",
  "properties": {
    "iso:country":"IN",
    "ks:ks_name":"Fatoria",
    "ks:ks_pop":183,
    "ks:ks_type":"HABITATION",
    "name:eng_x_preferred":[
        "Fatoria"
    ],
    "wof:name":"Fatoria",
    "wof:placetype":"locality",
    "wof:population":183
},
  "geometry": {"coordinates":[86.63457699999999,24.673431],"type":"Point"}
}