{
  "type": "Feature",
  "properties": {
    "gn:admin1_code":"24.0",
    "gn:admin2_code":"124.0",
    "gn:asciiname":"Dhani",
    "gn:country_code":"IN",
    "gn:dem":269,
    "gn:feature_class":"P",
    "gn:feature_code":"PPL",
    "gn:name":"Dh\u0101ni",
    "gn:population":0,
    "gn:timezone":"Asia/Kolkata",
    "iso:country":"IN",
    "ks:ks_name":"Dhani",
    "ks:ks_pop":626,
    "ks:ks_type":"HABITATION",
    "name:deu_x_preferred":[
        "Dhani"
    ],
    "name:eng_x_preferred":[
        "Dhani"
    ],
    "wof:name":"Dhani",
    "wof:placetype":"locality",
    "wof:population":626
},
  "geometry": {"coordinates":[73.718148,23.903328],"type":"Point"}
}