{
  "type": "Feature",
  "properties": {
    "iso:country":"IN",
    "ks:ks_alt_nam":"GADARIYAN KA PURA",
    "ks:ks_name":"Gadariyan Ka Pura",
    "ks:ks_pop":208,
    "ks:ks_type":"HABITATION",
    "name:eng_x_preferred":[
        "Gadariyan Ka Pura"
    ],
    "wof:name":"Gadariyan Ka Pura",
    "wof:placetype":"locality",
    "wof:population":208
},
  "geometry": {"coordinates":[82.15843,26.265861],"type":"Point"}
}