{
  "type": "Feature",
  "properties": {
    "iso:country":"IN",
    "ks:ks_alt_nam":"Pandit ka Purwa",
    "ks:ks_name":"Pandit Ka Purwa",
    "ks:ks_pop":300,
    "ks:ks_type":"HABITATION",
    "ks:ks_uagg_main":0,
    "name:eng_x_preferred":[
        "Pandit Ka Purwa"
    ],
    "wof:name":"Pandit Ka Purwa",
    "wof:placetype":"neighbourhood",
    "wof:population":300
},
  "geometry": {"coordinates":[81.34871699999999,26.441824],"type":"Point"}
}