{
  "type": "Feature",
  "properties": {
    "iso:country":"IN",
    "ks:ks_alt_nam":"Purk\u0101bod\u012b",
    "ks:ks_name":"Purkabodi",
    "ks:ks_type":"VILLAGE",
    "name:eng_x_preferred":[
        "Purkabodi"
    ],
    "name:eng_x_variant":[
        "Purk\u0101bod\u012b"
    ],
    "wof:name":"Purkabodi",
    "wof:placetype":"locality"
},
  "geometry": {"coordinates":[80.086279,21.180724],"type":"Point"}
}