{
  "type": "Feature",
  "properties": {
    "iso:country":"IN",
    "ks:ks_name":"Bangaruba",
    "ks:ks_pop":58,
    "ks:ks_type":"VILLAGE",
    "name:eng_x_preferred":[
        "Bangaruba"
    ],
    "wof:name":"Bangaruba",
    "wof:placetype":"locality",
    "wof:population":58
},
  "geometry": {"coordinates":[84.206322,18.95957],"type":"Point"}
}