{
  "type": "Feature",
  "properties": {
    "gn:admin1_code":"34.0",
    "gn:admin2_code":"221.0",
    "gn:asciiname":"Fatehpur Bala",
    "gn:country_code":"IN",
    "gn:dem":53,
    "gn:feature_class":"P",
    "gn:feature_code":"PPL",
    "gn:name":"Fatehpur B\u0101la",
    "gn:population":0,
    "gn:timezone":"Asia/Kolkata",
    "iso:country":"IN",
    "ks:ks_alt_nam":"Fatehpur B\u0101la",
    "ks:ks_name":"Fatehpur Bala",
    "ks:ks_pop":8990,
    "ks:ks_type":"VILLAGE",
    "name:eng_x_preferred":[
        "Fatehpur Bala"
    ],
    "name:eng_x_variant":[
        "Fatehpur B\u0101la"
    ],
    "wof:name":"Fatehpur Bala",
    "wof:placetype":"locality",
    "wof:population":8990
},
  "geometry": {"coordinates":[85.695054,25.831321],"type":"Point"}
}