{
  "type": "Feature",
  "properties": {
    "iso:country":"IN",
    "ks:ks_name":"Bhangath",
    "ks:ks_pop":7,
    "ks:ks_type":"VILLAGE",
    "name:eng_x_preferred":[
        "Bhangath"
    ],
    "wof:name":"Bhangath",
    "wof:placetype":"locality",
    "wof:population":7
},
  "geometry": {"coordinates":[86.187015,23.895803],"type":"Point"}
}