{
  "type": "Feature",
  "properties": {
    "iso:country":"IN",
    "ks:ks_name":"Pappakudi",
    "ks:ks_pop":70,
    "ks:ks_type":"HABITATION",
    "name:eng_x_preferred":[
        "Pappakudi"
    ],
    "wof:name":"Pappakudi",
    "wof:placetype":"locality",
    "wof:population":70
},
  "geometry": {"coordinates":[78.91187600000001,10.020775],"type":"Point"}
}