{
  "type": "Feature",
  "properties": {
    "iso:country":"IN",
    "ks:ks_name":"Parimuga",
    "ks:ks_pop":200,
    "ks:ks_type":"HABITATION",
    "name:eng_x_preferred":[
        "Parimuga"
    ],
    "wof:name":"Parimuga",
    "wof:placetype":"locality",
    "wof:population":200
},
  "geometry": {"coordinates":[75.185597,12.993263],"type":"Point"}
}