{
  "type": "Feature",
  "properties": {
    "iso:country":"IN",
    "ks:ks_alt_nam":"Hizim Angura II",
    "ks:ks_name":"Hizim Angura Ii",
    "ks:ks_pop":969,
    "ks:ks_type":"HABITATION",
    "name:eng_x_preferred":[
        "Hizim Angura Ii"
    ],
    "wof:name":"Hizim Angura Ii",
    "wof:placetype":"locality",
    "wof:population":969
},
  "geometry": {"coordinates":[92.312624,24.769983],"type":"Point"}
}