{
  "type": "Feature",
  "properties": {
    "iso:country":"IN",
    "ks:ks_name":"Damdarsai",
    "ks:ks_pop":476,
    "ks:ks_type":"VILLAGE",
    "name:eng_x_preferred":[
        "Damdarsai"
    ],
    "wof:name":"Damdarsai",
    "wof:placetype":"locality",
    "wof:population":476
},
  "geometry": {"coordinates":[85.850718,22.031311],"type":"Point"}
}