{
  "type": "Feature",
  "properties": {
    "iso:country":"IN",
    "ks:ks_name":"Idpe",
    "ks:ks_pop":111,
    "ks:ks_type":"VILLAGE",
    "name:eng_x_preferred":[
        "Idpe"
    ],
    "wof:name":"Idpe",
    "wof:placetype":"locality",
    "wof:population":111
},
  "geometry": {"coordinates":[87.739322,24.873908],"type":"Point"}
}