{
  "type": "Feature",
  "properties": {
    "iso:country":"IN",
    "ks:ks_name":"Bodireddikandriga",
    "ks:ks_pop":93,
    "ks:ks_type":"HABITATION",
    "name:eng_x_preferred":[
        "Bodireddikandriga"
    ],
    "wof:name":"Bodireddikandriga",
    "wof:placetype":"locality",
    "wof:population":93
},
  "geometry": {"coordinates":[79.10696,13.325783],"type":"Point"}
}