{
  "type": "Feature",
  "properties": {
    "iso:country":"IN",
    "ks:ks_name":"Ibarat Deeh",
    "ks:ks_pop":332,
    "ks:ks_type":"HABITATION",
    "name:eng_x_preferred":[
        "Ibarat Deeh"
    ],
    "wof:name":"Ibarat Deeh",
    "wof:placetype":"locality",
    "wof:population":332
},
  "geometry": {"coordinates":[82.910387,27.092601],"type":"Point"}
}