{
  "type": "Feature",
  "properties": {
    "gn:admin1_code":"2.0",
    "gn:admin2_code":"553.0",
    "gn:asciiname":"Kadirikuntlapalle",
    "gn:country_code":"IN",
    "gn:dem":527,
    "gn:feature_class":"P",
    "gn:feature_code":"PPL",
    "gn:name":"Kadirikuntlapalle",
    "gn:population":0,
    "gn:timezone":"Asia/Kolkata",
    "iso:country":"IN",
    "wof:name":"Kadirikuntlapalle",
    "wof:placetype":"locality"
},
  "geometry": {"coordinates":[78.16374,14.17286],"type":"Point"}
}