{
  "type": "Feature",
  "properties": {
    "iso:country":"IN",
    "ks:ks_alt_nam":"KAYAST TOLLA",
    "ks:ks_name":"Kayast Tolla",
    "ks:ks_pop":200,
    "ks:ks_type":"HABITATION",
    "ks:ks_uagg_main":0,
    "name:eng_x_preferred":[
        "Kayast Tolla"
    ],
    "wof:name":"Kayast Tolla",
    "wof:placetype":"neighbourhood",
    "wof:population":200
},
  "geometry": {"coordinates":[86.88748699999999,26.26495],"type":"Point"}
}