{
  "type": "Feature",
  "properties": {
    "gn:admin1_code":"16.0",
    "gn:admin2_code":"507.0",
    "gn:asciiname":"Karanji",
    "gn:country_code":"IN",
    "gn:dem":304,
    "gn:feature_class":"P",
    "gn:feature_code":"PPL",
    "gn:name":"Karanj\u012b",
    "gn:population":0,
    "gn:timezone":"Asia/Kolkata",
    "iso:country":"IN",
    "wof:name":"Karanji",
    "wof:placetype":"locality"
},
  "geometry": {"coordinates":[80.32311999999997,21.48344],"type":"Point"}
}