{
  "type": "Feature",
  "properties": {
    "iso:country":"IN",
    "ks:ks_name":"Bhos",
    "ks:ks_pop":518,
    "ks:ks_type":"VILLAGE",
    "name:eng_x_preferred":[
        "Bhos"
    ],
    "wof:name":"Bhos",
    "wof:placetype":"locality",
    "wof:population":518
},
  "geometry": {"coordinates":[82.707751,24.345584],"type":"Point"}
}