{
  "type": "Feature",
  "properties": {
    "iso:country":"IN",
    "ks:ks_name":"Bajau",
    "ks:ks_pop":250,
    "ks:ks_type":"HABITATION",
    "name:eng_x_preferred":[
        "Bajau"
    ],
    "wof:name":"Bajau",
    "wof:placetype":"locality",
    "wof:population":250
},
  "geometry": {"coordinates":[77.99113800000001,30.622656],"type":"Point"}
}