{
  "type": "Feature",
  "properties": {
    "iso:country":"IN",
    "ks:ks_name":"Naubasta",
    "ks:ks_pop":169,
    "ks:ks_type":"HABITATION",
    "ks:ks_uagg_main":0,
    "name:eng_x_preferred":[
        "Naubasta"
    ],
    "wof:name":"Naubasta",
    "wof:placetype":"neighbourhood",
    "wof:population":169
},
  "geometry": {"coordinates":[80.87027,26.372966],"type":"Point"}
}