{
  "type": "Feature",
  "properties": {
    "iso:country":"IN",
    "ks:ks_name":"Nakapara",
    "ks:ks_pop":262,
    "ks:ks_type":"HABITATION",
    "name:eng_x_preferred":[
        "Nakapara"
    ],
    "wof:name":"Nakapara",
    "wof:placetype":"locality",
    "wof:population":262
},
  "geometry": {"coordinates":[81.569851,19.08958],"type":"Point"}
}