{
  "type": "Feature",
  "properties": {
    "iso:country":"IN",
    "ks:ks_name":"Baswar Wasti",
    "ks:ks_pop":116,
    "ks:ks_type":"HABITATION",
    "name:eng_x_preferred":[
        "Baswar Wasti"
    ],
    "wof:name":"Baswar Wasti",
    "wof:placetype":"locality",
    "wof:population":116
},
  "geometry": {"coordinates":[75.98736599999999,18.785303],"type":"Point"}
}