{
  "type": "Feature",
  "properties": {
    "gn:admin1_code":"36",
    "gn:admin2_code":"200.0",
    "gn:asciiname":"Pagdihwa",
    "gn:country_code":"IN",
    "gn:dem":221,
    "gn:feature_class":"P",
    "gn:feature_code":"PPL",
    "gn:name":"Pagd\u012bhwa",
    "gn:population":0,
    "gn:timezone":"Asia/Kolkata",
    "iso:country":"IN",
    "ks:ks_alt_nam":"Pagd\u012bhwa",
    "ks:ks_name":"Pagdihwa",
    "ks:ks_type":"VILLAGE",
    "name:eng_x_preferred":[
        "Pagdihwa"
    ],
    "name:eng_x_variant":[
        "Pagd\u012bhwa"
    ],
    "wof:name":"Pagdihwa",
    "wof:placetype":"locality"
},
  "geometry": {"coordinates":[83.22808000000001,24.304352],"type":"Point"}
}