{
  "type": "Feature",
  "properties": {
    "iso:country":"IN",
    "ks:ks_name":"Sawal Deh East",
    "ks:ks_pop":1102,
    "ks:ks_type":"VILLAGE",
    "ks:ks_uagg_main":0,
    "name:eng_x_preferred":[
        "Sawal Deh East"
    ],
    "wof:name":"Sawal Deh East",
    "wof:placetype":"neighbourhood",
    "wof:population":1102
},
  "geometry": {"coordinates":[79.064014,29.400864],"type":"Point"}
}