{
  "type": "Feature",
  "properties": {
    "iso:country":"IN",
    "ks:ks_name":"Bahagadi",
    "ks:ks_pop":549,
    "ks:ks_type":"HABITATION",
    "name:eng_x_preferred":[
        "Bahagadi"
    ],
    "wof:name":"Bahagadi",
    "wof:placetype":"locality",
    "wof:population":549
},
  "geometry": {"coordinates":[87.05683500000001,21.839987],"type":"Point"}
}