{
  "type": "Feature",
  "properties": {
    "iso:country":"IN",
    "ks:ks_name":"Jadaput",
    "ks:ks_pop":91,
    "ks:ks_type":"VILLAGE",
    "name:eng_x_preferred":[
        "Jadaput"
    ],
    "wof:name":"Jadaput",
    "wof:placetype":"locality",
    "wof:population":91
},
  "geometry": {"coordinates":[83.193506,19.008142],"type":"Point"}
}