{
  "type": "Feature",
  "properties": {
    "iso:country":"IN",
    "ks:ks_name":"Titihichapar",
    "ks:ks_pop":292,
    "ks:ks_type":"VILLAGE",
    "name:eng_x_preferred":[
        "Titihichapar"
    ],
    "wof:name":"Titihichapar",
    "wof:placetype":"locality",
    "wof:population":292
},
  "geometry": {"coordinates":[86.57639399999999,24.194101],"type":"Point"}
}