{
  "type": "Feature",
  "properties": {
    "iso:country":"IN",
    "ks:ks_name":"Alamprabh",
    "ks:ks_pop":46,
    "ks:ks_type":"HABITATION",
    "name:eng_x_preferred":[
        "Alamprabh"
    ],
    "wof:name":"Alamprabh",
    "wof:placetype":"locality",
    "wof:population":46
},
  "geometry": {"coordinates":[75.674649,18.456866],"type":"Point"}
}