{
  "type": "Feature",
  "properties": {
    "iso:country":"IN",
    "ks:ks_alt_nam":"UTTAR MADHABDANGA",
    "ks:ks_name":"Uttar Madhabdanga",
    "ks:ks_pop":684,
    "ks:ks_type":"HABITATION",
    "name:eng_x_preferred":[
        "Uttar Madhabdanga"
    ],
    "wof:name":"Uttar Madhabdanga",
    "wof:placetype":"locality",
    "wof:population":684
},
  "geometry": {"coordinates":[88.802632,26.552055],"type":"Point"}
}