{
  "type": "Feature",
  "properties": {
    "gn:admin1_code":"19",
    "gn:admin2_code":"568.0",
    "gn:asciiname":"Kannikere",
    "gn:country_code":"IN",
    "gn:dem":574,
    "gn:feature_class":"P",
    "gn:feature_code":"PPL",
    "gn:name":"Kannikere",
    "gn:population":0,
    "gn:timezone":"Asia/Kolkata",
    "iso:country":"IN",
    "wof:name":"Kannikere",
    "wof:placetype":"locality"
},
  "geometry": {"coordinates":[74.96661,14.00718],"type":"Point"}
}