{
  "type": "Feature",
  "properties": {
    "iso:country":"IN",
    "ks:ks_name":"Chittamakki",
    "ks:ks_pop":22,
    "ks:ks_type":"HABITATION",
    "name:eng_x_preferred":[
        "Chittamakki"
    ],
    "wof:name":"Chittamakki",
    "wof:placetype":"locality",
    "wof:population":22
},
  "geometry": {"coordinates":[74.621357,14.990554],"type":"Point"}
}