{
  "type": "Feature",
  "properties": {
    "iso:country":"IN",
    "ks:ks_name":"Kariyannanahatty",
    "ks:ks_pop":249,
    "ks:ks_type":"HABITATION",
    "name:eng_x_preferred":[
        "Kariyannanahatty"
    ],
    "wof:name":"Kariyannanahatty",
    "wof:placetype":"locality",
    "wof:population":249
},
  "geometry": {"coordinates":[76.530091,13.957263],"type":"Point"}
}