{
  "type": "Feature",
  "properties": {
    "iso:country":"IN",
    "ks:ks_name":"Sullyody",
    "ks:ks_pop":150,
    "ks:ks_type":"HABITATION",
    "name:eng_x_preferred":[
        "Sullyody"
    ],
    "wof:name":"Sullyody",
    "wof:placetype":"locality",
    "wof:population":150
},
  "geometry": {"coordinates":[75.264436,13.053459],"type":"Point"}
}