{
  "type": "Feature",
  "properties": {
    "iso:country":"IN",
    "ks:ks_name":"Nani Singloti",
    "ks:ks_pop":1490,
    "ks:ks_type":"VILLAGE",
    "name:eng_x_preferred":[
        "Nani Singloti"
    ],
    "wof:name":"Nani Singloti",
    "wof:placetype":"locality",
    "wof:population":1490
},
  "geometry": {"coordinates":[73.655908,21.661564],"type":"Point"}
}