{
  "type": "Feature",
  "properties": {
    "iso:country":"IN",
    "ks:ks_alt_nam":"Math \u0100dam",
    "ks:ks_name":"Math Adam",
    "ks:ks_type":"VILLAGE",
    "name:eng_x_preferred":[
        "Math Adam"
    ],
    "name:eng_x_variant":[
        "Math \u0100dam"
    ],
    "wof:name":"Math Adam",
    "wof:placetype":"locality"
},
  "geometry": {"coordinates":[83.25243500000001,26.475485],"type":"Point"}
}