{
  "type": "Feature",
  "properties": {
    "gn:admin1_code":"09",
    "gn:admin2_code":"468.0",
    "gn:asciiname":"Mankuwa",
    "gn:country_code":"IN",
    "gn:dem":129,
    "gn:feature_class":"P",
    "gn:feature_code":"PPL",
    "gn:name":"M\u0101nkuwa",
    "gn:population":0,
    "gn:timezone":"Asia/Kolkata",
    "iso:country":"IN",
    "name:und_x_variant":[
        "Mankuva",
        "M\u0101nkuwa"
    ],
    "wof:name":"Mankuwa",
    "wof:placetype":"locality"
},
  "geometry": {"coordinates":[69.56758000000001,23.20986],"type":"Point"}
}