{
  "type": "Feature",
  "properties": {
    "gn:admin1_code":"37",
    "gn:admin2_code":"404.0",
    "gn:asciiname":"Ghanwara",
    "gn:country_code":"IN",
    "gn:dem":453,
    "gn:feature_class":"P",
    "gn:feature_code":"PPL",
    "gn:name":"Ghanw\u0101ra",
    "gn:population":0,
    "gn:timezone":"Asia/Kolkata",
    "iso:country":"IN",
    "ks:ks_name":"Ghanwara",
    "ks:ks_pop":201,
    "ks:ks_type":"VILLAGE",
    "name:eng_x_preferred":[
        "Ghanwara"
    ],
    "wof:name":"Ghanwara",
    "wof:placetype":"locality",
    "wof:population":201
},
  "geometry": {"coordinates":[82.183493,22.674389],"type":"Point"}
}