{
  "type": "Feature",
  "properties": {
    "iso:country":"IN",
    "ks:ks_name":"Teppagi",
    "ks:ks_pop":231,
    "ks:ks_type":"HABITATION",
    "name:eng_x_preferred":[
        "Teppagi"
    ],
    "wof:name":"Teppagi",
    "wof:placetype":"locality",
    "wof:population":231
},
  "geometry": {"coordinates":[74.691231,14.636881],"type":"Point"}
}