{
  "type": "Feature",
  "properties": {
    "gn:admin1_code":"25.0",
    "gn:admin2_code":"624.0",
    "gn:asciiname":"Rasivarai Tottam",
    "gn:country_code":"IN",
    "gn:dem":1179,
    "gn:feature_class":"P",
    "gn:feature_code":"PPL",
    "gn:name":"R\u0101sivarai Tottam",
    "gn:population":0,
    "gn:timezone":"Asia/Kolkata",
    "iso:country":"IN",
    "wof:name":"Rasivarai Tottam",
    "wof:placetype":"locality"
},
  "geometry": {"coordinates":[77.24713,10.05895],"type":"Point"}
}