{
  "type": "Feature",
  "properties": {
    "iso:country":"IN",
    "ks:ks_name":"Berdhana Mal.",
    "ks:ks_pop":241,
    "ks:ks_type":"VILLAGE",
    "name:eng_x_preferred":[
        "Berdhana Mal."
    ],
    "wof:name":"Berdhana Mal.",
    "wof:placetype":"locality",
    "wof:population":241
},
  "geometry": {"coordinates":[79.527507,23.462422],"type":"Point"}
}