{
  "type": "Feature",
  "properties": {
    "gn:admin1_code":"35.0",
    "gn:admin2_code":"423",
    "gn:asciiname":"Kankar",
    "gn:country_code":"IN",
    "gn:dem":398,
    "gn:feature_class":"P",
    "gn:feature_code":"PPL",
    "gn:name":"K\u0101nkar",
    "gn:population":0,
    "gn:timezone":"Asia/Kolkata",
    "iso:country":"IN",
    "name:deu_x_preferred":[
        "Kankar"
    ],
    "name:kan_x_preferred":[
        "\u0c95\u0c82\u0c95\u0cb0\u0ccd"
    ],
    "name:und_x_variant":[
        "K\u0101nkar",
        "Kh\u0101nkar"
    ],
    "wof:name":"Kankar",
    "wof:placetype":"locality"
},
  "geometry": {"coordinates":[77.73633000000002,25.5542],"type":"Point"}
}