{
  "type": "Feature",
  "properties": {
    "iso:country":"IN",
    "ks:ks_name":"Garbhudih Mal",
    "ks:ks_pop":513,
    "ks:ks_type":"VILLAGE",
    "name:eng_x_preferred":[
        "Garbhudih Mal"
    ],
    "wof:name":"Garbhudih Mal",
    "wof:placetype":"locality",
    "wof:population":513
},
  "geometry": {"coordinates":[87.20721,25.15176],"type":"Point"}
}