{
  "type": "Feature",
  "properties": {
    "iso:country":"IN",
    "ks:ks_name":"Bapusulewasti",
    "ks:ks_pop":150,
    "ks:ks_type":"HABITATION",
    "name:eng_x_preferred":[
        "Bapusulewasti"
    ],
    "wof:name":"Bapusulewasti",
    "wof:placetype":"locality",
    "wof:population":150
},
  "geometry": {"coordinates":[74.943905,17.680661],"type":"Point"}
}