{
  "type": "Feature",
  "properties": {
    "iso:country":"IN",
    "ks:ks_name":"Panjapadar",
    "ks:ks_pop":106,
    "ks:ks_type":"VILLAGE",
    "name:eng_x_preferred":[
        "Panjapadar"
    ],
    "wof:name":"Panjapadar",
    "wof:placetype":"locality",
    "wof:population":106
},
  "geometry": {"coordinates":[84.206469,20.273147],"type":"Point"}
}