{
  "type": "Feature",
  "properties": {
    "iso:country":"IN",
    "ks:ks_name":"Chak Sekhapur",
    "ks:ks_pop":543,
    "ks:ks_type":"HABITATION",
    "name:eng_x_preferred":[
        "Chak Sekhapur"
    ],
    "wof:name":"Chak Sekhapur",
    "wof:placetype":"locality",
    "wof:population":543
},
  "geometry": {"coordinates":[80.94641300000001,25.268393],"type":"Point"}
}