{
  "type": "Feature",
  "properties": {
    "iso:country":"IN",
    "ks:ks_name":"Bankata",
    "ks:ks_pop":398,
    "ks:ks_type":"HABITATION",
    "name:eng_x_preferred":[
        "Bankata"
    ],
    "wof:name":"Bankata",
    "wof:placetype":"locality",
    "wof:population":398
},
  "geometry": {"coordinates":[82.276117,27.685406],"type":"Point"}
}