{
  "type": "Feature",
  "properties": {
    "iso:country":"IN",
    "ks:ks_name":"Phulpur Pachhiari",
    "ks:ks_pop":675,
    "ks:ks_type":"VILLAGE",
    "name:eng_x_preferred":[
        "Phulpur Pachhiari"
    ],
    "wof:name":"Phulpur Pachhiari",
    "wof:placetype":"locality",
    "wof:population":675
},
  "geometry": {"coordinates":[87.543907,26.065398],"type":"Point"}
}