{
  "type": "Feature",
  "properties": {
    "iso:country":"IN",
    "ks:ks_name":"Moktarpur",
    "ks:ks_pop":992,
    "ks:ks_type":"VILLAGE",
    "name:eng_x_preferred":[
        "Moktarpur"
    ],
    "wof:name":"Moktarpur",
    "wof:placetype":"locality",
    "wof:population":992
},
  "geometry": {"coordinates":[88.55083500000001,23.870949],"type":"Point"}
}