{
  "type": "Feature",
  "properties": {
    "iso:country":"IN",
    "ks:ks_name":"Kendukhupuli",
    "ks:ks_pop":188,
    "ks:ks_type":"VILLAGE",
    "name:eng_x_preferred":[
        "Kendukhupuli"
    ],
    "wof:name":"Kendukhupuli",
    "wof:placetype":"locality",
    "wof:population":188
},
  "geometry": {"coordinates":[84.411395,21.061089],"type":"Point"}
}