{
  "type": "Feature",
  "properties": {
    "gn:admin1_code":"19.0",
    "gn:admin2_code":"577",
    "gn:asciiname":"Bhimanahalli",
    "gn:country_code":"IN",
    "gn:dem":771,
    "gn:feature_class":"P",
    "gn:feature_code":"PPL",
    "gn:name":"Bh\u012bmanahalli",
    "gn:population":0,
    "gn:timezone":"Asia/Kolkata",
    "iso:country":"IN",
    "name:und_x_variant":[
        "Bh\u016bnanahalli",
        "Bh\u012bmanahalli"
    ],
    "wof:name":"Bhimanahalli",
    "wof:placetype":"locality"
},
  "geometry": {"coordinates":[76.27766,12.18645],"type":"Point"}
}