{
  "type": "Feature",
  "properties": {
    "iso:country":"IN",
    "ks:ks_name":"Lankalagannavaram",
    "ks:ks_pop":5025,
    "ks:ks_type":"VILLAGE",
    "name:eng_x_preferred":[
        "Lankalagannavaram"
    ],
    "wof:name":"Lankalagannavaram",
    "wof:placetype":"locality",
    "wof:population":5025
},
  "geometry": {"coordinates":[81.864679,16.569017],"type":"Point"}
}