{
  "type": "Feature",
  "properties": {
    "iso:country":"IN",
    "ks:ks_name":"Marhi",
    "ks:ks_pop":48,
    "ks:ks_type":"HABITATION",
    "name:eng_x_preferred":[
        "Marhi"
    ],
    "wof:name":"Marhi",
    "wof:placetype":"locality",
    "wof:population":48
},
  "geometry": {"coordinates":[77.872992,27.654491],"type":"Point"}
}