{
  "type": "Feature",
  "properties": {
    "gn:admin1_code":"10.0",
    "gn:admin2_code":"069",
    "gn:asciiname":"Bir Firozri",
    "gn:country_code":"IN",
    "gn:dem":335,
    "gn:feature_class":"P",
    "gn:feature_code":"PPL",
    "gn:name":"B\u012br F\u012brozri",
    "gn:population":0,
    "gn:timezone":"Asia/Kolkata",
    "iso:country":"IN",
    "wof:name":"Bir Firozri",
    "wof:placetype":"locality"
},
  "geometry": {"coordinates":[76.934,30.60903],"type":"Point"}
}