{
  "type": "Feature",
  "properties": {
    "iso:country":"IN",
    "ks:ks_alt_nam":"Din tola",
    "ks:ks_name":"Din Tola",
    "ks:ks_pop":827,
    "ks:ks_type":"HABITATION",
    "name:eng_x_preferred":[
        "Din Tola"
    ],
    "wof:name":"Din Tola",
    "wof:placetype":"locality",
    "wof:population":827
},
  "geometry": {"coordinates":[86.460003,25.775534],"type":"Point"}
}