{
  "type": "Feature",
  "properties": {
    "gn:admin1_code":"36",
    "gn:admin2_code":"202.0",
    "gn:asciiname":"Inayatpur",
    "gn:country_code":"IN",
    "gn:dem":176,
    "gn:feature_class":"P",
    "gn:feature_code":"PPL",
    "gn:name":"In\u0101yatpur",
    "gn:population":0,
    "gn:timezone":"Asia/Kolkata",
    "iso:country":"IN",
    "name:und_x_variant":[
        "In\u0101yatpur",
        "Nagla S\u016bkha"
    ],
    "wof:name":"Inayatpur",
    "wof:placetype":"locality"
},
  "geometry": {"coordinates":[78.67985,27.87078],"type":"Point"}
}