{
  "type": "Feature",
  "properties": {
    "iso:country":"IN",
    "ks:ks_name":"Vader Faliya",
    "ks:ks_pop":742,
    "ks:ks_type":"HABITATION",
    "name:eng_x_preferred":[
        "Vader Faliya"
    ],
    "wof:name":"Vader Faliya",
    "wof:placetype":"locality",
    "wof:population":742
},
  "geometry": {"coordinates":[73.77815,22.875333],"type":"Point"}
}