{
  "type": "Feature",
  "properties": {
    "iso:country":"IN",
    "ks:ks_name":"Pedajojer",
    "ks:ks_pop":372,
    "ks:ks_type":"VILLAGE",
    "name:eng_x_preferred":[
        "Pedajojer"
    ],
    "wof:name":"Pedajojer",
    "wof:placetype":"locality",
    "wof:population":372
},
  "geometry": {"coordinates":[81.002252,18.843533],"type":"Point"}
}