{
  "type": "Feature",
  "properties": {
    "gn:admin1_code":"02",
    "gn:admin2_code":"550.0",
    "gn:asciiname":"Muttukuru",
    "gn:country_code":"IN",
    "gn:dem":11,
    "gn:feature_class":"P",
    "gn:feature_code":"PPL",
    "gn:name":"Muttuk\u016bru",
    "gn:population":0,
    "gn:timezone":"Asia/Kolkata",
    "iso:country":"IN",
    "name:und_x_variant":[
        "Muthukuru",
        "Muttuk\u016bru"
    ],
    "wof:name":"Muttukuru",
    "wof:placetype":"locality"
},
  "geometry": {"coordinates":[80.0949,14.29022],"type":"Point"}
}