{
  "type": "Feature",
  "properties": {
    "iso:country":"IN",
    "ks:ks_name":"Krishnadebpur",
    "ks:ks_pop":2728,
    "ks:ks_type":"VILLAGE",
    "name:eng_x_preferred":[
        "Krishnadebpur"
    ],
    "wof:name":"Krishnadebpur",
    "wof:placetype":"locality",
    "wof:population":2728
},
  "geometry": {"coordinates":[88.328115,22.165729],"type":"Point"}
}