{
  "type": "Feature",
  "properties": {
    "gn:admin1_code":"10",
    "gn:admin2_code":"87.0",
    "gn:asciiname":"Pratapbas",
    "gn:country_code":"IN",
    "gn:dem":192,
    "gn:feature_class":"P",
    "gn:feature_code":"PPL",
    "gn:name":"Prat\u0101pb\u0101s",
    "gn:population":0,
    "gn:timezone":"Asia/Kolkata",
    "iso:country":"IN",
    "wof:name":"Pratapbas",
    "wof:placetype":"locality"
},
  "geometry": {"coordinates":[77.06158000000001,27.9896],"type":"Point"}
}