{
  "type": "Feature",
  "properties": {
    "iso:country":"IN",
    "ks:ks_name":"Sinawariya",
    "ks:ks_pop":360,
    "ks:ks_type":"HABITATION",
    "name:eng_x_preferred":[
        "Sinawariya"
    ],
    "wof:name":"Sinawariya",
    "wof:placetype":"locality",
    "wof:population":360
},
  "geometry": {"coordinates":[71.746422,26.601014],"type":"Point"}
}