{
  "type": "Feature",
  "properties": {
    "iso:country":"IN",
    "ks:ks_name":"Madachegalu",
    "ks:ks_pop":75,
    "ks:ks_type":"HABITATION",
    "name:eng_x_preferred":[
        "Madachegalu"
    ],
    "wof:name":"Madachegalu",
    "wof:placetype":"locality",
    "wof:population":75
},
  "geometry": {"coordinates":[73.801722,15.796889],"type":"Point"}
}