{
  "type": "Feature",
  "properties": {
    "iso:country":"IN",
    "ks:ks_name":"Tiwari Pur",
    "ks:ks_pop":57,
    "ks:ks_type":"HABITATION",
    "name:eng_x_preferred":[
        "Tiwari Pur"
    ],
    "wof:name":"Tiwari Pur",
    "wof:placetype":"locality",
    "wof:population":57
},
  "geometry": {"coordinates":[81.801799,26.090075],"type":"Point"}
}