{
  "type": "Feature",
  "properties": {
    "iso:country":"IN",
    "ks:ks_name":"Nallasellipalayam",
    "ks:ks_pop":155,
    "ks:ks_type":"HABITATION",
    "name:eng_x_preferred":[
        "Nallasellipalayam"
    ],
    "wof:name":"Nallasellipalayam",
    "wof:placetype":"locality",
    "wof:population":155
},
  "geometry": {"coordinates":[78.172335,11.035675],"type":"Point"}
}