{
  "type": "Feature",
  "properties": {
    "iso:country":"IN",
    "ks:ks_name":"Munda Budri",
    "ks:ks_pop":96,
    "ks:ks_type":"HABITATION",
    "name:eng_x_preferred":[
        "Munda Budri"
    ],
    "wof:name":"Munda Budri",
    "wof:placetype":"locality",
    "wof:population":96
},
  "geometry": {"coordinates":[85.45535,23.262805],"type":"Point"}
}