{
  "type": "Feature",
  "properties": {
    "iso:country":"IN",
    "ks:ks_name":"Jamtiri",
    "ks:ks_pop":254,
    "ks:ks_type":"VILLAGE",
    "name:eng_x_preferred":[
        "Jamtiri"
    ],
    "wof:name":"Jamtiri",
    "wof:placetype":"locality",
    "wof:population":254
},
  "geometry": {"coordinates":[85.211181,22.584109],"type":"Point"}
}