{
  "type": "Feature",
  "properties": {
    "gn:admin1_code":"38",
    "gn:admin2_code":"346.0",
    "gn:asciiname":"Gonda",
    "gn:country_code":"IN",
    "gn:dem":242,
    "gn:feature_class":"P",
    "gn:feature_code":"PPL",
    "gn:name":"Gonda",
    "gn:population":0,
    "gn:timezone":"Asia/Kolkata",
    "iso:country":"IN",
    "ks:ks_name":"Gonda",
    "ks:ks_pop":3596,
    "ks:ks_type":"VILLAGE",
    "ks:ks_uagg_main":0,
    "name:ara_x_preferred":[
        "\u063a\u0648\u0646\u062f\u0627"
    ],
    "name:ben_bn_x_preferred":[
        "\u0997\u09cb\u09a3\u09cd\u09a1\u09be"
    ],
    "name:ben_in_x_preferred":[
        "\u0997\u09cb\u09a3\u09cd\u09a1\u09be"
    ],
    "name:bih_x_preferred":[
        "\u0917\u094b\u0902\u0921\u093e"
    ],
    "name:bpy_x_preferred":[
        "\u0997\u09cb\u09a8\u09cd\u09a6\u09be"
    ],
    "name:ceb_x_preferred":[
        "Gonda"
    ],
    "name:deu_x_preferred":[
        "Gonda"
    ],
    "name:eng_x_preferred":[
        "Gonda"
    ],
    "name:guj_x_preferred":[
        "\u0a97\u0acb\u0a82\u0aa1\u0abe"
    ],
    "name:hin_x_preferred":[
        "\u0917\u094b\u0902\u0921\u093e"
    ],
    "name:kan_x_preferred":[
        "\u0c97\u0cca\u0c82\u0ca1"
    ],
    "name:mal_x_preferred":[
        "\u0d17\u0d4b\u0d23\u0d4d\u0d1f"
    ],
    "name:mar_x_preferred":[
        "\u0917\u094b\u0902\u0921\u093e"
    ],
    "name:new_x_preferred":[
        "\u0917\u094b\u0902\u0921\u093e"
    ],
    "name:nld_x_preferred":[
        "Gonda"
    ],
    "name:pan_x_preferred":[
        "\u0a17\u0a4c\u0a02\u0a21\u0a3e"
    ],
    "name:pnb_x_preferred":[
        "\u06af\u0648\u0646\u0688\u06c1"
    ],
    "name:pol_x_preferred":[
        "Gonda"
    ],
    "name:por_x_preferred":[
        "Gonda"
    ],
    "name:swe_x_preferred":[
        "Gonda"
    ],
    "name:tam_x_preferred":[
        "\u0b95\u0bca\u0ba9\u0bcd\u0b9f\u0bbe"
    ],
    "name:tel_x_preferred":[
        "\u0c17\u0c4b\u0c02\u0c21\u0c3e"
    ],
    "name:urd_x_preferred":[
        "\u06af\u0648\u0646\u0688\u06c1"
    ],
    "wof:name":"Gonda",
    "wof:placetype":"neighbourhood",
    "wof:population":3596
},
  "geometry": {"coordinates":[83.691914,24.187494],"type":"Point"}
}