{
  "type": "Feature",
  "properties": {
    "iso:country":"IN",
    "ks:ks_name":"Isainagar No1",
    "ks:ks_pop":263,
    "ks:ks_type":"VILLAGE",
    "ks:ks_uagg_main":0,
    "name:eng_x_preferred":[
        "Isainagar No1"
    ],
    "wof:name":"Isainagar No1",
    "wof:placetype":"neighbourhood",
    "wof:population":263
},
  "geometry": {"coordinates":[79.426755,29.234741],"type":"Point"}
}