{
  "type": "Feature",
  "properties": {
    "gn:admin1_code":"37",
    "gn:admin2_code":"406.0",
    "gn:asciiname":"Sakola",
    "gn:country_code":"IN",
    "gn:dem":584,
    "gn:feature_class":"P",
    "gn:feature_code":"PPL",
    "gn:name":"Sakola",
    "gn:population":0,
    "gn:timezone":"Asia/Kolkata",
    "iso:country":"IN",
    "ks:ks_alt_nam":"SAKOLA",
    "ks:ks_name":"Sakola",
    "ks:ks_pop":1612,
    "ks:ks_type":"HABITATION",
    "name:eng_x_preferred":[
        "Sakola"
    ],
    "wof:name":"Sakola",
    "wof:placetype":"locality",
    "wof:population":1612
},
  "geometry": {"coordinates":[82.07278100000001,22.801152],"type":"Point"}
}