{
  "type": "Feature",
  "properties": {
    "gn:admin1_code":"11.0",
    "gn:admin2_code":"31.0",
    "gn:asciiname":"Hirti",
    "gn:country_code":"IN",
    "gn:dem":1719,
    "gn:feature_class":"P",
    "gn:feature_code":"PPL",
    "gn:name":"H\u012brti",
    "gn:population":0,
    "gn:timezone":"Asia/Kolkata",
    "iso:country":"IN",
    "wof:name":"Hirti",
    "wof:placetype":"locality"
},
  "geometry": {"coordinates":[77.11383000000002,30.98931],"type":"Point"}
}