{
  "type": "Feature",
  "properties": {
    "gn:admin1_code":"36.0",
    "gn:admin2_code":"165.0",
    "gn:asciiname":"Shaikhpur Buzurg",
    "gn:country_code":"IN",
    "gn:dem":145,
    "gn:feature_class":"P",
    "gn:feature_code":"PPL",
    "gn:name":"Shaikhpur Buzurg",
    "gn:population":0,
    "gn:timezone":"Asia/Kolkata",
    "iso:country":"IN",
    "wof:name":"Shaikhpur Buzurg",
    "wof:placetype":"locality"
},
  "geometry": {"coordinates":[79.37504,26.23229000000001],"type":"Point"}
}