{
  "type": "Feature",
  "properties": {
    "iso:country":"IN",
    "ks:ks_alt_nam":"Hindudara dukpamane dara",
    "ks:ks_name":"Hindudara Dukpamane Dara",
    "ks:ks_pop":507,
    "ks:ks_type":"HABITATION",
    "name:eng_x_preferred":[
        "Hindudara Dukpamane Dara"
    ],
    "wof:name":"Hindudara Dukpamane Dara",
    "wof:placetype":"locality",
    "wof:population":507
},
  "geometry": {"coordinates":[88.148259,26.998064],"type":"Point"}
}