{
  "type": "Feature",
  "properties": {
    "iso:country":"IN",
    "ks:ks_name":"Soykota Te",
    "ks:ks_pop":315,
    "ks:ks_type":"HABITATION",
    "ks:ks_uagg_main":0,
    "name:eng_x_preferred":[
        "Soykota Te"
    ],
    "wof:name":"Soykota Te",
    "wof:placetype":"neighbourhood",
    "wof:population":315
},
  "geometry": {"coordinates":[94.264921,26.652061],"type":"Point"}
}