{
  "type": "Feature",
  "properties": {
    "iso:country":"IN",
    "ks:ks_name":"Bhairam Pur",
    "ks:ks_pop":556,
    "ks:ks_type":"HABITATION",
    "name:eng_x_preferred":[
        "Bhairam Pur"
    ],
    "wof:name":"Bhairam Pur",
    "wof:placetype":"locality",
    "wof:population":556
},
  "geometry": {"coordinates":[81.720451,27.178239],"type":"Point"}
}