{
  "type": "Feature",
  "properties": {
    "iso:country":"IN",
    "ks:ks_name":"Echalakunte",
    "ks:ks_pop":83,
    "ks:ks_type":"HABITATION",
    "name:eng_x_preferred":[
        "Echalakunte"
    ],
    "wof:name":"Echalakunte",
    "wof:placetype":"locality",
    "wof:population":83
},
  "geometry": {"coordinates":[77.027309,13.397644],"type":"Point"}
}