{
  "type": "Feature",
  "properties": {
    "iso:country":"IN",
    "ks:ks_alt_nam":"Angalamman Kovil street",
    "ks:ks_name":"Angalamman Kovil Street",
    "ks:ks_pop":400,
    "ks:ks_type":"HABITATION",
    "name:eng_x_preferred":[
        "Angalamman Kovil Street"
    ],
    "wof:name":"Angalamman Kovil Street",
    "wof:placetype":"locality",
    "wof:population":400
},
  "geometry": {"coordinates":[79.728405,10.388287],"type":"Point"}
}