{
  "type": "Feature",
  "properties": {
    "iso:country":"IN",
    "ks:ks_name":"Baulewadi",
    "ks:ks_pop":106,
    "ks:ks_type":"HABITATION",
    "name:eng_x_preferred":[
        "Baulewadi"
    ],
    "wof:name":"Baulewadi",
    "wof:placetype":"locality",
    "wof:population":106
},
  "geometry": {"coordinates":[73.41519,18.262196],"type":"Point"}
}