{
  "type": "Feature",
  "properties": {
    "iso:country":"IN",
    "ks:ks_name":"Santos Jamadhar Para",
    "ks:ks_pop":72,
    "ks:ks_type":"HABITATION",
    "name:eng_x_preferred":[
        "Santos Jamadhar Para"
    ],
    "wof:name":"Santos Jamadhar Para",
    "wof:placetype":"locality",
    "wof:population":72
},
  "geometry": {"coordinates":[91.489232,23.963265],"type":"Point"}
}