{
  "type": "Feature",
  "properties": {
    "iso:country":"IN",
    "ks:ks_name":"Chaktamakgara",
    "ks:ks_pop":0,
    "ks:ks_type":"VILLAGE",
    "name:eng_x_preferred":[
        "Chaktamakgara"
    ],
    "wof:name":"Chaktamakgara",
    "wof:placetype":"locality",
    "wof:population":0
},
  "geometry": {"coordinates":[86.89366800000001,23.246365],"type":"Point"}
}