{
  "type": "Feature",
  "properties": {
    "iso:country":"IN",
    "ks:ks_alt_nam":"Dhakiabari supa",
    "ks:ks_name":"Dhakiabari Supa",
    "ks:ks_pop":214,
    "ks:ks_type":"HABITATION",
    "name:eng_x_preferred":[
        "Dhakiabari Supa"
    ],
    "wof:name":"Dhakiabari Supa",
    "wof:placetype":"locality",
    "wof:population":214
},
  "geometry": {"coordinates":[91.264163,26.706868],"type":"Point"}
}