{
  "type": "Feature",
  "properties": {
    "iso:country":"IN",
    "ks:ks_name":"Matwan",
    "ks:ks_pop":652,
    "ks:ks_type":"VILLAGE",
    "name:eng_x_preferred":[
        "Matwan"
    ],
    "wof:name":"Matwan",
    "wof:placetype":"locality",
    "wof:population":652
},
  "geometry": {"coordinates":[73.490234,18.075819],"type":"Point"}
}