{
  "type": "Feature",
  "properties": {
    "gn:admin1_code":"36",
    "gn:admin2_code":"175.0",
    "gn:asciiname":"Phaphamau",
    "gn:country_code":"IN",
    "gn:dem":97,
    "gn:feature_class":"P",
    "gn:feature_code":"PPL",
    "gn:name":"Ph\u0101ph\u0101mau",
    "gn:population":0,
    "gn:timezone":"Asia/Kolkata",
    "iso:country":"IN",
    "ks:ks_alt_nam":"phaphamau",
    "ks:ks_name":"Phaphamau",
    "ks:ks_pop":15,
    "ks:ks_type":"HABITATION",
    "name:eng_x_preferred":[
        "Phaphamau"
    ],
    "name:und_x_variant":[
        "Ph\u0101ph\u0101mau"
    ],
    "wof:name":"Phaphamau",
    "wof:placetype":"locality",
    "wof:population":15
},
  "geometry": {"coordinates":[81.84703,25.51574],"type":"Point"}
}