{
  "type": "Feature",
  "properties": {
    "iso:country":"IN",
    "ks:ks_name":"Chinanerallavalasa",
    "ks:ks_pop":138,
    "ks:ks_type":"HABITATION",
    "name:eng_x_preferred":[
        "Chinanerallavalasa"
    ],
    "wof:name":"Chinanerallavalasa",
    "wof:placetype":"locality",
    "wof:population":138
},
  "geometry": {"coordinates":[83.24171699999999,18.473118],"type":"Point"}
}