{
  "type": "Feature",
  "properties": {
    "gn:admin1_code":"11.0",
    "gn:admin2_code":"27.0",
    "gn:asciiname":"Shara",
    "gn:country_code":"IN",
    "gn:dem":1066,
    "gn:feature_class":"P",
    "gn:feature_code":"PPL",
    "gn:name":"Sh\u0101ra",
    "gn:population":0,
    "gn:timezone":"Asia/Kolkata",
    "iso:country":"IN",
    "name:ceb_x_preferred":[
        "Shara"
    ],
    "name:ita_x_preferred":[
        "Shara"
    ],
    "name:swe_x_preferred":[
        "Shara"
    ],
    "wof:name":"Shara",
    "wof:placetype":"locality"
},
  "geometry": {"coordinates":[77.18689999999999,31.70963],"type":"Point"}
}