{
  "type": "Feature",
  "properties": {
    "iso:country":"IN",
    "ks:ks_name":"Karbiland",
    "ks:ks_pop":176,
    "ks:ks_type":"HABITATION",
    "name:eng_x_preferred":[
        "Karbiland"
    ],
    "wof:name":"Karbiland",
    "wof:placetype":"locality",
    "wof:population":176
},
  "geometry": {"coordinates":[92.759432,25.031715],"type":"Point"}
}