{
  "type": "Feature",
  "properties": {
    "gn:admin1_code":"13",
    "gn:admin2_code":"596.0",
    "gn:asciiname":"Kuttampuzha",
    "gn:country_code":"IN",
    "gn:dem":48,
    "gn:feature_class":"P",
    "gn:feature_code":"PPL",
    "gn:name":"Kuttampuzha",
    "gn:population":25436,
    "gn:timezone":"Asia/Kolkata",
    "iso:country":"IN",
    "wof:name":"Kuttampuzha",
    "wof:placetype":"locality",
    "wof:population":25436
},
  "geometry": {"coordinates":[76.73544,10.15033],"type":"Point"}
}