{
  "type": "Feature",
  "properties": {
    "iso:country":"IN",
    "ks:ks_name":"Ayyavarikalva",
    "ks:ks_pop":9,
    "ks:ks_type":"HABITATION",
    "name:eng_x_preferred":[
        "Ayyavarikalva"
    ],
    "wof:name":"Ayyavarikalva",
    "wof:placetype":"locality",
    "wof:population":9
},
  "geometry": {"coordinates":[78.455427,13.523247],"type":"Point"}
}