{
  "type": "Feature",
  "properties": {
    "iso:country":"IN",
    "ks:ks_alt_nam":"BUBNALE VASTI",
    "ks:ks_name":"Bubnale Vasti",
    "ks:ks_pop":213,
    "ks:ks_type":"HABITATION",
    "name:eng_x_preferred":[
        "Bubnale Vasti"
    ],
    "wof:name":"Bubnale Vasti",
    "wof:placetype":"locality",
    "wof:population":213
},
  "geometry": {"coordinates":[74.73025,16.816703],"type":"Point"}
}