{
  "type": "Feature",
  "properties": {
    "gn:admin1_code":"36",
    "gn:admin2_code":"195.0",
    "gn:asciiname":"Hajipur Baresar",
    "gn:country_code":"IN",
    "gn:dem":75,
    "gn:feature_class":"P",
    "gn:feature_code":"PPL",
    "gn:name":"H\u0101j\u012bpur Baresar",
    "gn:population":0,
    "gn:timezone":"Asia/Kolkata",
    "iso:country":"IN",
    "ks:ks_name":"Hazipur Baresar",
    "ks:ks_pop":1166,
    "ks:ks_type":"VILLAGE",
    "name:eng_x_preferred":[
        "Hazipur Baresar"
    ],
    "name:eng_x_variant":[
        "Hajipur Baresar"
    ],
    "wof:name":"Hazipur Baresar",
    "wof:placetype":"locality",
    "wof:population":1166
},
  "geometry": {"coordinates":[83.747286,25.775858],"type":"Point"}
}