{
  "type": "Feature",
  "properties": {
    "iso:country":"IN",
    "ks:ks_name":"Neheremala",
    "ks:ks_pop":213,
    "ks:ks_type":"HABITATION",
    "ks:ks_uagg_main":0,
    "name:eng_x_preferred":[
        "Neheremala"
    ],
    "wof:name":"Neheremala",
    "wof:placetype":"neighbourhood",
    "wof:population":213
},
  "geometry": {"coordinates":[74.099126,19.131814],"type":"Point"}
}