{
  "type": "Feature",
  "properties": {
    "iso:country":"IN",
    "ks:ks_name":"Prayag Pur",
    "ks:ks_pop":334,
    "ks:ks_type":"HABITATION",
    "ks:ks_uagg_main":0,
    "name:eng_x_preferred":[
        "Prayag Pur"
    ],
    "wof:name":"Prayag Pur",
    "wof:placetype":"neighbourhood",
    "wof:population":334
},
  "geometry": {"coordinates":[85.52906,25.128043],"type":"Point"}
}