{
  "type": "Feature",
  "properties": {
    "iso:country":"IN",
    "ks:ks_name":"Kukripara",
    "ks:ks_pop":588,
    "ks:ks_type":"VILLAGE",
    "name:eng_x_preferred":[
        "Kukripara"
    ],
    "wof:name":"Kukripara",
    "wof:placetype":"locality",
    "wof:population":588
},
  "geometry": {"coordinates":[74.735314,23.215897],"type":"Point"}
}