{
  "type": "Feature",
  "properties": {
    "iso:country":"IN",
    "ks:ks_name":"Shekhpuri",
    "ks:ks_type":"VILLAGE",
    "ks:ks_uagg_main":0,
    "name:eng_x_preferred":[
        "Shekhpuri"
    ],
    "wof:name":"Shekhpuri",
    "wof:placetype":"neighbourhood"
},
  "geometry": {"coordinates":[77.872643,29.866279],"type":"Point"}
}