{
  "type": "Feature",
  "properties": {
    "gn:admin1_code":"19",
    "gn:admin2_code":"559.0",
    "gn:asciiname":"Sirvar",
    "gn:country_code":"IN",
    "gn:dem":418,
    "gn:feature_class":"P",
    "gn:feature_code":"PPL",
    "gn:name":"Sirv\u0101r",
    "gn:population":0,
    "gn:timezone":"Asia/Kolkata",
    "iso:country":"IN",
    "name:ceb_x_preferred":[
        "Sirv\u0101r"
    ],
    "name:swe_x_preferred":[
        "Sirv\u0101r"
    ],
    "name:und_x_variant":[
        "Sirwar",
        "Sirv\u0101r"
    ],
    "wof:name":"Sirvar",
    "wof:placetype":"locality"
},
  "geometry": {"coordinates":[77.02134000000002,16.17526],"type":"Point"}
}