{
  "type": "Feature",
  "properties": {
    "iso:country":"IN",
    "ks:ks_name":"Bhalukkhal",
    "ks:ks_pop":9,
    "ks:ks_type":"VILLAGE",
    "name:eng_x_preferred":[
        "Bhalukkhal"
    ],
    "wof:name":"Bhalukkhal",
    "wof:placetype":"locality",
    "wof:population":9
},
  "geometry": {"coordinates":[86.375614,23.046234],"type":"Point"}
}