{
  "type": "Feature",
  "properties": {
    "iso:country":"IN",
    "ks:ks_name":"Jhapahapara",
    "ks:ks_pop":53,
    "ks:ks_type":"HABITATION",
    "name:eng_x_preferred":[
        "Jhapahapara"
    ],
    "wof:name":"Jhapahapara",
    "wof:placetype":"locality",
    "wof:population":53
},
  "geometry": {"coordinates":[82.27122199999999,22.76792],"type":"Point"}
}