{
  "type": "Feature",
  "properties": {
    "iso:country":"IN",
    "ks:ks_name":"Varchiwadi",
    "ks:ks_pop":173,
    "ks:ks_type":"HABITATION",
    "name:eng_x_preferred":[
        "Varchiwadi"
    ],
    "wof:name":"Varchiwadi",
    "wof:placetype":"locality",
    "wof:population":173
},
  "geometry": {"coordinates":[73.55500000000001,17.361389],"type":"Point"}
}