{
  "type": "Feature",
  "properties": {
    "iso:country":"IN",
    "ks:ks_alt_nam":"NISHAN CH. PARA",
    "ks:ks_name":"Nishan Ch. Para",
    "ks:ks_pop":169,
    "ks:ks_type":"HABITATION",
    "name:eng_x_preferred":[
        "Nishan Ch. Para"
    ],
    "wof:name":"Nishan Ch. Para",
    "wof:placetype":"locality",
    "wof:population":169
},
  "geometry": {"coordinates":[91.718919,23.97684],"type":"Point"}
}