{
  "type": "Feature",
  "properties": {
    "gn:admin1_code":"12.0",
    "gn:asciiname":"Namb",
    "gn:country_code":"IN",
    "gn:dem":809,
    "gn:feature_class":"P",
    "gn:feature_code":"PPL",
    "gn:name":"Namb",
    "gn:population":0,
    "gn:timezone":"Asia/Kolkata",
    "iso:country":"IN",
    "wof:name":"Namb",
    "wof:placetype":"locality"
},
  "geometry": {"coordinates":[74.03321,33.25096],"type":"Point"}
}