{
  "type": "Feature",
  "properties": {
    "iso:country":"IN",
    "ks:ks_name":"Dumri",
    "ks:ks_pop":448,
    "ks:ks_type":"VILLAGE",
    "ks:ks_uagg_main":0,
    "name:eng_x_preferred":[
        "Dumri"
    ],
    "wof:name":"Dumri",
    "wof:placetype":"neighbourhood",
    "wof:population":448
},
  "geometry": {"coordinates":[84.99281000000001,24.271869],"type":"Point"}
}