{
  "type": "Feature",
  "properties": {
    "iso:country":"IN",
    "ks:ks_name":"Bandhanpada",
    "ks:ks_pop":33,
    "ks:ks_type":"HABITATION",
    "name:eng_x_preferred":[
        "Bandhanpada"
    ],
    "wof:name":"Bandhanpada",
    "wof:placetype":"locality",
    "wof:population":33
},
  "geometry": {"coordinates":[73.189517,19.637064],"type":"Point"}
}