{
  "type": "Feature",
  "properties": {
    "iso:country":"IN",
    "ks:ks_name":"Rongkhelan",
    "ks:ks_pop":292,
    "ks:ks_type":"HABITATION",
    "name:eng_x_preferred":[
        "Rongkhelan"
    ],
    "wof:name":"Rongkhelan",
    "wof:placetype":"locality",
    "wof:population":292
},
  "geometry": {"coordinates":[92.514458,25.657822],"type":"Point"}
}