{
  "type": "Feature",
  "properties": {
    "gn:admin1_code":"39.0",
    "gn:admin2_code":"060",
    "gn:asciiname":"Dawathara",
    "gn:country_code":"IN",
    "gn:dem":1185,
    "gn:feature_class":"P",
    "gn:feature_code":"PPL",
    "gn:name":"Daw\u0101thara",
    "gn:population":0,
    "gn:timezone":"Asia/Kolkata",
    "iso:country":"IN",
    "wof:name":"Dawathara",
    "wof:placetype":"locality"
},
  "geometry": {"coordinates":[77.93474999999999,30.45782],"type":"Point"}
}