{
  "type": "Feature",
  "properties": {
    "gn:admin1_code":"36.0",
    "gn:admin2_code":"177.0",
    "gn:asciiname":"Kuti",
    "gn:country_code":"IN",
    "gn:dem":108,
    "gn:feature_class":"P",
    "gn:feature_code":"PPL",
    "gn:name":"Kuti",
    "gn:population":0,
    "gn:timezone":"Asia/Kolkata",
    "iso:country":"IN",
    "name:bos_x_preferred":[
        "Kuti"
    ],
    "name:ceb_x_preferred":[
        "Kuti"
    ],
    "name:deu_x_preferred":[
        "Kuti"
    ],
    "name:fra_x_preferred":[
        "Kuti"
    ],
    "name:hrv_x_preferred":[
        "Kuti"
    ],
    "name:pol_x_preferred":[
        "Kuti"
    ],
    "name:rus_x_preferred":[
        "\u041a\u0443\u0442\u0438"
    ],
    "name:slv_x_preferred":[
        "Kuti"
    ],
    "name:srp_x_preferred":[
        "\u041a\u0443\u0442\u0438"
    ],
    "name:swe_x_preferred":[
        "Kuti"
    ],
    "wof:name":"Kuti",
    "wof:placetype":"locality"
},
  "geometry": {"coordinates":[82.00076999999997,26.74095],"type":"Point"}
}