{
  "type": "Feature",
  "properties": {
    "gn:admin1_code":"36.0",
    "gn:admin2_code":"193.0",
    "gn:asciiname":"Gangahra",
    "gn:country_code":"IN",
    "gn:dem":67,
    "gn:feature_class":"P",
    "gn:feature_code":"PPL",
    "gn:name":"Gangahra",
    "gn:population":0,
    "gn:timezone":"Asia/Kolkata",
    "iso:country":"IN",
    "ks:ks_name":"Gangahara",
    "ks:ks_pop":1748,
    "ks:ks_type":"VILLAGE",
    "name:eng_x_preferred":[
        "Gangahara"
    ],
    "name:eng_x_variant":[
        "Gangahra"
    ],
    "wof:name":"Gangahara",
    "wof:placetype":"locality",
    "wof:population":1748
},
  "geometry": {"coordinates":[84.084052,25.750483],"type":"Point"}
}