{
  "type": "Feature",
  "properties": {
    "iso:country":"IN",
    "ks:ks_name":"Dakshindih",
    "ks:ks_pop":768,
    "ks:ks_type":"VILLAGE",
    "ks:ks_uagg_main":0,
    "name:eng_x_preferred":[
        "Dakshindih"
    ],
    "wof:name":"Dakshindih",
    "wof:placetype":"neighbourhood",
    "wof:population":768
},
  "geometry": {"coordinates":[86.559821,24.11584],"type":"Point"}
}