{
  "type": "Feature",
  "properties": {
    "iso:country":"IN",
    "ks:ks_name":"Gosavi Wasti",
    "ks:ks_pop":591,
    "ks:ks_type":"HABITATION",
    "name:eng_x_preferred":[
        "Gosavi Wasti"
    ],
    "wof:name":"Gosavi Wasti",
    "wof:placetype":"locality",
    "wof:population":591
},
  "geometry": {"coordinates":[75.25500599999999,17.848796],"type":"Point"}
}