{
  "type": "Feature",
  "properties": {
    "iso:country":"IN",
    "ks:ks_name":"Phanshi",
    "ks:ks_pop":257,
    "ks:ks_type":"VILLAGE",
    "name:eng_x_preferred":[
        "Phanshi"
    ],
    "wof:name":"Phanshi",
    "wof:placetype":"locality",
    "wof:population":257
},
  "geometry": {"coordinates":[73.709362,18.260826],"type":"Point"}
}