{
  "type": "Feature",
  "properties": {
    "iso:country":"IN",
    "ks:ks_name":"Ramakrishnapuram",
    "ks:ks_pop":80,
    "ks:ks_type":"HABITATION",
    "ks:ks_uagg_main":0,
    "name:eng_x_preferred":[
        "Ramakrishnapuram"
    ],
    "wof:name":"Ramakrishnapuram",
    "wof:placetype":"neighbourhood",
    "wof:population":80
},
  "geometry": {"coordinates":[77.559743,8.491185],"type":"Point"}
}