{
  "type": "Feature",
  "properties": {
    "iso:country":"IN",
    "ks:ks_name":"Meleka Dhing",
    "ks:ks_pop":3960,
    "ks:ks_type":"VILLAGE",
    "name:eng_x_preferred":[
        "Meleka Dhing"
    ],
    "wof:name":"Meleka Dhing",
    "wof:placetype":"locality",
    "wof:population":3960
},
  "geometry": {"coordinates":[92.584298,26.467982],"type":"Point"}
}