{
  "type": "Feature",
  "properties": {
    "iso:country":"IN",
    "ks:ks_name":"Ippalachelaka",
    "ks:ks_pop":102,
    "ks:ks_type":"HABITATION",
    "name:eng_x_preferred":[
        "Ippalachelaka"
    ],
    "wof:name":"Ippalachelaka",
    "wof:placetype":"locality",
    "wof:population":102
},
  "geometry": {"coordinates":[80.470089,17.687989],"type":"Point"}
}