{
  "type": "Feature",
  "properties": {
    "iso:country":"IN",
    "ks:ks_name":"Madenahalli",
    "ks:ks_pop":1066,
    "ks:ks_type":"VILLAGE",
    "name:eng_x_preferred":[
        "Madenahalli"
    ],
    "wof:name":"Madenahalli",
    "wof:placetype":"locality",
    "wof:population":1066
},
  "geometry": {"coordinates":[76.846107,13.592402],"type":"Point"}
}