{
  "type": "Feature",
  "properties": {
    "gn:admin1_code":"35",
    "gn:admin2_code":"466.0",
    "gn:asciiname":"Sunud",
    "gn:country_code":"IN",
    "gn:dem":352,
    "gn:feature_class":"P",
    "gn:feature_code":"PPL",
    "gn:name":"Sun\u016bd",
    "gn:population":0,
    "gn:timezone":"Asia/Kolkata",
    "iso:country":"IN",
    "name:jpn_x_preferred":[
        "\u30b9\u30cb\u30c8"
    ],
    "name:rus_x_preferred":[
        "\u0421\u0443\u043d\u0438\u0442\u044b"
    ],
    "name:zho_x_preferred":[
        "\u82cf\u5c3c\u7279\u90e8"
    ],
    "wof:name":"Sunud",
    "wof:placetype":"locality"
},
  "geometry": {"coordinates":[76.23883000000002,21.84123],"type":"Point"}
}