{
  "type": "Feature",
  "properties": {
    "gn:admin1_code":"36",
    "gn:admin2_code":"194.0",
    "gn:asciiname":"Chak Inglis",
    "gn:country_code":"IN",
    "gn:dem":87,
    "gn:feature_class":"P",
    "gn:feature_code":"PPL",
    "gn:name":"Chak Inglis",
    "gn:population":0,
    "gn:timezone":"Asia/Kolkata",
    "iso:country":"IN",
    "name:und_x_variant":[
        "Chh\u0101ng\u0101pur",
        "\u0100lamsingh"
    ],
    "wof:name":"Chak Inglis",
    "wof:placetype":"locality"
},
  "geometry": {"coordinates":[82.6143,25.56201],"type":"Point"}
}