{
  "type": "Feature",
  "properties": {
    "iso:country":"IN",
    "ks:ks_name":"Jogipahari",
    "ks:ks_pop":162,
    "ks:ks_type":"VILLAGE",
    "name:eng_x_preferred":[
        "Jogipahari"
    ],
    "wof:name":"Jogipahari",
    "wof:placetype":"locality",
    "wof:population":162
},
  "geometry": {"coordinates":[86.902154,24.781543],"type":"Point"}
}