{
  "type": "Feature",
  "properties": {
    "iso:country":"IN",
    "ks:ks_name":"Mulampadam Jn",
    "ks:ks_pop":1489,
    "ks:ks_type":"HABITATION",
    "name:eng_x_preferred":[
        "Mulampadam Jn"
    ],
    "wof:name":"Mulampadam Jn",
    "wof:placetype":"locality",
    "wof:population":1489
},
  "geometry": {"coordinates":[76.703025,8.902639],"type":"Point"}
}