{
  "type": "Feature",
  "properties": {
    "iso:country":"IN",
    "ks:ks_name":"Rudrabhagahi",
    "ks:ks_pop":674,
    "ks:ks_type":"HABITATION",
    "name:eng_x_preferred":[
        "Rudrabhagahi"
    ],
    "wof:name":"Rudrabhagahi",
    "wof:placetype":"locality",
    "wof:population":674
},
  "geometry": {"coordinates":[82.671188,26.521897],"type":"Point"}
}