{
  "type": "Feature",
  "properties": {
    "iso:country":"IN",
    "ks:ks_name":"Padiapada",
    "ks:ks_pop":279,
    "ks:ks_type":"VILLAGE",
    "name:eng_x_preferred":[
        "Padiapada"
    ],
    "wof:name":"Padiapada",
    "wof:placetype":"locality",
    "wof:population":279
},
  "geometry": {"coordinates":[86.346542,21.079388],"type":"Point"}
}