{
  "type": "Feature",
  "properties": {
    "gn:admin1_code":"36",
    "gn:admin2_code":"154.0",
    "gn:asciiname":"Kunj Behari Purwa",
    "gn:country_code":"IN",
    "gn:dem":123,
    "gn:feature_class":"P",
    "gn:feature_code":"PPL",
    "gn:name":"Kunj Beh\u0101ri Purwa",
    "gn:population":0,
    "gn:timezone":"Asia/Kolkata",
    "iso:country":"IN",
    "wof:name":"Kunj Behari Purwa",
    "wof:placetype":"locality"
},
  "geometry": {"coordinates":[81.15312,27.56257],"type":"Point"}
}