{
  "type": "Feature",
  "properties": {
    "gn:admin1_code":"21.0",
    "gn:admin2_code":"390.0",
    "gn:asciiname":"Sana Maramang",
    "gn:country_code":"IN",
    "gn:dem":756,
    "gn:feature_class":"P",
    "gn:feature_code":"PPL",
    "gn:name":"S\u0101na Maramang",
    "gn:population":0,
    "gn:timezone":"Asia/Kolkata",
    "iso:country":"IN",
    "wof:name":"Sana Maramang",
    "wof:placetype":"locality"
},
  "geometry": {"coordinates":[83.87848000000002,19.80529],"type":"Point"}
}