{
  "type": "Feature",
  "properties": {
    "iso:country":"IN",
    "ks:ks_name":"Keshapura",
    "ks:ks_pop":95,
    "ks:ks_type":"HABITATION",
    "name:eng_x_preferred":[
        "Keshapura"
    ],
    "wof:name":"Keshapura",
    "wof:placetype":"locality",
    "wof:population":95
},
  "geometry": {"coordinates":[73.588917,23.463778],"type":"Point"}
}