{
  "type": "Feature",
  "properties": {
    "iso:country":"IN",
    "ks:ks_name":"Polio Nathuwala",
    "ks:ks_pop":1313,
    "ks:ks_type":"VILLAGE",
    "name:eng_x_preferred":[
        "Polio Nathuwala"
    ],
    "wof:name":"Polio Nathuwala",
    "wof:placetype":"locality",
    "wof:population":1313
},
  "geometry": {"coordinates":[77.902613,30.318447],"type":"Point"}
}