{
  "type": "Feature",
  "properties": {
    "iso:country":"IN",
    "ks:ks_alt_nam":"Eight hundred mile",
    "ks:ks_name":"Eight Hundred Mile",
    "ks:ks_pop":834,
    "ks:ks_type":"HABITATION",
    "name:eng_x_preferred":[
        "Eight Hundred Mile"
    ],
    "wof:name":"Eight Hundred Mile",
    "wof:placetype":"locality",
    "wof:population":834
},
  "geometry": {"coordinates":[76.84885199999999,9.438116],"type":"Point"}
}