{
  "type": "Feature",
  "properties": {
    "iso:country":"IN",
    "ks:ks_name":"Bilagaravally",
    "ks:ks_pop":314,
    "ks:ks_type":"HABITATION",
    "name:eng_x_preferred":[
        "Bilagaravally"
    ],
    "wof:name":"Bilagaravally",
    "wof:placetype":"locality",
    "wof:population":314
},
  "geometry": {"coordinates":[75.90177,13.018643],"type":"Point"}
}