{
  "type": "Feature",
  "properties": {
    "iso:country":"IN",
    "ks:ks_name":"Pacharlabai",
    "ks:ks_pop":211,
    "ks:ks_type":"HABITATION",
    "name:eng_x_preferred":[
        "Pacharlabai"
    ],
    "wof:name":"Pacharlabai",
    "wof:placetype":"locality",
    "wof:population":211
},
  "geometry": {"coordinates":[78.863939,17.396298],"type":"Point"}
}