{
  "type": "Feature",
  "properties": {
    "gn:admin1_code":"35.0",
    "gn:admin2_code":"427.0",
    "gn:asciiname":"Singhpur",
    "gn:country_code":"IN",
    "gn:dem":448,
    "gn:feature_class":"P",
    "gn:feature_code":"PPL",
    "gn:name":"Singhpur",
    "gn:population":0,
    "gn:timezone":"Asia/Kolkata",
    "iso:country":"IN",
    "wof:name":"Singhpur",
    "wof:placetype":"locality"
},
  "geometry": {"coordinates":[79.02195999999998,24.24971],"type":"Point"}
}