{
  "type": "Feature",
  "properties": {
    "gn:admin1_code":"10.0",
    "gn:admin2_code":"73.0",
    "gn:asciiname":"Gagarpur",
    "gn:country_code":"IN",
    "gn:dem":247,
    "gn:feature_class":"P",
    "gn:feature_code":"PPL",
    "gn:name":"Gagarpur",
    "gn:population":0,
    "gn:timezone":"Asia/Kolkata",
    "iso:country":"IN",
    "wof:name":"Gagarpur",
    "wof:placetype":"locality"
},
  "geometry": {"coordinates":[76.41023,30.13047000000001],"type":"Point"}
}