{
  "type": "Feature",
  "properties": {
    "iso:country":"IN",
    "ks:ks_name":"Kheriya Mritya",
    "ks:ks_pop":215,
    "ks:ks_type":"HABITATION",
    "name:eng_x_preferred":[
        "Kheriya Mritya"
    ],
    "wof:name":"Kheriya Mritya",
    "wof:placetype":"locality",
    "wof:population":215
},
  "geometry": {"coordinates":[78.110529,26.115972],"type":"Point"}
}