{
  "type": "Feature",
  "properties": {
    "iso:country":"IN",
    "ks:ks_name":"Sikdarpur",
    "ks:ks_pop":281,
    "ks:ks_type":"VILLAGE",
    "ks:ks_uagg_main":0,
    "name:eng_x_preferred":[
        "Sikdarpur"
    ],
    "wof:name":"Sikdarpur",
    "wof:placetype":"neighbourhood",
    "wof:population":281
},
  "geometry": {"coordinates":[86.315804,24.368669],"type":"Point"}
}