{
  "type": "Feature",
  "properties": {
    "iso:country":"IN",
    "ks:ks_alt_nam":"Sappaniparambu Reserved Forest",
    "ks:ks_name":"Sappaniparambu",
    "ks:ks_type":"VILLAGE",
    "name:eng_x_preferred":[
        "Sappaniparambu"
    ],
    "name:eng_x_variant":[
        "Sappaniparambu Reserved Forest"
    ],
    "wof:name":"Sappaniparambu",
    "wof:placetype":"locality"
},
  "geometry": {"coordinates":[77.523304,9.484159],"type":"Point"}
}