{
  "type": "Feature",
  "properties": {
    "iso:country":"IN",
    "ks:ks_name":"S Talapada",
    "ks:ks_pop":37,
    "ks:ks_type":"HABITATION",
    "name:eng_x_preferred":[
        "S Talapada"
    ],
    "wof:name":"S Talapada",
    "wof:placetype":"locality",
    "wof:population":37
},
  "geometry": {"coordinates":[84.458547,19.111852],"type":"Point"}
}