{
  "type": "Feature",
  "properties": {
    "iso:country":"IN",
    "ks:ks_name":"Sundar Bigha",
    "ks:ks_pop":223,
    "ks:ks_type":"HABITATION",
    "name:eng_x_preferred":[
        "Sundar Bigha"
    ],
    "wof:name":"Sundar Bigha",
    "wof:placetype":"locality",
    "wof:population":223
},
  "geometry": {"coordinates":[85.480728,25.216979],"type":"Point"}
}