{
  "type": "Feature",
  "properties": {
    "gn:admin1_code":"36",
    "gn:admin2_code":"186.0",
    "gn:asciiname":"Dihwapar",
    "gn:country_code":"IN",
    "gn:dem":86,
    "gn:feature_class":"P",
    "gn:feature_code":"PPL",
    "gn:name":"D\u012bhw\u0101p\u0101r",
    "gn:population":0,
    "gn:timezone":"Asia/Kolkata",
    "iso:country":"IN",
    "ks:ks_alt_nam":"D\u012bhw\u0101p\u0101r",
    "ks:ks_name":"Dihwapar",
    "ks:ks_type":"VILLAGE",
    "ks:ks_uagg_main":0,
    "name:eng_x_preferred":[
        "Dihwapar"
    ],
    "name:eng_x_variant":[
        "D\u012bhw\u0101p\u0101r"
    ],
    "wof:name":"Dihwapar",
    "wof:placetype":"neighbourhood"
},
  "geometry": {"coordinates":[83.02743700000001,26.819307],"type":"Point"}
}