{
  "type": "Feature",
  "properties": {
    "iso:country":"IN",
    "ks:ks_alt_nam":"RAIYA BASTI",
    "ks:ks_name":"Raiya Basti",
    "ks:ks_pop":460,
    "ks:ks_type":"HABITATION",
    "name:eng_x_preferred":[
        "Raiya Basti"
    ],
    "wof:name":"Raiya Basti",
    "wof:placetype":"locality",
    "wof:population":460
},
  "geometry": {"coordinates":[82.28510799999999,26.191411],"type":"Point"}
}