{
  "type": "Feature",
  "properties": {
    "iso:country":"IN",
    "ks:ks_name":"Bikrampur",
    "ks:ks_pop":1560,
    "ks:ks_type":"VILLAGE",
    "ks:ks_uagg_main":0,
    "name:eng_x_preferred":[
        "Bikrampur"
    ],
    "wof:name":"Bikrampur",
    "wof:placetype":"neighbourhood",
    "wof:population":1560
},
  "geometry": {"coordinates":[85.73319100000001,26.443381],"type":"Point"}
}