{
  "type": "Feature",
  "properties": {
    "iso:country":"IN",
    "ks:ks_name":"Unkla Tanda",
    "ks:ks_pop":201,
    "ks:ks_type":"HABITATION",
    "name:eng_x_preferred":[
        "Unkla Tanda"
    ],
    "wof:name":"Unkla Tanda",
    "wof:placetype":"locality",
    "wof:population":201
},
  "geometry": {"coordinates":[77.071822,18.824987],"type":"Point"}
}