{
  "type": "Feature",
  "properties": {
    "gn:admin1_code":"24.0",
    "gn:admin2_code":"102",
    "gn:asciiname":"Titarwali Dhani",
    "gn:country_code":"IN",
    "gn:dem":224,
    "gn:feature_class":"P",
    "gn:feature_code":"PPL",
    "gn:name":"Titarw\u0101li Dh\u0101ni",
    "gn:population":0,
    "gn:timezone":"Asia/Kolkata",
    "iso:country":"IN",
    "name:und_x_variant":[
        "Titarw\u0101li Dh\u0101ni",
        "Dh\u0101ni Tetarw\u0101l"
    ],
    "wof:name":"Titarwali Dhani",
    "wof:placetype":"neighbourhood"
},
  "geometry": {"coordinates":[74.62966,28.68204],"type":"Point"}
}