{
  "type": "Feature",
  "properties": {
    "iso:country":"IN",
    "ks:ks_name":"Noligwar",
    "ks:ks_pop":75,
    "ks:ks_type":"VILLAGE",
    "name:eng_x_preferred":[
        "Noligwar"
    ],
    "wof:name":"Noligwar",
    "wof:placetype":"locality",
    "wof:population":75
},
  "geometry": {"coordinates":[79.493199,30.480475],"type":"Point"}
}