{
  "type": "Feature",
  "properties": {
    "iso:country":"IN",
    "ks:ks_name":"Vellarvally",
    "ks:ks_pop":2230,
    "ks:ks_type":"VILLAGE",
    "name:eng_x_preferred":[
        "Vellarvally"
    ],
    "wof:name":"Vellarvally",
    "wof:placetype":"locality",
    "wof:population":2230
},
  "geometry": {"coordinates":[75.70912800000001,11.895862],"type":"Point"}
}