{
  "type": "Feature",
  "properties": {
    "iso:country":"IN",
    "ks:ks_name":"Raipal",
    "ks:ks_pop":125,
    "ks:ks_type":"VILLAGE",
    "name:eng_x_preferred":[
        "Raipal"
    ],
    "wof:name":"Raipal",
    "wof:placetype":"locality",
    "wof:population":125
},
  "geometry": {"coordinates":[86.980284,21.785091],"type":"Point"}
}