{
  "type": "Feature",
  "properties": {
    "gn:admin1_code":"35",
    "gn:admin2_code":"430.0",
    "gn:asciiname":"Barsaina",
    "gn:country_code":"IN",
    "gn:dem":110,
    "gn:feature_class":"P",
    "gn:feature_code":"PPL",
    "gn:name":"Barsaina",
    "gn:population":0,
    "gn:timezone":"Asia/Kolkata",
    "iso:country":"IN",
    "ks:ks_name":"Barsena",
    "ks:ks_pop":207,
    "ks:ks_type":"VILLAGE",
    "name:eng_x_preferred":[
        "Barsena"
    ],
    "name:eng_x_variant":[
        "Barsaina"
    ],
    "wof:name":"Barsena",
    "wof:placetype":"locality",
    "wof:population":207
},
  "geometry": {"coordinates":[81.573077,24.981982],"type":"Point"}
}