{
  "type": "Feature",
  "properties": {
    "iso:country":"IN",
    "ks:ks_name":"Dwariatan",
    "ks:ks_pop":1174,
    "ks:ks_type":"VILLAGE",
    "name:eng_x_preferred":[
        "Dwariatan"
    ],
    "wof:name":"Dwariatan",
    "wof:placetype":"locality",
    "wof:population":1174
},
  "geometry": {"coordinates":[88.330321,23.189192],"type":"Point"}
}