{
  "type": "Feature",
  "properties": {
    "gn:country":"IN",
    "gn:fcode":"PPL",
    "gn:pop":18298,
    "iso:country":"IN",
    "name:ben_x_preferred":[
        "\u09a6\u09be\u09ac\u09cb\u09b9"
    ],
    "name:bpy_x_preferred":[
        "\u09a6\u09be\u09ac\u09cb\u09b9"
    ],
    "name:bul_x_preferred":[
        "\u0414\u0430\u0431\u043e\u0445"
    ],
    "name:ceb_x_preferred":[
        "Daboh"
    ],
    "name:eng_x_preferred":[
        "Daboh"
    ],
    "name:fra_x_preferred":[
        "Daboh"
    ],
    "name:ita_x_preferred":[
        "Daboh"
    ],
    "name:msa_x_preferred":[
        "Daboh"
    ],
    "name:nan_x_preferred":[
        "Daboh"
    ],
    "name:new_x_preferred":[
        "\u0926\u092c\u094b\u0939"
    ],
    "name:nld_x_preferred":[
        "Daboh"
    ],
    "name:por_x_preferred":[
        "Daboh"
    ],
    "name:spa_x_preferred":[
        "Daboh"
    ],
    "name:swe_x_preferred":[
        "Daboh"
    ],
    "name:vie_x_preferred":[
        "Daboh"
    ],
    "name:zho_x_preferred":[
        "\u8fbe\u535a"
    ],
    "qs:name":"Daboh",
    "qs:photos_9r":0,
    "qs:photos_sr":0,
    "qs:pop_sr":"6",
    "wd:wordcount":142,
    "wof:name":"Daboh",
    "wof:placetype":"locality",
    "wof:population":18298
},
  "geometry": {"coordinates":[78.87658,26.00239],"type":"Point"}
}