{
  "type": "Feature",
  "properties": {
    "iso:country":"IN",
    "ks:ks_name":"Pathamanapuram",
    "ks:ks_pop":122,
    "ks:ks_type":"HABITATION",
    "name:eng_x_preferred":[
        "Pathamanapuram"
    ],
    "wof:name":"Pathamanapuram",
    "wof:placetype":"locality",
    "wof:population":122
},
  "geometry": {"coordinates":[83.659537,18.754702],"type":"Point"}
}