{
  "type": "Feature",
  "properties": {
    "gn:admin1_code":"25.0",
    "gn:admin2_code":"607.0",
    "gn:asciiname":"Poruvallur",
    "gn:country_code":"IN",
    "gn:dem":142,
    "gn:feature_class":"P",
    "gn:feature_code":"PPL",
    "gn:name":"Poruvall\u016br",
    "gn:population":0,
    "gn:timezone":"Asia/Kolkata",
    "iso:country":"IN",
    "ks:ks_name":"Poruvalur",
    "ks:ks_pop":2706,
    "ks:ks_type":"VILLAGE",
    "ks:ks_uagg_main":0,
    "name:eng_x_preferred":[
        "Poruvalur"
    ],
    "wof:name":"Poruvalur",
    "wof:placetype":"neighbourhood",
    "wof:population":2706
},
  "geometry": {"coordinates":[78.977001,12.056309],"type":"Point"}
}