{
  "type": "Feature",
  "properties": {
    "iso:country":"IN",
    "ks:ks_name":"Ratuakhera",
    "ks:ks_pop":0,
    "ks:ks_type":"VILLAGE",
    "name:eng_x_preferred":[
        "Ratuakhera"
    ],
    "wof:name":"Ratuakhera",
    "wof:placetype":"locality",
    "wof:population":0
},
  "geometry": {"coordinates":[80.608234,26.223791],"type":"Point"}
}