{
  "type": "Feature",
  "properties": {
    "gn:admin1_code":"16",
    "gn:admin2_code":"514.0",
    "gn:asciiname":"Mantha",
    "gn:country_code":"IN",
    "gn:dem":453,
    "gn:feature_class":"P",
    "gn:feature_code":"PPL",
    "gn:name":"Mantha",
    "gn:population":0,
    "gn:timezone":"Asia/Kolkata",
    "iso:country":"IN",
    "wof:name":"Mantha",
    "wof:placetype":"locality"
},
  "geometry": {"coordinates":[76.38715999999999,19.64937],"type":"Point"}
}