{
  "type": "Feature",
  "properties": {
    "iso:country":"IN",
    "ks:ks_name":"Kenduakhunta",
    "ks:ks_pop":117,
    "ks:ks_type":"VILLAGE",
    "name:eng_x_preferred":[
        "Kenduakhunta"
    ],
    "wof:name":"Kenduakhunta",
    "wof:placetype":"locality",
    "wof:population":117
},
  "geometry": {"coordinates":[86.664483,21.623736],"type":"Point"}
}