{
  "type": "Feature",
  "properties": {
    "gn:admin1_code":"9.0",
    "gn:admin2_code":"477",
    "gn:asciiname":"Khimrana",
    "gn:country_code":"IN",
    "gn:dem":20,
    "gn:feature_class":"P",
    "gn:feature_code":"PPL",
    "gn:name":"Khimrana",
    "gn:population":0,
    "gn:timezone":"Asia/Kolkata",
    "iso:country":"IN",
    "name:und_x_variant":[
        "Khimrara",
        "Khimrana"
    ],
    "wof:name":"Khimrana",
    "wof:placetype":"locality"
},
  "geometry": {"coordinates":[70.16592,22.47079],"type":"Point"}
}