{
  "type": "Feature",
  "properties": {
    "gn:admin1_code":"38",
    "gn:admin2_code":"358.0",
    "gn:asciiname":"Chhatwa",
    "gn:country_code":"IN",
    "gn:dem":251,
    "gn:feature_class":"P",
    "gn:feature_code":"PPL",
    "gn:name":"Chhatw\u0101",
    "gn:population":0,
    "gn:timezone":"Asia/Kolkata",
    "iso:country":"IN",
    "wof:name":"Chhatwa",
    "wof:placetype":"locality"
},
  "geometry": {"coordinates":[83.94494,23.99174],"type":"Point"}
}