{
  "type": "Feature",
  "properties": {
    "iso:country":"IN",
    "ks:ks_name":"Maankot",
    "ks:ks_pop":255,
    "ks:ks_type":"HABITATION",
    "name:eng_x_preferred":[
        "Maankot"
    ],
    "wof:name":"Maankot",
    "wof:placetype":"locality",
    "wof:population":255
},
  "geometry": {"coordinates":[81.26916300000001,19.942343],"type":"Point"}
}