{
  "type": "Feature",
  "properties": {
    "iso:country":"IN",
    "ks:ks_name":"Manapatti",
    "ks:ks_pop":155,
    "ks:ks_type":"HABITATION",
    "name:eng_x_preferred":[
        "Manapatti"
    ],
    "wof:name":"Manapatti",
    "wof:placetype":"locality",
    "wof:population":155
},
  "geometry": {"coordinates":[78.800032,10.343892],"type":"Point"}
}