{
  "type": "Feature",
  "properties": {
    "iso:country":"IN",
    "ks:ks_name":"Aparia",
    "ks:ks_pop":3920,
    "ks:ks_type":"VILLAGE",
    "name:eng_x_preferred":[
        "Aparia"
    ],
    "wof:name":"Aparia",
    "wof:placetype":"locality",
    "wof:population":3920
},
  "geometry": {"coordinates":[91.95673499999999,26.298256],"type":"Point"}
}