{
  "type": "Feature",
  "properties": {
    "iso:country":"IN",
    "ks:ks_alt_nam":"B\u0101gharpali",
    "ks:ks_name":"Bagharpali",
    "ks:ks_pop":61,
    "ks:ks_type":"VILLAGE",
    "name:eng_x_preferred":[
        "Bagharpali"
    ],
    "name:eng_x_variant":[
        "B\u0101gharpali"
    ],
    "wof:name":"Bagharpali",
    "wof:placetype":"locality",
    "wof:population":61
},
  "geometry": {"coordinates":[84.2955,20.963917],"type":"Point"}
}