{
  "type": "Feature",
  "properties": {
    "iso:country":"IN",
    "ks:ks_name":"Maj Tongia Gaon",
    "ks:ks_pop":142,
    "ks:ks_type":"HABITATION",
    "name:eng_x_preferred":[
        "Maj Tongia Gaon"
    ],
    "wof:name":"Maj Tongia Gaon",
    "wof:placetype":"locality",
    "wof:population":142
},
  "geometry": {"coordinates":[94.95899300000001,26.97079],"type":"Point"}
}