{
  "type": "Feature",
  "properties": {
    "iso:country":"IN",
    "ks:ks_name":"Tenginkeri",
    "ks:ks_pop":181,
    "ks:ks_type":"HABITATION",
    "name:eng_x_preferred":[
        "Tenginkeri"
    ],
    "wof:name":"Tenginkeri",
    "wof:placetype":"locality",
    "wof:population":181
},
  "geometry": {"coordinates":[74.810616,15.06244],"type":"Point"}
}