{
  "type": "Feature",
  "properties": {
    "gn:admin1_code":"23",
    "gn:admin2_code":"38.0",
    "gn:asciiname":"Budhaya",
    "gn:country_code":"IN",
    "gn:dem":235,
    "gn:feature_class":"P",
    "gn:feature_code":"PPL",
    "gn:name":"Budh\u0101ya",
    "gn:population":0,
    "gn:timezone":"Asia/Kolkata",
    "iso:country":"IN",
    "wof:name":"Budhaya",
    "wof:placetype":"locality"
},
  "geometry": {"coordinates":[75.57021,31.86707],"type":"Point"}
}