{
  "type": "Feature",
  "properties": {
    "iso:country":"IN",
    "ks:ks_name":"Hanumanthanapalya",
    "ks:ks_pop":87,
    "ks:ks_type":"HABITATION",
    "name:eng_x_preferred":[
        "Hanumanthanapalya"
    ],
    "wof:name":"Hanumanthanapalya",
    "wof:placetype":"locality",
    "wof:population":87
},
  "geometry": {"coordinates":[77.180761,13.098843],"type":"Point"}
}