{
  "type": "Feature",
  "properties": {
    "iso:country":"IN",
    "ks:ks_name":"Mohalla",
    "ks:ks_pop":582,
    "ks:ks_type":"HABITATION",
    "name:eng_x_preferred":[
        "Mohalla"
    ],
    "wof:name":"Mohalla",
    "wof:placetype":"locality",
    "wof:population":582
},
  "geometry": {"coordinates":[73.5025,17.53],"type":"Point"}
}