{
  "type": "Feature",
  "properties": {
    "gn:admin1_code":"36.0",
    "gn:admin2_code":"183.0",
    "gn:asciiname":"Thakur",
    "gn:country_code":"IN",
    "gn:dem":109,
    "gn:feature_class":"P",
    "gn:feature_code":"PPL",
    "gn:name":"Th\u0101kur",
    "gn:population":0,
    "gn:timezone":"Asia/Kolkata",
    "iso:country":"IN",
    "name:ben_x_preferred":[
        "\u09a0\u09be\u0995\u09c1\u09b0"
    ],
    "name:deu_x_preferred":[
        "Thakur"
    ],
    "name:pol_x_preferred":[
        "Thakur"
    ],
    "name:spa_x_preferred":[
        "Thakur"
    ],
    "wof:name":"Thakur",
    "wof:placetype":"neighbourhood"
},
  "geometry": {"coordinates":[81.61767,27.10247],"type":"Point"}
}