{
  "type": "Feature",
  "properties": {
    "iso:country":"IN",
    "ks:ks_name":"Mahulia",
    "ks:ks_pop":1201,
    "ks:ks_type":"VILLAGE",
    "ks:ks_uagg_main":0,
    "name:eng_x_preferred":[
        "Mahulia"
    ],
    "wof:name":"Mahulia",
    "wof:placetype":"neighbourhood",
    "wof:population":1201
},
  "geometry": {"coordinates":[87.175315,21.797567],"type":"Point"}
}