{
  "type": "Feature",
  "properties": {
    "gn:admin1_code":"16.0",
    "gn:admin2_code":"529.0",
    "gn:asciiname":"Kumbharvada",
    "gn:country_code":"IN",
    "gn:dem":45,
    "gn:feature_class":"P",
    "gn:feature_code":"PPL",
    "gn:name":"Kumbh\u0101rv\u0101da",
    "gn:population":0,
    "gn:timezone":"Asia/Kolkata",
    "iso:country":"IN",
    "wof:name":"Kumbharvada",
    "wof:placetype":"locality"
},
  "geometry": {"coordinates":[74.05306999999998,15.62625],"type":"Point"}
}