{
  "type": "Feature",
  "properties": {
    "iso:country":"IN",
    "ks:ks_name":"Chinnareddygaripalli",
    "ks:ks_pop":77,
    "ks:ks_type":"HABITATION",
    "name:eng_x_preferred":[
        "Chinnareddygaripalli"
    ],
    "wof:name":"Chinnareddygaripalli",
    "wof:placetype":"locality",
    "wof:population":77
},
  "geometry": {"coordinates":[78.913495,14.19443],"type":"Point"}
}