{
  "type": "Feature",
  "properties": {
    "gn:admin1_code":"13.0",
    "gn:admin2_code":"588.0",
    "gn:asciiname":"Nettanige",
    "gn:country_code":"IN",
    "gn:dem":133,
    "gn:feature_class":"P",
    "gn:feature_code":"PPLL",
    "gn:name":"Nettanige",
    "gn:population":0,
    "gn:timezone":"Asia/Kolkata",
    "iso:country":"IN",
    "name:mal_x_preferred":[
        "\u0d28\u0d46\u0d1f\u0d4d\u0d1f\u0d23\u0d3f\u0d17\u0d46"
    ],
    "wof:name":"Nettanige",
    "wof:placetype":"locality"
},
  "geometry": {"coordinates":[75.18434999999999,12.6058],"type":"Point"}
}