{
  "type": "Feature",
  "properties": {
    "gn:admin1_code":"13.0",
    "gn:admin2_code":"588.0",
    "gn:asciiname":"Nettanige",
    "gn:country_code":"IN",
    "gn:dem":133,
    "gn:feature_class":"P",
    "gn:feature_code":"PPLL",
    "gn:name":"Nettanige",
    "gn:population":0,
    "gn:timezone":"Asia/Kolkata",
    "iso:country":"IN",
    "ks:ks_name":"Nettanige",
    "ks:ks_pop":1273,
    "ks:ks_type":"VILLAGE",
    "name:eng_x_preferred":[
        "Nettanige"
    ],
    "name:mal_x_preferred":[
        "\u0d28\u0d46\u0d1f\u0d4d\u0d1f\u0d23\u0d3f\u0d17\u0d46"
    ],
    "wof:name":"Nettanige",
    "wof:placetype":"locality",
    "wof:population":1273
},
  "geometry": {"coordinates":[75.192421,12.601772],"type":"Point"}
}