{
  "type": "Feature",
  "properties": {
    "iso:country":"IN",
    "ks:ks_name":"Haldauni",
    "ks:ks_pop":1789,
    "ks:ks_type":"VILLAGE",
    "ks:ks_uagg_main":0,
    "name:eng_x_preferred":[
        "Haldauni"
    ],
    "wof:name":"Haldauni",
    "wof:placetype":"neighbourhood",
    "wof:population":1789
},
  "geometry": {"coordinates":[77.439885,28.539889],"type":"Point"}
}