{
  "type": "Feature",
  "properties": {
    "gn:admin1_code":"36",
    "gn:admin2_code":"168.0",
    "gn:asciiname":"Jamangawan",
    "gn:country_code":"IN",
    "gn:dem":148,
    "gn:feature_class":"P",
    "gn:feature_code":"PPL",
    "gn:name":"Jamangaw\u0101n",
    "gn:population":0,
    "gn:timezone":"Asia/Kolkata",
    "iso:country":"IN",
    "ks:ks_alt_nam":"Jamangaw\u0101n",
    "ks:ks_name":"Jamangawan",
    "ks:ks_type":"VILLAGE",
    "name:eng_x_preferred":[
        "Jamangawan"
    ],
    "name:eng_x_variant":[
        "Jamangaw\u0101n"
    ],
    "wof:name":"Jamangawan",
    "wof:placetype":"locality"
},
  "geometry": {"coordinates":[79.53989,25.751692],"type":"Point"}
}