{
  "type": "Feature",
  "properties": {
    "gn:country":"IN",
    "gn:fcode":"PPL",
    "gn:pop":19402,
    "iso:country":"IN",
    "name:ben_x_preferred":[
        "\u09b8\u09bf\u0999\u09cd\u0997\u09c1\u09b0"
    ],
    "name:bpy_x_preferred":[
        "\u09b8\u09bf\u0999\u09cd\u0997\u09c1\u09b0"
    ],
    "name:bul_x_preferred":[
        "\u0421\u0438\u043d\u0433\u0443\u0440"
    ],
    "name:chi_x_preferred":[
        "\u8f9b\u683c\u4e4c\u5c14"
    ],
    "name:dut_x_preferred":[
        "Singur"
    ],
    "name:eng_x_preferred":[
        "Singur"
    ],
    "name:fre_x_preferred":[
        "Singur"
    ],
    "name:hif_x_preferred":[
        "Singur"
    ],
    "name:hin_x_preferred":[
        "\u0938\u093f\u0902\u0917\u0942\u0930"
    ],
    "name:ind_x_preferred":[
        "Singur"
    ],
    "name:ita_x_preferred":[
        "Singur"
    ],
    "name:jpn_x_preferred":[
        "\u30b7\u30f3\u30b0\u30eb"
    ],
    "name:may_x_preferred":[
        "Singur"
    ],
    "name:nan_x_preferred":[
        "Singur"
    ],
    "name:por_x_preferred":[
        "Singur"
    ],
    "name:swe_x_preferred":[
        "Singur"
    ],
    "name:vie_x_preferred":[
        "Singur"
    ],
    "qs:name":"Singur",
    "qs:name_adm0":"India",
    "qs:name_adm1":"West Bengal",
    "qs:photos":24,
    "qs:photos_1k":5,
    "qs:photos_9k":1,
    "qs:photos_9r":2,
    "qs:photos_all":59,
    "qs:photos_sr":1,
    "qs:placetype":"Town",
    "qs:pop_sr":"6",
    "wd:wordcount":457,
    "wof:name":"Singur",
    "wof:placetype":"locality",
    "wof:population":19402
},
  "geometry": {"coordinates":[88.22944,22.80917],"type":"Point"}
}