{
  "type": "Feature",
  "properties": {
    "gn:admin1_code":"28.0",
    "gn:admin2_code":"330.0",
    "gn:asciiname":"Balanja",
    "gn:country_code":"IN",
    "gn:dem":50,
    "gn:feature_class":"P",
    "gn:feature_code":"PPL",
    "gn:name":"Balanja",
    "gn:population":0,
    "gn:timezone":"Asia/Kolkata",
    "iso:country":"IN",
    "wof:name":"Balanja",
    "wof:placetype":"neighbourhood"
},
  "geometry": {"coordinates":[87.98813,26.0191],"type":"Point"}
}