{
  "type": "Feature",
  "properties": {
    "iso:country":"IN",
    "ks:ks_name":"Harijanavada",
    "ks:ks_pop":82,
    "ks:ks_type":"HABITATION",
    "name:eng_x_preferred":[
        "Harijanavada"
    ],
    "wof:name":"Harijanavada",
    "wof:placetype":"locality",
    "wof:population":82
},
  "geometry": {"coordinates":[83.497474,17.94167],"type":"Point"}
}