{
  "type": "Feature",
  "properties": {
    "iso:country":"IN",
    "ks:ks_name":"Naigaon",
    "ks:ks_pop":290,
    "ks:ks_type":"VILLAGE",
    "ks:ks_uagg_main":0,
    "name:eng_x_preferred":[
        "Naigaon"
    ],
    "wof:name":"Naigaon",
    "wof:placetype":"neighbourhood",
    "wof:population":290
},
  "geometry": {"coordinates":[85.650451,21.647309],"type":"Point"}
}