{
  "type": "Feature",
  "properties": {
    "iso:country":"IN",
    "ks:ks_name":"Dangaewadi",
    "ks:ks_pop":426,
    "ks:ks_type":"HABITATION",
    "name:eng_x_preferred":[
        "Dangaewadi"
    ],
    "wof:name":"Dangaewadi",
    "wof:placetype":"locality",
    "wof:population":426
},
  "geometry": {"coordinates":[75.162947,19.211196],"type":"Point"}
}