{
  "type": "Feature",
  "properties": {
    "iso:country":"IN",
    "ks:ks_name":"Kanakapur",
    "ks:ks_pop":23,
    "ks:ks_type":"VILLAGE",
    "name:eng_x_preferred":[
        "Kanakapur"
    ],
    "wof:name":"Kanakapur",
    "wof:placetype":"locality",
    "wof:population":23
},
  "geometry": {"coordinates":[86.842562,20.598811],"type":"Point"}
}