{
  "type": "Feature",
  "properties": {
    "gn:admin1_code":"40.0",
    "gn:admin2_code":"532.0",
    "gn:asciiname":"Langampalli",
    "gn:country_code":"IN",
    "gn:dem":128,
    "gn:feature_class":"P",
    "gn:feature_code":"PPL",
    "gn:name":"Langampalli",
    "gn:population":0,
    "gn:timezone":"Asia/Kolkata",
    "iso:country":"IN",
    "ks:ks_name":"Lingampalle",
    "ks:ks_pop":263,
    "ks:ks_type":"VILLAGE",
    "name:eng_x_preferred":[
        "Lingampalle"
    ],
    "name:eng_x_variant":[
        "Langampalli"
    ],
    "wof:name":"Lingampalle",
    "wof:placetype":"locality",
    "wof:population":263
},
  "geometry": {"coordinates":[79.733254,18.834462],"type":"Point"}
}