{
  "type": "Feature",
  "properties": {
    "iso:country":"IN",
    "ks:ks_name":"Vangalapuram",
    "ks:ks_pop":450,
    "ks:ks_type":"HABITATION",
    "name:eng_x_preferred":[
        "Vangalapuram"
    ],
    "wof:name":"Vangalapuram",
    "wof:placetype":"locality",
    "wof:population":450
},
  "geometry": {"coordinates":[77.930137,10.60444],"type":"Point"}
}