{
  "type": "Feature",
  "properties": {
    "iso:country":"IN",
    "ks:ks_name":"Sundharemukku",
    "ks:ks_pop":150,
    "ks:ks_type":"HABITATION",
    "name:eng_x_preferred":[
        "Sundharemukku"
    ],
    "wof:name":"Sundharemukku",
    "wof:placetype":"locality",
    "wof:population":150
},
  "geometry": {"coordinates":[76.90339,8.645558],"type":"Point"}
}