{
  "type": "Feature",
  "properties": {
    "gn:admin1_code":"24.0",
    "gn:admin2_code":"111.0",
    "gn:asciiname":"Athidhanji ki Dhani",
    "gn:country_code":"IN",
    "gn:dem":306,
    "gn:feature_class":"P",
    "gn:feature_code":"PPL",
    "gn:name":"Athidh\u0101nji ki Dh\u0101ni",
    "gn:population":0,
    "gn:timezone":"Asia/Kolkata",
    "iso:country":"IN",
    "name:und_x_variant":[
        "Athidh\u0101nji ki Dh\u0101ni",
        "Ath\u012bdh\u0101nji ki Dh\u0101ni"
    ],
    "wof:name":"Athidhanji ki Dhani",
    "wof:placetype":"locality"
},
  "geometry": {"coordinates":[74.88724000000001,28.11208],"type":"Point"}
}