{
  "type": "Feature",
  "properties": {
    "iso:country":"IN",
    "ks:ks_name":"Irpaguda Rajuguda",
    "ks:ks_pop":60,
    "ks:ks_type":"HABITATION",
    "name:eng_x_preferred":[
        "Irpaguda Rajuguda"
    ],
    "wof:name":"Irpaguda Rajuguda",
    "wof:placetype":"locality",
    "wof:population":60
},
  "geometry": {"coordinates":[79.217017,19.075068],"type":"Point"}
}