{
  "type": "Feature",
  "properties": {
    "iso:country":"IN",
    "ks:ks_name":"Nishchalpur",
    "ks:ks_pop":408,
    "ks:ks_type":"HABITATION",
    "name:eng_x_preferred":[
        "Nishchalpur"
    ],
    "wof:name":"Nishchalpur",
    "wof:placetype":"locality",
    "wof:population":408
},
  "geometry": {"coordinates":[82.423652,27.436545],"type":"Point"}
}