{
  "type": "Feature",
  "properties": {
    "gn:admin1_code":"28.0",
    "gn:admin2_code":"332.0",
    "gn:asciiname":"Chandipura",
    "gn:country_code":"IN",
    "gn:dem":32,
    "gn:feature_class":"P",
    "gn:feature_code":"PPL",
    "gn:name":"Chand\u012bpura",
    "gn:population":0,
    "gn:timezone":"Asia/Kolkata",
    "iso:country":"IN",
    "wof:name":"Chandipura",
    "wof:placetype":"locality"
},
  "geometry": {"coordinates":[87.88573000000002,25.5013],"type":"Point"}
}