{
  "type": "Feature",
  "properties": {
    "gn:admin1_code":"24",
    "gn:admin2_code":"123.0",
    "gn:asciiname":"Mokhampura",
    "gn:country_code":"IN",
    "gn:dem":588,
    "gn:feature_class":"P",
    "gn:feature_code":"PPL",
    "gn:name":"Mokhampura",
    "gn:population":0,
    "gn:timezone":"Asia/Kolkata",
    "iso:country":"IN",
    "ks:ks_name":"Mokhampura",
    "ks:ks_pop":859,
    "ks:ks_type":"VILLAGE",
    "ks:ks_uagg_main":0,
    "name:eng_x_preferred":[
        "Mokhampura"
    ],
    "wof:name":"Mokhampura",
    "wof:placetype":"neighbourhood",
    "wof:population":859
},
  "geometry": {"coordinates":[73.850583,25.132447],"type":"Point"}
}