{
  "type": "Feature",
  "properties": {
    "iso:country":"IN",
    "ks:ks_alt_nam":"MALIBHAG2",
    "ks:ks_name":"Malibhag2",
    "ks:ks_pop":100,
    "ks:ks_type":"HABITATION",
    "name:eng_x_preferred":[
        "Malibhag2"
    ],
    "wof:name":"Malibhag2",
    "wof:placetype":"locality",
    "wof:population":100
},
  "geometry": {"coordinates":[74.687493,17.06876],"type":"Point"}
}