{
  "type": "Feature",
  "properties": {
    "iso:country":"IN",
    "ks:ks_name":"Ghogha",
    "ks:ks_pop":197,
    "ks:ks_type":"VILLAGE",
    "ks:ks_uagg_main":0,
    "name:eng_x_preferred":[
        "Ghogha"
    ],
    "wof:name":"Ghogha",
    "wof:placetype":"neighbourhood",
    "wof:population":197
},
  "geometry": {"coordinates":[87.03061700000001,24.499453],"type":"Point"}
}