{
  "type": "Feature",
  "properties": {
    "gn:admin1_code":"2.0",
    "gn:admin2_code":"554.0",
    "gn:asciiname":"Vankamadivaripalli",
    "gn:country_code":"IN",
    "gn:dem":565,
    "gn:feature_class":"P",
    "gn:feature_code":"PPL",
    "gn:name":"Vankamadiv\u0101ripalli",
    "gn:population":0,
    "gn:timezone":"Asia/Kolkata",
    "iso:country":"IN",
    "wof:name":"Vankamadivaripalli",
    "wof:placetype":"locality"
},
  "geometry": {"coordinates":[79.10585999999998,13.72083],"type":"Point"}
}