{
  "type": "Feature",
  "properties": {
    "iso:country":"IN",
    "ks:ks_alt_nam":"Tatti moole",
    "ks:ks_name":"Tatti Moole",
    "ks:ks_pop":183,
    "ks:ks_type":"HABITATION",
    "name:eng_x_preferred":[
        "Tatti Moole"
    ],
    "wof:name":"Tatti Moole",
    "wof:placetype":"locality",
    "wof:population":183
},
  "geometry": {"coordinates":[74.506688,14.171639],"type":"Point"}
}