{
  "type": "Feature",
  "properties": {
    "iso:country":"IN",
    "ks:ks_alt_nam":"Sehad\u0101",
    "ks:ks_name":"Sehada",
    "ks:ks_pop":355,
    "ks:ks_type":"VILLAGE",
    "name:eng_x_preferred":[
        "Sehada"
    ],
    "name:eng_x_variant":[
        "Sehad\u0101"
    ],
    "wof:name":"Sehada",
    "wof:placetype":"locality",
    "wof:population":355
},
  "geometry": {"coordinates":[84.863409,24.245877],"type":"Point"}
}