{
  "type": "Feature",
  "properties": {
    "gn:admin1_code":"34.0",
    "gn:admin2_code":"226.0",
    "gn:asciiname":"Nimiatanr",
    "gn:country_code":"IN",
    "gn:dem":48,
    "gn:feature_class":"P",
    "gn:feature_code":"PPL",
    "gn:name":"Nimi\u0101t\u0101nr",
    "gn:population":0,
    "gn:timezone":"Asia/Kolkata",
    "iso:country":"IN",
    "wof:name":"Nimiatanr",
    "wof:placetype":"locality"
},
  "geometry": {"coordinates":[86.47587,25.27366],"type":"Point"}
}