{
  "type": "Feature",
  "properties": {
    "gn:admin1_code":"34.0",
    "gn:admin2_code":"219.0",
    "gn:asciiname":"Abdul Hai",
    "gn:country_code":"IN",
    "gn:dem":45,
    "gn:feature_class":"P",
    "gn:feature_code":"PPL",
    "gn:name":"\u0100bdul H\u0101i",
    "gn:population":0,
    "gn:timezone":"Asia/Kolkata",
    "iso:country":"IN",
    "ks:ks_alt_nam":"\u0100bdul H\u0101i",
    "ks:ks_name":"Abdul Hai",
    "ks:ks_type":"VILLAGE",
    "name:ara_x_preferred":[
        "\u0639\u0628\u062f \u0627\u0644\u062d\u064a"
    ],
    "name:cat_x_preferred":[
        "Abd-al-Hayy"
    ],
    "name:eng_x_preferred":[
        "Abdul Hai"
    ],
    "name:eng_x_variant":[
        "\u0100bdul H\u0101i"
    ],
    "wof:name":"Abdul Hai",
    "wof:placetype":"locality"
},
  "geometry": {"coordinates":[85.117637,25.734638],"type":"Point"}
}