{
  "type": "Feature",
  "properties": {
    "gn:admin1_code":"24",
    "gn:admin2_code":"110.0",
    "gn:asciiname":"Harari",
    "gn:country_code":"IN",
    "gn:dem":383,
    "gn:feature_class":"P",
    "gn:feature_code":"PPL",
    "gn:name":"Harari",
    "gn:population":0,
    "gn:timezone":"Asia/Kolkata",
    "iso:country":"IN",
    "name:bar_x_preferred":[
        "Harari"
    ],
    "name:ceb_x_preferred":[
        "Harari"
    ],
    "name:deu_x_preferred":[
        "Harari"
    ],
    "name:fra_x_preferred":[
        "Harari"
    ],
    "name:heb_x_preferred":[
        "\u05d4\u05e8\u05e8\u05d9"
    ],
    "name:ita_x_preferred":[
        "Harari"
    ],
    "name:nld_x_preferred":[
        "Harari"
    ],
    "name:rus_x_preferred":[
        "\u0425\u0430\u0440\u0430\u0440\u0438"
    ],
    "name:srp_x_preferred":[
        "\u0425\u0430\u0440\u0430\u0440\u0438"
    ],
    "name:swe_x_preferred":[
        "Harari"
    ],
    "name:ukr_x_preferred":[
        "\u0425\u0430\u0440\u0430\u0440\u0456"
    ],
    "wof:name":"Harari",
    "wof:placetype":"neighbourhood"
},
  "geometry": {"coordinates":[75.98675,26.89165],"type":"Point"}
}