{
  "type": "Feature",
  "properties": {
    "gn:admin1_code":"21",
    "gn:admin2_code":"395.0",
    "gn:asciiname":"Kaksi",
    "gn:country_code":"IN",
    "gn:dem":643,
    "gn:feature_class":"P",
    "gn:feature_code":"PPL",
    "gn:name":"Kaksi",
    "gn:population":0,
    "gn:timezone":"Asia/Kolkata",
    "iso:country":"IN",
    "ks:ks_name":"Kaksi",
    "ks:ks_type":"VILLAGE",
    "name:eng_x_preferred":[
        "Kaksi"
    ],
    "wof:name":"Kaksi",
    "wof:placetype":"locality"
},
  "geometry": {"coordinates":[83.275092,19.830727],"type":"Point"}
}