{
  "type": "Feature",
  "properties": {
    "iso:country":"IN",
    "ks:ks_alt_nam":"PURA JAOTA",
    "ks:ks_name":"Pura Jaota",
    "ks:ks_pop":66,
    "ks:ks_type":"HABITATION",
    "name:eng_x_preferred":[
        "Pura Jaota"
    ],
    "wof:name":"Pura Jaota",
    "wof:placetype":"locality",
    "wof:population":66
},
  "geometry": {"coordinates":[81.57172,26.604214],"type":"Point"}
}