{
  "type": "Feature",
  "properties": {
    "iso:country":"IN",
    "ks:ks_name":"Mahadeopur",
    "ks:ks_pop":176,
    "ks:ks_type":"VILLAGE",
    "name:eng_x_preferred":[
        "Mahadeopur"
    ],
    "wof:name":"Mahadeopur",
    "wof:placetype":"locality",
    "wof:population":176
},
  "geometry": {"coordinates":[83.247561,24.727383],"type":"Point"}
}