{
  "type": "Feature",
  "properties": {
    "iso:country":"IN",
    "ks:ks_name":"Sembhuchak",
    "ks:ks_pop":460,
    "ks:ks_type":"VILLAGE",
    "ks:ks_uagg_main":0,
    "name:eng_x_preferred":[
        "Sembhuchak"
    ],
    "wof:name":"Sembhuchak",
    "wof:placetype":"neighbourhood",
    "wof:population":460
},
  "geometry": {"coordinates":[84.215053,23.964097],"type":"Point"}
}