{
  "type": "Feature",
  "properties": {
    "iso:country":"IN",
    "ks:ks_name":"Gadhra",
    "ks:ks_pop":15767,
    "ks:ks_type":"VILLAGE",
    "ks:ks_uagg_main":0,
    "name:eng_x_preferred":[
        "Gadhra"
    ],
    "wof:name":"Gadhra",
    "wof:placetype":"neighbourhood",
    "wof:population":15767
},
  "geometry": {"coordinates":[86.245447,22.741842],"type":"Point"}
}