{
  "type": "Feature",
  "properties": {
    "iso:country":"IN",
    "ks:ks_alt_nam":"Mele maripuzha",
    "ks:ks_name":"Mele Maripuzha",
    "ks:ks_pop":205,
    "ks:ks_type":"HABITATION",
    "name:eng_x_preferred":[
        "Mele Maripuzha"
    ],
    "wof:name":"Mele Maripuzha",
    "wof:placetype":"locality",
    "wof:population":205
},
  "geometry": {"coordinates":[76.102497,11.447076],"type":"Point"}
}