{
  "type": "Feature",
  "properties": {
    "iso:country":"IN",
    "ks:ks_name":"Shivnara",
    "ks:ks_pop":957,
    "ks:ks_type":"HABITATION",
    "name:eng_x_preferred":[
        "Shivnara"
    ],
    "wof:name":"Shivnara",
    "wof:placetype":"locality",
    "wof:population":957
},
  "geometry": {"coordinates":[73.194506,27.066553],"type":"Point"}
}