{
  "type": "Feature",
  "properties": {
    "iso:country":"IN",
    "ks:ks_name":"Pandrabahal",
    "ks:ks_pop":98,
    "ks:ks_type":"HABITATION",
    "name:eng_x_preferred":[
        "Pandrabahal"
    ],
    "wof:name":"Pandrabahal",
    "wof:placetype":"locality",
    "wof:population":98
},
  "geometry": {"coordinates":[83.547702,19.747485],"type":"Point"}
}