{
  "type": "Feature",
  "properties": {
    "iso:country":"IN",
    "ks:ks_name":"Gadicherlapally",
    "ks:ks_pop":222,
    "ks:ks_type":"HABITATION",
    "name:eng_x_preferred":[
        "Gadicherlapally"
    ],
    "wof:name":"Gadicherlapally",
    "wof:placetype":"locality",
    "wof:population":222
},
  "geometry": {"coordinates":[78.92911599999999,18.18999],"type":"Point"}
}