{
  "type": "Feature",
  "properties": {
    "iso:country":"IN",
    "ks:ks_name":"Balchand Bigha",
    "ks:ks_pop":420,
    "ks:ks_type":"HABITATION",
    "name:eng_x_preferred":[
        "Balchand Bigha"
    ],
    "wof:name":"Balchand Bigha",
    "wof:placetype":"locality",
    "wof:population":420
},
  "geometry": {"coordinates":[85.60478999999999,25.096151],"type":"Point"}
}