{
  "type": "Feature",
  "properties": {
    "iso:country":"IN",
    "ks:ks_name":"Sulagodu",
    "ks:ks_pop":35,
    "ks:ks_type":"HABITATION",
    "name:eng_x_preferred":[
        "Sulagodu"
    ],
    "wof:name":"Sulagodu",
    "wof:placetype":"locality",
    "wof:population":35
},
  "geometry": {"coordinates":[74.983315,13.826513],"type":"Point"}
}