{
  "type": "Feature",
  "properties": {
    "iso:country":"IN",
    "ks:ks_name":"Karhi Khas",
    "ks:ks_pop":2359,
    "ks:ks_type":"VILLAGE",
    "name:eng_x_preferred":[
        "Karhi Khas"
    ],
    "wof:name":"Karhi Khas",
    "wof:placetype":"locality",
    "wof:population":2359
},
  "geometry": {"coordinates":[82.77006299999999,27.236832],"type":"Point"}
}