{
  "type": "Feature",
  "properties": {
    "iso:country":"IN",
    "ks:ks_alt_nam":"KUCHIKONA",
    "ks:ks_name":"Kuchikona",
    "ks:ks_pop":131,
    "ks:ks_type":"HABITATION",
    "name:eng_x_preferred":[
        "Kuchikona"
    ],
    "wof:name":"Kuchikona",
    "wof:placetype":"locality",
    "wof:population":131
},
  "geometry": {"coordinates":[84.02005,23.025845],"type":"Point"}
}