{
  "type": "Feature",
  "properties": {
    "iso:country":"IN",
    "ks:ks_name":"Bhadua Samil Bachhuribandh",
    "ks:ks_pop":1,
    "ks:ks_type":"HABITATION",
    "name:eng_x_preferred":[
        "Bhadua Samil Bachhuribandh"
    ],
    "wof:name":"Bhadua Samil Bachhuribandh",
    "wof:placetype":"locality",
    "wof:population":1
},
  "geometry": {"coordinates":[86.479373,22.261251],"type":"Point"}
}