{
  "type": "Feature",
  "properties": {
    "iso:country":"IN",
    "ks:ks_alt_nam":"Kot\u0101m",
    "ks:ks_name":"Kotam",
    "ks:ks_pop":358,
    "ks:ks_type":"VILLAGE",
    "name:eng_x_preferred":[
        "Kotam"
    ],
    "name:eng_x_variant":[
        "Kot\u0101m"
    ],
    "wof:name":"Kotam",
    "wof:placetype":"locality",
    "wof:population":358
},
  "geometry": {"coordinates":[84.375427,23.148616],"type":"Point"}
}