{
  "type": "Feature",
  "properties": {
    "gn:admin1_code":"36",
    "gn:admin2_code":"147.0",
    "gn:asciiname":"Dera",
    "gn:country_code":"IN",
    "gn:dem":155,
    "gn:feature_class":"P",
    "gn:feature_code":"PPL",
    "gn:name":"Dera",
    "gn:population":0,
    "gn:timezone":"Asia/Kolkata",
    "iso:country":"IN",
    "name:fra_x_preferred":[
        "Dera"
    ],
    "name:snd_x_preferred":[
        "\u062f\u064a\u0631\u0648"
    ],
    "name:urd_x_preferred":[
        "\u0688\u06cc\u0631\u06c1"
    ],
    "wof:name":"Dera",
    "wof:placetype":"locality"
},
  "geometry": {"coordinates":[78.70701,26.97144],"type":"Point"}
}