{
  "type": "Feature",
  "properties": {
    "iso:country":"IN",
    "ks:ks_name":"Harkundi",
    "ks:ks_pop":105,
    "ks:ks_type":"VILLAGE",
    "ks:ks_uagg_main":0,
    "name:eng_x_preferred":[
        "Harkundi"
    ],
    "wof:name":"Harkundi",
    "wof:placetype":"neighbourhood",
    "wof:population":105
},
  "geometry": {"coordinates":[73.51165,22.737633],"type":"Point"}
}