{
  "type": "Feature",
  "properties": {
    "iso:country":"IN",
    "ks:ks_name":"Bodegudem",
    "ks:ks_pop":45,
    "ks:ks_type":"HABITATION",
    "name:eng_x_preferred":[
        "Bodegudem"
    ],
    "wof:name":"Bodegudem",
    "wof:placetype":"locality",
    "wof:population":45
},
  "geometry": {"coordinates":[81.69833800000001,17.302385],"type":"Point"}
}