{
  "type": "Feature",
  "properties": {
    "iso:country":"IN",
    "ks:ks_name":"Karambpada Falia",
    "ks:ks_pop":128,
    "ks:ks_type":"HABITATION",
    "name:eng_x_preferred":[
        "Karambpada Falia"
    ],
    "wof:name":"Karambpada Falia",
    "wof:placetype":"locality",
    "wof:population":128
},
  "geometry": {"coordinates":[73.226083,20.189944],"type":"Point"}
}