{
  "type": "Feature",
  "properties": {
    "iso:country":"IN",
    "ks:ks_name":"Chakkuldiha",
    "ks:ks_pop":611,
    "ks:ks_type":"VILLAGE",
    "name:eng_x_preferred":[
        "Chakkuldiha"
    ],
    "wof:name":"Chakkuldiha",
    "wof:placetype":"locality",
    "wof:population":611
},
  "geometry": {"coordinates":[86.99327,22.997364],"type":"Point"}
}