{
  "type": "Feature",
  "properties": {
    "iso:country":"IN",
    "ks:ks_name":"Badanpur Nava",
    "ks:ks_pop":432,
    "ks:ks_type":"VILLAGE",
    "ks:ks_uagg_main":0,
    "name:eng_x_preferred":[
        "Badanpur Nava"
    ],
    "wof:name":"Badanpur Nava",
    "wof:placetype":"neighbourhood",
    "wof:population":432
},
  "geometry": {"coordinates":[71.001732,21.725353],"type":"Point"}
}