{
  "type": "Feature",
  "properties": {
    "iso:country":"IN",
    "ks:ks_name":"Amari Jhanga",
    "ks:ks_pop":1272,
    "ks:ks_type":"VILLAGE",
    "name:eng_x_preferred":[
        "Amari Jhanga"
    ],
    "wof:name":"Amari Jhanga",
    "wof:placetype":"locality",
    "wof:population":1272
},
  "geometry": {"coordinates":[83.764916,26.668547],"type":"Point"}
}