{
  "type": "Feature",
  "properties": {
    "gn:admin1_code":"35",
    "gn:admin2_code":"456.0",
    "gn:asciiname":"Mohgaon",
    "gn:country_code":"IN",
    "gn:dem":644,
    "gn:feature_class":"P",
    "gn:feature_code":"PPL",
    "gn:name":"Mohgaon",
    "gn:population":0,
    "gn:timezone":"Asia/Kolkata",
    "iso:country":"IN",
    "wof:name":"Mohgaon",
    "wof:placetype":"locality"
},
  "geometry": {"coordinates":[79.52498,21.91937],"type":"Point"}
}