{
  "type": "Feature",
  "properties": {
    "iso:country":"IN",
    "ks:ks_name":"Boudhawadi",
    "ks:ks_pop":75,
    "ks:ks_type":"HABITATION",
    "name:eng_x_preferred":[
        "Boudhawadi"
    ],
    "wof:name":"Boudhawadi",
    "wof:placetype":"locality",
    "wof:population":75
},
  "geometry": {"coordinates":[73.714702,16.190292],"type":"Point"}
}