{
  "type": "Feature",
  "properties": {
    "iso:country":"IN",
    "ks:ks_name":"Ratanpur",
    "ks:ks_pop":339,
    "ks:ks_type":"VILLAGE",
    "ks:ks_uagg_main":0,
    "name:eng_x_preferred":[
        "Ratanpur"
    ],
    "wof:name":"Ratanpur",
    "wof:placetype":"neighbourhood",
    "wof:population":339
},
  "geometry": {"coordinates":[86.15998399999999,23.875361],"type":"Point"}
}