{
  "type": "Feature",
  "properties": {
    "iso:country":"IN",
    "ks:ks_name":"Gudiapara",
    "ks:ks_pop":95,
    "ks:ks_type":"HABITATION",
    "name:eng_x_preferred":[
        "Gudiapara"
    ],
    "wof:name":"Gudiapara",
    "wof:placetype":"locality",
    "wof:population":95
},
  "geometry": {"coordinates":[84.192032,22.356011],"type":"Point"}
}