{
  "type": "Feature",
  "properties": {
    "gn:admin1_code":"09",
    "gn:admin2_code":"476.0",
    "gn:asciiname":"Shapur",
    "gn:country_code":"IN",
    "gn:dem":34,
    "gn:feature_class":"P",
    "gn:feature_code":"PPL",
    "gn:name":"Sh\u0101pur",
    "gn:population":0,
    "gn:timezone":"Asia/Kolkata",
    "iso:country":"IN",
    "wof:name":"Shapur",
    "wof:placetype":"neighbourhood"
},
  "geometry": {"coordinates":[70.89302000000001,22.98067],"type":"Point"}
}