{
  "type": "Feature",
  "properties": {
    "iso:country":"IN",
    "ks:ks_name":"Kaeda",
    "ks:ks_pop":1052,
    "ks:ks_type":"VILLAGE",
    "name:eng_x_preferred":[
        "Kaeda"
    ],
    "wof:name":"Kaeda",
    "wof:placetype":"locality",
    "wof:population":1052
},
  "geometry": {"coordinates":[85.26863,22.469662],"type":"Point"}
}