{
  "type": "Feature",
  "properties": {
    "gn:admin1_code":"34.0",
    "gn:admin2_code":"219.0",
    "gn:asciiname":"Murlipur",
    "gn:country_code":"IN",
    "gn:dem":59,
    "gn:feature_class":"P",
    "gn:feature_code":"PPL",
    "gn:name":"Murl\u012bpur",
    "gn:population":0,
    "gn:timezone":"Asia/Kolkata",
    "iso:country":"IN",
    "ks:ks_name":"Murlipur",
    "ks:ks_pop":749,
    "ks:ks_type":"VILLAGE",
    "name:eng_x_preferred":[
        "Murlipur"
    ],
    "wof:name":"Murlipur",
    "wof:placetype":"locality",
    "wof:population":749
},
  "geometry": {"coordinates":[84.87787299999999,26.058653],"type":"Point"}
}