{
  "type": "Feature",
  "properties": {
    "iso:country":"IN",
    "ks:ks_name":"Biyaghati",
    "ks:ks_pop":219,
    "ks:ks_type":"HABITATION",
    "name:eng_x_preferred":[
        "Biyaghati"
    ],
    "wof:name":"Biyaghati",
    "wof:placetype":"locality",
    "wof:population":219
},
  "geometry": {"coordinates":[75.52664300000001,22.45219],"type":"Point"}
}