{
  "type": "Feature",
  "properties": {
    "iso:country":"IN",
    "ks:ks_name":"Khaira Form",
    "ks:ks_pop":184,
    "ks:ks_type":"HABITATION",
    "name:eng_x_preferred":[
        "Khaira Form"
    ],
    "wof:name":"Khaira Form",
    "wof:placetype":"locality",
    "wof:population":184
},
  "geometry": {"coordinates":[80.56760800000001,28.136262],"type":"Point"}
}