{
  "type": "Feature",
  "properties": {
    "gn:admin1_code":"19.0",
    "gn:admin2_code":"571.0",
    "gn:asciiname":"Suragondanahalli",
    "gn:country_code":"IN",
    "gn:dem":790,
    "gn:feature_class":"P",
    "gn:feature_code":"PPL",
    "gn:name":"S\u016bragondanahalli",
    "gn:population":0,
    "gn:timezone":"Asia/Kolkata",
    "iso:country":"IN",
    "wof:name":"Suragondanahalli",
    "wof:placetype":"locality"
},
  "geometry": {"coordinates":[76.43212,13.4054],"type":"Point"}
}