{
  "type": "Feature",
  "properties": {
    "iso:country":"IN",
    "ks:ks_name":"Shila",
    "ks:ks_pop":1879,
    "ks:ks_type":"VILLAGE",
    "name:eng_x_preferred":[
        "Shila"
    ],
    "wof:name":"Shila",
    "wof:placetype":"locality",
    "wof:population":1879
},
  "geometry": {"coordinates":[88.156192,23.496794],"type":"Point"}
}