{
  "type": "Feature",
  "properties": {
    "iso:country":"IN",
    "ks:ks_alt_nam":"WARNA NADI",
    "ks:ks_name":"Warna Nadi",
    "ks:ks_pop":90,
    "ks:ks_type":"HABITATION",
    "name:eng_x_preferred":[
        "Warna Nadi"
    ],
    "wof:name":"Warna Nadi",
    "wof:placetype":"locality",
    "wof:population":90
},
  "geometry": {"coordinates":[74.0307,16.950265],"type":"Point"}
}