{
  "type": "Feature",
  "properties": {
    "gn:admin1_code":"28",
    "gn:admin2_code":"328.0",
    "gn:asciiname":"Madari Hat",
    "gn:country_code":"IN",
    "gn:dem":105,
    "gn:feature_class":"P",
    "gn:feature_code":"PPL",
    "gn:name":"M\u0101d\u0101ri H\u0101t",
    "gn:population":0,
    "gn:timezone":"Asia/Kolkata",
    "iso:country":"IN",
    "name:und_x_variant":[
        "Madarihat",
        "M\u0101d\u0101ri H\u0101t"
    ],
    "name:urd_x_preferred":[
        "\u0645\u06cc\u0688\u0627\u0631\u06cc\u06c1\u0627\u0679"
    ],
    "wof:name":"Madari Hat",
    "wof:placetype":"locality"
},
  "geometry": {"coordinates":[89.28145000000001,26.69523],"type":"Point"}
}