{
  "type": "Feature",
  "properties": {
    "iso:country":"IN",
    "ks:ks_name":"Lwintha",
    "ks:ks_pop":27,
    "ks:ks_type":"VILLAGE",
    "name:eng_x_preferred":[
        "Lwintha"
    ],
    "wof:name":"Lwintha",
    "wof:placetype":"locality",
    "wof:population":27
},
  "geometry": {"coordinates":[79.211564,30.225217],"type":"Point"}
}