{
  "type": "Feature",
  "properties": {
    "iso:country":"IN",
    "ks:ks_name":"Hanamanal",
    "ks:ks_pop":403,
    "ks:ks_type":"VILLAGE",
    "ks:ks_uagg_main":0,
    "name:eng_x_preferred":[
        "Hanamanal"
    ],
    "wof:name":"Hanamanal",
    "wof:placetype":"neighbourhood",
    "wof:population":403
},
  "geometry": {"coordinates":[76.134458,15.934758],"type":"Point"}
}