{
  "type": "Feature",
  "properties": {
    "gn:admin1_code":"36.0",
    "gn:admin2_code":"179.0",
    "gn:asciiname":"Kishandaspur",
    "gn:country_code":"IN",
    "gn:dem":106,
    "gn:feature_class":"P",
    "gn:feature_code":"PPL",
    "gn:name":"Kishand\u0101spur",
    "gn:population":0,
    "gn:timezone":"Asia/Kolkata",
    "iso:country":"IN",
    "ks:ks_alt_nam":"Kishand\u0101spur",
    "ks:ks_name":"Kishandaspur",
    "ks:ks_pop":520,
    "ks:ks_type":"VILLAGE",
    "ks:ks_uagg_main":0,
    "name:eng_x_preferred":[
        "Kishandaspur"
    ],
    "name:eng_x_variant":[
        "Kishand\u0101spur"
    ],
    "wof:name":"Kishandaspur",
    "wof:placetype":"neighbourhood",
    "wof:population":520
},
  "geometry": {"coordinates":[81.823249,26.314261],"type":"Point"}
}