{
  "type": "Feature",
  "properties": {
    "gn:admin1_code":"36",
    "gn:admin2_code":"159.0",
    "gn:asciiname":"Sikandarpur Nagla Binaik",
    "gn:country_code":"IN",
    "gn:dem":156,
    "gn:feature_class":"P",
    "gn:feature_code":"PPL",
    "gn:name":"Sikandarpur Nagla Binaik",
    "gn:population":0,
    "gn:timezone":"Asia/Kolkata",
    "iso:country":"IN",
    "wof:name":"Sikandarpur Nagla Binaik",
    "wof:placetype":"locality"
},
  "geometry": {"coordinates":[79.38038,27.40143],"type":"Point"}
}