{
  "type": "Feature",
  "properties": {
    "gn:admin1_code":"38.0",
    "gn:admin2_code":"348.0",
    "gn:asciiname":"Guri Kalan",
    "gn:country_code":"IN",
    "gn:dem":413,
    "gn:feature_class":"P",
    "gn:feature_code":"PPL",
    "gn:name":"Guri Kal\u0101n",
    "gn:population":0,
    "gn:timezone":"Asia/Kolkata",
    "iso:country":"IN",
    "ks:ks_name":"Guri Kalan",
    "ks:ks_pop":277,
    "ks:ks_type":"VILLAGE",
    "name:eng_x_preferred":[
        "Guri Kalan"
    ],
    "wof:name":"Guri Kalan",
    "wof:placetype":"locality",
    "wof:population":277
},
  "geometry": {"coordinates":[85.187411,24.355347],"type":"Point"}
}