{
  "type": "Feature",
  "properties": {
    "gn:admin1_code":"34.0",
    "gn:admin2_code":"234.0",
    "gn:asciiname":"Batsa",
    "gn:country_code":"IN",
    "gn:dem":86,
    "gn:feature_class":"P",
    "gn:feature_code":"PPL",
    "gn:name":"Batsa",
    "gn:population":0,
    "gn:timezone":"Asia/Kolkata",
    "iso:country":"IN",
    "name:ceb_x_preferred":[
        "Batsa"
    ],
    "name:fra_x_preferred":[
        "Batsa Itsandra"
    ],
    "name:swe_x_preferred":[
        "Batsa Itsandra"
    ],
    "wof:name":"Batsa",
    "wof:placetype":"locality"
},
  "geometry": {"coordinates":[84.23050000000001,25.34208],"type":"Point"}
}