{
  "type": "Feature",
  "properties": {
    "iso:country":"IN",
    "ks:ks_name":"Karmoda",
    "ks:ks_pop":1400,
    "ks:ks_type":"VILLAGE",
    "name:eng_x_preferred":[
        "Karmoda"
    ],
    "wof:name":"Karmoda",
    "wof:placetype":"locality",
    "wof:population":1400
},
  "geometry": {"coordinates":[77.649227,22.872114],"type":"Point"}
}