{
  "type": "Feature",
  "properties": {
    "iso:country":"IN",
    "ks:ks_name":"Kamubediya",
    "ks:ks_pop":210,
    "ks:ks_type":"VILLAGE",
    "name:eng_x_preferred":[
        "Kamubediya"
    ],
    "wof:name":"Kamubediya",
    "wof:placetype":"locality",
    "wof:population":210
},
  "geometry": {"coordinates":[87.04366,23.865225],"type":"Point"}
}