{
  "type": "Feature",
  "properties": {
    "iso:country":"IN",
    "ks:ks_name":"Chatra",
    "ks:ks_pop":418,
    "ks:ks_type":"VILLAGE",
    "name:eng_x_preferred":[
        "Chatra"
    ],
    "wof:name":"Chatra",
    "wof:placetype":"locality",
    "wof:population":418
},
  "geometry": {"coordinates":[87.367977,24.863684],"type":"Point"}
}