{
  "type": "Feature",
  "properties": {
    "iso:country":"IN",
    "ks:ks_name":"Nilara",
    "ks:ks_pop":33,
    "ks:ks_type":"VILLAGE",
    "name:eng_x_preferred":[
        "Nilara"
    ],
    "wof:name":"Nilara",
    "wof:placetype":"locality",
    "wof:population":33
},
  "geometry": {"coordinates":[78.81766500000001,30.020054],"type":"Point"}
}