{
  "type": "Feature",
  "properties": {
    "iso:country":"IN",
    "ks:ks_name":"Kolar",
    "ks:ks_pop":390,
    "ks:ks_type":"VILLAGE",
    "name:eng_x_preferred":[
        "Kolar"
    ],
    "name:hin_x_preferred":[
        "\u0915\u094b\u0932\u093e\u0930"
    ],
    "name:kan_x_preferred":[
        "\u0c95\u0ccb\u0cb2\u0cbe\u0cb0"
    ],
    "wof:name":"Kolar",
    "wof:placetype":"locality",
    "wof:population":390
},
  "geometry": {"coordinates":[73.865719,24.122819],"type":"Point"}
}