{
  "type": "Feature",
  "properties": {
    "gn:admin1_code":"35",
    "gn:admin2_code":"428.0",
    "gn:asciiname":"Manakpura",
    "gn:country_code":"IN",
    "gn:dem":460,
    "gn:feature_class":"P",
    "gn:feature_code":"PPL",
    "gn:name":"M\u0101nakpura",
    "gn:population":0,
    "gn:timezone":"Asia/Kolkata",
    "iso:country":"IN",
    "ks:ks_name":"Manakpura",
    "ks:ks_pop":98,
    "ks:ks_type":"VILLAGE",
    "name:eng_x_preferred":[
        "Manakpura"
    ],
    "wof:name":"Manakpura",
    "wof:placetype":"locality",
    "wof:population":98
},
  "geometry": {"coordinates":[79.51385399999999,24.386664],"type":"Point"}
}