{
  "type": "Feature",
  "properties": {
    "iso:country":"IN",
    "qs:name":"Biligiriranganabetta",
    "qs:name_adm0":"India",
    "qs:name_adm1":"Karnataka",
    "qs:photos":95,
    "qs:photos_1k":19,
    "qs:photos_9k":1,
    "qs:photos_9r":3,
    "qs:photos_all":95,
    "qs:photos_sr":3,
    "qs:placetype":"Town",
    "qs:pop_sr":"0",
    "wof:name":"Biligiriranganabetta",
    "wof:placetype":"locality"
},
  "geometry": {"coordinates":[77.14370700000001,12.001489],"type":"Point"}
}