{
  "type": "Feature",
  "properties": {
    "iso:country":"IN",
    "ks:ks_alt_nam":"Thalasserry PWD",
    "ks:ks_name":"Thalasserry Pwd",
    "ks:ks_pop":627,
    "ks:ks_type":"HABITATION",
    "name:eng_x_preferred":[
        "Thalasserry Pwd"
    ],
    "wof:name":"Thalasserry Pwd",
    "wof:placetype":"locality",
    "wof:population":627
},
  "geometry": {"coordinates":[76.216746,10.731736],"type":"Point"}
}