{
  "type": "Feature",
  "properties": {
    "iso:country":"IN",
    "ks:ks_name":"Bilrahan Purwa",
    "ks:ks_pop":360,
    "ks:ks_type":"HABITATION",
    "ks:ks_uagg_main":0,
    "name:eng_x_preferred":[
        "Bilrahan Purwa"
    ],
    "wof:name":"Bilrahan Purwa",
    "wof:placetype":"neighbourhood",
    "wof:population":360
},
  "geometry": {"coordinates":[81.711491,26.97749],"type":"Point"}
}