{
  "type": "Feature",
  "properties": {
    "iso:country":"IN",
    "ks:ks_name":"Muktarpur",
    "ks:ks_pop":899,
    "ks:ks_type":"VILLAGE",
    "ks:ks_uagg_main":0,
    "name:eng_x_preferred":[
        "Muktarpur"
    ],
    "wof:name":"Muktarpur",
    "wof:placetype":"neighbourhood",
    "wof:population":899
},
  "geometry": {"coordinates":[87.723955,22.797329],"type":"Point"}
}