{
  "type": "Feature",
  "properties": {
    "iso:country":"IN",
    "ks:ks_name":"Majhwalia",
    "ks:ks_pop":170,
    "ks:ks_type":"VILLAGE",
    "name:eng_x_preferred":[
        "Majhwalia"
    ],
    "wof:name":"Majhwalia",
    "wof:placetype":"locality",
    "wof:population":170
},
  "geometry": {"coordinates":[84.543307,24.505917],"type":"Point"}
}