{
  "type": "Feature",
  "properties": {
    "gn:admin1_code":"28.0",
    "gn:admin2_code":"327.0",
    "gn:asciiname":"Rishihat",
    "gn:country_code":"IN",
    "gn:dem":1640,
    "gn:feature_class":"P",
    "gn:feature_code":"PPL",
    "gn:name":"Rish\u012bh\u0101t",
    "gn:population":0,
    "gn:timezone":"Asia/Kolkata",
    "iso:country":"IN",
    "wof:name":"Rishihat",
    "wof:placetype":"locality"
},
  "geometry": {"coordinates":[88.21914,27.0283],"type":"Point"}
}