{
  "type": "Feature",
  "properties": {
    "iso:country":"IN",
    "ks:ks_name":"Dhumalwasti",
    "ks:ks_pop":450,
    "ks:ks_type":"HABITATION",
    "name:eng_x_preferred":[
        "Dhumalwasti"
    ],
    "wof:name":"Dhumalwasti",
    "wof:placetype":"locality",
    "wof:population":450
},
  "geometry": {"coordinates":[74.365959,19.145026],"type":"Point"}
}