{
  "type": "Feature",
  "properties": {
    "iso:country":"IN",
    "ks:ks_name":"Rohai",
    "ks:ks_pop":860,
    "ks:ks_type":"VILLAGE",
    "name:eng_x_preferred":[
        "Rohai"
    ],
    "wof:name":"Rohai",
    "wof:placetype":"locality",
    "wof:population":860
},
  "geometry": {"coordinates":[80.070801,27.524016],"type":"Point"}
}