{
  "type": "Feature",
  "properties": {
    "gn:admin1_code":"12",
    "gn:admin2_code":"12.0",
    "gn:asciiname":"Juwan Gosairr",
    "gn:country_code":"IN",
    "gn:dem":1736,
    "gn:feature_class":"P",
    "gn:feature_code":"PPL",
    "gn:name":"J\u016bwan Gos\u0101irr",
    "gn:population":0,
    "gn:timezone":"Asia/Kolkata",
    "iso:country":"IN",
    "wof:name":"Juwan Gosairr",
    "wof:placetype":"locality"
},
  "geometry": {"coordinates":[75.00686,33.98819],"type":"Point"}
}