{
  "type": "Feature",
  "properties": {
    "gn:admin1_code":"34.0",
    "gn:admin2_code":"225.0",
    "gn:asciiname":"Tilakpur",
    "gn:country_code":"IN",
    "gn:dem":62,
    "gn:feature_class":"P",
    "gn:feature_code":"PPL",
    "gn:name":"Tilakpur",
    "gn:population":0,
    "gn:timezone":"Asia/Kolkata",
    "iso:country":"IN",
    "name:ceb_x_preferred":[
        "Tilakpur"
    ],
    "name:hin_x_preferred":[
        "\u0924\u093f\u0932\u0915\u092a\u0941\u0930"
    ],
    "name:msa_x_preferred":[
        "Tilakpur"
    ],
    "name:new_x_preferred":[
        "\u0924\u093f\u0932\u0915\u092a\u0941\u0930"
    ],
    "name:pol_x_preferred":[
        "Tilakpur"
    ],
    "wof:name":"Tilakpur",
    "wof:placetype":"locality"
},
  "geometry": {"coordinates":[87.02543,25.01215],"type":"Point"}
}