{
  "type": "Feature",
  "properties": {
    "iso:country":"IN",
    "ks:ks_name":"Mahmadapur",
    "ks:ks_pop":1849,
    "ks:ks_type":"VILLAGE",
    "name:eng_x_preferred":[
        "Mahmadapur"
    ],
    "wof:name":"Mahmadapur",
    "wof:placetype":"locality",
    "wof:population":1849
},
  "geometry": {"coordinates":[80.292906,27.453006],"type":"Point"}
}