{
  "type": "Feature",
  "properties": {
    "iso:country":"IN",
    "ks:ks_name":"Barail",
    "ks:ks_pop":2063,
    "ks:ks_type":"VILLAGE",
    "ks:ks_uagg_main":0,
    "name:eng_x_preferred":[
        "Barail"
    ],
    "wof:name":"Barail",
    "wof:placetype":"neighbourhood",
    "wof:population":2063
},
  "geometry": {"coordinates":[88.39203999999999,25.393848],"type":"Point"}
}