{
  "type": "Feature",
  "properties": {
    "gn:admin1_code":"3.0",
    "gn:admin2_code":"301",
    "gn:asciiname":"Dingdinga",
    "gn:country_code":"IN",
    "gn:dem":41,
    "gn:feature_class":"P",
    "gn:feature_code":"PPL",
    "gn:name":"Dingdinga",
    "gn:population":0,
    "gn:timezone":"Asia/Kolkata",
    "iso:country":"IN",
    "ks:ks_name":"Dingdinga",
    "ks:ks_pop":789,
    "ks:ks_type":"HABITATION",
    "ks:ks_uagg_main":0,
    "name:eng_x_preferred":[
        "Dingdinga"
    ],
    "name:und_x_variant":[
        "Dingdirga",
        "Dingdinga"
    ],
    "wof:name":"Dingdinga",
    "wof:placetype":"neighbourhood",
    "wof:population":789
},
  "geometry": {"coordinates":[89.88893899999999,26.334724],"type":"Point"}
}