{
  "type": "Feature",
  "properties": {
    "iso:country":"IN",
    "ks:ks_name":"Paobanki",
    "ks:ks_pop":878,
    "ks:ks_type":"VILLAGE",
    "name:eng_x_preferred":[
        "Paobanki"
    ],
    "wof:name":"Paobanki",
    "wof:placetype":"locality",
    "wof:population":878
},
  "geometry": {"coordinates":[87.71824100000001,22.368606],"type":"Point"}
}