{
  "type": "Feature",
  "properties": {
    "iso:country":"IN",
    "ks:ks_name":"Attapalayam",
    "ks:ks_pop":106,
    "ks:ks_type":"HABITATION",
    "name:eng_x_preferred":[
        "Attapalayam"
    ],
    "wof:name":"Attapalayam",
    "wof:placetype":"locality",
    "wof:population":106
},
  "geometry": {"coordinates":[80.19591699999999,13.268225],"type":"Point"}
}