{
  "type": "Feature",
  "properties": {
    "iso:country":"IN",
    "ks:ks_name":"Bhutri Forest",
    "ks:ks_pop":183,
    "ks:ks_type":"VILLAGE",
    "name:eng_x_preferred":[
        "Bhutri Forest"
    ],
    "wof:name":"Bhutri Forest",
    "wof:placetype":"locality",
    "wof:population":183
},
  "geometry": {"coordinates":[89.42076,26.770534],"type":"Point"}
}