{
  "type": "Feature",
  "properties": {
    "iso:country":"IN",
    "ks:ks_name":"Sadadi",
    "ks:ks_pop":374,
    "ks:ks_type":"VILLAGE",
    "name:eng_x_preferred":[
        "Sadadi"
    ],
    "wof:name":"Sadadi",
    "wof:placetype":"locality",
    "wof:population":374
},
  "geometry": {"coordinates":[81.530348,19.689155],"type":"Point"}
}