{
  "type": "Feature",
  "properties": {
    "iso:country":"IN",
    "ks:ks_alt_nam":"Matai para",
    "ks:ks_name":"Matai Para",
    "ks:ks_pop":397,
    "ks:ks_type":"HABITATION",
    "ks:ks_uagg_main":0,
    "name:eng_x_preferred":[
        "Matai Para"
    ],
    "wof:name":"Matai Para",
    "wof:placetype":"neighbourhood",
    "wof:population":397
},
  "geometry": {"coordinates":[91.483717,23.925511],"type":"Point"}
}