{
  "type": "Feature",
  "properties": {
    "gn:admin1_code":"25.0",
    "gn:admin2_code":"619.0",
    "gn:asciiname":"Ponnur",
    "gn:country_code":"IN",
    "gn:dem":18,
    "gn:feature_class":"P",
    "gn:feature_code":"PPL",
    "gn:name":"Ponn\u016br",
    "gn:population":0,
    "gn:timezone":"Asia/Kolkata",
    "iso:country":"IN",
    "name:bpy_x_preferred":[
        "\u09aa\u09cb\u09a8\u09cd\u09a8\u09c1\u09b0"
    ],
    "name:ceb_x_preferred":[
        "Ponnur"
    ],
    "name:ita_x_preferred":[
        "Ponnur"
    ],
    "name:msa_x_preferred":[
        "Ponnur"
    ],
    "name:new_x_preferred":[
        "\u092a\u094b\u0928\u094d\u0928\u0942\u0930\u0941 \u092e\u0923\u094d\u0921\u0932"
    ],
    "name:ori_x_preferred":[
        "\u0b2a\u0b4b\u0b28\u0b4d\u0b28\u0b41\u0b30"
    ],
    "name:pam_x_preferred":[
        "Ponnur"
    ],
    "name:por_x_preferred":[
        "Ponnur"
    ],
    "name:swe_x_preferred":[
        "Ponnur"
    ],
    "name:tel_x_preferred":[
        "\u0c2a\u0c4a\u0c28\u0c4d\u0c28\u0c42\u0c30\u0c41"
    ],
    "name:vie_x_preferred":[
        "Ponnur"
    ],
    "name:zho_x_preferred":[
        "\u84ec\u52aa\u5c14"
    ],
    "wof:name":"Ponnur",
    "wof:placetype":"locality"
},
  "geometry": {"coordinates":[79.46969,10.82798],"type":"Point"}
}