{
  "type": "Feature",
  "properties": {
    "iso:country":"IN",
    "ks:ks_name":"Akbarpur Damodar",
    "ks:ks_pop":327,
    "ks:ks_type":"VILLAGE",
    "ks:ks_uagg_main":0,
    "name:eng_x_preferred":[
        "Akbarpur Damodar"
    ],
    "wof:name":"Akbarpur Damodar",
    "wof:placetype":"neighbourhood",
    "wof:population":327
},
  "geometry": {"coordinates":[79.43642800000001,27.542923],"type":"Point"}
}