{
  "type": "Feature",
  "properties": {
    "iso:country":"IN",
    "ks:ks_name":"Botala Purohitan",
    "ks:ks_pop":668,
    "ks:ks_type":"VILLAGE",
    "name:eng_x_preferred":[
        "Botala Purohitan"
    ],
    "wof:name":"Botala Purohitan",
    "wof:placetype":"locality",
    "wof:population":668
},
  "geometry": {"coordinates":[71.92169699999999,25.894981],"type":"Point"}
}