{
  "type": "Feature",
  "properties": {
    "iso:country":"IN",
    "ks:ks_name":"Dakshin Sol",
    "ks:ks_pop":14,
    "ks:ks_type":"VILLAGE",
    "name:eng_x_preferred":[
        "Dakshin Sol"
    ],
    "wof:name":"Dakshin Sol",
    "wof:placetype":"locality",
    "wof:population":14
},
  "geometry": {"coordinates":[86.90521699999999,22.439066],"type":"Point"}
}