{
  "type": "Feature",
  "properties": {
    "gn:admin1_code":"36.0",
    "gn:admin2_code":"151.0",
    "gn:asciiname":"Puraianian",
    "gn:country_code":"IN",
    "gn:dem":182,
    "gn:feature_class":"P",
    "gn:feature_code":"PPL",
    "gn:name":"Puraiani\u0101n",
    "gn:population":0,
    "gn:timezone":"Asia/Kolkata",
    "iso:country":"IN",
    "ks:ks_alt_nam":"Puraini\u0101n",
    "ks:ks_name":"Purainian",
    "ks:ks_type":"VILLAGE",
    "name:eng_x_preferred":[
        "Purainian"
    ],
    "name:eng_x_variant":[
        "Puraianian",
        "Puraini\u0101n"
    ],
    "wof:name":"Purainian",
    "wof:placetype":"locality"
},
  "geometry": {"coordinates":[79.757465,28.501136],"type":"Point"}
}