{
  "type": "Feature",
  "properties": {
    "iso:country":"IN",
    "ks:ks_name":"Chadripahadi",
    "ks:ks_pop":278,
    "ks:ks_type":"VILLAGE",
    "name:eng_x_preferred":[
        "Chadripahadi"
    ],
    "wof:name":"Chadripahadi",
    "wof:placetype":"locality",
    "wof:population":278
},
  "geometry": {"coordinates":[86.245644,22.036952],"type":"Point"}
}