{
  "type": "Feature",
  "properties": {
    "iso:country":"IN",
    "ks:ks_name":"Kottaikadu",
    "ks:ks_pop":392,
    "ks:ks_type":"VILLAGE",
    "ks:ks_uagg_main":0,
    "name:eng_x_preferred":[
        "Kottaikadu"
    ],
    "wof:name":"Kottaikadu",
    "wof:placetype":"neighbourhood",
    "wof:population":392
},
  "geometry": {"coordinates":[79.247288,10.318849],"type":"Point"}
}