{
  "type": "Feature",
  "properties": {
    "iso:country":"IN",
    "ks:ks_name":"Kutingguda",
    "ks:ks_pop":88,
    "ks:ks_type":"VILLAGE",
    "name:eng_x_preferred":[
        "Kutingguda"
    ],
    "wof:name":"Kutingguda",
    "wof:placetype":"locality",
    "wof:population":88
},
  "geometry": {"coordinates":[83.70201900000001,19.538478],"type":"Point"}
}