{
  "type": "Feature",
  "properties": {
    "iso:country":"IN",
    "ks:ks_alt_nam":"HARIJANBASTI 2",
    "ks:ks_name":"Harijanbasti 2",
    "ks:ks_pop":343,
    "ks:ks_type":"HABITATION",
    "ks:ks_uagg_main":0,
    "name:eng_x_preferred":[
        "Harijanbasti 2"
    ],
    "wof:name":"Harijanbasti 2",
    "wof:placetype":"neighbourhood",
    "wof:population":343
},
  "geometry": {"coordinates":[83.13270799999999,25.411921],"type":"Point"}
}