{
  "type": "Feature",
  "properties": {
    "iso:country":"IN",
    "ks:ks_name":"Madhanerikottai",
    "ks:ks_pop":377,
    "ks:ks_type":"HABITATION",
    "name:eng_x_preferred":[
        "Madhanerikottai"
    ],
    "wof:name":"Madhanerikottai",
    "wof:placetype":"locality",
    "wof:population":377
},
  "geometry": {"coordinates":[78.120998,12.327068],"type":"Point"}
}