{
  "type": "Feature",
  "properties": {
    "iso:country":"IN",
    "ks:ks_name":"Bara Kalhajor",
    "ks:ks_pop":858,
    "ks:ks_type":"VILLAGE",
    "name:eng_x_preferred":[
        "Bara Kalhajor"
    ],
    "wof:name":"Bara Kalhajor",
    "wof:placetype":"locality",
    "wof:population":858
},
  "geometry": {"coordinates":[87.3558,24.739086],"type":"Point"}
}