{
  "type": "Feature",
  "properties": {
    "gn:admin1_code":"13.0",
    "gn:admin2_code":"599.0",
    "gn:asciiname":"Thumpamon",
    "gn:country_code":"IN",
    "gn:dem":29,
    "gn:feature_class":"P",
    "gn:feature_code":"PPL",
    "gn:name":"Thumpamon",
    "gn:population":0,
    "gn:timezone":"Asia/Kolkata",
    "iso:country":"IN",
    "name:mal_x_preferred":[
        "\u0d24\u0d41\u0d2e\u0d4d\u0d2a\u0d2e\u0d7a \u0d17\u0d4d\u0d30\u0d3e\u0d2e\u0d2a\u0d1e\u0d4d\u0d1a\u0d3e\u0d2f\u0d24\u0d4d\u0d24\u0d4d"
    ],
    "wof:name":"Thumpamon",
    "wof:placetype":"locality"
},
  "geometry": {"coordinates":[76.71186,9.21933],"type":"Point"}
}