{
  "type": "Feature",
  "properties": {
    "iso:country":"IN",
    "ks:ks_alt_nam":"thangal colony",
    "ks:ks_name":"Thangal Colony",
    "ks:ks_pop":57,
    "ks:ks_type":"HABITATION",
    "name:eng_x_preferred":[
        "Thangal Colony"
    ],
    "wof:name":"Thangal Colony",
    "wof:placetype":"locality",
    "wof:population":57
},
  "geometry": {"coordinates":[79.458384,12.348121],"type":"Point"}
}