{
  "type": "Feature",
  "properties": {
    "gn:admin1_code":"19.0",
    "gn:admin2_code":"573.0",
    "gn:asciiname":"Kundur",
    "gn:country_code":"IN",
    "gn:dem":863,
    "gn:feature_class":"P",
    "gn:feature_code":"PPL",
    "gn:name":"Kund\u016br",
    "gn:population":0,
    "gn:timezone":"Asia/Kolkata",
    "iso:country":"IN",
    "name:ceb_x_preferred":[
        "Kundur"
    ],
    "name:nld_x_preferred":[
        "Kundur"
    ],
    "name:swe_x_preferred":[
        "Kundur"
    ],
    "wof:name":"Kundur",
    "wof:placetype":"locality"
},
  "geometry": {"coordinates":[76.47657,12.76042],"type":"Point"}
}