{
  "type": "Feature",
  "properties": {
    "gn:admin1_code":"36.0",
    "gn:admin2_code":"174.0",
    "gn:asciiname":"Tira",
    "gn:country_code":"IN",
    "gn:dem":102,
    "gn:feature_class":"P",
    "gn:feature_code":"PPL",
    "gn:name":"T\u012bra",
    "gn:population":0,
    "gn:timezone":"Asia/Kolkata",
    "iso:country":"IN",
    "name:ceb_x_preferred":[
        "Tira"
    ],
    "name:ces_x_preferred":[
        "Tira"
    ],
    "name:deu_x_preferred":[
        "Tira"
    ],
    "name:fra_x_preferred":[
        "Tira"
    ],
    "name:heb_x_preferred":[
        "\u05d8\u05d9\u05e8\u05d4"
    ],
    "name:ita_x_preferred":[
        "Tira"
    ],
    "name:lav_x_preferred":[
        "Tira"
    ],
    "name:nld_x_preferred":[
        "Tira"
    ],
    "name:oss_x_preferred":[
        "\u0422\u0438\u0440\u0430"
    ],
    "name:por_x_preferred":[
        "Tira"
    ],
    "name:rus_x_preferred":[
        "\u0422\u0438\u0440\u0430"
    ],
    "name:spa_x_preferred":[
        "Tira"
    ],
    "name:swe_x_preferred":[
        "Tira"
    ],
    "wof:name":"Tira",
    "wof:placetype":"locality"
},
  "geometry": {"coordinates":[81.68616999999998,25.38861],"type":"Point"}
}