{
  "type": "Feature",
  "properties": {
    "gn:gn_country":"IN",
    "gn:gn_fcode":"PPL",
    "gn:gn_pop":1365,
    "gn:population":1365,
    "iso:country":"IN",
    "name:ast_x_preferred":[
        "Morjim"
    ],
    "name:ceb_x_preferred":[
        "Morjim"
    ],
    "name:eng_x_preferred":[
        "Morjim"
    ],
    "name:gom_x_preferred":[
        "Morji"
    ],
    "name:nld_x_preferred":[
        "Morjim"
    ],
    "name:rus_x_preferred":[
        "\u041c\u043e\u0440\u0434\u0436\u0438\u043c"
    ],
    "name:swe_x_preferred":[
        "Morjim"
    ],
    "qs_pg:aaroncc":"IN",
    "qs_pg:gn_country":"IN",
    "qs_pg:gn_fcode":"PPL",
    "qs_pg:gn_pop":1365,
    "qs_pg:name":"Morgim",
    "qs_pg:name_adm0":"India",
    "qs_pg:name_adm1":"Goa",
    "qs_pg:photos":81,
    "qs_pg:photos_1k":16,
    "qs_pg:photos_9k":1,
    "qs_pg:photos_9r":3,
    "qs_pg:photos_all":81,
    "qs_pg:photos_sr":3,
    "qs_pg:pop_sr":3,
    "qs_pg:qs_pg_placetype":"locality",
    "qs_pg:qs_pg_placetype_gp":"Town",
    "qs_pg:woe_adm0":23424848,
    "woe:adm0_id":23424848,
    "woe:name_adm0":"India",
    "woe:name_adm1":"Goa",
    "woe:placetype":"Town",
    "wof:name":"Morgim",
    "wof:placetype":"locality",
    "wof:population":1365
},
  "geometry": {"coordinates":[73.73903,15.63097],"type":"Point"}
}