{
  "type": "Feature",
  "properties": {
    "iso:country":"IN",
    "ks:ks_name":"Atri",
    "ks:ks_pop":2071,
    "ks:ks_type":"VILLAGE",
    "ks:ks_uagg_main":0,
    "name:eng_x_preferred":[
        "Atri"
    ],
    "wof:name":"Atri",
    "wof:placetype":"neighbourhood",
    "wof:population":2071
},
  "geometry": {"coordinates":[86.55820199999999,26.484367],"type":"Point"}
}