{
  "type": "Feature",
  "properties": {
    "iso:country":"IN",
    "ks:ks_name":"Sidhpur",
    "ks:ks_pop":82,
    "ks:ks_type":"HABITATION",
    "name:eng_x_preferred":[
        "Sidhpur"
    ],
    "wof:name":"Sidhpur",
    "wof:placetype":"locality",
    "wof:population":82
},
  "geometry": {"coordinates":[78.911844,29.694144],"type":"Point"}
}