{
  "type": "Feature",
  "properties": {
    "iso:country":"IN",
    "ks:ks_name":"Bellipal",
    "ks:ks_pop":64,
    "ks:ks_type":"HABITATION",
    "name:eng_x_preferred":[
        "Bellipal"
    ],
    "wof:name":"Bellipal",
    "wof:placetype":"locality",
    "wof:population":64
},
  "geometry": {"coordinates":[74.577313,14.897742],"type":"Point"}
}