{
  "type": "Feature",
  "properties": {
    "iso:country":"IN",
    "ks:ks_name":"Fanaskond",
    "ks:ks_pop":243,
    "ks:ks_type":"VILLAGE",
    "ks:ks_uagg_main":0,
    "name:eng_x_preferred":[
        "Fanaskond"
    ],
    "wof:name":"Fanaskond",
    "wof:placetype":"neighbourhood",
    "wof:population":243
},
  "geometry": {"coordinates":[73.463432,17.909962],"type":"Point"}
}