{
  "type": "Feature",
  "properties": {
    "gn:admin1_code":"12.0",
    "gn:admin2_code":"7.0",
    "gn:asciiname":"Nagrota",
    "gn:country_code":"IN",
    "gn:dem":489,
    "gn:feature_class":"P",
    "gn:feature_code":"PPL",
    "gn:name":"Nagrota",
    "gn:population":0,
    "gn:timezone":"Asia/Kolkata",
    "iso:country":"IN",
    "name:hin_x_preferred":[
        "\u0928\u0917\u0930\u094b\u091f\u093e"
    ],
    "name:nld_x_preferred":[
        "Nagrota"
    ],
    "wof:name":"Nagrota",
    "wof:placetype":"locality"
},
  "geometry": {"coordinates":[75.64315999999999,32.46867],"type":"Point"}
}