{
  "type": "Feature",
  "properties": {
    "iso:country":"IN",
    "ks:ks_name":"Bommikapeta",
    "ks:ks_pop":55,
    "ks:ks_type":"HABITATION",
    "name:eng_x_preferred":[
        "Bommikapeta"
    ],
    "wof:name":"Bommikapeta",
    "wof:placetype":"locality",
    "wof:population":55
},
  "geometry": {"coordinates":[84.02478499999999,18.58949],"type":"Point"}
}