{
  "type": "Feature",
  "properties": {
    "iso:country":"IN",
    "ks:ks_name":"Karegapadar",
    "ks:ks_pop":62,
    "ks:ks_type":"VILLAGE",
    "name:eng_x_preferred":[
        "Karegapadar"
    ],
    "wof:name":"Karegapadar",
    "wof:placetype":"locality",
    "wof:population":62
},
  "geometry": {"coordinates":[83.719036,19.433857],"type":"Point"}
}