{
  "type": "Feature",
  "properties": {
    "iso:country":"IN",
    "ks:ks_name":"Kholanai",
    "ks:ks_pop":238,
    "ks:ks_type":"VILLAGE",
    "name:eng_x_preferred":[
        "Kholanai"
    ],
    "wof:name":"Kholanai",
    "wof:placetype":"locality",
    "wof:population":238
},
  "geometry": {"coordinates":[86.648832,20.470223],"type":"Point"}
}