{
  "type": "Feature",
  "properties": {
    "gn:admin1_code":"11",
    "gn:admin2_code":"23.0",
    "gn:asciiname":"Chinar",
    "gn:country_code":"IN",
    "gn:dem":2514,
    "gn:feature_class":"P",
    "gn:feature_code":"PPL",
    "gn:name":"Chin\u0101r",
    "gn:population":0,
    "gn:timezone":"Asia/Kolkata",
    "iso:country":"IN",
    "wof:name":"Chinar",
    "wof:placetype":"locality"
},
  "geometry": {"coordinates":[76.40770000000001,33.07837],"type":"Point"}
}