{
  "type": "Feature",
  "properties": {
    "iso:country":"IN",
    "ks:ks_alt_nam":"PUNIO KA TALA",
    "ks:ks_name":"Punio Ka Tala",
    "ks:ks_pop":103,
    "ks:ks_type":"HABITATION",
    "name:eng_x_preferred":[
        "Punio Ka Tala"
    ],
    "wof:name":"Punio Ka Tala",
    "wof:placetype":"locality",
    "wof:population":103
},
  "geometry": {"coordinates":[71.440056,25.400656],"type":"Point"}
}