{
  "type": "Feature",
  "properties": {
    "iso:country":"IN",
    "ks:ks_name":"Garvanipada",
    "ks:ks_pop":820,
    "ks:ks_type":"VILLAGE",
    "name:eng_x_preferred":[
        "Garvanipada"
    ],
    "wof:name":"Garvanipada",
    "wof:placetype":"locality",
    "wof:population":820
},
  "geometry": {"coordinates":[85.32623100000001,20.216466],"type":"Point"}
}