{
  "type": "Feature",
  "properties": {
    "gn:admin1_code":"2.0",
    "gn:admin2_code":"549.0",
    "gn:asciiname":"Velagapudi",
    "gn:country_code":"IN",
    "gn:dem":8,
    "gn:feature_class":"P",
    "gn:feature_code":"PPL",
    "gn:name":"Velagap\u016bdi",
    "gn:population":0,
    "gn:timezone":"Asia/Kolkata",
    "iso:country":"IN",
    "name:tel_x_preferred":[
        "\u0c35\u0c46\u0c32\u0c17\u0c2a\u0c42\u0c21\u0c3f"
    ],
    "wof:name":"Velagapudi",
    "wof:placetype":"locality"
},
  "geometry": {"coordinates":[80.06522,15.32211],"type":"Point"}
}