{
  "type": "Feature",
  "properties": {
    "iso:country":"IN",
    "ks:ks_alt_nam":"ASHO",
    "ks:ks_name":"Asho",
    "ks:ks_pop":1281,
    "ks:ks_type":"HABITATION",
    "name:eng_x_preferred":[
        "Asho"
    ],
    "wof:name":"Asho",
    "wof:placetype":"locality",
    "wof:population":1281
},
  "geometry": {"coordinates":[86.246514,25.87221],"type":"Point"}
}