{
  "type": "Feature",
  "properties": {
    "gn:admin1_code":"12.0",
    "gn:admin2_code":"16.0",
    "gn:asciiname":"Bungalow",
    "gn:country_code":"IN",
    "gn:dem":1852,
    "gn:feature_class":"P",
    "gn:feature_code":"PPL",
    "gn:name":"Bungalow",
    "gn:population":0,
    "gn:timezone":"Asia/Kolkata",
    "iso:country":"IN",
    "name:bul_x_preferred":[
        "\u0411\u0443\u043d\u0433\u0430\u043b\u043e"
    ],
    "name:cat_x_preferred":[
        "Bungalou"
    ],
    "name:ces_x_preferred":[
        "Bungalov"
    ],
    "name:cym_x_preferred":[
        "Byngalo"
    ],
    "name:dan_x_preferred":[
        "Bungalow"
    ],
    "name:deu_x_preferred":[
        "Bungalow"
    ],
    "name:epo_x_preferred":[
        "Bangalo"
    ],
    "name:est_x_preferred":[
        "Bangalo"
    ],
    "name:eus_x_preferred":[
        "Bungalow"
    ],
    "name:fas_x_preferred":[
        "\u0628\u0627\u0646\u06af\u0627\u0644\u0648"
    ],
    "name:fin_x_preferred":[
        "Bungalow"
    ],
    "name:fra_x_preferred":[
        "Bungalow"
    ],
    "name:heb_x_preferred":[
        "\u05d1\u05d5\u05e0\u05d2\u05dc\u05d5"
    ],
    "name:ina_x_preferred":[
        "Bungalow"
    ],
    "name:ind_x_preferred":[
        "Bungalow"
    ],
    "name:ita_x_preferred":[
        "Bungalow"
    ],
    "name:jpn_x_preferred":[
        "\u30d0\u30f3\u30ac\u30ed\u30fc"
    ],
    "name:msa_x_preferred":[
        "Banglo"
    ],
    "name:nld_x_preferred":[
        "Bungalow"
    ],
    "name:nor_x_preferred":[
        "Bungalow"
    ],
    "name:pnb_x_preferred":[
        "\u0628\u0646\u06af\u0644\u0627"
    ],
    "name:pol_x_preferred":[
        "Bungalow"
    ],
    "name:por_x_preferred":[
        "Bangal\u00f4"
    ],
    "name:rus_x_preferred":[
        "\u0411\u0443\u043d\u0433\u0430\u043b\u043e"
    ],
    "name:spa_x_preferred":[
        "Bungal\u00f3"
    ],
    "name:swe_x_preferred":[
        "Bungalow"
    ],
    "name:tam_x_preferred":[
        "\u0b93\u0bb0\u0b9f\u0bc1\u0b95\u0bcd\u0b95\u0bc1 \u0bae\u0ba9\u0bc8"
    ],
    "name:tel_x_preferred":[
        "\u0c2c\u0c02\u0c17\u0c4d\u0c32\u0c3e"
    ],
    "name:tha_x_preferred":[
        "\u0e1a\u0e31\u0e07\u0e01\u0e30\u0e42\u0e25"
    ],
    "name:ukr_x_preferred":[
        "\u0411\u0443\u043d\u0433\u0430\u043b\u043e"
    ],
    "name:vie_x_preferred":[
        "Bungalow"
    ],
    "wof:name":"Bungalow",
    "wof:placetype":"locality"
},
  "geometry": {"coordinates":[75.85604000000002,33.03986],"type":"Point"}
}