{
  "type": "Feature",
  "properties": {
    "gn:admin1_code":"24.0",
    "gn:admin2_code":"124.0",
    "gn:asciiname":"Nawadera",
    "gn:country_code":"IN",
    "gn:dem":288,
    "gn:feature_class":"P",
    "gn:feature_code":"PPL",
    "gn:name":"Naw\u0101dera",
    "gn:population":0,
    "gn:timezone":"Asia/Kolkata",
    "iso:country":"IN",
    "ks:ks_alt_nam":"Naw\u0101dera",
    "ks:ks_name":"Nawadera",
    "ks:ks_type":"VILLAGE",
    "ks:ks_uagg_main":0,
    "name:eng_x_preferred":[
        "Nawadera"
    ],
    "name:eng_x_variant":[
        "Naw\u0101dera"
    ],
    "wof:name":"Nawadera",
    "wof:placetype":"neighbourhood"
},
  "geometry": {"coordinates":[73.702398,23.84276],"type":"Point"}
}