{
  "type": "Feature",
  "properties": {
    "iso:country":"IN",
    "ks:ks_name":"Duutka",
    "ks:ks_pop":978,
    "ks:ks_type":"HABITATION",
    "name:eng_x_preferred":[
        "Duutka"
    ],
    "wof:name":"Duutka",
    "wof:placetype":"locality",
    "wof:population":978
},
  "geometry": {"coordinates":[80.517634,22.582602],"type":"Point"}
}