{
  "type": "Feature",
  "properties": {
    "iso:country":"IN",
    "ks:ks_name":"Damda Chhota",
    "ks:ks_pop":499,
    "ks:ks_type":"HABITATION",
    "name:eng_x_preferred":[
        "Damda Chhota"
    ],
    "wof:name":"Damda Chhota",
    "wof:placetype":"locality",
    "wof:population":499
},
  "geometry": {"coordinates":[81.786511,27.857969],"type":"Point"}
}