{
  "type": "Feature",
  "properties": {
    "iso:country":"IN",
    "ks:ks_name":"Kudigu",
    "ks:ks_pop":104,
    "ks:ks_type":"HABITATION",
    "name:eng_x_preferred":[
        "Kudigu"
    ],
    "wof:name":"Kudigu",
    "wof:placetype":"locality",
    "wof:population":104
},
  "geometry": {"coordinates":[75.406575,12.741771],"type":"Point"}
}