{
  "type": "Feature",
  "properties": {
    "iso:country":"IN",
    "ks:ks_name":"Kherane Kh",
    "ks:ks_pop":1129,
    "ks:ks_type":"VILLAGE",
    "name:eng_x_preferred":[
        "Kherane Kh"
    ],
    "wof:name":"Kherane Kh",
    "wof:placetype":"locality",
    "wof:population":1129
},
  "geometry": {"coordinates":[73.14270999999999,19.082286],"type":"Point"}
}