{
  "type": "Feature",
  "properties": {
    "iso:country":"IN",
    "ks:ks_alt_nam":"BALMU BIGHA",
    "ks:ks_name":"Balmu Bigha",
    "ks:ks_pop":105,
    "ks:ks_type":"HABITATION",
    "name:eng_x_preferred":[
        "Balmu Bigha"
    ],
    "wof:name":"Balmu Bigha",
    "wof:placetype":"locality",
    "wof:population":105
},
  "geometry": {"coordinates":[84.950788,25.009079],"type":"Point"}
}