{
  "type": "Feature",
  "properties": {
    "iso:country":"IN",
    "ks:ks_name":"Gauwnbasti",
    "ks:ks_pop":32,
    "ks:ks_type":"HABITATION",
    "name:eng_x_preferred":[
        "Gauwnbasti"
    ],
    "wof:name":"Gauwnbasti",
    "wof:placetype":"locality",
    "wof:population":32
},
  "geometry": {"coordinates":[83.12517200000001,24.602137],"type":"Point"}
}