{
  "type": "Feature",
  "properties": {
    "gn:admin1_code":"34.0",
    "gn:admin2_code":"235.0",
    "gn:asciiname":"Suhi",
    "gn:country_code":"IN",
    "gn:dem":140,
    "gn:feature_class":"P",
    "gn:feature_code":"PPL",
    "gn:name":"S\u016bh\u012b",
    "gn:population":0,
    "gn:timezone":"Asia/Kolkata",
    "iso:country":"IN",
    "ks:ks_alt_nam":"S\u016bh\u012b",
    "ks:ks_name":"Suhi",
    "ks:ks_pop":349,
    "ks:ks_type":"VILLAGE",
    "name:eng_x_preferred":[
        "Suhi"
    ],
    "name:eng_x_variant":[
        "S\u016bh\u012b"
    ],
    "wof:name":"Suhi",
    "wof:placetype":"locality",
    "wof:population":349
},
  "geometry": {"coordinates":[84.214795,24.630125],"type":"Point"}
}