{
  "type": "Feature",
  "properties": {
    "gn:admin1_code":"34.0",
    "gn:admin2_code":"235.0",
    "gn:asciiname":"Suhi",
    "gn:country_code":"IN",
    "gn:dem":140,
    "gn:feature_class":"P",
    "gn:feature_code":"PPL",
    "gn:name":"S\u016bh\u012b",
    "gn:population":0,
    "gn:timezone":"Asia/Kolkata",
    "iso:country":"IN",
    "wof:name":"Suhi",
    "wof:placetype":"locality"
},
  "geometry": {"coordinates":[84.21086,24.63426],"type":"Point"}
}