{
  "type": "Feature",
  "properties": {
    "iso:country":"IN",
    "ks:ks_alt_nam":"M\u0101ghpur Hul\u0101s",
    "ks:ks_name":"Maghpur Hulas",
    "ks:ks_type":"VILLAGE",
    "name:eng_x_preferred":[
        "Maghpur Hulas"
    ],
    "name:eng_x_variant":[
        "M\u0101ghpur Hul\u0101s"
    ],
    "wof:name":"Maghpur Hulas",
    "wof:placetype":"locality"
},
  "geometry": {"coordinates":[78.601303,29.132698],"type":"Point"}
}