{
  "type": "Feature",
  "properties": {
    "iso:country":"IN",
    "ks:ks_name":"Muthiri",
    "ks:ks_pop":309,
    "ks:ks_type":"HABITATION",
    "name:eng_x_preferred":[
        "Muthiri"
    ],
    "wof:name":"Muthiri",
    "wof:placetype":"locality",
    "wof:population":309
},
  "geometry": {"coordinates":[76.85945,11.363944],"type":"Point"}
}