{
  "type": "Feature",
  "properties": {
    "gn:admin1_code":"38.0",
    "gn:admin2_code":"347.0",
    "gn:asciiname":"Patharia",
    "gn:country_code":"IN",
    "gn:dem":433,
    "gn:feature_class":"P",
    "gn:feature_code":"PPL",
    "gn:name":"Pathari\u0101",
    "gn:population":0,
    "gn:timezone":"Asia/Kolkata",
    "iso:country":"IN",
    "name:ben_x_preferred":[
        "\u09aa\u09be\u09a5\u09be\u09b0\u09bf\u09af\u09bc\u09be"
    ],
    "name:bih_x_preferred":[
        "\u092a\u0925\u0930\u093f\u092f\u093e"
    ],
    "name:bpy_x_preferred":[
        "\u09aa\u09be\u09a5\u09be\u09b0\u09bf\u09af\u09bc\u09be"
    ],
    "name:cat_x_preferred":[
        "Patharia"
    ],
    "name:ceb_x_preferred":[
        "Patharia"
    ],
    "name:ita_x_preferred":[
        "Patharia"
    ],
    "name:msa_x_preferred":[
        "Patharia"
    ],
    "name:nld_x_preferred":[
        "Patharia"
    ],
    "name:por_x_preferred":[
        "Patharia"
    ],
    "name:spa_x_preferred":[
        "Patharia"
    ],
    "name:vie_x_preferred":[
        "Patharia"
    ],
    "name:zho_x_preferred":[
        "\u5e15\u5854\u91cc\u4e9a"
    ],
    "wof:name":"Patharia",
    "wof:placetype":"locality"
},
  "geometry": {"coordinates":[85.18682,24.26413],"type":"Point"}
}