{
  "type": "Feature",
  "properties": {
    "iso:country":"IN",
    "ks:ks_name":"Nilkanthpur",
    "ks:ks_pop":356,
    "ks:ks_type":"VILLAGE",
    "ks:ks_uagg_main":0,
    "name:eng_x_preferred":[
        "Nilkanthpur"
    ],
    "wof:name":"Nilkanthpur",
    "wof:placetype":"neighbourhood",
    "wof:population":356
},
  "geometry": {"coordinates":[87.20568799999999,24.8754],"type":"Point"}
}