{
  "type": "Feature",
  "properties": {
    "iso:country":"IN",
    "ks:ks_name":"Iyyapuram",
    "ks:ks_pop":487,
    "ks:ks_type":"HABITATION",
    "ks:ks_uagg_main":0,
    "name:eng_x_preferred":[
        "Iyyapuram"
    ],
    "wof:name":"Iyyapuram",
    "wof:placetype":"neighbourhood",
    "wof:population":487
},
  "geometry": {"coordinates":[77.683842,9.091707],"type":"Point"}
}