{
  "type": "Feature",
  "properties": {
    "iso:country":"IN",
    "ks:ks_name":"Pratapmath",
    "ks:ks_pop":284,
    "ks:ks_type":"VILLAGE",
    "name:eng_x_preferred":[
        "Pratapmath"
    ],
    "wof:name":"Pratapmath",
    "wof:placetype":"locality",
    "wof:population":284
},
  "geometry": {"coordinates":[87.612762,23.122879],"type":"Point"}
}