{
  "type": "Feature",
  "properties": {
    "gn:admin1_code":"2.0",
    "gn:admin2_code":"550.0",
    "gn:asciiname":"Rapuryarikhandrika",
    "gn:country_code":"IN",
    "gn:dem":15,
    "gn:feature_class":"P",
    "gn:feature_code":"PPL",
    "gn:name":"R\u0101p\u016bry\u0101rikhandrika",
    "gn:population":0,
    "gn:timezone":"Asia/Kolkata",
    "iso:country":"IN",
    "wof:name":"Rapuryarikhandrika",
    "wof:placetype":"neighbourhood"
},
  "geometry": {"coordinates":[80.03569,14.39309],"type":"Point"}
}