{
  "type": "Feature",
  "properties": {
    "gn:admin1_code":"36",
    "gn:admin2_code":"188.0",
    "gn:asciiname":"Chautara Patti Kutia",
    "gn:country_code":"IN",
    "gn:dem":84,
    "gn:feature_class":"P",
    "gn:feature_code":"PPL",
    "gn:name":"Chautara Patti Kutia",
    "gn:population":0,
    "gn:timezone":"Asia/Kolkata",
    "iso:country":"IN",
    "wof:name":"Chautara Patti Kutia",
    "wof:placetype":"neighbourhood"
},
  "geometry": {"coordinates":[83.11977,26.45286],"type":"Point"}
}