{
  "type": "Feature",
  "properties": {
    "gn:admin1_code":"36",
    "gn:admin2_code":"163.0",
    "gn:asciiname":"Dundua Mahua",
    "gn:country_code":"IN",
    "gn:dem":144,
    "gn:feature_class":"P",
    "gn:feature_code":"PPL",
    "gn:name":"Dundua Mahua",
    "gn:population":0,
    "gn:timezone":"Asia/Kolkata",
    "iso:country":"IN",
    "wof:name":"Dundua Mahua",
    "wof:placetype":"locality"
},
  "geometry": {"coordinates":[79.74686,26.69654],"type":"Point"}
}