{
  "type": "Feature",
  "properties": {
    "iso:country":"IN",
    "ks:ks_name":"Ukhri Seri",
    "ks:ks_pop":251,
    "ks:ks_type":"HABITATION",
    "name:eng_x_preferred":[
        "Ukhri Seri"
    ],
    "wof:name":"Ukhri Seri",
    "wof:placetype":"locality",
    "wof:population":251
},
  "geometry": {"coordinates":[80.211135,29.654545],"type":"Point"}
}