{
  "type": "Feature",
  "properties": {
    "iso:country":"IN",
    "ks:ks_name":"Haripur",
    "ks:ks_pop":522,
    "ks:ks_type":"VILLAGE",
    "name:eng_x_preferred":[
        "Haripur"
    ],
    "wof:name":"Haripur",
    "wof:placetype":"locality",
    "wof:population":522
},
  "geometry": {"coordinates":[87.522211,23.146552],"type":"Point"}
}