{
  "type": "Feature",
  "properties": {
    "gn:admin1_code":"38",
    "gn:admin2_code":"346.0",
    "gn:asciiname":"Uchri",
    "gn:country_code":"IN",
    "gn:dem":389,
    "gn:feature_class":"P",
    "gn:feature_code":"PPL",
    "gn:name":"Uchr\u012b",
    "gn:population":0,
    "gn:timezone":"Asia/Kolkata",
    "iso:country":"IN",
    "ks:ks_alt_nam":"Uchr\u012b",
    "ks:ks_name":"Uchri",
    "ks:ks_pop":1007,
    "ks:ks_type":"VILLAGE",
    "name:eng_x_preferred":[
        "Uchri"
    ],
    "name:eng_x_variant":[
        "Uchr\u012b"
    ],
    "wof:name":"Uchri",
    "wof:placetype":"locality",
    "wof:population":1007
},
  "geometry": {"coordinates":[83.75706099999999,23.979385],"type":"Point"}
}