{
  "type": "Feature",
  "properties": {
    "iso:country":"IN",
    "ks:ks_name":"Sahana",
    "ks:ks_pop":1765,
    "ks:ks_type":"VILLAGE",
    "ks:ks_uagg_main":0,
    "name:eng_x_preferred":[
        "Sahana"
    ],
    "wof:name":"Sahana",
    "wof:placetype":"locality",
    "wof:population":1765
},
  "geometry": {"coordinates":[88.27099200000001,22.755172],"type":"Point"}
}