{
  "type": "Feature",
  "properties": {
    "iso:country":"IN",
    "ks:ks_alt_nam":"URAON TOLI",
    "ks:ks_name":"Uraon Toli",
    "ks:ks_pop":198,
    "ks:ks_type":"HABITATION",
    "name:eng_x_preferred":[
        "Uraon Toli"
    ],
    "wof:name":"Uraon Toli",
    "wof:placetype":"locality",
    "wof:population":198
},
  "geometry": {"coordinates":[83.801519,23.237497],"type":"Point"}
}