{
  "type": "Feature",
  "properties": {
    "gn:admin1_code":"36.0",
    "gn:admin2_code":"149",
    "gn:asciiname":"Mirzapur Basant",
    "gn:country_code":"IN",
    "gn:dem":154,
    "gn:feature_class":"P",
    "gn:feature_code":"PPL",
    "gn:name":"Mirz\u0101pur Basant",
    "gn:population":0,
    "gn:timezone":"Asia/Kolkata",
    "iso:country":"IN",
    "wof:name":"Mirzapur Basant",
    "wof:placetype":"locality"
},
  "geometry": {"coordinates":[79.21884,27.79223],"type":"Point"}
}