{
  "type": "Feature",
  "properties": {
    "gn:admin1_code":"36",
    "gn:admin2_code":"195.0",
    "gn:asciiname":"Karanda",
    "gn:country_code":"IN",
    "gn:dem":77,
    "gn:feature_class":"P",
    "gn:feature_code":"PPL",
    "gn:name":"Karanda",
    "gn:population":0,
    "gn:timezone":"Asia/Kolkata",
    "iso:country":"IN",
    "ks:ks_name":"Karanda",
    "ks:ks_pop":2971,
    "ks:ks_type":"VILLAGE",
    "ks:ks_uagg_main":0,
    "name:ceb_x_preferred":[
        "Karanda"
    ],
    "name:eng_x_preferred":[
        "Karanda"
    ],
    "name:swe_x_preferred":[
        "Karanda"
    ],
    "wof:name":"Karanda",
    "wof:placetype":"neighbourhood",
    "wof:population":2971
},
  "geometry": {"coordinates":[83.464833,25.490266],"type":"Point"}
}