{
  "type": "Feature",
  "properties": {
    "iso:country":"IN",
    "ks:ks_name":"Panchasi",
    "ks:ks_pop":1329,
    "ks:ks_type":"VILLAGE",
    "name:eng_x_preferred":[
        "Panchasi"
    ],
    "wof:name":"Panchasi",
    "wof:placetype":"locality",
    "wof:population":1329
},
  "geometry": {"coordinates":[91.832858,24.17949],"type":"Point"}
}