{
  "type": "Feature",
  "properties": {
    "gn:admin1_code":"39.0",
    "gn:admin2_code":"63.0",
    "gn:asciiname":"Dhamoli",
    "gn:country_code":"IN",
    "gn:dem":1244,
    "gn:feature_class":"P",
    "gn:feature_code":"PPL",
    "gn:name":"Dhamoli",
    "gn:population":0,
    "gn:timezone":"Asia/Kolkata",
    "iso:country":"IN",
    "wof:name":"Dhamoli",
    "wof:placetype":"locality"
},
  "geometry": {"coordinates":[79.70531,29.89208],"type":"Point"}
}