{
  "type": "Feature",
  "properties": {
    "gn:admin1_code":"36.0",
    "gn:admin2_code":"162",
    "gn:asciiname":"Parhin",
    "gn:country_code":"IN",
    "gn:dem":140,
    "gn:feature_class":"P",
    "gn:feature_code":"PPL",
    "gn:name":"Parh\u012bn",
    "gn:population":0,
    "gn:timezone":"Asia/Kolkata",
    "iso:country":"IN",
    "wof:name":"Parhin",
    "wof:placetype":"locality"
},
  "geometry": {"coordinates":[79.48822,26.49912],"type":"Point"}
}