{
  "type": "Feature",
  "properties": {
    "gn:admin1_code":"36.0",
    "gn:admin2_code":"175.0",
    "gn:asciiname":"Baswanapur",
    "gn:country_code":"IN",
    "gn:dem":102,
    "gn:feature_class":"P",
    "gn:feature_code":"PPL",
    "gn:name":"Baswan\u0101pur",
    "gn:population":0,
    "gn:timezone":"Asia/Kolkata",
    "iso:country":"IN",
    "ks:ks_name":"Basaonapur",
    "ks:ks_pop":500,
    "ks:ks_type":"HABITATION",
    "name:eng_x_preferred":[
        "Basaonapur"
    ],
    "name:eng_x_variant":[
        "Baswanapur"
    ],
    "wof:name":"Basaonapur",
    "wof:placetype":"locality",
    "wof:population":500
},
  "geometry": {"coordinates":[81.927813,25.727545],"type":"Point"}
}