{
  "type": "Feature",
  "properties": {
    "gn:admin1_code":"23.0",
    "gn:admin2_code":"38.0",
    "gn:asciiname":"Kukanet",
    "gn:country_code":"IN",
    "gn:dem":446,
    "gn:feature_class":"P",
    "gn:feature_code":"PPL",
    "gn:name":"Kukanet",
    "gn:population":0,
    "gn:timezone":"Asia/Kolkata",
    "iso:country":"IN",
    "ks:ks_name":"Kukanet",
    "ks:ks_pop":991,
    "ks:ks_type":"VILLAGE",
    "name:eng_x_preferred":[
        "Kukanet"
    ],
    "wof:name":"Kukanet",
    "wof:placetype":"locality",
    "wof:population":991
},
  "geometry": {"coordinates":[75.91483700000001,31.75932],"type":"Point"}
}