{
  "type": "Feature",
  "properties": {
    "iso:country":"IN",
    "ks:ks_name":"Ganga Kheda",
    "ks:ks_pop":132,
    "ks:ks_type":"HABITATION",
    "ks:ks_uagg_main":0,
    "name:eng_x_preferred":[
        "Ganga Kheda"
    ],
    "wof:name":"Ganga Kheda",
    "wof:placetype":"neighbourhood",
    "wof:population":132
},
  "geometry": {"coordinates":[80.95733300000001,26.50558],"type":"Point"}
}