{
  "type": "Feature",
  "properties": {
    "iso:country":"IN",
    "ks:ks_name":"Sarkar Para",
    "ks:ks_pop":1170,
    "ks:ks_type":"HABITATION",
    "name:eng_x_preferred":[
        "Sarkar Para"
    ],
    "wof:name":"Sarkar Para",
    "wof:placetype":"locality",
    "wof:population":1170
},
  "geometry": {"coordinates":[89.721902,26.320381],"type":"Point"}
}