{
  "type": "Feature",
  "properties": {
    "iso:country":"IN",
    "ks:ks_name":"Vadi",
    "ks:ks_pop":493,
    "ks:ks_type":"VILLAGE",
    "name:eng_x_preferred":[
        "Vadi"
    ],
    "wof:name":"Vadi",
    "wof:placetype":"locality",
    "wof:population":493
},
  "geometry": {"coordinates":[73.983065,15.373181],"type":"Point"}
}