{
  "type": "Feature",
  "properties": {
    "iso:country":"IN",
    "ks:ks_name":"Chikhli",
    "ks:ks_type":"VILLAGE",
    "name:eng_x_preferred":[
        "Chikhli"
    ],
    "wof:name":"Chikhli",
    "wof:placetype":"locality"
},
  "geometry": {"coordinates":[77.548123,21.265741],"type":"Point"}
}