{
  "type": "Feature",
  "properties": {
    "gn:admin1_code":"16.0",
    "gn:admin2_code":"499.0",
    "gn:asciiname":"Satara",
    "gn:country_code":"IN",
    "gn:dem":204,
    "gn:feature_class":"P",
    "gn:feature_code":"PPL",
    "gn:name":"Sat\u0101ra",
    "gn:population":0,
    "gn:timezone":"Asia/Kolkata",
    "iso:country":"IN",
    "name:bih_x_preferred":[
        "\u0938\u0924\u093e\u0930\u093e"
    ],
    "name:ceb_x_preferred":[
        "Satara"
    ],
    "name:deu_x_preferred":[
        "Satara"
    ],
    "name:nld_x_preferred":[
        "Satara"
    ],
    "name:ron_x_preferred":[
        "Satara"
    ],
    "name:swe_x_preferred":[
        "Satara"
    ],
    "wof:name":"Satara",
    "wof:placetype":"locality"
},
  "geometry": {"coordinates":[75.77584,21.04937],"type":"Point"}
}