{
  "type": "Feature",
  "properties": {
    "gn:admin1_code":"38",
    "gn:admin2_code":"358.0",
    "gn:asciiname":"Nawa",
    "gn:country_code":"IN",
    "gn:dem":316,
    "gn:feature_class":"P",
    "gn:feature_code":"PPL",
    "gn:name":"N\u0101wa",
    "gn:population":0,
    "gn:timezone":"Asia/Kolkata",
    "iso:country":"IN",
    "name:ceb_x_preferred":[
        "Nawa"
    ],
    "name:deu_x_preferred":[
        "Nawa"
    ],
    "name:ita_x_preferred":[
        "Nawa"
    ],
    "name:pol_x_preferred":[
        "Nawa"
    ],
    "name:rus_x_preferred":[
        "\u041d\u0430\u0432\u0430"
    ],
    "name:swe_x_preferred":[
        "Nawa"
    ],
    "name:ukr_x_preferred":[
        "\u041d\u0430\u0432\u0430"
    ],
    "wof:name":"Nawa",
    "wof:placetype":"locality"
},
  "geometry": {"coordinates":[84.09908,24.28546],"type":"Point"}
}