{
  "type": "Feature",
  "properties": {
    "iso:country":"IN",
    "ks:ks_name":"Sah Toli",
    "ks:ks_pop":774,
    "ks:ks_type":"HABITATION",
    "name:eng_x_preferred":[
        "Sah Toli"
    ],
    "wof:name":"Sah Toli",
    "wof:placetype":"locality",
    "wof:population":774
},
  "geometry": {"coordinates":[83.84083699999999,25.450613],"type":"Point"}
}