{
  "type": "Feature",
  "properties": {
    "iso:country":"IN",
    "ks:ks_alt_nam":"4 URURAL",
    "ks:ks_name":"4 Urural",
    "ks:ks_pop":20,
    "ks:ks_type":"HABITATION",
    "name:eng_x_preferred":[
        "4 Urural"
    ],
    "wof:name":"4 Urural",
    "wof:placetype":"locality",
    "wof:population":20
},
  "geometry": {"coordinates":[73.644792,29.928022],"type":"Point"}
}