{
  "type": "Feature",
  "properties": {
    "gn:admin1_code":"36.0",
    "gn:admin2_code":"155.0",
    "gn:asciiname":"Chamaren Purwa",
    "gn:country_code":"IN",
    "gn:dem":141,
    "gn:feature_class":"P",
    "gn:feature_code":"PPL",
    "gn:name":"Cham\u0101ren Purwa",
    "gn:population":0,
    "gn:timezone":"Asia/Kolkata",
    "iso:country":"IN",
    "wof:name":"Chamaren Purwa",
    "wof:placetype":"locality"
},
  "geometry": {"coordinates":[80.23791999999997,27.425],"type":"Point"}
}