{
  "type": "Feature",
  "properties": {
    "iso:country":"IN",
    "ks:ks_alt_nam":"Thoriyoka bera",
    "ks:ks_name":"Thoriyoka Bera",
    "ks:ks_pop":772,
    "ks:ks_type":"HABITATION",
    "name:eng_x_preferred":[
        "Thoriyoka Bera"
    ],
    "wof:name":"Thoriyoka Bera",
    "wof:placetype":"locality",
    "wof:population":772
},
  "geometry": {"coordinates":[72.638003,27.132436],"type":"Point"}
}