{
  "type": "Feature",
  "properties": {
    "iso:country":"IN",
    "ks:ks_name":"Harizan Basti",
    "ks:ks_pop":224,
    "ks:ks_type":"HABITATION",
    "name:eng_x_preferred":[
        "Harizan Basti"
    ],
    "wof:name":"Harizan Basti",
    "wof:placetype":"locality",
    "wof:population":224
},
  "geometry": {"coordinates":[82.958844,25.512173],"type":"Point"}
}