{
  "type": "Feature",
  "properties": {
    "iso:country":"IN",
    "ks:ks_name":"Tarmabordi",
    "ks:ks_pop":272,
    "ks:ks_type":"HABITATION",
    "name:eng_x_preferred":[
        "Tarmabordi"
    ],
    "wof:name":"Tarmabordi",
    "wof:placetype":"locality",
    "wof:population":272
},
  "geometry": {"coordinates":[74.866381,23.330202],"type":"Point"}
}