{
  "type": "Feature",
  "properties": {
    "iso:country":"IN",
    "ks:ks_name":"Tamta",
    "ks:ks_pop":283,
    "ks:ks_type":"HABITATION",
    "name:eng_x_preferred":[
        "Tamta"
    ],
    "wof:name":"Tamta",
    "wof:placetype":"locality",
    "wof:population":283
},
  "geometry": {"coordinates":[74.636325,24.199917],"type":"Point"}
}