{
  "type": "Feature",
  "properties": {
    "iso:country":"IN",
    "ks:ks_name":"Elavengal",
    "ks:ks_pop":517,
    "ks:ks_type":"HABITATION",
    "ks:ks_uagg_main":0,
    "name:eng_x_preferred":[
        "Elavengal"
    ],
    "wof:name":"Elavengal",
    "wof:placetype":"neighbourhood",
    "wof:population":517
},
  "geometry": {"coordinates":[76.185332,11.858376],"type":"Point"}
}