{
  "type": "Feature",
  "properties": {
    "iso:country":"IN",
    "ks:ks_alt_nam":"talaipada",
    "ks:ks_name":"Talaipada",
    "ks:ks_pop":128,
    "ks:ks_type":"HABITATION",
    "ks:ks_uagg_main":0,
    "name:eng_x_preferred":[
        "Talaipada"
    ],
    "wof:name":"Talaipada",
    "wof:placetype":"neighbourhood",
    "wof:population":128
},
  "geometry": {"coordinates":[72.981452,19.646214],"type":"Point"}
}