{
  "type": "Feature",
  "properties": {
    "gn:admin1_code":"12.0",
    "gn:admin2_code":"19.0",
    "gn:asciiname":"Kori",
    "gn:country_code":"IN",
    "gn:dem":603,
    "gn:feature_class":"P",
    "gn:feature_code":"PPL",
    "gn:name":"Kori",
    "gn:population":0,
    "gn:timezone":"Asia/Kolkata",
    "iso:country":"IN",
    "wof:name":"Kori",
    "wof:placetype":"locality"
},
  "geometry": {"coordinates":[75.30418,32.65029000000001],"type":"Point"}
}