{
  "type": "Feature",
  "properties": {
    "gn:admin1_code":"36.0",
    "gn:admin2_code":"135.0",
    "gn:asciiname":"Kishanpur",
    "gn:country_code":"IN",
    "gn:dem":213,
    "gn:feature_class":"P",
    "gn:feature_code":"PPL",
    "gn:name":"Kishanpur",
    "gn:population":0,
    "gn:timezone":"Asia/Kolkata",
    "iso:country":"IN",
    "ks:ks_name":"Kishanpur",
    "ks:ks_type":"VILLAGE",
    "ks:ks_uagg_main":0,
    "name:eng_x_preferred":[
        "Kishanpur"
    ],
    "name:und_x_variant":[
        "D\u016bl\u0101nagar"
    ],
    "wof:name":"Kishanpur",
    "wof:placetype":"neighbourhood"
},
  "geometry": {"coordinates":[78.93398000000001,29.053852],"type":"Point"}
}