{
  "type": "Feature",
  "properties": {
    "iso:country":"IN",
    "ks:ks_name":"Seganathapuram",
    "ks:ks_pop":300,
    "ks:ks_type":"HABITATION",
    "ks:ks_uagg_main":0,
    "name:eng_x_preferred":[
        "Seganathapuram"
    ],
    "wof:name":"Seganathapuram",
    "wof:placetype":"neighbourhood",
    "wof:population":300
},
  "geometry": {"coordinates":[78.391702,9.393232],"type":"Point"}
}