{
  "type": "Feature",
  "properties": {
    "gn:admin1_code":"2.0",
    "gn:admin2_code":"542.0",
    "gn:asciiname":"Ravivalasa",
    "gn:country_code":"IN",
    "gn:dem":95,
    "gn:feature_class":"P",
    "gn:feature_code":"PPL",
    "gn:name":"R\u0101vivalasa",
    "gn:population":0,
    "gn:timezone":"Asia/Kolkata",
    "iso:country":"IN",
    "name:tel_x_preferred":[
        "\u0c30\u0c3e\u0c35\u0c3f\u0c35\u0c32\u0c38"
    ],
    "wof:name":"Ravivalasa",
    "wof:placetype":"locality"
},
  "geometry": {"coordinates":[83.57765999999999,18.30267000000001],"type":"Point"}
}