{
  "type": "Feature",
  "properties": {
    "iso:country":"IN",
    "ks:ks_name":"Naimgang",
    "ks:ks_pop":629,
    "ks:ks_type":"VILLAGE",
    "ks:ks_uagg_main":0,
    "name:eng_x_preferred":[
        "Naimgang"
    ],
    "wof:name":"Naimgang",
    "wof:placetype":"neighbourhood",
    "wof:population":629
},
  "geometry": {"coordinates":[79.02336,28.691179],"type":"Point"}
}