{
  "type": "Feature",
  "properties": {
    "gn:admin1_code":"39",
    "gn:admin2_code":"66.0",
    "gn:asciiname":"Sipka",
    "gn:country_code":"IN",
    "gn:dem":269,
    "gn:feature_class":"P",
    "gn:feature_code":"PPL",
    "gn:name":"S\u012bpka",
    "gn:population":0,
    "gn:timezone":"Asia/Kolkata",
    "iso:country":"IN",
    "ks:ks_name":"Sipka",
    "ks:ks_pop":49,
    "ks:ks_type":"HABITATION",
    "name:eng_x_preferred":[
        "Sipka"
    ],
    "name:und_x_variant":[
        "S\u012bpka",
        "Patr\u0101mpur"
    ],
    "wof:name":"Sipka",
    "wof:placetype":"locality",
    "wof:population":49
},
  "geometry": {"coordinates":[78.87155,29.35234],"type":"Point"}
}