{
  "type": "Feature",
  "properties": {
    "iso:country":"IN",
    "ks:ks_name":"Pathakurakulapalle",
    "ks:ks_pop":28,
    "ks:ks_type":"HABITATION",
    "name:eng_x_preferred":[
        "Pathakurakulapalle"
    ],
    "wof:name":"Pathakurakulapalle",
    "wof:placetype":"locality",
    "wof:population":28
},
  "geometry": {"coordinates":[78.585611,13.627285],"type":"Point"}
}