{
  "type": "Feature",
  "properties": {
    "iso:country":"IN",
    "ks:ks_alt_nam":"PURAB TOLA",
    "ks:ks_name":"Purab Tola",
    "ks:ks_pop":627,
    "ks:ks_type":"HABITATION",
    "ks:ks_uagg_main":0,
    "name:eng_x_preferred":[
        "Purab Tola"
    ],
    "wof:name":"Purab Tola",
    "wof:placetype":"neighbourhood",
    "wof:population":627
},
  "geometry": {"coordinates":[84.802857,25.889604],"type":"Point"}
}