{
  "type": "Feature",
  "properties": {
    "iso:country":"IN",
    "ks:ks_name":"Pradhaniguda",
    "ks:ks_pop":475,
    "ks:ks_type":"HABITATION",
    "name:eng_x_preferred":[
        "Pradhaniguda"
    ],
    "wof:name":"Pradhaniguda",
    "wof:placetype":"locality",
    "wof:population":475
},
  "geometry": {"coordinates":[82.57302,19.318476],"type":"Point"}
}