{
  "type": "Feature",
  "properties": {
    "iso:country":"IN",
    "ks:ks_name":"Bor Chapda",
    "ks:ks_pop":489,
    "ks:ks_type":"HABITATION",
    "name:eng_x_preferred":[
        "Bor Chapda"
    ],
    "wof:name":"Bor Chapda",
    "wof:placetype":"locality",
    "wof:population":489
},
  "geometry": {"coordinates":[74.851709,21.773301],"type":"Point"}
}