{
  "type": "Feature",
  "properties": {
    "iso:country":"IN",
    "ks:ks_alt_nam":"Akhade bhandaveasti",
    "ks:ks_name":"Akhade Bhandaveasti",
    "ks:ks_pop":350,
    "ks:ks_type":"HABITATION",
    "ks:ks_uagg_main":0,
    "name:eng_x_preferred":[
        "Akhade Bhandaveasti"
    ],
    "wof:name":"Akhade Bhandaveasti",
    "wof:placetype":"neighbourhood",
    "wof:population":350
},
  "geometry": {"coordinates":[74.22865,18.4774],"type":"Point"}
}