{
  "type": "Feature",
  "properties": {
    "iso:country":"IN",
    "name:eng_x_preferred":[
        "Vepery"
    ],
    "name:eng_x_variant":[
        "Madras Vepery"
    ],
    "name:fas_x_preferred":[
        "\u0648\u067e\u0631\u06cc"
    ],
    "name:nld_x_preferred":[
        "Vepery"
    ],
    "name:tam_x_preferred":[
        "\u0bb5\u0bc7\u0baa\u0bcd\u0baa\u0bc7\u0bb0\u0bbf"
    ],
    "qs:gn_adm0_cc":"IN",
    "qs:gn_fcode":"PPL",
    "qs:gn_local":1264527,
    "qs:gn_nam_loc":"Chennai, Chennai, Tamil Nadu, IN",
    "qs:gn_namadm1":"25",
    "qs:gn_name":"Vepery",
    "qs:local_max":2138,
    "qs:local_sum":21081,
    "qs:localhoods":47,
    "qs:name":"Vepery",
    "qs:name_adm0":"India",
    "qs:name_adm1":"Tamil Nadu",
    "qs:name_adm2":"Chennai",
    "qs:name_local":"Chennai",
    "qs:photo_max":309,
    "qs:photo_sum":587,
    "qs:placetype":"Suburb",
    "qs:quad_count":11,
    "qs:woe_adm0":23424848,
    "qs:woe_adm1":2345758,
    "qs:woe_adm2":12586677,
    "qs:woe_lau":0,
    "qs:woe_local":2295424,
    "qs:woe_ver":"7.10.0",
    "wd:wordcount":378,
    "wof:lang":[
        "eng"
    ],
    "wof:name":"Vepery",
    "wof:placetype":"neighbourhood"
},
  "geometry": {"coordinates":[80.27035600000001,13.091385],"type":"Point"}
}