{
  "type": "Feature",
  "properties": {
    "iso:country":"IN",
    "ks:ks_alt_nam":"Parsad\u0101",
    "ks:ks_name":"Parsada",
    "ks:ks_type":"VILLAGE",
    "ks:ks_uagg_main":0,
    "name:eng_x_preferred":[
        "Parsada"
    ],
    "name:eng_x_variant":[
        "Parsad\u0101"
    ],
    "wof:name":"Parsada",
    "wof:placetype":"locality"
},
  "geometry": {"coordinates":[82.123713,22.037248],"type":"Point"}
}