{
  "type": "Feature",
  "properties": {
    "iso:country":"IN",
    "ks:ks_name":"Boro Robi",
    "ks:ks_pop":60,
    "ks:ks_type":"HABITATION",
    "name:eng_x_preferred":[
        "Boro Robi"
    ],
    "wof:name":"Boro Robi",
    "wof:placetype":"locality",
    "wof:population":60
},
  "geometry": {"coordinates":[93.005264,25.152261],"type":"Point"}
}