{
  "type": "Feature",
  "properties": {
    "iso:country":"IN",
    "ks:ks_alt_nam":"KHADAKMALA",
    "ks:ks_name":"Khadakmala",
    "ks:ks_pop":156,
    "ks:ks_type":"HABITATION",
    "name:eng_x_preferred":[
        "Khadakmala"
    ],
    "wof:name":"Khadakmala",
    "wof:placetype":"locality",
    "wof:population":156
},
  "geometry": {"coordinates":[74.175669,17.122349],"type":"Point"}
}