{
  "type": "Feature",
  "properties": {
    "iso:country":"IN",
    "ks:ks_name":"Ghatala",
    "ks:ks_pop":234,
    "ks:ks_type":"VILLAGE",
    "ks:ks_uagg_main":0,
    "name:eng_x_preferred":[
        "Ghatala"
    ],
    "wof:name":"Ghatala",
    "wof:placetype":"neighbourhood",
    "wof:population":234
},
  "geometry": {"coordinates":[77.767493,23.354379],"type":"Point"}
}