{
  "type": "Feature",
  "properties": {
    "iso:country":"IN",
    "ks:ks_name":"Sonakhuli I",
    "ks:ks_pop":1058,
    "ks:ks_type":"VILLAGE",
    "ks:ks_uagg_main":0,
    "name:eng_x_preferred":[
        "Sonakhuli I"
    ],
    "wof:name":"Sonakhuli I",
    "wof:placetype":"neighbourhood",
    "wof:population":1058
},
  "geometry": {"coordinates":[90.694293,26.385054],"type":"Point"}
}