{
  "type": "Feature",
  "properties": {
    "gn:admin1_code":"24.0",
    "gn:admin2_code":"100.0",
    "gn:asciiname":"Kirara",
    "gn:country_code":"IN",
    "gn:dem":204,
    "gn:feature_class":"P",
    "gn:feature_code":"PPL",
    "gn:name":"Kir\u0101ra",
    "gn:population":0,
    "gn:timezone":"Asia/Kolkata",
    "iso:country":"IN",
    "name:ceb_x_preferred":[
        "Kirara"
    ],
    "name:jpn_x_preferred":[
        "\u304d\u3089\u3089"
    ],
    "name:spa_x_preferred":[
        "Kirara"
    ],
    "wof:name":"Kirara",
    "wof:placetype":"neighbourhood"
},
  "geometry": {"coordinates":[75.13404,28.94607],"type":"Point"}
}