{
  "type": "Feature",
  "properties": {
    "iso:country":"IN",
    "ks:ks_name":"Gadwahi",
    "ks:ks_pop":185,
    "ks:ks_type":"VILLAGE",
    "name:eng_x_preferred":[
        "Gadwahi"
    ],
    "wof:name":"Gadwahi",
    "wof:placetype":"locality",
    "wof:population":185
},
  "geometry": {"coordinates":[82.160994,23.929587],"type":"Point"}
}