{
  "type": "Feature",
  "properties": {
    "gn:admin1_code":"35",
    "gn:admin2_code":"455.0",
    "gn:asciiname":"Bhata",
    "gn:country_code":"IN",
    "gn:dem":490,
    "gn:feature_class":"P",
    "gn:feature_code":"PPL",
    "gn:name":"Bh\u0101ta",
    "gn:population":0,
    "gn:timezone":"Asia/Kolkata",
    "iso:country":"IN",
    "name:fas_x_preferred":[
        "\u0628\u0647\u0627\u062a\u0627"
    ],
    "name:pnb_x_preferred":[
        "\u0628\u06be\u0627\u0679\u0627"
    ],
    "name:urd_x_preferred":[
        "\u0628\u06be\u0627\u0679\u0627"
    ],
    "wof:name":"Bhata",
    "wof:placetype":"locality"
},
  "geometry": {"coordinates":[78.33156,22.15569],"type":"Point"}
}