{
  "type": "Feature",
  "properties": {
    "iso:country":"IN",
    "ks:ks_name":"Paswan Tola",
    "ks:ks_pop":1844,
    "ks:ks_type":"HABITATION",
    "name:eng_x_preferred":[
        "Paswan Tola"
    ],
    "wof:name":"Paswan Tola",
    "wof:placetype":"locality",
    "wof:population":1844
},
  "geometry": {"coordinates":[87.365433,26.232329],"type":"Point"}
}