{
  "type": "Feature",
  "properties": {
    "iso:country":"IN",
    "ks:ks_name":"Kottala Thanda",
    "ks:ks_pop":94,
    "ks:ks_type":"HABITATION",
    "name:eng_x_preferred":[
        "Kottala Thanda"
    ],
    "wof:name":"Kottala Thanda",
    "wof:placetype":"locality",
    "wof:population":94
},
  "geometry": {"coordinates":[78.259503,17.924948],"type":"Point"}
}