{
  "type": "Feature",
  "properties": {
    "iso:country":"IN",
    "ks:ks_name":"Barkulhati",
    "ks:ks_pop":551,
    "ks:ks_type":"VILLAGE",
    "name:eng_x_preferred":[
        "Barkulhati"
    ],
    "wof:name":"Barkulhati",
    "wof:placetype":"locality",
    "wof:population":551
},
  "geometry": {"coordinates":[91.48304,26.381665],"type":"Point"}
}