{
  "type": "Feature",
  "properties": {
    "gn:admin1_code":"23.0",
    "gn:admin2_code":"43.0",
    "gn:asciiname":"Kamaluddin Niazi",
    "gn:country_code":"IN",
    "gn:dem":195,
    "gn:feature_class":"P",
    "gn:feature_code":"PPL",
    "gn:name":"Kam\u0101ludd\u012bn Ni\u0101zi",
    "gn:population":0,
    "gn:timezone":"Asia/Kolkata",
    "iso:country":"IN",
    "ks:ks_name":"Kamaldin Niazi",
    "ks:ks_pop":279,
    "ks:ks_type":"VILLAGE",
    "name:eng_x_preferred":[
        "Kamaldin Niazi"
    ],
    "name:eng_x_variant":[
        "Kamaluddin Niazi"
    ],
    "wof:name":"Kamaldin Niazi",
    "wof:placetype":"locality",
    "wof:population":279
},
  "geometry": {"coordinates":[74.500409,30.92992],"type":"Point"}
}