{
  "type": "Feature",
  "properties": {
    "gn:admin1_code":"23.0",
    "gn:admin2_code":"43.0",
    "gn:asciiname":"Kamaluddin Niazi",
    "gn:country_code":"IN",
    "gn:dem":195,
    "gn:feature_class":"P",
    "gn:feature_code":"PPL",
    "gn:name":"Kam\u0101ludd\u012bn Ni\u0101zi",
    "gn:population":0,
    "gn:timezone":"Asia/Kolkata",
    "iso:country":"IN",
    "wof:name":"Kamaluddin Niazi",
    "wof:placetype":"locality"
},
  "geometry": {"coordinates":[74.51034,30.92568],"type":"Point"}
}