{
  "type": "Feature",
  "properties": {
    "gn:admin1_code":"34.0",
    "gn:admin2_code":"236.0",
    "gn:asciiname":"Bhindis",
    "gn:country_code":"IN",
    "gn:dem":128,
    "gn:feature_class":"P",
    "gn:feature_code":"PPL",
    "gn:name":"Bhindis",
    "gn:population":0,
    "gn:timezone":"Asia/Kolkata",
    "iso:country":"IN",
    "wof:name":"Bhindis",
    "wof:placetype":"locality"
},
  "geometry": {"coordinates":[84.7364,24.67584],"type":"Point"}
}