{
  "type": "Feature",
  "properties": {
    "gn:admin1_code":"19.0",
    "gn:admin2_code":"572.0",
    "gn:asciiname":"Guniagrahar",
    "gn:country_code":"IN",
    "gn:dem":893,
    "gn:feature_class":"P",
    "gn:feature_code":"PPL",
    "gn:name":"Guniagrah\u0101r",
    "gn:population":0,
    "gn:timezone":"Asia/Kolkata",
    "iso:country":"IN",
    "wof:name":"Guniagrahar",
    "wof:placetype":"locality"
},
  "geometry": {"coordinates":[77.52343,13.09794],"type":"Point"}
}