{
  "type": "Feature",
  "properties": {
    "iso:country":"IN",
    "ks:ks_name":"Alagjara",
    "ks:ks_pop":132,
    "ks:ks_type":"VILLAGE",
    "ks:ks_uagg_main":0,
    "name:eng_x_preferred":[
        "Alagjara"
    ],
    "wof:name":"Alagjara",
    "wof:placetype":"neighbourhood",
    "wof:population":132
},
  "geometry": {"coordinates":[86.422236,24.926189],"type":"Point"}
}