{
  "type": "Feature",
  "properties": {
    "iso:country":"IN",
    "ks:ks_name":"Kanakkanpalayam",
    "ks:ks_pop":250,
    "ks:ks_type":"HABITATION",
    "name:eng_x_preferred":[
        "Kanakkanpalayam"
    ],
    "wof:name":"Kanakkanpalayam",
    "wof:placetype":"locality",
    "wof:population":250
},
  "geometry": {"coordinates":[79.555723,11.886779],"type":"Point"}
}