{
  "type": "Feature",
  "properties": {
    "iso:country":"IN",
    "name:ben_x_preferred":[
        "\u09ae\u09be\u09af\u09bc\u09be\u09aa\u09c1\u09b0"
    ],
    "name:ces_x_preferred":[
        "Majapur"
    ],
    "name:deu_x_preferred":[
        "Mayapur"
    ],
    "name:eng_x_preferred":[
        "Mayapur"
    ],
    "name:fra_x_preferred":[
        "Mayapur"
    ],
    "name:hin_x_preferred":[
        "\u092e\u093e\u092f\u093e\u092a\u0941\u0930"
    ],
    "name:hun_x_preferred":[
        "M\u00e1j\u00e1pur"
    ],
    "name:pol_x_preferred":[
        "Majapur"
    ],
    "name:rus_x_preferred":[
        "\u041c\u0430\u044f\u043f\u0443\u0440"
    ],
    "name:spa_x_preferred":[
        "M\u0101y\u0101pur"
    ],
    "name:tat_x_preferred":[
        "\u041c\u0430\u044f\u043f\u0443\u0440"
    ],
    "name:ukr_x_preferred":[
        "\u041c\u0430\u044f\u043f\u0443\u0440"
    ],
    "name:urd_x_preferred":[
        "\u0645\u0627\u06cc\u0627 \u067e\u0648\u0631"
    ],
    "qs:gn_adm0_cc":"IN",
    "qs:gn_fcode":"PPL",
    "qs:gn_local":1270351,
    "qs:gn_nam_loc":"Haridwar, Hardwar, Uttarakhand, IN",
    "qs:gn_namadm1":"39",
    "qs:gn_name":"Madanpur",
    "qs:local_max":899,
    "qs:local_sum":2009,
    "qs:localhoods":5,
    "qs:name":"Mayapur",
    "qs:name_adm0":"India",
    "qs:name_adm1":"Uttarakhand",
    "qs:name_adm2":"Haridwar",
    "qs:name_local":"Hardwar",
    "qs:photo_max":39,
    "qs:photo_sum":173,
    "qs:placetype":"Suburb",
    "qs:quad_count":13,
    "qs:woe_adm0":23424848,
    "qs:woe_adm1":20070462,
    "qs:woe_adm2":12586750,
    "qs:woe_lau":0,
    "qs:woe_local":2294971,
    "qs:woe_ver":"7.10.0",
    "wof:lang":[
        "eng"
    ],
    "wof:name":"Mayapur",
    "wof:placetype":"neighbourhood"
},
  "geometry": {"coordinates":[78.152845,29.937213],"type":"Point"}
}