{
  "type": "Feature",
  "properties": {
    "iso:country":"IN",
    "ks:ks_name":"Dhushadh Toli",
    "ks:ks_pop":4812,
    "ks:ks_type":"HABITATION",
    "name:eng_x_preferred":[
        "Dhushadh Toli"
    ],
    "wof:name":"Dhushadh Toli",
    "wof:placetype":"locality",
    "wof:population":4812
},
  "geometry": {"coordinates":[85.060759,24.812845],"type":"Point"}
}