{
  "type": "Feature",
  "properties": {
    "iso:country":"IN",
    "ks:ks_name":"Konhara Hardas",
    "ks:ks_pop":1565,
    "ks:ks_type":"VILLAGE",
    "name:eng_x_preferred":[
        "Konhara Hardas"
    ],
    "wof:name":"Konhara Hardas",
    "wof:placetype":"locality",
    "wof:population":1565
},
  "geometry": {"coordinates":[85.497668,26.145601],"type":"Point"}
}