{
  "type": "Feature",
  "properties": {
    "gn:admin1_code":"36.0",
    "gn:admin2_code":"150.0",
    "gn:asciiname":"Bhairpuri",
    "gn:country_code":"IN",
    "gn:dem":188,
    "gn:feature_class":"P",
    "gn:feature_code":"PPL",
    "gn:name":"Bhairpur\u012b",
    "gn:population":0,
    "gn:timezone":"Asia/Kolkata",
    "iso:country":"IN",
    "ks:ks_alt_nam":"Bhairpur\u012b",
    "ks:ks_name":"Bhairpuri",
    "ks:ks_type":"VILLAGE",
    "name:eng_x_preferred":[
        "Bhairpuri"
    ],
    "name:eng_x_variant":[
        "Bhairpur\u012b"
    ],
    "wof:name":"Bhairpuri",
    "wof:placetype":"locality"
},
  "geometry": {"coordinates":[79.533731,28.702469],"type":"Point"}
}