{
  "type": "Feature",
  "properties": {
    "iso:country":"IN",
    "ks:ks_name":"Damor Faliya",
    "ks:ks_pop":1084,
    "ks:ks_type":"HABITATION",
    "name:eng_x_preferred":[
        "Damor Faliya"
    ],
    "wof:name":"Damor Faliya",
    "wof:placetype":"locality",
    "wof:population":1084
},
  "geometry": {"coordinates":[73.889278,23.3255],"type":"Point"}
}