{
  "type": "Feature",
  "properties": {
    "iso:country":"IN",
    "ks:ks_name":"Sindhisingi",
    "ks:ks_pop":77,
    "ks:ks_type":"HABITATION",
    "name:eng_x_preferred":[
        "Sindhisingi"
    ],
    "wof:name":"Sindhisingi",
    "wof:placetype":"locality",
    "wof:population":77
},
  "geometry": {"coordinates":[84.162144,18.999241],"type":"Point"}
}