{
  "type": "Feature",
  "properties": {
    "iso:country":"IN",
    "ks:ks_name":"Ramakani",
    "ks:ks_pop":365,
    "ks:ks_type":"VILLAGE",
    "name:eng_x_preferred":[
        "Ramakani"
    ],
    "wof:name":"Ramakani",
    "wof:placetype":"locality",
    "wof:population":365
},
  "geometry": {"coordinates":[86.584767,20.442921],"type":"Point"}
}