{
  "type": "Feature",
  "properties": {
    "gn:admin1_code":"23.0",
    "gn:asciiname":"Chhannan Mallahan",
    "gn:country_code":"IN",
    "gn:dem":235,
    "gn:feature_class":"P",
    "gn:feature_code":"PPL",
    "gn:name":"Chhann\u0101n Mall\u0101h\u0101n",
    "gn:population":0,
    "gn:timezone":"Asia/Kolkata",
    "iso:country":"IN",
    "wof:name":"Chhannan Mallahan",
    "wof:placetype":"locality"
},
  "geometry": {"coordinates":[74.82850000000001,31.97692],"type":"Point"}
}