{
  "type": "Feature",
  "properties": {
    "iso:country":"IN",
    "ks:ks_alt_nam":"5 BWM",
    "ks:ks_name":"5 Bwm",
    "ks:ks_pop":2,
    "ks:ks_type":"HABITATION",
    "name:eng_x_preferred":[
        "5 Bwm"
    ],
    "wof:name":"5 Bwm",
    "wof:placetype":"locality",
    "wof:population":2
},
  "geometry": {"coordinates":[73.19986,29.406691],"type":"Point"}
}