{
  "type": "Feature",
  "properties": {
    "gn:admin1_code":"25.0",
    "gn:admin2_code":"631.0",
    "gn:asciiname":"Kallupalli",
    "gn:country_code":"IN",
    "gn:dem":941,
    "gn:feature_class":"P",
    "gn:feature_code":"PPL",
    "gn:name":"Kallupalli",
    "gn:population":0,
    "gn:timezone":"Asia/Kolkata",
    "iso:country":"IN",
    "wof:name":"Kallupalli",
    "wof:placetype":"locality"
},
  "geometry": {"coordinates":[77.72495000000001,12.64593],"type":"Point"}
}