{
  "type": "Feature",
  "properties": {
    "iso:country":"IN",
    "ks:ks_name":"Chapergundi",
    "ks:ks_pop":24,
    "ks:ks_type":"HABITATION",
    "name:eng_x_preferred":[
        "Chapergundi"
    ],
    "wof:name":"Chapergundi",
    "wof:placetype":"locality",
    "wof:population":24
},
  "geometry": {"coordinates":[74.71629299999999,14.99825],"type":"Point"}
}