{
  "type": "Feature",
  "properties": {
    "gn:admin1_code":"35.0",
    "gn:admin2_code":"452.0",
    "gn:asciiname":"Bariadhana",
    "gn:country_code":"IN",
    "gn:dem":767,
    "gn:feature_class":"P",
    "gn:feature_code":"PPL",
    "gn:name":"Bari\u0101dh\u0101na",
    "gn:population":0,
    "gn:timezone":"Asia/Kolkata",
    "iso:country":"IN",
    "ks:ks_alt_nam":"Bari\u0101dh\u0101na",
    "ks:ks_name":"Bariadhana",
    "ks:ks_type":"VILLAGE",
    "name:eng_x_preferred":[
        "Bariadhana"
    ],
    "name:eng_x_variant":[
        "Bari\u0101dh\u0101na"
    ],
    "wof:name":"Bariadhana",
    "wof:placetype":"locality"
},
  "geometry": {"coordinates":[78.86179799999999,22.708493],"type":"Point"}
}