{
  "type": "Feature",
  "properties": {
    "iso:country":"IN",
    "ks:ks_name":"Manibailu",
    "ks:ks_pop":21,
    "ks:ks_type":"HABITATION",
    "name:eng_x_preferred":[
        "Manibailu"
    ],
    "wof:name":"Manibailu",
    "wof:placetype":"locality",
    "wof:population":21
},
  "geometry": {"coordinates":[75.220753,13.391662],"type":"Point"}
}