{
  "type": "Feature",
  "properties": {
    "iso:country":"IN",
    "ks:ks_name":"Yarakanabailu",
    "ks:ks_pop":158,
    "ks:ks_type":"HABITATION",
    "name:eng_x_preferred":[
        "Yarakanabailu"
    ],
    "wof:name":"Yarakanabailu",
    "wof:placetype":"locality",
    "wof:population":158
},
  "geometry": {"coordinates":[74.80929500000001,13.72159],"type":"Point"}
}