{
  "type": "Feature",
  "properties": {
    "iso:country":"IN",
    "ks:ks_name":"Sikrahata",
    "ks:ks_pop":2695,
    "ks:ks_type":"VILLAGE",
    "name:eng_x_preferred":[
        "Sikrahata"
    ],
    "wof:name":"Sikrahata",
    "wof:placetype":"locality",
    "wof:population":2695
},
  "geometry": {"coordinates":[86.73214900000001,26.378672],"type":"Point"}
}