{
  "type": "Feature",
  "properties": {
    "gn:admin1_code":"35",
    "gn:admin2_code":"464.0",
    "gn:asciiname":"Wathan",
    "gn:country_code":"IN",
    "gn:dem":275,
    "gn:feature_class":"P",
    "gn:feature_code":"PPL",
    "gn:name":"Wath\u0101n",
    "gn:population":0,
    "gn:timezone":"Asia/Kolkata",
    "iso:country":"IN",
    "wof:name":"Wathan",
    "wof:placetype":"locality"
},
  "geometry": {"coordinates":[74.3736,23.0694],"type":"Point"}
}