{
  "type": "Feature",
  "properties": {
    "iso:country":"IN",
    "ks:ks_name":"Bungalow Nagar",
    "ks:ks_pop":105,
    "ks:ks_type":"HABITATION",
    "ks:ks_uagg_main":0,
    "name:eng_x_preferred":[
        "Bungalow Nagar"
    ],
    "wof:name":"Bungalow Nagar",
    "wof:placetype":"neighbourhood",
    "wof:population":105
},
  "geometry": {"coordinates":[77.925406,11.05341],"type":"Point"}
}