{
  "type": "Feature",
  "properties": {
    "iso:country":"IN",
    "ks:ks_name":"Shukla Nagar",
    "ks:ks_pop":50,
    "ks:ks_type":"HABITATION",
    "name:eng_x_preferred":[
        "Shukla Nagar"
    ],
    "wof:name":"Shukla Nagar",
    "wof:placetype":"locality",
    "wof:population":50
},
  "geometry": {"coordinates":[80.63664,26.065358],"type":"Point"}
}