{
  "type": "Feature",
  "properties": {
    "gn:admin1_code":"13.0",
    "gn:admin2_code":"594",
    "gn:asciiname":"Irimbranallur",
    "gn:country_code":"IN",
    "gn:dem":10,
    "gn:feature_class":"P",
    "gn:feature_code":"PPL",
    "gn:name":"Irimbranall\u016br",
    "gn:population":0,
    "gn:timezone":"Asia/Kolkata",
    "iso:country":"IN",
    "ks:ks_alt_nam":"Irimbranall\u016br",
    "ks:ks_name":"Irimbranallur",
    "ks:ks_pop":2925,
    "ks:ks_type":"VILLAGE",
    "ks:ks_uagg_main":0,
    "name:eng_x_preferred":[
        "Irimbranallur"
    ],
    "name:eng_x_variant":[
        "Irimbranall\u016br"
    ],
    "name:msa_x_preferred":[
        "Irimbranallur"
    ],
    "name:und_x_variant":[
        "Irimbranall\u016br"
    ],
    "wof:name":"Irimbranallur",
    "wof:placetype":"neighbourhood",
    "wof:population":2925
},
  "geometry": {"coordinates":[76.100652,10.508207],"type":"Point"}
}