{
  "type": "Feature",
  "properties": {
    "iso:country":"IN",
    "ks:ks_name":"Gobargarha",
    "ks:ks_type":"VILLAGE",
    "ks:ks_uagg_main":0,
    "name:eng_x_preferred":[
        "Gobargarha"
    ],
    "wof:name":"Gobargarha",
    "wof:placetype":"locality"
},
  "geometry": {"coordinates":[86.619919,26.122521],"type":"Point"}
}