{
  "type": "Feature",
  "properties": {
    "iso:country":"IN",
    "ks:ks_name":"Sanambajharan",
    "ks:ks_pop":87,
    "ks:ks_type":"VILLAGE",
    "name:eng_x_preferred":[
        "Sanambajharan"
    ],
    "wof:name":"Sanambajharan",
    "wof:placetype":"locality",
    "wof:population":87
},
  "geometry": {"coordinates":[84.98006599999999,22.129022],"type":"Point"}
}