{
  "type": "Feature",
  "properties": {
    "gn:admin1_code":"12.0",
    "gn:admin2_code":"9.0",
    "gn:asciiname":"Budarnar",
    "gn:country_code":"IN",
    "gn:dem":1903,
    "gn:feature_class":"P",
    "gn:feature_code":"PPL",
    "gn:name":"Budarn\u0101r",
    "gn:population":0,
    "gn:timezone":"Asia/Kolkata",
    "iso:country":"IN",
    "name:eng_x_preferred":[
        "Budarn\u0101r"
    ],
    "wof:name":"Budarnar",
    "wof:placetype":"locality"
},
  "geometry": {"coordinates":[74.71511,34.37842],"type":"Point"}
}