{
  "type": "Feature",
  "properties": {
    "gn:admin1_code":"35.0",
    "gn:admin2_code":"445.0",
    "gn:asciiname":"Bordi Khurd",
    "gn:country_code":"IN",
    "gn:dem":519,
    "gn:feature_class":"P",
    "gn:feature_code":"PPL",
    "gn:name":"Bordi Khurd",
    "gn:population":0,
    "gn:timezone":"Asia/Kolkata",
    "iso:country":"IN",
    "ks:ks_name":"Bordikhurd",
    "ks:ks_pop":249,
    "ks:ks_type":"HABITATION",
    "name:eng_x_preferred":[
        "Bordikhurd"
    ],
    "name:eng_x_variant":[
        "Bordi Khurd"
    ],
    "wof:name":"Bordikhurd",
    "wof:placetype":"locality",
    "wof:population":249
},
  "geometry": {"coordinates":[76.982865,22.897174],"type":"Point"}
}