{
  "type": "Feature",
  "properties": {
    "gn:admin1_code":"35.0",
    "gn:admin2_code":"445.0",
    "gn:asciiname":"Bordi Khurd",
    "gn:country_code":"IN",
    "gn:dem":519,
    "gn:feature_class":"P",
    "gn:feature_code":"PPL",
    "gn:name":"Bordi Khurd",
    "gn:population":0,
    "gn:timezone":"Asia/Kolkata",
    "iso:country":"IN",
    "wof:name":"Bordi Khurd",
    "wof:placetype":"locality"
},
  "geometry": {"coordinates":[76.98334,22.89773],"type":"Point"}
}