{
  "type": "Feature",
  "properties": {
    "iso:country":"IN",
    "ks:ks_name":"Chanchadakhata",
    "ks:ks_pop":222,
    "ks:ks_type":"VILLAGE",
    "name:eng_x_preferred":[
        "Chanchadakhata"
    ],
    "wof:name":"Chanchadakhata",
    "wof:placetype":"locality",
    "wof:population":222
},
  "geometry": {"coordinates":[84.321101,19.071994],"type":"Point"}
}