{
  "type": "Feature",
  "properties": {
    "iso:country":"IN",
    "ks:ks_name":"Vippamanuguda",
    "ks:ks_pop":70,
    "ks:ks_type":"HABITATION",
    "name:eng_x_preferred":[
        "Vippamanuguda"
    ],
    "wof:name":"Vippamanuguda",
    "wof:placetype":"locality",
    "wof:population":70
},
  "geometry": {"coordinates":[83.691349,18.91579],"type":"Point"}
}