{
  "type": "Feature",
  "properties": {
    "iso:country":"IN",
    "ks:ks_name":"Nagalapur Y",
    "ks:ks_pop":79,
    "ks:ks_type":"HABITATION",
    "name:eng_x_preferred":[
        "Nagalapur Y"
    ],
    "wof:name":"Nagalapur Y",
    "wof:placetype":"locality",
    "wof:population":79
},
  "geometry": {"coordinates":[77.343614,16.092283],"type":"Point"}
}