{
  "type": "Feature",
  "properties": {
    "gn:admin1_code":"34.0",
    "gn:admin2_code":"220.0",
    "gn:asciiname":"Chak Rasul",
    "gn:country_code":"IN",
    "gn:dem":58,
    "gn:feature_class":"P",
    "gn:feature_code":"PPL",
    "gn:name":"Chak Ras\u016bl",
    "gn:population":0,
    "gn:timezone":"Asia/Kolkata",
    "iso:country":"IN",
    "ks:ks_alt_nam":"Chak Ras\u016bl",
    "ks:ks_name":"Chak Rasul",
    "ks:ks_type":"VILLAGE",
    "ks:ks_uagg_main":0,
    "name:eng_x_preferred":[
        "Chak Rasul"
    ],
    "name:eng_x_variant":[
        "Chak Ras\u016bl"
    ],
    "wof:name":"Chak Rasul",
    "wof:placetype":"neighbourhood"
},
  "geometry": {"coordinates":[85.105419,25.932759],"type":"Point"}
}