{
  "type": "Feature",
  "properties": {
    "iso:country":"IN",
    "ks:ks_name":"Hukhai",
    "ks:ks_pop":288,
    "ks:ks_type":"HABITATION",
    "ks:ks_uagg_main":0,
    "name:eng_x_preferred":[
        "Hukhai"
    ],
    "wof:name":"Hukhai",
    "wof:placetype":"neighbourhood",
    "wof:population":288
},
  "geometry": {"coordinates":[93.90580300000001,26.037724],"type":"Point"}
}