{
  "type": "Feature",
  "properties": {
    "gn:admin1_code":"36.0",
    "gn:admin2_code":"189.0",
    "gn:asciiname":"Dumarbhar",
    "gn:country_code":"IN",
    "gn:dem":82,
    "gn:feature_class":"P",
    "gn:feature_code":"PPL",
    "gn:name":"Dumarbh\u0101r",
    "gn:population":0,
    "gn:timezone":"Asia/Kolkata",
    "iso:country":"IN",
    "ks:ks_alt_nam":"Dumarbh\u0101r",
    "ks:ks_name":"Dumarbhar",
    "ks:ks_type":"VILLAGE",
    "name:eng_x_preferred":[
        "Dumarbhar"
    ],
    "name:eng_x_variant":[
        "Dumarbh\u0101r"
    ],
    "wof:name":"Dumarbhar",
    "wof:placetype":"locality"
},
  "geometry": {"coordinates":[84.131174,26.693441],"type":"Point"}
}