{
  "type": "Feature",
  "properties": {
    "iso:country":"IN",
    "ks:ks_name":"Perumalpatti Colony",
    "ks:ks_pop":796,
    "ks:ks_type":"HABITATION",
    "ks:ks_uagg_main":0,
    "name:eng_x_preferred":[
        "Perumalpatti Colony"
    ],
    "wof:name":"Perumalpatti Colony",
    "wof:placetype":"neighbourhood",
    "wof:population":796
},
  "geometry": {"coordinates":[78.114859,10.874587],"type":"Point"}
}