{
  "type": "Feature",
  "properties": {
    "iso:country":"IN",
    "ks:ks_name":"Pallatahru",
    "ks:ks_pop":260,
    "ks:ks_type":"HABITATION",
    "name:eng_x_preferred":[
        "Pallatahru"
    ],
    "wof:name":"Pallatahru",
    "wof:placetype":"locality",
    "wof:population":260
},
  "geometry": {"coordinates":[75.293454,12.679498],"type":"Point"}
}