{
  "type": "Feature",
  "properties": {
    "gn:admin1_code":"38.0",
    "gn:admin2_code":"358.0",
    "gn:asciiname":"Chak Rudarpur",
    "gn:country_code":"IN",
    "gn:dem":260,
    "gn:feature_class":"P",
    "gn:feature_code":"PPL",
    "gn:name":"Chak Rudarpur",
    "gn:population":0,
    "gn:timezone":"Asia/Kolkata",
    "iso:country":"IN",
    "ks:ks_alt_nam":"CHAKRKUDARPUR",
    "ks:ks_name":"Chakrkudarpur",
    "ks:ks_pop":457,
    "ks:ks_type":"HABITATION",
    "name:eng_x_preferred":[
        "Chakrkudarpur"
    ],
    "name:eng_x_variant":[
        "Chak Rudarpur"
    ],
    "wof:name":"Chakrkudarpur",
    "wof:placetype":"locality",
    "wof:population":457
},
  "geometry": {"coordinates":[84.13901199999999,24.202393],"type":"Point"}
}