{
  "type": "Feature",
  "properties": {
    "iso:country":"IN",
    "ks:ks_name":"Sakrauda Reserved Forest",
    "ks:ks_type":"VILLAGE",
    "name:eng_x_preferred":[
        "Sakrauda Reserved Forest"
    ],
    "wof:name":"Sakrauda Reserved Forest",
    "wof:placetype":"locality"
},
  "geometry": {"coordinates":[77.861054,30.042779],"type":"Point"}
}