{
  "type": "Feature",
  "properties": {
    "iso:country":"IN",
    "ks:ks_name":"Brahman Tola Harizan Basti",
    "ks:ks_pop":1034,
    "ks:ks_type":"HABITATION",
    "ks:ks_uagg_main":0,
    "name:eng_x_preferred":[
        "Brahman Tola Harizan Basti"
    ],
    "wof:name":"Brahman Tola Harizan Basti",
    "wof:placetype":"neighbourhood",
    "wof:population":1034
},
  "geometry": {"coordinates":[83.59847000000001,26.700275],"type":"Point"}
}