{
  "type": "Feature",
  "properties": {
    "iso:country":"IN",
    "ks:ks_name":"Saurbhat Gaon",
    "ks:ks_pop":593,
    "ks:ks_type":"HABITATION",
    "name:eng_x_preferred":[
        "Saurbhat Gaon"
    ],
    "wof:name":"Saurbhat Gaon",
    "wof:placetype":"locality",
    "wof:population":593
},
  "geometry": {"coordinates":[79.01717600000001,30.373307],"type":"Point"}
}