{
  "type": "Feature",
  "properties": {
    "gn:admin1_code":"09",
    "gn:admin2_code":"481.0",
    "gn:asciiname":"Parodi",
    "gn:country_code":"IN",
    "gn:dem":116,
    "gn:feature_class":"P",
    "gn:feature_code":"PPL",
    "gn:name":"Parodi",
    "gn:population":0,
    "gn:timezone":"Asia/Kolkata",
    "iso:country":"IN",
    "name:bul_x_preferred":[
        "\u041f\u0430\u0440\u043e\u0434\u0438"
    ],
    "name:deu_x_preferred":[
        "Parodi"
    ],
    "name:fra_x_preferred":[
        "Parodi"
    ],
    "name:ita_x_preferred":[
        "Parodi"
    ],
    "name:rus_x_preferred":[
        "\u041f\u0430\u0440\u043e\u0434\u0438"
    ],
    "name:spa_x_preferred":[
        "Parodi"
    ],
    "wof:name":"Parodi",
    "wof:placetype":"locality"
},
  "geometry": {"coordinates":[71.62982,21.57007],"type":"Point"}
}