{
  "type": "Feature",
  "properties": {
    "iso:country":"IN",
    "ks:ks_name":"Patapur",
    "ks:ks_pop":99,
    "ks:ks_type":"VILLAGE",
    "name:eng_x_preferred":[
        "Patapur"
    ],
    "wof:name":"Patapur",
    "wof:placetype":"locality",
    "wof:population":99
},
  "geometry": {"coordinates":[85.35293,20.264053],"type":"Point"}
}