{
  "type": "Feature",
  "properties": {
    "gn:admin1_code":"39.0",
    "gn:admin2_code":"63.0",
    "gn:asciiname":"Siroli",
    "gn:country_code":"IN",
    "gn:dem":1496,
    "gn:feature_class":"P",
    "gn:feature_code":"PPL",
    "gn:name":"S\u012broli",
    "gn:population":0,
    "gn:timezone":"Asia/Kolkata",
    "iso:country":"IN",
    "ks:ks_alt_nam":"S\u012broli",
    "ks:ks_name":"Siroli",
    "ks:ks_pop":330,
    "ks:ks_type":"VILLAGE",
    "name:eng_x_preferred":[
        "Siroli"
    ],
    "name:eng_x_variant":[
        "S\u012broli"
    ],
    "wof:name":"Siroli",
    "wof:placetype":"locality",
    "wof:population":330
},
  "geometry": {"coordinates":[79.837228,29.83095],"type":"Point"}
}