{
  "type": "Feature",
  "properties": {
    "gn:admin1_code":"39.0",
    "gn:admin2_code":"63.0",
    "gn:asciiname":"Siroli",
    "gn:country_code":"IN",
    "gn:dem":1496,
    "gn:feature_class":"P",
    "gn:feature_code":"PPL",
    "gn:name":"S\u012broli",
    "gn:population":0,
    "gn:timezone":"Asia/Kolkata",
    "iso:country":"IN",
    "wof:name":"Siroli",
    "wof:placetype":"locality"
},
  "geometry": {"coordinates":[79.83948000000002,29.83176],"type":"Point"}
}