{
  "type": "Feature",
  "properties": {
    "iso:country":"IN",
    "ks:ks_name":"Sikarpai",
    "ks:ks_pop":38,
    "ks:ks_type":"HABITATION",
    "name:eng_x_preferred":[
        "Sikarpai"
    ],
    "wof:name":"Sikarpai",
    "wof:placetype":"locality",
    "wof:population":38
},
  "geometry": {"coordinates":[83.848761,19.215056],"type":"Point"}
}