{
  "type": "Feature",
  "properties": {
    "gn:admin1_code":"19",
    "gn:admin2_code":"563.0",
    "gn:asciiname":"Targod",
    "gn:country_code":"IN",
    "gn:dem":518,
    "gn:feature_class":"P",
    "gn:feature_code":"PPL",
    "gn:name":"T\u0101rgod",
    "gn:population":0,
    "gn:timezone":"Asia/Kolkata",
    "iso:country":"IN",
    "ks:ks_name":"Taragod",
    "ks:ks_pop":306,
    "ks:ks_type":"VILLAGE",
    "name:eng_x_preferred":[
        "Taragod"
    ],
    "name:eng_x_variant":[
        "Targod"
    ],
    "wof:name":"Taragod",
    "wof:placetype":"locality",
    "wof:population":306
},
  "geometry": {"coordinates":[74.79068599999999,14.31824],"type":"Point"}
}