{
  "type": "Feature",
  "properties": {
    "gn:admin1_code":"19",
    "gn:admin2_code":"563.0",
    "gn:asciiname":"Targod",
    "gn:country_code":"IN",
    "gn:dem":518,
    "gn:feature_class":"P",
    "gn:feature_code":"PPL",
    "gn:name":"T\u0101rgod",
    "gn:population":0,
    "gn:timezone":"Asia/Kolkata",
    "iso:country":"IN",
    "wof:name":"Targod",
    "wof:placetype":"locality"
},
  "geometry": {"coordinates":[74.78804000000002,14.3249],"type":"Point"}
}