{
  "type": "Feature",
  "properties": {
    "iso:country":"IN",
    "ks:ks_alt_nam":"Salsude wasti",
    "ks:ks_name":"Salsude Wasti",
    "ks:ks_pop":364,
    "ks:ks_type":"HABITATION",
    "name:eng_x_preferred":[
        "Salsude Wasti"
    ],
    "wof:name":"Salsude Wasti",
    "wof:placetype":"locality",
    "wof:population":364
},
  "geometry": {"coordinates":[75.43617999999999,18.085716],"type":"Point"}
}