{
  "type": "Feature",
  "properties": {
    "iso:country":"IN",
    "ks:ks_alt_nam":"KEBAL PARA",
    "ks:ks_name":"Kebal Para",
    "ks:ks_pop":500,
    "ks:ks_type":"HABITATION",
    "name:eng_x_preferred":[
        "Kebal Para"
    ],
    "wof:name":"Kebal Para",
    "wof:placetype":"locality",
    "wof:population":500
},
  "geometry": {"coordinates":[88.58150000000001,26.602194],"type":"Point"}
}