{
  "type": "Feature",
  "properties": {
    "iso:country":"IN",
    "ks:ks_name":"Fulpur",
    "ks:ks_pop":1024,
    "ks:ks_type":"HABITATION",
    "name:eng_x_preferred":[
        "Fulpur"
    ],
    "wof:name":"Fulpur",
    "wof:placetype":"locality",
    "wof:population":1024
},
  "geometry": {"coordinates":[82.50458,23.282662],"type":"Point"}
}