{
  "type": "Feature",
  "properties": {
    "iso:country":"IN",
    "ks:ks_name":"Chinadevakiwada",
    "ks:ks_pop":255,
    "ks:ks_type":"HABITATION",
    "name:eng_x_preferred":[
        "Chinadevakiwada"
    ],
    "wof:name":"Chinadevakiwada",
    "wof:placetype":"locality",
    "wof:population":255
},
  "geometry": {"coordinates":[83.574183,18.590659],"type":"Point"}
}