{
  "type": "Feature",
  "properties": {
    "iso:country":"IN",
    "ks:ks_alt_nam":"Shekh bigha",
    "ks:ks_name":"Shekh Bigha",
    "ks:ks_pop":700,
    "ks:ks_type":"HABITATION",
    "name:eng_x_preferred":[
        "Shekh Bigha"
    ],
    "wof:name":"Shekh Bigha",
    "wof:placetype":"locality",
    "wof:population":700
},
  "geometry": {"coordinates":[84.450598,24.887148],"type":"Point"}
}