{
  "type": "Feature",
  "properties": {
    "gn:admin1_code":"16",
    "gn:admin2_code":"502.0",
    "gn:asciiname":"Sendurjan",
    "gn:country_code":"IN",
    "gn:dem":515,
    "gn:feature_class":"P",
    "gn:feature_code":"PPL",
    "gn:name":"Sendurjan",
    "gn:population":0,
    "gn:timezone":"Asia/Kolkata",
    "iso:country":"IN",
    "name:und_x_variant":[
        "Sendurjana",
        "Sendurjan"
    ],
    "wof:name":"Sendurjan",
    "wof:placetype":"locality"
},
  "geometry": {"coordinates":[77.4507,20.1491],"type":"Point"}
}