{
  "type": "Feature",
  "properties": {
    "iso:country":"IN",
    "ks:ks_name":"Karaundaha",
    "ks:ks_pop":83,
    "ks:ks_type":"VILLAGE",
    "name:eng_x_preferred":[
        "Karaundaha"
    ],
    "wof:name":"Karaundaha",
    "wof:placetype":"locality",
    "wof:population":83
},
  "geometry": {"coordinates":[81.658777,24.665218],"type":"Point"}
}