{
  "type": "Feature",
  "properties": {
    "iso:country":"IN",
    "ks:ks_name":"Timajhola",
    "ks:ks_pop":15,
    "ks:ks_type":"HABITATION",
    "name:eng_x_preferred":[
        "Timajhola"
    ],
    "wof:name":"Timajhola",
    "wof:placetype":"locality",
    "wof:population":15
},
  "geometry": {"coordinates":[84.53099400000001,20.372251],"type":"Point"}
}