{
  "type": "Feature",
  "properties": {
    "iso:country":"IN",
    "ks:ks_name":"Boda",
    "ks:ks_pop":121,
    "ks:ks_type":"HABITATION",
    "name:eng_x_preferred":[
        "Boda"
    ],
    "wof:name":"Boda",
    "wof:placetype":"locality",
    "wof:population":121
},
  "geometry": {"coordinates":[80.308724,24.289071],"type":"Point"}
}