{
  "type": "Feature",
  "properties": {
    "iso:country":"IN",
    "ks:ks_name":"Kuri",
    "ks:ks_pop":272,
    "ks:ks_type":"VILLAGE",
    "name:eng_x_preferred":[
        "Kuri"
    ],
    "wof:name":"Kuri",
    "wof:placetype":"locality",
    "wof:population":272
},
  "geometry": {"coordinates":[79.864722,29.519692],"type":"Point"}
}