{
  "type": "Feature",
  "properties": {
    "gn:admin1_code":"24.0",
    "gn:admin2_code":"103.0",
    "gn:asciiname":"Jakhal",
    "gn:country_code":"IN",
    "gn:dem":395,
    "gn:feature_class":"P",
    "gn:feature_code":"PPL",
    "gn:name":"Jakhal",
    "gn:population":0,
    "gn:timezone":"Asia/Kolkata",
    "iso:country":"IN",
    "name:urd_x_preferred":[
        "\u062c\u062e\u0644"
    ],
    "wof:name":"Jakhal",
    "wof:placetype":"locality"
},
  "geometry": {"coordinates":[75.44333,27.91259],"type":"Point"}
}