{
  "type": "Feature",
  "properties": {
    "iso:country":"IN",
    "ks:ks_name":"Chapnamari",
    "ks:ks_pop":935,
    "ks:ks_type":"HABITATION",
    "name:eng_x_preferred":[
        "Chapnamari"
    ],
    "wof:name":"Chapnamari",
    "wof:placetype":"locality",
    "wof:population":935
},
  "geometry": {"coordinates":[88.48033,22.462276],"type":"Point"}
}