{
  "type": "Feature",
  "properties": {
    "gn:admin1_code":"2.0",
    "gn:admin2_code":"553.0",
    "gn:asciiname":"Akutotapalle",
    "gn:country_code":"IN",
    "gn:dem":439,
    "gn:feature_class":"P",
    "gn:feature_code":"PPL",
    "gn:name":"\u0100kutotapalle",
    "gn:population":0,
    "gn:timezone":"Asia/Kolkata",
    "iso:country":"IN",
    "wof:name":"Akutotapalle",
    "wof:placetype":"locality"
},
  "geometry": {"coordinates":[78.1033,14.36472],"type":"Point"}
}