{
  "type": "Feature",
  "properties": {
    "iso:country":"IN",
    "ks:ks_name":"Latibari",
    "ks:ks_pop":63,
    "ks:ks_type":"HABITATION",
    "name:eng_x_preferred":[
        "Latibari"
    ],
    "wof:name":"Latibari",
    "wof:placetype":"locality",
    "wof:population":63
},
  "geometry": {"coordinates":[82.25104,18.739408],"type":"Point"}
}