{
  "type": "Feature",
  "properties": {
    "gn:admin1_code":"34",
    "gn:admin2_code":"218.0",
    "gn:asciiname":"Phalpura",
    "gn:country_code":"IN",
    "gn:dem":67,
    "gn:feature_class":"P",
    "gn:feature_code":"PPL",
    "gn:name":"Phalpura",
    "gn:population":0,
    "gn:timezone":"Asia/Kolkata",
    "iso:country":"IN",
    "wof:name":"Phalpura",
    "wof:placetype":"locality"
},
  "geometry": {"coordinates":[84.45236,26.17075],"type":"Point"}
}