{
  "type": "Feature",
  "properties": {
    "iso:country":"IN",
    "ks:ks_name":"Laungapani",
    "ks:ks_pop":464,
    "ks:ks_type":"HABITATION",
    "name:eng_x_preferred":[
        "Laungapani"
    ],
    "wof:name":"Laungapani",
    "wof:placetype":"locality",
    "wof:population":464
},
  "geometry": {"coordinates":[84.35306199999999,22.769933],"type":"Point"}
}