{
  "type": "Feature",
  "properties": {
    "iso:country":"IN",
    "ks:ks_name":"Bela",
    "ks:ks_pop":1576,
    "ks:ks_type":"VILLAGE",
    "name:eng_x_preferred":[
        "Bela"
    ],
    "wof:name":"Bela",
    "wof:placetype":"locality",
    "wof:population":1576
},
  "geometry": {"coordinates":[86.541884,24.845138],"type":"Point"}
}