{
  "type": "Feature",
  "properties": {
    "iso:country":"IN",
    "ks:ks_name":"Poovathingal",
    "ks:ks_pop":1234,
    "ks:ks_type":"HABITATION",
    "ks:ks_uagg_main":0,
    "name:eng_x_preferred":[
        "Poovathingal"
    ],
    "wof:name":"Poovathingal",
    "wof:placetype":"neighbourhood",
    "wof:population":1234
},
  "geometry": {"coordinates":[75.875523,11.066003],"type":"Point"}
}