{
  "type": "Feature",
  "properties": {
    "iso:country":"IN",
    "ks:ks_name":"Ayyampalayam",
    "ks:ks_pop":581,
    "ks:ks_type":"HABITATION",
    "name:eng_x_preferred":[
        "Ayyampalayam"
    ],
    "wof:name":"Ayyampalayam",
    "wof:placetype":"locality",
    "wof:population":581
},
  "geometry": {"coordinates":[78.538214,11.103825],"type":"Point"}
}