{
  "type": "Feature",
  "properties": {
    "gn:admin1_code":"39.0",
    "gn:admin2_code":"60.0",
    "gn:asciiname":"Maleta",
    "gn:country_code":"IN",
    "gn:dem":1330,
    "gn:feature_class":"P",
    "gn:feature_code":"PPL",
    "gn:name":"Maleta",
    "gn:population":0,
    "gn:timezone":"Asia/Kolkata",
    "iso:country":"IN",
    "ks:ks_name":"Maleta",
    "ks:ks_type":"VILLAGE",
    "name:eng_x_preferred":[
        "Maleta"
    ],
    "wof:name":"Maleta",
    "wof:placetype":"locality"
},
  "geometry": {"coordinates":[77.79566,30.672369],"type":"Point"}
}