{
  "type": "Feature",
  "properties": {
    "iso:country":"IN",
    "ks:ks_name":"Paul O Haldar Para",
    "ks:ks_pop":1639,
    "ks:ks_type":"HABITATION",
    "name:eng_x_preferred":[
        "Paul O Haldar Para"
    ],
    "wof:name":"Paul O Haldar Para",
    "wof:placetype":"locality",
    "wof:population":1639
},
  "geometry": {"coordinates":[88.33640699999999,22.109293],"type":"Point"}
}