{
  "type": "Feature",
  "properties": {
    "iso:country":"IN",
    "ks:ks_name":"Dakapanga",
    "ks:ks_pop":170,
    "ks:ks_type":"VILLAGE",
    "name:eng_x_preferred":[
        "Dakapanga"
    ],
    "wof:name":"Dakapanga",
    "wof:placetype":"locality",
    "wof:population":170
},
  "geometry": {"coordinates":[84.408151,19.912325],"type":"Point"}
}