{
  "type": "Feature",
  "properties": {
    "iso:country":"IN",
    "ks:ks_name":"Kalloopura",
    "ks:ks_pop":690,
    "ks:ks_type":"VILLAGE",
    "ks:ks_uagg_main":0,
    "name:eng_x_preferred":[
        "Kalloopura"
    ],
    "wof:name":"Kalloopura",
    "wof:placetype":"neighbourhood",
    "wof:population":690
},
  "geometry": {"coordinates":[77.612714,26.781294],"type":"Point"}
}