{
  "type": "Feature",
  "properties": {
    "gn:admin1_code":"36",
    "gn:admin2_code":"181.0",
    "gn:asciiname":"Ghauspur",
    "gn:country_code":"IN",
    "gn:dem":132,
    "gn:feature_class":"P",
    "gn:feature_code":"PPL",
    "gn:name":"Ghauspur",
    "gn:population":0,
    "gn:timezone":"Asia/Kolkata",
    "iso:country":"IN",
    "ks:ks_name":"Gaus Pur",
    "ks:ks_pop":558,
    "ks:ks_type":"VILLAGE",
    "ks:ks_uagg_main":0,
    "name:eng_x_preferred":[
        "Gaus Pur"
    ],
    "wof:name":"Gaus Pur",
    "wof:placetype":"neighbourhood",
    "wof:population":558
},
  "geometry": {"coordinates":[81.72639100000001,27.723978],"type":"Point"}
}