{
  "type": "Feature",
  "properties": {
    "gn:admin1_code":"34.0",
    "gn:admin2_code":"217.0",
    "gn:asciiname":"Guriawan",
    "gn:country_code":"IN",
    "gn:dem":80,
    "gn:feature_class":"P",
    "gn:feature_code":"PPL",
    "gn:name":"Guri\u0101wan",
    "gn:population":0,
    "gn:timezone":"Asia/Kolkata",
    "iso:country":"IN",
    "ks:ks_name":"Gurianw",
    "ks:ks_pop":842,
    "ks:ks_type":"VILLAGE",
    "name:eng_x_preferred":[
        "Gurianw"
    ],
    "name:eng_x_variant":[
        "Guriawan"
    ],
    "wof:name":"Gurianw",
    "wof:placetype":"locality",
    "wof:population":842
},
  "geometry": {"coordinates":[84.201386,26.558225],"type":"Point"}
}