{
  "type": "Feature",
  "properties": {
    "iso:country":"IN",
    "ks:ks_name":"Kerli",
    "ks:ks_pop":755,
    "ks:ks_type":"HABITATION",
    "name:eng_x_preferred":[
        "Kerli"
    ],
    "wof:name":"Kerli",
    "wof:placetype":"locality",
    "wof:population":755
},
  "geometry": {"coordinates":[72.80269699999999,26.180272],"type":"Point"}
}