{
  "type": "Feature",
  "properties": {
    "gn:admin1_code":"36",
    "gn:admin2_code":"172.0",
    "gn:asciiname":"Keshoraipur Khewatmai",
    "gn:country_code":"IN",
    "gn:dem":110,
    "gn:feature_class":"P",
    "gn:feature_code":"PPL",
    "gn:name":"Keshor\u0101ipur Khewatmai",
    "gn:population":0,
    "gn:timezone":"Asia/Kolkata",
    "iso:country":"IN",
    "wof:name":"Keshoraipur Khewatmai",
    "wof:placetype":"locality"
},
  "geometry": {"coordinates":[81.18746,25.63584],"type":"Point"}
}