{
  "type": "Feature",
  "properties": {
    "iso:country":"IN",
    "ks:ks_name":"Kolaram",
    "ks:ks_pop":305,
    "ks:ks_type":"HABITATION",
    "name:eng_x_preferred":[
        "Kolaram"
    ],
    "wof:name":"Kolaram",
    "wof:placetype":"locality",
    "wof:population":305
},
  "geometry": {"coordinates":[77.96491899999999,11.27089],"type":"Point"}
}