{
  "type": "Feature",
  "properties": {
    "iso:country":"IN",
    "ks:ks_name":"Veerlamamidi",
    "ks:ks_pop":140,
    "ks:ks_type":"VILLAGE",
    "name:eng_x_preferred":[
        "Veerlamamidi"
    ],
    "wof:name":"Veerlamamidi",
    "wof:placetype":"locality",
    "wof:population":140
},
  "geometry": {"coordinates":[82.447607,17.921143],"type":"Point"}
}