{
  "type": "Feature",
  "properties": {
    "iso:country":"IN",
    "ks:ks_name":"Raj Kumar Para",
    "ks:ks_pop":59,
    "ks:ks_type":"HABITATION",
    "name:eng_x_preferred":[
        "Raj Kumar Para"
    ],
    "wof:name":"Raj Kumar Para",
    "wof:placetype":"locality",
    "wof:population":59
},
  "geometry": {"coordinates":[91.492895,23.765756],"type":"Point"}
}