{
  "type": "Feature",
  "properties": {
    "gn:admin1_code":"2.0",
    "gn:admin2_code":"544.0",
    "gn:asciiname":"Kottavalasa",
    "gn:country_code":"IN",
    "gn:dem":973,
    "gn:feature_class":"P",
    "gn:feature_code":"PPL",
    "gn:name":"Kottavalasa",
    "gn:population":0,
    "gn:timezone":"Asia/Kolkata",
    "iso:country":"IN",
    "wof:name":"Kottavalasa",
    "wof:placetype":"locality"
},
  "geometry": {"coordinates":[83.00518000000002,18.23601],"type":"Point"}
}