{
  "type": "Feature",
  "properties": {
    "iso:country":"IN",
    "ks:ks_alt_nam":"3 BRP",
    "ks:ks_name":"3 Brp",
    "ks:ks_pop":17,
    "ks:ks_type":"HABITATION",
    "name:eng_x_preferred":[
        "3 Brp"
    ],
    "wof:name":"3 Brp",
    "wof:placetype":"locality",
    "wof:population":17
},
  "geometry": {"coordinates":[74.00571100000001,29.371825],"type":"Point"}
}