{
  "type": "Feature",
  "properties": {
    "iso:country":"IN",
    "ks:ks_name":"Bhandara",
    "ks:ks_pop":146,
    "ks:ks_type":"HABITATION",
    "ks:ks_uagg_main":0,
    "name:eng_x_preferred":[
        "Bhandara"
    ],
    "wof:name":"Bhandara",
    "wof:placetype":"neighbourhood",
    "wof:population":146
},
  "geometry": {"coordinates":[86.911252,22.584124],"type":"Point"}
}