{
  "type": "Feature",
  "properties": {
    "iso:country":"IN",
    "ks:ks_name":"Kushedurip",
    "ks:ks_pop":1785,
    "ks:ks_type":"HABITATION",
    "name:eng_x_preferred":[
        "Kushedurip"
    ],
    "wof:name":"Kushedurip",
    "wof:placetype":"locality",
    "wof:population":1785
},
  "geometry": {"coordinates":[87.439223,23.14906],"type":"Point"}
}