{
  "type": "Feature",
  "properties": {
    "iso:country":"IN",
    "ks:ks_name":"Surari",
    "ks:ks_pop":34,
    "ks:ks_type":"VILLAGE",
    "name:eng_x_preferred":[
        "Surari"
    ],
    "wof:name":"Surari",
    "wof:placetype":"locality",
    "wof:population":34
},
  "geometry": {"coordinates":[78.639475,30.249907],"type":"Point"}
}