{
  "type": "Feature",
  "properties": {
    "iso:country":"IN",
    "ks:ks_name":"Mahakal Dara Raigaon",
    "ks:ks_pop":450,
    "ks:ks_type":"HABITATION",
    "name:eng_x_preferred":[
        "Mahakal Dara Raigaon"
    ],
    "wof:name":"Mahakal Dara Raigaon",
    "wof:placetype":"locality",
    "wof:population":450
},
  "geometry": {"coordinates":[88.4829,27.09809],"type":"Point"}
}