{
  "type": "Feature",
  "properties": {
    "iso:country":"IN",
    "ks:ks_name":"Rajabasa",
    "ks:ks_pop":223,
    "ks:ks_type":"VILLAGE",
    "name:eng_x_preferred":[
        "Rajabasa"
    ],
    "wof:name":"Rajabasa",
    "wof:placetype":"locality",
    "wof:population":223
},
  "geometry": {"coordinates":[86.474881,22.185686],"type":"Point"}
}