{
  "type": "Feature",
  "properties": {
    "gn:admin1_code":"10.0",
    "gn:admin2_code":"81.0",
    "gn:asciiname":"Bapaura",
    "gn:country_code":"IN",
    "gn:dem":219,
    "gn:feature_class":"P",
    "gn:feature_code":"PPL",
    "gn:name":"B\u0101paura",
    "gn:population":0,
    "gn:timezone":"Asia/Kolkata",
    "iso:country":"IN",
    "name:spa_x_preferred":[
        "Bapora"
    ],
    "name:tat_x_preferred":[
        "\u0411\u0430\u043f\u043e\u0440\u0430"
    ],
    "name:und_x_variant":[
        "B\u0101paura",
        "Bapaura"
    ],
    "wof:name":"Bapaura",
    "wof:placetype":"neighbourhood"
},
  "geometry": {"coordinates":[76.0672,28.81851],"type":"Point"}
}