{
  "type": "Feature",
  "properties": {
    "gn:admin1_code":"37",
    "gn:admin2_code":"413.0",
    "gn:asciiname":"Batingtola",
    "gn:country_code":"IN",
    "gn:dem":357,
    "gn:feature_class":"P",
    "gn:feature_code":"PPL",
    "gn:name":"B\u0101tingtola",
    "gn:population":0,
    "gn:timezone":"Asia/Kolkata",
    "iso:country":"IN",
    "ks:ks_alt_nam":"B\u0101tingtola",
    "ks:ks_name":"Batingtola",
    "ks:ks_type":"VILLAGE",
    "name:eng_x_preferred":[
        "Batingtola"
    ],
    "name:eng_x_variant":[
        "B\u0101tingtola"
    ],
    "wof:name":"Batingtola",
    "wof:placetype":"locality"
},
  "geometry": {"coordinates":[80.973528,20.137848],"type":"Point"}
}