{
  "type": "Feature",
  "properties": {
    "gn:admin1_code":"36",
    "gn:admin2_code":"173.0",
    "gn:asciiname":"Sonbarsapatti",
    "gn:country_code":"IN",
    "gn:dem":98,
    "gn:feature_class":"P",
    "gn:feature_code":"PPL",
    "gn:name":"Sonbars\u0101patti",
    "gn:population":0,
    "gn:timezone":"Asia/Kolkata",
    "iso:country":"IN",
    "ks:ks_alt_nam":"Sonbars\u0101patti",
    "ks:ks_name":"Sonbarsapatti",
    "ks:ks_type":"VILLAGE",
    "ks:ks_uagg_main":0,
    "name:eng_x_preferred":[
        "Sonbarsapatti"
    ],
    "name:eng_x_variant":[
        "Sonbars\u0101patti"
    ],
    "wof:name":"Sonbarsapatti",
    "wof:placetype":"neighbourhood"
},
  "geometry": {"coordinates":[82.218371,25.963939],"type":"Point"}
}