{
  "type": "Feature",
  "properties": {
    "gn:admin1_code":"34.0",
    "gn:admin2_code":"229.0",
    "gn:asciiname":"Nagwan",
    "gn:country_code":"IN",
    "gn:dem":61,
    "gn:feature_class":"P",
    "gn:feature_code":"PPL",
    "gn:name":"Nagw\u0101n",
    "gn:population":0,
    "gn:timezone":"Asia/Kolkata",
    "iso:country":"IN",
    "ks:ks_name":"Nagman",
    "ks:ks_pop":1155,
    "ks:ks_type":"HABITATION",
    "name:eng_x_preferred":[
        "Nagman"
    ],
    "name:eng_x_variant":[
        "Nagwan"
    ],
    "wof:name":"Nagman",
    "wof:placetype":"locality",
    "wof:population":1155
},
  "geometry": {"coordinates":[85.473258,25.146857],"type":"Point"}
}