{
  "type": "Feature",
  "properties": {
    "iso:country":"IN",
    "ks:ks_name":"Tamligoda",
    "ks:ks_pop":192,
    "ks:ks_type":"VILLAGE",
    "name:eng_x_preferred":[
        "Tamligoda"
    ],
    "wof:name":"Tamligoda",
    "wof:placetype":"locality",
    "wof:population":192
},
  "geometry": {"coordinates":[87.42646999999999,24.778197],"type":"Point"}
}