{
  "type": "Feature",
  "properties": {
    "gn:admin1_code":"36.0",
    "gn:admin2_code":"161",
    "gn:asciiname":"Merhi Dudhi",
    "gn:country_code":"IN",
    "gn:dem":150,
    "gn:feature_class":"P",
    "gn:feature_code":"PPL",
    "gn:name":"Merhi Dudhi",
    "gn:population":0,
    "gn:timezone":"Asia/Kolkata",
    "iso:country":"IN",
    "name:und_x_variant":[
        "Meri Dudhi",
        "Meri Dudhj",
        "Merhi Dudhi"
    ],
    "wof:name":"Merhi Dudhi",
    "wof:placetype":"locality"
},
  "geometry": {"coordinates":[79.15279,26.75249],"type":"Point"}
}