{
  "type": "Feature",
  "properties": {
    "iso:country":"IN",
    "ks:ks_name":"Salwadera",
    "ks:ks_pop":140,
    "ks:ks_type":"HABITATION",
    "ks:ks_uagg_main":0,
    "name:eng_x_preferred":[
        "Salwadera"
    ],
    "wof:name":"Salwadera",
    "wof:placetype":"neighbourhood",
    "wof:population":140
},
  "geometry": {"coordinates":[82.714944,22.171856],"type":"Point"}
}