{
  "type": "Feature",
  "properties": {
    "gn:admin1_code":"11.0",
    "gn:admin2_code":"32.0",
    "gn:asciiname":"Bagan",
    "gn:country_code":"IN",
    "gn:dem":1522,
    "gn:feature_class":"P",
    "gn:feature_code":"PPL",
    "gn:name":"B\u0101gan",
    "gn:population":0,
    "gn:timezone":"Asia/Kolkata",
    "iso:country":"IN",
    "wof:name":"Bagan",
    "wof:placetype":"locality"
},
  "geometry": {"coordinates":[77.71595000000001,30.6828],"type":"Point"}
}