{
  "type": "Feature",
  "properties": {
    "iso:country":"IN",
    "ks:ks_alt_nam":"Thakur kodari",
    "ks:ks_name":"Thakur Kodari",
    "ks:ks_pop":341,
    "ks:ks_type":"HABITATION",
    "name:eng_x_preferred":[
        "Thakur Kodari"
    ],
    "wof:name":"Thakur Kodari",
    "wof:placetype":"locality",
    "wof:population":341
},
  "geometry": {"coordinates":[81.582381,26.985585],"type":"Point"}
}