{
  "type": "Feature",
  "properties": {
    "iso:country":"IN",
    "ks:ks_name":"Police Lane",
    "ks:ks_pop":417,
    "ks:ks_type":"HABITATION",
    "name:eng_x_preferred":[
        "Police Lane"
    ],
    "wof:name":"Police Lane",
    "wof:placetype":"locality",
    "wof:population":417
},
  "geometry": {"coordinates":[78.807204,13.655792],"type":"Point"}
}