{
  "type": "Feature",
  "properties": {
    "iso:country":"IN",
    "ks:ks_name":"Ghormara",
    "ks:ks_pop":287,
    "ks:ks_type":"VILLAGE",
    "name:eng_x_preferred":[
        "Ghormara"
    ],
    "wof:name":"Ghormara",
    "wof:placetype":"locality",
    "wof:population":287
},
  "geometry": {"coordinates":[91.41939499999999,26.012266],"type":"Point"}
}