{
  "type": "Feature",
  "properties": {
    "gn:country":"IN",
    "gn:fcode":"PPL",
    "gn:pop":14854,
    "iso:country":"IN",
    "qs:name":"Kh\u0101npur",
    "qs:photos_9r":0,
    "qs:photos_sr":0,
    "qs:pop_sr":"6",
    "wof:name":"Kh\u0101npur",
    "wof:placetype":"locality",
    "wof:population":14854
},
  "geometry": {"coordinates":[76.39601,24.73241],"type":"Point"}
}