{
  "type": "Feature",
  "properties": {
    "iso:country":"IN",
    "ks:ks_alt_nam":"HARIJAN VASTI",
    "ks:ks_name":"Harijan Vasti",
    "ks:ks_pop":101,
    "ks:ks_type":"HABITATION",
    "name:eng_x_preferred":[
        "Harijan Vasti"
    ],
    "wof:name":"Harijan Vasti",
    "wof:placetype":"locality",
    "wof:population":101
},
  "geometry": {"coordinates":[74.89017699999999,16.807797],"type":"Point"}
}