{
  "type": "Feature",
  "properties": {
    "gn:admin1_code":"25.0",
    "gn:admin2_code":"630.0",
    "gn:asciiname":"Samandahalli",
    "gn:country_code":"IN",
    "gn:dem":390,
    "gn:feature_class":"P",
    "gn:feature_code":"PPL",
    "gn:name":"S\u0101m\u0101ndahalli",
    "gn:population":0,
    "gn:timezone":"Asia/Kolkata",
    "iso:country":"IN",
    "wof:name":"Samandahalli",
    "wof:placetype":"locality"
},
  "geometry": {"coordinates":[78.40078000000003,12.17405],"type":"Point"}
}