{
  "type": "Feature",
  "properties": {
    "gn:admin1_code":"24.0",
    "gn:admin2_code":"123.0",
    "gn:asciiname":"Bhartwa",
    "gn:country_code":"IN",
    "gn:dem":551,
    "gn:feature_class":"P",
    "gn:feature_code":"PPL",
    "gn:name":"Bhartwa",
    "gn:population":0,
    "gn:timezone":"Asia/Kolkata",
    "iso:country":"IN",
    "ks:ks_name":"Bhartawa",
    "ks:ks_pop":1001,
    "ks:ks_type":"VILLAGE",
    "name:eng_x_preferred":[
        "Bhartawa"
    ],
    "name:eng_x_variant":[
        "Bhartwa"
    ],
    "wof:name":"Bhartawa",
    "wof:placetype":"locality",
    "wof:population":1001
},
  "geometry": {"coordinates":[74.260897,25.925181],"type":"Point"}
}