{
  "type": "Feature",
  "properties": {
    "iso:country":"IN",
    "ks:ks_name":"Dimiripal",
    "ks:ks_pop":117,
    "ks:ks_type":"HABITATION",
    "name:eng_x_preferred":[
        "Dimiripal"
    ],
    "wof:name":"Dimiripal",
    "wof:placetype":"locality",
    "wof:population":117
},
  "geometry": {"coordinates":[85.992751,21.104028],"type":"Point"}
}