{
  "type": "Feature",
  "properties": {
    "iso:country":"IN",
    "ks:ks_name":"Dantunguda",
    "ks:ks_pop":162,
    "ks:ks_type":"VILLAGE",
    "name:eng_x_preferred":[
        "Dantunguda"
    ],
    "wof:name":"Dantunguda",
    "wof:placetype":"locality",
    "wof:population":162
},
  "geometry": {"coordinates":[82.17888600000001,18.106241],"type":"Point"}
}