{
  "type": "Feature",
  "properties": {
    "gn:admin1_code":"36.0",
    "gn:admin2_code":"150.0",
    "gn:asciiname":"Naugawan Wiran",
    "gn:country_code":"IN",
    "gn:dem":180,
    "gn:feature_class":"P",
    "gn:feature_code":"PPL",
    "gn:name":"Naugaw\u0101n W\u012br\u0101n",
    "gn:population":0,
    "gn:timezone":"Asia/Kolkata",
    "iso:country":"IN",
    "wof:name":"Naugawan Wiran",
    "wof:placetype":"locality"
},
  "geometry": {"coordinates":[79.68800999999998,28.51284],"type":"Point"}
}