{
  "type": "Feature",
  "properties": {
    "iso:country":"IN",
    "ks:ks_name":"Jamchuwa",
    "ks:ks_pop":356,
    "ks:ks_type":"VILLAGE",
    "name:eng_x_preferred":[
        "Jamchuwa"
    ],
    "wof:name":"Jamchuwa",
    "wof:placetype":"locality",
    "wof:population":356
},
  "geometry": {"coordinates":[83.990745,22.676357],"type":"Point"}
}