{
  "type": "Feature",
  "properties": {
    "iso:country":"IN",
    "ks:ks_name":"Bharathiar Nagar",
    "ks:ks_pop":850,
    "ks:ks_type":"HABITATION",
    "ks:ks_uagg_main":0,
    "name:eng_x_preferred":[
        "Bharathiar Nagar"
    ],
    "wof:name":"Bharathiar Nagar",
    "wof:placetype":"neighbourhood",
    "wof:population":850
},
  "geometry": {"coordinates":[77.63137,8.71475],"type":"Point"}
}