{
  "type": "Feature",
  "properties": {
    "iso:country":"IN",
    "ks:ks_name":"Thakurtola",
    "ks:ks_pop":295,
    "ks:ks_type":"HABITATION",
    "name:eng_x_preferred":[
        "Thakurtola"
    ],
    "wof:name":"Thakurtola",
    "wof:placetype":"locality",
    "wof:population":295
},
  "geometry": {"coordinates":[81.30805599999999,22.34694],"type":"Point"}
}