{
  "type": "Feature",
  "properties": {
    "iso:country":"IN",
    "ks:ks_name":"Chandpur",
    "ks:ks_pop":0,
    "ks:ks_type":"VILLAGE",
    "name:eng_x_preferred":[
        "Chandpur"
    ],
    "wof:name":"Chandpur",
    "wof:placetype":"locality",
    "wof:population":0
},
  "geometry": {"coordinates":[85.638082,22.76576],"type":"Point"}
}