{
  "type": "Feature",
  "properties": {
    "iso:country":"IN",
    "ks:ks_name":"Bichkoli",
    "ks:ks_pop":28,
    "ks:ks_type":"HABITATION",
    "name:eng_x_preferred":[
        "Bichkoli"
    ],
    "wof:name":"Bichkoli",
    "wof:placetype":"locality",
    "wof:population":28
},
  "geometry": {"coordinates":[78.86741600000001,29.968904],"type":"Point"}
}