{
  "type": "Feature",
  "properties": {
    "iso:country":"IN",
    "ks:ks_name":"Kinavanewadi",
    "ks:ks_pop":60,
    "ks:ks_type":"HABITATION",
    "name:eng_x_preferred":[
        "Kinavanewadi"
    ],
    "wof:name":"Kinavanewadi",
    "wof:placetype":"locality",
    "wof:population":60
},
  "geometry": {"coordinates":[73.83617099999999,16.215825],"type":"Point"}
}