{
  "type": "Feature",
  "properties": {
    "gn:admin1_code":"36",
    "gn:admin2_code":"176.0",
    "gn:asciiname":"Safedabad",
    "gn:country_code":"IN",
    "gn:dem":124,
    "gn:feature_class":"P",
    "gn:feature_code":"PPL",
    "gn:name":"Safed\u0101b\u0101d",
    "gn:population":0,
    "gn:timezone":"Asia/Kolkata",
    "iso:country":"IN",
    "ks:ks_name":"Safedabad",
    "ks:ks_pop":731,
    "ks:ks_type":"VILLAGE",
    "ks:ks_uagg_main":0,
    "name:eng_x_preferred":[
        "Safedabad"
    ],
    "wof:name":"Safedabad",
    "wof:placetype":"neighbourhood",
    "wof:population":731
},
  "geometry": {"coordinates":[81.119596,26.903177],"type":"Point"}
}