{
  "type": "Feature",
  "properties": {
    "gn:admin1_code":"23.0",
    "gn:admin2_code":"37.0",
    "gn:asciiname":"Khurshedpur",
    "gn:country_code":"IN",
    "gn:dem":223,
    "gn:feature_class":"P",
    "gn:feature_code":"PPL",
    "gn:name":"Khurshedpur",
    "gn:population":0,
    "gn:timezone":"Asia/Kolkata",
    "iso:country":"IN",
    "wof:name":"Khurshedpur",
    "wof:placetype":"locality"
},
  "geometry": {"coordinates":[75.48239000000002,30.98063],"type":"Point"}
}