{
  "type": "Feature",
  "properties": {
    "iso:country":"IN",
    "ks:ks_name":"Tikrapara",
    "ks:ks_pop":302,
    "ks:ks_type":"HABITATION",
    "name:eng_x_preferred":[
        "Tikrapara"
    ],
    "wof:name":"Tikrapara",
    "wof:placetype":"locality",
    "wof:population":302
},
  "geometry": {"coordinates":[82.559854,22.949368],"type":"Point"}
}