{
  "type": "Feature",
  "properties": {
    "iso:country":"IN",
    "ks:ks_name":"Pechatti",
    "ks:ks_pop":90,
    "ks:ks_type":"HABITATION",
    "name:eng_x_preferred":[
        "Pechatti"
    ],
    "wof:name":"Pechatti",
    "wof:placetype":"locality",
    "wof:population":90
},
  "geometry": {"coordinates":[78.570088,9.677018],"type":"Point"}
}