{
  "type": "Feature",
  "properties": {
    "iso:country":"IN",
    "ks:ks_name":"Ansari Tola",
    "ks:ks_pop":380,
    "ks:ks_type":"HABITATION",
    "name:eng_x_preferred":[
        "Ansari Tola"
    ],
    "wof:name":"Ansari Tola",
    "wof:placetype":"locality",
    "wof:population":380
},
  "geometry": {"coordinates":[84.749769,26.213719],"type":"Point"}
}