{
  "type": "Feature",
  "properties": {
    "gn:admin1_code":"36.0",
    "gn:admin2_code":"177.0",
    "gn:asciiname":"Sardar Singh",
    "gn:country_code":"IN",
    "gn:dem":110,
    "gn:feature_class":"P",
    "gn:feature_code":"PPL",
    "gn:name":"Sard\u0101r Singh",
    "gn:population":0,
    "gn:timezone":"Asia/Kolkata",
    "iso:country":"IN",
    "wof:name":"Sardar Singh",
    "wof:placetype":"locality"
},
  "geometry": {"coordinates":[81.91895,26.7629],"type":"Point"}
}