{
  "type": "Feature",
  "properties": {
    "iso:country":"IN",
    "ks:ks_name":"Parammel",
    "ks:ks_pop":396,
    "ks:ks_type":"HABITATION",
    "name:eng_x_preferred":[
        "Parammel"
    ],
    "wof:name":"Parammel",
    "wof:placetype":"locality",
    "wof:population":396
},
  "geometry": {"coordinates":[75.727153,11.696429],"type":"Point"}
}