{
  "type": "Feature",
  "properties": {
    "iso:country":"IN",
    "ks:ks_name":"Haliasahi",
    "ks:ks_pop":1014,
    "ks:ks_type":"VILLAGE",
    "ks:ks_uagg_main":0,
    "name:eng_x_preferred":[
        "Haliasahi"
    ],
    "wof:name":"Haliasahi",
    "wof:placetype":"neighbourhood",
    "wof:population":1014
},
  "geometry": {"coordinates":[85.468159,20.337109],"type":"Point"}
}