{
  "type": "Feature",
  "properties": {
    "iso:country":"IN",
    "ks:ks_name":"Satakhanda",
    "ks:ks_pop":451,
    "ks:ks_type":"VILLAGE",
    "name:eng_x_preferred":[
        "Satakhanda"
    ],
    "wof:name":"Satakhanda",
    "wof:placetype":"locality",
    "wof:population":451
},
  "geometry": {"coordinates":[84.680003,20.528109],"type":"Point"}
}