{
  "type": "Feature",
  "properties": {
    "iso:country":"IN",
    "ks:ks_name":"Dolalmadhab1",
    "ks:ks_pop":367,
    "ks:ks_type":"HABITATION",
    "ks:ks_uagg_main":0,
    "name:eng_x_preferred":[
        "Dolalmadhab1"
    ],
    "wof:name":"Dolalmadhab1",
    "wof:placetype":"neighbourhood",
    "wof:population":367
},
  "geometry": {"coordinates":[92.95797399999999,26.60027],"type":"Point"}
}