{
  "type": "Feature",
  "properties": {
    "iso:country":"IN",
    "ks:ks_name":"Vellalar Agaram",
    "ks:ks_pop":4282,
    "ks:ks_type":"VILLAGE",
    "ks:ks_uagg_main":0,
    "name:eng_x_preferred":[
        "Vellalar Agaram"
    ],
    "wof:name":"Vellalar Agaram",
    "wof:placetype":"neighbourhood",
    "wof:population":4282
},
  "geometry": {"coordinates":[79.66539899999999,11.11844],"type":"Point"}
}