{
  "type": "Feature",
  "properties": {
    "iso:country":"IN",
    "ks:ks_name":"Pimpalchiwadi",
    "ks:ks_pop":562,
    "ks:ks_type":"HABITATION",
    "name:eng_x_preferred":[
        "Pimpalchiwadi"
    ],
    "wof:name":"Pimpalchiwadi",
    "wof:placetype":"locality",
    "wof:population":562
},
  "geometry": {"coordinates":[74.047218,18.395653],"type":"Point"}
}