{
  "type": "Feature",
  "properties": {
    "iso:country":"IN",
    "ks:ks_alt_nam":"Chack Dheeman wali",
    "ks:ks_name":"Chack Dheeman Wali",
    "ks:ks_pop":510,
    "ks:ks_type":"HABITATION",
    "name:eng_x_preferred":[
        "Chack Dheeman Wali"
    ],
    "wof:name":"Chack Dheeman Wali",
    "wof:placetype":"locality",
    "wof:population":510
},
  "geometry": {"coordinates":[74.707739,30.59356],"type":"Point"}
}