{
  "type": "Feature",
  "properties": {
    "iso:country":"IN",
    "ks:ks_name":"Gandragoyyi",
    "ks:ks_pop":53,
    "ks:ks_type":"HABITATION",
    "name:eng_x_preferred":[
        "Gandragoyyi"
    ],
    "wof:name":"Gandragoyyi",
    "wof:placetype":"locality",
    "wof:population":53
},
  "geometry": {"coordinates":[83.12797999999999,18.699322],"type":"Point"}
}