{
  "type": "Feature",
  "properties": {
    "gn:admin1_code":"19.0",
    "gn:admin2_code":"578.0",
    "gn:asciiname":"Ammanapura",
    "gn:country_code":"IN",
    "gn:dem":683,
    "gn:feature_class":"P",
    "gn:feature_code":"PPL",
    "gn:name":"Ammanapura",
    "gn:population":0,
    "gn:timezone":"Asia/Kolkata",
    "iso:country":"IN",
    "wof:name":"Ammanapura",
    "wof:placetype":"locality"
},
  "geometry": {"coordinates":[77.03644,11.95507],"type":"Point"}
}