{
  "type": "Feature",
  "properties": {
    "gn:admin1_code":"36",
    "gn:admin2_code":"199.0",
    "gn:asciiname":"Barauhan",
    "gn:country_code":"IN",
    "gn:dem":244,
    "gn:feature_class":"P",
    "gn:feature_code":"PPL",
    "gn:name":"Barauh\u0101n",
    "gn:population":0,
    "gn:timezone":"Asia/Kolkata",
    "iso:country":"IN",
    "wof:name":"Barauhan",
    "wof:placetype":"locality"
},
  "geometry": {"coordinates":[82.35035999999999,24.63976],"type":"Point"}
}