{
  "type": "Feature",
  "properties": {
    "gn:admin1_code":"21.0",
    "gn:admin2_code":"371.0",
    "gn:asciiname":"Tangarpali",
    "gn:country_code":"IN",
    "gn:dem":223,
    "gn:feature_class":"P",
    "gn:feature_code":"PPL",
    "gn:name":"Tangarpali",
    "gn:population":0,
    "gn:timezone":"Asia/Kolkata",
    "iso:country":"IN",
    "wof:name":"Tangarpali",
    "wof:placetype":"locality"
},
  "geometry": {"coordinates":[84.02963000000003,21.94003],"type":"Point"}
}