{
  "type": "Feature",
  "properties": {
    "iso:country":"IN",
    "ks:ks_alt_nam":"KHATTI",
    "ks:ks_name":"Khatti",
    "ks:ks_pop":567,
    "ks:ks_type":"HABITATION",
    "name:eng_x_preferred":[
        "Khatti"
    ],
    "wof:name":"Khatti",
    "wof:placetype":"locality",
    "wof:population":567
},
  "geometry": {"coordinates":[87.809504,25.260263],"type":"Point"}
}