{
  "type": "Feature",
  "properties": {
    "iso:country":"IN",
    "ks:ks_alt_nam":"M\u0101ngrur",
    "ks:ks_name":"Mangrur",
    "ks:ks_pop":0,
    "ks:ks_type":"VILLAGE",
    "name:eng_x_preferred":[
        "Mangrur"
    ],
    "name:eng_x_variant":[
        "M\u0101ngrur"
    ],
    "wof:name":"Mangrur",
    "wof:placetype":"locality",
    "wof:population":0
},
  "geometry": {"coordinates":[79.29230099999999,20.483917],"type":"Point"}
}