{
  "type": "Feature",
  "properties": {
    "iso:country":"IN",
    "ks:ks_name":"Chak Usman",
    "ks:ks_pop":0,
    "ks:ks_type":"VILLAGE",
    "name:eng_x_preferred":[
        "Chak Usman"
    ],
    "wof:name":"Chak Usman",
    "wof:placetype":"locality",
    "wof:population":0
},
  "geometry": {"coordinates":[85.754891,25.134634],"type":"Point"}
}