{
  "type": "Feature",
  "properties": {
    "gn:admin1_code":"35.0",
    "gn:admin2_code":"420.0",
    "gn:asciiname":"Singwari",
    "gn:country_code":"IN",
    "gn:dem":178,
    "gn:feature_class":"P",
    "gn:feature_code":"PPL",
    "gn:name":"Singw\u0101ri",
    "gn:population":0,
    "gn:timezone":"Asia/Kolkata",
    "iso:country":"IN",
    "wof:name":"Singwari",
    "wof:placetype":"neighbourhood"
},
  "geometry": {"coordinates":[78.28636,26.3744],"type":"Point"}
}