{
  "type": "Feature",
  "properties": {
    "iso:country":"IN",
    "ks:ks_alt_nam":"BABAR PANAND",
    "ks:ks_name":"Babar Panand",
    "ks:ks_pop":158,
    "ks:ks_type":"HABITATION",
    "name:eng_x_preferred":[
        "Babar Panand"
    ],
    "wof:name":"Babar Panand",
    "wof:placetype":"locality",
    "wof:population":158
},
  "geometry": {"coordinates":[74.24176,16.941436],"type":"Point"}
}