{
  "type": "Feature",
  "properties": {
    "iso:country":"IN",
    "ks:ks_name":"Rajpur Miya Tola",
    "ks:ks_pop":529,
    "ks:ks_type":"HABITATION",
    "name:eng_x_preferred":[
        "Rajpur Miya Tola"
    ],
    "wof:name":"Rajpur Miya Tola",
    "wof:placetype":"locality",
    "wof:population":529
},
  "geometry": {"coordinates":[86.832142,25.919877],"type":"Point"}
}