{
  "type": "Feature",
  "properties": {
    "gn:admin1_code":"35",
    "gn:admin2_code":"423.0",
    "gn:asciiname":"Tilatili ka Chak",
    "gn:country_code":"IN",
    "gn:dem":443,
    "gn:feature_class":"P",
    "gn:feature_code":"PPL",
    "gn:name":"Til\u0101tili ka Chak",
    "gn:population":0,
    "gn:timezone":"Asia/Kolkata",
    "iso:country":"IN",
    "name:und_x_variant":[
        "Til\u0101tili ka Chak",
        "R\u0101mpura"
    ],
    "wof:name":"Tilatili ka Chak",
    "wof:placetype":"locality"
},
  "geometry": {"coordinates":[77.57961,25.01013],"type":"Point"}
}