{
  "type": "Feature",
  "properties": {
    "iso:country":"IN",
    "ks:ks_name":"Pedaguda",
    "ks:ks_pop":145,
    "ks:ks_type":"HABITATION",
    "name:eng_x_preferred":[
        "Pedaguda"
    ],
    "wof:name":"Pedaguda",
    "wof:placetype":"locality",
    "wof:population":145
},
  "geometry": {"coordinates":[83.688243,19.029085],"type":"Point"}
}