{
  "type": "Feature",
  "properties": {
    "iso:country":"IN",
    "ks:ks_name":"Haribar",
    "ks:ks_pop":444,
    "ks:ks_type":"VILLAGE",
    "name:eng_x_preferred":[
        "Haribar"
    ],
    "wof:name":"Haribar",
    "wof:placetype":"locality",
    "wof:population":444
},
  "geometry": {"coordinates":[87.36629000000001,22.062856],"type":"Point"}
}