{
  "type": "Feature",
  "properties": {
    "iso:country":"IN",
    "ks:ks_alt_nam":"HENDA",
    "ks:ks_name":"Henda",
    "ks:ks_pop":151,
    "ks:ks_type":"HABITATION",
    "name:eng_x_preferred":[
        "Henda"
    ],
    "wof:name":"Henda",
    "wof:placetype":"locality",
    "wof:population":151
},
  "geometry": {"coordinates":[85.23086000000001,23.754504],"type":"Point"}
}