{
  "type": "Feature",
  "properties": {
    "gn:admin1_code":"39.0",
    "gn:admin2_code":"64.0",
    "gn:asciiname":"Durnauli",
    "gn:country_code":"IN",
    "gn:dem":883,
    "gn:feature_class":"P",
    "gn:feature_code":"PPL",
    "gn:name":"Durnauli",
    "gn:population":0,
    "gn:timezone":"Asia/Kolkata",
    "iso:country":"IN",
    "wof:name":"Durnauli",
    "wof:placetype":"locality"
},
  "geometry": {"coordinates":[79.89490000000001,29.48958],"type":"Point"}
}