{
  "type": "Feature",
  "properties": {
    "iso:country":"IN",
    "ks:ks_name":"Manauwar Chak",
    "ks:ks_pop":439,
    "ks:ks_type":"VILLAGE",
    "ks:ks_uagg_main":0,
    "name:eng_x_preferred":[
        "Manauwar Chak"
    ],
    "wof:name":"Manauwar Chak",
    "wof:placetype":"neighbourhood",
    "wof:population":439
},
  "geometry": {"coordinates":[84.005359,25.564625],"type":"Point"}
}