{
  "type": "Feature",
  "properties": {
    "gn:admin1_code":"36",
    "gn:admin2_code":"147.0",
    "gn:asciiname":"Nagla Khera",
    "gn:country_code":"IN",
    "gn:dem":160,
    "gn:feature_class":"P",
    "gn:feature_code":"PPL",
    "gn:name":"Nagla Khera",
    "gn:population":0,
    "gn:timezone":"Asia/Kolkata",
    "iso:country":"IN",
    "ks:ks_alt_nam":"NAGLA KHERA",
    "ks:ks_name":"Nagla Khera",
    "ks:ks_pop":82,
    "ks:ks_type":"HABITATION",
    "name:eng_x_preferred":[
        "Nagla Khera"
    ],
    "wof:name":"Nagla Khera",
    "wof:placetype":"locality",
    "wof:population":82
},
  "geometry": {"coordinates":[78.673265,27.044086],"type":"Point"}
}