{
  "type": "Feature",
  "properties": {
    "gn:admin1_code":"40.0",
    "gn:admin2_code":"541.0",
    "gn:asciiname":"Kokkiragudem",
    "gn:country_code":"IN",
    "gn:dem":97,
    "gn:feature_class":"P",
    "gn:feature_code":"PPL",
    "gn:name":"Kokkirag\u016bdem",
    "gn:population":0,
    "gn:timezone":"Asia/Kolkata",
    "iso:country":"IN",
    "ks:ks_alt_nam":"Kokkirag\u016bdem",
    "ks:ks_name":"Kokkiragudem",
    "ks:ks_type":"VILLAGE",
    "name:eng_x_preferred":[
        "Kokkiragudem"
    ],
    "name:eng_x_variant":[
        "Kokkirag\u016bdem"
    ],
    "wof:name":"Kokkiragudem",
    "wof:placetype":"locality"
},
  "geometry": {"coordinates":[81.418756,17.664583],"type":"Point"}
}