{
  "type": "Feature",
  "properties": {
    "iso:country":"IN",
    "ks:ks_name":"Barli",
    "ks:ks_pop":502,
    "ks:ks_type":"HABITATION",
    "name:eng_x_preferred":[
        "Barli"
    ],
    "wof:name":"Barli",
    "wof:placetype":"locality",
    "wof:population":502
},
  "geometry": {"coordinates":[75.443899,12.960632],"type":"Point"}
}