{
  "type": "Feature",
  "properties": {
    "iso:country":"IN",
    "ks:ks_name":"Samalpur",
    "ks:ks_pop":154,
    "ks:ks_type":"VILLAGE",
    "ks:ks_uagg_main":0,
    "name:eng_x_preferred":[
        "Samalpur"
    ],
    "wof:name":"Samalpur",
    "wof:placetype":"neighbourhood",
    "wof:population":154
},
  "geometry": {"coordinates":[85.83290599999999,20.124476],"type":"Point"}
}