{
  "type": "Feature",
  "properties": {
    "gn:admin1_code":"11",
    "gn:admin2_code":"30.0",
    "gn:asciiname":"Sarhwar",
    "gn:country_code":"IN",
    "gn:dem":1143,
    "gn:feature_class":"P",
    "gn:feature_code":"PPL",
    "gn:name":"Sarhw\u0101r",
    "gn:population":0,
    "gn:timezone":"Asia/Kolkata",
    "iso:country":"IN",
    "wof:name":"Sarhwar",
    "wof:placetype":"locality"
},
  "geometry": {"coordinates":[76.85594,31.30645],"type":"Point"}
}