{
  "type": "Feature",
  "properties": {
    "iso:country":"IN",
    "ks:ks_name":"Kothaguda",
    "ks:ks_pop":12,
    "ks:ks_type":"HABITATION",
    "name:eng_x_preferred":[
        "Kothaguda"
    ],
    "wof:name":"Kothaguda",
    "wof:placetype":"locality",
    "wof:population":12
},
  "geometry": {"coordinates":[84.008134,18.806415],"type":"Point"}
}