{
  "type": "Feature",
  "properties": {
    "iso:country":"IN",
    "ks:ks_alt_nam":"SALIHA",
    "ks:ks_name":"Saliha",
    "ks:ks_pop":690,
    "ks:ks_type":"HABITATION",
    "name:eng_x_preferred":[
        "Saliha"
    ],
    "wof:name":"Saliha",
    "wof:placetype":"locality",
    "wof:population":690
},
  "geometry": {"coordinates":[81.748909,22.269064],"type":"Point"}
}