{
  "type": "Feature",
  "properties": {
    "iso:country":"IN",
    "ks:ks_name":"Kusumtoli",
    "ks:ks_pop":260,
    "ks:ks_type":"HABITATION",
    "name:eng_x_preferred":[
        "Kusumtoli"
    ],
    "wof:name":"Kusumtoli",
    "wof:placetype":"locality",
    "wof:population":260
},
  "geometry": {"coordinates":[84.781012,23.062857],"type":"Point"}
}