{
  "type": "Feature",
  "properties": {
    "iso:country":"IN",
    "ks:ks_name":"Chatamba",
    "ks:ks_pop":50,
    "ks:ks_type":"HABITATION",
    "name:eng_x_preferred":[
        "Chatamba"
    ],
    "wof:name":"Chatamba",
    "wof:placetype":"locality",
    "wof:population":50
},
  "geometry": {"coordinates":[82.863317,19.173138],"type":"Point"}
}