{
  "type": "Feature",
  "properties": {
    "iso:country":"IN",
    "ks:ks_name":"Zuralewasti",
    "ks:ks_pop":250,
    "ks:ks_type":"HABITATION",
    "name:eng_x_preferred":[
        "Zuralewasti"
    ],
    "wof:name":"Zuralewasti",
    "wof:placetype":"locality",
    "wof:population":250
},
  "geometry": {"coordinates":[75.181422,17.86723],"type":"Point"}
}