{
  "type": "Feature",
  "properties": {
    "iso:country":"IN",
    "ks:ks_alt_nam":"PURE KAMUAN NAGAR",
    "ks:ks_name":"Pure Kamuan Nagar",
    "ks:ks_pop":71,
    "ks:ks_type":"HABITATION",
    "name:eng_x_preferred":[
        "Pure Kamuan Nagar"
    ],
    "wof:name":"Pure Kamuan Nagar",
    "wof:placetype":"locality",
    "wof:population":71
},
  "geometry": {"coordinates":[81.4358,26.4717],"type":"Point"}
}