{
  "type": "Feature",
  "properties": {
    "iso:country":"IN",
    "ks:ks_alt_nam":"Harchandra R. para",
    "ks:ks_name":"Harchandra R. Para",
    "ks:ks_pop":233,
    "ks:ks_type":"HABITATION",
    "name:eng_x_preferred":[
        "Harchandra R. Para"
    ],
    "wof:name":"Harchandra R. Para",
    "wof:placetype":"locality",
    "wof:population":233
},
  "geometry": {"coordinates":[91.379234,23.30844],"type":"Point"}
}