{
  "type": "Feature",
  "properties": {
    "iso:country":"IN",
    "ks:ks_name":"Chchaity",
    "ks:ks_pop":387,
    "ks:ks_type":"HABITATION",
    "name:eng_x_preferred":[
        "Chchaity"
    ],
    "wof:name":"Chchaity",
    "wof:placetype":"locality",
    "wof:population":387
},
  "geometry": {"coordinates":[78.393804,27.508619],"type":"Point"}
}