{
  "type": "Feature",
  "properties": {
    "iso:country":"IN",
    "ks:ks_name":"Mailawas Gusaiyan",
    "ks:ks_pop":100,
    "ks:ks_type":"VILLAGE",
    "name:eng_x_preferred":[
        "Mailawas Gusaiyan"
    ],
    "wof:name":"Mailawas Gusaiyan",
    "wof:placetype":"locality",
    "wof:population":100
},
  "geometry": {"coordinates":[71.728069,25.020617],"type":"Point"}
}