{
  "type": "Feature",
  "properties": {
    "iso:country":"IN",
    "ks:ks_name":"Pahadwa",
    "ks:ks_pop":659,
    "ks:ks_type":"VILLAGE",
    "name:eng_x_preferred":[
        "Pahadwa"
    ],
    "wof:name":"Pahadwa",
    "wof:placetype":"locality",
    "wof:population":659
},
  "geometry": {"coordinates":[74.69192,22.430264],"type":"Point"}
}