{
  "type": "Feature",
  "properties": {
    "gn:admin1_code":"28.0",
    "gn:admin2_code":"345",
    "gn:asciiname":"Argoal",
    "gn:country_code":"IN",
    "gn:dem":7,
    "gn:feature_class":"P",
    "gn:feature_code":"PPL",
    "gn:name":"\u0100rgo\u0101l",
    "gn:population":0,
    "gn:timezone":"Asia/Kolkata",
    "iso:country":"IN",
    "wof:name":"Argoal",
    "wof:placetype":"locality"
},
  "geometry": {"coordinates":[87.63398000000002,21.96939],"type":"Point"}
}