{
  "type": "Feature",
  "properties": {
    "gn:admin1_code":"24.0",
    "gn:admin2_code":"124",
    "gn:asciiname":"Dhambora",
    "gn:country_code":"IN",
    "gn:dem":233,
    "gn:feature_class":"P",
    "gn:feature_code":"PPL",
    "gn:name":"Dhambora",
    "gn:population":0,
    "gn:timezone":"Asia/Kolkata",
    "iso:country":"IN",
    "name:und_x_variant":[
        "Dhambola",
        "Dhambora"
    ],
    "wof:name":"Dhambora",
    "wof:placetype":"locality"
},
  "geometry": {"coordinates":[73.76656,23.58968],"type":"Point"}
}