{
  "type": "Feature",
  "properties": {
    "iso:country":"IN",
    "ks:ks_name":"Nandiya",
    "ks:ks_pop":243,
    "ks:ks_type":"HABITATION",
    "name:eng_x_preferred":[
        "Nandiya"
    ],
    "wof:name":"Nandiya",
    "wof:placetype":"locality",
    "wof:population":243
},
  "geometry": {"coordinates":[73.36648099999999,24.53955],"type":"Point"}
}