{
  "type": "Feature",
  "properties": {
    "iso:country":"IN",
    "ks:ks_name":"Khara Mahechan",
    "ks:ks_pop":980,
    "ks:ks_type":"HABITATION",
    "name:eng_x_preferred":[
        "Khara Mahechan"
    ],
    "wof:name":"Khara Mahechan",
    "wof:placetype":"locality",
    "wof:population":980
},
  "geometry": {"coordinates":[72.013006,25.512197],"type":"Point"}
}