{
  "type": "Feature",
  "properties": {
    "iso:country":"IN",
    "ks:ks_name":"Patil Wasti",
    "ks:ks_pop":213,
    "ks:ks_type":"HABITATION",
    "name:eng_x_preferred":[
        "Patil Wasti"
    ],
    "wof:name":"Patil Wasti",
    "wof:placetype":"locality",
    "wof:population":213
},
  "geometry": {"coordinates":[75.400357,17.968515],"type":"Point"}
}