{
  "type": "Feature",
  "properties": {
    "gn:admin1_code":"2",
    "gn:admin2_code":"544.0",
    "gn:asciiname":"Zangalapalle Agraharam",
    "gn:country_code":"IN",
    "gn:dem":43,
    "gn:feature_class":"P",
    "gn:feature_code":"PPL",
    "gn:name":"Zang\u0101lapalle Agrah\u0101ram",
    "gn:population":0,
    "gn:timezone":"Asia/Kolkata",
    "iso:country":"IN",
    "wof:name":"Zangalapalle Agraharam",
    "wof:placetype":"locality"
},
  "geometry": {"coordinates":[82.71034,17.579],"type":"Point"}
}