{
  "type": "Feature",
  "properties": {
    "iso:country":"IN",
    "ks:ks_alt_nam":"TS Kadlur",
    "ks:ks_name":"Ts Kadlur",
    "ks:ks_pop":1481,
    "ks:ks_type":"HABITATION",
    "name:eng_x_preferred":[
        "Ts Kadlur"
    ],
    "wof:name":"Ts Kadlur",
    "wof:placetype":"locality",
    "wof:population":1481
},
  "geometry": {"coordinates":[77.022865,15.817968],"type":"Point"}
}