{
  "type": "Feature",
  "properties": {
    "iso:country":"IN",
    "ks:ks_name":"Sera Pakhudi",
    "ks:ks_pop":102,
    "ks:ks_type":"VILLAGE",
    "name:eng_x_preferred":[
        "Sera Pakhudi"
    ],
    "wof:name":"Sera Pakhudi",
    "wof:placetype":"locality",
    "wof:population":102
},
  "geometry": {"coordinates":[79.327845,30.199252],"type":"Point"}
}