{
  "type": "Feature",
  "properties": {
    "gn:admin1_code":"34",
    "gn:admin2_code":"207.0",
    "gn:asciiname":"Laukaha",
    "gn:country_code":"IN",
    "gn:dem":86,
    "gn:feature_class":"P",
    "gn:feature_code":"PPL",
    "gn:name":"Lauk\u0101ha",
    "gn:population":0,
    "gn:timezone":"Asia/Kolkata",
    "iso:country":"IN",
    "name:und_x_variant":[
        "Lauk\u0101ha"
    ],
    "wof:name":"Laukaha",
    "wof:placetype":"locality"
},
  "geometry": {"coordinates":[86.47269,26.55045],"type":"Point"}
}