{
  "type": "Feature",
  "properties": {
    "iso:country":"IN",
    "ks:ks_name":"Mundamoole",
    "ks:ks_pop":231,
    "ks:ks_type":"HABITATION",
    "name:eng_x_preferred":[
        "Mundamoole"
    ],
    "wof:name":"Mundamoole",
    "wof:placetype":"locality",
    "wof:population":231
},
  "geometry": {"coordinates":[75.076193,12.677226],"type":"Point"}
}