{
  "type": "Feature",
  "properties": {
    "iso:country":"IN",
    "ks:ks_name":"Sainbiri",
    "ks:ks_pop":198,
    "ks:ks_type":"HABITATION",
    "name:eng_x_preferred":[
        "Sainbiri"
    ],
    "wof:name":"Sainbiri",
    "wof:placetype":"locality",
    "wof:population":198
},
  "geometry": {"coordinates":[85.36945299999999,20.936878],"type":"Point"}
}