{
  "type": "Feature",
  "properties": {
    "gn:admin1_code":"37",
    "gn:admin2_code":"404.0",
    "gn:asciiname":"Basin",
    "gn:country_code":"IN",
    "gn:dem":436,
    "gn:feature_class":"P",
    "gn:feature_code":"PPL",
    "gn:name":"B\u0101sin",
    "gn:population":0,
    "gn:timezone":"Asia/Kolkata",
    "iso:country":"IN",
    "ks:ks_name":"Basin",
    "ks:ks_pop":371,
    "ks:ks_type":"HABITATION",
    "name:ara_x_preferred":[
        "\u062d\u0648\u0636"
    ],
    "name:cat_x_preferred":[
        "Basin"
    ],
    "name:ceb_x_preferred":[
        "Basin"
    ],
    "name:deu_x_preferred":[
        "Basin"
    ],
    "name:eng_x_preferred":[
        "Basin"
    ],
    "name:fra_x_preferred":[
        "Basin"
    ],
    "name:ind_x_preferred":[
        "Basin"
    ],
    "name:ita_x_preferred":[
        "Basin"
    ],
    "name:nld_x_preferred":[
        "Basin"
    ],
    "name:pol_x_preferred":[
        "Basin"
    ],
    "name:por_x_preferred":[
        "Basin"
    ],
    "name:rus_x_preferred":[
        "\u0411\u0430\u0441\u0438\u043d"
    ],
    "name:spa_x_preferred":[
        "Basin"
    ],
    "name:srp_x_preferred":[
        "\u0411\u0430\u0441\u0435\u043d"
    ],
    "name:ukr_x_preferred":[
        "\u0411\u0430\u0441\u0456\u043d"
    ],
    "name:vol_x_preferred":[
        "Basin"
    ],
    "wof:name":"Basin",
    "wof:placetype":"locality",
    "wof:population":371
},
  "geometry": {"coordinates":[82.345063,22.777357],"type":"Point"}
}