{
  "type": "Feature",
  "properties": {
    "iso:country":"IN",
    "ks:ks_name":"K K S C Colony",
    "ks:ks_pop":359,
    "ks:ks_type":"HABITATION",
    "ks:ks_uagg_main":0,
    "name:eng_x_preferred":[
        "K K S C Colony"
    ],
    "wof:name":"K K S C Colony",
    "wof:placetype":"neighbourhood",
    "wof:population":359
},
  "geometry": {"coordinates":[79.038265,14.580561],"type":"Point"}
}