{
  "type": "Feature",
  "properties": {
    "iso:country":"IN",
    "ks:ks_alt_nam":"LAVANGARE WASTI",
    "ks:ks_name":"Lavangare Wasti",
    "ks:ks_pop":226,
    "ks:ks_type":"HABITATION",
    "name:eng_x_preferred":[
        "Lavangare Wasti"
    ],
    "wof:name":"Lavangare Wasti",
    "wof:placetype":"locality",
    "wof:population":226
},
  "geometry": {"coordinates":[74.325338,17.37228],"type":"Point"}
}