{
  "type": "Feature",
  "properties": {
    "gn:admin1_code":"25.0",
    "gn:admin2_code":"602.0",
    "gn:asciiname":"Suravarikandigai",
    "gn:country_code":"IN",
    "gn:dem":34,
    "gn:feature_class":"P",
    "gn:feature_code":"PPL",
    "gn:name":"S\u016brav\u0101rikandigai",
    "gn:population":0,
    "gn:timezone":"Asia/Kolkata",
    "iso:country":"IN",
    "ks:ks_name":"Sooravari Kandigai",
    "ks:ks_pop":732,
    "ks:ks_type":"HABITATION",
    "name:eng_x_preferred":[
        "Sooravari Kandigai"
    ],
    "name:eng_x_variant":[
        "Suravarikandigai"
    ],
    "wof:name":"Sooravari Kandigai",
    "wof:placetype":"locality",
    "wof:population":732
},
  "geometry": {"coordinates":[80.059825,13.390339],"type":"Point"}
}