{
  "type": "Feature",
  "properties": {
    "gn:admin1_code":"11",
    "gn:admin2_code":"33.0",
    "gn:asciiname":"Boileauganj",
    "gn:country_code":"IN",
    "gn:dem":2098,
    "gn:feature_class":"P",
    "gn:feature_code":"PPL",
    "gn:name":"Boileauganj",
    "gn:population":0,
    "gn:timezone":"Asia/Kolkata",
    "iso:country":"IN",
    "wof:name":"Boileauganj",
    "wof:placetype":"locality"
},
  "geometry": {"coordinates":[77.13965,31.0996],"type":"Point"}
}