{
  "type": "Feature",
  "properties": {
    "iso:country":"IN",
    "ks:ks_name":"Bansdih",
    "ks:ks_pop":1314,
    "ks:ks_type":"VILLAGE",
    "name:eng_x_preferred":[
        "Bansdih"
    ],
    "wof:name":"Bansdih",
    "wof:placetype":"locality",
    "wof:population":1314
},
  "geometry": {"coordinates":[86.232209,24.429948],"type":"Point"}
}