{
  "type": "Feature",
  "properties": {
    "iso:country":"IN",
    "ks:ks_alt_nam":"MAHATPURA",
    "ks:ks_name":"Mahatpura",
    "ks:ks_pop":875,
    "ks:ks_type":"HABITATION",
    "ks:ks_uagg_main":0,
    "name:eng_x_preferred":[
        "Mahatpura"
    ],
    "wof:name":"Mahatpura",
    "wof:placetype":"neighbourhood",
    "wof:population":875
},
  "geometry": {"coordinates":[78.852864,26.85177],"type":"Point"}
}