{
  "type": "Feature",
  "properties": {
    "iso:country":"IN",
    "ks:ks_alt_nam":"madi ka magra",
    "ks:ks_name":"Madi Ka Magra",
    "ks:ks_pop":530,
    "ks:ks_type":"HABITATION",
    "name:eng_x_preferred":[
        "Madi Ka Magra"
    ],
    "wof:name":"Madi Ka Magra",
    "wof:placetype":"locality",
    "wof:population":530
},
  "geometry": {"coordinates":[72.84803599999999,27.888083],"type":"Point"}
}