{
  "type": "Feature",
  "properties": {
    "iso:country":"IN",
    "ks:ks_name":"Goraul Bhagwanpur",
    "ks:ks_pop":4811,
    "ks:ks_type":"VILLAGE",
    "name:eng_x_preferred":[
        "Goraul Bhagwanpur"
    ],
    "wof:name":"Goraul Bhagwanpur",
    "wof:placetype":"locality",
    "wof:population":4811
},
  "geometry": {"coordinates":[85.329949,25.938523],"type":"Point"}
}