{
  "type": "Feature",
  "properties": {
    "iso:country":"IN",
    "ks:ks_name":"Dangarwasti",
    "ks:ks_pop":90,
    "ks:ks_type":"HABITATION",
    "name:eng_x_preferred":[
        "Dangarwasti"
    ],
    "wof:name":"Dangarwasti",
    "wof:placetype":"locality",
    "wof:population":90
},
  "geometry": {"coordinates":[74.355071,17.815433],"type":"Point"}
}