{
  "type": "Feature",
  "properties": {
    "iso:country":"IN",
    "ks:ks_name":"Kanakpura",
    "ks:ks_pop":795,
    "ks:ks_type":"HABITATION",
    "name:eng_x_preferred":[
        "Kanakpura"
    ],
    "wof:name":"Kanakpura",
    "wof:placetype":"locality",
    "wof:population":795
},
  "geometry": {"coordinates":[72.858907,22.520995],"type":"Point"}
}