{
  "type": "Feature",
  "properties": {
    "gn:admin1_code":"36",
    "gn:admin2_code":"202.0",
    "gn:asciiname":"Partabpur",
    "gn:country_code":"IN",
    "gn:dem":175,
    "gn:feature_class":"P",
    "gn:feature_code":"PPL",
    "gn:name":"Part\u0101bpur",
    "gn:population":0,
    "gn:timezone":"Asia/Kolkata",
    "iso:country":"IN",
    "name:und_x_variant":[
        "Part\u0101bpur",
        "Ni\u0101zunnisa"
    ],
    "wof:name":"Partabpur",
    "wof:placetype":"locality"
},
  "geometry": {"coordinates":[78.80141999999999,27.79047000000001],"type":"Point"}
}