{
  "type": "Feature",
  "properties": {
    "iso:country":"IN",
    "ks:ks_name":"Borolanghereng",
    "ks:ks_pop":14,
    "ks:ks_type":"HABITATION",
    "name:eng_x_preferred":[
        "Borolanghereng"
    ],
    "wof:name":"Borolanghereng",
    "wof:placetype":"locality",
    "wof:population":14
},
  "geometry": {"coordinates":[92.888407,25.551535],"type":"Point"}
}