{
  "type": "Feature",
  "properties": {
    "gn:admin1_code":"34.0",
    "gn:admin2_code":"236.0",
    "gn:asciiname":"Chanaria",
    "gn:country_code":"IN",
    "gn:dem":200,
    "gn:feature_class":"P",
    "gn:feature_code":"PPL",
    "gn:name":"Chanari\u0101",
    "gn:population":0,
    "gn:timezone":"Asia/Kolkata",
    "iso:country":"IN",
    "ks:ks_name":"Chanariya",
    "ks:ks_pop":572,
    "ks:ks_type":"VILLAGE",
    "ks:ks_uagg_main":0,
    "name:eng_x_preferred":[
        "Chanariya"
    ],
    "name:spa_x_preferred":[
        "Chanaria"
    ],
    "wof:name":"Chanariya",
    "wof:placetype":"neighbourhood",
    "wof:population":572
},
  "geometry": {"coordinates":[84.477757,24.448479],"type":"Point"}
}