{
  "type": "Feature",
  "properties": {
    "iso:country":"IN",
    "ks:ks_name":"Ramagoundenvalasu",
    "ks:ks_pop":320,
    "ks:ks_type":"HABITATION",
    "name:eng_x_preferred":[
        "Ramagoundenvalasu"
    ],
    "wof:name":"Ramagoundenvalasu",
    "wof:placetype":"locality",
    "wof:population":320
},
  "geometry": {"coordinates":[77.640822,11.439177],"type":"Point"}
}