{
  "type": "Feature",
  "properties": {
    "iso:country":"IN",
    "ks:ks_name":"Kombara",
    "ks:ks_pop":760,
    "ks:ks_type":"HABITATION",
    "name:eng_x_preferred":[
        "Kombara"
    ],
    "wof:name":"Kombara",
    "wof:placetype":"locality",
    "wof:population":760
},
  "geometry": {"coordinates":[76.965076,9.526017],"type":"Point"}
}