{
  "type": "Feature",
  "properties": {
    "iso:country":"IN",
    "ks:ks_alt_nam":"SHERIVASTI",
    "ks:ks_name":"Sherivasti",
    "ks:ks_pop":127,
    "ks:ks_type":"HABITATION",
    "name:eng_x_preferred":[
        "Sherivasti"
    ],
    "wof:name":"Sherivasti",
    "wof:placetype":"locality",
    "wof:population":127
},
  "geometry": {"coordinates":[75.536029,17.150275],"type":"Point"}
}