{
  "type": "Feature",
  "properties": {
    "iso:country":"IN",
    "ks:ks_name":"Pure Chedi",
    "ks:ks_pop":183,
    "ks:ks_type":"HABITATION",
    "ks:ks_uagg_main":0,
    "name:eng_x_preferred":[
        "Pure Chedi"
    ],
    "wof:name":"Pure Chedi",
    "wof:placetype":"neighbourhood",
    "wof:population":183
},
  "geometry": {"coordinates":[81.462551,25.970571],"type":"Point"}
}