{
  "type": "Feature",
  "properties": {
    "iso:country":"IN",
    "qs:name":"Jabalpur Cantt",
    "qs:name_adm0":"India",
    "qs:name_adm1":"Madhya Pradesh",
    "qs:photos":12,
    "qs:photos_1k":2,
    "qs:photos_9k":1,
    "qs:photos_9r":1,
    "qs:photos_all":12,
    "qs:photos_sr":1,
    "qs:placetype":"Town",
    "qs:pop_sr":"0",
    "wd:wordcount":108,
    "wof:name":"Jabalpur Cantt",
    "wof:placetype":"locality"
},
  "geometry": {"coordinates":[80.01685999999999,23.161825],"type":"Point"}
}