{
  "type": "Feature",
  "properties": {
    "gn:country":"IN",
    "gn:fcode":"PPL",
    "gn:population":13345,
    "iso:country":"IN",
    "name:ceb_x_preferred":[
        "M\u0101ndal"
    ],
    "name:eng_x_preferred":[
        "Mandal"
    ],
    "name:guj_x_preferred":[
        "\u0aae\u0abe\u0a82\u0aa1\u0ab2"
    ],
    "name:swe_x_preferred":[
        "M\u0101ndal"
    ],
    "qs:name":"Mandal",
    "qs:name_adm0":"India",
    "qs:name_adm1":"Gujarat",
    "qs:photos_9r":0,
    "qs:photos_sr":0,
    "qs:placetype":"Town",
    "qs:pop_sr":"6",
    "wof:name":"Mandal",
    "wof:placetype":"locality",
    "wof:population":13345
},
  "geometry": {"coordinates":[71.91853999999999,23.28865],"type":"Point"}
}