{
  "type": "Feature",
  "properties": {
    "iso:country":"IN",
    "name:eng_x_preferred":[
        "Govandi"
    ],
    "name:mar_x_preferred":[
        "\u0917\u094b\u0935\u0902\u0921\u0940"
    ],
    "name:sat_x_preferred":[
        "\u1c5c\u1c5a\u1c75\u1c77\u1c5f\u1c71\u1c6b\u1c64"
    ],
    "name:urd_x_preferred":[
        "\u06af\u0648\u0648\u0646\u0688\u06cc"
    ],
    "qs:gn_adm0_cc":"IN",
    "qs:gn_local":1275339,
    "qs:local_max":3819,
    "qs:local_sum":50908,
    "qs:localhoods":70,
    "qs:name":"Govandi",
    "qs:name_adm0":"India",
    "qs:name_adm1":"Maharashtra",
    "qs:name_adm2":"Mumbai Suburban",
    "qs:name_local":"Mumbai",
    "qs:photo_max":45,
    "qs:photo_sum":138,
    "qs:placetype":"Suburb",
    "qs:quad_count":18,
    "qs:woe_adm0":23424848,
    "qs:woe_adm1":2345750,
    "qs:woe_adm2":28743745,
    "qs:woe_lau":0,
    "qs:woe_local":2295411,
    "qs:woe_ver":"7.10.0",
    "wd:wordcount":620,
    "wof:lang":[
        "eng"
    ],
    "wof:name":"Govandi",
    "wof:placetype":"neighbourhood"
},
  "geometry": {"coordinates":[72.919011,19.052796],"type":"Point"}
}