{
  "type": "Feature",
  "properties": {
    "iso:country":"IN",
    "ks:ks_name":"Gaonthanpada",
    "ks:ks_pop":87,
    "ks:ks_type":"HABITATION",
    "name:eng_x_preferred":[
        "Gaonthanpada"
    ],
    "wof:name":"Gaonthanpada",
    "wof:placetype":"locality",
    "wof:population":87
},
  "geometry": {"coordinates":[73.02763400000001,19.926972],"type":"Point"}
}