{
  "type": "Feature",
  "properties": {
    "iso:country":"IN",
    "ks:ks_name":"Kattuvalasu",
    "ks:ks_pop":105,
    "ks:ks_type":"HABITATION",
    "ks:ks_uagg_main":0,
    "name:eng_x_preferred":[
        "Kattuvalasu"
    ],
    "wof:name":"Kattuvalasu",
    "wof:placetype":"neighbourhood",
    "wof:population":105
},
  "geometry": {"coordinates":[77.316642,11.260308],"type":"Point"}
}