{
  "type": "Feature",
  "properties": {
    "iso:country":"IN",
    "ks:ks_name":"Meenambanallur",
    "ks:ks_pop":810,
    "ks:ks_type":"HABITATION",
    "name:eng_x_preferred":[
        "Meenambanallur"
    ],
    "wof:name":"Meenambanallur",
    "wof:placetype":"locality",
    "wof:population":810
},
  "geometry": {"coordinates":[79.7824,10.634353],"type":"Point"}
}