{
  "type": "Feature",
  "properties": {
    "iso:country":"IN",
    "ks:ks_name":"Suvvapalli",
    "ks:ks_pop":71,
    "ks:ks_type":"HABITATION",
    "name:eng_x_preferred":[
        "Suvvapalli"
    ],
    "wof:name":"Suvvapalli",
    "wof:placetype":"locality",
    "wof:population":71
},
  "geometry": {"coordinates":[82.115497,17.904751],"type":"Point"}
}