{
  "type": "Feature",
  "properties": {
    "iso:country":"IN",
    "ks:ks_name":"Brindabanpur",
    "ks:ks_pop":52,
    "ks:ks_type":"VILLAGE",
    "name:eng_x_preferred":[
        "Brindabanpur"
    ],
    "wof:name":"Brindabanpur",
    "wof:placetype":"locality",
    "wof:population":52
},
  "geometry": {"coordinates":[87.46262400000001,23.341733],"type":"Point"}
}