{
  "type": "Feature",
  "properties": {
    "gn:admin1_code":"36",
    "gn:admin2_code":"181.0",
    "gn:asciiname":"Gilaula",
    "gn:country_code":"IN",
    "gn:dem":124,
    "gn:feature_class":"P",
    "gn:feature_code":"PPL",
    "gn:name":"Gilaula",
    "gn:population":0,
    "gn:timezone":"Asia/Kolkata",
    "iso:country":"IN",
    "ks:ks_name":"Gilaula",
    "ks:ks_pop":4008,
    "ks:ks_type":"VILLAGE",
    "ks:ks_uagg_main":0,
    "name:eng_x_preferred":[
        "Gilaula"
    ],
    "wof:name":"Gilaula",
    "wof:placetype":"neighbourhood",
    "wof:population":4008
},
  "geometry": {"coordinates":[81.79982099999999,27.548042],"type":"Point"}
}