{
  "type": "Feature",
  "properties": {
    "iso:country":"IN",
    "ks:ks_alt_nam":"Jallivaripeta-Kodurupadu",
    "ks:ks_name":"Jallivaripeta-kodurupadu",
    "ks:ks_pop":419,
    "ks:ks_type":"HABITATION",
    "name:eng_x_preferred":[
        "Jallivaripeta-kodurupadu"
    ],
    "wof:name":"Jallivaripeta-kodurupadu",
    "wof:placetype":"locality",
    "wof:population":419
},
  "geometry": {"coordinates":[82.000805,16.540109],"type":"Point"}
}