{
  "type": "Feature",
  "properties": {
    "iso:country":"IN",
    "ks:ks_alt_nam":"Mahi\u0101rpur",
    "ks:ks_name":"Mahiarpur",
    "ks:ks_type":"VILLAGE",
    "name:eng_x_preferred":[
        "Mahiarpur"
    ],
    "name:eng_x_variant":[
        "Mahi\u0101rpur"
    ],
    "wof:name":"Mahiarpur",
    "wof:placetype":"locality"
},
  "geometry": {"coordinates":[87.51977599999999,25.391833],"type":"Point"}
}