{
  "type": "Feature",
  "properties": {
    "iso:country":"IN",
    "ks:ks_name":"Yegarthachapalli",
    "ks:ks_pop":115,
    "ks:ks_type":"HABITATION",
    "name:eng_x_preferred":[
        "Yegarthachapalli"
    ],
    "wof:name":"Yegarthachapalli",
    "wof:placetype":"locality",
    "wof:population":115
},
  "geometry": {"coordinates":[82.517786,18.009396],"type":"Point"}
}