{
  "type": "Feature",
  "properties": {
    "iso:country":"IN",
    "ks:ks_name":"Baigundi",
    "ks:ks_pop":404,
    "ks:ks_type":"VILLAGE",
    "name:eng_x_preferred":[
        "Baigundi"
    ],
    "wof:name":"Baigundi",
    "wof:placetype":"locality",
    "wof:population":404
},
  "geometry": {"coordinates":[86.02291700000001,21.461868],"type":"Point"}
}