{
  "type": "Feature",
  "properties": {
    "iso:country":"IN",
    "ks:ks_name":"Kamipadar",
    "ks:ks_pop":424,
    "ks:ks_type":"HABITATION",
    "name:eng_x_preferred":[
        "Kamipadar"
    ],
    "wof:name":"Kamipadar",
    "wof:placetype":"locality",
    "wof:population":424
},
  "geometry": {"coordinates":[83.129316,18.92429],"type":"Point"}
}