{
  "type": "Feature",
  "properties": {
    "gn:admin1_code":"10.0",
    "gn:admin2_code":"71.0",
    "gn:asciiname":"Shadipur",
    "gn:country_code":"IN",
    "gn:dem":270,
    "gn:feature_class":"P",
    "gn:feature_code":"PPL",
    "gn:name":"Sh\u0101d\u012bpur",
    "gn:population":0,
    "gn:timezone":"Asia/Kolkata",
    "iso:country":"IN",
    "name:mal_x_preferred":[
        "\u0d36\u0d3e\u0d26\u0d3f\u0d2a\u0d42\u0d7c"
    ],
    "name:pan_x_preferred":[
        "\u0a38\u0a3c\u0a3e\u0a26\u0a40\u0a2a\u0a41\u0a30"
    ],
    "wof:name":"Shadipur",
    "wof:placetype":"locality"
},
  "geometry": {"coordinates":[77.27972,30.09995],"type":"Point"}
}