{
  "type": "Feature",
  "properties": {
    "gn:admin1_code":"39.0",
    "gn:admin2_code":"66.0",
    "gn:asciiname":"Gangapur",
    "gn:country_code":"IN",
    "gn:dem":328,
    "gn:feature_class":"P",
    "gn:feature_code":"PPL",
    "gn:name":"Gangapur",
    "gn:population":0,
    "gn:timezone":"Asia/Kolkata",
    "iso:country":"IN",
    "name:bih_x_preferred":[
        "\u0917\u0902\u0917\u093e\u092a\u0941\u0930"
    ],
    "name:ceb_x_preferred":[
        "Gangapur"
    ],
    "name:hin_x_preferred":[
        "\u0917\u0902\u0917\u093e\u092a\u0941\u0930"
    ],
    "name:ita_x_preferred":[
        "Gangapur"
    ],
    "name:pol_x_preferred":[
        "Gangapur"
    ],
    "name:swe_x_preferred":[
        "Gangapur"
    ],
    "name:vie_x_preferred":[
        "Gangapur"
    ],
    "wof:name":"Gangapur",
    "wof:placetype":"locality"
},
  "geometry": {"coordinates":[79.60999,29.16116],"type":"Point"}
}