{
  "type": "Feature",
  "properties": {
    "gn:admin1_code":"36",
    "gn:admin2_code":"179.0",
    "gn:asciiname":"Bhagwatgarh",
    "gn:country_code":"IN",
    "gn:dem":101,
    "gn:feature_class":"P",
    "gn:feature_code":"PPL",
    "gn:name":"Bhagwatgarh",
    "gn:population":0,
    "gn:timezone":"Asia/Kolkata",
    "iso:country":"IN",
    "name:hin_x_preferred":[
        "\u092d\u0917\u0935\u0924\u0917\u0922\u093c"
    ],
    "wof:name":"Bhagwatgarh",
    "wof:placetype":"locality"
},
  "geometry": {"coordinates":[82.09739,26.19517],"type":"Point"}
}