{
  "type": "Feature",
  "properties": {
    "gn:admin1_code":"36.0",
    "gn:admin2_code":"185.0",
    "gn:asciiname":"Puraina",
    "gn:country_code":"IN",
    "gn:dem":91,
    "gn:feature_class":"P",
    "gn:feature_code":"PPL",
    "gn:name":"Puraina",
    "gn:population":0,
    "gn:timezone":"Asia/Kolkata",
    "iso:country":"IN",
    "name:ceb_x_preferred":[
        "Puraina"
    ],
    "name:mai_x_preferred":[
        "\u092a\u0941\u0930\u0948\u0928\u093e"
    ],
    "name:msa_x_preferred":[
        "Puraina"
    ],
    "name:nep_x_preferred":[
        "\u092a\u0941\u0930\u0948\u0928\u093e"
    ],
    "name:new_x_preferred":[
        "\u092a\u0941\u0930\u0948\u0928\u093e"
    ],
    "name:pol_x_preferred":[
        "Puraina"
    ],
    "wof:name":"Puraina",
    "wof:placetype":"locality"
},
  "geometry": {"coordinates":[82.73520000000001,27.0032],"type":"Point"}
}