{
  "type": "Feature",
  "properties": {
    "iso:country":"IN",
    "ks:ks_name":"Odiaguda",
    "ks:ks_pop":40,
    "ks:ks_type":"HABITATION",
    "name:eng_x_preferred":[
        "Odiaguda"
    ],
    "wof:name":"Odiaguda",
    "wof:placetype":"locality",
    "wof:population":40
},
  "geometry": {"coordinates":[82.194231,18.58988],"type":"Point"}
}