{
  "type": "Feature",
  "properties": {
    "iso:country":"IN",
    "ks:ks_name":"Madan Pur",
    "ks:ks_pop":1402,
    "ks:ks_type":"VILLAGE",
    "name:eng_x_preferred":[
        "Madan Pur"
    ],
    "wof:name":"Madan Pur",
    "wof:placetype":"locality",
    "wof:population":1402
},
  "geometry": {"coordinates":[86.678657,20.580596],"type":"Point"}
}