{
  "type": "Feature",
  "properties": {
    "iso:country":"IN",
    "ks:ks_name":"Darapada",
    "ks:ks_pop":147,
    "ks:ks_type":"HABITATION",
    "name:eng_x_preferred":[
        "Darapada"
    ],
    "wof:name":"Darapada",
    "wof:placetype":"locality",
    "wof:population":147
},
  "geometry": {"coordinates":[73.458415,20.686934],"type":"Point"}
}