{
  "type": "Feature",
  "properties": {
    "iso:country":"IN",
    "ks:ks_name":"Malidihi",
    "ks:ks_pop":67,
    "ks:ks_type":"HABITATION",
    "ks:ks_uagg_main":0,
    "name:eng_x_preferred":[
        "Malidihi"
    ],
    "wof:name":"Malidihi",
    "wof:placetype":"neighbourhood",
    "wof:population":67
},
  "geometry": {"coordinates":[84.372615,22.273082],"type":"Point"}
}