{
  "type": "Feature",
  "properties": {
    "gn:admin1_code":"19.0",
    "gn:admin2_code":"570.0",
    "gn:asciiname":"Attikodagi",
    "gn:country_code":"IN",
    "gn:dem":813,
    "gn:feature_class":"P",
    "gn:feature_code":"PPL",
    "gn:name":"Attikodagi",
    "gn:population":0,
    "gn:timezone":"Asia/Kolkata",
    "iso:country":"IN",
    "wof:name":"Attikodagi",
    "wof:placetype":"locality"
},
  "geometry": {"coordinates":[75.34498000000001,13.31852],"type":"Point"}
}