{
  "type": "Feature",
  "properties": {
    "iso:country":"IN",
    "ks:ks_name":"Sindhua",
    "ks:ks_pop":1001,
    "ks:ks_type":"VILLAGE",
    "name:eng_x_preferred":[
        "Sindhua"
    ],
    "wof:name":"Sindhua",
    "wof:placetype":"locality",
    "wof:population":1001
},
  "geometry": {"coordinates":[86.658372,21.389915],"type":"Point"}
}