{
  "type": "Feature",
  "properties": {
    "gn:admin1_code":"37",
    "gn:admin2_code":"409.0",
    "gn:asciiname":"Bhimpuri",
    "gn:country_code":"IN",
    "gn:dem":279,
    "gn:feature_class":"P",
    "gn:feature_code":"PPL",
    "gn:name":"Bh\u012bmpuri",
    "gn:population":0,
    "gn:timezone":"Asia/Kolkata",
    "iso:country":"IN",
    "ks:ks_alt_nam":"Bh\u012bmpuri",
    "ks:ks_name":"Bhimpuri",
    "ks:ks_pop":256,
    "ks:ks_type":"VILLAGE",
    "ks:ks_uagg_main":0,
    "name:eng_x_preferred":[
        "Bhimpuri"
    ],
    "name:eng_x_variant":[
        "Bh\u012bmpuri"
    ],
    "wof:name":"Bhimpuri",
    "wof:placetype":"neighbourhood",
    "wof:population":256
},
  "geometry": {"coordinates":[81.58080200000001,21.923323],"type":"Point"}
}