{
  "type": "Feature",
  "properties": {
    "gn:admin1_code":"36.0",
    "gn:admin2_code":"190.0",
    "gn:asciiname":"Bheri",
    "gn:country_code":"IN",
    "gn:dem":76,
    "gn:feature_class":"P",
    "gn:feature_code":"PPL",
    "gn:name":"Bheri",
    "gn:population":0,
    "gn:timezone":"Asia/Kolkata",
    "iso:country":"IN",
    "name:heb_x_preferred":[
        "\u05d1\u05d4\u05e8\u05d9"
    ],
    "name:hun_x_preferred":[
        "Bheri"
    ],
    "name:slk_x_preferred":[
        "Bheri"
    ],
    "wof:name":"Bheri",
    "wof:placetype":"locality"
},
  "geometry": {"coordinates":[83.50738,26.42386],"type":"Point"}
}