{
  "type": "Feature",
  "properties": {
    "gn:admin1_code":"37",
    "gn:admin2_code":"407.0",
    "gn:asciiname":"Tatakasa",
    "gn:country_code":"IN",
    "gn:dem":316,
    "gn:feature_class":"P",
    "gn:feature_code":"PPL",
    "gn:name":"T\u0101t\u0101kasa",
    "gn:population":0,
    "gn:timezone":"Asia/Kolkata",
    "iso:country":"IN",
    "ks:ks_alt_nam":"T\u0101t\u0101kasa",
    "ks:ks_name":"Tatakasa",
    "ks:ks_pop":566,
    "ks:ks_type":"VILLAGE",
    "ks:ks_uagg_main":0,
    "name:eng_x_preferred":[
        "Tatakasa"
    ],
    "name:eng_x_variant":[
        "T\u0101t\u0101kasa"
    ],
    "wof:name":"Tatakasa",
    "wof:placetype":"neighbourhood",
    "wof:population":566
},
  "geometry": {"coordinates":[81.459749,22.072413],"type":"Point"}
}