{
  "type": "Feature",
  "properties": {
    "gn:admin1_code":"24.0",
    "gn:admin2_code":"130.0",
    "gn:asciiname":"Gamri",
    "gn:country_code":"IN",
    "gn:dem":212,
    "gn:feature_class":"P",
    "gn:feature_code":"PPL",
    "gn:name":"G\u0101mri",
    "gn:population":0,
    "gn:timezone":"Asia/Kolkata",
    "iso:country":"IN",
    "ks:ks_alt_nam":"G\u0101mri",
    "ks:ks_name":"Gamri",
    "ks:ks_pop":195,
    "ks:ks_type":"VILLAGE",
    "name:eng_x_preferred":[
        "Gamri"
    ],
    "name:eng_x_variant":[
        "G\u0101mri"
    ],
    "wof:name":"Gamri",
    "wof:placetype":"locality",
    "wof:population":195
},
  "geometry": {"coordinates":[74.02424999999999,24.006245],"type":"Point"}
}