{
  "type": "Feature",
  "properties": {
    "gn:admin1_code":"24.0",
    "gn:admin2_code":"130.0",
    "gn:asciiname":"Gamri",
    "gn:country_code":"IN",
    "gn:dem":212,
    "gn:feature_class":"P",
    "gn:feature_code":"PPL",
    "gn:name":"G\u0101mri",
    "gn:population":0,
    "gn:timezone":"Asia/Kolkata",
    "iso:country":"IN",
    "wof:name":"Gamri",
    "wof:placetype":"locality"
},
  "geometry": {"coordinates":[74.02186999999998,24.00867],"type":"Point"}
}