{
  "type": "Feature",
  "properties": {
    "iso:country":"IN",
    "ks:ks_name":"Habrubari",
    "ks:ks_pop":573,
    "ks:ks_type":"HABITATION",
    "name:eng_x_preferred":[
        "Habrubari"
    ],
    "wof:name":"Habrubari",
    "wof:placetype":"locality",
    "wof:population":573
},
  "geometry": {"coordinates":[90.14349,26.525632],"type":"Point"}
}