{
  "type": "Feature",
  "properties": {
    "iso:country":"IN",
    "ks:ks_alt_nam":"Basa Rongphar gaon",
    "ks:ks_name":"Basa Rongphar Gaon",
    "ks:ks_pop":200,
    "ks:ks_type":"HABITATION",
    "ks:ks_uagg_main":0,
    "name:eng_x_preferred":[
        "Basa Rongphar Gaon"
    ],
    "wof:name":"Basa Rongphar Gaon",
    "wof:placetype":"neighbourhood",
    "wof:population":200
},
  "geometry": {"coordinates":[92.760496,25.942935],"type":"Point"}
}