{
  "type": "Feature",
  "properties": {
    "gn:admin1_code":"34.0",
    "gn:admin2_code":"221.0",
    "gn:asciiname":"Dasaut",
    "gn:country_code":"IN",
    "gn:dem":48,
    "gn:feature_class":"P",
    "gn:feature_code":"PPL",
    "gn:name":"Dasaut",
    "gn:population":0,
    "gn:timezone":"Asia/Kolkata",
    "iso:country":"IN",
    "ks:ks_name":"Dasaut",
    "ks:ks_pop":1138,
    "ks:ks_type":"VILLAGE",
    "ks:ks_uagg_main":0,
    "name:eng_x_preferred":[
        "Dasaut"
    ],
    "wof:name":"Dasaut",
    "wof:placetype":"neighbourhood",
    "wof:population":1138
},
  "geometry": {"coordinates":[86.095912,25.89886],"type":"Point"}
}