{
  "type": "Feature",
  "properties": {
    "iso:country":"IN",
    "ks:ks_name":"Dewan Chak",
    "ks:ks_pop":298,
    "ks:ks_type":"VILLAGE",
    "name:eng_x_preferred":[
        "Dewan Chak"
    ],
    "wof:name":"Dewan Chak",
    "wof:placetype":"locality",
    "wof:population":298
},
  "geometry": {"coordinates":[87.69153300000001,22.79554],"type":"Point"}
}