{
  "type": "Feature",
  "properties": {
    "iso:country":"IN",
    "ks:ks_name":"Bailbaru",
    "ks:ks_pop":30,
    "ks:ks_type":"HABITATION",
    "name:eng_x_preferred":[
        "Bailbaru"
    ],
    "wof:name":"Bailbaru",
    "wof:placetype":"locality",
    "wof:population":30
},
  "geometry": {"coordinates":[75.168498,13.488762],"type":"Point"}
}