{
  "type": "Feature",
  "properties": {
    "gn:admin1_code":"12.0",
    "gn:admin2_code":"22.0",
    "gn:asciiname":"Bajpur",
    "gn:country_code":"IN",
    "gn:dem":354,
    "gn:feature_class":"P",
    "gn:feature_code":"PPL",
    "gn:name":"Bajpur",
    "gn:population":0,
    "gn:timezone":"Asia/Kolkata",
    "iso:country":"IN",
    "name:bpy_x_preferred":[
        "\u09ac\u099c\u09aa\u09c1\u09b0"
    ],
    "name:hin_x_preferred":[
        "\u092c\u093e\u091c\u092a\u0941\u0930"
    ],
    "name:ita_x_preferred":[
        "Bajpur"
    ],
    "name:mlg_x_preferred":[
        "Bajpur"
    ],
    "name:msa_x_preferred":[
        "Bajpur"
    ],
    "name:new_x_preferred":[
        "\u092c\u091c\u092a\u0941\u0930"
    ],
    "name:nld_x_preferred":[
        "Bajpur"
    ],
    "name:ori_x_preferred":[
        "\u0b2c\u0b3e\u0b1c\u0b2a\u0b41\u0b30"
    ],
    "name:pol_x_preferred":[
        "Bajpur"
    ],
    "name:por_x_preferred":[
        "Bajpur"
    ],
    "name:vie_x_preferred":[
        "Bajpur"
    ],
    "name:zho_x_preferred":[
        "\u5df4\u6770\u666e\u5c14"
    ],
    "wof:name":"Bajpur",
    "wof:placetype":"locality"
},
  "geometry": {"coordinates":[75.02767,32.57193],"type":"Point"}
}