{
  "type": "Feature",
  "properties": {
    "iso:country":"IN",
    "ks:ks_alt_nam":"Khiriy\u0101khera",
    "ks:ks_name":"Khiriyakhera",
    "ks:ks_type":"VILLAGE",
    "name:eng_x_preferred":[
        "Khiriyakhera"
    ],
    "name:eng_x_variant":[
        "Khiriy\u0101khera"
    ],
    "wof:name":"Khiriyakhera",
    "wof:placetype":"locality"
},
  "geometry": {"coordinates":[77.936401,24.41819],"type":"Point"}
}