{
  "type": "Feature",
  "properties": {
    "iso:country":"IN",
    "ks:ks_name":"Teteleguri Natun 1",
    "ks:ks_pop":96,
    "ks:ks_type":"HABITATION",
    "name:eng_x_preferred":[
        "Teteleguri Natun 1"
    ],
    "wof:name":"Teteleguri Natun 1",
    "wof:placetype":"locality",
    "wof:population":96
},
  "geometry": {"coordinates":[93.17988699999999,26.099196],"type":"Point"}
}