{
  "type": "Feature",
  "properties": {
    "iso:country":"IN",
    "ks:ks_name":"Maharakarka",
    "ks:ks_pop":751,
    "ks:ks_type":"VILLAGE",
    "name:eng_x_preferred":[
        "Maharakarka"
    ],
    "wof:name":"Maharakarka",
    "wof:placetype":"locality",
    "wof:population":751
},
  "geometry": {"coordinates":[81.45609,18.665458],"type":"Point"}
}