{
  "type": "Feature",
  "properties": {
    "iso:country":"IN",
    "ks:ks_alt_nam":"nauan purwa",
    "ks:ks_name":"Nauan Purwa",
    "ks:ks_pop":50,
    "ks:ks_type":"HABITATION",
    "name:eng_x_preferred":[
        "Nauan Purwa"
    ],
    "wof:name":"Nauan Purwa",
    "wof:placetype":"locality",
    "wof:population":50
},
  "geometry": {"coordinates":[81.51093899999999,27.168173],"type":"Point"}
}