{
  "type": "Feature",
  "properties": {
    "iso:country":"IN",
    "ks:ks_alt_nam":"Sree bhuvavshtram",
    "ks:ks_name":"Sree Bhuvavshtram",
    "ks:ks_pop":320,
    "ks:ks_type":"HABITATION",
    "name:eng_x_preferred":[
        "Sree Bhuvavshtram"
    ],
    "wof:name":"Sree Bhuvavshtram",
    "wof:placetype":"locality",
    "wof:population":320
},
  "geometry": {"coordinates":[76.860028,8.891298],"type":"Point"}
}