{
  "type": "Feature",
  "properties": {
    "gn:admin1_code":"11",
    "gn:admin2_code":"24.0",
    "gn:asciiname":"Kohli",
    "gn:country_code":"IN",
    "gn:dem":420,
    "gn:feature_class":"P",
    "gn:feature_code":"PPL",
    "gn:name":"Kohli",
    "gn:population":0,
    "gn:timezone":"Asia/Kolkata",
    "iso:country":"IN",
    "name:hin_x_preferred":[
        "\u0915\u094b\u0939\u0932\u0940"
    ],
    "wof:name":"Kohli",
    "wof:placetype":"locality"
},
  "geometry": {"coordinates":[76.15864000000001,31.94308],"type":"Point"}
}