{
  "type": "Feature",
  "properties": {
    "gn:admin1_code":"35",
    "gn:admin2_code":"442.0",
    "gn:asciiname":"Nihal",
    "gn:country_code":"IN",
    "gn:dem":429,
    "gn:feature_class":"P",
    "gn:feature_code":"PPL",
    "gn:name":"Nih\u0101l",
    "gn:population":0,
    "gn:timezone":"Asia/Kolkata",
    "iso:country":"IN",
    "wof:name":"Nihal",
    "wof:placetype":"locality"
},
  "geometry": {"coordinates":[76.44049,23.55756],"type":"Point"}
}