{
  "type": "Feature",
  "properties": {
    "iso:country":"IN",
    "ks:ks_alt_nam":"SemerwaKhasPara",
    "ks:ks_name":"Semerwakhaspara",
    "ks:ks_pop":607,
    "ks:ks_type":"HABITATION",
    "name:eng_x_preferred":[
        "Semerwakhaspara"
    ],
    "wof:name":"Semerwakhaspara",
    "wof:placetype":"locality",
    "wof:population":607
},
  "geometry": {"coordinates":[83.374264,24.083353],"type":"Point"}
}