{
  "type": "Feature",
  "properties": {
    "gn:admin1_code":"16.0",
    "gn:admin2_code":"497.0",
    "gn:asciiname":"Bhavar",
    "gn:country_code":"IN",
    "gn:dem":129,
    "gn:feature_class":"P",
    "gn:feature_code":"PPL",
    "gn:name":"Bhavar",
    "gn:population":0,
    "gn:timezone":"Asia/Kolkata",
    "iso:country":"IN",
    "name:und_x_variant":[
        "Digar"
    ],
    "wof:name":"Bhavar",
    "wof:placetype":"locality"
},
  "geometry": {"coordinates":[74.18816,21.57232],"type":"Point"}
}