{
  "type": "Feature",
  "properties": {
    "iso:country":"IN",
    "ks:ks_name":"Hirijingi",
    "ks:ks_pop":166,
    "ks:ks_type":"VILLAGE",
    "name:eng_x_preferred":[
        "Hirijingi"
    ],
    "wof:name":"Hirijingi",
    "wof:placetype":"locality",
    "wof:population":166
},
  "geometry": {"coordinates":[83.945767,19.235842],"type":"Point"}
}