{
  "type": "Feature",
  "properties": {
    "gn:admin1_code":"35",
    "gn:admin2_code":"453.0",
    "gn:asciiname":"Andhiyarkho",
    "gn:country_code":"IN",
    "gn:dem":655,
    "gn:feature_class":"P",
    "gn:feature_code":"PPL",
    "gn:name":"Andhiy\u0101rkho",
    "gn:population":0,
    "gn:timezone":"Asia/Kolkata",
    "iso:country":"IN",
    "wof:name":"Andhiyarkho",
    "wof:placetype":"locality"
},
  "geometry": {"coordinates":[81.00610999999998,22.61156],"type":"Point"}
}