{
  "type": "Feature",
  "properties": {
    "gn:admin1_code":"24.0",
    "gn:admin2_code":"128.0",
    "gn:asciiname":"Digoda",
    "gn:country_code":"IN",
    "gn:dem":326,
    "gn:feature_class":"P",
    "gn:feature_code":"PPL",
    "gn:name":"D\u012bgoda",
    "gn:population":0,
    "gn:timezone":"Asia/Kolkata",
    "iso:country":"IN",
    "ks:ks_alt_nam":"D\u012bgoda",
    "ks:ks_name":"Digoda",
    "ks:ks_type":"VILLAGE",
    "name:eng_x_preferred":[
        "Digoda"
    ],
    "name:eng_x_variant":[
        "D\u012bgoda"
    ],
    "wof:name":"Digoda",
    "wof:placetype":"locality"
},
  "geometry": {"coordinates":[76.850937,25.18386],"type":"Point"}
}