{
  "type": "Feature",
  "properties": {
    "iso:country":"IN",
    "ks:ks_alt_nam":"RUP KUMAR PARA",
    "ks:ks_name":"Rup Kumar Para",
    "ks:ks_pop":259,
    "ks:ks_type":"HABITATION",
    "ks:ks_uagg_main":0,
    "name:eng_x_preferred":[
        "Rup Kumar Para"
    ],
    "wof:name":"Rup Kumar Para",
    "wof:placetype":"neighbourhood",
    "wof:population":259
},
  "geometry": {"coordinates":[91.26784600000001,23.567767],"type":"Point"}
}