{
  "type": "Feature",
  "properties": {
    "gn:admin1_code":"11",
    "gn:admin2_code":"23.0",
    "gn:asciiname":"Sanda",
    "gn:country_code":"IN",
    "gn:dem":829,
    "gn:feature_class":"P",
    "gn:feature_code":"PPL",
    "gn:name":"Sanda",
    "gn:population":0,
    "gn:timezone":"Asia/Kolkata",
    "iso:country":"IN",
    "name:bul_x_preferred":[
        "\u0421\u0430\u043d\u0434\u0430"
    ],
    "name:ceb_x_preferred":[
        "Sanda"
    ],
    "name:deu_x_preferred":[
        "Sanda"
    ],
    "name:fra_x_preferred":[
        "Sanda"
    ],
    "name:hin_x_preferred":[
        "\u0938\u093e\u0902\u0921\u093e"
    ],
    "name:jpn_x_preferred":[
        "\u30b5\u30f3\u30c0"
    ],
    "name:nld_x_preferred":[
        "Sanda"
    ],
    "name:pol_x_preferred":[
        "Sanda"
    ],
    "name:por_x_preferred":[
        "Sanda"
    ],
    "name:ron_x_preferred":[
        "Sanda"
    ],
    "name:rus_x_preferred":[
        "\u0421\u0430\u043d\u0434\u0430"
    ],
    "name:swe_x_preferred":[
        "Sanda"
    ],
    "wof:name":"Sanda",
    "wof:placetype":"neighbourhood"
},
  "geometry": {"coordinates":[76.11418999999999,32.56433],"type":"Point"}
}