{
  "type": "Feature",
  "properties": {
    "iso:country":"IN",
    "ks:ks_name":"Bangadabettu",
    "ks:ks_pop":279,
    "ks:ks_type":"HABITATION",
    "name:eng_x_preferred":[
        "Bangadabettu"
    ],
    "wof:name":"Bangadabettu",
    "wof:placetype":"locality",
    "wof:population":279
},
  "geometry": {"coordinates":[74.96449,13.045403],"type":"Point"}
}