{
  "type": "Feature",
  "properties": {
    "iso:country":"IN",
    "ks:ks_alt_nam":"Nayki wad",
    "ks:ks_name":"Nayki Wad",
    "ks:ks_pop":237,
    "ks:ks_type":"HABITATION",
    "name:eng_x_preferred":[
        "Nayki Wad"
    ],
    "wof:name":"Nayki Wad",
    "wof:placetype":"locality",
    "wof:population":237
},
  "geometry": {"coordinates":[73.268806,20.499694],"type":"Point"}
}