{
  "type": "Feature",
  "properties": {
    "iso:country":"IN",
    "ks:ks_name":"Shiruchak",
    "ks:ks_pop":169,
    "ks:ks_type":"VILLAGE",
    "name:eng_x_preferred":[
        "Shiruchak"
    ],
    "wof:name":"Shiruchak",
    "wof:placetype":"locality",
    "wof:population":169
},
  "geometry": {"coordinates":[87.446032,21.987418],"type":"Point"}
}