{
  "type": "Feature",
  "properties": {
    "iso:country":"IN",
    "ks:ks_name":"Hatimuria Gaon",
    "ks:ks_pop":513,
    "ks:ks_type":"HABITATION",
    "name:eng_x_preferred":[
        "Hatimuria Gaon"
    ],
    "wof:name":"Hatimuria Gaon",
    "wof:placetype":"locality",
    "wof:population":513
},
  "geometry": {"coordinates":[94.70337000000001,26.959825],"type":"Point"}
}