{
  "type": "Feature",
  "properties": {
    "iso:country":"IN",
    "ks:ks_name":"Sisha East Tola",
    "ks:ks_pop":37,
    "ks:ks_type":"HABITATION",
    "ks:ks_uagg_main":0,
    "name:eng_x_preferred":[
        "Sisha East Tola"
    ],
    "wof:name":"Sisha East Tola",
    "wof:placetype":"neighbourhood",
    "wof:population":37
},
  "geometry": {"coordinates":[86.913724,25.80328],"type":"Point"}
}