{
  "type": "Feature",
  "properties": {
    "iso:country":"IN",
    "ks:ks_name":"Sastrirai Para",
    "ks:ks_pop":179,
    "ks:ks_type":"HABITATION",
    "name:eng_x_preferred":[
        "Sastrirai Para"
    ],
    "wof:name":"Sastrirai Para",
    "wof:placetype":"locality",
    "wof:population":179
},
  "geometry": {"coordinates":[91.664788,23.544758],"type":"Point"}
}