{
  "type": "Feature",
  "properties": {
    "iso:country":"IN",
    "ks:ks_name":"Badambeeru",
    "ks:ks_pop":168,
    "ks:ks_type":"HABITATION",
    "name:eng_x_preferred":[
        "Badambeeru"
    ],
    "wof:name":"Badambeeru",
    "wof:placetype":"locality",
    "wof:population":168
},
  "geometry": {"coordinates":[82.479336,18.309771],"type":"Point"}
}