{
  "type": "Feature",
  "properties": {
    "gn:admin1_code":"34.0",
    "gn:admin2_code":"216.0",
    "gn:asciiname":"Balthi Narsingh",
    "gn:country_code":"IN",
    "gn:dem":63,
    "gn:feature_class":"P",
    "gn:feature_code":"PPL",
    "gn:name":"Balthi Narsingh",
    "gn:population":0,
    "gn:timezone":"Asia/Kolkata",
    "iso:country":"IN",
    "ks:ks_name":"Balthi Narsingh",
    "ks:ks_pop":570,
    "ks:ks_type":"VILLAGE",
    "ks:ks_uagg_main":0,
    "name:eng_x_preferred":[
        "Balthi Narsingh"
    ],
    "wof:name":"Balthi Narsingh",
    "wof:placetype":"neighbourhood",
    "wof:population":570
},
  "geometry": {"coordinates":[85.00073399999999,26.296306],"type":"Point"}
}