{
  "type": "Feature",
  "properties": {
    "gn:admin1_code":"38",
    "gn:admin2_code":"369.0",
    "gn:asciiname":"Matkumbera",
    "gn:country_code":"IN",
    "gn:dem":183,
    "gn:feature_class":"P",
    "gn:feature_code":"PPL",
    "gn:name":"Matkumbera",
    "gn:population":0,
    "gn:timezone":"Asia/Kolkata",
    "iso:country":"IN",
    "wof:name":"Matkumbera",
    "wof:placetype":"locality"
},
  "geometry": {"coordinates":[86.11060999999999,22.67271],"type":"Point"}
}