{
  "type": "Feature",
  "properties": {
    "gn:admin1_code":"35",
    "gn:admin2_code":"429.0",
    "gn:asciiname":"Bhadra",
    "gn:country_code":"IN",
    "gn:dem":334,
    "gn:feature_class":"P",
    "gn:feature_code":"PPL",
    "gn:name":"Bhadra",
    "gn:population":0,
    "gn:timezone":"Asia/Kolkata",
    "iso:country":"IN",
    "name:mal_x_preferred":[
        "\u0d2d\u0d26\u0d4d\u0d30"
    ],
    "name:pan_x_preferred":[
        "\u0a2d\u0a26\u0a30"
    ],
    "wof:name":"Bhadra",
    "wof:placetype":"locality"
},
  "geometry": {"coordinates":[81.17085,24.36229],"type":"Point"}
}