{
  "type": "Feature",
  "properties": {
    "iso:country":"IN",
    "ks:ks_name":"Kantini",
    "ks:ks_pop":339,
    "ks:ks_type":"HABITATION",
    "name:eng_x_preferred":[
        "Kantini"
    ],
    "wof:name":"Kantini",
    "wof:placetype":"locality",
    "wof:population":339
},
  "geometry": {"coordinates":[85.618314,21.222364],"type":"Point"}
}