{
  "type": "Feature",
  "properties": {
    "iso:country":"IN",
    "ks:ks_name":"Purunahat",
    "ks:ks_pop":711,
    "ks:ks_type":"VILLAGE",
    "ks:ks_uagg_main":0,
    "name:eng_x_preferred":[
        "Purunahat"
    ],
    "wof:name":"Purunahat",
    "wof:placetype":"neighbourhood",
    "wof:population":711
},
  "geometry": {"coordinates":[86.111379,20.431181],"type":"Point"}
}