{
  "type": "Feature",
  "properties": {
    "gn:admin1_code":"25.0",
    "gn:admin2_code":"622.0",
    "gn:asciiname":"Puduvayal",
    "gn:country_code":"IN",
    "gn:dem":81,
    "gn:feature_class":"P",
    "gn:feature_code":"PPL",
    "gn:name":"Puduvayal",
    "gn:population":0,
    "gn:timezone":"Asia/Kolkata",
    "iso:country":"IN",
    "name:bpy_x_preferred":[
        "\u09aa\u09c1\u09a1\u09bc\u09c1\u09ac\u09be\u09af\u09bc\u09be\u09b2"
    ],
    "name:ita_x_preferred":[
        "Puduvayal"
    ],
    "name:msa_x_preferred":[
        "Puduvayal"
    ],
    "name:nld_x_preferred":[
        "Puduvayal"
    ],
    "name:tam_x_preferred":[
        "\u0baa\u0bc1\u0ba4\u0bc1\u0bb5\u0baf\u0bb2\u0bcd"
    ],
    "name:vie_x_preferred":[
        "Puduvayal"
    ],
    "name:zho_x_preferred":[
        "\u666e\u675c\u74e6\u8036\u5c14"
    ],
    "wof:name":"Puduvayal",
    "wof:placetype":"locality"
},
  "geometry": {"coordinates":[78.84624000000002,10.10338],"type":"Point"}
}