{
  "type": "Feature",
  "properties": {
    "gn:admin1_code":"25.0",
    "gn:admin2_code":"622.0",
    "gn:asciiname":"Puduvayal",
    "gn:country_code":"IN",
    "gn:dem":81,
    "gn:feature_class":"P",
    "gn:feature_code":"PPL",
    "gn:name":"Puduvayal",
    "gn:population":0,
    "gn:timezone":"Asia/Kolkata",
    "iso:country":"IN",
    "wof:name":"Puduvayal",
    "wof:placetype":"locality"
},
  "geometry": {"coordinates":[78.84624000000002,10.10338],"type":"Point"}
}