{
  "type": "Feature",
  "properties": {
    "gn:admin1_code":"16.0",
    "gn:admin2_code":"523",
    "gn:asciiname":"Khokarmoho",
    "gn:country_code":"IN",
    "gn:dem":557,
    "gn:feature_class":"P",
    "gn:feature_code":"PPL",
    "gn:name":"Khokarmoho",
    "gn:population":0,
    "gn:timezone":"Asia/Kolkata",
    "iso:country":"IN",
    "wof:name":"Khokarmoho",
    "wof:placetype":"locality"
},
  "geometry": {"coordinates":[75.55755000000001,18.99861],"type":"Point"}
}