{
  "type": "Feature",
  "properties": {
    "iso:country":"IN",
    "ks:ks_name":"P. Chhit",
    "ks:ks_pop":426,
    "ks:ks_type":"HABITATION",
    "name:eng_x_preferred":[
        "P. Chhit"
    ],
    "wof:name":"P. Chhit",
    "wof:placetype":"locality",
    "wof:population":426
},
  "geometry": {"coordinates":[81.15251000000001,26.126179],"type":"Point"}
}