{
  "type": "Feature",
  "properties": {
    "gn:admin1_code":"35",
    "gn:admin2_code":"443.0",
    "gn:asciiname":"Kundalpur",
    "gn:country_code":"IN",
    "gn:dem":518,
    "gn:feature_class":"P",
    "gn:feature_code":"PPL",
    "gn:name":"Kundalpur",
    "gn:population":0,
    "gn:timezone":"Asia/Kolkata",
    "iso:country":"IN",
    "name:deu_x_preferred":[
        "Kundalpur"
    ],
    "name:hin_x_preferred":[
        "\u0915\u0941\u0923\u094d\u0921\u0932\u092a\u0941\u0930"
    ],
    "name:ori_x_preferred":[
        "\u0b15\u0b41\u0b23\u0b4d\u0b21\u0b33 \u0b2a\u0b41\u0b30"
    ],
    "wof:name":"Kundalpur",
    "wof:placetype":"locality"
},
  "geometry": {"coordinates":[77.42841999999997,24.22248],"type":"Point"}
}