{
  "type": "Feature",
  "properties": {
    "gn:admin1_code":"21.0",
    "gn:admin2_code":"399.0",
    "gn:asciiname":"Tulaguram",
    "gn:country_code":"IN",
    "gn:dem":548,
    "gn:feature_class":"P",
    "gn:feature_code":"PPL",
    "gn:name":"Tulaguram",
    "gn:population":0,
    "gn:timezone":"Asia/Kolkata",
    "iso:country":"IN",
    "ks:ks_name":"Tulaguram",
    "ks:ks_type":"VILLAGE",
    "name:eng_x_preferred":[
        "Tulaguram"
    ],
    "wof:name":"Tulaguram",
    "wof:placetype":"locality"
},
  "geometry": {"coordinates":[82.304081,18.489128],"type":"Point"}
}