{
  "type": "Feature",
  "properties": {
    "iso:country":"IN",
    "ks:ks_name":"Panchathi",
    "ks:ks_pop":152,
    "ks:ks_type":"HABITATION",
    "name:eng_x_preferred":[
        "Panchathi"
    ],
    "wof:name":"Panchathi",
    "wof:placetype":"locality",
    "wof:population":152
},
  "geometry": {"coordinates":[78.736237,9.65485],"type":"Point"}
}