{
  "type": "Feature",
  "properties": {
    "gn:admin1_code":"3.0",
    "gn:admin2_code":"319.0",
    "gn:asciiname":"Bhatipara",
    "gn:country_code":"IN",
    "gn:dem":52,
    "gn:feature_class":"P",
    "gn:feature_code":"PPL",
    "gn:name":"Bh\u0101tip\u0101ra",
    "gn:population":0,
    "gn:timezone":"Asia/Kolkata",
    "iso:country":"IN",
    "wof:name":"Bhatipara",
    "wof:placetype":"neighbourhood"
},
  "geometry": {"coordinates":[90.81632999999999,26.45347],"type":"Point"}
}