{
  "type": "Feature",
  "properties": {
    "gn:admin1_code":"25.0",
    "gn:admin2_code":"616.0",
    "gn:asciiname":"Silambur",
    "gn:country_code":"IN",
    "gn:dem":79,
    "gn:feature_class":"P",
    "gn:feature_code":"PPL",
    "gn:name":"Silamb\u016br",
    "gn:population":0,
    "gn:timezone":"Asia/Kolkata",
    "iso:country":"IN",
    "ks:ks_name":"Silambur",
    "ks:ks_pop":1480,
    "ks:ks_type":"HABITATION",
    "name:eng_x_preferred":[
        "Silambur"
    ],
    "wof:name":"Silambur",
    "wof:placetype":"locality",
    "wof:population":1480
},
  "geometry": {"coordinates":[79.311556,11.347948],"type":"Point"}
}