{
  "type": "Feature",
  "properties": {
    "iso:country":"IN",
    "ks:ks_alt_nam":"CHIKUPARA",
    "ks:ks_name":"Chikupara",
    "ks:ks_pop":823,
    "ks:ks_type":"HABITATION",
    "name:eng_x_preferred":[
        "Chikupara"
    ],
    "wof:name":"Chikupara",
    "wof:placetype":"locality",
    "wof:population":823
},
  "geometry": {"coordinates":[88.553774,26.568452],"type":"Point"}
}