{
  "type": "Feature",
  "properties": {
    "iso:country":"IN",
    "ks:ks_name":"Chadiya",
    "ks:ks_pop":620,
    "ks:ks_type":"VILLAGE",
    "name:eng_x_preferred":[
        "Chadiya"
    ],
    "wof:name":"Chadiya",
    "wof:placetype":"locality",
    "wof:population":620
},
  "geometry": {"coordinates":[84.085589,22.966667],"type":"Point"}
}