{
  "type": "Feature",
  "properties": {
    "gn:admin1_code":"35",
    "gn:admin2_code":"448.0",
    "gn:asciiname":"Junapani",
    "gn:country_code":"IN",
    "gn:dem":536,
    "gn:feature_class":"P",
    "gn:feature_code":"PPL",
    "gn:name":"Jun\u0101p\u0101ni",
    "gn:population":0,
    "gn:timezone":"Asia/Kolkata",
    "iso:country":"IN",
    "ks:ks_name":"Junapani",
    "ks:ks_pop":484,
    "ks:ks_type":"HABITATION",
    "name:eng_x_preferred":[
        "Junapani"
    ],
    "wof:name":"Junapani",
    "wof:placetype":"locality",
    "wof:population":484
},
  "geometry": {"coordinates":[77.28851,21.977585],"type":"Point"}
}