{
  "type": "Feature",
  "properties": {
    "gn:admin1_code":"38.0",
    "gn:admin2_code":"347.0",
    "gn:asciiname":"Dumi",
    "gn:country_code":"IN",
    "gn:dem":486,
    "gn:feature_class":"P",
    "gn:feature_code":"PPL",
    "gn:name":"Dumi",
    "gn:population":0,
    "gn:timezone":"Asia/Kolkata",
    "iso:country":"IN",
    "ks:ks_name":"Dumi",
    "ks:ks_pop":536,
    "ks:ks_type":"VILLAGE",
    "ks:ks_uagg_main":0,
    "name:bih_x_preferred":[
        "\u091a\u094c\u0930\u092a\u093e\u091f\u0940"
    ],
    "name:ceb_x_preferred":[
        "Dumkibas"
    ],
    "name:eng_x_preferred":[
        "Dumi"
    ],
    "name:fra_x_preferred":[
        "Duni"
    ],
    "name:hin_x_preferred":[
        "\u0926\u0941\u0928\u0940"
    ],
    "name:mai_x_preferred":[
        "\u0926\u0941\u0928\u0940"
    ],
    "name:msa_x_preferred":[
        "Dumi"
    ],
    "name:nep_x_preferred":[
        "\u0926\u0941\u0928\u0940"
    ],
    "name:new_x_preferred":[
        "\u0926\u0941\u0928\u0940"
    ],
    "name:pol_x_preferred":[
        "Dumkibas"
    ],
    "wof:name":"Dumi",
    "wof:placetype":"neighbourhood",
    "wof:population":536
},
  "geometry": {"coordinates":[85.055981,24.109936],"type":"Point"}
}