{
  "type": "Feature",
  "properties": {
    "iso:country":"IN",
    "ks:ks_name":"Kharkhoti",
    "ks:ks_pop":939,
    "ks:ks_type":"VILLAGE",
    "name:eng_x_preferred":[
        "Kharkhoti"
    ],
    "wof:name":"Kharkhoti",
    "wof:placetype":"locality",
    "wof:population":939
},
  "geometry": {"coordinates":[74.56331400000001,23.657354],"type":"Point"}
}