{
  "type": "Feature",
  "properties": {
    "gn:admin1_code":"36",
    "gn:admin2_code":"175.0",
    "gn:asciiname":"Suara",
    "gn:country_code":"IN",
    "gn:dem":94,
    "gn:feature_class":"P",
    "gn:feature_code":"PPL",
    "gn:name":"Suara",
    "gn:population":0,
    "gn:timezone":"Asia/Kolkata",
    "iso:country":"IN",
    "name:bar_x_preferred":[
        "Suara"
    ],
    "name:dan_x_preferred":[
        "Suara"
    ],
    "name:fra_x_preferred":[
        "Suara"
    ],
    "name:hun_x_preferred":[
        "Suara"
    ],
    "name:ind_x_preferred":[
        "Suara"
    ],
    "name:ita_x_preferred":[
        "Suara"
    ],
    "name:jpn_x_preferred":[
        "Suara"
    ],
    "name:kor_x_preferred":[
        "Suara"
    ],
    "name:tgl_x_preferred":[
        "Suara"
    ],
    "name:zho_x_preferred":[
        "Suara"
    ],
    "wof:name":"Suara",
    "wof:placetype":"locality"
},
  "geometry": {"coordinates":[82.25448,25.29188],"type":"Point"}
}