{
  "type": "Feature",
  "properties": {
    "iso:country":"IN",
    "ks:ks_name":"Nakatikhar",
    "ks:ks_pop":909,
    "ks:ks_type":"HABITATION",
    "ks:ks_uagg_main":1,
    "name:eng_x_preferred":[
        "Nakatikhar"
    ],
    "wof:name":"Nakatikhar",
    "wof:placetype":"neighbourhood",
    "wof:population":909
},
  "geometry": {"coordinates":[82.77194299999999,22.343767],"type":"Point"}
}