{
  "type": "Feature",
  "properties": {
    "gn:admin1_code":"36.0",
    "gn:admin2_code":"136.0",
    "gn:asciiname":"Malpur",
    "gn:country_code":"IN",
    "gn:dem":185,
    "gn:feature_class":"P",
    "gn:feature_code":"PPL",
    "gn:name":"Malpur",
    "gn:population":0,
    "gn:timezone":"Asia/Kolkata",
    "iso:country":"IN",
    "name:bpy_x_preferred":[
        "\u09ae\u09be\u09b2\u09aa\u09c1\u09b0"
    ],
    "name:ceb_x_preferred":[
        "M\u0101lpur"
    ],
    "name:guj_x_preferred":[
        "\u0aae\u0abe\u0ab2\u0aaa\u0ac1\u0ab0"
    ],
    "name:ita_x_preferred":[
        "Malpur"
    ],
    "name:mlg_x_preferred":[
        "Malpur"
    ],
    "name:msa_x_preferred":[
        "Malpur"
    ],
    "name:new_x_preferred":[
        "\u092e\u0932\u094d\u092a\u0941\u0930"
    ],
    "name:nld_x_preferred":[
        "Malpur"
    ],
    "name:swe_x_preferred":[
        "M\u0101lpur"
    ],
    "name:vie_x_preferred":[
        "Malpur"
    ],
    "name:zho_x_preferred":[
        "\u9a6c\u5c14\u666e\u5c14"
    ],
    "wof:name":"Malpur",
    "wof:placetype":"locality"
},
  "geometry": {"coordinates":[78.99949000000002,28.49819],"type":"Point"}
}