{
  "type": "Feature",
  "properties": {
    "iso:country":"IN",
    "ks:ks_name":"Tola Tatidah",
    "ks:ks_pop":0,
    "ks:ks_type":"VILLAGE",
    "name:eng_x_preferred":[
        "Tola Tatidah"
    ],
    "wof:name":"Tola Tatidah",
    "wof:placetype":"locality",
    "wof:population":0
},
  "geometry": {"coordinates":[86.800156,24.67206],"type":"Point"}
}