{
  "type": "Feature",
  "properties": {
    "iso:country":"IN",
    "ks:ks_alt_nam":"AMALI FALAN",
    "ks:ks_name":"Amali Falan",
    "ks:ks_pop":386,
    "ks:ks_type":"HABITATION",
    "name:eng_x_preferred":[
        "Amali Falan"
    ],
    "wof:name":"Amali Falan",
    "wof:placetype":"locality",
    "wof:population":386
},
  "geometry": {"coordinates":[74.851603,24.189586],"type":"Point"}
}