{
  "type": "Feature",
  "properties": {
    "iso:country":"IN",
    "ks:ks_alt_nam":"PATIL-BARWE WASTI",
    "ks:ks_name":"Patil-barwe Wasti",
    "ks:ks_pop":166,
    "ks:ks_type":"HABITATION",
    "name:eng_x_preferred":[
        "Patil-barwe Wasti"
    ],
    "wof:name":"Patil-barwe Wasti",
    "wof:placetype":"locality",
    "wof:population":166
},
  "geometry": {"coordinates":[75.02195,19.28152],"type":"Point"}
}