{
  "type": "Feature",
  "properties": {
    "iso:country":"IN",
    "ks:ks_alt_nam":"SARFRAJ BIGHA",
    "ks:ks_name":"Sarfraj Bigha",
    "ks:ks_pop":85,
    "ks:ks_type":"HABITATION",
    "name:eng_x_preferred":[
        "Sarfraj Bigha"
    ],
    "wof:name":"Sarfraj Bigha",
    "wof:placetype":"locality",
    "wof:population":85
},
  "geometry": {"coordinates":[84.85854500000001,25.03618],"type":"Point"}
}