{
  "type": "Feature",
  "properties": {
    "gn:admin1_code":"36.0",
    "gn:admin2_code":"151.0",
    "gn:asciiname":"Nagra Taluka Musapur",
    "gn:country_code":"IN",
    "gn:dem":182,
    "gn:feature_class":"P",
    "gn:feature_code":"PPL",
    "gn:name":"Nagra T\u0101luka M\u016bs\u0101pur",
    "gn:population":0,
    "gn:timezone":"Asia/Kolkata",
    "iso:country":"IN",
    "wof:name":"Nagra Taluka Musapur",
    "wof:placetype":"locality"
},
  "geometry": {"coordinates":[79.89743,28.48145],"type":"Point"}
}