{
  "type": "Feature",
  "properties": {
    "iso:country":"IN",
    "ks:ks_name":"Khetupada",
    "ks:ks_pop":248,
    "ks:ks_type":"VILLAGE",
    "name:eng_x_preferred":[
        "Khetupada"
    ],
    "wof:name":"Khetupada",
    "wof:placetype":"locality",
    "wof:population":248
},
  "geometry": {"coordinates":[83.366784,20.199355],"type":"Point"}
}