{
  "type": "Feature",
  "properties": {
    "iso:country":"IN",
    "ks:ks_name":"Kal Chaura",
    "ks:ks_pop":500,
    "ks:ks_type":"VILLAGE",
    "name:eng_x_preferred":[
        "Kal Chaura"
    ],
    "wof:name":"Kal Chaura",
    "wof:placetype":"locality",
    "wof:population":500
},
  "geometry": {"coordinates":[80.02964,29.392591],"type":"Point"}
}