{
  "type": "Feature",
  "properties": {
    "iso:country":"IN",
    "ks:ks_name":"Palavagu Gumpu",
    "ks:ks_pop":66,
    "ks:ks_type":"HABITATION",
    "name:eng_x_preferred":[
        "Palavagu Gumpu"
    ],
    "wof:name":"Palavagu Gumpu",
    "wof:placetype":"locality",
    "wof:population":66
},
  "geometry": {"coordinates":[80.752742,17.741031],"type":"Point"}
}