{
  "type": "Feature",
  "properties": {
    "iso:country":"IN",
    "ks:ks_name":"Bhunar Gaon",
    "ks:ks_pop":79,
    "ks:ks_type":"VILLAGE",
    "name:eng_x_preferred":[
        "Bhunar Gaon"
    ],
    "wof:name":"Bhunar Gaon",
    "wof:placetype":"locality",
    "wof:population":79
},
  "geometry": {"coordinates":[78.05843,30.613076],"type":"Point"}
}