{
  "type": "Feature",
  "properties": {
    "gn:admin1_code":"36.0",
    "gn:admin2_code":"189.0",
    "gn:asciiname":"Pirpra Sobhmal",
    "gn:country_code":"IN",
    "gn:dem":84,
    "gn:feature_class":"P",
    "gn:feature_code":"PPL",
    "gn:name":"Pirpr\u0101 Sobhmal",
    "gn:population":0,
    "gn:timezone":"Asia/Kolkata",
    "iso:country":"IN",
    "wof:name":"Pirpra Sobhmal",
    "wof:placetype":"locality"
},
  "geometry": {"coordinates":[84.02766,26.86494],"type":"Point"}
}