{
  "type": "Feature",
  "properties": {
    "iso:country":"IN",
    "ks:ks_name":"Eatamanuguda",
    "ks:ks_pop":119,
    "ks:ks_type":"HABITATION",
    "name:eng_x_preferred":[
        "Eatamanuguda"
    ],
    "wof:name":"Eatamanuguda",
    "wof:placetype":"locality",
    "wof:population":119
},
  "geometry": {"coordinates":[83.797747,18.65533],"type":"Point"}
}