{
  "type": "Feature",
  "properties": {
    "iso:country":"IN",
    "ks:ks_name":"Sema",
    "ks:ks_pop":562,
    "ks:ks_type":"VILLAGE",
    "name:eng_x_preferred":[
        "Sema"
    ],
    "wof:name":"Sema",
    "wof:placetype":"locality",
    "wof:population":562
},
  "geometry": {"coordinates":[78.954376,30.351413],"type":"Point"}
}