{
  "type": "Feature",
  "properties": {
    "gn:admin1_code":"24",
    "gn:admin2_code":"115.0",
    "gn:asciiname":"Shiv",
    "gn:cc2":"IN",
    "gn:country_code":"IN",
    "gn:dem":231,
    "gn:feature_class":"P",
    "gn:feature_code":"PPL",
    "gn:name":"Shiv",
    "gn:population":0,
    "gn:timezone":"Asia/Kolkata",
    "iso:country":"IN",
    "name:tam_x_preferred":[
        "\u0b9a\u0bbf\u0baf\u0bca"
    ],
    "name:und_x_variant":[
        "Sheo",
        "Shiv"
    ],
    "wof:name":"Shiv",
    "wof:placetype":"neighbourhood"
},
  "geometry": {"coordinates":[71.24436,26.1911],"type":"Point"}
}