{
  "type": "Feature",
  "properties": {
    "iso:country":"IN",
    "ks:ks_name":"Devapur",
    "ks:ks_pop":498,
    "ks:ks_type":"HABITATION",
    "name:eng_x_preferred":[
        "Devapur"
    ],
    "wof:name":"Devapur",
    "wof:placetype":"locality",
    "wof:population":498
},
  "geometry": {"coordinates":[77.03898,17.016392],"type":"Point"}
}