{
  "type": "Feature",
  "properties": {
    "iso:country":"IN",
    "ks:ks_name":"Kulanthankattupudur",
    "ks:ks_pop":29,
    "ks:ks_type":"HABITATION",
    "name:eng_x_preferred":[
        "Kulanthankattupudur"
    ],
    "wof:name":"Kulanthankattupudur",
    "wof:placetype":"locality",
    "wof:population":29
},
  "geometry": {"coordinates":[77.80739,10.944079],"type":"Point"}
}