{
  "type": "Feature",
  "properties": {
    "iso:country":"IN",
    "ks:ks_name":"Mundali",
    "ks:ks_pop":155,
    "ks:ks_type":"VILLAGE",
    "ks:ks_uagg_main":0,
    "name:eng_x_preferred":[
        "Mundali"
    ],
    "wof:name":"Mundali",
    "wof:placetype":"neighbourhood",
    "wof:population":155
},
  "geometry": {"coordinates":[86.635807,22.232619],"type":"Point"}
}