{
  "type": "Feature",
  "properties": {
    "iso:country":"IN",
    "ks:ks_name":"Bajai",
    "ks:ks_pop":44,
    "ks:ks_type":"HABITATION",
    "name:eng_x_preferred":[
        "Bajai"
    ],
    "wof:name":"Bajai",
    "wof:placetype":"locality",
    "wof:population":44
},
  "geometry": {"coordinates":[79.685677,30.01471],"type":"Point"}
}