{
  "type": "Feature",
  "properties": {
    "iso:country":"IN",
    "ks:ks_name":"Humid",
    "ks:ks_pop":859,
    "ks:ks_type":"VILLAGE",
    "name:eng_x_preferred":[
        "Humid"
    ],
    "wof:name":"Humid",
    "wof:placetype":"locality",
    "wof:population":859
},
  "geometry": {"coordinates":[86.081828,22.929923],"type":"Point"}
}