{
  "type": "Feature",
  "properties": {
    "gn:country":"IN",
    "gn:fcode":"PPL",
    "gn:pop":16411,
    "iso:country":"IN",
    "name:ben_x_preferred":[
        "\u0996\u09bf\u09b2\u099a\u09bf\u09aa\u09c1\u09b0"
    ],
    "name:bpy_x_preferred":[
        "\u0996\u09bf\u09b2\u099a\u09bf\u09aa\u09c1\u09b0"
    ],
    "name:bul_x_preferred":[
        "\u041a\u0445\u0438\u043b\u0447\u0438\u043f\u0443\u0440"
    ],
    "name:cat_x_preferred":[
        "Khilchipur"
    ],
    "name:chi_x_preferred":[
        "\u57fa\u5c14\u5947\u666e\u5c14"
    ],
    "name:dut_x_preferred":[
        "Khilchipur"
    ],
    "name:eng_x_preferred":[
        "Khilchipur"
    ],
    "name:fre_x_preferred":[
        "Khilchipur"
    ],
    "name:ger_x_preferred":[
        "Khilchipur"
    ],
    "name:guj_x_preferred":[
        "\u0a96\u0abf\u0ab2\u0a9a\u0ac0\u0aaa\u0ac1\u0ab0"
    ],
    "name:ita_x_preferred":[
        "Khilchipur"
    ],
    "name:jpn_x_preferred":[
        "\u30ad\u30eb\u30c1\u30d7\u30fc\u30eb"
    ],
    "name:kan_x_preferred":[
        "\u0c96\u0cbf\u0cb2\u0ccd\u0c9a\u0cbf\u0caa\u0cc1\u0cb0"
    ],
    "name:kor_x_preferred":[
        "\ud0ac\uce58\ud478\ub974"
    ],
    "name:may_x_preferred":[
        "Khilchipur"
    ],
    "name:mlg_x_preferred":[
        "Khilchipur"
    ],
    "name:nan_x_preferred":[
        "Khilchipur"
    ],
    "name:new_x_preferred":[
        "\u0916\u093f\u091a\u093f\u092a\u0941\u0930"
    ],
    "name:pam_x_preferred":[
        "Khilchipur"
    ],
    "name:por_x_preferred":[
        "Khilchipur"
    ],
    "name:rus_x_preferred":[
        "\u041a\u0445\u0438\u043b\u0447\u0438\u043f\u0443\u0440"
    ],
    "name:spa_x_preferred":[
        "Khilchipur"
    ],
    "name:swe_x_preferred":[
        "Khilchipur"
    ],
    "name:tam_x_preferred":[
        "\u0b95\u0bb9\u0bc0\u0bb2\u0bcd\u0b9a\u0bbf\u0baa\u0bc1\u0bb0\u0bcd"
    ],
    "name:tel_x_preferred":[
        "\u0c15\u0c3f\u0c32\u0c4d\u0c1a\u0c3f\u0c2a\u0c42\u0c30\u0c4d"
    ],
    "name:urd_x_preferred":[
        "\u062e\u06cc\u0644\u0686\u06cc\u067e\u0648\u0631"
    ],
    "name:vie_x_preferred":[
        "Khilchipur"
    ],
    "qs:name":"Khilchipur",
    "qs:photos_9r":0,
    "qs:photos_sr":0,
    "qs:pop_sr":"6",
    "wd:wordcount":231,
    "wof:name":"Khilchipur",
    "wof:placetype":"locality",
    "wof:population":16411
},
  "geometry": {"coordinates":[76.578,24.03943],"type":"Point"}
}