{
  "type": "Feature",
  "properties": {
    "iso:country":"IN",
    "ks:ks_name":"Patelarkeri",
    "ks:ks_pop":32,
    "ks:ks_type":"HABITATION",
    "name:eng_x_preferred":[
        "Patelarkeri"
    ],
    "wof:name":"Patelarkeri",
    "wof:placetype":"locality",
    "wof:population":32
},
  "geometry": {"coordinates":[74.417323,14.497257],"type":"Point"}
}