{
  "type": "Feature",
  "properties": {
    "iso:country":"IN",
    "ks:ks_name":"Nim 4 Tandreybong",
    "ks:ks_pop":1095,
    "ks:ks_type":"HABITATION",
    "name:eng_x_preferred":[
        "Nim 4 Tandreybong"
    ],
    "wof:name":"Nim 4 Tandreybong",
    "wof:placetype":"locality",
    "wof:population":1095
},
  "geometry": {"coordinates":[88.68141799999999,27.002935],"type":"Point"}
}