{
  "type": "Feature",
  "properties": {
    "iso:country":"IN",
    "ks:ks_name":"Dakhinsarisa",
    "ks:ks_pop":1192,
    "ks:ks_type":"VILLAGE",
    "ks:ks_uagg_main":0,
    "name:eng_x_preferred":[
        "Dakhinsarisa"
    ],
    "wof:name":"Dakhinsarisa",
    "wof:placetype":"locality",
    "wof:population":1192
},
  "geometry": {"coordinates":[87.471232,21.627281],"type":"Point"}
}