{
  "type": "Feature",
  "properties": {
    "gn:admin1_code":"34.0",
    "gn:admin2_code":"217.0",
    "gn:asciiname":"Kheman Tola",
    "gn:country_code":"IN",
    "gn:dem":73,
    "gn:feature_class":"P",
    "gn:feature_code":"PPL",
    "gn:name":"Kheman Tola",
    "gn:population":0,
    "gn:timezone":"Asia/Kolkata",
    "iso:country":"IN",
    "ks:ks_name":"Kheman Tola",
    "ks:ks_pop":407,
    "ks:ks_type":"VILLAGE",
    "ks:ks_uagg_main":0,
    "name:eng_x_preferred":[
        "Kheman Tola"
    ],
    "wof:name":"Kheman Tola",
    "wof:placetype":"neighbourhood",
    "wof:population":407
},
  "geometry": {"coordinates":[84.23705200000001,26.379951],"type":"Point"}
}