{
  "type": "Feature",
  "properties": {
    "gn:admin1_code":"40.0",
    "gn:admin2_code":"535",
    "gn:asciiname":"Jogipet",
    "gn:country_code":"IN",
    "gn:dem":505,
    "gn:feature_class":"P",
    "gn:feature_code":"PPL",
    "gn:name":"Jogipet",
    "gn:population":0,
    "gn:timezone":"Asia/Kolkata",
    "iso:country":"IN",
    "name:und_x_variant":[
        "Joqipet",
        "Jogipet"
    ],
    "wof:name":"Jogipet",
    "wof:placetype":"locality"
},
  "geometry": {"coordinates":[78.06811,17.83563999999999],"type":"Point"}
}