{
  "type": "Feature",
  "properties": {
    "iso:country":"IN",
    "ks:ks_name":"Nairoha Para",
    "ks:ks_pop":174,
    "ks:ks_type":"HABITATION",
    "name:eng_x_preferred":[
        "Nairoha Para"
    ],
    "wof:name":"Nairoha Para",
    "wof:placetype":"locality",
    "wof:population":174
},
  "geometry": {"coordinates":[91.81634200000001,23.569211],"type":"Point"}
}