{
  "type": "Feature",
  "properties": {
    "iso:country":"IN",
    "name:eng_x_preferred":[
        "Katraj"
    ],
    "name:hin_x_preferred":[
        "\u0915\u093e\u0924\u094d\u0930\u091c"
    ],
    "name:mar_x_preferred":[
        "\u0915\u093e\u0924\u094d\u0930\u091c"
    ],
    "name:tam_x_preferred":[
        "\u0b95\u0bbe\u0ba4\u0bcd\u0bb0\u0b9c\u0bcd"
    ],
    "qs:name":"Katraj",
    "qs:name_adm0":"India",
    "qs:name_adm1":"Maharashtra",
    "qs:photos":18,
    "qs:photos_1k":4,
    "qs:photos_9k":1,
    "qs:photos_9r":1,
    "qs:photos_all":18,
    "qs:photos_sr":1,
    "qs:placetype":"Town",
    "qs:pop_sr":"0",
    "wd:wordcount":143,
    "wof:name":"Katraj",
    "wof:placetype":"locality"
},
  "geometry": {"coordinates":[74.837279,18.293966],"type":"Point"}
}