{
  "type": "Feature",
  "properties": {
    "iso:country":"IN",
    "name:ara_x_preferred":[
        "\u0643\u0627\u062a\u0631\u0627\u062c"
    ],
    "name:ben_bn_x_preferred":[
        "\u0995\u09be\u099f\u09b0\u09be\u099c"
    ],
    "name:ben_in_x_preferred":[
        "\u0995\u09be\u099f\u09b0\u09be\u099c"
    ],
    "name:eng_x_preferred":[
        "Katraj"
    ],
    "name:guj_x_preferred":[
        "\u0a95\u0a9f\u0ab0\u0abe\u0a9c"
    ],
    "name:hin_x_preferred":[
        "\u0915\u091f\u0930\u093e\u091c"
    ],
    "name:hin_x_variant":[
        "\u0915\u093e\u0924\u094d\u0930\u091c"
    ],
    "name:kan_x_preferred":[
        "\u0c95\u0ca4\u0ccd\u0cb0\u0cbe\u0c9c\u0ccd"
    ],
    "name:mal_x_preferred":[
        "\u0d15\u0d24\u0d4d\u0d30\u0d3e\u0d1c\u0d4d"
    ],
    "name:mar_x_preferred":[
        "\u0915\u093e\u0924\u094d\u0930\u091c"
    ],
    "name:pan_x_preferred":[
        "\u0a15\u0a1f\u0a30\u0a3e\u0a1c"
    ],
    "name:tam_x_preferred":[
        "\u0b95\u0b9f\u0bcd\u0bb0\u0bbe\u0b9c\u0bcd"
    ],
    "name:tam_x_variant":[
        "\u0b95\u0bbe\u0ba4\u0bcd\u0bb0\u0b9c\u0bcd"
    ],
    "name:tel_x_preferred":[
        "\u0c15\u0c24\u0c4d\u0c30\u0c3e\u0c1c\u0c4d"
    ],
    "name:urd_x_preferred":[
        "\u06a9\u0679\u0631\u0627\u062c"
    ],
    "qs:name":"Katraj",
    "qs:name_adm0":"India",
    "qs:name_adm1":"Maharashtra",
    "qs:photos":18,
    "qs:photos_1k":4,
    "qs:photos_9k":1,
    "qs:photos_9r":1,
    "qs:photos_all":18,
    "qs:photos_sr":1,
    "qs:placetype":"Town",
    "qs:pop_sr":"0",
    "wd:wordcount":143,
    "wof:name":"Katraj",
    "wof:placetype":"locality"
},
  "geometry": {"coordinates":[74.837279,18.293966],"type":"Point"}
}