{
  "type": "Feature",
  "properties": {
    "iso:country":"IN",
    "ks:ks_name":"Gopalsahi",
    "ks:ks_pop":20,
    "ks:ks_type":"HABITATION",
    "name:eng_x_preferred":[
        "Gopalsahi"
    ],
    "wof:name":"Gopalsahi",
    "wof:placetype":"locality",
    "wof:population":20
},
  "geometry": {"coordinates":[85.32855600000001,21.617066],"type":"Point"}
}