{
  "type": "Feature",
  "properties": {
    "gn:admin1_code":"28.0",
    "gn:admin2_code":"343",
    "gn:asciiname":"Budhakhali",
    "gn:country_code":"IN",
    "gn:dem":5,
    "gn:feature_class":"P",
    "gn:feature_code":"PPL",
    "gn:name":"Budhakh\u0101li",
    "gn:population":0,
    "gn:timezone":"Asia/Kolkata",
    "iso:country":"IN",
    "ks:ks_alt_nam":"Budhakh\u0101li",
    "ks:ks_name":"Budhakhali",
    "ks:ks_pop":4696,
    "ks:ks_type":"VILLAGE",
    "name:eng_x_preferred":[
        "Budhakhali"
    ],
    "name:eng_x_variant":[
        "Budhakh\u0101li"
    ],
    "wof:name":"Budhakhali",
    "wof:placetype":"locality",
    "wof:population":4696
},
  "geometry": {"coordinates":[88.208056,21.823056],"type":"Point"}
}