{
  "type": "Feature",
  "properties": {
    "gn:admin1_code":"34.0",
    "gn:admin2_code":"236.0",
    "gn:asciiname":"Sakhwa",
    "gn:country_code":"IN",
    "gn:dem":195,
    "gn:feature_class":"P",
    "gn:feature_code":"PPL",
    "gn:name":"Sakhwa",
    "gn:population":0,
    "gn:timezone":"Asia/Kolkata",
    "iso:country":"IN",
    "ks:ks_alt_nam":"SAKHWA",
    "ks:ks_name":"Sakhwa",
    "ks:ks_pop":198,
    "ks:ks_type":"HABITATION",
    "name:eng_x_preferred":[
        "Sakhwa"
    ],
    "wof:name":"Sakhwa",
    "wof:placetype":"locality",
    "wof:population":198
},
  "geometry": {"coordinates":[85.118565,24.410987],"type":"Point"}
}