{
  "type": "Feature",
  "properties": {
    "iso:country":"IN",
    "ks:ks_name":"Chandra Hansa Para",
    "ks:ks_pop":582,
    "ks:ks_type":"HABITATION",
    "name:eng_x_preferred":[
        "Chandra Hansa Para"
    ],
    "wof:name":"Chandra Hansa Para",
    "wof:placetype":"locality",
    "wof:population":582
},
  "geometry": {"coordinates":[91.92923999999999,24.014116],"type":"Point"}
}