{
  "type": "Feature",
  "properties": {
    "iso:country":"IN",
    "ks:ks_name":"Melkalpattadai",
    "ks:ks_pop":220,
    "ks:ks_type":"HABITATION",
    "name:eng_x_preferred":[
        "Melkalpattadai"
    ],
    "wof:name":"Melkalpattadai",
    "wof:placetype":"locality",
    "wof:population":220
},
  "geometry": {"coordinates":[79.427677,13.332692],"type":"Point"}
}