{
  "type": "Feature",
  "properties": {
    "gn:admin1_code":"2.0",
    "gn:admin2_code":"542.0",
    "gn:asciiname":"Haripurampallapuram",
    "gn:country_code":"IN",
    "gn:dem":71,
    "gn:feature_class":"P",
    "gn:feature_code":"PPL",
    "gn:name":"Haripurampall\u0101puram",
    "gn:population":0,
    "gn:timezone":"Asia/Kolkata",
    "iso:country":"IN",
    "ks:ks_alt_nam":"Haripurampall\u0101puram",
    "ks:ks_name":"Haripurampallapuram",
    "ks:ks_type":"VILLAGE",
    "name:eng_x_preferred":[
        "Haripurampallapuram"
    ],
    "name:eng_x_variant":[
        "Haripurampall\u0101puram"
    ],
    "wof:name":"Haripurampallapuram",
    "wof:placetype":"locality"
},
  "geometry": {"coordinates":[83.791432,18.598043],"type":"Point"}
}