{
  "type": "Feature",
  "properties": {
    "iso:country":"IN",
    "ks:ks_name":"Shajapur",
    "ks:ks_pop":593,
    "ks:ks_type":"HABITATION",
    "name:eng_x_preferred":[
        "Shajapur"
    ],
    "wof:name":"Shajapur",
    "wof:placetype":"locality",
    "wof:population":593
},
  "geometry": {"coordinates":[77.60987299999999,24.905001],"type":"Point"}
}