{
  "type": "Feature",
  "properties": {
    "iso:country":"IN",
    "ks:ks_name":"Kathai",
    "ks:ks_pop":700,
    "ks:ks_type":"VILLAGE",
    "name:eng_x_preferred":[
        "Kathai"
    ],
    "wof:name":"Kathai",
    "wof:placetype":"locality",
    "wof:population":700
},
  "geometry": {"coordinates":[81.177134,23.515366],"type":"Point"}
}