{
  "type": "Feature",
  "properties": {
    "gn:admin1_code":"35",
    "gn:admin2_code":"463.0",
    "gn:asciiname":"Panwar",
    "gn:country_code":"IN",
    "gn:dem":194,
    "gn:feature_class":"P",
    "gn:feature_code":"PPL",
    "gn:name":"Panwar",
    "gn:population":0,
    "gn:timezone":"Asia/Kolkata",
    "iso:country":"IN",
    "ks:ks_name":"Panwar",
    "ks:ks_pop":417,
    "ks:ks_type":"VILLAGE",
    "name:eng_x_preferred":[
        "Panwar"
    ],
    "wof:name":"Panwar",
    "wof:placetype":"locality",
    "wof:population":417
},
  "geometry": {"coordinates":[82.661584,24.570052],"type":"Point"}
}