{
  "type": "Feature",
  "properties": {
    "iso:country":"IN",
    "ks:ks_name":"Adhiaria",
    "ks:ks_pop":843,
    "ks:ks_type":"VILLAGE",
    "name:eng_x_preferred":[
        "Adhiaria"
    ],
    "wof:name":"Adhiaria",
    "wof:placetype":"locality",
    "wof:population":843
},
  "geometry": {"coordinates":[82.21201000000001,24.168048],"type":"Point"}
}