{
  "type": "Feature",
  "properties": {
    "iso:country":"IN",
    "ks:ks_name":"Bhanga Band",
    "ks:ks_pop":61,
    "ks:ks_type":"VILLAGE",
    "ks:ks_uagg_main":0,
    "name:eng_x_preferred":[
        "Bhanga Band"
    ],
    "wof:name":"Bhanga Band",
    "wof:placetype":"neighbourhood",
    "wof:population":61
},
  "geometry": {"coordinates":[86.99163799999999,22.284386],"type":"Point"}
}