{
  "type": "Feature",
  "properties": {
    "iso:country":"IN",
    "ks:ks_name":"Meghwalon Ki Dhani",
    "ks:ks_pop":437,
    "ks:ks_type":"VILLAGE",
    "name:eng_x_preferred":[
        "Meghwalon Ki Dhani"
    ],
    "wof:name":"Meghwalon Ki Dhani",
    "wof:placetype":"locality",
    "wof:population":437
},
  "geometry": {"coordinates":[71.756017,25.484989],"type":"Point"}
}