{
  "type": "Feature",
  "properties": {
    "iso:country":"IN",
    "ks:ks_name":"Harjipura",
    "ks:ks_pop":168,
    "ks:ks_type":"HABITATION",
    "name:eng_x_preferred":[
        "Harjipura"
    ],
    "wof:name":"Harjipura",
    "wof:placetype":"locality",
    "wof:population":168
},
  "geometry": {"coordinates":[76.698767,24.058239],"type":"Point"}
}