{
  "type": "Feature",
  "properties": {
    "gn:admin1_code":"36.0",
    "gn:admin2_code":"165.0",
    "gn:asciiname":"Tajpura Awwal",
    "gn:country_code":"IN",
    "gn:dem":149,
    "gn:feature_class":"P",
    "gn:feature_code":"PPL",
    "gn:name":"T\u0101jpura Awwal",
    "gn:population":0,
    "gn:timezone":"Asia/Kolkata",
    "iso:country":"IN",
    "ks:ks_alt_nam":"T\u0101jpura Awwal",
    "ks:ks_name":"Tajpura Awwal",
    "ks:ks_type":"VILLAGE",
    "ks:ks_uagg_main":0,
    "name:eng_x_preferred":[
        "Tajpura Awwal"
    ],
    "name:eng_x_variant":[
        "T\u0101jpura Awwal"
    ],
    "wof:name":"Tajpura Awwal",
    "wof:placetype":"neighbourhood"
},
  "geometry": {"coordinates":[79.145323,26.228762],"type":"Point"}
}