{
  "type": "Feature",
  "properties": {
    "iso:country":"IN",
    "ks:ks_alt_nam":"ITCHKING",
    "ks:ks_name":"Itchking",
    "ks:ks_pop":236,
    "ks:ks_type":"HABITATION",
    "name:eng_x_preferred":[
        "Itchking"
    ],
    "wof:name":"Itchking",
    "wof:placetype":"locality",
    "wof:population":236
},
  "geometry": {"coordinates":[85.860456,22.634276],"type":"Point"}
}