{
  "type": "Feature",
  "properties": {
    "gn:admin1_code":"39.0",
    "gn:admin2_code":"061",
    "gn:asciiname":"Kandakhani",
    "gn:country_code":"IN",
    "gn:dem":1463,
    "gn:feature_class":"P",
    "gn:feature_code":"PPL",
    "gn:name":"Kand\u0101khani",
    "gn:population":0,
    "gn:timezone":"Asia/Kolkata",
    "iso:country":"IN",
    "ks:ks_name":"Kandakhari",
    "ks:ks_pop":295,
    "ks:ks_type":"VILLAGE",
    "name:eng_x_preferred":[
        "Kandakhari"
    ],
    "name:eng_x_variant":[
        "Kandakhani"
    ],
    "wof:name":"Kandakhari",
    "wof:placetype":"locality",
    "wof:population":295
},
  "geometry": {"coordinates":[78.56649299999999,29.936339],"type":"Point"}
}