{
  "type": "Feature",
  "properties": {
    "gn:admin1_code":"39.0",
    "gn:admin2_code":"061",
    "gn:asciiname":"Kandakhani",
    "gn:country_code":"IN",
    "gn:dem":1463,
    "gn:feature_class":"P",
    "gn:feature_code":"PPL",
    "gn:name":"Kand\u0101khani",
    "gn:population":0,
    "gn:timezone":"Asia/Kolkata",
    "iso:country":"IN",
    "wof:name":"Kandakhani",
    "wof:placetype":"locality"
},
  "geometry": {"coordinates":[78.56796,29.93572],"type":"Point"}
}