{
  "type": "Feature",
  "properties": {
    "iso:country":"IN",
    "ks:ks_name":"Bangadunguri",
    "ks:ks_pop":15,
    "ks:ks_type":"HABITATION",
    "name:eng_x_preferred":[
        "Bangadunguri"
    ],
    "wof:name":"Bangadunguri",
    "wof:placetype":"locality",
    "wof:population":15
},
  "geometry": {"coordinates":[86.31216499999999,22.320037],"type":"Point"}
}