{
  "type": "Feature",
  "properties": {
    "iso:country":"IN",
    "ks:ks_name":"Pathkhauli B .pura",
    "ks:ks_pop":811,
    "ks:ks_type":"HABITATION",
    "name:eng_x_preferred":[
        "Pathkhauli B .pura"
    ],
    "wof:name":"Pathkhauli B .pura",
    "wof:placetype":"locality",
    "wof:population":811
},
  "geometry": {"coordinates":[83.00902499999999,26.247863],"type":"Point"}
}