{
  "type": "Feature",
  "properties": {
    "gn:admin1_code":"25.0",
    "gn:admin2_code":"606.0",
    "gn:asciiname":"Randam",
    "gn:country_code":"IN",
    "gn:dem":139,
    "gn:feature_class":"P",
    "gn:feature_code":"PPL",
    "gn:name":"R\u0101ndam",
    "gn:population":0,
    "gn:timezone":"Asia/Kolkata",
    "iso:country":"IN",
    "ks:ks_name":"Randham",
    "ks:ks_pop":891,
    "ks:ks_type":"HABITATION",
    "name:eng_x_preferred":[
        "Randham"
    ],
    "name:eng_x_variant":[
        "Randam"
    ],
    "wof:name":"Randham",
    "wof:placetype":"locality",
    "wof:population":891
},
  "geometry": {"coordinates":[79.30757,12.575436],"type":"Point"}
}