{
  "type": "Feature",
  "properties": {
    "iso:country":"IN",
    "ks:ks_name":"Arandiya",
    "ks:ks_pop":160,
    "ks:ks_type":"VILLAGE",
    "name:eng_x_preferred":[
        "Arandiya"
    ],
    "wof:name":"Arandiya",
    "wof:placetype":"locality",
    "wof:population":160
},
  "geometry": {"coordinates":[86.970055,24.303545],"type":"Point"}
}