{
  "type": "Feature",
  "properties": {
    "gn:admin1_code":"40",
    "gn:admin2_code":"537.0",
    "gn:asciiname":"Narsapur",
    "gn:country_code":"IN",
    "gn:dem":596,
    "gn:feature_class":"P",
    "gn:feature_code":"PPL",
    "gn:name":"Nars\u0101pur",
    "gn:population":0,
    "gn:timezone":"Asia/Kolkata",
    "iso:country":"IN",
    "name:tel_x_preferred":[
        "\u0c28\u0c30\u0c38\u0c3e\u0c2a\u0c41\u0c30\u0c02"
    ],
    "wof:name":"Narsapur",
    "wof:placetype":"locality"
},
  "geometry": {"coordinates":[77.83504000000001,17.56534],"type":"Point"}
}