{
  "type": "Feature",
  "properties": {
    "gn:country":"IN",
    "gn:fcode":"PPL",
    "gn:pop":18976,
    "iso:country":"IN",
    "name:ben_x_preferred":[
        "\u0995\u09c1\u09b2\u09aa\u09be\u09b9\u09be\u09b0"
    ],
    "name:bpy_x_preferred":[
        "\u0995\u09c1\u09b2 \u09aa\u09be\u09b9\u09be\u09a1\u09bc"
    ],
    "name:chi_x_preferred":[
        "\u5e93\u5c14\u5e15\u54c8\u5c14"
    ],
    "name:dut_x_preferred":[
        "Kulpahar"
    ],
    "name:eng_x_preferred":[
        "Kulpahar"
    ],
    "name:fre_x_preferred":[
        "Kulpahar"
    ],
    "name:ger_x_preferred":[
        "Kulpahar"
    ],
    "name:guj_x_preferred":[
        "\u0a95\u0ac1\u0ab2\u0aaa\u0ab9\u0abe\u0ab0"
    ],
    "name:ita_x_preferred":[
        "Kulpahar"
    ],
    "name:jpn_x_preferred":[
        "\u30af\u30eb\u30d1\u30cf\u30fc\u30eb"
    ],
    "name:kan_x_preferred":[
        "\u0c95\u0cc1\u0cb2\u0ccd\u0caa\u0cb9\u0cbe\u0cb0\u0ccd"
    ],
    "name:kor_x_preferred":[
        "\ucfe8\ud30c\ud558\ub974"
    ],
    "name:may_x_preferred":[
        "Kul Pahar"
    ],
    "name:mlg_x_preferred":[
        "Kulpahar"
    ],
    "name:nan_x_preferred":[
        "Kul Pahar"
    ],
    "name:new_x_preferred":[
        "\u0915\u0941\u0932 \u092a\u0939\u093e\u0921"
    ],
    "name:pam_x_preferred":[
        "Kulpahar"
    ],
    "name:pol_x_preferred":[
        "Kulpahar"
    ],
    "name:por_x_preferred":[
        "Kul Pahar"
    ],
    "name:rus_x_preferred":[
        "\u041a\u0443\u043b\u043f\u0430\u0445\u0430\u0440"
    ],
    "name:spa_x_preferred":[
        "Kulpahar"
    ],
    "name:swe_x_preferred":[
        "Kulpah\u0101r"
    ],
    "name:tam_x_preferred":[
        "\u0b95\u0bc1\u0bb2\u0bcd\u0baa\u0bb9\u0bb0\u0bcd"
    ],
    "name:tel_x_preferred":[
        "\u0c15\u0c41\u0c32\u0c4d\u0c2a\u0c39\u0c3e\u0c30\u0c4d"
    ],
    "name:unk_x_variant":[
        "Kulpah\u0101r"
    ],
    "name:urd_x_preferred":[
        "\u06a9\u0644\u067e\u06c1\u0631"
    ],
    "name:vie_x_preferred":[
        "Kul Pahar"
    ],
    "qs:name":"Kulpahar",
    "qs:name_adm0":"India",
    "qs:name_adm1":"Uttar Pradesh",
    "qs:photos_9k":1,
    "qs:photos_9r":1,
    "qs:photos_all":3,
    "qs:photos_sr":0,
    "qs:placetype":"Town",
    "qs:pop_sr":"6",
    "wd:wordcount":2673,
    "wof:name":"Kulpahar",
    "wof:placetype":"locality",
    "wof:population":18976
},
  "geometry": {"coordinates":[79.63987,25.3202],"type":"Point"}
}