{
  "type": "Feature",
  "properties": {
    "gn:admin1_code":"10.0",
    "gn:admin2_code":"71.0",
    "gn:asciiname":"Tamiun",
    "gn:country_code":"IN",
    "gn:dem":296,
    "gn:feature_class":"P",
    "gn:feature_code":"PPL",
    "gn:name":"Tamiun",
    "gn:population":0,
    "gn:timezone":"Asia/Kolkata",
    "iso:country":"IN",
    "wof:name":"Tamiun",
    "wof:placetype":"locality"
},
  "geometry": {"coordinates":[77.45780000000001,30.29152],"type":"Point"}
}