{
  "type": "Feature",
  "properties": {
    "gn:admin1_code":"40",
    "gn:admin2_code":"539.0",
    "gn:asciiname":"Panguvankunta Tanda",
    "gn:country_code":"IN",
    "gn:dem":156,
    "gn:feature_class":"P",
    "gn:feature_code":"PPL",
    "gn:name":"Panguv\u0101nkunta T\u0101nda",
    "gn:population":0,
    "gn:timezone":"Asia/Kolkata",
    "iso:country":"IN",
    "wof:name":"Panguvankunta Tanda",
    "wof:placetype":"neighbourhood"
},
  "geometry": {"coordinates":[79.30752,16.73776],"type":"Point"}
}