{
  "type": "Feature",
  "properties": {
    "gn:admin1_code":"36",
    "gn:admin2_code":"179.0",
    "gn:asciiname":"Ramchandpur",
    "gn:country_code":"IN",
    "gn:dem":102,
    "gn:feature_class":"P",
    "gn:feature_code":"PPL",
    "gn:name":"R\u0101mchandpur",
    "gn:population":0,
    "gn:timezone":"Asia/Kolkata",
    "iso:country":"IN",
    "ks:ks_name":"Ramchandra Pur",
    "ks:ks_pop":127,
    "ks:ks_type":"VILLAGE",
    "ks:ks_uagg_main":0,
    "name:eng_x_preferred":[
        "Ramchandra Pur"
    ],
    "wof:name":"Ramchandra Pur",
    "wof:placetype":"neighbourhood",
    "wof:population":127
},
  "geometry": {"coordinates":[82.024495,26.111366],"type":"Point"}
}