{
  "type": "Feature",
  "properties": {
    "iso:country":"IN",
    "ks:ks_name":"Yadavdih",
    "ks:ks_pop":94,
    "ks:ks_type":"HABITATION",
    "name:eng_x_preferred":[
        "Yadavdih"
    ],
    "wof:name":"Yadavdih",
    "wof:placetype":"locality",
    "wof:population":94
},
  "geometry": {"coordinates":[86.07078799999999,24.310137],"type":"Point"}
}