{
  "type": "Feature",
  "properties": {
    "gn:country":"IN",
    "gn:fcode":"PPL",
    "gn:population":22555,
    "iso:country":"IN",
    "name:ben_x_preferred":[
        "\u09aa\u09c1\u0996\u09cd\u09b0\u09be\u09af\u09bc\u09a8"
    ],
    "name:bpy_x_preferred":[
        "\u09aa\u09c1\u0996\u09b0\u09be\u09af\u09bc\u09be\u09a8"
    ],
    "name:ceb_x_preferred":[
        "Pukhr\u0101y\u0101n"
    ],
    "name:deu_x_preferred":[
        "Pukhrayan"
    ],
    "name:eng_x_preferred":[
        "Pukhrayan"
    ],
    "name:fas_x_preferred":[
        "\u067e\u0648\u06a9\u0631\u0627\u06cc\u0627\u0646"
    ],
    "name:fra_x_preferred":[
        "Pukhrayan"
    ],
    "name:guj_x_preferred":[
        "\u0aaa\u0acb\u0a96\u0ab0\u0abe\u0aaf\u0aa3"
    ],
    "name:hif_x_preferred":[
        "Pukhrayan"
    ],
    "name:hin_x_preferred":[
        "\u092a\u0941\u0916\u0930\u093e\u092f\u093e\u0901"
    ],
    "name:ita_x_preferred":[
        "Pukhrayan"
    ],
    "name:jpn_x_preferred":[
        "\u30d7\u30af\u30e9\u30e4\u30f3"
    ],
    "name:kan_x_preferred":[
        "\u0caa\u0cc1\u0c96\u0ccd\u0cb0\u0caf\u0cbe\u0ca8\u0ccd"
    ],
    "name:kor_x_preferred":[
        "\ud478\ud06c\ub77c\uc580"
    ],
    "name:mar_x_preferred":[
        "\u092a\u0941\u0916\u0930\u093e\u092f\u0923"
    ],
    "name:mlg_x_preferred":[
        "Pukhrayan"
    ],
    "name:msa_x_preferred":[
        "Pukhrayan"
    ],
    "name:nan_x_preferred":[
        "Pukhrayan"
    ],
    "name:nld_x_preferred":[
        "Pukhrayan"
    ],
    "name:ori_x_preferred":[
        "\u0b2a\u0b41\u0b16\u0b30\u0b3e\u0b5f\u0b3e\u0b01"
    ],
    "name:pnb_x_preferred":[
        "\u067e\u06a9\u06be\u0631\u0627\u06cc\u0627\u06ba"
    ],
    "name:pol_x_preferred":[
        "Pukhrayan"
    ],
    "name:por_x_preferred":[
        "Pukhrayan"
    ],
    "name:rus_x_preferred":[
        "\u041f\u0443\u043a\u0445\u0440\u0430\u0439\u044f\u043d"
    ],
    "name:spa_x_preferred":[
        "Pukhrayan"
    ],
    "name:swe_x_preferred":[
        "Pukhr\u0101y\u0101n"
    ],
    "name:tam_x_preferred":[
        "\u0baa\u0bc1\u0b95\u0bcd\u0bb9\u0bb0\u0baf\u0bbe\u0ba9\u0bcd"
    ],
    "name:tel_x_preferred":[
        "\u0c2a\u0c41\u0c16\u0c4d\u0c30\u0c2f\u0c28\u0c4d"
    ],
    "name:urd_x_preferred":[
        "\u067e\u06a9\u06be\u0631\u0627\u06cc\u0627\u06ba"
    ],
    "name:vie_x_preferred":[
        "Pukhrayan"
    ],
    "name:zho_x_preferred":[
        "\u666e\u514b\u62c9\u5ef6"
    ],
    "qs:name":"Pukhrayan",
    "qs:name_adm0":"India",
    "qs:name_adm1":"Uttar Pradesh",
    "qs:photos_9k":1,
    "qs:photos_9r":1,
    "qs:photos_all":2,
    "qs:photos_sr":0,
    "qs:placetype":"Town",
    "qs:pop_sr":"7",
    "wd:wordcount":351,
    "wof:name":"Pukhrayan",
    "wof:placetype":"locality",
    "wof:population":22555
},
  "geometry": {"coordinates":[79.83718,26.22287],"type":"Point"}
}