{
  "type": "Feature",
  "properties": {
    "iso:country":"IN",
    "ks:ks_name":"Mehpur",
    "ks:ks_pop":613,
    "ks:ks_type":"HABITATION",
    "name:eng_x_preferred":[
        "Mehpur"
    ],
    "wof:name":"Mehpur",
    "wof:placetype":"locality",
    "wof:population":613
},
  "geometry": {"coordinates":[78.428831,27.171067],"type":"Point"}
}