{
  "type": "Feature",
  "properties": {
    "iso:country":"IN",
    "ks:ks_name":"Liundi",
    "ks:ks_pop":15,
    "ks:ks_type":"VILLAGE",
    "name:eng_x_preferred":[
        "Liundi"
    ],
    "wof:name":"Liundi",
    "wof:placetype":"locality",
    "wof:population":15
},
  "geometry": {"coordinates":[84.38706500000001,19.798987],"type":"Point"}
}