{
  "type": "Feature",
  "properties": {
    "gn:admin1_code":"11",
    "gn:admin2_code":"23.0",
    "gn:asciiname":"Bhaian Caraon",
    "gn:country_code":"IN",
    "gn:dem":1939,
    "gn:feature_class":"P",
    "gn:feature_code":"PPL",
    "gn:name":"Bhai\u0101n Car\u0101on",
    "gn:population":0,
    "gn:timezone":"Asia/Kolkata",
    "iso:country":"IN",
    "wof:name":"Bhaian Caraon",
    "wof:placetype":"locality"
},
  "geometry": {"coordinates":[76.20924000000002,32.57105],"type":"Point"}
}