{
  "type": "Feature",
  "properties": {
    "gn:admin1_code":"2",
    "gn:admin2_code":"544.0",
    "gn:asciiname":"Laskarguda",
    "gn:country_code":"IN",
    "gn:dem":952,
    "gn:feature_class":"P",
    "gn:feature_code":"PPL",
    "gn:name":"Laskarg\u016bda",
    "gn:population":0,
    "gn:timezone":"Asia/Kolkata",
    "iso:country":"IN",
    "wof:name":"Laskarguda",
    "wof:placetype":"locality"
},
  "geometry": {"coordinates":[82.77247,18.29493],"type":"Point"}
}