{
  "type": "Feature",
  "properties": {
    "iso:country":"IN",
    "ks:ks_name":"Pali Kolsari",
    "ks:ks_pop":441,
    "ks:ks_type":"HABITATION",
    "name:eng_x_preferred":[
        "Pali Kolsari"
    ],
    "wof:name":"Pali Kolsari",
    "wof:placetype":"locality",
    "wof:population":441
},
  "geometry": {"coordinates":[78.538065,30.207184],"type":"Point"}
}