{
  "type": "Feature",
  "properties": {
    "gn:admin1_code":"13.0",
    "gn:admin2_code":"597.0",
    "gn:asciiname":"Chemmanam Tekkumbhagam",
    "gn:country_code":"IN",
    "gn:dem":10,
    "gn:feature_class":"P",
    "gn:feature_code":"PPL",
    "gn:name":"Chemmanam Tekkumbh\u0101gam",
    "gn:population":0,
    "gn:timezone":"Asia/Kolkata",
    "iso:country":"IN",
    "wof:name":"Chemmanam Tekkumbhagam",
    "wof:placetype":"locality"
},
  "geometry": {"coordinates":[76.4066,9.72006],"type":"Point"}
}