{
  "type": "Feature",
  "properties": {
    "iso:country":"IN",
    "ks:ks_name":"Gopinathpur",
    "ks:ks_pop":1344,
    "ks:ks_type":"HABITATION",
    "name:eng_x_preferred":[
        "Gopinathpur"
    ],
    "wof:name":"Gopinathpur",
    "wof:placetype":"locality",
    "wof:population":1344
},
  "geometry": {"coordinates":[86.84673100000001,20.95398],"type":"Point"}
}