{
  "type": "Feature",
  "properties": {
    "iso:country":"IN",
    "ks:ks_name":"Arossim",
    "ks:ks_pop":1708,
    "ks:ks_type":"VILLAGE",
    "ks:ks_uagg_main":0,
    "name:eng_x_preferred":[
        "Arossim"
    ],
    "wof:name":"Arossim",
    "wof:placetype":"locality",
    "wof:population":1708
},
  "geometry": {"coordinates":[73.904932,15.33695],"type":"Point"}
}