{
  "type": "Feature",
  "properties": {
    "gn:admin1_code":"10.0",
    "gn:admin2_code":"82.0",
    "gn:asciiname":"Sunari Kalan",
    "gn:country_code":"IN",
    "gn:dem":223,
    "gn:feature_class":"P",
    "gn:feature_code":"PPL",
    "gn:name":"Sun\u0101ri Kal\u0101n",
    "gn:population":0,
    "gn:timezone":"Asia/Kolkata",
    "iso:country":"IN",
    "ks:ks_alt_nam":"Sun\u0101ri Kal\u0101n",
    "ks:ks_name":"Sunari Kalan",
    "ks:ks_pop":2912,
    "ks:ks_type":"VILLAGE",
    "ks:ks_uagg_main":0,
    "name:eng_x_preferred":[
        "Sunari Kalan"
    ],
    "name:eng_x_variant":[
        "Sun\u0101ri Kal\u0101n"
    ],
    "wof:name":"Sunari Kalan",
    "wof:placetype":"locality",
    "wof:population":2912
},
  "geometry": {"coordinates":[76.570178,28.860549],"type":"Point"}
}