{
  "type": "Feature",
  "properties": {
    "iso:country":"IN",
    "ks:ks_name":"Moti Raval",
    "ks:ks_pop":683,
    "ks:ks_type":"VILLAGE",
    "name:eng_x_preferred":[
        "Moti Raval"
    ],
    "wof:name":"Moti Raval",
    "wof:placetype":"locality",
    "wof:population":683
},
  "geometry": {"coordinates":[73.631496,21.87052],"type":"Point"}
}