{
  "type": "Feature",
  "properties": {
    "iso:country":"IN",
    "ks:ks_name":"Penchaldihi",
    "ks:ks_pop":0,
    "ks:ks_type":"VILLAGE",
    "name:eng_x_preferred":[
        "Penchaldihi"
    ],
    "wof:name":"Penchaldihi",
    "wof:placetype":"locality",
    "wof:population":0
},
  "geometry": {"coordinates":[86.975284,23.219824],"type":"Point"}
}