{
  "type": "Feature",
  "properties": {
    "gn:admin1_code":"16.0",
    "gn:admin2_code":"499.0",
    "gn:asciiname":"Kahurkheda",
    "gn:country_code":"IN",
    "gn:dem":262,
    "gn:feature_class":"P",
    "gn:feature_code":"PPL",
    "gn:name":"K\u0101hurkheda",
    "gn:population":0,
    "gn:timezone":"Asia/Kolkata",
    "iso:country":"IN",
    "wof:name":"Kahurkheda",
    "wof:placetype":"locality"
},
  "geometry": {"coordinates":[75.9684,21.02548],"type":"Point"}
}