{
  "type": "Feature",
  "properties": {
    "iso:country":"IN",
    "ks:ks_alt_nam":"PUJARIWASTI",
    "ks:ks_name":"Pujariwasti",
    "ks:ks_pop":146,
    "ks:ks_type":"HABITATION",
    "ks:ks_uagg_main":0,
    "name:eng_x_preferred":[
        "Pujariwasti"
    ],
    "wof:name":"Pujariwasti",
    "wof:placetype":"neighbourhood",
    "wof:population":146
},
  "geometry": {"coordinates":[75.158332,17.233865],"type":"Point"}
}