{
  "type": "Feature",
  "properties": {
    "gn:admin1_code":"36.0",
    "gn:admin2_code":"179.0",
    "gn:asciiname":"Sujanpur",
    "gn:country_code":"IN",
    "gn:dem":109,
    "gn:feature_class":"P",
    "gn:feature_code":"PPL",
    "gn:name":"Suj\u0101npur",
    "gn:population":0,
    "gn:timezone":"Asia/Kolkata",
    "iso:country":"IN",
    "name:ben_x_preferred":[
        "\u09b8\u09c1\u099c\u09a8\u09aa\u09c1\u09b0"
    ],
    "name:bpy_x_preferred":[
        "\u09b8\u09c1\u099c\u09a8\u09aa\u09c1\u09b0"
    ],
    "name:ita_x_preferred":[
        "Sujanpur"
    ],
    "name:msa_x_preferred":[
        "Sujanpur"
    ],
    "name:nld_x_preferred":[
        "Sujanpur"
    ],
    "name:ori_x_preferred":[
        "\u0b38\u0b41\u0b1c\u0b3e\u0b28\u0b2a\u0b41\u0b30"
    ],
    "name:pan_x_preferred":[
        "\u0a38\u0a41\u0a1c\u0a3e\u0a28\u0a2a\u0a41\u0a30"
    ],
    "name:por_x_preferred":[
        "Sujanpur"
    ],
    "name:urd_x_preferred":[
        "\u0633\u062c\u0627\u0646 \u067e\u0648\u0631"
    ],
    "name:vie_x_preferred":[
        "Sujanpur"
    ],
    "name:zho_x_preferred":[
        "\u82cf\u8a79\u666e\u5c14"
    ],
    "wof:name":"Sujanpur",
    "wof:placetype":"locality"
},
  "geometry": {"coordinates":[81.62434,26.55184],"type":"Point"}
}