{
  "type": "Feature",
  "properties": {
    "gn:country":"IN",
    "gn:fcode":"PPL",
    "gn:population":12469,
    "iso:country":"IN",
    "name:ast_x_preferred":[
        "Navelim"
    ],
    "name:azb_x_preferred":[
        "\u0646\u0627\u0648\u0644\u06cc\u0645"
    ],
    "name:ben_x_preferred":[
        "\u09a8\u09be\u09ad\u09c7\u09b2\u09bf\u09ae"
    ],
    "name:bpy_x_preferred":[
        "\u09a8\u09be\u09ad\u09c7\u09b2\u09bf\u09ae"
    ],
    "name:ceb_x_preferred":[
        "Navelim"
    ],
    "name:eng_x_preferred":[
        "Navelim"
    ],
    "name:fra_x_preferred":[
        "Navelim"
    ],
    "name:gom_x_preferred":[
        "Navelim"
    ],
    "name:guj_x_preferred":[
        "\u0aa8\u0ab5\u0ac7\u0ab2\u0ac0\u0aae"
    ],
    "name:ita_x_preferred":[
        "Navelim"
    ],
    "name:mlg_x_preferred":[
        "Navelim"
    ],
    "name:msa_x_preferred":[
        "Navelim"
    ],
    "name:nan_x_preferred":[
        "Navelim"
    ],
    "name:new_x_preferred":[
        "\u0928\u0935\u0947\u0932\u093f\u092e"
    ],
    "name:nld_x_preferred":[
        "Navelim"
    ],
    "name:swe_x_preferred":[
        "Navelim"
    ],
    "name:vie_x_preferred":[
        "Navelim"
    ],
    "name:zho_x_preferred":[
        "\u7eb3\u97e6\u5229\u59c6"
    ],
    "qs:name":"Navelim",
    "qs:name_adm0":"India",
    "qs:name_adm1":"Goa",
    "qs:photos_9r":0,
    "qs:photos_sr":0,
    "qs:placetype":"Town",
    "qs:pop_sr":"6",
    "wd:wordcount":917,
    "wof:name":"Navelim",
    "wof:placetype":"locality",
    "wof:population":12469
},
  "geometry": {"coordinates":[73.98333,15.53333],"type":"Point"}
}