{
  "type": "Feature",
  "properties": {
    "gn:country":"IN",
    "gn:fcode":"PPL",
    "gn:pop":12469,
    "iso:country":"IN",
    "name:ben_x_preferred":[
        "\u09a8\u09be\u09ad\u09c7\u09b2\u09bf\u09ae"
    ],
    "name:bpy_x_preferred":[
        "\u09a8\u09be\u09ad\u09c7\u09b2\u09bf\u09ae"
    ],
    "name:chi_x_preferred":[
        "\u7eb3\u97e6\u5229\u59c6"
    ],
    "name:dut_x_preferred":[
        "Navelim"
    ],
    "name:eng_x_preferred":[
        "Navelim"
    ],
    "name:fre_x_preferred":[
        "Navelim"
    ],
    "name:gom_x_preferred":[
        "Navelim"
    ],
    "name:ita_x_preferred":[
        "Navelim"
    ],
    "name:may_x_preferred":[
        "Navelim"
    ],
    "name:mlg_x_preferred":[
        "Navelim"
    ],
    "name:nan_x_preferred":[
        "Navelim"
    ],
    "name:new_x_preferred":[
        "\u0928\u0935\u0947\u0932\u093f\u092e"
    ],
    "name:swe_x_preferred":[
        "Navelim"
    ],
    "name:vie_x_preferred":[
        "Navelim"
    ],
    "qs:name":"Navelim",
    "qs:name_adm0":"India",
    "qs:name_adm1":"Goa",
    "qs:photos_9r":0,
    "qs:photos_sr":0,
    "qs:placetype":"Town",
    "qs:pop_sr":"6",
    "wd:wordcount":917,
    "wof:name":"Navelim",
    "wof:placetype":"locality",
    "wof:population":12469
},
  "geometry": {"coordinates":[73.98333,15.53333],"type":"Point"}
}