{
  "type": "Feature",
  "properties": {
    "iso:country":"IN",
    "ks:ks_name":"Devgaon",
    "ks:ks_type":"VILLAGE",
    "name:eng_x_preferred":[
        "Devgaon"
    ],
    "wof:name":"Devgaon",
    "wof:placetype":"locality"
},
  "geometry": {"coordinates":[77.913189,20.169314],"type":"Point"}
}