{
  "type": "Feature",
  "properties": {
    "iso:country":"IN",
    "ks:ks_name":"Santhal Tola",
    "ks:ks_pop":203,
    "ks:ks_type":"HABITATION",
    "name:eng_x_preferred":[
        "Santhal Tola"
    ],
    "wof:name":"Santhal Tola",
    "wof:placetype":"locality",
    "wof:population":203
},
  "geometry": {"coordinates":[87.370372,26.248404],"type":"Point"}
}