{
  "type": "Feature",
  "properties": {
    "iso:country":"IN",
    "ks:ks_name":"Jalapali",
    "ks:ks_pop":223,
    "ks:ks_type":"VILLAGE",
    "name:eng_x_preferred":[
        "Jalapali"
    ],
    "wof:name":"Jalapali",
    "wof:placetype":"locality",
    "wof:population":223
},
  "geometry": {"coordinates":[83.76394999999999,20.66205],"type":"Point"}
}