{
  "type": "Feature",
  "properties": {
    "gn:admin1_code":"36",
    "gn:admin2_code":"165.0",
    "gn:asciiname":"Dasahri",
    "gn:country_code":"IN",
    "gn:dem":140,
    "gn:feature_class":"P",
    "gn:feature_code":"PPL",
    "gn:name":"Dasahri",
    "gn:population":0,
    "gn:timezone":"Asia/Kolkata",
    "iso:country":"IN",
    "wof:name":"Dasahri",
    "wof:placetype":"locality"
},
  "geometry": {"coordinates":[79.67601999999999,25.96998],"type":"Point"}
}