{
  "type": "Feature",
  "properties": {
    "iso:country":"IN",
    "ks:ks_name":"Sanaindas",
    "ks:ks_pop":524,
    "ks:ks_type":"VILLAGE",
    "name:eng_x_preferred":[
        "Sanaindas"
    ],
    "wof:name":"Sanaindas",
    "wof:placetype":"locality",
    "wof:population":524
},
  "geometry": {"coordinates":[86.370566,20.79461],"type":"Point"}
}