{
  "type": "Feature",
  "properties": {
    "iso:country":"IN",
    "ks:ks_name":"Natu Nagar",
    "ks:ks_pop":726,
    "ks:ks_type":"VILLAGE",
    "name:eng_x_preferred":[
        "Natu Nagar"
    ],
    "wof:name":"Natu Nagar",
    "wof:placetype":"locality",
    "wof:population":726
},
  "geometry": {"coordinates":[73.406222,17.828269],"type":"Point"}
}