{
  "type": "Feature",
  "properties": {
    "gn:admin1_code":"21",
    "gn:admin2_code":"398.0",
    "gn:asciiname":"Dummurivalasa",
    "gn:country_code":"IN",
    "gn:dem":946,
    "gn:feature_class":"P",
    "gn:feature_code":"PPL",
    "gn:name":"Dummurivalasa",
    "gn:population":0,
    "gn:timezone":"Asia/Kolkata",
    "iso:country":"IN",
    "wof:name":"Dummurivalasa",
    "wof:placetype":"locality"
},
  "geometry": {"coordinates":[82.89664,18.48408],"type":"Point"}
}