{
  "type": "Feature",
  "properties": {
    "gn:admin1_code":"39.0",
    "gn:admin2_code":"63.0",
    "gn:asciiname":"Tandola Kharak",
    "gn:country_code":"IN",
    "gn:dem":2060,
    "gn:feature_class":"P",
    "gn:feature_code":"PPL",
    "gn:name":"Tandola Kharak",
    "gn:population":0,
    "gn:timezone":"Asia/Kolkata",
    "iso:country":"IN",
    "wof:name":"Tandola Kharak",
    "wof:placetype":"locality"
},
  "geometry": {"coordinates":[79.76408000000001,29.99638],"type":"Point"}
}