{
  "type": "Feature",
  "properties": {
    "iso:country":"IN",
    "ks:ks_name":"Pipalkhuta",
    "ks:ks_pop":653,
    "ks:ks_type":"VILLAGE",
    "name:eng_x_preferred":[
        "Pipalkhuta"
    ],
    "wof:name":"Pipalkhuta",
    "wof:placetype":"locality",
    "wof:population":653
},
  "geometry": {"coordinates":[82.313841,19.988959],"type":"Point"}
}