{
  "type": "Feature",
  "properties": {
    "gn:admin1_code":"2.0",
    "gn:admin2_code":"543.0",
    "gn:asciiname":"Reddivanivalasa",
    "gn:country_code":"IN",
    "gn:dem":150,
    "gn:feature_class":"P",
    "gn:feature_code":"PPL",
    "gn:name":"Reddiv\u0101nivalasa",
    "gn:population":0,
    "gn:timezone":"Asia/Kolkata",
    "iso:country":"IN",
    "ks:ks_name":"Reddivanivalasa",
    "ks:ks_pop":146,
    "ks:ks_type":"HABITATION",
    "name:eng_x_preferred":[
        "Reddivanivalasa"
    ],
    "wof:name":"Reddivanivalasa",
    "wof:placetype":"locality",
    "wof:population":146
},
  "geometry": {"coordinates":[83.22554100000001,18.368645],"type":"Point"}
}