{
  "type": "Feature",
  "properties": {
    "gn:admin1_code":"3.0",
    "gn:admin2_code":"309.0",
    "gn:asciiname":"Keseruguri",
    "gn:country_code":"IN",
    "gn:dem":129,
    "gn:feature_class":"P",
    "gn:feature_code":"PPL",
    "gn:name":"Keseruguri",
    "gn:population":0,
    "gn:timezone":"Asia/Kolkata",
    "iso:country":"IN",
    "wof:name":"Keseruguri",
    "wof:placetype":"locality"
},
  "geometry": {"coordinates":[95.45943,27.63894],"type":"Point"}
}