{
  "type": "Feature",
  "properties": {
    "iso:country":"IN",
    "ks:ks_name":"Likson Goan",
    "ks:ks_pop":206,
    "ks:ks_type":"HABITATION",
    "ks:ks_uagg_main":0,
    "name:eng_x_preferred":[
        "Likson Goan"
    ],
    "wof:name":"Likson Goan",
    "wof:placetype":"neighbourhood",
    "wof:population":206
},
  "geometry": {"coordinates":[93.847408,26.645579],"type":"Point"}
}