{
  "type": "Feature",
  "properties": {
    "gn:admin1_code":"19",
    "gn:admin2_code":"580.0",
    "gn:asciiname":"Hayyala Khurd",
    "gn:country_code":"IN",
    "gn:dem":376,
    "gn:feature_class":"P",
    "gn:feature_code":"PPL",
    "gn:name":"Hayy\u0101la Khurd",
    "gn:population":0,
    "gn:timezone":"Asia/Kolkata",
    "iso:country":"IN",
    "wof:name":"Hayyala Khurd",
    "wof:placetype":"neighbourhood"
},
  "geometry": {"coordinates":[76.9425,16.60793],"type":"Point"}
}