{
  "type": "Feature",
  "properties": {
    "gn:admin1_code":"2.0",
    "gn:admin2_code":"554.0",
    "gn:asciiname":"Nunjariyanpalle",
    "gn:country_code":"IN",
    "gn:dem":681,
    "gn:feature_class":"P",
    "gn:feature_code":"PPL",
    "gn:name":"Nunj\u0101riyanpalle",
    "gn:population":0,
    "gn:timezone":"Asia/Kolkata",
    "iso:country":"IN",
    "wof:name":"Nunjariyanpalle",
    "wof:placetype":"locality"
},
  "geometry": {"coordinates":[78.74135,13.46055],"type":"Point"}
}