{
  "type": "Feature",
  "properties": {
    "iso:country":"IN",
    "ks:ks_name":"Sahasraling",
    "ks:ks_type":"VILLAGE",
    "name:eng_x_preferred":[
        "Sahasraling"
    ],
    "wof:name":"Sahasraling",
    "wof:placetype":"locality"
},
  "geometry": {"coordinates":[75.95814,21.317608],"type":"Point"}
}