{
  "type": "Feature",
  "properties": {
    "iso:country":"IN",
    "ks:ks_name":"Sugali Thanda",
    "ks:ks_pop":20,
    "ks:ks_type":"HABITATION",
    "name:eng_x_preferred":[
        "Sugali Thanda"
    ],
    "wof:name":"Sugali Thanda",
    "wof:placetype":"locality",
    "wof:population":20
},
  "geometry": {"coordinates":[78.986712,13.613272],"type":"Point"}
}