{
  "type": "Feature",
  "properties": {
    "iso:country":"IN",
    "ks:ks_name":"Pure Baha",
    "ks:ks_pop":179,
    "ks:ks_type":"HABITATION",
    "ks:ks_uagg_main":0,
    "name:eng_x_preferred":[
        "Pure Baha"
    ],
    "wof:name":"Pure Baha",
    "wof:placetype":"neighbourhood",
    "wof:population":179
},
  "geometry": {"coordinates":[81.621865,26.210165],"type":"Point"}
}