{
  "type": "Feature",
  "properties": {
    "gn:admin1_code":"23",
    "gn:admin2_code":"36.0",
    "gn:asciiname":"Pandorj Rajputan",
    "gn:country_code":"IN",
    "gn:dem":228,
    "gn:feature_class":"P",
    "gn:feature_code":"PPL",
    "gn:name":"Pandorj R\u0101jput\u0101n",
    "gn:population":0,
    "gn:timezone":"Asia/Kolkata",
    "iso:country":"IN",
    "wof:name":"Pandorj Rajputan",
    "wof:placetype":"locality"
},
  "geometry": {"coordinates":[75.5056,31.52314],"type":"Point"}
}