{
  "type": "Feature",
  "properties": {
    "gn:admin1_code":"36.0",
    "gn:admin2_code":"149.0",
    "gn:asciiname":"Jagwasai",
    "gn:country_code":"IN",
    "gn:dem":163,
    "gn:feature_class":"P",
    "gn:feature_code":"PPL",
    "gn:name":"Jagw\u0101sai",
    "gn:population":0,
    "gn:timezone":"Asia/Kolkata",
    "iso:country":"IN",
    "ks:ks_alt_nam":"Jagw\u0101sai",
    "ks:ks_name":"Jagwasai",
    "ks:ks_pop":997,
    "ks:ks_type":"VILLAGE",
    "name:eng_x_preferred":[
        "Jagwasai"
    ],
    "name:eng_x_variant":[
        "Jagw\u0101sai"
    ],
    "wof:name":"Jagwasai",
    "wof:placetype":"locality",
    "wof:population":997
},
  "geometry": {"coordinates":[79.33832099999999,28.103789],"type":"Point"}
}