{
  "type": "Feature",
  "properties": {
    "iso:country":"IN",
    "ks:ks_alt_nam":"Rokatigutta tanda",
    "ks:ks_name":"Rokatigutta Tanda",
    "ks:ks_pop":235,
    "ks:ks_type":"HABITATION",
    "name:eng_x_preferred":[
        "Rokatigutta Tanda"
    ],
    "wof:name":"Rokatigutta Tanda",
    "wof:placetype":"locality",
    "wof:population":235
},
  "geometry": {"coordinates":[77.885876,16.984311],"type":"Point"}
}