{
  "type": "Feature",
  "properties": {
    "iso:country":"IN",
    "ks:ks_name":"Suanlo",
    "ks:ks_pop":150,
    "ks:ks_type":"HABITATION",
    "name:eng_x_preferred":[
        "Suanlo"
    ],
    "wof:name":"Suanlo",
    "wof:placetype":"locality",
    "wof:population":150
},
  "geometry": {"coordinates":[86.621951,20.564158],"type":"Point"}
}