{
  "type": "Feature",
  "properties": {
    "gn:admin1_code":"36.0",
    "gn:admin2_code":"174.0",
    "gn:asciiname":"Kokrahiya",
    "gn:country_code":"IN",
    "gn:dem":106,
    "gn:feature_class":"P",
    "gn:feature_code":"PPL",
    "gn:name":"Kokrahiya",
    "gn:population":0,
    "gn:timezone":"Asia/Kolkata",
    "iso:country":"IN",
    "name:und_x_variant":[
        "Kiraon Kh\u0101s"
    ],
    "wof:name":"Kokrahiya",
    "wof:placetype":"locality"
},
  "geometry": {"coordinates":[81.43374,25.39767],"type":"Point"}
}