{
  "type": "Feature",
  "properties": {
    "iso:country":"IN",
    "ks:ks_name":"Bandhtola",
    "ks:ks_pop":236,
    "ks:ks_type":"HABITATION",
    "name:eng_x_preferred":[
        "Bandhtola"
    ],
    "wof:name":"Bandhtola",
    "wof:placetype":"locality",
    "wof:population":236
},
  "geometry": {"coordinates":[85.119968,23.531893],"type":"Point"}
}