{
  "type": "Feature",
  "properties": {
    "gn:admin1_code":"36.0",
    "gn:admin2_code":"183.0",
    "gn:asciiname":"Khargupur",
    "gn:country_code":"IN",
    "gn:dem":105,
    "gn:feature_class":"P",
    "gn:feature_code":"PPL",
    "gn:name":"Khargupur",
    "gn:population":0,
    "gn:timezone":"Asia/Kolkata",
    "iso:country":"IN",
    "name:bpy_x_preferred":[
        "\u0996\u09b0\u0997\u09c1\u09aa\u09c1\u09b0"
    ],
    "name:ceb_x_preferred":[
        "Khargupur"
    ],
    "name:hin_x_preferred":[
        "\u0916\u0930\u0917\u0942\u092a\u0941\u0930"
    ],
    "name:ita_x_preferred":[
        "Khargupur"
    ],
    "name:mlg_x_preferred":[
        "Khargupur"
    ],
    "name:msa_x_preferred":[
        "Khargupur"
    ],
    "name:new_x_preferred":[
        "\u0916\u0930\u094d\u0917\u0942\u092a\u0941\u0930"
    ],
    "name:nld_x_preferred":[
        "Khargupur"
    ],
    "name:pol_x_preferred":[
        "Khargupur"
    ],
    "name:por_x_preferred":[
        "Khargupur"
    ],
    "name:swe_x_preferred":[
        "Khargupur"
    ],
    "name:urd_x_preferred":[
        "\u06a9\u06be\u0631\u06af\u0648\u067e\u0648\u0631"
    ],
    "name:vie_x_preferred":[
        "Khargupur"
    ],
    "name:zho_x_preferred":[
        "\u5361\u5c14\u53e4\u666e\u5c14"
    ],
    "wof:name":"Khargupur",
    "wof:placetype":"locality"
},
  "geometry": {"coordinates":[82.25614,27.07853],"type":"Point"}
}