{
  "type": "Feature",
  "properties": {
    "gn:admin1_code":"34.0",
    "gn:admin2_code":"218.0",
    "gn:asciiname":"Chandaur",
    "gn:country_code":"IN",
    "gn:dem":70,
    "gn:feature_class":"P",
    "gn:feature_code":"PPL",
    "gn:name":"Chandaur",
    "gn:population":0,
    "gn:timezone":"Asia/Kolkata",
    "iso:country":"IN",
    "ks:ks_name":"Chandaur",
    "ks:ks_pop":1009,
    "ks:ks_type":"VILLAGE",
    "ks:ks_uagg_main":0,
    "name:bih_x_preferred":[
        "\u091a\u0902\u0926\u094c\u0930"
    ],
    "name:bpy_x_preferred":[
        "\u099a\u09be\u09a8\u09cd\u09a6\u09be\u0989\u09b0"
    ],
    "name:eng_x_preferred":[
        "Chandaur"
    ],
    "name:ita_x_preferred":[
        "Chandaur"
    ],
    "name:msa_x_preferred":[
        "Chandaur"
    ],
    "name:new_x_preferred":[
        "\u091a\u0928\u094d\u0926\u094c\u0930"
    ],
    "name:nld_x_preferred":[
        "Chandaur"
    ],
    "name:por_x_preferred":[
        "Chandaur"
    ],
    "name:spa_x_preferred":[
        "Chandaur"
    ],
    "name:vie_x_preferred":[
        "Chandaur"
    ],
    "name:zho_x_preferred":[
        "\u6070\u6069\u9053\u5c14"
    ],
    "wof:name":"Chandaur",
    "wof:placetype":"neighbourhood",
    "wof:population":1009
},
  "geometry": {"coordinates":[84.090284,26.140303],"type":"Point"}
}