{
  "type": "Feature",
  "properties": {
    "iso:country":"IN",
    "ks:ks_name":"Gauntia Milak",
    "ks:ks_pop":642,
    "ks:ks_type":"HABITATION",
    "name:eng_x_preferred":[
        "Gauntia Milak"
    ],
    "wof:name":"Gauntia Milak",
    "wof:placetype":"locality",
    "wof:population":642
},
  "geometry": {"coordinates":[79.293167,28.249303],"type":"Point"}
}