{
  "type": "Feature",
  "properties": {
    "iso:country":"IN",
    "ks:ks_name":"Maranahlli",
    "ks:ks_pop":145,
    "ks:ks_type":"HABITATION",
    "name:eng_x_preferred":[
        "Maranahlli"
    ],
    "wof:name":"Maranahlli",
    "wof:placetype":"locality",
    "wof:population":145
},
  "geometry": {"coordinates":[75.95887999999999,13.031676],"type":"Point"}
}