{
  "type": "Feature",
  "properties": {
    "gn:admin1_code":"2.0",
    "gn:admin2_code":"544.0",
    "gn:asciiname":"Pedda Uncharangi",
    "gn:country_code":"IN",
    "gn:dem":1026,
    "gn:feature_class":"P",
    "gn:feature_code":"PPL",
    "gn:name":"Pedda Uncharangi",
    "gn:population":0,
    "gn:timezone":"Asia/Kolkata",
    "iso:country":"IN",
    "wof:name":"Pedda Uncharangi",
    "wof:placetype":"locality"
},
  "geometry": {"coordinates":[82.46091,18.19743],"type":"Point"}
}