{
  "type": "Feature",
  "properties": {
    "gn:admin1_code":"2.0",
    "gn:admin2_code":"544.0",
    "gn:asciiname":"Pedda Uncharangi",
    "gn:country_code":"IN",
    "gn:dem":1026,
    "gn:feature_class":"P",
    "gn:feature_code":"PPL",
    "gn:name":"Pedda Uncharangi",
    "gn:population":0,
    "gn:timezone":"Asia/Kolkata",
    "iso:country":"IN",
    "ks:ks_name":"Peda Vancharangi",
    "ks:ks_pop":101,
    "ks:ks_type":"HABITATION",
    "name:eng_x_preferred":[
        "Peda Vancharangi"
    ],
    "name:eng_x_variant":[
        "Pedda Uncharangi"
    ],
    "wof:name":"Peda Vancharangi",
    "wof:placetype":"locality",
    "wof:population":101
},
  "geometry": {"coordinates":[82.46080499999999,18.196117],"type":"Point"}
}