{
  "type": "Feature",
  "properties": {
    "gn:admin1_code":"34.0",
    "gn:admin2_code":"222.0",
    "gn:asciiname":"Kohua",
    "gn:country_code":"IN",
    "gn:dem":45,
    "gn:feature_class":"P",
    "gn:feature_code":"PPL",
    "gn:name":"Kohua",
    "gn:population":0,
    "gn:timezone":"Asia/Kolkata",
    "iso:country":"IN",
    "ks:ks_name":"Kohua",
    "ks:ks_type":"VILLAGE",
    "name:eng_x_preferred":[
        "Kohua"
    ],
    "wof:name":"Kohua",
    "wof:placetype":"locality"
},
  "geometry": {"coordinates":[86.26366299999999,25.304216],"type":"Point"}
}