{
  "type": "Feature",
  "properties": {
    "iso:country":"IN",
    "ks:ks_name":"Bansora",
    "ks:ks_type":"VILLAGE",
    "name:eng_x_preferred":[
        "Bansora"
    ],
    "wof:name":"Bansora",
    "wof:placetype":"locality"
},
  "geometry": {"coordinates":[83.390685,25.920822],"type":"Point"}
}