{
  "type": "Feature",
  "properties": {
    "iso:country":"IN",
    "ks:ks_name":"Kodasalhebhat",
    "ks:ks_pop":260,
    "ks:ks_type":"VILLAGE",
    "name:eng_x_preferred":[
        "Kodasalhebhat"
    ],
    "wof:name":"Kodasalhebhat",
    "wof:placetype":"locality",
    "wof:population":260
},
  "geometry": {"coordinates":[80.941867,20.002429],"type":"Point"}
}