{
  "type": "Feature",
  "properties": {
    "gn:admin1_code":"36",
    "gn:admin2_code":"194.0",
    "gn:asciiname":"Chandpur",
    "gn:country_code":"IN",
    "gn:dem":91,
    "gn:feature_class":"P",
    "gn:feature_code":"PPL",
    "gn:name":"Ch\u0101ndpur",
    "gn:population":0,
    "gn:timezone":"Asia/Kolkata",
    "iso:country":"IN",
    "name:ben_x_preferred":[
        "\u099a\u09be\u0981\u09a6\u09aa\u09c1\u09b0"
    ],
    "name:ceb_x_preferred":[
        "Chandpur"
    ],
    "name:deu_x_preferred":[
        "Chandpur"
    ],
    "name:ita_x_preferred":[
        "Chandpur"
    ],
    "name:nld_x_preferred":[
        "Chandpur"
    ],
    "name:pol_x_preferred":[
        "Chandpur"
    ],
    "name:rus_x_preferred":[
        "\u0427\u0430\u043d\u0434\u043f\u0443\u0440"
    ],
    "name:swe_x_preferred":[
        "Chandpur"
    ],
    "wof:name":"Chandpur",
    "wof:placetype":"locality"
},
  "geometry": {"coordinates":[82.37071999999998,25.85643],"type":"Point"}
}