{
  "type": "Feature",
  "properties": {
    "iso:country":"IN",
    "ks:ks_alt_nam":"Jaisawal basti",
    "ks:ks_name":"Jaisawal Basti",
    "ks:ks_pop":275,
    "ks:ks_type":"HABITATION",
    "name:eng_x_preferred":[
        "Jaisawal Basti"
    ],
    "wof:name":"Jaisawal Basti",
    "wof:placetype":"locality",
    "wof:population":275
},
  "geometry": {"coordinates":[83.03233299999999,25.544361],"type":"Point"}
}