{
  "type": "Feature",
  "properties": {
    "gn:admin1_code":"11",
    "gn:admin2_code":"24.0",
    "gn:asciiname":"Bheth Jinkli",
    "gn:country_code":"IN",
    "gn:dem":1006,
    "gn:feature_class":"P",
    "gn:feature_code":"PPL",
    "gn:name":"Bheth Jinkli",
    "gn:population":0,
    "gn:timezone":"Asia/Kolkata",
    "iso:country":"IN",
    "wof:name":"Bheth Jinkli",
    "wof:placetype":"locality"
},
  "geometry": {"coordinates":[76.62331999999998,32.07455],"type":"Point"}
}