{
  "type": "Feature",
  "properties": {
    "iso:country":"IN",
    "ks:ks_name":"Purnadih",
    "ks:ks_pop":162,
    "ks:ks_type":"HABITATION",
    "name:eng_x_preferred":[
        "Purnadih"
    ],
    "wof:name":"Purnadih",
    "wof:placetype":"locality",
    "wof:population":162
},
  "geometry": {"coordinates":[85.763003,23.666471],"type":"Point"}
}