{
  "type": "Feature",
  "properties": {
    "iso:country":"IN",
    "ks:ks_name":"Panchudala",
    "ks:ks_pop":20,
    "ks:ks_type":"VILLAGE",
    "name:eng_x_preferred":[
        "Panchudala"
    ],
    "wof:name":"Panchudala",
    "wof:placetype":"locality",
    "wof:population":20
},
  "geometry": {"coordinates":[85.957324,21.976512],"type":"Point"}
}