{
  "type": "Feature",
  "properties": {
    "iso:country":"IN",
    "ks:ks_name":"Devi Dass",
    "ks:ks_pop":751,
    "ks:ks_type":"VILLAGE",
    "ks:ks_uagg_main":0,
    "name:eng_x_preferred":[
        "Devi Dass"
    ],
    "wof:name":"Devi Dass",
    "wof:placetype":"neighbourhood",
    "wof:population":751
},
  "geometry": {"coordinates":[75.619607,31.877258],"type":"Point"}
}