{
  "type": "Feature",
  "properties": {
    "iso:country":"IN",
    "ks:ks_alt_nam":"RADHANATH CHOW. PARA",
    "ks:ks_name":"Radhanath Chow. Para",
    "ks:ks_pop":245,
    "ks:ks_type":"HABITATION",
    "name:eng_x_preferred":[
        "Radhanath Chow. Para"
    ],
    "wof:name":"Radhanath Chow. Para",
    "wof:placetype":"locality",
    "wof:population":245
},
  "geometry": {"coordinates":[91.341628,23.54823],"type":"Point"}
}