{
  "type": "Feature",
  "properties": {
    "gn:admin1_code":"30.0",
    "gn:admin2_code":"246",
    "gn:asciiname":"Gohaintan",
    "gn:country_code":"IN",
    "gn:dem":1387,
    "gn:feature_class":"P",
    "gn:feature_code":"PPL",
    "gn:name":"Gohaintan",
    "gn:population":0,
    "gn:timezone":"Asia/Kolkata",
    "iso:country":"IN",
    "wof:name":"Gohaintan",
    "wof:placetype":"locality"
},
  "geometry": {"coordinates":[92.64838,27.24404],"type":"Point"}
}