{
  "type": "Feature",
  "properties": {
    "iso:country":"IN",
    "ks:ks_name":"Amba Bada",
    "ks:ks_pop":316,
    "ks:ks_type":"HABITATION",
    "name:eng_x_preferred":[
        "Amba Bada"
    ],
    "wof:name":"Amba Bada",
    "wof:placetype":"locality",
    "wof:population":316
},
  "geometry": {"coordinates":[74.251772,21.936642],"type":"Point"}
}