{
  "type": "Feature",
  "properties": {
    "iso:country":"IN",
    "ks:ks_name":"Babanpur",
    "ks:ks_pop":7435,
    "ks:ks_type":"VILLAGE",
    "ks:ks_uagg_main":0,
    "name:eng_x_preferred":[
        "Babanpur"
    ],
    "wof:name":"Babanpur",
    "wof:placetype":"neighbourhood",
    "wof:population":7435
},
  "geometry": {"coordinates":[88.38601300000001,22.78828],"type":"Point"}
}