{
  "type": "Feature",
  "properties": {
    "iso:country":"IN",
    "ks:ks_alt_nam":"Hemala school",
    "ks:ks_name":"Hemala School",
    "ks:ks_pop":259,
    "ks:ks_type":"HABITATION",
    "name:eng_x_preferred":[
        "Hemala School"
    ],
    "wof:name":"Hemala School",
    "wof:placetype":"locality",
    "wof:population":259
},
  "geometry": {"coordinates":[75.51242000000001,12.60577],"type":"Point"}
}