{
  "type": "Feature",
  "properties": {
    "iso:country":"IN",
    "ks:ks_alt_nam":"bandhandiha",
    "ks:ks_name":"Bandhandiha",
    "ks:ks_pop":211,
    "ks:ks_type":"HABITATION",
    "name:eng_x_preferred":[
        "Bandhandiha"
    ],
    "wof:name":"Bandhandiha",
    "wof:placetype":"locality",
    "wof:population":211
},
  "geometry": {"coordinates":[86.895511,24.231435],"type":"Point"}
}