{
  "type": "Feature",
  "properties": {
    "gn:admin1_code":"36.0",
    "gn:admin2_code":"139.0",
    "gn:asciiname":"Muzaffarpur Kamala",
    "gn:country_code":"IN",
    "gn:dem":226,
    "gn:feature_class":"P",
    "gn:feature_code":"PPL",
    "gn:name":"Muzaffarpur Kam\u0101la",
    "gn:population":0,
    "gn:timezone":"Asia/Kolkata",
    "iso:country":"IN",
    "wof:name":"Muzaffarpur Kamala",
    "wof:placetype":"locality"
},
  "geometry": {"coordinates":[77.40254,29.04498],"type":"Point"}
}