{
  "type": "Feature",
  "properties": {
    "iso:country":"IN",
    "ks:ks_name":"Kudrum",
    "ks:ks_pop":220,
    "ks:ks_type":"HABITATION",
    "name:eng_x_preferred":[
        "Kudrum"
    ],
    "wof:name":"Kudrum",
    "wof:placetype":"locality",
    "wof:population":220
},
  "geometry": {"coordinates":[84.98826099999999,22.590829],"type":"Point"}
}