{
  "type": "Feature",
  "properties": {
    "iso:country":"IN",
    "ks:ks_name":"Khopdia",
    "ks:ks_pop":105,
    "ks:ks_type":"HABITATION",
    "ks:ks_uagg_main":0,
    "name:eng_x_preferred":[
        "Khopdia"
    ],
    "wof:name":"Khopdia",
    "wof:placetype":"neighbourhood",
    "wof:population":105
},
  "geometry": {"coordinates":[91.44810699999999,25.931182],"type":"Point"}
}