{
  "type": "Feature",
  "properties": {
    "gn:admin1_code":"36",
    "gn:admin2_code":"186.0",
    "gn:asciiname":"Purwa Ghurau",
    "gn:country_code":"IN",
    "gn:dem":84,
    "gn:feature_class":"P",
    "gn:feature_code":"PPL",
    "gn:name":"Purwa Ghurau",
    "gn:population":0,
    "gn:timezone":"Asia/Kolkata",
    "iso:country":"IN",
    "wof:name":"Purwa Ghurau",
    "wof:placetype":"neighbourhood"
},
  "geometry": {"coordinates":[83.02298999999999,26.88812],"type":"Point"}
}