{
  "type": "Feature",
  "properties": {
    "iso:country":"IN",
    "ks:ks_name":"Padyar",
    "ks:ks_pop":200,
    "ks:ks_type":"HABITATION",
    "name:eng_x_preferred":[
        "Padyar"
    ],
    "wof:name":"Padyar",
    "wof:placetype":"locality",
    "wof:population":200
},
  "geometry": {"coordinates":[75.234455,12.9873],"type":"Point"}
}