{
  "type": "Feature",
  "properties": {
    "iso:country":"IN",
    "ks:ks_name":"Paskoljhora",
    "ks:ks_pop":1205,
    "ks:ks_type":"HABITATION",
    "name:eng_x_preferred":[
        "Paskoljhora"
    ],
    "wof:name":"Paskoljhora",
    "wof:placetype":"locality",
    "wof:population":1205
},
  "geometry": {"coordinates":[90.349991,26.535393],"type":"Point"}
}