{
  "type": "Feature",
  "properties": {
    "gn:admin1_code":"35",
    "gn:admin2_code":"457.0",
    "gn:asciiname":"Paraswaraghat",
    "gn:country_code":"IN",
    "gn:dem":339,
    "gn:feature_class":"P",
    "gn:feature_code":"PPL",
    "gn:name":"Parasw\u0101r\u0101gh\u0101t",
    "gn:population":0,
    "gn:timezone":"Asia/Kolkata",
    "iso:country":"IN",
    "name:und_x_variant":[
        "Parasw\u0101r\u0101gh\u0101t",
        "Parasw\u0101ragh\u0101t"
    ],
    "wof:name":"Paraswaraghat",
    "wof:placetype":"locality"
},
  "geometry": {"coordinates":[79.80265,21.66234],"type":"Point"}
}