{
  "type": "Feature",
  "properties": {
    "gn:admin1_code":"11.0",
    "gn:admin2_code":"33.0",
    "gn:asciiname":"Dharapur",
    "gn:country_code":"IN",
    "gn:dem":1317,
    "gn:feature_class":"P",
    "gn:feature_code":"PPL",
    "gn:name":"Dh\u0101rapur",
    "gn:population":0,
    "gn:timezone":"Asia/Kolkata",
    "iso:country":"IN",
    "name:bpy_x_preferred":[
        "\u09a6\u09be\u09b0\u09be\u09aa\u09c1\u09b0"
    ],
    "name:ita_x_preferred":[
        "Dharapur"
    ],
    "name:msa_x_preferred":[
        "Dharapur"
    ],
    "name:new_x_preferred":[
        "\u0927\u093e\u0930\u093e\u092a\u0941\u0930"
    ],
    "name:nld_x_preferred":[
        "Dharapur"
    ],
    "name:por_x_preferred":[
        "Dharapur"
    ],
    "name:tam_x_preferred":[
        "\u0ba4\u0bbe\u0bb0\u0bbe\u0baa\u0bcd\u0baa\u0bc2\u0bb0\u0bcd"
    ],
    "name:vie_x_preferred":[
        "Dharapur"
    ],
    "name:zho_x_preferred":[
        "\u8fbe\u62c9\u666e\u5c14"
    ],
    "wof:name":"Dharapur",
    "wof:placetype":"locality"
},
  "geometry": {"coordinates":[77.74128,31.59306],"type":"Point"}
}