{
  "type": "Feature",
  "properties": {
    "gn:admin1_code":"34.0",
    "gn:admin2_code":"236.0",
    "gn:asciiname":"Danapur",
    "gn:country_code":"IN",
    "gn:dem":208,
    "gn:feature_class":"P",
    "gn:feature_code":"PPL",
    "gn:name":"D\u0101n\u0101pur",
    "gn:population":0,
    "gn:timezone":"Asia/Kolkata",
    "iso:country":"IN",
    "ks:ks_alt_nam":"D\u0101n\u0101pur",
    "ks:ks_name":"Danapur",
    "ks:ks_type":"VILLAGE",
    "ks:ks_uagg_main":0,
    "name:bih_x_preferred":[
        "\u0926\u093e\u0928\u093e\u092a\u0941\u0930"
    ],
    "name:cat_x_preferred":[
        "Dinapur"
    ],
    "name:ceb_x_preferred":[
        "D\u0101n\u0101pur"
    ],
    "name:deu_x_preferred":[
        "Danapur"
    ],
    "name:eng_x_preferred":[
        "Danapur"
    ],
    "name:eng_x_variant":[
        "D\u0101n\u0101pur"
    ],
    "name:mar_x_preferred":[
        "\u0926\u093e\u0928\u093e\u092a\u0942\u0930"
    ],
    "name:ori_x_preferred":[
        "\u0b26\u0b3e\u0b28\u0b3e\u0b2a\u0b41\u0b30"
    ],
    "name:por_x_preferred":[
        "Dinapore"
    ],
    "name:spa_x_preferred":[
        "Danapur"
    ],
    "name:swe_x_preferred":[
        "D\u0101n\u0101pur"
    ],
    "name:tam_x_preferred":[
        "\u0ba4\u0bbe\u0ba9\u0bbe\u0baa\u0bc2\u0bb0\u0bcd"
    ],
    "name:ukr_x_preferred":[
        "\u0414\u0430\u043d\u0430\u043f\u0443\u0440"
    ],
    "name:urd_x_preferred":[
        "\u062f\u0627\u0646\u0627\u067e\u0648\u0631"
    ],
    "name:vie_x_preferred":[
        "Danapur"
    ],
    "wof:name":"Danapur",
    "wof:placetype":"neighbourhood"
},
  "geometry": {"coordinates":[84.53962,24.382664],"type":"Point"}
}