{
  "type": "Feature",
  "properties": {
    "iso:country":"IN",
    "ks:ks_name":"Thallamadugu",
    "ks:ks_pop":279,
    "ks:ks_type":"HABITATION",
    "name:eng_x_preferred":[
        "Thallamadugu"
    ],
    "wof:name":"Thallamadugu",
    "wof:placetype":"locality",
    "wof:population":279
},
  "geometry": {"coordinates":[78.96422800000001,13.15491],"type":"Point"}
}