{
  "type": "Feature",
  "properties": {
    "iso:country":"IN",
    "ks:ks_alt_nam":"Vishal nagar",
    "ks:ks_name":"Vishal Nagar",
    "ks:ks_pop":156,
    "ks:ks_type":"HABITATION",
    "name:eng_x_preferred":[
        "Vishal Nagar"
    ],
    "wof:name":"Vishal Nagar",
    "wof:placetype":"locality",
    "wof:population":156
},
  "geometry": {"coordinates":[74.819695,14.74752],"type":"Point"}
}