{
  "type": "Feature",
  "properties": {
    "gn:admin1_code":"33.0",
    "gn:admin2_code":"585.0",
    "gn:asciiname":"Onda",
    "gn:country_code":"IN",
    "gn:dem":62,
    "gn:feature_class":"P",
    "gn:feature_code":"PPL",
    "gn:name":"Onda",
    "gn:population":0,
    "gn:timezone":"Asia/Kolkata",
    "iso:country":"IN",
    "wof:name":"Onda",
    "wof:placetype":"locality"
},
  "geometry": {"coordinates":[74.05848,15.55635],"type":"Point"}
}