{
  "type": "Feature",
  "properties": {
    "iso:country":"IN",
    "ks:ks_name":"Gosai Pur",
    "ks:ks_pop":784,
    "ks:ks_type":"VILLAGE",
    "ks:ks_uagg_main":0,
    "name:eng_x_preferred":[
        "Gosai Pur"
    ],
    "wof:name":"Gosai Pur",
    "wof:placetype":"neighbourhood",
    "wof:population":784
},
  "geometry": {"coordinates":[84.19199399999999,25.915045],"type":"Point"}
}