{
  "type": "Feature",
  "properties": {
    "iso:country":"IN",
    "ks:ks_name":"Khori Lagga Rana",
    "ks:ks_pop":21,
    "ks:ks_type":"VILLAGE",
    "name:eng_x_preferred":[
        "Khori Lagga Rana"
    ],
    "wof:name":"Khori Lagga Rana",
    "wof:placetype":"locality",
    "wof:population":21
},
  "geometry": {"coordinates":[79.18012,30.298806],"type":"Point"}
}