{
  "type": "Feature",
  "properties": {
    "gn:admin1_code":"36",
    "gn:admin2_code":"179.0",
    "gn:asciiname":"Pura Shewak Sukhi",
    "gn:country_code":"IN",
    "gn:dem":109,
    "gn:feature_class":"P",
    "gn:feature_code":"PPL",
    "gn:name":"Pura Shewak Sukhi",
    "gn:population":0,
    "gn:timezone":"Asia/Kolkata",
    "iso:country":"IN",
    "wof:name":"Pura Shewak Sukhi",
    "wof:placetype":"neighbourhood"
},
  "geometry": {"coordinates":[81.69298999999999,26.36693],"type":"Point"}
}