{
  "type": "Feature",
  "properties": {
    "iso:country":"IN",
    "ks:ks_alt_nam":"Dwarka Kacharipara Pt II",
    "ks:ks_name":"Dwarka Kacharipara Pt Ii",
    "ks:ks_pop":267,
    "ks:ks_type":"HABITATION",
    "ks:ks_uagg_main":0,
    "name:eng_x_preferred":[
        "Dwarka Kacharipara Pt Ii"
    ],
    "wof:name":"Dwarka Kacharipara Pt Ii",
    "wof:placetype":"neighbourhood",
    "wof:population":267
},
  "geometry": {"coordinates":[90.500423,26.058707],"type":"Point"}
}