{
  "type": "Feature",
  "properties": {
    "iso:country":"IN",
    "ks:ks_name":"Dhangadpada",
    "ks:ks_pop":136,
    "ks:ks_type":"HABITATION",
    "name:eng_x_preferred":[
        "Dhangadpada"
    ],
    "wof:name":"Dhangadpada",
    "wof:placetype":"locality",
    "wof:population":136
},
  "geometry": {"coordinates":[73.03274500000001,19.826771],"type":"Point"}
}