{
  "type": "Feature",
  "properties": {
    "iso:country":"IN",
    "ks:ks_name":"Karnojy",
    "ks:ks_pop":80,
    "ks:ks_type":"HABITATION",
    "name:eng_x_preferred":[
        "Karnojy"
    ],
    "wof:name":"Karnojy",
    "wof:placetype":"locality",
    "wof:population":80
},
  "geometry": {"coordinates":[75.227818,12.816525],"type":"Point"}
}