{
  "type": "Feature",
  "properties": {
    "gn:admin1_code":"37.0",
    "gn:admin2_code":"409.0",
    "gn:asciiname":"Semaria",
    "gn:country_code":"IN",
    "gn:dem":302,
    "gn:feature_class":"P",
    "gn:feature_code":"PPL",
    "gn:name":"Semaria",
    "gn:population":0,
    "gn:timezone":"Asia/Kolkata",
    "iso:country":"IN",
    "wof:name":"Semaria",
    "wof:placetype":"locality"
},
  "geometry": {"coordinates":[81.20891,21.34833],"type":"Point"}
}