{
  "type": "Feature",
  "properties": {
    "iso:country":"IN",
    "ks:ks_name":"Chak Rameshwar",
    "ks:ks_pop":0,
    "ks:ks_type":"VILLAGE",
    "name:eng_x_preferred":[
        "Chak Rameshwar"
    ],
    "wof:name":"Chak Rameshwar",
    "wof:placetype":"locality",
    "wof:population":0
},
  "geometry": {"coordinates":[87.585953,22.422682],"type":"Point"}
}