{
  "type": "Feature",
  "properties": {
    "gn:admin1_code":"2",
    "gn:admin2_code":"544.0",
    "gn:asciiname":"Gandirangani",
    "gn:country_code":"IN",
    "gn:dem":1194,
    "gn:feature_class":"P",
    "gn:feature_code":"PPL",
    "gn:name":"Gandirangani",
    "gn:population":0,
    "gn:timezone":"Asia/Kolkata",
    "iso:country":"IN",
    "wof:name":"Gandirangani",
    "wof:placetype":"locality"
},
  "geometry": {"coordinates":[82.8822,18.24941],"type":"Point"}
}