{
  "type": "Feature",
  "properties": {
    "iso:country":"IN",
    "ks:ks_name":"Siddipatnam",
    "ks:ks_pop":2,
    "ks:ks_type":"HABITATION",
    "name:eng_x_preferred":[
        "Siddipatnam"
    ],
    "wof:name":"Siddipatnam",
    "wof:placetype":"locality",
    "wof:population":2
},
  "geometry": {"coordinates":[82.53326800000001,17.585376],"type":"Point"}
}