{
  "type": "Feature",
  "properties": {
    "iso:country":"IN",
    "ks:ks_name":"Biakhorowa 1",
    "ks:ks_pop":587,
    "ks:ks_type":"HABITATION",
    "ks:ks_uagg_main":0,
    "name:eng_x_preferred":[
        "Biakhorowa 1"
    ],
    "wof:name":"Biakhorowa 1",
    "wof:placetype":"neighbourhood",
    "wof:population":587
},
  "geometry": {"coordinates":[93.979148,26.331073],"type":"Point"}
}