{
  "type": "Feature",
  "properties": {
    "iso:country":"IN",
    "ks:ks_name":"Injamoorigudem",
    "ks:ks_pop":242,
    "ks:ks_type":"HABITATION",
    "name:eng_x_preferred":[
        "Injamoorigudem"
    ],
    "wof:name":"Injamoorigudem",
    "wof:placetype":"locality",
    "wof:population":242
},
  "geometry": {"coordinates":[79.71998600000001,16.836846],"type":"Point"}
}