{
  "type": "Feature",
  "properties": {
    "iso:country":"IN",
    "ks:ks_name":"Chengamari Gaon",
    "ks:ks_pop":542,
    "ks:ks_type":"VILLAGE",
    "ks:ks_uagg_main":0,
    "name:eng_x_preferred":[
        "Chengamari Gaon"
    ],
    "wof:name":"Chengamari Gaon",
    "wof:placetype":"neighbourhood",
    "wof:population":542
},
  "geometry": {"coordinates":[94.96658499999999,27.37036],"type":"Point"}
}