{
  "type": "Feature",
  "properties": {
    "iso:country":"IN",
    "ks:ks_alt_nam":"Samurs\u0101i",
    "ks:ks_name":"Samursai",
    "ks:ks_pop":439,
    "ks:ks_type":"VILLAGE",
    "ks:ks_uagg_main":0,
    "name:eng_x_preferred":[
        "Samursai"
    ],
    "name:eng_x_variant":[
        "Samurs\u0101i"
    ],
    "wof:name":"Samursai",
    "wof:placetype":"neighbourhood",
    "wof:population":439
},
  "geometry": {"coordinates":[85.727143,22.693717],"type":"Point"}
}