{
  "type": "Feature",
  "properties": {
    "iso:country":"IN",
    "ks:ks_name":"Sutola",
    "ks:ks_pop":39,
    "ks:ks_type":"VILLAGE",
    "name:eng_x_preferred":[
        "Sutola"
    ],
    "wof:name":"Sutola",
    "wof:placetype":"locality",
    "wof:population":39
},
  "geometry": {"coordinates":[80.146647,29.233897],"type":"Point"}
}