{
  "type": "Feature",
  "properties": {
    "iso:country":"IN",
    "ks:ks_name":"Maikuli",
    "ks:ks_pop":215,
    "ks:ks_type":"HABITATION",
    "name:eng_x_preferred":[
        "Maikuli"
    ],
    "wof:name":"Maikuli",
    "wof:placetype":"locality",
    "wof:population":215
},
  "geometry": {"coordinates":[75.216838,12.615105],"type":"Point"}
}