{
  "type": "Feature",
  "properties": {
    "gn:admin1_code":"19.0",
    "gn:admin2_code":"567.0",
    "gn:asciiname":"Kanchikeri",
    "gn:country_code":"IN",
    "gn:dem":627,
    "gn:feature_class":"P",
    "gn:feature_code":"PPL",
    "gn:name":"Kanchikeri",
    "gn:population":0,
    "gn:timezone":"Asia/Kolkata",
    "iso:country":"IN",
    "wof:name":"Kanchikeri",
    "wof:placetype":"locality"
},
  "geometry": {"coordinates":[75.97641,14.61515],"type":"Point"}
}