{
  "type": "Feature",
  "properties": {
    "iso:country":"IN",
    "ks:ks_name":"Kaltapara",
    "ks:ks_pop":0,
    "ks:ks_type":"VILLAGE",
    "name:eng_x_preferred":[
        "Kaltapara"
    ],
    "wof:name":"Kaltapara",
    "wof:placetype":"locality",
    "wof:population":0
},
  "geometry": {"coordinates":[88.24264700000001,24.231105],"type":"Point"}
}