{
  "type": "Feature",
  "properties": {
    "iso:country":"IN",
    "ks:ks_name":"Sukhasan",
    "ks:ks_pop":474,
    "ks:ks_type":"HABITATION",
    "name:eng_x_preferred":[
        "Sukhasan"
    ],
    "wof:name":"Sukhasan",
    "wof:placetype":"locality",
    "wof:population":474
},
  "geometry": {"coordinates":[86.45774,24.946218],"type":"Point"}
}