{
  "type": "Feature",
  "properties": {
    "iso:country":"IN",
    "ks:ks_name":"Ahardanga Tikayetpur",
    "ks:ks_pop":635,
    "ks:ks_type":"HABITATION",
    "ks:ks_uagg_main":0,
    "name:eng_x_preferred":[
        "Ahardanga Tikayetpur"
    ],
    "wof:name":"Ahardanga Tikayetpur",
    "wof:placetype":"neighbourhood",
    "wof:population":635
},
  "geometry": {"coordinates":[86.86429800000001,22.22853],"type":"Point"}
}