{
  "type": "Feature",
  "properties": {
    "iso:country":"IN",
    "ks:ks_name":"Chilakalamamidi",
    "ks:ks_pop":24,
    "ks:ks_type":"HABITATION",
    "name:eng_x_preferred":[
        "Chilakalamamidi"
    ],
    "wof:name":"Chilakalamamidi",
    "wof:placetype":"locality",
    "wof:population":24
},
  "geometry": {"coordinates":[82.53520899999999,17.964267],"type":"Point"}
}