{
  "type": "Feature",
  "properties": {
    "iso:country":"IN",
    "ks:ks_name":"Desaiwadi",
    "ks:ks_pop":252,
    "ks:ks_type":"HABITATION",
    "name:eng_x_preferred":[
        "Desaiwadi"
    ],
    "wof:name":"Desaiwadi",
    "wof:placetype":"locality",
    "wof:population":252
},
  "geometry": {"coordinates":[74.17014399999999,16.311519],"type":"Point"}
}