{
  "type": "Feature",
  "properties": {
    "iso:country":"IN",
    "ks:ks_name":"Kesogaon",
    "ks:ks_pop":272,
    "ks:ks_type":"HABITATION",
    "name:eng_x_preferred":[
        "Kesogaon"
    ],
    "wof:name":"Kesogaon",
    "wof:placetype":"locality",
    "wof:population":272
},
  "geometry": {"coordinates":[90.37917400000001,26.527681],"type":"Point"}
}