{
  "type": "Feature",
  "properties": {
    "gn:admin1_code":"36",
    "gn:admin2_code":"200.0",
    "gn:asciiname":"Pakari",
    "gn:country_code":"IN",
    "gn:dem":249,
    "gn:feature_class":"P",
    "gn:feature_code":"PPL",
    "gn:name":"Pakari",
    "gn:population":0,
    "gn:timezone":"Asia/Kolkata",
    "iso:country":"IN",
    "ks:ks_name":"Pakari",
    "ks:ks_type":"VILLAGE",
    "name:bih_x_preferred":[
        "\u092a\u0915\u0930\u0940"
    ],
    "name:ceb_x_preferred":[
        "Pakari"
    ],
    "name:eng_x_preferred":[
        "Pakari"
    ],
    "name:fra_x_preferred":[
        "Pakari"
    ],
    "name:hin_x_preferred":[
        "\u092a\u0915\u0930\u0940"
    ],
    "name:mai_x_preferred":[
        "\u092a\u0915\u0930\u0940"
    ],
    "name:msa_x_preferred":[
        "Pakari"
    ],
    "name:nep_x_preferred":[
        "\u092a\u0915\u0930\u0940"
    ],
    "name:new_x_preferred":[
        "\u092a\u0915\u0930\u0940"
    ],
    "name:pol_x_preferred":[
        "Pakari"
    ],
    "wof:name":"Pakari",
    "wof:placetype":"locality"
},
  "geometry": {"coordinates":[83.309037,24.180064],"type":"Point"}
}