{
  "type": "Feature",
  "properties": {
    "iso:country":"IN",
    "ks:ks_name":"Kirmilli",
    "ks:ks_pop":551,
    "ks:ks_type":"HABITATION",
    "name:eng_x_preferred":[
        "Kirmilli"
    ],
    "wof:name":"Kirmilli",
    "wof:placetype":"locality",
    "wof:population":551
},
  "geometry": {"coordinates":[82.536586,20.753934],"type":"Point"}
}