{
  "type": "Feature",
  "properties": {
    "iso:country":"IN",
    "ks:ks_alt_nam":"Niz-Sarabari part 2",
    "ks:ks_name":"Niz-sarabari Part 2",
    "ks:ks_pop":700,
    "ks:ks_type":"HABITATION",
    "name:eng_x_preferred":[
        "Niz-sarabari Part 2"
    ],
    "wof:name":"Niz-sarabari Part 2",
    "wof:placetype":"locality",
    "wof:population":700
},
  "geometry": {"coordinates":[91.869393,26.53456],"type":"Point"}
}