{
  "type": "Feature",
  "properties": {
    "iso:country":"IN",
    "ks:ks_name":"Paschim Raumari",
    "ks:ks_pop":187,
    "ks:ks_type":"HABITATION",
    "ks:ks_uagg_main":0,
    "name:eng_x_preferred":[
        "Paschim Raumari"
    ],
    "wof:name":"Paschim Raumari",
    "wof:placetype":"neighbourhood",
    "wof:population":187
},
  "geometry": {"coordinates":[91.43668099999999,26.633748],"type":"Point"}
}