{
  "type": "Feature",
  "properties": {
    "gn:admin1_code":"34.0",
    "gn:admin2_code":"235.0",
    "gn:asciiname":"Sitarampur",
    "gn:country_code":"IN",
    "gn:dem":110,
    "gn:feature_class":"P",
    "gn:feature_code":"PPL",
    "gn:name":"Sitar\u0101mpur",
    "gn:population":0,
    "gn:timezone":"Asia/Kolkata",
    "iso:country":"IN",
    "ks:ks_name":"Seeta Rampur",
    "ks:ks_pop":132,
    "ks:ks_type":"HABITATION",
    "name:eng_x_preferred":[
        "Seeta Rampur"
    ],
    "name:eng_x_variant":[
        "Sitarampur"
    ],
    "wof:name":"Seeta Rampur",
    "wof:placetype":"locality",
    "wof:population":132
},
  "geometry": {"coordinates":[84.316692,24.822459],"type":"Point"}
}