{
  "type": "Feature",
  "properties": {
    "gn:admin1_code":"36",
    "gn:admin2_code":"143.0",
    "gn:asciiname":"Bilochpur",
    "gn:country_code":"IN",
    "gn:dem":186,
    "gn:feature_class":"P",
    "gn:feature_code":"PPL",
    "gn:name":"Bilochpur",
    "gn:population":0,
    "gn:timezone":"Asia/Kolkata",
    "iso:country":"IN",
    "ks:ks_name":"Bilochpur",
    "ks:ks_pop":3423,
    "ks:ks_type":"VILLAGE",
    "name:eng_x_preferred":[
        "Bilochpur"
    ],
    "wof:name":"Bilochpur",
    "wof:placetype":"locality",
    "wof:population":3423
},
  "geometry": {"coordinates":[77.498374,28.034414],"type":"Point"}
}