{
  "type": "Feature",
  "properties": {
    "iso:country":"IN",
    "ks:ks_name":"Tadwadi",
    "ks:ks_pop":37,
    "ks:ks_type":"HABITATION",
    "ks:ks_uagg_main":0,
    "name:eng_x_preferred":[
        "Tadwadi"
    ],
    "wof:name":"Tadwadi",
    "wof:placetype":"neighbourhood",
    "wof:population":37
},
  "geometry": {"coordinates":[73.500072,17.430439],"type":"Point"}
}