{
  "type": "Feature",
  "properties": {
    "iso:country":"IN",
    "ks:ks_name":"Chokkanendal",
    "ks:ks_pop":246,
    "ks:ks_type":"HABITATION",
    "name:eng_x_preferred":[
        "Chokkanendal"
    ],
    "wof:name":"Chokkanendal",
    "wof:placetype":"locality",
    "wof:population":246
},
  "geometry": {"coordinates":[78.59554,9.695904],"type":"Point"}
}