{
  "type": "Feature",
  "properties": {
    "iso:country":"IN",
    "ks:ks_name":"Upadhyay",
    "ks:ks_pop":250,
    "ks:ks_type":"HABITATION",
    "name:eng_x_preferred":[
        "Upadhyay"
    ],
    "wof:name":"Upadhyay",
    "wof:placetype":"locality",
    "wof:population":250
},
  "geometry": {"coordinates":[81.38903000000001,26.448086],"type":"Point"}
}