{
  "type": "Feature",
  "properties": {
    "iso:country":"IN",
    "ks:ks_name":"Basauli Jagarnath",
    "ks:ks_pop":446,
    "ks:ks_type":"VILLAGE",
    "ks:ks_uagg_main":0,
    "name:eng_x_preferred":[
        "Basauli Jagarnath"
    ],
    "wof:name":"Basauli Jagarnath",
    "wof:placetype":"neighbourhood",
    "wof:population":446
},
  "geometry": {"coordinates":[85.449524,26.195553],"type":"Point"}
}