{
  "type": "Feature",
  "properties": {
    "gn:admin1_code":"36",
    "gn:admin2_code":"187.0",
    "gn:asciiname":"Bakhtawarpur",
    "gn:country_code":"IN",
    "gn:dem":89,
    "gn:feature_class":"P",
    "gn:feature_code":"PPL",
    "gn:name":"Bakht\u0101warpur",
    "gn:population":0,
    "gn:timezone":"Asia/Kolkata",
    "iso:country":"IN",
    "wof:name":"Bakhtawarpur",
    "wof:placetype":"neighbourhood"
},
  "geometry": {"coordinates":[83.1969,27.14766],"type":"Point"}
}