{
  "type": "Feature",
  "properties": {
    "iso:country":"IN",
    "ks:ks_alt_nam":"MANAANG",
    "ks:ks_name":"Manaang",
    "ks:ks_pop":164,
    "ks:ks_type":"HABITATION",
    "name:eng_x_preferred":[
        "Manaang"
    ],
    "wof:name":"Manaang",
    "wof:placetype":"locality",
    "wof:population":164
},
  "geometry": {"coordinates":[83.78093,22.474483],"type":"Point"}
}