{
  "type": "Feature",
  "properties": {
    "gn:admin1_code":"36",
    "gn:admin2_code":"184.0",
    "gn:asciiname":"Bangra",
    "gn:country_code":"IN",
    "gn:dem":89,
    "gn:feature_class":"P",
    "gn:feature_code":"PPL",
    "gn:name":"Bangra",
    "gn:population":0,
    "gn:timezone":"Asia/Kolkata",
    "iso:country":"IN",
    "ks:ks_name":"Bangara",
    "ks:ks_pop":790,
    "ks:ks_type":"VILLAGE",
    "name:eng_x_preferred":[
        "Bangara"
    ],
    "name:eng_x_variant":[
        "Bangra"
    ],
    "wof:name":"Bangara",
    "wof:placetype":"locality",
    "wof:population":790
},
  "geometry": {"coordinates":[83.01988900000001,27.220978],"type":"Point"}
}