{
  "type": "Feature",
  "properties": {
    "gn:admin1_code":"16",
    "gn:admin2_code":"521.0",
    "gn:asciiname":"Talegaon Dhamdhere",
    "gn:country_code":"IN",
    "gn:dem":569,
    "gn:feature_class":"P",
    "gn:feature_code":"PPL",
    "gn:name":"Talegaon Dhamdhere",
    "gn:population":0,
    "gn:timezone":"Asia/Kolkata",
    "iso:country":"IN",
    "name:ceb_x_preferred":[
        "Talegaon Dhamdhere"
    ],
    "name:swe_x_preferred":[
        "Talegaon Dhamdhere"
    ],
    "name:und_x_variant":[
        "Talegaon Dhamdhera"
    ],
    "wof:name":"Talegaon Dhamdhere",
    "wof:placetype":"locality"
},
  "geometry": {"coordinates":[74.15170999999999,18.66847000000001],"type":"Point"}
}