{
  "type": "Feature",
  "properties": {
    "gn:admin1_code":"36",
    "gn:admin2_code":"194.0",
    "gn:asciiname":"Khajurahwan",
    "gn:country_code":"IN",
    "gn:dem":90,
    "gn:feature_class":"P",
    "gn:feature_code":"PPL",
    "gn:name":"Khajurahw\u0101n",
    "gn:population":0,
    "gn:timezone":"Asia/Kolkata",
    "iso:country":"IN",
    "ks:ks_alt_nam":"Khajurahw\u0101n",
    "ks:ks_name":"Khajurahwan",
    "ks:ks_type":"VILLAGE",
    "ks:ks_uagg_main":0,
    "name:eng_x_preferred":[
        "Khajurahwan"
    ],
    "name:eng_x_variant":[
        "Khajurahw\u0101n"
    ],
    "wof:name":"Khajurahwan",
    "wof:placetype":"neighbourhood"
},
  "geometry": {"coordinates":[82.567153,25.660627],"type":"Point"}
}