{
  "type": "Feature",
  "properties": {
    "iso:country":"IN",
    "ks:ks_name":"Dhaka Tal",
    "ks:ks_pop":459,
    "ks:ks_type":"HABITATION",
    "ks:ks_uagg_main":0,
    "name:eng_x_preferred":[
        "Dhaka Tal"
    ],
    "wof:name":"Dhaka Tal",
    "wof:placetype":"neighbourhood",
    "wof:population":459
},
  "geometry": {"coordinates":[79.205563,26.603113],"type":"Point"}
}