{
  "type": "Feature",
  "properties": {
    "gn:admin1_code":"19",
    "gn:admin2_code":"562.0",
    "gn:asciiname":"Mugad",
    "gn:country_code":"IN",
    "gn:dem":706,
    "gn:feature_class":"P",
    "gn:feature_code":"PPL",
    "gn:name":"Mugad",
    "gn:population":0,
    "gn:timezone":"Asia/Kolkata",
    "iso:country":"IN",
    "wof:name":"Mugad",
    "wof:placetype":"locality"
},
  "geometry": {"coordinates":[74.91065999999999,15.44258],"type":"Point"}
}