{
  "type": "Feature",
  "properties": {
    "gn:admin1_code":"28.0",
    "gn:admin2_code":"337",
    "gn:asciiname":"Uttar Jaytara",
    "gn:country_code":"IN",
    "gn:dem":11,
    "gn:feature_class":"P",
    "gn:feature_code":"PPL",
    "gn:name":"Uttar Jayt\u0101ra",
    "gn:population":0,
    "gn:timezone":"Asia/Kolkata",
    "iso:country":"IN",
    "wof:name":"Uttar Jaytara",
    "wof:placetype":"locality"
},
  "geometry": {"coordinates":[88.69806,22.9175],"type":"Point"}
}