{
  "type": "Feature",
  "properties": {
    "iso:country":"IN",
    "ks:ks_alt_nam":"Anna colony",
    "ks:ks_name":"Anna Colony",
    "ks:ks_pop":228,
    "ks:ks_type":"HABITATION",
    "ks:ks_uagg_main":0,
    "name:eng_x_preferred":[
        "Anna Colony"
    ],
    "wof:name":"Anna Colony",
    "wof:placetype":"neighbourhood",
    "wof:population":228
},
  "geometry": {"coordinates":[77.42496800000001,8.255667],"type":"Point"}
}