{
  "type": "Feature",
  "properties": {
    "gn:admin1_code":"35",
    "gn:admin2_code":"418.0",
    "gn:asciiname":"Ochha",
    "gn:country_code":"IN",
    "gn:dem":250,
    "gn:feature_class":"P",
    "gn:feature_code":"PPL",
    "gn:name":"Ochha",
    "gn:population":0,
    "gn:timezone":"Asia/Kolkata",
    "iso:country":"IN",
    "ks:ks_name":"Ochha",
    "ks:ks_type":"VILLAGE",
    "name:eng_x_preferred":[
        "Ochha"
    ],
    "wof:name":"Ochha",
    "wof:placetype":"locality"
},
  "geometry": {"coordinates":[77.01737300000001,25.943879],"type":"Point"}
}