{
  "type": "Feature",
  "properties": {
    "iso:country":"IN",
    "ks:ks_name":"Sankainahatti",
    "ks:ks_pop":154,
    "ks:ks_type":"HABITATION",
    "name:eng_x_preferred":[
        "Sankainahatti"
    ],
    "wof:name":"Sankainahatti",
    "wof:placetype":"locality",
    "wof:population":154
},
  "geometry": {"coordinates":[76.256111,13.826667],"type":"Point"}
}