{
  "type": "Feature",
  "properties": {
    "iso:country":"IN",
    "ks:ks_name":"Masthiappan Doddy",
    "ks:ks_pop":135,
    "ks:ks_type":"HABITATION",
    "name:eng_x_preferred":[
        "Masthiappan Doddy"
    ],
    "wof:name":"Masthiappan Doddy",
    "wof:placetype":"locality",
    "wof:population":135
},
  "geometry": {"coordinates":[77.603647,12.55198],"type":"Point"}
}