{
  "type": "Feature",
  "properties": {
    "gn:admin1_code":"40.0",
    "gn:admin2_code":"539",
    "gn:asciiname":"Jangampalli",
    "gn:country_code":"IN",
    "gn:dem":483,
    "gn:feature_class":"P",
    "gn:feature_code":"PPL",
    "gn:name":"Jangampalli",
    "gn:population":0,
    "gn:timezone":"Asia/Kolkata",
    "iso:country":"IN",
    "wof:name":"Jangampalli",
    "wof:placetype":"locality"
},
  "geometry": {"coordinates":[78.87350000000001,17.61162999999999],"type":"Point"}
}