{
  "type": "Feature",
  "properties": {
    "gn:admin1_code":"19.0",
    "gn:admin2_code":"584.0",
    "gn:asciiname":"Averahalli",
    "gn:country_code":"IN",
    "gn:dem":682,
    "gn:feature_class":"P",
    "gn:feature_code":"PPL",
    "gn:name":"Averahalli",
    "gn:population":0,
    "gn:timezone":"Asia/Kolkata",
    "iso:country":"IN",
    "wof:name":"Averahalli",
    "wof:placetype":"locality"
},
  "geometry": {"coordinates":[77.10292,12.69261],"type":"Point"}
}