{
  "type": "Feature",
  "properties": {
    "iso:country":"IN",
    "ks:ks_name":"Fuliakhar",
    "ks:ks_pop":298,
    "ks:ks_type":"HABITATION",
    "name:eng_x_preferred":[
        "Fuliakhar"
    ],
    "wof:name":"Fuliakhar",
    "wof:placetype":"locality",
    "wof:population":298
},
  "geometry": {"coordinates":[84.524265,26.654835],"type":"Point"}
}