{
  "type": "Feature",
  "properties": {
    "iso:country":"IN",
    "ks:ks_name":"Devalinganapura",
    "ks:ks_pop":203,
    "ks:ks_type":"VILLAGE",
    "name:eng_x_preferred":[
        "Devalinganapura"
    ],
    "wof:name":"Devalinganapura",
    "wof:placetype":"locality",
    "wof:population":203
},
  "geometry": {"coordinates":[77.068692,12.348925],"type":"Point"}
}