{
  "type": "Feature",
  "properties": {
    "iso:country":"IN",
    "ks:ks_name":"Tanginikot",
    "ks:ks_pop":119,
    "ks:ks_type":"VILLAGE",
    "name:eng_x_preferred":[
        "Tanginikot"
    ],
    "wof:name":"Tanginikot",
    "wof:placetype":"locality",
    "wof:population":119
},
  "geometry": {"coordinates":[82.824316,19.159647],"type":"Point"}
}