{
  "type": "Feature",
  "properties": {
    "gn:admin1_code":"36.0",
    "gn:admin2_code":"137.0",
    "gn:asciiname":"Lalu Nagla",
    "gn:country_code":"IN",
    "gn:dem":216,
    "gn:feature_class":"P",
    "gn:feature_code":"PPL",
    "gn:name":"L\u0101lu Nagla",
    "gn:population":0,
    "gn:timezone":"Asia/Kolkata",
    "iso:country":"IN",
    "ks:ks_alt_nam":"L\u0101lu Nagla",
    "ks:ks_name":"Lalu Nagla",
    "ks:ks_type":"VILLAGE",
    "ks:ks_uagg_main":0,
    "name:eng_x_preferred":[
        "Lalu Nagla"
    ],
    "name:eng_x_variant":[
        "L\u0101lu Nagla"
    ],
    "wof:name":"Lalu Nagla",
    "wof:placetype":"neighbourhood"
},
  "geometry": {"coordinates":[78.510728,28.962985],"type":"Point"}
}