{
  "type": "Feature",
  "properties": {
    "iso:country":"IN",
    "ks:ks_name":"Huryaldand",
    "ks:ks_pop":181,
    "ks:ks_type":"VILLAGE",
    "name:eng_x_preferred":[
        "Huryaldand"
    ],
    "wof:name":"Huryaldand",
    "wof:placetype":"locality",
    "wof:population":181
},
  "geometry": {"coordinates":[80.438507,20.476843],"type":"Point"}
}