{
  "type": "Feature",
  "properties": {
    "iso:country":"IN",
    "ks:ks_name":"Tukura 1",
    "ks:ks_pop":1366,
    "ks:ks_type":"HABITATION",
    "name:eng_x_preferred":[
        "Tukura 1"
    ],
    "wof:name":"Tukura 1",
    "wof:placetype":"locality",
    "wof:population":1366
},
  "geometry": {"coordinates":[90.632553,26.073414],"type":"Point"}
}