{
  "type": "Feature",
  "properties": {
    "iso:country":"IN",
    "ks:ks_name":"Sanakarei",
    "ks:ks_pop":661,
    "ks:ks_type":"VILLAGE",
    "name:eng_x_preferred":[
        "Sanakarei"
    ],
    "wof:name":"Sanakarei",
    "wof:placetype":"locality",
    "wof:population":661
},
  "geometry": {"coordinates":[85.367706,21.585469],"type":"Point"}
}