{
  "type": "Feature",
  "properties": {
    "iso:country":"IN",
    "ks:ks_alt_nam":"Subhash colony",
    "ks:ks_name":"Subhash Colony",
    "ks:ks_pop":180,
    "ks:ks_type":"HABITATION",
    "name:eng_x_preferred":[
        "Subhash Colony"
    ],
    "wof:name":"Subhash Colony",
    "wof:placetype":"locality",
    "wof:population":180
},
  "geometry": {"coordinates":[76.31304299999999,12.267476],"type":"Point"}
}