{
  "type": "Feature",
  "properties": {
    "iso:country":"IN",
    "ks:ks_name":"Thuraipadu",
    "ks:ks_pop":81,
    "ks:ks_type":"HABITATION",
    "name:eng_x_preferred":[
        "Thuraipadu"
    ],
    "wof:name":"Thuraipadu",
    "wof:placetype":"locality",
    "wof:population":81
},
  "geometry": {"coordinates":[83.118049,18.626186],"type":"Point"}
}