{
  "type": "Feature",
  "properties": {
    "iso:country":"IN",
    "ks:ks_name":"Gangavanewasti",
    "ks:ks_pop":300,
    "ks:ks_type":"HABITATION",
    "name:eng_x_preferred":[
        "Gangavanewasti"
    ],
    "wof:name":"Gangavanewasti",
    "wof:placetype":"locality",
    "wof:population":300
},
  "geometry": {"coordinates":[74.968636,18.691144],"type":"Point"}
}