{
  "type": "Feature",
  "properties": {
    "iso:country":"IN",
    "ks:ks_name":"Pillakkurichi",
    "ks:ks_pop":323,
    "ks:ks_type":"HABITATION",
    "name:eng_x_preferred":[
        "Pillakkurichi"
    ],
    "wof:name":"Pillakkurichi",
    "wof:placetype":"locality",
    "wof:population":323
},
  "geometry": {"coordinates":[79.167563,10.448739],"type":"Point"}
}