{
  "type": "Feature",
  "properties": {
    "iso:country":"IN",
    "ks:ks_name":"Darima Jhumarpara",
    "ks:ks_pop":721,
    "ks:ks_type":"HABITATION",
    "name:eng_x_preferred":[
        "Darima Jhumarpara"
    ],
    "wof:name":"Darima Jhumarpara",
    "wof:placetype":"locality",
    "wof:population":721
},
  "geometry": {"coordinates":[83.19757199999999,23.017911],"type":"Point"}
}