{
  "type": "Feature",
  "properties": {
    "iso:country":"IN",
    "ks:ks_name":"Dilli Terang",
    "ks:ks_pop":107,
    "ks:ks_type":"HABITATION",
    "name:eng_x_preferred":[
        "Dilli Terang"
    ],
    "wof:name":"Dilli Terang",
    "wof:placetype":"locality",
    "wof:population":107
},
  "geometry": {"coordinates":[93.375753,25.92455],"type":"Point"}
}