{
  "type": "Feature",
  "properties": {
    "iso:country":"IN",
    "ks:ks_alt_nam":"N.Lehara",
    "ks:ks_name":"N.lehara",
    "ks:ks_pop":348,
    "ks:ks_type":"HABITATION",
    "name:eng_x_preferred":[
        "N.lehara"
    ],
    "wof:name":"N.lehara",
    "wof:placetype":"locality",
    "wof:population":348
},
  "geometry": {"coordinates":[78.69041300000001,27.587309],"type":"Point"}
}