{
  "type": "Feature",
  "properties": {
    "gn:admin1_code":"24.0",
    "gn:admin2_code":"125.0",
    "gn:asciiname":"Pando",
    "gn:country_code":"IN",
    "gn:dem":393,
    "gn:feature_class":"P",
    "gn:feature_code":"PPL",
    "gn:name":"Pando",
    "gn:population":0,
    "gn:timezone":"Asia/Kolkata",
    "iso:country":"IN",
    "name:ast_x_preferred":[
        "Pando"
    ],
    "name:cat_x_preferred":[
        "Pando"
    ],
    "name:ceb_x_preferred":[
        "Pando"
    ],
    "name:deu_x_preferred":[
        "Pando"
    ],
    "name:epo_x_preferred":[
        "Pando"
    ],
    "name:eus_x_preferred":[
        "Pando"
    ],
    "name:fra_x_preferred":[
        "Pando"
    ],
    "name:glg_x_preferred":[
        "Pando"
    ],
    "name:hrv_x_preferred":[
        "Pando"
    ],
    "name:ita_x_preferred":[
        "Pando"
    ],
    "name:kor_x_preferred":[
        "\ud310\ub3c4"
    ],
    "name:nld_x_preferred":[
        "Pando"
    ],
    "name:rus_x_preferred":[
        "\u041f\u0430\u043d\u0434\u043e"
    ],
    "name:spa_x_preferred":[
        "Pando"
    ],
    "name:swe_x_preferred":[
        "Pando"
    ],
    "name:ukr_x_preferred":[
        "\u041f\u0430\u043d\u0434\u043e"
    ],
    "wof:name":"Pando",
    "wof:placetype":"locality"
},
  "geometry": {"coordinates":[74.67553000000002,23.22067],"type":"Point"}
}