{
  "type": "Feature",
  "properties": {
    "gn:admin1_code":"36",
    "gn:admin2_code":"189.0",
    "gn:asciiname":"Pakri",
    "gn:country_code":"IN",
    "gn:dem":87,
    "gn:feature_class":"P",
    "gn:feature_code":"PPL",
    "gn:name":"Pakri",
    "gn:population":0,
    "gn:timezone":"Asia/Kolkata",
    "iso:country":"IN",
    "name:est_x_preferred":[
        "Pakri"
    ],
    "name:lav_x_preferred":[
        "Pakri"
    ],
    "wof:name":"Pakri",
    "wof:placetype":"locality"
},
  "geometry": {"coordinates":[83.68485,26.83876],"type":"Point"}
}