{
  "type": "Feature",
  "properties": {
    "iso:country":"IN",
    "ks:ks_name":"Rongo",
    "ks:ks_pop":919,
    "ks:ks_type":"VILLAGE",
    "name:eng_x_preferred":[
        "Rongo"
    ],
    "wof:name":"Rongo",
    "wof:placetype":"locality",
    "wof:population":919
},
  "geometry": {"coordinates":[85.273917,22.404503],"type":"Point"}
}