{
  "type": "Feature",
  "properties": {
    "iso:country":"IN",
    "ks:ks_name":"Dudhpaniya",
    "ks:ks_pop":57,
    "ks:ks_type":"HABITATION",
    "name:eng_x_preferred":[
        "Dudhpaniya"
    ],
    "wof:name":"Dudhpaniya",
    "wof:placetype":"locality",
    "wof:population":57
},
  "geometry": {"coordinates":[86.226136,24.047977],"type":"Point"}
}