{
  "type": "Feature",
  "properties": {
    "gn:admin1_code":"21",
    "gn:admin2_code":"396.0",
    "gn:asciiname":"Gundriguda",
    "gn:country_code":"IN",
    "gn:dem":405,
    "gn:feature_class":"P",
    "gn:feature_code":"PPL",
    "gn:name":"Gundriguda",
    "gn:population":0,
    "gn:timezone":"Asia/Kolkata",
    "iso:country":"IN",
    "ks:ks_name":"Gundriguda",
    "ks:ks_type":"VILLAGE",
    "name:eng_x_preferred":[
        "Gundriguda"
    ],
    "wof:name":"Gundriguda",
    "wof:placetype":"locality"
},
  "geometry": {"coordinates":[83.564655,19.792713],"type":"Point"}
}