{
  "type": "Feature",
  "properties": {
    "iso:country":"IN",
    "ks:ks_name":"Koodallor",
    "ks:ks_pop":1475,
    "ks:ks_type":"HABITATION",
    "name:eng_x_preferred":[
        "Koodallor"
    ],
    "wof:name":"Koodallor",
    "wof:placetype":"locality",
    "wof:population":1475
},
  "geometry": {"coordinates":[76.07881500000001,10.832658],"type":"Point"}
}