{
  "type": "Feature",
  "properties": {
    "gn:admin1_code":"28.0",
    "gn:admin2_code":"329.0",
    "gn:asciiname":"Palika",
    "gn:country_code":"IN",
    "gn:dem":42,
    "gn:feature_class":"P",
    "gn:feature_code":"PPL",
    "gn:name":"P\u0101lika",
    "gn:population":0,
    "gn:timezone":"Asia/Kolkata",
    "iso:country":"IN",
    "ks:ks_alt_nam":"P\u0101lika",
    "ks:ks_name":"Palika",
    "ks:ks_pop":2445,
    "ks:ks_type":"VILLAGE",
    "name:eng_x_preferred":[
        "Palika"
    ],
    "name:eng_x_variant":[
        "P\u0101lika"
    ],
    "wof:name":"Palika",
    "wof:placetype":"locality",
    "wof:population":2445
},
  "geometry": {"coordinates":[89.750153,26.361939],"type":"Point"}
}