{
  "type": "Feature",
  "properties": {
    "gn:admin1_code":"25.0",
    "gn:admin2_code":"602.0",
    "gn:asciiname":"Gaunipuramsubbarajukhandriga",
    "gn:country_code":"IN",
    "gn:dem":166,
    "gn:feature_class":"P",
    "gn:feature_code":"PPL",
    "gn:name":"Gaunipuramsubbar\u0101jukhandriga",
    "gn:population":0,
    "gn:timezone":"Asia/Kolkata",
    "iso:country":"IN",
    "wof:name":"Gaunipuramsubbarajukhandriga",
    "wof:placetype":"locality"
},
  "geometry": {"coordinates":[79.47394,13.20479],"type":"Point"}
}