{
  "type": "Feature",
  "properties": {
    "gn:admin1_code":"17.0",
    "gn:admin2_code":"273.0",
    "gn:asciiname":"Teikhang",
    "gn:country_code":"IN",
    "gn:dem":841,
    "gn:feature_class":"P",
    "gn:feature_code":"PPL",
    "gn:name":"Teikhang",
    "gn:population":0,
    "gn:timezone":"Asia/Kolkata",
    "iso:country":"IN",
    "wof:name":"Teikhang",
    "wof:placetype":"locality"
},
  "geometry": {"coordinates":[93.37371,24.59472],"type":"Point"}
}