{
  "type": "Feature",
  "properties": {
    "iso:country":"IN",
    "ks:ks_name":"Peethas",
    "ks:ks_pop":1329,
    "ks:ks_type":"VILLAGE",
    "name:eng_x_preferred":[
        "Peethas"
    ],
    "wof:name":"Peethas",
    "wof:placetype":"locality",
    "wof:population":1329
},
  "geometry": {"coordinates":[74.794856,25.269578],"type":"Point"}
}