{
  "type": "Feature",
  "properties": {
    "gn:admin1_code":"12.0",
    "gn:admin2_code":"18.0",
    "gn:asciiname":"Oungi Baihk",
    "gn:country_code":"IN",
    "gn:dem":2896,
    "gn:feature_class":"P",
    "gn:feature_code":"PPL",
    "gn:name":"Oungi Baihk",
    "gn:population":0,
    "gn:timezone":"Asia/Kolkata",
    "iso:country":"IN",
    "wof:name":"Oungi Baihk",
    "wof:placetype":"locality"
},
  "geometry": {"coordinates":[75.54179999999999,33.43042],"type":"Point"}
}