{
  "type": "Feature",
  "properties": {
    "iso:country":"IN",
    "ks:ks_name":"Jagamohan",
    "ks:ks_pop":2228,
    "ks:ks_type":"VILLAGE",
    "name:eng_x_preferred":[
        "Jagamohan"
    ],
    "wof:name":"Jagamohan",
    "wof:placetype":"locality",
    "wof:population":2228
},
  "geometry": {"coordinates":[84.597719,19.653057],"type":"Point"}
}