{
  "type": "Feature",
  "properties": {
    "iso:country":"IN",
    "ks:ks_name":"Totapada",
    "ks:ks_pop":349,
    "ks:ks_type":"VILLAGE",
    "ks:ks_uagg_main":0,
    "name:eng_x_preferred":[
        "Totapada"
    ],
    "wof:name":"Totapada",
    "wof:placetype":"neighbourhood",
    "wof:population":349
},
  "geometry": {"coordinates":[86.146017,20.410088],"type":"Point"}
}