{
  "type": "Feature",
  "properties": {
    "gn:admin1_code":"36",
    "gn:admin2_code":"162.0",
    "gn:asciiname":"Marhaiyan",
    "gn:country_code":"IN",
    "gn:dem":138,
    "gn:feature_class":"P",
    "gn:feature_code":"PPL",
    "gn:name":"Marhaiy\u0101n",
    "gn:population":0,
    "gn:timezone":"Asia/Kolkata",
    "iso:country":"IN",
    "ks:ks_alt_nam":"Marhaiy\u0101n",
    "ks:ks_name":"Marhaiyan",
    "ks:ks_type":"VILLAGE",
    "name:eng_x_preferred":[
        "Marhaiyan"
    ],
    "name:eng_x_variant":[
        "Marhaiy\u0101n"
    ],
    "wof:name":"Marhaiyan",
    "wof:placetype":"locality"
},
  "geometry": {"coordinates":[79.51429,26.424074],"type":"Point"}
}