{
  "type": "Feature",
  "properties": {
    "iso:country":"IN",
    "ks:ks_alt_nam":"Dhunia basti",
    "ks:ks_name":"Dhunia Basti",
    "ks:ks_pop":124,
    "ks:ks_type":"HABITATION",
    "name:eng_x_preferred":[
        "Dhunia Basti"
    ],
    "wof:name":"Dhunia Basti",
    "wof:placetype":"locality",
    "wof:population":124
},
  "geometry": {"coordinates":[82.740324,25.394597],"type":"Point"}
}