{
  "type": "Feature",
  "properties": {
    "iso:country":"IN",
    "name:ast_x_preferred":[
        "Irumbai"
    ],
    "name:azb_x_preferred":[
        "\u0627\u06cc\u0631\u0648\u0645\u0628\u0627\u06cc"
    ],
    "name:eng_x_preferred":[
        "Irumbai"
    ],
    "name:nld_x_preferred":[
        "Irumbai"
    ],
    "qs:name":"Irumbai",
    "qs:name_adm0":"India",
    "qs:name_adm1":"Tamil Nadu",
    "qs:photos":3410,
    "qs:photos_1k":691,
    "qs:photos_9k":15,
    "qs:photos_9r":11,
    "qs:photos_all":3410,
    "qs:photos_sr":20,
    "qs:placetype":"Town",
    "qs:pop_sr":"0",
    "wd:wordcount":75,
    "wof:name":"Irumbai",
    "wof:placetype":"neighbourhood"
},
  "geometry": {"coordinates":[79.804344,12.001459],"type":"Point"}
}