{
  "type": "Feature",
  "properties": {
    "gn:admin1_code":"12.0",
    "gn:admin2_code":"006",
    "gn:asciiname":"Kalajhang",
    "gn:country_code":"IN",
    "gn:dem":580,
    "gn:feature_class":"P",
    "gn:feature_code":"PPL",
    "gn:name":"Kalajhang",
    "gn:population":0,
    "gn:timezone":"Asia/Kolkata",
    "iso:country":"IN",
    "wof:name":"Kalajhang",
    "wof:placetype":"locality"
},
  "geometry": {"coordinates":[74.42222,33.11111],"type":"Point"}
}