{
  "type": "Feature",
  "properties": {
    "gn:admin1_code":"12.0",
    "gn:admin2_code":"1.0",
    "gn:asciiname":"Sedori",
    "gn:country_code":"IN",
    "gn:dem":1724,
    "gn:feature_class":"P",
    "gn:feature_code":"PPL",
    "gn:name":"Sedori",
    "gn:population":0,
    "gn:timezone":"Asia/Kolkata",
    "iso:country":"IN",
    "wof:name":"Sedori",
    "wof:placetype":"locality"
},
  "geometry": {"coordinates":[74.39849,34.51685],"type":"Point"}
}