{
  "type": "Feature",
  "properties": {
    "iso:country":"IN",
    "ks:ks_name":"Sipty",
    "ks:ks_pop":507,
    "ks:ks_type":"VILLAGE",
    "name:eng_x_preferred":[
        "Sipty"
    ],
    "wof:name":"Sipty",
    "wof:placetype":"locality",
    "wof:population":507
},
  "geometry": {"coordinates":[80.01567,29.309573],"type":"Point"}
}