{
  "type": "Feature",
  "properties": {
    "iso:country":"IN",
    "ks:ks_name":"Jamuna Purwa",
    "ks:ks_pop":121,
    "ks:ks_type":"HABITATION",
    "name:eng_x_preferred":[
        "Jamuna Purwa"
    ],
    "wof:name":"Jamuna Purwa",
    "wof:placetype":"locality",
    "wof:population":121
},
  "geometry": {"coordinates":[81.776381,27.254228],"type":"Point"}
}