{
  "type": "Feature",
  "properties": {
    "iso:country":"IN",
    "ks:ks_name":"Goran",
    "ks:ks_pop":122,
    "ks:ks_type":"HABITATION",
    "name:eng_x_preferred":[
        "Goran"
    ],
    "wof:name":"Goran",
    "wof:placetype":"locality",
    "wof:population":122
},
  "geometry": {"coordinates":[78.713933,30.02633],"type":"Point"}
}