{
  "type": "Feature",
  "properties": {
    "gn:admin1_code":"23",
    "gn:admin2_code":"35.0",
    "gn:asciiname":"Saidowal",
    "gn:country_code":"IN",
    "gn:dem":239,
    "gn:feature_class":"P",
    "gn:feature_code":"PPL",
    "gn:name":"Saidowal",
    "gn:population":0,
    "gn:timezone":"Asia/Kolkata",
    "iso:country":"IN",
    "ks:ks_name":"Saidowal",
    "ks:ks_pop":304,
    "ks:ks_type":"VILLAGE",
    "name:eng_x_preferred":[
        "Saidowal"
    ],
    "name:urd_x_preferred":[
        "\u0633\u06cc\u062f\u0648\u0648\u0627\u0644"
    ],
    "wof:name":"Saidowal",
    "wof:placetype":"locality",
    "wof:population":304
},
  "geometry": {"coordinates":[75.569024,31.824046],"type":"Point"}
}