{
  "type": "Feature",
  "properties": {
    "gn:admin1_code":"23",
    "gn:admin2_code":"35.0",
    "gn:asciiname":"Saidowal",
    "gn:country_code":"IN",
    "gn:dem":239,
    "gn:feature_class":"P",
    "gn:feature_code":"PPL",
    "gn:name":"Saidowal",
    "gn:population":0,
    "gn:timezone":"Asia/Kolkata",
    "iso:country":"IN",
    "wof:name":"Saidowal",
    "wof:placetype":"locality"
},
  "geometry": {"coordinates":[75.56961,31.82314],"type":"Point"}
}