{
  "type": "Feature",
  "properties": {
    "iso:country":"IN",
    "ks:ks_name":"Lekotoli",
    "ks:ks_pop":145,
    "ks:ks_type":"HABITATION",
    "ks:ks_uagg_main":0,
    "name:eng_x_preferred":[
        "Lekotoli"
    ],
    "wof:name":"Lekotoli",
    "wof:placetype":"neighbourhood",
    "wof:population":145
},
  "geometry": {"coordinates":[84.899658,23.233715],"type":"Point"}
}