{
  "type": "Feature",
  "properties": {
    "iso:country":"IN",
    "ks:ks_name":"Hardibahra Khas",
    "ks:ks_pop":1057,
    "ks:ks_type":"HABITATION",
    "name:eng_x_preferred":[
        "Hardibahra Khas"
    ],
    "wof:name":"Hardibahra Khas",
    "wof:placetype":"locality",
    "wof:population":1057
},
  "geometry": {"coordinates":[82.78837,23.900623],"type":"Point"}
}