{
  "type": "Feature",
  "properties": {
    "iso:country":"IN",
    "ks:ks_name":"Hatvada Fa",
    "ks:ks_pop":135,
    "ks:ks_type":"HABITATION",
    "name:eng_x_preferred":[
        "Hatvada Fa"
    ],
    "wof:name":"Hatvada Fa",
    "wof:placetype":"locality",
    "wof:population":135
},
  "geometry": {"coordinates":[72.991028,20.481667],"type":"Point"}
}