{
  "type": "Feature",
  "properties": {
    "iso:country":"IN",
    "ks:ks_name":"Alsabettu Akabettu",
    "ks:ks_pop":249,
    "ks:ks_type":"HABITATION",
    "name:eng_x_preferred":[
        "Alsabettu Akabettu"
    ],
    "wof:name":"Alsabettu Akabettu",
    "wof:placetype":"locality",
    "wof:population":249
},
  "geometry": {"coordinates":[74.70452400000001,13.459381],"type":"Point"}
}