{
  "type": "Feature",
  "properties": {
    "gn:admin1_code":"24.0",
    "gn:admin2_code":"123",
    "gn:asciiname":"Baneriya",
    "gn:country_code":"IN",
    "gn:dem":528,
    "gn:feature_class":"P",
    "gn:feature_code":"PPL",
    "gn:name":"Baneriya",
    "gn:population":0,
    "gn:timezone":"Asia/Kolkata",
    "iso:country":"IN",
    "name:und_x_variant":[
        "Baneria"
    ],
    "wof:name":"Baneriya",
    "wof:placetype":"locality"
},
  "geometry": {"coordinates":[74.01738,24.94983],"type":"Point"}
}