{
  "type": "Feature",
  "properties": {
    "gn:admin1_code":"19.0",
    "gn:admin2_code":"568.0",
    "gn:asciiname":"Hullatti",
    "gn:country_code":"IN",
    "gn:dem":701,
    "gn:feature_class":"P",
    "gn:feature_code":"PPL",
    "gn:name":"Hullatti",
    "gn:population":0,
    "gn:timezone":"Asia/Kolkata",
    "iso:country":"IN",
    "wof:name":"Hullatti",
    "wof:placetype":"locality"
},
  "geometry": {"coordinates":[75.26541999999998,13.81071],"type":"Point"}
}