{
  "type": "Feature",
  "properties": {
    "iso:country":"IN",
    "ks:ks_name":"Vandandi",
    "ks:ks_pop":305,
    "ks:ks_type":"HABITATION",
    "name:eng_x_preferred":[
        "Vandandi"
    ],
    "wof:name":"Vandandi",
    "wof:placetype":"locality",
    "wof:population":305
},
  "geometry": {"coordinates":[79.237831,10.781713],"type":"Point"}
}