{
  "type": "Feature",
  "properties": {
    "gn:admin1_code":"2",
    "gn:admin2_code":"544.0",
    "gn:asciiname":"Bhimaram",
    "gn:country_code":"IN",
    "gn:dem":1191,
    "gn:feature_class":"P",
    "gn:feature_code":"PPL",
    "gn:name":"Bhimaram",
    "gn:population":0,
    "gn:timezone":"Asia/Kolkata",
    "iso:country":"IN",
    "wof:name":"Bhimaram",
    "wof:placetype":"locality"
},
  "geometry": {"coordinates":[82.75376999999997,18.1291],"type":"Point"}
}