{
  "type": "Feature",
  "properties": {
    "iso:country":"IN",
    "ks:ks_name":"Gubar Dhan Chuk",
    "ks:ks_pop":654,
    "ks:ks_type":"HABITATION",
    "name:eng_x_preferred":[
        "Gubar Dhan Chuk"
    ],
    "wof:name":"Gubar Dhan Chuk",
    "wof:placetype":"locality",
    "wof:population":654
},
  "geometry": {"coordinates":[95.265968,27.143726],"type":"Point"}
}