{
  "type": "Feature",
  "properties": {
    "iso:country":"IN",
    "ks:ks_name":"Gaikwadwasti",
    "ks:ks_pop":173,
    "ks:ks_type":"HABITATION",
    "name:eng_x_preferred":[
        "Gaikwadwasti"
    ],
    "wof:name":"Gaikwadwasti",
    "wof:placetype":"locality",
    "wof:population":173
},
  "geometry": {"coordinates":[74.487928,17.512332],"type":"Point"}
}