{
  "type": "Feature",
  "properties": {
    "iso:country":"IN",
    "ks:ks_name":"Anaikoundanur",
    "ks:ks_pop":295,
    "ks:ks_type":"HABITATION",
    "ks:ks_uagg_main":0,
    "name:eng_x_preferred":[
        "Anaikoundanur"
    ],
    "wof:name":"Anaikoundanur",
    "wof:placetype":"neighbourhood",
    "wof:population":295
},
  "geometry": {"coordinates":[78.39764,10.869108],"type":"Point"}
}