{
  "type": "Feature",
  "properties": {
    "iso:country":"IN",
    "ks:ks_name":"Choutaki II",
    "ks:ks_pop":1042,
    "ks:ks_type":"VILLAGE",
    "name:eng_x_preferred":[
        "Choutaki II"
    ],
    "wof:name":"Choutaki II",
    "wof:placetype":"locality",
    "wof:population":1042
},
  "geometry": {"coordinates":[90.347314,26.462441],"type":"Point"}
}