{
  "type": "Feature",
  "properties": {
    "iso:country":"IN",
    "ks:ks_name":"Naakar Rampur",
    "ks:ks_pop":401,
    "ks:ks_type":"VILLAGE",
    "ks:ks_uagg_main":0,
    "name:eng_x_preferred":[
        "Naakar Rampur"
    ],
    "wof:name":"Naakar Rampur",
    "wof:placetype":"locality",
    "wof:population":401
},
  "geometry": {"coordinates":[84.039441,27.195123],"type":"Point"}
}