{
  "type": "Feature",
  "properties": {
    "iso:country":"IN",
    "ks:ks_name":"Badatrilochan Pur",
    "ks:ks_pop":1054,
    "ks:ks_type":"VILLAGE",
    "name:eng_x_preferred":[
        "Badatrilochan Pur"
    ],
    "wof:name":"Badatrilochan Pur",
    "wof:placetype":"locality",
    "wof:population":1054
},
  "geometry": {"coordinates":[86.285904,20.853839],"type":"Point"}
}