{
  "type": "Feature",
  "properties": {
    "iso:country":"IN",
    "ks:ks_name":"Koeri Tola",
    "ks:ks_pop":254,
    "ks:ks_type":"HABITATION",
    "name:eng_x_preferred":[
        "Koeri Tola"
    ],
    "wof:name":"Koeri Tola",
    "wof:placetype":"locality",
    "wof:population":254
},
  "geometry": {"coordinates":[83.95698299999999,25.799367],"type":"Point"}
}