{
  "type": "Feature",
  "properties": {
    "iso:country":"IN",
    "ks:ks_name":"Deokhera",
    "ks:ks_pop":686,
    "ks:ks_type":"HABITATION",
    "name:eng_x_preferred":[
        "Deokhera"
    ],
    "wof:name":"Deokhera",
    "wof:placetype":"locality",
    "wof:population":686
},
  "geometry": {"coordinates":[75.123214,25.819497],"type":"Point"}
}