{
  "type": "Feature",
  "properties": {
    "iso:country":"IN",
    "ks:ks_name":"Luhasing",
    "ks:ks_pop":257,
    "ks:ks_type":"VILLAGE",
    "name:eng_x_preferred":[
        "Luhasing"
    ],
    "wof:name":"Luhasing",
    "wof:placetype":"locality",
    "wof:population":257
},
  "geometry": {"coordinates":[84.069683,19.15801],"type":"Point"}
}