{
  "type": "Feature",
  "properties": {
    "iso:country":"IN",
    "ks:ks_name":"Puliyoor",
    "ks:ks_pop":510,
    "ks:ks_type":"HABITATION",
    "ks:ks_uagg_main":0,
    "name:eng_x_preferred":[
        "Puliyoor"
    ],
    "wof:name":"Puliyoor",
    "wof:placetype":"neighbourhood",
    "wof:population":510
},
  "geometry": {"coordinates":[77.022379,8.706758],"type":"Point"}
}