{
  "type": "Feature",
  "properties": {
    "iso:country":"IN",
    "ks:ks_name":"Saray Neel Kanth Khas",
    "ks:ks_pop":261,
    "ks:ks_type":"HABITATION",
    "ks:ks_uagg_main":0,
    "name:eng_x_preferred":[
        "Saray Neel Kanth Khas"
    ],
    "wof:name":"Saray Neel Kanth Khas",
    "wof:placetype":"neighbourhood",
    "wof:population":261
},
  "geometry": {"coordinates":[82.955721,26.484496],"type":"Point"}
}