{
  "type": "Feature",
  "properties": {
    "gn:admin1_code":"11",
    "gn:admin2_code":"23.0",
    "gn:asciiname":"Devi Debna",
    "gn:country_code":"IN",
    "gn:dem":1789,
    "gn:feature_class":"P",
    "gn:feature_code":"PPL",
    "gn:name":"Devi Debna",
    "gn:population":0,
    "gn:timezone":"Asia/Kolkata",
    "iso:country":"IN",
    "wof:name":"Devi Debna",
    "wof:placetype":"locality"
},
  "geometry": {"coordinates":[76.07316,32.50438],"type":"Point"}
}