{
  "type": "Feature",
  "properties": {
    "iso:country":"IN",
    "ks:ks_name":"Kalya Chak",
    "ks:ks_pop":1280,
    "ks:ks_type":"VILLAGE",
    "ks:ks_uagg_main":0,
    "name:eng_x_preferred":[
        "Kalya Chak"
    ],
    "wof:name":"Kalya Chak",
    "wof:placetype":"neighbourhood",
    "wof:population":1280
},
  "geometry": {"coordinates":[87.79165399999999,21.983394],"type":"Point"}
}