{
  "type": "Feature",
  "properties": {
    "iso:country":"IN",
    "ks:ks_alt_nam":"P\u016bnandgaon",
    "ks:ks_name":"Punandgaon",
    "ks:ks_type":"VILLAGE",
    "name:eng_x_preferred":[
        "Punandgaon"
    ],
    "name:eng_x_variant":[
        "P\u016bnandgaon"
    ],
    "wof:name":"Punandgaon",
    "wof:placetype":"locality"
},
  "geometry": {"coordinates":[76.137835,19.125822],"type":"Point"}
}