{
  "type": "Feature",
  "properties": {
    "iso:country":"IN",
    "ks:ks_alt_nam":"KALAKHILA",
    "ks:ks_name":"Kalakhila",
    "ks:ks_pop":151,
    "ks:ks_type":"HABITATION",
    "name:eng_x_preferred":[
        "Kalakhila"
    ],
    "wof:name":"Kalakhila",
    "wof:placetype":"locality",
    "wof:population":151
},
  "geometry": {"coordinates":[74.812062,17.301308],"type":"Point"}
}