{
  "type": "Feature",
  "properties": {
    "iso:country":"IN",
    "ks:ks_name":"Siswan",
    "ks:ks_pop":323,
    "ks:ks_type":"VILLAGE",
    "ks:ks_uagg_main":0,
    "name:eng_x_preferred":[
        "Siswan"
    ],
    "wof:name":"Siswan",
    "wof:placetype":"neighbourhood",
    "wof:population":323
},
  "geometry": {"coordinates":[85.077658,26.296366],"type":"Point"}
}