{
  "type": "Feature",
  "properties": {
    "iso:country":"IN",
    "ks:ks_name":"Anegundi",
    "ks:ks_pop":24,
    "ks:ks_type":"HABITATION",
    "name:eng_x_preferred":[
        "Anegundi"
    ],
    "wof:name":"Anegundi",
    "wof:placetype":"locality",
    "wof:population":24
},
  "geometry": {"coordinates":[74.887485,14.843748],"type":"Point"}
}