{
  "type": "Feature",
  "properties": {
    "gn:admin1_code":"2.0",
    "gn:admin2_code":"543.0",
    "gn:asciiname":"Kittalapadu",
    "gn:country_code":"IN",
    "gn:dem":138,
    "gn:feature_class":"P",
    "gn:feature_code":"PPL",
    "gn:name":"Kittalap\u0101du",
    "gn:population":0,
    "gn:timezone":"Asia/Kolkata",
    "iso:country":"IN",
    "ks:ks_alt_nam":"KILTHAPADU",
    "ks:ks_name":"Kilthapadu",
    "ks:ks_pop":118,
    "ks:ks_type":"HABITATION",
    "name:eng_x_preferred":[
        "Kilthapadu"
    ],
    "name:eng_x_variant":[
        "Kittalapadu"
    ],
    "wof:name":"Kilthapadu",
    "wof:placetype":"locality",
    "wof:population":118
},
  "geometry": {"coordinates":[83.601918,18.835977],"type":"Point"}
}