{
  "type": "Feature",
  "properties": {
    "gn:admin1_code":"11.0",
    "gn:admin2_code":"33.0",
    "gn:asciiname":"Damiyan",
    "gn:country_code":"IN",
    "gn:dem":1870,
    "gn:feature_class":"P",
    "gn:feature_code":"PPL",
    "gn:name":"Damiy\u0101n",
    "gn:population":0,
    "gn:timezone":"Asia/Kolkata",
    "iso:country":"IN",
    "wof:name":"Damiyan",
    "wof:placetype":"locality"
},
  "geometry": {"coordinates":[77.29249,31.11718],"type":"Point"}
}