{
  "type": "Feature",
  "properties": {
    "gn:admin1_code":"23.0",
    "gn:admin2_code":"053",
    "gn:asciiname":"Sati",
    "gn:country_code":"IN",
    "gn:dem":252,
    "gn:feature_class":"P",
    "gn:feature_code":"PPL",
    "gn:name":"Sati",
    "gn:population":0,
    "gn:timezone":"Asia/Kolkata",
    "iso:country":"IN",
    "wof:name":"Sati",
    "wof:placetype":"locality"
},
  "geometry": {"coordinates":[76.00227,30.59025],"type":"Point"}
}