{
  "type": "Feature",
  "properties": {
    "iso:country":"IN",
    "ks:ks_name":"Rankinipur",
    "ks:ks_pop":3285,
    "ks:ks_type":"VILLAGE",
    "ks:ks_uagg_main":0,
    "name:eng_x_preferred":[
        "Rankinipur"
    ],
    "wof:name":"Rankinipur",
    "wof:placetype":"neighbourhood",
    "wof:population":3285
},
  "geometry": {"coordinates":[87.88104300000001,21.997233],"type":"Point"}
}