{
  "type": "Feature",
  "properties": {
    "iso:country":"IN",
    "ks:ks_name":"Charak Kala",
    "ks:ks_pop":652,
    "ks:ks_type":"VILLAGE",
    "name:eng_x_preferred":[
        "Charak Kala"
    ],
    "wof:name":"Charak Kala",
    "wof:placetype":"locality",
    "wof:population":652
},
  "geometry": {"coordinates":[86.400949,24.03492],"type":"Point"}
}