{
  "type": "Feature",
  "properties": {
    "iso:country":"IN",
    "ks:ks_name":"Jhari",
    "ks:ks_pop":238,
    "ks:ks_type":"VILLAGE",
    "name:eng_x_preferred":[
        "Jhari"
    ],
    "wof:name":"Jhari",
    "wof:placetype":"locality",
    "wof:population":238
},
  "geometry": {"coordinates":[73.906083,20.825556],"type":"Point"}
}