{
  "type": "Feature",
  "properties": {
    "gn:admin1_code":"24.0",
    "gn:admin2_code":"125.0",
    "gn:asciiname":"Morjhira",
    "gn:country_code":"IN",
    "gn:dem":419,
    "gn:feature_class":"P",
    "gn:feature_code":"PPL",
    "gn:name":"Morjhira",
    "gn:population":0,
    "gn:timezone":"Asia/Kolkata",
    "iso:country":"IN",
    "ks:ks_name":"Morjhari",
    "ks:ks_pop":1185,
    "ks:ks_type":"VILLAGE",
    "name:eng_x_preferred":[
        "Morjhari"
    ],
    "name:eng_x_variant":[
        "Morjhira"
    ],
    "wof:name":"Morjhari",
    "wof:placetype":"locality",
    "wof:population":1185
},
  "geometry": {"coordinates":[74.65321900000001,23.22205],"type":"Point"}
}