{
  "type": "Feature",
  "properties": {
    "iso:country":"IN",
    "ks:ks_alt_nam":"Nellimattom east",
    "ks:ks_name":"Nellimattom East",
    "ks:ks_pop":1033,
    "ks:ks_type":"HABITATION",
    "name:eng_x_preferred":[
        "Nellimattom East"
    ],
    "wof:name":"Nellimattom East",
    "wof:placetype":"locality",
    "wof:population":1033
},
  "geometry": {"coordinates":[76.688304,10.047228],"type":"Point"}
}