{
  "type": "Feature",
  "properties": {
    "iso:country":"IN",
    "ks:ks_name":"Telimala",
    "ks:ks_pop":2,
    "ks:ks_type":"HABITATION",
    "name:eng_x_preferred":[
        "Telimala"
    ],
    "wof:name":"Telimala",
    "wof:placetype":"locality",
    "wof:population":2
},
  "geometry": {"coordinates":[84.892641,19.706972],"type":"Point"}
}