{
  "type": "Feature",
  "properties": {
    "iso:country":"IN",
    "ks:ks_name":"Munasabpeta",
    "ks:ks_pop":150,
    "ks:ks_type":"HABITATION",
    "name:eng_x_preferred":[
        "Munasabpeta"
    ],
    "wof:name":"Munasabpeta",
    "wof:placetype":"locality",
    "wof:population":150
},
  "geometry": {"coordinates":[84.250899,18.588071],"type":"Point"}
}