{
  "type": "Feature",
  "properties": {
    "iso:country":"IN",
    "ks:ks_name":"Hanspura",
    "ks:ks_pop":0,
    "ks:ks_type":"VILLAGE",
    "name:eng_x_preferred":[
        "Hanspura"
    ],
    "wof:name":"Hanspura",
    "wof:placetype":"locality",
    "wof:population":0
},
  "geometry": {"coordinates":[74.894616,24.516607],"type":"Point"}
}