{
  "type": "Feature",
  "properties": {
    "gn:admin1_code":"2.0",
    "gn:admin2_code":"543.0",
    "gn:asciiname":"Rayadupeta",
    "gn:country_code":"IN",
    "gn:dem":21,
    "gn:feature_class":"P",
    "gn:feature_code":"PPL",
    "gn:name":"R\u0101yadupeta",
    "gn:population":0,
    "gn:timezone":"Asia/Kolkata",
    "iso:country":"IN",
    "ks:ks_name":"Raydupeta",
    "ks:ks_pop":640,
    "ks:ks_type":"HABITATION",
    "name:eng_x_preferred":[
        "Raydupeta"
    ],
    "name:eng_x_variant":[
        "Rayadupeta"
    ],
    "wof:name":"Raydupeta",
    "wof:placetype":"locality",
    "wof:population":640
},
  "geometry": {"coordinates":[83.614762,18.054132],"type":"Point"}
}