{
  "type": "Feature",
  "properties": {
    "gn:admin1_code":"10",
    "gn:admin2_code":"87.0",
    "gn:asciiname":"Bikti",
    "gn:country_code":"IN",
    "gn:dem":187,
    "gn:feature_class":"P",
    "gn:feature_code":"PPL",
    "gn:name":"Bikti",
    "gn:population":0,
    "gn:timezone":"Asia/Kolkata",
    "iso:country":"IN",
    "wof:name":"Bikti",
    "wof:placetype":"locality"
},
  "geometry": {"coordinates":[77.23777,27.78841],"type":"Point"}
}