{
  "type": "Feature",
  "properties": {
    "iso:country":"IN",
    "ks:ks_name":"Nai Basti",
    "ks:ks_pop":42,
    "ks:ks_type":"HABITATION",
    "name:eng_x_preferred":[
        "Nai Basti"
    ],
    "wof:name":"Nai Basti",
    "wof:placetype":"locality",
    "wof:population":42
},
  "geometry": {"coordinates":[83.467769,26.326405],"type":"Point"}
}