{
  "type": "Feature",
  "properties": {
    "iso:country":"IN",
    "ks:ks_alt_nam":"Musht\u0101qnagar",
    "ks:ks_name":"Mushtaqnagar",
    "ks:ks_type":"VILLAGE",
    "name:eng_x_preferred":[
        "Mushtaqnagar"
    ],
    "name:eng_x_variant":[
        "Musht\u0101qnagar"
    ],
    "wof:name":"Mushtaqnagar",
    "wof:placetype":"locality"
},
  "geometry": {"coordinates":[79.900713,26.057293],"type":"Point"}
}