{
  "type": "Feature",
  "properties": {
    "iso:country":"IN",
    "ks:ks_name":"Kharmora",
    "ks:ks_pop":809,
    "ks:ks_type":"HABITATION",
    "name:eng_x_preferred":[
        "Kharmora"
    ],
    "wof:name":"Kharmora",
    "wof:placetype":"locality",
    "wof:population":809
},
  "geometry": {"coordinates":[80.214158,24.1303],"type":"Point"}
}