{
  "type": "Feature",
  "properties": {
    "iso:country":"IN",
    "ks:ks_name":"Jamgaon",
    "ks:ks_pop":56,
    "ks:ks_type":"HABITATION",
    "name:eng_x_preferred":[
        "Jamgaon"
    ],
    "wof:name":"Jamgaon",
    "wof:placetype":"locality",
    "wof:population":56
},
  "geometry": {"coordinates":[79.087881,19.702647],"type":"Point"}
}