{
  "type": "Feature",
  "properties": {
    "iso:country":"IN",
    "ks:ks_name":"Husnapur",
    "ks:ks_pop":26,
    "ks:ks_type":"HABITATION",
    "name:eng_x_preferred":[
        "Husnapur"
    ],
    "wof:name":"Husnapur",
    "wof:placetype":"locality",
    "wof:population":26
},
  "geometry": {"coordinates":[77.748487,20.320828],"type":"Point"}
}