{
  "type": "Feature",
  "properties": {
    "iso:country":"IN",
    "ks:ks_name":"Panjraj Singh Ki Dhani",
    "ks:ks_pop":103,
    "ks:ks_type":"HABITATION",
    "name:eng_x_preferred":[
        "Panjraj Singh Ki Dhani"
    ],
    "wof:name":"Panjraj Singh Ki Dhani",
    "wof:placetype":"locality",
    "wof:population":103
},
  "geometry": {"coordinates":[71.296328,26.257853],"type":"Point"}
}