{
  "type": "Feature",
  "properties": {
    "iso:country":"IN",
    "ks:ks_name":"Salepal",
    "ks:ks_pop":46,
    "ks:ks_type":"HABITATION",
    "name:eng_x_preferred":[
        "Salepal"
    ],
    "wof:name":"Salepal",
    "wof:placetype":"locality",
    "wof:population":46
},
  "geometry": {"coordinates":[74.440884,14.312964],"type":"Point"}
}