{
  "type": "Feature",
  "properties": {
    "iso:country":"IN",
    "ks:ks_alt_nam":"OJHA TOLI",
    "ks:ks_name":"Ojha Toli",
    "ks:ks_pop":160,
    "ks:ks_type":"HABITATION",
    "name:eng_x_preferred":[
        "Ojha Toli"
    ],
    "wof:name":"Ojha Toli",
    "wof:placetype":"locality",
    "wof:population":160
},
  "geometry": {"coordinates":[84.820976,26.230034],"type":"Point"}
}