{
  "type": "Feature",
  "properties": {
    "iso:country":"IN",
    "ks:ks_name":"Boladka",
    "ks:ks_pop":21,
    "ks:ks_type":"HABITATION",
    "name:eng_x_preferred":[
        "Boladka"
    ],
    "wof:name":"Boladka",
    "wof:placetype":"locality",
    "wof:population":21
},
  "geometry": {"coordinates":[75.549632,12.692769],"type":"Point"}
}