{
  "type": "Feature",
  "properties": {
    "gn:admin1_code":"36.0",
    "gn:admin2_code":"195.0",
    "gn:asciiname":"Birbhanpur",
    "gn:country_code":"IN",
    "gn:dem":71,
    "gn:feature_class":"P",
    "gn:feature_code":"PPL",
    "gn:name":"Birbh\u0101npur",
    "gn:population":0,
    "gn:timezone":"Asia/Kolkata",
    "iso:country":"IN",
    "name:urd_x_preferred":[
        "\u0628\u0631\u0628\u06be\u0627\u0646 \u067e\u0648\u0631"
    ],
    "wof:name":"Birbhanpur",
    "wof:placetype":"neighbourhood"
},
  "geometry": {"coordinates":[83.73963999999999,25.73003],"type":"Point"}
}