{
  "type": "Feature",
  "properties": {
    "gn:admin1_code":"24.0",
    "gn:admin2_code":"123.0",
    "gn:asciiname":"Malikmoria",
    "gn:country_code":"IN",
    "gn:dem":577,
    "gn:feature_class":"P",
    "gn:feature_code":"PPL",
    "gn:name":"M\u0101likmoria",
    "gn:population":0,
    "gn:timezone":"Asia/Kolkata",
    "iso:country":"IN",
    "wof:name":"Malikmoria",
    "wof:placetype":"locality"
},
  "geometry": {"coordinates":[74.05306999999998,25.59975],"type":"Point"}
}