{
  "type": "Feature",
  "properties": {
    "iso:country":"IN",
    "ks:ks_name":"Kadamdhar",
    "ks:ks_pop":143,
    "ks:ks_type":"HABITATION",
    "name:eng_x_preferred":[
        "Kadamdhar"
    ],
    "wof:name":"Kadamdhar",
    "wof:placetype":"locality",
    "wof:population":143
},
  "geometry": {"coordinates":[84.779777,21.456253],"type":"Point"}
}