{
  "type": "Feature",
  "properties": {
    "iso:country":"IN",
    "ks:ks_name":"Saranda",
    "ks:ks_pop":1272,
    "ks:ks_type":"VILLAGE",
    "ks:ks_uagg_main":0,
    "name:eng_x_preferred":[
        "Saranda"
    ],
    "wof:name":"Saranda",
    "wof:placetype":"neighbourhood",
    "wof:population":1272
},
  "geometry": {"coordinates":[85.981022,24.218822],"type":"Point"}
}