{
  "type": "Feature",
  "properties": {
    "iso:country":"IN",
    "ks:ks_name":"Bagha",
    "ks:ks_type":"VILLAGE",
    "name:eng_x_preferred":[
        "Bagha"
    ],
    "wof:name":"Bagha",
    "wof:placetype":"locality"
},
  "geometry": {"coordinates":[80.430514,27.975329],"type":"Point"}
}