{
  "type": "Feature",
  "properties": {
    "iso:country":"IN",
    "ks:ks_name":"Jamdih Alias Haramagara",
    "ks:ks_pop":1287,
    "ks:ks_type":"VILLAGE",
    "name:eng_x_preferred":[
        "Jamdih Alias Haramagara"
    ],
    "wof:name":"Jamdih Alias Haramagara",
    "wof:placetype":"locality",
    "wof:population":1287
},
  "geometry": {"coordinates":[84.042179,23.536689],"type":"Point"}
}