{
  "type": "Feature",
  "properties": {
    "iso:country":"IN",
    "ks:ks_name":"Yanadi Wada",
    "ks:ks_pop":298,
    "ks:ks_type":"HABITATION",
    "ks:ks_uagg_main":0,
    "name:eng_x_preferred":[
        "Yanadi Wada"
    ],
    "wof:name":"Yanadi Wada",
    "wof:placetype":"neighbourhood",
    "wof:population":298
},
  "geometry": {"coordinates":[79.29181699999999,14.23232],"type":"Point"}
}