{
  "type": "Feature",
  "properties": {
    "gn:admin1_code":"36",
    "gn:admin2_code":"189.0",
    "gn:asciiname":"Belwa",
    "gn:country_code":"IN",
    "gn:dem":87,
    "gn:feature_class":"P",
    "gn:feature_code":"PPL",
    "gn:name":"Belwa",
    "gn:population":0,
    "gn:timezone":"Asia/Kolkata",
    "iso:country":"IN",
    "wof:name":"Belwa",
    "wof:placetype":"locality"
},
  "geometry": {"coordinates":[83.57998000000001,26.82181],"type":"Point"}
}