{
  "type": "Feature",
  "properties": {
    "gn:admin1_code":"35",
    "gn:admin2_code":"429.0",
    "gn:asciiname":"Poria",
    "gn:country_code":"IN",
    "gn:dem":369,
    "gn:feature_class":"P",
    "gn:feature_code":"PPL",
    "gn:name":"Poria",
    "gn:population":0,
    "gn:timezone":"Asia/Kolkata",
    "iso:country":"IN",
    "name:ceb_x_preferred":[
        "Poria"
    ],
    "name:swe_x_preferred":[
        "Poria"
    ],
    "wof:name":"Poria",
    "wof:placetype":"locality"
},
  "geometry": {"coordinates":[81.07939,24.19477],"type":"Point"}
}