{
  "type": "Feature",
  "properties": {
    "gn:admin1_code":"34.0",
    "gn:admin2_code":"210.0",
    "gn:asciiname":"Khajurbari",
    "gn:country_code":"IN",
    "gn:dem":62,
    "gn:feature_class":"P",
    "gn:feature_code":"PPL",
    "gn:name":"Khaj\u016brb\u0101ri",
    "gn:population":0,
    "gn:timezone":"Asia/Kolkata",
    "iso:country":"IN",
    "ks:ks_name":"Khajuribari",
    "ks:ks_pop":1118,
    "ks:ks_type":"VILLAGE",
    "ks:ks_uagg_main":0,
    "name:eng_x_preferred":[
        "Khajuribari"
    ],
    "wof:name":"Khajuribari",
    "wof:placetype":"neighbourhood",
    "wof:population":1118
},
  "geometry": {"coordinates":[87.662009,26.31694],"type":"Point"}
}