{
  "type": "Feature",
  "properties": {
    "iso:country":"IN",
    "ks:ks_alt_nam":"Kheml\u0101",
    "ks:ks_alt_nam_2":"Khemla",
    "ks:ks_name":"Khemela",
    "ks:ks_pop":0,
    "ks:ks_type":"VILLAGE",
    "name:eng_x_preferred":[
        "Khemela"
    ],
    "name:eng_x_variant":[
        "Kheml\u0101",
        "Khemla"
    ],
    "wof:name":"Khemela",
    "wof:placetype":"locality",
    "wof:population":0
},
  "geometry": {"coordinates":[85.04991,21.307494],"type":"Point"}
}