{
  "type": "Feature",
  "properties": {
    "iso:country":"IN",
    "ks:ks_name":"Tirang",
    "ks:ks_pop":254,
    "ks:ks_type":"HABITATION",
    "name:eng_x_preferred":[
        "Tirang"
    ],
    "wof:name":"Tirang",
    "wof:placetype":"locality",
    "wof:population":254
},
  "geometry": {"coordinates":[90.646086,25.961593],"type":"Point"}
}