{
  "type": "Feature",
  "properties": {
    "gn:admin1_code":"19.0",
    "gn:asciiname":"Devarmole",
    "gn:country_code":"IN",
    "gn:dem":6,
    "gn:feature_class":"P",
    "gn:feature_code":"PPL",
    "gn:name":"Devarmole",
    "gn:population":0,
    "gn:timezone":"Asia/Kolkata",
    "iso:country":"IN",
    "ks:ks_name":"Devarmote",
    "ks:ks_pop":105,
    "ks:ks_type":"HABITATION",
    "name:eng_x_preferred":[
        "Devarmote"
    ],
    "name:eng_x_variant":[
        "Devarmole"
    ],
    "wof:name":"Devarmote",
    "wof:placetype":"locality",
    "wof:population":105
},
  "geometry": {"coordinates":[74.477225,14.277727],"type":"Point"}
}