{
  "type": "Feature",
  "properties": {
    "iso:country":"IN",
    "ks:ks_name":"Andharbadi",
    "ks:ks_pop":41,
    "ks:ks_type":"HABITATION",
    "name:eng_x_preferred":[
        "Andharbadi"
    ],
    "wof:name":"Andharbadi",
    "wof:placetype":"locality",
    "wof:population":41
},
  "geometry": {"coordinates":[84.48968000000001,20.341819],"type":"Point"}
}