{
  "type": "Feature",
  "properties": {
    "iso:country":"IN",
    "ks:ks_alt_nam":"Naugaw\u0101n Brahman\u0101n",
    "ks:ks_name":"Naugawan Brahmanan",
    "ks:ks_type":"VILLAGE",
    "name:eng_x_preferred":[
        "Naugawan Brahmanan"
    ],
    "name:eng_x_variant":[
        "Naugaw\u0101n Brahman\u0101n"
    ],
    "wof:name":"Naugawan Brahmanan",
    "wof:placetype":"locality"
},
  "geometry": {"coordinates":[79.260856,28.379546],"type":"Point"}
}