{
  "type": "Feature",
  "properties": {
    "gn:admin1_code":"39.0",
    "gn:admin2_code":"64.0",
    "gn:asciiname":"Chhanadaryan",
    "gn:country_code":"IN",
    "gn:dem":1343,
    "gn:feature_class":"P",
    "gn:feature_code":"PPL",
    "gn:name":"Chh\u0101n\u0101daryan",
    "gn:population":0,
    "gn:timezone":"Asia/Kolkata",
    "iso:country":"IN",
    "wof:name":"Chhanadaryan",
    "wof:placetype":"locality"
},
  "geometry": {"coordinates":[79.5703,29.65941],"type":"Point"}
}