{
  "type": "Feature",
  "properties": {
    "iso:country":"IN",
    "ks:ks_name":"Newada",
    "ks:ks_pop":50,
    "ks:ks_type":"HABITATION",
    "name:eng_x_preferred":[
        "Newada"
    ],
    "wof:name":"Newada",
    "wof:placetype":"locality",
    "wof:population":50
},
  "geometry": {"coordinates":[82.73942099999999,25.315141],"type":"Point"}
}