{
  "type": "Feature",
  "properties": {
    "iso:country":"IN",
    "ks:ks_name":"Barigundi",
    "ks:ks_pop":30,
    "ks:ks_type":"HABITATION",
    "name:eng_x_preferred":[
        "Barigundi"
    ],
    "wof:name":"Barigundi",
    "wof:placetype":"locality",
    "wof:population":30
},
  "geometry": {"coordinates":[74.983096,13.898772],"type":"Point"}
}