{
  "type": "Feature",
  "properties": {
    "iso:country":"IN",
    "ks:ks_name":"Banauli",
    "ks:ks_pop":1740,
    "ks:ks_type":"VILLAGE",
    "ks:ks_uagg_main":0,
    "name:eng_x_preferred":[
        "Banauli"
    ],
    "wof:name":"Banauli",
    "wof:placetype":"neighbourhood",
    "wof:population":1740
},
  "geometry": {"coordinates":[85.704836,26.647122],"type":"Point"}
}