{
  "type": "Feature",
  "properties": {
    "gn:admin1_code":"35.0",
    "gn:asciiname":"Mau",
    "gn:country_code":"IN",
    "gn:dem":145,
    "gn:feature_class":"P",
    "gn:feature_code":"PPL",
    "gn:name":"Mau",
    "gn:population":0,
    "gn:timezone":"Asia/Kolkata",
    "iso:country":"IN",
    "name:azb_x_preferred":[
        "\u0645\u0627\u0648"
    ],
    "name:cat_x_preferred":[
        "Mau"
    ],
    "name:ceb_x_preferred":[
        "Mau"
    ],
    "name:deu_x_preferred":[
        "Mau"
    ],
    "name:fas_x_preferred":[
        "\u0645\u0627\u0648"
    ],
    "name:fra_x_preferred":[
        "Mau"
    ],
    "name:hin_x_preferred":[
        "\u092e\u090a"
    ],
    "name:ita_x_preferred":[
        "Mau"
    ],
    "name:msa_x_preferred":[
        "Mau"
    ],
    "name:nld_x_preferred":[
        "Mau"
    ],
    "name:pnb_x_preferred":[
        "\u0645\u0626\u0648"
    ],
    "name:pol_x_preferred":[
        "Mau"
    ],
    "name:por_x_preferred":[
        "Maunath Bhanjan"
    ],
    "name:rus_x_preferred":[
        "\u041c\u0430\u0443"
    ],
    "name:san_x_preferred":[
        "\u092e\u0935\u0941"
    ],
    "name:srp_x_preferred":[
        "\u041c\u0430\u0443"
    ],
    "name:swe_x_preferred":[
        "Maunath Bhanjan"
    ],
    "name:urd_x_preferred":[
        "\u0645\u0626\u0648"
    ],
    "name:vie_x_preferred":[
        "Maunath Bhanjan"
    ],
    "name:war_x_preferred":[
        "Mau"
    ],
    "name:zho_x_preferred":[
        "\u6bdb\u7eb3\u7279\u73ed\u8a79"
    ],
    "wof:name":"Mau",
    "wof:placetype":"locality"
},
  "geometry": {"coordinates":[78.98411,26.0459],"type":"Point"}
}