{
  "type": "Feature",
  "properties": {
    "gn:admin1_code":"35.0",
    "gn:admin2_code":"450.0",
    "gn:asciiname":"Bareli",
    "gn:country_code":"IN",
    "gn:dem":405,
    "gn:feature_class":"P",
    "gn:feature_code":"PPL",
    "gn:name":"Bar\u0113li",
    "gn:population":0,
    "gn:timezone":"Asia/Kolkata",
    "iso:country":"IN",
    "ks:ks_alt_nam":"Bar\u0113li",
    "ks:ks_name":"Bareli",
    "ks:ks_pop":817,
    "ks:ks_type":"VILLAGE",
    "ks:ks_uagg_main":0,
    "name:ceb_x_preferred":[
        "Bareli"
    ],
    "name:eng_x_preferred":[
        "Bareli"
    ],
    "name:eng_x_variant":[
        "Bar\u0113li"
    ],
    "name:fin_x_preferred":[
        "Bareli"
    ],
    "name:swe_x_preferred":[
        "Bareli"
    ],
    "wof:name":"Bareli",
    "wof:placetype":"neighbourhood",
    "wof:population":817
},
  "geometry": {"coordinates":[80.24507199999999,23.543697],"type":"Point"}
}