{
  "type": "Feature",
  "properties": {
    "gn:admin1_code":"16.0",
    "gn:admin2_code":"508.0",
    "gn:asciiname":"Belgutta",
    "gn:country_code":"IN",
    "gn:dem":225,
    "gn:feature_class":"P",
    "gn:feature_code":"PPL",
    "gn:name":"Belgutta",
    "gn:population":0,
    "gn:timezone":"Asia/Kolkata",
    "iso:country":"IN",
    "ks:ks_name":"Belgutta",
    "ks:ks_type":"VILLAGE",
    "name:eng_x_preferred":[
        "Belgutta"
    ],
    "wof:name":"Belgutta",
    "wof:placetype":"locality"
},
  "geometry": {"coordinates":[79.97350299999999,19.845144],"type":"Point"}
}