{
  "type": "Feature",
  "properties": {
    "iso:country":"IN",
    "ks:ks_name":"Baraipur Urf Parauli",
    "ks:ks_pop":217,
    "ks:ks_type":"VILLAGE",
    "ks:ks_uagg_main":0,
    "name:eng_x_preferred":[
        "Baraipur Urf Parauli"
    ],
    "wof:name":"Baraipur Urf Parauli",
    "wof:placetype":"neighbourhood",
    "wof:population":217
},
  "geometry": {"coordinates":[83.349756,26.39005],"type":"Point"}
}