{
  "type": "Feature",
  "properties": {
    "gn:country":"IN",
    "gn:fcode":"PPL",
    "gn:population":8282,
    "iso:country":"IN",
    "name:ben_x_preferred":[
        "\u09ac\u09be\u09b2\u09a6\u09c7\u0993\u0997\u09a1\u09bc"
    ],
    "name:bpy_x_preferred":[
        "\u09ac\u09be\u09b2\u09a6\u09c7\u0993\u0997\u09a1\u09bc"
    ],
    "name:bul_x_preferred":[
        "\u0411\u0430\u043b\u0434\u0435\u043e\u0433\u0430\u0440\u0445"
    ],
    "name:ceb_x_preferred":[
        "Baldeogarh"
    ],
    "name:eng_x_preferred":[
        "Baldeogarh"
    ],
    "name:fra_x_preferred":[
        "Baldeogarh"
    ],
    "name:ita_x_preferred":[
        "Baldeogarh"
    ],
    "name:msa_x_preferred":[
        "Baldeogarh"
    ],
    "name:nan_x_preferred":[
        "Baldeogarh"
    ],
    "name:new_x_preferred":[
        "\u092c\u0932\u0926\u0947\u0935\u0917\u0922"
    ],
    "name:nld_x_preferred":[
        "Baldeogarh"
    ],
    "name:por_x_preferred":[
        "Baldeogarh"
    ],
    "name:spa_x_preferred":[
        "Baldeogarh"
    ],
    "name:swe_x_preferred":[
        "Baldeogarh"
    ],
    "name:vie_x_preferred":[
        "Baldeogarh"
    ],
    "name:zho_x_preferred":[
        "\u5df4\u5c14\u5fb7\u5965\u52a0\u5c14"
    ],
    "qs:name":"Baldeogarh",
    "qs:name_adm0":"India",
    "qs:name_adm1":"Madhya Pradesh",
    "qs:photos_9r":0,
    "qs:photos_sr":0,
    "qs:placetype":"Town",
    "qs:pop_sr":"5",
    "wd:wordcount":214,
    "wof:name":"Baldeogarh",
    "wof:placetype":"locality",
    "wof:population":8282
},
  "geometry": {"coordinates":[79.06715,24.75619],"type":"Point"}
}