{
  "type": "Feature",
  "properties": {
    "iso:country":"IN",
    "ks:ks_name":"Basudevpur",
    "ks:ks_pop":168,
    "ks:ks_type":"VILLAGE",
    "ks:ks_uagg_main":0,
    "name:eng_x_preferred":[
        "Basudevpur"
    ],
    "wof:name":"Basudevpur",
    "wof:placetype":"neighbourhood",
    "wof:population":168
},
  "geometry": {"coordinates":[86.88495399999999,21.6248],"type":"Point"}
}