{
  "type": "Feature",
  "properties": {
    "iso:country":"IN",
    "ks:ks_name":"Kurur Raulipar",
    "ks:ks_pop":121,
    "ks:ks_type":"VILLAGE",
    "name:eng_x_preferred":[
        "Kurur Raulipar"
    ],
    "wof:name":"Kurur Raulipar",
    "wof:placetype":"locality",
    "wof:population":121
},
  "geometry": {"coordinates":[79.44241100000001,30.278949],"type":"Point"}
}