{
  "type": "Feature",
  "properties": {
    "iso:country":"IN",
    "ks:ks_alt_nam":"VASANTMALI WASTI",
    "ks:ks_name":"Vasantmali Wasti",
    "ks:ks_pop":140,
    "ks:ks_type":"HABITATION",
    "name:eng_x_preferred":[
        "Vasantmali Wasti"
    ],
    "wof:name":"Vasantmali Wasti",
    "wof:placetype":"locality",
    "wof:population":140
},
  "geometry": {"coordinates":[74.479697,17.331284],"type":"Point"}
}