{
  "type": "Feature",
  "properties": {
    "iso:country":"IN",
    "ks:ks_name":"Thenari",
    "ks:ks_pop":1010,
    "ks:ks_type":"HABITATION",
    "ks:ks_uagg_main":0,
    "name:eng_x_preferred":[
        "Thenari"
    ],
    "wof:name":"Thenari",
    "wof:placetype":"neighbourhood",
    "wof:population":1010
},
  "geometry": {"coordinates":[76.744519,10.781718],"type":"Point"}
}