{
  "type": "Feature",
  "properties": {
    "iso:country":"IN",
    "ks:ks_name":"Dharampur Saravagi",
    "ks:ks_pop":1745,
    "ks:ks_type":"VILLAGE",
    "name:eng_x_preferred":[
        "Dharampur Saravagi"
    ],
    "wof:name":"Dharampur Saravagi",
    "wof:placetype":"locality",
    "wof:population":1745
},
  "geometry": {"coordinates":[77.62433299999999,29.762696],"type":"Point"}
}