{
  "type": "Feature",
  "properties": {
    "gn:admin1_code":"10.0",
    "gn:admin2_code":"070",
    "gn:asciiname":"Abdullahgarh",
    "gn:country_code":"IN",
    "gn:dem":268,
    "gn:feature_class":"P",
    "gn:feature_code":"PPL",
    "gn:name":"Abdull\u0101hgarh",
    "gn:population":0,
    "gn:timezone":"Asia/Kolkata",
    "iso:country":"IN",
    "ks:ks_name":"Abdulgarh",
    "ks:ks_pop":515,
    "ks:ks_type":"VILLAGE",
    "name:eng_x_preferred":[
        "Abdulgarh"
    ],
    "name:eng_x_variant":[
        "Abdullahgarh"
    ],
    "wof:name":"Abdulgarh",
    "wof:placetype":"locality",
    "wof:population":515
},
  "geometry": {"coordinates":[76.947991,30.170904],"type":"Point"}
}