{
  "type": "Feature",
  "properties": {
    "gn:admin1_code":"24.0",
    "gn:admin2_code":"104.0",
    "gn:asciiname":"Dabla Meo",
    "gn:country_code":"IN",
    "gn:dem":304,
    "gn:feature_class":"P",
    "gn:feature_code":"PPL",
    "gn:name":"D\u0101bla Meo",
    "gn:population":0,
    "gn:timezone":"Asia/Kolkata",
    "iso:country":"IN",
    "wof:name":"Dabla Meo",
    "wof:placetype":"locality"
},
  "geometry": {"coordinates":[76.6468,27.26672],"type":"Point"}
}