{
  "type": "Feature",
  "properties": {
    "iso:country":"IN",
    "ks:ks_name":"Nautolia",
    "ks:ks_pop":1379,
    "ks:ks_type":"HABITATION",
    "name:eng_x_preferred":[
        "Nautolia"
    ],
    "wof:name":"Nautolia",
    "wof:placetype":"locality",
    "wof:population":1379
},
  "geometry": {"coordinates":[83.08501200000001,24.435204],"type":"Point"}
}