{
  "type": "Feature",
  "properties": {
    "iso:country":"IN",
    "ks:ks_name":"Dusadh Tola",
    "ks:ks_pop":147,
    "ks:ks_type":"HABITATION",
    "name:eng_x_preferred":[
        "Dusadh Tola"
    ],
    "wof:name":"Dusadh Tola",
    "wof:placetype":"locality",
    "wof:population":147
},
  "geometry": {"coordinates":[85.53474300000001,25.60992],"type":"Point"}
}