{
  "type": "Feature",
  "properties": {
    "iso:country":"IN",
    "ks:ks_alt_nam":"snobhyun Estate",
    "ks:ks_name":"Snobhyun Estate",
    "ks:ks_pop":17,
    "ks:ks_type":"HABITATION",
    "name:eng_x_preferred":[
        "Snobhyun Estate"
    ],
    "wof:name":"Snobhyun Estate",
    "wof:placetype":"locality",
    "wof:population":17
},
  "geometry": {"coordinates":[79.673635,29.6237],"type":"Point"}
}