{
  "type": "Feature",
  "properties": {
    "iso:country":"IN",
    "ks:ks_name":"Meralikir",
    "ks:ks_pop":285,
    "ks:ks_type":"VILLAGE",
    "name:eng_x_preferred":[
        "Meralikir"
    ],
    "wof:name":"Meralikir",
    "wof:placetype":"locality",
    "wof:population":285
},
  "geometry": {"coordinates":[85.082928,22.465599],"type":"Point"}
}