{
  "type": "Feature",
  "properties": {
    "iso:country":"IN",
    "ks:ks_name":"Daukuriya",
    "ks:ks_pop":0,
    "ks:ks_type":"VILLAGE",
    "name:eng_x_preferred":[
        "Daukuriya"
    ],
    "wof:name":"Daukuriya",
    "wof:placetype":"locality",
    "wof:population":0
},
  "geometry": {"coordinates":[87.43342,24.859799],"type":"Point"}
}