{
  "type": "Feature",
  "properties": {
    "iso:country":"IN",
    "ks:ks_name":"Gundigadde",
    "ks:ks_pop":82,
    "ks:ks_type":"HABITATION",
    "name:eng_x_preferred":[
        "Gundigadde"
    ],
    "wof:name":"Gundigadde",
    "wof:placetype":"locality",
    "wof:population":82
},
  "geometry": {"coordinates":[75.11337,13.669946],"type":"Point"}
}