{
  "type": "Feature",
  "properties": {
    "gn:admin1_code":"19.0",
    "gn:admin2_code":"584.0",
    "gn:asciiname":"Vajarhalli",
    "gn:country_code":"IN",
    "gn:dem":874,
    "gn:feature_class":"P",
    "gn:feature_code":"PPL",
    "gn:name":"Vajarhalli",
    "gn:population":0,
    "gn:timezone":"Asia/Kolkata",
    "iso:country":"IN",
    "wof:name":"Vajarhalli",
    "wof:placetype":"locality"
},
  "geometry": {"coordinates":[77.21014,13.05104],"type":"Point"}
}