{
  "type": "Feature",
  "properties": {
    "iso:country":"IN",
    "ks:ks_name":"Jevnarahan",
    "ks:ks_pop":453,
    "ks:ks_type":"HABITATION",
    "ks:ks_uagg_main":0,
    "name:eng_x_preferred":[
        "Jevnarahan"
    ],
    "wof:name":"Jevnarahan",
    "wof:placetype":"neighbourhood",
    "wof:population":453
},
  "geometry": {"coordinates":[83.699359,26.740286],"type":"Point"}
}