{
  "type": "Feature",
  "properties": {
    "iso:country":"IN",
    "ks:ks_name":"Geratpur",
    "ks:ks_pop":2021,
    "ks:ks_type":"VILLAGE",
    "name:eng_x_preferred":[
        "Geratpur"
    ],
    "wof:name":"Geratpur",
    "wof:placetype":"neighbourhood",
    "wof:population":2021
},
  "geometry": {"coordinates":[72.65921,22.928719],"type":"Point"}
}