{
  "type": "Feature",
  "properties": {
    "gn:admin1_code":"36",
    "gn:admin2_code":"170.0",
    "gn:asciiname":"Ahar",
    "gn:country_code":"IN",
    "gn:dem":124,
    "gn:feature_class":"P",
    "gn:feature_code":"PPL",
    "gn:name":"Ah\u0101r",
    "gn:population":0,
    "gn:timezone":"Asia/Kolkata",
    "iso:country":"IN",
    "name:ara_x_preferred":[
        "\u0623\u0647\u0631"
    ],
    "name:azb_x_preferred":[
        "\u0627\u0647\u0631"
    ],
    "name:aze_x_preferred":[
        "\u018fh\u0259r"
    ],
    "name:ben_x_preferred":[
        "\u0986\u09b9\u09be\u09b0"
    ],
    "name:cat_x_preferred":[
        "Ahar"
    ],
    "name:ceb_x_preferred":[
        "Ahar"
    ],
    "name:deu_x_preferred":[
        "Ahar"
    ],
    "name:ell_x_preferred":[
        "\u0391\u03c7\u03ac\u03c1"
    ],
    "name:fas_x_preferred":[
        "\u0627\u0647\u0631"
    ],
    "name:fra_x_preferred":[
        "Ahar"
    ],
    "name:heb_x_preferred":[
        "\u05d0\u05d4\u05d0\u05e8"
    ],
    "name:hin_x_preferred":[
        "\u0905\u0939\u093e\u0930"
    ],
    "name:hun_x_preferred":[
        "Ahar"
    ],
    "name:ind_x_preferred":[
        "Ahar"
    ],
    "name:ita_x_preferred":[
        "Ahar"
    ],
    "name:jpn_x_preferred":[
        "\u30a2\u30cf\u30fc\u30eb"
    ],
    "name:kor_x_preferred":[
        "\uc544\ud558\ub974"
    ],
    "name:mlg_x_preferred":[
        "Ahar"
    ],
    "name:msa_x_preferred":[
        "Ahar"
    ],
    "name:pnb_x_preferred":[
        "\u0627\u06c1\u0627\u0631"
    ],
    "name:pol_x_preferred":[
        "Ahar"
    ],
    "name:por_x_preferred":[
        "Ahar"
    ],
    "name:ron_x_preferred":[
        "Ahar"
    ],
    "name:rus_x_preferred":[
        "\u0410\u0445\u0430\u0440"
    ],
    "name:spa_x_preferred":[
        "Ahar"
    ],
    "name:swe_x_preferred":[
        "Ahar"
    ],
    "name:tgk_x_preferred":[
        "\u0410\u04b3\u0430\u0440"
    ],
    "name:tur_x_preferred":[
        "Eher"
    ],
    "name:urd_x_preferred":[
        "\u0627\u06c1\u0631"
    ],
    "name:vie_x_preferred":[
        "Ahar"
    ],
    "name:zho_x_preferred":[
        "\u963f\u54c8\u5c14"
    ],
    "wof:name":"Ahar",
    "wof:placetype":"locality"
},
  "geometry": {"coordinates":[80.63970999999999,25.52175],"type":"Point"}
}