{
  "type": "Feature",
  "properties": {
    "iso:country":"IN",
    "ks:ks_alt_nam":"dulam ka pura",
    "ks:ks_name":"Dulam Ka Pura",
    "ks:ks_pop":1000,
    "ks:ks_type":"HABITATION",
    "name:eng_x_preferred":[
        "Dulam Ka Pura"
    ],
    "wof:name":"Dulam Ka Pura",
    "wof:placetype":"locality",
    "wof:population":1000
},
  "geometry": {"coordinates":[82.1987,25.26973],"type":"Point"}
}