{
  "type": "Feature",
  "properties": {
    "iso:country":"IN",
    "ks:ks_alt_nam":"Bodavani thanda",
    "ks:ks_name":"Bodavani Thanda",
    "ks:ks_pop":125,
    "ks:ks_type":"HABITATION",
    "name:eng_x_preferred":[
        "Bodavani Thanda"
    ],
    "wof:name":"Bodavani Thanda",
    "wof:placetype":"locality",
    "wof:population":125
},
  "geometry": {"coordinates":[79.376909,17.558822],"type":"Point"}
}