{
  "type": "Feature",
  "properties": {
    "gn:admin1_code":"25.0",
    "gn:admin2_code":"606.0",
    "gn:asciiname":"Paranellimarathur",
    "gn:country_code":"IN",
    "gn:dem":754,
    "gn:feature_class":"P",
    "gn:feature_code":"PPL",
    "gn:name":"Paranellimarath\u016br",
    "gn:population":0,
    "gn:timezone":"Asia/Kolkata",
    "iso:country":"IN",
    "wof:name":"Paranellimarathur",
    "wof:placetype":"locality"
},
  "geometry": {"coordinates":[78.91037,12.57448],"type":"Point"}
}