{
  "type": "Feature",
  "properties": {
    "gn:admin1_code":"11.0",
    "gn:admin2_code":"27.0",
    "gn:asciiname":"Parali Seri",
    "gn:country_code":"IN",
    "gn:dem":2101,
    "gn:feature_class":"P",
    "gn:feature_code":"PPL",
    "gn:name":"Par\u0101li Seri",
    "gn:population":0,
    "gn:timezone":"Asia/Kolkata",
    "iso:country":"IN",
    "wof:name":"Parali Seri",
    "wof:placetype":"locality"
},
  "geometry": {"coordinates":[77.31985999999998,31.43464],"type":"Point"}
}