{
  "type": "Feature",
  "properties": {
    "gn:admin1_code":"38.0",
    "gn:admin2_code":"347.0",
    "gn:asciiname":"Mohanpur",
    "gn:country_code":"IN",
    "gn:dem":409,
    "gn:feature_class":"P",
    "gn:feature_code":"PPL",
    "gn:name":"Mohanpur",
    "gn:population":0,
    "gn:timezone":"Asia/Kolkata",
    "iso:country":"IN",
    "name:ceb_x_preferred":[
        "Mohanpur"
    ],
    "name:fra_x_preferred":[
        "Mohanpur"
    ],
    "name:ita_x_preferred":[
        "Mohanpur"
    ],
    "name:new_x_preferred":[
        "\u092e\u094b\u0939\u0928\u092a\u0941\u0930 \u0917\u093e\u0935\u093f\u0938"
    ],
    "name:pol_x_preferred":[
        "Mohanpur"
    ],
    "name:swe_x_preferred":[
        "Mohanpur"
    ],
    "wof:name":"Mohanpur",
    "wof:placetype":"locality"
},
  "geometry": {"coordinates":[84.6699,24.22808],"type":"Point"}
}