{
  "type": "Feature",
  "properties": {
    "gn:admin1_code":"38.0",
    "gn:admin2_code":"347.0",
    "gn:asciiname":"Mohanpur",
    "gn:country_code":"IN",
    "gn:dem":409,
    "gn:feature_class":"P",
    "gn:feature_code":"PPL",
    "gn:name":"Mohanpur",
    "gn:population":0,
    "gn:timezone":"Asia/Kolkata",
    "iso:country":"IN",
    "name:ara_x_preferred":[
        "\u0645\u0648\u0647\u064a\u0646\u0628\u0648\u0631"
    ],
    "name:ben_bn_x_preferred":[
        "\u09ae\u09cb\u09b9\u09a8\u09aa\u09c1\u09b0"
    ],
    "name:ben_in_x_preferred":[
        "\u09ae\u09cb\u09b9\u09a8\u09aa\u09c1\u09b0"
    ],
    "name:ceb_x_preferred":[
        "Mohanpur"
    ],
    "name:fra_x_preferred":[
        "Mohanpur"
    ],
    "name:guj_x_preferred":[
        "\u0aae\u0acb\u0ab9\u0aa8\u0aaa\u0ac1\u0ab0"
    ],
    "name:hin_x_preferred":[
        "\u092e\u094b\u0939\u0928\u092a\u0941\u0930"
    ],
    "name:ita_x_preferred":[
        "Mohanpur"
    ],
    "name:kan_x_preferred":[
        "\u0cae\u0ccb\u0cb9\u0caa\u0cc1\u0cb0"
    ],
    "name:mal_x_preferred":[
        "\u0d2e\u0d4b\u0d39\u0d7b\u0d2a\u0d42\u0d7c"
    ],
    "name:mar_x_preferred":[
        "\u092e\u094b\u0939\u0928\u092a\u0942\u0930"
    ],
    "name:new_x_preferred":[
        "\u092e\u094b\u0939\u0928\u092a\u0941\u0930 \u0917\u093e\u0935\u093f\u0938"
    ],
    "name:pan_x_preferred":[
        "\u0a2e\u0a4b\u0a39\u0a28\u0a2a\u0a41\u0a30"
    ],
    "name:pol_x_preferred":[
        "Mohanpur"
    ],
    "name:swe_x_preferred":[
        "Mohanpur"
    ],
    "name:tam_x_preferred":[
        "\u0bae\u0bcb\u0b95\u0ba9\u0bcd\u0baa\u0bc2\u0bb0\u0bcd"
    ],
    "name:tel_x_preferred":[
        "\u0c2e\u0c4b\u0c39\u0c28\u0c4d"
    ],
    "name:urd_x_preferred":[
        "\u0645\u0648\u06c1\u0646 \u067e\u0648\u0631"
    ],
    "wof:name":"Mohanpur",
    "wof:placetype":"locality"
},
  "geometry": {"coordinates":[84.6699,24.22808],"type":"Point"}
}