{
  "type": "Feature",
  "properties": {
    "iso:country":"IN",
    "ks:ks_name":"Danewala",
    "ks:ks_pop":2903,
    "ks:ks_type":"VILLAGE",
    "ks:ks_uagg_main":0,
    "name:eng_x_preferred":[
        "Danewala"
    ],
    "wof:name":"Danewala",
    "wof:placetype":"neighbourhood",
    "wof:population":2903
},
  "geometry": {"coordinates":[74.510414,30.174068],"type":"Point"}
}