{
  "type": "Feature",
  "properties": {
    "gn:admin1_code":"34.0",
    "gn:admin2_code":"235.0",
    "gn:asciiname":"Koni",
    "gn:country_code":"IN",
    "gn:dem":132,
    "gn:feature_class":"P",
    "gn:feature_code":"PPL",
    "gn:name":"Kon\u012b",
    "gn:population":0,
    "gn:timezone":"Asia/Kolkata",
    "iso:country":"IN",
    "name:aka_x_preferred":[
        "Koni"
    ],
    "name:ceb_x_preferred":[
        "Koni"
    ],
    "name:deu_x_preferred":[
        "Koni"
    ],
    "name:est_x_preferred":[
        "Koni"
    ],
    "name:fra_x_preferred":[
        "Koni"
    ],
    "name:kat_x_preferred":[
        "\u10d9\u10dd\u10dc\u10d8"
    ],
    "name:rus_x_preferred":[
        "\u041a\u043e\u043d\u0438"
    ],
    "name:srp_x_preferred":[
        "\u041a\u043e\u043d\u0438"
    ],
    "name:swe_x_preferred":[
        "Koni"
    ],
    "wof:name":"Koni",
    "wof:placetype":"locality"
},
  "geometry": {"coordinates":[84.20614999999999,24.66703],"type":"Point"}
}