{
  "type": "Feature",
  "properties": {
    "iso:country":"IN",
    "ks:ks_name":"Itchalabetta",
    "ks:ks_pop":70,
    "ks:ks_type":"HABITATION",
    "name:eng_x_preferred":[
        "Itchalabetta"
    ],
    "wof:name":"Itchalabetta",
    "wof:placetype":"locality",
    "wof:population":70
},
  "geometry": {"coordinates":[74.76718700000001,14.519255],"type":"Point"}
}