{
  "type": "Feature",
  "properties": {
    "iso:country":"IN",
    "ks:ks_name":"Bekobad",
    "ks:ks_pop":453,
    "ks:ks_type":"VILLAGE",
    "name:eng_x_preferred":[
        "Bekobad"
    ],
    "wof:name":"Bekobad",
    "wof:placetype":"locality",
    "wof:population":453
},
  "geometry": {"coordinates":[86.29606200000001,24.417335],"type":"Point"}
}