{
  "type": "Feature",
  "properties": {
    "iso:country":"IN",
    "ks:ks_name":"Daluibazar",
    "ks:ks_pop":3420,
    "ks:ks_type":"VILLAGE",
    "ks:ks_uagg_main":0,
    "name:eng_x_preferred":[
        "Daluibazar"
    ],
    "wof:name":"Daluibazar",
    "wof:placetype":"neighbourhood",
    "wof:population":3420
},
  "geometry": {"coordinates":[88.029068,23.18637],"type":"Point"}
}