{
  "type": "Feature",
  "properties": {
    "iso:country":"IN",
    "ks:ks_name":"Nagla Subali",
    "ks:ks_pop":267,
    "ks:ks_type":"HABITATION",
    "name:eng_x_preferred":[
        "Nagla Subali"
    ],
    "wof:name":"Nagla Subali",
    "wof:placetype":"locality",
    "wof:population":267
},
  "geometry": {"coordinates":[78.403721,28.135299],"type":"Point"}
}