{
  "type": "Feature",
  "properties": {
    "iso:country":"IN",
    "ks:ks_name":"Burampada",
    "ks:ks_pop":0,
    "ks:ks_type":"VILLAGE",
    "name:eng_x_preferred":[
        "Burampada"
    ],
    "wof:name":"Burampada",
    "wof:placetype":"locality",
    "wof:population":0
},
  "geometry": {"coordinates":[85.883306,22.109701],"type":"Point"}
}