{
  "type": "Feature",
  "properties": {
    "iso:country":"IN",
    "ks:ks_name":"Dherageria",
    "ks:ks_pop":349,
    "ks:ks_type":"HABITATION",
    "name:eng_x_preferred":[
        "Dherageria"
    ],
    "wof:name":"Dherageria",
    "wof:placetype":"locality",
    "wof:population":349
},
  "geometry": {"coordinates":[86.890979,22.266593],"type":"Point"}
}