{
  "type": "Feature",
  "properties": {
    "iso:country":"IN",
    "ks:ks_alt_nam":"POKOTTU KULAMBU",
    "ks:ks_name":"Pokottu Kulambu",
    "ks:ks_pop":1398,
    "ks:ks_type":"HABITATION",
    "name:eng_x_preferred":[
        "Pokottu Kulambu"
    ],
    "wof:name":"Pokottu Kulambu",
    "wof:placetype":"locality",
    "wof:population":1398
},
  "geometry": {"coordinates":[76.159446,10.875903],"type":"Point"}
}