{
  "type": "Feature",
  "properties": {
    "iso:country":"IN",
    "ks:ks_name":"Tagapanga",
    "ks:ks_pop":227,
    "ks:ks_type":"VILLAGE",
    "name:eng_x_preferred":[
        "Tagapanga"
    ],
    "wof:name":"Tagapanga",
    "wof:placetype":"locality",
    "wof:population":227
},
  "geometry": {"coordinates":[84.099031,19.900071],"type":"Point"}
}