{
  "type": "Feature",
  "properties": {
    "iso:country":"IN",
    "ks:ks_name":"Shamar Pura",
    "ks:ks_pop":131,
    "ks:ks_type":"VILLAGE",
    "ks:ks_uagg_main":0,
    "name:eng_x_preferred":[
        "Shamar Pura"
    ],
    "wof:name":"Shamar Pura",
    "wof:placetype":"neighbourhood",
    "wof:population":131
},
  "geometry": {"coordinates":[83.91148,25.551165],"type":"Point"}
}