{
  "type": "Feature",
  "properties": {
    "iso:country":"IN",
    "ks:ks_name":"Ugvatkond",
    "ks:ks_pop":59,
    "ks:ks_type":"HABITATION",
    "name:eng_x_preferred":[
        "Ugvatkond"
    ],
    "wof:name":"Ugvatkond",
    "wof:placetype":"locality",
    "wof:population":59
},
  "geometry": {"coordinates":[73.34202999999999,18.034302],"type":"Point"}
}