{
  "type": "Feature",
  "properties": {
    "gn:admin1_code":"28.0",
    "gn:admin2_code":"328.0",
    "gn:asciiname":"Malbazar",
    "gn:country_code":"IN",
    "gn:dem":135,
    "gn:feature_class":"P",
    "gn:feature_code":"PPLL",
    "gn:name":"Malbazar",
    "gn:population":0,
    "gn:timezone":"Asia/Kolkata",
    "iso:country":"IN",
    "wof:name":"Malbazar",
    "wof:placetype":"locality"
},
  "geometry": {"coordinates":[88.75,26.85],"type":"Point"}
}