{
  "type": "Feature",
  "properties": {
    "iso:country":"IN",
    "ks:ks_name":"Banasil",
    "ks:ks_pop":524,
    "ks:ks_type":"VILLAGE",
    "name:eng_x_preferred":[
        "Banasil"
    ],
    "wof:name":"Banasil",
    "wof:placetype":"locality",
    "wof:population":524
},
  "geometry": {"coordinates":[82.931027,19.082955],"type":"Point"}
}