{
  "type": "Feature",
  "properties": {
    "iso:country":"IN",
    "ks:ks_name":"Enayat Nagar Rasulpur",
    "ks:ks_pop":2796,
    "ks:ks_type":"VILLAGE",
    "name:eng_x_preferred":[
        "Enayat Nagar Rasulpur"
    ],
    "wof:name":"Enayat Nagar Rasulpur",
    "wof:placetype":"locality",
    "wof:population":2796
},
  "geometry": {"coordinates":[85.301418,25.944348],"type":"Point"}
}