{
  "type": "Feature",
  "properties": {
    "iso:country":"IN",
    "ks:ks_name":"Palangaya",
    "ks:ks_pop":33,
    "ks:ks_type":"HABITATION",
    "name:eng_x_preferred":[
        "Palangaya"
    ],
    "wof:name":"Palangaya",
    "wof:placetype":"locality",
    "wof:population":33
},
  "geometry": {"coordinates":[75.47655399999999,12.646806],"type":"Point"}
}