{
  "type": "Feature",
  "properties": {
    "gn:admin1_code":"10",
    "gn:admin2_code":"70.0",
    "gn:asciiname":"Khatauli",
    "gn:country_code":"IN",
    "gn:dem":281,
    "gn:feature_class":"P",
    "gn:feature_code":"PPL",
    "gn:name":"Khatauli",
    "gn:population":0,
    "gn:timezone":"Asia/Kolkata",
    "iso:country":"IN",
    "name:bpy_x_preferred":[
        "\u0996\u09be\u099f\u09c1\u09af\u09bc\u09be\u09b2\u09bf"
    ],
    "name:cat_x_preferred":[
        "Khatauli"
    ],
    "name:ceb_x_preferred":[
        "Khatauli"
    ],
    "name:hin_x_preferred":[
        "\u0916\u0924\u094c\u0932\u0940"
    ],
    "name:ita_x_preferred":[
        "Khatauli"
    ],
    "name:mlg_x_preferred":[
        "Khatauli"
    ],
    "name:msa_x_preferred":[
        "Khatauli"
    ],
    "name:new_x_preferred":[
        "\u0916\u091f\u094c\u0932\u0940"
    ],
    "name:nld_x_preferred":[
        "Khatauli"
    ],
    "name:pol_x_preferred":[
        "Khatauli"
    ],
    "name:por_x_preferred":[
        "Khatauli"
    ],
    "name:swe_x_preferred":[
        "Khatauli"
    ],
    "name:urd_x_preferred":[
        "\u06a9\u06be\u062a\u0648\u0644\u06cc"
    ],
    "name:vie_x_preferred":[
        "Khatauli"
    ],
    "name:zho_x_preferred":[
        "\u5361\u9676\u5229"
    ],
    "wof:name":"Khatauli",
    "wof:placetype":"locality"
},
  "geometry": {"coordinates":[76.8257,30.40749000000001],"type":"Point"}
}