{
  "type": "Feature",
  "properties": {
    "iso:country":"IN",
    "ks:ks_name":"Jagatpur",
    "ks:ks_pop":1040,
    "ks:ks_type":"VILLAGE",
    "ks:ks_uagg_main":0,
    "name:eng_x_preferred":[
        "Jagatpur"
    ],
    "wof:name":"Jagatpur",
    "wof:placetype":"neighbourhood",
    "wof:population":1040
},
  "geometry": {"coordinates":[86.792654,24.995756],"type":"Point"}
}