{
  "type": "Feature",
  "properties": {
    "gn:admin1_code":"19.0",
    "gn:admin2_code":"576.0",
    "gn:asciiname":"Nallugote",
    "gn:country_code":"IN",
    "gn:dem":893,
    "gn:feature_class":"P",
    "gn:feature_code":"PPLL",
    "gn:name":"Nallugote",
    "gn:population":0,
    "gn:timezone":"Asia/Kolkata",
    "iso:country":"IN",
    "ks:ks_name":"Nallugote",
    "ks:ks_pop":710,
    "ks:ks_type":"HABITATION",
    "name:eng_x_preferred":[
        "Nallugote"
    ],
    "wof:name":"Nallugote",
    "wof:placetype":"locality",
    "wof:population":710
},
  "geometry": {"coordinates":[75.931291,12.210646],"type":"Point"}
}