{
  "type": "Feature",
  "properties": {
    "iso:country":"IN",
    "ks:ks_name":"Sansarpur",
    "ks:ks_pop":4060,
    "ks:ks_type":"URBAN",
    "ks:ks_uagg_main":0,
    "name:eng_x_preferred":[
        "Sansarpur"
    ],
    "wof:name":"Sansarpur",
    "wof:placetype":"neighbourhood",
    "wof:population":4060
},
  "geometry": {"coordinates":[75.620396,31.268883],"type":"Point"}
}