{
  "type": "Feature",
  "properties": {
    "iso:country":"IN",
    "ks:ks_name":"Talai",
    "ks:ks_pop":169,
    "ks:ks_type":"HABITATION",
    "name:eng_x_preferred":[
        "Talai"
    ],
    "wof:name":"Talai",
    "wof:placetype":"locality",
    "wof:population":169
},
  "geometry": {"coordinates":[79.222708,29.915263],"type":"Point"}
}