{
  "type": "Feature",
  "properties": {
    "iso:country":"IN",
    "ks:ks_name":"Nalaee",
    "ks:ks_pop":321,
    "ks:ks_type":"VILLAGE",
    "name:eng_x_preferred":[
        "Nalaee"
    ],
    "wof:name":"Nalaee",
    "wof:placetype":"locality",
    "wof:population":321
},
  "geometry": {"coordinates":[78.95724300000001,30.15836],"type":"Point"}
}