{
  "type": "Feature",
  "properties": {
    "gn:country":"IN",
    "gn:fcode":"PPL",
    "gn:pop":26011,
    "iso:country":"IN",
    "name:ben_x_preferred":[
        "\u09b0\u09be\u09a8\u09be\u09ad\u09ac"
    ],
    "name:bpy_x_preferred":[
        "\u09b0\u09be\u09a8\u09be\u09ac\u09be\u09ac"
    ],
    "name:ceb_x_preferred":[
        "R\u0101n\u0101v\u0101v"
    ],
    "name:deu_x_preferred":[
        "Ranavav"
    ],
    "name:eng_x_preferred":[
        "Ranavav"
    ],
    "name:fra_x_preferred":[
        "Ranavav"
    ],
    "name:guj_x_preferred":[
        "\u0ab0\u0abe\u0aa3\u0abe\u0ab5\u0abe\u0ab5"
    ],
    "name:hif_x_preferred":[
        "Ranavav"
    ],
    "name:hin_x_preferred":[
        "\u0930\u093e\u0923\u093e\u0935\u093e\u0935"
    ],
    "name:ita_x_preferred":[
        "Ranavav"
    ],
    "name:jpn_x_preferred":[
        "\u30e9\u30ca\u30f4\u30a1\u30f4"
    ],
    "name:kan_x_preferred":[
        "\u0cb0\u0ca3\u0cb5\u0cb5\u0ccd"
    ],
    "name:kor_x_preferred":[
        "\ub77c\ub098\ubc14\ube0c"
    ],
    "name:msa_x_preferred":[
        "Ranavav"
    ],
    "name:nld_x_preferred":[
        "Ranavav"
    ],
    "name:ori_x_preferred":[
        "\u0b30\u0b3e\u0b23\u0b3e\u0b2d\u0b3e\u0b2c"
    ],
    "name:por_x_preferred":[
        "Ranavav"
    ],
    "name:rus_x_preferred":[
        "\u0420\u0430\u043d\u0430\u0432\u0430\u0432"
    ],
    "name:spa_x_preferred":[
        "Ranavav"
    ],
    "name:swe_x_preferred":[
        "R\u0101n\u0101v\u0101v"
    ],
    "name:tam_x_preferred":[
        "\u0bb0\u0ba9\u0bb5\u0bb5\u0bcd"
    ],
    "name:tel_x_preferred":[
        "\u0c30\u0c23\u0c35\u0c35\u0c4d"
    ],
    "name:unk_x_variant":[
        "R\u0101n\u0101w\u0101o"
    ],
    "name:urd_x_preferred":[
        "\u0631\u0627\u0646\u0627\u0648\u0627\u0648"
    ],
    "name:vie_x_preferred":[
        "Ranavav"
    ],
    "name:zho_x_preferred":[
        "\u62c9\u7eb3\u74e6\u6c83"
    ],
    "qs:name":"Ranavav",
    "qs:name_adm0":"India",
    "qs:name_adm1":"Gujarat",
    "qs:photos_9k":1,
    "qs:photos_9r":1,
    "qs:photos_all":2,
    "qs:photos_sr":0,
    "qs:placetype":"Town",
    "qs:pop_sr":"7",
    "wd:elevation":40.0,
    "wd:wordcount":436,
    "wof:name":"Ranavav",
    "wof:placetype":"locality",
    "wof:population":26011
},
  "geometry": {"coordinates":[69.74485,21.68734],"type":"Point"}
}