{
  "type": "Feature",
  "properties": {
    "gn:admin1_code":"36.0",
    "gn:admin2_code":"151.0",
    "gn:asciiname":"Nakta",
    "gn:country_code":"IN",
    "gn:dem":179,
    "gn:feature_class":"P",
    "gn:feature_code":"PPL",
    "gn:name":"Nakta",
    "gn:population":0,
    "gn:timezone":"Asia/Kolkata",
    "iso:country":"IN",
    "ks:ks_name":"Nakta",
    "ks:ks_type":"VILLAGE",
    "name:eng_x_preferred":[
        "Nakta"
    ],
    "name:und_x_variant":[
        "Mor\u0101d\u0101b\u0101d"
    ],
    "wof:name":"Nakta",
    "wof:placetype":"locality"
},
  "geometry": {"coordinates":[79.813621,28.468352],"type":"Point"}
}