{
  "type": "Feature",
  "properties": {
    "gn:admin1_code":"35",
    "gn:admin2_code":"430.0",
    "gn:asciiname":"Murali",
    "gn:country_code":"IN",
    "gn:dem":323,
    "gn:feature_class":"P",
    "gn:feature_code":"PPL",
    "gn:name":"Mur\u0101li",
    "gn:population":0,
    "gn:timezone":"Asia/Kolkata",
    "iso:country":"IN",
    "name:deu_x_preferred":[
        "Murali"
    ],
    "name:mal_x_preferred":[
        "\u0d2e\u0d41\u0d30\u0d33\u0d3f"
    ],
    "name:rus_x_preferred":[
        "\u041c\u0443\u0440\u0430\u043b\u0438"
    ],
    "name:tat_x_preferred":[
        "\u041c\u04e9\u0440\u04d9\u043b\u0435"
    ],
    "wof:name":"Murali",
    "wof:placetype":"locality"
},
  "geometry": {"coordinates":[81.73539,24.9451],"type":"Point"}
}