{
  "type": "Feature",
  "properties": {
    "gn:admin1_code":"11",
    "gn:admin2_code":"27.0",
    "gn:asciiname":"Sianji",
    "gn:country_code":"IN",
    "gn:dem":1172,
    "gn:feature_class":"P",
    "gn:feature_code":"PPL",
    "gn:name":"Si\u0101nji",
    "gn:population":0,
    "gn:timezone":"Asia/Kolkata",
    "iso:country":"IN",
    "wof:name":"Sianji",
    "wof:placetype":"locality"
},
  "geometry": {"coordinates":[76.96026999999999,31.50892],"type":"Point"}
}