{
  "type": "Feature",
  "properties": {
    "iso:country":"IN",
    "ks:ks_name":"Tadwan Chaubapur",
    "ks:ks_pop":248,
    "ks:ks_type":"VILLAGE",
    "ks:ks_uagg_main":0,
    "name:eng_x_preferred":[
        "Tadwan Chaubapur"
    ],
    "wof:name":"Tadwan Chaubapur",
    "wof:placetype":"neighbourhood",
    "wof:population":248
},
  "geometry": {"coordinates":[83.365207,25.986173],"type":"Point"}
}