{
  "type": "Feature",
  "properties": {
    "iso:country":"IN",
    "ks:ks_name":"Bagi Semaltiyun Ki",
    "ks:ks_pop":8,
    "ks:ks_type":"HABITATION",
    "name:eng_x_preferred":[
        "Bagi Semaltiyun Ki"
    ],
    "wof:name":"Bagi Semaltiyun Ki",
    "wof:placetype":"locality",
    "wof:population":8
},
  "geometry": {"coordinates":[78.56594800000001,30.325097],"type":"Point"}
}