{
  "type": "Feature",
  "properties": {
    "iso:country":"IN",
    "ks:ks_name":"Bhair Gaon",
    "ks:ks_pop":379,
    "ks:ks_type":"VILLAGE",
    "name:eng_x_preferred":[
        "Bhair Gaon"
    ],
    "wof:name":"Bhair Gaon",
    "wof:placetype":"locality",
    "wof:population":379
},
  "geometry": {"coordinates":[78.85234,29.894782],"type":"Point"}
}