{
  "type": "Feature",
  "properties": {
    "iso:country":"IN",
    "ks:ks_name":"Bahadur Chak",
    "ks:ks_pop":0,
    "ks:ks_type":"VILLAGE",
    "name:eng_x_preferred":[
        "Bahadur Chak"
    ],
    "wof:name":"Bahadur Chak",
    "wof:placetype":"locality",
    "wof:population":0
},
  "geometry": {"coordinates":[83.96852199999999,25.651414],"type":"Point"}
}