{
  "type": "Feature",
  "properties": {
    "iso:country":"IN",
    "ks:ks_name":"Siswa",
    "ks:ks_pop":1020,
    "ks:ks_type":"VILLAGE",
    "name:eng_x_preferred":[
        "Siswa"
    ],
    "wof:name":"Siswa",
    "wof:placetype":"locality",
    "wof:population":1020
},
  "geometry": {"coordinates":[86.57794199999999,26.203141],"type":"Point"}
}