{
  "type": "Feature",
  "properties": {
    "iso:country":"IN",
    "ks:ks_name":"Juljul",
    "ks:ks_pop":272,
    "ks:ks_type":"VILLAGE",
    "ks:ks_uagg_main":0,
    "name:eng_x_preferred":[
        "Juljul"
    ],
    "wof:name":"Juljul",
    "wof:placetype":"neighbourhood",
    "wof:population":272
},
  "geometry": {"coordinates":[85.422894,23.969493],"type":"Point"}
}