{
  "type": "Feature",
  "properties": {
    "iso:country":"IN",
    "ks:ks_name":"Vengamala",
    "ks:ks_pop":350,
    "ks:ks_type":"HABITATION",
    "name:eng_x_preferred":[
        "Vengamala"
    ],
    "wof:name":"Vengamala",
    "wof:placetype":"locality",
    "wof:population":350
},
  "geometry": {"coordinates":[77.02259100000001,8.828025],"type":"Point"}
}