{
  "type": "Feature",
  "properties": {
    "iso:country":"IN",
    "ks:ks_alt_nam":"Lalu tanda",
    "ks:ks_name":"Lalu Tanda",
    "ks:ks_pop":78,
    "ks:ks_type":"HABITATION",
    "name:eng_x_preferred":[
        "Lalu Tanda"
    ],
    "wof:name":"Lalu Tanda",
    "wof:placetype":"locality",
    "wof:population":78
},
  "geometry": {"coordinates":[77.54227299999999,18.141269],"type":"Point"}
}