{
  "type": "Feature",
  "properties": {
    "iso:country":"IN",
    "ks:ks_name":"Eshapura Koracharahatti",
    "ks:ks_pop":145,
    "ks:ks_type":"HABITATION",
    "name:eng_x_preferred":[
        "Eshapura Koracharahatti"
    ],
    "wof:name":"Eshapura Koracharahatti",
    "wof:placetype":"locality",
    "wof:population":145
},
  "geometry": {"coordinates":[75.84851,14.871472],"type":"Point"}
}