{
  "type": "Feature",
  "properties": {
    "gn:admin1_code":"11",
    "gn:admin2_code":"23.0",
    "gn:asciiname":"Bang Behi",
    "gn:country_code":"IN",
    "gn:dem":2182,
    "gn:feature_class":"P",
    "gn:feature_code":"PPL",
    "gn:name":"Bang Behi",
    "gn:population":0,
    "gn:timezone":"Asia/Kolkata",
    "iso:country":"IN",
    "wof:name":"Bang Behi",
    "wof:placetype":"locality"
},
  "geometry": {"coordinates":[76.0547,32.51129],"type":"Point"}
}