{
  "type": "Feature",
  "properties": {
    "iso:country":"IN",
    "ks:ks_alt_nam":"2 BLD-A",
    "ks:ks_name":"2 Bld-a",
    "ks:ks_pop":236,
    "ks:ks_type":"HABITATION",
    "name:eng_x_preferred":[
        "2 Bld-a"
    ],
    "wof:name":"2 Bld-a",
    "wof:placetype":"locality",
    "wof:population":236
},
  "geometry": {"coordinates":[73.525961,29.305044],"type":"Point"}
}