{
  "type": "Feature",
  "properties": {
    "iso:country":"IN",
    "ks:ks_alt_nam":"Pindw\u0101la Kal\u0101n",
    "ks:ks_name":"Pindwala Kalan",
    "ks:ks_type":"VILLAGE",
    "name:eng_x_preferred":[
        "Pindwala Kalan"
    ],
    "name:eng_x_variant":[
        "Pindw\u0101la Kal\u0101n"
    ],
    "wof:name":"Pindwala Kalan",
    "wof:placetype":"neighbourhood"
},
  "geometry": {"coordinates":[76.96106399999999,28.567649],"type":"Point"}
}