{
  "type": "Feature",
  "properties": {
    "gn:admin1_code":"19.0",
    "gn:admin2_code":"568.0",
    "gn:asciiname":"Mavinakana",
    "gn:country_code":"IN",
    "gn:dem":570,
    "gn:feature_class":"P",
    "gn:feature_code":"PPL",
    "gn:name":"Mavinakana",
    "gn:population":0,
    "gn:timezone":"Asia/Kolkata",
    "iso:country":"IN",
    "ks:ks_name":"Mavinakana",
    "ks:ks_pop":4,
    "ks:ks_type":"HABITATION",
    "name:eng_x_preferred":[
        "Mavinakana"
    ],
    "wof:name":"Mavinakana",
    "wof:placetype":"locality",
    "wof:population":4
},
  "geometry": {"coordinates":[75.026821,13.723051],"type":"Point"}
}