{
  "type": "Feature",
  "properties": {
    "iso:country":"IN",
    "ks:ks_name":"Uttar Para",
    "ks:ks_pop":208,
    "ks:ks_type":"HABITATION",
    "name:eng_x_preferred":[
        "Uttar Para"
    ],
    "wof:name":"Uttar Para",
    "wof:placetype":"locality",
    "wof:population":208
},
  "geometry": {"coordinates":[88.394395,22.18242],"type":"Point"}
}