{
  "type": "Feature",
  "properties": {
    "iso:country":"IN",
    "ks:ks_name":"Samantarapur",
    "ks:ks_pop":352,
    "ks:ks_type":"HABITATION",
    "name:eng_x_preferred":[
        "Samantarapur"
    ],
    "wof:name":"Samantarapur",
    "wof:placetype":"locality",
    "wof:population":352
},
  "geometry": {"coordinates":[85.259849,20.164779],"type":"Point"}
}