{
  "type": "Feature",
  "properties": {
    "iso:country":"IN",
    "ks:ks_name":"3 MGM",
    "ks:ks_pop":149,
    "ks:ks_type":"VILLAGE",
    "name:eng_x_preferred":[
        "3 MGM"
    ],
    "wof:name":"3 MGM",
    "wof:placetype":"locality",
    "wof:population":149
},
  "geometry": {"coordinates":[73.050674,28.809061],"type":"Point"}
}