{
  "type": "Feature",
  "properties": {
    "gn:admin1_code":"24.0",
    "gn:admin2_code":"107",
    "gn:asciiname":"Garh Moran",
    "gn:country_code":"IN",
    "gn:dem":296,
    "gn:feature_class":"P",
    "gn:feature_code":"PPL",
    "gn:name":"Garh Mor\u0101n",
    "gn:population":0,
    "gn:timezone":"Asia/Kolkata",
    "iso:country":"IN",
    "wof:name":"Garh Moran",
    "wof:placetype":"locality"
},
  "geometry": {"coordinates":[76.53904,26.70722],"type":"Point"}
}