{
  "type": "Feature",
  "properties": {
    "iso:country":"IN",
    "ks:ks_name":"Komnambi",
    "ks:ks_pop":52,
    "ks:ks_type":"HABITATION",
    "name:eng_x_preferred":[
        "Komnambi"
    ],
    "wof:name":"Komnambi",
    "wof:placetype":"locality",
    "wof:population":52
},
  "geometry": {"coordinates":[75.367194,13.459578],"type":"Point"}
}