{
  "type": "Feature",
  "properties": {
    "gn:admin1_code":"36.0",
    "gn:admin2_code":"176.0",
    "gn:asciiname":"Pura Fakir Shah",
    "gn:country_code":"IN",
    "gn:dem":116,
    "gn:feature_class":"P",
    "gn:feature_code":"PPL",
    "gn:name":"Pura Fakir Sh\u0101h",
    "gn:population":0,
    "gn:timezone":"Asia/Kolkata",
    "iso:country":"IN",
    "wof:name":"Pura Fakir Shah",
    "wof:placetype":"locality"
},
  "geometry": {"coordinates":[81.51869000000001,26.59911],"type":"Point"}
}