{
  "type": "Feature",
  "properties": {
    "gn:admin1_code":"2.0",
    "gn:admin2_code":"552.0",
    "gn:asciiname":"Mettupalle",
    "gn:country_code":"IN",
    "gn:dem":207,
    "gn:feature_class":"P",
    "gn:feature_code":"PPL",
    "gn:name":"Mettupalle",
    "gn:population":0,
    "gn:timezone":"Asia/Kolkata",
    "iso:country":"IN",
    "wof:name":"Mettupalle",
    "wof:placetype":"locality"
},
  "geometry": {"coordinates":[78.11575000000001,15.24134],"type":"Point"}
}