{
  "type": "Feature",
  "properties": {
    "gn:admin1_code":"37.0",
    "gn:admin2_code":"412",
    "gn:asciiname":"Kaspur",
    "gn:country_code":"IN",
    "gn:dem":464,
    "gn:feature_class":"P",
    "gn:feature_code":"PPL",
    "gn:name":"Kaspur",
    "gn:population":0,
    "gn:timezone":"Asia/Kolkata",
    "iso:country":"IN",
    "wof:name":"Kaspur",
    "wof:placetype":"locality"
},
  "geometry": {"coordinates":[81.86359,20.22771],"type":"Point"}
}