{
  "type": "Feature",
  "properties": {
    "iso:country":"IN",
    "ks:ks_alt_nam":"21.800 RD",
    "ks:ks_name":"21.800 Rd",
    "ks:ks_pop":346,
    "ks:ks_type":"HABITATION",
    "name:eng_x_preferred":[
        "21.800 Rd"
    ],
    "wof:name":"21.800 Rd",
    "wof:placetype":"locality",
    "wof:population":346
},
  "geometry": {"coordinates":[73.88454,29.152819],"type":"Point"}
}