{
  "type": "Feature",
  "properties": {
    "iso:country":"IN",
    "ks:ks_name":"Vadavali Tarf Gargaon",
    "ks:ks_pop":326,
    "ks:ks_type":"HABITATION",
    "name:eng_x_preferred":[
        "Vadavali Tarf Gargaon"
    ],
    "wof:name":"Vadavali Tarf Gargaon",
    "wof:placetype":"locality",
    "wof:population":326
},
  "geometry": {"coordinates":[73.277715,19.805402],"type":"Point"}
}