{
  "type": "Feature",
  "properties": {
    "iso:country":"IN",
    "ks:ks_name":"Navagam",
    "ks:ks_pop":767,
    "ks:ks_type":"VILLAGE",
    "name:eng_x_preferred":[
        "Navagam"
    ],
    "wof:name":"Navagam",
    "wof:placetype":"locality",
    "wof:population":767
},
  "geometry": {"coordinates":[73.62779999999999,22.688067],"type":"Point"}
}