{
  "type": "Feature",
  "properties": {
    "gn:admin1_code":"37",
    "gn:admin2_code":"409.0",
    "gn:asciiname":"Tora",
    "gn:country_code":"IN",
    "gn:dem":272,
    "gn:feature_class":"P",
    "gn:feature_code":"PPL",
    "gn:name":"Tora",
    "gn:population":0,
    "gn:timezone":"Asia/Kolkata",
    "iso:country":"IN",
    "name:cat_x_preferred":[
        "Tor\u00e0"
    ],
    "name:ceb_x_preferred":[
        "Tora"
    ],
    "name:deu_x_preferred":[
        "Tora"
    ],
    "name:eus_x_preferred":[
        "Tora"
    ],
    "name:fra_x_preferred":[
        "Tora"
    ],
    "name:hye_x_preferred":[
        "\u054f\u0578\u0580\u0561"
    ],
    "name:ita_x_preferred":[
        "Tora"
    ],
    "name:lav_x_preferred":[
        "Tora"
    ],
    "name:nld_x_preferred":[
        "Tora"
    ],
    "name:nor_x_preferred":[
        "Tora"
    ],
    "name:por_x_preferred":[
        "Tora"
    ],
    "name:ron_x_preferred":[
        "Thora"
    ],
    "name:rus_x_preferred":[
        "\u0422\u043e\u0440\u0430"
    ],
    "name:spa_x_preferred":[
        "Tora"
    ],
    "name:swe_x_preferred":[
        "Tora"
    ],
    "name:ukr_x_preferred":[
        "\u0422\u043e\u0440\u0430"
    ],
    "name:uzb_x_preferred":[
        "Tora"
    ],
    "wof:name":"Tora",
    "wof:placetype":"locality"
},
  "geometry": {"coordinates":[81.57613000000001,21.85894],"type":"Point"}
}