{
  "type": "Feature",
  "properties": {
    "iso:country":"IN",
    "ks:ks_name":"Bhupurdoddi",
    "ks:ks_pop":158,
    "ks:ks_type":"HABITATION",
    "name:eng_x_preferred":[
        "Bhupurdoddi"
    ],
    "wof:name":"Bhupurdoddi",
    "wof:placetype":"locality",
    "wof:population":158
},
  "geometry": {"coordinates":[76.577597,16.264271],"type":"Point"}
}