{
  "type": "Feature",
  "properties": {
    "iso:country":"IN",
    "ks:ks_alt_nam":"Verawali kondwadi",
    "ks:ks_name":"Verawali Kondwadi",
    "ks:ks_pop":21,
    "ks:ks_type":"HABITATION",
    "name:eng_x_preferred":[
        "Verawali Kondwadi"
    ],
    "wof:name":"Verawali Kondwadi",
    "wof:placetype":"locality",
    "wof:population":21
},
  "geometry": {"coordinates":[73.60954099999999,16.825633],"type":"Point"}
}