{
  "type": "Feature",
  "properties": {
    "iso:country":"IN",
    "ks:ks_alt_nam":"BASAUDI",
    "ks:ks_name":"Basaudi",
    "ks:ks_pop":122,
    "ks:ks_type":"HABITATION",
    "name:eng_x_preferred":[
        "Basaudi"
    ],
    "wof:name":"Basaudi",
    "wof:placetype":"locality",
    "wof:population":122
},
  "geometry": {"coordinates":[80.09274499999999,29.484325],"type":"Point"}
}