{
  "type": "Feature",
  "properties": {
    "iso:country":"IN",
    "ks:ks_name":"Dakshin Talbangrua",
    "ks:ks_pop":1886,
    "ks:ks_type":"HABITATION",
    "name:eng_x_preferred":[
        "Dakshin Talbangrua"
    ],
    "wof:name":"Dakshin Talbangrua",
    "wof:placetype":"locality",
    "wof:population":1886
},
  "geometry": {"coordinates":[87.858093,25.340618],"type":"Point"}
}