{
  "type": "Feature",
  "properties": {
    "iso:country":"IN",
    "ks:ks_alt_nam":"Uranipuram west",
    "ks:ks_name":"Uranipuram West",
    "ks:ks_pop":200,
    "ks:ks_type":"HABITATION",
    "name:eng_x_preferred":[
        "Uranipuram West"
    ],
    "wof:name":"Uranipuram West",
    "wof:placetype":"locality",
    "wof:population":200
},
  "geometry": {"coordinates":[79.17683,10.463539],"type":"Point"}
}