{
  "type": "Feature",
  "properties": {
    "gn:admin1_code":"36.0",
    "gn:admin2_code":"149.0",
    "gn:asciiname":"Bidha Nagla",
    "gn:country_code":"IN",
    "gn:dem":181,
    "gn:feature_class":"P",
    "gn:feature_code":"PPL",
    "gn:name":"B\u012bdha Nagla",
    "gn:population":0,
    "gn:timezone":"Asia/Kolkata",
    "iso:country":"IN",
    "ks:ks_name":"Bidha Nagala",
    "ks:ks_pop":1901,
    "ks:ks_type":"VILLAGE",
    "ks:ks_uagg_main":0,
    "name:eng_x_preferred":[
        "Bidha Nagala"
    ],
    "wof:name":"Bidha Nagala",
    "wof:placetype":"neighbourhood",
    "wof:population":1901
},
  "geometry": {"coordinates":[79.025103,28.369857],"type":"Point"}
}