{
  "type": "Feature",
  "properties": {
    "iso:country":"IN",
    "ks:ks_name":"3 DSM",
    "ks:ks_pop":127,
    "ks:ks_type":"VILLAGE",
    "name:eng_x_preferred":[
        "3 DSM"
    ],
    "wof:name":"3 DSM",
    "wof:placetype":"locality",
    "wof:population":127
},
  "geometry": {"coordinates":[73.339842,29.022531],"type":"Point"}
}