{
  "type": "Feature",
  "properties": {
    "iso:country":"IN",
    "ks:ks_name":"Charmakarwadi",
    "ks:ks_pop":79,
    "ks:ks_type":"HABITATION",
    "name:eng_x_preferred":[
        "Charmakarwadi"
    ],
    "wof:name":"Charmakarwadi",
    "wof:placetype":"locality",
    "wof:population":79
},
  "geometry": {"coordinates":[73.87705200000001,16.181944],"type":"Point"}
}