{
  "type": "Feature",
  "properties": {
    "iso:country":"IN",
    "ks:ks_name":"Godekoppa",
    "ks:ks_pop":16,
    "ks:ks_type":"HABITATION",
    "name:eng_x_preferred":[
        "Godekoppa"
    ],
    "wof:name":"Godekoppa",
    "wof:placetype":"locality",
    "wof:population":16
},
  "geometry": {"coordinates":[75.132515,13.534631],"type":"Point"}
}