{
  "type": "Feature",
  "properties": {
    "iso:country":"IN",
    "ks:ks_alt_nam":"GAYAKEWADI",
    "ks:ks_name":"Gayakewadi",
    "ks:ks_pop":260,
    "ks:ks_type":"HABITATION",
    "name:eng_x_preferred":[
        "Gayakewadi"
    ],
    "wof:name":"Gayakewadi",
    "wof:placetype":"locality",
    "wof:population":260
},
  "geometry": {"coordinates":[75.52122199999999,20.106162],"type":"Point"}
}