{
  "type": "Feature",
  "properties": {
    "iso:country":"IN",
    "ks:ks_name":"Ysr Puram",
    "ks:ks_pop":29,
    "ks:ks_type":"HABITATION",
    "name:eng_x_preferred":[
        "Ysr Puram"
    ],
    "wof:name":"Ysr Puram",
    "wof:placetype":"locality",
    "wof:population":29
},
  "geometry": {"coordinates":[83.146126,18.270498],"type":"Point"}
}