{
  "type": "Feature",
  "properties": {
    "gn:admin1_code":"36",
    "gn:admin2_code":"147.0",
    "gn:asciiname":"Nagla Sati",
    "gn:country_code":"IN",
    "gn:dem":170,
    "gn:feature_class":"P",
    "gn:feature_code":"PPL",
    "gn:name":"Nagla Sat\u012b",
    "gn:population":0,
    "gn:timezone":"Asia/Kolkata",
    "iso:country":"IN",
    "wof:name":"Nagla Sati",
    "wof:placetype":"locality"
},
  "geometry": {"coordinates":[78.44985,27.33308],"type":"Point"}
}