{
  "type": "Feature",
  "properties": {
    "iso:country":"IN",
    "ks:ks_alt_nam":"O.G.Halli",
    "ks:ks_name":"O.g.halli",
    "ks:ks_pop":746,
    "ks:ks_type":"HABITATION",
    "name:eng_x_preferred":[
        "O.g.halli"
    ],
    "wof:name":"O.g.halli",
    "wof:placetype":"locality",
    "wof:population":746
},
  "geometry": {"coordinates":[78.055183,12.188442],"type":"Point"}
}