{
  "type": "Feature",
  "properties": {
    "iso:country":"IN",
    "ks:ks_name":"Bakhar Falia",
    "ks:ks_pop":522,
    "ks:ks_type":"HABITATION",
    "name:eng_x_preferred":[
        "Bakhar Falia"
    ],
    "wof:name":"Bakhar Falia",
    "wof:placetype":"locality",
    "wof:population":522
},
  "geometry": {"coordinates":[73.065,20.665333],"type":"Point"}
}