{
  "type": "Feature",
  "properties": {
    "iso:country":"IN",
    "ks:ks_name":"Phulman Tola",
    "ks:ks_pop":36,
    "ks:ks_type":"HABITATION",
    "name:eng_x_preferred":[
        "Phulman Tola"
    ],
    "wof:name":"Phulman Tola",
    "wof:placetype":"locality",
    "wof:population":36
},
  "geometry": {"coordinates":[83.383487,27.095967],"type":"Point"}
}