{
  "type": "Feature",
  "properties": {
    "iso:country":"IN",
    "ks:ks_name":"Kormuta",
    "ks:ks_pop":455,
    "ks:ks_type":"HABITATION",
    "name:eng_x_preferred":[
        "Kormuta"
    ],
    "wof:name":"Kormuta",
    "wof:placetype":"locality",
    "wof:population":455
},
  "geometry": {"coordinates":[80.810576,19.095084],"type":"Point"}
}