{
  "type": "Feature",
  "properties": {
    "iso:country":"IN",
    "ks:ks_name":"Jamuniya",
    "ks:ks_pop":0,
    "ks:ks_type":"VILLAGE",
    "name:eng_x_preferred":[
        "Jamuniya"
    ],
    "wof:name":"Jamuniya",
    "wof:placetype":"locality",
    "wof:population":0
},
  "geometry": {"coordinates":[77.12586400000001,22.188143],"type":"Point"}
}