{
  "type": "Feature",
  "properties": {
    "gn:admin1_code":"35",
    "gn:admin2_code":"426.0",
    "gn:asciiname":"Biharwara",
    "gn:country_code":"IN",
    "gn:dem":322,
    "gn:feature_class":"P",
    "gn:feature_code":"PPL",
    "gn:name":"Biharw\u0101ra",
    "gn:population":0,
    "gn:timezone":"Asia/Kolkata",
    "iso:country":"IN",
    "ks:ks_alt_nam":"Biharw\u0101ra",
    "ks:ks_name":"Biharwara",
    "ks:ks_pop":210,
    "ks:ks_type":"VILLAGE",
    "ks:ks_uagg_main":0,
    "name:eng_x_preferred":[
        "Biharwara"
    ],
    "name:eng_x_variant":[
        "Biharw\u0101ra"
    ],
    "wof:name":"Biharwara",
    "wof:placetype":"neighbourhood",
    "wof:population":210
},
  "geometry": {"coordinates":[79.787581,24.086323],"type":"Point"}
}