{
  "type": "Feature",
  "properties": {
    "iso:country":"IN",
    "ks:ks_name":"Jatauliya",
    "ks:ks_pop":301,
    "ks:ks_type":"VILLAGE",
    "ks:ks_uagg_main":0,
    "name:eng_x_preferred":[
        "Jatauliya"
    ],
    "wof:name":"Jatauliya",
    "wof:placetype":"neighbourhood",
    "wof:population":301
},
  "geometry": {"coordinates":[82.266865,26.906526],"type":"Point"}
}