{
  "type": "Feature",
  "properties": {
    "iso:country":"IN",
    "ks:ks_name":"Aramgam",
    "ks:ks_pop":1060,
    "ks:ks_type":"HABITATION",
    "name:eng_x_preferred":[
        "Aramgam"
    ],
    "wof:name":"Aramgam",
    "wof:placetype":"locality",
    "wof:population":1060
},
  "geometry": {"coordinates":[75.466424,12.203081],"type":"Point"}
}