{
  "type": "Feature",
  "properties": {
    "gn:admin1_code":"25.0",
    "gn:admin2_code":"632.0",
    "gn:asciiname":"Manikkampalaiyam",
    "gn:country_code":"IN",
    "gn:dem":383,
    "gn:feature_class":"P",
    "gn:feature_code":"PPL",
    "gn:name":"M\u0101nikkamp\u0101laiyam",
    "gn:population":0,
    "gn:timezone":"Asia/Kolkata",
    "iso:country":"IN",
    "wof:name":"Manikkampalaiyam",
    "wof:placetype":"locality"
},
  "geometry": {"coordinates":[77.05575999999998,11.14291],"type":"Point"}
}