{
  "type": "Feature",
  "properties": {
    "gn:admin1_code":"34.0",
    "gn:admin2_code":"221.0",
    "gn:asciiname":"Bachhauli",
    "gn:country_code":"IN",
    "gn:dem":52,
    "gn:feature_class":"P",
    "gn:feature_code":"PPL",
    "gn:name":"Bachhauli",
    "gn:population":0,
    "gn:timezone":"Asia/Kolkata",
    "iso:country":"IN",
    "ks:ks_name":"Bachhauli",
    "ks:ks_pop":1417,
    "ks:ks_type":"VILLAGE",
    "name:eng_x_preferred":[
        "Bachhauli"
    ],
    "wof:name":"Bachhauli",
    "wof:placetype":"locality",
    "wof:population":1417
},
  "geometry": {"coordinates":[85.930457,25.790396],"type":"Point"}
}