{
  "type": "Feature",
  "properties": {
    "iso:country":"IN",
    "ks:ks_name":"Narayan Purwa",
    "ks:ks_pop":38,
    "ks:ks_type":"HABITATION",
    "ks:ks_uagg_main":0,
    "name:eng_x_preferred":[
        "Narayan Purwa"
    ],
    "wof:name":"Narayan Purwa",
    "wof:placetype":"neighbourhood",
    "wof:population":38
},
  "geometry": {"coordinates":[81.71356400000001,27.564732],"type":"Point"}
}