{
  "type": "Feature",
  "properties": {
    "gn:admin1_code":"11",
    "gn:admin2_code":"23.0",
    "gn:asciiname":"Baladh",
    "gn:country_code":"IN",
    "gn:dem":1698,
    "gn:feature_class":"P",
    "gn:feature_code":"PPL",
    "gn:name":"Baladh",
    "gn:population":0,
    "gn:timezone":"Asia/Kolkata",
    "iso:country":"IN",
    "wof:name":"Baladh",
    "wof:placetype":"locality"
},
  "geometry": {"coordinates":[76.16396999999998,32.79494],"type":"Point"}
}