{
  "type": "Feature",
  "properties": {
    "gn:admin1_code":"35.0",
    "gn:admin2_code":"464.0",
    "gn:asciiname":"Pipalkonta",
    "gn:country_code":"IN",
    "gn:dem":295,
    "gn:feature_class":"P",
    "gn:feature_code":"PPL",
    "gn:name":"Pipalkonta",
    "gn:population":0,
    "gn:timezone":"Asia/Kolkata",
    "iso:country":"IN",
    "ks:ks_name":"Pipal Khunta",
    "ks:ks_pop":1866,
    "ks:ks_type":"VILLAGE",
    "name:eng_x_preferred":[
        "Pipal Khunta"
    ],
    "name:eng_x_variant":[
        "Pipalkonta"
    ],
    "wof:name":"Pipal Khunta",
    "wof:placetype":"locality",
    "wof:population":1866
},
  "geometry": {"coordinates":[74.48518,22.943524],"type":"Point"}
}