{
  "type": "Feature",
  "properties": {
    "gn:admin1_code":"40.0",
    "gn:admin2_code":"537",
    "gn:asciiname":"Rawiral",
    "gn:country_code":"IN",
    "gn:dem":568,
    "gn:feature_class":"P",
    "gn:feature_code":"PPL",
    "gn:name":"R\u0101wir\u0101l",
    "gn:population":0,
    "gn:timezone":"Asia/Kolkata",
    "iso:country":"IN",
    "name:und_x_variant":[
        "R\u0101wir\u0101l",
        "R\u0101wir\u0101l Kongara"
    ],
    "wof:name":"Rawiral",
    "wof:placetype":"locality"
},
  "geometry": {"coordinates":[78.51028000000002,17.22028],"type":"Point"}
}