{
  "type": "Feature",
  "properties": {
    "iso:country":"IN",
    "ks:ks_name":"Haludih",
    "ks:ks_pop":78,
    "ks:ks_type":"HABITATION",
    "name:eng_x_preferred":[
        "Haludih"
    ],
    "wof:name":"Haludih",
    "wof:placetype":"locality",
    "wof:population":78
},
  "geometry": {"coordinates":[85.566097,23.224804],"type":"Point"}
}