{
  "type": "Feature",
  "properties": {
    "iso:country":"IN",
    "ks:ks_name":"Melur",
    "ks:ks_pop":188,
    "ks:ks_type":"HABITATION",
    "name:eng_x_preferred":[
        "Melur"
    ],
    "wof:name":"Melur",
    "wof:placetype":"locality",
    "wof:population":188
},
  "geometry": {"coordinates":[78.671485,11.256121],"type":"Point"}
}