{
  "type": "Feature",
  "properties": {
    "gn:admin1_code":"35.0",
    "gn:admin2_code":"458",
    "gn:asciiname":"Dharnaoda",
    "gn:country_code":"IN",
    "gn:dem":398,
    "gn:feature_class":"P",
    "gn:feature_code":"PPL",
    "gn:name":"Dharnaoda",
    "gn:population":0,
    "gn:timezone":"Asia/Kolkata",
    "iso:country":"IN",
    "name:und_x_variant":[
        "Dharaoda",
        "Dharnaoda"
    ],
    "wof:name":"Dharnaoda",
    "wof:placetype":"locality"
},
  "geometry": {"coordinates":[77.09741,24.58936],"type":"Point"}
}