{
  "type": "Feature",
  "properties": {
    "gn:admin1_code":"39.0",
    "gn:admin2_code":"061",
    "gn:asciiname":"Kandara",
    "gn:country_code":"IN",
    "gn:dem":1367,
    "gn:feature_class":"P",
    "gn:feature_code":"PPL",
    "gn:name":"Kand\u0101ra",
    "gn:population":0,
    "gn:timezone":"Asia/Kolkata",
    "iso:country":"IN",
    "ks:ks_alt_nam":"Kand\u0101ra",
    "ks:ks_name":"Kandara",
    "ks:ks_pop":65,
    "ks:ks_type":"VILLAGE",
    "name:ceb_x_preferred":[
        "Kandara"
    ],
    "name:eng_x_preferred":[
        "Kandara"
    ],
    "name:eng_x_variant":[
        "Kand\u0101ra"
    ],
    "name:pol_x_preferred":[
        "Kandara"
    ],
    "name:swa_x_preferred":[
        "Kandara"
    ],
    "name:swe_x_preferred":[
        "Kandara"
    ],
    "wof:name":"Kandara",
    "wof:placetype":"locality",
    "wof:population":65
},
  "geometry": {"coordinates":[78.73437699999999,29.971024],"type":"Point"}
}