{
  "type": "Feature",
  "properties": {
    "gn:admin1_code":"36",
    "gn:admin2_code":"161.0",
    "gn:asciiname":"Barhpura",
    "gn:country_code":"IN",
    "gn:dem":151,
    "gn:feature_class":"P",
    "gn:feature_code":"PPL",
    "gn:name":"Barhpura",
    "gn:population":0,
    "gn:timezone":"Asia/Kolkata",
    "iso:country":"IN",
    "ks:ks_name":"Barhpura",
    "ks:ks_type":"VILLAGE",
    "name:eng_x_preferred":[
        "Barhpura"
    ],
    "wof:name":"Barhpura",
    "wof:placetype":"locality"
},
  "geometry": {"coordinates":[78.906509,26.710692],"type":"Point"}
}