{
  "type": "Feature",
  "properties": {
    "iso:country":"IN",
    "ks:ks_alt_nam":"UTTAR TOLA",
    "ks:ks_name":"Uttar Tola",
    "ks:ks_pop":250,
    "ks:ks_type":"HABITATION",
    "ks:ks_uagg_main":0,
    "name:eng_x_preferred":[
        "Uttar Tola"
    ],
    "wof:name":"Uttar Tola",
    "wof:placetype":"neighbourhood",
    "wof:population":250
},
  "geometry": {"coordinates":[84.24398100000001,25.616478],"type":"Point"}
}