{
  "type": "Feature",
  "properties": {
    "iso:country":"IN",
    "ks:ks_name":"Kusmatanr",
    "ks:ks_pop":21,
    "ks:ks_type":"VILLAGE",
    "name:eng_x_preferred":[
        "Kusmatanr"
    ],
    "wof:name":"Kusmatanr",
    "wof:placetype":"locality",
    "wof:population":21
},
  "geometry": {"coordinates":[86.10939999999999,24.532754],"type":"Point"}
}