{
  "type": "Feature",
  "properties": {
    "iso:country":"IN",
    "ks:ks_name":"Bhemiya",
    "ks:ks_pop":475,
    "ks:ks_type":"HABITATION",
    "name:eng_x_preferred":[
        "Bhemiya"
    ],
    "wof:name":"Bhemiya",
    "wof:placetype":"locality",
    "wof:population":475
},
  "geometry": {"coordinates":[86.731982,24.81999],"type":"Point"}
}