{
  "type": "Feature",
  "properties": {
    "gn:admin1_code":"2.0",
    "gn:admin2_code":"550.0",
    "gn:asciiname":"Ramapuram",
    "gn:country_code":"IN",
    "gn:dem":17,
    "gn:feature_class":"P",
    "gn:feature_code":"PPL",
    "gn:name":"R\u0101m\u0101puram",
    "gn:population":0,
    "gn:timezone":"Asia/Kolkata",
    "iso:country":"IN",
    "ks:ks_name":"Ramapuram",
    "ks:ks_pop":130,
    "ks:ks_type":"HABITATION",
    "name:ceb_x_preferred":[
        "Ramapuram"
    ],
    "name:eng_x_preferred":[
        "Ramapuram"
    ],
    "name:ita_x_preferred":[
        "Ramapuram"
    ],
    "name:mal_x_preferred":[
        "\u0d30\u0d3e\u0d2e\u0d2a\u0d41\u0d30\u0d02"
    ],
    "name:swe_x_preferred":[
        "Ramapuram"
    ],
    "wof:name":"Ramapuram",
    "wof:placetype":"locality",
    "wof:population":130
},
  "geometry": {"coordinates":[79.97269799999999,14.080523],"type":"Point"}
}