{
  "type": "Feature",
  "properties": {
    "iso:country":"IN",
    "ks:ks_name":"Malkha Dungrcha",
    "ks:ks_pop":380,
    "ks:ks_type":"HABITATION",
    "name:eng_x_preferred":[
        "Malkha Dungrcha"
    ],
    "wof:name":"Malkha Dungrcha",
    "wof:placetype":"locality",
    "wof:population":380
},
  "geometry": {"coordinates":[80.063833,30.053269],"type":"Point"}
}