{
  "type": "Feature",
  "properties": {
    "iso:country":"IN",
    "ks:ks_name":"Patrapara",
    "ks:ks_pop":148,
    "ks:ks_type":"VILLAGE",
    "name:eng_x_preferred":[
        "Patrapara"
    ],
    "wof:name":"Patrapara",
    "wof:placetype":"locality",
    "wof:population":148
},
  "geometry": {"coordinates":[87.54577999999999,24.603453],"type":"Point"}
}