{
  "type": "Feature",
  "properties": {
    "iso:country":"IN",
    "ks:ks_name":"Gaothanwadi",
    "ks:ks_pop":113,
    "ks:ks_type":"HABITATION",
    "name:eng_x_preferred":[
        "Gaothanwadi"
    ],
    "wof:name":"Gaothanwadi",
    "wof:placetype":"locality",
    "wof:population":113
},
  "geometry": {"coordinates":[73.352497,17.408214],"type":"Point"}
}