{
  "type": "Feature",
  "properties": {
    "gn:admin1_code":"35",
    "gn:admin2_code":"446.0",
    "gn:asciiname":"Senkuwan",
    "gn:country_code":"IN",
    "gn:dem":339,
    "gn:feature_class":"P",
    "gn:feature_code":"PPL",
    "gn:name":"Senkuw\u0101n",
    "gn:population":0,
    "gn:timezone":"Asia/Kolkata",
    "iso:country":"IN",
    "wof:name":"Senkuwan",
    "wof:placetype":"locality"
},
  "geometry": {"coordinates":[78.226,23.10573],"type":"Point"}
}