{
  "type": "Feature",
  "properties": {
    "gn:admin1_code":"34.0",
    "gn:admin2_code":"236.0",
    "gn:asciiname":"Kabilpur",
    "gn:country_code":"IN",
    "gn:dem":168,
    "gn:feature_class":"P",
    "gn:feature_code":"PPL",
    "gn:name":"Kabilpur",
    "gn:population":0,
    "gn:timezone":"Asia/Kolkata",
    "iso:country":"IN",
    "ks:ks_name":"Kabilpur",
    "ks:ks_pop":847,
    "ks:ks_type":"VILLAGE",
    "ks:ks_uagg_main":0,
    "name:eng_x_preferred":[
        "Kabilpur"
    ],
    "wof:name":"Kabilpur",
    "wof:placetype":"neighbourhood",
    "wof:population":847
},
  "geometry": {"coordinates":[85.242452,24.579423],"type":"Point"}
}