{
  "type": "Feature",
  "properties": {
    "iso:country":"IN",
    "ks:ks_name":"Chacham",
    "ks:ks_pop":117,
    "ks:ks_type":"VILLAGE",
    "name:eng_x_preferred":[
        "Chacham"
    ],
    "wof:name":"Chacham",
    "wof:placetype":"locality",
    "wof:population":117
},
  "geometry": {"coordinates":[87.404989,24.840919],"type":"Point"}
}