{
  "type": "Feature",
  "properties": {
    "gn:admin1_code":"34.0",
    "gn:admin2_code":"235.0",
    "gn:asciiname":"Mayapur",
    "gn:country_code":"IN",
    "gn:dem":99,
    "gn:feature_class":"P",
    "gn:feature_code":"PPL",
    "gn:name":"M\u0101y\u0101pur",
    "gn:population":0,
    "gn:timezone":"Asia/Kolkata",
    "iso:country":"IN",
    "name:ben_x_preferred":[
        "\u09ae\u09be\u09af\u09bc\u09be\u09aa\u09c1\u09b0"
    ],
    "name:ces_x_preferred":[
        "Majapur"
    ],
    "name:deu_x_preferred":[
        "Mayapur"
    ],
    "name:fra_x_preferred":[
        "Mayapur"
    ],
    "name:hin_x_preferred":[
        "\u092e\u093e\u092f\u093e\u092a\u0941\u0930"
    ],
    "name:hun_x_preferred":[
        "M\u00e1j\u00e1pur"
    ],
    "name:pol_x_preferred":[
        "Majapur"
    ],
    "name:rus_x_preferred":[
        "\u041c\u0430\u044f\u043f\u0443\u0440"
    ],
    "name:spa_x_preferred":[
        "M\u0101y\u0101pur"
    ],
    "name:tat_x_preferred":[
        "\u041c\u0430\u044f\u043f\u0443\u0440"
    ],
    "name:ukr_x_preferred":[
        "\u041c\u0430\u044f\u043f\u0443\u0440"
    ],
    "name:urd_x_preferred":[
        "\u0645\u0627\u06cc\u0627 \u067e\u0648\u0631"
    ],
    "wof:name":"Mayapur",
    "wof:placetype":"locality"
},
  "geometry": {"coordinates":[84.39244000000002,24.87813],"type":"Point"}
}