{
  "type": "Feature",
  "properties": {
    "iso:country":"IN",
    "ks:ks_name":"Yolbong Lungrep",
    "ks:ks_pop":650,
    "ks:ks_type":"HABITATION",
    "name:eng_x_preferred":[
        "Yolbong Lungrep"
    ],
    "wof:name":"Yolbong Lungrep",
    "wof:placetype":"locality",
    "wof:population":650
},
  "geometry": {"coordinates":[88.578863,26.948784],"type":"Point"}
}