{
  "type": "Feature",
  "properties": {
    "gn:admin1_code":"12.0",
    "gn:admin2_code":"16.0",
    "gn:asciiname":"Sar",
    "gn:country_code":"IN",
    "gn:dem":2862,
    "gn:feature_class":"P",
    "gn:feature_code":"PPL",
    "gn:name":"Sar",
    "gn:population":0,
    "gn:timezone":"Asia/Kolkata",
    "iso:country":"IN",
    "wof:name":"Sar",
    "wof:placetype":"locality"
},
  "geometry": {"coordinates":[75.52508,33.02161],"type":"Point"}
}