{
  "type": "Feature",
  "properties": {
    "iso:country":"IN",
    "ks:ks_name":"Devarahosakoppa",
    "ks:ks_pop":300,
    "ks:ks_type":"VILLAGE",
    "name:eng_x_preferred":[
        "Devarahosakoppa"
    ],
    "wof:name":"Devarahosakoppa",
    "wof:placetype":"locality",
    "wof:population":300
},
  "geometry": {"coordinates":[75.09282,14.618789],"type":"Point"}
}