{
  "type": "Feature",
  "properties": {
    "gn:admin1_code":"2.0",
    "gn:admin2_code":"554.0",
    "gn:asciiname":"Gunduvaripalle",
    "gn:country_code":"IN",
    "gn:dem":837,
    "gn:feature_class":"P",
    "gn:feature_code":"PPL",
    "gn:name":"Gunduv\u0101ripalle",
    "gn:population":0,
    "gn:timezone":"Asia/Kolkata",
    "iso:country":"IN",
    "wof:name":"Gunduvaripalle",
    "wof:placetype":"locality"
},
  "geometry": {"coordinates":[78.39416,13.4083],"type":"Point"}
}