{
  "type": "Feature",
  "properties": {
    "iso:country":"IN",
    "ks:ks_name":"Mishra Tola",
    "ks:ks_pop":77,
    "ks:ks_type":"HABITATION",
    "ks:ks_uagg_main":0,
    "name:eng_x_preferred":[
        "Mishra Tola"
    ],
    "wof:name":"Mishra Tola",
    "wof:placetype":"neighbourhood",
    "wof:population":77
},
  "geometry": {"coordinates":[83.65648299999999,27.06648],"type":"Point"}
}