{
  "type": "Feature",
  "properties": {
    "iso:country":"IN",
    "ks:ks_name":"Gosainbari",
    "ks:ks_pop":502,
    "ks:ks_type":"VILLAGE",
    "ks:ks_uagg_main":0,
    "name:eng_x_preferred":[
        "Gosainbari"
    ],
    "wof:name":"Gosainbari",
    "wof:placetype":"neighbourhood",
    "wof:population":502
},
  "geometry": {"coordinates":[93.842337,27.003989],"type":"Point"}
}