{
  "type": "Feature",
  "properties": {
    "gn:admin1_code":"40",
    "gn:admin2_code":"535.0",
    "gn:asciiname":"Chapial",
    "gn:country_code":"IN",
    "gn:dem":510,
    "gn:feature_class":"P",
    "gn:feature_code":"PPL",
    "gn:name":"Chapial",
    "gn:population":0,
    "gn:timezone":"Asia/Kolkata",
    "iso:country":"IN",
    "wof:name":"Chapial",
    "wof:placetype":"locality"
},
  "geometry": {"coordinates":[78.65376999999999,18.03411],"type":"Point"}
}