{
  "type": "Feature",
  "properties": {
    "gn:admin1_code":"25.0",
    "gn:admin2_code":"608.0",
    "gn:asciiname":"Kaliyur",
    "gn:country_code":"IN",
    "gn:dem":313,
    "gn:feature_class":"P",
    "gn:feature_code":"PPL",
    "gn:name":"K\u0101liy\u016br",
    "gn:population":0,
    "gn:timezone":"Asia/Kolkata",
    "iso:country":"IN",
    "wof:name":"Kaliyur",
    "wof:placetype":"locality"
},
  "geometry": {"coordinates":[77.87595999999998,11.79908],"type":"Point"}
}