{
  "type": "Feature",
  "properties": {
    "iso:country":"IN",
    "ks:ks_name":"Ankarimarlu",
    "ks:ks_pop":221,
    "ks:ks_type":"HABITATION",
    "name:eng_x_preferred":[
        "Ankarimarlu"
    ],
    "wof:name":"Ankarimarlu",
    "wof:placetype":"locality",
    "wof:population":221
},
  "geometry": {"coordinates":[75.340226,13.038726],"type":"Point"}
}