{
  "type": "Feature",
  "properties": {
    "iso:country":"IN",
    "ks:ks_alt_nam":"Bhand\u0101r\u012bmunda",
    "ks:ks_name":"Bhandarimunda",
    "ks:ks_pop":389,
    "ks:ks_type":"VILLAGE",
    "name:eng_x_preferred":[
        "Bhandarimunda"
    ],
    "name:eng_x_variant":[
        "Bhand\u0101r\u012bmunda"
    ],
    "wof:name":"Bhandarimunda",
    "wof:placetype":"locality",
    "wof:population":389
},
  "geometry": {"coordinates":[84.361902,20.91836],"type":"Point"}
}