{
  "type": "Feature",
  "properties": {
    "iso:country":"IN",
    "ks:ks_name":"Taliwadi",
    "ks:ks_pop":941,
    "ks:ks_type":"HABITATION",
    "name:eng_x_preferred":[
        "Taliwadi"
    ],
    "wof:name":"Taliwadi",
    "wof:placetype":"locality",
    "wof:population":941
},
  "geometry": {"coordinates":[73.40313,16.883663],"type":"Point"}
}