{
  "type": "Feature",
  "properties": {
    "iso:country":"IN",
    "ks:ks_alt_nam":"Chilli chode",
    "ks:ks_name":"Chilli Chode",
    "ks:ks_pop":16,
    "ks:ks_type":"HABITATION",
    "name:eng_x_preferred":[
        "Chilli Chode"
    ],
    "wof:name":"Chilli Chode",
    "wof:placetype":"locality",
    "wof:population":16
},
  "geometry": {"coordinates":[76.042984,11.495678],"type":"Point"}
}