{
  "type": "Feature",
  "properties": {
    "gn:admin1_code":"21.0",
    "gn:admin2_code":"395.0",
    "gn:asciiname":"Durduri",
    "gn:country_code":"IN",
    "gn:dem":255,
    "gn:feature_class":"P",
    "gn:feature_code":"PPL",
    "gn:name":"Durduri",
    "gn:population":0,
    "gn:timezone":"Asia/Kolkata",
    "iso:country":"IN",
    "wof:name":"Durduri",
    "wof:placetype":"locality"
},
  "geometry": {"coordinates":[83.15552,19.85563],"type":"Point"}
}