{
  "type": "Feature",
  "properties": {
    "gn:admin1_code":"21.0",
    "gn:admin2_code":"395.0",
    "gn:asciiname":"Durduri",
    "gn:country_code":"IN",
    "gn:dem":255,
    "gn:feature_class":"P",
    "gn:feature_code":"PPL",
    "gn:name":"Durduri",
    "gn:population":0,
    "gn:timezone":"Asia/Kolkata",
    "iso:country":"IN",
    "ks:ks_name":"Durduri",
    "ks:ks_pop":281,
    "ks:ks_type":"VILLAGE",
    "name:eng_x_preferred":[
        "Durduri"
    ],
    "wof:name":"Durduri",
    "wof:placetype":"locality",
    "wof:population":281
},
  "geometry": {"coordinates":[83.16251800000001,19.863062],"type":"Point"}
}