{
  "type": "Feature",
  "properties": {
    "iso:country":"IN",
    "ks:ks_name":"Patichamala",
    "ks:ks_pop":166,
    "ks:ks_type":"HABITATION",
    "name:eng_x_preferred":[
        "Patichamala"
    ],
    "wof:name":"Patichamala",
    "wof:placetype":"locality",
    "wof:population":166
},
  "geometry": {"coordinates":[74.249362,17.9797],"type":"Point"}
}