{
  "type": "Feature",
  "properties": {
    "gn:admin1_code":"11.0",
    "gn:admin2_code":"24.0",
    "gn:asciiname":"Kau",
    "gn:country_code":"IN",
    "gn:dem":535,
    "gn:feature_class":"P",
    "gn:feature_code":"PPL",
    "gn:name":"Kau",
    "gn:population":0,
    "gn:timezone":"Asia/Kolkata",
    "iso:country":"IN",
    "name:ceb_x_preferred":[
        "Kau"
    ],
    "name:fra_x_preferred":[
        "Kau"
    ],
    "name:swe_x_preferred":[
        "Kau"
    ],
    "wof:name":"Kau",
    "wof:placetype":"locality"
},
  "geometry": {"coordinates":[75.96835,32.20149],"type":"Point"}
}