{
  "type": "Feature",
  "properties": {
    "gn:admin1_code":"36.0",
    "gn:admin2_code":"136.0",
    "gn:asciiname":"Mazra Mandaiyan Tulsi",
    "gn:country_code":"IN",
    "gn:dem":180,
    "gn:feature_class":"P",
    "gn:feature_code":"PPL",
    "gn:name":"Mazra Mandaiy\u0101n Tulsi",
    "gn:population":0,
    "gn:timezone":"Asia/Kolkata",
    "iso:country":"IN",
    "wof:name":"Mazra Mandaiyan Tulsi",
    "wof:placetype":"locality"
},
  "geometry": {"coordinates":[78.98687,28.60081],"type":"Point"}
}