{
  "type": "Feature",
  "properties": {
    "iso:country":"IN",
    "ks:ks_name":"Gohalamura",
    "ks:ks_pop":393,
    "ks:ks_type":"VILLAGE",
    "name:eng_x_preferred":[
        "Gohalamura"
    ],
    "wof:name":"Gohalamura",
    "wof:placetype":"locality",
    "wof:population":393
},
  "geometry": {"coordinates":[86.845783,22.293618],"type":"Point"}
}