{
  "type": "Feature",
  "properties": {
    "iso:country":"IN",
    "ks:ks_name":"Amuniagobindapur",
    "ks:ks_pop":628,
    "ks:ks_type":"VILLAGE",
    "name:eng_x_preferred":[
        "Amuniagobindapur"
    ],
    "wof:name":"Amuniagobindapur",
    "wof:placetype":"locality",
    "wof:population":628
},
  "geometry": {"coordinates":[84.819804,19.492137],"type":"Point"}
}