{
  "type": "Feature",
  "properties": {
    "iso:country":"IN",
    "ks:ks_name":"Pokhri",
    "ks:ks_pop":16,
    "ks:ks_type":"VILLAGE",
    "name:eng_x_preferred":[
        "Pokhri"
    ],
    "wof:name":"Pokhri",
    "wof:placetype":"locality",
    "wof:population":16
},
  "geometry": {"coordinates":[79.58187100000001,29.487474],"type":"Point"}
}