{
  "type": "Feature",
  "properties": {
    "gn:admin1_code":"2.0",
    "gn:admin2_code":"554.0",
    "gn:asciiname":"Raganipalle",
    "gn:country_code":"IN",
    "gn:dem":744,
    "gn:feature_class":"P",
    "gn:feature_code":"PPL",
    "gn:name":"R\u0101g\u0101nipalle",
    "gn:population":0,
    "gn:timezone":"Asia/Kolkata",
    "iso:country":"IN",
    "wof:name":"Raganipalle",
    "wof:placetype":"locality"
},
  "geometry": {"coordinates":[78.57802,13.39489],"type":"Point"}
}