{
  "type": "Feature",
  "properties": {
    "iso:country":"IN",
    "ks:ks_name":"Khytoliya",
    "ks:ks_pop":305,
    "ks:ks_type":"HABITATION",
    "name:eng_x_preferred":[
        "Khytoliya"
    ],
    "wof:name":"Khytoliya",
    "wof:placetype":"locality",
    "wof:population":305
},
  "geometry": {"coordinates":[82.61913300000001,27.197541],"type":"Point"}
}