{
  "type": "Feature",
  "properties": {
    "gn:admin1_code":"34",
    "gn:admin2_code":"212.0",
    "gn:asciiname":"Semapur",
    "gn:country_code":"IN",
    "gn:dem":38,
    "gn:feature_class":"P",
    "gn:feature_code":"PPL",
    "gn:name":"Sem\u0101pur",
    "gn:population":0,
    "gn:timezone":"Asia/Kolkata",
    "iso:country":"IN",
    "wof:name":"Semapur",
    "wof:placetype":"neighbourhood"
},
  "geometry": {"coordinates":[87.46688,25.52454],"type":"Point"}
}