{
  "type": "Feature",
  "properties": {
    "iso:country":"IN",
    "ks:ks_name":"Naigaon",
    "ks:ks_pop":641,
    "ks:ks_type":"VILLAGE",
    "name:eng_x_preferred":[
        "Naigaon"
    ],
    "wof:name":"Naigaon",
    "wof:placetype":"locality",
    "wof:population":641
},
  "geometry": {"coordinates":[90.198999,26.522977],"type":"Point"}
}