{
  "type": "Feature",
  "properties": {
    "iso:country":"IN",
    "ks:ks_name":"Dunga",
    "ks:ks_pop":1166,
    "ks:ks_type":"HABITATION",
    "name:eng_x_preferred":[
        "Dunga"
    ],
    "wof:name":"Dunga",
    "wof:placetype":"locality",
    "wof:population":1166
},
  "geometry": {"coordinates":[81.053927,19.294008],"type":"Point"}
}