{
  "type": "Feature",
  "properties": {
    "iso:country":"IN",
    "ks:ks_name":"Kodayagoundanpatti",
    "ks:ks_pop":510,
    "ks:ks_type":"HABITATION",
    "name:eng_x_preferred":[
        "Kodayagoundanpatti"
    ],
    "wof:name":"Kodayagoundanpatti",
    "wof:placetype":"locality",
    "wof:population":510
},
  "geometry": {"coordinates":[78.452611,10.552706],"type":"Point"}
}