{
  "type": "Feature",
  "properties": {
    "iso:country":"IN",
    "ks:ks_name":"Kakulam",
    "ks:ks_pop":32,
    "ks:ks_type":"HABITATION",
    "name:eng_x_preferred":[
        "Kakulam"
    ],
    "wof:name":"Kakulam",
    "wof:placetype":"locality",
    "wof:population":32
},
  "geometry": {"coordinates":[78.696443,9.736347],"type":"Point"}
}