{
  "type": "Feature",
  "properties": {
    "iso:country":"IN",
    "ks:ks_name":"23 DWD",
    "ks:ks_pop":337,
    "ks:ks_type":"VILLAGE",
    "name:eng_x_preferred":[
        "23 DWD"
    ],
    "wof:name":"23 DWD",
    "wof:placetype":"locality",
    "wof:population":337
},
  "geometry": {"coordinates":[74.375728,29.218949],"type":"Point"}
}