{
  "type": "Feature",
  "properties": {
    "gn:admin1_code":"21.0",
    "gn:admin2_code":"370",
    "gn:asciiname":"Bhursipali",
    "gn:country_code":"IN",
    "gn:dem":182,
    "gn:feature_class":"P",
    "gn:feature_code":"PPL",
    "gn:name":"Bhursip\u0101li",
    "gn:population":0,
    "gn:timezone":"Asia/Kolkata",
    "iso:country":"IN",
    "name:und_x_variant":[
        "Bhursipuli",
        "Bhursip\u0101li"
    ],
    "wof:name":"Bhursipali",
    "wof:placetype":"locality"
},
  "geometry": {"coordinates":[83.745,21.39332000000001],"type":"Point"}
}