{
  "type": "Feature",
  "properties": {
    "gn:admin1_code":"36",
    "gn:admin2_code":"155.0",
    "gn:asciiname":"Lakhai Khera",
    "gn:country_code":"IN",
    "gn:dem":128,
    "gn:feature_class":"P",
    "gn:feature_code":"PPL",
    "gn:name":"Lakhai Khera",
    "gn:population":0,
    "gn:timezone":"Asia/Kolkata",
    "iso:country":"IN",
    "ks:ks_name":"Lakhai Khera",
    "ks:ks_pop":132,
    "ks:ks_type":"HABITATION",
    "ks:ks_uagg_main":0,
    "name:eng_x_preferred":[
        "Lakhai Khera"
    ],
    "wof:name":"Lakhai Khera",
    "wof:placetype":"neighbourhood",
    "wof:population":132
},
  "geometry": {"coordinates":[80.675061,27.097391],"type":"Point"}
}