{
  "type": "Feature",
  "properties": {
    "gn:admin1_code":"12.0",
    "gn:admin2_code":"005",
    "gn:asciiname":"Kasalran",
    "gn:country_code":"IN",
    "gn:dem":1004,
    "gn:feature_class":"P",
    "gn:feature_code":"PPL",
    "gn:name":"Kasalr\u0101n",
    "gn:population":0,
    "gn:timezone":"Asia/Kolkata",
    "iso:country":"IN",
    "name:und_x_variant":[
        "Kasalr\u0101n",
        "Kasal\u012ban",
        "Kasal\u012byan"
    ],
    "wof:name":"Kasalran",
    "wof:placetype":"locality"
},
  "geometry": {"coordinates":[74.05207,33.77607],"type":"Point"}
}