{
  "type": "Feature",
  "properties": {
    "iso:country":"IN",
    "ks:ks_name":"Ganeshnagar",
    "ks:ks_pop":771,
    "ks:ks_type":"HABITATION",
    "name:eng_x_preferred":[
        "Ganeshnagar"
    ],
    "wof:name":"Ganeshnagar",
    "wof:placetype":"locality",
    "wof:population":771
},
  "geometry": {"coordinates":[72.69989200000001,27.230553],"type":"Point"}
}