{
  "type": "Feature",
  "properties": {
    "iso:country":"IN",
    "ks:ks_name":"Mirjapur",
    "ks:ks_pop":926,
    "ks:ks_type":"VILLAGE",
    "name:eng_x_preferred":[
        "Mirjapur"
    ],
    "wof:name":"Mirjapur",
    "wof:placetype":"locality",
    "wof:population":926
},
  "geometry": {"coordinates":[86.281154,20.814225],"type":"Point"}
}