{
  "type": "Feature",
  "properties": {
    "iso:country":"IN",
    "ks:ks_name":"Ottamaungal",
    "ks:ks_pop":1821,
    "ks:ks_type":"HABITATION",
    "name:eng_x_preferred":[
        "Ottamaungal"
    ],
    "wof:name":"Ottamaungal",
    "wof:placetype":"locality",
    "wof:population":1821
},
  "geometry": {"coordinates":[75.22642500000001,12.497291],"type":"Point"}
}