{
  "type": "Feature",
  "properties": {
    "iso:country":"IN",
    "ks:ks_name":"Hanuman Mushahari",
    "ks:ks_pop":427,
    "ks:ks_type":"HABITATION",
    "name:eng_x_preferred":[
        "Hanuman Mushahari"
    ],
    "wof:name":"Hanuman Mushahari",
    "wof:placetype":"locality",
    "wof:population":427
},
  "geometry": {"coordinates":[86.87575,25.742595],"type":"Point"}
}