{
  "type": "Feature",
  "properties": {
    "iso:country":"IN",
    "ks:ks_name":"Katkna",
    "ks:ks_pop":64,
    "ks:ks_type":"HABITATION",
    "name:eng_x_preferred":[
        "Katkna"
    ],
    "wof:name":"Katkna",
    "wof:placetype":"locality",
    "wof:population":64
},
  "geometry": {"coordinates":[84.38385599999999,24.499052],"type":"Point"}
}