{
  "type": "Feature",
  "properties": {
    "gn:admin1_code":"09",
    "gn:admin2_code":"468.0",
    "gn:asciiname":"Sandhan",
    "gn:country_code":"IN",
    "gn:dem":21,
    "gn:feature_class":"P",
    "gn:feature_code":"PPL",
    "gn:name":"S\u0101ndh\u0101n",
    "gn:population":0,
    "gn:timezone":"Asia/Kolkata",
    "iso:country":"IN",
    "name:guj_x_preferred":[
        "\u0ab8\u0abe\u0a82\u0aa7\u0abe\u0aa3"
    ],
    "name:und_x_variant":[
        "S\u0101ndh\u0101n"
    ],
    "wof:name":"Sandhan",
    "wof:placetype":"locality"
},
  "geometry": {"coordinates":[68.99341,23.02069],"type":"Point"}
}