{
  "type": "Feature",
  "properties": {
    "gn:admin1_code":"09",
    "gn:admin2_code":"493.0",
    "gn:asciiname":"Vajpur",
    "gn:country_code":"IN",
    "gn:dem":96,
    "gn:feature_class":"P",
    "gn:feature_code":"PPL",
    "gn:name":"V\u0101jpur",
    "gn:population":0,
    "gn:timezone":"Asia/Kolkata",
    "iso:country":"IN",
    "ks:ks_alt_nam":"V\u0101jpur",
    "ks:ks_name":"Vajpur",
    "ks:ks_type":"VILLAGE",
    "name:eng_x_preferred":[
        "Vajpur"
    ],
    "name:eng_x_variant":[
        "V\u0101jpur"
    ],
    "wof:name":"Vajpur",
    "wof:placetype":"locality"
},
  "geometry": {"coordinates":[73.77395799999999,21.367608],"type":"Point"}
}