{
  "type": "Feature",
  "properties": {
    "gn:admin1_code":"35.0",
    "gn:admin2_code":"444",
    "gn:asciiname":"Karhaia Khoh",
    "gn:country_code":"IN",
    "gn:dem":508,
    "gn:feature_class":"P",
    "gn:feature_code":"PPL",
    "gn:name":"Karhaia Khoh",
    "gn:population":0,
    "gn:timezone":"Asia/Kolkata",
    "iso:country":"IN",
    "wof:name":"Karhaia Khoh",
    "wof:placetype":"locality"
},
  "geometry": {"coordinates":[77.28676999999998,23.63286],"type":"Point"}
}