{
  "type": "Feature",
  "properties": {
    "iso:country":"IN",
    "ks:ks_name":"Lag",
    "ks:ks_pop":158,
    "ks:ks_type":"HABITATION",
    "name:eng_x_preferred":[
        "Lag"
    ],
    "wof:name":"Lag",
    "wof:placetype":"locality",
    "wof:population":158
},
  "geometry": {"coordinates":[73.988383,24.365808],"type":"Point"}
}