{
  "type": "Feature",
  "properties": {
    "iso:country":"IN",
    "ks:ks_name":"Badalpur",
    "ks:ks_pop":738,
    "ks:ks_type":"VILLAGE",
    "ks:ks_uagg_main":0,
    "name:eng_x_preferred":[
        "Badalpur"
    ],
    "wof:name":"Badalpur",
    "wof:placetype":"neighbourhood",
    "wof:population":738
},
  "geometry": {"coordinates":[88.49335499999999,25.26692],"type":"Point"}
}