{
  "type": "Feature",
  "properties": {
    "gn:admin1_code":"24.0",
    "gn:admin2_code":"126.0",
    "gn:asciiname":"Jiwanayak ka Khera",
    "gn:country_code":"IN",
    "gn:dem":418,
    "gn:feature_class":"P",
    "gn:feature_code":"PPL",
    "gn:name":"J\u012bw\u0101n\u0101yak ka Khera",
    "gn:population":0,
    "gn:timezone":"Asia/Kolkata",
    "iso:country":"IN",
    "wof:name":"Jiwanayak ka Khera",
    "wof:placetype":"locality"
},
  "geometry": {"coordinates":[74.64475999999998,25.08484],"type":"Point"}
}