{
  "type": "Feature",
  "properties": {
    "iso:country":"IN",
    "ks:ks_name":"Puwasa",
    "ks:ks_pop":1335,
    "ks:ks_type":"VILLAGE",
    "name:eng_x_preferred":[
        "Puwasa"
    ],
    "wof:name":"Puwasa",
    "wof:placetype":"locality",
    "wof:population":1335
},
  "geometry": {"coordinates":[74.275705,22.120031],"type":"Point"}
}