{
  "type": "Feature",
  "properties": {
    "iso:country":"IN",
    "ks:ks_alt_nam":"KALABARI BASTI",
    "ks:ks_name":"Kalabari Basti",
    "ks:ks_pop":459,
    "ks:ks_type":"HABITATION",
    "name:eng_x_preferred":[
        "Kalabari Basti"
    ],
    "wof:name":"Kalabari Basti",
    "wof:placetype":"locality",
    "wof:population":459
},
  "geometry": {"coordinates":[88.934685,26.790545],"type":"Point"}
}