{
  "type": "Feature",
  "properties": {
    "iso:country":"IN",
    "ks:ks_name":"Bhardi",
    "ks:ks_pop":0,
    "ks:ks_type":"VILLAGE",
    "name:eng_x_preferred":[
        "Bhardi"
    ],
    "wof:name":"Bhardi",
    "wof:placetype":"locality",
    "wof:population":0
},
  "geometry": {"coordinates":[78.803219,20.459661],"type":"Point"}
}