{
  "type": "Feature",
  "properties": {
    "gn:admin1_code":"12.0",
    "gn:admin2_code":"19.0",
    "gn:asciiname":"Chhapra Lahr",
    "gn:country_code":"IN",
    "gn:dem":1808,
    "gn:feature_class":"P",
    "gn:feature_code":"PPL",
    "gn:name":"Chhapra Lahr",
    "gn:population":0,
    "gn:timezone":"Asia/Kolkata",
    "iso:country":"IN",
    "wof:name":"Chhapra Lahr",
    "wof:placetype":"locality"
},
  "geometry": {"coordinates":[75.05072,33.01786],"type":"Point"}
}