{
  "type": "Feature",
  "properties": {
    "iso:country":"IN",
    "ks:ks_name":"Pubapada",
    "ks:ks_pop":662,
    "ks:ks_type":"VILLAGE",
    "name:eng_x_preferred":[
        "Pubapada"
    ],
    "wof:name":"Pubapada",
    "wof:placetype":"locality",
    "wof:population":662
},
  "geometry": {"coordinates":[86.293997,20.304071],"type":"Point"}
}