{
  "type": "Feature",
  "properties": {
    "iso:country":"IN",
    "ks:ks_name":"Pimpalchoch",
    "ks:ks_pop":65,
    "ks:ks_type":"HABITATION",
    "name:eng_x_preferred":[
        "Pimpalchoch"
    ],
    "wof:name":"Pimpalchoch",
    "wof:placetype":"locality",
    "wof:population":65
},
  "geometry": {"coordinates":[76.380831,20.657493],"type":"Point"}
}