{
  "type": "Feature",
  "properties": {
    "gn:admin1_code":"36",
    "gn:admin2_code":"194.0",
    "gn:asciiname":"Mahngupur",
    "gn:country_code":"IN",
    "gn:dem":85,
    "gn:feature_class":"P",
    "gn:feature_code":"PPL",
    "gn:name":"Mahng\u016bpur",
    "gn:population":0,
    "gn:timezone":"Asia/Kolkata",
    "iso:country":"IN",
    "ks:ks_name":"Mahagupur",
    "ks:ks_pop":237,
    "ks:ks_type":"VILLAGE",
    "ks:ks_uagg_main":0,
    "name:eng_x_preferred":[
        "Mahagupur"
    ],
    "wof:name":"Mahagupur",
    "wof:placetype":"locality",
    "wof:population":237
},
  "geometry": {"coordinates":[82.72294599999999,25.768792],"type":"Point"}
}