{
  "type": "Feature",
  "properties": {
    "iso:country":"IN",
    "ks:ks_name":"Kolipatti",
    "ks:ks_pop":150,
    "ks:ks_type":"HABITATION",
    "name:eng_x_preferred":[
        "Kolipatti"
    ],
    "wof:name":"Kolipatti",
    "wof:placetype":"locality",
    "wof:population":150
},
  "geometry": {"coordinates":[78.404954,9.387016],"type":"Point"}
}