{
  "type": "Feature",
  "properties": {
    "iso:country":"IN",
    "ks:ks_name":"Kiddan Paguthi",
    "ks:ks_pop":227,
    "ks:ks_type":"HABITATION",
    "name:eng_x_preferred":[
        "Kiddan Paguthi"
    ],
    "wof:name":"Kiddan Paguthi",
    "wof:placetype":"locality",
    "wof:population":227
},
  "geometry": {"coordinates":[79.15891000000001,12.751852],"type":"Point"}
}