{
  "type": "Feature",
  "properties": {
    "iso:country":"IN",
    "ks:ks_alt_nam":"jhalia purwa",
    "ks:ks_name":"Jhalia Purwa",
    "ks:ks_pop":201,
    "ks:ks_type":"HABITATION",
    "ks:ks_uagg_main":0,
    "name:eng_x_preferred":[
        "Jhalia Purwa"
    ],
    "wof:name":"Jhalia Purwa",
    "wof:placetype":"neighbourhood",
    "wof:population":201
},
  "geometry": {"coordinates":[81.715491,27.323593],"type":"Point"}
}