{
  "type": "Feature",
  "properties": {
    "iso:country":"IN",
    "ks:ks_name":"Basera Patti",
    "ks:ks_pop":0,
    "ks:ks_type":"VILLAGE",
    "name:eng_x_preferred":[
        "Basera Patti"
    ],
    "wof:name":"Basera Patti",
    "wof:placetype":"locality",
    "wof:population":0
},
  "geometry": {"coordinates":[78.762558,28.682532],"type":"Point"}
}