{
  "type": "Feature",
  "properties": {
    "iso:country":"IN",
    "ks:ks_name":"Thakarwadi",
    "ks:ks_pop":222,
    "ks:ks_type":"HABITATION",
    "name:eng_x_preferred":[
        "Thakarwadi"
    ],
    "wof:name":"Thakarwadi",
    "wof:placetype":"locality",
    "wof:population":222
},
  "geometry": {"coordinates":[73.790791,19.211165],"type":"Point"}
}