{
  "type": "Feature",
  "properties": {
    "iso:country":"IN",
    "ks:ks_name":"Mukuna",
    "ks:ks_pop":0,
    "ks:ks_type":"VILLAGE",
    "name:eng_x_preferred":[
        "Mukuna"
    ],
    "wof:name":"Mukuna",
    "wof:placetype":"locality",
    "wof:population":0
},
  "geometry": {"coordinates":[85.811729,21.940697],"type":"Point"}
}