{
  "type": "Feature",
  "properties": {
    "iso:country":"IN",
    "ks:ks_alt_nam":"Majhauli-Bairamu",
    "ks:ks_name":"Majhauli-bairamu",
    "ks:ks_pop":7,
    "ks:ks_type":"HABITATION",
    "name:eng_x_preferred":[
        "Majhauli-bairamu"
    ],
    "wof:name":"Majhauli-bairamu",
    "wof:placetype":"locality",
    "wof:population":7
},
  "geometry": {"coordinates":[83.475646,23.523379],"type":"Point"}
}