{
  "type": "Feature",
  "properties": {
    "gn:admin1_code":"2.0",
    "gn:admin2_code":"554.0",
    "gn:asciiname":"Nayanipalli",
    "gn:country_code":"IN",
    "gn:dem":770,
    "gn:feature_class":"P",
    "gn:feature_code":"PPL",
    "gn:name":"N\u0101yanipalli",
    "gn:population":0,
    "gn:timezone":"Asia/Kolkata",
    "iso:country":"IN",
    "wof:name":"Nayanipalli",
    "wof:placetype":"neighbourhood"
},
  "geometry": {"coordinates":[78.44176,12.90831],"type":"Point"}
}