{
  "type": "Feature",
  "properties": {
    "iso:country":"IN",
    "ks:ks_name":"Fakir Basti",
    "ks:ks_pop":259,
    "ks:ks_type":"HABITATION",
    "name:eng_x_preferred":[
        "Fakir Basti"
    ],
    "wof:name":"Fakir Basti",
    "wof:placetype":"locality",
    "wof:population":259
},
  "geometry": {"coordinates":[88.074592,26.347178],"type":"Point"}
}