{
  "type": "Feature",
  "properties": {
    "iso:country":"IN",
    "ks:ks_name":"Muslim Para",
    "ks:ks_pop":1076,
    "ks:ks_type":"HABITATION",
    "name:eng_x_preferred":[
        "Muslim Para"
    ],
    "wof:name":"Muslim Para",
    "wof:placetype":"locality",
    "wof:population":1076
},
  "geometry": {"coordinates":[89.064424,26.637429],"type":"Point"}
}