{
  "type": "Feature",
  "properties": {
    "iso:country":"IN",
    "ks:ks_name":"Shanthanagadde",
    "ks:ks_pop":127,
    "ks:ks_type":"HABITATION",
    "name:eng_x_preferred":[
        "Shanthanagadde"
    ],
    "wof:name":"Shanthanagadde",
    "wof:placetype":"locality",
    "wof:population":127
},
  "geometry": {"coordinates":[75.096395,13.953356],"type":"Point"}
}