{
  "type": "Feature",
  "properties": {
    "iso:country":"IN",
    "ks:ks_name":"Simulbari",
    "ks:ks_pop":977,
    "ks:ks_type":"HABITATION",
    "ks:ks_uagg_main":0,
    "name:eng_x_preferred":[
        "Simulbari"
    ],
    "wof:name":"Simulbari",
    "wof:placetype":"neighbourhood",
    "wof:population":977
},
  "geometry": {"coordinates":[90.319208,26.060967],"type":"Point"}
}