{
  "type": "Feature",
  "properties": {
    "iso:country":"IN",
    "ks:ks_name":"Birapatana",
    "ks:ks_pop":119,
    "ks:ks_type":"VILLAGE",
    "name:eng_x_preferred":[
        "Birapatana"
    ],
    "wof:name":"Birapatana",
    "wof:placetype":"locality",
    "wof:population":119
},
  "geometry": {"coordinates":[85.15271300000001,19.73273],"type":"Point"}
}