{
  "type": "Feature",
  "properties": {
    "iso:country":"IN",
    "ks:ks_name":"Bhajircpur",
    "ks:ks_pop":206,
    "ks:ks_type":"HABITATION",
    "ks:ks_uagg_main":0,
    "name:eng_x_preferred":[
        "Bhajircpur"
    ],
    "wof:name":"Bhajircpur",
    "wof:placetype":"neighbourhood",
    "wof:population":206
},
  "geometry": {"coordinates":[81.762123,27.84591],"type":"Point"}
}