{
  "type": "Feature",
  "properties": {
    "iso:country":"IN",
    "ks:ks_name":"Moolegadde",
    "ks:ks_pop":14,
    "ks:ks_type":"HABITATION",
    "name:eng_x_preferred":[
        "Moolegadde"
    ],
    "wof:name":"Moolegadde",
    "wof:placetype":"locality",
    "wof:population":14
},
  "geometry": {"coordinates":[75.640738,12.601584],"type":"Point"}
}