{
  "type": "Feature",
  "properties": {
    "gn:admin1_code":"19.0",
    "gn:admin2_code":"574.0",
    "gn:asciiname":"Yarehalli",
    "gn:country_code":"IN",
    "gn:dem":772,
    "gn:feature_class":"P",
    "gn:feature_code":"PPL",
    "gn:name":"Yarehalli",
    "gn:population":0,
    "gn:timezone":"Asia/Kolkata",
    "iso:country":"IN",
    "wof:name":"Yarehalli",
    "wof:placetype":"locality"
},
  "geometry": {"coordinates":[76.3866,13.48451],"type":"Point"}
}