{
  "type": "Feature",
  "properties": {
    "gn:admin1_code":"19.0",
    "gn:admin2_code":"574.0",
    "gn:asciiname":"Yarehalli",
    "gn:country_code":"IN",
    "gn:dem":772,
    "gn:feature_class":"P",
    "gn:feature_code":"PPL",
    "gn:name":"Yarehalli",
    "gn:population":0,
    "gn:timezone":"Asia/Kolkata",
    "iso:country":"IN",
    "ks:ks_name":"Yarehalli",
    "ks:ks_pop":1025,
    "ks:ks_type":"VILLAGE",
    "name:eng_x_preferred":[
        "Yarehalli"
    ],
    "wof:name":"Yarehalli",
    "wof:placetype":"locality",
    "wof:population":1025
},
  "geometry": {"coordinates":[76.38672699999999,13.487227],"type":"Point"}
}