{
  "type": "Feature",
  "properties": {
    "gn:admin1_code":"2.0",
    "gn:admin2_code":"554.0",
    "gn:asciiname":"Tatireddipalli",
    "gn:country_code":"IN",
    "gn:dem":356,
    "gn:feature_class":"P",
    "gn:feature_code":"PPL",
    "gn:name":"T\u0101tireddipalli",
    "gn:population":0,
    "gn:timezone":"Asia/Kolkata",
    "iso:country":"IN",
    "ks:ks_name":"Thathireddipalle",
    "ks:ks_pop":24,
    "ks:ks_type":"VILLAGE",
    "name:eng_x_preferred":[
        "Thathireddipalle"
    ],
    "name:eng_x_variant":[
        "Tatireddipalli"
    ],
    "wof:name":"Thathireddipalle",
    "wof:placetype":"locality",
    "wof:population":24
},
  "geometry": {"coordinates":[79.164216,13.350502],"type":"Point"}
}