{
  "type": "Feature",
  "properties": {
    "gn:admin1_code":"16",
    "gn:admin2_code":"510.0",
    "gn:asciiname":"Ghotamba",
    "gn:country_code":"IN",
    "gn:dem":297,
    "gn:feature_class":"P",
    "gn:feature_code":"PPL",
    "gn:name":"Ghot\u0101mba",
    "gn:population":0,
    "gn:timezone":"Asia/Kolkata",
    "iso:country":"IN",
    "wof:name":"Ghotamba",
    "wof:placetype":"locality"
},
  "geometry": {"coordinates":[78.46351999999997,20.17293],"type":"Point"}
}