{
  "type": "Feature",
  "properties": {
    "gn:admin1_code":"39.0",
    "gn:admin2_code":"64.0",
    "gn:asciiname":"Ladhyura",
    "gn:country_code":"IN",
    "gn:dem":1542,
    "gn:feature_class":"P",
    "gn:feature_code":"PPL",
    "gn:name":"Ladhyura",
    "gn:population":0,
    "gn:timezone":"Asia/Kolkata",
    "iso:country":"IN",
    "wof:name":"Ladhyura",
    "wof:placetype":"locality"
},
  "geometry": {"coordinates":[79.57571999999998,29.791],"type":"Point"}
}