{
  "type": "Feature",
  "properties": {
    "gn:admin1_code":"39.0",
    "gn:admin2_code":"64.0",
    "gn:asciiname":"Ladhyura",
    "gn:country_code":"IN",
    "gn:dem":1542,
    "gn:feature_class":"P",
    "gn:feature_code":"PPL",
    "gn:name":"Ladhyura",
    "gn:population":0,
    "gn:timezone":"Asia/Kolkata",
    "iso:country":"IN",
    "ks:ks_name":"Ladyura",
    "ks:ks_type":"VILLAGE",
    "name:eng_x_preferred":[
        "Ladyura"
    ],
    "name:eng_x_variant":[
        "Ladhyura"
    ],
    "wof:name":"Ladyura",
    "wof:placetype":"locality"
},
  "geometry": {"coordinates":[79.580904,29.795291],"type":"Point"}
}