{
  "type": "Feature",
  "properties": {
    "iso:country":"IN",
    "ks:ks_name":"Beochitala",
    "ks:ks_pop":913,
    "ks:ks_type":"HABITATION",
    "ks:ks_uagg_main":0,
    "name:eng_x_preferred":[
        "Beochitala"
    ],
    "wof:name":"Beochitala",
    "wof:placetype":"neighbourhood",
    "wof:population":913
},
  "geometry": {"coordinates":[88.381996,24.108631],"type":"Point"}
}