{
  "type": "Feature",
  "properties": {
    "iso:country":"IN",
    "ks:ks_name":"Borkhedi",
    "ks:ks_pop":20,
    "ks:ks_type":"HABITATION",
    "name:eng_x_preferred":[
        "Borkhedi"
    ],
    "wof:name":"Borkhedi",
    "wof:placetype":"locality",
    "wof:population":20
},
  "geometry": {"coordinates":[78.215897,21.288143],"type":"Point"}
}