{
  "type": "Feature",
  "properties": {
    "gn:admin1_code":"35",
    "gn:admin2_code":"423.0",
    "gn:asciiname":"Beharda",
    "gn:country_code":"IN",
    "gn:dem":358,
    "gn:feature_class":"P",
    "gn:feature_code":"PPL",
    "gn:name":"Beharda",
    "gn:population":0,
    "gn:timezone":"Asia/Kolkata",
    "iso:country":"IN",
    "ks:ks_name":"Beharda",
    "ks:ks_pop":334,
    "ks:ks_type":"VILLAGE",
    "name:eng_x_preferred":[
        "Beharda"
    ],
    "wof:name":"Beharda",
    "wof:placetype":"locality",
    "wof:population":334
},
  "geometry": {"coordinates":[77.322095,25.716022],"type":"Point"}
}