{
  "type": "Feature",
  "properties": {
    "gn:admin1_code":"35",
    "gn:admin2_code":"459.0",
    "gn:asciiname":"Karmai",
    "gn:country_code":"IN",
    "gn:dem":450,
    "gn:feature_class":"P",
    "gn:feature_code":"PPL",
    "gn:name":"Karmai",
    "gn:population":0,
    "gn:timezone":"Asia/Kolkata",
    "iso:country":"IN",
    "name:msa_x_preferred":[
        "Karmai"
    ],
    "name:zho_x_preferred":[
        "\u5361\u9ea6\u4e61"
    ],
    "wof:name":"Karmai",
    "wof:placetype":"locality"
},
  "geometry": {"coordinates":[78.14279000000001,24.63526],"type":"Point"}
}