{
  "type": "Feature",
  "properties": {
    "iso:country":"IN",
    "ks:ks_alt_nam":"niripakunnu SC colony",
    "ks:ks_name":"Niripakunnu Sc Colony",
    "ks:ks_pop":401,
    "ks:ks_type":"HABITATION",
    "name:eng_x_preferred":[
        "Niripakunnu Sc Colony"
    ],
    "wof:name":"Niripakunnu Sc Colony",
    "wof:placetype":"locality",
    "wof:population":401
},
  "geometry": {"coordinates":[75.695982,11.574621],"type":"Point"}
}