{
  "type": "Feature",
  "properties": {
    "iso:country":"IN",
    "ks:ks_name":"Tilakipada",
    "ks:ks_pop":87,
    "ks:ks_type":"VILLAGE",
    "name:eng_x_preferred":[
        "Tilakipada"
    ],
    "wof:name":"Tilakipada",
    "wof:placetype":"locality",
    "wof:population":87
},
  "geometry": {"coordinates":[83.742771,20.25748],"type":"Point"}
}