{
  "type": "Feature",
  "properties": {
    "iso:country":"IN",
    "ks:ks_name":"Keradapadar",
    "ks:ks_pop":109,
    "ks:ks_type":"VILLAGE",
    "name:eng_x_preferred":[
        "Keradapadar"
    ],
    "wof:name":"Keradapadar",
    "wof:placetype":"locality",
    "wof:population":109
},
  "geometry": {"coordinates":[83.379119,19.465637],"type":"Point"}
}