{
  "type": "Feature",
  "properties": {
    "iso:country":"IN",
    "ks:ks_alt_nam":"Basant pura",
    "ks:ks_name":"Basant Pura",
    "ks:ks_pop":364,
    "ks:ks_type":"HABITATION",
    "name:eng_x_preferred":[
        "Basant Pura"
    ],
    "wof:name":"Basant Pura",
    "wof:placetype":"locality",
    "wof:population":364
},
  "geometry": {"coordinates":[77.589505,25.060746],"type":"Point"}
}