{
  "type": "Feature",
  "properties": {
    "gn:admin1_code":"19.0",
    "gn:admin2_code":"571.0",
    "gn:asciiname":"Gidobanhalli",
    "gn:country_code":"IN",
    "gn:dem":762,
    "gn:feature_class":"P",
    "gn:feature_code":"PPL",
    "gn:name":"Gidobanhalli",
    "gn:population":0,
    "gn:timezone":"Asia/Kolkata",
    "iso:country":"IN",
    "wof:name":"Gidobanhalli",
    "wof:placetype":"locality"
},
  "geometry": {"coordinates":[77.30439,13.47622],"type":"Point"}
}