{
  "type": "Feature",
  "properties": {
    "iso:country":"IN",
    "ks:ks_name":"Rampur Rudar",
    "ks:ks_pop":1046,
    "ks:ks_type":"VILLAGE",
    "name:eng_x_preferred":[
        "Rampur Rudar"
    ],
    "wof:name":"Rampur Rudar",
    "wof:placetype":"locality",
    "wof:population":1046
},
  "geometry": {"coordinates":[84.91413900000001,26.11584],"type":"Point"}
}