{
  "type": "Feature",
  "properties": {
    "iso:country":"IN",
    "ks:ks_name":"Masautha Khurd",
    "ks:ks_pop":503,
    "ks:ks_type":"VILLAGE",
    "name:eng_x_preferred":[
        "Masautha Khurd"
    ],
    "wof:name":"Masautha Khurd",
    "wof:placetype":"locality",
    "wof:population":503
},
  "geometry": {"coordinates":[85.06608799999999,24.776133],"type":"Point"}
}