{
  "type": "Feature",
  "properties": {
    "gn:admin1_code":"12.0",
    "gn:admin2_code":"004",
    "gn:asciiname":"Grugurdo",
    "gn:country_code":"IN",
    "gn:dem":2682,
    "gn:feature_class":"P",
    "gn:feature_code":"PPL",
    "gn:name":"Grugurdo",
    "gn:population":0,
    "gn:timezone":"Asia/Kolkata",
    "iso:country":"IN",
    "wof:name":"Grugurdo",
    "wof:placetype":"locality"
},
  "geometry": {"coordinates":[76.33889000000001,34.6625],"type":"Point"}
}