{
  "type": "Feature",
  "properties": {
    "iso:country":"IN",
    "ks:ks_name":"Panaichetti Vattam",
    "ks:ks_pop":315,
    "ks:ks_type":"HABITATION",
    "name:eng_x_preferred":[
        "Panaichetti Vattam"
    ],
    "wof:name":"Panaichetti Vattam",
    "wof:placetype":"locality",
    "wof:population":315
},
  "geometry": {"coordinates":[78.638724,12.621881],"type":"Point"}
}