{
  "type": "Feature",
  "properties": {
    "iso:country":"IN",
    "ks:ks_name":"Arjunpali",
    "ks:ks_pop":492,
    "ks:ks_type":"VILLAGE",
    "name:eng_x_preferred":[
        "Arjunpali"
    ],
    "wof:name":"Arjunpali",
    "wof:placetype":"locality",
    "wof:population":492
},
  "geometry": {"coordinates":[84.40854299999999,21.529035],"type":"Point"}
}