{
  "type": "Feature",
  "properties": {
    "gn:admin1_code":"36",
    "gn:admin2_code":"177.0",
    "gn:asciiname":"Neonan Pachchhim",
    "gn:country_code":"IN",
    "gn:dem":105,
    "gn:feature_class":"P",
    "gn:feature_code":"PPL",
    "gn:name":"Neon\u0101n Pachchhim",
    "gn:population":0,
    "gn:timezone":"Asia/Kolkata",
    "iso:country":"IN",
    "ks:ks_alt_nam":"Neon\u0101n Pachchhim",
    "ks:ks_name":"Neonan Pachchhim",
    "ks:ks_type":"VILLAGE",
    "ks:ks_uagg_main":0,
    "name:eng_x_preferred":[
        "Neonan Pachchhim"
    ],
    "name:eng_x_variant":[
        "Neon\u0101n Pachchhim"
    ],
    "wof:name":"Neonan Pachchhim",
    "wof:placetype":"neighbourhood"
},
  "geometry": {"coordinates":[82.169416,26.487104],"type":"Point"}
}