{
  "type": "Feature",
  "properties": {
    "gn:admin1_code":"34.0",
    "gn:admin2_code":"217.0",
    "gn:asciiname":"Bhopatpur",
    "gn:country_code":"IN",
    "gn:dem":76,
    "gn:feature_class":"P",
    "gn:feature_code":"PPL",
    "gn:name":"Bhopatpur",
    "gn:population":0,
    "gn:timezone":"Asia/Kolkata",
    "iso:country":"IN",
    "ks:ks_name":"Bhopatpur",
    "ks:ks_pop":400,
    "ks:ks_type":"VILLAGE",
    "ks:ks_uagg_main":0,
    "name:eng_x_preferred":[
        "Bhopatpur"
    ],
    "wof:name":"Bhopatpur",
    "wof:placetype":"neighbourhood",
    "wof:population":400
},
  "geometry": {"coordinates":[84.296531,26.527755],"type":"Point"}
}