{
  "type": "Feature",
  "properties": {
    "iso:country":"IN",
    "ks:ks_name":"Abadi Salotarian",
    "ks:ks_pop":920,
    "ks:ks_type":"HABITATION",
    "name:eng_x_preferred":[
        "Abadi Salotarian"
    ],
    "wof:name":"Abadi Salotarian",
    "wof:placetype":"locality",
    "wof:population":920
},
  "geometry": {"coordinates":[74.792903,31.750979],"type":"Point"}
}