{
  "type": "Feature",
  "properties": {
    "gn:admin1_code":"12",
    "gn:asciiname":"Baren",
    "gn:country_code":"IN",
    "gn:dem":1778,
    "gn:feature_class":"P",
    "gn:feature_code":"PPL",
    "gn:name":"Baren",
    "gn:population":0,
    "gn:timezone":"Asia/Kolkata",
    "iso:country":"IN",
    "name:ceb_x_preferred":[
        "Baren"
    ],
    "name:deu_x_preferred":[
        "Baren"
    ],
    "name:fra_x_preferred":[
        "Baren"
    ],
    "name:srp_x_preferred":[
        "\u0411\u0430\u0440\u0430\u043d"
    ],
    "wof:name":"Baren",
    "wof:placetype":"locality"
},
  "geometry": {"coordinates":[74.19869,34.07675],"type":"Point"}
}