{
  "type": "Feature",
  "properties": {
    "iso:country":"IN",
    "ks:ks_name":"Saganinal Falia",
    "ks:ks_pop":393,
    "ks:ks_type":"HABITATION",
    "name:eng_x_preferred":[
        "Saganinal Falia"
    ],
    "wof:name":"Saganinal Falia",
    "wof:placetype":"locality",
    "wof:population":393
},
  "geometry": {"coordinates":[73.118116,20.2189],"type":"Point"}
}