{
  "type": "Feature",
  "properties": {
    "gn:admin1_code":"36",
    "gn:admin2_code":"199.0",
    "gn:asciiname":"Kutui",
    "gn:country_code":"IN",
    "gn:dem":81,
    "gn:feature_class":"P",
    "gn:feature_code":"PPL",
    "gn:name":"Kutui",
    "gn:population":0,
    "gn:timezone":"Asia/Kolkata",
    "iso:country":"IN",
    "ks:ks_name":"Kutui",
    "ks:ks_type":"VILLAGE",
    "name:eng_x_preferred":[
        "Kutui"
    ],
    "wof:name":"Kutui",
    "wof:placetype":"locality"
},
  "geometry": {"coordinates":[82.592157,25.189618],"type":"Point"}
}