{
  "type": "Feature",
  "properties": {
    "iso:country":"IN",
    "ks:ks_name":"Bramhan Basti",
    "ks:ks_pop":324,
    "ks:ks_type":"HABITATION",
    "name:eng_x_preferred":[
        "Bramhan Basti"
    ],
    "wof:name":"Bramhan Basti",
    "wof:placetype":"locality",
    "wof:population":324
},
  "geometry": {"coordinates":[82.42805199999999,25.867866],"type":"Point"}
}