{
  "type": "Feature",
  "properties": {
    "iso:country":"IN",
    "ks:ks_name":"Baikunthpur",
    "ks:ks_pop":142,
    "ks:ks_type":"HABITATION",
    "name:eng_x_preferred":[
        "Baikunthpur"
    ],
    "wof:name":"Baikunthpur",
    "wof:placetype":"locality",
    "wof:population":142
},
  "geometry": {"coordinates":[86.904149,22.052978],"type":"Point"}
}