{
  "type": "Feature",
  "properties": {
    "iso:country":"IN",
    "ks:ks_name":"Prasantapur",
    "ks:ks_pop":1,
    "ks:ks_type":"VILLAGE",
    "name:eng_x_preferred":[
        "Prasantapur"
    ],
    "wof:name":"Prasantapur",
    "wof:placetype":"locality",
    "wof:population":1
},
  "geometry": {"coordinates":[82.300303,18.517555],"type":"Point"}
}