{
  "type": "Feature",
  "properties": {
    "gn:admin1_code":"16",
    "gn:admin2_code":"503.0",
    "gn:asciiname":"Jambhal",
    "gn:country_code":"IN",
    "gn:dem":433,
    "gn:feature_class":"P",
    "gn:feature_code":"PPL",
    "gn:name":"J\u0101mbhal",
    "gn:population":0,
    "gn:timezone":"Asia/Kolkata",
    "iso:country":"IN",
    "name:und_x_variant":[
        "J\u0101mbhal",
        "Naw\u0101kheda"
    ],
    "wof:name":"Jambhal",
    "wof:placetype":"locality"
},
  "geometry": {"coordinates":[77.4012,21.29182],"type":"Point"}
}