{
  "type": "Feature",
  "properties": {
    "iso:country":"IN",
    "ks:ks_name":"Neemba Ki Dhani",
    "ks:ks_pop":711,
    "ks:ks_type":"VILLAGE",
    "name:eng_x_preferred":[
        "Neemba Ki Dhani"
    ],
    "wof:name":"Neemba Ki Dhani",
    "wof:placetype":"locality",
    "wof:population":711
},
  "geometry": {"coordinates":[71.936706,26.219525],"type":"Point"}
}