{
  "type": "Feature",
  "properties": {
    "gn:admin1_code":"35",
    "gn:admin2_code":"443.0",
    "gn:asciiname":"Madnai",
    "gn:country_code":"IN",
    "gn:dem":471,
    "gn:feature_class":"P",
    "gn:feature_code":"PPL",
    "gn:name":"Madnai",
    "gn:population":0,
    "gn:timezone":"Asia/Kolkata",
    "iso:country":"IN",
    "ks:ks_name":"Madnai",
    "ks:ks_type":"VILLAGE",
    "name:eng_x_preferred":[
        "Madnai"
    ],
    "wof:name":"Madnai",
    "wof:placetype":"locality"
},
  "geometry": {"coordinates":[78.242351,23.611992],"type":"Point"}
}