{
  "type": "Feature",
  "properties": {
    "iso:country":"IN",
    "ks:ks_name":"Nagla Manoharpur",
    "ks:ks_pop":26,
    "ks:ks_type":"HABITATION",
    "name:eng_x_preferred":[
        "Nagla Manoharpur"
    ],
    "wof:name":"Nagla Manoharpur",
    "wof:placetype":"locality",
    "wof:population":26
},
  "geometry": {"coordinates":[79.356767,26.72563],"type":"Point"}
}