{
  "type": "Feature",
  "properties": {
    "gn:admin1_code":"11",
    "gn:admin2_code":"23.0",
    "gn:asciiname":"Haledh",
    "gn:country_code":"IN",
    "gn:dem":1297,
    "gn:feature_class":"P",
    "gn:feature_code":"PPL",
    "gn:name":"Haledh",
    "gn:population":0,
    "gn:timezone":"Asia/Kolkata",
    "iso:country":"IN",
    "wof:name":"Haledh",
    "wof:placetype":"locality"
},
  "geometry": {"coordinates":[76.05894000000001,32.38756],"type":"Point"}
}