{
  "type": "Feature",
  "properties": {
    "iso:country":"IN",
    "ks:ks_name":"Muslim Tola Niche",
    "ks:ks_pop":174,
    "ks:ks_type":"HABITATION",
    "name:eng_x_preferred":[
        "Muslim Tola Niche"
    ],
    "wof:name":"Muslim Tola Niche",
    "wof:placetype":"locality",
    "wof:population":174
},
  "geometry": {"coordinates":[86.17181600000001,24.390106],"type":"Point"}
}