{
  "type": "Feature",
  "properties": {
    "gn:admin1_code":"2.0",
    "gn:admin2_code":"550",
    "gn:asciiname":"Chintaladevi",
    "gn:country_code":"IN",
    "gn:dem":60,
    "gn:feature_class":"P",
    "gn:feature_code":"PPL",
    "gn:name":"Chintaladevi",
    "gn:population":0,
    "gn:timezone":"Asia/Kolkata",
    "iso:country":"IN",
    "wof:name":"Chintaladevi",
    "wof:placetype":"locality"
},
  "geometry": {"coordinates":[79.64703,14.9768],"type":"Point"}
}