{
  "type": "Feature",
  "properties": {
    "gn:admin1_code":"9.0",
    "gn:admin2_code":"484.0",
    "gn:asciiname":"Boria",
    "gn:country_code":"IN",
    "gn:dem":124,
    "gn:feature_class":"P",
    "gn:feature_code":"PPL",
    "gn:name":"Boria",
    "gn:population":0,
    "gn:timezone":"Asia/Kolkata",
    "iso:country":"IN",
    "name:ceb_x_preferred":[
        "Boria"
    ],
    "name:swe_x_preferred":[
        "Boria"
    ],
    "wof:name":"Boria",
    "wof:placetype":"locality"
},
  "geometry": {"coordinates":[73.65899999999998,23.0431],"type":"Point"}
}