{
  "type": "Feature",
  "properties": {
    "iso:country":"IN",
    "ks:ks_alt_nam":"PAPANNA KUNTA INDLU",
    "ks:ks_name":"Papanna Kunta Indlu",
    "ks:ks_pop":162,
    "ks:ks_type":"HABITATION",
    "name:eng_x_preferred":[
        "Papanna Kunta Indlu"
    ],
    "wof:name":"Papanna Kunta Indlu",
    "wof:placetype":"locality",
    "wof:population":162
},
  "geometry": {"coordinates":[78.295742,12.733123],"type":"Point"}
}