{
  "type": "Feature",
  "properties": {
    "iso:country":"IN",
    "ks:ks_name":"Neetadaka",
    "ks:ks_pop":18,
    "ks:ks_type":"HABITATION",
    "name:eng_x_preferred":[
        "Neetadaka"
    ],
    "wof:name":"Neetadaka",
    "wof:placetype":"locality",
    "wof:population":18
},
  "geometry": {"coordinates":[75.38782500000001,12.745426],"type":"Point"}
}