{
  "type": "Feature",
  "properties": {
    "gn:admin1_code":"40",
    "gn:admin2_code":"538.0",
    "gn:asciiname":"Akkacheruvu Tanda",
    "gn:country_code":"IN",
    "gn:dem":567,
    "gn:feature_class":"P",
    "gn:feature_code":"PPL",
    "gn:name":"Akkacheruvu T\u0101nda",
    "gn:population":0,
    "gn:timezone":"Asia/Kolkata",
    "iso:country":"IN",
    "wof:name":"Akkacheruvu Tanda",
    "wof:placetype":"locality"
},
  "geometry": {"coordinates":[77.67966,17.08481],"type":"Point"}
}