{
  "type": "Feature",
  "properties": {
    "gn:admin1_code":"40",
    "gn:admin2_code":"538.0",
    "gn:asciiname":"Akkacheruvu Tanda",
    "gn:country_code":"IN",
    "gn:dem":567,
    "gn:feature_class":"P",
    "gn:feature_code":"PPL",
    "gn:name":"Akkacheruvu T\u0101nda",
    "gn:population":0,
    "gn:timezone":"Asia/Kolkata",
    "iso:country":"IN",
    "ks:ks_name":"Ekkachervutanda",
    "ks:ks_pop":51,
    "ks:ks_type":"HABITATION",
    "name:eng_x_preferred":[
        "Ekkachervutanda"
    ],
    "name:eng_x_variant":[
        "Akkacheruvu Tanda"
    ],
    "wof:name":"Ekkachervutanda",
    "wof:placetype":"locality",
    "wof:population":51
},
  "geometry": {"coordinates":[77.679714,17.084633],"type":"Point"}
}