{
  "type": "Feature",
  "properties": {
    "gn:admin1_code":"40",
    "gn:admin2_code":"535.0",
    "gn:asciiname":"Kallapalli",
    "gn:country_code":"IN",
    "gn:dem":529,
    "gn:feature_class":"P",
    "gn:feature_code":"PPL",
    "gn:name":"Kall\u0101palli",
    "gn:population":0,
    "gn:timezone":"Asia/Kolkata",
    "iso:country":"IN",
    "ks:ks_alt_nam":"Kall\u0101palli",
    "ks:ks_name":"Kallapalli",
    "ks:ks_type":"VILLAGE",
    "name:eng_x_preferred":[
        "Kallapalli"
    ],
    "name:eng_x_variant":[
        "Kall\u0101palli"
    ],
    "wof:name":"Kallapalli",
    "wof:placetype":"locality"
},
  "geometry": {"coordinates":[77.890067,17.792039],"type":"Point"}
}