{
  "type": "Feature",
  "properties": {
    "iso:country":"IN",
    "ks:ks_name":"Kheda Narela",
    "ks:ks_pop":1905,
    "ks:ks_type":"VILLAGE",
    "name:eng_x_preferred":[
        "Kheda Narela"
    ],
    "wof:name":"Kheda Narela",
    "wof:placetype":"locality",
    "wof:population":1905
},
  "geometry": {"coordinates":[75.75242900000001,23.733566],"type":"Point"}
}