{
  "type": "Feature",
  "properties": {
    "iso:country":"IN",
    "ks:ks_alt_nam":"DHIRAJ NAGAR",
    "ks:ks_name":"Dhiraj Nagar",
    "ks:ks_pop":295,
    "ks:ks_type":"HABITATION",
    "name:eng_x_preferred":[
        "Dhiraj Nagar"
    ],
    "wof:name":"Dhiraj Nagar",
    "wof:placetype":"locality",
    "wof:population":295
},
  "geometry": {"coordinates":[85.521429,24.921881],"type":"Point"}
}