{
  "type": "Feature",
  "properties": {
    "gn:admin1_code":"11.0",
    "gn:admin2_code":"26.0",
    "gn:asciiname":"Sara Agi",
    "gn:country_code":"IN",
    "gn:dem":1551,
    "gn:feature_class":"P",
    "gn:feature_code":"PPL",
    "gn:name":"Sara \u0100gi",
    "gn:population":0,
    "gn:timezone":"Asia/Kolkata",
    "iso:country":"IN",
    "wof:name":"Sara Agi",
    "wof:placetype":"locality"
},
  "geometry": {"coordinates":[77.66874,31.48626],"type":"Point"}
}