{
  "type": "Feature",
  "properties": {
    "iso:country":"IN",
    "ks:ks_name":"Beloda",
    "ks:ks_pop":132,
    "ks:ks_type":"VILLAGE",
    "name:eng_x_preferred":[
        "Beloda"
    ],
    "wof:name":"Beloda",
    "wof:placetype":"locality",
    "wof:population":132
},
  "geometry": {"coordinates":[80.646874,19.821123],"type":"Point"}
}