{
  "type": "Feature",
  "properties": {
    "iso:country":"IN",
    "ks:ks_name":"Rewari Khurd",
    "ks:ks_pop":1411,
    "ks:ks_type":"VILLAGE",
    "ks:ks_uagg_main":0,
    "name:eng_x_preferred":[
        "Rewari Khurd"
    ],
    "wof:name":"Rewari Khurd",
    "wof:placetype":"neighbourhood",
    "wof:population":1411
},
  "geometry": {"coordinates":[80.67754499999999,26.063373],"type":"Point"}
}