{
  "type": "Feature",
  "properties": {
    "iso:country":"IN",
    "ks:ks_name":"Moth",
    "ks:ks_pop":215,
    "ks:ks_type":"VILLAGE",
    "name:eng_x_preferred":[
        "Moth"
    ],
    "wof:name":"Moth",
    "wof:placetype":"locality",
    "wof:population":215
},
  "geometry": {"coordinates":[73.840569,23.931926],"type":"Point"}
}