{
  "type": "Feature",
  "properties": {
    "iso:country":"IN",
    "ks:ks_name":"Dhamkot",
    "ks:ks_pop":137,
    "ks:ks_type":"HABITATION",
    "name:eng_x_preferred":[
        "Dhamkot"
    ],
    "wof:name":"Dhamkot",
    "wof:placetype":"locality",
    "wof:population":137
},
  "geometry": {"coordinates":[79.49857,29.779892],"type":"Point"}
}