{
  "type": "Feature",
  "properties": {
    "gn:admin1_code":"36",
    "gn:admin2_code":"191.0",
    "gn:asciiname":"Masuriapur",
    "gn:country_code":"IN",
    "gn:dem":77,
    "gn:feature_class":"P",
    "gn:feature_code":"PPL",
    "gn:name":"Masuri\u0101pur",
    "gn:population":0,
    "gn:timezone":"Asia/Kolkata",
    "iso:country":"IN",
    "ks:ks_name":"Mansuriyapur",
    "ks:ks_pop":1836,
    "ks:ks_type":"VILLAGE",
    "ks:ks_uagg_main":0,
    "name:eng_x_preferred":[
        "Mansuriyapur"
    ],
    "wof:name":"Mansuriyapur",
    "wof:placetype":"neighbourhood",
    "wof:population":1836
},
  "geometry": {"coordinates":[83.329898,26.282696],"type":"Point"}
}