{
  "type": "Feature",
  "properties": {
    "iso:country":"IN",
    "ks:ks_name":"Bhatta",
    "ks:ks_type":"VILLAGE",
    "name:eng_x_preferred":[
        "Bhatta"
    ],
    "wof:name":"Bhatta",
    "wof:placetype":"locality"
},
  "geometry": {"coordinates":[79.95553099999999,28.480011],"type":"Point"}
}