{
  "type": "Feature",
  "properties": {
    "iso:country":"IN",
    "ks:ks_name":"Pudur",
    "ks:ks_pop":431,
    "ks:ks_type":"HABITATION",
    "name:eng_x_preferred":[
        "Pudur"
    ],
    "wof:name":"Pudur",
    "wof:placetype":"locality",
    "wof:population":431
},
  "geometry": {"coordinates":[79.015331,12.885261],"type":"Point"}
}