{
  "type": "Feature",
  "properties": {
    "gn:admin1_code":"25.0",
    "gn:admin2_code":"605.0",
    "gn:asciiname":"Athiparamanur",
    "gn:country_code":"IN",
    "gn:dem":428,
    "gn:feature_class":"P",
    "gn:feature_code":"PPL",
    "gn:name":"Athiparaman\u016br",
    "gn:population":0,
    "gn:timezone":"Asia/Kolkata",
    "iso:country":"IN",
    "wof:name":"Athiparamanur",
    "wof:placetype":"locality"
},
  "geometry": {"coordinates":[78.52678,12.59073],"type":"Point"}
}