{
  "type": "Feature",
  "properties": {
    "iso:country":"IN",
    "ks:ks_name":"Nilkanta Pur",
    "ks:ks_pop":1348,
    "ks:ks_type":"VILLAGE",
    "ks:ks_uagg_main":0,
    "name:eng_x_preferred":[
        "Nilkanta Pur"
    ],
    "wof:name":"Nilkanta Pur",
    "wof:placetype":"neighbourhood",
    "wof:population":1348
},
  "geometry": {"coordinates":[87.67520399999999,22.107941],"type":"Point"}
}