{
  "type": "Feature",
  "properties": {
    "iso:country":"IN",
    "ks:ks_name":"Dhodhanpur",
    "ks:ks_pop":18,
    "ks:ks_type":"VILLAGE",
    "name:eng_x_preferred":[
        "Dhodhanpur"
    ],
    "wof:name":"Dhodhanpur",
    "wof:placetype":"locality",
    "wof:population":18
},
  "geometry": {"coordinates":[80.002273,28.038795],"type":"Point"}
}