{
  "type": "Feature",
  "properties": {
    "iso:country":"IN",
    "ks:ks_name":"Mahadeva Kita",
    "ks:ks_pop":34,
    "ks:ks_type":"VILLAGE",
    "name:eng_x_preferred":[
        "Mahadeva Kita"
    ],
    "wof:name":"Mahadeva Kita",
    "wof:placetype":"locality",
    "wof:population":34
},
  "geometry": {"coordinates":[87.26782,24.951216],"type":"Point"}
}