{
  "type": "Feature",
  "properties": {
    "iso:country":"IN",
    "ks:ks_name":"Wadachiwadi",
    "ks:ks_pop":443,
    "ks:ks_type":"HABITATION",
    "name:eng_x_preferred":[
        "Wadachiwadi"
    ],
    "wof:name":"Wadachiwadi",
    "wof:placetype":"locality",
    "wof:population":443
},
  "geometry": {"coordinates":[75.27119999999999,17.7052],"type":"Point"}
}