{
  "type": "Feature",
  "properties": {
    "gn:admin1_code":"35.0",
    "gn:admin2_code":"450",
    "gn:asciiname":"Barwara Kalan",
    "gn:country_code":"IN",
    "gn:dem":410,
    "gn:feature_class":"P",
    "gn:feature_code":"PPL",
    "gn:name":"Barw\u0101ra Kal\u0101n",
    "gn:population":0,
    "gn:timezone":"Asia/Kolkata",
    "iso:country":"IN",
    "name:und_x_variant":[
        "Barw\u00e1ra Kal\u00e1n",
        "Banvara",
        "Banv\u0101ra Kal\u0101n",
        "Barw\u0101ra Kal\u0101n"
    ],
    "wof:name":"Barwara Kalan",
    "wof:placetype":"locality"
},
  "geometry": {"coordinates":[80.57441,23.74838],"type":"Point"}
}