{
  "type": "Feature",
  "properties": {
    "gn:admin1_code":"36",
    "gn:admin2_code":"145.0",
    "gn:asciiname":"Patparganj",
    "gn:country_code":"IN",
    "gn:dem":181,
    "gn:feature_class":"P",
    "gn:feature_code":"PPL",
    "gn:name":"Patparganj",
    "gn:population":0,
    "gn:timezone":"Asia/Kolkata",
    "iso:country":"IN",
    "name:jpn_x_preferred":[
        "\u30d1\u30c8\u30d1\u30eb\u30ac\u30f3\u30b8"
    ],
    "name:nld_x_preferred":[
        "Patparganj"
    ],
    "name:urd_x_preferred":[
        "\u067e\u0679\u067e\u0631 \u06af\u0646\u062c"
    ],
    "wof:name":"Patparganj",
    "wof:placetype":"locality"
},
  "geometry": {"coordinates":[77.64615999999999,27.43712],"type":"Point"}
}