{
  "type": "Feature",
  "properties": {
    "gn:admin1_code":"2.0",
    "gn:admin2_code":"552.0",
    "gn:asciiname":"Dasaradoddi",
    "gn:country_code":"IN",
    "gn:dem":380,
    "gn:feature_class":"P",
    "gn:feature_code":"PPL",
    "gn:name":"D\u0101saradoddi",
    "gn:population":0,
    "gn:timezone":"Asia/Kolkata",
    "iso:country":"IN",
    "wof:name":"Dasaradoddi",
    "wof:placetype":"locality"
},
  "geometry": {"coordinates":[77.99139,15.51283],"type":"Point"}
}