{
  "type": "Feature",
  "properties": {
    "iso:country":"IN",
    "ks:ks_name":"Panpukuria",
    "ks:ks_pop":0,
    "ks:ks_type":"VILLAGE",
    "name:eng_x_preferred":[
        "Panpukuria"
    ],
    "wof:name":"Panpukuria",
    "wof:placetype":"locality",
    "wof:population":0
},
  "geometry": {"coordinates":[86.899241,23.201277],"type":"Point"}
}