{
  "type": "Feature",
  "properties": {
    "gn:admin1_code":"35",
    "gn:admin2_code":"446.0",
    "gn:asciiname":"Maheshwari",
    "gn:country_code":"IN",
    "gn:dem":449,
    "gn:feature_class":"P",
    "gn:feature_code":"PPL",
    "gn:name":"Maheshwari",
    "gn:population":0,
    "gn:timezone":"Asia/Kolkata",
    "iso:country":"IN",
    "name:hin_x_preferred":[
        "\u092e\u093e\u0939\u0947\u0936\u094d\u0935\u0930\u0940"
    ],
    "wof:name":"Maheshwari",
    "wof:placetype":"locality"
},
  "geometry": {"coordinates":[78.03416999999997,23.33603],"type":"Point"}
}