{
  "type": "Feature",
  "properties": {
    "gn:admin1_code":"19.0",
    "gn:admin2_code":"575.0",
    "gn:asciiname":"Talipadi",
    "gn:country_code":"IN",
    "gn:dem":48,
    "gn:feature_class":"P",
    "gn:feature_code":"PPLL",
    "gn:name":"T\u0101lip\u0101di",
    "gn:population":0,
    "gn:timezone":"Asia/Kolkata",
    "iso:country":"IN",
    "ks:ks_name":"Talipady",
    "ks:ks_pop":6498,
    "ks:ks_type":"VILLAGE",
    "ks:ks_uagg_main":0,
    "name:eng_x_preferred":[
        "Talipady"
    ],
    "wof:name":"Talipady",
    "wof:placetype":"locality",
    "wof:population":6498
},
  "geometry": {"coordinates":[74.843569,13.07806],"type":"Point"}
}