{
  "type": "Feature",
  "properties": {
    "iso:country":"IN",
    "ks:ks_name":"Janoa",
    "ks:ks_pop":893,
    "ks:ks_type":"VILLAGE",
    "name:eng_x_preferred":[
        "Janoa"
    ],
    "wof:name":"Janoa",
    "wof:placetype":"locality",
    "wof:population":893
},
  "geometry": {"coordinates":[85.519881,22.662538],"type":"Point"}
}