{
  "type": "Feature",
  "properties": {
    "iso:country":"IN",
    "ks:ks_name":"Jamdarwadi",
    "ks:ks_pop":566,
    "ks:ks_type":"HABITATION",
    "name:eng_x_preferred":[
        "Jamdarwadi"
    ],
    "wof:name":"Jamdarwadi",
    "wof:placetype":"locality",
    "wof:population":566
},
  "geometry": {"coordinates":[75.32765499999999,18.715347],"type":"Point"}
}