{
  "type": "Feature",
  "properties": {
    "iso:country":"IN",
    "ks:ks_name":"Singha",
    "ks:ks_type":"VILLAGE",
    "name:eng_x_preferred":[
        "Singha"
    ],
    "wof:name":"Singha",
    "wof:placetype":"locality"
},
  "geometry": {"coordinates":[83.177266,27.036794],"type":"Point"}
}