{
  "type": "Feature",
  "properties": {
    "iso:country":"IN",
    "ks:ks_name":"Boringguda",
    "ks:ks_pop":125,
    "ks:ks_type":"HABITATION",
    "name:eng_x_preferred":[
        "Boringguda"
    ],
    "wof:name":"Boringguda",
    "wof:placetype":"locality",
    "wof:population":125
},
  "geometry": {"coordinates":[78.603838,19.356212],"type":"Point"}
}