{
  "type": "Feature",
  "properties": {
    "iso:country":"IN",
    "ks:ks_name":"Dhap Dhapi",
    "ks:ks_pop":1816,
    "ks:ks_type":"HABITATION",
    "name:eng_x_preferred":[
        "Dhap Dhapi"
    ],
    "wof:name":"Dhap Dhapi",
    "wof:placetype":"locality",
    "wof:population":1816
},
  "geometry": {"coordinates":[88.50203399999999,22.334259],"type":"Point"}
}