{
  "type": "Feature",
  "properties": {
    "iso:country":"IN",
    "ks:ks_name":"Daracha",
    "ks:ks_pop":187,
    "ks:ks_type":"VILLAGE",
    "ks:ks_uagg_main":0,
    "name:eng_x_preferred":[
        "Daracha"
    ],
    "wof:name":"Daracha",
    "wof:placetype":"neighbourhood",
    "wof:population":187
},
  "geometry": {"coordinates":[83.028462,26.268405],"type":"Point"}
}