{
  "type": "Feature",
  "properties": {
    "gn:admin1_code":"36.0",
    "gn:admin2_code":"189.0",
    "gn:asciiname":"Sumahi",
    "gn:country_code":"IN",
    "gn:dem":85,
    "gn:feature_class":"P",
    "gn:feature_code":"PPL",
    "gn:name":"Sum\u0101hi",
    "gn:population":0,
    "gn:timezone":"Asia/Kolkata",
    "iso:country":"IN",
    "ks:ks_alt_nam":"Sum\u0101hi",
    "ks:ks_name":"Sumahi",
    "ks:ks_pop":280,
    "ks:ks_type":"VILLAGE",
    "name:eng_x_preferred":[
        "Sumahi"
    ],
    "name:eng_x_variant":[
        "Sum\u0101hi"
    ],
    "wof:name":"Sumahi",
    "wof:placetype":"locality",
    "wof:population":280
},
  "geometry": {"coordinates":[84.239681,26.703657],"type":"Point"}
}