{
  "type": "Feature",
  "properties": {
    "gn:admin1_code":"11.0",
    "gn:admin2_code":"33.0",
    "gn:asciiname":"Gadiyogra",
    "gn:country_code":"IN",
    "gn:dem":2041,
    "gn:feature_class":"P",
    "gn:feature_code":"PPL",
    "gn:name":"Gadiyogra",
    "gn:population":0,
    "gn:timezone":"Asia/Kolkata",
    "iso:country":"IN",
    "wof:name":"Gadiyogra",
    "wof:placetype":"locality"
},
  "geometry": {"coordinates":[77.35423,31.16536],"type":"Point"}
}