{
  "type": "Feature",
  "properties": {
    "gn:admin1_code":"35",
    "gn:admin2_code":"447.0",
    "gn:asciiname":"Meghnath Dhana",
    "gn:country_code":"IN",
    "gn:dem":1024,
    "gn:feature_class":"P",
    "gn:feature_code":"PPL",
    "gn:name":"Meghn\u0101th Dh\u0101na",
    "gn:population":0,
    "gn:timezone":"Asia/Kolkata",
    "iso:country":"IN",
    "wof:name":"Meghnath Dhana",
    "wof:placetype":"neighbourhood"
},
  "geometry": {"coordinates":[77.50958,21.50696],"type":"Point"}
}