{
  "type": "Feature",
  "properties": {
    "gn:admin1_code":"35",
    "gn:admin2_code":"463.0",
    "gn:asciiname":"Manakpur",
    "gn:country_code":"IN",
    "gn:dem":239,
    "gn:feature_class":"P",
    "gn:feature_code":"PPL",
    "gn:name":"Manakpur",
    "gn:population":0,
    "gn:timezone":"Asia/Kolkata",
    "iso:country":"IN",
    "ks:ks_name":"Manikpur",
    "ks:ks_pop":795,
    "ks:ks_type":"VILLAGE",
    "name:eng_x_preferred":[
        "Manikpur"
    ],
    "name:eng_x_variant":[
        "Manakpur"
    ],
    "name:fas_x_preferred":[
        "\u0645\u0627\u0646\u06a9\u200c\u067e\u0648\u0631"
    ],
    "name:urd_x_preferred":[
        "\u0645\u0627\u0646\u06a9 \u067e\u0648\u0631"
    ],
    "wof:name":"Manikpur",
    "wof:placetype":"locality",
    "wof:population":795
},
  "geometry": {"coordinates":[82.41786399999999,24.511233],"type":"Point"}
}