{
  "type": "Feature",
  "properties": {
    "gn:admin1_code":"35",
    "gn:admin2_code":"463.0",
    "gn:asciiname":"Manakpur",
    "gn:country_code":"IN",
    "gn:dem":239,
    "gn:feature_class":"P",
    "gn:feature_code":"PPL",
    "gn:name":"Manakpur",
    "gn:population":0,
    "gn:timezone":"Asia/Kolkata",
    "iso:country":"IN",
    "name:fas_x_preferred":[
        "\u0645\u0627\u0646\u06a9\u200c\u067e\u0648\u0631"
    ],
    "name:urd_x_preferred":[
        "\u0645\u0627\u0646\u06a9 \u067e\u0648\u0631"
    ],
    "wof:name":"Manakpur",
    "wof:placetype":"locality"
},
  "geometry": {"coordinates":[82.43284,24.5092],"type":"Point"}
}