{
  "type": "Feature",
  "properties": {
    "iso:country":"IN",
    "ks:ks_name":"Suhel Mustkil",
    "ks:ks_pop":402,
    "ks:ks_type":"VILLAGE",
    "ks:ks_uagg_main":0,
    "name:eng_x_preferred":[
        "Suhel Mustkil"
    ],
    "wof:name":"Suhel Mustkil",
    "wof:placetype":"neighbourhood",
    "wof:population":402
},
  "geometry": {"coordinates":[81.30541700000001,25.331102],"type":"Point"}
}