{
  "type": "Feature",
  "properties": {
    "gn:admin1_code":"11.0",
    "gn:admin2_code":"33.0",
    "gn:asciiname":"Kharena",
    "gn:country_code":"IN",
    "gn:dem":2149,
    "gn:feature_class":"P",
    "gn:feature_code":"PPL",
    "gn:name":"Kharena",
    "gn:population":0,
    "gn:timezone":"Asia/Kolkata",
    "iso:country":"IN",
    "wof:name":"Kharena",
    "wof:placetype":"locality"
},
  "geometry": {"coordinates":[77.59102,31.12045],"type":"Point"}
}