{
  "type": "Feature",
  "properties": {
    "iso:country":"IN",
    "ks:ks_name":"Kavali",
    "ks:ks_pop":16,
    "ks:ks_type":"HABITATION",
    "name:eng_x_preferred":[
        "Kavali"
    ],
    "name:hin_x_preferred":[
        "\u0915\u0935\u093e\u0932\u0940"
    ],
    "name:tel_x_preferred":[
        "\u0c15\u0c3e\u0c35\u0c32\u0c3f"
    ],
    "name:urd_x_preferred":[
        "\u06a9\u0627\u0648\u0644\u06cc"
    ],
    "wof:name":"Kavali",
    "wof:placetype":"locality",
    "wof:population":16
},
  "geometry": {"coordinates":[75.359967,13.392171],"type":"Point"}
}