{
  "type": "Feature",
  "properties": {
    "iso:country":"IN",
    "ks:ks_name":"Mado",
    "ks:ks_pop":136,
    "ks:ks_type":"VILLAGE",
    "name:eng_x_preferred":[
        "Mado"
    ],
    "wof:name":"Mado",
    "wof:placetype":"locality",
    "wof:population":136
},
  "geometry": {"coordinates":[83.60043,19.599602],"type":"Point"}
}