{
  "type": "Feature",
  "properties": {
    "gn:admin1_code":"11",
    "gn:admin2_code":"23.0",
    "gn:asciiname":"Bhalun",
    "gn:country_code":"IN",
    "gn:dem":1703,
    "gn:feature_class":"P",
    "gn:feature_code":"PPL",
    "gn:name":"Bh\u0101lun",
    "gn:population":0,
    "gn:timezone":"Asia/Kolkata",
    "iso:country":"IN",
    "wof:name":"Bhalun",
    "wof:placetype":"locality"
},
  "geometry": {"coordinates":[76.14617,32.72569],"type":"Point"}
}