{
  "type": "Feature",
  "properties": {
    "iso:country":"IN",
    "ks:ks_name":"Seenta",
    "ks:ks_pop":709,
    "ks:ks_type":"VILLAGE",
    "name:eng_x_preferred":[
        "Seenta"
    ],
    "wof:name":"Seenta",
    "wof:placetype":"neighbourhood",
    "wof:population":709
},
  "geometry": {"coordinates":[75.843918,25.236376],"type":"Point"}
}