{
  "type": "Feature",
  "properties": {
    "gn:admin1_code":"11",
    "gn:admin2_code":"27.0",
    "gn:asciiname":"Tamled",
    "gn:country_code":"IN",
    "gn:dem":965,
    "gn:feature_class":"P",
    "gn:feature_code":"PPL",
    "gn:name":"Tamled",
    "gn:population":0,
    "gn:timezone":"Asia/Kolkata",
    "iso:country":"IN",
    "wof:name":"Tamled",
    "wof:placetype":"locality"
},
  "geometry": {"coordinates":[76.79222,31.57819000000001],"type":"Point"}
}