{
  "type": "Feature",
  "properties": {
    "gn:admin1_code":"10",
    "gn:admin2_code":"71.0",
    "gn:asciiname":"Sadhaura",
    "gn:country_code":"IN",
    "gn:dem":310,
    "gn:feature_class":"P",
    "gn:feature_code":"PPL",
    "gn:name":"S\u0101dhaura",
    "gn:population":0,
    "gn:timezone":"Asia/Kolkata",
    "iso:country":"IN",
    "ks:ks_alt_nam":"S\u0101dhaura",
    "ks:ks_name":"Sadhaura",
    "ks:ks_type":"VILLAGE",
    "ks:ks_uagg_main":0,
    "name:eng_x_preferred":[
        "Sadhaura"
    ],
    "name:eng_x_variant":[
        "S\u0101dhaura"
    ],
    "wof:name":"Sadhaura",
    "wof:placetype":"neighbourhood"
},
  "geometry": {"coordinates":[77.221994,30.385409],"type":"Point"}
}