{
  "type": "Feature",
  "properties": {
    "gn:admin1_code":"16.0",
    "gn:admin2_code":"508.0",
    "gn:asciiname":"Muliala",
    "gn:country_code":"IN",
    "gn:dem":117,
    "gn:feature_class":"P",
    "gn:feature_code":"PPL",
    "gn:name":"Muli\u0101la",
    "gn:population":0,
    "gn:timezone":"Asia/Kolkata",
    "iso:country":"IN",
    "wof:name":"Muliala",
    "wof:placetype":"locality"
},
  "geometry": {"coordinates":[79.95641999999999,18.99392000000001],"type":"Point"}
}