{
  "type": "Feature",
  "properties": {
    "iso:country":"IN",
    "ks:ks_name":"Kotgaon Niche",
    "ks:ks_pop":542,
    "ks:ks_type":"HABITATION",
    "name:eng_x_preferred":[
        "Kotgaon Niche"
    ],
    "wof:name":"Kotgaon Niche",
    "wof:placetype":"locality",
    "wof:population":542
},
  "geometry": {"coordinates":[81.267645,20.23937],"type":"Point"}
}