{
  "type": "Feature",
  "properties": {
    "iso:country":"IN",
    "ks:ks_name":"Addka",
    "ks:ks_pop":2019,
    "ks:ks_type":"HABITATION",
    "name:eng_x_preferred":[
        "Addka"
    ],
    "wof:name":"Addka",
    "wof:placetype":"locality",
    "wof:population":2019
},
  "geometry": {"coordinates":[74.93117700000001,12.653662],"type":"Point"}
}