{
  "type": "Feature",
  "properties": {
    "gn:admin1_code":"16.0",
    "gn:admin2_code":"508",
    "gn:asciiname":"Jharapapra",
    "gn:country_code":"IN",
    "gn:dem":318,
    "gn:feature_class":"P",
    "gn:feature_code":"PPL",
    "gn:name":"Jh\u0101r\u0101p\u0101pra",
    "gn:population":0,
    "gn:timezone":"Asia/Kolkata",
    "iso:country":"IN",
    "ks:ks_alt_nam":"Jh\u0101r\u0101p\u0101pra",
    "ks:ks_name":"Jharapapra",
    "ks:ks_type":"VILLAGE",
    "name:eng_x_preferred":[
        "Jharapapra"
    ],
    "name:eng_x_variant":[
        "Jh\u0101r\u0101p\u0101pra"
    ],
    "wof:name":"Jharapapra",
    "wof:placetype":"locality"
},
  "geometry": {"coordinates":[80.50339200000001,20.074847],"type":"Point"}
}