{
  "type": "Feature",
  "properties": {
    "iso:country":"IN",
    "ks:ks_name":"Kutilo",
    "ks:ks_pop":770,
    "ks:ks_type":"VILLAGE",
    "name:eng_x_preferred":[
        "Kutilo"
    ],
    "wof:name":"Kutilo",
    "wof:placetype":"locality",
    "wof:population":770
},
  "geometry": {"coordinates":[86.258082,20.437469],"type":"Point"}
}