{
  "type": "Feature",
  "properties": {
    "gn:admin1_code":"19.0",
    "gn:admin2_code":"570.0",
    "gn:asciiname":"Sigehadlu",
    "gn:country_code":"IN",
    "gn:dem":766,
    "gn:feature_class":"P",
    "gn:feature_code":"PPL",
    "gn:name":"S\u012bgehadlu",
    "gn:population":0,
    "gn:timezone":"Asia/Kolkata",
    "iso:country":"IN",
    "wof:name":"Sigehadlu",
    "wof:placetype":"locality"
},
  "geometry": {"coordinates":[76.02204999999999,13.59864],"type":"Point"}
}