{
  "type": "Feature",
  "properties": {
    "iso:country":"IN",
    "ks:ks_name":"Bara Chak",
    "ks:ks_pop":15,
    "ks:ks_type":"VILLAGE",
    "name:eng_x_preferred":[
        "Bara Chak"
    ],
    "wof:name":"Bara Chak",
    "wof:placetype":"locality",
    "wof:population":15
},
  "geometry": {"coordinates":[87.779048,22.145238],"type":"Point"}
}