{
  "type": "Feature",
  "properties": {
    "iso:country":"IN",
    "ks:ks_name":"Indradaveedhi",
    "ks:ks_pop":108,
    "ks:ks_type":"HABITATION",
    "name:eng_x_preferred":[
        "Indradaveedhi"
    ],
    "wof:name":"Indradaveedhi",
    "wof:placetype":"locality",
    "wof:population":108
},
  "geometry": {"coordinates":[84.443101,18.834171],"type":"Point"}
}