{
  "type": "Feature",
  "properties": {
    "iso:country":"IN",
    "ks:ks_name":"Salda",
    "ks:ks_pop":680,
    "ks:ks_type":"VILLAGE",
    "name:eng_x_preferred":[
        "Salda"
    ],
    "wof:name":"Salda",
    "wof:placetype":"locality",
    "wof:population":680
},
  "geometry": {"coordinates":[81.317752,23.592925],"type":"Point"}
}