{
  "type": "Feature",
  "properties": {
    "gn:admin1_code":"2.0",
    "gn:admin2_code":"545.0",
    "gn:asciiname":"Turumamidi",
    "gn:country_code":"IN",
    "gn:dem":462,
    "gn:feature_class":"P",
    "gn:feature_code":"PPL",
    "gn:name":"Turum\u0101midi",
    "gn:population":0,
    "gn:timezone":"Asia/Kolkata",
    "iso:country":"IN",
    "ks:ks_alt_nam":"Turum\u0101midi",
    "ks:ks_name":"Turumamidi",
    "ks:ks_type":"VILLAGE",
    "name:eng_x_preferred":[
        "Turumamidi"
    ],
    "name:eng_x_variant":[
        "Turum\u0101midi"
    ],
    "wof:name":"Turumamidi",
    "wof:placetype":"locality"
},
  "geometry": {"coordinates":[81.614389,17.532253],"type":"Point"}
}