{
  "type": "Feature",
  "properties": {
    "iso:country":"IN",
    "ks:ks_name":"Hedutane",
    "ks:ks_pop":448,
    "ks:ks_type":"VILLAGE",
    "name:eng_x_preferred":[
        "Hedutane"
    ],
    "wof:name":"Hedutane",
    "wof:placetype":"locality",
    "wof:population":448
},
  "geometry": {"coordinates":[73.145467,19.046589],"type":"Point"}
}