{
  "type": "Feature",
  "properties": {
    "iso:country":"IN",
    "ks:ks_name":"Gadaram Para",
    "ks:ks_pop":351,
    "ks:ks_type":"HABITATION",
    "name:eng_x_preferred":[
        "Gadaram Para"
    ],
    "wof:name":"Gadaram Para",
    "wof:placetype":"locality",
    "wof:population":351
},
  "geometry": {"coordinates":[91.87366,23.550049],"type":"Point"}
}