{
  "type": "Feature",
  "properties": {
    "iso:country":"IN",
    "ks:ks_name":"Neriya Kadu",
    "ks:ks_pop":260,
    "ks:ks_type":"HABITATION",
    "name:eng_x_preferred":[
        "Neriya Kadu"
    ],
    "wof:name":"Neriya Kadu",
    "wof:placetype":"locality",
    "wof:population":260
},
  "geometry": {"coordinates":[75.48805299999999,13.006087],"type":"Point"}
}