{
  "type": "Feature",
  "properties": {
    "iso:country":"IN",
    "ks:ks_name":"Lakshmipuram",
    "ks:ks_pop":151,
    "ks:ks_type":"HABITATION",
    "ks:ks_uagg_main":0,
    "name:eng_x_preferred":[
        "Lakshmipuram"
    ],
    "wof:name":"Lakshmipuram",
    "wof:placetype":"neighbourhood",
    "wof:population":151
},
  "geometry": {"coordinates":[78.210684,9.285083],"type":"Point"}
}