{
  "type": "Feature",
  "properties": {
    "iso:country":"IN",
    "ks:ks_name":"Kanapuri",
    "ks:ks_pop":610,
    "ks:ks_type":"HABITATION",
    "ks:ks_uagg_main":0,
    "name:eng_x_preferred":[
        "Kanapuri"
    ],
    "wof:name":"Kanapuri",
    "wof:placetype":"neighbourhood",
    "wof:population":610
},
  "geometry": {"coordinates":[73.67358299999999,22.746067],"type":"Point"}
}