{
  "type": "Feature",
  "properties": {
    "gn:admin1_code":"13.0",
    "gn:admin2_code":"597.0",
    "gn:asciiname":"Kuvatalavadaku",
    "gn:country_code":"IN",
    "gn:dem":53,
    "gn:feature_class":"P",
    "gn:feature_code":"PPL",
    "gn:name":"Kuvatal\u0101vadaku",
    "gn:population":0,
    "gn:timezone":"Asia/Kolkata",
    "iso:country":"IN",
    "wof:name":"Kuvatalavadaku",
    "wof:placetype":"locality"
},
  "geometry": {"coordinates":[76.76297,9.54865],"type":"Point"}
}