{
  "type": "Feature",
  "properties": {
    "iso:country":"IN",
    "ks:ks_name":"Tarapuram",
    "ks:ks_pop":1350,
    "ks:ks_type":"HABITATION",
    "name:eng_x_preferred":[
        "Tarapuram"
    ],
    "wof:name":"Tarapuram",
    "wof:placetype":"locality",
    "wof:population":1350
},
  "geometry": {"coordinates":[77.544606,16.142389],"type":"Point"}
}