{
  "type": "Feature",
  "properties": {
    "iso:country":"IN",
    "ks:ks_alt_nam":"CHAHURTANDA",
    "ks:ks_name":"Chahurtanda",
    "ks:ks_pop":141,
    "ks:ks_type":"HABITATION",
    "name:eng_x_preferred":[
        "Chahurtanda"
    ],
    "wof:name":"Chahurtanda",
    "wof:placetype":"locality",
    "wof:population":141
},
  "geometry": {"coordinates":[76.175849,19.066798],"type":"Point"}
}