{
  "type": "Feature",
  "properties": {
    "gn:admin1_code":"19.0",
    "gn:admin2_code":"576.0",
    "gn:asciiname":"Chennapuri",
    "gn:country_code":"IN",
    "gn:dem":1026,
    "gn:feature_class":"P",
    "gn:feature_code":"PPL",
    "gn:name":"Chennapuri",
    "gn:population":0,
    "gn:timezone":"Asia/Kolkata",
    "iso:country":"IN",
    "wof:name":"Chennapuri",
    "wof:placetype":"locality"
},
  "geometry": {"coordinates":[75.87918000000001,12.64271],"type":"Point"}
}