{
  "type": "Feature",
  "properties": {
    "iso:country":"IN",
    "ks:ks_name":"Bharadidhar",
    "ks:ks_pop":63,
    "ks:ks_type":"VILLAGE",
    "name:eng_x_preferred":[
        "Bharadidhar"
    ],
    "wof:name":"Bharadidhar",
    "wof:placetype":"locality",
    "wof:population":63
},
  "geometry": {"coordinates":[79.11453899999999,29.917214],"type":"Point"}
}