{
  "type": "Feature",
  "properties": {
    "iso:country":"IN",
    "ks:ks_name":"Boregowdanapalya",
    "ks:ks_pop":135,
    "ks:ks_type":"HABITATION",
    "name:eng_x_preferred":[
        "Boregowdanapalya"
    ],
    "wof:name":"Boregowdanapalya",
    "wof:placetype":"locality",
    "wof:population":135
},
  "geometry": {"coordinates":[76.94395299999999,13.20155],"type":"Point"}
}