{
  "type": "Feature",
  "properties": {
    "iso:country":"IN",
    "ks:ks_name":"Chudakhai",
    "ks:ks_pop":58,
    "ks:ks_type":"HABITATION",
    "name:eng_x_preferred":[
        "Chudakhai"
    ],
    "wof:name":"Chudakhai",
    "wof:placetype":"locality",
    "wof:population":58
},
  "geometry": {"coordinates":[84.865612,21.67485],"type":"Point"}
}