{
  "type": "Feature",
  "properties": {
    "gn:admin1_code":"23.0",
    "gn:admin2_code":"49.0",
    "gn:asciiname":"Mandiala",
    "gn:country_code":"IN",
    "gn:dem":227,
    "gn:feature_class":"P",
    "gn:feature_code":"PPL",
    "gn:name":"Mandi\u0101la",
    "gn:population":0,
    "gn:timezone":"Asia/Kolkata",
    "iso:country":"IN",
    "ks:ks_name":"Mandiala",
    "ks:ks_pop":2178,
    "ks:ks_type":"VILLAGE",
    "name:eng_x_preferred":[
        "Mandiala"
    ],
    "wof:name":"Mandiala",
    "wof:placetype":"locality",
    "wof:population":2178
},
  "geometry": {"coordinates":[74.84728,31.549576],"type":"Point"}
}