{
  "type": "Feature",
  "properties": {
    "gn:admin1_code":"36.0",
    "gn:admin2_code":"153.0",
    "gn:asciiname":"Nazimabad",
    "gn:country_code":"IN",
    "gn:dem":156,
    "gn:feature_class":"P",
    "gn:feature_code":"PPL",
    "gn:name":"Naz\u012bm\u0101b\u0101d",
    "gn:population":0,
    "gn:timezone":"Asia/Kolkata",
    "iso:country":"IN",
    "name:pnb_x_preferred":[
        "\u0646\u0627\u0638\u0645 \u0622\u0628\u0627\u062f"
    ],
    "wof:name":"Nazimabad",
    "wof:placetype":"locality"
},
  "geometry": {"coordinates":[80.49176999999997,27.94754],"type":"Point"}
}