{
  "type": "Feature",
  "properties": {
    "iso:country":"IN",
    "ks:ks_name":"Barmer Agor",
    "ks:ks_pop":1809,
    "ks:ks_type":"VILLAGE",
    "name:eng_x_preferred":[
        "Barmer Agor"
    ],
    "wof:name":"Barmer Agor",
    "wof:placetype":"neighbourhood",
    "wof:population":1809
},
  "geometry": {"coordinates":[71.43749200000001,25.756233],"type":"Point"}
}