{
  "type": "Feature",
  "properties": {
    "iso:country":"IN",
    "ks:ks_name":"Sadhushankar T",
    "ks:ks_pop":260,
    "ks:ks_type":"HABITATION",
    "name:eng_x_preferred":[
        "Sadhushankar T"
    ],
    "wof:name":"Sadhushankar T",
    "wof:placetype":"locality",
    "wof:population":260
},
  "geometry": {"coordinates":[77.60778500000001,18.122171],"type":"Point"}
}