{
  "type": "Feature",
  "properties": {
    "gn:admin1_code":"36",
    "gn:admin2_code":"152.0",
    "gn:asciiname":"Dohelia",
    "gn:country_code":"IN",
    "gn:dem":151,
    "gn:feature_class":"P",
    "gn:feature_code":"PPL",
    "gn:name":"Doh\u0113li\u0101",
    "gn:population":0,
    "gn:timezone":"Asia/Kolkata",
    "iso:country":"IN",
    "wof:name":"Dohelia",
    "wof:placetype":"neighbourhood"
},
  "geometry": {"coordinates":[79.50279,27.78361],"type":"Point"}
}