{
  "type": "Feature",
  "properties": {
    "gn:admin1_code":"2",
    "gn:admin2_code":"545.0",
    "gn:asciiname":"Boddapalle",
    "gn:country_code":"IN",
    "gn:dem":264,
    "gn:feature_class":"P",
    "gn:feature_code":"PPL",
    "gn:name":"Boddapalle",
    "gn:population":0,
    "gn:timezone":"Asia/Kolkata",
    "iso:country":"IN",
    "ks:ks_name":"Boddapalli",
    "ks:ks_pop":178,
    "ks:ks_type":"HABITATION",
    "name:eng_x_preferred":[
        "Boddapalli"
    ],
    "name:eng_x_variant":[
        "Boddapalle"
    ],
    "wof:name":"Boddapalli",
    "wof:placetype":"locality",
    "wof:population":178
},
  "geometry": {"coordinates":[81.90984400000001,17.54956],"type":"Point"}
}