{
  "type": "Feature",
  "properties": {
    "iso:country":"IN",
    "ks:ks_name":"Hatibil",
    "ks:ks_pop":995,
    "ks:ks_type":"HABITATION",
    "name:eng_x_preferred":[
        "Hatibil"
    ],
    "wof:name":"Hatibil",
    "wof:placetype":"locality",
    "wof:population":995
},
  "geometry": {"coordinates":[91.726349,26.739447],"type":"Point"}
}