{
  "type": "Feature",
  "properties": {
    "iso:country":"IN",
    "ks:ks_name":"Vajarath",
    "ks:ks_pop":787,
    "ks:ks_type":"VILLAGE",
    "name:eng_x_preferred":[
        "Vajarath"
    ],
    "wof:name":"Vajarath",
    "wof:placetype":"locality",
    "wof:population":787
},
  "geometry": {"coordinates":[73.715419,15.907707],"type":"Point"}
}