{
  "type": "Feature",
  "properties": {
    "gn:admin1_code":"23.0",
    "gn:admin2_code":"35.0",
    "gn:asciiname":"Maira",
    "gn:country_code":"IN",
    "gn:dem":414,
    "gn:feature_class":"P",
    "gn:feature_code":"PPL",
    "gn:name":"Maira",
    "gn:population":0,
    "gn:timezone":"Asia/Kolkata",
    "iso:country":"IN",
    "name:deu_x_preferred":[
        "Maira"
    ],
    "name:fra_x_preferred":[
        "Maira"
    ],
    "name:ita_x_preferred":[
        "Maira"
    ],
    "name:oci_x_preferred":[
        "Maira"
    ],
    "name:pms_x_preferred":[
        "M\u00e0ira"
    ],
    "name:pol_x_preferred":[
        "Maira"
    ],
    "name:rus_x_preferred":[
        "\u041c\u0430\u0439\u0440\u0430"
    ],
    "name:zho_x_preferred":[
        "\u99ac\u4f0a\u62c9\u6cb3"
    ],
    "wof:name":"Maira",
    "wof:placetype":"locality"
},
  "geometry": {"coordinates":[75.71195999999998,32.40322],"type":"Point"}
}