{
  "type": "Feature",
  "properties": {
    "gn:admin1_code":"36",
    "gn:admin2_code":"155.0",
    "gn:asciiname":"Barria",
    "gn:country_code":"IN",
    "gn:dem":131,
    "gn:feature_class":"P",
    "gn:feature_code":"PPL",
    "gn:name":"Barri\u0101",
    "gn:population":0,
    "gn:timezone":"Asia/Kolkata",
    "iso:country":"IN",
    "name:ceb_x_preferred":[
        "Barria piceae"
    ],
    "name:swe_x_preferred":[
        "Barria piceae"
    ],
    "name:ukr_x_preferred":[
        "Barria"
    ],
    "name:war_x_preferred":[
        "Barria piceae"
    ],
    "wof:name":"Barria",
    "wof:placetype":"locality"
},
  "geometry": {"coordinates":[80.67164,27.11252],"type":"Point"}
}