{
  "type": "Feature",
  "properties": {
    "gn:admin1_code":"34.0",
    "gn:admin2_code":"204.0",
    "gn:asciiname":"Tikaita",
    "gn:country_code":"IN",
    "gn:dem":70,
    "gn:feature_class":"P",
    "gn:feature_code":"PPL",
    "gn:name":"Tikaita",
    "gn:population":0,
    "gn:timezone":"Asia/Kolkata",
    "iso:country":"IN",
    "ks:ks_name":"Tikaita",
    "ks:ks_pop":1300,
    "ks:ks_type":"VILLAGE",
    "ks:ks_uagg_main":0,
    "name:eng_x_preferred":[
        "Tikaita"
    ],
    "wof:name":"Tikaita",
    "wof:placetype":"neighbourhood",
    "wof:population":1300
},
  "geometry": {"coordinates":[84.872041,26.582128],"type":"Point"}
}