{
  "type": "Feature",
  "properties": {
    "gn:admin1_code":"19.0",
    "gn:admin2_code":"575.0",
    "gn:asciiname":"Mudakallu",
    "gn:country_code":"IN",
    "gn:dem":137,
    "gn:feature_class":"P",
    "gn:feature_code":"PPL",
    "gn:name":"Mudakallu",
    "gn:population":0,
    "gn:timezone":"Asia/Kolkata",
    "iso:country":"IN",
    "ks:ks_name":"Mudekallu",
    "ks:ks_pop":14,
    "ks:ks_type":"HABITATION",
    "name:eng_x_preferred":[
        "Mudekallu"
    ],
    "name:eng_x_variant":[
        "Mudakallu"
    ],
    "wof:name":"Mudekallu",
    "wof:placetype":"locality",
    "wof:population":14
},
  "geometry": {"coordinates":[75.411029,12.604645],"type":"Point"}
}