{
  "type": "Feature",
  "properties": {
    "iso:country":"IN",
    "ks:ks_name":"Benagerya",
    "ks:ks_pop":0,
    "ks:ks_type":"VILLAGE",
    "name:eng_x_preferred":[
        "Benagerya"
    ],
    "wof:name":"Benagerya",
    "wof:placetype":"locality",
    "wof:population":0
},
  "geometry": {"coordinates":[86.808938,23.127464],"type":"Point"}
}