{
  "type": "Feature",
  "properties": {
    "iso:country":"IN",
    "ks:ks_name":"Darai",
    "ks:ks_pop":230,
    "ks:ks_type":"VILLAGE",
    "name:eng_x_preferred":[
        "Darai"
    ],
    "wof:name":"Darai",
    "wof:placetype":"locality",
    "wof:population":230
},
  "geometry": {"coordinates":[81.185807,22.405433],"type":"Point"}
}