{
  "type": "Feature",
  "properties": {
    "gn:admin1_code":"21",
    "gn:admin2_code":"370.0",
    "gn:asciiname":"Halankanasi",
    "gn:country_code":"IN",
    "gn:dem":180,
    "gn:feature_class":"P",
    "gn:feature_code":"PPL",
    "gn:name":"Halankan\u0101si",
    "gn:population":0,
    "gn:timezone":"Asia/Kolkata",
    "iso:country":"IN",
    "ks:ks_name":"Halankanasi",
    "ks:ks_pop":248,
    "ks:ks_type":"VILLAGE",
    "name:eng_x_preferred":[
        "Halankanasi"
    ],
    "wof:name":"Halankanasi",
    "wof:placetype":"locality",
    "wof:population":248
},
  "geometry": {"coordinates":[83.271086,20.990747],"type":"Point"}
}