{
  "type": "Feature",
  "properties": {
    "iso:country":"IN",
    "ks:ks_name":"Parav",
    "ks:ks_pop":466,
    "ks:ks_type":"HABITATION",
    "name:eng_x_preferred":[
        "Parav"
    ],
    "wof:name":"Parav",
    "wof:placetype":"locality",
    "wof:population":466
},
  "geometry": {"coordinates":[74.88055900000001,23.700129],"type":"Point"}
}