{
  "type": "Feature",
  "properties": {
    "iso:country":"IN",
    "ks:ks_name":"Jirikibadi",
    "ks:ks_pop":218,
    "ks:ks_type":"VILLAGE",
    "name:eng_x_preferred":[
        "Jirikibadi"
    ],
    "wof:name":"Jirikibadi",
    "wof:placetype":"locality",
    "wof:population":218
},
  "geometry": {"coordinates":[84.58667,20.35398],"type":"Point"}
}