{
  "type": "Feature",
  "properties": {
    "iso:country":"IN",
    "ks:ks_name":"Chatu Tola",
    "ks:ks_pop":294,
    "ks:ks_type":"HABITATION",
    "name:eng_x_preferred":[
        "Chatu Tola"
    ],
    "wof:name":"Chatu Tola",
    "wof:placetype":"locality",
    "wof:population":294
},
  "geometry": {"coordinates":[87.886151,26.21463],"type":"Point"}
}