{
  "type": "Feature",
  "properties": {
    "iso:country":"IN",
    "ks:ks_name":"Gowthamanagar",
    "ks:ks_pop":249,
    "ks:ks_type":"HABITATION",
    "name:eng_x_preferred":[
        "Gowthamanagar"
    ],
    "wof:name":"Gowthamanagar",
    "wof:placetype":"locality",
    "wof:population":249
},
  "geometry": {"coordinates":[77.462109,13.775711],"type":"Point"}
}