{
  "type": "Feature",
  "properties": {
    "gn:admin1_code":"35.0",
    "gn:admin2_code":"432",
    "gn:asciiname":"Baktuni",
    "gn:country_code":"IN",
    "gn:dem":431,
    "gn:feature_class":"P",
    "gn:feature_code":"PPL",
    "gn:name":"Baktuni",
    "gn:population":0,
    "gn:timezone":"Asia/Kolkata",
    "iso:country":"IN",
    "wof:name":"Baktuni",
    "wof:placetype":"locality"
},
  "geometry": {"coordinates":[75.31728000000003,24.68163],"type":"Point"}
}