{
  "type": "Feature",
  "properties": {
    "iso:country":"IN",
    "ks:ks_name":"Bikrampur Diara",
    "ks:ks_pop":20,
    "ks:ks_type":"HABITATION",
    "ks:ks_uagg_main":0,
    "name:eng_x_preferred":[
        "Bikrampur Diara"
    ],
    "wof:name":"Bikrampur Diara",
    "wof:placetype":"neighbourhood",
    "wof:population":20
},
  "geometry": {"coordinates":[84.27857899999999,26.129888],"type":"Point"}
}