{
  "type": "Feature",
  "properties": {
    "iso:country":"IN",
    "ks:ks_name":"Lalkura",
    "ks:ks_pop":844,
    "ks:ks_type":"VILLAGE",
    "name:eng_x_preferred":[
        "Lalkura"
    ],
    "wof:name":"Lalkura",
    "wof:placetype":"locality",
    "wof:population":844
},
  "geometry": {"coordinates":[90.392805,26.245503],"type":"Point"}
}