{
  "type": "Feature",
  "properties": {
    "iso:country":"IN",
    "ks:ks_name":"Beejadakatte",
    "ks:ks_pop":74,
    "ks:ks_type":"HABITATION",
    "name:eng_x_preferred":[
        "Beejadakatte"
    ],
    "wof:name":"Beejadakatte",
    "wof:placetype":"locality",
    "wof:population":74
},
  "geometry": {"coordinates":[75.090085,13.251643],"type":"Point"}
}