{
  "type": "Feature",
  "properties": {
    "iso:country":"IN",
    "ks:ks_name":"Dewald Gaon",
    "ks:ks_pop":235,
    "ks:ks_type":"HABITATION",
    "name:eng_x_preferred":[
        "Dewald Gaon"
    ],
    "wof:name":"Dewald Gaon",
    "wof:placetype":"locality",
    "wof:population":235
},
  "geometry": {"coordinates":[78.584649,30.14154],"type":"Point"}
}