{
  "type": "Feature",
  "properties": {
    "iso:country":"IN",
    "ks:ks_name":"Nagla Jatkora",
    "ks:ks_pop":524,
    "ks:ks_type":"HABITATION",
    "name:eng_x_preferred":[
        "Nagla Jatkora"
    ],
    "wof:name":"Nagla Jatkora",
    "wof:placetype":"locality",
    "wof:population":524
},
  "geometry": {"coordinates":[78.505652,27.94523],"type":"Point"}
}