{
  "type": "Feature",
  "properties": {
    "iso:country":"IN",
    "ks:ks_name":"Jaganathaprasadpatana",
    "ks:ks_pop":507,
    "ks:ks_type":"VILLAGE",
    "name:eng_x_preferred":[
        "Jaganathaprasadpatana"
    ],
    "wof:name":"Jaganathaprasadpatana",
    "wof:placetype":"locality",
    "wof:population":507
},
  "geometry": {"coordinates":[84.996881,20.504092],"type":"Point"}
}