{
  "type": "Feature",
  "properties": {
    "iso:country":"IN",
    "ks:ks_name":"Kalgawa",
    "ks:ks_pop":152,
    "ks:ks_type":"HABITATION",
    "name:eng_x_preferred":[
        "Kalgawa"
    ],
    "wof:name":"Kalgawa",
    "wof:placetype":"locality",
    "wof:population":152
},
  "geometry": {"coordinates":[82.699682,27.239635],"type":"Point"}
}