{
  "type": "Feature",
  "properties": {
    "iso:country":"IN",
    "ks:ks_name":"Chikati Pada",
    "ks:ks_pop":600,
    "ks:ks_type":"HABITATION",
    "name:eng_x_preferred":[
        "Chikati Pada"
    ],
    "wof:name":"Chikati Pada",
    "wof:placetype":"locality",
    "wof:population":600
},
  "geometry": {"coordinates":[73.314639,20.596028],"type":"Point"}
}