{
  "type": "Feature",
  "properties": {
    "iso:country":"IN",
    "ks:ks_name":"Rangana Gunta",
    "ks:ks_pop":150,
    "ks:ks_type":"HABITATION",
    "name:eng_x_preferred":[
        "Rangana Gunta"
    ],
    "wof:name":"Rangana Gunta",
    "wof:placetype":"locality",
    "wof:population":150
},
  "geometry": {"coordinates":[80.064035,14.009683],"type":"Point"}
}