{
  "type": "Feature",
  "properties": {
    "iso:country":"IN",
    "ks:ks_name":"Gothankarwadi",
    "ks:ks_pop":51,
    "ks:ks_type":"HABITATION",
    "name:eng_x_preferred":[
        "Gothankarwadi"
    ],
    "wof:name":"Gothankarwadi",
    "wof:placetype":"locality",
    "wof:population":51
},
  "geometry": {"coordinates":[73.328306,16.751225],"type":"Point"}
}