{
  "type": "Feature",
  "properties": {
    "iso:country":"IN",
    "ks:ks_name":"Ravi Das Tola",
    "ks:ks_pop":188,
    "ks:ks_type":"HABITATION",
    "name:eng_x_preferred":[
        "Ravi Das Tola"
    ],
    "wof:name":"Ravi Das Tola",
    "wof:placetype":"locality",
    "wof:population":188
},
  "geometry": {"coordinates":[86.136639,24.588655],"type":"Point"}
}