{
  "type": "Feature",
  "properties": {
    "gn:admin1_code":"36",
    "gn:admin2_code":"165.0",
    "gn:asciiname":"Kahta",
    "gn:country_code":"IN",
    "gn:dem":134,
    "gn:feature_class":"P",
    "gn:feature_code":"PPL",
    "gn:name":"K\u0101hta",
    "gn:population":0,
    "gn:timezone":"Asia/Kolkata",
    "iso:country":"IN",
    "ks:ks_alt_nam":"K\u0101hta",
    "ks:ks_name":"Kahta",
    "ks:ks_pop":1359,
    "ks:ks_type":"VILLAGE",
    "name:eng_x_preferred":[
        "Kahta"
    ],
    "name:eng_x_variant":[
        "K\u0101hta"
    ],
    "wof:name":"Kahta",
    "wof:placetype":"locality",
    "wof:population":1359
},
  "geometry": {"coordinates":[79.39862100000001,25.810728],"type":"Point"}
}