{
  "type": "Feature",
  "properties": {
    "gn:admin1_code":"19.0",
    "gn:admin2_code":"570.0",
    "gn:asciiname":"Gedlihalli",
    "gn:country_code":"IN",
    "gn:dem":752,
    "gn:feature_class":"P",
    "gn:feature_code":"PPL",
    "gn:name":"Gedlihalli",
    "gn:population":0,
    "gn:timezone":"Asia/Kolkata",
    "iso:country":"IN",
    "wof:name":"Gedlihalli",
    "wof:placetype":"locality"
},
  "geometry": {"coordinates":[76.04751999999998,13.51102],"type":"Point"}
}