{
  "type": "Feature",
  "properties": {
    "iso:country":"IN",
    "ks:ks_name":"Mathadathimmanahalli",
    "ks:ks_pop":84,
    "ks:ks_type":"HABITATION",
    "ks:ks_uagg_main":0,
    "name:eng_x_preferred":[
        "Mathadathimmanahalli"
    ],
    "wof:name":"Mathadathimmanahalli",
    "wof:placetype":"neighbourhood",
    "wof:population":84
},
  "geometry": {"coordinates":[75.785189,13.266188],"type":"Point"}
}