{
  "type": "Feature",
  "properties": {
    "iso:country":"IN",
    "ks:ks_name":"Turibhejiguda",
    "ks:ks_pop":198,
    "ks:ks_type":"VILLAGE",
    "name:eng_x_preferred":[
        "Turibhejiguda"
    ],
    "wof:name":"Turibhejiguda",
    "wof:placetype":"locality",
    "wof:population":198
},
  "geometry": {"coordinates":[83.16399800000001,19.551655],"type":"Point"}
}