{
  "type": "Feature",
  "properties": {
    "iso:country":"IN",
    "ks:ks_name":"V Sevalpatti",
    "ks:ks_pop":350,
    "ks:ks_type":"HABITATION",
    "name:eng_x_preferred":[
        "V Sevalpatti"
    ],
    "wof:name":"V Sevalpatti",
    "wof:placetype":"locality",
    "wof:population":350
},
  "geometry": {"coordinates":[78.471582,10.579422],"type":"Point"}
}