{
  "type": "Feature",
  "properties": {
    "iso:country":"IN",
    "ks:ks_alt_nam":"Jit\u0101gh\u0101ti",
    "ks:ks_name":"Jitaghati",
    "ks:ks_type":"VILLAGE",
    "name:eng_x_preferred":[
        "Jitaghati"
    ],
    "name:eng_x_variant":[
        "Jit\u0101gh\u0101ti"
    ],
    "wof:name":"Jitaghati",
    "wof:placetype":"locality"
},
  "geometry": {"coordinates":[84.503967,20.19479],"type":"Point"}
}