{
  "type": "Feature",
  "properties": {
    "gn:admin1_code":"37",
    "gn:admin2_code":"408.0",
    "gn:asciiname":"Dumartola",
    "gn:country_code":"IN",
    "gn:dem":436,
    "gn:feature_class":"P",
    "gn:feature_code":"PPL",
    "gn:name":"D\u016bmartola",
    "gn:population":0,
    "gn:timezone":"Asia/Kolkata",
    "iso:country":"IN",
    "ks:ks_alt_nam":"D\u016bmartola",
    "ks:ks_name":"Dumartola",
    "ks:ks_pop":142,
    "ks:ks_type":"VILLAGE",
    "name:eng_x_preferred":[
        "Dumartola"
    ],
    "name:eng_x_variant":[
        "D\u016bmartola"
    ],
    "wof:name":"Dumartola",
    "wof:placetype":"locality",
    "wof:population":142
},
  "geometry": {"coordinates":[80.956579,20.582808],"type":"Point"}
}