{
  "type": "Feature",
  "properties": {
    "iso:country":"IN",
    "ks:ks_name":"Ainagobindapur",
    "ks:ks_pop":551,
    "ks:ks_type":"VILLAGE",
    "name:eng_x_preferred":[
        "Ainagobindapur"
    ],
    "wof:name":"Ainagobindapur",
    "wof:placetype":"locality",
    "wof:population":551
},
  "geometry": {"coordinates":[87.169414,23.247079],"type":"Point"}
}