{
  "type": "Feature",
  "properties": {
    "gn:admin1_code":"24.0",
    "gn:admin2_code":"125.0",
    "gn:asciiname":"Barsala",
    "gn:country_code":"IN",
    "gn:dem":433,
    "gn:feature_class":"P",
    "gn:feature_code":"PPL",
    "gn:name":"Barsala",
    "gn:population":0,
    "gn:timezone":"Asia/Kolkata",
    "iso:country":"IN",
    "ks:ks_name":"Varsala",
    "ks:ks_pop":1297,
    "ks:ks_type":"VILLAGE",
    "name:eng_x_preferred":[
        "Varsala"
    ],
    "name:eng_x_variant":[
        "Barsala"
    ],
    "wof:name":"Varsala",
    "wof:placetype":"locality",
    "wof:population":1297
},
  "geometry": {"coordinates":[74.635007,23.213538],"type":"Point"}
}