{
  "type": "Feature",
  "properties": {
    "iso:country":"IN",
    "ks:ks_name":"Kotharevallapalem",
    "ks:ks_pop":12,
    "ks:ks_type":"HABITATION",
    "name:eng_x_preferred":[
        "Kotharevallapalem"
    ],
    "wof:name":"Kotharevallapalem",
    "wof:placetype":"locality",
    "wof:population":12
},
  "geometry": {"coordinates":[82.94827600000001,18.025578],"type":"Point"}
}