{
  "type": "Feature",
  "properties": {
    "iso:country":"IN",
    "ks:ks_name":"Kasthuravalli",
    "ks:ks_pop":122,
    "ks:ks_type":"HABITATION",
    "name:eng_x_preferred":[
        "Kasthuravalli"
    ],
    "wof:name":"Kasthuravalli",
    "wof:placetype":"locality",
    "wof:population":122
},
  "geometry": {"coordinates":[76.145602,12.988644],"type":"Point"}
}