{
  "type": "Feature",
  "properties": {
    "iso:country":"IN",
    "ks:ks_name":"Basi",
    "ks:ks_pop":2239,
    "ks:ks_type":"VILLAGE",
    "ks:ks_uagg_main":0,
    "name:eng_x_preferred":[
        "Basi"
    ],
    "wof:name":"Basi",
    "wof:placetype":"neighbourhood",
    "wof:population":2239
},
  "geometry": {"coordinates":[73.168296,27.790541],"type":"Point"}
}