{
  "type": "Feature",
  "properties": {
    "gn:admin1_code":"29.0",
    "gn:admin2_code":"243.0",
    "gn:asciiname":"Kopre",
    "gn:country_code":"IN",
    "gn:dem":1084,
    "gn:feature_class":"P",
    "gn:feature_code":"PPL",
    "gn:name":"K\u014dpre",
    "gn:population":0,
    "gn:timezone":"Asia/Kolkata",
    "iso:country":"IN",
    "wof:name":"Kopre",
    "wof:placetype":"locality"
},
  "geometry": {"coordinates":[88.47624999999999,27.18001],"type":"Point"}
}