{
  "type": "Feature",
  "properties": {
    "gn:admin1_code":"2.0",
    "gn:admin2_code":"551.0",
    "gn:asciiname":"Kondapeta",
    "gn:country_code":"IN",
    "gn:dem":196,
    "gn:feature_class":"P",
    "gn:feature_code":"PPL",
    "gn:name":"Kondapeta",
    "gn:population":0,
    "gn:timezone":"Asia/Kolkata",
    "iso:country":"IN",
    "ks:ks_name":"Kondapeta",
    "ks:ks_pop":713,
    "ks:ks_type":"VILLAGE",
    "ks:ks_uagg_main":0,
    "name:eng_x_preferred":[
        "Kondapeta"
    ],
    "wof:name":"Kondapeta",
    "wof:placetype":"neighbourhood",
    "wof:population":713
},
  "geometry": {"coordinates":[78.917148,15.092631],"type":"Point"}
}