{
  "type": "Feature",
  "properties": {
    "iso:country":"IN",
    "ks:ks_name":"Aligara",
    "ks:ks_pop":1682,
    "ks:ks_type":"VILLAGE",
    "ks:ks_uagg_main":0,
    "name:eng_x_preferred":[
        "Aligara"
    ],
    "wof:name":"Aligara",
    "wof:placetype":"neighbourhood",
    "wof:population":1682
},
  "geometry": {"coordinates":[88.41057600000001,25.392393],"type":"Point"}
}