{
  "type": "Feature",
  "properties": {
    "iso:country":"IN",
    "ks:ks_name":"Devanilaya",
    "ks:ks_pop":33,
    "ks:ks_type":"HABITATION",
    "name:eng_x_preferred":[
        "Devanilaya"
    ],
    "wof:name":"Devanilaya",
    "wof:placetype":"locality",
    "wof:population":33
},
  "geometry": {"coordinates":[74.840434,14.639629],"type":"Point"}
}