{
  "type": "Feature",
  "properties": {
    "iso:country":"IN",
    "ks:ks_name":"Saidpur",
    "ks:ks_pop":0,
    "ks:ks_type":"VILLAGE",
    "name:eng_x_preferred":[
        "Saidpur"
    ],
    "wof:name":"Saidpur",
    "wof:placetype":"locality",
    "wof:population":0
},
  "geometry": {"coordinates":[84.142599,25.237269],"type":"Point"}
}