{
  "type": "Feature",
  "properties": {
    "iso:country":"IN",
    "ks:ks_name":"Andilo",
    "ks:ks_pop":2764,
    "ks:ks_type":"VILLAGE",
    "ks:ks_uagg_main":0,
    "name:eng_x_preferred":[
        "Andilo"
    ],
    "wof:name":"Andilo",
    "wof:placetype":"neighbourhood",
    "wof:population":2764
},
  "geometry": {"coordinates":[85.891699,20.301398],"type":"Point"}
}