{
  "type": "Feature",
  "properties": {
    "iso:country":"IN",
    "ks:ks_name":"Karanpur",
    "ks:ks_pop":8613,
    "ks:ks_type":"VILLAGE",
    "name:eng_x_preferred":[
        "Karanpur"
    ],
    "wof:name":"Karanpur",
    "wof:placetype":"locality",
    "wof:population":8613
},
  "geometry": {"coordinates":[85.46726,26.166717],"type":"Point"}
}