{
  "type": "Feature",
  "properties": {
    "iso:country":"IN",
    "ks:ks_name":"Chandmari Satbaini",
    "ks:ks_pop":1514,
    "ks:ks_type":"VILLAGE",
    "ks:ks_uagg_main":0,
    "name:eng_x_preferred":[
        "Chandmari Satbaini"
    ],
    "wof:name":"Chandmari Satbaini",
    "wof:placetype":"neighbourhood",
    "wof:population":1514
},
  "geometry": {"coordinates":[90.59625,26.068003],"type":"Point"}
}