{
  "type": "Feature",
  "properties": {
    "iso:country":"IN",
    "ks:ks_alt_nam":"Ras\u012bdpur",
    "ks:ks_name":"Rasidpur",
    "ks:ks_type":"VILLAGE",
    "name:eng_x_preferred":[
        "Rasidpur"
    ],
    "name:eng_x_variant":[
        "Ras\u012bdpur"
    ],
    "wof:name":"Rasidpur",
    "wof:placetype":"locality"
},
  "geometry": {"coordinates":[78.519567,28.579628],"type":"Point"}
}