{
  "type": "Feature",
  "properties": {
    "iso:country":"IN",
    "ks:ks_name":"Russala",
    "ks:ks_pop":256,
    "ks:ks_type":"HABITATION",
    "name:eng_x_preferred":[
        "Russala"
    ],
    "wof:name":"Russala",
    "wof:placetype":"locality",
    "wof:population":256
},
  "geometry": {"coordinates":[78.17374700000001,24.009644],"type":"Point"}
}