{
  "type": "Feature",
  "properties": {
    "gn:admin1_code":"2",
    "gn:admin2_code":"544.0",
    "gn:asciiname":"Papaipalem",
    "gn:country_code":"IN",
    "gn:dem":108,
    "gn:feature_class":"P",
    "gn:feature_code":"PPL",
    "gn:name":"Papaip\u0101lem",
    "gn:population":0,
    "gn:timezone":"Asia/Kolkata",
    "iso:country":"IN",
    "wof:name":"Papaipalem",
    "wof:placetype":"neighbourhood"
},
  "geometry": {"coordinates":[82.74111000000001,17.6652],"type":"Point"}
}