{
  "type": "Feature",
  "properties": {
    "iso:country":"IN",
    "ks:ks_name":"Hanuman Temple",
    "ks:ks_pop":26,
    "ks:ks_type":"HABITATION",
    "name:eng_x_preferred":[
        "Hanuman Temple"
    ],
    "wof:name":"Hanuman Temple",
    "wof:placetype":"locality",
    "wof:population":26
},
  "geometry": {"coordinates":[77.43869100000001,18.118956],"type":"Point"}
}