{
  "type": "Feature",
  "properties": {
    "iso:country":"IN",
    "ks:ks_name":"Kuttamboor",
    "ks:ks_pop":1912,
    "ks:ks_type":"HABITATION",
    "name:eng_x_preferred":[
        "Kuttamboor"
    ],
    "wof:name":"Kuttamboor",
    "wof:placetype":"locality",
    "wof:population":1912
},
  "geometry": {"coordinates":[75.849841,11.395748],"type":"Point"}
}