{
  "type": "Feature",
  "properties": {
    "iso:country":"IN",
    "ks:ks_name":"Bampur",
    "ks:ks_pop":390,
    "ks:ks_type":"HABITATION",
    "ks:ks_uagg_main":0,
    "name:eng_x_preferred":[
        "Bampur"
    ],
    "wof:name":"Bampur",
    "wof:placetype":"neighbourhood",
    "wof:population":390
},
  "geometry": {"coordinates":[85.78664499999999,25.467754],"type":"Point"}
}