{
  "type": "Feature",
  "properties": {
    "iso:country":"IN",
    "ks:ks_name":"Deobari",
    "ks:ks_pop":16,
    "ks:ks_type":"HABITATION",
    "name:eng_x_preferred":[
        "Deobari"
    ],
    "wof:name":"Deobari",
    "wof:placetype":"locality",
    "wof:population":16
},
  "geometry": {"coordinates":[78.564622,29.908679],"type":"Point"}
}