{
  "type": "Feature",
  "properties": {
    "iso:country":"IN",
    "ks:ks_alt_nam":"padila",
    "ks:ks_name":"Padila",
    "ks:ks_pop":2000,
    "ks:ks_type":"HABITATION",
    "name:eng_x_preferred":[
        "Padila"
    ],
    "wof:name":"Padila",
    "wof:placetype":"locality",
    "wof:population":2000
},
  "geometry": {"coordinates":[81.87024099999999,25.512621],"type":"Point"}
}