{
  "type": "Feature",
  "properties": {
    "iso:country":"IN",
    "ks:ks_name":"Jambudiya",
    "ks:ks_pop":549,
    "ks:ks_type":"HABITATION",
    "name:eng_x_preferred":[
        "Jambudiya"
    ],
    "wof:name":"Jambudiya",
    "wof:placetype":"locality",
    "wof:population":549
},
  "geometry": {"coordinates":[72.72413899999999,22.343806],"type":"Point"}
}