{
  "type": "Feature",
  "properties": {
    "iso:country":"IN",
    "ks:ks_name":"Rathbar",
    "ks:ks_pop":28,
    "ks:ks_type":"VILLAGE",
    "name:eng_x_preferred":[
        "Rathbar"
    ],
    "wof:name":"Rathbar",
    "wof:placetype":"locality",
    "wof:population":28
},
  "geometry": {"coordinates":[87.324811,22.251315],"type":"Point"}
}