{
  "type": "Feature",
  "properties": {
    "iso:country":"IN",
    "ks:ks_name":"Saraidaha",
    "ks:ks_pop":35,
    "ks:ks_type":"HABITATION",
    "name:eng_x_preferred":[
        "Saraidaha"
    ],
    "wof:name":"Saraidaha",
    "wof:placetype":"locality",
    "wof:population":35
},
  "geometry": {"coordinates":[86.329035,23.926307],"type":"Point"}
}