{
  "type": "Feature",
  "properties": {
    "iso:country":"IN",
    "ks:ks_name":"Pipali",
    "ks:ks_pop":1068,
    "ks:ks_type":"HABITATION",
    "name:eng_x_preferred":[
        "Pipali"
    ],
    "wof:name":"Pipali",
    "wof:placetype":"locality",
    "wof:population":1068
},
  "geometry": {"coordinates":[74.00197199999999,22.877139],"type":"Point"}
}