{
  "type": "Feature",
  "properties": {
    "iso:country":"IN",
    "ks:ks_alt_nam":"chunga",
    "ks:ks_name":"Chunga",
    "ks:ks_pop":10,
    "ks:ks_type":"HABITATION",
    "name:eng_x_preferred":[
        "Chunga"
    ],
    "wof:name":"Chunga",
    "wof:placetype":"locality",
    "wof:population":10
},
  "geometry": {"coordinates":[76.333601,12.508703],"type":"Point"}
}