{
  "type": "Feature",
  "properties": {
    "iso:country":"IN",
    "ks:ks_name":"Larapari",
    "ks:ks_pop":222,
    "ks:ks_type":"HABITATION",
    "name:eng_x_preferred":[
        "Larapari"
    ],
    "wof:name":"Larapari",
    "wof:placetype":"locality",
    "wof:population":222
},
  "geometry": {"coordinates":[82.927003,20.345413],"type":"Point"}
}