{
  "type": "Feature",
  "properties": {
    "iso:country":"IN",
    "ks:ks_name":"Vadia",
    "ks:ks_pop":4480,
    "ks:ks_type":"VILLAGE",
    "ks:ks_uagg_main":0,
    "name:eng_x_preferred":[
        "Vadia"
    ],
    "wof:name":"Vadia",
    "wof:placetype":"neighbourhood",
    "wof:population":4480
},
  "geometry": {"coordinates":[73.517284,21.866616],"type":"Point"}
}