{
  "type": "Feature",
  "properties": {
    "gn:admin1_code":"23.0",
    "gn:admin2_code":"51.0",
    "gn:asciiname":"Khizrpur",
    "gn:country_code":"IN",
    "gn:dem":264,
    "gn:feature_class":"P",
    "gn:feature_code":"PPL",
    "gn:name":"Khizrpur",
    "gn:population":0,
    "gn:timezone":"Asia/Kolkata",
    "iso:country":"IN",
    "ks:ks_name":"Khizrpur",
    "ks:ks_type":"VILLAGE",
    "name:eng_x_preferred":[
        "Khizrpur"
    ],
    "wof:name":"Khizrpur",
    "wof:placetype":"locality"
},
  "geometry": {"coordinates":[76.44273099999999,30.95627],"type":"Point"}
}