{
  "type": "Feature",
  "properties": {
    "gn:admin1_code":"21",
    "gn:admin2_code":"394.0",
    "gn:asciiname":"Karamahul",
    "gn:country_code":"IN",
    "gn:dem":298,
    "gn:feature_class":"P",
    "gn:feature_code":"PPL",
    "gn:name":"Kar\u0101mahul",
    "gn:population":0,
    "gn:timezone":"Asia/Kolkata",
    "iso:country":"IN",
    "ks:ks_alt_nam":"Kar\u0101mahul",
    "ks:ks_name":"Karamahul",
    "ks:ks_type":"VILLAGE",
    "name:eng_x_preferred":[
        "Karamahul"
    ],
    "name:eng_x_variant":[
        "Kar\u0101mahul"
    ],
    "wof:name":"Karamahul",
    "wof:placetype":"locality"
},
  "geometry": {"coordinates":[82.69099799999999,20.485322],"type":"Point"}
}