{
  "type": "Feature",
  "properties": {
    "iso:country":"IN",
    "ks:ks_name":"Shailaran Para",
    "ks:ks_pop":109,
    "ks:ks_type":"HABITATION",
    "name:eng_x_preferred":[
        "Shailaran Para"
    ],
    "wof:name":"Shailaran Para",
    "wof:placetype":"locality",
    "wof:population":109
},
  "geometry": {"coordinates":[92.176112,23.963712],"type":"Point"}
}