{
  "type": "Feature",
  "properties": {
    "iso:country":"IN",
    "ks:ks_name":"Kepulagudde",
    "ks:ks_pop":371,
    "ks:ks_type":"HABITATION",
    "name:eng_x_preferred":[
        "Kepulagudde"
    ],
    "wof:name":"Kepulagudde",
    "wof:placetype":"locality",
    "wof:population":371
},
  "geometry": {"coordinates":[75.136267,12.753465],"type":"Point"}
}