{
  "type": "Feature",
  "properties": {
    "iso:country":"IN",
    "ks:ks_alt_nam":"karpadar",
    "ks:ks_name":"Karpadar",
    "ks:ks_pop":200,
    "ks:ks_type":"HABITATION",
    "name:eng_x_preferred":[
        "Karpadar"
    ],
    "wof:name":"Karpadar",
    "wof:placetype":"locality",
    "wof:population":200
},
  "geometry": {"coordinates":[83.274123,19.921322],"type":"Point"}
}