{
  "type": "Feature",
  "properties": {
    "iso:country":"IN",
    "ks:ks_name":"Adhiyar Khoh",
    "ks:ks_pop":237,
    "ks:ks_type":"VILLAGE",
    "name:eng_x_preferred":[
        "Adhiyar Khoh"
    ],
    "wof:name":"Adhiyar Khoh",
    "wof:placetype":"locality",
    "wof:population":237
},
  "geometry": {"coordinates":[81.519526,23.612462],"type":"Point"}
}