{
  "type": "Feature",
  "properties": {
    "gn:admin1_code":"36",
    "gn:admin2_code":"200.0",
    "gn:asciiname":"Kuchmarwa",
    "gn:country_code":"IN",
    "gn:dem":304,
    "gn:feature_class":"P",
    "gn:feature_code":"PPL",
    "gn:name":"Kuchmarwa",
    "gn:population":0,
    "gn:timezone":"Asia/Kolkata",
    "iso:country":"IN",
    "name:und_x_variant":[
        "Bhairopur"
    ],
    "wof:name":"Kuchmarwa",
    "wof:placetype":"locality"
},
  "geometry": {"coordinates":[83.00953,24.77108],"type":"Point"}
}