{
  "type": "Feature",
  "properties": {
    "iso:country":"IN",
    "qs:name":"Kishan Ganj",
    "qs:name_adm0":"India",
    "qs:name_adm1":"Delhi",
    "qs:photos":40,
    "qs:photos_1k":8,
    "qs:photos_9k":1,
    "qs:photos_9r":2,
    "qs:photos_all":40,
    "qs:photos_sr":2,
    "qs:placetype":"Suburb",
    "qs:pop_sr":"0",
    "wof:name":"Kishan Ganj",
    "wof:placetype":"neighbourhood"
},
  "geometry": {"coordinates":[77.199039,28.660918],"type":"Point"}
}