{
  "type": "Feature",
  "properties": {
    "iso:country":"IN",
    "ks:ks_alt_nam":"Nallappan kadu",
    "ks:ks_name":"Nallappan Kadu",
    "ks:ks_pop":145,
    "ks:ks_type":"HABITATION",
    "name:eng_x_preferred":[
        "Nallappan Kadu"
    ],
    "wof:name":"Nallappan Kadu",
    "wof:placetype":"neighbourhood",
    "wof:population":145
},
  "geometry": {"coordinates":[78.11551900000001,11.731291],"type":"Point"}
}