{
  "type": "Feature",
  "properties": {
    "iso:country":"IN",
    "ks:ks_name":"Kalipahari",
    "ks:ks_pop":337,
    "ks:ks_type":"VILLAGE",
    "name:eng_x_preferred":[
        "Kalipahari"
    ],
    "wof:name":"Kalipahari",
    "wof:placetype":"locality",
    "wof:population":337
},
  "geometry": {"coordinates":[87.043274,23.848727],"type":"Point"}
}