{
  "type": "Feature",
  "properties": {
    "iso:country":"IN",
    "ks:ks_name":"Afjupur",
    "ks:ks_pop":64,
    "ks:ks_type":"VILLAGE",
    "name:eng_x_preferred":[
        "Afjupur"
    ],
    "wof:name":"Afjupur",
    "wof:placetype":"locality",
    "wof:population":64
},
  "geometry": {"coordinates":[86.41328300000001,25.233257],"type":"Point"}
}