{
  "type": "Feature",
  "properties": {
    "iso:country":"IN",
    "ks:ks_name":"Hope Town",
    "ks:ks_type":"VILLAGE",
    "ks:ks_uagg_main":0,
    "name:eng_x_preferred":[
        "Hope Town"
    ],
    "wof:name":"Hope Town",
    "wof:placetype":"neighbourhood"
},
  "geometry": {"coordinates":[92.733333,11.666667],"type":"Point"}
}