{
  "type": "Feature",
  "properties": {
    "iso:country":"IN",
    "ks:ks_name":"Canal Saho",
    "ks:ks_pop":151,
    "ks:ks_type":"HABITATION",
    "name:eng_x_preferred":[
        "Canal Saho"
    ],
    "wof:name":"Canal Saho",
    "wof:placetype":"locality",
    "wof:population":151
},
  "geometry": {"coordinates":[82.564341,18.984648],"type":"Point"}
}