{
  "type": "Feature",
  "properties": {
    "iso:country":"IN",
    "ks:ks_name":"Calata",
    "ks:ks_pop":1686,
    "ks:ks_type":"VILLAGE",
    "ks:ks_uagg_main":0,
    "name:eng_x_preferred":[
        "Calata"
    ],
    "wof:name":"Calata",
    "wof:placetype":"neighbourhood",
    "wof:population":1686
},
  "geometry": {"coordinates":[73.918227,15.311059],"type":"Point"}
}