{
  "type": "Feature",
  "properties": {
    "iso:country":"IN",
    "ks:ks_name":"Dharma",
    "ks:ks_pop":39,
    "ks:ks_type":"VILLAGE",
    "name:eng_x_preferred":[
        "Dharma"
    ],
    "wof:name":"Dharma",
    "wof:placetype":"locality",
    "wof:population":39
},
  "geometry": {"coordinates":[81.093405,19.075341],"type":"Point"}
}