{
  "type": "Feature",
  "properties": {
    "iso:country":"IN",
    "ks:ks_name":"Chopari",
    "ks:ks_pop":112,
    "ks:ks_type":"HABITATION",
    "name:eng_x_preferred":[
        "Chopari"
    ],
    "wof:name":"Chopari",
    "wof:placetype":"locality",
    "wof:population":112
},
  "geometry": {"coordinates":[78.638251,30.041684],"type":"Point"}
}