{
  "type": "Feature",
  "properties": {
    "iso:country":"IN",
    "ks:ks_name":"Malmatha",
    "ks:ks_pop":2846,
    "ks:ks_type":"VILLAGE",
    "name:eng_x_preferred":[
        "Malmatha"
    ],
    "wof:name":"Malmatha",
    "wof:placetype":"locality",
    "wof:population":2846
},
  "geometry": {"coordinates":[73.53290800000001,23.737389],"type":"Point"}
}