{
  "type": "Feature",
  "properties": {
    "iso:country":"IN",
    "ks:ks_name":"Bisunpur",
    "ks:ks_pop":12,
    "ks:ks_type":"VILLAGE",
    "name:eng_x_preferred":[
        "Bisunpur"
    ],
    "wof:name":"Bisunpur",
    "wof:placetype":"locality",
    "wof:population":12
},
  "geometry": {"coordinates":[86.812342,24.163664],"type":"Point"}
}