{
  "type": "Feature",
  "properties": {
    "iso:country":"IN",
    "ks:ks_name":"Golamitara",
    "ks:ks_pop":30,
    "ks:ks_type":"VILLAGE",
    "name:eng_x_preferred":[
        "Golamitara"
    ],
    "wof:name":"Golamitara",
    "wof:placetype":"locality",
    "wof:population":30
},
  "geometry": {"coordinates":[86.98662,23.204265],"type":"Point"}
}