{
  "type": "Feature",
  "properties": {
    "gn:admin1_code":"25.0",
    "gn:admin2_code":"604.0",
    "gn:asciiname":"Nagamalai",
    "gn:country_code":"IN",
    "gn:dem":26,
    "gn:feature_class":"P",
    "gn:feature_code":"PPL",
    "gn:name":"Nagamalai",
    "gn:population":0,
    "gn:timezone":"Asia/Kolkata",
    "iso:country":"IN",
    "name:tam_x_preferred":[
        "\u0ba8\u0bbe\u0b95\u0bae\u0bb2\u0bc8"
    ],
    "wof:name":"Nagamalai",
    "wof:placetype":"neighbourhood"
},
  "geometry": {"coordinates":[79.98159,12.3931],"type":"Point"}
}