{
  "type": "Feature",
  "properties": {
    "iso:country":"IN",
    "ks:ks_name":"Devli",
    "ks:ks_pop":1138,
    "ks:ks_type":"VILLAGE",
    "name:eng_x_preferred":[
        "Devli"
    ],
    "wof:name":"Devli",
    "wof:placetype":"locality",
    "wof:population":1138
},
  "geometry": {"coordinates":[73.51016799999999,16.025207],"type":"Point"}
}