{
  "type": "Feature",
  "properties": {
    "iso:country":"IN",
    "ks:ks_name":"Kabbinapala",
    "ks:ks_pop":21,
    "ks:ks_type":"HABITATION",
    "name:eng_x_preferred":[
        "Kabbinapala"
    ],
    "wof:name":"Kabbinapala",
    "wof:placetype":"locality",
    "wof:population":21
},
  "geometry": {"coordinates":[76.019722,12.033333],"type":"Point"}
}