{
  "type": "Feature",
  "properties": {
    "gn:admin1_code":"12.0",
    "gn:admin2_code":"19.0",
    "gn:asciiname":"Bannu",
    "gn:country_code":"IN",
    "gn:dem":757,
    "gn:feature_class":"P",
    "gn:feature_code":"PPL",
    "gn:name":"Bannu",
    "gn:population":0,
    "gn:timezone":"Asia/Kolkata",
    "iso:country":"IN",
    "name:ara_x_preferred":[
        "\u0628\u0627\u0646\u0648"
    ],
    "name:cat_x_preferred":[
        "Bannu"
    ],
    "name:ceb_x_preferred":[
        "Bannu"
    ],
    "name:deu_x_preferred":[
        "Bannu"
    ],
    "name:fas_x_preferred":[
        "\u0628\u0646\u0648"
    ],
    "name:fra_x_preferred":[
        "Bannu"
    ],
    "name:hin_x_preferred":[
        "\u092c\u0928\u094d\u0928\u0942"
    ],
    "name:hun_x_preferred":[
        "Bannu"
    ],
    "name:ind_x_preferred":[
        "Bannu"
    ],
    "name:ita_x_preferred":[
        "Bannu"
    ],
    "name:jpn_x_preferred":[
        "\u30d0\u30f3\u30cc"
    ],
    "name:lit_x_preferred":[
        "Banu"
    ],
    "name:mai_x_preferred":[
        "\u092c\u0928\u094d\u0928\u0941 \u091c\u093f\u0932\u093e"
    ],
    "name:msa_x_preferred":[
        "Bannu"
    ],
    "name:pnb_x_preferred":[
        "\u0628\u0646\u0648\u06ba"
    ],
    "name:por_x_preferred":[
        "Bannu"
    ],
    "name:rus_x_preferred":[
        "\u0411\u0430\u043d\u043d\u0443"
    ],
    "name:spa_x_preferred":[
        "Bannu"
    ],
    "name:swe_x_preferred":[
        "Bannu"
    ],
    "name:szl_x_preferred":[
        "Bannu"
    ],
    "name:ukr_x_preferred":[
        "\u0411\u0430\u043d\u043d\u0443"
    ],
    "name:urd_x_preferred":[
        "\u0628\u0646\u0648\u06ba"
    ],
    "wof:name":"Bannu",
    "wof:placetype":"locality"
},
  "geometry": {"coordinates":[75.28216999999999,32.6927],"type":"Point"}
}