{
  "type": "Feature",
  "properties": {
    "iso:country":"IN",
    "ks:ks_name":"Kosanda Buzurg",
    "ks:ks_pop":308,
    "ks:ks_type":"VILLAGE",
    "name:eng_x_preferred":[
        "Kosanda Buzurg"
    ],
    "wof:name":"Kosanda Buzurg",
    "wof:placetype":"locality",
    "wof:population":308
},
  "geometry": {"coordinates":[84.26836299999999,25.291051],"type":"Point"}
}