{
  "type": "Feature",
  "properties": {
    "iso:country":"IN",
    "ks:ks_name":"Sighardaha",
    "ks:ks_pop":2910,
    "ks:ks_type":"HABITATION",
    "name:eng_x_preferred":[
        "Sighardaha"
    ],
    "wof:name":"Sighardaha",
    "wof:placetype":"locality",
    "wof:population":2910
},
  "geometry": {"coordinates":[87.989,25.848494],"type":"Point"}
}