{
  "type": "Feature",
  "properties": {
    "gn:admin1_code":"25.0",
    "gn:admin2_code":"630.0",
    "gn:asciiname":"Vepparakkavundanhalli",
    "gn:country_code":"IN",
    "gn:dem":444,
    "gn:feature_class":"P",
    "gn:feature_code":"PPL",
    "gn:name":"Vepparakkavundanhalli",
    "gn:population":0,
    "gn:timezone":"Asia/Kolkata",
    "iso:country":"IN",
    "wof:name":"Vepparakkavundanhalli",
    "wof:placetype":"locality"
},
  "geometry": {"coordinates":[78.25248000000001,12.17122],"type":"Point"}
}