{
  "type": "Feature",
  "properties": {
    "iso:country":"IN",
    "ks:ks_name":"Madhopur",
    "ks:ks_pop":175,
    "ks:ks_type":"HABITATION",
    "name:eng_x_preferred":[
        "Madhopur"
    ],
    "wof:name":"Madhopur",
    "wof:placetype":"locality",
    "wof:population":175
},
  "geometry": {"coordinates":[84.925651,25.126989],"type":"Point"}
}