{
  "type": "Feature",
  "properties": {
    "gn:admin1_code":"21",
    "gn:admin2_code":"374.0",
    "gn:asciiname":"Ghumra San",
    "gn:country_code":"IN",
    "gn:dem":266,
    "gn:feature_class":"P",
    "gn:feature_code":"PPL",
    "gn:name":"Ghumra San",
    "gn:population":0,
    "gn:timezone":"Asia/Kolkata",
    "iso:country":"IN",
    "wof:name":"Ghumra San",
    "wof:placetype":"neighbourhood"
},
  "geometry": {"coordinates":[83.79349000000001,21.96065],"type":"Point"}
}