{
  "type": "Feature",
  "properties": {
    "iso:country":"IN",
    "ks:ks_name":"Phingar Tok",
    "ks:ks_type":"VILLAGE",
    "name:eng_x_preferred":[
        "Phingar Tok"
    ],
    "wof:name":"Phingar Tok",
    "wof:placetype":"locality"
},
  "geometry": {"coordinates":[78.83930599999999,29.74756],"type":"Point"}
}