{
  "type": "Feature",
  "properties": {
    "iso:country":"IN",
    "ks:ks_name":"Sadhopur Inglish",
    "ks:ks_pop":0,
    "ks:ks_type":"VILLAGE",
    "name:eng_x_preferred":[
        "Sadhopur Inglish"
    ],
    "wof:name":"Sadhopur Inglish",
    "wof:placetype":"locality",
    "wof:population":0
},
  "geometry": {"coordinates":[86.728652,25.176988],"type":"Point"}
}