{
  "type": "Feature",
  "properties": {
    "iso:country":"IN",
    "ks:ks_name":"Bharri",
    "ks:ks_pop":364,
    "ks:ks_type":"HABITATION",
    "name:eng_x_preferred":[
        "Bharri"
    ],
    "wof:name":"Bharri",
    "wof:placetype":"locality",
    "wof:population":364
},
  "geometry": {"coordinates":[81.76266200000001,23.427147],"type":"Point"}
}