{
  "type": "Feature",
  "properties": {
    "iso:country":"IN",
    "ks:ks_name":"Marathwadi",
    "ks:ks_pop":122,
    "ks:ks_type":"HABITATION",
    "name:eng_x_preferred":[
        "Marathwadi"
    ],
    "wof:name":"Marathwadi",
    "wof:placetype":"locality",
    "wof:population":122
},
  "geometry": {"coordinates":[73.327944,18.064972],"type":"Point"}
}