{
  "type": "Feature",
  "properties": {
    "gn:admin1_code":"23.0",
    "gn:admin2_code":"48.0",
    "gn:asciiname":"Malkana",
    "gn:country_code":"IN",
    "gn:dem":247,
    "gn:feature_class":"P",
    "gn:feature_code":"PPL",
    "gn:name":"Malk\u0101na",
    "gn:population":0,
    "gn:timezone":"Asia/Kolkata",
    "iso:country":"IN",
    "name:urd_x_preferred":[
        "\u0645\u0644\u06a9\u0627\u0646\u06c1"
    ],
    "wof:name":"Malkana",
    "wof:placetype":"locality"
},
  "geometry": {"coordinates":[76.20158000000001,30.1525],"type":"Point"}
}