{
  "type": "Feature",
  "properties": {
    "iso:country":"IN",
    "ks:ks_name":"Panawara",
    "ks:ks_pop":932,
    "ks:ks_type":"VILLAGE",
    "name:eng_x_preferred":[
        "Panawara"
    ],
    "wof:name":"Panawara",
    "wof:placetype":"locality",
    "wof:population":932
},
  "geometry": {"coordinates":[71.781172,26.029433],"type":"Point"}
}