{
  "type": "Feature",
  "properties": {
    "iso:country":"IN",
    "ks:ks_name":"Takilod",
    "ks:ks_pop":278,
    "ks:ks_type":"HABITATION",
    "name:eng_x_preferred":[
        "Takilod"
    ],
    "wof:name":"Takilod",
    "wof:placetype":"locality",
    "wof:population":278
},
  "geometry": {"coordinates":[81.12822799999999,19.11444],"type":"Point"}
}