{
  "type": "Feature",
  "properties": {
    "iso:country":"IN",
    "ks:ks_name":"Ravadapalem",
    "ks:ks_pop":110,
    "ks:ks_type":"HABITATION",
    "name:eng_x_preferred":[
        "Ravadapalem"
    ],
    "wof:name":"Ravadapalem",
    "wof:placetype":"locality",
    "wof:population":110
},
  "geometry": {"coordinates":[83.0154,17.955192],"type":"Point"}
}