{
  "type": "Feature",
  "properties": {
    "gn:admin1_code":"34.0",
    "gn:admin2_code":"231.0",
    "gn:asciiname":"Sirpalpur",
    "gn:country_code":"IN",
    "gn:dem":63,
    "gn:feature_class":"P",
    "gn:feature_code":"PPL",
    "gn:name":"Sirp\u0101lpur",
    "gn:population":0,
    "gn:timezone":"Asia/Kolkata",
    "iso:country":"IN",
    "ks:ks_alt_nam":"Sirp\u0101lpur",
    "ks:ks_name":"Sirpalpur",
    "ks:ks_pop":912,
    "ks:ks_type":"VILLAGE",
    "name:eng_x_preferred":[
        "Sirpalpur"
    ],
    "name:eng_x_variant":[
        "Sirp\u0101lpur"
    ],
    "wof:name":"Sirpalpur",
    "wof:placetype":"locality",
    "wof:population":912
},
  "geometry": {"coordinates":[84.77354,25.611577],"type":"Point"}
}