{
  "type": "Feature",
  "properties": {
    "iso:country":"IN",
    "ks:ks_name":"Mahadevasol",
    "ks:ks_pop":0,
    "ks:ks_type":"VILLAGE",
    "name:eng_x_preferred":[
        "Mahadevasol"
    ],
    "wof:name":"Mahadevasol",
    "wof:placetype":"locality",
    "wof:population":0
},
  "geometry": {"coordinates":[87.31629100000001,24.50775],"type":"Point"}
}