{
  "type": "Feature",
  "properties": {
    "iso:country":"IN",
    "ks:ks_name":"Sankadabagilu",
    "ks:ks_pop":68,
    "ks:ks_type":"HABITATION",
    "name:eng_x_preferred":[
        "Sankadabagilu"
    ],
    "wof:name":"Sankadabagilu",
    "wof:placetype":"locality",
    "wof:population":68
},
  "geometry": {"coordinates":[74.820668,13.460467],"type":"Point"}
}