{
  "type": "Feature",
  "properties": {
    "iso:country":"IN",
    "ks:ks_name":"Pulikona Vanka",
    "ks:ks_pop":94,
    "ks:ks_type":"HABITATION",
    "name:eng_x_preferred":[
        "Pulikona Vanka"
    ],
    "wof:name":"Pulikona Vanka",
    "wof:placetype":"locality",
    "wof:population":94
},
  "geometry": {"coordinates":[78.737864,13.452038],"type":"Point"}
}