{
  "type": "Feature",
  "properties": {
    "iso:country":"IN",
    "ks:ks_name":"Maithana",
    "ks:ks_pop":274,
    "ks:ks_type":"VILLAGE",
    "name:eng_x_preferred":[
        "Maithana"
    ],
    "wof:name":"Maithana",
    "wof:placetype":"locality",
    "wof:population":274
},
  "geometry": {"coordinates":[79.04661900000001,30.108767],"type":"Point"}
}