{
  "type": "Feature",
  "properties": {
    "gn:admin1_code":"36.0",
    "gn:admin2_code":"183.0",
    "gn:asciiname":"Baram",
    "gn:country_code":"IN",
    "gn:dem":103,
    "gn:feature_class":"P",
    "gn:feature_code":"PPL",
    "gn:name":"B\u0101r\u0101m",
    "gn:population":0,
    "gn:timezone":"Asia/Kolkata",
    "iso:country":"IN",
    "name:rus_x_preferred":[
        "\u0411\u0430\u0440\u0430\u043c"
    ],
    "name:ukr_x_preferred":[
        "\u0411\u0430\u0440\u0430\u043c"
    ],
    "wof:name":"Baram",
    "wof:placetype":"locality"
},
  "geometry": {"coordinates":[82.44740999999998,27.0754],"type":"Point"}
}