{
  "type": "Feature",
  "properties": {
    "iso:country":"IN",
    "ks:ks_name":"Gulab Ka Purwa",
    "ks:ks_pop":192,
    "ks:ks_type":"HABITATION",
    "ks:ks_uagg_main":0,
    "name:eng_x_preferred":[
        "Gulab Ka Purwa"
    ],
    "wof:name":"Gulab Ka Purwa",
    "wof:placetype":"neighbourhood",
    "wof:population":192
},
  "geometry": {"coordinates":[80.776188,25.204294],"type":"Point"}
}