{
  "type": "Feature",
  "properties": {
    "iso:country":"IN",
    "ks:ks_name":"Kusumpur",
    "ks:ks_pop":174,
    "ks:ks_type":"HABITATION",
    "name:eng_x_preferred":[
        "Kusumpur"
    ],
    "wof:name":"Kusumpur",
    "wof:placetype":"locality",
    "wof:population":174
},
  "geometry": {"coordinates":[78.720319,19.139126],"type":"Point"}
}