{
  "type": "Feature",
  "properties": {
    "iso:country":"IN",
    "ks:ks_name":"Kuribank",
    "ks:ks_pop":0,
    "ks:ks_type":"VILLAGE",
    "name:eng_x_preferred":[
        "Kuribank"
    ],
    "wof:name":"Kuribank",
    "wof:placetype":"locality",
    "wof:population":0
},
  "geometry": {"coordinates":[86.71257199999999,24.546218],"type":"Point"}
}