{
  "type": "Feature",
  "properties": {
    "iso:country":"IN",
    "ks:ks_name":"Farson",
    "ks:ks_pop":181,
    "ks:ks_type":"HABITATION",
    "name:eng_x_preferred":[
        "Farson"
    ],
    "wof:name":"Farson",
    "wof:placetype":"locality",
    "wof:population":181
},
  "geometry": {"coordinates":[79.316354,30.006629],"type":"Point"}
}