{
  "type": "Feature",
  "properties": {
    "iso:country":"IN",
    "ks:ks_alt_nam":"16.800 RD",
    "ks:ks_name":"16.800 Rd",
    "ks:ks_pop":6,
    "ks:ks_type":"HABITATION",
    "name:eng_x_preferred":[
        "16.800 Rd"
    ],
    "wof:name":"16.800 Rd",
    "wof:placetype":"locality",
    "wof:population":6
},
  "geometry": {"coordinates":[73.905119,29.163833],"type":"Point"}
}