{
  "type": "Feature",
  "properties": {
    "gn:admin1_code":"12.0",
    "gn:admin2_code":"10.0",
    "gn:asciiname":"Tsanthan",
    "gn:country_code":"IN",
    "gn:dem":1793,
    "gn:feature_class":"P",
    "gn:feature_code":"PPL",
    "gn:name":"Ts\u0101nthan",
    "gn:population":0,
    "gn:timezone":"Asia/Kolkata",
    "iso:country":"IN",
    "wof:name":"Tsanthan",
    "wof:placetype":"locality"
},
  "geometry": {"coordinates":[74.75272,34.27618],"type":"Point"}
}