{
  "type": "Feature",
  "properties": {
    "gn:admin1_code":"35",
    "gn:admin2_code":"427.0",
    "gn:asciiname":"Makronia",
    "gn:country_code":"IN",
    "gn:dem":544,
    "gn:feature_class":"P",
    "gn:feature_code":"PPL",
    "gn:name":"Makronia",
    "gn:population":0,
    "gn:timezone":"Asia/Kolkata",
    "iso:country":"IN",
    "ks:ks_alt_nam":"Makronia Buzurg",
    "ks:ks_name":"Makronia",
    "ks:ks_pop":14360,
    "ks:ks_type":"VILLAGE",
    "ks:ks_uagg_main":0,
    "name:ben_x_preferred":[
        "\u09ae\u09be\u0995\u09b0\u09a8\u09bf\u09af\u09bc\u09be"
    ],
    "name:bpy_x_preferred":[
        "\u09ae\u09be\u0995\u09b0\u09a8\u09bf\u09af\u09bc\u09be"
    ],
    "name:eng_x_preferred":[
        "Makronia"
    ],
    "name:eng_x_variant":[
        "Makronia Buzurg"
    ],
    "name:ita_x_preferred":[
        "Makronia"
    ],
    "name:msa_x_preferred":[
        "Makronia"
    ],
    "name:new_x_preferred":[
        "\u092e\u0915\u094d\u0930\u094b\u0928\u093f\u092f\u093e"
    ],
    "name:nld_x_preferred":[
        "Makronia"
    ],
    "name:por_x_preferred":[
        "Makronia"
    ],
    "name:vie_x_preferred":[
        "Makronia"
    ],
    "name:zho_x_preferred":[
        "\u9a6c\u514b\u7f57\u5c3c\u4e9a"
    ],
    "wof:name":"Makronia",
    "wof:placetype":"locality",
    "wof:population":14360
},
  "geometry": {"coordinates":[78.80130800000001,23.852432],"type":"Point"}
}