{
  "type": "Feature",
  "properties": {
    "iso:country":"IN",
    "ks:ks_name":"Gaurapurwar",
    "ks:ks_pop":3422,
    "ks:ks_type":"VILLAGE",
    "ks:ks_uagg_main":0,
    "name:eng_x_preferred":[
        "Gaurapurwar"
    ],
    "wof:name":"Gaurapurwar",
    "wof:placetype":"locality",
    "wof:population":3422
},
  "geometry": {"coordinates":[83.11679599999999,25.449364],"type":"Point"}
}