{
  "type": "Feature",
  "properties": {
    "gn:admin1_code":"39.0",
    "gn:admin2_code":"061",
    "gn:asciiname":"Mathali",
    "gn:country_code":"IN",
    "gn:dem":991,
    "gn:feature_class":"P",
    "gn:feature_code":"PPL",
    "gn:name":"Math\u0101li",
    "gn:population":0,
    "gn:timezone":"Asia/Kolkata",
    "iso:country":"IN",
    "wof:name":"Mathali",
    "wof:placetype":"locality"
},
  "geometry": {"coordinates":[78.72185999999998,29.8454],"type":"Point"}
}