{
  "type": "Feature",
  "properties": {
    "gn:admin1_code":"11",
    "gn:admin2_code":"33.0",
    "gn:asciiname":"Bab Dogri",
    "gn:country_code":"IN",
    "gn:dem":2435,
    "gn:feature_class":"P",
    "gn:feature_code":"PPL",
    "gn:name":"Bab Dogri",
    "gn:population":0,
    "gn:timezone":"Asia/Kolkata",
    "iso:country":"IN",
    "wof:name":"Bab Dogri",
    "wof:placetype":"locality"
},
  "geometry": {"coordinates":[77.55315999999998,30.85027],"type":"Point"}
}