{
  "type": "Feature",
  "properties": {
    "iso:country":"IN",
    "ks:ks_alt_nam":"harilalpurwa",
    "ks:ks_name":"Harilalpurwa",
    "ks:ks_pop":108,
    "ks:ks_type":"HABITATION",
    "name:eng_x_preferred":[
        "Harilalpurwa"
    ],
    "wof:name":"Harilalpurwa",
    "wof:placetype":"locality",
    "wof:population":108
},
  "geometry": {"coordinates":[81.786603,27.358534],"type":"Point"}
}