{
  "type": "Feature",
  "properties": {
    "gn:admin1_code":"39",
    "gn:admin2_code":"58.0",
    "gn:asciiname":"Nalaputan",
    "gn:country_code":"IN",
    "gn:dem":1973,
    "gn:feature_class":"P",
    "gn:feature_code":"PPL",
    "gn:name":"Nalaputan",
    "gn:population":0,
    "gn:timezone":"Asia/Kolkata",
    "iso:country":"IN",
    "wof:name":"Nalaputan",
    "wof:placetype":"locality"
},
  "geometry": {"coordinates":[79.17196,30.53589],"type":"Point"}
}