{
  "type": "Feature",
  "properties": {
    "iso:country":"IN",
    "ks:ks_alt_nam":"Kamna \u016amra",
    "ks:ks_name":"Kamna Umra",
    "ks:ks_type":"VILLAGE",
    "name:eng_x_preferred":[
        "Kamna Umra"
    ],
    "name:eng_x_variant":[
        "Kamna \u016amra"
    ],
    "wof:name":"Kamna Umra",
    "wof:placetype":"locality"
},
  "geometry": {"coordinates":[78.39531100000001,29.089598],"type":"Point"}
}