{
  "type": "Feature",
  "properties": {
    "iso:country":"IN",
    "ks:ks_alt_nam":"Chavan wadi",
    "ks:ks_name":"Chavan Wadi",
    "ks:ks_pop":229,
    "ks:ks_type":"HABITATION",
    "name:eng_x_preferred":[
        "Chavan Wadi"
    ],
    "wof:name":"Chavan Wadi",
    "wof:placetype":"locality",
    "wof:population":229
},
  "geometry": {"coordinates":[74.35831899999999,16.202328],"type":"Point"}
}