{
  "type": "Feature",
  "properties": {
    "iso:country":"IN",
    "ks:ks_name":"Tigra",
    "ks:ks_pop":7,
    "ks:ks_type":"VILLAGE",
    "name:eng_x_preferred":[
        "Tigra"
    ],
    "wof:name":"Tigra",
    "wof:placetype":"locality",
    "wof:population":7
},
  "geometry": {"coordinates":[77.732877,23.540825],"type":"Point"}
}