{
  "type": "Feature",
  "properties": {
    "iso:country":"IN",
    "ks:ks_name":"New Lands Tea Garden",
    "ks:ks_pop":6200,
    "ks:ks_type":"VILLAGE",
    "name:eng_x_preferred":[
        "New Lands Tea Garden"
    ],
    "wof:name":"New Lands Tea Garden",
    "wof:placetype":"locality",
    "wof:population":6200
},
  "geometry": {"coordinates":[89.79620799999999,26.659862],"type":"Point"}
}