{
  "type": "Feature",
  "properties": {
    "gn:admin1_code":"11",
    "gn:admin2_code":"30.0",
    "gn:asciiname":"Tiun",
    "gn:country_code":"IN",
    "gn:dem":1199,
    "gn:feature_class":"P",
    "gn:feature_code":"PPL",
    "gn:name":"Tiun",
    "gn:population":0,
    "gn:timezone":"Asia/Kolkata",
    "iso:country":"IN",
    "wof:name":"Tiun",
    "wof:placetype":"locality"
},
  "geometry": {"coordinates":[76.6884,31.23785],"type":"Point"}
}