{
  "type": "Feature",
  "properties": {
    "iso:country":"IN",
    "ks:ks_name":"Radhaballavpur",
    "ks:ks_pop":303,
    "ks:ks_type":"VILLAGE",
    "ks:ks_uagg_main":0,
    "name:eng_x_preferred":[
        "Radhaballavpur"
    ],
    "wof:name":"Radhaballavpur",
    "wof:placetype":"neighbourhood",
    "wof:population":303
},
  "geometry": {"coordinates":[86.66739699999999,21.307842],"type":"Point"}
}