{
  "type": "Feature",
  "properties": {
    "iso:country":"IN",
    "ks:ks_alt_nam":"BHAT TOLA NORTH",
    "ks:ks_name":"Bhat Tola North",
    "ks:ks_pop":282,
    "ks:ks_type":"HABITATION",
    "ks:ks_uagg_main":0,
    "name:eng_x_preferred":[
        "Bhat Tola North"
    ],
    "wof:name":"Bhat Tola North",
    "wof:placetype":"neighbourhood",
    "wof:population":282
},
  "geometry": {"coordinates":[84.018783,26.480909],"type":"Point"}
}