{
  "type": "Feature",
  "properties": {
    "iso:country":"IN",
    "ks:ks_alt_nam":"Palaya Colony kod",
    "ks:ks_name":"Palaya Colony Kod",
    "ks:ks_pop":200,
    "ks:ks_type":"HABITATION",
    "ks:ks_uagg_main":0,
    "name:eng_x_preferred":[
        "Palaya Colony Kod"
    ],
    "wof:name":"Palaya Colony Kod",
    "wof:placetype":"neighbourhood",
    "wof:population":200
},
  "geometry": {"coordinates":[78.580935,12.666433],"type":"Point"}
}