{
  "type": "Feature",
  "properties": {
    "gn:admin1_code":"11",
    "gn:admin2_code":"23.0",
    "gn:asciiname":"Sidhpura",
    "gn:country_code":"IN",
    "gn:dem":791,
    "gn:feature_class":"P",
    "gn:feature_code":"PPL",
    "gn:name":"Sidhp\u016bra",
    "gn:population":0,
    "gn:timezone":"Asia/Kolkata",
    "iso:country":"IN",
    "wof:name":"Sidhpura",
    "wof:placetype":"locality"
},
  "geometry": {"coordinates":[76.10666999999999,32.58512],"type":"Point"}
}