{
  "type": "Feature",
  "properties": {
    "gn:admin1_code":"11",
    "gn:admin2_code":"23.0",
    "gn:asciiname":"Sidhpura",
    "gn:country_code":"IN",
    "gn:dem":791,
    "gn:feature_class":"P",
    "gn:feature_code":"PPL",
    "gn:name":"Sidhp\u016bra",
    "gn:population":0,
    "gn:timezone":"Asia/Kolkata",
    "iso:country":"IN",
    "name:bpy_x_preferred":[
        "\u09b8\u09bf\u09a7\u09aa\u09c1\u09b0\u09be"
    ],
    "name:ceb_x_preferred":[
        "Sidhpura"
    ],
    "name:ita_x_preferred":[
        "Sidhpura"
    ],
    "name:mlg_x_preferred":[
        "Sidhpura"
    ],
    "name:msa_x_preferred":[
        "Sidhpura"
    ],
    "name:nld_x_preferred":[
        "Sidhpura"
    ],
    "name:pol_x_preferred":[
        "Sidhpura"
    ],
    "name:por_x_preferred":[
        "Sidhpura"
    ],
    "name:swe_x_preferred":[
        "Sidhpura"
    ],
    "name:urd_x_preferred":[
        "\u0633\u062f\u06be\u067e\u0648\u0631\u0627"
    ],
    "name:vie_x_preferred":[
        "Sidhpura"
    ],
    "name:zho_x_preferred":[
        "\u897f\u5fb7\u666e\u62c9"
    ],
    "wof:name":"Sidhpura",
    "wof:placetype":"locality"
},
  "geometry": {"coordinates":[76.10666999999999,32.58512],"type":"Point"}
}