{
  "type": "Feature",
  "properties": {
    "iso:country":"IN",
    "ks:ks_alt_nam":"morewadi",
    "ks:ks_name":"Morewadi",
    "ks:ks_pop":250,
    "ks:ks_type":"HABITATION",
    "name:eng_x_preferred":[
        "Morewadi"
    ],
    "wof:name":"Morewadi",
    "wof:placetype":"locality",
    "wof:population":250
},
  "geometry": {"coordinates":[73.502442,17.357344],"type":"Point"}
}