{
  "type": "Feature",
  "properties": {
    "iso:country":"IN",
    "ks:ks_name":"Hadmatiya",
    "ks:ks_pop":1033,
    "ks:ks_type":"HABITATION",
    "name:eng_x_preferred":[
        "Hadmatiya"
    ],
    "wof:name":"Hadmatiya",
    "wof:placetype":"locality",
    "wof:population":1033
},
  "geometry": {"coordinates":[75.012838,23.085292],"type":"Point"}
}