{
  "type": "Feature",
  "properties": {
    "gn:admin1_code":"36",
    "gn:admin2_code":"133.0",
    "gn:asciiname":"Jawan",
    "gn:country_code":"IN",
    "gn:dem":235,
    "gn:feature_class":"P",
    "gn:feature_code":"PPL",
    "gn:name":"J\u0101wan",
    "gn:population":0,
    "gn:timezone":"Asia/Kolkata",
    "iso:country":"IN",
    "name:ceb_x_preferred":[
        "Jawan"
    ],
    "name:swe_x_preferred":[
        "Jawan"
    ],
    "wof:name":"Jawan",
    "wof:placetype":"locality"
},
  "geometry": {"coordinates":[77.80167,29.2418],"type":"Point"}
}