{
  "type": "Feature",
  "properties": {
    "gn:admin1_code":"10.0",
    "gn:admin2_code":"69.0",
    "gn:asciiname":"Narayanpur",
    "gn:country_code":"IN",
    "gn:dem":339,
    "gn:feature_class":"P",
    "gn:feature_code":"PPL",
    "gn:name":"N\u0101r\u0101yanpur",
    "gn:population":0,
    "gn:timezone":"Asia/Kolkata",
    "iso:country":"IN",
    "name:ara_x_preferred":[
        "\u0646\u0627\u0631\u0627\u064a\u0627\u0646 \u0628\u0648\u0631"
    ],
    "name:ben_bn_x_preferred":[
        "\u09a8\u09be\u09b0\u09be\u09af\u09bc\u09a3\u09aa\u09c1\u09b0"
    ],
    "name:ben_in_x_preferred":[
        "\u09a8\u09be\u09b0\u09be\u09af\u09bc\u09a3\u09aa\u09c1\u09b0"
    ],
    "name:ceb_x_preferred":[
        "Narayanpur"
    ],
    "name:fra_x_preferred":[
        "Narayanpur"
    ],
    "name:guj_x_preferred":[
        "\u0aa8\u0abe\u0ab0\u0abe\u0aaf\u0aa3\u0aaa\u0ac1\u0ab0"
    ],
    "name:hin_x_preferred":[
        "\u0928\u093e\u0930\u093e\u092f\u0923\u092a\u0941\u0930"
    ],
    "name:kan_x_preferred":[
        "\u0ca8\u0cbe\u0cb0\u0cbe\u0caf\u0ca3\u0ccd"
    ],
    "name:mal_x_preferred":[
        "\u0d28\u0d3e\u0d30\u0d3e\u0d2f\u0d7a\u0d2a\u0d42\u0d7c"
    ],
    "name:mar_x_preferred":[
        "\u0928\u093e\u0930\u093e\u092f\u0923\u092a\u0942\u0930"
    ],
    "name:pan_x_preferred":[
        "\u0a28\u0a30\u0a3e\u0a07\u0a23\u0a2a\u0a41\u0a30"
    ],
    "name:pol_x_preferred":[
        "Narayanpur"
    ],
    "name:swe_x_preferred":[
        "Narayanpur"
    ],
    "name:tam_x_preferred":[
        "\u0ba8\u0bbe\u0bb0\u0bbe\u0baf\u0ba3\u0bcd\u0baa\u0bc2\u0bb0\u0bcd"
    ],
    "name:tel_x_preferred":[
        "\u0c28\u0c3e\u0c30\u0c3e\u0c2f\u0c23\u0c4d"
    ],
    "name:tel_x_variant":[
        "\u0c28\u0c3e\u0c30\u0c3e\u0c2f\u0c23\u0c4d\u200c\u0c2a\u0c42\u0c30\u0c4d"
    ],
    "name:urd_x_preferred":[
        "\u0646\u0627\u0631\u0627\u0626\u0646 \u067e\u0648\u0631"
    ],
    "wof:name":"Narayanpur",
    "wof:placetype":"locality"
},
  "geometry": {"coordinates":[77.03744,30.60149],"type":"Point"}
}