{
  "type": "Feature",
  "properties": {
    "gn:admin1_code":"19.0",
    "gn:admin2_code":"581.0",
    "gn:asciiname":"Apsandra",
    "gn:country_code":"IN",
    "gn:dem":877,
    "gn:feature_class":"P",
    "gn:feature_code":"PPL",
    "gn:name":"Apsandra",
    "gn:population":0,
    "gn:timezone":"Asia/Kolkata",
    "iso:country":"IN",
    "ks:ks_name":"Appasandra",
    "ks:ks_pop":495,
    "ks:ks_type":"VILLAGE",
    "ks:ks_uagg_main":0,
    "name:eng_x_preferred":[
        "Appasandra"
    ],
    "wof:name":"Appasandra",
    "wof:placetype":"neighbourhood",
    "wof:population":495
},
  "geometry": {"coordinates":[77.993514,13.12093],"type":"Point"}
}