{
  "type": "Feature",
  "properties": {
    "iso:country":"IN",
    "ks:ks_name":"Tolokabeda",
    "ks:ks_pop":2287,
    "ks:ks_type":"VILLAGE",
    "ks:ks_uagg_main":0,
    "name:eng_x_preferred":[
        "Tolokabeda"
    ],
    "wof:name":"Tolokabeda",
    "wof:placetype":"neighbourhood",
    "wof:population":2287
},
  "geometry": {"coordinates":[85.07074299999999,21.103828],"type":"Point"}
}