{
  "type": "Feature",
  "properties": {
    "iso:country":"IN",
    "ks:ks_name":"Dhanikhali",
    "ks:ks_pop":1325,
    "ks:ks_type":"VILLAGE",
    "name:eng_x_preferred":[
        "Dhanikhali"
    ],
    "wof:name":"Dhanikhali",
    "wof:placetype":"locality",
    "wof:population":1325
},
  "geometry": {"coordinates":[88.908935,22.459073],"type":"Point"}
}