{
  "type": "Feature",
  "properties": {
    "gn:admin1_code":"39",
    "gn:admin2_code":"61.0",
    "gn:asciiname":"Belam",
    "gn:country_code":"IN",
    "gn:dem":1049,
    "gn:feature_class":"P",
    "gn:feature_code":"PPL",
    "gn:name":"Belam",
    "gn:population":0,
    "gn:timezone":"Asia/Kolkata",
    "iso:country":"IN",
    "ks:ks_name":"Balam",
    "ks:ks_pop":63,
    "ks:ks_type":"HABITATION",
    "name:eng_x_preferred":[
        "Balam"
    ],
    "name:eng_x_variant":[
        "Belam"
    ],
    "wof:name":"Balam",
    "wof:placetype":"locality",
    "wof:population":63
},
  "geometry": {"coordinates":[78.996116,29.689415],"type":"Point"}
}