{
  "type": "Feature",
  "properties": {
    "iso:country":"IN",
    "ks:ks_name":"Uttar Para",
    "ks:ks_pop":595,
    "ks:ks_type":"HABITATION",
    "name:eng_x_preferred":[
        "Uttar Para"
    ],
    "wof:name":"Uttar Para",
    "wof:placetype":"locality",
    "wof:population":595
},
  "geometry": {"coordinates":[89.533322,26.336173],"type":"Point"}
}