{
  "type": "Feature",
  "properties": {
    "iso:country":"IN",
    "ks:ks_name":"Melinamane",
    "ks:ks_pop":83,
    "ks:ks_type":"HABITATION",
    "name:eng_x_preferred":[
        "Melinamane"
    ],
    "wof:name":"Melinamane",
    "wof:placetype":"locality",
    "wof:population":83
},
  "geometry": {"coordinates":[74.65524499999999,14.341349],"type":"Point"}
}