{
  "type": "Feature",
  "properties": {
    "gn:admin1_code":"24.0",
    "gn:admin2_code":"103",
    "gn:asciiname":"Gadhara ka Bas",
    "gn:country_code":"IN",
    "gn:dem":317,
    "gn:feature_class":"P",
    "gn:feature_code":"PPL",
    "gn:name":"Gadh\u0101ra ka B\u0101s",
    "gn:population":0,
    "gn:timezone":"Asia/Kolkata",
    "iso:country":"IN",
    "name:und_x_variant":[
        "Godh\u0101ra ki B\u0101s",
        "B\u0101s",
        "Gadh\u0101ra ka B\u0101s"
    ],
    "wof:name":"Gadhara ka Bas",
    "wof:placetype":"locality"
},
  "geometry": {"coordinates":[75.62860999999999,28.2454],"type":"Point"}
}