{
  "type": "Feature",
  "properties": {
    "iso:country":"IN",
    "ks:ks_name":"Dhapada",
    "ks:ks_pop":2651,
    "ks:ks_type":"VILLAGE",
    "name:eng_x_preferred":[
        "Dhapada"
    ],
    "wof:name":"Dhapada",
    "wof:placetype":"locality",
    "wof:population":2651
},
  "geometry": {"coordinates":[86.425658,21.396962],"type":"Point"}
}