{
  "type": "Feature",
  "properties": {
    "iso:country":"IN",
    "ks:ks_name":"Hadmangarh",
    "ks:ks_pop":419,
    "ks:ks_type":"HABITATION",
    "name:eng_x_preferred":[
        "Hadmangarh"
    ],
    "wof:name":"Hadmangarh",
    "wof:placetype":"locality",
    "wof:population":419
},
  "geometry": {"coordinates":[72.65222799999999,26.293014],"type":"Point"}
}