{
  "type": "Feature",
  "properties": {
    "iso:country":"IN",
    "ks:ks_alt_nam":"madhalamala",
    "ks:ks_name":"Madhalamala",
    "ks:ks_pop":85,
    "ks:ks_type":"HABITATION",
    "ks:ks_uagg_main":0,
    "name:eng_x_preferred":[
        "Madhalamala"
    ],
    "wof:name":"Madhalamala",
    "wof:placetype":"neighbourhood",
    "wof:population":85
},
  "geometry": {"coordinates":[74.515,18.1006],"type":"Point"}
}