{
  "type": "Feature",
  "properties": {
    "iso:country":"IN",
    "ks:ks_alt_nam":"R\u0101wli Mahd\u016bd",
    "ks:ks_alt_nam_2":"Rawli Mahdud",
    "ks:ks_name":"Rawali Mahdood",
    "ks:ks_pop":7256,
    "ks:ks_type":"VILLAGE",
    "ks:ks_uagg_main":0,
    "name:eng_x_preferred":[
        "Rawali Mahdood"
    ],
    "name:eng_x_variant":[
        "R\u0101wli Mahd\u016bd",
        "Rawli Mahdud"
    ],
    "wof:name":"Rawali Mahdood",
    "wof:placetype":"locality",
    "wof:population":7256
},
  "geometry": {"coordinates":[78.06447900000001,29.943324],"type":"Point"}
}