{
  "type": "Feature",
  "properties": {
    "iso:country":"IN",
    "ks:ks_name":"Sangudumaha",
    "ks:ks_pop":550,
    "ks:ks_type":"VILLAGE",
    "name:eng_x_preferred":[
        "Sangudumaha"
    ],
    "wof:name":"Sangudumaha",
    "wof:placetype":"locality",
    "wof:population":550
},
  "geometry": {"coordinates":[84.10480099999999,19.88429],"type":"Point"}
}