{
  "type": "Feature",
  "properties": {
    "iso:country":"IN",
    "ks:ks_name":"Pagura Bahar",
    "ks:ks_pop":159,
    "ks:ks_type":"HABITATION",
    "name:eng_x_preferred":[
        "Pagura Bahar"
    ],
    "wof:name":"Pagura Bahar",
    "wof:placetype":"locality",
    "wof:population":159
},
  "geometry": {"coordinates":[84.13386300000001,22.696112],"type":"Point"}
}