{
  "type": "Feature",
  "properties": {
    "iso:country":"IN",
    "ks:ks_name":"Kayadangi",
    "ks:ks_pop":1573,
    "ks:ks_type":"VILLAGE",
    "name:eng_x_preferred":[
        "Kayadangi"
    ],
    "wof:name":"Kayadangi",
    "wof:placetype":"locality",
    "wof:population":1573
},
  "geometry": {"coordinates":[87.79700200000001,22.439829],"type":"Point"}
}