{
  "type": "Feature",
  "properties": {
    "iso:country":"IN",
    "ks:ks_name":"Majhiguda",
    "ks:ks_pop":39,
    "ks:ks_type":"VILLAGE",
    "name:eng_x_preferred":[
        "Majhiguda"
    ],
    "wof:name":"Majhiguda",
    "wof:placetype":"locality",
    "wof:population":39
},
  "geometry": {"coordinates":[83.88130200000001,19.701139],"type":"Point"}
}