{
  "type": "Feature",
  "properties": {
    "iso:country":"IN",
    "ks:ks_name":"Dakhin Labdanguri Gaon",
    "ks:ks_pop":595,
    "ks:ks_type":"HABITATION",
    "name:eng_x_preferred":[
        "Dakhin Labdanguri Gaon"
    ],
    "wof:name":"Dakhin Labdanguri Gaon",
    "wof:placetype":"locality",
    "wof:population":595
},
  "geometry": {"coordinates":[90.95098900000001,26.594518],"type":"Point"}
}