{
  "type": "Feature",
  "properties": {
    "iso:country":"IN",
    "ks:ks_alt_nam":"Lapr\u0101",
    "ks:ks_name":"Lapra",
    "ks:ks_pop":1045,
    "ks:ks_type":"VILLAGE",
    "ks:ks_uagg_main":0,
    "name:eng_x_preferred":[
        "Lapra"
    ],
    "name:eng_x_variant":[
        "Lapr\u0101"
    ],
    "wof:name":"Lapra",
    "wof:placetype":"neighbourhood",
    "wof:population":1045
},
  "geometry": {"coordinates":[84.933116,23.65277],"type":"Point"}
}