{
  "type": "Feature",
  "properties": {
    "iso:country":"IN",
    "ks:ks_name":"Irlaindlu",
    "ks:ks_pop":134,
    "ks:ks_type":"HABITATION",
    "name:eng_x_preferred":[
        "Irlaindlu"
    ],
    "wof:name":"Irlaindlu",
    "wof:placetype":"locality",
    "wof:population":134
},
  "geometry": {"coordinates":[79.592196,13.437428],"type":"Point"}
}