{
  "type": "Feature",
  "properties": {
    "iso:country":"IN",
    "ks:ks_name":"Narayanpur",
    "ks:ks_pop":917,
    "ks:ks_type":"VILLAGE",
    "ks:ks_uagg_main":0,
    "name:eng_x_preferred":[
        "Narayanpur"
    ],
    "wof:name":"Narayanpur",
    "wof:placetype":"neighbourhood",
    "wof:population":917
},
  "geometry": {"coordinates":[87.28619500000001,23.740064],"type":"Point"}
}