{
  "type": "Feature",
  "properties": {
    "iso:country":"IN",
    "ks:ks_name":"Shayampatti",
    "ks:ks_pop":725,
    "ks:ks_type":"HABITATION",
    "name:eng_x_preferred":[
        "Shayampatti"
    ],
    "wof:name":"Shayampatti",
    "wof:placetype":"locality",
    "wof:population":725
},
  "geometry": {"coordinates":[86.160579,26.45889],"type":"Point"}
}