{
  "type": "Feature",
  "properties": {
    "iso:country":"IN",
    "ks:ks_alt_nam":"KAILAS CHAIRMAN WASTI",
    "ks:ks_name":"Kailas Chairman Wasti",
    "ks:ks_pop":130,
    "ks:ks_type":"HABITATION",
    "name:eng_x_preferred":[
        "Kailas Chairman Wasti"
    ],
    "wof:name":"Kailas Chairman Wasti",
    "wof:placetype":"locality",
    "wof:population":130
},
  "geometry": {"coordinates":[74.85901,17.457758],"type":"Point"}
}