{
  "type": "Feature",
  "properties": {
    "iso:country":"IN",
    "ks:ks_name":"Bhon Sagar",
    "ks:ks_pop":361,
    "ks:ks_type":"HABITATION",
    "name:eng_x_preferred":[
        "Bhon Sagar"
    ],
    "wof:name":"Bhon Sagar",
    "wof:placetype":"locality",
    "wof:population":361
},
  "geometry": {"coordinates":[72.285533,26.289544],"type":"Point"}
}