{
  "type": "Feature",
  "properties": {
    "gn:admin1_code":"37",
    "gn:admin2_code":"406.0",
    "gn:asciiname":"Madai",
    "gn:country_code":"IN",
    "gn:dem":283,
    "gn:feature_class":"P",
    "gn:feature_code":"PPL",
    "gn:name":"Madai",
    "gn:population":0,
    "gn:timezone":"Asia/Kolkata",
    "iso:country":"IN",
    "name:bod_x_preferred":[
        "\u0f58\u0f0b\u0f51\u0f0b\u0f68\u0f72\u0f0d"
    ],
    "name:deu_x_preferred":[
        "Madai"
    ],
    "name:ell_x_preferred":[
        "\u039c\u03b1\u03b4\u03b1\u03af"
    ],
    "name:fas_x_preferred":[
        "\u0645\u062f\u0627\u06cc"
    ],
    "name:fin_x_preferred":[
        "Madai"
    ],
    "name:fra_x_preferred":[
        "Mada\u00ef"
    ],
    "name:ind_x_preferred":[
        "Madai"
    ],
    "name:ita_x_preferred":[
        "Madai"
    ],
    "name:kor_x_preferred":[
        "\ub9c8\ub300"
    ],
    "name:nld_x_preferred":[
        "Madai"
    ],
    "name:pol_x_preferred":[
        "Madaj"
    ],
    "name:por_x_preferred":[
        "Madai"
    ],
    "name:ron_x_preferred":[
        "Madai"
    ],
    "name:rus_x_preferred":[
        "\u041c\u0430\u0434\u0430\u0439"
    ],
    "name:ukr_x_preferred":[
        "\u041c\u0430\u0434\u0430\u0439"
    ],
    "wof:name":"Madai",
    "wof:placetype":"locality"
},
  "geometry": {"coordinates":[82.40406,22.16151],"type":"Point"}
}