{
  "type": "Feature",
  "properties": {
    "iso:country":"IN",
    "ks:ks_name":"Karady",
    "ks:ks_pop":144,
    "ks:ks_type":"HABITATION",
    "name:eng_x_preferred":[
        "Karady"
    ],
    "wof:name":"Karady",
    "wof:placetype":"locality",
    "wof:population":144
},
  "geometry": {"coordinates":[74.958144,13.47948],"type":"Point"}
}