{
  "type": "Feature",
  "properties": {
    "gn:admin1_code":"19.0",
    "gn:admin2_code":"563.0",
    "gn:asciiname":"Mugve",
    "gn:country_code":"IN",
    "gn:dem":17,
    "gn:feature_class":"P",
    "gn:feature_code":"PPL",
    "gn:name":"Mugve",
    "gn:population":0,
    "gn:timezone":"Asia/Kolkata",
    "iso:country":"IN",
    "wof:name":"Mugve",
    "wof:placetype":"locality"
},
  "geometry": {"coordinates":[74.47696999999999,14.28876],"type":"Point"}
}