{
  "type": "Feature",
  "properties": {
    "gn:admin1_code":"19.0",
    "gn:admin2_code":"563.0",
    "gn:asciiname":"Mugve",
    "gn:country_code":"IN",
    "gn:dem":17,
    "gn:feature_class":"P",
    "gn:feature_code":"PPL",
    "gn:name":"Mugve",
    "gn:population":0,
    "gn:timezone":"Asia/Kolkata",
    "iso:country":"IN",
    "ks:ks_name":"Mugva",
    "ks:ks_pop":59,
    "ks:ks_type":"HABITATION",
    "name:eng_x_preferred":[
        "Mugva"
    ],
    "name:eng_x_variant":[
        "Mugve"
    ],
    "wof:name":"Mugva",
    "wof:placetype":"locality",
    "wof:population":59
},
  "geometry": {"coordinates":[74.481871,14.294054],"type":"Point"}
}