{
  "type": "Feature",
  "properties": {
    "iso:country":"IN",
    "ks:ks_name":"Kaligadi",
    "ks:ks_pop":61,
    "ks:ks_type":"VILLAGE",
    "ks:ks_uagg_main":0,
    "name:eng_x_preferred":[
        "Kaligadi"
    ],
    "wof:name":"Kaligadi",
    "wof:placetype":"neighbourhood",
    "wof:population":61
},
  "geometry": {"coordinates":[86.777086,21.041703],"type":"Point"}
}