{
  "type": "Feature",
  "properties": {
    "iso:country":"IN",
    "ks:ks_name":"Uthpathanahalli",
    "ks:ks_pop":267,
    "ks:ks_type":"HABITATION",
    "name:eng_x_preferred":[
        "Uthpathanahalli"
    ],
    "wof:name":"Uthpathanahalli",
    "wof:placetype":"locality",
    "wof:population":267
},
  "geometry": {"coordinates":[75.85510600000001,13.153236],"type":"Point"}
}