{
  "type": "Feature",
  "properties": {
    "gn:admin1_code":"23.0",
    "gn:admin2_code":"048",
    "gn:asciiname":"Malakpur",
    "gn:country_code":"IN",
    "gn:dem":255,
    "gn:feature_class":"P",
    "gn:feature_code":"PPL",
    "gn:name":"Malakpur",
    "gn:population":0,
    "gn:timezone":"Asia/Kolkata",
    "iso:country":"IN",
    "ks:ks_name":"Malakpur",
    "ks:ks_pop":555,
    "ks:ks_type":"VILLAGE",
    "ks:ks_uagg_main":0,
    "name:eng_x_preferred":[
        "Malakpur"
    ],
    "name:pan_x_preferred":[
        "\u0a2e\u0a3e\u0a32\u0a15\u0a2a\u0a41\u0a30"
    ],
    "name:und_x_variant":[
        "Kamboh\u0101n",
        "Malakpur",
        "Kambah\u0101n"
    ],
    "wof:name":"Malakpur",
    "wof:placetype":"neighbourhood",
    "wof:population":555
},
  "geometry": {"coordinates":[76.542191,30.224692],"type":"Point"}
}