{
  "type": "Feature",
  "properties": {
    "gn:admin1_code":"2",
    "gn:admin2_code":"544.0",
    "gn:asciiname":"Sirumetta",
    "gn:country_code":"IN",
    "gn:dem":957,
    "gn:feature_class":"P",
    "gn:feature_code":"PPL",
    "gn:name":"Sirumetta",
    "gn:population":0,
    "gn:timezone":"Asia/Kolkata",
    "iso:country":"IN",
    "wof:name":"Sirumetta",
    "wof:placetype":"locality"
},
  "geometry": {"coordinates":[82.77223000000002,18.03641],"type":"Point"}
}