{
  "type": "Feature",
  "properties": {
    "iso:country":"IN",
    "ks:ks_name":"Ladpura",
    "ks:ks_pop":109,
    "ks:ks_type":"VILLAGE",
    "name:eng_x_preferred":[
        "Ladpura"
    ],
    "wof:name":"Ladpura",
    "wof:placetype":"locality",
    "wof:population":109
},
  "geometry": {"coordinates":[76.71171,25.579623],"type":"Point"}
}