{
  "type": "Feature",
  "properties": {
    "gn:admin1_code":"28.0",
    "gn:admin2_code":"334.0",
    "gn:asciiname":"Seura",
    "gn:country_code":"IN",
    "gn:dem":39,
    "gn:feature_class":"P",
    "gn:feature_code":"PPL",
    "gn:name":"Seura",
    "gn:population":0,
    "gn:timezone":"Asia/Kolkata",
    "iso:country":"IN",
    "name:fin_x_preferred":[
        "Seura"
    ],
    "name:swe_x_preferred":[
        "Seura"
    ],
    "wof:name":"Seura",
    "wof:placetype":"locality"
},
  "geometry": {"coordinates":[87.86176,24.26282],"type":"Point"}
}