{
  "type": "Feature",
  "properties": {
    "iso:country":"IN",
    "ks:ks_name":"Neelakantapura",
    "ks:ks_type":"VILLAGE",
    "name:eng_x_preferred":[
        "Neelakantapura"
    ],
    "wof:name":"Neelakantapura",
    "wof:placetype":"locality"
},
  "geometry": {"coordinates":[78.27582200000001,13.417915],"type":"Point"}
}