{
  "type": "Feature",
  "properties": {
    "iso:country":"IN",
    "ks:ks_name":"Bhingaldaha",
    "ks:ks_pop":509,
    "ks:ks_type":"VILLAGE",
    "name:eng_x_preferred":[
        "Bhingaldaha"
    ],
    "wof:name":"Bhingaldaha",
    "wof:placetype":"locality",
    "wof:population":509
},
  "geometry": {"coordinates":[88.45536300000001,25.487635],"type":"Point"}
}