{
  "type": "Feature",
  "properties": {
    "iso:country":"IN",
    "ks:ks_alt_nam":"BINDI PARA",
    "ks:ks_name":"Bindi Para",
    "ks:ks_pop":77,
    "ks:ks_type":"HABITATION",
    "name:eng_x_preferred":[
        "Bindi Para"
    ],
    "wof:name":"Bindi Para",
    "wof:placetype":"locality",
    "wof:population":77
},
  "geometry": {"coordinates":[89.628575,26.468003],"type":"Point"}
}