{
  "type": "Feature",
  "properties": {
    "iso:country":"IN",
    "ks:ks_alt_nam":"RADHIA PARA",
    "ks:ks_name":"Radhia Para",
    "ks:ks_pop":220,
    "ks:ks_type":"HABITATION",
    "ks:ks_uagg_main":0,
    "name:eng_x_preferred":[
        "Radhia Para"
    ],
    "wof:name":"Radhia Para",
    "wof:placetype":"neighbourhood",
    "wof:population":220
},
  "geometry": {"coordinates":[91.41001900000001,23.916239],"type":"Point"}
}