{
  "type": "Feature",
  "properties": {
    "iso:country":"IN",
    "ks:ks_name":"Mendora",
    "ks:ks_pop":707,
    "ks:ks_type":"VILLAGE",
    "name:eng_x_preferred":[
        "Mendora"
    ],
    "wof:name":"Mendora",
    "wof:placetype":"locality",
    "wof:population":707
},
  "geometry": {"coordinates":[77.346627,23.182117],"type":"Point"}
}