{
  "type": "Feature",
  "properties": {
    "iso:country":"IN",
    "ks:ks_name":"Taya",
    "ks:ks_pop":377,
    "ks:ks_type":"VILLAGE",
    "name:eng_x_preferred":[
        "Taya"
    ],
    "wof:name":"Taya",
    "wof:placetype":"locality",
    "wof:population":377
},
  "geometry": {"coordinates":[79.24259499999999,29.644667],"type":"Point"}
}