{
  "type": "Feature",
  "properties": {
    "iso:country":"IN",
    "ks:ks_name":"Soulmari Pt.II",
    "ks:ks_pop":2602,
    "ks:ks_type":"VILLAGE",
    "name:eng_x_preferred":[
        "Soulmari Pt.II"
    ],
    "wof:name":"Soulmari Pt.II",
    "wof:placetype":"locality",
    "wof:population":2602
},
  "geometry": {"coordinates":[89.852615,26.051313],"type":"Point"}
}