{
  "type": "Feature",
  "properties": {
    "gn:admin1_code":"17.0",
    "gn:admin2_code":"273.0",
    "gn:asciiname":"Long",
    "gn:country_code":"IN",
    "gn:dem":920,
    "gn:feature_class":"P",
    "gn:feature_code":"PPL",
    "gn:name":"Long",
    "gn:population":0,
    "gn:timezone":"Asia/Kolkata",
    "iso:country":"IN",
    "name:ara_x_preferred":[
        "\u0637\u0648\u064a\u0644"
    ],
    "name:bul_x_preferred":[
        "\u041b\u043e\u043d\u0433"
    ],
    "name:ceb_x_preferred":[
        "Long"
    ],
    "name:ces_x_preferred":[
        "Long"
    ],
    "name:deu_x_preferred":[
        "Long"
    ],
    "name:fas_x_preferred":[
        "\u0628\u0644\u0646\u062f"
    ],
    "name:fin_x_preferred":[
        "Long"
    ],
    "name:fra_x_preferred":[
        "Long"
    ],
    "name:heb_x_preferred":[
        "\u05dc\u05d5\u05e0\u05d2"
    ],
    "name:ind_x_preferred":[
        "Long"
    ],
    "name:ita_x_preferred":[
        "Long"
    ],
    "name:jpn_x_preferred":[
        "\u30ed\u30f3\u30b0"
    ],
    "name:nld_x_preferred":[
        "Long"
    ],
    "name:pol_x_preferred":[
        "Long"
    ],
    "name:por_x_preferred":[
        "Long"
    ],
    "name:ron_x_preferred":[
        "Long"
    ],
    "name:rus_x_preferred":[
        "Long"
    ],
    "name:srp_x_preferred":[
        "\u041b\u043e\u043d\u0433"
    ],
    "name:swe_x_preferred":[
        "Long"
    ],
    "name:ukr_x_preferred":[
        "\u041b\u043e\u043d\u0433"
    ],
    "name:vie_x_preferred":[
        "Long"
    ],
    "wof:name":"Long",
    "wof:placetype":"locality"
},
  "geometry": {"coordinates":[93.69371,25.31188],"type":"Point"}
}