{
  "type": "Feature",
  "properties": {
    "iso:country":"IN",
    "ks:ks_name":"Juni Phoujdarwadi",
    "ks:ks_pop":104,
    "ks:ks_type":"HABITATION",
    "name:eng_x_preferred":[
        "Juni Phoujdarwadi"
    ],
    "wof:name":"Juni Phoujdarwadi",
    "wof:placetype":"locality",
    "wof:population":104
},
  "geometry": {"coordinates":[73.68418699999999,16.300164],"type":"Point"}
}