{
  "type": "Feature",
  "properties": {
    "iso:country":"IN",
    "ks:ks_name":"Chakeri Shahgarh",
    "ks:ks_pop":549,
    "ks:ks_type":"VILLAGE",
    "name:eng_x_preferred":[
        "Chakeri Shahgarh"
    ],
    "wof:name":"Chakeri Shahgarh",
    "wof:placetype":"locality",
    "wof:population":549
},
  "geometry": {"coordinates":[79.081001,24.066248],"type":"Point"}
}