{
  "type": "Feature",
  "properties": {
    "iso:country":"IN",
    "ks:ks_name":"Guralur",
    "ks:ks_pop":82,
    "ks:ks_type":"VILLAGE",
    "name:eng_x_preferred":[
        "Guralur"
    ],
    "wof:name":"Guralur",
    "wof:placetype":"locality",
    "wof:population":82
},
  "geometry": {"coordinates":[81.871529,17.98267],"type":"Point"}
}