{
  "type": "Feature",
  "properties": {
    "iso:country":"IN",
    "ks:ks_name":"Nath Basti",
    "ks:ks_pop":226,
    "ks:ks_type":"HABITATION",
    "name:eng_x_preferred":[
        "Nath Basti"
    ],
    "wof:name":"Nath Basti",
    "wof:placetype":"locality",
    "wof:population":226
},
  "geometry": {"coordinates":[91.96099599999999,26.235426],"type":"Point"}
}