{
  "type": "Feature",
  "properties": {
    "gn:admin1_code":"10.0",
    "gn:admin2_code":"082",
    "gn:asciiname":"Bhagotipur",
    "gn:country_code":"IN",
    "gn:dem":224,
    "gn:feature_class":"P",
    "gn:feature_code":"PPL",
    "gn:name":"Bhagot\u012bpur",
    "gn:population":0,
    "gn:timezone":"Asia/Kolkata",
    "iso:country":"IN",
    "wof:name":"Bhagotipur",
    "wof:placetype":"locality"
},
  "geometry": {"coordinates":[76.51608,28.98427],"type":"Point"}
}