{
  "type": "Feature",
  "properties": {
    "gn:admin1_code":"2.0",
    "gn:admin2_code":"554.0",
    "gn:asciiname":"Bommandodla",
    "gn:country_code":"IN",
    "gn:dem":319,
    "gn:feature_class":"P",
    "gn:feature_code":"PPL",
    "gn:name":"Bommandodla",
    "gn:population":0,
    "gn:timezone":"Asia/Kolkata",
    "iso:country":"IN",
    "wof:name":"Bommandodla",
    "wof:placetype":"neighbourhood"
},
  "geometry": {"coordinates":[79.36554,13.45594],"type":"Point"}
}