{
  "type": "Feature",
  "properties": {
    "iso:country":"IN",
    "ks:ks_name":"Parasinga",
    "ks:ks_pop":703,
    "ks:ks_type":"HABITATION",
    "name:eng_x_preferred":[
        "Parasinga"
    ],
    "wof:name":"Parasinga",
    "wof:placetype":"locality",
    "wof:population":703
},
  "geometry": {"coordinates":[86.531702,21.078329],"type":"Point"}
}