{
  "type": "Feature",
  "properties": {
    "gn:admin1_code":"36",
    "gn:admin2_code":"184.0",
    "gn:asciiname":"Mahua",
    "gn:country_code":"IN",
    "gn:dem":86,
    "gn:feature_class":"P",
    "gn:feature_code":"PPL",
    "gn:name":"Mahua",
    "gn:population":0,
    "gn:timezone":"Asia/Kolkata",
    "iso:country":"IN",
    "name:bih_x_preferred":[
        "\u092e\u0939\u0941\u0906"
    ],
    "name:ceb_x_preferred":[
        "Mahua"
    ],
    "name:swe_x_preferred":[
        "Mahua"
    ],
    "wof:name":"Mahua",
    "wof:placetype":"locality"
},
  "geometry": {"coordinates":[83.11355,27.20471],"type":"Point"}
}