{
  "type": "Feature",
  "properties": {
    "iso:country":"IN",
    "ks:ks_name":"Sawpur",
    "ks:ks_pop":3020,
    "ks:ks_type":"VILLAGE",
    "ks:ks_uagg_main":0,
    "name:eng_x_preferred":[
        "Sawpur"
    ],
    "wof:name":"Sawpur",
    "wof:placetype":"neighbourhood",
    "wof:population":3020
},
  "geometry": {"coordinates":[90.85890000000001,26.31823],"type":"Point"}
}