{
  "type": "Feature",
  "properties": {
    "gn:admin1_code":"02",
    "gn:admin2_code":"551.0",
    "gn:asciiname":"Tanguturu",
    "gn:country_code":"IN",
    "gn:dem":122,
    "gn:feature_class":"P",
    "gn:feature_code":"PPL",
    "gn:name":"Tangut\u016bru",
    "gn:population":0,
    "gn:timezone":"Asia/Kolkata",
    "iso:country":"IN",
    "name:und_x_variant":[
        "Tangut\u016bru",
        "Tangat\u016br"
    ],
    "wof:name":"Tanguturu",
    "wof:placetype":"locality"
},
  "geometry": {"coordinates":[79.22216,14.29537],"type":"Point"}
}