{
  "type": "Feature",
  "properties": {
    "iso:country":"IN",
    "ks:ks_alt_nam":"karki",
    "ks:ks_name":"Karki",
    "ks:ks_pop":52,
    "ks:ks_type":"HABITATION",
    "name:eng_x_preferred":[
        "Karki"
    ],
    "wof:name":"Karki",
    "wof:placetype":"locality",
    "wof:population":52
},
  "geometry": {"coordinates":[75.25625700000001,13.725006],"type":"Point"}
}