{
  "type": "Feature",
  "properties": {
    "gn:admin1_code":"34.0",
    "gn:admin2_code":"217.0",
    "gn:asciiname":"Mahra Deur",
    "gn:country_code":"IN",
    "gn:dem":78,
    "gn:feature_class":"P",
    "gn:feature_code":"PPL",
    "gn:name":"Mahra Deur",
    "gn:population":0,
    "gn:timezone":"Asia/Kolkata",
    "iso:country":"IN",
    "ks:ks_name":"Mahra Deur",
    "ks:ks_pop":1977,
    "ks:ks_type":"VILLAGE",
    "name:eng_x_preferred":[
        "Mahra Deur"
    ],
    "wof:name":"Mahra Deur",
    "wof:placetype":"locality",
    "wof:population":1977
},
  "geometry": {"coordinates":[84.117779,26.489976],"type":"Point"}
}