{
  "type": "Feature",
  "properties": {
    "iso:country":"IN",
    "ks:ks_name":"Thimiri",
    "ks:ks_pop":1445,
    "ks:ks_type":"VILLAGE",
    "ks:ks_uagg_main":0,
    "name:eng_x_preferred":[
        "Thimiri"
    ],
    "wof:name":"Thimiri",
    "wof:placetype":"locality",
    "wof:population":1445
},
  "geometry": {"coordinates":[75.175112,12.218669],"type":"Point"}
}