{
  "type": "Feature",
  "properties": {
    "gn:admin1_code":"10.0",
    "gn:admin2_code":"082",
    "gn:asciiname":"Nasharpur",
    "gn:country_code":"IN",
    "gn:dem":224,
    "gn:feature_class":"P",
    "gn:feature_code":"PPL",
    "gn:name":"N\u0101sharpur",
    "gn:population":0,
    "gn:timezone":"Asia/Kolkata",
    "iso:country":"IN",
    "ks:ks_name":"Nasirpur",
    "ks:ks_pop":464,
    "ks:ks_type":"VILLAGE",
    "name:eng_x_preferred":[
        "Nasirpur"
    ],
    "name:eng_x_variant":[
        "Nasharpur"
    ],
    "wof:name":"Nasirpur",
    "wof:placetype":"locality",
    "wof:population":464
},
  "geometry": {"coordinates":[76.57983400000001,28.945997],"type":"Point"}
}