{
  "type": "Feature",
  "properties": {
    "iso:country":"IN",
    "ks:ks_name":"Patti",
    "ks:ks_pop":289,
    "ks:ks_type":"VILLAGE",
    "name:eng_x_preferred":[
        "Patti"
    ],
    "wof:name":"Patti",
    "wof:placetype":"locality",
    "wof:population":289
},
  "geometry": {"coordinates":[83.601056,25.20243],"type":"Point"}
}