{
  "type": "Feature",
  "properties": {
    "gn:admin1_code":"36",
    "gn:admin2_code":"179.0",
    "gn:asciiname":"Kazi Patti",
    "gn:country_code":"IN",
    "gn:dem":113,
    "gn:feature_class":"P",
    "gn:feature_code":"PPL",
    "gn:name":"K\u0101zi Patti",
    "gn:population":0,
    "gn:timezone":"Asia/Kolkata",
    "iso:country":"IN",
    "ks:ks_name":"Kaji Patti",
    "ks:ks_pop":547,
    "ks:ks_type":"VILLAGE",
    "ks:ks_uagg_main":0,
    "name:eng_x_preferred":[
        "Kaji Patti"
    ],
    "wof:name":"Kaji Patti",
    "wof:placetype":"neighbourhood",
    "wof:population":547
},
  "geometry": {"coordinates":[81.647081,26.220726],"type":"Point"}
}