{
  "type": "Feature",
  "properties": {
    "iso:country":"IN",
    "ks:ks_name":"Dongaripada",
    "ks:ks_pop":33,
    "ks:ks_type":"HABITATION",
    "name:eng_x_preferred":[
        "Dongaripada"
    ],
    "wof:name":"Dongaripada",
    "wof:placetype":"locality",
    "wof:population":33
},
  "geometry": {"coordinates":[72.840039,19.766721],"type":"Point"}
}