{
  "type": "Feature",
  "properties": {
    "iso:country":"IN",
    "ks:ks_name":"Adamtilla",
    "ks:ks_pop":1412,
    "ks:ks_type":"VILLAGE",
    "ks:ks_uagg_main":0,
    "name:eng_x_preferred":[
        "Adamtilla"
    ],
    "wof:name":"Adamtilla",
    "wof:placetype":"neighbourhood",
    "wof:population":1412
},
  "geometry": {"coordinates":[92.286101,24.602113],"type":"Point"}
}