{
  "type": "Feature",
  "properties": {
    "iso:country":"IN",
    "ks:ks_name":"Siarbeda",
    "ks:ks_pop":132,
    "ks:ks_type":"HABITATION",
    "name:eng_x_preferred":[
        "Siarbeda"
    ],
    "wof:name":"Siarbeda",
    "wof:placetype":"locality",
    "wof:population":132
},
  "geometry": {"coordinates":[86.982589,23.208155],"type":"Point"}
}