{
  "type": "Feature",
  "properties": {
    "iso:country":"IN",
    "ks:ks_name":"Kathud",
    "ks:ks_pop":806,
    "ks:ks_type":"VILLAGE",
    "name:eng_x_preferred":[
        "Kathud"
    ],
    "wof:name":"Kathud",
    "wof:placetype":"locality",
    "wof:population":806
},
  "geometry": {"coordinates":[79.06590199999999,30.109234],"type":"Point"}
}