{
  "type": "Feature",
  "properties": {
    "iso:country":"IN",
    "ks:ks_name":"Mavinakoppa",
    "ks:ks_pop":120,
    "ks:ks_type":"HABITATION",
    "name:eng_x_preferred":[
        "Mavinakoppa"
    ],
    "wof:name":"Mavinakoppa",
    "wof:placetype":"locality",
    "wof:population":120
},
  "geometry": {"coordinates":[74.915175,14.669604],"type":"Point"}
}