{
  "type": "Feature",
  "properties": {
    "gn:admin1_code":"36",
    "gn:admin2_code":"179.0",
    "gn:asciiname":"Pura Babu",
    "gn:country_code":"IN",
    "gn:dem":112,
    "gn:feature_class":"P",
    "gn:feature_code":"PPL",
    "gn:name":"Pura B\u0101bu",
    "gn:population":0,
    "gn:timezone":"Asia/Kolkata",
    "iso:country":"IN",
    "wof:name":"Pura Babu",
    "wof:placetype":"neighbourhood"
},
  "geometry": {"coordinates":[81.58168999999999,26.28452],"type":"Point"}
}