{
  "type": "Feature",
  "properties": {
    "iso:country":"IN",
    "ks:ks_name":"Chilapatna",
    "ks:ks_pop":480,
    "ks:ks_type":"HABITATION",
    "name:eng_x_preferred":[
        "Chilapatna"
    ],
    "wof:name":"Chilapatna",
    "wof:placetype":"locality",
    "wof:population":480
},
  "geometry": {"coordinates":[85.878945,19.955273],"type":"Point"}
}