{
  "type": "Feature",
  "properties": {
    "gn:admin1_code":"39.0",
    "gn:admin2_code":"66.0",
    "gn:asciiname":"Motipur",
    "gn:country_code":"IN",
    "gn:dem":286,
    "gn:feature_class":"P",
    "gn:feature_code":"PPL",
    "gn:name":"Mot\u012bpur",
    "gn:population":0,
    "gn:timezone":"Asia/Kolkata",
    "iso:country":"IN",
    "name:fra_x_preferred":[
        "Motipur"
    ],
    "name:pol_x_preferred":[
        "Motipur"
    ],
    "wof:name":"Motipur",
    "wof:placetype":"locality"
},
  "geometry": {"coordinates":[79.07805999999999,29.32314],"type":"Point"}
}