{
  "type": "Feature",
  "properties": {
    "iso:country":"IN",
    "ks:ks_alt_nam":"Sihari\u0101 Lakha",
    "ks:ks_alt_nam_2":"Siharia Lakha",
    "ks:ks_name":"Siharia",
    "ks:ks_type":"VILLAGE",
    "name:eng_x_preferred":[
        "Siharia"
    ],
    "name:eng_x_variant":[
        "Sihari\u0101 Lakha",
        "Siharia Lakha"
    ],
    "wof:name":"Siharia",
    "wof:placetype":"locality"
},
  "geometry": {"coordinates":[79.009805,28.944565],"type":"Point"}
}