{
  "type": "Feature",
  "properties": {
    "gn:admin1_code":"36",
    "gn:admin2_code":"201.0",
    "gn:asciiname":"Chandi",
    "gn:country_code":"IN",
    "gn:dem":169,
    "gn:feature_class":"P",
    "gn:feature_code":"PPL",
    "gn:name":"Ch\u0101ndi",
    "gn:population":0,
    "gn:timezone":"Asia/Kolkata",
    "iso:country":"IN",
    "name:ben_x_preferred":[
        "\u099a\u09a3\u09cd\u09a1\u09c0"
    ],
    "name:bos_x_preferred":[
        "Chandi"
    ],
    "name:fra_x_preferred":[
        "Chandi"
    ],
    "name:hin_x_preferred":[
        "\u091a\u0923\u094d\u0921\u0940"
    ],
    "name:hrv_x_preferred":[
        "Chandi"
    ],
    "name:pol_x_preferred":[
        "\u0106andi"
    ],
    "name:rus_x_preferred":[
        "\u0427\u0430\u043d\u0434\u0438"
    ],
    "name:sco_x_preferred":[
        "Chandi"
    ],
    "name:tel_x_preferred":[
        "\u0c1a\u0c02\u0c21\u0c3f"
    ],
    "name:urd_x_preferred":[
        "\u0686\u0646\u0688\u06cc"
    ],
    "wof:name":"Chandi",
    "wof:placetype":"locality"
},
  "geometry": {"coordinates":[78.65888000000002,27.54126],"type":"Point"}
}