{
  "type": "Feature",
  "properties": {
    "gn:admin1_code":"36",
    "gn:admin2_code":"201.0",
    "gn:asciiname":"Chandi",
    "gn:country_code":"IN",
    "gn:dem":169,
    "gn:feature_class":"P",
    "gn:feature_code":"PPL",
    "gn:name":"Ch\u0101ndi",
    "gn:population":0,
    "gn:timezone":"Asia/Kolkata",
    "iso:country":"IN",
    "name:ara_x_preferred":[
        "\u0634\u0627\u0646\u062f\u064a"
    ],
    "name:ben_bn_x_preferred":[
        "\u099a\u09be\u09a8\u09cd\u09a6\u09bf"
    ],
    "name:ben_in_x_preferred":[
        "\u099a\u09be\u09a8\u09cd\u09a6\u09bf"
    ],
    "name:ben_x_preferred":[
        "\u099a\u09a3\u09cd\u09a1\u09c0"
    ],
    "name:bos_x_preferred":[
        "Chandi"
    ],
    "name:fra_x_preferred":[
        "Chandi"
    ],
    "name:guj_x_preferred":[
        "\u0a9a\u0abe\u0a82\u0aa6\u0ac0"
    ],
    "name:hin_x_preferred":[
        "\u091a\u093e\u0902\u0926\u0940"
    ],
    "name:hin_x_variant":[
        "\u091a\u0923\u094d\u0921\u0940"
    ],
    "name:hrv_x_preferred":[
        "Chandi"
    ],
    "name:kan_x_preferred":[
        "\u0c9a\u0cbe\u0c82\u0ca6\u0cbf"
    ],
    "name:mal_x_preferred":[
        "\u0d1a\u0d3e\u0d23\u0d4d\u0d1f\u0d3f"
    ],
    "name:mar_x_preferred":[
        "\u091a\u0902\u0921\u0940"
    ],
    "name:pan_x_preferred":[
        "\u0a1a\u0a70\u0a21\u0a40"
    ],
    "name:pol_x_preferred":[
        "\u0106andi"
    ],
    "name:rus_x_preferred":[
        "\u0427\u0430\u043d\u0434\u0438"
    ],
    "name:sco_x_preferred":[
        "Chandi"
    ],
    "name:tam_x_preferred":[
        "\u0b9a\u0ba9\u0bcd\u0b9f\u0bbf"
    ],
    "name:tel_x_preferred":[
        "\u0c1b\u0c3e\u0c02\u0c26\u0c3f"
    ],
    "name:tel_x_variant":[
        "\u0c1a\u0c02\u0c21\u0c3f"
    ],
    "name:urd_x_preferred":[
        "\u0686\u0627\u0646\u0688\u06cc"
    ],
    "name:urd_x_variant":[
        "\u0686\u0646\u0688\u06cc"
    ],
    "wof:name":"Chandi",
    "wof:placetype":"locality"
},
  "geometry": {"coordinates":[78.65888000000002,27.54126],"type":"Point"}
}