{
  "type": "Feature",
  "properties": {
    "gn:admin1_code":"21",
    "gn:admin2_code":"390.0",
    "gn:asciiname":"Gurulimaska",
    "gn:country_code":"IN",
    "gn:dem":730,
    "gn:feature_class":"P",
    "gn:feature_code":"PPL",
    "gn:name":"Gurulimaska",
    "gn:population":0,
    "gn:timezone":"Asia/Kolkata",
    "iso:country":"IN",
    "ks:ks_name":"Gurulimaska",
    "ks:ks_type":"VILLAGE",
    "name:eng_x_preferred":[
        "Gurulimaska"
    ],
    "wof:name":"Gurulimaska",
    "wof:placetype":"locality"
},
  "geometry": {"coordinates":[83.58597399999999,19.982766],"type":"Point"}
}