{
  "type": "Feature",
  "properties": {
    "iso:country":"IN",
    "ks:ks_name":"Chokshol",
    "ks:ks_pop":593,
    "ks:ks_type":"VILLAGE",
    "name:eng_x_preferred":[
        "Chokshol"
    ],
    "wof:name":"Chokshol",
    "wof:placetype":"locality",
    "wof:population":593
},
  "geometry": {"coordinates":[86.594081,22.354825],"type":"Point"}
}