{
  "type": "Feature",
  "properties": {
    "iso:country":"IN",
    "ks:ks_name":"Bakulguri",
    "ks:ks_pop":912,
    "ks:ks_type":"VILLAGE",
    "name:eng_x_preferred":[
        "Bakulguri"
    ],
    "wof:name":"Bakulguri",
    "wof:placetype":"locality",
    "wof:population":912
},
  "geometry": {"coordinates":[91.74551200000001,26.573026],"type":"Point"}
}