{
  "type": "Feature",
  "properties": {
    "gn:admin1_code":"23.0",
    "gn:admin2_code":"52.0",
    "gn:asciiname":"Chintgarh",
    "gn:country_code":"IN",
    "gn:dem":305,
    "gn:feature_class":"P",
    "gn:feature_code":"PPL",
    "gn:name":"Chintgarh",
    "gn:population":0,
    "gn:timezone":"Asia/Kolkata",
    "iso:country":"IN",
    "wof:name":"Chintgarh",
    "wof:placetype":"locality"
},
  "geometry": {"coordinates":[76.59313,30.85665],"type":"Point"}
}