{
  "type": "Feature",
  "properties": {
    "iso:country":"IN",
    "ks:ks_name":"Gavalipura",
    "ks:ks_pop":419,
    "ks:ks_type":"HABITATION",
    "name:eng_x_preferred":[
        "Gavalipura"
    ],
    "wof:name":"Gavalipura",
    "wof:placetype":"locality",
    "wof:population":419
},
  "geometry": {"coordinates":[75.821725,20.33052],"type":"Point"}
}