{
  "type": "Feature",
  "properties": {
    "gn:admin1_code":"36",
    "gn:admin2_code":"194.0",
    "gn:asciiname":"Neorhia",
    "gn:country_code":"IN",
    "gn:dem":89,
    "gn:feature_class":"P",
    "gn:feature_code":"PPL",
    "gn:name":"Neorhia",
    "gn:population":0,
    "gn:timezone":"Asia/Kolkata",
    "iso:country":"IN",
    "name:und_x_variant":[
        "Purwa Rasulha"
    ],
    "wof:name":"Neorhia",
    "wof:placetype":"locality"
},
  "geometry": {"coordinates":[82.68186999999998,25.45117],"type":"Point"}
}