{
  "type": "Feature",
  "properties": {
    "gn:admin1_code":"36",
    "gn:admin2_code":"138.0",
    "gn:asciiname":"Dhomu Nagli",
    "gn:country_code":"IN",
    "gn:dem":230,
    "gn:feature_class":"P",
    "gn:feature_code":"PPL",
    "gn:name":"Dhomu Nagli",
    "gn:population":0,
    "gn:timezone":"Asia/Kolkata",
    "iso:country":"IN",
    "ks:ks_name":"Dhuma Nagli",
    "ks:ks_pop":754,
    "ks:ks_type":"VILLAGE",
    "ks:ks_uagg_main":0,
    "name:eng_x_preferred":[
        "Dhuma Nagli"
    ],
    "wof:name":"Dhuma Nagli",
    "wof:placetype":"neighbourhood",
    "wof:population":754
},
  "geometry": {"coordinates":[77.991845,29.098152],"type":"Point"}
}