{
  "type": "Feature",
  "properties": {
    "iso:country":"IN",
    "ks:ks_name":"Bachahalli",
    "ks:ks_pop":178,
    "ks:ks_type":"HABITATION",
    "name:eng_x_preferred":[
        "Bachahalli"
    ],
    "wof:name":"Bachahalli",
    "wof:placetype":"locality",
    "wof:population":178
},
  "geometry": {"coordinates":[76.299511,12.270438],"type":"Point"}
}