{
  "type": "Feature",
  "properties": {
    "gn:admin1_code":"10.0",
    "gn:admin2_code":"84.0",
    "gn:asciiname":"Dhani Partal",
    "gn:country_code":"IN",
    "gn:dem":267,
    "gn:feature_class":"P",
    "gn:feature_code":"PPL",
    "gn:name":"Dh\u0101ni Part\u0101l",
    "gn:population":0,
    "gn:timezone":"Asia/Kolkata",
    "iso:country":"IN",
    "wof:name":"Dhani Partal",
    "wof:placetype":"locality"
},
  "geometry": {"coordinates":[76.31235,28.25828],"type":"Point"}
}