{
  "type": "Feature",
  "properties": {
    "gn:admin1_code":"2",
    "gn:admin2_code":"544.0",
    "gn:asciiname":"Nandiput",
    "gn:country_code":"IN",
    "gn:dem":1058,
    "gn:feature_class":"P",
    "gn:feature_code":"PPL",
    "gn:name":"Nandiput",
    "gn:population":0,
    "gn:timezone":"Asia/Kolkata",
    "iso:country":"IN",
    "ks:ks_name":"Nandiput",
    "ks:ks_type":"VILLAGE",
    "name:eng_x_preferred":[
        "Nandiput"
    ],
    "wof:name":"Nandiput",
    "wof:placetype":"locality"
},
  "geometry": {"coordinates":[82.764252,18.075826],"type":"Point"}
}