{
  "type": "Feature",
  "properties": {
    "iso:country":"IN",
    "ks:ks_name":"Chain Tiwari Ka Purwa",
    "ks:ks_pop":500,
    "ks:ks_type":"HABITATION",
    "ks:ks_uagg_main":0,
    "name:eng_x_preferred":[
        "Chain Tiwari Ka Purwa"
    ],
    "wof:name":"Chain Tiwari Ka Purwa",
    "wof:placetype":"neighbourhood",
    "wof:population":500
},
  "geometry": {"coordinates":[81.545744,26.128727],"type":"Point"}
}