{
  "type": "Feature",
  "properties": {
    "iso:country":"IN",
    "ks:ks_alt_nam":"HAVELI VADGAON",
    "ks:ks_name":"Haveli Vadgaon",
    "ks:ks_pop":75,
    "ks:ks_type":"HABITATION",
    "name:eng_x_preferred":[
        "Haveli Vadgaon"
    ],
    "wof:name":"Haveli Vadgaon",
    "wof:placetype":"locality",
    "wof:population":75
},
  "geometry": {"coordinates":[74.280694,17.223363],"type":"Point"}
}