{
  "type": "Feature",
  "properties": {
    "iso:country":"IN",
    "ks:ks_name":"Andrewasti",
    "ks:ks_pop":256,
    "ks:ks_type":"HABITATION",
    "ks:ks_uagg_main":0,
    "name:eng_x_preferred":[
        "Andrewasti"
    ],
    "wof:name":"Andrewasti",
    "wof:placetype":"neighbourhood",
    "wof:population":256
},
  "geometry": {"coordinates":[73.752893,19.016895],"type":"Point"}
}