{
  "type": "Feature",
  "properties": {
    "gn:admin1_code":"2.0",
    "gn:admin2_code":"554.0",
    "gn:asciiname":"Udayamanikyam",
    "gn:country_code":"IN",
    "gn:dem":570,
    "gn:feature_class":"P",
    "gn:feature_code":"PPL",
    "gn:name":"Udayam\u0101nikyam",
    "gn:population":0,
    "gn:timezone":"Asia/Kolkata",
    "iso:country":"IN",
    "ks:ks_alt_nam":"Udayam\u0101nikyam",
    "ks:ks_name":"Udayamanikyam",
    "ks:ks_pop":1,
    "ks:ks_type":"VILLAGE",
    "name:eng_x_preferred":[
        "Udayamanikyam"
    ],
    "name:eng_x_variant":[
        "Udayam\u0101nikyam"
    ],
    "wof:name":"Udayamanikyam",
    "wof:placetype":"locality",
    "wof:population":1
},
  "geometry": {"coordinates":[79.12032000000001,13.738932],"type":"Point"}
}