{
  "type": "Feature",
  "properties": {
    "gn:admin1_code":"24.0",
    "gn:admin2_code":"102.0",
    "gn:asciiname":"Sadau",
    "gn:country_code":"IN",
    "gn:dem":237,
    "gn:feature_class":"P",
    "gn:feature_code":"PPL",
    "gn:name":"Sad\u0101u",
    "gn:population":0,
    "gn:timezone":"Asia/Kolkata",
    "iso:country":"IN",
    "wof:name":"Sadau",
    "wof:placetype":"locality"
},
  "geometry": {"coordinates":[75.50482,28.67335],"type":"Point"}
}