{
  "type": "Feature",
  "properties": {
    "iso:country":"IN",
    "ks:ks_name":"Mohida",
    "ks:ks_pop":5,
    "ks:ks_type":"HABITATION",
    "name:eng_x_preferred":[
        "Mohida"
    ],
    "wof:name":"Mohida",
    "wof:placetype":"locality",
    "wof:population":5
},
  "geometry": {"coordinates":[76.030038,22.294038],"type":"Point"}
}