{
  "type": "Feature",
  "properties": {
    "gn:admin1_code":"2.0",
    "gn:admin2_code":"544.0",
    "gn:asciiname":"Mardapalle",
    "gn:country_code":"IN",
    "gn:dem":1006,
    "gn:feature_class":"P",
    "gn:feature_code":"PPL",
    "gn:name":"Mardapalle",
    "gn:population":0,
    "gn:timezone":"Asia/Kolkata",
    "iso:country":"IN",
    "wof:name":"Mardapalle",
    "wof:placetype":"locality"
},
  "geometry": {"coordinates":[82.57635999999999,18.17253],"type":"Point"}
}