{
  "type": "Feature",
  "properties": {
    "gn:admin1_code":"2.0",
    "gn:admin2_code":"544.0",
    "gn:asciiname":"Mardapalle",
    "gn:country_code":"IN",
    "gn:dem":1006,
    "gn:feature_class":"P",
    "gn:feature_code":"PPL",
    "gn:name":"Mardapalle",
    "gn:population":0,
    "gn:timezone":"Asia/Kolkata",
    "iso:country":"IN",
    "ks:ks_name":"Maradapalle",
    "ks:ks_pop":166,
    "ks:ks_type":"HABITATION",
    "name:eng_x_preferred":[
        "Maradapalle"
    ],
    "name:eng_x_variant":[
        "Mardapalle"
    ],
    "wof:name":"Maradapalle",
    "wof:placetype":"locality",
    "wof:population":166
},
  "geometry": {"coordinates":[82.575237,18.170553],"type":"Point"}
}