{
  "type": "Feature",
  "properties": {
    "gn:admin1_code":"12",
    "gn:admin2_code":"15.0",
    "gn:asciiname":"Gujarpor",
    "gn:country_code":"IN",
    "gn:dem":2070,
    "gn:feature_class":"P",
    "gn:feature_code":"PPL",
    "gn:name":"Gujarp\u014dr",
    "gn:population":0,
    "gn:timezone":"Asia/Kolkata",
    "iso:country":"IN",
    "wof:name":"Gujarpor",
    "wof:placetype":"locality"
},
  "geometry": {"coordinates":[74.94108,33.5834],"type":"Point"}
}