{
  "type": "Feature",
  "properties": {
    "iso:country":"IN",
    "ks:ks_name":"Pandhramati",
    "ks:ks_pop":893,
    "ks:ks_type":"VILLAGE",
    "name:eng_x_preferred":[
        "Pandhramati"
    ],
    "wof:name":"Pandhramati",
    "wof:placetype":"locality",
    "wof:population":893
},
  "geometry": {"coordinates":[73.858045,21.747274],"type":"Point"}
}