{
  "type": "Feature",
  "properties": {
    "iso:country":"IN",
    "ks:ks_name":"Kodukarakavalasa",
    "ks:ks_pop":35,
    "ks:ks_type":"VILLAGE",
    "name:eng_x_preferred":[
        "Kodukarakavalasa"
    ],
    "wof:name":"Kodukarakavalasa",
    "wof:placetype":"locality",
    "wof:population":35
},
  "geometry": {"coordinates":[83.18652,18.577389],"type":"Point"}
}