{
  "type": "Feature",
  "properties": {
    "iso:country":"IN",
    "ks:ks_name":"Dubghati",
    "ks:ks_pop":69,
    "ks:ks_type":"VILLAGE",
    "name:eng_x_preferred":[
        "Dubghati"
    ],
    "wof:name":"Dubghati",
    "wof:placetype":"locality",
    "wof:population":69
},
  "geometry": {"coordinates":[84.290426,20.369343],"type":"Point"}
}