{
  "type": "Feature",
  "properties": {
    "gn:admin1_code":"36",
    "gn:admin2_code":"188.0",
    "gn:asciiname":"Gerua",
    "gn:country_code":"IN",
    "gn:dem":83,
    "gn:feature_class":"P",
    "gn:feature_code":"PPL",
    "gn:name":"Gerua",
    "gn:population":0,
    "gn:timezone":"Asia/Kolkata",
    "iso:country":"IN",
    "name:ita_x_preferred":[
        "Gerua"
    ],
    "wof:name":"Gerua",
    "wof:placetype":"neighbourhood"
},
  "geometry": {"coordinates":[83.34081999999999,26.56454],"type":"Point"}
}