{
  "type": "Feature",
  "properties": {
    "iso:country":"IN",
    "ks:ks_name":"Verapapanikunta",
    "ks:ks_pop":98,
    "ks:ks_type":"VILLAGE",
    "name:eng_x_preferred":[
        "Verapapanikunta"
    ],
    "wof:name":"Verapapanikunta",
    "wof:placetype":"locality",
    "wof:population":98
},
  "geometry": {"coordinates":[81.35886000000001,17.650482],"type":"Point"}
}