{
  "type": "Feature",
  "properties": {
    "iso:country":"IN",
    "ks:ks_name":"Lohagathi",
    "ks:ks_pop":118,
    "ks:ks_type":"HABITATION",
    "name:eng_x_preferred":[
        "Lohagathi"
    ],
    "wof:name":"Lohagathi",
    "wof:placetype":"locality",
    "wof:population":118
},
  "geometry": {"coordinates":[81.193022,25.219303],"type":"Point"}
}