{
  "type": "Feature",
  "properties": {
    "iso:country":"IN",
    "ks:ks_name":"Chak Jalal",
    "ks:ks_pop":97,
    "ks:ks_type":"VILLAGE",
    "name:eng_x_preferred":[
        "Chak Jalal"
    ],
    "wof:name":"Chak Jalal",
    "wof:placetype":"locality",
    "wof:population":97
},
  "geometry": {"coordinates":[85.227046,25.664721],"type":"Point"}
}