{
  "type": "Feature",
  "properties": {
    "iso:country":"IN",
    "ks:ks_name":"Khutaul",
    "ks:ks_pop":0,
    "ks:ks_type":"VILLAGE",
    "name:eng_x_preferred":[
        "Khutaul"
    ],
    "wof:name":"Khutaul",
    "wof:placetype":"locality",
    "wof:population":0
},
  "geometry": {"coordinates":[85.889746,24.949359],"type":"Point"}
}