{
  "type": "Feature",
  "properties": {
    "iso:country":"IN",
    "ks:ks_alt_nam":"N. HARIJAN TOLA",
    "ks:ks_name":"N. Harijan Tola",
    "ks:ks_pop":150,
    "ks:ks_type":"HABITATION",
    "name:eng_x_preferred":[
        "N. Harijan Tola"
    ],
    "wof:name":"N. Harijan Tola",
    "wof:placetype":"locality",
    "wof:population":150
},
  "geometry": {"coordinates":[86.50643599999999,26.086819],"type":"Point"}
}