{
  "type": "Feature",
  "properties": {
    "iso:country":"IN",
    "ks:ks_name":"Tulli",
    "ks:ks_pop":50,
    "ks:ks_type":"VILLAGE",
    "name:eng_x_preferred":[
        "Tulli"
    ],
    "wof:name":"Tulli",
    "wof:placetype":"locality",
    "wof:population":50
},
  "geometry": {"coordinates":[80.488443,28.506704],"type":"Point"}
}