{
  "type": "Feature",
  "properties": {
    "iso:country":"IN",
    "ks:ks_alt_nam":"Mutlapady JHC",
    "ks:ks_name":"Mutlapady Jhc",
    "ks:ks_pop":180,
    "ks:ks_type":"HABITATION",
    "name:eng_x_preferred":[
        "Mutlapady Jhc"
    ],
    "wof:name":"Mutlapady Jhc",
    "wof:placetype":"locality",
    "wof:population":180
},
  "geometry": {"coordinates":[75.042198,13.361619],"type":"Point"}
}