{
  "type": "Feature",
  "properties": {
    "iso:country":"IN",
    "ks:ks_name":"Bar Mohanpur",
    "ks:ks_pop":260,
    "ks:ks_type":"VILLAGE",
    "name:eng_x_preferred":[
        "Bar Mohanpur"
    ],
    "wof:name":"Bar Mohanpur",
    "wof:placetype":"locality",
    "wof:population":260
},
  "geometry": {"coordinates":[88.103082,22.159731],"type":"Point"}
}