{
  "type": "Feature",
  "properties": {
    "iso:country":"IN",
    "ks:ks_name":"Ghamur",
    "ks:ks_pop":294,
    "ks:ks_type":"VILLAGE",
    "ks:ks_uagg_main":0,
    "name:eng_x_preferred":[
        "Ghamur"
    ],
    "wof:name":"Ghamur",
    "wof:placetype":"neighbourhood",
    "wof:population":294
},
  "geometry": {"coordinates":[83.25079100000001,26.584405],"type":"Point"}
}