{
  "type": "Feature",
  "properties": {
    "iso:country":"IN",
    "ks:ks_name":"Shankarpur",
    "ks:ks_pop":530,
    "ks:ks_type":"VILLAGE",
    "name:eng_x_preferred":[
        "Shankarpur"
    ],
    "wof:name":"Shankarpur",
    "wof:placetype":"locality",
    "wof:population":530
},
  "geometry": {"coordinates":[83.533024,23.633661],"type":"Point"}
}