{
  "type": "Feature",
  "properties": {
    "iso:country":"IN",
    "ks:ks_name":"Govele",
    "ks:ks_pop":561,
    "ks:ks_type":"VILLAGE",
    "name:eng_x_preferred":[
        "Govele"
    ],
    "wof:name":"Govele",
    "wof:placetype":"locality",
    "wof:population":561
},
  "geometry": {"coordinates":[73.57348,18.008526],"type":"Point"}
}