{
  "type": "Feature",
  "properties": {
    "gn:admin1_code":"12.0",
    "gn:admin2_code":"13.0",
    "gn:asciiname":"Mul",
    "gn:country_code":"IN",
    "gn:dem":1802,
    "gn:feature_class":"P",
    "gn:feature_code":"PPL",
    "gn:name":"M\u016bl",
    "gn:population":0,
    "gn:timezone":"Asia/Kolkata",
    "iso:country":"IN",
    "wof:name":"Mul",
    "wof:placetype":"locality"
},
  "geometry": {"coordinates":[74.90676999999999,33.77403],"type":"Point"}
}