{
  "type": "Feature",
  "properties": {
    "gn:admin1_code":"36",
    "gn:admin2_code":"147.0",
    "gn:asciiname":"Azizabad",
    "gn:country_code":"IN",
    "gn:dem":163,
    "gn:feature_class":"P",
    "gn:feature_code":"PPL",
    "gn:name":"Az\u012bz\u0101b\u0101d",
    "gn:population":0,
    "gn:timezone":"Asia/Kolkata",
    "iso:country":"IN",
    "name:ckb_x_preferred":[
        "\u0639\u06d5\u0632\u06cc\u0632\u0627\u0648\u0627"
    ],
    "name:fas_x_preferred":[
        "\u0639\u0632\u06cc\u0632\u0622\u0628\u0627\u062f"
    ],
    "wof:name":"Azizabad",
    "wof:placetype":"locality"
},
  "geometry": {"coordinates":[78.6375,27.09125],"type":"Point"}
}