{
  "type": "Feature",
  "properties": {
    "gn:admin1_code":"36",
    "gn:admin2_code":"156.0",
    "gn:asciiname":"Hindupur",
    "gn:country_code":"IN",
    "gn:dem":124,
    "gn:feature_class":"P",
    "gn:feature_code":"PPL",
    "gn:name":"Hindupur",
    "gn:population":0,
    "gn:timezone":"Asia/Kolkata",
    "iso:country":"IN",
    "name:bih_x_preferred":[
        "\u0939\u093f\u0902\u0926\u0941\u092a\u0941\u0930"
    ],
    "name:bpy_x_preferred":[
        "\u09b9\u09bf\u09a8\u09cd\u09a6\u09c1\u09aa\u09c1\u09b0"
    ],
    "name:ceb_x_preferred":[
        "Hindupur"
    ],
    "name:ita_x_preferred":[
        "Hindupur"
    ],
    "name:mlg_x_preferred":[
        "Hindupur"
    ],
    "name:msa_x_preferred":[
        "Hindupur"
    ],
    "name:new_x_preferred":[
        "\u0939\u093f\u0928\u094d\u0926\u0941\u092a\u0941\u0930"
    ],
    "name:ori_x_preferred":[
        "\u0b39\u0b3f\u0b28\u0b4d\u0b26\u0b41\u0b2a\u0b41\u0b30"
    ],
    "name:pnb_x_preferred":[
        "\u06c1\u0646\u062f\u0648\u067e\u0648\u0631"
    ],
    "name:por_x_preferred":[
        "Hindupur"
    ],
    "name:spa_x_preferred":[
        "Hindupur"
    ],
    "name:swe_x_preferred":[
        "Hindupur"
    ],
    "name:tam_x_preferred":[
        "\u0b87\u0ba8\u0bcd\u0ba4\u0bc1\u0baa\u0bcd\u0baa\u0bc2\u0bb0\u0bcd"
    ],
    "name:tel_x_preferred":[
        "\u0c39\u0c3f\u0c02\u0c26\u0c42\u0c2a\u0c41\u0c30\u0c02"
    ],
    "name:tgl_x_preferred":[
        "Hindupur"
    ],
    "name:urd_x_preferred":[
        "\u06c1\u0646\u062f\u0648\u067e\u0648\u0631"
    ],
    "name:vie_x_preferred":[
        "Hindupur"
    ],
    "name:war_x_preferred":[
        "Hindupur"
    ],
    "name:zho_x_preferred":[
        "\u5e0c\u6069\u675c\u666e\u5c14"
    ],
    "wof:name":"Hindupur",
    "wof:placetype":"locality"
},
  "geometry": {"coordinates":[80.8458,26.30569],"type":"Point"}
}