{
  "type": "Feature",
  "properties": {
    "iso:country":"IN",
    "ks:ks_name":"Hansanabadchaka Bada Ghumuri",
    "ks:ks_pop":287,
    "ks:ks_type":"VILLAGE",
    "name:eng_x_preferred":[
        "Hansanabadchaka Bada Ghumuri"
    ],
    "wof:name":"Hansanabadchaka Bada Ghumuri",
    "wof:placetype":"locality",
    "wof:population":287
},
  "geometry": {"coordinates":[86.123026,20.64607],"type":"Point"}
}