{
  "type": "Feature",
  "properties": {
    "iso:country":"IN",
    "ks:ks_name":"Anghula",
    "ks:ks_pop":74,
    "ks:ks_type":"HABITATION",
    "name:eng_x_preferred":[
        "Anghula"
    ],
    "wof:name":"Anghula",
    "wof:placetype":"locality",
    "wof:population":74
},
  "geometry": {"coordinates":[81.872947,26.398828],"type":"Point"}
}