{
  "type": "Feature",
  "properties": {
    "gn:admin1_code":"36",
    "gn:admin2_code":"162.0",
    "gn:asciiname":"Bamhuripur Ki Marhaiyan",
    "gn:country_code":"IN",
    "gn:dem":143,
    "gn:feature_class":"P",
    "gn:feature_code":"PPL",
    "gn:name":"Bamh\u016br\u012bpur Ki Marhaiy\u0101n",
    "gn:population":0,
    "gn:timezone":"Asia/Kolkata",
    "iso:country":"IN",
    "wof:name":"Bamhuripur Ki Marhaiyan",
    "wof:placetype":"neighbourhood"
},
  "geometry": {"coordinates":[79.54379,26.51136],"type":"Point"}
}