{
  "type": "Feature",
  "properties": {
    "gn:admin1_code":"34.0",
    "gn:admin2_code":"204.0",
    "gn:asciiname":"Dumri",
    "gn:country_code":"IN",
    "gn:dem":77,
    "gn:feature_class":"P",
    "gn:feature_code":"PPL",
    "gn:name":"Dumri",
    "gn:population":0,
    "gn:timezone":"Asia/Kolkata",
    "iso:country":"IN",
    "wof:name":"Dumri",
    "wof:placetype":"neighbourhood"
},
  "geometry": {"coordinates":[84.76428,26.7796],"type":"Point"}
}