{
  "type": "Feature",
  "properties": {
    "iso:country":"IN",
    "ks:ks_name":"Nainol",
    "ks:ks_pop":2641,
    "ks:ks_type":"VILLAGE",
    "name:eng_x_preferred":[
        "Nainol"
    ],
    "wof:name":"Nainol",
    "wof:placetype":"locality",
    "wof:population":2641
},
  "geometry": {"coordinates":[71.886686,24.699161],"type":"Point"}
}