{
  "type": "Feature",
  "properties": {
    "iso:country":"IN",
    "ks:ks_name":"Daudpur",
    "ks:ks_pop":759,
    "ks:ks_type":"VILLAGE",
    "ks:ks_uagg_main":0,
    "name:eng_x_preferred":[
        "Daudpur"
    ],
    "wof:name":"Daudpur",
    "wof:placetype":"neighbourhood",
    "wof:population":759
},
  "geometry": {"coordinates":[87.560211,21.855701],"type":"Point"}
}