{
  "type": "Feature",
  "properties": {
    "gn:admin1_code":"11",
    "gn:admin2_code":"23.0",
    "gn:asciiname":"Rell",
    "gn:country_code":"IN",
    "gn:dem":2477,
    "gn:feature_class":"P",
    "gn:feature_code":"PPL",
    "gn:name":"Rell",
    "gn:population":0,
    "gn:timezone":"Asia/Kolkata",
    "iso:country":"IN",
    "wof:name":"Rell",
    "wof:placetype":"locality"
},
  "geometry": {"coordinates":[76.24602,32.5241],"type":"Point"}
}