{
  "type": "Feature",
  "properties": {
    "iso:country":"IN",
    "ks:ks_name":"Nellavaripeta",
    "ks:ks_pop":311,
    "ks:ks_type":"HABITATION",
    "name:eng_x_preferred":[
        "Nellavaripeta"
    ],
    "wof:name":"Nellavaripeta",
    "wof:placetype":"locality",
    "wof:population":311
},
  "geometry": {"coordinates":[81.916307,16.67711],"type":"Point"}
}