{
  "type": "Feature",
  "properties": {
    "gn:admin1_code":"36.0",
    "gn:admin2_code":"193.0",
    "gn:asciiname":"Eksar",
    "gn:country_code":"IN",
    "gn:dem":69,
    "gn:feature_class":"P",
    "gn:feature_code":"PPL",
    "gn:name":"Eksar",
    "gn:population":0,
    "gn:timezone":"Asia/Kolkata",
    "iso:country":"IN",
    "name:ara_x_preferred":[
        "\u0625\u0643\u0633\u0627\u0631"
    ],
    "name:ben_bn_x_preferred":[
        "\u098f\u0995\u09b8\u09be\u09b0"
    ],
    "name:ben_in_x_preferred":[
        "\u098f\u0995\u09b8\u09b0"
    ],
    "name:guj_x_preferred":[
        "\u0a8f\u0a95\u0ab8\u0abe\u0ab0"
    ],
    "name:hin_x_preferred":[
        "\u090f\u0915\u0938\u0930"
    ],
    "name:kan_x_preferred":[
        "\u0c8f\u0c95\u0ccd\u0cb8\u0cb0\u0ccd\u200c"
    ],
    "name:mal_x_preferred":[
        "\u0d0e\u0d15\u0d4d\u0d38\u0d3e\u0d30\u0d4d\u200d\u200c"
    ],
    "name:mar_x_preferred":[
        "\u090f\u0915\u094d\u0938\u0930"
    ],
    "name:pan_x_preferred":[
        "\u0a10\u0a15\u0a38\u0a30"
    ],
    "name:tam_x_preferred":[
        "\u0b8e\u0b95\u0bcd\u0b9a\u0bb0\u0bcd"
    ],
    "name:tel_x_preferred":[
        "\u0c0e\u0c15\u0c4d\u0c38\u0c3e\u0c30\u0c4d"
    ],
    "name:urd_x_preferred":[
        "\u0627\u06cc\u06a9\u0633\u0627\u0631"
    ],
    "wof:name":"Eksar",
    "wof:placetype":"locality"
},
  "geometry": {"coordinates":[84.00861,26.07034],"type":"Point"}
}