{
  "type": "Feature",
  "properties": {
    "iso:country":"IN",
    "ks:ks_name":"Halekote",
    "ks:ks_pop":187,
    "ks:ks_type":"HABITATION",
    "name:eng_x_preferred":[
        "Halekote"
    ],
    "wof:name":"Halekote",
    "wof:placetype":"locality",
    "wof:population":187
},
  "geometry": {"coordinates":[77.202939,13.387537],"type":"Point"}
}