{
  "type": "Feature",
  "properties": {
    "gn:admin1_code":"34.0",
    "gn:admin2_code":"224.0",
    "gn:asciiname":"Kamlakund",
    "gn:country_code":"IN",
    "gn:dem":27,
    "gn:feature_class":"P",
    "gn:feature_code":"PPL",
    "gn:name":"Kaml\u0101kund",
    "gn:population":0,
    "gn:timezone":"Asia/Kolkata",
    "iso:country":"IN",
    "ks:ks_name":"Kamlakund",
    "ks:ks_pop":3048,
    "ks:ks_type":"VILLAGE",
    "name:eng_x_preferred":[
        "Kamlakund"
    ],
    "wof:name":"Kamlakund",
    "wof:placetype":"locality",
    "wof:population":3048
},
  "geometry": {"coordinates":[87.153091,25.298255],"type":"Point"}
}