{
  "type": "Feature",
  "properties": {
    "gn:admin1_code":"34.0",
    "gn:admin2_code":"215.0",
    "gn:asciiname":"Satghara",
    "gn:country_code":"IN",
    "gn:dem":53,
    "gn:feature_class":"P",
    "gn:feature_code":"PPL",
    "gn:name":"Satghara",
    "gn:population":0,
    "gn:timezone":"Asia/Kolkata",
    "iso:country":"IN",
    "name:fas_x_preferred":[
        "\u0633\u062a\u06af\u0647\u0631\u0647"
    ],
    "name:urd_x_preferred":[
        "\u0633\u062a\u06af\u06be\u0631\u06c1"
    ],
    "wof:name":"Satghara",
    "wof:placetype":"neighbourhood"
},
  "geometry": {"coordinates":[86.01684,26.07684],"type":"Point"}
}