{
  "type": "Feature",
  "properties": {
    "iso:country":"IN",
    "ks:ks_name":"Nagmai",
    "ks:ks_pop":135,
    "ks:ks_type":"HABITATION",
    "ks:ks_uagg_main":0,
    "name:eng_x_preferred":[
        "Nagmai"
    ],
    "wof:name":"Nagmai",
    "wof:placetype":"neighbourhood",
    "wof:population":135
},
  "geometry": {"coordinates":[78.85972700000001,27.596038],"type":"Point"}
}