{
  "type": "Feature",
  "properties": {
    "gn:admin1_code":"19.0",
    "gn:admin2_code":"571.0",
    "gn:asciiname":"Kempasagara",
    "gn:country_code":"IN",
    "gn:dem":794,
    "gn:feature_class":"P",
    "gn:feature_code":"PPL",
    "gn:name":"Kempas\u0101gara",
    "gn:population":0,
    "gn:timezone":"Asia/Kolkata",
    "iso:country":"IN",
    "wof:name":"Kempasagara",
    "wof:placetype":"locality"
},
  "geometry": {"coordinates":[77.07143000000001,13.07476],"type":"Point"}
}