{
  "type": "Feature",
  "properties": {
    "iso:country":"IN",
    "ks:ks_name":"Rasalpur",
    "ks:ks_pop":156,
    "ks:ks_type":"VILLAGE",
    "name:eng_x_preferred":[
        "Rasalpur"
    ],
    "wof:name":"Rasalpur",
    "wof:placetype":"locality",
    "wof:population":156
},
  "geometry": {"coordinates":[86.261437,20.859363],"type":"Point"}
}