{
  "type": "Feature",
  "properties": {
    "gn:admin1_code":"21",
    "gn:admin2_code":"370.0",
    "gn:asciiname":"Phirupali",
    "gn:country_code":"IN",
    "gn:dem":185,
    "gn:feature_class":"P",
    "gn:feature_code":"PPL",
    "gn:name":"Phirup\u0101li",
    "gn:population":0,
    "gn:timezone":"Asia/Kolkata",
    "iso:country":"IN",
    "ks:ks_alt_nam":"Phirup\u0101li",
    "ks:ks_name":"Phirupali",
    "ks:ks_type":"VILLAGE",
    "name:eng_x_preferred":[
        "Phirupali"
    ],
    "name:eng_x_variant":[
        "Phirup\u0101li"
    ],
    "wof:name":"Phirupali",
    "wof:placetype":"locality"
},
  "geometry": {"coordinates":[83.115054,20.983869],"type":"Point"}
}