{
  "type": "Feature",
  "properties": {
    "iso:country":"IN",
    "ks:ks_alt_nam":"Ibr\u0101h\u012bmpur",
    "ks:ks_name":"Ibrahimpur",
    "ks:ks_type":"VILLAGE",
    "name:eng_x_preferred":[
        "Ibrahimpur"
    ],
    "name:eng_x_variant":[
        "Ibr\u0101h\u012bmpur"
    ],
    "wof:name":"Ibrahimpur",
    "wof:placetype":"locality"
},
  "geometry": {"coordinates":[83.3912,25.364614],"type":"Point"}
}