{
  "type": "Feature",
  "properties": {
    "gn:admin1_code":"36.0",
    "gn:admin2_code":"136.0",
    "gn:asciiname":"Jadhonwala Mazra",
    "gn:country_code":"IN",
    "gn:dem":213,
    "gn:feature_class":"P",
    "gn:feature_code":"PPL",
    "gn:name":"J\u0101dhonw\u0101la Mazra",
    "gn:population":0,
    "gn:timezone":"Asia/Kolkata",
    "iso:country":"IN",
    "wof:name":"Jadhonwala Mazra",
    "wof:placetype":"neighbourhood"
},
  "geometry": {"coordinates":[79.13035000000001,29.06873],"type":"Point"}
}