{
  "type": "Feature",
  "properties": {
    "iso:country":"IN",
    "ks:ks_name":"Doddanahalli",
    "ks:ks_type":"VILLAGE",
    "name:eng_x_preferred":[
        "Doddanahalli"
    ],
    "wof:name":"Doddanahalli",
    "wof:placetype":"locality"
},
  "geometry": {"coordinates":[77.326274,13.757541],"type":"Point"}
}