{
  "type": "Feature",
  "properties": {
    "iso:country":"IN",
    "ks:ks_name":"Yerrametla",
    "ks:ks_pop":206,
    "ks:ks_type":"VILLAGE",
    "name:eng_x_preferred":[
        "Yerrametla"
    ],
    "wof:name":"Yerrametla",
    "wof:placetype":"locality",
    "wof:population":206
},
  "geometry": {"coordinates":[81.662661,17.38345],"type":"Point"}
}