{
  "type": "Feature",
  "properties": {
    "iso:country":"IN",
    "ks:ks_name":"Chakuli",
    "ks:ks_pop":285,
    "ks:ks_type":"VILLAGE",
    "name:eng_x_preferred":[
        "Chakuli"
    ],
    "wof:name":"Chakuli",
    "wof:placetype":"locality",
    "wof:population":285
},
  "geometry": {"coordinates":[83.91456700000001,22.067534],"type":"Point"}
}