{
  "type": "Feature",
  "properties": {
    "gn:admin1_code":"10.0",
    "gn:admin2_code":"072",
    "gn:asciiname":"Hibana",
    "gn:country_code":"IN",
    "gn:dem":262,
    "gn:feature_class":"P",
    "gn:feature_code":"PPL",
    "gn:name":"Hib\u0101na",
    "gn:population":0,
    "gn:timezone":"Asia/Kolkata",
    "iso:country":"IN",
    "name:ceb_x_preferred":[
        "Hibana"
    ],
    "name:fra_x_preferred":[
        "Hibana"
    ],
    "name:msa_x_preferred":[
        "Hibana"
    ],
    "name:nld_x_preferred":[
        "Hibana"
    ],
    "name:ron_x_preferred":[
        "Hibana"
    ],
    "name:spa_x_preferred":[
        "Hibana"
    ],
    "name:swe_x_preferred":[
        "Hibana"
    ],
    "name:vie_x_preferred":[
        "Hibana"
    ],
    "name:war_x_preferred":[
        "Hibana"
    ],
    "wof:name":"Hibana",
    "wof:placetype":"locality"
},
  "geometry": {"coordinates":[76.85054000000002,30.1257],"type":"Point"}
}