{
  "type": "Feature",
  "properties": {
    "iso:country":"IN",
    "ks:ks_name":"Halmorabasti",
    "ks:ks_pop":191,
    "ks:ks_type":"HABITATION",
    "name:eng_x_preferred":[
        "Halmorabasti"
    ],
    "wof:name":"Halmorabasti",
    "wof:placetype":"locality",
    "wof:population":191
},
  "geometry": {"coordinates":[94.915091,27.030097],"type":"Point"}
}