{
  "type": "Feature",
  "properties": {
    "gn:admin1_code":"23.0",
    "gn:admin2_code":"53.0",
    "gn:asciiname":"Muhammadpur Chhatriwala",
    "gn:country_code":"IN",
    "gn:dem":239,
    "gn:feature_class":"P",
    "gn:feature_code":"PPL",
    "gn:name":"Muhammadpur Chhatriw\u0101la",
    "gn:population":0,
    "gn:timezone":"Asia/Kolkata",
    "iso:country":"IN",
    "wof:name":"Muhammadpur Chhatriwala",
    "wof:placetype":"locality"
},
  "geometry": {"coordinates":[75.99141999999998,30.38882000000001],"type":"Point"}
}