{
  "type": "Feature",
  "properties": {
    "iso:country":"IN",
    "ks:ks_alt_nam":"BANIYA TOLA",
    "ks:ks_name":"Baniya Tola",
    "ks:ks_pop":578,
    "ks:ks_type":"HABITATION",
    "name:eng_x_preferred":[
        "Baniya Tola"
    ],
    "wof:name":"Baniya Tola",
    "wof:placetype":"locality",
    "wof:population":578
},
  "geometry": {"coordinates":[83.84450200000001,23.9382],"type":"Point"}
}