{
  "type": "Feature",
  "properties": {
    "gn:admin1_code":"11",
    "gn:admin2_code":"23.0",
    "gn:asciiname":"Manglot Adwar",
    "gn:country_code":"IN",
    "gn:dem":2768,
    "gn:feature_class":"P",
    "gn:feature_code":"PPL",
    "gn:name":"Manglot Adw\u0101r",
    "gn:population":0,
    "gn:timezone":"Asia/Kolkata",
    "iso:country":"IN",
    "wof:name":"Manglot Adwar",
    "wof:placetype":"locality"
},
  "geometry": {"coordinates":[76.09409000000002,32.86342],"type":"Point"}
}