{
  "type": "Feature",
  "properties": {
    "gn:admin1_code":"16",
    "gn:admin2_code":"528.0",
    "gn:asciiname":"Nevra",
    "gn:country_code":"IN",
    "gn:dem":31,
    "gn:feature_class":"P",
    "gn:feature_code":"PPL",
    "gn:name":"Nevra",
    "gn:population":0,
    "gn:timezone":"Asia/Kolkata",
    "iso:country":"IN",
    "name:und_x_variant":[
        "Neori",
        "Nevra"
    ],
    "wof:name":"Nevra",
    "wof:placetype":"neighbourhood"
},
  "geometry": {"coordinates":[73.304,17.11381],"type":"Point"}
}