{
  "type": "Feature",
  "properties": {
    "iso:country":"IN",
    "ks:ks_name":"Sulikata No. 1",
    "ks:ks_pop":90,
    "ks:ks_type":"HABITATION",
    "name:eng_x_preferred":[
        "Sulikata No. 1"
    ],
    "wof:name":"Sulikata No. 1",
    "wof:placetype":"locality",
    "wof:population":90
},
  "geometry": {"coordinates":[91.468272,25.953954],"type":"Point"}
}