{
  "type": "Feature",
  "properties": {
    "iso:country":"IN",
    "ks:ks_name":"Yakatpur",
    "ks:ks_type":"VILLAGE",
    "name:eng_x_preferred":[
        "Yakatpur"
    ],
    "wof:name":"Yakatpur",
    "wof:placetype":"locality"
},
  "geometry": {"coordinates":[77.526107,17.455869],"type":"Point"}
}