{
  "type": "Feature",
  "properties": {
    "gn:admin1_code":"39.0",
    "gn:admin2_code":"061",
    "gn:asciiname":"Aldaba",
    "gn:country_code":"IN",
    "gn:dem":1088,
    "gn:feature_class":"P",
    "gn:feature_code":"PPL",
    "gn:name":"Ald\u0101ba",
    "gn:population":0,
    "gn:timezone":"Asia/Kolkata",
    "iso:country":"IN",
    "wof:name":"Aldaba",
    "wof:placetype":"locality"
},
  "geometry": {"coordinates":[78.6084,29.79284],"type":"Point"}
}