{
  "type": "Feature",
  "properties": {
    "gn:admin1_code":"39.0",
    "gn:admin2_code":"061",
    "gn:asciiname":"Aldaba",
    "gn:country_code":"IN",
    "gn:dem":1088,
    "gn:feature_class":"P",
    "gn:feature_code":"PPL",
    "gn:name":"Ald\u0101ba",
    "gn:population":0,
    "gn:timezone":"Asia/Kolkata",
    "iso:country":"IN",
    "ks:ks_name":"Aldawa",
    "ks:ks_pop":97,
    "ks:ks_type":"HABITATION",
    "name:eng_x_preferred":[
        "Aldawa"
    ],
    "name:eng_x_variant":[
        "Aldaba"
    ],
    "wof:name":"Aldawa",
    "wof:placetype":"locality",
    "wof:population":97
},
  "geometry": {"coordinates":[78.607308,29.793725],"type":"Point"}
}