{
  "type": "Feature",
  "properties": {
    "iso:country":"IN",
    "ks:ks_name":"Gudrapara",
    "ks:ks_pop":520,
    "ks:ks_type":"HABITATION",
    "name:eng_x_preferred":[
        "Gudrapara"
    ],
    "wof:name":"Gudrapara",
    "wof:placetype":"locality",
    "wof:population":520
},
  "geometry": {"coordinates":[82.700986,23.797972],"type":"Point"}
}