{
  "type": "Feature",
  "properties": {
    "gn:admin1_code":"19.0",
    "gn:admin2_code":"566",
    "gn:asciiname":"Belagur",
    "gn:country_code":"IN",
    "gn:dem":707,
    "gn:feature_class":"P",
    "gn:feature_code":"PPL",
    "gn:name":"Belag\u016br",
    "gn:population":0,
    "gn:timezone":"Asia/Kolkata",
    "iso:country":"IN",
    "name:vie_x_preferred":[
        "Belagur"
    ],
    "wof:name":"Belagur",
    "wof:placetype":"locality"
},
  "geometry": {"coordinates":[76.29030999999998,13.62588],"type":"Point"}
}