{
  "type": "Feature",
  "properties": {
    "iso:country":"IN",
    "ks:ks_name":"Kishanpura",
    "ks:ks_pop":484,
    "ks:ks_type":"VILLAGE",
    "name:eng_x_preferred":[
        "Kishanpura"
    ],
    "wof:name":"Kishanpura",
    "wof:placetype":"locality",
    "wof:population":484
},
  "geometry": {"coordinates":[76.123561,26.795614],"type":"Point"}
}