{
  "type": "Feature",
  "properties": {
    "iso:country":"IN",
    "ks:ks_name":"Bankata",
    "ks:ks_pop":579,
    "ks:ks_type":"VILLAGE",
    "name:eng_x_preferred":[
        "Bankata"
    ],
    "wof:name":"Bankata",
    "wof:placetype":"locality",
    "wof:population":579
},
  "geometry": {"coordinates":[87.000051,22.916039],"type":"Point"}
}