{
  "type": "Feature",
  "properties": {
    "gn:admin1_code":"36",
    "gn:admin2_code":"160.0",
    "gn:asciiname":"Bakhtaurapur",
    "gn:country_code":"IN",
    "gn:dem":142,
    "gn:feature_class":"P",
    "gn:feature_code":"PPL",
    "gn:name":"Bakhtaur\u0101pur",
    "gn:population":0,
    "gn:timezone":"Asia/Kolkata",
    "iso:country":"IN",
    "ks:ks_alt_nam":"Baktaura pur",
    "ks:ks_name":"Baktaura Pur",
    "ks:ks_pop":200,
    "ks:ks_type":"HABITATION",
    "name:eng_x_preferred":[
        "Baktaura Pur"
    ],
    "name:eng_x_variant":[
        "Bakhtaurapur"
    ],
    "wof:name":"Baktaura Pur",
    "wof:placetype":"locality",
    "wof:population":200
},
  "geometry": {"coordinates":[79.84657300000001,26.926975],"type":"Point"}
}