{
  "type": "Feature",
  "properties": {
    "iso:country":"IN",
    "ks:ks_name":"Porlubanda",
    "ks:ks_pop":1,
    "ks:ks_type":"VILLAGE",
    "name:eng_x_preferred":[
        "Porlubanda"
    ],
    "wof:name":"Porlubanda",
    "wof:placetype":"locality",
    "wof:population":1
},
  "geometry": {"coordinates":[82.94844500000001,18.087078],"type":"Point"}
}