{
  "type": "Feature",
  "properties": {
    "iso:country":"IN",
    "ks:ks_name":"Binega Surwaya",
    "ks:ks_pop":328,
    "ks:ks_type":"HABITATION",
    "name:eng_x_preferred":[
        "Binega Surwaya"
    ],
    "wof:name":"Binega Surwaya",
    "wof:placetype":"locality",
    "wof:population":328
},
  "geometry": {"coordinates":[77.879389,25.494923],"type":"Point"}
}