{
  "type": "Feature",
  "properties": {
    "iso:country":"IN",
    "ks:ks_name":"Ranasarapur",
    "ks:ks_pop":408,
    "ks:ks_type":"VILLAGE",
    "name:eng_x_preferred":[
        "Ranasarapur"
    ],
    "wof:name":"Ranasarapur",
    "wof:placetype":"locality",
    "wof:population":408
},
  "geometry": {"coordinates":[86.196479,20.960491],"type":"Point"}
}