{
  "type": "Feature",
  "properties": {
    "iso:country":"IN",
    "ks:ks_name":"Gavthanwadi",
    "ks:ks_pop":340,
    "ks:ks_type":"HABITATION",
    "name:eng_x_preferred":[
        "Gavthanwadi"
    ],
    "wof:name":"Gavthanwadi",
    "wof:placetype":"locality",
    "wof:population":340
},
  "geometry": {"coordinates":[73.747788,15.966082],"type":"Point"}
}