{
  "type": "Feature",
  "properties": {
    "iso:country":"IN",
    "ks:ks_name":"Dangesiguda",
    "ks:ks_pop":404,
    "ks:ks_type":"VILLAGE",
    "name:eng_x_preferred":[
        "Dangesiguda"
    ],
    "wof:name":"Dangesiguda",
    "wof:placetype":"locality",
    "wof:population":404
},
  "geometry": {"coordinates":[83.724622,20.072446],"type":"Point"}
}