{
  "type": "Feature",
  "properties": {
    "iso:country":"IN",
    "ks:ks_alt_nam":"pangamaha",
    "ks:ks_name":"Pangamaha",
    "ks:ks_pop":71,
    "ks:ks_type":"HABITATION",
    "name:eng_x_preferred":[
        "Pangamaha"
    ],
    "wof:name":"Pangamaha",
    "wof:placetype":"locality",
    "wof:population":71
},
  "geometry": {"coordinates":[84.05176899999999,20.253326],"type":"Point"}
}