{
  "type": "Feature",
  "properties": {
    "iso:country":"IN",
    "ks:ks_name":"Bollinampadu Agraharam",
    "ks:ks_pop":281,
    "ks:ks_type":"HABITATION",
    "name:eng_x_preferred":[
        "Bollinampadu Agraharam"
    ],
    "wof:name":"Bollinampadu Agraharam",
    "wof:placetype":"locality",
    "wof:population":281
},
  "geometry": {"coordinates":[81.237745,16.554043],"type":"Point"}
}