{
  "type": "Feature",
  "properties": {
    "gn:admin1_code":"38.0",
    "gn:admin2_code":"358.0",
    "gn:asciiname":"Puraini",
    "gn:country_code":"IN",
    "gn:dem":255,
    "gn:feature_class":"P",
    "gn:feature_code":"PPL",
    "gn:name":"Purain\u012b",
    "gn:population":0,
    "gn:timezone":"Asia/Kolkata",
    "iso:country":"IN",
    "ks:ks_alt_nam":"Purain\u012b",
    "ks:ks_name":"Puraini",
    "ks:ks_pop":29,
    "ks:ks_type":"VILLAGE",
    "name:ceb_x_preferred":[
        "Puraini"
    ],
    "name:eng_x_preferred":[
        "Puraini"
    ],
    "name:eng_x_variant":[
        "Purain\u012b"
    ],
    "name:mai_x_preferred":[
        "\u092a\u0941\u0930\u0948\u0928\u0940"
    ],
    "name:msa_x_preferred":[
        "Puraini"
    ],
    "name:nep_x_preferred":[
        "\u092a\u0941\u0930\u0948\u0928\u0940"
    ],
    "name:new_x_preferred":[
        "\u092a\u0941\u0930\u0948\u0928\u0940"
    ],
    "name:pol_x_preferred":[
        "Puraini"
    ],
    "wof:name":"Puraini",
    "wof:placetype":"locality",
    "wof:population":29
},
  "geometry": {"coordinates":[84.33928899999999,24.069949],"type":"Point"}
}