{
  "type": "Feature",
  "properties": {
    "iso:country":"IN",
    "ks:ks_name":"Keezhthonnakkal",
    "ks:ks_pop":11638,
    "ks:ks_type":"VILLAGE",
    "name:eng_x_preferred":[
        "Keezhthonnakkal"
    ],
    "wof:name":"Keezhthonnakkal",
    "wof:placetype":"locality",
    "wof:population":11638
},
  "geometry": {"coordinates":[76.876975,8.644013],"type":"Point"}
}