{
  "type": "Feature",
  "properties": {
    "gn:admin1_code":"35",
    "gn:admin2_code":"447.0",
    "gn:asciiname":"Raksi",
    "gn:country_code":"IN",
    "gn:dem":778,
    "gn:feature_class":"P",
    "gn:feature_code":"PPL",
    "gn:name":"R\u0101ksi",
    "gn:population":0,
    "gn:timezone":"Asia/Kolkata",
    "iso:country":"IN",
    "name:dty_x_preferred":[
        "\u0930\u0915\u094d\u0938\u0940"
    ],
    "name:fra_x_preferred":[
        "Raksi"
    ],
    "name:jpn_x_preferred":[
        "\u30e9\u30ad\u30b7\u30fc"
    ],
    "name:lit_x_preferred":[
        "Rak\u0161i"
    ],
    "name:nep_x_preferred":[
        "\u0930\u0915\u094d\u0938\u0940"
    ],
    "name:nld_x_preferred":[
        "Raksi"
    ],
    "name:spa_x_preferred":[
        "Rakshi"
    ],
    "name:ukr_x_preferred":[
        "\u0420\u0430\u043a\u0441\u0456"
    ],
    "wof:name":"Raksi",
    "wof:placetype":"locality"
},
  "geometry": {"coordinates":[77.63866999999998,21.71384],"type":"Point"}
}