{
  "type": "Feature",
  "properties": {
    "gn:admin1_code":"36.0",
    "gn:admin2_code":"140.0",
    "gn:asciiname":"Vijaynagar",
    "gn:country_code":"IN",
    "gn:dem":216,
    "gn:feature_class":"P",
    "gn:feature_code":"PPL",
    "gn:name":"Vijaynagar",
    "gn:population":0,
    "gn:timezone":"Asia/Kolkata",
    "iso:country":"IN",
    "name:ara_x_preferred":[
        "\u0641\u064a\u062c\u0627\u064a\u0627\u0646\u0627\u062c\u0627\u0631"
    ],
    "name:ben_bn_x_preferred":[
        "\u09ac\u09bf\u099c\u09df\u09a8\u0997\u09b0"
    ],
    "name:ben_in_x_preferred":[
        "\u09ac\u09bf\u099c\u09df\u09a8\u0997\u09b0"
    ],
    "name:guj_x_preferred":[
        "\u0ab5\u0abf\u0a9c\u0aaf\u0aa8\u0a97\u0ab0"
    ],
    "name:hin_x_preferred":[
        "\u0935\u093f\u091c\u092f\u0928\u0917\u0930"
    ],
    "name:hin_x_variant":[
        "\u0935\u093f\u091c\u092f \u0928\u0917\u0930"
    ],
    "name:kan_x_preferred":[
        "\u0cb5\u0cbf\u0c9c\u0caf\u0ca8\u0c97\u0cb0"
    ],
    "name:mal_x_preferred":[
        "\u0d35\u0d3f\u0d1c\u0d2f\u0d28\u0d17\u0d7c"
    ],
    "name:mar_x_preferred":[
        "\u0935\u093f\u091c\u092f\u0928\u0917\u0930"
    ],
    "name:pan_x_preferred":[
        "\u0a35\u0a3f\u0a1c\u0a47\u0a28\u0a17\u0a30"
    ],
    "name:tam_x_preferred":[
        "\u0bb5\u0bbf\u0b9c\u0baf\u0ba8\u0b95\u0bb0\u0bcd"
    ],
    "name:tel_x_preferred":[
        "\u0c35\u0c3f\u0c1c\u0c2f\u0c28\u0c17\u0c30\u0c4d"
    ],
    "name:urd_x_preferred":[
        "\u0648\u062c\u06d2 \u0646\u06af\u0631"
    ],
    "wof:name":"Vijaynagar",
    "wof:placetype":"neighbourhood"
},
  "geometry": {"coordinates":[77.42964000000001,28.64539],"type":"Point"}
}