{
  "type": "Feature",
  "properties": {
    "iso:country":"IN",
    "ks:ks_name":"Guruniyal Gaon",
    "ks:ks_pop":249,
    "ks:ks_type":"HABITATION",
    "name:eng_x_preferred":[
        "Guruniyal Gaon"
    ],
    "wof:name":"Guruniyal Gaon",
    "wof:placetype":"locality",
    "wof:population":249
},
  "geometry": {"coordinates":[78.346588,30.352408],"type":"Point"}
}