{
  "type": "Feature",
  "properties": {
    "iso:country":"IN",
    "ks:ks_name":"Khurahatoli",
    "ks:ks_pop":500,
    "ks:ks_type":"HABITATION",
    "name:eng_x_preferred":[
        "Khurahatoli"
    ],
    "wof:name":"Khurahatoli",
    "wof:placetype":"locality",
    "wof:population":500
},
  "geometry": {"coordinates":[84.988043,23.246594],"type":"Point"}
}