{
  "type": "Feature",
  "properties": {
    "iso:country":"IN",
    "ks:ks_name":"Khant Faliya",
    "ks:ks_pop":1060,
    "ks:ks_type":"HABITATION",
    "name:eng_x_preferred":[
        "Khant Faliya"
    ],
    "wof:name":"Khant Faliya",
    "wof:placetype":"locality",
    "wof:population":1060
},
  "geometry": {"coordinates":[73.79691699999999,22.933361],"type":"Point"}
}