{
  "type": "Feature",
  "properties": {
    "iso:country":"IN",
    "ks:ks_name":"Thavaru Naik Tanda",
    "ks:ks_pop":300,
    "ks:ks_type":"HABITATION",
    "name:eng_x_preferred":[
        "Thavaru Naik Tanda"
    ],
    "wof:name":"Thavaru Naik Tanda",
    "wof:placetype":"locality",
    "wof:population":300
},
  "geometry": {"coordinates":[77.050973,16.930315],"type":"Point"}
}