{
  "type": "Feature",
  "properties": {
    "iso:country":"IN",
    "ks:ks_name":"Chimalathota",
    "ks:ks_pop":26,
    "ks:ks_type":"HABITATION",
    "name:eng_x_preferred":[
        "Chimalathota"
    ],
    "wof:name":"Chimalathota",
    "wof:placetype":"locality",
    "wof:population":26
},
  "geometry": {"coordinates":[82.86862000000001,18.192371],"type":"Point"}
}