{
  "type": "Feature",
  "properties": {
    "iso:country":"IN",
    "ks:ks_name":"Padda",
    "ks:ks_pop":1285,
    "ks:ks_type":"VILLAGE",
    "name:eng_x_preferred":[
        "Padda"
    ],
    "wof:name":"Padda",
    "wof:placetype":"locality",
    "wof:population":1285
},
  "geometry": {"coordinates":[75.382229,31.625368],"type":"Point"}
}