{
  "type": "Feature",
  "properties": {
    "iso:country":"IN",
    "ks:ks_name":"Bhalki",
    "ks:ks_pop":1558,
    "ks:ks_type":"VILLAGE",
    "name:eng_x_preferred":[
        "Bhalki"
    ],
    "wof:name":"Bhalki",
    "wof:placetype":"locality",
    "wof:population":1558
},
  "geometry": {"coordinates":[87.113134,24.486563],"type":"Point"}
}