{
  "type": "Feature",
  "properties": {
    "iso:country":"IN",
    "ks:ks_name":"Dhaurai",
    "ks:ks_pop":886,
    "ks:ks_type":"VILLAGE",
    "name:eng_x_preferred":[
        "Dhaurai"
    ],
    "wof:name":"Dhaurai",
    "wof:placetype":"locality",
    "wof:population":886
},
  "geometry": {"coordinates":[81.28052099999999,23.381638],"type":"Point"}
}