{
  "type": "Feature",
  "properties": {
    "iso:country":"IN",
    "ks:ks_name":"Barhati",
    "ks:ks_pop":2669,
    "ks:ks_type":"VILLAGE",
    "name:eng_x_preferred":[
        "Barhati"
    ],
    "wof:name":"Barhati",
    "wof:placetype":"neighbourhood",
    "wof:population":2669
},
  "geometry": {"coordinates":[78.10110400000001,27.942455],"type":"Point"}
}