{
  "type": "Feature",
  "properties": {
    "gn:admin1_code":"34",
    "gn:admin2_code":"233.0",
    "gn:asciiname":"Gamharia",
    "gn:country_code":"IN",
    "gn:dem":389,
    "gn:feature_class":"P",
    "gn:feature_code":"PPL",
    "gn:name":"Gamharia",
    "gn:population":0,
    "gn:timezone":"Asia/Kolkata",
    "iso:country":"IN",
    "ks:ks_name":"Gamharia",
    "ks:ks_pop":251,
    "ks:ks_type":"VILLAGE",
    "name:eng_x_preferred":[
        "Gamharia"
    ],
    "name:hif_x_preferred":[
        "Gamhari"
    ],
    "name:hin_x_preferred":[
        "\u0917\u092e\u094d\u0939\u0930\u093f\u092f\u093e"
    ],
    "wof:name":"Gamharia",
    "wof:placetype":"locality",
    "wof:population":251
},
  "geometry": {"coordinates":[83.548119,24.763015],"type":"Point"}
}