{
  "type": "Feature",
  "properties": {
    "iso:country":"IN",
    "ks:ks_name":"Mahdaniya Tola",
    "ks:ks_pop":268,
    "ks:ks_type":"HABITATION",
    "name:eng_x_preferred":[
        "Mahdaniya Tola"
    ],
    "wof:name":"Mahdaniya Tola",
    "wof:placetype":"locality",
    "wof:population":268
},
  "geometry": {"coordinates":[83.119389,24.186492],"type":"Point"}
}