{
  "type": "Feature",
  "properties": {
    "gn:admin1_code":"35",
    "gn:admin2_code":"419.0",
    "gn:asciiname":"Pirawali",
    "gn:country_code":"IN",
    "gn:dem":174,
    "gn:feature_class":"P",
    "gn:feature_code":"PPL",
    "gn:name":"Pirawali",
    "gn:population":0,
    "gn:timezone":"Asia/Kolkata",
    "iso:country":"IN",
    "wof:name":"Pirawali",
    "wof:placetype":"locality"
},
  "geometry": {"coordinates":[78.01893000000003,26.57451],"type":"Point"}
}