{
  "type": "Feature",
  "properties": {
    "iso:country":"IN",
    "ks:ks_name":"Birauridand",
    "ks:ks_pop":523,
    "ks:ks_type":"VILLAGE",
    "name:eng_x_preferred":[
        "Birauridand"
    ],
    "wof:name":"Birauridand",
    "wof:placetype":"locality",
    "wof:population":523
},
  "geometry": {"coordinates":[82.098985,23.446387],"type":"Point"}
}