{
  "type": "Feature",
  "properties": {
    "gn:admin1_code":"39.0",
    "gn:admin2_code":"60.0",
    "gn:asciiname":"Chalchala",
    "gn:country_code":"IN",
    "gn:dem":2061,
    "gn:feature_class":"P",
    "gn:feature_code":"PPL",
    "gn:name":"Chalchala",
    "gn:population":0,
    "gn:timezone":"Asia/Kolkata",
    "iso:country":"IN",
    "wof:name":"Chalchala",
    "wof:placetype":"locality"
},
  "geometry": {"coordinates":[78.19025000000001,30.43532],"type":"Point"}
}