{
  "type": "Feature",
  "properties": {
    "iso:country":"IN",
    "ks:ks_name":"Parajaburuda",
    "ks:ks_pop":304,
    "ks:ks_type":"VILLAGE",
    "name:eng_x_preferred":[
        "Parajaburuda"
    ],
    "wof:name":"Parajaburuda",
    "wof:placetype":"locality",
    "wof:population":304
},
  "geometry": {"coordinates":[82.801981,18.488726],"type":"Point"}
}