{
  "type": "Feature",
  "properties": {
    "iso:country":"IN",
    "ks:ks_name":"Mangalivanithanda",
    "ks:ks_pop":620,
    "ks:ks_type":"HABITATION",
    "name:eng_x_preferred":[
        "Mangalivanithanda"
    ],
    "wof:name":"Mangalivanithanda",
    "wof:placetype":"locality",
    "wof:population":620
},
  "geometry": {"coordinates":[79.239688,18.055627],"type":"Point"}
}