{
  "type": "Feature",
  "properties": {
    "iso:country":"IN",
    "ks:ks_alt_nam":"Mirz\u0101pur",
    "ks:ks_name":"Mirzapur",
    "ks:ks_type":"VILLAGE",
    "name:eng_x_preferred":[
        "Mirzapur"
    ],
    "name:eng_x_variant":[
        "Mirz\u0101pur"
    ],
    "wof:name":"Mirzapur",
    "wof:placetype":"locality"
},
  "geometry": {"coordinates":[82.277897,26.785521],"type":"Point"}
}