{
  "type": "Feature",
  "properties": {
    "gn:admin1_code":"19.0",
    "gn:admin2_code":"561.0",
    "gn:asciiname":"Bellikop",
    "gn:country_code":"IN",
    "gn:dem":660,
    "gn:feature_class":"P",
    "gn:feature_code":"PPL",
    "gn:name":"Bellikop",
    "gn:population":0,
    "gn:timezone":"Asia/Kolkata",
    "iso:country":"IN",
    "wof:name":"Bellikop",
    "wof:placetype":"locality"
},
  "geometry": {"coordinates":[75.57073000000003,15.40942],"type":"Point"}
}