{
  "type": "Feature",
  "properties": {
    "iso:country":"IN",
    "ks:ks_name":"Dusankarwadi",
    "ks:ks_pop":251,
    "ks:ks_type":"HABITATION",
    "name:eng_x_preferred":[
        "Dusankarwadi"
    ],
    "wof:name":"Dusankarwadi",
    "wof:placetype":"locality",
    "wof:population":251
},
  "geometry": {"coordinates":[73.553742,16.395279],"type":"Point"}
}