{
  "type": "Feature",
  "properties": {
    "gn:admin1_code":"23.0",
    "gn:admin2_code":"41.0",
    "gn:asciiname":"Tharike",
    "gn:country_code":"IN",
    "gn:dem":248,
    "gn:feature_class":"P",
    "gn:feature_code":"PPL",
    "gn:name":"Thar\u012bke",
    "gn:population":0,
    "gn:timezone":"Asia/Kolkata",
    "iso:country":"IN",
    "ks:ks_name":"Tharike",
    "ks:ks_pop":8884,
    "ks:ks_type":"URBAN",
    "ks:ks_uagg_main":0,
    "name:pan_x_preferred":[
        "\u0a25\u0a30\u0a40\u0a15\u0a47"
    ],
    "name:und_x_variant":[
        "Thar\u012bke"
    ],
    "wof:name":"Tharike",
    "wof:placetype":"neighbourhood"
},
  "geometry": {"coordinates":[75.78163000000001,30.86669],"type":"Point"}
}