{
  "type": "Feature",
  "properties": {
    "iso:country":"IN",
    "ks:ks_name":"Tahvariya",
    "ks:ks_pop":151,
    "ks:ks_type":"HABITATION",
    "name:eng_x_preferred":[
        "Tahvariya"
    ],
    "wof:name":"Tahvariya",
    "wof:placetype":"locality",
    "wof:population":151
},
  "geometry": {"coordinates":[77.84949400000001,24.297524],"type":"Point"}
}