{
  "type": "Feature",
  "properties": {
    "gn:gn_country":"IN",
    "gn:gn_fcode":"PPL",
    "gn:gn_pop":2440,
    "gn:population":2440,
    "iso:country":"IN",
    "name:bpy_x_preferred":[
        "\u0995\u09cb\u09b0\u09cd\u099f\u09b2\u09be\u09ae"
    ],
    "name:ceb_x_preferred":[
        "Kutt\u0101lam"
    ],
    "name:deu_x_preferred":[
        "Courtallam"
    ],
    "name:eng_x_preferred":[
        "Courtallam"
    ],
    "name:fra_x_preferred":[
        "Courtallam"
    ],
    "name:hin_x_preferred":[
        "\u0915\u0941\u091f\u094d\u0930\u093e\u0932\u092e"
    ],
    "name:ita_x_preferred":[
        "Courtalam"
    ],
    "name:jpn_x_preferred":[
        "\u30b3\u30fc\u30bf\u30e9\u30e0"
    ],
    "name:kan_x_preferred":[
        "\u0c95\u0cc1\u0cb0\u0ccd\u0c9f\u0cbe\u0cb2\u0cae\u0ccd"
    ],
    "name:mal_x_preferred":[
        "\u0d15\u0d41\u0d31\u0d4d\u0d31\u0d3e\u0d32\u0d02"
    ],
    "name:mar_x_preferred":[
        "\u0915\u0941\u0924\u094d\u0930\u093e\u0932\u092e \u0927\u092c\u0927\u092c\u093e"
    ],
    "name:msa_x_preferred":[
        "Courtalam"
    ],
    "name:nan_x_preferred":[
        "Courtalam"
    ],
    "name:new_x_preferred":[
        "\u0915\u094b\u0930\u094d\u091f\u0947\u0932\u093e\u092e"
    ],
    "name:nld_x_preferred":[
        "Courtallam"
    ],
    "name:por_x_preferred":[
        "Courtalam"
    ],
    "name:san_x_preferred":[
        "\u0915\u0941\u091f\u094d\u0930\u093e\u0932\u092e\u094d"
    ],
    "name:swe_x_preferred":[
        "Kutt\u0101lam"
    ],
    "name:tam_x_preferred":[
        "\u0b95\u0bc1\u0bb1\u0bcd\u0bb1\u0bbe\u0bb2\u0bae\u0bcd"
    ],
    "name:tel_x_preferred":[
        "\u0c15\u0c41\u0c1f\u0c4d\u0c30\u0c3e\u0c32\u0c02"
    ],
    "name:unk_x_variant":[
        "Courtalam"
    ],
    "name:vie_x_preferred":[
        "Courtalam"
    ],
    "name:zho_x_preferred":[
        "\u4e54\u4e4c\u5c14\u5854\u62c9\u59c6"
    ],
    "qs_pg:aaroncc":"IN",
    "qs_pg:gn_country":"IN",
    "qs_pg:gn_fcode":"PPL",
    "qs_pg:gn_pop":2440,
    "qs_pg:name":"Kuttam",
    "qs_pg:name_adm0":"India",
    "qs_pg:name_adm1":"Tamil Nadu",
    "qs_pg:photos_9k":1,
    "qs_pg:photos_9r":1,
    "qs_pg:photos_all":1,
    "qs_pg:photos_sr":0,
    "qs_pg:pop_sr":4,
    "qs_pg:qs_pg_placetype":"locality",
    "qs_pg:qs_pg_placetype_gp":"Town",
    "qs_pg:woe_adm0":23424848,
    "woe:adm0_id":23424848,
    "woe:name_adm0":"India",
    "woe:name_adm1":"Tamil Nadu",
    "woe:placetype":"Town",
    "wof:name":"Kuttam",
    "wof:placetype":"locality",
    "wof:population":2440
},
  "geometry": {"coordinates":[77.26951,8.9303],"type":"Point"}
}