{
  "type": "Feature",
  "properties": {
    "iso:country":"IN",
    "ks:ks_name":"Dhodhari",
    "ks:ks_pop":83,
    "ks:ks_type":"HABITATION",
    "name:eng_x_preferred":[
        "Dhodhari"
    ],
    "wof:name":"Dhodhari",
    "wof:placetype":"locality",
    "wof:population":83
},
  "geometry": {"coordinates":[81.80782000000001,24.593565],"type":"Point"}
}