{
  "type": "Feature",
  "properties": {
    "gn:admin1_code":"19.0",
    "gn:admin2_code":"574.0",
    "gn:asciiname":"Kadrahalli",
    "gn:country_code":"IN",
    "gn:dem":948,
    "gn:feature_class":"P",
    "gn:feature_code":"PPLL",
    "gn:name":"Kadrahalli",
    "gn:population":0,
    "gn:timezone":"Asia/Kolkata",
    "iso:country":"IN",
    "ks:ks_name":"Kadrahalli",
    "ks:ks_pop":40,
    "ks:ks_type":"HABITATION",
    "name:eng_x_preferred":[
        "Kadrahalli"
    ],
    "wof:name":"Kadrahalli",
    "wof:placetype":"locality",
    "wof:population":40
},
  "geometry": {"coordinates":[75.72411,12.734573],"type":"Point"}
}