{
  "type": "Feature",
  "properties": {
    "gn:admin1_code":"23.0",
    "gn:admin2_code":"47.0",
    "gn:asciiname":"Ullak",
    "gn:country_code":"IN",
    "gn:dem":218,
    "gn:feature_class":"P",
    "gn:feature_code":"PPL",
    "gn:name":"Ullak",
    "gn:population":0,
    "gn:timezone":"Asia/Kolkata",
    "iso:country":"IN",
    "name:pan_x_preferred":[
        "\u0a09\u0a71\u0a32\u0a15"
    ],
    "wof:name":"Ullak",
    "wof:placetype":"locality"
},
  "geometry": {"coordinates":[75.25343000000002,29.83542000000001],"type":"Point"}
}