{
  "type": "Feature",
  "properties": {
    "iso:country":"IN",
    "ks:ks_name":"Pujaripara",
    "ks:ks_pop":23,
    "ks:ks_type":"HABITATION",
    "name:eng_x_preferred":[
        "Pujaripara"
    ],
    "wof:name":"Pujaripara",
    "wof:placetype":"locality",
    "wof:population":23
},
  "geometry": {"coordinates":[82.177082,19.940648],"type":"Point"}
}