{
  "type": "Feature",
  "properties": {
    "gn:admin1_code":"12.0",
    "gn:admin2_code":"1.0",
    "gn:asciiname":"Rashanpur",
    "gn:country_code":"IN",
    "gn:dem":2023,
    "gn:feature_class":"P",
    "gn:feature_code":"PPL",
    "gn:name":"Rashanpur",
    "gn:population":0,
    "gn:timezone":"Asia/Kolkata",
    "iso:country":"IN",
    "wof:name":"Rashanpur",
    "wof:placetype":"locality"
},
  "geometry": {"coordinates":[74.07267,34.53043],"type":"Point"}
}