{
  "type": "Feature",
  "properties": {
    "iso:country":"IN",
    "ks:ks_name":"Kuttanpara Jn",
    "ks:ks_pop":657,
    "ks:ks_type":"HABITATION",
    "name:eng_x_preferred":[
        "Kuttanpara Jn"
    ],
    "wof:name":"Kuttanpara Jn",
    "wof:placetype":"locality",
    "wof:population":657
},
  "geometry": {"coordinates":[76.271711,11.2637],"type":"Point"}
}