{
  "type": "Feature",
  "properties": {
    "gn:admin1_code":"36",
    "gn:admin2_code":"159.0",
    "gn:asciiname":"Sitwanpur Pisu",
    "gn:country_code":"IN",
    "gn:dem":160,
    "gn:feature_class":"P",
    "gn:feature_code":"PPL",
    "gn:name":"Sitwanpur P\u012bsu",
    "gn:population":0,
    "gn:timezone":"Asia/Kolkata",
    "iso:country":"IN",
    "wof:name":"Sitwanpur Pisu",
    "wof:placetype":"locality"
},
  "geometry": {"coordinates":[79.37345999999999,27.3824],"type":"Point"}
}