{
  "type": "Feature",
  "properties": {
    "gn:admin1_code":"30",
    "gn:admin2_code":"250.0",
    "gn:asciiname":"Mega",
    "gn:country_code":"IN",
    "gn:dem":918,
    "gn:feature_class":"P",
    "gn:feature_code":"PPL",
    "gn:name":"Mega",
    "gn:population":0,
    "gn:timezone":"Asia/Kolkata",
    "iso:country":"IN",
    "wof:name":"Mega",
    "wof:placetype":"locality"
},
  "geometry": {"coordinates":[94.67265999999999,28.49468],"type":"Point"}
}