{
  "type": "Feature",
  "properties": {
    "gn:admin1_code":"19",
    "gn:admin2_code":"563.0",
    "gn:asciiname":"Nipli",
    "gn:country_code":"IN",
    "gn:dem":580,
    "gn:feature_class":"P",
    "gn:feature_code":"PPL",
    "gn:name":"Nipli",
    "gn:population":0,
    "gn:timezone":"Asia/Kolkata",
    "iso:country":"IN",
    "ks:ks_name":"Nipli",
    "ks:ks_pop":151,
    "ks:ks_type":"HABITATION",
    "name:eng_x_preferred":[
        "Nipli"
    ],
    "wof:name":"Nipli",
    "wof:placetype":"locality",
    "wof:population":151
},
  "geometry": {"coordinates":[74.854077,14.275523],"type":"Point"}
}