{
  "type": "Feature",
  "properties": {
    "iso:country":"IN",
    "ks:ks_name":"Khaskhal",
    "ks:ks_pop":221,
    "ks:ks_type":"VILLAGE",
    "name:eng_x_preferred":[
        "Khaskhal"
    ],
    "wof:name":"Khaskhal",
    "wof:placetype":"locality",
    "wof:population":221
},
  "geometry": {"coordinates":[79.20453500000001,30.285367],"type":"Point"}
}