{
  "type": "Feature",
  "properties": {
    "iso:country":"IN",
    "ks:ks_name":"12 P",
    "ks:ks_pop":391,
    "ks:ks_type":"VILLAGE",
    "name:eng_x_preferred":[
        "12 P"
    ],
    "wof:name":"12 P",
    "wof:placetype":"locality",
    "wof:population":391
},
  "geometry": {"coordinates":[73.137333,29.12372],"type":"Point"}
}