{
  "type": "Feature",
  "properties": {
    "iso:country":"IN",
    "ks:ks_name":"Kachartala",
    "ks:ks_pop":4,
    "ks:ks_type":"VILLAGE",
    "name:eng_x_preferred":[
        "Kachartala"
    ],
    "wof:name":"Kachartala",
    "wof:placetype":"locality",
    "wof:population":4
},
  "geometry": {"coordinates":[79.47216899999999,23.045476],"type":"Point"}
}