{
  "type": "Feature",
  "properties": {
    "gn:admin1_code":"36",
    "gn:admin2_code":"185.0",
    "gn:asciiname":"Tursi",
    "gn:country_code":"IN",
    "gn:dem":92,
    "gn:feature_class":"P",
    "gn:feature_code":"PPL",
    "gn:name":"Tursi",
    "gn:population":0,
    "gn:timezone":"Asia/Kolkata",
    "iso:country":"IN",
    "name:ara_x_preferred":[
        "\u062a\u0648\u0631\u0633\u064a"
    ],
    "name:azb_x_preferred":[
        "\u062a\u0648\u0631\u0633\u06cc"
    ],
    "name:bul_x_preferred":[
        "\u0422\u0443\u0440\u0441\u0438"
    ],
    "name:ceb_x_preferred":[
        "Tursi"
    ],
    "name:deu_x_preferred":[
        "Tursi"
    ],
    "name:epo_x_preferred":[
        "Tursi"
    ],
    "name:eus_x_preferred":[
        "Tursi"
    ],
    "name:fas_x_preferred":[
        "\u062a\u0648\u0631\u0633\u06cc"
    ],
    "name:fra_x_preferred":[
        "Tursi"
    ],
    "name:hun_x_preferred":[
        "Tursi"
    ],
    "name:hye_x_preferred":[
        "\u054f\u0578\u0582\u0580\u057d\u056b"
    ],
    "name:ina_x_preferred":[
        "Tursi"
    ],
    "name:ita_x_preferred":[
        "Tursi"
    ],
    "name:jpn_x_preferred":[
        "\u30c8\u30a5\u30eb\u30b7"
    ],
    "name:kaz_x_preferred":[
        "\u0422\u0443\u0440\u0441\u0438"
    ],
    "name:lat_x_preferred":[
        "Tursium"
    ],
    "name:lmo_x_preferred":[
        "Tursi"
    ],
    "name:msa_x_preferred":[
        "Tursi"
    ],
    "name:nap_x_preferred":[
        "Tursi"
    ],
    "name:nld_x_preferred":[
        "Tursi"
    ],
    "name:nor_x_preferred":[
        "Tursi"
    ],
    "name:pms_x_preferred":[
        "Tursi"
    ],
    "name:pol_x_preferred":[
        "Tursi"
    ],
    "name:por_x_preferred":[
        "Tursi"
    ],
    "name:ron_x_preferred":[
        "Tursi"
    ],
    "name:rus_x_preferred":[
        "\u0422\u0443\u0440\u0441\u0438"
    ],
    "name:scn_x_preferred":[
        "Tursi"
    ],
    "name:spa_x_preferred":[
        "Tursi"
    ],
    "name:srp_x_preferred":[
        "\u0422\u0443\u0440\u0437\u0438"
    ],
    "name:swe_x_preferred":[
        "Tursi"
    ],
    "name:tur_x_preferred":[
        "Tursi"
    ],
    "name:ukr_x_preferred":[
        "\u0422\u0443\u0440\u0441\u0456"
    ],
    "name:urd_x_preferred":[
        "\u062a\u0631\u0633\u06cc"
    ],
    "name:uzb_x_preferred":[
        "Tursi"
    ],
    "name:vol_x_preferred":[
        "Tursi"
    ],
    "name:war_x_preferred":[
        "Tursi"
    ],
    "name:zho_x_preferred":[
        "\u56fe\u5c14\u897f"
    ],
    "wof:name":"Tursi",
    "wof:placetype":"locality"
},
  "geometry": {"coordinates":[82.34407,26.76232000000001],"type":"Point"}
}