{
  "type": "Feature",
  "properties": {
    "iso:country":"IN",
    "ks:ks_name":"Bahadalpur",
    "ks:ks_pop":97,
    "ks:ks_type":"VILLAGE",
    "name:eng_x_preferred":[
        "Bahadalpur"
    ],
    "wof:name":"Bahadalpur",
    "wof:placetype":"locality",
    "wof:population":97
},
  "geometry": {"coordinates":[86.348726,21.163022],"type":"Point"}
}