{
  "type": "Feature",
  "properties": {
    "iso:country":"IN",
    "ks:ks_name":"Tetlakocha",
    "ks:ks_pop":138,
    "ks:ks_type":"VILLAGE",
    "name:eng_x_preferred":[
        "Tetlakocha"
    ],
    "wof:name":"Tetlakocha",
    "wof:placetype":"locality",
    "wof:population":138
},
  "geometry": {"coordinates":[86.582612,22.673416],"type":"Point"}
}