{
  "type": "Feature",
  "properties": {
    "iso:country":"IN",
    "ks:ks_name":"N. Ram Lachan",
    "ks:ks_pop":74,
    "ks:ks_type":"HABITATION",
    "name:eng_x_preferred":[
        "N. Ram Lachan"
    ],
    "wof:name":"N. Ram Lachan",
    "wof:placetype":"locality",
    "wof:population":74
},
  "geometry": {"coordinates":[78.496009,27.013781],"type":"Point"}
}