{
  "type": "Feature",
  "properties": {
    "iso:country":"IN",
    "ks:ks_name":"Melina Halerkeri",
    "ks:ks_pop":47,
    "ks:ks_type":"HABITATION",
    "name:eng_x_preferred":[
        "Melina Halerkeri"
    ],
    "wof:name":"Melina Halerkeri",
    "wof:placetype":"locality",
    "wof:population":47
},
  "geometry": {"coordinates":[74.564218,14.255052],"type":"Point"}
}