{
  "type": "Feature",
  "properties": {
    "gn:admin1_code":"36",
    "gn:admin2_code":"191.0",
    "gn:asciiname":"Madhopur",
    "gn:country_code":"IN",
    "gn:dem":86,
    "gn:feature_class":"P",
    "gn:feature_code":"PPL",
    "gn:name":"M\u0101dhopur",
    "gn:population":0,
    "gn:timezone":"Asia/Kolkata",
    "iso:country":"IN",
    "name:und_x_variant":[
        "M\u0101dhopur",
        "Dhar\u0101ng"
    ],
    "wof:name":"Madhopur",
    "wof:placetype":"neighbourhood"
},
  "geometry": {"coordinates":[82.95258,25.79498],"type":"Point"}
}