{
  "type": "Feature",
  "properties": {
    "gn:admin1_code":"39.0",
    "gn:admin2_code":"66.0",
    "gn:asciiname":"Bans Khera",
    "gn:country_code":"IN",
    "gn:dem":314,
    "gn:feature_class":"P",
    "gn:feature_code":"PPL",
    "gn:name":"B\u0101ns Khera",
    "gn:population":0,
    "gn:timezone":"Asia/Kolkata",
    "iso:country":"IN",
    "wof:name":"Bans Khera",
    "wof:placetype":"locality"
},
  "geometry": {"coordinates":[79.14173000000002,29.33186],"type":"Point"}
}