{
  "type": "Feature",
  "properties": {
    "gn:admin1_code":"19.0",
    "gn:admin2_code":"573.0",
    "gn:asciiname":"Kulgere",
    "gn:country_code":"IN",
    "gn:dem":617,
    "gn:feature_class":"P",
    "gn:feature_code":"PPL",
    "gn:name":"Kulgere",
    "gn:population":0,
    "gn:timezone":"Asia/Kolkata",
    "iso:country":"IN",
    "wof:name":"Kulgere",
    "wof:placetype":"neighbourhood"
},
  "geometry": {"coordinates":[77.11382,12.49077],"type":"Point"}
}