{
  "type": "Feature",
  "properties": {
    "iso:country":"IN",
    "ks:ks_name":"Kawadotola",
    "ks:ks_pop":235,
    "ks:ks_type":"HABITATION",
    "name:eng_x_preferred":[
        "Kawadotola"
    ],
    "wof:name":"Kawadotola",
    "wof:placetype":"locality",
    "wof:population":235
},
  "geometry": {"coordinates":[80.30681300000001,20.66686],"type":"Point"}
}