{
  "type": "Feature",
  "properties": {
    "gn:admin1_code":"40",
    "gn:admin2_code":"535.0",
    "gn:asciiname":"Maktagudam",
    "gn:country_code":"IN",
    "gn:dem":525,
    "gn:feature_class":"P",
    "gn:feature_code":"PPL",
    "gn:name":"Makt\u0101gudam",
    "gn:population":0,
    "gn:timezone":"Asia/Kolkata",
    "iso:country":"IN",
    "wof:name":"Maktagudam",
    "wof:placetype":"locality"
},
  "geometry": {"coordinates":[77.98441,17.85837],"type":"Point"}
}