{
  "type": "Feature",
  "properties": {
    "iso:country":"IN",
    "ks:ks_name":"Khandpale",
    "ks:ks_pop":563,
    "ks:ks_type":"VILLAGE",
    "name:eng_x_preferred":[
        "Khandpale"
    ],
    "wof:name":"Khandpale",
    "wof:placetype":"locality",
    "wof:population":563
},
  "geometry": {"coordinates":[73.32861800000001,18.143802],"type":"Point"}
}