{
  "type": "Feature",
  "properties": {
    "gn:admin1_code":"40.0",
    "gn:admin2_code":"538",
    "gn:asciiname":"Amrabad",
    "gn:country_code":"IN",
    "gn:dem":588,
    "gn:feature_class":"P",
    "gn:feature_code":"PPL",
    "gn:name":"Amr\u0101b\u0101d",
    "gn:population":0,
    "gn:timezone":"Asia/Kolkata",
    "iso:country":"IN",
    "name:und_x_variant":[
        "Amr\u0101b\u0101d"
    ],
    "wof:name":"Amrabad",
    "wof:placetype":"locality"
},
  "geometry": {"coordinates":[78.83338000000001,16.37612],"type":"Point"}
}