{
  "type": "Feature",
  "properties": {
    "gn:admin1_code":"40.0",
    "gn:admin2_code":"538",
    "gn:asciiname":"Amrabad",
    "gn:country_code":"IN",
    "gn:dem":588,
    "gn:feature_class":"P",
    "gn:feature_code":"PPL",
    "gn:name":"Amr\u0101b\u0101d",
    "gn:population":0,
    "gn:timezone":"Asia/Kolkata",
    "iso:country":"IN",
    "name:hin_x_preferred":[
        "\u0905\u092e\u094d\u0930\u093e\u092c\u093e\u0926"
    ],
    "name:kan_x_preferred":[
        "\u0c85\u0cae\u0ccd\u0cb0\u0cac\u0cbe\u0ca6\u0ccd"
    ],
    "name:tel_x_preferred":[
        "\u0c05\u0c2e\u0c4d\u0c30\u0c3e\u0c2c\u0c3e\u0c26\u0c4d"
    ],
    "name:und_x_variant":[
        "Amr\u0101b\u0101d"
    ],
    "wof:name":"Amrabad",
    "wof:placetype":"locality"
},
  "geometry": {"coordinates":[78.83338000000001,16.37612],"type":"Point"}
}