{
  "type": "Feature",
  "properties": {
    "iso:country":"IN",
    "ks:ks_name":"Dasanahudilu",
    "ks:ks_pop":57,
    "ks:ks_type":"HABITATION",
    "name:eng_x_preferred":[
        "Dasanahudilu"
    ],
    "wof:name":"Dasanahudilu",
    "wof:placetype":"locality",
    "wof:population":57
},
  "geometry": {"coordinates":[74.73166399999999,14.316565],"type":"Point"}
}