{
  "type": "Feature",
  "properties": {
    "iso:country":"IN",
    "ks:ks_name":"Therkukollaimedu",
    "ks:ks_pop":897,
    "ks:ks_type":"HABITATION",
    "name:eng_x_preferred":[
        "Therkukollaimedu"
    ],
    "wof:name":"Therkukollaimedu",
    "wof:placetype":"locality",
    "wof:population":897
},
  "geometry": {"coordinates":[79.155697,12.826496],"type":"Point"}
}