{
  "type": "Feature",
  "properties": {
    "iso:country":"IN",
    "ks:ks_alt_nam":"Gaikwad wasti",
    "ks:ks_name":"Gaikwad Wasti",
    "ks:ks_pop":272,
    "ks:ks_type":"HABITATION",
    "name:eng_x_preferred":[
        "Gaikwad Wasti"
    ],
    "wof:name":"Gaikwad Wasti",
    "wof:placetype":"locality",
    "wof:population":272
},
  "geometry": {"coordinates":[75.23410699999999,17.989961],"type":"Point"}
}