{
  "type": "Feature",
  "properties": {
    "gn:admin1_code":"36",
    "gn:admin2_code":"185.0",
    "gn:asciiname":"Takia",
    "gn:country_code":"IN",
    "gn:dem":91,
    "gn:feature_class":"P",
    "gn:feature_code":"PPL",
    "gn:name":"Takia",
    "gn:population":0,
    "gn:timezone":"Asia/Kolkata",
    "iso:country":"IN",
    "name:ceb_x_preferred":[
        "Takia"
    ],
    "name:deu_x_preferred":[
        "Takia"
    ],
    "name:swe_x_preferred":[
        "Takia"
    ],
    "wof:name":"Takia",
    "wof:placetype":"locality"
},
  "geometry": {"coordinates":[82.81941999999999,26.7911],"type":"Point"}
}