{
  "type": "Feature",
  "properties": {
    "iso:country":"IN",
    "ks:ks_name":"Khusalpur",
    "ks:ks_pop":150,
    "ks:ks_type":"VILLAGE",
    "name:eng_x_preferred":[
        "Khusalpur"
    ],
    "wof:name":"Khusalpur",
    "wof:placetype":"locality",
    "wof:population":150
},
  "geometry": {"coordinates":[87.670036,24.175893],"type":"Point"}
}