{
  "type": "Feature",
  "properties": {
    "gn:admin1_code":"2.0",
    "gn:admin2_code":"551.0",
    "gn:asciiname":"Appayyarazupeta",
    "gn:country_code":"IN",
    "gn:dem":169,
    "gn:feature_class":"P",
    "gn:feature_code":"PPL",
    "gn:name":"Appayyar\u0101zupeta",
    "gn:population":0,
    "gn:timezone":"Asia/Kolkata",
    "iso:country":"IN",
    "wof:name":"Appayyarazupeta",
    "wof:placetype":"locality"
},
  "geometry": {"coordinates":[79.21596,14.10226],"type":"Point"}
}