{
  "type": "Feature",
  "properties": {
    "iso:country":"IN",
    "ks:ks_name":"Kudaspur",
    "ks:ks_pop":57,
    "ks:ks_type":"VILLAGE",
    "name:eng_x_preferred":[
        "Kudaspur"
    ],
    "wof:name":"Kudaspur",
    "wof:placetype":"locality",
    "wof:population":57
},
  "geometry": {"coordinates":[76.631141,30.94553],"type":"Point"}
}