{
  "type": "Feature",
  "properties": {
    "iso:country":"IN",
    "ks:ks_name":"Shibraikro",
    "ks:ks_pop":216,
    "ks:ks_type":"HABITATION",
    "ks:ks_uagg_main":0,
    "name:eng_x_preferred":[
        "Shibraikro"
    ],
    "wof:name":"Shibraikro",
    "wof:placetype":"neighbourhood",
    "wof:population":216
},
  "geometry": {"coordinates":[92.727723,25.50435],"type":"Point"}
}