{
  "type": "Feature",
  "properties": {
    "iso:country":"IN",
    "ks:ks_name":"Dekapara",
    "ks:ks_pop":225,
    "ks:ks_type":"VILLAGE",
    "ks:ks_uagg_main":0,
    "name:eng_x_preferred":[
        "Dekapara"
    ],
    "wof:name":"Dekapara",
    "wof:placetype":"neighbourhood",
    "wof:population":225
},
  "geometry": {"coordinates":[91.126513,25.9708],"type":"Point"}
}