{
  "type": "Feature",
  "properties": {
    "gn:admin1_code":"38.0",
    "gn:admin2_code":"358.0",
    "gn:asciiname":"Buchi Lami",
    "gn:country_code":"IN",
    "gn:dem":246,
    "gn:feature_class":"P",
    "gn:feature_code":"PPL",
    "gn:name":"Buch\u012b L\u0101m\u012b",
    "gn:population":0,
    "gn:timezone":"Asia/Kolkata",
    "iso:country":"IN",
    "ks:ks_alt_nam":"Buch\u012b L\u0101m\u012b",
    "ks:ks_name":"Buchi Lami",
    "ks:ks_pop":899,
    "ks:ks_type":"VILLAGE",
    "ks:ks_uagg_main":0,
    "name:eng_x_preferred":[
        "Buchi Lami"
    ],
    "name:eng_x_variant":[
        "Buch\u012b L\u0101m\u012b"
    ],
    "wof:name":"Buchi Lami",
    "wof:placetype":"neighbourhood",
    "wof:population":899
},
  "geometry": {"coordinates":[84.11407800000001,24.19191],"type":"Point"}
}