{
  "type": "Feature",
  "properties": {
    "gn:admin1_code":"19.0",
    "gn:admin2_code":"568.0",
    "gn:asciiname":"Melinkoppa",
    "gn:country_code":"IN",
    "gn:dem":570,
    "gn:feature_class":"P",
    "gn:feature_code":"PPL",
    "gn:name":"Melinkoppa",
    "gn:population":0,
    "gn:timezone":"Asia/Kolkata",
    "iso:country":"IN",
    "ks:ks_name":"Melinakoppa",
    "ks:ks_pop":3,
    "ks:ks_type":"HABITATION",
    "name:eng_x_preferred":[
        "Melinakoppa"
    ],
    "name:eng_x_variant":[
        "Melinkoppa"
    ],
    "wof:name":"Melinakoppa",
    "wof:placetype":"locality",
    "wof:population":3
},
  "geometry": {"coordinates":[75.03270500000001,13.723638],"type":"Point"}
}