{
  "type": "Feature",
  "properties": {
    "gn:admin1_code":"11.0",
    "gn:admin2_code":"32.0",
    "gn:asciiname":"Kahala",
    "gn:country_code":"IN",
    "gn:dem":1461,
    "gn:feature_class":"P",
    "gn:feature_code":"PPL",
    "gn:name":"Kahala",
    "gn:population":0,
    "gn:timezone":"Asia/Kolkata",
    "iso:country":"IN",
    "name:ceb_x_preferred":[
        "Kahala"
    ],
    "name:ces_x_preferred":[
        "Kahala"
    ],
    "name:deu_x_preferred":[
        "Kahala"
    ],
    "name:est_x_preferred":[
        "Kahala"
    ],
    "name:fra_x_preferred":[
        "Kahala"
    ],
    "name:hye_x_preferred":[
        "\u053f\u0561\u0570\u0561\u056c\u0561"
    ],
    "name:nld_x_preferred":[
        "Kahala"
    ],
    "name:pol_x_preferred":[
        "Kahala"
    ],
    "name:rus_x_preferred":[
        "\u041a\u0430\u0445\u0430\u043b\u0430"
    ],
    "name:swe_x_preferred":[
        "Kahala"
    ],
    "name:ukr_x_preferred":[
        "\u041a\u0430\u0433\u0430\u043b\u0430"
    ],
    "name:vol_x_preferred":[
        "Kahala"
    ],
    "wof:name":"Kahala",
    "wof:placetype":"locality"
},
  "geometry": {"coordinates":[77.44147,30.96317],"type":"Point"}
}