{
  "type": "Feature",
  "properties": {
    "gn:admin1_code":"24.0",
    "gn:admin2_code":"113",
    "gn:asciiname":"Dadu",
    "gn:country_code":"IN",
    "gn:dem":252,
    "gn:feature_class":"P",
    "gn:feature_code":"PPL",
    "gn:name":"Dadu",
    "gn:population":0,
    "gn:timezone":"Asia/Kolkata",
    "iso:country":"IN",
    "name:ceb_x_preferred":[
        "Dadu"
    ],
    "name:ces_x_preferred":[
        "Ta-tu"
    ],
    "name:deu_x_preferred":[
        "Dadu"
    ],
    "name:fra_x_preferred":[
        "Dadu"
    ],
    "name:ind_x_preferred":[
        "Dadu"
    ],
    "name:nld_x_preferred":[
        "Dadu"
    ],
    "name:nor_x_preferred":[
        "Dadu"
    ],
    "name:scn_x_preferred":[
        "Dadu"
    ],
    "name:swe_x_preferred":[
        "Dadu"
    ],
    "wof:name":"Dadu",
    "wof:placetype":"locality"
},
  "geometry": {"coordinates":[72.13529,26.92214],"type":"Point"}
}