{
  "type": "Feature",
  "properties": {
    "iso:country":"IN",
    "ks:ks_name":"Bajakresal",
    "ks:ks_pop":100,
    "ks:ks_type":"HABITATION",
    "name:eng_x_preferred":[
        "Bajakresal"
    ],
    "wof:name":"Bajakresal",
    "wof:placetype":"locality",
    "wof:population":100
},
  "geometry": {"coordinates":[75.28565399999999,12.998616],"type":"Point"}
}