{
  "type": "Feature",
  "properties": {
    "iso:country":"IN",
    "ks:ks_alt_nam":"BHULIYAN",
    "ks:ks_name":"Bhuliyan",
    "ks:ks_pop":673,
    "ks:ks_type":"HABITATION",
    "name:eng_x_preferred":[
        "Bhuliyan"
    ],
    "wof:name":"Bhuliyan",
    "wof:placetype":"locality",
    "wof:population":673
},
  "geometry": {"coordinates":[82.28498,25.42453],"type":"Point"}
}