{
  "type": "Feature",
  "properties": {
    "gn:admin1_code":"19.0",
    "gn:admin2_code":"582.0",
    "gn:asciiname":"Velluru Appayyanadinne",
    "gn:country_code":"IN",
    "gn:dem":852,
    "gn:feature_class":"P",
    "gn:feature_code":"PPL",
    "gn:name":"Velluru Appayyanadinne",
    "gn:population":0,
    "gn:timezone":"Asia/Kolkata",
    "iso:country":"IN",
    "wof:name":"Velluru Appayyanadinne",
    "wof:placetype":"neighbourhood"
},
  "geometry": {"coordinates":[77.69916000000001,13.6489],"type":"Point"}
}