{
  "type": "Feature",
  "properties": {
    "iso:country":"IN",
    "ks:ks_name":"Satpoutia",
    "ks:ks_pop":636,
    "ks:ks_type":"HABITATION",
    "name:eng_x_preferred":[
        "Satpoutia"
    ],
    "wof:name":"Satpoutia",
    "wof:placetype":"locality",
    "wof:population":636
},
  "geometry": {"coordinates":[87.064273,21.938536],"type":"Point"}
}