{
  "type": "Feature",
  "properties": {
    "gn:admin1_code":"36.0",
    "gn:admin2_code":"152.0",
    "gn:asciiname":"Ratauli",
    "gn:country_code":"IN",
    "gn:dem":155,
    "gn:feature_class":"P",
    "gn:feature_code":"PPL",
    "gn:name":"Ratauli",
    "gn:population":0,
    "gn:timezone":"Asia/Kolkata",
    "iso:country":"IN",
    "name:ceb_x_preferred":[
        "Ratauli"
    ],
    "name:mai_x_preferred":[
        "\u0930\u0924\u094c\u0932\u0940"
    ],
    "name:msa_x_preferred":[
        "Ratauli"
    ],
    "name:new_x_preferred":[
        "\u0930\u0924\u094c\u0932\u0940"
    ],
    "name:pol_x_preferred":[
        "Ratauli"
    ],
    "wof:name":"Ratauli",
    "wof:placetype":"locality"
},
  "geometry": {"coordinates":[79.81978000000002,28.00511],"type":"Point"}
}