{
  "type": "Feature",
  "properties": {
    "gn:admin1_code":"19.0",
    "gn:admin2_code":"571.0",
    "gn:asciiname":"Nilammanahalli",
    "gn:country_code":"IN",
    "gn:dem":592,
    "gn:feature_class":"P",
    "gn:feature_code":"PPL",
    "gn:name":"N\u012blammanahalli",
    "gn:population":0,
    "gn:timezone":"Asia/Kolkata",
    "iso:country":"IN",
    "wof:name":"Nilammanahalli",
    "wof:placetype":"locality"
},
  "geometry": {"coordinates":[77.26812,14.22909],"type":"Point"}
}