{
  "type": "Feature",
  "properties": {
    "iso:country":"IN",
    "ks:ks_alt_nam":"Dumudum\u0101",
    "ks:ks_name":"Dumuduma",
    "ks:ks_pop":184,
    "ks:ks_type":"VILLAGE",
    "name:eng_x_preferred":[
        "Dumuduma"
    ],
    "name:eng_x_variant":[
        "Dumudum\u0101"
    ],
    "wof:name":"Dumuduma",
    "wof:placetype":"locality",
    "wof:population":184
},
  "geometry": {"coordinates":[85.168322,21.01811],"type":"Point"}
}