{
  "type": "Feature",
  "properties": {
    "gn:admin1_code":"29.0",
    "gn:admin2_code":"242.0",
    "gn:asciiname":"Kamigaon",
    "gn:country_code":"IN",
    "gn:dem":957,
    "gn:feature_class":"P",
    "gn:feature_code":"PPL",
    "gn:name":"K\u0101m\u012bgaon",
    "gn:population":0,
    "gn:timezone":"Asia/Kolkata",
    "iso:country":"IN",
    "wof:name":"Kamigaon",
    "wof:placetype":"locality"
},
  "geometry": {"coordinates":[88.2788,27.16336],"type":"Point"}
}