{
  "type": "Feature",
  "properties": {
    "iso:country":"IN",
    "ks:ks_name":"Sarulai",
    "ks:ks_pop":0,
    "ks:ks_type":"VILLAGE",
    "name:eng_x_preferred":[
        "Sarulai"
    ],
    "wof:name":"Sarulai",
    "wof:placetype":"locality",
    "wof:population":0
},
  "geometry": {"coordinates":[84.04374300000001,20.281158],"type":"Point"}
}