{
  "type": "Feature",
  "properties": {
    "gn:admin1_code":"24.0",
    "gn:admin2_code":"123.0",
    "gn:asciiname":"Kundian",
    "gn:country_code":"IN",
    "gn:dem":466,
    "gn:feature_class":"P",
    "gn:feature_code":"PPL",
    "gn:name":"K\u016bndian",
    "gn:population":0,
    "gn:timezone":"Asia/Kolkata",
    "iso:country":"IN",
    "name:ben_x_preferred":[
        "\u0995\u09c1\u09a8\u09cd\u09a6\u09bf\u09af\u09bc\u09be\u09a8"
    ],
    "name:ceb_x_preferred":[
        "Kundi\u0101n"
    ],
    "name:fas_x_preferred":[
        "\u06a9\u0646\u062f\u06cc\u0627\u0646"
    ],
    "name:fra_x_preferred":[
        "Kundian"
    ],
    "name:pol_x_preferred":[
        "Kundian"
    ],
    "name:por_x_preferred":[
        "Kundian"
    ],
    "name:spa_x_preferred":[
        "Kundian"
    ],
    "name:urd_x_preferred":[
        "\u06a9\u0646\u062f\u06cc\u0627\u06ba"
    ],
    "wof:name":"Kundian",
    "wof:placetype":"locality"
},
  "geometry": {"coordinates":[74.30405,25.02588],"type":"Point"}
}