{
  "type": "Feature",
  "properties": {
    "gn:admin1_code":"24.0",
    "gn:admin2_code":"123.0",
    "gn:asciiname":"Kundian",
    "gn:country_code":"IN",
    "gn:dem":466,
    "gn:feature_class":"P",
    "gn:feature_code":"PPL",
    "gn:name":"K\u016bndian",
    "gn:population":0,
    "gn:timezone":"Asia/Kolkata",
    "iso:country":"IN",
    "name:ben_x_preferred":[
        "\u0995\u09c1\u09a8\u09cd\u09a6\u09bf\u09af\u09bc\u09be\u09a8"
    ],
    "name:ceb_x_preferred":[
        "Kundi\u0101n"
    ],
    "name:deu_x_preferred":[
        "Kundian"
    ],
    "name:ell_x_preferred":[
        "\u039a\u03bf\u03cd\u03bd\u03c4\u03b9\u03b1\u03bd"
    ],
    "name:fas_x_preferred":[
        "\u06a9\u0646\u062f\u06cc\u0627\u0646"
    ],
    "name:fra_x_preferred":[
        "Kundian"
    ],
    "name:heb_x_preferred":[
        "\u05e7\u05d5\u05e0\u05d3\u05d9\u05d0\u05df"
    ],
    "name:hin_x_preferred":[
        "\u0915\u0902\u0921\u093f\u092f\u093e\u0928"
    ],
    "name:hun_x_preferred":[
        "Kundian"
    ],
    "name:ind_x_preferred":[
        "Kundian"
    ],
    "name:ita_x_preferred":[
        "Kundian"
    ],
    "name:jpn_x_preferred":[
        "\u30af\u30f3\u30c7\u30a3\u30a2\u30f3"
    ],
    "name:kor_x_preferred":[
        "\ucfe4\ub514\uc548"
    ],
    "name:pol_x_preferred":[
        "Kundian"
    ],
    "name:por_x_preferred":[
        "Kundian"
    ],
    "name:rus_x_preferred":[
        "\u041a\u0443\u043d\u0434\u0438\u0430\u043d"
    ],
    "name:spa_x_preferred":[
        "Kundian"
    ],
    "name:swe_x_preferred":[
        "Kundian"
    ],
    "name:tur_x_preferred":[
        "Kundian"
    ],
    "name:ukr_x_preferred":[
        "\u041a\u0443\u043d\u0434\u0456\u0430\u043d"
    ],
    "name:urd_x_preferred":[
        "\u06a9\u0646\u062f\u06cc\u0627\u06ba"
    ],
    "name:vie_x_preferred":[
        "Kundian"
    ],
    "name:zho_cn_x_preferred":[
        "\u8d21\u8fea\u626c"
    ],
    "name:zho_tw_x_preferred":[
        "\u6606\u7538"
    ],
    "wof:name":"Kundian",
    "wof:placetype":"locality"
},
  "geometry": {"coordinates":[74.30405,25.02588],"type":"Point"}
}