{
  "type": "Feature",
  "properties": {
    "iso:country":"IN",
    "ks:ks_name":"Naranpur",
    "ks:ks_pop":610,
    "ks:ks_type":"VILLAGE",
    "ks:ks_uagg_main":0,
    "name:eng_x_preferred":[
        "Naranpur"
    ],
    "wof:name":"Naranpur",
    "wof:placetype":"neighbourhood",
    "wof:population":610
},
  "geometry": {"coordinates":[85.844032,20.437707],"type":"Point"}
}