{
  "type": "Feature",
  "properties": {
    "iso:country":"IN",
    "ks:ks_name":"Kashyappur",
    "ks:ks_pop":1722,
    "ks:ks_type":"VILLAGE",
    "ks:ks_uagg_main":0,
    "name:eng_x_preferred":[
        "Kashyappur"
    ],
    "wof:name":"Kashyappur",
    "wof:placetype":"locality",
    "wof:population":1722
},
  "geometry": {"coordinates":[88.00988099999999,22.472414],"type":"Point"}
}