{
  "type": "Feature",
  "properties": {
    "iso:country":"IN",
    "ks:ks_name":"Kakkadde",
    "ks:ks_pop":26,
    "ks:ks_type":"HABITATION",
    "name:eng_x_preferred":[
        "Kakkadde"
    ],
    "wof:name":"Kakkadde",
    "wof:placetype":"locality",
    "wof:population":26
},
  "geometry": {"coordinates":[75.328971,13.381858],"type":"Point"}
}