{
  "type": "Feature",
  "properties": {
    "gn:admin1_code":"36",
    "gn:admin2_code":"155.0",
    "gn:asciiname":"Parsa",
    "gn:country_code":"IN",
    "gn:dem":135,
    "gn:feature_class":"P",
    "gn:feature_code":"PPL",
    "gn:name":"Parsa",
    "gn:population":0,
    "gn:timezone":"Asia/Kolkata",
    "iso:country":"IN",
    "name:bak_x_preferred":[
        "\u041f\u0430\u0440\u0441\u0430"
    ],
    "name:cat_x_preferred":[
        "Parsuwaix"
    ],
    "name:ceb_x_preferred":[
        "Parsa"
    ],
    "name:deu_x_preferred":[
        "Parsa"
    ],
    "name:fas_x_preferred":[
        "\u067e\u0627\u0631\u0633\u0627"
    ],
    "name:hin_x_preferred":[
        "\u092a\u0930\u094d\u0938\u093e"
    ],
    "name:rus_x_preferred":[
        "\u041f\u0430\u0440\u0441\u0430"
    ],
    "name:swe_x_preferred":[
        "Parsa"
    ],
    "wof:name":"Parsa",
    "wof:placetype":"locality"
},
  "geometry": {"coordinates":[80.63789,27.16612000000001],"type":"Point"}
}