{
  "type": "Feature",
  "properties": {
    "iso:country":"IN",
    "ks:ks_alt_nam":"B\u0101l\u0101mb\u0101puram",
    "ks:ks_name":"Balambapuram",
    "ks:ks_type":"VILLAGE",
    "ks:ks_uagg_main":0,
    "name:eng_x_preferred":[
        "Balambapuram"
    ],
    "name:eng_x_variant":[
        "B\u0101l\u0101mb\u0101puram"
    ],
    "wof:name":"Balambapuram",
    "wof:placetype":"neighbourhood"
},
  "geometry": {"coordinates":[78.072694,10.976583],"type":"Point"}
}