{
  "type": "Feature",
  "properties": {
    "gn:admin1_code":"35",
    "gn:admin2_code":"436.0",
    "gn:asciiname":"Mawana",
    "gn:country_code":"IN",
    "gn:dem":424,
    "gn:feature_class":"P",
    "gn:feature_code":"PPL",
    "gn:name":"Maw\u0101na",
    "gn:population":0,
    "gn:timezone":"Asia/Kolkata",
    "iso:country":"IN",
    "name:und_x_variant":[
        "Maw\u0101na",
        "Mohana"
    ],
    "wof:name":"Mawana",
    "wof:placetype":"locality"
},
  "geometry": {"coordinates":[76.37206999999999,23.69292],"type":"Point"}
}