{
  "type": "Feature",
  "properties": {
    "iso:country":"IN",
    "qs:name":"Narwal",
    "qs:name_adm0":"India",
    "qs:name_adm1":"Madhya Pradesh",
    "qs:photos":1,
    "qs:photos_1k":1,
    "qs:photos_9k":1,
    "qs:photos_9r":1,
    "qs:photos_all":1,
    "qs:photos_sr":1,
    "qs:placetype":"Suburb",
    "qs:pop_sr":"0",
    "wd:wordcount":19,
    "wof:name":"Narwal",
    "wof:placetype":"neighbourhood"
},
  "geometry": {"coordinates":[75.865112,22.721221],"type":"Point"}
}