{
  "type": "Feature",
  "properties": {
    "gn:admin1_code":"16",
    "gn:admin2_code":"506.0",
    "gn:asciiname":"Salebardi",
    "gn:country_code":"IN",
    "gn:dem":252,
    "gn:feature_class":"P",
    "gn:feature_code":"PPL",
    "gn:name":"Salebardi",
    "gn:population":0,
    "gn:timezone":"Asia/Kolkata",
    "iso:country":"IN",
    "ks:ks_name":"Salebardi",
    "ks:ks_type":"VILLAGE",
    "name:eng_x_preferred":[
        "Salebardi"
    ],
    "wof:name":"Salebardi",
    "wof:placetype":"locality"
},
  "geometry": {"coordinates":[79.660073,21.134792],"type":"Point"}
}