{
  "type": "Feature",
  "properties": {
    "iso:country":"IN",
    "ks:ks_name":"Ketolira Devaiah Family",
    "ks:ks_pop":49,
    "ks:ks_type":"HABITATION",
    "name:eng_x_preferred":[
        "Ketolira Devaiah Family"
    ],
    "wof:name":"Ketolira Devaiah Family",
    "wof:placetype":"locality",
    "wof:population":49
},
  "geometry": {"coordinates":[75.694444,12.391389],"type":"Point"}
}