{
  "type": "Feature",
  "properties": {
    "iso:country":"IN",
    "ks:ks_name":"Chikhli",
    "ks:ks_pop":38,
    "ks:ks_type":"VILLAGE",
    "name:eng_x_preferred":[
        "Chikhli"
    ],
    "name:hin_x_preferred":[
        "\u091a\u093f\u0916\u0932\u0940"
    ],
    "name:mar_x_preferred":[
        "\u091a\u093f\u0916\u0932\u0940"
    ],
    "wof:name":"Chikhli",
    "wof:placetype":"locality",
    "wof:population":38
},
  "geometry": {"coordinates":[82.232643,23.638082],"type":"Point"}
}