{
  "type": "Feature",
  "properties": {
    "iso:country":"IN",
    "ks:ks_name":"Satjalia",
    "ks:ks_pop":8243,
    "ks:ks_type":"VILLAGE",
    "name:eng_x_preferred":[
        "Satjalia"
    ],
    "wof:name":"Satjalia",
    "wof:placetype":"locality",
    "wof:population":8243
},
  "geometry": {"coordinates":[88.872242,22.157643],"type":"Point"}
}