{
  "type": "Feature",
  "properties": {
    "gn:admin1_code":"23.0",
    "gn:admin2_code":"49.0",
    "gn:asciiname":"Thathi",
    "gn:country_code":"IN",
    "gn:dem":224,
    "gn:feature_class":"P",
    "gn:feature_code":"PPL",
    "gn:name":"Thathi",
    "gn:population":0,
    "gn:timezone":"Asia/Kolkata",
    "iso:country":"IN",
    "ks:ks_name":"Thathi",
    "ks:ks_type":"VILLAGE",
    "name:eng_x_preferred":[
        "Thathi"
    ],
    "name:fas_x_preferred":[
        "\u062a\u0647\u062a\u06cc"
    ],
    "name:pnb_x_preferred":[
        "\u0679\u06be\u0679\u06be\u06cc"
    ],
    "name:urd_x_preferred":[
        "\u0679\u06be\u0679\u06cc"
    ],
    "wof:name":"Thathi",
    "wof:placetype":"locality"
},
  "geometry": {"coordinates":[74.61246199999999,31.70711],"type":"Point"}
}