{
  "type": "Feature",
  "properties": {
    "iso:country":"IN",
    "ks:ks_name":"Mhakalwasti",
    "ks:ks_pop":532,
    "ks:ks_type":"HABITATION",
    "name:eng_x_preferred":[
        "Mhakalwasti"
    ],
    "wof:name":"Mhakalwasti",
    "wof:placetype":"locality",
    "wof:population":532
},
  "geometry": {"coordinates":[75.205997,17.344914],"type":"Point"}
}