{
  "type": "Feature",
  "properties": {
    "gn:admin1_code":"3.0",
    "gn:admin2_code":"319.0",
    "gn:asciiname":"Pakhriguri",
    "gn:country_code":"IN",
    "gn:dem":41,
    "gn:feature_class":"P",
    "gn:feature_code":"PPL",
    "gn:name":"P\u0101khriguri",
    "gn:population":0,
    "gn:timezone":"Asia/Kolkata",
    "iso:country":"IN",
    "ks:ks_name":"Pakhiriguri",
    "ks:ks_pop":834,
    "ks:ks_type":"VILLAGE",
    "ks:ks_uagg_main":0,
    "name:eng_x_preferred":[
        "Pakhiriguri"
    ],
    "wof:name":"Pakhiriguri",
    "wof:placetype":"neighbourhood",
    "wof:population":834
},
  "geometry": {"coordinates":[90.706295,26.388166],"type":"Point"}
}