{
  "type": "Feature",
  "properties": {
    "gn:admin1_code":"11.0",
    "gn:admin2_code":"27.0",
    "gn:asciiname":"Salo",
    "gn:country_code":"IN",
    "gn:dem":1412,
    "gn:feature_class":"P",
    "gn:feature_code":"PPL",
    "gn:name":"Salo",
    "gn:population":0,
    "gn:timezone":"Asia/Kolkata",
    "iso:country":"IN",
    "wof:name":"Salo",
    "wof:placetype":"locality"
},
  "geometry": {"coordinates":[77.15675,31.71112],"type":"Point"}
}