{
  "type": "Feature",
  "properties": {
    "iso:country":"IN",
    "ks:ks_name":"Simlaguri Parepara",
    "ks:ks_pop":250,
    "ks:ks_type":"HABITATION",
    "name:eng_x_preferred":[
        "Simlaguri Parepara"
    ],
    "wof:name":"Simlaguri Parepara",
    "wof:placetype":"locality",
    "wof:population":250
},
  "geometry": {"coordinates":[90.66367200000001,26.405155],"type":"Point"}
}