{
  "type": "Feature",
  "properties": {
    "iso:country":"IN",
    "ks:ks_name":"Bhogapur",
    "ks:ks_pop":535,
    "ks:ks_type":"VILLAGE",
    "name:eng_x_preferred":[
        "Bhogapur"
    ],
    "wof:name":"Bhogapur",
    "wof:placetype":"locality",
    "wof:population":535
},
  "geometry": {"coordinates":[85.572686,20.034234],"type":"Point"}
}