{
  "type": "Feature",
  "properties": {
    "gn:admin1_code":"19.0",
    "gn:admin2_code":"581.0",
    "gn:asciiname":"Gundamnatta",
    "gn:country_code":"IN",
    "gn:dem":825,
    "gn:feature_class":"P",
    "gn:feature_code":"PPL",
    "gn:name":"Gundamnatta",
    "gn:population":0,
    "gn:timezone":"Asia/Kolkata",
    "iso:country":"IN",
    "wof:name":"Gundamnatta",
    "wof:placetype":"locality"
},
  "geometry": {"coordinates":[78.20610000000001,13.29631],"type":"Point"}
}