{
  "type": "Feature",
  "properties": {
    "iso:country":"IN",
    "ks:ks_name":"Mishran Tola",
    "ks:ks_pop":305,
    "ks:ks_type":"HABITATION",
    "name:eng_x_preferred":[
        "Mishran Tola"
    ],
    "wof:name":"Mishran Tola",
    "wof:placetype":"locality",
    "wof:population":305
},
  "geometry": {"coordinates":[84.251994,26.620424],"type":"Point"}
}