{
  "type": "Feature",
  "properties": {
    "iso:country":"IN",
    "ks:ks_name":"Chongkhili 2",
    "ks:ks_pop":192,
    "ks:ks_type":"HABITATION",
    "name:eng_x_preferred":[
        "Chongkhili 2"
    ],
    "wof:name":"Chongkhili 2",
    "wof:placetype":"locality",
    "wof:population":192
},
  "geometry": {"coordinates":[92.720405,25.624987],"type":"Point"}
}