{
  "type": "Feature",
  "properties": {
    "gn:admin1_code":"37",
    "gn:admin2_code":"409.0",
    "gn:asciiname":"Newai",
    "gn:country_code":"IN",
    "gn:dem":318,
    "gn:feature_class":"P",
    "gn:feature_code":"PPL",
    "gn:name":"Newai",
    "gn:population":0,
    "gn:timezone":"Asia/Kolkata",
    "iso:country":"IN",
    "name:ben_x_preferred":[
        "\u09a8\u09bf\u0993\u09af\u09bc\u09be\u0987"
    ],
    "name:bpy_x_preferred":[
        "\u09a8\u09bf\u09f1\u09be\u0987"
    ],
    "name:ceb_x_preferred":[
        "Niwai"
    ],
    "name:hin_x_preferred":[
        "\u0928\u093f\u0935\u093e\u0908"
    ],
    "name:ita_x_preferred":[
        "Niwai"
    ],
    "name:msa_x_preferred":[
        "Niwai"
    ],
    "name:new_x_preferred":[
        "\u0928\u093f\u0935\u093e\u0908"
    ],
    "name:ori_x_preferred":[
        "\u0b28\u0b3f\u0b71\u0b3e\u0b07"
    ],
    "name:pnb_x_preferred":[
        "\u0646\u06cc\u0648\u0627\u0626\u06cc"
    ],
    "name:por_x_preferred":[
        "Niwai"
    ],
    "name:swe_x_preferred":[
        "Niwai"
    ],
    "name:urd_x_preferred":[
        "\u0646\u06cc\u0648\u0627\u0626\u06cc"
    ],
    "name:vie_x_preferred":[
        "Niwai"
    ],
    "name:zho_x_preferred":[
        "\u5c3c\u74e6\u4f0a"
    ],
    "wof:name":"Newai",
    "wof:placetype":"locality"
},
  "geometry": {"coordinates":[81.36407,21.148],"type":"Point"}
}