{
  "type": "Feature",
  "properties": {
    "iso:country":"IN",
    "ks:ks_name":"Bikrampur Alias Mainjariya",
    "ks:ks_pop":1381,
    "ks:ks_type":"VILLAGE",
    "name:eng_x_preferred":[
        "Bikrampur Alias Mainjariya"
    ],
    "wof:name":"Bikrampur Alias Mainjariya",
    "wof:placetype":"locality",
    "wof:population":1381
},
  "geometry": {"coordinates":[86.478331,22.466203],"type":"Point"}
}