{
  "type": "Feature",
  "properties": {
    "iso:country":"IN",
    "qs:name":"Tagore Garden Extension",
    "qs:name_adm0":"India",
    "qs:name_adm1":"Delhi",
    "qs:photos":17,
    "qs:photos_1k":3,
    "qs:photos_9k":1,
    "qs:photos_9r":1,
    "qs:photos_all":17,
    "qs:photos_sr":1,
    "qs:placetype":"Suburb",
    "qs:pop_sr":"0",
    "wd:wordcount":33,
    "wof:name":"Tagore Garden Extension",
    "wof:placetype":"neighbourhood"
},
  "geometry": {"coordinates":[77.114796,28.651578],"type":"Point"}
}