{
  "type": "Feature",
  "properties": {
    "iso:country":"IN",
    "name:ben_x_preferred":[
        "\u099f\u09c7\u0997\u09cb\u09b0 \u0997\u09be\u09b0\u09cd\u09a1\u09c7\u09a8 \u09ae\u09c7\u099f\u09cd\u09b0\u09cb \u09b8\u09cd\u099f\u09c7\u09b6\u09a8"
    ],
    "name:eng_x_preferred":[
        "Tagore Garden metro station"
    ],
    "name:hin_x_preferred":[
        "\u091f\u0948\u0917\u094b\u0930 \u0917\u093e\u0930\u094d\u0921\u0928"
    ],
    "name:jpn_x_preferred":[
        "\u30bf\u30b4\u30fc\u30eb\u516c\u5712\u99c5"
    ],
    "name:kor_x_preferred":[
        "\ud0c0\uace0\ub974 \uac00\ub4e0 \uc5ed"
    ],
    "name:zho_x_preferred":[
        "\u6cf0\u6208\u723e\u82b1\u5712\u7ad9"
    ],
    "qs:name":"Tagore Garden Extension",
    "qs:name_adm0":"India",
    "qs:name_adm1":"Delhi",
    "qs:photos":17,
    "qs:photos_1k":3,
    "qs:photos_9k":1,
    "qs:photos_9r":1,
    "qs:photos_all":17,
    "qs:photos_sr":1,
    "qs:placetype":"Suburb",
    "qs:pop_sr":"0",
    "wd:wordcount":33,
    "wof:name":"Tagore Garden Extension",
    "wof:placetype":"neighbourhood"
},
  "geometry": {"coordinates":[77.114796,28.651578],"type":"Point"}
}