{
  "type": "Feature",
  "properties": {
    "iso:country":"IN",
    "ks:ks_name":"Pulikkadu",
    "ks:ks_pop":2493,
    "ks:ks_type":"HABITATION",
    "name:eng_x_preferred":[
        "Pulikkadu"
    ],
    "wof:name":"Pulikkadu",
    "wof:placetype":"locality",
    "wof:population":2493
},
  "geometry": {"coordinates":[76.009418,10.759848],"type":"Point"}
}