{
  "type": "Feature",
  "properties": {
    "iso:country":"IN",
    "ks:ks_name":"Chhotekawali",
    "ks:ks_pop":799,
    "ks:ks_type":"VILLAGE",
    "ks:ks_uagg_main":0,
    "name:eng_x_preferred":[
        "Chhotekawali"
    ],
    "wof:name":"Chhotekawali",
    "wof:placetype":"neighbourhood",
    "wof:population":799
},
  "geometry": {"coordinates":[82.033103,18.932531],"type":"Point"}
}