{
  "type": "Feature",
  "properties": {
    "iso:country":"IN",
    "ks:ks_name":"Nachikutti R.F.",
    "ks:ks_pop":1840,
    "ks:ks_type":"VILLAGE",
    "name:eng_x_preferred":[
        "Nachikutti R.F."
    ],
    "wof:name":"Nachikutti R.F.",
    "wof:placetype":"locality",
    "wof:population":1840
},
  "geometry": {"coordinates":[78.46432799999999,11.842779],"type":"Point"}
}