{
  "type": "Feature",
  "properties": {
    "gn:admin1_code":"24",
    "gn:admin2_code":"121.0",
    "gn:asciiname":"Phalinda",
    "gn:country_code":"IN",
    "gn:dem":324,
    "gn:feature_class":"P",
    "gn:feature_code":"PPL",
    "gn:name":"Ph\u0101linda",
    "gn:population":0,
    "gn:timezone":"Asia/Kolkata",
    "iso:country":"IN",
    "wof:name":"Phalinda",
    "wof:placetype":"locality"
},
  "geometry": {"coordinates":[75.37546,25.51939],"type":"Point"}
}