{
  "type": "Feature",
  "properties": {
    "iso:country":"IN",
    "ks:ks_name":"Firozpur Amrol Bila Ahatmali",
    "ks:ks_pop":543,
    "ks:ks_type":"VILLAGE",
    "name:eng_x_preferred":[
        "Firozpur Amrol Bila Ahatmali"
    ],
    "wof:name":"Firozpur Amrol Bila Ahatmali",
    "wof:placetype":"locality",
    "wof:population":543
},
  "geometry": {"coordinates":[78.57610699999999,29.376448],"type":"Point"}
}