{
  "type": "Feature",
  "properties": {
    "gn:admin1_code":"2.0",
    "gn:admin2_code":"548.0",
    "gn:asciiname":"Datlavaripalem",
    "gn:country_code":"IN",
    "gn:dem":82,
    "gn:feature_class":"P",
    "gn:feature_code":"PPL",
    "gn:name":"Datlav\u0101rip\u0101lem",
    "gn:population":0,
    "gn:timezone":"Asia/Kolkata",
    "iso:country":"IN",
    "ks:ks_name":"Kdatlavaripalem",
    "ks:ks_pop":385,
    "ks:ks_type":"HABITATION",
    "name:eng_x_preferred":[
        "Kdatlavaripalem"
    ],
    "name:eng_x_variant":[
        "Datlavaripalem"
    ],
    "wof:name":"Kdatlavaripalem",
    "wof:placetype":"locality",
    "wof:population":385
},
  "geometry": {"coordinates":[79.76372499999999,15.954619],"type":"Point"}
}