{
  "type": "Feature",
  "properties": {
    "gn:admin1_code":"25.0",
    "gn:admin2_code":"631.0",
    "gn:asciiname":"Pachavampatti Paratheruvu",
    "gn:country_code":"IN",
    "gn:dem":450,
    "gn:feature_class":"P",
    "gn:feature_code":"PPL",
    "gn:name":"Pachavampatti Paratheruvu",
    "gn:population":0,
    "gn:timezone":"Asia/Kolkata",
    "iso:country":"IN",
    "wof:name":"Pachavampatti Paratheruvu",
    "wof:placetype":"locality"
},
  "geometry": {"coordinates":[78.24169000000001,12.32242],"type":"Point"}
}