{
  "type": "Feature",
  "properties": {
    "iso:country":"IN",
    "ks:ks_name":"Borosupa",
    "ks:ks_pop":798,
    "ks:ks_type":"HABITATION",
    "name:eng_x_preferred":[
        "Borosupa"
    ],
    "wof:name":"Borosupa",
    "wof:placetype":"locality",
    "wof:population":798
},
  "geometry": {"coordinates":[91.731477,26.232324],"type":"Point"}
}