{
  "type": "Feature",
  "properties": {
    "gn:admin1_code":"35.0",
    "gn:admin2_code":"456.0",
    "gn:asciiname":"Alikata",
    "gn:country_code":"IN",
    "gn:dem":504,
    "gn:feature_class":"P",
    "gn:feature_code":"PPL",
    "gn:name":"Al\u012bkata",
    "gn:population":0,
    "gn:timezone":"Asia/Kolkata",
    "iso:country":"IN",
    "name:und_x_variant":[
        "Al\u012bkata",
        "Alikat\u0101"
    ],
    "wof:name":"Alikata",
    "wof:placetype":"locality"
},
  "geometry": {"coordinates":[79.28861999999999,21.77452000000001],"type":"Point"}
}