{
  "type": "Feature",
  "properties": {
    "gn:admin1_code":"35.0",
    "gn:admin2_code":"456.0",
    "gn:asciiname":"Alikata",
    "gn:country_code":"IN",
    "gn:dem":504,
    "gn:feature_class":"P",
    "gn:feature_code":"PPL",
    "gn:name":"Al\u012bkata",
    "gn:population":0,
    "gn:timezone":"Asia/Kolkata",
    "iso:country":"IN",
    "ks:ks_alt_nam":"Alikat\u0101",
    "ks:ks_name":"Alikata",
    "ks:ks_type":"VILLAGE",
    "name:eng_x_preferred":[
        "Alikata"
    ],
    "name:eng_x_variant":[
        "Alikat\u0101"
    ],
    "name:und_x_variant":[
        "Al\u012bkata",
        "Alikat\u0101"
    ],
    "wof:name":"Alikata",
    "wof:placetype":"locality"
},
  "geometry": {"coordinates":[79.28862100000001,21.774516],"type":"Point"}
}