{
  "type": "Feature",
  "properties": {
    "iso:country":"IN",
    "ks:ks_name":"Damanbandi",
    "ks:ks_pop":2,
    "ks:ks_type":"HABITATION",
    "name:eng_x_preferred":[
        "Damanbandi"
    ],
    "wof:name":"Damanbandi",
    "wof:placetype":"locality",
    "wof:population":2
},
  "geometry": {"coordinates":[87.08281599999999,23.271186],"type":"Point"}
}