{
  "type": "Feature",
  "properties": {
    "gn:admin1_code":"37",
    "gn:admin2_code":"404.0",
    "gn:asciiname":"Puta",
    "gn:country_code":"IN",
    "gn:dem":488,
    "gn:feature_class":"P",
    "gn:feature_code":"PPL",
    "gn:name":"P\u016bt\u0101",
    "gn:population":0,
    "gn:timezone":"Asia/Kolkata",
    "iso:country":"IN",
    "ks:ks_alt_nam":"P\u016bt\u0101",
    "ks:ks_name":"Puta",
    "ks:ks_pop":416,
    "ks:ks_type":"VILLAGE",
    "name:ceb_x_preferred":[
        "Puta"
    ],
    "name:eng_x_preferred":[
        "Puta"
    ],
    "name:eng_x_variant":[
        "P\u016bt\u0101"
    ],
    "name:por_x_preferred":[
        "Puta"
    ],
    "name:swe_x_preferred":[
        "Puta"
    ],
    "wof:name":"Puta",
    "wof:placetype":"locality",
    "wof:population":416
},
  "geometry": {"coordinates":[82.706936,22.822758],"type":"Point"}
}