{
  "type": "Feature",
  "properties": {
    "iso:country":"IN",
    "ks:ks_name":"Dhanuharpara",
    "ks:ks_pop":472,
    "ks:ks_type":"HABITATION",
    "name:eng_x_preferred":[
        "Dhanuharpara"
    ],
    "wof:name":"Dhanuharpara",
    "wof:placetype":"locality",
    "wof:population":472
},
  "geometry": {"coordinates":[82.569113,22.274541],"type":"Point"}
}