{
  "type": "Feature",
  "properties": {
    "iso:country":"IN",
    "ks:ks_name":"Desalsar Bhatiyan",
    "ks:ks_pop":744,
    "ks:ks_type":"VILLAGE",
    "ks:ks_uagg_main":0,
    "name:eng_x_preferred":[
        "Desalsar Bhatiyan"
    ],
    "wof:name":"Desalsar Bhatiyan",
    "wof:placetype":"neighbourhood",
    "wof:population":744
},
  "geometry": {"coordinates":[73.311976,27.659999],"type":"Point"}
}