{
  "type": "Feature",
  "properties": {
    "iso:country":"IN",
    "ks:ks_alt_nam":"S.C Colony",
    "ks:ks_name":"S.c Colony",
    "ks:ks_pop":112,
    "ks:ks_type":"HABITATION",
    "name:eng_x_preferred":[
        "S.c Colony"
    ],
    "wof:name":"S.c Colony",
    "wof:placetype":"locality",
    "wof:population":112
},
  "geometry": {"coordinates":[76.282641,12.618599],"type":"Point"}
}