{
  "type": "Feature",
  "properties": {
    "iso:country":"IN",
    "ks:ks_alt_nam":"PURE AHIR",
    "ks:ks_name":"Pure Ahir",
    "ks:ks_pop":89,
    "ks:ks_type":"HABITATION",
    "ks:ks_uagg_main":0,
    "name:eng_x_preferred":[
        "Pure Ahir"
    ],
    "wof:name":"Pure Ahir",
    "wof:placetype":"neighbourhood",
    "wof:population":89
},
  "geometry": {"coordinates":[81.50620000000001,26.439],"type":"Point"}
}