{
  "type": "Feature",
  "properties": {
    "iso:country":"IN",
    "ks:ks_name":"Sirismadh",
    "ks:ks_pop":294,
    "ks:ks_type":"VILLAGE",
    "name:eng_x_preferred":[
        "Sirismadh"
    ],
    "wof:name":"Sirismadh",
    "wof:placetype":"locality",
    "wof:population":294
},
  "geometry": {"coordinates":[84.714968,23.979101],"type":"Point"}
}