{
  "type": "Feature",
  "properties": {
    "gn:admin1_code":"2",
    "gn:admin2_code":"545.0",
    "gn:asciiname":"Edlakonda",
    "gn:country_code":"IN",
    "gn:dem":591,
    "gn:feature_class":"P",
    "gn:feature_code":"PPL",
    "gn:name":"Edlakonda",
    "gn:population":0,
    "gn:timezone":"Asia/Kolkata",
    "iso:country":"IN",
    "ks:ks_name":"Yedlakonda",
    "ks:ks_pop":165,
    "ks:ks_type":"HABITATION",
    "name:eng_x_preferred":[
        "Yedlakonda"
    ],
    "name:eng_x_variant":[
        "Edlakonda"
    ],
    "wof:name":"Yedlakonda",
    "wof:placetype":"locality",
    "wof:population":165
},
  "geometry": {"coordinates":[81.929627,17.827821],"type":"Point"}
}