{
  "type": "Feature",
  "properties": {
    "iso:country":"IN",
    "ks:ks_name":"Than Sahid",
    "ks:ks_pop":503,
    "ks:ks_type":"HABITATION",
    "name:eng_x_preferred":[
        "Than Sahid"
    ],
    "wof:name":"Than Sahid",
    "wof:placetype":"locality",
    "wof:population":503
},
  "geometry": {"coordinates":[78.548734,27.003733],"type":"Point"}
}