{
  "type": "Feature",
  "properties": {
    "gn:admin1_code":"39.0",
    "gn:admin2_code":"63.0",
    "gn:asciiname":"Jaitkuna",
    "gn:country_code":"IN",
    "gn:dem":1879,
    "gn:feature_class":"P",
    "gn:feature_code":"PPL",
    "gn:name":"Jaitkuna",
    "gn:population":0,
    "gn:timezone":"Asia/Kolkata",
    "iso:country":"IN",
    "wof:name":"Jaitkuna",
    "wof:placetype":"locality"
},
  "geometry": {"coordinates":[79.60285999999998,29.98978],"type":"Point"}
}