{
  "type": "Feature",
  "properties": {
    "gn:admin1_code":"34.0",
    "gn:admin2_code":"224.0",
    "gn:asciiname":"Basia Chak",
    "gn:country_code":"IN",
    "gn:dem":42,
    "gn:feature_class":"P",
    "gn:feature_code":"PPL",
    "gn:name":"B\u0101sia Chak",
    "gn:population":0,
    "gn:timezone":"Asia/Kolkata",
    "iso:country":"IN",
    "ks:ks_name":"Asiachak",
    "ks:ks_pop":2037,
    "ks:ks_type":"VILLAGE",
    "name:eng_x_preferred":[
        "Asiachak"
    ],
    "name:eng_x_variant":[
        "Basia Chak"
    ],
    "wof:name":"Asiachak",
    "wof:placetype":"locality",
    "wof:population":2037
},
  "geometry": {"coordinates":[86.703619,25.203973],"type":"Point"}
}