{
  "type": "Feature",
  "properties": {
    "iso:country":"IN",
    "ks:ks_name":"Kothali",
    "ks:ks_pop":410,
    "ks:ks_type":"VILLAGE",
    "name:eng_x_preferred":[
        "Kothali"
    ],
    "wof:name":"Kothali",
    "wof:placetype":"locality",
    "wof:population":410
},
  "geometry": {"coordinates":[79.354269,30.228524],"type":"Point"}
}