{
  "type": "Feature",
  "properties": {
    "gn:admin1_code":"34.0",
    "gn:admin2_code":"212.0",
    "gn:asciiname":"Panikgala",
    "gn:country_code":"IN",
    "gn:dem":34,
    "gn:feature_class":"P",
    "gn:feature_code":"PPL",
    "gn:name":"Panikgala",
    "gn:population":0,
    "gn:timezone":"Asia/Kolkata",
    "iso:country":"IN",
    "wof:name":"Panikgala",
    "wof:placetype":"locality"
},
  "geometry": {"coordinates":[87.79308,25.31712000000001],"type":"Point"}
}