{
  "type": "Feature",
  "properties": {
    "iso:country":"IN",
    "ks:ks_name":"Sutarwadi",
    "ks:ks_pop":178,
    "ks:ks_type":"HABITATION",
    "name:eng_x_preferred":[
        "Sutarwadi"
    ],
    "wof:name":"Sutarwadi",
    "wof:placetype":"locality",
    "wof:population":178
},
  "geometry": {"coordinates":[73.517588,17.468374],"type":"Point"}
}