{
  "type": "Feature",
  "properties": {
    "gn:admin1_code":"25.0",
    "gn:admin2_code":"630.0",
    "gn:asciiname":"Melur",
    "gn:country_code":"IN",
    "gn:dem":449,
    "gn:feature_class":"P",
    "gn:feature_code":"PPL",
    "gn:name":"Mel\u016br",
    "gn:population":0,
    "gn:timezone":"Asia/Kolkata",
    "iso:country":"IN",
    "name:bpy_x_preferred":[
        "\u09ae\u09c7\u09b2\u09c1\u09b0"
    ],
    "name:ceb_x_preferred":[
        "Melur"
    ],
    "name:hin_x_preferred":[
        "\u092e\u0947\u0932\u0941\u0930"
    ],
    "name:ita_x_preferred":[
        "Melur"
    ],
    "name:jpn_x_preferred":[
        "\u30e1\u30fc\u30eb\u30fc\u30eb"
    ],
    "name:mlg_x_preferred":[
        "Melur"
    ],
    "name:msa_x_preferred":[
        "Melur"
    ],
    "name:new_x_preferred":[
        "\u092e\u0947\u0932\u0941\u0930"
    ],
    "name:swe_x_preferred":[
        "Melur"
    ],
    "name:tam_x_preferred":[
        "\u0bae\u0bc7\u0bb2\u0bc2\u0bb0\u0bcd"
    ],
    "name:vie_x_preferred":[
        "Melur"
    ],
    "name:zho_x_preferred":[
        "\u6885\u5362\u5c14"
    ],
    "wof:name":"Melur",
    "wof:placetype":"locality"
},
  "geometry": {"coordinates":[78.21205999999999,12.236],"type":"Point"}
}