{
  "type": "Feature",
  "properties": {
    "iso:country":"IN",
    "ks:ks_name":"Palia Chhoti",
    "ks:ks_pop":461,
    "ks:ks_type":"HABITATION",
    "name:eng_x_preferred":[
        "Palia Chhoti"
    ],
    "wof:name":"Palia Chhoti",
    "wof:placetype":"locality",
    "wof:population":461
},
  "geometry": {"coordinates":[79.778216,26.690152],"type":"Point"}
}