{
  "type": "Feature",
  "properties": {
    "iso:country":"IN",
    "ks:ks_name":"Bouddhwadi",
    "ks:ks_pop":5,
    "ks:ks_type":"HABITATION",
    "name:eng_x_preferred":[
        "Bouddhwadi"
    ],
    "wof:name":"Bouddhwadi",
    "wof:placetype":"locality",
    "wof:population":5
},
  "geometry": {"coordinates":[73.619725,16.740219],"type":"Point"}
}