{
  "type": "Feature",
  "properties": {
    "gn:admin1_code":"21",
    "gn:admin2_code":"399.0",
    "gn:asciiname":"Atalguda",
    "gn:country_code":"IN",
    "gn:dem":258,
    "gn:feature_class":"P",
    "gn:feature_code":"PPL",
    "gn:name":"Atalguda",
    "gn:population":0,
    "gn:timezone":"Asia/Kolkata",
    "iso:country":"IN",
    "ks:ks_name":"Atalaguda2",
    "ks:ks_pop":126,
    "ks:ks_type":"HABITATION",
    "name:eng_x_preferred":[
        "Atalaguda2"
    ],
    "name:eng_x_variant":[
        "Atalguda"
    ],
    "wof:name":"Atalaguda2",
    "wof:placetype":"locality",
    "wof:population":126
},
  "geometry": {"coordinates":[82.105013,18.420714],"type":"Point"}
}