{
  "type": "Feature",
  "properties": {
    "gn:admin1_code":"16.0",
    "gn:admin2_code":"505.0",
    "gn:asciiname":"Dharti",
    "gn:country_code":"IN",
    "gn:dem":456,
    "gn:feature_class":"P",
    "gn:feature_code":"PPL",
    "gn:name":"Dharti",
    "gn:population":0,
    "gn:timezone":"Asia/Kolkata",
    "iso:country":"IN",
    "wof:name":"Dharti",
    "wof:placetype":"locality"
},
  "geometry": {"coordinates":[78.50927,21.18602000000001],"type":"Point"}
}