{
  "type": "Feature",
  "properties": {
    "iso:country":"IN",
    "ks:ks_name":"Chirong Laga Bedula",
    "ks:ks_pop":53,
    "ks:ks_type":"VILLAGE",
    "name:eng_x_preferred":[
        "Chirong Laga Bedula"
    ],
    "wof:name":"Chirong Laga Bedula",
    "wof:placetype":"locality",
    "wof:population":53
},
  "geometry": {"coordinates":[79.332818,30.135304],"type":"Point"}
}