{
  "type": "Feature",
  "properties": {
    "iso:country":"IN",
    "ks:ks_name":"Gudoor",
    "ks:ks_pop":281,
    "ks:ks_type":"VILLAGE",
    "ks:ks_uagg_main":0,
    "name:eng_x_preferred":[
        "Gudoor"
    ],
    "wof:name":"Gudoor",
    "wof:placetype":"neighbourhood",
    "wof:population":281
},
  "geometry": {"coordinates":[79.875356,18.68914],"type":"Point"}
}