{
  "type": "Feature",
  "properties": {
    "iso:country":"IN",
    "ks:ks_name":"Pohardia",
    "ks:ks_pop":300,
    "ks:ks_type":"VILLAGE",
    "name:eng_x_preferred":[
        "Pohardia"
    ],
    "wof:name":"Pohardia",
    "wof:placetype":"locality",
    "wof:population":300
},
  "geometry": {"coordinates":[94.182666,26.942296],"type":"Point"}
}