{
  "type": "Feature",
  "properties": {
    "iso:country":"IN",
    "ks:ks_name":"Hariharpur",
    "ks:ks_pop":720,
    "ks:ks_type":"HABITATION",
    "name:eng_x_preferred":[
        "Hariharpur"
    ],
    "wof:name":"Hariharpur",
    "wof:placetype":"locality",
    "wof:population":720
},
  "geometry": {"coordinates":[86.340639,23.939277],"type":"Point"}
}