{
  "type": "Feature",
  "properties": {
    "gn:admin1_code":"36",
    "gn:admin2_code":"166.0",
    "gn:asciiname":"Bahadurganj",
    "gn:country_code":"IN",
    "gn:dem":180,
    "gn:feature_class":"P",
    "gn:feature_code":"PPL",
    "gn:name":"Bah\u0101durganj",
    "gn:population":0,
    "gn:timezone":"Asia/Kolkata",
    "iso:country":"IN",
    "name:ben_x_preferred":[
        "\u09ac\u09be\u09b9\u09be\u09a6\u09c1\u09b0\u0997\u099e\u09cd\u099c"
    ],
    "name:ceb_x_preferred":[
        "Bahadurganj"
    ],
    "name:ita_x_preferred":[
        "Bahadurganj"
    ],
    "name:nld_x_preferred":[
        "Bahadurganj"
    ],
    "name:pol_x_preferred":[
        "Bahadurganj"
    ],
    "name:swe_x_preferred":[
        "Bahadurganj"
    ],
    "wof:name":"Bahadurganj",
    "wof:placetype":"locality"
},
  "geometry": {"coordinates":[79.21111999999999,25.43532],"type":"Point"}
}