{
  "type": "Feature",
  "properties": {
    "iso:country":"IN",
    "ks:ks_name":"Udhiraparampu",
    "ks:ks_pop":496,
    "ks:ks_type":"HABITATION",
    "name:eng_x_preferred":[
        "Udhiraparampu"
    ],
    "wof:name":"Udhiraparampu",
    "wof:placetype":"locality",
    "wof:population":496
},
  "geometry": {"coordinates":[76.35818999999999,10.338508],"type":"Point"}
}