{
  "type": "Feature",
  "properties": {
    "iso:country":"IN",
    "ks:ks_name":"Madanuwa Uperhar",
    "ks:ks_pop":30,
    "ks:ks_type":"VILLAGE",
    "ks:ks_uagg_main":0,
    "name:eng_x_preferred":[
        "Madanuwa Uperhar"
    ],
    "wof:name":"Madanuwa Uperhar",
    "wof:placetype":"neighbourhood",
    "wof:population":30
},
  "geometry": {"coordinates":[81.900747,25.382715],"type":"Point"}
}