{
  "type": "Feature",
  "properties": {
    "iso:country":"IN",
    "ks:ks_name":"Sarigeta",
    "ks:ks_pop":103,
    "ks:ks_type":"VILLAGE",
    "name:eng_x_preferred":[
        "Sarigeta"
    ],
    "wof:name":"Sarigeta",
    "wof:placetype":"locality",
    "wof:population":103
},
  "geometry": {"coordinates":[81.949791,18.039807],"type":"Point"}
}