{
  "type": "Feature",
  "properties": {
    "gn:admin1_code":"25",
    "gn:admin2_code":"627.0",
    "gn:asciiname":"Seydunganallur",
    "gn:country_code":"IN",
    "gn:dem":28,
    "gn:feature_class":"P",
    "gn:feature_code":"PPL",
    "gn:name":"Seydunganall\u016br",
    "gn:population":0,
    "gn:timezone":"Asia/Kolkata",
    "iso:country":"IN",
    "wof:name":"Seydunganallur",
    "wof:placetype":"locality"
},
  "geometry": {"coordinates":[77.82928000000003,8.66241],"type":"Point"}
}