{
  "type": "Feature",
  "properties": {
    "iso:country":"IN",
    "ks:ks_name":"Nawapara",
    "ks:ks_pop":355,
    "ks:ks_type":"HABITATION",
    "name:eng_x_preferred":[
        "Nawapara"
    ],
    "wof:name":"Nawapara",
    "wof:placetype":"locality",
    "wof:population":355
},
  "geometry": {"coordinates":[82.089276,20.402766],"type":"Point"}
}