{
  "type": "Feature",
  "properties": {
    "gn:admin1_code":"11.0",
    "gn:admin2_code":"33.0",
    "gn:asciiname":"Kalna",
    "gn:country_code":"IN",
    "gn:dem":2337,
    "gn:feature_class":"P",
    "gn:feature_code":"PPL",
    "gn:name":"K\u0101lna",
    "gn:population":0,
    "gn:timezone":"Asia/Kolkata",
    "iso:country":"IN",
    "name:ben_x_preferred":[
        "\u0995\u09be\u09b2\u09a8\u09be"
    ],
    "name:ceb_x_preferred":[
        "Kalna"
    ],
    "name:deu_x_preferred":[
        "Kalna"
    ],
    "name:fra_x_preferred":[
        "Kalna"
    ],
    "name:hin_x_preferred":[
        "\u0915\u093e\u0932\u094d\u0928\u093e"
    ],
    "name:msa_x_preferred":[
        "Kalna"
    ],
    "name:pol_x_preferred":[
        "Kalna"
    ],
    "name:rus_x_preferred":[
        "\u041a\u0430\u043b\u044c\u043d\u0430\u044f"
    ],
    "name:slv_x_preferred":[
        "Kalna"
    ],
    "name:srp_x_preferred":[
        "\u041a\u0430\u043b\u043d\u0430"
    ],
    "name:swe_x_preferred":[
        "Kalna"
    ],
    "name:ukr_x_preferred":[
        "\u041a\u0430\u043b\u044c\u043d\u0430"
    ],
    "wof:name":"Kalna",
    "wof:placetype":"locality"
},
  "geometry": {"coordinates":[77.52064,31.04849],"type":"Point"}
}