{
  "type": "Feature",
  "properties": {
    "iso:country":"IN",
    "ks:ks_name":"Jagannathpur 1",
    "ks:ks_pop":864,
    "ks:ks_type":"HABITATION",
    "name:eng_x_preferred":[
        "Jagannathpur 1"
    ],
    "wof:name":"Jagannathpur 1",
    "wof:placetype":"locality",
    "wof:population":864
},
  "geometry": {"coordinates":[87.644704,21.792506],"type":"Point"}
}