{
  "type": "Feature",
  "properties": {
    "gn:admin1_code":"11.0",
    "gn:admin2_code":"27.0",
    "gn:asciiname":"Shaigla",
    "gn:country_code":"IN",
    "gn:dem":1926,
    "gn:feature_class":"P",
    "gn:feature_code":"PPL",
    "gn:name":"Shaigla",
    "gn:population":0,
    "gn:timezone":"Asia/Kolkata",
    "iso:country":"IN",
    "wof:name":"Shaigla",
    "wof:placetype":"locality"
},
  "geometry": {"coordinates":[77.23158000000002,31.69633],"type":"Point"}
}