{
  "type": "Feature",
  "properties": {
    "gn:admin1_code":"36",
    "gn:admin2_code":"142.0",
    "gn:asciiname":"Mustafabad",
    "gn:country_code":"IN",
    "gn:dem":197,
    "gn:feature_class":"P",
    "gn:feature_code":"PPL",
    "gn:name":"Mustaf\u0101b\u0101d",
    "gn:population":0,
    "gn:timezone":"Asia/Kolkata",
    "iso:country":"IN",
    "ks:ks_name":"Mustafabad",
    "ks:ks_pop":10,
    "ks:ks_type":"VILLAGE",
    "name:eng_x_preferred":[
        "Mustafabad"
    ],
    "wof:name":"Mustafabad",
    "wof:placetype":"locality",
    "wof:population":10
},
  "geometry": {"coordinates":[77.769817,28.301295],"type":"Point"}
}