{
  "type": "Feature",
  "properties": {
    "iso:country":"IN",
    "ks:ks_name":"Hiyatpur",
    "ks:ks_pop":297,
    "ks:ks_type":"VILLAGE",
    "ks:ks_uagg_main":0,
    "name:eng_x_preferred":[
        "Hiyatpur"
    ],
    "wof:name":"Hiyatpur",
    "wof:placetype":"neighbourhood",
    "wof:population":297
},
  "geometry": {"coordinates":[88.39345299999999,25.096594],"type":"Point"}
}