{
  "type": "Feature",
  "properties": {
    "iso:country":"IN",
    "ks:ks_alt_nam":"PURE GOOSIE",
    "ks:ks_name":"Pure Goosie",
    "ks:ks_pop":24,
    "ks:ks_type":"HABITATION",
    "name:eng_x_preferred":[
        "Pure Goosie"
    ],
    "wof:name":"Pure Goosie",
    "wof:placetype":"locality",
    "wof:population":24
},
  "geometry": {"coordinates":[82.246731,26.568144],"type":"Point"}
}