{
  "type": "Feature",
  "properties": {
    "gn:admin1_code":"36.0",
    "gn:admin2_code":"175.0",
    "gn:asciiname":"Jagdishpur",
    "gn:country_code":"IN",
    "gn:dem":95,
    "gn:feature_class":"P",
    "gn:feature_code":"PPL",
    "gn:name":"Jagd\u012bshpur",
    "gn:population":0,
    "gn:timezone":"Asia/Kolkata",
    "iso:country":"IN",
    "ks:ks_alt_nam":"Jagd\u012bshpur",
    "ks:ks_name":"Jagdishpur",
    "ks:ks_pop":841,
    "ks:ks_type":"VILLAGE",
    "ks:ks_uagg_main":0,
    "name:eng_x_preferred":[
        "Jagdishpur"
    ],
    "name:eng_x_variant":[
        "Jagd\u012bshpur"
    ],
    "name:pol_x_preferred":[
        "Jagdishpur"
    ],
    "wof:name":"Jagdishpur",
    "wof:placetype":"neighbourhood",
    "wof:population":841
},
  "geometry": {"coordinates":[81.980721,25.289612],"type":"Point"}
}