{
  "type": "Feature",
  "properties": {
    "iso:country":"IN",
    "ks:ks_name":"Saidanpur",
    "ks:ks_pop":2293,
    "ks:ks_type":"HABITATION",
    "name:eng_x_preferred":[
        "Saidanpur"
    ],
    "wof:name":"Saidanpur",
    "wof:placetype":"locality",
    "wof:population":2293
},
  "geometry": {"coordinates":[82.60123299999999,25.786326],"type":"Point"}
}