{
  "type": "Feature",
  "properties": {
    "iso:country":"IN",
    "ks:ks_name":"Bagdipara",
    "ks:ks_pop":1018,
    "ks:ks_type":"HABITATION",
    "ks:ks_uagg_main":0,
    "name:eng_x_preferred":[
        "Bagdipara"
    ],
    "wof:name":"Bagdipara",
    "wof:placetype":"neighbourhood",
    "wof:population":1018
},
  "geometry": {"coordinates":[88.122444,23.032225],"type":"Point"}
}