{
  "type": "Feature",
  "properties": {
    "iso:country":"IN",
    "ks:ks_name":"Takabari Pt I",
    "ks:ks_pop":1000,
    "ks:ks_type":"HABITATION",
    "name:eng_x_preferred":[
        "Takabari Pt I"
    ],
    "wof:name":"Takabari Pt I",
    "wof:placetype":"locality",
    "wof:population":1000
},
  "geometry": {"coordinates":[90.84291899999999,26.422936],"type":"Point"}
}