{
  "type": "Feature",
  "properties": {
    "iso:country":"IN",
    "ks:ks_alt_nam":"salekoppa",
    "ks:ks_name":"Salekoppa",
    "ks:ks_pop":28,
    "ks:ks_type":"HABITATION",
    "name:eng_x_preferred":[
        "Salekoppa"
    ],
    "wof:name":"Salekoppa",
    "wof:placetype":"locality",
    "wof:population":28
},
  "geometry": {"coordinates":[74.903268,14.711697],"type":"Point"}
}