{
  "type": "Feature",
  "properties": {
    "iso:country":"IN",
    "ks:ks_alt_nam":"Kir\u0101n\u012bpura",
    "ks:ks_name":"Kiranipura",
    "ks:ks_type":"VILLAGE",
    "ks:ks_uagg_main":0,
    "name:eng_x_preferred":[
        "Kiranipura"
    ],
    "name:eng_x_variant":[
        "Kir\u0101n\u012bpura"
    ],
    "wof:name":"Kiranipura",
    "wof:placetype":"neighbourhood"
},
  "geometry": {"coordinates":[74.673633,26.435518],"type":"Point"}
}