{
  "type": "Feature",
  "properties": {
    "gn:admin1_code":"16",
    "gn:admin2_code":"515.0",
    "gn:asciiname":"Yesgaon",
    "gn:country_code":"IN",
    "gn:dem":654,
    "gn:feature_class":"P",
    "gn:feature_code":"PPL",
    "gn:name":"Yesgaon",
    "gn:population":0,
    "gn:timezone":"Asia/Kolkata",
    "iso:country":"IN",
    "ks:ks_name":"Yesgaon",
    "ks:ks_type":"VILLAGE",
    "name:eng_x_preferred":[
        "Yesgaon"
    ],
    "wof:name":"Yesgaon",
    "wof:placetype":"locality"
},
  "geometry": {"coordinates":[75.327172,20.091052],"type":"Point"}
}