{
  "type": "Feature",
  "properties": {
    "gn:admin1_code":"35.0",
    "gn:admin2_code":"443",
    "gn:asciiname":"Mariya",
    "gn:country_code":"IN",
    "gn:dem":397,
    "gn:feature_class":"P",
    "gn:feature_code":"PPL",
    "gn:name":"Mariya",
    "gn:population":0,
    "gn:timezone":"Asia/Kolkata",
    "iso:country":"IN",
    "name:aze_x_preferred":[
        "Mariya"
    ],
    "name:fra_x_preferred":[
        "Mariya"
    ],
    "wof:name":"Mariya",
    "wof:placetype":"locality"
},
  "geometry": {"coordinates":[78.03333000000001,24.07751],"type":"Point"}
}