{
  "type": "Feature",
  "properties": {
    "gn:admin1_code":"35.0",
    "gn:admin2_code":"443",
    "gn:asciiname":"Mariya",
    "gn:country_code":"IN",
    "gn:dem":397,
    "gn:feature_class":"P",
    "gn:feature_code":"PPL",
    "gn:name":"Mariya",
    "gn:population":0,
    "gn:timezone":"Asia/Kolkata",
    "iso:country":"IN",
    "ks:ks_name":"Madiya",
    "ks:ks_pop":38,
    "ks:ks_type":"VILLAGE",
    "name:aze_x_preferred":[
        "Mariya"
    ],
    "name:eng_x_preferred":[
        "Madiya"
    ],
    "name:eng_x_variant":[
        "Mariya"
    ],
    "name:fra_x_preferred":[
        "Mariya"
    ],
    "wof:name":"Madiya",
    "wof:placetype":"locality",
    "wof:population":38
},
  "geometry": {"coordinates":[78.033449,24.077801],"type":"Point"}
}