{
  "type": "Feature",
  "properties": {
    "gn:admin1_code":"37",
    "gn:admin2_code":"410.0",
    "gn:asciiname":"Padharidih",
    "gn:country_code":"IN",
    "gn:dem":273,
    "gn:feature_class":"P",
    "gn:feature_code":"PPL",
    "gn:name":"Padh\u0101r\u012bdih",
    "gn:population":0,
    "gn:timezone":"Asia/Kolkata",
    "iso:country":"IN",
    "ks:ks_name":"Patharidih",
    "ks:ks_pop":957,
    "ks:ks_type":"VILLAGE",
    "ks:ks_uagg_main":0,
    "name:eng_x_preferred":[
        "Patharidih"
    ],
    "wof:name":"Patharidih",
    "wof:placetype":"locality",
    "wof:population":957
},
  "geometry": {"coordinates":[81.60383299999999,21.334127],"type":"Point"}
}