{
  "type": "Feature",
  "properties": {
    "iso:country":"IN",
    "ks:ks_name":"Rawadi",
    "ks:ks_pop":670,
    "ks:ks_type":"VILLAGE",
    "ks:ks_uagg_main":0,
    "name:eng_x_preferred":[
        "Rawadi"
    ],
    "wof:name":"Rawadi",
    "wof:placetype":"neighbourhood",
    "wof:population":670
},
  "geometry": {"coordinates":[78.803684,30.216493],"type":"Point"}
}