{
  "type": "Feature",
  "properties": {
    "iso:country":"IN",
    "ks:ks_alt_nam":"PURE BEDAU",
    "ks:ks_name":"Pure Bedau",
    "ks:ks_pop":73,
    "ks:ks_type":"HABITATION",
    "name:eng_x_preferred":[
        "Pure Bedau"
    ],
    "wof:name":"Pure Bedau",
    "wof:placetype":"locality",
    "wof:population":73
},
  "geometry": {"coordinates":[82.042393,26.347921],"type":"Point"}
}