{
  "type": "Feature",
  "properties": {
    "gn:admin1_code":"2.0",
    "gn:admin2_code":"544.0",
    "gn:asciiname":"Kotapadu",
    "gn:country_code":"IN",
    "gn:dem":84,
    "gn:feature_class":"P",
    "gn:feature_code":"PPL",
    "gn:name":"Kotap\u0101du",
    "gn:population":0,
    "gn:timezone":"Asia/Kolkata",
    "iso:country":"IN",
    "name:tel_x_preferred":[
        "\u0c15\u0c4b\u0c1f\u0c2a\u0c3e\u0c21\u0c41(\u0c1a\u0c3e\u0c1f\u0c4d\u0c30\u0c3e\u0c2f\u0c3f)"
    ],
    "wof:name":"Kotapadu",
    "wof:placetype":"neighbourhood"
},
  "geometry": {"coordinates":[83.0454,17.88524],"type":"Point"}
}