{
  "type": "Feature",
  "properties": {
    "gn:admin1_code":"10.0",
    "gn:admin2_code":"85.0",
    "gn:asciiname":"Dungarwas",
    "gn:country_code":"IN",
    "gn:dem":247,
    "gn:feature_class":"P",
    "gn:feature_code":"PPL",
    "gn:name":"Dungarw\u0101s",
    "gn:population":0,
    "gn:timezone":"Asia/Kolkata",
    "iso:country":"IN",
    "name:und_x_variant":[
        "Dungarw\u0101s"
    ],
    "wof:name":"Dungarwas",
    "wof:placetype":"locality"
},
  "geometry": {"coordinates":[76.72123000000001,28.19513],"type":"Point"}
}