{
  "type": "Feature",
  "properties": {
    "iso:country":"IN",
    "ks:ks_name":"Avige",
    "ks:ks_pop":16,
    "ks:ks_type":"HABITATION",
    "name:eng_x_preferred":[
        "Avige"
    ],
    "wof:name":"Avige",
    "wof:placetype":"locality",
    "wof:population":16
},
  "geometry": {"coordinates":[75.25261,13.340452],"type":"Point"}
}