{
  "type": "Feature",
  "properties": {
    "iso:country":"IN",
    "ks:ks_name":"Bholadanga",
    "ks:ks_pop":3058,
    "ks:ks_type":"VILLAGE",
    "name:eng_x_preferred":[
        "Bholadanga"
    ],
    "wof:name":"Bholadanga",
    "wof:placetype":"locality",
    "wof:population":3058
},
  "geometry": {"coordinates":[88.422864,23.562313],"type":"Point"}
}