{
  "type": "Feature",
  "properties": {
    "iso:country":"IN",
    "ks:ks_name":"Panai",
    "ks:ks_pop":740,
    "ks:ks_type":"HABITATION",
    "name:eng_x_preferred":[
        "Panai"
    ],
    "wof:name":"Panai",
    "wof:placetype":"locality",
    "wof:population":740
},
  "geometry": {"coordinates":[73.060069,24.122628],"type":"Point"}
}