{
  "type": "Feature",
  "properties": {
    "gn:admin1_code":"34",
    "gn:admin2_code":"233.0",
    "gn:asciiname":"Manradag",
    "gn:country_code":"IN",
    "gn:dem":336,
    "gn:feature_class":"P",
    "gn:feature_code":"PPL",
    "gn:name":"M\u0101nr\u0101d\u0101g",
    "gn:population":0,
    "gn:timezone":"Asia/Kolkata",
    "iso:country":"IN",
    "ks:ks_alt_nam":"M\u0101nr\u0101d\u0101g",
    "ks:ks_name":"Manradag",
    "ks:ks_pop":0,
    "ks:ks_type":"VILLAGE",
    "name:eng_x_preferred":[
        "Manradag"
    ],
    "name:eng_x_variant":[
        "M\u0101nr\u0101d\u0101g"
    ],
    "wof:name":"Manradag",
    "wof:placetype":"locality",
    "wof:population":0
},
  "geometry": {"coordinates":[83.634237,24.810121],"type":"Point"}
}