{
  "type": "Feature",
  "properties": {
    "iso:country":"IN",
    "ks:ks_name":"Amagarha",
    "ks:ks_pop":0,
    "ks:ks_type":"VILLAGE",
    "name:eng_x_preferred":[
        "Amagarha"
    ],
    "wof:name":"Amagarha",
    "wof:placetype":"locality",
    "wof:population":0
},
  "geometry": {"coordinates":[86.474917,23.758097],"type":"Point"}
}