{
  "type": "Feature",
  "properties": {
    "iso:country":"IN",
    "ks:ks_name":"Kharktamta",
    "ks:ks_pop":291,
    "ks:ks_type":"HABITATION",
    "name:eng_x_preferred":[
        "Kharktamta"
    ],
    "wof:name":"Kharktamta",
    "wof:placetype":"locality",
    "wof:population":291
},
  "geometry": {"coordinates":[79.73616,29.778495],"type":"Point"}
}