{
  "type": "Feature",
  "properties": {
    "iso:country":"IN",
    "ks:ks_name":"Khap Tola",
    "ks:ks_pop":428,
    "ks:ks_type":"HABITATION",
    "name:eng_x_preferred":[
        "Khap Tola"
    ],
    "wof:name":"Khap Tola",
    "wof:placetype":"locality",
    "wof:population":428
},
  "geometry": {"coordinates":[85.11755100000001,26.426647],"type":"Point"}
}