{
  "type": "Feature",
  "properties": {
    "iso:country":"IN",
    "ks:ks_name":"Dcheptaghat",
    "ks:ks_pop":76,
    "ks:ks_type":"HABITATION",
    "name:eng_x_preferred":[
        "Dcheptaghat"
    ],
    "wof:name":"Dcheptaghat",
    "wof:placetype":"locality",
    "wof:population":76
},
  "geometry": {"coordinates":[82.90572400000001,19.309915],"type":"Point"}
}