{
  "type": "Feature",
  "properties": {
    "gn:admin1_code":"34.0",
    "gn:admin2_code":"203.0",
    "gn:asciiname":"Nimuia",
    "gn:country_code":"IN",
    "gn:dem":84,
    "gn:feature_class":"P",
    "gn:feature_code":"PPL",
    "gn:name":"Nimui\u0101",
    "gn:population":0,
    "gn:timezone":"Asia/Kolkata",
    "iso:country":"IN",
    "ks:ks_alt_nam":"Nimui\u0101",
    "ks:ks_name":"Nimuia",
    "ks:ks_type":"VILLAGE",
    "ks:ks_uagg_main":0,
    "name:eng_x_preferred":[
        "Nimuia"
    ],
    "name:eng_x_variant":[
        "Nimui\u0101"
    ],
    "wof:name":"Nimuia",
    "wof:placetype":"neighbourhood"
},
  "geometry": {"coordinates":[84.42755,26.823682],"type":"Point"}
}