{
  "type": "Feature",
  "properties": {
    "gn:admin1_code":"34.0",
    "gn:admin2_code":"236.0",
    "gn:asciiname":"Bardih",
    "gn:country_code":"IN",
    "gn:dem":184,
    "gn:feature_class":"P",
    "gn:feature_code":"PPL",
    "gn:name":"Bardih",
    "gn:population":0,
    "gn:timezone":"Asia/Kolkata",
    "iso:country":"IN",
    "wof:name":"Bardih",
    "wof:placetype":"locality"
},
  "geometry": {"coordinates":[84.56811,24.44400000000001],"type":"Point"}
}