{
  "type": "Feature",
  "properties": {
    "iso:country":"IN",
    "ks:ks_name":"Ng. Ponth",
    "ks:ks_pop":445,
    "ks:ks_type":"HABITATION",
    "name:eng_x_preferred":[
        "Ng. Ponth"
    ],
    "wof:name":"Ng. Ponth",
    "wof:placetype":"locality",
    "wof:population":445
},
  "geometry": {"coordinates":[78.8259,27.380438],"type":"Point"}
}