{
  "type": "Feature",
  "properties": {
    "gn:admin1_code":"40.0",
    "gn:admin2_code":"533.0",
    "gn:asciiname":"Lingal",
    "gn:country_code":"IN",
    "gn:dem":449,
    "gn:feature_class":"P",
    "gn:feature_code":"PPL",
    "gn:name":"Ling\u0101l",
    "gn:population":0,
    "gn:timezone":"Asia/Kolkata",
    "iso:country":"IN",
    "name:tel_x_preferred":[
        "\u0c32\u0c3f\u0c02\u0c17\u0c3e\u0c32"
    ],
    "name:und_x_variant":[
        "Ling\u0101l",
        "Goli"
    ],
    "wof:name":"Lingal",
    "wof:placetype":"locality"
},
  "geometry": {"coordinates":[78.14471999999998,18.09116],"type":"Point"}
}