{
  "type": "Feature",
  "properties": {
    "iso:country":"IN",
    "ks:ks_name":"Mahsaul Urf Rampur Lachmi",
    "ks:ks_pop":23664,
    "ks:ks_type":"VILLAGE",
    "ks:ks_uagg_main":0,
    "name:eng_x_preferred":[
        "Mahsaul Urf Rampur Lachmi"
    ],
    "wof:name":"Mahsaul Urf Rampur Lachmi",
    "wof:placetype":"neighbourhood",
    "wof:population":23664
},
  "geometry": {"coordinates":[85.51173799999999,26.592973],"type":"Point"}
}