{
  "type": "Feature",
  "properties": {
    "gn:admin1_code":"36.0",
    "gn:admin2_code":"136.0",
    "gn:asciiname":"Bahpuri",
    "gn:country_code":"IN",
    "gn:dem":183,
    "gn:feature_class":"P",
    "gn:feature_code":"PPL",
    "gn:name":"Bahpuri",
    "gn:population":0,
    "gn:timezone":"Asia/Kolkata",
    "iso:country":"IN",
    "wof:name":"Bahpuri",
    "wof:placetype":"locality"
},
  "geometry": {"coordinates":[78.99271,28.67156],"type":"Point"}
}