{
  "type": "Feature",
  "properties": {
    "iso:country":"IN",
    "ks:ks_alt_nam":"JANAKPUR",
    "ks:ks_name":"Janakpur",
    "ks:ks_pop":260,
    "ks:ks_type":"HABITATION",
    "name:eng_x_preferred":[
        "Janakpur"
    ],
    "wof:name":"Janakpur",
    "wof:placetype":"locality",
    "wof:population":260
},
  "geometry": {"coordinates":[85.28645299999999,24.793003],"type":"Point"}
}