{
  "type": "Feature",
  "properties": {
    "iso:country":"IN",
    "ks:ks_name":"Kopatti Colony 2",
    "ks:ks_pop":35,
    "ks:ks_type":"HABITATION",
    "name:eng_x_preferred":[
        "Kopatti Colony 2"
    ],
    "wof:name":"Kopatti Colony 2",
    "wof:placetype":"locality",
    "wof:population":35
},
  "geometry": {"coordinates":[75.59612,12.378351],"type":"Point"}
}