{
  "type": "Feature",
  "properties": {
    "iso:country":"IN",
    "ks:ks_name":"Erpukkattalai",
    "ks:ks_pop":410,
    "ks:ks_type":"HABITATION",
    "name:eng_x_preferred":[
        "Erpukkattalai"
    ],
    "wof:name":"Erpukkattalai",
    "wof:placetype":"locality",
    "wof:population":410
},
  "geometry": {"coordinates":[79.690754,10.568372],"type":"Point"}
}