{
  "type": "Feature",
  "properties": {
    "iso:country":"IN",
    "ks:ks_alt_nam":"Bardaha south tola",
    "ks:ks_name":"Bardaha South Tola",
    "ks:ks_pop":1240,
    "ks:ks_type":"HABITATION",
    "name:eng_x_preferred":[
        "Bardaha South Tola"
    ],
    "wof:name":"Bardaha South Tola",
    "wof:placetype":"locality",
    "wof:population":1240
},
  "geometry": {"coordinates":[87.534094,26.347763],"type":"Point"}
}