{
  "type": "Feature",
  "properties": {
    "iso:country":"IN",
    "ks:ks_name":"Ranipokhari",
    "ks:ks_pop":291,
    "ks:ks_type":"VILLAGE",
    "name:eng_x_preferred":[
        "Ranipokhari"
    ],
    "wof:name":"Ranipokhari",
    "wof:placetype":"locality",
    "wof:population":291
},
  "geometry": {"coordinates":[86.51264399999999,21.372352],"type":"Point"}
}