{
  "type": "Feature",
  "properties": {
    "gn:admin1_code":"23",
    "gn:admin2_code":"39.0",
    "gn:asciiname":"Bir Sarangwal",
    "gn:country_code":"IN",
    "gn:dem":243,
    "gn:feature_class":"P",
    "gn:feature_code":"PPL",
    "gn:name":"Bir Sarangw\u0101l",
    "gn:population":0,
    "gn:timezone":"Asia/Kolkata",
    "iso:country":"IN",
    "name:por_x_preferred":[
        "Bir Sarangwal"
    ],
    "wof:name":"Bir Sarangwal",
    "wof:placetype":"locality"
},
  "geometry": {"coordinates":[75.8471,31.22261],"type":"Point"}
}