{
  "type": "Feature",
  "properties": {
    "iso:country":"IN",
    "ks:ks_name":"Poovathinchola",
    "ks:ks_pop":2052,
    "ks:ks_type":"HABITATION",
    "name:eng_x_preferred":[
        "Poovathinchola"
    ],
    "wof:name":"Poovathinchola",
    "wof:placetype":"locality",
    "wof:population":2052
},
  "geometry": {"coordinates":[75.80901299999999,11.870655],"type":"Point"}
}