{
  "type": "Feature",
  "properties": {
    "iso:country":"IN",
    "ks:ks_name":"Lower Khairan",
    "ks:ks_pop":250,
    "ks:ks_type":"HABITATION",
    "name:eng_x_preferred":[
        "Lower Khairan"
    ],
    "wof:name":"Lower Khairan",
    "wof:placetype":"locality",
    "wof:population":250
},
  "geometry": {"coordinates":[86.388839,24.86901],"type":"Point"}
}