{
  "type": "Feature",
  "properties": {
    "iso:country":"IN",
    "ks:ks_name":"Sooliya",
    "ks:ks_pop":1639,
    "ks:ks_type":"VILLAGE",
    "name:eng_x_preferred":[
        "Sooliya"
    ],
    "wof:name":"Sooliya",
    "wof:placetype":"locality",
    "wof:population":1639
},
  "geometry": {"coordinates":[74.21948500000001,25.616273],"type":"Point"}
}