{
  "type": "Feature",
  "properties": {
    "iso:country":"IN",
    "ks:ks_alt_nam":"MOHAN CH.BARI",
    "ks:ks_name":"Mohan Ch.bari",
    "ks:ks_pop":45,
    "ks:ks_type":"HABITATION",
    "name:eng_x_preferred":[
        "Mohan Ch.bari"
    ],
    "wof:name":"Mohan Ch.bari",
    "wof:placetype":"locality",
    "wof:population":45
},
  "geometry": {"coordinates":[91.66033400000001,24.138538],"type":"Point"}
}