{
  "type": "Feature",
  "properties": {
    "iso:country":"IN",
    "ks:ks_name":"Bichpuri",
    "ks:ks_pop":662,
    "ks:ks_type":"VILLAGE",
    "name:eng_x_preferred":[
        "Bichpuri"
    ],
    "wof:name":"Bichpuri",
    "wof:placetype":"locality",
    "wof:population":662
},
  "geometry": {"coordinates":[77.856764,26.292582],"type":"Point"}
}