{
  "type": "Feature",
  "properties": {
    "iso:country":"IN",
    "ks:ks_name":"Imaliya Raiyat",
    "ks:ks_pop":203,
    "ks:ks_type":"HABITATION",
    "name:eng_x_preferred":[
        "Imaliya Raiyat"
    ],
    "wof:name":"Imaliya Raiyat",
    "wof:placetype":"locality",
    "wof:population":203
},
  "geometry": {"coordinates":[80.531931,22.550098],"type":"Point"}
}