{
  "type": "Feature",
  "properties": {
    "iso:country":"IN",
    "ks:ks_name":"Ramdhangarh",
    "ks:ks_pop":340,
    "ks:ks_type":"HABITATION",
    "name:eng_x_preferred":[
        "Ramdhangarh"
    ],
    "wof:name":"Ramdhangarh",
    "wof:placetype":"locality",
    "wof:population":340
},
  "geometry": {"coordinates":[72.156819,26.564283],"type":"Point"}
}