{
  "type": "Feature",
  "properties": {
    "gn:admin1_code":"11",
    "gn:admin2_code":"24.0",
    "gn:asciiname":"Bindali Pir",
    "gn:country_code":"IN",
    "gn:dem":624,
    "gn:feature_class":"P",
    "gn:feature_code":"PPL",
    "gn:name":"Bind\u0101li P\u012br",
    "gn:population":0,
    "gn:timezone":"Asia/Kolkata",
    "iso:country":"IN",
    "wof:name":"Bindali Pir",
    "wof:placetype":"locality"
},
  "geometry": {"coordinates":[76.12689,32.08544000000001],"type":"Point"}
}