{
  "type": "Feature",
  "properties": {
    "iso:country":"IN",
    "ks:ks_name":"Charanni Muvadi",
    "ks:ks_pop":127,
    "ks:ks_type":"VILLAGE",
    "ks:ks_uagg_main":0,
    "name:eng_x_preferred":[
        "Charanni Muvadi"
    ],
    "wof:name":"Charanni Muvadi",
    "wof:placetype":"neighbourhood",
    "wof:population":127
},
  "geometry": {"coordinates":[73.825833,23.27125],"type":"Point"}
}