{
  "type": "Feature",
  "properties": {
    "gn:admin1_code":"16",
    "gn:admin2_code":"513.0",
    "gn:asciiname":"Sonpet",
    "gn:country_code":"IN",
    "gn:dem":406,
    "gn:feature_class":"P",
    "gn:feature_code":"PPL",
    "gn:name":"Sonpet",
    "gn:population":0,
    "gn:timezone":"Asia/Kolkata",
    "iso:country":"IN",
    "name:und_x_variant":[
        "Sonepett",
        "Sonepet",
        "Sonpet"
    ],
    "wof:name":"Sonpet",
    "wof:placetype":"locality"
},
  "geometry": {"coordinates":[76.47394,19.02594],"type":"Point"}
}