{
  "type": "Feature",
  "properties": {
    "iso:country":"IN",
    "ks:ks_name":"Karra",
    "ks:ks_pop":0,
    "ks:ks_type":"VILLAGE",
    "name:eng_x_preferred":[
        "Karra"
    ],
    "wof:name":"Karra",
    "wof:placetype":"locality",
    "wof:population":0
},
  "geometry": {"coordinates":[78.33527599999999,25.68096],"type":"Point"}
}