{
  "type": "Feature",
  "properties": {
    "iso:country":"IN",
    "ks:ks_name":"Lvesh Syani",
    "ks:ks_pop":952,
    "ks:ks_type":"VILLAGE",
    "name:eng_x_preferred":[
        "Lvesh Syani"
    ],
    "wof:name":"Lvesh Syani",
    "wof:placetype":"locality",
    "wof:population":952
},
  "geometry": {"coordinates":[79.58437000000001,29.45925],"type":"Point"}
}