{
  "type": "Feature",
  "properties": {
    "iso:country":"IN",
    "ks:ks_name":"Kundara",
    "ks:ks_pop":238,
    "ks:ks_type":"VILLAGE",
    "name:eng_x_preferred":[
        "Kundara"
    ],
    "wof:name":"Kundara",
    "wof:placetype":"locality",
    "wof:population":238
},
  "geometry": {"coordinates":[78.32659,22.101807],"type":"Point"}
}