{
  "type": "Feature",
  "properties": {
    "iso:country":"IN",
    "ks:ks_name":"Khooran",
    "ks:ks_pop":140,
    "ks:ks_type":"HABITATION",
    "name:eng_x_preferred":[
        "Khooran"
    ],
    "wof:name":"Khooran",
    "wof:placetype":"locality",
    "wof:population":140
},
  "geometry": {"coordinates":[79.248822,26.43364],"type":"Point"}
}