{
  "type": "Feature",
  "properties": {
    "gn:admin1_code":"36",
    "gn:admin2_code":"196.0",
    "gn:asciiname":"Baranga",
    "gn:country_code":"IN",
    "gn:dem":81,
    "gn:feature_class":"P",
    "gn:feature_code":"PPL",
    "gn:name":"Baranga",
    "gn:population":0,
    "gn:timezone":"Asia/Kolkata",
    "iso:country":"IN",
    "name:ron_x_preferred":[
        "Baranga"
    ],
    "name:spa_x_preferred":[
        "Barangay"
    ],
    "wof:name":"Baranga",
    "wof:placetype":"locality"
},
  "geometry": {"coordinates":[83.3308,25.26666],"type":"Point"}
}