{
  "type": "Feature",
  "properties": {
    "iso:country":"IN",
    "ks:ks_name":"Baguda",
    "ks:ks_pop":177,
    "ks:ks_type":"VILLAGE",
    "name:eng_x_preferred":[
        "Baguda"
    ],
    "wof:name":"Baguda",
    "wof:placetype":"locality",
    "wof:population":177
},
  "geometry": {"coordinates":[84.983452,19.828027],"type":"Point"}
}