{
  "type": "Feature",
  "properties": {
    "gn:admin1_code":"38.0",
    "gn:admin2_code":"362.0",
    "gn:asciiname":"Dumuria",
    "gn:country_code":"IN",
    "gn:dem":162,
    "gn:feature_class":"P",
    "gn:feature_code":"PPL",
    "gn:name":"Dumuria",
    "gn:population":0,
    "gn:timezone":"Asia/Kolkata",
    "iso:country":"IN",
    "ks:ks_name":"Dumaria",
    "ks:ks_pop":283,
    "ks:ks_type":"VILLAGE",
    "name:eng_x_preferred":[
        "Dumaria"
    ],
    "name:eng_x_variant":[
        "Dumuria"
    ],
    "wof:name":"Dumaria",
    "wof:placetype":"locality",
    "wof:population":283
},
  "geometry": {"coordinates":[87.537605,24.403652],"type":"Point"}
}