{
  "type": "Feature",
  "properties": {
    "gn:admin1_code":"38.0",
    "gn:admin2_code":"352.0",
    "gn:asciiname":"Motipahari Bara",
    "gn:country_code":"IN",
    "gn:dem":106,
    "gn:feature_class":"P",
    "gn:feature_code":"PPL",
    "gn:name":"Mot\u012bpah\u0101ri Bara",
    "gn:population":0,
    "gn:timezone":"Asia/Kolkata",
    "iso:country":"IN",
    "ks:ks_alt_nam":"Mot\u012bpah\u0101ri Bara",
    "ks:ks_name":"Motipahari Bara",
    "ks:ks_pop":2106,
    "ks:ks_type":"VILLAGE",
    "name:eng_x_preferred":[
        "Motipahari Bara"
    ],
    "name:eng_x_variant":[
        "Mot\u012bpah\u0101ri Bara"
    ],
    "wof:name":"Motipahari Bara",
    "wof:placetype":"locality",
    "wof:population":2106
},
  "geometry": {"coordinates":[87.540807,25.024814],"type":"Point"}
}