{
  "type": "Feature",
  "properties": {
    "gn:admin1_code":"36.0",
    "gn:admin2_code":"155.0",
    "gn:asciiname":"Gulkhauria",
    "gn:country_code":"IN",
    "gn:dem":144,
    "gn:feature_class":"P",
    "gn:feature_code":"PPL",
    "gn:name":"Gulkhauria",
    "gn:population":0,
    "gn:timezone":"Asia/Kolkata",
    "iso:country":"IN",
    "ks:ks_name":"Gulkheria",
    "ks:ks_pop":197,
    "ks:ks_type":"HABITATION",
    "name:eng_x_preferred":[
        "Gulkheria"
    ],
    "name:eng_x_variant":[
        "Gulkhauria"
    ],
    "wof:name":"Gulkheria",
    "wof:placetype":"locality",
    "wof:population":197
},
  "geometry": {"coordinates":[80.237841,27.336656],"type":"Point"}
}