{
  "type": "Feature",
  "properties": {
    "gn:admin1_code":"37",
    "gn:admin2_code":"414.0",
    "gn:asciiname":"Gobindpur",
    "gn:country_code":"IN",
    "gn:dem":662,
    "gn:feature_class":"P",
    "gn:feature_code":"PPL",
    "gn:name":"Gobindpur",
    "gn:population":0,
    "gn:timezone":"Asia/Kolkata",
    "iso:country":"IN",
    "ks:ks_name":"Govindpur",
    "ks:ks_pop":423,
    "ks:ks_type":"HABITATION",
    "name:ceb_x_preferred":[
        "Gobindpur"
    ],
    "name:eng_x_preferred":[
        "Govindpur"
    ],
    "name:eng_x_variant":[
        "Gobindpur"
    ],
    "name:swe_x_preferred":[
        "Gobindpur"
    ],
    "wof:name":"Govindpur",
    "wof:placetype":"locality",
    "wof:population":423
},
  "geometry": {"coordinates":[81.805238,20.14526],"type":"Point"}
}