{
  "type": "Feature",
  "properties": {
    "iso:country":"IN",
    "ks:ks_name":"Singarpur",
    "ks:ks_pop":1071,
    "ks:ks_type":"VILLAGE",
    "name:eng_x_preferred":[
        "Singarpur"
    ],
    "wof:name":"Singarpur",
    "wof:placetype":"locality",
    "wof:population":1071
},
  "geometry": {"coordinates":[86.079734,21.928353],"type":"Point"}
}