{
  "type": "Feature",
  "properties": {
    "gn:admin1_code":"11.0",
    "gn:admin2_code":"33.0",
    "gn:asciiname":"Matal",
    "gn:country_code":"IN",
    "gn:dem":2308,
    "gn:feature_class":"P",
    "gn:feature_code":"PPL",
    "gn:name":"M\u0101tal",
    "gn:population":0,
    "gn:timezone":"Asia/Kolkata",
    "iso:country":"IN",
    "wof:name":"Matal",
    "wof:placetype":"locality"
},
  "geometry": {"coordinates":[77.59043,31.02014],"type":"Point"}
}