{
  "type": "Feature",
  "properties": {
    "gn:admin1_code":"36.0",
    "gn:admin2_code":"138.0",
    "gn:asciiname":"Gesupur Bapawat",
    "gn:country_code":"IN",
    "gn:dem":230,
    "gn:feature_class":"P",
    "gn:feature_code":"PPL",
    "gn:name":"Ges\u016bpur Bap\u0101wat",
    "gn:population":0,
    "gn:timezone":"Asia/Kolkata",
    "iso:country":"IN",
    "wof:name":"Gesupur Bapawat",
    "wof:placetype":"locality"
},
  "geometry": {"coordinates":[77.67385,29.09659000000001],"type":"Point"}
}