{
  "type": "Feature",
  "properties": {
    "gn:admin1_code":"12.0",
    "gn:admin2_code":"22.0",
    "gn:asciiname":"Han",
    "gn:country_code":"IN",
    "gn:dem":468,
    "gn:feature_class":"P",
    "gn:feature_code":"PPL",
    "gn:name":"Han",
    "gn:population":0,
    "gn:timezone":"Asia/Kolkata",
    "iso:country":"IN",
    "name:bel_x_preferred":[
        "\u0425\u0430\u043d"
    ],
    "name:bul_x_preferred":[
        "\u0425\u0430\u043d"
    ],
    "name:cat_x_preferred":[
        "Han"
    ],
    "name:ceb_x_preferred":[
        "Han"
    ],
    "name:ces_x_preferred":[
        "Han"
    ],
    "name:cym_x_preferred":[
        "Han"
    ],
    "name:deu_x_preferred":[
        "Han"
    ],
    "name:est_x_preferred":[
        "Han"
    ],
    "name:fas_x_preferred":[
        "\u0647\u0627\u0646"
    ],
    "name:fin_x_preferred":[
        "Han"
    ],
    "name:fra_x_preferred":[
        "Han"
    ],
    "name:heb_x_preferred":[
        "\u05d7\u05d0\u05df"
    ],
    "name:hrv_x_preferred":[
        "Han"
    ],
    "name:hun_x_preferred":[
        "Han"
    ],
    "name:hye_x_preferred":[
        "\u053d\u0561\u0576"
    ],
    "name:ind_x_preferred":[
        "Han"
    ],
    "name:lit_x_preferred":[
        "Han"
    ],
    "name:ltz_x_preferred":[
        "Han"
    ],
    "name:msa_x_preferred":[
        "Han"
    ],
    "name:nld_x_preferred":[
        "Han"
    ],
    "name:nor_x_preferred":[
        "Han"
    ],
    "name:pol_x_preferred":[
        "Han"
    ],
    "name:por_x_preferred":[
        "Han"
    ],
    "name:ron_x_preferred":[
        "Han"
    ],
    "name:rus_x_preferred":[
        "\u0425\u0430\u043d"
    ],
    "name:sco_x_preferred":[
        "Han"
    ],
    "name:slv_x_preferred":[
        "Han"
    ],
    "name:spa_x_preferred":[
        "Han"
    ],
    "name:srp_x_preferred":[
        "\u0425\u0430\u043d"
    ],
    "name:swa_x_preferred":[
        "Han"
    ],
    "name:swe_x_preferred":[
        "Han"
    ],
    "name:tgk_x_preferred":[
        "\u0425\u043e\u043d"
    ],
    "name:tha_x_preferred":[
        "\u0e2e\u0e31\u0e48\u0e19"
    ],
    "name:tur_x_preferred":[
        "Han"
    ],
    "name:ukr_x_preferred":[
        "\u0425\u0430\u043d"
    ],
    "name:uzb_x_preferred":[
        "Xon"
    ],
    "name:vie_x_preferred":[
        "H\u00e1n"
    ],
    "wof:name":"Han",
    "wof:placetype":"locality"
},
  "geometry": {"coordinates":[75.16614,32.5476],"type":"Point"}
}