{
  "type": "Feature",
  "properties": {
    "gn:admin1_code":"24.0",
    "gn:admin2_code":"129.0",
    "gn:asciiname":"Borda",
    "gn:country_code":"IN",
    "gn:dem":320,
    "gn:feature_class":"P",
    "gn:feature_code":"PPL",
    "gn:name":"Borda",
    "gn:population":0,
    "gn:timezone":"Asia/Kolkata",
    "iso:country":"IN",
    "name:arg_x_preferred":[
        "Borda"
    ],
    "name:ceb_x_preferred":[
        "Borda"
    ],
    "name:deu_x_preferred":[
        "Borda"
    ],
    "name:fas_x_preferred":[
        "\u0628\u0631\u062f\u0627"
    ],
    "name:fra_x_preferred":[
        "Borda"
    ],
    "name:ita_x_preferred":[
        "Borda"
    ],
    "name:nds_x_preferred":[
        "Borda"
    ],
    "name:pol_x_preferred":[
        "Borda"
    ],
    "name:por_x_preferred":[
        "Borda"
    ],
    "name:spa_x_preferred":[
        "Borda"
    ],
    "name:srp_x_preferred":[
        "Borda"
    ],
    "name:swe_x_preferred":[
        "Borda"
    ],
    "wof:name":"Borda",
    "wof:placetype":"locality"
},
  "geometry": {"coordinates":[76.52223000000002,24.42507],"type":"Point"}
}