{
  "type": "Feature",
  "properties": {
    "iso:country":"IN",
    "ks:ks_alt_nam":"KUMHAR TOLA",
    "ks:ks_name":"Kumhar Tola",
    "ks:ks_pop":400,
    "ks:ks_type":"HABITATION",
    "name:eng_x_preferred":[
        "Kumhar Tola"
    ],
    "wof:name":"Kumhar Tola",
    "wof:placetype":"locality",
    "wof:population":400
},
  "geometry": {"coordinates":[86.826646,26.295134],"type":"Point"}
}