{
  "type": "Feature",
  "properties": {
    "iso:country":"IN",
    "ks:ks_name":"Bhura Yadav",
    "ks:ks_pop":50,
    "ks:ks_type":"HABITATION",
    "name:eng_x_preferred":[
        "Bhura Yadav"
    ],
    "wof:name":"Bhura Yadav",
    "wof:placetype":"locality",
    "wof:population":50
},
  "geometry": {"coordinates":[80.866167,25.36827],"type":"Point"}
}