{
  "type": "Feature",
  "properties": {
    "iso:country":"IN",
    "ks:ks_name":"Parvathgiri Bhetta",
    "ks:ks_pop":5,
    "ks:ks_type":"HABITATION",
    "name:eng_x_preferred":[
        "Parvathgiri Bhetta"
    ],
    "wof:name":"Parvathgiri Bhetta",
    "wof:placetype":"locality",
    "wof:population":5
},
  "geometry": {"coordinates":[75.757222,12.675556],"type":"Point"}
}