{
  "type": "Feature",
  "properties": {
    "iso:country":"IN",
    "ks:ks_name":"Damodarpur",
    "ks:ks_pop":228,
    "ks:ks_type":"VILLAGE",
    "ks:ks_uagg_main":0,
    "name:eng_x_preferred":[
        "Damodarpur"
    ],
    "wof:name":"Damodarpur",
    "wof:placetype":"neighbourhood",
    "wof:population":228
},
  "geometry": {"coordinates":[85.08194,26.279356],"type":"Point"}
}