{
  "type": "Feature",
  "properties": {
    "iso:country":"IN",
    "ks:ks_name":"Nimbapaur",
    "ks:ks_pop":345,
    "ks:ks_type":"VILLAGE",
    "name:eng_x_preferred":[
        "Nimbapaur"
    ],
    "wof:name":"Nimbapaur",
    "wof:placetype":"locality",
    "wof:population":345
},
  "geometry": {"coordinates":[73.013268,19.981968],"type":"Point"}
}