{
  "type": "Feature",
  "properties": {
    "iso:country":"IN",
    "ks:ks_name":"Ao Basti",
    "ks:ks_pop":267,
    "ks:ks_type":"HABITATION",
    "name:eng_x_preferred":[
        "Ao Basti"
    ],
    "wof:name":"Ao Basti",
    "wof:placetype":"locality",
    "wof:population":267
},
  "geometry": {"coordinates":[93.876987,26.042221],"type":"Point"}
}