{
  "type": "Feature",
  "properties": {
    "iso:country":"IN",
    "ks:ks_name":"Ansari Tola",
    "ks:ks_pop":170,
    "ks:ks_type":"HABITATION",
    "ks:ks_uagg_main":0,
    "name:eng_x_preferred":[
        "Ansari Tola"
    ],
    "wof:name":"Ansari Tola",
    "wof:placetype":"neighbourhood",
    "wof:population":170
},
  "geometry": {"coordinates":[87.785787,26.103989],"type":"Point"}
}