{
  "type": "Feature",
  "properties": {
    "iso:country":"IN",
    "ks:ks_name":"Bodwada Khurd",
    "ks:ks_pop":11,
    "ks:ks_type":"VILLAGE",
    "name:eng_x_preferred":[
        "Bodwada Khurd"
    ],
    "wof:name":"Bodwada Khurd",
    "wof:placetype":"locality",
    "wof:population":11
},
  "geometry": {"coordinates":[75.397976,22.706478],"type":"Point"}
}