{
  "type": "Feature",
  "properties": {
    "iso:country":"IN",
    "ks:ks_name":"Koliwadi",
    "ks:ks_pop":49,
    "ks:ks_type":"HABITATION",
    "name:eng_x_preferred":[
        "Koliwadi"
    ],
    "wof:name":"Koliwadi",
    "wof:placetype":"locality",
    "wof:population":49
},
  "geometry": {"coordinates":[73.56440000000001,17.8343],"type":"Point"}
}