{
  "type": "Feature",
  "properties": {
    "iso:country":"IN",
    "ks:ks_name":"Chala Kura Pt V",
    "ks:ks_pop":923,
    "ks:ks_type":"VILLAGE",
    "name:eng_x_preferred":[
        "Chala Kura Pt V"
    ],
    "wof:name":"Chala Kura Pt V",
    "wof:placetype":"locality",
    "wof:population":923
},
  "geometry": {"coordinates":[90.06444500000001,26.013278],"type":"Point"}
}