{
  "type": "Feature",
  "properties": {
    "gn:admin1_code":"36",
    "gn:admin2_code":"196.0",
    "gn:asciiname":"Ranpur",
    "gn:country_code":"IN",
    "gn:dem":76,
    "gn:feature_class":"P",
    "gn:feature_code":"PPL",
    "gn:name":"Ranpur",
    "gn:population":0,
    "gn:timezone":"Asia/Kolkata",
    "iso:country":"IN",
    "name:cat_x_preferred":[
        "Ranpur"
    ],
    "name:guj_x_preferred":[
        "\u0ab0\u0abe\u0aa3\u0aaa\u0ac1\u0ab0"
    ],
    "name:hin_x_preferred":[
        "\u0930\u093e\u0923\u092a\u0941\u0930"
    ],
    "wof:name":"Ranpur",
    "wof:placetype":"locality"
},
  "geometry": {"coordinates":[83.41588,25.44461],"type":"Point"}
}