{
  "type": "Feature",
  "properties": {
    "iso:country":"IN",
    "ks:ks_alt_nam":"TINGAREWASTI",
    "ks:ks_name":"Tingarewasti",
    "ks:ks_pop":105,
    "ks:ks_type":"HABITATION",
    "name:eng_x_preferred":[
        "Tingarewasti"
    ],
    "wof:name":"Tingarewasti",
    "wof:placetype":"locality",
    "wof:population":105
},
  "geometry": {"coordinates":[74.938197,17.56329],"type":"Point"}
}