{
  "type": "Feature",
  "properties": {
    "iso:country":"IN",
    "ks:ks_name":"Khundi",
    "ks:ks_pop":698,
    "ks:ks_type":"HABITATION",
    "name:eng_x_preferred":[
        "Khundi"
    ],
    "wof:name":"Khundi",
    "wof:placetype":"locality",
    "wof:population":698
},
  "geometry": {"coordinates":[74.272446,21.977729],"type":"Point"}
}