{
  "type": "Feature",
  "properties": {
    "gn:admin1_code":"28.0",
    "gn:admin2_code":"337.0",
    "gn:asciiname":"Chakla",
    "gn:country_code":"IN",
    "gn:dem":10,
    "gn:feature_class":"P",
    "gn:feature_code":"PPL",
    "gn:name":"Chakla",
    "gn:population":0,
    "gn:timezone":"Asia/Kolkata",
    "iso:country":"IN",
    "ks:ks_name":"Chakla",
    "ks:ks_pop":2353,
    "ks:ks_type":"VILLAGE",
    "ks:ks_uagg_main":0,
    "name:eng_x_preferred":[
        "Chakla"
    ],
    "name:hin_x_preferred":[
        "\u091a\u0915\u0932\u093e"
    ],
    "wof:name":"Chakla",
    "wof:placetype":"neighbourhood",
    "wof:population":2353
},
  "geometry": {"coordinates":[88.692654,22.756733],"type":"Point"}
}