{
  "type": "Feature",
  "properties": {
    "iso:country":"IN",
    "ks:ks_name":"Khasjangal",
    "ks:ks_pop":326,
    "ks:ks_type":"VILLAGE",
    "name:eng_x_preferred":[
        "Khasjangal"
    ],
    "wof:name":"Khasjangal",
    "wof:placetype":"locality",
    "wof:population":326
},
  "geometry": {"coordinates":[86.944329,22.343284],"type":"Point"}
}