{
  "type": "Feature",
  "properties": {
    "gn:admin1_code":"16.0",
    "gn:admin2_code":"520",
    "gn:asciiname":"Kune",
    "gn:country_code":"IN",
    "gn:dem":21,
    "gn:feature_class":"P",
    "gn:feature_code":"PPL",
    "gn:name":"K\u016bne",
    "gn:population":0,
    "gn:timezone":"Asia/Kolkata",
    "iso:country":"IN",
    "ks:ks_alt_nam":"K\u016bne",
    "ks:ks_name":"Kune",
    "ks:ks_pop":514,
    "ks:ks_type":"VILLAGE",
    "name:eng_x_preferred":[
        "Kune"
    ],
    "name:eng_x_variant":[
        "K\u016bne"
    ],
    "wof:name":"Kune",
    "wof:placetype":"locality",
    "wof:population":514
},
  "geometry": {"coordinates":[72.973573,18.608611],"type":"Point"}
}