{
  "type": "Feature",
  "properties": {
    "gn:admin1_code":"19.0",
    "gn:admin2_code":"568.0",
    "gn:asciiname":"Torebail",
    "gn:country_code":"IN",
    "gn:dem":668,
    "gn:feature_class":"P",
    "gn:feature_code":"PPL",
    "gn:name":"Torebail",
    "gn:population":0,
    "gn:timezone":"Asia/Kolkata",
    "iso:country":"IN",
    "ks:ks_name":"Thorebailu",
    "ks:ks_pop":411,
    "ks:ks_type":"VILLAGE",
    "name:eng_x_preferred":[
        "Thorebailu"
    ],
    "name:eng_x_variant":[
        "Torebail"
    ],
    "wof:name":"Thorebailu",
    "wof:placetype":"locality",
    "wof:population":411
},
  "geometry": {"coordinates":[75.298558,13.844139],"type":"Point"}
}