{
  "type": "Feature",
  "properties": {
    "iso:country":"IN",
    "ks:ks_alt_nam":"Al\u0101pur",
    "ks:ks_name":"Alapur",
    "ks:ks_type":"VILLAGE",
    "ks:ks_uagg_main":0,
    "name:eng_x_preferred":[
        "Alapur"
    ],
    "name:eng_x_variant":[
        "Al\u0101pur"
    ],
    "wof:name":"Alapur",
    "wof:placetype":"neighbourhood"
},
  "geometry": {"coordinates":[78.408079,17.457419],"type":"Point"}
}