{
  "type": "Feature",
  "properties": {
    "iso:country":"IN",
    "ks:ks_name":"Barvita",
    "ks:ks_pop":629,
    "ks:ks_type":"HABITATION",
    "name:eng_x_preferred":[
        "Barvita"
    ],
    "wof:name":"Barvita",
    "wof:placetype":"locality",
    "wof:population":629
},
  "geometry": {"coordinates":[90.50590800000001,26.178162],"type":"Point"}
}