{
  "type": "Feature",
  "properties": {
    "iso:country":"IN",
    "ks:ks_name":"14 H",
    "ks:ks_pop":12,
    "ks:ks_type":"VILLAGE",
    "name:eng_x_preferred":[
        "14 H"
    ],
    "wof:name":"14 H",
    "wof:placetype":"locality",
    "wof:population":12
},
  "geometry": {"coordinates":[73.033828,29.074835],"type":"Point"}
}