{
  "type": "Feature",
  "properties": {
    "gn:admin1_code":"19.0",
    "gn:admin2_code":"568.0",
    "gn:asciiname":"Venkatapura",
    "gn:country_code":"IN",
    "gn:dem":554,
    "gn:feature_class":"P",
    "gn:feature_code":"PPL",
    "gn:name":"Venkat\u0101pura",
    "gn:population":0,
    "gn:timezone":"Asia/Kolkata",
    "iso:country":"IN",
    "ks:ks_name":"Venkatapura",
    "ks:ks_pop":155,
    "ks:ks_type":"HABITATION",
    "name:eng_x_preferred":[
        "Venkatapura"
    ],
    "wof:name":"Venkatapura",
    "wof:placetype":"locality",
    "wof:population":155
},
  "geometry": {"coordinates":[75.13504,14.6062],"type":"Point"}
}