{
  "type": "Feature",
  "properties": {
    "iso:country":"IN",
    "ks:ks_name":"Talaiguda",
    "ks:ks_pop":50,
    "ks:ks_type":"HABITATION",
    "name:eng_x_preferred":[
        "Talaiguda"
    ],
    "wof:name":"Talaiguda",
    "wof:placetype":"locality",
    "wof:population":50
},
  "geometry": {"coordinates":[78.72029999999999,19.675287],"type":"Point"}
}