{
  "type": "Feature",
  "properties": {
    "iso:country":"IN",
    "ks:ks_name":"Panaragadi Jn.",
    "ks:ks_pop":746,
    "ks:ks_type":"HABITATION",
    "name:eng_x_preferred":[
        "Panaragadi Jn."
    ],
    "wof:name":"Panaragadi Jn.",
    "wof:placetype":"locality",
    "wof:population":746
},
  "geometry": {"coordinates":[76.295653,11.100772],"type":"Point"}
}