{
  "type": "Feature",
  "properties": {
    "iso:country":"IN",
    "ks:ks_name":"Buragam",
    "ks:ks_pop":1426,
    "ks:ks_type":"VILLAGE",
    "ks:ks_uagg_main":0,
    "name:eng_x_preferred":[
        "Buragam"
    ],
    "wof:name":"Buragam",
    "wof:placetype":"neighbourhood",
    "wof:population":1426
},
  "geometry": {"coordinates":[84.068314,18.732162],"type":"Point"}
}