{
  "type": "Feature",
  "properties": {
    "gn:admin1_code":"19.0",
    "gn:admin2_code":"574.0",
    "gn:asciiname":"Kote Kapparavalli",
    "gn:country_code":"IN",
    "gn:dem":866,
    "gn:feature_class":"P",
    "gn:feature_code":"PPL",
    "gn:name":"Kote Kapparavalli",
    "gn:population":0,
    "gn:timezone":"Asia/Kolkata",
    "iso:country":"IN",
    "wof:name":"Kote Kapparavalli",
    "wof:placetype":"locality"
},
  "geometry": {"coordinates":[76.11399999999998,12.66344],"type":"Point"}
}