{
  "type": "Feature",
  "properties": {
    "iso:country":"IN",
    "ks:ks_name":"Majhipada",
    "ks:ks_pop":450,
    "ks:ks_type":"HABITATION",
    "name:eng_x_preferred":[
        "Majhipada"
    ],
    "wof:name":"Majhipada",
    "wof:placetype":"locality",
    "wof:population":450
},
  "geometry": {"coordinates":[86.061362,20.116083],"type":"Point"}
}