{
  "type": "Feature",
  "properties": {
    "iso:country":"IN",
    "ks:ks_name":"Tunndri Guda Para",
    "ks:ks_pop":214,
    "ks:ks_type":"HABITATION",
    "name:eng_x_preferred":[
        "Tunndri Guda Para"
    ],
    "wof:name":"Tunndri Guda Para",
    "wof:placetype":"locality",
    "wof:population":214
},
  "geometry": {"coordinates":[81.94627699999999,19.417036],"type":"Point"}
}