{
  "type": "Feature",
  "properties": {
    "iso:country":"IN",
    "ks:ks_alt_nam":"Daldali khaspara",
    "ks:ks_name":"Daldali Khaspara",
    "ks:ks_pop":193,
    "ks:ks_type":"HABITATION",
    "name:eng_x_preferred":[
        "Daldali Khaspara"
    ],
    "wof:name":"Daldali Khaspara",
    "wof:placetype":"locality",
    "wof:population":193
},
  "geometry": {"coordinates":[83.173271,23.424883],"type":"Point"}
}