{
  "type": "Feature",
  "properties": {
    "gn:admin1_code":"39.0",
    "gn:admin2_code":"64.0",
    "gn:asciiname":"Baret",
    "gn:country_code":"IN",
    "gn:dem":1095,
    "gn:feature_class":"P",
    "gn:feature_code":"PPL",
    "gn:name":"Baret",
    "gn:population":0,
    "gn:timezone":"Asia/Kolkata",
    "iso:country":"IN",
    "ks:ks_name":"Baret",
    "ks:ks_pop":282,
    "ks:ks_type":"VILLAGE",
    "name:eng_x_preferred":[
        "Baret"
    ],
    "wof:name":"Baret",
    "wof:placetype":"locality",
    "wof:population":282
},
  "geometry": {"coordinates":[79.409964,29.70616],"type":"Point"}
}