{
  "type": "Feature",
  "properties": {
    "iso:country":"IN",
    "ks:ks_name":"Krushnapur Jungle",
    "ks:ks_pop":191,
    "ks:ks_type":"VILLAGE",
    "name:eng_x_preferred":[
        "Krushnapur Jungle"
    ],
    "wof:name":"Krushnapur Jungle",
    "wof:placetype":"locality",
    "wof:population":191
},
  "geometry": {"coordinates":[83.97731400000001,21.110081],"type":"Point"}
}