{
  "type": "Feature",
  "properties": {
    "iso:country":"IN",
    "ks:ks_name":"Chigrumajhudih",
    "ks:ks_pop":63,
    "ks:ks_type":"VILLAGE",
    "name:eng_x_preferred":[
        "Chigrumajhudih"
    ],
    "wof:name":"Chigrumajhudih",
    "wof:placetype":"locality",
    "wof:population":63
},
  "geometry": {"coordinates":[86.710688,24.573981],"type":"Point"}
}