{
  "type": "Feature",
  "properties": {
    "iso:country":"IN",
    "ks:ks_name":"Surhud",
    "ks:ks_pop":309,
    "ks:ks_type":"VILLAGE",
    "name:eng_x_preferred":[
        "Surhud"
    ],
    "wof:name":"Surhud",
    "wof:placetype":"locality",
    "wof:population":309
},
  "geometry": {"coordinates":[84.950042,24.323917],"type":"Point"}
}