{
  "type": "Feature",
  "properties": {
    "iso:country":"IN",
    "ks:ks_name":"Beejadakatte",
    "ks:ks_pop":95,
    "ks:ks_type":"HABITATION",
    "name:eng_x_preferred":[
        "Beejadakatte"
    ],
    "wof:name":"Beejadakatte",
    "wof:placetype":"locality",
    "wof:population":95
},
  "geometry": {"coordinates":[75.50843999999999,12.513657],"type":"Point"}
}