{
  "type": "Feature",
  "properties": {
    "iso:country":"IN",
    "ks:ks_name":"Jiari",
    "ks:ks_pop":292,
    "ks:ks_type":"VILLAGE",
    "name:eng_x_preferred":[
        "Jiari"
    ],
    "wof:name":"Jiari",
    "wof:placetype":"locality",
    "wof:population":292
},
  "geometry": {"coordinates":[83.602389,19.524346],"type":"Point"}
}