{
  "type": "Feature",
  "properties": {
    "iso:country":"IN",
    "name:ara_x_preferred":[
        "\u0641\u064a\u062c\u0627\u064a \u0646\u0627\u062c\u0627\u0631"
    ],
    "name:ben_bn_x_preferred":[
        "\u09ac\u09bf\u099c\u09df \u09a8\u0997\u09b0"
    ],
    "name:ben_in_x_preferred":[
        "\u09ac\u09bf\u099c\u09df \u09a8\u0997\u09b0"
    ],
    "name:eng_x_preferred":[
        "Vijay Nagar"
    ],
    "name:guj_x_preferred":[
        "\u0ab5\u0abf\u0a9c\u0aaf \u0aa8\u0a97\u0ab0"
    ],
    "name:hin_x_preferred":[
        "\u0935\u093f\u091c\u092f \u0928\u0917\u0930"
    ],
    "name:kan_x_preferred":[
        "\u0cb5\u0cbf\u0c9c\u0caf \u0ca8\u0c97\u0cb0"
    ],
    "name:mal_x_preferred":[
        "\u0d35\u0d3f\u0d1c\u0d2f\u0d4d \u0d28\u0d17\u0d7c"
    ],
    "name:mar_x_preferred":[
        "\u0935\u093f\u091c\u092f \u0928\u0917\u0930"
    ],
    "name:pan_x_preferred":[
        "\u0a35\u0a3f\u0a1c\u0a47 \u0a28\u0a17\u0a30"
    ],
    "name:tam_x_preferred":[
        "\u0bb5\u0bbf\u0b9c\u0baf\u0bcd \u0ba8\u0b95\u0bb0\u0bcd"
    ],
    "name:tel_x_preferred":[
        "\u0c35\u0c3f\u0c1c\u0c2f\u0c4d \u0c28\u0c17\u0c30\u0c4d"
    ],
    "name:urd_x_preferred":[
        "\u0648\u062c\u06d2 \u0646\u06af\u0631"
    ],
    "qs:gn_adm0_cc":"IN",
    "qs:gn_local":1269743,
    "qs:gn_nam_loc":"Indore Madhya Pradesh, Indore, IN",
    "qs:gn_namadm1":"35",
    "qs:local_max":114,
    "qs:local_sum":150,
    "qs:localhoods":3,
    "qs:name":"Vijay Nagar",
    "qs:name_adm0":"India",
    "qs:name_adm1":"Madhya Pradesh",
    "qs:name_adm2":"Indore",
    "qs:name_local":"Indore",
    "qs:photo_max":12,
    "qs:photo_sum":15,
    "qs:placetype":"Suburb",
    "qs:quad_count":4,
    "qs:woe_adm0":23424848,
    "qs:woe_adm1":2345749,
    "qs:woe_adm2":12586497,
    "qs:woe_lau":0,
    "qs:woe_local":2295408,
    "qs:woe_ver":"7.10.0",
    "wd:wordcount":127,
    "wof:lang":[
        "eng"
    ],
    "wof:name":"Vijay Nagar",
    "wof:placetype":"neighbourhood"
},
  "geometry": {"coordinates":[75.891541,22.752373],"type":"Point"}
}