{
  "type": "Feature",
  "properties": {
    "gn:admin1_code":"38",
    "gn:admin2_code":"367.0",
    "gn:asciiname":"Kurdeg",
    "gn:country_code":"IN",
    "gn:dem":429,
    "gn:feature_class":"P",
    "gn:feature_code":"PPL",
    "gn:name":"Kurdeg",
    "gn:population":0,
    "gn:timezone":"Asia/Kolkata",
    "iso:country":"IN",
    "ks:ks_name":"Kurdeg",
    "ks:ks_pop":1163,
    "ks:ks_type":"VILLAGE",
    "ks:ks_uagg_main":0,
    "name:eng_x_preferred":[
        "Kurdeg"
    ],
    "wof:name":"Kurdeg",
    "wof:placetype":"neighbourhood",
    "wof:population":1163
},
  "geometry": {"coordinates":[84.131874,22.570118],"type":"Point"}
}