{
  "type": "Feature",
  "properties": {
    "iso:country":"IN",
    "ks:ks_name":"Kusumbeda",
    "ks:ks_pop":400,
    "ks:ks_type":"HABITATION",
    "name:eng_x_preferred":[
        "Kusumbeda"
    ],
    "wof:name":"Kusumbeda",
    "wof:placetype":"locality",
    "wof:population":400
},
  "geometry": {"coordinates":[85.054168,21.933747],"type":"Point"}
}