{
  "type": "Feature",
  "properties": {
    "gn:country":"IN",
    "gn:fcode":"PPL",
    "gn:population":5699,
    "iso:country":"IN",
    "name:ben_x_preferred":[
        "\u0995\u09c1\u09af\u09bc\u09c7\u09a8\u09c1\u09b2\u09be"
    ],
    "name:bpy_x_preferred":[
        "\u0995\u09c1\u09af\u09bc\u09c7\u09a8\u09c1\u09b2\u09be"
    ],
    "name:ceb_x_preferred":[
        "Queula"
    ],
    "name:eng_x_preferred":[
        "Queula"
    ],
    "name:fra_x_preferred":[
        "Queula"
    ],
    "name:hin_x_preferred":[
        "\u0915\u094d\u092f\u0942\u0932\u093e"
    ],
    "name:ind_x_preferred":[
        "Queula"
    ],
    "name:ita_x_preferred":[
        "Queula"
    ],
    "name:msa_x_preferred":[
        "Queula"
    ],
    "name:nan_x_preferred":[
        "Queula"
    ],
    "name:nld_x_preferred":[
        "Queula"
    ],
    "name:por_x_preferred":[
        "Queula"
    ],
    "name:swe_x_preferred":[
        "Queula"
    ],
    "name:vie_x_preferred":[
        "Queula"
    ],
    "name:zho_x_preferred":[
        "\u5e93\u57c3\u4e4c\u62c9"
    ],
    "qs:name":"Queula",
    "qs:name_adm0":"India",
    "qs:name_adm1":"Goa",
    "qs:photos":98,
    "qs:photos_1k":20,
    "qs:photos_9k":1,
    "qs:photos_9r":3,
    "qs:photos_all":98,
    "qs:photos_sr":3,
    "qs:placetype":"Town",
    "qs:pop_sr":"5",
    "wd:wordcount":123,
    "wof:name":"Queula",
    "wof:placetype":"locality",
    "wof:population":5699
},
  "geometry": {"coordinates":[73.98557,15.39011],"type":"Point"}
}