{
  "type": "Feature",
  "properties": {
    "iso:country":"IN",
    "ks:ks_alt_nam":"Patelpara  piparpara",
    "ks:ks_name":"Patelpara Piparpara",
    "ks:ks_pop":220,
    "ks:ks_type":"HABITATION",
    "name:eng_x_preferred":[
        "Patelpara Piparpara"
    ],
    "name:eng_x_variant":[
        "Patelpara  piparpara"
    ],
    "wof:name":"Patelpara Piparpara",
    "wof:placetype":"locality",
    "wof:population":220
},
  "geometry": {"coordinates":[82.61958300000001,23.565517],"type":"Point"}
}