{
  "type": "Feature",
  "properties": {
    "iso:country":"IN",
    "ks:ks_name":"Godiyan Purwa",
    "ks:ks_pop":311,
    "ks:ks_type":"HABITATION",
    "ks:ks_uagg_main":0,
    "name:eng_x_preferred":[
        "Godiyan Purwa"
    ],
    "wof:name":"Godiyan Purwa",
    "wof:placetype":"neighbourhood",
    "wof:population":311
},
  "geometry": {"coordinates":[81.537853,27.5454],"type":"Point"}
}