{
  "type": "Feature",
  "properties": {
    "iso:country":"IN",
    "ks:ks_name":"Kamal Pur",
    "ks:ks_pop":80,
    "ks:ks_type":"VILLAGE",
    "ks:ks_uagg_main":0,
    "name:eng_x_preferred":[
        "Kamal Pur"
    ],
    "wof:name":"Kamal Pur",
    "wof:placetype":"neighbourhood",
    "wof:population":80
},
  "geometry": {"coordinates":[85.986982,26.374762],"type":"Point"}
}