{
  "type": "Feature",
  "properties": {
    "iso:country":"IN",
    "ks:ks_alt_nam":"Ch\u0101r\u0101dih",
    "ks:ks_name":"Charadih",
    "ks:ks_pop":167,
    "ks:ks_type":"VILLAGE",
    "name:eng_x_preferred":[
        "Charadih"
    ],
    "name:eng_x_variant":[
        "Ch\u0101r\u0101dih"
    ],
    "wof:name":"Charadih",
    "wof:placetype":"locality",
    "wof:population":167
},
  "geometry": {"coordinates":[85.420821,22.954864],"type":"Point"}
}