{
  "type": "Feature",
  "properties": {
    "gn:admin1_code":"36.0",
    "gn:admin2_code":"160",
    "gn:asciiname":"Sarai",
    "gn:country_code":"IN",
    "gn:dem":137,
    "gn:feature_class":"P",
    "gn:feature_code":"PPL",
    "gn:name":"Sarai",
    "gn:population":0,
    "gn:timezone":"Asia/Kolkata",
    "iso:country":"IN",
    "name:cat_x_preferred":[
        "Sarai"
    ],
    "name:ceb_x_preferred":[
        "Sarai"
    ],
    "name:deu_x_preferred":[
        "Sarai"
    ],
    "name:fra_x_preferred":[
        "Sarai"
    ],
    "name:ind_x_preferred":[
        "Sarai"
    ],
    "name:jpn_x_preferred":[
        "\u30b5\u30e9\u30a4"
    ],
    "name:nld_x_preferred":[
        "Sarai"
    ],
    "name:swe_x_preferred":[
        "Sarai"
    ],
    "name:tgl_x_preferred":[
        "Sarai"
    ],
    "wof:name":"Sarai",
    "wof:placetype":"locality"
},
  "geometry": {"coordinates":[79.80653000000002,27.16239],"type":"Point"}
}