{
  "type": "Feature",
  "properties": {
    "iso:country":"IN",
    "ks:ks_name":"Bishunpur",
    "ks:ks_pop":3488,
    "ks:ks_type":"VILLAGE",
    "name:eng_x_preferred":[
        "Bishunpur"
    ],
    "wof:name":"Bishunpur",
    "wof:placetype":"locality",
    "wof:population":3488
},
  "geometry": {"coordinates":[86.78304799999999,26.330706],"type":"Point"}
}