{
  "type": "Feature",
  "properties": {
    "gn:admin1_code":"19.0",
    "gn:admin2_code":"564.0",
    "gn:asciiname":"Naregal",
    "gn:country_code":"IN",
    "gn:dem":551,
    "gn:feature_class":"P",
    "gn:feature_code":"PPL",
    "gn:name":"Naregal",
    "gn:population":0,
    "gn:timezone":"Asia/Kolkata",
    "iso:country":"IN",
    "wof:name":"Naregal",
    "wof:placetype":"locality"
},
  "geometry": {"coordinates":[75.27963000000003,14.82804],"type":"Point"}
}