{
  "type": "Feature",
  "properties": {
    "iso:country":"IN",
    "ks:ks_name":"Sauaa",
    "ks:ks_pop":224,
    "ks:ks_type":"HABITATION",
    "ks:ks_uagg_main":0,
    "name:eng_x_preferred":[
        "Sauaa"
    ],
    "wof:name":"Sauaa",
    "wof:placetype":"neighbourhood",
    "wof:population":224
},
  "geometry": {"coordinates":[79.80819700000001,26.97885],"type":"Point"}
}