{
  "type": "Feature",
  "properties": {
    "gn:admin1_code":"10.0",
    "gn:admin2_code":"74.0",
    "gn:asciiname":"Faizpur",
    "gn:country_code":"IN",
    "gn:dem":241,
    "gn:feature_class":"P",
    "gn:feature_code":"PPL",
    "gn:name":"Faizpur",
    "gn:population":0,
    "gn:timezone":"Asia/Kolkata",
    "iso:country":"IN",
    "name:ben_x_preferred":[
        "\u09ab\u09af\u09bc\u09bf\u099c\u09aa\u09c1\u09b0"
    ],
    "name:bpy_x_preferred":[
        "\u09ab\u09af\u09bc\u09bf\u099c\u09aa\u09c1\u09b0"
    ],
    "name:ceb_x_preferred":[
        "Faizpur"
    ],
    "name:ita_x_preferred":[
        "Faizpur"
    ],
    "name:msa_x_preferred":[
        "Faizpur"
    ],
    "name:new_x_preferred":[
        "\u092b\u0948\u091c\u092a\u0941\u0930"
    ],
    "name:nld_x_preferred":[
        "Faizpur"
    ],
    "name:por_x_preferred":[
        "Faizpur"
    ],
    "name:swe_x_preferred":[
        "Faizpur"
    ],
    "name:urd_x_preferred":[
        "\u0641\u06cc\u0636 \u067e\u0648\u0631"
    ],
    "name:vie_x_preferred":[
        "Faizpur"
    ],
    "name:zho_x_preferred":[
        "\u6cd5\u4f0a\u5179\u666e\u5c14"
    ],
    "wof:name":"Faizpur",
    "wof:placetype":"locality"
},
  "geometry": {"coordinates":[76.71082,29.55901],"type":"Point"}
}