{
  "type": "Feature",
  "properties": {
    "gn:admin1_code":"10.0",
    "gn:admin2_code":"74.0",
    "gn:asciiname":"Faizpur",
    "gn:country_code":"IN",
    "gn:dem":241,
    "gn:feature_class":"P",
    "gn:feature_code":"PPL",
    "gn:name":"Faizpur",
    "gn:population":0,
    "gn:timezone":"Asia/Kolkata",
    "iso:country":"IN",
    "wof:name":"Faizpur",
    "wof:placetype":"locality"
},
  "geometry": {"coordinates":[76.71082,29.55901],"type":"Point"}
}