{
  "type": "Feature",
  "properties": {
    "gn:admin1_code":"21",
    "gn:admin2_code":"384.0",
    "gn:asciiname":"Tulka",
    "gn:country_code":"IN",
    "gn:dem":166,
    "gn:feature_class":"P",
    "gn:feature_code":"PPL",
    "gn:name":"Tulka",
    "gn:population":0,
    "gn:timezone":"Asia/Kolkata",
    "iso:country":"IN",
    "wof:name":"Tulka",
    "wof:placetype":"locality"
},
  "geometry": {"coordinates":[84.95863,20.60371],"type":"Point"}
}