{
  "type": "Feature",
  "properties": {
    "gn:admin1_code":"25.0",
    "gn:admin2_code":"608.0",
    "gn:asciiname":"Varappallattur",
    "gn:country_code":"IN",
    "gn:dem":265,
    "gn:feature_class":"P",
    "gn:feature_code":"PPL",
    "gn:name":"Varappallatt\u016br",
    "gn:population":0,
    "gn:timezone":"Asia/Kolkata",
    "iso:country":"IN",
    "ks:ks_name":"Varapallathur",
    "ks:ks_pop":120,
    "ks:ks_type":"HABITATION",
    "name:eng_x_preferred":[
        "Varapallathur"
    ],
    "name:eng_x_variant":[
        "Varappallattur"
    ],
    "wof:name":"Varapallathur",
    "wof:placetype":"locality",
    "wof:population":120
},
  "geometry": {"coordinates":[77.766336,11.863476],"type":"Point"}
}