{
  "type": "Feature",
  "properties": {
    "iso:country":"IN",
    "ks:ks_name":"Garudabasa",
    "ks:ks_pop":596,
    "ks:ks_type":"VILLAGE",
    "name:eng_x_preferred":[
        "Garudabasa"
    ],
    "wof:name":"Garudabasa",
    "wof:placetype":"locality",
    "wof:population":596
},
  "geometry": {"coordinates":[86.82615,21.753464],"type":"Point"}
}