{
  "type": "Feature",
  "properties": {
    "iso:country":"IN",
    "ks:ks_name":"Hathabhanri",
    "ks:ks_pop":865,
    "ks:ks_type":"VILLAGE",
    "name:eng_x_preferred":[
        "Hathabhanri"
    ],
    "wof:name":"Hathabhanri",
    "wof:placetype":"locality",
    "wof:population":865
},
  "geometry": {"coordinates":[84.262553,22.751335],"type":"Point"}
}