{
  "type": "Feature",
  "properties": {
    "iso:country":"IN",
    "ks:ks_name":"Jamna Pur",
    "ks:ks_pop":198,
    "ks:ks_type":"HABITATION",
    "name:eng_x_preferred":[
        "Jamna Pur"
    ],
    "wof:name":"Jamna Pur",
    "wof:placetype":"locality",
    "wof:population":198
},
  "geometry": {"coordinates":[85.313591,24.87488],"type":"Point"}
}