{
  "type": "Feature",
  "properties": {
    "gn:admin1_code":"19.0",
    "gn:admin2_code":"577.0",
    "gn:asciiname":"Yachanahalli",
    "gn:country_code":"IN",
    "gn:dem":713,
    "gn:feature_class":"P",
    "gn:feature_code":"PPL",
    "gn:name":"Y\u0101chanahalli",
    "gn:population":0,
    "gn:timezone":"Asia/Kolkata",
    "iso:country":"IN",
    "wof:name":"Yachanahalli",
    "wof:placetype":"locality"
},
  "geometry": {"coordinates":[76.89813000000002,12.39883],"type":"Point"}
}