{
  "type": "Feature",
  "properties": {
    "iso:country":"IN",
    "ks:ks_name":"Hodka",
    "ks:ks_pop":2954,
    "ks:ks_type":"VILLAGE",
    "name:eng_x_preferred":[
        "Hodka"
    ],
    "wof:name":"Hodka",
    "wof:placetype":"locality",
    "wof:population":2954
},
  "geometry": {"coordinates":[69.582722,23.663223],"type":"Point"}
}