{
  "type": "Feature",
  "properties": {
    "iso:country":"IN",
    "ks:ks_name":"Chmar Tola",
    "ks:ks_pop":124,
    "ks:ks_type":"HABITATION",
    "ks:ks_uagg_main":0,
    "name:eng_x_preferred":[
        "Chmar Tola"
    ],
    "wof:name":"Chmar Tola",
    "wof:placetype":"neighbourhood",
    "wof:population":124
},
  "geometry": {"coordinates":[83.86797199999999,26.089104],"type":"Point"}
}