{
  "type": "Feature",
  "properties": {
    "gn:admin1_code":"34.0",
    "gn:admin2_code":"207.0",
    "gn:asciiname":"Bhatsimar",
    "gn:country_code":"IN",
    "gn:dem":63,
    "gn:feature_class":"P",
    "gn:feature_code":"PPL",
    "gn:name":"Bhatsimar",
    "gn:population":0,
    "gn:timezone":"Asia/Kolkata",
    "iso:country":"IN",
    "ks:ks_alt_nam":"BHATSIMAR",
    "ks:ks_name":"Bhatsimar",
    "ks:ks_pop":7376,
    "ks:ks_type":"HABITATION",
    "name:eng_x_preferred":[
        "Bhatsimar"
    ],
    "wof:name":"Bhatsimar",
    "wof:placetype":"locality",
    "wof:population":7376
},
  "geometry": {"coordinates":[86.219993,26.365739],"type":"Point"}
}