{
  "type": "Feature",
  "properties": {
    "gn:admin1_code":"25.0",
    "gn:admin2_code":"606.0",
    "gn:asciiname":"Cheri",
    "gn:country_code":"IN",
    "gn:dem":166,
    "gn:feature_class":"P",
    "gn:feature_code":"PPL",
    "gn:name":"Cheri",
    "gn:population":0,
    "gn:timezone":"Asia/Kolkata",
    "iso:country":"IN",
    "name:ceb_x_preferred":[
        "Cheri"
    ],
    "name:est_x_preferred":[
        "Cheri"
    ],
    "name:fin_x_preferred":[
        "Cheri"
    ],
    "name:nld_x_preferred":[
        "Cheri"
    ],
    "name:swe_x_preferred":[
        "Cheri"
    ],
    "wof:name":"Cheri",
    "wof:placetype":"locality"
},
  "geometry": {"coordinates":[79.21935000000001,12.67535],"type":"Point"}
}