{
  "type": "Feature",
  "properties": {
    "iso:country":"IN",
    "ks:ks_name":"Malik Salpara",
    "ks:ks_pop":320,
    "ks:ks_type":"HABITATION",
    "name:eng_x_preferred":[
        "Malik Salpara"
    ],
    "wof:name":"Malik Salpara",
    "wof:placetype":"locality",
    "wof:population":320
},
  "geometry": {"coordinates":[87.938182,22.613127],"type":"Point"}
}