{
  "type": "Feature",
  "properties": {
    "iso:country":"IN",
    "ks:ks_name":"Harai",
    "ks:ks_type":"VILLAGE",
    "name:eng_x_preferred":[
        "Harai"
    ],
    "wof:name":"Harai",
    "wof:placetype":"locality"
},
  "geometry": {"coordinates":[83.304436,24.610256],"type":"Point"}
}