{
  "type": "Feature",
  "properties": {
    "iso:country":"IN",
    "ks:ks_alt_nam":"Pahal\u0101m\u0101ra",
    "ks:ks_name":"Pahalamara",
    "ks:ks_type":"VILLAGE",
    "name:eng_x_preferred":[
        "Pahalamara"
    ],
    "name:eng_x_variant":[
        "Pahal\u0101m\u0101ra"
    ],
    "wof:name":"Pahalamara",
    "wof:placetype":"locality"
},
  "geometry": {"coordinates":[84.525051,21.65981],"type":"Point"}
}