{
  "type": "Feature",
  "properties": {
    "iso:country":"IN",
    "ks:ks_name":"Chikkahalli Kaval",
    "ks:ks_pop":104,
    "ks:ks_type":"VILLAGE",
    "name:eng_x_preferred":[
        "Chikkahalli Kaval"
    ],
    "wof:name":"Chikkahalli Kaval",
    "wof:placetype":"locality",
    "wof:population":104
},
  "geometry": {"coordinates":[76.599079,13.154999],"type":"Point"}
}