{
  "type": "Feature",
  "properties": {
    "iso:country":"IN",
    "ks:ks_name":"Harijanawada",
    "ks:ks_pop":359,
    "ks:ks_type":"HABITATION",
    "ks:ks_uagg_main":0,
    "name:eng_x_preferred":[
        "Harijanawada"
    ],
    "wof:name":"Harijanawada",
    "wof:placetype":"neighbourhood",
    "wof:population":359
},
  "geometry": {"coordinates":[78.80726900000001,19.071002],"type":"Point"}
}