{
  "type": "Feature",
  "properties": {
    "gn:admin1_code":"36",
    "gn:admin2_code":"199.0",
    "gn:asciiname":"Amoi",
    "gn:country_code":"IN",
    "gn:dem":220,
    "gn:feature_class":"P",
    "gn:feature_code":"PPL",
    "gn:name":"Amoi",
    "gn:population":0,
    "gn:timezone":"Asia/Kolkata",
    "iso:country":"IN",
    "name:ita_x_preferred":[
        "Amoi"
    ],
    "name:pol_x_preferred":[
        "Amoi"
    ],
    "name:zho_x_preferred":[
        "\u590f\u65b0\u79d1\u6280"
    ],
    "wof:name":"Amoi",
    "wof:placetype":"locality"
},
  "geometry": {"coordinates":[82.49079999999999,24.9436],"type":"Point"}
}