{
  "type": "Feature",
  "properties": {
    "iso:country":"IN",
    "ks:ks_name":"No 1 Gandhmow",
    "ks:ks_pop":2406,
    "ks:ks_type":"HABITATION",
    "ks:ks_uagg_main":0,
    "name:eng_x_preferred":[
        "No 1 Gandhmow"
    ],
    "wof:name":"No 1 Gandhmow",
    "wof:placetype":"neighbourhood",
    "wof:population":2406
},
  "geometry": {"coordinates":[91.554429,26.200231],"type":"Point"}
}