{
  "type": "Feature",
  "properties": {
    "gn:admin1_code":"36",
    "gn:admin2_code":"167.0",
    "gn:asciiname":"Budhni",
    "gn:country_code":"IN",
    "gn:dem":387,
    "gn:feature_class":"P",
    "gn:feature_code":"PPL",
    "gn:name":"B\u016bdhni",
    "gn:population":0,
    "gn:timezone":"Asia/Kolkata",
    "iso:country":"IN",
    "name:ben_x_preferred":[
        "\u09ac\u09c1\u09a7\u09a8\u09bf"
    ],
    "name:bpy_x_preferred":[
        "\u09ac\u09c1\u09a7\u09a8\u09bf"
    ],
    "name:hin_x_preferred":[
        "\u092c\u0941\u0926\u0928\u0940"
    ],
    "name:ita_x_preferred":[
        "Budni"
    ],
    "name:msa_x_preferred":[
        "Budhni"
    ],
    "name:new_x_preferred":[
        "\u092c\u0941\u0927\u094d\u0928\u0940"
    ],
    "name:nld_x_preferred":[
        "Budhni"
    ],
    "name:por_x_preferred":[
        "Budhni"
    ],
    "name:spa_x_preferred":[
        "Budhni"
    ],
    "name:vie_x_preferred":[
        "Budhni"
    ],
    "name:zho_x_preferred":[
        "\u5e03\u5fb7\u5c3c"
    ],
    "wof:name":"Budhni",
    "wof:placetype":"locality"
},
  "geometry": {"coordinates":[78.69695,24.43497],"type":"Point"}
}