{
  "type": "Feature",
  "properties": {
    "iso:country":"IN",
    "ks:ks_name":"Agaramkalappal",
    "ks:ks_pop":250,
    "ks:ks_type":"HABITATION",
    "name:eng_x_preferred":[
        "Agaramkalappal"
    ],
    "wof:name":"Agaramkalappal",
    "wof:placetype":"locality",
    "wof:population":250
},
  "geometry": {"coordinates":[79.550545,10.52818],"type":"Point"}
}