{
  "type": "Feature",
  "properties": {
    "iso:country":"IN",
    "ks:ks_alt_nam":"Atar kale wasti",
    "ks:ks_name":"Atar Kale Wasti",
    "ks:ks_pop":249,
    "ks:ks_type":"HABITATION",
    "name:eng_x_preferred":[
        "Atar Kale Wasti"
    ],
    "wof:name":"Atar Kale Wasti",
    "wof:placetype":"locality",
    "wof:population":249
},
  "geometry": {"coordinates":[74.947835,18.584152],"type":"Point"}
}