{
  "type": "Feature",
  "properties": {
    "gn:admin1_code":"36",
    "gn:admin2_code":"194.0",
    "gn:asciiname":"Bisauli",
    "gn:country_code":"IN",
    "gn:dem":94,
    "gn:feature_class":"P",
    "gn:feature_code":"PPL",
    "gn:name":"Bisauli",
    "gn:population":0,
    "gn:timezone":"Asia/Kolkata",
    "iso:country":"IN",
    "name:bpy_x_preferred":[
        "\u09ac\u09bf\u09b8\u09cc\u09b2\u09bf"
    ],
    "name:ceb_x_preferred":[
        "Bisauli"
    ],
    "name:hin_x_preferred":[
        "\u092c\u093f\u0938\u094c\u0932\u0940"
    ],
    "name:ita_x_preferred":[
        "Bisauli"
    ],
    "name:mlg_x_preferred":[
        "Bisauli"
    ],
    "name:msa_x_preferred":[
        "Bisauli"
    ],
    "name:new_x_preferred":[
        "\u092c\u093f\u0938\u094c\u0932\u0940"
    ],
    "name:nld_x_preferred":[
        "Bisauli"
    ],
    "name:pol_x_preferred":[
        "Bisauli"
    ],
    "name:por_x_preferred":[
        "Bisauli"
    ],
    "name:swe_x_preferred":[
        "Bisauli"
    ],
    "name:urd_x_preferred":[
        "\u0628\u0633\u0648\u0644\u06cc"
    ],
    "name:vie_x_preferred":[
        "Bisauli"
    ],
    "name:zho_x_preferred":[
        "\u6bd4\u7ecd\u5229"
    ],
    "wof:name":"Bisauli",
    "wof:placetype":"locality"
},
  "geometry": {"coordinates":[82.4971,26.04481],"type":"Point"}
}