{
  "type": "Feature",
  "properties": {
    "gn:admin1_code":"35",
    "gn:admin2_code":"455.0",
    "gn:asciiname":"Mandal",
    "gn:country_code":"IN",
    "gn:dem":1100,
    "gn:feature_class":"P",
    "gn:feature_code":"PPL",
    "gn:name":"M\u0101ndal",
    "gn:population":0,
    "gn:timezone":"Asia/Kolkata",
    "iso:country":"IN",
    "name:nld_x_preferred":[
        "Mandal"
    ],
    "wof:name":"Mandal",
    "wof:placetype":"locality"
},
  "geometry": {"coordinates":[78.8133,22.45385],"type":"Point"}
}