{
  "type": "Feature",
  "properties": {
    "iso:country":"IN",
    "ks:ks_name":"Dungarpura",
    "ks:ks_pop":781,
    "ks:ks_type":"HABITATION",
    "ks:ks_uagg_main":0,
    "name:eng_x_preferred":[
        "Dungarpura"
    ],
    "wof:name":"Dungarpura",
    "wof:placetype":"neighbourhood",
    "wof:population":781
},
  "geometry": {"coordinates":[76.72687000000001,23.856338],"type":"Point"}
}