{
  "type": "Feature",
  "properties": {
    "gn:admin1_code":"34",
    "gn:admin2_code":"232.0",
    "gn:asciiname":"Birbalpur",
    "gn:country_code":"IN",
    "gn:dem":71,
    "gn:feature_class":"P",
    "gn:feature_code":"PPL",
    "gn:name":"Birbalpur",
    "gn:population":0,
    "gn:timezone":"Asia/Kolkata",
    "iso:country":"IN",
    "wof:name":"Birbalpur",
    "wof:placetype":"locality"
},
  "geometry": {"coordinates":[83.87413000000002,25.33294],"type":"Point"}
}