{
  "type": "Feature",
  "properties": {
    "gn:admin1_code":"37.0",
    "gn:admin2_code":"408.0",
    "gn:asciiname":"Bhurbhusi",
    "gn:country_code":"IN",
    "gn:dem":321,
    "gn:feature_class":"P",
    "gn:feature_code":"PPL",
    "gn:name":"Bhurbhusi",
    "gn:population":0,
    "gn:timezone":"Asia/Kolkata",
    "iso:country":"IN",
    "name:eng_x_preferred":[
        "Bhurbhusi"
    ],
    "wof:name":"Bhurbhusi",
    "wof:placetype":"locality"
},
  "geometry": {"coordinates":[81.11620000000001,21.66716],"type":"Point"}
}