{
  "type": "Feature",
  "properties": {
    "gn:admin1_code":"16",
    "gn:admin2_code":"514.0",
    "gn:asciiname":"Ranjani",
    "gn:country_code":"IN",
    "gn:dem":458,
    "gn:feature_class":"P",
    "gn:feature_code":"PPL",
    "gn:name":"R\u0101njani",
    "gn:population":0,
    "gn:timezone":"Asia/Kolkata",
    "iso:country":"IN",
    "name:ara_x_preferred":[
        "\u0631\u0627\u0646\u062c\u0627\u0646\u064a"
    ],
    "name:ben_bn_x_preferred":[
        "\u09b0\u099e\u09cd\u099c\u09a8\u09bf"
    ],
    "name:ben_in_x_preferred":[
        "\u09b0\u099e\u09cd\u099c\u09a8\u09bf"
    ],
    "name:guj_x_preferred":[
        "\u0ab0\u0a82\u0a9c\u0aa8\u0ac0"
    ],
    "name:hin_x_preferred":[
        "\u0930\u0902\u091c\u0928\u0940"
    ],
    "name:kan_x_preferred":[
        "\u0cb0\u0c82\u0c9c\u0ca8\u0cbf"
    ],
    "name:mal_x_preferred":[
        "\u0d30\u0d1e\u0d4d\u0d1c\u0d28\u0d3f"
    ],
    "name:mar_x_preferred":[
        "\u0930\u0902\u091c\u0928\u0940"
    ],
    "name:pan_x_preferred":[
        "\u0a30\u0a70\u0a1c\u0a28\u0a40"
    ],
    "name:tam_x_preferred":[
        "\u0bb0\u0b9e\u0bcd\u0b9a\u0ba9\u0bbf"
    ],
    "name:tel_x_preferred":[
        "\u0c30\u0c02\u0c1c\u0c28\u0c3f"
    ],
    "name:und_x_variant":[
        "Ranjni",
        "R\u0101njani"
    ],
    "name:urd_x_preferred":[
        "\u0631\u0646\u062c\u0646\u06cc"
    ],
    "wof:name":"Ranjani",
    "wof:placetype":"locality"
},
  "geometry": {"coordinates":[76.12298,19.65487000000001],"type":"Point"}
}