{
  "type": "Feature",
  "properties": {
    "gn:admin1_code":"16",
    "gn:admin2_code":"514.0",
    "gn:asciiname":"Ranjani",
    "gn:country_code":"IN",
    "gn:dem":458,
    "gn:feature_class":"P",
    "gn:feature_code":"PPL",
    "gn:name":"R\u0101njani",
    "gn:population":0,
    "gn:timezone":"Asia/Kolkata",
    "iso:country":"IN",
    "name:und_x_variant":[
        "Ranjni",
        "R\u0101njani"
    ],
    "wof:name":"Ranjani",
    "wof:placetype":"locality"
},
  "geometry": {"coordinates":[76.12298,19.65487000000001],"type":"Point"}
}