{
  "type": "Feature",
  "properties": {
    "iso:country":"IN",
    "ks:ks_name":"Chikkabargi",
    "ks:ks_pop":210,
    "ks:ks_type":"HABITATION",
    "name:eng_x_preferred":[
        "Chikkabargi"
    ],
    "wof:name":"Chikkabargi",
    "wof:placetype":"locality",
    "wof:population":210
},
  "geometry": {"coordinates":[76.429073,11.892588],"type":"Point"}
}