{
  "type": "Feature",
  "properties": {
    "iso:country":"IN",
    "ks:ks_alt_nam":"Ind\u0101pur",
    "ks:ks_name":"Indapur",
    "ks:ks_type":"VILLAGE",
    "name:eng_x_preferred":[
        "Indapur"
    ],
    "name:eng_x_variant":[
        "Ind\u0101pur"
    ],
    "wof:name":"Indapur",
    "wof:placetype":"locality"
},
  "geometry": {"coordinates":[77.54902,20.861938],"type":"Point"}
}