{
  "type": "Feature",
  "properties": {
    "gn:admin1_code":"21.0",
    "gn:admin2_code":"381",
    "gn:asciiname":"Barang",
    "gn:country_code":"IN",
    "gn:dem":30,
    "gn:feature_class":"P",
    "gn:feature_code":"PPL",
    "gn:name":"B\u0101rang",
    "gn:population":0,
    "gn:timezone":"Asia/Kolkata",
    "iso:country":"IN",
    "name:ceb_x_preferred":[
        "Barang"
    ],
    "name:fas_x_preferred":[
        "\u0628\u0631\u0646\u06af"
    ],
    "name:nld_x_preferred":[
        "Barang"
    ],
    "name:swe_x_preferred":[
        "Barang"
    ],
    "wof:name":"Barang",
    "wof:placetype":"locality"
},
  "geometry": {"coordinates":[85.83496,20.40714],"type":"Point"}
}