{
  "type": "Feature",
  "properties": {
    "gn:admin1_code":"21.0",
    "gn:admin2_code":"381",
    "gn:asciiname":"Barang",
    "gn:country_code":"IN",
    "gn:dem":30,
    "gn:feature_class":"P",
    "gn:feature_code":"PPL",
    "gn:name":"B\u0101rang",
    "gn:population":0,
    "gn:timezone":"Asia/Kolkata",
    "iso:country":"IN",
    "ks:ks_name":"Baranga",
    "ks:ks_pop":1334,
    "ks:ks_type":"HABITATION",
    "name:ceb_x_preferred":[
        "Barang"
    ],
    "name:eng_x_preferred":[
        "Baranga"
    ],
    "name:eng_x_variant":[
        "Barang"
    ],
    "name:fas_x_preferred":[
        "\u0628\u0631\u0646\u06af"
    ],
    "name:nld_x_preferred":[
        "Barang"
    ],
    "name:swe_x_preferred":[
        "Barang"
    ],
    "wof:name":"Baranga",
    "wof:placetype":"locality",
    "wof:population":1334
},
  "geometry": {"coordinates":[85.825885,20.41899],"type":"Point"}
}