{
  "type": "Feature",
  "properties": {
    "iso:country":"IN",
    "ks:ks_name":"Hullekere",
    "ks:ks_pop":97,
    "ks:ks_type":"VILLAGE",
    "name:eng_x_preferred":[
        "Hullekere"
    ],
    "wof:name":"Hullekere",
    "wof:placetype":"locality",
    "wof:population":97
},
  "geometry": {"coordinates":[76.90805,13.158087],"type":"Point"}
}