{
  "type": "Feature",
  "properties": {
    "gn:admin1_code":"19.0",
    "gn:admin2_code":"556.0",
    "gn:asciiname":"Gidnaikanhal",
    "gn:country_code":"IN",
    "gn:dem":573,
    "gn:feature_class":"P",
    "gn:feature_code":"PPL",
    "gn:name":"Gidn\u0101ikanh\u0101l",
    "gn:population":0,
    "gn:timezone":"Asia/Kolkata",
    "iso:country":"IN",
    "wof:name":"Gidnaikanhal",
    "wof:placetype":"locality"
},
  "geometry": {"coordinates":[75.82529,15.89047],"type":"Point"}
}