{
  "type": "Feature",
  "properties": {
    "iso:country":"IN",
    "ks:ks_name":"Dharola Faliya",
    "ks:ks_pop":428,
    "ks:ks_type":"HABITATION",
    "ks:ks_uagg_main":0,
    "name:eng_x_preferred":[
        "Dharola Faliya"
    ],
    "wof:name":"Dharola Faliya",
    "wof:placetype":"neighbourhood",
    "wof:population":428
},
  "geometry": {"coordinates":[73.38525,22.812817],"type":"Point"}
}