{
  "type": "Feature",
  "properties": {
    "iso:country":"IN",
    "ks:ks_name":"Dhatilpada",
    "ks:ks_pop":94,
    "ks:ks_type":"HABITATION",
    "name:eng_x_preferred":[
        "Dhatilpada"
    ],
    "wof:name":"Dhatilpada",
    "wof:placetype":"locality",
    "wof:population":94
},
  "geometry": {"coordinates":[73.178856,19.952361],"type":"Point"}
}