{
  "type": "Feature",
  "properties": {
    "iso:country":"IN",
    "ks:ks_name":"Chheetra",
    "ks:ks_pop":1014,
    "ks:ks_type":"VILLAGE",
    "ks:ks_uagg_main":0,
    "name:eng_x_preferred":[
        "Chheetra"
    ],
    "wof:name":"Chheetra",
    "wof:placetype":"neighbourhood",
    "wof:population":1014
},
  "geometry": {"coordinates":[78.24975999999999,28.905954],"type":"Point"}
}