{
  "type": "Feature",
  "properties": {
    "iso:country":"IN",
    "ks:ks_name":"Muniyaru",
    "ks:ks_pop":51,
    "ks:ks_type":"HABITATION",
    "name:eng_x_preferred":[
        "Muniyaru"
    ],
    "wof:name":"Muniyaru",
    "wof:placetype":"locality",
    "wof:population":51
},
  "geometry": {"coordinates":[75.26732800000001,13.545728],"type":"Point"}
}