{
  "type": "Feature",
  "properties": {
    "iso:country":"IN",
    "ks:ks_name":"Bata",
    "ks:ks_pop":154,
    "ks:ks_type":"VILLAGE",
    "name:eng_x_preferred":[
        "Bata"
    ],
    "wof:name":"Bata",
    "wof:placetype":"locality",
    "wof:population":154
},
  "geometry": {"coordinates":[80.320407,30.030514],"type":"Point"}
}