{
  "type": "Feature",
  "properties": {
    "gn:admin1_code":"36",
    "gn:admin2_code":"159.0",
    "gn:asciiname":"Reha",
    "gn:country_code":"IN",
    "gn:dem":150,
    "gn:feature_class":"P",
    "gn:feature_code":"PPL",
    "gn:name":"Reha",
    "gn:population":0,
    "gn:timezone":"Asia/Kolkata",
    "iso:country":"IN",
    "name:guj_x_preferred":[
        "\u0aae\u0acb\u0a9f\u0abe \u0ab0\u0ac7\u0ab9\u0abe"
    ],
    "name:msa_x_preferred":[
        "Reha"
    ],
    "wof:name":"Reha",
    "wof:placetype":"locality"
},
  "geometry": {"coordinates":[79.52574,27.38238],"type":"Point"}
}