{
  "type": "Feature",
  "properties": {
    "iso:country":"IN",
    "ks:ks_name":"Dhapadpada",
    "ks:ks_pop":90,
    "ks:ks_type":"HABITATION",
    "name:eng_x_preferred":[
        "Dhapadpada"
    ],
    "wof:name":"Dhapadpada",
    "wof:placetype":"locality",
    "wof:population":90
},
  "geometry": {"coordinates":[73.165367,19.543106],"type":"Point"}
}