{
  "type": "Feature",
  "properties": {
    "gn:admin1_code":"10.0",
    "gn:admin2_code":"81.0",
    "gn:asciiname":"Badesra",
    "gn:country_code":"IN",
    "gn:dem":224,
    "gn:feature_class":"P",
    "gn:feature_code":"PPL",
    "gn:name":"Badesra",
    "gn:population":0,
    "gn:timezone":"Asia/Kolkata",
    "iso:country":"IN",
    "name:tat_x_preferred":[
        "\u0411\u0430\u0434\u0435\u0441\u0440\u0430"
    ],
    "wof:name":"Badesra",
    "wof:placetype":"locality"
},
  "geometry": {"coordinates":[76.21009000000002,28.9263],"type":"Point"}
}