{
  "type": "Feature",
  "properties": {
    "iso:country":"IN",
    "ks:ks_name":"Wakadepada",
    "ks:ks_pop":64,
    "ks:ks_type":"HABITATION",
    "name:eng_x_preferred":[
        "Wakadepada"
    ],
    "wof:name":"Wakadepada",
    "wof:placetype":"locality",
    "wof:population":64
},
  "geometry": {"coordinates":[73.05630499999999,19.665893],"type":"Point"}
}