{
  "type": "Feature",
  "properties": {
    "iso:country":"IN",
    "ks:ks_name":"Chaipat Diyal",
    "ks:ks_pop":2137,
    "ks:ks_type":"HABITATION",
    "name:eng_x_preferred":[
        "Chaipat Diyal"
    ],
    "wof:name":"Chaipat Diyal",
    "wof:placetype":"locality",
    "wof:population":2137
},
  "geometry": {"coordinates":[87.794842,22.569626],"type":"Point"}
}