{
  "type": "Feature",
  "properties": {
    "gn:admin1_code":"39.0",
    "gn:admin2_code":"64.0",
    "gn:asciiname":"Majgaon",
    "gn:country_code":"IN",
    "gn:dem":894,
    "gn:feature_class":"P",
    "gn:feature_code":"PPL",
    "gn:name":"Majgaon",
    "gn:population":0,
    "gn:timezone":"Asia/Kolkata",
    "iso:country":"IN",
    "wof:name":"Majgaon",
    "wof:placetype":"locality"
},
  "geometry": {"coordinates":[79.35854999999999,29.70476],"type":"Point"}
}