{
  "type": "Feature",
  "properties": {
    "gn:admin1_code":"39.0",
    "gn:admin2_code":"64.0",
    "gn:asciiname":"Majgaon",
    "gn:country_code":"IN",
    "gn:dem":894,
    "gn:feature_class":"P",
    "gn:feature_code":"PPL",
    "gn:name":"Majgaon",
    "gn:population":0,
    "gn:timezone":"Asia/Kolkata",
    "iso:country":"IN",
    "ks:ks_name":"Majgaon",
    "ks:ks_type":"VILLAGE",
    "name:bpy_x_preferred":[
        "\u09ae\u09be\u099d\u0997\u09be\u0981\u0993"
    ],
    "name:eng_x_preferred":[
        "Majgaon"
    ],
    "name:ita_x_preferred":[
        "Majgaon"
    ],
    "name:msa_x_preferred":[
        "Majgaon"
    ],
    "name:nld_x_preferred":[
        "Majgaon"
    ],
    "name:por_x_preferred":[
        "Majgaon"
    ],
    "name:vie_x_preferred":[
        "Majgaon"
    ],
    "name:zho_x_preferred":[
        "\u9a6c\u6770\u52a0\u5965\u6069"
    ],
    "wof:name":"Majgaon",
    "wof:placetype":"locality"
},
  "geometry": {"coordinates":[79.358552,29.704757],"type":"Point"}
}