{
  "type": "Feature",
  "properties": {
    "iso:country":"IN",
    "ks:ks_alt_nam":"KUTCH COLONEY",
    "ks:ks_name":"Kutch Coloney",
    "ks:ks_pop":146,
    "ks:ks_type":"HABITATION",
    "name:eng_x_preferred":[
        "Kutch Coloney"
    ],
    "wof:name":"Kutch Coloney",
    "wof:placetype":"locality",
    "wof:population":146
},
  "geometry": {"coordinates":[91.64439900000001,23.924292],"type":"Point"}
}