{
  "type": "Feature",
  "properties": {
    "iso:country":"IN",
    "ks:ks_name":"Beldari",
    "ks:ks_pop":191,
    "ks:ks_type":"HABITATION",
    "name:eng_x_preferred":[
        "Beldari"
    ],
    "wof:name":"Beldari",
    "wof:placetype":"locality",
    "wof:population":191
},
  "geometry": {"coordinates":[85.058115,25.04719],"type":"Point"}
}