{
  "type": "Feature",
  "properties": {
    "iso:country":"IN",
    "ks:ks_name":"Kallehalli",
    "ks:ks_pop":130,
    "ks:ks_type":"HABITATION",
    "name:eng_x_preferred":[
        "Kallehalli"
    ],
    "wof:name":"Kallehalli",
    "wof:placetype":"locality",
    "wof:population":130
},
  "geometry": {"coordinates":[75.92287,13.198327],"type":"Point"}
}