{
  "type": "Feature",
  "properties": {
    "iso:country":"IN",
    "ks:ks_alt_nam":"Dabli chapori",
    "ks:ks_name":"Dabli Chapori",
    "ks:ks_pop":324,
    "ks:ks_type":"HABITATION",
    "name:eng_x_preferred":[
        "Dabli Chapori"
    ],
    "wof:name":"Dabli Chapori",
    "wof:placetype":"locality",
    "wof:population":324
},
  "geometry": {"coordinates":[94.488223,27.041397],"type":"Point"}
}