{
  "type": "Feature",
  "properties": {
    "gn:admin1_code":"39",
    "gn:admin2_code":"61.0",
    "gn:asciiname":"Mallakhola",
    "gn:country_code":"IN",
    "gn:dem":1539,
    "gn:feature_class":"P",
    "gn:feature_code":"PPL",
    "gn:name":"Mall\u0101khola",
    "gn:population":0,
    "gn:timezone":"Asia/Kolkata",
    "iso:country":"IN",
    "wof:name":"Mallakhola",
    "wof:placetype":"locality"
},
  "geometry": {"coordinates":[78.95976999999998,29.70347000000001],"type":"Point"}
}