{
  "type": "Feature",
  "properties": {
    "gn:admin1_code":"39",
    "gn:admin2_code":"61.0",
    "gn:asciiname":"Mallakhola",
    "gn:country_code":"IN",
    "gn:dem":1539,
    "gn:feature_class":"P",
    "gn:feature_code":"PPL",
    "gn:name":"Mall\u0101khola",
    "gn:population":0,
    "gn:timezone":"Asia/Kolkata",
    "iso:country":"IN",
    "ks:ks_alt_nam":"Mall\u0101khola",
    "ks:ks_name":"Mallakhola",
    "ks:ks_type":"VILLAGE",
    "name:eng_x_preferred":[
        "Mallakhola"
    ],
    "name:eng_x_variant":[
        "Mall\u0101khola"
    ],
    "wof:name":"Mallakhola",
    "wof:placetype":"locality"
},
  "geometry": {"coordinates":[78.959766,29.703471],"type":"Point"}
}