{
  "type": "Feature",
  "properties": {
    "gn:admin1_code":"24",
    "gn:admin2_code":"123.0",
    "gn:asciiname":"Banai",
    "gn:country_code":"IN",
    "gn:dem":554,
    "gn:feature_class":"P",
    "gn:feature_code":"PPL",
    "gn:name":"Ban\u0101i",
    "gn:population":0,
    "gn:timezone":"Asia/Kolkata",
    "iso:country":"IN",
    "name:fra_x_preferred":[
        "Banai"
    ],
    "wof:name":"Banai",
    "wof:placetype":"locality"
},
  "geometry": {"coordinates":[73.9418,25.12379],"type":"Point"}
}