{
  "type": "Feature",
  "properties": {
    "iso:country":"IN",
    "ks:ks_name":"Thotadamajalu",
    "ks:ks_pop":179,
    "ks:ks_type":"HABITATION",
    "name:eng_x_preferred":[
        "Thotadamajalu"
    ],
    "wof:name":"Thotadamajalu",
    "wof:placetype":"locality",
    "wof:population":179
},
  "geometry": {"coordinates":[75.598354,12.579275],"type":"Point"}
}