{
  "type": "Feature",
  "properties": {
    "iso:country":"IN",
    "ks:ks_name":"Ahri Chak",
    "ks:ks_pop":0,
    "ks:ks_type":"VILLAGE",
    "name:eng_x_preferred":[
        "Ahri Chak"
    ],
    "wof:name":"Ahri Chak",
    "wof:placetype":"locality",
    "wof:population":0
},
  "geometry": {"coordinates":[85.670294,25.027812],"type":"Point"}
}