{
  "type": "Feature",
  "properties": {
    "iso:country":"IN",
    "ks:ks_name":"Bardehri",
    "ks:ks_pop":0,
    "ks:ks_type":"VILLAGE",
    "name:eng_x_preferred":[
        "Bardehri"
    ],
    "wof:name":"Bardehri",
    "wof:placetype":"locality",
    "wof:population":0
},
  "geometry": {"coordinates":[83.74214499999999,25.203374],"type":"Point"}
}