{
  "type": "Feature",
  "properties": {
    "iso:country":"IN",
    "ks:ks_name":"Maratiwada",
    "ks:ks_pop":400,
    "ks:ks_type":"HABITATION",
    "name:eng_x_preferred":[
        "Maratiwada"
    ],
    "wof:name":"Maratiwada",
    "wof:placetype":"locality",
    "wof:population":400
},
  "geometry": {"coordinates":[78.111062,17.420775],"type":"Point"}
}