{
  "type": "Feature",
  "properties": {
    "gn:admin1_code":"34.0",
    "gn:admin2_code":"219.0",
    "gn:asciiname":"Khalispur",
    "gn:country_code":"IN",
    "gn:dem":60,
    "gn:feature_class":"P",
    "gn:feature_code":"PPL",
    "gn:name":"Kh\u0101lispur",
    "gn:population":0,
    "gn:timezone":"Asia/Kolkata",
    "iso:country":"IN",
    "ks:ks_alt_nam":"Kh\u0101lispur",
    "ks:ks_name":"Khalispur",
    "ks:ks_pop":1417,
    "ks:ks_type":"VILLAGE",
    "ks:ks_uagg_main":0,
    "name:eng_x_preferred":[
        "Khalispur"
    ],
    "name:eng_x_variant":[
        "Kh\u0101lispur"
    ],
    "wof:name":"Khalispur",
    "wof:placetype":"neighbourhood",
    "wof:population":1417
},
  "geometry": {"coordinates":[84.778779,25.982458],"type":"Point"}
}