{
  "type": "Feature",
  "properties": {
    "iso:country":"IN",
    "ks:ks_name":"Idnalli",
    "ks:ks_pop":17,
    "ks:ks_type":"HABITATION",
    "name:eng_x_preferred":[
        "Idnalli"
    ],
    "wof:name":"Idnalli",
    "wof:placetype":"locality",
    "wof:population":17
},
  "geometry": {"coordinates":[74.700181,14.494086],"type":"Point"}
}