{
  "type": "Feature",
  "properties": {
    "gn:admin1_code":"36.0",
    "gn:admin2_code":"158.0",
    "gn:asciiname":"Pitthapatti",
    "gn:country_code":"IN",
    "gn:dem":115,
    "gn:feature_class":"P",
    "gn:feature_code":"PPL",
    "gn:name":"P\u012btth\u0101patti",
    "gn:population":0,
    "gn:timezone":"Asia/Kolkata",
    "iso:country":"IN",
    "wof:name":"Pitthapatti",
    "wof:placetype":"locality"
},
  "geometry": {"coordinates":[81.38389000000002,25.98665],"type":"Point"}
}