{
  "type": "Feature",
  "properties": {
    "iso:country":"IN",
    "ks:ks_name":"Kimkhet",
    "ks:ks_pop":337,
    "ks:ks_type":"VILLAGE",
    "name:eng_x_preferred":[
        "Kimkhet"
    ],
    "wof:name":"Kimkhet",
    "wof:placetype":"locality",
    "wof:population":337
},
  "geometry": {"coordinates":[80.14282900000001,29.99146],"type":"Point"}
}