{
  "type": "Feature",
  "properties": {
    "gn:admin1_code":"36",
    "gn:admin2_code":"163.0",
    "gn:asciiname":"Nawada Kalan",
    "gn:country_code":"IN",
    "gn:dem":140,
    "gn:feature_class":"P",
    "gn:feature_code":"PPL",
    "gn:name":"Naw\u0101da Kal\u0101n",
    "gn:population":0,
    "gn:timezone":"Asia/Kolkata",
    "iso:country":"IN",
    "name:und_x_variant":[
        "Naw\u0101da Kal\u0101n",
        "Aurang\u0101b\u0101d Bhola Hul\u0101s"
    ],
    "wof:name":"Nawada Kalan",
    "wof:placetype":"locality"
},
  "geometry": {"coordinates":[79.65124,26.54338],"type":"Point"}
}