{
  "type": "Feature",
  "properties": {
    "gn:admin1_code":"34.0",
    "gn:admin2_code":"230.0",
    "gn:asciiname":"Yusufpur",
    "gn:country_code":"IN",
    "gn:dem":53,
    "gn:feature_class":"P",
    "gn:feature_code":"PPL",
    "gn:name":"Y\u016bsufpur",
    "gn:population":0,
    "gn:timezone":"Asia/Kolkata",
    "iso:country":"IN",
    "name:msa_x_preferred":[
        "Yusufpur"
    ],
    "wof:name":"Yusufpur",
    "wof:placetype":"neighbourhood"
},
  "geometry": {"coordinates":[85.34388,25.49826],"type":"Point"}
}