{
  "type": "Feature",
  "properties": {
    "gn:admin1_code":"36",
    "gn:admin2_code":"180.0",
    "gn:asciiname":"Aima",
    "gn:country_code":"IN",
    "gn:dem":110,
    "gn:feature_class":"P",
    "gn:feature_code":"PPL",
    "gn:name":"Aima",
    "gn:population":0,
    "gn:timezone":"Asia/Kolkata",
    "iso:country":"IN",
    "ks:ks_name":"Ayma",
    "ks:ks_pop":55,
    "ks:ks_type":"HABITATION",
    "ks:ks_uagg_main":0,
    "name:eng_x_preferred":[
        "Ayma"
    ],
    "wof:name":"Ayma",
    "wof:placetype":"neighbourhood",
    "wof:population":55
},
  "geometry": {"coordinates":[81.66723399999999,27.297121],"type":"Point"}
}