{
  "type": "Feature",
  "properties": {
    "iso:country":"IN",
    "ks:ks_name":"Majorsuba",
    "ks:ks_pop":246,
    "ks:ks_type":"HABITATION",
    "ks:ks_uagg_main":0,
    "name:eng_x_preferred":[
        "Majorsuba"
    ],
    "wof:name":"Majorsuba",
    "wof:placetype":"neighbourhood",
    "wof:population":246
},
  "geometry": {"coordinates":[92.03219,26.144431],"type":"Point"}
}