{
  "type": "Feature",
  "properties": {
    "gn:admin1_code":"36",
    "gn:admin2_code":"197.0",
    "gn:asciiname":"Niyasipur",
    "gn:country_code":"IN",
    "gn:dem":83,
    "gn:feature_class":"P",
    "gn:feature_code":"PPL",
    "gn:name":"Niyas\u012bpur",
    "gn:population":0,
    "gn:timezone":"Asia/Kolkata",
    "iso:country":"IN",
    "ks:ks_name":"Niyaisipur",
    "ks:ks_pop":449,
    "ks:ks_type":"VILLAGE",
    "name:eng_x_preferred":[
        "Niyaisipur"
    ],
    "name:eng_x_variant":[
        "Niyasipur"
    ],
    "wof:name":"Niyaisipur",
    "wof:placetype":"locality",
    "wof:population":449
},
  "geometry": {"coordinates":[82.878257,25.213799],"type":"Point"}
}