{
  "type": "Feature",
  "properties": {
    "gn:admin1_code":"36",
    "gn:admin2_code":"197.0",
    "gn:asciiname":"Niyasipur",
    "gn:country_code":"IN",
    "gn:dem":83,
    "gn:feature_class":"P",
    "gn:feature_code":"PPL",
    "gn:name":"Niyas\u012bpur",
    "gn:population":0,
    "gn:timezone":"Asia/Kolkata",
    "iso:country":"IN",
    "wof:name":"Niyasipur",
    "wof:placetype":"locality"
},
  "geometry": {"coordinates":[82.88085,25.21624],"type":"Point"}
}