{
  "type": "Feature",
  "properties": {
    "iso:country":"IN",
    "ks:ks_name":"Bommanpatti",
    "ks:ks_pop":572,
    "ks:ks_type":"HABITATION",
    "name:eng_x_preferred":[
        "Bommanpatti"
    ],
    "wof:name":"Bommanpatti",
    "wof:placetype":"locality",
    "wof:population":572
},
  "geometry": {"coordinates":[77.925099,10.072153],"type":"Point"}
}