{
  "type": "Feature",
  "properties": {
    "iso:country":"IN",
    "ks:ks_name":"Barai Purwa",
    "ks:ks_pop":220,
    "ks:ks_type":"HABITATION",
    "name:eng_x_preferred":[
        "Barai Purwa"
    ],
    "wof:name":"Barai Purwa",
    "wof:placetype":"locality",
    "wof:population":220
},
  "geometry": {"coordinates":[82.300535,26.91014],"type":"Point"}
}