{
  "type": "Feature",
  "properties": {
    "gn:admin1_code":"19.0",
    "gn:admin2_code":"563.0",
    "gn:asciiname":"Alkod",
    "gn:country_code":"IN",
    "gn:dem":20,
    "gn:feature_class":"P",
    "gn:feature_code":"PPL",
    "gn:name":"Alkod",
    "gn:population":0,
    "gn:timezone":"Asia/Kolkata",
    "iso:country":"IN",
    "ks:ks_name":"Alkod",
    "ks:ks_pop":795,
    "ks:ks_type":"VILLAGE",
    "name:eng_x_preferred":[
        "Alkod"
    ],
    "wof:name":"Alkod",
    "wof:placetype":"locality",
    "wof:population":795
},
  "geometry": {"coordinates":[74.494407,14.489],"type":"Point"}
}