{
  "type": "Feature",
  "properties": {
    "iso:country":"IN",
    "ks:ks_name":"Pura Sareley",
    "ks:ks_pop":95,
    "ks:ks_type":"HABITATION",
    "name:eng_x_preferred":[
        "Pura Sareley"
    ],
    "wof:name":"Pura Sareley",
    "wof:placetype":"locality",
    "wof:population":95
},
  "geometry": {"coordinates":[78.273583,26.973476],"type":"Point"}
}