{
  "type": "Feature",
  "properties": {
    "iso:country":"IN",
    "ks:ks_name":"Dhobin Purwa",
    "ks:ks_pop":54,
    "ks:ks_type":"HABITATION",
    "name:eng_x_preferred":[
        "Dhobin Purwa"
    ],
    "wof:name":"Dhobin Purwa",
    "wof:placetype":"locality",
    "wof:population":54
},
  "geometry": {"coordinates":[81.35243,27.828723],"type":"Point"}
}