{
  "type": "Feature",
  "properties": {
    "gn:admin1_code":"12.0",
    "gn:admin2_code":"18.0",
    "gn:asciiname":"Diukond",
    "gn:country_code":"IN",
    "gn:dem":2487,
    "gn:feature_class":"P",
    "gn:feature_code":"PPL",
    "gn:name":"Diukond",
    "gn:population":0,
    "gn:timezone":"Asia/Kolkata",
    "iso:country":"IN",
    "wof:name":"Diukond",
    "wof:placetype":"locality"
},
  "geometry": {"coordinates":[75.79613000000001,33.48017],"type":"Point"}
}