{
  "type": "Feature",
  "properties": {
    "iso:country":"IN",
    "ks:ks_name":"Khairai",
    "ks:ks_pop":558,
    "ks:ks_type":"VILLAGE",
    "name:eng_x_preferred":[
        "Khairai"
    ],
    "wof:name":"Khairai",
    "wof:placetype":"locality",
    "wof:population":558
},
  "geometry": {"coordinates":[77.628286,25.163431],"type":"Point"}
}