{
  "type": "Feature",
  "properties": {
    "iso:country":"IN",
    "ks:ks_name":"Bagmari",
    "ks:ks_pop":153,
    "ks:ks_type":"VILLAGE",
    "name:eng_x_preferred":[
        "Bagmari"
    ],
    "wof:name":"Bagmari",
    "wof:placetype":"locality",
    "wof:population":153
},
  "geometry": {"coordinates":[87.48804699999999,22.493438],"type":"Point"}
}