{
  "type": "Feature",
  "properties": {
    "iso:country":"IN",
    "ks:ks_name":"Sipahipara",
    "ks:ks_pop":160,
    "ks:ks_type":"HABITATION",
    "ks:ks_uagg_main":0,
    "name:eng_x_preferred":[
        "Sipahipara"
    ],
    "wof:name":"Sipahipara",
    "wof:placetype":"neighbourhood",
    "wof:population":160
},
  "geometry": {"coordinates":[91.449451,25.937493],"type":"Point"}
}