{
  "type": "Feature",
  "properties": {
    "gn:admin1_code":"35",
    "gn:admin2_code":"425.0",
    "gn:asciiname":"Dhawari",
    "gn:country_code":"IN",
    "gn:dem":169,
    "gn:feature_class":"P",
    "gn:feature_code":"PPL",
    "gn:name":"Dhaw\u0101ri",
    "gn:population":0,
    "gn:timezone":"Asia/Kolkata",
    "iso:country":"IN",
    "name:eng_x_preferred":[
        "Dhaw\u0101ri"
    ],
    "wof:name":"Dhawari",
    "wof:placetype":"locality"
},
  "geometry": {"coordinates":[80.0702,25.25137],"type":"Point"}
}