{
  "type": "Feature",
  "properties": {
    "gn:admin1_code":"36.0",
    "gn:admin2_code":"149.0",
    "gn:asciiname":"Akbarabad",
    "gn:country_code":"IN",
    "gn:dem":173,
    "gn:feature_class":"P",
    "gn:feature_code":"PPL",
    "gn:name":"Akbar\u0101b\u0101d",
    "gn:population":0,
    "gn:timezone":"Asia/Kolkata",
    "iso:country":"IN",
    "ks:ks_alt_nam":"Akbar\u0101b\u0101d",
    "ks:ks_name":"Akbarabad",
    "ks:ks_type":"VILLAGE",
    "ks:ks_uagg_main":0,
    "name:ara_x_preferred":[
        "\u0623\u06a9\u0628\u0631 \u0623\u0628\u0627\u062f"
    ],
    "name:fas_x_preferred":[
        "\u0627\u06a9\u0628\u0631\u0622\u0628\u0627\u062f"
    ],
    "name:ron_x_preferred":[
        "Akbarabad"
    ],
    "wof:name":"Akbarabad",
    "wof:placetype":"neighbourhood"
},
  "geometry": {"coordinates":[78.75013,28.06301],"type":"Point"}
}