{
  "type": "Feature",
  "properties": {
    "gn:admin1_code":"12.0",
    "gn:admin2_code":"10.0",
    "gn:asciiname":"Panzin",
    "gn:country_code":"IN",
    "gn:dem":1870,
    "gn:feature_class":"P",
    "gn:feature_code":"PPL",
    "gn:name":"Panzin",
    "gn:population":0,
    "gn:timezone":"Asia/Kolkata",
    "iso:country":"IN",
    "wof:name":"Panzin",
    "wof:placetype":"locality"
},
  "geometry": {"coordinates":[74.90146999999997,34.27575],"type":"Point"}
}