{
  "type": "Feature",
  "properties": {
    "iso:country":"IN",
    "ks:ks_alt_nam":"GODRAPAR",
    "ks:ks_name":"Godrapar",
    "ks:ks_pop":376,
    "ks:ks_type":"HABITATION",
    "name:eng_x_preferred":[
        "Godrapar"
    ],
    "wof:name":"Godrapar",
    "wof:placetype":"locality",
    "wof:population":376
},
  "geometry": {"coordinates":[85.366257,24.82286],"type":"Point"}
}