{
  "type": "Feature",
  "properties": {
    "iso:country":"IN",
    "ks:ks_name":"Dhaurasand",
    "ks:ks_pop":264,
    "ks:ks_type":"HABITATION",
    "name:eng_x_preferred":[
        "Dhaurasand"
    ],
    "wof:name":"Dhaurasand",
    "wof:placetype":"locality",
    "wof:population":264
},
  "geometry": {"coordinates":[84.055283,22.675158],"type":"Point"}
}