{
  "type": "Feature",
  "properties": {
    "gn:admin1_code":"24",
    "gn:admin2_code":"118.0",
    "gn:asciiname":"Miniari",
    "gn:country_code":"IN",
    "gn:dem":215,
    "gn:feature_class":"P",
    "gn:feature_code":"PPL",
    "gn:name":"Mini\u0101ri",
    "gn:population":0,
    "gn:timezone":"Asia/Kolkata",
    "iso:country":"IN",
    "wof:name":"Miniari",
    "wof:placetype":"locality"
},
  "geometry": {"coordinates":[73.11963,25.66739],"type":"Point"}
}