{
  "type": "Feature",
  "properties": {
    "iso:country":"IN",
    "ks:ks_name":"Baraipur",
    "ks:ks_pop":207,
    "ks:ks_type":"HABITATION",
    "name:eng_x_preferred":[
        "Baraipur"
    ],
    "wof:name":"Baraipur",
    "wof:placetype":"locality",
    "wof:population":207
},
  "geometry": {"coordinates":[83.630336,26.683032],"type":"Point"}
}