{
  "type": "Feature",
  "properties": {
    "gn:admin1_code":"39.0",
    "gn:admin2_code":"64.0",
    "gn:asciiname":"Minoli",
    "gn:country_code":"IN",
    "gn:dem":1544,
    "gn:feature_class":"P",
    "gn:feature_code":"PPL",
    "gn:name":"Minoli",
    "gn:population":0,
    "gn:timezone":"Asia/Kolkata",
    "iso:country":"IN",
    "name:ita_x_preferred":[
        "Minoli"
    ],
    "wof:name":"Minoli",
    "wof:placetype":"locality"
},
  "geometry": {"coordinates":[79.92784,29.59643],"type":"Point"}
}