{
  "type": "Feature",
  "properties": {
    "iso:country":"IN",
    "ks:ks_name":"Kasigejaddi",
    "ks:ks_pop":15,
    "ks:ks_type":"HABITATION",
    "name:eng_x_preferred":[
        "Kasigejaddi"
    ],
    "wof:name":"Kasigejaddi",
    "wof:placetype":"locality",
    "wof:population":15
},
  "geometry": {"coordinates":[74.731129,14.41432],"type":"Point"}
}