{
  "type": "Feature",
  "properties": {
    "iso:country":"IN",
    "ks:ks_name":"Nimbli",
    "ks:ks_pop":431,
    "ks:ks_type":"HABITATION",
    "name:eng_x_preferred":[
        "Nimbli"
    ],
    "wof:name":"Nimbli",
    "wof:placetype":"locality",
    "wof:population":431
},
  "geometry": {"coordinates":[72.820986,26.218803],"type":"Point"}
}