{
  "type": "Feature",
  "properties": {
    "iso:country":"IN",
    "ks:ks_name":"Tiradih",
    "ks:ks_pop":356,
    "ks:ks_type":"HABITATION",
    "name:eng_x_preferred":[
        "Tiradih"
    ],
    "wof:name":"Tiradih",
    "wof:placetype":"locality",
    "wof:population":356
},
  "geometry": {"coordinates":[84.815219,23.071639],"type":"Point"}
}