{
  "type": "Feature",
  "properties": {
    "iso:country":"IN",
    "ks:ks_name":"Kurtha",
    "ks:ks_pop":359,
    "ks:ks_type":"VILLAGE",
    "name:eng_x_preferred":[
        "Kurtha"
    ],
    "wof:name":"Kurtha",
    "wof:placetype":"locality",
    "wof:population":359
},
  "geometry": {"coordinates":[83.68127699999999,24.967119],"type":"Point"}
}