{
  "type": "Feature",
  "properties": {
    "gn:admin1_code":"25.0",
    "gn:admin2_code":"602.0",
    "gn:asciiname":"Vadamadurai",
    "gn:country_code":"IN",
    "gn:dem":29,
    "gn:feature_class":"P",
    "gn:feature_code":"PPL",
    "gn:name":"Vadamadurai",
    "gn:population":0,
    "gn:timezone":"Asia/Kolkata",
    "iso:country":"IN",
    "name:bpy_x_preferred":[
        "\u09ac\u09be\u09a6\u09be\u09ae\u09a6\u09c1\u09b0\u09be\u0987"
    ],
    "name:ceb_x_preferred":[
        "Vadamadurai"
    ],
    "name:ita_x_preferred":[
        "Vadamadurai"
    ],
    "name:msa_x_preferred":[
        "Vadamadurai"
    ],
    "name:nld_x_preferred":[
        "Vadamadurai"
    ],
    "name:por_x_preferred":[
        "Vadamadurai"
    ],
    "name:swe_x_preferred":[
        "Vadamadurai"
    ],
    "name:tam_x_preferred":[
        "\u0bb5\u0b9f\u0bae\u0ba4\u0bc1\u0bb0\u0bc8"
    ],
    "name:vie_x_preferred":[
        "Vadamadurai"
    ],
    "name:zho_x_preferred":[
        "\u74e6\u8fbe\u9a6c\u675c\u8d56"
    ],
    "wof:name":"Vadamadurai",
    "wof:placetype":"locality"
},
  "geometry": {"coordinates":[80.04046,13.28693],"type":"Point"}
}