{
  "type": "Feature",
  "properties": {
    "gn:admin1_code":"24",
    "gn:admin2_code":"119.0",
    "gn:asciiname":"Pakriawas",
    "gn:country_code":"IN",
    "gn:dem":486,
    "gn:feature_class":"P",
    "gn:feature_code":"PPL",
    "gn:name":"Pakri\u0101w\u0101s",
    "gn:population":0,
    "gn:timezone":"Asia/Kolkata",
    "iso:country":"IN",
    "wof:name":"Pakriawas",
    "wof:placetype":"locality"
},
  "geometry": {"coordinates":[74.40736,26.09612000000001],"type":"Point"}
}