{
  "type": "Feature",
  "properties": {
    "iso:country":"IN",
    "ks:ks_name":"Arasamarathur",
    "ks:ks_pop":69,
    "ks:ks_type":"HABITATION",
    "name:eng_x_preferred":[
        "Arasamarathur"
    ],
    "wof:name":"Arasamarathur",
    "wof:placetype":"locality",
    "wof:population":69
},
  "geometry": {"coordinates":[79.02440199999999,12.71233],"type":"Point"}
}