{
  "type": "Feature",
  "properties": {
    "gn:admin1_code":"36",
    "gn:admin2_code":"147.0",
    "gn:asciiname":"Muhabbatpur Ahir",
    "gn:country_code":"IN",
    "gn:dem":164,
    "gn:feature_class":"P",
    "gn:feature_code":"PPL",
    "gn:name":"Muhabbatpur Ahir",
    "gn:population":0,
    "gn:timezone":"Asia/Kolkata",
    "iso:country":"IN",
    "wof:name":"Muhabbatpur Ahir",
    "wof:placetype":"locality"
},
  "geometry": {"coordinates":[78.54656999999997,27.08861],"type":"Point"}
}