{
  "type": "Feature",
  "properties": {
    "gn:admin1_code":"35.0",
    "gn:admin2_code":"455.0",
    "gn:asciiname":"Dhobiwara",
    "gn:country_code":"IN",
    "gn:dem":1064,
    "gn:feature_class":"P",
    "gn:feature_code":"PPL",
    "gn:name":"Dhobiw\u0101ra",
    "gn:population":0,
    "gn:timezone":"Asia/Kolkata",
    "iso:country":"IN",
    "wof:name":"Dhobiwara",
    "wof:placetype":"locality"
},
  "geometry": {"coordinates":[78.58816999999998,22.29815],"type":"Point"}
}