{
  "type": "Feature",
  "properties": {
    "iso:country":"IN",
    "ks:ks_name":"Darewadi",
    "ks:ks_pop":128,
    "ks:ks_type":"HABITATION",
    "name:eng_x_preferred":[
        "Darewadi"
    ],
    "wof:name":"Darewadi",
    "wof:placetype":"locality",
    "wof:population":128
},
  "geometry": {"coordinates":[73.994581,19.470275],"type":"Point"}
}