{
  "type": "Feature",
  "properties": {
    "iso:country":"IN",
    "ks:ks_name":"Chhoto Atiabari",
    "ks:ks_pop":1020,
    "ks:ks_type":"VILLAGE",
    "name:eng_x_preferred":[
        "Chhoto Atiabari"
    ],
    "wof:name":"Chhoto Atiabari",
    "wof:placetype":"locality",
    "wof:population":1020
},
  "geometry": {"coordinates":[89.481689,26.117245],"type":"Point"}
}