{
  "type": "Feature",
  "properties": {
    "iso:country":"IN",
    "ks:ks_name":"Bere",
    "ks:ks_pop":684,
    "ks:ks_type":"VILLAGE",
    "name:eng_x_preferred":[
        "Bere"
    ],
    "wof:name":"Bere",
    "wof:placetype":"locality",
    "wof:population":684
},
  "geometry": {"coordinates":[84.102414,23.70397],"type":"Point"}
}