{
  "type": "Feature",
  "properties": {
    "iso:country":"IN",
    "ks:ks_name":"Palaskhobra",
    "ks:ks_pop":366,
    "ks:ks_type":"HABITATION",
    "name:eng_x_preferred":[
        "Palaskhobra"
    ],
    "wof:name":"Palaskhobra",
    "wof:placetype":"locality",
    "wof:population":366
},
  "geometry": {"coordinates":[74.02563600000001,21.865119],"type":"Point"}
}