{
  "type": "Feature",
  "properties": {
    "iso:country":"IN",
    "ks:ks_name":"Bowali",
    "ks:ks_pop":10202,
    "ks:ks_type":"URBAN",
    "ks:ks_uagg_main":0,
    "name:eng_x_preferred":[
        "Bowali"
    ],
    "wof:name":"Bowali",
    "wof:placetype":"locality",
    "wof:population":10202
},
  "geometry": {"coordinates":[88.185081,22.422487],"type":"Point"}
}