{
  "type": "Feature",
  "properties": {
    "iso:country":"IN",
    "ks:ks_name":"9 CHTM",
    "ks:ks_pop":754,
    "ks:ks_type":"VILLAGE",
    "name:eng_x_preferred":[
        "9 CHTM"
    ],
    "wof:name":"9 CHTM",
    "wof:placetype":"locality",
    "wof:population":754
},
  "geometry": {"coordinates":[73.066834,28.705757],"type":"Point"}
}