{
  "type": "Feature",
  "properties": {
    "iso:country":"IN",
    "ks:ks_name":"Urnaw Purwa",
    "ks:ks_pop":1044,
    "ks:ks_type":"HABITATION",
    "name:eng_x_preferred":[
        "Urnaw Purwa"
    ],
    "wof:name":"Urnaw Purwa",
    "wof:placetype":"locality",
    "wof:population":1044
},
  "geometry": {"coordinates":[79.72843,26.512005],"type":"Point"}
}