{
  "type": "Feature",
  "properties": {
    "gn:admin1_code":"34.0",
    "gn:admin2_code":"235.0",
    "gn:asciiname":"Karmi",
    "gn:country_code":"IN",
    "gn:dem":102,
    "gn:feature_class":"P",
    "gn:feature_code":"PPL",
    "gn:name":"Karmi",
    "gn:population":0,
    "gn:timezone":"Asia/Kolkata",
    "iso:country":"IN",
    "ks:ks_name":"Karmi",
    "ks:ks_pop":500,
    "ks:ks_type":"VILLAGE",
    "ks:ks_uagg_main":0,
    "name:ceb_x_preferred":[
        "Karmi"
    ],
    "name:deu_x_preferred":[
        "Karmi"
    ],
    "name:eng_x_preferred":[
        "Karmi"
    ],
    "name:fra_x_preferred":[
        "Karmi"
    ],
    "name:heb_x_preferred":[
        "\u05db\u05e8\u05de\u05d9"
    ],
    "name:rus_x_preferred":[
        "\u041a\u0430\u0440\u043c\u0438"
    ],
    "name:swe_x_preferred":[
        "Karmi"
    ],
    "wof:name":"Karmi",
    "wof:placetype":"neighbourhood",
    "wof:population":500
},
  "geometry": {"coordinates":[84.635458,24.824481],"type":"Point"}
}