{
  "type": "Feature",
  "properties": {
    "iso:country":"IN",
    "ks:ks_name":"Bajarpeth",
    "ks:ks_pop":44,
    "ks:ks_type":"HABITATION",
    "name:eng_x_preferred":[
        "Bajarpeth"
    ],
    "wof:name":"Bajarpeth",
    "wof:placetype":"locality",
    "wof:population":44
},
  "geometry": {"coordinates":[73.71166700000001,17.049444],"type":"Point"}
}