{
  "type": "Feature",
  "properties": {
    "gn:admin1_code":"21.0",
    "gn:admin2_code":"376",
    "gn:asciiname":"Balidiha",
    "gn:country_code":"IN",
    "gn:dem":76,
    "gn:feature_class":"P",
    "gn:feature_code":"PPL",
    "gn:name":"B\u0101lidiha",
    "gn:population":0,
    "gn:timezone":"Asia/Kolkata",
    "iso:country":"IN",
    "ks:ks_alt_nam":"B\u0101lidiha",
    "ks:ks_name":"Balidiha",
    "ks:ks_pop":2614,
    "ks:ks_type":"VILLAGE",
    "name:eng_x_preferred":[
        "Balidiha"
    ],
    "name:eng_x_variant":[
        "B\u0101lidiha"
    ],
    "wof:name":"Balidiha",
    "wof:placetype":"locality",
    "wof:population":2614
},
  "geometry": {"coordinates":[86.626603,21.966384],"type":"Point"}
}