{
  "type": "Feature",
  "properties": {
    "gn:admin1_code":"21.0",
    "gn:admin2_code":"376",
    "gn:asciiname":"Balidiha",
    "gn:country_code":"IN",
    "gn:dem":76,
    "gn:feature_class":"P",
    "gn:feature_code":"PPL",
    "gn:name":"B\u0101lidiha",
    "gn:population":0,
    "gn:timezone":"Asia/Kolkata",
    "iso:country":"IN",
    "wof:name":"Balidiha",
    "wof:placetype":"locality"
},
  "geometry": {"coordinates":[86.62609,21.96652000000001],"type":"Point"}
}