{
  "type": "Feature",
  "properties": {
    "gn:admin1_code":"36.0",
    "gn:admin2_code":"137.0",
    "gn:asciiname":"Nagla Khadar",
    "gn:country_code":"IN",
    "gn:dem":194,
    "gn:feature_class":"P",
    "gn:feature_code":"PPL",
    "gn:name":"Nagla Kh\u0101dar",
    "gn:population":0,
    "gn:timezone":"Asia/Kolkata",
    "iso:country":"IN",
    "wof:name":"Nagla Khadar",
    "wof:placetype":"locality"
},
  "geometry": {"coordinates":[78.32847,28.5951],"type":"Point"}
}