{
  "type": "Feature",
  "properties": {
    "gn:admin1_code":"34.0",
    "gn:admin2_code":"238.0",
    "gn:asciiname":"Tanrpur",
    "gn:country_code":"IN",
    "gn:dem":160,
    "gn:feature_class":"P",
    "gn:feature_code":"PPL",
    "gn:name":"T\u0101nrp\u016br",
    "gn:population":0,
    "gn:timezone":"Asia/Kolkata",
    "iso:country":"IN",
    "wof:name":"Tanrpur",
    "wof:placetype":"locality"
},
  "geometry": {"coordinates":[86.08608000000002,24.79556],"type":"Point"}
}