{
  "type": "Feature",
  "properties": {
    "gn:admin1_code":"11",
    "gn:admin2_code":"23.0",
    "gn:asciiname":"Haripur",
    "gn:country_code":"IN",
    "gn:dem":889,
    "gn:feature_class":"P",
    "gn:feature_code":"PPL",
    "gn:name":"Har\u012bp\u016br",
    "gn:population":0,
    "gn:timezone":"Asia/Kolkata",
    "iso:country":"IN",
    "name:ara_x_preferred":[
        "\u0647\u0627\u0631\u064a\u0628\u0648\u0631"
    ],
    "name:ben_bn_x_preferred":[
        "\u09b9\u09b0\u09bf\u09aa\u09c1\u09b0"
    ],
    "name:ben_in_x_preferred":[
        "\u09b9\u09b0\u09bf\u09aa\u09c1\u09b0"
    ],
    "name:cat_x_preferred":[
        "Haripur"
    ],
    "name:ceb_x_preferred":[
        "Haripur"
    ],
    "name:fra_x_preferred":[
        "Haripur"
    ],
    "name:guj_x_preferred":[
        "\u0ab9\u0ab0\u0abf\u0aaa\u0ac1\u0ab0"
    ],
    "name:hin_x_preferred":[
        "\u0939\u0930\u093f\u092a\u0941\u0930"
    ],
    "name:kan_x_preferred":[
        "\u0cb9\u0cb0\u0cbf\u0caa\u0cc1\u0cb0"
    ],
    "name:mal_x_preferred":[
        "\u0d39\u0d30\u0d3f\u0d2a\u0d42\u0d7c"
    ],
    "name:mar_x_preferred":[
        "\u0939\u0930\u093f\u092a\u0942\u0930"
    ],
    "name:new_x_preferred":[
        "\u0939\u0930\u093f\u092a\u0941\u0930 \u0917\u093e\u0935\u093f\u0938"
    ],
    "name:pan_x_preferred":[
        "\u0a39\u0a30\u0a40\u0a2a\u0a41\u0a30"
    ],
    "name:pol_x_preferred":[
        "Haripur"
    ],
    "name:rus_x_preferred":[
        "\u0425\u0430\u0440\u0438\u043f\u0443\u0440"
    ],
    "name:swe_x_preferred":[
        "Haripur"
    ],
    "name:tam_x_preferred":[
        "\u0bb9\u0bb0\u0bbf\u0baa\u0bcd\u0baa\u0bc2\u0bb0\u0bcd"
    ],
    "name:tel_x_preferred":[
        "\u0c39\u0c30\u0c3f\u0c2a\u0c42\u0c30\u0c4d"
    ],
    "name:tur_x_preferred":[
        "Haripur"
    ],
    "name:urd_x_preferred":[
        "\u06c1\u0631\u06cc \u067e\u0648\u0631"
    ],
    "wof:name":"Haripur",
    "wof:placetype":"locality"
},
  "geometry": {"coordinates":[76.11448,32.58646],"type":"Point"}
}