{
  "type": "Feature",
  "properties": {
    "gn:admin1_code":"21.0",
    "gn:admin2_code":"396.0",
    "gn:asciiname":"Papikhallu",
    "gn:country_code":"IN",
    "gn:dem":512,
    "gn:feature_class":"P",
    "gn:feature_code":"PPL",
    "gn:name":"P\u0101pikhallu",
    "gn:population":0,
    "gn:timezone":"Asia/Kolkata",
    "iso:country":"IN",
    "ks:ks_name":"Papikhal",
    "ks:ks_pop":322,
    "ks:ks_type":"VILLAGE",
    "name:eng_x_preferred":[
        "Papikhal"
    ],
    "name:eng_x_variant":[
        "Papikhallu"
    ],
    "wof:name":"Papikhal",
    "wof:placetype":"locality",
    "wof:population":322
},
  "geometry": {"coordinates":[83.60737,19.407933],"type":"Point"}
}