{
  "type": "Feature",
  "properties": {
    "iso:country":"IN",
    "ks:ks_name":"Nadimivalasa",
    "ks:ks_pop":94,
    "ks:ks_type":"HABITATION",
    "name:eng_x_preferred":[
        "Nadimivalasa"
    ],
    "wof:name":"Nadimivalasa",
    "wof:placetype":"locality",
    "wof:population":94
},
  "geometry": {"coordinates":[83.05812,18.249125],"type":"Point"}
}