{
  "type": "Feature",
  "properties": {
    "gn:admin1_code":"19",
    "gn:admin2_code":"578.0",
    "gn:asciiname":"Terakanambi",
    "gn:country_code":"IN",
    "gn:dem":836,
    "gn:feature_class":"P",
    "gn:feature_code":"PPL",
    "gn:name":"Terakanambi",
    "gn:population":0,
    "gn:timezone":"Asia/Kolkata",
    "iso:country":"IN",
    "name:kan_x_preferred":[
        "\u0ca4\u0cc6\u0cb0\u0c95\u0ca3\u0cbe\u0c82\u0cac\u0cbf"
    ],
    "wof:name":"Terakanambi",
    "wof:placetype":"locality"
},
  "geometry": {"coordinates":[76.79091,11.81418],"type":"Point"}
}