{
  "type": "Feature",
  "properties": {
    "gn:admin1_code":"34.0",
    "gn:admin2_code":"239.0",
    "gn:asciiname":"Badhanpura",
    "gn:country_code":"IN",
    "gn:dem":76,
    "gn:feature_class":"P",
    "gn:feature_code":"PPL",
    "gn:name":"Badhanpura",
    "gn:population":0,
    "gn:timezone":"Asia/Kolkata",
    "iso:country":"IN",
    "ks:ks_name":"Babhanpura",
    "ks:ks_pop":1505,
    "ks:ks_type":"VILLAGE",
    "ks:ks_uagg_main":0,
    "name:eng_x_preferred":[
        "Babhanpura"
    ],
    "wof:name":"Babhanpura",
    "wof:placetype":"neighbourhood",
    "wof:population":1505
},
  "geometry": {"coordinates":[85.073142,25.124687],"type":"Point"}
}