{
  "type": "Feature",
  "properties": {
    "iso:country":"IN",
    "ks:ks_name":"Saisar",
    "ks:ks_pop":3443,
    "ks:ks_type":"VILLAGE",
    "name:eng_x_preferred":[
        "Saisar"
    ],
    "wof:name":"Saisar",
    "wof:placetype":"locality",
    "wof:population":3443
},
  "geometry": {"coordinates":[73.03855799999999,27.484911],"type":"Point"}
}