{
  "type": "Feature",
  "properties": {
    "iso:country":"IN",
    "ks:ks_name":"Nathathottampudur",
    "ks:ks_pop":230,
    "ks:ks_type":"HABITATION",
    "name:eng_x_preferred":[
        "Nathathottampudur"
    ],
    "wof:name":"Nathathottampudur",
    "wof:placetype":"locality",
    "wof:population":230
},
  "geometry": {"coordinates":[77.486425,11.164429],"type":"Point"}
}