{
  "type": "Feature",
  "properties": {
    "gn:admin1_code":"36.0",
    "gn:admin2_code":"185.0",
    "gn:asciiname":"Dhanusa Dih",
    "gn:country_code":"IN",
    "gn:dem":91,
    "gn:feature_class":"P",
    "gn:feature_code":"PPL",
    "gn:name":"Dhanusa D\u012bh",
    "gn:population":0,
    "gn:timezone":"Asia/Kolkata",
    "iso:country":"IN",
    "ks:ks_alt_nam":"Dhanusa D\u012bh",
    "ks:ks_name":"Dhanusa Dih",
    "ks:ks_type":"VILLAGE",
    "ks:ks_uagg_main":0,
    "name:eng_x_preferred":[
        "Dhanusa Dih"
    ],
    "name:eng_x_variant":[
        "Dhanusa D\u012bh"
    ],
    "wof:name":"Dhanusa Dih",
    "wof:placetype":"neighbourhood"
},
  "geometry": {"coordinates":[82.792078,27.04391],"type":"Point"}
}