{
  "type": "Feature",
  "properties": {
    "iso:country":"IN",
    "ks:ks_name":"Niluvase",
    "ks:ks_pop":64,
    "ks:ks_type":"HABITATION",
    "name:eng_x_preferred":[
        "Niluvase"
    ],
    "wof:name":"Niluvase",
    "wof:placetype":"locality",
    "wof:population":64
},
  "geometry": {"coordinates":[75.433806,13.719766],"type":"Point"}
}