{
  "type": "Feature",
  "properties": {
    "gn:admin1_code":"16.0",
    "gn:admin2_code":"528.0",
    "gn:asciiname":"Kulvadi",
    "gn:country_code":"IN",
    "gn:dem":187,
    "gn:feature_class":"P",
    "gn:feature_code":"PPL",
    "gn:name":"Kulvadi",
    "gn:population":0,
    "gn:timezone":"Asia/Kolkata",
    "iso:country":"IN",
    "wof:name":"Kulvadi",
    "wof:placetype":"locality"
},
  "geometry": {"coordinates":[73.49445,16.81059],"type":"Point"}
}