{
  "type": "Feature",
  "properties": {
    "iso:country":"IN",
    "ks:ks_alt_nam":"MAMMANA GN COLONY",
    "ks:ks_name":"Mammana Gn Colony",
    "ks:ks_pop":50,
    "ks:ks_type":"HABITATION",
    "name:eng_x_preferred":[
        "Mammana Gn Colony"
    ],
    "wof:name":"Mammana Gn Colony",
    "wof:placetype":"locality",
    "wof:population":50
},
  "geometry": {"coordinates":[76.617062,11.078839],"type":"Point"}
}