{
  "type": "Feature",
  "properties": {
    "gn:admin1_code":"16.0",
    "gn:admin2_code":"516.0",
    "gn:asciiname":"Gujarkhede",
    "gn:country_code":"IN",
    "gn:dem":608,
    "gn:feature_class":"P",
    "gn:feature_code":"PPL",
    "gn:name":"Gujarkhede",
    "gn:population":0,
    "gn:timezone":"Asia/Kolkata",
    "iso:country":"IN",
    "wof:name":"Gujarkhede",
    "wof:placetype":"locality"
},
  "geometry": {"coordinates":[74.41506,20.14979],"type":"Point"}
}