{
  "type": "Feature",
  "properties": {
    "iso:country":"IN",
    "ks:ks_name":"Bhujbalwasti",
    "ks:ks_pop":150,
    "ks:ks_type":"HABITATION",
    "name:eng_x_preferred":[
        "Bhujbalwasti"
    ],
    "wof:name":"Bhujbalwasti",
    "wof:placetype":"locality",
    "wof:population":150
},
  "geometry": {"coordinates":[74.70876,17.841437],"type":"Point"}
}