{
  "type": "Feature",
  "properties": {
    "gn:admin1_code":"36",
    "gn:admin2_code":"156.0",
    "gn:asciiname":"Kardah",
    "gn:country_code":"IN",
    "gn:dem":117,
    "gn:feature_class":"P",
    "gn:feature_code":"PPL",
    "gn:name":"Kard\u0101h",
    "gn:population":0,
    "gn:timezone":"Asia/Kolkata",
    "iso:country":"IN",
    "wof:name":"Kardah",
    "wof:placetype":"locality"
},
  "geometry": {"coordinates":[81.00861,26.42463],"type":"Point"}
}