{
  "type": "Feature",
  "properties": {
    "gn:admin1_code":"35",
    "gn:admin2_code":"458.0",
    "gn:asciiname":"Raipura",
    "gn:country_code":"IN",
    "gn:dem":404,
    "gn:feature_class":"P",
    "gn:feature_code":"PPL",
    "gn:name":"R\u0101ipura",
    "gn:population":0,
    "gn:timezone":"Asia/Kolkata",
    "iso:country":"IN",
    "ks:ks_alt_nam":"R\u0101ipura",
    "ks:ks_name":"Raipura",
    "ks:ks_type":"VILLAGE",
    "name:eng_x_preferred":[
        "Raipura"
    ],
    "name:eng_x_variant":[
        "R\u0101ipura"
    ],
    "name:msa_x_preferred":[
        "Raipura"
    ],
    "wof:name":"Raipura",
    "wof:placetype":"locality"
},
  "geometry": {"coordinates":[77.11259699999999,24.29459],"type":"Point"}
}