{
  "type": "Feature",
  "properties": {
    "iso:country":"IN",
    "ks:ks_name":"Anandapura",
    "ks:ks_pop":819,
    "ks:ks_type":"HABITATION",
    "name:eng_x_preferred":[
        "Anandapura"
    ],
    "wof:name":"Anandapura",
    "wof:placetype":"locality",
    "wof:population":819
},
  "geometry": {"coordinates":[75.202093,14.075597],"type":"Point"}
}