{
  "type": "Feature",
  "properties": {
    "iso:country":"IN",
    "ks:ks_name":"Khaaspara Amodi",
    "ks:ks_pop":380,
    "ks:ks_type":"HABITATION",
    "name:eng_x_preferred":[
        "Khaaspara Amodi"
    ],
    "wof:name":"Khaaspara Amodi",
    "wof:placetype":"locality",
    "wof:population":380
},
  "geometry": {"coordinates":[81.010086,20.163331],"type":"Point"}
}