{
  "type": "Feature",
  "properties": {
    "iso:country":"IN",
    "ks:ks_name":"Padari Mustacum",
    "ks:ks_pop":1407,
    "ks:ks_type":"VILLAGE",
    "name:eng_x_preferred":[
        "Padari Mustacum"
    ],
    "wof:name":"Padari Mustacum",
    "wof:placetype":"locality",
    "wof:population":1407
},
  "geometry": {"coordinates":[82.625604,27.217843],"type":"Point"}
}