{
  "type": "Feature",
  "properties": {
    "iso:country":"IN",
    "ks:ks_name":"Sandha Kairara",
    "ks:ks_pop":690,
    "ks:ks_type":"VILLAGE",
    "name:eng_x_preferred":[
        "Sandha Kairara"
    ],
    "wof:name":"Sandha Kairara",
    "wof:placetype":"locality",
    "wof:population":690
},
  "geometry": {"coordinates":[91.47789899999999,26.453871],"type":"Point"}
}