{
  "type": "Feature",
  "properties": {
    "iso:country":"IN",
    "ks:ks_name":"Borappanahatty",
    "ks:ks_pop":116,
    "ks:ks_type":"HABITATION",
    "name:eng_x_preferred":[
        "Borappanahatty"
    ],
    "wof:name":"Borappanahatty",
    "wof:placetype":"locality",
    "wof:population":116
},
  "geometry": {"coordinates":[77.07055800000001,13.537264],"type":"Point"}
}