{
  "type": "Feature",
  "properties": {
    "iso:country":"IN",
    "ks:ks_name":"Pabusariya",
    "ks:ks_pop":242,
    "ks:ks_type":"VILLAGE",
    "name:eng_x_preferred":[
        "Pabusariya"
    ],
    "wof:name":"Pabusariya",
    "wof:placetype":"locality",
    "wof:population":242
},
  "geometry": {"coordinates":[70.862317,25.818978],"type":"Point"}
}