{
  "type": "Feature",
  "properties": {
    "gn:admin1_code":"34.0",
    "gn:admin2_code":"210.0",
    "gn:asciiname":"Dogachhi",
    "gn:country_code":"IN",
    "gn:dem":59,
    "gn:feature_class":"P",
    "gn:feature_code":"PPL",
    "gn:name":"Dog\u0101chhi",
    "gn:population":0,
    "gn:timezone":"Asia/Kolkata",
    "iso:country":"IN",
    "wof:name":"Dogachhi",
    "wof:placetype":"locality"
},
  "geometry": {"coordinates":[87.77036,26.29065],"type":"Point"}
}