{
  "type": "Feature",
  "properties": {
    "gn:admin1_code":"10.0",
    "gn:admin2_code":"81.0",
    "gn:asciiname":"Kuchpar",
    "gn:country_code":"IN",
    "gn:dem":222,
    "gn:feature_class":"P",
    "gn:feature_code":"PPL",
    "gn:name":"Kuchpar",
    "gn:population":0,
    "gn:timezone":"Asia/Kolkata",
    "iso:country":"IN",
    "wof:name":"Kuchpar",
    "wof:placetype":"locality"
},
  "geometry": {"coordinates":[76.21079,28.95233],"type":"Point"}
}