{
  "type": "Feature",
  "properties": {
    "gn:admin1_code":"36",
    "gn:admin2_code":"194.0",
    "gn:asciiname":"Alampur",
    "gn:country_code":"IN",
    "gn:dem":90,
    "gn:feature_class":"P",
    "gn:feature_code":"PPL",
    "gn:name":"\u0100lampur",
    "gn:population":0,
    "gn:timezone":"Asia/Kolkata",
    "iso:country":"IN",
    "ks:ks_name":"Aalampur",
    "ks:ks_pop":115,
    "ks:ks_type":"VILLAGE",
    "name:ceb_x_preferred":[
        "Alampur"
    ],
    "name:eng_x_preferred":[
        "Aalampur"
    ],
    "name:eng_x_variant":[
        "Alampur"
    ],
    "name:hin_x_preferred":[
        "\u0906\u0932\u092e\u092a\u0941\u0930"
    ],
    "name:swe_x_preferred":[
        "Alampur"
    ],
    "wof:name":"Aalampur",
    "wof:placetype":"locality",
    "wof:population":115
},
  "geometry": {"coordinates":[82.58527599999999,25.984476],"type":"Point"}
}