{
  "type": "Feature",
  "properties": {
    "gn:admin1_code":"38.0",
    "gn:admin2_code":"353.0",
    "gn:asciiname":"Maheshgaria",
    "gn:country_code":"IN",
    "gn:dem":67,
    "gn:feature_class":"P",
    "gn:feature_code":"PPL",
    "gn:name":"Maheshgaria",
    "gn:population":0,
    "gn:timezone":"Asia/Kolkata",
    "iso:country":"IN",
    "ks:ks_name":"Maheshgaria",
    "ks:ks_pop":575,
    "ks:ks_type":"VILLAGE",
    "name:eng_x_preferred":[
        "Maheshgaria"
    ],
    "wof:name":"Maheshgaria",
    "wof:placetype":"locality",
    "wof:population":575
},
  "geometry": {"coordinates":[87.70586900000001,24.467144],"type":"Point"}
}