{
  "type": "Feature",
  "properties": {
    "iso:country":"IN",
    "ks:ks_name":"Nutan Para",
    "ks:ks_pop":347,
    "ks:ks_type":"HABITATION",
    "name:eng_x_preferred":[
        "Nutan Para"
    ],
    "wof:name":"Nutan Para",
    "wof:placetype":"locality",
    "wof:population":347
},
  "geometry": {"coordinates":[92.203627,23.754261],"type":"Point"}
}