{
  "type": "Feature",
  "properties": {
    "iso:country":"IN",
    "ks:ks_name":"Kebat Tola",
    "ks:ks_pop":344,
    "ks:ks_type":"HABITATION",
    "name:eng_x_preferred":[
        "Kebat Tola"
    ],
    "wof:name":"Kebat Tola",
    "wof:placetype":"locality",
    "wof:population":344
},
  "geometry": {"coordinates":[86.216397,24.089558],"type":"Point"}
}