{
  "type": "Feature",
  "properties": {
    "iso:country":"IN",
    "ks:ks_name":"Gadaipura",
    "ks:ks_pop":158,
    "ks:ks_type":"VILLAGE",
    "name:eng_x_preferred":[
        "Gadaipura"
    ],
    "wof:name":"Gadaipura",
    "wof:placetype":"locality",
    "wof:population":158
},
  "geometry": {"coordinates":[79.122517,27.173845],"type":"Point"}
}