{
  "type": "Feature",
  "properties": {
    "iso:country":"IN",
    "ks:ks_name":"Borahom Katoni",
    "ks:ks_pop":498,
    "ks:ks_type":"VILLAGE",
    "ks:ks_uagg_main":0,
    "name:eng_x_preferred":[
        "Borahom Katoni"
    ],
    "wof:name":"Borahom Katoni",
    "wof:placetype":"locality",
    "wof:population":498
},
  "geometry": {"coordinates":[94.107513,26.737226],"type":"Point"}
}