{
  "type": "Feature",
  "properties": {
    "iso:country":"IN",
    "name:ben_x_preferred":[
        "\u099c\u09af\u09bc\u0999\u09cd\u0995\u09cb\u09a3\u09cd\u09a1\u09ae"
    ],
    "name:bpy_x_preferred":[
        "\u099c\u09af\u09bc\u09a8\u0995\u09cb\u09a8\u09cd\u09a1\u09ae"
    ],
    "name:ceb_x_preferred":[
        "Jayamkondacholapuram"
    ],
    "name:eng_x_preferred":[
        "Jayankondam"
    ],
    "name:fra_x_preferred":[
        "Jayankondam"
    ],
    "name:hin_x_preferred":[
        "\u091c\u092f\u0928\u0915\u094b\u0902\u0921\u092e"
    ],
    "name:ita_x_preferred":[
        "Jayankondam"
    ],
    "name:msa_x_preferred":[
        "Jayankondam"
    ],
    "name:nan_x_preferred":[
        "Jayankondam"
    ],
    "name:new_x_preferred":[
        "\u091c\u092f\u0915\u0941\u0923\u094d\u0921\u092e"
    ],
    "name:nld_x_preferred":[
        "Jayankondam"
    ],
    "name:por_x_preferred":[
        "Jayankondam"
    ],
    "name:spa_x_preferred":[
        "Jayankondam"
    ],
    "name:swe_x_preferred":[
        "Jayamkondacholapuram"
    ],
    "name:tam_x_preferred":[
        "\u0b9c\u0bc6\u0baf\u0b99\u0bcd\u0b95\u0bca\u0ba3\u0bcd\u0b9f\u0bae\u0bcd"
    ],
    "name:vie_x_preferred":[
        "Jayankondam"
    ],
    "name:zho_x_preferred":[
        "\u8d3e\u5ef6\u5b54\u8fbe\u59c6"
    ],
    "qs:name":"Jayankondam",
    "qs:name_adm0":"India",
    "qs:name_adm1":"Tamil Nadu",
    "qs:photos":92,
    "qs:photos_1k":19,
    "qs:photos_9k":1,
    "qs:photos_9r":3,
    "qs:photos_all":92,
    "qs:photos_sr":3,
    "qs:placetype":"Town",
    "qs:pop_sr":"0",
    "wd:wordcount":522,
    "wof:name":"Jayankondam",
    "wof:placetype":"locality"
},
  "geometry": {"coordinates":[79.365019,11.211428],"type":"Point"}
}