{
  "type": "Feature",
  "properties": {
    "iso:country":"IN",
    "ks:ks_name":"Taramoy Para",
    "ks:ks_pop":190,
    "ks:ks_type":"HABITATION",
    "name:eng_x_preferred":[
        "Taramoy Para"
    ],
    "wof:name":"Taramoy Para",
    "wof:placetype":"locality",
    "wof:population":190
},
  "geometry": {"coordinates":[91.84774299999999,23.762176],"type":"Point"}
}