{
  "type": "Feature",
  "properties": {
    "gn:admin1_code":"24.0",
    "gn:admin2_code":"107.0",
    "gn:asciiname":"Jogdishpur",
    "gn:country_code":"IN",
    "gn:dem":216,
    "gn:feature_class":"P",
    "gn:feature_code":"PPL",
    "gn:name":"Jogd\u012bshpur",
    "gn:population":0,
    "gn:timezone":"Asia/Kolkata",
    "iso:country":"IN",
    "wof:name":"Jogdishpur",
    "wof:placetype":"locality"
},
  "geometry": {"coordinates":[76.94870999999998,26.82485],"type":"Point"}
}