{
  "type": "Feature",
  "properties": {
    "iso:country":"IN",
    "ks:ks_name":"Bhaisya Gangashri",
    "ks:ks_pop":118,
    "ks:ks_type":"VILLAGE",
    "name:eng_x_preferred":[
        "Bhaisya Gangashri"
    ],
    "wof:name":"Bhaisya Gangashri",
    "wof:placetype":"locality",
    "wof:population":118
},
  "geometry": {"coordinates":[79.084632,29.641997],"type":"Point"}
}