{
  "type": "Feature",
  "properties": {
    "iso:country":"IN",
    "ks:ks_name":"Jaurumal",
    "ks:ks_pop":1839,
    "ks:ks_type":"VILLAGE",
    "ks:ks_uagg_main":0,
    "name:eng_x_preferred":[
        "Jaurumal"
    ],
    "wof:name":"Jaurumal",
    "wof:placetype":"neighbourhood",
    "wof:population":1839
},
  "geometry": {"coordinates":[84.56910000000001,22.183747],"type":"Point"}
}