{
  "type": "Feature",
  "properties": {
    "iso:country":"IN",
    "ks:ks_name":"Bailukoppa",
    "ks:ks_pop":29,
    "ks:ks_type":"HABITATION",
    "name:eng_x_preferred":[
        "Bailukoppa"
    ],
    "wof:name":"Bailukoppa",
    "wof:placetype":"locality",
    "wof:population":29
},
  "geometry": {"coordinates":[75.19189900000001,13.407543],"type":"Point"}
}