{
  "type": "Feature",
  "properties": {
    "iso:country":"IN",
    "ks:ks_name":"Hotasar",
    "ks:ks_pop":210,
    "ks:ks_type":"HABITATION",
    "name:eng_x_preferred":[
        "Hotasar"
    ],
    "wof:name":"Hotasar",
    "wof:placetype":"locality",
    "wof:population":210
},
  "geometry": {"coordinates":[71.183207,27.420805],"type":"Point"}
}