{
  "type": "Feature",
  "properties": {
    "iso:country":"IN",
    "ks:ks_alt_nam":"HARIJAN TOLI-1",
    "ks:ks_name":"Harijan Toli-1",
    "ks:ks_pop":130,
    "ks:ks_type":"HABITATION",
    "name:eng_x_preferred":[
        "Harijan Toli-1"
    ],
    "wof:name":"Harijan Toli-1",
    "wof:placetype":"locality",
    "wof:population":130
},
  "geometry": {"coordinates":[83.969454,25.413866],"type":"Point"}
}