{
  "type": "Feature",
  "properties": {
    "iso:country":"IN",
    "ks:ks_name":"Behirabadih",
    "ks:ks_pop":86,
    "ks:ks_type":"VILLAGE",
    "name:eng_x_preferred":[
        "Behirabadih"
    ],
    "wof:name":"Behirabadih",
    "wof:placetype":"locality",
    "wof:population":86
},
  "geometry": {"coordinates":[87.081813,24.910675],"type":"Point"}
}