{
  "type": "Feature",
  "properties": {
    "gn:admin1_code":"36",
    "gn:admin2_code":"198.0",
    "gn:asciiname":"Ajaipur",
    "gn:country_code":"IN",
    "gn:dem":90,
    "gn:feature_class":"P",
    "gn:feature_code":"PPL",
    "gn:name":"Ajaipur",
    "gn:population":0,
    "gn:timezone":"Asia/Kolkata",
    "iso:country":"IN",
    "name:urd_x_preferred":[
        "\u0627\u062c\u0627\u0626\u06cc \u067e\u0648\u0631"
    ],
    "wof:name":"Ajaipur",
    "wof:placetype":"locality"
},
  "geometry": {"coordinates":[82.49564000000002,25.3814],"type":"Point"}
}