{
  "type": "Feature",
  "properties": {
    "gn:admin1_code":"35.0",
    "gn:admin2_code":"465.0",
    "gn:asciiname":"Kalibel",
    "gn:country_code":"IN",
    "gn:dem":337,
    "gn:feature_class":"P",
    "gn:feature_code":"PPL",
    "gn:name":"Kalibel",
    "gn:population":0,
    "gn:timezone":"Asia/Kolkata",
    "iso:country":"IN",
    "wof:name":"Kalibel",
    "wof:placetype":"locality"
},
  "geometry": {"coordinates":[74.21065,22.21859],"type":"Point"}
}