{
  "type": "Feature",
  "properties": {
    "gn:country":"IN",
    "gn:fcode":"PPL",
    "gn:pop":6020,
    "iso:country":"IN",
    "name:ben_x_preferred":[
        "\u0985\u09b8\u09b0\u0997\u099e\u09cd\u099c"
    ],
    "name:bpy_x_preferred":[
        "\u0985\u09b8\u09be\u09b0\u0997\u099e\u09cd\u099c"
    ],
    "name:eng_x_preferred":[
        "Asarganj"
    ],
    "name:fra_x_preferred":[
        "Asarganj"
    ],
    "name:guj_x_preferred":[
        "\u0a85\u0ab8\u0ab0\u0a97\u0a82\u0a9c"
    ],
    "name:hin_x_preferred":[
        "\u0905\u0938\u0930\u0917\u0902\u091c"
    ],
    "name:ita_x_preferred":[
        "Asarganj"
    ],
    "name:msa_x_preferred":[
        "Asarganj"
    ],
    "name:nan_x_preferred":[
        "Asarganj"
    ],
    "name:nep_x_preferred":[
        "\u0905\u0938\u0930\u0917\u0902\u091c"
    ],
    "name:new_x_preferred":[
        "\u0905\u0938\u0930\u0917\u091e\u094d\u091c"
    ],
    "name:nld_x_preferred":[
        "Asarganj"
    ],
    "name:ori_x_preferred":[
        "\u0b06\u0b38\u0b30\u0b4d\u200c\u0b17\u0b1e\u0b4d\u0b1c"
    ],
    "name:pan_x_preferred":[
        "\u0a05\u0a38\u0a30\u0a17\u0a70\u0a1c"
    ],
    "name:por_x_preferred":[
        "Asarganj"
    ],
    "name:swe_x_preferred":[
        "Asarganj"
    ],
    "name:unk_x_variant":[
        "Asarganj"
    ],
    "name:urd_x_preferred":[
        "\u0627\u0633\u0631\u06af\u0646\u062c"
    ],
    "name:vie_x_preferred":[
        "Asarganj"
    ],
    "name:zho_x_preferred":[
        "\u963f\u8428\u5c14\u52a0\u6069\u6770"
    ],
    "qs:name":"Madarganj",
    "qs:name_adm0":"India",
    "qs:name_adm1":"Bihar",
    "qs:photos_9r":0,
    "qs:photos_sr":0,
    "qs:placetype":"Town",
    "qs:pop_sr":"5",
    "wof:name":"Madarganj",
    "wof:placetype":"locality",
    "wof:population":6020
},
  "geometry": {"coordinates":[86.68639,25.15046],"type":"Point"}
}