{
  "type": "Feature",
  "properties": {
    "gn:admin1_code":"36.0",
    "gn:admin2_code":"189.0",
    "gn:asciiname":"Sakhui Misir",
    "gn:country_code":"IN",
    "gn:dem":91,
    "gn:feature_class":"P",
    "gn:feature_code":"PPL",
    "gn:name":"Sakhui Misir",
    "gn:population":0,
    "gn:timezone":"Asia/Kolkata",
    "iso:country":"IN",
    "ks:ks_name":"Sakhui Misir",
    "ks:ks_type":"VILLAGE",
    "name:eng_x_preferred":[
        "Sakhui Misir"
    ],
    "wof:name":"Sakhui Misir",
    "wof:placetype":"locality"
},
  "geometry": {"coordinates":[83.88846700000001,26.945202],"type":"Point"}
}