{
  "type": "Feature",
  "properties": {
    "iso:country":"IN",
    "ks:ks_alt_nam":"mushahr basti",
    "ks:ks_name":"Mushahr Basti",
    "ks:ks_pop":155,
    "ks:ks_type":"HABITATION",
    "name:eng_x_preferred":[
        "Mushahr Basti"
    ],
    "wof:name":"Mushahr Basti",
    "wof:placetype":"locality",
    "wof:population":155
},
  "geometry": {"coordinates":[82.93875199999999,25.444769],"type":"Point"}
}