{
  "type": "Feature",
  "properties": {
    "iso:country":"IN",
    "ks:ks_name":"Hosalli",
    "ks:ks_pop":294,
    "ks:ks_type":"HABITATION",
    "name:eng_x_preferred":[
        "Hosalli"
    ],
    "wof:name":"Hosalli",
    "wof:placetype":"locality",
    "wof:population":294
},
  "geometry": {"coordinates":[77.467983,12.137458],"type":"Point"}
}