{
  "type": "Feature",
  "properties": {
    "gn:admin1_code":"24.0",
    "gn:admin2_code":"122.0",
    "gn:asciiname":"Murliya",
    "gn:country_code":"IN",
    "gn:dem":388,
    "gn:feature_class":"P",
    "gn:feature_code":"PPL",
    "gn:name":"Murliya",
    "gn:population":0,
    "gn:timezone":"Asia/Kolkata",
    "iso:country":"IN",
    "ks:ks_name":"Murliya",
    "ks:ks_pop":823,
    "ks:ks_type":"VILLAGE",
    "name:eng_x_preferred":[
        "Murliya"
    ],
    "wof:name":"Murliya",
    "wof:placetype":"locality",
    "wof:population":823
},
  "geometry": {"coordinates":[74.801017,25.18945],"type":"Point"}
}