{
  "type": "Feature",
  "properties": {
    "iso:country":"IN",
    "ks:ks_name":"P Jagannath",
    "ks:ks_pop":307,
    "ks:ks_type":"HABITATION",
    "name:eng_x_preferred":[
        "P Jagannath"
    ],
    "wof:name":"P Jagannath",
    "wof:placetype":"locality",
    "wof:population":307
},
  "geometry": {"coordinates":[81.42809200000001,26.196386],"type":"Point"}
}