{
  "type": "Feature",
  "properties": {
    "gn:admin1_code":"19.0",
    "gn:admin2_code":"582.0",
    "gn:asciiname":"Doddabommanahalli",
    "gn:country_code":"IN",
    "gn:dem":843,
    "gn:feature_class":"P",
    "gn:feature_code":"PPL",
    "gn:name":"Doddabommanahalli",
    "gn:population":0,
    "gn:timezone":"Asia/Kolkata",
    "iso:country":"IN",
    "wof:name":"Doddabommanahalli",
    "wof:placetype":"locality"
},
  "geometry": {"coordinates":[78.11895,13.30948],"type":"Point"}
}