{
  "type": "Feature",
  "properties": {
    "iso:country":"IN",
    "ks:ks_name":"Amarpura",
    "ks:ks_pop":30,
    "ks:ks_type":"VILLAGE",
    "name:eng_x_preferred":[
        "Amarpura"
    ],
    "wof:name":"Amarpura",
    "wof:placetype":"locality",
    "wof:population":30
},
  "geometry": {"coordinates":[74.785197,23.957826],"type":"Point"}
}