{
  "type": "Feature",
  "properties": {
    "iso:country":"IN",
    "ks:ks_name":"Vengoor West",
    "ks:ks_pop":17318,
    "ks:ks_type":"VILLAGE",
    "name:eng_x_preferred":[
        "Vengoor West"
    ],
    "wof:name":"Vengoor West",
    "wof:placetype":"locality",
    "wof:population":17318
},
  "geometry": {"coordinates":[76.536936,10.114388],"type":"Point"}
}