{
  "type": "Feature",
  "properties": {
    "iso:country":"IN",
    "ks:ks_alt_nam":"Gidhm\u0101l",
    "ks:ks_name":"Gidhmal",
    "ks:ks_pop":208,
    "ks:ks_type":"VILLAGE",
    "name:eng_x_preferred":[
        "Gidhmal"
    ],
    "name:eng_x_variant":[
        "Gidhm\u0101l"
    ],
    "wof:name":"Gidhmal",
    "wof:placetype":"locality",
    "wof:population":208
},
  "geometry": {"coordinates":[84.04178400000001,21.192003],"type":"Point"}
}