{
  "type": "Feature",
  "properties": {
    "gn:admin1_code":"24.0",
    "gn:admin2_code":"100.0",
    "gn:asciiname":"Kharliyan",
    "gn:country_code":"IN",
    "gn:dem":178,
    "gn:feature_class":"P",
    "gn:feature_code":"PPL",
    "gn:name":"Kharliy\u0101n",
    "gn:population":0,
    "gn:timezone":"Asia/Kolkata",
    "iso:country":"IN",
    "wof:name":"Kharliyan",
    "wof:placetype":"neighbourhood"
},
  "geometry": {"coordinates":[73.99290000000001,29.52244],"type":"Point"}
}