{
  "type": "Feature",
  "properties": {
    "iso:country":"IN",
    "name:ara_x_preferred":[
        "\u062c\u0627\u064a\u0633\u0628\u0648\u0631\u0627"
    ],
    "name:ben_bn_x_preferred":[
        "\u0997\u09bf\u09df\u09be\u09b8\u09aa\u09c1\u09b0\u09be"
    ],
    "name:ben_in_x_preferred":[
        "\u0997\u09bf\u09df\u09be\u09b8\u09aa\u09c1\u09b0\u09be"
    ],
    "name:eng_x_preferred":[
        "Gyaspura"
    ],
    "name:guj_x_preferred":[
        "\u0a97\u0aaf\u0abe\u0ab8\u0acd\u0aaa\u0ac1\u0ab0\u0abe"
    ],
    "name:hin_x_preferred":[
        "\u0917\u094d\u092f\u093e\u0938\u092a\u0941\u0930\u093e"
    ],
    "name:kan_x_preferred":[
        "\u0c97\u0ccd\u0caf\u0cbe\u0cb8\u0ccd"
    ],
    "name:mal_x_preferred":[
        "\u0d17\u0d4d\u0d2f\u0d3e\u0d38\u0d4d\u0d2a\u0d41\u0d30"
    ],
    "name:mar_x_preferred":[
        "\u0917\u094d\u092f\u093e\u0938\u092a\u0941\u0930\u093e"
    ],
    "name:pan_x_preferred":[
        "\u0a17\u0a3f\u0a06\u0a38\u0a2a\u0a41\u0a30\u0a3e"
    ],
    "name:tam_x_preferred":[
        "\u0b95\u0bcd\u0baf\u0bbe\u0bb8\u0bcd\u0baa\u0bc1\u0bb0\u0bbe"
    ],
    "name:tel_x_preferred":[
        "\u0c17\u0c4d\u0c2f\u0c3e\u0c38\u0c4d"
    ],
    "name:urd_x_preferred":[
        "\u063a\u06cc\u0627\u062b \u067e\u0648\u0631\u06c1"
    ],
    "qs:gn_adm0_cc":"IN",
    "qs:gn_fcode":"PPL",
    "qs:gn_local":1279259,
    "qs:gn_nam_loc":"Agra, Agra, Uttar Pradesh, IN",
    "qs:gn_namadm1":"24",
    "qs:gn_name":"Gajpura",
    "qs:local_max":10925,
    "qs:local_sum":42779,
    "qs:localhoods":21,
    "qs:name":"Gyaspura",
    "qs:name_adm0":"India",
    "qs:name_adm1":"Uttar Pradesh",
    "qs:name_adm2":"Agra",
    "qs:name_local":"Agra",
    "qs:photo_max":7,
    "qs:photo_sum":8,
    "qs:placetype":"Suburb",
    "qs:quad_count":2,
    "qs:woe_adm0":23424848,
    "qs:woe_adm1":2345760,
    "qs:woe_adm2":12586712,
    "qs:woe_lau":0,
    "qs:woe_local":2295399,
    "qs:woe_ver":"7.10.0",
    "wof:lang":[
        "eng"
    ],
    "wof:name":"Gyaspura",
    "wof:placetype":"neighbourhood"
},
  "geometry": {"coordinates":[77.978897,27.174026],"type":"Point"}
}