{
  "type": "Feature",
  "properties": {
    "iso:country":"IN",
    "ks:ks_name":"Munusa",
    "ks:ks_pop":85,
    "ks:ks_type":"VILLAGE",
    "name:eng_x_preferred":[
        "Munusa"
    ],
    "wof:name":"Munusa",
    "wof:placetype":"locality",
    "wof:population":85
},
  "geometry": {"coordinates":[81.97102099999999,18.376116],"type":"Point"}
}