{
  "type": "Feature",
  "properties": {
    "iso:country":"IN",
    "ks:ks_name":"Lalapur",
    "ks:ks_pop":21,
    "ks:ks_type":"VILLAGE",
    "name:eng_x_preferred":[
        "Lalapur"
    ],
    "wof:name":"Lalapur",
    "wof:placetype":"locality",
    "wof:population":21
},
  "geometry": {"coordinates":[75.581295,31.492223],"type":"Point"}
}