{
  "type": "Feature",
  "properties": {
    "iso:country":"IN",
    "ks:ks_name":"Abdul Purwa",
    "ks:ks_pop":76,
    "ks:ks_type":"HABITATION",
    "name:eng_x_preferred":[
        "Abdul Purwa"
    ],
    "wof:name":"Abdul Purwa",
    "wof:placetype":"locality",
    "wof:population":76
},
  "geometry": {"coordinates":[81.94368799999999,27.592943],"type":"Point"}
}