{
  "type": "Feature",
  "properties": {
    "iso:country":"IN",
    "ks:ks_name":"Deetowala",
    "ks:ks_pop":0,
    "ks:ks_type":"VILLAGE",
    "name:eng_x_preferred":[
        "Deetowala"
    ],
    "wof:name":"Deetowala",
    "wof:placetype":"locality",
    "wof:population":0
},
  "geometry": {"coordinates":[70.731493,27.738246],"type":"Point"}
}