{
  "type": "Feature",
  "properties": {
    "iso:country":"IN",
    "ks:ks_name":"Sahupara",
    "ks:ks_pop":171,
    "ks:ks_type":"HABITATION",
    "name:eng_x_preferred":[
        "Sahupara"
    ],
    "wof:name":"Sahupara",
    "wof:placetype":"locality",
    "wof:population":171
},
  "geometry": {"coordinates":[82.42764,19.676412],"type":"Point"}
}