{
  "type": "Feature",
  "properties": {
    "iso:country":"IN",
    "ks:ks_name":"Baghera",
    "ks:ks_pop":307,
    "ks:ks_type":"HABITATION",
    "name:eng_x_preferred":[
        "Baghera"
    ],
    "wof:name":"Baghera",
    "wof:placetype":"locality",
    "wof:population":307
},
  "geometry": {"coordinates":[81.22168600000001,24.86246],"type":"Point"}
}