{
  "type": "Feature",
  "properties": {
    "gn:admin1_code":"11.0",
    "gn:admin2_code":"33.0",
    "gn:asciiname":"Dim",
    "gn:country_code":"IN",
    "gn:dem":2409,
    "gn:feature_class":"P",
    "gn:feature_code":"PPL",
    "gn:name":"Dim",
    "gn:population":0,
    "gn:timezone":"Asia/Kolkata",
    "iso:country":"IN",
    "name:bos_x_preferred":[
        "Dim"
    ],
    "name:ceb_x_preferred":[
        "Dim"
    ],
    "name:fra_x_preferred":[
        "Dim"
    ],
    "name:swe_x_preferred":[
        "Dim"
    ],
    "wof:name":"Dim",
    "wof:placetype":"locality"
},
  "geometry": {"coordinates":[77.65004,31.11915],"type":"Point"}
}