{
  "type": "Feature",
  "properties": {
    "iso:country":"IN",
    "ks:ks_name":"Kodarige",
    "ks:ks_pop":73,
    "ks:ks_type":"HABITATION",
    "name:eng_x_preferred":[
        "Kodarige"
    ],
    "wof:name":"Kodarige",
    "wof:placetype":"locality",
    "wof:population":73
},
  "geometry": {"coordinates":[75.129465,14.042691],"type":"Point"}
}