{
  "type": "Feature",
  "properties": {
    "iso:country":"IN",
    "ks:ks_name":"Ramreddy Camp",
    "ks:ks_pop":1159,
    "ks:ks_type":"HABITATION",
    "name:eng_x_preferred":[
        "Ramreddy Camp"
    ],
    "wof:name":"Ramreddy Camp",
    "wof:placetype":"locality",
    "wof:population":1159
},
  "geometry": {"coordinates":[76.750322,15.836974],"type":"Point"}
}