{
  "type": "Feature",
  "properties": {
    "iso:country":"IN",
    "ks:ks_name":"Jaitpura",
    "ks:ks_pop":616,
    "ks:ks_type":"VILLAGE",
    "name:eng_x_preferred":[
        "Jaitpura"
    ],
    "wof:name":"Jaitpura",
    "wof:placetype":"locality",
    "wof:population":616
},
  "geometry": {"coordinates":[76.35591100000001,26.749275],"type":"Point"}
}