{
  "type": "Feature",
  "properties": {
    "iso:country":"IN",
    "ks:ks_name":"Jainagra",
    "ks:ks_pop":0,
    "ks:ks_type":"VILLAGE",
    "name:eng_x_preferred":[
        "Jainagra"
    ],
    "wof:name":"Jainagra",
    "wof:placetype":"locality",
    "wof:population":0
},
  "geometry": {"coordinates":[85.578012,24.674174],"type":"Point"}
}