{
  "type": "Feature",
  "properties": {
    "iso:country":"IN",
    "ks:ks_alt_nam":"PAWAR WASTI",
    "ks:ks_name":"Pawar Wasti",
    "ks:ks_pop":402,
    "ks:ks_type":"HABITATION",
    "name:eng_x_preferred":[
        "Pawar Wasti"
    ],
    "wof:name":"Pawar Wasti",
    "wof:placetype":"locality",
    "wof:population":402
},
  "geometry": {"coordinates":[74.459014,19.848359],"type":"Point"}
}