{
  "type": "Feature",
  "properties": {
    "iso:country":"IN",
    "ks:ks_name":"Bettahalliaragadu",
    "ks:ks_pop":172,
    "ks:ks_type":"HABITATION",
    "name:eng_x_preferred":[
        "Bettahalliaragadu"
    ],
    "wof:name":"Bettahalliaragadu",
    "wof:placetype":"locality",
    "wof:population":172
},
  "geometry": {"coordinates":[77.477979,12.482456],"type":"Point"}
}