{
  "type": "Feature",
  "properties": {
    "gn:admin1_code":"19.0",
    "gn:admin2_code":"572",
    "gn:asciiname":"Ibbalur",
    "gn:country_code":"IN",
    "gn:dem":893,
    "gn:feature_class":"P",
    "gn:feature_code":"PPL",
    "gn:name":"Ibbalur",
    "gn:population":0,
    "gn:timezone":"Asia/Kolkata",
    "iso:country":"IN",
    "wof:name":"Ibbalur",
    "wof:placetype":"neighbourhood"
},
  "geometry": {"coordinates":[77.66289,12.92173],"type":"Point"}
}