{
  "type": "Feature",
  "properties": {
    "iso:country":"IN",
    "ks:ks_name":"Artabali",
    "ks:ks_pop":59,
    "ks:ks_type":"VILLAGE",
    "name:eng_x_preferred":[
        "Artabali"
    ],
    "wof:name":"Artabali",
    "wof:placetype":"locality",
    "wof:population":59
},
  "geometry": {"coordinates":[83.634467,20.013425],"type":"Point"}
}