{
  "type": "Feature",
  "properties": {
    "gn:admin1_code":"38.0",
    "gn:admin2_code":"347.0",
    "gn:asciiname":"Ghuji",
    "gn:country_code":"IN",
    "gn:dem":210,
    "gn:feature_class":"P",
    "gn:feature_code":"PPL",
    "gn:name":"Ghuji",
    "gn:population":0,
    "gn:timezone":"Asia/Kolkata",
    "iso:country":"IN",
    "ks:ks_name":"Ghuji",
    "ks:ks_pop":845,
    "ks:ks_type":"VILLAGE",
    "ks:ks_uagg_main":0,
    "name:eng_x_preferred":[
        "Ghuji"
    ],
    "wof:name":"Ghuji",
    "wof:placetype":"neighbourhood",
    "wof:population":845
},
  "geometry": {"coordinates":[84.622686,24.386862],"type":"Point"}
}