{
  "type": "Feature",
  "properties": {
    "gn:admin1_code":"39.0",
    "gn:admin2_code":"66.0",
    "gn:asciiname":"Shiblalpur Pande",
    "gn:country_code":"IN",
    "gn:dem":331,
    "gn:feature_class":"P",
    "gn:feature_code":"PPL",
    "gn:name":"Shibl\u0101lpur P\u0101nde",
    "gn:population":0,
    "gn:timezone":"Asia/Kolkata",
    "iso:country":"IN",
    "ks:ks_name":"Shivlalpur Pandey",
    "ks:ks_type":"VILLAGE",
    "name:eng_x_preferred":[
        "Shivlalpur Pandey"
    ],
    "name:eng_x_variant":[
        "Shiblalpur Pande"
    ],
    "wof:name":"Shivlalpur Pandey",
    "wof:placetype":"locality"
},
  "geometry": {"coordinates":[79.256863,29.293817],"type":"Point"}
}