{
  "type": "Feature",
  "properties": {
    "iso:country":"IN",
    "ks:ks_name":"Konakuli",
    "ks:ks_pop":60,
    "ks:ks_type":"HABITATION",
    "name:eng_x_preferred":[
        "Konakuli"
    ],
    "wof:name":"Konakuli",
    "wof:placetype":"locality",
    "wof:population":60
},
  "geometry": {"coordinates":[74.308661,14.882733],"type":"Point"}
}