{
  "type": "Feature",
  "properties": {
    "iso:country":"IN",
    "ks:ks_name":"Bhelia Diha",
    "ks:ks_pop":80,
    "ks:ks_type":"VILLAGE",
    "name:eng_x_preferred":[
        "Bhelia Diha"
    ],
    "wof:name":"Bhelia Diha",
    "wof:placetype":"locality",
    "wof:population":80
},
  "geometry": {"coordinates":[87.06151800000001,22.018123],"type":"Point"}
}