{
  "type": "Feature",
  "properties": {
    "iso:country":"IN",
    "ks:ks_name":"Gawari",
    "ks:ks_pop":138,
    "ks:ks_type":"VILLAGE",
    "name:eng_x_preferred":[
        "Gawari"
    ],
    "wof:name":"Gawari",
    "wof:placetype":"locality",
    "wof:population":138
},
  "geometry": {"coordinates":[78.621999,30.026236],"type":"Point"}
}