{
  "type": "Feature",
  "properties": {
    "iso:country":"IN",
    "ks:ks_name":"Horogoppa",
    "ks:ks_pop":36,
    "ks:ks_type":"HABITATION",
    "name:eng_x_preferred":[
        "Horogoppa"
    ],
    "wof:name":"Horogoppa",
    "wof:placetype":"locality",
    "wof:population":36
},
  "geometry": {"coordinates":[74.784745,13.947356],"type":"Point"}
}