{
  "type": "Feature",
  "properties": {
    "iso:country":"IN",
    "ks:ks_name":"Lodi Kachari",
    "ks:ks_pop":91,
    "ks:ks_type":"HABITATION",
    "name:eng_x_preferred":[
        "Lodi Kachari"
    ],
    "wof:name":"Lodi Kachari",
    "wof:placetype":"locality",
    "wof:population":91
},
  "geometry": {"coordinates":[93.069436,25.008079],"type":"Point"}
}