{
  "type": "Feature",
  "properties": {
    "gn:admin1_code":"12.0",
    "gn:asciiname":"Taratsar",
    "gn:country_code":"IN",
    "gn:dem":2862,
    "gn:feature_class":"P",
    "gn:feature_code":"PPL",
    "gn:name":"Taratsar",
    "gn:population":0,
    "gn:timezone":"Asia/Kolkata",
    "iso:country":"IN",
    "wof:name":"Taratsar",
    "wof:placetype":"locality"
},
  "geometry": {"coordinates":[73.91226,34.41755],"type":"Point"}
}