{
  "type": "Feature",
  "properties": {
    "iso:country":"IN",
    "ks:ks_alt_nam":"lakshmipura",
    "ks:ks_name":"Lakshmipura",
    "ks:ks_pop":256,
    "ks:ks_type":"HABITATION",
    "name:eng_x_preferred":[
        "Lakshmipura"
    ],
    "wof:name":"Lakshmipura",
    "wof:placetype":"locality",
    "wof:population":256
},
  "geometry": {"coordinates":[76.65807700000001,12.671516],"type":"Point"}
}