{
  "type": "Feature",
  "properties": {
    "iso:country":"IN",
    "ks:ks_name":"Manikamputhur",
    "ks:ks_pop":206,
    "ks:ks_type":"HABITATION",
    "name:eng_x_preferred":[
        "Manikamputhur"
    ],
    "wof:name":"Manikamputhur",
    "wof:placetype":"locality",
    "wof:population":206
},
  "geometry": {"coordinates":[77.63723299999999,8.249992],"type":"Point"}
}