{
  "type": "Feature",
  "properties": {
    "gn:admin1_code":"11.0",
    "gn:admin2_code":"33.0",
    "gn:asciiname":"Bithal",
    "gn:country_code":"IN",
    "gn:dem":927,
    "gn:feature_class":"P",
    "gn:feature_code":"PPL",
    "gn:name":"Bithal",
    "gn:population":0,
    "gn:timezone":"Asia/Kolkata",
    "iso:country":"IN",
    "wof:name":"Bithal",
    "wof:placetype":"locality"
},
  "geometry": {"coordinates":[77.48399000000001,31.35221],"type":"Point"}
}