{
  "type": "Feature",
  "properties": {
    "iso:country":"IN",
    "ks:ks_name":"Valani Jn",
    "ks:ks_pop":584,
    "ks:ks_type":"HABITATION",
    "name:eng_x_preferred":[
        "Valani Jn"
    ],
    "wof:name":"Valani Jn",
    "wof:placetype":"locality",
    "wof:population":584
},
  "geometry": {"coordinates":[76.195966,11.117467],"type":"Point"}
}