{
  "type": "Feature",
  "properties": {
    "gn:admin1_code":"16.0",
    "gn:admin2_code":"499.0",
    "gn:asciiname":"Savkheda",
    "gn:country_code":"IN",
    "gn:dem":242,
    "gn:feature_class":"P",
    "gn:feature_code":"PPL",
    "gn:name":"S\u0101vkheda",
    "gn:population":0,
    "gn:timezone":"Asia/Kolkata",
    "iso:country":"IN",
    "name:und_x_variant":[
        "S\u0101vkheda",
        "Mar\u0101th\u012b"
    ],
    "wof:name":"Savkheda",
    "wof:placetype":"neighbourhood"
},
  "geometry": {"coordinates":[75.25429,20.90072],"type":"Point"}
}