{
  "type": "Feature",
  "properties": {
    "gn:admin1_code":"36.0",
    "gn:admin2_code":"195.0",
    "gn:asciiname":"Lawa",
    "gn:country_code":"IN",
    "gn:dem":74,
    "gn:feature_class":"P",
    "gn:feature_code":"PPL",
    "gn:name":"Law\u0101",
    "gn:population":0,
    "gn:timezone":"Asia/Kolkata",
    "iso:country":"IN",
    "name:ceb_x_preferred":[
        "Lawa"
    ],
    "name:deu_x_preferred":[
        "Lawa"
    ],
    "name:fra_x_preferred":[
        "Lawa"
    ],
    "name:ita_x_preferred":[
        "Lawa"
    ],
    "name:swe_x_preferred":[
        "Lawa"
    ],
    "wof:name":"Lawa",
    "wof:placetype":"neighbourhood"
},
  "geometry": {"coordinates":[83.61712,25.68501],"type":"Point"}
}