{
  "type": "Feature",
  "properties": {
    "iso:country":"IN",
    "ks:ks_name":"Keshwapur",
    "ks:ks_pop":583,
    "ks:ks_type":"VILLAGE",
    "ks:ks_uagg_main":0,
    "name:eng_x_preferred":[
        "Keshwapur"
    ],
    "wof:name":"Keshwapur",
    "wof:placetype":"neighbourhood",
    "wof:population":583
},
  "geometry": {"coordinates":[79.767506,18.05421],"type":"Point"}
}