{
  "type": "Feature",
  "properties": {
    "iso:country":"IN",
    "ks:ks_name":"Kathari Bilhata",
    "ks:ks_pop":513,
    "ks:ks_type":"VILLAGE",
    "name:eng_x_preferred":[
        "Kathari Bilhata"
    ],
    "wof:name":"Kathari Bilhata",
    "wof:placetype":"locality",
    "wof:population":513
},
  "geometry": {"coordinates":[79.941715,24.580325],"type":"Point"}
}