{
  "type": "Feature",
  "properties": {
    "iso:country":"IN",
    "ks:ks_name":"Kokatewasti",
    "ks:ks_pop":253,
    "ks:ks_type":"HABITATION",
    "name:eng_x_preferred":[
        "Kokatewasti"
    ],
    "wof:name":"Kokatewasti",
    "wof:placetype":"locality",
    "wof:population":253
},
  "geometry": {"coordinates":[74.025813,19.242328],"type":"Point"}
}