{
  "type": "Feature",
  "properties": {
    "iso:country":"IN",
    "ks:ks_name":"Palada",
    "ks:ks_pop":326,
    "ks:ks_type":"VILLAGE",
    "name:eng_x_preferred":[
        "Palada"
    ],
    "wof:name":"Palada",
    "wof:placetype":"locality",
    "wof:population":326
},
  "geometry": {"coordinates":[84.25188,19.521612],"type":"Point"}
}