{
  "type": "Feature",
  "properties": {
    "iso:country":"IN",
    "ks:ks_alt_nam":"J\u012br\u0101d",
    "ks:ks_name":"Jirad",
    "ks:ks_pop":185,
    "ks:ks_type":"VILLAGE",
    "name:eng_x_preferred":[
        "Jirad"
    ],
    "name:eng_x_variant":[
        "J\u012br\u0101d"
    ],
    "wof:name":"Jirad",
    "wof:placetype":"locality",
    "wof:population":185
},
  "geometry": {"coordinates":[84.47829900000001,20.650174],"type":"Point"}
}