{
  "type": "Feature",
  "properties": {
    "iso:country":"IN",
    "ks:ks_alt_nam":"Mangalp\u0101di",
    "ks:ks_name":"Mangalpadi",
    "ks:ks_type":"VILLAGE",
    "name:eng_x_preferred":[
        "Mangalpadi"
    ],
    "name:eng_x_variant":[
        "Mangalp\u0101di"
    ],
    "wof:name":"Mangalpadi",
    "wof:placetype":"locality"
},
  "geometry": {"coordinates":[79.65098399999999,12.849983],"type":"Point"}
}