{
  "type": "Feature",
  "properties": {
    "iso:country":"IN",
    "ks:ks_name":"Rakanpur",
    "ks:ks_pop":2145,
    "ks:ks_type":"VILLAGE",
    "ks:ks_uagg_main":0,
    "name:eng_x_preferred":[
        "Rakanpur"
    ],
    "wof:name":"Rakanpur",
    "wof:placetype":"locality",
    "wof:population":2145
},
  "geometry": {"coordinates":[72.484278,23.104694],"type":"Point"}
}