{
  "type": "Feature",
  "properties": {
    "iso:country":"IN",
    "ks:ks_name":"Benathali",
    "ks:ks_pop":1249,
    "ks:ks_type":"VILLAGE",
    "name:eng_x_preferred":[
        "Benathali"
    ],
    "wof:name":"Benathali",
    "wof:placetype":"locality",
    "wof:population":1249
},
  "geometry": {"coordinates":[88.09414200000001,23.032511],"type":"Point"}
}