{
  "type": "Feature",
  "properties": {
    "iso:country":"IN",
    "ks:ks_name":"Palhaji Madhya Supa",
    "ks:ks_pop":855,
    "ks:ks_type":"HABITATION",
    "ks:ks_uagg_main":0,
    "name:eng_x_preferred":[
        "Palhaji Madhya Supa"
    ],
    "wof:name":"Palhaji Madhya Supa",
    "wof:placetype":"neighbourhood",
    "wof:population":855
},
  "geometry": {"coordinates":[91.054058,26.267088],"type":"Point"}
}