{
  "type": "Feature",
  "properties": {
    "iso:country":"IN",
    "ks:ks_name":"Phutan",
    "ks:ks_pop":182,
    "ks:ks_type":"HABITATION",
    "name:eng_x_preferred":[
        "Phutan"
    ],
    "wof:name":"Phutan",
    "wof:placetype":"locality",
    "wof:population":182
},
  "geometry": {"coordinates":[73.354861,24.240583],"type":"Point"}
}