{
  "type": "Feature",
  "properties": {
    "iso:country":"IN",
    "ks:ks_name":"Mal Falia",
    "ks:ks_pop":90,
    "ks:ks_type":"HABITATION",
    "ks:ks_uagg_main":0,
    "name:eng_x_preferred":[
        "Mal Falia"
    ],
    "wof:name":"Mal Falia",
    "wof:placetype":"neighbourhood",
    "wof:population":90
},
  "geometry": {"coordinates":[73.311167,20.689806],"type":"Point"}
}