{
  "type": "Feature",
  "properties": {
    "gn:admin1_code":"12.0",
    "gn:admin2_code":"001",
    "gn:asciiname":"Undi",
    "gn:country_code":"IN",
    "gn:dem":3121,
    "gn:feature_class":"P",
    "gn:feature_code":"PPL",
    "gn:name":"\u016andi",
    "gn:population":0,
    "gn:timezone":"Asia/Kolkata",
    "iso:country":"IN",
    "name:new_x_preferred":[
        "\u0909\u0902\u0921\u093f \u092e\u0923\u094d\u0921\u0932"
    ],
    "name:tam_x_preferred":[
        "\u0b89\u0ba3\u0bcd\u0b9f\u0bbf"
    ],
    "name:tel_x_preferred":[
        "\u0c09\u0c02\u0c21\u0c3f"
    ],
    "name:urd_x_preferred":[
        "\u0627\u0648\u0646\u0688\u06cc"
    ],
    "wof:name":"Undi",
    "wof:placetype":"locality"
},
  "geometry": {"coordinates":[73.92161,34.46887],"type":"Point"}
}