{
  "type": "Feature",
  "properties": {
    "iso:country":"IN",
    "ks:ks_name":"Shendge Wasti",
    "ks:ks_pop":210,
    "ks:ks_type":"HABITATION",
    "name:eng_x_preferred":[
        "Shendge Wasti"
    ],
    "wof:name":"Shendge Wasti",
    "wof:placetype":"locality",
    "wof:population":210
},
  "geometry": {"coordinates":[75.34833999999999,18.166577],"type":"Point"}
}