{
  "type": "Feature",
  "properties": {
    "iso:country":"IN",
    "ks:ks_name":"Habutola",
    "ks:ks_pop":422,
    "ks:ks_type":"HABITATION",
    "name:eng_x_preferred":[
        "Habutola"
    ],
    "wof:name":"Habutola",
    "wof:placetype":"locality",
    "wof:population":422
},
  "geometry": {"coordinates":[80.14820400000001,21.54662],"type":"Point"}
}