{
  "type": "Feature",
  "properties": {
    "iso:country":"IN",
    "ks:ks_alt_nam":"Gangimundatoli",
    "ks:ks_name":"Gangimunda",
    "ks:ks_pop":139,
    "ks:ks_type":"VILLAGE",
    "name:eng_x_preferred":[
        "Gangimunda"
    ],
    "name:eng_x_variant":[
        "Gangimundatoli"
    ],
    "wof:name":"Gangimunda",
    "wof:placetype":"locality",
    "wof:population":139
},
  "geometry": {"coordinates":[84.19161,22.660954],"type":"Point"}
}