{
  "type": "Feature",
  "properties": {
    "gn:admin1_code":"19",
    "gn:admin2_code":"579.0",
    "gn:asciiname":"Polkampalli Tanda",
    "gn:country_code":"IN",
    "gn:dem":463,
    "gn:feature_class":"P",
    "gn:feature_code":"PPL",
    "gn:name":"Polkampalli T\u0101nda",
    "gn:population":0,
    "gn:timezone":"Asia/Kolkata",
    "iso:country":"IN",
    "wof:name":"Polkampalli Tanda",
    "wof:placetype":"locality"
},
  "geometry": {"coordinates":[77.44931,17.41185],"type":"Point"}
}