{
  "type": "Feature",
  "properties": {
    "iso:country":"IN",
    "ks:ks_name":"Nagla Bebalpur",
    "ks:ks_pop":187,
    "ks:ks_type":"HABITATION",
    "name:eng_x_preferred":[
        "Nagla Bebalpur"
    ],
    "wof:name":"Nagla Bebalpur",
    "wof:placetype":"locality",
    "wof:population":187
},
  "geometry": {"coordinates":[78.674482,27.264921],"type":"Point"}
}