{
  "type": "Feature",
  "properties": {
    "iso:country":"IN",
    "ks:ks_name":"Badda Talla",
    "ks:ks_pop":24,
    "ks:ks_type":"HABITATION",
    "name:eng_x_preferred":[
        "Badda Talla"
    ],
    "wof:name":"Badda Talla",
    "wof:placetype":"locality",
    "wof:population":24
},
  "geometry": {"coordinates":[78.888411,29.785685],"type":"Point"}
}