{
  "type": "Feature",
  "properties": {
    "iso:country":"IN",
    "ks:ks_name":"Kharagpur",
    "ks:ks_type":"VILLAGE",
    "name:eng_x_preferred":[
        "Kharagpur"
    ],
    "wof:name":"Kharagpur",
    "wof:placetype":"locality"
},
  "geometry": {"coordinates":[78.155591,28.76567],"type":"Point"}
}