{
  "type": "Feature",
  "properties": {
    "iso:country":"IN",
    "ks:ks_name":"Anjani Mukku",
    "ks:ks_pop":1325,
    "ks:ks_type":"HABITATION",
    "name:eng_x_preferred":[
        "Anjani Mukku"
    ],
    "wof:name":"Anjani Mukku",
    "wof:placetype":"locality",
    "wof:population":1325
},
  "geometry": {"coordinates":[75.80463399999999,11.61144],"type":"Point"}
}