{
  "type": "Feature",
  "properties": {
    "iso:country":"IN",
    "ks:ks_name":"Usara Tola",
    "ks:ks_pop":142,
    "ks:ks_type":"HABITATION",
    "ks:ks_uagg_main":0,
    "name:eng_x_preferred":[
        "Usara Tola"
    ],
    "wof:name":"Usara Tola",
    "wof:placetype":"neighbourhood",
    "wof:population":142
},
  "geometry": {"coordinates":[83.886685,26.38739],"type":"Point"}
}