{
  "type": "Feature",
  "properties": {
    "iso:country":"IN",
    "ks:ks_alt_nam":"NAIK WADI",
    "ks:ks_name":"Naik Wadi",
    "ks:ks_pop":231,
    "ks:ks_type":"HABITATION",
    "name:eng_x_preferred":[
        "Naik Wadi"
    ],
    "wof:name":"Naik Wadi",
    "wof:placetype":"locality",
    "wof:population":231
},
  "geometry": {"coordinates":[75.16680599999999,17.172035],"type":"Point"}
}