{
  "type": "Feature",
  "properties": {
    "gn:admin1_code":"36.0",
    "gn:admin2_code":"158.0",
    "gn:asciiname":"Milkha Sahib",
    "gn:country_code":"IN",
    "gn:dem":116,
    "gn:feature_class":"P",
    "gn:feature_code":"PPL",
    "gn:name":"Milkha S\u0101hib",
    "gn:population":0,
    "gn:timezone":"Asia/Kolkata",
    "iso:country":"IN",
    "wof:name":"Milkha Sahib",
    "wof:placetype":"neighbourhood"
},
  "geometry": {"coordinates":[81.21371000000001,26.08268],"type":"Point"}
}