{
  "type": "Feature",
  "properties": {
    "iso:country":"IN",
    "ks:ks_name":"Mailpiri",
    "ks:ks_pop":60,
    "ks:ks_type":"VILLAGE",
    "name:eng_x_preferred":[
        "Mailpiri"
    ],
    "wof:name":"Mailpiri",
    "wof:placetype":"locality",
    "wof:population":60
},
  "geometry": {"coordinates":[85.433561,22.953347],"type":"Point"}
}