{
  "type": "Feature",
  "properties": {
    "gn:admin1_code":"24.0",
    "gn:admin2_code":"119.0",
    "gn:asciiname":"Balapura",
    "gn:country_code":"IN",
    "gn:dem":393,
    "gn:feature_class":"P",
    "gn:feature_code":"PPL",
    "gn:name":"B\u0101lapura",
    "gn:population":0,
    "gn:timezone":"Asia/Kolkata",
    "iso:country":"IN",
    "wof:name":"Balapura",
    "wof:placetype":"locality"
},
  "geometry": {"coordinates":[74.89024000000001,26.01078],"type":"Point"}
}