{
  "type": "Feature",
  "properties": {
    "iso:country":"IN",
    "ks:ks_name":"Saiadpur Chak",
    "ks:ks_pop":28,
    "ks:ks_type":"VILLAGE",
    "name:eng_x_preferred":[
        "Saiadpur Chak"
    ],
    "wof:name":"Saiadpur Chak",
    "wof:placetype":"locality",
    "wof:population":28
},
  "geometry": {"coordinates":[87.991525,23.236314],"type":"Point"}
}