{
  "type": "Feature",
  "properties": {
    "iso:country":"IN",
    "ks:ks_name":"Rava",
    "ks:ks_pop":270,
    "ks:ks_type":"VILLAGE",
    "name:eng_x_preferred":[
        "Rava"
    ],
    "wof:name":"Rava",
    "wof:placetype":"locality",
    "wof:population":270
},
  "geometry": {"coordinates":[82.258531,18.324124],"type":"Point"}
}