{
  "type": "Feature",
  "properties": {
    "iso:country":"IN",
    "ks:ks_name":"Tarnagadde",
    "ks:ks_pop":346,
    "ks:ks_type":"HABITATION",
    "name:eng_x_preferred":[
        "Tarnagadde"
    ],
    "wof:name":"Tarnagadde",
    "wof:placetype":"locality",
    "wof:population":346
},
  "geometry": {"coordinates":[74.44997499999999,14.376517],"type":"Point"}
}