{
  "type": "Feature",
  "properties": {
    "gn:admin1_code":"35",
    "gn:admin2_code":"453.0",
    "gn:asciiname":"Sailwara",
    "gn:country_code":"IN",
    "gn:dem":780,
    "gn:feature_class":"P",
    "gn:feature_code":"PPL",
    "gn:name":"Sailw\u0101ra",
    "gn:population":0,
    "gn:timezone":"Asia/Kolkata",
    "iso:country":"IN",
    "wof:name":"Sailwara",
    "wof:placetype":"locality"
},
  "geometry": {"coordinates":[81.18356999999997,22.68437],"type":"Point"}
}