{
  "type": "Feature",
  "properties": {
    "iso:country":"IN",
    "ks:ks_alt_nam":"BAGMARA PAHARIA",
    "ks:ks_name":"Bagmara Paharia",
    "ks:ks_pop":29,
    "ks:ks_type":"HABITATION",
    "name:eng_x_preferred":[
        "Bagmara Paharia"
    ],
    "wof:name":"Bagmara Paharia",
    "wof:placetype":"locality",
    "wof:population":29
},
  "geometry": {"coordinates":[87.751868,24.331551],"type":"Point"}
}