{
  "type": "Feature",
  "properties": {
    "iso:country":"IN",
    "ks:ks_name":"Balrampura",
    "ks:ks_pop":265,
    "ks:ks_type":"VILLAGE",
    "name:eng_x_preferred":[
        "Balrampura"
    ],
    "wof:name":"Balrampura",
    "wof:placetype":"locality",
    "wof:population":265
},
  "geometry": {"coordinates":[76.12837500000001,26.657158],"type":"Point"}
}