{
  "type": "Feature",
  "properties": {
    "iso:country":"IN",
    "ks:ks_alt_nam":"KODAI KA PURWA",
    "ks:ks_name":"Kodai Ka Purwa",
    "ks:ks_pop":373,
    "ks:ks_type":"HABITATION",
    "name:eng_x_preferred":[
        "Kodai Ka Purwa"
    ],
    "wof:name":"Kodai Ka Purwa",
    "wof:placetype":"locality",
    "wof:population":373
},
  "geometry": {"coordinates":[81.959981,26.236362],"type":"Point"}
}