{
  "type": "Feature",
  "properties": {
    "iso:country":"IN",
    "ks:ks_alt_nam":"Manikoth kunnu",
    "ks:ks_name":"Manikoth Kunnu",
    "ks:ks_pop":615,
    "ks:ks_type":"HABITATION",
    "name:eng_x_preferred":[
        "Manikoth Kunnu"
    ],
    "wof:name":"Manikoth Kunnu",
    "wof:placetype":"locality",
    "wof:population":615
},
  "geometry": {"coordinates":[75.791445,11.526299],"type":"Point"}
}