{
  "type": "Feature",
  "properties": {
    "iso:country":"IN",
    "ks:ks_name":"Sawarapara",
    "ks:ks_pop":170,
    "ks:ks_type":"HABITATION",
    "name:eng_x_preferred":[
        "Sawarapara"
    ],
    "wof:name":"Sawarapara",
    "wof:placetype":"locality",
    "wof:population":170
},
  "geometry": {"coordinates":[82.539744,22.523607],"type":"Point"}
}