{
  "type": "Feature",
  "properties": {
    "iso:country":"IN",
    "ks:ks_name":"T Sulakunda",
    "ks:ks_pop":719,
    "ks:ks_type":"HABITATION",
    "name:eng_x_preferred":[
        "T Sulakunda"
    ],
    "wof:name":"T Sulakunda",
    "wof:placetype":"locality",
    "wof:population":719
},
  "geometry": {"coordinates":[77.65162599999999,12.433074],"type":"Point"}
}