{
  "type": "Feature",
  "properties": {
    "iso:country":"IN",
    "ks:ks_name":"Mangalwasi",
    "ks:ks_pop":426,
    "ks:ks_type":"VILLAGE",
    "name:eng_x_preferred":[
        "Mangalwasi"
    ],
    "wof:name":"Mangalwasi",
    "wof:placetype":"locality",
    "wof:population":426
},
  "geometry": {"coordinates":[74.177813,27.616377],"type":"Point"}
}