{
  "type": "Feature",
  "properties": {
    "iso:country":"IN",
    "ks:ks_name":"Sultanpurtanda",
    "ks:ks_pop":62,
    "ks:ks_type":"HABITATION",
    "name:eng_x_preferred":[
        "Sultanpurtanda"
    ],
    "wof:name":"Sultanpurtanda",
    "wof:placetype":"locality",
    "wof:population":62
},
  "geometry": {"coordinates":[77.541555,16.943616],"type":"Point"}
}