{
  "type": "Feature",
  "properties": {
    "iso:country":"IN",
    "ks:ks_name":"Kundiyapada",
    "ks:ks_pop":518,
    "ks:ks_type":"VILLAGE",
    "name:eng_x_preferred":[
        "Kundiyapada"
    ],
    "wof:name":"Kundiyapada",
    "wof:placetype":"locality",
    "wof:population":518
},
  "geometry": {"coordinates":[74.738226,23.262011],"type":"Point"}
}