{
  "type": "Feature",
  "properties": {
    "iso:country":"IN",
    "ks:ks_name":"Jangalapalli",
    "ks:ks_pop":142,
    "ks:ks_type":"HABITATION",
    "name:eng_x_preferred":[
        "Jangalapalli"
    ],
    "wof:name":"Jangalapalli",
    "wof:placetype":"locality",
    "wof:population":142
},
  "geometry": {"coordinates":[80.484567,17.739723],"type":"Point"}
}