{
  "type": "Feature",
  "properties": {
    "iso:country":"IN",
    "ks:ks_name":"Gattipalna",
    "ks:ks_pop":981,
    "ks:ks_type":"VILLAGE",
    "ks:ks_uagg_main":0,
    "name:eng_x_preferred":[
        "Gattipalna"
    ],
    "wof:name":"Gattipalna",
    "wof:placetype":"neighbourhood",
    "wof:population":981
},
  "geometry": {"coordinates":[81.633861,19.860158],"type":"Point"}
}