{
  "type": "Feature",
  "properties": {
    "iso:country":"IN",
    "ks:ks_name":"Pademata",
    "ks:ks_pop":205,
    "ks:ks_type":"HABITATION",
    "name:eng_x_preferred":[
        "Pademata"
    ],
    "wof:name":"Pademata",
    "wof:placetype":"locality",
    "wof:population":205
},
  "geometry": {"coordinates":[80.924611,19.430216],"type":"Point"}
}