{
  "type": "Feature",
  "properties": {
    "gn:admin1_code":"39",
    "gn:admin2_code":"58.0",
    "gn:asciiname":"Muktaganes",
    "gn:country_code":"IN",
    "gn:dem":2155,
    "gn:feature_class":"P",
    "gn:feature_code":"PPL",
    "gn:name":"M\u016bkt\u0101ganes",
    "gn:population":0,
    "gn:timezone":"Asia/Kolkata",
    "iso:country":"IN",
    "wof:name":"Muktaganes",
    "wof:placetype":"locality"
},
  "geometry": {"coordinates":[79.10039999999999,30.63868],"type":"Point"}
}