{
  "type": "Feature",
  "properties": {
    "gn:admin1_code":"24.0",
    "gn:admin2_code":"110",
    "gn:asciiname":"Chirota",
    "gn:country_code":"IN",
    "gn:dem":357,
    "gn:feature_class":"P",
    "gn:feature_code":"PPL",
    "gn:name":"Chirota",
    "gn:population":0,
    "gn:timezone":"Asia/Kolkata",
    "iso:country":"IN",
    "ks:ks_name":"Chirota",
    "ks:ks_pop":869,
    "ks:ks_type":"VILLAGE",
    "ks:ks_uagg_main":0,
    "name:eng_x_preferred":[
        "Chirota"
    ],
    "wof:name":"Chirota",
    "wof:placetype":"neighbourhood",
    "wof:population":869
},
  "geometry": {"coordinates":[75.57230199999999,26.797468],"type":"Point"}
}