{
  "type": "Feature",
  "properties": {
    "iso:country":"IN",
    "ks:ks_name":"Rompi",
    "ks:ks_pop":84,
    "ks:ks_type":"VILLAGE",
    "name:eng_x_preferred":[
        "Rompi"
    ],
    "wof:name":"Rompi",
    "wof:placetype":"locality",
    "wof:population":84
},
  "geometry": {"coordinates":[84.14597500000001,18.697959],"type":"Point"}
}