{
  "type": "Feature",
  "properties": {
    "iso:country":"IN",
    "ks:ks_name":"Basahat Sarb",
    "ks:ks_pop":264,
    "ks:ks_type":"HABITATION",
    "name:eng_x_preferred":[
        "Basahat Sarb"
    ],
    "wof:name":"Basahat Sarb",
    "wof:placetype":"locality",
    "wof:population":264
},
  "geometry": {"coordinates":[82.573571,22.67987],"type":"Point"}
}