{
  "type": "Feature",
  "properties": {
    "iso:country":"IN",
    "ks:ks_name":"Revasa",
    "ks:ks_pop":5267,
    "ks:ks_type":"VILLAGE",
    "name:eng_x_preferred":[
        "Revasa"
    ],
    "wof:name":"Revasa",
    "wof:placetype":"locality",
    "wof:population":5267
},
  "geometry": {"coordinates":[83.176886,25.272089],"type":"Point"}
}