{
  "type": "Feature",
  "properties": {
    "gn:admin1_code":"21.0",
    "gn:admin2_code":"389.0",
    "gn:asciiname":"Siyyali",
    "gn:country_code":"IN",
    "gn:dem":152,
    "gn:feature_class":"P",
    "gn:feature_code":"PPL",
    "gn:name":"Siyy\u0101li",
    "gn:population":0,
    "gn:timezone":"Asia/Kolkata",
    "iso:country":"IN",
    "wof:name":"Siyyali",
    "wof:placetype":"locality"
},
  "geometry": {"coordinates":[83.87127,18.92608],"type":"Point"}
}