{
  "type": "Feature",
  "properties": {
    "gn:admin1_code":"36.0",
    "gn:admin2_code":"181.0",
    "gn:asciiname":"Bhalohia",
    "gn:country_code":"IN",
    "gn:dem":117,
    "gn:feature_class":"P",
    "gn:feature_code":"PPL",
    "gn:name":"Bhalohia",
    "gn:population":0,
    "gn:timezone":"Asia/Kolkata",
    "iso:country":"IN",
    "wof:name":"Bhalohia",
    "wof:placetype":"neighbourhood"
},
  "geometry": {"coordinates":[81.95715,27.48573],"type":"Point"}
}