{
  "type": "Feature",
  "properties": {
    "gn:admin1_code":"12.0",
    "gn:asciiname":"Kalsian",
    "gn:country_code":"IN",
    "gn:dem":686,
    "gn:feature_class":"P",
    "gn:feature_code":"PPL",
    "gn:name":"Kalsi\u0101n",
    "gn:population":0,
    "gn:timezone":"Asia/Kolkata",
    "iso:country":"IN",
    "wof:name":"Kalsian",
    "wof:placetype":"locality"
},
  "geometry": {"coordinates":[74.1337,33.17897],"type":"Point"}
}