{
  "type": "Feature",
  "properties": {
    "iso:country":"IN",
    "ks:ks_name":"Moyar",
    "ks:ks_pop":600,
    "ks:ks_type":"HABITATION",
    "name:eng_x_preferred":[
        "Moyar"
    ],
    "wof:name":"Moyar",
    "wof:placetype":"locality",
    "wof:population":600
},
  "geometry": {"coordinates":[76.704457,11.597158],"type":"Point"}
}