{
  "type": "Feature",
  "properties": {
    "iso:country":"IN",
    "ks:ks_name":"Selda",
    "ks:ks_pop":481,
    "ks:ks_type":"VILLAGE",
    "name:eng_x_preferred":[
        "Selda"
    ],
    "wof:name":"Selda",
    "wof:placetype":"locality",
    "wof:population":481
},
  "geometry": {"coordinates":[85.46014099999999,22.967759],"type":"Point"}
}