{
  "type": "Feature",
  "properties": {
    "iso:country":"IN",
    "ks:ks_name":"Dali",
    "ks:ks_pop":976,
    "ks:ks_type":"HABITATION",
    "ks:ks_uagg_main":0,
    "name:eng_x_preferred":[
        "Dali"
    ],
    "wof:name":"Dali",
    "wof:placetype":"neighbourhood",
    "wof:population":976
},
  "geometry": {"coordinates":[77.04990599999999,8.879233],"type":"Point"}
}