{
  "type": "Feature",
  "properties": {
    "iso:country":"IN",
    "ks:ks_name":"Chandrapura",
    "ks:ks_type":"VILLAGE",
    "name:eng_x_preferred":[
        "Chandrapura"
    ],
    "wof:name":"Chandrapura",
    "wof:placetype":"locality"
},
  "geometry": {"coordinates":[77.83767899999999,13.035741],"type":"Point"}
}