{
  "type": "Feature",
  "properties": {
    "iso:country":"IN",
    "ks:ks_alt_nam":"GURMAHA",
    "ks:ks_name":"Gurmaha",
    "ks:ks_pop":1825,
    "ks:ks_type":"HABITATION",
    "name:eng_x_preferred":[
        "Gurmaha"
    ],
    "wof:name":"Gurmaha",
    "wof:placetype":"locality",
    "wof:population":1825
},
  "geometry": {"coordinates":[85.58226999999999,24.948489],"type":"Point"}
}