{
  "type": "Feature",
  "properties": {
    "iso:country":"IN",
    "ks:ks_name":"Kodwatanralias Bhitugarha",
    "ks:ks_pop":6283,
    "ks:ks_type":"HABITATION",
    "name:eng_x_preferred":[
        "Kodwatanralias Bhitugarha"
    ],
    "wof:name":"Kodwatanralias Bhitugarha",
    "wof:placetype":"locality",
    "wof:population":6283
},
  "geometry": {"coordinates":[85.77904599999999,23.840562],"type":"Point"}
}