{
  "type": "Feature",
  "properties": {
    "gn:admin1_code":"35",
    "gn:admin2_code":"447.0",
    "gn:asciiname":"Gargur",
    "gn:country_code":"IN",
    "gn:dem":627,
    "gn:feature_class":"P",
    "gn:feature_code":"PPL",
    "gn:name":"G\u0101rgur",
    "gn:population":0,
    "gn:timezone":"Asia/Kolkata",
    "iso:country":"IN",
    "name:ceb_x_preferred":[
        "Garg\u016br"
    ],
    "name:fas_x_preferred":[
        "\u06af\u0631\u06af\u0648\u0631"
    ],
    "name:msa_x_preferred":[
        "Gargur"
    ],
    "name:swe_x_preferred":[
        "Garg\u016br"
    ],
    "wof:name":"Gargur",
    "wof:placetype":"locality"
},
  "geometry": {"coordinates":[77.84007,21.48784],"type":"Point"}
}