{
  "type": "Feature",
  "properties": {
    "gn:admin1_code":"19.0",
    "gn:admin2_code":"563.0",
    "gn:asciiname":"Kodthali",
    "gn:country_code":"IN",
    "gn:dem":473,
    "gn:feature_class":"P",
    "gn:feature_code":"PPL",
    "gn:name":"Kodth\u0101li",
    "gn:population":0,
    "gn:timezone":"Asia/Kolkata",
    "iso:country":"IN",
    "ks:ks_name":"Kodthalli",
    "ks:ks_pop":84,
    "ks:ks_type":"VILLAGE",
    "name:eng_x_preferred":[
        "Kodthalli"
    ],
    "name:eng_x_variant":[
        "Kodthali"
    ],
    "wof:name":"Kodthalli",
    "wof:placetype":"locality",
    "wof:population":84
},
  "geometry": {"coordinates":[74.51185099999999,14.96391],"type":"Point"}
}