{
  "type": "Feature",
  "properties": {
    "gn:admin1_code":"36.0",
    "gn:admin2_code":"157.0",
    "gn:asciiname":"Behlampur",
    "gn:country_code":"IN",
    "gn:dem":128,
    "gn:feature_class":"P",
    "gn:feature_code":"PPL",
    "gn:name":"Behlampur",
    "gn:population":0,
    "gn:timezone":"Asia/Kolkata",
    "iso:country":"IN",
    "wof:name":"Behlampur",
    "wof:placetype":"locality"
},
  "geometry": {"coordinates":[80.75968,27.09432],"type":"Point"}
}