{
  "type": "Feature",
  "properties": {
    "iso:country":"IN",
    "ks:ks_name":"Dalkati",
    "ks:ks_pop":122,
    "ks:ks_type":"VILLAGE",
    "ks:ks_uagg_main":0,
    "name:eng_x_preferred":[
        "Dalkati"
    ],
    "wof:name":"Dalkati",
    "wof:placetype":"neighbourhood",
    "wof:population":122
},
  "geometry": {"coordinates":[87.21139599999999,22.234317],"type":"Point"}
}