{
  "type": "Feature",
  "properties": {
    "iso:country":"IN",
    "ks:ks_name":"Bhaliapada",
    "ks:ks_pop":251,
    "ks:ks_type":"VILLAGE",
    "name:eng_x_preferred":[
        "Bhaliapada"
    ],
    "wof:name":"Bhaliapada",
    "wof:placetype":"locality",
    "wof:population":251
},
  "geometry": {"coordinates":[84.24248299999999,19.443297],"type":"Point"}
}