{
  "type": "Feature",
  "properties": {
    "gn:admin1_code":"39.0",
    "gn:admin2_code":"64.0",
    "gn:asciiname":"Balsun",
    "gn:country_code":"IN",
    "gn:dem":1613,
    "gn:feature_class":"P",
    "gn:feature_code":"PPL",
    "gn:name":"Balsun",
    "gn:population":0,
    "gn:timezone":"Asia/Kolkata",
    "iso:country":"IN",
    "ks:ks_name":"Balsuna",
    "ks:ks_pop":168,
    "ks:ks_type":"VILLAGE",
    "name:eng_x_preferred":[
        "Balsuna"
    ],
    "name:eng_x_variant":[
        "Balsun"
    ],
    "wof:name":"Balsuna",
    "wof:placetype":"locality",
    "wof:population":168
},
  "geometry": {"coordinates":[79.78658799999999,29.558083],"type":"Point"}
}