{
  "type": "Feature",
  "properties": {
    "iso:country":"IN",
    "ks:ks_name":"Vangewadi",
    "ks:ks_pop":20,
    "ks:ks_type":"HABITATION",
    "name:eng_x_preferred":[
        "Vangewadi"
    ],
    "wof:name":"Vangewadi",
    "wof:placetype":"locality",
    "wof:population":20
},
  "geometry": {"coordinates":[73.257997,17.568033],"type":"Point"}
}