{
  "type": "Feature",
  "properties": {
    "iso:country":"IN",
    "ks:ks_alt_nam":"PURE HAIDER ALI",
    "ks:ks_name":"Pure Haider Ali",
    "ks:ks_pop":380,
    "ks:ks_type":"HABITATION",
    "ks:ks_uagg_main":0,
    "name:eng_x_preferred":[
        "Pure Haider Ali"
    ],
    "wof:name":"Pure Haider Ali",
    "wof:placetype":"neighbourhood",
    "wof:population":380
},
  "geometry": {"coordinates":[81.734103,26.504371],"type":"Point"}
}