{
  "type": "Feature",
  "properties": {
    "iso:country":"IN",
    "ks:ks_name":"Mansoorpur",
    "ks:ks_pop":0,
    "ks:ks_type":"VILLAGE",
    "name:eng_x_preferred":[
        "Mansoorpur"
    ],
    "wof:name":"Mansoorpur",
    "wof:placetype":"locality",
    "wof:population":0
},
  "geometry": {"coordinates":[78.628621,28.217399],"type":"Point"}
}