{
  "type": "Feature",
  "properties": {
    "gn:admin1_code":"23.0",
    "gn:admin2_code":"35.0",
    "gn:asciiname":"Bahjolpur",
    "gn:country_code":"IN",
    "gn:dem":240,
    "gn:feature_class":"P",
    "gn:feature_code":"PPL",
    "gn:name":"Bahjolpur",
    "gn:population":0,
    "gn:timezone":"Asia/Kolkata",
    "iso:country":"IN",
    "ks:ks_alt_nam":"Bahlolpur Khurd",
    "ks:ks_name":"Bahlolpur",
    "ks:ks_pop":601,
    "ks:ks_type":"VILLAGE",
    "name:eng_x_preferred":[
        "Bahlolpur"
    ],
    "name:eng_x_variant":[
        "Bahjolpur",
        "Bahlolpur Khurd"
    ],
    "wof:name":"Bahlolpur",
    "wof:placetype":"locality",
    "wof:population":601
},
  "geometry": {"coordinates":[75.068153,31.991885],"type":"Point"}
}