{
  "type": "Feature",
  "properties": {
    "iso:country":"IN",
    "ks:ks_alt_nam":"TAL.BORDER PRATAPPUR",
    "ks:ks_name":"Tal.border Pratappur",
    "ks:ks_pop":75,
    "ks:ks_type":"HABITATION",
    "name:eng_x_preferred":[
        "Tal.border Pratappur"
    ],
    "wof:name":"Tal.border Pratappur",
    "wof:placetype":"locality",
    "wof:population":75
},
  "geometry": {"coordinates":[75.066018,17.148591],"type":"Point"}
}