{
  "type": "Feature",
  "properties": {
    "iso:country":"IN",
    "ks:ks_name":"5 MSR",
    "ks:ks_pop":163,
    "ks:ks_type":"VILLAGE",
    "name:eng_x_preferred":[
        "5 MSR"
    ],
    "wof:name":"5 MSR",
    "wof:placetype":"locality",
    "wof:population":163
},
  "geometry": {"coordinates":[75.08244999999999,29.153282],"type":"Point"}
}