{
  "type": "Feature",
  "properties": {
    "gn:admin1_code":"19.0",
    "gn:admin2_code":"555.0",
    "gn:asciiname":"Anantpur",
    "gn:country_code":"IN",
    "gn:dem":580,
    "gn:feature_class":"P",
    "gn:feature_code":"PPL",
    "gn:name":"Anantpur",
    "gn:population":0,
    "gn:timezone":"Asia/Kolkata",
    "iso:country":"IN",
    "name:urd_x_preferred":[
        "\u0627\u0646\u0646\u062a \u067e\u0648\u0631"
    ],
    "wof:name":"Anantpur",
    "wof:placetype":"locality"
},
  "geometry": {"coordinates":[75.01458000000002,16.88896],"type":"Point"}
}