{
  "type": "Feature",
  "properties": {
    "iso:country":"IN",
    "ks:ks_alt_nam":"kathan khera",
    "ks:ks_name":"Kathan Khera",
    "ks:ks_pop":350,
    "ks:ks_type":"HABITATION",
    "ks:ks_uagg_main":0,
    "name:eng_x_preferred":[
        "Kathan Khera"
    ],
    "wof:name":"Kathan Khera",
    "wof:placetype":"neighbourhood",
    "wof:population":350
},
  "geometry": {"coordinates":[80.503598,26.599953],"type":"Point"}
}