{
  "type": "Feature",
  "properties": {
    "iso:country":"IN",
    "ks:ks_name":"Konda",
    "ks:ks_pop":43,
    "ks:ks_type":"VILLAGE",
    "name:eng_x_preferred":[
        "Konda"
    ],
    "wof:name":"Konda",
    "wof:placetype":"locality",
    "wof:population":43
},
  "geometry": {"coordinates":[74.55772,15.303116],"type":"Point"}
}