{
  "type": "Feature",
  "properties": {
    "iso:country":"IN",
    "ks:ks_name":"Tola Majhgain",
    "ks:ks_pop":186,
    "ks:ks_type":"VILLAGE",
    "name:eng_x_preferred":[
        "Tola Majhgain"
    ],
    "wof:name":"Tola Majhgain",
    "wof:placetype":"locality",
    "wof:population":186
},
  "geometry": {"coordinates":[86.85423299999999,24.578861],"type":"Point"}
}