{
  "type": "Feature",
  "properties": {
    "iso:country":"IN",
    "ks:ks_name":"Sotran",
    "ks:ks_type":"VILLAGE",
    "name:eng_x_preferred":[
        "Sotran"
    ],
    "wof:name":"Sotran",
    "wof:placetype":"neighbourhood"
},
  "geometry": {"coordinates":[75.98491799999999,31.177681],"type":"Point"}
}