{
  "type": "Feature",
  "properties": {
    "iso:country":"IN",
    "ks:ks_name":"Gobindpur",
    "ks:ks_pop":103,
    "ks:ks_type":"VILLAGE",
    "name:eng_x_preferred":[
        "Gobindpur"
    ],
    "wof:name":"Gobindpur",
    "wof:placetype":"locality",
    "wof:population":103
},
  "geometry": {"coordinates":[85.169883,22.384347],"type":"Point"}
}