{
  "type": "Feature",
  "properties": {
    "iso:country":"IN",
    "ks:ks_name":"Raithal",
    "ks:ks_pop":904,
    "ks:ks_type":"VILLAGE",
    "name:eng_x_preferred":[
        "Raithal"
    ],
    "wof:name":"Raithal",
    "wof:placetype":"locality",
    "wof:population":904
},
  "geometry": {"coordinates":[78.605752,30.81739],"type":"Point"}
}