{
  "type": "Feature",
  "properties": {
    "gn:admin1_code":"35.0",
    "gn:admin2_code":"450.0",
    "gn:asciiname":"Dhauli",
    "gn:country_code":"IN",
    "gn:dem":430,
    "gn:feature_class":"P",
    "gn:feature_code":"PPL",
    "gn:name":"Dhauli",
    "gn:population":0,
    "gn:timezone":"Asia/Kolkata",
    "iso:country":"IN",
    "name:cat_x_preferred":[
        "Dhauli"
    ],
    "name:ceb_x_preferred":[
        "Dhauli"
    ],
    "name:deu_x_preferred":[
        "Dhauli"
    ],
    "name:hin_x_preferred":[
        "\u0927\u094c\u0932\u0940 \u0917\u093f\u0930\u093f"
    ],
    "name:mar_x_preferred":[
        "\u0927\u094c\u0932\u0940 \u092a\u094d\u0930\u0938\u094d\u0924\u0930\u0932\u0947\u0916"
    ],
    "name:ori_x_preferred":[
        "\u0b27\u0b09\u0b33\u0b3f"
    ],
    "name:pan_x_preferred":[
        "\u0a27\u0a4c\u0a32\u0a40"
    ],
    "name:pol_x_preferred":[
        "Dhauli"
    ],
    "name:por_x_preferred":[
        "Dauli"
    ],
    "name:sin_x_preferred":[
        "\u0db0\u0dde\u0dbd\u0dd2"
    ],
    "name:tam_x_preferred":[
        "\u0ba4\u0bcc\u0bb2\u0bbf"
    ],
    "name:tel_x_preferred":[
        "\u0c27\u0c4c\u0c33\u0c3f\u0c17\u0c3f\u0c30\u0c3f"
    ],
    "wof:name":"Dhauli",
    "wof:placetype":"locality"
},
  "geometry": {"coordinates":[80.27970999999999,23.58427],"type":"Point"}
}