{
  "type": "Feature",
  "properties": {
    "gn:admin1_code":"24.0",
    "gn:admin2_code":"126.0",
    "gn:asciiname":"Ghosundi",
    "gn:country_code":"IN",
    "gn:dem":405,
    "gn:feature_class":"P",
    "gn:feature_code":"PPL",
    "gn:name":"Ghosundi",
    "gn:population":0,
    "gn:timezone":"Asia/Kolkata",
    "iso:country":"IN",
    "ks:ks_name":"Ghosunda",
    "ks:ks_pop":4778,
    "ks:ks_type":"VILLAGE",
    "ks:ks_uagg_main":0,
    "name:eng_x_preferred":[
        "Ghosunda"
    ],
    "wof:name":"Ghosunda",
    "wof:placetype":"neighbourhood",
    "wof:population":4778
},
  "geometry": {"coordinates":[74.76142299999999,25.010602],"type":"Point"}
}