{
  "type": "Feature",
  "properties": {
    "iso:country":"IN",
    "ks:ks_name":"Kukurakhaiti",
    "ks:ks_pop":534,
    "ks:ks_type":"VILLAGE",
    "name:eng_x_preferred":[
        "Kukurakhaiti"
    ],
    "wof:name":"Kukurakhaiti",
    "wof:placetype":"locality",
    "wof:population":534
},
  "geometry": {"coordinates":[92.296868,26.77884],"type":"Point"}
}