{
  "type": "Feature",
  "properties": {
    "gn:admin1_code":"36",
    "gn:admin2_code":"175.0",
    "gn:asciiname":"Bhawapur",
    "gn:country_code":"IN",
    "gn:dem":94,
    "gn:feature_class":"P",
    "gn:feature_code":"PPL",
    "gn:name":"Bh\u0101w\u0101pur",
    "gn:population":0,
    "gn:timezone":"Asia/Kolkata",
    "iso:country":"IN",
    "ks:ks_alt_nam":"Bh\u0101w\u0101pur",
    "ks:ks_name":"Bhawapur",
    "ks:ks_type":"VILLAGE",
    "ks:ks_uagg_main":0,
    "name:eng_x_preferred":[
        "Bhawapur"
    ],
    "name:eng_x_variant":[
        "Bh\u0101w\u0101pur"
    ],
    "wof:name":"Bhawapur",
    "wof:placetype":"neighbourhood"
},
  "geometry": {"coordinates":[82.252826,25.378685],"type":"Point"}
}