{
  "type": "Feature",
  "properties": {
    "iso:country":"IN",
    "ks:ks_name":"Santak Lengibor",
    "ks:ks_pop":217,
    "ks:ks_type":"HABITATION",
    "name:eng_x_preferred":[
        "Santak Lengibor"
    ],
    "wof:name":"Santak Lengibor",
    "wof:placetype":"locality",
    "wof:population":217
},
  "geometry": {"coordinates":[94.850617,26.890423],"type":"Point"}
}