{
  "type": "Feature",
  "properties": {
    "iso:country":"IN",
    "ks:ks_name":"Baba Kuti",
    "ks:ks_pop":4,
    "ks:ks_type":"HABITATION",
    "name:eng_x_preferred":[
        "Baba Kuti"
    ],
    "wof:name":"Baba Kuti",
    "wof:placetype":"locality",
    "wof:population":4
},
  "geometry": {"coordinates":[82.360598,27.320893],"type":"Point"}
}