{
  "type": "Feature",
  "properties": {
    "iso:country":"IN",
    "ks:ks_name":"Kandagadha",
    "ks:ks_pop":11,
    "ks:ks_type":"VILLAGE",
    "name:eng_x_preferred":[
        "Kandagadha"
    ],
    "wof:name":"Kandagadha",
    "wof:placetype":"locality",
    "wof:population":11
},
  "geometry": {"coordinates":[84.815378,22.305287],"type":"Point"}
}