{
  "type": "Feature",
  "properties": {
    "iso:country":"IN",
    "ks:ks_name":"Vodenabailu",
    "ks:ks_pop":144,
    "ks:ks_type":"HABITATION",
    "name:eng_x_preferred":[
        "Vodenabailu"
    ],
    "wof:name":"Vodenabailu",
    "wof:placetype":"locality",
    "wof:population":144
},
  "geometry": {"coordinates":[74.758938,13.681887],"type":"Point"}
}