{
  "type": "Feature",
  "properties": {
    "iso:country":"IN",
    "ks:ks_name":"Pandit Vasti",
    "ks:ks_pop":211,
    "ks:ks_type":"HABITATION",
    "name:eng_x_preferred":[
        "Pandit Vasti"
    ],
    "wof:name":"Pandit Vasti",
    "wof:placetype":"locality",
    "wof:population":211
},
  "geometry": {"coordinates":[75.034417,19.463314],"type":"Point"}
}