{
  "type": "Feature",
  "properties": {
    "iso:country":"IN",
    "ks:ks_name":"Utrasu",
    "ks:ks_pop":178,
    "ks:ks_type":"VILLAGE",
    "name:eng_x_preferred":[
        "Utrasu"
    ],
    "wof:name":"Utrasu",
    "wof:placetype":"locality",
    "wof:population":178
},
  "geometry": {"coordinates":[78.643872,30.191234],"type":"Point"}
}