{
  "type": "Feature",
  "properties": {
    "iso:country":"IN",
    "ks:ks_name":"Kathula Thanda",
    "ks:ks_pop":79,
    "ks:ks_type":"HABITATION",
    "name:eng_x_preferred":[
        "Kathula Thanda"
    ],
    "wof:name":"Kathula Thanda",
    "wof:placetype":"locality",
    "wof:population":79
},
  "geometry": {"coordinates":[79.840349,17.481075],"type":"Point"}
}