{
  "type": "Feature",
  "properties": {
    "iso:country":"IN",
    "ks:ks_name":"Pemipura",
    "ks:ks_pop":143,
    "ks:ks_type":"HABITATION",
    "name:eng_x_preferred":[
        "Pemipura"
    ],
    "wof:name":"Pemipura",
    "wof:placetype":"locality",
    "wof:population":143
},
  "geometry": {"coordinates":[75.287846,22.569136],"type":"Point"}
}