{
  "type": "Feature",
  "properties": {
    "iso:country":"IN",
    "ks:ks_name":"Zadamali",
    "ks:ks_pop":584,
    "ks:ks_type":"HABITATION",
    "name:eng_x_preferred":[
        "Zadamali"
    ],
    "wof:name":"Zadamali",
    "wof:placetype":"locality",
    "wof:population":584
},
  "geometry": {"coordinates":[74.71986,22.49218],"type":"Point"}
}