{
  "type": "Feature",
  "properties": {
    "gn:admin1_code":"11",
    "gn:admin2_code":"33.0",
    "gn:asciiname":"Ichha Ser",
    "gn:country_code":"IN",
    "gn:dem":1837,
    "gn:feature_class":"P",
    "gn:feature_code":"PPL",
    "gn:name":"Ichha Ser",
    "gn:population":0,
    "gn:timezone":"Asia/Kolkata",
    "iso:country":"IN",
    "wof:name":"Ichha Ser",
    "wof:placetype":"locality"
},
  "geometry": {"coordinates":[77.09761,31.13508],"type":"Point"}
}