{
  "type": "Feature",
  "properties": {
    "iso:country":"IN",
    "ks:ks_name":"Putagadia",
    "ks:ks_pop":818,
    "ks:ks_type":"VILLAGE",
    "ks:ks_uagg_main":0,
    "name:eng_x_preferred":[
        "Putagadia"
    ],
    "wof:name":"Putagadia",
    "wof:placetype":"neighbourhood",
    "wof:population":818
},
  "geometry": {"coordinates":[84.88177399999999,20.950877],"type":"Point"}
}