{
  "type": "Feature",
  "properties": {
    "iso:country":"IN",
    "ks:ks_name":"Ambagadia",
    "ks:ks_pop":120,
    "ks:ks_type":"HABITATION",
    "name:eng_x_preferred":[
        "Ambagadia"
    ],
    "wof:name":"Ambagadia",
    "wof:placetype":"locality",
    "wof:population":120
},
  "geometry": {"coordinates":[86.31781599999999,21.001991],"type":"Point"}
}