{
  "type": "Feature",
  "properties": {
    "gn:admin1_code":"37",
    "gn:admin2_code":"409.0",
    "gn:asciiname":"Chuhka",
    "gn:country_code":"IN",
    "gn:dem":283,
    "gn:feature_class":"P",
    "gn:feature_code":"PPL",
    "gn:name":"Chuhka",
    "gn:population":0,
    "gn:timezone":"Asia/Kolkata",
    "iso:country":"IN",
    "wof:name":"Chuhka",
    "wof:placetype":"locality"
},
  "geometry": {"coordinates":[81.37366999999998,21.71146],"type":"Point"}
}