{
  "type": "Feature",
  "properties": {
    "gn:admin1_code":"37.0",
    "gn:admin2_code":"416",
    "gn:asciiname":"Burgam",
    "gn:country_code":"IN",
    "gn:dem":546,
    "gn:feature_class":"P",
    "gn:feature_code":"PPL",
    "gn:name":"B\u016brgam",
    "gn:population":0,
    "gn:timezone":"Asia/Kolkata",
    "iso:country":"IN",
    "ks:ks_name":"Burgum",
    "ks:ks_pop":355,
    "ks:ks_type":"VILLAGE",
    "name:eng_x_preferred":[
        "Burgum"
    ],
    "name:eng_x_variant":[
        "Burgam"
    ],
    "name:und_x_variant":[
        "Burgum",
        "B\u016brgam"
    ],
    "wof:name":"Burgum",
    "wof:placetype":"locality",
    "wof:population":355
},
  "geometry": {"coordinates":[81.40061300000001,18.506092],"type":"Point"}
}