{
  "type": "Feature",
  "properties": {
    "gn:admin1_code":"37.0",
    "gn:admin2_code":"416",
    "gn:asciiname":"Burgam",
    "gn:country_code":"IN",
    "gn:dem":546,
    "gn:feature_class":"P",
    "gn:feature_code":"PPL",
    "gn:name":"B\u016brgam",
    "gn:population":0,
    "gn:timezone":"Asia/Kolkata",
    "iso:country":"IN",
    "name:und_x_variant":[
        "Burgum",
        "B\u016brgam"
    ],
    "wof:name":"Burgam",
    "wof:placetype":"locality"
},
  "geometry": {"coordinates":[81.39981,18.50457],"type":"Point"}
}