{
  "type": "Feature",
  "properties": {
    "gn:admin1_code":"21",
    "gn:admin2_code":"384.0",
    "gn:asciiname":"Mahidharpur",
    "gn:country_code":"IN",
    "gn:dem":112,
    "gn:feature_class":"P",
    "gn:feature_code":"PPL",
    "gn:name":"Mahidharpur",
    "gn:population":0,
    "gn:timezone":"Asia/Kolkata",
    "iso:country":"IN",
    "name:und_x_variant":[
        "Maidharapur"
    ],
    "wof:name":"Mahidharpur",
    "wof:placetype":"locality"
},
  "geometry": {"coordinates":[85.18095,20.69627],"type":"Point"}
}