{
  "type": "Feature",
  "properties": {
    "iso:country":"IN",
    "ks:ks_name":"Waghrat",
    "ks:ks_pop":1100,
    "ks:ks_type":"VILLAGE",
    "name:eng_x_preferred":[
        "Waghrat"
    ],
    "wof:name":"Waghrat",
    "wof:placetype":"locality",
    "wof:population":1100
},
  "geometry": {"coordinates":[73.431535,16.851599],"type":"Point"}
}