{
  "type": "Feature",
  "properties": {
    "iso:country":"IN",
    "ks:ks_name":"Dombale Chware Zagade",
    "ks:ks_pop":250,
    "ks:ks_type":"HABITATION",
    "name:eng_x_preferred":[
        "Dombale Chware Zagade"
    ],
    "wof:name":"Dombale Chware Zagade",
    "wof:placetype":"locality",
    "wof:population":250
},
  "geometry": {"coordinates":[74.84999999999999,18.125],"type":"Point"}
}