{
  "type": "Feature",
  "properties": {
    "iso:country":"IN",
    "ks:ks_name":"Uluvebailu",
    "ks:ks_pop":53,
    "ks:ks_type":"HABITATION",
    "name:eng_x_preferred":[
        "Uluvebailu"
    ],
    "wof:name":"Uluvebailu",
    "wof:placetype":"locality",
    "wof:population":53
},
  "geometry": {"coordinates":[75.267326,13.444297],"type":"Point"}
}