{
  "type": "Feature",
  "properties": {
    "iso:country":"IN",
    "ks:ks_name":"Dudyewadi",
    "ks:ks_pop":255,
    "ks:ks_type":"HABITATION",
    "name:eng_x_preferred":[
        "Dudyewadi"
    ],
    "wof:name":"Dudyewadi",
    "wof:placetype":"locality",
    "wof:population":255
},
  "geometry": {"coordinates":[73.576836,16.827511],"type":"Point"}
}