{
  "type": "Feature",
  "properties": {
    "gn:admin1_code":"11",
    "gn:admin2_code":"23.0",
    "gn:asciiname":"Tretana",
    "gn:country_code":"IN",
    "gn:dem":2964,
    "gn:feature_class":"P",
    "gn:feature_code":"PPL",
    "gn:name":"Tret\u0101na",
    "gn:population":0,
    "gn:timezone":"Asia/Kolkata",
    "iso:country":"IN",
    "wof:name":"Tretana",
    "wof:placetype":"locality"
},
  "geometry": {"coordinates":[76.2272,32.69637],"type":"Point"}
}