{
  "type": "Feature",
  "properties": {
    "iso:country":"IN",
    "ks:ks_name":"Thuthivalasai",
    "ks:ks_pop":660,
    "ks:ks_type":"HABITATION",
    "ks:ks_uagg_main":0,
    "name:eng_x_preferred":[
        "Thuthivalasai"
    ],
    "wof:name":"Thuthivalasai",
    "wof:placetype":"neighbourhood",
    "wof:population":660
},
  "geometry": {"coordinates":[79.01178299999999,9.315453],"type":"Point"}
}