{
  "type": "Feature",
  "properties": {
    "gn:admin1_code":"36.0",
    "gn:admin2_code":"183.0",
    "gn:asciiname":"Pura Manoga",
    "gn:country_code":"IN",
    "gn:dem":108,
    "gn:feature_class":"P",
    "gn:feature_code":"PPL",
    "gn:name":"Pura Manoga",
    "gn:population":0,
    "gn:timezone":"Asia/Kolkata",
    "iso:country":"IN",
    "ks:ks_name":"Purey Manoga",
    "ks:ks_pop":154,
    "ks:ks_type":"VILLAGE",
    "ks:ks_uagg_main":0,
    "name:eng_x_preferred":[
        "Purey Manoga"
    ],
    "wof:name":"Purey Manoga",
    "wof:placetype":"neighbourhood",
    "wof:population":154
},
  "geometry": {"coordinates":[82.06681500000001,27.252312],"type":"Point"}
}