{
  "type": "Feature",
  "properties": {
    "gn:admin1_code":"35",
    "gn:admin2_code":"423.0",
    "gn:asciiname":"Chandupahar",
    "gn:country_code":"IN",
    "gn:dem":344,
    "gn:feature_class":"P",
    "gn:feature_code":"PPL",
    "gn:name":"Chand\u016bpah\u0101r",
    "gn:population":0,
    "gn:timezone":"Asia/Kolkata",
    "iso:country":"IN",
    "ks:ks_name":"Chandu Pahadi",
    "ks:ks_pop":755,
    "ks:ks_type":"VILLAGE",
    "name:eng_x_preferred":[
        "Chandu Pahadi"
    ],
    "name:eng_x_variant":[
        "Chandupahar"
    ],
    "wof:name":"Chandu Pahadi",
    "wof:placetype":"locality",
    "wof:population":755
},
  "geometry": {"coordinates":[78.247778,25.26731],"type":"Point"}
}