{
  "type": "Feature",
  "properties": {
    "gn:admin1_code":"21",
    "gn:admin2_code":"399.0",
    "gn:asciiname":"Danniguda",
    "gn:country_code":"IN",
    "gn:dem":262,
    "gn:feature_class":"P",
    "gn:feature_code":"PPL",
    "gn:name":"Dannig\u016bda",
    "gn:population":0,
    "gn:timezone":"Asia/Kolkata",
    "iso:country":"IN",
    "ks:ks_name":"Daniguda",
    "ks:ks_pop":238,
    "ks:ks_type":"VILLAGE",
    "name:eng_x_preferred":[
        "Daniguda"
    ],
    "name:eng_x_variant":[
        "Danniguda"
    ],
    "wof:name":"Daniguda",
    "wof:placetype":"locality",
    "wof:population":238
},
  "geometry": {"coordinates":[82.086547,18.518324],"type":"Point"}
}