{
  "type": "Feature",
  "properties": {
    "iso:country":"IN",
    "ks:ks_alt_nam":"puttamakkul",
    "ks:ks_name":"Puttamakkul",
    "ks:ks_pop":886,
    "ks:ks_type":"HABITATION",
    "name:eng_x_preferred":[
        "Puttamakkul"
    ],
    "wof:name":"Puttamakkul",
    "wof:placetype":"locality",
    "wof:population":886
},
  "geometry": {"coordinates":[75.64691999999999,11.571984],"type":"Point"}
}