{
  "type": "Feature",
  "properties": {
    "iso:country":"IN",
    "ks:ks_name":"Talabelgaon",
    "ks:ks_pop":220,
    "ks:ks_type":"VILLAGE",
    "name:eng_x_preferred":[
        "Talabelgaon"
    ],
    "wof:name":"Talabelgaon",
    "wof:placetype":"locality",
    "wof:population":220
},
  "geometry": {"coordinates":[83.196944,19.850197],"type":"Point"}
}