{
  "type": "Feature",
  "properties": {
    "gn:admin1_code":"21.0",
    "gn:admin2_code":"387",
    "gn:asciiname":"Gop",
    "gn:country_code":"IN",
    "gn:dem":13,
    "gn:feature_class":"P",
    "gn:feature_code":"PPL",
    "gn:name":"Gop",
    "gn:population":0,
    "gn:timezone":"Asia/Kolkata",
    "iso:country":"IN",
    "name:und_x_variant":[
        "Gope",
        "Gop"
    ],
    "wof:name":"Gop",
    "wof:placetype":"locality"
},
  "geometry": {"coordinates":[86.02561999999998,19.98543],"type":"Point"}
}