{
  "type": "Feature",
  "properties": {
    "iso:country":"IN",
    "ks:ks_name":"Hoskoppa",
    "ks:ks_pop":87,
    "ks:ks_type":"HABITATION",
    "name:eng_x_preferred":[
        "Hoskoppa"
    ],
    "wof:name":"Hoskoppa",
    "wof:placetype":"locality",
    "wof:population":87
},
  "geometry": {"coordinates":[74.836001,14.502836],"type":"Point"}
}