{
  "type": "Feature",
  "properties": {
    "iso:country":"IN",
    "ks:ks_name":"Chakkamina",
    "ks:ks_pop":2645,
    "ks:ks_type":"VILLAGE",
    "name:eng_x_preferred":[
        "Chakkamina"
    ],
    "wof:name":"Chakkamina",
    "wof:placetype":"locality",
    "wof:population":2645
},
  "geometry": {"coordinates":[87.92728,22.275],"type":"Point"}
}