{
  "type": "Feature",
  "properties": {
    "iso:country":"IN",
    "ks:ks_name":"Artatranapur",
    "ks:ks_pop":293,
    "ks:ks_type":"VILLAGE",
    "name:eng_x_preferred":[
        "Artatranapur"
    ],
    "wof:name":"Artatranapur",
    "wof:placetype":"locality",
    "wof:population":293
},
  "geometry": {"coordinates":[82.81137,20.196337],"type":"Point"}
}