{
  "type": "Feature",
  "properties": {
    "iso:country":"IN",
    "ks:ks_name":"Kailanpur",
    "ks:ks_pop":447,
    "ks:ks_type":"VILLAGE",
    "ks:ks_uagg_main":0,
    "name:eng_x_preferred":[
        "Kailanpur"
    ],
    "wof:name":"Kailanpur",
    "wof:placetype":"neighbourhood",
    "wof:population":447
},
  "geometry": {"coordinates":[79.067609,27.220454],"type":"Point"}
}