{
  "type": "Feature",
  "properties": {
    "iso:country":"IN",
    "ks:ks_name":"Bakrikuchi",
    "ks:ks_pop":395,
    "ks:ks_type":"HABITATION",
    "name:eng_x_preferred":[
        "Bakrikuchi"
    ],
    "wof:name":"Bakrikuchi",
    "wof:placetype":"locality",
    "wof:population":395
},
  "geometry": {"coordinates":[91.325873,26.284477],"type":"Point"}
}