{
  "type": "Feature",
  "properties": {
    "iso:country":"IN",
    "ks:ks_name":"Janatha Colony",
    "ks:ks_pop":55,
    "ks:ks_type":"HABITATION",
    "name:eng_x_preferred":[
        "Janatha Colony"
    ],
    "wof:name":"Janatha Colony",
    "wof:placetype":"locality",
    "wof:population":55
},
  "geometry": {"coordinates":[74.552176,14.52186],"type":"Point"}
}