{
  "type": "Feature",
  "properties": {
    "iso:country":"IN",
    "ks:ks_name":"Kumbharaguda",
    "ks:ks_pop":572,
    "ks:ks_type":"HABITATION",
    "name:eng_x_preferred":[
        "Kumbharaguda"
    ],
    "wof:name":"Kumbharaguda",
    "wof:placetype":"locality",
    "wof:population":572
},
  "geometry": {"coordinates":[82.612233,19.146692],"type":"Point"}
}