{
  "type": "Feature",
  "properties": {
    "iso:country":"IN",
    "ks:ks_name":"Khijirpur",
    "ks:ks_pop":199,
    "ks:ks_type":"VILLAGE",
    "name:eng_x_preferred":[
        "Khijirpur"
    ],
    "wof:name":"Khijirpur",
    "wof:placetype":"locality",
    "wof:population":199
},
  "geometry": {"coordinates":[83.31623999999999,25.251396],"type":"Point"}
}