{
  "type": "Feature",
  "properties": {
    "gn:country":"IN",
    "gn:fcode":"PPL",
    "gn:pop":6462,
    "iso:country":"IN",
    "name:dut_x_preferred":[
        "Waghai"
    ],
    "name:eng_x_preferred":[
        "Waghai"
    ],
    "name:guj_x_preferred":[
        "\u0ab5\u0a98\u0a87"
    ],
    "name:mar_x_preferred":[
        "\u0935\u0918\u0908"
    ],
    "name:swe_x_preferred":[
        "Wagh\u0101i"
    ],
    "name:unk_x_variant":[
        "Wagh\u0101i"
    ],
    "qs:name":"Waghai",
    "qs:name_adm0":"India",
    "qs:name_adm1":"Gujarat",
    "qs:photos":112,
    "qs:photos_1k":23,
    "qs:photos_9k":1,
    "qs:photos_9r":3,
    "qs:photos_all":112,
    "qs:photos_sr":3,
    "qs:placetype":"Town",
    "qs:pop_sr":"5",
    "wd:wordcount":522,
    "wof:name":"Waghai",
    "wof:placetype":"locality",
    "wof:population":6462
},
  "geometry": {"coordinates":[73.50073999999999,20.77048],"type":"Point"}
}