{
  "type": "Feature",
  "properties": {
    "iso:country":"IN",
    "ks:ks_name":"Kallani",
    "ks:ks_pop":466,
    "ks:ks_type":"HABITATION",
    "name:eng_x_preferred":[
        "Kallani"
    ],
    "wof:name":"Kallani",
    "wof:placetype":"locality",
    "wof:population":466
},
  "geometry": {"coordinates":[78.71509399999999,9.663842],"type":"Point"}
}