{
  "type": "Feature",
  "properties": {
    "gn:admin1_code":"36",
    "gn:admin2_code":"179.0",
    "gn:asciiname":"Matha",
    "gn:country_code":"IN",
    "gn:dem":101,
    "gn:feature_class":"P",
    "gn:feature_code":"PPL",
    "gn:name":"Matha",
    "gn:population":0,
    "gn:timezone":"Asia/Kolkata",
    "iso:country":"IN",
    "name:pol_x_preferred":[
        "Matha"
    ],
    "name:rus_x_preferred":[
        "\u041c\u0430\u0442\u0445\u0430"
    ],
    "name:sqi_x_preferred":[
        "Matha"
    ],
    "name:tam_x_preferred":[
        "\u0bae\u0b9f\u0bae\u0bcd"
    ],
    "name:ukr_x_preferred":[
        "\u041c\u0430\u0442\u0445\u0430"
    ],
    "wof:name":"Matha",
    "wof:placetype":"locality"
},
  "geometry": {"coordinates":[82.05601,26.31151],"type":"Point"}
}