{
  "type": "Feature",
  "properties": {
    "gn:admin1_code":"35",
    "gn:admin2_code":"428.0",
    "gn:asciiname":"Gorkha",
    "gn:country_code":"IN",
    "gn:dem":368,
    "gn:feature_class":"P",
    "gn:feature_code":"PPL",
    "gn:name":"Gorkha",
    "gn:population":0,
    "gn:timezone":"Asia/Kolkata",
    "iso:country":"IN",
    "ks:ks_name":"Gorkha",
    "ks:ks_pop":688,
    "ks:ks_type":"VILLAGE",
    "name:eng_x_preferred":[
        "Gorkha"
    ],
    "wof:name":"Gorkha",
    "wof:placetype":"locality",
    "wof:population":688
},
  "geometry": {"coordinates":[79.46041200000001,23.520498],"type":"Point"}
}