{
  "type": "Feature",
  "properties": {
    "gn:admin1_code":"36",
    "gn:admin2_code":"147.0",
    "gn:asciiname":"Nagla Nanda",
    "gn:country_code":"IN",
    "gn:dem":153,
    "gn:feature_class":"P",
    "gn:feature_code":"PPL",
    "gn:name":"Nagla Nanda",
    "gn:population":0,
    "gn:timezone":"Asia/Kolkata",
    "iso:country":"IN",
    "ks:ks_name":"Nagla Nanda",
    "ks:ks_pop":964,
    "ks:ks_type":"HABITATION",
    "name:eng_x_preferred":[
        "Nagla Nanda"
    ],
    "wof:name":"Nagla Nanda",
    "wof:placetype":"locality",
    "wof:population":964
},
  "geometry": {"coordinates":[78.283083,27.102734],"type":"Point"}
}