{
  "type": "Feature",
  "properties": {
    "iso:country":"IN",
    "ks:ks_name":"Bandhaguda",
    "ks:ks_pop":111,
    "ks:ks_type":"VILLAGE",
    "name:eng_x_preferred":[
        "Bandhaguda"
    ],
    "wof:name":"Bandhaguda",
    "wof:placetype":"locality",
    "wof:population":111
},
  "geometry": {"coordinates":[82.78292,18.457146],"type":"Point"}
}