{
  "type": "Feature",
  "properties": {
    "gn:admin1_code":"34.0",
    "gn:admin2_code":"212.0",
    "gn:asciiname":"Lalganj",
    "gn:country_code":"IN",
    "gn:dem":29,
    "gn:feature_class":"P",
    "gn:feature_code":"PPL",
    "gn:name":"L\u0101lganj",
    "gn:population":0,
    "gn:timezone":"Asia/Kolkata",
    "iso:country":"IN",
    "name:pol_x_preferred":[
        "Lalganj"
    ],
    "wof:name":"Lalganj",
    "wof:placetype":"neighbourhood"
},
  "geometry": {"coordinates":[87.75158,25.43296],"type":"Point"}
}