{
  "type": "Feature",
  "properties": {
    "gn:admin1_code":"38",
    "gn:admin2_code":"346.0",
    "gn:asciiname":"Dhorhipanitola",
    "gn:country_code":"IN",
    "gn:dem":452,
    "gn:feature_class":"P",
    "gn:feature_code":"PPL",
    "gn:name":"Dhorh\u012bp\u0101n\u012btola",
    "gn:population":0,
    "gn:timezone":"Asia/Kolkata",
    "iso:country":"IN",
    "wof:name":"Dhorhipanitola",
    "wof:placetype":"locality"
},
  "geometry": {"coordinates":[83.86091999999999,23.70312],"type":"Point"}
}