{
  "type": "Feature",
  "properties": {
    "iso:country":"IN",
    "ks:ks_name":"Dharapali",
    "ks:ks_pop":0,
    "ks:ks_type":"VILLAGE",
    "name:eng_x_preferred":[
        "Dharapali"
    ],
    "wof:name":"Dharapali",
    "wof:placetype":"locality",
    "wof:population":0
},
  "geometry": {"coordinates":[83.783629,21.038939],"type":"Point"}
}