{
  "type": "Feature",
  "properties": {
    "iso:country":"IN",
    "ks:ks_alt_nam":"MADHYA PARA",
    "ks:ks_name":"Madhya Para",
    "ks:ks_pop":422,
    "ks:ks_type":"HABITATION",
    "name:eng_x_preferred":[
        "Madhya Para"
    ],
    "wof:name":"Madhya Para",
    "wof:placetype":"locality",
    "wof:population":422
},
  "geometry": {"coordinates":[91.38602,23.47643],"type":"Point"}
}