{
  "type": "Feature",
  "properties": {
    "gn:admin1_code":"36",
    "gn:admin2_code":"146.0",
    "gn:asciiname":"Malhan ka Pura",
    "gn:country_code":"IN",
    "gn:dem":164,
    "gn:feature_class":"P",
    "gn:feature_code":"PPL",
    "gn:name":"Malhan ka Pura",
    "gn:population":0,
    "gn:timezone":"Asia/Kolkata",
    "iso:country":"IN",
    "wof:name":"Malhan ka Pura",
    "wof:placetype":"neighbourhood"
},
  "geometry": {"coordinates":[78.42614,26.9057],"type":"Point"}
}