{
  "type": "Feature",
  "properties": {
    "iso:country":"IN",
    "ks:ks_name":"Yaramuddenahalli",
    "ks:ks_pop":7,
    "ks:ks_type":"VILLAGE",
    "name:eng_x_preferred":[
        "Yaramuddenahalli"
    ],
    "wof:name":"Yaramuddenahalli",
    "wof:placetype":"locality",
    "wof:population":7
},
  "geometry": {"coordinates":[77.43442899999999,13.457212],"type":"Point"}
}