{
  "type": "Feature",
  "properties": {
    "gn:admin1_code":"19.0",
    "gn:admin2_code":"561.0",
    "gn:asciiname":"Narayanpur",
    "gn:country_code":"IN",
    "gn:dem":587,
    "gn:feature_class":"P",
    "gn:feature_code":"PPL",
    "gn:name":"N\u0101r\u0101yanpur",
    "gn:population":0,
    "gn:timezone":"Asia/Kolkata",
    "iso:country":"IN",
    "wof:name":"Narayanpur",
    "wof:placetype":"locality"
},
  "geometry": {"coordinates":[75.65378,15.07587],"type":"Point"}
}