{
  "type": "Feature",
  "properties": {
    "iso:country":"IN",
    "ks:ks_name":"Mohammadpur Barkali",
    "ks:ks_pop":384,
    "ks:ks_type":"VILLAGE",
    "ks:ks_uagg_main":0,
    "name:eng_x_preferred":[
        "Mohammadpur Barkali"
    ],
    "wof:name":"Mohammadpur Barkali",
    "wof:placetype":"locality",
    "wof:population":384
},
  "geometry": {"coordinates":[78.03283399999999,30.222849],"type":"Point"}
}