{
  "type": "Feature",
  "properties": {
    "iso:country":"IN",
    "ks:ks_name":"Ghughri Kheda F1",
    "ks:ks_pop":162,
    "ks:ks_type":"HABITATION",
    "name:eng_x_preferred":[
        "Ghughri Kheda F1"
    ],
    "wof:name":"Ghughri Kheda F1",
    "wof:placetype":"locality",
    "wof:population":162
},
  "geometry": {"coordinates":[79.281873,23.564965],"type":"Point"}
}