{
  "type": "Feature",
  "properties": {
    "gn:admin1_code":"21",
    "gn:admin2_code":"395.0",
    "gn:asciiname":"Merghara",
    "gn:country_code":"IN",
    "gn:dem":466,
    "gn:feature_class":"P",
    "gn:feature_code":"PPL",
    "gn:name":"Merghara",
    "gn:population":0,
    "gn:timezone":"Asia/Kolkata",
    "iso:country":"IN",
    "wof:name":"Merghara",
    "wof:placetype":"locality"
},
  "geometry": {"coordinates":[83.04186999999997,19.69863],"type":"Point"}
}