{
  "type": "Feature",
  "properties": {
    "gn:admin1_code":"28.0",
    "gn:admin2_code":"337.0",
    "gn:asciiname":"Baganati",
    "gn:country_code":"IN",
    "gn:dem":9,
    "gn:feature_class":"P",
    "gn:feature_code":"PPL",
    "gn:name":"Baganati",
    "gn:population":0,
    "gn:timezone":"Asia/Kolkata",
    "iso:country":"IN",
    "ks:ks_name":"Baganati",
    "ks:ks_pop":1138,
    "ks:ks_type":"VILLAGE",
    "ks:ks_uagg_main":0,
    "name:eng_x_preferred":[
        "Baganati"
    ],
    "wof:name":"Baganati",
    "wof:placetype":"neighbourhood",
    "wof:population":1138
},
  "geometry": {"coordinates":[88.66928299999999,22.59312],"type":"Point"}
}