{
  "type": "Feature",
  "properties": {
    "gn:admin1_code":"36.0",
    "gn:admin2_code":"164.0",
    "gn:asciiname":"Baradhari",
    "gn:country_code":"IN",
    "gn:dem":124,
    "gn:feature_class":"P",
    "gn:feature_code":"PPL",
    "gn:name":"B\u0101r\u0101dhari",
    "gn:population":0,
    "gn:timezone":"Asia/Kolkata",
    "iso:country":"IN",
    "wof:name":"Baradhari",
    "wof:placetype":"locality"
},
  "geometry": {"coordinates":[80.41999,26.29128],"type":"Point"}
}