{
  "type": "Feature",
  "properties": {
    "gn:admin1_code":"11.0",
    "gn:admin2_code":"32.0",
    "gn:asciiname":"Paplahan",
    "gn:country_code":"IN",
    "gn:dem":1391,
    "gn:feature_class":"P",
    "gn:feature_code":"PPL",
    "gn:name":"Papl\u0101h\u0101n",
    "gn:population":0,
    "gn:timezone":"Asia/Kolkata",
    "iso:country":"IN",
    "wof:name":"Paplahan",
    "wof:placetype":"locality"
},
  "geometry": {"coordinates":[77.24653000000001,30.6632],"type":"Point"}
}