{
  "type": "Feature",
  "properties": {
    "iso:country":"IN",
    "ks:ks_name":"Mahgrey Purwa",
    "ks:ks_pop":54,
    "ks:ks_type":"HABITATION",
    "ks:ks_uagg_main":0,
    "name:eng_x_preferred":[
        "Mahgrey Purwa"
    ],
    "wof:name":"Mahgrey Purwa",
    "wof:placetype":"neighbourhood",
    "wof:population":54
},
  "geometry": {"coordinates":[81.338193,27.790647],"type":"Point"}
}