{
  "type": "Feature",
  "properties": {
    "iso:country":"IN",
    "ks:ks_alt_nam":"SHALBARI",
    "ks:ks_name":"Shalbari",
    "ks:ks_pop":642,
    "ks:ks_type":"HABITATION",
    "name:eng_x_preferred":[
        "Shalbari"
    ],
    "wof:name":"Shalbari",
    "wof:placetype":"locality",
    "wof:population":642
},
  "geometry": {"coordinates":[88.745907,26.364394],"type":"Point"}
}