{
  "type": "Feature",
  "properties": {
    "iso:country":"IN",
    "ks:ks_alt_nam":"Khokhara ka oda",
    "ks:ks_name":"Khokhara Ka Oda",
    "ks:ks_pop":313,
    "ks:ks_type":"HABITATION",
    "name:eng_x_preferred":[
        "Khokhara Ka Oda"
    ],
    "wof:name":"Khokhara Ka Oda",
    "wof:placetype":"locality",
    "wof:population":313
},
  "geometry": {"coordinates":[73.75138699999999,25.548292],"type":"Point"}
}