{
  "type": "Feature",
  "properties": {
    "gn:admin1_code":"36",
    "gn:admin2_code":"194.0",
    "gn:asciiname":"Ahirana",
    "gn:country_code":"IN",
    "gn:dem":89,
    "gn:feature_class":"P",
    "gn:feature_code":"PPL",
    "gn:name":"Ah\u012br\u0101na",
    "gn:population":0,
    "gn:timezone":"Asia/Kolkata",
    "iso:country":"IN",
    "ks:ks_name":"Ahiran",
    "ks:ks_pop":332,
    "ks:ks_type":"HABITATION",
    "name:eng_x_preferred":[
        "Ahiran"
    ],
    "name:eng_x_variant":[
        "Ahirana"
    ],
    "wof:name":"Ahiran",
    "wof:placetype":"locality",
    "wof:population":332
},
  "geometry": {"coordinates":[82.637264,26.069701],"type":"Point"}
}