{
  "type": "Feature",
  "properties": {
    "iso:country":"IN",
    "ks:ks_name":"Naya Purwa",
    "ks:ks_pop":108,
    "ks:ks_type":"HABITATION",
    "ks:ks_uagg_main":0,
    "name:eng_x_preferred":[
        "Naya Purwa"
    ],
    "wof:name":"Naya Purwa",
    "wof:placetype":"neighbourhood",
    "wof:population":108
},
  "geometry": {"coordinates":[81.700118,26.284864],"type":"Point"}
}