{
  "type": "Feature",
  "properties": {
    "iso:country":"IN",
    "ks:ks_name":"Pathak Tola",
    "ks:ks_pop":150,
    "ks:ks_type":"HABITATION",
    "name:eng_x_preferred":[
        "Pathak Tola"
    ],
    "wof:name":"Pathak Tola",
    "wof:placetype":"locality",
    "wof:population":150
},
  "geometry": {"coordinates":[84.65714800000001,25.804783],"type":"Point"}
}