{
  "type": "Feature",
  "properties": {
    "gn:admin1_code":"12.0",
    "gn:admin2_code":"2.0",
    "gn:asciiname":"Zuhom Kandipur",
    "gn:country_code":"IN",
    "gn:dem":1799,
    "gn:feature_class":"P",
    "gn:feature_code":"PPL",
    "gn:name":"Zuhom K\u0101ndipur",
    "gn:population":0,
    "gn:timezone":"Asia/Kolkata",
    "iso:country":"IN",
    "wof:name":"Zuhom Kandipur",
    "wof:placetype":"locality"
},
  "geometry": {"coordinates":[74.74608000000001,33.9265],"type":"Point"}
}