{
  "type": "Feature",
  "properties": {
    "iso:country":"IN",
    "ks:ks_name":"Kundanapalli",
    "ks:ks_type":"VILLAGE",
    "name:eng_x_preferred":[
        "Kundanapalli"
    ],
    "wof:name":"Kundanapalli",
    "wof:placetype":"neighbourhood"
},
  "geometry": {"coordinates":[79.433716,18.747848],"type":"Point"}
}