{
  "type": "Feature",
  "properties": {
    "iso:country":"IN",
    "ks:ks_name":"Chinnagudipet",
    "ks:ks_pop":1343,
    "ks:ks_type":"VILLAGE",
    "name:eng_x_preferred":[
        "Chinnagudipet"
    ],
    "wof:name":"Chinnagudipet",
    "wof:placetype":"locality",
    "wof:population":1343
},
  "geometry": {"coordinates":[79.654218,19.241731],"type":"Point"}
}