{
  "type": "Feature",
  "properties": {
    "iso:country":"IN",
    "ks:ks_name":"Dombegadde",
    "ks:ks_pop":13,
    "ks:ks_type":"HABITATION",
    "name:eng_x_preferred":[
        "Dombegadde"
    ],
    "wof:name":"Dombegadde",
    "wof:placetype":"locality",
    "wof:population":13
},
  "geometry": {"coordinates":[74.800904,14.461489],"type":"Point"}
}