{
  "type": "Feature",
  "properties": {
    "iso:country":"IN",
    "ks:ks_name":"Kurichy",
    "ks:ks_pop":32992,
    "ks:ks_type":"VILLAGE",
    "name:eng_x_preferred":[
        "Kurichy"
    ],
    "wof:name":"Kurichy",
    "wof:placetype":"locality",
    "wof:population":32992
},
  "geometry": {"coordinates":[76.550715,9.480828],"type":"Point"}
}