{
  "type": "Feature",
  "properties": {
    "gn:admin1_code":"24",
    "gn:admin2_code":"125.0",
    "gn:asciiname":"Jakoriajagta Bara",
    "gn:country_code":"IN",
    "gn:dem":233,
    "gn:feature_class":"P",
    "gn:feature_code":"PPL",
    "gn:name":"Jakori\u0101jagta Bara",
    "gn:population":0,
    "gn:timezone":"Asia/Kolkata",
    "iso:country":"IN",
    "wof:name":"Jakoriajagta Bara",
    "wof:placetype":"locality"
},
  "geometry": {"coordinates":[74.27246,23.24589],"type":"Point"}
}