{
  "type": "Feature",
  "properties": {
    "gn:admin1_code":"36",
    "gn:admin2_code":"194.0",
    "gn:asciiname":"Babura",
    "gn:country_code":"IN",
    "gn:dem":91,
    "gn:feature_class":"P",
    "gn:feature_code":"PPL",
    "gn:name":"Bab\u016bra",
    "gn:population":0,
    "gn:timezone":"Asia/Kolkata",
    "iso:country":"IN",
    "name:fra_x_preferred":[
        "Babura"
    ],
    "name:hau_x_preferred":[
        "Babura"
    ],
    "name:ita_x_preferred":[
        "Babura"
    ],
    "name:spa_x_preferred":[
        "Babura"
    ],
    "wof:name":"Babura",
    "wof:placetype":"locality"
},
  "geometry": {"coordinates":[82.42299,25.90545],"type":"Point"}
}