{
  "type": "Feature",
  "properties": {
    "gn:admin1_code":"21.0",
    "gn:admin2_code":"399.0",
    "gn:asciiname":"Tummikamadaka",
    "gn:country_code":"IN",
    "gn:dem":163,
    "gn:feature_class":"P",
    "gn:feature_code":"PPL",
    "gn:name":"Tummikamadaka",
    "gn:population":0,
    "gn:timezone":"Asia/Kolkata",
    "iso:country":"IN",
    "name:und_x_variant":[
        "Gampakondag\u016bda"
    ],
    "wof:name":"Tummikamadaka",
    "wof:placetype":"locality"
},
  "geometry": {"coordinates":[81.83346999999998,18.10431],"type":"Point"}
}