{
  "type": "Feature",
  "properties": {
    "gn:admin1_code":"13",
    "gn:admin2_code":"590.0",
    "gn:asciiname":"Tindummal",
    "gn:country_code":"IN",
    "gn:dem":765,
    "gn:feature_class":"P",
    "gn:feature_code":"PPL",
    "gn:name":"Tindummal",
    "gn:population":0,
    "gn:timezone":"Asia/Kolkata",
    "iso:country":"IN",
    "wof:name":"Tindummal",
    "wof:placetype":"neighbourhood"
},
  "geometry": {"coordinates":[75.94862999999999,11.83771],"type":"Point"}
}