{
  "type": "Feature",
  "properties": {
    "iso:country":"IN",
    "ks:ks_name":"Huuchakot",
    "ks:ks_pop":173,
    "ks:ks_type":"HABITATION",
    "name:eng_x_preferred":[
        "Huuchakot"
    ],
    "wof:name":"Huuchakot",
    "wof:placetype":"locality",
    "wof:population":173
},
  "geometry": {"coordinates":[80.98701,20.116452],"type":"Point"}
}