{
  "type": "Feature",
  "properties": {
    "iso:country":"IN",
    "ks:ks_alt_nam":"KARUBYLU",
    "ks:ks_name":"Karubylu",
    "ks:ks_pop":70,
    "ks:ks_type":"HABITATION",
    "name:eng_x_preferred":[
        "Karubylu"
    ],
    "wof:name":"Karubylu",
    "wof:placetype":"locality",
    "wof:population":70
},
  "geometry": {"coordinates":[75.20761899999999,13.597995],"type":"Point"}
}