{
  "type": "Feature",
  "properties": {
    "iso:country":"IN",
    "ks:ks_name":"Kanipokhari",
    "ks:ks_pop":102,
    "ks:ks_type":"VILLAGE",
    "name:eng_x_preferred":[
        "Kanipokhari"
    ],
    "wof:name":"Kanipokhari",
    "wof:placetype":"locality",
    "wof:population":102
},
  "geometry": {"coordinates":[84.93231400000001,20.463337],"type":"Point"}
}