{
  "type": "Feature",
  "properties": {
    "iso:country":"IN",
    "ks:ks_name":"Nawada Urf Gonawa",
    "ks:ks_pop":6174,
    "ks:ks_type":"VILLAGE",
    "ks:ks_uagg_main":0,
    "name:eng_x_preferred":[
        "Nawada Urf Gonawa"
    ],
    "wof:name":"Nawada Urf Gonawa",
    "wof:placetype":"neighbourhood",
    "wof:population":6174
},
  "geometry": {"coordinates":[85.54593300000001,24.899896],"type":"Point"}
}