{
  "type": "Feature",
  "properties": {
    "iso:country":"IN",
    "ks:ks_name":"Arasanthangal",
    "ks:ks_pop":575,
    "ks:ks_type":"HABITATION",
    "name:eng_x_preferred":[
        "Arasanthangal"
    ],
    "wof:name":"Arasanthangal",
    "wof:placetype":"locality",
    "wof:population":575
},
  "geometry": {"coordinates":[79.023197,12.333933],"type":"Point"}
}