{
  "type": "Feature",
  "properties": {
    "gn:admin1_code":"35",
    "gn:admin2_code":"429.0",
    "gn:asciiname":"Aber",
    "gn:country_code":"IN",
    "gn:dem":295,
    "gn:feature_class":"P",
    "gn:feature_code":"PPL",
    "gn:name":"Aber",
    "gn:population":0,
    "gn:timezone":"Asia/Kolkata",
    "iso:country":"IN",
    "name:ceb_x_preferred":[
        "Aber"
    ],
    "name:cor_x_preferred":[
        "Aber"
    ],
    "name:deu_x_preferred":[
        "Aber"
    ],
    "name:fra_x_preferred":[
        "Aber"
    ],
    "name:nno_x_preferred":[
        "Aber"
    ],
    "name:swe_x_preferred":[
        "Aber"
    ],
    "wof:name":"Aber",
    "wof:placetype":"locality"
},
  "geometry": {"coordinates":[81.02209999999999,24.69728],"type":"Point"}
}