{
  "type": "Feature",
  "properties": {
    "iso:country":"IN",
    "ks:ks_name":"Sevra",
    "ks:ks_pop":376,
    "ks:ks_type":"HABITATION",
    "name:eng_x_preferred":[
        "Sevra"
    ],
    "wof:name":"Sevra",
    "wof:placetype":"locality",
    "wof:population":376
},
  "geometry": {"coordinates":[81.456816,26.195994],"type":"Point"}
}