{
  "type": "Feature",
  "properties": {
    "iso:country":"IN",
    "ks:ks_alt_nam":"No.2 DighaliNo.2 Dighali",
    "ks:ks_name":"No.2 Dighalino.2 Dighali",
    "ks:ks_pop":231,
    "ks:ks_type":"HABITATION",
    "name:eng_x_preferred":[
        "No.2 Dighalino.2 Dighali"
    ],
    "wof:name":"No.2 Dighalino.2 Dighali",
    "wof:placetype":"locality",
    "wof:population":231
},
  "geometry": {"coordinates":[94.706349,27.522998],"type":"Point"}
}