{
  "type": "Feature",
  "properties": {
    "iso:country":"IN",
    "ks:ks_name":"Moolur",
    "ks:ks_pop":500,
    "ks:ks_type":"HABITATION",
    "ks:ks_uagg_main":0,
    "name:eng_x_preferred":[
        "Moolur"
    ],
    "wof:name":"Moolur",
    "wof:placetype":"neighbourhood",
    "wof:population":500
},
  "geometry": {"coordinates":[74.933378,12.945159],"type":"Point"}
}