{
  "type": "Feature",
  "properties": {
    "iso:country":"IN",
    "ks:ks_alt_nam":"Kakh\u0101rum\u0101l",
    "ks:ks_name":"Kakharumal",
    "ks:ks_type":"VILLAGE",
    "ks:ks_uagg_main":0,
    "name:eng_x_preferred":[
        "Kakharumal"
    ],
    "name:eng_x_variant":[
        "Kakh\u0101rum\u0101l"
    ],
    "wof:name":"Kakharumal",
    "wof:placetype":"neighbourhood"
},
  "geometry": {"coordinates":[84.640415,21.338322],"type":"Point"}
}