{
  "type": "Feature",
  "properties": {
    "iso:country":"IN",
    "ks:ks_name":"Chikar Falia",
    "ks:ks_pop":135,
    "ks:ks_type":"HABITATION",
    "name:eng_x_preferred":[
        "Chikar Falia"
    ],
    "wof:name":"Chikar Falia",
    "wof:placetype":"locality",
    "wof:population":135
},
  "geometry": {"coordinates":[73.45916699999999,20.880056],"type":"Point"}
}