{
  "type": "Feature",
  "properties": {
    "iso:country":"IN",
    "ks:ks_name":"Sari Talli",
    "ks:ks_pop":106,
    "ks:ks_type":"VILLAGE",
    "name:eng_x_preferred":[
        "Sari Talli"
    ],
    "wof:name":"Sari Talli",
    "wof:placetype":"locality",
    "wof:population":106
},
  "geometry": {"coordinates":[78.691632,29.8792],"type":"Point"}
}