{
  "type": "Feature",
  "properties": {
    "iso:country":"IN",
    "ks:ks_name":"Tattigadde",
    "ks:ks_pop":16,
    "ks:ks_type":"HABITATION",
    "name:eng_x_preferred":[
        "Tattigadde"
    ],
    "wof:name":"Tattigadde",
    "wof:placetype":"locality",
    "wof:population":16
},
  "geometry": {"coordinates":[74.687533,14.881634],"type":"Point"}
}