{
  "type": "Feature",
  "properties": {
    "gn:admin1_code":"24.0",
    "gn:admin2_code":"116.0",
    "gn:asciiname":"Janvi",
    "gn:country_code":"IN",
    "gn:dem":23,
    "gn:feature_class":"P",
    "gn:feature_code":"PPL",
    "gn:name":"J\u0101nvi",
    "gn:population":0,
    "gn:timezone":"Asia/Kolkata",
    "iso:country":"IN",
    "wof:name":"Janvi",
    "wof:placetype":"locality"
},
  "geometry": {"coordinates":[71.54759,24.8015],"type":"Point"}
}