{
  "type": "Feature",
  "properties": {
    "gn:admin1_code":"36.0",
    "gn:admin2_code":"193.0",
    "gn:asciiname":"Surhi",
    "gn:country_code":"IN",
    "gn:dem":67,
    "gn:feature_class":"P",
    "gn:feature_code":"PPL",
    "gn:name":"Surhi",
    "gn:population":0,
    "gn:timezone":"Asia/Kolkata",
    "iso:country":"IN",
    "wof:name":"Surhi",
    "wof:placetype":"locality"
},
  "geometry": {"coordinates":[84.00972,25.64512],"type":"Point"}
}