{
  "type": "Feature",
  "properties": {
    "iso:country":"IN",
    "ks:ks_name":"Pasai",
    "ks:ks_pop":3051,
    "ks:ks_type":"VILLAGE",
    "ks:ks_uagg_main":0,
    "name:eng_x_preferred":[
        "Pasai"
    ],
    "wof:name":"Pasai",
    "wof:placetype":"neighbourhood",
    "wof:population":3051
},
  "geometry": {"coordinates":[85.319051,23.981659],"type":"Point"}
}