{
  "type": "Feature",
  "properties": {
    "iso:country":"IN",
    "ks:ks_name":"Talang",
    "ks:ks_pop":0,
    "ks:ks_type":"VILLAGE",
    "name:eng_x_preferred":[
        "Talang"
    ],
    "wof:name":"Talang",
    "wof:placetype":"locality",
    "wof:population":0
},
  "geometry": {"coordinates":[82.85029,19.204011],"type":"Point"}
}