{
  "type": "Feature",
  "properties": {
    "iso:country":"IN",
    "ks:ks_name":"Pandiyarnagar",
    "ks:ks_pop":812,
    "ks:ks_type":"HABITATION",
    "name:eng_x_preferred":[
        "Pandiyarnagar"
    ],
    "wof:name":"Pandiyarnagar",
    "wof:placetype":"locality",
    "wof:population":812
},
  "geometry": {"coordinates":[78.920551,9.313876],"type":"Point"}
}