{
  "type": "Feature",
  "properties": {
    "gn:admin1_code":"10.0",
    "gn:admin2_code":"081",
    "gn:asciiname":"Mauhala",
    "gn:country_code":"IN",
    "gn:dem":222,
    "gn:feature_class":"P",
    "gn:feature_code":"PPL",
    "gn:name":"Mauhala",
    "gn:population":0,
    "gn:timezone":"Asia/Kolkata",
    "iso:country":"IN",
    "name:eng_x_preferred":[
        "Mohila"
    ],
    "name:eng_x_variant":[
        "Mauhala"
    ],
    "wof:name":"Mohila",
    "wof:placetype":"locality"
},
  "geometry": {"coordinates":[75.62278000000001,28.84691],"type":"Point"}
}