{
  "type": "Feature",
  "properties": {
    "iso:country":"IN",
    "ks:ks_name":"Kalantira",
    "ks:ks_pop":1101,
    "ks:ks_type":"VILLAGE",
    "ks:ks_uagg_main":0,
    "name:eng_x_preferred":[
        "Kalantira"
    ],
    "wof:name":"Kalantira",
    "wof:placetype":"neighbourhood",
    "wof:population":1101
},
  "geometry": {"coordinates":[86.054433,20.385961],"type":"Point"}
}