{
  "type": "Feature",
  "properties": {
    "iso:country":"IN",
    "ks:ks_name":"Ger",
    "ks:ks_pop":681,
    "ks:ks_type":"VILLAGE",
    "name:eng_x_preferred":[
        "Ger"
    ],
    "wof:name":"Ger",
    "wof:placetype":"locality",
    "wof:population":681
},
  "geometry": {"coordinates":[73.41014800000001,23.785431],"type":"Point"}
}