{
  "type": "Feature",
  "properties": {
    "iso:country":"IN",
    "ks:ks_name":"Huklamane",
    "ks:ks_pop":8,
    "ks:ks_type":"HABITATION",
    "name:eng_x_preferred":[
        "Huklamane"
    ],
    "wof:name":"Huklamane",
    "wof:placetype":"locality",
    "wof:population":8
},
  "geometry": {"coordinates":[74.75071800000001,14.491538],"type":"Point"}
}