{
  "type": "Feature",
  "properties": {
    "gn:admin1_code":"19.0",
    "gn:admin2_code":"571.0",
    "gn:asciiname":"Devalapur",
    "gn:country_code":"IN",
    "gn:dem":846,
    "gn:feature_class":"P",
    "gn:feature_code":"PPL",
    "gn:name":"Deval\u0101pur",
    "gn:population":0,
    "gn:timezone":"Asia/Kolkata",
    "iso:country":"IN",
    "name:vie_x_preferred":[
        "Devalapur"
    ],
    "wof:name":"Devalapur",
    "wof:placetype":"locality"
},
  "geometry": {"coordinates":[77.10645,13.48715],"type":"Point"}
}