{
  "type": "Feature",
  "properties": {
    "gn:admin1_code":"35.0",
    "gn:admin2_code":"441.0",
    "gn:asciiname":"Harla",
    "gn:country_code":"IN",
    "gn:dem":435,
    "gn:feature_class":"P",
    "gn:feature_code":"PPL",
    "gn:name":"Harla",
    "gn:population":0,
    "gn:timezone":"Asia/Kolkata",
    "iso:country":"IN",
    "wof:name":"Harla",
    "wof:placetype":"locality"
},
  "geometry": {"coordinates":[74.63911,21.94712],"type":"Point"}
}