{
  "type": "Feature",
  "properties": {
    "gn:admin1_code":"35.0",
    "gn:admin2_code":"441.0",
    "gn:asciiname":"Harla",
    "gn:country_code":"IN",
    "gn:dem":435,
    "gn:feature_class":"P",
    "gn:feature_code":"PPL",
    "gn:name":"Harla",
    "gn:population":0,
    "gn:timezone":"Asia/Kolkata",
    "iso:country":"IN",
    "ks:ks_name":"Harla",
    "ks:ks_pop":504,
    "ks:ks_type":"VILLAGE",
    "name:eng_x_preferred":[
        "Harla"
    ],
    "wof:name":"Harla",
    "wof:placetype":"locality",
    "wof:population":504
},
  "geometry": {"coordinates":[74.65600499999999,21.957448],"type":"Point"}
}