{
  "type": "Feature",
  "properties": {
    "iso:country":"IN",
    "ks:ks_alt_nam":"chhipalbad",
    "ks:ks_name":"Chhipalbad",
    "ks:ks_pop":737,
    "ks:ks_type":"HABITATION",
    "name:eng_x_preferred":[
        "Chhipalbad"
    ],
    "wof:name":"Chhipalbad",
    "wof:placetype":"locality",
    "wof:population":737
},
  "geometry": {"coordinates":[86.433148,23.626479],"type":"Point"}
}