{
  "type": "Feature",
  "properties": {
    "gn:admin1_code":"23.0",
    "gn:admin2_code":"42.0",
    "gn:asciiname":"Machhike",
    "gn:country_code":"IN",
    "gn:dem":231,
    "gn:feature_class":"P",
    "gn:feature_code":"PPL",
    "gn:name":"Machhike",
    "gn:population":0,
    "gn:timezone":"Asia/Kolkata",
    "iso:country":"IN",
    "name:pan_x_preferred":[
        "\u0a2e\u0a3e\u0a1b\u0a40\u0a15\u0a47"
    ],
    "wof:name":"Machhike",
    "wof:placetype":"locality"
},
  "geometry": {"coordinates":[75.38020999999998,30.55605],"type":"Point"}
}