{
  "type": "Feature",
  "properties": {
    "iso:country":"IN",
    "ks:ks_name":"Chintavanipeta",
    "ks:ks_pop":157,
    "ks:ks_type":"HABITATION",
    "name:eng_x_preferred":[
        "Chintavanipeta"
    ],
    "wof:name":"Chintavanipeta",
    "wof:placetype":"locality",
    "wof:population":157
},
  "geometry": {"coordinates":[84.495064,18.748988],"type":"Point"}
}