{
  "type": "Feature",
  "properties": {
    "gn:admin1_code":"16",
    "gn:admin2_code":"520.0",
    "gn:asciiname":"Thal",
    "gn:country_code":"IN",
    "gn:dem":1,
    "gn:feature_class":"P",
    "gn:feature_code":"PPL",
    "gn:name":"Th\u0101l",
    "gn:population":0,
    "gn:timezone":"Asia/Kolkata",
    "iso:country":"IN",
    "wof:name":"Thal",
    "wof:placetype":"locality"
},
  "geometry": {"coordinates":[72.91667,18.58333],"type":"Point"}
}