{
  "type": "Feature",
  "properties": {
    "iso:country":"IN",
    "ks:ks_name":"Charaikhola",
    "ks:ks_pop":2050,
    "ks:ks_type":"VILLAGE",
    "name:eng_x_preferred":[
        "Charaikhola"
    ],
    "wof:name":"Charaikhola",
    "wof:placetype":"locality",
    "wof:population":2050
},
  "geometry": {"coordinates":[89.838447,26.145851],"type":"Point"}
}