{
  "type": "Feature",
  "properties": {
    "gn:admin1_code":"34.0",
    "gn:admin2_code":"235",
    "gn:asciiname":"Dihra",
    "gn:country_code":"IN",
    "gn:dem":105,
    "gn:feature_class":"P",
    "gn:feature_code":"PPL",
    "gn:name":"Dihra",
    "gn:population":0,
    "gn:timezone":"Asia/Kolkata",
    "iso:country":"IN",
    "name:und_x_variant":[
        "Dihar",
        "Dihra"
    ],
    "wof:name":"Dihra",
    "wof:placetype":"locality"
},
  "geometry": {"coordinates":[84.31142,24.97311],"type":"Point"}
}