{
  "type": "Feature",
  "properties": {
    "iso:country":"IN",
    "ks:ks_alt_nam":"KALABARI LINE",
    "ks:ks_name":"Kalabari Line",
    "ks:ks_pop":513,
    "ks:ks_type":"HABITATION",
    "name:eng_x_preferred":[
        "Kalabari Line"
    ],
    "wof:name":"Kalabari Line",
    "wof:placetype":"locality",
    "wof:population":513
},
  "geometry": {"coordinates":[89.16653100000001,26.776158],"type":"Point"}
}