{
  "type": "Feature",
  "properties": {
    "gn:country":"IN",
    "gn:fcode":"PPL",
    "gn:pop":33467,
    "iso:country":"IN",
    "name:ben_x_preferred":[
        "\u09ac\u09c7\u0997\u09ae\u0997\u099e\u09cd\u099c"
    ],
    "name:bpy_x_preferred":[
        "\u09ac\u09c7\u0997\u09ae\u0997\u099e\u09cd\u099c"
    ],
    "name:deu_x_preferred":[
        "Begamganj"
    ],
    "name:eng_x_preferred":[
        "Begamganj"
    ],
    "name:fas_x_preferred":[
        "\u0628\u06cc\u06af\u0645\u200c\u06af\u0646\u062c"
    ],
    "name:fra_x_preferred":[
        "Begamganj"
    ],
    "name:guj_x_preferred":[
        "\u0aac\u0ac7\u0a97\u0aae\u0a97\u0a82\u0a9c"
    ],
    "name:ita_x_preferred":[
        "Begamganj"
    ],
    "name:jpn_x_preferred":[
        "\u30d9\u30ac\u30e0\u30ac\u30f3\u30b8"
    ],
    "name:kan_x_preferred":[
        "\u0cac\u0cc7\u0c97\u0c82\u0c97\u0c82\u0c9c\u0ccd"
    ],
    "name:kor_x_preferred":[
        "\ubca0\uac00\uac04\uc9c0"
    ],
    "name:mlg_x_preferred":[
        "Begamganj"
    ],
    "name:msa_x_preferred":[
        "Begamganj"
    ],
    "name:new_x_preferred":[
        "\u092c\u0947\u0917\u092e\u0917\u091e\u094d\u091c17"
    ],
    "name:nld_x_preferred":[
        "Begamganj"
    ],
    "name:por_x_preferred":[
        "Begamganj"
    ],
    "name:rus_x_preferred":[
        "\u0411\u0435\u0433\u0430\u043c\u0433\u0430\u043d\u0434\u0436"
    ],
    "name:spa_x_preferred":[
        "Begamganj"
    ],
    "name:swe_x_preferred":[
        "Begamganj"
    ],
    "name:tam_x_preferred":[
        "\u0baa\u0bc7\u0b95\u0bae\u0bcd\u0b95\u0b9e\u0bcd"
    ],
    "name:tel_x_preferred":[
        "\u0c2c\u0c47\u0c17\u0c02\u0c17\u0c02\u0c1c\u0c4d"
    ],
    "name:urd_x_preferred":[
        "\u0628\u06cc\u062c\u0627\u0645\u062c\u0627\u0646\u062c"
    ],
    "name:vie_x_preferred":[
        "Begamganj"
    ],
    "name:zho_x_preferred":[
        "\u8d1d\u52a0\u59c6\u7518\u6770"
    ],
    "qs:name":"Begamganj",
    "qs:name_adm0":"India",
    "qs:name_adm1":"Madhya Pradesh",
    "qs:photos_9k":1,
    "qs:photos_9r":1,
    "qs:photos_all":1,
    "qs:photos_sr":0,
    "qs:placetype":"Town",
    "qs:pop_sr":"7",
    "wd:wordcount":342,
    "wof:name":"Begamganj",
    "wof:placetype":"locality",
    "wof:population":33467
},
  "geometry": {"coordinates":[78.33976,23.60134],"type":"Point"}
}