{
  "type": "Feature",
  "properties": {
    "iso:country":"IN",
    "ks:ks_name":"Fatepur",
    "ks:ks_pop":473,
    "ks:ks_type":"VILLAGE",
    "name:eng_x_preferred":[
        "Fatepur"
    ],
    "wof:name":"Fatepur",
    "wof:placetype":"locality",
    "wof:population":473
},
  "geometry": {"coordinates":[86.362718,20.971838],"type":"Point"}
}