{
  "type": "Feature",
  "properties": {
    "iso:country":"IN",
    "ks:ks_name":"Kandhaambajhar",
    "ks:ks_pop":513,
    "ks:ks_type":"VILLAGE",
    "name:eng_x_preferred":[
        "Kandhaambajhar"
    ],
    "wof:name":"Kandhaambajhar",
    "wof:placetype":"locality",
    "wof:population":513
},
  "geometry": {"coordinates":[85.27931,19.868634],"type":"Point"}
}