{
  "type": "Feature",
  "properties": {
    "iso:country":"IN",
    "ks:ks_name":"N Kothakottalu",
    "ks:ks_pop":32,
    "ks:ks_type":"HABITATION",
    "name:eng_x_preferred":[
        "N Kothakottalu"
    ],
    "wof:name":"N Kothakottalu",
    "wof:placetype":"locality",
    "wof:population":32
},
  "geometry": {"coordinates":[78.97489899999999,14.433707],"type":"Point"}
}