{
  "type": "Feature",
  "properties": {
    "iso:country":"IN",
    "ks:ks_name":"Nichli Goran",
    "ks:ks_pop":705,
    "ks:ks_type":"HABITATION",
    "name:eng_x_preferred":[
        "Nichli Goran"
    ],
    "wof:name":"Nichli Goran",
    "wof:placetype":"locality",
    "wof:population":705
},
  "geometry": {"coordinates":[73.506603,24.273828],"type":"Point"}
}