{
  "type": "Feature",
  "properties": {
    "iso:country":"IN",
    "ks:ks_name":"Kechoru Guri",
    "ks:ks_pop":47,
    "ks:ks_type":"HABITATION",
    "ks:ks_uagg_main":0,
    "name:eng_x_preferred":[
        "Kechoru Guri"
    ],
    "wof:name":"Kechoru Guri",
    "wof:placetype":"neighbourhood",
    "wof:population":47
},
  "geometry": {"coordinates":[94.519851,27.34396],"type":"Point"}
}