{
  "type": "Feature",
  "properties": {
    "iso:country":"IN",
    "ks:ks_name":"Malikpur Arazi",
    "ks:ks_pop":726,
    "ks:ks_type":"VILLAGE",
    "name:eng_x_preferred":[
        "Malikpur Arazi"
    ],
    "wof:name":"Malikpur Arazi",
    "wof:placetype":"locality",
    "wof:population":726
},
  "geometry": {"coordinates":[87.768738,25.68652],"type":"Point"}
}