{
  "type": "Feature",
  "properties": {
    "iso:country":"IN",
    "ks:ks_name":"Nawadih",
    "ks:ks_pop":495,
    "ks:ks_type":"VILLAGE",
    "ks:ks_uagg_main":0,
    "name:eng_x_preferred":[
        "Nawadih"
    ],
    "wof:name":"Nawadih",
    "wof:placetype":"neighbourhood",
    "wof:population":495
},
  "geometry": {"coordinates":[86.63918700000001,24.541345],"type":"Point"}
}