{
  "type": "Feature",
  "properties": {
    "gn:admin1_code":"3.0",
    "gn:admin2_code":"314.0",
    "gn:asciiname":"Sonarijangaon",
    "gn:country_code":"IN",
    "gn:dem":93,
    "gn:feature_class":"P",
    "gn:feature_code":"PPL",
    "gn:name":"Son\u0101rij\u0101ng\u0101on",
    "gn:population":0,
    "gn:timezone":"Asia/Kolkata",
    "iso:country":"IN",
    "wof:name":"Sonarijangaon",
    "wof:placetype":"locality"
},
  "geometry": {"coordinates":[93.13684000000001,26.22391],"type":"Point"}
}