{
  "type": "Feature",
  "properties": {
    "gn:admin1_code":"35.0",
    "gn:admin2_code":"455.0",
    "gn:asciiname":"Kankheri",
    "gn:country_code":"IN",
    "gn:dem":617,
    "gn:feature_class":"P",
    "gn:feature_code":"PPL",
    "gn:name":"K\u0101nkheri",
    "gn:population":0,
    "gn:timezone":"Asia/Kolkata",
    "iso:country":"IN",
    "ks:ks_alt_nam":"K\u0101nkheri",
    "ks:ks_name":"Kankheri",
    "ks:ks_type":"VILLAGE",
    "name:eng_x_preferred":[
        "Kankheri"
    ],
    "name:eng_x_variant":[
        "K\u0101nkheri"
    ],
    "wof:name":"Kankheri",
    "wof:placetype":"locality"
},
  "geometry": {"coordinates":[78.56570499999999,22.341364],"type":"Point"}
}