{
  "type": "Feature",
  "properties": {
    "gn:admin1_code":"35.0",
    "gn:admin2_code":"451.0",
    "gn:asciiname":"Murta",
    "gn:country_code":"IN",
    "gn:dem":390,
    "gn:feature_class":"P",
    "gn:feature_code":"PPL",
    "gn:name":"Murta",
    "gn:population":0,
    "gn:timezone":"Asia/Kolkata",
    "iso:country":"IN",
    "wof:name":"Murta",
    "wof:placetype":"locality"
},
  "geometry": {"coordinates":[80.14995999999999,23.46281],"type":"Point"}
}