{
  "type": "Feature",
  "properties": {
    "gn:admin1_code":"34.0",
    "gn:admin2_code":"225.0",
    "gn:asciiname":"Beldiha",
    "gn:country_code":"IN",
    "gn:dem":63,
    "gn:feature_class":"P",
    "gn:feature_code":"PPL",
    "gn:name":"Beldiha",
    "gn:population":0,
    "gn:timezone":"Asia/Kolkata",
    "iso:country":"IN",
    "ks:ks_name":"Beldiha",
    "ks:ks_pop":1713,
    "ks:ks_type":"VILLAGE",
    "name:eng_x_preferred":[
        "Beldiha"
    ],
    "wof:name":"Beldiha",
    "wof:placetype":"locality",
    "wof:population":1713
},
  "geometry": {"coordinates":[87.12845,24.94266],"type":"Point"}
}