{
  "type": "Feature",
  "properties": {
    "gn:admin1_code":"35.0",
    "gn:admin2_code":"453.0",
    "gn:asciiname":"Patharkata",
    "gn:country_code":"IN",
    "gn:dem":712,
    "gn:feature_class":"P",
    "gn:feature_code":"PPL",
    "gn:name":"Patharkata",
    "gn:population":0,
    "gn:timezone":"Asia/Kolkata",
    "iso:country":"IN",
    "wof:name":"Patharkata",
    "wof:placetype":"locality"
},
  "geometry": {"coordinates":[80.69256999999998,23.12351],"type":"Point"}
}