{
  "type": "Feature",
  "properties": {
    "gn:admin1_code":"21",
    "gn:admin2_code":"372.0",
    "gn:asciiname":"Kainsir",
    "gn:country_code":"IN",
    "gn:dem":179,
    "gn:feature_class":"P",
    "gn:feature_code":"PPL",
    "gn:name":"K\u0101insir",
    "gn:population":0,
    "gn:timezone":"Asia/Kolkata",
    "iso:country":"IN",
    "wof:name":"Kainsir",
    "wof:placetype":"locality"
},
  "geometry": {"coordinates":[83.99124,21.51021],"type":"Point"}
}