{
  "type": "Feature",
  "properties": {
    "gn:admin1_code":"19.0",
    "gn:admin2_code":"575.0",
    "gn:asciiname":"Komali",
    "gn:country_code":"IN",
    "gn:dem":35,
    "gn:feature_class":"P",
    "gn:feature_code":"PPL",
    "gn:name":"Komali",
    "gn:population":0,
    "gn:timezone":"Asia/Kolkata",
    "iso:country":"IN",
    "ks:ks_name":"Komali",
    "ks:ks_pop":508,
    "ks:ks_type":"HABITATION",
    "name:eng_x_preferred":[
        "Komali"
    ],
    "wof:name":"Komali",
    "wof:placetype":"locality",
    "wof:population":508
},
  "geometry": {"coordinates":[75.03379099999999,12.830692],"type":"Point"}
}