{
  "type": "Feature",
  "properties": {
    "gn:admin1_code":"11.0",
    "gn:admin2_code":"32.0",
    "gn:asciiname":"Koilanu",
    "gn:country_code":"IN",
    "gn:dem":1540,
    "gn:feature_class":"P",
    "gn:feature_code":"PPL",
    "gn:name":"Koil\u0101nu",
    "gn:population":0,
    "gn:timezone":"Asia/Kolkata",
    "iso:country":"IN",
    "wof:name":"Koilanu",
    "wof:placetype":"locality"
},
  "geometry": {"coordinates":[77.60406999999999,30.7474],"type":"Point"}
}