{
  "type": "Feature",
  "properties": {
    "gn:admin1_code":"19.0",
    "gn:asciiname":"Tammapuram",
    "gn:country_code":"IN",
    "gn:dem":947,
    "gn:feature_class":"P",
    "gn:feature_code":"PPL",
    "gn:name":"Tammapuram",
    "gn:population":0,
    "gn:timezone":"Asia/Kolkata",
    "iso:country":"IN",
    "wof:name":"Tammapuram",
    "wof:placetype":"locality"
},
  "geometry": {"coordinates":[77.67451,12.66928],"type":"Point"}
}