{
  "type": "Feature",
  "properties": {
    "gn:admin1_code":"19.0",
    "gn:asciiname":"Tammapuram",
    "gn:country_code":"IN",
    "gn:dem":947,
    "gn:feature_class":"P",
    "gn:feature_code":"PPL",
    "gn:name":"Tammapuram",
    "gn:population":0,
    "gn:timezone":"Asia/Kolkata",
    "iso:country":"IN",
    "ks:ks_name":"Thammapuram",
    "ks:ks_pop":616,
    "ks:ks_type":"HABITATION",
    "name:eng_x_preferred":[
        "Thammapuram"
    ],
    "name:eng_x_variant":[
        "Tammapuram"
    ],
    "wof:name":"Thammapuram",
    "wof:placetype":"locality",
    "wof:population":616
},
  "geometry": {"coordinates":[77.66713900000001,12.67593],"type":"Point"}
}