{
  "type": "Feature",
  "properties": {
    "iso:country":"IN",
    "ks:ks_name":"Koilnangai",
    "ks:ks_pop":302,
    "ks:ks_type":"HABITATION",
    "name:eng_x_preferred":[
        "Koilnangai"
    ],
    "wof:name":"Koilnangai",
    "wof:placetype":"locality",
    "wof:population":302
},
  "geometry": {"coordinates":[79.625483,10.848617],"type":"Point"}
}