{
  "type": "Feature",
  "properties": {
    "iso:country":"IN",
    "ks:ks_name":"Khedi",
    "ks:ks_pop":5,
    "ks:ks_type":"VILLAGE",
    "name:eng_x_preferred":[
        "Khedi"
    ],
    "wof:name":"Khedi",
    "wof:placetype":"locality",
    "wof:population":5
},
  "geometry": {"coordinates":[75.270245,22.096057],"type":"Point"}
}