{
  "type": "Feature",
  "properties": {
    "iso:country":"IN",
    "ks:ks_alt_nam":"Dh\u0101l\u0101mau",
    "ks:ks_name":"Dhalamau",
    "ks:ks_type":"VILLAGE",
    "name:eng_x_preferred":[
        "Dhalamau"
    ],
    "name:eng_x_variant":[
        "Dh\u0101l\u0101mau"
    ],
    "wof:name":"Dhalamau",
    "wof:placetype":"locality"
},
  "geometry": {"coordinates":[77.783326,22.403827],"type":"Point"}
}