{
  "type": "Feature",
  "properties": {
    "iso:country":"IN",
    "ks:ks_name":"Sialdanga",
    "ks:ks_pop":0,
    "ks:ks_type":"VILLAGE",
    "name:eng_x_preferred":[
        "Sialdanga"
    ],
    "wof:name":"Sialdanga",
    "wof:placetype":"locality",
    "wof:population":0
},
  "geometry": {"coordinates":[87.78414600000001,24.156822],"type":"Point"}
}