{
  "type": "Feature",
  "properties": {
    "iso:country":"IN",
    "ks:ks_name":"Bauthal Laga Khatyana",
    "ks:ks_pop":129,
    "ks:ks_type":"VILLAGE",
    "name:eng_x_preferred":[
        "Bauthal Laga Khatyana"
    ],
    "wof:name":"Bauthal Laga Khatyana",
    "wof:placetype":"locality",
    "wof:population":129
},
  "geometry": {"coordinates":[78.994945,30.317892],"type":"Point"}
}