{
  "type": "Feature",
  "properties": {
    "gn:admin1_code":"25.0",
    "gn:admin2_code":"619.0",
    "gn:asciiname":"Ullurvallamanattam",
    "gn:country_code":"IN",
    "gn:dem":22,
    "gn:feature_class":"P",
    "gn:feature_code":"PPL",
    "gn:name":"Ull\u016brvallam\u0101nattam",
    "gn:population":0,
    "gn:timezone":"Asia/Kolkata",
    "iso:country":"IN",
    "wof:name":"Ullurvallamanattam",
    "wof:placetype":"locality"
},
  "geometry": {"coordinates":[79.44953000000002,10.68699],"type":"Point"}
}