{
  "type": "Feature",
  "properties": {
    "iso:country":"IN",
    "ks:ks_name":"Gatiguda",
    "ks:ks_pop":597,
    "ks:ks_type":"HABITATION",
    "name:eng_x_preferred":[
        "Gatiguda"
    ],
    "wof:name":"Gatiguda",
    "wof:placetype":"locality",
    "wof:population":597
},
  "geometry": {"coordinates":[82.03151699999999,18.539824],"type":"Point"}
}