{
  "type": "Feature",
  "properties": {
    "gn:admin1_code":"24.0",
    "gn:admin2_code":"108",
    "gn:asciiname":"Khilchipur",
    "gn:country_code":"IN",
    "gn:dem":263,
    "gn:feature_class":"P",
    "gn:feature_code":"PPL",
    "gn:name":"Khilch\u012bpur",
    "gn:population":0,
    "gn:timezone":"Asia/Kolkata",
    "iso:country":"IN",
    "name:ben_x_preferred":[
        "\u0996\u09bf\u09b2\u099a\u09bf\u09aa\u09c1\u09b0"
    ],
    "name:bpy_x_preferred":[
        "\u0996\u09bf\u09b2\u099a\u09bf\u09aa\u09c1\u09b0"
    ],
    "name:cat_x_preferred":[
        "Khilchipur"
    ],
    "name:ceb_x_preferred":[
        "Khilchipur"
    ],
    "name:ita_x_preferred":[
        "Khilchipur"
    ],
    "name:mlg_x_preferred":[
        "Khilchipur"
    ],
    "name:msa_x_preferred":[
        "Khilchipur"
    ],
    "name:new_x_preferred":[
        "\u0916\u093f\u091a\u093f\u092a\u0941\u0930"
    ],
    "name:nld_x_preferred":[
        "Khilchipur"
    ],
    "name:pam_x_preferred":[
        "Khilchipur"
    ],
    "name:por_x_preferred":[
        "Khilchipur"
    ],
    "name:swe_x_preferred":[
        "Khilchipur"
    ],
    "name:vie_x_preferred":[
        "Khilchipur"
    ],
    "name:zho_x_preferred":[
        "\u57fa\u5c14\u5947\u666e\u5c14"
    ],
    "wof:name":"Khilchipur",
    "wof:placetype":"locality"
},
  "geometry": {"coordinates":[76.42014,26.05728],"type":"Point"}
}