{
  "type": "Feature",
  "properties": {
    "gn:admin1_code":"38.0",
    "gn:admin2_code":"358.0",
    "gn:asciiname":"Nagwa",
    "gn:country_code":"IN",
    "gn:dem":224,
    "gn:feature_class":"P",
    "gn:feature_code":"PPL",
    "gn:name":"Nagw\u0101",
    "gn:population":0,
    "gn:timezone":"Asia/Kolkata",
    "iso:country":"IN",
    "ks:ks_name":"Nagwa",
    "ks:ks_pop":1050,
    "ks:ks_type":"VILLAGE",
    "ks:ks_uagg_main":0,
    "name:ara_x_preferred":[
        "\u0646\u062c\u0648\u0649"
    ],
    "name:ben_bn_x_preferred":[
        "\u09a8\u09be\u0997\u0993\u09df\u09be"
    ],
    "name:ben_in_x_preferred":[
        "\u09a8\u09be\u0997\u0993\u09df\u09be"
    ],
    "name:eng_x_preferred":[
        "Nagwa"
    ],
    "name:guj_x_preferred":[
        "\u0aa8\u0abe\u0a97\u0acd\u0ab5\u0abe"
    ],
    "name:hin_x_preferred":[
        "\u0928\u093e\u0917\u0935\u093e"
    ],
    "name:kan_x_preferred":[
        "\u0ca8\u0c97\u0ccd\u0cb5\u0cbe"
    ],
    "name:mal_x_preferred":[
        "\u0d28\u0d3e\u0d17\u0d4d\u0d35"
    ],
    "name:mar_x_preferred":[
        "\u0928\u093e\u0917\u0935\u093e"
    ],
    "name:pan_x_preferred":[
        "\u0a28\u0a17\u0a35\u0a3e"
    ],
    "name:tam_x_preferred":[
        "\u0ba8\u0b95\u0bcd\u0bb5\u0bbe"
    ],
    "name:tel_x_preferred":[
        "\u0c28\u0c3e\u0c17\u0c4d\u0c35\u0c3e"
    ],
    "name:urd_x_preferred":[
        "\u0646\u0627\u06af\u0648\u0627"
    ],
    "wof:name":"Nagwa",
    "wof:placetype":"neighbourhood",
    "wof:population":1050
},
  "geometry": {"coordinates":[84.023623,24.09583],"type":"Point"}
}