{
  "type": "Feature",
  "properties": {
    "iso:country":"IN",
    "ks:ks_name":"Nikinikhwa",
    "ks:ks_pop":510,
    "ks:ks_type":"HABITATION",
    "ks:ks_uagg_main":0,
    "name:eng_x_preferred":[
        "Nikinikhwa"
    ],
    "wof:name":"Nikinikhwa",
    "wof:placetype":"neighbourhood",
    "wof:population":510
},
  "geometry": {"coordinates":[94.219292,27.024761],"type":"Point"}
}