{
  "type": "Feature",
  "properties": {
    "iso:country":"IN",
    "ks:ks_name":"Derawali",
    "ks:ks_pop":926,
    "ks:ks_type":"VILLAGE",
    "name:eng_x_preferred":[
        "Derawali"
    ],
    "wof:name":"Derawali",
    "wof:placetype":"locality",
    "wof:population":926
},
  "geometry": {"coordinates":[73.14303,18.958897],"type":"Point"}
}