{
  "type": "Feature",
  "properties": {
    "iso:country":"IN",
    "ks:ks_alt_nam":"Chanda dandi",
    "ks:ks_name":"Chanda Dandi",
    "ks:ks_pop":1142,
    "ks:ks_type":"HABITATION",
    "name:eng_x_preferred":[
        "Chanda Dandi"
    ],
    "wof:name":"Chanda Dandi",
    "wof:placetype":"locality",
    "wof:population":1142
},
  "geometry": {"coordinates":[84.004763,23.353383],"type":"Point"}
}