{
  "type": "Feature",
  "properties": {
    "gn:admin1_code":"34.0",
    "gn:admin2_code":"231.0",
    "gn:asciiname":"Pandipur",
    "gn:country_code":"IN",
    "gn:dem":60,
    "gn:feature_class":"P",
    "gn:feature_code":"PPL",
    "gn:name":"Pandipur",
    "gn:population":0,
    "gn:timezone":"Asia/Kolkata",
    "iso:country":"IN",
    "ks:ks_name":"Panditpur",
    "ks:ks_pop":1352,
    "ks:ks_type":"VILLAGE",
    "ks:ks_uagg_main":0,
    "name:eng_x_preferred":[
        "Panditpur"
    ],
    "wof:name":"Panditpur",
    "wof:placetype":"neighbourhood",
    "wof:population":1352
},
  "geometry": {"coordinates":[84.72136999999999,25.650243],"type":"Point"}
}