{
  "type": "Feature",
  "properties": {
    "iso:country":"IN",
    "ks:ks_name":"Sampathnagar",
    "ks:ks_pop":128,
    "ks:ks_type":"HABITATION",
    "name:eng_x_preferred":[
        "Sampathnagar"
    ],
    "wof:name":"Sampathnagar",
    "wof:placetype":"locality",
    "wof:population":128
},
  "geometry": {"coordinates":[77.84018500000001,12.486699],"type":"Point"}
}