{
  "type": "Feature",
  "properties": {
    "iso:country":"IN",
    "ks:ks_name":"Chak Gopal",
    "ks:ks_pop":336,
    "ks:ks_type":"VILLAGE",
    "ks:ks_uagg_main":0,
    "name:eng_x_preferred":[
        "Chak Gopal"
    ],
    "wof:name":"Chak Gopal",
    "wof:placetype":"neighbourhood",
    "wof:population":336
},
  "geometry": {"coordinates":[88.962273,25.258441],"type":"Point"}
}