{
  "type": "Feature",
  "properties": {
    "iso:country":"IN",
    "ks:ks_name":"Kadiyavayal",
    "ks:ks_pop":56,
    "ks:ks_type":"HABITATION",
    "name:eng_x_preferred":[
        "Kadiyavayal"
    ],
    "wof:name":"Kadiyavayal",
    "wof:placetype":"locality",
    "wof:population":56
},
  "geometry": {"coordinates":[78.590368,9.75271],"type":"Point"}
}