{
  "type": "Feature",
  "properties": {
    "iso:country":"IN",
    "ks:ks_name":"Dubradi",
    "ks:ks_type":"VILLAGE",
    "name:eng_x_preferred":[
        "Dubradi"
    ],
    "wof:name":"Dubradi",
    "wof:placetype":"locality"
},
  "geometry": {"coordinates":[86.66651299999999,23.505807],"type":"Point"}
}