{
  "type": "Feature",
  "properties": {
    "iso:country":"IN",
    "ks:ks_name":"Ramdev Falia",
    "ks:ks_pop":133,
    "ks:ks_type":"HABITATION",
    "name:eng_x_preferred":[
        "Ramdev Falia"
    ],
    "wof:name":"Ramdev Falia",
    "wof:placetype":"locality",
    "wof:population":133
},
  "geometry": {"coordinates":[73.982389,23.074889],"type":"Point"}
}