{
  "type": "Feature",
  "properties": {
    "iso:country":"IN",
    "ks:ks_alt_nam":"Hemari teron gaon",
    "ks:ks_name":"Hemari Teron Gaon",
    "ks:ks_pop":155,
    "ks:ks_type":"HABITATION",
    "name:eng_x_preferred":[
        "Hemari Teron Gaon"
    ],
    "wof:name":"Hemari Teron Gaon",
    "wof:placetype":"locality",
    "wof:population":155
},
  "geometry": {"coordinates":[93.16465100000001,25.99573],"type":"Point"}
}