{
  "type": "Feature",
  "properties": {
    "gn:admin1_code":"39",
    "gn:admin2_code":"60.0",
    "gn:asciiname":"Bastil",
    "gn:country_code":"IN",
    "gn:dem":1579,
    "gn:feature_class":"P",
    "gn:feature_code":"PPL",
    "gn:name":"B\u0101stil",
    "gn:population":0,
    "gn:timezone":"Asia/Kolkata",
    "iso:country":"IN",
    "wof:name":"Bastil",
    "wof:placetype":"locality"
},
  "geometry": {"coordinates":[77.85566999999998,30.91911],"type":"Point"}
}