{
  "type": "Feature",
  "properties": {
    "iso:country":"IN",
    "ks:ks_name":"Hareti Dugri",
    "ks:ks_pop":25,
    "ks:ks_type":"HABITATION",
    "name:eng_x_preferred":[
        "Hareti Dugri"
    ],
    "wof:name":"Hareti Dugri",
    "wof:placetype":"locality",
    "wof:population":25
},
  "geometry": {"coordinates":[80.15689,29.634757],"type":"Point"}
}