{
  "type": "Feature",
  "properties": {
    "iso:country":"IN",
    "ks:ks_name":"Sumudag",
    "ks:ks_pop":195,
    "ks:ks_type":"HABITATION",
    "name:eng_x_preferred":[
        "Sumudag"
    ],
    "wof:name":"Sumudag",
    "wof:placetype":"locality",
    "wof:population":195
},
  "geometry": {"coordinates":[85.301309,23.570638],"type":"Point"}
}