{
  "type": "Feature",
  "properties": {
    "iso:country":"IN",
    "ks:ks_name":"Barwotola",
    "ks:ks_pop":925,
    "ks:ks_type":"HABITATION",
    "name:eng_x_preferred":[
        "Barwotola"
    ],
    "wof:name":"Barwotola",
    "wof:placetype":"locality",
    "wof:population":925
},
  "geometry": {"coordinates":[83.308618,24.435185],"type":"Point"}
}