{
  "type": "Feature",
  "properties": {
    "iso:country":"IN",
    "ks:ks_name":"Sarpanchpara",
    "ks:ks_pop":146,
    "ks:ks_type":"HABITATION",
    "name:eng_x_preferred":[
        "Sarpanchpara"
    ],
    "wof:name":"Sarpanchpara",
    "wof:placetype":"locality",
    "wof:population":146
},
  "geometry": {"coordinates":[81.826352,19.233131],"type":"Point"}
}