{
  "type": "Feature",
  "properties": {
    "gn:admin1_code":"16",
    "gn:admin2_code":"505.0",
    "gn:asciiname":"Bir Jatamkhora",
    "gn:country_code":"IN",
    "gn:dem":386,
    "gn:feature_class":"P",
    "gn:feature_code":"PPL",
    "gn:name":"B\u012br Jat\u0101mkhora",
    "gn:population":0,
    "gn:timezone":"Asia/Kolkata",
    "iso:country":"IN",
    "wof:name":"Bir Jatamkhora",
    "wof:placetype":"locality"
},
  "geometry": {"coordinates":[78.82868000000001,21.47365],"type":"Point"}
}