{
  "type": "Feature",
  "properties": {
    "gn:admin1_code":"2.0",
    "gn:admin2_code":"544.0",
    "gn:asciiname":"Saravanipalem",
    "gn:country_code":"IN",
    "gn:dem":122,
    "gn:feature_class":"P",
    "gn:feature_code":"PPL",
    "gn:name":"S\u0101ravanip\u0101lem",
    "gn:population":0,
    "gn:timezone":"Asia/Kolkata",
    "iso:country":"IN",
    "ks:ks_name":"Saravani Palem",
    "ks:ks_pop":184,
    "ks:ks_type":"HABITATION",
    "name:eng_x_preferred":[
        "Saravani Palem"
    ],
    "name:eng_x_variant":[
        "Saravanipalem"
    ],
    "wof:name":"Saravani Palem",
    "wof:placetype":"locality",
    "wof:population":184
},
  "geometry": {"coordinates":[83.11445399999999,18.228227],"type":"Point"}
}