{
  "type": "Feature",
  "properties": {
    "gn:admin1_code":"18.0",
    "gn:admin2_code":"296.0",
    "gn:asciiname":"Rangmaw",
    "gn:country_code":"IN",
    "gn:dem":1620,
    "gn:feature_class":"P",
    "gn:feature_code":"PPL",
    "gn:name":"Rangmaw",
    "gn:population":0,
    "gn:timezone":"Asia/Kolkata",
    "iso:country":"IN",
    "wof:name":"Rangmaw",
    "wof:placetype":"locality"
},
  "geometry": {"coordinates":[91.51546,25.37274],"type":"Point"}
}