{
  "type": "Feature",
  "properties": {
    "gn:admin1_code":"34.0",
    "gn:admin2_code":"223.0",
    "gn:asciiname":"Kokraha",
    "gn:country_code":"IN",
    "gn:dem":42,
    "gn:feature_class":"P",
    "gn:feature_code":"PPL",
    "gn:name":"Kokr\u0101ha",
    "gn:population":0,
    "gn:timezone":"Asia/Kolkata",
    "iso:country":"IN",
    "wof:name":"Kokraha",
    "wof:placetype":"locality"
},
  "geometry": {"coordinates":[86.37365,25.69984],"type":"Point"}
}