{
  "type": "Feature",
  "properties": {
    "iso:country":"IN",
    "ks:ks_name":"Saniyadari",
    "ks:ks_pop":2061,
    "ks:ks_type":"VILLAGE",
    "name:eng_x_preferred":[
        "Saniyadari"
    ],
    "wof:name":"Saniyadari",
    "wof:placetype":"locality",
    "wof:population":2061
},
  "geometry": {"coordinates":[73.776717,22.238161],"type":"Point"}
}