{
  "type": "Feature",
  "properties": {
    "gn:admin1_code":"21.0",
    "gn:admin2_code":"398.0",
    "gn:asciiname":"Dalayipeta",
    "gn:country_code":"IN",
    "gn:dem":208,
    "gn:feature_class":"P",
    "gn:feature_code":"PPL",
    "gn:name":"Dal\u0101yipeta",
    "gn:population":0,
    "gn:timezone":"Asia/Kolkata",
    "iso:country":"IN",
    "ks:ks_name":"Daleipeta",
    "ks:ks_pop":43,
    "ks:ks_type":"VILLAGE",
    "name:eng_x_preferred":[
        "Daleipeta"
    ],
    "name:eng_x_variant":[
        "Dalayipeta"
    ],
    "wof:name":"Daleipeta",
    "wof:placetype":"locality",
    "wof:population":43
},
  "geometry": {"coordinates":[83.268721,18.77088],"type":"Point"}
}