{
  "type": "Feature",
  "properties": {
    "gn:admin1_code":"19.0",
    "gn:admin2_code":"571",
    "gn:asciiname":"Hullenhalli",
    "gn:country_code":"IN",
    "gn:dem":833,
    "gn:feature_class":"P",
    "gn:feature_code":"PPL",
    "gn:name":"Hullenhalli",
    "gn:population":0,
    "gn:timezone":"Asia/Kolkata",
    "iso:country":"IN",
    "wof:name":"Hullenhalli",
    "wof:placetype":"locality"
},
  "geometry": {"coordinates":[77.1074,13.23109],"type":"Point"}
}