{
  "type": "Feature",
  "properties": {
    "gn:admin1_code":"2.0",
    "gn:admin2_code":"552.0",
    "gn:asciiname":"Gnanapuram",
    "gn:country_code":"IN",
    "gn:dem":175,
    "gn:feature_class":"P",
    "gn:feature_code":"PPL",
    "gn:name":"Gn\u0101n\u0101p\u016bram",
    "gn:population":0,
    "gn:timezone":"Asia/Kolkata",
    "iso:country":"IN",
    "name:tam_x_preferred":[
        "\u0b9e\u0bbe\u0ba9\u0baa\u0bc1\u0bb0\u0bae\u0bcd"
    ],
    "name:tel_x_preferred":[
        "\u0c1c\u0c4d\u0c1e\u0c3e\u0c28\u0c3e\u0c2a\u0c41\u0c30\u0c02"
    ],
    "wof:name":"Gnanapuram",
    "wof:placetype":"locality"
},
  "geometry": {"coordinates":[78.62824000000001,14.94734],"type":"Point"}
}