{
  "type": "Feature",
  "properties": {
    "iso:country":"IN",
    "ks:ks_alt_nam":"Ayanikkad Road start",
    "ks:ks_name":"Ayanikkad Road Start",
    "ks:ks_pop":778,
    "ks:ks_type":"HABITATION",
    "name:eng_x_preferred":[
        "Ayanikkad Road Start"
    ],
    "wof:name":"Ayanikkad Road Start",
    "wof:placetype":"locality",
    "wof:population":778
},
  "geometry": {"coordinates":[76.127765,10.544069],"type":"Point"}
}