{
  "type": "Feature",
  "properties": {
    "iso:country":"IN",
    "ks:ks_name":"Ghodgaon",
    "ks:ks_pop":303,
    "ks:ks_type":"HABITATION",
    "name:eng_x_preferred":[
        "Ghodgaon"
    ],
    "wof:name":"Ghodgaon",
    "wof:placetype":"locality",
    "wof:population":303
},
  "geometry": {"coordinates":[73.18653399999999,18.593396],"type":"Point"}
}