{
  "type": "Feature",
  "properties": {
    "iso:country":"IN",
    "ks:ks_name":"Urusakani",
    "ks:ks_pop":34,
    "ks:ks_type":"VILLAGE",
    "name:eng_x_preferred":[
        "Urusakani"
    ],
    "wof:name":"Urusakani",
    "wof:placetype":"locality",
    "wof:population":34
},
  "geometry": {"coordinates":[83.434468,19.491002],"type":"Point"}
}