{
  "type": "Feature",
  "properties": {
    "iso:country":"IN",
    "ks:ks_name":"Nallabilli",
    "ks:ks_pop":219,
    "ks:ks_type":"HABITATION",
    "name:eng_x_preferred":[
        "Nallabilli"
    ],
    "wof:name":"Nallabilli",
    "wof:placetype":"locality",
    "wof:population":219
},
  "geometry": {"coordinates":[82.15842000000001,17.77273],"type":"Point"}
}