{
  "type": "Feature",
  "properties": {
    "iso:country":"IN",
    "ks:ks_alt_nam":"Dighir para",
    "ks:ks_name":"Dighir Para",
    "ks:ks_pop":756,
    "ks:ks_type":"HABITATION",
    "ks:ks_uagg_main":0,
    "name:eng_x_preferred":[
        "Dighir Para"
    ],
    "wof:name":"Dighir Para",
    "wof:placetype":"locality",
    "wof:population":756
},
  "geometry": {"coordinates":[88.175798,22.630578],"type":"Point"}
}