{
  "type": "Feature",
  "properties": {
    "gn:admin1_code":"2.0",
    "gn:admin2_code":"542.0",
    "gn:asciiname":"Nayuduguda",
    "gn:country_code":"IN",
    "gn:dem":470,
    "gn:feature_class":"P",
    "gn:feature_code":"PPL",
    "gn:name":"N\u0101yudug\u016bda",
    "gn:population":0,
    "gn:timezone":"Asia/Kolkata",
    "iso:country":"IN",
    "wof:name":"Nayuduguda",
    "wof:placetype":"locality"
},
  "geometry": {"coordinates":[83.85944000000001,18.59773],"type":"Point"}
}