{
  "type": "Feature",
  "properties": {
    "iso:country":"IN",
    "ks:ks_name":"Nawabpeta",
    "ks:ks_pop":346,
    "ks:ks_type":"HABITATION",
    "name:eng_x_preferred":[
        "Nawabpeta"
    ],
    "wof:name":"Nawabpeta",
    "wof:placetype":"locality",
    "wof:population":346
},
  "geometry": {"coordinates":[80.239367,13.82057],"type":"Point"}
}