{
  "type": "Feature",
  "properties": {
    "gn:country":"IN",
    "gn:fcode":"PPL",
    "gn:pop":49114,
    "iso:country":"IN",
    "name:ben_x_preferred":[
        "\u09b8\u09bf\u09a6\u09b2\u09be\u0998\u09be\u09a4\u09cd\u09a4\u09be"
    ],
    "name:bpy_x_preferred":[
        "\u09b8\u09bf\u09a6\u09b2\u09be\u0998\u09be\u09a4\u09cd\u09a4\u09be"
    ],
    "name:deu_x_preferred":[
        "Sidlaghatta"
    ],
    "name:eng_x_preferred":[
        "Sidlaghatta"
    ],
    "name:fra_x_preferred":[
        "Sidlaghatta"
    ],
    "name:guj_x_preferred":[
        "\u0ab8\u0abf\u0aa6\u0ab2\u0abe\u0a98\u0a9f\u0acd\u0a9f\u0abe"
    ],
    "name:ita_x_preferred":[
        "Sidlaghatta"
    ],
    "name:jpn_x_preferred":[
        "\u30b7\u30c9\u30e9\u30ac\u30c3\u30bf"
    ],
    "name:kan_x_preferred":[
        "\u0cb6\u0cbf\u0ca1\u0ccd\u0cb2\u0c98\u0c9f\u0ccd\u0c9f"
    ],
    "name:kor_x_preferred":[
        "\uc2dc\ub4e4\ub77c\ud558\ud0c0"
    ],
    "name:mlg_x_preferred":[
        "Sidlaghatta"
    ],
    "name:msa_x_preferred":[
        "Sidlaghatta"
    ],
    "name:nan_x_preferred":[
        "Sidlaghatta"
    ],
    "name:nld_x_preferred":[
        "Sidlaghatta"
    ],
    "name:ori_x_preferred":[
        "\u0b38\u0b3f\u0b26\u0b32\u0b3e\u0b18\u0b3e\u0b1f"
    ],
    "name:por_x_preferred":[
        "Sidlaghatta"
    ],
    "name:rus_x_preferred":[
        "\u0421\u0438\u0434\u043b\u0430\u0433\u0445\u0430\u0442\u0442\u0430"
    ],
    "name:spa_x_preferred":[
        "Sidlaghatta"
    ],
    "name:swe_x_preferred":[
        "Sidlaghatta Taluk"
    ],
    "name:tam_x_preferred":[
        "\u0b9a\u0bbf\u0b9f\u0bcd\u0bb2\u0b95\u0bbe\u0b9f\u0bcd\u0b9f\u0bbe"
    ],
    "name:tel_x_preferred":[
        "\u0c38\u0c3f\u0c26\u0c4d\u0c32\u0c18\u0c3e\u0c1f\u0c4d"
    ],
    "name:unk_x_variant":[
        "Sidlaghatta"
    ],
    "name:urd_x_preferred":[
        "\u0633\u06cc\u062f\u0644\u0627\u06af\u06be\u0627\u062a\u062a\u0627"
    ],
    "name:vie_x_preferred":[
        "Sidlaghatta"
    ],
    "name:zho_x_preferred":[
        "\u897f\u5fb7\u62c9\u52a0\u7279\u5854"
    ],
    "qs:name":"Nidagatta",
    "qs:name_adm0":"India",
    "qs:name_adm1":"Karnataka",
    "qs:photos_9k":1,
    "qs:photos_9r":1,
    "qs:photos_all":1,
    "qs:photos_sr":0,
    "qs:placetype":"Town",
    "qs:pop_sr":"7",
    "wof:name":"Nidagatta",
    "wof:placetype":"locality",
    "wof:population":49114
},
  "geometry": {"coordinates":[77.86488,13.39141],"type":"Point"}
}