{
  "type": "Feature",
  "properties": {
    "gn:admin1_code":"35.0",
    "gn:admin2_code":"422.0",
    "gn:asciiname":"Bahruka",
    "gn:country_code":"IN",
    "gn:dem":204,
    "gn:feature_class":"P",
    "gn:feature_code":"PPL",
    "gn:name":"Bahr\u016bka",
    "gn:population":0,
    "gn:timezone":"Asia/Kolkata",
    "iso:country":"IN",
    "wof:name":"Bahruka",
    "wof:placetype":"locality"
},
  "geometry": {"coordinates":[78.43167,25.80258],"type":"Point"}
}