{
  "type": "Feature",
  "properties": {
    "gn:admin1_code":"34",
    "gn:admin2_code":"233.0",
    "gn:asciiname":"Darauli",
    "gn:country_code":"IN",
    "gn:dem":78,
    "gn:feature_class":"P",
    "gn:feature_code":"PPL",
    "gn:name":"Darauli",
    "gn:population":0,
    "gn:timezone":"Asia/Kolkata",
    "iso:country":"IN",
    "name:bih_x_preferred":[
        "\u0926\u0930\u094c\u0932\u0940"
    ],
    "name:hin_x_preferred":[
        "\u0926\u0930\u094c\u0932\u0940 \u092a\u094d\u0930\u0916\u0923\u094d\u0921"
    ],
    "wof:name":"Darauli",
    "wof:placetype":"locality"
},
  "geometry": {"coordinates":[83.52332,25.20919],"type":"Point"}
}