{
  "type": "Feature",
  "properties": {
    "iso:country":"IN",
    "ks:ks_name":"Akandakeshari",
    "ks:ks_pop":2532,
    "ks:ks_type":"VILLAGE",
    "ks:ks_uagg_main":0,
    "name:eng_x_preferred":[
        "Akandakeshari"
    ],
    "wof:name":"Akandakeshari",
    "wof:placetype":"locality",
    "wof:population":2532
},
  "geometry": {"coordinates":[88.518838,22.556347],"type":"Point"}
}