{
  "type": "Feature",
  "properties": {
    "iso:country":"IN",
    "ks:ks_name":"Banduguri",
    "ks:ks_pop":71,
    "ks:ks_type":"HABITATION",
    "ks:ks_uagg_main":0,
    "name:eng_x_preferred":[
        "Banduguri"
    ],
    "wof:name":"Banduguri",
    "wof:placetype":"neighbourhood",
    "wof:population":71
},
  "geometry": {"coordinates":[93.179097,26.223342],"type":"Point"}
}