{
  "type": "Feature",
  "properties": {
    "iso:country":"IN",
    "ks:ks_name":"Bhatu Raidih",
    "ks:ks_pop":208,
    "ks:ks_type":"VILLAGE",
    "name:eng_x_preferred":[
        "Bhatu Raidih"
    ],
    "wof:name":"Bhatu Raidih",
    "wof:placetype":"locality",
    "wof:population":208
},
  "geometry": {"coordinates":[86.184652,24.552278],"type":"Point"}
}