{
  "type": "Feature",
  "properties": {
    "gn:admin1_code":"11.0",
    "gn:admin2_code":"33.0",
    "gn:asciiname":"Salaunbag",
    "gn:country_code":"IN",
    "gn:dem":2251,
    "gn:feature_class":"P",
    "gn:feature_code":"PPL",
    "gn:name":"Salaunb\u0101g",
    "gn:population":0,
    "gn:timezone":"Asia/Kolkata",
    "iso:country":"IN",
    "wof:name":"Salaunbag",
    "wof:placetype":"locality"
},
  "geometry": {"coordinates":[77.27056,31.05242],"type":"Point"}
}