{
  "type": "Feature",
  "properties": {
    "gn:admin1_code":"10.0",
    "gn:admin2_code":"84.0",
    "gn:asciiname":"Manpur",
    "gn:country_code":"IN",
    "gn:dem":270,
    "gn:feature_class":"P",
    "gn:feature_code":"PPL",
    "gn:name":"M\u0101npur",
    "gn:population":0,
    "gn:timezone":"Asia/Kolkata",
    "iso:country":"IN",
    "name:ceb_x_preferred":[
        "Manpur"
    ],
    "name:fra_x_preferred":[
        "Manpur"
    ],
    "name:pol_x_preferred":[
        "Manpur"
    ],
    "name:swe_x_preferred":[
        "Manpur"
    ],
    "name:und_x_variant":[
        "M\u0101npur",
        "Korika"
    ],
    "wof:name":"Manpur",
    "wof:placetype":"locality"
},
  "geometry": {"coordinates":[76.34068000000001,28.25181],"type":"Point"}
}