{
  "type": "Feature",
  "properties": {
    "iso:country":"IN",
    "ks:ks_name":"Kesavanipetathanda",
    "ks:ks_pop":151,
    "ks:ks_type":"HABITATION",
    "name:eng_x_preferred":[
        "Kesavanipetathanda"
    ],
    "wof:name":"Kesavanipetathanda",
    "wof:placetype":"locality",
    "wof:population":151
},
  "geometry": {"coordinates":[79.619985,16.109184],"type":"Point"}
}