{
  "type": "Feature",
  "properties": {
    "iso:country":"IN",
    "ks:ks_name":"Bamuntari",
    "ks:ks_pop":1341,
    "ks:ks_type":"HABITATION",
    "ks:ks_uagg_main":0,
    "name:eng_x_preferred":[
        "Bamuntari"
    ],
    "wof:name":"Bamuntari",
    "wof:placetype":"neighbourhood",
    "wof:population":1341
},
  "geometry": {"coordinates":[91.480919,26.293528],"type":"Point"}
}