{
  "type": "Feature",
  "properties": {
    "iso:country":"IN",
    "ks:ks_name":"Rudrappanaickenpatti",
    "ks:ks_pop":285,
    "ks:ks_type":"VILLAGE",
    "name:eng_x_preferred":[
        "Rudrappanaickenpatti"
    ],
    "wof:name":"Rudrappanaickenpatti",
    "wof:placetype":"locality",
    "wof:population":285
},
  "geometry": {"coordinates":[77.75634100000001,9.638294],"type":"Point"}
}