{
  "type": "Feature",
  "properties": {
    "iso:country":"IN",
    "ks:ks_name":"Bachpur",
    "ks:ks_pop":788,
    "ks:ks_type":"VILLAGE",
    "ks:ks_uagg_main":0,
    "name:eng_x_preferred":[
        "Bachpur"
    ],
    "wof:name":"Bachpur",
    "wof:placetype":"neighbourhood",
    "wof:population":788
},
  "geometry": {"coordinates":[88.26994999999999,23.390136],"type":"Point"}
}