{
  "type": "Feature",
  "properties": {
    "gn:admin1_code":"9.0",
    "gn:admin2_code":"486.0",
    "gn:asciiname":"Jamli",
    "gn:country_code":"IN",
    "gn:dem":259,
    "gn:feature_class":"P",
    "gn:feature_code":"PPL",
    "gn:name":"J\u0101mli",
    "gn:population":0,
    "gn:timezone":"Asia/Kolkata",
    "iso:country":"IN",
    "ks:ks_name":"Jamali",
    "ks:ks_pop":937,
    "ks:ks_type":"VILLAGE",
    "name:eng_x_preferred":[
        "Jamali"
    ],
    "name:eng_x_variant":[
        "Jamli"
    ],
    "wof:name":"Jamali",
    "wof:placetype":"locality",
    "wof:population":937
},
  "geometry": {"coordinates":[74.11666,22.060257],"type":"Point"}
}