{
  "type": "Feature",
  "properties": {
    "iso:country":"IN",
    "ks:ks_name":"Bhabanipur",
    "ks:ks_pop":189,
    "ks:ks_type":"VILLAGE",
    "name:eng_x_preferred":[
        "Bhabanipur"
    ],
    "wof:name":"Bhabanipur",
    "wof:placetype":"locality",
    "wof:population":189
},
  "geometry": {"coordinates":[85.29839,19.848489],"type":"Point"}
}