{
  "type": "Feature",
  "properties": {
    "gn:country":"IN",
    "gn:fcode":"PPL",
    "gn:pop":7411,
    "iso:country":"IN",
    "name:ben_x_preferred":[
        "\u099c\u09be\u0996\u09be\u09b2 \u09ae\u09be\u09a8\u09cd\u09a6\u09bf"
    ],
    "name:bpy_x_preferred":[
        "\u099c\u09be\u0996\u09be\u09b2 \u09ae\u09be\u09a8\u09cd\u09a6\u09bf"
    ],
    "name:chi_x_preferred":[
        "\u8d3e\u5361\u5c14\u9a6c\u6069\u8fea"
    ],
    "name:dut_x_preferred":[
        "Jakhal Mandi"
    ],
    "name:eng_x_preferred":[
        "Jakhal Mandi"
    ],
    "name:ita_x_preferred":[
        "Jakhalmandi"
    ],
    "name:may_x_preferred":[
        "Jakhal Mandi"
    ],
    "name:nan_x_preferred":[
        "Jakhal Mandi"
    ],
    "name:new_x_preferred":[
        "\u091c\u0916\u0932 \u092e\u0923\u094d\u0921\u0940"
    ],
    "name:por_x_preferred":[
        "Jakhal Mandi"
    ],
    "name:san_x_preferred":[
        "\u091c\u0916\u0932\u094d \u092e\u0928\u094d\u0926\u093f"
    ],
    "name:swe_x_preferred":[
        "J\u0101khal"
    ],
    "name:unk_x_variant":[
        "Jakhal Mandi"
    ],
    "name:urd_x_preferred":[
        "\u062c\u062e\u0644 \u0645\u0646\u062f\u06cc"
    ],
    "name:vie_x_preferred":[
        "Jakhal Mandi"
    ],
    "qs:name":"J\u0101khal",
    "qs:photos_9r":0,
    "qs:photos_sr":0,
    "qs:pop_sr":"5",
    "wof:name":"J\u0101khal",
    "wof:placetype":"locality",
    "wof:population":7411
},
  "geometry": {"coordinates":[75.82392,29.79627],"type":"Point"}
}