{
  "type": "Feature",
  "properties": {
    "iso:country":"IN",
    "ks:ks_name":"Belhar Mafi",
    "ks:ks_pop":480,
    "ks:ks_type":"VILLAGE",
    "name:eng_x_preferred":[
        "Belhar Mafi"
    ],
    "wof:name":"Belhar Mafi",
    "wof:placetype":"locality",
    "wof:population":480
},
  "geometry": {"coordinates":[83.23404600000001,26.775891],"type":"Point"}
}