{
  "type": "Feature",
  "properties": {
    "gn:admin1_code":"36.0",
    "gn:admin2_code":"134.0",
    "gn:asciiname":"Bhangarwala",
    "gn:country_code":"IN",
    "gn:dem":244,
    "gn:feature_class":"P",
    "gn:feature_code":"PPL",
    "gn:name":"Bhangarw\u0101la",
    "gn:population":0,
    "gn:timezone":"Asia/Kolkata",
    "iso:country":"IN",
    "name:und_x_variant":[
        "Bhangarw\u0101la",
        "Daulatpur"
    ],
    "wof:name":"Bhangarwala",
    "wof:placetype":"locality"
},
  "geometry": {"coordinates":[78.72138000000002,29.40142],"type":"Point"}
}