{
  "type": "Feature",
  "properties": {
    "iso:country":"IN",
    "ks:ks_name":"Robratoli",
    "ks:ks_pop":91,
    "ks:ks_type":"HABITATION",
    "name:eng_x_preferred":[
        "Robratoli"
    ],
    "wof:name":"Robratoli",
    "wof:placetype":"locality",
    "wof:population":91
},
  "geometry": {"coordinates":[85.368759,22.870124],"type":"Point"}
}