{
  "type": "Feature",
  "properties": {
    "iso:country":"IN",
    "ks:ks_name":"Ghawdetola",
    "ks:ks_pop":28,
    "ks:ks_type":"HABITATION",
    "name:eng_x_preferred":[
        "Ghawdetola"
    ],
    "wof:name":"Ghawdetola",
    "wof:placetype":"locality",
    "wof:population":28
},
  "geometry": {"coordinates":[80.639439,20.638713],"type":"Point"}
}