{
  "type": "Feature",
  "properties": {
    "iso:country":"IN",
    "ks:ks_alt_nam":"letwa",
    "ks:ks_name":"Letwa",
    "ks:ks_pop":213,
    "ks:ks_type":"HABITATION",
    "name:eng_x_preferred":[
        "Letwa"
    ],
    "wof:name":"Letwa",
    "wof:placetype":"locality",
    "wof:population":213
},
  "geometry": {"coordinates":[86.76827299999999,24.580499],"type":"Point"}
}