{
  "type": "Feature",
  "properties": {
    "iso:country":"IN",
    "ks:ks_alt_nam":"Basitha laxminia",
    "ks:ks_name":"Basitha Laxminia",
    "ks:ks_pop":899,
    "ks:ks_type":"HABITATION",
    "name:eng_x_preferred":[
        "Basitha Laxminia"
    ],
    "wof:name":"Basitha Laxminia",
    "wof:placetype":"locality",
    "wof:population":899
},
  "geometry": {"coordinates":[87.054984,25.5126],"type":"Point"}
}