{
  "type": "Feature",
  "properties": {
    "iso:country":"IN",
    "ks:ks_alt_nam":"koilthoppu",
    "ks:ks_name":"Koilthoppu",
    "ks:ks_pop":628,
    "ks:ks_type":"HABITATION",
    "name:eng_x_preferred":[
        "Koilthoppu"
    ],
    "wof:name":"Koilthoppu",
    "wof:placetype":"locality",
    "wof:population":628
},
  "geometry": {"coordinates":[79.63225300000001,10.517261],"type":"Point"}
}