{
  "type": "Feature",
  "properties": {
    "iso:country":"IN",
    "ks:ks_name":"Srinivas Camp",
    "ks:ks_pop":650,
    "ks:ks_type":"HABITATION",
    "name:eng_x_preferred":[
        "Srinivas Camp"
    ],
    "wof:name":"Srinivas Camp",
    "wof:placetype":"locality",
    "wof:population":650
},
  "geometry": {"coordinates":[76.97317700000001,16.080992],"type":"Point"}
}