{
  "type": "Feature",
  "properties": {
    "gn:admin1_code":"10.0",
    "gn:admin2_code":"81.0",
    "gn:asciiname":"Mirch",
    "gn:country_code":"IN",
    "gn:dem":215,
    "gn:feature_class":"P",
    "gn:feature_code":"PPL",
    "gn:name":"Mirch",
    "gn:population":0,
    "gn:timezone":"Asia/Kolkata",
    "iso:country":"IN",
    "name:hin_x_preferred":[
        "\u092e\u093f\u0930\u094d\u091a"
    ],
    "wof:name":"Mirch",
    "wof:placetype":"locality"
},
  "geometry": {"coordinates":[76.26196999999998,28.6484],"type":"Point"}
}