{
  "type": "Feature",
  "properties": {
    "gn:country":"IN",
    "gn:fcode":"PPL",
    "gn:population":0,
    "iso:country":"IN",
    "name:ara_x_preferred":[
        "\u0645\u0648\u0644\u0627\u0634\u064a\u0631\u064a"
    ],
    "name:ben_bn_x_preferred":[
        "\u09ae\u09c1\u09b2\u09be\u099a\u09c7\u09b0\u09bf"
    ],
    "name:ben_in_x_preferred":[
        "\u09ae\u09c1\u09b2\u09be\u099a\u09c7\u09b0\u09bf"
    ],
    "name:guj_x_preferred":[
        "\u0aae\u0ac2\u0ab2\u0abe\u0a9a\u0ac7\u0ab0\u0ac0"
    ],
    "name:hin_x_preferred":[
        "\u092e\u0942\u0932\u093e\u091a\u0947\u0930\u0940"
    ],
    "name:kan_x_preferred":[
        "\u0cae\u0cc2\u0cb2\u0c9a\u0cc6\u0cb0\u0cbf"
    ],
    "name:mal_x_preferred":[
        "\u0d2e\u0d42\u0d32\u0d1a\u0d47\u0d30\u0d3f"
    ],
    "name:mar_x_preferred":[
        "\u092e\u0942\u0932\u091a\u0947\u0930\u0940"
    ],
    "name:pan_x_preferred":[
        "\u0a2e\u0a42\u0a32\u0a3e\u0a1a\u0a47\u0a30\u0a40"
    ],
    "name:tam_x_preferred":[
        "\u0bae\u0bc2\u0bb2\u0b9a\u0bcd\u0b9a\u0bc7\u0bb0\u0bbf"
    ],
    "name:tel_x_preferred":[
        "\u0c2e\u0c42\u0c32\u0c3e\u0c1a\u0c46\u0c30\u0c3f"
    ],
    "name:urd_x_preferred":[
        "\u0645\u0648\u0644\u0627\u0686\u06cc\u0631\u06cc"
    ],
    "qs:name":"Moolacheri",
    "qs:name_adm0":"India",
    "qs:name_adm1":"Tamil Nadu",
    "qs:photos":1,
    "qs:photos_1k":1,
    "qs:photos_9k":1,
    "qs:photos_9r":1,
    "qs:photos_all":1,
    "qs:photos_sr":1,
    "qs:placetype":"Suburb",
    "qs:pop_sr":"0",
    "wof:name":"Moolacheri",
    "wof:placetype":"neighbourhood",
    "wof:population":0
},
  "geometry": {"coordinates":[80.17376,12.85619],"type":"Point"}
}