{
  "type": "Feature",
  "properties": {
    "gn:admin1_code":"19.0",
    "gn:admin2_code":"563.0",
    "gn:asciiname":"Bennehalli",
    "gn:country_code":"IN",
    "gn:dem":506,
    "gn:feature_class":"P",
    "gn:feature_code":"PPL",
    "gn:name":"Bennehalli",
    "gn:population":0,
    "gn:timezone":"Asia/Kolkata",
    "iso:country":"IN",
    "ks:ks_name":"Bennalli",
    "ks:ks_pop":16,
    "ks:ks_type":"HABITATION",
    "name:eng_x_preferred":[
        "Bennalli"
    ],
    "name:eng_x_variant":[
        "Bennehalli"
    ],
    "wof:name":"Bennalli",
    "wof:placetype":"locality",
    "wof:population":16
},
  "geometry": {"coordinates":[74.733199,14.42059],"type":"Point"}
}