{
  "type": "Feature",
  "properties": {
    "gn:admin1_code":"39",
    "gn:admin2_code":"61.0",
    "gn:asciiname":"Pokhri",
    "gn:country_code":"IN",
    "gn:dem":1394,
    "gn:feature_class":"P",
    "gn:feature_code":"PPL",
    "gn:name":"Pokhri",
    "gn:population":0,
    "gn:timezone":"Asia/Kolkata",
    "iso:country":"IN",
    "wof:name":"Pokhri",
    "wof:placetype":"locality"
},
  "geometry": {"coordinates":[78.81033000000002,30.15911],"type":"Point"}
}