{
  "type": "Feature",
  "properties": {
    "iso:country":"IN",
    "ks:ks_name":"Banoli Malli",
    "ks:ks_pop":94,
    "ks:ks_type":"VILLAGE",
    "name:eng_x_preferred":[
        "Banoli Malli"
    ],
    "wof:name":"Banoli Malli",
    "wof:placetype":"locality",
    "wof:population":94
},
  "geometry": {"coordinates":[78.40617899999999,30.219019],"type":"Point"}
}