{
  "type": "Feature",
  "properties": {
    "gn:admin1_code":"36.0",
    "gn:admin2_code":"175.0",
    "gn:asciiname":"Austapur Muhammadabad",
    "gn:country_code":"IN",
    "gn:dem":98,
    "gn:feature_class":"P",
    "gn:feature_code":"PPL",
    "gn:name":"Aust\u0101pur Muhammad\u0101b\u0101d",
    "gn:population":0,
    "gn:timezone":"Asia/Kolkata",
    "iso:country":"IN",
    "wof:name":"Austapur Muhammadabad",
    "wof:placetype":"neighbourhood"
},
  "geometry": {"coordinates":[81.92747,25.40016],"type":"Point"}
}