{
  "type": "Feature",
  "properties": {
    "iso:country":"IN",
    "ks:ks_name":"Lajbaimata",
    "ks:ks_pop":928,
    "ks:ks_type":"HABITATION",
    "name:eng_x_preferred":[
        "Lajbaimata"
    ],
    "wof:name":"Lajbaimata",
    "wof:placetype":"locality",
    "wof:population":928
},
  "geometry": {"coordinates":[72.990583,22.50425],"type":"Point"}
}