{
  "type": "Feature",
  "properties": {
    "iso:country":"IN",
    "ks:ks_name":"Lower Tola",
    "ks:ks_pop":65,
    "ks:ks_type":"HABITATION",
    "name:eng_x_preferred":[
        "Lower Tola"
    ],
    "wof:name":"Lower Tola",
    "wof:placetype":"locality",
    "wof:population":65
},
  "geometry": {"coordinates":[86.49177299999999,24.498441],"type":"Point"}
}