{
  "type": "Feature",
  "properties": {
    "gn:admin1_code":"12.0",
    "gn:asciiname":"Parar",
    "gn:country_code":"IN",
    "gn:dem":535,
    "gn:feature_class":"P",
    "gn:feature_code":"PPL",
    "gn:name":"Par\u0101r",
    "gn:population":0,
    "gn:timezone":"Asia/Kolkata",
    "iso:country":"IN",
    "name:und_x_variant":[
        "Par\u0101r",
        "P\u0101r\u0101r"
    ],
    "wof:name":"Parar",
    "wof:placetype":"locality"
},
  "geometry": {"coordinates":[74.49689000000002,32.96775],"type":"Point"}
}