{
  "type": "Feature",
  "properties": {
    "iso:country":"IN",
    "ks:ks_name":"Chauktangra",
    "ks:ks_pop":331,
    "ks:ks_type":"HABITATION",
    "name:eng_x_preferred":[
        "Chauktangra"
    ],
    "wof:name":"Chauktangra",
    "wof:placetype":"locality",
    "wof:population":331
},
  "geometry": {"coordinates":[84.638666,22.863126],"type":"Point"}
}