{
  "type": "Feature",
  "properties": {
    "gn:admin1_code":"12.0",
    "gn:admin2_code":"021",
    "gn:asciiname":"Barmhal",
    "gn:country_code":"IN",
    "gn:dem":278,
    "gn:feature_class":"P",
    "gn:feature_code":"PPL",
    "gn:name":"Barmh\u0101l",
    "gn:population":0,
    "gn:timezone":"Asia/Kolkata",
    "iso:country":"IN",
    "name:und_x_variant":[
        "Barmh\u0101l",
        "Bamn\u0101l"
    ],
    "wof:name":"Barmhal",
    "wof:placetype":"locality"
},
  "geometry": {"coordinates":[74.87523,32.549],"type":"Point"}
}