{
  "type": "Feature",
  "properties": {
    "iso:country":"IN",
    "ks:ks_name":"Dalurbond",
    "ks:ks_pop":646,
    "ks:ks_type":"VILLAGE",
    "name:eng_x_preferred":[
        "Dalurbond"
    ],
    "wof:name":"Dalurbond",
    "wof:placetype":"locality",
    "wof:population":646
},
  "geometry": {"coordinates":[92.46280299999999,24.626845],"type":"Point"}
}