{
  "type": "Feature",
  "properties": {
    "iso:country":"IN",
    "ks:ks_name":"Kulabeda",
    "ks:ks_pop":441,
    "ks:ks_type":"HABITATION",
    "name:eng_x_preferred":[
        "Kulabeda"
    ],
    "wof:name":"Kulabeda",
    "wof:placetype":"locality",
    "wof:population":441
},
  "geometry": {"coordinates":[82.226991,18.661196],"type":"Point"}
}