{
  "type": "Feature",
  "properties": {
    "iso:country":"IN",
    "ks:ks_name":"Bhikhapur",
    "ks:ks_pop":331,
    "ks:ks_type":"VILLAGE",
    "name:eng_x_preferred":[
        "Bhikhapur"
    ],
    "wof:name":"Bhikhapur",
    "wof:placetype":"locality",
    "wof:population":331
},
  "geometry": {"coordinates":[83.14107199999999,25.311558],"type":"Point"}
}