{
  "type": "Feature",
  "properties": {
    "iso:country":"IN",
    "ks:ks_alt_nam":"\u0100lw\u0101rkarkulam",
    "ks:ks_name":"Alwarkarkulam",
    "ks:ks_pop":1632,
    "ks:ks_type":"VILLAGE",
    "name:eng_x_preferred":[
        "Alwarkarkulam"
    ],
    "name:eng_x_variant":[
        "\u0100lw\u0101rkarkulam"
    ],
    "wof:name":"Alwarkarkulam",
    "wof:placetype":"locality",
    "wof:population":1632
},
  "geometry": {"coordinates":[77.88198300000001,8.6554],"type":"Point"}
}