{
  "type": "Feature",
  "properties": {
    "gn:admin1_code":"36",
    "gn:admin2_code":"200.0",
    "gn:asciiname":"Patkhirna",
    "gn:country_code":"IN",
    "gn:dem":314,
    "gn:feature_class":"P",
    "gn:feature_code":"PPL",
    "gn:name":"Patkhirna",
    "gn:population":0,
    "gn:timezone":"Asia/Kolkata",
    "iso:country":"IN",
    "ks:ks_name":"Patkhirana",
    "ks:ks_pop":365,
    "ks:ks_type":"VILLAGE",
    "name:eng_x_preferred":[
        "Patkhirana"
    ],
    "name:eng_x_variant":[
        "Patkhirna"
    ],
    "wof:name":"Patkhirana",
    "wof:placetype":"locality",
    "wof:population":365
},
  "geometry": {"coordinates":[82.952039,24.041642],"type":"Point"}
}