{
  "type": "Feature",
  "properties": {
    "iso:country":"IN",
    "ks:ks_name":"Madurli",
    "ks:ks_pop":60,
    "ks:ks_type":"HABITATION",
    "name:eng_x_preferred":[
        "Madurli"
    ],
    "wof:name":"Madurli",
    "wof:placetype":"locality",
    "wof:population":60
},
  "geometry": {"coordinates":[74.38350800000001,15.124922],"type":"Point"}
}