{
  "type": "Feature",
  "properties": {
    "gn:admin1_code":"34",
    "gn:admin2_code":"233.0",
    "gn:asciiname":"Neurus",
    "gn:country_code":"IN",
    "gn:dem":518,
    "gn:feature_class":"P",
    "gn:feature_code":"PPL",
    "gn:name":"Neurus",
    "gn:population":0,
    "gn:timezone":"Asia/Kolkata",
    "iso:country":"IN",
    "ks:ks_name":"Neurus",
    "ks:ks_pop":188,
    "ks:ks_type":"VILLAGE",
    "name:eng_x_preferred":[
        "Neurus"
    ],
    "wof:name":"Neurus",
    "wof:placetype":"locality",
    "wof:population":188
},
  "geometry": {"coordinates":[83.690836,24.630831],"type":"Point"}
}