{
  "type": "Feature",
  "properties": {
    "iso:country":"IN",
    "ks:ks_name":"Anipevaripeta",
    "ks:ks_pop":201,
    "ks:ks_type":"HABITATION",
    "name:eng_x_preferred":[
        "Anipevaripeta"
    ],
    "wof:name":"Anipevaripeta",
    "wof:placetype":"locality",
    "wof:population":201
},
  "geometry": {"coordinates":[81.932113,16.668881],"type":"Point"}
}