{
  "type": "Feature",
  "properties": {
    "iso:country":"IN",
    "ks:ks_name":"Dehberri",
    "ks:ks_pop":89,
    "ks:ks_type":"VILLAGE",
    "ks:ks_uagg_main":0,
    "name:eng_x_preferred":[
        "Dehberri"
    ],
    "wof:name":"Dehberri",
    "wof:placetype":"neighbourhood",
    "wof:population":89
},
  "geometry": {"coordinates":[85.435728,24.73032],"type":"Point"}
}