{
  "type": "Feature",
  "properties": {
    "iso:country":"IN",
    "ks:ks_alt_nam":"PALISAI",
    "ks:ks_name":"Palisai",
    "ks:ks_pop":675,
    "ks:ks_type":"HABITATION",
    "name:eng_x_preferred":[
        "Palisai"
    ],
    "wof:name":"Palisai",
    "wof:placetype":"locality",
    "wof:population":675
},
  "geometry": {"coordinates":[85.59054,22.409891],"type":"Point"}
}