{
  "type": "Feature",
  "properties": {
    "iso:country":"IN",
    "ks:ks_name":"Shitamaki",
    "ks:ks_pop":325,
    "ks:ks_type":"HABITATION",
    "name:eng_x_preferred":[
        "Shitamaki"
    ],
    "wof:name":"Shitamaki",
    "wof:placetype":"locality",
    "wof:population":325
},
  "geometry": {"coordinates":[74.30235500000001,14.842382],"type":"Point"}
}