{
  "type": "Feature",
  "properties": {
    "iso:country":"IN",
    "ks:ks_name":"Nakargundi",
    "ks:ks_pop":844,
    "ks:ks_type":"VILLAGE",
    "name:eng_x_preferred":[
        "Nakargundi"
    ],
    "wof:name":"Nakargundi",
    "wof:placetype":"locality",
    "wof:population":844
},
  "geometry": {"coordinates":[75.66078899999999,16.217764],"type":"Point"}
}