{
  "type": "Feature",
  "properties": {
    "iso:country":"IN",
    "ks:ks_name":"Goli",
    "ks:ks_pop":158,
    "ks:ks_type":"VILLAGE",
    "name:eng_x_preferred":[
        "Goli"
    ],
    "wof:name":"Goli",
    "wof:placetype":"locality",
    "wof:population":158
},
  "geometry": {"coordinates":[86.114183,24.729659],"type":"Point"}
}