{
  "type": "Feature",
  "properties": {
    "iso:country":"IN",
    "ks:ks_name":"Kasiyaghola",
    "ks:ks_pop":527,
    "ks:ks_type":"HABITATION",
    "name:eng_x_preferred":[
        "Kasiyaghola"
    ],
    "wof:name":"Kasiyaghola",
    "wof:placetype":"locality",
    "wof:population":527
},
  "geometry": {"coordinates":[73.61408299999999,22.6694],"type":"Point"}
}