{
  "type": "Feature",
  "properties": {
    "iso:country":"IN",
    "ks:ks_name":"Ramnagar Urf Rampura",
    "ks:ks_pop":460,
    "ks:ks_type":"VILLAGE",
    "ks:ks_uagg_main":0,
    "name:eng_x_preferred":[
        "Ramnagar Urf Rampura"
    ],
    "wof:name":"Ramnagar Urf Rampura",
    "wof:placetype":"neighbourhood",
    "wof:population":460
},
  "geometry": {"coordinates":[78.62352300000001,28.987688],"type":"Point"}
}