{
  "type": "Feature",
  "properties": {
    "iso:country":"IN",
    "ks:ks_name":"Borkundiya",
    "ks:ks_pop":2040,
    "ks:ks_type":"VILLAGE",
    "name:eng_x_preferred":[
        "Borkundiya"
    ],
    "wof:name":"Borkundiya",
    "wof:placetype":"locality",
    "wof:population":2040
},
  "geometry": {"coordinates":[74.26686599999999,22.583218],"type":"Point"}
}