{
  "type": "Feature",
  "properties": {
    "gn:admin1_code":"37.0",
    "gn:admin2_code":"409.0",
    "gn:asciiname":"Tedi",
    "gn:country_code":"IN",
    "gn:dem":300,
    "gn:feature_class":"P",
    "gn:feature_code":"PPL",
    "gn:name":"Tedi",
    "gn:population":0,
    "gn:timezone":"Asia/Kolkata",
    "iso:country":"IN",
    "name:fra_x_preferred":[
        "Tedi"
    ],
    "name:sqi_x_preferred":[
        "Tedi"
    ],
    "wof:name":"Tedi",
    "wof:placetype":"locality"
},
  "geometry": {"coordinates":[81.29316999999998,21.75546],"type":"Point"}
}