{
  "type": "Feature",
  "properties": {
    "iso:country":"IN",
    "ks:ks_name":"Kalipadar",
    "ks:ks_pop":145,
    "ks:ks_type":"HABITATION",
    "name:eng_x_preferred":[
        "Kalipadar"
    ],
    "wof:name":"Kalipadar",
    "wof:placetype":"locality",
    "wof:population":145
},
  "geometry": {"coordinates":[84.701978,20.322169],"type":"Point"}
}