{
  "type": "Feature",
  "properties": {
    "iso:country":"IN",
    "ks:ks_name":"Menasinasara",
    "ks:ks_pop":115,
    "ks:ks_type":"HABITATION",
    "name:eng_x_preferred":[
        "Menasinasara"
    ],
    "wof:name":"Menasinasara",
    "wof:placetype":"locality",
    "wof:population":115
},
  "geometry": {"coordinates":[75.261135,14.080586],"type":"Point"}
}