{
  "type": "Feature",
  "properties": {
    "gn:admin1_code":"2.0",
    "gn:admin2_code":"553.0",
    "gn:asciiname":"Muddanapalle",
    "gn:country_code":"IN",
    "gn:dem":347,
    "gn:feature_class":"P",
    "gn:feature_code":"PPL",
    "gn:name":"Muddanapalle",
    "gn:population":0,
    "gn:timezone":"Asia/Kolkata",
    "iso:country":"IN",
    "wof:name":"Muddanapalle",
    "wof:placetype":"locality"
},
  "geometry": {"coordinates":[77.88724000000001,14.41106],"type":"Point"}
}