{
  "type": "Feature",
  "properties": {
    "iso:country":"IN",
    "ks:ks_name":"Doom Pathar",
    "ks:ks_pop":1124,
    "ks:ks_type":"VILLAGE",
    "name:eng_x_preferred":[
        "Doom Pathar"
    ],
    "wof:name":"Doom Pathar",
    "wof:placetype":"locality",
    "wof:population":1124
},
  "geometry": {"coordinates":[95.77354800000001,27.859997],"type":"Point"}
}