{
  "type": "Feature",
  "properties": {
    "iso:country":"IN",
    "ks:ks_name":"Daiyawara",
    "ks:ks_pop":518,
    "ks:ks_type":"HABITATION",
    "name:eng_x_preferred":[
        "Daiyawara"
    ],
    "wof:name":"Daiyawara",
    "wof:placetype":"locality",
    "wof:population":518
},
  "geometry": {"coordinates":[73.501147,24.005517],"type":"Point"}
}