{
  "type": "Feature",
  "properties": {
    "gn:admin1_code":"19.0",
    "gn:admin2_code":"574.0",
    "gn:asciiname":"Kumarhalli",
    "gn:country_code":"IN",
    "gn:dem":980,
    "gn:feature_class":"P",
    "gn:feature_code":"PPL",
    "gn:name":"Kumarhalli",
    "gn:population":0,
    "gn:timezone":"Asia/Kolkata",
    "iso:country":"IN",
    "ks:ks_name":"Kumarhalli",
    "ks:ks_type":"VILLAGE",
    "name:eng_x_preferred":[
        "Kumarhalli"
    ],
    "wof:name":"Kumarhalli",
    "wof:placetype":"locality"
},
  "geometry": {"coordinates":[75.63279799999999,12.974618],"type":"Point"}
}