{
  "type": "Feature",
  "properties": {
    "gn:admin1_code":"19.0",
    "gn:admin2_code":"574.0",
    "gn:asciiname":"Kumarhalli",
    "gn:country_code":"IN",
    "gn:dem":980,
    "gn:feature_class":"P",
    "gn:feature_code":"PPL",
    "gn:name":"Kumarhalli",
    "gn:population":0,
    "gn:timezone":"Asia/Kolkata",
    "iso:country":"IN",
    "wof:name":"Kumarhalli",
    "wof:placetype":"locality"
},
  "geometry": {"coordinates":[75.6328,12.97462],"type":"Point"}
}