{
  "type": "Feature",
  "properties": {
    "iso:country":"IN",
    "ks:ks_name":"Tenginjeddi",
    "ks:ks_pop":22,
    "ks:ks_type":"HABITATION",
    "name:eng_x_preferred":[
        "Tenginjeddi"
    ],
    "wof:name":"Tenginjeddi",
    "wof:placetype":"locality",
    "wof:population":22
},
  "geometry": {"coordinates":[74.69892,14.881521],"type":"Point"}
}