{
  "type": "Feature",
  "properties": {
    "iso:country":"IN",
    "ks:ks_name":"Muktiram Chowdhury Para",
    "ks:ks_pop":139,
    "ks:ks_type":"HABITATION",
    "name:eng_x_preferred":[
        "Muktiram Chowdhury Para"
    ],
    "wof:name":"Muktiram Chowdhury Para",
    "wof:placetype":"locality",
    "wof:population":139
},
  "geometry": {"coordinates":[92.078885,23.753619],"type":"Point"}
}