{
  "type": "Feature",
  "properties": {
    "iso:country":"IN",
    "ks:ks_name":"Hb",
    "ks:ks_pop":195,
    "ks:ks_type":"HABITATION",
    "ks:ks_uagg_main":0,
    "name:eng_x_preferred":[
        "Hb"
    ],
    "wof:name":"Hb",
    "wof:placetype":"neighbourhood",
    "wof:population":195
},
  "geometry": {"coordinates":[82.975919,25.833461],"type":"Point"}
}