{
  "type": "Feature",
  "properties": {
    "iso:country":"IN",
    "ks:ks_name":"Avanam",
    "ks:ks_pop":142,
    "ks:ks_type":"VILLAGE",
    "ks:ks_uagg_main":0,
    "name:eng_x_preferred":[
        "Avanam"
    ],
    "wof:name":"Avanam",
    "wof:placetype":"neighbourhood",
    "wof:population":142
},
  "geometry": {"coordinates":[79.118256,10.329566],"type":"Point"}
}