{
  "type": "Feature",
  "properties": {
    "iso:country":"IN",
    "ks:ks_name":"8 KD",
    "ks:ks_pop":331,
    "ks:ks_type":"VILLAGE",
    "name:eng_x_preferred":[
        "8 KD"
    ],
    "wof:name":"8 KD",
    "wof:placetype":"locality",
    "wof:population":331
},
  "geometry": {"coordinates":[72.90412000000001,28.890892],"type":"Point"}
}