{
  "type": "Feature",
  "properties": {
    "iso:country":"IN",
    "ks:ks_alt_nam":"K. kesupuram",
    "ks:ks_name":"K. Kesupuram",
    "ks:ks_pop":88,
    "ks:ks_type":"HABITATION",
    "name:eng_x_preferred":[
        "K. Kesupuram"
    ],
    "wof:name":"K. Kesupuram",
    "wof:placetype":"locality",
    "wof:population":88
},
  "geometry": {"coordinates":[84.501077,18.820632],"type":"Point"}
}