{
  "type": "Feature",
  "properties": {
    "gn:admin1_code":"13.0",
    "gn:admin2_code":"593.0",
    "gn:asciiname":"Yedavani",
    "gn:country_code":"IN",
    "gn:dem":847,
    "gn:feature_class":"P",
    "gn:feature_code":"PPL",
    "gn:name":"Yedavani",
    "gn:population":0,
    "gn:timezone":"Asia/Kolkata",
    "iso:country":"IN",
    "wof:name":"Yedavani",
    "wof:placetype":"locality"
},
  "geometry": {"coordinates":[76.58305,11.14407],"type":"Point"}
}