{
  "type": "Feature",
  "properties": {
    "iso:country":"IN",
    "ks:ks_name":"Dughdha",
    "ks:ks_pop":855,
    "ks:ks_type":"VILLAGE",
    "name:eng_x_preferred":[
        "Dughdha"
    ],
    "wof:name":"Dughdha",
    "wof:placetype":"locality",
    "wof:population":855
},
  "geometry": {"coordinates":[73.930446,21.993555],"type":"Point"}
}