{
  "type": "Feature",
  "properties": {
    "gn:admin1_code":"13.0",
    "gn:admin2_code":"593.0",
    "gn:asciiname":"Chekkod",
    "gn:country_code":"IN",
    "gn:dem":38,
    "gn:feature_class":"P",
    "gn:feature_code":"PPL",
    "gn:name":"Ch\u0113kk\u014dd",
    "gn:population":0,
    "gn:timezone":"Asia/Kolkata",
    "iso:country":"IN",
    "ks:ks_name":"Chekkode",
    "ks:ks_pop":2817,
    "ks:ks_type":"HABITATION",
    "name:eng_x_preferred":[
        "Chekkode"
    ],
    "name:eng_x_variant":[
        "Chekkod"
    ],
    "wof:name":"Chekkode",
    "wof:placetype":"locality",
    "wof:population":2817
},
  "geometry": {"coordinates":[76.063965,10.803137],"type":"Point"}
}