{
  "type": "Feature",
  "properties": {
    "iso:country":"IN",
    "ks:ks_name":"Rawani Tola",
    "ks:ks_pop":411,
    "ks:ks_type":"HABITATION",
    "name:eng_x_preferred":[
        "Rawani Tola"
    ],
    "wof:name":"Rawani Tola",
    "wof:placetype":"locality",
    "wof:population":411
},
  "geometry": {"coordinates":[86.15942200000001,24.58277],"type":"Point"}
}