{
  "type": "Feature",
  "properties": {
    "iso:country":"IN",
    "ks:ks_name":"Upper Lamagaon",
    "ks:ks_pop":1014,
    "ks:ks_type":"HABITATION",
    "name:eng_x_preferred":[
        "Upper Lamagaon"
    ],
    "wof:name":"Upper Lamagaon",
    "wof:placetype":"locality",
    "wof:population":1014
},
  "geometry": {"coordinates":[88.1431,27.061018],"type":"Point"}
}