{
  "type": "Feature",
  "properties": {
    "iso:country":"IN",
    "ks:ks_name":"Kattur",
    "ks:ks_pop":17574,
    "ks:ks_type":"VILLAGE",
    "name:eng_x_preferred":[
        "Kattur"
    ],
    "wof:name":"Kattur",
    "wof:placetype":"locality",
    "wof:population":17574
},
  "geometry": {"coordinates":[76.159865,10.383356],"type":"Point"}
}