{
  "type": "Feature",
  "properties": {
    "iso:country":"IN",
    "ks:ks_name":"Milan Sangha Pally",
    "ks:ks_pop":1253,
    "ks:ks_type":"HABITATION",
    "name:eng_x_preferred":[
        "Milan Sangha Pally"
    ],
    "wof:name":"Milan Sangha Pally",
    "wof:placetype":"locality",
    "wof:population":1253
},
  "geometry": {"coordinates":[88.436233,21.871242],"type":"Point"}
}