{
  "type": "Feature",
  "properties": {
    "gn:admin1_code":"36.0",
    "gn:admin2_code":"177.0",
    "gn:asciiname":"Purwa Prag",
    "gn:country_code":"IN",
    "gn:dem":110,
    "gn:feature_class":"P",
    "gn:feature_code":"PPL",
    "gn:name":"Purwa Pr\u0101g",
    "gn:population":0,
    "gn:timezone":"Asia/Kolkata",
    "iso:country":"IN",
    "wof:name":"Purwa Prag",
    "wof:placetype":"neighbourhood"
},
  "geometry": {"coordinates":[82.02307,26.58591],"type":"Point"}
}