{
  "type": "Feature",
  "properties": {
    "iso:country":"IN",
    "ks:ks_name":"Altor",
    "ks:ks_pop":926,
    "ks:ks_type":"VILLAGE",
    "name:eng_x_preferred":[
        "Altor"
    ],
    "wof:name":"Altor",
    "wof:placetype":"locality",
    "wof:population":926
},
  "geometry": {"coordinates":[88.30010900000001,25.168388],"type":"Point"}
}