{
  "type": "Feature",
  "properties": {
    "iso:country":"IN",
    "ks:ks_name":"Kalautia",
    "ks:ks_pop":62,
    "ks:ks_type":"HABITATION",
    "name:eng_x_preferred":[
        "Kalautia"
    ],
    "wof:name":"Kalautia",
    "wof:placetype":"locality",
    "wof:population":62
},
  "geometry": {"coordinates":[79.55987500000001,29.653851],"type":"Point"}
}