{
  "type": "Feature",
  "properties": {
    "iso:country":"IN",
    "ks:ks_name":"Chandradhwajapur",
    "ks:ks_pop":605,
    "ks:ks_type":"VILLAGE",
    "ks:ks_uagg_main":0,
    "name:eng_x_preferred":[
        "Chandradhwajapur"
    ],
    "wof:name":"Chandradhwajapur",
    "wof:placetype":"neighbourhood",
    "wof:population":605
},
  "geometry": {"coordinates":[86.41762300000001,20.284485],"type":"Point"}
}