{
  "type": "Feature",
  "properties": {
    "iso:country":"IN",
    "ks:ks_name":"Sukhatanbag",
    "ks:ks_pop":714,
    "ks:ks_type":"HABITATION",
    "name:eng_x_preferred":[
        "Sukhatanbag"
    ],
    "wof:name":"Sukhatanbag",
    "wof:placetype":"locality",
    "wof:population":714
},
  "geometry": {"coordinates":[73.63742999999999,15.831691],"type":"Point"}
}