{
  "type": "Feature",
  "properties": {
    "iso:country":"IN",
    "ks:ks_name":"Panapukur",
    "ks:ks_pop":3143,
    "ks:ks_type":"VILLAGE",
    "ks:ks_uagg_main":0,
    "name:eng_x_preferred":[
        "Panapukur"
    ],
    "wof:name":"Panapukur",
    "wof:placetype":"neighbourhood",
    "wof:population":3143
},
  "geometry": {"coordinates":[88.601049,22.516403],"type":"Point"}
}