{
  "type": "Feature",
  "properties": {
    "gn:admin1_code":"34.0",
    "gn:admin2_code":"236.0",
    "gn:asciiname":"Warman",
    "gn:country_code":"IN",
    "gn:dem":161,
    "gn:feature_class":"P",
    "gn:feature_code":"PPL",
    "gn:name":"W\u0101rman",
    "gn:population":0,
    "gn:timezone":"Asia/Kolkata",
    "iso:country":"IN",
    "ks:ks_alt_nam":"W\u0101rman",
    "ks:ks_name":"Warman",
    "ks:ks_type":"VILLAGE",
    "ks:ks_uagg_main":0,
    "name:eng_x_preferred":[
        "Warman"
    ],
    "name:eng_x_variant":[
        "W\u0101rman"
    ],
    "wof:name":"Warman",
    "wof:placetype":"neighbourhood"
},
  "geometry": {"coordinates":[84.901414,24.513798],"type":"Point"}
}