{
  "type": "Feature",
  "properties": {
    "iso:country":"IN",
    "ks:ks_name":"Namapara",
    "ks:ks_pop":387,
    "ks:ks_type":"HABITATION",
    "name:eng_x_preferred":[
        "Namapara"
    ],
    "wof:name":"Namapara",
    "wof:placetype":"locality",
    "wof:population":387
},
  "geometry": {"coordinates":[81.876648,18.717238],"type":"Point"}
}