{
  "type": "Feature",
  "properties": {
    "iso:country":"IN",
    "ks:ks_alt_nam":"T\u0101lda",
    "ks:ks_name":"Talda",
    "ks:ks_pop":173,
    "ks:ks_type":"VILLAGE",
    "name:eng_x_preferred":[
        "Talda"
    ],
    "name:eng_x_variant":[
        "T\u0101lda"
    ],
    "wof:name":"Talda",
    "wof:placetype":"locality",
    "wof:population":173
},
  "geometry": {"coordinates":[85.111127,22.805251],"type":"Point"}
}