{
  "type": "Feature",
  "properties": {
    "gn:admin1_code":"2.0",
    "gn:admin2_code":"554.0",
    "gn:asciiname":"Gangammagaripalli",
    "gn:country_code":"IN",
    "gn:dem":351,
    "gn:feature_class":"P",
    "gn:feature_code":"PPL",
    "gn:name":"Gangammag\u0101ripalli",
    "gn:population":0,
    "gn:timezone":"Asia/Kolkata",
    "iso:country":"IN",
    "ks:ks_alt_nam":"E GAGAMMAGARIPALLE",
    "ks:ks_name":"E Gagammagaripalle",
    "ks:ks_pop":123,
    "ks:ks_type":"HABITATION",
    "name:eng_x_preferred":[
        "E Gagammagaripalle"
    ],
    "name:eng_x_variant":[
        "Gangammagaripalli"
    ],
    "wof:name":"E Gagammagaripalle",
    "wof:placetype":"locality",
    "wof:population":123
},
  "geometry": {"coordinates":[79.15809900000001,13.373413],"type":"Point"}
}