{
  "type": "Feature",
  "properties": {
    "gn:admin1_code":"37.0",
    "gn:admin2_code":"401.0",
    "gn:asciiname":"Pipraul",
    "gn:country_code":"IN",
    "gn:dem":456,
    "gn:feature_class":"P",
    "gn:feature_code":"PPL",
    "gn:name":"Pipraul",
    "gn:population":0,
    "gn:timezone":"Asia/Kolkata",
    "iso:country":"IN",
    "wof:name":"Pipraul",
    "wof:placetype":"locality"
},
  "geometry": {"coordinates":[83.58519,23.71411],"type":"Point"}
}