{
  "type": "Feature",
  "properties": {
    "iso:country":"IN",
    "ks:ks_name":"Paidapattana",
    "ks:ks_pop":730,
    "ks:ks_type":"VILLAGE",
    "name:eng_x_preferred":[
        "Paidapattana"
    ],
    "wof:name":"Paidapattana",
    "wof:placetype":"locality",
    "wof:population":730
},
  "geometry": {"coordinates":[85.83381900000001,21.4383],"type":"Point"}
}