{
  "type": "Feature",
  "properties": {
    "iso:country":"IN",
    "ks:ks_name":"Dodakiya",
    "ks:ks_pop":898,
    "ks:ks_type":"VILLAGE",
    "name:eng_x_preferred":[
        "Dodakiya"
    ],
    "wof:name":"Dodakiya",
    "wof:placetype":"locality",
    "wof:population":898
},
  "geometry": {"coordinates":[81.56043699999999,25.099586],"type":"Point"}
}