{
  "type": "Feature",
  "properties": {
    "iso:country":"IN",
    "ks:ks_name":"Dhobi Basti",
    "ks:ks_pop":28,
    "ks:ks_type":"HABITATION",
    "name:eng_x_preferred":[
        "Dhobi Basti"
    ],
    "wof:name":"Dhobi Basti",
    "wof:placetype":"locality",
    "wof:population":28
},
  "geometry": {"coordinates":[82.93339,25.153953],"type":"Point"}
}