{
  "type": "Feature",
  "properties": {
    "iso:country":"IN",
    "ks:ks_alt_nam":"khapchua",
    "ks:ks_name":"Khapchua",
    "ks:ks_pop":201,
    "ks:ks_type":"HABITATION",
    "name:eng_x_preferred":[
        "Khapchua"
    ],
    "wof:name":"Khapchua",
    "wof:placetype":"locality",
    "wof:population":201
},
  "geometry": {"coordinates":[86.883534,24.530858],"type":"Point"}
}