{
  "type": "Feature",
  "properties": {
    "iso:country":"IN",
    "ks:ks_name":"Lilingpadar",
    "ks:ks_pop":54,
    "ks:ks_type":"HABITATION",
    "name:eng_x_preferred":[
        "Lilingpadar"
    ],
    "wof:name":"Lilingpadar",
    "wof:placetype":"locality",
    "wof:population":54
},
  "geometry": {"coordinates":[83.218126,19.453122],"type":"Point"}
}