{
  "type": "Feature",
  "properties": {
    "iso:country":"IN",
    "ks:ks_name":"Devari Khadar",
    "ks:ks_pop":0,
    "ks:ks_type":"VILLAGE",
    "name:eng_x_preferred":[
        "Devari Khadar"
    ],
    "wof:name":"Devari Khadar",
    "wof:placetype":"locality",
    "wof:population":0
},
  "geometry": {"coordinates":[81.181157,25.490025],"type":"Point"}
}