{
  "type": "Feature",
  "properties": {
    "gn:admin1_code":"13",
    "gn:admin2_code":"595.0",
    "gn:asciiname":"Poringalkuthu",
    "gn:country_code":"IN",
    "gn:dem":35,
    "gn:feature_class":"P",
    "gn:feature_code":"PPL",
    "gn:name":"Poringalkuthu",
    "gn:population":0,
    "gn:timezone":"Asia/Kolkata",
    "iso:country":"IN",
    "wof:name":"Poringalkuthu",
    "wof:placetype":"neighbourhood"
},
  "geometry": {"coordinates":[76.43333,10.28333],"type":"Point"}
}