{
  "type": "Feature",
  "properties": {
    "gn:admin1_code":"25.0",
    "gn:admin2_code":"620.0",
    "gn:asciiname":"Kovilampundi",
    "gn:country_code":"IN",
    "gn:dem":36,
    "gn:feature_class":"P",
    "gn:feature_code":"PPL",
    "gn:name":"Kovil\u0101mp\u016bndi",
    "gn:population":0,
    "gn:timezone":"Asia/Kolkata",
    "iso:country":"IN",
    "ks:ks_name":"Kovilanpoondi",
    "ks:ks_pop":242,
    "ks:ks_type":"HABITATION",
    "name:eng_x_preferred":[
        "Kovilanpoondi"
    ],
    "name:eng_x_variant":[
        "Kovilampundi"
    ],
    "wof:name":"Kovilanpoondi",
    "wof:placetype":"locality",
    "wof:population":242
},
  "geometry": {"coordinates":[79.259838,10.892088],"type":"Point"}
}