{
  "type": "Feature",
  "properties": {
    "iso:country":"IN",
    "ks:ks_name":"Mangelpada",
    "ks:ks_pop":260,
    "ks:ks_type":"HABITATION",
    "name:eng_x_preferred":[
        "Mangelpada"
    ],
    "wof:name":"Mangelpada",
    "wof:placetype":"locality",
    "wof:population":260
},
  "geometry": {"coordinates":[72.963966,19.954471],"type":"Point"}
}