{
  "type": "Feature",
  "properties": {
    "iso:country":"IN",
    "ks:ks_name":"Dudheli Ka Bhatra",
    "ks:ks_pop":122,
    "ks:ks_type":"HABITATION",
    "name:eng_x_preferred":[
        "Dudheli Ka Bhatra"
    ],
    "wof:name":"Dudheli Ka Bhatra",
    "wof:placetype":"locality",
    "wof:population":122
},
  "geometry": {"coordinates":[73.661974,23.674656],"type":"Point"}
}