{
  "type": "Feature",
  "properties": {
    "iso:country":"IN",
    "ks:ks_name":"Khotalapadar",
    "ks:ks_pop":183,
    "ks:ks_type":"VILLAGE",
    "name:eng_x_preferred":[
        "Khotalapadar"
    ],
    "wof:name":"Khotalapadar",
    "wof:placetype":"locality",
    "wof:population":183
},
  "geometry": {"coordinates":[82.96910800000001,19.22855],"type":"Point"}
}