{
  "type": "Feature",
  "properties": {
    "iso:country":"IN",
    "ks:ks_name":"Rangamatiya",
    "ks:ks_pop":377,
    "ks:ks_type":"VILLAGE",
    "name:eng_x_preferred":[
        "Rangamatiya"
    ],
    "wof:name":"Rangamatiya",
    "wof:placetype":"locality",
    "wof:population":377
},
  "geometry": {"coordinates":[86.91998100000001,24.084692],"type":"Point"}
}