{
  "type": "Feature",
  "properties": {
    "gn:admin1_code":"37",
    "gn:admin2_code":"405.0",
    "gn:asciiname":"Kurda",
    "gn:country_code":"IN",
    "gn:dem":266,
    "gn:feature_class":"P",
    "gn:feature_code":"PPL",
    "gn:name":"Kurda",
    "gn:population":0,
    "gn:timezone":"Asia/Kolkata",
    "iso:country":"IN",
    "ks:ks_name":"Kurda",
    "ks:ks_pop":3801,
    "ks:ks_type":"VILLAGE",
    "ks:ks_uagg_main":0,
    "name:cat_x_preferred":[
        "Kurda"
    ],
    "name:eng_x_preferred":[
        "Kurda"
    ],
    "name:rus_x_preferred":[
        "\u041a\u0443\u0440\u0434\u0430"
    ],
    "wof:name":"Kurda",
    "wof:placetype":"neighbourhood",
    "wof:population":3801
},
  "geometry": {"coordinates":[82.65487299999999,22.05758],"type":"Point"}
}