{
  "type": "Feature",
  "properties": {
    "iso:country":"IN",
    "ks:ks_name":"16 MD",
    "ks:ks_pop":32,
    "ks:ks_type":"VILLAGE",
    "name:eng_x_preferred":[
        "16 MD"
    ],
    "wof:name":"16 MD",
    "wof:placetype":"locality",
    "wof:population":32
},
  "geometry": {"coordinates":[73.077189,29.038645],"type":"Point"}
}