{
  "type": "Feature",
  "properties": {
    "gn:admin1_code":"13.0",
    "gn:admin2_code":"593.0",
    "gn:asciiname":"Pulapattassheri",
    "gn:country_code":"IN",
    "gn:dem":59,
    "gn:feature_class":"P",
    "gn:feature_code":"PPL",
    "gn:name":"Pul\u0101pattassh\u0113ri",
    "gn:population":0,
    "gn:timezone":"Asia/Kolkata",
    "iso:country":"IN",
    "ks:ks_name":"Pulapattassery",
    "ks:ks_pop":750,
    "ks:ks_type":"HABITATION",
    "name:eng_x_preferred":[
        "Pulapattassery"
    ],
    "name:eng_x_variant":[
        "Pulapattassheri"
    ],
    "wof:name":"Pulapattassery",
    "wof:placetype":"locality",
    "wof:population":750
},
  "geometry": {"coordinates":[76.43928699999999,10.820344],"type":"Point"}
}