{
  "type": "Feature",
  "properties": {
    "gn:admin1_code":"34.0",
    "gn:admin2_code":"213.0",
    "gn:asciiname":"Matiahi",
    "gn:country_code":"IN",
    "gn:dem":49,
    "gn:feature_class":"P",
    "gn:feature_code":"PPL",
    "gn:name":"Mati\u0101hi",
    "gn:population":0,
    "gn:timezone":"Asia/Kolkata",
    "iso:country":"IN",
    "ks:ks_alt_nam":"Mati\u0101hi",
    "ks:ks_name":"Matiahi",
    "ks:ks_pop":3517,
    "ks:ks_type":"VILLAGE",
    "ks:ks_uagg_main":0,
    "name:eng_x_preferred":[
        "Matiahi"
    ],
    "name:eng_x_variant":[
        "Mati\u0101hi"
    ],
    "wof:name":"Matiahi",
    "wof:placetype":"neighbourhood",
    "wof:population":3517
},
  "geometry": {"coordinates":[86.725348,25.90406],"type":"Point"}
}