{
  "type": "Feature",
  "properties": {
    "iso:country":"IN",
    "ks:ks_name":"Naga United",
    "ks:ks_pop":1492,
    "ks:ks_type":"HABITATION",
    "ks:ks_uagg_main":0,
    "name:eng_x_preferred":[
        "Naga United"
    ],
    "wof:name":"Naga United",
    "wof:placetype":"neighbourhood",
    "wof:population":1492
},
  "geometry": {"coordinates":[93.797087,25.862238],"type":"Point"}
}