{
  "type": "Feature",
  "properties": {
    "iso:country":"IN",
    "ks:ks_name":"Chil",
    "ks:ks_pop":457,
    "ks:ks_type":"HABITATION",
    "name:eng_x_preferred":[
        "Chil"
    ],
    "wof:name":"Chil",
    "wof:placetype":"locality",
    "wof:population":457
},
  "geometry": {"coordinates":[79.89420800000001,29.549595],"type":"Point"}
}