{
  "type": "Feature",
  "properties": {
    "gn:admin1_code":"16",
    "gn:admin2_code":"510.0",
    "gn:asciiname":"Phulsangwi",
    "gn:country_code":"IN",
    "gn:dem":286,
    "gn:feature_class":"P",
    "gn:feature_code":"PPL",
    "gn:name":"Phuls\u0101ngwi",
    "gn:population":0,
    "gn:timezone":"Asia/Kolkata",
    "iso:country":"IN",
    "name:und_x_variant":[
        "Phuls\u0101ngwi",
        "Phuls\u0101ngvi"
    ],
    "wof:name":"Phulsangwi",
    "wof:placetype":"neighbourhood"
},
  "geometry": {"coordinates":[77.87578000000001,19.72363],"type":"Point"}
}