{
  "type": "Feature",
  "properties": {
    "iso:country":"IN",
    "ks:ks_name":"Chharchhum",
    "ks:ks_pop":302,
    "ks:ks_type":"VILLAGE",
    "name:eng_x_preferred":[
        "Chharchhum"
    ],
    "wof:name":"Chharchhum",
    "wof:placetype":"locality",
    "wof:population":302
},
  "geometry": {"coordinates":[80.460819,29.802976],"type":"Point"}
}