{
  "type": "Feature",
  "properties": {
    "iso:country":"IN",
    "ks:ks_name":"Karihithala",
    "ks:ks_pop":133,
    "ks:ks_type":"HABITATION",
    "name:eng_x_preferred":[
        "Karihithala"
    ],
    "wof:name":"Karihithala",
    "wof:placetype":"locality",
    "wof:population":133
},
  "geometry": {"coordinates":[74.391367,14.443086],"type":"Point"}
}