{
  "type": "Feature",
  "properties": {
    "gn:admin1_code":"35",
    "gn:admin2_code":"463.0",
    "gn:asciiname":"Parasi",
    "gn:country_code":"IN",
    "gn:dem":392,
    "gn:feature_class":"P",
    "gn:feature_code":"PPL",
    "gn:name":"Par\u0101si",
    "gn:population":0,
    "gn:timezone":"Asia/Kolkata",
    "iso:country":"IN",
    "ks:ks_alt_nam":"Par\u0101si",
    "ks:ks_name":"Parasi",
    "ks:ks_pop":1588,
    "ks:ks_type":"VILLAGE",
    "name:eng_x_preferred":[
        "Parasi"
    ],
    "name:eng_x_variant":[
        "Par\u0101si"
    ],
    "wof:name":"Parasi",
    "wof:placetype":"locality",
    "wof:population":1588
},
  "geometry": {"coordinates":[82.044381,24.046241],"type":"Point"}
}