{
  "type": "Feature",
  "properties": {
    "iso:country":"IN",
    "ks:ks_name":"Sukhari Tola",
    "ks:ks_pop":866,
    "ks:ks_type":"VILLAGE",
    "name:eng_x_preferred":[
        "Sukhari Tola"
    ],
    "wof:name":"Sukhari Tola",
    "wof:placetype":"locality",
    "wof:population":866
},
  "geometry": {"coordinates":[82.496949,23.912014],"type":"Point"}
}