{
  "type": "Feature",
  "properties": {
    "iso:country":"IN",
    "ks:ks_name":"Ballaru",
    "ks:ks_pop":242,
    "ks:ks_type":"HABITATION",
    "name:eng_x_preferred":[
        "Ballaru"
    ],
    "wof:name":"Ballaru",
    "wof:placetype":"locality",
    "wof:population":242
},
  "geometry": {"coordinates":[75.164342,12.842922],"type":"Point"}
}