{
  "type": "Feature",
  "properties": {
    "iso:country":"IN",
    "ks:ks_name":"Baidyaharana",
    "ks:ks_pop":211,
    "ks:ks_type":"VILLAGE",
    "name:eng_x_preferred":[
        "Baidyaharana"
    ],
    "wof:name":"Baidyaharana",
    "wof:placetype":"locality",
    "wof:population":211
},
  "geometry": {"coordinates":[87.71695800000001,21.750759],"type":"Point"}
}