{
  "type": "Feature",
  "properties": {
    "gn:admin1_code":"36.0",
    "gn:admin2_code":"161",
    "gn:asciiname":"Rur",
    "gn:country_code":"IN",
    "gn:dem":156,
    "gn:feature_class":"P",
    "gn:feature_code":"PPL",
    "gn:name":"Rur",
    "gn:population":0,
    "gn:timezone":"Asia/Kolkata",
    "iso:country":"IN",
    "name:bre_x_preferred":[
        "Roer"
    ],
    "name:bul_x_preferred":[
        "\u0420\u0443\u0440"
    ],
    "name:cat_x_preferred":[
        "Rur"
    ],
    "name:ceb_x_preferred":[
        "Rur"
    ],
    "name:ces_x_preferred":[
        "Rour"
    ],
    "name:chv_x_preferred":[
        "\u0420\u0443\u0440"
    ],
    "name:dan_x_preferred":[
        "Rur"
    ],
    "name:deu_x_preferred":[
        "Rur"
    ],
    "name:ell_x_preferred":[
        "\u03a1\u03cc\u03b5\u03c1"
    ],
    "name:epo_x_preferred":[
        "Rur"
    ],
    "name:eus_x_preferred":[
        "Rur"
    ],
    "name:fra_x_preferred":[
        "Roer"
    ],
    "name:ina_x_preferred":[
        "Fluvio Rur"
    ],
    "name:ind_x_preferred":[
        "Sungai Rur"
    ],
    "name:ita_x_preferred":[
        "Roer"
    ],
    "name:kat_x_preferred":[
        "\u10e0\u10e3\u10e0\u10d8"
    ],
    "name:ksh_x_preferred":[
        "Rur"
    ],
    "name:lat_x_preferred":[
        "Rura"
    ],
    "name:lim_x_preferred":[
        "Roer"
    ],
    "name:lit_x_preferred":[
        "R\u016bras"
    ],
    "name:ltz_x_preferred":[
        "Roer"
    ],
    "name:nld_x_preferred":[
        "Roer"
    ],
    "name:nno_x_preferred":[
        "Roer"
    ],
    "name:nor_x_preferred":[
        "Rur"
    ],
    "name:pol_x_preferred":[
        "Rur"
    ],
    "name:por_x_preferred":[
        "Rio Rur"
    ],
    "name:ron_x_preferred":[
        "Rur"
    ],
    "name:rus_x_preferred":[
        "\u0420\u0443\u0440"
    ],
    "name:spa_x_preferred":[
        "R\u00edo Rur"
    ],
    "name:swe_x_preferred":[
        "Rur"
    ],
    "name:tam_x_preferred":[
        "\u0bb0\u0bc2\u0bb0\u0bcd \u0b86\u0bb1\u0bc1"
    ],
    "name:tur_x_preferred":[
        "Rur Nehri"
    ],
    "name:ukr_x_preferred":[
        "\u0420\u0443\u0440"
    ],
    "name:und_x_variant":[
        "R\u016br"
    ],
    "name:wln_x_preferred":[
        "Ro\u00fble"
    ],
    "name:zho_x_preferred":[
        "\u9b6f\u723e\u6cb3"
    ],
    "wof:name":"Rur",
    "wof:placetype":"locality"
},
  "geometry": {"coordinates":[79.15937,26.99617000000001],"type":"Point"}
}