{
  "type": "Feature",
  "properties": {
    "iso:country":"IN",
    "ks:ks_name":"Godar Kala",
    "ks:ks_pop":338,
    "ks:ks_type":"HABITATION",
    "ks:ks_uagg_main":0,
    "name:eng_x_preferred":[
        "Godar Kala"
    ],
    "wof:name":"Godar Kala",
    "wof:placetype":"neighbourhood",
    "wof:population":338
},
  "geometry": {"coordinates":[82.49185300000001,25.024053],"type":"Point"}
}