{
  "type": "Feature",
  "properties": {
    "iso:country":"IN",
    "ks:ks_name":"Kasundi",
    "ks:ks_pop":73,
    "ks:ks_type":"VILLAGE",
    "name:eng_x_preferred":[
        "Kasundi"
    ],
    "wof:name":"Kasundi",
    "wof:placetype":"locality",
    "wof:population":73
},
  "geometry": {"coordinates":[87.686818,25.495902],"type":"Point"}
}