{
  "type": "Feature",
  "properties": {
    "gn:admin1_code":"19.0",
    "gn:admin2_code":"576.0",
    "gn:asciiname":"Naluvattokkalu",
    "gn:country_code":"IN",
    "gn:dem":940,
    "gn:feature_class":"P",
    "gn:feature_code":"PPLL",
    "gn:name":"Naluvattokkalu",
    "gn:population":0,
    "gn:timezone":"Asia/Kolkata",
    "iso:country":"IN",
    "wof:name":"Naluvattokkalu",
    "wof:placetype":"locality"
},
  "geometry": {"coordinates":[75.84397,12.19598],"type":"Point"}
}