{
  "type": "Feature",
  "properties": {
    "gn:admin1_code":"26",
    "gn:admin2_code":"289.0",
    "gn:asciiname":"Santinagar",
    "gn:country_code":"IN",
    "gn:dem":40,
    "gn:feature_class":"P",
    "gn:feature_code":"PPL",
    "gn:name":"S\u0101ntinagar",
    "gn:population":0,
    "gn:timezone":"Asia/Kolkata",
    "iso:country":"IN",
    "wof:name":"Santinagar",
    "wof:placetype":"locality"
},
  "geometry": {"coordinates":[91.61657,23.98093],"type":"Point"}
}