{
  "type": "Feature",
  "properties": {
    "iso:country":"IN",
    "ks:ks_name":"Torani Borkachari 2",
    "ks:ks_pop":200,
    "ks:ks_type":"HABITATION",
    "ks:ks_uagg_main":0,
    "name:eng_x_preferred":[
        "Torani Borkachari 2"
    ],
    "wof:name":"Torani Borkachari 2",
    "wof:placetype":"neighbourhood",
    "wof:population":200
},
  "geometry": {"coordinates":[94.114115,26.370675],"type":"Point"}
}