{
  "type": "Feature",
  "properties": {
    "iso:country":"IN",
    "ks:ks_name":"Matgaran",
    "ks:ks_pop":1838,
    "ks:ks_type":"VILLAGE",
    "name:eng_x_preferred":[
        "Matgaran"
    ],
    "wof:name":"Matgaran",
    "wof:placetype":"locality",
    "wof:population":1838
},
  "geometry": {"coordinates":[88.736199,22.176625],"type":"Point"}
}