{
  "type": "Feature",
  "properties": {
    "iso:country":"IN",
    "ks:ks_name":"Balachari Amguri",
    "ks:ks_pop":376,
    "ks:ks_type":"VILLAGE",
    "ks:ks_uagg_main":0,
    "name:eng_x_preferred":[
        "Balachari Amguri"
    ],
    "wof:name":"Balachari Amguri",
    "wof:placetype":"neighbourhood",
    "wof:population":376
},
  "geometry": {"coordinates":[90.463916,26.038326],"type":"Point"}
}