{
  "type": "Feature",
  "properties": {
    "iso:country":"IN",
    "ks:ks_name":"Siddapur",
    "ks:ks_pop":69,
    "ks:ks_type":"URBAN",
    "name:eng_x_preferred":[
        "Siddapur"
    ],
    "wof:name":"Siddapur",
    "wof:placetype":"locality",
    "wof:population":69
},
  "geometry": {"coordinates":[74.762124,15.287363],"type":"Point"}
}