{
  "type": "Feature",
  "properties": {
    "gn:admin1_code":"39.0",
    "gn:admin2_code":"64.0",
    "gn:asciiname":"Dhargaon",
    "gn:country_code":"IN",
    "gn:dem":1210,
    "gn:feature_class":"P",
    "gn:feature_code":"PPL",
    "gn:name":"Dhargaon",
    "gn:population":0,
    "gn:timezone":"Asia/Kolkata",
    "iso:country":"IN",
    "wof:name":"Dhargaon",
    "wof:placetype":"locality"
},
  "geometry": {"coordinates":[79.39265,29.77902000000001],"type":"Point"}
}