{
  "type": "Feature",
  "properties": {
    "iso:country":"IN",
    "ks:ks_alt_nam":"Varapallam Karumutti Kattupatti settlement",
    "ks:ks_name":"Varapallam Karumutti Kattupatti Settlement",
    "ks:ks_pop":850,
    "ks:ks_type":"HABITATION",
    "name:eng_x_preferred":[
        "Varapallam Karumutti Kattupatti Settlement"
    ],
    "wof:name":"Varapallam Karumutti Kattupatti Settlement",
    "wof:placetype":"locality",
    "wof:population":850
},
  "geometry": {"coordinates":[77.08511300000001,10.486762],"type":"Point"}
}