{
  "type": "Feature",
  "properties": {
    "iso:country":"IN",
    "ks:ks_name":"Bilagoor",
    "ks:ks_pop":143,
    "ks:ks_type":"HABITATION",
    "name:eng_x_preferred":[
        "Bilagoor"
    ],
    "wof:name":"Bilagoor",
    "wof:placetype":"locality",
    "wof:population":143
},
  "geometry": {"coordinates":[75.445527,13.230358],"type":"Point"}
}