{
  "type": "Feature",
  "properties": {
    "iso:country":"IN",
    "ks:ks_name":"Janasi",
    "ks:ks_pop":165,
    "ks:ks_type":"HABITATION",
    "name:eng_x_preferred":[
        "Janasi"
    ],
    "wof:name":"Janasi",
    "wof:placetype":"locality",
    "wof:population":165
},
  "geometry": {"coordinates":[75.54986100000001,20.466466],"type":"Point"}
}