{
  "type": "Feature",
  "properties": {
    "gn:admin1_code":"11",
    "gn:admin2_code":"23.0",
    "gn:asciiname":"Dhamsar Adwar",
    "gn:country_code":"IN",
    "gn:dem":3121,
    "gn:feature_class":"P",
    "gn:feature_code":"PPL",
    "gn:name":"Dhamsar Adw\u0101r",
    "gn:population":0,
    "gn:timezone":"Asia/Kolkata",
    "iso:country":"IN",
    "wof:name":"Dhamsar Adwar",
    "wof:placetype":"locality"
},
  "geometry": {"coordinates":[76.38393000000001,33.10415],"type":"Point"}
}