{
  "type": "Feature",
  "properties": {
    "gn:admin1_code":"24",
    "gn:admin2_code":"123.0",
    "gn:asciiname":"Sakroda",
    "gn:country_code":"IN",
    "gn:dem":622,
    "gn:feature_class":"P",
    "gn:feature_code":"PPL",
    "gn:name":"S\u0101kroda",
    "gn:population":0,
    "gn:timezone":"Asia/Kolkata",
    "iso:country":"IN",
    "wof:name":"Sakroda",
    "wof:placetype":"locality"
},
  "geometry": {"coordinates":[73.7821,25.06387],"type":"Point"}
}