{
  "type": "Feature",
  "properties": {
    "iso:country":"IN",
    "ks:ks_name":"Katikamamidi",
    "ks:ks_pop":9,
    "ks:ks_type":"HABITATION",
    "name:eng_x_preferred":[
        "Katikamamidi"
    ],
    "wof:name":"Katikamamidi",
    "wof:placetype":"locality",
    "wof:population":9
},
  "geometry": {"coordinates":[82.952868,18.042297],"type":"Point"}
}