{
  "type": "Feature",
  "properties": {
    "gn:admin1_code":"39.0",
    "gn:admin2_code":"060",
    "gn:asciiname":"Bansiwala",
    "gn:country_code":"IN",
    "gn:dem":539,
    "gn:feature_class":"P",
    "gn:feature_code":"PPL",
    "gn:name":"Bans\u012bw\u0101la",
    "gn:population":0,
    "gn:timezone":"Asia/Kolkata",
    "iso:country":"IN",
    "ks:ks_name":"Banshiwala",
    "ks:ks_pop":429,
    "ks:ks_type":"VILLAGE",
    "ks:ks_uagg_main":0,
    "name:eng_x_preferred":[
        "Banshiwala"
    ],
    "wof:name":"Banshiwala",
    "wof:placetype":"locality",
    "wof:population":429
},
  "geometry": {"coordinates":[77.897986,30.346536],"type":"Point"}
}