{
  "type": "Feature",
  "properties": {
    "iso:country":"IN",
    "ks:ks_alt_nam":"dongaripada",
    "ks:ks_name":"Dongaripada",
    "ks:ks_pop":70,
    "ks:ks_type":"HABITATION",
    "name:eng_x_preferred":[
        "Dongaripada"
    ],
    "wof:name":"Dongaripada",
    "wof:placetype":"locality",
    "wof:population":70
},
  "geometry": {"coordinates":[73.25895199999999,19.659904],"type":"Point"}
}