{
  "type": "Feature",
  "properties": {
    "iso:country":"IN",
    "ks:ks_name":"Bhacheriya",
    "ks:ks_pop":215,
    "ks:ks_type":"VILLAGE",
    "name:eng_x_preferred":[
        "Bhacheriya"
    ],
    "wof:name":"Bhacheriya",
    "wof:placetype":"locality",
    "wof:population":215
},
  "geometry": {"coordinates":[74.673858,23.914614],"type":"Point"}
}