{
  "type": "Feature",
  "properties": {
    "iso:country":"IN",
    "ks:ks_name":"Tharu Tola",
    "ks:ks_pop":149,
    "ks:ks_type":"HABITATION",
    "name:eng_x_preferred":[
        "Tharu Tola"
    ],
    "wof:name":"Tharu Tola",
    "wof:placetype":"locality",
    "wof:population":149
},
  "geometry": {"coordinates":[84.227091,27.395798],"type":"Point"}
}