{
  "type": "Feature",
  "properties": {
    "gn:admin1_code":"9.0",
    "gn:admin2_code":"486.0",
    "gn:asciiname":"Gotri",
    "gn:country_code":"IN",
    "gn:dem":33,
    "gn:feature_class":"P",
    "gn:feature_code":"PPL",
    "gn:name":"Gotri",
    "gn:population":0,
    "gn:timezone":"Asia/Kolkata",
    "iso:country":"IN",
    "name:ceb_x_preferred":[
        "Gotree"
    ],
    "name:fra_x_preferred":[
        "Gotree"
    ],
    "name:mai_x_preferred":[
        "\u0917\u094b\u0924\u094d\u0930\u0940"
    ],
    "name:msa_x_preferred":[
        "Gotree"
    ],
    "name:nep_x_preferred":[
        "\u0917\u094b\u0924\u094d\u0930\u0940"
    ],
    "name:new_x_preferred":[
        "\u0917\u094b\u0924\u094d\u0930\u0940"
    ],
    "name:pol_x_preferred":[
        "Gotree"
    ],
    "wof:name":"Gotri",
    "wof:placetype":"neighbourhood"
},
  "geometry": {"coordinates":[73.14381,22.31501],"type":"Point"}
}