{
  "type": "Feature",
  "properties": {
    "iso:country":"IN",
    "ks:ks_name":"Alamapada",
    "ks:ks_pop":160,
    "ks:ks_type":"HABITATION",
    "name:eng_x_preferred":[
        "Alamapada"
    ],
    "wof:name":"Alamapada",
    "wof:placetype":"locality",
    "wof:population":160
},
  "geometry": {"coordinates":[73.209444,19.484444],"type":"Point"}
}