{
  "type": "Feature",
  "properties": {
    "iso:country":"IN",
    "name:ara_x_preferred":[
        "\u0645\u0627\u062f\u0648\u0631 \u0628\u0627\u0643\u0648\u0645"
    ],
    "name:ben_bn_x_preferred":[
        "\u09ae\u09be\u09a6\u09c1\u09b0\u09be\u09aa\u09be\u0995\u09cd\u0995\u09be\u09ae"
    ],
    "name:ben_in_x_preferred":[
        "\u09ae\u09be\u09a6\u09c1\u09b0\u09be\u09aa\u09be\u0995\u09cd\u0995\u09be\u09ae"
    ],
    "name:guj_x_preferred":[
        "\u0a85\u0aa6\u0ac1\u0ab0\u0abe\u0aaa\u0a95\u0acd\u0a95\u0aae"
    ],
    "name:hin_x_preferred":[
        "\u092e\u0926\u0941\u0930\u093e\u092a\u0915\u094d\u0915\u092e"
    ],
    "name:kan_x_preferred":[
        "\u0cae\u0ca6\u0cc1\u0cb0\u0caa\u0c95\u0ccd\u0c95\u0cae\u0ccd"
    ],
    "name:mal_x_preferred":[
        "\u0d2e\u0d27\u0d41\u0d30\u0d2a\u0d4d\u0d2a\u0d3e\u0d15\u0d4d\u0d15\u0d02"
    ],
    "name:mar_x_preferred":[
        "\u092e\u0926\u0941\u0930\u093e\u092a\u0915\u094d\u0915\u092e"
    ],
    "name:pan_x_preferred":[
        "\u0a2e\u0a26\u0a41\u0a30\u0a3e\u0a2a\u0a71\u0a15\u0a2e"
    ],
    "name:tam_x_preferred":[
        "\u0bae\u0ba4\u0bc1\u0bb0\u0baa\u0bcd\u0baa\u0bbe\u0b95\u0bcd\u0b95\u0bae\u0bcd"
    ],
    "name:tel_x_preferred":[
        "\u0c2e\u0c26\u0c41\u0c30\u0c2a\u0c15\u0c4d\u0c15\u0c02"
    ],
    "name:urd_x_preferred":[
        "\u0645\u062f\u0648\u0631\u0627 \u067e\u06a9\u0651\u0645"
    ],
    "qs:name":"Madurapakkam",
    "qs:name_adm0":"India",
    "qs:name_adm1":"Tamil Nadu",
    "qs:photos":4,
    "qs:photos_1k":1,
    "qs:photos_9k":1,
    "qs:photos_9r":1,
    "qs:photos_all":4,
    "qs:photos_sr":1,
    "qs:placetype":"Suburb",
    "qs:pop_sr":"0",
    "wof:name":"Madurapakkam",
    "wof:placetype":"neighbourhood"
},
  "geometry": {"coordinates":[80.121917,12.946261],"type":"Point"}
}