{
  "type": "Feature",
  "properties": {
    "iso:country":"IN",
    "ks:ks_name":"Madagudi",
    "ks:ks_pop":63,
    "ks:ks_type":"VILLAGE",
    "name:eng_x_preferred":[
        "Madagudi"
    ],
    "wof:name":"Madagudi",
    "wof:placetype":"locality",
    "wof:population":63
},
  "geometry": {"coordinates":[83.709142,19.756104],"type":"Point"}
}