{
  "type": "Feature",
  "properties": {
    "gn:country":"IN",
    "gn:fcode":"PPL",
    "gn:population":30832,
    "iso:country":"IN",
    "qs:name":"El\u016br",
    "qs:photos_9r":0,
    "qs:photos_sr":0,
    "qs:pop_sr":"7",
    "wof:name":"El\u016br",
    "wof:placetype":"locality",
    "wof:population":30832
},
  "geometry": {"coordinates":[76.28333000000001,10.06667],"type":"Point"}
}