{
  "type": "Feature",
  "properties": {
    "iso:country":"IN",
    "ks:ks_name":"Katalwadi",
    "ks:ks_pop":70,
    "ks:ks_type":"HABITATION",
    "name:eng_x_preferred":[
        "Katalwadi"
    ],
    "wof:name":"Katalwadi",
    "wof:placetype":"locality",
    "wof:population":70
},
  "geometry": {"coordinates":[73.381456,17.698969],"type":"Point"}
}