{
  "type": "Feature",
  "properties": {
    "iso:country":"IN",
    "ks:ks_name":"Charki Guriyawan",
    "ks:ks_pop":339,
    "ks:ks_type":"HABITATION",
    "name:eng_x_preferred":[
        "Charki Guriyawan"
    ],
    "wof:name":"Charki Guriyawan",
    "wof:placetype":"locality",
    "wof:population":339
},
  "geometry": {"coordinates":[82.464116,25.014234],"type":"Point"}
}