{
  "type": "Feature",
  "properties": {
    "gn:admin1_code":"38",
    "gn:admin2_code":"346.0",
    "gn:asciiname":"Henho",
    "gn:country_code":"IN",
    "gn:dem":249,
    "gn:feature_class":"P",
    "gn:feature_code":"PPL",
    "gn:name":"Henho",
    "gn:population":0,
    "gn:timezone":"Asia/Kolkata",
    "iso:country":"IN",
    "ks:ks_name":"Henho",
    "ks:ks_pop":593,
    "ks:ks_type":"VILLAGE",
    "ks:ks_uagg_main":0,
    "name:eng_x_preferred":[
        "Henho"
    ],
    "wof:name":"Henho",
    "wof:placetype":"neighbourhood",
    "wof:population":593
},
  "geometry": {"coordinates":[83.505574,24.27793],"type":"Point"}
}