{
  "type": "Feature",
  "properties": {
    "iso:country":"IN",
    "ks:ks_name":"Mirzapur",
    "ks:ks_pop":1497,
    "ks:ks_type":"VILLAGE",
    "ks:ks_uagg_main":0,
    "name:eng_x_preferred":[
        "Mirzapur"
    ],
    "wof:name":"Mirzapur",
    "wof:placetype":"neighbourhood",
    "wof:population":1497
},
  "geometry": {"coordinates":[88.226472,22.234991],"type":"Point"}
}