{
  "type": "Feature",
  "properties": {
    "gn:admin1_code":"39.0",
    "gn:admin2_code":"64.0",
    "gn:asciiname":"Sahaskhet",
    "gn:country_code":"IN",
    "gn:dem":1754,
    "gn:feature_class":"P",
    "gn:feature_code":"PPL",
    "gn:name":"Sahaskhet",
    "gn:population":0,
    "gn:timezone":"Asia/Kolkata",
    "iso:country":"IN",
    "wof:name":"Sahaskhet",
    "wof:placetype":"locality"
},
  "geometry": {"coordinates":[79.26566,29.90392],"type":"Point"}
}