{
  "type": "Feature",
  "properties": {
    "gn:admin1_code":"36",
    "gn:admin2_code":"185.0",
    "gn:asciiname":"Bhasolia Doem",
    "gn:country_code":"IN",
    "gn:dem":83,
    "gn:feature_class":"P",
    "gn:feature_code":"PPLL",
    "gn:name":"Bhasolia Doem",
    "gn:population":0,
    "gn:timezone":"Asia/Kolkata",
    "iso:country":"IN",
    "wof:name":"Bhasolia Doem",
    "wof:placetype":"locality"
},
  "geometry": {"coordinates":[82.87281999999998,26.71057],"type":"Point"}
}