{
  "type": "Feature",
  "properties": {
    "gn:admin1_code":"13.0",
    "gn:admin2_code":"593.0",
    "gn:asciiname":"Kallikkad",
    "gn:country_code":"IN",
    "gn:dem":92,
    "gn:feature_class":"P",
    "gn:feature_code":"PPL",
    "gn:name":"Kallikk\u0101d",
    "gn:population":0,
    "gn:timezone":"Asia/Kolkata",
    "iso:country":"IN",
    "name:mal_x_preferred":[
        "\u0d15\u0d33\u0d4d\u0d33\u0d3f\u0d15\u0d4d\u0d15\u0d3e\u0d1f\u0d4d"
    ],
    "wof:name":"Kallikkad",
    "wof:placetype":"neighbourhood"
},
  "geometry": {"coordinates":[76.61244000000001,10.78564],"type":"Point"}
}