{
  "type": "Feature",
  "properties": {
    "gn:admin1_code":"25.0",
    "gn:admin2_code":"631.0",
    "gn:asciiname":"Kuntibanattam",
    "gn:country_code":"IN",
    "gn:dem":495,
    "gn:feature_class":"P",
    "gn:feature_code":"PPL",
    "gn:name":"Kuntibanattam",
    "gn:population":0,
    "gn:timezone":"Asia/Kolkata",
    "iso:country":"IN",
    "wof:name":"Kuntibanattam",
    "wof:placetype":"neighbourhood"
},
  "geometry": {"coordinates":[78.40465,12.5477],"type":"Point"}
}