{
  "type": "Feature",
  "properties": {
    "gn:admin1_code":"16",
    "gn:admin2_code":"505.0",
    "gn:asciiname":"Tangla",
    "gn:country_code":"IN",
    "gn:dem":357,
    "gn:feature_class":"P",
    "gn:feature_code":"PPL",
    "gn:name":"T\u0101ngla",
    "gn:population":0,
    "gn:timezone":"Asia/Kolkata",
    "iso:country":"IN",
    "name:asm_x_preferred":[
        "\u099f\u0982\u09b2\u09be"
    ],
    "name:ben_x_preferred":[
        "\u099f\u0982\u09b2\u09be"
    ],
    "name:bpy_x_preferred":[
        "\u099f\u09be\u0982\u09b2\u09be"
    ],
    "name:ita_x_preferred":[
        "Tangla"
    ],
    "name:msa_x_preferred":[
        "Tangla"
    ],
    "name:nld_x_preferred":[
        "Tangla"
    ],
    "name:por_x_preferred":[
        "Tangla"
    ],
    "name:spa_x_preferred":[
        "Tangla"
    ],
    "name:und_x_variant":[
        "T\u0101ngla"
    ],
    "name:vie_x_preferred":[
        "Tangla"
    ],
    "name:zho_x_preferred":[
        "\u5510\u683c\u62c9"
    ],
    "wof:name":"Tangla",
    "wof:placetype":"locality"
},
  "geometry": {"coordinates":[79.48997,21.53182],"type":"Point"}
}