{
  "type": "Feature",
  "properties": {
    "iso:country":"IN",
    "ks:ks_name":"Rule",
    "ks:ks_pop":245,
    "ks:ks_type":"VILLAGE",
    "name:eng_x_preferred":[
        "Rule"
    ],
    "wof:name":"Rule",
    "wof:placetype":"locality",
    "wof:population":245
},
  "geometry": {"coordinates":[72.937088,18.675418],"type":"Point"}
}