{
  "type": "Feature",
  "properties": {
    "gn:admin1_code":"35.0",
    "gn:admin2_code":"455.0",
    "gn:asciiname":"Kundai",
    "gn:country_code":"IN",
    "gn:dem":668,
    "gn:feature_class":"P",
    "gn:feature_code":"PPL",
    "gn:name":"Kundai",
    "gn:population":0,
    "gn:timezone":"Asia/Kolkata",
    "iso:country":"IN",
    "ks:ks_name":"Kundai",
    "ks:ks_pop":604,
    "ks:ks_type":"VILLAGE",
    "name:eng_x_preferred":[
        "Kundai"
    ],
    "wof:name":"Kundai",
    "wof:placetype":"locality",
    "wof:population":604
},
  "geometry": {"coordinates":[78.54002300000001,22.034304],"type":"Point"}
}