{
  "type": "Feature",
  "properties": {
    "iso:country":"IN",
    "ks:ks_alt_nam":"Badri bigha",
    "ks:ks_name":"Badri Bigha",
    "ks:ks_pop":112,
    "ks:ks_type":"HABITATION",
    "name:eng_x_preferred":[
        "Badri Bigha"
    ],
    "wof:name":"Badri Bigha",
    "wof:placetype":"locality",
    "wof:population":112
},
  "geometry": {"coordinates":[84.57026399999999,24.894823],"type":"Point"}
}