{
  "type": "Feature",
  "properties": {
    "iso:country":"IN",
    "ks:ks_alt_nam":"BURUHANGAI",
    "ks:ks_name":"Buruhangai",
    "ks:ks_pop":225,
    "ks:ks_type":"HABITATION",
    "name:eng_x_preferred":[
        "Buruhangai"
    ],
    "wof:name":"Buruhangai",
    "wof:placetype":"locality",
    "wof:population":225
},
  "geometry": {"coordinates":[85.337502,22.131268],"type":"Point"}
}