{
  "type": "Feature",
  "properties": {
    "iso:country":"IN",
    "ks:ks_name":"Angajanahalli",
    "ks:ks_pop":44,
    "ks:ks_type":"VILLAGE",
    "name:eng_x_preferred":[
        "Angajanahalli"
    ],
    "wof:name":"Angajanahalli",
    "wof:placetype":"locality",
    "wof:population":44
},
  "geometry": {"coordinates":[75.744648,13.186501],"type":"Point"}
}