{
  "type": "Feature",
  "properties": {
    "iso:country":"IN",
    "ks:ks_name":"Ruhia",
    "ks:ks_pop":2277,
    "ks:ks_type":"VILLAGE",
    "ks:ks_uagg_main":0,
    "name:eng_x_preferred":[
        "Ruhia"
    ],
    "wof:name":"Ruhia",
    "wof:placetype":"neighbourhood",
    "wof:population":2277
},
  "geometry": {"coordinates":[88.376459,24.150625],"type":"Point"}
}