{
  "type": "Feature",
  "properties": {
    "iso:country":"IN",
    "ks:ks_name":"Pipra",
    "ks:ks_pop":166,
    "ks:ks_type":"VILLAGE",
    "name:eng_x_preferred":[
        "Pipra"
    ],
    "wof:name":"Pipra",
    "wof:placetype":"locality",
    "wof:population":166
},
  "geometry": {"coordinates":[86.522946,24.478502],"type":"Point"}
}