{
  "type": "Feature",
  "properties": {
    "iso:country":"IN",
    "ks:ks_name":"Kariyaje",
    "ks:ks_pop":106,
    "ks:ks_type":"HABITATION",
    "name:eng_x_preferred":[
        "Kariyaje"
    ],
    "wof:name":"Kariyaje",
    "wof:placetype":"locality",
    "wof:population":106
},
  "geometry": {"coordinates":[75.19699300000001,12.979039],"type":"Point"}
}