{
  "type": "Feature",
  "properties": {
    "iso:country":"IN",
    "ks:ks_alt_nam":"Periyangere area",
    "ks:ks_name":"Periyangere Area",
    "ks:ks_pop":283,
    "ks:ks_type":"HABITATION",
    "name:eng_x_preferred":[
        "Periyangere Area"
    ],
    "wof:name":"Periyangere Area",
    "wof:placetype":"locality",
    "wof:population":283
},
  "geometry": {"coordinates":[75.731312,12.219061],"type":"Point"}
}