{
  "type": "Feature",
  "properties": {
    "iso:country":"IN",
    "ks:ks_name":"Thana Viran",
    "ks:ks_pop":165,
    "ks:ks_type":"HABITATION",
    "name:eng_x_preferred":[
        "Thana Viran"
    ],
    "wof:name":"Thana Viran",
    "wof:placetype":"locality",
    "wof:population":165
},
  "geometry": {"coordinates":[77.411411,23.906778],"type":"Point"}
}