{
  "type": "Feature",
  "properties": {
    "gn:admin1_code":"37",
    "gn:admin2_code":"406.0",
    "gn:asciiname":"Chorbhatti",
    "gn:country_code":"IN",
    "gn:dem":278,
    "gn:feature_class":"P",
    "gn:feature_code":"PPL",
    "gn:name":"Chorbhatti",
    "gn:population":0,
    "gn:timezone":"Asia/Kolkata",
    "iso:country":"IN",
    "ks:ks_name":"Chorbhatti",
    "ks:ks_pop":1906,
    "ks:ks_type":"VILLAGE",
    "ks:ks_uagg_main":0,
    "name:eng_x_preferred":[
        "Chorbhatti"
    ],
    "wof:name":"Chorbhatti",
    "wof:placetype":"neighbourhood",
    "wof:population":1906
},
  "geometry": {"coordinates":[81.840023,22.014393],"type":"Point"}
}