{
  "type": "Feature",
  "properties": {
    "iso:country":"IN",
    "ks:ks_name":"Tangarjore",
    "ks:ks_pop":204,
    "ks:ks_type":"HABITATION",
    "name:eng_x_preferred":[
        "Tangarjore"
    ],
    "wof:name":"Tangarjore",
    "wof:placetype":"locality",
    "wof:population":204
},
  "geometry": {"coordinates":[83.90454800000001,22.26948],"type":"Point"}
}