{
  "type": "Feature",
  "properties": {
    "gn:admin1_code":"19",
    "gn:admin2_code":"579.0",
    "gn:asciiname":"Padasavli",
    "gn:country_code":"IN",
    "gn:dem":503,
    "gn:feature_class":"P",
    "gn:feature_code":"PPL",
    "gn:name":"Padas\u0101vli",
    "gn:population":0,
    "gn:timezone":"Asia/Kolkata",
    "iso:country":"IN",
    "name:und_x_variant":[
        "Padas\u0101vli",
        "Pars\u0101wli"
    ],
    "wof:name":"Padasavli",
    "wof:placetype":"locality"
},
  "geometry": {"coordinates":[76.45868,17.59689],"type":"Point"}
}