{
  "type": "Feature",
  "properties": {
    "gn:admin1_code":"36",
    "gn:admin2_code":"191.0",
    "gn:asciiname":"Purwa",
    "gn:country_code":"IN",
    "gn:dem":89,
    "gn:feature_class":"P",
    "gn:feature_code":"PPL",
    "gn:name":"Purwa",
    "gn:population":0,
    "gn:timezone":"Asia/Kolkata",
    "iso:country":"IN",
    "name:bpy_x_preferred":[
        "\u09aa\u09c1\u09b0\u09f1\u09be"
    ],
    "name:ceb_x_preferred":[
        "Purwa"
    ],
    "name:hin_x_preferred":[
        "\u092a\u0942\u0930\u094d\u0935\u093e"
    ],
    "name:ita_x_preferred":[
        "Purwa"
    ],
    "name:mlg_x_preferred":[
        "Purwa"
    ],
    "name:msa_x_preferred":[
        "Purwa"
    ],
    "name:new_x_preferred":[
        "\u092a\u0941\u0930\u0935\u093e \u0924\u0939\u0938\u0940\u0932"
    ],
    "name:nld_x_preferred":[
        "Purwa"
    ],
    "name:ori_x_preferred":[
        "\u0b2a\u0b41\u0b30\u0b4d\u0b71\u0b3e"
    ],
    "name:pnb_x_preferred":[
        "\u067e\u0631\u0648\u0627"
    ],
    "name:pol_x_preferred":[
        "Purwa"
    ],
    "name:por_x_preferred":[
        "Purwa"
    ],
    "name:swe_x_preferred":[
        "Purwa"
    ],
    "name:urd_x_preferred":[
        "\u067e\u0631\u0648\u0627"
    ],
    "name:vie_x_preferred":[
        "Purwa"
    ],
    "name:zho_x_preferred":[
        "\u666e\u5c14\u74e6"
    ],
    "wof:name":"Purwa",
    "wof:placetype":"neighbourhood"
},
  "geometry": {"coordinates":[82.73565000000001,26.19873],"type":"Point"}
}