{
  "type": "Feature",
  "properties": {
    "iso:country":"IN",
    "ks:ks_alt_nam":"SUSALADVASTI",
    "ks:ks_name":"Susaladvasti",
    "ks:ks_pop":92,
    "ks:ks_type":"HABITATION",
    "name:eng_x_preferred":[
        "Susaladvasti"
    ],
    "wof:name":"Susaladvasti",
    "wof:placetype":"locality",
    "wof:population":92
},
  "geometry": {"coordinates":[75.489214,17.170965],"type":"Point"}
}