{
  "type": "Feature",
  "properties": {
    "iso:country":"IN",
    "ks:ks_name":"Sawarooppur",
    "ks:ks_pop":163,
    "ks:ks_type":"HABITATION",
    "ks:ks_uagg_main":0,
    "name:eng_x_preferred":[
        "Sawarooppur"
    ],
    "wof:name":"Sawarooppur",
    "wof:placetype":"neighbourhood",
    "wof:population":163
},
  "geometry": {"coordinates":[78.59473699999999,27.486697],"type":"Point"}
}