{
  "type": "Feature",
  "properties": {
    "iso:country":"IN",
    "ks:ks_name":"Narsingpur",
    "ks:ks_pop":288,
    "ks:ks_type":"VILLAGE",
    "name:eng_x_preferred":[
        "Narsingpur"
    ],
    "wof:name":"Narsingpur",
    "wof:placetype":"locality",
    "wof:population":288
},
  "geometry": {"coordinates":[75.147413,20.274978],"type":"Point"}
}