{
  "type": "Feature",
  "properties": {
    "iso:country":"IN",
    "ks:ks_name":"Gamallapeta",
    "ks:ks_pop":570,
    "ks:ks_type":"HABITATION",
    "name:eng_x_preferred":[
        "Gamallapeta"
    ],
    "wof:name":"Gamallapeta",
    "wof:placetype":"locality",
    "wof:population":570
},
  "geometry": {"coordinates":[81.82231899999999,16.507448],"type":"Point"}
}