{
  "type": "Feature",
  "properties": {
    "gn:admin1_code":"11",
    "gn:admin2_code":"27.0",
    "gn:asciiname":"Nagohi",
    "gn:country_code":"IN",
    "gn:dem":970,
    "gn:feature_class":"P",
    "gn:feature_code":"PPL",
    "gn:name":"Nagohi",
    "gn:population":0,
    "gn:timezone":"Asia/Kolkata",
    "iso:country":"IN",
    "wof:name":"Nagohi",
    "wof:placetype":"locality"
},
  "geometry": {"coordinates":[76.83208,31.83488],"type":"Point"}
}