{
  "type": "Feature",
  "properties": {
    "gn:admin1_code":"19.0",
    "gn:admin2_code":"572.0",
    "gn:asciiname":"Muniyanpalya",
    "gn:country_code":"IN",
    "gn:dem":854,
    "gn:feature_class":"P",
    "gn:feature_code":"PPL",
    "gn:name":"Muniyanp\u0101lya",
    "gn:population":0,
    "gn:timezone":"Asia/Kolkata",
    "iso:country":"IN",
    "ks:ks_name":"Muniyanapalya",
    "ks:ks_pop":118,
    "ks:ks_type":"HABITATION",
    "ks:ks_uagg_main":0,
    "name:eng_x_preferred":[
        "Muniyanapalya"
    ],
    "wof:name":"Muniyanapalya",
    "wof:placetype":"neighbourhood",
    "wof:population":118
},
  "geometry": {"coordinates":[77.472565,13.10155],"type":"Point"}
}