{
  "type": "Feature",
  "properties": {
    "iso:country":"IN",
    "ks:ks_name":"Bommarasanahally",
    "ks:ks_pop":300,
    "ks:ks_type":"HABITATION",
    "name:eng_x_preferred":[
        "Bommarasanahally"
    ],
    "wof:name":"Bommarasanahally",
    "wof:placetype":"locality",
    "wof:population":300
},
  "geometry": {"coordinates":[76.933941,13.808657],"type":"Point"}
}