{
  "type": "Feature",
  "properties": {
    "gn:admin1_code":"10",
    "gn:admin2_code":"83.0",
    "gn:asciiname":"Asadpur Khera",
    "gn:country_code":"IN",
    "gn:dem":220,
    "gn:feature_class":"P",
    "gn:feature_code":"PPL",
    "gn:name":"Asadpur Khera",
    "gn:population":0,
    "gn:timezone":"Asia/Kolkata",
    "iso:country":"IN",
    "wof:name":"Asadpur Khera",
    "wof:placetype":"locality"
},
  "geometry": {"coordinates":[76.6324,28.45264],"type":"Point"}
}