{
  "type": "Feature",
  "properties": {
    "gn:admin1_code":"28.0",
    "gn:admin2_code":"339.0",
    "gn:asciiname":"Hansdima",
    "gn:country_code":"IN",
    "gn:dem":187,
    "gn:feature_class":"P",
    "gn:feature_code":"PPL",
    "gn:name":"Hansdima",
    "gn:population":0,
    "gn:timezone":"Asia/Kolkata",
    "iso:country":"IN",
    "wof:name":"Hansdima",
    "wof:placetype":"locality"
},
  "geometry": {"coordinates":[86.90642,23.51942],"type":"Point"}
}