{
  "type": "Feature",
  "properties": {
    "iso:country":"IN",
    "ks:ks_name":"Samadpur Bhawa",
    "ks:ks_pop":868,
    "ks:ks_type":"VILLAGE",
    "name:eng_x_preferred":[
        "Samadpur Bhawa"
    ],
    "wof:name":"Samadpur Bhawa",
    "wof:placetype":"locality",
    "wof:population":868
},
  "geometry": {"coordinates":[80.603706,26.842166],"type":"Point"}
}