{
  "type": "Feature",
  "properties": {
    "gn:admin1_code":"37",
    "gn:admin2_code":"407.0",
    "gn:asciiname":"Sambhupipar",
    "gn:country_code":"IN",
    "gn:dem":793,
    "gn:feature_class":"P",
    "gn:feature_code":"PPL",
    "gn:name":"Sambhup\u012bpar",
    "gn:population":0,
    "gn:timezone":"Asia/Kolkata",
    "iso:country":"IN",
    "ks:ks_name":"Shambhupiper",
    "ks:ks_pop":239,
    "ks:ks_type":"HABITATION",
    "name:eng_x_preferred":[
        "Shambhupiper"
    ],
    "name:eng_x_variant":[
        "Sambhupipar"
    ],
    "wof:name":"Shambhupiper",
    "wof:placetype":"locality",
    "wof:population":239
},
  "geometry": {"coordinates":[81.126604,22.278502],"type":"Point"}
}