{
  "type": "Feature",
  "properties": {
    "gn:admin1_code":"37",
    "gn:admin2_code":"407.0",
    "gn:asciiname":"Sambhupipar",
    "gn:country_code":"IN",
    "gn:dem":793,
    "gn:feature_class":"P",
    "gn:feature_code":"PPL",
    "gn:name":"Sambhup\u012bpar",
    "gn:population":0,
    "gn:timezone":"Asia/Kolkata",
    "iso:country":"IN",
    "wof:name":"Sambhupipar",
    "wof:placetype":"locality"
},
  "geometry": {"coordinates":[81.12721999999999,22.27739],"type":"Point"}
}