{
  "type": "Feature",
  "properties": {
    "gn:admin1_code":"36",
    "gn:admin2_code":"147.0",
    "gn:asciiname":"Tikri",
    "gn:country_code":"IN",
    "gn:dem":168,
    "gn:feature_class":"P",
    "gn:feature_code":"PPL",
    "gn:name":"T\u012bkri",
    "gn:population":0,
    "gn:timezone":"Asia/Kolkata",
    "iso:country":"IN",
    "name:ceb_x_preferred":[
        "Tikri"
    ],
    "name:swe_x_preferred":[
        "Tikri"
    ],
    "wof:name":"Tikri",
    "wof:placetype":"locality"
},
  "geometry": {"coordinates":[78.27334999999999,27.17572],"type":"Point"}
}