{
  "type": "Feature",
  "properties": {
    "iso:country":"IN",
    "ks:ks_name":"Lakkesiripalke",
    "ks:ks_pop":125,
    "ks:ks_type":"HABITATION",
    "name:eng_x_preferred":[
        "Lakkesiripalke"
    ],
    "wof:name":"Lakkesiripalke",
    "wof:placetype":"locality",
    "wof:population":125
},
  "geometry": {"coordinates":[74.949433,13.156153],"type":"Point"}
}