{
  "type": "Feature",
  "properties": {
    "iso:country":"IN",
    "ks:ks_name":"Bhadar Singh Ki Dhani",
    "ks:ks_pop":15,
    "ks:ks_type":"HABITATION",
    "name:eng_x_preferred":[
        "Bhadar Singh Ki Dhani"
    ],
    "wof:name":"Bhadar Singh Ki Dhani",
    "wof:placetype":"locality",
    "wof:population":15
},
  "geometry": {"coordinates":[74.38737500000001,29.541697],"type":"Point"}
}