{
  "type": "Feature",
  "properties": {
    "gn:admin1_code":"38.0",
    "gn:admin2_code":"353.0",
    "gn:asciiname":"Baliapatra",
    "gn:country_code":"IN",
    "gn:dem":89,
    "gn:feature_class":"P",
    "gn:feature_code":"PPL",
    "gn:name":"Bali\u0101patra",
    "gn:population":0,
    "gn:timezone":"Asia/Kolkata",
    "iso:country":"IN",
    "ks:ks_alt_nam":"Bali\u0101patra",
    "ks:ks_name":"Baliapatra",
    "ks:ks_pop":468,
    "ks:ks_type":"VILLAGE",
    "name:eng_x_preferred":[
        "Baliapatra"
    ],
    "name:eng_x_variant":[
        "Bali\u0101patra"
    ],
    "wof:name":"Baliapatra",
    "wof:placetype":"locality",
    "wof:population":468
},
  "geometry": {"coordinates":[87.739328,24.374874],"type":"Point"}
}