{
  "type": "Feature",
  "properties": {
    "iso:country":"IN",
    "ks:ks_name":"Maniyampatti",
    "ks:ks_pop":230,
    "ks:ks_type":"HABITATION",
    "name:eng_x_preferred":[
        "Maniyampatti"
    ],
    "wof:name":"Maniyampatti",
    "wof:placetype":"locality",
    "wof:population":230
},
  "geometry": {"coordinates":[78.585928,10.99222],"type":"Point"}
}