{
  "type": "Feature",
  "properties": {
    "iso:country":"IN",
    "ks:ks_name":"Haribaskar Colony",
    "ks:ks_pop":655,
    "ks:ks_type":"HABITATION",
    "ks:ks_uagg_main":0,
    "name:eng_x_preferred":[
        "Haribaskar Colony"
    ],
    "wof:name":"Haribaskar Colony",
    "wof:placetype":"locality",
    "wof:population":655
},
  "geometry": {"coordinates":[78.63411600000001,10.775943],"type":"Point"}
}