{
  "type": "Feature",
  "properties": {
    "gn:admin1_code":"11",
    "gn:admin2_code":"27.0",
    "gn:asciiname":"Dewali Badehr",
    "gn:country_code":"IN",
    "gn:dem":1250,
    "gn:feature_class":"P",
    "gn:feature_code":"PPL",
    "gn:name":"Dew\u0101li Badehr",
    "gn:population":0,
    "gn:timezone":"Asia/Kolkata",
    "iso:country":"IN",
    "wof:name":"Dewali Badehr",
    "wof:placetype":"locality"
},
  "geometry": {"coordinates":[76.83311999999999,31.79564],"type":"Point"}
}