{
  "type": "Feature",
  "properties": {
    "gn:admin1_code":"12.0",
    "gn:admin2_code":"006",
    "gn:asciiname":"Tarutin Dhara",
    "gn:country_code":"IN",
    "gn:dem":1476,
    "gn:feature_class":"P",
    "gn:feature_code":"PPL",
    "gn:name":"Tarutin Dhara",
    "gn:population":0,
    "gn:timezone":"Asia/Kolkata",
    "iso:country":"IN",
    "name:und_x_variant":[
        "Tarutla Dhara",
        "Tarutala Dhara"
    ],
    "wof:name":"Tarutin Dhara",
    "wof:placetype":"locality"
},
  "geometry": {"coordinates":[74.21219000000001,33.44153],"type":"Point"}
}