{
  "type": "Feature",
  "properties": {
    "gn:admin1_code":"12.0",
    "gn:admin2_code":"004",
    "gn:asciiname":"Astangas",
    "gn:country_code":"IN",
    "gn:dem":3052,
    "gn:feature_class":"P",
    "gn:feature_code":"PPL",
    "gn:name":"Astangas",
    "gn:population":0,
    "gn:timezone":"Asia/Kolkata",
    "iso:country":"IN",
    "wof:name":"Astangas",
    "wof:placetype":"locality"
},
  "geometry": {"coordinates":[76.19167,34.55833],"type":"Point"}
}