{
  "type": "Feature",
  "properties": {
    "iso:country":"IN",
    "ks:ks_alt_nam":"Shurpur XXX",
    "ks:ks_name":"Shurpur Xxx",
    "ks:ks_pop":2514,
    "ks:ks_type":"HABITATION",
    "name:eng_x_preferred":[
        "Shurpur Xxx"
    ],
    "wof:name":"Shurpur Xxx",
    "wof:placetype":"locality",
    "wof:population":2514
},
  "geometry": {"coordinates":[78.769779,27.775584],"type":"Point"}
}