{
  "type": "Feature",
  "properties": {
    "iso:country":"IN",
    "ks:ks_alt_nam":"Sagadip\u0101l",
    "ks:ks_name":"Sagadipal",
    "ks:ks_type":"VILLAGE",
    "name:eng_x_preferred":[
        "Sagadipal"
    ],
    "name:eng_x_variant":[
        "Sagadip\u0101l"
    ],
    "wof:name":"Sagadipal",
    "wof:placetype":"locality"
},
  "geometry": {"coordinates":[85.105768,21.097191],"type":"Point"}
}