{
  "type": "Feature",
  "properties": {
    "iso:country":"IN",
    "ks:ks_name":"Cheruthana",
    "ks:ks_pop":1757,
    "ks:ks_type":"VILLAGE",
    "name:eng_x_preferred":[
        "Cheruthana"
    ],
    "wof:name":"Cheruthana",
    "wof:placetype":"locality",
    "wof:population":1757
},
  "geometry": {"coordinates":[76.438867,9.343376],"type":"Point"}
}