{
  "type": "Feature",
  "properties": {
    "iso:country":"IN",
    "ks:ks_name":"30 AS-A",
    "ks:ks_pop":191,
    "ks:ks_type":"VILLAGE",
    "name:eng_x_preferred":[
        "30 AS-A"
    ],
    "wof:name":"30 AS-A",
    "wof:placetype":"locality",
    "wof:population":191
},
  "geometry": {"coordinates":[72.886428,28.867766],"type":"Point"}
}