{
  "type": "Feature",
  "properties": {
    "iso:country":"IN",
    "ks:ks_alt_nam":"Bel\u0101t\u0101nr",
    "ks:ks_name":"Belatanr",
    "ks:ks_type":"VILLAGE",
    "name:eng_x_preferred":[
        "Belatanr"
    ],
    "name:eng_x_variant":[
        "Bel\u0101t\u0101nr"
    ],
    "wof:name":"Belatanr",
    "wof:placetype":"locality"
},
  "geometry": {"coordinates":[86.219351,24.682256],"type":"Point"}
}