{
  "type": "Feature",
  "properties": {
    "gn:admin1_code":"25.0",
    "gn:admin2_code":"619.0",
    "gn:asciiname":"Mangottainattam",
    "gn:country_code":"IN",
    "gn:dem":18,
    "gn:feature_class":"P",
    "gn:feature_code":"PPL",
    "gn:name":"M\u0101ngottainattam",
    "gn:population":0,
    "gn:timezone":"Asia/Kolkata",
    "iso:country":"IN",
    "wof:name":"Mangottainattam",
    "wof:placetype":"locality"
},
  "geometry": {"coordinates":[79.46646,10.54771],"type":"Point"}
}