{
  "type": "Feature",
  "properties": {
    "iso:country":"IN",
    "ks:ks_name":"Middle Ultapani",
    "ks:ks_pop":172,
    "ks:ks_type":"HABITATION",
    "name:eng_x_preferred":[
        "Middle Ultapani"
    ],
    "wof:name":"Middle Ultapani",
    "wof:placetype":"locality",
    "wof:population":172
},
  "geometry": {"coordinates":[90.303561,26.778132],"type":"Point"}
}