{
  "type": "Feature",
  "properties": {
    "gn:admin1_code":"2.0",
    "gn:asciiname":"Burugpalli",
    "gn:country_code":"IN",
    "gn:dem":452,
    "gn:feature_class":"P",
    "gn:feature_code":"PPL",
    "gn:name":"Burugpalli",
    "gn:population":0,
    "gn:timezone":"Asia/Kolkata",
    "iso:country":"IN",
    "wof:name":"Burugpalli",
    "wof:placetype":"locality"
},
  "geometry": {"coordinates":[78.45644,19.15131],"type":"Point"}
}