{
  "type": "Feature",
  "properties": {
    "iso:country":"IN",
    "ks:ks_name":"Piperjoriya",
    "ks:ks_pop":141,
    "ks:ks_type":"HABITATION",
    "name:eng_x_preferred":[
        "Piperjoriya"
    ],
    "wof:name":"Piperjoriya",
    "wof:placetype":"locality",
    "wof:population":141
},
  "geometry": {"coordinates":[87.418567,24.805262],"type":"Point"}
}