{
  "type": "Feature",
  "properties": {
    "iso:country":"IN",
    "ks:ks_name":"Lalvadi",
    "ks:ks_pop":337,
    "ks:ks_type":"HABITATION",
    "name:eng_x_preferred":[
        "Lalvadi"
    ],
    "wof:name":"Lalvadi",
    "wof:placetype":"locality",
    "wof:population":337
},
  "geometry": {"coordinates":[74.08994300000001,18.40439],"type":"Point"}
}