{
  "type": "Feature",
  "properties": {
    "iso:country":"IN",
    "ks:ks_name":"Bamaniya",
    "ks:ks_pop":894,
    "ks:ks_type":"VILLAGE",
    "name:eng_x_preferred":[
        "Bamaniya"
    ],
    "wof:name":"Bamaniya",
    "wof:placetype":"locality",
    "wof:population":894
},
  "geometry": {"coordinates":[73.989287,24.062342],"type":"Point"}
}