{
  "type": "Feature",
  "properties": {
    "iso:country":"IN",
    "ks:ks_name":"Lassiamba",
    "ks:ks_pop":163,
    "ks:ks_type":"HABITATION",
    "name:eng_x_preferred":[
        "Lassiamba"
    ],
    "wof:name":"Lassiamba",
    "wof:placetype":"locality",
    "wof:population":163
},
  "geometry": {"coordinates":[84.040144,22.604768],"type":"Point"}
}