{
  "type": "Feature",
  "properties": {
    "iso:country":"IN",
    "ks:ks_name":"Baruwa Seduri",
    "ks:ks_pop":569,
    "ks:ks_type":"HABITATION",
    "name:eng_x_preferred":[
        "Baruwa Seduri"
    ],
    "wof:name":"Baruwa Seduri",
    "wof:placetype":"locality",
    "wof:population":569
},
  "geometry": {"coordinates":[81.00756,24.879828],"type":"Point"}
}