{
  "type": "Feature",
  "properties": {
    "iso:country":"IN",
    "ks:ks_name":"Nuapani",
    "ks:ks_pop":435,
    "ks:ks_type":"VILLAGE",
    "ks:ks_uagg_main":0,
    "name:eng_x_preferred":[
        "Nuapani"
    ],
    "wof:name":"Nuapani",
    "wof:placetype":"neighbourhood",
    "wof:population":435
},
  "geometry": {"coordinates":[85.60857,20.921539],"type":"Point"}
}