{
  "type": "Feature",
  "properties": {
    "iso:country":"IN",
    "ks:ks_name":"Rengna",
    "ks:ks_pop":550,
    "ks:ks_type":"HABITATION",
    "name:eng_x_preferred":[
        "Rengna"
    ],
    "wof:name":"Rengna",
    "wof:placetype":"locality",
    "wof:population":550
},
  "geometry": {"coordinates":[80.41541700000001,25.91475],"type":"Point"}
}