{
  "type": "Feature",
  "properties": {
    "iso:country":"IN",
    "ks:ks_name":"Kodangadde",
    "ks:ks_pop":13,
    "ks:ks_type":"HABITATION",
    "name:eng_x_preferred":[
        "Kodangadde"
    ],
    "wof:name":"Kodangadde",
    "wof:placetype":"locality",
    "wof:population":13
},
  "geometry": {"coordinates":[74.705262,14.890543],"type":"Point"}
}