{
  "type": "Feature",
  "properties": {
    "gn:admin1_code":"12.0",
    "gn:admin2_code":"13.0",
    "gn:asciiname":"Lasipur",
    "gn:country_code":"IN",
    "gn:dem":1652,
    "gn:feature_class":"P",
    "gn:feature_code":"PPL",
    "gn:name":"Lasipur",
    "gn:population":0,
    "gn:timezone":"Asia/Kolkata",
    "iso:country":"IN",
    "wof:name":"Lasipur",
    "wof:placetype":"locality"
},
  "geometry": {"coordinates":[74.94167,33.81445],"type":"Point"}
}