{
  "type": "Feature",
  "properties": {
    "iso:country":"IN",
    "ks:ks_name":"Arekarwadi",
    "ks:ks_pop":200,
    "ks:ks_type":"HABITATION",
    "name:eng_x_preferred":[
        "Arekarwadi"
    ],
    "wof:name":"Arekarwadi",
    "wof:placetype":"locality",
    "wof:population":200
},
  "geometry": {"coordinates":[73.539053,16.616787],"type":"Point"}
}