{
  "type": "Feature",
  "properties": {
    "gn:admin1_code":"36",
    "gn:admin2_code":"155.0",
    "gn:asciiname":"Daria",
    "gn:country_code":"IN",
    "gn:dem":135,
    "gn:feature_class":"P",
    "gn:feature_code":"PPL",
    "gn:name":"Daria",
    "gn:population":0,
    "gn:timezone":"Asia/Kolkata",
    "iso:country":"IN",
    "name:ara_x_preferred":[
        "\u062f\u0627\u0631\u064a\u0627"
    ],
    "name:ben_bn_x_preferred":[
        "\u09a6\u09be\u09b0\u09bf\u09df\u09be"
    ],
    "name:ben_in_x_preferred":[
        "\u09a6\u09be\u09b0\u09bf\u09df\u09be"
    ],
    "name:cat_x_preferred":[
        "D\u00e0ria"
    ],
    "name:ces_x_preferred":[
        "Daria"
    ],
    "name:dan_x_preferred":[
        "Daria"
    ],
    "name:deu_x_preferred":[
        "Daria"
    ],
    "name:fin_x_preferred":[
        "Daria"
    ],
    "name:fra_x_preferred":[
        "Daria"
    ],
    "name:guj_x_preferred":[
        "\u0aa6\u0ab0\u0abf\u0aaf\u0abe"
    ],
    "name:heb_x_preferred":[
        "\u05d3\u05e8\u05d9\u05d4"
    ],
    "name:hin_x_preferred":[
        "\u0926\u0930\u093f\u092f\u093e"
    ],
    "name:hrv_x_preferred":[
        "Daria"
    ],
    "name:hun_x_preferred":[
        "Daria"
    ],
    "name:hye_x_preferred":[
        "\u0534\u0561\u0580\u056b\u0561"
    ],
    "name:ita_x_preferred":[
        "Daria"
    ],
    "name:kan_x_preferred":[
        "\u0ca6\u0cb0\u0cbf\u0caf\u0cbe"
    ],
    "name:kat_x_preferred":[
        "\u10d3\u10d0\u10e0\u10d8\u10d0"
    ],
    "name:mal_x_preferred":[
        "\u0d26\u0d3e\u0d30\u0d3f\u0d2f"
    ],
    "name:mar_x_preferred":[
        "\u0926\u0930\u093f\u092f\u093e"
    ],
    "name:nld_x_preferred":[
        "Daria"
    ],
    "name:pan_x_preferred":[
        "\u0a26\u0a30\u0a3f\u0a06"
    ],
    "name:pol_x_preferred":[
        "Daria"
    ],
    "name:por_x_preferred":[
        "Daria"
    ],
    "name:rus_x_preferred":[
        "\u0414\u0430\u0440\u044c\u044f"
    ],
    "name:spa_x_preferred":[
        "Daria"
    ],
    "name:swe_x_preferred":[
        "Daria"
    ],
    "name:tam_x_preferred":[
        "\u0ba4\u0bb0\u0bbf\u0baf\u0bbe"
    ],
    "name:tel_x_preferred":[
        "\u0c26\u0c30\u0c3f\u0c2f\u0c3e"
    ],
    "name:ukr_x_preferred":[
        "\u0414\u0430\u0440\u0456\u044f"
    ],
    "name:urd_x_preferred":[
        "\u062f\u0631\u06cc\u0627"
    ],
    "wof:name":"Daria",
    "wof:placetype":"locality"
},
  "geometry": {"coordinates":[79.8206,27.29351],"type":"Point"}
}