{
  "type": "Feature",
  "properties": {
    "gn:admin1_code":"36",
    "gn:admin2_code":"155.0",
    "gn:asciiname":"Daria",
    "gn:country_code":"IN",
    "gn:dem":135,
    "gn:feature_class":"P",
    "gn:feature_code":"PPL",
    "gn:name":"Daria",
    "gn:population":0,
    "gn:timezone":"Asia/Kolkata",
    "iso:country":"IN",
    "name:cat_x_preferred":[
        "D\u00e0ria"
    ],
    "name:ces_x_preferred":[
        "Daria"
    ],
    "name:dan_x_preferred":[
        "Daria"
    ],
    "name:deu_x_preferred":[
        "Daria"
    ],
    "name:fin_x_preferred":[
        "Daria"
    ],
    "name:fra_x_preferred":[
        "Daria"
    ],
    "name:heb_x_preferred":[
        "\u05d3\u05e8\u05d9\u05d4"
    ],
    "name:hrv_x_preferred":[
        "Daria"
    ],
    "name:hun_x_preferred":[
        "Daria"
    ],
    "name:hye_x_preferred":[
        "\u0534\u0561\u0580\u056b\u0561"
    ],
    "name:ita_x_preferred":[
        "Daria"
    ],
    "name:kat_x_preferred":[
        "\u10d3\u10d0\u10e0\u10d8\u10d0"
    ],
    "name:nld_x_preferred":[
        "Daria"
    ],
    "name:pol_x_preferred":[
        "Daria"
    ],
    "name:por_x_preferred":[
        "Daria"
    ],
    "name:rus_x_preferred":[
        "\u0414\u0430\u0440\u044c\u044f"
    ],
    "name:spa_x_preferred":[
        "Daria"
    ],
    "name:swe_x_preferred":[
        "Daria"
    ],
    "name:ukr_x_preferred":[
        "\u0414\u0430\u0440\u0456\u044f"
    ],
    "wof:name":"Daria",
    "wof:placetype":"locality"
},
  "geometry": {"coordinates":[79.8206,27.29351],"type":"Point"}
}