{
  "type": "Feature",
  "properties": {
    "gn:admin1_code":"12",
    "gn:asciiname":"Nerian",
    "gn:country_code":"IN",
    "gn:dem":2509,
    "gn:feature_class":"P",
    "gn:feature_code":"PPL",
    "gn:name":"Neri\u0101n",
    "gn:population":0,
    "gn:timezone":"Asia/Kolkata",
    "iso:country":"IN",
    "wof:name":"Nerian",
    "wof:placetype":"locality"
},
  "geometry": {"coordinates":[74.17092,34.04152],"type":"Point"}
}