{
  "type": "Feature",
  "properties": {
    "gn:admin1_code":"39.0",
    "gn:admin2_code":"66.0",
    "gn:asciiname":"Malla Pachhonia",
    "gn:country_code":"IN",
    "gn:dem":311,
    "gn:feature_class":"P",
    "gn:feature_code":"PPL",
    "gn:name":"Malla Pachhonia",
    "gn:population":0,
    "gn:timezone":"Asia/Kolkata",
    "iso:country":"IN",
    "ks:ks_name":"Talla Pachaunia",
    "ks:ks_pop":264,
    "ks:ks_type":"VILLAGE",
    "ks:ks_uagg_main":0,
    "name:eng_x_preferred":[
        "Talla Pachaunia"
    ],
    "wof:name":"Talla Pachaunia",
    "wof:placetype":"neighbourhood",
    "wof:population":264
},
  "geometry": {"coordinates":[79.70471499999999,29.115972],"type":"Point"}
}