{
  "type": "Feature",
  "properties": {
    "gn:admin1_code":"24.0",
    "gn:admin2_code":"101.0",
    "gn:asciiname":"Nathon ki Dhani",
    "gn:country_code":"IN",
    "gn:dem":212,
    "gn:feature_class":"P",
    "gn:feature_code":"PPL",
    "gn:name":"N\u0101thon ki Dh\u0101ni",
    "gn:population":0,
    "gn:timezone":"Asia/Kolkata",
    "iso:country":"IN",
    "wof:name":"Nathon ki Dhani",
    "wof:placetype":"locality"
},
  "geometry": {"coordinates":[73.87761,28.48178],"type":"Point"}
}