{
  "type": "Feature",
  "properties": {
    "gn:admin1_code":"36",
    "gn:admin2_code":"155.0",
    "gn:asciiname":"Chamaran Purwa",
    "gn:country_code":"IN",
    "gn:dem":135,
    "gn:feature_class":"P",
    "gn:feature_code":"PPL",
    "gn:name":"Cham\u0101ran Purwa",
    "gn:population":0,
    "gn:timezone":"Asia/Kolkata",
    "iso:country":"IN",
    "ks:ks_name":"Chmaran Purwa",
    "ks:ks_pop":441,
    "ks:ks_type":"HABITATION",
    "name:eng_x_preferred":[
        "Chmaran Purwa"
    ],
    "name:eng_x_variant":[
        "Chamaran Purwa"
    ],
    "wof:name":"Chmaran Purwa",
    "wof:placetype":"locality",
    "wof:population":441
},
  "geometry": {"coordinates":[79.87665800000001,27.289987],"type":"Point"}
}