{
  "type": "Feature",
  "properties": {
    "iso:country":"IN",
    "ks:ks_name":"Bataguda",
    "ks:ks_pop":1656,
    "ks:ks_type":"VILLAGE",
    "name:eng_x_preferred":[
        "Bataguda"
    ],
    "wof:name":"Bataguda",
    "wof:placetype":"locality",
    "wof:population":1656
},
  "geometry": {"coordinates":[83.847875,20.120986],"type":"Point"}
}