{
  "type": "Feature",
  "properties": {
    "iso:country":"IN",
    "ks:ks_alt_nam":"RAM CH. PARA",
    "ks:ks_name":"Ram Ch. Para",
    "ks:ks_pop":145,
    "ks:ks_type":"HABITATION",
    "name:eng_x_preferred":[
        "Ram Ch. Para"
    ],
    "wof:name":"Ram Ch. Para",
    "wof:placetype":"locality",
    "wof:population":145
},
  "geometry": {"coordinates":[91.672155,23.782947],"type":"Point"}
}