{
  "type": "Feature",
  "properties": {
    "iso:country":"IN",
    "ks:ks_alt_nam":"AD Colony",
    "ks:ks_name":"Ad Colony",
    "ks:ks_pop":320,
    "ks:ks_type":"HABITATION",
    "name:eng_x_preferred":[
        "Ad Colony"
    ],
    "wof:name":"Ad Colony",
    "wof:placetype":"locality",
    "wof:population":320
},
  "geometry": {"coordinates":[79.06998,10.149812],"type":"Point"}
}