{
  "type": "Feature",
  "properties": {
    "iso:country":"IN",
    "ks:ks_name":"Dikoli Kalan",
    "ks:ks_pop":1495,
    "ks:ks_type":"HABITATION",
    "name:eng_x_preferred":[
        "Dikoli Kalan"
    ],
    "wof:name":"Dikoli Kalan",
    "wof:placetype":"locality",
    "wof:population":1495
},
  "geometry": {"coordinates":[76.677179,26.305027],"type":"Point"}
}