{
  "type": "Feature",
  "properties": {
    "iso:country":"IN",
    "ks:ks_name":"Porusottampur",
    "ks:ks_pop":1781,
    "ks:ks_type":"VILLAGE",
    "ks:ks_uagg_main":0,
    "name:eng_x_preferred":[
        "Porusottampur"
    ],
    "wof:name":"Porusottampur",
    "wof:placetype":"locality",
    "wof:population":1781
},
  "geometry": {"coordinates":[87.467454,21.647031],"type":"Point"}
}