{
  "type": "Feature",
  "properties": {
    "gn:admin1_code":"36.0",
    "gn:admin2_code":"149",
    "gn:asciiname":"Taksena",
    "gn:country_code":"IN",
    "gn:dem":156,
    "gn:feature_class":"P",
    "gn:feature_code":"PPL",
    "gn:name":"Taksena",
    "gn:population":0,
    "gn:timezone":"Asia/Kolkata",
    "iso:country":"IN",
    "ks:ks_name":"Taksena",
    "ks:ks_pop":389,
    "ks:ks_type":"VILLAGE",
    "name:eng_x_preferred":[
        "Taksena"
    ],
    "wof:name":"Taksena",
    "wof:placetype":"locality",
    "wof:population":389
},
  "geometry": {"coordinates":[79.356206,27.908431],"type":"Point"}
}