{
  "type": "Feature",
  "properties": {
    "iso:country":"IN",
    "ks:ks_alt_nam":"Goliyangadi HC",
    "ks:ks_name":"Goliyangadi Hc",
    "ks:ks_pop":200,
    "ks:ks_type":"HABITATION",
    "ks:ks_uagg_main":0,
    "name:eng_x_preferred":[
        "Goliyangadi Hc"
    ],
    "wof:name":"Goliyangadi Hc",
    "wof:placetype":"neighbourhood",
    "wof:population":200
},
  "geometry": {"coordinates":[75.159712,13.005668],"type":"Point"}
}