{
  "type": "Feature",
  "properties": {
    "gn:admin1_code":"36.0",
    "gn:admin2_code":"161",
    "gn:asciiname":"Jagramau",
    "gn:country_code":"IN",
    "gn:dem":152,
    "gn:feature_class":"P",
    "gn:feature_code":"PPL",
    "gn:name":"Jagr\u0101mau",
    "gn:population":0,
    "gn:timezone":"Asia/Kolkata",
    "iso:country":"IN",
    "name:und_x_variant":[
        "Jagr\u0101mau",
        "Jugr\u0101mau"
    ],
    "wof:name":"Jagramau",
    "wof:placetype":"neighbourhood"
},
  "geometry": {"coordinates":[79.05085,26.79605],"type":"Point"}
}