{
  "type": "Feature",
  "properties": {
    "gn:admin1_code":"2",
    "gn:admin2_code":"548.0",
    "gn:asciiname":"Kothur",
    "gn:country_code":"IN",
    "gn:dem":157,
    "gn:feature_class":"P",
    "gn:feature_code":"PPL",
    "gn:name":"Koth\u016br",
    "gn:population":0,
    "gn:timezone":"Asia/Kolkata",
    "iso:country":"IN",
    "name:tel_x_preferred":[
        "\u0c15\u0c4a\u0c24\u0c4d\u0c24\u0c42\u0c30\u0c41"
    ],
    "wof:name":"Kothur",
    "wof:placetype":"locality"
},
  "geometry": {"coordinates":[79.36072,16.54201],"type":"Point"}
}