{
  "type": "Feature",
  "properties": {
    "iso:country":"IN",
    "ks:ks_alt_nam":"kombaithotti",
    "ks:ks_name":"Kombaithotti",
    "ks:ks_pop":300,
    "ks:ks_type":"HABITATION",
    "name:eng_x_preferred":[
        "Kombaithotti"
    ],
    "wof:name":"Kombaithotti",
    "wof:placetype":"locality",
    "wof:population":300
},
  "geometry": {"coordinates":[77.24808,11.690202],"type":"Point"}
}