{
  "type": "Feature",
  "properties": {
    "iso:country":"IN",
    "ks:ks_name":"Angadibail",
    "ks:ks_pop":84,
    "ks:ks_type":"HABITATION",
    "name:eng_x_preferred":[
        "Angadibail"
    ],
    "wof:name":"Angadibail",
    "wof:placetype":"locality",
    "wof:population":84
},
  "geometry": {"coordinates":[74.55653599999999,14.441523],"type":"Point"}
}