{
  "type": "Feature",
  "properties": {
    "iso:country":"IN",
    "ks:ks_name":"Chhakapada",
    "ks:ks_pop":145,
    "ks:ks_type":"HABITATION",
    "name:eng_x_preferred":[
        "Chhakapada"
    ],
    "wof:name":"Chhakapada",
    "wof:placetype":"locality",
    "wof:population":145
},
  "geometry": {"coordinates":[82.86798899999999,19.784703],"type":"Point"}
}