{
  "type": "Feature",
  "properties": {
    "iso:country":"IN",
    "ks:ks_name":"Ramgarh",
    "ks:ks_pop":935,
    "ks:ks_type":"HABITATION",
    "name:eng_x_preferred":[
        "Ramgarh"
    ],
    "wof:name":"Ramgarh",
    "wof:placetype":"locality",
    "wof:population":935
},
  "geometry": {"coordinates":[74.51920800000001,23.38365],"type":"Point"}
}