{
  "type": "Feature",
  "properties": {
    "gn:admin1_code":"37",
    "gn:admin2_code":"408.0",
    "gn:asciiname":"Murum",
    "gn:country_code":"IN",
    "gn:dem":657,
    "gn:feature_class":"P",
    "gn:feature_code":"PPL",
    "gn:name":"Murum",
    "gn:population":0,
    "gn:timezone":"Asia/Kolkata",
    "iso:country":"IN",
    "ks:ks_name":"Murum",
    "ks:ks_pop":119,
    "ks:ks_type":"VILLAGE",
    "name:deu_x_preferred":[
        "Murum"
    ],
    "name:eng_x_preferred":[
        "Murum"
    ],
    "wof:name":"Murum",
    "wof:placetype":"locality",
    "wof:population":119
},
  "geometry": {"coordinates":[80.866862,21.679824],"type":"Point"}
}