{
  "type": "Feature",
  "properties": {
    "gn:admin1_code":"37",
    "gn:admin2_code":"408.0",
    "gn:asciiname":"Murum",
    "gn:country_code":"IN",
    "gn:dem":657,
    "gn:feature_class":"P",
    "gn:feature_code":"PPL",
    "gn:name":"Murum",
    "gn:population":0,
    "gn:timezone":"Asia/Kolkata",
    "iso:country":"IN",
    "name:deu_x_preferred":[
        "Murum"
    ],
    "wof:name":"Murum",
    "wof:placetype":"locality"
},
  "geometry": {"coordinates":[80.86575000000001,21.68045],"type":"Point"}
}