{
  "type": "Feature",
  "properties": {
    "iso:country":"IN",
    "ks:ks_name":"Appikondapalem",
    "ks:ks_pop":107,
    "ks:ks_type":"HABITATION",
    "name:eng_x_preferred":[
        "Appikondapalem"
    ],
    "wof:name":"Appikondapalem",
    "wof:placetype":"locality",
    "wof:population":107
},
  "geometry": {"coordinates":[83.275284,17.823567],"type":"Point"}
}