{
  "type": "Feature",
  "properties": {
    "iso:country":"IN",
    "ks:ks_alt_nam":"Dhungb\u0101ri",
    "ks:ks_alt_nam_2":"Dhungbari",
    "ks:ks_name":"Dhung",
    "ks:ks_type":"VILLAGE",
    "name:eng_x_preferred":[
        "Dhung"
    ],
    "name:eng_x_variant":[
        "Dhungb\u0101ri",
        "Dhungbari"
    ],
    "wof:name":"Dhung",
    "wof:placetype":"locality"
},
  "geometry": {"coordinates":[78.84650000000001,29.918608],"type":"Point"}
}