{
  "type": "Feature",
  "properties": {
    "gn:admin1_code":"25.0",
    "gn:admin2_code":"633.0",
    "gn:asciiname":"Ravgavayakkanur",
    "gn:country_code":"IN",
    "gn:dem":312,
    "gn:feature_class":"P",
    "gn:feature_code":"PPL",
    "gn:name":"Ravgav\u0101yakkan\u016br",
    "gn:population":0,
    "gn:timezone":"Asia/Kolkata",
    "iso:country":"IN",
    "wof:name":"Ravgavayakkanur",
    "wof:placetype":"neighbourhood"
},
  "geometry": {"coordinates":[77.46232999999999,11.26746],"type":"Point"}
}