{
  "type": "Feature",
  "properties": {
    "gn:admin1_code":"11.0",
    "gn:admin2_code":"34.0",
    "gn:asciiname":"Sholtu",
    "gn:country_code":"IN",
    "gn:dem":1914,
    "gn:feature_class":"P",
    "gn:feature_code":"PPL",
    "gn:name":"Sholtu",
    "gn:population":0,
    "gn:timezone":"Asia/Kolkata",
    "iso:country":"IN",
    "wof:name":"Sholtu",
    "wof:placetype":"locality"
},
  "geometry": {"coordinates":[78.10056999999998,31.51273],"type":"Point"}
}