{
  "type": "Feature",
  "properties": {
    "iso:country":"IN",
    "ks:ks_name":"Sarolipada",
    "ks:ks_pop":490,
    "ks:ks_type":"HABITATION",
    "name:eng_x_preferred":[
        "Sarolipada"
    ],
    "wof:name":"Sarolipada",
    "wof:placetype":"locality",
    "wof:population":490
},
  "geometry": {"coordinates":[73.26261700000001,20.109849],"type":"Point"}
}