{
  "type": "Feature",
  "properties": {
    "iso:country":"IN",
    "ks:ks_name":"Sirhaguda",
    "ks:ks_pop":234,
    "ks:ks_type":"HABITATION",
    "name:eng_x_preferred":[
        "Sirhaguda"
    ],
    "wof:name":"Sirhaguda",
    "wof:placetype":"locality",
    "wof:population":234
},
  "geometry": {"coordinates":[82.08538,19.105917],"type":"Point"}
}