{
  "type": "Feature",
  "properties": {
    "gn:admin1_code":"36",
    "gn:admin2_code":"179.0",
    "gn:asciiname":"Chandpur",
    "gn:country_code":"IN",
    "gn:dem":98,
    "gn:feature_class":"P",
    "gn:feature_code":"PPL",
    "gn:name":"Chandpur",
    "gn:population":0,
    "gn:timezone":"Asia/Kolkata",
    "iso:country":"IN",
    "ks:ks_name":"Chandpur",
    "ks:ks_type":"VILLAGE",
    "ks:ks_uagg_main":0,
    "name:ben_x_preferred":[
        "\u099a\u09be\u0981\u09a6\u09aa\u09c1\u09b0"
    ],
    "name:ceb_x_preferred":[
        "Chandpur"
    ],
    "name:deu_x_preferred":[
        "Chandpur"
    ],
    "name:eng_x_preferred":[
        "Chandpur"
    ],
    "name:hin_x_preferred":[
        "\u091a\u093e\u0902\u0926\u092a\u0941\u0930"
    ],
    "name:ita_x_preferred":[
        "Chandpur"
    ],
    "name:nld_x_preferred":[
        "Chandpur"
    ],
    "name:pol_x_preferred":[
        "Chandpur"
    ],
    "name:rus_x_preferred":[
        "\u0427\u0430\u043d\u0434\u043f\u0443\u0440"
    ],
    "name:swe_x_preferred":[
        "Chandpur"
    ],
    "wof:name":"Chandpur",
    "wof:placetype":"neighbourhood"
},
  "geometry": {"coordinates":[82.274612,26.34955],"type":"Point"}
}