{
  "type": "Feature",
  "properties": {
    "gn:admin1_code":"11",
    "gn:admin2_code":"24.0",
    "gn:asciiname":"Ghamrotha",
    "gn:country_code":"IN",
    "gn:dem":1516,
    "gn:feature_class":"P",
    "gn:feature_code":"PPL",
    "gn:name":"Ghamrotha",
    "gn:population":0,
    "gn:timezone":"Asia/Kolkata",
    "iso:country":"IN",
    "wof:name":"Ghamrotha",
    "wof:placetype":"locality"
},
  "geometry": {"coordinates":[76.49110999999998,32.14785],"type":"Point"}
}