{
  "type": "Feature",
  "properties": {
    "gn:admin1_code":"36.0",
    "gn:admin2_code":"143.0",
    "gn:asciiname":"Bolla",
    "gn:country_code":"IN",
    "gn:dem":193,
    "gn:feature_class":"P",
    "gn:feature_code":"PPL",
    "gn:name":"Bolla",
    "gn:population":0,
    "gn:timezone":"Asia/Kolkata",
    "iso:country":"IN",
    "name:ara_x_preferred":[
        "\u0628\u0648\u0644\u0627"
    ],
    "name:deu_x_preferred":[
        "Bolla"
    ],
    "name:fra_x_preferred":[
        "Bolla"
    ],
    "name:jpn_x_preferred":[
        "\u30dc\u30e9"
    ],
    "name:lit_x_preferred":[
        "Bola"
    ],
    "name:por_x_preferred":[
        "Bolla"
    ],
    "name:rus_x_preferred":[
        "\u0411\u043e\u043b\u043b\u0430"
    ],
    "name:sqi_x_preferred":[
        "Ku\u00e7edra"
    ],
    "name:ukr_x_preferred":[
        "\u0411\u043e\u043b\u043b\u0430"
    ],
    "wof:name":"Bolla",
    "wof:placetype":"locality"
},
  "geometry": {"coordinates":[77.92014,27.89626],"type":"Point"}
}