{
  "type": "Feature",
  "properties": {
    "iso:country":"IN",
    "ks:ks_name":"Benagiya",
    "ks:ks_pop":348,
    "ks:ks_type":"VILLAGE",
    "name:eng_x_preferred":[
        "Benagiya"
    ],
    "wof:name":"Benagiya",
    "wof:placetype":"locality",
    "wof:population":348
},
  "geometry": {"coordinates":[73.342911,24.407375],"type":"Point"}
}