{
  "type": "Feature",
  "properties": {
    "iso:country":"IN",
    "ks:ks_alt_nam":"Sarathamukku jn",
    "ks:ks_name":"Sarathamukku Jn",
    "ks:ks_pop":789,
    "ks:ks_type":"HABITATION",
    "name:eng_x_preferred":[
        "Sarathamukku Jn"
    ],
    "wof:name":"Sarathamukku Jn",
    "wof:placetype":"locality",
    "wof:population":789
},
  "geometry": {"coordinates":[76.715503,8.801527],"type":"Point"}
}