{
  "type": "Feature",
  "properties": {
    "iso:country":"IN",
    "ks:ks_name":"Sampat Nagar",
    "ks:ks_pop":168,
    "ks:ks_type":"HABITATION",
    "name:eng_x_preferred":[
        "Sampat Nagar"
    ],
    "wof:name":"Sampat Nagar",
    "wof:placetype":"locality",
    "wof:population":168
},
  "geometry": {"coordinates":[71.246047,27.540644],"type":"Point"}
}