{
  "type": "Feature",
  "properties": {
    "gn:admin1_code":"35",
    "gn:admin2_code":"427.0",
    "gn:asciiname":"Arjundeh",
    "gn:country_code":"IN",
    "gn:dem":469,
    "gn:feature_class":"P",
    "gn:feature_code":"PPL",
    "gn:name":"Arjundeh",
    "gn:population":0,
    "gn:timezone":"Asia/Kolkata",
    "iso:country":"IN",
    "ks:ks_name":"Arjunda",
    "ks:ks_pop":654,
    "ks:ks_type":"VILLAGE",
    "name:eng_x_preferred":[
        "Arjunda"
    ],
    "name:eng_x_variant":[
        "Arjundeh"
    ],
    "wof:name":"Arjunda",
    "wof:placetype":"locality",
    "wof:population":654
},
  "geometry": {"coordinates":[79.171983,23.276255],"type":"Point"}
}