{
  "type": "Feature",
  "properties": {
    "iso:country":"IN",
    "ks:ks_alt_nam":"K\u0101k\u0101deo",
    "ks:ks_name":"Kakadeo",
    "ks:ks_type":"VILLAGE",
    "ks:ks_uagg_main":0,
    "name:eng_x_preferred":[
        "Kakadeo"
    ],
    "name:eng_x_variant":[
        "K\u0101k\u0101deo"
    ],
    "wof:name":"Kakadeo",
    "wof:placetype":"neighbourhood"
},
  "geometry": {"coordinates":[80.290998,26.474131],"type":"Point"}
}