{
  "type": "Feature",
  "properties": {
    "iso:country":"IN",
    "ks:ks_name":"Dinanathpur Pt I",
    "ks:ks_pop":3362,
    "ks:ks_type":"VILLAGE",
    "name:eng_x_preferred":[
        "Dinanathpur Pt I"
    ],
    "wof:name":"Dinanathpur Pt I",
    "wof:placetype":"locality",
    "wof:population":3362
},
  "geometry": {"coordinates":[92.528103,24.511115],"type":"Point"}
}