{
  "type": "Feature",
  "properties": {
    "iso:country":"IN",
    "ks:ks_name":"Sohag Pur",
    "ks:ks_pop":2044,
    "ks:ks_type":"VILLAGE",
    "name:eng_x_preferred":[
        "Sohag Pur"
    ],
    "wof:name":"Sohag Pur",
    "wof:placetype":"locality",
    "wof:population":2044
},
  "geometry": {"coordinates":[87.44514100000001,22.018625],"type":"Point"}
}