{
  "type": "Feature",
  "properties": {
    "iso:country":"IN",
    "ks:ks_alt_nam":"balayi",
    "ks:ks_name":"Balayi",
    "ks:ks_pop":368,
    "ks:ks_type":"HABITATION",
    "name:eng_x_preferred":[
        "Balayi"
    ],
    "wof:name":"Balayi",
    "wof:placetype":"locality",
    "wof:population":368
},
  "geometry": {"coordinates":[75.273033,12.720484],"type":"Point"}
}