{
  "type": "Feature",
  "properties": {
    "gn:admin1_code":"39.0",
    "gn:admin2_code":"056",
    "gn:asciiname":"Bhetiara",
    "gn:country_code":"IN",
    "gn:dem":1653,
    "gn:feature_class":"P",
    "gn:feature_code":"PPL",
    "gn:name":"Bheti\u0101ra",
    "gn:population":0,
    "gn:timezone":"Asia/Kolkata",
    "iso:country":"IN",
    "name:und_x_variant":[
        "Batari",
        "Bheti\u0101ra"
    ],
    "wof:name":"Bhetiara",
    "wof:placetype":"locality"
},
  "geometry": {"coordinates":[78.5151,30.61052],"type":"Point"}
}