{
  "type": "Feature",
  "properties": {
    "gn:admin1_code":"35.0",
    "gn:admin2_code":"461",
    "gn:asciiname":"Chokan",
    "gn:country_code":"IN",
    "gn:dem":533,
    "gn:feature_class":"P",
    "gn:feature_code":"PPL",
    "gn:name":"Chokan",
    "gn:population":0,
    "gn:timezone":"Asia/Kolkata",
    "iso:country":"IN",
    "wof:name":"Chokan",
    "wof:placetype":"locality"
},
  "geometry": {"coordinates":[82.04498000000002,23.12035],"type":"Point"}
}