{
  "type": "Feature",
  "properties": {
    "iso:country":"IN",
    "ks:ks_alt_nam":"PIPARI",
    "ks:ks_name":"Pipari",
    "ks:ks_pop":201,
    "ks:ks_type":"HABITATION",
    "name:eng_x_preferred":[
        "Pipari"
    ],
    "wof:name":"Pipari",
    "wof:placetype":"locality",
    "wof:population":201
},
  "geometry": {"coordinates":[84.30775,24.94088],"type":"Point"}
}