{
  "type": "Feature",
  "properties": {
    "iso:country":"IN",
    "ks:ks_name":"Marchawa Choota",
    "ks:ks_pop":492,
    "ks:ks_type":"HABITATION",
    "ks:ks_uagg_main":0,
    "name:eng_x_preferred":[
        "Marchawa Choota"
    ],
    "wof:name":"Marchawa Choota",
    "wof:placetype":"neighbourhood",
    "wof:population":492
},
  "geometry": {"coordinates":[83.489885,27.361129],"type":"Point"}
}