{
  "type": "Feature",
  "properties": {
    "iso:country":"IN",
    "ks:ks_alt_nam":"uppalathur",
    "ks:ks_name":"Uppalathur",
    "ks:ks_pop":68,
    "ks:ks_type":"HABITATION",
    "name:eng_x_preferred":[
        "Uppalathur"
    ],
    "wof:name":"Uppalathur",
    "wof:placetype":"locality",
    "wof:population":68
},
  "geometry": {"coordinates":[79.47192800000001,12.323621],"type":"Point"}
}