{
  "type": "Feature",
  "properties": {
    "iso:country":"IN",
    "ks:ks_name":"Bhandibaba",
    "ks:ks_pop":107,
    "ks:ks_type":"HABITATION",
    "name:eng_x_preferred":[
        "Bhandibaba"
    ],
    "wof:name":"Bhandibaba",
    "wof:placetype":"locality",
    "wof:population":107
},
  "geometry": {"coordinates":[80.25679700000001,27.689487],"type":"Point"}
}