{
  "type": "Feature",
  "properties": {
    "iso:country":"IN",
    "ks:ks_name":"Pulimoodu",
    "ks:ks_pop":600,
    "ks:ks_type":"HABITATION",
    "ks:ks_uagg_main":0,
    "name:eng_x_preferred":[
        "Pulimoodu"
    ],
    "wof:name":"Pulimoodu",
    "wof:placetype":"neighbourhood",
    "wof:population":600
},
  "geometry": {"coordinates":[76.468198,9.443858],"type":"Point"}
}