{
  "type": "Feature",
  "properties": {
    "gn:admin1_code":"19.0",
    "gn:admin2_code":"566.0",
    "gn:asciiname":"Srirangapura",
    "gn:country_code":"IN",
    "gn:dem":698,
    "gn:feature_class":"P",
    "gn:feature_code":"PPL",
    "gn:name":"Sr\u012brangapura",
    "gn:population":0,
    "gn:timezone":"Asia/Kolkata",
    "iso:country":"IN",
    "wof:name":"Srirangapura",
    "wof:placetype":"locality"
},
  "geometry": {"coordinates":[76.30677,13.81203],"type":"Point"}
}