{
  "type": "Feature",
  "properties": {
    "iso:country":"IN",
    "ks:ks_alt_nam":"Naiya and Mondal Para",
    "ks:ks_name":"Naiya And Mondal Para",
    "ks:ks_pop":1200,
    "ks:ks_type":"HABITATION",
    "name:eng_x_preferred":[
        "Naiya And Mondal Para"
    ],
    "wof:name":"Naiya And Mondal Para",
    "wof:placetype":"locality",
    "wof:population":1200
},
  "geometry": {"coordinates":[88.506319,22.253865],"type":"Point"}
}