{
  "type": "Feature",
  "properties": {
    "iso:country":"IN",
    "ks:ks_alt_nam":"GANJHUTOLI",
    "ks:ks_name":"Ganjhutoli",
    "ks:ks_pop":182,
    "ks:ks_type":"HABITATION",
    "name:eng_x_preferred":[
        "Ganjhutoli"
    ],
    "wof:name":"Ganjhutoli",
    "wof:placetype":"locality",
    "wof:population":182
},
  "geometry": {"coordinates":[83.91498300000001,22.618323],"type":"Point"}
}