{
  "type": "Feature",
  "properties": {
    "iso:country":"IN",
    "ks:ks_name":"Lakkondanahalli",
    "ks:ks_pop":12,
    "ks:ks_type":"VILLAGE",
    "name:eng_x_preferred":[
        "Lakkondanahalli"
    ],
    "wof:name":"Lakkondanahalli",
    "wof:placetype":"locality",
    "wof:population":12
},
  "geometry": {"coordinates":[75.99419399999999,12.815627],"type":"Point"}
}