{
  "type": "Feature",
  "properties": {
    "iso:country":"IN",
    "ks:ks_name":"Chhoti Kewtahi",
    "ks:ks_pop":267,
    "ks:ks_type":"HABITATION",
    "name:eng_x_preferred":[
        "Chhoti Kewtahi"
    ],
    "wof:name":"Chhoti Kewtahi",
    "wof:placetype":"locality",
    "wof:population":267
},
  "geometry": {"coordinates":[82.8325,26.394031],"type":"Point"}
}