{
  "type": "Feature",
  "properties": {
    "iso:country":"IN",
    "ks:ks_name":"Harijanawada",
    "ks:ks_pop":165,
    "ks:ks_type":"HABITATION",
    "name:eng_x_preferred":[
        "Harijanawada"
    ],
    "wof:name":"Harijanawada",
    "wof:placetype":"locality",
    "wof:population":165
},
  "geometry": {"coordinates":[78.134675,14.016955],"type":"Point"}
}