{
  "type": "Feature",
  "properties": {
    "iso:country":"IN",
    "ks:ks_name":"Jambhatha",
    "ks:ks_pop":253,
    "ks:ks_type":"HABITATION",
    "name:eng_x_preferred":[
        "Jambhatha"
    ],
    "wof:name":"Jambhatha",
    "wof:placetype":"locality",
    "wof:population":253
},
  "geometry": {"coordinates":[82.79952900000001,22.634271],"type":"Point"}
}