{
  "type": "Feature",
  "properties": {
    "gn:admin1_code":"34",
    "gn:admin2_code":"233.0",
    "gn:asciiname":"Karaudia",
    "gn:country_code":"IN",
    "gn:dem":84,
    "gn:feature_class":"P",
    "gn:feature_code":"PPL",
    "gn:name":"Karaudia",
    "gn:population":0,
    "gn:timezone":"Asia/Kolkata",
    "iso:country":"IN",
    "ks:ks_name":"Karaundia",
    "ks:ks_pop":572,
    "ks:ks_type":"VILLAGE",
    "name:cat_x_preferred":[
        "Karaudia"
    ],
    "name:eng_x_preferred":[
        "Karaundia"
    ],
    "name:eng_x_variant":[
        "Karaudia"
    ],
    "wof:name":"Karaundia",
    "wof:placetype":"locality",
    "wof:population":572
},
  "geometry": {"coordinates":[83.54168300000001,25.04907],"type":"Point"}
}