{
  "type": "Feature",
  "properties": {
    "iso:country":"IN",
    "ks:ks_alt_nam":"BANKAR MALA",
    "ks:ks_name":"Bankar Mala",
    "ks:ks_pop":153,
    "ks:ks_type":"HABITATION",
    "name:eng_x_preferred":[
        "Bankar Mala"
    ],
    "wof:name":"Bankar Mala",
    "wof:placetype":"locality",
    "wof:population":153
},
  "geometry": {"coordinates":[74.475662,18.801774],"type":"Point"}
}