{
  "type": "Feature",
  "properties": {
    "iso:country":"IN",
    "ks:ks_name":"Kantal Ka Par",
    "ks:ks_pop":1030,
    "ks:ks_type":"VILLAGE",
    "name:eng_x_preferred":[
        "Kantal Ka Par"
    ],
    "wof:name":"Kantal Ka Par",
    "wof:placetype":"locality",
    "wof:population":1030
},
  "geometry": {"coordinates":[70.797274,25.731121],"type":"Point"}
}