{
  "type": "Feature",
  "properties": {
    "gn:admin1_code":"16",
    "gn:admin2_code":"527.0",
    "gn:asciiname":"Shingnapur",
    "gn:country_code":"IN",
    "gn:dem":821,
    "gn:feature_class":"P",
    "gn:feature_code":"PPL",
    "gn:name":"Shingn\u0101pur",
    "gn:population":0,
    "gn:timezone":"Asia/Kolkata",
    "iso:country":"IN",
    "wof:name":"Shingnapur",
    "wof:placetype":"locality"
},
  "geometry": {"coordinates":[74.66385,17.85054],"type":"Point"}
}