{
  "type": "Feature",
  "properties": {
    "iso:country":"IN",
    "ks:ks_name":"Dadutola",
    "ks:ks_pop":63,
    "ks:ks_type":"HABITATION",
    "name:eng_x_preferred":[
        "Dadutola"
    ],
    "wof:name":"Dadutola",
    "wof:placetype":"locality",
    "wof:population":63
},
  "geometry": {"coordinates":[81.022769,22.061498],"type":"Point"}
}