{
  "type": "Feature",
  "properties": {
    "iso:country":"IN",
    "ks:ks_name":"Narayanguda",
    "ks:ks_pop":258,
    "ks:ks_type":"HABITATION",
    "ks:ks_uagg_main":0,
    "name:eng_x_preferred":[
        "Narayanguda"
    ],
    "wof:name":"Narayanguda",
    "wof:placetype":"neighbourhood",
    "wof:population":258
},
  "geometry": {"coordinates":[82.50282,19.093232],"type":"Point"}
}