{
  "type": "Feature",
  "properties": {
    "iso:country":"IN",
    "ks:ks_name":"Halair Par",
    "ks:ks_pop":1477,
    "ks:ks_type":"HABITATION",
    "name:eng_x_preferred":[
        "Halair Par"
    ],
    "wof:name":"Halair Par",
    "wof:placetype":"locality",
    "wof:population":1477
},
  "geometry": {"coordinates":[91.990165,24.300395],"type":"Point"}
}