{
  "type": "Feature",
  "properties": {
    "iso:country":"IN",
    "ks:ks_name":"Halderpara",
    "ks:ks_pop":1100,
    "ks:ks_type":"HABITATION",
    "name:eng_x_preferred":[
        "Halderpara"
    ],
    "wof:name":"Halderpara",
    "wof:placetype":"locality",
    "wof:population":1100
},
  "geometry": {"coordinates":[88.71767699999999,22.407029],"type":"Point"}
}