{
  "type": "Feature",
  "properties": {
    "iso:country":"IN",
    "ks:ks_name":"Chokkupillaipatty",
    "ks:ks_pop":845,
    "ks:ks_type":"HABITATION",
    "ks:ks_uagg_main":0,
    "name:eng_x_preferred":[
        "Chokkupillaipatty"
    ],
    "wof:name":"Chokkupillaipatty",
    "wof:placetype":"neighbourhood",
    "wof:population":845
},
  "geometry": {"coordinates":[77.857709,10.094978],"type":"Point"}
}