{
  "type": "Feature",
  "properties": {
    "iso:country":"IN",
    "ks:ks_name":"Raghunathpur",
    "ks:ks_pop":3709,
    "ks:ks_type":"VILLAGE",
    "ks:ks_uagg_main":0,
    "name:eng_x_preferred":[
        "Raghunathpur"
    ],
    "wof:name":"Raghunathpur",
    "wof:placetype":"neighbourhood",
    "wof:population":3709
},
  "geometry": {"coordinates":[88.76666,22.726987],"type":"Point"}
}