{
  "type": "Feature",
  "properties": {
    "iso:country":"IN",
    "ks:ks_name":"Murkai",
    "ks:ks_pop":8,
    "ks:ks_type":"HABITATION",
    "name:eng_x_preferred":[
        "Murkai"
    ],
    "wof:name":"Murkai",
    "wof:placetype":"locality",
    "wof:population":8
},
  "geometry": {"coordinates":[75.032624,14.039675],"type":"Point"}
}