{
  "type": "Feature",
  "properties": {
    "iso:country":"IN",
    "ks:ks_name":"Amdahara",
    "ks:ks_pop":143,
    "ks:ks_type":"VILLAGE",
    "name:eng_x_preferred":[
        "Amdahara"
    ],
    "wof:name":"Amdahara",
    "wof:placetype":"locality",
    "wof:population":143
},
  "geometry": {"coordinates":[87.666177,23.786436],"type":"Point"}
}