{
  "type": "Feature",
  "properties": {
    "iso:country":"IN",
    "ks:ks_name":"Cheembra",
    "ks:ks_pop":2407,
    "ks:ks_type":"HABITATION",
    "name:eng_x_preferred":[
        "Cheembra"
    ],
    "wof:name":"Cheembra",
    "wof:placetype":"locality",
    "wof:population":2407
},
  "geometry": {"coordinates":[76.679216,10.006263],"type":"Point"}
}