{
  "type": "Feature",
  "properties": {
    "iso:country":"IN",
    "ks:ks_name":"Chak Beethnokh",
    "ks:ks_pop":4,
    "ks:ks_type":"VILLAGE",
    "name:eng_x_preferred":[
        "Chak Beethnokh"
    ],
    "wof:name":"Chak Beethnokh",
    "wof:placetype":"locality",
    "wof:population":4
},
  "geometry": {"coordinates":[72.772341,27.81559],"type":"Point"}
}