{
  "type": "Feature",
  "properties": {
    "iso:country":"IN",
    "ks:ks_name":"Tontpur",
    "ks:ks_pop":1592,
    "ks:ks_type":"VILLAGE",
    "ks:ks_uagg_main":0,
    "name:eng_x_preferred":[
        "Tontpur"
    ],
    "wof:name":"Tontpur",
    "wof:placetype":"locality",
    "wof:population":1592
},
  "geometry": {"coordinates":[77.489208,27.239239],"type":"Point"}
}