{
  "type": "Feature",
  "properties": {
    "iso:country":"IN",
    "ks:ks_name":"Astia",
    "ks:ks_pop":435,
    "ks:ks_type":"VILLAGE",
    "ks:ks_uagg_main":0,
    "name:eng_x_preferred":[
        "Astia"
    ],
    "wof:name":"Astia",
    "wof:placetype":"neighbourhood",
    "wof:population":435
},
  "geometry": {"coordinates":[87.145245,21.813593],"type":"Point"}
}