{
  "type": "Feature",
  "properties": {
    "iso:country":"IN",
    "ks:ks_alt_nam":"BALMUKUND TOLA",
    "ks:ks_name":"Balmukund Tola",
    "ks:ks_pop":945,
    "ks:ks_type":"HABITATION",
    "name:eng_x_preferred":[
        "Balmukund Tola"
    ],
    "wof:name":"Balmukund Tola",
    "wof:placetype":"locality",
    "wof:population":945
},
  "geometry": {"coordinates":[87.834613,25.280783],"type":"Point"}
}