{
  "type": "Feature",
  "properties": {
    "gn:admin1_code":"39.0",
    "gn:admin2_code":"67.0",
    "gn:asciiname":"Kulia",
    "gn:country_code":"IN",
    "gn:dem":238,
    "gn:feature_class":"P",
    "gn:feature_code":"PPL",
    "gn:name":"Kulia",
    "gn:population":0,
    "gn:timezone":"Asia/Kolkata",
    "iso:country":"IN",
    "name:deu_x_preferred":[
        "Kulia"
    ],
    "name:nor_x_preferred":[
        "Kulia"
    ],
    "name:pol_x_preferred":[
        "Kulia"
    ],
    "name:spa_x_preferred":[
        "Kulia"
    ],
    "wof:name":"Kulia",
    "wof:placetype":"locality"
},
  "geometry": {"coordinates":[79.33617,29.10686],"type":"Point"}
}