{
  "type": "Feature",
  "properties": {
    "gn:admin1_code":"35",
    "gn:admin2_code":"451.0",
    "gn:asciiname":"Suhagi",
    "gn:country_code":"IN",
    "gn:dem":391,
    "gn:feature_class":"P",
    "gn:feature_code":"PPL",
    "gn:name":"Suh\u0101gi",
    "gn:population":0,
    "gn:timezone":"Asia/Kolkata",
    "iso:country":"IN",
    "ks:ks_alt_nam":"Suh\u0101gi",
    "ks:ks_name":"Suhagi",
    "ks:ks_pop":8145,
    "ks:ks_type":"VILLAGE",
    "ks:ks_uagg_main":0,
    "name:ben_x_preferred":[
        "\u09b8\u09c1\u09b9\u09be\u0997\u09bf"
    ],
    "name:bpy_x_preferred":[
        "\u09b8\u09c1\u09b9\u09be\u0997\u09bf"
    ],
    "name:eng_x_preferred":[
        "Suhagi"
    ],
    "name:eng_x_variant":[
        "Suh\u0101gi"
    ],
    "name:ita_x_preferred":[
        "Suhagi"
    ],
    "name:msa_x_preferred":[
        "Suhagi"
    ],
    "name:nld_x_preferred":[
        "Suhagi"
    ],
    "name:por_x_preferred":[
        "Suhagi"
    ],
    "name:vie_x_preferred":[
        "Suhagi"
    ],
    "name:zho_x_preferred":[
        "\u82cf\u54c8\u5409"
    ],
    "wof:name":"Suhagi",
    "wof:placetype":"locality",
    "wof:population":8145
},
  "geometry": {"coordinates":[79.95890799999999,23.224525],"type":"Point"}
}