{
  "type": "Feature",
  "properties": {
    "iso:country":"IN",
    "ks:ks_alt_nam":"JORWAR WASTI",
    "ks:ks_name":"Jorwar Wasti",
    "ks:ks_pop":146,
    "ks:ks_type":"HABITATION",
    "name:eng_x_preferred":[
        "Jorwar Wasti"
    ],
    "wof:name":"Jorwar Wasti",
    "wof:placetype":"locality",
    "wof:population":146
},
  "geometry": {"coordinates":[75.33913099999999,17.097964],"type":"Point"}
}