{
  "type": "Feature",
  "properties": {
    "iso:country":"IN",
    "ks:ks_name":"Adiwasi Tola",
    "ks:ks_pop":834,
    "ks:ks_type":"HABITATION",
    "name:eng_x_preferred":[
        "Adiwasi Tola"
    ],
    "wof:name":"Adiwasi Tola",
    "wof:placetype":"locality",
    "wof:population":834
},
  "geometry": {"coordinates":[83.52731,24.469476],"type":"Point"}
}