{
  "type": "Feature",
  "properties": {
    "iso:country":"IN",
    "ks:ks_name":"Sardarpara",
    "ks:ks_pop":1500,
    "ks:ks_type":"HABITATION",
    "name:eng_x_preferred":[
        "Sardarpara"
    ],
    "wof:name":"Sardarpara",
    "wof:placetype":"locality",
    "wof:population":1500
},
  "geometry": {"coordinates":[88.68400099999999,22.408836],"type":"Point"}
}