{
  "type": "Feature",
  "properties": {
    "gn:admin1_code":"23",
    "gn:admin2_code":"48.0",
    "gn:asciiname":"Kheri Gurna",
    "gn:country_code":"IN",
    "gn:dem":278,
    "gn:feature_class":"P",
    "gn:feature_code":"PPL",
    "gn:name":"Kheri G\u016brna",
    "gn:population":0,
    "gn:timezone":"Asia/Kolkata",
    "iso:country":"IN",
    "wof:name":"Kheri Gurna",
    "wof:placetype":"locality"
},
  "geometry": {"coordinates":[76.71469,30.48697],"type":"Point"}
}