{
  "type": "Feature",
  "properties": {
    "gn:admin1_code":"35",
    "gn:asciiname":"Bamhori Suhagi",
    "gn:country_code":"IN",
    "gn:dem":226,
    "gn:feature_class":"P",
    "gn:feature_code":"PPL",
    "gn:name":"Bamhori Suh\u0101gi",
    "gn:population":0,
    "gn:timezone":"Asia/Kolkata",
    "iso:country":"IN",
    "wof:name":"Bamhori Suhagi",
    "wof:placetype":"locality"
},
  "geometry": {"coordinates":[79.02408,25.24717],"type":"Point"}
}