{
  "type": "Feature",
  "properties": {
    "gn:admin1_code":"2.0",
    "gn:admin2_code":"544.0",
    "gn:asciiname":"Neraduvalasa",
    "gn:country_code":"IN",
    "gn:dem":979,
    "gn:feature_class":"P",
    "gn:feature_code":"PPL",
    "gn:name":"Neraduvalasa",
    "gn:population":0,
    "gn:timezone":"Asia/Kolkata",
    "iso:country":"IN",
    "ks:ks_name":"Nereduvalasa",
    "ks:ks_pop":39,
    "ks:ks_type":"HABITATION",
    "name:eng_x_preferred":[
        "Nereduvalasa"
    ],
    "name:eng_x_variant":[
        "Neraduvalasa"
    ],
    "wof:name":"Nereduvalasa",
    "wof:placetype":"locality",
    "wof:population":39
},
  "geometry": {"coordinates":[82.69100400000001,18.250366],"type":"Point"}
}