{
  "type": "Feature",
  "properties": {
    "gn:admin1_code":"2.0",
    "gn:admin2_code":"544.0",
    "gn:asciiname":"Neraduvalasa",
    "gn:country_code":"IN",
    "gn:dem":979,
    "gn:feature_class":"P",
    "gn:feature_code":"PPL",
    "gn:name":"Neraduvalasa",
    "gn:population":0,
    "gn:timezone":"Asia/Kolkata",
    "iso:country":"IN",
    "wof:name":"Neraduvalasa",
    "wof:placetype":"locality"
},
  "geometry": {"coordinates":[82.67612,18.24939],"type":"Point"}
}