{
  "type": "Feature",
  "properties": {
    "gn:admin1_code":"34.0",
    "gn:admin2_code":"218.0",
    "gn:asciiname":"Misrauli Khap",
    "gn:country_code":"IN",
    "gn:dem":71,
    "gn:feature_class":"P",
    "gn:feature_code":"PPL",
    "gn:name":"Misrauli Khap",
    "gn:population":0,
    "gn:timezone":"Asia/Kolkata",
    "iso:country":"IN",
    "ks:ks_name":"Misrauli Khas",
    "ks:ks_pop":697,
    "ks:ks_type":"VILLAGE",
    "name:eng_x_preferred":[
        "Misrauli Khas"
    ],
    "name:eng_x_variant":[
        "Misrauli Khap"
    ],
    "wof:name":"Misrauli Khas",
    "wof:placetype":"locality",
    "wof:population":697
},
  "geometry": {"coordinates":[84.18503800000001,26.293819],"type":"Point"}
}