{
  "type": "Feature",
  "properties": {
    "iso:country":"IN",
    "ks:ks_name":"Bhaday",
    "ks:ks_pop":876,
    "ks:ks_type":"VILLAGE",
    "ks:ks_uagg_main":0,
    "name:eng_x_preferred":[
        "Bhaday"
    ],
    "wof:name":"Bhaday",
    "wof:placetype":"neighbourhood",
    "wof:population":876
},
  "geometry": {"coordinates":[84.477206,26.26804],"type":"Point"}
}