{
  "type": "Feature",
  "properties": {
    "gn:admin1_code":"39.0",
    "gn:admin2_code":"64.0",
    "gn:asciiname":"Dhaneta Malla",
    "gn:country_code":"IN",
    "gn:dem":1370,
    "gn:feature_class":"P",
    "gn:feature_code":"PPL",
    "gn:name":"Dhaneta Malla",
    "gn:population":0,
    "gn:timezone":"Asia/Kolkata",
    "iso:country":"IN",
    "wof:name":"Dhaneta Malla",
    "wof:placetype":"locality"
},
  "geometry": {"coordinates":[79.17358,29.79863],"type":"Point"}
}