{
  "type": "Feature",
  "properties": {
    "iso:country":"IN",
    "ks:ks_name":"Bahauddinpur",
    "ks:ks_pop":576,
    "ks:ks_type":"VILLAGE",
    "name:eng_x_preferred":[
        "Bahauddinpur"
    ],
    "wof:name":"Bahauddinpur",
    "wof:placetype":"locality",
    "wof:population":576
},
  "geometry": {"coordinates":[85.625816,25.907895],"type":"Point"}
}