{
  "type": "Feature",
  "properties": {
    "iso:country":"IN",
    "ks:ks_name":"Mastikari",
    "ks:ks_pop":3297,
    "ks:ks_type":"VILLAGE",
    "ks:ks_uagg_main":0,
    "name:eng_x_preferred":[
        "Mastikari"
    ],
    "wof:name":"Mastikari",
    "wof:placetype":"neighbourhood",
    "wof:population":3297
},
  "geometry": {"coordinates":[88.441942,22.229862],"type":"Point"}
}