{
  "type": "Feature",
  "properties": {
    "gn:admin1_code":"24.0",
    "gn:admin2_code":"108.0",
    "gn:asciiname":"Mei Khurd",
    "gn:country_code":"IN",
    "gn:dem":222,
    "gn:feature_class":"P",
    "gn:feature_code":"PPL",
    "gn:name":"Mei Khurd",
    "gn:population":0,
    "gn:timezone":"Asia/Kolkata",
    "iso:country":"IN",
    "wof:name":"Mei Khurd",
    "wof:placetype":"locality"
},
  "geometry": {"coordinates":[76.57568000000001,25.95694],"type":"Point"}
}