{
  "type": "Feature",
  "properties": {
    "gn:admin1_code":"19.0",
    "gn:admin2_code":"568.0",
    "gn:asciiname":"Horani",
    "gn:country_code":"IN",
    "gn:dem":628,
    "gn:feature_class":"P",
    "gn:feature_code":"PPL",
    "gn:name":"Horani",
    "gn:population":0,
    "gn:timezone":"Asia/Kolkata",
    "iso:country":"IN",
    "ks:ks_name":"Horani",
    "ks:ks_type":"VILLAGE",
    "name:eng_x_preferred":[
        "Horani"
    ],
    "wof:name":"Horani",
    "wof:placetype":"locality"
},
  "geometry": {"coordinates":[75.20052699999999,13.696497],"type":"Point"}
}