{
  "type": "Feature",
  "properties": {
    "iso:country":"IN",
    "ks:ks_alt_nam":"uttar Atagaon",
    "ks:ks_name":"Uttar Atagaon",
    "ks:ks_pop":898,
    "ks:ks_type":"HABITATION",
    "name:eng_x_preferred":[
        "Uttar Atagaon"
    ],
    "wof:name":"Uttar Atagaon",
    "wof:placetype":"locality",
    "wof:population":898
},
  "geometry": {"coordinates":[90.998295,26.520448],"type":"Point"}
}