{
  "type": "Feature",
  "properties": {
    "iso:country":"IN",
    "ks:ks_name":"Mardipada",
    "ks:ks_pop":555,
    "ks:ks_type":"HABITATION",
    "name:eng_x_preferred":[
        "Mardipada"
    ],
    "wof:name":"Mardipada",
    "wof:placetype":"locality",
    "wof:population":555
},
  "geometry": {"coordinates":[74.306147,21.762374],"type":"Point"}
}