{
  "type": "Feature",
  "properties": {
    "iso:country":"IN",
    "ks:ks_alt_nam":"KHAUDIYA",
    "ks:ks_name":"Khaudiya",
    "ks:ks_pop":403,
    "ks:ks_type":"HABITATION",
    "name:eng_x_preferred":[
        "Khaudiya"
    ],
    "wof:name":"Khaudiya",
    "wof:placetype":"locality",
    "wof:population":403
},
  "geometry": {"coordinates":[81.729242,26.41211],"type":"Point"}
}