{
  "type": "Feature",
  "properties": {
    "iso:country":"IN",
    "ks:ks_name":"Giliriduma",
    "ks:ks_pop":87,
    "ks:ks_type":"VILLAGE",
    "name:eng_x_preferred":[
        "Giliriduma"
    ],
    "wof:name":"Giliriduma",
    "wof:placetype":"locality",
    "wof:population":87
},
  "geometry": {"coordinates":[85.92676,21.5949],"type":"Point"}
}