{
  "type": "Feature",
  "properties": {
    "iso:country":"IN",
    "ks:ks_alt_nam":"MOMIN TOLA",
    "ks:ks_name":"Momin Tola",
    "ks:ks_pop":756,
    "ks:ks_type":"HABITATION",
    "name:eng_x_preferred":[
        "Momin Tola"
    ],
    "wof:name":"Momin Tola",
    "wof:placetype":"locality",
    "wof:population":756
},
  "geometry": {"coordinates":[87.68328,25.51682],"type":"Point"}
}