{
  "type": "Feature",
  "properties": {
    "iso:country":"IN",
    "ks:ks_name":"Gobindapur",
    "ks:ks_pop":2280,
    "ks:ks_type":"VILLAGE",
    "ks:ks_uagg_main":0,
    "name:eng_x_preferred":[
        "Gobindapur"
    ],
    "wof:name":"Gobindapur",
    "wof:placetype":"neighbourhood",
    "wof:population":2280
},
  "geometry": {"coordinates":[88.00354400000001,22.298052],"type":"Point"}
}