{
  "type": "Feature",
  "properties": {
    "iso:country":"IN",
    "ks:ks_name":"Kesarpura",
    "ks:ks_pop":353,
    "ks:ks_type":"VILLAGE",
    "name:eng_x_preferred":[
        "Kesarpura"
    ],
    "wof:name":"Kesarpura",
    "wof:placetype":"locality",
    "wof:population":353
},
  "geometry": {"coordinates":[74.27589999999999,23.814748],"type":"Point"}
}