{
  "type": "Feature",
  "properties": {
    "gn:admin1_code":"34.0",
    "gn:admin2_code":"221.0",
    "gn:asciiname":"Hasauli",
    "gn:country_code":"IN",
    "gn:dem":51,
    "gn:feature_class":"P",
    "gn:feature_code":"PPL",
    "gn:name":"Hasauli",
    "gn:population":0,
    "gn:timezone":"Asia/Kolkata",
    "iso:country":"IN",
    "ks:ks_name":"Hasauli",
    "ks:ks_pop":1308,
    "ks:ks_type":"VILLAGE",
    "name:eng_x_preferred":[
        "Hasauli"
    ],
    "wof:name":"Hasauli",
    "wof:placetype":"locality",
    "wof:population":1308
},
  "geometry": {"coordinates":[85.842598,25.784688],"type":"Point"}
}