{
  "type": "Feature",
  "properties": {
    "gn:admin1_code":"9.0",
    "gn:admin2_code":"486.0",
    "gn:asciiname":"Watra",
    "gn:country_code":"IN",
    "gn:dem":178,
    "gn:feature_class":"P",
    "gn:feature_code":"PPL",
    "gn:name":"Watra",
    "gn:population":0,
    "gn:timezone":"Asia/Kolkata",
    "iso:country":"IN",
    "wof:name":"Watra",
    "wof:placetype":"neighbourhood"
},
  "geometry": {"coordinates":[74.0526,22.17706],"type":"Point"}
}