{
  "type": "Feature",
  "properties": {
    "gn:admin1_code":"36",
    "gn:admin2_code":"161.0",
    "gn:asciiname":"Marhaiyan Bukhera",
    "gn:country_code":"IN",
    "gn:dem":149,
    "gn:feature_class":"P",
    "gn:feature_code":"PPL",
    "gn:name":"Marhaiy\u0101n Bukhera",
    "gn:population":0,
    "gn:timezone":"Asia/Kolkata",
    "iso:country":"IN",
    "wof:name":"Marhaiyan Bukhera",
    "wof:placetype":"locality"
},
  "geometry": {"coordinates":[78.92107,26.71674],"type":"Point"}
}