{
  "type": "Feature",
  "properties": {
    "gn:admin1_code":"2.0",
    "gn:admin2_code":"542.0",
    "gn:asciiname":"Turakavalasa",
    "gn:country_code":"IN",
    "gn:dem":192,
    "gn:feature_class":"P",
    "gn:feature_code":"PPL",
    "gn:name":"Turakavalasa",
    "gn:population":0,
    "gn:timezone":"Asia/Kolkata",
    "iso:country":"IN",
    "ks:ks_name":"Thorikavalasa",
    "ks:ks_pop":77,
    "ks:ks_type":"HABITATION",
    "name:eng_x_preferred":[
        "Thorikavalasa"
    ],
    "name:eng_x_variant":[
        "Turakavalasa"
    ],
    "wof:name":"Thorikavalasa",
    "wof:placetype":"locality",
    "wof:population":77
},
  "geometry": {"coordinates":[83.848972,18.611424],"type":"Point"}
}