{
  "type": "Feature",
  "properties": {
    "iso:country":"IN",
    "ks:ks_name":"Zada Fa",
    "ks:ks_pop":294,
    "ks:ks_type":"HABITATION",
    "name:eng_x_preferred":[
        "Zada Fa"
    ],
    "wof:name":"Zada Fa",
    "wof:placetype":"locality",
    "wof:population":294
},
  "geometry": {"coordinates":[73.07769399999999,20.466472],"type":"Point"}
}