{
  "type": "Feature",
  "properties": {
    "iso:country":"IN",
    "ks:ks_name":"Soobri Ki Nal",
    "ks:ks_pop":272,
    "ks:ks_type":"VILLAGE",
    "name:eng_x_preferred":[
        "Soobri Ki Nal"
    ],
    "wof:name":"Soobri Ki Nal",
    "wof:placetype":"locality",
    "wof:population":272
},
  "geometry": {"coordinates":[73.186583,24.444297],"type":"Point"}
}