{
  "type": "Feature",
  "properties": {
    "iso:country":"IN",
    "ks:ks_name":"Chhota Parulia",
    "ks:ks_pop":372,
    "ks:ks_type":"VILLAGE",
    "ks:ks_uagg_main":0,
    "name:eng_x_preferred":[
        "Chhota Parulia"
    ],
    "wof:name":"Chhota Parulia",
    "wof:placetype":"neighbourhood",
    "wof:population":372
},
  "geometry": {"coordinates":[86.999419,22.300838],"type":"Point"}
}