{
  "type": "Feature",
  "properties": {
    "gn:admin1_code":"25.0",
    "gn:admin2_code":"605.0",
    "gn:asciiname":"Mettusakkaraikkuppam",
    "gn:country_code":"IN",
    "gn:dem":413,
    "gn:feature_class":"P",
    "gn:feature_code":"PPL",
    "gn:name":"Mettusakkaraikkuppam",
    "gn:population":0,
    "gn:timezone":"Asia/Kolkata",
    "iso:country":"IN",
    "wof:name":"Mettusakkaraikkuppam",
    "wof:placetype":"locality"
},
  "geometry": {"coordinates":[78.58641999999998,12.5761],"type":"Point"}
}