{
  "type": "Feature",
  "properties": {
    "iso:country":"IN",
    "ks:ks_name":"Bhikhika Purwa",
    "ks:ks_pop":182,
    "ks:ks_type":"HABITATION",
    "ks:ks_uagg_main":0,
    "name:eng_x_preferred":[
        "Bhikhika Purwa"
    ],
    "wof:name":"Bhikhika Purwa",
    "wof:placetype":"neighbourhood",
    "wof:population":182
},
  "geometry": {"coordinates":[81.91040599999999,25.77478],"type":"Point"}
}