{
  "type": "Feature",
  "properties": {
    "gn:admin1_code":"2.0",
    "gn:admin2_code":"551.0",
    "gn:asciiname":"Chintakuntavandlapallle",
    "gn:country_code":"IN",
    "gn:dem":409,
    "gn:feature_class":"P",
    "gn:feature_code":"PPL",
    "gn:name":"Chintakuntav\u0101ndlapallle",
    "gn:population":0,
    "gn:timezone":"Asia/Kolkata",
    "iso:country":"IN",
    "wof:name":"Chintakuntavandlapallle",
    "wof:placetype":"locality"
},
  "geometry": {"coordinates":[78.94006999999998,14.10835],"type":"Point"}
}