{
  "type": "Feature",
  "properties": {
    "gn:admin1_code":"20",
    "gn:admin2_code":"269.0",
    "gn:asciiname":"Sirire",
    "gn:country_code":"IN",
    "gn:dem":1710,
    "gn:feature_class":"P",
    "gn:feature_code":"PPL",
    "gn:name":"Sirire",
    "gn:population":0,
    "gn:timezone":"Asia/Kolkata",
    "iso:country":"IN",
    "wof:name":"Sirire",
    "wof:placetype":"locality"
},
  "geometry": {"coordinates":[94.76701,25.91053],"type":"Point"}
}