{
  "type": "Feature",
  "properties": {
    "gn:admin1_code":"16.0",
    "gn:admin2_code":"511.0",
    "gn:asciiname":"Ashta",
    "gn:country_code":"IN",
    "gn:dem":272,
    "gn:feature_class":"P",
    "gn:feature_code":"PPL",
    "gn:name":"\u0100shta",
    "gn:population":0,
    "gn:timezone":"Asia/Kolkata",
    "iso:country":"IN",
    "name:cat_x_preferred":[
        "Ashta"
    ],
    "name:ceb_x_preferred":[
        "Ashta"
    ],
    "name:swe_x_preferred":[
        "Ashta"
    ],
    "wof:name":"Ashta",
    "wof:placetype":"locality"
},
  "geometry": {"coordinates":[77.98666999999998,19.87771],"type":"Point"}
}