{
  "type": "Feature",
  "properties": {
    "iso:country":"IN",
    "ks:ks_name":"Mulgam Falia",
    "ks:ks_pop":78,
    "ks:ks_type":"HABITATION",
    "name:eng_x_preferred":[
        "Mulgam Falia"
    ],
    "wof:name":"Mulgam Falia",
    "wof:placetype":"locality",
    "wof:population":78
},
  "geometry": {"coordinates":[73.16588900000001,20.343361],"type":"Point"}
}