{
  "type": "Feature",
  "properties": {
    "iso:country":"IN",
    "ks:ks_alt_nam":"DAGIRE MALA",
    "ks:ks_name":"Dagire Mala",
    "ks:ks_pop":75,
    "ks:ks_type":"HABITATION",
    "name:eng_x_preferred":[
        "Dagire Mala"
    ],
    "wof:name":"Dagire Mala",
    "wof:placetype":"locality",
    "wof:population":75
},
  "geometry": {"coordinates":[74.32855000000001,17.37362],"type":"Point"}
}