{
  "type": "Feature",
  "properties": {
    "iso:country":"IN",
    "ks:ks_name":"Vancharba",
    "ks:ks_pop":139,
    "ks:ks_type":"HABITATION",
    "name:eng_x_preferred":[
        "Vancharba"
    ],
    "wof:name":"Vancharba",
    "wof:placetype":"locality",
    "wof:population":139
},
  "geometry": {"coordinates":[82.57020799999999,18.164126],"type":"Point"}
}