{
  "type": "Feature",
  "properties": {
    "iso:country":"IN",
    "ks:ks_name":"Dhanua",
    "ks:ks_pop":250,
    "ks:ks_type":"HABITATION",
    "name:eng_x_preferred":[
        "Dhanua"
    ],
    "wof:name":"Dhanua",
    "wof:placetype":"locality",
    "wof:population":250
},
  "geometry": {"coordinates":[87.283236,22.056715],"type":"Point"}
}