{
  "type": "Feature",
  "properties": {
    "iso:country":"IN",
    "ks:ks_name":"Manajoy Roaja Para",
    "ks:ks_pop":279,
    "ks:ks_type":"HABITATION",
    "ks:ks_uagg_main":0,
    "name:eng_x_preferred":[
        "Manajoy Roaja Para"
    ],
    "wof:name":"Manajoy Roaja Para",
    "wof:placetype":"neighbourhood",
    "wof:population":279
},
  "geometry": {"coordinates":[91.91514100000001,23.496245],"type":"Point"}
}