{
  "type": "Feature",
  "properties": {
    "gn:admin1_code":"34.0",
    "gn:admin2_code":"237.0",
    "gn:asciiname":"Oraiya",
    "gn:country_code":"IN",
    "gn:dem":123,
    "gn:feature_class":"P",
    "gn:feature_code":"PPL",
    "gn:name":"Oraiya",
    "gn:population":0,
    "gn:timezone":"Asia/Kolkata",
    "iso:country":"IN",
    "ks:ks_name":"Oraiya",
    "ks:ks_pop":846,
    "ks:ks_type":"VILLAGE",
    "name:eng_x_preferred":[
        "Oraiya"
    ],
    "wof:name":"Oraiya",
    "wof:placetype":"locality",
    "wof:population":846
},
  "geometry": {"coordinates":[85.487229,24.739915],"type":"Point"}
}