{
  "type": "Feature",
  "properties": {
    "iso:country":"IN",
    "ks:ks_name":"Wakipada",
    "ks:ks_pop":190,
    "ks:ks_type":"HABITATION",
    "name:eng_x_preferred":[
        "Wakipada"
    ],
    "wof:name":"Wakipada",
    "wof:placetype":"locality",
    "wof:population":190
},
  "geometry": {"coordinates":[72.897279,19.919563],"type":"Point"}
}