{
  "type": "Feature",
  "properties": {
    "gn:admin1_code":"24.0",
    "gn:admin2_code":"099",
    "gn:asciiname":"Fatuhi Labana",
    "gn:country_code":"IN",
    "gn:dem":178,
    "gn:feature_class":"P",
    "gn:feature_code":"PPL",
    "gn:name":"Fatuhi Lab\u0101na",
    "gn:population":0,
    "gn:timezone":"Asia/Kolkata",
    "iso:country":"IN",
    "wof:name":"Fatuhi Labana",
    "wof:placetype":"neighbourhood"
},
  "geometry": {"coordinates":[73.87218,30.03743],"type":"Point"}
}