{
  "type": "Feature",
  "properties": {
    "iso:country":"IN",
    "ks:ks_alt_nam":"girja ram tola",
    "ks:ks_name":"Girja Ram Tola",
    "ks:ks_pop":1054,
    "ks:ks_type":"HABITATION",
    "name:eng_x_preferred":[
        "Girja Ram Tola"
    ],
    "wof:name":"Girja Ram Tola",
    "wof:placetype":"locality",
    "wof:population":1054
},
  "geometry": {"coordinates":[84.76951099999999,26.662576],"type":"Point"}
}