{
  "type": "Feature",
  "properties": {
    "iso:country":"IN",
    "ks:ks_alt_nam":"Lukkupura urf Ashrafnagar",
    "ks:ks_name":"Lukkupura Urf Ashrafnagar",
    "ks:ks_pop":566,
    "ks:ks_type":"HABITATION",
    "name:eng_x_preferred":[
        "Lukkupura Urf Ashrafnagar"
    ],
    "wof:name":"Lukkupura Urf Ashrafnagar",
    "wof:placetype":"locality",
    "wof:population":566
},
  "geometry": {"coordinates":[72.456903,27.316436],"type":"Point"}
}