{
  "type": "Feature",
  "properties": {
    "gn:admin1_code":"39.0",
    "gn:admin2_code":"64.0",
    "gn:asciiname":"Khadgoli",
    "gn:country_code":"IN",
    "gn:dem":1247,
    "gn:feature_class":"P",
    "gn:feature_code":"PPL",
    "gn:name":"Khadgoli",
    "gn:population":0,
    "gn:timezone":"Asia/Kolkata",
    "iso:country":"IN",
    "wof:name":"Khadgoli",
    "wof:placetype":"locality"
},
  "geometry": {"coordinates":[79.40425999999999,29.68183],"type":"Point"}
}