{
  "type": "Feature",
  "properties": {
    "iso:country":"IN",
    "ks:ks_name":"Bhikhampur",
    "ks:ks_pop":179,
    "ks:ks_type":"HABITATION",
    "ks:ks_uagg_main":0,
    "name:eng_x_preferred":[
        "Bhikhampur"
    ],
    "wof:name":"Bhikhampur",
    "wof:placetype":"neighbourhood",
    "wof:population":179
},
  "geometry": {"coordinates":[81.635989,26.895528],"type":"Point"}
}