{
  "type": "Feature",
  "properties": {
    "gn:admin1_code":"19.0",
    "gn:admin2_code":"574.0",
    "gn:asciiname":"Birakanahalli",
    "gn:country_code":"IN",
    "gn:dem":954,
    "gn:feature_class":"P",
    "gn:feature_code":"PPL",
    "gn:name":"B\u012brakanahalli",
    "gn:population":0,
    "gn:timezone":"Asia/Kolkata",
    "iso:country":"IN",
    "wof:name":"Birakanahalli",
    "wof:placetype":"locality"
},
  "geometry": {"coordinates":[75.93054000000002,13.0372],"type":"Point"}
}