{
  "type": "Feature",
  "properties": {
    "gn:admin1_code":"35.0",
    "gn:admin2_code":"443",
    "gn:asciiname":"Bhainswaha",
    "gn:country_code":"IN",
    "gn:dem":407,
    "gn:feature_class":"P",
    "gn:feature_code":"PPL",
    "gn:name":"Bhainsw\u0101ha",
    "gn:population":0,
    "gn:timezone":"Asia/Kolkata",
    "iso:country":"IN",
    "wof:name":"Bhainswaha",
    "wof:placetype":"locality"
},
  "geometry": {"coordinates":[78.06426999999999,24.01309],"type":"Point"}
}