{
  "type": "Feature",
  "properties": {
    "iso:country":"IN",
    "ks:ks_name":"Adalakoppa",
    "ks:ks_pop":122,
    "ks:ks_type":"HABITATION",
    "name:eng_x_preferred":[
        "Adalakoppa"
    ],
    "wof:name":"Adalakoppa",
    "wof:placetype":"locality",
    "wof:population":122
},
  "geometry": {"coordinates":[75.13549,14.028888],"type":"Point"}
}