{
  "type": "Feature",
  "properties": {
    "gn:admin1_code":"25.0",
    "gn:admin2_code":"605.0",
    "gn:asciiname":"Nemili",
    "gn:country_code":"IN",
    "gn:dem":429,
    "gn:feature_class":"P",
    "gn:feature_code":"PPL",
    "gn:name":"Nemili",
    "gn:population":0,
    "gn:timezone":"Asia/Kolkata",
    "iso:country":"IN",
    "name:bpy_x_preferred":[
        "\u09a8\u09c7\u09ae\u09bf\u09b2\u09bf"
    ],
    "name:ceb_x_preferred":[
        "Nemili"
    ],
    "name:ita_x_preferred":[
        "Nemili"
    ],
    "name:msa_x_preferred":[
        "Nemili"
    ],
    "name:new_x_preferred":[
        "\u0928\u0947\u092e\u093f\u0932\u0940"
    ],
    "name:nld_x_preferred":[
        "Nemili"
    ],
    "name:por_x_preferred":[
        "Nemili"
    ],
    "name:swe_x_preferred":[
        "Nemili"
    ],
    "name:tam_x_preferred":[
        "\u0ba8\u0bc6\u0bae\u0bbf\u0bb2\u0bbf"
    ],
    "name:vie_x_preferred":[
        "Nemili"
    ],
    "name:zho_x_preferred":[
        "\u5185\u7c73\u5229"
    ],
    "wof:name":"Nemili",
    "wof:placetype":"neighbourhood"
},
  "geometry": {"coordinates":[78.51533999999999,12.59578],"type":"Point"}
}