{
  "type": "Feature",
  "properties": {
    "iso:country":"IN",
    "ks:ks_alt_nam":"Mettu alipatty",
    "ks:ks_name":"Mettu Alipatty",
    "ks:ks_pop":353,
    "ks:ks_type":"HABITATION",
    "name:eng_x_preferred":[
        "Mettu Alipatty"
    ],
    "wof:name":"Mettu Alipatty",
    "wof:placetype":"locality",
    "wof:population":353
},
  "geometry": {"coordinates":[78.412567,10.659529],"type":"Point"}
}