{
  "type": "Feature",
  "properties": {
    "iso:country":"IN",
    "ks:ks_name":"Badhi Tola",
    "ks:ks_pop":308,
    "ks:ks_type":"HABITATION",
    "name:eng_x_preferred":[
        "Badhi Tola"
    ],
    "wof:name":"Badhi Tola",
    "wof:placetype":"locality",
    "wof:population":308
},
  "geometry": {"coordinates":[84.869868,26.555099],"type":"Point"}
}