{
  "type": "Feature",
  "properties": {
    "gn:admin1_code":"37.0",
    "gn:admin2_code":"403",
    "gn:asciiname":"Konpara",
    "gn:country_code":"IN",
    "gn:dem":316,
    "gn:feature_class":"P",
    "gn:feature_code":"PPL",
    "gn:name":"Konp\u0101ra",
    "gn:population":0,
    "gn:timezone":"Asia/Kolkata",
    "iso:country":"IN",
    "name:und_x_variant":[
        "Kanp\u0101ra",
        "Konp\u0101ra"
    ],
    "wof:name":"Konpara",
    "wof:placetype":"locality"
},
  "geometry": {"coordinates":[83.40325,22.24825],"type":"Point"}
}