{
  "type": "Feature",
  "properties": {
    "iso:country":"IN",
    "ks:ks_name":"Ladwadi",
    "ks:ks_pop":52,
    "ks:ks_type":"HABITATION",
    "name:eng_x_preferred":[
        "Ladwadi"
    ],
    "wof:name":"Ladwadi",
    "wof:placetype":"locality",
    "wof:population":52
},
  "geometry": {"coordinates":[73.637573,16.064299],"type":"Point"}
}