{
  "type": "Feature",
  "properties": {
    "iso:country":"IN",
    "ks:ks_name":"Sembo",
    "ks:ks_pop":1051,
    "ks:ks_type":"VILLAGE",
    "ks:ks_uagg_main":1,
    "name:eng_x_preferred":[
        "Sembo"
    ],
    "wof:name":"Sembo",
    "wof:placetype":"neighbourhood",
    "wof:population":1051
},
  "geometry": {"coordinates":[85.23298200000001,23.297352],"type":"Point"}
}