{
  "type": "Feature",
  "properties": {
    "gn:admin1_code":"25.0",
    "gn:admin2_code":"626.0",
    "gn:asciiname":"Olaiyur",
    "gn:country_code":"IN",
    "gn:dem":25,
    "gn:feature_class":"P",
    "gn:feature_code":"PPL",
    "gn:name":"Olaiy\u016br",
    "gn:population":0,
    "gn:timezone":"Asia/Kolkata",
    "iso:country":"IN",
    "wof:name":"Olaiyur",
    "wof:placetype":"locality"
},
  "geometry": {"coordinates":[78.63964,9.37545],"type":"Point"}
}