{
  "type": "Feature",
  "properties": {
    "iso:country":"IN",
    "ks:ks_name":"Barajamsala",
    "ks:ks_pop":391,
    "ks:ks_type":"HABITATION",
    "name:eng_x_preferred":[
        "Barajamsala"
    ],
    "wof:name":"Barajamsala",
    "wof:placetype":"locality",
    "wof:population":391
},
  "geometry": {"coordinates":[87.013009,22.282199],"type":"Point"}
}