{
  "type": "Feature",
  "properties": {
    "iso:country":"IN",
    "ks:ks_name":"Vokahiya",
    "ks:ks_pop":213,
    "ks:ks_type":"HABITATION",
    "name:eng_x_preferred":[
        "Vokahiya"
    ],
    "wof:name":"Vokahiya",
    "wof:placetype":"locality",
    "wof:population":213
},
  "geometry": {"coordinates":[81.484858,27.267022],"type":"Point"}
}