{
  "type": "Feature",
  "properties": {
    "gn:admin1_code":"36",
    "gn:admin2_code":"188.0",
    "gn:asciiname":"Khajuri Pande",
    "gn:country_code":"IN",
    "gn:dem":75,
    "gn:feature_class":"P",
    "gn:feature_code":"PPL",
    "gn:name":"Khaj\u016bri P\u0101nde",
    "gn:population":0,
    "gn:timezone":"Asia/Kolkata",
    "iso:country":"IN",
    "wof:name":"Khajuri Pande",
    "wof:placetype":"locality"
},
  "geometry": {"coordinates":[83.49053000000001,26.30388],"type":"Point"}
}