{
  "type": "Feature",
  "properties": {
    "iso:country":"IN",
    "ks:ks_name":"Lowapi",
    "ks:ks_pop":55,
    "ks:ks_type":"HABITATION",
    "name:eng_x_preferred":[
        "Lowapi"
    ],
    "wof:name":"Lowapi",
    "wof:placetype":"locality",
    "wof:population":55
},
  "geometry": {"coordinates":[85.742268,22.165781],"type":"Point"}
}