{
  "type": "Feature",
  "properties": {
    "gn:admin1_code":"21.0",
    "gn:admin2_code":"393",
    "gn:asciiname":"Dhandamunda",
    "gn:country_code":"IN",
    "gn:dem":297,
    "gn:feature_class":"P",
    "gn:feature_code":"PPL",
    "gn:name":"Dhand\u0101munda",
    "gn:population":0,
    "gn:timezone":"Asia/Kolkata",
    "iso:country":"IN",
    "wof:name":"Dhandamunda",
    "wof:placetype":"locality"
},
  "geometry": {"coordinates":[82.92874,20.79692],"type":"Point"}
}