{
  "type": "Feature",
  "properties": {
    "iso:country":"IN",
    "ks:ks_alt_nam":"Muttaya kundu Forest Rd End",
    "ks:ks_name":"Muttaya Kundu Forest Rd End",
    "ks:ks_pop":386,
    "ks:ks_type":"HABITATION",
    "name:eng_x_preferred":[
        "Muttaya Kundu Forest Rd End"
    ],
    "wof:name":"Muttaya Kundu Forest Rd End",
    "wof:placetype":"locality",
    "wof:population":386
},
  "geometry": {"coordinates":[76.376041,10.683059],"type":"Point"}
}