{
  "type": "Feature",
  "properties": {
    "iso:country":"IN",
    "ks:ks_alt_nam":"Dunri falia",
    "ks:ks_name":"Dunri Falia",
    "ks:ks_pop":185,
    "ks:ks_type":"HABITATION",
    "ks:ks_uagg_main":0,
    "name:eng_x_preferred":[
        "Dunri Falia"
    ],
    "wof:name":"Dunri Falia",
    "wof:placetype":"neighbourhood",
    "wof:population":185
},
  "geometry": {"coordinates":[73.328694,21.027472],"type":"Point"}
}