{
  "type": "Feature",
  "properties": {
    "iso:country":"IN",
    "ks:ks_name":"Panchuara",
    "ks:ks_pop":2329,
    "ks:ks_type":"VILLAGE",
    "name:eng_x_preferred":[
        "Panchuara"
    ],
    "wof:name":"Panchuara",
    "wof:placetype":"locality",
    "wof:population":2329
},
  "geometry": {"coordinates":[87.52118299999999,24.518248],"type":"Point"}
}