{
  "type": "Feature",
  "properties": {
    "iso:country":"IN",
    "ks:ks_name":"Naramamidi Gondi",
    "ks:ks_pop":86,
    "ks:ks_type":"VILLAGE",
    "name:eng_x_preferred":[
        "Naramamidi Gondi"
    ],
    "wof:name":"Naramamidi Gondi",
    "wof:placetype":"locality",
    "wof:population":86
},
  "geometry": {"coordinates":[82.15384,18.02429],"type":"Point"}
}