{
  "type": "Feature",
  "properties": {
    "gn:admin1_code":"25.0",
    "gn:admin2_code":"619.0",
    "gn:asciiname":"Ariyalur",
    "gn:country_code":"IN",
    "gn:dem":5,
    "gn:feature_class":"P",
    "gn:feature_code":"PPL",
    "gn:name":"Ariyal\u016br",
    "gn:population":0,
    "gn:timezone":"Asia/Kolkata",
    "iso:country":"IN",
    "name:ara_x_preferred":[
        "\u0623\u0631\u064a\u0644\u0648\u0631"
    ],
    "name:ben_bn_x_preferred":[
        "\u0986\u09b0\u09bf\u09df\u09be\u09b2\u09c1\u09b0"
    ],
    "name:ben_in_x_preferred":[
        "\u0986\u09b0\u09bf\u09df\u09be\u09b2\u09c1\u09b0"
    ],
    "name:bpy_x_preferred":[
        "\u0986\u09b0\u09bf\u09af\u09bc\u09be\u09b2\u09c1\u09b0"
    ],
    "name:cat_x_preferred":[
        "Ariyalur"
    ],
    "name:ceb_x_preferred":[
        "Ariyal\u016br"
    ],
    "name:deu_x_preferred":[
        "Ariyalur"
    ],
    "name:fra_x_preferred":[
        "Ariyalur"
    ],
    "name:guj_x_preferred":[
        "\u0a85\u0ab0\u0abf\u0aaf\u0abe\u0ab2\u0ac1\u0ab0"
    ],
    "name:hin_x_preferred":[
        "\u0905\u0930\u093f\u092f\u093e\u0932\u0941\u0930"
    ],
    "name:hin_x_variant":[
        "\u0905\u0930\u093f\u092f\u093e\u0932\u0942\u0930"
    ],
    "name:ita_x_preferred":[
        "Ariyalur"
    ],
    "name:kan_x_preferred":[
        "\u0c85\u0cb0\u0cbf\u0caf\u0cb2\u0cc2\u0cb0\u0cc1"
    ],
    "name:kan_x_variant":[
        "\u0c85\u0cb0\u0cbf\u0caf\u0cb2\u0cc2\u0cb0\u0ccd"
    ],
    "name:mal_x_preferred":[
        "\u0d05\u0d30\u0d3f\u0d2f\u0d32\u0d42\u0d7c"
    ],
    "name:mar_x_preferred":[
        "\u0905\u0930\u093f\u092f\u093e\u0932\u0942\u0930"
    ],
    "name:msa_x_preferred":[
        "Ariyalur"
    ],
    "name:new_x_preferred":[
        "\u0905\u0930\u093f\u092f\u093e\u0932\u0941\u0930"
    ],
    "name:nld_x_preferred":[
        "Ariyalur"
    ],
    "name:pan_x_preferred":[
        "\u0a06\u0a30\u0a3f\u0a2f\u0a3e\u0a32\u0a41\u0a30"
    ],
    "name:pol_x_preferred":[
        "Ariyalur"
    ],
    "name:por_x_preferred":[
        "Ariyalur"
    ],
    "name:rus_x_preferred":[
        "\u0410\u0440\u0438\u044f\u043b\u0443\u0440"
    ],
    "name:san_x_preferred":[
        "\u0905\u0930\u093f\u092f\u0932\u0942\u0930\u094d"
    ],
    "name:spa_x_preferred":[
        "Ariyalur"
    ],
    "name:swe_x_preferred":[
        "Ariyal\u016br"
    ],
    "name:tam_x_preferred":[
        "\u0b85\u0bb0\u0bbf\u0baf\u0bb2\u0bc2\u0bb0\u0bcd"
    ],
    "name:tel_x_preferred":[
        "\u0c05\u0c30\u0c3f\u0c2f\u0c3e\u0c32\u0c42\u0c30\u0c4d"
    ],
    "name:urd_x_preferred":[
        "\u0627\u0631\u06cc\u0627\u0644\u0648\u0631"
    ],
    "name:vie_x_preferred":[
        "Ariyalur"
    ],
    "name:zho_x_preferred":[
        "\u963f\u91cc\u8036\u5362\u5c14"
    ],
    "wof:name":"Ariyalur",
    "wof:placetype":"locality"
},
  "geometry": {"coordinates":[79.65023000000002,10.54221],"type":"Point"}
}