{
  "type": "Feature",
  "properties": {
    "iso:country":"IN",
    "ks:ks_name":"Maruthur",
    "ks:ks_pop":637,
    "ks:ks_type":"HABITATION",
    "name:eng_x_preferred":[
        "Maruthur"
    ],
    "wof:name":"Maruthur",
    "wof:placetype":"locality",
    "wof:population":637
},
  "geometry": {"coordinates":[79.725283,11.112638],"type":"Point"}
}