{
  "type": "Feature",
  "properties": {
    "gn:admin1_code":"25.0",
    "gn:admin2_code":"631.0",
    "gn:asciiname":"Sundatti",
    "gn:country_code":"IN",
    "gn:dem":834,
    "gn:feature_class":"P",
    "gn:feature_code":"PPL",
    "gn:name":"Sundatti",
    "gn:population":0,
    "gn:timezone":"Asia/Kolkata",
    "iso:country":"IN",
    "ks:ks_name":"Sundatti",
    "ks:ks_pop":371,
    "ks:ks_type":"HABITATION",
    "ks:ks_uagg_main":0,
    "name:eng_x_preferred":[
        "Sundatti"
    ],
    "wof:name":"Sundatti",
    "wof:placetype":"neighbourhood",
    "wof:population":371
},
  "geometry": {"coordinates":[77.93342699999999,12.713033],"type":"Point"}
}