{
  "type": "Feature",
  "properties": {
    "iso:country":"IN",
    "ks:ks_name":"Dhobi Tola",
    "ks:ks_pop":1067,
    "ks:ks_type":"HABITATION",
    "name:eng_x_preferred":[
        "Dhobi Tola"
    ],
    "wof:name":"Dhobi Tola",
    "wof:placetype":"locality",
    "wof:population":1067
},
  "geometry": {"coordinates":[85.68605100000001,26.117343],"type":"Point"}
}