{
  "type": "Feature",
  "properties": {
    "iso:country":"IN",
    "ks:ks_name":"Kajla",
    "ks:ks_pop":160,
    "ks:ks_type":"VILLAGE",
    "name:eng_x_preferred":[
        "Kajla"
    ],
    "wof:name":"Kajla",
    "wof:placetype":"locality",
    "wof:population":160
},
  "geometry": {"coordinates":[80.602881,21.443787],"type":"Point"}
}