{
  "type": "Feature",
  "properties": {
    "iso:country":"IN",
    "ks:ks_name":"Naula",
    "ks:ks_pop":104,
    "ks:ks_type":"VILLAGE",
    "name:eng_x_preferred":[
        "Naula"
    ],
    "wof:name":"Naula",
    "wof:placetype":"locality",
    "wof:population":104
},
  "geometry": {"coordinates":[79.03201,30.197873],"type":"Point"}
}