{
  "type": "Feature",
  "properties": {
    "gn:admin1_code":"36.0",
    "gn:admin2_code":"146.0",
    "gn:asciiname":"Holipura",
    "gn:country_code":"IN",
    "gn:dem":224,
    "gn:feature_class":"P",
    "gn:feature_code":"PPL",
    "gn:name":"Hol\u012bpura",
    "gn:population":0,
    "gn:timezone":"Asia/Kolkata",
    "iso:country":"IN",
    "wof:name":"Holipura",
    "wof:placetype":"neighbourhood"
},
  "geometry": {"coordinates":[77.46423,26.84104],"type":"Point"}
}