{
  "type": "Feature",
  "properties": {
    "iso:country":"IN",
    "ks:ks_name":"Pure Bisesar",
    "ks:ks_pop":459,
    "ks:ks_type":"HABITATION",
    "ks:ks_uagg_main":0,
    "name:eng_x_preferred":[
        "Pure Bisesar"
    ],
    "wof:name":"Pure Bisesar",
    "wof:placetype":"neighbourhood",
    "wof:population":459
},
  "geometry": {"coordinates":[80.845653,26.053404],"type":"Point"}
}