{
  "type": "Feature",
  "properties": {
    "gn:admin1_code":"38.0",
    "gn:admin2_code":"357",
    "gn:asciiname":"Baharagora",
    "gn:country_code":"IN",
    "gn:dem":81,
    "gn:feature_class":"P",
    "gn:feature_code":"PPL",
    "gn:name":"Bahar\u0101gora",
    "gn:population":0,
    "gn:timezone":"Asia/Kolkata",
    "iso:country":"IN",
    "ks:ks_name":"Baharagora",
    "ks:ks_pop":1040,
    "ks:ks_type":"VILLAGE",
    "ks:ks_uagg_main":0,
    "name:ceb_x_preferred":[
        "Bahar\u0101gora"
    ],
    "name:eng_x_preferred":[
        "Baharagora"
    ],
    "name:swe_x_preferred":[
        "Bahar\u0101gora"
    ],
    "name:vie_x_preferred":[
        "Baharagora"
    ],
    "wof:name":"Baharagora",
    "wof:placetype":"neighbourhood",
    "wof:population":1040
},
  "geometry": {"coordinates":[86.720738,22.275293],"type":"Point"}
}