{
  "type": "Feature",
  "properties": {
    "gn:admin1_code":"25",
    "gn:admin2_code":"603.0",
    "gn:asciiname":"Sembiyam",
    "gn:cc2":"IN",
    "gn:country_code":"IN",
    "gn:dem":12,
    "gn:feature_class":"P",
    "gn:feature_code":"PPL",
    "gn:name":"Sembiyam",
    "gn:population":0,
    "gn:timezone":"Asia/Kolkata",
    "iso:country":"IN",
    "name:und_x_variant":[
        "Sembiem",
        "Sembivam",
        "Sembiyam"
    ],
    "wof:name":"Sembiyam",
    "wof:placetype":"locality"
},
  "geometry": {"coordinates":[80.2325,13.11667],"type":"Point"}
}