{
  "type": "Feature",
  "properties": {
    "gn:admin1_code":"36.0",
    "gn:admin2_code":"155.0",
    "gn:asciiname":"Patti Purwa",
    "gn:country_code":"IN",
    "gn:dem":144,
    "gn:feature_class":"P",
    "gn:feature_code":"PPL",
    "gn:name":"Patti Purwa",
    "gn:population":0,
    "gn:timezone":"Asia/Kolkata",
    "iso:country":"IN",
    "wof:name":"Patti Purwa",
    "wof:placetype":"locality"
},
  "geometry": {"coordinates":[80.22256999999998,27.27787],"type":"Point"}
}