{
  "type": "Feature",
  "properties": {
    "iso:country":"IN",
    "ks:ks_name":"Patil Falia",
    "ks:ks_pop":348,
    "ks:ks_type":"HABITATION",
    "name:eng_x_preferred":[
        "Patil Falia"
    ],
    "wof:name":"Patil Falia",
    "wof:placetype":"locality",
    "wof:population":348
},
  "geometry": {"coordinates":[73.298389,20.265444],"type":"Point"}
}