{
  "type": "Feature",
  "properties": {
    "iso:country":"IN",
    "ks:ks_name":"Jamuguri",
    "ks:ks_pop":359,
    "ks:ks_type":"HABITATION",
    "ks:ks_uagg_main":0,
    "name:eng_x_preferred":[
        "Jamuguri"
    ],
    "wof:name":"Jamuguri",
    "wof:placetype":"neighbourhood",
    "wof:population":359
},
  "geometry": {"coordinates":[93.13218000000001,26.23519],"type":"Point"}
}