{
  "type": "Feature",
  "properties": {
    "iso:country":"IN",
    "ks:ks_name":"Teliyana",
    "ks:ks_pop":111,
    "ks:ks_type":"HABITATION",
    "ks:ks_uagg_main":0,
    "name:eng_x_preferred":[
        "Teliyana"
    ],
    "wof:name":"Teliyana",
    "wof:placetype":"neighbourhood",
    "wof:population":111
},
  "geometry": {"coordinates":[82.828177,26.279242],"type":"Point"}
}