{
  "type": "Feature",
  "properties": {
    "gn:admin1_code":"24",
    "gn:admin2_code":"122.0",
    "gn:asciiname":"Saganer",
    "gn:country_code":"IN",
    "gn:dem":412,
    "gn:feature_class":"P",
    "gn:feature_code":"PPL",
    "gn:name":"S\u0101g\u0101ner",
    "gn:population":0,
    "gn:timezone":"Asia/Kolkata",
    "iso:country":"IN",
    "name:und_x_variant":[
        "S\u0101g\u0101ner",
        "S\u0101nganer"
    ],
    "wof:name":"Saganer",
    "wof:placetype":"locality"
},
  "geometry": {"coordinates":[74.66876999999999,25.37441],"type":"Point"}
}