{
  "type": "Feature",
  "properties": {
    "iso:country":"IN",
    "qs:name":"Tri Nagar",
    "qs:name_adm0":"India",
    "qs:name_adm1":"Delhi",
    "qs:photos":1,
    "qs:photos_1k":1,
    "qs:photos_9k":1,
    "qs:photos_9r":1,
    "qs:photos_all":1,
    "qs:photos_sr":1,
    "qs:placetype":"Suburb",
    "qs:pop_sr":"0",
    "wof:name":"Tri Nagar",
    "wof:placetype":"neighbourhood"
},
  "geometry": {"coordinates":[77.08844999999999,28.63956],"type":"Point"}
}