{
  "type": "Feature",
  "properties": {
    "iso:country":"IN",
    "ks:ks_name":"Babnabera",
    "ks:ks_pop":2752,
    "ks:ks_type":"VILLAGE",
    "name:eng_x_preferred":[
        "Babnabera"
    ],
    "wof:name":"Babnabera",
    "wof:placetype":"neighbourhood",
    "wof:population":2752
},
  "geometry": {"coordinates":[87.361414,23.454581],"type":"Point"}
}