{
  "type": "Feature",
  "properties": {
    "iso:country":"IN",
    "ks:ks_name":"Mahiuddinpur Yusufabad",
    "ks:ks_pop":3,
    "ks:ks_type":"VILLAGE",
    "name:eng_x_preferred":[
        "Mahiuddinpur Yusufabad"
    ],
    "wof:name":"Mahiuddinpur Yusufabad",
    "wof:placetype":"locality",
    "wof:population":3
},
  "geometry": {"coordinates":[77.85791500000001,28.695226],"type":"Point"}
}