{
  "type": "Feature",
  "properties": {
    "gn:admin1_code":"40",
    "gn:admin2_code":"540.0",
    "gn:asciiname":"Salbaka",
    "gn:country_code":"IN",
    "gn:dem":99,
    "gn:feature_class":"P",
    "gn:feature_code":"PPL",
    "gn:name":"Salb\u0101ka",
    "gn:population":0,
    "gn:timezone":"Asia/Kolkata",
    "iso:country":"IN",
    "wof:name":"Salbaka",
    "wof:placetype":"locality"
},
  "geometry": {"coordinates":[80.37164,18.40521],"type":"Point"}
}