{
  "type": "Feature",
  "properties": {
    "iso:country":"IN",
    "ks:ks_name":"Therabecha",
    "ks:ks_pop":132,
    "ks:ks_type":"HABITATION",
    "name:eng_x_preferred":[
        "Therabecha"
    ],
    "wof:name":"Therabecha",
    "wof:placetype":"locality",
    "wof:population":132
},
  "geometry": {"coordinates":[92.947549,26.34635],"type":"Point"}
}