{
  "type": "Feature",
  "properties": {
    "gn:admin1_code":"24.0",
    "gn:admin2_code":"110.0",
    "gn:asciiname":"Chhani ki Dhani",
    "gn:country_code":"IN",
    "gn:dem":391,
    "gn:feature_class":"P",
    "gn:feature_code":"PPL",
    "gn:name":"Chh\u0101ni ki Dh\u0101ni",
    "gn:population":0,
    "gn:timezone":"Asia/Kolkata",
    "iso:country":"IN",
    "wof:name":"Chhani ki Dhani",
    "wof:placetype":"locality"
},
  "geometry": {"coordinates":[76.13032,27.55928],"type":"Point"}
}