{
  "type": "Feature",
  "properties": {
    "iso:country":"IN",
    "ks:ks_name":"Jhareli",
    "ks:ks_pop":1734,
    "ks:ks_type":"VILLAGE",
    "name:eng_x_preferred":[
        "Jhareli"
    ],
    "wof:name":"Jhareli",
    "wof:placetype":"locality",
    "wof:population":1734
},
  "geometry": {"coordinates":[73.210256,27.274628],"type":"Point"}
}