{
  "type": "Feature",
  "properties": {
    "gn:admin1_code":"39.0",
    "gn:admin2_code":"66.0",
    "gn:asciiname":"Talli Dini",
    "gn:country_code":"IN",
    "gn:dem":1738,
    "gn:feature_class":"P",
    "gn:feature_code":"PPL",
    "gn:name":"Talli Dini",
    "gn:population":0,
    "gn:timezone":"Asia/Kolkata",
    "iso:country":"IN",
    "wof:name":"Talli Dini",
    "wof:placetype":"locality"
},
  "geometry": {"coordinates":[79.7175,29.40211],"type":"Point"}
}