{
  "type": "Feature",
  "properties": {
    "iso:country":"IN",
    "ks:ks_name":"Yasodadebi Bari Tola",
    "ks:ks_pop":97,
    "ks:ks_type":"HABITATION",
    "name:eng_x_preferred":[
        "Yasodadebi Bari Tola"
    ],
    "wof:name":"Yasodadebi Bari Tola",
    "wof:placetype":"locality",
    "wof:population":97
},
  "geometry": {"coordinates":[85.126704,26.423824],"type":"Point"}
}