{
  "type": "Feature",
  "properties": {
    "gn:admin1_code":"36.0",
    "gn:admin2_code":"167",
    "gn:asciiname":"Shyampura",
    "gn:country_code":"IN",
    "gn:dem":358,
    "gn:feature_class":"P",
    "gn:feature_code":"PPL",
    "gn:name":"Shy\u0101mpura",
    "gn:population":0,
    "gn:timezone":"Asia/Kolkata",
    "iso:country":"IN",
    "wof:name":"Shyampura",
    "wof:placetype":"locality"
},
  "geometry": {"coordinates":[78.53098,24.72111],"type":"Point"}
}