{
  "type": "Feature",
  "properties": {
    "gn:admin1_code":"25.0",
    "gn:admin2_code":"617.0",
    "gn:asciiname":"Valaiyamadevi",
    "gn:country_code":"IN",
    "gn:dem":24,
    "gn:feature_class":"P",
    "gn:feature_code":"PPL",
    "gn:name":"Valaiyam\u0101devi",
    "gn:population":0,
    "gn:timezone":"Asia/Kolkata",
    "iso:country":"IN",
    "wof:name":"Valaiyamadevi",
    "wof:placetype":"locality"
},
  "geometry": {"coordinates":[79.50012,11.47155],"type":"Point"}
}