{
  "type": "Feature",
  "properties": {
    "gn:country":"IN",
    "gn:fcode":"PPL",
    "gn:pop":38939,
    "iso:country":"IN",
    "name:unk_x_variant":[
        "Bhagalpur"
    ],
    "qs:name":"Banka",
    "qs:name_adm0":"India",
    "qs:name_adm1":"Jharkhand",
    "qs:photos_9r":0,
    "qs:photos_sr":0,
    "qs:placetype":"Town",
    "qs:pop_sr":"7",
    "wd:wordcount":108,
    "wof:name":"Banka",
    "wof:placetype":"locality",
    "wof:population":38939
},
  "geometry": {"coordinates":[86.92256999999999,24.88091],"type":"Point"}
}