{
  "type": "Feature",
  "properties": {
    "iso:country":"IN",
    "ks:ks_name":"Chak Manohari",
    "ks:ks_pop":476,
    "ks:ks_type":"VILLAGE",
    "ks:ks_uagg_main":0,
    "name:eng_x_preferred":[
        "Chak Manohari"
    ],
    "wof:name":"Chak Manohari",
    "wof:placetype":"neighbourhood",
    "wof:population":476
},
  "geometry": {"coordinates":[88.245605,22.092477],"type":"Point"}
}