{
  "type": "Feature",
  "properties": {
    "iso:country":"IN",
    "ks:ks_name":"Nauvan Purwa",
    "ks:ks_pop":312,
    "ks:ks_type":"HABITATION",
    "name:eng_x_preferred":[
        "Nauvan Purwa"
    ],
    "wof:name":"Nauvan Purwa",
    "wof:placetype":"locality",
    "wof:population":312
},
  "geometry": {"coordinates":[81.35433999999999,27.809717],"type":"Point"}
}