{
  "type": "Feature",
  "properties": {
    "iso:country":"IN",
    "ks:ks_name":"Acharjee Para",
    "ks:ks_pop":121,
    "ks:ks_type":"HABITATION",
    "ks:ks_uagg_main":0,
    "name:eng_x_preferred":[
        "Acharjee Para"
    ],
    "wof:name":"Acharjee Para",
    "wof:placetype":"neighbourhood",
    "wof:population":121
},
  "geometry": {"coordinates":[91.983436,24.094383],"type":"Point"}
}