{
  "type": "Feature",
  "properties": {
    "iso:country":"IN",
    "ks:ks_name":"Mahuli",
    "ks:ks_pop":50,
    "ks:ks_type":"HABITATION",
    "name:eng_x_preferred":[
        "Mahuli"
    ],
    "wof:name":"Mahuli",
    "wof:placetype":"locality",
    "wof:population":50
},
  "geometry": {"coordinates":[80.175995,20.865414],"type":"Point"}
}