{
  "type": "Feature",
  "properties": {
    "iso:country":"IN",
    "ks:ks_name":"Harha",
    "ks:ks_pop":222,
    "ks:ks_type":"HABITATION",
    "name:eng_x_preferred":[
        "Harha"
    ],
    "wof:name":"Harha",
    "wof:placetype":"locality",
    "wof:population":222
},
  "geometry": {"coordinates":[81.724132,27.307156],"type":"Point"}
}