{
  "type": "Feature",
  "properties": {
    "iso:country":"IN",
    "ks:ks_name":"Dakkhinr Milekuchi",
    "ks:ks_pop":601,
    "ks:ks_type":"HABITATION",
    "ks:ks_uagg_main":0,
    "name:eng_x_preferred":[
        "Dakkhinr Milekuchi"
    ],
    "wof:name":"Dakkhinr Milekuchi",
    "wof:placetype":"neighbourhood",
    "wof:population":601
},
  "geometry": {"coordinates":[91.051402,26.284368],"type":"Point"}
}