{
  "type": "Feature",
  "properties": {
    "gn:admin1_code":"19.0",
    "gn:admin2_code":"581.0",
    "gn:asciiname":"Byatarayanahalli",
    "gn:country_code":"IN",
    "gn:dem":780,
    "gn:feature_class":"P",
    "gn:feature_code":"PPL",
    "gn:name":"Byatarayanahalli",
    "gn:population":0,
    "gn:timezone":"Asia/Kolkata",
    "iso:country":"IN",
    "wof:name":"Byatarayanahalli",
    "wof:placetype":"locality"
},
  "geometry": {"coordinates":[78.33920999999999,12.99257],"type":"Point"}
}