{
  "type": "Feature",
  "properties": {
    "gn:admin1_code":"35",
    "gn:admin2_code":"449.0",
    "gn:asciiname":"Gadrapur",
    "gn:country_code":"IN",
    "gn:dem":298,
    "gn:feature_class":"P",
    "gn:feature_code":"PPL",
    "gn:name":"G\u0101dr\u0101pur",
    "gn:population":0,
    "gn:timezone":"Asia/Kolkata",
    "iso:country":"IN",
    "wof:name":"Gadrapur",
    "wof:placetype":"locality"
},
  "geometry": {"coordinates":[77.27781,22.49014],"type":"Point"}
}