{
  "type": "Feature",
  "properties": {
    "iso:country":"IN",
    "ks:ks_name":"Kalua",
    "ks:ks_pop":9189,
    "ks:ks_type":"VILLAGE",
    "ks:ks_uagg_main":0,
    "name:eng_x_preferred":[
        "Kalua"
    ],
    "wof:name":"Kalua",
    "wof:placetype":"neighbourhood",
    "wof:population":9189
},
  "geometry": {"coordinates":[88.313244,22.448455],"type":"Point"}
}