{
  "type": "Feature",
  "properties": {
    "gn:admin1_code":"11",
    "gn:admin2_code":"27.0",
    "gn:asciiname":"Aiwara",
    "gn:country_code":"IN",
    "gn:dem":1042,
    "gn:feature_class":"P",
    "gn:feature_code":"PPL",
    "gn:name":"Aiwara",
    "gn:population":0,
    "gn:timezone":"Asia/Kolkata",
    "iso:country":"IN",
    "wof:name":"Aiwara",
    "wof:placetype":"locality"
},
  "geometry": {"coordinates":[76.76996,31.97943],"type":"Point"}
}