{
  "type": "Feature",
  "properties": {
    "iso:country":"IN",
    "ks:ks_name":"Kelawara A",
    "ks:ks_pop":345,
    "ks:ks_type":"HABITATION",
    "name:eng_x_preferred":[
        "Kelawara A"
    ],
    "wof:name":"Kelawara A",
    "wof:placetype":"locality",
    "wof:population":345
},
  "geometry": {"coordinates":[73.527265,24.061418],"type":"Point"}
}