{
  "type": "Feature",
  "properties": {
    "iso:country":"IN",
    "ks:ks_name":"Mori Puthikhaity",
    "ks:ks_pop":1329,
    "ks:ks_type":"VILLAGE",
    "ks:ks_uagg_main":0,
    "name:eng_x_preferred":[
        "Mori Puthikhaity"
    ],
    "wof:name":"Mori Puthikhaity",
    "wof:placetype":"neighbourhood",
    "wof:population":1329
},
  "geometry": {"coordinates":[92.828968,26.476475],"type":"Point"}
}