{
  "type": "Feature",
  "properties": {
    "iso:country":"IN",
    "ks:ks_name":"Balkani",
    "ks:ks_pop":299,
    "ks:ks_type":"VILLAGE",
    "name:eng_x_preferred":[
        "Balkani"
    ],
    "wof:name":"Balkani",
    "wof:placetype":"locality",
    "wof:population":299
},
  "geometry": {"coordinates":[87.449478,24.990475],"type":"Point"}
}