{
  "type": "Feature",
  "properties": {
    "iso:country":"IN",
    "ks:ks_name":"Janhamunda",
    "ks:ks_pop":100,
    "ks:ks_type":"VILLAGE",
    "name:eng_x_preferred":[
        "Janhamunda"
    ],
    "wof:name":"Janhamunda",
    "wof:placetype":"locality",
    "wof:population":100
},
  "geometry": {"coordinates":[85.235834,20.745211],"type":"Point"}
}