{
  "type": "Feature",
  "properties": {
    "iso:country":"IN",
    "ks:ks_name":"Sabakar",
    "ks:ks_pop":10,
    "ks:ks_type":"HABITATION",
    "name:eng_x_preferred":[
        "Sabakar"
    ],
    "wof:name":"Sabakar",
    "wof:placetype":"locality",
    "wof:population":10
},
  "geometry": {"coordinates":[74.773365,14.515153],"type":"Point"}
}