{
  "type": "Feature",
  "properties": {
    "iso:country":"IN",
    "ks:ks_alt_nam":"DEVARAGADDE",
    "ks:ks_name":"Devaragadde",
    "ks:ks_pop":2,
    "ks:ks_type":"HABITATION",
    "name:eng_x_preferred":[
        "Devaragadde"
    ],
    "wof:name":"Devaragadde",
    "wof:placetype":"locality",
    "wof:population":2
},
  "geometry": {"coordinates":[75.393416,13.811411],"type":"Point"}
}