{
  "type": "Feature",
  "properties": {
    "iso:country":"IN",
    "ks:ks_name":"Shakti Nagar",
    "ks:ks_pop":766,
    "ks:ks_type":"HABITATION",
    "name:eng_x_preferred":[
        "Shakti Nagar"
    ],
    "wof:name":"Shakti Nagar",
    "wof:placetype":"locality",
    "wof:population":766
},
  "geometry": {"coordinates":[71.956778,27.705658],"type":"Point"}
}