{
  "type": "Feature",
  "properties": {
    "iso:country":"IN",
    "ks:ks_name":"Miya",
    "ks:ks_pop":110,
    "ks:ks_type":"HABITATION",
    "name:eng_x_preferred":[
        "Miya"
    ],
    "wof:name":"Miya",
    "wof:placetype":"locality",
    "wof:population":110
},
  "geometry": {"coordinates":[75.27141399999999,13.039223],"type":"Point"}
}