{
  "type": "Feature",
  "properties": {
    "gn:admin1_code":"19.0",
    "gn:admin2_code":"563",
    "gn:asciiname":"Gunjavati",
    "gn:country_code":"IN",
    "gn:dem":519,
    "gn:feature_class":"P",
    "gn:feature_code":"PPL",
    "gn:name":"Gunjavati",
    "gn:population":0,
    "gn:timezone":"Asia/Kolkata",
    "iso:country":"IN",
    "name:und_x_variant":[
        "Gunjavan",
        "Gunj\u0101vati",
        "Gunjavati"
    ],
    "wof:name":"Gunjavati",
    "wof:placetype":"locality"
},
  "geometry": {"coordinates":[74.92529999999999,14.99616],"type":"Point"}
}