{
  "type": "Feature",
  "properties": {
    "gn:admin1_code":"19.0",
    "gn:admin2_code":"563",
    "gn:asciiname":"Gunjavati",
    "gn:country_code":"IN",
    "gn:dem":519,
    "gn:feature_class":"P",
    "gn:feature_code":"PPL",
    "gn:name":"Gunjavati",
    "gn:population":0,
    "gn:timezone":"Asia/Kolkata",
    "iso:country":"IN",
    "ks:ks_name":"Gunjavati",
    "ks:ks_pop":635,
    "ks:ks_type":"VILLAGE",
    "name:eng_x_preferred":[
        "Gunjavati"
    ],
    "name:und_x_variant":[
        "Gunjavan",
        "Gunj\u0101vati",
        "Gunjavati"
    ],
    "wof:name":"Gunjavati",
    "wof:placetype":"locality",
    "wof:population":635
},
  "geometry": {"coordinates":[74.931451,14.997037],"type":"Point"}
}