{
  "type": "Feature",
  "properties": {
    "iso:country":"IN",
    "ks:ks_name":"Ataranisf Thathiya",
    "ks:ks_pop":543,
    "ks:ks_type":"VILLAGE",
    "ks:ks_uagg_main":0,
    "name:eng_x_preferred":[
        "Ataranisf Thathiya"
    ],
    "wof:name":"Ataranisf Thathiya",
    "wof:placetype":"neighbourhood",
    "wof:population":543
},
  "geometry": {"coordinates":[79.820628,27.050667],"type":"Point"}
}