{
  "type": "Feature",
  "properties": {
    "iso:country":"IN",
    "ks:ks_name":"Bari",
    "ks:ks_pop":452,
    "ks:ks_type":"VILLAGE",
    "ks:ks_uagg_main":0,
    "name:eng_x_preferred":[
        "Bari"
    ],
    "wof:name":"Bari",
    "wof:placetype":"neighbourhood",
    "wof:population":452
},
  "geometry": {"coordinates":[86.063202,20.660195],"type":"Point"}
}