{
  "type": "Feature",
  "properties": {
    "gn:admin1_code":"11",
    "gn:admin2_code":"23.0",
    "gn:asciiname":"Gador",
    "gn:country_code":"IN",
    "gn:dem":1390,
    "gn:feature_class":"P",
    "gn:feature_code":"PPL",
    "gn:name":"Gador",
    "gn:population":0,
    "gn:timezone":"Asia/Kolkata",
    "iso:country":"IN",
    "wof:name":"Gador",
    "wof:placetype":"locality"
},
  "geometry": {"coordinates":[76.19533,32.76059],"type":"Point"}
}