{
  "type": "Feature",
  "properties": {
    "gn:admin1_code":"38.0",
    "gn:admin2_code":"354.0",
    "gn:asciiname":"Basaria",
    "gn:country_code":"IN",
    "gn:dem":223,
    "gn:feature_class":"P",
    "gn:feature_code":"PPL",
    "gn:name":"Basaria",
    "gn:population":0,
    "gn:timezone":"Asia/Kolkata",
    "iso:country":"IN",
    "name:bih_x_preferred":[
        "\u092c\u0938\u0930\u093f\u092f\u093e"
    ],
    "name:bpy_x_preferred":[
        "\u09ac\u09be\u09b8\u09be\u09b0\u09bf\u09af\u09bc\u09be"
    ],
    "name:ita_x_preferred":[
        "Basaria"
    ],
    "name:msa_x_preferred":[
        "Basaria"
    ],
    "name:nld_x_preferred":[
        "Basaria"
    ],
    "name:por_x_preferred":[
        "Basaria"
    ],
    "name:spa_x_preferred":[
        "Basaria"
    ],
    "name:vie_x_preferred":[
        "Basaria"
    ],
    "name:zho_x_preferred":[
        "\u5df4\u8428\u91cc\u4e9a"
    ],
    "wof:name":"Basaria",
    "wof:placetype":"locality"
},
  "geometry": {"coordinates":[86.37546,23.78947],"type":"Point"}
}