{
  "type": "Feature",
  "properties": {
    "gn:country":"IN",
    "gn:fcode":"PPL",
    "gn:population":11162,
    "iso:country":"IN",
    "name:und_x_variant":[
        "Lakhsetipet"
    ],
    "qs:name":"Lakshettipet",
    "qs:photos_9r":0,
    "qs:photos_sr":0,
    "qs:pop_sr":"6",
    "wof:name":"Lakshettipet",
    "wof:placetype":"locality",
    "wof:population":11162
},
  "geometry": {"coordinates":[79.21666999999999,18.86667],"type":"Point"}
}