{
  "type": "Feature",
  "properties": {
    "gn:admin1_code":"16.0",
    "gn:admin2_code":"504.0",
    "gn:asciiname":"Jam",
    "gn:country_code":"IN",
    "gn:dem":308,
    "gn:feature_class":"P",
    "gn:feature_code":"PPL",
    "gn:name":"J\u0101m",
    "gn:population":0,
    "gn:timezone":"Asia/Kolkata",
    "iso:country":"IN",
    "name:tur_x_preferred":[
        "Re\u00e7el"
    ],
    "wof:name":"Jam",
    "wof:placetype":"neighbourhood"
},
  "geometry": {"coordinates":[78.22411,21.02606],"type":"Point"}
}