{
  "type": "Feature",
  "properties": {
    "gn:admin1_code":"36",
    "gn:admin2_code":"200.0",
    "gn:asciiname":"Barwari",
    "gn:country_code":"IN",
    "gn:dem":419,
    "gn:feature_class":"P",
    "gn:feature_code":"PPL",
    "gn:name":"Barw\u0101ri",
    "gn:population":0,
    "gn:timezone":"Asia/Kolkata",
    "iso:country":"IN",
    "wof:name":"Barwari",
    "wof:placetype":"locality"
},
  "geometry": {"coordinates":[83.48569000000001,24.66214],"type":"Point"}
}