{
  "type": "Feature",
  "properties": {
    "gn:admin1_code":"16",
    "gn:admin2_code":"510.0",
    "gn:asciiname":"Bhalki",
    "gn:country_code":"IN",
    "gn:dem":390,
    "gn:feature_class":"P",
    "gn:feature_code":"PPL",
    "gn:name":"Bh\u0101lki",
    "gn:population":0,
    "gn:timezone":"Asia/Kolkata",
    "iso:country":"IN",
    "ks:ks_alt_nam":"Bh\u0101lki",
    "ks:ks_name":"Bhalki",
    "ks:ks_pop":0,
    "ks:ks_type":"VILLAGE",
    "name:ben_x_preferred":[
        "\u09ad\u09be\u09b2\u0995\u09bf"
    ],
    "name:bpy_x_preferred":[
        "\u09ad\u09be\u09b2\u0995\u09bf"
    ],
    "name:ceb_x_preferred":[
        "Bhalki Taluk"
    ],
    "name:eng_x_preferred":[
        "Bhalki"
    ],
    "name:eng_x_variant":[
        "Bh\u0101lki"
    ],
    "name:ita_x_preferred":[
        "Bhalki"
    ],
    "name:kan_x_preferred":[
        "\u0cad\u0cbe\u0cb2\u0ccd\u0c95\u0cbf"
    ],
    "name:mlg_x_preferred":[
        "Bhalki"
    ],
    "name:msa_x_preferred":[
        "Bhalki"
    ],
    "name:new_x_preferred":[
        "\u092d\u0932\u094d\u0915\u0940"
    ],
    "name:nld_x_preferred":[
        "Bhalki"
    ],
    "name:por_x_preferred":[
        "Bhalki"
    ],
    "name:san_x_preferred":[
        "\u092d\u093e\u0932\u094d\u0915\u0940"
    ],
    "name:spa_x_preferred":[
        "Bhalki"
    ],
    "name:swe_x_preferred":[
        "Bhalki Taluk"
    ],
    "name:vie_x_preferred":[
        "Bhalki"
    ],
    "wof:name":"Bhalki",
    "wof:placetype":"locality",
    "wof:population":0
},
  "geometry": {"coordinates":[77.68173400000001,20.472239],"type":"Point"}
}