{
  "type": "Feature",
  "properties": {
    "gn:admin1_code":"12.0",
    "gn:admin2_code":"19.0",
    "gn:asciiname":"Sanor",
    "gn:country_code":"IN",
    "gn:dem":1979,
    "gn:feature_class":"P",
    "gn:feature_code":"PPL",
    "gn:name":"Sanor",
    "gn:population":0,
    "gn:timezone":"Asia/Kolkata",
    "iso:country":"IN",
    "name:msa_x_preferred":[
        "Sanor"
    ],
    "wof:name":"Sanor",
    "wof:placetype":"locality"
},
  "geometry": {"coordinates":[75.53919,32.74593],"type":"Point"}
}