{
  "type": "Feature",
  "properties": {
    "iso:country":"IN",
    "ks:ks_name":"Lakwa Rly. Station",
    "ks:ks_pop":186,
    "ks:ks_type":"HABITATION",
    "name:eng_x_preferred":[
        "Lakwa Rly. Station"
    ],
    "wof:name":"Lakwa Rly. Station",
    "wof:placetype":"locality",
    "wof:population":186
},
  "geometry": {"coordinates":[94.84732,27.007507],"type":"Point"}
}