{
  "type": "Feature",
  "properties": {
    "gn:admin1_code":"36.0",
    "gn:admin2_code":"161",
    "gn:asciiname":"Nagla Bachhlan",
    "gn:country_code":"IN",
    "gn:dem":150,
    "gn:feature_class":"P",
    "gn:feature_code":"PPL",
    "gn:name":"Nagla Bachhlan",
    "gn:population":0,
    "gn:timezone":"Asia/Kolkata",
    "iso:country":"IN",
    "name:und_x_variant":[
        "Nagla B\u0101chhai"
    ],
    "wof:name":"Nagla Bachhlan",
    "wof:placetype":"neighbourhood"
},
  "geometry": {"coordinates":[79.22271000000001,26.85547],"type":"Point"}
}