{
  "type": "Feature",
  "properties": {
    "iso:country":"IN",
    "ks:ks_name":"Ghaneghar",
    "ks:ks_pop":182,
    "ks:ks_type":"VILLAGE",
    "name:eng_x_preferred":[
        "Ghaneghar"
    ],
    "wof:name":"Ghaneghar",
    "wof:placetype":"locality",
    "wof:population":182
},
  "geometry": {"coordinates":[72.968828,19.779257],"type":"Point"}
}