{
  "type": "Feature",
  "properties": {
    "gn:admin1_code":"35",
    "gn:admin2_code":"425.0",
    "gn:asciiname":"Mamasi",
    "gn:country_code":"IN",
    "gn:dem":286,
    "gn:feature_class":"P",
    "gn:feature_code":"PPL",
    "gn:name":"Mam\u0101si",
    "gn:population":0,
    "gn:timezone":"Asia/Kolkata",
    "iso:country":"IN",
    "wof:name":"Mamasi",
    "wof:placetype":"neighbourhood"
},
  "geometry": {"coordinates":[79.55543,24.95322],"type":"Point"}
}