{
  "type": "Feature",
  "properties": {
    "gn:admin1_code":"35.0",
    "gn:admin2_code":"446.0",
    "gn:asciiname":"Damnapur",
    "gn:country_code":"IN",
    "gn:dem":364,
    "gn:feature_class":"P",
    "gn:feature_code":"PPL",
    "gn:name":"Damn\u0101pur",
    "gn:population":0,
    "gn:timezone":"Asia/Kolkata",
    "iso:country":"IN",
    "wof:name":"Damnapur",
    "wof:placetype":"locality"
},
  "geometry": {"coordinates":[78.53591999999998,23.26483],"type":"Point"}
}