{
  "type": "Feature",
  "properties": {
    "gn:admin1_code":"24.0",
    "gn:admin2_code":"102",
    "gn:asciiname":"Sahjusar",
    "gn:country_code":"IN",
    "gn:dem":287,
    "gn:feature_class":"P",
    "gn:feature_code":"PPL",
    "gn:name":"Sahjusar",
    "gn:population":0,
    "gn:timezone":"Asia/Kolkata",
    "iso:country":"IN",
    "name:und_x_variant":[
        "S\u0101dusir"
    ],
    "wof:name":"Sahjusar",
    "wof:placetype":"locality"
},
  "geometry": {"coordinates":[74.96911,28.38054],"type":"Point"}
}