{
  "type": "Feature",
  "properties": {
    "iso:country":"IN",
    "ks:ks_alt_nam":"JUGIRAM PARA",
    "ks:ks_name":"Jugiram Para",
    "ks:ks_pop":811,
    "ks:ks_type":"HABITATION",
    "name:eng_x_preferred":[
        "Jugiram Para"
    ],
    "wof:name":"Jugiram Para",
    "wof:placetype":"locality",
    "wof:population":811
},
  "geometry": {"coordinates":[91.337025,23.642066],"type":"Point"}
}