{
  "type": "Feature",
  "properties": {
    "gn:admin1_code":"11",
    "gn:admin2_code":"34.0",
    "gn:asciiname":"Kurpo Dogri",
    "gn:country_code":"IN",
    "gn:dem":2532,
    "gn:feature_class":"P",
    "gn:feature_code":"PPL",
    "gn:name":"Kurpo Dogri",
    "gn:population":0,
    "gn:timezone":"Asia/Kolkata",
    "iso:country":"IN",
    "wof:name":"Kurpo Dogri",
    "wof:placetype":"locality"
},
  "geometry": {"coordinates":[78.36851,31.57577],"type":"Point"}
}