{
  "type": "Feature",
  "properties": {
    "iso:country":"IN",
    "ks:ks_name":"Sevalal Nagara",
    "ks:ks_pop":335,
    "ks:ks_type":"VILLAGE",
    "name:eng_x_preferred":[
        "Sevalal Nagara"
    ],
    "wof:name":"Sevalal Nagara",
    "wof:placetype":"locality",
    "wof:population":335
},
  "geometry": {"coordinates":[76.032127,13.317297],"type":"Point"}
}