{
  "type": "Feature",
  "properties": {
    "gn:admin1_code":"40",
    "gn:admin2_code":"535.0",
    "gn:asciiname":"Turkapalli",
    "gn:country_code":"IN",
    "gn:dem":489,
    "gn:feature_class":"P",
    "gn:feature_code":"PPL",
    "gn:name":"Turkapalli",
    "gn:population":0,
    "gn:timezone":"Asia/Kolkata",
    "iso:country":"IN",
    "wof:name":"Turkapalli",
    "wof:placetype":"locality"
},
  "geometry": {"coordinates":[77.76745,18.08054],"type":"Point"}
}