{
  "type": "Feature",
  "properties": {
    "iso:country":"IN",
    "ks:ks_alt_nam":"Kere hadi",
    "ks:ks_name":"Kere Hadi",
    "ks:ks_pop":140,
    "ks:ks_type":"HABITATION",
    "name:eng_x_preferred":[
        "Kere Hadi"
    ],
    "wof:name":"Kere Hadi",
    "wof:placetype":"locality",
    "wof:population":140
},
  "geometry": {"coordinates":[76.202195,12.186019],"type":"Point"}
}