{
  "type": "Feature",
  "properties": {
    "gn:admin1_code":"19.0",
    "gn:admin2_code":"582.0",
    "gn:asciiname":"Chinnakondrapalli",
    "gn:country_code":"IN",
    "gn:dem":912,
    "gn:feature_class":"P",
    "gn:feature_code":"PPL",
    "gn:name":"Chinnakondrapalli",
    "gn:population":0,
    "gn:timezone":"Asia/Kolkata",
    "iso:country":"IN",
    "wof:name":"Chinnakondrapalli",
    "wof:placetype":"locality"
},
  "geometry": {"coordinates":[78.00324999999999,13.38347],"type":"Point"}
}