{
  "type": "Feature",
  "properties": {
    "iso:country":"IN",
    "ks:ks_name":"Mindhodi Fa",
    "ks:ks_pop":737,
    "ks:ks_type":"HABITATION",
    "name:eng_x_preferred":[
        "Mindhodi Fa"
    ],
    "wof:name":"Mindhodi Fa",
    "wof:placetype":"locality",
    "wof:population":737
},
  "geometry": {"coordinates":[73.048028,20.412583],"type":"Point"}
}