{
  "type": "Feature",
  "properties": {
    "gn:admin1_code":"19.0",
    "gn:admin2_code":"573.0",
    "gn:asciiname":"Honnenahalli",
    "gn:country_code":"IN",
    "gn:dem":921,
    "gn:feature_class":"P",
    "gn:feature_code":"PPL",
    "gn:name":"Honnenahalli",
    "gn:population":0,
    "gn:timezone":"Asia/Kolkata",
    "iso:country":"IN",
    "wof:name":"Honnenahalli",
    "wof:placetype":"locality"
},
  "geometry": {"coordinates":[76.65366,12.83428],"type":"Point"}
}