{
  "type": "Feature",
  "properties": {
    "gn:admin1_code":"16",
    "gn:admin2_code":"505.0",
    "gn:asciiname":"Garla",
    "gn:country_code":"IN",
    "gn:dem":274,
    "gn:feature_class":"P",
    "gn:feature_code":"PPL",
    "gn:name":"G\u0101rla",
    "gn:population":0,
    "gn:timezone":"Asia/Kolkata",
    "iso:country":"IN",
    "name:new_x_preferred":[
        "\u0917\u093e\u0930\u094d\u0932 \u092e\u0923\u094d\u0921\u0932"
    ],
    "wof:name":"Garla",
    "wof:placetype":"locality"
},
  "geometry": {"coordinates":[79.25444,21.1176],"type":"Point"}
}