{
  "type": "Feature",
  "properties": {
    "iso:country":"IN",
    "ks:ks_name":"Moti Patel Fali",
    "ks:ks_pop":100,
    "ks:ks_type":"HABITATION",
    "name:eng_x_preferred":[
        "Moti Patel Fali"
    ],
    "wof:name":"Moti Patel Fali",
    "wof:placetype":"locality",
    "wof:population":100
},
  "geometry": {"coordinates":[72.719981,24.460252],"type":"Point"}
}