{
  "type": "Feature",
  "properties": {
    "gn:admin1_code":"36",
    "gn:admin2_code":"159.0",
    "gn:asciiname":"Pitaura",
    "gn:country_code":"IN",
    "gn:dem":160,
    "gn:feature_class":"P",
    "gn:feature_code":"PPL",
    "gn:name":"Pitaura",
    "gn:population":0,
    "gn:timezone":"Asia/Kolkata",
    "iso:country":"IN",
    "ks:ks_name":"Pitoura",
    "ks:ks_pop":3769,
    "ks:ks_type":"VILLAGE",
    "ks:ks_uagg_main":0,
    "name:eng_x_preferred":[
        "Pitoura"
    ],
    "wof:name":"Pitoura",
    "wof:placetype":"neighbourhood",
    "wof:population":3769
},
  "geometry": {"coordinates":[79.34223900000001,27.539077],"type":"Point"}
}