{
  "type": "Feature",
  "properties": {
    "gn:admin1_code":"16",
    "gn:admin2_code":"504.0",
    "gn:asciiname":"Chikhli",
    "gn:country_code":"IN",
    "gn:dem":248,
    "gn:feature_class":"P",
    "gn:feature_code":"PPL",
    "gn:name":"Chikhli",
    "gn:population":0,
    "gn:timezone":"Asia/Kolkata",
    "iso:country":"IN",
    "name:ben_x_preferred":[
        "\u099a\u09bf\u0996\u09b2\u09bf"
    ],
    "name:bpy_x_preferred":[
        "\u099a\u09bf\u0996\u09b2\u09bf"
    ],
    "name:ceb_x_preferred":[
        "Chikhli"
    ],
    "name:nld_x_preferred":[
        "Chikhli"
    ],
    "name:swe_x_preferred":[
        "Chikhli"
    ],
    "wof:name":"Chikhli",
    "wof:placetype":"locality"
},
  "geometry": {"coordinates":[78.52396999999998,20.60185],"type":"Point"}
}