{
  "type": "Feature",
  "properties": {
    "iso:country":"IN",
    "ks:ks_name":"Yanadi Colony",
    "ks:ks_pop":234,
    "ks:ks_type":"HABITATION",
    "name:eng_x_preferred":[
        "Yanadi Colony"
    ],
    "wof:name":"Yanadi Colony",
    "wof:placetype":"locality",
    "wof:population":234
},
  "geometry": {"coordinates":[79.99234199999999,13.636974],"type":"Point"}
}