{
  "type": "Feature",
  "properties": {
    "iso:country":"IN",
    "ks:ks_name":"Mettupatti",
    "ks:ks_pop":50,
    "ks:ks_type":"HABITATION",
    "ks:ks_uagg_main":0,
    "name:eng_x_preferred":[
        "Mettupatti"
    ],
    "wof:name":"Mettupatti",
    "wof:placetype":"neighbourhood",
    "wof:population":50
},
  "geometry": {"coordinates":[77.49999,9.364598],"type":"Point"}
}