{
  "type": "Feature",
  "properties": {
    "iso:country":"IN",
    "ks:ks_alt_nam":"BULAKI BIGHA",
    "ks:ks_name":"Bulaki Bigha",
    "ks:ks_pop":67,
    "ks:ks_type":"HABITATION",
    "ks:ks_uagg_main":0,
    "name:eng_x_preferred":[
        "Bulaki Bigha"
    ],
    "wof:name":"Bulaki Bigha",
    "wof:placetype":"neighbourhood",
    "wof:population":67
},
  "geometry": {"coordinates":[84.499661,25.104561],"type":"Point"}
}