{
  "type": "Feature",
  "properties": {
    "iso:country":"IN",
    "ks:ks_name":"Giriatola",
    "ks:ks_pop":357,
    "ks:ks_type":"HABITATION",
    "name:eng_x_preferred":[
        "Giriatola"
    ],
    "wof:name":"Giriatola",
    "wof:placetype":"locality",
    "wof:population":357
},
  "geometry": {"coordinates":[84.883421,22.404734],"type":"Point"}
}