{
  "type": "Feature",
  "properties": {
    "iso:country":"IN",
    "ks:ks_name":"Chandlagi",
    "ks:ks_pop":211,
    "ks:ks_type":"VILLAGE",
    "name:eng_x_preferred":[
        "Chandlagi"
    ],
    "wof:name":"Chandlagi",
    "wof:placetype":"locality",
    "wof:population":211
},
  "geometry": {"coordinates":[84.537944,23.571279],"type":"Point"}
}