{
  "type": "Feature",
  "properties": {
    "iso:country":"IN",
    "ks:ks_name":"Nimpur",
    "ks:ks_pop":1698,
    "ks:ks_type":"VILLAGE",
    "ks:ks_uagg_main":0,
    "name:eng_x_preferred":[
        "Nimpur"
    ],
    "wof:name":"Nimpur",
    "wof:placetype":"neighbourhood",
    "wof:population":1698
},
  "geometry": {"coordinates":[87.31368000000001,21.81421],"type":"Point"}
}