{
  "type": "Feature",
  "properties": {
    "iso:country":"IN",
    "ks:ks_name":"Mahisha Dani",
    "ks:ks_pop":0,
    "ks:ks_type":"VILLAGE",
    "name:eng_x_preferred":[
        "Mahisha Dani"
    ],
    "wof:name":"Mahisha Dani",
    "wof:placetype":"locality",
    "wof:population":0
},
  "geometry": {"coordinates":[87.542497,22.596374],"type":"Point"}
}