{
  "type": "Feature",
  "properties": {
    "iso:country":"IN",
    "ks:ks_name":"Bajhan",
    "ks:ks_pop":805,
    "ks:ks_type":"HABITATION",
    "name:eng_x_preferred":[
        "Bajhan"
    ],
    "wof:name":"Bajhan",
    "wof:placetype":"locality",
    "wof:population":805
},
  "geometry": {"coordinates":[84.172522,25.796908],"type":"Point"}
}