{
  "type": "Feature",
  "properties": {
    "iso:country":"IN",
    "ks:ks_name":"Bilagallu",
    "ks:ks_pop":96,
    "ks:ks_type":"HABITATION",
    "name:eng_x_preferred":[
        "Bilagallu"
    ],
    "wof:name":"Bilagallu",
    "wof:placetype":"locality",
    "wof:population":96
},
  "geometry": {"coordinates":[75.01791799999999,14.089104],"type":"Point"}
}