{
  "type": "Feature",
  "properties": {
    "gn:admin1_code":"19.0",
    "gn:admin2_code":"574.0",
    "gn:asciiname":"Jinnathapura",
    "gn:country_code":"IN",
    "gn:dem":876,
    "gn:feature_class":"P",
    "gn:feature_code":"PPL",
    "gn:name":"Jinn\u0101thapura",
    "gn:population":0,
    "gn:timezone":"Asia/Kolkata",
    "iso:country":"IN",
    "wof:name":"Jinnathapura",
    "wof:placetype":"locality"
},
  "geometry": {"coordinates":[76.48975,12.86558],"type":"Point"}
}