{
  "type": "Feature",
  "properties": {
    "iso:country":"IN",
    "ks:ks_name":"Said Pur Namales",
    "ks:ks_pop":7,
    "ks:ks_type":"HABITATION",
    "name:eng_x_preferred":[
        "Said Pur Namales"
    ],
    "wof:name":"Said Pur Namales",
    "wof:placetype":"locality",
    "wof:population":7
},
  "geometry": {"coordinates":[82.70328499999999,25.81119],"type":"Point"}
}