{
  "type": "Feature",
  "properties": {
    "gn:admin1_code":"35.0",
    "gn:admin2_code":"464.0",
    "gn:asciiname":"Kelkua",
    "gn:country_code":"IN",
    "gn:dem":288,
    "gn:feature_class":"P",
    "gn:feature_code":"PPL",
    "gn:name":"Kelkua",
    "gn:population":0,
    "gn:timezone":"Asia/Kolkata",
    "iso:country":"IN",
    "ks:ks_name":"Kelkua",
    "ks:ks_type":"VILLAGE",
    "name:eng_x_preferred":[
        "Kelkua"
    ],
    "wof:name":"Kelkua",
    "wof:placetype":"locality"
},
  "geometry": {"coordinates":[74.41447700000001,22.984607],"type":"Point"}
}