{
  "type": "Feature",
  "properties": {
    "gn:admin1_code":"11.0",
    "gn:admin2_code":"34.0",
    "gn:asciiname":"Dute",
    "gn:country_code":"IN",
    "gn:dem":2594,
    "gn:feature_class":"P",
    "gn:feature_code":"PPL",
    "gn:name":"Dute",
    "gn:population":0,
    "gn:timezone":"Asia/Kolkata",
    "iso:country":"IN",
    "wof:name":"Dute",
    "wof:placetype":"locality"
},
  "geometry": {"coordinates":[78.05414,31.56913],"type":"Point"}
}