{
  "type": "Feature",
  "properties": {
    "gn:admin1_code":"36.0",
    "gn:admin2_code":"182.0",
    "gn:asciiname":"Pura Thakur Kurmi",
    "gn:country_code":"IN",
    "gn:dem":102,
    "gn:feature_class":"P",
    "gn:feature_code":"PPL",
    "gn:name":"Pura Th\u0101kur Kurmi",
    "gn:population":0,
    "gn:timezone":"Asia/Kolkata",
    "iso:country":"IN",
    "wof:name":"Pura Thakur Kurmi",
    "wof:placetype":"locality"
},
  "geometry": {"coordinates":[82.29103000000001,27.1955],"type":"Point"}
}