{
  "type": "Feature",
  "properties": {
    "iso:country":"IN",
    "ks:ks_name":"Biranjoy Para",
    "ks:ks_pop":109,
    "ks:ks_type":"HABITATION",
    "name:eng_x_preferred":[
        "Biranjoy Para"
    ],
    "wof:name":"Biranjoy Para",
    "wof:placetype":"locality",
    "wof:population":109
},
  "geometry": {"coordinates":[91.894391,23.859301],"type":"Point"}
}