{
  "type": "Feature",
  "properties": {
    "iso:country":"IN",
    "ks:ks_name":"Malhipur",
    "ks:ks_pop":0,
    "ks:ks_type":"VILLAGE",
    "name:eng_x_preferred":[
        "Malhipur"
    ],
    "wof:name":"Malhipur",
    "wof:placetype":"locality",
    "wof:population":0
},
  "geometry": {"coordinates":[79.896631,26.72112],"type":"Point"}
}