{
  "type": "Feature",
  "properties": {
    "gn:admin1_code":"9.0",
    "gn:admin2_code":"481",
    "gn:asciiname":"Chuna",
    "gn:country_code":"IN",
    "gn:dem":65,
    "gn:feature_class":"P",
    "gn:feature_code":"PPL",
    "gn:name":"Chuna",
    "gn:population":0,
    "gn:timezone":"Asia/Kolkata",
    "iso:country":"IN",
    "name:ara_x_preferred":[
        "\u062a\u0634\u0648\u0646\u0627"
    ],
    "name:ben_x_preferred":[
        "\u099a\u09c1\u09a8\u09be"
    ],
    "name:ell_x_preferred":[
        "\u03a4\u03c3\u03bf\u03cd\u03bd\u03b1"
    ],
    "name:fas_x_preferred":[
        "\u0686\u0648\u0646\u0627"
    ],
    "name:heb_x_preferred":[
        "\u05e6'\u05d5\u05e0\u05d4"
    ],
    "name:hin_x_preferred":[
        "\u091a\u0941\u0928\u093e"
    ],
    "name:ind_x_preferred":[
        "Chuna"
    ],
    "name:kor_x_preferred":[
        "\ucd94\ub098"
    ],
    "name:por_x_preferred":[
        "Chuna"
    ],
    "name:tur_x_preferred":[
        "Chuna"
    ],
    "name:urd_x_preferred":[
        "\u0686\u0648\u0646\u0627"
    ],
    "name:vie_x_preferred":[
        "S\u00f4ng Chuna"
    ],
    "wof:name":"Chuna",
    "wof:placetype":"locality"
},
  "geometry": {"coordinates":[71.76485,21.2053],"type":"Point"}
}