{
  "type": "Feature",
  "properties": {
    "gn:admin1_code":"34.0",
    "gn:admin2_code":"208.0",
    "gn:asciiname":"Khurd",
    "gn:country_code":"IN",
    "gn:dem":58,
    "gn:feature_class":"P",
    "gn:feature_code":"PPL",
    "gn:name":"Khurd",
    "gn:population":0,
    "gn:timezone":"Asia/Kolkata",
    "iso:country":"IN",
    "wof:name":"Khurd",
    "wof:placetype":"neighbourhood"
},
  "geometry": {"coordinates":[86.97931,26.10791],"type":"Point"}
}