{
  "type": "Feature",
  "properties": {
    "iso:country":"IN",
    "ks:ks_alt_nam":"boudhawadi",
    "ks:ks_name":"Boudhawadi",
    "ks:ks_pop":208,
    "ks:ks_type":"HABITATION",
    "name:eng_x_preferred":[
        "Boudhawadi"
    ],
    "wof:name":"Boudhawadi",
    "wof:placetype":"locality",
    "wof:population":208
},
  "geometry": {"coordinates":[73.46767199999999,17.427556],"type":"Point"}
}