{
  "type": "Feature",
  "properties": {
    "iso:country":"IN",
    "ks:ks_name":"Bujadpada",
    "ks:ks_pop":95,
    "ks:ks_type":"HABITATION",
    "name:eng_x_preferred":[
        "Bujadpada"
    ],
    "wof:name":"Bujadpada",
    "wof:placetype":"locality",
    "wof:population":95
},
  "geometry": {"coordinates":[73.124588,19.592882],"type":"Point"}
}