{
  "type": "Feature",
  "properties": {
    "gn:admin1_code":"12.0",
    "gn:admin2_code":"019",
    "gn:asciiname":"Chakhar",
    "gn:country_code":"IN",
    "gn:dem":797,
    "gn:feature_class":"P",
    "gn:feature_code":"PPL",
    "gn:name":"Chakhar",
    "gn:population":0,
    "gn:timezone":"Asia/Kolkata",
    "iso:country":"IN",
    "wof:name":"Chakhar",
    "wof:placetype":"locality"
},
  "geometry": {"coordinates":[74.99319,32.94349],"type":"Point"}
}