{
  "type": "Feature",
  "properties": {
    "iso:country":"IN",
    "ks:ks_name":"Bhramanabeduru",
    "ks:ks_pop":216,
    "ks:ks_type":"HABITATION",
    "name:eng_x_preferred":[
        "Bhramanabeduru"
    ],
    "wof:name":"Bhramanabeduru",
    "wof:placetype":"locality",
    "wof:population":216
},
  "geometry": {"coordinates":[75.009829,14.13188],"type":"Point"}
}