{
  "type": "Feature",
  "properties": {
    "iso:country":"IN",
    "ks:ks_name":"Valasai",
    "ks:ks_pop":314,
    "ks:ks_type":"HABITATION",
    "name:eng_x_preferred":[
        "Valasai"
    ],
    "wof:name":"Valasai",
    "wof:placetype":"locality",
    "wof:population":314
},
  "geometry": {"coordinates":[78.259388,10.296377],"type":"Point"}
}