{
  "type": "Feature",
  "properties": {
    "gn:admin1_code":"19.0",
    "gn:admin2_code":"565.0",
    "gn:asciiname":"Basapur",
    "gn:country_code":"IN",
    "gn:dem":467,
    "gn:feature_class":"P",
    "gn:feature_code":"PPL",
    "gn:name":"Bas\u0101p\u016br",
    "gn:population":0,
    "gn:timezone":"Asia/Kolkata",
    "iso:country":"IN",
    "ks:ks_name":"Basapura",
    "ks:ks_pop":676,
    "ks:ks_type":"HABITATION",
    "name:eng_x_preferred":[
        "Basapura"
    ],
    "name:eng_x_variant":[
        "Basapur"
    ],
    "name:vie_x_preferred":[
        "Basapur"
    ],
    "wof:name":"Basapura",
    "wof:placetype":"locality",
    "wof:population":676
},
  "geometry": {"coordinates":[76.82341099999999,15.208704],"type":"Point"}
}