{
  "type": "Feature",
  "properties": {
    "iso:country":"IN",
    "ks:ks_name":"Manda",
    "ks:ks_pop":65,
    "ks:ks_type":"VILLAGE",
    "name:eng_x_preferred":[
        "Manda"
    ],
    "wof:name":"Manda",
    "wof:placetype":"locality",
    "wof:population":65
},
  "geometry": {"coordinates":[78.56187,30.135313],"type":"Point"}
}