{
  "type": "Feature",
  "properties": {
    "gn:admin1_code":"34.0",
    "gn:admin2_code":"218",
    "gn:asciiname":"Duraundha",
    "gn:country_code":"IN",
    "gn:dem":62,
    "gn:feature_class":"P",
    "gn:feature_code":"PPL",
    "gn:name":"Duraundha",
    "gn:population":0,
    "gn:timezone":"Asia/Kolkata",
    "iso:country":"IN",
    "wof:name":"Duraundha",
    "wof:placetype":"locality"
},
  "geometry": {"coordinates":[84.45603,26.08641],"type":"Point"}
}