{
  "type": "Feature",
  "properties": {
    "gn:admin1_code":"12.0",
    "gn:admin2_code":"008",
    "gn:asciiname":"Kasdal",
    "gn:country_code":"IN",
    "gn:dem":3195,
    "gn:feature_class":"P",
    "gn:feature_code":"PPL",
    "gn:name":"Kasdal",
    "gn:population":0,
    "gn:timezone":"Asia/Kolkata",
    "iso:country":"IN",
    "wof:name":"Kasdal",
    "wof:placetype":"locality"
},
  "geometry": {"coordinates":[74.41798,33.97738],"type":"Point"}
}