{
  "type": "Feature",
  "properties": {
    "gn:admin1_code":"25.0",
    "gn:admin2_code":"602.0",
    "gn:asciiname":"Lakshmipuram",
    "gn:country_code":"IN",
    "gn:dem":85,
    "gn:feature_class":"P",
    "gn:feature_code":"PPL",
    "gn:name":"Lakshmipuram",
    "gn:population":0,
    "gn:timezone":"Asia/Kolkata",
    "iso:country":"IN",
    "wof:name":"Lakshmipuram",
    "wof:placetype":"locality"
},
  "geometry": {"coordinates":[79.63769000000001,13.25585],"type":"Point"}
}