{
  "type": "Feature",
  "properties": {
    "iso:country":"IN",
    "ks:ks_name":"Bhoiwadi",
    "ks:ks_pop":47,
    "ks:ks_type":"HABITATION",
    "name:eng_x_preferred":[
        "Bhoiwadi"
    ],
    "wof:name":"Bhoiwadi",
    "wof:placetype":"locality",
    "wof:population":47
},
  "geometry": {"coordinates":[73.354972,17.574539],"type":"Point"}
}