{
  "type": "Feature",
  "properties": {
    "gn:admin1_code":"12.0",
    "gn:asciiname":"Gumla",
    "gn:country_code":"IN",
    "gn:dem":2504,
    "gn:feature_class":"P",
    "gn:feature_code":"PPL",
    "gn:name":"Gumla",
    "gn:population":0,
    "gn:timezone":"Asia/Kolkata",
    "iso:country":"IN",
    "name:ara_x_preferred":[
        "\u062c\u0648\u0645\u0627\u0644\u0627"
    ],
    "name:ben_bn_x_preferred":[
        "\u0997\u09be\u09ae\u09b2\u09be"
    ],
    "name:ben_in_x_preferred":[
        "\u0997\u09be\u09ae\u09b2\u09be"
    ],
    "name:bih_x_preferred":[
        "\u0917\u0941\u092e\u0932\u093e"
    ],
    "name:bpy_x_preferred":[
        "\u0997\u09c1\u09ae\u09b2\u09be"
    ],
    "name:ceb_x_preferred":[
        "Gumla"
    ],
    "name:fas_x_preferred":[
        "\u06af\u0648\u0645\u0644\u0627"
    ],
    "name:fra_x_preferred":[
        "Gumla"
    ],
    "name:guj_x_preferred":[
        "\u0a97\u0ac1\u0aae\u0ab2\u0abe"
    ],
    "name:hin_x_preferred":[
        "\u0917\u0941\u092e\u0932\u093e"
    ],
    "name:ita_x_preferred":[
        "Gumla"
    ],
    "name:kan_x_preferred":[
        "\u0c97\u0cc1\u0cae\u0ccd\u0cb2\u0cbe"
    ],
    "name:mal_x_preferred":[
        "\u0d17\u0d41\u0d02\u0d32"
    ],
    "name:mar_x_preferred":[
        "\u0917\u0941\u092e\u0932\u093e"
    ],
    "name:mlg_x_preferred":[
        "Gumla"
    ],
    "name:msa_x_preferred":[
        "Gumla"
    ],
    "name:new_x_preferred":[
        "\u0917\u0941\u0932\u094d\u092e\u093e"
    ],
    "name:pam_x_preferred":[
        "Gumla"
    ],
    "name:pan_x_preferred":[
        "\u0a17\u0a41\u0a2e\u0a32\u0a3e"
    ],
    "name:rus_x_preferred":[
        "\u0413\u0443\u043c\u043b\u0430"
    ],
    "name:san_x_preferred":[
        "\u0917\u0941\u092e\u0932\u093e"
    ],
    "name:spa_x_preferred":[
        "Gumla"
    ],
    "name:swe_x_preferred":[
        "Gumla"
    ],
    "name:tam_x_preferred":[
        "\u0b95\u0bc1\u0bae\u0bcd\u0bb2\u0bbe"
    ],
    "name:tel_x_preferred":[
        "\u0c17\u0c41\u0c2e\u0c4d\u0c32\u0c3e"
    ],
    "name:urd_x_preferred":[
        "\u06af\u0645\u0644\u0627"
    ],
    "name:urd_x_variant":[
        "\u06af\u0648\u0645\u0644\u0627"
    ],
    "name:vie_x_preferred":[
        "Gumla"
    ],
    "name:zho_x_preferred":[
        "\u53e4\u59c6\u62c9"
    ],
    "wof:name":"Gumla",
    "wof:placetype":"locality"
},
  "geometry": {"coordinates":[73.99913000000002,34.6187],"type":"Point"}
}