{
  "type": "Feature",
  "properties": {
    "gn:admin1_code":"12.0",
    "gn:asciiname":"Gumla",
    "gn:country_code":"IN",
    "gn:dem":2504,
    "gn:feature_class":"P",
    "gn:feature_code":"PPL",
    "gn:name":"Gumla",
    "gn:population":0,
    "gn:timezone":"Asia/Kolkata",
    "iso:country":"IN",
    "name:bih_x_preferred":[
        "\u0917\u0941\u092e\u0932\u093e"
    ],
    "name:bpy_x_preferred":[
        "\u0997\u09c1\u09ae\u09b2\u09be"
    ],
    "name:ceb_x_preferred":[
        "Gumla"
    ],
    "name:fas_x_preferred":[
        "\u06af\u0648\u0645\u0644\u0627"
    ],
    "name:fra_x_preferred":[
        "Gumla"
    ],
    "name:hin_x_preferred":[
        "\u0917\u0941\u092e\u0932\u093e"
    ],
    "name:ita_x_preferred":[
        "Gumla"
    ],
    "name:mar_x_preferred":[
        "\u0917\u0941\u092e\u0932\u093e"
    ],
    "name:mlg_x_preferred":[
        "Gumla"
    ],
    "name:msa_x_preferred":[
        "Gumla"
    ],
    "name:new_x_preferred":[
        "\u0917\u0941\u0932\u094d\u092e\u093e"
    ],
    "name:pam_x_preferred":[
        "Gumla"
    ],
    "name:rus_x_preferred":[
        "\u0413\u0443\u043c\u043b\u0430"
    ],
    "name:san_x_preferred":[
        "\u0917\u0941\u092e\u0932\u093e"
    ],
    "name:spa_x_preferred":[
        "Gumla"
    ],
    "name:swe_x_preferred":[
        "Gumla"
    ],
    "name:urd_x_preferred":[
        "\u06af\u0648\u0645\u0644\u0627"
    ],
    "name:vie_x_preferred":[
        "Gumla"
    ],
    "name:zho_x_preferred":[
        "\u53e4\u59c6\u62c9"
    ],
    "wof:name":"Gumla",
    "wof:placetype":"locality"
},
  "geometry": {"coordinates":[73.99913000000002,34.6187],"type":"Point"}
}