{
  "type": "Feature",
  "properties": {
    "gn:admin1_code":"12.0",
    "gn:asciiname":"Gumla",
    "gn:country_code":"IN",
    "gn:dem":2504,
    "gn:feature_class":"P",
    "gn:feature_code":"PPL",
    "gn:name":"Gumla",
    "gn:population":0,
    "gn:timezone":"Asia/Kolkata",
    "iso:country":"IN",
    "wof:name":"Gumla",
    "wof:placetype":"locality"
},
  "geometry": {"coordinates":[73.99913000000002,34.6187],"type":"Point"}
}