{
  "type": "Feature",
  "properties": {
    "iso:country":"IN",
    "ks:ks_name":"Maroowara",
    "ks:ks_pop":2277,
    "ks:ks_type":"HABITATION",
    "name:eng_x_preferred":[
        "Maroowara"
    ],
    "wof:name":"Maroowara",
    "wof:placetype":"locality",
    "wof:population":2277
},
  "geometry": {"coordinates":[72.12542000000001,24.701508],"type":"Point"}
}