{
  "type": "Feature",
  "properties": {
    "gn:admin1_code":"12",
    "gn:asciiname":"Silikott",
    "gn:country_code":"IN",
    "gn:dem":1598,
    "gn:feature_class":"P",
    "gn:feature_code":"PPL",
    "gn:name":"Silikott",
    "gn:population":0,
    "gn:timezone":"Asia/Kolkata",
    "iso:country":"IN",
    "wof:name":"Silikott",
    "wof:placetype":"locality"
},
  "geometry": {"coordinates":[74.07822,34.03797],"type":"Point"}
}