{
  "type": "Feature",
  "properties": {
    "iso:country":"IN",
    "ks:ks_name":"Korampally",
    "ks:ks_pop":1,
    "ks:ks_type":"HABITATION",
    "name:eng_x_preferred":[
        "Korampally"
    ],
    "wof:name":"Korampally",
    "wof:placetype":"locality",
    "wof:population":1
},
  "geometry": {"coordinates":[78.072868,17.991138],"type":"Point"}
}