{
  "type": "Feature",
  "properties": {
    "iso:country":"IN",
    "ks:ks_name":"Luta",
    "ks:ks_pop":171,
    "ks:ks_type":"VILLAGE",
    "name:eng_x_preferred":[
        "Luta"
    ],
    "wof:name":"Luta",
    "wof:placetype":"locality",
    "wof:population":171
},
  "geometry": {"coordinates":[84.886836,24.381726],"type":"Point"}
}