{
  "type": "Feature",
  "properties": {
    "iso:country":"IN",
    "ks:ks_name":"Ambdiha",
    "ks:ks_pop":2119,
    "ks:ks_type":"VILLAGE",
    "name:eng_x_preferred":[
        "Ambdiha"
    ],
    "wof:name":"Ambdiha",
    "wof:placetype":"locality",
    "wof:population":2119
},
  "geometry": {"coordinates":[85.707309,22.26126],"type":"Point"}
}