{
  "type": "Feature",
  "properties": {
    "iso:country":"IN",
    "ks:ks_name":"Boripada",
    "ks:ks_pop":92,
    "ks:ks_type":"HABITATION",
    "name:eng_x_preferred":[
        "Boripada"
    ],
    "wof:name":"Boripada",
    "wof:placetype":"locality",
    "wof:population":92
},
  "geometry": {"coordinates":[73.07633300000001,20.176833],"type":"Point"}
}