{
  "type": "Feature",
  "properties": {
    "gn:admin1_code":"35",
    "gn:admin2_code":"458.0",
    "gn:asciiname":"Banbirkheri",
    "gn:country_code":"IN",
    "gn:dem":515,
    "gn:feature_class":"P",
    "gn:feature_code":"PPL",
    "gn:name":"Banbirkheri",
    "gn:population":0,
    "gn:timezone":"Asia/Kolkata",
    "iso:country":"IN",
    "wof:name":"Banbirkheri",
    "wof:placetype":"neighbourhood"
},
  "geometry": {"coordinates":[77.36493,24.42657],"type":"Point"}
}