{
  "type": "Feature",
  "properties": {
    "iso:country":"IN",
    "ks:ks_name":"Rengachamuthrapatti",
    "ks:ks_pop":162,
    "ks:ks_type":"HABITATION",
    "ks:ks_uagg_main":0,
    "name:eng_x_preferred":[
        "Rengachamuthrapatti"
    ],
    "wof:name":"Rengachamuthrapatti",
    "wof:placetype":"neighbourhood",
    "wof:population":162
},
  "geometry": {"coordinates":[78.025881,10.319834],"type":"Point"}
}