{
  "type": "Feature",
  "properties": {
    "gn:country":"IN",
    "gn:fcode":"PPLX",
    "gn:population":0,
    "iso:country":"IN",
    "name:eng_x_preferred":[
        "Girgaon"
    ],
    "name:fra_x_preferred":[
        "Girgaon"
    ],
    "name:jpn_x_preferred":[
        "\u30ae\u30eb\u30ac\u30aa\u30f3"
    ],
    "name:kan_x_preferred":[
        "\u0c97\u0cbf\u0cb0\u0ccd \u0c97\u0cbe\u0c82\u0cb5\u0ccd"
    ],
    "name:mar_x_preferred":[
        "\u0917\u093f\u0930\u0917\u093e\u0935"
    ],
    "name:nld_x_preferred":[
        "Girgaon"
    ],
    "name:rus_x_preferred":[
        "\u0413\u0438\u0433\u0440\u0430\u043e\u043d"
    ],
    "name:und_x_variant":[
        "Bombay Girgaon"
    ],
    "name:vie_x_preferred":[
        "Girgaon"
    ],
    "qs:name":"Girgaum",
    "qs:name_adm0":"India",
    "qs:name_adm1":"Maharashtra",
    "qs:photos":117,
    "qs:photos_1k":24,
    "qs:photos_9k":1,
    "qs:photos_9r":3,
    "qs:photos_all":117,
    "qs:photos_sr":3,
    "qs:placetype":"Suburb",
    "qs:pop_sr":"0",
    "wd:wordcount":747,
    "wof:name":"Girgaum",
    "wof:placetype":"neighbourhood",
    "wof:population":0
},
  "geometry": {"coordinates":[72.81667,18.95],"type":"Point"}
}