{
  "type": "Feature",
  "properties": {
    "iso:country":"IN",
    "ks:ks_name":"Vadakala Thottam",
    "ks:ks_pop":352,
    "ks:ks_type":"HABITATION",
    "ks:ks_uagg_main":0,
    "name:eng_x_preferred":[
        "Vadakala Thottam"
    ],
    "wof:name":"Vadakala Thottam",
    "wof:placetype":"neighbourhood",
    "wof:population":352
},
  "geometry": {"coordinates":[77.699315,11.607824],"type":"Point"}
}