{
  "type": "Feature",
  "properties": {
    "iso:country":"IN",
    "ks:ks_name":"Bandakindapalli",
    "ks:ks_pop":67,
    "ks:ks_type":"HABITATION",
    "name:eng_x_preferred":[
        "Bandakindapalli"
    ],
    "wof:name":"Bandakindapalli",
    "wof:placetype":"locality",
    "wof:population":67
},
  "geometry": {"coordinates":[78.061851,13.993542],"type":"Point"}
}