{
  "type": "Feature",
  "properties": {
    "iso:country":"IN",
    "ks:ks_alt_nam":"Jogeshw\u0101ri",
    "ks:ks_name":"Jogeshwari",
    "ks:ks_pop":1318,
    "ks:ks_type":"VILLAGE",
    "ks:ks_uagg_main":0,
    "name:eng_x_preferred":[
        "Jogeshwari"
    ],
    "name:eng_x_variant":[
        "Jogeshw\u0101ri"
    ],
    "wof:name":"Jogeshwari",
    "wof:placetype":"neighbourhood",
    "wof:population":1318
},
  "geometry": {"coordinates":[75.20509300000001,19.826438],"type":"Point"}
}