{
  "type": "Feature",
  "properties": {
    "iso:country":"IN",
    "ks:ks_name":"Baharadaraba",
    "ks:ks_pop":59,
    "ks:ks_type":"VILLAGE",
    "name:eng_x_preferred":[
        "Baharadaraba"
    ],
    "wof:name":"Baharadaraba",
    "wof:placetype":"locality",
    "wof:population":59
},
  "geometry": {"coordinates":[83.28323,19.388952],"type":"Point"}
}