{
  "type": "Feature",
  "properties": {
    "iso:country":"IN",
    "ks:ks_name":"Taluadanga",
    "ks:ks_pop":700,
    "ks:ks_type":"HABITATION",
    "name:eng_x_preferred":[
        "Taluadanga"
    ],
    "wof:name":"Taluadanga",
    "wof:placetype":"locality",
    "wof:population":700
},
  "geometry": {"coordinates":[87.893552,24.389148],"type":"Point"}
}