{
  "type": "Feature",
  "properties": {
    "iso:country":"IN",
    "ks:ks_name":"Balashettimoole",
    "ks:ks_pop":508,
    "ks:ks_type":"HABITATION",
    "name:eng_x_preferred":[
        "Balashettimoole"
    ],
    "wof:name":"Balashettimoole",
    "wof:placetype":"locality",
    "wof:population":508
},
  "geometry": {"coordinates":[75.059943,12.714958],"type":"Point"}
}