{
  "type": "Feature",
  "properties": {
    "gn:admin1_code":"40",
    "gn:admin2_code":"537.0",
    "gn:asciiname":"Patlur",
    "gn:country_code":"IN",
    "gn:dem":610,
    "gn:feature_class":"P",
    "gn:feature_code":"PPL",
    "gn:name":"Patl\u016br",
    "gn:population":0,
    "gn:timezone":"Asia/Kolkata",
    "iso:country":"IN",
    "name:und_x_variant":[
        "Patl\u016br"
    ],
    "wof:name":"Patlur",
    "wof:placetype":"locality"
},
  "geometry": {"coordinates":[77.79303,17.58542000000001],"type":"Point"}
}