{
  "type": "Feature",
  "properties": {
    "iso:country":"IN",
    "ks:ks_name":"Shahwazpur Goojar Ahatmali",
    "ks:ks_pop":722,
    "ks:ks_type":"VILLAGE",
    "ks:ks_uagg_main":0,
    "name:eng_x_preferred":[
        "Shahwazpur Goojar Ahatmali"
    ],
    "wof:name":"Shahwazpur Goojar Ahatmali",
    "wof:placetype":"neighbourhood",
    "wof:population":722
},
  "geometry": {"coordinates":[78.22551900000001,28.602012],"type":"Point"}
}