{
  "type": "Feature",
  "properties": {
    "iso:country":"IN",
    "ks:ks_name":"Brahmapur",
    "ks:ks_pop":58,
    "ks:ks_type":"VILLAGE",
    "name:eng_x_preferred":[
        "Brahmapur"
    ],
    "wof:name":"Brahmapur",
    "wof:placetype":"locality",
    "wof:population":58
},
  "geometry": {"coordinates":[86.272003,20.276079],"type":"Point"}
}