{
  "type": "Feature",
  "properties": {
    "iso:country":"IN",
    "ks:ks_name":"Chikari Faliya",
    "ks:ks_pop":100,
    "ks:ks_type":"HABITATION",
    "name:eng_x_preferred":[
        "Chikari Faliya"
    ],
    "wof:name":"Chikari Faliya",
    "wof:placetype":"locality",
    "wof:population":100
},
  "geometry": {"coordinates":[73.299947,20.528798],"type":"Point"}
}