{
  "type": "Feature",
  "properties": {
    "iso:country":"IN",
    "ks:ks_name":"Kasari Chouhan",
    "ks:ks_pop":1455,
    "ks:ks_type":"HABITATION",
    "name:eng_x_preferred":[
        "Kasari Chouhan"
    ],
    "wof:name":"Kasari Chouhan",
    "wof:placetype":"locality",
    "wof:population":1455
},
  "geometry": {"coordinates":[75.493234,23.572304],"type":"Point"}
}