{
  "type": "Feature",
  "properties": {
    "iso:country":"IN",
    "ks:ks_alt_nam":"ANDAKUDI",
    "ks:ks_name":"Andakudi",
    "ks:ks_pop":160,
    "ks:ks_type":"HABITATION",
    "name:eng_x_preferred":[
        "Andakudi"
    ],
    "wof:name":"Andakudi",
    "wof:placetype":"locality",
    "wof:population":160
},
  "geometry": {"coordinates":[78.889934,10.033817],"type":"Point"}
}