{
  "type": "Feature",
  "properties": {
    "iso:country":"IN",
    "ks:ks_name":"Damodarpur",
    "ks:ks_pop":621,
    "ks:ks_type":"VILLAGE",
    "name:eng_x_preferred":[
        "Damodarpur"
    ],
    "wof:name":"Damodarpur",
    "wof:placetype":"locality",
    "wof:population":621
},
  "geometry": {"coordinates":[89.40457600000001,26.325989],"type":"Point"}
}