{
  "type": "Feature",
  "properties": {
    "iso:country":"IN",
    "ks:ks_alt_nam":"thadikkadavu",
    "ks:ks_name":"Thadikkadavu",
    "ks:ks_pop":1539,
    "ks:ks_type":"HABITATION",
    "name:eng_x_preferred":[
        "Thadikkadavu"
    ],
    "wof:name":"Thadikkadavu",
    "wof:placetype":"locality",
    "wof:population":1539
},
  "geometry": {"coordinates":[75.439178,12.141254],"type":"Point"}
}