{
  "type": "Feature",
  "properties": {
    "gn:admin1_code":"2.0",
    "gn:admin2_code":"554.0",
    "gn:asciiname":"Peddakondapalli",
    "gn:country_code":"IN",
    "gn:dem":303,
    "gn:feature_class":"P",
    "gn:feature_code":"PPL",
    "gn:name":"Peddakondapalli",
    "gn:population":0,
    "gn:timezone":"Asia/Kolkata",
    "iso:country":"IN",
    "wof:name":"Peddakondapalli",
    "wof:placetype":"locality"
},
  "geometry": {"coordinates":[79.19239,13.27099],"type":"Point"}
}