{
  "type": "Feature",
  "properties": {
    "gn:admin1_code":"12.0",
    "gn:admin2_code":"008",
    "gn:asciiname":"Chinkipur",
    "gn:country_code":"IN",
    "gn:dem":1584,
    "gn:feature_class":"P",
    "gn:feature_code":"PPL",
    "gn:name":"Chinkipur",
    "gn:population":0,
    "gn:timezone":"Asia/Kolkata",
    "iso:country":"IN",
    "wof:name":"Chinkipur",
    "wof:placetype":"neighbourhood"
},
  "geometry": {"coordinates":[74.4789,34.29027],"type":"Point"}
}