{
  "type": "Feature",
  "properties": {
    "iso:country":"IN",
    "ks:ks_name":"Bohawa",
    "ks:ks_pop":71,
    "ks:ks_type":"VILLAGE",
    "name:eng_x_preferred":[
        "Bohawa"
    ],
    "wof:name":"Bohawa",
    "wof:placetype":"locality",
    "wof:population":71
},
  "geometry": {"coordinates":[76.856465,30.29053],"type":"Point"}
}