{
  "type": "Feature",
  "properties": {
    "iso:country":"IN",
    "ks:ks_alt_nam":"Sedapatti.M",
    "ks:ks_name":"Sedapatti.m",
    "ks:ks_pop":126,
    "ks:ks_type":"HABITATION",
    "name:eng_x_preferred":[
        "Sedapatti.m"
    ],
    "wof:name":"Sedapatti.m",
    "wof:placetype":"locality",
    "wof:population":126
},
  "geometry": {"coordinates":[77.66606,9.829599],"type":"Point"}
}