{
  "type": "Feature",
  "properties": {
    "iso:country":"IN",
    "ks:ks_name":"Kenduguda1",
    "ks:ks_pop":494,
    "ks:ks_type":"HABITATION",
    "name:eng_x_preferred":[
        "Kenduguda1"
    ],
    "wof:name":"Kenduguda1",
    "wof:placetype":"locality",
    "wof:population":494
},
  "geometry": {"coordinates":[81.97343100000001,18.359361],"type":"Point"}
}