{
  "type": "Feature",
  "properties": {
    "iso:country":"IN",
    "ks:ks_name":"Mudral",
    "ks:ks_pop":100,
    "ks:ks_type":"HABITATION",
    "name:eng_x_preferred":[
        "Mudral"
    ],
    "wof:name":"Mudral",
    "wof:placetype":"locality",
    "wof:population":100
},
  "geometry": {"coordinates":[75.07414,13.210613],"type":"Point"}
}