{
  "type": "Feature",
  "properties": {
    "iso:country":"IN",
    "ks:ks_alt_nam":"kalsan tiyin tola",
    "ks:ks_name":"Kalsan Tiyin Tola",
    "ks:ks_pop":856,
    "ks:ks_type":"HABITATION",
    "ks:ks_uagg_main":0,
    "name:eng_x_preferred":[
        "Kalsan Tiyin Tola"
    ],
    "wof:name":"Kalsan Tiyin Tola",
    "wof:placetype":"neighbourhood",
    "wof:population":856
},
  "geometry": {"coordinates":[87.029607,25.576727],"type":"Point"}
}