{
  "type": "Feature",
  "properties": {
    "iso:country":"IN",
    "ks:ks_name":"Barachatkam",
    "ks:ks_pop":329,
    "ks:ks_type":"VILLAGE",
    "name:eng_x_preferred":[
        "Barachatkam"
    ],
    "wof:name":"Barachatkam",
    "wof:placetype":"locality",
    "wof:population":329
},
  "geometry": {"coordinates":[87.48796299999999,24.762321],"type":"Point"}
}