{
  "type": "Feature",
  "properties": {
    "gn:admin1_code":"36",
    "gn:admin2_code":"170.0",
    "gn:asciiname":"Mahanda",
    "gn:country_code":"IN",
    "gn:dem":117,
    "gn:feature_class":"P",
    "gn:feature_code":"PPL",
    "gn:name":"Mahanda",
    "gn:population":0,
    "gn:timezone":"Asia/Kolkata",
    "iso:country":"IN",
    "wof:name":"Mahanda",
    "wof:placetype":"locality"
},
  "geometry": {"coordinates":[80.30263000000002,25.78741],"type":"Point"}
}