{
  "type": "Feature",
  "properties": {
    "iso:country":"IN",
    "ks:ks_name":"Shushunia Parasibana",
    "ks:ks_pop":217,
    "ks:ks_type":"VILLAGE",
    "name:eng_x_preferred":[
        "Shushunia Parasibana"
    ],
    "wof:name":"Shushunia Parasibana",
    "wof:placetype":"locality",
    "wof:population":217
},
  "geometry": {"coordinates":[86.976867,23.383711],"type":"Point"}
}