{
  "type": "Feature",
  "properties": {
    "iso:country":"IN",
    "ks:ks_name":"Ghotulpara",
    "ks:ks_pop":49,
    "ks:ks_type":"HABITATION",
    "name:eng_x_preferred":[
        "Ghotulpara"
    ],
    "wof:name":"Ghotulpara",
    "wof:placetype":"locality",
    "wof:population":49
},
  "geometry": {"coordinates":[81.312814,19.578143],"type":"Point"}
}