{
  "type": "Feature",
  "properties": {
    "iso:country":"IN",
    "ks:ks_name":"Malauna",
    "ks:ks_pop":176,
    "ks:ks_type":"HABITATION",
    "name:eng_x_preferred":[
        "Malauna"
    ],
    "wof:name":"Malauna",
    "wof:placetype":"locality",
    "wof:population":176
},
  "geometry": {"coordinates":[81.64710100000001,27.168129],"type":"Point"}
}