{
  "type": "Feature",
  "properties": {
    "iso:country":"IN",
    "ks:ks_name":"Telipukur",
    "ks:ks_pop":605,
    "ks:ks_type":"HABITATION",
    "name:eng_x_preferred":[
        "Telipukur"
    ],
    "wof:name":"Telipukur",
    "wof:placetype":"locality",
    "wof:population":605
},
  "geometry": {"coordinates":[88.217399,25.519444],"type":"Point"}
}