{
  "type": "Feature",
  "properties": {
    "gn:admin1_code":"36.0",
    "gn:admin2_code":"173.0",
    "gn:asciiname":"Maghi",
    "gn:country_code":"IN",
    "gn:dem":108,
    "gn:feature_class":"P",
    "gn:feature_code":"PPL",
    "gn:name":"M\u0101ghi",
    "gn:population":0,
    "gn:timezone":"Asia/Kolkata",
    "iso:country":"IN",
    "name:kan_x_preferred":[
        "\u0cae\u0cbe\u0c98\u0cbf"
    ],
    "name:mal_x_preferred":[
        "\u0d2e\u0d3e\u0d18\u0d3f"
    ],
    "name:nno_x_preferred":[
        "Maghi"
    ],
    "name:pan_x_preferred":[
        "\u0a2e\u0a3e\u0a18\u0a40"
    ],
    "name:pnb_x_preferred":[
        "\u0645\u0627\u06af\u06be\u06cc"
    ],
    "name:tam_x_preferred":[
        "\u0bae\u0b95\u0bbf"
    ],
    "name:tel_x_preferred":[
        "\u0c2e\u0c3e\u0c18\u0c40"
    ],
    "name:urd_x_preferred":[
        "\u0645\u06af\u06be\u06cc"
    ],
    "wof:name":"Maghi",
    "wof:placetype":"neighbourhood"
},
  "geometry": {"coordinates":[81.62233999999999,25.73955],"type":"Point"}
}