{
  "type": "Feature",
  "properties": {
    "gn:admin1_code":"12.0",
    "gn:admin2_code":"011",
    "gn:asciiname":"Mungshungan",
    "gn:country_code":"IN",
    "gn:dem":3337,
    "gn:feature_class":"P",
    "gn:feature_code":"PPL",
    "gn:name":"Mungshungan",
    "gn:population":0,
    "gn:timezone":"Asia/Kolkata",
    "iso:country":"IN",
    "wof:name":"Mungshungan",
    "wof:placetype":"locality"
},
  "geometry": {"coordinates":[74.95902,34.41317],"type":"Point"}
}