{
  "type": "Feature",
  "properties": {
    "iso:country":"IN",
    "ks:ks_name":"Brahmanpara",
    "ks:ks_pop":270,
    "ks:ks_type":"HABITATION",
    "name:eng_x_preferred":[
        "Brahmanpara"
    ],
    "wof:name":"Brahmanpara",
    "wof:placetype":"locality",
    "wof:population":270
},
  "geometry": {"coordinates":[81.53852999999999,19.389358],"type":"Point"}
}