{
  "type": "Feature",
  "properties": {
    "iso:country":"IN",
    "ks:ks_name":"Ramnagar Sankalpa",
    "ks:ks_pop":442,
    "ks:ks_type":"VILLAGE",
    "ks:ks_uagg_main":0,
    "name:eng_x_preferred":[
        "Ramnagar Sankalpa"
    ],
    "wof:name":"Ramnagar Sankalpa",
    "wof:placetype":"neighbourhood",
    "wof:population":442
},
  "geometry": {"coordinates":[80.832645,28.363095],"type":"Point"}
}