{
  "type": "Feature",
  "properties": {
    "iso:country":"IN",
    "ks:ks_name":"Gattinayakanapura",
    "ks:ks_pop":20,
    "ks:ks_type":"HABITATION",
    "name:eng_x_preferred":[
        "Gattinayakanapura"
    ],
    "wof:name":"Gattinayakanapura",
    "wof:placetype":"locality",
    "wof:population":20
},
  "geometry": {"coordinates":[76.66689100000001,13.185679],"type":"Point"}
}