{
  "type": "Feature",
  "properties": {
    "gn:admin1_code":"16",
    "gn:admin2_code":"511.0",
    "gn:asciiname":"Bodri",
    "gn:country_code":"IN",
    "gn:dem":356,
    "gn:feature_class":"P",
    "gn:feature_code":"PPL",
    "gn:name":"Bodri",
    "gn:population":0,
    "gn:timezone":"Asia/Kolkata",
    "iso:country":"IN",
    "name:ben_x_preferred":[
        "\u09ac\u09cb\u09a6\u09b0\u09bf"
    ],
    "name:bpy_x_preferred":[
        "\u09ac\u09cb\u09a6\u09b0\u09bf"
    ],
    "name:ceb_x_preferred":[
        "Bodri"
    ],
    "name:ita_x_preferred":[
        "Bodri"
    ],
    "name:msa_x_preferred":[
        "Bodri"
    ],
    "name:new_x_preferred":[
        "\u092c\u094b\u0926\u094d\u0930\u0940"
    ],
    "name:nld_x_preferred":[
        "Bodri"
    ],
    "name:por_x_preferred":[
        "Bodri"
    ],
    "name:swe_x_preferred":[
        "Bodri"
    ],
    "name:urd_x_preferred":[
        "\u0628\u0648\u0688\u0631\u06cc"
    ],
    "name:vie_x_preferred":[
        "Bodri"
    ],
    "name:zho_x_preferred":[
        "\u535a\u5fb7\u91cc"
    ],
    "wof:name":"Bodri",
    "wof:placetype":"locality"
},
  "geometry": {"coordinates":[78.19306,19.4972],"type":"Point"}
}