{
  "type": "Feature",
  "properties": {
    "iso:country":"IN",
    "ks:ks_name":"Majhigawan",
    "ks:ks_pop":57,
    "ks:ks_type":"VILLAGE",
    "name:eng_x_preferred":[
        "Majhigawan"
    ],
    "wof:name":"Majhigawan",
    "wof:placetype":"locality",
    "wof:population":57
},
  "geometry": {"coordinates":[81.730799,24.857138],"type":"Point"}
}