{
  "type": "Feature",
  "properties": {
    "gn:admin1_code":"28.0",
    "gn:admin2_code":"333.0",
    "gn:asciiname":"Amtala",
    "gn:country_code":"IN",
    "gn:dem":27,
    "gn:feature_class":"P",
    "gn:feature_code":"PPL",
    "gn:name":"\u0100mtala",
    "gn:population":0,
    "gn:timezone":"Asia/Kolkata",
    "iso:country":"IN",
    "wof:name":"Amtala",
    "wof:placetype":"locality"
},
  "geometry": {"coordinates":[87.90156,24.72514],"type":"Point"}
}