{
  "type": "Feature",
  "properties": {
    "iso:country":"IN",
    "ks:ks_name":"Bangolawa",
    "ks:ks_pop":181,
    "ks:ks_type":"HABITATION",
    "name:eng_x_preferred":[
        "Bangolawa"
    ],
    "wof:name":"Bangolawa",
    "wof:placetype":"locality",
    "wof:population":181
},
  "geometry": {"coordinates":[83.046083,27.203851],"type":"Point"}
}