{
  "type": "Feature",
  "properties": {
    "gn:admin1_code":"35",
    "gn:admin2_code":"459.0",
    "gn:asciiname":"Kakrua Tumen",
    "gn:country_code":"IN",
    "gn:dem":498,
    "gn:feature_class":"P",
    "gn:feature_code":"PPL",
    "gn:name":"Kakr\u016ba Tumen",
    "gn:population":0,
    "gn:timezone":"Asia/Kolkata",
    "iso:country":"IN",
    "wof:name":"Kakrua Tumen",
    "wof:placetype":"locality"
},
  "geometry": {"coordinates":[77.65583000000002,24.48657],"type":"Point"}
}