{
  "type": "Feature",
  "properties": {
    "gn:admin1_code":"36",
    "gn:admin2_code":"148.0",
    "gn:asciiname":"Rudainian",
    "gn:country_code":"IN",
    "gn:dem":158,
    "gn:feature_class":"P",
    "gn:feature_code":"PPL",
    "gn:name":"Rudaini\u0101n",
    "gn:population":0,
    "gn:timezone":"Asia/Kolkata",
    "iso:country":"IN",
    "ks:ks_name":"Rudaunia",
    "ks:ks_pop":31,
    "ks:ks_type":"VILLAGE",
    "name:eng_x_preferred":[
        "Rudaunia"
    ],
    "name:eng_x_variant":[
        "Rudainian"
    ],
    "wof:name":"Rudaunia",
    "wof:placetype":"locality",
    "wof:population":31
},
  "geometry": {"coordinates":[79.111662,27.34679],"type":"Point"}
}