{
  "type": "Feature",
  "properties": {
    "gn:admin1_code":"25.0",
    "gn:admin2_code":"606.0",
    "gn:asciiname":"Birudur",
    "gn:country_code":"IN",
    "gn:dem":70,
    "gn:feature_class":"P",
    "gn:feature_code":"PPL",
    "gn:name":"Birud\u016br",
    "gn:population":0,
    "gn:timezone":"Asia/Kolkata",
    "iso:country":"IN",
    "ks:ks_alt_nam":"Birud\u016br",
    "ks:ks_name":"Birudur",
    "ks:ks_pop":734,
    "ks:ks_type":"VILLAGE",
    "ks:ks_uagg_main":0,
    "name:eng_x_preferred":[
        "Birudur"
    ],
    "name:eng_x_variant":[
        "Birud\u016br"
    ],
    "name:tam_x_preferred":[
        "\u0baa\u0bbf\u0bb0\u0bc1\u0ba4\u0bc2\u0bb0\u0bcd"
    ],
    "wof:name":"Birudur",
    "wof:placetype":"neighbourhood",
    "wof:population":734
},
  "geometry": {"coordinates":[79.632102,12.502643],"type":"Point"}
}