{
  "type": "Feature",
  "properties": {
    "iso:country":"IN",
    "ks:ks_name":"Pauli Purwa",
    "ks:ks_pop":65,
    "ks:ks_type":"HABITATION",
    "ks:ks_uagg_main":0,
    "name:eng_x_preferred":[
        "Pauli Purwa"
    ],
    "wof:name":"Pauli Purwa",
    "wof:placetype":"neighbourhood",
    "wof:population":65
},
  "geometry": {"coordinates":[81.53727499999999,27.62544],"type":"Point"}
}