{
  "type": "Feature",
  "properties": {
    "iso:country":"IN",
    "ks:ks_name":"Chandpur",
    "ks:ks_pop":500,
    "ks:ks_type":"VILLAGE",
    "ks:ks_uagg_main":0,
    "name:eng_x_preferred":[
        "Chandpur"
    ],
    "wof:name":"Chandpur",
    "wof:placetype":"neighbourhood",
    "wof:population":500
},
  "geometry": {"coordinates":[79.356381,28.25801],"type":"Point"}
}