{
  "type": "Feature",
  "properties": {
    "iso:country":"IN",
    "ks:ks_name":"Nana Baria",
    "ks:ks_pop":564,
    "ks:ks_type":"HABITATION",
    "name:eng_x_preferred":[
        "Nana Baria"
    ],
    "wof:name":"Nana Baria",
    "wof:placetype":"locality",
    "wof:population":564
},
  "geometry": {"coordinates":[74.17827800000001,22.6995],"type":"Point"}
}