{
  "type": "Feature",
  "properties": {
    "iso:country":"IN",
    "ks:ks_name":"Pottakulam",
    "ks:ks_pop":270,
    "ks:ks_type":"HABITATION",
    "name:eng_x_preferred":[
        "Pottakulam"
    ],
    "wof:name":"Pottakulam",
    "wof:placetype":"locality",
    "wof:population":270
},
  "geometry": {"coordinates":[78.440501,9.471323],"type":"Point"}
}