{
  "type": "Feature",
  "properties": {
    "iso:country":"IN",
    "ks:ks_name":"Dewadand",
    "ks:ks_pop":852,
    "ks:ks_type":"VILLAGE",
    "name:eng_x_preferred":[
        "Dewadand"
    ],
    "wof:name":"Dewadand",
    "wof:placetype":"locality",
    "wof:population":852
},
  "geometry": {"coordinates":[83.840963,24.590391],"type":"Point"}
}