{
  "type": "Feature",
  "properties": {
    "gn:admin1_code":"2",
    "gn:admin2_code":"545.0",
    "gn:asciiname":"Kapalabanda",
    "gn:country_code":"IN",
    "gn:dem":288,
    "gn:feature_class":"P",
    "gn:feature_code":"PPL",
    "gn:name":"Kapalabanda",
    "gn:population":0,
    "gn:timezone":"Asia/Kolkata",
    "iso:country":"IN",
    "ks:ks_name":"Kappalabanda",
    "ks:ks_pop":19,
    "ks:ks_type":"HABITATION",
    "name:eng_x_preferred":[
        "Kappalabanda"
    ],
    "name:eng_x_variant":[
        "Kapalabanda"
    ],
    "wof:name":"Kappalabanda",
    "wof:placetype":"locality",
    "wof:population":19
},
  "geometry": {"coordinates":[82.00386,17.661934],"type":"Point"}
}