{
  "type": "Feature",
  "properties": {
    "gn:admin1_code":"24",
    "gn:admin2_code":"118.0",
    "gn:asciiname":"Nadol",
    "gn:country_code":"IN",
    "gn:dem":322,
    "gn:feature_class":"P",
    "gn:feature_code":"PPL",
    "gn:name":"N\u0101dol",
    "gn:population":0,
    "gn:timezone":"Asia/Kolkata",
    "iso:country":"IN",
    "name:cat_x_preferred":[
        "Nadol"
    ],
    "name:ceb_x_preferred":[
        "N\u0101dol"
    ],
    "name:hin_x_preferred":[
        "\u0928\u093e\u0921\u094b\u0932"
    ],
    "name:swe_x_preferred":[
        "N\u0101dol"
    ],
    "wof:name":"Nadol",
    "wof:placetype":"locality"
},
  "geometry": {"coordinates":[73.45617,25.36836],"type":"Point"}
}