{
  "type": "Feature",
  "properties": {
    "iso:country":"IN",
    "ks:ks_name":"Tupdang",
    "ks:ks_pop":178,
    "ks:ks_type":"VILLAGE",
    "name:eng_x_preferred":[
        "Tupdang"
    ],
    "wof:name":"Tupdang",
    "wof:placetype":"locality",
    "wof:population":178
},
  "geometry": {"coordinates":[85.435525,22.830688],"type":"Point"}
}