{
  "type": "Feature",
  "properties": {
    "gn:admin1_code":"19.0",
    "gn:admin2_code":"570.0",
    "gn:asciiname":"Hosahalli",
    "gn:country_code":"IN",
    "gn:dem":782,
    "gn:feature_class":"P",
    "gn:feature_code":"PPL",
    "gn:name":"Hosahalli",
    "gn:population":0,
    "gn:timezone":"Asia/Kolkata",
    "iso:country":"IN",
    "name:kan_x_preferred":[
        "\u0cb9\u0cca\u0cb8 \u0cb9\u0cb3\u0ccd\u0cb3\u0cbf"
    ],
    "wof:name":"Hosahalli",
    "wof:placetype":"locality"
},
  "geometry": {"coordinates":[76.00053,13.5514],"type":"Point"}
}