{
  "type": "Feature",
  "properties": {
    "gn:admin1_code":"36",
    "gn:admin2_code":"189.0",
    "gn:asciiname":"Rohua Satbharia",
    "gn:country_code":"IN",
    "gn:dem":89,
    "gn:feature_class":"P",
    "gn:feature_code":"PPL",
    "gn:name":"Rohua Satbharia",
    "gn:population":0,
    "gn:timezone":"Asia/Kolkata",
    "iso:country":"IN",
    "ks:ks_name":"Rohuwasat Bharia",
    "ks:ks_pop":1532,
    "ks:ks_type":"VILLAGE",
    "name:eng_x_preferred":[
        "Rohuwasat Bharia"
    ],
    "name:eng_x_variant":[
        "Rohua Satbharia"
    ],
    "wof:name":"Rohuwasat Bharia",
    "wof:placetype":"locality",
    "wof:population":1532
},
  "geometry": {"coordinates":[83.71627599999999,26.822283],"type":"Point"}
}