{
  "type": "Feature",
  "properties": {
    "iso:country":"IN",
    "ks:ks_name":"Kalyanpur Bharauti",
    "ks:ks_pop":250,
    "ks:ks_type":"HABITATION",
    "name:eng_x_preferred":[
        "Kalyanpur Bharauti"
    ],
    "wof:name":"Kalyanpur Bharauti",
    "wof:placetype":"locality",
    "wof:population":250
},
  "geometry": {"coordinates":[82.55957100000001,26.30798],"type":"Point"}
}