{
  "type": "Feature",
  "properties": {
    "iso:country":"IN",
    "ks:ks_name":"Kaparaganahalli",
    "ks:ks_pop":181,
    "ks:ks_type":"HABITATION",
    "name:eng_x_preferred":[
        "Kaparaganahalli"
    ],
    "wof:name":"Kaparaganahalli",
    "wof:placetype":"locality",
    "wof:population":181
},
  "geometry": {"coordinates":[77.352628,13.508467],"type":"Point"}
}