{
  "type": "Feature",
  "properties": {
    "iso:country":"IN",
    "ks:ks_name":"Narikkalkaradu",
    "ks:ks_pop":448,
    "ks:ks_type":"HABITATION",
    "ks:ks_uagg_main":0,
    "name:eng_x_preferred":[
        "Narikkalkaradu"
    ],
    "wof:name":"Narikkalkaradu",
    "wof:placetype":"neighbourhood",
    "wof:population":448
},
  "geometry": {"coordinates":[78.094955,11.506706],"type":"Point"}
}