{
  "type": "Feature",
  "properties": {
    "iso:country":"IN",
    "ks:ks_name":"Jaspur",
    "ks:ks_pop":76,
    "ks:ks_type":"VILLAGE",
    "name:eng_x_preferred":[
        "Jaspur"
    ],
    "wof:name":"Jaspur",
    "wof:placetype":"locality",
    "wof:population":76
},
  "geometry": {"coordinates":[79.216358,30.181972],"type":"Point"}
}