{
  "type": "Feature",
  "properties": {
    "iso:country":"IN",
    "ks:ks_name":"Ghurwakhera",
    "ks:ks_pop":1691,
    "ks:ks_type":"VILLAGE",
    "name:eng_x_preferred":[
        "Ghurwakhera"
    ],
    "wof:name":"Ghurwakhera",
    "wof:placetype":"neighbourhood",
    "wof:population":1691
},
  "geometry": {"coordinates":[80.362506,26.365017],"type":"Point"}
}