{
  "type": "Feature",
  "properties": {
    "gn:admin1_code":"25.0",
    "gn:admin2_code":"610",
    "gn:asciiname":"Dimbam",
    "gn:country_code":"IN",
    "gn:dem":1090,
    "gn:feature_class":"P",
    "gn:feature_code":"PPL",
    "gn:name":"Dimbam",
    "gn:population":0,
    "gn:timezone":"Asia/Kolkata",
    "iso:country":"IN",
    "wof:name":"Dimbam",
    "wof:placetype":"locality"
},
  "geometry": {"coordinates":[77.12931999999998,11.62224],"type":"Point"}
}