{
  "type": "Feature",
  "properties": {
    "iso:country":"IN",
    "ks:ks_name":"Chulhiyaland",
    "ks:ks_pop":471,
    "ks:ks_type":"HABITATION",
    "name:eng_x_preferred":[
        "Chulhiyaland"
    ],
    "wof:name":"Chulhiyaland",
    "wof:placetype":"locality",
    "wof:population":471
},
  "geometry": {"coordinates":[86.830827,24.905662],"type":"Point"}
}