{
  "type": "Feature",
  "properties": {
    "gn:admin1_code":"35",
    "gn:admin2_code":"454.0",
    "gn:asciiname":"Ruru",
    "gn:country_code":"IN",
    "gn:dem":695,
    "gn:feature_class":"P",
    "gn:feature_code":"PPL",
    "gn:name":"R\u016bru",
    "gn:population":0,
    "gn:timezone":"Asia/Kolkata",
    "iso:country":"IN",
    "name:ceb_x_preferred":[
        "Ruru"
    ],
    "name:new_x_preferred":[
        "\u0930\u0941\u0930\u0941"
    ],
    "name:swe_x_preferred":[
        "Ruru"
    ],
    "wof:name":"Ruru",
    "wof:placetype":"locality"
},
  "geometry": {"coordinates":[81.02365,22.29454],"type":"Point"}
}