{
  "type": "Feature",
  "properties": {
    "iso:country":"IN",
    "ks:ks_name":"Salakania",
    "ks:ks_pop":526,
    "ks:ks_type":"VILLAGE",
    "name:eng_x_preferred":[
        "Salakania"
    ],
    "wof:name":"Salakania",
    "wof:placetype":"locality",
    "wof:population":526
},
  "geometry": {"coordinates":[86.287302,21.085416],"type":"Point"}
}