{
  "type": "Feature",
  "properties": {
    "iso:country":"IN",
    "ks:ks_name":"Prem Purwa",
    "ks:ks_pop":123,
    "ks:ks_type":"HABITATION",
    "ks:ks_uagg_main":0,
    "name:eng_x_preferred":[
        "Prem Purwa"
    ],
    "wof:name":"Prem Purwa",
    "wof:placetype":"neighbourhood",
    "wof:population":123
},
  "geometry": {"coordinates":[81.72182599999999,27.264154],"type":"Point"}
}