{
  "type": "Feature",
  "properties": {
    "iso:country":"IN",
    "ks:ks_alt_nam":"Sh\u0101h\u0101b\u0101d",
    "ks:ks_name":"Shahabad",
    "ks:ks_type":"VILLAGE",
    "ks:ks_uagg_main":0,
    "name:eng_x_preferred":[
        "Shahabad"
    ],
    "name:eng_x_variant":[
        "Sh\u0101h\u0101b\u0101d"
    ],
    "wof:name":"Shahabad",
    "wof:placetype":"neighbourhood"
},
  "geometry": {"coordinates":[77.398573,28.652166],"type":"Point"}
}