{
  "type": "Feature",
  "properties": {
    "iso:country":"IN",
    "ks:ks_name":"Bitling Para",
    "ks:ks_pop":299,
    "ks:ks_type":"HABITATION",
    "name:eng_x_preferred":[
        "Bitling Para"
    ],
    "wof:name":"Bitling Para",
    "wof:placetype":"locality",
    "wof:population":299
},
  "geometry": {"coordinates":[81.818839,20.408099],"type":"Point"}
}