{
  "type": "Feature",
  "properties": {
    "iso:country":"IN",
    "ks:ks_name":"Pachhagaon",
    "ks:ks_pop":269,
    "ks:ks_type":"HABITATION",
    "name:eng_x_preferred":[
        "Pachhagaon"
    ],
    "wof:name":"Pachhagaon",
    "wof:placetype":"locality",
    "wof:population":269
},
  "geometry": {"coordinates":[86.888851,21.404766],"type":"Point"}
}