{
  "type": "Feature",
  "properties": {
    "iso:country":"IN",
    "ks:ks_alt_nam":"Pah\u0101r Gond\u0101",
    "ks:ks_name":"Pahar Gonda",
    "ks:ks_pop":0,
    "ks:ks_type":"VILLAGE",
    "ks:ks_uagg_main":0,
    "name:eng_x_preferred":[
        "Pahar Gonda"
    ],
    "name:eng_x_variant":[
        "Pah\u0101r Gond\u0101"
    ],
    "wof:name":"Pahar Gonda",
    "wof:placetype":"neighbourhood",
    "wof:population":0
},
  "geometry": {"coordinates":[85.31743400000001,23.401721],"type":"Point"}
}