{
  "type": "Feature",
  "properties": {
    "iso:country":"IN",
    "ks:ks_name":"Bhetuli",
    "ks:ks_pop":660,
    "ks:ks_type":"HABITATION",
    "name:eng_x_preferred":[
        "Bhetuli"
    ],
    "wof:name":"Bhetuli",
    "wof:placetype":"locality",
    "wof:population":660
},
  "geometry": {"coordinates":[79.623386,29.775166],"type":"Point"}
}