{
  "type": "Feature",
  "properties": {
    "gn:admin1_code":"2.0",
    "gn:admin2_code":"553.0",
    "gn:asciiname":"Chinnaramannagaripalle",
    "gn:country_code":"IN",
    "gn:dem":606,
    "gn:feature_class":"P",
    "gn:feature_code":"PPL",
    "gn:name":"Chinnar\u0101mannag\u0101ripalle",
    "gn:population":0,
    "gn:timezone":"Asia/Kolkata",
    "iso:country":"IN",
    "wof:name":"Chinnaramannagaripalle",
    "wof:placetype":"locality"
},
  "geometry": {"coordinates":[78.14816,13.93265],"type":"Point"}
}