{
  "type": "Feature",
  "properties": {
    "iso:country":"IN",
    "ks:ks_name":"Owabari",
    "ks:ks_pop":195,
    "ks:ks_type":"HABITATION",
    "name:eng_x_preferred":[
        "Owabari"
    ],
    "wof:name":"Owabari",
    "wof:placetype":"locality",
    "wof:population":195
},
  "geometry": {"coordinates":[93.917929,26.143272],"type":"Point"}
}