{
  "type": "Feature",
  "properties": {
    "iso:country":"IN",
    "ks:ks_name":"Charipada",
    "ks:ks_pop":522,
    "ks:ks_type":"HABITATION",
    "name:eng_x_preferred":[
        "Charipada"
    ],
    "wof:name":"Charipada",
    "wof:placetype":"locality",
    "wof:population":522
},
  "geometry": {"coordinates":[72.967401,19.88161],"type":"Point"}
}