{
  "type": "Feature",
  "properties": {
    "iso:country":"IN",
    "ks:ks_name":"Hema",
    "ks:ks_pop":153,
    "ks:ks_type":"HABITATION",
    "name:eng_x_preferred":[
        "Hema"
    ],
    "wof:name":"Hema",
    "wof:placetype":"locality",
    "wof:population":153
},
  "geometry": {"coordinates":[70.517011,27.271061],"type":"Point"}
}