{
  "type": "Feature",
  "properties": {
    "iso:country":"IN",
    "ks:ks_name":"Kherjan Forest Village",
    "ks:ks_pop":600,
    "ks:ks_type":"HABITATION",
    "name:eng_x_preferred":[
        "Kherjan Forest Village"
    ],
    "wof:name":"Kherjan Forest Village",
    "wof:placetype":"locality",
    "wof:population":600
},
  "geometry": {"coordinates":[95.689905,27.58098],"type":"Point"}
}