{
  "type": "Feature",
  "properties": {
    "gn:admin1_code":"38.0",
    "gn:admin2_code":"352.0",
    "gn:asciiname":"Parerkola",
    "gn:country_code":"IN",
    "gn:dem":58,
    "gn:feature_class":"P",
    "gn:feature_code":"PPL",
    "gn:name":"P\u0101rerkola",
    "gn:population":0,
    "gn:timezone":"Asia/Kolkata",
    "iso:country":"IN",
    "ks:ks_alt_nam":"P\u0101rerkola",
    "ks:ks_name":"Parerkola",
    "ks:ks_pop":98,
    "ks:ks_type":"VILLAGE",
    "name:eng_x_preferred":[
        "Parerkola"
    ],
    "name:eng_x_variant":[
        "P\u0101rerkola"
    ],
    "wof:name":"Parerkola",
    "wof:placetype":"locality",
    "wof:population":98
},
  "geometry": {"coordinates":[87.711949,25.074328],"type":"Point"}
}