{
  "type": "Feature",
  "properties": {
    "gn:admin1_code":"19.0",
    "gn:admin2_code":"563.0",
    "gn:asciiname":"Sidimane",
    "gn:country_code":"IN",
    "gn:dem":554,
    "gn:feature_class":"P",
    "gn:feature_code":"PPL",
    "gn:name":"S\u012bdimane",
    "gn:population":0,
    "gn:timezone":"Asia/Kolkata",
    "iso:country":"IN",
    "ks:ks_name":"Shedimane",
    "ks:ks_pop":50,
    "ks:ks_type":"HABITATION",
    "name:eng_x_preferred":[
        "Shedimane"
    ],
    "name:eng_x_variant":[
        "Sidimane"
    ],
    "wof:name":"Shedimane",
    "wof:placetype":"locality",
    "wof:population":50
},
  "geometry": {"coordinates":[74.488748,14.807933],"type":"Point"}
}