{
  "type": "Feature",
  "properties": {
    "gn:admin1_code":"34.0",
    "gn:admin2_code":"222.0",
    "gn:asciiname":"Buchauli",
    "gn:country_code":"IN",
    "gn:dem":47,
    "gn:feature_class":"P",
    "gn:feature_code":"PPL",
    "gn:name":"Buchauli",
    "gn:population":0,
    "gn:timezone":"Asia/Kolkata",
    "iso:country":"IN",
    "ks:ks_name":"Buchauli",
    "ks:ks_type":"VILLAGE",
    "name:eng_x_preferred":[
        "Buchauli"
    ],
    "wof:name":"Buchauli",
    "wof:placetype":"locality"
},
  "geometry": {"coordinates":[86.0424,25.578185],"type":"Point"}
}