{
  "type": "Feature",
  "properties": {
    "iso:country":"IN",
    "ks:ks_name":"Lasunguda",
    "ks:ks_pop":226,
    "ks:ks_type":"HABITATION",
    "name:eng_x_preferred":[
        "Lasunguda"
    ],
    "wof:name":"Lasunguda",
    "wof:placetype":"locality",
    "wof:population":226
},
  "geometry": {"coordinates":[82.743909,18.450607],"type":"Point"}
}