{
  "type": "Feature",
  "properties": {
    "iso:country":"IN",
    "ks:ks_alt_nam":"MLA Valavu",
    "ks:ks_name":"Mla Valavu",
    "ks:ks_pop":450,
    "ks:ks_type":"HABITATION",
    "name:eng_x_preferred":[
        "Mla Valavu"
    ],
    "wof:name":"Mla Valavu",
    "wof:placetype":"locality",
    "wof:population":450
},
  "geometry": {"coordinates":[76.068697,10.475334],"type":"Point"}
}