{
  "type": "Feature",
  "properties": {
    "iso:country":"IN",
    "ks:ks_alt_nam":"MOHITEWASTI",
    "ks:ks_name":"Mohitewasti",
    "ks:ks_pop":104,
    "ks:ks_type":"HABITATION",
    "name:eng_x_preferred":[
        "Mohitewasti"
    ],
    "wof:name":"Mohitewasti",
    "wof:placetype":"locality",
    "wof:population":104
},
  "geometry": {"coordinates":[74.943759,17.054859],"type":"Point"}
}