{
  "type": "Feature",
  "properties": {
    "gn:admin1_code":"3.0",
    "gn:admin2_code":"316",
    "gn:asciiname":"Dhalai",
    "gn:country_code":"IN",
    "gn:dem":35,
    "gn:feature_class":"P",
    "gn:feature_code":"PPL",
    "gn:name":"Dhalai",
    "gn:population":0,
    "gn:timezone":"Asia/Kolkata",
    "iso:country":"IN",
    "name:ara_x_preferred":[
        "\u062f\u0647\u0627\u0644\u064a"
    ],
    "name:ben_bn_x_preferred":[
        "\u09a7\u09b2\u09be\u0987"
    ],
    "name:ben_in_x_preferred":[
        "\u09a7\u09b2\u09be\u0987"
    ],
    "name:ben_x_preferred":[
        "\u09a7\u09b2\u09be\u0987"
    ],
    "name:guj_x_preferred":[
        "\u0aa7\u0ab2\u0abe\u0a88"
    ],
    "name:hin_x_preferred":[
        "\u0927\u0932\u093e\u0908"
    ],
    "name:kan_x_preferred":[
        "\u0ca7\u0cbe\u0cb2\u0cc8"
    ],
    "name:mal_x_preferred":[
        "\u0d27\u0d32\u0d48"
    ],
    "name:mar_x_preferred":[
        "\u0927\u0932\u093e\u0908"
    ],
    "name:pan_x_preferred":[
        "\u0a22\u0a32\u0a3e\u0a08"
    ],
    "name:tam_x_preferred":[
        "\u0ba4\u0bb2\u0bbe\u0baf\u0bcd"
    ],
    "name:tel_x_preferred":[
        "\u0c27\u0c32\u0c3e\u0c2f\u0c4d"
    ],
    "name:urd_x_preferred":[
        "\u0688\u06be\u0644\u0627\u0626\u06cc"
    ],
    "wof:name":"Dhalai",
    "wof:placetype":"neighbourhood"
},
  "geometry": {"coordinates":[92.84784999999999,24.60117],"type":"Point"}
}