{
  "type": "Feature",
  "properties": {
    "iso:country":"IN",
    "ks:ks_name":"Nilaram",
    "ks:ks_pop":79,
    "ks:ks_type":"HABITATION",
    "name:eng_x_preferred":[
        "Nilaram"
    ],
    "wof:name":"Nilaram",
    "wof:placetype":"locality",
    "wof:population":79
},
  "geometry": {"coordinates":[82.217434,18.212563],"type":"Point"}
}