{
  "type": "Feature",
  "properties": {
    "gn:admin1_code":"25.0",
    "gn:admin2_code":"602.0",
    "gn:asciiname":"Nayar",
    "gn:country_code":"IN",
    "gn:dem":16,
    "gn:feature_class":"P",
    "gn:feature_code":"PPL",
    "gn:name":"N\u0101yar",
    "gn:population":0,
    "gn:timezone":"Asia/Kolkata",
    "iso:country":"IN",
    "name:deu_x_preferred":[
        "Nayar"
    ],
    "name:spa_x_preferred":[
        "Nayar"
    ],
    "wof:name":"Nayar",
    "wof:placetype":"locality"
},
  "geometry": {"coordinates":[80.21939999999999,13.26256],"type":"Point"}
}