{
  "type": "Feature",
  "properties": {
    "gn:admin1_code":"39.0",
    "gn:admin2_code":"63.0",
    "gn:asciiname":"Bamtana",
    "gn:country_code":"IN",
    "gn:dem":1314,
    "gn:feature_class":"P",
    "gn:feature_code":"PPL",
    "gn:name":"Bamt\u0101na",
    "gn:population":0,
    "gn:timezone":"Asia/Kolkata",
    "iso:country":"IN",
    "ks:ks_name":"Bamtana",
    "ks:ks_pop":65,
    "ks:ks_type":"VILLAGE",
    "name:eng_x_preferred":[
        "Bamtana"
    ],
    "wof:name":"Bamtana",
    "wof:placetype":"locality",
    "wof:population":65
},
  "geometry": {"coordinates":[79.73496900000001,29.818189],"type":"Point"}
}