{
  "type": "Feature",
  "properties": {
    "iso:country":"IN",
    "ks:ks_name":"Bagalwasti",
    "ks:ks_pop":180,
    "ks:ks_type":"HABITATION",
    "name:eng_x_preferred":[
        "Bagalwasti"
    ],
    "wof:name":"Bagalwasti",
    "wof:placetype":"locality",
    "wof:population":180
},
  "geometry": {"coordinates":[74.625232,18.492173],"type":"Point"}
}