{
  "type": "Feature",
  "properties": {
    "iso:country":"IN",
    "ks:ks_alt_nam":"tuingutu",
    "ks:ks_name":"Tuingutu",
    "ks:ks_pop":334,
    "ks:ks_type":"HABITATION",
    "name:eng_x_preferred":[
        "Tuingutu"
    ],
    "wof:name":"Tuingutu",
    "wof:placetype":"locality",
    "wof:population":334
},
  "geometry": {"coordinates":[85.40773299999999,22.878998],"type":"Point"}
}