{
  "type": "Feature",
  "properties": {
    "iso:country":"IN",
    "ks:ks_name":"Rangappanaiduvari Palem",
    "ks:ks_pop":404,
    "ks:ks_type":"HABITATION",
    "name:eng_x_preferred":[
        "Rangappanaiduvari Palem"
    ],
    "wof:name":"Rangappanaiduvari Palem",
    "wof:placetype":"locality",
    "wof:population":404
},
  "geometry": {"coordinates":[80.265901,15.829144],"type":"Point"}
}