{
  "type": "Feature",
  "properties": {
    "gn:admin1_code":"37",
    "gn:admin2_code":"404.0",
    "gn:asciiname":"Kolbari",
    "gn:country_code":"IN",
    "gn:dem":341,
    "gn:feature_class":"P",
    "gn:feature_code":"PPL",
    "gn:name":"Kolbar\u012b",
    "gn:population":0,
    "gn:timezone":"Asia/Kolkata",
    "iso:country":"IN",
    "ks:ks_alt_nam":"Kolbar\u012b",
    "ks:ks_name":"Kolbari",
    "ks:ks_pop":533,
    "ks:ks_type":"VILLAGE",
    "name:eng_x_preferred":[
        "Kolbari"
    ],
    "name:eng_x_variant":[
        "Kolbar\u012b"
    ],
    "wof:name":"Kolbari",
    "wof:placetype":"locality",
    "wof:population":533
},
  "geometry": {"coordinates":[82.56682000000001,22.536745],"type":"Point"}
}