{
  "type": "Feature",
  "properties": {
    "iso:country":"IN",
    "ks:ks_name":"Kotha Indlu",
    "ks:ks_pop":43,
    "ks:ks_type":"HABITATION",
    "ks:ks_uagg_main":0,
    "name:eng_x_preferred":[
        "Kotha Indlu"
    ],
    "wof:name":"Kotha Indlu",
    "wof:placetype":"neighbourhood",
    "wof:population":43
},
  "geometry": {"coordinates":[79.42818800000001,13.564244],"type":"Point"}
}