{
  "type": "Feature",
  "properties": {
    "iso:country":"IN",
    "ks:ks_name":"Lochapoda",
    "ks:ks_pop":9240,
    "ks:ks_type":"VILLAGE",
    "ks:ks_uagg_main":0,
    "name:eng_x_preferred":[
        "Lochapoda"
    ],
    "wof:name":"Lochapoda",
    "wof:placetype":"neighbourhood",
    "wof:population":9240
},
  "geometry": {"coordinates":[84.804732,19.323874],"type":"Point"}
}