{
  "type": "Feature",
  "properties": {
    "iso:country":"IN",
    "ks:ks_name":"Behereda",
    "ks:ks_pop":286,
    "ks:ks_type":"HABITATION",
    "name:eng_x_preferred":[
        "Behereda"
    ],
    "wof:name":"Behereda",
    "wof:placetype":"locality",
    "wof:population":286
},
  "geometry": {"coordinates":[85.93698999999999,19.966405],"type":"Point"}
}