{
  "type": "Feature",
  "properties": {
    "gn:admin1_code":"23.0",
    "gn:admin2_code":"44.0",
    "gn:asciiname":"Kuttyanwali",
    "gn:country_code":"IN",
    "gn:dem":192,
    "gn:feature_class":"P",
    "gn:feature_code":"PPL",
    "gn:name":"Kutty\u0101nw\u0101li",
    "gn:population":0,
    "gn:timezone":"Asia/Kolkata",
    "iso:country":"IN",
    "name:und_x_variant":[
        "Kutty\u0101nw\u0101li",
        "Nathupur Sus\u0101nw\u0101li"
    ],
    "wof:name":"Kuttyanwali",
    "wof:placetype":"locality"
},
  "geometry": {"coordinates":[74.46861,30.03185],"type":"Point"}
}