{
  "type": "Feature",
  "properties": {
    "gn:admin1_code":"19.0",
    "gn:admin2_code":"584.0",
    "gn:asciiname":"Manchanaikanhalli",
    "gn:country_code":"IN",
    "gn:dem":771,
    "gn:feature_class":"P",
    "gn:feature_code":"PPL",
    "gn:name":"Manchanaikanhalli",
    "gn:population":0,
    "gn:timezone":"Asia/Kolkata",
    "iso:country":"IN",
    "ks:ks_name":"Manchanayakanahalli",
    "ks:ks_pop":1968,
    "ks:ks_type":"VILLAGE",
    "ks:ks_uagg_main":0,
    "name:eng_x_preferred":[
        "Manchanayakanahalli"
    ],
    "wof:name":"Manchanayakanahalli",
    "wof:placetype":"locality",
    "wof:population":1968
},
  "geometry": {"coordinates":[77.41538199999999,12.833536],"type":"Point"}
}