{
  "type": "Feature",
  "properties": {
    "iso:country":"IN",
    "ks:ks_name":"Sajalpara",
    "ks:ks_pop":473,
    "ks:ks_type":"VILLAGE",
    "ks:ks_uagg_main":0,
    "name:eng_x_preferred":[
        "Sajalpara"
    ],
    "wof:name":"Sajalpara",
    "wof:placetype":"neighbourhood",
    "wof:population":473
},
  "geometry": {"coordinates":[90.768306,26.378371],"type":"Point"}
}