{
  "type": "Feature",
  "properties": {
    "gn:admin1_code":"35",
    "gn:admin2_code":"430.0",
    "gn:asciiname":"Chorhati",
    "gn:country_code":"IN",
    "gn:dem":322,
    "gn:feature_class":"P",
    "gn:feature_code":"PPL",
    "gn:name":"Chorhati",
    "gn:population":0,
    "gn:timezone":"Asia/Kolkata",
    "iso:country":"IN",
    "ks:ks_name":"Chorhata",
    "ks:ks_pop":3449,
    "ks:ks_type":"VILLAGE",
    "name:eng_x_preferred":[
        "Chorhata"
    ],
    "name:eng_x_variant":[
        "Chorhati"
    ],
    "wof:name":"Chorhata",
    "wof:placetype":"locality",
    "wof:population":3449
},
  "geometry": {"coordinates":[81.23575099999999,24.508714],"type":"Point"}
}