{
  "type": "Feature",
  "properties": {
    "gn:admin1_code":"34.0",
    "gn:admin2_code":"240.0",
    "gn:asciiname":"Sarauti",
    "gn:country_code":"IN",
    "gn:dem":82,
    "gn:feature_class":"P",
    "gn:feature_code":"PPL",
    "gn:name":"Sarauti",
    "gn:population":0,
    "gn:timezone":"Asia/Kolkata",
    "iso:country":"IN",
    "wof:name":"Sarauti",
    "wof:placetype":"locality"
},
  "geometry": {"coordinates":[84.65706999999998,25.19799],"type":"Point"}
}