{
  "type": "Feature",
  "properties": {
    "iso:country":"IN",
    "ks:ks_name":"Majhdih",
    "ks:ks_pop":62,
    "ks:ks_type":"HABITATION",
    "name:eng_x_preferred":[
        "Majhdih"
    ],
    "wof:name":"Majhdih",
    "wof:placetype":"locality",
    "wof:population":62
},
  "geometry": {"coordinates":[86.301058,24.032594],"type":"Point"}
}