{
  "type": "Feature",
  "properties": {
    "gn:admin1_code":"23.0",
    "gn:admin2_code":"53.0",
    "gn:asciiname":"Jaswantpura",
    "gn:country_code":"IN",
    "gn:dem":227,
    "gn:feature_class":"P",
    "gn:feature_code":"PPL",
    "gn:name":"Jaswantpura",
    "gn:population":0,
    "gn:timezone":"Asia/Kolkata",
    "iso:country":"IN",
    "name:ceb_x_preferred":[
        "Jaswantpura"
    ],
    "name:swe_x_preferred":[
        "Jaswantpura"
    ],
    "name:urd_x_preferred":[
        "\u062c\u0633\u0648\u0646\u062a\u067e\u0631\u0627"
    ],
    "wof:name":"Jaswantpura",
    "wof:placetype":"locality"
},
  "geometry": {"coordinates":[76.04595999999999,29.86235],"type":"Point"}
}