{
  "type": "Feature",
  "properties": {
    "gn:admin1_code":"35",
    "gn:admin2_code":"425.0",
    "gn:asciiname":"Bamnara Khurd",
    "gn:country_code":"IN",
    "gn:dem":297,
    "gn:feature_class":"P",
    "gn:feature_code":"PPL",
    "gn:name":"Bamnara Khurd",
    "gn:population":0,
    "gn:timezone":"Asia/Kolkata",
    "iso:country":"IN",
    "ks:ks_name":"Bamnora Khurd",
    "ks:ks_pop":73,
    "ks:ks_type":"HABITATION",
    "name:eng_x_preferred":[
        "Bamnora Khurd"
    ],
    "name:eng_x_variant":[
        "Bamnara Khurd"
    ],
    "wof:name":"Bamnora Khurd",
    "wof:placetype":"locality",
    "wof:population":73
},
  "geometry": {"coordinates":[79.331025,24.631367],"type":"Point"}
}