{
  "type": "Feature",
  "properties": {
    "iso:country":"IN",
    "ks:ks_name":"Haldar Para",
    "ks:ks_pop":594,
    "ks:ks_type":"HABITATION",
    "ks:ks_uagg_main":0,
    "name:eng_x_preferred":[
        "Haldar Para"
    ],
    "wof:name":"Haldar Para",
    "wof:placetype":"neighbourhood",
    "wof:population":594
},
  "geometry": {"coordinates":[88.32749200000001,22.159396],"type":"Point"}
}