{
  "type": "Feature",
  "properties": {
    "gn:admin1_code":"35.0",
    "gn:admin2_code":"441.0",
    "gn:asciiname":"Matli",
    "gn:country_code":"IN",
    "gn:dem":361,
    "gn:feature_class":"P",
    "gn:feature_code":"PPL",
    "gn:name":"Matli",
    "gn:population":0,
    "gn:timezone":"Asia/Kolkata",
    "iso:country":"IN",
    "name:fas_x_preferred":[
        "\u0645\u0627\u062a\u0644\u06cc"
    ],
    "name:fra_x_preferred":[
        "Matli"
    ],
    "name:snd_x_preferred":[
        "\u0645\u0627\u062a\u0644\u064a"
    ],
    "name:spa_x_preferred":[
        "Matli"
    ],
    "name:urd_x_preferred":[
        "\u0645\u0627\u062a\u0644\u06cc"
    ],
    "wof:name":"Matli",
    "wof:placetype":"locality"
},
  "geometry": {"coordinates":[75.03296,21.82024],"type":"Point"}
}