{
  "type": "Feature",
  "properties": {
    "iso:country":"IN",
    "ks:ks_alt_nam":"Sericulture complex",
    "ks:ks_name":"Sericulture Complex",
    "ks:ks_pop":9,
    "ks:ks_type":"HABITATION",
    "name:eng_x_preferred":[
        "Sericulture Complex"
    ],
    "wof:name":"Sericulture Complex",
    "wof:placetype":"locality",
    "wof:population":9
},
  "geometry": {"coordinates":[78.557793,13.533588],"type":"Point"}
}