{
  "type": "Feature",
  "properties": {
    "iso:country":"IN",
    "ks:ks_name":"Padwe",
    "ks:ks_pop":334,
    "ks:ks_type":"VILLAGE",
    "name:eng_x_preferred":[
        "Padwe"
    ],
    "wof:name":"Padwe",
    "wof:placetype":"locality",
    "wof:population":334
},
  "geometry": {"coordinates":[73.255764,18.056166],"type":"Point"}
}