{
  "type": "Feature",
  "properties": {
    "iso:country":"IN",
    "ks:ks_name":"Parla Jageer",
    "ks:ks_pop":417,
    "ks:ks_type":"HABITATION",
    "name:eng_x_preferred":[
        "Parla Jageer"
    ],
    "wof:name":"Parla Jageer",
    "wof:placetype":"locality",
    "wof:population":417
},
  "geometry": {"coordinates":[76.856683,26.960806],"type":"Point"}
}