{
  "type": "Feature",
  "properties": {
    "gn:admin1_code":"36.0",
    "gn:admin2_code":"189.0",
    "gn:asciiname":"Dubauli",
    "gn:country_code":"IN",
    "gn:dem":92,
    "gn:feature_class":"P",
    "gn:feature_code":"PPL",
    "gn:name":"Dubauli",
    "gn:population":0,
    "gn:timezone":"Asia/Kolkata",
    "iso:country":"IN",
    "ks:ks_name":"Dubauli",
    "ks:ks_pop":2015,
    "ks:ks_type":"VILLAGE",
    "name:eng_x_preferred":[
        "Dubauli"
    ],
    "wof:name":"Dubauli",
    "wof:placetype":"locality",
    "wof:population":2015
},
  "geometry": {"coordinates":[83.953056,26.998231],"type":"Point"}
}