{
  "type": "Feature",
  "properties": {
    "iso:country":"IN",
    "ks:ks_name":"Radhikadeipur",
    "ks:ks_pop":231,
    "ks:ks_type":"VILLAGE",
    "ks:ks_uagg_main":0,
    "name:eng_x_preferred":[
        "Radhikadeipur"
    ],
    "wof:name":"Radhikadeipur",
    "wof:placetype":"neighbourhood",
    "wof:population":231
},
  "geometry": {"coordinates":[85.709774,21.830255],"type":"Point"}
}