{
  "type": "Feature",
  "properties": {
    "iso:country":"IN",
    "ks:ks_name":"Binora",
    "ks:ks_pop":12,
    "ks:ks_type":"HABITATION",
    "name:eng_x_preferred":[
        "Binora"
    ],
    "wof:name":"Binora",
    "wof:placetype":"locality",
    "wof:population":12
},
  "geometry": {"coordinates":[78.38664199999999,22.801124],"type":"Point"}
}