{
  "type": "Feature",
  "properties": {
    "gn:admin1_code":"03",
    "gn:admin2_code":"308.0",
    "gn:asciiname":"Murkong Selek",
    "gn:country_code":"IN",
    "gn:dem":129,
    "gn:feature_class":"P",
    "gn:feature_code":"PPL",
    "gn:name":"Murkong Selek",
    "gn:population":0,
    "gn:timezone":"Asia/Kolkata",
    "iso:country":"IN",
    "name:und_x_variant":[
        "Murkong Selok",
        "Murkong Selek"
    ],
    "wof:name":"Murkong Selek",
    "wof:placetype":"neighbourhood"
},
  "geometry": {"coordinates":[95.22902000000001,27.82541],"type":"Point"}
}