{
  "type": "Feature",
  "properties": {
    "gn:admin1_code":"34.0",
    "gn:admin2_code":"239.0",
    "gn:asciiname":"Lakhapur",
    "gn:country_code":"IN",
    "gn:dem":68,
    "gn:feature_class":"P",
    "gn:feature_code":"PPL",
    "gn:name":"Lakh\u0101pur",
    "gn:population":0,
    "gn:timezone":"Asia/Kolkata",
    "iso:country":"IN",
    "ks:ks_alt_nam":"Lakh\u0101pur",
    "ks:ks_name":"Lakhapur",
    "ks:ks_pop":1132,
    "ks:ks_type":"VILLAGE",
    "name:eng_x_preferred":[
        "Lakhapur"
    ],
    "name:eng_x_variant":[
        "Lakh\u0101pur"
    ],
    "wof:name":"Lakhapur",
    "wof:placetype":"locality",
    "wof:population":1132
},
  "geometry": {"coordinates":[84.88587200000001,25.241355],"type":"Point"}
}