{
  "type": "Feature",
  "properties": {
    "iso:country":"IN",
    "ks:ks_alt_nam":"Pandrip\u0101ni",
    "ks:ks_name":"Pandripani",
    "ks:ks_pop":871,
    "ks:ks_type":"VILLAGE",
    "name:eng_x_preferred":[
        "Pandripani"
    ],
    "name:eng_x_variant":[
        "Pandrip\u0101ni"
    ],
    "wof:name":"Pandripani",
    "wof:placetype":"locality",
    "wof:population":871
},
  "geometry": {"coordinates":[84.611137,22.473296],"type":"Point"}
}