{
  "type": "Feature",
  "properties": {
    "iso:country":"IN",
    "ks:ks_alt_nam":"Jooktoli Borbam 206.203 T.E.24.1",
    "ks:ks_name":"Jooktoli Borbam 206.203 T.e.24.1",
    "ks:ks_pop":17,
    "ks:ks_type":"HABITATION",
    "name:eng_x_preferred":[
        "Jooktoli Borbam 206.203 T.e.24.1"
    ],
    "wof:name":"Jooktoli Borbam 206.203 T.e.24.1",
    "wof:placetype":"locality",
    "wof:population":17
},
  "geometry": {"coordinates":[95.068501,27.136813],"type":"Point"}
}