{
  "type": "Feature",
  "properties": {
    "gn:admin1_code":"23",
    "gn:admin2_code":"51.0",
    "gn:asciiname":"Bajrur",
    "gn:country_code":"IN",
    "gn:dem":285,
    "gn:feature_class":"P",
    "gn:feature_code":"PPL",
    "gn:name":"Bajrur",
    "gn:population":0,
    "gn:timezone":"Asia/Kolkata",
    "iso:country":"IN",
    "wof:name":"Bajrur",
    "wof:placetype":"locality"
},
  "geometry": {"coordinates":[76.54446,31.10554],"type":"Point"}
}