{
  "type": "Feature",
  "properties": {
    "iso:country":"IN",
    "ks:ks_name":"Kutilodh",
    "ks:ks_pop":211,
    "ks:ks_type":"HABITATION",
    "ks:ks_uagg_main":0,
    "name:eng_x_preferred":[
        "Kutilodh"
    ],
    "wof:name":"Kutilodh",
    "wof:placetype":"neighbourhood",
    "wof:population":211
},
  "geometry": {"coordinates":[81.606416,26.519126],"type":"Point"}
}