{
  "type": "Feature",
  "properties": {
    "gn:admin1_code":"34",
    "gn:admin2_code":"218.0",
    "gn:asciiname":"Pakaulia",
    "gn:country_code":"IN",
    "gn:dem":68,
    "gn:feature_class":"P",
    "gn:feature_code":"PPL",
    "gn:name":"Pakaulia",
    "gn:population":0,
    "gn:timezone":"Asia/Kolkata",
    "iso:country":"IN",
    "ks:ks_name":"Pakaulia",
    "ks:ks_pop":2288,
    "ks:ks_type":"VILLAGE",
    "ks:ks_uagg_main":0,
    "name:eng_x_preferred":[
        "Pakaulia"
    ],
    "wof:name":"Pakaulia",
    "wof:placetype":"locality",
    "wof:population":2288
},
  "geometry": {"coordinates":[84.340189,26.212611],"type":"Point"}
}