{
  "type": "Feature",
  "properties": {
    "iso:country":"IN",
    "ks:ks_name":"Dopada",
    "ks:ks_pop":187,
    "ks:ks_type":"VILLAGE",
    "ks:ks_uagg_main":0,
    "name:eng_x_preferred":[
        "Dopada"
    ],
    "wof:name":"Dopada",
    "wof:placetype":"neighbourhood",
    "wof:population":187
},
  "geometry": {"coordinates":[85.97285100000001,19.874079],"type":"Point"}
}