{
  "type": "Feature",
  "properties": {
    "iso:country":"IN",
    "ks:ks_alt_nam":"DERGE SAI",
    "ks:ks_name":"Derge Sai",
    "ks:ks_pop":175,
    "ks:ks_type":"HABITATION",
    "name:eng_x_preferred":[
        "Derge Sai"
    ],
    "wof:name":"Derge Sai",
    "wof:placetype":"locality",
    "wof:population":175
},
  "geometry": {"coordinates":[85.605153,22.336163],"type":"Point"}
}