{
  "type": "Feature",
  "properties": {
    "iso:country":"IN",
    "ks:ks_name":"Chamunda Nagar",
    "ks:ks_pop":335,
    "ks:ks_type":"HABITATION",
    "name:eng_x_preferred":[
        "Chamunda Nagar"
    ],
    "wof:name":"Chamunda Nagar",
    "wof:placetype":"locality",
    "wof:population":335
},
  "geometry": {"coordinates":[73.221692,25.993881],"type":"Point"}
}