{
  "type": "Feature",
  "properties": {
    "iso:country":"IN",
    "ks:ks_name":"Chawdang Gaon",
    "ks:ks_pop":273,
    "ks:ks_type":"HABITATION",
    "ks:ks_uagg_main":0,
    "name:eng_x_preferred":[
        "Chawdang Gaon"
    ],
    "wof:name":"Chawdang Gaon",
    "wof:placetype":"neighbourhood",
    "wof:population":273
},
  "geometry": {"coordinates":[94.489598,26.83614],"type":"Point"}
}