{
  "type": "Feature",
  "properties": {
    "gn:admin1_code":"24.0",
    "gn:admin2_code":"130.0",
    "gn:asciiname":"Vana",
    "gn:country_code":"IN",
    "gn:dem":746,
    "gn:feature_class":"P",
    "gn:feature_code":"PPL",
    "gn:name":"V\u0101na",
    "gn:population":0,
    "gn:timezone":"Asia/Kolkata",
    "iso:country":"IN",
    "name:deu_x_preferred":[
        "Vana"
    ],
    "name:fra_x_preferred":[
        "Vana"
    ],
    "name:lav_x_preferred":[
        "Vana"
    ],
    "name:nld_x_preferred":[
        "Vana"
    ],
    "wof:name":"Vana",
    "wof:placetype":"neighbourhood"
},
  "geometry": {"coordinates":[73.51708000000001,24.91812],"type":"Point"}
}