{
  "type": "Feature",
  "properties": {
    "iso:country":"IN",
    "ks:ks_name":"Hasori Kh.",
    "ks:ks_pop":759,
    "ks:ks_type":"VILLAGE",
    "name:eng_x_preferred":[
        "Hasori Kh."
    ],
    "wof:name":"Hasori Kh.",
    "wof:placetype":"locality",
    "wof:population":759
},
  "geometry": {"coordinates":[76.741314,17.975898],"type":"Point"}
}