{
  "type": "Feature",
  "properties": {
    "iso:country":"IN",
    "ks:ks_name":"Harharpur Samukhia",
    "ks:ks_type":"VILLAGE",
    "name:eng_x_preferred":[
        "Harharpur Samukhia"
    ],
    "wof:name":"Harharpur Samukhia",
    "wof:placetype":"locality"
},
  "geometry": {"coordinates":[79.62779999999999,28.850767],"type":"Point"}
}