{
  "type": "Feature",
  "properties": {
    "iso:country":"IN",
    "ks:ks_name":"Chhayrabari",
    "ks:ks_pop":431,
    "ks:ks_type":"VILLAGE",
    "name:eng_x_preferred":[
        "Chhayrabari"
    ],
    "wof:name":"Chhayrabari",
    "wof:placetype":"locality",
    "wof:population":431
},
  "geometry": {"coordinates":[86.828316,23.555197],"type":"Point"}
}