{
  "type": "Feature",
  "properties": {
    "iso:country":"IN",
    "ks:ks_name":"Janduon Ki Dhani",
    "ks:ks_pop":638,
    "ks:ks_type":"HABITATION",
    "name:eng_x_preferred":[
        "Janduon Ki Dhani"
    ],
    "wof:name":"Janduon Ki Dhani",
    "wof:placetype":"locality",
    "wof:population":638
},
  "geometry": {"coordinates":[71.669797,25.973206],"type":"Point"}
}