{
  "type": "Feature",
  "properties": {
    "iso:country":"IN",
    "ks:ks_name":"Lelapada",
    "ks:ks_pop":61,
    "ks:ks_type":"HABITATION",
    "name:eng_x_preferred":[
        "Lelapada"
    ],
    "wof:name":"Lelapada",
    "wof:placetype":"locality",
    "wof:population":61
},
  "geometry": {"coordinates":[84.232631,22.10058],"type":"Point"}
}