{
  "type": "Feature",
  "properties": {
    "iso:country":"IN",
    "ks:ks_name":"Hadawlewasti",
    "ks:ks_pop":450,
    "ks:ks_type":"HABITATION",
    "name:eng_x_preferred":[
        "Hadawlewasti"
    ],
    "wof:name":"Hadawlewasti",
    "wof:placetype":"locality",
    "wof:population":450
},
  "geometry": {"coordinates":[74.04447999999999,19.424512],"type":"Point"}
}