{
  "type": "Feature",
  "properties": {
    "gn:admin1_code":"19.0",
    "gn:admin2_code":"573.0",
    "gn:asciiname":"Byadarahalli",
    "gn:country_code":"IN",
    "gn:dem":736,
    "gn:feature_class":"P",
    "gn:feature_code":"PPL",
    "gn:name":"By\u0101darahalli",
    "gn:population":0,
    "gn:timezone":"Asia/Kolkata",
    "iso:country":"IN",
    "wof:name":"Byadarahalli",
    "wof:placetype":"neighbourhood"
},
  "geometry": {"coordinates":[76.75022,12.50428],"type":"Point"}
}