{
  "type": "Feature",
  "properties": {
    "iso:country":"IN",
    "ks:ks_alt_nam":"jeemesu",
    "ks:ks_name":"Jeemesu",
    "ks:ks_pop":42,
    "ks:ks_type":"HABITATION",
    "name:eng_x_preferred":[
        "Jeemesu"
    ],
    "wof:name":"Jeemesu",
    "wof:placetype":"locality",
    "wof:population":42
},
  "geometry": {"coordinates":[83.393942,18.911437],"type":"Point"}
}