{
  "type": "Feature",
  "properties": {
    "iso:country":"IN",
    "ks:ks_name":"Nadipar",
    "ks:ks_pop":146,
    "ks:ks_type":"HABITATION",
    "name:eng_x_preferred":[
        "Nadipar"
    ],
    "wof:name":"Nadipar",
    "wof:placetype":"locality",
    "wof:population":146
},
  "geometry": {"coordinates":[84.566776,24.413712],"type":"Point"}
}