{
  "type": "Feature",
  "properties": {
    "gn:admin1_code":"34.0",
    "gn:admin2_code":"231.0",
    "gn:asciiname":"Bankat",
    "gn:country_code":"IN",
    "gn:dem":69,
    "gn:feature_class":"P",
    "gn:feature_code":"PPL",
    "gn:name":"Bankat",
    "gn:population":0,
    "gn:timezone":"Asia/Kolkata",
    "iso:country":"IN",
    "name:fas_x_preferred":[
        "\u0634\u0645\u0634\u06cc\u0631\u0622\u0628\u0627\u062f"
    ],
    "name:msa_x_preferred":[
        "Bankat"
    ],
    "name:por_x_preferred":[
        "Bankat"
    ],
    "wof:name":"Bankat",
    "wof:placetype":"locality"
},
  "geometry": {"coordinates":[84.35763,25.56733],"type":"Point"}
}