{
  "type": "Feature",
  "properties": {
    "iso:country":"IN",
    "ks:ks_alt_nam":"Purwa Bahadur singh",
    "ks:ks_name":"Purwa Bahadur Singh",
    "ks:ks_pop":80,
    "ks:ks_type":"HABITATION",
    "ks:ks_uagg_main":0,
    "name:eng_x_preferred":[
        "Purwa Bahadur Singh"
    ],
    "wof:name":"Purwa Bahadur Singh",
    "wof:placetype":"neighbourhood",
    "wof:population":80
},
  "geometry": {"coordinates":[81.001963,27.27381],"type":"Point"}
}