{
  "type": "Feature",
  "properties": {
    "iso:country":"IN",
    "ks:ks_name":"Sanakadagadde",
    "ks:ks_pop":33,
    "ks:ks_type":"HABITATION",
    "name:eng_x_preferred":[
        "Sanakadagadde"
    ],
    "wof:name":"Sanakadagadde",
    "wof:placetype":"locality",
    "wof:population":33
},
  "geometry": {"coordinates":[75.276606,13.498864],"type":"Point"}
}