{
  "type": "Feature",
  "properties": {
    "gn:admin1_code":"38.0",
    "gn:admin2_code":"353.0",
    "gn:asciiname":"Chhota Pokharia",
    "gn:country_code":"IN",
    "gn:dem":141,
    "gn:feature_class":"P",
    "gn:feature_code":"PPL",
    "gn:name":"Chhota Pokharia",
    "gn:population":0,
    "gn:timezone":"Asia/Kolkata",
    "iso:country":"IN",
    "ks:ks_name":"Chhotapokhria",
    "ks:ks_pop":186,
    "ks:ks_type":"VILLAGE",
    "name:eng_x_preferred":[
        "Chhotapokhria"
    ],
    "name:eng_x_variant":[
        "Chhota Pokharia"
    ],
    "wof:name":"Chhotapokhria",
    "wof:placetype":"locality",
    "wof:population":186
},
  "geometry": {"coordinates":[87.570516,24.703226],"type":"Point"}
}