{
  "type": "Feature",
  "properties": {
    "iso:country":"IN",
    "ks:ks_name":"Kundilpur Chuburi",
    "ks:ks_pop":316,
    "ks:ks_type":"HABITATION",
    "name:eng_x_preferred":[
        "Kundilpur Chuburi"
    ],
    "wof:name":"Kundilpur Chuburi",
    "wof:placetype":"locality",
    "wof:population":316
},
  "geometry": {"coordinates":[94.005734,27.022824],"type":"Point"}
}