{
  "type": "Feature",
  "properties": {
    "gn:admin1_code":"36.0",
    "gn:admin2_code":"173.0",
    "gn:asciiname":"Sarai Sagar",
    "gn:country_code":"IN",
    "gn:dem":97,
    "gn:feature_class":"P",
    "gn:feature_code":"PPL",
    "gn:name":"Sar\u0101i S\u0101gar",
    "gn:population":0,
    "gn:timezone":"Asia/Kolkata",
    "iso:country":"IN",
    "ks:ks_alt_nam":"Sar\u0101i S\u0101gar",
    "ks:ks_name":"Sarai Sagar",
    "ks:ks_pop":1559,
    "ks:ks_type":"VILLAGE",
    "ks:ks_uagg_main":0,
    "name:eng_x_preferred":[
        "Sarai Sagar"
    ],
    "name:eng_x_variant":[
        "Sar\u0101i S\u0101gar"
    ],
    "wof:name":"Sarai Sagar",
    "wof:placetype":"neighbourhood",
    "wof:population":1559
},
  "geometry": {"coordinates":[81.97024999999999,25.870073],"type":"Point"}
}