{
  "type": "Feature",
  "properties": {
    "iso:country":"IN",
    "ks:ks_name":"Velakurichi",
    "ks:ks_pop":637,
    "ks:ks_type":"HABITATION",
    "name:eng_x_preferred":[
        "Velakurichi"
    ],
    "wof:name":"Velakurichi",
    "wof:placetype":"locality",
    "wof:population":637
},
  "geometry": {"coordinates":[78.344087,10.410397],"type":"Point"}
}