{
  "type": "Feature",
  "properties": {
    "gn:admin1_code":"11.0",
    "gn:admin2_code":"26.0",
    "gn:asciiname":"Kunda Kot",
    "gn:country_code":"IN",
    "gn:dem":1775,
    "gn:feature_class":"P",
    "gn:feature_code":"PPL",
    "gn:name":"Kunda Kot",
    "gn:population":0,
    "gn:timezone":"Asia/Kolkata",
    "iso:country":"IN",
    "wof:name":"Kunda Kot",
    "wof:placetype":"locality"
},
  "geometry": {"coordinates":[77.58540000000001,31.42999],"type":"Point"}
}