{
  "type": "Feature",
  "properties": {
    "iso:country":"IN",
    "ks:ks_name":"Sidai",
    "ks:ks_pop":411,
    "ks:ks_type":"VILLAGE",
    "name:eng_x_preferred":[
        "Sidai"
    ],
    "wof:name":"Sidai",
    "wof:placetype":"locality",
    "wof:population":411
},
  "geometry": {"coordinates":[88.950108,25.25855],"type":"Point"}
}