{
  "type": "Feature",
  "properties": {
    "iso:country":"IN",
    "ks:ks_name":"Ganga Bhavanipuram",
    "ks:ks_pop":1026,
    "ks:ks_type":"HABITATION",
    "name:eng_x_preferred":[
        "Ganga Bhavanipuram"
    ],
    "wof:name":"Ganga Bhavanipuram",
    "wof:placetype":"locality",
    "wof:population":1026
},
  "geometry": {"coordinates":[79.714958,16.699885],"type":"Point"}
}