{
  "type": "Feature",
  "properties": {
    "iso:country":"IN",
    "ks:ks_name":"Gowri Hole",
    "ks:ks_pop":650,
    "ks:ks_type":"HABITATION",
    "name:eng_x_preferred":[
        "Gowri Hole"
    ],
    "wof:name":"Gowri Hole",
    "wof:placetype":"locality",
    "wof:population":650
},
  "geometry": {"coordinates":[75.38295599999999,12.656253],"type":"Point"}
}