{
  "type": "Feature",
  "properties": {
    "gn:admin1_code":"36",
    "gn:admin2_code":"199.0",
    "gn:asciiname":"Haraura",
    "gn:country_code":"IN",
    "gn:dem":146,
    "gn:feature_class":"P",
    "gn:feature_code":"PPL",
    "gn:name":"Haraura",
    "gn:population":0,
    "gn:timezone":"Asia/Kolkata",
    "iso:country":"IN",
    "ks:ks_name":"Haraura",
    "ks:ks_pop":1351,
    "ks:ks_type":"VILLAGE",
    "name:eng_x_preferred":[
        "Haraura"
    ],
    "wof:name":"Haraura",
    "wof:placetype":"locality",
    "wof:population":1351
},
  "geometry": {"coordinates":[82.59378100000001,25.020768],"type":"Point"}
}