{
  "type": "Feature",
  "properties": {
    "gn:admin1_code":"11",
    "gn:admin2_code":"27.0",
    "gn:asciiname":"Salwahan",
    "gn:country_code":"IN",
    "gn:dem":813,
    "gn:feature_class":"P",
    "gn:feature_code":"PPL",
    "gn:name":"Salw\u0101han",
    "gn:population":0,
    "gn:timezone":"Asia/Kolkata",
    "iso:country":"IN",
    "wof:name":"Salwahan",
    "wof:placetype":"locality"
},
  "geometry": {"coordinates":[76.95003,31.56761],"type":"Point"}
}