{
  "type": "Feature",
  "properties": {
    "iso:country":"IN",
    "ks:ks_name":"Uddain Kheda",
    "ks:ks_pop":440,
    "ks:ks_type":"HABITATION",
    "name:eng_x_preferred":[
        "Uddain Kheda"
    ],
    "wof:name":"Uddain Kheda",
    "wof:placetype":"locality",
    "wof:population":440
},
  "geometry": {"coordinates":[80.80678,26.533833],"type":"Point"}
}