{
  "type": "Feature",
  "properties": {
    "iso:country":"IN",
    "ks:ks_name":"Asaimadaka",
    "ks:ks_pop":600,
    "ks:ks_type":"HABITATION",
    "name:eng_x_preferred":[
        "Asaimadaka"
    ],
    "wof:name":"Asaimadaka",
    "wof:placetype":"locality",
    "wof:population":600
},
  "geometry": {"coordinates":[74.911725,12.799102],"type":"Point"}
}