{
  "type": "Feature",
  "properties": {
    "iso:country":"IN",
    "ks:ks_name":"Ganeipadar",
    "ks:ks_pop":34,
    "ks:ks_type":"VILLAGE",
    "name:eng_x_preferred":[
        "Ganeipadar"
    ],
    "wof:name":"Ganeipadar",
    "wof:placetype":"locality",
    "wof:population":34
},
  "geometry": {"coordinates":[82.93547100000001,18.869906],"type":"Point"}
}