{
  "type": "Feature",
  "properties": {
    "iso:country":"IN",
    "ks:ks_name":"Kadasigse",
    "ks:ks_pop":65,
    "ks:ks_type":"HABITATION",
    "name:eng_x_preferred":[
        "Kadasigse"
    ],
    "wof:name":"Kadasigse",
    "wof:placetype":"locality",
    "wof:population":65
},
  "geometry": {"coordinates":[75.449483,13.393039],"type":"Point"}
}