{
  "type": "Feature",
  "properties": {
    "gn:admin1_code":"2.0",
    "gn:admin2_code":"553.0",
    "gn:asciiname":"Tummalapuram",
    "gn:country_code":"IN",
    "gn:dem":232,
    "gn:feature_class":"P",
    "gn:feature_code":"PPL",
    "gn:name":"Tummal\u0101puram",
    "gn:population":0,
    "gn:timezone":"Asia/Kolkata",
    "iso:country":"IN",
    "ks:ks_name":"Thimmapuram",
    "ks:ks_pop":299,
    "ks:ks_type":"HABITATION",
    "name:eng_x_preferred":[
        "Thimmapuram"
    ],
    "name:eng_x_variant":[
        "Tummalapuram"
    ],
    "wof:name":"Thimmapuram",
    "wof:placetype":"locality",
    "wof:population":299
},
  "geometry": {"coordinates":[78.04402899999999,14.847658],"type":"Point"}
}