{
  "type": "Feature",
  "properties": {
    "gn:admin1_code":"24.0",
    "gn:admin2_code":"129.0",
    "gn:asciiname":"Pathupura",
    "gn:country_code":"IN",
    "gn:dem":333,
    "gn:feature_class":"P",
    "gn:feature_code":"PPL",
    "gn:name":"P\u0101thupura",
    "gn:population":0,
    "gn:timezone":"Asia/Kolkata",
    "iso:country":"IN",
    "name:und_x_variant":[
        "P\u0101thupura",
        "Bareri Kal\u0101n"
    ],
    "wof:name":"Pathupura",
    "wof:placetype":"neighbourhood"
},
  "geometry": {"coordinates":[76.55083,24.3805],"type":"Point"}
}