{
  "type": "Feature",
  "properties": {
    "gn:admin1_code":"10",
    "gn:admin2_code":"89.0",
    "gn:asciiname":"Raunija",
    "gn:country_code":"IN",
    "gn:dem":197,
    "gn:feature_class":"P",
    "gn:feature_code":"PPL",
    "gn:name":"Raun\u012bja",
    "gn:population":0,
    "gn:timezone":"Asia/Kolkata",
    "iso:country":"IN",
    "wof:name":"Raunija",
    "wof:placetype":"locality"
},
  "geometry": {"coordinates":[77.36268000000003,28.11965],"type":"Point"}
}