{
  "type": "Feature",
  "properties": {
    "iso:country":"IN",
    "ks:ks_name":"Bandaru Vandlapalle",
    "ks:ks_pop":29,
    "ks:ks_type":"HABITATION",
    "name:eng_x_preferred":[
        "Bandaru Vandlapalle"
    ],
    "wof:name":"Bandaru Vandlapalle",
    "wof:placetype":"locality",
    "wof:population":29
},
  "geometry": {"coordinates":[78.88068,13.729925],"type":"Point"}
}