{
  "type": "Feature",
  "properties": {
    "iso:country":"IN",
    "ks:ks_alt_nam":"patratoli",
    "ks:ks_name":"Patratoli",
    "ks:ks_pop":92,
    "ks:ks_type":"HABITATION",
    "name:eng_x_preferred":[
        "Patratoli"
    ],
    "wof:name":"Patratoli",
    "wof:placetype":"locality",
    "wof:population":92
},
  "geometry": {"coordinates":[84.68182,22.983291],"type":"Point"}
}