{
  "type": "Feature",
  "properties": {
    "iso:country":"IN",
    "ks:ks_name":"Sirshai",
    "ks:ks_pop":992,
    "ks:ks_type":"HABITATION",
    "name:eng_x_preferred":[
        "Sirshai"
    ],
    "wof:name":"Sirshai",
    "wof:placetype":"locality",
    "wof:population":992
},
  "geometry": {"coordinates":[82.68645100000001,24.752634],"type":"Point"}
}