{
  "type": "Feature",
  "properties": {
    "gn:admin1_code":"19.0",
    "gn:admin2_code":"559.0",
    "gn:asciiname":"Duddal",
    "gn:country_code":"IN",
    "gn:dem":342,
    "gn:feature_class":"P",
    "gn:feature_code":"PPL",
    "gn:name":"Duddal",
    "gn:population":0,
    "gn:timezone":"Asia/Kolkata",
    "iso:country":"IN",
    "wof:name":"Duddal",
    "wof:placetype":"locality"
},
  "geometry": {"coordinates":[77.13739,15.94798],"type":"Point"}
}