{
  "type": "Feature",
  "properties": {
    "iso:country":"IN",
    "ks:ks_name":"Parsa Belahari",
    "ks:ks_pop":685,
    "ks:ks_type":"HABITATION",
    "ks:ks_uagg_main":0,
    "name:eng_x_preferred":[
        "Parsa Belahari"
    ],
    "wof:name":"Parsa Belahari",
    "wof:placetype":"neighbourhood",
    "wof:population":685
},
  "geometry": {"coordinates":[83.131743,27.451989],"type":"Point"}
}