{
  "type": "Feature",
  "properties": {
    "iso:country":"IN",
    "ks:ks_name":"Lota",
    "ks:ks_pop":670,
    "ks:ks_type":"VILLAGE",
    "name:eng_x_preferred":[
        "Lota"
    ],
    "wof:name":"Lota",
    "wof:placetype":"locality",
    "wof:population":670
},
  "geometry": {"coordinates":[85.547963,22.626449],"type":"Point"}
}