{
  "type": "Feature",
  "properties": {
    "iso:country":"IN",
    "ks:ks_name":"Musobad",
    "ks:ks_pop":0,
    "ks:ks_type":"VILLAGE",
    "name:eng_x_preferred":[
        "Musobad"
    ],
    "wof:name":"Musobad",
    "wof:placetype":"locality",
    "wof:population":0
},
  "geometry": {"coordinates":[85.823211,24.415191],"type":"Point"}
}