{
  "type": "Feature",
  "properties": {
    "iso:country":"IN",
    "ks:ks_alt_nam":"MUJAWAR ANJANAKARWASTI",
    "ks:ks_name":"Mujawar Anjanakarwasti",
    "ks:ks_pop":126,
    "ks:ks_type":"HABITATION",
    "name:eng_x_preferred":[
        "Mujawar Anjanakarwasti"
    ],
    "wof:name":"Mujawar Anjanakarwasti",
    "wof:placetype":"locality",
    "wof:population":126
},
  "geometry": {"coordinates":[74.689138,17.040117],"type":"Point"}
}