{
  "type": "Feature",
  "properties": {
    "gn:admin1_code":"36",
    "gn:admin2_code":"142.0",
    "gn:asciiname":"Nagla Dharakpur",
    "gn:country_code":"IN",
    "gn:dem":189,
    "gn:feature_class":"P",
    "gn:feature_code":"PPL",
    "gn:name":"Nagla Dh\u0101rakp\u016br",
    "gn:population":0,
    "gn:timezone":"Asia/Kolkata",
    "iso:country":"IN",
    "ks:ks_name":"Nagla Dharak",
    "ks:ks_pop":563,
    "ks:ks_type":"HABITATION",
    "ks:ks_uagg_main":0,
    "name:eng_x_preferred":[
        "Nagla Dharak"
    ],
    "wof:name":"Nagla Dharak",
    "wof:placetype":"neighbourhood",
    "wof:population":563
},
  "geometry": {"coordinates":[78.37828,28.149386],"type":"Point"}
}