{
  "type": "Feature",
  "properties": {
    "gn:admin1_code":"19.0",
    "gn:admin2_code":"582.0",
    "gn:asciiname":"Kamati Kadirenahalli",
    "gn:country_code":"IN",
    "gn:dem":718,
    "gn:feature_class":"P",
    "gn:feature_code":"PPL",
    "gn:name":"K\u0101m\u0101ti Kadirenahalli",
    "gn:population":0,
    "gn:timezone":"Asia/Kolkata",
    "iso:country":"IN",
    "wof:name":"Kamati Kadirenahalli",
    "wof:placetype":"locality"
},
  "geometry": {"coordinates":[77.61249000000002,13.6294],"type":"Point"}
}