{
  "type": "Feature",
  "properties": {
    "iso:country":"IN",
    "ks:ks_name":"Surta Fali",
    "ks:ks_pop":100,
    "ks:ks_type":"HABITATION",
    "name:eng_x_preferred":[
        "Surta Fali"
    ],
    "wof:name":"Surta Fali",
    "wof:placetype":"locality",
    "wof:population":100
},
  "geometry": {"coordinates":[72.986225,24.511531],"type":"Point"}
}