{
  "type": "Feature",
  "properties": {
    "iso:country":"IN",
    "ks:ks_name":"Kodgana Koplu",
    "ks:ks_pop":189,
    "ks:ks_type":"HABITATION",
    "name:eng_x_preferred":[
        "Kodgana Koplu"
    ],
    "wof:name":"Kodgana Koplu",
    "wof:placetype":"locality",
    "wof:population":189
},
  "geometry": {"coordinates":[76.361852,13.184992],"type":"Point"}
}