{
  "type": "Feature",
  "properties": {
    "iso:country":"IN",
    "ks:ks_name":"Agahua",
    "ks:ks_pop":699,
    "ks:ks_type":"VILLAGE",
    "ks:ks_uagg_main":0,
    "name:eng_x_preferred":[
        "Agahua"
    ],
    "wof:name":"Agahua",
    "wof:placetype":"neighbourhood",
    "wof:population":699
},
  "geometry": {"coordinates":[82.132183,25.628419],"type":"Point"}
}