{
  "type": "Feature",
  "properties": {
    "gn:admin1_code":"36",
    "gn:admin2_code":"149.0",
    "gn:asciiname":"Nagla Baran",
    "gn:country_code":"IN",
    "gn:dem":168,
    "gn:feature_class":"P",
    "gn:feature_code":"PPL",
    "gn:name":"Nagla Baran",
    "gn:population":0,
    "gn:timezone":"Asia/Kolkata",
    "iso:country":"IN",
    "wof:name":"Nagla Baran",
    "wof:placetype":"locality"
},
  "geometry": {"coordinates":[78.76624,27.98862],"type":"Point"}
}