{
  "type": "Feature",
  "properties": {
    "iso:country":"IN",
    "ks:ks_name":"Pandigaje",
    "ks:ks_pop":19,
    "ks:ks_type":"HABITATION",
    "name:eng_x_preferred":[
        "Pandigaje"
    ],
    "wof:name":"Pandigaje",
    "wof:placetype":"locality",
    "wof:population":19
},
  "geometry": {"coordinates":[75.51050600000001,12.697192],"type":"Point"}
}