{
  "type": "Feature",
  "properties": {
    "gn:admin1_code":"12.0",
    "gn:admin2_code":"8.0",
    "gn:asciiname":"Gund-i-jahangir",
    "gn:country_code":"IN",
    "gn:dem":1584,
    "gn:feature_class":"P",
    "gn:feature_code":"PPL",
    "gn:name":"Gund-i-jah\u0101ng\u012br",
    "gn:population":0,
    "gn:timezone":"Asia/Kolkata",
    "iso:country":"IN",
    "name:eng_x_preferred":[
        "Gund-i-jah\u0101ng\u012br"
    ],
    "wof:name":"Gund-i-jahangir",
    "wof:placetype":"locality"
},
  "geometry": {"coordinates":[74.55070000000001,34.26678],"type":"Point"}
}