{
  "type": "Feature",
  "properties": {
    "gn:admin1_code":"37",
    "gn:admin2_code":"408.0",
    "gn:asciiname":"Boirdih",
    "gn:country_code":"IN",
    "gn:dem":346,
    "gn:feature_class":"P",
    "gn:feature_code":"PPL",
    "gn:name":"Boird\u012bh",
    "gn:population":0,
    "gn:timezone":"Asia/Kolkata",
    "iso:country":"IN",
    "wof:name":"Boirdih",
    "wof:placetype":"locality"
},
  "geometry": {"coordinates":[80.66269,21.00792],"type":"Point"}
}