{
  "type": "Feature",
  "properties": {
    "gn:admin1_code":"36",
    "gn:admin2_code":"146.0",
    "gn:asciiname":"Tarauli Gujar",
    "gn:country_code":"IN",
    "gn:dem":162,
    "gn:feature_class":"P",
    "gn:feature_code":"PPL",
    "gn:name":"Tarauli G\u016bjar",
    "gn:population":0,
    "gn:timezone":"Asia/Kolkata",
    "iso:country":"IN",
    "ks:ks_alt_nam":"Tarauli G\u016bjar",
    "ks:ks_name":"Tarauli Gujar",
    "ks:ks_pop":657,
    "ks:ks_type":"VILLAGE",
    "name:eng_x_preferred":[
        "Tarauli Gujar"
    ],
    "name:eng_x_variant":[
        "Tarauli G\u016bjar"
    ],
    "wof:name":"Tarauli Gujar",
    "wof:placetype":"locality",
    "wof:population":657
},
  "geometry": {"coordinates":[78.419766,26.984422],"type":"Point"}
}