{
  "type": "Feature",
  "properties": {
    "gn:admin1_code":"35",
    "gn:admin2_code":"443.0",
    "gn:asciiname":"Lalitpur",
    "gn:country_code":"IN",
    "gn:dem":453,
    "gn:feature_class":"P",
    "gn:feature_code":"PPL",
    "gn:name":"Lalitpur",
    "gn:population":0,
    "gn:timezone":"Asia/Kolkata",
    "iso:country":"IN",
    "name:ceb_x_preferred":[
        "Lalitpur"
    ],
    "name:deu_x_preferred":[
        "Lalitpur"
    ],
    "name:fin_x_preferred":[
        "Lalitpur"
    ],
    "name:fra_x_preferred":[
        "Lalitpur"
    ],
    "name:kor_x_preferred":[
        "\ub784\ub9bf\ud478\ub974"
    ],
    "name:nld_x_preferred":[
        "Lalitpur"
    ],
    "name:pol_x_preferred":[
        "Lalitpur"
    ],
    "name:rus_x_preferred":[
        "\u041b\u0430\u043b\u0438\u0442\u043f\u0443\u0440"
    ],
    "name:spa_x_preferred":[
        "Lalitpur"
    ],
    "name:swe_x_preferred":[
        "Lalitpur"
    ],
    "name:vie_x_preferred":[
        "Lalitpur"
    ],
    "wof:name":"Lalitpur",
    "wof:placetype":"locality"
},
  "geometry": {"coordinates":[77.82942,24.28982],"type":"Point"}
}