{
  "type": "Feature",
  "properties": {
    "gn:admin1_code":"19.0",
    "gn:admin2_code":"577.0",
    "gn:asciiname":"Kuruhundi",
    "gn:country_code":"IN",
    "gn:dem":686,
    "gn:feature_class":"P",
    "gn:feature_code":"PPL",
    "gn:name":"Kuruhundi",
    "gn:population":0,
    "gn:timezone":"Asia/Kolkata",
    "iso:country":"IN",
    "wof:name":"Kuruhundi",
    "wof:placetype":"locality"
},
  "geometry": {"coordinates":[76.66374999999999,12.12754],"type":"Point"}
}