{
  "type": "Feature",
  "properties": {
    "iso:country":"IN",
    "ks:ks_name":"Andikottagam",
    "ks:ks_pop":838,
    "ks:ks_type":"HABITATION",
    "name:eng_x_preferred":[
        "Andikottagam"
    ],
    "wof:name":"Andikottagam",
    "wof:placetype":"locality",
    "wof:population":838
},
  "geometry": {"coordinates":[79.73573,11.26114],"type":"Point"}
}