{
  "type": "Feature",
  "properties": {
    "iso:country":"IN",
    "ks:ks_name":"Telipara Tea Garden",
    "ks:ks_pop":27399,
    "ks:ks_type":"URBAN",
    "name:eng_x_preferred":[
        "Telipara Tea Garden"
    ],
    "wof:name":"Telipara Tea Garden",
    "wof:placetype":"locality",
    "wof:population":27399
},
  "geometry": {"coordinates":[89.045593,26.719995],"type":"Point"}
}