{
  "type": "Feature",
  "properties": {
    "iso:country":"IN",
    "ks:ks_name":"Punnamoodu",
    "ks:ks_pop":78,
    "ks:ks_type":"HABITATION",
    "name:eng_x_preferred":[
        "Punnamoodu"
    ],
    "wof:name":"Punnamoodu",
    "wof:placetype":"locality",
    "wof:population":78
},
  "geometry": {"coordinates":[76.868588,9.139074],"type":"Point"}
}