{
  "type": "Feature",
  "properties": {
    "gn:admin1_code":"36",
    "gn:admin2_code":"181.0",
    "gn:asciiname":"Kishanpur",
    "gn:country_code":"IN",
    "gn:dem":124,
    "gn:feature_class":"P",
    "gn:feature_code":"PPL",
    "gn:name":"Kishanpur",
    "gn:population":0,
    "gn:timezone":"Asia/Kolkata",
    "iso:country":"IN",
    "wof:name":"Kishanpur",
    "wof:placetype":"locality"
},
  "geometry": {"coordinates":[81.80481,27.73992],"type":"Point"}
}