{
  "type": "Feature",
  "properties": {
    "iso:country":"IN",
    "ks:ks_alt_nam":"panditwasti",
    "ks:ks_name":"Panditwasti",
    "ks:ks_pop":100,
    "ks:ks_type":"HABITATION",
    "name:eng_x_preferred":[
        "Panditwasti"
    ],
    "wof:name":"Panditwasti",
    "wof:placetype":"locality",
    "wof:population":100
},
  "geometry": {"coordinates":[75.9033,19.3495],"type":"Point"}
}