{
  "type": "Feature",
  "properties": {
    "gn:admin1_code":"9.0",
    "gn:admin2_code":"474",
    "gn:asciiname":"Hebatpur",
    "gn:country_code":"IN",
    "gn:dem":12,
    "gn:feature_class":"P",
    "gn:feature_code":"PPL",
    "gn:name":"Hebatpur",
    "gn:population":0,
    "gn:timezone":"Asia/Kolkata",
    "iso:country":"IN",
    "wof:name":"Hebatpur",
    "wof:placetype":"locality"
},
  "geometry": {"coordinates":[72.10051,22.1393],"type":"Point"}
}