{
  "type": "Feature",
  "properties": {
    "iso:country":"IN",
    "ks:ks_alt_nam":"TIRE KI HARIJAN BASTI",
    "ks:ks_name":"Tire Ki Harijan Basti",
    "ks:ks_pop":126,
    "ks:ks_type":"HABITATION",
    "name:eng_x_preferred":[
        "Tire Ki Harijan Basti"
    ],
    "wof:name":"Tire Ki Harijan Basti",
    "wof:placetype":"locality",
    "wof:population":126
},
  "geometry": {"coordinates":[82.39842400000001,26.049919],"type":"Point"}
}