{
  "type": "Feature",
  "properties": {
    "gn:admin1_code":"39.0",
    "gn:admin2_code":"062",
    "gn:asciiname":"Dharamgarh",
    "gn:country_code":"IN",
    "gn:dem":1947,
    "gn:feature_class":"P",
    "gn:feature_code":"PPL",
    "gn:name":"Dharamgarh",
    "gn:population":0,
    "gn:timezone":"Asia/Kolkata",
    "iso:country":"IN",
    "wof:name":"Dharamgarh",
    "wof:placetype":"locality"
},
  "geometry": {"coordinates":[80.01666999999998,29.88333],"type":"Point"}
}