{
  "type": "Feature",
  "properties": {
    "iso:country":"IN",
    "ks:ks_name":"Konduru",
    "ks:ks_pop":21,
    "ks:ks_type":"HABITATION",
    "ks:ks_uagg_main":0,
    "name:eng_x_preferred":[
        "Konduru"
    ],
    "wof:name":"Konduru",
    "wof:placetype":"neighbourhood",
    "wof:population":21
},
  "geometry": {"coordinates":[79.339049,13.150407],"type":"Point"}
}