{
  "type": "Feature",
  "properties": {
    "iso:country":"IN",
    "ks:ks_name":"Bichuwa",
    "ks:ks_pop":106,
    "ks:ks_type":"HABITATION",
    "name:eng_x_preferred":[
        "Bichuwa"
    ],
    "wof:name":"Bichuwa",
    "wof:placetype":"locality",
    "wof:population":106
},
  "geometry": {"coordinates":[79.231599,23.653489],"type":"Point"}
}