{
  "type": "Feature",
  "properties": {
    "iso:country":"IN",
    "ks:ks_name":"20 AMS",
    "ks:ks_pop":376,
    "ks:ks_type":"VILLAGE",
    "name:eng_x_preferred":[
        "20 AMS"
    ],
    "wof:name":"20 AMS",
    "wof:placetype":"locality",
    "wof:population":376
},
  "geometry": {"coordinates":[75.17828900000001,29.195556],"type":"Point"}
}