{
  "type": "Feature",
  "properties": {
    "iso:country":"IN",
    "ks:ks_name":"Madhaliwadi",
    "ks:ks_pop":95,
    "ks:ks_type":"HABITATION",
    "name:eng_x_preferred":[
        "Madhaliwadi"
    ],
    "wof:name":"Madhaliwadi",
    "wof:placetype":"locality",
    "wof:population":95
},
  "geometry": {"coordinates":[73.305256,17.728992],"type":"Point"}
}