{
  "type": "Feature",
  "properties": {
    "iso:country":"IN",
    "ks:ks_name":"Kanapur",
    "ks:ks_pop":958,
    "ks:ks_type":"VILLAGE",
    "name:eng_x_preferred":[
        "Kanapur"
    ],
    "wof:name":"Kanapur",
    "wof:placetype":"locality",
    "wof:population":958
},
  "geometry": {"coordinates":[86.042331,20.046016],"type":"Point"}
}