{
  "type": "Feature",
  "properties": {
    "gn:admin1_code":"16",
    "gn:admin2_code":"510.0",
    "gn:asciiname":"Runjha",
    "gn:country_code":"IN",
    "gn:dem":284,
    "gn:feature_class":"P",
    "gn:feature_code":"PPL",
    "gn:name":"R\u016bnjha",
    "gn:population":0,
    "gn:timezone":"Asia/Kolkata",
    "iso:country":"IN",
    "name:und_x_variant":[
        "R\u016bnjha",
        "Runjha"
    ],
    "wof:name":"Runjha",
    "wof:placetype":"locality"
},
  "geometry": {"coordinates":[78.48459,20.16858],"type":"Point"}
}