{
  "type": "Feature",
  "properties": {
    "gn:admin1_code":"19.0",
    "gn:admin2_code":"568.0",
    "gn:asciiname":"Toravanda",
    "gn:country_code":"IN",
    "gn:dem":556,
    "gn:feature_class":"P",
    "gn:feature_code":"PPL",
    "gn:name":"Toravanda",
    "gn:population":0,
    "gn:timezone":"Asia/Kolkata",
    "iso:country":"IN",
    "wof:name":"Toravanda",
    "wof:placetype":"locality"
},
  "geometry": {"coordinates":[75.16984000000002,14.6136],"type":"Point"}
}