{
  "type": "Feature",
  "properties": {
    "iso:country":"IN",
    "ks:ks_name":"Kulapada",
    "ks:ks_pop":494,
    "ks:ks_type":"VILLAGE",
    "name:eng_x_preferred":[
        "Kulapada"
    ],
    "wof:name":"Kulapada",
    "wof:placetype":"locality",
    "wof:population":494
},
  "geometry": {"coordinates":[86.488544,20.484528],"type":"Point"}
}