{
  "type": "Feature",
  "properties": {
    "iso:country":"IN",
    "ks:ks_name":"Chhat Guriahati",
    "ks:ks_pop":2922,
    "ks:ks_type":"VILLAGE",
    "name:eng_x_preferred":[
        "Chhat Guriahati"
    ],
    "wof:name":"Chhat Guriahati",
    "wof:placetype":"locality",
    "wof:population":2922
},
  "geometry": {"coordinates":[89.44930100000001,26.298378],"type":"Point"}
}