{
  "type": "Feature",
  "properties": {
    "gn:admin1_code":"36",
    "gn:admin2_code":"196.0",
    "gn:asciiname":"Jeuripatti Anjabirai",
    "gn:country_code":"IN",
    "gn:dem":76,
    "gn:feature_class":"P",
    "gn:feature_code":"PPL",
    "gn:name":"Jeuripatti Anjabir\u0101i",
    "gn:population":0,
    "gn:timezone":"Asia/Kolkata",
    "iso:country":"IN",
    "wof:name":"Jeuripatti Anjabirai",
    "wof:placetype":"locality"
},
  "geometry": {"coordinates":[83.39075,25.27948],"type":"Point"}
}