{
  "type": "Feature",
  "properties": {
    "gn:admin1_code":"10",
    "gn:admin2_code":"75.0",
    "gn:asciiname":"Dhadoli",
    "gn:country_code":"IN",
    "gn:dem":231,
    "gn:feature_class":"P",
    "gn:feature_code":"PPL",
    "gn:name":"Dh\u0101doli",
    "gn:population":0,
    "gn:timezone":"Asia/Kolkata",
    "iso:country":"IN",
    "ks:ks_alt_nam":"Dh\u0101doli",
    "ks:ks_name":"Dhadoli",
    "ks:ks_type":"VILLAGE",
    "ks:ks_uagg_main":0,
    "name:eng_x_preferred":[
        "Dhadoli"
    ],
    "name:eng_x_variant":[
        "Dh\u0101doli"
    ],
    "wof:name":"Dhadoli",
    "wof:placetype":"neighbourhood"
},
  "geometry": {"coordinates":[77.031448,29.344104],"type":"Point"}
}