{
  "type": "Feature",
  "properties": {
    "gn:admin1_code":"19.0",
    "gn:admin2_code":"564.0",
    "gn:asciiname":"Bannur",
    "gn:country_code":"IN",
    "gn:dem":618,
    "gn:feature_class":"P",
    "gn:feature_code":"PPL",
    "gn:name":"Bann\u016br",
    "gn:population":0,
    "gn:timezone":"Asia/Kolkata",
    "iso:country":"IN",
    "wof:name":"Bannur",
    "wof:placetype":"locality"
},
  "geometry": {"coordinates":[75.24748000000002,15.0351],"type":"Point"}
}