{
  "type": "Feature",
  "properties": {
    "gn:admin1_code":"36.0",
    "gn:admin2_code":"189.0",
    "gn:asciiname":"Jharwa",
    "gn:country_code":"IN",
    "gn:dem":81,
    "gn:feature_class":"P",
    "gn:feature_code":"PPL",
    "gn:name":"Jharwa",
    "gn:population":0,
    "gn:timezone":"Asia/Kolkata",
    "iso:country":"IN",
    "ks:ks_name":"Jharwa",
    "ks:ks_pop":300,
    "ks:ks_type":"VILLAGE",
    "name:eng_x_preferred":[
        "Jharwa"
    ],
    "wof:name":"Jharwa",
    "wof:placetype":"locality",
    "wof:population":300
},
  "geometry": {"coordinates":[84.27054099999999,26.689739],"type":"Point"}
}