{
  "type": "Feature",
  "properties": {
    "gn:admin1_code":"10",
    "gn:admin2_code":"82.0",
    "gn:asciiname":"Kalanaur Kalan",
    "gn:country_code":"IN",
    "gn:dem":221,
    "gn:feature_class":"P",
    "gn:feature_code":"PPL",
    "gn:name":"Kal\u0101naur Kal\u0101n",
    "gn:population":0,
    "gn:timezone":"Asia/Kolkata",
    "iso:country":"IN",
    "wof:name":"Kalanaur Kalan",
    "wof:placetype":"locality"
},
  "geometry": {"coordinates":[76.40784000000002,28.8343],"type":"Point"}
}