{
  "type": "Feature",
  "properties": {
    "iso:country":"IN",
    "ks:ks_name":"Mahmood Pur",
    "ks:ks_pop":285,
    "ks:ks_type":"HABITATION",
    "name:eng_x_preferred":[
        "Mahmood Pur"
    ],
    "wof:name":"Mahmood Pur",
    "wof:placetype":"locality",
    "wof:population":285
},
  "geometry": {"coordinates":[79.770668,27.37246],"type":"Point"}
}