{
  "type": "Feature",
  "properties": {
    "iso:country":"IN",
    "ks:ks_name":"Likhi Kampa",
    "ks:ks_pop":352,
    "ks:ks_type":"HABITATION",
    "name:eng_x_preferred":[
        "Likhi Kampa"
    ],
    "wof:name":"Likhi Kampa",
    "wof:placetype":"locality",
    "wof:population":352
},
  "geometry": {"coordinates":[73.029667,23.688944],"type":"Point"}
}