{
  "type": "Feature",
  "properties": {
    "iso:country":"IN",
    "ks:ks_name":"Thoppukuttikadu",
    "ks:ks_pop":217,
    "ks:ks_type":"HABITATION",
    "name:eng_x_preferred":[
        "Thoppukuttikadu"
    ],
    "wof:name":"Thoppukuttikadu",
    "wof:placetype":"locality",
    "wof:population":217
},
  "geometry": {"coordinates":[78.602501,10.800689],"type":"Point"}
}