{
  "type": "Feature",
  "properties": {
    "gn:admin1_code":"35",
    "gn:admin2_code":"459.0",
    "gn:asciiname":"Begampur",
    "gn:country_code":"IN",
    "gn:dem":468,
    "gn:feature_class":"P",
    "gn:feature_code":"PPL",
    "gn:name":"Begampur",
    "gn:population":0,
    "gn:timezone":"Asia/Kolkata",
    "iso:country":"IN",
    "wof:name":"Begampur",
    "wof:placetype":"locality"
},
  "geometry": {"coordinates":[77.90574000000002,24.42323],"type":"Point"}
}