{
  "type": "Feature",
  "properties": {
    "iso:country":"IN",
    "ks:ks_name":"Thottu Valli",
    "ks:ks_pop":345,
    "ks:ks_type":"HABITATION",
    "name:eng_x_preferred":[
        "Thottu Valli"
    ],
    "wof:name":"Thottu Valli",
    "wof:placetype":"locality",
    "wof:population":345
},
  "geometry": {"coordinates":[76.85207,8.838755],"type":"Point"}
}