{
  "type": "Feature",
  "properties": {
    "iso:country":"IN",
    "ks:ks_name":"Karaunda Pani",
    "ks:ks_pop":342,
    "ks:ks_type":"VILLAGE",
    "name:eng_x_preferred":[
        "Karaunda Pani"
    ],
    "wof:name":"Karaunda Pani",
    "wof:placetype":"locality",
    "wof:population":342
},
  "geometry": {"coordinates":[81.455246,23.01841],"type":"Point"}
}