{
  "type": "Feature",
  "properties": {
    "gn:admin1_code":"19.0",
    "gn:admin2_code":"571.0",
    "gn:asciiname":"Yaladadlu",
    "gn:country_code":"IN",
    "gn:dem":831,
    "gn:feature_class":"P",
    "gn:feature_code":"PPL",
    "gn:name":"Yalad\u0101dlu",
    "gn:population":0,
    "gn:timezone":"Asia/Kolkata",
    "iso:country":"IN",
    "wof:name":"Yaladadlu",
    "wof:placetype":"locality"
},
  "geometry": {"coordinates":[77.03445000000001,13.51268],"type":"Point"}
}