{
  "type": "Feature",
  "properties": {
    "iso:country":"IN",
    "ks:ks_name":"Vydyashala",
    "ks:ks_pop":354,
    "ks:ks_type":"HABITATION",
    "ks:ks_uagg_main":0,
    "name:eng_x_preferred":[
        "Vydyashala"
    ],
    "wof:name":"Vydyashala",
    "wof:placetype":"neighbourhood",
    "wof:population":354
},
  "geometry": {"coordinates":[76.286008,10.428803],"type":"Point"}
}