{
  "type": "Feature",
  "properties": {
    "iso:country":"IN",
    "ks:ks_alt_nam":"KOTECHA DHANDHUO KD",
    "ks:ks_name":"Kotecha Dhandhuo Kd",
    "ks:ks_pop":70,
    "ks:ks_type":"HABITATION",
    "name:eng_x_preferred":[
        "Kotecha Dhandhuo Kd"
    ],
    "wof:name":"Kotecha Dhandhuo Kd",
    "wof:placetype":"locality",
    "wof:population":70
},
  "geometry": {"coordinates":[71.197372,25.750497],"type":"Point"}
}