{
  "type": "Feature",
  "properties": {
    "iso:country":"IN",
    "ks:ks_name":"Saleh Chak",
    "ks:ks_pop":0,
    "ks:ks_type":"VILLAGE",
    "name:eng_x_preferred":[
        "Saleh Chak"
    ],
    "wof:name":"Saleh Chak",
    "wof:placetype":"locality",
    "wof:population":0
},
  "geometry": {"coordinates":[86.97803399999999,25.114742],"type":"Point"}
}