{
  "type": "Feature",
  "properties": {
    "gn:admin1_code":"19.0",
    "gn:admin2_code":"573.0",
    "gn:asciiname":"Malasamudra",
    "gn:country_code":"IN",
    "gn:dem":982,
    "gn:feature_class":"P",
    "gn:feature_code":"PPL",
    "gn:name":"Malasamudra",
    "gn:population":0,
    "gn:timezone":"Asia/Kolkata",
    "iso:country":"IN",
    "wof:name":"Malasamudra",
    "wof:placetype":"neighbourhood"
},
  "geometry": {"coordinates":[76.66314,12.79662],"type":"Point"}
}