{
  "type": "Feature",
  "properties": {
    "gn:admin1_code":"37.0",
    "gn:admin2_code":"412.0",
    "gn:asciiname":"Bhalukona",
    "gn:country_code":"IN",
    "gn:dem":421,
    "gn:feature_class":"P",
    "gn:feature_code":"PPL",
    "gn:name":"Bh\u0101l\u016bkona",
    "gn:population":0,
    "gn:timezone":"Asia/Kolkata",
    "iso:country":"IN",
    "wof:name":"Bhalukona",
    "wof:placetype":"locality"
},
  "geometry": {"coordinates":[81.4786,20.52774],"type":"Point"}
}