{
  "type": "Feature",
  "properties": {
    "iso:country":"IN",
    "ks:ks_name":"Dilpachhanda",
    "ks:ks_pop":133,
    "ks:ks_type":"VILLAGE",
    "name:eng_x_preferred":[
        "Dilpachhanda"
    ],
    "wof:name":"Dilpachhanda",
    "wof:placetype":"locality",
    "wof:population":133
},
  "geometry": {"coordinates":[88.686955,25.332749],"type":"Point"}
}