{
  "type": "Feature",
  "properties": {
    "iso:country":"IN",
    "ks:ks_name":"Ettige",
    "ks:ks_pop":17,
    "ks:ks_type":"HABITATION",
    "name:eng_x_preferred":[
        "Ettige"
    ],
    "wof:name":"Ettige",
    "wof:placetype":"locality",
    "wof:population":17
},
  "geometry": {"coordinates":[74.84054500000001,14.139502],"type":"Point"}
}