{
  "type": "Feature",
  "properties": {
    "iso:country":"IN",
    "ks:ks_alt_nam":"S\u0101wajp\u0101ni Reserved Forest",
    "ks:ks_name":"Sawajpani Reserved Forest",
    "ks:ks_type":"VILLAGE",
    "name:eng_x_preferred":[
        "Sawajpani Reserved Forest"
    ],
    "name:eng_x_variant":[
        "S\u0101wajp\u0101ni Reserved Forest"
    ],
    "wof:name":"Sawajpani Reserved Forest",
    "wof:placetype":"locality"
},
  "geometry": {"coordinates":[78.650096,21.583447],"type":"Point"}
}