{
  "type": "Feature",
  "properties": {
    "gn:admin1_code":"9",
    "gn:admin2_code":"485.0",
    "gn:asciiname":"Palikpur",
    "gn:country_code":"IN",
    "gn:dem":203,
    "gn:feature_class":"P",
    "gn:feature_code":"PPL",
    "gn:name":"P\u0101likpur",
    "gn:population":0,
    "gn:timezone":"Asia/Kolkata",
    "iso:country":"IN",
    "wof:name":"Palikpur",
    "wof:placetype":"locality"
},
  "geometry": {"coordinates":[74.04953,23.16138],"type":"Point"}
}