{
  "type": "Feature",
  "properties": {
    "gn:admin1_code":"34.0",
    "gn:admin2_code":"229.0",
    "gn:asciiname":"Hanumangarh",
    "gn:country_code":"IN",
    "gn:dem":55,
    "gn:feature_class":"P",
    "gn:feature_code":"PPL",
    "gn:name":"Hanum\u0101ngarh",
    "gn:population":0,
    "gn:timezone":"Asia/Kolkata",
    "iso:country":"IN",
    "name:ara_x_preferred":[
        "\u0647\u0627\u0646\u0648\u0645\u0627\u0646\u062c\u0631\u0627"
    ],
    "name:ben_bn_x_preferred":[
        "\u09b9\u09a8\u09c1\u09ae\u09be\u09a8\u0997\u09a1\u09bc"
    ],
    "name:ben_in_x_preferred":[
        "\u09b9\u09a8\u09c1\u09ae\u09be\u09a8\u0997\u09a1\u09bc"
    ],
    "name:ben_x_preferred":[
        "\u09b9\u09a8\u09c1\u09ae\u09be\u09a8\u0997\u09a1\u09bc"
    ],
    "name:bih_x_preferred":[
        "\u0939\u0928\u0941\u092e\u093e\u0928\u0917\u0922"
    ],
    "name:bpy_x_preferred":[
        "\u09b9\u09a8\u09c1\u09ae\u09be\u09a8\u0997\u09a1\u09bc"
    ],
    "name:cat_x_preferred":[
        "Hanumangarh"
    ],
    "name:ceb_x_preferred":[
        "Hanum\u0101ngarh"
    ],
    "name:deu_x_preferred":[
        "Hanumangarh"
    ],
    "name:fra_x_preferred":[
        "Hanumangarh"
    ],
    "name:guj_x_preferred":[
        "\u0ab9\u0aa8\u0ac1\u0aae\u0abe\u0aa8\u0a97\u0aa2"
    ],
    "name:hin_x_preferred":[
        "\u0939\u0928\u0941\u092e\u093e\u0928\u0917\u095d"
    ],
    "name:hin_x_variant":[
        "\u0939\u0928\u0941\u092e\u093e\u0928\u0917\u0922\u093c"
    ],
    "name:ita_x_preferred":[
        "Hanumangarh"
    ],
    "name:kan_x_preferred":[
        "\u0cb9\u0ca8\u0cc1\u0cae\u0cbe\u0ca8\u0ccd"
    ],
    "name:mal_x_preferred":[
        "\u0d39\u0d28\u0d41\u0d2e\u0d3e\u0d7b\u0d17\u0d21\u0d4d"
    ],
    "name:mar_x_preferred":[
        "\u0939\u0928\u0941\u092e\u093e\u0928\u0917\u0921"
    ],
    "name:mar_x_variant":[
        "\u0939\u0928\u0941\u092e\u093e\u0928\u0917\u0922"
    ],
    "name:mlg_x_preferred":[
        "Hanumangarh"
    ],
    "name:msa_x_preferred":[
        "Hanumangarh"
    ],
    "name:new_x_preferred":[
        "\u0939\u0928\u0941\u092e\u093e\u0928\u0917\u0922"
    ],
    "name:pam_x_preferred":[
        "Hanumangarh"
    ],
    "name:pan_x_preferred":[
        "\u0a39\u0a28\u0a42\u0a2e\u0a3e\u0a28\u0a17\u0a5c\u0a4d\u0a39"
    ],
    "name:pan_x_variant":[
        "\u0a39\u0a28\u0a42\u0a70\u0a2e\u0a3e\u0a28\u0a17\u0a5c\u0a4d\u0a39"
    ],
    "name:pnb_x_preferred":[
        "\u06c1\u0646\u0648\u0645\u0627\u0646\u06af\u06c1\u0691"
    ],
    "name:pol_x_preferred":[
        "Hanumangarh"
    ],
    "name:rus_x_preferred":[
        "\u0425\u0430\u043d\u0443\u043c\u0430\u043d\u0433\u0430\u0440\u0445"
    ],
    "name:san_x_preferred":[
        "\u0939\u0928\u0941\u092e\u093e\u0928\u0917\u0922"
    ],
    "name:swe_x_preferred":[
        "Hanumangarh"
    ],
    "name:tam_x_preferred":[
        "\u0b85\u0ba9\u0bc1\u0bae\u0ba9\u0bcd\u0b95\u0bb0\u0bcd"
    ],
    "name:tel_x_preferred":[
        "\u0c39\u0c28\u0c41\u0c2e\u0c3e\u0c28\u0c4d"
    ],
    "name:urd_x_preferred":[
        "\u06c1\u0646\u0648\u0645\u0627\u0646 \u06af\u0691\u06be"
    ],
    "name:vie_x_preferred":[
        "Hanumangarh"
    ],
    "name:xmf_x_preferred":[
        "\u10f0\u10d0\u10dc\u10e3\u10db\u10d0\u10dc\u10d2\u10d0\u10e0\u10f0\u10d8"
    ],
    "name:zho_x_preferred":[
        "\u54c8\u52aa\u8292\u683c\u963f\u5c14"
    ],
    "wof:name":"Hanumangarh",
    "wof:placetype":"locality"
},
  "geometry": {"coordinates":[85.40746,25.33236],"type":"Point"}
}