{
  "type": "Feature",
  "properties": {
    "gn:admin1_code":"19.0",
    "gn:admin2_code":"563.0",
    "gn:asciiname":"Salkod",
    "gn:country_code":"IN",
    "gn:dem":26,
    "gn:feature_class":"P",
    "gn:feature_code":"PPL",
    "gn:name":"S\u0101lkod",
    "gn:population":0,
    "gn:timezone":"Asia/Kolkata",
    "iso:country":"IN",
    "ks:ks_alt_nam":"S\u0101lkod",
    "ks:ks_name":"Salkod",
    "ks:ks_pop":4073,
    "ks:ks_type":"VILLAGE",
    "name:eng_x_preferred":[
        "Salkod"
    ],
    "name:eng_x_variant":[
        "S\u0101lkod"
    ],
    "wof:name":"Salkod",
    "wof:placetype":"locality",
    "wof:population":4073
},
  "geometry": {"coordinates":[74.50500700000001,14.312989],"type":"Point"}
}