{
  "type": "Feature",
  "properties": {
    "gn:admin1_code":"11.0",
    "gn:admin2_code":"033",
    "gn:asciiname":"Kufri",
    "gn:country_code":"IN",
    "gn:dem":2476,
    "gn:feature_class":"P",
    "gn:feature_code":"PPL",
    "gn:name":"Kufri",
    "gn:population":0,
    "gn:timezone":"Asia/Kolkata",
    "iso:country":"IN",
    "name:ceb_x_preferred":[
        "Kufri"
    ],
    "name:eng_x_preferred":[
        "Kufri"
    ],
    "name:guj_x_preferred":[
        "\u0a95\u0ac1\u0aab\u0ab0\u0ac0"
    ],
    "name:hin_x_preferred":[
        "\u0915\u0941\u092b\u0930\u0940"
    ],
    "name:mal_x_preferred":[
        "\u0d15\u0d41\u0d2b\u0d4d\u0d30\u0d3f"
    ],
    "name:pol_x_preferred":[
        "Kufri"
    ],
    "name:swe_x_preferred":[
        "Kufri"
    ],
    "name:tam_x_preferred":[
        "\u0b95\u0bc1\u0baa\u0bcd\u0bb0\u0bbf"
    ],
    "name:und_x_variant":[
        "K\u016bfr\u012b",
        "Kufri"
    ],
    "wof:name":"Kufri",
    "wof:placetype":"locality"
},
  "geometry": {"coordinates":[77.26508000000003,31.10221],"type":"Point"}
}