{
  "type": "Feature",
  "properties": {
    "gn:admin1_code":"11.0",
    "gn:admin2_code":"033",
    "gn:asciiname":"Kufri",
    "gn:country_code":"IN",
    "gn:dem":2476,
    "gn:feature_class":"P",
    "gn:feature_code":"PPL",
    "gn:name":"Kufri",
    "gn:population":0,
    "gn:timezone":"Asia/Kolkata",
    "iso:country":"IN",
    "name:eng_x_preferred":[
        "Kufri"
    ],
    "name:und_x_variant":[
        "K\u016bfr\u012b",
        "Kufri"
    ],
    "wof:name":"Kufri",
    "wof:placetype":"locality"
},
  "geometry": {"coordinates":[77.26508000000003,31.10221],"type":"Point"}
}