{
  "type": "Feature",
  "properties": {
    "iso:country":"IN",
    "ks:ks_name":"Pandurangapura",
    "ks:ks_pop":192,
    "ks:ks_type":"HABITATION",
    "name:eng_x_preferred":[
        "Pandurangapura"
    ],
    "wof:name":"Pandurangapura",
    "wof:placetype":"locality",
    "wof:population":192
},
  "geometry": {"coordinates":[77.660706,13.269848],"type":"Point"}
}