{
  "type": "Feature",
  "properties": {
    "gn:admin1_code":"19.0",
    "gn:admin2_code":"574.0",
    "gn:asciiname":"Harohalli",
    "gn:country_code":"IN",
    "gn:dem":953,
    "gn:feature_class":"P",
    "gn:feature_code":"PPL",
    "gn:name":"Harohalli",
    "gn:population":0,
    "gn:timezone":"Asia/Kolkata",
    "iso:country":"IN",
    "name:ceb_x_preferred":[
        "H\u0101rohalli"
    ],
    "name:swe_x_preferred":[
        "H\u0101rohalli"
    ],
    "name:vie_x_preferred":[
        "Harohalli"
    ],
    "wof:name":"Harohalli",
    "wof:placetype":"locality"
},
  "geometry": {"coordinates":[75.93106999999998,12.88053],"type":"Point"}
}