{
  "type": "Feature",
  "properties": {
    "iso:country":"IN",
    "ks:ks_name":"Chumra Cheradand",
    "ks:ks_pop":225,
    "ks:ks_type":"HABITATION",
    "name:eng_x_preferred":[
        "Chumra Cheradand"
    ],
    "wof:name":"Chumra Cheradand",
    "wof:placetype":"locality",
    "wof:population":225
},
  "geometry": {"coordinates":[83.50156800000001,23.788128],"type":"Point"}
}