{
  "type": "Feature",
  "properties": {
    "iso:country":"IN",
    "ks:ks_name":"Ayyannur",
    "ks:ks_pop":269,
    "ks:ks_type":"HABITATION",
    "name:eng_x_preferred":[
        "Ayyannur"
    ],
    "wof:name":"Ayyannur",
    "wof:placetype":"locality",
    "wof:population":269
},
  "geometry": {"coordinates":[76.058903,10.692135],"type":"Point"}
}