{
  "type": "Feature",
  "properties": {
    "iso:country":"IN",
    "ks:ks_name":"Gunupur",
    "ks:ks_pop":707,
    "ks:ks_type":"VILLAGE",
    "name:eng_x_preferred":[
        "Gunupur"
    ],
    "wof:name":"Gunupur",
    "wof:placetype":"locality",
    "wof:population":707
},
  "geometry": {"coordinates":[86.556713,20.514978],"type":"Point"}
}