{
  "type": "Feature",
  "properties": {
    "iso:country":"IN",
    "ks:ks_alt_nam":"KamboBhtta",
    "ks:ks_name":"Kambobhtta",
    "ks:ks_pop":605,
    "ks:ks_type":"HABITATION",
    "name:eng_x_preferred":[
        "Kambobhtta"
    ],
    "wof:name":"Kambobhtta",
    "wof:placetype":"locality",
    "wof:population":605
},
  "geometry": {"coordinates":[88.061176,26.38138],"type":"Point"}
}