{
  "type": "Feature",
  "properties": {
    "gn:admin1_code":"12",
    "gn:admin2_code":"3.0",
    "gn:asciiname":"Kumdok",
    "gn:country_code":"IN",
    "gn:dem":4309,
    "gn:feature_class":"P",
    "gn:feature_code":"PPL",
    "gn:name":"Kumdok",
    "gn:population":0,
    "gn:timezone":"Asia/Kolkata",
    "iso:country":"IN",
    "wof:name":"Kumdok",
    "wof:placetype":"locality"
},
  "geometry": {"coordinates":[78.19014,33.5213],"type":"Point"}
}