{
  "type": "Feature",
  "properties": {
    "gn:admin1_code":"35",
    "gn:admin2_code":"451.0",
    "gn:asciiname":"Ghunsaur",
    "gn:country_code":"IN",
    "gn:dem":389,
    "gn:feature_class":"P",
    "gn:feature_code":"PPL",
    "gn:name":"Ghunsaur",
    "gn:population":0,
    "gn:timezone":"Asia/Kolkata",
    "iso:country":"IN",
    "wof:name":"Ghunsaur",
    "wof:placetype":"locality"
},
  "geometry": {"coordinates":[79.8644,23.1059],"type":"Point"}
}