{
  "type": "Feature",
  "properties": {
    "gn:admin1_code":"12",
    "gn:admin2_code":"14.0",
    "gn:asciiname":"Zamtarwan",
    "gn:country_code":"IN",
    "gn:dem":2621,
    "gn:feature_class":"P",
    "gn:feature_code":"PPL",
    "gn:name":"Zamtarw\u0101n",
    "gn:population":0,
    "gn:timezone":"Asia/Kolkata",
    "iso:country":"IN",
    "wof:name":"Zamtarwan",
    "wof:placetype":"locality"
},
  "geometry": {"coordinates":[75.30783000000002,34.05074],"type":"Point"}
}