{
  "type": "Feature",
  "properties": {
    "iso:country":"IN",
    "ks:ks_name":"Pindralet",
    "ks:ks_pop":278,
    "ks:ks_type":"VILLAGE",
    "name:eng_x_preferred":[
        "Pindralet"
    ],
    "wof:name":"Pindralet",
    "wof:placetype":"locality",
    "wof:population":278
},
  "geometry": {"coordinates":[86.980874,24.379197],"type":"Point"}
}