{
  "type": "Feature",
  "properties": {
    "gn:admin1_code":"12.0",
    "gn:admin2_code":"7.0",
    "gn:asciiname":"Rea",
    "gn:country_code":"IN",
    "gn:dem":826,
    "gn:feature_class":"P",
    "gn:feature_code":"PPL",
    "gn:name":"Rea",
    "gn:population":0,
    "gn:timezone":"Asia/Kolkata",
    "iso:country":"IN",
    "name:bre_x_preferred":[
        "Rea"
    ],
    "name:cat_x_preferred":[
        "Rea"
    ],
    "name:ceb_x_preferred":[
        "Rea"
    ],
    "name:ces_x_preferred":[
        "Rea"
    ],
    "name:eus_x_preferred":[
        "Rea"
    ],
    "name:fra_x_preferred":[
        "Rea"
    ],
    "name:glg_x_preferred":[
        "Rea"
    ],
    "name:hun_x_preferred":[
        "Rea"
    ],
    "name:nds_x_preferred":[
        "Rea"
    ],
    "name:nld_x_preferred":[
        "Rea"
    ],
    "name:pol_x_preferred":[
        "Rea"
    ],
    "name:por_x_preferred":[
        "Rea"
    ],
    "name:slv_x_preferred":[
        "Rea"
    ],
    "name:spa_x_preferred":[
        "Rea"
    ],
    "name:vol_x_preferred":[
        "Rea"
    ],
    "wof:name":"Rea",
    "wof:placetype":"locality"
},
  "geometry": {"coordinates":[75.57966,32.63002],"type":"Point"}
}