{
  "type": "Feature",
  "properties": {
    "gn:admin1_code":"36",
    "gn:admin2_code":"158.0",
    "gn:asciiname":"Kasimpur Baghel",
    "gn:country_code":"IN",
    "gn:dem":117,
    "gn:feature_class":"P",
    "gn:feature_code":"PPL",
    "gn:name":"K\u0101simpur Baghel",
    "gn:population":0,
    "gn:timezone":"Asia/Kolkata",
    "iso:country":"IN",
    "ks:ks_alt_nam":"K\u0101simpur Baghel",
    "ks:ks_name":"Kasimpur Baghel",
    "ks:ks_type":"VILLAGE",
    "ks:ks_uagg_main":0,
    "name:eng_x_preferred":[
        "Kasimpur Baghel"
    ],
    "name:eng_x_variant":[
        "K\u0101simpur Baghel"
    ],
    "wof:name":"Kasimpur Baghel",
    "wof:placetype":"neighbourhood"
},
  "geometry": {"coordinates":[81.329503,26.247084],"type":"Point"}
}