{
  "type": "Feature",
  "properties": {
    "gn:admin1_code":"11",
    "gn:admin2_code":"23.0",
    "gn:asciiname":"Guddan",
    "gn:country_code":"IN",
    "gn:dem":2364,
    "gn:feature_class":"P",
    "gn:feature_code":"PPL",
    "gn:name":"Guddan",
    "gn:population":0,
    "gn:timezone":"Asia/Kolkata",
    "iso:country":"IN",
    "wof:name":"Guddan",
    "wof:placetype":"locality"
},
  "geometry": {"coordinates":[76.17076999999998,32.94237],"type":"Point"}
}