{
  "type": "Feature",
  "properties": {
    "iso:country":"IN",
    "ks:ks_name":"Kadanmala",
    "ks:ks_pop":500,
    "ks:ks_type":"HABITATION",
    "name:eng_x_preferred":[
        "Kadanmala"
    ],
    "wof:name":"Kadanmala",
    "wof:placetype":"locality",
    "wof:population":500
},
  "geometry": {"coordinates":[75.790314,11.864221],"type":"Point"}
}