{
  "type": "Feature",
  "properties": {
    "iso:country":"IN",
    "ks:ks_name":"Gochuvalli",
    "ks:ks_pop":62,
    "ks:ks_type":"HABITATION",
    "name:eng_x_preferred":[
        "Gochuvalli"
    ],
    "wof:name":"Gochuvalli",
    "wof:placetype":"locality",
    "wof:population":62
},
  "geometry": {"coordinates":[75.273841,13.394803],"type":"Point"}
}