{
  "type": "Feature",
  "properties": {
    "iso:country":"IN",
    "ks:ks_name":"Bandhudih",
    "ks:ks_pop":645,
    "ks:ks_type":"HABITATION",
    "name:eng_x_preferred":[
        "Bandhudih"
    ],
    "wof:name":"Bandhudih",
    "wof:placetype":"locality",
    "wof:population":645
},
  "geometry": {"coordinates":[86.140998,23.608467],"type":"Point"}
}