{
  "type": "Feature",
  "properties": {
    "iso:country":"IN",
    "ks:ks_name":"Makrandpur Urf Fathepur",
    "ks:ks_pop":1040,
    "ks:ks_type":"HABITATION",
    "name:eng_x_preferred":[
        "Makrandpur Urf Fathepur"
    ],
    "wof:name":"Makrandpur Urf Fathepur",
    "wof:placetype":"locality",
    "wof:population":1040
},
  "geometry": {"coordinates":[77.69723500000001,28.377451],"type":"Point"}
}