{
  "type": "Feature",
  "properties": {
    "gn:admin1_code":"2.0",
    "gn:admin2_code":"552",
    "gn:asciiname":"Gattimanikonda",
    "gn:country_code":"IN",
    "gn:dem":452,
    "gn:feature_class":"P",
    "gn:feature_code":"PPL",
    "gn:name":"Gattim\u0101nikonda",
    "gn:population":0,
    "gn:timezone":"Asia/Kolkata",
    "iso:country":"IN",
    "wof:name":"Gattimanikonda",
    "wof:placetype":"neighbourhood"
},
  "geometry": {"coordinates":[78.17948,15.53208],"type":"Point"}
}