{
  "type": "Feature",
  "properties": {
    "iso:country":"IN",
    "ks:ks_name":"Lehi",
    "ks:ks_pop":246,
    "ks:ks_type":"HABITATION",
    "name:eng_x_preferred":[
        "Lehi"
    ],
    "wof:name":"Lehi",
    "wof:placetype":"locality",
    "wof:population":246
},
  "geometry": {"coordinates":[91.106131,26.244972],"type":"Point"}
}