{
  "type": "Feature",
  "properties": {
    "iso:country":"IN",
    "ks:ks_name":"Naluapara",
    "ks:ks_pop":850,
    "ks:ks_type":"HABITATION",
    "name:eng_x_preferred":[
        "Naluapara"
    ],
    "wof:name":"Naluapara",
    "wof:placetype":"locality",
    "wof:population":850
},
  "geometry": {"coordinates":[90.601479,26.067977],"type":"Point"}
}