{
  "type": "Feature",
  "properties": {
    "iso:country":"IN",
    "ks:ks_name":"Bahlolpur",
    "ks:ks_pop":1040,
    "ks:ks_type":"VILLAGE",
    "name:eng_x_preferred":[
        "Bahlolpur"
    ],
    "wof:name":"Bahlolpur",
    "wof:placetype":"locality",
    "wof:population":1040
},
  "geometry": {"coordinates":[85.032425,26.100636],"type":"Point"}
}