{
  "type": "Feature",
  "properties": {
    "gn:admin1_code":"12",
    "gn:admin2_code":"3.0",
    "gn:asciiname":"Thoise",
    "gn:country_code":"IN",
    "gn:dem":3067,
    "gn:feature_class":"P",
    "gn:feature_code":"PPL",
    "gn:name":"Thoise",
    "gn:population":0,
    "gn:timezone":"Asia/Kolkata",
    "iso:country":"IN",
    "name:deu_x_preferred":[
        "Thoise"
    ],
    "name:nor_x_preferred":[
        "Thoise"
    ],
    "name:rus_x_preferred":[
        "\u0422\u043e\u0438\u0441\u0438"
    ],
    "wof:name":"Thoise",
    "wof:placetype":"locality"
},
  "geometry": {"coordinates":[77.36121999999997,34.65679],"type":"Point"}
}