{
  "type": "Feature",
  "properties": {
    "iso:country":"IN",
    "ks:ks_name":"Halekalthodu",
    "ks:ks_pop":122,
    "ks:ks_type":"HABITATION",
    "name:eng_x_preferred":[
        "Halekalthodu"
    ],
    "wof:name":"Halekalthodu",
    "wof:placetype":"locality",
    "wof:population":122
},
  "geometry": {"coordinates":[74.679913,13.815882],"type":"Point"}
}