{
  "type": "Feature",
  "properties": {
    "iso:country":"IN",
    "ks:ks_name":"Garadeswar",
    "ks:ks_pop":737,
    "ks:ks_type":"VILLAGE",
    "name:eng_x_preferred":[
        "Garadeswar"
    ],
    "wof:name":"Garadeswar",
    "wof:placetype":"locality",
    "wof:population":737
},
  "geometry": {"coordinates":[86.376812,20.858312],"type":"Point"}
}