{
  "type": "Feature",
  "properties": {
    "iso:country":"IN",
    "ks:ks_name":"Kagli Khora",
    "ks:ks_pop":952,
    "ks:ks_type":"VILLAGE",
    "name:eng_x_preferred":[
        "Kagli Khora"
    ],
    "wof:name":"Kagli Khora",
    "wof:placetype":"locality",
    "wof:population":952
},
  "geometry": {"coordinates":[74.63490899999999,23.42385],"type":"Point"}
}