{
  "type": "Feature",
  "properties": {
    "iso:country":"IN",
    "ks:ks_name":"Patiroy",
    "ks:ks_pop":130,
    "ks:ks_type":"HABITATION",
    "name:eng_x_preferred":[
        "Patiroy"
    ],
    "wof:name":"Patiroy",
    "wof:placetype":"locality",
    "wof:population":130
},
  "geometry": {"coordinates":[91.890069,23.801667],"type":"Point"}
}