{
  "type": "Feature",
  "properties": {
    "iso:country":"IN",
    "ks:ks_name":"Bhoirpara",
    "ks:ks_pop":558,
    "ks:ks_type":"HABITATION",
    "name:eng_x_preferred":[
        "Bhoirpara"
    ],
    "wof:name":"Bhoirpara",
    "wof:placetype":"locality",
    "wof:population":558
},
  "geometry": {"coordinates":[83.329899,20.359157],"type":"Point"}
}