{
  "type": "Feature",
  "properties": {
    "iso:country":"IN",
    "ks:ks_name":"Sankatpur",
    "ks:ks_pop":964,
    "ks:ks_type":"HABITATION",
    "name:eng_x_preferred":[
        "Sankatpur"
    ],
    "wof:name":"Sankatpur",
    "wof:placetype":"locality",
    "wof:population":964
},
  "geometry": {"coordinates":[82.664225,27.386964],"type":"Point"}
}