{
  "type": "Feature",
  "properties": {
    "gn:admin1_code":"16",
    "gn:admin2_code":"511.0",
    "gn:asciiname":"Walki",
    "gn:country_code":"IN",
    "gn:dem":403,
    "gn:feature_class":"P",
    "gn:feature_code":"PPL",
    "gn:name":"W\u0101lki",
    "gn:population":0,
    "gn:timezone":"Asia/Kolkata",
    "iso:country":"IN",
    "ks:ks_alt_nam":"W\u0101lki",
    "ks:ks_name":"Walki",
    "ks:ks_pop":1647,
    "ks:ks_type":"VILLAGE",
    "name:eng_x_preferred":[
        "Walki"
    ],
    "name:eng_x_variant":[
        "W\u0101lki"
    ],
    "wof:name":"Walki",
    "wof:placetype":"locality",
    "wof:population":1647
},
  "geometry": {"coordinates":[78.01930400000001,19.39344],"type":"Point"}
}