{
  "type": "Feature",
  "properties": {
    "iso:country":"IN",
    "ks:ks_name":"Dhukrai",
    "ks:ks_type":"VILLAGE",
    "name:eng_x_preferred":[
        "Dhukrai"
    ],
    "wof:name":"Dhukrai",
    "wof:placetype":"locality"
},
  "geometry": {"coordinates":[78.31498000000001,25.336161],"type":"Point"}
}