{
  "type": "Feature",
  "properties": {
    "gn:admin1_code":"36",
    "gn:admin2_code":"167.0",
    "gn:asciiname":"Gujrati",
    "gn:country_code":"IN",
    "gn:dem":379,
    "gn:feature_class":"P",
    "gn:feature_code":"PPL",
    "gn:name":"Gujr\u0101ti",
    "gn:population":0,
    "gn:timezone":"Asia/Kolkata",
    "iso:country":"IN",
    "name:bih_x_preferred":[
        "\u0917\u0941\u091c\u0930\u093e\u0924\u0940"
    ],
    "wof:name":"Gujrati",
    "wof:placetype":"locality"
},
  "geometry": {"coordinates":[78.35544,24.74451],"type":"Point"}
}