{
  "type": "Feature",
  "properties": {
    "iso:country":"IN",
    "ks:ks_name":"Kuntodi",
    "ks:ks_pop":78,
    "ks:ks_type":"HABITATION",
    "name:eng_x_preferred":[
        "Kuntodi"
    ],
    "wof:name":"Kuntodi",
    "wof:placetype":"locality",
    "wof:population":78
},
  "geometry": {"coordinates":[74.661061,14.228698],"type":"Point"}
}