{
  "type": "Feature",
  "properties": {
    "iso:country":"IN",
    "ks:ks_alt_nam":"Kumhar tola",
    "ks:ks_name":"Kumhar Tola",
    "ks:ks_pop":104,
    "ks:ks_type":"HABITATION",
    "name:eng_x_preferred":[
        "Kumhar Tola"
    ],
    "wof:name":"Kumhar Tola",
    "wof:placetype":"locality",
    "wof:population":104
},
  "geometry": {"coordinates":[85.993241,24.559417],"type":"Point"}
}