{
  "type": "Feature",
  "properties": {
    "iso:country":"IN",
    "ks:ks_name":"Manburu",
    "ks:ks_pop":249,
    "ks:ks_type":"HABITATION",
    "name:eng_x_preferred":[
        "Manburu"
    ],
    "wof:name":"Manburu",
    "wof:placetype":"locality",
    "wof:population":249
},
  "geometry": {"coordinates":[85.68074900000001,22.256285],"type":"Point"}
}