{
  "type": "Feature",
  "properties": {
    "iso:country":"IN",
    "ks:ks_name":"Sialia A",
    "ks:ks_pop":624,
    "ks:ks_type":"VILLAGE",
    "name:eng_x_preferred":[
        "Sialia A"
    ],
    "wof:name":"Sialia A",
    "wof:placetype":"locality",
    "wof:population":624
},
  "geometry": {"coordinates":[86.66866400000001,21.70301],"type":"Point"}
}