{
  "type": "Feature",
  "properties": {
    "gn:admin1_code":"2",
    "gn:admin2_code":"546.0",
    "gn:asciiname":"Gollapudi",
    "gn:country_code":"IN",
    "gn:dem":143,
    "gn:feature_class":"P",
    "gn:feature_code":"PPL",
    "gn:name":"Gollap\u016bdi",
    "gn:population":0,
    "gn:timezone":"Asia/Kolkata",
    "iso:country":"IN",
    "ks:ks_name":"Gullapudi",
    "ks:ks_pop":652,
    "ks:ks_type":"HABITATION",
    "name:eng_x_preferred":[
        "Gullapudi"
    ],
    "name:eng_x_variant":[
        "Gollapudi"
    ],
    "name:tel_x_preferred":[
        "\u0c17\u0c4a\u0c32\u0c4d\u0c32\u0c2a\u0c42\u0c21\u0c3f"
    ],
    "wof:name":"Gullapudi",
    "wof:placetype":"locality",
    "wof:population":652
},
  "geometry": {"coordinates":[80.88216799999999,17.115241],"type":"Point"}
}