{
  "type": "Feature",
  "properties": {
    "iso:country":"IN",
    "ks:ks_name":"Chirandha",
    "ks:ks_pop":156,
    "ks:ks_type":"HABITATION",
    "ks:ks_uagg_main":0,
    "name:eng_x_preferred":[
        "Chirandha"
    ],
    "wof:name":"Chirandha",
    "wof:placetype":"neighbourhood",
    "wof:population":156
},
  "geometry": {"coordinates":[81.459181,26.347836],"type":"Point"}
}