{
  "type": "Feature",
  "properties": {
    "iso:country":"IN",
    "ks:ks_name":"Haalkuni",
    "ks:ks_pop":97,
    "ks:ks_type":"HABITATION",
    "name:eng_x_preferred":[
        "Haalkuni"
    ],
    "wof:name":"Haalkuni",
    "wof:placetype":"locality",
    "wof:population":97
},
  "geometry": {"coordinates":[75.33863599999999,14.087774],"type":"Point"}
}