{
  "type": "Feature",
  "properties": {
    "iso:country":"IN",
    "ks:ks_name":"Dakshinpara",
    "ks:ks_pop":1297,
    "ks:ks_type":"HABITATION",
    "ks:ks_uagg_main":0,
    "name:eng_x_preferred":[
        "Dakshinpara"
    ],
    "wof:name":"Dakshinpara",
    "wof:placetype":"locality",
    "wof:population":1297
},
  "geometry": {"coordinates":[88.231319,22.809718],"type":"Point"}
}