{
  "type": "Feature",
  "properties": {
    "gn:admin1_code":"25.0",
    "gn:admin2_code":"620.0",
    "gn:asciiname":"Srinivasanallur",
    "gn:country_code":"IN",
    "gn:dem":27,
    "gn:feature_class":"P",
    "gn:feature_code":"PPL",
    "gn:name":"Sr\u012bniv\u0101sanall\u016br",
    "gn:population":0,
    "gn:timezone":"Asia/Kolkata",
    "iso:country":"IN",
    "wof:name":"Srinivasanallur",
    "wof:placetype":"neighbourhood"
},
  "geometry": {"coordinates":[79.44164000000001,10.93864],"type":"Point"}
}