{
  "type": "Feature",
  "properties": {
    "iso:country":"IN",
    "ks:ks_name":"Bela Bigha",
    "ks:ks_pop":250,
    "ks:ks_type":"HABITATION",
    "name:eng_x_preferred":[
        "Bela Bigha"
    ],
    "wof:name":"Bela Bigha",
    "wof:placetype":"locality",
    "wof:population":250
},
  "geometry": {"coordinates":[84.49805499999999,25.02001],"type":"Point"}
}