{
  "type": "Feature",
  "properties": {
    "iso:country":"IN",
    "ks:ks_name":"Pamba Dam Area",
    "ks:ks_pop":205,
    "ks:ks_type":"HABITATION",
    "name:eng_x_preferred":[
        "Pamba Dam Area"
    ],
    "wof:name":"Pamba Dam Area",
    "wof:placetype":"locality",
    "wof:population":205
},
  "geometry": {"coordinates":[77.156494,9.387306],"type":"Point"}
}