{
  "type": "Feature",
  "properties": {
    "iso:country":"IN",
    "ks:ks_name":"N S Nagar",
    "ks:ks_pop":494,
    "ks:ks_type":"HABITATION",
    "ks:ks_uagg_main":0,
    "name:eng_x_preferred":[
        "N S Nagar"
    ],
    "wof:name":"N S Nagar",
    "wof:placetype":"locality",
    "wof:population":494
},
  "geometry": {"coordinates":[77.99745799999999,10.389209],"type":"Point"}
}