{
  "type": "Feature",
  "properties": {
    "iso:country":"IN",
    "ks:ks_name":"Kachhara",
    "ks:ks_pop":3055,
    "ks:ks_type":"VILLAGE",
    "ks:ks_uagg_main":0,
    "name:eng_x_preferred":[
        "Kachhara"
    ],
    "wof:name":"Kachhara",
    "wof:placetype":"neighbourhood",
    "wof:population":3055
},
  "geometry": {"coordinates":[85.887417,26.442192],"type":"Point"}
}