{
  "type": "Feature",
  "properties": {
    "iso:country":"IN",
    "ks:ks_name":"Suknokhali",
    "ks:ks_pop":603,
    "ks:ks_type":"VILLAGE",
    "name:eng_x_preferred":[
        "Suknokhali"
    ],
    "wof:name":"Suknokhali",
    "wof:placetype":"locality",
    "wof:population":603
},
  "geometry": {"coordinates":[87.081075,22.879258],"type":"Point"}
}