{
  "type": "Feature",
  "properties": {
    "gn:admin1_code":"23",
    "gn:admin2_code":"49.0",
    "gn:asciiname":"Verka",
    "gn:country_code":"IN",
    "gn:dem":236,
    "gn:feature_class":"P",
    "gn:feature_code":"PPL",
    "gn:name":"Verka",
    "gn:population":0,
    "gn:timezone":"Asia/Kolkata",
    "iso:country":"IN",
    "ks:ks_name":"Verka",
    "ks:ks_type":"VILLAGE",
    "ks:ks_uagg_main":0,
    "name:mkd_x_preferred":[
        "\u0412\u0435\u0440\u043a\u0430"
    ],
    "wof:name":"Verka",
    "wof:placetype":"neighbourhood"
},
  "geometry": {"coordinates":[74.93626999999999,31.66468],"type":"Point"}
}