{
  "type": "Feature",
  "properties": {
    "iso:country":"IN",
    "ks:ks_name":"Mahuapara",
    "ks:ks_pop":26,
    "ks:ks_type":"HABITATION",
    "name:eng_x_preferred":[
        "Mahuapara"
    ],
    "wof:name":"Mahuapara",
    "wof:placetype":"locality",
    "wof:population":26
},
  "geometry": {"coordinates":[82.37669200000001,22.845089],"type":"Point"}
}