{
  "type": "Feature",
  "properties": {
    "gn:admin1_code":"36",
    "gn:admin2_code":"178.0",
    "gn:asciiname":"Shankarpur Agilwabir",
    "gn:country_code":"IN",
    "gn:dem":87,
    "gn:feature_class":"P",
    "gn:feature_code":"PPL",
    "gn:name":"Shankarpur Agilw\u0101b\u012br",
    "gn:population":0,
    "gn:timezone":"Asia/Kolkata",
    "iso:country":"IN",
    "wof:name":"Shankarpur Agilwabir",
    "wof:placetype":"locality"
},
  "geometry": {"coordinates":[82.96779000000002,26.4732],"type":"Point"}
}