{
  "type": "Feature",
  "properties": {
    "iso:country":"IN",
    "ks:ks_name":"Ismil Nagar Siroha",
    "ks:ks_type":"VILLAGE",
    "name:eng_x_preferred":[
        "Ismil Nagar Siroha"
    ],
    "wof:name":"Ismil Nagar Siroha",
    "wof:placetype":"locality"
},
  "geometry": {"coordinates":[81.866302,26.829749],"type":"Point"}
}