{
  "type": "Feature",
  "properties": {
    "gn:admin1_code":"25.0",
    "gn:admin2_code":"608.0",
    "gn:asciiname":"Upparappatti",
    "gn:country_code":"IN",
    "gn:dem":232,
    "gn:feature_class":"P",
    "gn:feature_code":"PPL",
    "gn:name":"Upp\u0101rappatti",
    "gn:population":0,
    "gn:timezone":"Asia/Kolkata",
    "iso:country":"IN",
    "wof:name":"Upparappatti",
    "wof:placetype":"locality"
},
  "geometry": {"coordinates":[77.91871,11.64833],"type":"Point"}
}