{
  "type": "Feature",
  "properties": {
    "gn:admin1_code":"24.0",
    "gn:admin2_code":"130",
    "gn:asciiname":"Gogunda",
    "gn:country_code":"IN",
    "gn:dem":840,
    "gn:feature_class":"P",
    "gn:feature_code":"PPL",
    "gn:name":"Gog\u016bnda",
    "gn:population":0,
    "gn:timezone":"Asia/Kolkata",
    "iso:country":"IN",
    "name:cat_x_preferred":[
        "Gogunda"
    ],
    "name:ceb_x_preferred":[
        "Gog\u016bnda"
    ],
    "name:hin_x_preferred":[
        "\u0917\u094b\u0917\u0941\u0928\u094d\u0926\u093e"
    ],
    "name:swe_x_preferred":[
        "Gog\u016bnda"
    ],
    "wof:name":"Gogunda",
    "wof:placetype":"locality"
},
  "geometry": {"coordinates":[73.52981,24.75844],"type":"Point"}
}