{
  "type": "Feature",
  "properties": {
    "iso:country":"IN",
    "ks:ks_name":"Savargharata",
    "ks:ks_pop":300,
    "ks:ks_type":"HABITATION",
    "name:eng_x_preferred":[
        "Savargharata"
    ],
    "wof:name":"Savargharata",
    "wof:placetype":"locality",
    "wof:population":300
},
  "geometry": {"coordinates":[73.257193,20.048593],"type":"Point"}
}