{
  "type": "Feature",
  "properties": {
    "iso:country":"IN",
    "ks:ks_name":"Surahapur (jhurhapur)",
    "ks:ks_pop":85,
    "ks:ks_type":"HABITATION",
    "name:eng_x_preferred":[
        "Surahapur (jhurhapur)"
    ],
    "wof:name":"Surahapur (jhurhapur)",
    "wof:placetype":"locality",
    "wof:population":85
},
  "geometry": {"coordinates":[81.035662,25.542627],"type":"Point"}
}