{
  "type": "Feature",
  "properties": {
    "iso:country":"IN",
    "ks:ks_name":"Kothuru",
    "ks:ks_pop":59,
    "ks:ks_type":"HABITATION",
    "name:eng_x_preferred":[
        "Kothuru"
    ],
    "wof:name":"Kothuru",
    "wof:placetype":"locality",
    "wof:population":59
},
  "geometry": {"coordinates":[82.768884,17.928848],"type":"Point"}
}