{
  "type": "Feature",
  "properties": {
    "iso:country":"IN",
    "ks:ks_name":"Sirtoli",
    "ks:ks_pop":95,
    "ks:ks_type":"VILLAGE",
    "name:eng_x_preferred":[
        "Sirtoli"
    ],
    "wof:name":"Sirtoli",
    "wof:placetype":"locality",
    "wof:population":95
},
  "geometry": {"coordinates":[80.319987,29.794345],"type":"Point"}
}