{
  "type": "Feature",
  "properties": {
    "iso:country":"IN",
    "ks:ks_name":"Lumbaniya Ki Dhani",
    "ks:ks_pop":396,
    "ks:ks_type":"VILLAGE",
    "name:eng_x_preferred":[
        "Lumbaniya Ki Dhani"
    ],
    "wof:name":"Lumbaniya Ki Dhani",
    "wof:placetype":"locality",
    "wof:population":396
},
  "geometry": {"coordinates":[72.099158,26.058269],"type":"Point"}
}