{
  "type": "Feature",
  "properties": {
    "gn:admin1_code":"24.0",
    "gn:admin2_code":"110",
    "gn:asciiname":"Kishorpura",
    "gn:country_code":"IN",
    "gn:dem":427,
    "gn:feature_class":"P",
    "gn:feature_code":"PPL",
    "gn:name":"Kishorpura",
    "gn:population":0,
    "gn:timezone":"Asia/Kolkata",
    "iso:country":"IN",
    "name:und_x_variant":[
        "Kishor\u012bpura"
    ],
    "wof:name":"Kishorpura",
    "wof:placetype":"locality"
},
  "geometry": {"coordinates":[75.66501,26.94629],"type":"Point"}
}