{
  "type": "Feature",
  "properties": {
    "iso:country":"IN",
    "ks:ks_name":"Pipal Khunta",
    "ks:ks_pop":10,
    "ks:ks_type":"VILLAGE",
    "name:eng_x_preferred":[
        "Pipal Khunta"
    ],
    "wof:name":"Pipal Khunta",
    "wof:placetype":"locality",
    "wof:population":10
},
  "geometry": {"coordinates":[75.17334200000001,22.973327],"type":"Point"}
}