{
  "type": "Feature",
  "properties": {
    "iso:country":"IN",
    "ks:ks_name":"Barhampur",
    "ks:ks_pop":46,
    "ks:ks_type":"VILLAGE",
    "name:eng_x_preferred":[
        "Barhampur"
    ],
    "wof:name":"Barhampur",
    "wof:placetype":"locality",
    "wof:population":46
},
  "geometry": {"coordinates":[85.181577,26.444209],"type":"Point"}
}