{
  "type": "Feature",
  "properties": {
    "iso:country":"IN",
    "ks:ks_name":"Duggaramakki",
    "ks:ks_pop":102,
    "ks:ks_type":"HABITATION",
    "name:eng_x_preferred":[
        "Duggaramakki"
    ],
    "wof:name":"Duggaramakki",
    "wof:placetype":"locality",
    "wof:population":102
},
  "geometry": {"coordinates":[74.948193,13.525974],"type":"Point"}
}