{
  "type": "Feature",
  "properties": {
    "iso:country":"IN",
    "ks:ks_name":"Madgi Bedo",
    "ks:ks_pop":46,
    "ks:ks_type":"VILLAGE",
    "name:eng_x_preferred":[
        "Madgi Bedo"
    ],
    "wof:name":"Madgi Bedo",
    "wof:placetype":"locality",
    "wof:population":46
},
  "geometry": {"coordinates":[87.454196,24.831245],"type":"Point"}
}