{
  "type": "Feature",
  "properties": {
    "gn:admin1_code":"23.0",
    "gn:admin2_code":"35.0",
    "gn:asciiname":"Nabipur",
    "gn:country_code":"IN",
    "gn:dem":259,
    "gn:feature_class":"P",
    "gn:feature_code":"PPL",
    "gn:name":"Nabipur",
    "gn:population":0,
    "gn:timezone":"Asia/Kolkata",
    "iso:country":"IN",
    "ks:ks_name":"Nabipur",
    "ks:ks_pop":2190,
    "ks:ks_type":"VILLAGE",
    "ks:ks_uagg_main":0,
    "name:eng_x_preferred":[
        "Nabipur"
    ],
    "wof:name":"Nabipur",
    "wof:placetype":"locality",
    "wof:population":2190
},
  "geometry": {"coordinates":[75.381682,32.031206],"type":"Point"}
}