{
  "type": "Feature",
  "properties": {
    "iso:country":"IN",
    "ks:ks_name":"Thaggihallikaval",
    "ks:ks_pop":2,
    "ks:ks_type":"VILLAGE",
    "name:eng_x_preferred":[
        "Thaggihallikaval"
    ],
    "wof:name":"Thaggihallikaval",
    "wof:placetype":"locality",
    "wof:population":2
},
  "geometry": {"coordinates":[76.274737,13.598974],"type":"Point"}
}