{
  "type": "Feature",
  "properties": {
    "iso:country":"IN",
    "ks:ks_name":"Kheta Purwa",
    "ks:ks_pop":244,
    "ks:ks_type":"HABITATION",
    "ks:ks_uagg_main":0,
    "name:eng_x_preferred":[
        "Kheta Purwa"
    ],
    "wof:name":"Kheta Purwa",
    "wof:placetype":"neighbourhood",
    "wof:population":244
},
  "geometry": {"coordinates":[80.129462,26.966377],"type":"Point"}
}