{
  "type": "Feature",
  "properties": {
    "gn:admin1_code":"34.0",
    "gn:admin2_code":"237.0",
    "gn:asciiname":"Khalkhu",
    "gn:country_code":"IN",
    "gn:dem":125,
    "gn:feature_class":"P",
    "gn:feature_code":"PPL",
    "gn:name":"Khalkhu",
    "gn:population":0,
    "gn:timezone":"Asia/Kolkata",
    "iso:country":"IN",
    "ks:ks_name":"Khalkhu",
    "ks:ks_pop":381,
    "ks:ks_type":"VILLAGE",
    "ks:ks_uagg_main":0,
    "name:eng_x_preferred":[
        "Khalkhu"
    ],
    "wof:name":"Khalkhu",
    "wof:placetype":"neighbourhood",
    "wof:population":381
},
  "geometry": {"coordinates":[85.39423600000001,24.697306],"type":"Point"}
}