{
  "type": "Feature",
  "properties": {
    "iso:country":"IN",
    "ks:ks_name":"Devipur",
    "ks:ks_pop":230,
    "ks:ks_type":"HABITATION",
    "name:eng_x_preferred":[
        "Devipur"
    ],
    "wof:name":"Devipur",
    "wof:placetype":"locality",
    "wof:population":230
},
  "geometry": {"coordinates":[81.469052,25.105596],"type":"Point"}
}