{
  "type": "Feature",
  "properties": {
    "gn:admin1_code":"37.0",
    "gn:admin2_code":"413.0",
    "gn:asciiname":"Albera",
    "gn:country_code":"IN",
    "gn:dem":424,
    "gn:feature_class":"P",
    "gn:feature_code":"PPL",
    "gn:name":"\u0100lbera",
    "gn:population":0,
    "gn:timezone":"Asia/Kolkata",
    "iso:country":"IN",
    "name:cat_x_preferred":[
        "Albera"
    ],
    "name:deu_x_preferred":[
        "Albera"
    ],
    "name:ita_x_preferred":[
        "Albera"
    ],
    "name:srp_x_preferred":[
        "Albera"
    ],
    "wof:name":"Albera",
    "wof:placetype":"locality"
},
  "geometry": {"coordinates":[81.36125,20.28001],"type":"Point"}
}