{
  "type": "Feature",
  "properties": {
    "iso:country":"IN",
    "ks:ks_name":"Mavaltiwadi Boudhawadi",
    "ks:ks_pop":545,
    "ks:ks_type":"HABITATION",
    "name:eng_x_preferred":[
        "Mavaltiwadi Boudhawadi"
    ],
    "wof:name":"Mavaltiwadi Boudhawadi",
    "wof:placetype":"locality",
    "wof:population":545
},
  "geometry": {"coordinates":[73.694925,17.037472],"type":"Point"}
}