{
  "type": "Feature",
  "properties": {
    "iso:country":"IN",
    "ks:ks_name":"Amlabhata",
    "ks:ks_pop":498,
    "ks:ks_type":"VILLAGE",
    "name:eng_x_preferred":[
        "Amlabhata"
    ],
    "wof:name":"Amlabhata",
    "wof:placetype":"locality",
    "wof:population":498
},
  "geometry": {"coordinates":[82.08642399999999,19.72228],"type":"Point"}
}