{
  "type": "Feature",
  "properties": {
    "iso:country":"IN",
    "ks:ks_name":"Majigurupura",
    "ks:ks_pop":998,
    "ks:ks_type":"HABITATION",
    "name:eng_x_preferred":[
        "Majigurupura"
    ],
    "wof:name":"Majigurupura",
    "wof:placetype":"locality",
    "wof:population":998
},
  "geometry": {"coordinates":[76.284352,12.206851],"type":"Point"}
}