{
  "type": "Feature",
  "properties": {
    "gn:admin1_code":"12.0",
    "gn:asciiname":"Jhugian",
    "gn:country_code":"IN",
    "gn:dem":1736,
    "gn:feature_class":"P",
    "gn:feature_code":"PPL",
    "gn:name":"Jhugi\u0101n",
    "gn:population":0,
    "gn:timezone":"Asia/Karachi",
    "iso:country":"IN",
    "wof:name":"Jhugian",
    "wof:placetype":"locality"
},
  "geometry": {"coordinates":[73.77585999999999,34.35543],"type":"Point"}
}