{
  "type": "Feature",
  "properties": {
    "iso:country":"IN",
    "ks:ks_alt_nam":"YADAV TOLA",
    "ks:ks_name":"Yadav Tola",
    "ks:ks_pop":287,
    "ks:ks_type":"HABITATION",
    "ks:ks_uagg_main":0,
    "name:eng_x_preferred":[
        "Yadav Tola"
    ],
    "wof:name":"Yadav Tola",
    "wof:placetype":"neighbourhood",
    "wof:population":287
},
  "geometry": {"coordinates":[86.604473,26.307808],"type":"Point"}
}