{
  "type": "Feature",
  "properties": {
    "iso:country":"IN",
    "ks:ks_name":"Tavapalli",
    "ks:ks_pop":710,
    "ks:ks_type":"VILLAGE",
    "ks:ks_uagg_main":0,
    "name:eng_x_preferred":[
        "Tavapalli"
    ],
    "wof:name":"Tavapalli",
    "wof:placetype":"neighbourhood",
    "wof:population":710
},
  "geometry": {"coordinates":[84.82677099999999,19.857237],"type":"Point"}
}