{
  "type": "Feature",
  "properties": {
    "iso:country":"IN",
    "ks:ks_name":"Chautarwa",
    "ks:ks_pop":2268,
    "ks:ks_type":"VILLAGE",
    "name:eng_x_preferred":[
        "Chautarwa"
    ],
    "wof:name":"Chautarwa",
    "wof:placetype":"locality",
    "wof:population":2268
},
  "geometry": {"coordinates":[84.252892,27.126085],"type":"Point"}
}