{
  "type": "Feature",
  "properties": {
    "iso:country":"IN",
    "ks:ks_alt_nam":"dersi",
    "ks:ks_name":"Dersi",
    "ks:ks_pop":276,
    "ks:ks_type":"HABITATION",
    "ks:ks_uagg_main":0,
    "name:eng_x_preferred":[
        "Dersi"
    ],
    "wof:name":"Dersi",
    "wof:placetype":"neighbourhood",
    "wof:population":276
},
  "geometry": {"coordinates":[92.986003,25.369452],"type":"Point"}
}