{
  "type": "Feature",
  "properties": {
    "iso:country":"IN",
    "ks:ks_name":"Thiru Nagar",
    "ks:ks_pop":274,
    "ks:ks_type":"HABITATION",
    "ks:ks_uagg_main":0,
    "name:eng_x_preferred":[
        "Thiru Nagar"
    ],
    "wof:name":"Thiru Nagar",
    "wof:placetype":"locality",
    "wof:population":274
},
  "geometry": {"coordinates":[78.56797400000001,9.561665],"type":"Point"}
}