{
  "type": "Feature",
  "properties": {
    "gn:admin1_code":"11.0",
    "gn:admin2_code":"31.0",
    "gn:asciiname":"Chauki",
    "gn:country_code":"IN",
    "gn:dem":1656,
    "gn:feature_class":"P",
    "gn:feature_code":"PPL",
    "gn:name":"Chauki",
    "gn:population":0,
    "gn:timezone":"Asia/Kolkata",
    "iso:country":"IN",
    "wof:name":"Chauki",
    "wof:placetype":"locality"
},
  "geometry": {"coordinates":[77.17471,30.98514],"type":"Point"}
}