{
  "type": "Feature",
  "properties": {
    "iso:country":"IN",
    "ks:ks_name":"Golliangadi",
    "ks:ks_pop":240,
    "ks:ks_type":"HABITATION",
    "name:eng_x_preferred":[
        "Golliangadi"
    ],
    "wof:name":"Golliangadi",
    "wof:placetype":"locality",
    "wof:population":240
},
  "geometry": {"coordinates":[74.90401199999999,13.564518],"type":"Point"}
}