{
  "type": "Feature",
  "properties": {
    "iso:country":"IN",
    "ks:ks_name":"Kamal Tola",
    "ks:ks_pop":909,
    "ks:ks_type":"HABITATION",
    "name:eng_x_preferred":[
        "Kamal Tola"
    ],
    "wof:name":"Kamal Tola",
    "wof:placetype":"locality",
    "wof:population":909
},
  "geometry": {"coordinates":[84.82054100000001,25.573859],"type":"Point"}
}