{
  "type": "Feature",
  "properties": {
    "iso:country":"IN",
    "ks:ks_name":"Harijanpura",
    "ks:ks_pop":209,
    "ks:ks_type":"HABITATION",
    "name:eng_x_preferred":[
        "Harijanpura"
    ],
    "wof:name":"Harijanpura",
    "wof:placetype":"locality",
    "wof:population":209
},
  "geometry": {"coordinates":[72.235429,24.187033],"type":"Point"}
}