{
  "type": "Feature",
  "properties": {
    "iso:country":"IN",
    "ks:ks_name":"Thoppampatti",
    "ks:ks_pop":249,
    "ks:ks_type":"HABITATION",
    "name:eng_x_preferred":[
        "Thoppampatti"
    ],
    "wof:name":"Thoppampatti",
    "wof:placetype":"locality",
    "wof:population":249
},
  "geometry": {"coordinates":[78.43427699999999,10.545029],"type":"Point"}
}