{
  "type": "Feature",
  "properties": {
    "iso:country":"IN",
    "ks:ks_name":"Keora Kalan",
    "ks:ks_pop":450,
    "ks:ks_type":"VILLAGE",
    "ks:ks_uagg_main":0,
    "name:eng_x_preferred":[
        "Keora Kalan"
    ],
    "wof:name":"Keora Kalan",
    "wof:placetype":"neighbourhood",
    "wof:population":450
},
  "geometry": {"coordinates":[73.768244,24.416758],"type":"Point"}
}