{
  "type": "Feature",
  "properties": {
    "gn:admin1_code":"34.0",
    "gn:admin2_code":"236.0",
    "gn:asciiname":"Murahi",
    "gn:country_code":"IN",
    "gn:dem":138,
    "gn:feature_class":"P",
    "gn:feature_code":"PPL",
    "gn:name":"Murahi",
    "gn:population":0,
    "gn:timezone":"Asia/Kolkata",
    "iso:country":"IN",
    "ks:ks_name":"Murahi",
    "ks:ks_type":"VILLAGE",
    "ks:ks_uagg_main":0,
    "name:eng_x_preferred":[
        "Murahi"
    ],
    "wof:name":"Murahi",
    "wof:placetype":"neighbourhood"
},
  "geometry": {"coordinates":[84.789545,24.636355],"type":"Point"}
}