{
  "type": "Feature",
  "properties": {
    "iso:country":"IN",
    "ks:ks_name":"Nittamamidi Palem",
    "ks:ks_pop":241,
    "ks:ks_type":"VILLAGE",
    "name:eng_x_preferred":[
        "Nittamamidi Palem"
    ],
    "wof:name":"Nittamamidi Palem",
    "wof:placetype":"locality",
    "wof:population":241
},
  "geometry": {"coordinates":[82.315805,17.943624],"type":"Point"}
}