{
  "type": "Feature",
  "properties": {
    "gn:admin1_code":"38.0",
    "gn:admin2_code":"358.0",
    "gn:asciiname":"Patkhaulia",
    "gn:country_code":"IN",
    "gn:dem":266,
    "gn:feature_class":"P",
    "gn:feature_code":"PPL",
    "gn:name":"Patkhaul\u012b\u0101",
    "gn:population":0,
    "gn:timezone":"Asia/Kolkata",
    "iso:country":"IN",
    "ks:ks_name":"Patkhauliya",
    "ks:ks_pop":170,
    "ks:ks_type":"VILLAGE",
    "ks:ks_uagg_main":0,
    "name:eng_x_preferred":[
        "Patkhauliya"
    ],
    "wof:name":"Patkhauliya",
    "wof:placetype":"neighbourhood",
    "wof:population":170
},
  "geometry": {"coordinates":[84.280348,24.027627],"type":"Point"}
}