{
  "type": "Feature",
  "properties": {
    "iso:country":"IN",
    "ks:ks_name":"Jhelam",
    "ks:ks_pop":660,
    "ks:ks_type":"VILLAGE",
    "name:eng_x_preferred":[
        "Jhelam"
    ],
    "wof:name":"Jhelam",
    "wof:placetype":"locality",
    "wof:population":660
},
  "geometry": {"coordinates":[78.54350599999999,30.322973],"type":"Point"}
}