{
  "type": "Feature",
  "properties": {
    "gn:admin1_code":"2",
    "gn:admin2_code":"545.0",
    "gn:asciiname":"Babbilova",
    "gn:country_code":"IN",
    "gn:dem":922,
    "gn:feature_class":"P",
    "gn:feature_code":"PPL",
    "gn:name":"Babbilova",
    "gn:population":0,
    "gn:timezone":"Asia/Kolkata",
    "iso:country":"IN",
    "wof:name":"Babbilova",
    "wof:placetype":"locality"
},
  "geometry": {"coordinates":[81.89253000000002,17.81447],"type":"Point"}
}