{
  "type": "Feature",
  "properties": {
    "gn:admin1_code":"2",
    "gn:admin2_code":"545.0",
    "gn:asciiname":"Babbilova",
    "gn:country_code":"IN",
    "gn:dem":922,
    "gn:feature_class":"P",
    "gn:feature_code":"PPL",
    "gn:name":"Babbilova",
    "gn:population":0,
    "gn:timezone":"Asia/Kolkata",
    "iso:country":"IN",
    "ks:ks_name":"Bobbilova",
    "ks:ks_pop":210,
    "ks:ks_type":"HABITATION",
    "name:eng_x_preferred":[
        "Bobbilova"
    ],
    "name:eng_x_variant":[
        "Babbilova"
    ],
    "wof:name":"Bobbilova",
    "wof:placetype":"locality",
    "wof:population":210
},
  "geometry": {"coordinates":[81.88936,17.812282],"type":"Point"}
}