{
  "type": "Feature",
  "properties": {
    "iso:country":"IN",
    "ks:ks_name":"Tikhipara",
    "ks:ks_pop":164,
    "ks:ks_type":"HABITATION",
    "name:eng_x_preferred":[
        "Tikhipara"
    ],
    "wof:name":"Tikhipara",
    "wof:placetype":"locality",
    "wof:population":164
},
  "geometry": {"coordinates":[74.946894,23.008869],"type":"Point"}
}