{
  "type": "Feature",
  "properties": {
    "iso:country":"IN",
    "ks:ks_alt_nam":"FAKIR PARA",
    "ks:ks_name":"Fakir Para",
    "ks:ks_pop":412,
    "ks:ks_type":"HABITATION",
    "name:eng_x_preferred":[
        "Fakir Para"
    ],
    "wof:name":"Fakir Para",
    "wof:placetype":"locality",
    "wof:population":412
},
  "geometry": {"coordinates":[88.718861,26.452076],"type":"Point"}
}