{
  "type": "Feature",
  "properties": {
    "iso:country":"IN",
    "ks:ks_name":"Khairamara",
    "ks:ks_pop":37,
    "ks:ks_type":"HABITATION",
    "name:eng_x_preferred":[
        "Khairamara"
    ],
    "wof:name":"Khairamara",
    "wof:placetype":"locality",
    "wof:population":37
},
  "geometry": {"coordinates":[86.652258,23.114341],"type":"Point"}
}