{
  "type": "Feature",
  "properties": {
    "iso:country":"IN",
    "ks:ks_name":"Nandanahitlu",
    "ks:ks_pop":100,
    "ks:ks_type":"HABITATION",
    "name:eng_x_preferred":[
        "Nandanahitlu"
    ],
    "wof:name":"Nandanahitlu",
    "wof:placetype":"locality",
    "wof:population":100
},
  "geometry": {"coordinates":[75.155706,13.01665],"type":"Point"}
}