{
  "type": "Feature",
  "properties": {
    "iso:country":"IN",
    "ks:ks_name":"Gummanuyenglapur",
    "ks:ks_pop":429,
    "ks:ks_type":"VILLAGE",
    "name:eng_x_preferred":[
        "Gummanuyenglapur"
    ],
    "wof:name":"Gummanuyenglapur",
    "wof:placetype":"locality",
    "wof:population":429
},
  "geometry": {"coordinates":[78.64630699999999,19.257395],"type":"Point"}
}