{
  "type": "Feature",
  "properties": {
    "iso:country":"IN",
    "ks:ks_name":"Manikdih",
    "ks:ks_pop":419,
    "ks:ks_type":"VILLAGE",
    "ks:ks_uagg_main":0,
    "name:eng_x_preferred":[
        "Manikdih"
    ],
    "wof:name":"Manikdih",
    "wof:placetype":"neighbourhood",
    "wof:population":419
},
  "geometry": {"coordinates":[84.322902,23.865915],"type":"Point"}
}