{
  "type": "Feature",
  "properties": {
    "gn:admin1_code":"35",
    "gn:admin2_code":"464.0",
    "gn:asciiname":"Chhain",
    "gn:country_code":"IN",
    "gn:dem":277,
    "gn:feature_class":"P",
    "gn:feature_code":"PPL",
    "gn:name":"Chhain",
    "gn:population":0,
    "gn:timezone":"Asia/Kolkata",
    "iso:country":"IN",
    "wof:name":"Chhain",
    "wof:placetype":"locality"
},
  "geometry": {"coordinates":[74.35812,23.07546],"type":"Point"}
}