{
  "type": "Feature",
  "properties": {
    "gn:admin1_code":"12.0",
    "gn:admin2_code":"18.0",
    "gn:asciiname":"Golo",
    "gn:country_code":"IN",
    "gn:dem":2028,
    "gn:feature_class":"P",
    "gn:feature_code":"PPL",
    "gn:name":"Golo",
    "gn:population":0,
    "gn:timezone":"Asia/Kolkata",
    "iso:country":"IN",
    "name:ceb_x_preferred":[
        "Golo"
    ],
    "name:deu_x_preferred":[
        "Golo"
    ],
    "name:fin_x_preferred":[
        "Golo"
    ],
    "name:fra_x_preferred":[
        "Golo"
    ],
    "name:nld_x_preferred":[
        "Golo"
    ],
    "name:swe_x_preferred":[
        "Golo"
    ],
    "wof:name":"Golo",
    "wof:placetype":"locality"
},
  "geometry": {"coordinates":[75.88032,33.14293],"type":"Point"}
}