{
  "type": "Feature",
  "properties": {
    "iso:country":"IN",
    "ks:ks_name":"Dandanhwa Tola",
    "ks:ks_pop":378,
    "ks:ks_type":"HABITATION",
    "name:eng_x_preferred":[
        "Dandanhwa Tola"
    ],
    "wof:name":"Dandanhwa Tola",
    "wof:placetype":"locality",
    "wof:population":378
},
  "geometry": {"coordinates":[83.433065,27.179058],"type":"Point"}
}