{
  "type": "Feature",
  "properties": {
    "gn:admin1_code":"16",
    "gn:admin2_code":"505.0",
    "gn:asciiname":"Mogra",
    "gn:country_code":"IN",
    "gn:dem":349,
    "gn:feature_class":"P",
    "gn:feature_code":"PPL",
    "gn:name":"Mogra",
    "gn:population":0,
    "gn:timezone":"Asia/Kolkata",
    "iso:country":"IN",
    "name:ara_x_preferred":[
        "\u0645\u0648\u063a\u0631\u0627"
    ],
    "name:ben_bn_x_preferred":[
        "\u09ae\u09cb\u0997\u09b0\u09be"
    ],
    "name:ben_in_x_preferred":[
        "\u09ae\u09cb\u0997\u09b0\u09be"
    ],
    "name:guj_x_preferred":[
        "\u0aae\u0acb\u0a97\u0ab0\u0abe"
    ],
    "name:hin_x_preferred":[
        "\u092e\u094b\u0917\u0930\u093e"
    ],
    "name:kan_x_preferred":[
        "\u0cae\u0ccb\u0c97\u0ccd\u0cb0\u0cbe"
    ],
    "name:mal_x_preferred":[
        "\u0d2e\u0d4b\u0d17\u0d4d\u0d30"
    ],
    "name:mar_x_preferred":[
        "\u092e\u094b\u0917\u0930\u093e"
    ],
    "name:pan_x_preferred":[
        "\u0a2e\u0a4b\u0a17\u0a30\u0a3e"
    ],
    "name:tam_x_preferred":[
        "\u0bae\u0bcb\u0b95\u0bcd\u0bb0\u0bbe"
    ],
    "name:tel_x_preferred":[
        "\u0c2e\u0c4b\u0c17\u0c4d\u0c30\u0c3e"
    ],
    "name:urd_x_preferred":[
        "\u0645\u0648\u06af\u0631\u0627"
    ],
    "wof:name":"Mogra",
    "wof:placetype":"locality"
},
  "geometry": {"coordinates":[79.31667,21.46667],"type":"Point"}
}