{
  "type": "Feature",
  "properties": {
    "iso:country":"IN",
    "ks:ks_name":"Barampur",
    "ks:ks_pop":2194,
    "ks:ks_type":"HABITATION",
    "name:eng_x_preferred":[
        "Barampur"
    ],
    "wof:name":"Barampur",
    "wof:placetype":"locality",
    "wof:population":2194
},
  "geometry": {"coordinates":[82.81674099999999,27.378796],"type":"Point"}
}