{
  "type": "Feature",
  "properties": {
    "iso:country":"IN",
    "ks:ks_name":"Pitei Maliguda",
    "ks:ks_pop":332,
    "ks:ks_type":"HABITATION",
    "name:eng_x_preferred":[
        "Pitei Maliguda"
    ],
    "wof:name":"Pitei Maliguda",
    "wof:placetype":"locality",
    "wof:population":332
},
  "geometry": {"coordinates":[82.717101,18.71997],"type":"Point"}
}