{
  "type": "Feature",
  "properties": {
    "gn:admin1_code":"2.0",
    "gn:admin2_code":"548.0",
    "gn:asciiname":"Perumallapalle",
    "gn:country_code":"IN",
    "gn:dem":60,
    "gn:feature_class":"P",
    "gn:feature_code":"PPL",
    "gn:name":"Perum\u0101llapalle",
    "gn:population":0,
    "gn:timezone":"Asia/Kolkata",
    "iso:country":"IN",
    "wof:name":"Perumallapalle",
    "wof:placetype":"locality"
},
  "geometry": {"coordinates":[79.81655000000001,15.99578],"type":"Point"}
}