{
  "type": "Feature",
  "properties": {
    "gn:admin1_code":"25.0",
    "gn:admin2_code":"633.0",
    "gn:asciiname":"Maruduraiyanvalasu",
    "gn:country_code":"IN",
    "gn:dem":322,
    "gn:feature_class":"P",
    "gn:feature_code":"PPL",
    "gn:name":"Maruduraiyanvalasu",
    "gn:population":0,
    "gn:timezone":"Asia/Kolkata",
    "iso:country":"IN",
    "ks:ks_name":"Marudhuraiyan Valasu",
    "ks:ks_pop":363,
    "ks:ks_type":"HABITATION",
    "ks:ks_uagg_main":0,
    "name:eng_x_preferred":[
        "Marudhuraiyan Valasu"
    ],
    "wof:name":"Marudhuraiyan Valasu",
    "wof:placetype":"neighbourhood",
    "wof:population":363
},
  "geometry": {"coordinates":[77.49928300000001,11.026507],"type":"Point"}
}