{
  "type": "Feature",
  "properties": {
    "gn:admin1_code":"37",
    "gn:admin2_code":"404.0",
    "gn:asciiname":"Lemru",
    "gn:country_code":"IN",
    "gn:dem":417,
    "gn:feature_class":"P",
    "gn:feature_code":"PPL",
    "gn:name":"Lemr\u016b",
    "gn:population":0,
    "gn:timezone":"Asia/Kolkata",
    "iso:country":"IN",
    "name:und_x_variant":[
        "Lemr\u016b",
        "Lemru"
    ],
    "wof:name":"Lemru",
    "wof:placetype":"locality"
},
  "geometry": {"coordinates":[82.83881,22.64288],"type":"Point"}
}