{
  "type": "Feature",
  "properties": {
    "iso:country":"IN",
    "ks:ks_name":"Surjnarayan Tola",
    "ks:ks_pop":32,
    "ks:ks_type":"HABITATION",
    "name:eng_x_preferred":[
        "Surjnarayan Tola"
    ],
    "wof:name":"Surjnarayan Tola",
    "wof:placetype":"locality",
    "wof:population":32
},
  "geometry": {"coordinates":[87.85379,26.442544],"type":"Point"}
}