{
  "type": "Feature",
  "properties": {
    "iso:country":"IN",
    "ks:ks_name":"Nutan Dewan",
    "ks:ks_pop":394,
    "ks:ks_type":"HABITATION",
    "name:eng_x_preferred":[
        "Nutan Dewan"
    ],
    "wof:name":"Nutan Dewan",
    "wof:placetype":"locality",
    "wof:population":394
},
  "geometry": {"coordinates":[91.56415200000001,23.560966],"type":"Point"}
}