{
  "type": "Feature",
  "properties": {
    "gn:admin1_code":"36",
    "gn:admin2_code":"175.0",
    "gn:asciiname":"Kangapur",
    "gn:country_code":"IN",
    "gn:dem":92,
    "gn:feature_class":"P",
    "gn:feature_code":"PPL",
    "gn:name":"K\u0101ng\u0101pur",
    "gn:population":0,
    "gn:timezone":"Asia/Kolkata",
    "iso:country":"IN",
    "ks:ks_alt_nam":"K\u0101ng\u0101pur",
    "ks:ks_name":"Kangapur",
    "ks:ks_pop":717,
    "ks:ks_type":"VILLAGE",
    "ks:ks_uagg_main":0,
    "name:eng_x_preferred":[
        "Kangapur"
    ],
    "name:eng_x_variant":[
        "K\u0101ng\u0101pur"
    ],
    "wof:name":"Kangapur",
    "wof:placetype":"neighbourhood",
    "wof:population":717
},
  "geometry": {"coordinates":[82.294084,25.359951],"type":"Point"}
}