{
  "type": "Feature",
  "properties": {
    "iso:country":"IN",
    "ks:ks_name":"Chhatawani",
    "ks:ks_pop":495,
    "ks:ks_type":"VILLAGE",
    "name:eng_x_preferred":[
        "Chhatawani"
    ],
    "wof:name":"Chhatawani",
    "wof:placetype":"locality",
    "wof:population":495
},
  "geometry": {"coordinates":[74.810705,22.523566],"type":"Point"}
}