{
  "type": "Feature",
  "properties": {
    "gn:admin1_code":"35",
    "gn:admin2_code":"429.0",
    "gn:asciiname":"Pureni",
    "gn:country_code":"IN",
    "gn:dem":322,
    "gn:feature_class":"P",
    "gn:feature_code":"PPL",
    "gn:name":"Pureni",
    "gn:population":0,
    "gn:timezone":"Asia/Kolkata",
    "iso:country":"IN",
    "wof:name":"Pureni",
    "wof:placetype":"locality"
},
  "geometry": {"coordinates":[80.87926,24.64716],"type":"Point"}
}