{
  "type": "Feature",
  "properties": {
    "gn:admin1_code":"13.0",
    "gn:asciiname":"Devansahputhur",
    "gn:country_code":"IN",
    "gn:dem":233,
    "gn:feature_class":"P",
    "gn:feature_code":"PPL",
    "gn:name":"Dev\u0101nsahputh\u016br",
    "gn:population":0,
    "gn:timezone":"Asia/Kolkata",
    "iso:country":"IN",
    "wof:name":"Devansahputhur",
    "wof:placetype":"neighbourhood"
},
  "geometry": {"coordinates":[76.87063999999999,10.62934],"type":"Point"}
}