{
  "type": "Feature",
  "properties": {
    "gn:admin1_code":"13.0",
    "gn:admin2_code":"591.0",
    "gn:asciiname":"Mantharattur",
    "gn:country_code":"IN",
    "gn:dem":23,
    "gn:feature_class":"P",
    "gn:feature_code":"PPL",
    "gn:name":"Mantharatt\u016br",
    "gn:population":0,
    "gn:timezone":"Asia/Kolkata",
    "iso:country":"IN",
    "ks:ks_name":"Mantharathur",
    "ks:ks_pop":1326,
    "ks:ks_type":"HABITATION",
    "ks:ks_uagg_main":0,
    "name:eng_x_preferred":[
        "Mantharathur"
    ],
    "wof:name":"Mantharathur",
    "wof:placetype":"neighbourhood",
    "wof:population":1326
},
  "geometry": {"coordinates":[75.661294,11.569581],"type":"Point"}
}