{
  "type": "Feature",
  "properties": {
    "gn:admin1_code":"39.0",
    "gn:admin2_code":"64.0",
    "gn:asciiname":"Dharkhola",
    "gn:country_code":"IN",
    "gn:dem":1536,
    "gn:feature_class":"P",
    "gn:feature_code":"PPL",
    "gn:name":"Dh\u0101rkhola",
    "gn:population":0,
    "gn:timezone":"Asia/Kolkata",
    "iso:country":"IN",
    "ks:ks_name":"Dhar Khola",
    "ks:ks_pop":59,
    "ks:ks_type":"VILLAGE",
    "name:eng_x_preferred":[
        "Dhar Khola"
    ],
    "name:eng_x_variant":[
        "Dharkhola"
    ],
    "wof:name":"Dhar Khola",
    "wof:placetype":"locality",
    "wof:population":59
},
  "geometry": {"coordinates":[79.713414,29.515898],"type":"Point"}
}