{
  "type": "Feature",
  "properties": {
    "iso:country":"IN",
    "ks:ks_name":"Navwan",
    "ks:ks_pop":326,
    "ks:ks_type":"HABITATION",
    "name:eng_x_preferred":[
        "Navwan"
    ],
    "wof:name":"Navwan",
    "wof:placetype":"locality",
    "wof:population":326
},
  "geometry": {"coordinates":[82.602816,25.591318],"type":"Point"}
}