{
  "type": "Feature",
  "properties": {
    "iso:country":"IN",
    "ks:ks_name":"Sadwar",
    "ks:ks_pop":572,
    "ks:ks_type":"HABITATION",
    "name:eng_x_preferred":[
        "Sadwar"
    ],
    "wof:name":"Sadwar",
    "wof:placetype":"locality",
    "wof:population":572
},
  "geometry": {"coordinates":[83.16423,23.09002],"type":"Point"}
}