{
  "type": "Feature",
  "properties": {
    "iso:country":"IN",
    "ks:ks_name":"Settivaripalli",
    "ks:ks_pop":296,
    "ks:ks_type":"HABITATION",
    "name:eng_x_preferred":[
        "Settivaripalli"
    ],
    "wof:name":"Settivaripalli",
    "wof:placetype":"locality",
    "wof:population":296
},
  "geometry": {"coordinates":[78.52559599999999,13.898565],"type":"Point"}
}