{
  "type": "Feature",
  "properties": {
    "iso:country":"IN",
    "ks:ks_alt_nam":"TALEWASTI",
    "ks:ks_name":"Talewasti",
    "ks:ks_pop":111,
    "ks:ks_type":"HABITATION",
    "name:eng_x_preferred":[
        "Talewasti"
    ],
    "wof:name":"Talewasti",
    "wof:placetype":"locality",
    "wof:population":111
},
  "geometry": {"coordinates":[74.83528099999999,17.314651],"type":"Point"}
}