{
  "type": "Feature",
  "properties": {
    "gn:admin1_code":"36",
    "gn:admin2_code":"170.0",
    "gn:asciiname":"Amlikaur",
    "gn:country_code":"IN",
    "gn:dem":114,
    "gn:feature_class":"P",
    "gn:feature_code":"PPL",
    "gn:name":"Amlikaur",
    "gn:population":0,
    "gn:timezone":"Asia/Kolkata",
    "iso:country":"IN",
    "name:und_x_variant":[
        "R\u0101j\u0101pur"
    ],
    "wof:name":"Amlikaur",
    "wof:placetype":"locality"
},
  "geometry": {"coordinates":[80.66207,25.68782],"type":"Point"}
}