{
  "type": "Feature",
  "properties": {
    "iso:country":"IN",
    "ks:ks_alt_nam":"\u0100r\u0101zi B\u0101ghi",
    "ks:ks_name":"Arazi Baghi",
    "ks:ks_type":"VILLAGE",
    "name:eng_x_preferred":[
        "Arazi Baghi"
    ],
    "name:eng_x_variant":[
        "\u0100r\u0101zi B\u0101ghi"
    ],
    "wof:name":"Arazi Baghi",
    "wof:placetype":"locality"
},
  "geometry": {"coordinates":[83.759995,24.940791],"type":"Point"}
}