{
  "type": "Feature",
  "properties": {
    "iso:country":"IN",
    "ks:ks_alt_nam":"kappemane",
    "ks:ks_name":"Kappemane",
    "ks:ks_pop":62,
    "ks:ks_type":"HABITATION",
    "name:eng_x_preferred":[
        "Kappemane"
    ],
    "wof:name":"Kappemane",
    "wof:placetype":"locality",
    "wof:population":62
},
  "geometry": {"coordinates":[74.58142700000001,14.880714],"type":"Point"}
}