{
  "type": "Feature",
  "properties": {
    "iso:country":"IN",
    "ks:ks_name":"Sana Ramachandrapur",
    "ks:ks_pop":753,
    "ks:ks_type":"VILLAGE",
    "ks:ks_uagg_main":0,
    "name:eng_x_preferred":[
        "Sana Ramachandrapur"
    ],
    "wof:name":"Sana Ramachandrapur",
    "wof:placetype":"neighbourhood",
    "wof:population":753
},
  "geometry": {"coordinates":[85.090169,19.487299],"type":"Point"}
}