{
  "type": "Feature",
  "properties": {
    "gn:admin1_code":"2.0",
    "gn:admin2_code":"544.0",
    "gn:asciiname":"Surtipalle",
    "gn:country_code":"IN",
    "gn:dem":909,
    "gn:feature_class":"P",
    "gn:feature_code":"PPL",
    "gn:name":"Surtipalle",
    "gn:population":0,
    "gn:timezone":"Asia/Kolkata",
    "iso:country":"IN",
    "wof:name":"Surtipalle",
    "wof:placetype":"locality"
},
  "geometry": {"coordinates":[82.47409,18.01768],"type":"Point"}
}