{
  "type": "Feature",
  "properties": {
    "gn:admin1_code":"2.0",
    "gn:admin2_code":"544.0",
    "gn:asciiname":"Surtipalle",
    "gn:country_code":"IN",
    "gn:dem":909,
    "gn:feature_class":"P",
    "gn:feature_code":"PPL",
    "gn:name":"Surtipalle",
    "gn:population":0,
    "gn:timezone":"Asia/Kolkata",
    "iso:country":"IN",
    "ks:ks_name":"Surtipalle",
    "ks:ks_type":"VILLAGE",
    "name:eng_x_preferred":[
        "Surtipalle"
    ],
    "wof:name":"Surtipalle",
    "wof:placetype":"locality"
},
  "geometry": {"coordinates":[82.474092,18.017675],"type":"Point"}
}