{
  "type": "Feature",
  "properties": {
    "iso:country":"IN",
    "ks:ks_alt_nam":"LAXMIPURAM",
    "ks:ks_name":"Laxmipuram",
    "ks:ks_pop":67,
    "ks:ks_type":"HABITATION",
    "name:eng_x_preferred":[
        "Laxmipuram"
    ],
    "wof:name":"Laxmipuram",
    "wof:placetype":"locality",
    "wof:population":67
},
  "geometry": {"coordinates":[78.472407,13.690771],"type":"Point"}
}