{
  "type": "Feature",
  "properties": {
    "iso:country":"IN",
    "ks:ks_name":"Chirkitha",
    "ks:ks_pop":42,
    "ks:ks_type":"HABITATION",
    "name:eng_x_preferred":[
        "Chirkitha"
    ],
    "wof:name":"Chirkitha",
    "wof:placetype":"locality",
    "wof:population":42
},
  "geometry": {"coordinates":[81.954533,24.753004],"type":"Point"}
}