{
  "type": "Feature",
  "properties": {
    "iso:country":"IN",
    "ks:ks_name":"Kasaibahara",
    "ks:ks_pop":473,
    "ks:ks_type":"VILLAGE",
    "name:eng_x_preferred":[
        "Kasaibahara"
    ],
    "wof:name":"Kasaibahara",
    "wof:placetype":"locality",
    "wof:population":473
},
  "geometry": {"coordinates":[82.030609,22.538113],"type":"Point"}
}