{
  "type": "Feature",
  "properties": {
    "iso:country":"IN",
    "ks:ks_alt_nam":"Thottapoyil south",
    "ks:ks_name":"Thottapoyil South",
    "ks:ks_pop":618,
    "ks:ks_type":"HABITATION",
    "name:eng_x_preferred":[
        "Thottapoyil South"
    ],
    "wof:name":"Thottapoyil South",
    "wof:placetype":"locality",
    "wof:population":618
},
  "geometry": {"coordinates":[76.27263600000001,11.275009],"type":"Point"}
}