{
  "type": "Feature",
  "properties": {
    "iso:country":"IN",
    "ks:ks_name":"Baghraj Khurd",
    "ks:ks_pop":159,
    "ks:ks_type":"VILLAGE",
    "name:eng_x_preferred":[
        "Baghraj Khurd"
    ],
    "wof:name":"Baghraj Khurd",
    "wof:placetype":"locality",
    "wof:population":159
},
  "geometry": {"coordinates":[79.89339099999999,23.74492],"type":"Point"}
}