{
  "type": "Feature",
  "properties": {
    "gn:admin1_code":"24.0",
    "gn:admin2_code":"103",
    "gn:asciiname":"Shyampura",
    "gn:country_code":"IN",
    "gn:dem":358,
    "gn:feature_class":"P",
    "gn:feature_code":"PPL",
    "gn:name":"Shy\u0101mpura",
    "gn:population":0,
    "gn:timezone":"Asia/Kolkata",
    "iso:country":"IN",
    "name:und_x_variant":[
        "Ch\u0101rno ki Dh\u0101ni",
        "Shy\u0101mpura"
    ],
    "wof:name":"Shyampura",
    "wof:placetype":"neighbourhood"
},
  "geometry": {"coordinates":[75.48424,28.02578],"type":"Point"}
}