{
  "type": "Feature",
  "properties": {
    "iso:country":"IN",
    "ks:ks_alt_nam":"Dh\u016bmnagar",
    "ks:ks_name":"Dhumnagar",
    "ks:ks_pop":1353,
    "ks:ks_type":"VILLAGE",
    "name:eng_x_preferred":[
        "Dhumnagar"
    ],
    "name:eng_x_variant":[
        "Dh\u016bmnagar"
    ],
    "wof:name":"Dhumnagar",
    "wof:placetype":"locality",
    "wof:population":1353
},
  "geometry": {"coordinates":[84.26432699999999,26.812173],"type":"Point"}
}