{
  "type": "Feature",
  "properties": {
    "iso:country":"IN",
    "ks:ks_name":"Madu Wasti",
    "ks:ks_pop":250,
    "ks:ks_type":"HABITATION",
    "name:eng_x_preferred":[
        "Madu Wasti"
    ],
    "wof:name":"Madu Wasti",
    "wof:placetype":"locality",
    "wof:population":250
},
  "geometry": {"coordinates":[75.304233,17.518687],"type":"Point"}
}