{
  "type": "Feature",
  "properties": {
    "gn:admin1_code":"23",
    "gn:admin2_code":"38.0",
    "gn:asciiname":"Ramdaspur",
    "gn:country_code":"IN",
    "gn:dem":267,
    "gn:feature_class":"P",
    "gn:feature_code":"PPL",
    "gn:name":"R\u0101mdaspur",
    "gn:population":0,
    "gn:timezone":"Asia/Kolkata",
    "iso:country":"IN",
    "ks:ks_name":"Ramdaspur",
    "ks:ks_pop":916,
    "ks:ks_type":"VILLAGE",
    "ks:ks_uagg_main":0,
    "name:eng_x_preferred":[
        "Ramdaspur"
    ],
    "wof:name":"Ramdaspur",
    "wof:placetype":"neighbourhood",
    "wof:population":916
},
  "geometry": {"coordinates":[75.718885,31.722006],"type":"Point"}
}