{
  "type": "Feature",
  "properties": {
    "gn:admin1_code":"36.0",
    "gn:admin2_code":"153.0",
    "gn:asciiname":"Daryabad Bhanpur",
    "gn:country_code":"IN",
    "gn:dem":156,
    "gn:feature_class":"P",
    "gn:feature_code":"PPL",
    "gn:name":"Dary\u0101b\u0101d Bh\u0101npur",
    "gn:population":0,
    "gn:timezone":"Asia/Kolkata",
    "iso:country":"IN",
    "wof:name":"Daryabad Bhanpur",
    "wof:placetype":"locality"
},
  "geometry": {"coordinates":[80.22658,27.81978],"type":"Point"}
}