{
  "type": "Feature",
  "properties": {
    "iso:country":"IN",
    "ks:ks_name":"Punjamahal",
    "ks:ks_pop":0,
    "ks:ks_type":"VILLAGE",
    "name:eng_x_preferred":[
        "Punjamahal"
    ],
    "wof:name":"Punjamahal",
    "wof:placetype":"locality",
    "wof:population":0
},
  "geometry": {"coordinates":[83.34603,19.485371],"type":"Point"}
}