{
  "type": "Feature",
  "properties": {
    "gn:admin1_code":"35",
    "gn:admin2_code":"429.0",
    "gn:asciiname":"Manikpur",
    "gn:country_code":"IN",
    "gn:dem":352,
    "gn:feature_class":"P",
    "gn:feature_code":"PPL",
    "gn:name":"M\u0101nikpur",
    "gn:population":0,
    "gn:timezone":"Asia/Kolkata",
    "iso:country":"IN",
    "name:nld_x_preferred":[
        "Manikpur"
    ],
    "name:pol_x_preferred":[
        "Manikpur"
    ],
    "wof:name":"Manikpur",
    "wof:placetype":"locality"
},
  "geometry": {"coordinates":[80.69919,24.49716],"type":"Point"}
}