{
  "type": "Feature",
  "properties": {
    "iso:country":"IN",
    "ks:ks_name":"Sukali",
    "ks:ks_pop":1285,
    "ks:ks_type":"VILLAGE",
    "ks:ks_uagg_main":0,
    "name:eng_x_preferred":[
        "Sukali"
    ],
    "wof:name":"Sukali",
    "wof:placetype":"neighbourhood",
    "wof:population":1285
},
  "geometry": {"coordinates":[76.605886,20.119514],"type":"Point"}
}