{
  "type": "Feature",
  "properties": {
    "gn:admin1_code":"19.0",
    "gn:admin2_code":"574.0",
    "gn:asciiname":"Gurgihalli",
    "gn:country_code":"IN",
    "gn:dem":1030,
    "gn:feature_class":"P",
    "gn:feature_code":"PPL",
    "gn:name":"Gurgihalli",
    "gn:population":0,
    "gn:timezone":"Asia/Kolkata",
    "iso:country":"IN",
    "ks:ks_name":"Gurgihalli",
    "ks:ks_pop":68,
    "ks:ks_type":"VILLAGE",
    "name:eng_x_preferred":[
        "Gurgihalli"
    ],
    "wof:name":"Gurgihalli",
    "wof:placetype":"locality",
    "wof:population":68
},
  "geometry": {"coordinates":[75.779583,13.061484],"type":"Point"}
}