{
  "type": "Feature",
  "properties": {
    "gn:admin1_code":"35.0",
    "gn:admin2_code":"458.0",
    "gn:asciiname":"Fatehpur Ka Pura",
    "gn:country_code":"IN",
    "gn:dem":434,
    "gn:feature_class":"P",
    "gn:feature_code":"PPL",
    "gn:name":"Fatehpur Ka Pura",
    "gn:population":0,
    "gn:timezone":"Asia/Kolkata",
    "iso:country":"IN",
    "wof:name":"Fatehpur Ka Pura",
    "wof:placetype":"locality"
},
  "geometry": {"coordinates":[76.88167,24.28016],"type":"Point"}
}