{
  "type": "Feature",
  "properties": {
    "gn:admin1_code":"2",
    "gn:admin2_code":"544.0",
    "gn:asciiname":"Malampeta",
    "gn:country_code":"IN",
    "gn:dem":177,
    "gn:feature_class":"P",
    "gn:feature_code":"PPL",
    "gn:name":"Malampeta",
    "gn:population":0,
    "gn:timezone":"Asia/Kolkata",
    "iso:country":"IN",
    "ks:ks_name":"Mallampeta",
    "ks:ks_pop":139,
    "ks:ks_type":"VILLAGE",
    "name:eng_x_preferred":[
        "Mallampeta"
    ],
    "name:eng_x_variant":[
        "Malampeta"
    ],
    "wof:name":"Mallampeta",
    "wof:placetype":"locality",
    "wof:population":139
},
  "geometry": {"coordinates":[82.943399,18.059803],"type":"Point"}
}