{
  "type": "Feature",
  "properties": {
    "iso:country":"IN",
    "ks:ks_name":"Manjoor Garhi",
    "ks:ks_pop":2912,
    "ks:ks_type":"URBAN",
    "ks:ks_uagg_main":0,
    "name:eng_x_preferred":[
        "Manjoor Garhi"
    ],
    "wof:name":"Manjoor Garhi",
    "wof:placetype":"neighbourhood",
    "wof:population":2912
},
  "geometry": {"coordinates":[78.076494,27.950799],"type":"Point"}
}