{
  "type": "Feature",
  "properties": {
    "gn:admin1_code":"35.0",
    "gn:admin2_code":"424",
    "gn:asciiname":"Kakarwaha",
    "gn:country_code":"IN",
    "gn:dem":354,
    "gn:feature_class":"P",
    "gn:feature_code":"PPL",
    "gn:name":"Kakarw\u0101ha",
    "gn:population":0,
    "gn:timezone":"Asia/Kolkata",
    "iso:country":"IN",
    "name:und_x_variant":[
        "Kakarw\u0101ha",
        "Kakarwao"
    ],
    "wof:name":"Kakarwaha",
    "wof:placetype":"locality"
},
  "geometry": {"coordinates":[78.97068,24.47157],"type":"Point"}
}