{
  "type": "Feature",
  "properties": {
    "iso:country":"IN",
    "ks:ks_name":"Chinnaiahpuram",
    "ks:ks_pop":161,
    "ks:ks_type":"HABITATION",
    "ks:ks_uagg_main":0,
    "name:eng_x_preferred":[
        "Chinnaiahpuram"
    ],
    "wof:name":"Chinnaiahpuram",
    "wof:placetype":"neighbourhood",
    "wof:population":161
},
  "geometry": {"coordinates":[77.759708,9.685045],"type":"Point"}
}