{
  "type": "Feature",
  "properties": {
    "iso:country":"IN",
    "ks:ks_name":"Raj Bhar Basti",
    "ks:ks_pop":251,
    "ks:ks_type":"HABITATION",
    "name:eng_x_preferred":[
        "Raj Bhar Basti"
    ],
    "wof:name":"Raj Bhar Basti",
    "wof:placetype":"locality",
    "wof:population":251
},
  "geometry": {"coordinates":[83.102073,25.363505],"type":"Point"}
}