{
  "type": "Feature",
  "properties": {
    "gn:admin1_code":"36.0",
    "gn:admin2_code":"202",
    "gn:asciiname":"Garhia",
    "gn:country_code":"IN",
    "gn:dem":158,
    "gn:feature_class":"P",
    "gn:feature_code":"PPL",
    "gn:name":"Garhia",
    "gn:population":0,
    "gn:timezone":"Asia/Kolkata",
    "iso:country":"IN",
    "wof:name":"Garhia",
    "wof:placetype":"neighbourhood"
},
  "geometry": {"coordinates":[79.05925000000001,27.78534],"type":"Point"}
}