{
  "type": "Feature",
  "properties": {
    "iso:country":"IN",
    "ks:ks_name":"Takapal",
    "ks:ks_pop":254,
    "ks:ks_type":"VILLAGE",
    "name:eng_x_preferred":[
        "Takapal"
    ],
    "wof:name":"Takapal",
    "wof:placetype":"locality",
    "wof:population":254
},
  "geometry": {"coordinates":[81.53129800000001,19.296072],"type":"Point"}
}