{
  "type": "Feature",
  "properties": {
    "iso:country":"IN",
    "ks:ks_alt_nam":"L\u012bnja",
    "ks:ks_name":"Linja",
    "ks:ks_type":"VILLAGE",
    "name:eng_x_preferred":[
        "Linja"
    ],
    "name:eng_x_variant":[
        "L\u012bnja"
    ],
    "wof:name":"Linja",
    "wof:placetype":"locality"
},
  "geometry": {"coordinates":[77.84544,26.138828],"type":"Point"}
}