{
  "type": "Feature",
  "properties": {
    "gn:admin1_code":"21",
    "gn:admin2_code":"392.0",
    "gn:asciiname":"Tomamura",
    "gn:country_code":"IN",
    "gn:dem":151,
    "gn:feature_class":"P",
    "gn:feature_code":"PPL",
    "gn:name":"Tomamura",
    "gn:population":0,
    "gn:timezone":"Asia/Kolkata",
    "iso:country":"IN",
    "wof:name":"Tomamura",
    "wof:placetype":"locality"
},
  "geometry": {"coordinates":[83.60168,21.00873],"type":"Point"}
}