{
  "type": "Feature",
  "properties": {
    "iso:country":"IN",
    "ks:ks_alt_nam":"bullapura",
    "ks:ks_name":"Bullapura",
    "ks:ks_pop":253,
    "ks:ks_type":"HABITATION",
    "name:eng_x_preferred":[
        "Bullapura"
    ],
    "wof:name":"Bullapura",
    "wof:placetype":"locality",
    "wof:population":253
},
  "geometry": {"coordinates":[75.374994,14.115225],"type":"Point"}
}