{
  "type": "Feature",
  "properties": {
    "iso:country":"IN",
    "ks:ks_name":"Ghaskaro",
    "ks:ks_pop":370,
    "ks:ks_type":"VILLAGE",
    "ks:ks_uagg_main":0,
    "name:eng_x_preferred":[
        "Ghaskaro"
    ],
    "wof:name":"Ghaskaro",
    "wof:placetype":"neighbourhood",
    "wof:population":370
},
  "geometry": {"coordinates":[85.98452399999999,24.341554],"type":"Point"}
}