{
  "type": "Feature",
  "properties": {
    "gn:admin1_code":"24.0",
    "gn:admin2_code":"129.0",
    "gn:asciiname":"Lachhmipura",
    "gn:country_code":"IN",
    "gn:dem":367,
    "gn:feature_class":"P",
    "gn:feature_code":"PPL",
    "gn:name":"Lachhm\u012bpura",
    "gn:population":0,
    "gn:timezone":"Asia/Kolkata",
    "iso:country":"IN",
    "wof:name":"Lachhmipura",
    "wof:placetype":"neighbourhood"
},
  "geometry": {"coordinates":[76.41023,24.34349],"type":"Point"}
}