{
  "type": "Feature",
  "properties": {
    "iso:country":"IN",
    "ks:ks_name":"Sailang",
    "ks:ks_pop":511,
    "ks:ks_type":"VILLAGE",
    "name:eng_x_preferred":[
        "Sailang"
    ],
    "wof:name":"Sailang",
    "wof:placetype":"locality",
    "wof:population":511
},
  "geometry": {"coordinates":[79.528345,30.539261],"type":"Point"}
}