{
  "type": "Feature",
  "properties": {
    "iso:country":"IN",
    "ks:ks_name":"Sijdia",
    "ks:ks_pop":1176,
    "ks:ks_type":"VILLAGE",
    "ks:ks_uagg_main":0,
    "name:eng_x_preferred":[
        "Sijdia"
    ],
    "wof:name":"Sijdia",
    "wof:placetype":"neighbourhood",
    "wof:population":1176
},
  "geometry": {"coordinates":[88.64479799999999,23.118299],"type":"Point"}
}