{
  "type": "Feature",
  "properties": {
    "iso:country":"IN",
    "ks:ks_alt_nam":"Balapuram AC",
    "ks:ks_name":"Balapuram Ac",
    "ks:ks_pop":175,
    "ks:ks_type":"HABITATION",
    "name:eng_x_preferred":[
        "Balapuram Ac"
    ],
    "wof:name":"Balapuram Ac",
    "wof:placetype":"locality",
    "wof:population":175
},
  "geometry": {"coordinates":[79.403509,13.18773],"type":"Point"}
}