{
  "type": "Feature",
  "properties": {
    "gn:admin1_code":"19.0",
    "gn:admin2_code":"570.0",
    "gn:asciiname":"Haranahalli",
    "gn:country_code":"IN",
    "gn:dem":1200,
    "gn:feature_class":"P",
    "gn:feature_code":"PPL",
    "gn:name":"H\u0101ranahalli",
    "gn:population":0,
    "gn:timezone":"Asia/Kolkata",
    "iso:country":"IN",
    "ks:ks_name":"Haranahalli",
    "ks:ks_pop":133,
    "ks:ks_type":"HABITATION",
    "name:eng_x_preferred":[
        "Haranahalli"
    ],
    "wof:name":"Haranahalli",
    "wof:placetype":"locality",
    "wof:population":133
},
  "geometry": {"coordinates":[75.69293,13.299834],"type":"Point"}
}