{
  "type": "Feature",
  "properties": {
    "iso:country":"IN",
    "ks:ks_name":"Achutapur",
    "ks:ks_pop":0,
    "ks:ks_type":"VILLAGE",
    "name:eng_x_preferred":[
        "Achutapur"
    ],
    "wof:name":"Achutapur",
    "wof:placetype":"locality",
    "wof:population":0
},
  "geometry": {"coordinates":[85.46613499999999,20.030049],"type":"Point"}
}