{
  "type": "Feature",
  "properties": {
    "iso:country":"IN",
    "ks:ks_name":"Baria Falia",
    "ks:ks_pop":416,
    "ks:ks_type":"HABITATION",
    "name:eng_x_preferred":[
        "Baria Falia"
    ],
    "wof:name":"Baria Falia",
    "wof:placetype":"locality",
    "wof:population":416
},
  "geometry": {"coordinates":[74.09397199999999,23.105361],"type":"Point"}
}