{
  "type": "Feature",
  "properties": {
    "iso:country":"IN",
    "ks:ks_name":"Jhagadewadi",
    "ks:ks_pop":98,
    "ks:ks_type":"HABITATION",
    "name:eng_x_preferred":[
        "Jhagadewadi"
    ],
    "wof:name":"Jhagadewadi",
    "wof:placetype":"locality",
    "wof:population":98
},
  "geometry": {"coordinates":[73.15279700000001,17.730597],"type":"Point"}
}