{
  "type": "Feature",
  "properties": {
    "gn:admin1_code":"35.0",
    "gn:admin2_code":"424",
    "gn:asciiname":"Kamalnagar",
    "gn:country_code":"IN",
    "gn:dem":284,
    "gn:feature_class":"P",
    "gn:feature_code":"PPL",
    "gn:name":"Kamalnagar",
    "gn:population":0,
    "gn:timezone":"Asia/Kolkata",
    "iso:country":"IN",
    "name:vie_x_preferred":[
        "Kamalnagar"
    ],
    "wof:name":"Kamalnagar",
    "wof:placetype":"locality"
},
  "geometry": {"coordinates":[78.97537,24.87066],"type":"Point"}
}