{
  "type": "Feature",
  "properties": {
    "iso:country":"IN",
    "ks:ks_name":"Kankjal Pashchim",
    "ks:ks_pop":1090,
    "ks:ks_type":"VILLAGE",
    "ks:ks_uagg_main":0,
    "name:eng_x_preferred":[
        "Kankjal Pashchim"
    ],
    "wof:name":"Kankjal Pashchim",
    "wof:placetype":"neighbourhood",
    "wof:population":1090
},
  "geometry": {"coordinates":[88.116305,22.218132],"type":"Point"}
}