{
  "type": "Feature",
  "properties": {
    "iso:country":"IN",
    "ks:ks_name":"Kalupur",
    "ks:ks_pop":0,
    "ks:ks_type":"VILLAGE",
    "name:eng_x_preferred":[
        "Kalupur"
    ],
    "wof:name":"Kalupur",
    "wof:placetype":"locality",
    "wof:population":0
},
  "geometry": {"coordinates":[84.004032,25.296541],"type":"Point"}
}