{
  "type": "Feature",
  "properties": {
    "gn:admin1_code":"36.0",
    "gn:admin2_code":"175.0",
    "gn:asciiname":"Baraipur",
    "gn:country_code":"IN",
    "gn:dem":100,
    "gn:feature_class":"P",
    "gn:feature_code":"PPL",
    "gn:name":"Bara\u012bpur",
    "gn:population":0,
    "gn:timezone":"Asia/Kolkata",
    "iso:country":"IN",
    "name:ceb_x_preferred":[
        "Baraipur"
    ],
    "name:msa_x_preferred":[
        "Baraipur"
    ],
    "name:pol_x_preferred":[
        "Baraipur"
    ],
    "wof:name":"Baraipur",
    "wof:placetype":"locality"
},
  "geometry": {"coordinates":[81.96993000000001,25.71398],"type":"Point"}
}