{
  "type": "Feature",
  "properties": {
    "iso:country":"IN",
    "ks:ks_name":"Orani",
    "ks:ks_pop":421,
    "ks:ks_type":"HABITATION",
    "ks:ks_uagg_main":0,
    "name:eng_x_preferred":[
        "Orani"
    ],
    "wof:name":"Orani",
    "wof:placetype":"neighbourhood",
    "wof:population":421
},
  "geometry": {"coordinates":[84.675995,25.180422],"type":"Point"}
}