{
  "type": "Feature",
  "properties": {
    "iso:country":"IN",
    "ks:ks_name":"Gharami Para",
    "ks:ks_pop":1027,
    "ks:ks_type":"HABITATION",
    "name:eng_x_preferred":[
        "Gharami Para"
    ],
    "wof:name":"Gharami Para",
    "wof:placetype":"locality",
    "wof:population":1027
},
  "geometry": {"coordinates":[88.898167,22.211048],"type":"Point"}
}