{
  "type": "Feature",
  "properties": {
    "gn:admin1_code":"3.0",
    "gn:admin2_code":"314",
    "gn:asciiname":"Hang Habai",
    "gn:country_code":"IN",
    "gn:dem":97,
    "gn:feature_class":"P",
    "gn:feature_code":"PPL",
    "gn:name":"H\u0101ng H\u0101b\u0101i",
    "gn:population":0,
    "gn:timezone":"Asia/Kolkata",
    "iso:country":"IN",
    "wof:name":"Hang Habai",
    "wof:placetype":"locality"
},
  "geometry": {"coordinates":[92.79586999999999,25.85584],"type":"Point"}
}