{
  "type": "Feature",
  "properties": {
    "iso:country":"IN",
    "ks:ks_name":"Salempur Jat",
    "ks:ks_pop":2539,
    "ks:ks_type":"HABITATION",
    "name:eng_x_preferred":[
        "Salempur Jat"
    ],
    "wof:name":"Salempur Jat",
    "wof:placetype":"locality",
    "wof:population":2539
},
  "geometry": {"coordinates":[77.714125,28.336297],"type":"Point"}
}