{
  "type": "Feature",
  "properties": {
    "iso:country":"IN",
    "ks:ks_name":"Gangapur Alias Lankasur",
    "ks:ks_pop":23,
    "ks:ks_type":"VILLAGE",
    "name:eng_x_preferred":[
        "Gangapur Alias Lankasur"
    ],
    "wof:name":"Gangapur Alias Lankasur",
    "wof:placetype":"locality",
    "wof:population":23
},
  "geometry": {"coordinates":[83.899612,24.437701],"type":"Point"}
}