{
  "type": "Feature",
  "properties": {
    "gn:admin1_code":"35",
    "gn:admin2_code":"430.0",
    "gn:asciiname":"Chachai",
    "gn:country_code":"IN",
    "gn:dem":290,
    "gn:feature_class":"P",
    "gn:feature_code":"PPL",
    "gn:name":"Chachai",
    "gn:population":0,
    "gn:timezone":"Asia/Kolkata",
    "iso:country":"IN",
    "ks:ks_name":"Chachai",
    "ks:ks_pop":4548,
    "ks:ks_type":"VILLAGE",
    "name:eng_x_preferred":[
        "Chachai"
    ],
    "wof:name":"Chachai",
    "wof:placetype":"locality",
    "wof:population":4548
},
  "geometry": {"coordinates":[81.301382,24.781575],"type":"Point"}
}