{
  "type": "Feature",
  "properties": {
    "iso:country":"IN",
    "ks:ks_alt_nam":"Surigram  pt II",
    "ks:ks_name":"Surigram Pt Ii",
    "ks:ks_pop":86,
    "ks:ks_type":"HABITATION",
    "name:eng_x_preferred":[
        "Surigram Pt Ii"
    ],
    "name:eng_x_variant":[
        "Surigram  pt II"
    ],
    "wof:name":"Surigram Pt Ii",
    "wof:placetype":"locality",
    "wof:population":86
},
  "geometry": {"coordinates":[92.306752,24.811794],"type":"Point"}
}