{
  "type": "Feature",
  "properties": {
    "iso:country":"IN",
    "ks:ks_alt_nam":"Shankareshwar temple",
    "ks:ks_name":"Shankareshwar Temple",
    "ks:ks_pop":212,
    "ks:ks_type":"HABITATION",
    "name:eng_x_preferred":[
        "Shankareshwar Temple"
    ],
    "wof:name":"Shankareshwar Temple",
    "wof:placetype":"locality",
    "wof:population":212
},
  "geometry": {"coordinates":[76.257357,13.38341],"type":"Point"}
}