{
  "type": "Feature",
  "properties": {
    "gn:admin1_code":"37",
    "gn:admin2_code":"405.0",
    "gn:asciiname":"Birgahani",
    "gn:country_code":"IN",
    "gn:dem":261,
    "gn:feature_class":"P",
    "gn:feature_code":"PPL",
    "gn:name":"Birgahan\u012b",
    "gn:population":0,
    "gn:timezone":"Asia/Kolkata",
    "iso:country":"IN",
    "wof:name":"Birgahani",
    "wof:placetype":"locality"
},
  "geometry": {"coordinates":[82.63171,22.01694],"type":"Point"}
}