{
  "type": "Feature",
  "properties": {
    "iso:country":"IN",
    "ks:ks_alt_nam":"poonchola",
    "ks:ks_name":"Poonchola",
    "ks:ks_pop":420,
    "ks:ks_type":"HABITATION",
    "name:eng_x_preferred":[
        "Poonchola"
    ],
    "wof:name":"Poonchola",
    "wof:placetype":"locality",
    "wof:population":420
},
  "geometry": {"coordinates":[75.71561,11.504097],"type":"Point"}
}