{
  "type": "Feature",
  "properties": {
    "iso:country":"IN",
    "ks:ks_name":"Chichghat",
    "ks:ks_pop":15,
    "ks:ks_type":"VILLAGE",
    "name:eng_x_preferred":[
        "Chichghat"
    ],
    "wof:name":"Chichghat",
    "wof:placetype":"locality",
    "wof:population":15
},
  "geometry": {"coordinates":[79.04775100000001,21.384555],"type":"Point"}
}