{
  "type": "Feature",
  "properties": {
    "iso:country":"IN",
    "ks:ks_name":"Sampannaguda",
    "ks:ks_pop":46,
    "ks:ks_type":"HABITATION",
    "name:eng_x_preferred":[
        "Sampannaguda"
    ],
    "wof:name":"Sampannaguda",
    "wof:placetype":"locality",
    "wof:population":46
},
  "geometry": {"coordinates":[83.711484,18.837391],"type":"Point"}
}