{
  "type": "Feature",
  "properties": {
    "iso:country":"IN",
    "ks:ks_name":"Baroshakdal",
    "ks:ks_pop":6790,
    "ks:ks_type":"HABITATION",
    "name:eng_x_preferred":[
        "Baroshakdal"
    ],
    "wof:name":"Baroshakdal",
    "wof:placetype":"locality",
    "wof:population":6790
},
  "geometry": {"coordinates":[89.541785,26.119618],"type":"Point"}
}