{
  "type": "Feature",
  "properties": {
    "gn:admin1_code":"19.0",
    "gn:admin2_code":"582.0",
    "gn:asciiname":"Konganahalli",
    "gn:country_code":"IN",
    "gn:dem":892,
    "gn:feature_class":"P",
    "gn:feature_code":"PPL",
    "gn:name":"Kong\u0101nahalli",
    "gn:population":0,
    "gn:timezone":"Asia/Kolkata",
    "iso:country":"IN",
    "wof:name":"Konganahalli",
    "wof:placetype":"locality"
},
  "geometry": {"coordinates":[78.0001,13.33026],"type":"Point"}
}