{
  "type": "Feature",
  "properties": {
    "iso:country":"IN",
    "ks:ks_name":"Sybetwadi",
    "ks:ks_pop":150,
    "ks:ks_type":"HABITATION",
    "name:eng_x_preferred":[
        "Sybetwadi"
    ],
    "wof:name":"Sybetwadi",
    "wof:placetype":"locality",
    "wof:population":150
},
  "geometry": {"coordinates":[76.760707,18.778018],"type":"Point"}
}