{
  "type": "Feature",
  "properties": {
    "iso:country":"IN",
    "ks:ks_name":"Bishanpur",
    "ks:ks_pop":743,
    "ks:ks_type":"VILLAGE",
    "ks:ks_uagg_main":0,
    "name:eng_x_preferred":[
        "Bishanpur"
    ],
    "wof:name":"Bishanpur",
    "wof:placetype":"neighbourhood",
    "wof:population":743
},
  "geometry": {"coordinates":[85.987095,26.264855],"type":"Point"}
}