{
  "type": "Feature",
  "properties": {
    "iso:country":"IN",
    "ks:ks_name":"Mokrambil",
    "ks:ks_pop":1896,
    "ks:ks_type":"VILLAGE",
    "name:eng_x_preferred":[
        "Mokrambil"
    ],
    "wof:name":"Mokrambil",
    "wof:placetype":"locality",
    "wof:population":1896
},
  "geometry": {"coordinates":[90.044511,26.400047],"type":"Point"}
}