{
  "type": "Feature",
  "properties": {
    "gn:admin1_code":"35",
    "gn:admin2_code":"456.0",
    "gn:asciiname":"Maina Piparia",
    "gn:country_code":"IN",
    "gn:dem":468,
    "gn:feature_class":"P",
    "gn:feature_code":"PPL",
    "gn:name":"Main\u0101 Pipari\u0101",
    "gn:population":0,
    "gn:timezone":"Asia/Kolkata",
    "iso:country":"IN",
    "wof:name":"Maina Piparia",
    "wof:placetype":"locality"
},
  "geometry": {"coordinates":[79.77529,22.34831],"type":"Point"}
}