{
  "type": "Feature",
  "properties": {
    "gn:admin1_code":"23",
    "gn:admin2_code":"39.0",
    "gn:asciiname":"Cheta",
    "gn:country_code":"IN",
    "gn:dem":242,
    "gn:feature_class":"P",
    "gn:feature_code":"PPL",
    "gn:name":"Cheta",
    "gn:population":0,
    "gn:timezone":"Asia/Kolkata",
    "iso:country":"IN",
    "name:bul_x_preferred":[
        "\u0427\u0435\u0442\u0430"
    ],
    "name:mkd_x_preferred":[
        "\u0427\u0435\u0442\u0430"
    ],
    "name:pol_x_preferred":[
        "Czeta"
    ],
    "wof:name":"Cheta",
    "wof:placetype":"locality"
},
  "geometry": {"coordinates":[75.90467,31.27891],"type":"Point"}
}