{
  "type": "Feature",
  "properties": {
    "iso:country":"IN",
    "ks:ks_alt_nam":"astal",
    "ks:ks_name":"Astal",
    "ks:ks_pop":37,
    "ks:ks_type":"HABITATION",
    "name:eng_x_preferred":[
        "Astal"
    ],
    "wof:name":"Astal",
    "wof:placetype":"locality",
    "wof:population":37
},
  "geometry": {"coordinates":[74.666382,14.737208],"type":"Point"}
}