{
  "type": "Feature",
  "properties": {
    "gn:admin1_code":"40",
    "gn:admin2_code":"539.0",
    "gn:asciiname":"Bhaskarlagudem",
    "gn:country_code":"IN",
    "gn:dem":237,
    "gn:feature_class":"P",
    "gn:feature_code":"PPL",
    "gn:name":"Bh\u0101skarlag\u016bdem",
    "gn:population":0,
    "gn:timezone":"Asia/Kolkata",
    "iso:country":"IN",
    "wof:name":"Bhaskarlagudem",
    "wof:placetype":"neighbourhood"
},
  "geometry": {"coordinates":[79.2625,17.12985],"type":"Point"}
}