{
  "type": "Feature",
  "properties": {
    "iso:country":"IN",
    "ks:ks_name":"Pipla",
    "ks:ks_pop":350,
    "ks:ks_type":"HABITATION",
    "name:eng_x_preferred":[
        "Pipla"
    ],
    "wof:name":"Pipla",
    "wof:placetype":"locality",
    "wof:population":350
},
  "geometry": {"coordinates":[73.423556,21.1635],"type":"Point"}
}