{
  "type": "Feature",
  "properties": {
    "iso:country":"IN",
    "ks:ks_name":"Talyachiwadi",
    "ks:ks_pop":102,
    "ks:ks_type":"HABITATION",
    "name:eng_x_preferred":[
        "Talyachiwadi"
    ],
    "wof:name":"Talyachiwadi",
    "wof:placetype":"locality",
    "wof:population":102
},
  "geometry": {"coordinates":[73.567667,17.99732],"type":"Point"}
}