{
  "type": "Feature",
  "properties": {
    "iso:country":"IN",
    "ks:ks_alt_nam":"NABA CH. PARA",
    "ks:ks_name":"Naba Ch. Para",
    "ks:ks_pop":112,
    "ks:ks_type":"HABITATION",
    "name:eng_x_preferred":[
        "Naba Ch. Para"
    ],
    "wof:name":"Naba Ch. Para",
    "wof:placetype":"locality",
    "wof:population":112
},
  "geometry": {"coordinates":[91.670377,24.128193],"type":"Point"}
}