{
  "type": "Feature",
  "properties": {
    "gn:admin1_code":"36",
    "gn:admin2_code":"145.0",
    "gn:asciiname":"Haripura",
    "gn:country_code":"IN",
    "gn:dem":184,
    "gn:feature_class":"P",
    "gn:feature_code":"PPL",
    "gn:name":"Har\u012bpura",
    "gn:population":0,
    "gn:timezone":"Asia/Kolkata",
    "iso:country":"IN",
    "ks:ks_name":"Haripura",
    "ks:ks_pop":120,
    "ks:ks_type":"HABITATION",
    "name:ara_x_preferred":[
        "\u0647\u064a\u0631\u0628\u0648\u0631\u0627"
    ],
    "name:ben_bn_x_preferred":[
        "\u09b9\u09b0\u09bf\u09aa\u09c1\u09b0\u09be"
    ],
    "name:ben_in_x_preferred":[
        "\u09b9\u09b0\u09bf\u09aa\u09c1\u09b0\u09be"
    ],
    "name:eng_x_preferred":[
        "Haripura"
    ],
    "name:guj_x_preferred":[
        "\u0ab9\u0ab0\u0abf\u0aaa\u0ac1\u0ab0\u0abe"
    ],
    "name:guj_x_variant":[
        "\u0ab9\u0ab0\u0ac0\u0aaa\u0ac1\u0ab0\u0abe"
    ],
    "name:hin_x_preferred":[
        "\u0939\u0930\u0940\u092a\u0941\u0930\u093e"
    ],
    "name:kan_x_preferred":[
        "\u0cb9\u0cb0\u0cbf\u0caa\u0cc1\u0cb0"
    ],
    "name:mal_x_preferred":[
        "\u0d39\u0d30\u0d3f\u0d2a\u0d41\u0d30"
    ],
    "name:mar_x_preferred":[
        "\u0939\u0930\u093f\u092a\u0941\u0930\u093e"
    ],
    "name:pan_x_preferred":[
        "\u0a39\u0a30\u0a40\u0a2a\u0a41\u0a30\u0a3e"
    ],
    "name:tam_x_preferred":[
        "\u0bb9\u0bb0\u0bbf\u0baa\u0bc1\u0bb0\u0bbe"
    ],
    "name:tel_x_preferred":[
        "\u0c39\u0c30\u0c3f\u0c2a\u0c41\u0c30\u0c3e"
    ],
    "name:urd_x_preferred":[
        "\u06c1\u0631\u06cc \u067e\u0648\u0631"
    ],
    "wof:name":"Haripura",
    "wof:placetype":"locality",
    "wof:population":120
},
  "geometry": {"coordinates":[77.542704,27.500903],"type":"Point"}
}