{
  "type": "Feature",
  "properties": {
    "gn:admin1_code":"38.0",
    "gn:admin2_code":"353.0",
    "gn:asciiname":"Domarhir",
    "gn:country_code":"IN",
    "gn:dem":88,
    "gn:feature_class":"P",
    "gn:feature_code":"PPL",
    "gn:name":"Domarhir",
    "gn:population":0,
    "gn:timezone":"Asia/Kolkata",
    "iso:country":"IN",
    "ks:ks_name":"Dumarhir",
    "ks:ks_pop":585,
    "ks:ks_type":"VILLAGE",
    "name:eng_x_preferred":[
        "Dumarhir"
    ],
    "name:eng_x_variant":[
        "Domarhir"
    ],
    "wof:name":"Dumarhir",
    "wof:placetype":"locality",
    "wof:population":585
},
  "geometry": {"coordinates":[87.579099,24.65984],"type":"Point"}
}