{
  "type": "Feature",
  "properties": {
    "iso:country":"IN",
    "ks:ks_name":"Pindra",
    "ks:ks_pop":147,
    "ks:ks_type":"VILLAGE",
    "name:eng_x_preferred":[
        "Pindra"
    ],
    "wof:name":"Pindra",
    "wof:placetype":"locality",
    "wof:population":147
},
  "geometry": {"coordinates":[84.758743,24.319269],"type":"Point"}
}