{
  "type": "Feature",
  "properties": {
    "iso:country":"IN",
    "ks:ks_name":"Deramnagar",
    "ks:ks_pop":578,
    "ks:ks_type":"HABITATION",
    "name:eng_x_preferred":[
        "Deramnagar"
    ],
    "wof:name":"Deramnagar",
    "wof:placetype":"locality",
    "wof:population":578
},
  "geometry": {"coordinates":[72.360406,26.851742],"type":"Point"}
}