{
  "type": "Feature",
  "properties": {
    "iso:country":"IN",
    "ks:ks_name":"Chamtola m",
    "ks:ks_pop":365,
    "ks:ks_type":"HABITATION",
    "name:eng_x_preferred":[
        "Chamtola m"
    ],
    "wof:name":"Chamtola m",
    "wof:placetype":"locality",
    "wof:population":365
},
  "geometry": {"coordinates":[82.892059,26.915809],"type":"Point"}
}