{
  "type": "Feature",
  "properties": {
    "iso:country":"IN",
    "ks:ks_name":"Kanrra",
    "ks:ks_pop":1452,
    "ks:ks_type":"VILLAGE",
    "ks:ks_uagg_main":0,
    "name:eng_x_preferred":[
        "Kanrra"
    ],
    "wof:name":"Kanrra",
    "wof:placetype":"locality",
    "wof:population":1452
},
  "geometry": {"coordinates":[86.48721,23.849449],"type":"Point"}
}