{
  "type": "Feature",
  "properties": {
    "iso:country":"IN",
    "ks:ks_name":"Varchiwadi",
    "ks:ks_pop":12,
    "ks:ks_type":"HABITATION",
    "name:eng_x_preferred":[
        "Varchiwadi"
    ],
    "wof:name":"Varchiwadi",
    "wof:placetype":"locality",
    "wof:population":12
},
  "geometry": {"coordinates":[73.618611,16.906111],"type":"Point"}
}