{
  "type": "Feature",
  "properties": {
    "gn:country":"IN",
    "gn:fcode":"PPL",
    "gn:population":15837,
    "iso:country":"IN",
    "name:ben_x_preferred":[
        "\u0989\u09a8\u09b9\u09c7\u09b2"
    ],
    "name:bpy_x_preferred":[
        "\u0989\u09a8\u09b9\u09c7\u09b2"
    ],
    "name:bul_x_preferred":[
        "\u0423\u043d\u0445\u0435\u043b"
    ],
    "name:ceb_x_preferred":[
        "Unhel"
    ],
    "name:eng_x_preferred":[
        "Unhel"
    ],
    "name:fra_x_preferred":[
        "Unhel"
    ],
    "name:ita_x_preferred":[
        "Unhel"
    ],
    "name:mlg_x_preferred":[
        "Unhel"
    ],
    "name:msa_x_preferred":[
        "Unhel"
    ],
    "name:nan_x_preferred":[
        "Unhel"
    ],
    "name:nld_x_preferred":[
        "Unhel"
    ],
    "name:por_x_preferred":[
        "Unhel"
    ],
    "name:spa_x_preferred":[
        "Unhel"
    ],
    "name:swe_x_preferred":[
        "Unhel"
    ],
    "name:vie_x_preferred":[
        "Unhel"
    ],
    "name:zho_x_preferred":[
        "\u4e4c\u6069\u8d6b\u5c14"
    ],
    "qs:name":"Unhel",
    "qs:photos_9r":0,
    "qs:photos_sr":0,
    "qs:pop_sr":"6",
    "wd:wordcount":308,
    "wof:name":"Unhel",
    "wof:placetype":"locality",
    "wof:population":15837
},
  "geometry": {"coordinates":[75.55931,23.33794],"type":"Point"}
}