{
  "type": "Feature",
  "properties": {
    "iso:country":"IN",
    "ks:ks_name":"Nagla Khubi",
    "ks:ks_pop":396,
    "ks:ks_type":"HABITATION",
    "name:eng_x_preferred":[
        "Nagla Khubi"
    ],
    "wof:name":"Nagla Khubi",
    "wof:placetype":"locality",
    "wof:population":396
},
  "geometry": {"coordinates":[77.761171,27.440052],"type":"Point"}
}