{
  "type": "Feature",
  "properties": {
    "iso:country":"IN",
    "ks:ks_name":"Lormi Reserved Forest",
    "ks:ks_pop":443,
    "ks:ks_type":"VILLAGE",
    "name:eng_x_preferred":[
        "Lormi Reserved Forest"
    ],
    "wof:name":"Lormi Reserved Forest",
    "wof:placetype":"locality",
    "wof:population":443
},
  "geometry": {"coordinates":[81.85317999999999,22.376708],"type":"Point"}
}