{
  "type": "Feature",
  "properties": {
    "gn:admin1_code":"36.0",
    "gn:admin2_code":"149.0",
    "gn:asciiname":"Sisaiyan Khurd",
    "gn:country_code":"IN",
    "gn:dem":162,
    "gn:feature_class":"P",
    "gn:feature_code":"PPL",
    "gn:name":"S\u012bsaiy\u0101n Kh\u016brd",
    "gn:population":0,
    "gn:timezone":"Asia/Kolkata",
    "iso:country":"IN",
    "wof:name":"Sisaiyan Khurd",
    "wof:placetype":"locality"
},
  "geometry": {"coordinates":[79.33849000000002,28.10617],"type":"Point"}
}