{
  "type": "Feature",
  "properties": {
    "iso:country":"IN",
    "ks:ks_name":"Padam Chak",
    "ks:ks_pop":2,
    "ks:ks_type":"VILLAGE",
    "name:eng_x_preferred":[
        "Padam Chak"
    ],
    "wof:name":"Padam Chak",
    "wof:placetype":"locality",
    "wof:population":2
},
  "geometry": {"coordinates":[87.370226,25.174013],"type":"Point"}
}