{
  "type": "Feature",
  "properties": {
    "iso:country":"IN",
    "ks:ks_name":"Dasappanadoddi",
    "ks:ks_pop":112,
    "ks:ks_type":"HABITATION",
    "name:eng_x_preferred":[
        "Dasappanadoddi"
    ],
    "wof:name":"Dasappanadoddi",
    "wof:placetype":"locality",
    "wof:population":112
},
  "geometry": {"coordinates":[77.435785,12.688228],"type":"Point"}
}