{
  "type": "Feature",
  "properties": {
    "iso:country":"IN",
    "ks:ks_name":"Thuthur Kalathuveedu",
    "ks:ks_pop":110,
    "ks:ks_type":"HABITATION",
    "name:eng_x_preferred":[
        "Thuthur Kalathuveedu"
    ],
    "wof:name":"Thuthur Kalathuveedu",
    "wof:placetype":"locality",
    "wof:population":110
},
  "geometry": {"coordinates":[78.547989,10.297819],"type":"Point"}
}