{
  "type": "Feature",
  "properties": {
    "gn:admin1_code":"36.0",
    "gn:admin2_code":"151.0",
    "gn:asciiname":"Muhammadpur Taluka Rampur Amirt",
    "gn:country_code":"IN",
    "gn:dem":169,
    "gn:feature_class":"P",
    "gn:feature_code":"PPL",
    "gn:name":"Muhammadpur Taluka R\u0101mpur Amirt",
    "gn:population":0,
    "gn:timezone":"Asia/Kolkata",
    "iso:country":"IN",
    "wof:name":"Muhammadpur Taluka Rampur Amirt",
    "wof:placetype":"neighbourhood"
},
  "geometry": {"coordinates":[79.91101999999999,28.24219],"type":"Point"}
}