{
  "type": "Feature",
  "properties": {
    "iso:country":"IN",
    "ks:ks_name":"Chipada",
    "ks:ks_pop":157,
    "ks:ks_type":"HABITATION",
    "name:eng_x_preferred":[
        "Chipada"
    ],
    "wof:name":"Chipada",
    "wof:placetype":"locality",
    "wof:population":157
},
  "geometry": {"coordinates":[72.988634,19.773139],"type":"Point"}
}