{
  "type": "Feature",
  "properties": {
    "gn:admin1_code":"36.0",
    "gn:admin2_code":"181.0",
    "gn:asciiname":"Sangramganj",
    "gn:country_code":"IN",
    "gn:dem":120,
    "gn:feature_class":"P",
    "gn:feature_code":"PPL",
    "gn:name":"Sangr\u0101mganj",
    "gn:population":0,
    "gn:timezone":"Asia/Kolkata",
    "iso:country":"IN",
    "ks:ks_alt_nam":"Sangr\u0101mganj",
    "ks:ks_name":"Sangramganj",
    "ks:ks_pop":1083,
    "ks:ks_type":"VILLAGE",
    "name:eng_x_preferred":[
        "Sangramganj"
    ],
    "name:eng_x_variant":[
        "Sangr\u0101mganj"
    ],
    "wof:name":"Sangramganj",
    "wof:placetype":"locality",
    "wof:population":1083
},
  "geometry": {"coordinates":[82.048761,27.658759],"type":"Point"}
}