{
  "type": "Feature",
  "properties": {
    "gn:admin1_code":"36",
    "gn:admin2_code":"199.0",
    "gn:asciiname":"Kotwa",
    "gn:country_code":"IN",
    "gn:dem":152,
    "gn:feature_class":"P",
    "gn:feature_code":"PPL",
    "gn:name":"Kotwa",
    "gn:population":0,
    "gn:timezone":"Asia/Kolkata",
    "iso:country":"IN",
    "name:bpy_x_preferred":[
        "\u0995\u09cb\u09a4\u09c1\u09f1\u09be"
    ],
    "name:ceb_x_preferred":[
        "Kotwa"
    ],
    "name:ita_x_preferred":[
        "Kotwa"
    ],
    "name:msa_x_preferred":[
        "Kotwa"
    ],
    "name:new_x_preferred":[
        "\u0915\u094b\u0924\u094d\u0935\u093e"
    ],
    "name:nld_x_preferred":[
        "Kotwa"
    ],
    "name:pol_x_preferred":[
        "Kotwa"
    ],
    "name:por_x_preferred":[
        "Kotwa"
    ],
    "name:swe_x_preferred":[
        "Kotwa"
    ],
    "name:urd_x_preferred":[
        "\u06a9\u0648\u0679\u0648\u0627"
    ],
    "name:vie_x_preferred":[
        "Kotwa"
    ],
    "name:zho_x_preferred":[
        "\u79d1\u7279\u74e6"
    ],
    "wof:name":"Kotwa",
    "wof:placetype":"locality"
},
  "geometry": {"coordinates":[82.60424,25.02025],"type":"Point"}
}