{
  "type": "Feature",
  "properties": {
    "iso:country":"IN",
    "ks:ks_name":"Nadavaradahalli",
    "ks:ks_pop":143,
    "ks:ks_type":"HABITATION",
    "name:eng_x_preferred":[
        "Nadavaradahalli"
    ],
    "wof:name":"Nadavaradahalli",
    "wof:placetype":"locality",
    "wof:population":143
},
  "geometry": {"coordinates":[74.977512,14.11197],"type":"Point"}
}