{
  "type": "Feature",
  "properties": {
    "iso:country":"IN",
    "ks:ks_name":"Bedjharia",
    "ks:ks_pop":158,
    "ks:ks_type":"VILLAGE",
    "name:eng_x_preferred":[
        "Bedjharia"
    ],
    "wof:name":"Bedjharia",
    "wof:placetype":"locality",
    "wof:population":158
},
  "geometry": {"coordinates":[87.084667,21.966453],"type":"Point"}
}