{
  "type": "Feature",
  "properties": {
    "iso:country":"IN",
    "ks:ks_alt_nam":"PATILWASTI",
    "ks:ks_name":"Patilwasti",
    "ks:ks_pop":220,
    "ks:ks_type":"HABITATION",
    "name:eng_x_preferred":[
        "Patilwasti"
    ],
    "wof:name":"Patilwasti",
    "wof:placetype":"locality",
    "wof:population":220
},
  "geometry": {"coordinates":[74.29899500000001,16.942216],"type":"Point"}
}