{
  "type": "Feature",
  "properties": {
    "iso:country":"IN",
    "ks:ks_name":"Vandre",
    "ks:ks_pop":215,
    "ks:ks_type":"VILLAGE",
    "name:eng_x_preferred":[
        "Vandre"
    ],
    "wof:name":"Vandre",
    "wof:placetype":"locality",
    "wof:population":215
},
  "geometry": {"coordinates":[73.214831,19.483383],"type":"Point"}
}