{
  "type": "Feature",
  "properties": {
    "iso:country":"IN",
    "ks:ks_name":"Pullamkulam",
    "ks:ks_pop":724,
    "ks:ks_type":"HABITATION",
    "name:eng_x_preferred":[
        "Pullamkulam"
    ],
    "wof:name":"Pullamkulam",
    "wof:placetype":"locality",
    "wof:population":724
},
  "geometry": {"coordinates":[76.288298,10.619064],"type":"Point"}
}