{
  "type": "Feature",
  "properties": {
    "iso:country":"IN",
    "ks:ks_name":"Kadakinbail",
    "ks:ks_pop":51,
    "ks:ks_type":"HABITATION",
    "name:eng_x_preferred":[
        "Kadakinbail"
    ],
    "wof:name":"Kadakinbail",
    "wof:placetype":"locality",
    "wof:population":51
},
  "geometry": {"coordinates":[74.71729000000001,14.667242],"type":"Point"}
}