{
  "type": "Feature",
  "properties": {
    "gn:admin1_code":"16.0",
    "gn:admin2_code":"522",
    "gn:asciiname":"Jowla",
    "gn:country_code":"IN",
    "gn:dem":534,
    "gn:feature_class":"P",
    "gn:feature_code":"PPL",
    "gn:name":"Jowla",
    "gn:population":0,
    "gn:timezone":"Asia/Kolkata",
    "iso:country":"IN",
    "wof:name":"Jowla",
    "wof:placetype":"locality"
},
  "geometry": {"coordinates":[75.27095,18.54534],"type":"Point"}
}