{
  "type": "Feature",
  "properties": {
    "iso:country":"IN",
    "ks:ks_name":"Alipur",
    "ks:ks_pop":5,
    "ks:ks_type":"VILLAGE",
    "name:eng_x_preferred":[
        "Alipur"
    ],
    "wof:name":"Alipur",
    "wof:placetype":"locality",
    "wof:population":5
},
  "geometry": {"coordinates":[77.04826300000001,30.594046],"type":"Point"}
}