{
  "type": "Feature",
  "properties": {
    "gn:admin1_code":"37.0",
    "gn:admin2_code":"404.0",
    "gn:asciiname":"Tilaidand",
    "gn:country_code":"IN",
    "gn:dem":635,
    "gn:feature_class":"P",
    "gn:feature_code":"PPL",
    "gn:name":"Tilaidand",
    "gn:population":0,
    "gn:timezone":"Asia/Kolkata",
    "iso:country":"IN",
    "ks:ks_alt_nam":"Tilaid\u0101nd",
    "ks:ks_name":"Tilaidand",
    "ks:ks_type":"VILLAGE",
    "name:eng_x_preferred":[
        "Tilaidand"
    ],
    "name:eng_x_variant":[
        "Tilaid\u0101nd"
    ],
    "wof:name":"Tilaidand",
    "wof:placetype":"locality"
},
  "geometry": {"coordinates":[82.29962399999999,22.736652],"type":"Point"}
}