{
  "type": "Feature",
  "properties": {
    "gn:admin1_code":"35",
    "gn:asciiname":"Shahpura",
    "gn:country_code":"IN",
    "gn:dem":176,
    "gn:feature_class":"P",
    "gn:feature_code":"PPL",
    "gn:name":"Sh\u0101hpura",
    "gn:population":0,
    "gn:timezone":"Asia/Kolkata",
    "iso:country":"IN",
    "name:ara_x_preferred":[
        "\u0634\u0627\u0647\u0628\u0648\u0631\u0627"
    ],
    "name:ben_bn_x_preferred":[
        "\u09b6\u09be\u09b9\u09aa\u09c1\u09b0\u09be"
    ],
    "name:ben_in_x_preferred":[
        "\u09b6\u09be\u09b9\u09aa\u09c1\u09b0\u09be"
    ],
    "name:bpy_x_preferred":[
        "\u09b6\u09be\u09b9\u09aa\u09c1\u09b0\u09be"
    ],
    "name:cat_x_preferred":[
        "Shahpura"
    ],
    "name:deu_x_preferred":[
        "Shahpura"
    ],
    "name:guj_x_preferred":[
        "\u0ab6\u0abe\u0ab9\u0aaa\u0ac1\u0ab0\u0abe"
    ],
    "name:hin_x_preferred":[
        "\u0936\u093e\u0939\u092a\u0941\u0930\u093e"
    ],
    "name:ita_x_preferred":[
        "Shahpura"
    ],
    "name:kan_x_preferred":[
        "\u0cb6\u0cbe\u0cb9\u0ccd"
    ],
    "name:mal_x_preferred":[
        "\u0d37\u0d3e\u0d2a\u0d41\u0d30"
    ],
    "name:mar_x_preferred":[
        "\u0936\u093e\u0939\u092a\u0941\u0930\u093e"
    ],
    "name:pan_x_preferred":[
        "\u0a36\u0a3e\u0a39\u0a2a\u0a41\u0a30\u0a3e"
    ],
    "name:tam_x_preferred":[
        "\u0bb7\u0bbe\u0baa\u0bc1\u0bb0\u0bbe"
    ],
    "name:tel_x_preferred":[
        "\u0c37\u0c3e\u0c2a\u0c41\u0c30\u0c3e"
    ],
    "name:urd_x_preferred":[
        "\u0634\u0627\u06c1 \u067e\u0648\u0631\u06c1"
    ],
    "wof:name":"Shahpura",
    "wof:placetype":"locality"
},
  "geometry": {"coordinates":[78.88639000000001,25.5573],"type":"Point"}
}