{
  "type": "Feature",
  "properties": {
    "iso:country":"IN",
    "ks:ks_name":"Sindwani Laga Kanda",
    "ks:ks_pop":98,
    "ks:ks_type":"VILLAGE",
    "name:eng_x_preferred":[
        "Sindwani Laga Kanda"
    ],
    "wof:name":"Sindwani Laga Kanda",
    "wof:placetype":"locality",
    "wof:population":98
},
  "geometry": {"coordinates":[79.12642,30.263993],"type":"Point"}
}