{
  "type": "Feature",
  "properties": {
    "iso:country":"IN",
    "ks:ks_name":"Nakudisaru",
    "ks:ks_pop":226,
    "ks:ks_type":"VILLAGE",
    "name:eng_x_preferred":[
        "Nakudisaru"
    ],
    "wof:name":"Nakudisaru",
    "wof:placetype":"locality",
    "wof:population":226
},
  "geometry": {"coordinates":[84.09784500000001,20.480526],"type":"Point"}
}