{
  "type": "Feature",
  "properties": {
    "gn:admin1_code":"34",
    "gn:admin2_code":"218.0",
    "gn:asciiname":"Bangra",
    "gn:country_code":"IN",
    "gn:dem":63,
    "gn:feature_class":"P",
    "gn:feature_code":"PPL",
    "gn:name":"Bangra",
    "gn:population":0,
    "gn:timezone":"Asia/Kolkata",
    "iso:country":"IN",
    "ks:ks_name":"Bangra",
    "ks:ks_pop":713,
    "ks:ks_type":"VILLAGE",
    "ks:ks_uagg_main":0,
    "name:eng_x_preferred":[
        "Bangra"
    ],
    "wof:name":"Bangra",
    "wof:placetype":"neighbourhood",
    "wof:population":713
},
  "geometry": {"coordinates":[84.37255999999999,26.04748],"type":"Point"}
}