{
  "type": "Feature",
  "properties": {
    "iso:country":"IN",
    "ks:ks_name":"Bakadamai",
    "ks:ks_pop":70,
    "ks:ks_type":"VILLAGE",
    "name:eng_x_preferred":[
        "Bakadamai"
    ],
    "wof:name":"Bakadamai",
    "wof:placetype":"locality",
    "wof:population":70
},
  "geometry": {"coordinates":[84.04577,20.451027],"type":"Point"}
}