{
  "type": "Feature",
  "properties": {
    "iso:country":"IN",
    "ks:ks_name":"Swargabrahmapur",
    "ks:ks_pop":540,
    "ks:ks_type":"VILLAGE",
    "ks:ks_uagg_main":0,
    "name:eng_x_preferred":[
        "Swargabrahmapur"
    ],
    "wof:name":"Swargabrahmapur",
    "wof:placetype":"neighbourhood",
    "wof:population":540
},
  "geometry": {"coordinates":[86.169611,20.32474],"type":"Point"}
}