{
  "type": "Feature",
  "properties": {
    "gn:admin1_code":"2",
    "gn:admin2_code":"544.0",
    "gn:asciiname":"Nandiguda",
    "gn:country_code":"IN",
    "gn:dem":1012,
    "gn:feature_class":"P",
    "gn:feature_code":"PPL",
    "gn:name":"Nandig\u016bda",
    "gn:population":0,
    "gn:timezone":"Asia/Kolkata",
    "iso:country":"IN",
    "wof:name":"Nandiguda",
    "wof:placetype":"locality"
},
  "geometry": {"coordinates":[82.80634000000001,18.25237000000001],"type":"Point"}
}