{
  "type": "Feature",
  "properties": {
    "iso:country":"IN",
    "ks:ks_name":"Diha",
    "ks:ks_type":"VILLAGE",
    "name:eng_x_preferred":[
        "Diha"
    ],
    "wof:name":"Diha",
    "wof:placetype":"locality"
},
  "geometry": {"coordinates":[79.951179,25.747806],"type":"Point"}
}