{
  "type": "Feature",
  "properties": {
    "iso:country":"IN",
    "ks:ks_name":"Dabba",
    "ks:ks_pop":356,
    "ks:ks_type":"VILLAGE",
    "name:eng_x_preferred":[
        "Dabba"
    ],
    "wof:name":"Dabba",
    "wof:placetype":"locality",
    "wof:population":356
},
  "geometry": {"coordinates":[81.60895499999999,18.708725],"type":"Point"}
}