{
  "type": "Feature",
  "properties": {
    "gn:admin1_code":"10.0",
    "gn:admin2_code":"77.0",
    "gn:asciiname":"Dhakal",
    "gn:country_code":"IN",
    "gn:dem":234,
    "gn:feature_class":"P",
    "gn:feature_code":"PPL",
    "gn:name":"Dh\u0101kal",
    "gn:population":0,
    "gn:timezone":"Asia/Kolkata",
    "iso:country":"IN",
    "name:nep_x_preferred":[
        "\u0922\u0915\u093e\u0932"
    ],
    "wof:name":"Dhakal",
    "wof:placetype":"locality"
},
  "geometry": {"coordinates":[76.16101999999999,29.58759],"type":"Point"}
}