{
  "type": "Feature",
  "properties": {
    "gn:admin1_code":"36",
    "gn:admin2_code":"191.0",
    "gn:asciiname":"Sheoka Abirpur",
    "gn:country_code":"IN",
    "gn:dem":81,
    "gn:feature_class":"P",
    "gn:feature_code":"PPL",
    "gn:name":"Sheoka Ab\u012brpur",
    "gn:population":0,
    "gn:timezone":"Asia/Kolkata",
    "iso:country":"IN",
    "ks:ks_name":"Sihuka Abirpur",
    "ks:ks_pop":1105,
    "ks:ks_type":"VILLAGE",
    "name:eng_x_preferred":[
        "Sihuka Abirpur"
    ],
    "name:eng_x_variant":[
        "Sheoka Abirpur"
    ],
    "wof:name":"Sihuka Abirpur",
    "wof:placetype":"locality",
    "wof:population":1105
},
  "geometry": {"coordinates":[83.130899,25.700162],"type":"Point"}
}