{
  "type": "Feature",
  "properties": {
    "iso:country":"IN",
    "ks:ks_alt_nam":"Bandhariya urt Patkheda",
    "ks:ks_name":"Bandhariya Urt Patkheda",
    "ks:ks_pop":584,
    "ks:ks_type":"HABITATION",
    "name:eng_x_preferred":[
        "Bandhariya Urt Patkheda"
    ],
    "wof:name":"Bandhariya Urt Patkheda",
    "wof:placetype":"locality",
    "wof:population":584
},
  "geometry": {"coordinates":[76.730096,22.160146],"type":"Point"}
}