{
  "type": "Feature",
  "properties": {
    "iso:country":"IN",
    "ks:ks_name":"Nadibettu Kervashe",
    "ks:ks_pop":135,
    "ks:ks_type":"HABITATION",
    "name:eng_x_preferred":[
        "Nadibettu Kervashe"
    ],
    "wof:name":"Nadibettu Kervashe",
    "wof:placetype":"locality",
    "wof:population":135
},
  "geometry": {"coordinates":[75.06500800000001,13.259366],"type":"Point"}
}