{
  "type": "Feature",
  "properties": {
    "gn:admin1_code":"25.0",
    "gn:admin2_code":"633.0",
    "gn:asciiname":"Ottaitalaiyampadi",
    "gn:country_code":"IN",
    "gn:dem":315,
    "gn:feature_class":"P",
    "gn:feature_code":"PPL",
    "gn:name":"Ottaitalaiyampadi",
    "gn:population":0,
    "gn:timezone":"Asia/Kolkata",
    "iso:country":"IN",
    "wof:name":"Ottaitalaiyampadi",
    "wof:placetype":"locality"
},
  "geometry": {"coordinates":[77.39146,11.25176],"type":"Point"}
}