{
  "type": "Feature",
  "properties": {
    "iso:country":"IN",
    "ks:ks_name":"Nishal Falia",
    "ks:ks_pop":281,
    "ks:ks_type":"HABITATION",
    "name:eng_x_preferred":[
        "Nishal Falia"
    ],
    "wof:name":"Nishal Falia",
    "wof:placetype":"locality",
    "wof:population":281
},
  "geometry": {"coordinates":[73.761717,22.749183],"type":"Point"}
}