{
  "type": "Feature",
  "properties": {
    "gn:admin1_code":"24.0",
    "gn:admin2_code":"121",
    "gn:asciiname":"Ganpatpura",
    "gn:country_code":"IN",
    "gn:dem":251,
    "gn:feature_class":"P",
    "gn:feature_code":"PPL",
    "gn:name":"Ganpatpura",
    "gn:population":0,
    "gn:timezone":"Asia/Kolkata",
    "iso:country":"IN",
    "wof:name":"Ganpatpura",
    "wof:placetype":"locality"
},
  "geometry": {"coordinates":[75.69901999999998,25.46093],"type":"Point"}
}