{
  "type": "Feature",
  "properties": {
    "gn:admin1_code":"36.0",
    "gn:admin2_code":"186",
    "gn:asciiname":"Baghnagar",
    "gn:country_code":"IN",
    "gn:dem":84,
    "gn:feature_class":"P",
    "gn:feature_code":"PPL",
    "gn:name":"B\u0101ghnagar",
    "gn:population":0,
    "gn:timezone":"Asia/Kolkata",
    "iso:country":"IN",
    "wof:name":"Baghnagar",
    "wof:placetype":"neighbourhood"
},
  "geometry": {"coordinates":[83.08461,26.91642],"type":"Point"}
}