{
  "type": "Feature",
  "properties": {
    "iso:country":"IN",
    "ks:ks_name":"Kalathuveedu",
    "ks:ks_pop":100,
    "ks:ks_type":"HABITATION",
    "name:eng_x_preferred":[
        "Kalathuveedu"
    ],
    "wof:name":"Kalathuveedu",
    "wof:placetype":"locality",
    "wof:population":100
},
  "geometry": {"coordinates":[78.582421,10.638933],"type":"Point"}
}