{
  "type": "Feature",
  "properties": {
    "gn:admin1_code":"18.0",
    "gn:admin2_code":"296.0",
    "gn:asciiname":"Langdiangngan",
    "gn:country_code":"IN",
    "gn:dem":373,
    "gn:feature_class":"P",
    "gn:feature_code":"PPL",
    "gn:name":"Langdiangngan",
    "gn:population":0,
    "gn:timezone":"Asia/Kolkata",
    "iso:country":"IN",
    "wof:name":"Langdiangngan",
    "wof:placetype":"locality"
},
  "geometry": {"coordinates":[90.9919,25.28087],"type":"Point"}
}