{
  "type": "Feature",
  "properties": {
    "iso:country":"IN",
    "ks:ks_name":"Godgawan",
    "ks:ks_pop":546,
    "ks:ks_type":"HABITATION",
    "name:eng_x_preferred":[
        "Godgawan"
    ],
    "wof:name":"Godgawan",
    "wof:placetype":"locality",
    "wof:population":546
},
  "geometry": {"coordinates":[82.32159799999999,24.322347],"type":"Point"}
}