{
  "type": "Feature",
  "properties": {
    "iso:country":"IN",
    "ks:ks_name":"Fatehpur",
    "ks:ks_pop":196,
    "ks:ks_type":"HABITATION",
    "name:eng_x_preferred":[
        "Fatehpur"
    ],
    "wof:name":"Fatehpur",
    "wof:placetype":"locality",
    "wof:population":196
},
  "geometry": {"coordinates":[77.29551499999999,24.453246],"type":"Point"}
}