{
  "type": "Feature",
  "properties": {
    "iso:country":"IN",
    "ks:ks_name":"Kottapuram",
    "ks:ks_pop":463,
    "ks:ks_type":"HABITATION",
    "name:eng_x_preferred":[
        "Kottapuram"
    ],
    "wof:name":"Kottapuram",
    "wof:placetype":"locality",
    "wof:population":463
},
  "geometry": {"coordinates":[76.905811,8.842298],"type":"Point"}
}