{
  "type": "Feature",
  "properties": {
    "iso:country":"IN",
    "ks:ks_name":"Khajuri Sukhanandan",
    "ks:ks_pop":96,
    "ks:ks_type":"VILLAGE",
    "name:eng_x_preferred":[
        "Khajuri Sukhanandan"
    ],
    "wof:name":"Khajuri Sukhanandan",
    "wof:placetype":"locality",
    "wof:population":96
},
  "geometry": {"coordinates":[81.246522,24.417447],"type":"Point"}
}