{
  "type": "Feature",
  "properties": {
    "iso:country":"IN",
    "ks:ks_name":"Kattappara",
    "ks:ks_pop":255,
    "ks:ks_type":"HABITATION",
    "name:eng_x_preferred":[
        "Kattappara"
    ],
    "wof:name":"Kattappara",
    "wof:placetype":"locality",
    "wof:population":255
},
  "geometry": {"coordinates":[77.069821,9.912257],"type":"Point"}
}