{
  "type": "Feature",
  "properties": {
    "iso:country":"IN",
    "ks:ks_name":"Ranipura",
    "ks:ks_pop":95,
    "ks:ks_type":"HABITATION",
    "name:eng_x_preferred":[
        "Ranipura"
    ],
    "wof:name":"Ranipura",
    "wof:placetype":"locality",
    "wof:population":95
},
  "geometry": {"coordinates":[72.080833,23.363011],"type":"Point"}
}