{
  "type": "Feature",
  "properties": {
    "iso:country":"IN",
    "ks:ks_name":"Niz-Gerua",
    "ks:ks_pop":1231,
    "ks:ks_type":"VILLAGE",
    "ks:ks_uagg_main":0,
    "name:eng_x_preferred":[
        "Niz-Gerua"
    ],
    "wof:name":"Niz-Gerua",
    "wof:placetype":"neighbourhood",
    "wof:population":1231
},
  "geometry": {"coordinates":[92.233734,26.343084],"type":"Point"}
}