{
  "type": "Feature",
  "properties": {
    "iso:country":"IN",
    "ks:ks_name":"Varnawadi",
    "ks:ks_pop":54,
    "ks:ks_type":"HABITATION",
    "name:eng_x_preferred":[
        "Varnawadi"
    ],
    "wof:name":"Varnawadi",
    "wof:placetype":"locality",
    "wof:population":54
},
  "geometry": {"coordinates":[73.129812,18.798167],"type":"Point"}
}