{
  "type": "Feature",
  "properties": {
    "gn:admin1_code":"16",
    "gn:admin2_code":"510.0",
    "gn:asciiname":"Majra",
    "gn:country_code":"IN",
    "gn:dem":288,
    "gn:feature_class":"P",
    "gn:feature_code":"PPL",
    "gn:name":"Majra",
    "gn:population":0,
    "gn:timezone":"Asia/Kolkata",
    "iso:country":"IN",
    "name:ara_x_preferred":[
        "\u0645\u0627\u062c\u064a\u0631\u0627"
    ],
    "name:ben_bn_x_preferred":[
        "\u09ae\u09be\u099c\u09b0\u09be"
    ],
    "name:ben_in_x_preferred":[
        "\u09ae\u09be\u099c\u09b0\u09be"
    ],
    "name:guj_x_preferred":[
        "\u0aae\u0abe\u0a9c\u0acd\u0ab0\u0abe"
    ],
    "name:hin_x_preferred":[
        "\u092e\u093e\u091c\u0930\u093e"
    ],
    "name:kan_x_preferred":[
        "\u0cae\u0cbe\u0c9c\u0ccd\u0cb0\u0cbe"
    ],
    "name:mal_x_preferred":[
        "\u0d2e\u0d1c\u0d4d"
    ],
    "name:mar_x_preferred":[
        "\u092e\u093e\u091c\u0930\u093e"
    ],
    "name:pan_x_preferred":[
        "\u0a2e\u0a3e\u0a1c\u0a30\u0a3e"
    ],
    "name:tam_x_preferred":[
        "\u0bae\u0b9c\u0bcd\u0bb0\u0bbe"
    ],
    "name:tel_x_preferred":[
        "\u0c2e\u0c1c\u0c4d\u0c30\u0c3e"
    ],
    "name:urd_x_preferred":[
        "\u0645\u0627\u062c\u0631\u0627"
    ],
    "wof:name":"Majra",
    "wof:placetype":"neighbourhood"
},
  "geometry": {"coordinates":[78.47443,20.34382],"type":"Point"}
}