{
  "type": "Feature",
  "properties": {
    "iso:country":"IN",
    "ks:ks_name":"Pipaliya Khurd",
    "ks:ks_pop":207,
    "ks:ks_type":"HABITATION",
    "name:eng_x_preferred":[
        "Pipaliya Khurd"
    ],
    "wof:name":"Pipaliya Khurd",
    "wof:placetype":"locality",
    "wof:population":207
},
  "geometry": {"coordinates":[77.746409,23.468864],"type":"Point"}
}