{
  "type": "Feature",
  "properties": {
    "iso:country":"IN",
    "ks:ks_name":"Baribancha",
    "ks:ks_pop":18,
    "ks:ks_type":"VILLAGE",
    "name:eng_x_preferred":[
        "Baribancha"
    ],
    "wof:name":"Baribancha",
    "wof:placetype":"locality",
    "wof:population":18
},
  "geometry": {"coordinates":[81.408323,17.85046],"type":"Point"}
}