{
  "type": "Feature",
  "properties": {
    "gn:admin1_code":"16.0",
    "gn:admin2_code":"508",
    "gn:asciiname":"Amgaon",
    "gn:country_code":"IN",
    "gn:dem":228,
    "gn:feature_class":"P",
    "gn:feature_code":"PPL",
    "gn:name":"\u0100mgaon",
    "gn:population":0,
    "gn:timezone":"Asia/Kolkata",
    "iso:country":"IN",
    "name:und_x_variant":[
        "Ambgaon",
        "\u0100mgaon",
        "\u0100mgaon Butti"
    ],
    "wof:name":"Amgaon",
    "wof:placetype":"locality"
},
  "geometry": {"coordinates":[79.95352,20.64297],"type":"Point"}
}