{
  "type": "Feature",
  "properties": {
    "iso:country":"IN",
    "ks:ks_name":"Semalkhedi",
    "ks:ks_pop":255,
    "ks:ks_type":"VILLAGE",
    "name:eng_x_preferred":[
        "Semalkhedi"
    ],
    "wof:name":"Semalkhedi",
    "wof:placetype":"locality",
    "wof:population":255
},
  "geometry": {"coordinates":[76.68789,24.146559],"type":"Point"}
}