{
  "type": "Feature",
  "properties": {
    "iso:country":"IN",
    "ks:ks_name":"Dudhariya",
    "ks:ks_pop":121,
    "ks:ks_type":"HABITATION",
    "name:eng_x_preferred":[
        "Dudhariya"
    ],
    "wof:name":"Dudhariya",
    "wof:placetype":"locality",
    "wof:population":121
},
  "geometry": {"coordinates":[81.570826,23.362298],"type":"Point"}
}