{
  "type": "Feature",
  "properties": {
    "iso:country":"IN",
    "ks:ks_alt_nam":"Mahu\u0101t\u0101nr",
    "ks:ks_name":"Mahuatanr",
    "ks:ks_pop":428,
    "ks:ks_type":"VILLAGE",
    "name:eng_x_preferred":[
        "Mahuatanr"
    ],
    "name:eng_x_variant":[
        "Mahu\u0101t\u0101nr"
    ],
    "wof:name":"Mahuatanr",
    "wof:placetype":"locality",
    "wof:population":428
},
  "geometry": {"coordinates":[86.351592,24.11256],"type":"Point"}
}