{
  "type": "Feature",
  "properties": {
    "iso:country":"IN",
    "ks:ks_name":"Thakurpara",
    "ks:ks_pop":117,
    "ks:ks_type":"HABITATION",
    "name:eng_x_preferred":[
        "Thakurpara"
    ],
    "wof:name":"Thakurpara",
    "wof:placetype":"locality",
    "wof:population":117
},
  "geometry": {"coordinates":[80.709621,20.634518],"type":"Point"}
}