{
  "type": "Feature",
  "properties": {
    "iso:country":"IN",
    "ks:ks_name":"Gulab Garh Jagir",
    "ks:ks_pop":420,
    "ks:ks_type":"HABITATION",
    "name:eng_x_preferred":[
        "Gulab Garh Jagir"
    ],
    "wof:name":"Gulab Garh Jagir",
    "wof:placetype":"locality",
    "wof:population":420
},
  "geometry": {"coordinates":[75.842951,31.368032],"type":"Point"}
}