{
  "type": "Feature",
  "properties": {
    "iso:country":"IN",
    "ks:ks_name":"3 HLM",
    "ks:ks_pop":2863,
    "ks:ks_type":"VILLAGE",
    "name:eng_x_preferred":[
        "3 HLM"
    ],
    "wof:name":"3 HLM",
    "wof:placetype":"locality",
    "wof:population":2863
},
  "geometry": {"coordinates":[74.287172,29.318861],"type":"Point"}
}