{
  "type": "Feature",
  "properties": {
    "gn:admin1_code":"19.0",
    "gn:admin2_code":"583.0",
    "gn:asciiname":"Chikgolhalli",
    "gn:country_code":"IN",
    "gn:dem":949,
    "gn:feature_class":"P",
    "gn:feature_code":"PPL",
    "gn:name":"Chikgolhalli",
    "gn:population":0,
    "gn:timezone":"Asia/Kolkata",
    "iso:country":"IN",
    "wof:name":"Chikgolhalli",
    "wof:placetype":"locality"
},
  "geometry": {"coordinates":[77.65399000000002,13.29837],"type":"Point"}
}