{
  "type": "Feature",
  "properties": {
    "gn:admin1_code":"19.0",
    "gn:admin2_code":"571.0",
    "gn:asciiname":"Mahratipalya",
    "gn:country_code":"IN",
    "gn:dem":723,
    "gn:feature_class":"P",
    "gn:feature_code":"PPL",
    "gn:name":"Mahr\u0101tip\u0101lya",
    "gn:population":0,
    "gn:timezone":"Asia/Kolkata",
    "iso:country":"IN",
    "wof:name":"Mahratipalya",
    "wof:placetype":"locality"
},
  "geometry": {"coordinates":[76.47965000000001,13.59038],"type":"Point"}
}