{
  "type": "Feature",
  "properties": {
    "gn:admin1_code":"38.0",
    "gn:admin2_code":"348.0",
    "gn:asciiname":"Selahra Khurd",
    "gn:country_code":"IN",
    "gn:dem":375,
    "gn:feature_class":"P",
    "gn:feature_code":"PPL",
    "gn:name":"Selahra Khurd",
    "gn:population":0,
    "gn:timezone":"Asia/Kolkata",
    "iso:country":"IN",
    "ks:ks_name":"Selahra Khurd",
    "ks:ks_type":"VILLAGE",
    "name:eng_x_preferred":[
        "Selahra Khurd"
    ],
    "wof:name":"Selahra Khurd",
    "wof:placetype":"locality"
},
  "geometry": {"coordinates":[85.373546,24.389583],"type":"Point"}
}