{
  "type": "Feature",
  "properties": {
    "iso:country":"IN",
    "ks:ks_alt_nam":"Kalamagura part I",
    "ks:ks_name":"Kalamagura Part I",
    "ks:ks_pop":360,
    "ks:ks_type":"HABITATION",
    "name:eng_x_preferred":[
        "Kalamagura Part I"
    ],
    "wof:name":"Kalamagura Part I",
    "wof:placetype":"locality",
    "wof:population":360
},
  "geometry": {"coordinates":[92.37854799999999,24.314195],"type":"Point"}
}