{
  "type": "Feature",
  "properties": {
    "iso:country":"IN",
    "ks:ks_name":"Bernatte",
    "ks:ks_pop":120,
    "ks:ks_type":"HABITATION",
    "name:eng_x_preferred":[
        "Bernatte"
    ],
    "wof:name":"Bernatte",
    "wof:placetype":"locality",
    "wof:population":120
},
  "geometry": {"coordinates":[74.846495,13.581347],"type":"Point"}
}