{
  "type": "Feature",
  "properties": {
    "gn:admin1_code":"23",
    "gn:admin2_code":"36.0",
    "gn:asciiname":"Gulabgarh",
    "gn:country_code":"IN",
    "gn:dem":242,
    "gn:feature_class":"P",
    "gn:feature_code":"PPL",
    "gn:name":"Gul\u0101bgarh",
    "gn:population":0,
    "gn:timezone":"Asia/Kolkata",
    "iso:country":"IN",
    "wof:name":"Gulabgarh",
    "wof:placetype":"locality"
},
  "geometry": {"coordinates":[75.80291,31.26167],"type":"Point"}
}