{
  "type": "Feature",
  "properties": {
    "iso:country":"IN",
    "ks:ks_alt_nam":"MUNDA PARA",
    "ks:ks_name":"Munda Para",
    "ks:ks_pop":181,
    "ks:ks_type":"HABITATION",
    "ks:ks_uagg_main":0,
    "name:eng_x_preferred":[
        "Munda Para"
    ],
    "wof:name":"Munda Para",
    "wof:placetype":"neighbourhood",
    "wof:population":181
},
  "geometry": {"coordinates":[91.300264,23.973914],"type":"Point"}
}