{
  "type": "Feature",
  "properties": {
    "iso:country":"IN",
    "ks:ks_name":"Abbakunta",
    "ks:ks_pop":170,
    "ks:ks_type":"HABITATION",
    "name:eng_x_preferred":[
        "Abbakunta"
    ],
    "wof:name":"Abbakunta",
    "wof:placetype":"locality",
    "wof:population":170
},
  "geometry": {"coordinates":[78.39684699999999,12.7336],"type":"Point"}
}