{
  "type": "Feature",
  "properties": {
    "gn:admin1_code":"24",
    "gn:admin2_code":"123.0",
    "gn:asciiname":"Chhaparkheri",
    "gn:country_code":"IN",
    "gn:dem":564,
    "gn:feature_class":"P",
    "gn:feature_code":"PPL",
    "gn:name":"Chh\u0101parkheri",
    "gn:population":0,
    "gn:timezone":"Asia/Kolkata",
    "iso:country":"IN",
    "ks:ks_name":"Chhapar Kheri",
    "ks:ks_pop":1038,
    "ks:ks_type":"VILLAGE",
    "ks:ks_uagg_main":0,
    "name:eng_x_preferred":[
        "Chhapar Kheri"
    ],
    "wof:name":"Chhapar Kheri",
    "wof:placetype":"neighbourhood",
    "wof:population":1038
},
  "geometry": {"coordinates":[73.881506,25.126789],"type":"Point"}
}