{
  "type": "Feature",
  "properties": {
    "iso:country":"IN",
    "ks:ks_name":"Chauraha Tola",
    "ks:ks_pop":67,
    "ks:ks_type":"HABITATION",
    "ks:ks_uagg_main":0,
    "name:eng_x_preferred":[
        "Chauraha Tola"
    ],
    "wof:name":"Chauraha Tola",
    "wof:placetype":"neighbourhood",
    "wof:population":67
},
  "geometry": {"coordinates":[83.448161,27.115505],"type":"Point"}
}