{
  "type": "Feature",
  "properties": {
    "iso:country":"IN",
    "ks:ks_name":"Jerenga Habi",
    "ks:ks_pop":85,
    "ks:ks_type":"VILLAGE",
    "name:eng_x_preferred":[
        "Jerenga Habi"
    ],
    "wof:name":"Jerenga Habi",
    "wof:placetype":"locality",
    "wof:population":85
},
  "geometry": {"coordinates":[94.576156,26.926922],"type":"Point"}
}