{
  "type": "Feature",
  "properties": {
    "gn:admin1_code":"35",
    "gn:admin2_code":"429.0",
    "gn:asciiname":"Dureha",
    "gn:country_code":"IN",
    "gn:dem":374,
    "gn:feature_class":"P",
    "gn:feature_code":"PPL",
    "gn:name":"Dureha",
    "gn:population":0,
    "gn:timezone":"Asia/Kolkata",
    "iso:country":"IN",
    "wof:name":"Dureha",
    "wof:placetype":"locality"
},
  "geometry": {"coordinates":[80.46259999999999,24.45666],"type":"Point"}
}