{
  "type": "Feature",
  "properties": {
    "iso:country":"IN",
    "ks:ks_name":"Perukkupathy",
    "ks:ks_pop":160,
    "ks:ks_type":"HABITATION",
    "name:eng_x_preferred":[
        "Perukkupathy"
    ],
    "wof:name":"Perukkupathy",
    "wof:placetype":"locality",
    "wof:population":160
},
  "geometry": {"coordinates":[76.86421799999999,11.156849],"type":"Point"}
}