{
  "type": "Feature",
  "properties": {
    "iso:country":"IN",
    "ks:ks_name":"Birhipani",
    "ks:ks_pop":410,
    "ks:ks_type":"VILLAGE",
    "name:eng_x_preferred":[
        "Birhipani"
    ],
    "wof:name":"Birhipani",
    "wof:placetype":"locality",
    "wof:population":410
},
  "geometry": {"coordinates":[83.82296100000001,22.47077],"type":"Point"}
}