{
  "type": "Feature",
  "properties": {
    "iso:country":"IN",
    "ks:ks_name":"Madhya Para",
    "ks:ks_pop":1674,
    "ks:ks_type":"HABITATION",
    "ks:ks_uagg_main":0,
    "name:eng_x_preferred":[
        "Madhya Para"
    ],
    "wof:name":"Madhya Para",
    "wof:placetype":"neighbourhood",
    "wof:population":1674
},
  "geometry": {"coordinates":[88.071398,21.651653],"type":"Point"}
}