{
  "type": "Feature",
  "properties": {
    "iso:country":"IN",
    "ks:ks_name":"Ghadiyarao",
    "ks:ks_pop":77,
    "ks:ks_type":"HABITATION",
    "name:eng_x_preferred":[
        "Ghadiyarao"
    ],
    "wof:name":"Ghadiyarao",
    "wof:placetype":"locality",
    "wof:population":77
},
  "geometry": {"coordinates":[69.591336,23.654175],"type":"Point"}
}