{
  "type": "Feature",
  "properties": {
    "iso:country":"IN",
    "ks:ks_name":"Jubutia",
    "ks:ks_pop":1456,
    "ks:ks_type":"VILLAGE",
    "ks:ks_uagg_main":0,
    "name:eng_x_preferred":[
        "Jubutia"
    ],
    "wof:name":"Jubutia",
    "wof:placetype":"neighbourhood",
    "wof:population":1456
},
  "geometry": {"coordinates":[87.896176,23.762523],"type":"Point"}
}