{
  "type": "Feature",
  "properties": {
    "iso:country":"IN",
    "ks:ks_alt_nam":"bhalgarha",
    "ks:ks_name":"Bhalgarha",
    "ks:ks_pop":49,
    "ks:ks_type":"HABITATION",
    "name:eng_x_preferred":[
        "Bhalgarha"
    ],
    "wof:name":"Bhalgarha",
    "wof:placetype":"locality",
    "wof:population":49
},
  "geometry": {"coordinates":[86.58193300000001,24.32737],"type":"Point"}
}