{
  "type": "Feature",
  "properties": {
    "iso:country":"IN",
    "ks:ks_name":"Mau Nankar",
    "ks:ks_pop":1196,
    "ks:ks_type":"HABITATION",
    "name:eng_x_preferred":[
        "Mau Nankar"
    ],
    "wof:name":"Mau Nankar",
    "wof:placetype":"locality",
    "wof:population":1196
},
  "geometry": {"coordinates":[82.794117,27.276113],"type":"Point"}
}