{
  "type": "Feature",
  "properties": {
    "gn:admin1_code":"34.0",
    "gn:admin2_code":"221.0",
    "gn:asciiname":"Maharajganj",
    "gn:country_code":"IN",
    "gn:dem":52,
    "gn:feature_class":"P",
    "gn:feature_code":"PPL",
    "gn:name":"Mah\u0101r\u0101jganj",
    "gn:population":0,
    "gn:timezone":"Asia/Kolkata",
    "iso:country":"IN",
    "ks:ks_name":"Maharajganj",
    "ks:ks_pop":1271,
    "ks:ks_type":"VILLAGE",
    "name:ara_x_preferred":[
        "\u0645\u0647\u0631\u0627\u062c \u063a\u0627\u0646\u062c"
    ],
    "name:ben_bn_x_preferred":[
        "\u09ae\u09b9\u09be\u09b0\u09be\u099c\u0997\u099e\u09cd\u099c"
    ],
    "name:ben_in_x_preferred":[
        "\u09ae\u09b9\u09be\u09b0\u09be\u099c\u0997\u099e\u09cd\u099c"
    ],
    "name:ceb_x_preferred":[
        "Maharajganj"
    ],
    "name:deu_x_preferred":[
        "Maharajganj"
    ],
    "name:eng_x_preferred":[
        "Maharajganj"
    ],
    "name:guj_x_preferred":[
        "\u0aae\u0ab9\u0abe\u0ab0\u0abe\u0a9c\u0a97\u0a82\u0a9c"
    ],
    "name:hin_x_preferred":[
        "\u092e\u0939\u093e\u0930\u093e\u091c\u0917\u0902\u091c"
    ],
    "name:kan_x_preferred":[
        "\u0cae\u0cb9\u0cbe\u0cb0\u0cbe\u0c9c\u0ccd"
    ],
    "name:mal_x_preferred":[
        "\u0d2e\u0d39\u0d3e\u0d30\u0d3e\u0d1c\u0d4d\u0d17\u0d1e\u0d4d\u0d1a\u0d4d"
    ],
    "name:mar_x_preferred":[
        "\u092e\u0939\u093e\u0930\u093e\u091c\u0917\u0902\u091c"
    ],
    "name:nld_x_preferred":[
        "Maharajganj"
    ],
    "name:pan_x_preferred":[
        "\u0a2e\u0a39\u0a3e\u0a30\u0a3e\u0a1c\u0a17\u0a70\u0a1c"
    ],
    "name:pol_x_preferred":[
        "Maharajganj"
    ],
    "name:swe_x_preferred":[
        "Maharajganj"
    ],
    "name:tam_x_preferred":[
        "\u0bae\u0b95\u0bb0\u0bbe\u0b9c\u0bcd\u0b95\u0b9e\u0bcd\u0b9a\u0bcd"
    ],
    "name:tel_x_preferred":[
        "\u0c2e\u0c39\u0c30\u0c3e\u0c1c\u0c4d"
    ],
    "name:urd_x_preferred":[
        "\u0645\u06c1\u0627\u0631\u0627\u062c \u06af\u0646\u062c"
    ],
    "wof:name":"Maharajganj",
    "wof:placetype":"locality",
    "wof:population":1271
},
  "geometry": {"coordinates":[85.822329,25.867981],"type":"Point"}
}