{
  "type": "Feature",
  "properties": {
    "gn:country":"IN",
    "gn:fcode":"PPL",
    "gn:pop":22653,
    "iso:country":"IN",
    "name:ceb_x_preferred":[
        "Cumbum"
    ],
    "name:eng_x_preferred":[
        "Cumbum"
    ],
    "name:new_x_preferred":[
        "\u0915\u0902\u092d\u0902 \u092e\u0923\u094d\u0921\u0932"
    ],
    "name:nld_x_preferred":[
        "Cumbum"
    ],
    "name:swe_x_preferred":[
        "Cumbum"
    ],
    "name:tel_x_preferred":[
        "\u0c15\u0c02\u0c2d\u0c02"
    ],
    "name:unk_x_variant":[
        "Kambhamu"
    ],
    "name:urd_x_preferred":[
        "\u06a9\u0645\u0628\u0645\u060c \u0622\u0646\u062f\u06be\u0631\u0627 \u067e\u0631\u062f\u06cc\u0634"
    ],
    "name:urd_x_variant":[
        "\u06a9\u0645\u0628\u0645"
    ],
    "qs:name":"Cumbum",
    "qs:photos_9r":0,
    "qs:photos_sr":0,
    "qs:pop_sr":"7",
    "wd:wordcount":32,
    "wof:name":"Cumbum",
    "wof:placetype":"locality",
    "wof:population":22653
},
  "geometry": {"coordinates":[79.10981,15.58302],"type":"Point"}
}