{
  "type": "Feature",
  "properties": {
    "iso:country":"IN",
    "ks:ks_name":"Ingalemala",
    "ks:ks_pop":398,
    "ks:ks_type":"HABITATION",
    "ks:ks_uagg_main":0,
    "name:eng_x_preferred":[
        "Ingalemala"
    ],
    "wof:name":"Ingalemala",
    "wof:placetype":"neighbourhood",
    "wof:population":398
},
  "geometry": {"coordinates":[74.078191,18.585904],"type":"Point"}
}