{
  "type": "Feature",
  "properties": {
    "iso:country":"IN",
    "ks:ks_name":"Simlaposi",
    "ks:ks_pop":271,
    "ks:ks_type":"VILLAGE",
    "ks:ks_uagg_main":0,
    "name:eng_x_preferred":[
        "Simlaposi"
    ],
    "wof:name":"Simlaposi",
    "wof:placetype":"neighbourhood",
    "wof:population":271
},
  "geometry": {"coordinates":[85.81019499999999,21.92195],"type":"Point"}
}