{
  "type": "Feature",
  "properties": {
    "iso:country":"IN",
    "ks:ks_name":"Raitali Falia",
    "ks:ks_pop":182,
    "ks:ks_type":"HABITATION",
    "name:eng_x_preferred":[
        "Raitali Falia"
    ],
    "wof:name":"Raitali Falia",
    "wof:placetype":"locality",
    "wof:population":182
},
  "geometry": {"coordinates":[73.095944,20.220806],"type":"Point"}
}