{
  "type": "Feature",
  "properties": {
    "gn:admin1_code":"37",
    "gn:admin2_code":"406.0",
    "gn:asciiname":"Mahora",
    "gn:country_code":"IN",
    "gn:dem":591,
    "gn:feature_class":"P",
    "gn:feature_code":"PPL",
    "gn:name":"Mahora",
    "gn:population":0,
    "gn:timezone":"Asia/Kolkata",
    "iso:country":"IN",
    "ks:ks_name":"Mahora",
    "ks:ks_type":"VILLAGE",
    "name:ceb_x_preferred":[
        "Mahora"
    ],
    "name:eng_x_preferred":[
        "Mahora"
    ],
    "name:swe_x_preferred":[
        "Mahora"
    ],
    "wof:name":"Mahora",
    "wof:placetype":"locality"
},
  "geometry": {"coordinates":[81.97013800000001,22.836544],"type":"Point"}
}