{
  "type": "Feature",
  "properties": {
    "gn:admin1_code":"33.0",
    "gn:admin2_code":"585",
    "gn:asciiname":"Dumacem",
    "gn:country_code":"IN",
    "gn:dem":11,
    "gn:feature_class":"P",
    "gn:feature_code":"PPL",
    "gn:name":"Dumacem",
    "gn:population":0,
    "gn:timezone":"Asia/Kolkata",
    "iso:country":"IN",
    "ks:ks_name":"Dumacem",
    "ks:ks_pop":325,
    "ks:ks_type":"VILLAGE",
    "name:eng_x_preferred":[
        "Dumacem"
    ],
    "wof:name":"Dumacem",
    "wof:placetype":"locality",
    "wof:population":325
},
  "geometry": {"coordinates":[73.909271,15.676636],"type":"Point"}
}