{
  "type": "Feature",
  "properties": {
    "iso:country":"IN",
    "qs:name":"Hadla",
    "qs:name_adm0":"India",
    "qs:name_adm1":"West Bengal",
    "qs:photos":26,
    "qs:photos_1k":5,
    "qs:photos_9k":1,
    "qs:photos_9r":2,
    "qs:photos_all":26,
    "qs:photos_sr":2,
    "qs:placetype":"Town",
    "qs:pop_sr":"0",
    "wof:name":"Hadla",
    "wof:placetype":"locality"
},
  "geometry": {"coordinates":[86.8166255,23.7905475],"type":"Point"}
}