{
  "type": "Feature",
  "properties": {
    "gn:admin1_code":"16.0",
    "gn:admin2_code":"510.0",
    "gn:asciiname":"Kurhadi",
    "gn:country_code":"IN",
    "gn:dem":375,
    "gn:feature_class":"P",
    "gn:feature_code":"PPL",
    "gn:name":"Kurh\u0101di",
    "gn:population":0,
    "gn:timezone":"Asia/Kolkata",
    "iso:country":"IN",
    "ks:ks_alt_nam":"Kurh\u0101di",
    "ks:ks_name":"Kurhadi",
    "ks:ks_type":"VILLAGE",
    "name:eng_x_preferred":[
        "Kurhadi"
    ],
    "name:eng_x_variant":[
        "Kurh\u0101di"
    ],
    "wof:name":"Kurhadi",
    "wof:placetype":"locality"
},
  "geometry": {"coordinates":[77.45372399999999,19.973483],"type":"Point"}
}