{
  "type": "Feature",
  "properties": {
    "iso:country":"IN",
    "ks:ks_name":"Arari",
    "ks:ks_pop":126,
    "ks:ks_type":"HABITATION",
    "name:eng_x_preferred":[
        "Arari"
    ],
    "wof:name":"Arari",
    "wof:placetype":"locality",
    "wof:population":126
},
  "geometry": {"coordinates":[74.816191,13.67812],"type":"Point"}
}