{
  "type": "Feature",
  "properties": {
    "iso:country":"IN",
    "ks:ks_alt_nam":"MGR nagar",
    "ks:ks_name":"Mgr Nagar",
    "ks:ks_pop":140,
    "ks:ks_type":"HABITATION",
    "ks:ks_uagg_main":0,
    "name:eng_x_preferred":[
        "Mgr Nagar"
    ],
    "wof:name":"Mgr Nagar",
    "wof:placetype":"neighbourhood",
    "wof:population":140
},
  "geometry": {"coordinates":[77.215906,10.900686],"type":"Point"}
}