{
  "type": "Feature",
  "properties": {
    "gn:admin1_code":"36",
    "gn:admin2_code":"145.0",
    "gn:asciiname":"Tantura",
    "gn:country_code":"IN",
    "gn:dem":177,
    "gn:feature_class":"P",
    "gn:feature_code":"PPL",
    "gn:name":"Tant\u016bra",
    "gn:population":0,
    "gn:timezone":"Asia/Kolkata",
    "iso:country":"IN",
    "name:ara_x_preferred":[
        "\u0627\u0644\u0637\u0646\u0637\u0648\u0631\u0629"
    ],
    "name:fra_x_preferred":[
        "Al-Tantoura"
    ],
    "name:heb_x_preferred":[
        "\u05d8\u05e0\u05d8\u05d5\u05e8\u05d4"
    ],
    "name:nld_x_preferred":[
        "Al-Tantoera"
    ],
    "name:pol_x_preferred":[
        "Tantura"
    ],
    "name:spa_x_preferred":[
        "Tantura"
    ],
    "wof:name":"Tantura",
    "wof:placetype":"neighbourhood"
},
  "geometry": {"coordinates":[77.68819999999999,27.45255],"type":"Point"}
}