{
  "type": "Feature",
  "properties": {
    "iso:country":"IN",
    "ks:ks_name":"Shivamnagar",
    "ks:ks_pop":582,
    "ks:ks_type":"HABITATION",
    "name:eng_x_preferred":[
        "Shivamnagar"
    ],
    "wof:name":"Shivamnagar",
    "wof:placetype":"locality",
    "wof:population":582
},
  "geometry": {"coordinates":[71.65301100000001,24.761108],"type":"Point"}
}