{
  "type": "Feature",
  "properties": {
    "iso:country":"IN",
    "ks:ks_name":"Kesoi Bari",
    "ks:ks_pop":91,
    "ks:ks_type":"HABITATION",
    "name:eng_x_preferred":[
        "Kesoi Bari"
    ],
    "wof:name":"Kesoi Bari",
    "wof:placetype":"locality",
    "wof:population":91
},
  "geometry": {"coordinates":[91.531728,23.150704],"type":"Point"}
}