{
  "type": "Feature",
  "properties": {
    "gn:admin1_code":"39.0",
    "gn:admin2_code":"65.0",
    "gn:asciiname":"Diyarchaura",
    "gn:country_code":"IN",
    "gn:dem":1442,
    "gn:feature_class":"P",
    "gn:feature_code":"PPL",
    "gn:name":"Diy\u0101rchaura",
    "gn:population":0,
    "gn:timezone":"Asia/Kolkata",
    "iso:country":"IN",
    "wof:name":"Diyarchaura",
    "wof:placetype":"locality"
},
  "geometry": {"coordinates":[79.93759,29.30701],"type":"Point"}
}