{
  "type": "Feature",
  "properties": {
    "iso:country":"IN",
    "ks:ks_name":"Kakar",
    "ks:ks_pop":172,
    "ks:ks_type":"HABITATION",
    "ks:ks_uagg_main":0,
    "name:eng_x_preferred":[
        "Kakar"
    ],
    "wof:name":"Kakar",
    "wof:placetype":"neighbourhood",
    "wof:population":172
},
  "geometry": {"coordinates":[78.196962,27.10609],"type":"Point"}
}