{
  "type": "Feature",
  "properties": {
    "iso:country":"IN",
    "ks:ks_name":"Kogilkuli",
    "ks:ks_pop":60,
    "ks:ks_type":"HABITATION",
    "name:eng_x_preferred":[
        "Kogilkuli"
    ],
    "wof:name":"Kogilkuli",
    "wof:placetype":"locality",
    "wof:population":60
},
  "geometry": {"coordinates":[74.86448,14.667417],"type":"Point"}
}