{
  "type": "Feature",
  "properties": {
    "gn:admin1_code":"02",
    "gn:admin2_code":"542.0",
    "gn:asciiname":"Srikurmam",
    "gn:country_code":"IN",
    "gn:dem":11,
    "gn:feature_class":"P",
    "gn:feature_code":"PPL",
    "gn:name":"Sr\u012bk\u016brmam",
    "gn:population":0,
    "gn:timezone":"Asia/Kolkata",
    "iso:country":"IN",
    "wof:name":"Srikurmam",
    "wof:placetype":"locality"
},
  "geometry": {"coordinates":[84.00442,18.27085],"type":"Point"}
}