{
  "type": "Feature",
  "properties": {
    "iso:country":"IN",
    "ks:ks_name":"Basavanagudi",
    "ks:ks_pop":650,
    "ks:ks_type":"HABITATION",
    "name:eng_x_preferred":[
        "Basavanagudi"
    ],
    "wof:name":"Basavanagudi",
    "wof:placetype":"locality",
    "wof:population":650
},
  "geometry": {"coordinates":[77.26618999999999,11.892059],"type":"Point"}
}