{
  "type": "Feature",
  "properties": {
    "gn:admin1_code":"34.0",
    "gn:admin2_code":"220.0",
    "gn:asciiname":"Jhirwa Mal",
    "gn:country_code":"IN",
    "gn:dem":52,
    "gn:feature_class":"P",
    "gn:feature_code":"PPL",
    "gn:name":"Jhirwa M\u0101l",
    "gn:population":0,
    "gn:timezone":"Asia/Kolkata",
    "iso:country":"IN",
    "ks:ks_name":"Jhirua Mal",
    "ks:ks_pop":199,
    "ks:ks_type":"VILLAGE",
    "name:eng_x_preferred":[
        "Jhirua Mal"
    ],
    "name:eng_x_variant":[
        "Jhirwa Mal"
    ],
    "wof:name":"Jhirua Mal",
    "wof:placetype":"locality",
    "wof:population":199
},
  "geometry": {"coordinates":[85.24660299999999,25.724846],"type":"Point"}
}