{
  "type": "Feature",
  "properties": {
    "gn:admin1_code":"23.0",
    "gn:admin2_code":"46.0",
    "gn:asciiname":"Jogiwala",
    "gn:country_code":"IN",
    "gn:dem":208,
    "gn:feature_class":"P",
    "gn:feature_code":"PPL",
    "gn:name":"Jogiw\u0101la",
    "gn:population":0,
    "gn:timezone":"Asia/Kolkata",
    "iso:country":"IN",
    "wof:name":"Jogiwala",
    "wof:placetype":"locality"
},
  "geometry": {"coordinates":[75.06573,29.88596],"type":"Point"}
}