{
  "type": "Feature",
  "properties": {
    "iso:country":"IN",
    "ks:ks_alt_nam":"kambalewasti",
    "ks:ks_name":"Kambalewasti",
    "ks:ks_pop":110,
    "ks:ks_type":"HABITATION",
    "name:eng_x_preferred":[
        "Kambalewasti"
    ],
    "wof:name":"Kambalewasti",
    "wof:placetype":"locality",
    "wof:population":110
},
  "geometry": {"coordinates":[74.54665199999999,17.66612],"type":"Point"}
}