{
  "type": "Feature",
  "properties": {
    "iso:country":"IN",
    "ks:ks_alt_nam":"Pardhi wasti",
    "ks:ks_name":"Pardhi Wasti",
    "ks:ks_pop":182,
    "ks:ks_type":"HABITATION",
    "name:eng_x_preferred":[
        "Pardhi Wasti"
    ],
    "wof:name":"Pardhi Wasti",
    "wof:placetype":"locality",
    "wof:population":182
},
  "geometry": {"coordinates":[76.023554,18.440304],"type":"Point"}
}