{
  "type": "Feature",
  "properties": {
    "gn:admin1_code":"36",
    "gn:admin2_code":"200.0",
    "gn:asciiname":"Kharatia",
    "gn:country_code":"IN",
    "gn:dem":330,
    "gn:feature_class":"P",
    "gn:feature_code":"PPL",
    "gn:name":"Kharatia",
    "gn:population":0,
    "gn:timezone":"Asia/Kolkata",
    "iso:country":"IN",
    "ks:ks_name":"Kharatia",
    "ks:ks_pop":2290,
    "ks:ks_type":"VILLAGE",
    "name:eng_x_preferred":[
        "Kharatia"
    ],
    "wof:name":"Kharatia",
    "wof:placetype":"locality",
    "wof:population":2290
},
  "geometry": {"coordinates":[83.17582299999999,24.085329],"type":"Point"}
}