{
  "type": "Feature",
  "properties": {
    "gn:admin1_code":"16",
    "gn:admin2_code":"511.0",
    "gn:asciiname":"Tardada Tanda",
    "gn:country_code":"IN",
    "gn:dem":463,
    "gn:feature_class":"P",
    "gn:feature_code":"PPL",
    "gn:name":"T\u0101rdada T\u0101nda",
    "gn:population":0,
    "gn:timezone":"Asia/Kolkata",
    "iso:country":"IN",
    "wof:name":"Tardada Tanda",
    "wof:placetype":"neighbourhood"
},
  "geometry": {"coordinates":[77.36862000000001,18.61968],"type":"Point"}
}