{
  "type": "Feature",
  "properties": {
    "iso:country":"IN",
    "ks:ks_name":"Punnakunnusseri",
    "ks:ks_pop":1443,
    "ks:ks_type":"HABITATION",
    "name:eng_x_preferred":[
        "Punnakunnusseri"
    ],
    "wof:name":"Punnakunnusseri",
    "wof:placetype":"locality",
    "wof:population":1443
},
  "geometry": {"coordinates":[76.44273200000001,9.440375],"type":"Point"}
}