{
  "type": "Feature",
  "properties": {
    "gn:admin1_code":"36",
    "gn:admin2_code":"134.0",
    "gn:asciiname":"Hathuwala",
    "gn:country_code":"IN",
    "gn:dem":249,
    "gn:feature_class":"P",
    "gn:feature_code":"PPL",
    "gn:name":"Hath\u016bw\u0101la",
    "gn:population":0,
    "gn:timezone":"Asia/Kolkata",
    "iso:country":"IN",
    "ks:ks_alt_nam":"Hath\u016bw\u0101la",
    "ks:ks_name":"Hathuwala",
    "ks:ks_type":"VILLAGE",
    "name:eng_x_preferred":[
        "Hathuwala"
    ],
    "name:eng_x_variant":[
        "Hath\u016bw\u0101la"
    ],
    "wof:name":"Hathuwala",
    "wof:placetype":"locality"
},
  "geometry": {"coordinates":[78.44238799999999,29.52657],"type":"Point"}
}