{
  "type": "Feature",
  "properties": {
    "gn:admin1_code":"19.0",
    "gn:admin2_code":"563.0",
    "gn:asciiname":"Sayajipal",
    "gn:country_code":"IN",
    "gn:dem":536,
    "gn:feature_class":"P",
    "gn:feature_code":"PPL",
    "gn:name":"Say\u0101jip\u0101l",
    "gn:population":0,
    "gn:timezone":"Asia/Kolkata",
    "iso:country":"IN",
    "wof:name":"Sayajipal",
    "wof:placetype":"locality"
},
  "geometry": {"coordinates":[74.69577,14.94385],"type":"Point"}
}