{
  "type": "Feature",
  "properties": {
    "iso:country":"IN",
    "ks:ks_alt_nam":"Moothedam jn",
    "ks:ks_name":"Moothedam Jn",
    "ks:ks_pop":312,
    "ks:ks_type":"HABITATION",
    "ks:ks_uagg_main":0,
    "name:eng_x_preferred":[
        "Moothedam Jn"
    ],
    "wof:name":"Moothedam Jn",
    "wof:placetype":"neighbourhood",
    "wof:population":312
},
  "geometry": {"coordinates":[76.315405,11.330487],"type":"Point"}
}