{
  "type": "Feature",
  "properties": {
    "iso:country":"IN",
    "ks:ks_name":"Dunigram",
    "ks:ks_pop":856,
    "ks:ks_type":"VILLAGE",
    "ks:ks_uagg_main":0,
    "name:eng_x_preferred":[
        "Dunigram"
    ],
    "wof:name":"Dunigram",
    "wof:placetype":"neighbourhood",
    "wof:population":856
},
  "geometry": {"coordinates":[88.002438,24.079446],"type":"Point"}
}