{
  "type": "Feature",
  "properties": {
    "iso:country":"IN",
    "ks:ks_name":"Chak Kamakuri",
    "ks:ks_pop":0,
    "ks:ks_type":"VILLAGE",
    "name:eng_x_preferred":[
        "Chak Kamakuri"
    ],
    "wof:name":"Chak Kamakuri",
    "wof:placetype":"locality",
    "wof:population":0
},
  "geometry": {"coordinates":[86.51223,23.618704],"type":"Point"}
}