{
  "type": "Feature",
  "properties": {
    "gn:admin1_code":"23.0",
    "gn:admin2_code":"46.0",
    "gn:asciiname":"Jodhpur Pakhar",
    "gn:country_code":"IN",
    "gn:dem":211,
    "gn:feature_class":"P",
    "gn:feature_code":"PPL",
    "gn:name":"Jodhpur P\u0101khar",
    "gn:population":0,
    "gn:timezone":"Asia/Kolkata",
    "iso:country":"IN",
    "wof:name":"Jodhpur Pakhar",
    "wof:placetype":"locality"
},
  "geometry": {"coordinates":[75.14979,30.05342000000001],"type":"Point"}
}