{
  "type": "Feature",
  "properties": {
    "iso:country":"IN",
    "ks:ks_name":"Batisha Colony",
    "ks:ks_pop":486,
    "ks:ks_type":"HABITATION",
    "ks:ks_uagg_main":0,
    "name:eng_x_preferred":[
        "Batisha Colony"
    ],
    "wof:name":"Batisha Colony",
    "wof:placetype":"neighbourhood",
    "wof:population":486
},
  "geometry": {"coordinates":[91.337204,23.200802],"type":"Point"}
}