{
  "type": "Feature",
  "properties": {
    "iso:country":"IN",
    "ks:ks_name":"Ghata Pathar",
    "ks:ks_pop":304,
    "ks:ks_type":"VILLAGE",
    "ks:ks_uagg_main":0,
    "name:eng_x_preferred":[
        "Ghata Pathar"
    ],
    "wof:name":"Ghata Pathar",
    "wof:placetype":"neighbourhood",
    "wof:population":304
},
  "geometry": {"coordinates":[94.41573200000001,27.461007],"type":"Point"}
}