{
  "type": "Feature",
  "properties": {
    "iso:country":"IN",
    "ks:ks_alt_nam":"panchakkadu",
    "ks:ks_name":"Panchakkadu",
    "ks:ks_pop":325,
    "ks:ks_type":"HABITATION",
    "ks:ks_uagg_main":0,
    "name:eng_x_preferred":[
        "Panchakkadu"
    ],
    "wof:name":"Panchakkadu",
    "wof:placetype":"neighbourhood",
    "wof:population":325
},
  "geometry": {"coordinates":[76.44072799999999,10.327029],"type":"Point"}
}