{
  "type": "Feature",
  "properties": {
    "gn:admin1_code":"21.0",
    "gn:admin2_code":"398.0",
    "gn:asciiname":"Sukkalpara",
    "gn:country_code":"IN",
    "gn:dem":783,
    "gn:feature_class":"P",
    "gn:feature_code":"PPL",
    "gn:name":"Sukkalp\u0101ra",
    "gn:population":0,
    "gn:timezone":"Asia/Kolkata",
    "iso:country":"IN",
    "wof:name":"Sukkalpara",
    "wof:placetype":"locality"
},
  "geometry": {"coordinates":[82.46335000000001,18.6521],"type":"Point"}
}