{
  "type": "Feature",
  "properties": {
    "iso:country":"IN",
    "ks:ks_alt_nam":"MURINA",
    "ks:ks_name":"Murina",
    "ks:ks_pop":281,
    "ks:ks_type":"HABITATION",
    "name:eng_x_preferred":[
        "Murina"
    ],
    "wof:name":"Murina",
    "wof:placetype":"locality",
    "wof:population":281
},
  "geometry": {"coordinates":[85.28544100000001,24.355968],"type":"Point"}
}