{
  "type": "Feature",
  "properties": {
    "gn:admin1_code":"35.0",
    "gn:admin2_code":"457.0",
    "gn:asciiname":"Karhu",
    "gn:country_code":"IN",
    "gn:dem":575,
    "gn:feature_class":"P",
    "gn:feature_code":"PPL",
    "gn:name":"Karhu",
    "gn:population":0,
    "gn:timezone":"Asia/Kolkata",
    "iso:country":"IN",
    "name:ces_x_preferred":[
        "Karhu"
    ],
    "name:fin_x_preferred":[
        "Karhu"
    ],
    "name:jpn_x_preferred":[
        "\u30ab\u30eb\u30d5"
    ],
    "name:nld_x_preferred":[
        "Karhu"
    ],
    "name:swe_x_preferred":[
        "Karhu"
    ],
    "wof:name":"Karhu",
    "wof:placetype":"locality"
},
  "geometry": {"coordinates":[80.67898000000002,22.081],"type":"Point"}
}