{
  "type": "Feature",
  "properties": {
    "gn:admin1_code":"37",
    "gn:admin2_code":"407.0",
    "gn:asciiname":"Mahli",
    "gn:country_code":"IN",
    "gn:dem":786,
    "gn:feature_class":"P",
    "gn:feature_code":"PPL",
    "gn:name":"M\u0101hli",
    "gn:population":0,
    "gn:timezone":"Asia/Kolkata",
    "iso:country":"IN",
    "name:ceb_x_preferred":[
        "Mahli"
    ],
    "name:swe_x_preferred":[
        "Mahli"
    ],
    "wof:name":"Mahli",
    "wof:placetype":"locality"
},
  "geometry": {"coordinates":[81.10814000000001,22.26796],"type":"Point"}
}