{
  "type": "Feature",
  "properties": {
    "gn:admin1_code":"10",
    "gn:admin2_code":"69.0",
    "gn:asciiname":"Paploha",
    "gn:country_code":"IN",
    "gn:dem":586,
    "gn:feature_class":"P",
    "gn:feature_code":"PPL",
    "gn:name":"Paploha",
    "gn:population":0,
    "gn:timezone":"Asia/Kolkata",
    "iso:country":"IN",
    "wof:name":"Paploha",
    "wof:placetype":"locality"
},
  "geometry": {"coordinates":[76.90505999999998,30.84928],"type":"Point"}
}