{
  "type": "Feature",
  "properties": {
    "iso:country":"IN",
    "ks:ks_name":"Basak Para Ghogarkuti",
    "ks:ks_pop":1040,
    "ks:ks_type":"HABITATION",
    "name:eng_x_preferred":[
        "Basak Para Ghogarkuti"
    ],
    "wof:name":"Basak Para Ghogarkuti",
    "wof:placetype":"locality",
    "wof:population":1040
},
  "geometry": {"coordinates":[89.636914,26.301671],"type":"Point"}
}