{
  "type": "Feature",
  "properties": {
    "iso:country":"IN",
    "ks:ks_name":"Melinanayakarandahally",
    "ks:ks_pop":776,
    "ks:ks_type":"HABITATION",
    "name:eng_x_preferred":[
        "Melinanayakarandahally"
    ],
    "wof:name":"Melinanayakarandahally",
    "wof:placetype":"locality",
    "wof:population":776
},
  "geometry": {"coordinates":[77.552982,13.317918],"type":"Point"}
}