{
  "type": "Feature",
  "properties": {
    "iso:country":"IN",
    "ks:ks_name":"Ramdas Tapu",
    "ks:ks_pop":450,
    "ks:ks_type":"HABITATION",
    "name:eng_x_preferred":[
        "Ramdas Tapu"
    ],
    "wof:name":"Ramdas Tapu",
    "wof:placetype":"locality",
    "wof:population":450
},
  "geometry": {"coordinates":[92.44649200000001,26.558216],"type":"Point"}
}