{
  "type": "Feature",
  "properties": {
    "iso:country":"IN",
    "ks:ks_name":"Kharagpur",
    "ks:ks_pop":611,
    "ks:ks_type":"VILLAGE",
    "name:eng_x_preferred":[
        "Kharagpur"
    ],
    "wof:name":"Kharagpur",
    "wof:placetype":"locality",
    "wof:population":611
},
  "geometry": {"coordinates":[79.925526,28.691346],"type":"Point"}
}