{
  "type": "Feature",
  "properties": {
    "iso:country":"IN",
    "ks:ks_name":"Madhu Pura",
    "ks:ks_pop":0,
    "ks:ks_type":"VILLAGE",
    "name:eng_x_preferred":[
        "Madhu Pura"
    ],
    "wof:name":"Madhu Pura",
    "wof:placetype":"locality",
    "wof:population":0
},
  "geometry": {"coordinates":[78.948654,25.48874],"type":"Point"}
}