{
  "type": "Feature",
  "properties": {
    "iso:country":"IN",
    "ks:ks_name":"Shukpukuria",
    "ks:ks_pop":1425,
    "ks:ks_type":"VILLAGE",
    "ks:ks_uagg_main":0,
    "name:eng_x_preferred":[
        "Shukpukuria"
    ],
    "wof:name":"Shukpukuria",
    "wof:placetype":"neighbourhood",
    "wof:population":1425
},
  "geometry": {"coordinates":[88.82283200000001,23.077019],"type":"Point"}
}