{
  "type": "Feature",
  "properties": {
    "iso:country":"IN",
    "ks:ks_name":"Sabalsingpur",
    "ks:ks_pop":826,
    "ks:ks_type":"VILLAGE",
    "ks:ks_uagg_main":0,
    "name:eng_x_preferred":[
        "Sabalsingpur"
    ],
    "wof:name":"Sabalsingpur",
    "wof:placetype":"neighbourhood",
    "wof:population":826
},
  "geometry": {"coordinates":[86.31603,20.400605],"type":"Point"}
}