{
  "type": "Feature",
  "properties": {
    "iso:country":"IN",
    "ks:ks_name":"Vayambu",
    "ks:ks_pop":1983,
    "ks:ks_type":"HABITATION",
    "name:eng_x_preferred":[
        "Vayambu"
    ],
    "wof:name":"Vayambu",
    "wof:placetype":"locality",
    "wof:population":1983
},
  "geometry": {"coordinates":[75.17095399999999,12.377079],"type":"Point"}
}