{
  "type": "Feature",
  "properties": {
    "iso:country":"IN",
    "ks:ks_alt_nam":"CHAVAN WASTI",
    "ks:ks_name":"Chavan Wasti",
    "ks:ks_pop":75,
    "ks:ks_type":"HABITATION",
    "name:eng_x_preferred":[
        "Chavan Wasti"
    ],
    "wof:name":"Chavan Wasti",
    "wof:placetype":"locality",
    "wof:population":75
},
  "geometry": {"coordinates":[74.918316,17.081201],"type":"Point"}
}