{
  "type": "Feature",
  "properties": {
    "iso:country":"IN",
    "ks:ks_name":"Naugama",
    "ks:ks_pop":445,
    "ks:ks_type":"VILLAGE",
    "name:eng_x_preferred":[
        "Naugama"
    ],
    "wof:name":"Naugama",
    "wof:placetype":"locality",
    "wof:population":445
},
  "geometry": {"coordinates":[73.04937,21.026995],"type":"Point"}
}