{
  "type": "Feature",
  "properties": {
    "iso:country":"IN",
    "ks:ks_name":"Bada Sunatha",
    "ks:ks_pop":747,
    "ks:ks_type":"HABITATION",
    "ks:ks_uagg_main":0,
    "name:eng_x_preferred":[
        "Bada Sunatha"
    ],
    "wof:name":"Bada Sunatha",
    "wof:placetype":"neighbourhood",
    "wof:population":747
},
  "geometry": {"coordinates":[79.709458,26.591087],"type":"Point"}
}