{
  "type": "Feature",
  "properties": {
    "iso:country":"IN",
    "ks:ks_name":"Dihwa",
    "ks:ks_pop":95,
    "ks:ks_type":"HABITATION",
    "name:eng_x_preferred":[
        "Dihwa"
    ],
    "wof:name":"Dihwa",
    "wof:placetype":"locality",
    "wof:population":95
},
  "geometry": {"coordinates":[82.831766,27.302616],"type":"Point"}
}