{
  "type": "Feature",
  "properties": {
    "gn:admin1_code":"2.0",
    "gn:admin2_code":"554.0",
    "gn:asciiname":"Pylapatturivaripalli",
    "gn:country_code":"IN",
    "gn:dem":577,
    "gn:feature_class":"P",
    "gn:feature_code":"PPL",
    "gn:name":"Pylapatt\u016brivaripalli",
    "gn:population":0,
    "gn:timezone":"Asia/Kolkata",
    "iso:country":"IN",
    "wof:name":"Pylapatturivaripalli",
    "wof:placetype":"locality"
},
  "geometry": {"coordinates":[79.11943000000002,13.71956],"type":"Point"}
}