{
  "type": "Feature",
  "properties": {
    "iso:country":"IN",
    "ks:ks_name":"Pandariya",
    "ks:ks_pop":0,
    "ks:ks_type":"VILLAGE",
    "name:eng_x_preferred":[
        "Pandariya"
    ],
    "wof:name":"Pandariya",
    "wof:placetype":"locality",
    "wof:population":0
},
  "geometry": {"coordinates":[85.610817,24.757292],"type":"Point"}
}