{
  "type": "Feature",
  "properties": {
    "gn:admin1_code":"11",
    "gn:admin2_code":"24.0",
    "gn:asciiname":"Khas Masal",
    "gn:country_code":"IN",
    "gn:dem":953,
    "gn:feature_class":"P",
    "gn:feature_code":"PPL",
    "gn:name":"Kh\u0101s Masal",
    "gn:population":0,
    "gn:timezone":"Asia/Kolkata",
    "iso:country":"IN",
    "wof:name":"Khas Masal",
    "wof:placetype":"locality"
},
  "geometry": {"coordinates":[76.40234,32.08988],"type":"Point"}
}