{
  "type": "Feature",
  "properties": {
    "gn:admin1_code":"36",
    "gn:admin2_code":"154.0",
    "gn:asciiname":"Tajpur",
    "gn:country_code":"IN",
    "gn:dem":135,
    "gn:feature_class":"P",
    "gn:feature_code":"PPL",
    "gn:name":"T\u0101jpur",
    "gn:population":0,
    "gn:timezone":"Asia/Kolkata",
    "iso:country":"IN",
    "ks:ks_alt_nam":"T\u0101jpur",
    "ks:ks_name":"Tajpur",
    "ks:ks_pop":510,
    "ks:ks_type":"VILLAGE",
    "ks:ks_uagg_main":0,
    "name:eng_x_preferred":[
        "Tajpur"
    ],
    "name:eng_x_variant":[
        "T\u0101jpur"
    ],
    "name:urd_x_preferred":[
        "\u062a\u0627\u062c\u067e\u0648\u0631"
    ],
    "wof:name":"Tajpur",
    "wof:placetype":"neighbourhood",
    "wof:population":510
},
  "geometry": {"coordinates":[81.047032,27.384819],"type":"Point"}
}