{
  "type": "Feature",
  "properties": {
    "gn:admin1_code":"35",
    "gn:admin2_code":"427.0",
    "gn:asciiname":"Simaria",
    "gn:country_code":"IN",
    "gn:dem":504,
    "gn:feature_class":"P",
    "gn:feature_code":"PPL",
    "gn:name":"Simaria",
    "gn:population":0,
    "gn:timezone":"Asia/Kolkata",
    "iso:country":"IN",
    "ks:ks_name":"Simariya",
    "ks:ks_pop":1041,
    "ks:ks_type":"HABITATION",
    "name:eng_x_preferred":[
        "Simariya"
    ],
    "name:eng_x_variant":[
        "Simaria"
    ],
    "wof:name":"Simariya",
    "wof:placetype":"locality",
    "wof:population":1041
},
  "geometry": {"coordinates":[79.18207700000001,23.207312],"type":"Point"}
}