{
  "type": "Feature",
  "properties": {
    "iso:country":"IN",
    "ks:ks_name":"Chuchuriya",
    "ks:ks_pop":310,
    "ks:ks_type":"HABITATION",
    "ks:ks_uagg_main":0,
    "name:eng_x_preferred":[
        "Chuchuriya"
    ],
    "wof:name":"Chuchuriya",
    "wof:placetype":"neighbourhood",
    "wof:population":310
},
  "geometry": {"coordinates":[80.139871,27.506107],"type":"Point"}
}