{
  "type": "Feature",
  "properties": {
    "iso:country":"IN",
    "ks:ks_name":"Rameshwar Ka Purwa",
    "ks:ks_pop":35,
    "ks:ks_type":"HABITATION",
    "name:eng_x_preferred":[
        "Rameshwar Ka Purwa"
    ],
    "wof:name":"Rameshwar Ka Purwa",
    "wof:placetype":"locality",
    "wof:population":35
},
  "geometry": {"coordinates":[80.987289,25.256135],"type":"Point"}
}