{
  "type": "Feature",
  "properties": {
    "gn:admin1_code":"21.0",
    "gn:admin2_code":"398.0",
    "gn:asciiname":"Amdiambo",
    "gn:country_code":"IN",
    "gn:dem":899,
    "gn:feature_class":"P",
    "gn:feature_code":"PPL",
    "gn:name":"\u0100mdi\u0101mbo",
    "gn:population":0,
    "gn:timezone":"Asia/Kolkata",
    "iso:country":"IN",
    "wof:name":"Amdiambo",
    "wof:placetype":"locality"
},
  "geometry": {"coordinates":[82.92118000000001,18.88593],"type":"Point"}
}