{
  "type": "Feature",
  "properties": {
    "iso:country":"IN",
    "ks:ks_name":"Fanaswadi",
    "ks:ks_pop":240,
    "ks:ks_type":"HABITATION",
    "name:eng_x_preferred":[
        "Fanaswadi"
    ],
    "wof:name":"Fanaswadi",
    "wof:placetype":"locality",
    "wof:population":240
},
  "geometry": {"coordinates":[73.118745,18.920626],"type":"Point"}
}