{
  "type": "Feature",
  "properties": {
    "iso:country":"IN",
    "ks:ks_alt_nam":"MEG. KHAMESHE KT SUNDAR NAGAR",
    "ks:ks_name":"Meg. Khameshe Kt Sundar Nagar",
    "ks:ks_pop":100,
    "ks:ks_type":"HABITATION",
    "name:eng_x_preferred":[
        "Meg. Khameshe Kt Sundar Nagar"
    ],
    "wof:name":"Meg. Khameshe Kt Sundar Nagar",
    "wof:placetype":"locality",
    "wof:population":100
},
  "geometry": {"coordinates":[71.08208500000001,25.365078],"type":"Point"}
}