{
  "type": "Feature",
  "properties": {
    "iso:country":"IN",
    "ks:ks_name":"Malancha",
    "ks:ks_pop":470,
    "ks:ks_type":"VILLAGE",
    "name:eng_x_preferred":[
        "Malancha"
    ],
    "wof:name":"Malancha",
    "wof:placetype":"locality",
    "wof:population":470
},
  "geometry": {"coordinates":[87.851356,23.880081],"type":"Point"}
}