{
  "type": "Feature",
  "properties": {
    "gn:admin1_code":"36.0",
    "gn:admin2_code":"135.0",
    "gn:asciiname":"Rayan Khurd",
    "gn:country_code":"IN",
    "gn:dem":203,
    "gn:feature_class":"P",
    "gn:feature_code":"PPL",
    "gn:name":"R\u0101y\u0101n Khurd",
    "gn:population":0,
    "gn:timezone":"Asia/Kolkata",
    "iso:country":"IN",
    "name:und_x_variant":[
        "R\u0101y\u0101n Khurd",
        "B\u012bb\u012bpur"
    ],
    "wof:name":"Rayan Khurd",
    "wof:placetype":"neighbourhood"
},
  "geometry": {"coordinates":[78.50627,28.64279],"type":"Point"}
}