{
  "type": "Feature",
  "properties": {
    "iso:country":"IN",
    "ks:ks_alt_nam":"R balliputtuga",
    "ks:ks_name":"R Balliputtuga",
    "ks:ks_pop":383,
    "ks:ks_type":"HABITATION",
    "name:eng_x_preferred":[
        "R Balliputtuga"
    ],
    "wof:name":"R Balliputtuga",
    "wof:placetype":"locality",
    "wof:population":383
},
  "geometry": {"coordinates":[84.65585799999999,19.03212],"type":"Point"}
}