{
  "type": "Feature",
  "properties": {
    "iso:country":"IN",
    "ks:ks_name":"Samarmal",
    "ks:ks_pop":513,
    "ks:ks_type":"VILLAGE",
    "name:eng_x_preferred":[
        "Samarmal"
    ],
    "wof:name":"Samarmal",
    "wof:placetype":"locality",
    "wof:population":513
},
  "geometry": {"coordinates":[73.286856,24.688972],"type":"Point"}
}