{
  "type": "Feature",
  "properties": {
    "gn:admin1_code":"35",
    "gn:admin2_code":"447.0",
    "gn:asciiname":"Partabpura",
    "gn:country_code":"IN",
    "gn:dem":353,
    "gn:feature_class":"P",
    "gn:feature_code":"PPL",
    "gn:name":"Part\u0101bpura",
    "gn:population":0,
    "gn:timezone":"Asia/Kolkata",
    "iso:country":"IN",
    "ks:ks_alt_nam":"Part\u0101bpura",
    "ks:ks_alt_nam_2":"Partabpura",
    "ks:ks_name":"Partabpur",
    "ks:ks_pop":527,
    "ks:ks_type":"VILLAGE",
    "name:eng_x_preferred":[
        "Partabpur"
    ],
    "name:eng_x_variant":[
        "Partabpura",
        "Part\u0101bpura"
    ],
    "wof:name":"Partabpur",
    "wof:placetype":"locality",
    "wof:population":527
},
  "geometry": {"coordinates":[77.086251,21.744046],"type":"Point"}
}