{
  "type": "Feature",
  "properties": {
    "gn:admin1_code":"11.0",
    "gn:admin2_code":"24.0",
    "gn:asciiname":"Bagh",
    "gn:country_code":"IN",
    "gn:dem":588,
    "gn:feature_class":"P",
    "gn:feature_code":"PPL",
    "gn:name":"B\u0101gh",
    "gn:population":0,
    "gn:timezone":"Asia/Kolkata",
    "iso:country":"IN",
    "name:cat_x_preferred":[
        "Bagh"
    ],
    "name:ceb_x_preferred":[
        "Bagh"
    ],
    "name:deu_x_preferred":[
        "Bagh"
    ],
    "name:fas_x_preferred":[
        "\u0628\u0627\u063a"
    ],
    "name:hye_x_preferred":[
        "\u0532\u0561\u0572"
    ],
    "name:nld_x_preferred":[
        "Bagh"
    ],
    "name:swe_x_preferred":[
        "Bagh"
    ],
    "name:urd_x_preferred":[
        "\u0628\u0627\u063a"
    ],
    "wof:name":"Bagh",
    "wof:placetype":"locality"
},
  "geometry": {"coordinates":[75.87978000000003,32.15508],"type":"Point"}
}