{
  "type": "Feature",
  "properties": {
    "iso:country":"IN",
    "ks:ks_name":"Chhatraul",
    "ks:ks_pop":1898,
    "ks:ks_type":"VILLAGE",
    "ks:ks_uagg_main":0,
    "name:eng_x_preferred":[
        "Chhatraul"
    ],
    "wof:name":"Chhatraul",
    "wof:placetype":"neighbourhood",
    "wof:population":1898
},
  "geometry": {"coordinates":[84.021704,27.292144],"type":"Point"}
}