{
  "type": "Feature",
  "properties": {
    "gn:admin1_code":"24.0",
    "gn:admin2_code":"101",
    "gn:asciiname":"Lambana Mulavan",
    "gn:country_code":"IN",
    "gn:dem":280,
    "gn:feature_class":"P",
    "gn:feature_code":"PPL",
    "gn:name":"Lamb\u0101na M\u016blav\u0101n",
    "gn:population":0,
    "gn:timezone":"Asia/Kolkata",
    "iso:country":"IN",
    "name:und_x_variant":[
        "Lamb\u0101na M\u016blav\u0101n",
        "Lamb\u0101na M\u016blv\u0101n"
    ],
    "wof:name":"Lambana Mulavan",
    "wof:placetype":"neighbourhood"
},
  "geometry": {"coordinates":[72.93288,27.61513],"type":"Point"}
}