{
  "type": "Feature",
  "properties": {
    "iso:country":"IN",
    "ks:ks_alt_nam":"MATHIYA",
    "ks:ks_name":"Mathiya",
    "ks:ks_pop":411,
    "ks:ks_type":"HABITATION",
    "name:eng_x_preferred":[
        "Mathiya"
    ],
    "wof:name":"Mathiya",
    "wof:placetype":"locality",
    "wof:population":411
},
  "geometry": {"coordinates":[84.50009,25.725112],"type":"Point"}
}