{
  "type": "Feature",
  "properties": {
    "iso:country":"IN",
    "ks:ks_name":"Thirupattti",
    "ks:ks_pop":249,
    "ks:ks_type":"HABITATION",
    "name:eng_x_preferred":[
        "Thirupattti"
    ],
    "wof:name":"Thirupattti",
    "wof:placetype":"locality",
    "wof:population":249
},
  "geometry": {"coordinates":[78.62352,9.94024],"type":"Point"}
}