{
  "type": "Feature",
  "properties": {
    "gn:admin1_code":"12",
    "gn:admin2_code":"17.0",
    "gn:asciiname":"Kantaul",
    "gn:country_code":"IN",
    "gn:dem":1795,
    "gn:feature_class":"P",
    "gn:feature_code":"PPL",
    "gn:name":"Kantaul",
    "gn:population":0,
    "gn:timezone":"Asia/Kolkata",
    "iso:country":"IN",
    "wof:name":"Kantaul",
    "wof:placetype":"locality"
},
  "geometry": {"coordinates":[75.13266999999998,33.57102],"type":"Point"}
}