{
  "type": "Feature",
  "properties": {
    "iso:country":"IN",
    "ks:ks_name":"Hosur New",
    "ks:ks_pop":117,
    "ks:ks_type":"HABITATION",
    "name:eng_x_preferred":[
        "Hosur New"
    ],
    "wof:name":"Hosur New",
    "wof:placetype":"locality",
    "wof:population":117
},
  "geometry": {"coordinates":[74.492474,15.997768],"type":"Point"}
}