{
  "type": "Feature",
  "properties": {
    "gn:admin1_code":"28",
    "gn:admin2_code":"343.0",
    "gn:asciiname":"Pratapnagar",
    "gn:country_code":"IN",
    "gn:dem":8,
    "gn:feature_class":"P",
    "gn:feature_code":"PPL",
    "gn:name":"Prat\u0101pnagar",
    "gn:population":0,
    "gn:timezone":"Asia/Kolkata",
    "iso:country":"IN",
    "ks:ks_alt_nam":"Prat\u0101pnagar",
    "ks:ks_name":"Pratapnagar",
    "ks:ks_pop":1747,
    "ks:ks_type":"VILLAGE",
    "ks:ks_uagg_main":0,
    "name:eng_x_preferred":[
        "Pratapnagar"
    ],
    "name:eng_x_variant":[
        "Prat\u0101pnagar"
    ],
    "wof:name":"Pratapnagar",
    "wof:placetype":"locality",
    "wof:population":1747
},
  "geometry": {"coordinates":[88.51540799999999,22.446219],"type":"Point"}
}