{
  "type": "Feature",
  "properties": {
    "iso:country":"IN",
    "ks:ks_name":"Dhagarya",
    "ks:ks_pop":0,
    "ks:ks_type":"VILLAGE",
    "name:eng_x_preferred":[
        "Dhagarya"
    ],
    "wof:name":"Dhagarya",
    "wof:placetype":"locality",
    "wof:population":0
},
  "geometry": {"coordinates":[87.190574,23.174872],"type":"Point"}
}