{
  "type": "Feature",
  "properties": {
    "gn:admin1_code":"36.0",
    "gn:admin2_code":"160.0",
    "gn:asciiname":"Qutabpur",
    "gn:country_code":"IN",
    "gn:dem":150,
    "gn:feature_class":"P",
    "gn:feature_code":"PPL",
    "gn:name":"Qutabpur",
    "gn:population":0,
    "gn:timezone":"Asia/Kolkata",
    "iso:country":"IN",
    "wof:name":"Qutabpur",
    "wof:placetype":"locality"
},
  "geometry": {"coordinates":[79.45208000000002,26.96362],"type":"Point"}
}