{
  "type": "Feature",
  "properties": {
    "iso:country":"IN",
    "ks:ks_name":"Matti Gunta",
    "ks:ks_pop":241,
    "ks:ks_type":"HABITATION",
    "name:eng_x_preferred":[
        "Matti Gunta"
    ],
    "wof:name":"Matti Gunta",
    "wof:placetype":"locality",
    "wof:population":241
},
  "geometry": {"coordinates":[80.124064,13.640777],"type":"Point"}
}