{
  "type": "Feature",
  "properties": {
    "gn:admin1_code":"13.0",
    "gn:admin2_code":"600.0",
    "gn:asciiname":"Adichanallur",
    "gn:country_code":"IN",
    "gn:dem":23,
    "gn:feature_class":"P",
    "gn:feature_code":"PPL",
    "gn:name":"Adich\u0101nall\u016br",
    "gn:population":0,
    "gn:timezone":"Asia/Kolkata",
    "iso:country":"IN",
    "ks:ks_name":"Adichanalloor",
    "ks:ks_pop":4997,
    "ks:ks_type":"HABITATION",
    "name:ara_x_preferred":[
        "\u0623\u062f\u064a\u062a\u0634\u0646\u0644\u0648\u0631"
    ],
    "name:eng_x_preferred":[
        "Adichanalloor"
    ],
    "name:eng_x_variant":[
        "Adichanallur"
    ],
    "name:fra_x_preferred":[
        "Adichanallur"
    ],
    "name:kan_x_preferred":[
        "\u0c86\u0ca6\u0cbf\u0c9a\u0ca8\u0cb2\u0ccd\u0cb2\u0cc2\u0cb0\u0cc1"
    ],
    "wof:name":"Adichanalloor",
    "wof:placetype":"locality",
    "wof:population":4997
},
  "geometry": {"coordinates":[76.71135,8.88025],"type":"Point"}
}