{
  "type": "Feature",
  "properties": {
    "iso:country":"IN",
    "ks:ks_alt_nam":"KODAKUPARA Bhairopur",
    "ks:ks_name":"Kodakupara Bhairopur",
    "ks:ks_pop":480,
    "ks:ks_type":"HABITATION",
    "name:eng_x_preferred":[
        "Kodakupara Bhairopur"
    ],
    "wof:name":"Kodakupara Bhairopur",
    "wof:placetype":"locality",
    "wof:population":480
},
  "geometry": {"coordinates":[83.242001,23.521579],"type":"Point"}
}