{
  "type": "Feature",
  "properties": {
    "gn:admin1_code":"36.0",
    "gn:admin2_code":"180.0",
    "gn:asciiname":"Rasulabad",
    "gn:country_code":"IN",
    "gn:dem":110,
    "gn:feature_class":"P",
    "gn:feature_code":"PPL",
    "gn:name":"Ras\u016blabad",
    "gn:population":0,
    "gn:timezone":"Asia/Kolkata",
    "iso:country":"IN",
    "name:bpy_x_preferred":[
        "\u09b0\u09b8\u09c1\u09b2\u09be\u09ac\u09be\u09a6"
    ],
    "name:ceb_x_preferred":[
        "Ras\u016bl\u0101b\u0101d"
    ],
    "name:ell_x_preferred":[
        "\u03a1\u03b1\u03c3\u03bf\u03c5\u03bb\u03b1\u03bc\u03c0\u03ac\u03bd\u03c4"
    ],
    "name:fas_x_preferred":[
        "\u0631\u0633\u0648\u0644\u200c\u0622\u0628\u0627\u062f"
    ],
    "name:ita_x_preferred":[
        "Rasulabad"
    ],
    "name:mlg_x_preferred":[
        "Rasulabad"
    ],
    "name:msa_x_preferred":[
        "Rasulabad"
    ],
    "name:nld_x_preferred":[
        "Rasulabad"
    ],
    "name:pol_x_preferred":[
        "Rasulabad"
    ],
    "name:por_x_preferred":[
        "Rasulabad"
    ],
    "name:urd_x_preferred":[
        "\u0631\u0633\u0648\u0644 \u0622\u0628\u0627\u062f"
    ],
    "name:vie_x_preferred":[
        "Rasulabad"
    ],
    "name:zho_x_preferred":[
        "\u62c9\u82cf\u62c9\u5df4\u5fb7"
    ],
    "wof:name":"Rasulabad",
    "wof:placetype":"locality"
},
  "geometry": {"coordinates":[81.60969,27.15519],"type":"Point"}
}