{
  "type": "Feature",
  "properties": {
    "iso:country":"IN",
    "ks:ks_name":"Abdulapur",
    "ks:ks_type":"VILLAGE",
    "name:eng_x_preferred":[
        "Abdulapur"
    ],
    "wof:name":"Abdulapur",
    "wof:placetype":"locality"
},
  "geometry": {"coordinates":[77.032822,29.041114],"type":"Point"}
}