{
  "type": "Feature",
  "properties": {
    "iso:country":"IN",
    "ks:ks_alt_nam":"Chak Daulat\u0101b\u0101d",
    "ks:ks_name":"Chak Daulatabad",
    "ks:ks_type":"VILLAGE",
    "ks:ks_uagg_main":0,
    "name:eng_x_preferred":[
        "Chak Daulatabad"
    ],
    "name:eng_x_variant":[
        "Chak Daulat\u0101b\u0101d"
    ],
    "wof:name":"Chak Daulatabad",
    "wof:placetype":"neighbourhood"
},
  "geometry": {"coordinates":[81.23295899999999,26.224777],"type":"Point"}
}