{
  "type": "Feature",
  "properties": {
    "iso:country":"IN",
    "ks:ks_name":"Telyamahu",
    "ks:ks_pop":167,
    "ks:ks_type":"HABITATION",
    "name:eng_x_preferred":[
        "Telyamahu"
    ],
    "wof:name":"Telyamahu",
    "wof:placetype":"locality",
    "wof:population":167
},
  "geometry": {"coordinates":[74.863979,21.579206],"type":"Point"}
}