{
  "type": "Feature",
  "properties": {
    "iso:country":"IN",
    "ks:ks_alt_nam":"bairiyadamar",
    "ks:ks_name":"Bairiyadamar",
    "ks:ks_pop":54,
    "ks:ks_type":"HABITATION",
    "name:eng_x_preferred":[
        "Bairiyadamar"
    ],
    "wof:name":"Bairiyadamar",
    "wof:placetype":"locality",
    "wof:population":54
},
  "geometry": {"coordinates":[83.81916,23.950779],"type":"Point"}
}