{
  "type": "Feature",
  "properties": {
    "iso:country":"IN",
    "ks:ks_name":"Tentulchita",
    "ks:ks_pop":0,
    "ks:ks_type":"VILLAGE",
    "name:eng_x_preferred":[
        "Tentulchita"
    ],
    "wof:name":"Tentulchita",
    "wof:placetype":"locality",
    "wof:population":0
},
  "geometry": {"coordinates":[86.930307,23.105047],"type":"Point"}
}