{
  "type": "Feature",
  "properties": {
    "iso:country":"IN",
    "ks:ks_alt_nam":"Keolari mal",
    "ks:ks_name":"Keolari Mal",
    "ks:ks_pop":548,
    "ks:ks_type":"HABITATION",
    "name:eng_x_preferred":[
        "Keolari Mal"
    ],
    "wof:name":"Keolari Mal",
    "wof:placetype":"locality",
    "wof:population":548
},
  "geometry": {"coordinates":[80.922116,22.949522],"type":"Point"}
}