{
  "type": "Feature",
  "properties": {
    "gn:admin1_code":"24.0",
    "gn:admin2_code":"116",
    "gn:asciiname":"Betu",
    "gn:country_code":"IN",
    "gn:dem":148,
    "gn:feature_class":"P",
    "gn:feature_code":"PPL",
    "gn:name":"Betu",
    "gn:population":0,
    "gn:timezone":"Asia/Kolkata",
    "iso:country":"IN",
    "name:ceb_x_preferred":[
        "Betu"
    ],
    "name:swe_x_preferred":[
        "Betu"
    ],
    "wof:name":"Betu",
    "wof:placetype":"neighbourhood"
},
  "geometry": {"coordinates":[72.57331000000001,25.44218],"type":"Point"}
}