{
  "type": "Feature",
  "properties": {
    "iso:country":"IN",
    "ks:ks_name":"Barakocha",
    "ks:ks_pop":105,
    "ks:ks_type":"HABITATION",
    "name:eng_x_preferred":[
        "Barakocha"
    ],
    "wof:name":"Barakocha",
    "wof:placetype":"locality",
    "wof:population":105
},
  "geometry": {"coordinates":[85.802297,23.804673],"type":"Point"}
}