{
  "type": "Feature",
  "properties": {
    "gn:admin1_code":"36.0",
    "gn:admin2_code":"134.0",
    "gn:asciiname":"Nurpur Chhibri",
    "gn:country_code":"IN",
    "gn:dem":241,
    "gn:feature_class":"P",
    "gn:feature_code":"PPL",
    "gn:name":"N\u016brpur Chhibri",
    "gn:population":0,
    "gn:timezone":"Asia/Kolkata",
    "iso:country":"IN",
    "ks:ks_alt_nam":"N\u016brpur Chhibri",
    "ks:ks_name":"Nurpur Chhibri",
    "ks:ks_type":"VILLAGE",
    "ks:ks_uagg_main":0,
    "name:eng_x_preferred":[
        "Nurpur Chhibri"
    ],
    "name:eng_x_variant":[
        "N\u016brpur Chhibri"
    ],
    "wof:name":"Nurpur Chhibri",
    "wof:placetype":"neighbourhood"
},
  "geometry": {"coordinates":[78.58417900000001,29.372701],"type":"Point"}
}