{
  "type": "Feature",
  "properties": {
    "iso:country":"IN",
    "ks:ks_name":"Umatta",
    "ks:ks_pop":172,
    "ks:ks_type":"VILLAGE",
    "name:eng_x_preferred":[
        "Umatta"
    ],
    "wof:name":"Umatta",
    "wof:placetype":"locality",
    "wof:population":172
},
  "geometry": {"coordinates":[79.214535,30.273986],"type":"Point"}
}