{
  "type": "Feature",
  "properties": {
    "iso:country":"IN",
    "ks:ks_alt_nam":"G.Kothuru",
    "ks:ks_name":"G.kothuru",
    "ks:ks_pop":40,
    "ks:ks_type":"HABITATION",
    "name:eng_x_preferred":[
        "G.kothuru"
    ],
    "wof:name":"G.kothuru",
    "wof:placetype":"locality",
    "wof:population":40
},
  "geometry": {"coordinates":[82.924525,17.971109],"type":"Point"}
}