{
  "type": "Feature",
  "properties": {
    "gn:admin1_code":"36.0",
    "gn:admin2_code":"173.0",
    "gn:asciiname":"Ashapur Mishra",
    "gn:country_code":"IN",
    "gn:dem":107,
    "gn:feature_class":"P",
    "gn:feature_code":"PPL",
    "gn:name":"\u0100sh\u0101pur Mishra",
    "gn:population":0,
    "gn:timezone":"Asia/Kolkata",
    "iso:country":"IN",
    "wof:name":"Ashapur Mishra",
    "wof:placetype":"locality"
},
  "geometry": {"coordinates":[81.91016999999999,25.99919],"type":"Point"}
}