{
  "type": "Feature",
  "properties": {
    "gn:admin1_code":"16.0",
    "gn:admin2_code":"511",
    "gn:asciiname":"Chikli Buzurg",
    "gn:country_code":"IN",
    "gn:dem":343,
    "gn:feature_class":"P",
    "gn:feature_code":"PPL",
    "gn:name":"Chikli Buzurg",
    "gn:population":0,
    "gn:timezone":"Asia/Kolkata",
    "iso:country":"IN",
    "name:und_x_variant":[
        "Chikli",
        "Chikli Buzurg"
    ],
    "wof:name":"Chikli Buzurg",
    "wof:placetype":"locality"
},
  "geometry": {"coordinates":[78.25149,19.54141],"type":"Point"}
}