{
  "type": "Feature",
  "properties": {
    "iso:country":"IN",
    "ks:ks_name":"Gadhwakala Ta.Khain",
    "ks:ks_pop":375,
    "ks:ks_type":"VILLAGE",
    "ks:ks_uagg_main":0,
    "name:eng_x_preferred":[
        "Gadhwakala Ta.Khain"
    ],
    "wof:name":"Gadhwakala Ta.Khain",
    "wof:placetype":"neighbourhood",
    "wof:population":375
},
  "geometry": {"coordinates":[82.00641299999999,25.243795],"type":"Point"}
}