{
  "type": "Feature",
  "properties": {
    "iso:country":"IN",
    "ks:ks_name":"Karanjaiwadi",
    "ks:ks_pop":113,
    "ks:ks_type":"HABITATION",
    "name:eng_x_preferred":[
        "Karanjaiwadi"
    ],
    "wof:name":"Karanjaiwadi",
    "wof:placetype":"locality",
    "wof:population":113
},
  "geometry": {"coordinates":[73.3476,16.490658],"type":"Point"}
}