{
  "type": "Feature",
  "properties": {
    "iso:country":"IN",
    "ks:ks_name":"Yadav Tola",
    "ks:ks_pop":85,
    "ks:ks_type":"HABITATION",
    "name:eng_x_preferred":[
        "Yadav Tola"
    ],
    "wof:name":"Yadav Tola",
    "wof:placetype":"locality",
    "wof:population":85
},
  "geometry": {"coordinates":[83.98900399999999,26.173764],"type":"Point"}
}