{
  "type": "Feature",
  "properties": {
    "gn:admin1_code":"35",
    "gn:admin2_code":"426.0",
    "gn:asciiname":"Madhopura",
    "gn:country_code":"IN",
    "gn:dem":437,
    "gn:feature_class":"P",
    "gn:feature_code":"PPL",
    "gn:name":"M\u0101dhopura",
    "gn:population":0,
    "gn:timezone":"Asia/Kolkata",
    "iso:country":"IN",
    "ks:ks_alt_nam":"M\u0101dhopura",
    "ks:ks_name":"Madhopura",
    "ks:ks_type":"VILLAGE",
    "ks:ks_uagg_main":0,
    "name:eng_x_preferred":[
        "Madhopura"
    ],
    "name:eng_x_variant":[
        "M\u0101dhopura"
    ],
    "wof:name":"Madhopura",
    "wof:placetype":"neighbourhood"
},
  "geometry": {"coordinates":[79.926126,23.847352],"type":"Point"}
}