{
  "type": "Feature",
  "properties": {
    "iso:country":"IN",
    "ks:ks_name":"Pure Ramsohan",
    "ks:ks_pop":292,
    "ks:ks_type":"HABITATION",
    "name:eng_x_preferred":[
        "Pure Ramsohan"
    ],
    "wof:name":"Pure Ramsohan",
    "wof:placetype":"locality",
    "wof:population":292
},
  "geometry": {"coordinates":[82.1348,26.83181],"type":"Point"}
}