{
  "type": "Feature",
  "properties": {
    "iso:country":"IN",
    "ks:ks_name":"Manikpur",
    "ks:ks_pop":548,
    "ks:ks_type":"VILLAGE",
    "name:eng_x_preferred":[
        "Manikpur"
    ],
    "wof:name":"Manikpur",
    "wof:placetype":"locality",
    "wof:population":548
},
  "geometry": {"coordinates":[84.04285,19.153658],"type":"Point"}
}