{
  "type": "Feature",
  "properties": {
    "iso:country":"IN",
    "ks:ks_name":"Saiding",
    "ks:ks_pop":275,
    "ks:ks_type":"HABITATION",
    "ks:ks_uagg_main":0,
    "name:eng_x_preferred":[
        "Saiding"
    ],
    "wof:name":"Saiding",
    "wof:placetype":"neighbourhood",
    "wof:population":275
},
  "geometry": {"coordinates":[92.80606400000001,25.091925],"type":"Point"}
}