{
  "type": "Feature",
  "properties": {
    "gn:admin1_code":"36",
    "gn:admin2_code":"177.0",
    "gn:asciiname":"Marwi Sahai Singh",
    "gn:country_code":"IN",
    "gn:dem":104,
    "gn:feature_class":"P",
    "gn:feature_code":"PPL",
    "gn:name":"Marwi Sah\u0101i Singh",
    "gn:population":0,
    "gn:timezone":"Asia/Kolkata",
    "iso:country":"IN",
    "wof:name":"Marwi Sahai Singh",
    "wof:placetype":"locality"
},
  "geometry": {"coordinates":[82.12264999999999,26.5572],"type":"Point"}
}