{
  "type": "Feature",
  "properties": {
    "iso:country":"IN",
    "ks:ks_name":"Tenduwa",
    "ks:ks_pop":490,
    "ks:ks_type":"VILLAGE",
    "name:eng_x_preferred":[
        "Tenduwa"
    ],
    "wof:name":"Tenduwa",
    "wof:placetype":"locality",
    "wof:population":490
},
  "geometry": {"coordinates":[79.003817,25.529071],"type":"Point"}
}