{
  "type": "Feature",
  "properties": {
    "iso:country":"IN",
    "ks:ks_name":"Dongargaon",
    "ks:ks_pop":1009,
    "ks:ks_type":"VILLAGE",
    "ks:ks_uagg_main":0,
    "name:eng_x_preferred":[
        "Dongargaon"
    ],
    "wof:name":"Dongargaon",
    "wof:placetype":"locality",
    "wof:population":1009
},
  "geometry": {"coordinates":[73.43351199999999,18.738921],"type":"Point"}
}