{
  "type": "Feature",
  "properties": {
    "iso:country":"IN",
    "name:ara_x_preferred":[
        "\u0646\u0648\u0627\u0628\u0627\u0644\u064a"
    ],
    "name:ben_bn_x_preferred":[
        "\u09a8\u09be\u0989\u09aa\u09b2\u09cd\u09b2\u09bf"
    ],
    "name:ben_in_x_preferred":[
        "\u09a8\u09be\u0989\u09aa\u09b2\u09cd\u09b2\u09bf"
    ],
    "name:eng_x_preferred":[
        "Nuapalli"
    ],
    "name:guj_x_preferred":[
        "\u0aa8\u0ac1\u0a86\u0aaa\u0ab2\u0acd\u0ab2\u0ac0"
    ],
    "name:hin_x_preferred":[
        "\u0928\u0941\u0906\u092a\u0932\u094d\u0932\u0940"
    ],
    "name:kan_x_preferred":[
        "\u0ca8\u0ccc\u0caa\u0cb2\u0ccd\u0cb2\u0cbf"
    ],
    "name:mal_x_preferred":[
        "\u0d28\u0d41\u0d35\u0d2a\u0d4d\u0d2a\u0d33\u0d4d\u0d33\u0d3f"
    ],
    "name:mar_x_preferred":[
        "\u0928\u0941\u0906\u092a\u0932\u094d\u0932\u0940"
    ],
    "name:pan_x_preferred":[
        "\u0a28\u0a41\u0a06\u0a2a\u0a71\u0a32\u0a40"
    ],
    "name:tam_x_preferred":[
        "\u0b9a\u0bc1\u0bb5\u0bbe\u0baa\u0bb2\u0bcd\u0bb2\u0bbf"
    ],
    "name:tel_x_preferred":[
        "\u0c28\u0c4c\u0c2a\u0c32\u0c4d\u0c32\u0c3f"
    ],
    "name:urd_x_preferred":[
        "\u0646\u0648\u0622 \u067e\u0644\u0651\u06cc"
    ],
    "qs:gn_adm0_cc":"IN",
    "qs:gn_fcode":"PPL",
    "qs:gn_local":1275817,
    "qs:gn_namadm1":"21",
    "qs:gn_name":"Nu\u0101palli",
    "qs:local_max":122,
    "qs:local_sum":302,
    "qs:localhoods":5,
    "qs:name":"Nuapalli",
    "qs:name_adm0":"India",
    "qs:name_adm1":"Orissa",
    "qs:name_adm2":"Khurda",
    "qs:name_local":"Bhubaneswar",
    "qs:photo_max":24,
    "qs:photo_sum":43,
    "qs:placetype":"Suburb",
    "qs:quad_count":9,
    "qs:woe_adm0":23424848,
    "qs:woe_adm1":2345755,
    "qs:woe_adm2":12586615,
    "qs:woe_lau":0,
    "qs:woe_local":2294941,
    "qs:woe_ver":"7.10.0",
    "wof:lang":[
        "eng"
    ],
    "wof:name":"Nuapalli",
    "wof:placetype":"neighbourhood"
},
  "geometry": {"coordinates":[85.81478300000001,20.289339],"type":"Point"}
}