{
  "type": "Feature",
  "properties": {
    "iso:country":"IN",
    "ks:ks_name":"Belgodu",
    "ks:ks_pop":120,
    "ks:ks_type":"HABITATION",
    "name:eng_x_preferred":[
        "Belgodu"
    ],
    "wof:name":"Belgodu",
    "wof:placetype":"locality",
    "wof:population":120
},
  "geometry": {"coordinates":[74.756018,13.546611],"type":"Point"}
}