{
  "type": "Feature",
  "properties": {
    "iso:country":"IN",
    "ks:ks_alt_nam":"33.490 RD - R",
    "ks:ks_name":"33.490 Rd - R",
    "ks:ks_pop":37,
    "ks:ks_type":"HABITATION",
    "name:eng_x_preferred":[
        "33.490 Rd - R"
    ],
    "wof:name":"33.490 Rd - R",
    "wof:placetype":"locality",
    "wof:population":37
},
  "geometry": {"coordinates":[73.889889,29.129472],"type":"Point"}
}