{
  "type": "Feature",
  "properties": {
    "iso:country":"IN",
    "ks:ks_name":"Ramnapara",
    "ks:ks_pop":894,
    "ks:ks_type":"VILLAGE",
    "ks:ks_uagg_main":0,
    "name:eng_x_preferred":[
        "Ramnapara"
    ],
    "wof:name":"Ramnapara",
    "wof:placetype":"neighbourhood",
    "wof:population":894
},
  "geometry": {"coordinates":[88.30131799999999,24.237608],"type":"Point"}
}