{
  "type": "Feature",
  "properties": {
    "gn:admin1_code":"19",
    "gn:admin2_code":"577.0",
    "gn:asciiname":"Naganahalli",
    "gn:country_code":"IN",
    "gn:dem":721,
    "gn:feature_class":"P",
    "gn:feature_code":"PPL",
    "gn:name":"N\u0101ganahalli",
    "gn:population":0,
    "gn:timezone":"Asia/Kolkata",
    "iso:country":"IN",
    "name:und_x_variant":[
        "Nagenahally",
        "N\u0101ganahalli"
    ],
    "wof:name":"Naganahalli",
    "wof:placetype":"locality"
},
  "geometry": {"coordinates":[76.65284,12.37925],"type":"Point"}
}