{
  "type": "Feature",
  "properties": {
    "iso:country":"IN",
    "ks:ks_name":"Nunia Tola",
    "ks:ks_pop":148,
    "ks:ks_type":"HABITATION",
    "name:eng_x_preferred":[
        "Nunia Tola"
    ],
    "wof:name":"Nunia Tola",
    "wof:placetype":"locality",
    "wof:population":148
},
  "geometry": {"coordinates":[84.59356200000001,26.979045],"type":"Point"}
}