{
  "type": "Feature",
  "properties": {
    "gn:admin1_code":"36",
    "gn:admin2_code":"191.0",
    "gn:asciiname":"Mauli",
    "gn:country_code":"IN",
    "gn:dem":79,
    "gn:feature_class":"P",
    "gn:feature_code":"PPL",
    "gn:name":"Mauli",
    "gn:population":0,
    "gn:timezone":"Asia/Kolkata",
    "iso:country":"IN",
    "name:ara_x_preferred":[
        "\u0645\u0648\u0644\u064a"
    ],
    "name:ben_bn_x_preferred":[
        "\u09ae\u09be\u0989\u09b2\u09bf"
    ],
    "name:ben_in_x_preferred":[
        "\u09ae\u09be\u0989\u09b2\u09bf"
    ],
    "name:guj_x_preferred":[
        "\u0aae\u0acc\u0ab2\u0ac0"
    ],
    "name:hin_x_preferred":[
        "\u092e\u094c\u0932\u0940"
    ],
    "name:ind_x_preferred":[
        "Mauli"
    ],
    "name:kan_x_preferred":[
        "\u0cae\u0ccc\u0cb2\u0cbf"
    ],
    "name:mal_x_preferred":[
        "\u0d2e\u0d57\u0d32\u0d3f"
    ],
    "name:mar_x_preferred":[
        "\u092e\u093e\u090a\u0932\u0940"
    ],
    "name:min_x_preferred":[
        "Wangsa Mauliwarmadewa"
    ],
    "name:pan_x_preferred":[
        "\u0a2e\u0a4c\u0a32\u0a40"
    ],
    "name:tam_x_preferred":[
        "\u0bae\u0bcc\u0bb2\u0bbf"
    ],
    "name:tel_x_preferred":[
        "\u0c2e\u0c4c\u0c33\u0c3f"
    ],
    "name:urd_x_preferred":[
        "\u0645\u0624\u0644\u06cc"
    ],
    "wof:name":"Mauli",
    "wof:placetype":"locality"
},
  "geometry": {"coordinates":[83.19327,25.8714],"type":"Point"}
}