{
  "type": "Feature",
  "properties": {
    "iso:country":"IN",
    "ks:ks_name":"Pandrikani",
    "ks:ks_pop":346,
    "ks:ks_type":"HABITATION",
    "name:eng_x_preferred":[
        "Pandrikani"
    ],
    "wof:name":"Pandrikani",
    "wof:placetype":"locality",
    "wof:population":346
},
  "geometry": {"coordinates":[84.082444,22.379445],"type":"Point"}
}