{
  "type": "Feature",
  "properties": {
    "iso:country":"IN",
    "ks:ks_name":"Teliwadi",
    "ks:ks_pop":280,
    "ks:ks_type":"HABITATION",
    "name:eng_x_preferred":[
        "Teliwadi"
    ],
    "wof:name":"Teliwadi",
    "wof:placetype":"locality",
    "wof:population":280
},
  "geometry": {"coordinates":[73.44041,16.38062],"type":"Point"}
}