{
  "type": "Feature",
  "properties": {
    "iso:country":"IN",
    "ks:ks_name":"Baramchati",
    "ks:ks_pop":683,
    "ks:ks_type":"VILLAGE",
    "ks:ks_uagg_main":0,
    "name:eng_x_preferred":[
        "Baramchati"
    ],
    "wof:name":"Baramchati",
    "wof:placetype":"neighbourhood",
    "wof:population":683
},
  "geometry": {"coordinates":[87.10584299999999,21.977069],"type":"Point"}
}