{
  "type": "Feature",
  "properties": {
    "gn:admin1_code":"35.0",
    "gn:admin2_code":"454.0",
    "gn:asciiname":"Malpathar",
    "gn:country_code":"IN",
    "gn:dem":655,
    "gn:feature_class":"P",
    "gn:feature_code":"PPL",
    "gn:name":"Malpath\u0101r",
    "gn:population":0,
    "gn:timezone":"Asia/Kolkata",
    "iso:country":"IN",
    "wof:name":"Malpathar",
    "wof:placetype":"locality"
},
  "geometry": {"coordinates":[80.23981999999999,22.66913],"type":"Point"}
}