{
  "type": "Feature",
  "properties": {
    "gn:admin1_code":"35.0",
    "gn:admin2_code":"454.0",
    "gn:asciiname":"Malpathar",
    "gn:country_code":"IN",
    "gn:dem":655,
    "gn:feature_class":"P",
    "gn:feature_code":"PPL",
    "gn:name":"Malpath\u0101r",
    "gn:population":0,
    "gn:timezone":"Asia/Kolkata",
    "iso:country":"IN",
    "ks:ks_name":"Malpathar F",
    "ks:ks_pop":319,
    "ks:ks_type":"HABITATION",
    "name:eng_x_preferred":[
        "Malpathar F"
    ],
    "name:eng_x_variant":[
        "Malpathar"
    ],
    "wof:name":"Malpathar F",
    "wof:placetype":"locality",
    "wof:population":319
},
  "geometry": {"coordinates":[80.240016,22.669423],"type":"Point"}
}