{
  "type": "Feature",
  "properties": {
    "gn:admin1_code":"36",
    "gn:admin2_code":"154.0",
    "gn:asciiname":"Asil",
    "gn:country_code":"IN",
    "gn:dem":136,
    "gn:feature_class":"P",
    "gn:feature_code":"PPL",
    "gn:name":"Asil",
    "gn:population":0,
    "gn:timezone":"Asia/Kolkata",
    "iso:country":"IN",
    "name:ara_x_preferred":[
        "\u0623\u0635\u064a\u0644"
    ],
    "name:tur_x_preferred":[
        "Asil"
    ],
    "wof:name":"Asil",
    "wof:placetype":"locality"
},
  "geometry": {"coordinates":[80.7504,27.31],"type":"Point"}
}