{
  "type": "Feature",
  "properties": {
    "iso:country":"IN",
    "ks:ks_name":"Sen Saw Mill Para",
    "ks:ks_pop":515,
    "ks:ks_type":"HABITATION",
    "ks:ks_uagg_main":0,
    "name:eng_x_preferred":[
        "Sen Saw Mill Para"
    ],
    "wof:name":"Sen Saw Mill Para",
    "wof:placetype":"neighbourhood",
    "wof:population":515
},
  "geometry": {"coordinates":[91.47609,23.547997],"type":"Point"}
}