{
  "type": "Feature",
  "properties": {
    "iso:country":"IN",
    "ks:ks_name":"Kuchakala",
    "ks:ks_pop":25,
    "ks:ks_type":"VILLAGE",
    "name:eng_x_preferred":[
        "Kuchakala"
    ],
    "wof:name":"Kuchakala",
    "wof:placetype":"locality",
    "wof:population":25
},
  "geometry": {"coordinates":[87.29487899999999,22.51777],"type":"Point"}
}