{
  "type": "Feature",
  "properties": {
    "iso:country":"IN",
    "ks:ks_name":"Devappal",
    "ks:ks_pop":4,
    "ks:ks_type":"HABITATION",
    "name:eng_x_preferred":[
        "Devappal"
    ],
    "wof:name":"Devappal",
    "wof:placetype":"locality",
    "wof:population":4
},
  "geometry": {"coordinates":[77.428611,13.461389],"type":"Point"}
}