{
  "type": "Feature",
  "properties": {
    "iso:country":"IN",
    "ks:ks_name":"Chhapri Kalan",
    "ks:ks_pop":1115,
    "ks:ks_type":"VILLAGE",
    "ks:ks_uagg_main":0,
    "name:eng_x_preferred":[
        "Chhapri Kalan"
    ],
    "wof:name":"Chhapri Kalan",
    "wof:placetype":"neighbourhood",
    "wof:population":1115
},
  "geometry": {"coordinates":[73.902,26.787483],"type":"Point"}
}