{
  "type": "Feature",
  "properties": {
    "iso:country":"IN",
    "ks:ks_alt_nam":"HIRETARY",
    "ks:ks_name":"Hiretary",
    "ks:ks_pop":736,
    "ks:ks_type":"HABITATION",
    "name:eng_x_preferred":[
        "Hiretary"
    ],
    "wof:name":"Hiretary",
    "wof:placetype":"locality",
    "wof:population":736
},
  "geometry": {"coordinates":[88.74599499999999,26.790738],"type":"Point"}
}