{
  "type": "Feature",
  "properties": {
    "gn:admin1_code":"09",
    "gn:admin2_code":"484.0",
    "gn:asciiname":"Simalia",
    "gn:country_code":"IN",
    "gn:dem":166,
    "gn:feature_class":"P",
    "gn:feature_code":"PPL",
    "gn:name":"Simalia",
    "gn:population":0,
    "gn:timezone":"Asia/Kolkata",
    "iso:country":"IN",
    "name:est_x_preferred":[
        "Simalia"
    ],
    "name:fra_x_preferred":[
        "Simalia"
    ],
    "name:nld_x_preferred":[
        "Simalia"
    ],
    "name:pol_x_preferred":[
        "Simalia"
    ],
    "name:rus_x_preferred":[
        "Simalia"
    ],
    "name:spa_x_preferred":[
        "Simalia"
    ],
    "wof:name":"Simalia",
    "wof:placetype":"locality"
},
  "geometry": {"coordinates":[73.71110999999998,22.68573],"type":"Point"}
}