{
  "type": "Feature",
  "properties": {
    "iso:country":"IN",
    "ks:ks_name":"Mahuatoli",
    "ks:ks_pop":39,
    "ks:ks_type":"HABITATION",
    "name:eng_x_preferred":[
        "Mahuatoli"
    ],
    "wof:name":"Mahuatoli",
    "wof:placetype":"locality",
    "wof:population":39
},
  "geometry": {"coordinates":[84.118611,22.538852],"type":"Point"}
}