{
  "type": "Feature",
  "properties": {
    "iso:country":"IN",
    "ks:ks_alt_nam":"R\u0101mpurw\u0101",
    "ks:ks_name":"Rampurwa",
    "ks:ks_pop":1086,
    "ks:ks_type":"VILLAGE",
    "ks:ks_uagg_main":0,
    "name:eng_x_preferred":[
        "Rampurwa"
    ],
    "name:eng_x_variant":[
        "R\u0101mpurw\u0101"
    ],
    "wof:name":"Rampurwa",
    "wof:placetype":"neighbourhood",
    "wof:population":1086
},
  "geometry": {"coordinates":[84.76259899999999,26.588816],"type":"Point"}
}