{
  "type": "Feature",
  "properties": {
    "gn:admin1_code":"36",
    "gn:admin2_code":"159.0",
    "gn:asciiname":"Sikandarpur Zila Bihar",
    "gn:country_code":"IN",
    "gn:dem":153,
    "gn:feature_class":"P",
    "gn:feature_code":"PPL",
    "gn:name":"Sikandarpur Zila Bih\u0101r",
    "gn:population":0,
    "gn:timezone":"Asia/Kolkata",
    "iso:country":"IN",
    "wof:name":"Sikandarpur Zila Bihar",
    "wof:placetype":"locality"
},
  "geometry": {"coordinates":[79.36781999999999,27.29327],"type":"Point"}
}