{
  "type": "Feature",
  "properties": {
    "iso:country":"IN",
    "ks:ks_name":"Konganam",
    "ks:ks_pop":105,
    "ks:ks_type":"HABITATION",
    "name:eng_x_preferred":[
        "Konganam"
    ],
    "wof:name":"Konganam",
    "wof:placetype":"locality",
    "wof:population":105
},
  "geometry": {"coordinates":[76.988692,8.666599],"type":"Point"}
}