{
  "type": "Feature",
  "properties": {
    "iso:country":"IN",
    "ks:ks_name":"Mulapurwa",
    "ks:ks_pop":453,
    "ks:ks_type":"HABITATION",
    "name:eng_x_preferred":[
        "Mulapurwa"
    ],
    "wof:name":"Mulapurwa",
    "wof:placetype":"locality",
    "wof:population":453
},
  "geometry": {"coordinates":[80.449899,27.841329],"type":"Point"}
}