{
  "type": "Feature",
  "properties": {
    "iso:country":"IN",
    "ks:ks_name":"Shewala Kala",
    "ks:ks_pop":3794,
    "ks:ks_type":"VILLAGE",
    "ks:ks_uagg_main":0,
    "name:eng_x_preferred":[
        "Shewala Kala"
    ],
    "wof:name":"Shewala Kala",
    "wof:placetype":"neighbourhood",
    "wof:population":3794
},
  "geometry": {"coordinates":[77.992741,30.293982],"type":"Point"}
}