{
  "type": "Feature",
  "properties": {
    "iso:country":"IN",
    "ks:ks_name":"Maipadka",
    "ks:ks_pop":750,
    "ks:ks_type":"HABITATION",
    "name:eng_x_preferred":[
        "Maipadka"
    ],
    "wof:name":"Maipadka",
    "wof:placetype":"locality",
    "wof:population":750
},
  "geometry": {"coordinates":[74.99906900000001,12.940149],"type":"Point"}
}