{
  "type": "Feature",
  "properties": {
    "iso:country":"IN",
    "ks:ks_name":"Tarka",
    "ks:ks_pop":865,
    "ks:ks_type":"VILLAGE",
    "name:eng_x_preferred":[
        "Tarka"
    ],
    "wof:name":"Tarka",
    "wof:placetype":"locality",
    "wof:population":865
},
  "geometry": {"coordinates":[82.793469,23.392714],"type":"Point"}
}