{
  "type": "Feature",
  "properties": {
    "iso:country":"IN",
    "ks:ks_alt_nam":"Sai purwa II",
    "ks:ks_name":"Sai Purwa Ii",
    "ks:ks_pop":25,
    "ks:ks_type":"HABITATION",
    "name:eng_x_preferred":[
        "Sai Purwa Ii"
    ],
    "wof:name":"Sai Purwa Ii",
    "wof:placetype":"locality",
    "wof:population":25
},
  "geometry": {"coordinates":[81.73495800000001,27.480325],"type":"Point"}
}