{
  "type": "Feature",
  "properties": {
    "gn:admin1_code":"38.0",
    "gn:admin2_code":"358.0",
    "gn:asciiname":"Tandwa",
    "gn:country_code":"IN",
    "gn:dem":274,
    "gn:feature_class":"P",
    "gn:feature_code":"PPL",
    "gn:name":"Tandw\u0101",
    "gn:population":0,
    "gn:timezone":"Asia/Kolkata",
    "iso:country":"IN",
    "wof:name":"Tandwa",
    "wof:placetype":"locality"
},
  "geometry": {"coordinates":[84.45724,24.0866],"type":"Point"}
}