{
  "type": "Feature",
  "properties": {
    "iso:country":"IN",
    "ks:ks_name":"Bangaon",
    "ks:ks_pop":1346,
    "ks:ks_type":"VILLAGE",
    "name:eng_x_preferred":[
        "Bangaon"
    ],
    "wof:name":"Bangaon",
    "wof:placetype":"locality",
    "wof:population":1346
},
  "geometry": {"coordinates":[91.456271,26.619359],"type":"Point"}
}