{
  "type": "Feature",
  "properties": {
    "iso:country":"IN",
    "ks:ks_name":"Jamubani",
    "ks:ks_pop":173,
    "ks:ks_type":"VILLAGE",
    "name:eng_x_preferred":[
        "Jamubani"
    ],
    "wof:name":"Jamubani",
    "wof:placetype":"locality",
    "wof:population":173
},
  "geometry": {"coordinates":[85.86636900000001,21.861302],"type":"Point"}
}