{
  "type": "Feature",
  "properties": {
    "iso:country":"IN",
    "ks:ks_name":"Tal Tola",
    "ks:ks_pop":793,
    "ks:ks_type":"HABITATION",
    "name:eng_x_preferred":[
        "Tal Tola"
    ],
    "wof:name":"Tal Tola",
    "wof:placetype":"locality",
    "wof:population":793
},
  "geometry": {"coordinates":[84.880501,26.650689],"type":"Point"}
}