{
  "type": "Feature",
  "properties": {
    "iso:country":"IN",
    "ks:ks_alt_nam":"Palanigoundenpalayam colony",
    "ks:ks_name":"Palanigoundenpalayam Colony",
    "ks:ks_pop":248,
    "ks:ks_type":"HABITATION",
    "name:eng_x_preferred":[
        "Palanigoundenpalayam Colony"
    ],
    "wof:name":"Palanigoundenpalayam Colony",
    "wof:placetype":"locality",
    "wof:population":248
},
  "geometry": {"coordinates":[77.35136799999999,11.427124],"type":"Point"}
}