{
  "type": "Feature",
  "properties": {
    "gn:admin1_code":"12.0",
    "gn:admin2_code":"2.0",
    "gn:asciiname":"Penkapur",
    "gn:country_code":"IN",
    "gn:dem":1851,
    "gn:feature_class":"P",
    "gn:feature_code":"PPL",
    "gn:name":"Penkapur",
    "gn:population":0,
    "gn:timezone":"Asia/Kolkata",
    "iso:country":"IN",
    "wof:name":"Penkapur",
    "wof:placetype":"locality"
},
  "geometry": {"coordinates":[74.5963,33.99459],"type":"Point"}
}