{
  "type": "Feature",
  "properties": {
    "iso:country":"IN",
    "ks:ks_name":"Dholbhanga",
    "ks:ks_pop":362,
    "ks:ks_type":"HABITATION",
    "name:eng_x_preferred":[
        "Dholbhanga"
    ],
    "wof:name":"Dholbhanga",
    "wof:placetype":"locality",
    "wof:population":362
},
  "geometry": {"coordinates":[86.798372,24.690229],"type":"Point"}
}