{
  "type": "Feature",
  "properties": {
    "gn:admin1_code":"2",
    "gn:admin2_code":"545.0",
    "gn:asciiname":"Pedda Garrangi",
    "gn:country_code":"IN",
    "gn:dem":224,
    "gn:feature_class":"P",
    "gn:feature_code":"PPL",
    "gn:name":"Pedda Garrangi",
    "gn:population":0,
    "gn:timezone":"Asia/Kolkata",
    "iso:country":"IN",
    "wof:name":"Pedda Garrangi",
    "wof:placetype":"locality"
},
  "geometry": {"coordinates":[82.23798000000002,17.43103],"type":"Point"}
}