{
  "type": "Feature",
  "properties": {
    "gn:admin1_code":"2",
    "gn:admin2_code":"545.0",
    "gn:asciiname":"Pedda Garrangi",
    "gn:country_code":"IN",
    "gn:dem":224,
    "gn:feature_class":"P",
    "gn:feature_code":"PPL",
    "gn:name":"Pedda Garrangi",
    "gn:population":0,
    "gn:timezone":"Asia/Kolkata",
    "iso:country":"IN",
    "ks:ks_name":"Pedagarrangi",
    "ks:ks_pop":819,
    "ks:ks_type":"VILLAGE",
    "name:eng_x_preferred":[
        "Pedagarrangi"
    ],
    "name:eng_x_variant":[
        "Pedda Garrangi"
    ],
    "wof:name":"Pedagarrangi",
    "wof:placetype":"locality",
    "wof:population":819
},
  "geometry": {"coordinates":[82.237683,17.431339],"type":"Point"}
}