{
  "type": "Feature",
  "properties": {
    "iso:country":"IN",
    "ks:ks_name":"Majhipada",
    "ks:ks_pop":150,
    "ks:ks_type":"HABITATION",
    "name:eng_x_preferred":[
        "Majhipada"
    ],
    "wof:name":"Majhipada",
    "wof:placetype":"locality",
    "wof:population":150
},
  "geometry": {"coordinates":[82.75109999999999,19.887989],"type":"Point"}
}