{
  "type": "Feature",
  "properties": {
    "iso:country":"IN",
    "ks:ks_name":"Khirsagarwasti",
    "ks:ks_pop":322,
    "ks:ks_type":"HABITATION",
    "name:eng_x_preferred":[
        "Khirsagarwasti"
    ],
    "wof:name":"Khirsagarwasti",
    "wof:placetype":"locality",
    "wof:population":322
},
  "geometry": {"coordinates":[75.11199999999999,17.957],"type":"Point"}
}