{
  "type": "Feature",
  "properties": {
    "gn:admin1_code":"16",
    "gn:admin2_code":"503.0",
    "gn:asciiname":"Karanja",
    "gn:country_code":"IN",
    "gn:dem":420,
    "gn:feature_class":"P",
    "gn:feature_code":"PPL",
    "gn:name":"K\u0101ranja",
    "gn:population":0,
    "gn:timezone":"Asia/Kolkata",
    "iso:country":"IN",
    "name:cat_x_preferred":[
        "Karanja"
    ],
    "name:ceb_x_preferred":[
        "Karanja"
    ],
    "name:swe_x_preferred":[
        "Karanja"
    ],
    "wof:name":"Karanja",
    "wof:placetype":"locality"
},
  "geometry": {"coordinates":[77.63273000000002,21.361],"type":"Point"}
}