{
  "type": "Feature",
  "properties": {
    "gn:admin1_code":"37.0",
    "gn:admin2_code":"416.0",
    "gn:asciiname":"Madakamiras",
    "gn:country_code":"IN",
    "gn:dem":247,
    "gn:feature_class":"P",
    "gn:feature_code":"PPL",
    "gn:name":"Madakamir\u0101s",
    "gn:population":0,
    "gn:timezone":"Asia/Kolkata",
    "iso:country":"IN",
    "wof:name":"Madakamiras",
    "wof:placetype":"locality"
},
  "geometry": {"coordinates":[81.87475000000001,18.69962],"type":"Point"}
}