{
  "type": "Feature",
  "properties": {
    "gn:admin1_code":"25.0",
    "gn:admin2_code":"620.0",
    "gn:asciiname":"Kilamanamedu",
    "gn:country_code":"IN",
    "gn:dem":27,
    "gn:feature_class":"P",
    "gn:feature_code":"PPL",
    "gn:name":"K\u012blamanamedu",
    "gn:population":0,
    "gn:timezone":"Asia/Kolkata",
    "iso:country":"IN",
    "ks:ks_name":"Keelanamedu",
    "ks:ks_pop":270,
    "ks:ks_type":"HABITATION",
    "name:eng_x_preferred":[
        "Keelanamedu"
    ],
    "name:eng_x_variant":[
        "Kilamanamedu"
    ],
    "wof:name":"Keelanamedu",
    "wof:placetype":"locality",
    "wof:population":270
},
  "geometry": {"coordinates":[79.39649,11.054045],"type":"Point"}
}