{
  "type": "Feature",
  "properties": {
    "iso:country":"IN",
    "ks:ks_name":"Khairi",
    "ks:ks_pop":714,
    "ks:ks_type":"HABITATION",
    "name:eng_x_preferred":[
        "Khairi"
    ],
    "wof:name":"Khairi",
    "wof:placetype":"locality",
    "wof:population":714
},
  "geometry": {"coordinates":[80.552421,23.311872],"type":"Point"}
}