{
  "type": "Feature",
  "properties": {
    "iso:country":"IN",
    "ks:ks_name":"Doddakoppalu",
    "ks:ks_pop":210,
    "ks:ks_type":"HABITATION",
    "name:eng_x_preferred":[
        "Doddakoppalu"
    ],
    "wof:name":"Doddakoppalu",
    "wof:placetype":"locality",
    "wof:population":210
},
  "geometry": {"coordinates":[76.75082999999999,12.54798],"type":"Point"}
}