{
  "type": "Feature",
  "properties": {
    "iso:country":"IN",
    "ks:ks_name":"Lweta",
    "ks:ks_pop":69,
    "ks:ks_type":"VILLAGE",
    "name:eng_x_preferred":[
        "Lweta"
    ],
    "wof:name":"Lweta",
    "wof:placetype":"locality",
    "wof:population":69
},
  "geometry": {"coordinates":[80.111665,29.918644],"type":"Point"}
}