{
  "type": "Feature",
  "properties": {
    "gn:admin1_code":"40",
    "gn:admin2_code":"535.0",
    "gn:asciiname":"Pocharam",
    "gn:country_code":"IN",
    "gn:dem":546,
    "gn:feature_class":"P",
    "gn:feature_code":"PPL",
    "gn:name":"Poch\u0101ram",
    "gn:population":0,
    "gn:timezone":"Asia/Kolkata",
    "iso:country":"IN",
    "name:tel_x_preferred":[
        "\u0c2a\u0c4b\u0c1a\u0c3e\u0c30\u0c02"
    ],
    "wof:name":"Pocharam",
    "wof:placetype":"locality"
},
  "geometry": {"coordinates":[77.83027,17.96415],"type":"Point"}
}