{
  "type": "Feature",
  "properties": {
    "iso:country":"IN",
    "ks:ks_name":"Chipa Kheda",
    "ks:ks_pop":383,
    "ks:ks_type":"VILLAGE",
    "name:eng_x_preferred":[
        "Chipa Kheda"
    ],
    "wof:name":"Chipa Kheda",
    "wof:placetype":"locality",
    "wof:population":383
},
  "geometry": {"coordinates":[77.805565,22.354937],"type":"Point"}
}