{
  "type": "Feature",
  "properties": {
    "iso:country":"IN",
    "ks:ks_name":"Nagla Nathauli",
    "ks:ks_pop":515,
    "ks:ks_type":"HABITATION",
    "name:eng_x_preferred":[
        "Nagla Nathauli"
    ],
    "wof:name":"Nagla Nathauli",
    "wof:placetype":"locality",
    "wof:population":515
},
  "geometry": {"coordinates":[78.125901,27.188036],"type":"Point"}
}