{
  "type": "Feature",
  "properties": {
    "iso:country":"IN",
    "ks:ks_name":"Tunganaputtuga",
    "ks:ks_pop":409,
    "ks:ks_type":"HABITATION",
    "name:eng_x_preferred":[
        "Tunganaputtuga"
    ],
    "wof:name":"Tunganaputtuga",
    "wof:placetype":"locality",
    "wof:population":409
},
  "geometry": {"coordinates":[84.645991,18.995871],"type":"Point"}
}