{
  "type": "Feature",
  "properties": {
    "iso:country":"IN",
    "ks:ks_name":"Babhanauli",
    "ks:ks_pop":372,
    "ks:ks_type":"HABITATION",
    "ks:ks_uagg_main":0,
    "name:eng_x_preferred":[
        "Babhanauli"
    ],
    "wof:name":"Babhanauli",
    "wof:placetype":"neighbourhood",
    "wof:population":372
},
  "geometry": {"coordinates":[84.15427699999999,26.367023],"type":"Point"}
}