{
  "type": "Feature",
  "properties": {
    "gn:admin1_code":"38",
    "gn:asciiname":"Nagra",
    "gn:country_code":"IN",
    "gn:dem":442,
    "gn:feature_class":"P",
    "gn:feature_code":"PPL",
    "gn:name":"Nagr\u0101",
    "gn:population":0,
    "gn:timezone":"Asia/Kolkata",
    "iso:country":"IN",
    "ks:ks_name":"Nagra",
    "ks:ks_pop":1757,
    "ks:ks_type":"VILLAGE",
    "name:cat_x_preferred":[
        "Nagra"
    ],
    "name:eng_x_preferred":[
        "Nagra"
    ],
    "name:fin_x_preferred":[
        "Nagra"
    ],
    "name:fra_x_preferred":[
        "Nagra"
    ],
    "name:ina_x_preferred":[
        "Nagra"
    ],
    "name:ita_x_preferred":[
        "Nagra"
    ],
    "name:pol_x_preferred":[
        "Nagra"
    ],
    "name:rus_x_preferred":[
        "Nagra"
    ],
    "name:spa_x_preferred":[
        "Nagra"
    ],
    "wof:name":"Nagra",
    "wof:placetype":"locality",
    "wof:population":1757
},
  "geometry": {"coordinates":[83.733285,23.720459],"type":"Point"}
}