{
  "type": "Feature",
  "properties": {
    "gn:admin1_code":"38",
    "gn:asciiname":"Nagra",
    "gn:country_code":"IN",
    "gn:dem":442,
    "gn:feature_class":"P",
    "gn:feature_code":"PPL",
    "gn:name":"Nagr\u0101",
    "gn:population":0,
    "gn:timezone":"Asia/Kolkata",
    "iso:country":"IN",
    "name:cat_x_preferred":[
        "Nagra"
    ],
    "name:fin_x_preferred":[
        "Nagra"
    ],
    "name:fra_x_preferred":[
        "Nagra"
    ],
    "name:ina_x_preferred":[
        "Nagra"
    ],
    "name:ita_x_preferred":[
        "Nagra"
    ],
    "name:pol_x_preferred":[
        "Nagra"
    ],
    "name:rus_x_preferred":[
        "Nagra"
    ],
    "name:spa_x_preferred":[
        "Nagra"
    ],
    "wof:name":"Nagra",
    "wof:placetype":"locality"
},
  "geometry": {"coordinates":[83.73209,23.72702],"type":"Point"}
}