{
  "type": "Feature",
  "properties": {
    "gn:admin1_code":"36",
    "gn:admin2_code":"133.0",
    "gn:asciiname":"Sikandarpur Khurd",
    "gn:country_code":"IN",
    "gn:dem":233,
    "gn:feature_class":"P",
    "gn:feature_code":"PPL",
    "gn:name":"Sikandarpur Kh\u016brd",
    "gn:population":0,
    "gn:timezone":"Asia/Kolkata",
    "iso:country":"IN",
    "wof:name":"Sikandarpur Khurd",
    "wof:placetype":"locality"
},
  "geometry": {"coordinates":[77.79661,29.21173],"type":"Point"}
}