{
  "type": "Feature",
  "properties": {
    "gn:admin1_code":"35",
    "gn:admin2_code":"458.0",
    "gn:asciiname":"Muhammadpur",
    "gn:country_code":"IN",
    "gn:dem":402,
    "gn:feature_class":"P",
    "gn:feature_code":"PPL",
    "gn:name":"Muhammadpur",
    "gn:population":0,
    "gn:timezone":"Asia/Kolkata",
    "iso:country":"IN",
    "ks:ks_name":"Mohmmadpur",
    "ks:ks_pop":131,
    "ks:ks_type":"HABITATION",
    "name:eng_x_preferred":[
        "Mohmmadpur"
    ],
    "name:eng_x_variant":[
        "Muhammadpur"
    ],
    "wof:name":"Mohmmadpur",
    "wof:placetype":"locality",
    "wof:population":131
},
  "geometry": {"coordinates":[77.118431,24.343385],"type":"Point"}
}