{
  "type": "Feature",
  "properties": {
    "iso:country":"IN",
    "ks:ks_name":"Dabhadpada",
    "ks:ks_pop":334,
    "ks:ks_type":"HABITATION",
    "name:eng_x_preferred":[
        "Dabhadpada"
    ],
    "wof:name":"Dabhadpada",
    "wof:placetype":"locality",
    "wof:population":334
},
  "geometry": {"coordinates":[73.114998,20.044451],"type":"Point"}
}