{
  "type": "Feature",
  "properties": {
    "iso:country":"IN",
    "ks:ks_name":"Dangra",
    "ks:ks_pop":44,
    "ks:ks_type":"VILLAGE",
    "name:eng_x_preferred":[
        "Dangra"
    ],
    "wof:name":"Dangra",
    "wof:placetype":"locality",
    "wof:population":44
},
  "geometry": {"coordinates":[81.126846,19.84844],"type":"Point"}
}