{
  "type": "Feature",
  "properties": {
    "iso:country":"IN",
    "ks:ks_name":"Kazipara Pt.III",
    "ks:ks_pop":1094,
    "ks:ks_type":"VILLAGE",
    "name:eng_x_preferred":[
        "Kazipara Pt.III"
    ],
    "wof:name":"Kazipara Pt.III",
    "wof:placetype":"locality",
    "wof:population":1094
},
  "geometry": {"coordinates":[90.46300100000001,26.272781],"type":"Point"}
}