{
  "type": "Feature",
  "properties": {
    "iso:country":"IN",
    "ks:ks_name":"Aattupuram",
    "ks:ks_pop":1458,
    "ks:ks_type":"HABITATION",
    "name:eng_x_preferred":[
        "Aattupuram"
    ],
    "wof:name":"Aattupuram",
    "wof:placetype":"locality",
    "wof:population":1458
},
  "geometry": {"coordinates":[76.10136799999999,10.847177],"type":"Point"}
}