{
  "type": "Feature",
  "properties": {
    "iso:country":"IN",
    "ks:ks_name":"Kamdhenwa",
    "ks:ks_type":"VILLAGE",
    "name:eng_x_preferred":[
        "Kamdhenwa"
    ],
    "wof:name":"Kamdhenwa",
    "wof:placetype":"locality"
},
  "geometry": {"coordinates":[84.129312,26.535182],"type":"Point"}
}