{
  "type": "Feature",
  "properties": {
    "iso:country":"IN",
    "ks:ks_name":"Murkotpalke",
    "ks:ks_pop":152,
    "ks:ks_type":"HABITATION",
    "name:eng_x_preferred":[
        "Murkotpalke"
    ],
    "wof:name":"Murkotpalke",
    "wof:placetype":"locality",
    "wof:population":152
},
  "geometry": {"coordinates":[74.9751,13.110557],"type":"Point"}
}