{
  "type": "Feature",
  "properties": {
    "iso:country":"IN",
    "ks:ks_name":"Naiguan",
    "ks:ks_pop":403,
    "ks:ks_type":"VILLAGE",
    "ks:ks_uagg_main":0,
    "name:eng_x_preferred":[
        "Naiguan"
    ],
    "wof:name":"Naiguan",
    "wof:placetype":"neighbourhood",
    "wof:population":403
},
  "geometry": {"coordinates":[86.40560499999999,20.242167],"type":"Point"}
}