{
  "type": "Feature",
  "properties": {
    "iso:country":"IN",
    "ks:ks_name":"Katha",
    "ks:ks_pop":5905,
    "ks:ks_type":"VILLAGE",
    "ks:ks_uagg_main":0,
    "name:eng_x_preferred":[
        "Katha"
    ],
    "wof:name":"Katha",
    "wof:placetype":"neighbourhood",
    "wof:population":5905
},
  "geometry": {"coordinates":[85.149537,26.360389],"type":"Point"}
}