{
  "type": "Feature",
  "properties": {
    "iso:country":"IN",
    "ks:ks_name":"Alaniyon Ki Dhani",
    "ks:ks_pop":70,
    "ks:ks_type":"VILLAGE",
    "name:eng_x_preferred":[
        "Alaniyon Ki Dhani"
    ],
    "wof:name":"Alaniyon Ki Dhani",
    "wof:placetype":"locality",
    "wof:population":70
},
  "geometry": {"coordinates":[71.515942,25.863419],"type":"Point"}
}