{
  "type": "Feature",
  "properties": {
    "iso:country":"IN",
    "ks:ks_name":"Teprabhola",
    "ks:ks_pop":0,
    "ks:ks_type":"VILLAGE",
    "name:eng_x_preferred":[
        "Teprabhola"
    ],
    "wof:name":"Teprabhola",
    "wof:placetype":"locality",
    "wof:population":0
},
  "geometry": {"coordinates":[88.26423200000001,26.756077],"type":"Point"}
}