{
  "type": "Feature",
  "properties": {
    "gn:admin1_code":"16.0",
    "gn:admin2_code":"510",
    "gn:asciiname":"Chatari",
    "gn:country_code":"IN",
    "gn:dem":396,
    "gn:feature_class":"P",
    "gn:feature_code":"PPL",
    "gn:name":"Ch\u0101t\u0101ri",
    "gn:population":0,
    "gn:timezone":"Asia/Kolkata",
    "iso:country":"IN",
    "name:bih_x_preferred":[
        "\u091a\u0924\u0930\u0940"
    ],
    "name:ceb_x_preferred":[
        "Chatari"
    ],
    "name:dty_x_preferred":[
        "\u091a\u0924\u0930\u0940"
    ],
    "name:mai_x_preferred":[
        "\u091a\u0924\u0930\u0940"
    ],
    "name:msa_x_preferred":[
        "Chatari"
    ],
    "name:nep_x_preferred":[
        "\u091a\u0924\u0930\u0940"
    ],
    "name:new_x_preferred":[
        "\u091a\u0924\u0930\u0940"
    ],
    "name:pol_x_preferred":[
        "Chatari"
    ],
    "wof:name":"Chatari",
    "wof:placetype":"locality"
},
  "geometry": {"coordinates":[77.79982,19.46835],"type":"Point"}
}