{
  "type": "Feature",
  "properties": {
    "gn:admin1_code":"2.0",
    "gn:admin2_code":"543.0",
    "gn:asciiname":"Jirikivalasa",
    "gn:country_code":"IN",
    "gn:dem":196,
    "gn:feature_class":"P",
    "gn:feature_code":"PPL",
    "gn:name":"J\u012brikivalasa",
    "gn:population":0,
    "gn:timezone":"Asia/Kolkata",
    "iso:country":"IN",
    "ks:ks_name":"Jeerikavalasa",
    "ks:ks_pop":122,
    "ks:ks_type":"HABITATION",
    "name:eng_x_preferred":[
        "Jeerikavalasa"
    ],
    "name:eng_x_variant":[
        "Jirikivalasa"
    ],
    "wof:name":"Jeerikavalasa",
    "wof:placetype":"locality",
    "wof:population":122
},
  "geometry": {"coordinates":[83.24265699999999,18.448832],"type":"Point"}
}