{
  "type": "Feature",
  "properties": {
    "iso:country":"IN",
    "ks:ks_name":"Bawadutola",
    "ks:ks_pop":136,
    "ks:ks_type":"VILLAGE",
    "name:eng_x_preferred":[
        "Bawadutola"
    ],
    "wof:name":"Bawadutola",
    "wof:placetype":"locality",
    "wof:population":136
},
  "geometry": {"coordinates":[80.921498,20.622004],"type":"Point"}
}