{
  "type": "Feature",
  "properties": {
    "iso:country":"IN",
    "ks:ks_name":"Chhikari",
    "ks:ks_pop":146,
    "ks:ks_type":"HABITATION",
    "name:eng_x_preferred":[
        "Chhikari"
    ],
    "wof:name":"Chhikari",
    "wof:placetype":"locality",
    "wof:population":146
},
  "geometry": {"coordinates":[77.889331,26.217971],"type":"Point"}
}