{
  "type": "Feature",
  "properties": {
    "iso:country":"IN",
    "ks:ks_name":"Bhaluadih Bhaluaha",
    "ks:ks_pop":839,
    "ks:ks_type":"HABITATION",
    "name:eng_x_preferred":[
        "Bhaluadih Bhaluaha"
    ],
    "wof:name":"Bhaluadih Bhaluaha",
    "wof:placetype":"locality",
    "wof:population":839
},
  "geometry": {"coordinates":[85.544504,26.628339],"type":"Point"}
}