{
  "type": "Feature",
  "properties": {
    "iso:country":"IN",
    "ks:ks_name":"Kaibnorpada",
    "ks:ks_pop":248,
    "ks:ks_type":"HABITATION",
    "name:eng_x_preferred":[
        "Kaibnorpada"
    ],
    "wof:name":"Kaibnorpada",
    "wof:placetype":"locality",
    "wof:population":248
},
  "geometry": {"coordinates":[73.00871100000001,20.089203],"type":"Point"}
}