{
  "type": "Feature",
  "properties": {
    "iso:country":"IN",
    "ks:ks_name":"Pure Mahesh",
    "ks:ks_pop":862,
    "ks:ks_type":"HABITATION",
    "ks:ks_uagg_main":0,
    "name:eng_x_preferred":[
        "Pure Mahesh"
    ],
    "wof:name":"Pure Mahesh",
    "wof:placetype":"neighbourhood",
    "wof:population":862
},
  "geometry": {"coordinates":[81.39619999999999,26.5128],"type":"Point"}
}