{
  "type": "Feature",
  "properties": {
    "iso:country":"IN",
    "ks:ks_name":"Borlengri",
    "ks:ks_pop":2180,
    "ks:ks_type":"HABITATION",
    "ks:ks_uagg_main":0,
    "name:eng_x_preferred":[
        "Borlengri"
    ],
    "wof:name":"Borlengri",
    "wof:placetype":"neighbourhood",
    "wof:population":2180
},
  "geometry": {"coordinates":[93.689063,25.92142],"type":"Point"}
}