{
  "type": "Feature",
  "properties": {
    "iso:country":"IN",
    "ks:ks_name":"Kundi Banasu",
    "ks:ks_pop":616,
    "ks:ks_type":"VILLAGE",
    "name:eng_x_preferred":[
        "Kundi Banasu"
    ],
    "wof:name":"Kundi Banasu",
    "wof:placetype":"locality",
    "wof:population":616
},
  "geometry": {"coordinates":[78.572351,30.481996],"type":"Point"}
}