{
  "type": "Feature",
  "properties": {
    "gn:admin1_code":"36",
    "gn:admin2_code":"191.0",
    "gn:asciiname":"Kiamuddinpur Patti",
    "gn:country_code":"IN",
    "gn:dem":83,
    "gn:feature_class":"P",
    "gn:feature_code":"PPL",
    "gn:name":"Ki\u0101mudd\u012bnpur Patti",
    "gn:population":0,
    "gn:timezone":"Asia/Kolkata",
    "iso:country":"IN",
    "wof:name":"Kiamuddinpur Patti",
    "wof:placetype":"locality"
},
  "geometry": {"coordinates":[83.00414000000001,26.01596],"type":"Point"}
}