{
  "type": "Feature",
  "properties": {
    "iso:country":"IN",
    "ks:ks_name":"Harsingpur",
    "ks:ks_pop":70,
    "ks:ks_type":"VILLAGE",
    "name:eng_x_preferred":[
        "Harsingpur"
    ],
    "wof:name":"Harsingpur",
    "wof:placetype":"locality",
    "wof:population":70
},
  "geometry": {"coordinates":[87.44967800000001,22.782224],"type":"Point"}
}