{
  "type": "Feature",
  "properties": {
    "iso:country":"IN",
    "ks:ks_name":"Hunuri",
    "ks:ks_pop":0,
    "ks:ks_type":"VILLAGE",
    "name:eng_x_preferred":[
        "Hunuri"
    ],
    "wof:name":"Hunuri",
    "wof:placetype":"locality",
    "wof:population":0
},
  "geometry": {"coordinates":[87.37545299999999,23.85204],"type":"Point"}
}