{
  "type": "Feature",
  "properties": {
    "gn:admin1_code":"34.0",
    "gn:admin2_code":"233.0",
    "gn:asciiname":"Mokaram",
    "gn:country_code":"IN",
    "gn:dem":97,
    "gn:feature_class":"P",
    "gn:feature_code":"PPL",
    "gn:name":"Mokaram",
    "gn:population":0,
    "gn:timezone":"Asia/Kolkata",
    "iso:country":"IN",
    "wof:name":"Mokaram",
    "wof:placetype":"neighbourhood"
},
  "geometry": {"coordinates":[83.65224000000001,24.94142],"type":"Point"}
}