{
  "type": "Feature",
  "properties": {
    "iso:country":"IN",
    "ks:ks_name":"Bartoli",
    "ks:ks_pop":105,
    "ks:ks_type":"HABITATION",
    "name:eng_x_preferred":[
        "Bartoli"
    ],
    "wof:name":"Bartoli",
    "wof:placetype":"locality",
    "wof:population":105
},
  "geometry": {"coordinates":[84.90751,22.731922],"type":"Point"}
}