{
  "type": "Feature",
  "properties": {
    "gn:admin1_code":"19.0",
    "gn:admin2_code":"571.0",
    "gn:asciiname":"Keremelinapalya",
    "gn:country_code":"IN",
    "gn:dem":749,
    "gn:feature_class":"P",
    "gn:feature_code":"PPL",
    "gn:name":"Keremelinap\u0101lya",
    "gn:population":0,
    "gn:timezone":"Asia/Kolkata",
    "iso:country":"IN",
    "ks:ks_name":"Keremegalapalya",
    "ks:ks_pop":30,
    "ks:ks_type":"HABITATION",
    "name:eng_x_preferred":[
        "Keremegalapalya"
    ],
    "name:eng_x_variant":[
        "Keremelinapalya"
    ],
    "wof:name":"Keremegalapalya",
    "wof:placetype":"locality",
    "wof:population":30
},
  "geometry": {"coordinates":[76.936961,12.963895],"type":"Point"}
}