{
  "type": "Feature",
  "properties": {
    "iso:country":"IN",
    "ks:ks_name":"Pure Baniyan",
    "ks:ks_pop":118,
    "ks:ks_type":"HABITATION",
    "ks:ks_uagg_main":0,
    "name:eng_x_preferred":[
        "Pure Baniyan"
    ],
    "wof:name":"Pure Baniyan",
    "wof:placetype":"neighbourhood",
    "wof:population":118
},
  "geometry": {"coordinates":[81.525831,26.134992],"type":"Point"}
}