{
  "type": "Feature",
  "properties": {
    "iso:country":"IN",
    "ks:ks_name":"Bajeena",
    "ks:ks_pop":232,
    "ks:ks_type":"VILLAGE",
    "name:eng_x_preferred":[
        "Bajeena"
    ],
    "wof:name":"Bajeena",
    "wof:placetype":"locality",
    "wof:population":232
},
  "geometry": {"coordinates":[79.483177,29.57418],"type":"Point"}
}