{
  "type": "Feature",
  "properties": {
    "iso:country":"IN",
    "name:eng_x_preferred":[
        "Mem Nagar"
    ],
    "qs:gn_adm0_cc":"IN",
    "qs:gn_local":1279233,
    "qs:gn_nam_loc":"Ahmadabad, Ahmadabad, Gujarat, IN",
    "qs:gn_namadm1":"09",
    "qs:local_max":718,
    "qs:local_sum":4704,
    "qs:localhoods":28,
    "qs:name":"Mem Nagar",
    "qs:name_adm0":"India",
    "qs:name_adm1":"Gujarat",
    "qs:name_adm2":"Ahmadabad",
    "qs:name_local":"Ahmadabad",
    "qs:photo_max":14,
    "qs:photo_sum":29,
    "qs:placetype":"Suburb",
    "qs:quad_count":3,
    "qs:woe_adm0":23424848,
    "qs:woe_adm1":2345743,
    "qs:woe_adm2":12586415,
    "qs:woe_lau":0,
    "qs:woe_local":2295402,
    "qs:woe_ver":"7.10.0",
    "wof:lang":[
        "eng"
    ],
    "wof:name":"Mem Nagar",
    "wof:placetype":"neighbourhood"
},
  "geometry": {"coordinates":[72.53833,23.044521],"type":"Point"}
}