{
  "type": "Feature",
  "properties": {
    "iso:country":"IN",
    "ks:ks_alt_nam":"Parkup Pahar II",
    "ks:ks_name":"Parkup Pahar Ii",
    "ks:ks_pop":67,
    "ks:ks_type":"HABITATION",
    "name:eng_x_preferred":[
        "Parkup Pahar Ii"
    ],
    "wof:name":"Parkup Pahar Ii",
    "wof:placetype":"locality",
    "wof:population":67
},
  "geometry": {"coordinates":[92.96157100000001,26.358435],"type":"Point"}
}