{
  "type": "Feature",
  "properties": {
    "gn:admin1_code":"2.0",
    "gn:admin2_code":"544.0",
    "gn:asciiname":"Baithinlanka",
    "gn:country_code":"IN",
    "gn:dem":1102,
    "gn:feature_class":"P",
    "gn:feature_code":"PPL",
    "gn:name":"Baithinlanka",
    "gn:population":0,
    "gn:timezone":"Asia/Kolkata",
    "iso:country":"IN",
    "ks:ks_name":"Baithinilanka",
    "ks:ks_pop":163,
    "ks:ks_type":"HABITATION",
    "name:eng_x_preferred":[
        "Baithinilanka"
    ],
    "name:eng_x_variant":[
        "Baithinlanka"
    ],
    "wof:name":"Baithinilanka",
    "wof:placetype":"locality",
    "wof:population":163
},
  "geometry": {"coordinates":[82.537678,18.141842],"type":"Point"}
}