{
  "type": "Feature",
  "properties": {
    "iso:country":"IN",
    "ks:ks_name":"Chuk Nagar",
    "ks:ks_pop":791,
    "ks:ks_type":"VILLAGE",
    "ks:ks_uagg_main":0,
    "name:eng_x_preferred":[
        "Chuk Nagar"
    ],
    "wof:name":"Chuk Nagar",
    "wof:placetype":"neighbourhood",
    "wof:population":791
},
  "geometry": {"coordinates":[88.776248,22.622944],"type":"Point"}
}