{
  "type": "Feature",
  "properties": {
    "iso:country":"IN",
    "ks:ks_name":"Dakhin Hahkata",
    "ks:ks_pop":327,
    "ks:ks_type":"HABITATION",
    "name:eng_x_preferred":[
        "Dakhin Hahkata"
    ],
    "wof:name":"Dakhin Hahkata",
    "wof:placetype":"locality",
    "wof:population":327
},
  "geometry": {"coordinates":[91.51378200000001,26.590202],"type":"Point"}
}