{
  "type": "Feature",
  "properties": {
    "iso:country":"IN",
    "ks:ks_name":"Hajjudih",
    "ks:ks_pop":68,
    "ks:ks_type":"VILLAGE",
    "name:eng_x_preferred":[
        "Hajjudih"
    ],
    "wof:name":"Hajjudih",
    "wof:placetype":"locality",
    "wof:population":68
},
  "geometry": {"coordinates":[87.09993799999999,25.09785],"type":"Point"}
}