{
  "type": "Feature",
  "properties": {
    "iso:country":"IN",
    "ks:ks_name":"Natpurwa1",
    "ks:ks_pop":286,
    "ks:ks_type":"HABITATION",
    "ks:ks_uagg_main":0,
    "name:eng_x_preferred":[
        "Natpurwa1"
    ],
    "wof:name":"Natpurwa1",
    "wof:placetype":"neighbourhood",
    "wof:population":286
},
  "geometry": {"coordinates":[80.53237900000001,27.647235],"type":"Point"}
}