{
  "type": "Feature",
  "properties": {
    "iso:country":"IN",
    "ks:ks_name":"Sumeswarpur",
    "ks:ks_pop":37,
    "ks:ks_type":"VILLAGE",
    "ks:ks_uagg_main":0,
    "name:eng_x_preferred":[
        "Sumeswarpur"
    ],
    "wof:name":"Sumeswarpur",
    "wof:placetype":"neighbourhood",
    "wof:population":37
},
  "geometry": {"coordinates":[83.182244,25.11599],"type":"Point"}
}