{
  "type": "Feature",
  "properties": {
    "gn:admin1_code":"16.0",
    "gn:admin2_code":"526.0",
    "gn:asciiname":"Itge",
    "gn:country_code":"IN",
    "gn:dem":440,
    "gn:feature_class":"P",
    "gn:feature_code":"PPL",
    "gn:name":"Itge",
    "gn:population":0,
    "gn:timezone":"Asia/Kolkata",
    "iso:country":"IN",
    "wof:name":"Itge",
    "wof:placetype":"locality"
},
  "geometry": {"coordinates":[76.23563,17.49383],"type":"Point"}
}