{
  "type": "Feature",
  "properties": {
    "iso:country":"IN",
    "ks:ks_name":"Kanhai Baba Ka Khoda",
    "ks:ks_pop":635,
    "ks:ks_type":"HABITATION",
    "name:eng_x_preferred":[
        "Kanhai Baba Ka Khoda"
    ],
    "wof:name":"Kanhai Baba Ka Khoda",
    "wof:placetype":"locality",
    "wof:population":635
},
  "geometry": {"coordinates":[80.01260499999999,25.584786],"type":"Point"}
}