{
  "type": "Feature",
  "properties": {
    "iso:country":"IN",
    "ks:ks_alt_nam":"Hatisar F.V",
    "ks:ks_name":"Hatisar F.v",
    "ks:ks_pop":381,
    "ks:ks_type":"HABITATION",
    "name:eng_x_preferred":[
        "Hatisar F.v"
    ],
    "wof:name":"Hatisar F.v",
    "wof:placetype":"locality",
    "wof:population":381
},
  "geometry": {"coordinates":[90.470758,26.852817],"type":"Point"}
}