{
  "type": "Feature",
  "properties": {
    "gn:admin1_code":"23.0",
    "gn:admin2_code":"38.0",
    "gn:asciiname":"Nangal Ghorewah",
    "gn:country_code":"IN",
    "gn:dem":316,
    "gn:feature_class":"P",
    "gn:feature_code":"PPL",
    "gn:name":"Nangal Ghorewah",
    "gn:population":0,
    "gn:timezone":"Asia/Kolkata",
    "iso:country":"IN",
    "ks:ks_name":"Nangal Ghorewah",
    "ks:ks_pop":506,
    "ks:ks_type":"VILLAGE",
    "ks:ks_uagg_main":0,
    "name:eng_x_preferred":[
        "Nangal Ghorewah"
    ],
    "wof:name":"Nangal Ghorewah",
    "wof:placetype":"neighbourhood",
    "wof:population":506
},
  "geometry": {"coordinates":[75.79782899999999,31.728977],"type":"Point"}
}