{
  "type": "Feature",
  "properties": {
    "gn:admin1_code":"34.0",
    "gn:admin2_code":"227.0",
    "gn:asciiname":"Babua Bazar",
    "gn:country_code":"IN",
    "gn:dem":49,
    "gn:feature_class":"P",
    "gn:feature_code":"PPL",
    "gn:name":"Babua B\u0101z\u0101r",
    "gn:population":0,
    "gn:timezone":"Asia/Kolkata",
    "iso:country":"IN",
    "wof:name":"Babua Bazar",
    "wof:placetype":"locality"
},
  "geometry": {"coordinates":[86.31477,25.21193],"type":"Point"}
}