{
  "type": "Feature",
  "properties": {
    "iso:country":"IN",
    "ks:ks_name":"Hendaljuri",
    "ks:ks_pop":1384,
    "ks:ks_type":"VILLAGE",
    "name:eng_x_preferred":[
        "Hendaljuri"
    ],
    "wof:name":"Hendaljuri",
    "wof:placetype":"locality",
    "wof:population":1384
},
  "geometry": {"coordinates":[86.43783999999999,22.655264],"type":"Point"}
}