{
  "type": "Feature",
  "properties": {
    "iso:country":"IN",
    "ks:ks_name":"Khanapur Tryambakpur",
    "ks:ks_pop":42,
    "ks:ks_type":"VILLAGE",
    "name:eng_x_preferred":[
        "Khanapur Tryambakpur"
    ],
    "wof:name":"Khanapur Tryambakpur",
    "wof:placetype":"locality",
    "wof:population":42
},
  "geometry": {"coordinates":[77.015581,21.077522],"type":"Point"}
}