{
  "type": "Feature",
  "properties": {
    "iso:country":"IN",
    "ks:ks_name":"Hire Shakuna",
    "ks:ks_pop":2424,
    "ks:ks_type":"VILLAGE",
    "ks:ks_uagg_main":0,
    "name:eng_x_preferred":[
        "Hire Shakuna"
    ],
    "wof:name":"Hire Shakuna",
    "wof:placetype":"locality",
    "wof:population":2424
},
  "geometry": {"coordinates":[75.101703,14.381322],"type":"Point"}
}