{
  "type": "Feature",
  "properties": {
    "gn:admin1_code":"36.0",
    "gn:admin2_code":"176.0",
    "gn:asciiname":"Rahaura",
    "gn:country_code":"IN",
    "gn:dem":108,
    "gn:feature_class":"P",
    "gn:feature_code":"PPL",
    "gn:name":"Rahaura",
    "gn:population":0,
    "gn:timezone":"Asia/Kolkata",
    "iso:country":"IN",
    "wof:name":"Rahaura",
    "wof:placetype":"neighbourhood"
},
  "geometry": {"coordinates":[81.54263,26.64226],"type":"Point"}
}