{
  "type": "Feature",
  "properties": {
    "gn:admin1_code":"36",
    "gn:admin2_code":"142.0",
    "gn:asciiname":"Kotra",
    "gn:country_code":"IN",
    "gn:dem":204,
    "gn:feature_class":"P",
    "gn:feature_code":"PPL",
    "gn:name":"Kotr\u0101",
    "gn:population":0,
    "gn:timezone":"Asia/Kolkata",
    "iso:country":"IN",
    "wof:name":"Kotra",
    "wof:placetype":"locality"
},
  "geometry": {"coordinates":[78.04738,28.44588],"type":"Point"}
}