{
  "type": "Feature",
  "properties": {
    "iso:country":"IN",
    "ks:ks_name":"Siwana",
    "ks:ks_pop":1606,
    "ks:ks_type":"VILLAGE",
    "name:eng_x_preferred":[
        "Siwana"
    ],
    "wof:name":"Siwana",
    "wof:placetype":"locality",
    "wof:population":1606
},
  "geometry": {"coordinates":[86.276618,25.242277],"type":"Point"}
}