{
  "type": "Feature",
  "properties": {
    "gn:admin1_code":"19.0",
    "gn:admin2_code":"570.0",
    "gn:asciiname":"Sarya",
    "gn:country_code":"IN",
    "gn:dem":691,
    "gn:feature_class":"P",
    "gn:feature_code":"PPL",
    "gn:name":"S\u0101rya",
    "gn:population":0,
    "gn:timezone":"Asia/Kolkata",
    "iso:country":"IN",
    "ks:ks_alt_nam":"S\u0101rya",
    "ks:ks_name":"Sarya",
    "ks:ks_pop":97,
    "ks:ks_type":"VILLAGE",
    "name:eng_x_preferred":[
        "Sarya"
    ],
    "name:eng_x_variant":[
        "S\u0101rya"
    ],
    "wof:name":"Sarya",
    "wof:placetype":"locality",
    "wof:population":97
},
  "geometry": {"coordinates":[75.54549299999999,13.528397],"type":"Point"}
}