{
  "type": "Feature",
  "properties": {
    "iso:country":"IN",
    "ks:ks_name":"Damriay",
    "ks:ks_pop":216,
    "ks:ks_type":"VILLAGE",
    "name:eng_x_preferred":[
        "Damriay"
    ],
    "wof:name":"Damriay",
    "wof:placetype":"locality",
    "wof:population":216
},
  "geometry": {"coordinates":[85.336641,22.922383],"type":"Point"}
}