{
  "type": "Feature",
  "properties": {
    "iso:country":"IN",
    "ks:ks_name":"Lakshmana",
    "ks:ks_pop":2438,
    "ks:ks_type":"HABITATION",
    "name:eng_x_preferred":[
        "Lakshmana"
    ],
    "wof:name":"Lakshmana",
    "wof:placetype":"locality",
    "wof:population":2438
},
  "geometry": {"coordinates":[82.52977799999999,25.258885],"type":"Point"}
}