{
  "type": "Feature",
  "properties": {
    "gn:admin1_code":"11.0",
    "gn:admin2_code":"32.0",
    "gn:asciiname":"Sanohat",
    "gn:country_code":"IN",
    "gn:dem":2072,
    "gn:feature_class":"P",
    "gn:feature_code":"PPL",
    "gn:name":"Sanohat",
    "gn:population":0,
    "gn:timezone":"Asia/Kolkata",
    "iso:country":"IN",
    "wof:name":"Sanohat",
    "wof:placetype":"locality"
},
  "geometry": {"coordinates":[77.36332,30.88638],"type":"Point"}
}