{
  "type": "Feature",
  "properties": {
    "gn:admin1_code":"25.0",
    "gn:admin2_code":"605.0",
    "gn:asciiname":"Ichchampattu",
    "gn:country_code":"IN",
    "gn:dem":346,
    "gn:feature_class":"P",
    "gn:feature_code":"PPL",
    "gn:name":"\u012achchampattu",
    "gn:population":0,
    "gn:timezone":"Asia/Kolkata",
    "iso:country":"IN",
    "wof:name":"Ichchampattu",
    "wof:placetype":"locality"
},
  "geometry": {"coordinates":[78.63621999999999,12.73053],"type":"Point"}
}