{
  "type": "Feature",
  "properties": {
    "iso:country":"IN",
    "ks:ks_name":"Kyadagisar",
    "ks:ks_pop":130,
    "ks:ks_type":"HABITATION",
    "name:eng_x_preferred":[
        "Kyadagisar"
    ],
    "wof:name":"Kyadagisar",
    "wof:placetype":"locality",
    "wof:population":130
},
  "geometry": {"coordinates":[74.793513,14.636355],"type":"Point"}
}