{
  "type": "Feature",
  "properties": {
    "iso:country":"IN",
    "ks:ks_alt_nam":"DODHI BIGHA",
    "ks:ks_name":"Dodhi Bigha",
    "ks:ks_pop":94,
    "ks:ks_type":"HABITATION",
    "name:eng_x_preferred":[
        "Dodhi Bigha"
    ],
    "wof:name":"Dodhi Bigha",
    "wof:placetype":"locality",
    "wof:population":94
},
  "geometry": {"coordinates":[84.634355,24.646625],"type":"Point"}
}