{
  "type": "Feature",
  "properties": {
    "iso:country":"IN",
    "ks:ks_name":"Gorai Urf Askauli",
    "ks:ks_pop":921,
    "ks:ks_type":"VILLAGE",
    "ks:ks_uagg_main":0,
    "name:eng_x_preferred":[
        "Gorai Urf Askauli"
    ],
    "wof:name":"Gorai Urf Askauli",
    "wof:placetype":"neighbourhood",
    "wof:population":921
},
  "geometry": {"coordinates":[85.55475300000001,26.26273],"type":"Point"}
}