{
  "type": "Feature",
  "properties": {
    "gn:admin1_code":"37",
    "gn:admin2_code":"410.0",
    "gn:asciiname":"Sandi",
    "gn:country_code":"IN",
    "gn:dem":282,
    "gn:feature_class":"P",
    "gn:feature_code":"PPL",
    "gn:name":"Sandi",
    "gn:population":0,
    "gn:timezone":"Asia/Kolkata",
    "iso:country":"IN",
    "ks:ks_name":"Sandi",
    "ks:ks_pop":395,
    "ks:ks_type":"VILLAGE",
    "ks:ks_uagg_main":0,
    "name:ceb_x_preferred":[
        "Sandi"
    ],
    "name:eng_x_preferred":[
        "Sandi"
    ],
    "name:ind_x_preferred":[
        "Sandi"
    ],
    "name:nld_x_preferred":[
        "Sandi"
    ],
    "name:swe_x_preferred":[
        "Sandi"
    ],
    "wof:name":"Sandi",
    "wof:placetype":"neighbourhood",
    "wof:population":395
},
  "geometry": {"coordinates":[82.068117,21.452996],"type":"Point"}
}