{
  "type": "Feature",
  "properties": {
    "iso:country":"IN",
    "ks:ks_name":"Gandhinagar",
    "ks:ks_pop":240,
    "ks:ks_type":"HABITATION",
    "name:eng_x_preferred":[
        "Gandhinagar"
    ],
    "wof:name":"Gandhinagar",
    "wof:placetype":"locality",
    "wof:population":240
},
  "geometry": {"coordinates":[76.917005,16.065525],"type":"Point"}
}