{
  "type": "Feature",
  "properties": {
    "iso:country":"IN",
    "ks:ks_name":"Gandhinagar",
    "ks:ks_pop":240,
    "ks:ks_type":"HABITATION",
    "name:eng_x_preferred":[
        "Gandhinagar"
    ],
    "name:guj_x_preferred":[
        "\u0a97\u0abe\u0a82\u0aa7\u0ac0\u0aa8\u0a97\u0ab0"
    ],
    "name:hin_x_preferred":[
        "\u0917\u093e\u0902\u0927\u0940\u0928\u0917\u0930"
    ],
    "wof:name":"Gandhinagar",
    "wof:placetype":"locality",
    "wof:population":240
},
  "geometry": {"coordinates":[76.917005,16.065525],"type":"Point"}
}