{
  "type": "Feature",
  "properties": {
    "iso:country":"IN",
    "ks:ks_name":"Kariyammana Agrahara",
    "ks:ks_pop":763,
    "ks:ks_type":"VILLAGE",
    "ks:ks_uagg_main":0,
    "name:eng_x_preferred":[
        "Kariyammana Agrahara"
    ],
    "wof:name":"Kariyammana Agrahara",
    "wof:placetype":"neighbourhood",
    "wof:population":763
},
  "geometry": {"coordinates":[77.68530800000001,12.936472],"type":"Point"}
}