{
  "type": "Feature",
  "properties": {
    "gn:admin1_code":"11.0",
    "gn:admin2_code":"23.0",
    "gn:asciiname":"Bahi da Bagh",
    "gn:country_code":"IN",
    "gn:dem":635,
    "gn:feature_class":"P",
    "gn:feature_code":"PPL",
    "gn:name":"Bahi da B\u0101gh",
    "gn:population":0,
    "gn:timezone":"Asia/Kolkata",
    "iso:country":"IN",
    "wof:name":"Bahi da Bagh",
    "wof:placetype":"locality"
},
  "geometry": {"coordinates":[75.94025000000001,32.40733],"type":"Point"}
}