{
  "type": "Feature",
  "properties": {
    "iso:country":"IN",
    "ks:ks_name":"Gundakalluhosur",
    "ks:ks_pop":10,
    "ks:ks_type":"HABITATION",
    "name:eng_x_preferred":[
        "Gundakalluhosur"
    ],
    "wof:name":"Gundakalluhosur",
    "wof:placetype":"locality",
    "wof:population":10
},
  "geometry": {"coordinates":[76.801886,12.814224],"type":"Point"}
}