{
  "type": "Feature",
  "properties": {
    "iso:country":"IN",
    "ks:ks_name":"Ayikkudi",
    "ks:ks_pop":3100,
    "ks:ks_type":"VILLAGE",
    "name:eng_x_preferred":[
        "Ayikkudi"
    ],
    "wof:name":"Ayikkudi",
    "wof:placetype":"locality",
    "wof:population":3100
},
  "geometry": {"coordinates":[79.538687,10.799819],"type":"Point"}
}