{
  "type": "Feature",
  "properties": {
    "iso:country":"IN",
    "ks:ks_name":"Sunapalmonda",
    "ks:ks_pop":381,
    "ks:ks_type":"VILLAGE",
    "name:eng_x_preferred":[
        "Sunapalmonda"
    ],
    "wof:name":"Sunapalmonda",
    "wof:placetype":"locality",
    "wof:population":381
},
  "geometry": {"coordinates":[83.288911,18.875419],"type":"Point"}
}