{
  "type": "Feature",
  "properties": {
    "iso:country":"IN",
    "ks:ks_alt_nam":"Dharegan",
    "ks:ks_name":"Daregaon",
    "ks:ks_pop":0,
    "ks:ks_type":"VILLAGE",
    "name:eng_x_preferred":[
        "Daregaon"
    ],
    "name:eng_x_variant":[
        "Dharegan"
    ],
    "wof:name":"Daregaon",
    "wof:placetype":"locality",
    "wof:population":0
},
  "geometry": {"coordinates":[76.09821100000001,19.908057],"type":"Point"}
}