{
  "type": "Feature",
  "properties": {
    "iso:country":"IN",
    "ks:ks_name":"Pure Dhurman",
    "ks:ks_pop":250,
    "ks:ks_type":"HABITATION",
    "name:eng_x_preferred":[
        "Pure Dhurman"
    ],
    "wof:name":"Pure Dhurman",
    "wof:placetype":"locality",
    "wof:population":250
},
  "geometry": {"coordinates":[81.99297199999999,26.848964],"type":"Point"}
}