{
  "type": "Feature",
  "properties": {
    "gn:admin1_code":"36.0",
    "gn:admin2_code":"135.0",
    "gn:asciiname":"Kanaur",
    "gn:country_code":"IN",
    "gn:dem":195,
    "gn:feature_class":"P",
    "gn:feature_code":"PPL",
    "gn:name":"Kanaur",
    "gn:population":0,
    "gn:timezone":"Asia/Kolkata",
    "iso:country":"IN",
    "wof:name":"Kanaur",
    "wof:placetype":"neighbourhood"
},
  "geometry": {"coordinates":[78.71503,28.80729],"type":"Point"}
}