{
  "type": "Feature",
  "properties": {
    "gn:gn_country":"IN",
    "gn:gn_fcode":"PPL",
    "gn:gn_pop":42381,
    "gn:population":42381,
    "iso:country":"IN",
    "name:ara_x_preferred":[
        "\u062f\u064a\u0646\u0647\u0627\u062a\u0629"
    ],
    "name:ben_x_preferred":[
        "\u09a6\u09bf\u09a8\u09b9\u09be\u099f\u09be"
    ],
    "name:bpy_x_preferred":[
        "\u09a6\u09bf\u09a8\u09b9\u09be\u099f\u09be"
    ],
    "name:ceb_x_preferred":[
        "D\u012bnh\u0101ta"
    ],
    "name:ell_x_preferred":[
        "\u039d\u03c4\u03b9\u03bd\u03c7\u03ac\u03c4\u03b1"
    ],
    "name:eng_x_preferred":[
        "Dinhata"
    ],
    "name:fra_x_preferred":[
        "Dinhata"
    ],
    "name:ita_x_preferred":[
        "Dinhata"
    ],
    "name:msa_x_preferred":[
        "Dinhata"
    ],
    "name:new_x_preferred":[
        "\u0926\u093f\u0928\u094d\u0939\u0924\u093e"
    ],
    "name:nld_x_preferred":[
        "Dinhata"
    ],
    "name:por_x_preferred":[
        "Dinhata"
    ],
    "name:spa_x_preferred":[
        "Dinhata"
    ],
    "name:swe_x_preferred":[
        "D\u012bnh\u0101ta"
    ],
    "name:unk_x_variant":[
        "D\u012bnh\u0101ta"
    ],
    "name:vie_x_preferred":[
        "Dinhata"
    ],
    "name:zho_x_preferred":[
        "\u4e01\u54c8\u5854"
    ],
    "qs_pg:aaroncc":"IN",
    "qs_pg:gn_country":"IN",
    "qs_pg:gn_fcode":"PPL",
    "qs_pg:gn_pop":42381,
    "qs_pg:name":"Dinhata",
    "qs_pg:name_adm0":"India",
    "qs_pg:name_adm1":"West Bengal",
    "qs_pg:photos_9k":1,
    "qs_pg:photos_9r":1,
    "qs_pg:photos_all":12,
    "qs_pg:photos_sr":0,
    "qs_pg:pop_sr":7,
    "qs_pg:qs_pg_placetype":"locality",
    "qs_pg:qs_pg_placetype_gp":"Town",
    "qs_pg:woe_adm0":23424848,
    "woe:adm0_id":23424848,
    "woe:name_adm0":"India",
    "woe:name_adm1":"West Bengal",
    "woe:placetype":"Town",
    "wof:name":"Dinhata",
    "wof:placetype":"locality",
    "wof:population":42381
},
  "geometry": {"coordinates":[89.46129000000001,26.13526],"type":"Point"}
}