{
  "type": "Feature",
  "properties": {
    "iso:country":"IN",
    "ks:ks_name":"Thenkulam",
    "ks:ks_pop":450,
    "ks:ks_type":"HABITATION",
    "name:eng_x_preferred":[
        "Thenkulam"
    ],
    "wof:name":"Thenkulam",
    "wof:placetype":"locality",
    "wof:population":450
},
  "geometry": {"coordinates":[75.735416,11.393442],"type":"Point"}
}