{
  "type": "Feature",
  "properties": {
    "iso:country":"IN",
    "ks:ks_name":"Thothiya Para",
    "ks:ks_pop":108,
    "ks:ks_type":"HABITATION",
    "name:eng_x_preferred":[
        "Thothiya Para"
    ],
    "wof:name":"Thothiya Para",
    "wof:placetype":"locality",
    "wof:population":108
},
  "geometry": {"coordinates":[82.127357,19.296007],"type":"Point"}
}