{
  "type": "Feature",
  "properties": {
    "gn:admin1_code":"35.0",
    "gn:admin2_code":"451.0",
    "gn:asciiname":"Bhainsdehi",
    "gn:country_code":"IN",
    "gn:dem":388,
    "gn:feature_class":"P",
    "gn:feature_code":"PPL",
    "gn:name":"Bhainsdehi",
    "gn:population":0,
    "gn:timezone":"Asia/Kolkata",
    "iso:country":"IN",
    "name:ben_x_preferred":[
        "\u09ad\u09c8\u09a8\u09b8\u09a6\u09c7\u09b9\u09bf"
    ],
    "name:bpy_x_preferred":[
        "\u09ad\u09c8\u09a8\u09b8\u09a6\u09c7\u09b9\u09bf"
    ],
    "name:ceb_x_preferred":[
        "Bhainsdehi"
    ],
    "name:ita_x_preferred":[
        "Bhainsdehi"
    ],
    "name:mlg_x_preferred":[
        "Bhainsdehi"
    ],
    "name:msa_x_preferred":[
        "Bhainsdehi"
    ],
    "name:new_x_preferred":[
        "\u092d\u0948\u0928\u094d\u0938\u094d\u0926\u0947\u0939\u0940"
    ],
    "name:nld_x_preferred":[
        "Bhainsdehi"
    ],
    "name:por_x_preferred":[
        "Bhainsdehi"
    ],
    "name:spa_x_preferred":[
        "Bhainsdehi"
    ],
    "name:swe_x_preferred":[
        "Bhainsdehi"
    ],
    "name:vie_x_preferred":[
        "Bhainsdehi"
    ],
    "name:zho_x_preferred":[
        "\u62dc\u6069\u65af\u5fb7\u5e0c"
    ],
    "wof:name":"Bhainsdehi",
    "wof:placetype":"locality"
},
  "geometry": {"coordinates":[80.01817,23.31497],"type":"Point"}
}