{
  "type": "Feature",
  "properties": {
    "iso:country":"IN",
    "ks:ks_name":"Sidarpara",
    "ks:ks_pop":458,
    "ks:ks_type":"HABITATION",
    "name:eng_x_preferred":[
        "Sidarpara"
    ],
    "wof:name":"Sidarpara",
    "wof:placetype":"locality",
    "wof:population":458
},
  "geometry": {"coordinates":[83.111203,22.264255],"type":"Point"}
}