{
  "type": "Feature",
  "properties": {
    "gn:admin1_code":"36",
    "gn:admin2_code":"194.0",
    "gn:asciiname":"Marar",
    "gn:country_code":"IN",
    "gn:dem":91,
    "gn:feature_class":"P",
    "gn:feature_code":"PPL",
    "gn:name":"Mar\u0101r",
    "gn:population":0,
    "gn:timezone":"Asia/Kolkata",
    "iso:country":"IN",
    "name:und_x_variant":[
        "Mar\u0101r",
        "Manr\u0101r D\u012bh"
    ],
    "wof:name":"Marar",
    "wof:placetype":"locality"
},
  "geometry": {"coordinates":[82.23974,25.68351],"type":"Point"}
}