{
  "type": "Feature",
  "properties": {
    "iso:country":"IN",
    "ks:ks_name":"Dhangadpada",
    "ks:ks_pop":197,
    "ks:ks_type":"HABITATION",
    "name:eng_x_preferred":[
        "Dhangadpada"
    ],
    "wof:name":"Dhangadpada",
    "wof:placetype":"locality",
    "wof:population":197
},
  "geometry": {"coordinates":[72.975239,19.971914],"type":"Point"}
}