{
  "type": "Feature",
  "properties": {
    "iso:country":"IN",
    "ks:ks_alt_nam":"Jal\u0101lpur",
    "ks:ks_name":"Jalalpur",
    "ks:ks_type":"VILLAGE",
    "ks:ks_uagg_main":0,
    "name:eng_x_preferred":[
        "Jalalpur"
    ],
    "name:eng_x_variant":[
        "Jal\u0101lpur"
    ],
    "wof:name":"Jalalpur",
    "wof:placetype":"neighbourhood"
},
  "geometry": {"coordinates":[85.060305,25.599977],"type":"Point"}
}