{
  "type": "Feature",
  "properties": {
    "iso:country":"IN",
    "ks:ks_name":"Badhawa",
    "ks:ks_pop":1442,
    "ks:ks_type":"VILLAGE",
    "name:eng_x_preferred":[
        "Badhawa"
    ],
    "wof:name":"Badhawa",
    "wof:placetype":"locality",
    "wof:population":1442
},
  "geometry": {"coordinates":[75.08268,24.798781],"type":"Point"}
}