{
  "type": "Feature",
  "properties": {
    "gn:admin1_code":"19.0",
    "gn:admin2_code":"577.0",
    "gn:asciiname":"Mundur",
    "gn:country_code":"IN",
    "gn:dem":838,
    "gn:feature_class":"P",
    "gn:feature_code":"PPL",
    "gn:name":"Mund\u016br",
    "gn:population":0,
    "gn:timezone":"Asia/Kolkata",
    "iso:country":"IN",
    "name:pol_x_preferred":[
        "Mundur"
    ],
    "wof:name":"Mundur",
    "wof:placetype":"locality"
},
  "geometry": {"coordinates":[76.25660000000001,12.60682],"type":"Point"}
}