{
  "type": "Feature",
  "properties": {
    "gn:admin1_code":"12.0",
    "gn:admin2_code":"22.0",
    "gn:asciiname":"Odh",
    "gn:country_code":"IN",
    "gn:dem":494,
    "gn:feature_class":"P",
    "gn:feature_code":"PPL",
    "gn:name":"Odh",
    "gn:population":0,
    "gn:timezone":"Asia/Kolkata",
    "iso:country":"IN",
    "wof:name":"Odh",
    "wof:placetype":"locality"
},
  "geometry": {"coordinates":[75.27034,32.57186],"type":"Point"}
}