{
  "type": "Feature",
  "properties": {
    "gn:admin1_code":"36.0",
    "gn:admin2_code":"138.0",
    "gn:asciiname":"Machhra",
    "gn:country_code":"IN",
    "gn:dem":219,
    "gn:feature_class":"P",
    "gn:feature_code":"PPL",
    "gn:name":"M\u0101chhra",
    "gn:population":0,
    "gn:timezone":"Asia/Kolkata",
    "iso:country":"IN",
    "ks:ks_alt_nam":"M\u0101chhra",
    "ks:ks_name":"Machhra",
    "ks:ks_type":"VILLAGE",
    "name:eng_x_preferred":[
        "Machhra"
    ],
    "name:eng_x_variant":[
        "M\u0101chhra"
    ],
    "wof:name":"Machhra",
    "wof:placetype":"locality"
},
  "geometry": {"coordinates":[77.893852,28.901595],"type":"Point"}
}