{
  "type": "Feature",
  "properties": {
    "gn:admin1_code":"36",
    "gn:admin2_code":"175.0",
    "gn:asciiname":"Sarai Gani",
    "gn:country_code":"IN",
    "gn:dem":101,
    "gn:feature_class":"P",
    "gn:feature_code":"PPL",
    "gn:name":"Sar\u0101i Gani",
    "gn:population":0,
    "gn:timezone":"Asia/Kolkata",
    "iso:country":"IN",
    "ks:ks_name":"Sarai Gani",
    "ks:ks_pop":880,
    "ks:ks_type":"VILLAGE",
    "ks:ks_uagg_main":0,
    "name:eng_x_preferred":[
        "Sarai Gani"
    ],
    "wof:name":"Sarai Gani",
    "wof:placetype":"neighbourhood",
    "wof:population":880
},
  "geometry": {"coordinates":[81.99582100000001,25.620416],"type":"Point"}
}