{
  "type": "Feature",
  "properties": {
    "iso:country":"IN",
    "ks:ks_name":"Khakhrisal",
    "ks:ks_pop":518,
    "ks:ks_type":"VILLAGE",
    "ks:ks_uagg_main":0,
    "name:eng_x_preferred":[
        "Khakhrisal"
    ],
    "wof:name":"Khakhrisal",
    "wof:placetype":"neighbourhood",
    "wof:population":518
},
  "geometry": {"coordinates":[91.378275,26.336265],"type":"Point"}
}