{
  "type": "Feature",
  "properties": {
    "iso:country":"IN",
    "ks:ks_alt_nam":"GANGDAHA",
    "ks:ks_name":"Gangdaha",
    "ks:ks_pop":88,
    "ks:ks_type":"HABITATION",
    "name:eng_x_preferred":[
        "Gangdaha"
    ],
    "wof:name":"Gangdaha",
    "wof:placetype":"locality",
    "wof:population":88
},
  "geometry": {"coordinates":[85.47790500000001,24.174441],"type":"Point"}
}