{
  "type": "Feature",
  "properties": {
    "iso:country":"IN",
    "ks:ks_alt_nam":"KOERI TOLA",
    "ks:ks_name":"Koeri Tola",
    "ks:ks_pop":60,
    "ks:ks_type":"HABITATION",
    "name:eng_x_preferred":[
        "Koeri Tola"
    ],
    "wof:name":"Koeri Tola",
    "wof:placetype":"locality",
    "wof:population":60
},
  "geometry": {"coordinates":[86.992493,25.178276],"type":"Point"}
}