{
  "type": "Feature",
  "properties": {
    "gn:admin1_code":"2",
    "gn:admin2_code":"546.0",
    "gn:asciiname":"Komarada",
    "gn:country_code":"IN",
    "gn:dem":7,
    "gn:feature_class":"P",
    "gn:feature_code":"PPL",
    "gn:name":"Komar\u0101da",
    "gn:population":0,
    "gn:timezone":"Asia/Kolkata",
    "iso:country":"IN",
    "name:new_x_preferred":[
        "\u0915\u094b\u092e\u0930\u093e\u0921 \u092e\u0923\u094d\u0921\u0932"
    ],
    "name:tam_x_preferred":[
        "\u0b95\u0bca\u0bae\u0bb0\u0bbe\u0b9f\u0bbe"
    ],
    "name:tel_x_preferred":[
        "\u0c15\u0c4a\u0c2e\u0c30\u0c3e\u0c21"
    ],
    "name:urd_x_preferred":[
        "\u06a9\u0648\u0645\u0627\u0631\u0627\u0691\u0627"
    ],
    "wof:name":"Komarada",
    "wof:placetype":"locality"
},
  "geometry": {"coordinates":[81.50739,16.49719],"type":"Point"}
}