{
  "type": "Feature",
  "properties": {
    "iso:country":"IN",
    "ks:ks_name":"Makanal",
    "ks:ks_pop":1050,
    "ks:ks_type":"HABITATION",
    "name:eng_x_preferred":[
        "Makanal"
    ],
    "wof:name":"Makanal",
    "wof:placetype":"locality",
    "wof:population":1050
},
  "geometry": {"coordinates":[76.72459000000001,9.449716],"type":"Point"}
}