{
  "type": "Feature",
  "properties": {
    "gn:admin1_code":"2.0",
    "gn:admin2_code":"543.0",
    "gn:asciiname":"Lollarpadu",
    "gn:country_code":"IN",
    "gn:dem":516,
    "gn:feature_class":"P",
    "gn:feature_code":"PPL",
    "gn:name":"Lollarp\u0101du",
    "gn:population":0,
    "gn:timezone":"Asia/Kolkata",
    "iso:country":"IN",
    "ks:ks_name":"Loilarapadu",
    "ks:ks_pop":185,
    "ks:ks_type":"HABITATION",
    "name:eng_x_preferred":[
        "Loilarapadu"
    ],
    "name:eng_x_variant":[
        "Lollarpadu"
    ],
    "wof:name":"Loilarapadu",
    "wof:placetype":"locality",
    "wof:population":185
},
  "geometry": {"coordinates":[83.20946499999999,18.415794],"type":"Point"}
}