{
  "type": "Feature",
  "properties": {
    "iso:country":"IN",
    "ks:ks_name":"Seemarlabavi",
    "ks:ks_pop":40,
    "ks:ks_type":"HABITATION",
    "name:eng_x_preferred":[
        "Seemarlabavi"
    ],
    "wof:name":"Seemarlabavi",
    "wof:placetype":"locality",
    "wof:population":40
},
  "geometry": {"coordinates":[78.923007,16.597104],"type":"Point"}
}