{
  "type": "Feature",
  "properties": {
    "iso:country":"IN",
    "ks:ks_name":"Gumadi m",
    "ks:ks_pop":56,
    "ks:ks_type":"VILLAGE",
    "name:eng_x_preferred":[
        "Gumadi m"
    ],
    "wof:name":"Gumadi m",
    "wof:placetype":"locality",
    "wof:population":56
},
  "geometry": {"coordinates":[80.28655000000001,19.965753],"type":"Point"}
}