{
  "type": "Feature",
  "properties": {
    "iso:country":"IN",
    "ks:ks_name":"Piyali",
    "ks:ks_pop":4033,
    "ks:ks_type":"HABITATION",
    "name:eng_x_preferred":[
        "Piyali"
    ],
    "wof:name":"Piyali",
    "wof:placetype":"locality",
    "wof:population":4033
},
  "geometry": {"coordinates":[88.51595500000001,22.377303],"type":"Point"}
}