{
  "type": "Feature",
  "properties": {
    "gn:admin1_code":"19.0",
    "gn:admin2_code":"569.0",
    "gn:asciiname":"Kanbettu",
    "gn:country_code":"IN",
    "gn:dem":75,
    "gn:feature_class":"P",
    "gn:feature_code":"PPL",
    "gn:name":"Kanbettu",
    "gn:population":0,
    "gn:timezone":"Asia/Kolkata",
    "iso:country":"IN",
    "ks:ks_name":"Kanabettu",
    "ks:ks_pop":36,
    "ks:ks_type":"HABITATION",
    "name:eng_x_preferred":[
        "Kanabettu"
    ],
    "name:eng_x_variant":[
        "Kanbettu"
    ],
    "wof:name":"Kanabettu",
    "wof:placetype":"locality",
    "wof:population":36
},
  "geometry": {"coordinates":[75.017285,13.492295],"type":"Point"}
}