{
  "type": "Feature",
  "properties": {
    "iso:country":"IN",
    "ks:ks_name":"Asgar Purwa",
    "ks:ks_pop":94,
    "ks:ks_type":"HABITATION",
    "name:eng_x_preferred":[
        "Asgar Purwa"
    ],
    "wof:name":"Asgar Purwa",
    "wof:placetype":"locality",
    "wof:population":94
},
  "geometry": {"coordinates":[81.620638,27.227515],"type":"Point"}
}