{
  "type": "Feature",
  "properties": {
    "iso:country":"IN",
    "ks:ks_name":"Tadama",
    "ks:ks_pop":89,
    "ks:ks_type":"VILLAGE",
    "name:eng_x_preferred":[
        "Tadama"
    ],
    "wof:name":"Tadama",
    "wof:placetype":"locality",
    "wof:population":89
},
  "geometry": {"coordinates":[84.35204,19.991311],"type":"Point"}
}