{
  "type": "Feature",
  "properties": {
    "gn:admin1_code":"13.0",
    "gn:admin2_code":"590.0",
    "gn:asciiname":"Alathur",
    "gn:country_code":"IN",
    "gn:dem":759,
    "gn:feature_class":"P",
    "gn:feature_code":"PPL",
    "gn:name":"Alath\u016br",
    "gn:population":0,
    "gn:timezone":"Asia/Kolkata",
    "iso:country":"IN",
    "name:fas_x_preferred":[
        "\u0622\u0644\u0627\u062a\u0647\u0648\u0631"
    ],
    "name:mal_x_preferred":[
        "\u0d06\u0d32\u0d24\u0d4d\u0d24\u0d42\u0d7c"
    ],
    "name:msa_x_preferred":[
        "Alathur"
    ],
    "name:tam_x_preferred":[
        "\u0b86\u0bb2\u0ba4\u0bcd\u0ba4\u0bc2\u0bb0\u0bcd"
    ],
    "name:urd_x_preferred":[
        "\u0622\u0644\u0627\u062a\u0648\u0631"
    ],
    "name:vie_x_preferred":[
        "Alathur"
    ],
    "wof:name":"Alathur",
    "wof:placetype":"locality"
},
  "geometry": {"coordinates":[76.05965999999999,11.86415],"type":"Point"}
}