{
  "type": "Feature",
  "properties": {
    "gn:admin1_code":"21",
    "gn:admin2_code":"370.0",
    "gn:asciiname":"Buren",
    "gn:country_code":"IN",
    "gn:dem":247,
    "gn:feature_class":"P",
    "gn:feature_code":"PPL",
    "gn:name":"Buren",
    "gn:population":0,
    "gn:timezone":"Asia/Kolkata",
    "iso:country":"IN",
    "name:ara_x_preferred":[
        "\u0628\u0648\u0631\u064a\u0646"
    ],
    "name:cat_x_preferred":[
        "Buren"
    ],
    "name:ceb_x_preferred":[
        "Gemeente Buren"
    ],
    "name:deu_x_preferred":[
        "Buren"
    ],
    "name:epo_x_preferred":[
        "Buren"
    ],
    "name:eus_x_preferred":[
        "Buren"
    ],
    "name:fas_x_preferred":[
        "\u0628\u0648\u0631\u0646"
    ],
    "name:fin_x_preferred":[
        "Buren"
    ],
    "name:fra_x_preferred":[
        "Buren"
    ],
    "name:fry_x_preferred":[
        "Buren"
    ],
    "name:hak_x_preferred":[
        "Buren"
    ],
    "name:hye_x_preferred":[
        "\u0532\u0578\u0582\u0580\u0565\u0576"
    ],
    "name:ind_x_preferred":[
        "Buren"
    ],
    "name:ita_x_preferred":[
        "Buren"
    ],
    "name:jav_x_preferred":[
        "Buren"
    ],
    "name:lim_x_preferred":[
        "Buren"
    ],
    "name:msa_x_preferred":[
        "Buren"
    ],
    "name:nld_x_preferred":[
        "Buren"
    ],
    "name:nor_x_preferred":[
        "Buren"
    ],
    "name:pol_x_preferred":[
        "Buren"
    ],
    "name:ron_x_preferred":[
        "Buren"
    ],
    "name:rus_x_preferred":[
        "\u0411\u044e\u0440\u0435\u043d"
    ],
    "name:spa_x_preferred":[
        "Buren"
    ],
    "name:sqi_x_preferred":[
        "Buren"
    ],
    "name:stq_x_preferred":[
        "Buren"
    ],
    "name:swe_x_preferred":[
        "Buren"
    ],
    "name:tur_x_preferred":[
        "Buren"
    ],
    "name:vie_x_preferred":[
        "Buren"
    ],
    "name:vol_x_preferred":[
        "Buren"
    ],
    "name:war_x_preferred":[
        "Buren"
    ],
    "name:zho_x_preferred":[
        "\u6bd4\u502b"
    ],
    "wof:name":"Buren",
    "wof:placetype":"locality"
},
  "geometry": {"coordinates":[83.01703000000001,20.88089],"type":"Point"}
}