{
  "type": "Feature",
  "properties": {
    "iso:country":"IN",
    "ks:ks_alt_nam":"KAIKATTI",
    "ks:ks_name":"Kaikatti",
    "ks:ks_pop":200,
    "ks:ks_type":"HABITATION",
    "name:eng_x_preferred":[
        "Kaikatti"
    ],
    "wof:name":"Kaikatti",
    "wof:placetype":"locality",
    "wof:population":200
},
  "geometry": {"coordinates":[76.873356,10.645459],"type":"Point"}
}