{
  "type": "Feature",
  "properties": {
    "iso:country":"IN",
    "ks:ks_alt_nam":"Balijan TE 8 No Line",
    "ks:ks_name":"Balijan Te 8 No Line",
    "ks:ks_pop":472,
    "ks:ks_type":"HABITATION",
    "name:eng_x_preferred":[
        "Balijan Te 8 No Line"
    ],
    "wof:name":"Balijan Te 8 No Line",
    "wof:placetype":"locality",
    "wof:population":472
},
  "geometry": {"coordinates":[95.16238300000001,27.527241],"type":"Point"}
}