{
  "type": "Feature",
  "properties": {
    "iso:country":"IN",
    "ks:ks_name":"Damgan Batimunda",
    "ks:ks_pop":57,
    "ks:ks_type":"VILLAGE",
    "name:eng_x_preferred":[
        "Damgan Batimunda"
    ],
    "wof:name":"Damgan Batimunda",
    "wof:placetype":"locality",
    "wof:population":57
},
  "geometry": {"coordinates":[83.664772,20.294133],"type":"Point"}
}