{
  "type": "Feature",
  "properties": {
    "gn:admin1_code":"2.0",
    "gn:admin2_code":"551.0",
    "gn:asciiname":"Murarichintala",
    "gn:country_code":"IN",
    "gn:dem":357,
    "gn:feature_class":"P",
    "gn:feature_code":"PPL",
    "gn:name":"Mur\u0101richintala",
    "gn:population":0,
    "gn:timezone":"Asia/Kolkata",
    "iso:country":"IN",
    "wof:name":"Murarichintala",
    "wof:placetype":"locality"
},
  "geometry": {"coordinates":[78.07495,14.44598],"type":"Point"}
}