{
  "type": "Feature",
  "properties": {
    "iso:country":"IN",
    "ks:ks_name":"Gajra",
    "ks:ks_pop":1121,
    "ks:ks_type":"VILLAGE",
    "name:eng_x_preferred":[
        "Gajra"
    ],
    "wof:name":"Gajra",
    "wof:placetype":"locality",
    "wof:population":1121
},
  "geometry": {"coordinates":[76.77928799999999,25.145552],"type":"Point"}
}