{
  "type": "Feature",
  "properties": {
    "iso:country":"IN",
    "ks:ks_alt_nam":"mashon",
    "ks:ks_name":"Mashon",
    "ks:ks_pop":299,
    "ks:ks_type":"HABITATION",
    "name:eng_x_preferred":[
        "Mashon"
    ],
    "wof:name":"Mashon",
    "wof:placetype":"locality",
    "wof:population":299
},
  "geometry": {"coordinates":[78.31472100000001,30.692962],"type":"Point"}
}