{
  "type": "Feature",
  "properties": {
    "iso:country":"IN",
    "ks:ks_name":"Karkapara",
    "ks:ks_pop":286,
    "ks:ks_type":"HABITATION",
    "name:eng_x_preferred":[
        "Karkapara"
    ],
    "wof:name":"Karkapara",
    "wof:placetype":"locality",
    "wof:population":286
},
  "geometry": {"coordinates":[81.329195,18.466986],"type":"Point"}
}