{
  "type": "Feature",
  "properties": {
    "iso:country":"IN",
    "ks:ks_name":"Vajrangi",
    "ks:ks_pop":100,
    "ks:ks_type":"HABITATION",
    "name:eng_x_preferred":[
        "Vajrangi"
    ],
    "wof:name":"Vajrangi",
    "wof:placetype":"locality",
    "wof:population":100
},
  "geometry": {"coordinates":[75.297944,12.857504],"type":"Point"}
}