{
  "type": "Feature",
  "properties": {
    "iso:country":"IN",
    "ks:ks_name":"Botha",
    "ks:ks_pop":281,
    "ks:ks_type":"HABITATION",
    "name:eng_x_preferred":[
        "Botha"
    ],
    "wof:name":"Botha",
    "wof:placetype":"locality",
    "wof:population":281
},
  "geometry": {"coordinates":[81.49914,19.829457],"type":"Point"}
}