{
  "type": "Feature",
  "properties": {
    "gn:admin1_code":"19.0",
    "gn:admin2_code":"583.0",
    "gn:asciiname":"Kattekelagnahalli",
    "gn:country_code":"IN",
    "gn:dem":758,
    "gn:feature_class":"P",
    "gn:feature_code":"PPL",
    "gn:name":"Kattekelagnahalli",
    "gn:population":0,
    "gn:timezone":"Asia/Kolkata",
    "iso:country":"IN",
    "wof:name":"Kattekelagnahalli",
    "wof:placetype":"locality"
},
  "geometry": {"coordinates":[77.45097,13.44258],"type":"Point"}
}