{
  "type": "Feature",
  "properties": {
    "iso:country":"IN",
    "ks:ks_name":"Saralikalam",
    "ks:ks_pop":210,
    "ks:ks_type":"HABITATION",
    "name:eng_x_preferred":[
        "Saralikalam"
    ],
    "wof:name":"Saralikalam",
    "wof:placetype":"locality",
    "wof:population":210
},
  "geometry": {"coordinates":[77.39543500000001,9.990038],"type":"Point"}
}