{
  "type": "Feature",
  "properties": {
    "gn:admin1_code":"35",
    "gn:admin2_code":"462.0",
    "gn:asciiname":"Chorba",
    "gn:country_code":"IN",
    "gn:dem":346,
    "gn:feature_class":"P",
    "gn:feature_code":"PPL",
    "gn:name":"Chorba",
    "gn:population":0,
    "gn:timezone":"Asia/Kolkata",
    "iso:country":"IN",
    "name:ben_x_preferred":[
        "\u09b6\u09b0\u09cd\u09ac\u09be"
    ],
    "name:bos_x_preferred":[
        "\u010corba"
    ],
    "name:cat_x_preferred":[
        "Shurba"
    ],
    "name:chv_x_preferred":[
        "\u0428\u04f3\u0440\u043f\u0435"
    ],
    "name:deu_x_preferred":[
        "Chorba"
    ],
    "name:fas_x_preferred":[
        "\u0634\u0648\u0631\u0628\u0627"
    ],
    "name:fra_x_preferred":[
        "Chorba"
    ],
    "name:ind_x_preferred":[
        "Chorba"
    ],
    "name:ita_x_preferred":[
        "Chorba"
    ],
    "name:jpn_x_preferred":[
        "\u30c1\u30e7\u30eb\u30d0"
    ],
    "name:kaz_x_preferred":[
        "\u0428\u0443\u0440\u043f\u0430"
    ],
    "name:kor_x_preferred":[
        "\ucd08\ub974\ubc14"
    ],
    "name:mkd_x_preferred":[
        "\u0427\u043e\u0440\u0431\u0430"
    ],
    "name:por_x_preferred":[
        "Sorpa"
    ],
    "name:rus_x_preferred":[
        "\u0428\u0443\u0440\u043f\u0430"
    ],
    "name:spa_x_preferred":[
        "\u00c7orba"
    ],
    "name:srp_x_preferred":[
        "\u0427\u043e\u0440\u0431\u0430"
    ],
    "name:tur_x_preferred":[
        "\u00c7orba"
    ],
    "name:ukr_x_preferred":[
        "\u0428\u0443\u0440\u043f\u0430"
    ],
    "wof:name":"Chorba",
    "wof:placetype":"locality"
},
  "geometry": {"coordinates":[81.67466999999998,24.15701],"type":"Point"}
}