{
  "type": "Feature",
  "properties": {
    "gn:admin1_code":"16.0",
    "gn:admin2_code":"507.0",
    "gn:asciiname":"Kikripartola",
    "gn:country_code":"IN",
    "gn:dem":320,
    "gn:feature_class":"P",
    "gn:feature_code":"PPL",
    "gn:name":"Kikr\u012bp\u0101rtol\u0101",
    "gn:population":0,
    "gn:timezone":"Asia/Kolkata",
    "iso:country":"IN",
    "wof:name":"Kikripartola",
    "wof:placetype":"neighbourhood"
},
  "geometry": {"coordinates":[80.34644,21.41332],"type":"Point"}
}