{
  "type": "Feature",
  "properties": {
    "iso:country":"IN",
    "ks:ks_name":"Chikkahebbarige",
    "ks:ks_pop":46,
    "ks:ks_type":"HABITATION",
    "name:eng_x_preferred":[
        "Chikkahebbarige"
    ],
    "wof:name":"Chikkahebbarige",
    "wof:placetype":"locality",
    "wof:population":46
},
  "geometry": {"coordinates":[75.056034,14.051284],"type":"Point"}
}