{
  "type": "Feature",
  "properties": {
    "iso:country":"IN",
    "ks:ks_alt_nam":"chatakpurwa",
    "ks:ks_name":"Chatakpurwa",
    "ks:ks_pop":92,
    "ks:ks_type":"HABITATION",
    "ks:ks_uagg_main":0,
    "name:eng_x_preferred":[
        "Chatakpurwa"
    ],
    "wof:name":"Chatakpurwa",
    "wof:placetype":"neighbourhood",
    "wof:population":92
},
  "geometry": {"coordinates":[81.75805800000001,27.347452],"type":"Point"}
}