{
  "type": "Feature",
  "properties": {
    "iso:country":"IN",
    "ks:ks_name":"Pauna",
    "ks:ks_pop":379,
    "ks:ks_type":"HABITATION",
    "name:eng_x_preferred":[
        "Pauna"
    ],
    "wof:name":"Pauna",
    "wof:placetype":"locality",
    "wof:population":379
},
  "geometry": {"coordinates":[82.857275,25.354458],"type":"Point"}
}