{
  "type": "Feature",
  "properties": {
    "gn:admin1_code":"2.0",
    "gn:admin2_code":"549.0",
    "gn:asciiname":"Gudem",
    "gn:country_code":"IN",
    "gn:dem":185,
    "gn:feature_class":"P",
    "gn:feature_code":"PPL",
    "gn:name":"G\u016bdem",
    "gn:population":0,
    "gn:timezone":"Asia/Kolkata",
    "iso:country":"IN",
    "name:tel_x_preferred":[
        "\u0c17\u0c42\u0c21\u0c46\u0c2e\u0c41"
    ],
    "wof:name":"Gudem",
    "wof:placetype":"neighbourhood"
},
  "geometry": {"coordinates":[79.11691,15.56183],"type":"Point"}
}