{
  "type": "Feature",
  "properties": {
    "gn:admin1_code":"35",
    "gn:admin2_code":"455.0",
    "gn:asciiname":"Bhardagarh",
    "gn:country_code":"IN",
    "gn:dem":700,
    "gn:feature_class":"P",
    "gn:feature_code":"PPL",
    "gn:name":"Bhard\u0101garh",
    "gn:population":0,
    "gn:timezone":"Asia/Kolkata",
    "iso:country":"IN",
    "ks:ks_alt_nam":"Bhard\u0101garh",
    "ks:ks_name":"Bhardagarh",
    "ks:ks_pop":2006,
    "ks:ks_type":"VILLAGE",
    "name:eng_x_preferred":[
        "Bhardagarh"
    ],
    "name:eng_x_variant":[
        "Bhard\u0101garh"
    ],
    "wof:name":"Bhardagarh",
    "wof:placetype":"locality",
    "wof:population":2006
},
  "geometry": {"coordinates":[78.391902,22.171671],"type":"Point"}
}