{
  "type": "Feature",
  "properties": {
    "iso:country":"IN",
    "ks:ks_name":"Chakk Barayatha",
    "ks:ks_pop":0,
    "ks:ks_type":"VILLAGE",
    "name:eng_x_preferred":[
        "Chakk Barayatha"
    ],
    "wof:name":"Chakk Barayatha",
    "wof:placetype":"locality",
    "wof:population":0
},
  "geometry": {"coordinates":[78.96287700000001,24.301607],"type":"Point"}
}