{
  "type": "Feature",
  "properties": {
    "iso:country":"IN",
    "ks:ks_name":"Hosamane",
    "ks:ks_pop":20,
    "ks:ks_type":"HABITATION",
    "name:eng_x_preferred":[
        "Hosamane"
    ],
    "wof:name":"Hosamane",
    "wof:placetype":"locality",
    "wof:population":20
},
  "geometry": {"coordinates":[74.731065,14.672032],"type":"Point"}
}