{
  "type": "Feature",
  "properties": {
    "iso:country":"IN",
    "ks:ks_name":"Chak Khunda Urf Milki",
    "ks:ks_pop":701,
    "ks:ks_type":"VILLAGE",
    "name:eng_x_preferred":[
        "Chak Khunda Urf Milki"
    ],
    "wof:name":"Chak Khunda Urf Milki",
    "wof:placetype":"locality",
    "wof:population":701
},
  "geometry": {"coordinates":[85.293403,25.732741],"type":"Point"}
}