{
  "type": "Feature",
  "properties": {
    "gn:admin1_code":"11",
    "gn:admin2_code":"23.0",
    "gn:asciiname":"Patruma",
    "gn:country_code":"IN",
    "gn:dem":1525,
    "gn:feature_class":"P",
    "gn:feature_code":"PPL",
    "gn:name":"Patr\u016bma",
    "gn:population":0,
    "gn:timezone":"Asia/Kolkata",
    "iso:country":"IN",
    "wof:name":"Patruma",
    "wof:placetype":"locality"
},
  "geometry": {"coordinates":[76.01004,32.71385],"type":"Point"}
}