{
  "type": "Feature",
  "properties": {
    "gn:admin1_code":"25.0",
    "gn:admin2_code":"610.0",
    "gn:asciiname":"Modavandipalaiyam",
    "gn:country_code":"IN",
    "gn:dem":266,
    "gn:feature_class":"P",
    "gn:feature_code":"PPL",
    "gn:name":"Modavandip\u0101laiyam",
    "gn:population":0,
    "gn:timezone":"Asia/Kolkata",
    "iso:country":"IN",
    "name:und_x_variant":[
        "Modavandip\u0101laiyam",
        "R\u0101yarp\u0101laiyam"
    ],
    "wof:name":"Modavandipalaiyam",
    "wof:placetype":"neighbourhood"
},
  "geometry": {"coordinates":[77.33091,11.39873],"type":"Point"}
}