{
  "type": "Feature",
  "properties": {
    "gn:admin1_code":"38.0",
    "gn:admin2_code":"354",
    "gn:asciiname":"Bhowra",
    "gn:country_code":"IN",
    "gn:dem":179,
    "gn:feature_class":"P",
    "gn:feature_code":"PPL",
    "gn:name":"Bhowra",
    "gn:population":0,
    "gn:timezone":"Asia/Kolkata",
    "iso:country":"IN",
    "wof:name":"Bhowra",
    "wof:placetype":"neighbourhood"
},
  "geometry": {"coordinates":[86.40000000000001,23.71667],"type":"Point"}
}