{
  "type": "Feature",
  "properties": {
    "gn:admin1_code":"11.0",
    "gn:admin2_code":"27.0",
    "gn:asciiname":"Kaitho",
    "gn:country_code":"IN",
    "gn:dem":1827,
    "gn:feature_class":"P",
    "gn:feature_code":"PPL",
    "gn:name":"Kaitho",
    "gn:population":0,
    "gn:timezone":"Asia/Kolkata",
    "iso:country":"IN",
    "wof:name":"Kaitho",
    "wof:placetype":"locality"
},
  "geometry": {"coordinates":[77.19569,31.3196],"type":"Point"}
}