{
  "type": "Feature",
  "properties": {
    "iso:country":"IN",
    "ks:ks_name":"Peer Khera",
    "ks:ks_pop":240,
    "ks:ks_type":"VILLAGE",
    "ks:ks_uagg_main":0,
    "name:eng_x_preferred":[
        "Peer Khera"
    ],
    "wof:name":"Peer Khera",
    "wof:placetype":"neighbourhood",
    "wof:population":240
},
  "geometry": {"coordinates":[74.625703,24.670733],"type":"Point"}
}