{
  "type": "Feature",
  "properties": {
    "iso:country":"IN",
    "ks:ks_name":"Chowdahalli",
    "ks:ks_type":"VILLAGE",
    "name:eng_x_preferred":[
        "Chowdahalli"
    ],
    "wof:name":"Chowdahalli",
    "wof:placetype":"locality"
},
  "geometry": {"coordinates":[76.473381,11.861265],"type":"Point"}
}