{
  "type": "Feature",
  "properties": {
    "iso:country":"IN",
    "ks:ks_name":"Hudera Athoona",
    "ks:ks_pop":761,
    "ks:ks_type":"VILLAGE",
    "ks:ks_uagg_main":0,
    "name:eng_x_preferred":[
        "Hudera Athoona"
    ],
    "wof:name":"Hudera Athoona",
    "wof:placetype":"neighbourhood",
    "wof:population":761
},
  "geometry": {"coordinates":[74.58285600000001,28.102008],"type":"Point"}
}