{
  "type": "Feature",
  "properties": {
    "iso:country":"IN",
    "ks:ks_name":"Kannumuthal",
    "ks:ks_pop":399,
    "ks:ks_type":"VILLAGE",
    "name:eng_x_preferred":[
        "Kannumuthal"
    ],
    "wof:name":"Kannumuthal",
    "wof:placetype":"locality",
    "wof:population":399
},
  "geometry": {"coordinates":[78.28122399999999,11.836103],"type":"Point"}
}