{
  "type": "Feature",
  "properties": {
    "iso:country":"IN",
    "ks:ks_alt_nam":"KRISHNA GADADE MALA",
    "ks:ks_name":"Krishna Gadade Mala",
    "ks:ks_pop":176,
    "ks:ks_type":"HABITATION",
    "ks:ks_uagg_main":0,
    "name:eng_x_preferred":[
        "Krishna Gadade Mala"
    ],
    "wof:name":"Krishna Gadade Mala",
    "wof:placetype":"neighbourhood",
    "wof:population":176
},
  "geometry": {"coordinates":[75.07769500000001,17.055435],"type":"Point"}
}