{
  "type": "Feature",
  "properties": {
    "gn:admin1_code":"16.0",
    "gn:admin2_code":"514.0",
    "gn:asciiname":"Shipor",
    "gn:country_code":"IN",
    "gn:dem":573,
    "gn:feature_class":"P",
    "gn:feature_code":"PPL",
    "gn:name":"Shipor",
    "gn:population":0,
    "gn:timezone":"Asia/Kolkata",
    "iso:country":"IN",
    "wof:name":"Shipor",
    "wof:placetype":"locality"
},
  "geometry": {"coordinates":[75.86044,20.25912000000001],"type":"Point"}
}