{
  "type": "Feature",
  "properties": {
    "gn:admin1_code":"16",
    "gn:admin2_code":"499.0",
    "gn:asciiname":"Melsangawe",
    "gn:country_code":"IN",
    "gn:dem":219,
    "gn:feature_class":"P",
    "gn:feature_code":"PPL",
    "gn:name":"Mels\u0101ngawe",
    "gn:population":0,
    "gn:timezone":"Asia/Kolkata",
    "iso:country":"IN",
    "ks:ks_name":"Mel Sangave",
    "ks:ks_pop":1275,
    "ks:ks_type":"VILLAGE",
    "ks:ks_uagg_main":0,
    "name:eng_x_preferred":[
        "Mel Sangave"
    ],
    "wof:name":"Mel Sangave",
    "wof:placetype":"neighbourhood",
    "wof:population":1275
},
  "geometry": {"coordinates":[76.03066,21.096927],"type":"Point"}
}