{
  "type": "Feature",
  "properties": {
    "iso:country":"IN",
    "ks:ks_name":"Erukuti",
    "ks:ks_pop":129,
    "ks:ks_type":"VILLAGE",
    "name:eng_x_preferred":[
        "Erukuti"
    ],
    "wof:name":"Erukuti",
    "wof:placetype":"locality",
    "wof:population":129
},
  "geometry": {"coordinates":[83.569844,19.148362],"type":"Point"}
}