{
  "type": "Feature",
  "properties": {
    "iso:country":"IN",
    "ks:ks_name":"Dihwa Tukkur",
    "ks:ks_pop":26,
    "ks:ks_type":"HABITATION",
    "ks:ks_uagg_main":0,
    "name:eng_x_preferred":[
        "Dihwa Tukkur"
    ],
    "wof:name":"Dihwa Tukkur",
    "wof:placetype":"neighbourhood",
    "wof:population":26
},
  "geometry": {"coordinates":[80.960437,27.191968],"type":"Point"}
}