{
  "type": "Feature",
  "properties": {
    "iso:country":"IN",
    "ks:ks_name":"Akaya",
    "ks:ks_pop":1304,
    "ks:ks_type":"HABITATION",
    "name:eng_x_preferred":[
        "Akaya"
    ],
    "wof:name":"Akaya",
    "wof:placetype":"locality",
    "wof:population":1304
},
  "geometry": {"coordinates":[76.070351,22.474327],"type":"Point"}
}