{
  "type": "Feature",
  "properties": {
    "iso:country":"IN",
    "ks:ks_alt_nam":"Devi purwa",
    "ks:ks_name":"Devi Purwa",
    "ks:ks_pop":64,
    "ks:ks_type":"HABITATION",
    "name:eng_x_preferred":[
        "Devi Purwa"
    ],
    "wof:name":"Devi Purwa",
    "wof:placetype":"locality",
    "wof:population":64
},
  "geometry": {"coordinates":[80.949685,27.096327],"type":"Point"}
}