{
  "type": "Feature",
  "properties": {
    "gn:admin1_code":"12.0",
    "gn:admin2_code":"5.0",
    "gn:asciiname":"Jasot",
    "gn:country_code":"IN",
    "gn:dem":2393,
    "gn:feature_class":"P",
    "gn:feature_code":"PPL",
    "gn:name":"Jas\u014dt",
    "gn:population":0,
    "gn:timezone":"Asia/Kolkata",
    "iso:country":"IN",
    "wof:name":"Jasot",
    "wof:placetype":"locality"
},
  "geometry": {"coordinates":[74.44758,33.66754],"type":"Point"}
}