{
  "type": "Feature",
  "properties": {
    "gn:admin1_code":"38.0",
    "gn:admin2_code":"347.0",
    "gn:asciiname":"Chanodih",
    "gn:country_code":"IN",
    "gn:dem":381,
    "gn:feature_class":"P",
    "gn:feature_code":"PPL",
    "gn:name":"Ch\u0101nodih",
    "gn:population":0,
    "gn:timezone":"Asia/Kolkata",
    "iso:country":"IN",
    "wof:name":"Chanodih",
    "wof:placetype":"locality"
},
  "geometry": {"coordinates":[84.62538000000001,24.22352],"type":"Point"}
}