{
  "type": "Feature",
  "properties": {
    "iso:country":"IN",
    "ks:ks_name":"Taravagumma",
    "ks:ks_pop":425,
    "ks:ks_type":"VILLAGE",
    "name:eng_x_preferred":[
        "Taravagumma"
    ],
    "wof:name":"Taravagumma",
    "wof:placetype":"locality",
    "wof:population":425
},
  "geometry": {"coordinates":[84.21622000000001,18.944249],"type":"Point"}
}