{
  "type": "Feature",
  "properties": {
    "gn:admin1_code":"09",
    "gn:admin2_code":"492.0",
    "gn:asciiname":"Wari",
    "gn:country_code":"IN",
    "gn:dem":123,
    "gn:feature_class":"P",
    "gn:feature_code":"PPL",
    "gn:name":"W\u0101ri",
    "gn:population":0,
    "gn:timezone":"Asia/Kolkata",
    "iso:country":"IN",
    "name:ceb_x_preferred":[
        "Wari"
    ],
    "name:deu_x_preferred":[
        "Wari"
    ],
    "name:fra_x_preferred":[
        "Wari"
    ],
    "name:jpn_x_preferred":[
        "\u30ef\u30ea"
    ],
    "name:mkd_x_preferred":[
        "\u0412\u0430\u0440\u0438"
    ],
    "name:pol_x_preferred":[
        "Wari"
    ],
    "name:rus_x_preferred":[
        "\u0412\u0430\u0440\u0438"
    ],
    "name:spa_x_preferred":[
        "Wari"
    ],
    "name:swe_x_preferred":[
        "Wari"
    ],
    "name:und_x_variant":[
        "Vari",
        "W\u0101ri"
    ],
    "wof:name":"Wari",
    "wof:placetype":"neighbourhood"
},
  "geometry": {"coordinates":[73.34439,21.47627],"type":"Point"}
}