{
  "type": "Feature",
  "properties": {
    "iso:country":"IN",
    "ks:ks_alt_nam":"Hanchina kodige",
    "ks:ks_name":"Hanchina Kodige",
    "ks:ks_pop":34,
    "ks:ks_type":"HABITATION",
    "name:eng_x_preferred":[
        "Hanchina Kodige"
    ],
    "wof:name":"Hanchina Kodige",
    "wof:placetype":"locality",
    "wof:population":34
},
  "geometry": {"coordinates":[75.277002,13.345074],"type":"Point"}
}