{
  "type": "Feature",
  "properties": {
    "gn:admin1_code":"23.0",
    "gn:admin2_code":"046",
    "gn:asciiname":"Chaoke",
    "gn:country_code":"IN",
    "gn:dem":220,
    "gn:feature_class":"P",
    "gn:feature_code":"PPL",
    "gn:name":"Ch\u0101oke",
    "gn:population":0,
    "gn:timezone":"Asia/Kolkata",
    "iso:country":"IN",
    "wof:name":"Chaoke",
    "wof:placetype":"locality"
},
  "geometry": {"coordinates":[75.33620999999999,30.1847],"type":"Point"}
}