{
  "type": "Feature",
  "properties": {
    "gn:admin1_code":"16",
    "gn:admin2_code":"523.0",
    "gn:asciiname":"Pimpla",
    "gn:country_code":"IN",
    "gn:dem":483,
    "gn:feature_class":"P",
    "gn:feature_code":"PPL",
    "gn:name":"Pimpla",
    "gn:population":0,
    "gn:timezone":"Asia/Kolkata",
    "iso:country":"IN",
    "name:ceb_x_preferred":[
        "Pimpla"
    ],
    "name:nld_x_preferred":[
        "Pimpla"
    ],
    "name:swe_x_preferred":[
        "Pimpla"
    ],
    "name:war_x_preferred":[
        "Pimpla"
    ],
    "wof:name":"Pimpla",
    "wof:placetype":"locality"
},
  "geometry": {"coordinates":[75.59358,19.20296],"type":"Point"}
}