{
  "type": "Feature",
  "properties": {
    "iso:country":"IN",
    "ks:ks_name":"Nikopara",
    "ks:ks_pop":297,
    "ks:ks_type":"HABITATION",
    "name:eng_x_preferred":[
        "Nikopara"
    ],
    "wof:name":"Nikopara",
    "wof:placetype":"locality",
    "wof:population":297
},
  "geometry": {"coordinates":[81.35003399999999,18.854966],"type":"Point"}
}