{
  "type": "Feature",
  "properties": {
    "iso:country":"IN",
    "ks:ks_name":"North Tola",
    "ks:ks_pop":100,
    "ks:ks_type":"HABITATION",
    "name:eng_x_preferred":[
        "North Tola"
    ],
    "wof:name":"North Tola",
    "wof:placetype":"locality",
    "wof:population":100
},
  "geometry": {"coordinates":[83.78647599999999,23.740239],"type":"Point"}
}