{
  "type": "Feature",
  "properties": {
    "gn:admin1_code":"34.0",
    "gn:admin2_code":"222.0",
    "gn:asciiname":"Parora",
    "gn:country_code":"IN",
    "gn:dem":44,
    "gn:feature_class":"P",
    "gn:feature_code":"PPL",
    "gn:name":"Parora",
    "gn:population":0,
    "gn:timezone":"Asia/Kolkata",
    "iso:country":"IN",
    "name:vie_x_preferred":[
        "Parora"
    ],
    "wof:name":"Parora",
    "wof:placetype":"neighbourhood"
},
  "geometry": {"coordinates":[86.36994,25.39965],"type":"Point"}
}