{
  "type": "Feature",
  "properties": {
    "iso:country":"IN",
    "ks:ks_name":"Lambanithanda 1",
    "ks:ks_pop":100,
    "ks:ks_type":"HABITATION",
    "name:eng_x_preferred":[
        "Lambanithanda 1"
    ],
    "wof:name":"Lambanithanda 1",
    "wof:placetype":"locality",
    "wof:population":100
},
  "geometry": {"coordinates":[77.123931,12.914884],"type":"Point"}
}