{
  "type": "Feature",
  "properties": {
    "iso:country":"IN",
    "ks:ks_name":"Kattaramanpatti",
    "ks:ks_pop":1039,
    "ks:ks_type":"VILLAGE",
    "ks:ks_uagg_main":0,
    "name:eng_x_preferred":[
        "Kattaramanpatti"
    ],
    "wof:name":"Kattaramanpatti",
    "wof:placetype":"neighbourhood",
    "wof:population":1039
},
  "geometry": {"coordinates":[77.929081,9.187904],"type":"Point"}
}