{
  "type": "Feature",
  "properties": {
    "iso:country":"IN",
    "ks:ks_alt_nam":"HARIJAN TOAL",
    "ks:ks_name":"Harijan Toal",
    "ks:ks_pop":478,
    "ks:ks_type":"HABITATION",
    "name:eng_x_preferred":[
        "Harijan Toal"
    ],
    "wof:name":"Harijan Toal",
    "wof:placetype":"locality",
    "wof:population":478
},
  "geometry": {"coordinates":[84.96401899999999,26.443],"type":"Point"}
}