{
  "type": "Feature",
  "properties": {
    "gn:admin1_code":"35",
    "gn:admin2_code":"423.0",
    "gn:asciiname":"Khisloni",
    "gn:country_code":"IN",
    "gn:dem":329,
    "gn:feature_class":"P",
    "gn:feature_code":"PPL",
    "gn:name":"Khisloni",
    "gn:population":0,
    "gn:timezone":"Asia/Kolkata",
    "iso:country":"IN",
    "wof:name":"Khisloni",
    "wof:placetype":"locality"
},
  "geometry": {"coordinates":[78.24651999999998,24.93702],"type":"Point"}
}