{
  "type": "Feature",
  "properties": {
    "gn:admin1_code":"36",
    "gn:admin2_code":"191.0",
    "gn:asciiname":"Arharia Khanumrai",
    "gn:country_code":"IN",
    "gn:dem":84,
    "gn:feature_class":"P",
    "gn:feature_code":"PPL",
    "gn:name":"Arharia Kh\u0101numr\u0101i",
    "gn:population":0,
    "gn:timezone":"Asia/Kolkata",
    "iso:country":"IN",
    "wof:name":"Arharia Khanumrai",
    "wof:placetype":"locality"
},
  "geometry": {"coordinates":[83.18323000000002,26.24022],"type":"Point"}
}