{
  "type": "Feature",
  "properties": {
    "iso:country":"IN",
    "ks:ks_name":"Dhol",
    "ks:ks_pop":252,
    "ks:ks_type":"HABITATION",
    "name:eng_x_preferred":[
        "Dhol"
    ],
    "wof:name":"Dhol",
    "wof:placetype":"locality",
    "wof:population":252
},
  "geometry": {"coordinates":[74.2325,14.880322],"type":"Point"}
}