{
  "type": "Feature",
  "properties": {
    "iso:country":"IN",
    "ks:ks_name":"Parsia Kalan",
    "ks:ks_pop":900,
    "ks:ks_type":"VILLAGE",
    "name:eng_x_preferred":[
        "Parsia Kalan"
    ],
    "wof:name":"Parsia Kalan",
    "wof:placetype":"locality",
    "wof:population":900
},
  "geometry": {"coordinates":[82.41826,24.707384],"type":"Point"}
}