{
  "type": "Feature",
  "properties": {
    "gn:admin1_code":"16",
    "gn:admin2_code":"507.0",
    "gn:asciiname":"Dongargaon",
    "gn:country_code":"IN",
    "gn:dem":280,
    "gn:feature_class":"P",
    "gn:feature_code":"PPL",
    "gn:name":"Dongargaon",
    "gn:population":0,
    "gn:timezone":"Asia/Kolkata",
    "iso:country":"IN",
    "name:ben_x_preferred":[
        "\u09a6\u0999\u09cd\u0997\u09be\u09b0\u0997\u09be\u0981\u0993"
    ],
    "name:bpy_x_preferred":[
        "\u09a6\u0999\u09cd\u0997\u09be\u09b0\u0997\u09be\u0981\u0993"
    ],
    "name:ceb_x_preferred":[
        "Dongargaon"
    ],
    "name:ita_x_preferred":[
        "Dongargaon"
    ],
    "name:msa_x_preferred":[
        "Dongargaon"
    ],
    "name:new_x_preferred":[
        "\u0921\u094b\u0902\u0917\u0930\u0917\u093e\u0902\u0935"
    ],
    "name:nld_x_preferred":[
        "Dongargaon"
    ],
    "name:por_x_preferred":[
        "Dongargaon"
    ],
    "name:spa_x_preferred":[
        "Dongargaon"
    ],
    "name:swe_x_preferred":[
        "Dongargaon"
    ],
    "name:tgl_x_preferred":[
        "Dongargaon"
    ],
    "name:vie_x_preferred":[
        "Dongargaon"
    ],
    "name:zho_x_preferred":[
        "\u4e1c\u683c\u963f\u5c14\u52a0\u5965\u6069"
    ],
    "wof:name":"Dongargaon",
    "wof:placetype":"locality"
},
  "geometry": {"coordinates":[80.09049,20.87728],"type":"Point"}
}