{
  "type": "Feature",
  "properties": {
    "iso:country":"IN",
    "ks:ks_alt_nam":"Sult\u0101n\u0101pur",
    "ks:ks_name":"Sultanapur",
    "ks:ks_type":"VILLAGE",
    "name:eng_x_preferred":[
        "Sultanapur"
    ],
    "name:eng_x_variant":[
        "Sult\u0101n\u0101pur"
    ],
    "wof:name":"Sultanapur",
    "wof:placetype":"neighbourhood"
},
  "geometry": {"coordinates":[82.54746799999999,25.367248],"type":"Point"}
}