{
  "type": "Feature",
  "properties": {
    "iso:country":"IN",
    "ks:ks_name":"Ganadakottige",
    "ks:ks_pop":148,
    "ks:ks_type":"HABITATION",
    "name:eng_x_preferred":[
        "Ganadakottige"
    ],
    "wof:name":"Ganadakottige",
    "wof:placetype":"locality",
    "wof:population":148
},
  "geometry": {"coordinates":[74.946331,13.307517],"type":"Point"}
}