{
  "type": "Feature",
  "properties": {
    "gn:admin1_code":"34.0",
    "gn:admin2_code":"221.0",
    "gn:asciiname":"Motipur",
    "gn:country_code":"IN",
    "gn:dem":53,
    "gn:feature_class":"P",
    "gn:feature_code":"PPL",
    "gn:name":"Mot\u012bpur",
    "gn:population":0,
    "gn:timezone":"Asia/Kolkata",
    "iso:country":"IN",
    "ks:ks_name":"Motipur",
    "ks:ks_pop":2207,
    "ks:ks_type":"VILLAGE",
    "name:eng_x_preferred":[
        "Motipur"
    ],
    "name:fra_x_preferred":[
        "Motipur"
    ],
    "name:pol_x_preferred":[
        "Motipur"
    ],
    "wof:name":"Motipur",
    "wof:placetype":"locality",
    "wof:population":2207
},
  "geometry": {"coordinates":[85.67804599999999,25.844557],"type":"Point"}
}