{
  "type": "Feature",
  "properties": {
    "gn:country":"IN",
    "gn:fcode":"PPL",
    "gn:population":12608,
    "iso:country":"IN",
    "name:ceb_x_preferred":[
        "Sirsa"
    ],
    "name:eng_x_preferred":[
        "Sirsa"
    ],
    "name:ita_x_preferred":[
        "Sirsa"
    ],
    "name:msa_x_preferred":[
        "Sirsa"
    ],
    "name:nld_x_preferred":[
        "Sirsa"
    ],
    "name:pol_x_preferred":[
        "Sirsa"
    ],
    "name:swe_x_preferred":[
        "Sirsa"
    ],
    "qs:name":"Sersa",
    "qs:name_adm0":"India",
    "qs:name_adm1":"Uttar Pradesh",
    "qs:photos_9r":0,
    "qs:photos_sr":0,
    "qs:placetype":"Town",
    "qs:pop_sr":"6",
    "wof:name":"Sersa",
    "wof:placetype":"locality",
    "wof:population":12608
},
  "geometry": {"coordinates":[82.09143,25.26177],"type":"Point"}
}