{
  "type": "Feature",
  "properties": {
    "gn:admin1_code":"36",
    "gn:admin2_code":"148.0",
    "gn:asciiname":"Nagla Gariwar",
    "gn:country_code":"IN",
    "gn:dem":156,
    "gn:feature_class":"P",
    "gn:feature_code":"PPL",
    "gn:name":"Nagla G\u0101r\u012bw\u0101r",
    "gn:population":0,
    "gn:timezone":"Asia/Kolkata",
    "iso:country":"IN",
    "wof:name":"Nagla Gariwar",
    "wof:placetype":"locality"
},
  "geometry": {"coordinates":[79.16978,27.10484000000001],"type":"Point"}
}