{
  "type": "Feature",
  "properties": {
    "iso:country":"IN",
    "ks:ks_name":"Majpara",
    "ks:ks_pop":171,
    "ks:ks_type":"HABITATION",
    "name:eng_x_preferred":[
        "Majpara"
    ],
    "wof:name":"Majpara",
    "wof:placetype":"locality",
    "wof:population":171
},
  "geometry": {"coordinates":[91.269931,25.921278],"type":"Point"}
}