{
  "type": "Feature",
  "properties": {
    "gn:admin1_code":"25.0",
    "gn:admin2_code":"633.0",
    "gn:asciiname":"Palanikavundanpalaiyam",
    "gn:country_code":"IN",
    "gn:dem":296,
    "gn:feature_class":"P",
    "gn:feature_code":"PPL",
    "gn:name":"Palanikavundanp\u0101laiyam",
    "gn:population":0,
    "gn:timezone":"Asia/Kolkata",
    "iso:country":"IN",
    "wof:name":"Palanikavundanpalaiyam",
    "wof:placetype":"locality"
},
  "geometry": {"coordinates":[77.43585,11.21349],"type":"Point"}
}