{
  "type": "Feature",
  "properties": {
    "iso:country":"IN",
    "ks:ks_name":"13 DOL-A",
    "ks:ks_pop":185,
    "ks:ks_type":"VILLAGE",
    "name:eng_x_preferred":[
        "13 DOL-A"
    ],
    "wof:name":"13 DOL-A",
    "wof:placetype":"locality",
    "wof:population":185
},
  "geometry": {"coordinates":[72.761403,28.845318],"type":"Point"}
}