{
  "type": "Feature",
  "properties": {
    "iso:country":"IN",
    "ks:ks_alt_nam":"Ramgopal tanda",
    "ks:ks_name":"Ramgopal Tanda",
    "ks:ks_pop":45,
    "ks:ks_type":"HABITATION",
    "name:eng_x_preferred":[
        "Ramgopal Tanda"
    ],
    "wof:name":"Ramgopal Tanda",
    "wof:placetype":"locality",
    "wof:population":45
},
  "geometry": {"coordinates":[77.872024,17.049272],"type":"Point"}
}