{
  "type": "Feature",
  "properties": {
    "iso:country":"IN",
    "ks:ks_name":"Rangpur",
    "ks:ks_pop":357,
    "ks:ks_type":"VILLAGE",
    "name:eng_x_preferred":[
        "Rangpur"
    ],
    "wof:name":"Rangpur",
    "wof:placetype":"locality",
    "wof:population":357
},
  "geometry": {"coordinates":[73.745796,23.762676],"type":"Point"}
}