{
  "type": "Feature",
  "properties": {
    "iso:country":"IN",
    "ks:ks_name":"Ambedkar Nagar",
    "ks:ks_pop":230,
    "ks:ks_type":"VILLAGE",
    "name:eng_x_preferred":[
        "Ambedkar Nagar"
    ],
    "name:hin_x_preferred":[
        "\u0905\u0902\u092c\u0947\u0921\u0915\u0930 \u0928\u0917\u0930"
    ],
    "wof:name":"Ambedkar Nagar",
    "wof:placetype":"locality",
    "wof:population":230
},
  "geometry": {"coordinates":[71.313367,25.343519],"type":"Point"}
}