{
  "type": "Feature",
  "properties": {
    "iso:country":"IN",
    "ks:ks_name":"Ambedkar Nagar",
    "ks:ks_pop":230,
    "ks:ks_type":"VILLAGE",
    "name:eng_x_preferred":[
        "Ambedkar Nagar"
    ],
    "wof:name":"Ambedkar Nagar",
    "wof:placetype":"locality",
    "wof:population":230
},
  "geometry": {"coordinates":[71.313367,25.343519],"type":"Point"}
}