{
  "type": "Feature",
  "properties": {
    "gn:admin1_code":"24.0",
    "gn:admin2_code":"114.0",
    "gn:asciiname":"Kapuria",
    "gn:country_code":"IN",
    "gn:dem":244,
    "gn:feature_class":"P",
    "gn:feature_code":"PPL",
    "gn:name":"Kapuria",
    "gn:population":0,
    "gn:timezone":"Asia/Kolkata",
    "iso:country":"IN",
    "wof:name":"Kapuria",
    "wof:placetype":"locality"
},
  "geometry": {"coordinates":[71.01195,26.45725],"type":"Point"}
}