{
  "type": "Feature",
  "properties": {
    "iso:country":"IN",
    "ks:ks_name":"Jaba Balarampur",
    "ks:ks_pop":403,
    "ks:ks_type":"VILLAGE",
    "name:eng_x_preferred":[
        "Jaba Balarampur"
    ],
    "wof:name":"Jaba Balarampur",
    "wof:placetype":"locality",
    "wof:population":403
},
  "geometry": {"coordinates":[87.110919,23.168735],"type":"Point"}
}