{
  "type": "Feature",
  "properties": {
    "iso:country":"IN",
    "ks:ks_name":"Moovala",
    "ks:ks_pop":120,
    "ks:ks_type":"HABITATION",
    "name:eng_x_preferred":[
        "Moovala"
    ],
    "wof:name":"Moovala",
    "wof:placetype":"locality",
    "wof:population":120
},
  "geometry": {"coordinates":[75.858216,13.045669],"type":"Point"}
}