{
  "type": "Feature",
  "properties": {
    "iso:country":"IN",
    "ks:ks_name":"Pandanitarh",
    "ks:ks_pop":231,
    "ks:ks_type":"HABITATION",
    "name:eng_x_preferred":[
        "Pandanitarh"
    ],
    "wof:name":"Pandanitarh",
    "wof:placetype":"locality",
    "wof:population":231
},
  "geometry": {"coordinates":[86.534807,23.952364],"type":"Point"}
}