{
  "type": "Feature",
  "properties": {
    "gn:admin1_code":"37",
    "gn:admin2_code":"410.0",
    "gn:asciiname":"Kaitha",
    "gn:country_code":"IN",
    "gn:dem":236,
    "gn:feature_class":"P",
    "gn:feature_code":"PPL",
    "gn:name":"Kaitha",
    "gn:population":0,
    "gn:timezone":"Asia/Kolkata",
    "iso:country":"IN",
    "wof:name":"Kaitha",
    "wof:placetype":"locality"
},
  "geometry": {"coordinates":[82.70184999999999,21.68578],"type":"Point"}
}