{
  "type": "Feature",
  "properties": {
    "gn:admin1_code":"35.0",
    "gn:admin2_code":"455.0",
    "gn:asciiname":"Kalkot",
    "gn:country_code":"IN",
    "gn:dem":601,
    "gn:feature_class":"P",
    "gn:feature_code":"PPL",
    "gn:name":"Kalkot",
    "gn:population":0,
    "gn:timezone":"Asia/Kolkata",
    "iso:country":"IN",
    "ks:ks_name":"Kalkot",
    "ks:ks_pop":700,
    "ks:ks_type":"VILLAGE",
    "name:eng_x_preferred":[
        "Kalkot"
    ],
    "name:urd_x_preferred":[
        "\u06a9\u0627\u0644\u06a9\u0648\u0679"
    ],
    "wof:name":"Kalkot",
    "wof:placetype":"locality",
    "wof:population":700
},
  "geometry": {"coordinates":[78.72739300000001,21.910721],"type":"Point"}
}