{
  "type": "Feature",
  "properties": {
    "iso:country":"IN",
    "ks:ks_name":"Alane",
    "ks:ks_pop":170,
    "ks:ks_type":"HABITATION",
    "name:eng_x_preferred":[
        "Alane"
    ],
    "wof:name":"Alane",
    "wof:placetype":"locality",
    "wof:population":170
},
  "geometry": {"coordinates":[75.312161,12.960017],"type":"Point"}
}