{
  "type": "Feature",
  "properties": {
    "iso:country":"IN",
    "ks:ks_name":"Langia Gaon",
    "ks:ks_pop":2918,
    "ks:ks_type":"VILLAGE",
    "ks:ks_uagg_main":0,
    "name:eng_x_preferred":[
        "Langia Gaon"
    ],
    "wof:name":"Langia Gaon",
    "wof:placetype":"neighbourhood",
    "wof:population":2918
},
  "geometry": {"coordinates":[92.54994499999999,26.497411],"type":"Point"}
}