{
  "type": "Feature",
  "properties": {
    "iso:country":"IN",
    "ks:ks_name":"Pasa",
    "ks:ks_pop":119,
    "ks:ks_type":"VILLAGE",
    "name:eng_x_preferred":[
        "Pasa"
    ],
    "wof:name":"Pasa",
    "wof:placetype":"locality",
    "wof:population":119
},
  "geometry": {"coordinates":[84.04749099999999,19.722466],"type":"Point"}
}