{
  "type": "Feature",
  "properties": {
    "iso:country":"IN",
    "ks:ks_name":"Munda Ka Pura",
    "ks:ks_pop":719,
    "ks:ks_type":"HABITATION",
    "name:eng_x_preferred":[
        "Munda Ka Pura"
    ],
    "wof:name":"Munda Ka Pura",
    "wof:placetype":"locality",
    "wof:population":719
},
  "geometry": {"coordinates":[77.144553,26.712158],"type":"Point"}
}