{
  "type": "Feature",
  "properties": {
    "gn:admin1_code":"36",
    "gn:admin2_code":"194.0",
    "gn:asciiname":"Madhpur",
    "gn:country_code":"IN",
    "gn:dem":94,
    "gn:feature_class":"P",
    "gn:feature_code":"PPL",
    "gn:name":"Madhpur",
    "gn:population":0,
    "gn:timezone":"Asia/Kolkata",
    "iso:country":"IN",
    "ks:ks_name":"Madhupur",
    "ks:ks_pop":890,
    "ks:ks_type":"VILLAGE",
    "name:eng_x_preferred":[
        "Madhupur"
    ],
    "name:eng_x_variant":[
        "Madhpur"
    ],
    "wof:name":"Madhupur",
    "wof:placetype":"locality",
    "wof:population":890
},
  "geometry": {"coordinates":[82.270628,25.721383],"type":"Point"}
}