{
  "type": "Feature",
  "properties": {
    "iso:country":"IN",
    "ks:ks_name":"Suddalapalem",
    "ks:ks_pop":41,
    "ks:ks_type":"VILLAGE",
    "name:eng_x_preferred":[
        "Suddalapalem"
    ],
    "wof:name":"Suddalapalem",
    "wof:placetype":"locality",
    "wof:population":41
},
  "geometry": {"coordinates":[82.541831,17.76103],"type":"Point"}
}