{
  "type": "Feature",
  "properties": {
    "iso:country":"IN",
    "ks:ks_name":"Sanwat Ka Bas",
    "ks:ks_pop":635,
    "ks:ks_type":"VILLAGE",
    "name:eng_x_preferred":[
        "Sanwat Ka Bas"
    ],
    "wof:name":"Sanwat Ka Bas",
    "wof:placetype":"locality",
    "wof:population":635
},
  "geometry": {"coordinates":[75.392951,27.170104],"type":"Point"}
}