{
  "type": "Feature",
  "properties": {
    "iso:country":"IN",
    "ks:ks_name":"Kondwadi",
    "ks:ks_pop":83,
    "ks:ks_type":"HABITATION",
    "name:eng_x_preferred":[
        "Kondwadi"
    ],
    "wof:name":"Kondwadi",
    "wof:placetype":"locality",
    "wof:population":83
},
  "geometry": {"coordinates":[73.344669,17.040963],"type":"Point"}
}