{
  "type": "Feature",
  "properties": {
    "iso:country":"IN",
    "ks:ks_name":"Ogenhalli",
    "ks:ks_pop":514,
    "ks:ks_type":"HABITATION",
    "name:eng_x_preferred":[
        "Ogenhalli"
    ],
    "wof:name":"Ogenhalli",
    "wof:placetype":"locality",
    "wof:population":514
},
  "geometry": {"coordinates":[77.50678499999999,16.311444],"type":"Point"}
}