{
  "type": "Feature",
  "properties": {
    "gn:country":"IN",
    "gn:fcode":"PPL",
    "gn:pop":12636,
    "iso:country":"IN",
    "qs:name":"Khudaganj",
    "qs:name_adm0":"India",
    "qs:name_adm1":"Uttar Pradesh",
    "qs:photos_9r":0,
    "qs:photos_sr":0,
    "qs:placetype":"Town",
    "qs:pop_sr":"6",
    "wd:wordcount":275,
    "wof:name":"Khudaganj",
    "wof:placetype":"locality",
    "wof:population":12636
},
  "geometry": {"coordinates":[79.7139,28.14694],"type":"Point"}
}