{
  "type": "Feature",
  "properties": {
    "gn:country":"IN",
    "gn:fcode":"PPL",
    "gn:population":12636,
    "iso:country":"IN",
    "name:bpy_x_preferred":[
        "\u0996\u09c1\u09a6\u09be\u0997\u099e\u09cd\u099c"
    ],
    "name:ceb_x_preferred":[
        "Khud\u0101ganj"
    ],
    "name:eng_x_preferred":[
        "Khudaganj"
    ],
    "name:ita_x_preferred":[
        "Khudaganj"
    ],
    "name:mlg_x_preferred":[
        "Khudaganj"
    ],
    "name:msa_x_preferred":[
        "Khudaganj"
    ],
    "name:nan_x_preferred":[
        "Khudaganj"
    ],
    "name:new_x_preferred":[
        "\u0916\u0941\u0926\u093e\u0917\u091e\u094d\u091c"
    ],
    "name:nld_x_preferred":[
        "Khudaganj"
    ],
    "name:pol_x_preferred":[
        "Khudaganj"
    ],
    "name:por_x_preferred":[
        "Khudaganj"
    ],
    "name:swe_x_preferred":[
        "Khud\u0101ganj"
    ],
    "name:urd_x_preferred":[
        "\u062e\u062f\u0627\u06af\u0646\u062c"
    ],
    "name:vie_x_preferred":[
        "Khudaganj"
    ],
    "name:zho_x_preferred":[
        "\u5e93\u8fbe\u7518\u6770"
    ],
    "qs:name":"Khudaganj",
    "qs:name_adm0":"India",
    "qs:name_adm1":"Uttar Pradesh",
    "qs:photos_9r":0,
    "qs:photos_sr":0,
    "qs:placetype":"Town",
    "qs:pop_sr":"6",
    "wd:wordcount":275,
    "wof:name":"Khudaganj",
    "wof:placetype":"locality",
    "wof:population":12636
},
  "geometry": {"coordinates":[79.7139,28.14694],"type":"Point"}
}