{
  "type": "Feature",
  "properties": {
    "gn:admin1_code":"3.0",
    "gn:admin2_code":"320.0",
    "gn:asciiname":"Birinchiguri",
    "gn:country_code":"IN",
    "gn:dem":114,
    "gn:feature_class":"P",
    "gn:feature_code":"PPL",
    "gn:name":"Birinchiguri",
    "gn:population":0,
    "gn:timezone":"Asia/Kolkata",
    "iso:country":"IN",
    "wof:name":"Birinchiguri",
    "wof:placetype":"locality"
},
  "geometry": {"coordinates":[90.44788,26.71653],"type":"Point"}
}