{
  "type": "Feature",
  "properties": {
    "gn:admin1_code":"2",
    "gn:admin2_code":"544.0",
    "gn:asciiname":"Osaband",
    "gn:country_code":"IN",
    "gn:dem":1000,
    "gn:feature_class":"P",
    "gn:feature_code":"PPL",
    "gn:name":"Osaband",
    "gn:population":0,
    "gn:timezone":"Asia/Kolkata",
    "iso:country":"IN",
    "wof:name":"Osaband",
    "wof:placetype":"locality"
},
  "geometry": {"coordinates":[82.79573000000001,18.38316],"type":"Point"}
}