{
  "type": "Feature",
  "properties": {
    "iso:country":"IN",
    "ks:ks_name":"Nirrabeda",
    "ks:ks_pop":248,
    "ks:ks_type":"HABITATION",
    "name:eng_x_preferred":[
        "Nirrabeda"
    ],
    "wof:name":"Nirrabeda",
    "wof:placetype":"locality",
    "wof:population":248
},
  "geometry": {"coordinates":[81.460042,19.942121],"type":"Point"}
}