{
  "type": "Feature",
  "properties": {
    "gn:admin1_code":"37.0",
    "gn:admin2_code":"402.0",
    "gn:asciiname":"Khokhso",
    "gn:country_code":"IN",
    "gn:dem":783,
    "gn:feature_class":"P",
    "gn:feature_code":"PPL",
    "gn:name":"Khokhso",
    "gn:population":0,
    "gn:timezone":"Asia/Kolkata",
    "iso:country":"IN",
    "wof:name":"Khokhso",
    "wof:placetype":"locality"
},
  "geometry": {"coordinates":[84.10553,23.006],"type":"Point"}
}