{
  "type": "Feature",
  "properties": {
    "iso:country":"IN",
    "ks:ks_name":"Chopadewadi",
    "ks:ks_pop":271,
    "ks:ks_type":"HABITATION",
    "name:eng_x_preferred":[
        "Chopadewadi"
    ],
    "wof:name":"Chopadewadi",
    "wof:placetype":"locality",
    "wof:population":271
},
  "geometry": {"coordinates":[74.126735,16.266027],"type":"Point"}
}