{
  "type": "Feature",
  "properties": {
    "iso:country":"IN",
    "ks:ks_name":"Kalaignar Nagar",
    "ks:ks_pop":116,
    "ks:ks_type":"HABITATION",
    "name:eng_x_preferred":[
        "Kalaignar Nagar"
    ],
    "wof:name":"Kalaignar Nagar",
    "wof:placetype":"locality",
    "wof:population":116
},
  "geometry": {"coordinates":[78.34226200000001,12.26672],"type":"Point"}
}