{
  "type": "Feature",
  "properties": {
    "gn:country":"IN",
    "gn:fcode":"PPL",
    "gn:population":19370,
    "iso:country":"IN",
    "name:ben_x_preferred":[
        "\u09b6\u09be\u09b9\u09be\u09aa\u09c1\u09b0"
    ],
    "name:bpy_x_preferred":[
        "\u09b6\u09be\u09b9\u09be\u09aa\u09c1\u09b0"
    ],
    "name:ceb_x_preferred":[
        "Sh\u0101h\u0101pur"
    ],
    "name:deu_x_preferred":[
        "Shahapur"
    ],
    "name:eng_x_preferred":[
        "Shahapur"
    ],
    "name:fra_x_preferred":[
        "Shahapur"
    ],
    "name:guj_x_preferred":[
        "\u0ab6\u0abe\u0ab9\u0aaa\u0ac1\u0ab0"
    ],
    "name:hin_x_preferred":[
        "\u0936\u0939\u093e\u092a\u0941\u0930"
    ],
    "name:ita_x_preferred":[
        "Shahapur"
    ],
    "name:jpn_x_preferred":[
        "\u30b7\u30e3\u30cf\u30d7\u30fc\u30eb"
    ],
    "name:kan_x_preferred":[
        "\u0cb6\u0cb9\u0cbe\u0caa\u0cc1\u0cb0\u0ccd"
    ],
    "name:kor_x_preferred":[
        "\uc0e4\ud558\ud478\ub974"
    ],
    "name:mar_x_preferred":[
        "\u0936\u0939\u093e\u092a\u0942\u0930"
    ],
    "name:msa_x_preferred":[
        "Shahapur"
    ],
    "name:nan_x_preferred":[
        "Shahapur"
    ],
    "name:nld_x_preferred":[
        "Shahapur"
    ],
    "name:por_x_preferred":[
        "Shahapur"
    ],
    "name:rus_x_preferred":[
        "\u0428\u0430\u0445\u0430\u043f\u0443\u0440"
    ],
    "name:spa_x_preferred":[
        "Shahapur"
    ],
    "name:swe_x_preferred":[
        "Sh\u0101h\u0101pur"
    ],
    "name:tam_x_preferred":[
        "\u0bb7\u0bb9\u0bbe\u0baa\u0bc1\u0bb0\u0bcd"
    ],
    "name:tel_x_preferred":[
        "\u0c37\u0c39\u0c2a\u0c42\u0c30\u0c4d"
    ],
    "name:und_x_variant":[
        "Sh\u0101hpur"
    ],
    "name:urd_x_preferred":[
        "\u0634\u0627\u06c1\u0627\u067e\u0648\u0631"
    ],
    "name:vie_x_preferred":[
        "Shahapur"
    ],
    "name:zho_x_preferred":[
        "\u65af\u54c8\u54c8\u666e\u5c14"
    ],
    "qs:name":"Shahapur",
    "qs:name_adm0":"India",
    "qs:name_adm1":"Maharashtra",
    "qs:photos_9r":0,
    "qs:photos_sr":0,
    "qs:placetype":"Town",
    "qs:pop_sr":"6",
    "wd:wordcount":709,
    "wof:name":"Shahapur",
    "wof:placetype":"locality",
    "wof:population":19370
},
  "geometry": {"coordinates":[76.22562000000001,21.2372],"type":"Point"}
}