{
  "type": "Feature",
  "properties": {
    "gn:country":"IN",
    "gn:fcode":"PPL",
    "gn:pop":19370,
    "iso:country":"IN",
    "name:unk_x_variant":[
        "Sh\u0101hpur"
    ],
    "qs:name":"Shahapur",
    "qs:name_adm0":"India",
    "qs:name_adm1":"Maharashtra",
    "qs:photos_9r":0,
    "qs:photos_sr":0,
    "qs:placetype":"Town",
    "qs:pop_sr":"6",
    "wd:wordcount":709,
    "wof:name":"Shahapur",
    "wof:placetype":"locality",
    "wof:population":19370
},
  "geometry": {"coordinates":[76.22562000000001,21.2372],"type":"Point"}
}