{
  "type": "Feature",
  "properties": {
    "gn:admin1_code":"35",
    "gn:admin2_code":"443.0",
    "gn:asciiname":"Mahoti",
    "gn:country_code":"IN",
    "gn:dem":538,
    "gn:feature_class":"P",
    "gn:feature_code":"PPL",
    "gn:name":"Mahoti",
    "gn:population":0,
    "gn:timezone":"Asia/Kolkata",
    "iso:country":"IN",
    "wof:name":"Mahoti",
    "wof:placetype":"locality"
},
  "geometry": {"coordinates":[77.366,24.21718],"type":"Point"}
}