{
  "type": "Feature",
  "properties": {
    "gn:admin1_code":"36",
    "gn:admin2_code":"154.0",
    "gn:asciiname":"Kewal Purwa",
    "gn:country_code":"IN",
    "gn:dem":124,
    "gn:feature_class":"P",
    "gn:feature_code":"PPL",
    "gn:name":"Kewal Purwa",
    "gn:population":0,
    "gn:timezone":"Asia/Kolkata",
    "iso:country":"IN",
    "wof:name":"Kewal Purwa",
    "wof:placetype":"locality"
},
  "geometry": {"coordinates":[81.19091,27.59471],"type":"Point"}
}