{
  "type": "Feature",
  "properties": {
    "gn:admin1_code":"12.0",
    "gn:admin2_code":"19.0",
    "gn:asciiname":"Purani Bhuti",
    "gn:country_code":"IN",
    "gn:dem":1358,
    "gn:feature_class":"P",
    "gn:feature_code":"PPL",
    "gn:name":"Pur\u0101n\u012b Bhut\u012b",
    "gn:population":0,
    "gn:timezone":"Asia/Kolkata",
    "iso:country":"IN",
    "wof:name":"Purani Bhuti",
    "wof:placetype":"locality"
},
  "geometry": {"coordinates":[75.14870999999999,33.12935],"type":"Point"}
}