{
  "type": "Feature",
  "properties": {
    "iso:country":"IN",
    "ks:ks_name":"Chundamala",
    "ks:ks_pop":2419,
    "ks:ks_type":"HABITATION",
    "name:eng_x_preferred":[
        "Chundamala"
    ],
    "wof:name":"Chundamala",
    "wof:placetype":"locality",
    "wof:population":2419
},
  "geometry": {"coordinates":[76.632025,9.670231],"type":"Point"}
}