{
  "type": "Feature",
  "properties": {
    "iso:country":"IN",
    "ks:ks_name":"Tieary Tola",
    "ks:ks_pop":486,
    "ks:ks_type":"HABITATION",
    "ks:ks_uagg_main":0,
    "name:eng_x_preferred":[
        "Tieary Tola"
    ],
    "wof:name":"Tieary Tola",
    "wof:placetype":"neighbourhood",
    "wof:population":486
},
  "geometry": {"coordinates":[84.32545,26.56098],"type":"Point"}
}