{
  "type": "Feature",
  "properties": {
    "gn:admin1_code":"36",
    "gn:admin2_code":"143.0",
    "gn:asciiname":"Loria",
    "gn:country_code":"IN",
    "gn:dem":179,
    "gn:feature_class":"P",
    "gn:feature_code":"PPL",
    "gn:name":"Loria",
    "gn:population":0,
    "gn:timezone":"Asia/Kolkata",
    "iso:country":"IN",
    "name:ceb_x_preferred":[
        "Loria"
    ],
    "name:deu_x_preferred":[
        "Loria"
    ],
    "name:eus_x_preferred":[
        "Loria"
    ],
    "name:fra_x_preferred":[
        "Loria"
    ],
    "name:ita_x_preferred":[
        "Loria"
    ],
    "name:swe_x_preferred":[
        "Loria"
    ],
    "wof:name":"Loria",
    "wof:placetype":"locality"
},
  "geometry": {"coordinates":[77.85857,27.60758],"type":"Point"}
}