{
  "type": "Feature",
  "properties": {
    "gn:admin1_code":"21.0",
    "gn:admin2_code":"398.0",
    "gn:asciiname":"Lakkavalasa",
    "gn:country_code":"IN",
    "gn:dem":902,
    "gn:feature_class":"P",
    "gn:feature_code":"PPL",
    "gn:name":"Lakkavalasa",
    "gn:population":0,
    "gn:timezone":"Asia/Kolkata",
    "iso:country":"IN",
    "wof:name":"Lakkavalasa",
    "wof:placetype":"neighbourhood"
},
  "geometry": {"coordinates":[82.86915,18.51544],"type":"Point"}
}