{
  "type": "Feature",
  "properties": {
    "iso:country":"IN",
    "ks:ks_alt_nam":"Miya tola",
    "ks:ks_name":"Miya Tola",
    "ks:ks_pop":282,
    "ks:ks_type":"HABITATION",
    "ks:ks_uagg_main":0,
    "name:eng_x_preferred":[
        "Miya Tola"
    ],
    "wof:name":"Miya Tola",
    "wof:placetype":"neighbourhood",
    "wof:population":282
},
  "geometry": {"coordinates":[84.2899,26.116224],"type":"Point"}
}