{
  "type": "Feature",
  "properties": {
    "gn:admin1_code":"39",
    "gn:admin2_code":"61.0",
    "gn:asciiname":"Chopra",
    "gn:country_code":"IN",
    "gn:dem":1150,
    "gn:feature_class":"P",
    "gn:feature_code":"PPL",
    "gn:name":"Chopra",
    "gn:population":0,
    "gn:timezone":"Asia/Kolkata",
    "iso:country":"IN",
    "ks:ks_name":"Chopra",
    "ks:ks_type":"VILLAGE",
    "name:eng_x_preferred":[
        "Chopra"
    ],
    "name:heb_x_preferred":[
        "\u05e6'\u05d5\u05e4\u05e8\u05d4"
    ],
    "name:hin_x_preferred":[
        "\u091a\u094b\u092a\u0921\u093c\u093e"
    ],
    "name:mar_x_preferred":[
        "\u091a\u094b\u092a\u0921\u093e"
    ],
    "name:swe_x_preferred":[
        "Jater#C"
    ],
    "wof:name":"Chopra",
    "wof:placetype":"locality"
},
  "geometry": {"coordinates":[78.886129,30.096069],"type":"Point"}
}