{
  "type": "Feature",
  "properties": {
    "gn:admin1_code":"36",
    "gn:admin2_code":"161.0",
    "gn:asciiname":"Dhauraira",
    "gn:country_code":"IN",
    "gn:dem":156,
    "gn:feature_class":"P",
    "gn:feature_code":"PPL",
    "gn:name":"Dhauraira",
    "gn:population":0,
    "gn:timezone":"Asia/Kolkata",
    "iso:country":"IN",
    "ks:ks_name":"Dhauraira",
    "ks:ks_type":"VILLAGE",
    "name:eng_x_preferred":[
        "Dhauraira"
    ],
    "wof:name":"Dhauraira",
    "wof:placetype":"locality"
},
  "geometry": {"coordinates":[78.86931199999999,26.90091],"type":"Point"}
}