{
  "type": "Feature",
  "properties": {
    "iso:country":"IN",
    "ks:ks_name":"Charlock",
    "ks:ks_pop":505,
    "ks:ks_type":"VILLAGE",
    "ks:ks_uagg_main":0,
    "name:eng_x_preferred":[
        "Charlock"
    ],
    "wof:name":"Charlock",
    "wof:placetype":"neighbourhood",
    "wof:population":505
},
  "geometry": {"coordinates":[92.792919,26.093937],"type":"Point"}
}