{
  "type": "Feature",
  "properties": {
    "iso:country":"IN",
    "ks:ks_name":"Ootapala",
    "ks:ks_pop":1446,
    "ks:ks_type":"HABITATION",
    "name:eng_x_preferred":[
        "Ootapala"
    ],
    "wof:name":"Ootapala",
    "wof:placetype":"locality",
    "wof:population":1446
},
  "geometry": {"coordinates":[75.856408,11.545616],"type":"Point"}
}