{
  "type": "Feature",
  "properties": {
    "iso:country":"IN",
    "ks:ks_name":"Meerapura",
    "ks:ks_pop":135,
    "ks:ks_type":"HABITATION",
    "name:eng_x_preferred":[
        "Meerapura"
    ],
    "wof:name":"Meerapura",
    "wof:placetype":"locality",
    "wof:population":135
},
  "geometry": {"coordinates":[71.563615,27.543161],"type":"Point"}
}