{
  "type": "Feature",
  "properties": {
    "gn:admin1_code":"35.0",
    "gn:admin2_code":"437.0",
    "gn:asciiname":"Jatashankar",
    "gn:country_code":"IN",
    "gn:dem":558,
    "gn:feature_class":"P",
    "gn:feature_code":"PPL",
    "gn:name":"Jat\u0101shankar",
    "gn:population":0,
    "gn:timezone":"Asia/Kolkata",
    "iso:country":"IN",
    "name:guj_x_preferred":[
        "\u0a9c\u0a9f\u0abe\u0ab6\u0a82\u0a95\u0ab0"
    ],
    "name:ori_x_preferred":[
        "\u0b1c\u0b1f\u0b3e\u0b36\u0b19\u0b4d\u0b15\u0b30 \u0b36\u0b48\u0b2c\u0b2a\u0b40\u0b20"
    ],
    "name:tat_x_preferred":[
        "\u0414\u0497\u0430\u0442\u0430\u0448\u0430\u043d\u043a\u0430\u0440"
    ],
    "wof:name":"Jatashankar",
    "wof:placetype":"locality"
},
  "geometry": {"coordinates":[76.37053,22.63234],"type":"Point"}
}