{
  "type": "Feature",
  "properties": {
    "gn:admin1_code":"24.0",
    "gn:admin2_code":"101",
    "gn:asciiname":"Jaimalsar",
    "gn:country_code":"IN",
    "gn:dem":181,
    "gn:feature_class":"P",
    "gn:feature_code":"PPL",
    "gn:name":"Jaimalsar",
    "gn:population":0,
    "gn:timezone":"Asia/Kolkata",
    "iso:country":"IN",
    "ks:ks_name":"Jaimalsar",
    "ks:ks_pop":4179,
    "ks:ks_type":"VILLAGE",
    "name:eng_x_preferred":[
        "Jaimalsar"
    ],
    "wof:name":"Jaimalsar",
    "wof:placetype":"locality",
    "wof:population":4179
},
  "geometry": {"coordinates":[72.98531699999999,28.120411],"type":"Point"}
}