{
  "type": "Feature",
  "properties": {
    "iso:country":"IN",
    "ks:ks_name":"Ksabyankodi",
    "ks:ks_pop":249,
    "ks:ks_type":"HABITATION",
    "name:eng_x_preferred":[
        "Ksabyankodi"
    ],
    "wof:name":"Ksabyankodi",
    "wof:placetype":"locality",
    "wof:population":249
},
  "geometry": {"coordinates":[74.75762,16.340793],"type":"Point"}
}