{
  "type": "Feature",
  "properties": {
    "iso:country":"IN",
    "ks:ks_name":"Kala Hazra",
    "ks:ks_pop":4264,
    "ks:ks_type":"VILLAGE",
    "name:eng_x_preferred":[
        "Kala Hazra"
    ],
    "wof:name":"Kala Hazra",
    "wof:placetype":"locality",
    "wof:population":4264
},
  "geometry": {"coordinates":[88.742209,22.237207],"type":"Point"}
}