{
  "type": "Feature",
  "properties": {
    "gn:admin1_code":"36.0",
    "gn:admin2_code":"136.0",
    "gn:asciiname":"Sadullahnagar",
    "gn:country_code":"IN",
    "gn:dem":199,
    "gn:feature_class":"P",
    "gn:feature_code":"PPL",
    "gn:name":"S\u0101dullahnagar",
    "gn:population":0,
    "gn:timezone":"Asia/Kolkata",
    "iso:country":"IN",
    "ks:ks_name":"Saidulla Nagar",
    "ks:ks_pop":39,
    "ks:ks_type":"VILLAGE",
    "name:eng_x_preferred":[
        "Saidulla Nagar"
    ],
    "name:eng_x_variant":[
        "Sadullahnagar"
    ],
    "wof:name":"Saidulla Nagar",
    "wof:placetype":"locality",
    "wof:population":39
},
  "geometry": {"coordinates":[79.193793,28.941418],"type":"Point"}
}