{
  "type": "Feature",
  "properties": {
    "iso:country":"IN",
    "ks:ks_name":"Teleijhari",
    "ks:ks_pop":483,
    "ks:ks_type":"VILLAGE",
    "name:eng_x_preferred":[
        "Teleijhari"
    ],
    "wof:name":"Teleijhari",
    "wof:placetype":"locality",
    "wof:population":483
},
  "geometry": {"coordinates":[86.21944499999999,22.347095],"type":"Point"}
}