{
  "type": "Feature",
  "properties": {
    "iso:country":"IN",
    "ks:ks_name":"Kolgewadi",
    "ks:ks_pop":58,
    "ks:ks_type":"HABITATION",
    "name:eng_x_preferred":[
        "Kolgewadi"
    ],
    "wof:name":"Kolgewadi",
    "wof:placetype":"locality",
    "wof:population":58
},
  "geometry": {"coordinates":[73.93647,16.056654],"type":"Point"}
}