{
  "type": "Feature",
  "properties": {
    "gn:admin1_code":"18.0",
    "gn:admin2_code":"293",
    "gn:asciiname":"Dabigiri",
    "gn:country_code":"IN",
    "gn:dem":121,
    "gn:feature_class":"P",
    "gn:feature_code":"PPL",
    "gn:name":"D\u0101bigiri",
    "gn:population":0,
    "gn:timezone":"Asia/Kolkata",
    "iso:country":"IN",
    "wof:name":"Dabigiri",
    "wof:placetype":"locality"
},
  "geometry": {"coordinates":[90.22163999999999,25.76808],"type":"Point"}
}