{
  "type": "Feature",
  "properties": {
    "iso:country":"IN",
    "name:ara_x_preferred":[
        "\u0628\u0644\u062f\u0629 \u0627\u0644\u064a\u0647\u0648\u062f"
    ],
    "name:ben_bn_x_preferred":[
        "\u099c\u09bf\u0989\u099f\u09be\u0989\u09a8"
    ],
    "name:ben_in_x_preferred":[
        "\u099c\u09bf\u0989\u099f\u09be\u0989\u09a8"
    ],
    "name:eng_x_preferred":[
        "Jewtown"
    ],
    "name:guj_x_preferred":[
        "\u0a9c\u0ac7\u0a89\u0a9f\u0abe\u0a89\u0aa8"
    ],
    "name:hin_x_preferred":[
        "\u091c\u094d\u092f\u0942\u091f\u093e\u0909\u0928"
    ],
    "name:kan_x_preferred":[
        "\u0c9c\u0ccd\u0caf\u0cc2\u0c9f\u0ccc\u0ca8\u0ccd"
    ],
    "name:mal_x_preferred":[
        "\u0d1c\u0d42\u0d1f\u0d57\u0d7a"
    ],
    "name:mar_x_preferred":[
        "\u091c\u094d\u092f\u0942 \u091f\u093e\u0909\u0928"
    ],
    "name:pan_x_preferred":[
        "\u0a1c\u0a3f\u0a0a\u0a1f\u0a3e\u0a0a\u0a28"
    ],
    "name:tam_x_preferred":[
        "\u0b9c\u0bcd\u0baf\u0bc2\u0b9f\u0bcc\u0ba9\u0bcd"
    ],
    "name:tel_x_preferred":[
        "\u0c1c\u0c4d\u0c2f\u0c42\u0c1f\u0c4c\u0c28\u0c4d"
    ],
    "name:urd_x_preferred":[
        "\u062c\u06cc\u0648\u0679\u0627\u0624\u0646"
    ],
    "qs:gn_local":0,
    "qs:local_max":3383,
    "qs:local_sum":8346,
    "qs:localhoods":12,
    "qs:name":"Jewtown",
    "qs:name_adm0":"India",
    "qs:name_adm1":"Kerala",
    "qs:name_adm2":"Ernakulam",
    "qs:name_local":"Kochi",
    "qs:photo_max":476,
    "qs:photo_sum":1414,
    "qs:placetype":"Suburb",
    "qs:quad_count":22,
    "qs:woe_adm0":23424848,
    "qs:woe_adm1":2345747,
    "qs:woe_adm2":12586468,
    "qs:woe_lau":0,
    "qs:woe_local":2295423,
    "qs:woe_ver":"7.10.0",
    "wd:wordcount":76,
    "wof:lang":[
        "eng"
    ],
    "wof:name":"Jewtown",
    "wof:placetype":"neighbourhood"
},
  "geometry": {"coordinates":[76.258864,9.957254],"type":"Point"}
}