{
  "type": "Feature",
  "properties": {
    "iso:country":"IN",
    "name:eng_x_preferred":[
        "Jewtown"
    ],
    "name:unk_x_variant":[
        "Jewtown"
    ],
    "qs:gn_local":0,
    "qs:local_max":3383,
    "qs:local_sum":8346,
    "qs:localhoods":12,
    "qs:name":"Jewtown",
    "qs:name_adm0":"India",
    "qs:name_adm1":"Kerala",
    "qs:name_adm2":"Ernakulam",
    "qs:name_local":"Kochi",
    "qs:photo_max":476,
    "qs:photo_sum":1414,
    "qs:placetype":"Suburb",
    "qs:quad_count":22,
    "qs:woe_adm0":23424848,
    "qs:woe_adm1":2345747,
    "qs:woe_adm2":12586468,
    "qs:woe_lau":0,
    "qs:woe_local":2295423,
    "qs:woe_ver":"7.10.0",
    "wd:wordcount":76,
    "wof:lang":[
        "eng"
    ],
    "wof:name":"Jewtown",
    "wof:placetype":"neighbourhood"
},
  "geometry": {"coordinates":[76.258864,9.957254],"type":"Point"}
}