{
  "type": "Feature",
  "properties": {
    "iso:country":"IN",
    "ks:ks_name":"Madhupur 2",
    "ks:ks_pop":104,
    "ks:ks_type":"HABITATION",
    "name:eng_x_preferred":[
        "Madhupur 2"
    ],
    "wof:name":"Madhupur 2",
    "wof:placetype":"locality",
    "wof:population":104
},
  "geometry": {"coordinates":[94.05069,26.395608],"type":"Point"}
}