{
  "type": "Feature",
  "properties": {
    "gn:admin1_code":"13.0",
    "gn:admin2_code":"595.0",
    "gn:asciiname":"Cheranellur",
    "gn:country_code":"IN",
    "gn:dem":9,
    "gn:feature_class":"P",
    "gn:feature_code":"PPL",
    "gn:name":"Cheranell\u016br",
    "gn:population":0,
    "gn:timezone":"Asia/Kolkata",
    "iso:country":"IN",
    "ks:ks_alt_nam":"Cheranell\u016br",
    "ks:ks_alt_nam_2":"Cheranellur",
    "ks:ks_name":"Cheranallur",
    "ks:ks_pop":26316,
    "ks:ks_type":"VILLAGE",
    "name:eng_x_preferred":[
        "Cheranallur"
    ],
    "name:eng_x_variant":[
        "Cheranellur",
        "Cheranell\u016br"
    ],
    "wof:name":"Cheranallur",
    "wof:placetype":"locality",
    "wof:population":26316
},
  "geometry": {"coordinates":[76.289598,10.054275],"type":"Point"}
}