{
  "type": "Feature",
  "properties": {
    "iso:country":"IN",
    "ks:ks_name":"Lata",
    "ks:ks_pop":403,
    "ks:ks_type":"VILLAGE",
    "name:eng_x_preferred":[
        "Lata"
    ],
    "wof:name":"Lata",
    "wof:placetype":"locality",
    "wof:population":403
},
  "geometry": {"coordinates":[78.598223,30.77307],"type":"Point"}
}