{
  "type": "Feature",
  "properties": {
    "iso:country":"IN",
    "ks:ks_name":"Kalika Jari",
    "ks:ks_pop":425,
    "ks:ks_type":"HABITATION",
    "ks:ks_uagg_main":0,
    "name:eng_x_preferred":[
        "Kalika Jari"
    ],
    "wof:name":"Kalika Jari",
    "wof:placetype":"neighbourhood",
    "wof:population":425
},
  "geometry": {"coordinates":[92.06155099999999,26.178796],"type":"Point"}
}