{
  "type": "Feature",
  "properties": {
    "iso:country":"IN",
    "ks:ks_alt_nam":"KANDEKAR PANAND",
    "ks:ks_name":"Kandekar Panand",
    "ks:ks_pop":80,
    "ks:ks_type":"HABITATION",
    "name:eng_x_preferred":[
        "Kandekar Panand"
    ],
    "wof:name":"Kandekar Panand",
    "wof:placetype":"locality",
    "wof:population":80
},
  "geometry": {"coordinates":[74.267319,16.932993],"type":"Point"}
}