{
  "type": "Feature",
  "properties": {
    "iso:country":"IN",
    "ks:ks_name":"Nagalkadu",
    "ks:ks_pop":593,
    "ks:ks_type":"VILLAGE",
    "name:eng_x_preferred":[
        "Nagalkadu"
    ],
    "wof:name":"Nagalkadu",
    "wof:placetype":"locality",
    "wof:population":593
},
  "geometry": {"coordinates":[77.244528,8.953292],"type":"Point"}
}