{
  "type": "Feature",
  "properties": {
    "gn:admin1_code":"03",
    "gn:admin2_code":"317.0",
    "gn:asciiname":"Nilambazar",
    "gn:country_code":"IN",
    "gn:dem":24,
    "gn:feature_class":"P",
    "gn:feature_code":"PPL",
    "gn:name":"Nil\u0101mb\u0101z\u0101r",
    "gn:population":0,
    "gn:timezone":"Asia/Kolkata",
    "iso:country":"IN",
    "name:und_x_variant":[
        "Nilamsbazar",
        "Nil\u0101mb\u0101z\u0101r"
    ],
    "wof:name":"Nilambazar",
    "wof:placetype":"neighbourhood"
},
  "geometry": {"coordinates":[92.34992,24.74594],"type":"Point"}
}