{
  "type": "Feature",
  "properties": {
    "iso:country":"IN",
    "ks:ks_alt_nam":"KC Mukku",
    "ks:ks_name":"Kc Mukku",
    "ks:ks_pop":508,
    "ks:ks_type":"HABITATION",
    "name:eng_x_preferred":[
        "Kc Mukku"
    ],
    "wof:name":"Kc Mukku",
    "wof:placetype":"locality",
    "wof:population":508
},
  "geometry": {"coordinates":[75.78299800000001,11.642609],"type":"Point"}
}