{
  "type": "Feature",
  "properties": {
    "iso:country":"IN",
    "ks:ks_name":"Pommayagoundanpatti",
    "ks:ks_pop":468,
    "ks:ks_type":"HABITATION",
    "name:eng_x_preferred":[
        "Pommayagoundanpatti"
    ],
    "wof:name":"Pommayagoundanpatti",
    "wof:placetype":"locality",
    "wof:population":468
},
  "geometry": {"coordinates":[78.07221800000001,10.321427],"type":"Point"}
}