{
  "type": "Feature",
  "properties": {
    "iso:country":"IN",
    "ks:ks_name":"Vankagaddamalapalle",
    "ks:ks_pop":144,
    "ks:ks_type":"HABITATION",
    "name:eng_x_preferred":[
        "Vankagaddamalapalle"
    ],
    "wof:name":"Vankagaddamalapalle",
    "wof:placetype":"locality",
    "wof:population":144
},
  "geometry": {"coordinates":[78.71201499999999,14.145812],"type":"Point"}
}