{
  "type": "Feature",
  "properties": {
    "gn:admin1_code":"36",
    "gn:admin2_code":"147.0",
    "gn:asciiname":"Daulatpur",
    "gn:country_code":"IN",
    "gn:dem":167,
    "gn:feature_class":"P",
    "gn:feature_code":"PPL",
    "gn:name":"Daulatpur",
    "gn:population":0,
    "gn:timezone":"Asia/Kolkata",
    "iso:country":"IN",
    "name:ben_x_preferred":[
        "\u09a6\u09cc\u09b2\u09a4\u09aa\u09c1\u09b0"
    ],
    "name:bpy_x_preferred":[
        "\u09a6\u09cc\u09b2\u09a4\u09aa\u09c1\u09b0"
    ],
    "name:ceb_x_preferred":[
        "Daulatpur"
    ],
    "name:fra_x_preferred":[
        "Daulatpur"
    ],
    "name:ita_x_preferred":[
        "Daulatpur"
    ],
    "name:nld_x_preferred":[
        "Daulatpur"
    ],
    "name:pol_x_preferred":[
        "Daulatpur"
    ],
    "name:swe_x_preferred":[
        "Daulatpur"
    ],
    "name:zho_x_preferred":[
        "\u8fbe\u4e4c\u62c9\u7279\u666e\u5c14"
    ],
    "wof:name":"Daulatpur",
    "wof:placetype":"locality"
},
  "geometry": {"coordinates":[78.3849,27.19101],"type":"Point"}
}