{
  "type": "Feature",
  "properties": {
    "iso:country":"IN",
    "ks:ks_name":"Purbapara",
    "ks:ks_pop":273,
    "ks:ks_type":"HABITATION",
    "name:eng_x_preferred":[
        "Purbapara"
    ],
    "wof:name":"Purbapara",
    "wof:placetype":"locality",
    "wof:population":273
},
  "geometry": {"coordinates":[91.323789,23.289513],"type":"Point"}
}