{
  "type": "Feature",
  "properties": {
    "gn:admin1_code":"36.0",
    "gn:admin2_code":"158.0",
    "gn:asciiname":"Purwa Rani Sahiba",
    "gn:country_code":"IN",
    "gn:dem":116,
    "gn:feature_class":"P",
    "gn:feature_code":"PPL",
    "gn:name":"Purwa R\u0101ni S\u0101hiba",
    "gn:population":0,
    "gn:timezone":"Asia/Kolkata",
    "iso:country":"IN",
    "wof:name":"Purwa Rani Sahiba",
    "wof:placetype":"neighbourhood"
},
  "geometry": {"coordinates":[81.33750999999999,26.40069],"type":"Point"}
}