{
  "type": "Feature",
  "properties": {
    "iso:country":"IN",
    "ks:ks_name":"Saba Khera 1",
    "ks:ks_pop":622,
    "ks:ks_type":"VILLAGE",
    "name:eng_x_preferred":[
        "Saba Khera 1"
    ],
    "wof:name":"Saba Khera 1",
    "wof:placetype":"locality",
    "wof:population":622
},
  "geometry": {"coordinates":[74.79726100000001,24.196828],"type":"Point"}
}