{
  "type": "Feature",
  "properties": {
    "gn:admin1_code":"39.0",
    "gn:admin2_code":"061",
    "gn:asciiname":"Pulinda",
    "gn:country_code":"IN",
    "gn:dem":1105,
    "gn:feature_class":"P",
    "gn:feature_code":"PPL",
    "gn:name":"Pulinda",
    "gn:population":0,
    "gn:timezone":"Asia/Kolkata",
    "iso:country":"IN",
    "ks:ks_name":"Pulinda",
    "ks:ks_pop":295,
    "ks:ks_type":"VILLAGE",
    "name:eng_x_preferred":[
        "Pulinda"
    ],
    "wof:name":"Pulinda",
    "wof:placetype":"locality",
    "wof:population":295
},
  "geometry": {"coordinates":[78.54418,29.806083],"type":"Point"}
}