{
  "type": "Feature",
  "properties": {
    "iso:country":"IN",
    "ks:ks_name":"Adampur",
    "ks:ks_pop":218,
    "ks:ks_type":"HABITATION",
    "name:eng_x_preferred":[
        "Adampur"
    ],
    "wof:name":"Adampur",
    "wof:placetype":"locality",
    "wof:population":218
},
  "geometry": {"coordinates":[83.686772,26.085125],"type":"Point"}
}