{
  "type": "Feature",
  "properties": {
    "iso:country":"IN",
    "ks:ks_name":"Undkha",
    "ks:ks_pop":1136,
    "ks:ks_type":"VILLAGE",
    "name:eng_x_preferred":[
        "Undkha"
    ],
    "wof:name":"Undkha",
    "wof:placetype":"locality",
    "wof:population":1136
},
  "geometry": {"coordinates":[71.355103,25.642747],"type":"Point"}
}