{
  "type": "Feature",
  "properties": {
    "gn:admin1_code":"35",
    "gn:admin2_code":"430.0",
    "gn:asciiname":"Jamul",
    "gn:country_code":"IN",
    "gn:dem":362,
    "gn:feature_class":"P",
    "gn:feature_code":"PPL",
    "gn:name":"Jamul",
    "gn:population":0,
    "gn:timezone":"Asia/Kolkata",
    "iso:country":"IN",
    "name:ceb_x_preferred":[
        "Jamul"
    ],
    "name:nld_x_preferred":[
        "Jamul"
    ],
    "name:swe_x_preferred":[
        "Jamul"
    ],
    "wof:name":"Jamul",
    "wof:placetype":"neighbourhood"
},
  "geometry": {"coordinates":[81.95860999999999,24.74138],"type":"Point"}
}