{
  "type": "Feature",
  "properties": {
    "iso:country":"IN",
    "ks:ks_alt_nam":"Haripur (Myana)",
    "ks:ks_name":"Haripur (myana)",
    "ks:ks_pop":226,
    "ks:ks_type":"HABITATION",
    "name:eng_x_preferred":[
        "Haripur (myana)"
    ],
    "wof:name":"Haripur (myana)",
    "wof:placetype":"locality",
    "wof:population":226
},
  "geometry": {"coordinates":[77.46158699999999,24.927638],"type":"Point"}
}