{
  "type": "Feature",
  "properties": {
    "iso:country":"IN",
    "ks:ks_name":"Umaria",
    "ks:ks_pop":686,
    "ks:ks_type":"HABITATION",
    "name:eng_x_preferred":[
        "Umaria"
    ],
    "wof:name":"Umaria",
    "wof:placetype":"locality",
    "wof:population":686
},
  "geometry": {"coordinates":[80.773743,27.807051],"type":"Point"}
}