{
  "type": "Feature",
  "properties": {
    "iso:country":"IN",
    "ks:ks_name":"Mandapalle Yanadi Colony",
    "ks:ks_pop":103,
    "ks:ks_type":"HABITATION",
    "name:eng_x_preferred":[
        "Mandapalle Yanadi Colony"
    ],
    "wof:name":"Mandapalle Yanadi Colony",
    "wof:placetype":"locality",
    "wof:population":103
},
  "geometry": {"coordinates":[78.95429799999999,14.389247],"type":"Point"}
}