{
  "type": "Feature",
  "properties": {
    "iso:country":"IN",
    "ks:ks_name":"Kovupuram",
    "ks:ks_pop":253,
    "ks:ks_type":"HABITATION",
    "name:eng_x_preferred":[
        "Kovupuram"
    ],
    "wof:name":"Kovupuram",
    "wof:placetype":"locality",
    "wof:population":253
},
  "geometry": {"coordinates":[75.699296,11.599876],"type":"Point"}
}