{
  "type": "Feature",
  "properties": {
    "iso:country":"IN",
    "ks:ks_name":"Duuuruguda",
    "ks:ks_pop":45,
    "ks:ks_type":"HABITATION",
    "name:eng_x_preferred":[
        "Duuuruguda"
    ],
    "wof:name":"Duuuruguda",
    "wof:placetype":"locality",
    "wof:population":45
},
  "geometry": {"coordinates":[83.50903,19.436995],"type":"Point"}
}