{
  "type": "Feature",
  "properties": {
    "iso:country":"IN",
    "ks:ks_name":"Surgiya",
    "ks:ks_pop":419,
    "ks:ks_type":"VILLAGE",
    "name:eng_x_preferred":[
        "Surgiya"
    ],
    "wof:name":"Surgiya",
    "wof:placetype":"locality",
    "wof:population":419
},
  "geometry": {"coordinates":[84.400689,24.263671],"type":"Point"}
}