{
  "type": "Feature",
  "properties": {
    "iso:country":"IN",
    "ks:ks_name":"Dangakurlia",
    "ks:ks_pop":122,
    "ks:ks_type":"VILLAGE",
    "name:eng_x_preferred":[
        "Dangakurlia"
    ],
    "wof:name":"Dangakurlia",
    "wof:placetype":"locality",
    "wof:population":122
},
  "geometry": {"coordinates":[87.493227,24.659808],"type":"Point"}
}