{
  "type": "Feature",
  "properties": {
    "iso:country":"IN",
    "ks:ks_name":"Bhimapara",
    "ks:ks_pop":301,
    "ks:ks_type":"HABITATION",
    "name:eng_x_preferred":[
        "Bhimapara"
    ],
    "wof:name":"Bhimapara",
    "wof:placetype":"locality",
    "wof:population":301
},
  "geometry": {"coordinates":[81.416178,18.534089],"type":"Point"}
}