{
  "type": "Feature",
  "properties": {
    "iso:country":"IN",
    "ks:ks_name":"Rajpur",
    "ks:ks_pop":3518,
    "ks:ks_type":"VILLAGE",
    "ks:ks_uagg_main":0,
    "name:eng_x_preferred":[
        "Rajpur"
    ],
    "wof:name":"Rajpur",
    "wof:placetype":"neighbourhood",
    "wof:population":3518
},
  "geometry": {"coordinates":[87.202353,21.788365],"type":"Point"}
}