{
  "type": "Feature",
  "properties": {
    "iso:country":"IN",
    "ks:ks_name":"Belianarayanpur",
    "ks:ks_pop":66,
    "ks:ks_type":"VILLAGE",
    "ks:ks_uagg_main":0,
    "name:eng_x_preferred":[
        "Belianarayanpur"
    ],
    "wof:name":"Belianarayanpur",
    "wof:placetype":"neighbourhood",
    "wof:population":66
},
  "geometry": {"coordinates":[87.314481,23.362426],"type":"Point"}
}