{
  "type": "Feature",
  "properties": {
    "iso:country":"IN",
    "ks:ks_name":"Shakhapur Tanda",
    "ks:ks_pop":306,
    "ks:ks_type":"HABITATION",
    "name:eng_x_preferred":[
        "Shakhapur Tanda"
    ],
    "wof:name":"Shakhapur Tanda",
    "wof:placetype":"locality",
    "wof:population":306
},
  "geometry": {"coordinates":[76.81500200000001,16.736014],"type":"Point"}
}