{
  "type": "Feature",
  "properties": {
    "iso:country":"IN",
    "ks:ks_name":"Deopani Chuk",
    "ks:ks_pop":335,
    "ks:ks_type":"HABITATION",
    "name:eng_x_preferred":[
        "Deopani Chuk"
    ],
    "wof:name":"Deopani Chuk",
    "wof:placetype":"locality",
    "wof:population":335
},
  "geometry": {"coordinates":[95.252379,27.109181],"type":"Point"}
}