{
  "type": "Feature",
  "properties": {
    "gn:admin1_code":"38.0",
    "gn:admin2_code":"347.0",
    "gn:asciiname":"Sonpura",
    "gn:country_code":"IN",
    "gn:dem":411,
    "gn:feature_class":"P",
    "gn:feature_code":"PPL",
    "gn:name":"Sonpur\u0101",
    "gn:population":0,
    "gn:timezone":"Asia/Kolkata",
    "iso:country":"IN",
    "name:guj_x_preferred":[
        "\u0ab8\u0acb\u0aa8\u0aaa\u0ac1\u0ab0\u0abe"
    ],
    "wof:name":"Sonpura",
    "wof:placetype":"locality"
},
  "geometry": {"coordinates":[85.15557,24.31929],"type":"Point"}
}