{
  "type": "Feature",
  "properties": {
    "gn:admin1_code":"16",
    "gn:admin2_code":"505.0",
    "gn:asciiname":"Manori",
    "gn:country_code":"IN",
    "gn:dem":256,
    "gn:feature_class":"P",
    "gn:feature_code":"PPL",
    "gn:name":"M\u0101nor\u012b",
    "gn:population":0,
    "gn:timezone":"Asia/Kolkata",
    "iso:country":"IN",
    "name:ara_x_preferred":[
        "\u0645\u0627\u0646\u0648\u0631\u064a"
    ],
    "name:ben_bn_x_preferred":[
        "\u09ae\u09be\u09a8\u09cb\u09b0\u09bf"
    ],
    "name:ben_in_x_preferred":[
        "\u09ae\u09be\u09a8\u09cb\u09b0\u09bf"
    ],
    "name:guj_x_preferred":[
        "\u0aae\u0aa8\u0acc\u0ab0\u0ac0"
    ],
    "name:hin_x_preferred":[
        "\u092e\u0928\u094b\u0930\u0940"
    ],
    "name:kan_x_preferred":[
        "\u0cae\u0ca8\u0ccb\u0cb0\u0cbf"
    ],
    "name:mal_x_preferred":[
        "\u0d2e\u0d28\u0d4b\u0d30\u0d3f"
    ],
    "name:mar_x_preferred":[
        "\u092e\u0928\u094b\u0930\u0940"
    ],
    "name:pan_x_preferred":[
        "\u0a2e\u0a28\u0a4c\u0a30\u0a40"
    ],
    "name:tam_x_preferred":[
        "\u0bae\u0ba9\u0bcb\u0bb0\u0bbf"
    ],
    "name:tel_x_preferred":[
        "\u0c2e\u0c28\u0c4b\u0c30\u0c3f"
    ],
    "name:urd_x_preferred":[
        "\u0645\u0646\u0648\u0631\u06cc"
    ],
    "wof:name":"Manori",
    "wof:placetype":"locality"
},
  "geometry": {"coordinates":[79.11389,20.70825],"type":"Point"}
}