{
  "type": "Feature",
  "properties": {
    "iso:country":"IN",
    "ks:ks_alt_nam":"pahar basti",
    "ks:ks_name":"Pahar Basti",
    "ks:ks_pop":400,
    "ks:ks_type":"HABITATION",
    "name:eng_x_preferred":[
        "Pahar Basti"
    ],
    "wof:name":"Pahar Basti",
    "wof:placetype":"locality",
    "wof:population":400
},
  "geometry": {"coordinates":[81.87259899999999,25.083314],"type":"Point"}
}