{
  "type": "Feature",
  "properties": {
    "gn:admin1_code":"23.0",
    "gn:admin2_code":"53.0",
    "gn:asciiname":"Nandgarh",
    "gn:country_code":"IN",
    "gn:dem":247,
    "gn:feature_class":"P",
    "gn:feature_code":"PPL",
    "gn:name":"Nandgarh",
    "gn:population":0,
    "gn:timezone":"Asia/Kolkata",
    "iso:country":"IN",
    "name:und_x_variant":[
        "Tam\u0101nsuw\u0101la"
    ],
    "wof:name":"Nandgarh",
    "wof:placetype":"locality"
},
  "geometry": {"coordinates":[76.08481999999999,30.22855],"type":"Point"}
}