{
  "type": "Feature",
  "properties": {
    "iso:country":"IN",
    "ks:ks_name":"Sanbhadua",
    "ks:ks_pop":248,
    "ks:ks_type":"VILLAGE",
    "name:eng_x_preferred":[
        "Sanbhadua"
    ],
    "wof:name":"Sanbhadua",
    "wof:placetype":"locality",
    "wof:population":248
},
  "geometry": {"coordinates":[87.01964,21.98721],"type":"Point"}
}