{
  "type": "Feature",
  "properties": {
    "gn:admin1_code":"19.0",
    "gn:admin2_code":"568.0",
    "gn:asciiname":"Sulebailu",
    "gn:country_code":"IN",
    "gn:dem":643,
    "gn:feature_class":"P",
    "gn:feature_code":"PPL",
    "gn:name":"Sulebailu",
    "gn:population":0,
    "gn:timezone":"Asia/Kolkata",
    "iso:country":"IN",
    "ks:ks_name":"Sulebailu",
    "ks:ks_pop":300,
    "ks:ks_type":"HABITATION",
    "name:eng_x_preferred":[
        "Sulebailu"
    ],
    "wof:name":"Sulebailu",
    "wof:placetype":"locality",
    "wof:population":300
},
  "geometry": {"coordinates":[75.231493,13.655689],"type":"Point"}
}