{
  "type": "Feature",
  "properties": {
    "iso:country":"IN",
    "ks:ks_name":"Jamodi Kala",
    "ks:ks_pop":1330,
    "ks:ks_type":"HABITATION",
    "name:eng_x_preferred":[
        "Jamodi Kala"
    ],
    "wof:name":"Jamodi Kala",
    "wof:placetype":"locality",
    "wof:population":1330
},
  "geometry": {"coordinates":[81.84354500000001,24.409447],"type":"Point"}
}