{
  "type": "Feature",
  "properties": {
    "iso:country":"IN",
    "ks:ks_name":"Naghatpur",
    "ks:ks_pop":1779,
    "ks:ks_type":"VILLAGE",
    "name:eng_x_preferred":[
        "Naghatpur"
    ],
    "wof:name":"Naghatpur",
    "wof:placetype":"locality",
    "wof:population":1779
},
  "geometry": {"coordinates":[79.25754000000001,26.535378],"type":"Point"}
}