{
  "type": "Feature",
  "properties": {
    "gn:admin1_code":"36.0",
    "gn:admin2_code":"157.0",
    "gn:asciiname":"Benipur",
    "gn:country_code":"IN",
    "gn:dem":129,
    "gn:feature_class":"P",
    "gn:feature_code":"PPL",
    "gn:name":"Benipur",
    "gn:population":0,
    "gn:timezone":"Asia/Kolkata",
    "iso:country":"IN",
    "name:urd_x_preferred":[
        "\u0628\u06cc\u0646\u06cc \u067e\u0648\u0631"
    ],
    "wof:name":"Benipur",
    "wof:placetype":"locality"
},
  "geometry": {"coordinates":[80.96693,27.07643],"type":"Point"}
}