{
  "type": "Feature",
  "properties": {
    "gn:admin1_code":"40.0",
    "gn:admin2_code":"533.0",
    "gn:asciiname":"Pakal",
    "gn:country_code":"IN",
    "gn:dem":550,
    "gn:feature_class":"P",
    "gn:feature_code":"PPL",
    "gn:name":"Pak\u0101l",
    "gn:population":0,
    "gn:timezone":"Asia/Kolkata",
    "iso:country":"IN",
    "ks:ks_name":"Pakhal",
    "ks:ks_pop":807,
    "ks:ks_type":"VILLAGE",
    "name:eng_x_preferred":[
        "Pakhal"
    ],
    "name:eng_x_variant":[
        "Pakal"
    ],
    "wof:name":"Pakhal",
    "wof:placetype":"locality",
    "wof:population":807
},
  "geometry": {"coordinates":[78.49979,18.516755],"type":"Point"}
}