{
  "type": "Feature",
  "properties": {
    "iso:country":"IN",
    "ks:ks_name":"Shettarapalya",
    "ks:ks_pop":70,
    "ks:ks_type":"HABITATION",
    "name:eng_x_preferred":[
        "Shettarapalya"
    ],
    "wof:name":"Shettarapalya",
    "wof:placetype":"locality",
    "wof:population":70
},
  "geometry": {"coordinates":[77.231897,13.351419],"type":"Point"}
}