{
  "type": "Feature",
  "properties": {
    "gn:admin1_code":"35.0",
    "gn:admin2_code":"429.0",
    "gn:asciiname":"Hirapur",
    "gn:country_code":"IN",
    "gn:dem":354,
    "gn:feature_class":"P",
    "gn:feature_code":"PPL",
    "gn:name":"H\u012br\u0101pur",
    "gn:population":0,
    "gn:timezone":"Asia/Kolkata",
    "iso:country":"IN",
    "ks:ks_alt_nam":"H\u012br\u0101pur",
    "ks:ks_name":"Hirapur",
    "ks:ks_pop":265,
    "ks:ks_type":"VILLAGE",
    "name:eng_x_preferred":[
        "Hirapur"
    ],
    "name:eng_x_variant":[
        "H\u012br\u0101pur"
    ],
    "name:fra_x_preferred":[
        "Hirapur"
    ],
    "wof:name":"Hirapur",
    "wof:placetype":"locality",
    "wof:population":265
},
  "geometry": {"coordinates":[80.705027,25.026881],"type":"Point"}
}