{
  "type": "Feature",
  "properties": {
    "iso:country":"IN",
    "ks:ks_name":"Cheennareddiyur",
    "ks:ks_pop":215,
    "ks:ks_type":"HABITATION",
    "name:eng_x_preferred":[
        "Cheennareddiyur"
    ],
    "wof:name":"Cheennareddiyur",
    "wof:placetype":"locality",
    "wof:population":215
},
  "geometry": {"coordinates":[79.06625699999999,12.984431],"type":"Point"}
}