{
  "type": "Feature",
  "properties": {
    "iso:country":"IN",
    "ks:ks_name":"Defence Island",
    "ks:ks_type":"VILLAGE",
    "name:eng_x_preferred":[
        "Defence Island"
    ],
    "wof:name":"Defence Island",
    "wof:placetype":"locality"
},
  "geometry": {"coordinates":[92.60087300000001,11.953949],"type":"Point"}
}