{
  "type": "Feature",
  "properties": {
    "gn:admin1_code":"24.0",
    "gn:admin2_code":"119.0",
    "gn:asciiname":"Kheri",
    "gn:country_code":"IN",
    "gn:dem":362,
    "gn:feature_class":"P",
    "gn:feature_code":"PPL",
    "gn:name":"Kheri",
    "gn:population":0,
    "gn:timezone":"Asia/Kolkata",
    "iso:country":"IN",
    "name:bih_x_preferred":[
        "\u0916\u0940\u0930\u0940"
    ],
    "name:cat_x_preferred":[
        "Kheri"
    ],
    "name:ceb_x_preferred":[
        "Kheri"
    ],
    "name:guj_x_preferred":[
        "\u0a96\u0ac7\u0ab0\u0ac0"
    ],
    "name:hin_x_preferred":[
        "\u0916\u0940\u0930\u0940"
    ],
    "name:ita_x_preferred":[
        "Kheri"
    ],
    "name:mlg_x_preferred":[
        "Kheri"
    ],
    "name:msa_x_preferred":[
        "Kheri"
    ],
    "name:new_x_preferred":[
        "\u0916\u0947\u0930\u0940"
    ],
    "name:nld_x_preferred":[
        "Lakhimpur Kheri"
    ],
    "name:pol_x_preferred":[
        "Kheri"
    ],
    "name:san_x_preferred":[
        "\u0916\u0940\u0930\u0940"
    ],
    "name:swe_x_preferred":[
        "Kheri"
    ],
    "name:urd_x_preferred":[
        "\u06a9\u06be\u06cc\u0631\u06cc"
    ],
    "name:vie_x_preferred":[
        "Kheri"
    ],
    "wof:name":"Kheri",
    "wof:placetype":"locality"
},
  "geometry": {"coordinates":[75.04092,25.91813],"type":"Point"}
}