{
  "type": "Feature",
  "properties": {
    "gn:admin1_code":"36",
    "gn:admin2_code":"172.0",
    "gn:asciiname":"Talibour",
    "gn:country_code":"IN",
    "gn:dem":120,
    "gn:feature_class":"P",
    "gn:feature_code":"PPL",
    "gn:name":"T\u0101libour",
    "gn:population":0,
    "gn:timezone":"Asia/Kolkata",
    "iso:country":"IN",
    "ks:ks_name":"Talibpur",
    "ks:ks_pop":472,
    "ks:ks_type":"VILLAGE",
    "ks:ks_uagg_main":0,
    "name:eng_x_preferred":[
        "Talibpur"
    ],
    "wof:name":"Talibpur",
    "wof:placetype":"neighbourhood",
    "wof:population":472
},
  "geometry": {"coordinates":[80.913004,26.03111],"type":"Point"}
}