{
  "type": "Feature",
  "properties": {
    "iso:country":"IN",
    "ks:ks_name":"Dolipur",
    "ks:ks_pop":198,
    "ks:ks_type":"HABITATION",
    "name:eng_x_preferred":[
        "Dolipur"
    ],
    "wof:name":"Dolipur",
    "wof:placetype":"locality",
    "wof:population":198
},
  "geometry": {"coordinates":[80.93705199999999,25.725186],"type":"Point"}
}