{
  "type": "Feature",
  "properties": {
    "iso:country":"IN",
    "ks:ks_alt_nam":"MUSHAHAR TOLA",
    "ks:ks_name":"Mushahar Tola",
    "ks:ks_pop":477,
    "ks:ks_type":"HABITATION",
    "name:eng_x_preferred":[
        "Mushahar Tola"
    ],
    "wof:name":"Mushahar Tola",
    "wof:placetype":"locality",
    "wof:population":477
},
  "geometry": {"coordinates":[85.91458,26.26966],"type":"Point"}
}