{
  "type": "Feature",
  "properties": {
    "iso:country":"IN",
    "ks:ks_name":"Joykrishnapur",
    "ks:ks_pop":3326,
    "ks:ks_type":"VILLAGE",
    "ks:ks_uagg_main":0,
    "name:eng_x_preferred":[
        "Joykrishnapur"
    ],
    "wof:name":"Joykrishnapur",
    "wof:placetype":"neighbourhood",
    "wof:population":3326
},
  "geometry": {"coordinates":[87.80484,24.185],"type":"Point"}
}