{
  "type": "Feature",
  "properties": {
    "gn:admin1_code":"34",
    "gn:admin2_code":"203.0",
    "gn:asciiname":"Mujra",
    "gn:country_code":"IN",
    "gn:dem":100,
    "gn:feature_class":"P",
    "gn:feature_code":"PPL",
    "gn:name":"Mujra",
    "gn:population":0,
    "gn:timezone":"Asia/Kolkata",
    "iso:country":"IN",
    "name:mal_x_preferred":[
        "\u0d2e\u0d41\u0d1c\u0d4d\u0d31"
    ],
    "wof:name":"Mujra",
    "wof:placetype":"locality"
},
  "geometry": {"coordinates":[84.34987,27.16418],"type":"Point"}
}