{
  "type": "Feature",
  "properties": {
    "gn:admin1_code":"16",
    "gn:asciiname":"Navalyal",
    "gn:cc2":"IN",
    "gn:country_code":"IN",
    "gn:dem":561,
    "gn:feature_class":"P",
    "gn:feature_code":"PPL",
    "gn:name":"Navalyal",
    "gn:population":0,
    "gn:timezone":"Asia/Kolkata",
    "iso:country":"IN",
    "name:und_x_variant":[
        "Kidgedi",
        "Navalyal"
    ],
    "wof:name":"Navalyal",
    "wof:placetype":"locality"
},
  "geometry": {"coordinates":[74.90000000000001,16.75],"type":"Point"}
}