{
  "type": "Feature",
  "properties": {
    "gn:admin1_code":"36.0",
    "gn:admin2_code":"177.0",
    "gn:asciiname":"Chandramau Bairam",
    "gn:country_code":"IN",
    "gn:dem":113,
    "gn:feature_class":"P",
    "gn:feature_code":"PPL",
    "gn:name":"Chandr\u0101mau Bairam",
    "gn:population":0,
    "gn:timezone":"Asia/Kolkata",
    "iso:country":"IN",
    "ks:ks_alt_nam":"Chandr\u0101mau Bairam",
    "ks:ks_name":"Chandramau Bairam",
    "ks:ks_pop":1959,
    "ks:ks_type":"VILLAGE",
    "ks:ks_uagg_main":0,
    "name:eng_x_preferred":[
        "Chandramau Bairam"
    ],
    "name:eng_x_variant":[
        "Chandr\u0101mau Bairam"
    ],
    "wof:name":"Chandramau Bairam",
    "wof:placetype":"neighbourhood",
    "wof:population":1959
},
  "geometry": {"coordinates":[81.679695,26.654356],"type":"Point"}
}