{
  "type": "Feature",
  "properties": {
    "iso:country":"IN",
    "ks:ks_name":"North East Para",
    "ks:ks_pop":683,
    "ks:ks_type":"HABITATION",
    "name:eng_x_preferred":[
        "North East Para"
    ],
    "wof:name":"North East Para",
    "wof:placetype":"locality",
    "wof:population":683
},
  "geometry": {"coordinates":[92.21441,24.367331],"type":"Point"}
}