{
  "type": "Feature",
  "properties": {
    "iso:country":"IN",
    "ks:ks_name":"Pokheri",
    "ks:ks_pop":222,
    "ks:ks_type":"HABITATION",
    "name:eng_x_preferred":[
        "Pokheri"
    ],
    "wof:name":"Pokheri",
    "wof:placetype":"locality",
    "wof:population":222
},
  "geometry": {"coordinates":[79.909943,29.822087],"type":"Point"}
}