{
  "type": "Feature",
  "properties": {
    "gn:admin1_code":"34.0",
    "gn:admin2_code":"229.0",
    "gn:asciiname":"Indwas",
    "gn:country_code":"IN",
    "gn:dem":53,
    "gn:feature_class":"P",
    "gn:feature_code":"PPL",
    "gn:name":"Indw\u0101s",
    "gn:population":0,
    "gn:timezone":"Asia/Kolkata",
    "iso:country":"IN",
    "ks:ks_alt_nam":"Indw\u0101s",
    "ks:ks_name":"Indwas",
    "ks:ks_pop":696,
    "ks:ks_type":"VILLAGE",
    "name:eng_x_preferred":[
        "Indwas"
    ],
    "name:eng_x_variant":[
        "Indw\u0101s"
    ],
    "wof:name":"Indwas",
    "wof:placetype":"locality",
    "wof:population":696
},
  "geometry": {"coordinates":[85.58961499999999,25.299468],"type":"Point"}
}