{
  "type": "Feature",
  "properties": {
    "iso:country":"IN",
    "ks:ks_name":"Badami",
    "ks:ks_pop":145,
    "ks:ks_type":"HABITATION",
    "name:eng_x_preferred":[
        "Badami"
    ],
    "wof:name":"Badami",
    "wof:placetype":"locality",
    "wof:population":145
},
  "geometry": {"coordinates":[81.952969,24.493949],"type":"Point"}
}