{
  "type": "Feature",
  "properties": {
    "gn:admin1_code":"36.0",
    "gn:admin2_code":"152.0",
    "gn:asciiname":"Kuria Kalan",
    "gn:country_code":"IN",
    "gn:dem":154,
    "gn:feature_class":"P",
    "gn:feature_code":"PPL",
    "gn:name":"K\u016bria Kal\u0101n",
    "gn:population":0,
    "gn:timezone":"Asia/Kolkata",
    "iso:country":"IN",
    "name:und_x_variant":[
        "K\u016bria Kal\u0101n",
        "Kal\u0101n"
    ],
    "wof:name":"Kuria Kalan",
    "wof:placetype":"locality"
},
  "geometry": {"coordinates":[79.79701,27.69095],"type":"Point"}
}