{
  "type": "Feature",
  "properties": {
    "gn:admin1_code":"34.0",
    "gn:admin2_code":"203.0",
    "gn:asciiname":"Dih Bherihari",
    "gn:country_code":"IN",
    "gn:dem":74,
    "gn:feature_class":"P",
    "gn:feature_code":"PPL",
    "gn:name":"D\u012bh Bherih\u0101ri",
    "gn:population":0,
    "gn:timezone":"Asia/Kolkata",
    "iso:country":"IN",
    "ks:ks_alt_nam":"D\u012bh Bherih\u0101ri",
    "ks:ks_name":"Dih Bherihari",
    "ks:ks_type":"VILLAGE",
    "name:eng_x_preferred":[
        "Dih Bherihari"
    ],
    "name:eng_x_variant":[
        "D\u012bh Bherih\u0101ri"
    ],
    "wof:name":"Dih Bherihari",
    "wof:placetype":"locality"
},
  "geometry": {"coordinates":[84.42666800000001,26.685907],"type":"Point"}
}