{
  "type": "Feature",
  "properties": {
    "iso:country":"IN",
    "ks:ks_name":"Kathalpara",
    "ks:ks_pop":291,
    "ks:ks_type":"HABITATION",
    "name:eng_x_preferred":[
        "Kathalpara"
    ],
    "wof:name":"Kathalpara",
    "wof:placetype":"locality",
    "wof:population":291
},
  "geometry": {"coordinates":[91.215396,25.886576],"type":"Point"}
}