{
  "type": "Feature",
  "properties": {
    "iso:country":"IN",
    "ks:ks_alt_nam":"TAd faliya",
    "ks:ks_name":"Tad Faliya",
    "ks:ks_pop":186,
    "ks:ks_type":"HABITATION",
    "name:eng_x_preferred":[
        "Tad Faliya"
    ],
    "wof:name":"Tad Faliya",
    "wof:placetype":"locality",
    "wof:population":186
},
  "geometry": {"coordinates":[73.21250000000001,20.446278],"type":"Point"}
}