{
  "type": "Feature",
  "properties": {
    "iso:country":"IN",
    "ks:ks_name":"Ghoghari",
    "ks:ks_pop":220,
    "ks:ks_type":"HABITATION",
    "name:eng_x_preferred":[
        "Ghoghari"
    ],
    "wof:name":"Ghoghari",
    "wof:placetype":"locality",
    "wof:population":220
},
  "geometry": {"coordinates":[80.8056,22.480106],"type":"Point"}
}