{
  "type": "Feature",
  "properties": {
    "gn:admin1_code":"39.0",
    "gn:admin2_code":"66.0",
    "gn:asciiname":"Kamlekh",
    "gn:country_code":"IN",
    "gn:dem":1405,
    "gn:feature_class":"P",
    "gn:feature_code":"PPL",
    "gn:name":"K\u0101mlekh",
    "gn:population":0,
    "gn:timezone":"Asia/Kolkata",
    "iso:country":"IN",
    "wof:name":"Kamlekh",
    "wof:placetype":"locality"
},
  "geometry": {"coordinates":[79.78695,29.30768],"type":"Point"}
}