{
  "type": "Feature",
  "properties": {
    "iso:country":"IN",
    "ks:ks_name":"Nagarjhar",
    "ks:ks_pop":1868,
    "ks:ks_type":"VILLAGE",
    "ks:ks_uagg_main":0,
    "name:eng_x_preferred":[
        "Nagarjhar"
    ],
    "wof:name":"Nagarjhar",
    "wof:placetype":"neighbourhood",
    "wof:population":1868
},
  "geometry": {"coordinates":[90.955798,26.437048],"type":"Point"}
}