{
  "type": "Feature",
  "properties": {
    "iso:country":"IN",
    "ks:ks_name":"Kwee Gaon",
    "ks:ks_pop":207,
    "ks:ks_type":"HABITATION",
    "name:eng_x_preferred":[
        "Kwee Gaon"
    ],
    "wof:name":"Kwee Gaon",
    "wof:placetype":"locality",
    "wof:population":207
},
  "geometry": {"coordinates":[80.28129300000001,29.506164],"type":"Point"}
}