{
  "type": "Feature",
  "properties": {
    "iso:country":"IN",
    "ks:ks_name":"Kujarpam",
    "ks:ks_pop":387,
    "ks:ks_type":"HABITATION",
    "name:eng_x_preferred":[
        "Kujarpam"
    ],
    "wof:name":"Kujarpam",
    "wof:placetype":"locality",
    "wof:population":387
},
  "geometry": {"coordinates":[91.701672,26.629053],"type":"Point"}
}