{
  "type": "Feature",
  "properties": {
    "iso:country":"IN",
    "ks:ks_name":"Dandi",
    "ks:ks_pop":535,
    "ks:ks_type":"HABITATION",
    "name:eng_x_preferred":[
        "Dandi"
    ],
    "wof:name":"Dandi",
    "wof:placetype":"locality",
    "wof:population":535
},
  "geometry": {"coordinates":[81.585384,25.279358],"type":"Point"}
}