{
  "type": "Feature",
  "properties": {
    "iso:country":"IN",
    "ks:ks_alt_nam":"harijan Tola",
    "ks:ks_name":"Harijan Tola",
    "ks:ks_pop":161,
    "ks:ks_type":"HABITATION",
    "name:eng_x_preferred":[
        "Harijan Tola"
    ],
    "wof:name":"Harijan Tola",
    "wof:placetype":"locality",
    "wof:population":161
},
  "geometry": {"coordinates":[86.805716,24.802573],"type":"Point"}
}