{
  "type": "Feature",
  "properties": {
    "iso:country":"IN",
    "ks:ks_alt_nam":"SC Colony",
    "ks:ks_name":"Sc Colony",
    "ks:ks_pop":634,
    "ks:ks_type":"HABITATION",
    "ks:ks_uagg_main":0,
    "name:eng_x_preferred":[
        "Sc Colony"
    ],
    "wof:name":"Sc Colony",
    "wof:placetype":"neighbourhood",
    "wof:population":634
},
  "geometry": {"coordinates":[76.78083100000001,9.204778],"type":"Point"}
}