{
  "type": "Feature",
  "properties": {
    "iso:country":"IN",
    "ks:ks_name":"Patti Dhusar",
    "ks:ks_pop":82,
    "ks:ks_type":"VILLAGE",
    "ks:ks_uagg_main":0,
    "name:eng_x_preferred":[
        "Patti Dhusar"
    ],
    "wof:name":"Patti Dhusar",
    "wof:placetype":"neighbourhood",
    "wof:population":82
},
  "geometry": {"coordinates":[83.674166,26.172275],"type":"Point"}
}