{
  "type": "Feature",
  "properties": {
    "iso:country":"IN",
    "ks:ks_name":"Girin Sarkar Tari",
    "ks:ks_pop":739,
    "ks:ks_type":"HABITATION",
    "name:eng_x_preferred":[
        "Girin Sarkar Tari"
    ],
    "wof:name":"Girin Sarkar Tari",
    "wof:placetype":"locality",
    "wof:population":739
},
  "geometry": {"coordinates":[89.205203,26.249718],"type":"Point"}
}