{
  "type": "Feature",
  "properties": {
    "gn:admin1_code":"12.0",
    "gn:admin2_code":"16.0",
    "gn:asciiname":"Divason",
    "gn:country_code":"IN",
    "gn:dem":1943,
    "gn:feature_class":"P",
    "gn:feature_code":"PPL",
    "gn:name":"Div\u0101son",
    "gn:population":0,
    "gn:timezone":"Asia/Kolkata",
    "iso:country":"IN",
    "wof:name":"Divason",
    "wof:placetype":"locality"
},
  "geometry": {"coordinates":[75.59958,33.00883],"type":"Point"}
}