{
  "type": "Feature",
  "properties": {
    "gn:admin1_code":"37.0",
    "gn:admin2_code":"412.0",
    "gn:asciiname":"Chorbhatti",
    "gn:country_code":"IN",
    "gn:dem":308,
    "gn:feature_class":"P",
    "gn:feature_code":"PPL",
    "gn:name":"Chorbhatti",
    "gn:population":0,
    "gn:timezone":"Asia/Kolkata",
    "iso:country":"IN",
    "wof:name":"Chorbhatti",
    "wof:placetype":"locality"
},
  "geometry": {"coordinates":[81.64790000000001,20.83928],"type":"Point"}
}