{
  "type": "Feature",
  "properties": {
    "iso:country":"IN",
    "ks:ks_name":"Kumharpader",
    "ks:ks_pop":80,
    "ks:ks_type":"HABITATION",
    "name:eng_x_preferred":[
        "Kumharpader"
    ],
    "wof:name":"Kumharpader",
    "wof:placetype":"locality",
    "wof:population":80
},
  "geometry": {"coordinates":[81.016626,17.834142],"type":"Point"}
}