{
  "type": "Feature",
  "properties": {
    "gn:admin1_code":"25",
    "gn:admin2_code":"604.0",
    "gn:asciiname":"Pandur",
    "gn:country_code":"IN",
    "gn:dem":19,
    "gn:feature_class":"P",
    "gn:feature_code":"PPL",
    "gn:name":"P\u0101nd\u016br",
    "gn:population":0,
    "gn:timezone":"Asia/Kolkata",
    "iso:country":"IN",
    "name:ceb_x_preferred":[
        "Pandur"
    ],
    "name:deu_x_preferred":[
        "Pandur"
    ],
    "name:fra_x_preferred":[
        "Pandur"
    ],
    "name:hrv_x_preferred":[
        "Pandur"
    ],
    "name:pol_x_preferred":[
        "Pandur"
    ],
    "name:slv_x_preferred":[
        "Pandur"
    ],
    "name:swe_x_preferred":[
        "Pandur"
    ],
    "wof:name":"Pandur",
    "wof:placetype":"locality"
},
  "geometry": {"coordinates":[80.03546,12.53599],"type":"Point"}
}