{
  "type": "Feature",
  "properties": {
    "iso:country":"IN",
    "ks:ks_name":"Marwatiya",
    "ks:ks_pop":0,
    "ks:ks_type":"VILLAGE",
    "name:eng_x_preferred":[
        "Marwatiya"
    ],
    "wof:name":"Marwatiya",
    "wof:placetype":"locality",
    "wof:population":0
},
  "geometry": {"coordinates":[84.128603,25.609982],"type":"Point"}
}