{
  "type": "Feature",
  "properties": {
    "gn:admin1_code":"11.0",
    "gn:admin2_code":"33.0",
    "gn:asciiname":"Bijhalta",
    "gn:country_code":"IN",
    "gn:dem":1317,
    "gn:feature_class":"P",
    "gn:feature_code":"PPL",
    "gn:name":"Bijh\u0101lta",
    "gn:population":0,
    "gn:timezone":"Asia/Kolkata",
    "iso:country":"IN",
    "wof:name":"Bijhalta",
    "wof:placetype":"locality"
},
  "geometry": {"coordinates":[77.37671999999998,31.03411],"type":"Point"}
}