{
  "type": "Feature",
  "properties": {
    "gn:admin1_code":"35",
    "gn:admin2_code":"431.0",
    "gn:asciiname":"Rohania",
    "gn:country_code":"IN",
    "gn:dem":454,
    "gn:feature_class":"P",
    "gn:feature_code":"PPL",
    "gn:name":"Rohania",
    "gn:population":0,
    "gn:timezone":"Asia/Kolkata",
    "iso:country":"IN",
    "wof:name":"Rohania",
    "wof:placetype":"locality"
},
  "geometry": {"coordinates":[81.00574,23.50786],"type":"Point"}
}