{
  "type": "Feature",
  "properties": {
    "gn:admin1_code":"35",
    "gn:admin2_code":"431.0",
    "gn:asciiname":"Rohania",
    "gn:country_code":"IN",
    "gn:dem":454,
    "gn:feature_class":"P",
    "gn:feature_code":"PPL",
    "gn:name":"Rohania",
    "gn:population":0,
    "gn:timezone":"Asia/Kolkata",
    "iso:country":"IN",
    "ks:ks_name":"Rohaniya",
    "ks:ks_pop":1283,
    "ks:ks_type":"VILLAGE",
    "name:eng_x_preferred":[
        "Rohaniya"
    ],
    "name:eng_x_variant":[
        "Rohania"
    ],
    "wof:name":"Rohaniya",
    "wof:placetype":"locality",
    "wof:population":1283
},
  "geometry": {"coordinates":[81.01449100000001,23.518447],"type":"Point"}
}