{
  "type": "Feature",
  "properties": {
    "iso:country":"IN",
    "ks:ks_name":"Chhotagholjor",
    "ks:ks_pop":170,
    "ks:ks_type":"VILLAGE",
    "name:eng_x_preferred":[
        "Chhotagholjor"
    ],
    "wof:name":"Chhotagholjor",
    "wof:placetype":"locality",
    "wof:population":170
},
  "geometry": {"coordinates":[87.11782100000001,23.949188],"type":"Point"}
}