{
  "type": "Feature",
  "properties": {
    "iso:country":"IN",
    "ks:ks_name":"Kothagudem",
    "ks:ks_pop":118,
    "ks:ks_type":"HABITATION",
    "name:eng_x_preferred":[
        "Kothagudem"
    ],
    "wof:name":"Kothagudem",
    "wof:placetype":"locality",
    "wof:population":118
},
  "geometry": {"coordinates":[80.383995,18.57348],"type":"Point"}
}