{
  "type": "Feature",
  "properties": {
    "iso:country":"IN",
    "ks:ks_alt_nam":"thamaramukku",
    "ks:ks_name":"Thamaramukku",
    "ks:ks_pop":510,
    "ks:ks_type":"HABITATION",
    "name:eng_x_preferred":[
        "Thamaramukku"
    ],
    "wof:name":"Thamaramukku",
    "wof:placetype":"locality",
    "wof:population":510
},
  "geometry": {"coordinates":[75.81577,11.628979],"type":"Point"}
}