{
  "type": "Feature",
  "properties": {
    "gn:country":"IN",
    "gn:fcode":"PPL",
    "gn:pop":22248,
    "iso:country":"IN",
    "name:ben_x_preferred":[
        "\u09ae\u09be\u09b0\u09bf\u09af\u09bc\u09be\u09b9\u09c1"
    ],
    "name:bpy_x_preferred":[
        "\u09ae\u09be\u09b0\u09bf\u09af\u09bc\u09be\u09b9\u09c1"
    ],
    "name:ceb_x_preferred":[
        "Mari\u0101h\u016b"
    ],
    "name:deu_x_preferred":[
        "Mariahu"
    ],
    "name:eng_x_preferred":[
        "Mariahu"
    ],
    "name:fra_x_preferred":[
        "Mariahu"
    ],
    "name:guj_x_preferred":[
        "\u0aae\u0ab0\u0abf\u0aaf\u0abe\u0ab9\u0ac1"
    ],
    "name:ita_x_preferred":[
        "Mariahu"
    ],
    "name:jpn_x_preferred":[
        "\u30de\u30ea\u30a2\u30d5"
    ],
    "name:kan_x_preferred":[
        "\u0cae\u0cb0\u0cbf\u0caf\u0cc1"
    ],
    "name:kor_x_preferred":[
        "\ub9c8\ub9ac\ud558\uc6b0"
    ],
    "name:mlg_x_preferred":[
        "Mariahu"
    ],
    "name:msa_x_preferred":[
        "Mariahu"
    ],
    "name:nan_x_preferred":[
        "Mariahu"
    ],
    "name:new_x_preferred":[
        "\u092e\u0930\u093f\u0906\u0939\u0941"
    ],
    "name:nld_x_preferred":[
        "Mariahu"
    ],
    "name:pol_x_preferred":[
        "Mariahu"
    ],
    "name:por_x_preferred":[
        "Mariahu"
    ],
    "name:rus_x_preferred":[
        "\u041c\u0430\u0440\u0438\u0430\u0445\u0443"
    ],
    "name:spa_x_preferred":[
        "Mariahu"
    ],
    "name:swe_x_preferred":[
        "Mari\u0101h\u016b"
    ],
    "name:tam_x_preferred":[
        "\u0bae\u0bb0\u0bbf\u0baf\u0bbe\u0bb9\u0bc1"
    ],
    "name:tel_x_preferred":[
        "\u0c2e\u0c30\u0c3f\u0c2f\u0c39\u0c41"
    ],
    "name:unk_x_variant":[
        "Mari\u0101hu"
    ],
    "name:urd_x_preferred":[
        "\u0645\u0631\u06cc\u0627\u06c1\u0648"
    ],
    "name:vie_x_preferred":[
        "Mariahu"
    ],
    "name:zho_x_preferred":[
        "\u9a6c\u91cc\u4e9a\u80e1"
    ],
    "qs:name":"Mariahu",
    "qs:name_adm0":"India",
    "qs:name_adm1":"Uttar Pradesh",
    "qs:photos_9r":0,
    "qs:photos_sr":0,
    "qs:placetype":"Town",
    "qs:pop_sr":"7",
    "wd:wordcount":446,
    "wof:name":"Mariahu",
    "wof:placetype":"locality",
    "wof:population":22248
},
  "geometry": {"coordinates":[82.60187000000001,25.60003],"type":"Point"}
}