{
  "type": "Feature",
  "properties": {
    "iso:country":"IN",
    "ks:ks_name":"Ganjauli",
    "ks:ks_pop":1351,
    "ks:ks_type":"VILLAGE",
    "ks:ks_uagg_main":0,
    "name:eng_x_preferred":[
        "Ganjauli"
    ],
    "wof:name":"Ganjauli",
    "wof:placetype":"locality",
    "wof:population":1351
},
  "geometry": {"coordinates":[80.542225,26.556651],"type":"Point"}
}