{
  "type": "Feature",
  "properties": {
    "iso:country":"IN",
    "ks:ks_alt_nam":"KHALE PURWA",
    "ks:ks_name":"Khale Purwa",
    "ks:ks_pop":74,
    "ks:ks_type":"HABITATION",
    "ks:ks_uagg_main":0,
    "name:eng_x_preferred":[
        "Khale Purwa"
    ],
    "wof:name":"Khale Purwa",
    "wof:placetype":"neighbourhood",
    "wof:population":74
},
  "geometry": {"coordinates":[81.679238,27.283227],"type":"Point"}
}