{
  "type": "Feature",
  "properties": {
    "iso:country":"IN",
    "ks:ks_name":"Sidpur",
    "ks:ks_pop":5,
    "ks:ks_type":"VILLAGE",
    "name:eng_x_preferred":[
        "Sidpur"
    ],
    "wof:name":"Sidpur",
    "wof:placetype":"locality",
    "wof:population":5
},
  "geometry": {"coordinates":[87.339127,23.949405],"type":"Point"}
}