{
  "type": "Feature",
  "properties": {
    "gn:admin1_code":"11.0",
    "gn:admin2_code":"33.0",
    "gn:asciiname":"Kupri",
    "gn:country_code":"IN",
    "gn:dem":2016,
    "gn:feature_class":"P",
    "gn:feature_code":"PPL",
    "gn:name":"Kupri",
    "gn:population":0,
    "gn:timezone":"Asia/Kolkata",
    "iso:country":"IN",
    "wof:name":"Kupri",
    "wof:placetype":"locality"
},
  "geometry": {"coordinates":[77.66814000000002,31.15752],"type":"Point"}
}