{
  "type": "Feature",
  "properties": {
    "gn:admin1_code":"12.0",
    "gn:admin2_code":"014",
    "gn:asciiname":"Khanabal",
    "gn:country_code":"IN",
    "gn:dem":1602,
    "gn:feature_class":"P",
    "gn:feature_code":"PPL",
    "gn:name":"Kh\u0101nabal",
    "gn:population":0,
    "gn:timezone":"Asia/Kolkata",
    "iso:country":"IN",
    "name:mar_x_preferred":[
        "\u0916\u0928\u093e\u092c\u0932"
    ],
    "name:und_x_variant":[
        "Kh\u0101nabal"
    ],
    "wof:name":"Khanabal",
    "wof:placetype":"neighbourhood"
},
  "geometry": {"coordinates":[75.13563000000001,33.74227],"type":"Point"}
}