{
  "type": "Feature",
  "properties": {
    "gn:admin1_code":"34",
    "gn:admin2_code":"218.0",
    "gn:asciiname":"Babhnauli",
    "gn:country_code":"IN",
    "gn:dem":70,
    "gn:feature_class":"P",
    "gn:feature_code":"PPL",
    "gn:name":"Babhnauli",
    "gn:population":0,
    "gn:timezone":"Asia/Kolkata",
    "iso:country":"IN",
    "ks:ks_name":"Babhnauli",
    "ks:ks_pop":447,
    "ks:ks_type":"VILLAGE",
    "ks:ks_uagg_main":0,
    "name:eng_x_preferred":[
        "Babhnauli"
    ],
    "wof:name":"Babhnauli",
    "wof:placetype":"locality",
    "wof:population":447
},
  "geometry": {"coordinates":[84.38652999999999,26.228167],"type":"Point"}
}