{
  "type": "Feature",
  "properties": {
    "gn:admin1_code":"19.0",
    "gn:admin2_code":"581.0",
    "gn:asciiname":"Dod-Vallabi",
    "gn:country_code":"IN",
    "gn:dem":860,
    "gn:feature_class":"P",
    "gn:feature_code":"PPL",
    "gn:name":"Dod-Vallabi",
    "gn:population":0,
    "gn:timezone":"Asia/Kolkata",
    "iso:country":"IN",
    "wof:name":"Dod-Vallabi",
    "wof:placetype":"locality"
},
  "geometry": {"coordinates":[77.99030999999999,13.1671],"type":"Point"}
}