{
  "type": "Feature",
  "properties": {
    "iso:country":"IN",
    "ks:ks_name":"Mangasandra",
    "ks:ks_type":"VILLAGE",
    "name:eng_x_preferred":[
        "Mangasandra"
    ],
    "wof:name":"Mangasandra",
    "wof:placetype":"locality"
},
  "geometry": {"coordinates":[77.785876,13.728829],"type":"Point"}
}