{
  "type": "Feature",
  "properties": {
    "iso:country":"IN",
    "ks:ks_name":"Niwari",
    "ks:ks_pop":1092,
    "ks:ks_type":"VILLAGE",
    "ks:ks_uagg_main":0,
    "name:eng_x_preferred":[
        "Niwari"
    ],
    "wof:name":"Niwari",
    "wof:placetype":"neighbourhood",
    "wof:population":1092
},
  "geometry": {"coordinates":[79.870722,27.951801],"type":"Point"}
}