{
  "type": "Feature",
  "properties": {
    "iso:country":"IN",
    "ks:ks_name":"Mahadeo Bhita",
    "ks:ks_pop":371,
    "ks:ks_type":"VILLAGE",
    "ks:ks_uagg_main":0,
    "name:eng_x_preferred":[
        "Mahadeo Bhita"
    ],
    "wof:name":"Mahadeo Bhita",
    "wof:placetype":"neighbourhood",
    "wof:population":371
},
  "geometry": {"coordinates":[87.79136099999999,25.572725],"type":"Point"}
}