{
  "type": "Feature",
  "properties": {
    "iso:country":"IN",
    "ks:ks_name":"Shivsharanwasti",
    "ks:ks_pop":70,
    "ks:ks_type":"HABITATION",
    "name:eng_x_preferred":[
        "Shivsharanwasti"
    ],
    "wof:name":"Shivsharanwasti",
    "wof:placetype":"locality",
    "wof:population":70
},
  "geometry": {"coordinates":[75.38592199999999,17.514679],"type":"Point"}
}