{
  "type": "Feature",
  "properties": {
    "iso:country":"IN",
    "ks:ks_name":"Kutiguda",
    "ks:ks_pop":0,
    "ks:ks_type":"VILLAGE",
    "name:eng_x_preferred":[
        "Kutiguda"
    ],
    "wof:name":"Kutiguda",
    "wof:placetype":"locality",
    "wof:population":0
},
  "geometry": {"coordinates":[83.754774,19.686475],"type":"Point"}
}