{
  "type": "Feature",
  "properties": {
    "gn:admin1_code":"2.0",
    "gn:admin2_code":"553.0",
    "gn:asciiname":"Sathalavandlapalle",
    "gn:country_code":"IN",
    "gn:dem":685,
    "gn:feature_class":"P",
    "gn:feature_code":"PPL",
    "gn:name":"Sathalav\u0101ndlapalle",
    "gn:population":0,
    "gn:timezone":"Asia/Kolkata",
    "iso:country":"IN",
    "ks:ks_name":"Saddalavandlapalli",
    "ks:ks_pop":125,
    "ks:ks_type":"HABITATION",
    "name:eng_x_preferred":[
        "Saddalavandlapalli"
    ],
    "name:eng_x_variant":[
        "Sathalavandlapalle"
    ],
    "wof:name":"Saddalavandlapalli",
    "wof:placetype":"locality",
    "wof:population":125
},
  "geometry": {"coordinates":[78.072791,13.924855],"type":"Point"}
}