{
  "type": "Feature",
  "properties": {
    "iso:country":"IN",
    "ks:ks_name":"Aadi Thakur",
    "ks:ks_pop":211,
    "ks:ks_type":"HABITATION",
    "ks:ks_uagg_main":0,
    "name:eng_x_preferred":[
        "Aadi Thakur"
    ],
    "wof:name":"Aadi Thakur",
    "wof:placetype":"neighbourhood",
    "wof:population":211
},
  "geometry": {"coordinates":[73.01145699999999,18.237067],"type":"Point"}
}