{
  "type": "Feature",
  "properties": {
    "iso:country":"IN",
    "ks:ks_name":"Taljha Tola.",
    "ks:ks_pop":672,
    "ks:ks_type":"HABITATION",
    "ks:ks_uagg_main":0,
    "name:eng_x_preferred":[
        "Taljha Tola."
    ],
    "wof:name":"Taljha Tola.",
    "wof:placetype":"neighbourhood",
    "wof:population":672
},
  "geometry": {"coordinates":[86.836242,25.837079],"type":"Point"}
}