{
  "type": "Feature",
  "properties": {
    "gn:admin1_code":"12.0",
    "gn:admin2_code":"12.0",
    "gn:asciiname":"Shit",
    "gn:country_code":"IN",
    "gn:dem":1608,
    "gn:feature_class":"P",
    "gn:feature_code":"PPL",
    "gn:name":"Shit",
    "gn:population":0,
    "gn:timezone":"Asia/Kolkata",
    "iso:country":"IN",
    "name:als_x_preferred":[
        "Scheisse"
    ],
    "name:ces_x_preferred":[
        "Hovno"
    ],
    "name:deu_x_preferred":[
        "Schei\u00dfe"
    ],
    "name:fra_x_preferred":[
        "Merde"
    ],
    "name:gle_x_preferred":[
        "Cac"
    ],
    "name:ita_x_preferred":[
        "Merda"
    ],
    "name:jpn_x_preferred":[
        "\u30e1\u30eb\u30c9"
    ],
    "name:kor_x_preferred":[
        "Shit"
    ],
    "name:msa_x_preferred":[
        "Shit"
    ],
    "name:nld_x_preferred":[
        "Shit"
    ],
    "name:nno_x_preferred":[
        "Drit"
    ],
    "name:por_x_preferred":[
        "Merda"
    ],
    "name:rus_x_preferred":[
        "\u0414\u0435\u0440\u044c\u043c\u043e"
    ],
    "name:scn_x_preferred":[
        "Merda"
    ],
    "name:spa_x_preferred":[
        "Mierda"
    ],
    "name:zho_x_preferred":[
        "Shit"
    ],
    "wof:name":"Shit",
    "wof:placetype":"locality"
},
  "geometry": {"coordinates":[74.96963000000002,33.83454],"type":"Point"}
}