{
  "type": "Feature",
  "properties": {
    "gn:admin1_code":"25.0",
    "gn:admin2_code":"602",
    "gn:asciiname":"Amudur",
    "gn:country_code":"IN",
    "gn:dem":35,
    "gn:feature_class":"P",
    "gn:feature_code":"PPL",
    "gn:name":"Amud\u016br",
    "gn:population":0,
    "gn:timezone":"Asia/Kolkata",
    "iso:country":"IN",
    "wof:name":"Amudur",
    "wof:placetype":"neighbourhood"
},
  "geometry": {"coordinates":[80.01148999999999,13.17103],"type":"Point"}
}