{
  "type": "Feature",
  "properties": {
    "iso:country":"IN",
    "ks:ks_name":"Ganeshpur",
    "ks:ks_pop":744,
    "ks:ks_type":"VILLAGE",
    "ks:ks_uagg_main":0,
    "name:eng_x_preferred":[
        "Ganeshpur"
    ],
    "wof:name":"Ganeshpur",
    "wof:placetype":"locality",
    "wof:population":744
},
  "geometry": {"coordinates":[73.296528,23.481056],"type":"Point"}
}