{
  "type": "Feature",
  "properties": {
    "iso:country":"IN",
    "ks:ks_name":"Bhatipada",
    "ks:ks_pop":168,
    "ks:ks_type":"HABITATION",
    "name:eng_x_preferred":[
        "Bhatipada"
    ],
    "wof:name":"Bhatipada",
    "wof:placetype":"locality",
    "wof:population":168
},
  "geometry": {"coordinates":[82.96093399999999,19.777321],"type":"Point"}
}