{
  "type": "Feature",
  "properties": {
    "gn:admin1_code":"24.0",
    "gn:admin2_code":"99.0",
    "gn:asciiname":"Godhuwali Dhani",
    "gn:country_code":"IN",
    "gn:dem":178,
    "gn:feature_class":"P",
    "gn:feature_code":"PPL",
    "gn:name":"Godh\u016bw\u0101li Dh\u0101ni",
    "gn:population":0,
    "gn:timezone":"Asia/Kolkata",
    "iso:country":"IN",
    "wof:name":"Godhuwali Dhani",
    "wof:placetype":"neighbourhood"
},
  "geometry": {"coordinates":[73.97084,29.7268],"type":"Point"}
}