{
  "type": "Feature",
  "properties": {
    "gn:admin1_code":"12.0",
    "gn:admin2_code":"5.0",
    "gn:asciiname":"Sahabwala",
    "gn:country_code":"IN",
    "gn:dem":2665,
    "gn:feature_class":"P",
    "gn:feature_code":"PPL",
    "gn:name":"S\u0101habw\u0101la",
    "gn:population":0,
    "gn:timezone":"Asia/Kolkata",
    "iso:country":"IN",
    "wof:name":"Sahabwala",
    "wof:placetype":"locality"
},
  "geometry": {"coordinates":[74.47929000000001,33.50565],"type":"Point"}
}