{
  "type": "Feature",
  "properties": {
    "iso:country":"IN",
    "ks:ks_name":"Saharjori",
    "ks:ks_pop":289,
    "ks:ks_type":"VILLAGE",
    "name:eng_x_preferred":[
        "Saharjori"
    ],
    "wof:name":"Saharjori",
    "wof:placetype":"locality",
    "wof:population":289
},
  "geometry": {"coordinates":[87.52192100000001,24.996075],"type":"Point"}
}