{
  "type": "Feature",
  "properties": {
    "iso:country":"IN",
    "ks:ks_name":"Undwela",
    "ks:ks_pop":695,
    "ks:ks_type":"HABITATION",
    "name:eng_x_preferred":[
        "Undwela"
    ],
    "wof:name":"Undwela",
    "wof:placetype":"locality",
    "wof:population":695
},
  "geometry": {"coordinates":[74.500714,23.749517],"type":"Point"}
}