{
  "type": "Feature",
  "properties": {
    "gn:admin1_code":"35.0",
    "gn:admin2_code":"427",
    "gn:asciiname":"Mala",
    "gn:country_code":"IN",
    "gn:dem":435,
    "gn:feature_class":"P",
    "gn:feature_code":"PPL",
    "gn:name":"M\u0101la",
    "gn:population":0,
    "gn:timezone":"Asia/Kolkata",
    "iso:country":"IN",
    "name:ara_x_preferred":[
        "\u0645\u0627\u0644\u0627"
    ],
    "name:ben_bn_x_preferred":[
        "\u09ae\u09be\u09b2\u09be"
    ],
    "name:ben_in_x_preferred":[
        "\u09ae\u09be\u09b2\u09be"
    ],
    "name:bos_x_preferred":[
        "Mala"
    ],
    "name:ceb_x_preferred":[
        "Mala"
    ],
    "name:deu_x_preferred":[
        "Mala"
    ],
    "name:fra_x_preferred":[
        "Mala"
    ],
    "name:guj_x_preferred":[
        "\u0aae\u0abe\u0ab2\u0abe"
    ],
    "name:hin_x_preferred":[
        "\u092e\u093e\u0932\u093e"
    ],
    "name:hun_x_preferred":[
        "Mala"
    ],
    "name:ita_x_preferred":[
        "Mala"
    ],
    "name:kan_x_preferred":[
        "\u0cae\u0cbe\u0cb2\u0cbe"
    ],
    "name:mal_x_preferred":[
        "\u0d2e\u0d3e\u0d33"
    ],
    "name:mar_x_preferred":[
        "\u092e\u093e\u0932\u093e"
    ],
    "name:nld_x_preferred":[
        "Mala"
    ],
    "name:nor_x_preferred":[
        "Mala"
    ],
    "name:pan_x_preferred":[
        "\u0a2e\u0a3e\u0a32\u0a3e"
    ],
    "name:pol_x_preferred":[
        "Mala"
    ],
    "name:por_x_preferred":[
        "Mala"
    ],
    "name:spa_x_preferred":[
        "Mala"
    ],
    "name:srp_x_preferred":[
        "Mala"
    ],
    "name:swe_x_preferred":[
        "Mala"
    ],
    "name:tam_x_preferred":[
        "\u0bae\u0bb2\u0bbe"
    ],
    "name:tel_x_preferred":[
        "\u0c2e\u0c3e\u0c32\u0c3e"
    ],
    "name:urd_x_preferred":[
        "\u0645\u0627\u0644\u0627"
    ],
    "name:uzb_x_preferred":[
        "Male"
    ],
    "wof:name":"Mala",
    "wof:placetype":"neighbourhood"
},
  "geometry": {"coordinates":[78.32993,24.21899],"type":"Point"}
}