{
  "type": "Feature",
  "properties": {
    "iso:country":"IN",
    "ks:ks_alt_nam":"Anegundi kaval",
    "ks:ks_name":"Anegundi Kaval",
    "ks:ks_pop":276,
    "ks:ks_type":"HABITATION",
    "name:eng_x_preferred":[
        "Anegundi Kaval"
    ],
    "wof:name":"Anegundi Kaval",
    "wof:placetype":"locality",
    "wof:population":276
},
  "geometry": {"coordinates":[76.139126,12.746728],"type":"Point"}
}