{
  "type": "Feature",
  "properties": {
    "iso:country":"IN",
    "ks:ks_name":"Chhota Purwa",
    "ks:ks_pop":242,
    "ks:ks_type":"HABITATION",
    "name:eng_x_preferred":[
        "Chhota Purwa"
    ],
    "wof:name":"Chhota Purwa",
    "wof:placetype":"locality",
    "wof:population":242
},
  "geometry": {"coordinates":[83.008224,27.082118],"type":"Point"}
}