{
  "type": "Feature",
  "properties": {
    "gn:admin1_code":"2.0",
    "gn:admin2_code":"543.0",
    "gn:asciiname":"Kavitibhadra",
    "gn:country_code":"IN",
    "gn:dem":153,
    "gn:feature_class":"P",
    "gn:feature_code":"PPL",
    "gn:name":"Kavitibhadra",
    "gn:population":0,
    "gn:timezone":"Asia/Kolkata",
    "iso:country":"IN",
    "wof:name":"Kavitibhadra",
    "wof:placetype":"locality"
},
  "geometry": {"coordinates":[83.34165,18.76626],"type":"Point"}
}