{
  "type": "Feature",
  "properties": {
    "iso:country":"IN",
    "ks:ks_alt_nam":"Mand Partap pur",
    "ks:ks_name":"Mand Partap Pur",
    "ks:ks_pop":377,
    "ks:ks_type":"HABITATION",
    "name:eng_x_preferred":[
        "Mand Partap Pur"
    ],
    "wof:name":"Mand Partap Pur",
    "wof:placetype":"locality",
    "wof:population":377
},
  "geometry": {"coordinates":[75.12079300000001,31.302027],"type":"Point"}
}