{
  "type": "Feature",
  "properties": {
    "iso:country":"IN",
    "ks:ks_name":"Krishnapur",
    "ks:ks_pop":0,
    "ks:ks_type":"VILLAGE",
    "name:eng_x_preferred":[
        "Krishnapur"
    ],
    "wof:name":"Krishnapur",
    "wof:placetype":"locality",
    "wof:population":0
},
  "geometry": {"coordinates":[87.334709,23.315877],"type":"Point"}
}