{
  "type": "Feature",
  "properties": {
    "iso:country":"IN",
    "ks:ks_alt_nam":"AdIPUR",
    "ks:ks_name":"Adipur",
    "ks:ks_pop":420,
    "ks:ks_type":"HABITATION",
    "ks:ks_uagg_main":0,
    "name:eng_x_preferred":[
        "Adipur"
    ],
    "wof:name":"Adipur",
    "wof:placetype":"neighbourhood",
    "wof:population":420
},
  "geometry": {"coordinates":[85.36095299999999,26.406134],"type":"Point"}
}