{
  "type": "Feature",
  "properties": {
    "iso:country":"IN",
    "ks:ks_name":"Daljiwada",
    "ks:ks_pop":90,
    "ks:ks_type":"HABITATION",
    "name:eng_x_preferred":[
        "Daljiwada"
    ],
    "wof:name":"Daljiwada",
    "wof:placetype":"locality",
    "wof:population":90
},
  "geometry": {"coordinates":[74.332199,14.602381],"type":"Point"}
}