{
  "type": "Feature",
  "properties": {
    "gn:admin1_code":"39",
    "gn:admin2_code":"61.0",
    "gn:asciiname":"Rabta",
    "gn:country_code":"IN",
    "gn:dem":347,
    "gn:feature_class":"P",
    "gn:feature_code":"PPL",
    "gn:name":"Rabta",
    "gn:population":0,
    "gn:timezone":"Asia/Kolkata",
    "iso:country":"IN",
    "name:ara_x_preferred":[
        "\u0627\u0644\u0631\u0627\u0628\u0637\u0629"
    ],
    "name:azb_x_preferred":[
        "\u0631\u0627\u0628\u0637\u0647"
    ],
    "name:fas_x_preferred":[
        "\u0631\u0627\u0628\u0637\u0647"
    ],
    "name:fra_x_preferred":[
        "Rabta"
    ],
    "name:ita_x_preferred":[
        "Rabta"
    ],
    "name:msa_x_preferred":[
        "Rabta"
    ],
    "name:por_x_preferred":[
        "Rabta"
    ],
    "name:ron_x_preferred":[
        "Rabta"
    ],
    "name:spa_x_preferred":[
        "Rabta"
    ],
    "name:vie_x_preferred":[
        "Rabta"
    ],
    "wof:name":"Rabta",
    "wof:placetype":"locality"
},
  "geometry": {"coordinates":[78.73279000000002,29.56458],"type":"Point"}
}