{
  "type": "Feature",
  "properties": {
    "iso:country":"IN",
    "ks:ks_name":"Thundukatalai",
    "ks:ks_pop":499,
    "ks:ks_type":"HABITATION",
    "ks:ks_uagg_main":0,
    "name:eng_x_preferred":[
        "Thundukatalai"
    ],
    "wof:name":"Thundukatalai",
    "wof:placetype":"neighbourhood",
    "wof:population":499
},
  "geometry": {"coordinates":[79.698385,11.08266],"type":"Point"}
}