{
  "type": "Feature",
  "properties": {
    "iso:country":"IN",
    "ks:ks_alt_nam":"JADHAV UGARE VASTI",
    "ks:ks_name":"Jadhav Ugare Vasti",
    "ks:ks_pop":101,
    "ks:ks_type":"HABITATION",
    "name:eng_x_preferred":[
        "Jadhav Ugare Vasti"
    ],
    "wof:name":"Jadhav Ugare Vasti",
    "wof:placetype":"locality",
    "wof:population":101
},
  "geometry": {"coordinates":[74.7371,16.831112],"type":"Point"}
}