{
  "type": "Feature",
  "properties": {
    "gn:admin1_code":"39.0",
    "gn:admin2_code":"66.0",
    "gn:asciiname":"Nai",
    "gn:country_code":"IN",
    "gn:dem":1679,
    "gn:feature_class":"P",
    "gn:feature_code":"PPL",
    "gn:name":"Nai",
    "gn:population":0,
    "gn:timezone":"Asia/Kolkata",
    "iso:country":"IN",
    "name:ceb_x_preferred":[
        "Nai"
    ],
    "name:ces_x_preferred":[
        "NaI"
    ],
    "name:fra_x_preferred":[
        "Nai"
    ],
    "name:srp_x_preferred":[
        "NaI"
    ],
    "name:swe_x_preferred":[
        "Nai"
    ],
    "name:vie_x_preferred":[
        "Nai"
    ],
    "wof:name":"Nai",
    "wof:placetype":"locality"
},
  "geometry": {"coordinates":[79.73404000000002,29.39098],"type":"Point"}
}