{
  "type": "Feature",
  "properties": {
    "iso:country":"IN",
    "ks:ks_name":"Rohal",
    "ks:ks_pop":1290,
    "ks:ks_type":"HABITATION",
    "name:eng_x_preferred":[
        "Rohal"
    ],
    "wof:name":"Rohal",
    "wof:placetype":"locality",
    "wof:population":1290
},
  "geometry": {"coordinates":[74.25749999999999,23.533889],"type":"Point"}
}