{
  "type": "Feature",
  "properties": {
    "iso:country":"IN",
    "ks:ks_name":"Tureighati",
    "ks:ks_pop":770,
    "ks:ks_type":"VILLAGE",
    "name:eng_x_preferred":[
        "Tureighati"
    ],
    "wof:name":"Tureighati",
    "wof:placetype":"locality",
    "wof:population":770
},
  "geometry": {"coordinates":[82.950564,19.169823],"type":"Point"}
}