{
  "type": "Feature",
  "properties": {
    "gn:admin1_code":"35",
    "gn:admin2_code":"452.0",
    "gn:asciiname":"Ganeshganj",
    "gn:country_code":"IN",
    "gn:dem":371,
    "gn:feature_class":"P",
    "gn:feature_code":"PPL",
    "gn:name":"Ganeshganj",
    "gn:population":0,
    "gn:timezone":"Asia/Kolkata",
    "iso:country":"IN",
    "ks:ks_name":"Ganeshganj",
    "ks:ks_type":"VILLAGE",
    "name:eng_x_preferred":[
        "Ganeshganj"
    ],
    "wof:name":"Ganeshganj",
    "wof:placetype":"locality"
},
  "geometry": {"coordinates":[79.115871,23.146138],"type":"Point"}
}