{
  "type": "Feature",
  "properties": {
    "gn:admin1_code":"24.0",
    "gn:admin2_code":"128.0",
    "gn:asciiname":"Semla",
    "gn:country_code":"IN",
    "gn:dem":372,
    "gn:feature_class":"P",
    "gn:feature_code":"PPL",
    "gn:name":"Semla",
    "gn:population":0,
    "gn:timezone":"Asia/Kolkata",
    "iso:country":"IN",
    "name:bel_x_preferred":[
        "\u0421\u0435\u043c\u043b\u0430"
    ],
    "name:dan_x_preferred":[
        "Fastelavnsbolle"
    ],
    "name:deu_x_preferred":[
        "Semla"
    ],
    "name:est_x_preferred":[
        "Vastlakukkel"
    ],
    "name:fas_x_preferred":[
        "\u0633\u0645\u0644\u0627"
    ],
    "name:fin_x_preferred":[
        "Laskiaispulla"
    ],
    "name:fra_x_preferred":[
        "Semla"
    ],
    "name:ita_x_preferred":[
        "Semla"
    ],
    "name:jpn_x_preferred":[
        "\u30bb\u30e0\u30e9"
    ],
    "name:lat_x_preferred":[
        "Massula antequadragesimalis"
    ],
    "name:nld_x_preferred":[
        "Semla"
    ],
    "name:nor_x_preferred":[
        "Fastelavnsbolle"
    ],
    "name:pol_x_preferred":[
        "Semla"
    ],
    "name:spa_x_preferred":[
        "Semla"
    ],
    "name:swe_x_preferred":[
        "Semla"
    ],
    "name:tgl_x_preferred":[
        "Semla"
    ],
    "name:ukr_x_preferred":[
        "\u0421\u0435\u043c\u043b\u0430"
    ],
    "wof:name":"Semla",
    "wof:placetype":"locality"
},
  "geometry": {"coordinates":[76.87336999999999,24.55179],"type":"Point"}
}