{
  "type": "Feature",
  "properties": {
    "gn:admin1_code":"40",
    "gn:admin2_code":"535.0",
    "gn:asciiname":"Malkarjanpalli",
    "gn:country_code":"IN",
    "gn:dem":530,
    "gn:feature_class":"P",
    "gn:feature_code":"PPL",
    "gn:name":"Malk\u0101rjanpalli",
    "gn:population":0,
    "gn:timezone":"Asia/Kolkata",
    "iso:country":"IN",
    "wof:name":"Malkarjanpalli",
    "wof:placetype":"locality"
},
  "geometry": {"coordinates":[77.87618000000001,17.73301],"type":"Point"}
}