{
  "type": "Feature",
  "properties": {
    "iso:country":"IN",
    "ks:ks_name":"Navtoliya",
    "ks:ks_pop":290,
    "ks:ks_type":"HABITATION",
    "name:eng_x_preferred":[
        "Navtoliya"
    ],
    "wof:name":"Navtoliya",
    "wof:placetype":"locality",
    "wof:population":290
},
  "geometry": {"coordinates":[86.911469,25.247374],"type":"Point"}
}