{
  "type": "Feature",
  "properties": {
    "iso:country":"IN",
    "ks:ks_name":"Vidyapith",
    "ks:ks_pop":427,
    "ks:ks_type":"HABITATION",
    "name:eng_x_preferred":[
        "Vidyapith"
    ],
    "wof:name":"Vidyapith",
    "wof:placetype":"locality",
    "wof:population":427
},
  "geometry": {"coordinates":[86.206897,23.994522],"type":"Point"}
}