{
  "type": "Feature",
  "properties": {
    "gn:admin1_code":"36",
    "gn:admin2_code":"143.0",
    "gn:asciiname":"Gopi",
    "gn:country_code":"IN",
    "gn:dem":186,
    "gn:feature_class":"P",
    "gn:feature_code":"PPL",
    "gn:name":"Gopi",
    "gn:population":0,
    "gn:timezone":"Asia/Kolkata",
    "iso:country":"IN",
    "name:deu_x_preferred":[
        "Gopi"
    ],
    "name:fra_x_preferred":[
        "Gopi"
    ],
    "name:hin_x_preferred":[
        "\u0917\u094b\u092a\u0940"
    ],
    "name:ita_x_preferred":[
        "Gop\u012b"
    ],
    "name:kan_x_preferred":[
        "\u0c97\u0ccb\u0caa\u0cbf"
    ],
    "name:lit_x_preferred":[
        "Gop\u0117"
    ],
    "name:pol_x_preferred":[
        "Gopi"
    ],
    "name:por_x_preferred":[
        "Gopi"
    ],
    "name:rus_x_preferred":[
        "\u0413\u043e\u043f\u0438"
    ],
    "name:spa_x_preferred":[
        "Gopi"
    ],
    "name:swe_x_preferred":[
        "Gopi"
    ],
    "name:tam_x_preferred":[
        "\u0b95\u0bcb\u0baa\u0bbf\u0baf\u0bb0\u0bcd"
    ],
    "name:tat_x_preferred":[
        "\u0413\u043e\u043f\u0438"
    ],
    "name:ukr_x_preferred":[
        "\u0490\u043e\u043f\u0456"
    ],
    "wof:name":"Gopi",
    "wof:placetype":"locality"
},
  "geometry": {"coordinates":[78.31766999999998,27.75093],"type":"Point"}
}