{
  "type": "Feature",
  "properties": {
    "iso:country":"IN",
    "ks:ks_alt_nam":"PURE CHANDRA KALI",
    "ks:ks_name":"Pure Chandra Kali",
    "ks:ks_pop":74,
    "ks:ks_type":"HABITATION",
    "ks:ks_uagg_main":0,
    "name:eng_x_preferred":[
        "Pure Chandra Kali"
    ],
    "wof:name":"Pure Chandra Kali",
    "wof:placetype":"neighbourhood",
    "wof:population":74
},
  "geometry": {"coordinates":[82.23441800000001,26.596815],"type":"Point"}
}