{
  "type": "Feature",
  "properties": {
    "iso:country":"IN",
    "ks:ks_name":"Banke Purwa",
    "ks:ks_pop":114,
    "ks:ks_type":"HABITATION",
    "name:eng_x_preferred":[
        "Banke Purwa"
    ],
    "wof:name":"Banke Purwa",
    "wof:placetype":"locality",
    "wof:population":114
},
  "geometry": {"coordinates":[81.97222499999999,27.234994],"type":"Point"}
}