{
  "type": "Feature",
  "properties": {
    "iso:country":"IN",
    "ks:ks_name":"J.B.-17",
    "ks:ks_pop":0,
    "ks:ks_type":"VILLAGE",
    "name:eng_x_preferred":[
        "J.B.-17"
    ],
    "wof:name":"J.B.-17",
    "wof:placetype":"locality",
    "wof:population":0
},
  "geometry": {"coordinates":[84.286615,19.190818],"type":"Point"}
}