{
  "type": "Feature",
  "properties": {
    "gn:admin1_code":"36",
    "gn:admin2_code":"181.0",
    "gn:asciiname":"Nankar",
    "gn:country_code":"IN",
    "gn:dem":123,
    "gn:feature_class":"P",
    "gn:feature_code":"PPL",
    "gn:name":"N\u0101nk\u0101r",
    "gn:population":0,
    "gn:timezone":"Asia/Kolkata",
    "iso:country":"IN",
    "name:und_x_variant":[
        "N\u0101nk\u0101r",
        "Saunraiya"
    ],
    "wof:name":"Nankar",
    "wof:placetype":"locality"
},
  "geometry": {"coordinates":[81.77490999999998,27.51491],"type":"Point"}
}