{
  "type": "Feature",
  "properties": {
    "iso:country":"IN",
    "ks:ks_name":"Gobarlad",
    "ks:ks_pop":148,
    "ks:ks_type":"HABITATION",
    "name:eng_x_preferred":[
        "Gobarlad"
    ],
    "wof:name":"Gobarlad",
    "wof:placetype":"locality",
    "wof:population":148
},
  "geometry": {"coordinates":[86.304998,22.902497],"type":"Point"}
}