{
  "type": "Feature",
  "properties": {
    "iso:country":"IN",
    "ks:ks_name":"Bhatpura",
    "ks:ks_pop":242,
    "ks:ks_type":"HABITATION",
    "name:eng_x_preferred":[
        "Bhatpura"
    ],
    "wof:name":"Bhatpura",
    "wof:placetype":"locality",
    "wof:population":242
},
  "geometry": {"coordinates":[72.792028,22.62625],"type":"Point"}
}