{
  "type": "Feature",
  "properties": {
    "iso:country":"IN",
    "ks:ks_alt_nam":"HARALE VASTI",
    "ks:ks_name":"Harale Vasti",
    "ks:ks_pop":176,
    "ks:ks_type":"HABITATION",
    "name:eng_x_preferred":[
        "Harale Vasti"
    ],
    "wof:name":"Harale Vasti",
    "wof:placetype":"locality",
    "wof:population":176
},
  "geometry": {"coordinates":[75.157236,16.972114],"type":"Point"}
}