{
  "type": "Feature",
  "properties": {
    "iso:country":"IN",
    "ks:ks_name":"Matera",
    "ks:ks_pop":48,
    "ks:ks_type":"HABITATION",
    "ks:ks_uagg_main":0,
    "name:eng_x_preferred":[
        "Matera"
    ],
    "wof:name":"Matera",
    "wof:placetype":"neighbourhood",
    "wof:population":48
},
  "geometry": {"coordinates":[81.55681800000001,27.77862],"type":"Point"}
}