{
  "type": "Feature",
  "properties": {
    "gn:admin1_code":"36",
    "gn:admin2_code":"159.0",
    "gn:asciiname":"Hamirpur",
    "gn:country_code":"IN",
    "gn:dem":154,
    "gn:feature_class":"P",
    "gn:feature_code":"PPL",
    "gn:name":"Ham\u012brpur",
    "gn:population":0,
    "gn:timezone":"Asia/Kolkata",
    "iso:country":"IN",
    "ks:ks_name":"Hamirpur",
    "ks:ks_pop":435,
    "ks:ks_type":"HABITATION",
    "ks:ks_uagg_main":0,
    "name:ara_x_preferred":[
        "\u0647\u0627\u0645\u064a\u0631\u0628\u0648\u0631"
    ],
    "name:ben_bn_x_preferred":[
        "\u09b9\u09be\u09ae\u09bf\u09b0\u09aa\u09c1\u09b0"
    ],
    "name:ben_in_x_preferred":[
        "\u09b9\u09be\u09ae\u09bf\u09b0\u09aa\u09c1\u09b0"
    ],
    "name:cat_x_preferred":[
        "Hamirpur"
    ],
    "name:deu_x_preferred":[
        "Hamirpur"
    ],
    "name:eng_x_preferred":[
        "Hamirpur"
    ],
    "name:fra_x_preferred":[
        "Hamirpur"
    ],
    "name:guj_x_preferred":[
        "\u0ab9\u0aae\u0abf\u0ab0\u0aaa\u0ac1\u0ab0"
    ],
    "name:hin_x_preferred":[
        "\u0939\u092e\u0940\u0930\u092a\u0941\u0930"
    ],
    "name:ita_x_preferred":[
        "Hamirpur"
    ],
    "name:kan_x_preferred":[
        "\u0cb9\u0cae\u0cc0\u0cb0\u0ccd"
    ],
    "name:mal_x_preferred":[
        "\u0d39\u0d3e\u0d2e\u0d3f\u0d7c\u0d2a\u0d42\u0d7c"
    ],
    "name:mar_x_preferred":[
        "\u0939\u092e\u0940\u0930\u092a\u0942\u0930"
    ],
    "name:nld_x_preferred":[
        "Hamirpur"
    ],
    "name:pan_x_preferred":[
        "\u0a39\u0a2e\u0a40\u0a30\u0a2a\u0a41\u0a30"
    ],
    "name:pnb_x_preferred":[
        "\u06be\u0645\u06cc\u0631 \u067e\u0648\u0631"
    ],
    "name:pol_x_preferred":[
        "Hamirpur"
    ],
    "name:rus_x_preferred":[
        "\u0425\u0430\u043c\u0438\u0440\u043f\u0443\u0440"
    ],
    "name:swe_x_preferred":[
        "Hamirpur"
    ],
    "name:tam_x_preferred":[
        "\u0bb9\u0bae\u0bc0\u0bb0\u0bcd\u0baa\u0bc2\u0bb0\u0bcd"
    ],
    "name:tel_x_preferred":[
        "\u0c39\u0c2e\u0c40\u0c30\u0c4d"
    ],
    "name:urd_x_preferred":[
        "\u06c1\u0645\u06cc\u0631 \u067e\u0648\u0631"
    ],
    "wof:name":"Hamirpur",
    "wof:placetype":"neighbourhood",
    "wof:population":435
},
  "geometry": {"coordinates":[79.467056,27.360683],"type":"Point"}
}