{
  "type": "Feature",
  "properties": {
    "iso:country":"IN",
    "ks:ks_name":"Sarhad Chhapri",
    "ks:ks_pop":147,
    "ks:ks_type":"VILLAGE",
    "name:eng_x_preferred":[
        "Sarhad Chhapri"
    ],
    "wof:name":"Sarhad Chhapri",
    "wof:placetype":"locality",
    "wof:population":147
},
  "geometry": {"coordinates":[72.806937,24.353697],"type":"Point"}
}