{
  "type": "Feature",
  "properties": {
    "iso:country":"IN",
    "ks:ks_alt_nam":"MK Mukku",
    "ks:ks_name":"Mk Mukku",
    "ks:ks_pop":808,
    "ks:ks_type":"HABITATION",
    "name:eng_x_preferred":[
        "Mk Mukku"
    ],
    "wof:name":"Mk Mukku",
    "wof:placetype":"locality",
    "wof:population":808
},
  "geometry": {"coordinates":[75.83512399999999,11.393904],"type":"Point"}
}