{
  "type": "Feature",
  "properties": {
    "iso:country":"IN",
    "ks:ks_name":"Jobar",
    "ks:ks_pop":1659,
    "ks:ks_type":"VILLAGE",
    "name:eng_x_preferred":[
        "Jobar"
    ],
    "wof:name":"Jobar",
    "wof:placetype":"locality",
    "wof:population":1659
},
  "geometry": {"coordinates":[85.871695,23.936916],"type":"Point"}
}