{
  "type": "Feature",
  "properties": {
    "iso:country":"IN",
    "ks:ks_name":"Doddakunnala",
    "ks:ks_pop":120,
    "ks:ks_type":"HABITATION",
    "name:eng_x_preferred":[
        "Doddakunnala"
    ],
    "wof:name":"Doddakunnala",
    "wof:placetype":"locality",
    "wof:population":120
},
  "geometry": {"coordinates":[76.90112499999999,13.18947],"type":"Point"}
}