{
  "type": "Feature",
  "properties": {
    "iso:country":"IN",
    "ks:ks_name":"Podapada",
    "ks:ks_pop":172,
    "ks:ks_type":"VILLAGE",
    "name:eng_x_preferred":[
        "Podapada"
    ],
    "wof:name":"Podapada",
    "wof:placetype":"locality",
    "wof:population":172
},
  "geometry": {"coordinates":[86.911688,21.729788],"type":"Point"}
}