{
  "type": "Feature",
  "properties": {
    "iso:country":"IN",
    "ks:ks_name":"Borkathani",
    "ks:ks_pop":1043,
    "ks:ks_type":"VILLAGE",
    "name:eng_x_preferred":[
        "Borkathani"
    ],
    "wof:name":"Borkathani",
    "wof:placetype":"locality",
    "wof:population":1043
},
  "geometry": {"coordinates":[93.79417599999999,26.897688],"type":"Point"}
}