{
  "type": "Feature",
  "properties": {
    "gn:admin1_code":"37.0",
    "gn:admin2_code":"408.0",
    "gn:asciiname":"Lamra",
    "gn:country_code":"IN",
    "gn:dem":619,
    "gn:feature_class":"P",
    "gn:feature_code":"PPL",
    "gn:name":"Lamra",
    "gn:population":0,
    "gn:timezone":"Asia/Kolkata",
    "iso:country":"IN",
    "ks:ks_name":"Lamra",
    "ks:ks_type":"VILLAGE",
    "name:eng_x_preferred":[
        "Lamra"
    ],
    "wof:name":"Lamra",
    "wof:placetype":"locality"
},
  "geometry": {"coordinates":[80.743735,21.561607],"type":"Point"}
}