{
  "type": "Feature",
  "properties": {
    "gn:admin1_code":"19",
    "gn:admin2_code":"580.0",
    "gn:asciiname":"Yaragol",
    "gn:country_code":"IN",
    "gn:dem":439,
    "gn:feature_class":"P",
    "gn:feature_code":"PPL",
    "gn:name":"Yaragol",
    "gn:population":0,
    "gn:timezone":"Asia/Kolkata",
    "iso:country":"IN",
    "name:und_x_variant":[
        "Yargol"
    ],
    "wof:name":"Yaragol",
    "wof:placetype":"locality"
},
  "geometry": {"coordinates":[77.06655000000001,16.90445],"type":"Point"}
}