{
  "type": "Feature",
  "properties": {
    "iso:country":"IN",
    "ks:ks_alt_nam":"Mangali thanda",
    "ks:ks_name":"Mangali Thanda",
    "ks:ks_pop":138,
    "ks:ks_type":"HABITATION",
    "name:eng_x_preferred":[
        "Mangali Thanda"
    ],
    "wof:name":"Mangali Thanda",
    "wof:placetype":"locality",
    "wof:population":138
},
  "geometry": {"coordinates":[79.832137,17.778187],"type":"Point"}
}