{
  "type": "Feature",
  "properties": {
    "gn:admin1_code":"11",
    "gn:admin2_code":"23.0",
    "gn:asciiname":"Rangroi",
    "gn:country_code":"IN",
    "gn:dem":1803,
    "gn:feature_class":"P",
    "gn:feature_code":"PPL",
    "gn:name":"Rangroi",
    "gn:population":0,
    "gn:timezone":"Asia/Kolkata",
    "iso:country":"IN",
    "wof:name":"Rangroi",
    "wof:placetype":"locality"
},
  "geometry": {"coordinates":[76.10536999999999,32.3729],"type":"Point"}
}