{
  "type": "Feature",
  "properties": {
    "iso:country":"IN",
    "ks:ks_name":"Pedachattu",
    "ks:ks_pop":65,
    "ks:ks_type":"HABITATION",
    "name:eng_x_preferred":[
        "Pedachattu"
    ],
    "wof:name":"Pedachattu",
    "wof:placetype":"locality",
    "wof:population":65
},
  "geometry": {"coordinates":[82.80525400000001,18.186114],"type":"Point"}
}