{
  "type": "Feature",
  "properties": {
    "iso:country":"IN",
    "ks:ks_name":"Vasantnagar",
    "ks:ks_pop":190,
    "ks:ks_type":"HABITATION",
    "name:eng_x_preferred":[
        "Vasantnagar"
    ],
    "wof:name":"Vasantnagar",
    "wof:placetype":"locality",
    "wof:population":190
},
  "geometry": {"coordinates":[77.28826599999999,18.517573],"type":"Point"}
}