{
  "type": "Feature",
  "properties": {
    "iso:country":"IN",
    "ks:ks_alt_nam":"Brahman tola",
    "ks:ks_name":"Brahman Tola",
    "ks:ks_pop":815,
    "ks:ks_type":"HABITATION",
    "name:eng_x_preferred":[
        "Brahman Tola"
    ],
    "wof:name":"Brahman Tola",
    "wof:placetype":"locality",
    "wof:population":815
},
  "geometry": {"coordinates":[85.33201800000001,26.545062],"type":"Point"}
}