{
  "type": "Feature",
  "properties": {
    "iso:country":"IN",
    "ks:ks_name":"Sri Ganda",
    "ks:ks_pop":103,
    "ks:ks_type":"HABITATION",
    "ks:ks_uagg_main":0,
    "name:eng_x_preferred":[
        "Sri Ganda"
    ],
    "wof:name":"Sri Ganda",
    "wof:placetype":"neighbourhood",
    "wof:population":103
},
  "geometry": {"coordinates":[82.194847,26.521246],"type":"Point"}
}