{
  "type": "Feature",
  "properties": {
    "iso:country":"IN",
    "ks:ks_name":"Kata",
    "ks:ks_pop":100,
    "ks:ks_type":"HABITATION",
    "name:eng_x_preferred":[
        "Kata"
    ],
    "wof:name":"Kata",
    "wof:placetype":"locality",
    "wof:population":100
},
  "geometry": {"coordinates":[73.337681,16.52273],"type":"Point"}
}