{
  "type": "Feature",
  "properties": {
    "gn:admin1_code":"2.0",
    "gn:admin2_code":"553.0",
    "gn:asciiname":"Mustipalle",
    "gn:country_code":"IN",
    "gn:dem":607,
    "gn:feature_class":"P",
    "gn:feature_code":"PPL",
    "gn:name":"Mustipalle",
    "gn:population":0,
    "gn:timezone":"Asia/Kolkata",
    "iso:country":"IN",
    "ks:ks_name":"Mustipalli",
    "ks:ks_pop":191,
    "ks:ks_type":"HABITATION",
    "name:eng_x_preferred":[
        "Mustipalli"
    ],
    "name:eng_x_variant":[
        "Mustipalle"
    ],
    "wof:name":"Mustipalli",
    "wof:placetype":"locality",
    "wof:population":191
},
  "geometry": {"coordinates":[78.19301299999999,14.129174],"type":"Point"}
}