{
  "type": "Feature",
  "properties": {
    "iso:country":"IN",
    "ks:ks_name":"Uttar Bhanderkhali",
    "ks:ks_pop":1689,
    "ks:ks_type":"HABITATION",
    "name:eng_x_preferred":[
        "Uttar Bhanderkhali"
    ],
    "wof:name":"Uttar Bhanderkhali",
    "wof:placetype":"locality",
    "wof:population":1689
},
  "geometry": {"coordinates":[88.932586,22.369629],"type":"Point"}
}