{
  "type": "Feature",
  "properties": {
    "gn:admin1_code":"38.0",
    "gn:admin2_code":"360.0",
    "gn:asciiname":"Marigara",
    "gn:country_code":"IN",
    "gn:dem":448,
    "gn:feature_class":"P",
    "gn:feature_code":"PPL",
    "gn:name":"M\u0101rigar\u0101",
    "gn:population":0,
    "gn:timezone":"Asia/Kolkata",
    "iso:country":"IN",
    "ks:ks_alt_nam":"M\u0101rigar\u0101",
    "ks:ks_name":"Marigara",
    "ks:ks_pop":510,
    "ks:ks_type":"VILLAGE",
    "name:eng_x_preferred":[
        "Marigara"
    ],
    "name:eng_x_variant":[
        "M\u0101rigar\u0101"
    ],
    "wof:name":"Marigara",
    "wof:placetype":"locality",
    "wof:population":510
},
  "geometry": {"coordinates":[85.16469600000001,24.198721],"type":"Point"}
}