{
  "type": "Feature",
  "properties": {
    "gn:admin1_code":"19.0",
    "gn:admin2_code":"582.0",
    "gn:asciiname":"Ghantamvaripalli",
    "gn:country_code":"IN",
    "gn:dem":726,
    "gn:feature_class":"P",
    "gn:feature_code":"PPL",
    "gn:name":"Ghantamv\u0101ripalli",
    "gn:population":0,
    "gn:timezone":"Asia/Kolkata",
    "iso:country":"IN",
    "ks:ks_alt_nam":"Ghantamv\u0101ripalli",
    "ks:ks_name":"Ghantamvaripalli",
    "ks:ks_type":"VILLAGE",
    "ks:ks_uagg_main":0,
    "name:eng_x_preferred":[
        "Ghantamvaripalli"
    ],
    "name:eng_x_variant":[
        "Ghantamv\u0101ripalli"
    ],
    "wof:name":"Ghantamvaripalli",
    "wof:placetype":"neighbourhood"
},
  "geometry": {"coordinates":[77.77341300000001,13.784431],"type":"Point"}
}