{
  "type": "Feature",
  "properties": {
    "gn:admin1_code":"39",
    "gn:admin2_code":"67.0",
    "gn:asciiname":"Bhawanipur",
    "gn:country_code":"IN",
    "gn:dem":242,
    "gn:feature_class":"P",
    "gn:feature_code":"PPL",
    "gn:name":"Bhaw\u0101n\u012bpur",
    "gn:population":0,
    "gn:timezone":"Asia/Kolkata",
    "iso:country":"IN",
    "wof:name":"Bhawanipur",
    "wof:placetype":"locality"
},
  "geometry": {"coordinates":[78.87366,29.26524],"type":"Point"}
}