{
  "type": "Feature",
  "properties": {
    "iso:country":"IN",
    "ks:ks_name":"Bogadal-1",
    "ks:ks_pop":272,
    "ks:ks_type":"HABITATION",
    "name:eng_x_preferred":[
        "Bogadal-1"
    ],
    "wof:name":"Bogadal-1",
    "wof:placetype":"locality",
    "wof:population":272
},
  "geometry": {"coordinates":[93.183471,26.23785],"type":"Point"}
}