{
  "type": "Feature",
  "properties": {
    "iso:country":"IN",
    "ks:ks_alt_nam":"kunnath thazha",
    "ks:ks_name":"Kunnath Thazha",
    "ks:ks_pop":1415,
    "ks:ks_type":"HABITATION",
    "name:eng_x_preferred":[
        "Kunnath Thazha"
    ],
    "wof:name":"Kunnath Thazha",
    "wof:placetype":"locality",
    "wof:population":1415
},
  "geometry": {"coordinates":[75.692342,11.578336],"type":"Point"}
}