{
  "type": "Feature",
  "properties": {
    "gn:admin1_code":"35",
    "gn:admin2_code":"463.0",
    "gn:asciiname":"Ponri",
    "gn:country_code":"IN",
    "gn:dem":306,
    "gn:feature_class":"P",
    "gn:feature_code":"PPL",
    "gn:name":"Ponri",
    "gn:population":0,
    "gn:timezone":"Asia/Kolkata",
    "iso:country":"IN",
    "ks:ks_name":"Pondi",
    "ks:ks_pop":853,
    "ks:ks_type":"VILLAGE",
    "name:eng_x_preferred":[
        "Pondi"
    ],
    "name:eng_x_variant":[
        "Ponri"
    ],
    "wof:name":"Pondi",
    "wof:placetype":"locality",
    "wof:population":853
},
  "geometry": {"coordinates":[82.649415,24.65414],"type":"Point"}
}