{
  "type": "Feature",
  "properties": {
    "iso:country":"IN",
    "ks:ks_name":"Kariyanahalli",
    "ks:ks_pop":22,
    "ks:ks_type":"VILLAGE",
    "name:eng_x_preferred":[
        "Kariyanahalli"
    ],
    "wof:name":"Kariyanahalli",
    "wof:placetype":"locality",
    "wof:population":22
},
  "geometry": {"coordinates":[75.953181,13.467367],"type":"Point"}
}