{
  "type": "Feature",
  "properties": {
    "gn:admin1_code":"24.0",
    "gn:admin2_code":"119.0",
    "gn:asciiname":"Chaondadevi",
    "gn:country_code":"IN",
    "gn:dem":636,
    "gn:feature_class":"P",
    "gn:feature_code":"PPL",
    "gn:name":"Ch\u0101ond\u0101devi",
    "gn:population":0,
    "gn:timezone":"Asia/Kolkata",
    "iso:country":"IN",
    "wof:name":"Chaondadevi",
    "wof:placetype":"locality"
},
  "geometry": {"coordinates":[74.60136,26.43876],"type":"Point"}
}