{
  "type": "Feature",
  "properties": {
    "iso:country":"IN",
    "ks:ks_name":"Bakasara",
    "ks:ks_pop":574,
    "ks:ks_type":"VILLAGE",
    "ks:ks_uagg_main":0,
    "name:eng_x_preferred":[
        "Bakasara"
    ],
    "wof:name":"Bakasara",
    "wof:placetype":"neighbourhood",
    "wof:population":574
},
  "geometry": {"coordinates":[80.02752599999999,26.141418],"type":"Point"}
}