{
  "type": "Feature",
  "properties": {
    "iso:country":"IN",
    "ks:ks_name":"Tikar Bariakalkihara",
    "ks:ks_pop":7433,
    "ks:ks_type":"VILLAGE",
    "ks:ks_uagg_main":0,
    "name:eng_x_preferred":[
        "Tikar Bariakalkihara"
    ],
    "wof:name":"Tikar Bariakalkihara",
    "wof:placetype":"neighbourhood",
    "wof:population":7433
},
  "geometry": {"coordinates":[88.602436,24.129324],"type":"Point"}
}