{
  "type": "Feature",
  "properties": {
    "iso:country":"IN",
    "ks:ks_name":"Naganahalli Colony",
    "ks:ks_pop":125,
    "ks:ks_type":"HABITATION",
    "name:eng_x_preferred":[
        "Naganahalli Colony"
    ],
    "wof:name":"Naganahalli Colony",
    "wof:placetype":"locality",
    "wof:population":125
},
  "geometry": {"coordinates":[75.823007,12.725239],"type":"Point"}
}