{
  "type": "Feature",
  "properties": {
    "gn:admin1_code":"16.0",
    "gn:admin2_code":"511.0",
    "gn:asciiname":"Neogha",
    "gn:country_code":"IN",
    "gn:dem":424,
    "gn:feature_class":"P",
    "gn:feature_code":"PPL",
    "gn:name":"Neogha",
    "gn:population":0,
    "gn:timezone":"Asia/Kolkata",
    "iso:country":"IN",
    "wof:name":"Neogha",
    "wof:placetype":"locality"
},
  "geometry": {"coordinates":[77.56182,19.58434],"type":"Point"}
}