{
  "type": "Feature",
  "properties": {
    "iso:country":"IN",
    "ks:ks_name":"Kuthavakarai",
    "ks:ks_pop":741,
    "ks:ks_type":"HABITATION",
    "ks:ks_uagg_main":0,
    "name:eng_x_preferred":[
        "Kuthavakarai"
    ],
    "wof:name":"Kuthavakarai",
    "wof:placetype":"neighbourhood",
    "wof:population":741
},
  "geometry": {"coordinates":[79.710937,11.326069],"type":"Point"}
}