{
  "type": "Feature",
  "properties": {
    "iso:country":"IN",
    "ks:ks_name":"Srirish Ch. Para",
    "ks:ks_pop":16,
    "ks:ks_type":"HABITATION",
    "ks:ks_uagg_main":0,
    "name:eng_x_preferred":[
        "Srirish Ch. Para"
    ],
    "wof:name":"Srirish Ch. Para",
    "wof:placetype":"neighbourhood",
    "wof:population":16
},
  "geometry": {"coordinates":[91.765202,23.340815],"type":"Point"}
}