{
  "type": "Feature",
  "properties": {
    "iso:country":"IN",
    "name:eng_x_preferred":[
        "Cumbala Hill"
    ],
    "name:eng_x_variant":[
        "Bombay Cumballa Hill",
        "Cumballa Hill",
        "Kumbala Hill"
    ],
    "name:hin_x_preferred":[
        "\u0915\u092e\u094d\u092c\u0932\u094d\u0932\u093e \u092a\u0939\u093e\u0921\u093c"
    ],
    "name:kan_x_preferred":[
        "\u0c95\u0c82\u0cac\u0cbe\u0cb2 \u0cac\u0cc6\u0c9f\u0ccd\u0c9f"
    ],
    "name:unk_x_variant":[
        "Kumbala Hill",
        "Cumbala Hill"
    ],
    "qs:gn_adm0_cc":"IN",
    "qs:gn_fcode":"PPLX",
    "qs:gn_local":1275339,
    "qs:gn_namadm1":"16",
    "qs:gn_name":"Cumballa Hill",
    "qs:local_max":3819,
    "qs:local_sum":50908,
    "qs:localhoods":70,
    "qs:name":"Cumbala Hill",
    "qs:name_adm0":"India",
    "qs:name_adm1":"Maharashtra",
    "qs:name_adm2":"Mumbai",
    "qs:name_local":"Mumbai",
    "qs:photo_max":38,
    "qs:photo_sum":126,
    "qs:placetype":"Suburb",
    "qs:quad_count":10,
    "qs:woe_adm0":23424848,
    "qs:woe_adm1":2345750,
    "qs:woe_adm2":12586539,
    "qs:woe_lau":0,
    "qs:woe_local":2295411,
    "qs:woe_ver":"7.10.0",
    "wd:wordcount":92,
    "wof:lang":[
        "eng"
    ],
    "wof:name":"Cumbala Hill",
    "wof:placetype":"neighbourhood"
},
  "geometry": {"coordinates":[72.805176,18.968657],"type":"Point"}
}