{
  "type": "Feature",
  "properties": {
    "iso:country":"IN",
    "ks:ks_name":"Kodenchi",
    "ks:ks_pop":100,
    "ks:ks_type":"HABITATION",
    "name:eng_x_preferred":[
        "Kodenchi"
    ],
    "wof:name":"Kodenchi",
    "wof:placetype":"locality",
    "wof:population":100
},
  "geometry": {"coordinates":[75.46559600000001,12.853051],"type":"Point"}
}