{
  "type": "Feature",
  "properties": {
    "gn:admin1_code":"12.0",
    "gn:admin2_code":"9.0",
    "gn:asciiname":"Chithi Bande",
    "gn:country_code":"IN",
    "gn:dem":1653,
    "gn:feature_class":"P",
    "gn:feature_code":"PPL",
    "gn:name":"Chithi B\u0101nde",
    "gn:population":0,
    "gn:timezone":"Asia/Kolkata",
    "iso:country":"IN",
    "name:eng_x_preferred":[
        "Chithi B\u0101nde"
    ],
    "wof:name":"Chithi Bande",
    "wof:placetype":"locality"
},
  "geometry": {"coordinates":[74.68774000000001,34.37913],"type":"Point"}
}