{
  "type": "Feature",
  "properties": {
    "gn:admin1_code":"25.0",
    "gn:admin2_code":"606.0",
    "gn:asciiname":"Manikkal",
    "gn:country_code":"IN",
    "gn:dem":307,
    "gn:feature_class":"P",
    "gn:feature_code":"PPL",
    "gn:name":"Manikkal",
    "gn:population":0,
    "gn:timezone":"Asia/Kolkata",
    "iso:country":"IN",
    "name:mal_x_preferred":[
        "\u0d2e\u0d3e\u0d23\u0d3f\u0d15\u0d4d\u0d15\u0d7d"
    ],
    "wof:name":"Manikkal",
    "wof:placetype":"locality"
},
  "geometry": {"coordinates":[78.7188,12.16173],"type":"Point"}
}