{
  "type": "Feature",
  "properties": {
    "gn:admin1_code":"16.0",
    "gn:admin2_code":"497.0",
    "gn:asciiname":"Umti",
    "gn:country_code":"IN",
    "gn:dem":462,
    "gn:feature_class":"P",
    "gn:feature_code":"PPL",
    "gn:name":"Umti",
    "gn:population":0,
    "gn:timezone":"Asia/Kolkata",
    "iso:country":"IN",
    "ks:ks_name":"Umti",
    "ks:ks_type":"VILLAGE",
    "name:eng_x_preferred":[
        "Umti"
    ],
    "wof:name":"Umti",
    "wof:placetype":"locality"
},
  "geometry": {"coordinates":[74.081671,21.775396],"type":"Point"}
}