{
  "type": "Feature",
  "properties": {
    "iso:country":"IN",
    "ks:ks_name":"Muvada Nayak Mahadev Dayara Faliya",
    "ks:ks_pop":1050,
    "ks:ks_type":"HABITATION",
    "name:eng_x_preferred":[
        "Muvada Nayak Mahadev Dayara Faliya"
    ],
    "wof:name":"Muvada Nayak Mahadev Dayara Faliya",
    "wof:placetype":"locality",
    "wof:population":1050
},
  "geometry": {"coordinates":[73.82875,22.962417],"type":"Point"}
}