{
  "type": "Feature",
  "properties": {
    "iso:country":"IN",
    "ks:ks_name":"Bechupur",
    "ks:ks_type":"VILLAGE",
    "name:eng_x_preferred":[
        "Bechupur"
    ],
    "wof:name":"Bechupur",
    "wof:placetype":"locality"
},
  "geometry": {"coordinates":[83.102856,25.283851],"type":"Point"}
}