{
  "type": "Feature",
  "properties": {
    "iso:country":"IN",
    "ks:ks_name":"Kotha Mt.Bhatauli",
    "ks:ks_pop":833,
    "ks:ks_type":"VILLAGE",
    "name:eng_x_preferred":[
        "Kotha Mt.Bhatauli"
    ],
    "wof:name":"Kotha Mt.Bhatauli",
    "wof:placetype":"locality",
    "wof:population":833
},
  "geometry": {"coordinates":[82.92825499999999,26.251311],"type":"Point"}
}