{
  "type": "Feature",
  "properties": {
    "iso:country":"IN",
    "ks:ks_name":"Asandih",
    "ks:ks_pop":664,
    "ks:ks_type":"VILLAGE",
    "name:eng_x_preferred":[
        "Asandih"
    ],
    "wof:name":"Asandih",
    "wof:placetype":"locality",
    "wof:population":664
},
  "geometry": {"coordinates":[83.47826999999999,23.204647],"type":"Point"}
}