{
  "type": "Feature",
  "properties": {
    "iso:country":"IN",
    "ks:ks_name":"Shapur Dhadhoi",
    "ks:ks_pop":2147,
    "ks:ks_type":"VILLAGE",
    "name:eng_x_preferred":[
        "Shapur Dhadhoi"
    ],
    "wof:name":"Shapur Dhadhoi",
    "wof:placetype":"locality",
    "wof:population":2147
},
  "geometry": {"coordinates":[77.876549,27.729292],"type":"Point"}
}