{
  "type": "Feature",
  "properties": {
    "gn:admin1_code":"2.0",
    "gn:admin2_code":"543.0",
    "gn:asciiname":"Sumitrapuram Agraharam",
    "gn:country_code":"IN",
    "gn:dem":91,
    "gn:feature_class":"P",
    "gn:feature_code":"PPL",
    "gn:name":"Sumitr\u0101puram Agrah\u0101ram",
    "gn:population":0,
    "gn:timezone":"Asia/Kolkata",
    "iso:country":"IN",
    "wof:name":"Sumitrapuram Agraharam",
    "wof:placetype":"locality"
},
  "geometry": {"coordinates":[83.46325999999998,18.68851],"type":"Point"}
}