{
  "type": "Feature",
  "properties": {
    "iso:country":"IN",
    "ks:ks_name":"Takali Pr. Chalisgaon",
    "ks:ks_pop":7277,
    "ks:ks_type":"URBAN",
    "name:eng_x_preferred":[
        "Takali Pr. Chalisgaon"
    ],
    "wof:name":"Takali Pr. Chalisgaon",
    "wof:placetype":"locality",
    "wof:population":7277
},
  "geometry": {"coordinates":[75.01655700000001,20.480151],"type":"Point"}
}