{
  "type": "Feature",
  "properties": {
    "gn:admin1_code":"2",
    "gn:admin2_code":"547.0",
    "gn:asciiname":"Venkatanarayanapuram",
    "gn:country_code":"IN",
    "gn:dem":7,
    "gn:feature_class":"P",
    "gn:feature_code":"PPL",
    "gn:name":"Venkatan\u0101r\u0101yanapuram",
    "gn:population":0,
    "gn:timezone":"Asia/Kolkata",
    "iso:country":"IN",
    "wof:name":"Venkatanarayanapuram",
    "wof:placetype":"locality"
},
  "geometry": {"coordinates":[81.30271,16.41322000000001],"type":"Point"}
}