{
  "type": "Feature",
  "properties": {
    "gn:admin1_code":"38.0",
    "gn:admin2_code":"353.0",
    "gn:asciiname":"Gaipathar",
    "gn:country_code":"IN",
    "gn:dem":88,
    "gn:feature_class":"P",
    "gn:feature_code":"PPL",
    "gn:name":"Gaip\u0101th\u0101r",
    "gn:population":0,
    "gn:timezone":"Asia/Kolkata",
    "iso:country":"IN",
    "ks:ks_alt_nam":"GAIPATHAR",
    "ks:ks_name":"Gaipathar",
    "ks:ks_pop":524,
    "ks:ks_type":"HABITATION",
    "name:eng_x_preferred":[
        "Gaipathar"
    ],
    "wof:name":"Gaipathar",
    "wof:placetype":"locality",
    "wof:population":524
},
  "geometry": {"coordinates":[87.606607,24.356671],"type":"Point"}
}