{
  "type": "Feature",
  "properties": {
    "iso:country":"IN",
    "ks:ks_name":"Khakhar Khedi",
    "ks:ks_pop":229,
    "ks:ks_type":"VILLAGE",
    "name:eng_x_preferred":[
        "Khakhar Khedi"
    ],
    "wof:name":"Khakhar Khedi",
    "wof:placetype":"locality",
    "wof:population":229
},
  "geometry": {"coordinates":[74.58298600000001,22.894271],"type":"Point"}
}