{
  "type": "Feature",
  "properties": {
    "iso:country":"IN",
    "ks:ks_name":"Jambira",
    "ks:ks_pop":197,
    "ks:ks_type":"VILLAGE",
    "name:eng_x_preferred":[
        "Jambira"
    ],
    "wof:name":"Jambira",
    "wof:placetype":"locality",
    "wof:population":197
},
  "geometry": {"coordinates":[83.328301,22.398405],"type":"Point"}
}