{
  "type": "Feature",
  "properties": {
    "gn:admin1_code":"35",
    "gn:admin2_code":"451.0",
    "gn:asciiname":"Mandhara",
    "gn:country_code":"IN",
    "gn:dem":380,
    "gn:feature_class":"P",
    "gn:feature_code":"PPL",
    "gn:name":"Mandhara",
    "gn:population":0,
    "gn:timezone":"Asia/Kolkata",
    "iso:country":"IN",
    "ks:ks_name":"Mandhara",
    "ks:ks_pop":641,
    "ks:ks_type":"VILLAGE",
    "ks:ks_uagg_main":0,
    "name:eng_x_preferred":[
        "Mandhara"
    ],
    "wof:name":"Mandhara",
    "wof:placetype":"neighbourhood",
    "wof:population":641
},
  "geometry": {"coordinates":[79.888734,23.517713],"type":"Point"}
}