{
  "type": "Feature",
  "properties": {
    "iso:country":"IN",
    "ks:ks_name":"Rampur Tappa Agsauli",
    "ks:ks_pop":896,
    "ks:ks_type":"VILLAGE",
    "name:eng_x_preferred":[
        "Rampur Tappa Agsauli"
    ],
    "wof:name":"Rampur Tappa Agsauli",
    "wof:placetype":"locality",
    "wof:population":896
},
  "geometry": {"coordinates":[78.458834,27.768204],"type":"Point"}
}