{
  "type": "Feature",
  "properties": {
    "iso:country":"IN",
    "ks:ks_name":"Jurunda",
    "ks:ks_pop":20,
    "ks:ks_type":"HABITATION",
    "name:eng_x_preferred":[
        "Jurunda"
    ],
    "wof:name":"Jurunda",
    "wof:placetype":"locality",
    "wof:population":20
},
  "geometry": {"coordinates":[86.40357400000001,21.93595],"type":"Point"}
}