{
  "type": "Feature",
  "properties": {
    "iso:country":"IN",
    "ks:ks_name":"Bandarumadigapalli",
    "ks:ks_pop":86,
    "ks:ks_type":"HABITATION",
    "name:eng_x_preferred":[
        "Bandarumadigapalli"
    ],
    "wof:name":"Bandarumadigapalli",
    "wof:placetype":"locality",
    "wof:population":86
},
  "geometry": {"coordinates":[78.536207,14.043918],"type":"Point"}
}