{
  "type": "Feature",
  "properties": {
    "gn:admin1_code":"17.0",
    "gn:admin2_code":"279",
    "gn:asciiname":"Boljang",
    "gn:country_code":"IN",
    "gn:dem":868,
    "gn:feature_class":"P",
    "gn:feature_code":"PPL",
    "gn:name":"Bolj\u0101ng",
    "gn:population":0,
    "gn:timezone":"Asia/Kolkata",
    "iso:country":"IN",
    "wof:name":"Boljang",
    "wof:placetype":"locality"
},
  "geometry": {"coordinates":[94.39801,24.62355],"type":"Point"}
}