{
  "type": "Feature",
  "properties": {
    "iso:country":"IN",
    "ks:ks_alt_nam":"7 NRD",
    "ks:ks_name":"7 Nrd",
    "ks:ks_pop":26,
    "ks:ks_type":"HABITATION",
    "name:eng_x_preferred":[
        "7 Nrd"
    ],
    "wof:name":"7 Nrd",
    "wof:placetype":"locality",
    "wof:population":26
},
  "geometry": {"coordinates":[73.797793,29.428897],"type":"Point"}
}