{
  "type": "Feature",
  "properties": {
    "gn:admin1_code":"35.0",
    "gn:admin2_code":"454.0",
    "gn:asciiname":"Kumha",
    "gn:country_code":"IN",
    "gn:dem":430,
    "gn:feature_class":"P",
    "gn:feature_code":"PPL",
    "gn:name":"K\u016bmha",
    "gn:population":0,
    "gn:timezone":"Asia/Kolkata",
    "iso:country":"IN",
    "ks:ks_alt_nam":"K\u016bmha",
    "ks:ks_name":"Kumha",
    "ks:ks_type":"VILLAGE",
    "name:eng_x_preferred":[
        "Kumha"
    ],
    "name:eng_x_variant":[
        "K\u016bmha"
    ],
    "wof:name":"Kumha",
    "wof:placetype":"locality"
},
  "geometry": {"coordinates":[80.26187,22.80489],"type":"Point"}
}