{
  "type": "Feature",
  "properties": {
    "iso:country":"IN",
    "ks:ks_name":"Piparha",
    "ks:ks_pop":198,
    "ks:ks_type":"HABITATION",
    "name:eng_x_preferred":[
        "Piparha"
    ],
    "wof:name":"Piparha",
    "wof:placetype":"locality",
    "wof:population":198
},
  "geometry": {"coordinates":[82.28043599999999,22.916512],"type":"Point"}
}