{
  "type": "Feature",
  "properties": {
    "iso:country":"IN",
    "ks:ks_alt_nam":"Parsi wadFaliyu",
    "ks:ks_name":"Parsi Wadfaliyu",
    "ks:ks_pop":109,
    "ks:ks_type":"HABITATION",
    "name:eng_x_preferred":[
        "Parsi Wadfaliyu"
    ],
    "wof:name":"Parsi Wadfaliyu",
    "wof:placetype":"locality",
    "wof:population":109
},
  "geometry": {"coordinates":[72.779472,20.241944],"type":"Point"}
}