{
  "type": "Feature",
  "properties": {
    "iso:country":"IN",
    "ks:ks_name":"Chamrupara",
    "ks:ks_pop":711,
    "ks:ks_type":"HABITATION",
    "name:eng_x_preferred":[
        "Chamrupara"
    ],
    "wof:name":"Chamrupara",
    "wof:placetype":"locality",
    "wof:population":711
},
  "geometry": {"coordinates":[81.915577,18.874412],"type":"Point"}
}