{
  "type": "Feature",
  "properties": {
    "iso:country":"IN",
    "ks:ks_name":"Bendrapali",
    "ks:ks_pop":25,
    "ks:ks_type":"HABITATION",
    "name:eng_x_preferred":[
        "Bendrapali"
    ],
    "wof:name":"Bendrapali",
    "wof:placetype":"locality",
    "wof:population":25
},
  "geometry": {"coordinates":[84.13212799999999,20.338718],"type":"Point"}
}