{
  "type": "Feature",
  "properties": {
    "gn:admin1_code":"36",
    "gn:admin2_code":"200.0",
    "gn:asciiname":"Injani",
    "gn:country_code":"IN",
    "gn:dem":350,
    "gn:feature_class":"P",
    "gn:feature_code":"PPL",
    "gn:name":"Injani",
    "gn:population":0,
    "gn:timezone":"Asia/Kolkata",
    "iso:country":"IN",
    "ks:ks_name":"Anjani",
    "ks:ks_pop":883,
    "ks:ks_type":"HABITATION",
    "name:eng_x_preferred":[
        "Anjani"
    ],
    "name:eng_x_variant":[
        "Injani"
    ],
    "wof:name":"Anjani",
    "wof:placetype":"locality",
    "wof:population":883
},
  "geometry": {"coordinates":[82.939487,24.00658],"type":"Point"}
}