{
  "type": "Feature",
  "properties": {
    "iso:country":"IN",
    "ks:ks_name":"Jambiapada",
    "ks:ks_pop":521,
    "ks:ks_type":"HABITATION",
    "name:eng_x_preferred":[
        "Jambiapada"
    ],
    "wof:name":"Jambiapada",
    "wof:placetype":"locality",
    "wof:population":521
},
  "geometry": {"coordinates":[74.168243,21.619934],"type":"Point"}
}