{
  "type": "Feature",
  "properties": {
    "gn:admin1_code":"34.0",
    "gn:admin2_code":"203.0",
    "gn:asciiname":"Sahi",
    "gn:country_code":"IN",
    "gn:dem":81,
    "gn:feature_class":"P",
    "gn:feature_code":"PPL",
    "gn:name":"S\u0101hi",
    "gn:population":0,
    "gn:timezone":"Asia/Kolkata",
    "iso:country":"IN",
    "name:ceb_x_preferred":[
        "Sahi"
    ],
    "name:swe_x_preferred":[
        "Sahi"
    ],
    "wof:name":"Sahi",
    "wof:placetype":"locality"
},
  "geometry": {"coordinates":[84.48224,26.77369],"type":"Point"}
}