{
  "type": "Feature",
  "properties": {
    "iso:country":"IN",
    "ks:ks_name":"Drekatte",
    "ks:ks_pop":566,
    "ks:ks_type":"HABITATION",
    "name:eng_x_preferred":[
        "Drekatte"
    ],
    "wof:name":"Drekatte",
    "wof:placetype":"locality",
    "wof:population":566
},
  "geometry": {"coordinates":[74.980716,12.908345],"type":"Point"}
}