{
  "type": "Feature",
  "properties": {
    "gn:admin1_code":"11.0",
    "gn:admin2_code":"32.0",
    "gn:asciiname":"Khilag",
    "gn:country_code":"IN",
    "gn:dem":2222,
    "gn:feature_class":"P",
    "gn:feature_code":"PPL",
    "gn:name":"Khilag",
    "gn:population":0,
    "gn:timezone":"Asia/Kolkata",
    "iso:country":"IN",
    "wof:name":"Khilag",
    "wof:placetype":"locality"
},
  "geometry": {"coordinates":[77.46194,30.81567],"type":"Point"}
}