{
  "type": "Feature",
  "properties": {
    "iso:country":"IN",
    "ks:ks_alt_nam":"Gop\u0101lpur",
    "ks:ks_name":"Gopalpur",
    "ks:ks_type":"VILLAGE",
    "name:eng_x_preferred":[
        "Gopalpur"
    ],
    "name:eng_x_variant":[
        "Gop\u0101lpur"
    ],
    "wof:name":"Gopalpur",
    "wof:placetype":"locality"
},
  "geometry": {"coordinates":[83.53767499999999,25.05803],"type":"Point"}
}