{
  "type": "Feature",
  "properties": {
    "iso:country":"IN",
    "ks:ks_name":"Chandanpur",
    "ks:ks_pop":272,
    "ks:ks_type":"HABITATION",
    "name:eng_x_preferred":[
        "Chandanpur"
    ],
    "wof:name":"Chandanpur",
    "wof:placetype":"locality",
    "wof:population":272
},
  "geometry": {"coordinates":[80.189289,26.172528],"type":"Point"}
}