{
  "type": "Feature",
  "properties": {
    "gn:admin1_code":"36.0",
    "gn:admin2_code":"133.0",
    "gn:asciiname":"Banipur",
    "gn:country_code":"IN",
    "gn:dem":242,
    "gn:feature_class":"P",
    "gn:feature_code":"PPL",
    "gn:name":"Ban\u012bpur",
    "gn:population":0,
    "gn:timezone":"Asia/Kolkata",
    "iso:country":"IN",
    "wof:name":"Banipur",
    "wof:placetype":"locality"
},
  "geometry": {"coordinates":[77.17388000000003,29.52602000000001],"type":"Point"}
}