{
  "type": "Feature",
  "properties": {
    "iso:country":"IN",
    "ks:ks_name":"Ontiputtu",
    "ks:ks_pop":139,
    "ks:ks_type":"HABITATION",
    "name:eng_x_preferred":[
        "Ontiputtu"
    ],
    "wof:name":"Ontiputtu",
    "wof:placetype":"locality",
    "wof:population":139
},
  "geometry": {"coordinates":[82.702252,18.186298],"type":"Point"}
}