{
  "type": "Feature",
  "properties": {
    "iso:country":"IN",
    "ks:ks_name":"Ghuroli",
    "ks:ks_pop":100,
    "ks:ks_type":"HABITATION",
    "name:eng_x_preferred":[
        "Ghuroli"
    ],
    "wof:name":"Ghuroli",
    "wof:placetype":"locality",
    "wof:population":100
},
  "geometry": {"coordinates":[78.688913,29.954078],"type":"Point"}
}