{
  "type": "Feature",
  "properties": {
    "iso:country":"IN",
    "ks:ks_name":"Pannawas",
    "ks:ks_pop":190,
    "ks:ks_type":"HABITATION",
    "name:eng_x_preferred":[
        "Pannawas"
    ],
    "wof:name":"Pannawas",
    "wof:placetype":"locality",
    "wof:population":190
},
  "geometry": {"coordinates":[71.661125,26.303989],"type":"Point"}
}