{
  "type": "Feature",
  "properties": {
    "iso:country":"IN",
    "ks:ks_name":"Bapur",
    "ks:ks_pop":618,
    "ks:ks_type":"VILLAGE",
    "name:eng_x_preferred":[
        "Bapur"
    ],
    "wof:name":"Bapur",
    "wof:placetype":"locality",
    "wof:population":618
},
  "geometry": {"coordinates":[77.522199,17.961136],"type":"Point"}
}