{
  "type": "Feature",
  "properties": {
    "iso:country":"IN",
    "ks:ks_name":"Irular Nagar",
    "ks:ks_pop":557,
    "ks:ks_type":"HABITATION",
    "ks:ks_uagg_main":0,
    "name:eng_x_preferred":[
        "Irular Nagar"
    ],
    "wof:name":"Irular Nagar",
    "wof:placetype":"locality",
    "wof:population":557
},
  "geometry": {"coordinates":[80.065504,12.978362],"type":"Point"}
}