{
  "type": "Feature",
  "properties": {
    "gn:admin1_code":"24.0",
    "gn:admin2_code":"111.0",
    "gn:asciiname":"Sudon ki Dhani",
    "gn:country_code":"IN",
    "gn:dem":317,
    "gn:feature_class":"P",
    "gn:feature_code":"PPL",
    "gn:name":"Sudon ki Dh\u0101ni",
    "gn:population":0,
    "gn:timezone":"Asia/Kolkata",
    "iso:country":"IN",
    "wof:name":"Sudon ki Dhani",
    "wof:placetype":"locality"
},
  "geometry": {"coordinates":[75.04201,28.13361],"type":"Point"}
}