{
  "type": "Feature",
  "properties": {
    "iso:country":"IN",
    "ks:ks_name":"Said Mohammadpur",
    "ks:ks_pop":0,
    "ks:ks_type":"VILLAGE",
    "name:eng_x_preferred":[
        "Said Mohammadpur"
    ],
    "wof:name":"Said Mohammadpur",
    "wof:placetype":"locality",
    "wof:population":0
},
  "geometry": {"coordinates":[78.721074,28.462967],"type":"Point"}
}