{
  "type": "Feature",
  "properties": {
    "gn:admin1_code":"36.0",
    "gn:admin2_code":"184.0",
    "gn:asciiname":"Semri",
    "gn:country_code":"IN",
    "gn:dem":100,
    "gn:feature_class":"P",
    "gn:feature_code":"PPL",
    "gn:name":"Semri",
    "gn:population":0,
    "gn:timezone":"Asia/Kolkata",
    "iso:country":"IN",
    "ks:ks_name":"Semari",
    "ks:ks_pop":372,
    "ks:ks_type":"HABITATION",
    "name:eng_x_preferred":[
        "Semari"
    ],
    "name:eng_x_variant":[
        "Semri"
    ],
    "wof:name":"Semari",
    "wof:placetype":"locality",
    "wof:population":372
},
  "geometry": {"coordinates":[82.596926,27.235142],"type":"Point"}
}