{
  "type": "Feature",
  "properties": {
    "gn:admin1_code":"36.0",
    "gn:admin2_code":"184.0",
    "gn:asciiname":"Semri",
    "gn:country_code":"IN",
    "gn:dem":100,
    "gn:feature_class":"P",
    "gn:feature_code":"PPL",
    "gn:name":"Semri",
    "gn:population":0,
    "gn:timezone":"Asia/Kolkata",
    "iso:country":"IN",
    "wof:name":"Semri",
    "wof:placetype":"locality"
},
  "geometry": {"coordinates":[82.58474,27.23913],"type":"Point"}
}