{
  "type": "Feature",
  "properties": {
    "gn:admin1_code":"36",
    "gn:admin2_code":"134.0",
    "gn:asciiname":"Shahzadpur",
    "gn:country_code":"IN",
    "gn:dem":259,
    "gn:feature_class":"P",
    "gn:feature_code":"PPL",
    "gn:name":"Sh\u0101hz\u0101dpur",
    "gn:population":0,
    "gn:timezone":"Asia/Kolkata",
    "iso:country":"IN",
    "name:und_x_variant":[
        "Sh\u0101hz\u0101dpur",
        "S\u0101datpur"
    ],
    "wof:name":"Shahzadpur",
    "wof:placetype":"locality"
},
  "geometry": {"coordinates":[78.33011999999999,29.55216],"type":"Point"}
}