{
  "type": "Feature",
  "properties": {
    "iso:country":"IN",
    "ks:ks_name":"Karalemane",
    "ks:ks_pop":21,
    "ks:ks_type":"HABITATION",
    "name:eng_x_preferred":[
        "Karalemane"
    ],
    "wof:name":"Karalemane",
    "wof:placetype":"locality",
    "wof:population":21
},
  "geometry": {"coordinates":[74.815831,15.302137],"type":"Point"}
}