{
  "type": "Feature",
  "properties": {
    "gn:admin1_code":"19.0",
    "gn:admin2_code":"561.0",
    "gn:asciiname":"Wadegol",
    "gn:country_code":"IN",
    "gn:dem":691,
    "gn:feature_class":"P",
    "gn:feature_code":"PPL",
    "gn:name":"Wadegol",
    "gn:population":0,
    "gn:timezone":"Asia/Kolkata",
    "iso:country":"IN",
    "ks:ks_alt_nam":"vadegol",
    "ks:ks_name":"Vadegol",
    "ks:ks_pop":482,
    "ks:ks_type":"HABITATION",
    "name:eng_x_preferred":[
        "Vadegol"
    ],
    "name:eng_x_variant":[
        "Wadegol"
    ],
    "wof:name":"Vadegol",
    "wof:placetype":"locality",
    "wof:population":482
},
  "geometry": {"coordinates":[75.978674,15.764037],"type":"Point"}
}