{
  "type": "Feature",
  "properties": {
    "iso:country":"IN",
    "ks:ks_name":"Alamarathumedu",
    "ks:ks_pop":550,
    "ks:ks_type":"HABITATION",
    "ks:ks_uagg_main":0,
    "name:eng_x_preferred":[
        "Alamarathumedu"
    ],
    "wof:name":"Alamarathumedu",
    "wof:placetype":"neighbourhood",
    "wof:population":550
},
  "geometry": {"coordinates":[77.98894,11.075095],"type":"Point"}
}