{
  "type": "Feature",
  "properties": {
    "iso:country":"IN",
    "ks:ks_name":"Umarbah",
    "ks:ks_pop":782,
    "ks:ks_type":"VILLAGE",
    "name:eng_x_preferred":[
        "Umarbah"
    ],
    "wof:name":"Umarbah",
    "wof:placetype":"locality",
    "wof:population":782
},
  "geometry": {"coordinates":[78.788061,22.367643],"type":"Point"}
}