{
  "type": "Feature",
  "properties": {
    "iso:country":"IN",
    "ks:ks_alt_nam":"Jamuni\u0101",
    "ks:ks_name":"Jamunia",
    "ks:ks_type":"VILLAGE",
    "name:eng_x_preferred":[
        "Jamunia"
    ],
    "name:eng_x_variant":[
        "Jamuni\u0101"
    ],
    "wof:name":"Jamunia",
    "wof:placetype":"locality"
},
  "geometry": {"coordinates":[84.296874,27.208262],"type":"Point"}
}