{
  "type": "Feature",
  "properties": {
    "gn:admin1_code":"34.0",
    "gn:admin2_code":"219.0",
    "gn:asciiname":"Kakarahat",
    "gn:country_code":"IN",
    "gn:dem":57,
    "gn:feature_class":"P",
    "gn:feature_code":"PPL",
    "gn:name":"Kakar\u0101hat",
    "gn:population":0,
    "gn:timezone":"Asia/Kolkata",
    "iso:country":"IN",
    "ks:ks_alt_nam":"Kakar\u0101hat",
    "ks:ks_name":"Kakarahat",
    "ks:ks_pop":409,
    "ks:ks_type":"VILLAGE",
    "ks:ks_uagg_main":0,
    "name:eng_x_preferred":[
        "Kakarahat"
    ],
    "name:eng_x_variant":[
        "Kakar\u0101hat"
    ],
    "wof:name":"Kakarahat",
    "wof:placetype":"neighbourhood",
    "wof:population":409
},
  "geometry": {"coordinates":[84.994929,25.833831],"type":"Point"}
}