{
  "type": "Feature",
  "properties": {
    "iso:country":"IN",
    "ks:ks_name":"Cannal Mor",
    "ks:ks_pop":173,
    "ks:ks_type":"HABITATION",
    "ks:ks_uagg_main":0,
    "name:eng_x_preferred":[
        "Cannal Mor"
    ],
    "wof:name":"Cannal Mor",
    "wof:placetype":"neighbourhood",
    "wof:population":173
},
  "geometry": {"coordinates":[86.713137,26.034216],"type":"Point"}
}