{
  "type": "Feature",
  "properties": {
    "iso:country":"IN",
    "ks:ks_name":"Khede",
    "ks:ks_pop":2200,
    "ks:ks_type":"VILLAGE",
    "ks:ks_uagg_main":0,
    "name:eng_x_preferred":[
        "Khede"
    ],
    "wof:name":"Khede",
    "wof:placetype":"neighbourhood",
    "wof:population":2200
},
  "geometry": {"coordinates":[74.126,20.1299],"type":"Point"}
}