{
  "type": "Feature",
  "properties": {
    "iso:country":"IN",
    "ks:ks_alt_nam":"Amuran Aahir faliya",
    "ks:ks_name":"Amuran Aahir Faliya",
    "ks:ks_pop":305,
    "ks:ks_type":"HABITATION",
    "ks:ks_uagg_main":0,
    "name:eng_x_preferred":[
        "Amuran Aahir Faliya"
    ],
    "wof:name":"Amuran Aahir Faliya",
    "wof:placetype":"neighbourhood",
    "wof:population":305
},
  "geometry": {"coordinates":[73.13582100000001,20.460866],"type":"Point"}
}