{
  "type": "Feature",
  "properties": {
    "iso:country":"IN",
    "ks:ks_name":"Karolu",
    "ks:ks_pop":138,
    "ks:ks_type":"HABITATION",
    "name:eng_x_preferred":[
        "Karolu"
    ],
    "wof:name":"Karolu",
    "wof:placetype":"locality",
    "wof:population":138
},
  "geometry": {"coordinates":[74.97859800000001,13.286155],"type":"Point"}
}