{
  "type": "Feature",
  "properties": {
    "iso:country":"IN",
    "ks:ks_name":"Jharjharia",
    "ks:ks_pop":345,
    "ks:ks_type":"HABITATION",
    "name:eng_x_preferred":[
        "Jharjharia"
    ],
    "wof:name":"Jharjharia",
    "wof:placetype":"locality",
    "wof:population":345
},
  "geometry": {"coordinates":[91.49754,23.226886],"type":"Point"}
}