{
  "type": "Feature",
  "properties": {
    "iso:country":"IN",
    "ks:ks_name":"Kotwarpara",
    "ks:ks_pop":119,
    "ks:ks_type":"HABITATION",
    "name:eng_x_preferred":[
        "Kotwarpara"
    ],
    "wof:name":"Kotwarpara",
    "wof:placetype":"locality",
    "wof:population":119
},
  "geometry": {"coordinates":[81.193556,19.065353],"type":"Point"}
}