{
  "type": "Feature",
  "properties": {
    "iso:country":"IN",
    "ks:ks_name":"Mohan Lal Ka Purwa",
    "ks:ks_pop":591,
    "ks:ks_type":"HABITATION",
    "name:eng_x_preferred":[
        "Mohan Lal Ka Purwa"
    ],
    "wof:name":"Mohan Lal Ka Purwa",
    "wof:placetype":"locality",
    "wof:population":591
},
  "geometry": {"coordinates":[81.657439,25.076316],"type":"Point"}
}