{
  "type": "Feature",
  "properties": {
    "iso:country":"IN",
    "ks:ks_name":"Jafarpur",
    "ks:ks_pop":2011,
    "ks:ks_type":"VILLAGE",
    "ks:ks_uagg_main":0,
    "name:eng_x_preferred":[
        "Jafarpur"
    ],
    "wof:name":"Jafarpur",
    "wof:placetype":"neighbourhood",
    "wof:population":2011
},
  "geometry": {"coordinates":[88.582582,22.722538],"type":"Point"}
}