{
  "type": "Feature",
  "properties": {
    "iso:country":"IN",
    "ks:ks_alt_nam":"kanhudihi",
    "ks:ks_name":"Kanhudihi",
    "ks:ks_pop":206,
    "ks:ks_type":"HABITATION",
    "name:eng_x_preferred":[
        "Kanhudihi"
    ],
    "wof:name":"Kanhudihi",
    "wof:placetype":"locality",
    "wof:population":206
},
  "geometry": {"coordinates":[86.075155,22.373341],"type":"Point"}
}