{
  "type": "Feature",
  "properties": {
    "iso:country":"IN",
    "ks:ks_name":"Chaldhoa",
    "ks:ks_pop":527,
    "ks:ks_type":"VILLAGE",
    "name:eng_x_preferred":[
        "Chaldhoa"
    ],
    "wof:name":"Chaldhoa",
    "wof:placetype":"locality",
    "wof:population":527
},
  "geometry": {"coordinates":[86.524288,23.973633],"type":"Point"}
}