{
  "type": "Feature",
  "properties": {
    "gn:admin1_code":"19.0",
    "gn:admin2_code":"568.0",
    "gn:asciiname":"Chik Kasavi",
    "gn:country_code":"IN",
    "gn:dem":635,
    "gn:feature_class":"P",
    "gn:feature_code":"PPL",
    "gn:name":"Chik Kasavi",
    "gn:population":0,
    "gn:timezone":"Asia/Kolkata",
    "iso:country":"IN",
    "ks:ks_name":"Chikkasavi",
    "ks:ks_pop":499,
    "ks:ks_type":"VILLAGE",
    "name:eng_x_preferred":[
        "Chikkasavi"
    ],
    "name:eng_x_variant":[
        "Chik Kasavi"
    ],
    "wof:name":"Chikkasavi",
    "wof:placetype":"locality",
    "wof:population":499
},
  "geometry": {"coordinates":[75.22443699999999,14.338946],"type":"Point"}
}