{
  "type": "Feature",
  "properties": {
    "gn:admin1_code":"2.0",
    "gn:admin2_code":"544.0",
    "gn:asciiname":"Lachchmipur",
    "gn:country_code":"IN",
    "gn:dem":866,
    "gn:feature_class":"P",
    "gn:feature_code":"PPL",
    "gn:name":"Lachchm\u012bpur",
    "gn:population":0,
    "gn:timezone":"Asia/Kolkata",
    "iso:country":"IN",
    "ks:ks_alt_nam":"Lachchm\u012bpur",
    "ks:ks_name":"Lachchmipur",
    "ks:ks_type":"VILLAGE",
    "name:eng_x_preferred":[
        "Lachchmipur"
    ],
    "name:eng_x_variant":[
        "Lachchm\u012bpur"
    ],
    "wof:name":"Lachchmipur",
    "wof:placetype":"locality"
},
  "geometry": {"coordinates":[82.41577700000001,18.032285],"type":"Point"}
}