{
  "type": "Feature",
  "properties": {
    "iso:country":"IN",
    "ks:ks_name":"Kallipatti Vadakku",
    "ks:ks_pop":459,
    "ks:ks_type":"HABITATION",
    "name:eng_x_preferred":[
        "Kallipatti Vadakku"
    ],
    "wof:name":"Kallipatti Vadakku",
    "wof:placetype":"locality",
    "wof:population":459
},
  "geometry": {"coordinates":[78.45834600000001,10.625346],"type":"Point"}
}