{
  "type": "Feature",
  "properties": {
    "gn:admin1_code":"25.0",
    "gn:admin2_code":"630.0",
    "gn:asciiname":"Nadur",
    "gn:country_code":"IN",
    "gn:dem":422,
    "gn:feature_class":"P",
    "gn:feature_code":"PPL",
    "gn:name":"Nad\u016br",
    "gn:population":0,
    "gn:timezone":"Asia/Kolkata",
    "iso:country":"IN",
    "name:cat_x_preferred":[
        "Nadur"
    ],
    "name:ceb_x_preferred":[
        "In-Nadur"
    ],
    "name:deu_x_preferred":[
        "Nadur"
    ],
    "name:epo_x_preferred":[
        "Nadur"
    ],
    "name:eus_x_preferred":[
        "Nadur"
    ],
    "name:fra_x_preferred":[
        "In-Nadur"
    ],
    "name:hun_x_preferred":[
        "Nadur"
    ],
    "name:ind_x_preferred":[
        "Nadur"
    ],
    "name:ita_x_preferred":[
        "Nadur"
    ],
    "name:kor_x_preferred":[
        "\ub098\ub450\ub974"
    ],
    "name:lit_x_preferred":[
        "Naduras"
    ],
    "name:nld_x_preferred":[
        "Nadur"
    ],
    "name:pol_x_preferred":[
        "Nadur"
    ],
    "name:por_x_preferred":[
        "Nadur"
    ],
    "name:scn_x_preferred":[
        "Nadur"
    ],
    "name:spa_x_preferred":[
        "Nadur"
    ],
    "name:urd_x_preferred":[
        "\u0646\u0627\u062f\u0648\u0631"
    ],
    "wof:name":"Nadur",
    "wof:placetype":"locality"
},
  "geometry": {"coordinates":[78.26619000000002,12.20922],"type":"Point"}
}