{
  "type": "Feature",
  "properties": {
    "iso:country":"IN",
    "ks:ks_name":"Phakirana",
    "ks:ks_pop":57,
    "ks:ks_type":"VILLAGE",
    "ks:ks_uagg_main":0,
    "name:eng_x_preferred":[
        "Phakirana"
    ],
    "wof:name":"Phakirana",
    "wof:placetype":"neighbourhood",
    "wof:population":57
},
  "geometry": {"coordinates":[86.323626,26.061288],"type":"Point"}
}