{
  "type": "Feature",
  "properties": {
    "iso:country":"IN",
    "ks:ks_name":"Tokawade",
    "ks:ks_pop":1115,
    "ks:ks_type":"VILLAGE",
    "name:eng_x_preferred":[
        "Tokawade"
    ],
    "wof:name":"Tokawade",
    "wof:placetype":"locality",
    "wof:population":1115
},
  "geometry": {"coordinates":[73.60945700000001,19.320256],"type":"Point"}
}