{
  "type": "Feature",
  "properties": {
    "gn:admin1_code":"37",
    "gn:admin2_code":"403.0",
    "gn:asciiname":"Muralipali",
    "gn:country_code":"IN",
    "gn:dem":241,
    "gn:feature_class":"P",
    "gn:feature_code":"PPL",
    "gn:name":"Mur\u0101lip\u0101li",
    "gn:population":0,
    "gn:timezone":"Asia/Kolkata",
    "iso:country":"IN",
    "ks:ks_alt_nam":"Mur\u0101lip\u0101li",
    "ks:ks_name":"Muralipali",
    "ks:ks_type":"VILLAGE",
    "ks:ks_uagg_main":0,
    "name:eng_x_preferred":[
        "Muralipali"
    ],
    "name:eng_x_variant":[
        "Mur\u0101lip\u0101li"
    ],
    "wof:name":"Muralipali",
    "wof:placetype":"neighbourhood"
},
  "geometry": {"coordinates":[83.311188,21.948791],"type":"Point"}
}