{
  "type": "Feature",
  "properties": {
    "iso:country":"IN",
    "ks:ks_name":"Adhavra",
    "ks:ks_pop":599,
    "ks:ks_type":"VILLAGE",
    "ks:ks_uagg_main":0,
    "name:eng_x_preferred":[
        "Adhavra"
    ],
    "wof:name":"Adhavra",
    "wof:placetype":"neighbourhood",
    "wof:population":599
},
  "geometry": {"coordinates":[82.785364,24.026736],"type":"Point"}
}