{
  "type": "Feature",
  "properties": {
    "iso:country":"IN",
    "ks:ks_name":"Manasya",
    "ks:ks_pop":54,
    "ks:ks_type":"HABITATION",
    "name:eng_x_preferred":[
        "Manasya"
    ],
    "wof:name":"Manasya",
    "wof:placetype":"locality",
    "wof:population":54
},
  "geometry": {"coordinates":[75.34663999999999,22.419263],"type":"Point"}
}