{
  "type": "Feature",
  "properties": {
    "gn:admin1_code":"19.0",
    "gn:admin2_code":"555.0",
    "gn:asciiname":"Basargi",
    "gn:country_code":"IN",
    "gn:dem":590,
    "gn:feature_class":"P",
    "gn:feature_code":"PPL",
    "gn:name":"Basargi",
    "gn:population":0,
    "gn:timezone":"Asia/Kolkata",
    "iso:country":"IN",
    "name:che_x_preferred":[
        "\u0411\u0430\u0441\u0430\u0440\u0433\u0438"
    ],
    "name:rus_x_preferred":[
        "\u0411\u0430\u0441\u0430\u0440\u0433\u0438"
    ],
    "wof:name":"Basargi",
    "wof:placetype":"locality"
},
  "geometry": {"coordinates":[75.17584000000002,15.89884],"type":"Point"}
}