{
  "type": "Feature",
  "properties": {
    "gn:admin1_code":"19",
    "gn:admin2_code":"559.0",
    "gn:asciiname":"Mittikellur",
    "gn:country_code":"IN",
    "gn:dem":511,
    "gn:feature_class":"P",
    "gn:feature_code":"PPL",
    "gn:name":"Mittikellur",
    "gn:population":0,
    "gn:timezone":"Asia/Kolkata",
    "iso:country":"IN",
    "wof:name":"Mittikellur",
    "wof:placetype":"locality"
},
  "geometry": {"coordinates":[76.53588000000001,16.0468],"type":"Point"}
}