{
  "type": "Feature",
  "properties": {
    "gn:admin1_code":"38.0",
    "gn:admin2_code":"351.0",
    "gn:asciiname":"Samda",
    "gn:country_code":"IN",
    "gn:dem":67,
    "gn:feature_class":"P",
    "gn:feature_code":"PPL",
    "gn:name":"S\u0101mda",
    "gn:population":0,
    "gn:timezone":"Asia/Kolkata",
    "iso:country":"IN",
    "ks:ks_alt_nam":"S\u0101mda",
    "ks:ks_name":"Samda",
    "ks:ks_type":"VILLAGE",
    "ks:ks_uagg_main":0,
    "name:eng_x_preferred":[
        "Samda"
    ],
    "name:eng_x_variant":[
        "S\u0101mda"
    ],
    "wof:name":"Samda",
    "wof:placetype":"neighbourhood"
},
  "geometry": {"coordinates":[87.272561,25.016178],"type":"Point"}
}