{
  "type": "Feature",
  "properties": {
    "iso:country":"IN",
    "ks:ks_name":"Meenpalam",
    "ks:ks_pop":650,
    "ks:ks_type":"HABITATION",
    "name:eng_x_preferred":[
        "Meenpalam"
    ],
    "wof:name":"Meenpalam",
    "wof:placetype":"locality",
    "wof:population":650
},
  "geometry": {"coordinates":[75.741395,11.593874],"type":"Point"}
}