{
  "type": "Feature",
  "properties": {
    "iso:country":"IN",
    "ks:ks_name":"Sarnada",
    "ks:ks_pop":842,
    "ks:ks_type":"HABITATION",
    "name:eng_x_preferred":[
        "Sarnada"
    ],
    "wof:name":"Sarnada",
    "wof:placetype":"locality",
    "wof:population":842
},
  "geometry": {"coordinates":[72.591672,27.161489],"type":"Point"}
}