{
  "type": "Feature",
  "properties": {
    "gn:admin1_code":"9.0",
    "gn:admin2_code":"484",
    "gn:asciiname":"Kajli",
    "gn:country_code":"IN",
    "gn:dem":123,
    "gn:feature_class":"P",
    "gn:feature_code":"PPL",
    "gn:name":"K\u0101jli",
    "gn:population":0,
    "gn:timezone":"Asia/Kolkata",
    "iso:country":"IN",
    "wof:name":"Kajli",
    "wof:placetype":"locality"
},
  "geometry": {"coordinates":[73.77124999999999,23.23508],"type":"Point"}
}