{
  "type": "Feature",
  "properties": {
    "iso:country":"IN",
    "ks:ks_name":"Tankjhiri",
    "ks:ks_pop":0,
    "ks:ks_type":"VILLAGE",
    "name:eng_x_preferred":[
        "Tankjhiri"
    ],
    "wof:name":"Tankjhiri",
    "wof:placetype":"locality",
    "wof:population":0
},
  "geometry": {"coordinates":[75.174826,22.518223],"type":"Point"}
}