{
  "type": "Feature",
  "properties": {
    "gn:admin1_code":"19.0",
    "gn:admin2_code":"584.0",
    "gn:asciiname":"Parvatanpalya",
    "gn:country_code":"IN",
    "gn:dem":917,
    "gn:feature_class":"P",
    "gn:feature_code":"PPL",
    "gn:name":"Parvatanp\u0101lya",
    "gn:population":0,
    "gn:timezone":"Asia/Kolkata",
    "iso:country":"IN",
    "ks:ks_name":"Parvathapalya",
    "ks:ks_pop":22,
    "ks:ks_type":"VILLAGE",
    "name:eng_x_preferred":[
        "Parvathapalya"
    ],
    "name:eng_x_variant":[
        "Parvatanpalya"
    ],
    "wof:name":"Parvathapalya",
    "wof:placetype":"locality",
    "wof:population":22
},
  "geometry": {"coordinates":[77.278395,13.075694],"type":"Point"}
}