{
  "type": "Feature",
  "properties": {
    "iso:country":"IN",
    "ks:ks_name":"Warghadwadi",
    "ks:ks_pop":45,
    "ks:ks_type":"HABITATION",
    "name:eng_x_preferred":[
        "Warghadwadi"
    ],
    "wof:name":"Warghadwadi",
    "wof:placetype":"locality",
    "wof:population":45
},
  "geometry": {"coordinates":[73.47441499999999,19.691018],"type":"Point"}
}