{
  "type": "Feature",
  "properties": {
    "gn:admin1_code":"17.0",
    "gn:admin2_code":"273",
    "gn:asciiname":"Khebuching",
    "gn:country_code":"IN",
    "gn:dem":755,
    "gn:feature_class":"P",
    "gn:feature_code":"PPL",
    "gn:name":"Khebuching",
    "gn:population":0,
    "gn:timezone":"Asia/Kolkata",
    "iso:country":"IN",
    "name:und_x_variant":[
        "Pochingmai",
        "Kheeuching",
        "Khebuching"
    ],
    "wof:name":"Khebuching",
    "wof:placetype":"locality"
},
  "geometry": {"coordinates":[93.51948,24.92963],"type":"Point"}
}