{
  "type": "Feature",
  "properties": {
    "gn:admin1_code":"23",
    "gn:admin2_code":"48.0",
    "gn:asciiname":"Pur",
    "gn:country_code":"IN",
    "gn:dem":255,
    "gn:feature_class":"P",
    "gn:feature_code":"PPL",
    "gn:name":"Pur",
    "gn:population":0,
    "gn:timezone":"Asia/Kolkata",
    "iso:country":"IN",
    "name:ara_x_preferred":[
        "\u0628\u0648\u0631"
    ],
    "name:ben_bn_x_preferred":[
        "\u09aa\u09c1\u09b0"
    ],
    "name:ben_in_x_preferred":[
        "\u09aa\u09c1\u09b0"
    ],
    "name:ceb_x_preferred":[
        "Pur"
    ],
    "name:deu_x_preferred":[
        "Pur"
    ],
    "name:fas_x_preferred":[
        "\u067e\u0648\u0631"
    ],
    "name:guj_x_preferred":[
        "\u0aaa\u0ac1\u0ab0"
    ],
    "name:hin_x_preferred":[
        "\u092a\u0941\u0930"
    ],
    "name:hun_x_preferred":[
        "Pur"
    ],
    "name:kan_x_preferred":[
        "\u0caa\u0cc1\u0cb0\u0ccd"
    ],
    "name:mal_x_preferred":[
        "\u0d2a\u0d41\u0d7c"
    ],
    "name:mar_x_preferred":[
        "\u092a\u0942\u0930"
    ],
    "name:pan_x_preferred":[
        "\u0a2a\u0a41\u0a30"
    ],
    "name:swe_x_preferred":[
        "Pur"
    ],
    "name:tam_x_preferred":[
        "\u0baa\u0bc2\u0bb0\u0bcd"
    ],
    "name:tel_x_preferred":[
        "\u0c2a\u0c42\u0c30\u0c4d"
    ],
    "name:urd_x_preferred":[
        "\u067e\u0631"
    ],
    "name:urd_x_variant":[
        "\u067e\u0648\u0631"
    ],
    "name:vie_x_preferred":[
        "S\u00f4ng Pur"
    ],
    "wof:name":"Pur",
    "wof:placetype":"locality"
},
  "geometry": {"coordinates":[76.55243,30.27152],"type":"Point"}
}