{
  "type": "Feature",
  "properties": {
    "iso:country":"IN",
    "ks:ks_name":"Theru Veedhi",
    "ks:ks_pop":145,
    "ks:ks_type":"HABITATION",
    "name:eng_x_preferred":[
        "Theru Veedhi"
    ],
    "wof:name":"Theru Veedhi",
    "wof:placetype":"locality",
    "wof:population":145
},
  "geometry": {"coordinates":[78.823989,13.630447],"type":"Point"}
}