{
  "type": "Feature",
  "properties": {
    "iso:country":"IN",
    "ks:ks_name":"27 PBN",
    "ks:ks_pop":32,
    "ks:ks_type":"VILLAGE",
    "name:eng_x_preferred":[
        "27 PBN"
    ],
    "wof:name":"27 PBN",
    "wof:placetype":"locality",
    "wof:population":32
},
  "geometry": {"coordinates":[73.908475,29.406147],"type":"Point"}
}