{
  "type": "Feature",
  "properties": {
    "gn:admin1_code":"16",
    "gn:admin2_code":"505.0",
    "gn:asciiname":"Dharmapuri",
    "gn:country_code":"IN",
    "gn:dem":277,
    "gn:feature_class":"P",
    "gn:feature_code":"PPL",
    "gn:name":"Dharm\u0101puri",
    "gn:population":0,
    "gn:timezone":"Asia/Kolkata",
    "iso:country":"IN",
    "name:bpy_x_preferred":[
        "\u09a7\u09b0\u09cd\u09ae\u09be\u09aa\u09c1\u09b0\u09bf"
    ],
    "name:ceb_x_preferred":[
        "Dharmapuri"
    ],
    "name:deu_x_preferred":[
        "Dharmapuri"
    ],
    "name:fra_x_preferred":[
        "Dharmapuri"
    ],
    "name:hin_x_preferred":[
        "\u0927\u0930\u094d\u092e\u092a\u0941\u0930\u0940"
    ],
    "name:ita_x_preferred":[
        "Dharmapuri"
    ],
    "name:jpn_x_preferred":[
        "\u30c0\u30eb\u30de\u30d7\u30ea"
    ],
    "name:mar_x_preferred":[
        "\u0927\u0930\u094d\u092e\u092a\u0941\u0930\u0940"
    ],
    "name:mlg_x_preferred":[
        "Dharmapuri"
    ],
    "name:msa_x_preferred":[
        "Dharmapuri"
    ],
    "name:nep_x_preferred":[
        "\u0927\u0930\u094d\u092e\u092a\u0941\u0930\u0940"
    ],
    "name:new_x_preferred":[
        "\u0927\u0930\u094d\u092e\u092a\u0941\u0930\u0940"
    ],
    "name:rus_x_preferred":[
        "\u0414\u0445\u0430\u0440\u043c\u0430\u043f\u0443\u0440\u0438"
    ],
    "name:san_x_preferred":[
        "\u0927\u0930\u094d\u092e\u092a\u0941\u0930\u0940"
    ],
    "name:spa_x_preferred":[
        "Dharmapuri"
    ],
    "name:swe_x_preferred":[
        "Dharmapuri"
    ],
    "name:tam_x_preferred":[
        "\u0ba4\u0bb0\u0bcd\u0bae\u0baa\u0bc1\u0bb0\u0bbf"
    ],
    "name:urd_x_preferred":[
        "\u062f\u06be\u0631\u0645 \u067e\u0648\u0631\u06cc"
    ],
    "name:vie_x_preferred":[
        "Dharmapuri"
    ],
    "name:zho_x_preferred":[
        "\u8fbe\u5c14\u9a6c\u666e\u91cc"
    ],
    "wof:name":"Dharmapuri",
    "wof:placetype":"locality"
},
  "geometry": {"coordinates":[79.50558000000002,21.27359],"type":"Point"}
}