{
  "type": "Feature",
  "properties": {
    "iso:country":"IN",
    "ks:ks_name":"Navapura",
    "ks:ks_pop":210,
    "ks:ks_type":"HABITATION",
    "name:eng_x_preferred":[
        "Navapura"
    ],
    "wof:name":"Navapura",
    "wof:placetype":"locality",
    "wof:population":210
},
  "geometry": {"coordinates":[72.454083,23.258083],"type":"Point"}
}