{
  "type": "Feature",
  "properties": {
    "gn:admin1_code":"19.0",
    "gn:admin2_code":"581.0",
    "gn:asciiname":"Hanumanaikanhalli",
    "gn:country_code":"IN",
    "gn:dem":907,
    "gn:feature_class":"P",
    "gn:feature_code":"PPL",
    "gn:name":"Hanuman\u0101ikanhalli",
    "gn:population":0,
    "gn:timezone":"Asia/Kolkata",
    "iso:country":"IN",
    "wof:name":"Hanumanaikanhalli",
    "wof:placetype":"locality"
},
  "geometry": {"coordinates":[77.91669,13.01496],"type":"Point"}
}