{
  "type": "Feature",
  "properties": {
    "iso:country":"IN",
    "ks:ks_alt_nam":"MANSHAHI TOLA",
    "ks:ks_name":"Manshahi Tola",
    "ks:ks_pop":428,
    "ks:ks_type":"HABITATION",
    "name:eng_x_preferred":[
        "Manshahi Tola"
    ],
    "wof:name":"Manshahi Tola",
    "wof:placetype":"locality",
    "wof:population":428
},
  "geometry": {"coordinates":[84.80265,25.19658],"type":"Point"}
}