{
  "type": "Feature",
  "properties": {
    "gn:admin1_code":"36.0",
    "gn:admin2_code":"176.0",
    "gn:asciiname":"Sardaha",
    "gn:country_code":"IN",
    "gn:dem":105,
    "gn:feature_class":"P",
    "gn:feature_code":"PPL",
    "gn:name":"Sardaha",
    "gn:population":0,
    "gn:timezone":"Asia/Kolkata",
    "iso:country":"IN",
    "ks:ks_name":"Sardaha",
    "ks:ks_type":"VILLAGE",
    "name:eng_x_preferred":[
        "Sardaha"
    ],
    "wof:name":"Sardaha",
    "wof:placetype":"locality"
},
  "geometry": {"coordinates":[81.514819,27.03573],"type":"Point"}
}