{
  "type": "Feature",
  "properties": {
    "iso:country":"IN",
    "ks:ks_name":"Bujon Ka Khera",
    "ks:ks_pop":281,
    "ks:ks_type":"HABITATION",
    "name:eng_x_preferred":[
        "Bujon Ka Khera"
    ],
    "wof:name":"Bujon Ka Khera",
    "wof:placetype":"locality",
    "wof:population":281
},
  "geometry": {"coordinates":[74.758408,23.648679],"type":"Point"}
}