{
  "type": "Feature",
  "properties": {
    "iso:country":"IN",
    "ks:ks_name":"Modambeda",
    "ks:ks_pop":96,
    "ks:ks_type":"HABITATION",
    "name:eng_x_preferred":[
        "Modambeda"
    ],
    "wof:name":"Modambeda",
    "wof:placetype":"locality",
    "wof:population":96
},
  "geometry": {"coordinates":[81.17230499999999,19.339326],"type":"Point"}
}