{
  "type": "Feature",
  "properties": {
    "iso:country":"IN",
    "ks:ks_alt_nam":"Ulh\u0101ra",
    "ks:ks_name":"Ulhara",
    "ks:ks_pop":347,
    "ks:ks_type":"VILLAGE",
    "name:eng_x_preferred":[
        "Ulhara"
    ],
    "name:eng_x_variant":[
        "Ulh\u0101ra"
    ],
    "wof:name":"Ulhara",
    "wof:placetype":"locality",
    "wof:population":347
},
  "geometry": {"coordinates":[85.526849,23.825649],"type":"Point"}
}