{
  "type": "Feature",
  "properties": {
    "iso:country":"IN",
    "ks:ks_name":"Trajpar",
    "ks:ks_pop":445,
    "ks:ks_type":"VILLAGE",
    "ks:ks_uagg_main":0,
    "name:eng_x_preferred":[
        "Trajpar"
    ],
    "wof:name":"Trajpar",
    "wof:placetype":"neighbourhood",
    "wof:population":445
},
  "geometry": {"coordinates":[70.81952800000001,22.821056],"type":"Point"}
}