{
  "type": "Feature",
  "properties": {
    "gn:admin1_code":"11.0",
    "gn:admin2_code":"33.0",
    "gn:asciiname":"Khuna",
    "gn:country_code":"IN",
    "gn:dem":1672,
    "gn:feature_class":"P",
    "gn:feature_code":"PPL",
    "gn:name":"Khuna",
    "gn:population":0,
    "gn:timezone":"Asia/Kolkata",
    "iso:country":"IN",
    "wof:name":"Khuna",
    "wof:placetype":"locality"
},
  "geometry": {"coordinates":[77.64140999999999,31.42732],"type":"Point"}
}