{
  "type": "Feature",
  "properties": {
    "iso:country":"IN",
    "ks:ks_name":"Kadavalli",
    "ks:ks_pop":104,
    "ks:ks_type":"HABITATION",
    "name:eng_x_preferred":[
        "Kadavalli"
    ],
    "wof:name":"Kadavalli",
    "wof:placetype":"locality",
    "wof:population":104
},
  "geometry": {"coordinates":[74.579182,14.410393],"type":"Point"}
}