{
  "type": "Feature",
  "properties": {
    "iso:country":"IN",
    "ks:ks_name":"Terdi",
    "ks:ks_pop":191,
    "ks:ks_type":"VILLAGE",
    "name:eng_x_preferred":[
        "Terdi"
    ],
    "wof:name":"Terdi",
    "wof:placetype":"locality",
    "wof:population":191
},
  "geometry": {"coordinates":[73.332644,17.993078],"type":"Point"}
}