{
  "type": "Feature",
  "properties": {
    "gn:admin1_code":"11.0",
    "gn:admin2_code":"32.0",
    "gn:asciiname":"Ghotari",
    "gn:country_code":"IN",
    "gn:dem":1923,
    "gn:feature_class":"P",
    "gn:feature_code":"PPL",
    "gn:name":"Ghot\u0101ri",
    "gn:population":0,
    "gn:timezone":"Asia/Kolkata",
    "iso:country":"IN",
    "wof:name":"Ghotari",
    "wof:placetype":"locality"
},
  "geometry": {"coordinates":[77.43267,30.94444],"type":"Point"}
}