{
  "type": "Feature",
  "properties": {
    "iso:country":"IN",
    "ks:ks_name":"Kuturugattu",
    "ks:ks_pop":483,
    "ks:ks_type":"HABITATION",
    "name:eng_x_preferred":[
        "Kuturugattu"
    ],
    "wof:name":"Kuturugattu",
    "wof:placetype":"locality",
    "wof:population":483
},
  "geometry": {"coordinates":[81.272362,17.708615],"type":"Point"}
}