{
  "type": "Feature",
  "properties": {
    "iso:country":"IN",
    "ks:ks_name":"Katabari",
    "ks:ks_pop":1631,
    "ks:ks_type":"VILLAGE",
    "ks:ks_uagg_main":0,
    "name:eng_x_preferred":[
        "Katabari"
    ],
    "wof:name":"Katabari",
    "wof:placetype":"neighbourhood",
    "wof:population":1631
},
  "geometry": {"coordinates":[88.480439,25.291345],"type":"Point"}
}