{
  "type": "Feature",
  "properties": {
    "gn:admin1_code":"16",
    "gn:admin2_code":"508.0",
    "gn:asciiname":"Warsa Kalan",
    "gn:country_code":"IN",
    "gn:dem":317,
    "gn:feature_class":"P",
    "gn:feature_code":"PPL",
    "gn:name":"Warsa Kal\u0101n",
    "gn:population":0,
    "gn:timezone":"Asia/Kolkata",
    "iso:country":"IN",
    "ks:ks_name":"Wadsakala",
    "ks:ks_pop":343,
    "ks:ks_type":"VILLAGE",
    "name:eng_x_preferred":[
        "Wadsakala"
    ],
    "name:eng_x_variant":[
        "Warsa Kalan"
    ],
    "wof:name":"Wadsakala",
    "wof:placetype":"locality",
    "wof:population":343
},
  "geometry": {"coordinates":[80.394417,20.032893],"type":"Point"}
}