{
  "type": "Feature",
  "properties": {
    "iso:country":"IN",
    "ks:ks_name":"Bantana Hakkalu",
    "ks:ks_pop":133,
    "ks:ks_type":"HABITATION",
    "name:eng_x_preferred":[
        "Bantana Hakkalu"
    ],
    "wof:name":"Bantana Hakkalu",
    "wof:placetype":"locality",
    "wof:population":133
},
  "geometry": {"coordinates":[74.93672100000001,14.179486],"type":"Point"}
}