{
  "type": "Feature",
  "properties": {
    "iso:country":"IN",
    "ks:ks_name":"Kasindipur",
    "ks:ks_pop":301,
    "ks:ks_type":"VILLAGE",
    "name:eng_x_preferred":[
        "Kasindipur"
    ],
    "wof:name":"Kasindipur",
    "wof:placetype":"locality",
    "wof:population":301
},
  "geometry": {"coordinates":[86.753209,20.982266],"type":"Point"}
}