{
  "type": "Feature",
  "properties": {
    "iso:country":"IN",
    "ks:ks_name":"Gittangi",
    "ks:ks_pop":244,
    "ks:ks_type":"VILLAGE",
    "name:eng_x_preferred":[
        "Gittangi"
    ],
    "wof:name":"Gittangi",
    "wof:placetype":"locality",
    "wof:population":244
},
  "geometry": {"coordinates":[84.150728,18.649811],"type":"Point"}
}