{
  "type": "Feature",
  "properties": {
    "iso:country":"IN",
    "ks:ks_name":"Sibhugli",
    "ks:ks_pop":2434,
    "ks:ks_type":"VILLAGE",
    "ks:ks_uagg_main":0,
    "name:eng_x_preferred":[
        "Sibhugli"
    ],
    "wof:name":"Sibhugli",
    "wof:placetype":"locality",
    "wof:population":2434
},
  "geometry": {"coordinates":[88.23101800000001,22.455076],"type":"Point"}
}