{
  "type": "Feature",
  "properties": {
    "iso:country":"IN",
    "ks:ks_name":"Kaanamadlu",
    "ks:ks_pop":12,
    "ks:ks_type":"HABITATION",
    "name:eng_x_preferred":[
        "Kaanamadlu"
    ],
    "wof:name":"Kaanamadlu",
    "wof:placetype":"locality",
    "wof:population":12
},
  "geometry": {"coordinates":[75.310208,13.420427],"type":"Point"}
}