{
  "type": "Feature",
  "properties": {
    "gn:admin1_code":"21.0",
    "gn:admin2_code":"371.0",
    "gn:asciiname":"Tareikela",
    "gn:country_code":"IN",
    "gn:dem":214,
    "gn:feature_class":"P",
    "gn:feature_code":"PPL",
    "gn:name":"Tareikela",
    "gn:population":0,
    "gn:timezone":"Asia/Kolkata",
    "iso:country":"IN",
    "wof:name":"Tareikela",
    "wof:placetype":"locality"
},
  "geometry": {"coordinates":[83.99204,21.76982000000001],"type":"Point"}
}