{
  "type": "Feature",
  "properties": {
    "iso:country":"IN",
    "ks:ks_name":"Tilmal",
    "ks:ks_pop":252,
    "ks:ks_type":"VILLAGE",
    "name:eng_x_preferred":[
        "Tilmal"
    ],
    "wof:name":"Tilmal",
    "wof:placetype":"locality",
    "wof:population":252
},
  "geometry": {"coordinates":[73.317716,19.694168],"type":"Point"}
}