{
  "type": "Feature",
  "properties": {
    "iso:country":"IN",
    "ks:ks_name":"Jamunia",
    "ks:ks_pop":80,
    "ks:ks_type":"HABITATION",
    "name:eng_x_preferred":[
        "Jamunia"
    ],
    "wof:name":"Jamunia",
    "wof:placetype":"locality",
    "wof:population":80
},
  "geometry": {"coordinates":[80.49463900000001,27.45874],"type":"Point"}
}