{
  "type": "Feature",
  "properties": {
    "gn:admin1_code":"36",
    "gn:admin2_code":"137.0",
    "gn:asciiname":"Chakanwala",
    "gn:country_code":"IN",
    "gn:dem":207,
    "gn:feature_class":"P",
    "gn:feature_code":"PPL",
    "gn:name":"Chakanw\u0101la",
    "gn:population":0,
    "gn:timezone":"Asia/Kolkata",
    "iso:country":"IN",
    "name:und_x_variant":[
        "Chakanw\u0101la",
        "Alluvial"
    ],
    "wof:name":"Chakanwala",
    "wof:placetype":"locality"
},
  "geometry": {"coordinates":[78.12958,28.90094],"type":"Point"}
}