{
  "type": "Feature",
  "properties": {
    "gn:admin1_code":"16.0",
    "gn:admin2_code":"497.0",
    "gn:asciiname":"Telkhadi",
    "gn:country_code":"IN",
    "gn:dem":479,
    "gn:feature_class":"P",
    "gn:feature_code":"PPL",
    "gn:name":"Telkhadi",
    "gn:population":0,
    "gn:timezone":"Asia/Kolkata",
    "iso:country":"IN",
    "wof:name":"Telkhadi",
    "wof:placetype":"locality"
},
  "geometry": {"coordinates":[74.31272,21.82106],"type":"Point"}
}