{
  "type": "Feature",
  "properties": {
    "gn:admin1_code":"16.0",
    "gn:admin2_code":"497.0",
    "gn:asciiname":"Telkhadi",
    "gn:country_code":"IN",
    "gn:dem":479,
    "gn:feature_class":"P",
    "gn:feature_code":"PPL",
    "gn:name":"Telkhadi",
    "gn:population":0,
    "gn:timezone":"Asia/Kolkata",
    "iso:country":"IN",
    "ks:ks_name":"Telkhedi",
    "ks:ks_pop":4062,
    "ks:ks_type":"HABITATION",
    "name:eng_x_preferred":[
        "Telkhedi"
    ],
    "name:eng_x_variant":[
        "Telkhadi"
    ],
    "wof:name":"Telkhedi",
    "wof:placetype":"locality",
    "wof:population":4062
},
  "geometry": {"coordinates":[74.318319,21.820937],"type":"Point"}
}