{
  "type": "Feature",
  "properties": {
    "iso:country":"IN",
    "ks:ks_alt_nam":"Kashiguri FV",
    "ks:ks_name":"Kashiguri Fv",
    "ks:ks_pop":577,
    "ks:ks_type":"HABITATION",
    "name:eng_x_preferred":[
        "Kashiguri Fv"
    ],
    "wof:name":"Kashiguri Fv",
    "wof:placetype":"locality",
    "wof:population":577
},
  "geometry": {"coordinates":[90.242519,26.58847],"type":"Point"}
}