{
  "type": "Feature",
  "properties": {
    "iso:country":"IN",
    "ks:ks_name":"Laxminarayanwadi",
    "ks:ks_pop":76,
    "ks:ks_type":"HABITATION",
    "ks:ks_uagg_main":0,
    "name:eng_x_preferred":[
        "Laxminarayanwadi"
    ],
    "wof:name":"Laxminarayanwadi",
    "wof:placetype":"neighbourhood",
    "wof:population":76
},
  "geometry": {"coordinates":[73.57646699999999,17.507689],"type":"Point"}
}