{
  "type": "Feature",
  "properties": {
    "iso:country":"IN",
    "ks:ks_name":"Hethbera",
    "ks:ks_pop":471,
    "ks:ks_type":"VILLAGE",
    "name:eng_x_preferred":[
        "Hethbera"
    ],
    "wof:name":"Hethbera",
    "wof:placetype":"locality",
    "wof:population":471
},
  "geometry": {"coordinates":[84.568731,23.781313],"type":"Point"}
}