{
  "type": "Feature",
  "properties": {
    "iso:country":"IN",
    "ks:ks_alt_nam":"PERODU",
    "ks:ks_name":"Perodu",
    "ks:ks_pop":1926,
    "ks:ks_type":"HABITATION",
    "name:eng_x_preferred":[
        "Perodu"
    ],
    "wof:name":"Perodu",
    "wof:placetype":"locality",
    "wof:population":1926
},
  "geometry": {"coordinates":[76.550865,10.555463],"type":"Point"}
}