{
  "type": "Feature",
  "properties": {
    "iso:country":"IN",
    "ks:ks_name":"Ratanpur",
    "ks:ks_pop":369,
    "ks:ks_type":"VILLAGE",
    "ks:ks_uagg_main":0,
    "name:eng_x_preferred":[
        "Ratanpur"
    ],
    "wof:name":"Ratanpur",
    "wof:placetype":"neighbourhood",
    "wof:population":369
},
  "geometry": {"coordinates":[87.712279,23.743179],"type":"Point"}
}