{
  "type": "Feature",
  "properties": {
    "gn:admin1_code":"21.0",
    "gn:admin2_code":"375.0",
    "gn:asciiname":"Anandapur",
    "gn:country_code":"IN",
    "gn:dem":48,
    "gn:feature_class":"P",
    "gn:feature_code":"PPL",
    "gn:name":"Anandapur",
    "gn:population":0,
    "gn:timezone":"Asia/Kolkata",
    "iso:country":"IN",
    "wof:name":"Anandapur",
    "wof:placetype":"locality"
},
  "geometry": {"coordinates":[86.11,21.21],"type":"Point"}
}