{
  "type": "Feature",
  "properties": {
    "gn:admin1_code":"21.0",
    "gn:admin2_code":"375.0",
    "gn:asciiname":"Anandapur",
    "gn:country_code":"IN",
    "gn:dem":48,
    "gn:feature_class":"P",
    "gn:feature_code":"PPL",
    "gn:name":"Anandapur",
    "gn:population":0,
    "gn:timezone":"Asia/Kolkata",
    "iso:country":"IN",
    "name:ben_x_preferred":[
        "\u0986\u09a8\u09a8\u09cd\u09a6\u09aa\u09c1\u09b0"
    ],
    "name:bpy_x_preferred":[
        "\u0986\u09a8\u09a8\u09cd\u09a6\u09aa\u09c1\u09b0"
    ],
    "name:deu_x_preferred":[
        "Anandapur"
    ],
    "name:fas_x_preferred":[
        "\u0627\u0646\u0627\u0646\u062f\u0627\u067e\u0648\u0631"
    ],
    "name:ind_x_preferred":[
        "Anandapur"
    ],
    "name:ita_x_preferred":[
        "Anandapur"
    ],
    "name:kan_x_preferred":[
        "\u0c85\u0ca8\u0c82\u0ca6\u0caa\u0cc1\u0cb0"
    ],
    "name:msa_x_preferred":[
        "Anandapur"
    ],
    "name:new_x_preferred":[
        "\u0906\u0928\u0928\u094d\u0926\u092a\u0941\u0930"
    ],
    "name:nld_x_preferred":[
        "Anandapur"
    ],
    "name:ori_x_preferred":[
        "\u0b06\u0b28\u0b28\u0b4d\u0b26\u0b2a\u0b41\u0b30"
    ],
    "name:pnb_x_preferred":[
        "\u0622\u0646\u0646\u062f\u0627\u067e\u0648\u0631\u0627"
    ],
    "name:por_x_preferred":[
        "Anandapur"
    ],
    "name:tam_x_preferred":[
        "\u0b85\u0ba9\u0ba8\u0bcd\u0ba4\u0bcd\u0baa\u0bc2\u0bb0\u0bcd"
    ],
    "name:vie_x_preferred":[
        "Anandapur"
    ],
    "name:zho_x_preferred":[
        "\u963f\u5357\u8fbe\u666e\u5c14"
    ],
    "wof:name":"Anandapur",
    "wof:placetype":"locality"
},
  "geometry": {"coordinates":[86.11,21.21],"type":"Point"}
}