{
  "type": "Feature",
  "properties": {
    "iso:country":"IN",
    "ks:ks_name":"Niz Bhabanipur",
    "ks:ks_pop":1914,
    "ks:ks_type":"VILLAGE",
    "ks:ks_uagg_main":0,
    "name:eng_x_preferred":[
        "Niz Bhabanipur"
    ],
    "wof:name":"Niz Bhabanipur",
    "wof:placetype":"neighbourhood",
    "wof:population":1914
},
  "geometry": {"coordinates":[91.070672,26.461697],"type":"Point"}
}