{
  "type": "Feature",
  "properties": {
    "iso:country":"IN",
    "ks:ks_name":"Bhaispuri",
    "ks:ks_pop":272,
    "ks:ks_type":"VILLAGE",
    "name:eng_x_preferred":[
        "Bhaispuri"
    ],
    "wof:name":"Bhaispuri",
    "wof:placetype":"locality",
    "wof:population":272
},
  "geometry": {"coordinates":[89.94427399999999,26.116568],"type":"Point"}
}