{
  "type": "Feature",
  "properties": {
    "iso:country":"IN",
    "ks:ks_name":"Tailorpura",
    "ks:ks_pop":315,
    "ks:ks_type":"HABITATION",
    "name:eng_x_preferred":[
        "Tailorpura"
    ],
    "wof:name":"Tailorpura",
    "wof:placetype":"locality",
    "wof:population":315
},
  "geometry": {"coordinates":[72.786333,22.436917],"type":"Point"}
}