{
  "type": "Feature",
  "properties": {
    "iso:country":"IN",
    "ks:ks_alt_nam":"N.Gadariya",
    "ks:ks_name":"N.gadariya",
    "ks:ks_pop":155,
    "ks:ks_type":"HABITATION",
    "ks:ks_uagg_main":0,
    "name:eng_x_preferred":[
        "N.gadariya"
    ],
    "wof:name":"N.gadariya",
    "wof:placetype":"neighbourhood",
    "wof:population":155
},
  "geometry": {"coordinates":[78.457567,27.58797],"type":"Point"}
}