{
  "type": "Feature",
  "properties": {
    "gn:admin1_code":"39.0",
    "gn:admin2_code":"64.0",
    "gn:asciiname":"Oliagaon",
    "gn:country_code":"IN",
    "gn:dem":1451,
    "gn:feature_class":"P",
    "gn:feature_code":"PPL",
    "gn:name":"Oliagaon",
    "gn:population":0,
    "gn:timezone":"Asia/Kolkata",
    "iso:country":"IN",
    "ks:ks_name":"Oliyagaon",
    "ks:ks_pop":188,
    "ks:ks_type":"VILLAGE",
    "name:eng_x_preferred":[
        "Oliyagaon"
    ],
    "name:eng_x_variant":[
        "Oliagaon"
    ],
    "wof:name":"Oliyagaon",
    "wof:placetype":"locality",
    "wof:population":188
},
  "geometry": {"coordinates":[79.532252,29.567001],"type":"Point"}
}