{
  "type": "Feature",
  "properties": {
    "gn:admin1_code":"39.0",
    "gn:admin2_code":"64.0",
    "gn:asciiname":"Oliagaon",
    "gn:country_code":"IN",
    "gn:dem":1451,
    "gn:feature_class":"P",
    "gn:feature_code":"PPL",
    "gn:name":"Oliagaon",
    "gn:population":0,
    "gn:timezone":"Asia/Kolkata",
    "iso:country":"IN",
    "wof:name":"Oliagaon",
    "wof:placetype":"locality"
},
  "geometry": {"coordinates":[79.53879999999999,29.56445],"type":"Point"}
}