{
  "type": "Feature",
  "properties": {
    "iso:country":"IN",
    "ks:ks_name":"Kovilthoppu",
    "ks:ks_pop":288,
    "ks:ks_type":"HABITATION",
    "name:eng_x_preferred":[
        "Kovilthoppu"
    ],
    "wof:name":"Kovilthoppu",
    "wof:placetype":"locality",
    "wof:population":288
},
  "geometry": {"coordinates":[79.68701,10.515435],"type":"Point"}
}