{
  "type": "Feature",
  "properties": {
    "gn:admin1_code":"24.0",
    "gn:admin2_code":"105.0",
    "gn:asciiname":"Nagla Chahra",
    "gn:country_code":"IN",
    "gn:dem":188,
    "gn:feature_class":"P",
    "gn:feature_code":"PPL",
    "gn:name":"Nagla Ch\u0101hra",
    "gn:population":0,
    "gn:timezone":"Asia/Kolkata",
    "iso:country":"IN",
    "ks:ks_alt_nam":"Nagla Ch\u0101hra",
    "ks:ks_name":"Nagla Chahra",
    "ks:ks_type":"VILLAGE",
    "name:eng_x_preferred":[
        "Nagla Chahra"
    ],
    "name:eng_x_variant":[
        "Nagla Ch\u0101hra"
    ],
    "wof:name":"Nagla Chahra",
    "wof:placetype":"locality"
},
  "geometry": {"coordinates":[77.29770000000001,27.742471],"type":"Point"}
}