{
  "type": "Feature",
  "properties": {
    "iso:country":"IN",
    "ks:ks_name":"Deopaniputa",
    "ks:ks_pop":473,
    "ks:ks_type":"HABITATION",
    "name:eng_x_preferred":[
        "Deopaniputa"
    ],
    "wof:name":"Deopaniputa",
    "wof:placetype":"locality",
    "wof:population":473
},
  "geometry": {"coordinates":[94.65120400000001,26.787128],"type":"Point"}
}