{
  "type": "Feature",
  "properties": {
    "iso:country":"IN",
    "ks:ks_name":"Murinjapuzha",
    "ks:ks_pop":1078,
    "ks:ks_type":"HABITATION",
    "name:eng_x_preferred":[
        "Murinjapuzha"
    ],
    "wof:name":"Murinjapuzha",
    "wof:placetype":"locality",
    "wof:population":1078
},
  "geometry": {"coordinates":[76.390418,9.819216],"type":"Point"}
}