{
  "type": "Feature",
  "properties": {
    "iso:country":"IN",
    "ks:ks_name":"Satsera Falia",
    "ks:ks_pop":944,
    "ks:ks_type":"HABITATION",
    "name:eng_x_preferred":[
        "Satsera Falia"
    ],
    "wof:name":"Satsera Falia",
    "wof:placetype":"locality",
    "wof:population":944
},
  "geometry": {"coordinates":[74.15297200000001,22.890806],"type":"Point"}
}