{
  "type": "Feature",
  "properties": {
    "iso:country":"IN",
    "ks:ks_name":"Barwadih Alias Koshiara",
    "ks:ks_pop":179,
    "ks:ks_type":"VILLAGE",
    "name:eng_x_preferred":[
        "Barwadih Alias Koshiara"
    ],
    "wof:name":"Barwadih Alias Koshiara",
    "wof:placetype":"locality",
    "wof:population":179
},
  "geometry": {"coordinates":[84.337219,24.341354],"type":"Point"}
}