{
  "type": "Feature",
  "properties": {
    "iso:country":"IN",
    "ks:ks_name":"Purba Basbari",
    "ks:ks_pop":189,
    "ks:ks_type":"VILLAGE",
    "name:eng_x_preferred":[
        "Purba Basbari"
    ],
    "wof:name":"Purba Basbari",
    "wof:placetype":"locality",
    "wof:population":189
},
  "geometry": {"coordinates":[90.41554499999999,26.611456],"type":"Point"}
}