{
  "type": "Feature",
  "properties": {
    "iso:country":"IN",
    "ks:ks_name":"Pajambadi",
    "ks:ks_pop":156,
    "ks:ks_type":"HABITATION",
    "name:eng_x_preferred":[
        "Pajambadi"
    ],
    "wof:name":"Pajambadi",
    "wof:placetype":"locality",
    "wof:population":156
},
  "geometry": {"coordinates":[75.08149400000001,13.040288],"type":"Point"}
}