{
  "type": "Feature",
  "properties": {
    "gn:admin1_code":"12.0",
    "gn:admin2_code":"008",
    "gn:asciiname":"Lariangan",
    "gn:country_code":"IN",
    "gn:dem":2034,
    "gn:feature_class":"P",
    "gn:feature_code":"PPL",
    "gn:name":"Lari\u0101ngan",
    "gn:population":0,
    "gn:timezone":"Asia/Kolkata",
    "iso:country":"IN",
    "wof:name":"Lariangan",
    "wof:placetype":"locality"
},
  "geometry": {"coordinates":[74.24422,34.25237],"type":"Point"}
}