{
  "type": "Feature",
  "properties": {
    "iso:country":"IN",
    "ks:ks_name":"Bantanda",
    "ks:ks_pop":230,
    "ks:ks_type":"HABITATION",
    "name:eng_x_preferred":[
        "Bantanda"
    ],
    "wof:name":"Bantanda",
    "wof:placetype":"locality",
    "wof:population":230
},
  "geometry": {"coordinates":[75.53496699999999,17.45085],"type":"Point"}
}