{
  "type": "Feature",
  "properties": {
    "gn:admin1_code":"40",
    "gn:admin2_code":"534.0",
    "gn:asciiname":"Dacharam",
    "gn:country_code":"IN",
    "gn:dem":417,
    "gn:feature_class":"P",
    "gn:feature_code":"PPL",
    "gn:name":"Dach\u0101ram",
    "gn:population":0,
    "gn:timezone":"Asia/Kolkata",
    "iso:country":"IN",
    "wof:name":"Dacharam",
    "wof:placetype":"locality"
},
  "geometry": {"coordinates":[78.84593000000002,18.2646],"type":"Point"}
}