{
  "type": "Feature",
  "properties": {
    "gn:admin1_code":"2.0",
    "gn:asciiname":"Reddigaripalli",
    "gn:country_code":"IN",
    "gn:dem":616,
    "gn:feature_class":"P",
    "gn:feature_code":"PPL",
    "gn:name":"Reddig\u0101ripalli",
    "gn:population":0,
    "gn:timezone":"Asia/Kolkata",
    "iso:country":"IN",
    "ks:ks_name":"Reddiganapalli",
    "ks:ks_pop":92,
    "ks:ks_type":"HABITATION",
    "name:eng_x_preferred":[
        "Reddiganapalli"
    ],
    "name:eng_x_variant":[
        "Reddigaripalli"
    ],
    "wof:name":"Reddiganapalli",
    "wof:placetype":"locality",
    "wof:population":92
},
  "geometry": {"coordinates":[78.09634699999999,13.861781],"type":"Point"}
}