{
  "type": "Feature",
  "properties": {
    "gn:admin1_code":"13.0",
    "gn:admin2_code":"591.0",
    "gn:asciiname":"Munnamkai",
    "gn:country_code":"IN",
    "gn:dem":29,
    "gn:feature_class":"P",
    "gn:feature_code":"PPL",
    "gn:name":"M\u016bnnamkai",
    "gn:population":0,
    "gn:timezone":"Asia/Kolkata",
    "iso:country":"IN",
    "wof:name":"Munnamkai",
    "wof:placetype":"locality"
},
  "geometry": {"coordinates":[75.78468000000002,11.67942],"type":"Point"}
}