{
  "type": "Feature",
  "properties": {
    "iso:country":"IN",
    "ks:ks_name":"Karkur",
    "ks:ks_type":"VILLAGE",
    "name:eng_x_preferred":[
        "Karkur"
    ],
    "wof:name":"Karkur",
    "wof:placetype":"locality"
},
  "geometry": {"coordinates":[76.251841,16.17868],"type":"Point"}
}