{
  "type": "Feature",
  "properties": {
    "iso:country":"IN",
    "ks:ks_name":"Berke Kanajar",
    "ks:ks_pop":205,
    "ks:ks_type":"HABITATION",
    "name:eng_x_preferred":[
        "Berke Kanajar"
    ],
    "wof:name":"Berke Kanajar",
    "wof:placetype":"locality",
    "wof:population":205
},
  "geometry": {"coordinates":[75.031419,13.206942],"type":"Point"}
}