{
  "type": "Feature",
  "properties": {
    "gn:admin1_code":"37",
    "gn:admin2_code":"410.0",
    "gn:asciiname":"Bhatapara",
    "gn:country_code":"IN",
    "gn:dem":277,
    "gn:feature_class":"P",
    "gn:feature_code":"PPL",
    "gn:name":"Bh\u0101t\u0101p\u0101ra",
    "gn:population":0,
    "gn:timezone":"Asia/Kolkata",
    "iso:country":"IN",
    "name:ben_x_preferred":[
        "\u09ad\u09be\u09a4\u09be\u09aa\u09be\u09b0\u09be"
    ],
    "name:bpy_x_preferred":[
        "\u09ad\u09be\u09a4\u09be\u09aa\u09be\u09b0\u09be"
    ],
    "name:ceb_x_preferred":[
        "Bh\u0101t\u0101p\u0101ra"
    ],
    "name:ita_x_preferred":[
        "Bhatapara"
    ],
    "name:msa_x_preferred":[
        "Bhatapara"
    ],
    "name:new_x_preferred":[
        "\u092d\u091f\u092a\u0930\u093e"
    ],
    "name:ori_x_preferred":[
        "\u0b2d\u0b3e\u0b24\u0b2a\u0b3e\u0b30\u0b3e"
    ],
    "name:por_x_preferred":[
        "Bhatapara"
    ],
    "name:swe_x_preferred":[
        "Bh\u0101t\u0101p\u0101ra"
    ],
    "name:urd_x_preferred":[
        "\u0628\u06be\u0627\u0679\u0627\u067e\u0627\u0631\u0627"
    ],
    "name:vie_x_preferred":[
        "Bhatapara"
    ],
    "name:zho_x_preferred":[
        "\u5df4\u5854\u5e15\u62c9"
    ],
    "wof:name":"Bhatapara",
    "wof:placetype":"locality"
},
  "geometry": {"coordinates":[81.82847,21.66418],"type":"Point"}
}