{
  "type": "Feature",
  "properties": {
    "iso:country":"IN",
    "ks:ks_name":"Kundil Chapori",
    "ks:ks_pop":206,
    "ks:ks_type":"HABITATION",
    "name:eng_x_preferred":[
        "Kundil Chapori"
    ],
    "wof:name":"Kundil Chapori",
    "wof:placetype":"locality",
    "wof:population":206
},
  "geometry": {"coordinates":[95.745728,27.862623],"type":"Point"}
}