{
  "type": "Feature",
  "properties": {
    "gn:admin1_code":"36",
    "gn:admin2_code":"181.0",
    "gn:asciiname":"Bathoi Purwa",
    "gn:country_code":"IN",
    "gn:dem":124,
    "gn:feature_class":"P",
    "gn:feature_code":"PPL",
    "gn:name":"Bathoi Purwa",
    "gn:population":0,
    "gn:timezone":"Asia/Kolkata",
    "iso:country":"IN",
    "ks:ks_name":"Batohi Purwa",
    "ks:ks_pop":51,
    "ks:ks_type":"HABITATION",
    "ks:ks_uagg_main":0,
    "name:eng_x_preferred":[
        "Batohi Purwa"
    ],
    "wof:name":"Batohi Purwa",
    "wof:placetype":"neighbourhood",
    "wof:population":51
},
  "geometry": {"coordinates":[81.75358300000001,27.586249],"type":"Point"}
}