{
  "type": "Feature",
  "properties": {
    "iso:country":"IN",
    "ks:ks_name":"Surjanpur",
    "ks:ks_pop":0,
    "ks:ks_type":"VILLAGE",
    "name:eng_x_preferred":[
        "Surjanpur"
    ],
    "wof:name":"Surjanpur",
    "wof:placetype":"locality",
    "wof:population":0
},
  "geometry": {"coordinates":[83.192831,25.167955],"type":"Point"}
}