{
  "type": "Feature",
  "properties": {
    "iso:country":"IN",
    "ks:ks_name":"Chataranga",
    "ks:ks_pop":1283,
    "ks:ks_type":"HABITATION",
    "name:eng_x_preferred":[
        "Chataranga"
    ],
    "wof:name":"Chataranga",
    "wof:placetype":"locality",
    "wof:population":1283
},
  "geometry": {"coordinates":[82.83206300000001,20.387497],"type":"Point"}
}