{
  "type": "Feature",
  "properties": {
    "gn:country":"IN",
    "gn:fcode":"PPL",
    "gn:pop":59170,
    "iso:country":"IN",
    "name:tel_x_preferred":[
        "\u0c15\u0c4b\u0c21\u0c42\u0c30\u0c41"
    ],
    "name:vie_x_preferred":[
        "Koduru"
    ],
    "qs:name":"Kodur",
    "qs:name_adm0":"India",
    "qs:name_adm1":"Andhra Pradesh",
    "qs:photos_9r":0,
    "qs:photos_sr":0,
    "qs:placetype":"Town",
    "qs:pop_sr":"8",
    "wd:wordcount":100,
    "wof:name":"Kodur",
    "wof:placetype":"locality",
    "wof:population":59170
},
  "geometry": {"coordinates":[79.96559999999999,16.9985],"type":"Point"}
}