{
  "type": "Feature",
  "properties": {
    "iso:country":"IN",
    "ks:ks_name":"Poch Basti",
    "ks:ks_pop":371,
    "ks:ks_type":"HABITATION",
    "name:eng_x_preferred":[
        "Poch Basti"
    ],
    "wof:name":"Poch Basti",
    "wof:placetype":"locality",
    "wof:population":371
},
  "geometry": {"coordinates":[87.86935099999999,26.192884],"type":"Point"}
}