{
  "type": "Feature",
  "properties": {
    "iso:country":"IN",
    "ks:ks_alt_nam":"ooralikkudy",
    "ks:ks_name":"Ooralikkudy",
    "ks:ks_pop":825,
    "ks:ks_type":"HABITATION",
    "name:eng_x_preferred":[
        "Ooralikkudy"
    ],
    "wof:name":"Ooralikkudy",
    "wof:placetype":"locality",
    "wof:population":825
},
  "geometry": {"coordinates":[76.849024,9.856561],"type":"Point"}
}