{
  "type": "Feature",
  "properties": {
    "gn:admin1_code":"36.0",
    "gn:admin2_code":"142.0",
    "gn:asciiname":"Nagla Jit",
    "gn:country_code":"IN",
    "gn:dem":207,
    "gn:feature_class":"P",
    "gn:feature_code":"PPL",
    "gn:name":"Nagla J\u012bt",
    "gn:population":0,
    "gn:timezone":"Asia/Kolkata",
    "iso:country":"IN",
    "wof:name":"Nagla Jit",
    "wof:placetype":"neighbourhood"
},
  "geometry": {"coordinates":[77.91580999999999,28.51478],"type":"Point"}
}