{
  "type": "Feature",
  "properties": {
    "iso:country":"IN",
    "ks:ks_name":"Geesada Pamula",
    "ks:ks_pop":221,
    "ks:ks_type":"HABITATION",
    "name:eng_x_preferred":[
        "Geesada Pamula"
    ],
    "wof:name":"Geesada Pamula",
    "wof:placetype":"locality",
    "wof:population":221
},
  "geometry": {"coordinates":[83.559403,19.019038],"type":"Point"}
}