{
  "type": "Feature",
  "properties": {
    "iso:country":"IN",
    "ks:ks_name":"Rangapara",
    "ks:ks_pop":139,
    "ks:ks_type":"HABITATION",
    "name:eng_x_preferred":[
        "Rangapara"
    ],
    "wof:name":"Rangapara",
    "wof:placetype":"locality",
    "wof:population":139
},
  "geometry": {"coordinates":[83.913571,22.304421],"type":"Point"}
}