{
  "type": "Feature",
  "properties": {
    "iso:country":"IN",
    "ks:ks_name":"Roonjiya",
    "ks:ks_pop":523,
    "ks:ks_type":"HABITATION",
    "name:eng_x_preferred":[
        "Roonjiya"
    ],
    "wof:name":"Roonjiya",
    "wof:placetype":"locality",
    "wof:population":523
},
  "geometry": {"coordinates":[74.72890599999999,23.541953],"type":"Point"}
}