{
  "type": "Feature",
  "properties": {
    "iso:country":"IN",
    "ks:ks_name":"Wazidpur",
    "ks:ks_pop":1766,
    "ks:ks_type":"VILLAGE",
    "ks:ks_uagg_main":0,
    "name:eng_x_preferred":[
        "Wazidpur"
    ],
    "wof:name":"Wazidpur",
    "wof:placetype":"neighbourhood",
    "wof:population":1766
},
  "geometry": {"coordinates":[78.48868299999999,29.272547],"type":"Point"}
}