{
  "type": "Feature",
  "properties": {
    "iso:country":"IN",
    "ks:ks_name":"Hariharpur",
    "ks:ks_pop":637,
    "ks:ks_type":"HABITATION",
    "ks:ks_uagg_main":0,
    "name:eng_x_preferred":[
        "Hariharpur"
    ],
    "wof:name":"Hariharpur",
    "wof:placetype":"neighbourhood",
    "wof:population":637
},
  "geometry": {"coordinates":[80.146147,27.546621],"type":"Point"}
}