{
  "type": "Feature",
  "properties": {
    "iso:country":"IN",
    "ks:ks_name":"Baudhawadi",
    "ks:ks_pop":66,
    "ks:ks_type":"HABITATION",
    "name:eng_x_preferred":[
        "Baudhawadi"
    ],
    "wof:name":"Baudhawadi",
    "wof:placetype":"locality",
    "wof:population":66
},
  "geometry": {"coordinates":[73.292272,17.844778],"type":"Point"}
}