{
  "type": "Feature",
  "properties": {
    "gn:admin1_code":"21.0",
    "gn:admin2_code":"370.0",
    "gn:asciiname":"Purna",
    "gn:country_code":"IN",
    "gn:dem":191,
    "gn:feature_class":"P",
    "gn:feature_code":"PPL",
    "gn:name":"Purna",
    "gn:population":0,
    "gn:timezone":"Asia/Kolkata",
    "iso:country":"IN",
    "name:ben_x_preferred":[
        "\u09aa\u09c1\u09b0\u09cd\u09a8\u09be"
    ],
    "name:bpy_x_preferred":[
        "\u09aa\u09c1\u09b0\u09cd\u09a8\u09be"
    ],
    "name:cat_x_preferred":[
        "Purna"
    ],
    "name:ceb_x_preferred":[
        "P\u016brna"
    ],
    "name:hin_x_preferred":[
        "\u092a\u0941\u0930\u094d\u0923\u093e"
    ],
    "name:ita_x_preferred":[
        "Purna"
    ],
    "name:mar_x_preferred":[
        "\u092a\u0941\u0930\u094d\u0923\u093e"
    ],
    "name:msa_x_preferred":[
        "Purna"
    ],
    "name:nld_x_preferred":[
        "Purna"
    ],
    "name:ori_x_preferred":[
        "\u0b2a\u0b41\u0b30\u0b4d\u0b28\u0b3e"
    ],
    "name:por_x_preferred":[
        "Purna"
    ],
    "name:swe_x_preferred":[
        "P\u016brna"
    ],
    "name:urd_x_preferred":[
        "\u067e\u0631\u0646\u0627"
    ],
    "name:vie_x_preferred":[
        "Purna"
    ],
    "name:zho_x_preferred":[
        "\u666e\u5c14\u7eb3"
    ],
    "wof:name":"Purna",
    "wof:placetype":"locality"
},
  "geometry": {"coordinates":[83.51102,21.21513],"type":"Point"}
}