{
  "type": "Feature",
  "properties": {
    "gn:admin1_code":"21.0",
    "gn:admin2_code":"370.0",
    "gn:asciiname":"Purna",
    "gn:country_code":"IN",
    "gn:dem":191,
    "gn:feature_class":"P",
    "gn:feature_code":"PPL",
    "gn:name":"Purna",
    "gn:population":0,
    "gn:timezone":"Asia/Kolkata",
    "iso:country":"IN",
    "wof:name":"Purna",
    "wof:placetype":"locality"
},
  "geometry": {"coordinates":[83.51102,21.21513],"type":"Point"}
}