{
  "type": "Feature",
  "properties": {
    "iso:country":"IN",
    "ks:ks_alt_nam":"PURA PARVAJPUR",
    "ks:ks_name":"Pura Parvajpur",
    "ks:ks_pop":895,
    "ks:ks_type":"HABITATION",
    "name:eng_x_preferred":[
        "Pura Parvajpur"
    ],
    "wof:name":"Pura Parvajpur",
    "wof:placetype":"locality",
    "wof:population":895
},
  "geometry": {"coordinates":[81.61108299999999,26.555588],"type":"Point"}
}