{
  "type": "Feature",
  "properties": {
    "gn:admin1_code":"35",
    "gn:admin2_code":"447.0",
    "gn:asciiname":"Sanvarida",
    "gn:country_code":"IN",
    "gn:dem":497,
    "gn:feature_class":"P",
    "gn:feature_code":"PPL",
    "gn:name":"S\u0101nvarida",
    "gn:population":0,
    "gn:timezone":"Asia/Kolkata",
    "iso:country":"IN",
    "ks:ks_alt_nam":"S\u0101nvarida",
    "ks:ks_name":"Sanvarida",
    "ks:ks_type":"VILLAGE",
    "name:eng_x_preferred":[
        "Sanvarida"
    ],
    "name:eng_x_variant":[
        "S\u0101nvarida"
    ],
    "wof:name":"Sanvarida",
    "wof:placetype":"locality"
},
  "geometry": {"coordinates":[77.69627199999999,22.300255],"type":"Point"}
}