{
  "type": "Feature",
  "properties": {
    "gn:admin1_code":"37",
    "gn:admin2_code":"410.0",
    "gn:asciiname":"Sondongri",
    "gn:country_code":"IN",
    "gn:dem":285,
    "gn:feature_class":"P",
    "gn:feature_code":"PPL",
    "gn:name":"Sondongri",
    "gn:population":0,
    "gn:timezone":"Asia/Kolkata",
    "iso:country":"IN",
    "ks:ks_name":"Sondongri",
    "ks:ks_type":"VILLAGE",
    "ks:ks_uagg_main":0,
    "name:eng_x_preferred":[
        "Sondongri"
    ],
    "wof:name":"Sondongri",
    "wof:placetype":"locality"
},
  "geometry": {"coordinates":[81.594652,21.277729],"type":"Point"}
}