{
  "type": "Feature",
  "properties": {
    "iso:country":"IN",
    "qs:name":"Badgaon",
    "qs:name_adm0":"India",
    "qs:name_adm1":"Maharashtra",
    "qs:photos":1,
    "qs:photos_1k":1,
    "qs:photos_9k":1,
    "qs:photos_9r":1,
    "qs:photos_all":1,
    "qs:photos_sr":1,
    "qs:placetype":"Suburb",
    "qs:pop_sr":"0",
    "wd:wordcount":35,
    "wof:name":"Badgaon",
    "wof:placetype":"neighbourhood"
},
  "geometry": {"coordinates":[73.853843,18.531709],"type":"Point"}
}