{
  "type": "Feature",
  "properties": {
    "iso:country":"IN",
    "ks:ks_name":"Hasimane",
    "ks:ks_pop":121,
    "ks:ks_type":"HABITATION",
    "name:eng_x_preferred":[
        "Hasimane"
    ],
    "wof:name":"Hasimane",
    "wof:placetype":"locality",
    "wof:population":121
},
  "geometry": {"coordinates":[74.526353,14.264527],"type":"Point"}
}