{
  "type": "Feature",
  "properties": {
    "gn:admin1_code":"34.0",
    "gn:admin2_code":"212.0",
    "gn:asciiname":"Samaikol",
    "gn:country_code":"IN",
    "gn:dem":37,
    "gn:feature_class":"P",
    "gn:feature_code":"PPL",
    "gn:name":"Samaikol",
    "gn:population":0,
    "gn:timezone":"Asia/Kolkata",
    "iso:country":"IN",
    "ks:ks_name":"Samaikol",
    "ks:ks_pop":548,
    "ks:ks_type":"VILLAGE",
    "ks:ks_uagg_main":0,
    "name:eng_x_preferred":[
        "Samaikol"
    ],
    "wof:name":"Samaikol",
    "wof:placetype":"neighbourhood",
    "wof:population":548
},
  "geometry": {"coordinates":[87.919658,25.549499],"type":"Point"}
}