{
  "type": "Feature",
  "properties": {
    "iso:country":"IN",
    "ks:ks_name":"Saidni",
    "ks:ks_type":"VILLAGE",
    "name:eng_x_preferred":[
        "Saidni"
    ],
    "wof:name":"Saidni",
    "wof:placetype":"locality"
},
  "geometry": {"coordinates":[77.867683,20.364202],"type":"Point"}
}