{
  "type": "Feature",
  "properties": {
    "iso:country":"IN",
    "ks:ks_name":"Saravanapuram",
    "ks:ks_pop":54,
    "ks:ks_type":"HABITATION",
    "name:eng_x_preferred":[
        "Saravanapuram"
    ],
    "wof:name":"Saravanapuram",
    "wof:placetype":"locality",
    "wof:population":54
},
  "geometry": {"coordinates":[79.39676799999999,12.205763],"type":"Point"}
}