{
  "type": "Feature",
  "properties": {
    "iso:country":"IN",
    "ks:ks_name":"Mulgam Falia",
    "ks:ks_pop":68,
    "ks:ks_type":"HABITATION",
    "name:eng_x_preferred":[
        "Mulgam Falia"
    ],
    "wof:name":"Mulgam Falia",
    "wof:placetype":"locality",
    "wof:population":68
},
  "geometry": {"coordinates":[73.18830199999999,20.318189],"type":"Point"}
}