{
  "type": "Feature",
  "properties": {
    "gn:admin1_code":"24.0",
    "gn:admin2_code":"110.0",
    "gn:asciiname":"Bisori",
    "gn:country_code":"IN",
    "gn:dem":410,
    "gn:feature_class":"P",
    "gn:feature_code":"PPL",
    "gn:name":"Bisori",
    "gn:population":0,
    "gn:timezone":"Asia/Kolkata",
    "iso:country":"IN",
    "wof:name":"Bisori",
    "wof:placetype":"locality"
},
  "geometry": {"coordinates":[75.97988000000002,27.07122],"type":"Point"}
}