{
  "type": "Feature",
  "properties": {
    "iso:country":"IN",
    "ks:ks_name":"Salwaniya",
    "ks:ks_pop":337,
    "ks:ks_type":"HABITATION",
    "name:eng_x_preferred":[
        "Salwaniya"
    ],
    "wof:name":"Salwaniya",
    "wof:placetype":"locality",
    "wof:population":337
},
  "geometry": {"coordinates":[74.80778599999999,23.497531],"type":"Point"}
}