{
  "type": "Feature",
  "properties": {
    "iso:country":"IN",
    "ks:ks_name":"Bhur",
    "ks:ks_pop":300,
    "ks:ks_type":"VILLAGE",
    "name:eng_x_preferred":[
        "Bhur"
    ],
    "wof:name":"Bhur",
    "wof:placetype":"locality",
    "wof:population":300
},
  "geometry": {"coordinates":[85.199461,22.719935],"type":"Point"}
}