{
  "type": "Feature",
  "properties": {
    "iso:country":"IN",
    "ks:ks_name":"Dhobi Tola",
    "ks:ks_pop":113,
    "ks:ks_type":"HABITATION",
    "name:eng_x_preferred":[
        "Dhobi Tola"
    ],
    "wof:name":"Dhobi Tola",
    "wof:placetype":"locality",
    "wof:population":113
},
  "geometry": {"coordinates":[86.77707100000001,25.981741],"type":"Point"}
}