{
  "type": "Feature",
  "properties": {
    "gn:admin1_code":"2.0",
    "gn:admin2_code":"554.0",
    "gn:asciiname":"Erragondipalle",
    "gn:country_code":"IN",
    "gn:dem":503,
    "gn:feature_class":"P",
    "gn:feature_code":"PPL",
    "gn:name":"Erragondipalle",
    "gn:population":0,
    "gn:timezone":"Asia/Kolkata",
    "iso:country":"IN",
    "wof:name":"Erragondipalle",
    "wof:placetype":"neighbourhood"
},
  "geometry": {"coordinates":[78.41359,13.86173],"type":"Point"}
}