{
  "type": "Feature",
  "properties": {
    "gn:admin1_code":"23.0",
    "gn:admin2_code":"35.0",
    "gn:asciiname":"Pairowal",
    "gn:country_code":"IN",
    "gn:dem":245,
    "gn:feature_class":"P",
    "gn:feature_code":"PPL",
    "gn:name":"Pairow\u0101l",
    "gn:population":0,
    "gn:timezone":"Asia/Kolkata",
    "iso:country":"IN",
    "wof:name":"Pairowal",
    "wof:placetype":"locality"
},
  "geometry": {"coordinates":[75.18259999999999,31.98424],"type":"Point"}
}