{
  "type": "Feature",
  "properties": {
    "iso:country":"IN",
    "ks:ks_name":"Gadkebala",
    "ks:ks_pop":253,
    "ks:ks_type":"HABITATION",
    "name:eng_x_preferred":[
        "Gadkebala"
    ],
    "wof:name":"Gadkebala",
    "wof:placetype":"locality",
    "wof:population":253
},
  "geometry": {"coordinates":[74.261363,14.880144],"type":"Point"}
}