{
  "type": "Feature",
  "properties": {
    "iso:country":"IN",
    "ks:ks_name":"Thekkummuri",
    "ks:ks_pop":1552,
    "ks:ks_type":"HABITATION",
    "name:eng_x_preferred":[
        "Thekkummuri"
    ],
    "wof:name":"Thekkummuri",
    "wof:placetype":"locality",
    "wof:population":1552
},
  "geometry": {"coordinates":[75.65773,11.763394],"type":"Point"}
}