{
  "type": "Feature",
  "properties": {
    "iso:country":"IN",
    "ks:ks_name":"Partappur Jagir",
    "ks:ks_pop":296,
    "ks:ks_type":"VILLAGE",
    "ks:ks_uagg_main":0,
    "name:eng_x_preferred":[
        "Partappur Jagir"
    ],
    "wof:name":"Partappur Jagir",
    "wof:placetype":"neighbourhood",
    "wof:population":296
},
  "geometry": {"coordinates":[87.40392,25.128195],"type":"Point"}
}