{
  "type": "Feature",
  "properties": {
    "iso:country":"IN",
    "ks:ks_alt_nam":"CHAMRAHI",
    "ks:ks_name":"Chamrahi",
    "ks:ks_pop":158,
    "ks:ks_type":"HABITATION",
    "name:eng_x_preferred":[
        "Chamrahi"
    ],
    "wof:name":"Chamrahi",
    "wof:placetype":"locality",
    "wof:population":158
},
  "geometry": {"coordinates":[81.147955,26.993255],"type":"Point"}
}