{
  "type": "Feature",
  "properties": {
    "iso:country":"IN",
    "ks:ks_name":"Maruthabacheri",
    "ks:ks_pop":109,
    "ks:ks_type":"HABITATION",
    "name:eng_x_preferred":[
        "Maruthabacheri"
    ],
    "wof:name":"Maruthabacheri",
    "wof:placetype":"locality",
    "wof:population":109
},
  "geometry": {"coordinates":[78.844858,9.590644],"type":"Point"}
}