{
  "type": "Feature",
  "properties": {
    "iso:country":"IN",
    "ks:ks_name":"Kasumbariya",
    "ks:ks_pop":187,
    "ks:ks_type":"VILLAGE",
    "ks:ks_uagg_main":0,
    "name:eng_x_preferred":[
        "Kasumbariya"
    ],
    "wof:name":"Kasumbariya",
    "wof:placetype":"neighbourhood",
    "wof:population":187
},
  "geometry": {"coordinates":[74.02038899999999,23.374463],"type":"Point"}
}