{
  "type": "Feature",
  "properties": {
    "iso:country":"IN",
    "ks:ks_name":"Balingia",
    "ks:ks_pop":36,
    "ks:ks_type":"VILLAGE",
    "name:eng_x_preferred":[
        "Balingia"
    ],
    "wof:name":"Balingia",
    "wof:placetype":"locality",
    "wof:population":36
},
  "geometry": {"coordinates":[84.310164,20.02461],"type":"Point"}
}