{
  "type": "Feature",
  "properties": {
    "iso:country":"IN",
    "ks:ks_alt_nam":"Aratal tota",
    "ks:ks_name":"Aratal Tota",
    "ks:ks_pop":142,
    "ks:ks_type":"HABITATION",
    "name:eng_x_preferred":[
        "Aratal Tota"
    ],
    "wof:name":"Aratal Tota",
    "wof:placetype":"locality",
    "wof:population":142
},
  "geometry": {"coordinates":[75.227298,16.760107],"type":"Point"}
}