{
  "type": "Feature",
  "properties": {
    "iso:country":"IN",
    "ks:ks_name":"Bramhanwadi",
    "ks:ks_pop":69,
    "ks:ks_type":"HABITATION",
    "name:eng_x_preferred":[
        "Bramhanwadi"
    ],
    "wof:name":"Bramhanwadi",
    "wof:placetype":"locality",
    "wof:population":69
},
  "geometry": {"coordinates":[73.816239,16.684351],"type":"Point"}
}