{
  "type": "Feature",
  "properties": {
    "iso:country":"IN",
    "ks:ks_name":"Mohammad Nagar Chot",
    "ks:ks_pop":309,
    "ks:ks_type":"HABITATION",
    "name:eng_x_preferred":[
        "Mohammad Nagar Chot"
    ],
    "wof:name":"Mohammad Nagar Chot",
    "wof:placetype":"locality",
    "wof:population":309
},
  "geometry": {"coordinates":[82.80740900000001,27.321626],"type":"Point"}
}