{
  "type": "Feature",
  "properties": {
    "gn:admin1_code":"2.0",
    "gn:admin2_code":"551.0",
    "gn:asciiname":"Kotavenkatramrazupuram",
    "gn:country_code":"IN",
    "gn:dem":165,
    "gn:feature_class":"P",
    "gn:feature_code":"PPL",
    "gn:name":"Kotavenkatr\u0101mr\u0101zupuram",
    "gn:population":0,
    "gn:timezone":"Asia/Kolkata",
    "iso:country":"IN",
    "wof:name":"Kotavenkatramrazupuram",
    "wof:placetype":"locality"
},
  "geometry": {"coordinates":[79.35087,14.04889],"type":"Point"}
}