{
  "type": "Feature",
  "properties": {
    "iso:country":"IN",
    "ks:ks_name":"Choki Wala",
    "ks:ks_pop":186,
    "ks:ks_type":"HABITATION",
    "name:eng_x_preferred":[
        "Choki Wala"
    ],
    "wof:name":"Choki Wala",
    "wof:placetype":"locality",
    "wof:population":186
},
  "geometry": {"coordinates":[79.145538,28.879038],"type":"Point"}
}