{
  "type": "Feature",
  "properties": {
    "gn:admin1_code":"21.0",
    "gn:admin2_code":"398.0",
    "gn:asciiname":"Kannapai",
    "gn:country_code":"IN",
    "gn:dem":844,
    "gn:feature_class":"P",
    "gn:feature_code":"PPL",
    "gn:name":"Kann\u0101pai",
    "gn:population":0,
    "gn:timezone":"Asia/Kolkata",
    "iso:country":"IN",
    "ks:ks_name":"Kanapai",
    "ks:ks_pop":62,
    "ks:ks_type":"VILLAGE",
    "name:eng_x_preferred":[
        "Kanapai"
    ],
    "name:eng_x_variant":[
        "Kannapai"
    ],
    "wof:name":"Kanapai",
    "wof:placetype":"locality",
    "wof:population":62
},
  "geometry": {"coordinates":[83.14588999999999,19.064513],"type":"Point"}
}