{
  "type": "Feature",
  "properties": {
    "iso:country":"IN",
    "ks:ks_name":"Ichhapur",
    "ks:ks_pop":285,
    "ks:ks_type":"VILLAGE",
    "name:eng_x_preferred":[
        "Ichhapur"
    ],
    "wof:name":"Ichhapur",
    "wof:placetype":"locality",
    "wof:population":285
},
  "geometry": {"coordinates":[86.27429100000001,21.116403],"type":"Point"}
}