{
  "type": "Feature",
  "properties": {
    "iso:country":"IN",
    "ks:ks_alt_nam":"PATELTOLI",
    "ks:ks_name":"Pateltoli",
    "ks:ks_pop":862,
    "ks:ks_type":"HABITATION",
    "name:eng_x_preferred":[
        "Pateltoli"
    ],
    "wof:name":"Pateltoli",
    "wof:placetype":"locality",
    "wof:population":862
},
  "geometry": {"coordinates":[83.596774,22.901792],"type":"Point"}
}