{
  "type": "Feature",
  "properties": {
    "iso:country":"IN",
    "ks:ks_name":"Matiaria Kalan",
    "ks:ks_pop":52,
    "ks:ks_type":"VILLAGE",
    "name:eng_x_preferred":[
        "Matiaria Kalan"
    ],
    "wof:name":"Matiaria Kalan",
    "wof:placetype":"locality",
    "wof:population":52
},
  "geometry": {"coordinates":[84.330386,27.23914],"type":"Point"}
}