{
  "type": "Feature",
  "properties": {
    "gn:admin1_code":"12",
    "gn:admin2_code":"14.0",
    "gn:asciiname":"Sirahom",
    "gn:country_code":"IN",
    "gn:dem":1723,
    "gn:feature_class":"P",
    "gn:feature_code":"PPL",
    "gn:name":"Sirah\u014dm",
    "gn:population":0,
    "gn:timezone":"Asia/Kolkata",
    "iso:country":"IN",
    "name:und_x_variant":[
        "Sirah\u014dm",
        "Sirahom"
    ],
    "wof:name":"Sirahom",
    "wof:placetype":"locality"
},
  "geometry": {"coordinates":[75.15899,33.84659],"type":"Point"}
}