{
  "type": "Feature",
  "properties": {
    "gn:admin1_code":"19.0",
    "gn:admin2_code":"568.0",
    "gn:asciiname":"Bilagi",
    "gn:country_code":"IN",
    "gn:dem":593,
    "gn:feature_class":"P",
    "gn:feature_code":"PPL",
    "gn:name":"Bil\u0101gi",
    "gn:population":0,
    "gn:timezone":"Asia/Kolkata",
    "iso:country":"IN",
    "name:ceb_x_preferred":[
        "Bilgi"
    ],
    "name:ita_x_preferred":[
        "Bilgi"
    ],
    "name:kan_x_preferred":[
        "\u0cac\u0cc0\u0cb3\u0c97\u0cbf"
    ],
    "name:msa_x_preferred":[
        "Bilgi"
    ],
    "name:nld_x_preferred":[
        "Bilgi"
    ],
    "name:vie_x_preferred":[
        "Bilgi"
    ],
    "name:zho_x_preferred":[
        "\u6bd4\u5c14\u5409"
    ],
    "wof:name":"Bilagi",
    "wof:placetype":"locality"
},
  "geometry": {"coordinates":[75.11674000000002,14.40851],"type":"Point"}
}