{
  "type": "Feature",
  "properties": {
    "gn:admin1_code":"34.0",
    "gn:admin2_code":"204.0",
    "gn:asciiname":"Gauri",
    "gn:country_code":"IN",
    "gn:dem":71,
    "gn:feature_class":"P",
    "gn:feature_code":"PPL",
    "gn:name":"Gauri",
    "gn:population":0,
    "gn:timezone":"Asia/Kolkata",
    "iso:country":"IN",
    "name:ceb_x_preferred":[
        "Gauri"
    ],
    "name:fra_x_preferred":[
        "Gaur\u00ee"
    ],
    "name:hin_x_preferred":[
        "\u0917\u094c\u0930\u0940"
    ],
    "name:kor_x_preferred":[
        "\uac00\uc6b0\ub9ac"
    ],
    "name:ori_x_preferred":[
        "\u0b17\u0b4c\u0b30\u0b40"
    ],
    "wof:name":"Gauri",
    "wof:placetype":"locality"
},
  "geometry": {"coordinates":[84.83951999999999,26.55614000000001],"type":"Point"}
}