{
  "type": "Feature",
  "properties": {
    "iso:country":"IN",
    "ks:ks_alt_nam":"keezhalpally",
    "ks:ks_name":"Keezhalpally",
    "ks:ks_pop":949,
    "ks:ks_type":"HABITATION",
    "name:eng_x_preferred":[
        "Keezhalpally"
    ],
    "wof:name":"Keezhalpally",
    "wof:placetype":"locality",
    "wof:population":949
},
  "geometry": {"coordinates":[75.656201,11.572491],"type":"Point"}
}