{
  "type": "Feature",
  "properties": {
    "gn:admin1_code":"36",
    "gn:admin2_code":"159.0",
    "gn:asciiname":"Ubrikhera Makrand",
    "gn:country_code":"IN",
    "gn:dem":150,
    "gn:feature_class":"P",
    "gn:feature_code":"PPL",
    "gn:name":"Ubr\u012bkhera Makrand",
    "gn:population":0,
    "gn:timezone":"Asia/Kolkata",
    "iso:country":"IN",
    "name:und_x_variant":[
        "Ubr\u012bkhera Makrand",
        "Suk\u0101npur"
    ],
    "wof:name":"Ubrikhera Makrand",
    "wof:placetype":"locality"
},
  "geometry": {"coordinates":[79.65054000000001,27.21885],"type":"Point"}
}