{
  "type": "Feature",
  "properties": {
    "iso:country":"IN",
    "ks:ks_name":"22 O-B",
    "ks:ks_pop":623,
    "ks:ks_type":"VILLAGE",
    "ks:ks_uagg_main":0,
    "name:eng_x_preferred":[
        "22 O-B"
    ],
    "wof:name":"22 O-B",
    "wof:placetype":"neighbourhood",
    "wof:population":623
},
  "geometry": {"coordinates":[73.398616,29.847285],"type":"Point"}
}