{
  "type": "Feature",
  "properties": {
    "gn:admin1_code":"13.0",
    "gn:asciiname":"Madakkanur",
    "gn:country_code":"IN",
    "gn:dem":916,
    "gn:feature_class":"P",
    "gn:feature_code":"PPL",
    "gn:name":"Madakkanur",
    "gn:population":0,
    "gn:timezone":"Asia/Kolkata",
    "iso:country":"IN",
    "wof:name":"Madakkanur",
    "wof:placetype":"locality"
},
  "geometry": {"coordinates":[76.33284,11.58898],"type":"Point"}
}