{
  "type": "Feature",
  "properties": {
    "gn:admin1_code":"19.0",
    "gn:admin2_code":"582.0",
    "gn:asciiname":"Bachuwarahalli",
    "gn:country_code":"IN",
    "gn:dem":862,
    "gn:feature_class":"P",
    "gn:feature_code":"PPL",
    "gn:name":"B\u0101chuw\u0101rahalli",
    "gn:population":0,
    "gn:timezone":"Asia/Kolkata",
    "iso:country":"IN",
    "wof:name":"Bachuwarahalli",
    "wof:placetype":"locality"
},
  "geometry": {"coordinates":[78.09709000000002,13.41718],"type":"Point"}
}