{
  "type": "Feature",
  "properties": {
    "iso:country":"IN",
    "ks:ks_name":"Garaiya",
    "ks:ks_pop":952,
    "ks:ks_type":"HABITATION",
    "name:eng_x_preferred":[
        "Garaiya"
    ],
    "wof:name":"Garaiya",
    "wof:placetype":"locality",
    "wof:population":952
},
  "geometry": {"coordinates":[87.045303,25.464181],"type":"Point"}
}