{
  "type": "Feature",
  "properties": {
    "iso:country":"IN",
    "ks:ks_name":"Tunighata",
    "ks:ks_pop":1617,
    "ks:ks_type":"VILLAGE",
    "ks:ks_uagg_main":0,
    "name:eng_x_preferred":[
        "Tunighata"
    ],
    "wof:name":"Tunighata",
    "wof:placetype":"locality",
    "wof:population":1617
},
  "geometry": {"coordinates":[88.694519,22.819653],"type":"Point"}
}