{
  "type": "Feature",
  "properties": {
    "iso:country":"IN",
    "ks:ks_name":"4 DOL",
    "ks:ks_pop":366,
    "ks:ks_type":"VILLAGE",
    "name:eng_x_preferred":[
        "4 DOL"
    ],
    "wof:name":"4 DOL",
    "wof:placetype":"locality",
    "wof:population":366
},
  "geometry": {"coordinates":[72.84766,28.83269],"type":"Point"}
}