{
  "type": "Feature",
  "properties": {
    "iso:country":"IN",
    "ks:ks_name":"Kalasapura",
    "ks:ks_pop":124,
    "ks:ks_type":"HABITATION",
    "name:eng_x_preferred":[
        "Kalasapura"
    ],
    "wof:name":"Kalasapura",
    "wof:placetype":"locality",
    "wof:population":124
},
  "geometry": {"coordinates":[75.37586899999999,13.453082],"type":"Point"}
}