{
  "type": "Feature",
  "properties": {
    "iso:country":"IN",
    "ks:ks_name":"Charki Bagriha",
    "ks:ks_pop":127,
    "ks:ks_type":"VILLAGE",
    "name:eng_x_preferred":[
        "Charki Bagriha"
    ],
    "wof:name":"Charki Bagriha",
    "wof:placetype":"locality",
    "wof:population":127
},
  "geometry": {"coordinates":[82.45738799999999,24.994255],"type":"Point"}
}