{
  "type": "Feature",
  "properties": {
    "iso:country":"IN",
    "ks:ks_name":"Bhapri",
    "ks:ks_pop":1190,
    "ks:ks_type":"HABITATION",
    "name:eng_x_preferred":[
        "Bhapri"
    ],
    "wof:name":"Bhapri",
    "wof:placetype":"locality",
    "wof:population":1190
},
  "geometry": {"coordinates":[72.080281,24.896269],"type":"Point"}
}