{
  "type": "Feature",
  "properties": {
    "iso:country":"IN",
    "ks:ks_name":"33 LLW",
    "ks:ks_pop":461,
    "ks:ks_type":"VILLAGE",
    "name:eng_x_preferred":[
        "33 LLW"
    ],
    "wof:name":"33 LLW",
    "wof:placetype":"locality",
    "wof:population":461
},
  "geometry": {"coordinates":[74.05630600000001,29.665667],"type":"Point"}
}