{
  "type": "Feature",
  "properties": {
    "iso:country":"IN",
    "ks:ks_name":"Rajapaju",
    "ks:ks_pop":108,
    "ks:ks_type":"VILLAGE",
    "name:eng_x_preferred":[
        "Rajapaju"
    ],
    "wof:name":"Rajapaju",
    "wof:placetype":"locality",
    "wof:population":108
},
  "geometry": {"coordinates":[84.286191,20.297611],"type":"Point"}
}