{
  "type": "Feature",
  "properties": {
    "iso:country":"IN",
    "ks:ks_name":"Lanku",
    "ks:ks_pop":1414,
    "ks:ks_type":"HABITATION",
    "name:eng_x_preferred":[
        "Lanku"
    ],
    "wof:name":"Lanku",
    "wof:placetype":"locality",
    "wof:population":1414
},
  "geometry": {"coordinates":[88.418898,26.953471],"type":"Point"}
}