{
  "type": "Feature",
  "properties": {
    "iso:country":"IN",
    "ks:ks_alt_nam":"Joldoba II",
    "ks:ks_name":"Joldoba Ii",
    "ks:ks_pop":3111,
    "ks:ks_type":"HABITATION",
    "name:eng_x_preferred":[
        "Joldoba Ii"
    ],
    "wof:name":"Joldoba Ii",
    "wof:placetype":"locality",
    "wof:population":3111
},
  "geometry": {"coordinates":[89.959137,26.169092],"type":"Point"}
}