{
  "type": "Feature",
  "properties": {
    "iso:country":"IN",
    "ks:ks_name":"Mirzak Purwa",
    "ks:ks_pop":280,
    "ks:ks_type":"HABITATION",
    "ks:ks_uagg_main":0,
    "name:eng_x_preferred":[
        "Mirzak Purwa"
    ],
    "wof:name":"Mirzak Purwa",
    "wof:placetype":"neighbourhood",
    "wof:population":280
},
  "geometry": {"coordinates":[82.224598,27.206757],"type":"Point"}
}