{
  "type": "Feature",
  "properties": {
    "gn:admin1_code":"11.0",
    "gn:admin2_code":"33.0",
    "gn:asciiname":"Ojaru",
    "gn:country_code":"IN",
    "gn:dem":1762,
    "gn:feature_class":"P",
    "gn:feature_code":"PPL",
    "gn:name":"Ojaru",
    "gn:population":0,
    "gn:timezone":"Asia/Kolkata",
    "iso:country":"IN",
    "wof:name":"Ojaru",
    "wof:placetype":"locality"
},
  "geometry": {"coordinates":[77.28458000000001,31.23728],"type":"Point"}
}