{
  "type": "Feature",
  "properties": {
    "iso:country":"IN",
    "ks:ks_name":"Chena Pat",
    "ks:ks_pop":284,
    "ks:ks_type":"VILLAGE",
    "name:eng_x_preferred":[
        "Chena Pat"
    ],
    "wof:name":"Chena Pat",
    "wof:placetype":"locality",
    "wof:population":284
},
  "geometry": {"coordinates":[87.494343,22.655267],"type":"Point"}
}