{
  "type": "Feature",
  "properties": {
    "gn:admin1_code":"11",
    "gn:admin2_code":"23.0",
    "gn:asciiname":"Hade",
    "gn:country_code":"IN",
    "gn:dem":1368,
    "gn:feature_class":"P",
    "gn:feature_code":"PPL",
    "gn:name":"Hade",
    "gn:population":0,
    "gn:timezone":"Asia/Kolkata",
    "iso:country":"IN",
    "wof:name":"Hade",
    "wof:placetype":"locality"
},
  "geometry": {"coordinates":[76.18701999999998,32.76537],"type":"Point"}
}