{
  "type": "Feature",
  "properties": {
    "iso:country":"IN",
    "ks:ks_name":"Sagron Ka Khera",
    "ks:ks_pop":256,
    "ks:ks_type":"VILLAGE",
    "name:eng_x_preferred":[
        "Sagron Ka Khera"
    ],
    "wof:name":"Sagron Ka Khera",
    "wof:placetype":"locality",
    "wof:population":256
},
  "geometry": {"coordinates":[74.73772700000001,23.64856],"type":"Point"}
}