{
  "type": "Feature",
  "properties": {
    "iso:country":"IN",
    "ks:ks_alt_nam":"Dind\u0101p\u0101i",
    "ks:ks_name":"Dindapai",
    "ks:ks_type":"VILLAGE",
    "name:eng_x_preferred":[
        "Dindapai"
    ],
    "name:eng_x_variant":[
        "Dind\u0101p\u0101i"
    ],
    "wof:name":"Dindapai",
    "wof:placetype":"locality"
},
  "geometry": {"coordinates":[85.34414700000001,22.664972],"type":"Point"}
}