{
  "type": "Feature",
  "properties": {
    "gn:admin1_code":"36",
    "gn:admin2_code":"200.0",
    "gn:asciiname":"Biyadamar",
    "gn:country_code":"IN",
    "gn:dem":284,
    "gn:feature_class":"P",
    "gn:feature_code":"PPL",
    "gn:name":"Biy\u0101d\u0101mar",
    "gn:population":0,
    "gn:timezone":"Asia/Kolkata",
    "iso:country":"IN",
    "name:und_x_variant":[
        "Biy\u0101d\u0101mar",
        "Biy\u0101d\u0101ndi"
    ],
    "wof:name":"Biyadamar",
    "wof:placetype":"locality"
},
  "geometry": {"coordinates":[83.3129,24.32126],"type":"Point"}
}