{
  "type": "Feature",
  "properties": {
    "iso:country":"IN",
    "ks:ks_name":"Baramasia",
    "ks:ks_pop":587,
    "ks:ks_type":"VILLAGE",
    "name:eng_x_preferred":[
        "Baramasia"
    ],
    "wof:name":"Baramasia",
    "wof:placetype":"locality",
    "wof:population":587
},
  "geometry": {"coordinates":[87.19684700000001,24.415782],"type":"Point"}
}