{
  "type": "Feature",
  "properties": {
    "iso:country":"IN",
    "ks:ks_alt_nam":"Irutt\u0101rk\u0101nal Block",
    "ks:ks_name":"Iruttarkanal Block",
    "ks:ks_type":"VILLAGE",
    "name:eng_x_preferred":[
        "Iruttarkanal Block"
    ],
    "name:eng_x_variant":[
        "Irutt\u0101rk\u0101nal Block"
    ],
    "wof:name":"Iruttarkanal Block",
    "wof:placetype":"locality"
},
  "geometry": {"coordinates":[77.62788,10.232443],"type":"Point"}
}