{
  "type": "Feature",
  "properties": {
    "gn:admin1_code":"38",
    "gn:admin2_code":"346.0",
    "gn:asciiname":"Chaukri",
    "gn:country_code":"IN",
    "gn:dem":374,
    "gn:feature_class":"P",
    "gn:feature_code":"PPL",
    "gn:name":"Chaukr\u012b",
    "gn:population":0,
    "gn:timezone":"Asia/Kolkata",
    "iso:country":"IN",
    "name:und_x_variant":[
        "Chaukr\u012b",
        "Sati\u0101r\u012b"
    ],
    "wof:name":"Chaukri",
    "wof:placetype":"locality"
},
  "geometry": {"coordinates":[83.77472,23.952],"type":"Point"}
}