{
  "type": "Feature",
  "properties": {
    "iso:country":"IN",
    "ks:ks_name":"Talitya",
    "ks:ks_pop":888,
    "ks:ks_type":"VILLAGE",
    "name:eng_x_preferred":[
        "Talitya"
    ],
    "wof:name":"Talitya",
    "wof:placetype":"locality",
    "wof:population":888
},
  "geometry": {"coordinates":[87.742487,22.451042],"type":"Point"}
}