{
  "type": "Feature",
  "properties": {
    "iso:country":"IN",
    "ks:ks_alt_nam":"Kulkod li",
    "ks:ks_name":"Kulkod Li",
    "ks:ks_pop":852,
    "ks:ks_type":"HABITATION",
    "name:eng_x_preferred":[
        "Kulkod Li"
    ],
    "wof:name":"Kulkod Li",
    "wof:placetype":"locality",
    "wof:population":852
},
  "geometry": {"coordinates":[74.460536,14.282614],"type":"Point"}
}