{
  "type": "Feature",
  "properties": {
    "iso:country":"IN",
    "ks:ks_name":"Bhawanipur",
    "ks:ks_pop":159,
    "ks:ks_type":"HABITATION",
    "ks:ks_uagg_main":0,
    "name:eng_x_preferred":[
        "Bhawanipur"
    ],
    "wof:name":"Bhawanipur",
    "wof:placetype":"neighbourhood",
    "wof:population":159
},
  "geometry": {"coordinates":[80.01953399999999,27.049929],"type":"Point"}
}