{
  "type": "Feature",
  "properties": {
    "gn:admin1_code":"21",
    "gn:admin2_code":"394.0",
    "gn:asciiname":"Suklimuri",
    "gn:country_code":"IN",
    "gn:dem":314,
    "gn:feature_class":"P",
    "gn:feature_code":"PPL",
    "gn:name":"Suklimuri",
    "gn:population":0,
    "gn:timezone":"Asia/Kolkata",
    "iso:country":"IN",
    "wof:name":"Suklimuri",
    "wof:placetype":"locality"
},
  "geometry": {"coordinates":[82.70435999999999,20.66985],"type":"Point"}
}