{
  "type": "Feature",
  "properties": {
    "iso:country":"IN",
    "ks:ks_name":"Therikkada",
    "ks:ks_pop":5023,
    "ks:ks_type":"HABITATION",
    "name:eng_x_preferred":[
        "Therikkada"
    ],
    "wof:name":"Therikkada",
    "wof:placetype":"locality",
    "wof:population":5023
},
  "geometry": {"coordinates":[76.865236,8.660585],"type":"Point"}
}