{
  "type": "Feature",
  "properties": {
    "iso:country":"IN",
    "ks:ks_name":"Karadapali",
    "ks:ks_pop":385,
    "ks:ks_type":"VILLAGE",
    "ks:ks_uagg_main":0,
    "name:eng_x_preferred":[
        "Karadapali"
    ],
    "wof:name":"Karadapali",
    "wof:placetype":"neighbourhood",
    "wof:population":385
},
  "geometry": {"coordinates":[85.32433899999999,20.264396],"type":"Point"}
}