{
  "type": "Feature",
  "properties": {
    "gn:admin1_code":"23.0",
    "gn:admin2_code":"36.0",
    "gn:asciiname":"Dhapai",
    "gn:country_code":"IN",
    "gn:dem":230,
    "gn:feature_class":"P",
    "gn:feature_code":"PPL",
    "gn:name":"Dhapai",
    "gn:population":0,
    "gn:timezone":"Asia/Kolkata",
    "iso:country":"IN",
    "name:fas_x_preferred":[
        "\u062f\u0647\u0627\u067e\u0627\u06cc"
    ],
    "name:urd_x_preferred":[
        "\u062f\u06be\u0627\u067e\u0626\u06cc"
    ],
    "wof:name":"Dhapai",
    "wof:placetype":"locality"
},
  "geometry": {"coordinates":[75.4316,31.34652],"type":"Point"}
}