{
  "type": "Feature",
  "properties": {
    "gn:admin1_code":"36",
    "gn:admin2_code":"170.0",
    "gn:asciiname":"Durai Mafi",
    "gn:country_code":"IN",
    "gn:dem":131,
    "gn:feature_class":"P",
    "gn:feature_code":"PPL",
    "gn:name":"Durai M\u0101fi",
    "gn:population":0,
    "gn:timezone":"Asia/Kolkata",
    "iso:country":"IN",
    "ks:ks_alt_nam":"Durai M\u0101fi",
    "ks:ks_name":"Durai Mafi",
    "ks:ks_pop":1023,
    "ks:ks_type":"VILLAGE",
    "ks:ks_uagg_main":0,
    "name:eng_x_preferred":[
        "Durai Mafi"
    ],
    "name:eng_x_variant":[
        "Durai M\u0101fi"
    ],
    "wof:name":"Durai Mafi",
    "wof:placetype":"neighbourhood",
    "wof:population":1023
},
  "geometry": {"coordinates":[80.53111800000001,25.37937],"type":"Point"}
}