{
  "type": "Feature",
  "properties": {
    "gn:admin1_code":"39.0",
    "gn:admin2_code":"66.0",
    "gn:asciiname":"Khimua Pipal",
    "gn:country_code":"IN",
    "gn:dem":644,
    "gn:feature_class":"P",
    "gn:feature_code":"PPL",
    "gn:name":"Khimua P\u012bpal",
    "gn:population":0,
    "gn:timezone":"Asia/Kolkata",
    "iso:country":"IN",
    "ks:ks_alt_nam":"Khimua P\u012bpal",
    "ks:ks_name":"Khimua Pipal",
    "ks:ks_type":"VILLAGE",
    "name:eng_x_preferred":[
        "Khimua Pipal"
    ],
    "name:eng_x_variant":[
        "Khimua P\u012bpal"
    ],
    "wof:name":"Khimua Pipal",
    "wof:placetype":"locality"
},
  "geometry": {"coordinates":[79.295019,29.393268],"type":"Point"}
}