{
  "type": "Feature",
  "properties": {
    "gn:country":"IN",
    "gn:fcode":"PPL",
    "gn:pop":6131,
    "iso:country":"IN",
    "name:ben_x_preferred":[
        "\u09b2\u09cb\u09a8\u09cd\u09a6\u09be"
    ],
    "name:bpy_x_preferred":[
        "\u09b2\u09cb\u09a8\u09cd\u09a6\u09be"
    ],
    "name:ceb_x_preferred":[
        "Londa"
    ],
    "name:eng_x_preferred":[
        "Londa"
    ],
    "name:epo_x_preferred":[
        "Londa"
    ],
    "name:fra_x_preferred":[
        "Londa"
    ],
    "name:ita_x_preferred":[
        "Londa"
    ],
    "name:msa_x_preferred":[
        "Londa"
    ],
    "name:nan_x_preferred":[
        "Londa"
    ],
    "name:nap_x_preferred":[
        "Londa"
    ],
    "name:new_x_preferred":[
        "\u0932\u094b\u0928\u094d\u0926\u093e"
    ],
    "name:nld_x_preferred":[
        "Londa"
    ],
    "name:pol_x_preferred":[
        "Londa"
    ],
    "name:pol_x_variant":[
        "Rarah"
    ],
    "name:por_x_preferred":[
        "Londa"
    ],
    "name:swe_x_preferred":[
        "Londa"
    ],
    "name:unk_x_variant":[
        "Landa"
    ],
    "qs:name":"Londa",
    "qs:photos_9r":0,
    "qs:photos_sr":0,
    "qs:pop_sr":"5",
    "wd:wordcount":12,
    "wof:name":"Londa",
    "wof:placetype":"locality",
    "wof:population":6131
},
  "geometry": {"coordinates":[74.51906,15.46907],"type":"Point"}
}