{
  "type": "Feature",
  "properties": {
    "gn:admin1_code":"12.0",
    "gn:admin2_code":"7.0",
    "gn:asciiname":"Peri",
    "gn:country_code":"IN",
    "gn:dem":493,
    "gn:feature_class":"P",
    "gn:feature_code":"PPL",
    "gn:name":"Peri",
    "gn:population":0,
    "gn:timezone":"Asia/Kolkata",
    "iso:country":"IN",
    "name:ara_x_preferred":[
        "\u062d\u0648\u0631\u064a\u0629"
    ],
    "name:bak_x_preferred":[
        "\u0411\u04d9\u0440\u0435\u0439"
    ],
    "name:ceb_x_preferred":[
        "Pari"
    ],
    "name:deu_x_preferred":[
        "Pari"
    ],
    "name:fas_x_preferred":[
        "\u067e\u0631\u06cc"
    ],
    "name:fra_x_preferred":[
        "P\u00e9ri"
    ],
    "name:ind_x_preferred":[
        "Peri"
    ],
    "name:kaz_x_preferred":[
        "\u041f\u0435\u0440\u0456"
    ],
    "name:nor_x_preferred":[
        "Peri"
    ],
    "name:rus_x_preferred":[
        "\u041f\u0435\u0440\u0438"
    ],
    "name:spa_x_preferred":[
        "Peri"
    ],
    "name:swe_x_preferred":[
        "Peri"
    ],
    "name:tgl_x_preferred":[
        "Pari"
    ],
    "name:ukr_x_preferred":[
        "\u041f\u0435\u0440\u0456"
    ],
    "name:und_x_variant":[
        "Jan\u0101l"
    ],
    "name:uzb_x_preferred":[
        "Pari"
    ],
    "wof:name":"Peri",
    "wof:placetype":"locality"
},
  "geometry": {"coordinates":[75.48591,32.52659],"type":"Point"}
}