{
  "type": "Feature",
  "properties": {
    "gn:admin1_code":"40.0",
    "gn:admin2_code":"532.0",
    "gn:asciiname":"Sumputum",
    "gn:country_code":"IN",
    "gn:dem":123,
    "gn:feature_class":"P",
    "gn:feature_code":"PPL",
    "gn:name":"Sumputum",
    "gn:population":0,
    "gn:timezone":"Asia/Kolkata",
    "iso:country":"IN",
    "ks:ks_name":"Sumputum",
    "ks:ks_pop":548,
    "ks:ks_type":"VILLAGE",
    "name:eng_x_preferred":[
        "Sumputum"
    ],
    "wof:name":"Sumputum",
    "wof:placetype":"locality",
    "wof:population":548
},
  "geometry": {"coordinates":[79.862312,19.131145],"type":"Point"}
}