{
  "type": "Feature",
  "properties": {
    "gn:admin1_code":"25",
    "gn:asciiname":"Ramapuram",
    "gn:country_code":"IN",
    "gn:dem":14,
    "gn:feature_class":"P",
    "gn:feature_code":"PPL",
    "gn:name":"R\u0101m\u0101puram",
    "gn:population":0,
    "gn:timezone":"Asia/Kolkata",
    "iso:country":"IN",
    "name:und_x_variant":[
        "R\u0101m\u0101puram"
    ],
    "wof:name":"Ramapuram",
    "wof:placetype":"locality"
},
  "geometry": {"coordinates":[80.08625000000001,13.51663],"type":"Point"}
}