{
  "type": "Feature",
  "properties": {
    "iso:country":"IN",
    "ks:ks_name":"Kesmudarpara",
    "ks:ks_pop":40,
    "ks:ks_type":"HABITATION",
    "name:eng_x_preferred":[
        "Kesmudarpara"
    ],
    "wof:name":"Kesmudarpara",
    "wof:placetype":"locality",
    "wof:population":40
},
  "geometry": {"coordinates":[81.104512,20.118867],"type":"Point"}
}