{
  "type": "Feature",
  "properties": {
    "iso:country":"IN",
    "ks:ks_name":"Basawan Ganj",
    "ks:ks_pop":0,
    "ks:ks_type":"VILLAGE",
    "name:eng_x_preferred":[
        "Basawan Ganj"
    ],
    "wof:name":"Basawan Ganj",
    "wof:placetype":"locality",
    "wof:population":0
},
  "geometry": {"coordinates":[87.109111,25.097291],"type":"Point"}
}