{
  "type": "Feature",
  "properties": {
    "iso:country":"IN",
    "ks:ks_name":"Kurmanadhapuram",
    "ks:ks_pop":193,
    "ks:ks_type":"VILLAGE",
    "name:eng_x_preferred":[
        "Kurmanadhapuram"
    ],
    "wof:name":"Kurmanadhapuram",
    "wof:placetype":"locality",
    "wof:population":193
},
  "geometry": {"coordinates":[82.768036,17.910889],"type":"Point"}
}