{
  "type": "Feature",
  "properties": {
    "iso:country":"IN",
    "ks:ks_name":"Puttaparthy",
    "ks:ks_pop":13,
    "ks:ks_type":"HABITATION",
    "name:eng_x_preferred":[
        "Puttaparthy"
    ],
    "wof:name":"Puttaparthy",
    "wof:placetype":"locality",
    "wof:population":13
},
  "geometry": {"coordinates":[78.09737199999999,13.671156],"type":"Point"}
}