{
  "type": "Feature",
  "properties": {
    "iso:country":"IN",
    "ks:ks_name":"Raighati",
    "ks:ks_pop":282,
    "ks:ks_type":"HABITATION",
    "name:eng_x_preferred":[
        "Raighati"
    ],
    "wof:name":"Raighati",
    "wof:placetype":"locality",
    "wof:population":282
},
  "geometry": {"coordinates":[85.990005,21.217531],"type":"Point"}
}