{
  "type": "Feature",
  "properties": {
    "iso:country":"IN",
    "ks:ks_name":"Kumargaon",
    "ks:ks_pop":341,
    "ks:ks_type":"HABITATION",
    "name:eng_x_preferred":[
        "Kumargaon"
    ],
    "wof:name":"Kumargaon",
    "wof:placetype":"locality",
    "wof:population":341
},
  "geometry": {"coordinates":[90.34307200000001,26.225691],"type":"Point"}
}