{
  "type": "Feature",
  "properties": {
    "iso:country":"IN",
    "ks:ks_name":"Polluguda",
    "ks:ks_pop":85,
    "ks:ks_type":"HABITATION",
    "name:eng_x_preferred":[
        "Polluguda"
    ],
    "wof:name":"Polluguda",
    "wof:placetype":"locality",
    "wof:population":85
},
  "geometry": {"coordinates":[78.703487,19.249266],"type":"Point"}
}