{
  "type": "Feature",
  "properties": {
    "gn:admin1_code":"02",
    "gn:admin2_code":"542.0",
    "gn:asciiname":"Meliyaputtu",
    "gn:country_code":"IN",
    "gn:dem":61,
    "gn:feature_class":"P",
    "gn:feature_code":"PPL",
    "gn:name":"Meliy\u0101puttu",
    "gn:population":0,
    "gn:timezone":"Asia/Kolkata",
    "iso:country":"IN",
    "name:und_x_variant":[
        "Melyaputtu",
        "Meliy\u0101puttu"
    ],
    "wof:name":"Meliyaputtu",
    "wof:placetype":"neighbourhood"
},
  "geometry": {"coordinates":[84.15608,18.77678],"type":"Point"}
}