{
  "type": "Feature",
  "properties": {
    "iso:country":"IN",
    "ks:ks_alt_nam":"S\u0101lgo",
    "ks:ks_name":"Salgo",
    "ks:ks_pop":615,
    "ks:ks_type":"VILLAGE",
    "name:eng_x_preferred":[
        "Salgo"
    ],
    "name:eng_x_variant":[
        "S\u0101lgo"
    ],
    "wof:name":"Salgo",
    "wof:placetype":"locality",
    "wof:population":615
},
  "geometry": {"coordinates":[85.35553400000001,23.587861],"type":"Point"}
}