{
  "type": "Feature",
  "properties": {
    "iso:country":"IN",
    "ks:ks_name":"Kandaiyankottai",
    "ks:ks_pop":104,
    "ks:ks_type":"VILLAGE",
    "name:eng_x_preferred":[
        "Kandaiyankottai"
    ],
    "wof:name":"Kandaiyankottai",
    "wof:placetype":"locality",
    "wof:population":104
},
  "geometry": {"coordinates":[79.093698,10.098922],"type":"Point"}
}