{
  "type": "Feature",
  "properties": {
    "gn:admin1_code":"2.0",
    "gn:admin2_code":"554.0",
    "gn:asciiname":"Rajanam",
    "gn:country_code":"IN",
    "gn:dem":715,
    "gn:feature_class":"P",
    "gn:feature_code":"PPL",
    "gn:name":"Raj\u0101nam",
    "gn:population":0,
    "gn:timezone":"Asia/Kolkata",
    "iso:country":"IN",
    "wof:name":"Rajanam",
    "wof:placetype":"locality"
},
  "geometry": {"coordinates":[78.30171,12.73145],"type":"Point"}
}