{
  "type": "Feature",
  "properties": {
    "gn:admin1_code":"37.0",
    "gn:admin2_code":"417.0",
    "gn:asciiname":"Bandarpalli",
    "gn:country_code":"IN",
    "gn:dem":163,
    "gn:feature_class":"P",
    "gn:feature_code":"PPL",
    "gn:name":"Band\u0101rpalli",
    "gn:population":0,
    "gn:timezone":"Asia/Kolkata",
    "iso:country":"IN",
    "wof:name":"Bandarpalli",
    "wof:placetype":"locality"
},
  "geometry": {"coordinates":[80.70716,18.69035],"type":"Point"}
}