{
  "type": "Feature",
  "properties": {
    "gn:admin1_code":"37.0",
    "gn:admin2_code":"417.0",
    "gn:asciiname":"Bandarpalli",
    "gn:country_code":"IN",
    "gn:dem":163,
    "gn:feature_class":"P",
    "gn:feature_code":"PPL",
    "gn:name":"Band\u0101rpalli",
    "gn:population":0,
    "gn:timezone":"Asia/Kolkata",
    "iso:country":"IN",
    "ks:ks_name":"Bhandarpal",
    "ks:ks_pop":254,
    "ks:ks_type":"VILLAGE",
    "name:eng_x_preferred":[
        "Bhandarpal"
    ],
    "name:eng_x_variant":[
        "Bandarpalli"
    ],
    "wof:name":"Bhandarpal",
    "wof:placetype":"locality",
    "wof:population":254
},
  "geometry": {"coordinates":[80.70835,18.68781],"type":"Point"}
}