{
  "type": "Feature",
  "properties": {
    "iso:country":"IN",
    "ks:ks_name":"Saliya",
    "ks:ks_pop":480,
    "ks:ks_type":"VILLAGE",
    "name:eng_x_preferred":[
        "Saliya"
    ],
    "wof:name":"Saliya",
    "wof:placetype":"locality",
    "wof:population":480
},
  "geometry": {"coordinates":[74.61547400000001,23.698315],"type":"Point"}
}