{
  "type": "Feature",
  "properties": {
    "iso:country":"IN",
    "ks:ks_name":"Kandhapendili",
    "ks:ks_pop":176,
    "ks:ks_type":"VILLAGE",
    "name:eng_x_preferred":[
        "Kandhapendili"
    ],
    "wof:name":"Kandhapendili",
    "wof:placetype":"locality",
    "wof:population":176
},
  "geometry": {"coordinates":[83.734196,19.442101],"type":"Point"}
}