{
  "type": "Feature",
  "properties": {
    "gn:admin1_code":"34.0",
    "gn:admin2_code":"219.0",
    "gn:asciiname":"Chand Kudaria",
    "gn:country_code":"IN",
    "gn:dem":64,
    "gn:feature_class":"P",
    "gn:feature_code":"PPL",
    "gn:name":"Ch\u0101nd Kudaria",
    "gn:population":0,
    "gn:timezone":"Asia/Kolkata",
    "iso:country":"IN",
    "ks:ks_alt_nam":"Ch\u0101nd Kudaria",
    "ks:ks_name":"Chand Kudaria",
    "ks:ks_type":"VILLAGE",
    "ks:ks_uagg_main":0,
    "name:eng_x_preferred":[
        "Chand Kudaria"
    ],
    "name:eng_x_variant":[
        "Ch\u0101nd Kudaria"
    ],
    "wof:name":"Chand Kudaria",
    "wof:placetype":"neighbourhood"
},
  "geometry": {"coordinates":[84.78817600000001,26.179436],"type":"Point"}
}