{
  "type": "Feature",
  "properties": {
    "iso:country":"IN",
    "ks:ks_name":"Patoli",
    "ks:ks_pop":59,
    "ks:ks_type":"HABITATION",
    "name:eng_x_preferred":[
        "Patoli"
    ],
    "wof:name":"Patoli",
    "wof:placetype":"locality",
    "wof:population":59
},
  "geometry": {"coordinates":[79.70974200000001,29.517653],"type":"Point"}
}