{
  "type": "Feature",
  "properties": {
    "iso:country":"IN",
    "ks:ks_name":"Rang Pathar",
    "ks:ks_pop":458,
    "ks:ks_type":"VILLAGE",
    "ks:ks_uagg_main":0,
    "name:eng_x_preferred":[
        "Rang Pathar"
    ],
    "wof:name":"Rang Pathar",
    "wof:placetype":"neighbourhood",
    "wof:population":458
},
  "geometry": {"coordinates":[90.875398,25.959391],"type":"Point"}
}