{
  "type": "Feature",
  "properties": {
    "iso:country":"IN",
    "ks:ks_name":"Chanthapadi",
    "ks:ks_pop":2000,
    "ks:ks_type":"HABITATION",
    "name:eng_x_preferred":[
        "Chanthapadi"
    ],
    "wof:name":"Chanthapadi",
    "wof:placetype":"locality",
    "wof:population":2000
},
  "geometry": {"coordinates":[75.912003,11.039728],"type":"Point"}
}