{
  "type": "Feature",
  "properties": {
    "iso:country":"IN",
    "ks:ks_name":"Marrak",
    "ks:ks_pop":216,
    "ks:ks_type":"HABITATION",
    "name:eng_x_preferred":[
        "Marrak"
    ],
    "wof:name":"Marrak",
    "wof:placetype":"locality",
    "wof:population":216
},
  "geometry": {"coordinates":[82.78142200000001,24.012287],"type":"Point"}
}