{
  "type": "Feature",
  "properties": {
    "iso:country":"IN",
    "ks:ks_alt_nam":"JANGLIJOBA",
    "ks:ks_name":"Janglijoba",
    "ks:ks_pop":280,
    "ks:ks_type":"HABITATION",
    "name:eng_x_preferred":[
        "Janglijoba"
    ],
    "wof:name":"Janglijoba",
    "wof:placetype":"locality",
    "wof:population":280
},
  "geometry": {"coordinates":[83.323353,22.856633],"type":"Point"}
}