{
  "type": "Feature",
  "properties": {
    "iso:country":"IN",
    "ks:ks_name":"Chak Shyam Nagar Neamatganj",
    "ks:ks_pop":0,
    "ks:ks_type":"VILLAGE",
    "name:eng_x_preferred":[
        "Chak Shyam Nagar Neamatganj"
    ],
    "wof:name":"Chak Shyam Nagar Neamatganj",
    "wof:placetype":"locality",
    "wof:population":0
},
  "geometry": {"coordinates":[85.730577,25.85416],"type":"Point"}
}