{
  "type": "Feature",
  "properties": {
    "iso:country":"IN",
    "ks:ks_name":"Hosakunda",
    "ks:ks_pop":356,
    "ks:ks_type":"HABITATION",
    "name:eng_x_preferred":[
        "Hosakunda"
    ],
    "wof:name":"Hosakunda",
    "wof:placetype":"locality",
    "wof:population":356
},
  "geometry": {"coordinates":[74.88839400000001,13.519372],"type":"Point"}
}