{
  "type": "Feature",
  "properties": {
    "iso:country":"IN",
    "ks:ks_name":"Dumrauli",
    "ks:ks_type":"VILLAGE",
    "ks:ks_uagg_main":0,
    "name:eng_x_preferred":[
        "Dumrauli"
    ],
    "wof:name":"Dumrauli",
    "wof:placetype":"neighbourhood"
},
  "geometry": {"coordinates":[82.57695099999999,25.138224],"type":"Point"}
}