{
  "type": "Feature",
  "properties": {
    "iso:country":"IN",
    "ks:ks_name":"Tighari Rai",
    "ks:ks_pop":549,
    "ks:ks_type":"HABITATION",
    "ks:ks_uagg_main":0,
    "name:eng_x_preferred":[
        "Tighari Rai"
    ],
    "wof:name":"Tighari Rai",
    "wof:placetype":"neighbourhood",
    "wof:population":549
},
  "geometry": {"coordinates":[82.68887700000001,27.228849],"type":"Point"}
}