{
  "type": "Feature",
  "properties": {
    "iso:country":"IN",
    "ks:ks_alt_nam":"R\u0101magondanahalli",
    "ks:ks_name":"Ramagondanahalli",
    "ks:ks_pop":441,
    "ks:ks_type":"VILLAGE",
    "name:eng_x_preferred":[
        "Ramagondanahalli"
    ],
    "name:eng_x_variant":[
        "R\u0101magondanahalli"
    ],
    "wof:name":"Ramagondanahalli",
    "wof:placetype":"locality",
    "wof:population":441
},
  "geometry": {"coordinates":[75.88,14.209],"type":"Point"}
}