{
  "type": "Feature",
  "properties": {
    "iso:country":"IN",
    "ks:ks_name":"Sankapurapalya",
    "ks:ks_pop":776,
    "ks:ks_type":"HABITATION",
    "name:eng_x_preferred":[
        "Sankapurapalya"
    ],
    "wof:name":"Sankapurapalya",
    "wof:placetype":"locality",
    "wof:population":776
},
  "geometry": {"coordinates":[77.05174,13.128194],"type":"Point"}
}