{
  "type": "Feature",
  "properties": {
    "iso:country":"IN",
    "ks:ks_name":"Chandaji Ka Gurha",
    "ks:ks_pop":794,
    "ks:ks_type":"VILLAGE",
    "name:eng_x_preferred":[
        "Chandaji Ka Gurha"
    ],
    "wof:name":"Chandaji Ka Gurha",
    "wof:placetype":"locality",
    "wof:population":794
},
  "geometry": {"coordinates":[74.26773900000001,24.290969],"type":"Point"}
}