{
  "type": "Feature",
  "properties": {
    "iso:country":"IN",
    "ks:ks_name":"Jahan Nagar",
    "ks:ks_pop":1087,
    "ks:ks_type":"VILLAGE",
    "ks:ks_uagg_main":0,
    "name:eng_x_preferred":[
        "Jahan Nagar"
    ],
    "wof:name":"Jahan Nagar",
    "wof:placetype":"locality",
    "wof:population":1087
},
  "geometry": {"coordinates":[88.329156,23.427834],"type":"Point"}
}