{
  "type": "Feature",
  "properties": {
    "iso:country":"IN",
    "ks:ks_name":"Kanawadi",
    "ks:ks_pop":188,
    "ks:ks_type":"HABITATION",
    "name:eng_x_preferred":[
        "Kanawadi"
    ],
    "wof:name":"Kanawadi",
    "wof:placetype":"locality",
    "wof:population":188
},
  "geometry": {"coordinates":[73.951272,15.854771],"type":"Point"}
}