{
  "type": "Feature",
  "properties": {
    "iso:country":"IN",
    "ks:ks_name":"Kallarpudur",
    "ks:ks_pop":400,
    "ks:ks_type":"HABITATION",
    "ks:ks_uagg_main":1,
    "name:eng_x_preferred":[
        "Kallarpudur"
    ],
    "wof:name":"Kallarpudur",
    "wof:placetype":"neighbourhood",
    "wof:population":400
},
  "geometry": {"coordinates":[76.88591599999999,11.337387],"type":"Point"}
}