{
  "type": "Feature",
  "properties": {
    "iso:country":"IN",
    "ks:ks_name":"Modekarwaste",
    "ks:ks_pop":136,
    "ks:ks_type":"HABITATION",
    "name:eng_x_preferred":[
        "Modekarwaste"
    ],
    "wof:name":"Modekarwaste",
    "wof:placetype":"locality",
    "wof:population":136
},
  "geometry": {"coordinates":[74.732024,17.571011],"type":"Point"}
}