{
  "type": "Feature",
  "properties": {
    "iso:country":"IN",
    "ks:ks_name":"Mora Basti",
    "ks:ks_pop":1458,
    "ks:ks_type":"VILLAGE",
    "name:eng_x_preferred":[
        "Mora Basti"
    ],
    "wof:name":"Mora Basti",
    "wof:placetype":"locality",
    "wof:population":1458
},
  "geometry": {"coordinates":[93.206467,25.762597],"type":"Point"}
}