{
  "type": "Feature",
  "properties": {
    "gn:admin1_code":"36.0",
    "gn:admin2_code":"133.0",
    "gn:asciiname":"Bilaspur",
    "gn:country_code":"IN",
    "gn:dem":247,
    "gn:feature_class":"P",
    "gn:feature_code":"PPL",
    "gn:name":"Bil\u0101spur",
    "gn:population":0,
    "gn:timezone":"Asia/Kolkata",
    "iso:country":"IN",
    "name:ara_x_preferred":[
        "\u0628\u064a\u0644\u0627\u0633 \u0628\u0648\u0631"
    ],
    "name:ben_x_preferred":[
        "\u09ac\u09bf\u09b2\u09be\u09b8\u09aa\u09c1\u09b0"
    ],
    "name:bpy_x_preferred":[
        "\u09ac\u09bf\u09b2\u09be\u09b8\u09aa\u09c1\u09b0"
    ],
    "name:cat_x_preferred":[
        "Bilaspur"
    ],
    "name:ceb_x_preferred":[
        "Bilaspur"
    ],
    "name:deu_x_preferred":[
        "Bilaspur"
    ],
    "name:hin_x_preferred":[
        "\u092c\u093f\u0932\u093e\u0938\u092a\u0941\u0930"
    ],
    "name:ita_x_preferred":[
        "Bilaspur"
    ],
    "name:nep_x_preferred":[
        "\u092c\u093f\u0932\u093e\u0938\u092a\u0941\u0930"
    ],
    "name:new_x_preferred":[
        "\u092c\u093f\u0932\u093e\u0938\u092a\u0941\u0930"
    ],
    "name:nld_x_preferred":[
        "Bilaspur"
    ],
    "name:pan_x_preferred":[
        "\u0a2c\u0a3f\u0a32\u0a3e\u0a38\u0a2a\u0a41\u0a30"
    ],
    "name:pol_x_preferred":[
        "Bilaspur"
    ],
    "name:rus_x_preferred":[
        "\u0411\u0438\u043b\u0430\u0441\u043f\u0443\u0440"
    ],
    "name:spa_x_preferred":[
        "Bilaspur"
    ],
    "name:swe_x_preferred":[
        "Bilaspur"
    ],
    "name:tam_x_preferred":[
        "\u0baa\u0bbf\u0bb2\u0bbe\u0b9a\u0bc1\u0baa\u0bcd\u0baa\u0bc2\u0bb0\u0bcd"
    ],
    "wof:name":"Bilaspur",
    "wof:placetype":"locality"
},
  "geometry": {"coordinates":[77.74751999999999,29.45399],"type":"Point"}
}