{
  "type": "Feature",
  "properties": {
    "gn:admin1_code":"25.0",
    "gn:admin2_code":"617.0",
    "gn:asciiname":"Kalarkuppam",
    "gn:country_code":"IN",
    "gn:dem":72,
    "gn:feature_class":"P",
    "gn:feature_code":"PPL",
    "gn:name":"Kalarkuppam",
    "gn:population":0,
    "gn:timezone":"Asia/Kolkata",
    "iso:country":"IN",
    "ks:ks_name":"Kalarkuppam",
    "ks:ks_pop":388,
    "ks:ks_type":"HABITATION",
    "ks:ks_uagg_main":0,
    "name:eng_x_preferred":[
        "Kalarkuppam"
    ],
    "wof:name":"Kalarkuppam",
    "wof:placetype":"neighbourhood",
    "wof:population":388
},
  "geometry": {"coordinates":[79.365218,11.658676],"type":"Point"}
}