{
  "type": "Feature",
  "properties": {
    "gn:admin1_code":"16",
    "gn:admin2_code":"501.0",
    "gn:asciiname":"Birsingpur",
    "gn:country_code":"IN",
    "gn:dem":289,
    "gn:feature_class":"P",
    "gn:feature_code":"PPL",
    "gn:name":"Birsingpur",
    "gn:population":0,
    "gn:timezone":"Asia/Kolkata",
    "iso:country":"IN",
    "ks:ks_name":"Birsingpur",
    "ks:ks_pop":267,
    "ks:ks_type":"VILLAGE",
    "name:eng_x_preferred":[
        "Birsingpur"
    ],
    "wof:name":"Birsingpur",
    "wof:placetype":"locality",
    "wof:population":267
},
  "geometry": {"coordinates":[77.261577,20.731763],"type":"Point"}
}