{
  "type": "Feature",
  "properties": {
    "iso:country":"IN",
    "ks:ks_name":"Gotiguda",
    "ks:ks_pop":642,
    "ks:ks_type":"VILLAGE",
    "name:eng_x_preferred":[
        "Gotiguda"
    ],
    "wof:name":"Gotiguda",
    "wof:placetype":"locality",
    "wof:population":642
},
  "geometry": {"coordinates":[82.17473699999999,18.436256],"type":"Point"}
}