{
  "type": "Feature",
  "properties": {
    "gn:admin1_code":"12.0",
    "gn:admin2_code":"006",
    "gn:asciiname":"Patani",
    "gn:country_code":"IN",
    "gn:dem":598,
    "gn:feature_class":"P",
    "gn:feature_code":"PPL",
    "gn:name":"Pat\u0101ni",
    "gn:population":0,
    "gn:timezone":"Asia/Kolkata",
    "iso:country":"IN",
    "name:und_x_variant":[
        "Pat\u0101ni",
        "Chauki"
    ],
    "wof:name":"Patani",
    "wof:placetype":"locality"
},
  "geometry": {"coordinates":[74.20446,33.16096],"type":"Point"}
}