{
  "type": "Feature",
  "properties": {
    "gn:admin1_code":"12.0",
    "gn:admin2_code":"006",
    "gn:asciiname":"Patani",
    "gn:country_code":"IN",
    "gn:dem":598,
    "gn:feature_class":"P",
    "gn:feature_code":"PPL",
    "gn:name":"Pat\u0101ni",
    "gn:population":0,
    "gn:timezone":"Asia/Kolkata",
    "iso:country":"IN",
    "name:fra_x_preferred":[
        "Patani"
    ],
    "name:jpn_x_preferred":[
        "\u6df1\u5357\u90e8"
    ],
    "name:msa_x_preferred":[
        "Pattani"
    ],
    "name:rus_x_preferred":[
        "\u0412\u0435\u043b\u0438\u043a\u0430\u044f \u041f\u0430\u0442\u0430\u043d\u0438"
    ],
    "name:tha_x_preferred":[
        "\u0e1b\u0e32\u0e15\u0e32\u0e19\u0e35"
    ],
    "name:ukr_x_preferred":[
        "\u041f\u0430\u0442\u0430\u043d\u0456"
    ],
    "name:und_x_variant":[
        "Pat\u0101ni",
        "Chauki"
    ],
    "name:zho_x_preferred":[
        "\u6cf0\u56fd\u5357\u90e8\u4e09\u5e9c"
    ],
    "wof:name":"Patani",
    "wof:placetype":"locality"
},
  "geometry": {"coordinates":[74.20446,33.16096],"type":"Point"}
}