{
  "type": "Feature",
  "properties": {
    "gn:admin1_code":"17.0",
    "gn:admin2_code":"279.0",
    "gn:asciiname":"Chammu",
    "gn:country_code":"IN",
    "gn:dem":1388,
    "gn:feature_class":"P",
    "gn:feature_code":"PPL",
    "gn:name":"Chammu",
    "gn:population":0,
    "gn:timezone":"Asia/Kolkata",
    "iso:country":"IN",
    "wof:name":"Chammu",
    "wof:placetype":"locality"
},
  "geometry": {"coordinates":[94.65114,25.061],"type":"Point"}
}