{
  "type": "Feature",
  "properties": {
    "iso:country":"IN",
    "ks:ks_name":"Maddipativarigudem",
    "ks:ks_pop":61,
    "ks:ks_type":"HABITATION",
    "name:eng_x_preferred":[
        "Maddipativarigudem"
    ],
    "wof:name":"Maddipativarigudem",
    "wof:placetype":"locality",
    "wof:population":61
},
  "geometry": {"coordinates":[81.21172799999999,17.005897],"type":"Point"}
}