{
  "type": "Feature",
  "properties": {
    "gn:admin1_code":"36",
    "gn:admin2_code":"180.0",
    "gn:asciiname":"Purwa Yar Muhammad",
    "gn:country_code":"IN",
    "gn:dem":120,
    "gn:feature_class":"P",
    "gn:feature_code":"PPL",
    "gn:name":"Purwa Y\u0101r Muhammad",
    "gn:population":0,
    "gn:timezone":"Asia/Kolkata",
    "iso:country":"IN",
    "wof:name":"Purwa Yar Muhammad",
    "wof:placetype":"locality"
},
  "geometry": {"coordinates":[81.59466999999999,27.64353],"type":"Point"}
}