{
  "type": "Feature",
  "properties": {
    "iso:country":"IN",
    "ks:ks_name":"Mathura",
    "ks:ks_pop":284,
    "ks:ks_type":"VILLAGE",
    "name:eng_x_preferred":[
        "Mathura"
    ],
    "wof:name":"Mathura",
    "wof:placetype":"locality",
    "wof:population":284
},
  "geometry": {"coordinates":[87.016077,23.975467],"type":"Point"}
}