{
  "type": "Feature",
  "properties": {
    "gn:admin1_code":"19",
    "gn:admin2_code":"560.0",
    "gn:asciiname":"Huchunur",
    "gn:country_code":"IN",
    "gn:dem":561,
    "gn:feature_class":"P",
    "gn:feature_code":"PPL",
    "gn:name":"Huchun\u016br",
    "gn:population":0,
    "gn:timezone":"Asia/Kolkata",
    "iso:country":"IN",
    "wof:name":"Huchunur",
    "wof:placetype":"neighbourhood"
},
  "geometry": {"coordinates":[76.02154,16.00324],"type":"Point"}
}