{
  "type": "Feature",
  "properties": {
    "iso:country":"IN",
    "ks:ks_name":"Gandametta",
    "ks:ks_type":"VILLAGE",
    "name:eng_x_preferred":[
        "Gandametta"
    ],
    "wof:name":"Gandametta",
    "wof:placetype":"locality"
},
  "geometry": {"coordinates":[82.94390300000001,18.27113],"type":"Point"}
}