{
  "type": "Feature",
  "properties": {
    "iso:country":"IN",
    "ks:ks_name":"Handisara",
    "ks:ks_pop":12,
    "ks:ks_type":"HABITATION",
    "name:eng_x_preferred":[
        "Handisara"
    ],
    "wof:name":"Handisara",
    "wof:placetype":"locality",
    "wof:population":12
},
  "geometry": {"coordinates":[74.795407,13.943461],"type":"Point"}
}