{
  "type": "Feature",
  "properties": {
    "iso:country":"IN",
    "ks:ks_name":"Godanpatti",
    "ks:ks_pop":592,
    "ks:ks_type":"VILLAGE",
    "ks:ks_uagg_main":0,
    "name:eng_x_preferred":[
        "Godanpatti"
    ],
    "wof:name":"Godanpatti",
    "wof:placetype":"neighbourhood",
    "wof:population":592
},
  "geometry": {"coordinates":[85.62255,26.087302],"type":"Point"}
}