{
  "type": "Feature",
  "properties": {
    "iso:country":"IN",
    "ks:ks_name":"Kathikutchanur",
    "ks:ks_pop":462,
    "ks:ks_type":"HABITATION",
    "name:eng_x_preferred":[
        "Kathikutchanur"
    ],
    "wof:name":"Kathikutchanur",
    "wof:placetype":"locality",
    "wof:population":462
},
  "geometry": {"coordinates":[79.212768,11.93398],"type":"Point"}
}