{
  "type": "Feature",
  "properties": {
    "iso:country":"IN",
    "ks:ks_name":"Allamputtu",
    "ks:ks_pop":108,
    "ks:ks_type":"VILLAGE",
    "name:eng_x_preferred":[
        "Allamputtu"
    ],
    "wof:name":"Allamputtu",
    "wof:placetype":"locality",
    "wof:population":108
},
  "geometry": {"coordinates":[82.849754,18.09235],"type":"Point"}
}