{
  "type": "Feature",
  "properties": {
    "gn:admin1_code":"35",
    "gn:admin2_code":"451.0",
    "gn:asciiname":"Kathotia",
    "gn:country_code":"IN",
    "gn:dem":414,
    "gn:feature_class":"P",
    "gn:feature_code":"PPL",
    "gn:name":"Kathotia",
    "gn:population":0,
    "gn:timezone":"Asia/Kolkata",
    "iso:country":"IN",
    "ks:ks_name":"Kathotiya",
    "ks:ks_pop":355,
    "ks:ks_type":"VILLAGE",
    "name:eng_x_preferred":[
        "Kathotiya"
    ],
    "name:eng_x_variant":[
        "Kathotia"
    ],
    "wof:name":"Kathotiya",
    "wof:placetype":"locality",
    "wof:population":355
},
  "geometry": {"coordinates":[79.950805,22.881969],"type":"Point"}
}