{
  "type": "Feature",
  "properties": {
    "gn:admin1_code":"12.0",
    "gn:asciiname":"Sadwanian",
    "gn:country_code":"IN",
    "gn:dem":1314,
    "gn:feature_class":"P",
    "gn:feature_code":"PPL",
    "gn:name":"Sadw\u0101ni\u0101n",
    "gn:population":0,
    "gn:timezone":"Asia/Kolkata",
    "iso:country":"IN",
    "name:und_x_variant":[
        "Sadw\u0101ni\u0101n",
        "Sadwanian"
    ],
    "wof:name":"Sadwanian",
    "wof:placetype":"locality"
},
  "geometry": {"coordinates":[73.97505,34.10361],"type":"Point"}
}