{
  "type": "Feature",
  "properties": {
    "gn:admin1_code":"38",
    "gn:admin2_code":"358.0",
    "gn:asciiname":"Bhaluani Khurd",
    "gn:country_code":"IN",
    "gn:dem":230,
    "gn:feature_class":"P",
    "gn:feature_code":"PPL",
    "gn:name":"Bhalu\u0101ni Khurd",
    "gn:population":0,
    "gn:timezone":"Asia/Kolkata",
    "iso:country":"IN",
    "ks:ks_alt_nam":"Bhalu\u0101ni Khurd",
    "ks:ks_name":"Bhaluani Khurd",
    "ks:ks_type":"VILLAGE",
    "name:eng_x_preferred":[
        "Bhaluani Khurd"
    ],
    "name:eng_x_variant":[
        "Bhalu\u0101ni Khurd"
    ],
    "wof:name":"Bhaluani Khurd",
    "wof:placetype":"locality"
},
  "geometry": {"coordinates":[83.951465,24.229817],"type":"Point"}
}