{
  "type": "Feature",
  "properties": {
    "iso:country":"IN",
    "ks:ks_name":"Bichla Tola",
    "ks:ks_pop":433,
    "ks:ks_type":"HABITATION",
    "name:eng_x_preferred":[
        "Bichla Tola"
    ],
    "wof:name":"Bichla Tola",
    "wof:placetype":"locality",
    "wof:population":433
},
  "geometry": {"coordinates":[83.41916500000001,24.468112],"type":"Point"}
}