{
  "type": "Feature",
  "properties": {
    "gn:admin1_code":"12.0",
    "gn:admin2_code":"12.0",
    "gn:asciiname":"Tikyun",
    "gn:country_code":"IN",
    "gn:dem":1720,
    "gn:feature_class":"P",
    "gn:feature_code":"PPL",
    "gn:name":"Tikyun",
    "gn:population":0,
    "gn:timezone":"Asia/Kolkata",
    "iso:country":"IN",
    "wof:name":"Tikyun",
    "wof:placetype":"locality"
},
  "geometry": {"coordinates":[74.87291999999999,33.84713],"type":"Point"}
}