{
  "type": "Feature",
  "properties": {
    "gn:country":"IN",
    "gn:fcode":"PPL",
    "gn:pop":14297,
    "iso:country":"IN",
    "name:ben_x_preferred":[
        "\u09ac\u09c1\u0997\u09c1\u09a6\u09be"
    ],
    "name:bpy_x_preferred":[
        "\u09ac\u09c1\u0997\u09c1\u09a6\u09be"
    ],
    "name:chi_x_preferred":[
        "\u5e03\u53e4\u8fbe"
    ],
    "name:dut_x_preferred":[
        "Buguda"
    ],
    "name:eng_x_preferred":[
        "Buguda"
    ],
    "name:ita_x_preferred":[
        "Buguda"
    ],
    "name:may_x_preferred":[
        "Buguda"
    ],
    "name:nan_x_preferred":[
        "Buguda"
    ],
    "name:new_x_preferred":[
        "\u092c\u0941\u0917\u0941\u0921\u093e"
    ],
    "name:ori_x_preferred":[
        "\u0b2c\u0b41\u0b17\u0b41\u0b21\u0b3c\u0b3e"
    ],
    "name:por_x_preferred":[
        "Buguda"
    ],
    "name:swe_x_preferred":[
        "Buguda"
    ],
    "name:unk_x_variant":[
        "Buguda"
    ],
    "name:vie_x_preferred":[
        "Buguda"
    ],
    "qs:name":"Budaguda",
    "qs:name_adm0":"India",
    "qs:name_adm1":"Orissa",
    "qs:photos_9r":0,
    "qs:photos_sr":0,
    "qs:placetype":"Town",
    "qs:pop_sr":"6",
    "wof:name":"Budaguda",
    "wof:placetype":"locality",
    "wof:population":14297
},
  "geometry": {"coordinates":[84.79084,19.80806],"type":"Point"}
}