{
  "type": "Feature",
  "properties": {
    "gn:admin1_code":"35",
    "gn:admin2_code":"458.0",
    "gn:asciiname":"Gelon",
    "gn:country_code":"IN",
    "gn:dem":530,
    "gn:feature_class":"P",
    "gn:feature_code":"PPL",
    "gn:name":"Gelon",
    "gn:population":0,
    "gn:timezone":"Asia/Kolkata",
    "iso:country":"IN",
    "name:als_x_preferred":[
        "Gelon"
    ],
    "name:bul_x_preferred":[
        "\u0413\u0435\u043b\u043e\u043d"
    ],
    "name:cat_x_preferred":[
        "Gel\u00f3"
    ],
    "name:ces_x_preferred":[
        "Gel\u00f3n"
    ],
    "name:deu_x_preferred":[
        "Gelon"
    ],
    "name:fin_x_preferred":[
        "Gelon"
    ],
    "name:fra_x_preferred":[
        "G\u00e9lon"
    ],
    "name:heb_x_preferred":[
        "\u05d2\u05dc\u05d5\u05df"
    ],
    "name:ita_x_preferred":[
        "Gelone"
    ],
    "name:jpn_x_preferred":[
        "\u30b2\u30ed\u30f3"
    ],
    "name:lat_x_preferred":[
        "Gelon"
    ],
    "name:pol_x_preferred":[
        "Gelon"
    ],
    "name:por_x_preferred":[
        "Gel\u00e3o"
    ],
    "name:rus_x_preferred":[
        "\u0413\u0435\u043b\u043e\u043d"
    ],
    "name:scn_x_preferred":[
        "Giluni"
    ],
    "name:spa_x_preferred":[
        "Gel\u00f3n"
    ],
    "name:swe_x_preferred":[
        "Gelon"
    ],
    "name:ukr_x_preferred":[
        "\u0413\u0435\u043b\u043e\u043d"
    ],
    "wof:name":"Gelon",
    "wof:placetype":"locality"
},
  "geometry": {"coordinates":[77.32804,24.42309],"type":"Point"}
}