{
  "type": "Feature",
  "properties": {
    "iso:country":"IN",
    "ks:ks_name":"Turebongalu",
    "ks:ks_pop":49,
    "ks:ks_type":"HABITATION",
    "name:eng_x_preferred":[
        "Turebongalu"
    ],
    "wof:name":"Turebongalu",
    "wof:placetype":"locality",
    "wof:population":49
},
  "geometry": {"coordinates":[82.439193,17.928493],"type":"Point"}
}