{
  "type": "Feature",
  "properties": {
    "iso:country":"IN",
    "ks:ks_name":"Kurthihawa",
    "ks:ks_pop":261,
    "ks:ks_type":"HABITATION",
    "name:eng_x_preferred":[
        "Kurthihawa"
    ],
    "wof:name":"Kurthihawa",
    "wof:placetype":"locality",
    "wof:population":261
},
  "geometry": {"coordinates":[82.888921,24.607067],"type":"Point"}
}