{
  "type": "Feature",
  "properties": {
    "iso:country":"IN",
    "ks:ks_name":"Kuntari Laga Phali",
    "ks:ks_pop":612,
    "ks:ks_type":"HABITATION",
    "name:eng_x_preferred":[
        "Kuntari Laga Phali"
    ],
    "wof:name":"Kuntari Laga Phali",
    "wof:placetype":"locality",
    "wof:population":612
},
  "geometry": {"coordinates":[79.44431899999999,30.243828],"type":"Point"}
}