{
  "type": "Feature",
  "properties": {
    "gn:admin1_code":"36",
    "gn:admin2_code":"136.0",
    "gn:asciiname":"Barwara Khas",
    "gn:country_code":"IN",
    "gn:dem":192,
    "gn:feature_class":"P",
    "gn:feature_code":"PPL",
    "gn:name":"Barw\u0101ra Kh\u0101s",
    "gn:population":0,
    "gn:timezone":"Asia/Kolkata",
    "iso:country":"IN",
    "ks:ks_alt_nam":"Barw\u0101ra Kh\u0101s",
    "ks:ks_name":"Barwara Khas",
    "ks:ks_type":"VILLAGE",
    "name:eng_x_preferred":[
        "Barwara Khas"
    ],
    "name:eng_x_variant":[
        "Barw\u0101ra Kh\u0101s"
    ],
    "wof:name":"Barwara Khas",
    "wof:placetype":"locality"
},
  "geometry": {"coordinates":[78.98275099999999,28.804692],"type":"Point"}
}