{
  "type": "Feature",
  "properties": {
    "iso:country":"IN",
    "ks:ks_alt_nam":"BENJ RAI KA TOLA",
    "ks:ks_name":"Benj Rai Ka Tola",
    "ks:ks_pop":1820,
    "ks:ks_type":"HABITATION",
    "ks:ks_uagg_main":0,
    "name:eng_x_preferred":[
        "Benj Rai Ka Tola"
    ],
    "wof:name":"Benj Rai Ka Tola",
    "wof:placetype":"neighbourhood",
    "wof:population":1820
},
  "geometry": {"coordinates":[84.570896,25.781108],"type":"Point"}
}