{
  "type": "Feature",
  "properties": {
    "iso:country":"IN",
    "ks:ks_name":"Nidhavali",
    "ks:ks_pop":430,
    "ks:ks_type":"VILLAGE",
    "name:eng_x_preferred":[
        "Nidhavali"
    ],
    "wof:name":"Nidhavali",
    "wof:placetype":"locality",
    "wof:population":430
},
  "geometry": {"coordinates":[73.137129,18.798254],"type":"Point"}
}