{
  "type": "Feature",
  "properties": {
    "gn:admin1_code":"35.0",
    "gn:admin2_code":"447.0",
    "gn:asciiname":"Narkhed",
    "gn:country_code":"IN",
    "gn:dem":728,
    "gn:feature_class":"P",
    "gn:feature_code":"PPL",
    "gn:name":"Narkhed",
    "gn:population":0,
    "gn:timezone":"Asia/Kolkata",
    "iso:country":"IN",
    "name:ben_x_preferred":[
        "\u09a8\u09be\u09b0\u0996\u09c7\u09a6"
    ],
    "name:bpy_x_preferred":[
        "\u09a8\u09be\u09b0\u0996\u09c7\u09a6"
    ],
    "name:hif_x_preferred":[
        "Narkhed"
    ],
    "name:hin_x_preferred":[
        "\u0928\u0930\u0916\u0947\u0921\u093c"
    ],
    "name:ind_x_preferred":[
        "Narkhed"
    ],
    "name:ita_x_preferred":[
        "Narkhed"
    ],
    "name:mar_x_preferred":[
        "\u0928\u0930\u0916\u0947\u0921"
    ],
    "name:msa_x_preferred":[
        "Narkhed"
    ],
    "name:new_x_preferred":[
        "\u0928\u0930\u094d\u0916\u0947\u0926"
    ],
    "name:nld_x_preferred":[
        "Narkhed"
    ],
    "name:ori_x_preferred":[
        "\u0b28\u0b3e\u0b30\u0b4d\u0b16\u0b47\u0b26\u0b4d"
    ],
    "name:por_x_preferred":[
        "Narkhed"
    ],
    "name:urd_x_preferred":[
        "\u0646\u0631\u06a9\u06be\u06cc\u0691"
    ],
    "name:vie_x_preferred":[
        "Narkhed"
    ],
    "name:zho_x_preferred":[
        "\u7eb3\u5c14\u51ef\u5fb7"
    ],
    "wof:name":"Narkhed",
    "wof:placetype":"locality"
},
  "geometry": {"coordinates":[78.25426999999998,21.69712],"type":"Point"}
}