{
  "type": "Feature",
  "properties": {
    "iso:country":"IN",
    "ks:ks_name":"Channagonda",
    "ks:ks_pop":1079,
    "ks:ks_type":"VILLAGE",
    "name:eng_x_preferred":[
        "Channagonda"
    ],
    "wof:name":"Channagonda",
    "wof:placetype":"locality",
    "wof:population":1079
},
  "geometry": {"coordinates":[74.76189100000001,14.043591],"type":"Point"}
}