{
  "type": "Feature",
  "properties": {
    "iso:country":"IN",
    "ks:ks_name":"Chakk Parasiya",
    "ks:ks_pop":54,
    "ks:ks_type":"HABITATION",
    "name:eng_x_preferred":[
        "Chakk Parasiya"
    ],
    "wof:name":"Chakk Parasiya",
    "wof:placetype":"locality",
    "wof:population":54
},
  "geometry": {"coordinates":[79.092598,23.783848],"type":"Point"}
}