{
  "type": "Feature",
  "properties": {
    "iso:country":"IN",
    "ks:ks_name":"Mumbar",
    "ks:ks_pop":114,
    "ks:ks_type":"HABITATION",
    "name:eng_x_preferred":[
        "Mumbar"
    ],
    "wof:name":"Mumbar",
    "wof:placetype":"locality",
    "wof:population":114
},
  "geometry": {"coordinates":[74.782448,13.658318],"type":"Point"}
}