{
  "type": "Feature",
  "properties": {
    "iso:country":"IN",
    "ks:ks_name":"Vanpura",
    "ks:ks_pop":268,
    "ks:ks_type":"HABITATION",
    "name:eng_x_preferred":[
        "Vanpura"
    ],
    "wof:name":"Vanpura",
    "wof:placetype":"locality",
    "wof:population":268
},
  "geometry": {"coordinates":[74.825238,23.494649],"type":"Point"}
}