{
  "type": "Feature",
  "properties": {
    "gn:admin1_code":"36",
    "gn:admin2_code":"194.0",
    "gn:asciiname":"Kandwa",
    "gn:country_code":"IN",
    "gn:dem":91,
    "gn:feature_class":"P",
    "gn:feature_code":"PPL",
    "gn:name":"Kandwa",
    "gn:population":0,
    "gn:timezone":"Asia/Kolkata",
    "iso:country":"IN",
    "name:bpy_x_preferred":[
        "\u0995\u09be\u09a8\u09cd\u09a6\u09f1\u09be"
    ],
    "name:ita_x_preferred":[
        "Kandwa"
    ],
    "name:msa_x_preferred":[
        "Kandwa"
    ],
    "name:new_x_preferred":[
        "\u0915\u0928\u094d\u0926\u094d\u0935\u093e"
    ],
    "name:nld_x_preferred":[
        "Kandwa"
    ],
    "name:pol_x_preferred":[
        "Kandwa"
    ],
    "name:por_x_preferred":[
        "Kandwa"
    ],
    "name:urd_x_preferred":[
        "\u06a9\u0646\u0688\u0648\u0627"
    ],
    "name:vie_x_preferred":[
        "Kandwa"
    ],
    "wof:name":"Kandwa",
    "wof:placetype":"locality"
},
  "geometry": {"coordinates":[82.56012,26.10726],"type":"Point"}
}