{
  "type": "Feature",
  "properties": {
    "iso:country":"IN",
    "ks:ks_name":"Bagdahasa",
    "ks:ks_pop":766,
    "ks:ks_type":"HABITATION",
    "name:eng_x_preferred":[
        "Bagdahasa"
    ],
    "wof:name":"Bagdahasa",
    "wof:placetype":"locality",
    "wof:population":766
},
  "geometry": {"coordinates":[87.450722,23.123004],"type":"Point"}
}