{
  "type": "Feature",
  "properties": {
    "iso:country":"IN",
    "ks:ks_name":"Bolgeri",
    "ks:ks_pop":99,
    "ks:ks_type":"HABITATION",
    "name:eng_x_preferred":[
        "Bolgeri"
    ],
    "wof:name":"Bolgeri",
    "wof:placetype":"locality",
    "wof:population":99
},
  "geometry": {"coordinates":[74.50964,14.32781],"type":"Point"}
}