{
  "type": "Feature",
  "properties": {
    "iso:country":"IN",
    "ks:ks_alt_nam":"barhmayin",
    "ks:ks_name":"Barhmayin",
    "ks:ks_pop":93,
    "ks:ks_type":"HABITATION",
    "name:eng_x_preferred":[
        "Barhmayin"
    ],
    "wof:name":"Barhmayin",
    "wof:placetype":"locality",
    "wof:population":93
},
  "geometry": {"coordinates":[82.929436,25.394941],"type":"Point"}
}