{
  "type": "Feature",
  "properties": {
    "iso:country":"IN",
    "ks:ks_name":"Sukhadukhia",
    "ks:ks_pop":551,
    "ks:ks_type":"VILLAGE",
    "ks:ks_uagg_main":0,
    "name:eng_x_preferred":[
        "Sukhadukhia"
    ],
    "wof:name":"Sukhadukhia",
    "wof:placetype":"neighbourhood",
    "wof:population":551
},
  "geometry": {"coordinates":[87.194399,21.797249],"type":"Point"}
}