{
  "type": "Feature",
  "properties": {
    "gn:admin1_code":"25.0",
    "gn:admin2_code":"631.0",
    "gn:asciiname":"Kottebarandur",
    "gn:country_code":"IN",
    "gn:dem":869,
    "gn:feature_class":"P",
    "gn:feature_code":"PPL",
    "gn:name":"K\u014dttebarand\u016br",
    "gn:population":0,
    "gn:timezone":"Asia/Kolkata",
    "iso:country":"IN",
    "wof:name":"Kottebarandur",
    "wof:placetype":"neighbourhood"
},
  "geometry": {"coordinates":[77.79707000000001,12.62975],"type":"Point"}
}