{
  "type": "Feature",
  "properties": {
    "gn:admin1_code":"24.0",
    "gn:admin2_code":"107.0",
    "gn:asciiname":"Dhaula Danta",
    "gn:country_code":"IN",
    "gn:dem":500,
    "gn:feature_class":"P",
    "gn:feature_code":"PPL",
    "gn:name":"Dhaula D\u0101nta",
    "gn:population":0,
    "gn:timezone":"Asia/Kolkata",
    "iso:country":"IN",
    "ks:ks_alt_nam":"Dhaula D\u0101nta",
    "ks:ks_name":"Dhaula Danta",
    "ks:ks_type":"VILLAGE",
    "name:eng_x_preferred":[
        "Dhaula Danta"
    ],
    "name:eng_x_variant":[
        "Dhaula D\u0101nta"
    ],
    "wof:name":"Dhaula Danta",
    "wof:placetype":"locality"
},
  "geometry": {"coordinates":[76.496865,26.723898],"type":"Point"}
}