{
  "type": "Feature",
  "properties": {
    "gn:admin1_code":"37",
    "gn:admin2_code":"404.0",
    "gn:asciiname":"Pahargaon",
    "gn:country_code":"IN",
    "gn:dem":591,
    "gn:feature_class":"P",
    "gn:feature_code":"PPL",
    "gn:name":"Pah\u0101rgaon",
    "gn:population":0,
    "gn:timezone":"Asia/Kolkata",
    "iso:country":"IN",
    "ks:ks_alt_nam":"Pah\u0101rgaon",
    "ks:ks_name":"Pahargaon",
    "ks:ks_pop":369,
    "ks:ks_type":"VILLAGE",
    "name:eng_x_preferred":[
        "Pahargaon"
    ],
    "name:eng_x_variant":[
        "Pah\u0101rgaon"
    ],
    "wof:name":"Pahargaon",
    "wof:placetype":"locality",
    "wof:population":369
},
  "geometry": {"coordinates":[82.34528400000001,22.526656],"type":"Point"}
}