{
  "type": "Feature",
  "properties": {
    "iso:country":"IN",
    "ks:ks_name":"Chaturpatti",
    "ks:ks_pop":0,
    "ks:ks_type":"VILLAGE",
    "name:eng_x_preferred":[
        "Chaturpatti"
    ],
    "wof:name":"Chaturpatti",
    "wof:placetype":"locality",
    "wof:population":0
},
  "geometry": {"coordinates":[82.307784,25.021196],"type":"Point"}
}