{
  "type": "Feature",
  "properties": {
    "iso:country":"IN",
    "ks:ks_name":"Chuniya Tola",
    "ks:ks_pop":821,
    "ks:ks_type":"HABITATION",
    "name:eng_x_preferred":[
        "Chuniya Tola"
    ],
    "wof:name":"Chuniya Tola",
    "wof:placetype":"locality",
    "wof:population":821
},
  "geometry": {"coordinates":[83.079268,23.949993],"type":"Point"}
}