{
  "type": "Feature",
  "properties": {
    "gn:admin1_code":"34.0",
    "gn:admin2_code":"220.0",
    "gn:asciiname":"Chak Fateh",
    "gn:country_code":"IN",
    "gn:dem":54,
    "gn:feature_class":"P",
    "gn:feature_code":"PPL",
    "gn:name":"Chak Fateh",
    "gn:population":0,
    "gn:timezone":"Asia/Kolkata",
    "iso:country":"IN",
    "ks:ks_name":"Chak Fateh",
    "ks:ks_pop":389,
    "ks:ks_type":"VILLAGE",
    "name:eng_x_preferred":[
        "Chak Fateh"
    ],
    "wof:name":"Chak Fateh",
    "wof:placetype":"locality",
    "wof:population":389
},
  "geometry": {"coordinates":[85.466617,25.703344],"type":"Point"}
}