{
  "type": "Feature",
  "properties": {
    "iso:country":"IN",
    "ks:ks_name":"Balimusti",
    "ks:ks_pop":166,
    "ks:ks_type":"VILLAGE",
    "name:eng_x_preferred":[
        "Balimusti"
    ],
    "wof:name":"Balimusti",
    "wof:placetype":"locality",
    "wof:population":166
},
  "geometry": {"coordinates":[83.831823,20.028466],"type":"Point"}
}