{
  "type": "Feature",
  "properties": {
    "iso:country":"IN",
    "ks:ks_name":"Farti",
    "ks:ks_pop":89,
    "ks:ks_type":"VILLAGE",
    "name:eng_x_preferred":[
        "Farti"
    ],
    "wof:name":"Farti",
    "wof:placetype":"locality",
    "wof:population":89
},
  "geometry": {"coordinates":[78.245683,30.250071],"type":"Point"}
}