{
  "type": "Feature",
  "properties": {
    "iso:country":"IN",
    "ks:ks_name":"Sultanpur",
    "ks:ks_pop":407,
    "ks:ks_type":"VILLAGE",
    "name:eng_x_preferred":[
        "Sultanpur"
    ],
    "wof:name":"Sultanpur",
    "wof:placetype":"locality",
    "wof:population":407
},
  "geometry": {"coordinates":[77.768254,18.775218],"type":"Point"}
}