{
  "type": "Feature",
  "properties": {
    "iso:country":"IN",
    "ks:ks_name":"Dimirikhole",
    "ks:ks_pop":133,
    "ks:ks_type":"VILLAGE",
    "name:eng_x_preferred":[
        "Dimirikhole"
    ],
    "wof:name":"Dimirikhole",
    "wof:placetype":"locality",
    "wof:population":133
},
  "geometry": {"coordinates":[84.102147,20.622494],"type":"Point"}
}