{
  "type": "Feature",
  "properties": {
    "iso:country":"IN",
    "ks:ks_name":"Konkani Falia",
    "ks:ks_pop":589,
    "ks:ks_type":"HABITATION",
    "name:eng_x_preferred":[
        "Konkani Falia"
    ],
    "wof:name":"Konkani Falia",
    "wof:placetype":"locality",
    "wof:population":589
},
  "geometry": {"coordinates":[73.4315,20.927722],"type":"Point"}
}