{
  "type": "Feature",
  "properties": {
    "iso:country":"IN",
    "ks:ks_alt_nam":"WAKYA MAU",
    "ks:ks_name":"Wakya Mau",
    "ks:ks_pop":376,
    "ks:ks_type":"HABITATION",
    "name:eng_x_preferred":[
        "Wakya Mau"
    ],
    "wof:name":"Wakya Mau",
    "wof:placetype":"locality",
    "wof:population":376
},
  "geometry": {"coordinates":[81.617532,26.534823],"type":"Point"}
}