{
  "type": "Feature",
  "properties": {
    "iso:country":"IN",
    "ks:ks_name":"Barmanpara Jaigir Chilakhana",
    "ks:ks_pop":967,
    "ks:ks_type":"HABITATION",
    "name:eng_x_preferred":[
        "Barmanpara Jaigir Chilakhana"
    ],
    "wof:name":"Barmanpara Jaigir Chilakhana",
    "wof:placetype":"locality",
    "wof:population":967
},
  "geometry": {"coordinates":[89.614745,26.310566],"type":"Point"}
}