{
  "type": "Feature",
  "properties": {
    "iso:country":"IN",
    "ks:ks_name":"Niz Kampur",
    "ks:ks_pop":1003,
    "ks:ks_type":"VILLAGE",
    "ks:ks_uagg_main":0,
    "name:eng_x_preferred":[
        "Niz Kampur"
    ],
    "wof:name":"Niz Kampur",
    "wof:placetype":"neighbourhood",
    "wof:population":1003
},
  "geometry": {"coordinates":[92.652525,26.180097],"type":"Point"}
}