{
  "type": "Feature",
  "properties": {
    "iso:country":"IN",
    "ks:ks_alt_nam":"KPC colony",
    "ks:ks_name":"Kpc Colony",
    "ks:ks_pop":26,
    "ks:ks_type":"HABITATION",
    "name:eng_x_preferred":[
        "Kpc Colony"
    ],
    "wof:name":"Kpc Colony",
    "wof:placetype":"locality",
    "wof:population":26
},
  "geometry": {"coordinates":[74.72344099999999,14.883598],"type":"Point"}
}