{
  "type": "Feature",
  "properties": {
    "gn:admin1_code":"16.0",
    "gn:admin2_code":"505",
    "gn:asciiname":"Khapa",
    "gn:country_code":"IN",
    "gn:dem":275,
    "gn:feature_class":"P",
    "gn:feature_code":"PPL",
    "gn:name":"Kh\u0101pa",
    "gn:population":0,
    "gn:timezone":"Asia/Kolkata",
    "iso:country":"IN",
    "name:und_x_variant":[
        "Kh\u0101pa"
    ],
    "wof:name":"Khapa",
    "wof:placetype":"locality"
},
  "geometry": {"coordinates":[78.95219,20.91808],"type":"Point"}
}