{
  "type": "Feature",
  "properties": {
    "iso:country":"IN",
    "ks:ks_name":"Jambhulpada",
    "ks:ks_pop":200,
    "ks:ks_type":"HABITATION",
    "name:eng_x_preferred":[
        "Jambhulpada"
    ],
    "wof:name":"Jambhulpada",
    "wof:placetype":"locality",
    "wof:population":200
},
  "geometry": {"coordinates":[73.25739400000001,19.411189],"type":"Point"}
}