{
  "type": "Feature",
  "properties": {
    "iso:country":"IN",
    "ks:ks_alt_nam":"BAGILA DHURA",
    "ks:ks_name":"Bagila Dhura",
    "ks:ks_pop":515,
    "ks:ks_type":"HABITATION",
    "name:eng_x_preferred":[
        "Bagila Dhura"
    ],
    "wof:name":"Bagila Dhura",
    "wof:placetype":"locality",
    "wof:population":515
},
  "geometry": {"coordinates":[88.759587,26.849425],"type":"Point"}
}