{
  "type": "Feature",
  "properties": {
    "iso:country":"IN",
    "ks:ks_name":"Surlangi",
    "ks:ks_pop":54,
    "ks:ks_type":"HABITATION",
    "name:eng_x_preferred":[
        "Surlangi"
    ],
    "wof:name":"Surlangi",
    "wof:placetype":"locality",
    "wof:population":54
},
  "geometry": {"coordinates":[83.257616,19.526332],"type":"Point"}
}