{
  "type": "Feature",
  "properties": {
    "iso:country":"IN",
    "ks:ks_name":"Bhelwan",
    "ks:ks_pop":1468,
    "ks:ks_type":"VILLAGE",
    "name:eng_x_preferred":[
        "Bhelwan"
    ],
    "wof:name":"Bhelwan",
    "wof:placetype":"locality",
    "wof:population":1468
},
  "geometry": {"coordinates":[83.85014200000001,22.359084],"type":"Point"}
}