{
  "type": "Feature",
  "properties": {
    "iso:country":"IN",
    "ks:ks_name":"Dadar",
    "ks:ks_pop":2,
    "ks:ks_type":"HABITATION",
    "name:eng_x_preferred":[
        "Dadar"
    ],
    "wof:name":"Dadar",
    "wof:placetype":"locality",
    "wof:population":2
},
  "geometry": {"coordinates":[81.538922,24.541452],"type":"Point"}
}