{
  "type": "Feature",
  "properties": {
    "gn:admin1_code":"19.0",
    "gn:admin2_code":"584.0",
    "gn:asciiname":"Marchanahalli",
    "gn:country_code":"IN",
    "gn:dem":660,
    "gn:feature_class":"P",
    "gn:feature_code":"PPL",
    "gn:name":"Marchanahalli",
    "gn:population":0,
    "gn:timezone":"Asia/Kolkata",
    "iso:country":"IN",
    "ks:ks_name":"Marchanahalli",
    "ks:ks_pop":1205,
    "ks:ks_type":"VILLAGE",
    "name:eng_x_preferred":[
        "Marchanahalli"
    ],
    "wof:name":"Marchanahalli",
    "wof:placetype":"locality",
    "wof:population":1205
},
  "geometry": {"coordinates":[77.10954599999999,12.610483],"type":"Point"}
}