{
  "type": "Feature",
  "properties": {
    "gn:admin1_code":"40.0",
    "gn:admin2_code":"533.0",
    "gn:asciiname":"Gudpa",
    "gn:country_code":"IN",
    "gn:dem":386,
    "gn:feature_class":"P",
    "gn:feature_code":"PPL",
    "gn:name":"G\u016bdpa",
    "gn:population":0,
    "gn:timezone":"Asia/Kolkata",
    "iso:country":"IN",
    "wof:name":"Gudpa",
    "wof:placetype":"locality"
},
  "geometry": {"coordinates":[78.19744,18.77439],"type":"Point"}
}