{
  "type": "Feature",
  "properties": {
    "iso:country":"IN",
    "ks:ks_name":"Haipalu",
    "ks:ks_pop":48,
    "ks:ks_type":"HABITATION",
    "name:eng_x_preferred":[
        "Haipalu"
    ],
    "wof:name":"Haipalu",
    "wof:placetype":"locality",
    "wof:population":48
},
  "geometry": {"coordinates":[75.069836,13.207476],"type":"Point"}
}