{
  "type": "Feature",
  "properties": {
    "iso:country":"IN",
    "ks:ks_name":"Gadesara",
    "ks:ks_pop":293,
    "ks:ks_type":"VILLAGE",
    "name:eng_x_preferred":[
        "Gadesara"
    ],
    "wof:name":"Gadesara",
    "wof:placetype":"locality",
    "wof:population":293
},
  "geometry": {"coordinates":[71.956563,25.518034],"type":"Point"}
}