{
  "type": "Feature",
  "properties": {
    "iso:country":"IN",
    "ks:ks_alt_nam":"AJARKABE GOVINDPUR",
    "ks:ks_name":"Ajarkabe Govindpur",
    "ks:ks_pop":317,
    "ks:ks_type":"HABITATION",
    "ks:ks_uagg_main":0,
    "name:eng_x_preferred":[
        "Ajarkabe Govindpur"
    ],
    "wof:name":"Ajarkabe Govindpur",
    "wof:placetype":"neighbourhood",
    "wof:population":317
},
  "geometry": {"coordinates":[86.223828,25.952814],"type":"Point"}
}