{
  "type": "Feature",
  "properties": {
    "gn:admin1_code":"16",
    "gn:admin2_code":"510.0",
    "gn:asciiname":"Pimpri",
    "gn:country_code":"IN",
    "gn:dem":252,
    "gn:feature_class":"P",
    "gn:feature_code":"PPL",
    "gn:name":"Pimpri",
    "gn:population":0,
    "gn:timezone":"Asia/Kolkata",
    "iso:country":"IN",
    "name:ara_x_preferred":[
        "\u0628\u064a\u0645\u0628\u0631\u064a"
    ],
    "name:ben_bn_x_preferred":[
        "\u09aa\u09bf\u09ae\u09cd\u09aa\u09dc\u09bf"
    ],
    "name:ben_in_x_preferred":[
        "\u09aa\u09bf\u09ae\u09cd\u09aa\u09dc\u09bf"
    ],
    "name:cat_x_preferred":[
        "Pimpri"
    ],
    "name:ceb_x_preferred":[
        "Pimpri"
    ],
    "name:guj_x_preferred":[
        "\u0aaa\u0abf\u0aae\u0acd\u0aaa\u0ab0\u0ac0"
    ],
    "name:hin_x_preferred":[
        "\u092a\u093f\u0902\u092a\u0930\u0940"
    ],
    "name:kan_x_preferred":[
        "\u0caa\u0cbf\u0c82\u0caa\u0ccd\u0cb0\u0cbf"
    ],
    "name:mal_x_preferred":[
        "\u0d2a\u0d3f\u0d02\u0d2a\u0d4d\u0d30\u0d3f"
    ],
    "name:mar_x_preferred":[
        "\u092a\u093f\u0902\u092a\u0930\u0940"
    ],
    "name:pan_x_preferred":[
        "\u0a2a\u0a3f\u0a70\u0a2a\u0a30\u0a40"
    ],
    "name:swe_x_preferred":[
        "Pimpri"
    ],
    "name:tam_x_preferred":[
        "\u0baa\u0bbf\u0bae\u0bcd\u0baa\u0bcd\u0bb0\u0bbf"
    ],
    "name:tam_x_variant":[
        "\u0baa\u0bbf\u0bae\u0bcd\u0baa\u0bbf\u0bb0\u0bbf"
    ],
    "name:tel_x_preferred":[
        "\u0c2a\u0c3f\u0c02\u0c2a\u0c4d\u0c30\u0c3f"
    ],
    "name:ukr_x_preferred":[
        "\u041f\u0456\u043c\u043f\u0440\u0456"
    ],
    "name:urd_x_preferred":[
        "\u067e\u0645\u067e\u0631\u06cc"
    ],
    "wof:name":"Pimpri",
    "wof:placetype":"locality"
},
  "geometry": {"coordinates":[78.54805,20.0429],"type":"Point"}
}