{
  "type": "Feature",
  "properties": {
    "gn:admin1_code":"16",
    "gn:admin2_code":"510.0",
    "gn:asciiname":"Pimpri",
    "gn:country_code":"IN",
    "gn:dem":252,
    "gn:feature_class":"P",
    "gn:feature_code":"PPL",
    "gn:name":"Pimpri",
    "gn:population":0,
    "gn:timezone":"Asia/Kolkata",
    "iso:country":"IN",
    "name:cat_x_preferred":[
        "Pimpri"
    ],
    "name:ceb_x_preferred":[
        "Pimpri"
    ],
    "name:hin_x_preferred":[
        "\u092a\u093f\u0902\u092a\u0930\u0940"
    ],
    "name:swe_x_preferred":[
        "Pimpri"
    ],
    "name:tam_x_preferred":[
        "\u0baa\u0bbf\u0bae\u0bcd\u0baa\u0bbf\u0bb0\u0bbf"
    ],
    "name:ukr_x_preferred":[
        "\u041f\u0456\u043c\u043f\u0440\u0456"
    ],
    "name:urd_x_preferred":[
        "\u067e\u0645\u067e\u0631\u06cc"
    ],
    "wof:name":"Pimpri",
    "wof:placetype":"locality"
},
  "geometry": {"coordinates":[78.54805,20.0429],"type":"Point"}
}