{
  "type": "Feature",
  "properties": {
    "iso:country":"IN",
    "ks:ks_name":"Irumpoorani",
    "ks:ks_pop":211,
    "ks:ks_type":"HABITATION",
    "name:eng_x_preferred":[
        "Irumpoorani"
    ],
    "wof:name":"Irumpoorani",
    "wof:placetype":"locality",
    "wof:population":211
},
  "geometry": {"coordinates":[78.37009999999999,10.286254],"type":"Point"}
}