{
  "type": "Feature",
  "properties": {
    "iso:country":"IN",
    "ks:ks_name":"Amritpur Kalan",
    "ks:ks_pop":2779,
    "ks:ks_type":"HABITATION",
    "ks:ks_uagg_main":0,
    "name:eng_x_preferred":[
        "Amritpur Kalan"
    ],
    "wof:name":"Amritpur Kalan",
    "wof:placetype":"neighbourhood",
    "wof:population":2779
},
  "geometry": {"coordinates":[77.04981100000001,29.593929],"type":"Point"}
}