{
  "type": "Feature",
  "properties": {
    "iso:country":"IN",
    "ks:ks_name":"Anegudde",
    "ks:ks_pop":506,
    "ks:ks_type":"HABITATION",
    "name:eng_x_preferred":[
        "Anegudde"
    ],
    "wof:name":"Anegudde",
    "wof:placetype":"locality",
    "wof:population":506
},
  "geometry": {"coordinates":[75.065657,13.107978],"type":"Point"}
}