{
  "type": "Feature",
  "properties": {
    "iso:country":"IN",
    "ks:ks_name":"Bhawarahiyan",
    "ks:ks_pop":274,
    "ks:ks_type":"HABITATION",
    "name:eng_x_preferred":[
        "Bhawarahiyan"
    ],
    "wof:name":"Bhawarahiyan",
    "wof:placetype":"locality",
    "wof:population":274
},
  "geometry": {"coordinates":[82.809326,25.362019],"type":"Point"}
}