{
  "type": "Feature",
  "properties": {
    "iso:country":"IN",
    "ks:ks_name":"Danra",
    "ks:ks_pop":632,
    "ks:ks_type":"VILLAGE",
    "name:eng_x_preferred":[
        "Danra"
    ],
    "wof:name":"Danra",
    "wof:placetype":"locality",
    "wof:population":632
},
  "geometry": {"coordinates":[85.716138,23.881591],"type":"Point"}
}