{
  "type": "Feature",
  "properties": {
    "gn:admin1_code":"35.0",
    "gn:admin2_code":"437.0",
    "gn:asciiname":"Nabipur",
    "gn:country_code":"IN",
    "gn:dem":557,
    "gn:feature_class":"P",
    "gn:feature_code":"PPL",
    "gn:name":"Nab\u012bpur",
    "gn:population":0,
    "gn:timezone":"Asia/Kolkata",
    "iso:country":"IN",
    "wof:name":"Nabipur",
    "wof:placetype":"locality"
},
  "geometry": {"coordinates":[76.17686999999999,22.82622000000001],"type":"Point"}
}