{
  "type": "Feature",
  "properties": {
    "iso:country":"IN",
    "ks:ks_alt_nam":"Kandh\u0101l",
    "ks:ks_name":"Kandhal",
    "ks:ks_pop":352,
    "ks:ks_type":"VILLAGE",
    "name:eng_x_preferred":[
        "Kandhal"
    ],
    "name:eng_x_variant":[
        "Kandh\u0101l"
    ],
    "wof:name":"Kandhal",
    "wof:placetype":"locality",
    "wof:population":352
},
  "geometry": {"coordinates":[84.16992399999999,21.05196],"type":"Point"}
}