{
  "type": "Feature",
  "properties": {
    "iso:country":"IN",
    "ks:ks_name":"Bhagwatpur",
    "ks:ks_pop":102,
    "ks:ks_type":"VILLAGE",
    "name:eng_x_preferred":[
        "Bhagwatpur"
    ],
    "wof:name":"Bhagwatpur",
    "wof:placetype":"locality",
    "wof:population":102
},
  "geometry": {"coordinates":[82.566245,23.515468],"type":"Point"}
}