{
  "type": "Feature",
  "properties": {
    "iso:country":"IN",
    "ks:ks_name":"Veerapuram",
    "ks:ks_pop":874,
    "ks:ks_type":"HABITATION",
    "ks:ks_uagg_main":0,
    "name:eng_x_preferred":[
        "Veerapuram"
    ],
    "wof:name":"Veerapuram",
    "wof:placetype":"locality",
    "wof:population":874
},
  "geometry": {"coordinates":[79.99207,12.742634],"type":"Point"}
}