{
  "type": "Feature",
  "properties": {
    "iso:country":"IN",
    "ks:ks_name":"Chakbandi Urf Pranpur",
    "ks:ks_pop":1558,
    "ks:ks_type":"VILLAGE",
    "name:eng_x_preferred":[
        "Chakbandi Urf Pranpur"
    ],
    "wof:name":"Chakbandi Urf Pranpur",
    "wof:placetype":"locality",
    "wof:population":1558
},
  "geometry": {"coordinates":[83.853765,26.498193],"type":"Point"}
}