{
  "type": "Feature",
  "properties": {
    "iso:country":"IN",
    "ks:ks_alt_nam":"Pudukudiyiruppu ambalakara street",
    "ks:ks_name":"Pudukudiyiruppu Ambalakara Street",
    "ks:ks_pop":475,
    "ks:ks_type":"HABITATION",
    "name:eng_x_preferred":[
        "Pudukudiyiruppu Ambalakara Street"
    ],
    "wof:name":"Pudukudiyiruppu Ambalakara Street",
    "wof:placetype":"locality",
    "wof:population":475
},
  "geometry": {"coordinates":[79.264751,10.517537],"type":"Point"}
}