{
  "type": "Feature",
  "properties": {
    "iso:country":"IN",
    "ks:ks_name":"Dumarbhawana",
    "ks:ks_pop":695,
    "ks:ks_type":"VILLAGE",
    "name:eng_x_preferred":[
        "Dumarbhawana"
    ],
    "wof:name":"Dumarbhawana",
    "wof:placetype":"locality",
    "wof:population":695
},
  "geometry": {"coordinates":[83.448337,22.871616],"type":"Point"}
}