{
  "type": "Feature",
  "properties": {
    "iso:country":"IN",
    "ks:ks_alt_nam":"jadhav mala",
    "ks:ks_name":"Jadhav Mala",
    "ks:ks_pop":764,
    "ks:ks_type":"HABITATION",
    "name:eng_x_preferred":[
        "Jadhav Mala"
    ],
    "wof:name":"Jadhav Mala",
    "wof:placetype":"locality",
    "wof:population":764
},
  "geometry": {"coordinates":[74.226035,17.184435],"type":"Point"}
}