{
  "type": "Feature",
  "properties": {
    "iso:country":"IN",
    "ks:ks_name":"Gangaram Chak",
    "ks:ks_pop":225,
    "ks:ks_type":"VILLAGE",
    "ks:ks_uagg_main":0,
    "name:eng_x_preferred":[
        "Gangaram Chak"
    ],
    "wof:name":"Gangaram Chak",
    "wof:placetype":"neighbourhood",
    "wof:population":225
},
  "geometry": {"coordinates":[87.55959,22.379409],"type":"Point"}
}