{
  "type": "Feature",
  "properties": {
    "gn:admin1_code":"25.0",
    "gn:admin2_code":"630.0",
    "gn:asciiname":"Kollupatti",
    "gn:country_code":"IN",
    "gn:dem":472,
    "gn:feature_class":"P",
    "gn:feature_code":"PPL",
    "gn:name":"Kollupatti",
    "gn:population":0,
    "gn:timezone":"Asia/Kolkata",
    "iso:country":"IN",
    "wof:name":"Kollupatti",
    "wof:placetype":"locality"
},
  "geometry": {"coordinates":[78.21281,12.3186],"type":"Point"}
}