{
  "type": "Feature",
  "properties": {
    "iso:country":"IN",
    "ks:ks_alt_nam":"Peerya thanda",
    "ks:ks_name":"Peerya Thanda",
    "ks:ks_pop":270,
    "ks:ks_type":"HABITATION",
    "name:eng_x_preferred":[
        "Peerya Thanda"
    ],
    "wof:name":"Peerya Thanda",
    "wof:placetype":"locality",
    "wof:population":270
},
  "geometry": {"coordinates":[79.80358,17.405684],"type":"Point"}
}