{
  "type": "Feature",
  "properties": {
    "iso:country":"IN",
    "ks:ks_name":"Hadakharsi",
    "ks:ks_pop":502,
    "ks:ks_type":"VILLAGE",
    "name:eng_x_preferred":[
        "Hadakharsi"
    ],
    "wof:name":"Hadakharsi",
    "wof:placetype":"locality",
    "wof:population":502
},
  "geometry": {"coordinates":[83.128952,19.593476],"type":"Point"}
}