{
  "type": "Feature",
  "properties": {
    "iso:country":"IN",
    "ks:ks_name":"Fulpur",
    "ks:ks_pop":48,
    "ks:ks_type":"HABITATION",
    "name:eng_x_preferred":[
        "Fulpur"
    ],
    "wof:name":"Fulpur",
    "wof:placetype":"locality",
    "wof:population":48
},
  "geometry": {"coordinates":[82.330856,27.340281],"type":"Point"}
}