{
  "type": "Feature",
  "properties": {
    "iso:country":"IN",
    "ks:ks_name":"Halenahalli",
    "ks:ks_pop":366,
    "ks:ks_type":"HABITATION",
    "name:eng_x_preferred":[
        "Halenahalli"
    ],
    "wof:name":"Halenahalli",
    "wof:placetype":"locality",
    "wof:population":366
},
  "geometry": {"coordinates":[75.75386,13.34711],"type":"Point"}
}