{
  "type": "Feature",
  "properties": {
    "gn:admin1_code":"37",
    "gn:admin2_code":"405.0",
    "gn:asciiname":"Dhotma",
    "gn:country_code":"IN",
    "gn:dem":221,
    "gn:feature_class":"P",
    "gn:feature_code":"PPL",
    "gn:name":"Dhotma",
    "gn:population":0,
    "gn:timezone":"Asia/Kolkata",
    "iso:country":"IN",
    "wof:name":"Dhotma",
    "wof:placetype":"locality"
},
  "geometry": {"coordinates":[82.88831999999999,21.70568],"type":"Point"}
}