{
  "type": "Feature",
  "properties": {
    "gn:admin1_code":"36",
    "gn:admin2_code":"176.0",
    "gn:asciiname":"Dhurha",
    "gn:country_code":"IN",
    "gn:dem":114,
    "gn:feature_class":"P",
    "gn:feature_code":"PPL",
    "gn:name":"Dhurha",
    "gn:population":0,
    "gn:timezone":"Asia/Kolkata",
    "iso:country":"IN",
    "ks:ks_name":"Dherha",
    "ks:ks_pop":696,
    "ks:ks_type":"VILLAGE",
    "name:eng_x_preferred":[
        "Dherha"
    ],
    "name:eng_x_variant":[
        "Dhurha"
    ],
    "wof:name":"Dherha",
    "wof:placetype":"locality",
    "wof:population":696
},
  "geometry": {"coordinates":[81.33406600000001,26.676299],"type":"Point"}
}