{
  "type": "Feature",
  "properties": {
    "iso:country":"IN",
    "ks:ks_name":"Lavhali",
    "ks:ks_pop":140,
    "ks:ks_type":"VILLAGE",
    "name:eng_x_preferred":[
        "Lavhali"
    ],
    "wof:name":"Lavhali",
    "wof:placetype":"locality",
    "wof:population":140
},
  "geometry": {"coordinates":[73.43884,20.283933],"type":"Point"}
}