{
  "type": "Feature",
  "properties": {
    "gn:admin1_code":"10.0",
    "gn:admin2_code":"87.0",
    "gn:asciiname":"Jhonpari Jaimal",
    "gn:country_code":"IN",
    "gn:dem":199,
    "gn:feature_class":"P",
    "gn:feature_code":"PPL",
    "gn:name":"Jhonpari Jaimal",
    "gn:population":0,
    "gn:timezone":"Asia/Kolkata",
    "iso:country":"IN",
    "wof:name":"Jhonpari Jaimal",
    "wof:placetype":"locality"
},
  "geometry": {"coordinates":[76.99540999999998,27.86569],"type":"Point"}
}