{
  "type": "Feature",
  "properties": {
    "iso:country":"IN",
    "ks:ks_name":"Dulllapur",
    "ks:ks_pop":396,
    "ks:ks_type":"HABITATION",
    "name:eng_x_preferred":[
        "Dulllapur"
    ],
    "wof:name":"Dulllapur",
    "wof:placetype":"locality",
    "wof:population":396
},
  "geometry": {"coordinates":[80.248766,27.58647],"type":"Point"}
}