{
  "type": "Feature",
  "properties": {
    "iso:country":"IN",
    "ks:ks_name":"Melaputhur",
    "ks:ks_pop":300,
    "ks:ks_type":"HABITATION",
    "name:eng_x_preferred":[
        "Melaputhur"
    ],
    "wof:name":"Melaputhur",
    "wof:placetype":"locality",
    "wof:population":300
},
  "geometry": {"coordinates":[79.521824,10.583106],"type":"Point"}
}