{
  "type": "Feature",
  "properties": {
    "gn:country":"IN",
    "gn:fcode":"PPL",
    "gn:pop":76341,
    "iso:country":"IN",
    "name:unk_x_variant":[
        "Kodarma"
    ],
    "qs:name":"Jhumri Tilaiya",
    "qs:name_adm0":"India",
    "qs:name_adm1":"Jharkhand",
    "qs:photos_9k":1,
    "qs:photos_9r":1,
    "qs:photos_all":3,
    "qs:photos_sr":0,
    "qs:placetype":"Town",
    "qs:pop_sr":"8",
    "wd:wordcount":1627,
    "wof:name":"Jhumri Tilaiya",
    "wof:placetype":"locality",
    "wof:population":76341
},
  "geometry": {"coordinates":[85.52951,24.4349],"type":"Point"}
}