{
  "type": "Feature",
  "properties": {
    "gn:country":"IN",
    "gn:fcode":"PPL",
    "gn:population":76341,
    "iso:country":"IN",
    "name:bho_x_preferred":[
        "\u091d\u0941\u092e\u0930\u0940 \u0924\u093f\u0932\u0948\u092f\u093e"
    ],
    "name:bpy_x_preferred":[
        "\u099d\u09c1\u09ae\u09b0\u09bf \u09a4\u09bf\u09b2\u09be\u0987\u09af\u09bc\u09be"
    ],
    "name:ceb_x_preferred":[
        "Jumri Tilaiy\u0101"
    ],
    "name:eng_x_preferred":[
        "Shikhar Jain"
    ],
    "name:hin_x_preferred":[
        "Shikhar"
    ],
    "name:ita_x_preferred":[
        "Jhumri Tilaiya"
    ],
    "name:msa_x_preferred":[
        "Jhumri Tilaiya"
    ],
    "name:nep_x_preferred":[
        "\u091d\u0941\u092e\u0930\u0940 \u0924\u093f\u0932\u0948\u092f\u093e"
    ],
    "name:new_x_preferred":[
        "\u091d\u0941\u092e\u094d\u0930\u0940 \u0924\u093f\u0932\u0948\u092f\u093e"
    ],
    "name:nld_x_preferred":[
        "Shikhar Jain"
    ],
    "name:ori_x_preferred":[
        "\u0b1d\u0b41\u0b2e\u0b30\u0b3f\u0b24\u0b3f\u0b32\u0b3f\u0b06"
    ],
    "name:pan_x_preferred":[
        "\u0a1d\u0a41\u0a2e\u0a30\u0a40 \u0a24\u0a32\u0a71\u0a08\u0a06"
    ],
    "name:pnb_x_preferred":[
        "\u062c\u06be\u0645\u0631\u06cc \u062a\u0644\u0626\u06cc\u0627"
    ],
    "name:spa_x_preferred":[
        "Jhumri Tilaiya"
    ],
    "name:swe_x_preferred":[
        "Jhumri Tilaiya"
    ],
    "name:und_x_variant":[
        "Kodarma"
    ],
    "name:urd_x_preferred":[
        "\u062c\u06be\u0645\u0631\u06cc \u062a\u0644\u0626\u06cc\u0627"
    ],
    "name:vie_x_preferred":[
        "Jhumri Tilaiya"
    ],
    "name:zho_x_preferred":[
        "\u4e45\u59c6\u91cc\u8482\u83b1\u8036"
    ],
    "qs:name":"Jhumri Tilaiya",
    "qs:name_adm0":"India",
    "qs:name_adm1":"Jharkhand",
    "qs:photos_9k":1,
    "qs:photos_9r":1,
    "qs:photos_all":3,
    "qs:photos_sr":0,
    "qs:placetype":"Town",
    "qs:pop_sr":"8",
    "wd:wordcount":1627,
    "wof:name":"Jhumri Tilaiya",
    "wof:placetype":"locality",
    "wof:population":76341
},
  "geometry": {"coordinates":[85.52951,24.4349],"type":"Point"}
}