{
  "type": "Feature",
  "properties": {
    "iso:country":"IN",
    "ks:ks_name":"Vinayagapuram",
    "ks:ks_pop":186,
    "ks:ks_type":"HABITATION",
    "ks:ks_uagg_main":0,
    "name:eng_x_preferred":[
        "Vinayagapuram"
    ],
    "wof:name":"Vinayagapuram",
    "wof:placetype":"neighbourhood",
    "wof:population":186
},
  "geometry": {"coordinates":[78.100504,8.717997],"type":"Point"}
}