{
  "type": "Feature",
  "properties": {
    "iso:country":"IN",
    "ks:ks_name":"Sukarangi",
    "ks:ks_pop":471,
    "ks:ks_type":"HABITATION",
    "name:eng_x_preferred":[
        "Sukarangi"
    ],
    "wof:name":"Sukarangi",
    "wof:placetype":"locality",
    "wof:population":471
},
  "geometry": {"coordinates":[85.810958,21.052637],"type":"Point"}
}