{
  "type": "Feature",
  "properties": {
    "iso:country":"IN",
    "ks:ks_name":"Likhani Kejhee",
    "ks:ks_pop":327,
    "ks:ks_type":"HABITATION",
    "ks:ks_uagg_main":0,
    "name:eng_x_preferred":[
        "Likhani Kejhee"
    ],
    "wof:name":"Likhani Kejhee",
    "wof:placetype":"neighbourhood",
    "wof:population":327
},
  "geometry": {"coordinates":[86.844735,24.902488],"type":"Point"}
}