{
  "type": "Feature",
  "properties": {
    "gn:admin1_code":"36",
    "gn:admin2_code":"199.0",
    "gn:asciiname":"Baghera",
    "gn:country_code":"IN",
    "gn:dem":81,
    "gn:feature_class":"P",
    "gn:feature_code":"PPL",
    "gn:name":"Baghera",
    "gn:population":0,
    "gn:timezone":"Asia/Kolkata",
    "iso:country":"IN",
    "ks:ks_name":"Baghera",
    "ks:ks_pop":1577,
    "ks:ks_type":"VILLAGE",
    "ks:ks_uagg_main":0,
    "name:eng_x_preferred":[
        "Baghera"
    ],
    "wof:name":"Baghera",
    "wof:placetype":"neighbourhood",
    "wof:population":1577
},
  "geometry": {"coordinates":[82.98397199999999,25.183624],"type":"Point"}
}