{
  "type": "Feature",
  "properties": {
    "gn:admin1_code":"40.0",
    "gn:admin2_code":"533.0",
    "gn:asciiname":"Ankapuram",
    "gn:country_code":"IN",
    "gn:dem":388,
    "gn:feature_class":"P",
    "gn:feature_code":"PPL",
    "gn:name":"Ank\u0101puram",
    "gn:population":0,
    "gn:timezone":"Asia/Kolkata",
    "iso:country":"IN",
    "wof:name":"Ankapuram",
    "wof:placetype":"locality"
},
  "geometry": {"coordinates":[78.25532,18.7656],"type":"Point"}
}