{
  "type": "Feature",
  "properties": {
    "gn:admin1_code":"34.0",
    "gn:admin2_code":"223.0",
    "gn:asciiname":"Nagor",
    "gn:country_code":"IN",
    "gn:dem":43,
    "gn:feature_class":"P",
    "gn:feature_code":"PPL",
    "gn:name":"Nagor",
    "gn:population":0,
    "gn:timezone":"Asia/Kolkata",
    "iso:country":"IN",
    "wof:name":"Nagor",
    "wof:placetype":"locality"
},
  "geometry": {"coordinates":[86.42743,25.59966],"type":"Point"}
}