{
  "type": "Feature",
  "properties": {
    "gn:admin1_code":"25.0",
    "gn:admin2_code":"602.0",
    "gn:asciiname":"Viraraghavapuram",
    "gn:country_code":"IN",
    "gn:dem":39,
    "gn:feature_class":"P",
    "gn:feature_code":"PPL",
    "gn:name":"V\u012brar\u0101ghavapuram",
    "gn:population":0,
    "gn:timezone":"Asia/Kolkata",
    "iso:country":"IN",
    "wof:name":"Viraraghavapuram",
    "wof:placetype":"neighbourhood"
},
  "geometry": {"coordinates":[79.96268000000001,13.16814],"type":"Point"}
}