{
  "type": "Feature",
  "properties": {
    "gn:admin1_code":"19.0",
    "gn:admin2_code":"563.0",
    "gn:asciiname":"Hebre",
    "gn:country_code":"IN",
    "gn:dem":495,
    "gn:feature_class":"P",
    "gn:feature_code":"PPL",
    "gn:name":"Hebre",
    "gn:population":0,
    "gn:timezone":"Asia/Kolkata",
    "iso:country":"IN",
    "ks:ks_name":"Hebre",
    "ks:ks_pop":957,
    "ks:ks_type":"VILLAGE",
    "name:eng_x_preferred":[
        "Hebre"
    ],
    "wof:name":"Hebre",
    "wof:placetype":"locality",
    "wof:population":957
},
  "geometry": {"coordinates":[74.63293400000001,14.555328],"type":"Point"}
}