{
  "type": "Feature",
  "properties": {
    "gn:admin1_code":"36.0",
    "gn:admin2_code":"160.0",
    "gn:asciiname":"Hamirpur",
    "gn:country_code":"IN",
    "gn:dem":145,
    "gn:feature_class":"P",
    "gn:feature_code":"PPL",
    "gn:name":"Ham\u012brpur",
    "gn:population":0,
    "gn:timezone":"Asia/Kolkata",
    "iso:country":"IN",
    "wof:name":"Hamirpur",
    "wof:placetype":"locality"
},
  "geometry": {"coordinates":[79.51394000000001,26.9956],"type":"Point"}
}