{
  "type": "Feature",
  "properties": {
    "iso:country":"IN",
    "ks:ks_name":"Ex Serviceman Area",
    "ks:ks_pop":189,
    "ks:ks_type":"HABITATION",
    "name:eng_x_preferred":[
        "Ex Serviceman Area"
    ],
    "wof:name":"Ex Serviceman Area",
    "wof:placetype":"locality",
    "wof:population":189
},
  "geometry": {"coordinates":[93.811018,26.046505],"type":"Point"}
}