{
  "type": "Feature",
  "properties": {
    "iso:country":"IN",
    "ks:ks_name":"Hanwant Nagar",
    "ks:ks_pop":635,
    "ks:ks_type":"VILLAGE",
    "name:eng_x_preferred":[
        "Hanwant Nagar"
    ],
    "wof:name":"Hanwant Nagar",
    "wof:placetype":"locality",
    "wof:population":635
},
  "geometry": {"coordinates":[71.915753,24.888275],"type":"Point"}
}