{
  "type": "Feature",
  "properties": {
    "iso:country":"IN",
    "ks:ks_name":"Heggattu",
    "ks:ks_pop":56,
    "ks:ks_type":"HABITATION",
    "name:eng_x_preferred":[
        "Heggattu"
    ],
    "wof:name":"Heggattu",
    "wof:placetype":"locality",
    "wof:population":56
},
  "geometry": {"coordinates":[75.04864499999999,14.048638],"type":"Point"}
}