{
  "type": "Feature",
  "properties": {
    "iso:country":"IN",
    "ks:ks_alt_nam":"Baroda D\u0101ng Reserved Forest",
    "ks:ks_name":"Baroda Dang Reserved Forest",
    "ks:ks_type":"VILLAGE",
    "name:eng_x_preferred":[
        "Baroda Dang Reserved Forest"
    ],
    "name:eng_x_variant":[
        "Baroda D\u0101ng Reserved Forest"
    ],
    "wof:name":"Baroda Dang Reserved Forest",
    "wof:placetype":"locality"
},
  "geometry": {"coordinates":[78.541185,24.917661],"type":"Point"}
}