{
  "type": "Feature",
  "properties": {
    "iso:country":"IN",
    "ks:ks_name":"Bhongdya",
    "ks:ks_pop":350,
    "ks:ks_type":"VILLAGE",
    "name:eng_x_preferred":[
        "Bhongdya"
    ],
    "wof:name":"Bhongdya",
    "wof:placetype":"locality",
    "wof:population":350
},
  "geometry": {"coordinates":[73.541265,20.911272],"type":"Point"}
}