{
  "type": "Feature",
  "properties": {
    "gn:admin1_code":"12.0",
    "gn:admin2_code":"004",
    "gn:asciiname":"Gampa",
    "gn:country_code":"IN",
    "gn:dem":2659,
    "gn:feature_class":"P",
    "gn:feature_code":"PPL",
    "gn:name":"Gampa",
    "gn:population":0,
    "gn:timezone":"Asia/Kolkata",
    "iso:country":"IN",
    "wof:name":"Gampa",
    "wof:placetype":"locality"
},
  "geometry": {"coordinates":[76.38472,34.63472],"type":"Point"}
}