{
  "type": "Feature",
  "properties": {
    "gn:admin1_code":"10.0",
    "gn:admin2_code":"072",
    "gn:asciiname":"Nurpur Buchi",
    "gn:country_code":"IN",
    "gn:dem":254,
    "gn:feature_class":"P",
    "gn:feature_code":"PPL",
    "gn:name":"N\u016brpur B\u016bchi",
    "gn:population":0,
    "gn:timezone":"Asia/Kolkata",
    "iso:country":"IN",
    "ks:ks_alt_nam":"N\u016brpur B\u016bchi",
    "ks:ks_name":"Nurpur Buchi",
    "ks:ks_type":"VILLAGE",
    "name:eng_x_preferred":[
        "Nurpur Buchi"
    ],
    "name:eng_x_variant":[
        "N\u016brpur B\u016bchi"
    ],
    "wof:name":"Nurpur Buchi",
    "wof:placetype":"locality"
},
  "geometry": {"coordinates":[76.69644,30.11511],"type":"Point"}
}