{
  "type": "Feature",
  "properties": {
    "iso:country":"IN",
    "ks:ks_alt_nam":"SOUTH TOLA",
    "ks:ks_name":"South Tola",
    "ks:ks_pop":79,
    "ks:ks_type":"HABITATION",
    "name:eng_x_preferred":[
        "South Tola"
    ],
    "wof:name":"South Tola",
    "wof:placetype":"locality",
    "wof:population":79
},
  "geometry": {"coordinates":[85.97901899999999,25.106256],"type":"Point"}
}