{
  "type": "Feature",
  "properties": {
    "gn:admin1_code":"40",
    "gn:admin2_code":"535.0",
    "gn:asciiname":"Potreddipalli",
    "gn:country_code":"IN",
    "gn:dem":534,
    "gn:feature_class":"P",
    "gn:feature_code":"PPL",
    "gn:name":"Potreddipalli",
    "gn:population":0,
    "gn:timezone":"Asia/Kolkata",
    "iso:country":"IN",
    "ks:ks_name":"Pothreddipalle",
    "ks:ks_pop":5740,
    "ks:ks_type":"VILLAGE",
    "ks:ks_uagg_main":0,
    "name:eng_x_preferred":[
        "Pothreddipalle"
    ],
    "wof:name":"Pothreddipalle",
    "wof:placetype":"neighbourhood",
    "wof:population":5740
},
  "geometry": {"coordinates":[78.084667,17.591016],"type":"Point"}
}