{
  "type": "Feature",
  "properties": {
    "iso:country":"IN",
    "ks:ks_alt_nam":"Perumal kovil",
    "ks:ks_name":"Perumal Kovil",
    "ks:ks_pop":62,
    "ks:ks_type":"HABITATION",
    "name:eng_x_preferred":[
        "Perumal Kovil"
    ],
    "wof:name":"Perumal Kovil",
    "wof:placetype":"locality",
    "wof:population":62
},
  "geometry": {"coordinates":[78.73945000000001,12.986148],"type":"Point"}
}