{
  "type": "Feature",
  "properties": {
    "iso:country":"IN",
    "ks:ks_name":"Lonian Purwa",
    "ks:ks_pop":206,
    "ks:ks_type":"HABITATION",
    "name:eng_x_preferred":[
        "Lonian Purwa"
    ],
    "wof:name":"Lonian Purwa",
    "wof:placetype":"locality",
    "wof:population":206
},
  "geometry": {"coordinates":[81.21641700000001,27.761433],"type":"Point"}
}