{
  "type": "Feature",
  "properties": {
    "iso:country":"IN",
    "ks:ks_name":"Vakasiya",
    "ks:ks_pop":1531,
    "ks:ks_type":"VILLAGE",
    "name:eng_x_preferred":[
        "Vakasiya"
    ],
    "wof:name":"Vakasiya",
    "wof:placetype":"locality",
    "wof:population":1531
},
  "geometry": {"coordinates":[74.078889,22.624361],"type":"Point"}
}