{
  "type": "Feature",
  "properties": {
    "iso:country":"IN",
    "ks:ks_name":"Vijay Nagar",
    "ks:ks_pop":824,
    "ks:ks_type":"HABITATION",
    "name:eng_x_preferred":[
        "Vijay Nagar"
    ],
    "wof:name":"Vijay Nagar",
    "wof:placetype":"locality",
    "wof:population":824
},
  "geometry": {"coordinates":[72.53787800000001,27.244464],"type":"Point"}
}