{
  "type": "Feature",
  "properties": {
    "iso:country":"IN",
    "ks:ks_name":"Nayatota",
    "ks:ks_pop":0,
    "ks:ks_type":"VILLAGE",
    "name:eng_x_preferred":[
        "Nayatota"
    ],
    "wof:name":"Nayatota",
    "wof:placetype":"locality",
    "wof:population":0
},
  "geometry": {"coordinates":[86.113062,20.80603],"type":"Point"}
}