{
  "type": "Feature",
  "properties": {
    "iso:country":"IN",
    "ks:ks_name":"Surajba",
    "ks:ks_pop":513,
    "ks:ks_type":"HABITATION",
    "name:eng_x_preferred":[
        "Surajba"
    ],
    "wof:name":"Surajba",
    "wof:placetype":"locality",
    "wof:population":513
},
  "geometry": {"coordinates":[72.76822199999999,22.324806],"type":"Point"}
}