{
  "type": "Feature",
  "properties": {
    "iso:country":"IN",
    "ks:ks_name":"Bherbheri Manabari",
    "ks:ks_pop":1285,
    "ks:ks_type":"VILLAGE",
    "ks:ks_uagg_main":0,
    "name:eng_x_preferred":[
        "Bherbheri Manabari"
    ],
    "wof:name":"Bherbheri Manabari",
    "wof:placetype":"neighbourhood",
    "wof:population":1285
},
  "geometry": {"coordinates":[89.220547,26.326672],"type":"Point"}
}