{
  "type": "Feature",
  "properties": {
    "iso:country":"IN",
    "ks:ks_name":"Deohati Dakhinpara",
    "ks:ks_pop":1428,
    "ks:ks_type":"VILLAGE",
    "ks:ks_uagg_main":0,
    "name:eng_x_preferred":[
        "Deohati Dakhinpara"
    ],
    "wof:name":"Deohati Dakhinpara",
    "wof:placetype":"neighbourhood",
    "wof:population":1428
},
  "geometry": {"coordinates":[90.64375099999999,26.346044],"type":"Point"}
}