{
  "type": "Feature",
  "properties": {
    "iso:country":"IN",
    "ks:ks_name":"Parmanandpur",
    "ks:ks_pop":1232,
    "ks:ks_type":"VILLAGE",
    "name:eng_x_preferred":[
        "Parmanandpur"
    ],
    "wof:name":"Parmanandpur",
    "wof:placetype":"locality",
    "wof:population":1232
},
  "geometry": {"coordinates":[85.350674,26.088453],"type":"Point"}
}