{
  "type": "Feature",
  "properties": {
    "gn:admin1_code":"10.0",
    "gn:admin2_code":"88.0",
    "gn:asciiname":"Sehatpur",
    "gn:country_code":"IN",
    "gn:dem":197,
    "gn:feature_class":"P",
    "gn:feature_code":"PPL",
    "gn:name":"Sehatpur",
    "gn:population":0,
    "gn:timezone":"Asia/Kolkata",
    "iso:country":"IN",
    "wof:name":"Sehatpur",
    "wof:placetype":"neighbourhood"
},
  "geometry": {"coordinates":[77.32804,28.47787000000001],"type":"Point"}
}