{
  "type": "Feature",
  "properties": {
    "iso:country":"IN",
    "ks:ks_name":"Makhdumpur",
    "ks:ks_pop":58,
    "ks:ks_type":"VILLAGE",
    "name:eng_x_preferred":[
        "Makhdumpur"
    ],
    "wof:name":"Makhdumpur",
    "wof:placetype":"locality",
    "wof:population":58
},
  "geometry": {"coordinates":[85.08404899999999,25.956037],"type":"Point"}
}