{
  "type": "Feature",
  "properties": {
    "gn:admin1_code":"34.0",
    "gn:admin2_code":"222.0",
    "gn:asciiname":"Takia",
    "gn:country_code":"IN",
    "gn:dem":48,
    "gn:feature_class":"P",
    "gn:feature_code":"PPL",
    "gn:name":"Takia",
    "gn:population":0,
    "gn:timezone":"Asia/Kolkata",
    "iso:country":"IN",
    "name:ceb_x_preferred":[
        "Takia"
    ],
    "name:deu_x_preferred":[
        "Takia"
    ],
    "name:swe_x_preferred":[
        "Takia"
    ],
    "wof:name":"Takia",
    "wof:placetype":"neighbourhood"
},
  "geometry": {"coordinates":[85.94029,25.53105],"type":"Point"}
}