{
  "type": "Feature",
  "properties": {
    "gn:admin1_code":"24",
    "gn:admin2_code":"105.0",
    "gn:asciiname":"Musipur",
    "gn:country_code":"IN",
    "gn:dem":189,
    "gn:feature_class":"P",
    "gn:feature_code":"PPL",
    "gn:name":"M\u016bs\u012bpur",
    "gn:population":0,
    "gn:timezone":"Asia/Kolkata",
    "iso:country":"IN",
    "name:und_x_variant":[
        "M\u016bs\u012bpur",
        "M\u016bsepur"
    ],
    "wof:name":"Musipur",
    "wof:placetype":"neighbourhood"
},
  "geometry": {"coordinates":[77.23227,27.69742],"type":"Point"}
}