{
  "type": "Feature",
  "properties": {
    "iso:country":"IN",
    "ks:ks_name":"Edapalayam",
    "ks:ks_pop":176,
    "ks:ks_type":"HABITATION",
    "name:eng_x_preferred":[
        "Edapalayam"
    ],
    "wof:name":"Edapalayam",
    "wof:placetype":"locality",
    "wof:population":176
},
  "geometry": {"coordinates":[79.45174299999999,12.537742],"type":"Point"}
}