{
  "type": "Feature",
  "properties": {
    "iso:country":"IN",
    "ks:ks_alt_nam":"Tatihara khurd",
    "ks:ks_name":"Tatihara Khurd",
    "ks:ks_pop":220,
    "ks:ks_type":"HABITATION",
    "name:eng_x_preferred":[
        "Tatihara Khurd"
    ],
    "wof:name":"Tatihara Khurd",
    "wof:placetype":"locality",
    "wof:population":220
},
  "geometry": {"coordinates":[81.77846,24.781539],"type":"Point"}
}