{
  "type": "Feature",
  "properties": {
    "gn:admin1_code":"34.0",
    "gn:admin2_code":"229.0",
    "gn:asciiname":"Kotri",
    "gn:country_code":"IN",
    "gn:dem":68,
    "gn:feature_class":"P",
    "gn:feature_code":"PPL",
    "gn:name":"Kotri",
    "gn:population":0,
    "gn:timezone":"Asia/Kolkata",
    "iso:country":"IN",
    "name:cat_x_preferred":[
        "Kotri"
    ],
    "name:fas_x_preferred":[
        "\u06a9\u0648\u062a\u0631\u06cc"
    ],
    "name:fra_x_preferred":[
        "Kotri"
    ],
    "name:pnb_x_preferred":[
        "\u06a9\u0648\u0679\u0631\u06cc"
    ],
    "name:rus_x_preferred":[
        "\u041a\u043e\u0442\u0440\u0438"
    ],
    "name:snd_x_preferred":[
        "\u06aa\u0648\u067d\u0699\u064a"
    ],
    "name:spa_x_preferred":[
        "Kotri"
    ],
    "name:swe_x_preferred":[
        "Kotri"
    ],
    "name:urd_x_preferred":[
        "\u06a9\u0648\u0679\u0631\u06cc"
    ],
    "wof:name":"Kotri",
    "wof:placetype":"locality"
},
  "geometry": {"coordinates":[85.17841999999997,25.19942],"type":"Point"}
}