{
  "type": "Feature",
  "properties": {
    "iso:country":"IN",
    "ks:ks_name":"Saikharipur",
    "ks:ks_pop":120,
    "ks:ks_type":"HABITATION",
    "name:eng_x_preferred":[
        "Saikharipur"
    ],
    "wof:name":"Saikharipur",
    "wof:placetype":"locality",
    "wof:population":120
},
  "geometry": {"coordinates":[81.195927,25.181618],"type":"Point"}
}