{
  "type": "Feature",
  "properties": {
    "iso:country":"IN",
    "ks:ks_name":"Pandharwani",
    "ks:ks_pop":280,
    "ks:ks_type":"VILLAGE",
    "name:eng_x_preferred":[
        "Pandharwani"
    ],
    "wof:name":"Pandharwani",
    "wof:placetype":"locality",
    "wof:population":280
},
  "geometry": {"coordinates":[79.09003300000001,19.638958],"type":"Point"}
}