{
  "type": "Feature",
  "properties": {
    "gn:admin1_code":"24",
    "gn:admin2_code":"120.0",
    "gn:asciiname":"Rampura",
    "gn:country_code":"IN",
    "gn:dem":318,
    "gn:feature_class":"P",
    "gn:feature_code":"PPL",
    "gn:name":"R\u0101mpura",
    "gn:population":0,
    "gn:timezone":"Asia/Kolkata",
    "iso:country":"IN",
    "name:ara_x_preferred":[
        "\u0631\u0627\u0645\u0628\u0648\u0631\u0627"
    ],
    "name:ben_bn_x_preferred":[
        "\u09b0\u09be\u09ae\u09aa\u09c1\u09b0\u09be"
    ],
    "name:ben_in_x_preferred":[
        "\u09b0\u09be\u09ae\u09aa\u09c1\u09b0\u09be"
    ],
    "name:cat_x_preferred":[
        "Rampura"
    ],
    "name:guj_x_preferred":[
        "\u0ab0\u0abe\u0aae\u0aaa\u0ac1\u0ab0\u0abe"
    ],
    "name:hin_x_preferred":[
        "\u0930\u093e\u092e\u092a\u0941\u0930\u093e"
    ],
    "name:kan_x_preferred":[
        "\u0cb0\u0cbe\u0cae\u0ccd"
    ],
    "name:mal_x_preferred":[
        "\u0d30\u0d3e\u0d02\u0d2a\u0d41\u0d30"
    ],
    "name:mar_x_preferred":[
        "\u0930\u093e\u092e\u092a\u0941\u0930\u093e"
    ],
    "name:pan_x_preferred":[
        "\u0a30\u0a3e\u0a2e\u0a2a\u0a41\u0a30\u0a3e"
    ],
    "name:pol_x_preferred":[
        "Rampura"
    ],
    "name:tam_x_preferred":[
        "\u0bb0\u0bbe\u0bae\u0bcd\u0baa\u0bc1\u0bb0\u0bbe"
    ],
    "name:tel_x_preferred":[
        "\u0c30\u0c3e\u0c02\u0c2a\u0c41\u0c30\u0c3e"
    ],
    "name:urd_x_preferred":[
        "\u0631\u0627\u0645\u067e\u0648\u0631\u06c1"
    ],
    "wof:name":"Rampura",
    "wof:placetype":"locality"
},
  "geometry": {"coordinates":[75.49556,25.94218],"type":"Point"}
}