{
  "type": "Feature",
  "properties": {
    "iso:country":"IN",
    "ks:ks_alt_nam":"pure kali pandey",
    "ks:ks_name":"Pure Kali Pandey",
    "ks:ks_pop":40,
    "ks:ks_type":"HABITATION",
    "name:eng_x_preferred":[
        "Pure Kali Pandey"
    ],
    "wof:name":"Pure Kali Pandey",
    "wof:placetype":"locality",
    "wof:population":40
},
  "geometry": {"coordinates":[81.609167,26.276417],"type":"Point"}
}