{
  "type": "Feature",
  "properties": {
    "iso:country":"IN",
    "ks:ks_name":"Dhavadewadi",
    "ks:ks_pop":77,
    "ks:ks_type":"HABITATION",
    "name:eng_x_preferred":[
        "Dhavadewadi"
    ],
    "wof:name":"Dhavadewadi",
    "wof:placetype":"locality",
    "wof:population":77
},
  "geometry": {"coordinates":[73.27632800000001,17.180186],"type":"Point"}
}