{
  "type": "Feature",
  "properties": {
    "gn:admin1_code":"36.0",
    "gn:admin2_code":"152.0",
    "gn:asciiname":"Lachhmipur",
    "gn:country_code":"IN",
    "gn:dem":165,
    "gn:feature_class":"P",
    "gn:feature_code":"PPL",
    "gn:name":"Lachhm\u012bpur",
    "gn:population":0,
    "gn:timezone":"Asia/Kolkata",
    "iso:country":"IN",
    "ks:ks_alt_nam":"Lachhm\u012bpur",
    "ks:ks_name":"Lachhmipur",
    "ks:ks_type":"VILLAGE",
    "ks:ks_uagg_main":0,
    "name:eng_x_preferred":[
        "Lachhmipur"
    ],
    "name:eng_x_variant":[
        "Lachhm\u012bpur"
    ],
    "wof:name":"Lachhmipur",
    "wof:placetype":"neighbourhood"
},
  "geometry": {"coordinates":[79.719171,28.15089],"type":"Point"}
}