{
  "type": "Feature",
  "properties": {
    "iso:country":"IN",
    "ks:ks_name":"Abanagar",
    "ks:ks_pop":601,
    "ks:ks_type":"HABITATION",
    "name:eng_x_preferred":[
        "Abanagar"
    ],
    "wof:name":"Abanagar",
    "wof:placetype":"locality",
    "wof:population":601
},
  "geometry": {"coordinates":[75.11621100000001,17.236469],"type":"Point"}
}