{
  "type": "Feature",
  "properties": {
    "gn:admin1_code":"16",
    "gn:admin2_code":"501.0",
    "gn:asciiname":"Dhanora",
    "gn:country_code":"IN",
    "gn:dem":325,
    "gn:feature_class":"P",
    "gn:feature_code":"PPL",
    "gn:name":"Dh\u0101nora",
    "gn:population":0,
    "gn:timezone":"Asia/Kolkata",
    "iso:country":"IN",
    "name:und_x_variant":[
        "Dh\u0101nora",
        "Vaidh"
    ],
    "wof:name":"Dhanora",
    "wof:placetype":"locality"
},
  "geometry": {"coordinates":[77.33511,20.66899],"type":"Point"}
}