{
  "type": "Feature",
  "properties": {
    "gn:admin1_code":"23.0",
    "gn:admin2_code":"35.0",
    "gn:asciiname":"Chaguwala",
    "gn:country_code":"IN",
    "gn:dem":249,
    "gn:feature_class":"P",
    "gn:feature_code":"PPL",
    "gn:name":"Chaguw\u0101la",
    "gn:population":0,
    "gn:timezone":"Asia/Kolkata",
    "iso:country":"IN",
    "wof:name":"Chaguwala",
    "wof:placetype":"locality"
},
  "geometry": {"coordinates":[75.28896999999998,32.05994],"type":"Point"}
}