{
  "type": "Feature",
  "properties": {
    "iso:country":"IN",
    "ks:ks_name":"Hatimada",
    "ks:ks_pop":46,
    "ks:ks_type":"VILLAGE",
    "name:eng_x_preferred":[
        "Hatimada"
    ],
    "wof:name":"Hatimada",
    "wof:placetype":"locality",
    "wof:population":46
},
  "geometry": {"coordinates":[86.711445,21.879247],"type":"Point"}
}