{
  "type": "Feature",
  "properties": {
    "iso:country":"IN",
    "ks:ks_alt_nam":"Harijan tola",
    "ks:ks_name":"Harijan Tola",
    "ks:ks_pop":470,
    "ks:ks_type":"HABITATION",
    "ks:ks_uagg_main":0,
    "name:eng_x_preferred":[
        "Harijan Tola"
    ],
    "wof:name":"Harijan Tola",
    "wof:placetype":"neighbourhood",
    "wof:population":470
},
  "geometry": {"coordinates":[85.35699099999999,26.612229],"type":"Point"}
}