{
  "type": "Feature",
  "properties": {
    "iso:country":"IN",
    "ks:ks_name":"Kanarpur",
    "ks:ks_pop":225,
    "ks:ks_type":"HABITATION",
    "name:eng_x_preferred":[
        "Kanarpur"
    ],
    "wof:name":"Kanarpur",
    "wof:placetype":"locality",
    "wof:population":225
},
  "geometry": {"coordinates":[85.523747,20.628518],"type":"Point"}
}