{
  "type": "Feature",
  "properties": {
    "iso:country":"IN",
    "ks:ks_name":"Bahalwan Nagar",
    "ks:ks_pop":824,
    "ks:ks_type":"HABITATION",
    "name:eng_x_preferred":[
        "Bahalwan Nagar"
    ],
    "wof:name":"Bahalwan Nagar",
    "wof:placetype":"locality",
    "wof:population":824
},
  "geometry": {"coordinates":[75.701098,27.96926],"type":"Point"}
}