{
  "type": "Feature",
  "properties": {
    "iso:country":"IN",
    "ks:ks_name":"Mahua Kheda",
    "ks:ks_pop":46,
    "ks:ks_type":"HABITATION",
    "name:eng_x_preferred":[
        "Mahua Kheda"
    ],
    "wof:name":"Mahua Kheda",
    "wof:placetype":"locality",
    "wof:population":46
},
  "geometry": {"coordinates":[77.75135299999999,25.931081],"type":"Point"}
}