{
  "type": "Feature",
  "properties": {
    "gn:admin1_code":"28.0",
    "gn:admin2_code":"334.0",
    "gn:asciiname":"Kisorpur",
    "gn:country_code":"IN",
    "gn:dem":34,
    "gn:feature_class":"P",
    "gn:feature_code":"PPL",
    "gn:name":"Kisorpur",
    "gn:population":0,
    "gn:timezone":"Asia/Kolkata",
    "iso:country":"IN",
    "wof:name":"Kisorpur",
    "wof:placetype":"locality"
},
  "geometry": {"coordinates":[87.95705,24.29813],"type":"Point"}
}