{
  "type": "Feature",
  "properties": {
    "iso:country":"IN",
    "ks:ks_name":"Ranwatoli",
    "ks:ks_pop":394,
    "ks:ks_type":"HABITATION",
    "name:eng_x_preferred":[
        "Ranwatoli"
    ],
    "wof:name":"Ranwatoli",
    "wof:placetype":"locality",
    "wof:population":394
},
  "geometry": {"coordinates":[84.725672,23.180572],"type":"Point"}
}