{
  "type": "Feature",
  "properties": {
    "gn:admin1_code":"12",
    "gn:admin2_code":"9.0",
    "gn:asciiname":"Kuthpathri",
    "gn:country_code":"IN",
    "gn:dem":3387,
    "gn:feature_class":"P",
    "gn:feature_code":"PPL",
    "gn:name":"Kuthpathri",
    "gn:population":0,
    "gn:timezone":"Asia/Kolkata",
    "iso:country":"IN",
    "wof:name":"Kuthpathri",
    "wof:placetype":"locality"
},
  "geometry": {"coordinates":[74.77481999999998,34.52867],"type":"Point"}
}