{
  "type": "Feature",
  "properties": {
    "iso:country":"IN",
    "ks:ks_name":"Ainladhipa",
    "ks:ks_pop":96,
    "ks:ks_type":"VILLAGE",
    "name:eng_x_preferred":[
        "Ainladhipa"
    ],
    "wof:name":"Ainladhipa",
    "wof:placetype":"locality",
    "wof:population":96
},
  "geometry": {"coordinates":[84.49955300000001,21.858637],"type":"Point"}
}