{
  "type": "Feature",
  "properties": {
    "iso:country":"IN",
    "ks:ks_name":"Pal Basti",
    "ks:ks_pop":500,
    "ks:ks_type":"HABITATION",
    "name:eng_x_preferred":[
        "Pal Basti"
    ],
    "wof:name":"Pal Basti",
    "wof:placetype":"locality",
    "wof:population":500
},
  "geometry": {"coordinates":[82.29563899999999,25.842793],"type":"Point"}
}