{
  "type": "Feature",
  "properties": {
    "iso:country":"IN",
    "ks:ks_name":"Baradia",
    "ks:ks_pop":758,
    "ks:ks_type":"VILLAGE",
    "name:eng_x_preferred":[
        "Baradia"
    ],
    "wof:name":"Baradia",
    "wof:placetype":"locality",
    "wof:population":758
},
  "geometry": {"coordinates":[86.15507700000001,20.55431],"type":"Point"}
}