{
  "type": "Feature",
  "properties": {
    "gn:admin1_code":"35",
    "gn:admin2_code":"446.0",
    "gn:asciiname":"Sinwaha",
    "gn:country_code":"IN",
    "gn:dem":329,
    "gn:feature_class":"P",
    "gn:feature_code":"PPL",
    "gn:name":"Sinw\u0101ha",
    "gn:population":0,
    "gn:timezone":"Asia/Kolkata",
    "iso:country":"IN",
    "ks:ks_name":"Sinwah",
    "ks:ks_pop":326,
    "ks:ks_type":"VILLAGE",
    "name:eng_x_preferred":[
        "Sinwah"
    ],
    "name:eng_x_variant":[
        "Sinwaha"
    ],
    "wof:name":"Sinwah",
    "wof:placetype":"locality",
    "wof:population":326
},
  "geometry": {"coordinates":[78.246443,23.060968],"type":"Point"}
}