{
  "type": "Feature",
  "properties": {
    "iso:country":"IN",
    "ks:ks_name":"Chatram",
    "ks:ks_pop":170,
    "ks:ks_type":"VILLAGE",
    "name:eng_x_preferred":[
        "Chatram"
    ],
    "wof:name":"Chatram",
    "wof:placetype":"locality",
    "wof:population":170
},
  "geometry": {"coordinates":[87.050544,24.6107],"type":"Point"}
}