{
  "type": "Feature",
  "properties": {
    "iso:country":"IN",
    "ks:ks_name":"Gopalpur",
    "ks:ks_pop":965,
    "ks:ks_type":"VILLAGE",
    "name:eng_x_preferred":[
        "Gopalpur"
    ],
    "wof:name":"Gopalpur",
    "wof:placetype":"locality",
    "wof:population":965
},
  "geometry": {"coordinates":[88.319202,22.085557],"type":"Point"}
}