{
  "type": "Feature",
  "properties": {
    "iso:country":"IN",
    "ks:ks_name":"Kolbamri",
    "ks:ks_pop":177,
    "ks:ks_type":"VILLAGE",
    "name:eng_x_preferred":[
        "Kolbamri"
    ],
    "wof:name":"Kolbamri",
    "wof:placetype":"locality",
    "wof:population":177
},
  "geometry": {"coordinates":[85.14396600000001,22.471079],"type":"Point"}
}