{
  "type": "Feature",
  "properties": {
    "gn:admin1_code":"25",
    "gn:admin2_code":"604.0",
    "gn:asciiname":"Tenmelpakkam",
    "gn:country_code":"IN",
    "gn:dem":51,
    "gn:feature_class":"P",
    "gn:feature_code":"PPL",
    "gn:name":"Tenmelp\u0101kkam",
    "gn:population":0,
    "gn:timezone":"Asia/Kolkata",
    "iso:country":"IN",
    "ks:ks_alt_nam":"Tenmelp\u0101kkam",
    "ks:ks_name":"Tenmelpakkam",
    "ks:ks_type":"VILLAGE",
    "ks:ks_uagg_main":0,
    "name:eng_x_preferred":[
        "Tenmelpakkam"
    ],
    "name:eng_x_variant":[
        "Tenmelp\u0101kkam"
    ],
    "wof:name":"Tenmelpakkam",
    "wof:placetype":"neighbourhood"
},
  "geometry": {"coordinates":[80.019004,12.73919],"type":"Point"}
}