{
  "type": "Feature",
  "properties": {
    "iso:country":"IN",
    "ks:ks_name":"Company Para",
    "ks:ks_pop":343,
    "ks:ks_type":"HABITATION",
    "name:eng_x_preferred":[
        "Company Para"
    ],
    "wof:name":"Company Para",
    "wof:placetype":"locality",
    "wof:population":343
},
  "geometry": {"coordinates":[92.088194,24.032017],"type":"Point"}
}