{
  "type": "Feature",
  "properties": {
    "iso:country":"IN",
    "ks:ks_name":"Jhagaru Pipal",
    "ks:ks_pop":125,
    "ks:ks_type":"HABITATION",
    "name:eng_x_preferred":[
        "Jhagaru Pipal"
    ],
    "wof:name":"Jhagaru Pipal",
    "wof:placetype":"locality",
    "wof:population":125
},
  "geometry": {"coordinates":[84.700462,24.940839],"type":"Point"}
}