{
  "type": "Feature",
  "properties": {
    "gn:country":"IN",
    "gn:fcode":"PPL",
    "gn:pop":22920,
    "iso:country":"IN",
    "name:eng_x_preferred":[
        "Vemulavada"
    ],
    "name:fas_x_preferred":[
        "\u0648\u0645\u0648\u0644\u0648\u062f\u0627"
    ],
    "name:new_x_preferred":[
        "\u0935\u0947\u092e\u0941\u0932\u0935\u093e\u0921 \u092e\u0923\u094d\u0921\u0932"
    ],
    "name:nld_x_preferred":[
        "Vemulavada"
    ],
    "name:pam_x_preferred":[
        "Vemulavada"
    ],
    "name:swe_x_preferred":[
        "Vemalw\u0101da"
    ],
    "name:tel_x_preferred":[
        "\u0c35\u0c47\u0c2e\u0c41\u0c32\u0c35\u0c3e\u0c21"
    ],
    "name:unk_x_variant":[
        "Lembulavataka"
    ],
    "qs:name":"Vemalw\u0101da",
    "qs:photos_9r":0,
    "qs:photos_sr":0,
    "qs:pop_sr":"7",
    "wof:name":"Vemalw\u0101da",
    "wof:placetype":"locality",
    "wof:population":22920
},
  "geometry": {"coordinates":[78.86893999999999,18.46523],"type":"Point"}
}