{
  "type": "Feature",
  "properties": {
    "iso:country":"IN",
    "ks:ks_name":"Keelakottai",
    "ks:ks_pop":133,
    "ks:ks_type":"HABITATION",
    "name:eng_x_preferred":[
        "Keelakottai"
    ],
    "wof:name":"Keelakottai",
    "wof:placetype":"locality",
    "wof:population":133
},
  "geometry": {"coordinates":[78.813868,9.73104],"type":"Point"}
}