{
  "type": "Feature",
  "properties": {
    "iso:country":"IN",
    "ks:ks_name":"Tamhane Karambe",
    "ks:ks_pop":316,
    "ks:ks_type":"VILLAGE",
    "name:eng_x_preferred":[
        "Tamhane Karambe"
    ],
    "wof:name":"Tamhane Karambe",
    "wof:placetype":"locality",
    "wof:population":316
},
  "geometry": {"coordinates":[73.142708,18.116092],"type":"Point"}
}