{
  "type": "Feature",
  "properties": {
    "iso:country":"IN",
    "ks:ks_name":"Peddapalle",
    "ks:ks_pop":73,
    "ks:ks_type":"HABITATION",
    "name:eng_x_preferred":[
        "Peddapalle"
    ],
    "wof:name":"Peddapalle",
    "wof:placetype":"locality",
    "wof:population":73
},
  "geometry": {"coordinates":[78.78840099999999,13.683697],"type":"Point"}
}