{
  "type": "Feature",
  "properties": {
    "iso:country":"IN",
    "ks:ks_name":"Govindapuram",
    "ks:ks_pop":65,
    "ks:ks_type":"HABITATION",
    "name:eng_x_preferred":[
        "Govindapuram"
    ],
    "wof:name":"Govindapuram",
    "wof:placetype":"locality",
    "wof:population":65
},
  "geometry": {"coordinates":[77.954572,12.541263],"type":"Point"}
}