{
  "type": "Feature",
  "properties": {
    "gn:admin1_code":"36",
    "gn:admin2_code":"188.0",
    "gn:asciiname":"Manjharia",
    "gn:country_code":"IN",
    "gn:dem":82,
    "gn:feature_class":"P",
    "gn:feature_code":"PPL",
    "gn:name":"Manjharia",
    "gn:population":0,
    "gn:timezone":"Asia/Kolkata",
    "iso:country":"IN",
    "ks:ks_name":"Manjharia",
    "ks:ks_pop":1934,
    "ks:ks_type":"VILLAGE",
    "ks:ks_uagg_main":0,
    "name:eng_x_preferred":[
        "Manjharia"
    ],
    "wof:name":"Manjharia",
    "wof:placetype":"neighbourhood",
    "wof:population":1934
},
  "geometry": {"coordinates":[83.24484099999999,26.905261],"type":"Point"}
}