{
  "type": "Feature",
  "properties": {
    "gn:admin1_code":"34.0",
    "gn:admin2_code":"212.0",
    "gn:asciiname":"Nayatola",
    "gn:country_code":"IN",
    "gn:dem":35,
    "gn:feature_class":"P",
    "gn:feature_code":"PPL",
    "gn:name":"Nay\u0101tola",
    "gn:population":0,
    "gn:timezone":"Asia/Kolkata",
    "iso:country":"IN",
    "name:ara_x_preferred":[
        "\u0646\u0627\u064a\u062a\u0648\u0644\u0627"
    ],
    "name:ben_bn_x_preferred":[
        "\u09a8\u09be\u09df\u09be\u099f\u09cb\u09b2\u09be"
    ],
    "name:ben_in_x_preferred":[
        "\u09a8\u09be\u09df\u09be\u099f\u09cb\u09b2\u09be"
    ],
    "name:guj_x_preferred":[
        "\u0aa8\u0aaf\u0abe\u0aa4\u0acb\u0ab2\u0abe"
    ],
    "name:hin_x_preferred":[
        "\u0928\u092f\u093e\u0924\u094b\u0932\u093e"
    ],
    "name:kan_x_preferred":[
        "\u0ca8\u0caf\u0cbe\u0ca4\u0cca\u0cb2"
    ],
    "name:mal_x_preferred":[
        "\u0d28\u0d2f\u0d3e\u0d24\u0d4b\u0d33"
    ],
    "name:mar_x_preferred":[
        "\u0928\u093e\u092f\u091f\u094b\u0932\u093e"
    ],
    "name:pan_x_preferred":[
        "\u0a28\u0a2f\u0a3e\u0a1f\u0a4b\u0a32\u0a3e"
    ],
    "name:tam_x_preferred":[
        "\u0ba8\u0baf\u0bbe\u0b9f\u0bca\u0bb2\u0bbe"
    ],
    "name:tel_x_preferred":[
        "\u0c28\u0c2f\u0c3e\u0c1f\u0c4b\u0c32\u0c3e"
    ],
    "name:urd_x_preferred":[
        "\u0646\u06cc\u0627 \u0679\u0648\u0644\u06c1"
    ],
    "wof:name":"Nayatola",
    "wof:placetype":"locality"
},
  "geometry": {"coordinates":[87.85629,25.66875],"type":"Point"}
}