{
  "type": "Feature",
  "properties": {
    "iso:country":"IN",
    "ks:ks_alt_nam":"HARIJAN TOL",
    "ks:ks_name":"Harijan Tol",
    "ks:ks_pop":1214,
    "ks:ks_type":"HABITATION",
    "name:eng_x_preferred":[
        "Harijan Tol"
    ],
    "wof:name":"Harijan Tol",
    "wof:placetype":"locality",
    "wof:population":1214
},
  "geometry": {"coordinates":[86.176592,25.933498],"type":"Point"}
}