{
  "type": "Feature",
  "properties": {
    "iso:country":"IN",
    "ks:ks_alt_nam":"Chakirevu cheruvu",
    "ks:ks_name":"Chakirevu Cheruvu",
    "ks:ks_pop":89,
    "ks:ks_type":"HABITATION",
    "name:eng_x_preferred":[
        "Chakirevu Cheruvu"
    ],
    "wof:name":"Chakirevu Cheruvu",
    "wof:placetype":"locality",
    "wof:population":89
},
  "geometry": {"coordinates":[81.762992,16.599455],"type":"Point"}
}