{
  "type": "Feature",
  "properties": {
    "iso:country":"IN",
    "ks:ks_name":"Singirpar",
    "ks:ks_pop":514,
    "ks:ks_type":"HABITATION",
    "ks:ks_uagg_main":0,
    "name:eng_x_preferred":[
        "Singirpar"
    ],
    "wof:name":"Singirpar",
    "wof:placetype":"neighbourhood",
    "wof:population":514
},
  "geometry": {"coordinates":[92.463346,24.578811],"type":"Point"}
}