{
  "type": "Feature",
  "properties": {
    "iso:country":"IN",
    "ks:ks_name":"Lodta Haridasot",
    "ks:ks_pop":1761,
    "ks:ks_type":"VILLAGE",
    "name:eng_x_preferred":[
        "Lodta Haridasot"
    ],
    "wof:name":"Lodta Haridasot",
    "wof:placetype":"locality",
    "wof:population":1761
},
  "geometry": {"coordinates":[72.431769,26.726719],"type":"Point"}
}