{
  "type": "Feature",
  "properties": {
    "iso:country":"IN",
    "ks:ks_name":"Gaunsuwal",
    "ks:ks_pop":885,
    "ks:ks_type":"VILLAGE",
    "name:eng_x_preferred":[
        "Gaunsuwal"
    ],
    "wof:name":"Gaunsuwal",
    "wof:placetype":"locality",
    "wof:population":885
},
  "geometry": {"coordinates":[75.46653000000001,30.98095],"type":"Point"}
}