{
  "type": "Feature",
  "properties": {
    "iso:country":"IN",
    "ks:ks_alt_nam":"NAGLABRIJE",
    "ks:ks_name":"Naglabrije",
    "ks:ks_pop":300,
    "ks:ks_type":"HABITATION",
    "name:eng_x_preferred":[
        "Naglabrije"
    ],
    "wof:name":"Naglabrije",
    "wof:placetype":"locality",
    "wof:population":300
},
  "geometry": {"coordinates":[79.015753,26.91835],"type":"Point"}
}