{
  "type": "Feature",
  "properties": {
    "iso:country":"IN",
    "ks:ks_name":"Romba",
    "ks:ks_pop":107,
    "ks:ks_type":"VILLAGE",
    "name:eng_x_preferred":[
        "Romba"
    ],
    "wof:name":"Romba",
    "wof:placetype":"locality",
    "wof:population":107
},
  "geometry": {"coordinates":[85.406566,22.921923],"type":"Point"}
}