{
  "type": "Feature",
  "properties": {
    "iso:country":"IN",
    "ks:ks_name":"Kumbarwada",
    "ks:ks_pop":45,
    "ks:ks_type":"HABITATION",
    "name:eng_x_preferred":[
        "Kumbarwada"
    ],
    "wof:name":"Kumbarwada",
    "wof:placetype":"locality",
    "wof:population":45
},
  "geometry": {"coordinates":[74.316016,15.444883],"type":"Point"}
}