{
  "type": "Feature",
  "properties": {
    "iso:country":"IN",
    "ks:ks_name":"Udaipur",
    "ks:ks_pop":0,
    "ks:ks_type":"VILLAGE",
    "name:eng_x_preferred":[
        "Udaipur"
    ],
    "name:hin_x_preferred":[
        "\u0909\u0926\u092f\u092a\u0941\u0930"
    ],
    "wof:name":"Udaipur",
    "wof:placetype":"locality",
    "wof:population":0
},
  "geometry": {"coordinates":[86.625118,24.682254],"type":"Point"}
}