{
  "type": "Feature",
  "properties": {
    "iso:country":"IN",
    "ks:ks_alt_nam":"KANU TOLA",
    "ks:ks_name":"Kanu Tola",
    "ks:ks_pop":388,
    "ks:ks_type":"HABITATION",
    "ks:ks_uagg_main":0,
    "name:eng_x_preferred":[
        "Kanu Tola"
    ],
    "wof:name":"Kanu Tola",
    "wof:placetype":"neighbourhood",
    "wof:population":388
},
  "geometry": {"coordinates":[84.628174,26.661586],"type":"Point"}
}