{
  "type": "Feature",
  "properties": {
    "gn:admin1_code":"2.0",
    "gn:admin2_code":"547.0",
    "gn:asciiname":"Pedda Pudi",
    "gn:country_code":"IN",
    "gn:dem":12,
    "gn:feature_class":"P",
    "gn:feature_code":"PPL",
    "gn:name":"Pedda P\u016bdi",
    "gn:population":0,
    "gn:timezone":"Asia/Kolkata",
    "iso:country":"IN",
    "ks:ks_name":"Pedapudi",
    "ks:ks_pop":3272,
    "ks:ks_type":"VILLAGE",
    "ks:ks_uagg_main":0,
    "name:eng_x_preferred":[
        "Pedapudi"
    ],
    "wof:name":"Pedapudi",
    "wof:placetype":"neighbourhood",
    "wof:population":3272
},
  "geometry": {"coordinates":[80.916225,16.255683],"type":"Point"}
}