{
  "type": "Feature",
  "properties": {
    "gn:admin1_code":"34.0",
    "gn:admin2_code":"217.0",
    "gn:asciiname":"Usri",
    "gn:country_code":"IN",
    "gn:dem":69,
    "gn:feature_class":"P",
    "gn:feature_code":"PPL",
    "gn:name":"Usri",
    "gn:population":0,
    "gn:timezone":"Asia/Kolkata",
    "iso:country":"IN",
    "ks:ks_name":"Usri",
    "ks:ks_pop":25,
    "ks:ks_type":"VILLAGE",
    "ks:ks_uagg_main":0,
    "name:eng_x_preferred":[
        "Usri"
    ],
    "wof:name":"Usri",
    "wof:placetype":"neighbourhood",
    "wof:population":25
},
  "geometry": {"coordinates":[84.77909699999999,26.298738],"type":"Point"}
}