{
  "type": "Feature",
  "properties": {
    "gn:admin1_code":"34.0",
    "gn:admin2_code":"223.0",
    "gn:asciiname":"Basbiti",
    "gn:country_code":"IN",
    "gn:dem":42,
    "gn:feature_class":"P",
    "gn:feature_code":"PPL",
    "gn:name":"Basbiti",
    "gn:population":0,
    "gn:timezone":"Asia/Kolkata",
    "iso:country":"IN",
    "name:bih_x_preferred":[
        "\u092c\u0938\u092c\u093f\u091f\u0940"
    ],
    "name:ceb_x_preferred":[
        "Basbiti"
    ],
    "name:fra_x_preferred":[
        "Basbiti"
    ],
    "name:mai_x_preferred":[
        "\u092c\u0938\u092c\u093f\u091f\u0940"
    ],
    "name:msa_x_preferred":[
        "Basbiti"
    ],
    "name:nep_x_preferred":[
        "\u092c\u0938\u092c\u093f\u091f\u0940"
    ],
    "name:pol_x_preferred":[
        "Basbiti"
    ],
    "wof:name":"Basbiti",
    "wof:placetype":"neighbourhood"
},
  "geometry": {"coordinates":[86.49827999999999,25.55411],"type":"Point"}
}