{
  "type": "Feature",
  "properties": {
    "gn:admin1_code":"19.0",
    "gn:admin2_code":"568.0",
    "gn:asciiname":"Hosahalli",
    "gn:country_code":"IN",
    "gn:dem":649,
    "gn:feature_class":"P",
    "gn:feature_code":"PPL",
    "gn:name":"Hosahalli",
    "gn:population":0,
    "gn:timezone":"Asia/Kolkata",
    "iso:country":"IN",
    "wof:name":"Hosahalli",
    "wof:placetype":"locality"
},
  "geometry": {"coordinates":[75.50039,13.95599],"type":"Point"}
}