{
  "type": "Feature",
  "properties": {
    "gn:admin1_code":"19.0",
    "gn:admin2_code":"568.0",
    "gn:asciiname":"Hosahalli",
    "gn:country_code":"IN",
    "gn:dem":649,
    "gn:feature_class":"P",
    "gn:feature_code":"PPL",
    "gn:name":"Hosahalli",
    "gn:population":0,
    "gn:timezone":"Asia/Kolkata",
    "iso:country":"IN",
    "name:ara_x_preferred":[
        "\u0647\u0648\u0633\u0647\u0627\u0644\u064a"
    ],
    "name:ben_bn_x_preferred":[
        "\u09b9\u09cb\u09b8\u09be\u09b9\u09be\u09b2\u09cd\u09b2\u09bf"
    ],
    "name:ben_in_x_preferred":[
        "\u09b9\u09cb\u09b8\u09be\u09b9\u09be\u09b2\u09cd\u09b2\u09bf"
    ],
    "name:guj_x_preferred":[
        "\u0ab9\u0acb\u0ab8\u0abe\u0ab9\u0ab2\u0acd\u0ab2\u0ac0"
    ],
    "name:hin_x_preferred":[
        "\u0939\u094b\u0938\u0939\u0932\u094d\u0932\u0940"
    ],
    "name:kan_x_preferred":[
        "\u0cb9\u0cca\u0cb8\u0cb9\u0cb3\u0ccd\u0cb3\u0cbf"
    ],
    "name:kan_x_variant":[
        "\u0cb9\u0cca\u0cb8 \u0cb9\u0cb3\u0ccd\u0cb3\u0cbf"
    ],
    "name:mal_x_preferred":[
        "\u0d39\u0d4b\u0d38\u0d39\u0d33\u0d4d\u0d33\u0d3f"
    ],
    "name:mar_x_preferred":[
        "\u0939\u094b\u0938\u093e\u0939\u0932\u094d\u0932\u0940"
    ],
    "name:pan_x_preferred":[
        "\u0a39\u0a4b\u0a38\u0a3e\u0a39\u0a71\u0a32\u0a40"
    ],
    "name:tam_x_preferred":[
        "\u0bb9\u0bca\u0b9a\u0bb9\u0bb3\u0bcd\u0bb3\u0bbf"
    ],
    "name:tel_x_preferred":[
        "\u0c39\u0c4b\u0c38\u0c3e\u0c39\u0c33\u0c4d\u0c33\u0c3f"
    ],
    "name:urd_x_preferred":[
        "\u06c1\u0648\u0633\u0627 \u06c1\u0644\u0651\u06cc"
    ],
    "wof:name":"Hosahalli",
    "wof:placetype":"locality"
},
  "geometry": {"coordinates":[75.50039,13.95599],"type":"Point"}
}