{
  "type": "Feature",
  "properties": {
    "gn:admin1_code":"16.0",
    "gn:admin2_code":"530.0",
    "gn:asciiname":"Gudavale",
    "gn:country_code":"IN",
    "gn:dem":723,
    "gn:feature_class":"P",
    "gn:feature_code":"PPL",
    "gn:name":"Gudavale",
    "gn:population":0,
    "gn:timezone":"Asia/Kolkata",
    "iso:country":"IN",
    "wof:name":"Gudavale",
    "wof:placetype":"locality"
},
  "geometry": {"coordinates":[74.16609,15.87089],"type":"Point"}
}