{
  "type": "Feature",
  "properties": {
    "iso:country":"IN",
    "ks:ks_name":"Kanthur Murnad",
    "ks:ks_pop":2696,
    "ks:ks_type":"HABITATION",
    "name:eng_x_preferred":[
        "Kanthur Murnad"
    ],
    "wof:name":"Kanthur Murnad",
    "wof:placetype":"locality",
    "wof:population":2696
},
  "geometry": {"coordinates":[75.747412,12.320461],"type":"Point"}
}