{
  "type": "Feature",
  "properties": {
    "iso:country":"IN",
    "ks:ks_alt_nam":"6 SGM-A",
    "ks:ks_name":"6 Sgm-a",
    "ks:ks_pop":1009,
    "ks:ks_type":"HABITATION",
    "name:eng_x_preferred":[
        "6 Sgm-a"
    ],
    "wof:name":"6 Sgm-a",
    "wof:placetype":"locality",
    "wof:population":1009
},
  "geometry": {"coordinates":[73.844847,29.372621],"type":"Point"}
}