{
  "type": "Feature",
  "properties": {
    "iso:country":"IN",
    "ks:ks_name":"Gulamaliwala",
    "ks:ks_pop":1934,
    "ks:ks_type":"HABITATION",
    "name:eng_x_preferred":[
        "Gulamaliwala"
    ],
    "wof:name":"Gulamaliwala",
    "wof:placetype":"locality",
    "wof:population":1934
},
  "geometry": {"coordinates":[72.542467,28.396581],"type":"Point"}
}