{
  "type": "Feature",
  "properties": {
    "iso:country":"IN",
    "ks:ks_name":"Kathavanendal",
    "ks:ks_pop":1002,
    "ks:ks_type":"VILLAGE",
    "name:eng_x_preferred":[
        "Kathavanendal"
    ],
    "wof:name":"Kathavanendal",
    "wof:placetype":"locality",
    "wof:population":1002
},
  "geometry": {"coordinates":[78.18536899999999,9.90877],"type":"Point"}
}