{
  "type": "Feature",
  "properties": {
    "iso:country":"IN",
    "ks:ks_name":"Shantibari",
    "ks:ks_pop":183,
    "ks:ks_type":"VILLAGE",
    "name:eng_x_preferred":[
        "Shantibari"
    ],
    "wof:name":"Shantibari",
    "wof:placetype":"locality",
    "wof:population":183
},
  "geometry": {"coordinates":[88.05028,26.083402],"type":"Point"}
}