{
  "type": "Feature",
  "properties": {
    "iso:country":"IN",
    "ks:ks_name":"Borah Gaon",
    "ks:ks_pop":1019,
    "ks:ks_type":"VILLAGE",
    "name:eng_x_preferred":[
        "Borah Gaon"
    ],
    "wof:name":"Borah Gaon",
    "wof:placetype":"locality",
    "wof:population":1019
},
  "geometry": {"coordinates":[95.149163,27.067261],"type":"Point"}
}