{
  "type": "Feature",
  "properties": {
    "iso:country":"IN",
    "ks:ks_name":"Hemakki",
    "ks:ks_pop":26,
    "ks:ks_type":"HABITATION",
    "name:eng_x_preferred":[
        "Hemakki"
    ],
    "wof:name":"Hemakki",
    "wof:placetype":"locality",
    "wof:population":26
},
  "geometry": {"coordinates":[75.051439,13.798616],"type":"Point"}
}