{
  "type": "Feature",
  "properties": {
    "iso:country":"IN",
    "ks:ks_name":"Saraipara",
    "ks:ks_pop":304,
    "ks:ks_type":"HABITATION",
    "name:eng_x_preferred":[
        "Saraipara"
    ],
    "wof:name":"Saraipara",
    "wof:placetype":"locality",
    "wof:population":304
},
  "geometry": {"coordinates":[83.730017,22.310937],"type":"Point"}
}