{
  "type": "Feature",
  "properties": {
    "gn:admin1_code":"36",
    "gn:admin2_code":"188.0",
    "gn:asciiname":"Suchitpur",
    "gn:country_code":"IN",
    "gn:dem":86,
    "gn:feature_class":"P",
    "gn:feature_code":"PPL",
    "gn:name":"Suchitpur",
    "gn:population":0,
    "gn:timezone":"Asia/Kolkata",
    "iso:country":"IN",
    "ks:ks_name":"Suchitpur",
    "ks:ks_pop":326,
    "ks:ks_type":"HABITATION",
    "ks:ks_uagg_main":0,
    "name:eng_x_preferred":[
        "Suchitpur"
    ],
    "wof:name":"Suchitpur",
    "wof:placetype":"neighbourhood",
    "wof:population":326
},
  "geometry": {"coordinates":[83.423371,26.922661],"type":"Point"}
}