{
  "type": "Feature",
  "properties": {
    "iso:country":"IN",
    "ks:ks_name":"Keuburla",
    "ks:ks_pop":91,
    "ks:ks_type":"VILLAGE",
    "name:eng_x_preferred":[
        "Keuburla"
    ],
    "wof:name":"Keuburla",
    "wof:placetype":"locality",
    "wof:population":91
},
  "geometry": {"coordinates":[82.45965700000001,19.911573],"type":"Point"}
}