{
  "type": "Feature",
  "properties": {
    "iso:country":"IN",
    "ks:ks_alt_nam":"Vabur khola",
    "ks:ks_name":"Vabur Khola",
    "ks:ks_pop":422,
    "ks:ks_type":"HABITATION",
    "name:eng_x_preferred":[
        "Vabur Khola"
    ],
    "wof:name":"Vabur Khola",
    "wof:placetype":"locality",
    "wof:population":422
},
  "geometry": {"coordinates":[79.445629,29.781685],"type":"Point"}
}