{
  "type": "Feature",
  "properties": {
    "gn:admin1_code":"36.0",
    "gn:admin2_code":"137.0",
    "gn:asciiname":"Deorala",
    "gn:country_code":"IN",
    "gn:dem":218,
    "gn:feature_class":"P",
    "gn:feature_code":"PPL",
    "gn:name":"Deor\u0101la",
    "gn:population":0,
    "gn:timezone":"Asia/Kolkata",
    "iso:country":"IN",
    "name:ara_x_preferred":[
        "\u062f\u064a\u0631\u0648\u0644\u0627"
    ],
    "name:ben_bn_x_preferred":[
        "\u09a6\u09c7\u0993\u09b0\u09be\u09b2\u09be"
    ],
    "name:ben_in_x_preferred":[
        "\u09a6\u09c7\u0993\u09b0\u09be\u09b2\u09be"
    ],
    "name:guj_x_preferred":[
        "\u0aa6\u0ac7\u0ab5\u0ab0\u0abe\u0ab2\u0abe"
    ],
    "name:hin_x_preferred":[
        "\u0926\u0947\u0935\u0930\u093e\u0932\u093e"
    ],
    "name:kan_x_preferred":[
        "\u0ca6\u0cbf\u0caf\u0ccb\u0cb0\u0cbe\u0cb2"
    ],
    "name:mal_x_preferred":[
        "\u0d21\u0d3f\u0d2f\u0d4b\u0d31\u0d32"
    ],
    "name:mar_x_preferred":[
        "\u0926\u0947\u0935\u0930\u0932\u093e"
    ],
    "name:pan_x_preferred":[
        "\u0a07\u0a13\u0a30\u0a32\u0a3e"
    ],
    "name:tam_x_preferred":[
        "\u0b9f\u0bbf\u0baf\u0bcb\u0bb0\u0bb2\u0bbe"
    ],
    "name:tel_x_preferred":[
        "\u0c26\u0c3f\u0c2f\u0c4b\u0c30\u0c3e\u0c32\u0c3e"
    ],
    "name:urd_x_preferred":[
        "\u062f\u06cc\u0648\u0631\u0627\u06c1\u0627"
    ],
    "wof:name":"Deorala",
    "wof:placetype":"locality"
},
  "geometry": {"coordinates":[78.32075,28.91694],"type":"Point"}
}