{
  "type": "Feature",
  "properties": {
    "gn:admin1_code":"25",
    "gn:admin2_code":"631.0",
    "gn:asciiname":"Uttangarai",
    "gn:cc2":"IN",
    "gn:country_code":"IN",
    "gn:dem":339,
    "gn:feature_class":"P",
    "gn:feature_code":"PPL",
    "gn:name":"\u016attangarai",
    "gn:population":0,
    "gn:timezone":"Asia/Kolkata",
    "iso:country":"IN",
    "name:und_x_variant":[
        "Uttangaral",
        "\u016attangarai"
    ],
    "wof:name":"Uttangarai",
    "wof:placetype":"locality"
},
  "geometry": {"coordinates":[78.53783,12.26713],"type":"Point"}
}