{
  "type": "Feature",
  "properties": {
    "iso:country":"IN",
    "ks:ks_alt_nam":"CHAUTHAI KA PURWA",
    "ks:ks_name":"Chauthai Ka Purwa",
    "ks:ks_pop":26,
    "ks:ks_type":"HABITATION",
    "ks:ks_uagg_main":0,
    "name:eng_x_preferred":[
        "Chauthai Ka Purwa"
    ],
    "wof:name":"Chauthai Ka Purwa",
    "wof:placetype":"neighbourhood",
    "wof:population":26
},
  "geometry": {"coordinates":[82.04859399999999,26.405683],"type":"Point"}
}