{
  "type": "Feature",
  "properties": {
    "gn:country":"IN",
    "gn:fcode":"PPL",
    "gn:pop":500,
    "iso:country":"IN",
    "qs:name":"kotta palem",
    "qs:photos_9r":0,
    "qs:photos_sr":0,
    "qs:pop_sr":"2",
    "wof:name":"kotta palem",
    "wof:placetype":"locality",
    "wof:population":500
},
  "geometry": {"coordinates":[80.16492,15.85747],"type":"Point"}
}