{
  "type": "Feature",
  "properties": {
    "iso:country":"IN",
    "ks:ks_alt_nam":"MishraWas",
    "ks:ks_name":"Mishrawas",
    "ks:ks_pop":75,
    "ks:ks_type":"HABITATION",
    "name:eng_x_preferred":[
        "Mishrawas"
    ],
    "wof:name":"Mishrawas",
    "wof:placetype":"locality",
    "wof:population":75
},
  "geometry": {"coordinates":[75.981089,27.326675],"type":"Point"}
}