{
  "type": "Feature",
  "properties": {
    "iso:country":"IN",
    "ks:ks_alt_nam":"R\u0101tung",
    "ks:ks_name":"Ratung",
    "ks:ks_pop":210,
    "ks:ks_type":"VILLAGE",
    "name:eng_x_preferred":[
        "Ratung"
    ],
    "name:eng_x_variant":[
        "R\u0101tung"
    ],
    "wof:name":"Ratung",
    "wof:placetype":"locality",
    "wof:population":210
},
  "geometry": {"coordinates":[85.402548,22.834937],"type":"Point"}
}