{
  "type": "Feature",
  "properties": {
    "iso:country":"IN",
    "ks:ks_name":"Kantashola",
    "ks:ks_pop":71,
    "ks:ks_type":"VILLAGE",
    "name:eng_x_preferred":[
        "Kantashola"
    ],
    "wof:name":"Kantashola",
    "wof:placetype":"locality",
    "wof:population":71
},
  "geometry": {"coordinates":[86.766102,22.299345],"type":"Point"}
}