{
  "type": "Feature",
  "properties": {
    "iso:country":"IN",
    "ks:ks_name":"Barudihi",
    "ks:ks_pop":176,
    "ks:ks_type":"VILLAGE",
    "name:eng_x_preferred":[
        "Barudihi"
    ],
    "wof:name":"Barudihi",
    "wof:placetype":"locality",
    "wof:population":176
},
  "geometry": {"coordinates":[86.54325,21.718131],"type":"Point"}
}