{
  "type": "Feature",
  "properties": {
    "gn:admin1_code":"2",
    "gn:admin2_code":"544.0",
    "gn:asciiname":"Chakipalle",
    "gn:country_code":"IN",
    "gn:dem":62,
    "gn:feature_class":"P",
    "gn:feature_code":"PPL",
    "gn:name":"Ch\u0101kipalle",
    "gn:population":0,
    "gn:timezone":"Asia/Kolkata",
    "iso:country":"IN",
    "wof:name":"Chakipalle",
    "wof:placetype":"locality"
},
  "geometry": {"coordinates":[82.93212,17.76952],"type":"Point"}
}