{
  "type": "Feature",
  "properties": {
    "gn:admin1_code":"35.0",
    "gn:admin2_code":"427",
    "gn:asciiname":"Kanti",
    "gn:country_code":"IN",
    "gn:dem":493,
    "gn:feature_class":"P",
    "gn:feature_code":"PPL",
    "gn:name":"K\u0101nti",
    "gn:population":0,
    "gn:timezone":"Asia/Kolkata",
    "iso:country":"IN",
    "wof:name":"Kanti",
    "wof:placetype":"locality"
},
  "geometry": {"coordinates":[78.9271,24.03854],"type":"Point"}
}