{
  "type": "Feature",
  "properties": {
    "iso:country":"IN",
    "ks:ks_name":"Virinjippadam",
    "ks:ks_pop":1100,
    "ks:ks_type":"HABITATION",
    "name:eng_x_preferred":[
        "Virinjippadam"
    ],
    "wof:name":"Virinjippadam",
    "wof:placetype":"locality",
    "wof:population":1100
},
  "geometry": {"coordinates":[76.683542,10.670295],"type":"Point"}
}