{
  "type": "Feature",
  "properties": {
    "iso:country":"IN",
    "ks:ks_name":"Thakurpada",
    "ks:ks_pop":154,
    "ks:ks_type":"HABITATION",
    "name:eng_x_preferred":[
        "Thakurpada"
    ],
    "wof:name":"Thakurpada",
    "wof:placetype":"locality",
    "wof:population":154
},
  "geometry": {"coordinates":[73.199985,19.428925],"type":"Point"}
}