{
  "type": "Feature",
  "properties": {
    "iso:country":"IN",
    "ks:ks_name":"Koorad Jn-2",
    "ks:ks_pop":1126,
    "ks:ks_type":"HABITATION",
    "ks:ks_uagg_main":0,
    "name:eng_x_preferred":[
        "Koorad Jn-2"
    ],
    "wof:name":"Koorad Jn-2",
    "wof:placetype":"neighbourhood",
    "wof:population":1126
},
  "geometry": {"coordinates":[76.28864299999999,11.214443],"type":"Point"}
}