{
  "type": "Feature",
  "properties": {
    "iso:country":"IN",
    "ks:ks_name":"Sapronde",
    "ks:ks_pop":738,
    "ks:ks_type":"VILLAGE",
    "ks:ks_uagg_main":0,
    "name:eng_x_preferred":[
        "Sapronde"
    ],
    "wof:name":"Sapronde",
    "wof:placetype":"neighbourhood",
    "wof:population":738
},
  "geometry": {"coordinates":[73.110021,19.530146],"type":"Point"}
}