{
  "type": "Feature",
  "properties": {
    "iso:country":"IN",
    "ks:ks_name":"Senkulam",
    "ks:ks_pop":1021,
    "ks:ks_type":"HABITATION",
    "name:eng_x_preferred":[
        "Senkulam"
    ],
    "wof:name":"Senkulam",
    "wof:placetype":"locality",
    "wof:population":1021
},
  "geometry": {"coordinates":[78.24784,10.237853],"type":"Point"}
}