{
  "type": "Feature",
  "properties": {
    "iso:country":"IN",
    "ks:ks_name":"N. Himmat",
    "ks:ks_pop":724,
    "ks:ks_type":"HABITATION",
    "name:eng_x_preferred":[
        "N. Himmat"
    ],
    "wof:name":"N. Himmat",
    "wof:placetype":"locality",
    "wof:population":724
},
  "geometry": {"coordinates":[79.176348,27.231483],"type":"Point"}
}