{
  "type": "Feature",
  "properties": {
    "gn:admin1_code":"37",
    "gn:admin2_code":"404.0",
    "gn:asciiname":"Kurudih",
    "gn:country_code":"IN",
    "gn:dem":269,
    "gn:feature_class":"P",
    "gn:feature_code":"PPL",
    "gn:name":"Kur\u016bd\u012bh",
    "gn:population":0,
    "gn:timezone":"Asia/Kolkata",
    "iso:country":"IN",
    "ks:ks_alt_nam":"Kur\u016bd\u012bh",
    "ks:ks_name":"Kurudih",
    "ks:ks_pop":595,
    "ks:ks_type":"VILLAGE",
    "ks:ks_uagg_main":0,
    "name:eng_x_preferred":[
        "Kurudih"
    ],
    "name:eng_x_variant":[
        "Kur\u016bd\u012bh"
    ],
    "wof:name":"Kurudih",
    "wof:placetype":"neighbourhood",
    "wof:population":595
},
  "geometry": {"coordinates":[82.71178500000001,22.124006],"type":"Point"}
}