{
  "type": "Feature",
  "properties": {
    "gn:admin1_code":"34.0",
    "gn:admin2_code":"209.0",
    "gn:asciiname":"Belbari",
    "gn:country_code":"IN",
    "gn:dem":56,
    "gn:feature_class":"P",
    "gn:feature_code":"PPL",
    "gn:name":"Belb\u0101ri",
    "gn:population":0,
    "gn:timezone":"Asia/Kolkata",
    "iso:country":"IN",
    "ks:ks_alt_nam":"Belb\u0101ri",
    "ks:ks_name":"Belbari",
    "ks:ks_pop":249,
    "ks:ks_type":"VILLAGE",
    "name:ceb_x_preferred":[
        "Belbari"
    ],
    "name:deu_x_preferred":[
        "Belbari"
    ],
    "name:eng_x_preferred":[
        "Belbari"
    ],
    "name:eng_x_variant":[
        "Belb\u0101ri"
    ],
    "name:mai_x_preferred":[
        "\u092c\u0947\u0932\u0935\u093e\u0930\u0940"
    ],
    "name:msa_x_preferred":[
        "Belbari"
    ],
    "name:nep_x_preferred":[
        "\u092c\u0947\u0932\u0935\u093e\u0930\u0940 \u0928\u0917\u0930\u092a\u093e\u0932\u093f\u0915\u093e"
    ],
    "name:pol_x_preferred":[
        "Belbari"
    ],
    "wof:name":"Belbari",
    "wof:placetype":"locality",
    "wof:population":249
},
  "geometry": {"coordinates":[87.637254,26.227029],"type":"Point"}
}