{
  "type": "Feature",
  "properties": {
    "gn:admin1_code":"7.0",
    "gn:admin2_code":"98.0",
    "gn:asciiname":"Laikuari",
    "gn:country_code":"IN",
    "gn:dem":221,
    "gn:feature_class":"P",
    "gn:feature_code":"PPL",
    "gn:name":"L\u0101iku\u0101ri",
    "gn:population":0,
    "gn:timezone":"Asia/Kolkata",
    "iso:country":"IN",
    "wof:name":"Laikuari",
    "wof:placetype":"neighbourhood"
},
  "geometry": {"coordinates":[77.28369000000001,28.50257],"type":"Point"}
}