{
  "type": "Feature",
  "properties": {
    "iso:country":"IN",
    "ks:ks_name":"Jot Awasti",
    "ks:ks_pop":130,
    "ks:ks_type":"HABITATION",
    "name:eng_x_preferred":[
        "Jot Awasti"
    ],
    "wof:name":"Jot Awasti",
    "wof:placetype":"locality",
    "wof:population":130
},
  "geometry": {"coordinates":[82.692919,26.534539],"type":"Point"}
}