{
  "type": "Feature",
  "properties": {
    "iso:country":"IN",
    "ks:ks_name":"Nalwat",
    "ks:ks_pop":34,
    "ks:ks_type":"HABITATION",
    "name:eng_x_preferred":[
        "Nalwat"
    ],
    "wof:name":"Nalwat",
    "wof:placetype":"locality",
    "wof:population":34
},
  "geometry": {"coordinates":[73.582013,18.253997],"type":"Point"}
}