{
  "type": "Feature",
  "properties": {
    "gn:admin1_code":"28",
    "gn:admin2_code":"334.0",
    "gn:asciiname":"Rajgan",
    "gn:country_code":"IN",
    "gn:dem":35,
    "gn:feature_class":"P",
    "gn:feature_code":"PPL",
    "gn:name":"R\u0101jg\u0101n",
    "gn:population":0,
    "gn:timezone":"Asia/Kolkata",
    "iso:country":"IN",
    "wof:name":"Rajgan",
    "wof:placetype":"locality"
},
  "geometry": {"coordinates":[87.8574,24.53266],"type":"Point"}
}