{
  "type": "Feature",
  "properties": {
    "iso:country":"IN",
    "ks:ks_name":"Bijaypur",
    "ks:ks_pop":769,
    "ks:ks_type":"HABITATION",
    "name:eng_x_preferred":[
        "Bijaypur"
    ],
    "wof:name":"Bijaypur",
    "wof:placetype":"locality",
    "wof:population":769
},
  "geometry": {"coordinates":[92.388789,24.306588],"type":"Point"}
}