{
  "type": "Feature",
  "properties": {
    "iso:country":"IN",
    "ks:ks_name":"Khejurdiha",
    "ks:ks_pop":117,
    "ks:ks_type":"VILLAGE",
    "ks:ks_uagg_main":0,
    "name:eng_x_preferred":[
        "Khejurdiha"
    ],
    "wof:name":"Khejurdiha",
    "wof:placetype":"neighbourhood",
    "wof:population":117
},
  "geometry": {"coordinates":[86.812038,22.29501],"type":"Point"}
}