{
  "type": "Feature",
  "properties": {
    "iso:country":"IN",
    "ks:ks_name":"Bidaramati",
    "ks:ks_pop":143,
    "ks:ks_type":"HABITATION",
    "name:eng_x_preferred":[
        "Bidaramati"
    ],
    "wof:name":"Bidaramati",
    "wof:placetype":"locality",
    "wof:population":143
},
  "geometry": {"coordinates":[75.280584,14.093168],"type":"Point"}
}