{
  "type": "Feature",
  "properties": {
    "iso:country":"IN",
    "ks:ks_name":"Mohanpur",
    "ks:ks_pop":1331,
    "ks:ks_type":"VILLAGE",
    "name:eng_x_preferred":[
        "Mohanpur"
    ],
    "wof:name":"Mohanpur",
    "wof:placetype":"locality",
    "wof:population":1331
},
  "geometry": {"coordinates":[86.803758,24.031152],"type":"Point"}
}