{
  "type": "Feature",
  "properties": {
    "gn:admin1_code":"25.0",
    "gn:admin2_code":"616.0",
    "gn:asciiname":"Melakkudikkadu",
    "gn:country_code":"IN",
    "gn:dem":25,
    "gn:feature_class":"P",
    "gn:feature_code":"PPL",
    "gn:name":"Melakkudikk\u0101du",
    "gn:population":0,
    "gn:timezone":"Asia/Kolkata",
    "iso:country":"IN",
    "wof:name":"Melakkudikkadu",
    "wof:placetype":"neighbourhood"
},
  "geometry": {"coordinates":[79.40326,11.08132],"type":"Point"}
}