{
  "type": "Feature",
  "properties": {
    "iso:country":"IN",
    "ks:ks_name":"Dagewadi Fata",
    "ks:ks_pop":58,
    "ks:ks_type":"HABITATION",
    "name:eng_x_preferred":[
        "Dagewadi Fata"
    ],
    "wof:name":"Dagewadi Fata",
    "wof:placetype":"locality",
    "wof:population":58
},
  "geometry": {"coordinates":[74.235792,19.224863],"type":"Point"}
}