{
  "type": "Feature",
  "properties": {
    "iso:country":"IN",
    "ks:ks_alt_nam":"Chenn\u0101pur",
    "ks:ks_name":"Chennapur",
    "ks:ks_type":"VILLAGE",
    "name:eng_x_preferred":[
        "Chennapur"
    ],
    "name:eng_x_variant":[
        "Chenn\u0101pur"
    ],
    "wof:name":"Chennapur",
    "wof:placetype":"locality"
},
  "geometry": {"coordinates":[75.09427100000001,14.897455],"type":"Point"}
}