{
  "type": "Feature",
  "properties": {
    "gn:admin1_code":"38.0",
    "gn:admin2_code":"351.0",
    "gn:asciiname":"Barkanali",
    "gn:country_code":"IN",
    "gn:dem":91,
    "gn:feature_class":"P",
    "gn:feature_code":"PPL",
    "gn:name":"B\u0101rk\u0101n\u0101li",
    "gn:population":0,
    "gn:timezone":"Asia/Kolkata",
    "iso:country":"IN",
    "ks:ks_name":"Barkandali",
    "ks:ks_pop":232,
    "ks:ks_type":"VILLAGE",
    "name:eng_x_preferred":[
        "Barkandali"
    ],
    "name:eng_x_variant":[
        "Barkanali"
    ],
    "wof:name":"Barkandali",
    "wof:placetype":"locality",
    "wof:population":232
},
  "geometry": {"coordinates":[87.382544,25.072841],"type":"Point"}
}