{
  "type": "Feature",
  "properties": {
    "iso:country":"IN",
    "ks:ks_name":"Banagawa",
    "ks:ks_pop":750,
    "ks:ks_type":"VILLAGE",
    "name:eng_x_preferred":[
        "Banagawa"
    ],
    "wof:name":"Banagawa",
    "wof:placetype":"locality",
    "wof:population":750
},
  "geometry": {"coordinates":[82.921584,27.3285],"type":"Point"}
}