{
  "type": "Feature",
  "properties": {
    "gn:admin1_code":"39.0",
    "gn:admin2_code":"63.0",
    "gn:asciiname":"Selta",
    "gn:country_code":"IN",
    "gn:dem":983,
    "gn:feature_class":"P",
    "gn:feature_code":"PPL",
    "gn:name":"Selta",
    "gn:population":0,
    "gn:timezone":"Asia/Kolkata",
    "iso:country":"IN",
    "ks:ks_name":"Selta",
    "ks:ks_type":"VILLAGE",
    "name:eng_x_preferred":[
        "Selta"
    ],
    "wof:name":"Selta",
    "wof:placetype":"locality"
},
  "geometry": {"coordinates":[79.72343100000001,29.868775],"type":"Point"}
}