{
  "type": "Feature",
  "properties": {
    "gn:admin1_code":"2.0",
    "gn:admin2_code":"552.0",
    "gn:asciiname":"Parla",
    "gn:country_code":"IN",
    "gn:dem":315,
    "gn:feature_class":"P",
    "gn:feature_code":"PPL",
    "gn:name":"Parla",
    "gn:population":0,
    "gn:timezone":"Asia/Kolkata",
    "iso:country":"IN",
    "name:ara_x_preferred":[
        "\u0628\u0627\u0631\u0644\u0627"
    ],
    "name:ast_x_preferred":[
        "Parla"
    ],
    "name:azb_x_preferred":[
        "\u067e\u0627\u0631\u0644\u0627"
    ],
    "name:bul_x_preferred":[
        "\u041f\u0430\u0440\u043b\u0430"
    ],
    "name:cat_x_preferred":[
        "Parla"
    ],
    "name:ceb_x_preferred":[
        "Parla"
    ],
    "name:deu_x_preferred":[
        "Parla"
    ],
    "name:diq_x_preferred":[
        "Parla"
    ],
    "name:epo_x_preferred":[
        "Parla"
    ],
    "name:eus_x_preferred":[
        "Parla"
    ],
    "name:fas_x_preferred":[
        "\u067e\u0627\u0631\u0644\u0627"
    ],
    "name:fra_x_preferred":[
        "Parla"
    ],
    "name:glg_x_preferred":[
        "Parla"
    ],
    "name:hun_x_preferred":[
        "Parla"
    ],
    "name:hye_x_preferred":[
        "\u054a\u0561\u0580\u056c\u0561"
    ],
    "name:ita_x_preferred":[
        "Parla"
    ],
    "name:jpn_x_preferred":[
        "\u30d1\u30eb\u30e9"
    ],
    "name:kor_x_preferred":[
        "\ud30c\ub97c\ub77c"
    ],
    "name:lat_x_preferred":[
        "Parla"
    ],
    "name:ltz_x_preferred":[
        "Parla"
    ],
    "name:mlg_x_preferred":[
        "Parla"
    ],
    "name:msa_x_preferred":[
        "Parla"
    ],
    "name:nld_x_preferred":[
        "Parla"
    ],
    "name:nno_x_preferred":[
        "Parla"
    ],
    "name:oci_x_preferred":[
        "Parla"
    ],
    "name:pol_x_preferred":[
        "Parla"
    ],
    "name:por_x_preferred":[
        "Parla"
    ],
    "name:rus_x_preferred":[
        "\u041f\u0430\u0440\u043b\u0430"
    ],
    "name:sco_x_preferred":[
        "Parla"
    ],
    "name:spa_x_preferred":[
        "Parla"
    ],
    "name:sqi_x_preferred":[
        "Parla"
    ],
    "name:srp_x_preferred":[
        "\u041f\u0430\u0440\u043b\u0430"
    ],
    "name:swe_x_preferred":[
        "Parla"
    ],
    "name:tat_x_preferred":[
        "\u041f\u0430\u0440\u043b\u0430"
    ],
    "name:tur_x_preferred":[
        "Parla"
    ],
    "name:ukr_x_preferred":[
        "\u041f\u0430\u0440\u043b\u0430"
    ],
    "name:vie_x_preferred":[
        "Parla"
    ],
    "name:war_x_preferred":[
        "Parla"
    ],
    "name:zho_x_preferred":[
        "\u5e15\u5c14\u62c9"
    ],
    "wof:name":"Parla",
    "wof:placetype":"locality"
},
  "geometry": {"coordinates":[77.90769,15.77731],"type":"Point"}
}