{
  "type": "Feature",
  "properties": {
    "iso:country":"IN",
    "ks:ks_name":"Chiran",
    "ks:ks_pop":607,
    "ks:ks_type":"VILLAGE",
    "ks:ks_uagg_main":0,
    "name:eng_x_preferred":[
        "Chiran"
    ],
    "wof:name":"Chiran",
    "wof:placetype":"neighbourhood",
    "wof:population":607
},
  "geometry": {"coordinates":[80.26681600000001,26.551288],"type":"Point"}
}