{
  "type": "Feature",
  "properties": {
    "iso:country":"IN",
    "ks:ks_name":"Maliburuda",
    "ks:ks_pop":542,
    "ks:ks_type":"VILLAGE",
    "name:eng_x_preferred":[
        "Maliburuda"
    ],
    "wof:name":"Maliburuda",
    "wof:placetype":"locality",
    "wof:population":542
},
  "geometry": {"coordinates":[82.804536,18.505483],"type":"Point"}
}