{
  "type": "Feature",
  "properties": {
    "iso:country":"IN",
    "ks:ks_alt_nam":"THEYYOTTUCHIRA",
    "ks:ks_name":"Theyyottuchira",
    "ks:ks_pop":1983,
    "ks:ks_type":"HABITATION",
    "name:eng_x_preferred":[
        "Theyyottuchira"
    ],
    "wof:name":"Theyyottuchira",
    "wof:placetype":"locality",
    "wof:population":1983
},
  "geometry": {"coordinates":[76.37723099999999,10.992038],"type":"Point"}
}