{
  "type": "Feature",
  "properties": {
    "iso:country":"IN",
    "ks:ks_name":"Dangtoli",
    "ks:ks_pop":287,
    "ks:ks_type":"VILLAGE",
    "name:eng_x_preferred":[
        "Dangtoli"
    ],
    "wof:name":"Dangtoli",
    "wof:placetype":"locality",
    "wof:population":287
},
  "geometry": {"coordinates":[79.410875,30.104689],"type":"Point"}
}