{
  "type": "Feature",
  "properties": {
    "gn:admin1_code":"36",
    "gn:admin2_code":"178.0",
    "gn:asciiname":"Gothia",
    "gn:country_code":"IN",
    "gn:dem":97,
    "gn:feature_class":"P",
    "gn:feature_code":"PPL",
    "gn:name":"Gothia",
    "gn:population":0,
    "gn:timezone":"Asia/Kolkata",
    "iso:country":"IN",
    "ks:ks_name":"Gothiya",
    "ks:ks_pop":250,
    "ks:ks_type":"HABITATION",
    "ks:ks_uagg_main":0,
    "name:deu_x_preferred":[
        "Gothia"
    ],
    "name:eng_x_preferred":[
        "Gothiya"
    ],
    "name:fin_x_preferred":[
        "Gothia"
    ],
    "name:fra_x_preferred":[
        "Gothie"
    ],
    "name:spa_x_preferred":[
        "Gotia"
    ],
    "name:swe_x_preferred":[
        "Gothia"
    ],
    "name:ukr_x_preferred":[
        "\u0413\u043e\u0442\u0456\u044f"
    ],
    "wof:name":"Gothiya",
    "wof:placetype":"neighbourhood",
    "wof:population":250
},
  "geometry": {"coordinates":[82.412953,26.374853],"type":"Point"}
}