{
  "type": "Feature",
  "properties": {
    "iso:country":"IN",
    "ks:ks_name":"Parmania Falia",
    "ks:ks_pop":590,
    "ks:ks_type":"HABITATION",
    "name:eng_x_preferred":[
        "Parmania Falia"
    ],
    "wof:name":"Parmania Falia",
    "wof:placetype":"locality",
    "wof:population":590
},
  "geometry": {"coordinates":[74.46688899999999,22.843806],"type":"Point"}
}