{
  "type": "Feature",
  "properties": {
    "gn:admin1_code":"37",
    "gn:admin2_code":"402.0",
    "gn:asciiname":"Kurdeg",
    "gn:country_code":"IN",
    "gn:dem":646,
    "gn:feature_class":"P",
    "gn:feature_code":"PPL",
    "gn:name":"Kurdeg",
    "gn:population":0,
    "gn:timezone":"Asia/Kolkata",
    "iso:country":"IN",
    "wof:name":"Kurdeg",
    "wof:placetype":"locality"
},
  "geometry": {"coordinates":[83.58261,22.90819],"type":"Point"}
}