{
  "type": "Feature",
  "properties": {
    "gn:admin1_code":"39.0",
    "gn:admin2_code":"63.0",
    "gn:asciiname":"Jogiona",
    "gn:country_code":"IN",
    "gn:dem":1155,
    "gn:feature_class":"P",
    "gn:feature_code":"PPL",
    "gn:name":"Jogiona",
    "gn:population":0,
    "gn:timezone":"Asia/Kolkata",
    "iso:country":"IN",
    "wof:name":"Jogiona",
    "wof:placetype":"locality"
},
  "geometry": {"coordinates":[79.72459000000001,29.86163],"type":"Point"}
}