{
  "type": "Feature",
  "properties": {
    "iso:country":"IN",
    "ks:ks_name":"Baripada",
    "ks:ks_pop":269,
    "ks:ks_type":"VILLAGE",
    "name:eng_x_preferred":[
        "Baripada"
    ],
    "wof:name":"Baripada",
    "wof:placetype":"locality",
    "wof:population":269
},
  "geometry": {"coordinates":[86.728658,21.190814],"type":"Point"}
}