{
  "type": "Feature",
  "properties": {
    "iso:country":"IN",
    "ks:ks_name":"Tiyara Kalan",
    "ks:ks_pop":588,
    "ks:ks_type":"HABITATION",
    "name:eng_x_preferred":[
        "Tiyara Kalan"
    ],
    "wof:name":"Tiyara Kalan",
    "wof:placetype":"locality",
    "wof:population":588
},
  "geometry": {"coordinates":[83.22683600000001,24.712081],"type":"Point"}
}