{
  "type": "Feature",
  "properties": {
    "gn:admin1_code":"35",
    "gn:admin2_code":"443.0",
    "gn:asciiname":"Barri",
    "gn:country_code":"IN",
    "gn:dem":411,
    "gn:feature_class":"P",
    "gn:feature_code":"PPL",
    "gn:name":"Barri",
    "gn:population":0,
    "gn:timezone":"Asia/Kolkata",
    "iso:country":"IN",
    "name:dan_x_preferred":[
        "Barre"
    ],
    "name:swe_x_preferred":[
        "Barr\u00f6"
    ],
    "name:zho_x_preferred":[
        "\u5df4\u91cc"
    ],
    "wof:name":"Barri",
    "wof:placetype":"locality"
},
  "geometry": {"coordinates":[77.96781,24.19853],"type":"Point"}
}