{
  "type": "Feature",
  "properties": {
    "iso:country":"IN",
    "ks:ks_name":"Raiyavan",
    "ks:ks_pop":1484,
    "ks:ks_type":"VILLAGE",
    "name:eng_x_preferred":[
        "Raiyavan"
    ],
    "wof:name":"Raiyavan",
    "wof:placetype":"locality",
    "wof:population":1484
},
  "geometry": {"coordinates":[74.099086,22.66512],"type":"Point"}
}