{
  "type": "Feature",
  "properties": {
    "gn:admin1_code":"24",
    "gn:admin2_code":"106.0",
    "gn:asciiname":"Nadanpur",
    "gn:country_code":"IN",
    "gn:dem":240,
    "gn:feature_class":"P",
    "gn:feature_code":"PPL",
    "gn:name":"N\u0101danpur",
    "gn:population":0,
    "gn:timezone":"Asia/Kolkata",
    "iso:country":"IN",
    "wof:name":"Nadanpur",
    "wof:placetype":"locality"
},
  "geometry": {"coordinates":[77.40142,26.65344],"type":"Point"}
}