{
  "type": "Feature",
  "properties": {
    "iso:country":"IN",
    "ks:ks_name":"16 SPD-A",
    "ks:ks_pop":55,
    "ks:ks_type":"VILLAGE",
    "name:eng_x_preferred":[
        "16 SPD-A"
    ],
    "wof:name":"16 SPD-A",
    "wof:placetype":"locality",
    "wof:population":55
},
  "geometry": {"coordinates":[74.15543599999999,29.344547],"type":"Point"}
}