{
  "type": "Feature",
  "properties": {
    "iso:country":"IN",
    "ks:ks_alt_nam":"Matam tanda",
    "ks:ks_name":"Matam Tanda",
    "ks:ks_pop":62,
    "ks:ks_type":"HABITATION",
    "name:eng_x_preferred":[
        "Matam Tanda"
    ],
    "wof:name":"Matam Tanda",
    "wof:placetype":"locality",
    "wof:population":62
},
  "geometry": {"coordinates":[78.432267,16.769755],"type":"Point"}
}