{
  "type": "Feature",
  "properties": {
    "iso:country":"IN",
    "ks:ks_name":"Banasagadde",
    "ks:ks_pop":24,
    "ks:ks_type":"HABITATION",
    "name:eng_x_preferred":[
        "Banasagadde"
    ],
    "wof:name":"Banasagadde",
    "wof:placetype":"locality",
    "wof:population":24
},
  "geometry": {"coordinates":[74.862866,13.949267],"type":"Point"}
}