{
  "type": "Feature",
  "properties": {
    "gn:admin1_code":"36",
    "gn:admin2_code":"160.0",
    "gn:asciiname":"Rampur Munderi Kazim Husain",
    "gn:country_code":"IN",
    "gn:dem":138,
    "gn:feature_class":"P",
    "gn:feature_code":"PPL",
    "gn:name":"R\u0101mpur Munderi K\u0101zim Husain",
    "gn:population":0,
    "gn:timezone":"Asia/Kolkata",
    "iso:country":"IN",
    "wof:name":"Rampur Munderi Kazim Husain",
    "wof:placetype":"locality"
},
  "geometry": {"coordinates":[79.94078,26.95889],"type":"Point"}
}