{
  "type": "Feature",
  "properties": {
    "gn:admin1_code":"34.0",
    "gn:admin2_code":"204.0",
    "gn:asciiname":"Patni",
    "gn:country_code":"IN",
    "gn:dem":77,
    "gn:feature_class":"P",
    "gn:feature_code":"PPL",
    "gn:name":"Patni",
    "gn:population":0,
    "gn:timezone":"Asia/Kolkata",
    "iso:country":"IN",
    "ks:ks_name":"Patni",
    "ks:ks_pop":6403,
    "ks:ks_type":"VILLAGE",
    "name:eng_x_preferred":[
        "Patni"
    ],
    "wof:name":"Patni",
    "wof:placetype":"locality",
    "wof:population":6403
},
  "geometry": {"coordinates":[84.79001599999999,26.871012],"type":"Point"}
}