{
  "type": "Feature",
  "properties": {
    "iso:country":"IN",
    "ks:ks_name":"Nakapara",
    "ks:ks_pop":242,
    "ks:ks_type":"HABITATION",
    "name:eng_x_preferred":[
        "Nakapara"
    ],
    "wof:name":"Nakapara",
    "wof:placetype":"locality",
    "wof:population":242
},
  "geometry": {"coordinates":[81.537449,18.592364],"type":"Point"}
}