{
  "type": "Feature",
  "properties": {
    "gn:admin1_code":"36",
    "gn:admin2_code":"152.0",
    "gn:asciiname":"Dakia Sobha",
    "gn:country_code":"IN",
    "gn:dem":155,
    "gn:feature_class":"P",
    "gn:feature_code":"PPL",
    "gn:name":"Dakia Sobha",
    "gn:population":0,
    "gn:timezone":"Asia/Kolkata",
    "iso:country":"IN",
    "ks:ks_name":"Dhakia Shobha",
    "ks:ks_pop":475,
    "ks:ks_type":"VILLAGE",
    "ks:ks_uagg_main":0,
    "name:eng_x_preferred":[
        "Dhakia Shobha"
    ],
    "wof:name":"Dhakia Shobha",
    "wof:placetype":"neighbourhood",
    "wof:population":475
},
  "geometry": {"coordinates":[79.793329,27.944638],"type":"Point"}
}