{
  "type": "Feature",
  "properties": {
    "iso:country":"IN",
    "ks:ks_name":"Gotadwadi",
    "ks:ks_pop":502,
    "ks:ks_type":"HABITATION",
    "name:eng_x_preferred":[
        "Gotadwadi"
    ],
    "wof:name":"Gotadwadi",
    "wof:placetype":"locality",
    "wof:population":502
},
  "geometry": {"coordinates":[73.39134199999999,16.898384],"type":"Point"}
}