{
  "type": "Feature",
  "properties": {
    "iso:country":"IN",
    "ks:ks_name":"Upenchowki Kuchlibari",
    "ks:ks_pop":3150,
    "ks:ks_type":"HABITATION",
    "name:eng_x_preferred":[
        "Upenchowki Kuchlibari"
    ],
    "wof:name":"Upenchowki Kuchlibari",
    "wof:placetype":"locality",
    "wof:population":3150
},
  "geometry": {"coordinates":[88.99189699999999,26.294226],"type":"Point"}
}