{
  "type": "Feature",
  "properties": {
    "gn:country":"IN",
    "gn:fcode":"PPL",
    "gn:pop":25845,
    "iso:country":"IN",
    "name:bpy_x_preferred":[
        "\u0995\u09a8\u09cd\u09a6\u09b2\u09be"
    ],
    "name:deu_x_preferred":[
        "Kandla"
    ],
    "name:eng_x_preferred":[
        "Kandla"
    ],
    "name:fra_x_preferred":[
        "Kandla"
    ],
    "name:guj_x_preferred":[
        "\u0a95\u0a82\u0aa1\u0ab2\u0abe \u0aac\u0a82\u0aa6\u0ab0"
    ],
    "name:hin_x_preferred":[
        "\u0915\u0902\u0921\u0932\u093e"
    ],
    "name:ita_x_preferred":[
        "Kandla"
    ],
    "name:mal_x_preferred":[
        "\u0d15\u0d23\u0d4d\u0d1f\u0d4d \u0d32"
    ],
    "name:mar_x_preferred":[
        "\u0915\u0902\u0921\u0932\u093e"
    ],
    "name:msa_x_preferred":[
        "Kandla"
    ],
    "name:nan_x_preferred":[
        "Kandla"
    ],
    "name:new_x_preferred":[
        "\u0915\u0928\u094d\u0926\u094d\u0932\u093e"
    ],
    "name:nld_x_preferred":[
        "Kandla"
    ],
    "name:nob_x_preferred":[
        "Kandla"
    ],
    "name:ori_x_preferred":[
        "\u0b15\u0b23\u0b4d\u0b21\u0b32\u0b3e"
    ],
    "name:pam_x_preferred":[
        "Kandla"
    ],
    "name:pan_x_preferred":[
        "\u0a15\u0a3e\u0a02\u0a21\u0a32\u0a3e"
    ],
    "name:ron_x_preferred":[
        "Kandla"
    ],
    "name:rus_x_preferred":[
        "\u041a\u0430\u043d\u0434\u043b\u0430"
    ],
    "name:swe_x_preferred":[
        "K\u0101ndla"
    ],
    "name:tam_x_preferred":[
        "kandla port"
    ],
    "name:unk_x_variant":[
        "Kundla"
    ],
    "name:vie_x_preferred":[
        "Kandla"
    ],
    "name:zho_x_preferred":[
        "\u5eb7\u5fb7\u62c9"
    ],
    "qs:name":"K\u0101ndla",
    "qs:photos_9r":0,
    "qs:photos_sr":0,
    "qs:pop_sr":"7",
    "wof:name":"K\u0101ndla",
    "wof:placetype":"locality",
    "wof:population":25845
},
  "geometry": {"coordinates":[70.21666999999999,23.03333],"type":"Point"}
}