{
  "type": "Feature",
  "properties": {
    "gn:admin1_code":"11",
    "gn:admin2_code":"23.0",
    "gn:asciiname":"Surai",
    "gn:country_code":"IN",
    "gn:dem":2047,
    "gn:feature_class":"P",
    "gn:feature_code":"PPL",
    "gn:name":"Surai",
    "gn:population":0,
    "gn:timezone":"Asia/Kolkata",
    "iso:country":"IN",
    "wof:name":"Surai",
    "wof:placetype":"locality"
},
  "geometry": {"coordinates":[76.68439000000002,32.27359000000001],"type":"Point"}
}