{
  "type": "Feature",
  "properties": {
    "iso:country":"IN",
    "ks:ks_name":"Semarwari",
    "ks:ks_pop":2299,
    "ks:ks_type":"HABITATION",
    "ks:ks_uagg_main":0,
    "name:eng_x_preferred":[
        "Semarwari"
    ],
    "wof:name":"Semarwari",
    "wof:placetype":"neighbourhood",
    "wof:population":2299
},
  "geometry": {"coordinates":[84.040015,27.045073],"type":"Point"}
}