{
  "type": "Feature",
  "properties": {
    "gn:admin1_code":"36",
    "gn:admin2_code":"191.0",
    "gn:asciiname":"Bibipur",
    "gn:country_code":"IN",
    "gn:dem":85,
    "gn:feature_class":"P",
    "gn:feature_code":"PPL",
    "gn:name":"Bibipur",
    "gn:population":0,
    "gn:timezone":"Asia/Kolkata",
    "iso:country":"IN",
    "name:und_x_variant":[
        "Kam\u0101lpur"
    ],
    "wof:name":"Bibipur",
    "wof:placetype":"locality"
},
  "geometry": {"coordinates":[82.90024,25.99692000000001],"type":"Point"}
}