{
  "type": "Feature",
  "properties": {
    "iso:country":"IN",
    "ks:ks_name":"Badapur",
    "ks:ks_pop":326,
    "ks:ks_type":"VILLAGE",
    "ks:ks_uagg_main":0,
    "name:eng_x_preferred":[
        "Badapur"
    ],
    "wof:name":"Badapur",
    "wof:placetype":"locality",
    "wof:population":326
},
  "geometry": {"coordinates":[84.885587,19.303519],"type":"Point"}
}