{
  "type": "Feature",
  "properties": {
    "gn:admin1_code":"38.0",
    "gn:admin2_code":"352.0",
    "gn:asciiname":"Tegra",
    "gn:country_code":"IN",
    "gn:dem":97,
    "gn:feature_class":"P",
    "gn:feature_code":"PPL",
    "gn:name":"Tegra",
    "gn:population":0,
    "gn:timezone":"Asia/Kolkata",
    "iso:country":"IN",
    "name:ara_x_preferred":[
        "\u062a\u064a\u062c\u0631\u0627"
    ],
    "name:bul_x_preferred":[
        "\u0422\u0435\u0433\u0440\u0430"
    ],
    "name:ces_x_preferred":[
        "Nvidia Tegra"
    ],
    "name:deu_x_preferred":[
        "Nvidia Tegra"
    ],
    "name:est_x_preferred":[
        "Nvidia Tegra"
    ],
    "name:fas_x_preferred":[
        "\u062a\u06af\u0631\u0627"
    ],
    "name:fin_x_preferred":[
        "Tegra"
    ],
    "name:fra_x_preferred":[
        "Tegra"
    ],
    "name:heb_x_preferred":[
        "\u05d8\u05d2\u05e8\u05d4"
    ],
    "name:hun_x_preferred":[
        "Tegra"
    ],
    "name:ita_x_preferred":[
        "Tegra"
    ],
    "name:jpn_x_preferred":[
        "NVIDIA Tegra"
    ],
    "name:kor_x_preferred":[
        "\uc5d4\ube44\ub514\uc544 \ud14c\uadf8\ub77c"
    ],
    "name:nld_x_preferred":[
        "Tegra"
    ],
    "name:nor_x_preferred":[
        "Tegra"
    ],
    "name:pol_x_preferred":[
        "Nvidia Tegra"
    ],
    "name:por_x_preferred":[
        "Nvidia Tegra"
    ],
    "name:rus_x_preferred":[
        "Tegra"
    ],
    "name:slk_x_preferred":[
        "Nvidia Tegra"
    ],
    "name:spa_x_preferred":[
        "Tegra"
    ],
    "name:tur_x_preferred":[
        "Tegra"
    ],
    "name:ukr_x_preferred":[
        "Nvidia Tegra"
    ],
    "wof:name":"Tegra",
    "wof:placetype":"locality"
},
  "geometry": {"coordinates":[87.69085,24.74933],"type":"Point"}
}