{
  "type": "Feature",
  "properties": {
    "gn:admin1_code":"38.0",
    "gn:admin2_code":"352.0",
    "gn:asciiname":"Tegra",
    "gn:country_code":"IN",
    "gn:dem":97,
    "gn:feature_class":"P",
    "gn:feature_code":"PPL",
    "gn:name":"Tegra",
    "gn:population":0,
    "gn:timezone":"Asia/Kolkata",
    "iso:country":"IN",
    "wof:name":"Tegra",
    "wof:placetype":"locality"
},
  "geometry": {"coordinates":[87.69085,24.74933],"type":"Point"}
}