{
  "type": "Feature",
  "properties": {
    "gn:admin1_code":"12.0",
    "gn:asciiname":"Rumail",
    "gn:country_code":"IN",
    "gn:dem":343,
    "gn:feature_class":"P",
    "gn:feature_code":"PPL",
    "gn:name":"Rum\u0101il",
    "gn:population":0,
    "gn:timezone":"Asia/Kolkata",
    "iso:country":"IN",
    "name:und_x_variant":[
        "Rum\u0101il",
        "Rum\u0101li"
    ],
    "wof:name":"Rumail",
    "wof:placetype":"locality"
},
  "geometry": {"coordinates":[74.47915999999999,32.87036],"type":"Point"}
}