{
  "type": "Feature",
  "properties": {
    "iso:country":"IN",
    "ks:ks_name":"Tolakadiha",
    "ks:ks_pop":60,
    "ks:ks_type":"VILLAGE",
    "name:eng_x_preferred":[
        "Tolakadiha"
    ],
    "wof:name":"Tolakadiha",
    "wof:placetype":"locality",
    "wof:population":60
},
  "geometry": {"coordinates":[87.06013799999999,21.618002],"type":"Point"}
}