{
  "type": "Feature",
  "properties": {
    "iso:country":"IN",
    "ks:ks_name":"Udaibhanpura",
    "ks:ks_pop":293,
    "ks:ks_type":"VILLAGE",
    "ks:ks_uagg_main":0,
    "name:eng_x_preferred":[
        "Udaibhanpura"
    ],
    "wof:name":"Udaibhanpura",
    "wof:placetype":"neighbourhood",
    "wof:population":293
},
  "geometry": {"coordinates":[74.432607,24.100883],"type":"Point"}
}