{
  "type": "Feature",
  "properties": {
    "gn:country":"IN",
    "gn:fcode":"PPL",
    "gn:population":0,
    "iso:country":"IN",
    "name:ara_x_preferred":[
        "\u062f\u062e\u0627\u0643\u0646\u0627 \u0628\u0648\u0631\u0648\u0627"
    ],
    "name:ben_bn_x_preferred":[
        "\u09a2\u09be\u0995\u09a8\u09be \u09aa\u09c1\u09b0\u0993\u09af\u09bc\u09be"
    ],
    "name:ben_in_x_preferred":[
        "\u09a2\u09be\u0995\u09a8\u09be \u09aa\u09c1\u09b0\u0993\u09af\u09bc\u09be"
    ],
    "name:guj_x_preferred":[
        "\u0aa7\u0a95\u0aa8 \u0aaa\u0ac2\u0ab0\u0acd\u0ab5\u0abe"
    ],
    "name:hin_x_preferred":[
        "\u0922\u093e\u0915\u0928\u093e \u092a\u0941\u0930\u094d\u0935\u093e"
    ],
    "name:kan_x_preferred":[
        "\u0ca7\u0c95\u0ccd\u0ca8\u0cbe \u0caa\u0cc2\u0cb0\u0ccd\u0cb5"
    ],
    "name:mal_x_preferred":[
        "\u0d27\u0d15\u0d4d\u0d28 \u0d2a\u0d42\u0d7c\u0d35"
    ],
    "name:mar_x_preferred":[
        "\u0922\u093e\u0915\u0928\u093e \u092a\u0941\u0930\u0935\u093e"
    ],
    "name:pan_x_preferred":[
        "\u0a22\u0a15\u0a28\u0a3e \u0a2a\u0a41\u0a30\u0a35\u0a3e"
    ],
    "name:tam_x_preferred":[
        "\u0ba4\u0bbe\u0b95\u0bcd\u0ba9\u0bbe \u0baa\u0bc2\u0bb0\u0bcd\u0bb5\u0bbe"
    ],
    "name:tel_x_preferred":[
        "\u0c22\u0c3e\u0c15\u0c4d\u0c28\u0c3e \u0c2a\u0c42\u0c30\u0c4d\u0c35\u0c3e"
    ],
    "name:urd_x_preferred":[
        "\u0688\u06be\u06a9\u0646\u0627 \u067e\u0648\u0631\u0648\u0627"
    ],
    "qs:name":"Dhakna Purwa",
    "qs:name_adm0":"India",
    "qs:name_adm1":"Uttar Pradesh",
    "qs:photos":2,
    "qs:photos_1k":1,
    "qs:photos_9k":1,
    "qs:photos_9r":1,
    "qs:photos_all":2,
    "qs:photos_sr":1,
    "qs:placetype":"Suburb",
    "qs:pop_sr":"0",
    "wof:name":"Dhakna Purwa",
    "wof:placetype":"neighbourhood",
    "wof:population":0
},
  "geometry": {"coordinates":[79.60853,26.93773],"type":"Point"}
}