{
  "type": "Feature",
  "properties": {
    "iso:country":"IN",
    "ks:ks_name":"Kandaguda",
    "ks:ks_pop":309,
    "ks:ks_type":"VILLAGE",
    "name:eng_x_preferred":[
        "Kandaguda"
    ],
    "wof:name":"Kandaguda",
    "wof:placetype":"locality",
    "wof:population":309
},
  "geometry": {"coordinates":[82.225042,18.507861],"type":"Point"}
}