{
  "type": "Feature",
  "properties": {
    "iso:country":"IN",
    "ks:ks_name":"Maduvanjarai",
    "ks:ks_pop":66,
    "ks:ks_type":"HABITATION",
    "name:eng_x_preferred":[
        "Maduvanjarai"
    ],
    "wof:name":"Maduvanjarai",
    "wof:placetype":"locality",
    "wof:population":66
},
  "geometry": {"coordinates":[78.588792,11.354539],"type":"Point"}
}