{
  "type": "Feature",
  "properties": {
    "iso:country":"IN",
    "ks:ks_alt_nam":"Jajayanthinagar koppalu",
    "ks:ks_name":"Jajayanthinagar Koppalu",
    "ks:ks_pop":158,
    "ks:ks_type":"HABITATION",
    "name:eng_x_preferred":[
        "Jajayanthinagar Koppalu"
    ],
    "wof:name":"Jajayanthinagar Koppalu",
    "wof:placetype":"locality",
    "wof:population":158
},
  "geometry": {"coordinates":[75.92399899999999,12.867838],"type":"Point"}
}