{
  "type": "Feature",
  "properties": {
    "gn:admin1_code":"35",
    "gn:admin2_code":"421.0",
    "gn:asciiname":"Gotpura",
    "gn:country_code":"IN",
    "gn:dem":325,
    "gn:feature_class":"P",
    "gn:feature_code":"PPL",
    "gn:name":"Gotpura",
    "gn:population":0,
    "gn:timezone":"Asia/Kolkata",
    "iso:country":"IN",
    "wof:name":"Gotpura",
    "wof:placetype":"locality"
},
  "geometry": {"coordinates":[77.89785999999999,26.21957],"type":"Point"}
}