{
  "type": "Feature",
  "properties": {
    "gn:admin1_code":"21",
    "gn:admin2_code":"398.0",
    "gn:asciiname":"Pangavalasa",
    "gn:country_code":"IN",
    "gn:dem":1039,
    "gn:feature_class":"P",
    "gn:feature_code":"PPL",
    "gn:name":"Pangavalasa",
    "gn:population":0,
    "gn:timezone":"Asia/Kolkata",
    "iso:country":"IN",
    "wof:name":"Pangavalasa",
    "wof:placetype":"locality"
},
  "geometry": {"coordinates":[82.97440999999998,18.48516],"type":"Point"}
}