{
  "type": "Feature",
  "properties": {
    "iso:country":"IN",
    "ks:ks_name":"Thimmalapura",
    "ks:ks_pop":196,
    "ks:ks_type":"VILLAGE",
    "name:eng_x_preferred":[
        "Thimmalapura"
    ],
    "wof:name":"Thimmalapura",
    "wof:placetype":"locality",
    "wof:population":196
},
  "geometry": {"coordinates":[76.452663,13.101199],"type":"Point"}
}