{
  "type": "Feature",
  "properties": {
    "iso:country":"IN",
    "ks:ks_name":"Hosamane",
    "ks:ks_pop":88,
    "ks:ks_type":"HABITATION",
    "name:eng_x_preferred":[
        "Hosamane"
    ],
    "wof:name":"Hosamane",
    "wof:placetype":"locality",
    "wof:population":88
},
  "geometry": {"coordinates":[74.814734,14.764689],"type":"Point"}
}