{
  "type": "Feature",
  "properties": {
    "gn:admin1_code":"34.0",
    "gn:admin2_code":"220.0",
    "gn:asciiname":"Bhalui",
    "gn:country_code":"IN",
    "gn:dem":55,
    "gn:feature_class":"P",
    "gn:feature_code":"PPL",
    "gn:name":"Bhalui",
    "gn:population":0,
    "gn:timezone":"Asia/Kolkata",
    "iso:country":"IN",
    "ks:ks_name":"Bhalui",
    "ks:ks_pop":895,
    "ks:ks_type":"VILLAGE",
    "name:eng_x_preferred":[
        "Bhalui"
    ],
    "wof:name":"Bhalui",
    "wof:placetype":"locality",
    "wof:population":895
},
  "geometry": {"coordinates":[85.34754700000001,25.730449],"type":"Point"}
}