{
  "type": "Feature",
  "properties": {
    "iso:country":"IN",
    "ks:ks_alt_nam":"TAMKHADI",
    "ks:ks_name":"Tamkhadi",
    "ks:ks_pop":126,
    "ks:ks_type":"HABITATION",
    "name:eng_x_preferred":[
        "Tamkhadi"
    ],
    "wof:name":"Tamkhadi",
    "wof:placetype":"locality",
    "wof:population":126
},
  "geometry": {"coordinates":[74.661565,17.245788],"type":"Point"}
}