{
  "type": "Feature",
  "properties": {
    "iso:country":"IN",
    "ks:ks_name":"Brahman Tola",
    "ks:ks_pop":107,
    "ks:ks_type":"HABITATION",
    "name:eng_x_preferred":[
        "Brahman Tola"
    ],
    "wof:name":"Brahman Tola",
    "wof:placetype":"locality",
    "wof:population":107
},
  "geometry": {"coordinates":[86.623279,25.130547],"type":"Point"}
}