{
  "type": "Feature",
  "properties": {
    "gn:admin1_code":"35",
    "gn:admin2_code":"452.0",
    "gn:asciiname":"Mehka",
    "gn:country_code":"IN",
    "gn:dem":346,
    "gn:feature_class":"P",
    "gn:feature_code":"PPL",
    "gn:name":"Mehka",
    "gn:population":0,
    "gn:timezone":"Asia/Kolkata",
    "iso:country":"IN",
    "ks:ks_name":"Mehka",
    "ks:ks_pop":374,
    "ks:ks_type":"VILLAGE",
    "name:eng_x_preferred":[
        "Mehka"
    ],
    "wof:name":"Mehka",
    "wof:placetype":"locality",
    "wof:population":374
},
  "geometry": {"coordinates":[79.264143,23.001111],"type":"Point"}
}