{
  "type": "Feature",
  "properties": {
    "iso:country":"IN",
    "ks:ks_name":"Giduguvaripalem",
    "ks:ks_pop":221,
    "ks:ks_type":"HABITATION",
    "name:eng_x_preferred":[
        "Giduguvaripalem"
    ],
    "wof:name":"Giduguvaripalem",
    "wof:placetype":"locality",
    "wof:population":221
},
  "geometry": {"coordinates":[81.89124099999999,16.427781],"type":"Point"}
}