{
  "type": "Feature",
  "properties": {
    "iso:country":"IN",
    "ks:ks_name":"Badena",
    "ks:ks_pop":516,
    "ks:ks_type":"VILLAGE",
    "name:eng_x_preferred":[
        "Badena"
    ],
    "wof:name":"Badena",
    "wof:placetype":"locality",
    "wof:population":516
},
  "geometry": {"coordinates":[80.02872000000001,29.574236],"type":"Point"}
}