{
  "type": "Feature",
  "properties": {
    "iso:country":"IN",
    "ks:ks_name":"Gogariyawala",
    "ks:ks_pop":1701,
    "ks:ks_type":"VILLAGE",
    "name:eng_x_preferred":[
        "Gogariyawala"
    ],
    "wof:name":"Gogariyawala",
    "wof:placetype":"locality",
    "wof:population":1701
},
  "geometry": {"coordinates":[72.31455200000001,27.813019],"type":"Point"}
}