{
  "type": "Feature",
  "properties": {
    "iso:country":"IN",
    "ks:ks_name":"Chokkalingapuram",
    "ks:ks_pop":245,
    "ks:ks_type":"HABITATION",
    "name:eng_x_preferred":[
        "Chokkalingapuram"
    ],
    "wof:name":"Chokkalingapuram",
    "wof:placetype":"locality",
    "wof:population":245
},
  "geometry": {"coordinates":[77.896666,9.004248],"type":"Point"}
}