{
  "type": "Feature",
  "properties": {
    "iso:country":"IN",
    "ks:ks_name":"Halemakki",
    "ks:ks_pop":2,
    "ks:ks_type":"HABITATION",
    "name:eng_x_preferred":[
        "Halemakki"
    ],
    "wof:name":"Halemakki",
    "wof:placetype":"locality",
    "wof:population":2
},
  "geometry": {"coordinates":[74.670171,14.101391],"type":"Point"}
}