{
  "type": "Feature",
  "properties": {
    "iso:country":"IN",
    "ks:ks_name":"Sri Sangiyaji Nagar",
    "ks:ks_pop":584,
    "ks:ks_type":"HABITATION",
    "name:eng_x_preferred":[
        "Sri Sangiyaji Nagar"
    ],
    "wof:name":"Sri Sangiyaji Nagar",
    "wof:placetype":"locality",
    "wof:population":584
},
  "geometry": {"coordinates":[72.869326,26.831164],"type":"Point"}
}