{
  "type": "Feature",
  "properties": {
    "iso:country":"IN",
    "ks:ks_name":"Bargikocha",
    "ks:ks_pop":330,
    "ks:ks_type":"VILLAGE",
    "name:eng_x_preferred":[
        "Bargikocha"
    ],
    "wof:name":"Bargikocha",
    "wof:placetype":"locality",
    "wof:population":330
},
  "geometry": {"coordinates":[86.25718000000001,22.550497],"type":"Point"}
}