{
  "type": "Feature",
  "properties": {
    "gn:admin1_code":"34.0",
    "gn:admin2_code":"220.0",
    "gn:asciiname":"Garauna",
    "gn:country_code":"IN",
    "gn:dem":56,
    "gn:feature_class":"P",
    "gn:feature_code":"PPL",
    "gn:name":"Garauna",
    "gn:population":0,
    "gn:timezone":"Asia/Kolkata",
    "iso:country":"IN",
    "ks:ks_name":"Garauna",
    "ks:ks_pop":626,
    "ks:ks_type":"VILLAGE",
    "name:eng_x_preferred":[
        "Garauna"
    ],
    "wof:name":"Garauna",
    "wof:placetype":"locality",
    "wof:population":626
},
  "geometry": {"coordinates":[85.22286200000001,25.839425],"type":"Point"}
}