{
  "type": "Feature",
  "properties": {
    "gn:admin1_code":"36.0",
    "gn:admin2_code":"141.0",
    "gn:asciiname":"Dadha",
    "gn:country_code":"IN",
    "gn:dem":210,
    "gn:feature_class":"P",
    "gn:feature_code":"PPL",
    "gn:name":"D\u0101dha",
    "gn:population":0,
    "gn:timezone":"Asia/Kolkata",
    "iso:country":"IN",
    "name:ara_x_preferred":[
        "\u062f\u0627\u062f\u0647\u0627"
    ],
    "name:ben_bn_x_preferred":[
        "\u09a6\u09a7\u09be"
    ],
    "name:ben_in_x_preferred":[
        "\u09a6\u09a7\u09be"
    ],
    "name:guj_x_preferred":[
        "\u0aa6\u0abe\u0aa7\u0abe"
    ],
    "name:hin_x_preferred":[
        "\u0926\u093e\u0927\u093e"
    ],
    "name:kan_x_preferred":[
        "\u0ca6\u0cbe\u0ca7\u0cbe"
    ],
    "name:mal_x_preferred":[
        "\u0d26\u0d3e\u0d26"
    ],
    "name:mar_x_preferred":[
        "\u0926\u0927\u093e"
    ],
    "name:pan_x_preferred":[
        "\u0a26\u0a71\u0a27\u0a3e"
    ],
    "name:tam_x_preferred":[
        "\u0b9f\u0ba4\u0bbe"
    ],
    "name:tel_x_preferred":[
        "\u0c26\u0c27\u0c3e"
    ],
    "name:urd_x_preferred":[
        "\u062f\u0627\u0688\u06be\u0627"
    ],
    "wof:name":"Dadha",
    "wof:placetype":"locality"
},
  "geometry": {"coordinates":[77.57624,28.46003],"type":"Point"}
}