{
  "type": "Feature",
  "properties": {
    "gn:admin1_code":"2.0",
    "gn:admin2_code":"551.0",
    "gn:asciiname":"Nadimpalli",
    "gn:country_code":"IN",
    "gn:dem":130,
    "gn:feature_class":"P",
    "gn:feature_code":"PPL",
    "gn:name":"Nadimpalli",
    "gn:population":0,
    "gn:timezone":"Asia/Kolkata",
    "iso:country":"IN",
    "ks:ks_name":"Nadimpalli",
    "ks:ks_pop":120,
    "ks:ks_type":"HABITATION",
    "ks:ks_uagg_main":0,
    "name:eng_x_preferred":[
        "Nadimpalli"
    ],
    "wof:name":"Nadimpalli",
    "wof:placetype":"neighbourhood",
    "wof:population":120
},
  "geometry": {"coordinates":[79.336055,14.189281],"type":"Point"}
}