{
  "type": "Feature",
  "properties": {
    "gn:admin1_code":"19.0",
    "gn:admin2_code":"566.0",
    "gn:asciiname":"Makunte",
    "gn:country_code":"IN",
    "gn:dem":708,
    "gn:feature_class":"P",
    "gn:feature_code":"PPL",
    "gn:name":"M\u0101kunte",
    "gn:population":0,
    "gn:timezone":"Asia/Kolkata",
    "iso:country":"IN",
    "ks:ks_alt_nam":"M\u0101kunte",
    "ks:ks_name":"Makunte",
    "ks:ks_pop":165,
    "ks:ks_type":"VILLAGE",
    "name:eng_x_preferred":[
        "Makunte"
    ],
    "name:eng_x_variant":[
        "M\u0101kunte"
    ],
    "wof:name":"Makunte",
    "wof:placetype":"locality",
    "wof:population":165
},
  "geometry": {"coordinates":[76.175364,14.127907],"type":"Point"}
}