{
  "type": "Feature",
  "properties": {
    "iso:country":"IN",
    "ks:ks_name":"Ramupura",
    "ks:ks_pop":980,
    "ks:ks_type":"HABITATION",
    "name:eng_x_preferred":[
        "Ramupura"
    ],
    "wof:name":"Ramupura",
    "wof:placetype":"locality",
    "wof:population":980
},
  "geometry": {"coordinates":[75.88586599999999,28.92882],"type":"Point"}
}