{
  "type": "Feature",
  "properties": {
    "gn:admin1_code":"35",
    "gn:admin2_code":"426.0",
    "gn:asciiname":"Sunwani Khurd",
    "gn:country_code":"IN",
    "gn:dem":313,
    "gn:feature_class":"P",
    "gn:feature_code":"PPL",
    "gn:name":"Sunw\u0101ni Khurd",
    "gn:population":0,
    "gn:timezone":"Asia/Kolkata",
    "iso:country":"IN",
    "name:eng_x_preferred":[
        "Sunw\u0101ni Khurd"
    ],
    "wof:name":"Sunwani Khurd",
    "wof:placetype":"locality"
},
  "geometry": {"coordinates":[79.91259000000002,24.352],"type":"Point"}
}