{
  "type": "Feature",
  "properties": {
    "iso:country":"IN",
    "ks:ks_alt_nam":"tarku",
    "ks:ks_name":"Tarku",
    "ks:ks_pop":250,
    "ks:ks_type":"HABITATION",
    "name:eng_x_preferred":[
        "Tarku"
    ],
    "wof:name":"Tarku",
    "wof:placetype":"locality",
    "wof:population":250
},
  "geometry": {"coordinates":[85.241238,22.738319],"type":"Point"}
}