{
  "type": "Feature",
  "properties": {
    "iso:country":"IN",
    "ks:ks_name":"Satikatta",
    "ks:ks_pop":110,
    "ks:ks_type":"HABITATION",
    "name:eng_x_preferred":[
        "Satikatta"
    ],
    "wof:name":"Satikatta",
    "wof:placetype":"locality",
    "wof:population":110
},
  "geometry": {"coordinates":[74.844093,15.103583],"type":"Point"}
}