{
  "type": "Feature",
  "properties": {
    "gn:admin1_code":"35",
    "gn:admin2_code":"456.0",
    "gn:asciiname":"Kharitola",
    "gn:country_code":"IN",
    "gn:dem":391,
    "gn:feature_class":"P",
    "gn:feature_code":"PPL",
    "gn:name":"Kh\u0101r\u012btola",
    "gn:population":0,
    "gn:timezone":"Asia/Kolkata",
    "iso:country":"IN",
    "ks:ks_alt_nam":"Kh\u0101r\u012btola",
    "ks:ks_name":"Kharitola",
    "ks:ks_type":"VILLAGE",
    "name:eng_x_preferred":[
        "Kharitola"
    ],
    "name:eng_x_variant":[
        "Kh\u0101r\u012btola"
    ],
    "wof:name":"Kharitola",
    "wof:placetype":"locality"
},
  "geometry": {"coordinates":[79.499675,21.744453],"type":"Point"}
}