{
  "type": "Feature",
  "properties": {
    "iso:country":"IN",
    "ks:ks_name":"Konagadde",
    "ks:ks_pop":58,
    "ks:ks_type":"HABITATION",
    "name:eng_x_preferred":[
        "Konagadde"
    ],
    "wof:name":"Konagadde",
    "wof:placetype":"locality",
    "wof:population":58
},
  "geometry": {"coordinates":[74.589466,14.233929],"type":"Point"}
}