{
  "type": "Feature",
  "properties": {
    "iso:country":"IN",
    "ks:ks_name":"Kadalijharan",
    "ks:ks_pop":64,
    "ks:ks_type":"VILLAGE",
    "name:eng_x_preferred":[
        "Kadalijharan"
    ],
    "wof:name":"Kadalijharan",
    "wof:placetype":"locality",
    "wof:population":64
},
  "geometry": {"coordinates":[83.065684,20.813082],"type":"Point"}
}