{
  "type": "Feature",
  "properties": {
    "iso:country":"IN",
    "qs:name":"Cherangala",
    "qs:name_adm0":"India",
    "qs:name_adm1":"Karnataka",
    "qs:photos":49,
    "qs:photos_1k":10,
    "qs:photos_9k":1,
    "qs:photos_9r":2,
    "qs:photos_all":49,
    "qs:photos_sr":2,
    "qs:placetype":"Town",
    "qs:pop_sr":"0",
    "wof:name":"Cherangala",
    "wof:placetype":"locality"
},
  "geometry": {"coordinates":[75.491311,12.38578],"type":"Point"}
}