{
  "type": "Feature",
  "properties": {
    "gn:admin1_code":"17",
    "gn:admin2_code":"278.0",
    "gn:asciiname":"Sagolmang",
    "gn:country_code":"IN",
    "gn:dem":797,
    "gn:feature_class":"P",
    "gn:feature_code":"PPL",
    "gn:name":"Sagolmang",
    "gn:population":0,
    "gn:timezone":"Asia/Kolkata",
    "iso:country":"IN",
    "wof:name":"Sagolmang",
    "wof:placetype":"locality"
},
  "geometry": {"coordinates":[94.02424999999999,24.95736],"type":"Point"}
}