{
  "type": "Feature",
  "properties": {
    "iso:country":"IN",
    "ks:ks_alt_nam":"G\u0101li",
    "ks:ks_name":"Gali",
    "ks:ks_pop":277,
    "ks:ks_type":"VILLAGE",
    "name:eng_x_preferred":[
        "Gali"
    ],
    "name:eng_x_variant":[
        "G\u0101li"
    ],
    "wof:name":"Gali",
    "wof:placetype":"locality",
    "wof:population":277
},
  "geometry": {"coordinates":[85.32723799999999,23.844174],"type":"Point"}
}