{
  "type": "Feature",
  "properties": {
    "gn:admin1_code":"21.0",
    "gn:admin2_code":"396",
    "gn:asciiname":"Deppeguda",
    "gn:country_code":"IN",
    "gn:dem":190,
    "gn:feature_class":"P",
    "gn:feature_code":"PPL",
    "gn:name":"Deppeguda",
    "gn:population":0,
    "gn:timezone":"Asia/Kolkata",
    "iso:country":"IN",
    "name:und_x_variant":[
        "Deppegurha"
    ],
    "wof:name":"Deppeguda",
    "wof:placetype":"locality"
},
  "geometry": {"coordinates":[83.90799999999999,19.30035],"type":"Point"}
}