{
  "type": "Feature",
  "properties": {
    "iso:country":"IN",
    "ks:ks_name":"Konde Panchatan",
    "ks:ks_pop":486,
    "ks:ks_type":"HABITATION",
    "name:eng_x_preferred":[
        "Konde Panchatan"
    ],
    "wof:name":"Konde Panchatan",
    "wof:placetype":"locality",
    "wof:population":486
},
  "geometry": {"coordinates":[73.025103,18.166305],"type":"Point"}
}