{
  "type": "Feature",
  "properties": {
    "iso:country":"IN",
    "ks:ks_name":"Chhota Sarenga",
    "ks:ks_pop":288,
    "ks:ks_type":"VILLAGE",
    "ks:ks_uagg_main":0,
    "name:eng_x_preferred":[
        "Chhota Sarenga"
    ],
    "wof:name":"Chhota Sarenga",
    "wof:placetype":"neighbourhood",
    "wof:population":288
},
  "geometry": {"coordinates":[87.356048,22.763533],"type":"Point"}
}