{
  "type": "Feature",
  "properties": {
    "gn:admin1_code":"34.0",
    "gn:admin2_code":"234.0",
    "gn:asciiname":"Amri",
    "gn:country_code":"IN",
    "gn:dem":110,
    "gn:feature_class":"P",
    "gn:feature_code":"PPL",
    "gn:name":"Amri",
    "gn:population":0,
    "gn:timezone":"Asia/Kolkata",
    "iso:country":"IN",
    "ks:ks_name":"Amri",
    "ks:ks_pop":3513,
    "ks:ks_type":"VILLAGE",
    "ks:ks_uagg_main":0,
    "name:ceb_x_preferred":[
        "Amri"
    ],
    "name:deu_x_preferred":[
        "Amri"
    ],
    "name:eng_x_preferred":[
        "Amri"
    ],
    "name:fra_x_preferred":[
        "Amri"
    ],
    "name:rus_x_preferred":[
        "\u0410\u043c\u0440\u0438"
    ],
    "wof:name":"Amri",
    "wof:placetype":"neighbourhood",
    "wof:population":3513
},
  "geometry": {"coordinates":[84.076449,24.960876],"type":"Point"}
}