{
  "type": "Feature",
  "properties": {
    "iso:country":"IN",
    "ks:ks_name":"Nachitola",
    "ks:ks_pop":39,
    "ks:ks_type":"HABITATION",
    "name:eng_x_preferred":[
        "Nachitola"
    ],
    "wof:name":"Nachitola",
    "wof:placetype":"locality",
    "wof:population":39
},
  "geometry": {"coordinates":[85.398251,23.164479],"type":"Point"}
}