{
  "type": "Feature",
  "properties": {
    "gn:admin1_code":"19.0",
    "gn:admin2_code":"568.0",
    "gn:asciiname":"Adgalale",
    "gn:country_code":"IN",
    "gn:dem":593,
    "gn:feature_class":"P",
    "gn:feature_code":"PPL",
    "gn:name":"Adgalale",
    "gn:population":0,
    "gn:timezone":"Asia/Kolkata",
    "iso:country":"IN",
    "ks:ks_name":"Adagalale",
    "ks:ks_pop":182,
    "ks:ks_type":"VILLAGE",
    "name:eng_x_preferred":[
        "Adagalale"
    ],
    "name:eng_x_variant":[
        "Adgalale"
    ],
    "wof:name":"Adagalale",
    "wof:placetype":"locality",
    "wof:population":182
},
  "geometry": {"coordinates":[74.814494,13.952704],"type":"Point"}
}