{
  "type": "Feature",
  "properties": {
    "gn:admin1_code":"36",
    "gn:admin2_code":"186.0",
    "gn:asciiname":"Pura Milan Khurd and Buzurg",
    "gn:country_code":"IN",
    "gn:dem":84,
    "gn:feature_class":"P",
    "gn:feature_code":"PPL",
    "gn:name":"Pura Mil\u0101n Khurd and Buzurg",
    "gn:population":0,
    "gn:timezone":"Asia/Kolkata",
    "iso:country":"IN",
    "wof:name":"Pura Milan Khurd and Buzurg",
    "wof:placetype":"neighbourhood"
},
  "geometry": {"coordinates":[82.94687999999999,26.92814],"type":"Point"}
}