{
  "type": "Feature",
  "properties": {
    "iso:country":"IN",
    "ks:ks_name":"Kulakaraiyadiyoor",
    "ks:ks_pop":160,
    "ks:ks_type":"HABITATION",
    "name:eng_x_preferred":[
        "Kulakaraiyadiyoor"
    ],
    "wof:name":"Kulakaraiyadiyoor",
    "wof:placetype":"locality",
    "wof:population":160
},
  "geometry": {"coordinates":[78.043166,8.655445],"type":"Point"}
}