{
  "type": "Feature",
  "properties": {
    "iso:country":"IN",
    "ks:ks_alt_nam":"PWD Kattoor Bazar Start",
    "ks:ks_name":"Pwd Kattoor Bazar Start",
    "ks:ks_pop":304,
    "ks:ks_type":"HABITATION",
    "name:eng_x_preferred":[
        "Pwd Kattoor Bazar Start"
    ],
    "wof:name":"Pwd Kattoor Bazar Start",
    "wof:placetype":"locality",
    "wof:population":304
},
  "geometry": {"coordinates":[76.15183399999999,10.37888],"type":"Point"}
}