{
  "type": "Feature",
  "properties": {
    "iso:country":"IN",
    "ks:ks_name":"Kanganipatty",
    "ks:ks_pop":148,
    "ks:ks_type":"HABITATION",
    "name:eng_x_preferred":[
        "Kanganipatty"
    ],
    "wof:name":"Kanganipatty",
    "wof:placetype":"locality",
    "wof:population":148
},
  "geometry": {"coordinates":[78.52251200000001,11.151363],"type":"Point"}
}