{
  "type": "Feature",
  "properties": {
    "iso:country":"IN",
    "ks:ks_name":"Tola Paharpur",
    "ks:ks_pop":194,
    "ks:ks_type":"VILLAGE",
    "name:eng_x_preferred":[
        "Tola Paharpur"
    ],
    "wof:name":"Tola Paharpur",
    "wof:placetype":"locality",
    "wof:population":194
},
  "geometry": {"coordinates":[86.828362,24.684472],"type":"Point"}
}