{
  "type": "Feature",
  "properties": {
    "gn:admin1_code":"36.0",
    "gn:admin2_code":"172.0",
    "gn:asciiname":"Kulharia",
    "gn:country_code":"IN",
    "gn:dem":114,
    "gn:feature_class":"P",
    "gn:feature_code":"PPL",
    "gn:name":"Kulharia",
    "gn:population":0,
    "gn:timezone":"Asia/Kolkata",
    "iso:country":"IN",
    "name:hif_x_preferred":[
        "Kulharia"
    ],
    "wof:name":"Kulharia",
    "wof:placetype":"locality"
},
  "geometry": {"coordinates":[81.07174000000001,25.8492],"type":"Point"}
}