{
  "type": "Feature",
  "properties": {
    "iso:country":"IN",
    "ks:ks_name":"Jamdoipada",
    "ks:ks_pop":462,
    "ks:ks_type":"HABITATION",
    "name:eng_x_preferred":[
        "Jamdoipada"
    ],
    "wof:name":"Jamdoipada",
    "wof:placetype":"locality",
    "wof:population":462
},
  "geometry": {"coordinates":[74.063963,21.767835],"type":"Point"}
}