{
  "type": "Feature",
  "properties": {
    "iso:country":"IN",
    "ks:ks_name":"Haripur Aht.",
    "ks:ks_pop":13,
    "ks:ks_type":"VILLAGE",
    "name:eng_x_preferred":[
        "Haripur Aht."
    ],
    "wof:name":"Haripur Aht.",
    "wof:placetype":"locality",
    "wof:population":13
},
  "geometry": {"coordinates":[80.701115,26.086577],"type":"Point"}
}