{
  "type": "Feature",
  "properties": {
    "iso:country":"IN",
    "ks:ks_name":"Madaiya",
    "ks:ks_pop":432,
    "ks:ks_type":"HABITATION",
    "name:eng_x_preferred":[
        "Madaiya"
    ],
    "wof:name":"Madaiya",
    "wof:placetype":"locality",
    "wof:population":432
},
  "geometry": {"coordinates":[79.611386,26.749395],"type":"Point"}
}