{
  "type": "Feature",
  "properties": {
    "iso:country":"IN",
    "ks:ks_name":"Pandra Urf Devipur",
    "ks:ks_pop":108,
    "ks:ks_type":"VILLAGE",
    "name:eng_x_preferred":[
        "Pandra Urf Devipur"
    ],
    "wof:name":"Pandra Urf Devipur",
    "wof:placetype":"locality",
    "wof:population":108
},
  "geometry": {"coordinates":[79.937634,28.514349],"type":"Point"}
}