{
  "type": "Feature",
  "properties": {
    "gn:admin1_code":"13.0",
    "gn:admin2_code":"601.0",
    "gn:asciiname":"Arandanam",
    "gn:country_code":"IN",
    "gn:dem":95,
    "gn:feature_class":"P",
    "gn:feature_code":"PPL",
    "gn:name":"\u0100r\u0101nd\u0101nam",
    "gn:population":0,
    "gn:timezone":"Asia/Kolkata",
    "iso:country":"IN",
    "ks:ks_name":"Aranthanam",
    "ks:ks_pop":5432,
    "ks:ks_type":"HABITATION",
    "name:eng_x_preferred":[
        "Aranthanam"
    ],
    "name:eng_x_variant":[
        "Arandanam"
    ],
    "wof:name":"Aranthanam",
    "wof:placetype":"locality",
    "wof:population":5432
},
  "geometry": {"coordinates":[76.89995500000001,8.731218],"type":"Point"}
}