{
  "type": "Feature",
  "properties": {
    "gn:admin1_code":"16.0",
    "gn:admin2_code":"530",
    "gn:asciiname":"Kasba Tarle",
    "gn:country_code":"IN",
    "gn:dem":577,
    "gn:feature_class":"P",
    "gn:feature_code":"PPL",
    "gn:name":"Kasba T\u0101rle",
    "gn:population":0,
    "gn:timezone":"Asia/Kolkata",
    "iso:country":"IN",
    "name:und_x_variant":[
        "Tarla Buzurg",
        "T\u0101rla",
        "Kasba T\u0101rle"
    ],
    "wof:name":"Kasba Tarle",
    "wof:placetype":"locality"
},
  "geometry": {"coordinates":[74.02169000000001,16.44841],"type":"Point"}
}