{
  "type": "Feature",
  "properties": {
    "iso:country":"IN",
    "ks:ks_name":"Pawara",
    "ks:ks_pop":628,
    "ks:ks_type":"HABITATION",
    "name:eng_x_preferred":[
        "Pawara"
    ],
    "wof:name":"Pawara",
    "wof:placetype":"locality",
    "wof:population":628
},
  "geometry": {"coordinates":[81.440738,25.46229],"type":"Point"}
}