{
  "type": "Feature",
  "properties": {
    "gn:admin1_code":"19.0",
    "gn:admin2_code":"563.0",
    "gn:asciiname":"Kandvalli",
    "gn:country_code":"IN",
    "gn:dem":20,
    "gn:feature_class":"P",
    "gn:feature_code":"PPL",
    "gn:name":"Kandvalli",
    "gn:population":0,
    "gn:timezone":"Asia/Kolkata",
    "iso:country":"IN",
    "ks:ks_name":"Kandavalli",
    "ks:ks_pop":105,
    "ks:ks_type":"HABITATION",
    "name:eng_x_preferred":[
        "Kandavalli"
    ],
    "name:eng_x_variant":[
        "Kandvalli"
    ],
    "wof:name":"Kandavalli",
    "wof:placetype":"locality",
    "wof:population":105
},
  "geometry": {"coordinates":[74.526285,14.437842],"type":"Point"}
}