{
  "type": "Feature",
  "properties": {
    "gn:admin1_code":"11.0",
    "gn:admin2_code":"26.0",
    "gn:asciiname":"Dhar",
    "gn:country_code":"IN",
    "gn:dem":2156,
    "gn:feature_class":"P",
    "gn:feature_code":"PPL",
    "gn:name":"Dh\u0101r",
    "gn:population":0,
    "gn:timezone":"Asia/Kolkata",
    "iso:country":"IN",
    "wof:name":"Dhar",
    "wof:placetype":"locality"
},
  "geometry": {"coordinates":[77.46704,31.47267],"type":"Point"}
}