{
  "type": "Feature",
  "properties": {
    "iso:country":"IN",
    "ks:ks_alt_nam":"Madhwa kalan",
    "ks:ks_name":"Madhwa Kalan",
    "ks:ks_pop":105,
    "ks:ks_type":"HABITATION",
    "name:eng_x_preferred":[
        "Madhwa Kalan"
    ],
    "wof:name":"Madhwa Kalan",
    "wof:placetype":"locality",
    "wof:population":105
},
  "geometry": {"coordinates":[81.785428,24.75902],"type":"Point"}
}