{
  "type": "Feature",
  "properties": {
    "iso:country":"IN",
    "ks:ks_name":"Sidabari",
    "ks:ks_pop":428,
    "ks:ks_type":"VILLAGE",
    "name:eng_x_preferred":[
        "Sidabari"
    ],
    "wof:name":"Sidabari",
    "wof:placetype":"locality",
    "wof:population":428
},
  "geometry": {"coordinates":[88.627257,26.730948],"type":"Point"}
}