{
  "type": "Feature",
  "properties": {
    "iso:country":"IN",
    "ks:ks_name":"Adipuducheri",
    "ks:ks_pop":567,
    "ks:ks_type":"VILLAGE",
    "name:eng_x_preferred":[
        "Adipuducheri"
    ],
    "wof:name":"Adipuducheri",
    "wof:placetype":"locality",
    "wof:population":567
},
  "geometry": {"coordinates":[79.680415,10.780509],"type":"Point"}
}