{
  "type": "Feature",
  "properties": {
    "gn:admin1_code":"29.0",
    "gn:admin2_code":"241",
    "gn:asciiname":"Donkung",
    "gn:country_code":"IN",
    "gn:dem":4867,
    "gn:feature_class":"P",
    "gn:feature_code":"PPL",
    "gn:name":"Donkung",
    "gn:population":0,
    "gn:timezone":"Asia/Kolkata",
    "iso:country":"IN",
    "name:und_x_variant":[
        "Dokung",
        "Dongthung",
        "Donkung"
    ],
    "wof:name":"Donkung",
    "wof:placetype":"locality"
},
  "geometry": {"coordinates":[88.60176,28.03533],"type":"Point"}
}