{
  "type": "Feature",
  "properties": {
    "gn:admin1_code":"36.0",
    "gn:admin2_code":"183.0",
    "gn:asciiname":"Baghai",
    "gn:country_code":"IN",
    "gn:dem":116,
    "gn:feature_class":"P",
    "gn:feature_code":"PPL",
    "gn:name":"Baghai",
    "gn:population":0,
    "gn:timezone":"Asia/Kolkata",
    "iso:country":"IN",
    "name:ara_x_preferred":[
        "\u0628\u063a\u0627\u064a"
    ],
    "name:azb_x_preferred":[
        "\u0628\u063a\u0627\u06cc"
    ],
    "name:fas_x_preferred":[
        "\u0628\u063a\u0627\u06cc"
    ],
    "name:fra_x_preferred":[
        "Bagha\u00ef"
    ],
    "name:ita_x_preferred":[
        "Bagha\u00ef"
    ],
    "name:msa_x_preferred":[
        "Baghai"
    ],
    "name:por_x_preferred":[
        "Baghai"
    ],
    "name:ron_x_preferred":[
        "Bagha\u00ef"
    ],
    "name:spa_x_preferred":[
        "Bagha\u00ef"
    ],
    "name:vie_x_preferred":[
        "Baghai"
    ],
    "wof:name":"Baghai",
    "wof:placetype":"neighbourhood"
},
  "geometry": {"coordinates":[81.93509,27.36564],"type":"Point"}
}