{
  "type": "Feature",
  "properties": {
    "iso:country":"IN",
    "ks:ks_name":"Sri Ramdeo Nagar Sirmandi",
    "ks:ks_pop":515,
    "ks:ks_type":"HABITATION",
    "name:eng_x_preferred":[
        "Sri Ramdeo Nagar Sirmandi"
    ],
    "wof:name":"Sri Ramdeo Nagar Sirmandi",
    "wof:placetype":"locality",
    "wof:population":515
},
  "geometry": {"coordinates":[72.86327199999999,26.798528],"type":"Point"}
}