{
  "type": "Feature",
  "properties": {
    "iso:country":"IN",
    "ks:ks_name":"Godauli Khas",
    "ks:ks_pop":760,
    "ks:ks_type":"VILLAGE",
    "ks:ks_uagg_main":0,
    "name:eng_x_preferred":[
        "Godauli Khas"
    ],
    "wof:name":"Godauli Khas",
    "wof:placetype":"neighbourhood",
    "wof:population":760
},
  "geometry": {"coordinates":[84.204021,25.981804],"type":"Point"}
}