{
  "type": "Feature",
  "properties": {
    "gn:admin1_code":"36",
    "gn:admin2_code":"186.0",
    "gn:asciiname":"Midrapar",
    "gn:country_code":"IN",
    "gn:dem":85,
    "gn:feature_class":"P",
    "gn:feature_code":"PPL",
    "gn:name":"Midr\u0101p\u0101r",
    "gn:population":0,
    "gn:timezone":"Asia/Kolkata",
    "iso:country":"IN",
    "ks:ks_alt_nam":"Midr\u0101p\u0101r",
    "ks:ks_name":"Midrapar",
    "ks:ks_type":"VILLAGE",
    "ks:ks_uagg_main":0,
    "name:eng_x_preferred":[
        "Midrapar"
    ],
    "name:eng_x_variant":[
        "Midr\u0101p\u0101r"
    ],
    "wof:name":"Midrapar",
    "wof:placetype":"neighbourhood"
},
  "geometry": {"coordinates":[83.085988,26.9109],"type":"Point"}
}