{
  "type": "Feature",
  "properties": {
    "iso:country":"IN",
    "ks:ks_name":"Kujkuria",
    "ks:ks_pop":520,
    "ks:ks_type":"VILLAGE",
    "name:eng_x_preferred":[
        "Kujkuria"
    ],
    "wof:name":"Kujkuria",
    "wof:placetype":"locality",
    "wof:population":520
},
  "geometry": {"coordinates":[86.95647200000001,23.607303],"type":"Point"}
}