{
  "type": "Feature",
  "properties": {
    "gn:admin1_code":"19.0",
    "gn:admin2_code":"564.0",
    "gn:asciiname":"Kalavihalli",
    "gn:country_code":"IN",
    "gn:dem":619,
    "gn:feature_class":"P",
    "gn:feature_code":"PPL",
    "gn:name":"K\u0101lavihalli",
    "gn:population":0,
    "gn:timezone":"Asia/Kolkata",
    "iso:country":"IN",
    "wof:name":"Kalavihalli",
    "wof:placetype":"locality"
},
  "geometry": {"coordinates":[75.37439999999999,14.44782],"type":"Point"}
}