{
  "type": "Feature",
  "properties": {
    "gn:admin1_code":"36",
    "gn:admin2_code":"175.0",
    "gn:asciiname":"Badanpur",
    "gn:country_code":"IN",
    "gn:dem":96,
    "gn:feature_class":"P",
    "gn:feature_code":"PPL",
    "gn:name":"Badanpur",
    "gn:population":0,
    "gn:timezone":"Asia/Kolkata",
    "iso:country":"IN",
    "ks:ks_name":"Baranpur",
    "ks:ks_pop":843,
    "ks:ks_type":"VILLAGE",
    "name:eng_x_preferred":[
        "Baranpur"
    ],
    "name:eng_x_variant":[
        "Badanpur"
    ],
    "wof:name":"Baranpur",
    "wof:placetype":"locality",
    "wof:population":843
},
  "geometry": {"coordinates":[82.056167,25.448896],"type":"Point"}
}