{
  "type": "Feature",
  "properties": {
    "gn:admin1_code":"2.0",
    "gn:admin2_code":"549.0",
    "gn:asciiname":"Parikondapadu Agraharam",
    "gn:country_code":"IN",
    "gn:dem":22,
    "gn:feature_class":"P",
    "gn:feature_code":"PPL",
    "gn:name":"Parikondap\u0101du Agrah\u0101ram",
    "gn:population":0,
    "gn:timezone":"Asia/Kolkata",
    "iso:country":"IN",
    "wof:name":"Parikondapadu Agraharam",
    "wof:placetype":"neighbourhood"
},
  "geometry": {"coordinates":[79.86358,15.13055],"type":"Point"}
}