{
  "type": "Feature",
  "properties": {
    "gn:admin1_code":"35",
    "gn:admin2_code":"439.0",
    "gn:asciiname":"Simrol",
    "gn:country_code":"IN",
    "gn:dem":584,
    "gn:feature_class":"P",
    "gn:feature_code":"PPL",
    "gn:name":"Simrol",
    "gn:population":0,
    "gn:timezone":"Asia/Kolkata",
    "iso:country":"IN",
    "wof:name":"Simrol",
    "wof:placetype":"locality"
},
  "geometry": {"coordinates":[75.91112,22.53871],"type":"Point"}
}