{
  "type": "Feature",
  "properties": {
    "iso:country":"IN",
    "ks:ks_name":"Kairam",
    "ks:ks_pop":559,
    "ks:ks_type":"VILLAGE",
    "name:eng_x_preferred":[
        "Kairam"
    ],
    "wof:name":"Kairam",
    "wof:placetype":"locality",
    "wof:population":559
},
  "geometry": {"coordinates":[85.28998799999999,22.509466],"type":"Point"}
}