{
  "type": "Feature",
  "properties": {
    "iso:country":"IN",
    "ks:ks_name":"Kallavi",
    "ks:ks_pop":113,
    "ks:ks_type":"VILLAGE",
    "name:eng_x_preferred":[
        "Kallavi"
    ],
    "wof:name":"Kallavi",
    "wof:placetype":"locality",
    "wof:population":113
},
  "geometry": {"coordinates":[77.138535,19.356186],"type":"Point"}
}