{
  "type": "Feature",
  "properties": {
    "gn:admin1_code":"12.0",
    "gn:admin2_code":"15.0",
    "gn:asciiname":"Mohu",
    "gn:country_code":"IN",
    "gn:dem":2410,
    "gn:feature_class":"P",
    "gn:feature_code":"PPL",
    "gn:name":"Mohu",
    "gn:population":0,
    "gn:timezone":"Asia/Kolkata",
    "iso:country":"IN",
    "wof:name":"Mohu",
    "wof:placetype":"locality"
},
  "geometry": {"coordinates":[75.08555,33.46707],"type":"Point"}
}