{
  "type": "Feature",
  "properties": {
    "iso:country":"IN",
    "ks:ks_name":"Pondyachamal",
    "ks:ks_pop":150,
    "ks:ks_type":"HABITATION",
    "name:eng_x_preferred":[
        "Pondyachamal"
    ],
    "wof:name":"Pondyachamal",
    "wof:placetype":"locality",
    "wof:population":150
},
  "geometry": {"coordinates":[73.487976,20.203117],"type":"Point"}
}