{
  "type": "Feature",
  "properties": {
    "iso:country":"IN",
    "ks:ks_name":"Dubepur",
    "ks:ks_type":"VILLAGE",
    "name:eng_x_preferred":[
        "Dubepur"
    ],
    "wof:name":"Dubepur",
    "wof:placetype":"locality"
},
  "geometry": {"coordinates":[83.494732,25.297121],"type":"Point"}
}