{
  "type": "Feature",
  "properties": {
    "iso:country":"IN",
    "ks:ks_name":"Kelami",
    "ks:ks_pop":376,
    "ks:ks_type":"VILLAGE",
    "ks:ks_uagg_main":0,
    "name:eng_x_preferred":[
        "Kelami"
    ],
    "wof:name":"Kelami",
    "wof:placetype":"neighbourhood",
    "wof:population":376
},
  "geometry": {"coordinates":[87.386274,22.698437],"type":"Point"}
}