{
  "type": "Feature",
  "properties": {
    "iso:country":"IN",
    "ks:ks_name":"Jangala Palle",
    "ks:ks_pop":264,
    "ks:ks_type":"HABITATION",
    "ks:ks_uagg_main":0,
    "name:eng_x_preferred":[
        "Jangala Palle"
    ],
    "wof:name":"Jangala Palle",
    "wof:placetype":"neighbourhood",
    "wof:population":264
},
  "geometry": {"coordinates":[78.75588500000001,13.160442],"type":"Point"}
}