{
  "type": "Feature",
  "properties": {
    "iso:country":"IN",
    "ks:ks_name":"Kumburti",
    "ks:ks_pop":224,
    "ks:ks_type":"VILLAGE",
    "name:eng_x_preferred":[
        "Kumburti"
    ],
    "wof:name":"Kumburti",
    "wof:placetype":"locality",
    "wof:population":224
},
  "geometry": {"coordinates":[82.946138,18.168607],"type":"Point"}
}