{
  "type": "Feature",
  "properties": {
    "iso:country":"IN",
    "ks:ks_name":"Bahbal Chak",
    "ks:ks_pop":0,
    "ks:ks_type":"VILLAGE",
    "name:eng_x_preferred":[
        "Bahbal Chak"
    ],
    "wof:name":"Bahbal Chak",
    "wof:placetype":"locality",
    "wof:population":0
},
  "geometry": {"coordinates":[85.093709,24.914456],"type":"Point"}
}