{
  "type": "Feature",
  "properties": {
    "gn:admin1_code":"35",
    "gn:admin2_code":"443.0",
    "gn:asciiname":"Gajar",
    "gn:country_code":"IN",
    "gn:dem":421,
    "gn:feature_class":"P",
    "gn:feature_code":"PPL",
    "gn:name":"Gaj\u0101r",
    "gn:population":0,
    "gn:timezone":"Asia/Kolkata",
    "iso:country":"IN",
    "ks:ks_name":"Gajar",
    "ks:ks_pop":262,
    "ks:ks_type":"VILLAGE",
    "name:eng_x_preferred":[
        "Gajar"
    ],
    "wof:name":"Gajar",
    "wof:placetype":"locality",
    "wof:population":262
},
  "geometry": {"coordinates":[77.847089,23.6178],"type":"Point"}
}