{
  "type": "Feature",
  "properties": {
    "iso:country":"IN",
    "ks:ks_name":"Bhaiyalal Singh Ka Purwa",
    "ks:ks_pop":20,
    "ks:ks_type":"HABITATION",
    "name:eng_x_preferred":[
        "Bhaiyalal Singh Ka Purwa"
    ],
    "wof:name":"Bhaiyalal Singh Ka Purwa",
    "wof:placetype":"locality",
    "wof:population":20
},
  "geometry": {"coordinates":[81.14256399999999,25.409052],"type":"Point"}
}