{
  "type": "Feature",
  "properties": {
    "iso:country":"IN",
    "ks:ks_name":"Baigna",
    "ks:ks_pop":581,
    "ks:ks_type":"VILLAGE",
    "ks:ks_uagg_main":0,
    "name:eng_x_preferred":[
        "Baigna"
    ],
    "wof:name":"Baigna",
    "wof:placetype":"neighbourhood",
    "wof:population":581
},
  "geometry": {"coordinates":[87.590188,25.539965],"type":"Point"}
}