{
  "type": "Feature",
  "properties": {
    "iso:country":"IN",
    "ks:ks_name":"Bagwadi",
    "ks:ks_pop":208,
    "ks:ks_type":"HABITATION",
    "name:eng_x_preferred":[
        "Bagwadi"
    ],
    "wof:name":"Bagwadi",
    "wof:placetype":"locality",
    "wof:population":208
},
  "geometry": {"coordinates":[73.332353,16.942039],"type":"Point"}
}