{
  "type": "Feature",
  "properties": {
    "iso:country":"IN",
    "ks:ks_name":"Ahir Tola West",
    "ks:ks_pop":160,
    "ks:ks_type":"HABITATION",
    "name:eng_x_preferred":[
        "Ahir Tola West"
    ],
    "wof:name":"Ahir Tola West",
    "wof:placetype":"locality",
    "wof:population":160
},
  "geometry": {"coordinates":[84.4055,26.61025],"type":"Point"}
}