{
  "type": "Feature",
  "properties": {
    "iso:country":"IN",
    "ks:ks_name":"Bojyathanda",
    "ks:ks_pop":165,
    "ks:ks_type":"HABITATION",
    "ks:ks_uagg_main":0,
    "name:eng_x_preferred":[
        "Bojyathanda"
    ],
    "wof:name":"Bojyathanda",
    "wof:placetype":"neighbourhood",
    "wof:population":165
},
  "geometry": {"coordinates":[78.951819,16.950169],"type":"Point"}
}