{
  "type": "Feature",
  "properties": {
    "iso:country":"IN",
    "ks:ks_name":"Baunsapahadi",
    "ks:ks_pop":68,
    "ks:ks_type":"VILLAGE",
    "name:eng_x_preferred":[
        "Baunsapahadi"
    ],
    "wof:name":"Baunsapahadi",
    "wof:placetype":"locality",
    "wof:population":68
},
  "geometry": {"coordinates":[86.398944,22.044349],"type":"Point"}
}