{
  "type": "Feature",
  "properties": {
    "iso:country":"IN",
    "ks:ks_name":"Kanapagaru",
    "ks:ks_pop":32,
    "ks:ks_type":"VILLAGE",
    "name:eng_x_preferred":[
        "Kanapagaru"
    ],
    "wof:name":"Kanapagaru",
    "wof:placetype":"locality",
    "wof:population":32
},
  "geometry": {"coordinates":[74.731674,14.131225],"type":"Point"}
}