{
  "type": "Feature",
  "properties": {
    "iso:country":"IN",
    "ks:ks_name":"Katrikia",
    "ks:ks_pop":591,
    "ks:ks_type":"VILLAGE",
    "ks:ks_uagg_main":0,
    "name:eng_x_preferred":[
        "Katrikia"
    ],
    "wof:name":"Katrikia",
    "wof:placetype":"neighbourhood",
    "wof:population":591
},
  "geometry": {"coordinates":[83.904318,20.058975],"type":"Point"}
}