{
  "type": "Feature",
  "properties": {
    "iso:country":"IN",
    "ks:ks_name":"Joginiatanr",
    "ks:ks_pop":287,
    "ks:ks_type":"VILLAGE",
    "ks:ks_uagg_main":0,
    "name:eng_x_preferred":[
        "Joginiatanr"
    ],
    "wof:name":"Joginiatanr",
    "wof:placetype":"neighbourhood",
    "wof:population":287
},
  "geometry": {"coordinates":[86.51105699999999,24.106348],"type":"Point"}
}