{
  "type": "Feature",
  "properties": {
    "iso:country":"IN",
    "ks:ks_name":"M. Gouliwad",
    "ks:ks_pop":160,
    "ks:ks_type":"HABITATION",
    "name:eng_x_preferred":[
        "M. Gouliwad"
    ],
    "wof:name":"M. Gouliwad",
    "wof:placetype":"locality",
    "wof:population":160
},
  "geometry": {"coordinates":[74.818032,15.379723],"type":"Point"}
}