{
  "type": "Feature",
  "properties": {
    "iso:country":"IN",
    "ks:ks_alt_nam":"seroikala",
    "ks:ks_name":"Seroikala",
    "ks:ks_pop":1750,
    "ks:ks_type":"HABITATION",
    "name:eng_x_preferred":[
        "Seroikala"
    ],
    "wof:name":"Seroikala",
    "wof:placetype":"locality",
    "wof:population":1750
},
  "geometry": {"coordinates":[83.707078,23.962624],"type":"Point"}
}