{
  "type": "Feature",
  "properties": {
    "gn:admin1_code":"35",
    "gn:admin2_code":"429.0",
    "gn:asciiname":"Pallanpur",
    "gn:country_code":"IN",
    "gn:dem":335,
    "gn:feature_class":"P",
    "gn:feature_code":"PPL",
    "gn:name":"Pallanpur",
    "gn:population":0,
    "gn:timezone":"Asia/Kolkata",
    "iso:country":"IN",
    "ks:ks_name":"Palhanpur",
    "ks:ks_pop":703,
    "ks:ks_type":"VILLAGE",
    "name:eng_x_preferred":[
        "Palhanpur"
    ],
    "name:eng_x_variant":[
        "Pallanpur"
    ],
    "wof:name":"Palhanpur",
    "wof:placetype":"locality",
    "wof:population":703
},
  "geometry": {"coordinates":[80.78479,24.395231],"type":"Point"}
}