{
  "type": "Feature",
  "properties": {
    "iso:country":"IN",
    "ks:ks_name":"Purba Dubrajpur",
    "ks:ks_pop":2029,
    "ks:ks_type":"VILLAGE",
    "ks:ks_uagg_main":0,
    "name:eng_x_preferred":[
        "Purba Dubrajpur"
    ],
    "wof:name":"Purba Dubrajpur",
    "wof:placetype":"neighbourhood",
    "wof:population":2029
},
  "geometry": {"coordinates":[87.48613899999999,23.283833],"type":"Point"}
}