{
  "type": "Feature",
  "properties": {
    "iso:country":"IN",
    "ks:ks_alt_nam":"Ajwani\u0101n",
    "ks:ks_name":"Ajwanian",
    "ks:ks_type":"VILLAGE",
    "ks:ks_uagg_main":0,
    "name:eng_x_preferred":[
        "Ajwanian"
    ],
    "name:eng_x_variant":[
        "Ajwani\u0101n"
    ],
    "wof:name":"Ajwanian",
    "wof:placetype":"neighbourhood"
},
  "geometry": {"coordinates":[83.369805,26.704947],"type":"Point"}
}