{
  "type": "Feature",
  "properties": {
    "gn:admin1_code":"34.0",
    "gn:admin2_code":"219.0",
    "gn:asciiname":"Pach Patra",
    "gn:country_code":"IN",
    "gn:dem":60,
    "gn:feature_class":"P",
    "gn:feature_code":"PPL",
    "gn:name":"Pach Patra",
    "gn:population":0,
    "gn:timezone":"Asia/Kolkata",
    "iso:country":"IN",
    "ks:ks_name":"Pach Patra",
    "ks:ks_pop":890,
    "ks:ks_type":"VILLAGE",
    "ks:ks_uagg_main":0,
    "name:eng_x_preferred":[
        "Pach Patra"
    ],
    "wof:name":"Pach Patra",
    "wof:placetype":"neighbourhood",
    "wof:population":890
},
  "geometry": {"coordinates":[84.672298,25.805797],"type":"Point"}
}