{
  "type": "Feature",
  "properties": {
    "iso:country":"IN",
    "ks:ks_name":"Jhajha",
    "ks:ks_pop":231,
    "ks:ks_type":"VILLAGE",
    "name:eng_x_preferred":[
        "Jhajha"
    ],
    "wof:name":"Jhajha",
    "wof:placetype":"locality",
    "wof:population":231
},
  "geometry": {"coordinates":[86.928785,24.437693],"type":"Point"}
}