{
  "type": "Feature",
  "properties": {
    "iso:country":"IN",
    "ks:ks_name":"Bhutan Khuti",
    "ks:ks_pop":260,
    "ks:ks_type":"VILLAGE",
    "ks:ks_uagg_main":0,
    "name:eng_x_preferred":[
        "Bhutan Khuti"
    ],
    "wof:name":"Bhutan Khuti",
    "wof:placetype":"neighbourhood",
    "wof:population":260
},
  "geometry": {"coordinates":[91.37518300000001,26.769799],"type":"Point"}
}