{
  "type": "Feature",
  "properties": {
    "gn:admin1_code":"10.0",
    "gn:admin2_code":"055",
    "gn:asciiname":"Bhagwanpura",
    "gn:country_code":"IN",
    "gn:dem":353,
    "gn:feature_class":"P",
    "gn:feature_code":"PPL",
    "gn:name":"Bhagw\u0101npura",
    "gn:population":0,
    "gn:timezone":"Asia/Kolkata",
    "iso:country":"IN",
    "wof:name":"Bhagwanpura",
    "wof:placetype":"neighbourhood"
},
  "geometry": {"coordinates":[76.83159000000001,30.73626],"type":"Point"}
}