{
  "type": "Feature",
  "properties": {
    "gn:admin1_code":"10.0",
    "gn:admin2_code":"055",
    "gn:asciiname":"Bhagwanpura",
    "gn:country_code":"IN",
    "gn:dem":353,
    "gn:feature_class":"P",
    "gn:feature_code":"PPL",
    "gn:name":"Bhagw\u0101npura",
    "gn:population":0,
    "gn:timezone":"Asia/Kolkata",
    "iso:country":"IN",
    "name:ara_x_preferred":[
        "\u0628\u0627\u062c\u0641\u0627\u0646\u0628\u0648\u0631\u0627"
    ],
    "name:ben_bn_x_preferred":[
        "\u09ad\u0997\u09ac\u09be\u09a8\u09aa\u09c1\u09b0\u09be"
    ],
    "name:ben_in_x_preferred":[
        "\u09ad\u0997\u09ac\u09be\u09a8\u09aa\u09c1\u09b0\u09be"
    ],
    "name:guj_x_preferred":[
        "\u0aad\u0a97\u0ab5\u0abe\u0aa8\u0aaa\u0ac1\u0ab0\u0abe"
    ],
    "name:hin_x_preferred":[
        "\u092d\u0917\u0935\u093e\u0928\u092a\u0941\u0930\u093e"
    ],
    "name:kan_x_preferred":[
        "\u0cad\u0c97\u0cb5\u0cbe\u0ca8\u0ccd"
    ],
    "name:mal_x_preferred":[
        "\u0d2d\u0d17\u0d35\u0d3e\u0d7b\u0d2a\u0d41\u0d30"
    ],
    "name:mar_x_preferred":[
        "\u092d\u0917\u0935\u093e\u0928\u092a\u0941\u0930\u093e"
    ],
    "name:pan_x_preferred":[
        "\u0a2d\u0a17\u0a35\u0a3e\u0a28\u0a2a\u0a41\u0a30\u0a3e"
    ],
    "name:tam_x_preferred":[
        "\u0baa\u0b95\u0bb5\u0bbe\u0ba9\u0bcd\u0baa\u0bc1\u0bb0\u0bbe"
    ],
    "name:tel_x_preferred":[
        "\u0c2d\u0c17\u0c4d\u0c35\u0c3e\u0c28\u0c4d"
    ],
    "name:urd_x_preferred":[
        "\u0628\u06be\u06af\u0648\u0627\u0646 \u067e\u0648\u0631\u06c1"
    ],
    "wof:name":"Bhagwanpura",
    "wof:placetype":"neighbourhood"
},
  "geometry": {"coordinates":[76.83159000000001,30.73626],"type":"Point"}
}