{
  "type": "Feature",
  "properties": {
    "iso:country":"IN",
    "ks:ks_name":"Son Tola",
    "ks:ks_pop":834,
    "ks:ks_type":"VILLAGE",
    "name:eng_x_preferred":[
        "Son Tola"
    ],
    "wof:name":"Son Tola",
    "wof:placetype":"locality",
    "wof:population":834
},
  "geometry": {"coordinates":[81.418589,23.407692],"type":"Point"}
}