{
  "type": "Feature",
  "properties": {
    "gn:admin1_code":"37",
    "gn:admin2_code":"413.0",
    "gn:asciiname":"Ainhur",
    "gn:country_code":"IN",
    "gn:dem":337,
    "gn:feature_class":"P",
    "gn:feature_code":"PPL",
    "gn:name":"Ainh\u016br",
    "gn:population":0,
    "gn:timezone":"Asia/Kolkata",
    "iso:country":"IN",
    "ks:ks_alt_nam":"Ainh\u016br",
    "ks:ks_name":"Ainhur",
    "ks:ks_type":"VILLAGE",
    "name:eng_x_preferred":[
        "Ainhur"
    ],
    "name:eng_x_variant":[
        "Ainh\u016br"
    ],
    "wof:name":"Ainhur",
    "wof:placetype":"locality"
},
  "geometry": {"coordinates":[80.78203999999999,20.18913],"type":"Point"}
}