{
  "type": "Feature",
  "properties": {
    "gn:admin1_code":"16",
    "gn:admin2_code":"508.0",
    "gn:asciiname":"Pulkhera",
    "gn:country_code":"IN",
    "gn:dem":236,
    "gn:feature_class":"P",
    "gn:feature_code":"PPL",
    "gn:name":"Pulkhera",
    "gn:population":0,
    "gn:timezone":"Asia/Kolkata",
    "iso:country":"IN",
    "wof:name":"Pulkhera",
    "wof:placetype":"locality"
},
  "geometry": {"coordinates":[80.20673000000002,20.18163],"type":"Point"}
}