{
  "type": "Feature",
  "properties": {
    "iso:country":"IN",
    "ks:ks_name":"Cheruvypeen",
    "ks:ks_pop":2415,
    "ks:ks_type":"HABITATION",
    "name:eng_x_preferred":[
        "Cheruvypeen"
    ],
    "wof:name":"Cheruvypeen",
    "wof:placetype":"locality",
    "wof:population":2415
},
  "geometry": {"coordinates":[76.22371699999999,10.050468],"type":"Point"}
}