{
  "type": "Feature",
  "properties": {
    "iso:country":"IN",
    "ks:ks_alt_nam":"PURE JORAW LANGRA",
    "ks:ks_name":"Pure Joraw Langra",
    "ks:ks_pop":168,
    "ks:ks_type":"HABITATION",
    "name:eng_x_preferred":[
        "Pure Joraw Langra"
    ],
    "wof:name":"Pure Joraw Langra",
    "wof:placetype":"locality",
    "wof:population":168
},
  "geometry": {"coordinates":[81.4443,26.548],"type":"Point"}
}