{
  "type": "Feature",
  "properties": {
    "gn:admin1_code":"36",
    "gn:admin2_code":"188.0",
    "gn:asciiname":"Kolia",
    "gn:country_code":"IN",
    "gn:dem":80,
    "gn:feature_class":"P",
    "gn:feature_code":"PPL",
    "gn:name":"Kolia",
    "gn:population":0,
    "gn:timezone":"Asia/Kolkata",
    "iso:country":"IN",
    "ks:ks_name":"Kolia",
    "ks:ks_type":"VILLAGE",
    "ks:ks_uagg_main":1,
    "name:eng_x_preferred":[
        "Kolia"
    ],
    "name:fra_x_preferred":[
        "Kolia"
    ],
    "name:ita_x_preferred":[
        "Kolia"
    ],
    "name:msa_x_preferred":[
        "Kolia"
    ],
    "wof:name":"Kolia",
    "wof:placetype":"locality"
},
  "geometry": {"coordinates":[83.317891,26.75961],"type":"Point"}
}