{
  "type": "Feature",
  "properties": {
    "gn:admin1_code":"38.0",
    "gn:admin2_code":"351.0",
    "gn:asciiname":"Simra Kita",
    "gn:country_code":"IN",
    "gn:dem":63,
    "gn:feature_class":"P",
    "gn:feature_code":"PPL",
    "gn:name":"Simra Kita",
    "gn:population":0,
    "gn:timezone":"Asia/Kolkata",
    "iso:country":"IN",
    "ks:ks_name":"Samrakita",
    "ks:ks_pop":79,
    "ks:ks_type":"VILLAGE",
    "name:eng_x_preferred":[
        "Samrakita"
    ],
    "name:eng_x_variant":[
        "Simra Kita"
    ],
    "wof:name":"Samrakita",
    "wof:placetype":"locality",
    "wof:population":79
},
  "geometry": {"coordinates":[87.25596299999999,25.010843],"type":"Point"}
}