{
  "type": "Feature",
  "properties": {
    "gn:admin1_code":"40.0",
    "gn:admin2_code":"540",
    "gn:asciiname":"Mustial",
    "gn:country_code":"IN",
    "gn:dem":481,
    "gn:feature_class":"P",
    "gn:feature_code":"PPL",
    "gn:name":"Mustial",
    "gn:population":0,
    "gn:timezone":"Asia/Kolkata",
    "iso:country":"IN",
    "wof:name":"Mustial",
    "wof:placetype":"locality"
},
  "geometry": {"coordinates":[78.99764999999999,17.89615],"type":"Point"}
}