{
  "type": "Feature",
  "properties": {
    "gn:admin1_code":"23.0",
    "gn:admin2_code":"47.0",
    "gn:asciiname":"Baran",
    "gn:country_code":"IN",
    "gn:dem":215,
    "gn:feature_class":"P",
    "gn:feature_code":"PPL",
    "gn:name":"Baran",
    "gn:population":0,
    "gn:timezone":"Asia/Kolkata",
    "iso:country":"IN",
    "name:deu_x_preferred":[
        "Baran"
    ],
    "name:fra_x_preferred":[
        "Baran"
    ],
    "name:ita_x_preferred":[
        "Baran"
    ],
    "name:nld_x_preferred":[
        "Baran"
    ],
    "name:pol_x_preferred":[
        "Baran"
    ],
    "name:rus_x_preferred":[
        "\u0411\u0430\u0440\u0430\u043d"
    ],
    "name:slk_x_preferred":[
        "Baran"
    ],
    "name:swe_x_preferred":[
        "Baran"
    ],
    "name:ukr_x_preferred":[
        "\u0411\u0430\u0440\u0430\u043d"
    ],
    "wof:name":"Baran",
    "wof:placetype":"locality"
},
  "geometry": {"coordinates":[75.36310999999998,29.71313],"type":"Point"}
}