{
  "type": "Feature",
  "properties": {
    "gn:admin1_code":"23.0",
    "gn:admin2_code":"47.0",
    "gn:asciiname":"Baran",
    "gn:country_code":"IN",
    "gn:dem":215,
    "gn:feature_class":"P",
    "gn:feature_code":"PPL",
    "gn:name":"Baran",
    "gn:population":0,
    "gn:timezone":"Asia/Kolkata",
    "iso:country":"IN",
    "name:ara_x_preferred":[
        "\u0628\u0627\u0631\u0627\u0646"
    ],
    "name:ben_bn_x_preferred":[
        "\u09ac\u09be\u09b0\u09be\u09a8"
    ],
    "name:ben_in_x_preferred":[
        "\u09ac\u09be\u09b0\u09be\u09a8"
    ],
    "name:deu_x_preferred":[
        "Baran"
    ],
    "name:fra_x_preferred":[
        "Baran"
    ],
    "name:guj_x_preferred":[
        "\u0aac\u0ab0\u0aa3"
    ],
    "name:hin_x_preferred":[
        "\u092c\u093e\u0930\u093e\u0902"
    ],
    "name:ita_x_preferred":[
        "Baran"
    ],
    "name:kan_x_preferred":[
        "\u0cac\u0cb0\u0ca8\u0ccd"
    ],
    "name:mal_x_preferred":[
        "\u0d2c\u0d3e\u0d30\u0d7b"
    ],
    "name:mar_x_preferred":[
        "\u092c\u0930\u0928"
    ],
    "name:nld_x_preferred":[
        "Baran"
    ],
    "name:pan_x_preferred":[
        "\u0a2c\u0a3e\u0a30\u0a3e\u0a28"
    ],
    "name:pol_x_preferred":[
        "Baran"
    ],
    "name:rus_x_preferred":[
        "\u0411\u0430\u0440\u0430\u043d"
    ],
    "name:slk_x_preferred":[
        "Baran"
    ],
    "name:swe_x_preferred":[
        "Baran"
    ],
    "name:tam_x_preferred":[
        "\u0baa\u0bb0\u0ba9\u0bcd"
    ],
    "name:tel_x_preferred":[
        "\u0c2c\u0c30\u0c3e\u0c28\u0c4d"
    ],
    "name:ukr_x_preferred":[
        "\u0411\u0430\u0440\u0430\u043d"
    ],
    "name:urd_x_preferred":[
        "\u0628\u0627\u0631\u0646"
    ],
    "wof:name":"Baran",
    "wof:placetype":"locality"
},
  "geometry": {"coordinates":[75.36310999999998,29.71313],"type":"Point"}
}