{
  "type": "Feature",
  "properties": {
    "gn:admin1_code":"40",
    "gn:admin2_code":"538.0",
    "gn:asciiname":"Narsaipalli",
    "gn:country_code":"IN",
    "gn:dem":490,
    "gn:feature_class":"P",
    "gn:feature_code":"PPL",
    "gn:name":"Narsaipalli",
    "gn:population":0,
    "gn:timezone":"Asia/Kolkata",
    "iso:country":"IN",
    "wof:name":"Narsaipalli",
    "wof:placetype":"locality"
},
  "geometry": {"coordinates":[78.3244,16.39135],"type":"Point"}
}