{
  "type": "Feature",
  "properties": {
    "gn:admin1_code":"39.0",
    "gn:admin2_code":"66.0",
    "gn:asciiname":"Pata",
    "gn:country_code":"IN",
    "gn:dem":1922,
    "gn:feature_class":"P",
    "gn:feature_code":"PPL",
    "gn:name":"P\u0101ta",
    "gn:population":0,
    "gn:timezone":"Asia/Kolkata",
    "iso:country":"IN",
    "name:ceb_x_preferred":[
        "Pata"
    ],
    "name:ces_x_preferred":[
        "Pata"
    ],
    "name:epo_x_preferred":[
        "Pata"
    ],
    "name:fin_x_preferred":[
        "Pata"
    ],
    "name:fra_x_preferred":[
        "Pata"
    ],
    "name:hun_x_preferred":[
        "Pata"
    ],
    "name:ita_x_preferred":[
        "Pata"
    ],
    "name:kor_x_preferred":[
        "\ud30c\ud0c0"
    ],
    "name:por_x_preferred":[
        "Pata"
    ],
    "name:que_x_preferred":[
        "Pata"
    ],
    "name:sco_x_preferred":[
        "Pata"
    ],
    "name:spa_x_preferred":[
        "Pata"
    ],
    "name:swe_x_preferred":[
        "Pata"
    ],
    "name:war_x_preferred":[
        "Pata"
    ],
    "wof:name":"Pata",
    "wof:placetype":"neighbourhood"
},
  "geometry": {"coordinates":[79.59887999999999,29.44442],"type":"Point"}
}