{
  "type": "Feature",
  "properties": {
    "iso:country":"IN",
    "ks:ks_name":"Kachrai Mathong No-1",
    "ks:ks_pop":434,
    "ks:ks_type":"VILLAGE",
    "ks:ks_uagg_main":0,
    "name:eng_x_preferred":[
        "Kachrai Mathong No-1"
    ],
    "wof:name":"Kachrai Mathong No-1",
    "wof:placetype":"neighbourhood",
    "wof:population":434
},
  "geometry": {"coordinates":[95.714788,27.686062],"type":"Point"}
}