{
  "type": "Feature",
  "properties": {
    "iso:country":"IN",
    "ks:ks_name":"Charathe",
    "ks:ks_pop":2635,
    "ks:ks_type":"VILLAGE",
    "ks:ks_uagg_main":0,
    "name:eng_x_preferred":[
        "Charathe"
    ],
    "wof:name":"Charathe",
    "wof:placetype":"neighbourhood",
    "wof:population":2635
},
  "geometry": {"coordinates":[73.83572599999999,15.900772],"type":"Point"}
}