{
  "type": "Feature",
  "properties": {
    "iso:country":"IN",
    "ks:ks_name":"Uparmuruji",
    "ks:ks_pop":8,
    "ks:ks_type":"VILLAGE",
    "name:eng_x_preferred":[
        "Uparmuruji"
    ],
    "wof:name":"Uparmuruji",
    "wof:placetype":"locality",
    "wof:population":8
},
  "geometry": {"coordinates":[83.22324399999999,19.900425],"type":"Point"}
}