{
  "type": "Feature",
  "properties": {
    "gn:admin1_code":"12.0",
    "gn:admin2_code":"003",
    "gn:asciiname":"Chorkongma",
    "gn:country_code":"IN",
    "gn:dem":5189,
    "gn:feature_class":"P",
    "gn:feature_code":"PPL",
    "gn:name":"Chorkongma",
    "gn:population":0,
    "gn:timezone":"Asia/Kolkata",
    "iso:country":"IN",
    "name:und_x_variant":[
        "Chorkangma",
        "Chorkongma"
    ],
    "wof:name":"Chorkongma",
    "wof:placetype":"locality"
},
  "geometry": {"coordinates":[78.58207,34.08095],"type":"Point"}
}