{
  "type": "Feature",
  "properties": {
    "iso:country":"IN",
    "ks:ks_name":"Palojori",
    "ks:ks_pop":824,
    "ks:ks_type":"VILLAGE",
    "name:eng_x_preferred":[
        "Palojori"
    ],
    "wof:name":"Palojori",
    "wof:placetype":"locality",
    "wof:population":824
},
  "geometry": {"coordinates":[86.95258800000001,24.125112],"type":"Point"}
}