{
  "type": "Feature",
  "properties": {
    "iso:country":"IN",
    "ks:ks_name":"Kandhaputabandha",
    "ks:ks_pop":165,
    "ks:ks_type":"HABITATION",
    "name:eng_x_preferred":[
        "Kandhaputabandha"
    ],
    "wof:name":"Kandhaputabandha",
    "wof:placetype":"locality",
    "wof:population":165
},
  "geometry": {"coordinates":[82.968901,18.387986],"type":"Point"}
}