{
  "type": "Feature",
  "properties": {
    "iso:country":"IN",
    "ks:ks_name":"Ijoli",
    "ks:ks_pop":527,
    "ks:ks_type":"VILLAGE",
    "name:eng_x_preferred":[
        "Ijoli"
    ],
    "wof:name":"Ijoli",
    "wof:placetype":"locality",
    "wof:population":527
},
  "geometry": {"coordinates":[73.887186,16.756812],"type":"Point"}
}