{
  "type": "Feature",
  "properties": {
    "iso:country":"IN",
    "ks:ks_name":"Umberpada",
    "ks:ks_pop":50,
    "ks:ks_type":"HABITATION",
    "name:eng_x_preferred":[
        "Umberpada"
    ],
    "wof:name":"Umberpada",
    "wof:placetype":"locality",
    "wof:population":50
},
  "geometry": {"coordinates":[72.932785,19.727767],"type":"Point"}
}