{
  "type": "Feature",
  "properties": {
    "gn:admin1_code":"37",
    "gn:admin2_code":"411.0",
    "gn:asciiname":"Raja Sewaiya",
    "gn:country_code":"IN",
    "gn:dem":297,
    "gn:feature_class":"P",
    "gn:feature_code":"PPL",
    "gn:name":"R\u0101ja Sewaiya",
    "gn:population":0,
    "gn:timezone":"Asia/Kolkata",
    "iso:country":"IN",
    "wof:name":"Raja Sewaiya",
    "wof:placetype":"locality"
},
  "geometry": {"coordinates":[82.53386,21.26201],"type":"Point"}
}