{
  "type": "Feature",
  "properties": {
    "gn:admin1_code":"19.0",
    "gn:admin2_code":"563.0",
    "gn:asciiname":"Sheveguli",
    "gn:country_code":"IN",
    "gn:dem":523,
    "gn:feature_class":"P",
    "gn:feature_code":"PPL",
    "gn:name":"Sheveguli",
    "gn:population":0,
    "gn:timezone":"Asia/Kolkata",
    "iso:country":"IN",
    "wof:name":"Sheveguli",
    "wof:placetype":"locality"
},
  "geometry": {"coordinates":[74.41644000000002,14.76024],"type":"Point"}
}