{
  "type": "Feature",
  "properties": {
    "iso:country":"IN",
    "ks:ks_name":"Pavo Wasti",
    "ks:ks_pop":225,
    "ks:ks_type":"HABITATION",
    "name:eng_x_preferred":[
        "Pavo Wasti"
    ],
    "wof:name":"Pavo Wasti",
    "wof:placetype":"locality",
    "wof:population":225
},
  "geometry": {"coordinates":[74.80800000000001,18.039],"type":"Point"}
}