{
  "type": "Feature",
  "properties": {
    "iso:country":"IN",
    "ks:ks_name":"Kontikarraguda",
    "ks:ks_pop":52,
    "ks:ks_type":"HABITATION",
    "name:eng_x_preferred":[
        "Kontikarraguda"
    ],
    "wof:name":"Kontikarraguda",
    "wof:placetype":"locality",
    "wof:population":52
},
  "geometry": {"coordinates":[83.856345,18.609087],"type":"Point"}
}