{
  "type": "Feature",
  "properties": {
    "iso:country":"IN",
    "ks:ks_name":"Kuvalakkudy",
    "ks:ks_pop":950,
    "ks:ks_type":"VILLAGE",
    "name:eng_x_preferred":[
        "Kuvalakkudy"
    ],
    "wof:name":"Kuvalakkudy",
    "wof:placetype":"neighbourhood",
    "wof:population":950
},
  "geometry": {"coordinates":[78.72922199999999,10.821121],"type":"Point"}
}