{
  "type": "Feature",
  "properties": {
    "iso:country":"IN",
    "ks:ks_name":"Bangerchole",
    "ks:ks_pop":254,
    "ks:ks_type":"VILLAGE",
    "name:eng_x_preferred":[
        "Bangerchole"
    ],
    "wof:name":"Bangerchole",
    "wof:placetype":"locality",
    "wof:population":254
},
  "geometry": {"coordinates":[72.97959,19.750996],"type":"Point"}
}