{
  "type": "Feature",
  "properties": {
    "iso:country":"IN",
    "ks:ks_name":"Mangalpur",
    "ks:ks_pop":153,
    "ks:ks_type":"VILLAGE",
    "name:eng_x_preferred":[
        "Mangalpur"
    ],
    "wof:name":"Mangalpur",
    "wof:placetype":"locality",
    "wof:population":153
},
  "geometry": {"coordinates":[87.224712,21.930181],"type":"Point"}
}