{
  "type": "Feature",
  "properties": {
    "iso:country":"IN",
    "ks:ks_name":"Bhetakhol",
    "ks:ks_pop":359,
    "ks:ks_type":"HABITATION",
    "name:eng_x_preferred":[
        "Bhetakhol"
    ],
    "wof:name":"Bhetakhol",
    "wof:placetype":"locality",
    "wof:population":359
},
  "geometry": {"coordinates":[84.290829,20.509791],"type":"Point"}
}