{
  "type": "Feature",
  "properties": {
    "iso:country":"IN",
    "ks:ks_name":"Chak Jogini Daha",
    "ks:ks_pop":0,
    "ks:ks_type":"VILLAGE",
    "name:eng_x_preferred":[
        "Chak Jogini Daha"
    ],
    "wof:name":"Chak Jogini Daha",
    "wof:placetype":"locality",
    "wof:population":0
},
  "geometry": {"coordinates":[88.658978,23.443081],"type":"Point"}
}