{
  "type": "Feature",
  "properties": {
    "iso:country":"IN",
    "ks:ks_name":"Hanumegowdanapalya",
    "ks:ks_pop":242,
    "ks:ks_type":"HABITATION",
    "name:eng_x_preferred":[
        "Hanumegowdanapalya"
    ],
    "wof:name":"Hanumegowdanapalya",
    "wof:placetype":"locality",
    "wof:population":242
},
  "geometry": {"coordinates":[76.97886800000001,13.957014],"type":"Point"}
}