{
  "type": "Feature",
  "properties": {
    "gn:admin1_code":"24",
    "gn:admin2_code":"123.0",
    "gn:asciiname":"Namano",
    "gn:country_code":"IN",
    "gn:dem":543,
    "gn:feature_class":"P",
    "gn:feature_code":"PPL",
    "gn:name":"Namano",
    "gn:population":0,
    "gn:timezone":"Asia/Kolkata",
    "iso:country":"IN",
    "name:und_x_variant":[
        "Nam\u0101na",
        "Namano"
    ],
    "wof:name":"Namano",
    "wof:placetype":"locality"
},
  "geometry": {"coordinates":[73.90245999999998,24.98935],"type":"Point"}
}