{
  "type": "Feature",
  "properties": {
    "iso:country":"IN",
    "ks:ks_name":"Harindhukri",
    "ks:ks_pop":658,
    "ks:ks_type":"VILLAGE",
    "ks:ks_uagg_main":0,
    "name:eng_x_preferred":[
        "Harindhukri"
    ],
    "wof:name":"Harindhukri",
    "wof:placetype":"neighbourhood",
    "wof:population":658
},
  "geometry": {"coordinates":[86.48915599999999,22.559468],"type":"Point"}
}