{
  "type": "Feature",
  "properties": {
    "iso:country":"IN",
    "ks:ks_name":"Kumhrauwa",
    "ks:ks_pop":646,
    "ks:ks_type":"VILLAGE",
    "name:eng_x_preferred":[
        "Kumhrauwa"
    ],
    "wof:name":"Kumhrauwa",
    "wof:placetype":"locality",
    "wof:population":646
},
  "geometry": {"coordinates":[78.773959,26.568187],"type":"Point"}
}