{
  "type": "Feature",
  "properties": {
    "gn:admin1_code":"10.0",
    "gn:admin2_code":"84.0",
    "gn:asciiname":"Naga",
    "gn:country_code":"IN",
    "gn:dem":289,
    "gn:feature_class":"P",
    "gn:feature_code":"PPL",
    "gn:name":"N\u0101ga",
    "gn:population":0,
    "gn:timezone":"Asia/Kolkata",
    "iso:country":"IN",
    "name:bcl_x_preferred":[
        "Naga"
    ],
    "name:cat_x_preferred":[
        "Naga"
    ],
    "name:ceb_x_preferred":[
        "Naga"
    ],
    "name:dan_x_preferred":[
        "Naga"
    ],
    "name:deu_x_preferred":[
        "Naga"
    ],
    "name:fin_x_preferred":[
        "Naga"
    ],
    "name:fra_x_preferred":[
        "Naga"
    ],
    "name:hrv_x_preferred":[
        "Naga"
    ],
    "name:ind_x_preferred":[
        "Naga"
    ],
    "name:ita_x_preferred":[
        "Naga"
    ],
    "name:jav_x_preferred":[
        "Naga"
    ],
    "name:kor_x_preferred":[
        "\ub098\uac00"
    ],
    "name:lit_x_preferred":[
        "Naga"
    ],
    "name:msa_x_preferred":[
        "Naga"
    ],
    "name:nld_x_preferred":[
        "Naga"
    ],
    "name:pol_x_preferred":[
        "Naga"
    ],
    "name:rus_x_preferred":[
        "\u041d\u0430\u0433\u0430"
    ],
    "name:swe_x_preferred":[
        "Naga"
    ],
    "name:tgl_x_preferred":[
        "Naga"
    ],
    "name:war_x_preferred":[
        "Naga"
    ],
    "wof:name":"Naga",
    "wof:placetype":"locality"
},
  "geometry": {"coordinates":[76.26014000000001,28.08985],"type":"Point"}
}