{
  "type": "Feature",
  "properties": {
    "iso:country":"IN",
    "ks:ks_alt_nam":"Dakshin Paschim para",
    "ks:ks_name":"Dakshin Paschim Para",
    "ks:ks_pop":581,
    "ks:ks_type":"HABITATION",
    "name:eng_x_preferred":[
        "Dakshin Paschim Para"
    ],
    "wof:name":"Dakshin Paschim Para",
    "wof:placetype":"locality",
    "wof:population":581
},
  "geometry": {"coordinates":[87.944081,22.703169],"type":"Point"}
}