{
  "type": "Feature",
  "properties": {
    "gn:admin1_code":"36",
    "gn:admin2_code":"154.0",
    "gn:asciiname":"Malhiabad",
    "gn:country_code":"IN",
    "gn:dem":147,
    "gn:feature_class":"P",
    "gn:feature_code":"PPL",
    "gn:name":"Malhi\u0101b\u0101d",
    "gn:population":0,
    "gn:timezone":"Asia/Kolkata",
    "iso:country":"IN",
    "wof:name":"Malhiabad",
    "wof:placetype":"locality"
},
  "geometry": {"coordinates":[80.75664,27.69038],"type":"Point"}
}