{
  "type": "Feature",
  "properties": {
    "gn:admin1_code":"23",
    "gn:admin2_code":"52.0",
    "gn:asciiname":"Dharamgarh",
    "gn:country_code":"IN",
    "gn:dem":282,
    "gn:feature_class":"P",
    "gn:feature_code":"PPL",
    "gn:name":"Dharamgarh",
    "gn:population":0,
    "gn:timezone":"Asia/Kolkata",
    "iso:country":"IN",
    "wof:name":"Dharamgarh",
    "wof:placetype":"locality"
},
  "geometry": {"coordinates":[76.8107,30.46218],"type":"Point"}
}