{
  "type": "Feature",
  "properties": {
    "iso:country":"IN",
    "ks:ks_name":"Gutipara Pt.V",
    "ks:ks_pop":3214,
    "ks:ks_type":"VILLAGE",
    "name:eng_x_preferred":[
        "Gutipara Pt.V"
    ],
    "wof:name":"Gutipara Pt.V",
    "wof:placetype":"locality",
    "wof:population":3214
},
  "geometry": {"coordinates":[90.161357,26.162627],"type":"Point"}
}