{
  "type": "Feature",
  "properties": {
    "gn:admin1_code":"24",
    "gn:admin2_code":"105.0",
    "gn:asciiname":"Gari",
    "gn:country_code":"IN",
    "gn:dem":180,
    "gn:feature_class":"P",
    "gn:feature_code":"PPL",
    "gn:name":"Gari",
    "gn:population":0,
    "gn:timezone":"Asia/Kolkata",
    "iso:country":"IN",
    "wof:name":"Gari",
    "wof:placetype":"locality"
},
  "geometry": {"coordinates":[77.56453,27.06564],"type":"Point"}
}