{
  "type": "Feature",
  "properties": {
    "gn:admin1_code":"36.0",
    "gn:admin2_code":"163.0",
    "gn:asciiname":"Nawada Kishandatt",
    "gn:country_code":"IN",
    "gn:dem":138,
    "gn:feature_class":"P",
    "gn:feature_code":"PPL",
    "gn:name":"Naw\u0101da Kishandatt",
    "gn:population":0,
    "gn:timezone":"Asia/Kolkata",
    "iso:country":"IN",
    "wof:name":"Nawada Kishandatt",
    "wof:placetype":"neighbourhood"
},
  "geometry": {"coordinates":[79.96046,26.68301],"type":"Point"}
}