{
  "type": "Feature",
  "properties": {
    "gn:admin1_code":"28.0",
    "gn:admin2_code":"335",
    "gn:asciiname":"Andal",
    "gn:country_code":"IN",
    "gn:dem":85,
    "gn:feature_class":"P",
    "gn:feature_code":"PPL",
    "gn:name":"And\u0101l",
    "gn:population":0,
    "gn:timezone":"Asia/Kolkata",
    "iso:country":"IN",
    "ks:ks_alt_nam":"And\u0101l",
    "ks:ks_name":"Andal",
    "ks:ks_pop":5356,
    "ks:ks_type":"VILLAGE",
    "ks:ks_uagg_main":0,
    "name:eng_x_preferred":[
        "Andal"
    ],
    "name:eng_x_variant":[
        "And\u0101l"
    ],
    "name:und_x_variant":[
        "Ondal Junction",
        "And\u0101l Junction",
        "Ondal",
        "And\u0101l"
    ],
    "wof:name":"Andal",
    "wof:placetype":"locality",
    "wof:population":5356
},
  "geometry": {"coordinates":[87.19047399999999,23.582166],"type":"Point"}
}