{
  "type": "Feature",
  "properties": {
    "gn:admin1_code":"34.0",
    "gn:admin2_code":"229",
    "gn:asciiname":"Khudaganj",
    "gn:country_code":"IN",
    "gn:dem":77,
    "gn:feature_class":"P",
    "gn:feature_code":"PPL",
    "gn:name":"Khud\u0101ganj",
    "gn:population":0,
    "gn:timezone":"Asia/Kolkata",
    "iso:country":"IN",
    "wof:name":"Khudaganj",
    "wof:placetype":"locality"
},
  "geometry": {"coordinates":[85.21826999999998,25.07782000000001],"type":"Point"}
}