{
  "type": "Feature",
  "properties": {
    "gn:admin1_code":"36.0",
    "gn:admin2_code":"183.0",
    "gn:asciiname":"Kanjar Purwa",
    "gn:country_code":"IN",
    "gn:dem":107,
    "gn:feature_class":"P",
    "gn:feature_code":"PPL",
    "gn:name":"Kanjar Purwa",
    "gn:population":0,
    "gn:timezone":"Asia/Kolkata",
    "iso:country":"IN",
    "name:ara_x_preferred":[
        "\u0643\u0646\u062c\u0631 \u0628\u0648\u0631\u0648\u0627"
    ],
    "name:ben_bn_x_preferred":[
        "\u0995\u099e\u09cd\u099c\u09b0 \u09aa\u09c1\u09b0\u0993\u09af\u09bc\u09be"
    ],
    "name:ben_in_x_preferred":[
        "\u0995\u099e\u09cd\u099c\u09b0 \u09aa\u09c1\u09b0\u0993\u09af\u09bc\u09be"
    ],
    "name:guj_x_preferred":[
        "\u0a95\u0abe\u0a82\u0a9c\u0ab0 \u0aaa\u0ac1\u0ab0\u0acd\u0ab5\u0abe"
    ],
    "name:hin_x_preferred":[
        "\u0915\u0902\u091c\u0930 \u092a\u0941\u0930\u094d\u0935\u093e"
    ],
    "name:kan_x_preferred":[
        "\u0c95\u0c82\u0c9c\u0cb0\u0ccd"
    ],
    "name:mal_x_preferred":[
        "\u0d15\u0d3e\u0d1e\u0d4d\u0d1a\u0d7c \u0d2a\u0d42\u0d7c\u0d35"
    ],
    "name:mar_x_preferred":[
        "\u0915\u0902\u091c\u0930 \u092a\u0941\u0930\u0935\u093e"
    ],
    "name:pan_x_preferred":[
        "\u0a15\u0a70\u0a1c\u0a30 \u0a2a\u0a41\u0a30\u0a35\u0a3e"
    ],
    "name:tam_x_preferred":[
        "\u0b95\u0b9e\u0bcd\u0b9a\u0bb0\u0bcd \u0baa\u0bc2\u0bb0\u0bcd\u0bb5\u0bbe"
    ],
    "name:tel_x_preferred":[
        "\u0c15\u0c02\u0c1c\u0c3e\u0c30\u0c4d \u0c2a\u0c42\u0c30\u0c4d\u0c35\u0c3e"
    ],
    "name:urd_x_preferred":[
        "\u06a9\u0646\u062c\u0631\u0627 \u067e\u0648\u0631\u0648\u0627"
    ],
    "wof:name":"Kanjar Purwa",
    "wof:placetype":"neighbourhood"
},
  "geometry": {"coordinates":[81.70793999999999,27.12901],"type":"Point"}
}