{
  "type": "Feature",
  "properties": {
    "iso:country":"IN",
    "ks:ks_name":"Bramhanwadi",
    "ks:ks_pop":47,
    "ks:ks_type":"HABITATION",
    "name:eng_x_preferred":[
        "Bramhanwadi"
    ],
    "wof:name":"Bramhanwadi",
    "wof:placetype":"locality",
    "wof:population":47
},
  "geometry": {"coordinates":[73.596356,17.130419],"type":"Point"}
}