{
  "type": "Feature",
  "properties": {
    "iso:country":"IN",
    "ks:ks_name":"Khagar Khera",
    "ks:ks_pop":198,
    "ks:ks_type":"HABITATION",
    "ks:ks_uagg_main":0,
    "name:eng_x_preferred":[
        "Khagar Khera"
    ],
    "wof:name":"Khagar Khera",
    "wof:placetype":"neighbourhood",
    "wof:population":198
},
  "geometry": {"coordinates":[80.875665,26.431493],"type":"Point"}
}