{
  "type": "Feature",
  "properties": {
    "gn:admin1_code":"19.0",
    "gn:admin2_code":"560.0",
    "gn:asciiname":"Sampur",
    "gn:country_code":"IN",
    "gn:dem":607,
    "gn:feature_class":"P",
    "gn:feature_code":"PPL",
    "gn:name":"S\u0101mpur",
    "gn:population":0,
    "gn:timezone":"Asia/Kolkata",
    "iso:country":"IN",
    "wof:name":"Sampur",
    "wof:placetype":"locality"
},
  "geometry": {"coordinates":[75.91605,15.68609],"type":"Point"}
}