{
  "type": "Feature",
  "properties": {
    "iso:country":"IN",
    "ks:ks_alt_nam":"BALIAMANI",
    "ks:ks_name":"Baliamani",
    "ks:ks_pop":554,
    "ks:ks_type":"HABITATION",
    "ks:ks_uagg_main":0,
    "name:eng_x_preferred":[
        "Baliamani"
    ],
    "wof:name":"Baliamani",
    "wof:placetype":"neighbourhood",
    "wof:population":554
},
  "geometry": {"coordinates":[87.78386399999999,26.037156],"type":"Point"}
}