{
  "type": "Feature",
  "properties": {
    "iso:country":"IN",
    "ks:ks_alt_nam":"BASMATI KI DHANI",
    "ks:ks_name":"Basmati Ki Dhani",
    "ks:ks_pop":27,
    "ks:ks_type":"HABITATION",
    "name:eng_x_preferred":[
        "Basmati Ki Dhani"
    ],
    "wof:name":"Basmati Ki Dhani",
    "wof:placetype":"locality",
    "wof:population":27
},
  "geometry": {"coordinates":[74.241569,28.958192],"type":"Point"}
}