{
  "type": "Feature",
  "properties": {
    "iso:country":"IN",
    "ks:ks_alt_nam":"SANKPAL MALI SHINDE PATIL VASTI",
    "ks:ks_name":"Sankpal Mali Shinde Patil Vasti",
    "ks:ks_pop":164,
    "ks:ks_type":"HABITATION",
    "name:eng_x_preferred":[
        "Sankpal Mali Shinde Patil Vasti"
    ],
    "wof:name":"Sankpal Mali Shinde Patil Vasti",
    "wof:placetype":"locality",
    "wof:population":164
},
  "geometry": {"coordinates":[75.05547199999999,16.996096],"type":"Point"}
}