{
  "type": "Feature",
  "properties": {
    "iso:country":"IN",
    "ks:ks_name":"Melakondaiyur",
    "ks:ks_pop":2081,
    "ks:ks_type":"VILLAGE",
    "name:eng_x_preferred":[
        "Melakondaiyur"
    ],
    "wof:name":"Melakondaiyur",
    "wof:placetype":"locality",
    "wof:population":2081
},
  "geometry": {"coordinates":[80.026281,13.191605],"type":"Point"}
}