{
  "type": "Feature",
  "properties": {
    "gn:admin1_code":"34.0",
    "gn:admin2_code":"237.0",
    "gn:asciiname":"Baluatari",
    "gn:country_code":"IN",
    "gn:dem":139,
    "gn:feature_class":"P",
    "gn:feature_code":"PPL",
    "gn:name":"Balu\u0101tari",
    "gn:population":0,
    "gn:timezone":"Asia/Kolkata",
    "iso:country":"IN",
    "ks:ks_alt_nam":"BALUA TARI",
    "ks:ks_name":"Balua Tari",
    "ks:ks_pop":375,
    "ks:ks_type":"HABITATION",
    "name:eng_x_preferred":[
        "Balua Tari"
    ],
    "name:eng_x_variant":[
        "Baluatari"
    ],
    "wof:name":"Balua Tari",
    "wof:placetype":"locality",
    "wof:population":375
},
  "geometry": {"coordinates":[85.36512,24.649763],"type":"Point"}
}