{
  "type": "Feature",
  "properties": {
    "gn:admin1_code":"23.0",
    "gn:admin2_code":"53.0",
    "gn:asciiname":"Lohar Mazra",
    "gn:country_code":"IN",
    "gn:dem":247,
    "gn:feature_class":"P",
    "gn:feature_code":"PPL",
    "gn:name":"Lohar M\u0101zra",
    "gn:population":0,
    "gn:timezone":"Asia/Kolkata",
    "iso:country":"IN",
    "wof:name":"Lohar Mazra",
    "wof:placetype":"locality"
},
  "geometry": {"coordinates":[75.94773000000001,30.42406],"type":"Point"}
}