{
  "type": "Feature",
  "properties": {
    "iso:country":"IN",
    "ks:ks_name":"Haribailu",
    "ks:ks_pop":78,
    "ks:ks_type":"HABITATION",
    "name:eng_x_preferred":[
        "Haribailu"
    ],
    "wof:name":"Haribailu",
    "wof:placetype":"locality",
    "wof:population":78
},
  "geometry": {"coordinates":[74.804174,13.7291],"type":"Point"}
}