{
  "type": "Feature",
  "properties": {
    "gn:admin1_code":"36",
    "gn:admin2_code":"188.0",
    "gn:asciiname":"Ekdanga",
    "gn:country_code":"IN",
    "gn:dem":80,
    "gn:feature_class":"P",
    "gn:feature_code":"PPL",
    "gn:name":"Ekdanga",
    "gn:population":0,
    "gn:timezone":"Asia/Kolkata",
    "iso:country":"IN",
    "ks:ks_name":"Ekdanga",
    "ks:ks_type":"VILLAGE",
    "name:eng_x_preferred":[
        "Ekdanga"
    ],
    "wof:name":"Ekdanga",
    "wof:placetype":"locality"
},
  "geometry": {"coordinates":[83.32051800000001,26.740673],"type":"Point"}
}