{
  "type": "Feature",
  "properties": {
    "gn:admin1_code":"35.0",
    "gn:admin2_code":"427",
    "gn:asciiname":"Bahrol",
    "gn:country_code":"IN",
    "gn:dem":424,
    "gn:feature_class":"P",
    "gn:feature_code":"PPL",
    "gn:name":"Bahrol",
    "gn:population":0,
    "gn:timezone":"Asia/Kolkata",
    "iso:country":"IN",
    "wof:name":"Bahrol",
    "wof:placetype":"locality"
},
  "geometry": {"coordinates":[78.39837,24.1178],"type":"Point"}
}