{
  "type": "Feature",
  "properties": {
    "gn:admin1_code":"35",
    "gn:admin2_code":"443.0",
    "gn:asciiname":"Fazalpur",
    "gn:country_code":"IN",
    "gn:dem":512,
    "gn:feature_class":"P",
    "gn:feature_code":"PPL",
    "gn:name":"Fazalpur",
    "gn:population":0,
    "gn:timezone":"Asia/Kolkata",
    "iso:country":"IN",
    "name:urd_x_preferred":[
        "\u0641\u0636\u0644 \u067e\u0648\u0631"
    ],
    "wof:name":"Fazalpur",
    "wof:placetype":"locality"
},
  "geometry": {"coordinates":[77.47503,24.20961],"type":"Point"}
}