{
  "type": "Feature",
  "properties": {
    "iso:country":"IN",
    "ks:ks_name":"Manjyar Gaon",
    "ks:ks_pop":177,
    "ks:ks_type":"HABITATION",
    "name:eng_x_preferred":[
        "Manjyar Gaon"
    ],
    "wof:name":"Manjyar Gaon",
    "wof:placetype":"locality",
    "wof:population":177
},
  "geometry": {"coordinates":[78.384327,30.375486],"type":"Point"}
}