{
  "type": "Feature",
  "properties": {
    "gn:admin1_code":"36",
    "gn:admin2_code":"185.0",
    "gn:asciiname":"Bishambhar Chak",
    "gn:country_code":"IN",
    "gn:dem":93,
    "gn:feature_class":"P",
    "gn:feature_code":"PPL",
    "gn:name":"Bishambhar Chak",
    "gn:population":0,
    "gn:timezone":"Asia/Kolkata",
    "iso:country":"IN",
    "wof:name":"Bishambhar Chak",
    "wof:placetype":"locality"
},
  "geometry": {"coordinates":[82.66084000000002,26.96124],"type":"Point"}
}