{
  "type": "Feature",
  "properties": {
    "iso:country":"IN",
    "ks:ks_name":"Bojjangada",
    "ks:ks_pop":21,
    "ks:ks_type":"HABITATION",
    "name:eng_x_preferred":[
        "Bojjangada"
    ],
    "wof:name":"Bojjangada",
    "wof:placetype":"locality",
    "wof:population":21
},
  "geometry": {"coordinates":[75.843611,11.994722],"type":"Point"}
}