{
  "type": "Feature",
  "properties": {
    "iso:country":"IN",
    "ks:ks_alt_nam":"His\u0101muddinpur",
    "ks:ks_name":"Hisamuddinpur",
    "ks:ks_type":"VILLAGE",
    "ks:ks_uagg_main":0,
    "name:eng_x_preferred":[
        "Hisamuddinpur"
    ],
    "name:eng_x_variant":[
        "His\u0101muddinpur"
    ],
    "wof:name":"Hisamuddinpur",
    "wof:placetype":"neighbourhood"
},
  "geometry": {"coordinates":[82.984936,26.462202],"type":"Point"}
}