{
  "type": "Feature",
  "properties": {
    "iso:country":"IN",
    "ks:ks_name":"Purvipara",
    "ks:ks_pop":260,
    "ks:ks_type":"HABITATION",
    "name:eng_x_preferred":[
        "Purvipara"
    ],
    "wof:name":"Purvipara",
    "wof:placetype":"locality",
    "wof:population":260
},
  "geometry": {"coordinates":[83.27811699999999,23.851398],"type":"Point"}
}