{
  "type": "Feature",
  "properties": {
    "gn:admin1_code":"35",
    "gn:admin2_code":"453.0",
    "gn:asciiname":"Bargaon",
    "gn:country_code":"IN",
    "gn:dem":775,
    "gn:feature_class":"P",
    "gn:feature_code":"PPL",
    "gn:name":"Bargaon",
    "gn:population":0,
    "gn:timezone":"Asia/Kolkata",
    "iso:country":"IN",
    "wof:name":"Bargaon",
    "wof:placetype":"locality"
},
  "geometry": {"coordinates":[81.31208000000002,22.83186],"type":"Point"}
}