{
  "type": "Feature",
  "properties": {
    "iso:country":"IN",
    "ks:ks_name":"Bhudnath",
    "ks:ks_pop":130,
    "ks:ks_type":"HABITATION",
    "name:eng_x_preferred":[
        "Bhudnath"
    ],
    "wof:name":"Bhudnath",
    "wof:placetype":"locality",
    "wof:population":130
},
  "geometry": {"coordinates":[73.62609999999999,22.80515],"type":"Point"}
}