{
  "type": "Feature",
  "properties": {
    "gn:admin1_code":"24.0",
    "gn:admin2_code":"104",
    "gn:asciiname":"Khohar",
    "gn:country_code":"IN",
    "gn:dem":311,
    "gn:feature_class":"P",
    "gn:feature_code":"PPL",
    "gn:name":"Khohar",
    "gn:population":0,
    "gn:timezone":"Asia/Kolkata",
    "iso:country":"IN",
    "name:und_x_variant":[
        "Khor"
    ],
    "wof:name":"Khohar",
    "wof:placetype":"locality"
},
  "geometry": {"coordinates":[76.25603000000002,27.99357],"type":"Point"}
}