{
  "type": "Feature",
  "properties": {
    "iso:country":"IN",
    "ks:ks_name":"Kodumanai H",
    "ks:ks_pop":250,
    "ks:ks_type":"HABITATION",
    "name:eng_x_preferred":[
        "Kodumanai H"
    ],
    "wof:name":"Kodumanai H",
    "wof:placetype":"locality",
    "wof:population":250
},
  "geometry": {"coordinates":[76.80386,11.418176],"type":"Point"}
}