{
  "type": "Feature",
  "properties": {
    "iso:country":"IN",
    "ks:ks_name":"Sultanpur Ubari",
    "ks:ks_pop":0,
    "ks:ks_type":"VILLAGE",
    "name:eng_x_preferred":[
        "Sultanpur Ubari"
    ],
    "wof:name":"Sultanpur Ubari",
    "wof:placetype":"locality",
    "wof:population":0
},
  "geometry": {"coordinates":[79.48568400000001,26.165516],"type":"Point"}
}