{
  "type": "Feature",
  "properties": {
    "iso:country":"IN",
    "ks:ks_name":"Bhogalewadi",
    "ks:ks_pop":158,
    "ks:ks_type":"HABITATION",
    "name:eng_x_preferred":[
        "Bhogalewadi"
    ],
    "wof:name":"Bhogalewadi",
    "wof:placetype":"locality",
    "wof:population":158
},
  "geometry": {"coordinates":[73.7371,16.051061],"type":"Point"}
}