{
  "type": "Feature",
  "properties": {
    "iso:country":"IN",
    "ks:ks_alt_nam":"pure goyne",
    "ks:ks_name":"Pure Goyne",
    "ks:ks_pop":193,
    "ks:ks_type":"HABITATION",
    "name:eng_x_preferred":[
        "Pure Goyne"
    ],
    "wof:name":"Pure Goyne",
    "wof:placetype":"locality",
    "wof:population":193
},
  "geometry": {"coordinates":[81.3745,26.491],"type":"Point"}
}