{
  "type": "Feature",
  "properties": {
    "iso:country":"IN",
    "ks:ks_alt_nam":"Deshmukh wasti",
    "ks:ks_name":"Deshmukh Wasti",
    "ks:ks_pop":186,
    "ks:ks_type":"HABITATION",
    "name:eng_x_preferred":[
        "Deshmukh Wasti"
    ],
    "wof:name":"Deshmukh Wasti",
    "wof:placetype":"locality",
    "wof:population":186
},
  "geometry": {"coordinates":[75.643666,17.974695],"type":"Point"}
}