{
  "type": "Feature",
  "properties": {
    "iso:country":"IN",
    "ks:ks_name":"Sindiput",
    "ks:ks_pop":24,
    "ks:ks_type":"HABITATION",
    "name:eng_x_preferred":[
        "Sindiput"
    ],
    "wof:name":"Sindiput",
    "wof:placetype":"locality",
    "wof:population":24
},
  "geometry": {"coordinates":[82.621078,17.984737],"type":"Point"}
}