{
  "type": "Feature",
  "properties": {
    "iso:country":"IN",
    "ks:ks_name":"Begenagara Chamua",
    "ks:ks_pop":313,
    "ks:ks_type":"VILLAGE",
    "name:eng_x_preferred":[
        "Begenagara Chamua"
    ],
    "wof:name":"Begenagara Chamua",
    "wof:placetype":"locality",
    "wof:population":313
},
  "geometry": {"coordinates":[94.555948,27.3734],"type":"Point"}
}