{
  "type": "Feature",
  "properties": {
    "gn:admin1_code":"39.0",
    "gn:admin2_code":"64.0",
    "gn:asciiname":"Chichaun",
    "gn:country_code":"IN",
    "gn:dem":1412,
    "gn:feature_class":"P",
    "gn:feature_code":"PPL",
    "gn:name":"Chichaun",
    "gn:population":0,
    "gn:timezone":"Asia/Kolkata",
    "iso:country":"IN",
    "ks:ks_name":"Chichoan",
    "ks:ks_pop":317,
    "ks:ks_type":"VILLAGE",
    "name:eng_x_preferred":[
        "Chichoan"
    ],
    "name:eng_x_variant":[
        "Chichaun"
    ],
    "wof:name":"Chichoan",
    "wof:placetype":"locality",
    "wof:population":317
},
  "geometry": {"coordinates":[79.17263699999999,29.778047],"type":"Point"}
}