{
  "type": "Feature",
  "properties": {
    "gn:admin1_code":"35",
    "gn:admin2_code":"439.0",
    "gn:asciiname":"Bhenslai",
    "gn:country_code":"IN",
    "gn:dem":554,
    "gn:feature_class":"P",
    "gn:feature_code":"PPL",
    "gn:name":"Bhenslai",
    "gn:population":0,
    "gn:timezone":"Asia/Kolkata",
    "iso:country":"IN",
    "wof:name":"Bhenslai",
    "wof:placetype":"locality"
},
  "geometry": {"coordinates":[75.74423,22.62252],"type":"Point"}
}