{
  "type": "Feature",
  "properties": {
    "iso:country":"IN",
    "ks:ks_name":"Bacchuwa Ban Malla",
    "ks:ks_pop":464,
    "ks:ks_type":"VILLAGE",
    "name:eng_x_preferred":[
        "Bacchuwa Ban Malla"
    ],
    "wof:name":"Bacchuwa Ban Malla",
    "wof:placetype":"locality",
    "wof:population":464
},
  "geometry": {"coordinates":[79.41781899999999,29.976864],"type":"Point"}
}