{
  "type": "Feature",
  "properties": {
    "iso:country":"IN",
    "ks:ks_name":"Salia Tekara Falia",
    "ks:ks_pop":185,
    "ks:ks_type":"HABITATION",
    "name:eng_x_preferred":[
        "Salia Tekara Falia"
    ],
    "wof:name":"Salia Tekara Falia",
    "wof:placetype":"locality",
    "wof:population":185
},
  "geometry": {"coordinates":[73.81569399999999,23.374333],"type":"Point"}
}