{
  "type": "Feature",
  "properties": {
    "gn:admin1_code":"36.0",
    "gn:admin2_code":"193.0",
    "gn:asciiname":"Dewakarpur",
    "gn:country_code":"IN",
    "gn:dem":63,
    "gn:feature_class":"P",
    "gn:feature_code":"PPL",
    "gn:name":"Dew\u0101karpur",
    "gn:population":0,
    "gn:timezone":"Asia/Kolkata",
    "iso:country":"IN",
    "ks:ks_alt_nam":"Dew\u0101karpur",
    "ks:ks_name":"Dewakarpur",
    "ks:ks_type":"VILLAGE",
    "ks:ks_uagg_main":0,
    "name:eng_x_preferred":[
        "Dewakarpur"
    ],
    "name:eng_x_variant":[
        "Dew\u0101karpur"
    ],
    "wof:name":"Dewakarpur",
    "wof:placetype":"neighbourhood"
},
  "geometry": {"coordinates":[84.215114,25.910083],"type":"Point"}
}