{
  "type": "Feature",
  "properties": {
    "iso:country":"IN",
    "ks:ks_name":"Keshuripara",
    "ks:ks_pop":242,
    "ks:ks_type":"HABITATION",
    "name:eng_x_preferred":[
        "Keshuripara"
    ],
    "wof:name":"Keshuripara",
    "wof:placetype":"locality",
    "wof:population":242
},
  "geometry": {"coordinates":[82.76395100000001,23.490775],"type":"Point"}
}