{
  "type": "Feature",
  "properties": {
    "iso:country":"IN",
    "ks:ks_name":"Korllkai",
    "ks:ks_pop":153,
    "ks:ks_type":"HABITATION",
    "name:eng_x_preferred":[
        "Korllkai"
    ],
    "wof:name":"Korllkai",
    "wof:placetype":"locality",
    "wof:population":153
},
  "geometry": {"coordinates":[74.787598,14.461089],"type":"Point"}
}