{
  "type": "Feature",
  "properties": {
    "iso:country":"IN",
    "ks:ks_name":"Shivbalak Ka Dera",
    "ks:ks_pop":50,
    "ks:ks_type":"HABITATION",
    "ks:ks_uagg_main":0,
    "name:eng_x_preferred":[
        "Shivbalak Ka Dera"
    ],
    "wof:name":"Shivbalak Ka Dera",
    "wof:placetype":"neighbourhood",
    "wof:population":50
},
  "geometry": {"coordinates":[80.46422800000001,25.915682],"type":"Point"}
}