{
  "type": "Feature",
  "properties": {
    "iso:country":"IN",
    "ks:ks_name":"Gugaguda",
    "ks:ks_pop":248,
    "ks:ks_type":"HABITATION",
    "name:eng_x_preferred":[
        "Gugaguda"
    ],
    "wof:name":"Gugaguda",
    "wof:placetype":"locality",
    "wof:population":248
},
  "geometry": {"coordinates":[82.64986500000001,18.446903],"type":"Point"}
}