{
  "type": "Feature",
  "properties": {
    "gn:admin1_code":"10.0",
    "gn:admin2_code":"071",
    "gn:asciiname":"Fatehgarh",
    "gn:country_code":"IN",
    "gn:dem":264,
    "gn:feature_class":"P",
    "gn:feature_code":"PPL",
    "gn:name":"Fatehgarh",
    "gn:population":0,
    "gn:timezone":"Asia/Kolkata",
    "iso:country":"IN",
    "name:bih_x_preferred":[
        "\u092b\u0924\u0947\u0939\u0917\u0922\u093c"
    ],
    "name:bpy_x_preferred":[
        "\u09ab\u09a4\u09c7\u09b9\u0997\u09a1\u09bc"
    ],
    "name:cat_x_preferred":[
        "Fatehgarh"
    ],
    "name:ceb_x_preferred":[
        "Fatehgarh"
    ],
    "name:deu_x_preferred":[
        "Fatehgarh"
    ],
    "name:fra_x_preferred":[
        "Fatehgarh"
    ],
    "name:hin_x_preferred":[
        "\u092b\u093c\u0924\u0947\u0939\u0917\u0922\u093c"
    ],
    "name:ita_x_preferred":[
        "Fatehgarh"
    ],
    "name:mlg_x_preferred":[
        "Fatehgarh"
    ],
    "name:msa_x_preferred":[
        "Fatehgarh"
    ],
    "name:new_x_preferred":[
        "\u092b\u0924\u0947\u0939\u0917\u0922"
    ],
    "name:nld_x_preferred":[
        "Fatehgarh"
    ],
    "name:pam_x_preferred":[
        "Fatehgarh"
    ],
    "name:pol_x_preferred":[
        "Fatehgarh"
    ],
    "name:rus_x_preferred":[
        "\u0424\u0430\u0442\u0435\u0445\u0433\u0430\u0440\u0445"
    ],
    "name:san_x_preferred":[
        "\u092b\u0924\u0947\u0939\u0917\u0922"
    ],
    "name:swe_x_preferred":[
        "Fatehgarh"
    ],
    "name:urd_x_preferred":[
        "\u0641\u062a\u062d \u06af\u0691\u06be"
    ],
    "name:vie_x_preferred":[
        "Fatehgarh"
    ],
    "name:war_x_preferred":[
        "Fatehgarh"
    ],
    "name:zho_x_preferred":[
        "\u6cd5\u6cf0\u8d6b\u52a0\u5c14"
    ],
    "wof:name":"Fatehgarh",
    "wof:placetype":"locality"
},
  "geometry": {"coordinates":[77.17256999999999,29.9963],"type":"Point"}
}