{
  "type": "Feature",
  "properties": {
    "gn:admin1_code":"39.0",
    "gn:admin2_code":"061",
    "gn:asciiname":"Borikh",
    "gn:country_code":"IN",
    "gn:dem":1460,
    "gn:feature_class":"P",
    "gn:feature_code":"PPL",
    "gn:name":"Borikh",
    "gn:population":0,
    "gn:timezone":"Asia/Kolkata",
    "iso:country":"IN",
    "ks:ks_name":"Borikh",
    "ks:ks_pop":23,
    "ks:ks_type":"VILLAGE",
    "name:eng_x_preferred":[
        "Borikh"
    ],
    "wof:name":"Borikh",
    "wof:placetype":"locality",
    "wof:population":23
},
  "geometry": {"coordinates":[78.73582399999999,29.991942],"type":"Point"}
}