{
  "type": "Feature",
  "properties": {
    "gn:admin1_code":"36",
    "gn:admin2_code":"178.0",
    "gn:asciiname":"Aliganj",
    "gn:country_code":"IN",
    "gn:dem":97,
    "gn:feature_class":"P",
    "gn:feature_code":"PPL",
    "gn:name":"Al\u012bganj",
    "gn:population":0,
    "gn:timezone":"Asia/Kolkata",
    "iso:country":"IN",
    "name:bih_x_preferred":[
        "\u0905\u0932\u0940\u0917\u0902\u091c"
    ],
    "name:bpy_x_preferred":[
        "\u0986\u09b2\u09bf\u0997\u099e\u09cd\u099c"
    ],
    "name:ceb_x_preferred":[
        "Al\u012bganj"
    ],
    "name:fas_x_preferred":[
        "\u0639\u0644\u06cc\u200c\u06af\u0646\u062c"
    ],
    "name:ita_x_preferred":[
        "Aliganj"
    ],
    "name:min_x_preferred":[
        "Aliganj"
    ],
    "name:mlg_x_preferred":[
        "Aliganj"
    ],
    "name:msa_x_preferred":[
        "Aliganj"
    ],
    "name:new_x_preferred":[
        "\u0905\u0932\u093f\u0917\u091e\u094d\u091c"
    ],
    "name:nld_x_preferred":[
        "Aliganj"
    ],
    "name:pol_x_preferred":[
        "Aliganj"
    ],
    "name:por_x_preferred":[
        "Aliganj"
    ],
    "name:swe_x_preferred":[
        "Aliganj"
    ],
    "name:tam_x_preferred":[
        "\u0b85\u0bb2\u0bbf\u0b95\u0b9e\u0bcd\u0b9a\u0bcd"
    ],
    "name:urd_x_preferred":[
        "\u0639\u0644\u06cc \u06af\u0646\u062c"
    ],
    "name:vie_x_preferred":[
        "Aliganj"
    ],
    "name:zho_x_preferred":[
        "\u963f\u5229\u7518\u6770"
    ],
    "wof:name":"Aliganj",
    "wof:placetype":"locality"
},
  "geometry": {"coordinates":[82.57288,26.53897000000001],"type":"Point"}
}