{
  "type": "Feature",
  "properties": {
    "iso:country":"IN",
    "ks:ks_name":"Biramanavilai",
    "ks:ks_pop":161,
    "ks:ks_type":"HABITATION",
    "ks:ks_uagg_main":0,
    "name:eng_x_preferred":[
        "Biramanavilai"
    ],
    "wof:name":"Biramanavilai",
    "wof:placetype":"neighbourhood",
    "wof:population":161
},
  "geometry": {"coordinates":[77.960014,8.359962],"type":"Point"}
}