{
  "type": "Feature",
  "properties": {
    "iso:country":"IN",
    "ks:ks_name":"Ghotul Para",
    "ks:ks_pop":99,
    "ks:ks_type":"HABITATION",
    "name:eng_x_preferred":[
        "Ghotul Para"
    ],
    "wof:name":"Ghotul Para",
    "wof:placetype":"locality",
    "wof:population":99
},
  "geometry": {"coordinates":[81.40294299999999,19.6139],"type":"Point"}
}