{
  "type": "Feature",
  "properties": {
    "gn:admin1_code":"11",
    "gn:admin2_code":"23.0",
    "gn:asciiname":"Chilgu",
    "gn:country_code":"IN",
    "gn:dem":2458,
    "gn:feature_class":"P",
    "gn:feature_code":"PPL",
    "gn:name":"Chilgu",
    "gn:population":0,
    "gn:timezone":"Asia/Kolkata",
    "iso:country":"IN",
    "wof:name":"Chilgu",
    "wof:placetype":"locality"
},
  "geometry": {"coordinates":[76.46496999999999,32.91649],"type":"Point"}
}