{
  "type": "Feature",
  "properties": {
    "iso:country":"IN",
    "ks:ks_name":"Raniganj",
    "ks:ks_pop":975,
    "ks:ks_type":"VILLAGE",
    "ks:ks_uagg_main":0,
    "name:eng_x_preferred":[
        "Raniganj"
    ],
    "wof:name":"Raniganj",
    "wof:placetype":"neighbourhood",
    "wof:population":975
},
  "geometry": {"coordinates":[86.94095900000001,26.487208],"type":"Point"}
}