{
  "type": "Feature",
  "properties": {
    "iso:country":"IN",
    "ks:ks_name":"Sankarpur",
    "ks:ks_pop":2726,
    "ks:ks_type":"VILLAGE",
    "name:eng_x_preferred":[
        "Sankarpur"
    ],
    "wof:name":"Sankarpur",
    "wof:placetype":"locality",
    "wof:population":2726
},
  "geometry": {"coordinates":[87.788275,22.702008],"type":"Point"}
}