{
  "type": "Feature",
  "properties": {
    "iso:country":"IN",
    "ks:ks_alt_nam":"Butpara visitar",
    "ks:ks_name":"Butpara Visitar",
    "ks:ks_pop":191,
    "ks:ks_type":"HABITATION",
    "name:eng_x_preferred":[
        "Butpara Visitar"
    ],
    "wof:name":"Butpara Visitar",
    "wof:placetype":"locality",
    "wof:population":191
},
  "geometry": {"coordinates":[72.903639,22.822501],"type":"Point"}
}