{
  "type": "Feature",
  "properties": {
    "gn:admin1_code":"34.0",
    "gn:admin2_code":"229.0",
    "gn:asciiname":"Koiri Bigha",
    "gn:country_code":"IN",
    "gn:dem":70,
    "gn:feature_class":"P",
    "gn:feature_code":"PPL",
    "gn:name":"Koiri Bigha",
    "gn:population":0,
    "gn:timezone":"Asia/Kolkata",
    "iso:country":"IN",
    "ks:ks_name":"Koyri Bigha",
    "ks:ks_pop":440,
    "ks:ks_type":"HABITATION",
    "ks:ks_uagg_main":0,
    "name:eng_x_preferred":[
        "Koyri Bigha"
    ],
    "wof:name":"Koyri Bigha",
    "wof:placetype":"neighbourhood",
    "wof:population":440
},
  "geometry": {"coordinates":[85.563377,25.058458],"type":"Point"}
}