{
  "type": "Feature",
  "properties": {
    "iso:country":"IN",
    "ks:ks_name":"Kanmane",
    "ks:ks_pop":4,
    "ks:ks_type":"HABITATION",
    "name:eng_x_preferred":[
        "Kanmane"
    ],
    "wof:name":"Kanmane",
    "wof:placetype":"locality",
    "wof:population":4
},
  "geometry": {"coordinates":[74.875232,13.999394],"type":"Point"}
}