{
  "type": "Feature",
  "properties": {
    "gn:admin1_code":"21",
    "gn:admin2_code":"370.0",
    "gn:asciiname":"Debrigarh",
    "gn:country_code":"IN",
    "gn:dem":471,
    "gn:feature_class":"P",
    "gn:feature_code":"PPL",
    "gn:name":"Debr\u012bgarh",
    "gn:population":0,
    "gn:timezone":"Asia/Kolkata",
    "iso:country":"IN",
    "wof:name":"Debrigarh",
    "wof:placetype":"locality"
},
  "geometry": {"coordinates":[83.58718,21.55279],"type":"Point"}
}