{
  "type": "Feature",
  "properties": {
    "iso:country":"IN",
    "ks:ks_name":"Dhakadpara",
    "ks:ks_pop":644,
    "ks:ks_type":"HABITATION",
    "name:eng_x_preferred":[
        "Dhakadpara"
    ],
    "wof:name":"Dhakadpara",
    "wof:placetype":"locality",
    "wof:population":644
},
  "geometry": {"coordinates":[81.63567999999999,19.054855],"type":"Point"}
}