{
  "type": "Feature",
  "properties": {
    "iso:country":"IN",
    "ks:ks_name":"2 Gariya Para",
    "ks:ks_pop":166,
    "ks:ks_type":"HABITATION",
    "name:eng_x_preferred":[
        "2 Gariya Para"
    ],
    "wof:name":"2 Gariya Para",
    "wof:placetype":"locality",
    "wof:population":166
},
  "geometry": {"coordinates":[91.448188,24.047212],"type":"Point"}
}