{
  "type": "Feature",
  "properties": {
    "iso:country":"IN",
    "ks:ks_alt_nam":"tharaiguda",
    "ks:ks_name":"Tharaiguda",
    "ks:ks_pop":30,
    "ks:ks_type":"HABITATION",
    "name:eng_x_preferred":[
        "Tharaiguda"
    ],
    "wof:name":"Tharaiguda",
    "wof:placetype":"locality",
    "wof:population":30
},
  "geometry": {"coordinates":[78.944197,19.273359],"type":"Point"}
}