{
  "type": "Feature",
  "properties": {
    "gn:admin1_code":"35.0",
    "gn:admin2_code":"464.0",
    "gn:asciiname":"Dhamna",
    "gn:country_code":"IN",
    "gn:dem":355,
    "gn:feature_class":"P",
    "gn:feature_code":"PPL",
    "gn:name":"Dhamna",
    "gn:population":0,
    "gn:timezone":"Asia/Kolkata",
    "iso:country":"IN",
    "wof:name":"Dhamna",
    "wof:placetype":"locality"
},
  "geometry": {"coordinates":[74.67375,23.04934],"type":"Point"}
}