{
  "type": "Feature",
  "properties": {
    "iso:country":"IN",
    "ks:ks_name":"Valampuram Jn.",
    "ks:ks_pop":684,
    "ks:ks_type":"HABITATION",
    "name:eng_x_preferred":[
        "Valampuram Jn."
    ],
    "wof:name":"Valampuram Jn.",
    "wof:placetype":"locality",
    "wof:population":684
},
  "geometry": {"coordinates":[76.279443,11.269228],"type":"Point"}
}