{
  "type": "Feature",
  "properties": {
    "iso:country":"IN",
    "ks:ks_alt_nam":"KAVLAPURE VASTI",
    "ks:ks_name":"Kavlapure Vasti",
    "ks:ks_pop":152,
    "ks:ks_type":"HABITATION",
    "name:eng_x_preferred":[
        "Kavlapure Vasti"
    ],
    "wof:name":"Kavlapure Vasti",
    "wof:placetype":"locality",
    "wof:population":152
},
  "geometry": {"coordinates":[74.86548999999999,16.88887],"type":"Point"}
}