{
  "type": "Feature",
  "properties": {
    "gn:admin1_code":"16.0",
    "gn:admin2_code":"525",
    "gn:asciiname":"Dalimb",
    "gn:country_code":"IN",
    "gn:dem":608,
    "gn:feature_class":"P",
    "gn:feature_code":"PPL",
    "gn:name":"D\u0101l\u012bmb",
    "gn:population":0,
    "gn:timezone":"Asia/Kolkata",
    "iso:country":"IN",
    "name:und_x_variant":[
        "D\u0101l\u012bmb",
        "D\u0101limb"
    ],
    "wof:name":"Dalimb",
    "wof:placetype":"locality"
},
  "geometry": {"coordinates":[76.47953000000003,17.86526],"type":"Point"}
}