{
  "type": "Feature",
  "properties": {
    "gn:admin1_code":"12",
    "gn:admin2_code":"15.0",
    "gn:asciiname":"Sarmarg",
    "gn:country_code":"IN",
    "gn:dem":2183,
    "gn:feature_class":"P",
    "gn:feature_code":"PPL",
    "gn:name":"Sarmarg",
    "gn:population":0,
    "gn:timezone":"Asia/Kolkata",
    "iso:country":"IN",
    "wof:name":"Sarmarg",
    "wof:placetype":"locality"
},
  "geometry": {"coordinates":[74.97833,33.55189],"type":"Point"}
}