{
  "type": "Feature",
  "properties": {
    "iso:country":"IN",
    "ks:ks_name":"Sanyavandh",
    "ks:ks_pop":80,
    "ks:ks_type":"HABITATION",
    "name:eng_x_preferred":[
        "Sanyavandh"
    ],
    "wof:name":"Sanyavandh",
    "wof:placetype":"locality",
    "wof:population":80
},
  "geometry": {"coordinates":[70.51051099999999,23.498506],"type":"Point"}
}