{
  "type": "Feature",
  "properties": {
    "iso:country":"IN",
    "ks:ks_name":"Kalwadi",
    "ks:ks_pop":7706,
    "ks:ks_type":"HABITATION",
    "name:eng_x_preferred":[
        "Kalwadi"
    ],
    "wof:name":"Kalwadi",
    "wof:placetype":"locality",
    "wof:population":7706
},
  "geometry": {"coordinates":[73.927865,19.685456],"type":"Point"}
}