{
  "type": "Feature",
  "properties": {
    "iso:country":"IN",
    "ks:ks_name":"Gowagaon",
    "ks:ks_pop":990,
    "ks:ks_type":"VILLAGE",
    "name:eng_x_preferred":[
        "Gowagaon"
    ],
    "wof:name":"Gowagaon",
    "wof:placetype":"locality",
    "wof:population":990
},
  "geometry": {"coordinates":[88.008735,25.656823],"type":"Point"}
}