{
  "type": "Feature",
  "properties": {
    "iso:country":"IN",
    "ks:ks_name":"Puwali Pathar No 2",
    "ks:ks_pop":88,
    "ks:ks_type":"HABITATION",
    "name:eng_x_preferred":[
        "Puwali Pathar No 2"
    ],
    "wof:name":"Puwali Pathar No 2",
    "wof:placetype":"locality",
    "wof:population":88
},
  "geometry": {"coordinates":[95.181639,27.209329],"type":"Point"}
}