{
  "type": "Feature",
  "properties": {
    "iso:country":"IN",
    "ks:ks_name":"Sarpanch Faliya",
    "ks:ks_pop":102,
    "ks:ks_type":"HABITATION",
    "ks:ks_uagg_main":0,
    "name:eng_x_preferred":[
        "Sarpanch Faliya"
    ],
    "wof:name":"Sarpanch Faliya",
    "wof:placetype":"neighbourhood",
    "wof:population":102
},
  "geometry": {"coordinates":[73.19888899999999,20.489667],"type":"Point"}
}