{
  "type": "Feature",
  "properties": {
    "iso:country":"IN",
    "name:ast_x_preferred":[
        "Aushapur"
    ],
    "name:eng_x_preferred":[
        "Aushapur"
    ],
    "name:nld_x_preferred":[
        "Aushapur"
    ],
    "qs:name":"Aushapur",
    "qs:name_adm0":"India",
    "qs:name_adm1":"Andhra Pradesh",
    "qs:photos":1,
    "qs:photos_1k":1,
    "qs:photos_9k":1,
    "qs:photos_9r":1,
    "qs:photos_all":1,
    "qs:photos_sr":1,
    "qs:placetype":"Suburb",
    "qs:pop_sr":"0",
    "wd:wordcount":46,
    "wof:name":"Aushapur",
    "wof:placetype":"neighbourhood"
},
  "geometry": {"coordinates":[78.434577,17.461797],"type":"Point"}
}