{
  "type": "Feature",
  "properties": {
    "iso:country":"IN",
    "ks:ks_alt_nam":"Ramakrishnapuram IC",
    "ks:ks_name":"Ramakrishnapuram Ic",
    "ks:ks_pop":40,
    "ks:ks_type":"HABITATION",
    "name:eng_x_preferred":[
        "Ramakrishnapuram Ic"
    ],
    "wof:name":"Ramakrishnapuram Ic",
    "wof:placetype":"locality",
    "wof:population":40
},
  "geometry": {"coordinates":[79.544999,13.145414],"type":"Point"}
}