{
  "type": "Feature",
  "properties": {
    "gn:admin1_code":"38",
    "gn:admin2_code":"346.0",
    "gn:asciiname":"Mangra",
    "gn:country_code":"IN",
    "gn:dem":249,
    "gn:feature_class":"P",
    "gn:feature_code":"PPL",
    "gn:name":"Mangra",
    "gn:population":0,
    "gn:timezone":"Asia/Kolkata",
    "iso:country":"IN",
    "name:msa_x_preferred":[
        "Mangra"
    ],
    "name:zho_x_preferred":[
        "\u832b\u62c9\u4e61"
    ],
    "wof:name":"Mangra",
    "wof:placetype":"locality"
},
  "geometry": {"coordinates":[83.5907,24.22238],"type":"Point"}
}