{
  "type": "Feature",
  "properties": {
    "gn:admin1_code":"34.0",
    "gn:admin2_code":"218.0",
    "gn:asciiname":"Surajbalia",
    "gn:country_code":"IN",
    "gn:dem":64,
    "gn:feature_class":"P",
    "gn:feature_code":"PPL",
    "gn:name":"Surajbalia",
    "gn:population":0,
    "gn:timezone":"Asia/Kolkata",
    "iso:country":"IN",
    "ks:ks_name":"Surajbalia",
    "ks:ks_pop":306,
    "ks:ks_type":"VILLAGE",
    "ks:ks_uagg_main":0,
    "name:eng_x_preferred":[
        "Surajbalia"
    ],
    "wof:name":"Surajbalia",
    "wof:placetype":"neighbourhood",
    "wof:population":306
},
  "geometry": {"coordinates":[84.245604,26.062251],"type":"Point"}
}