{
  "type": "Feature",
  "properties": {
    "iso:country":"IN",
    "ks:ks_name":"Muchhamput",
    "ks:ks_pop":102,
    "ks:ks_type":"HABITATION",
    "name:eng_x_preferred":[
        "Muchhamput"
    ],
    "wof:name":"Muchhamput",
    "wof:placetype":"locality",
    "wof:population":102
},
  "geometry": {"coordinates":[82.545523,18.56203],"type":"Point"}
}