{
  "type": "Feature",
  "properties": {
    "gn:admin1_code":"35.0",
    "gn:admin2_code":"425.0",
    "gn:asciiname":"Kaimaha",
    "gn:country_code":"IN",
    "gn:dem":205,
    "gn:feature_class":"P",
    "gn:feature_code":"PPL",
    "gn:name":"Kaim\u0101ha",
    "gn:population":0,
    "gn:timezone":"Asia/Kolkata",
    "iso:country":"IN",
    "ks:ks_name":"Kaimaha",
    "ks:ks_pop":723,
    "ks:ks_type":"VILLAGE",
    "name:eng_x_preferred":[
        "Kaimaha"
    ],
    "wof:name":"Kaimaha",
    "wof:placetype":"locality",
    "wof:population":723
},
  "geometry": {"coordinates":[79.35067100000001,25.270828],"type":"Point"}
}