{
  "type": "Feature",
  "properties": {
    "gn:admin1_code":"35.0",
    "gn:admin2_code":"425.0",
    "gn:asciiname":"Kaimaha",
    "gn:country_code":"IN",
    "gn:dem":205,
    "gn:feature_class":"P",
    "gn:feature_code":"PPL",
    "gn:name":"Kaim\u0101ha",
    "gn:population":0,
    "gn:timezone":"Asia/Kolkata",
    "iso:country":"IN",
    "wof:name":"Kaimaha",
    "wof:placetype":"locality"
},
  "geometry": {"coordinates":[79.34557,25.27358],"type":"Point"}
}