{
  "type": "Feature",
  "properties": {
    "iso:country":"IN",
    "ks:ks_name":"Hanoli",
    "ks:ks_pop":59,
    "ks:ks_type":"HABITATION",
    "name:eng_x_preferred":[
        "Hanoli"
    ],
    "wof:name":"Hanoli",
    "wof:placetype":"locality",
    "wof:population":59
},
  "geometry": {"coordinates":[74.506676,15.063132],"type":"Point"}
}