{
  "type": "Feature",
  "properties": {
    "iso:country":"IN",
    "ks:ks_alt_nam":"NC Hiloikhunda",
    "ks:ks_name":"Nc Hiloikhunda",
    "ks:ks_pop":486,
    "ks:ks_type":"HABITATION",
    "name:eng_x_preferred":[
        "Nc Hiloikhunda"
    ],
    "wof:name":"Nc Hiloikhunda",
    "wof:placetype":"locality",
    "wof:population":486
},
  "geometry": {"coordinates":[92.091528,26.372882],"type":"Point"}
}