{
  "type": "Feature",
  "properties": {
    "iso:country":"IN",
    "ks:ks_name":"Janjuri",
    "ks:ks_pop":563,
    "ks:ks_type":"HABITATION",
    "name:eng_x_preferred":[
        "Janjuri"
    ],
    "wof:name":"Janjuri",
    "wof:placetype":"locality",
    "wof:population":563
},
  "geometry": {"coordinates":[93.910977,26.11228],"type":"Point"}
}