{
  "type": "Feature",
  "properties": {
    "iso:country":"IN",
    "ks:ks_name":"Tiragalamamidi",
    "ks:ks_pop":58,
    "ks:ks_type":"HABITATION",
    "name:eng_x_preferred":[
        "Tiragalamamidi"
    ],
    "wof:name":"Tiragalamamidi",
    "wof:placetype":"locality",
    "wof:population":58
},
  "geometry": {"coordinates":[82.278403,17.959935],"type":"Point"}
}