{
  "type": "Feature",
  "properties": {
    "iso:country":"IN",
    "ks:ks_alt_nam":"217 RD",
    "ks:ks_name":"217 Rd",
    "ks:ks_pop":85,
    "ks:ks_type":"HABITATION",
    "name:eng_x_preferred":[
        "217 Rd"
    ],
    "wof:name":"217 Rd",
    "wof:placetype":"locality",
    "wof:population":85
},
  "geometry": {"coordinates":[74.01385399999999,29.20543],"type":"Point"}
}