{
  "type": "Feature",
  "properties": {
    "iso:country":"IN",
    "ks:ks_name":"Pandva Gamtal",
    "ks:ks_pop":332,
    "ks:ks_type":"HABITATION",
    "name:eng_x_preferred":[
        "Pandva Gamtal"
    ],
    "wof:name":"Pandva Gamtal",
    "wof:placetype":"locality",
    "wof:population":332
},
  "geometry": {"coordinates":[73.55965,22.7819],"type":"Point"}
}