{
  "type": "Feature",
  "properties": {
    "iso:country":"IN",
    "ks:ks_name":"Muchuradaldali",
    "ks:ks_pop":307,
    "ks:ks_type":"VILLAGE",
    "name:eng_x_preferred":[
        "Muchuradaldali"
    ],
    "wof:name":"Muchuradaldali",
    "wof:placetype":"locality",
    "wof:population":307
},
  "geometry": {"coordinates":[87.482488,25.026825],"type":"Point"}
}