{
  "type": "Feature",
  "properties": {
    "iso:country":"IN",
    "ks:ks_name":"Bhambhet Ahatmali",
    "ks:ks_pop":0,
    "ks:ks_type":"VILLAGE",
    "name:eng_x_preferred":[
        "Bhambhet Ahatmali"
    ],
    "wof:name":"Bhambhet Ahatmali",
    "wof:placetype":"locality",
    "wof:population":0
},
  "geometry": {"coordinates":[81.17888499999999,25.372439],"type":"Point"}
}