{
  "type": "Feature",
  "properties": {
    "gn:admin1_code":"21.0",
    "gn:admin2_code":"398.0",
    "gn:asciiname":"Mettaguda",
    "gn:country_code":"IN",
    "gn:dem":945,
    "gn:feature_class":"P",
    "gn:feature_code":"PPL",
    "gn:name":"Mettaguda",
    "gn:population":0,
    "gn:timezone":"Asia/Kolkata",
    "iso:country":"IN",
    "wof:name":"Mettaguda",
    "wof:placetype":"locality"
},
  "geometry": {"coordinates":[82.8284,18.50433],"type":"Point"}
}