{
  "type": "Feature",
  "properties": {
    "iso:country":"IN",
    "ks:ks_name":"Hatinga Gaon",
    "ks:ks_pop":402,
    "ks:ks_type":"VILLAGE",
    "ks:ks_uagg_main":0,
    "name:eng_x_preferred":[
        "Hatinga Gaon"
    ],
    "wof:name":"Hatinga Gaon",
    "wof:placetype":"neighbourhood",
    "wof:population":402
},
  "geometry": {"coordinates":[92.93719299999999,26.817333],"type":"Point"}
}