{
  "type": "Feature",
  "properties": {
    "iso:country":"IN",
    "ks:ks_alt_nam":"MANEPATILWASTI",
    "ks:ks_name":"Manepatilwasti",
    "ks:ks_pop":100,
    "ks:ks_type":"HABITATION",
    "name:eng_x_preferred":[
        "Manepatilwasti"
    ],
    "wof:name":"Manepatilwasti",
    "wof:placetype":"locality",
    "wof:population":100
},
  "geometry": {"coordinates":[74.34656,17.117034],"type":"Point"}
}