{
  "type": "Feature",
  "properties": {
    "iso:country":"IN",
    "ks:ks_name":"Deojharan",
    "ks:ks_pop":226,
    "ks:ks_type":"VILLAGE",
    "name:eng_x_preferred":[
        "Deojharan"
    ],
    "wof:name":"Deojharan",
    "wof:placetype":"locality",
    "wof:population":226
},
  "geometry": {"coordinates":[86.134033,21.403897],"type":"Point"}
}