{
  "type": "Feature",
  "properties": {
    "iso:country":"IN",
    "ks:ks_name":"Uttar Bagidora",
    "ks:ks_pop":215,
    "ks:ks_type":"HABITATION",
    "ks:ks_uagg_main":0,
    "name:eng_x_preferred":[
        "Uttar Bagidora"
    ],
    "wof:name":"Uttar Bagidora",
    "wof:placetype":"neighbourhood",
    "wof:population":215
},
  "geometry": {"coordinates":[90.86541800000001,26.589613],"type":"Point"}
}