{
  "type": "Feature",
  "properties": {
    "iso:country":"IN",
    "ks:ks_name":"Kurmian",
    "ks:ks_pop":104,
    "ks:ks_type":"HABITATION",
    "name:eng_x_preferred":[
        "Kurmian"
    ],
    "wof:name":"Kurmian",
    "wof:placetype":"locality",
    "wof:population":104
},
  "geometry": {"coordinates":[81.964862,25.307404],"type":"Point"}
}