{
  "type": "Feature",
  "properties": {
    "iso:country":"IN",
    "ks:ks_name":"Mondal Para",
    "ks:ks_pop":1384,
    "ks:ks_type":"HABITATION",
    "name:eng_x_preferred":[
        "Mondal Para"
    ],
    "wof:name":"Mondal Para",
    "wof:placetype":"locality",
    "wof:population":1384
},
  "geometry": {"coordinates":[88.595242,22.235339],"type":"Point"}
}