{
  "type": "Feature",
  "properties": {
    "iso:country":"IN",
    "ks:ks_name":"Kampa Falia",
    "ks:ks_pop":1012,
    "ks:ks_type":"HABITATION",
    "name:eng_x_preferred":[
        "Kampa Falia"
    ],
    "wof:name":"Kampa Falia",
    "wof:placetype":"locality",
    "wof:population":1012
},
  "geometry": {"coordinates":[73.783889,23.412444],"type":"Point"}
}