{
  "type": "Feature",
  "properties": {
    "iso:country":"IN",
    "ks:ks_name":"Kutti Ujarawa Purwa",
    "ks:ks_pop":9,
    "ks:ks_type":"HABITATION",
    "name:eng_x_preferred":[
        "Kutti Ujarawa Purwa"
    ],
    "wof:name":"Kutti Ujarawa Purwa",
    "wof:placetype":"locality",
    "wof:population":9
},
  "geometry": {"coordinates":[82.684118,26.821745],"type":"Point"}
}