{
  "type": "Feature",
  "properties": {
    "iso:country":"IN",
    "ks:ks_name":"Ghhipa",
    "ks:ks_pop":122,
    "ks:ks_type":"HABITATION",
    "name:eng_x_preferred":[
        "Ghhipa"
    ],
    "wof:name":"Ghhipa",
    "wof:placetype":"locality",
    "wof:population":122
},
  "geometry": {"coordinates":[79.219039,29.891235],"type":"Point"}
}