{
  "type": "Feature",
  "properties": {
    "gn:admin1_code":"35",
    "gn:admin2_code":"429.0",
    "gn:asciiname":"Semra",
    "gn:country_code":"IN",
    "gn:dem":366,
    "gn:feature_class":"P",
    "gn:feature_code":"PPL",
    "gn:name":"Semra",
    "gn:population":0,
    "gn:timezone":"Asia/Kolkata",
    "iso:country":"IN",
    "name:ara_x_preferred":[
        "\u0633\u064a\u0645\u0631\u0627"
    ],
    "name:ben_bn_x_preferred":[
        "\u09b8\u09c7\u09ae\u09dc\u09be"
    ],
    "name:ben_in_x_preferred":[
        "\u09b8\u09c7\u09ae\u09dc\u09be"
    ],
    "name:deu_x_preferred":[
        "Semra"
    ],
    "name:guj_x_preferred":[
        "\u0ab8\u0ac7\u0aae\u0acd\u0ab0\u0abe"
    ],
    "name:hin_x_preferred":[
        "\u0938\u0947\u092e\u0930\u093e"
    ],
    "name:kan_x_preferred":[
        "\u0cb8\u0cc6\u0cae\u0ccd\u0cb0\u0cbe"
    ],
    "name:mal_x_preferred":[
        "\u0d38\u0d46\u0d2e\u0d4d\u0d30"
    ],
    "name:mar_x_preferred":[
        "\u0938\u0947\u092e\u0930\u093e"
    ],
    "name:pan_x_preferred":[
        "\u0a38\u0a48\u0a2e\u0a30\u0a3e"
    ],
    "name:tam_x_preferred":[
        "\u0b9a\u0bc6\u0bae\u0bcd\u0bb0\u0bbe"
    ],
    "name:tel_x_preferred":[
        "\u0c38\u0c46\u0c2e\u0c4d\u0c30\u0c3e"
    ],
    "name:urd_x_preferred":[
        "\u0633\u0645\u0631\u0627"
    ],
    "wof:name":"Semra",
    "wof:placetype":"locality"
},
  "geometry": {"coordinates":[80.62396,24.11504],"type":"Point"}
}