{
  "type": "Feature",
  "properties": {
    "iso:country":"IN",
    "ks:ks_name":"Chokkalingapuram",
    "ks:ks_pop":680,
    "ks:ks_type":"HABITATION",
    "name:eng_x_preferred":[
        "Chokkalingapuram"
    ],
    "wof:name":"Chokkalingapuram",
    "wof:placetype":"locality",
    "wof:population":680
},
  "geometry": {"coordinates":[77.992085,10.068167],"type":"Point"}
}