{
  "type": "Feature",
  "properties": {
    "gn:admin1_code":"35.0",
    "gn:admin2_code":"420.0",
    "gn:asciiname":"Kheriya Mahanand",
    "gn:country_code":"IN",
    "gn:dem":158,
    "gn:feature_class":"P",
    "gn:feature_code":"PPL",
    "gn:name":"Kheriya Mah\u0101nand",
    "gn:population":0,
    "gn:timezone":"Asia/Kolkata",
    "iso:country":"IN",
    "name:eng_x_preferred":[
        "Kheriya Mah\u0101nand"
    ],
    "wof:name":"Kheriya Mahanand",
    "wof:placetype":"locality"
},
  "geometry": {"coordinates":[78.48782,26.4253],"type":"Point"}
}