{
  "type": "Feature",
  "properties": {
    "iso:country":"IN",
    "ks:ks_name":"Pure Murain",
    "ks:ks_pop":131,
    "ks:ks_type":"HABITATION",
    "name:eng_x_preferred":[
        "Pure Murain"
    ],
    "wof:name":"Pure Murain",
    "wof:placetype":"locality",
    "wof:population":131
},
  "geometry": {"coordinates":[81.67478,26.44527],"type":"Point"}
}