{
  "type": "Feature",
  "properties": {
    "iso:country":"IN",
    "ks:ks_alt_nam":"raut tola",
    "ks:ks_name":"Raut Tola",
    "ks:ks_pop":734,
    "ks:ks_type":"HABITATION",
    "name:eng_x_preferred":[
        "Raut Tola"
    ],
    "wof:name":"Raut Tola",
    "wof:placetype":"locality",
    "wof:population":734
},
  "geometry": {"coordinates":[86.97757300000001,25.565958],"type":"Point"}
}