{
  "type": "Feature",
  "properties": {
    "gn:admin1_code":"40.0",
    "gn:admin2_code":"535.0",
    "gn:asciiname":"Srinivaspuram",
    "gn:country_code":"IN",
    "gn:dem":568,
    "gn:feature_class":"P",
    "gn:feature_code":"PPL",
    "gn:name":"Sr\u012bniv\u0101spuram",
    "gn:population":0,
    "gn:timezone":"Asia/Kolkata",
    "iso:country":"IN",
    "ks:ks_name":"Srinivasapur",
    "ks:ks_pop":172,
    "ks:ks_type":"VILLAGE",
    "name:eng_x_preferred":[
        "Srinivasapur"
    ],
    "name:eng_x_variant":[
        "Srinivaspuram"
    ],
    "wof:name":"Srinivasapur",
    "wof:placetype":"locality",
    "wof:population":172
},
  "geometry": {"coordinates":[78.78607599999999,17.709535],"type":"Point"}
}