{
  "type": "Feature",
  "properties": {
    "iso:country":"IN",
    "ks:ks_name":"Simaljor",
    "ks:ks_pop":172,
    "ks:ks_type":"VILLAGE",
    "name:eng_x_preferred":[
        "Simaljor"
    ],
    "wof:name":"Simaljor",
    "wof:placetype":"locality",
    "wof:population":172
},
  "geometry": {"coordinates":[87.380241,24.169271],"type":"Point"}
}