{
  "type": "Feature",
  "properties": {
    "iso:country":"IN",
    "ks:ks_name":"Itara",
    "ks:ks_pop":548,
    "ks:ks_type":"VILLAGE",
    "name:eng_x_preferred":[
        "Itara"
    ],
    "wof:name":"Itara",
    "wof:placetype":"locality",
    "wof:population":548
},
  "geometry": {"coordinates":[86.36410600000001,20.812409],"type":"Point"}
}