{
  "type": "Feature",
  "properties": {
    "iso:country":"IN",
    "ks:ks_name":"Pangalewadi",
    "ks:ks_pop":180,
    "ks:ks_type":"HABITATION",
    "name:eng_x_preferred":[
        "Pangalewadi"
    ],
    "wof:name":"Pangalewadi",
    "wof:placetype":"locality",
    "wof:population":180
},
  "geometry": {"coordinates":[73.811002,16.383489],"type":"Point"}
}