{
  "type": "Feature",
  "properties": {
    "gn:admin1_code":"23.0",
    "gn:admin2_code":"53.0",
    "gn:asciiname":"Rai Singhwala",
    "gn:country_code":"IN",
    "gn:dem":243,
    "gn:feature_class":"P",
    "gn:feature_code":"PPL",
    "gn:name":"Rai Singhw\u0101la",
    "gn:population":0,
    "gn:timezone":"Asia/Kolkata",
    "iso:country":"IN",
    "name:und_x_variant":[
        "Rai Singhw\u0101la",
        "Raipur"
    ],
    "wof:name":"Rai Singhwala",
    "wof:placetype":"locality"
},
  "geometry": {"coordinates":[75.99446999999998,30.28419],"type":"Point"}
}