{
  "type": "Feature",
  "properties": {
    "iso:country":"IN",
    "ks:ks_name":"Brindabanpur",
    "ks:ks_pop":4345,
    "ks:ks_type":"VILLAGE",
    "ks:ks_uagg_main":0,
    "name:eng_x_preferred":[
        "Brindabanpur"
    ],
    "wof:name":"Brindabanpur",
    "wof:placetype":"neighbourhood",
    "wof:population":4345
},
  "geometry": {"coordinates":[86.747361,23.763211],"type":"Point"}
}