{
  "type": "Feature",
  "properties": {
    "gn:admin1_code":"40.0",
    "gn:admin2_code":"534.0",
    "gn:asciiname":"Arepalli",
    "gn:country_code":"IN",
    "gn:dem":356,
    "gn:feature_class":"P",
    "gn:feature_code":"PPL",
    "gn:name":"Arepalli",
    "gn:population":0,
    "gn:timezone":"Asia/Kolkata",
    "iso:country":"IN",
    "wof:name":"Arepalli",
    "wof:placetype":"neighbourhood"
},
  "geometry": {"coordinates":[79.20032,18.13608],"type":"Point"}
}