{
  "type": "Feature",
  "properties": {
    "iso:country":"IN",
    "ks:ks_name":"Devaravanka",
    "ks:ks_pop":109,
    "ks:ks_type":"HABITATION",
    "name:eng_x_preferred":[
        "Devaravanka"
    ],
    "wof:name":"Devaravanka",
    "wof:placetype":"locality",
    "wof:population":109
},
  "geometry": {"coordinates":[77.987335,13.850137],"type":"Point"}
}