{
  "type": "Feature",
  "properties": {
    "iso:country":"IN",
    "ks:ks_name":"Jarkapaksara",
    "ks:ks_pop":1205,
    "ks:ks_type":"VILLAGE",
    "name:eng_x_preferred":[
        "Jarkapaksara"
    ],
    "wof:name":"Jarkapaksara",
    "wof:placetype":"locality",
    "wof:population":1205
},
  "geometry": {"coordinates":[86.974709,23.001515],"type":"Point"}
}