{
  "type": "Feature",
  "properties": {
    "gn:admin1_code":"36",
    "gn:admin2_code":"143.0",
    "gn:asciiname":"Kalai",
    "gn:country_code":"IN",
    "gn:dem":190,
    "gn:feature_class":"P",
    "gn:feature_code":"PPL",
    "gn:name":"Kalai",
    "gn:population":0,
    "gn:timezone":"Asia/Kolkata",
    "iso:country":"IN",
    "name:ceb_x_preferred":[
        "Kalai"
    ],
    "name:deu_x_preferred":[
        "Kalai"
    ],
    "name:fra_x_preferred":[
        "Kalai"
    ],
    "name:heb_x_preferred":[
        "\u05e7\u05dc\u05e2\u05d9"
    ],
    "name:ita_x_preferred":[
        "Kalai"
    ],
    "name:msa_x_preferred":[
        "Kalai"
    ],
    "name:por_x_preferred":[
        "Kalai"
    ],
    "name:swe_x_preferred":[
        "Kalai"
    ],
    "wof:name":"Kalai",
    "wof:placetype":"locality"
},
  "geometry": {"coordinates":[78.203,27.9579],"type":"Point"}
}