{
  "type": "Feature",
  "properties": {
    "iso:country":"IN",
    "ks:ks_name":"Goushimane",
    "ks:ks_pop":10,
    "ks:ks_type":"HABITATION",
    "name:eng_x_preferred":[
        "Goushimane"
    ],
    "wof:name":"Goushimane",
    "wof:placetype":"locality",
    "wof:population":10
},
  "geometry": {"coordinates":[74.62200199999999,14.718795],"type":"Point"}
}