{
  "type": "Feature",
  "properties": {
    "iso:country":"IN",
    "ks:ks_name":"Sundar Tola",
    "ks:ks_pop":294,
    "ks:ks_type":"HABITATION",
    "name:eng_x_preferred":[
        "Sundar Tola"
    ],
    "wof:name":"Sundar Tola",
    "wof:placetype":"locality",
    "wof:population":294
},
  "geometry": {"coordinates":[87.786866,26.292858],"type":"Point"}
}