{
  "type": "Feature",
  "properties": {
    "gn:admin1_code":"16.0",
    "gn:admin2_code":"508.0",
    "gn:asciiname":"Nasirkhanpalli",
    "gn:country_code":"IN",
    "gn:dem":118,
    "gn:feature_class":"P",
    "gn:feature_code":"PPL",
    "gn:name":"N\u0101sirkh\u0101npalli",
    "gn:population":0,
    "gn:timezone":"Asia/Kolkata",
    "iso:country":"IN",
    "ks:ks_name":"Nasirkhapalli",
    "ks:ks_pop":63,
    "ks:ks_type":"VILLAGE",
    "name:eng_x_preferred":[
        "Nasirkhapalli"
    ],
    "name:eng_x_variant":[
        "Nasirkhanpalli"
    ],
    "wof:name":"Nasirkhapalli",
    "wof:placetype":"locality",
    "wof:population":63
},
  "geometry": {"coordinates":[79.959433,18.830314],"type":"Point"}
}