{
  "type": "Feature",
  "properties": {
    "iso:country":"IN",
    "ks:ks_alt_nam":"shivjichiwadi",
    "ks:ks_name":"Shivjichiwadi",
    "ks:ks_pop":180,
    "ks:ks_type":"HABITATION",
    "name:eng_x_preferred":[
        "Shivjichiwadi"
    ],
    "wof:name":"Shivjichiwadi",
    "wof:placetype":"locality",
    "wof:population":180
},
  "geometry": {"coordinates":[73.19412199999999,18.798459],"type":"Point"}
}