{
  "type": "Feature",
  "properties": {
    "iso:country":"IN",
    "ks:ks_name":"Vettikundu",
    "ks:ks_pop":299,
    "ks:ks_type":"HABITATION",
    "name:eng_x_preferred":[
        "Vettikundu"
    ],
    "wof:name":"Vettikundu",
    "wof:placetype":"locality",
    "wof:population":299
},
  "geometry": {"coordinates":[76.685109,11.103877],"type":"Point"}
}