{
  "type": "Feature",
  "properties": {
    "iso:country":"IN",
    "ks:ks_name":"Tattigadde",
    "ks:ks_pop":108,
    "ks:ks_type":"HABITATION",
    "name:eng_x_preferred":[
        "Tattigadde"
    ],
    "wof:name":"Tattigadde",
    "wof:placetype":"locality",
    "wof:population":108
},
  "geometry": {"coordinates":[74.717873,14.755757],"type":"Point"}
}