{
  "type": "Feature",
  "properties": {
    "gn:admin1_code":"2.0",
    "gn:admin2_code":"553.0",
    "gn:asciiname":"Chinnappanayanipeta",
    "gn:country_code":"IN",
    "gn:dem":442,
    "gn:feature_class":"P",
    "gn:feature_code":"PPL",
    "gn:name":"Chinnappan\u0101yanipeta",
    "gn:population":0,
    "gn:timezone":"Asia/Kolkata",
    "iso:country":"IN",
    "wof:name":"Chinnappanayanipeta",
    "wof:placetype":"neighbourhood"
},
  "geometry": {"coordinates":[77.58655,14.27866],"type":"Point"}
}