{
  "type": "Feature",
  "properties": {
    "gn:admin1_code":"11",
    "gn:admin2_code":"33.0",
    "gn:asciiname":"Bhatwari",
    "gn:country_code":"IN",
    "gn:dem":1858,
    "gn:feature_class":"P",
    "gn:feature_code":"PPL",
    "gn:name":"Bhatw\u0101ri",
    "gn:population":0,
    "gn:timezone":"Asia/Kolkata",
    "iso:country":"IN",
    "wof:name":"Bhatwari",
    "wof:placetype":"locality"
},
  "geometry": {"coordinates":[77.81038000000002,31.19936],"type":"Point"}
}