{
  "type": "Feature",
  "properties": {
    "gn:admin1_code":"25.0",
    "gn:admin2_code":"613.0",
    "gn:asciiname":"Kalivalaiyam",
    "gn:country_code":"IN",
    "gn:dem":154,
    "gn:feature_class":"P",
    "gn:feature_code":"PPL",
    "gn:name":"K\u0101livalaiyam",
    "gn:population":0,
    "gn:timezone":"Asia/Kolkata",
    "iso:country":"IN",
    "wof:name":"Kalivalaiyam",
    "wof:placetype":"locality"
},
  "geometry": {"coordinates":[77.97620000000001,11.03801],"type":"Point"}
}