{
  "type": "Feature",
  "properties": {
    "iso:country":"IN",
    "ks:ks_name":"Sandlekad Moidukutty Family",
    "ks:ks_pop":118,
    "ks:ks_type":"HABITATION",
    "name:eng_x_preferred":[
        "Sandlekad Moidukutty Family"
    ],
    "wof:name":"Sandlekad Moidukutty Family",
    "wof:placetype":"locality",
    "wof:population":118
},
  "geometry": {"coordinates":[75.77500000000001,12.421389],"type":"Point"}
}