{
  "type": "Feature",
  "properties": {
    "gn:admin1_code":"36",
    "gn:admin2_code":"195.0",
    "gn:asciiname":"Barharia",
    "gn:country_code":"IN",
    "gn:dem":70,
    "gn:feature_class":"P",
    "gn:feature_code":"PPL",
    "gn:name":"Barharia",
    "gn:population":0,
    "gn:timezone":"Asia/Kolkata",
    "iso:country":"IN",
    "name:bih_x_preferred":[
        "\u092c\u0921\u093c\u0939\u0930\u093f\u092f\u093e"
    ],
    "name:hin_x_preferred":[
        "\u092c\u0930\u0939\u0930\u093f\u092f\u093e \u092a\u094d\u0930\u0916\u0923\u094d\u0921"
    ],
    "wof:name":"Barharia",
    "wof:placetype":"locality"
},
  "geometry": {"coordinates":[83.51573,25.4491],"type":"Point"}
}