{
  "type": "Feature",
  "properties": {
    "iso:country":"IN",
    "ks:ks_name":"Laxmanapalli",
    "ks:ks_pop":1159,
    "ks:ks_type":"VILLAGE",
    "name:eng_x_preferred":[
        "Laxmanapalli"
    ],
    "wof:name":"Laxmanapalli",
    "wof:placetype":"locality",
    "wof:population":1159
},
  "geometry": {"coordinates":[84.82455400000001,19.722406],"type":"Point"}
}