{
  "type": "Feature",
  "properties": {
    "iso:country":"IN",
    "ks:ks_alt_nam":"PORAHAMUDA",
    "ks:ks_name":"Porahamuda",
    "ks:ks_pop":248,
    "ks:ks_type":"HABITATION",
    "name:eng_x_preferred":[
        "Porahamuda"
    ],
    "wof:name":"Porahamuda",
    "wof:placetype":"locality",
    "wof:population":248
},
  "geometry": {"coordinates":[83.98488500000001,22.567044],"type":"Point"}
}