{
  "type": "Feature",
  "properties": {
    "gn:admin1_code":"36",
    "gn:admin2_code":"178.0",
    "gn:asciiname":"Phulpur",
    "gn:country_code":"IN",
    "gn:dem":89,
    "gn:feature_class":"P",
    "gn:feature_code":"PPL",
    "gn:name":"Ph\u016blpur",
    "gn:population":0,
    "gn:timezone":"Asia/Kolkata",
    "iso:country":"IN",
    "name:ita_x_preferred":[
        "Phulpur"
    ],
    "name:pol_x_preferred":[
        "Phulpur"
    ],
    "wof:name":"Phulpur",
    "wof:placetype":"locality"
},
  "geometry": {"coordinates":[82.85656,26.43489000000001],"type":"Point"}
}