{
  "type": "Feature",
  "properties": {
    "gn:admin1_code":"40.0",
    "gn:admin2_code":"534.0",
    "gn:asciiname":"Godangiri",
    "gn:country_code":"IN",
    "gn:dem":365,
    "gn:feature_class":"P",
    "gn:feature_code":"PPL",
    "gn:name":"Godangiri",
    "gn:population":0,
    "gn:timezone":"Asia/Kolkata",
    "iso:country":"IN",
    "wof:name":"Godangiri",
    "wof:placetype":"neighbourhood"
},
  "geometry": {"coordinates":[79.16427,18.10449],"type":"Point"}
}