{
  "type": "Feature",
  "properties": {
    "iso:country":"IN",
    "ks:ks_name":"Gundanavapalli",
    "ks:ks_pop":92,
    "ks:ks_type":"HABITATION",
    "name:eng_x_preferred":[
        "Gundanavapalli"
    ],
    "wof:name":"Gundanavapalli",
    "wof:placetype":"locality",
    "wof:population":92
},
  "geometry": {"coordinates":[77.978218,13.69233],"type":"Point"}
}