{
  "type": "Feature",
  "properties": {
    "iso:country":"IN",
    "ks:ks_name":"Unchhaun",
    "ks:ks_pop":169,
    "ks:ks_type":"HABITATION",
    "name:eng_x_preferred":[
        "Unchhaun"
    ],
    "wof:name":"Unchhaun",
    "wof:placetype":"locality",
    "wof:population":169
},
  "geometry": {"coordinates":[78.67313300000001,30.304235],"type":"Point"}
}