{
  "type": "Feature",
  "properties": {
    "iso:country":"IN",
    "ks:ks_name":"Brahmanachitratte",
    "ks:ks_pop":156,
    "ks:ks_type":"VILLAGE",
    "name:eng_x_preferred":[
        "Brahmanachitratte"
    ],
    "wof:name":"Brahmanachitratte",
    "wof:placetype":"locality",
    "wof:population":156
},
  "geometry": {"coordinates":[75.092996,14.125608],"type":"Point"}
}