{
  "type": "Feature",
  "properties": {
    "gn:admin1_code":"11",
    "gn:admin2_code":"23.0",
    "gn:asciiname":"Kundal",
    "gn:country_code":"IN",
    "gn:dem":2021,
    "gn:feature_class":"P",
    "gn:feature_code":"PPL",
    "gn:name":"Kundal",
    "gn:population":0,
    "gn:timezone":"Asia/Kolkata",
    "iso:country":"IN",
    "wof:name":"Kundal",
    "wof:placetype":"locality"
},
  "geometry": {"coordinates":[76.00699,32.76600999999999],"type":"Point"}
}