{
  "type": "Feature",
  "properties": {
    "gn:admin1_code":"24",
    "gn:admin2_code":"111.0",
    "gn:asciiname":"Nimera",
    "gn:country_code":"IN",
    "gn:dem":493,
    "gn:feature_class":"P",
    "gn:feature_code":"PPL",
    "gn:name":"Nimera",
    "gn:population":0,
    "gn:timezone":"Asia/Kolkata",
    "iso:country":"IN",
    "wof:name":"Nimera",
    "wof:placetype":"locality"
},
  "geometry": {"coordinates":[75.52956,27.51874],"type":"Point"}
}