{
  "type": "Feature",
  "properties": {
    "gn:admin1_code":"36",
    "gn:admin2_code":"185.0",
    "gn:asciiname":"Bhuila",
    "gn:country_code":"IN",
    "gn:dem":98,
    "gn:feature_class":"P",
    "gn:feature_code":"PPL",
    "gn:name":"Bhuila",
    "gn:population":0,
    "gn:timezone":"Asia/Kolkata",
    "iso:country":"IN",
    "ks:ks_name":"Bhuila",
    "ks:ks_type":"VILLAGE",
    "name:eng_x_preferred":[
        "Bhuila"
    ],
    "wof:name":"Bhuila",
    "wof:placetype":"locality"
},
  "geometry": {"coordinates":[82.534696,26.901484],"type":"Point"}
}