{
  "type": "Feature",
  "properties": {
    "iso:country":"IN",
    "ks:ks_name":"Biran Goan",
    "ks:ks_pop":116,
    "ks:ks_type":"VILLAGE",
    "name:eng_x_preferred":[
        "Biran Goan"
    ],
    "wof:name":"Biran Goan",
    "wof:placetype":"locality",
    "wof:population":116
},
  "geometry": {"coordinates":[78.92499100000001,30.35836],"type":"Point"}
}