{
  "type": "Feature",
  "properties": {
    "gn:admin1_code":"12.0",
    "gn:asciiname":"Pukharn",
    "gn:country_code":"IN",
    "gn:dem":866,
    "gn:feature_class":"P",
    "gn:feature_code":"PPL",
    "gn:name":"Pukharn",
    "gn:population":0,
    "gn:timezone":"Asia/Karachi",
    "iso:country":"IN",
    "name:und_x_variant":[
        "Pukharni",
        "Pukh\u0101rni"
    ],
    "wof:name":"Pukharn",
    "wof:placetype":"locality"
},
  "geometry": {"coordinates":[74.10311999999998,33.27204],"type":"Point"}
}