{
  "type": "Feature",
  "properties": {
    "iso:country":"IN",
    "ks:ks_name":"Maruguda",
    "ks:ks_pop":191,
    "ks:ks_type":"HABITATION",
    "name:eng_x_preferred":[
        "Maruguda"
    ],
    "wof:name":"Maruguda",
    "wof:placetype":"locality",
    "wof:population":191
},
  "geometry": {"coordinates":[79.051616,19.244577],"type":"Point"}
}