{
  "type": "Feature",
  "properties": {
    "iso:country":"IN",
    "ks:ks_name":"Kuchena",
    "ks:ks_pop":89,
    "ks:ks_type":"VILLAGE",
    "name:eng_x_preferred":[
        "Kuchena"
    ],
    "wof:name":"Kuchena",
    "wof:placetype":"locality",
    "wof:population":89
},
  "geometry": {"coordinates":[82.01709,20.58319],"type":"Point"}
}