{
  "type": "Feature",
  "properties": {
    "iso:country":"IN",
    "ks:ks_alt_nam":"atraila",
    "ks:ks_name":"Atraila",
    "ks:ks_pop":1000,
    "ks:ks_type":"HABITATION",
    "name:eng_x_preferred":[
        "Atraila"
    ],
    "wof:name":"Atraila",
    "wof:placetype":"locality",
    "wof:population":1000
},
  "geometry": {"coordinates":[81.8446,25.28459],"type":"Point"}
}