{
  "type": "Feature",
  "properties": {
    "iso:country":"IN",
    "ks:ks_name":"Urlupada",
    "ks:ks_pop":180,
    "ks:ks_type":"HABITATION",
    "name:eng_x_preferred":[
        "Urlupada"
    ],
    "wof:name":"Urlupada",
    "wof:placetype":"locality",
    "wof:population":180
},
  "geometry": {"coordinates":[82.76264500000001,20.190632],"type":"Point"}
}