{
  "type": "Feature",
  "properties": {
    "iso:country":"IN",
    "ks:ks_name":"Pashim Dusadh Toli",
    "ks:ks_pop":111,
    "ks:ks_type":"HABITATION",
    "name:eng_x_preferred":[
        "Pashim Dusadh Toli"
    ],
    "wof:name":"Pashim Dusadh Toli",
    "wof:placetype":"locality",
    "wof:population":111
},
  "geometry": {"coordinates":[84.960768,26.485127],"type":"Point"}
}