{
  "type": "Feature",
  "properties": {
    "gn:admin1_code":"11.0",
    "gn:admin2_code":"33.0",
    "gn:asciiname":"Golan",
    "gn:country_code":"IN",
    "gn:dem":1274,
    "gn:feature_class":"P",
    "gn:feature_code":"PPL",
    "gn:name":"Golan",
    "gn:population":0,
    "gn:timezone":"Asia/Kolkata",
    "iso:country":"IN",
    "name:cat_x_preferred":[
        "Gaulanitis"
    ],
    "name:cym_x_preferred":[
        "Golan"
    ],
    "name:fra_x_preferred":[
        "Gaulanitide"
    ],
    "name:heb_x_preferred":[
        "\u05d2\u05d5\u05dc\u05df"
    ],
    "name:ind_x_preferred":[
        "Golan"
    ],
    "name:ita_x_preferred":[
        "Golan"
    ],
    "name:jpn_x_preferred":[
        "\u30b4\u30e9\u30f3"
    ],
    "name:pol_x_preferred":[
        "Golan"
    ],
    "name:spa_x_preferred":[
        "Gaulan\u00edtide"
    ],
    "wof:name":"Golan",
    "wof:placetype":"locality"
},
  "geometry": {"coordinates":[77.04987,31.25236],"type":"Point"}
}