{
  "type": "Feature",
  "properties": {
    "gn:admin1_code":"19.0",
    "gn:admin2_code":"563.0",
    "gn:asciiname":"Hoskop",
    "gn:country_code":"IN",
    "gn:dem":575,
    "gn:feature_class":"P",
    "gn:feature_code":"PPL",
    "gn:name":"Hoskop",
    "gn:population":0,
    "gn:timezone":"Asia/Kolkata",
    "iso:country":"IN",
    "wof:name":"Hoskop",
    "wof:placetype":"locality"
},
  "geometry": {"coordinates":[75.04559999999999,14.91347],"type":"Point"}
}