{
  "type": "Feature",
  "properties": {
    "iso:country":"IN",
    "ks:ks_name":"Bhuriya Kund",
    "ks:ks_pop":378,
    "ks:ks_type":"HABITATION",
    "name:eng_x_preferred":[
        "Bhuriya Kund"
    ],
    "wof:name":"Bhuriya Kund",
    "wof:placetype":"locality",
    "wof:population":378
},
  "geometry": {"coordinates":[75.157949,22.523785],"type":"Point"}
}