{
  "type": "Feature",
  "properties": {
    "iso:country":"IN",
    "ks:ks_alt_nam":"Harijan tola",
    "ks:ks_name":"Harijan Tola",
    "ks:ks_pop":487,
    "ks:ks_type":"HABITATION",
    "name:eng_x_preferred":[
        "Harijan Tola"
    ],
    "wof:name":"Harijan Tola",
    "wof:placetype":"locality",
    "wof:population":487
},
  "geometry": {"coordinates":[85.659487,25.455744],"type":"Point"}
}