{
  "type": "Feature",
  "properties": {
    "gn:admin1_code":"25.0",
    "gn:admin2_code":"610.0",
    "gn:asciiname":"Pattimaniyakaranpalaiyam",
    "gn:country_code":"IN",
    "gn:dem":283,
    "gn:feature_class":"P",
    "gn:feature_code":"PPL",
    "gn:name":"Pattimaniyak\u0101ranp\u0101laiyam",
    "gn:population":0,
    "gn:timezone":"Asia/Kolkata",
    "iso:country":"IN",
    "ks:ks_name":"Patti Maniyakaran Palayam",
    "ks:ks_pop":182,
    "ks:ks_type":"HABITATION",
    "ks:ks_uagg_main":0,
    "name:eng_x_preferred":[
        "Patti Maniyakaran Palayam"
    ],
    "wof:name":"Patti Maniyakaran Palayam",
    "wof:placetype":"neighbourhood",
    "wof:population":182
},
  "geometry": {"coordinates":[77.253282,11.358682],"type":"Point"}
}