{
  "type": "Feature",
  "properties": {
    "iso:country":"IN",
    "ks:ks_name":"Mehandi Pur",
    "ks:ks_pop":158,
    "ks:ks_type":"HABITATION",
    "name:eng_x_preferred":[
        "Mehandi Pur"
    ],
    "wof:name":"Mehandi Pur",
    "wof:placetype":"locality",
    "wof:population":158
},
  "geometry": {"coordinates":[81.346996,25.509806],"type":"Point"}
}