{
  "type": "Feature",
  "properties": {
    "gn:admin1_code":"36",
    "gn:admin2_code":"159.0",
    "gn:asciiname":"Khummarpur",
    "gn:country_code":"IN",
    "gn:dem":154,
    "gn:feature_class":"P",
    "gn:feature_code":"PPL",
    "gn:name":"Khummarpur",
    "gn:population":0,
    "gn:timezone":"Asia/Kolkata",
    "iso:country":"IN",
    "wof:name":"Khummarpur",
    "wof:placetype":"locality"
},
  "geometry": {"coordinates":[79.49386,27.41096],"type":"Point"}
}