{
  "type": "Feature",
  "properties": {
    "iso:country":"IN",
    "ks:ks_alt_nam":"BHARRATOLA",
    "ks:ks_name":"Bharratola",
    "ks:ks_pop":119,
    "ks:ks_type":"HABITATION",
    "name:eng_x_preferred":[
        "Bharratola"
    ],
    "wof:name":"Bharratola",
    "wof:placetype":"locality",
    "wof:population":119
},
  "geometry": {"coordinates":[81.90325300000001,22.842009],"type":"Point"}
}