{
  "type": "Feature",
  "properties": {
    "gn:admin1_code":"35",
    "gn:admin2_code":"428.0",
    "gn:asciiname":"Dhariya",
    "gn:country_code":"IN",
    "gn:dem":496,
    "gn:feature_class":"P",
    "gn:feature_code":"PPL",
    "gn:name":"Dhariya",
    "gn:population":0,
    "gn:timezone":"Asia/Kolkata",
    "iso:country":"IN",
    "ks:ks_name":"Dhauriya",
    "ks:ks_pop":152,
    "ks:ks_type":"VILLAGE",
    "name:eng_x_preferred":[
        "Dhauriya"
    ],
    "name:eng_x_variant":[
        "Dhariya"
    ],
    "wof:name":"Dhauriya",
    "wof:placetype":"locality",
    "wof:population":152
},
  "geometry": {"coordinates":[79.533872,24.321544],"type":"Point"}
}