{
  "type": "Feature",
  "properties": {
    "gn:admin1_code":"37",
    "gn:admin2_code":"410.0",
    "gn:asciiname":"Cheria",
    "gn:country_code":"IN",
    "gn:dem":301,
    "gn:feature_class":"P",
    "gn:feature_code":"PPL",
    "gn:name":"Cheria",
    "gn:population":0,
    "gn:timezone":"Asia/Kolkata",
    "iso:country":"IN",
    "name:ara_x_preferred":[
        "\u0627\u0644\u0634\u0631\u064a\u0639\u0629"
    ],
    "name:azb_x_preferred":[
        "\u0634\u0631\u06cc\u0639\u0647"
    ],
    "name:ceb_x_preferred":[
        "Cheria"
    ],
    "name:fas_x_preferred":[
        "\u0634\u0631\u06cc\u0639\u0647"
    ],
    "name:fra_x_preferred":[
        "Cheria"
    ],
    "name:ita_x_preferred":[
        "Cheria"
    ],
    "name:msa_x_preferred":[
        "Cheria"
    ],
    "name:pol_x_preferred":[
        "Asz-Szaria"
    ],
    "name:por_x_preferred":[
        "Cheria"
    ],
    "name:ron_x_preferred":[
        "Cheria"
    ],
    "name:spa_x_preferred":[
        "Cheria"
    ],
    "name:swe_x_preferred":[
        "Cheria"
    ],
    "name:zho_x_preferred":[
        "\u820d\u91cc\u8036"
    ],
    "wof:name":"Cheria",
    "wof:placetype":"locality"
},
  "geometry": {"coordinates":[81.83384000000002,21.12199],"type":"Point"}
}