{
  "type": "Feature",
  "properties": {
    "iso:country":"IN",
    "ks:ks_name":"Pajankul",
    "ks:ks_pop":1602,
    "ks:ks_type":"VILLAGE",
    "ks:ks_uagg_main":0,
    "name:eng_x_preferred":[
        "Pajankul"
    ],
    "wof:name":"Pajankul",
    "wof:placetype":"neighbourhood",
    "wof:population":1602
},
  "geometry": {"coordinates":[87.74043500000001,22.094318],"type":"Point"}
}