{
  "type": "Feature",
  "properties": {
    "iso:country":"IN",
    "ks:ks_name":"Jodigadde",
    "ks:ks_pop":26,
    "ks:ks_type":"HABITATION",
    "name:eng_x_preferred":[
        "Jodigadde"
    ],
    "wof:name":"Jodigadde",
    "wof:placetype":"locality",
    "wof:population":26
},
  "geometry": {"coordinates":[75.727143,12.770788],"type":"Point"}
}