{
  "type": "Feature",
  "properties": {
    "iso:country":"IN",
    "ks:ks_name":"Majra Bewaqta",
    "ks:ks_pop":675,
    "ks:ks_type":"HABITATION",
    "name:eng_x_preferred":[
        "Majra Bewaqta"
    ],
    "wof:name":"Majra Bewaqta",
    "wof:placetype":"locality",
    "wof:population":675
},
  "geometry": {"coordinates":[79.026177,29.093653],"type":"Point"}
}