{
  "type": "Feature",
  "properties": {
    "gn:admin1_code":"19.0",
    "gn:admin2_code":"574.0",
    "gn:asciiname":"Madanahalli",
    "gn:country_code":"IN",
    "gn:dem":819,
    "gn:feature_class":"P",
    "gn:feature_code":"PPL",
    "gn:name":"Madanahalli",
    "gn:population":0,
    "gn:timezone":"Asia/Kolkata",
    "iso:country":"IN",
    "ks:ks_name":"Madanahalli",
    "ks:ks_pop":753,
    "ks:ks_type":"VILLAGE",
    "name:eng_x_preferred":[
        "Madanahalli"
    ],
    "wof:name":"Madanahalli",
    "wof:placetype":"locality",
    "wof:population":753
},
  "geometry": {"coordinates":[76.132437,13.318029],"type":"Point"}
}