{
  "type": "Feature",
  "properties": {
    "gn:admin1_code":"19.0",
    "gn:admin2_code":"574.0",
    "gn:asciiname":"Madanahalli",
    "gn:country_code":"IN",
    "gn:dem":819,
    "gn:feature_class":"P",
    "gn:feature_code":"PPL",
    "gn:name":"Madanahalli",
    "gn:population":0,
    "gn:timezone":"Asia/Kolkata",
    "iso:country":"IN",
    "wof:name":"Madanahalli",
    "wof:placetype":"locality"
},
  "geometry": {"coordinates":[76.13670999999999,13.31508],"type":"Point"}
}