{
  "type": "Feature",
  "properties": {
    "gn:admin1_code":"19",
    "gn:admin2_code":"557.0",
    "gn:asciiname":"Hanchinal",
    "gn:country_code":"IN",
    "gn:dem":460,
    "gn:feature_class":"P",
    "gn:feature_code":"PPL",
    "gn:name":"Hanchin\u0101l",
    "gn:population":0,
    "gn:timezone":"Asia/Kolkata",
    "iso:country":"IN",
    "ks:ks_alt_nam":"Hanchin\u0101l",
    "ks:ks_name":"Hanchinal",
    "ks:ks_pop":827,
    "ks:ks_type":"VILLAGE",
    "name:eng_x_preferred":[
        "Hanchinal"
    ],
    "name:eng_x_variant":[
        "Hanchin\u0101l"
    ],
    "wof:name":"Hanchinal",
    "wof:placetype":"locality",
    "wof:population":827
},
  "geometry": {"coordinates":[76.380275,16.996201],"type":"Point"}
}