{
  "type": "Feature",
  "properties": {
    "gn:admin1_code":"36",
    "gn:admin2_code":"179.0",
    "gn:asciiname":"Dewapur",
    "gn:country_code":"IN",
    "gn:dem":95,
    "gn:feature_class":"P",
    "gn:feature_code":"PPL",
    "gn:name":"Dew\u0101pur",
    "gn:population":0,
    "gn:timezone":"Asia/Kolkata",
    "iso:country":"IN",
    "name:ceb_x_preferred":[
        "Dewapur"
    ],
    "name:fra_x_preferred":[
        "Dewapur"
    ],
    "name:mai_x_preferred":[
        "\u0926\u0947\u0935\u093e\u092a\u0941\u0930"
    ],
    "name:msa_x_preferred":[
        "Dewapur"
    ],
    "name:nep_x_preferred":[
        "\u0926\u0947\u0935\u093e\u092a\u0941\u0930"
    ],
    "name:new_x_preferred":[
        "\u0926\u0947\u0935\u093e\u092a\u0941\u0930"
    ],
    "name:pol_x_preferred":[
        "Dewapur"
    ],
    "wof:name":"Dewapur",
    "wof:placetype":"locality"
},
  "geometry": {"coordinates":[82.30391999999998,26.12718],"type":"Point"}
}