{
  "type": "Feature",
  "properties": {
    "gn:admin1_code":"25.0",
    "gn:admin2_code":"633.0",
    "gn:asciiname":"Merku Sadaiyapalaiyam",
    "gn:country_code":"IN",
    "gn:dem":328,
    "gn:feature_class":"P",
    "gn:feature_code":"PPL",
    "gn:name":"Merku Sadaiyapalaiyam",
    "gn:population":0,
    "gn:timezone":"Asia/Kolkata",
    "iso:country":"IN",
    "wof:name":"Merku Sadaiyapalaiyam",
    "wof:placetype":"locality"
},
  "geometry": {"coordinates":[77.28368,10.7998],"type":"Point"}
}