{
  "type": "Feature",
  "properties": {
    "iso:country":"IN",
    "ks:ks_name":"Milki",
    "ks:ks_pop":68,
    "ks:ks_type":"VILLAGE",
    "ks:ks_uagg_main":0,
    "name:eng_x_preferred":[
        "Milki"
    ],
    "wof:name":"Milki",
    "wof:placetype":"neighbourhood",
    "wof:population":68
},
  "geometry": {"coordinates":[85.803709,25.16742],"type":"Point"}
}