{
  "type": "Feature",
  "properties": {
    "iso:country":"IN",
    "ks:ks_alt_nam":"G\u0101r\u0101d\u012bh",
    "ks:ks_name":"Garadih",
    "ks:ks_pop":311,
    "ks:ks_type":"VILLAGE",
    "name:eng_x_preferred":[
        "Garadih"
    ],
    "name:eng_x_variant":[
        "G\u0101r\u0101d\u012bh"
    ],
    "wof:name":"Garadih",
    "wof:placetype":"locality",
    "wof:population":311
},
  "geometry": {"coordinates":[85.962159,23.062841],"type":"Point"}
}