{
  "type": "Feature",
  "properties": {
    "iso:country":"IN",
    "ks:ks_name":"Kassowala",
    "ks:ks_pop":0,
    "ks:ks_type":"VILLAGE",
    "name:eng_x_preferred":[
        "Kassowala"
    ],
    "wof:name":"Kassowala",
    "wof:placetype":"locality",
    "wof:population":0
},
  "geometry": {"coordinates":[74.915533,32.042065],"type":"Point"}
}