{
  "type": "Feature",
  "properties": {
    "gn:admin1_code":"13.0",
    "gn:admin2_code":"589.0",
    "gn:asciiname":"Kunoth",
    "gn:country_code":"IN",
    "gn:dem":30,
    "gn:feature_class":"P",
    "gn:feature_code":"PPL",
    "gn:name":"Kun\u014dth",
    "gn:population":0,
    "gn:timezone":"Asia/Kolkata",
    "iso:country":"IN",
    "ks:ks_name":"Kunnoth",
    "ks:ks_pop":1448,
    "ks:ks_type":"HABITATION",
    "name:eng_x_preferred":[
        "Kunnoth"
    ],
    "name:eng_x_variant":[
        "Kunoth"
    ],
    "wof:name":"Kunnoth",
    "wof:placetype":"locality",
    "wof:population":1448
},
  "geometry": {"coordinates":[75.53903200000001,11.945068],"type":"Point"}
}