{
  "type": "Feature",
  "properties": {
    "gn:admin1_code":"13.0",
    "gn:admin2_code":"589.0",
    "gn:asciiname":"Kunoth",
    "gn:country_code":"IN",
    "gn:dem":30,
    "gn:feature_class":"P",
    "gn:feature_code":"PPL",
    "gn:name":"Kun\u014dth",
    "gn:population":0,
    "gn:timezone":"Asia/Kolkata",
    "iso:country":"IN",
    "wof:name":"Kunoth",
    "wof:placetype":"locality"
},
  "geometry": {"coordinates":[75.52485,11.95548],"type":"Point"}
}