{
  "type": "Feature",
  "properties": {
    "iso:country":"IN",
    "ks:ks_name":"Azmeera Thanda",
    "ks:ks_pop":110,
    "ks:ks_type":"HABITATION",
    "name:eng_x_preferred":[
        "Azmeera Thanda"
    ],
    "wof:name":"Azmeera Thanda",
    "wof:placetype":"locality",
    "wof:population":110
},
  "geometry": {"coordinates":[79.87333,17.450129],"type":"Point"}
}