{
  "type": "Feature",
  "properties": {
    "gn:admin1_code":"25.0",
    "gn:admin2_code":"617.0",
    "gn:asciiname":"Vaidinayakkankuppam",
    "gn:country_code":"IN",
    "gn:dem":51,
    "gn:feature_class":"P",
    "gn:feature_code":"PPL",
    "gn:name":"Vaidin\u0101yakkankuppam",
    "gn:population":0,
    "gn:timezone":"Asia/Kolkata",
    "iso:country":"IN",
    "wof:name":"Vaidinayakkankuppam",
    "wof:placetype":"locality"
},
  "geometry": {"coordinates":[79.48286999999998,11.56617],"type":"Point"}
}