{
  "type": "Feature",
  "properties": {
    "gn:admin1_code":"19.0",
    "gn:admin2_code":"568.0",
    "gn:asciiname":"Sulumane",
    "gn:country_code":"IN",
    "gn:dem":651,
    "gn:feature_class":"P",
    "gn:feature_code":"PPL",
    "gn:name":"S\u016blumane",
    "gn:population":0,
    "gn:timezone":"Asia/Kolkata",
    "iso:country":"IN",
    "wof:name":"Sulumane",
    "wof:placetype":"locality"
},
  "geometry": {"coordinates":[75.01874000000002,14.12442],"type":"Point"}
}