{
  "type": "Feature",
  "properties": {
    "iso:country":"IN",
    "ks:ks_name":"Cheepurugondi",
    "ks:ks_pop":102,
    "ks:ks_type":"HABITATION",
    "name:eng_x_preferred":[
        "Cheepurugondi"
    ],
    "wof:name":"Cheepurugondi",
    "wof:placetype":"locality",
    "wof:population":102
},
  "geometry": {"coordinates":[82.174903,17.813501],"type":"Point"}
}