{
  "type": "Feature",
  "properties": {
    "iso:country":"IN",
    "ks:ks_name":"Baragaon",
    "ks:ks_pop":54,
    "ks:ks_type":"HABITATION",
    "name:eng_x_preferred":[
        "Baragaon"
    ],
    "wof:name":"Baragaon",
    "wof:placetype":"locality",
    "wof:population":54
},
  "geometry": {"coordinates":[83.853814,20.665512],"type":"Point"}
}