{
  "type": "Feature",
  "properties": {
    "iso:country":"IN",
    "ks:ks_name":"Edapparamba",
    "ks:ks_pop":1451,
    "ks:ks_type":"HABITATION",
    "name:eng_x_preferred":[
        "Edapparamba"
    ],
    "wof:name":"Edapparamba",
    "wof:placetype":"locality",
    "wof:population":1451
},
  "geometry": {"coordinates":[75.217772,12.546577],"type":"Point"}
}