{
  "type": "Feature",
  "properties": {
    "iso:country":"IN",
    "ks:ks_name":"Rainiya",
    "ks:ks_pop":45,
    "ks:ks_type":"VILLAGE",
    "name:eng_x_preferred":[
        "Rainiya"
    ],
    "wof:name":"Rainiya",
    "wof:placetype":"locality",
    "wof:population":45
},
  "geometry": {"coordinates":[73.73463099999999,24.773889],"type":"Point"}
}