{
  "type": "Feature",
  "properties": {
    "gn:admin1_code":"21",
    "gn:admin2_code":"396.0",
    "gn:asciiname":"Badipanga",
    "gn:country_code":"IN",
    "gn:dem":449,
    "gn:feature_class":"P",
    "gn:feature_code":"PPL",
    "gn:name":"B\u0101dipanga",
    "gn:population":0,
    "gn:timezone":"Asia/Kolkata",
    "iso:country":"IN",
    "ks:ks_name":"Banipanga",
    "ks:ks_pop":86,
    "ks:ks_type":"VILLAGE",
    "name:eng_x_preferred":[
        "Banipanga"
    ],
    "name:eng_x_variant":[
        "Badipanga"
    ],
    "wof:name":"Banipanga",
    "wof:placetype":"locality",
    "wof:population":86
},
  "geometry": {"coordinates":[83.54657,19.823851],"type":"Point"}
}