{
  "type": "Feature",
  "properties": {
    "iso:country":"IN",
    "ks:ks_alt_nam":"Srinath para",
    "ks:ks_name":"Srinath Para",
    "ks:ks_pop":112,
    "ks:ks_type":"HABITATION",
    "name:eng_x_preferred":[
        "Srinath Para"
    ],
    "wof:name":"Srinath Para",
    "wof:placetype":"locality",
    "wof:population":112
},
  "geometry": {"coordinates":[91.80462199999999,23.35264],"type":"Point"}
}