{
  "type": "Feature",
  "properties": {
    "iso:country":"IN",
    "ks:ks_alt_nam":"Patr\u0101dih",
    "ks:ks_name":"Patradih",
    "ks:ks_pop":91,
    "ks:ks_type":"VILLAGE",
    "name:eng_x_preferred":[
        "Patradih"
    ],
    "name:eng_x_variant":[
        "Patr\u0101dih"
    ],
    "wof:name":"Patradih",
    "wof:placetype":"locality",
    "wof:population":91
},
  "geometry": {"coordinates":[84.11202299999999,23.690962],"type":"Point"}
}