{
  "type": "Feature",
  "properties": {
    "iso:country":"IN",
    "ks:ks_alt_nam":"PREM NAGAR",
    "ks:ks_name":"Prem Nagar",
    "ks:ks_pop":164,
    "ks:ks_type":"HABITATION",
    "ks:ks_uagg_main":0,
    "name:eng_x_preferred":[
        "Prem Nagar"
    ],
    "wof:name":"Prem Nagar",
    "wof:placetype":"neighbourhood",
    "wof:population":164
},
  "geometry": {"coordinates":[86.56,25.326],"type":"Point"}
}