{
  "type": "Feature",
  "properties": {
    "iso:country":"IN",
    "ks:ks_name":"Haldhara",
    "ks:ks_pop":0,
    "ks:ks_type":"VILLAGE",
    "name:eng_x_preferred":[
        "Haldhara"
    ],
    "wof:name":"Haldhara",
    "wof:placetype":"locality",
    "wof:population":0
},
  "geometry": {"coordinates":[87.708996,25.679392],"type":"Point"}
}