{
  "type": "Feature",
  "properties": {
    "iso:country":"IN",
    "ks:ks_name":"Karamo",
    "ks:ks_pop":91,
    "ks:ks_type":"VILLAGE",
    "name:eng_x_preferred":[
        "Karamo"
    ],
    "wof:name":"Karamo",
    "wof:placetype":"locality",
    "wof:population":91
},
  "geometry": {"coordinates":[84.91499399999999,24.315709],"type":"Point"}
}