{
  "type": "Feature",
  "properties": {
    "iso:country":"IN",
    "ks:ks_name":"Kupatimari",
    "ks:ks_pop":1742,
    "ks:ks_type":"VILLAGE",
    "ks:ks_uagg_main":0,
    "name:eng_x_preferred":[
        "Kupatimari"
    ],
    "wof:name":"Kupatimari",
    "wof:placetype":"neighbourhood",
    "wof:population":1742
},
  "geometry": {"coordinates":[92.23875099999999,26.403983],"type":"Point"}
}