{
  "type": "Feature",
  "properties": {
    "iso:country":"IN",
    "ks:ks_name":"Dhupuri No.1",
    "ks:ks_pop":917,
    "ks:ks_type":"VILLAGE",
    "ks:ks_uagg_main":0,
    "name:eng_x_preferred":[
        "Dhupuri No.1"
    ],
    "wof:name":"Dhupuri No.1",
    "wof:placetype":"neighbourhood",
    "wof:population":917
},
  "geometry": {"coordinates":[90.790795,26.491558],"type":"Point"}
}