{
  "type": "Feature",
  "properties": {
    "iso:country":"IN",
    "ks:ks_name":"Chalthan",
    "ks:ks_pop":12774,
    "ks:ks_type":"URBAN",
    "ks:ks_uagg_main":0,
    "name:eng_x_preferred":[
        "Chalthan"
    ],
    "wof:name":"Chalthan",
    "wof:placetype":"neighbourhood",
    "wof:population":12774
},
  "geometry": {"coordinates":[72.96181799999999,21.153059],"type":"Point"}
}