{
  "type": "Feature",
  "properties": {
    "gn:admin1_code":"36",
    "gn:admin2_code":"171.0",
    "gn:asciiname":"Bilas",
    "gn:country_code":"IN",
    "gn:dem":106,
    "gn:feature_class":"P",
    "gn:feature_code":"PPL",
    "gn:name":"Bil\u0101s",
    "gn:population":0,
    "gn:timezone":"Asia/Kolkata",
    "iso:country":"IN",
    "name:ukr_x_preferred":[
        "\u0411\u0456\u043b\u0430\u0441"
    ],
    "wof:name":"Bilas",
    "wof:placetype":"locality"
},
  "geometry": {"coordinates":[81.02175,25.53877],"type":"Point"}
}