{
  "type": "Feature",
  "properties": {
    "gn:admin1_code":"25.0",
    "gn:admin2_code":"605",
    "gn:asciiname":"Agaram",
    "gn:country_code":"IN",
    "gn:dem":300,
    "gn:feature_class":"P",
    "gn:feature_code":"PPL",
    "gn:name":"Agaram",
    "gn:population":0,
    "gn:timezone":"Asia/Kolkata",
    "iso:country":"IN",
    "name:bpy_x_preferred":[
        "\u0985\u0997\u09cd\u09b0\u09ae"
    ],
    "name:ita_x_preferred":[
        "Agaram"
    ],
    "name:min_x_preferred":[
        "Agaram"
    ],
    "name:msa_x_preferred":[
        "Agaram"
    ],
    "name:new_x_preferred":[
        "\u0905\u0917\u093e\u0930\u093e\u092e"
    ],
    "name:nld_x_preferred":[
        "Agaram"
    ],
    "name:por_x_preferred":[
        "Agaram"
    ],
    "name:tam_x_preferred":[
        "\u0b85\u0b95\u0bb0\u0bae\u0bcd"
    ],
    "name:vie_x_preferred":[
        "Agaram"
    ],
    "name:zho_x_preferred":[
        "\u963f\u52a0\u62c9\u59c6"
    ],
    "wof:name":"Agaram",
    "wof:placetype":"locality"
},
  "geometry": {"coordinates":[78.89072,12.82202],"type":"Point"}
}