{
  "type": "Feature",
  "properties": {
    "iso:country":"IN",
    "ks:ks_name":"Ayubhatu",
    "ks:ks_pop":197,
    "ks:ks_type":"VILLAGE",
    "name:eng_x_preferred":[
        "Ayubhatu"
    ],
    "wof:name":"Ayubhatu",
    "wof:placetype":"locality",
    "wof:population":197
},
  "geometry": {"coordinates":[85.390883,23.062976],"type":"Point"}
}