{
  "type": "Feature",
  "properties": {
    "iso:country":"IN",
    "ks:ks_name":"Gurma",
    "ks:ks_pop":874,
    "ks:ks_type":"VILLAGE",
    "ks:ks_uagg_main":0,
    "name:eng_x_preferred":[
        "Gurma"
    ],
    "wof:name":"Gurma",
    "wof:placetype":"neighbourhood",
    "wof:population":874
},
  "geometry": {"coordinates":[86.345743,22.762412],"type":"Point"}
}