{
  "type": "Feature",
  "properties": {
    "iso:country":"IN",
    "ks:ks_name":"Madhab Bari",
    "ks:ks_pop":466,
    "ks:ks_type":"HABITATION",
    "ks:ks_uagg_main":0,
    "name:eng_x_preferred":[
        "Madhab Bari"
    ],
    "wof:name":"Madhab Bari",
    "wof:placetype":"neighbourhood",
    "wof:population":466
},
  "geometry": {"coordinates":[91.410302,23.820309],"type":"Point"}
}