{
  "type": "Feature",
  "properties": {
    "iso:country":"IN",
    "ks:ks_name":"Daun",
    "ks:ks_pop":2836,
    "ks:ks_type":"VILLAGE",
    "ks:ks_uagg_main":0,
    "name:eng_x_preferred":[
        "Daun"
    ],
    "wof:name":"Daun",
    "wof:placetype":"neighbourhood",
    "wof:population":2836
},
  "geometry": {"coordinates":[76.68454199999999,30.741159],"type":"Point"}
}