{
  "type": "Feature",
  "properties": {
    "iso:country":"IN",
    "ks:ks_name":"Kushth Rog Ashram",
    "ks:ks_pop":225,
    "ks:ks_type":"HABITATION",
    "name:eng_x_preferred":[
        "Kushth Rog Ashram"
    ],
    "wof:name":"Kushth Rog Ashram",
    "wof:placetype":"locality",
    "wof:population":225
},
  "geometry": {"coordinates":[82.10793700000001,26.671133],"type":"Point"}
}