{
  "type": "Feature",
  "properties": {
    "iso:country":"IN",
    "ks:ks_name":"Hanumanpura",
    "ks:ks_pop":832,
    "ks:ks_type":"VILLAGE",
    "name:eng_x_preferred":[
        "Hanumanpura"
    ],
    "wof:name":"Hanumanpura",
    "wof:placetype":"locality",
    "wof:population":832
},
  "geometry": {"coordinates":[72.597667,26.445183],"type":"Point"}
}