{
  "type": "Feature",
  "properties": {
    "iso:country":"IN",
    "ks:ks_name":"Bhandaro",
    "ks:ks_pop":3033,
    "ks:ks_type":"HABITATION",
    "name:eng_x_preferred":[
        "Bhandaro"
    ],
    "wof:name":"Bhandaro",
    "wof:placetype":"locality",
    "wof:population":3033
},
  "geometry": {"coordinates":[86.783477,24.365665],"type":"Point"}
}