{
  "type": "Feature",
  "properties": {
    "iso:country":"IN",
    "ks:ks_name":"Simada Falia",
    "ks:ks_pop":387,
    "ks:ks_type":"HABITATION",
    "name:eng_x_preferred":[
        "Simada Falia"
    ],
    "wof:name":"Simada Falia",
    "wof:placetype":"locality",
    "wof:population":387
},
  "geometry": {"coordinates":[74.04041700000001,22.682],"type":"Point"}
}