{
  "type": "Feature",
  "properties": {
    "iso:country":"IN",
    "ks:ks_name":"Kachiatoli",
    "ks:ks_pop":123,
    "ks:ks_type":"HABITATION",
    "name:eng_x_preferred":[
        "Kachiatoli"
    ],
    "wof:name":"Kachiatoli",
    "wof:placetype":"locality",
    "wof:population":123
},
  "geometry": {"coordinates":[84.94802300000001,23.09484],"type":"Point"}
}