{
  "type": "Feature",
  "properties": {
    "iso:country":"IN",
    "ks:ks_alt_nam":"Chaigar Para A.D.C.Village",
    "ks:ks_name":"Chaigar Para A.d.c.village",
    "ks:ks_pop":222,
    "ks:ks_type":"HABITATION",
    "name:eng_x_preferred":[
        "Chaigar Para A.d.c.village"
    ],
    "wof:name":"Chaigar Para A.d.c.village",
    "wof:placetype":"locality",
    "wof:population":222
},
  "geometry": {"coordinates":[92.172183,23.757673],"type":"Point"}
}