{
  "type": "Feature",
  "properties": {
    "iso:country":"IN",
    "ks:ks_alt_nam":"musalpada",
    "ks:ks_name":"Musalpada",
    "ks:ks_pop":896,
    "ks:ks_type":"HABITATION",
    "name:eng_x_preferred":[
        "Musalpada"
    ],
    "wof:name":"Musalpada",
    "wof:placetype":"locality",
    "wof:population":896
},
  "geometry": {"coordinates":[72.75760099999999,20.016025],"type":"Point"}
}