{
  "type": "Feature",
  "properties": {
    "gn:admin1_code":"39.0",
    "gn:admin2_code":"061",
    "gn:asciiname":"Mall",
    "gn:country_code":"IN",
    "gn:dem":1528,
    "gn:feature_class":"P",
    "gn:feature_code":"PPL",
    "gn:name":"Mall",
    "gn:population":0,
    "gn:timezone":"Asia/Kolkata",
    "iso:country":"IN",
    "ks:ks_name":"Mal",
    "ks:ks_pop":78,
    "ks:ks_type":"VILLAGE",
    "name:ceb_x_preferred":[
        "Mall"
    ],
    "name:ces_x_preferred":[
        "Mall"
    ],
    "name:deu_x_preferred":[
        "Mall"
    ],
    "name:eng_x_preferred":[
        "Mal"
    ],
    "name:eng_x_variant":[
        "Mall"
    ],
    "name:est_x_preferred":[
        "Mall"
    ],
    "name:hin_x_preferred":[
        "\u092e\u0932"
    ],
    "name:ita_x_preferred":[
        "Mall"
    ],
    "name:nld_x_preferred":[
        "The Mall"
    ],
    "name:ron_x_preferred":[
        "Mall"
    ],
    "name:swe_x_preferred":[
        "Mall"
    ],
    "wof:name":"Mal",
    "wof:placetype":"locality",
    "wof:population":78
},
  "geometry": {"coordinates":[78.561177,29.970465],"type":"Point"}
}