{
  "type": "Feature",
  "properties": {
    "gn:admin1_code":"39.0",
    "gn:admin2_code":"061",
    "gn:asciiname":"Mall",
    "gn:country_code":"IN",
    "gn:dem":1528,
    "gn:feature_class":"P",
    "gn:feature_code":"PPL",
    "gn:name":"Mall",
    "gn:population":0,
    "gn:timezone":"Asia/Kolkata",
    "iso:country":"IN",
    "name:ceb_x_preferred":[
        "Mall"
    ],
    "name:ces_x_preferred":[
        "Mall"
    ],
    "name:deu_x_preferred":[
        "Mall"
    ],
    "name:est_x_preferred":[
        "Mall"
    ],
    "name:ita_x_preferred":[
        "Mall"
    ],
    "name:nld_x_preferred":[
        "The Mall"
    ],
    "name:ron_x_preferred":[
        "Mall"
    ],
    "name:swe_x_preferred":[
        "Mall"
    ],
    "wof:name":"Mall",
    "wof:placetype":"locality"
},
  "geometry": {"coordinates":[78.56154000000002,29.96974],"type":"Point"}
}