{
  "type": "Feature",
  "properties": {
    "iso:country":"IN",
    "ks:ks_name":"Kakrahi Urf Faridabad",
    "ks:ks_pop":758,
    "ks:ks_type":"VILLAGE",
    "name:eng_x_preferred":[
        "Kakrahi Urf Faridabad"
    ],
    "wof:name":"Kakrahi Urf Faridabad",
    "wof:placetype":"locality",
    "wof:population":758
},
  "geometry": {"coordinates":[85.076295,25.983361],"type":"Point"}
}