{
  "type": "Feature",
  "properties": {
    "iso:country":"IN",
    "ks:ks_name":"Charpara",
    "ks:ks_pop":365,
    "ks:ks_type":"HABITATION",
    "name:eng_x_preferred":[
        "Charpara"
    ],
    "wof:name":"Charpara",
    "wof:placetype":"locality",
    "wof:population":365
},
  "geometry": {"coordinates":[82.426151,22.422182],"type":"Point"}
}