{
  "type": "Feature",
  "properties": {
    "gn:admin1_code":"12.0",
    "gn:admin2_code":"1.0",
    "gn:asciiname":"Khumbrial",
    "gn:country_code":"IN",
    "gn:dem":1651,
    "gn:feature_class":"P",
    "gn:feature_code":"PPL",
    "gn:name":"Khumbrial",
    "gn:population":0,
    "gn:timezone":"Asia/Kolkata",
    "iso:country":"IN",
    "wof:name":"Khumbrial",
    "wof:placetype":"locality"
},
  "geometry": {"coordinates":[74.30558000000001,34.54079],"type":"Point"}
}