{
  "type": "Feature",
  "properties": {
    "iso:country":"IN",
    "ks:ks_name":"Kannimaanagar",
    "ks:ks_pop":16,
    "ks:ks_type":"HABITATION",
    "name:eng_x_preferred":[
        "Kannimaanagar"
    ],
    "wof:name":"Kannimaanagar",
    "wof:placetype":"locality",
    "wof:population":16
},
  "geometry": {"coordinates":[77.942498,10.686783],"type":"Point"}
}