{
  "type": "Feature",
  "properties": {
    "iso:country":"IN",
    "ks:ks_name":"Gossaigaon",
    "ks:ks_pop":3221,
    "ks:ks_type":"VILLAGE",
    "ks:ks_uagg_main":0,
    "name:eng_x_preferred":[
        "Gossaigaon"
    ],
    "wof:name":"Gossaigaon",
    "wof:placetype":"neighbourhood",
    "wof:population":3221
},
  "geometry": {"coordinates":[90.06595900000001,26.375409],"type":"Point"}
}