{
  "type": "Feature",
  "properties": {
    "iso:country":"IN",
    "ks:ks_name":"Bechana Family",
    "ks:ks_pop":9,
    "ks:ks_type":"HABITATION",
    "name:eng_x_preferred":[
        "Bechana Family"
    ],
    "wof:name":"Bechana Family",
    "wof:placetype":"locality",
    "wof:population":9
},
  "geometry": {"coordinates":[75.771389,12.377778],"type":"Point"}
}