{
  "type": "Feature",
  "properties": {
    "gn:admin1_code":"35.0",
    "gn:admin2_code":"429.0",
    "gn:asciiname":"Lidri",
    "gn:country_code":"IN",
    "gn:dem":367,
    "gn:feature_class":"P",
    "gn:feature_code":"PPL",
    "gn:name":"Lidri",
    "gn:population":0,
    "gn:timezone":"Asia/Kolkata",
    "iso:country":"IN",
    "wof:name":"Lidri",
    "wof:placetype":"locality"
},
  "geometry": {"coordinates":[80.36015,23.97158],"type":"Point"}
}