{
  "type": "Feature",
  "properties": {
    "iso:country":"IN",
    "ks:ks_alt_nam":"8 PSD-A",
    "ks:ks_name":"8 Psd-a",
    "ks:ks_pop":178,
    "ks:ks_type":"HABITATION",
    "name:eng_x_preferred":[
        "8 Psd-a"
    ],
    "wof:name":"8 Psd-a",
    "wof:placetype":"locality",
    "wof:population":178
},
  "geometry": {"coordinates":[72.917011,28.840831],"type":"Point"}
}