{
  "type": "Feature",
  "properties": {
    "gn:admin1_code":"35",
    "gn:admin2_code":"447.0",
    "gn:asciiname":"Chikhlar Khurd",
    "gn:country_code":"IN",
    "gn:dem":787,
    "gn:feature_class":"P",
    "gn:feature_code":"PPL",
    "gn:name":"Chikhl\u0101r Khurd",
    "gn:population":0,
    "gn:timezone":"Asia/Kolkata",
    "iso:country":"IN",
    "wof:name":"Chikhlar Khurd",
    "wof:placetype":"locality"
},
  "geometry": {"coordinates":[78.26399000000001,22.04133],"type":"Point"}
}