{
  "type": "Feature",
  "properties": {
    "iso:country":"IN",
    "ks:ks_name":"Bharisalata",
    "ks:ks_pop":124,
    "ks:ks_type":"HABITATION",
    "name:eng_x_preferred":[
        "Bharisalata"
    ],
    "wof:name":"Bharisalata",
    "wof:placetype":"locality",
    "wof:population":124
},
  "geometry": {"coordinates":[84.708708,22.362229],"type":"Point"}
}