{
  "type": "Feature",
  "properties": {
    "iso:country":"IN",
    "ks:ks_name":"Bhorad",
    "ks:ks_type":"VILLAGE",
    "name:eng_x_preferred":[
        "Bhorad"
    ],
    "wof:name":"Bhorad",
    "wof:placetype":"locality"
},
  "geometry": {"coordinates":[78.632204,19.895612],"type":"Point"}
}