{
  "type": "Feature",
  "properties": {
    "gn:admin1_code":"12",
    "gn:admin2_code":"12.0",
    "gn:asciiname":"Khanakah",
    "gn:country_code":"IN",
    "gn:dem":1676,
    "gn:feature_class":"P",
    "gn:feature_code":"PPL",
    "gn:name":"Kh\u0101nak\u0101h",
    "gn:population":0,
    "gn:timezone":"Asia/Kolkata",
    "iso:country":"IN",
    "wof:name":"Khanakah",
    "wof:placetype":"locality"
},
  "geometry": {"coordinates":[75.06104999999999,33.92028],"type":"Point"}
}