{
  "type": "Feature",
  "properties": {
    "gn:admin1_code":"19",
    "gn:admin2_code":"558.0",
    "gn:asciiname":"Dasarwadi",
    "gn:country_code":"IN",
    "gn:dem":629,
    "gn:feature_class":"P",
    "gn:feature_code":"PPL",
    "gn:name":"D\u0101sarw\u0101di",
    "gn:population":0,
    "gn:timezone":"Asia/Kolkata",
    "iso:country":"IN",
    "wof:name":"Dasarwadi",
    "wof:placetype":"locality"
},
  "geometry": {"coordinates":[76.94631,17.75574],"type":"Point"}
}