{
  "type": "Feature",
  "properties": {
    "gn:admin1_code":"2.0",
    "gn:admin2_code":"542.0",
    "gn:asciiname":"Akkurada",
    "gn:country_code":"IN",
    "gn:dem":43,
    "gn:feature_class":"P",
    "gn:feature_code":"PPL",
    "gn:name":"Akkur\u0101da",
    "gn:population":0,
    "gn:timezone":"Asia/Kolkata",
    "iso:country":"IN",
    "wof:name":"Akkurada",
    "wof:placetype":"locality"
},
  "geometry": {"coordinates":[83.99519000000002,18.51748],"type":"Point"}
}