{
  "type": "Feature",
  "properties": {
    "iso:country":"IN",
    "ks:ks_name":"Lahladpur Urf Rasulpur Alehdad",
    "ks:ks_pop":1175,
    "ks:ks_type":"VILLAGE",
    "name:eng_x_preferred":[
        "Lahladpur Urf Rasulpur Alehdad"
    ],
    "wof:name":"Lahladpur Urf Rasulpur Alehdad",
    "wof:placetype":"locality",
    "wof:population":1175
},
  "geometry": {"coordinates":[85.548838,25.879445],"type":"Point"}
}