{
  "type": "Feature",
  "properties": {
    "iso:country":"IN",
    "ks:ks_name":"Sankaryagudem",
    "ks:ks_pop":939,
    "ks:ks_type":"HABITATION",
    "name:eng_x_preferred":[
        "Sankaryagudem"
    ],
    "wof:name":"Sankaryagudem",
    "wof:placetype":"locality",
    "wof:population":939
},
  "geometry": {"coordinates":[82.068909,16.650043],"type":"Point"}
}