{
  "type": "Feature",
  "properties": {
    "gn:admin1_code":"36",
    "gn:admin2_code":"193.0",
    "gn:asciiname":"Khajuriapura",
    "gn:country_code":"IN",
    "gn:dem":71,
    "gn:feature_class":"P",
    "gn:feature_code":"PPL",
    "gn:name":"Khajuri\u0101pur\u0101",
    "gn:population":0,
    "gn:timezone":"Asia/Kolkata",
    "iso:country":"IN",
    "wof:name":"Khajuriapura",
    "wof:placetype":"locality"
},
  "geometry": {"coordinates":[83.75608000000003,25.86426],"type":"Point"}
}