{
  "type": "Feature",
  "properties": {
    "iso:country":"IN",
    "ks:ks_name":"Kannamangalam",
    "ks:ks_type":"VILLAGE",
    "name:eng_x_preferred":[
        "Kannamangalam"
    ],
    "wof:name":"Kannamangalam",
    "wof:placetype":"locality"
},
  "geometry": {"coordinates":[76.521157,9.241931],"type":"Point"}
}