{
  "type": "Feature",
  "properties": {
    "gn:admin1_code":"24.0",
    "gn:admin2_code":"111.0",
    "gn:asciiname":"Joshi ki Dhani",
    "gn:country_code":"IN",
    "gn:dem":323,
    "gn:feature_class":"P",
    "gn:feature_code":"PPL",
    "gn:name":"Joshi ki Dh\u0101ni",
    "gn:population":0,
    "gn:timezone":"Asia/Kolkata",
    "iso:country":"IN",
    "wof:name":"Joshi ki Dhani",
    "wof:placetype":"locality"
},
  "geometry": {"coordinates":[75.05438000000002,28.05805],"type":"Point"}
}