{
  "type": "Feature",
  "properties": {
    "gn:admin1_code":"24",
    "gn:admin2_code":"103.0",
    "gn:asciiname":"Aryanagar",
    "gn:country_code":"IN",
    "gn:dem":276,
    "gn:feature_class":"P",
    "gn:feature_code":"PPL",
    "gn:name":"\u0100ry\u0101nagar",
    "gn:population":0,
    "gn:timezone":"Asia/Kolkata",
    "iso:country":"IN",
    "name:und_x_variant":[
        "\u0100ry\u0101nagar",
        "Sur\u0101na ka B\u0101s"
    ],
    "wof:name":"Aryanagar",
    "wof:placetype":"locality"
},
  "geometry": {"coordinates":[75.82113000000003,28.38359],"type":"Point"}
}