{
  "type": "Feature",
  "properties": {
    "iso:country":"IN",
    "ks:ks_name":"Tumari Koppa",
    "ks:ks_pop":66,
    "ks:ks_type":"VILLAGE",
    "name:eng_x_preferred":[
        "Tumari Koppa"
    ],
    "wof:name":"Tumari Koppa",
    "wof:placetype":"locality",
    "wof:population":66
},
  "geometry": {"coordinates":[75.16854600000001,14.060313],"type":"Point"}
}