{
  "type": "Feature",
  "properties": {
    "iso:country":"IN",
    "ks:ks_name":"Harsing",
    "ks:ks_pop":206,
    "ks:ks_type":"HABITATION",
    "name:eng_x_preferred":[
        "Harsing"
    ],
    "wof:name":"Harsing",
    "wof:placetype":"locality",
    "wof:population":206
},
  "geometry": {"coordinates":[92.219273,23.860401],"type":"Point"}
}