{
  "type": "Feature",
  "properties": {
    "gn:admin1_code":"19.0",
    "gn:admin2_code":"584.0",
    "gn:asciiname":"Narasegaudandoddi",
    "gn:country_code":"IN",
    "gn:dem":674,
    "gn:feature_class":"P",
    "gn:feature_code":"PPL",
    "gn:name":"Narasegaudandoddi",
    "gn:population":0,
    "gn:timezone":"Asia/Kolkata",
    "iso:country":"IN",
    "wof:name":"Narasegaudandoddi",
    "wof:placetype":"locality"
},
  "geometry": {"coordinates":[77.3815,12.48453],"type":"Point"}
}