{
  "type": "Feature",
  "properties": {
    "gn:admin1_code":"19.0",
    "gn:admin2_code":"571.0",
    "gn:asciiname":"Kerebandipalya",
    "gn:country_code":"IN",
    "gn:dem":811,
    "gn:feature_class":"P",
    "gn:feature_code":"PPL",
    "gn:name":"Kerebandip\u0101lya",
    "gn:population":0,
    "gn:timezone":"Asia/Kolkata",
    "iso:country":"IN",
    "wof:name":"Kerebandipalya",
    "wof:placetype":"locality"
},
  "geometry": {"coordinates":[76.39227,13.34736],"type":"Point"}
}