{
  "type": "Feature",
  "properties": {
    "iso:country":"IN",
    "ks:ks_alt_nam":"Mushar tola",
    "ks:ks_name":"Mushar Tola",
    "ks:ks_pop":672,
    "ks:ks_type":"HABITATION",
    "name:eng_x_preferred":[
        "Mushar Tola"
    ],
    "wof:name":"Mushar Tola",
    "wof:placetype":"locality",
    "wof:population":672
},
  "geometry": {"coordinates":[87.30755600000001,26.184057],"type":"Point"}
}