{
  "type": "Feature",
  "properties": {
    "gn:admin1_code":"24.0",
    "gn:admin2_code":"119.0",
    "gn:asciiname":"Beonja",
    "gn:country_code":"IN",
    "gn:dem":422,
    "gn:feature_class":"P",
    "gn:feature_code":"PPL",
    "gn:name":"Beonja",
    "gn:population":0,
    "gn:timezone":"Asia/Kolkata",
    "iso:country":"IN",
    "wof:name":"Beonja",
    "wof:placetype":"neighbourhood"
},
  "geometry": {"coordinates":[74.77589,26.31149],"type":"Point"}
}