{
  "type": "Feature",
  "properties": {
    "iso:country":"IN",
    "ks:ks_name":"Ragam Corner",
    "ks:ks_pop":1571,
    "ks:ks_type":"HABITATION",
    "ks:ks_uagg_main":0,
    "name:eng_x_preferred":[
        "Ragam Corner"
    ],
    "wof:name":"Ragam Corner",
    "wof:placetype":"neighbourhood",
    "wof:population":1571
},
  "geometry": {"coordinates":[76.403082,10.898941],"type":"Point"}
}