{
  "type": "Feature",
  "properties": {
    "iso:country":"IN",
    "ks:ks_name":"Manjhladih",
    "ks:ks_pop":250,
    "ks:ks_type":"VILLAGE",
    "name:eng_x_preferred":[
        "Manjhladih"
    ],
    "wof:name":"Manjhladih",
    "wof:placetype":"locality",
    "wof:population":250
},
  "geometry": {"coordinates":[85.901945,24.543466],"type":"Point"}
}