{
  "type": "Feature",
  "properties": {
    "iso:country":"IN",
    "ks:ks_name":"Adeguli",
    "ks:ks_pop":60,
    "ks:ks_type":"HABITATION",
    "name:eng_x_preferred":[
        "Adeguli"
    ],
    "wof:name":"Adeguli",
    "wof:placetype":"locality",
    "wof:population":60
},
  "geometry": {"coordinates":[74.74658100000001,14.636263],"type":"Point"}
}