{
  "type": "Feature",
  "properties": {
    "gn:admin1_code":"36.0",
    "gn:admin2_code":"153.0",
    "gn:asciiname":"Nardi",
    "gn:country_code":"IN",
    "gn:dem":155,
    "gn:feature_class":"P",
    "gn:feature_code":"PPL",
    "gn:name":"Nardi",
    "gn:population":0,
    "gn:timezone":"Asia/Kolkata",
    "iso:country":"IN",
    "ks:ks_name":"Nardi",
    "ks:ks_pop":1296,
    "ks:ks_type":"VILLAGE",
    "ks:ks_uagg_main":0,
    "name:eng_x_preferred":[
        "Nardi"
    ],
    "name:ita_x_preferred":[
        "Nardi"
    ],
    "wof:name":"Nardi",
    "wof:placetype":"neighbourhood",
    "wof:population":1296
},
  "geometry": {"coordinates":[80.180603,27.804453],"type":"Point"}
}