{
  "type": "Feature",
  "properties": {
    "iso:country":"IN",
    "ks:ks_alt_nam":"Jamuni\u0101t\u0101nr",
    "ks:ks_name":"Jamuniatanr",
    "ks:ks_pop":537,
    "ks:ks_type":"VILLAGE",
    "ks:ks_uagg_main":0,
    "name:eng_x_preferred":[
        "Jamuniatanr"
    ],
    "name:eng_x_variant":[
        "Jamuni\u0101t\u0101nr"
    ],
    "wof:name":"Jamuniatanr",
    "wof:placetype":"neighbourhood",
    "wof:population":537
},
  "geometry": {"coordinates":[86.062524,24.588454],"type":"Point"}
}