{
  "type": "Feature",
  "properties": {
    "iso:country":"IN",
    "ks:ks_alt_nam":"School falia",
    "ks:ks_name":"School Falia",
    "ks:ks_pop":466,
    "ks:ks_type":"HABITATION",
    "ks:ks_uagg_main":0,
    "name:eng_x_preferred":[
        "School Falia"
    ],
    "wof:name":"School Falia",
    "wof:placetype":"neighbourhood",
    "wof:population":466
},
  "geometry": {"coordinates":[72.8165,20.983722],"type":"Point"}
}