{
  "type": "Feature",
  "properties": {
    "gn:admin1_code":"2.0",
    "gn:admin2_code":"551.0",
    "gn:asciiname":"Reddivaripalle",
    "gn:country_code":"IN",
    "gn:dem":306,
    "gn:feature_class":"P",
    "gn:feature_code":"PPL",
    "gn:name":"Reddiv\u0101ripalle",
    "gn:population":0,
    "gn:timezone":"Asia/Kolkata",
    "iso:country":"IN",
    "ks:ks_name":"Reddivaripalli",
    "ks:ks_pop":126,
    "ks:ks_type":"HABITATION",
    "ks:ks_uagg_main":0,
    "name:eng_x_preferred":[
        "Reddivaripalli"
    ],
    "wof:name":"Reddivaripalli",
    "wof:placetype":"neighbourhood",
    "wof:population":126
},
  "geometry": {"coordinates":[78.82302199999999,14.101699],"type":"Point"}
}