{
  "type": "Feature",
  "properties": {
    "gn:admin1_code":"36.0",
    "gn:admin2_code":"149.0",
    "gn:asciiname":"Qadirabad",
    "gn:country_code":"IN",
    "gn:dem":161,
    "gn:feature_class":"P",
    "gn:feature_code":"PPL",
    "gn:name":"Q\u0101dir\u0101b\u0101d",
    "gn:population":0,
    "gn:timezone":"Asia/Kolkata",
    "iso:country":"IN",
    "wof:name":"Qadirabad",
    "wof:placetype":"locality"
},
  "geometry": {"coordinates":[79.29897,28.09701],"type":"Point"}
}