{
  "type": "Feature",
  "properties": {
    "iso:country":"IN",
    "ks:ks_name":"Dhodgapara",
    "ks:ks_pop":398,
    "ks:ks_type":"HABITATION",
    "name:eng_x_preferred":[
        "Dhodgapara"
    ],
    "wof:name":"Dhodgapara",
    "wof:placetype":"locality",
    "wof:population":398
},
  "geometry": {"coordinates":[81.648439,19.936496],"type":"Point"}
}