{
  "type": "Feature",
  "properties": {
    "iso:country":"IN",
    "ks:ks_name":"Nazirpur",
    "ks:ks_pop":1056,
    "ks:ks_type":"HABITATION",
    "ks:ks_uagg_main":0,
    "name:eng_x_preferred":[
        "Nazirpur"
    ],
    "wof:name":"Nazirpur",
    "wof:placetype":"neighbourhood",
    "wof:population":1056
},
  "geometry": {"coordinates":[88.493341,24.149244],"type":"Point"}
}