{
  "type": "Feature",
  "properties": {
    "iso:country":"IN",
    "ks:ks_name":"Painda",
    "ks:ks_pop":88,
    "ks:ks_type":"VILLAGE",
    "name:eng_x_preferred":[
        "Painda"
    ],
    "wof:name":"Painda",
    "wof:placetype":"locality",
    "wof:population":88
},
  "geometry": {"coordinates":[84.33874,19.166155],"type":"Point"}
}