{
  "type": "Feature",
  "properties": {
    "iso:country":"IN",
    "ks:ks_name":"Nawadih Parthumanjhi",
    "ks:ks_pop":821,
    "ks:ks_type":"VILLAGE",
    "name:eng_x_preferred":[
        "Nawadih Parthumanjhi"
    ],
    "wof:name":"Nawadih Parthumanjhi",
    "wof:placetype":"locality",
    "wof:population":821
},
  "geometry": {"coordinates":[87.391485,25.155642],"type":"Point"}
}