{
  "type": "Feature",
  "properties": {
    "gn:admin1_code":"36",
    "gn:admin2_code":"194.0",
    "gn:asciiname":"Sahanpur",
    "gn:country_code":"IN",
    "gn:dem":88,
    "gn:feature_class":"P",
    "gn:feature_code":"PPL",
    "gn:name":"S\u0101hanpur",
    "gn:population":0,
    "gn:timezone":"Asia/Kolkata",
    "iso:country":"IN",
    "name:bpy_x_preferred":[
        "\u09b8\u09be\u09b9\u09be\u09a8\u09aa\u09c1\u09b0"
    ],
    "name:ita_x_preferred":[
        "Sahanpur"
    ],
    "name:msa_x_preferred":[
        "Sahanpur"
    ],
    "name:nld_x_preferred":[
        "Sahanpur"
    ],
    "name:pol_x_preferred":[
        "Sahanpur"
    ],
    "name:por_x_preferred":[
        "Sahanpur"
    ],
    "name:urd_x_preferred":[
        "\u0633\u06c1\u0627\u0646\u067e\u0648\u0631"
    ],
    "name:vie_x_preferred":[
        "Sahanpur"
    ],
    "name:zho_x_preferred":[
        "\u8428\u6c49\u666e\u5c14"
    ],
    "wof:name":"Sahanpur",
    "wof:placetype":"locality"
},
  "geometry": {"coordinates":[82.55769000000002,25.48326],"type":"Point"}
}