{
  "type": "Feature",
  "properties": {
    "iso:country":"IN",
    "ks:ks_name":"Banjarsahi",
    "ks:ks_pop":20,
    "ks:ks_type":"HABITATION",
    "name:eng_x_preferred":[
        "Banjarsahi"
    ],
    "wof:name":"Banjarsahi",
    "wof:placetype":"locality",
    "wof:population":20
},
  "geometry": {"coordinates":[84.534097,20.158315],"type":"Point"}
}