{
  "type": "Feature",
  "properties": {
    "iso:country":"IN",
    "ks:ks_name":"Rahakhandol",
    "ks:ks_pop":0,
    "ks:ks_type":"VILLAGE",
    "name:eng_x_preferred":[
        "Rahakhandol"
    ],
    "wof:name":"Rahakhandol",
    "wof:placetype":"locality",
    "wof:population":0
},
  "geometry": {"coordinates":[86.247823,19.914932],"type":"Point"}
}