{
  "type": "Feature",
  "properties": {
    "gn:admin1_code":"36.0",
    "gn:admin2_code":"184.0",
    "gn:asciiname":"Bhatgaon",
    "gn:country_code":"IN",
    "gn:dem":95,
    "gn:feature_class":"P",
    "gn:feature_code":"PPL",
    "gn:name":"Bhatg\u0101on",
    "gn:population":0,
    "gn:timezone":"Asia/Kolkata",
    "iso:country":"IN",
    "ks:ks_alt_nam":"Bhatg\u0101on",
    "ks:ks_name":"Bhatgaon",
    "ks:ks_type":"VILLAGE",
    "ks:ks_uagg_main":0,
    "name:cat_x_preferred":[
        "Bhatgaon"
    ],
    "name:eng_x_preferred":[
        "Bhatgaon"
    ],
    "name:eng_x_variant":[
        "Bhatg\u0101on"
    ],
    "wof:name":"Bhatgaon",
    "wof:placetype":"neighbourhood"
},
  "geometry": {"coordinates":[82.655053,27.171713],"type":"Point"}
}