{
  "type": "Feature",
  "properties": {
    "gn:country":"IN",
    "gn:fcode":"PPL",
    "gn:pop":65598,
    "iso:country":"IN",
    "name:ben_x_preferred":[
        "\u099a\u09cb\u09aa\u09a6\u09be"
    ],
    "name:bpy_x_preferred":[
        "\u099a\u09cb\u09aa\u09a6\u09be"
    ],
    "name:bul_x_preferred":[
        "\u0427\u043e\u043f\u0434\u0430"
    ],
    "name:deu_x_preferred":[
        "Chopda"
    ],
    "name:eng_x_preferred":[
        "Chopda"
    ],
    "name:fra_x_preferred":[
        "Chopda"
    ],
    "name:guj_x_preferred":[
        "\u0a9a\u0acb\u0aaa\u0aa1\u0abe"
    ],
    "name:ita_x_preferred":[
        "Chopda"
    ],
    "name:jpn_x_preferred":[
        "\u30c1\u30e7\u30c3\u30d7\u30c0"
    ],
    "name:kan_x_preferred":[
        "\u0c9a\u0ccb\u0caa\u0ccd\u0ca6"
    ],
    "name:kor_x_preferred":[
        "\ucd19\ub2e4"
    ],
    "name:mar_x_preferred":[
        "\u091a\u094b\u092a\u0921\u093e"
    ],
    "name:msa_x_preferred":[
        "Chopda"
    ],
    "name:nan_x_preferred":[
        "Chopda"
    ],
    "name:new_x_preferred":[
        "\u091a\u094b\u092a\u094d\u0926\u093e"
    ],
    "name:nld_x_preferred":[
        "Chopda"
    ],
    "name:por_x_preferred":[
        "Chopda"
    ],
    "name:rus_x_preferred":[
        "\u0427\u043e\u043f\u0434\u0430"
    ],
    "name:spa_x_preferred":[
        "Chopda"
    ],
    "name:swe_x_preferred":[
        "Chopda"
    ],
    "name:tam_x_preferred":[
        "\u0b9a\u0bcb\u0baa\u0bcd\u0b9f\u0bbe"
    ],
    "name:tel_x_preferred":[
        "\u0c1a\u0c4b\u0c2a\u0c4d\u0c21"
    ],
    "name:urd_x_preferred":[
        "\u0686\u0648\u067e\u0691\u0627"
    ],
    "name:vie_x_preferred":[
        "Chopda"
    ],
    "name:zho_x_preferred":[
        "\u4e54\u666e\u8fbe"
    ],
    "qs:name":"Chopda",
    "qs:name_adm0":"India",
    "qs:name_adm1":"Maharashtra",
    "qs:photos_9r":0,
    "qs:photos_sr":0,
    "qs:placetype":"Town",
    "qs:pop_sr":"8",
    "wd:wordcount":735,
    "wof:name":"Chopda",
    "wof:placetype":"locality",
    "wof:population":65598
},
  "geometry": {"coordinates":[75.29819000000001,21.24706],"type":"Point"}
}