{
  "type": "Feature",
  "properties": {
    "iso:country":"IN",
    "ks:ks_alt_nam":"Puthiakhat Part II",
    "ks:ks_name":"Puthiakhat Part Ii",
    "ks:ks_pop":400,
    "ks:ks_type":"HABITATION",
    "name:eng_x_preferred":[
        "Puthiakhat Part Ii"
    ],
    "wof:name":"Puthiakhat Part Ii",
    "wof:placetype":"locality",
    "wof:population":400
},
  "geometry": {"coordinates":[92.009214,26.591031],"type":"Point"}
}