{
  "type": "Feature",
  "properties": {
    "gn:admin1_code":"2.0",
    "gn:asciiname":"Arlapada",
    "gn:country_code":"IN",
    "gn:dem":538,
    "gn:feature_class":"P",
    "gn:feature_code":"PPL",
    "gn:name":"Arlap\u0101da",
    "gn:population":0,
    "gn:timezone":"Asia/Kolkata",
    "iso:country":"IN",
    "ks:ks_name":"Aralipada",
    "ks:ks_pop":92,
    "ks:ks_type":"VILLAGE",
    "name:eng_x_preferred":[
        "Aralipada"
    ],
    "name:eng_x_variant":[
        "Arlapada"
    ],
    "wof:name":"Aralipada",
    "wof:placetype":"locality",
    "wof:population":92
},
  "geometry": {"coordinates":[82.373428,18.38773],"type":"Point"}
}