{
  "type": "Feature",
  "properties": {
    "gn:admin1_code":"11",
    "gn:admin2_code":"27.0",
    "gn:asciiname":"Diar",
    "gn:country_code":"IN",
    "gn:dem":1224,
    "gn:feature_class":"P",
    "gn:feature_code":"PPL",
    "gn:name":"Di\u0101r",
    "gn:population":0,
    "gn:timezone":"Asia/Kolkata",
    "iso:country":"IN",
    "name:deu_x_preferred":[
        "Diar Khodro"
    ],
    "name:fas_x_preferred":[
        "\u062f\u06cc\u0627\u0631 \u062e\u0648\u062f\u0631\u0648"
    ],
    "wof:name":"Diar",
    "wof:placetype":"locality"
},
  "geometry": {"coordinates":[76.92882,31.6717],"type":"Point"}
}