{
  "type": "Feature",
  "properties": {
    "gn:admin1_code":"11.0",
    "gn:admin2_code":"32.0",
    "gn:asciiname":"Sanog",
    "gn:country_code":"IN",
    "gn:dem":2886,
    "gn:feature_class":"P",
    "gn:feature_code":"PPL",
    "gn:name":"Sanog",
    "gn:population":0,
    "gn:timezone":"Asia/Kolkata",
    "iso:country":"IN",
    "wof:name":"Sanog",
    "wof:placetype":"locality"
},
  "geometry": {"coordinates":[77.41159,30.8835],"type":"Point"}
}