{
  "type": "Feature",
  "properties": {
    "gn:admin1_code":"2.0",
    "gn:admin2_code":"553",
    "gn:asciiname":"Ellanuru",
    "gn:country_code":"IN",
    "gn:dem":237,
    "gn:feature_class":"P",
    "gn:feature_code":"PPL",
    "gn:name":"Ellan\u016bru",
    "gn:population":0,
    "gn:timezone":"Asia/Kolkata",
    "iso:country":"IN",
    "name:und_x_variant":[
        "Yellanur",
        "Ellan\u016bru"
    ],
    "wof:name":"Ellanuru",
    "wof:placetype":"neighbourhood"
},
  "geometry": {"coordinates":[78.07516,14.69783],"type":"Point"}
}