{
  "type": "Feature",
  "properties": {
    "gn:admin1_code":"36.0",
    "gn:admin2_code":"134.0",
    "gn:asciiname":"Naurangabad",
    "gn:country_code":"IN",
    "gn:dem":237,
    "gn:feature_class":"P",
    "gn:feature_code":"PPL",
    "gn:name":"Naurang\u0101b\u0101d",
    "gn:population":0,
    "gn:timezone":"Asia/Kolkata",
    "iso:country":"IN",
    "name:und_x_variant":[
        "Naurang\u0101b\u0101d",
        "Allahpur"
    ],
    "wof:name":"Naurangabad",
    "wof:placetype":"locality"
},
  "geometry": {"coordinates":[78.51850999999998,29.30226],"type":"Point"}
}