{
  "type": "Feature",
  "properties": {
    "iso:country":"IN",
    "ks:ks_name":"Ranipura",
    "ks:ks_pop":169,
    "ks:ks_type":"HABITATION",
    "name:eng_x_preferred":[
        "Ranipura"
    ],
    "wof:name":"Ranipura",
    "wof:placetype":"locality",
    "wof:population":169
},
  "geometry": {"coordinates":[73.84480600000001,22.713472],"type":"Point"}
}