{
  "type": "Feature",
  "properties": {
    "iso:country":"IN",
    "ks:ks_name":"Manoharganj",
    "ks:ks_pop":392,
    "ks:ks_type":"VILLAGE",
    "ks:ks_uagg_main":0,
    "name:eng_x_preferred":[
        "Manoharganj"
    ],
    "wof:name":"Manoharganj",
    "wof:placetype":"neighbourhood",
    "wof:population":392
},
  "geometry": {"coordinates":[87.662904,22.423415],"type":"Point"}
}