{
  "type": "Feature",
  "properties": {
    "iso:country":"IN",
    "ks:ks_name":"Bara Bhaki",
    "ks:ks_pop":547,
    "ks:ks_type":"VILLAGE",
    "name:eng_x_preferred":[
        "Bara Bhaki"
    ],
    "wof:name":"Bara Bhaki",
    "wof:placetype":"locality",
    "wof:population":547
},
  "geometry": {"coordinates":[87.499099,24.316922],"type":"Point"}
}