{
  "type": "Feature",
  "properties": {
    "gn:country":"IN",
    "gn:fcode":"PPL",
    "gn:pop":47419,
    "iso:country":"IN",
    "name:ceb_x_preferred":[
        "Gudalur"
    ],
    "name:eng_x_preferred":[
        "Gudalur"
    ],
    "name:fra_x_preferred":[
        "Gudalur"
    ],
    "name:ita_x_preferred":[
        "Gudalur"
    ],
    "name:jpn_x_preferred":[
        "\u30af\u30fc\u30c0\u30eb\u30fc\u30eb"
    ],
    "name:msa_x_preferred":[
        "Gudalur"
    ],
    "name:nld_x_preferred":[
        "Gudalur"
    ],
    "name:spa_x_preferred":[
        "Gudalur"
    ],
    "name:swe_x_preferred":[
        "Gudalur"
    ],
    "name:tam_x_preferred":[
        "\u0b95\u0bc2\u0b9f\u0bb2\u0bc2\u0bb0\u0bcd"
    ],
    "name:unk_x_variant":[
        "G\u016bdal\u016br"
    ],
    "qs:name":"Gudalur",
    "qs:name_adm0":"India",
    "qs:name_adm1":"Tamil Nadu",
    "qs:photos":290,
    "qs:photos_1k":59,
    "qs:photos_9k":1,
    "qs:photos_9r":4,
    "qs:photos_all":290,
    "qs:photos_sr":5,
    "qs:placetype":"Town",
    "qs:pop_sr":"7",
    "wd:wordcount":17,
    "wof:name":"Gudalur",
    "wof:placetype":"locality",
    "wof:population":47419
},
  "geometry": {"coordinates":[77.24951,9.67826],"type":"Point"}
}