{
  "type": "Feature",
  "properties": {
    "iso:country":"IN",
    "ks:ks_alt_nam":"LIMGAON RD.WASTI",
    "ks:ks_name":"Limgaon Rd.wasti",
    "ks:ks_pop":357,
    "ks:ks_type":"HABITATION",
    "name:eng_x_preferred":[
        "Limgaon Rd.wasti"
    ],
    "wof:name":"Limgaon Rd.wasti",
    "wof:placetype":"locality",
    "wof:population":357
},
  "geometry": {"coordinates":[74.47385800000001,19.98795],"type":"Point"}
}