{
  "type": "Feature",
  "properties": {
    "iso:country":"IN",
    "ks:ks_name":"Kadalihanda",
    "ks:ks_pop":614,
    "ks:ks_type":"VILLAGE",
    "ks:ks_uagg_main":0,
    "name:eng_x_preferred":[
        "Kadalihanda"
    ],
    "wof:name":"Kadalihanda",
    "wof:placetype":"neighbourhood",
    "wof:population":614
},
  "geometry": {"coordinates":[87.09839599999999,21.66292],"type":"Point"}
}