{
  "type": "Feature",
  "properties": {
    "iso:country":"IN",
    "ks:ks_alt_nam":"Mavinchodu sc colony",
    "ks:ks_name":"Mavinchodu Sc Colony",
    "ks:ks_pop":398,
    "ks:ks_type":"HABITATION",
    "name:eng_x_preferred":[
        "Mavinchodu Sc Colony"
    ],
    "wof:name":"Mavinchodu Sc Colony",
    "wof:placetype":"locality",
    "wof:population":398
},
  "geometry": {"coordinates":[76.050568,11.420619],"type":"Point"}
}