{
  "type": "Feature",
  "properties": {
    "iso:country":"IN",
    "ks:ks_name":"Mukhalis Patti",
    "ks:ks_pop":262,
    "ks:ks_type":"VILLAGE",
    "name:eng_x_preferred":[
        "Mukhalis Patti"
    ],
    "wof:name":"Mukhalis Patti",
    "wof:placetype":"locality",
    "wof:population":262
},
  "geometry": {"coordinates":[83.301186,26.300112],"type":"Point"}
}