{
  "type": "Feature",
  "properties": {
    "gn:admin1_code":"19.0",
    "gn:admin2_code":"576.0",
    "gn:asciiname":"Chikanahalli",
    "gn:country_code":"IN",
    "gn:dem":933,
    "gn:feature_class":"P",
    "gn:feature_code":"PPL",
    "gn:name":"Chikanahalli",
    "gn:population":0,
    "gn:timezone":"Asia/Kolkata",
    "iso:country":"IN",
    "ks:ks_name":"Cheekanalli",
    "ks:ks_pop":96,
    "ks:ks_type":"VILLAGE",
    "name:eng_x_preferred":[
        "Cheekanalli"
    ],
    "name:eng_x_variant":[
        "Chikanahalli"
    ],
    "wof:name":"Cheekanalli",
    "wof:placetype":"locality",
    "wof:population":96
},
  "geometry": {"coordinates":[75.858554,12.729933],"type":"Point"}
}