{
  "type": "Feature",
  "properties": {
    "iso:country":"IN",
    "ks:ks_name":"Ermekalu",
    "ks:ks_pop":53,
    "ks:ks_type":"HABITATION",
    "name:eng_x_preferred":[
        "Ermekalu"
    ],
    "wof:name":"Ermekalu",
    "wof:placetype":"locality",
    "wof:population":53
},
  "geometry": {"coordinates":[75.533889,12.401111],"type":"Point"}
}