{
  "type": "Feature",
  "properties": {
    "iso:country":"IN",
    "ks:ks_alt_nam":"bhandariya",
    "ks:ks_name":"Bhandariya",
    "ks:ks_pop":1064,
    "ks:ks_type":"HABITATION",
    "name:eng_x_preferred":[
        "Bhandariya"
    ],
    "wof:name":"Bhandariya",
    "wof:placetype":"locality",
    "wof:population":1064
},
  "geometry": {"coordinates":[71.24767799999999,24.775794],"type":"Point"}
}