{
  "type": "Feature",
  "properties": {
    "iso:country":"IN",
    "ks:ks_name":"Donne Hosuru",
    "ks:ks_pop":260,
    "ks:ks_type":"HABITATION",
    "name:eng_x_preferred":[
        "Donne Hosuru"
    ],
    "wof:name":"Donne Hosuru",
    "wof:placetype":"locality",
    "wof:population":260
},
  "geometry": {"coordinates":[75.248552,14.166305],"type":"Point"}
}