{
  "type": "Feature",
  "properties": {
    "iso:country":"IN",
    "ks:ks_name":"Kalighai",
    "ks:ks_pop":235,
    "ks:ks_type":"HABITATION",
    "name:eng_x_preferred":[
        "Kalighai"
    ],
    "wof:name":"Kalighai",
    "wof:placetype":"locality",
    "wof:population":235
},
  "geometry": {"coordinates":[85.952352,21.519903],"type":"Point"}
}