{
  "type": "Feature",
  "properties": {
    "iso:country":"IN",
    "ks:ks_name":"Seethapuram",
    "ks:ks_pop":338,
    "ks:ks_type":"VILLAGE",
    "ks:ks_uagg_main":0,
    "name:eng_x_preferred":[
        "Seethapuram"
    ],
    "wof:name":"Seethapuram",
    "wof:placetype":"neighbourhood",
    "wof:population":338
},
  "geometry": {"coordinates":[84.40480700000001,18.708891],"type":"Point"}
}