{
  "type": "Feature",
  "properties": {
    "iso:country":"IN",
    "ks:ks_name":"Pambaipadiyur",
    "ks:ks_pop":982,
    "ks:ks_type":"HABITATION",
    "ks:ks_uagg_main":0,
    "name:eng_x_preferred":[
        "Pambaipadiyur"
    ],
    "wof:name":"Pambaipadiyur",
    "wof:placetype":"locality",
    "wof:population":982
},
  "geometry": {"coordinates":[79.35861,10.928297],"type":"Point"}
}