{
  "type": "Feature",
  "properties": {
    "iso:country":"IN",
    "ks:ks_name":"Halavirathota",
    "ks:ks_pop":180,
    "ks:ks_type":"HABITATION",
    "name:eng_x_preferred":[
        "Halavirathota"
    ],
    "wof:name":"Halavirathota",
    "wof:placetype":"locality",
    "wof:population":180
},
  "geometry": {"coordinates":[74.728787,13.652731],"type":"Point"}
}