{
  "type": "Feature",
  "properties": {
    "iso:country":"IN",
    "ks:ks_name":"Pul Par",
    "ks:ks_pop":172,
    "ks:ks_type":"HABITATION",
    "name:eng_x_preferred":[
        "Pul Par"
    ],
    "wof:name":"Pul Par",
    "wof:placetype":"locality",
    "wof:population":172
},
  "geometry": {"coordinates":[85.178932,25.27145],"type":"Point"}
}