{
  "type": "Feature",
  "properties": {
    "iso:country":"IN",
    "ks:ks_alt_nam":"R.Doddavaram",
    "ks:ks_name":"R.doddavaram",
    "ks:ks_pop":217,
    "ks:ks_type":"HABITATION",
    "name:eng_x_preferred":[
        "R.doddavaram"
    ],
    "wof:name":"R.doddavaram",
    "wof:placetype":"locality",
    "wof:population":217
},
  "geometry": {"coordinates":[82.104598,17.652684],"type":"Point"}
}