{
  "type": "Feature",
  "properties": {
    "gn:admin1_code":"12.0",
    "gn:admin2_code":"022",
    "gn:asciiname":"Kothe Manhasan",
    "gn:country_code":"IN",
    "gn:dem":316,
    "gn:feature_class":"P",
    "gn:feature_code":"PPL",
    "gn:name":"Kothe Manh\u0101s\u0101n",
    "gn:population":0,
    "gn:timezone":"Asia/Kolkata",
    "iso:country":"IN",
    "wof:name":"Kothe Manhasan",
    "wof:placetype":"locality"
},
  "geometry": {"coordinates":[74.95833,32.56389],"type":"Point"}
}