{
  "type": "Feature",
  "properties": {
    "gn:admin1_code":"39.0",
    "gn:admin2_code":"64.0",
    "gn:asciiname":"Taleshwar",
    "gn:country_code":"IN",
    "gn:dem":1213,
    "gn:feature_class":"P",
    "gn:feature_code":"PPL",
    "gn:name":"T\u0101leshwar",
    "gn:population":0,
    "gn:timezone":"Asia/Kolkata",
    "iso:country":"IN",
    "ks:ks_alt_nam":"T\u0101leshwar",
    "ks:ks_name":"Taleshwar",
    "ks:ks_type":"VILLAGE",
    "name:eng_x_preferred":[
        "Taleshwar"
    ],
    "name:eng_x_variant":[
        "T\u0101leshwar"
    ],
    "wof:name":"Taleshwar",
    "wof:placetype":"locality"
},
  "geometry": {"coordinates":[79.19976,29.917858],"type":"Point"}
}