{
  "type": "Feature",
  "properties": {
    "iso:country":"IN",
    "ks:ks_alt_nam":"M\u0101lbhuin",
    "ks:ks_name":"Malbhuin",
    "ks:ks_pop":118,
    "ks:ks_type":"VILLAGE",
    "name:eng_x_preferred":[
        "Malbhuin"
    ],
    "name:eng_x_variant":[
        "M\u0101lbhuin"
    ],
    "wof:name":"Malbhuin",
    "wof:placetype":"locality",
    "wof:population":118
},
  "geometry": {"coordinates":[84.361457,20.474745],"type":"Point"}
}