{
  "type": "Feature",
  "properties": {
    "iso:country":"IN",
    "ks:ks_name":"Kirundadu",
    "ks:ks_pop":1032,
    "ks:ks_type":"VILLAGE",
    "name:eng_x_preferred":[
        "Kirundadu"
    ],
    "wof:name":"Kirundadu",
    "wof:placetype":"locality",
    "wof:population":1032
},
  "geometry": {"coordinates":[75.69414,12.265616],"type":"Point"}
}