{
  "type": "Feature",
  "properties": {
    "iso:country":"IN",
    "ks:ks_name":"Bhaudiha",
    "ks:ks_pop":0,
    "ks:ks_type":"VILLAGE",
    "name:eng_x_preferred":[
        "Bhaudiha"
    ],
    "wof:name":"Bhaudiha",
    "wof:placetype":"locality",
    "wof:population":0
},
  "geometry": {"coordinates":[84.475983,24.773453],"type":"Point"}
}