{
  "type": "Feature",
  "properties": {
    "gn:admin1_code":"36.0",
    "gn:admin2_code":"136.0",
    "gn:asciiname":"Tuntpuri",
    "gn:country_code":"IN",
    "gn:dem":205,
    "gn:feature_class":"P",
    "gn:feature_code":"PPL",
    "gn:name":"Tuntpur\u012b",
    "gn:population":0,
    "gn:timezone":"Asia/Kolkata",
    "iso:country":"IN",
    "ks:ks_name":"Tuntpura",
    "ks:ks_pop":131,
    "ks:ks_type":"HABITATION",
    "name:eng_x_preferred":[
        "Tuntpura"
    ],
    "name:eng_x_variant":[
        "Tuntpuri"
    ],
    "wof:name":"Tuntpura",
    "wof:placetype":"locality",
    "wof:population":131
},
  "geometry": {"coordinates":[79.150768,28.992058],"type":"Point"}
}