{
  "type": "Feature",
  "properties": {
    "gn:admin1_code":"21.0",
    "gn:admin2_code":"383.0",
    "gn:asciiname":"Ratnapravapodapada",
    "gn:country_code":"IN",
    "gn:dem":73,
    "gn:feature_class":"P",
    "gn:feature_code":"PPL",
    "gn:name":"Ratnapravapodapada",
    "gn:population":0,
    "gn:timezone":"Asia/Kolkata",
    "iso:country":"IN",
    "wof:name":"Ratnapravapodapada",
    "wof:placetype":"locality"
},
  "geometry": {"coordinates":[85.45303,20.75365],"type":"Point"}
}