{
  "type": "Feature",
  "properties": {
    "gn:admin1_code":"39.0",
    "gn:admin2_code":"68.0",
    "gn:asciiname":"Jhinwarheri",
    "gn:country_code":"IN",
    "gn:dem":238,
    "gn:feature_class":"P",
    "gn:feature_code":"PPL",
    "gn:name":"Jhinw\u0101rheri",
    "gn:population":0,
    "gn:timezone":"Asia/Kolkata",
    "iso:country":"IN",
    "name:und_x_variant":[
        "Jhinw\u0101rheri",
        "Jaw\u0101har Kh\u0101n"
    ],
    "wof:name":"Jhinwarheri",
    "wof:placetype":"locality"
},
  "geometry": {"coordinates":[78.11128000000002,29.73599],"type":"Point"}
}