{
  "type": "Feature",
  "properties": {
    "gn:admin1_code":"24.0",
    "gn:admin2_code":"114",
    "gn:asciiname":"Dhanana",
    "gn:country_code":"IN",
    "gn:dem":110,
    "gn:feature_class":"P",
    "gn:feature_code":"PPL",
    "gn:name":"Dh\u0101n\u0101na",
    "gn:population":0,
    "gn:timezone":"Asia/Kolkata",
    "iso:country":"IN",
    "ks:ks_alt_nam":"Dhan\u0101na",
    "ks:ks_name":"Dhanana",
    "ks:ks_pop":378,
    "ks:ks_type":"VILLAGE",
    "name:eng_x_preferred":[
        "Dhanana"
    ],
    "name:eng_x_variant":[
        "Dhan\u0101na"
    ],
    "name:spa_x_preferred":[
        "Dhanana"
    ],
    "name:und_x_variant":[
        "Dh\u0101n\u0101na",
        "Dhan\u0101na"
    ],
    "wof:name":"Dhanana",
    "wof:placetype":"locality",
    "wof:population":378
},
  "geometry": {"coordinates":[70.205737,26.724472],"type":"Point"}
}