{
  "type": "Feature",
  "properties": {
    "gn:admin1_code":"24.0",
    "gn:admin2_code":"114",
    "gn:asciiname":"Dhanana",
    "gn:country_code":"IN",
    "gn:dem":110,
    "gn:feature_class":"P",
    "gn:feature_code":"PPL",
    "gn:name":"Dh\u0101n\u0101na",
    "gn:population":0,
    "gn:timezone":"Asia/Kolkata",
    "iso:country":"IN",
    "name:spa_x_preferred":[
        "Dhanana"
    ],
    "name:und_x_variant":[
        "Dh\u0101n\u0101na",
        "Dhan\u0101na"
    ],
    "wof:name":"Dhanana",
    "wof:placetype":"locality"
},
  "geometry": {"coordinates":[70.19105,26.70123],"type":"Point"}
}