{
  "type": "Feature",
  "properties": {
    "iso:country":"IN",
    "ks:ks_name":"Rowmari Domdoma",
    "ks:ks_pop":1033,
    "ks:ks_type":"VILLAGE",
    "ks:ks_uagg_main":0,
    "name:eng_x_preferred":[
        "Rowmari Domdoma"
    ],
    "wof:name":"Rowmari Domdoma",
    "wof:placetype":"neighbourhood",
    "wof:population":1033
},
  "geometry": {"coordinates":[91.277348,26.28717],"type":"Point"}
}