{
  "type": "Feature",
  "properties": {
    "iso:country":"IN",
    "ks:ks_name":"Haradas Para",
    "ks:ks_pop":249,
    "ks:ks_type":"HABITATION",
    "name:eng_x_preferred":[
        "Haradas Para"
    ],
    "wof:name":"Haradas Para",
    "wof:placetype":"locality",
    "wof:population":249
},
  "geometry": {"coordinates":[91.759289,23.374763],"type":"Point"}
}