{
  "type": "Feature",
  "properties": {
    "iso:country":"IN",
    "ks:ks_name":"Kalikud",
    "ks:ks_pop":0,
    "ks:ks_type":"VILLAGE",
    "name:eng_x_preferred":[
        "Kalikud"
    ],
    "wof:name":"Kalikud",
    "wof:placetype":"locality",
    "wof:population":0
},
  "geometry": {"coordinates":[84.842883,21.448871],"type":"Point"}
}