{
  "type": "Feature",
  "properties": {
    "iso:country":"IN",
    "ks:ks_name":"Koriya",
    "ks:ks_pop":140,
    "ks:ks_type":"HABITATION",
    "name:eng_x_preferred":[
        "Koriya"
    ],
    "wof:name":"Koriya",
    "wof:placetype":"locality",
    "wof:population":140
},
  "geometry": {"coordinates":[75.10735200000001,12.858506],"type":"Point"}
}