{
  "type": "Feature",
  "properties": {
    "gn:admin1_code":"36.0",
    "gn:admin2_code":"182.0",
    "gn:asciiname":"Kallu Dih",
    "gn:country_code":"IN",
    "gn:dem":101,
    "gn:feature_class":"P",
    "gn:feature_code":"PPL",
    "gn:name":"Kallu D\u012bh",
    "gn:population":0,
    "gn:timezone":"Asia/Kolkata",
    "iso:country":"IN",
    "ks:ks_name":"Kallu Deeh",
    "ks:ks_pop":276,
    "ks:ks_type":"HABITATION",
    "name:eng_x_preferred":[
        "Kallu Deeh"
    ],
    "name:eng_x_variant":[
        "Kallu Dih"
    ],
    "wof:name":"Kallu Deeh",
    "wof:placetype":"locality",
    "wof:population":276
},
  "geometry": {"coordinates":[82.52101999999999,27.44358],"type":"Point"}
}