{
  "type": "Feature",
  "properties": {
    "iso:country":"IN",
    "ks:ks_name":"Tarwara Manakwara",
    "ks:ks_pop":202,
    "ks:ks_type":"HABITATION",
    "name:eng_x_preferred":[
        "Tarwara Manakwara"
    ],
    "wof:name":"Tarwara Manakwara",
    "wof:placetype":"locality",
    "wof:population":202
},
  "geometry": {"coordinates":[79.59079800000001,23.048867],"type":"Point"}
}