{
  "type": "Feature",
  "properties": {
    "iso:country":"IN",
    "ks:ks_name":"Visamundi",
    "ks:ks_pop":497,
    "ks:ks_type":"VILLAGE",
    "name:eng_x_preferred":[
        "Visamundi"
    ],
    "wof:name":"Visamundi",
    "wof:placetype":"locality",
    "wof:population":497
},
  "geometry": {"coordinates":[80.40976499999999,19.507102],"type":"Point"}
}