{
  "type": "Feature",
  "properties": {
    "iso:country":"IN",
    "ks:ks_name":"Barnizara Suba",
    "ks:ks_pop":388,
    "ks:ks_type":"HABITATION",
    "name:eng_x_preferred":[
        "Barnizara Suba"
    ],
    "wof:name":"Barnizara Suba",
    "wof:placetype":"locality",
    "wof:population":388
},
  "geometry": {"coordinates":[91.780838,26.290328],"type":"Point"}
}