{
  "type": "Feature",
  "properties": {
    "gn:admin1_code":"39.0",
    "gn:admin2_code":"62.0",
    "gn:asciiname":"Bankot",
    "gn:country_code":"IN",
    "gn:dem":1277,
    "gn:feature_class":"P",
    "gn:feature_code":"PPL",
    "gn:name":"Bankot",
    "gn:population":0,
    "gn:timezone":"Asia/Kolkata",
    "iso:country":"IN",
    "name:cat_x_preferred":[
        "Bankot"
    ],
    "name:mar_x_preferred":[
        "\u092c\u093e\u0923\u0915\u094b\u091f"
    ],
    "name:urd_x_preferred":[
        "\u0628\u0646\u06a9\u0648\u0679"
    ],
    "wof:name":"Bankot",
    "wof:placetype":"locality"
},
  "geometry": {"coordinates":[79.87461999999999,29.76116],"type":"Point"}
}