{
  "type": "Feature",
  "properties": {
    "gn:admin1_code":"36.0",
    "gn:admin2_code":"162.0",
    "gn:asciiname":"Purwa Banjaran",
    "gn:country_code":"IN",
    "gn:dem":144,
    "gn:feature_class":"P",
    "gn:feature_code":"PPL",
    "gn:name":"Purwa Banj\u0101r\u0101n",
    "gn:population":0,
    "gn:timezone":"Asia/Kolkata",
    "iso:country":"IN",
    "ks:ks_name":"Purwa Banjaran",
    "ks:ks_pop":312,
    "ks:ks_type":"HABITATION",
    "name:eng_x_preferred":[
        "Purwa Banjaran"
    ],
    "wof:name":"Purwa Banjaran",
    "wof:placetype":"locality",
    "wof:population":312
},
  "geometry": {"coordinates":[79.626344,26.759906],"type":"Point"}
}