{
  "type": "Feature",
  "properties": {
    "iso:country":"IN",
    "ks:ks_name":"Uttar Karkara",
    "ks:ks_pop":735,
    "ks:ks_type":"VILLAGE",
    "name:eng_x_preferred":[
        "Uttar Karkara"
    ],
    "wof:name":"Uttar Karkara",
    "wof:placetype":"locality",
    "wof:population":735
},
  "geometry": {"coordinates":[87.371697,22.114731],"type":"Point"}
}