{
  "type": "Feature",
  "properties": {
    "gn:admin1_code":"24.0",
    "gn:admin2_code":"122.0",
    "gn:asciiname":"Bhumion ka Baria",
    "gn:country_code":"IN",
    "gn:dem":548,
    "gn:feature_class":"P",
    "gn:feature_code":"PPL",
    "gn:name":"Bhumion ka B\u0101ria",
    "gn:population":0,
    "gn:timezone":"Asia/Kolkata",
    "iso:country":"IN",
    "wof:name":"Bhumion ka Baria",
    "wof:placetype":"locality"
},
  "geometry": {"coordinates":[74.13263000000001,25.52603],"type":"Point"}
}