{
  "type": "Feature",
  "properties": {
    "iso:country":"IN",
    "ks:ks_name":"Kotwarpara",
    "ks:ks_pop":75,
    "ks:ks_type":"HABITATION",
    "name:eng_x_preferred":[
        "Kotwarpara"
    ],
    "wof:name":"Kotwarpara",
    "wof:placetype":"locality",
    "wof:population":75
},
  "geometry": {"coordinates":[81.37767599999999,19.680235],"type":"Point"}
}