{
  "type": "Feature",
  "properties": {
    "iso:country":"IN",
    "ks:ks_name":"Lagura",
    "ks:ks_pop":251,
    "ks:ks_type":"VILLAGE",
    "name:eng_x_preferred":[
        "Lagura"
    ],
    "wof:name":"Lagura",
    "wof:placetype":"locality",
    "wof:population":251
},
  "geometry": {"coordinates":[85.37945999999999,22.822824],"type":"Point"}
}