{
  "type": "Feature",
  "properties": {
    "iso:country":"IN",
    "ks:ks_alt_nam":"Chailis urf Bahttar",
    "ks:ks_name":"Chailis Urf Bahttar",
    "ks:ks_pop":97,
    "ks:ks_type":"HABITATION",
    "ks:ks_uagg_main":0,
    "name:eng_x_preferred":[
        "Chailis Urf Bahttar"
    ],
    "wof:name":"Chailis Urf Bahttar",
    "wof:placetype":"neighbourhood",
    "wof:population":97
},
  "geometry": {"coordinates":[82.13904599999999,25.328591],"type":"Point"}
}