{
  "type": "Feature",
  "properties": {
    "iso:country":"IN",
    "ks:ks_name":"Harinarayanpur",
    "ks:ks_pop":710,
    "ks:ks_type":"VILLAGE",
    "name:eng_x_preferred":[
        "Harinarayanpur"
    ],
    "wof:name":"Harinarayanpur",
    "wof:placetype":"locality",
    "wof:population":710
},
  "geometry": {"coordinates":[87.73748399999999,22.485868],"type":"Point"}
}