{
  "type": "Feature",
  "properties": {
    "iso:country":"IN",
    "ks:ks_name":"Nayatol",
    "ks:ks_pop":1961,
    "ks:ks_type":"VILLAGE",
    "name:eng_x_preferred":[
        "Nayatol"
    ],
    "wof:name":"Nayatol",
    "wof:placetype":"locality",
    "wof:population":1961
},
  "geometry": {"coordinates":[85.955352,25.603178],"type":"Point"}
}