{
  "type": "Feature",
  "properties": {
    "iso:country":"IN",
    "ks:ks_name":"Bhel Sarda",
    "ks:ks_pop":23,
    "ks:ks_type":"VILLAGE",
    "name:eng_x_preferred":[
        "Bhel Sarda"
    ],
    "wof:name":"Bhel Sarda",
    "wof:placetype":"locality",
    "wof:population":23
},
  "geometry": {"coordinates":[78.56527,29.801752],"type":"Point"}
}