{
  "type": "Feature",
  "properties": {
    "iso:country":"IN",
    "ks:ks_name":"Periyamadaippaychchal",
    "ks:ks_pop":4719,
    "ks:ks_type":"VILLAGE",
    "name:eng_x_preferred":[
        "Periyamadaippaychchal"
    ],
    "wof:name":"Periyamadaippaychchal",
    "wof:placetype":"locality",
    "wof:population":4719
},
  "geometry": {"coordinates":[79.16163,9.953035],"type":"Point"}
}