{
  "type": "Feature",
  "properties": {
    "iso:country":"IN",
    "ks:ks_alt_nam":"CHANDINI CHOEK",
    "ks:ks_name":"Chandini Choek",
    "ks:ks_pop":291,
    "ks:ks_type":"HABITATION",
    "name:eng_x_preferred":[
        "Chandini Choek"
    ],
    "wof:name":"Chandini Choek",
    "wof:placetype":"locality",
    "wof:population":291
},
  "geometry": {"coordinates":[81.829915,26.162466],"type":"Point"}
}