{
  "type": "Feature",
  "properties": {
    "gn:admin1_code":"25.0",
    "gn:admin2_code":"628.0",
    "gn:asciiname":"Ittamozhi",
    "gn:country_code":"IN",
    "gn:dem":41,
    "gn:feature_class":"P",
    "gn:feature_code":"PPL",
    "gn:name":"Ittamozhi",
    "gn:population":0,
    "gn:timezone":"Asia/Kolkata",
    "iso:country":"IN",
    "name:tam_x_preferred":[
        "\u0b87\u0b9f\u0bcd\u0b9f\u0bae\u0bca\u0bb4\u0bbf"
    ],
    "wof:name":"Ittamozhi",
    "wof:placetype":"locality"
},
  "geometry": {"coordinates":[77.84865000000001,8.39447],"type":"Point"}
}