{
  "type": "Feature",
  "properties": {
    "gn:admin1_code":"19.0",
    "gn:admin2_code":"577.0",
    "gn:asciiname":"Sidayyanahundi",
    "gn:country_code":"IN",
    "gn:dem":759,
    "gn:feature_class":"P",
    "gn:feature_code":"PPL",
    "gn:name":"Sidayyanahundi",
    "gn:population":0,
    "gn:timezone":"Asia/Kolkata",
    "iso:country":"IN",
    "wof:name":"Sidayyanahundi",
    "wof:placetype":"locality"
},
  "geometry": {"coordinates":[76.63393000000001,12.0067],"type":"Point"}
}