{
  "type": "Feature",
  "properties": {
    "iso:country":"IN",
    "ks:ks_name":"Mantapada",
    "ks:ks_pop":5,
    "ks:ks_type":"VILLAGE",
    "name:eng_x_preferred":[
        "Mantapada"
    ],
    "wof:name":"Mantapada",
    "wof:placetype":"locality",
    "wof:population":5
},
  "geometry": {"coordinates":[86.856318,20.893433],"type":"Point"}
}