{
  "type": "Feature",
  "properties": {
    "iso:country":"IN",
    "ks:ks_name":"Poidal",
    "ks:ks_pop":717,
    "ks:ks_type":"HABITATION",
    "name:eng_x_preferred":[
        "Poidal"
    ],
    "wof:name":"Poidal",
    "wof:placetype":"locality",
    "wof:population":717
},
  "geometry": {"coordinates":[74.933164,12.891135],"type":"Point"}
}