{
  "type": "Feature",
  "properties": {
    "gn:admin1_code":"37.0",
    "gn:admin2_code":"412.0",
    "gn:asciiname":"Kotgaon",
    "gn:country_code":"IN",
    "gn:dem":306,
    "gn:feature_class":"P",
    "gn:feature_code":"PPL",
    "gn:name":"Kotgaon",
    "gn:population":0,
    "gn:timezone":"Asia/Kolkata",
    "iso:country":"IN",
    "wof:name":"Kotgaon",
    "wof:placetype":"locality"
},
  "geometry": {"coordinates":[81.73248000000002,20.97553],"type":"Point"}
}