{
  "type": "Feature",
  "properties": {
    "iso:country":"IN",
    "ks:ks_name":"Nawaan Basti",
    "ks:ks_pop":200,
    "ks:ks_type":"HABITATION",
    "name:eng_x_preferred":[
        "Nawaan Basti"
    ],
    "wof:name":"Nawaan Basti",
    "wof:placetype":"locality",
    "wof:population":200
},
  "geometry": {"coordinates":[82.548547,25.20808],"type":"Point"}
}