{
  "type": "Feature",
  "properties": {
    "iso:country":"IN",
    "ks:ks_name":"Das Para",
    "ks:ks_pop":342,
    "ks:ks_type":"HABITATION",
    "name:eng_x_preferred":[
        "Das Para"
    ],
    "wof:name":"Das Para",
    "wof:placetype":"locality",
    "wof:population":342
},
  "geometry": {"coordinates":[91.527973,23.355631],"type":"Point"}
}