{
  "type": "Feature",
  "properties": {
    "gn:admin1_code":"37",
    "gn:admin2_code":"410.0",
    "gn:asciiname":"Tarpongi",
    "gn:country_code":"IN",
    "gn:dem":273,
    "gn:feature_class":"P",
    "gn:feature_code":"PPL",
    "gn:name":"Tarpongi",
    "gn:population":0,
    "gn:timezone":"Asia/Kolkata",
    "iso:country":"IN",
    "wof:name":"Tarpongi",
    "wof:placetype":"locality"
},
  "geometry": {"coordinates":[81.68656999999997,21.49297],"type":"Point"}
}