{
  "type": "Feature",
  "properties": {
    "iso:country":"IN",
    "ks:ks_name":"Burikipeta",
    "ks:ks_pop":101,
    "ks:ks_type":"HABITATION",
    "name:eng_x_preferred":[
        "Burikipeta"
    ],
    "wof:name":"Burikipeta",
    "wof:placetype":"locality",
    "wof:population":101
},
  "geometry": {"coordinates":[84.10327599999999,18.727234],"type":"Point"}
}