{
  "type": "Feature",
  "properties": {
    "gn:admin1_code":"2.0",
    "gn:admin2_code":"554.0",
    "gn:asciiname":"Kotalavandlapalle",
    "gn:country_code":"IN",
    "gn:dem":687,
    "gn:feature_class":"P",
    "gn:feature_code":"PPL",
    "gn:name":"Kot\u0101lav\u0101ndlapalle",
    "gn:population":0,
    "gn:timezone":"Asia/Kolkata",
    "iso:country":"IN",
    "wof:name":"Kotalavandlapalle",
    "wof:placetype":"neighbourhood"
},
  "geometry": {"coordinates":[78.10836,13.74761],"type":"Point"}
}