{
  "type": "Feature",
  "properties": {
    "iso:country":"IN",
    "ks:ks_name":"Chinchewadi",
    "ks:ks_pop":128,
    "ks:ks_type":"HABITATION",
    "name:eng_x_preferred":[
        "Chinchewadi"
    ],
    "wof:name":"Chinchewadi",
    "wof:placetype":"locality",
    "wof:population":128
},
  "geometry": {"coordinates":[73.9606,16.80144],"type":"Point"}
}