{
  "type": "Feature",
  "properties": {
    "iso:country":"IN",
    "ks:ks_alt_nam":"N\u0101g\u0101chchi",
    "ks:ks_alt_nam_2":"Nagachchi",
    "ks:ks_name":"Nagachi",
    "ks:ks_pop":1011,
    "ks:ks_type":"VILLAGE",
    "name:eng_x_preferred":[
        "Nagachi"
    ],
    "name:eng_x_variant":[
        "N\u0101g\u0101chchi",
        "Nagachchi"
    ],
    "wof:name":"Nagachi",
    "wof:placetype":"locality",
    "wof:population":1011
},
  "geometry": {"coordinates":[78.74001,9.458088],"type":"Point"}
}