{
  "type": "Feature",
  "properties": {
    "gn:admin1_code":"36",
    "gn:admin2_code":"159.0",
    "gn:asciiname":"Garhi",
    "gn:country_code":"IN",
    "gn:dem":156,
    "gn:feature_class":"P",
    "gn:feature_code":"PPL",
    "gn:name":"Garhi",
    "gn:population":0,
    "gn:timezone":"Asia/Kolkata",
    "iso:country":"IN",
    "name:cat_x_preferred":[
        "Garhi"
    ],
    "wof:name":"Garhi",
    "wof:placetype":"locality"
},
  "geometry": {"coordinates":[79.34293000000002,27.302],"type":"Point"}
}