{
  "type": "Feature",
  "properties": {
    "gn:admin1_code":"35",
    "gn:admin2_code":"428.0",
    "gn:asciiname":"Deori",
    "gn:country_code":"IN",
    "gn:dem":593,
    "gn:feature_class":"P",
    "gn:feature_code":"PPL",
    "gn:name":"Deori",
    "gn:population":0,
    "gn:timezone":"Asia/Kolkata",
    "iso:country":"IN",
    "ks:ks_name":"Deori",
    "ks:ks_pop":345,
    "ks:ks_type":"VILLAGE",
    "name:cat_x_preferred":[
        "Deori"
    ],
    "name:ceb_x_preferred":[
        "Deori"
    ],
    "name:eng_x_preferred":[
        "Deori"
    ],
    "name:por_x_preferred":[
        "Deori"
    ],
    "name:swe_x_preferred":[
        "Deori"
    ],
    "wof:name":"Deori",
    "wof:placetype":"locality",
    "wof:population":345
},
  "geometry": {"coordinates":[79.77802699999999,23.499028],"type":"Point"}
}