{
  "type": "Feature",
  "properties": {
    "iso:country":"IN",
    "ks:ks_alt_nam":"JAGDISH PURWA",
    "ks:ks_name":"Jagdish Purwa",
    "ks:ks_pop":40,
    "ks:ks_type":"HABITATION",
    "ks:ks_uagg_main":0,
    "name:eng_x_preferred":[
        "Jagdish Purwa"
    ],
    "wof:name":"Jagdish Purwa",
    "wof:placetype":"neighbourhood",
    "wof:population":40
},
  "geometry": {"coordinates":[81.27267000000001,28.111415],"type":"Point"}
}