{
  "type": "Feature",
  "properties": {
    "iso:country":"IN",
    "ks:ks_alt_nam":"TEMBHU CANOL",
    "ks:ks_name":"Tembhu Canol",
    "ks:ks_pop":120,
    "ks:ks_type":"HABITATION",
    "name:eng_x_preferred":[
        "Tembhu Canol"
    ],
    "wof:name":"Tembhu Canol",
    "wof:placetype":"locality",
    "wof:population":120
},
  "geometry": {"coordinates":[74.36030700000001,17.176252],"type":"Point"}
}