{
  "type": "Feature",
  "properties": {
    "gn:admin1_code":"12.0",
    "gn:admin2_code":"1.0",
    "gn:asciiname":"Kunan Babagund",
    "gn:country_code":"IN",
    "gn:dem":1675,
    "gn:feature_class":"P",
    "gn:feature_code":"PPL",
    "gn:name":"Kunan Bab\u0101gund",
    "gn:population":0,
    "gn:timezone":"Asia/Kolkata",
    "iso:country":"IN",
    "wof:name":"Kunan Babagund",
    "wof:placetype":"locality"
},
  "geometry": {"coordinates":[74.19197,34.51095],"type":"Point"}
}