{
  "type": "Feature",
  "properties": {
    "gn:admin1_code":"36",
    "gn:admin2_code":"188.0",
    "gn:asciiname":"Bandhua",
    "gn:country_code":"IN",
    "gn:dem":80,
    "gn:feature_class":"P",
    "gn:feature_code":"PPL",
    "gn:name":"Bandhua",
    "gn:population":0,
    "gn:timezone":"Asia/Kolkata",
    "iso:country":"IN",
    "wof:name":"Bandhua",
    "wof:placetype":"locality"
},
  "geometry": {"coordinates":[83.46998000000001,26.48002],"type":"Point"}
}