{
  "type": "Feature",
  "properties": {
    "iso:country":"IN",
    "ks:ks_name":"Baghuasol",
    "ks:ks_pop":265,
    "ks:ks_type":"HABITATION",
    "name:eng_x_preferred":[
        "Baghuasol"
    ],
    "wof:name":"Baghuasol",
    "wof:placetype":"locality",
    "wof:population":265
},
  "geometry": {"coordinates":[86.96327700000001,22.51813],"type":"Point"}
}