{
  "type": "Feature",
  "properties": {
    "iso:country":"IN",
    "ks:ks_name":"Vadhela Gamtal",
    "ks:ks_pop":605,
    "ks:ks_type":"HABITATION",
    "name:eng_x_preferred":[
        "Vadhela Gamtal"
    ],
    "wof:name":"Vadhela Gamtal",
    "wof:placetype":"locality",
    "wof:population":605
},
  "geometry": {"coordinates":[73.648144,23.417406],"type":"Point"}
}