{
  "type": "Feature",
  "properties": {
    "gn:admin1_code":"16.0",
    "gn:admin2_code":"521.0",
    "gn:asciiname":"Kurkumb",
    "gn:country_code":"IN",
    "gn:dem":614,
    "gn:feature_class":"P",
    "gn:feature_code":"PPL",
    "gn:name":"Kurkumb",
    "gn:population":0,
    "gn:timezone":"Asia/Kolkata",
    "iso:country":"IN",
    "wof:name":"Kurkumb",
    "wof:placetype":"locality"
},
  "geometry": {"coordinates":[74.54225,18.39825],"type":"Point"}
}