{
  "type": "Feature",
  "properties": {
    "iso:country":"IN",
    "ks:ks_name":"Gundiji",
    "ks:ks_pop":26,
    "ks:ks_type":"HABITATION",
    "name:eng_x_preferred":[
        "Gundiji"
    ],
    "wof:name":"Gundiji",
    "wof:placetype":"locality",
    "wof:population":26
},
  "geometry": {"coordinates":[75.2769,12.778255],"type":"Point"}
}