{
  "type": "Feature",
  "properties": {
    "iso:country":"IN",
    "ks:ks_name":"Manoor",
    "ks:ks_pop":700,
    "ks:ks_type":"HABITATION",
    "name:eng_x_preferred":[
        "Manoor"
    ],
    "wof:name":"Manoor",
    "wof:placetype":"locality",
    "wof:population":700
},
  "geometry": {"coordinates":[76.284999,11.54883],"type":"Point"}
}