{
  "type": "Feature",
  "properties": {
    "iso:country":"IN",
    "ks:ks_name":"Mazurmunda",
    "ks:ks_pop":1283,
    "ks:ks_type":"VILLAGE",
    "name:eng_x_preferred":[
        "Mazurmunda"
    ],
    "wof:name":"Mazurmunda",
    "wof:placetype":"locality",
    "wof:population":1283
},
  "geometry": {"coordinates":[82.559489,18.947076],"type":"Point"}
}