{
  "type": "Feature",
  "properties": {
    "gn:admin1_code":"35",
    "gn:admin2_code":"453.0",
    "gn:asciiname":"Manikpur",
    "gn:country_code":"IN",
    "gn:dem":782,
    "gn:feature_class":"P",
    "gn:feature_code":"PPL",
    "gn:name":"M\u0101nikpur",
    "gn:population":0,
    "gn:timezone":"Asia/Kolkata",
    "iso:country":"IN",
    "wof:name":"Manikpur",
    "wof:placetype":"locality"
},
  "geometry": {"coordinates":[81.19134,22.78042],"type":"Point"}
}