{
  "type": "Feature",
  "properties": {
    "iso:country":"IN",
    "ks:ks_alt_nam":"BIND TOLA",
    "ks:ks_name":"Bind Tola",
    "ks:ks_pop":277,
    "ks:ks_type":"HABITATION",
    "name:eng_x_preferred":[
        "Bind Tola"
    ],
    "wof:name":"Bind Tola",
    "wof:placetype":"locality",
    "wof:population":277
},
  "geometry": {"coordinates":[86.21037,25.02439],"type":"Point"}
}