{
  "type": "Feature",
  "properties": {
    "iso:country":"IN",
    "ks:ks_name":"Baniban",
    "ks:ks_pop":5914,
    "ks:ks_type":"URBAN",
    "name:eng_x_preferred":[
        "Baniban"
    ],
    "wof:name":"Baniban",
    "wof:placetype":"locality",
    "wof:population":5914
},
  "geometry": {"coordinates":[88.080195,22.498643],"type":"Point"}
}