{
  "type": "Feature",
  "properties": {
    "iso:country":"IN",
    "ks:ks_name":"Tardon Ka Tala",
    "ks:ks_pop":489,
    "ks:ks_type":"VILLAGE",
    "name:eng_x_preferred":[
        "Tardon Ka Tala"
    ],
    "wof:name":"Tardon Ka Tala",
    "wof:placetype":"locality",
    "wof:population":489
},
  "geometry": {"coordinates":[71.195025,25.272519],"type":"Point"}
}