{
  "type": "Feature",
  "properties": {
    "iso:country":"IN",
    "ks:ks_name":"Nambikudi",
    "ks:ks_pop":150,
    "ks:ks_type":"HABITATION",
    "name:eng_x_preferred":[
        "Nambikudi"
    ],
    "wof:name":"Nambikudi",
    "wof:placetype":"locality",
    "wof:population":150
},
  "geometry": {"coordinates":[79.71428299999999,10.9066],"type":"Point"}
}