{
  "type": "Feature",
  "properties": {
    "iso:country":"IN",
    "ks:ks_name":"Soil Conservation",
    "ks:ks_pop":104,
    "ks:ks_type":"HABITATION",
    "ks:ks_uagg_main":0,
    "name:eng_x_preferred":[
        "Soil Conservation"
    ],
    "wof:name":"Soil Conservation",
    "wof:placetype":"neighbourhood",
    "wof:population":104
},
  "geometry": {"coordinates":[93.12539599999999,25.319632],"type":"Point"}
}