{
  "type": "Feature",
  "properties": {
    "iso:country":"IN",
    "ks:ks_name":"Haragachhia",
    "ks:ks_pop":565,
    "ks:ks_type":"HABITATION",
    "name:eng_x_preferred":[
        "Haragachhia"
    ],
    "wof:name":"Haragachhia",
    "wof:placetype":"locality",
    "wof:population":565
},
  "geometry": {"coordinates":[87.710959,21.881308],"type":"Point"}
}