{
  "type": "Feature",
  "properties": {
    "iso:country":"IN",
    "ks:ks_name":"Radhakantapur",
    "ks:ks_pop":1003,
    "ks:ks_type":"VILLAGE",
    "name:eng_x_preferred":[
        "Radhakantapur"
    ],
    "wof:name":"Radhakantapur",
    "wof:placetype":"locality",
    "wof:population":1003
},
  "geometry": {"coordinates":[87.70677999999999,22.632254],"type":"Point"}
}