{
  "type": "Feature",
  "properties": {
    "gn:admin1_code":"16",
    "gn:admin2_code":"525.0",
    "gn:asciiname":"Moha",
    "gn:country_code":"IN",
    "gn:dem":694,
    "gn:feature_class":"P",
    "gn:feature_code":"PPL",
    "gn:name":"Moha",
    "gn:population":0,
    "gn:timezone":"Asia/Kolkata",
    "iso:country":"IN",
    "name:ceb_x_preferred":[
        "Moha"
    ],
    "name:deu_x_preferred":[
        "Moha"
    ],
    "name:fra_x_preferred":[
        "Moha"
    ],
    "name:hun_x_preferred":[
        "Moha"
    ],
    "name:nld_x_preferred":[
        "Moha"
    ],
    "name:swe_x_preferred":[
        "Moha"
    ],
    "wof:name":"Moha",
    "wof:placetype":"locality"
},
  "geometry": {"coordinates":[75.99762,18.47093],"type":"Point"}
}