{
  "type": "Feature",
  "properties": {
    "gn:admin1_code":"13.0",
    "gn:admin2_code":"600.0",
    "gn:asciiname":"Modalakkilvayalkara",
    "gn:country_code":"IN",
    "gn:dem":19,
    "gn:feature_class":"P",
    "gn:feature_code":"PPL",
    "gn:name":"Modalakkilvayalkara",
    "gn:population":0,
    "gn:timezone":"Asia/Kolkata",
    "iso:country":"IN",
    "wof:name":"Modalakkilvayalkara",
    "wof:placetype":"locality"
},
  "geometry": {"coordinates":[76.61490000000001,8.96027],"type":"Point"}
}