{
  "type": "Feature",
  "properties": {
    "gn:admin1_code":"23.0",
    "gn:admin2_code":"49.0",
    "gn:asciiname":"Sarja",
    "gn:country_code":"IN",
    "gn:dem":237,
    "gn:feature_class":"P",
    "gn:feature_code":"PPL",
    "gn:name":"Sarja",
    "gn:population":0,
    "gn:timezone":"Asia/Kolkata",
    "iso:country":"IN",
    "name:deu_x_preferred":[
        "Sarja"
    ],
    "name:fin_x_preferred":[
        "Sarja"
    ],
    "name:lav_x_preferred":[
        "Sarja"
    ],
    "name:swe_x_preferred":[
        "Sarja"
    ],
    "wof:name":"Sarja",
    "wof:placetype":"locality"
},
  "geometry": {"coordinates":[75.16169000000002,31.59309],"type":"Point"}
}