{
  "type": "Feature",
  "properties": {
    "iso:country":"IN",
    "ks:ks_name":"Mauzama",
    "ks:ks_pop":3145,
    "ks:ks_type":"HABITATION",
    "name:eng_x_preferred":[
        "Mauzama"
    ],
    "wof:name":"Mauzama",
    "wof:placetype":"locality",
    "wof:population":3145
},
  "geometry": {"coordinates":[86.88180800000001,25.98895],"type":"Point"}
}