{
  "type": "Feature",
  "properties": {
    "iso:country":"IN",
    "ks:ks_name":"Muri Semar",
    "ks:ks_pop":3242,
    "ks:ks_type":"VILLAGE",
    "name:eng_x_preferred":[
        "Muri Semar"
    ],
    "wof:name":"Muri Semar",
    "wof:placetype":"locality",
    "wof:population":3242
},
  "geometry": {"coordinates":[83.39239600000001,24.247214],"type":"Point"}
}