{
  "type": "Feature",
  "properties": {
    "gn:admin1_code":"36.0",
    "gn:admin2_code":"150.0",
    "gn:asciiname":"Lamba Khera",
    "gn:country_code":"IN",
    "gn:dem":182,
    "gn:feature_class":"P",
    "gn:feature_code":"PPL",
    "gn:name":"L\u0101mba Khera",
    "gn:population":0,
    "gn:timezone":"Asia/Kolkata",
    "iso:country":"IN",
    "ks:ks_alt_nam":"L\u0101mba Khera",
    "ks:ks_name":"Lamba Khera",
    "ks:ks_pop":1785,
    "ks:ks_type":"VILLAGE",
    "name:eng_x_preferred":[
        "Lamba Khera"
    ],
    "name:eng_x_variant":[
        "L\u0101mba Khera"
    ],
    "wof:name":"Lamba Khera",
    "wof:placetype":"locality",
    "wof:population":1785
},
  "geometry": {"coordinates":[79.540604,28.557352],"type":"Point"}
}