{
  "type": "Feature",
  "properties": {
    "iso:country":"IN",
    "ks:ks_name":"Baghabindha",
    "ks:ks_pop":58,
    "ks:ks_type":"VILLAGE",
    "name:eng_x_preferred":[
        "Baghabindha"
    ],
    "wof:name":"Baghabindha",
    "wof:placetype":"locality",
    "wof:population":58
},
  "geometry": {"coordinates":[84.63238200000001,22.001564],"type":"Point"}
}