{
  "type": "Feature",
  "properties": {
    "iso:country":"IN",
    "ks:ks_name":"Netaji Dalvewasti",
    "ks:ks_pop":132,
    "ks:ks_type":"HABITATION",
    "name:eng_x_preferred":[
        "Netaji Dalvewasti"
    ],
    "wof:name":"Netaji Dalvewasti",
    "wof:placetype":"locality",
    "wof:population":132
},
  "geometry": {"coordinates":[75.604955,17.877297],"type":"Point"}
}