{
  "type": "Feature",
  "properties": {
    "gn:admin1_code":"36.0",
    "gn:admin2_code":"183.0",
    "gn:asciiname":"Chandantara",
    "gn:country_code":"IN",
    "gn:dem":104,
    "gn:feature_class":"P",
    "gn:feature_code":"PPL",
    "gn:name":"Chandantara",
    "gn:population":0,
    "gn:timezone":"Asia/Kolkata",
    "iso:country":"IN",
    "ks:ks_name":"Chandan Tara",
    "ks:ks_pop":342,
    "ks:ks_type":"HABITATION",
    "ks:ks_uagg_main":0,
    "name:eng_x_preferred":[
        "Chandan Tara"
    ],
    "wof:name":"Chandan Tara",
    "wof:placetype":"neighbourhood",
    "wof:population":342
},
  "geometry": {"coordinates":[82.00155599999999,26.887977],"type":"Point"}
}