{
  "type": "Feature",
  "properties": {
    "iso:country":"IN",
    "ks:ks_name":"Bhuwada",
    "ks:ks_pop":1149,
    "ks:ks_type":"HABITATION",
    "name:eng_x_preferred":[
        "Bhuwada"
    ],
    "wof:name":"Bhuwada",
    "wof:placetype":"locality",
    "wof:population":1149
},
  "geometry": {"coordinates":[75.109748,22.409798],"type":"Point"}
}