{
  "type": "Feature",
  "properties": {
    "gn:admin1_code":"34.0",
    "gn:admin2_code":"218.0",
    "gn:asciiname":"Pharchhua",
    "gn:country_code":"IN",
    "gn:dem":69,
    "gn:feature_class":"P",
    "gn:feature_code":"PPL",
    "gn:name":"Pharchhua",
    "gn:population":0,
    "gn:timezone":"Asia/Kolkata",
    "iso:country":"IN",
    "ks:ks_name":"Pharchhua",
    "ks:ks_pop":1636,
    "ks:ks_type":"VILLAGE",
    "ks:ks_uagg_main":0,
    "name:eng_x_preferred":[
        "Pharchhua"
    ],
    "wof:name":"Pharchhua",
    "wof:placetype":"neighbourhood",
    "wof:population":1636
},
  "geometry": {"coordinates":[84.19537099999999,26.221399],"type":"Point"}
}