{
  "type": "Feature",
  "properties": {
    "iso:country":"IN",
    "ks:ks_name":"Bakhtawarpura",
    "ks:ks_pop":456,
    "ks:ks_type":"VILLAGE",
    "name:eng_x_preferred":[
        "Bakhtawarpura"
    ],
    "wof:name":"Bakhtawarpura",
    "wof:placetype":"locality",
    "wof:population":456
},
  "geometry": {"coordinates":[73.62142299999999,27.723183],"type":"Point"}
}