{
  "type": "Feature",
  "properties": {
    "gn:admin1_code":"36",
    "gn:admin2_code":"197.0",
    "gn:asciiname":"Badalpura",
    "gn:country_code":"IN",
    "gn:dem":81,
    "gn:feature_class":"P",
    "gn:feature_code":"PPL",
    "gn:name":"Badalpura",
    "gn:population":0,
    "gn:timezone":"Asia/Kolkata",
    "iso:country":"IN",
    "name:ben_x_preferred":[
        "\u09ac\u09a6\u09b2\u09aa\u09c1\u09b0\u09be"
    ],
    "name:urd_x_preferred":[
        "\u0628\u0627\u062f\u0644\u067e\u0648\u0631\u06c1"
    ],
    "wof:name":"Badalpura",
    "wof:placetype":"locality"
},
  "geometry": {"coordinates":[82.97355999999998,25.3989],"type":"Point"}
}