{
  "type": "Feature",
  "properties": {
    "iso:country":"IN",
    "ks:ks_name":"Pandiyadeh",
    "ks:ks_pop":309,
    "ks:ks_type":"HABITATION",
    "name:eng_x_preferred":[
        "Pandiyadeh"
    ],
    "wof:name":"Pandiyadeh",
    "wof:placetype":"locality",
    "wof:population":309
},
  "geometry": {"coordinates":[76.63175699999999,22.263864],"type":"Point"}
}