{
  "type": "Feature",
  "properties": {
    "iso:country":"IN",
    "ks:ks_alt_nam":"BHIMPUR2",
    "ks:ks_name":"Bhimpur2",
    "ks:ks_pop":16,
    "ks:ks_type":"HABITATION",
    "name:eng_x_preferred":[
        "Bhimpur2"
    ],
    "wof:name":"Bhimpur2",
    "wof:placetype":"locality",
    "wof:population":16
},
  "geometry": {"coordinates":[87.68569100000001,24.544338],"type":"Point"}
}