{
  "type": "Feature",
  "properties": {
    "iso:country":"IN",
    "ks:ks_name":"Palappalli",
    "ks:ks_pop":250,
    "ks:ks_type":"HABITATION",
    "name:eng_x_preferred":[
        "Palappalli"
    ],
    "wof:name":"Palappalli",
    "wof:placetype":"locality",
    "wof:population":250
},
  "geometry": {"coordinates":[76.37002699999999,11.584322],"type":"Point"}
}