{
  "type": "Feature",
  "properties": {
    "iso:country":"IN",
    "ks:ks_name":"Purbba Nukha",
    "ks:ks_pop":4766,
    "ks:ks_type":"VILLAGE",
    "name:eng_x_preferred":[
        "Purbba Nukha"
    ],
    "wof:name":"Purbba Nukha",
    "wof:placetype":"locality",
    "wof:population":4766
},
  "geometry": {"coordinates":[87.822101,22.272881],"type":"Point"}
}