{
  "type": "Feature",
  "properties": {
    "iso:country":"IN",
    "ks:ks_name":"Achagalidoddi",
    "ks:ks_pop":108,
    "ks:ks_type":"HABITATION",
    "name:eng_x_preferred":[
        "Achagalidoddi"
    ],
    "wof:name":"Achagalidoddi",
    "wof:placetype":"locality",
    "wof:population":108
},
  "geometry": {"coordinates":[77.26075299999999,12.153604],"type":"Point"}
}