{
  "type": "Feature",
  "properties": {
    "iso:country":"IN",
    "ks:ks_alt_nam":"Kul\u0101dor",
    "ks:ks_name":"Kulador",
    "ks:ks_type":"VILLAGE",
    "name:eng_x_preferred":[
        "Kulador"
    ],
    "name:eng_x_variant":[
        "Kul\u0101dor"
    ],
    "wof:name":"Kulador",
    "wof:placetype":"locality"
},
  "geometry": {"coordinates":[84.09680400000001,23.079133],"type":"Point"}
}