{
  "type": "Feature",
  "properties": {
    "gn:admin1_code":"36.0",
    "gn:admin2_code":"189.0",
    "gn:asciiname":"Narahwa Maila",
    "gn:country_code":"IN",
    "gn:dem":89,
    "gn:feature_class":"P",
    "gn:feature_code":"PPL",
    "gn:name":"Narahw\u0101 Mail\u0101",
    "gn:population":0,
    "gn:timezone":"Asia/Kolkata",
    "iso:country":"IN",
    "ks:ks_alt_nam":"Narahw\u0101 Mail\u0101",
    "ks:ks_name":"Narahwa Maila",
    "ks:ks_type":"VILLAGE",
    "name:eng_x_preferred":[
        "Narahwa Maila"
    ],
    "name:eng_x_variant":[
        "Narahw\u0101 Mail\u0101"
    ],
    "wof:name":"Narahwa Maila",
    "wof:placetype":"locality"
},
  "geometry": {"coordinates":[84.122677,26.858317],"type":"Point"}
}