{
  "type": "Feature",
  "properties": {
    "iso:country":"IN",
    "ks:ks_alt_nam":"baldipurwa",
    "ks:ks_name":"Baldipurwa",
    "ks:ks_pop":100,
    "ks:ks_type":"HABITATION",
    "ks:ks_uagg_main":0,
    "name:eng_x_preferred":[
        "Baldipurwa"
    ],
    "wof:name":"Baldipurwa",
    "wof:placetype":"neighbourhood",
    "wof:population":100
},
  "geometry": {"coordinates":[81.983428,27.450183],"type":"Point"}
}