{
  "type": "Feature",
  "properties": {
    "gn:admin1_code":"23.0",
    "gn:admin2_code":"46.0",
    "gn:asciiname":"Burj Gillan",
    "gn:country_code":"IN",
    "gn:dem":219,
    "gn:feature_class":"P",
    "gn:feature_code":"PPL",
    "gn:name":"Burj Gill\u0101n",
    "gn:population":0,
    "gn:timezone":"Asia/Kolkata",
    "iso:country":"IN",
    "wof:name":"Burj Gillan",
    "wof:placetype":"locality"
},
  "geometry": {"coordinates":[75.23103,30.3918],"type":"Point"}
}