{
  "type": "Feature",
  "properties": {
    "gn:admin1_code":"25.0",
    "gn:admin2_code":"606.0",
    "gn:asciiname":"Nellimodu",
    "gn:country_code":"IN",
    "gn:dem":184,
    "gn:feature_class":"P",
    "gn:feature_code":"PPL",
    "gn:name":"Nellimodu",
    "gn:population":0,
    "gn:timezone":"Asia/Kolkata",
    "iso:country":"IN",
    "ks:ks_name":"Nellimedu",
    "ks:ks_pop":830,
    "ks:ks_type":"VILLAGE",
    "name:eng_x_preferred":[
        "Nellimedu"
    ],
    "name:eng_x_variant":[
        "Nellimodu"
    ],
    "wof:name":"Nellimedu",
    "wof:placetype":"locality",
    "wof:population":830
},
  "geometry": {"coordinates":[79.081059,12.414933],"type":"Point"}
}