{
  "type": "Feature",
  "properties": {
    "gn:admin1_code":"16",
    "gn:admin2_code":"508.0",
    "gn:asciiname":"Tohagaon",
    "gn:country_code":"IN",
    "gn:dem":238,
    "gn:feature_class":"P",
    "gn:feature_code":"PPL",
    "gn:name":"Toh\u0101gaon",
    "gn:population":0,
    "gn:timezone":"Asia/Kolkata",
    "iso:country":"IN",
    "ks:ks_alt_nam":"Toh\u0101gaon",
    "ks:ks_name":"Tohagaon",
    "ks:ks_pop":109,
    "ks:ks_type":"VILLAGE",
    "name:eng_x_preferred":[
        "Tohagaon"
    ],
    "name:eng_x_variant":[
        "Toh\u0101gaon"
    ],
    "wof:name":"Tohagaon",
    "wof:placetype":"locality",
    "wof:population":109
},
  "geometry": {"coordinates":[80.190285,20.033714],"type":"Point"}
}