{
  "type": "Feature",
  "properties": {
    "iso:country":"IN",
    "ks:ks_alt_nam":"Kumhar tola",
    "ks:ks_name":"Kumhar Tola",
    "ks:ks_pop":203,
    "ks:ks_type":"HABITATION",
    "ks:ks_uagg_main":0,
    "name:eng_x_preferred":[
        "Kumhar Tola"
    ],
    "wof:name":"Kumhar Tola",
    "wof:placetype":"neighbourhood",
    "wof:population":203
},
  "geometry": {"coordinates":[84.596115,26.525118],"type":"Point"}
}