{
  "type": "Feature",
  "properties": {
    "iso:country":"IN",
    "ks:ks_name":"Bhantanagavi A K Hatti",
    "ks:ks_pop":239,
    "ks:ks_type":"HABITATION",
    "name:eng_x_preferred":[
        "Bhantanagavi A K Hatti"
    ],
    "wof:name":"Bhantanagavi A K Hatti",
    "wof:placetype":"locality",
    "wof:population":239
},
  "geometry": {"coordinates":[76.393969,13.847235],"type":"Point"}
}