{
  "type": "Feature",
  "properties": {
    "iso:country":"IN",
    "ks:ks_name":"Lolki Saraswatipara",
    "ks:ks_pop":497,
    "ks:ks_type":"HABITATION",
    "name:eng_x_preferred":[
        "Lolki Saraswatipara"
    ],
    "wof:name":"Lolki Saraswatipara",
    "wof:placetype":"locality",
    "wof:population":497
},
  "geometry": {"coordinates":[83.266873,23.575274],"type":"Point"}
}