{
  "type": "Feature",
  "properties": {
    "iso:country":"IN",
    "ks:ks_alt_nam":"Bennur camp",
    "ks:ks_name":"Bennur Camp",
    "ks:ks_pop":216,
    "ks:ks_type":"HABITATION",
    "name:eng_x_preferred":[
        "Bennur Camp"
    ],
    "wof:name":"Bennur Camp",
    "wof:placetype":"locality",
    "wof:population":216
},
  "geometry": {"coordinates":[76.759968,15.514223],"type":"Point"}
}