{
  "type": "Feature",
  "properties": {
    "iso:country":"IN",
    "ks:ks_name":"Pure Bholai",
    "ks:ks_pop":317,
    "ks:ks_type":"HABITATION",
    "name:eng_x_preferred":[
        "Pure Bholai"
    ],
    "wof:name":"Pure Bholai",
    "wof:placetype":"locality",
    "wof:population":317
},
  "geometry": {"coordinates":[81.065427,26.256379],"type":"Point"}
}