{
  "type": "Feature",
  "properties": {
    "gn:admin1_code":"13.0",
    "gn:admin2_code":"594.0",
    "gn:asciiname":"Kupravalli",
    "gn:country_code":"IN",
    "gn:dem":8,
    "gn:feature_class":"P",
    "gn:feature_code":"PPL",
    "gn:name":"Kupravalli",
    "gn:population":0,
    "gn:timezone":"Asia/Kolkata",
    "iso:country":"IN",
    "wof:name":"Kupravalli",
    "wof:placetype":"locality"
},
  "geometry": {"coordinates":[76.00196,10.6746],"type":"Point"}
}