{
  "type": "Feature",
  "properties": {
    "iso:country":"IN",
    "ks:ks_name":"Birajpur",
    "ks:ks_pop":113,
    "ks:ks_type":"VILLAGE",
    "name:eng_x_preferred":[
        "Birajpur"
    ],
    "wof:name":"Birajpur",
    "wof:placetype":"locality",
    "wof:population":113
},
  "geometry": {"coordinates":[86.696623,24.386973],"type":"Point"}
}