{
  "type": "Feature",
  "properties": {
    "gn:admin1_code":"2",
    "gn:admin2_code":"544.0",
    "gn:asciiname":"Peta",
    "gn:country_code":"IN",
    "gn:dem":11,
    "gn:feature_class":"P",
    "gn:feature_code":"PPL",
    "gn:name":"Peta",
    "gn:population":0,
    "gn:timezone":"Asia/Kolkata",
    "iso:country":"IN",
    "name:isl_x_preferred":[
        "Peta"
    ],
    "wof:name":"Peta",
    "wof:placetype":"neighbourhood"
},
  "geometry": {"coordinates":[82.83968,17.4838],"type":"Point"}
}