{
  "type": "Feature",
  "properties": {
    "iso:country":"IN",
    "ks:ks_name":"Nemori",
    "ks:ks_pop":387,
    "ks:ks_type":"HABITATION",
    "name:eng_x_preferred":[
        "Nemori"
    ],
    "wof:name":"Nemori",
    "wof:placetype":"locality",
    "wof:population":387
},
  "geometry": {"coordinates":[86.323583,23.966959],"type":"Point"}
}