{
  "type": "Feature",
  "properties": {
    "iso:country":"IN",
    "ks:ks_name":"Kuladiha",
    "ks:ks_pop":379,
    "ks:ks_type":"VILLAGE",
    "name:eng_x_preferred":[
        "Kuladiha"
    ],
    "wof:name":"Kuladiha",
    "wof:placetype":"locality",
    "wof:population":379
},
  "geometry": {"coordinates":[86.121492,21.427161],"type":"Point"}
}