{
  "type": "Feature",
  "properties": {
    "iso:country":"IN",
    "ks:ks_name":"Deshlopa",
    "ks:ks_pop":1108,
    "ks:ks_type":"VILLAGE",
    "ks:ks_uagg_main":0,
    "name:eng_x_preferred":[
        "Deshlopa"
    ],
    "wof:name":"Deshlopa",
    "wof:placetype":"neighbourhood",
    "wof:population":1108
},
  "geometry": {"coordinates":[87.31115,23.713669],"type":"Point"}
}