{
  "type": "Feature",
  "properties": {
    "gn:admin1_code":"35",
    "gn:admin2_code":"427.0",
    "gn:asciiname":"Nawalpur",
    "gn:country_code":"IN",
    "gn:dem":393,
    "gn:feature_class":"P",
    "gn:feature_code":"PPL",
    "gn:name":"Nawalpur",
    "gn:population":0,
    "gn:timezone":"Asia/Kolkata",
    "iso:country":"IN",
    "name:ceb_x_preferred":[
        "Nawalpur"
    ],
    "name:msa_x_preferred":[
        "Nawalpur"
    ],
    "name:nep_x_preferred":[
        "\u0928\u0935\u0932\u092a\u0941\u0930"
    ],
    "name:new_x_preferred":[
        "\u0928\u0935\u0932\u092a\u0941\u0930"
    ],
    "name:pol_x_preferred":[
        "Nawalpur"
    ],
    "wof:name":"Nawalpur",
    "wof:placetype":"locality"
},
  "geometry": {"coordinates":[79.07804,23.72494],"type":"Point"}
}