{
  "type": "Feature",
  "properties": {
    "iso:country":"IN",
    "ks:ks_name":"Bagia Tatarpur",
    "ks:ks_pop":83,
    "ks:ks_type":"HABITATION",
    "name:eng_x_preferred":[
        "Bagia Tatarpur"
    ],
    "wof:name":"Bagia Tatarpur",
    "wof:placetype":"locality",
    "wof:population":83
},
  "geometry": {"coordinates":[79.223946,26.441049],"type":"Point"}
}