{
  "type": "Feature",
  "properties": {
    "iso:country":"IN",
    "ks:ks_alt_nam":"MIDC",
    "ks:ks_name":"Midc",
    "ks:ks_pop":259,
    "ks:ks_type":"HABITATION",
    "ks:ks_uagg_main":0,
    "name:eng_x_preferred":[
        "Midc"
    ],
    "wof:name":"Midc",
    "wof:placetype":"neighbourhood",
    "wof:population":259
},
  "geometry": {"coordinates":[74.698852,19.152827],"type":"Point"}
}