{
  "type": "Feature",
  "properties": {
    "iso:country":"IN",
    "ks:ks_name":"Barbandha",
    "ks:ks_pop":881,
    "ks:ks_type":"VILLAGE",
    "name:eng_x_preferred":[
        "Barbandha"
    ],
    "wof:name":"Barbandha",
    "wof:placetype":"locality",
    "wof:population":881
},
  "geometry": {"coordinates":[83.066013,20.411498],"type":"Point"}
}