{
  "type": "Feature",
  "properties": {
    "gn:admin1_code":"36.0",
    "gn:admin2_code":"158.0",
    "gn:asciiname":"Jahangirganj",
    "gn:country_code":"IN",
    "gn:dem":111,
    "gn:feature_class":"P",
    "gn:feature_code":"PPL",
    "gn:name":"J\u0101h\u0101ngirganj",
    "gn:population":0,
    "gn:timezone":"Asia/Kolkata",
    "iso:country":"IN",
    "wof:name":"Jahangirganj",
    "wof:placetype":"locality"
},
  "geometry": {"coordinates":[81.39676,26.42254],"type":"Point"}
}