{
  "type": "Feature",
  "properties": {
    "gn:admin1_code":"34.0",
    "gn:admin2_code":"238.0",
    "gn:asciiname":"Nabinagar",
    "gn:country_code":"IN",
    "gn:dem":71,
    "gn:feature_class":"P",
    "gn:feature_code":"PPL",
    "gn:name":"Nab\u012bnagar",
    "gn:population":0,
    "gn:timezone":"Asia/Kolkata",
    "iso:country":"IN",
    "name:ben_x_preferred":[
        "\u09a8\u09ac\u09c0\u09a8\u0997\u09b0"
    ],
    "name:bpy_x_preferred":[
        "\u09a8\u09ac\u09c0\u09a8\u0997\u09b0"
    ],
    "name:ceb_x_preferred":[
        "Nab\u012bnagar"
    ],
    "name:hif_x_preferred":[
        "Nabinagar"
    ],
    "name:ita_x_preferred":[
        "Nabinagar"
    ],
    "name:mlg_x_preferred":[
        "Nabinagar"
    ],
    "name:msa_x_preferred":[
        "Nabinagar"
    ],
    "name:new_x_preferred":[
        "\u0928\u0935\u093f\u0928\u0917\u0930"
    ],
    "name:nld_x_preferred":[
        "Nabinagar"
    ],
    "name:por_x_preferred":[
        "Nabinagar"
    ],
    "name:spa_x_preferred":[
        "Nabinagar"
    ],
    "name:vie_x_preferred":[
        "Nabinagar"
    ],
    "name:zho_x_preferred":[
        "\u7eb3\u6bd4\u7eb3\u52a0\u5c14"
    ],
    "wof:name":"Nabinagar",
    "wof:placetype":"locality"
},
  "geometry": {"coordinates":[86.15546999999999,25.03027],"type":"Point"}
}