{
  "type": "Feature",
  "properties": {
    "iso:country":"IN",
    "ks:ks_name":"Kadambagudi",
    "ks:ks_pop":113,
    "ks:ks_type":"HABITATION",
    "name:eng_x_preferred":[
        "Kadambagudi"
    ],
    "wof:name":"Kadambagudi",
    "wof:placetype":"locality",
    "wof:population":113
},
  "geometry": {"coordinates":[79.546915,10.710499],"type":"Point"}
}