{
  "type": "Feature",
  "properties": {
    "iso:country":"IN",
    "ks:ks_name":"Dolimal",
    "ks:ks_pop":107,
    "ks:ks_type":"HABITATION",
    "name:eng_x_preferred":[
        "Dolimal"
    ],
    "wof:name":"Dolimal",
    "wof:placetype":"locality",
    "wof:population":107
},
  "geometry": {"coordinates":[82.80812299999999,19.034271],"type":"Point"}
}