{
  "type": "Feature",
  "properties": {
    "iso:country":"IN",
    "ks:ks_name":"1 L",
    "ks:ks_pop":27,
    "ks:ks_type":"HABITATION",
    "name:eng_x_preferred":[
        "1 L"
    ],
    "wof:name":"1 L",
    "wof:placetype":"locality",
    "wof:population":27
},
  "geometry": {"coordinates":[73.74913100000001,29.920439],"type":"Point"}
}