{
  "type": "Feature",
  "properties": {
    "iso:country":"IN",
    "ks:ks_name":"Chaukijore",
    "ks:ks_pop":752,
    "ks:ks_type":"HABITATION",
    "name:eng_x_preferred":[
        "Chaukijore"
    ],
    "wof:name":"Chaukijore",
    "wof:placetype":"locality",
    "wof:population":752
},
  "geometry": {"coordinates":[86.527781,24.824303],"type":"Point"}
}