{
  "type": "Feature",
  "properties": {
    "iso:country":"IN",
    "ks:ks_name":"Odiyana Family",
    "ks:ks_pop":189,
    "ks:ks_type":"HABITATION",
    "name:eng_x_preferred":[
        "Odiyana Family"
    ],
    "wof:name":"Odiyana Family",
    "wof:placetype":"locality",
    "wof:population":189
},
  "geometry": {"coordinates":[75.73514900000001,12.38118],"type":"Point"}
}