{
  "type": "Feature",
  "properties": {
    "iso:country":"IN",
    "ks:ks_alt_nam":"SRIRAMPUR",
    "ks:ks_name":"Srirampur",
    "ks:ks_pop":1700,
    "ks:ks_type":"HABITATION",
    "name:eng_x_preferred":[
        "Srirampur"
    ],
    "wof:name":"Srirampur",
    "wof:placetype":"locality",
    "wof:population":1700
},
  "geometry": {"coordinates":[88.673401,23.028771],"type":"Point"}
}