{
  "type": "Feature",
  "properties": {
    "iso:country":"IN",
    "ks:ks_name":"Bhatdi",
    "ks:ks_pop":1024,
    "ks:ks_type":"VILLAGE",
    "ks:ks_uagg_main":0,
    "name:eng_x_preferred":[
        "Bhatdi"
    ],
    "wof:name":"Bhatdi",
    "wof:placetype":"neighbourhood",
    "wof:population":1024
},
  "geometry": {"coordinates":[86.26535699999999,23.721656],"type":"Point"}
}