{
  "type": "Feature",
  "properties": {
    "gn:admin1_code":"35",
    "gn:admin2_code":"435.0",
    "gn:asciiname":"Unkarpura",
    "gn:country_code":"IN",
    "gn:dem":485,
    "gn:feature_class":"P",
    "gn:feature_code":"PPL",
    "gn:name":"Unk\u0101rpura",
    "gn:population":0,
    "gn:timezone":"Asia/Kolkata",
    "iso:country":"IN",
    "wof:name":"Unkarpura",
    "wof:placetype":"locality"
},
  "geometry": {"coordinates":[75.48671999999998,23.19016],"type":"Point"}
}