{
  "type": "Feature",
  "properties": {
    "iso:country":"IN",
    "ks:ks_alt_nam":"Jharana ghughri",
    "ks:ks_name":"Jharana Ghughri",
    "ks:ks_pop":1038,
    "ks:ks_type":"HABITATION",
    "name:eng_x_preferred":[
        "Jharana Ghughri"
    ],
    "wof:name":"Jharana Ghughri",
    "wof:placetype":"locality",
    "wof:population":1038
},
  "geometry": {"coordinates":[80.90521699999999,22.788276],"type":"Point"}
}