{
  "type": "Feature",
  "properties": {
    "iso:country":"IN",
    "ks:ks_name":"Kolathupalayam",
    "ks:ks_pop":296,
    "ks:ks_type":"HABITATION",
    "name:eng_x_preferred":[
        "Kolathupalayam"
    ],
    "wof:name":"Kolathupalayam",
    "wof:placetype":"locality",
    "wof:population":296
},
  "geometry": {"coordinates":[77.649136,11.023153],"type":"Point"}
}