{
  "type": "Feature",
  "properties": {
    "iso:country":"IN",
    "ks:ks_alt_nam":"RAJ MANGAL PARA",
    "ks:ks_name":"Raj Mangal Para",
    "ks:ks_pop":73,
    "ks:ks_type":"HABITATION",
    "ks:ks_uagg_main":0,
    "name:eng_x_preferred":[
        "Raj Mangal Para"
    ],
    "wof:name":"Raj Mangal Para",
    "wof:placetype":"neighbourhood",
    "wof:population":73
},
  "geometry": {"coordinates":[91.45412,23.873764],"type":"Point"}
}