{
  "type": "Feature",
  "properties": {
    "iso:country":"IN",
    "ks:ks_name":"Vishal Nagar",
    "ks:ks_pop":100,
    "ks:ks_type":"HABITATION",
    "name:eng_x_preferred":[
        "Vishal Nagar"
    ],
    "wof:name":"Vishal Nagar",
    "wof:placetype":"locality",
    "wof:population":100
},
  "geometry": {"coordinates":[78.91298999999999,27.227464],"type":"Point"}
}