{
  "type": "Feature",
  "properties": {
    "iso:country":"IN",
    "ks:ks_name":"Salaraitoli",
    "ks:ks_pop":323,
    "ks:ks_type":"VILLAGE",
    "name:eng_x_preferred":[
        "Salaraitoli"
    ],
    "wof:name":"Salaraitoli",
    "wof:placetype":"locality",
    "wof:population":323
},
  "geometry": {"coordinates":[79.43544,30.422484],"type":"Point"}
}