{
  "type": "Feature",
  "properties": {
    "iso:country":"IN",
    "ks:ks_name":"Bharkibhatta",
    "ks:ks_pop":262,
    "ks:ks_type":"HABITATION",
    "name:eng_x_preferred":[
        "Bharkibhatta"
    ],
    "wof:name":"Bharkibhatta",
    "wof:placetype":"locality",
    "wof:population":262
},
  "geometry": {"coordinates":[82.488626,19.688578],"type":"Point"}
}