{
  "type": "Feature",
  "properties": {
    "iso:country":"IN",
    "ks:ks_name":"Sambaha",
    "ks:ks_pop":1063,
    "ks:ks_type":"VILLAGE",
    "name:eng_x_preferred":[
        "Sambaha"
    ],
    "wof:name":"Sambaha",
    "wof:placetype":"locality",
    "wof:population":1063
},
  "geometry": {"coordinates":[85.49768,26.040657],"type":"Point"}
}