{
  "type": "Feature",
  "properties": {
    "iso:country":"IN",
    "ks:ks_name":"Chelyadka",
    "ks:ks_pop":55,
    "ks:ks_type":"HABITATION",
    "name:eng_x_preferred":[
        "Chelyadka"
    ],
    "wof:name":"Chelyadka",
    "wof:placetype":"locality",
    "wof:population":55
},
  "geometry": {"coordinates":[75.20825499999999,12.680782],"type":"Point"}
}