{
  "type": "Feature",
  "properties": {
    "gn:admin1_code":"34.0",
    "gn:admin2_code":"236.0",
    "gn:asciiname":"Chandaila",
    "gn:country_code":"IN",
    "gn:dem":95,
    "gn:feature_class":"P",
    "gn:feature_code":"PPL",
    "gn:name":"Chandaila",
    "gn:population":0,
    "gn:timezone":"Asia/Kolkata",
    "iso:country":"IN",
    "wof:name":"Chandaila",
    "wof:placetype":"locality"
},
  "geometry": {"coordinates":[85.31683000000002,24.90196],"type":"Point"}
}