{
  "type": "Feature",
  "properties": {
    "iso:country":"IN",
    "ks:ks_name":"Nagla Tarak",
    "ks:ks_pop":373,
    "ks:ks_type":"HABITATION",
    "ks:ks_uagg_main":0,
    "name:eng_x_preferred":[
        "Nagla Tarak"
    ],
    "wof:name":"Nagla Tarak",
    "wof:placetype":"neighbourhood",
    "wof:population":373
},
  "geometry": {"coordinates":[78.86284499999999,27.597638],"type":"Point"}
}