{
  "type": "Feature",
  "properties": {
    "iso:country":"IN",
    "ks:ks_name":"Chakpipulbaria",
    "ks:ks_pop":602,
    "ks:ks_type":"VILLAGE",
    "ks:ks_uagg_main":0,
    "name:eng_x_preferred":[
        "Chakpipulbaria"
    ],
    "wof:name":"Chakpipulbaria",
    "wof:placetype":"neighbourhood",
    "wof:population":602
},
  "geometry": {"coordinates":[88.69801099999999,23.91437],"type":"Point"}
}