{
  "type": "Feature",
  "properties": {
    "iso:country":"IN",
    "ks:ks_name":"Jadhari",
    "ks:ks_pop":1083,
    "ks:ks_type":"VILLAGE",
    "name:eng_x_preferred":[
        "Jadhari"
    ],
    "wof:name":"Jadhari",
    "wof:placetype":"locality",
    "wof:population":1083
},
  "geometry": {"coordinates":[82.29438399999999,23.112651],"type":"Point"}
}