{
  "type": "Feature",
  "properties": {
    "iso:country":"IN",
    "ks:ks_name":"Benji",
    "ks:ks_pop":128,
    "ks:ks_type":"VILLAGE",
    "name:eng_x_preferred":[
        "Benji"
    ],
    "wof:name":"Benji",
    "wof:placetype":"locality",
    "wof:population":128
},
  "geometry": {"coordinates":[79.00707800000001,30.372123],"type":"Point"}
}