{
  "type": "Feature",
  "properties": {
    "iso:country":"IN",
    "ks:ks_alt_nam":"2 No. sensowa",
    "ks:ks_name":"2 No. Sensowa",
    "ks:ks_pop":312,
    "ks:ks_type":"HABITATION",
    "name:eng_x_preferred":[
        "2 No. Sensowa"
    ],
    "wof:name":"2 No. Sensowa",
    "wof:placetype":"locality",
    "wof:population":312
},
  "geometry": {"coordinates":[93.93223999999999,26.567661],"type":"Point"}
}