{
  "type": "Feature",
  "properties": {
    "iso:country":"IN",
    "ks:ks_name":"Melina Heggarani",
    "ks:ks_pop":159,
    "ks:ks_type":"HABITATION",
    "name:eng_x_preferred":[
        "Melina Heggarani"
    ],
    "wof:name":"Melina Heggarani",
    "wof:placetype":"locality",
    "wof:population":159
},
  "geometry": {"coordinates":[74.741012,14.452181],"type":"Point"}
}