{
  "type": "Feature",
  "properties": {
    "iso:country":"IN",
    "ks:ks_name":"Gallagaon",
    "ks:ks_pop":317,
    "ks:ks_type":"VILLAGE",
    "name:eng_x_preferred":[
        "Gallagaon"
    ],
    "wof:name":"Gallagaon",
    "wof:placetype":"locality",
    "wof:population":317
},
  "geometry": {"coordinates":[80.06333600000001,29.437501],"type":"Point"}
}