{
  "type": "Feature",
  "properties": {
    "iso:country":"IN",
    "ks:ks_name":"Gorakshwasti",
    "ks:ks_pop":491,
    "ks:ks_type":"HABITATION",
    "name:eng_x_preferred":[
        "Gorakshwasti"
    ],
    "wof:name":"Gorakshwasti",
    "wof:placetype":"locality",
    "wof:population":491
},
  "geometry": {"coordinates":[74.377144,19.507486],"type":"Point"}
}