{
  "type": "Feature",
  "properties": {
    "iso:country":"IN",
    "ks:ks_name":"Kaleen Purwa",
    "ks:ks_pop":107,
    "ks:ks_type":"HABITATION",
    "name:eng_x_preferred":[
        "Kaleen Purwa"
    ],
    "wof:name":"Kaleen Purwa",
    "wof:placetype":"locality",
    "wof:population":107
},
  "geometry": {"coordinates":[80.053749,26.74052],"type":"Point"}
}