{
  "type": "Feature",
  "properties": {
    "iso:country":"IN",
    "ks:ks_alt_nam":"Siur\u012b",
    "ks:ks_name":"Siuri",
    "ks:ks_type":"VILLAGE",
    "name:eng_x_preferred":[
        "Siuri"
    ],
    "name:eng_x_variant":[
        "Siur\u012b"
    ],
    "wof:name":"Siuri",
    "wof:placetype":"locality"
},
  "geometry": {"coordinates":[83.676788,25.696269],"type":"Point"}
}