{
  "type": "Feature",
  "properties": {
    "iso:country":"IN",
    "ks:ks_name":"Dandabahal",
    "ks:ks_pop":0,
    "ks:ks_type":"VILLAGE",
    "name:eng_x_preferred":[
        "Dandabahal"
    ],
    "wof:name":"Dandabahal",
    "wof:placetype":"locality",
    "wof:population":0
},
  "geometry": {"coordinates":[84.860952,21.744101],"type":"Point"}
}