{
  "type": "Feature",
  "properties": {
    "iso:country":"IN",
    "ks:ks_name":"Kursahi",
    "ks:ks_type":"VILLAGE",
    "name:eng_x_preferred":[
        "Kursahi"
    ],
    "wof:name":"Kursahi",
    "wof:placetype":"locality"
},
  "geometry": {"coordinates":[81.664751,27.442305],"type":"Point"}
}