{
  "type": "Feature",
  "properties": {
    "iso:country":"IN",
    "ks:ks_name":"Badaposi",
    "ks:ks_pop":505,
    "ks:ks_type":"VILLAGE",
    "name:eng_x_preferred":[
        "Badaposi"
    ],
    "wof:name":"Badaposi",
    "wof:placetype":"locality",
    "wof:population":505
},
  "geometry": {"coordinates":[86.032932,21.616625],"type":"Point"}
}