{
  "type": "Feature",
  "properties": {
    "gn:admin1_code":"28.0",
    "gn:admin2_code":"337",
    "gn:asciiname":"Hingalganj",
    "gn:country_code":"IN",
    "gn:dem":9,
    "gn:feature_class":"P",
    "gn:feature_code":"PPL",
    "gn:name":"Hingalganj",
    "gn:population":0,
    "gn:timezone":"Asia/Kolkata",
    "iso:country":"IN",
    "name:und_x_variant":[
        "Hingulganj",
        "Hingalganj"
    ],
    "wof:name":"Hingalganj",
    "wof:placetype":"locality"
},
  "geometry": {"coordinates":[88.98989,22.47051],"type":"Point"}
}