{
  "type": "Feature",
  "properties": {
    "iso:country":"IN",
    "ks:ks_name":"Lower Tola",
    "ks:ks_pop":289,
    "ks:ks_type":"HABITATION",
    "name:eng_x_preferred":[
        "Lower Tola"
    ],
    "wof:name":"Lower Tola",
    "wof:placetype":"locality",
    "wof:population":289
},
  "geometry": {"coordinates":[86.36951000000001,24.55367],"type":"Point"}
}