{
  "type": "Feature",
  "properties": {
    "gn:admin1_code":"2.0",
    "gn:admin2_code":"542.0",
    "gn:asciiname":"Rayimanguda",
    "gn:country_code":"IN",
    "gn:dem":295,
    "gn:feature_class":"P",
    "gn:feature_code":"PPL",
    "gn:name":"R\u0101yim\u0101ng\u016bda",
    "gn:population":0,
    "gn:timezone":"Asia/Kolkata",
    "iso:country":"IN",
    "ks:ks_name":"Rayamanuguda",
    "ks:ks_pop":20,
    "ks:ks_type":"HABITATION",
    "name:eng_x_preferred":[
        "Rayamanuguda"
    ],
    "name:eng_x_variant":[
        "Rayimanguda"
    ],
    "wof:name":"Rayamanuguda",
    "wof:placetype":"locality",
    "wof:population":20
},
  "geometry": {"coordinates":[83.87053899999999,18.593229],"type":"Point"}
}