{
  "type": "Feature",
  "properties": {
    "iso:country":"IN",
    "ks:ks_alt_nam":"PACHHIM TOLA",
    "ks:ks_name":"Pachhim Tola",
    "ks:ks_pop":693,
    "ks:ks_type":"HABITATION",
    "name:eng_x_preferred":[
        "Pachhim Tola"
    ],
    "wof:name":"Pachhim Tola",
    "wof:placetype":"locality",
    "wof:population":693
},
  "geometry": {"coordinates":[86.732815,25.277622],"type":"Point"}
}