{
  "type": "Feature",
  "properties": {
    "gn:admin1_code":"19.0",
    "gn:admin2_code":"575.0",
    "gn:asciiname":"Koyyuru",
    "gn:country_code":"IN",
    "gn:dem":122,
    "gn:feature_class":"P",
    "gn:feature_code":"PPLL",
    "gn:name":"Koyy\u016bru",
    "gn:population":0,
    "gn:timezone":"Asia/Kolkata",
    "iso:country":"IN",
    "ks:ks_name":"Koyyur",
    "ks:ks_pop":4592,
    "ks:ks_type":"VILLAGE",
    "name:eng_x_preferred":[
        "Koyyur"
    ],
    "name:eng_x_variant":[
        "Koyyuru"
    ],
    "name:new_x_preferred":[
        "\u0915\u094b\u092f\u094d\u092f\u0942\u0930\u0941 \u092e\u0923\u094d\u0921\u0932"
    ],
    "name:tam_x_preferred":[
        "\u0b95\u0bca\u0baf\u0bcd\u0baf\u0bc2\u0bb0\u0bcd \u0bae\u0ba3\u0bcd\u0b9f\u0bb2\u0bae\u0bcd"
    ],
    "name:tel_x_preferred":[
        "\u0c15\u0c4a\u0c2f\u0c4d\u0c2f\u0c42\u0c30\u0c41"
    ],
    "name:urd_x_preferred":[
        "\u06a9\u0648\u06cc\u0648\u0631\u0648"
    ],
    "name:vie_x_preferred":[
        "Koyyuru"
    ],
    "wof:name":"Koyyur",
    "wof:placetype":"locality",
    "wof:population":4592
},
  "geometry": {"coordinates":[75.294595,12.951957],"type":"Point"}
}