{
  "type": "Feature",
  "properties": {
    "iso:country":"IN",
    "ks:ks_name":"Rampakhara",
    "ks:ks_pop":0,
    "ks:ks_type":"VILLAGE",
    "name:eng_x_preferred":[
        "Rampakhara"
    ],
    "wof:name":"Rampakhara",
    "wof:placetype":"locality",
    "wof:population":0
},
  "geometry": {"coordinates":[82.746129,22.318655],"type":"Point"}
}