{
  "type": "Feature",
  "properties": {
    "iso:country":"IN",
    "ks:ks_name":"Mundali",
    "ks:ks_pop":353,
    "ks:ks_type":"VILLAGE",
    "name:eng_x_preferred":[
        "Mundali"
    ],
    "wof:name":"Mundali",
    "wof:placetype":"locality",
    "wof:population":353
},
  "geometry": {"coordinates":[85.463165,20.352801],"type":"Point"}
}