{
  "type": "Feature",
  "properties": {
    "gn:admin1_code":"39",
    "gn:admin2_code":"56.0",
    "gn:asciiname":"Yamda Thach",
    "gn:country_code":"IN",
    "gn:dem":2238,
    "gn:feature_class":"P",
    "gn:feature_code":"PPL",
    "gn:name":"Yamda Th\u0101ch",
    "gn:population":0,
    "gn:timezone":"Asia/Kolkata",
    "iso:country":"IN",
    "wof:name":"Yamda Thach",
    "wof:placetype":"locality"
},
  "geometry": {"coordinates":[77.88606,31.00034],"type":"Point"}
}