{
  "type": "Feature",
  "properties": {
    "gn:admin1_code":"11",
    "gn:admin2_code":"32.0",
    "gn:asciiname":"Bashnach",
    "gn:country_code":"IN",
    "gn:dem":1920,
    "gn:feature_class":"P",
    "gn:feature_code":"PPL",
    "gn:name":"Bashnach",
    "gn:population":0,
    "gn:timezone":"Asia/Kolkata",
    "iso:country":"IN",
    "wof:name":"Bashnach",
    "wof:placetype":"locality"
},
  "geometry": {"coordinates":[77.54248,30.75004],"type":"Point"}
}