{
  "type": "Feature",
  "properties": {
    "iso:country":"IN",
    "ks:ks_alt_nam":"RATANPAL",
    "ks:ks_name":"Ratanpal",
    "ks:ks_pop":213,
    "ks:ks_type":"HABITATION",
    "name:eng_x_preferred":[
        "Ratanpal"
    ],
    "wof:name":"Ratanpal",
    "wof:placetype":"locality",
    "wof:population":213
},
  "geometry": {"coordinates":[85.592876,22.38656],"type":"Point"}
}