{
  "type": "Feature",
  "properties": {
    "iso:country":"IN",
    "ks:ks_name":"Kulajamin",
    "ks:ks_pop":87,
    "ks:ks_type":"VILLAGE",
    "name:eng_x_preferred":[
        "Kulajamin"
    ],
    "wof:name":"Kulajamin",
    "wof:placetype":"locality",
    "wof:population":87
},
  "geometry": {"coordinates":[78.490385,30.041792],"type":"Point"}
}