{
  "type": "Feature",
  "properties": {
    "gn:admin1_code":"38.0",
    "gn:admin2_code":"352.0",
    "gn:asciiname":"Motijharna",
    "gn:country_code":"IN",
    "gn:dem":41,
    "gn:feature_class":"P",
    "gn:feature_code":"PPL",
    "gn:name":"Mot\u012bjharna",
    "gn:population":0,
    "gn:timezone":"Asia/Kolkata",
    "iso:country":"IN",
    "ks:ks_name":"Moti Jharna",
    "ks:ks_pop":2424,
    "ks:ks_type":"VILLAGE",
    "ks:ks_uagg_main":0,
    "name:eng_x_preferred":[
        "Moti Jharna"
    ],
    "wof:name":"Moti Jharna",
    "wof:placetype":"neighbourhood",
    "wof:population":2424
},
  "geometry": {"coordinates":[87.744935,25.21167],"type":"Point"}
}