{
  "type": "Feature",
  "properties": {
    "iso:country":"IN",
    "ks:ks_alt_nam":"bandaralavaripalle",
    "ks:ks_name":"Bandaralavaripalle",
    "ks:ks_pop":22,
    "ks:ks_type":"HABITATION",
    "name:eng_x_preferred":[
        "Bandaralavaripalle"
    ],
    "wof:name":"Bandaralavaripalle",
    "wof:placetype":"locality",
    "wof:population":22
},
  "geometry": {"coordinates":[79.041684,13.69958],"type":"Point"}
}