{
  "type": "Feature",
  "properties": {
    "iso:country":"IN",
    "ks:ks_name":"Patti Jhamra Shahbad 253",
    "ks:ks_pop":2456,
    "ks:ks_type":"HABITATION",
    "name:eng_x_preferred":[
        "Patti Jhamra Shahbad 253"
    ],
    "wof:name":"Patti Jhamra Shahbad 253",
    "wof:placetype":"locality",
    "wof:population":2456
},
  "geometry": {"coordinates":[76.885588,30.134346],"type":"Point"}
}