{
  "type": "Feature",
  "properties": {
    "gn:admin1_code":"2.0",
    "gn:asciiname":"Poimala",
    "gn:country_code":"IN",
    "gn:dem":782,
    "gn:feature_class":"P",
    "gn:feature_code":"PPL",
    "gn:name":"Poim\u0101la",
    "gn:population":0,
    "gn:timezone":"Asia/Kolkata",
    "iso:country":"IN",
    "ks:ks_name":"Poyimala",
    "ks:ks_pop":141,
    "ks:ks_type":"HABITATION",
    "name:eng_x_preferred":[
        "Poyimala"
    ],
    "name:eng_x_variant":[
        "Poimala"
    ],
    "wof:name":"Poyimala",
    "wof:placetype":"locality",
    "wof:population":141
},
  "geometry": {"coordinates":[83.14433699999999,18.752118],"type":"Point"}
}