{
  "type": "Feature",
  "properties": {
    "iso:country":"IN",
    "ks:ks_name":"Mordhi",
    "ks:ks_pop":1830,
    "ks:ks_type":"VILLAGE",
    "name:eng_x_preferred":[
        "Mordhi"
    ],
    "wof:name":"Mordhi",
    "wof:placetype":"locality",
    "wof:population":1830
},
  "geometry": {"coordinates":[74.23470500000001,22.337873],"type":"Point"}
}