{
  "type": "Feature",
  "properties": {
    "iso:country":"IN",
    "ks:ks_name":"Bhulsi Khurd",
    "ks:ks_pop":227,
    "ks:ks_type":"VILLAGE",
    "name:eng_x_preferred":[
        "Bhulsi Khurd"
    ],
    "wof:name":"Bhulsi Khurd",
    "wof:placetype":"locality",
    "wof:population":227
},
  "geometry": {"coordinates":[83.832297,23.347904],"type":"Point"}
}