{
  "type": "Feature",
  "properties": {
    "gn:admin1_code":"35.0",
    "gn:admin2_code":"439.0",
    "gn:asciiname":"Kelodkartal",
    "gn:country_code":"IN",
    "gn:dem":581,
    "gn:feature_class":"P",
    "gn:feature_code":"PPL",
    "gn:name":"Kelodkart\u0101l",
    "gn:population":0,
    "gn:timezone":"Asia/Kolkata",
    "iso:country":"IN",
    "ks:ks_name":"Kalod Kartal",
    "ks:ks_pop":7668,
    "ks:ks_type":"VILLAGE",
    "name:eng_x_preferred":[
        "Kalod Kartal"
    ],
    "name:eng_x_variant":[
        "Kelodkartal"
    ],
    "wof:name":"Kalod Kartal",
    "wof:placetype":"locality",
    "wof:population":7668
},
  "geometry": {"coordinates":[75.886822,22.638485],"type":"Point"}
}