{
  "type": "Feature",
  "properties": {
    "iso:country":"IN",
    "ks:ks_name":"Yerkheda",
    "ks:ks_pop":18872,
    "ks:ks_type":"URBAN",
    "ks:ks_uagg_main":0,
    "name:eng_x_preferred":[
        "Yerkheda"
    ],
    "wof:name":"Yerkheda",
    "wof:placetype":"neighbourhood",
    "wof:population":18872
},
  "geometry": {"coordinates":[79.187196,21.213024],"type":"Point"}
}