{
  "type": "Feature",
  "properties": {
    "iso:country":"IN",
    "ks:ks_alt_nam":"TAHI BIGHA",
    "ks:ks_name":"Tahi Bigha",
    "ks:ks_pop":255,
    "ks:ks_type":"HABITATION",
    "name:eng_x_preferred":[
        "Tahi Bigha"
    ],
    "wof:name":"Tahi Bigha",
    "wof:placetype":"locality",
    "wof:population":255
},
  "geometry": {"coordinates":[84.978971,24.893941],"type":"Point"}
}