{
  "type": "Feature",
  "properties": {
    "iso:country":"IN",
    "ks:ks_name":"Pundaje",
    "ks:ks_pop":143,
    "ks:ks_type":"HABITATION",
    "name:eng_x_preferred":[
        "Pundaje"
    ],
    "wof:name":"Pundaje",
    "wof:placetype":"locality",
    "wof:population":143
},
  "geometry": {"coordinates":[75.24296,12.966888],"type":"Point"}
}