{
  "type": "Feature",
  "properties": {
    "iso:country":"IN",
    "ks:ks_name":"Gopalpur Bishunpur Lala",
    "ks:ks_pop":356,
    "ks:ks_type":"VILLAGE",
    "name:eng_x_preferred":[
        "Gopalpur Bishunpur Lala"
    ],
    "wof:name":"Gopalpur Bishunpur Lala",
    "wof:placetype":"locality",
    "wof:population":356
},
  "geometry": {"coordinates":[85.49898899999999,26.043123],"type":"Point"}
}