{
  "type": "Feature",
  "properties": {
    "gn:admin1_code":"13.0",
    "gn:admin2_code":"591.0",
    "gn:asciiname":"Pantalayini",
    "gn:country_code":"IN",
    "gn:dem":23,
    "gn:feature_class":"P",
    "gn:feature_code":"PPL",
    "gn:name":"Pantal\u0101yini",
    "gn:population":0,
    "gn:timezone":"Asia/Kolkata",
    "iso:country":"IN",
    "wof:name":"Pantalayini",
    "wof:placetype":"locality"
},
  "geometry": {"coordinates":[75.69141999999999,11.45384],"type":"Point"}
}