{
  "type": "Feature",
  "properties": {
    "gn:admin1_code":"40",
    "gn:admin2_code":"541.0",
    "gn:asciiname":"Mangamuthaya Banjar",
    "gn:country_code":"IN",
    "gn:dem":127,
    "gn:feature_class":"P",
    "gn:feature_code":"PPL",
    "gn:name":"Mangamuthaya Banjar",
    "gn:population":0,
    "gn:timezone":"Asia/Kolkata",
    "iso:country":"IN",
    "wof:name":"Mangamuthaya Banjar",
    "wof:placetype":"locality"
},
  "geometry": {"coordinates":[80.65634,17.20802999999999],"type":"Point"}
}