{
  "type": "Feature",
  "properties": {
    "gn:admin1_code":"11.0",
    "gn:admin2_code":"23.0",
    "gn:asciiname":"Hathu Dhar",
    "gn:country_code":"IN",
    "gn:dem":1280,
    "gn:feature_class":"P",
    "gn:feature_code":"PPL",
    "gn:name":"Hathu Dh\u0101r",
    "gn:population":0,
    "gn:timezone":"Asia/Kolkata",
    "iso:country":"IN",
    "wof:name":"Hathu Dhar",
    "wof:placetype":"locality"
},
  "geometry": {"coordinates":[75.97865,32.3899],"type":"Point"}
}