{
  "type": "Feature",
  "properties": {
    "gn:admin1_code":"36.0",
    "gn:admin2_code":"175.0",
    "gn:asciiname":"Nanaksahi",
    "gn:country_code":"IN",
    "gn:dem":105,
    "gn:feature_class":"P",
    "gn:feature_code":"PPL",
    "gn:name":"N\u0101naks\u0101hi",
    "gn:population":0,
    "gn:timezone":"Asia/Kolkata",
    "iso:country":"IN",
    "name:und_x_variant":[
        "N\u0101naks\u0101hi",
        "Sar\u0101i Chandarbh\u0101n"
    ],
    "wof:name":"Nanaksahi",
    "wof:placetype":"locality"
},
  "geometry": {"coordinates":[81.75402,25.60232],"type":"Point"}
}