{
  "type": "Feature",
  "properties": {
    "iso:country":"IN",
    "ks:ks_name":"Koliya Para",
    "ks:ks_pop":197,
    "ks:ks_type":"HABITATION",
    "name:eng_x_preferred":[
        "Koliya Para"
    ],
    "wof:name":"Koliya Para",
    "wof:placetype":"locality",
    "wof:population":197
},
  "geometry": {"coordinates":[81.947103,19.213421],"type":"Point"}
}