{
  "type": "Feature",
  "properties": {
    "gn:admin1_code":"36",
    "gn:admin2_code":"162.0",
    "gn:asciiname":"Kanauli",
    "gn:country_code":"IN",
    "gn:dem":141,
    "gn:feature_class":"P",
    "gn:feature_code":"PPL",
    "gn:name":"Kanauli",
    "gn:population":0,
    "gn:timezone":"Asia/Kolkata",
    "iso:country":"IN",
    "ks:ks_name":"Kanauli",
    "ks:ks_pop":1,
    "ks:ks_type":"VILLAGE",
    "name:eng_x_preferred":[
        "Kanauli"
    ],
    "wof:name":"Kanauli",
    "wof:placetype":"locality",
    "wof:population":1
},
  "geometry": {"coordinates":[79.649394,26.642015],"type":"Point"}
}