{
  "type": "Feature",
  "properties": {
    "iso:country":"IN",
    "ks:ks_name":"Gunjakhol",
    "ks:ks_pop":111,
    "ks:ks_type":"VILLAGE",
    "name:eng_x_preferred":[
        "Gunjakhol"
    ],
    "wof:name":"Gunjakhol",
    "wof:placetype":"locality",
    "wof:population":111
},
  "geometry": {"coordinates":[83.67795599999999,22.15239],"type":"Point"}
}