{
  "type": "Feature",
  "properties": {
    "iso:country":"IN",
    "ks:ks_name":"Khajooriya",
    "ks:ks_pop":1048,
    "ks:ks_type":"VILLAGE",
    "name:eng_x_preferred":[
        "Khajooriya"
    ],
    "wof:name":"Khajooriya",
    "wof:placetype":"locality",
    "wof:population":1048
},
  "geometry": {"coordinates":[76.688889,24.599722],"type":"Point"}
}