{
  "type": "Feature",
  "properties": {
    "gn:admin1_code":"36.0",
    "gn:admin2_code":"150.0",
    "gn:asciiname":"Budhauli",
    "gn:country_code":"IN",
    "gn:dem":170,
    "gn:feature_class":"P",
    "gn:feature_code":"PPL",
    "gn:name":"Budhauli",
    "gn:population":0,
    "gn:timezone":"Asia/Kolkata",
    "iso:country":"IN",
    "ks:ks_name":"Budhauli",
    "ks:ks_type":"VILLAGE",
    "name:eng_x_preferred":[
        "Budhauli"
    ],
    "wof:name":"Budhauli",
    "wof:placetype":"locality"
},
  "geometry": {"coordinates":[79.665845,28.253456],"type":"Point"}
}