{
  "type": "Feature",
  "properties": {
    "gn:admin1_code":"34.0",
    "gn:admin2_code":"220.0",
    "gn:asciiname":"Muzaffarpur Malahi",
    "gn:country_code":"IN",
    "gn:dem":58,
    "gn:feature_class":"P",
    "gn:feature_code":"PPL",
    "gn:name":"Muzaffarpur Mal\u0101hi",
    "gn:population":0,
    "gn:timezone":"Asia/Kolkata",
    "iso:country":"IN",
    "ks:ks_name":"Mozaffarpur Malahi",
    "ks:ks_pop":1166,
    "ks:ks_type":"VILLAGE",
    "name:eng_x_preferred":[
        "Mozaffarpur Malahi"
    ],
    "name:eng_x_variant":[
        "Muzaffarpur Malahi"
    ],
    "wof:name":"Mozaffarpur Malahi",
    "wof:placetype":"locality",
    "wof:population":1166
},
  "geometry": {"coordinates":[85.272688,25.819569],"type":"Point"}
}