{
  "type": "Feature",
  "properties": {
    "gn:admin1_code":"34.0",
    "gn:admin2_code":"220.0",
    "gn:asciiname":"Muzaffarpur Malahi",
    "gn:country_code":"IN",
    "gn:dem":58,
    "gn:feature_class":"P",
    "gn:feature_code":"PPL",
    "gn:name":"Muzaffarpur Mal\u0101hi",
    "gn:population":0,
    "gn:timezone":"Asia/Kolkata",
    "iso:country":"IN",
    "wof:name":"Muzaffarpur Malahi",
    "wof:placetype":"locality"
},
  "geometry": {"coordinates":[85.26990000000001,25.82269],"type":"Point"}
}