{
  "type": "Feature",
  "properties": {
    "iso:country":"IN",
    "ks:ks_alt_nam":"Chennegowdana doddi",
    "ks:ks_name":"Chennegowdana Doddi",
    "ks:ks_pop":91,
    "ks:ks_type":"HABITATION",
    "name:eng_x_preferred":[
        "Chennegowdana Doddi"
    ],
    "wof:name":"Chennegowdana Doddi",
    "wof:placetype":"locality",
    "wof:population":91
},
  "geometry": {"coordinates":[77.20119699999999,12.776972],"type":"Point"}
}