{
  "type": "Feature",
  "properties": {
    "iso:country":"IN",
    "ks:ks_name":"Sahabazpur",
    "ks:ks_pop":2921,
    "ks:ks_type":"VILLAGE",
    "ks:ks_uagg_main":0,
    "name:eng_x_preferred":[
        "Sahabazpur"
    ],
    "wof:name":"Sahabazpur",
    "wof:placetype":"neighbourhood",
    "wof:population":2921
},
  "geometry": {"coordinates":[87.90128,24.725669],"type":"Point"}
}