{
  "type": "Feature",
  "properties": {
    "iso:country":"IN",
    "ks:ks_name":"Jawahar Kheda",
    "ks:ks_pop":71,
    "ks:ks_type":"HABITATION",
    "ks:ks_uagg_main":0,
    "name:eng_x_preferred":[
        "Jawahar Kheda"
    ],
    "wof:name":"Jawahar Kheda",
    "wof:placetype":"neighbourhood",
    "wof:population":71
},
  "geometry": {"coordinates":[80.377416,26.898231],"type":"Point"}
}