{
  "type": "Feature",
  "properties": {
    "iso:country":"IN",
    "ks:ks_name":"Jambupada",
    "ks:ks_pop":300,
    "ks:ks_type":"HABITATION",
    "name:eng_x_preferred":[
        "Jambupada"
    ],
    "wof:name":"Jambupada",
    "wof:placetype":"locality",
    "wof:population":300
},
  "geometry": {"coordinates":[72.69669,19.941408],"type":"Point"}
}