{
  "type": "Feature",
  "properties": {
    "gn:admin1_code":"2",
    "gn:admin2_code":"548.0",
    "gn:asciiname":"Kantepudi",
    "gn:country_code":"IN",
    "gn:dem":70,
    "gn:feature_class":"P",
    "gn:feature_code":"PPL",
    "gn:name":"Kantep\u016bdi",
    "gn:population":0,
    "gn:timezone":"Asia/Kolkata",
    "iso:country":"IN",
    "name:tel_x_preferred":[
        "\u0c15\u0c02\u0c1f\u0c3f\u0c2a\u0c42\u0c21\u0c3f"
    ],
    "wof:name":"Kantepudi",
    "wof:placetype":"locality"
},
  "geometry": {"coordinates":[80.21965,16.37813],"type":"Point"}
}