{
  "type": "Feature",
  "properties": {
    "gn:admin1_code":"11.0",
    "gn:admin2_code":"32.0",
    "gn:asciiname":"Nalka Obra",
    "gn:country_code":"IN",
    "gn:dem":1760,
    "gn:feature_class":"P",
    "gn:feature_code":"PPL",
    "gn:name":"N\u0101lka Obra",
    "gn:population":0,
    "gn:timezone":"Asia/Kolkata",
    "iso:country":"IN",
    "wof:name":"Nalka Obra",
    "wof:placetype":"locality"
},
  "geometry": {"coordinates":[77.36761,30.94591],"type":"Point"}
}