{
  "type": "Feature",
  "properties": {
    "iso:country":"IN",
    "ks:ks_name":"Paschim Bala Pet",
    "ks:ks_pop":670,
    "ks:ks_type":"HABITATION",
    "name:eng_x_preferred":[
        "Paschim Bala Pet"
    ],
    "wof:name":"Paschim Bala Pet",
    "wof:placetype":"locality",
    "wof:population":670
},
  "geometry": {"coordinates":[90.809372,26.433949],"type":"Point"}
}