{
  "type": "Feature",
  "properties": {
    "gn:admin1_code":"19.0",
    "gn:admin2_code":"563.0",
    "gn:asciiname":"Bellemane",
    "gn:country_code":"IN",
    "gn:dem":521,
    "gn:feature_class":"P",
    "gn:feature_code":"PPL",
    "gn:name":"Bellemane",
    "gn:population":0,
    "gn:timezone":"Asia/Kolkata",
    "iso:country":"IN",
    "wof:name":"Bellemane",
    "wof:placetype":"locality"
},
  "geometry": {"coordinates":[74.66311,14.78308],"type":"Point"}
}