{
  "type": "Feature",
  "properties": {
    "iso:country":"IN",
    "ks:ks_name":"Tejinpurwa",
    "ks:ks_pop":123,
    "ks:ks_type":"HABITATION",
    "name:eng_x_preferred":[
        "Tejinpurwa"
    ],
    "wof:name":"Tejinpurwa",
    "wof:placetype":"locality",
    "wof:population":123
},
  "geometry": {"coordinates":[80.851411,27.236735],"type":"Point"}
}