{
  "type": "Feature",
  "properties": {
    "gn:admin1_code":"19.0",
    "gn:admin2_code":"574.0",
    "gn:asciiname":"Kunkumana Hosur",
    "gn:country_code":"IN",
    "gn:dem":851,
    "gn:feature_class":"P",
    "gn:feature_code":"PPL",
    "gn:name":"Kunkumana Hos\u016br",
    "gn:population":0,
    "gn:timezone":"Asia/Kolkata",
    "iso:country":"IN",
    "wof:name":"Kunkumana Hosur",
    "wof:placetype":"locality"
},
  "geometry": {"coordinates":[76.27330000000001,12.82658],"type":"Point"}
}