{
  "type": "Feature",
  "properties": {
    "iso:country":"IN",
    "ks:ks_name":"Supahi",
    "ks:ks_pop":222,
    "ks:ks_type":"VILLAGE",
    "name:eng_x_preferred":[
        "Supahi"
    ],
    "wof:name":"Supahi",
    "wof:placetype":"locality",
    "wof:population":222
},
  "geometry": {"coordinates":[84.25982399999999,26.426153],"type":"Point"}
}