{
  "type": "Feature",
  "properties": {
    "gn:admin1_code":"39.0",
    "gn:admin2_code":"65.0",
    "gn:asciiname":"Sungaon",
    "gn:country_code":"IN",
    "gn:dem":1033,
    "gn:feature_class":"P",
    "gn:feature_code":"PPL",
    "gn:name":"Sungaon",
    "gn:population":0,
    "gn:timezone":"Asia/Kolkata",
    "iso:country":"IN",
    "wof:name":"Sungaon",
    "wof:placetype":"locality"
},
  "geometry": {"coordinates":[80.16374999999999,29.22715],"type":"Point"}
}