{
  "type": "Feature",
  "properties": {
    "iso:country":"IN",
    "ks:ks_name":"Kandavara Old Village",
    "ks:ks_pop":40,
    "ks:ks_type":"HABITATION",
    "name:eng_x_preferred":[
        "Kandavara Old Village"
    ],
    "wof:name":"Kandavara Old Village",
    "wof:placetype":"locality",
    "wof:population":40
},
  "geometry": {"coordinates":[75.74965,13.12606],"type":"Point"}
}