{
  "type": "Feature",
  "properties": {
    "gn:admin1_code":"39.0",
    "gn:admin2_code":"68.0",
    "gn:asciiname":"Alipur",
    "gn:country_code":"IN",
    "gn:dem":267,
    "gn:feature_class":"P",
    "gn:feature_code":"PPL",
    "gn:name":"Al\u012bpur",
    "gn:population":0,
    "gn:timezone":"Asia/Kolkata",
    "iso:country":"IN",
    "name:cat_x_preferred":[
        "Alipur"
    ],
    "name:ceb_x_preferred":[
        "Alipur"
    ],
    "name:swe_x_preferred":[
        "Alipur"
    ],
    "name:und_x_variant":[
        "Al\u012bpur",
        "Ibr\u0101h\u012bmpur"
    ],
    "wof:name":"Alipur",
    "wof:placetype":"locality"
},
  "geometry": {"coordinates":[78.05473000000001,29.89333],"type":"Point"}
}