{
  "type": "Feature",
  "properties": {
    "iso:country":"IN",
    "ks:ks_name":"Panchberia Barberia",
    "ks:ks_pop":2248,
    "ks:ks_type":"VILLAGE",
    "ks:ks_uagg_main":0,
    "name:eng_x_preferred":[
        "Panchberia Barberia"
    ],
    "wof:name":"Panchberia Barberia",
    "wof:placetype":"locality",
    "wof:population":2248
},
  "geometry": {"coordinates":[88.036339,22.444497],"type":"Point"}
}