{
  "type": "Feature",
  "properties": {
    "gn:admin1_code":"2.0",
    "gn:admin2_code":"553.0",
    "gn:asciiname":"Puttagundlapalle",
    "gn:country_code":"IN",
    "gn:dem":652,
    "gn:feature_class":"P",
    "gn:feature_code":"PPL",
    "gn:name":"Puttagundlapalle",
    "gn:population":0,
    "gn:timezone":"Asia/Kolkata",
    "iso:country":"IN",
    "wof:name":"Puttagundlapalle",
    "wof:placetype":"locality"
},
  "geometry": {"coordinates":[77.73828,14.01096],"type":"Point"}
}