{
  "type": "Feature",
  "properties": {
    "gn:admin1_code":"2.0",
    "gn:admin2_code":"553.0",
    "gn:asciiname":"Puttagundlapalle",
    "gn:country_code":"IN",
    "gn:dem":652,
    "gn:feature_class":"P",
    "gn:feature_code":"PPL",
    "gn:name":"Puttagundlapalle",
    "gn:population":0,
    "gn:timezone":"Asia/Kolkata",
    "iso:country":"IN",
    "ks:ks_name":"Puttagundlapalli",
    "ks:ks_pop":713,
    "ks:ks_type":"HABITATION",
    "name:eng_x_preferred":[
        "Puttagundlapalli"
    ],
    "name:eng_x_variant":[
        "Puttagundlapalle"
    ],
    "wof:name":"Puttagundlapalli",
    "wof:placetype":"locality",
    "wof:population":713
},
  "geometry": {"coordinates":[77.73716400000001,14.011762],"type":"Point"}
}