{
  "type": "Feature",
  "properties": {
    "gn:admin1_code":"23.0",
    "gn:admin2_code":"45.0",
    "gn:asciiname":"Sandhwan",
    "gn:country_code":"IN",
    "gn:dem":208,
    "gn:feature_class":"P",
    "gn:feature_code":"PPL",
    "gn:name":"Sandhw\u0101n",
    "gn:population":0,
    "gn:timezone":"Asia/Kolkata",
    "iso:country":"IN",
    "ks:ks_name":"Sandhwan",
    "ks:ks_pop":5288,
    "ks:ks_type":"VILLAGE",
    "ks:ks_uagg_main":0,
    "name:eng_x_preferred":[
        "Sandhwan"
    ],
    "name:und_x_variant":[
        "Sandhw\u0101n"
    ],
    "wof:name":"Sandhwan",
    "wof:placetype":"locality",
    "wof:population":5288
},
  "geometry": {"coordinates":[74.802402,30.61228],"type":"Point"}
}