{
  "type": "Feature",
  "properties": {
    "gn:admin1_code":"24.0",
    "gn:admin2_code":"102",
    "gn:asciiname":"Dadrewa",
    "gn:country_code":"IN",
    "gn:dem":230,
    "gn:feature_class":"P",
    "gn:feature_code":"PPL",
    "gn:name":"Dadrewa",
    "gn:population":0,
    "gn:timezone":"Asia/Kolkata",
    "iso:country":"IN",
    "name:hin_x_preferred":[
        "\u0926\u0926\u0930\u0947\u0935\u093e"
    ],
    "wof:name":"Dadrewa",
    "wof:placetype":"locality"
},
  "geometry": {"coordinates":[75.23608,28.6733],"type":"Point"}
}