{
  "type": "Feature",
  "properties": {
    "gn:admin1_code":"28.0",
    "gn:admin2_code":"342.0",
    "gn:asciiname":"Beniapukur",
    "gn:country_code":"IN",
    "gn:dem":5,
    "gn:feature_class":"P",
    "gn:feature_code":"PPL",
    "gn:name":"Beniapukur",
    "gn:population":0,
    "gn:timezone":"Asia/Kolkata",
    "iso:country":"IN",
    "name:ara_x_preferred":[
        "\u0628\u064a\u0646\u064a\u0627\u0628\u0648\u0643\u0648\u0631"
    ],
    "name:ben_bn_x_preferred":[
        "\u09ac\u09c7\u09a8\u09bf\u09df\u09be\u09aa\u09c1\u0995\u09c1\u09b0"
    ],
    "name:ben_in_x_preferred":[
        "\u09ac\u09c7\u09a8\u09bf\u09df\u09be\u09aa\u09c1\u0995\u09c1\u09b0"
    ],
    "name:ben_x_preferred":[
        "\u09ac\u09c7\u09a8\u09bf\u09af\u09bc\u09be\u09aa\u09c1\u0995\u09c1\u09b0"
    ],
    "name:guj_x_preferred":[
        "\u0aac\u0ac7\u0aa8\u0abf\u0aaf\u0abe\u0aaa\u0ac1\u0a95\u0ac1\u0ab0"
    ],
    "name:hin_x_preferred":[
        "\u092c\u0947\u0928\u093f\u092f\u093e\u092a\u0941\u0915\u0941\u0930"
    ],
    "name:kan_x_preferred":[
        "\u0cac\u0cc7\u0ca8\u0cbf\u0caf\u0cbe\u0caa\u0cc1\u0c95\u0cc1\u0cb0\u0ccd"
    ],
    "name:mal_x_preferred":[
        "\u0d2c\u0d46\u0d28\u0d3f\u0d2f\u0d3e\u0d2a\u0d41\u0d15\u0d42\u0d7c"
    ],
    "name:mar_x_preferred":[
        "\u092c\u0947\u0928\u093f\u092f\u093e\u092a\u0941\u0915\u0941\u0930"
    ],
    "name:pan_x_preferred":[
        "\u0a2c\u0a48\u0a28\u0a40\u0a06\u0a2a\u0a41\u0a15\u0a41\u0a30"
    ],
    "name:tam_x_preferred":[
        "\u0baa\u0bc6\u0ba9\u0bbf\u0baf\u0bbe\u0baa\u0bc1\u0b95\u0bc2\u0bb0\u0bcd"
    ],
    "name:tel_x_preferred":[
        "\u0c2c\u0c46\u0c28\u0c3f\u0c2f\u0c3e\u0c2a\u0c41\u0c15\u0c41\u0c30\u0c4d"
    ],
    "name:urd_x_preferred":[
        "\u0628\u06cc\u0646\u06cc\u0627 \u067e\u0648\u06a9\u0648\u0631"
    ],
    "wof:name":"Beniapukur",
    "wof:placetype":"neighbourhood"
},
  "geometry": {"coordinates":[88.36939,22.54971],"type":"Point"}
}