{
  "type": "Feature",
  "properties": {
    "gn:admin1_code":"28.0",
    "gn:admin2_code":"342.0",
    "gn:asciiname":"Beniapukur",
    "gn:country_code":"IN",
    "gn:dem":5,
    "gn:feature_class":"P",
    "gn:feature_code":"PPL",
    "gn:name":"Beniapukur",
    "gn:population":0,
    "gn:timezone":"Asia/Kolkata",
    "iso:country":"IN",
    "name:ben_x_preferred":[
        "\u09ac\u09c7\u09a8\u09bf\u09af\u09bc\u09be\u09aa\u09c1\u0995\u09c1\u09b0"
    ],
    "wof:name":"Beniapukur",
    "wof:placetype":"neighbourhood"
},
  "geometry": {"coordinates":[88.36939,22.54971],"type":"Point"}
}