{
  "type": "Feature",
  "properties": {
    "gn:admin1_code":"20.0",
    "gn:admin2_code":"267.0",
    "gn:asciiname":"Nokhu",
    "gn:country_code":"IN",
    "gn:dem":1193,
    "gn:feature_class":"P",
    "gn:feature_code":"PPL",
    "gn:name":"Nokhu",
    "gn:population":0,
    "gn:timezone":"Asia/Kolkata",
    "iso:country":"IN",
    "wof:name":"Nokhu",
    "wof:placetype":"locality"
},
  "geometry": {"coordinates":[95.01877,26.15279],"type":"Point"}
}