{
  "type": "Feature",
  "properties": {
    "gn:admin1_code":"16",
    "gn:admin2_code":"510.0",
    "gn:asciiname":"Mudahati",
    "gn:country_code":"IN",
    "gn:dem":260,
    "gn:feature_class":"P",
    "gn:feature_code":"PPL",
    "gn:name":"Mud\u0101hati",
    "gn:population":0,
    "gn:timezone":"Asia/Kolkata",
    "iso:country":"IN",
    "ks:ks_alt_nam":"Mud\u0101hati",
    "ks:ks_name":"Mudahati",
    "ks:ks_type":"VILLAGE",
    "name:eng_x_preferred":[
        "Mudahati"
    ],
    "name:eng_x_variant":[
        "Mud\u0101hati"
    ],
    "wof:name":"Mudahati",
    "wof:placetype":"locality"
},
  "geometry": {"coordinates":[78.66579,19.857129],"type":"Point"}
}