{
  "type": "Feature",
  "properties": {
    "gn:admin1_code":"11",
    "gn:admin2_code":"27.0",
    "gn:asciiname":"Kanan",
    "gn:country_code":"IN",
    "gn:dem":1362,
    "gn:feature_class":"P",
    "gn:feature_code":"PPL",
    "gn:name":"Kan\u0101n",
    "gn:population":0,
    "gn:timezone":"Asia/Kolkata",
    "iso:country":"IN",
    "name:bar_x_preferred":[
        "Kanan"
    ],
    "name:ceb_x_preferred":[
        "Kanan"
    ],
    "name:deu_x_preferred":[
        "Kanan"
    ],
    "name:epo_x_preferred":[
        "Kanan"
    ],
    "name:ind_x_preferred":[
        "Kanan"
    ],
    "name:swe_x_preferred":[
        "Kanan"
    ],
    "name:tgl_x_preferred":[
        "Kanan"
    ],
    "wof:name":"Kanan",
    "wof:placetype":"locality"
},
  "geometry": {"coordinates":[76.82136,31.69124],"type":"Point"}
}