{
  "type": "Feature",
  "properties": {
    "gn:admin1_code":"40",
    "gn:admin2_code":"539.0",
    "gn:asciiname":"Kankanalapalli",
    "gn:country_code":"IN",
    "gn:dem":203,
    "gn:feature_class":"P",
    "gn:feature_code":"PPL",
    "gn:name":"Kankan\u0101lapalli",
    "gn:population":0,
    "gn:timezone":"Asia/Kolkata",
    "iso:country":"IN",
    "name:tel_x_preferred":[
        "\u0c15\u0c02\u0c15\u0c23\u0c3e\u0c32\u0c2a\u0c32\u0c4d\u0c32\u0c3f"
    ],
    "wof:name":"Kankanalapalli",
    "wof:placetype":"locality"
},
  "geometry": {"coordinates":[79.3447,17.04262],"type":"Point"}
}