{
  "type": "Feature",
  "properties": {
    "iso:country":"IN",
    "ks:ks_name":"Newada Khurd",
    "ks:ks_pop":373,
    "ks:ks_type":"VILLAGE",
    "ks:ks_uagg_main":0,
    "name:eng_x_preferred":[
        "Newada Khurd"
    ],
    "wof:name":"Newada Khurd",
    "wof:placetype":"neighbourhood",
    "wof:population":373
},
  "geometry": {"coordinates":[82.8098,26.21051],"type":"Point"}
}