{
  "type": "Feature",
  "properties": {
    "iso:country":"IN",
    "ks:ks_name":"Bharad",
    "ks:ks_pop":1119,
    "ks:ks_type":"VILLAGE",
    "name:eng_x_preferred":[
        "Bharad"
    ],
    "wof:name":"Bharad",
    "wof:placetype":"locality",
    "wof:population":1119
},
  "geometry": {"coordinates":[72.930706,19.899627],"type":"Point"}
}