{
  "type": "Feature",
  "properties": {
    "iso:country":"IN",
    "ks:ks_name":"Malik Uttarpara",
    "ks:ks_pop":891,
    "ks:ks_type":"HABITATION",
    "name:eng_x_preferred":[
        "Malik Uttarpara"
    ],
    "wof:name":"Malik Uttarpara",
    "wof:placetype":"locality",
    "wof:population":891
},
  "geometry": {"coordinates":[87.983425,22.562471],"type":"Point"}
}