{
  "type": "Feature",
  "properties": {
    "gn:admin1_code":"35",
    "gn:admin2_code":"452.0",
    "gn:asciiname":"Murgakhera",
    "gn:country_code":"IN",
    "gn:dem":353,
    "gn:feature_class":"P",
    "gn:feature_code":"PPL",
    "gn:name":"Murg\u0101khera",
    "gn:population":0,
    "gn:timezone":"Asia/Kolkata",
    "iso:country":"IN",
    "ks:ks_name":"Murgakheda",
    "ks:ks_pop":943,
    "ks:ks_type":"VILLAGE",
    "name:eng_x_preferred":[
        "Murgakheda"
    ],
    "name:eng_x_variant":[
        "Murgakhera"
    ],
    "wof:name":"Murgakheda",
    "wof:placetype":"locality",
    "wof:population":943
},
  "geometry": {"coordinates":[79.242715,23.089246],"type":"Point"}
}