{
  "type": "Feature",
  "properties": {
    "iso:country":"IN",
    "ks:ks_name":"Pandedih",
    "ks:ks_pop":91,
    "ks:ks_type":"HABITATION",
    "name:eng_x_preferred":[
        "Pandedih"
    ],
    "wof:name":"Pandedih",
    "wof:placetype":"locality",
    "wof:population":91
},
  "geometry": {"coordinates":[86.92102,24.427297],"type":"Point"}
}