{
  "type": "Feature",
  "properties": {
    "iso:country":"IN",
    "ks:ks_name":"Chandrama",
    "ks:ks_pop":27,
    "ks:ks_type":"VILLAGE",
    "name:eng_x_preferred":[
        "Chandrama"
    ],
    "wof:name":"Chandrama",
    "wof:placetype":"locality",
    "wof:population":27
},
  "geometry": {"coordinates":[85.077742,19.825761],"type":"Point"}
}