{
  "type": "Feature",
  "properties": {
    "gn:admin1_code":"21.0",
    "gn:admin2_code":"388.0",
    "gn:asciiname":"Srirampalli",
    "gn:country_code":"IN",
    "gn:dem":232,
    "gn:feature_class":"P",
    "gn:feature_code":"PPL",
    "gn:name":"Srirampalli",
    "gn:population":0,
    "gn:timezone":"Asia/Kolkata",
    "iso:country":"IN",
    "wof:name":"Srirampalli",
    "wof:placetype":"locality"
},
  "geometry": {"coordinates":[84.36735,19.70372],"type":"Point"}
}