{
  "type": "Feature",
  "properties": {
    "iso:country":"IN",
    "ks:ks_name":"Kapia",
    "ks:ks_pop":353,
    "ks:ks_type":"HABITATION",
    "name:eng_x_preferred":[
        "Kapia"
    ],
    "wof:name":"Kapia",
    "wof:placetype":"locality",
    "wof:population":353
},
  "geometry": {"coordinates":[82.89903700000001,27.015306],"type":"Point"}
}