{
  "type": "Feature",
  "properties": {
    "gn:admin1_code":"36",
    "gn:admin2_code":"194.0",
    "gn:asciiname":"Bhogirathpur",
    "gn:country_code":"IN",
    "gn:dem":89,
    "gn:feature_class":"P",
    "gn:feature_code":"PPL",
    "gn:name":"Bhog\u012brathpur",
    "gn:population":0,
    "gn:timezone":"Asia/Kolkata",
    "iso:country":"IN",
    "wof:name":"Bhogirathpur",
    "wof:placetype":"locality"
},
  "geometry": {"coordinates":[82.54771,25.67946],"type":"Point"}
}