{
  "type": "Feature",
  "properties": {
    "gn:admin1_code":"24",
    "gn:admin2_code":"125.0",
    "gn:asciiname":"Bhandari",
    "gn:country_code":"IN",
    "gn:dem":281,
    "gn:feature_class":"P",
    "gn:feature_code":"PPL",
    "gn:name":"Bhand\u0101ri",
    "gn:population":0,
    "gn:timezone":"Asia/Kolkata",
    "iso:country":"IN",
    "ks:ks_name":"Bhandariya",
    "ks:ks_pop":74,
    "ks:ks_type":"VILLAGE",
    "name:eng_x_preferred":[
        "Bhandariya"
    ],
    "name:eng_x_variant":[
        "Bhandari"
    ],
    "name:nep_x_preferred":[
        "\u092d\u0923\u094d\u0921\u093e\u0930\u0940"
    ],
    "wof:name":"Bhandariya",
    "wof:placetype":"locality",
    "wof:population":74
},
  "geometry": {"coordinates":[74.43865,23.214794],"type":"Point"}
}