{
  "type": "Feature",
  "properties": {
    "iso:country":"IN",
    "ks:ks_name":"Outram Island",
    "ks:ks_type":"VILLAGE",
    "name:eng_x_preferred":[
        "Outram Island"
    ],
    "wof:name":"Outram Island",
    "wof:placetype":"locality"
},
  "geometry": {"coordinates":[93.079292,12.234912],"type":"Point"}
}