{
  "type": "Feature",
  "properties": {
    "gn:admin1_code":"2",
    "gn:admin2_code":"544.0",
    "gn:asciiname":"Kusumaguda",
    "gn:country_code":"IN",
    "gn:dem":962,
    "gn:feature_class":"P",
    "gn:feature_code":"PPL",
    "gn:name":"Kusumag\u016bda",
    "gn:population":0,
    "gn:timezone":"Asia/Kolkata",
    "iso:country":"IN",
    "wof:name":"Kusumaguda",
    "wof:placetype":"locality"
},
  "geometry": {"coordinates":[82.79878000000002,18.26839],"type":"Point"}
}