{
  "type": "Feature",
  "properties": {
    "gn:admin1_code":"2",
    "gn:admin2_code":"544.0",
    "gn:asciiname":"Kusumaguda",
    "gn:country_code":"IN",
    "gn:dem":962,
    "gn:feature_class":"P",
    "gn:feature_code":"PPL",
    "gn:name":"Kusumag\u016bda",
    "gn:population":0,
    "gn:timezone":"Asia/Kolkata",
    "iso:country":"IN",
    "ks:ks_name":"Kusumaguda",
    "ks:ks_pop":94,
    "ks:ks_type":"HABITATION",
    "name:eng_x_preferred":[
        "Kusumaguda"
    ],
    "wof:name":"Kusumaguda",
    "wof:placetype":"locality",
    "wof:population":94
},
  "geometry": {"coordinates":[82.79858,18.250193],"type":"Point"}
}