{
  "type": "Feature",
  "properties": {
    "gn:admin1_code":"24",
    "gn:admin2_code":"103.0",
    "gn:asciiname":"Urika",
    "gn:country_code":"IN",
    "gn:dem":294,
    "gn:feature_class":"P",
    "gn:feature_code":"PPL",
    "gn:name":"Urika",
    "gn:population":0,
    "gn:timezone":"Asia/Kolkata",
    "iso:country":"IN",
    "name:und_x_variant":[
        "\u016arika"
    ],
    "wof:name":"Urika",
    "wof:placetype":"neighbourhood"
},
  "geometry": {"coordinates":[75.90747,28.35253],"type":"Point"}
}