{
  "type": "Feature",
  "properties": {
    "iso:country":"IN",
    "ks:ks_name":"Kumarapatty",
    "ks:ks_pop":171,
    "ks:ks_type":"HABITATION",
    "name:eng_x_preferred":[
        "Kumarapatty"
    ],
    "wof:name":"Kumarapatty",
    "wof:placetype":"locality",
    "wof:population":171
},
  "geometry": {"coordinates":[78.26777800000001,10.264052],"type":"Point"}
}