{
  "type": "Feature",
  "properties": {
    "gn:admin1_code":"16",
    "gn:admin2_code":"511.0",
    "gn:asciiname":"Majar Sangvi",
    "gn:country_code":"IN",
    "gn:dem":431,
    "gn:feature_class":"P",
    "gn:feature_code":"PPL",
    "gn:name":"Majar S\u0101ngvi",
    "gn:population":0,
    "gn:timezone":"Asia/Kolkata",
    "iso:country":"IN",
    "wof:name":"Majar Sangvi",
    "wof:placetype":"locality"
},
  "geometry": {"coordinates":[77.09275,18.83285],"type":"Point"}
}