{
  "type": "Feature",
  "properties": {
    "iso:country":"IN",
    "ks:ks_name":"Hurrapara",
    "ks:ks_pop":480,
    "ks:ks_type":"HABITATION",
    "name:eng_x_preferred":[
        "Hurrapara"
    ],
    "wof:name":"Hurrapara",
    "wof:placetype":"locality",
    "wof:population":480
},
  "geometry": {"coordinates":[81.413831,18.770123],"type":"Point"}
}