{
  "type": "Feature",
  "properties": {
    "iso:country":"IN",
    "ks:ks_alt_nam":"Pulsingh tanda",
    "ks:ks_name":"Pulsingh Tanda",
    "ks:ks_pop":89,
    "ks:ks_type":"HABITATION",
    "name:eng_x_preferred":[
        "Pulsingh Tanda"
    ],
    "wof:name":"Pulsingh Tanda",
    "wof:placetype":"locality",
    "wof:population":89
},
  "geometry": {"coordinates":[78.387709,16.868201],"type":"Point"}
}