{
  "type": "Feature",
  "properties": {
    "gn:admin1_code":"35",
    "gn:admin2_code":"448.0",
    "gn:asciiname":"Uchan",
    "gn:country_code":"IN",
    "gn:dem":272,
    "gn:feature_class":"P",
    "gn:feature_code":"PPL",
    "gn:name":"Uch\u0101n",
    "gn:population":0,
    "gn:timezone":"Asia/Kolkata",
    "iso:country":"IN",
    "ks:ks_alt_nam":"Uch\u0101n",
    "ks:ks_name":"Uchan",
    "ks:ks_pop":268,
    "ks:ks_type":"VILLAGE",
    "name:eng_x_preferred":[
        "Uchan"
    ],
    "name:eng_x_variant":[
        "Uch\u0101n"
    ],
    "wof:name":"Uchan",
    "wof:placetype":"locality",
    "wof:population":268
},
  "geometry": {"coordinates":[76.86793900000001,22.45226],"type":"Point"}
}