{
  "type": "Feature",
  "properties": {
    "iso:country":"IN",
    "ks:ks_name":"Bhelaidi",
    "ks:ks_pop":514,
    "ks:ks_type":"VILLAGE",
    "name:eng_x_preferred":[
        "Bhelaidi"
    ],
    "wof:name":"Bhelaidi",
    "wof:placetype":"locality",
    "wof:population":514
},
  "geometry": {"coordinates":[86.17030800000001,23.420891],"type":"Point"}
}