{
  "type": "Feature",
  "properties": {
    "iso:country":"IN",
    "ks:ks_name":"Kailas Nagar",
    "ks:ks_pop":185,
    "ks:ks_type":"HABITATION",
    "name:eng_x_preferred":[
        "Kailas Nagar"
    ],
    "wof:name":"Kailas Nagar",
    "wof:placetype":"locality",
    "wof:population":185
},
  "geometry": {"coordinates":[81.090341,28.12978],"type":"Point"}
}