{
  "type": "Feature",
  "properties": {
    "iso:country":"IN",
    "ks:ks_name":"Bhulabori No4",
    "ks:ks_pop":202,
    "ks:ks_type":"HABITATION",
    "name:eng_x_preferred":[
        "Bhulabori No4"
    ],
    "wof:name":"Bhulabori No4",
    "wof:placetype":"locality",
    "wof:population":202
},
  "geometry": {"coordinates":[93.80906,27.031693],"type":"Point"}
}