{
  "type": "Feature",
  "properties": {
    "iso:country":"IN",
    "ks:ks_name":"Rollakonda",
    "ks:ks_pop":1112,
    "ks:ks_type":"HABITATION",
    "name:eng_x_preferred":[
        "Rollakonda"
    ],
    "wof:name":"Rollakonda",
    "wof:placetype":"locality",
    "wof:population":1112
},
  "geometry": {"coordinates":[77.112906,13.854892],"type":"Point"}
}