{
  "type": "Feature",
  "properties": {
    "iso:country":"IN",
    "ks:ks_name":"Chanda",
    "ks:ks_pop":0,
    "ks:ks_type":"VILLAGE",
    "name:eng_x_preferred":[
        "Chanda"
    ],
    "wof:name":"Chanda",
    "wof:placetype":"locality",
    "wof:population":0
},
  "geometry": {"coordinates":[87.17599800000001,22.177241],"type":"Point"}
}