{
  "type": "Feature",
  "properties": {
    "iso:country":"IN",
    "ks:ks_name":"Sarswati Nagar",
    "ks:ks_pop":143,
    "ks:ks_type":"HABITATION",
    "name:eng_x_preferred":[
        "Sarswati Nagar"
    ],
    "wof:name":"Sarswati Nagar",
    "wof:placetype":"locality",
    "wof:population":143
},
  "geometry": {"coordinates":[71.037892,26.089367],"type":"Point"}
}