{
  "type": "Feature",
  "properties": {
    "iso:country":"IN",
    "ks:ks_name":"Katkarwadi",
    "ks:ks_pop":171,
    "ks:ks_type":"HABITATION",
    "name:eng_x_preferred":[
        "Katkarwadi"
    ],
    "wof:name":"Katkarwadi",
    "wof:placetype":"locality",
    "wof:population":171
},
  "geometry": {"coordinates":[73.69081199999999,16.615813],"type":"Point"}
}