{
  "type": "Feature",
  "properties": {
    "gn:admin1_code":"09",
    "gn:admin2_code":"475.0",
    "gn:asciiname":"Vanala",
    "gn:country_code":"IN",
    "gn:dem":31,
    "gn:feature_class":"P",
    "gn:feature_code":"PPL",
    "gn:name":"Van\u0101la",
    "gn:population":0,
    "gn:timezone":"Asia/Kolkata",
    "iso:country":"IN",
    "name:ara_x_preferred":[
        "\u0641\u0627\u0646\u0627\u0644\u0627"
    ],
    "name:fas_x_preferred":[
        "\u0648\u0646\u0644\u0627"
    ],
    "name:und_x_variant":[
        "Van\u0101la"
    ],
    "wof:name":"Vanala",
    "wof:placetype":"locality"
},
  "geometry": {"coordinates":[71.92143,22.43662],"type":"Point"}
}