{
  "type": "Feature",
  "properties": {
    "iso:country":"IN",
    "ks:ks_name":"Boranamane",
    "ks:ks_pop":46,
    "ks:ks_type":"VILLAGE",
    "name:eng_x_preferred":[
        "Boranamane"
    ],
    "wof:name":"Boranamane",
    "wof:placetype":"locality",
    "wof:population":46
},
  "geometry": {"coordinates":[75.72080699999999,12.74575],"type":"Point"}
}