{
  "type": "Feature",
  "properties": {
    "iso:country":"IN",
    "ks:ks_name":"Vajjepalle",
    "ks:ks_pop":1652,
    "ks:ks_type":"VILLAGE",
    "name:eng_x_preferred":[
        "Vajjepalle"
    ],
    "wof:name":"Vajjepalle",
    "wof:placetype":"locality",
    "wof:population":1652
},
  "geometry": {"coordinates":[78.197665,18.474999],"type":"Point"}
}