{
  "type": "Feature",
  "properties": {
    "gn:admin1_code":"21",
    "gn:admin2_code":"395.0",
    "gn:asciiname":"Gopinathpur",
    "gn:country_code":"IN",
    "gn:dem":265,
    "gn:feature_class":"P",
    "gn:feature_code":"PPL",
    "gn:name":"Gopinathpur",
    "gn:population":0,
    "gn:timezone":"Asia/Kolkata",
    "iso:country":"IN",
    "wof:name":"Gopinathpur",
    "wof:placetype":"locality"
},
  "geometry": {"coordinates":[83.25013,19.96024],"type":"Point"}
}