{
  "type": "Feature",
  "properties": {
    "iso:country":"IN",
    "ks:ks_name":"Pachim Joypur",
    "ks:ks_pop":557,
    "ks:ks_type":"VILLAGE",
    "ks:ks_uagg_main":0,
    "name:eng_x_preferred":[
        "Pachim Joypur"
    ],
    "wof:name":"Pachim Joypur",
    "wof:placetype":"neighbourhood",
    "wof:population":557
},
  "geometry": {"coordinates":[90.547184,26.604455],"type":"Point"}
}