{
  "type": "Feature",
  "properties": {
    "gn:admin1_code":"12.0",
    "gn:admin2_code":"7.0",
    "gn:asciiname":"Banari",
    "gn:country_code":"IN",
    "gn:dem":464,
    "gn:feature_class":"P",
    "gn:feature_code":"PPL",
    "gn:name":"Ban\u0101ri",
    "gn:population":0,
    "gn:timezone":"Asia/Kolkata",
    "iso:country":"IN",
    "name:arg_x_preferred":[
        "B\u00e0nari"
    ],
    "name:azb_x_preferred":[
        "\u0628\u0627\u0646\u0627\u0631\u06cc"
    ],
    "name:bel_x_preferred":[
        "\u0411\u0430\u043d\u0430\u0440\u044b"
    ],
    "name:bos_x_preferred":[
        "Banari"
    ],
    "name:bul_x_preferred":[
        "\u0411\u0430\u043d\u0430\u0440\u0438"
    ],
    "name:cat_x_preferred":[
        "Banari"
    ],
    "name:ceb_x_preferred":[
        "Banari"
    ],
    "name:ces_x_preferred":[
        "Banari"
    ],
    "name:dan_x_preferred":[
        "Banari"
    ],
    "name:deu_x_preferred":[
        "Banari"
    ],
    "name:epo_x_preferred":[
        "Banari"
    ],
    "name:eus_x_preferred":[
        "Banari"
    ],
    "name:fas_x_preferred":[
        "\u0628\u0627\u0646\u0627\u0631\u06cc"
    ],
    "name:fin_x_preferred":[
        "Banari"
    ],
    "name:fra_x_preferred":[
        "Banari"
    ],
    "name:hrv_x_preferred":[
        "Banari"
    ],
    "name:hun_x_preferred":[
        "Banari"
    ],
    "name:hye_x_preferred":[
        "\u0532\u0561\u0576\u0561\u0580\u056b"
    ],
    "name:ind_x_preferred":[
        "Banari"
    ],
    "name:ita_x_preferred":[
        "Banari"
    ],
    "name:jpn_x_preferred":[
        "\u30d0\u30fc\u30ca\u30ea"
    ],
    "name:kaz_x_preferred":[
        "\u0411\u0430\u043d\u0430\u0440\u0438"
    ],
    "name:lat_x_preferred":[
        "Bannaris"
    ],
    "name:lmo_x_preferred":[
        "Banari"
    ],
    "name:msa_x_preferred":[
        "Banari"
    ],
    "name:nap_x_preferred":[
        "Banari"
    ],
    "name:nld_x_preferred":[
        "Banari"
    ],
    "name:nno_x_preferred":[
        "Banari"
    ],
    "name:nor_x_preferred":[
        "Banari"
    ],
    "name:pms_x_preferred":[
        "Banari"
    ],
    "name:pol_x_preferred":[
        "Banari"
    ],
    "name:por_x_preferred":[
        "Banari"
    ],
    "name:ron_x_preferred":[
        "Banari"
    ],
    "name:rus_x_preferred":[
        "\u0411\u0430\u043d\u0430\u0440\u0438"
    ],
    "name:scn_x_preferred":[
        "Banari"
    ],
    "name:spa_x_preferred":[
        "Banari"
    ],
    "name:sqi_x_preferred":[
        "Banari"
    ],
    "name:srd_x_preferred":[
        "B\u00e0nari"
    ],
    "name:srp_x_preferred":[
        "\u0411\u0430\u043d\u0430\u0440\u0438"
    ],
    "name:tgl_x_preferred":[
        "Banari"
    ],
    "name:tur_x_preferred":[
        "Banari"
    ],
    "name:ukr_x_preferred":[
        "\u0411\u0430\u043d\u0430\u0440\u0456"
    ],
    "name:uzb_x_preferred":[
        "Banari"
    ],
    "name:vec_x_preferred":[
        "Banari"
    ],
    "name:vie_x_preferred":[
        "Banari"
    ],
    "name:vol_x_preferred":[
        "Banari"
    ],
    "name:war_x_preferred":[
        "Banari"
    ],
    "name:zho_x_preferred":[
        "\u5df4\u7eb3\u91cc"
    ],
    "wof:name":"Banari",
    "wof:placetype":"locality"
},
  "geometry": {"coordinates":[75.63809999999999,32.40956],"type":"Point"}
}