{
  "type": "Feature",
  "properties": {
    "iso:country":"IN",
    "ks:ks_name":"Godi",
    "ks:ks_pop":34,
    "ks:ks_type":"VILLAGE",
    "name:eng_x_preferred":[
        "Godi"
    ],
    "wof:name":"Godi",
    "wof:placetype":"locality",
    "wof:population":34
},
  "geometry": {"coordinates":[78.629738,30.103976],"type":"Point"}
}