{
  "type": "Feature",
  "properties": {
    "iso:country":"IN",
    "ks:ks_name":"Uli Taw",
    "ks:ks_pop":98,
    "ks:ks_type":"VILLAGE",
    "name:eng_x_preferred":[
        "Uli Taw"
    ],
    "wof:name":"Uli Taw",
    "wof:placetype":"locality",
    "wof:population":98
},
  "geometry": {"coordinates":[94.537728,27.591595],"type":"Point"}
}