{
  "type": "Feature",
  "properties": {
    "iso:country":"IN",
    "ks:ks_name":"Madhliwadi",
    "ks:ks_pop":189,
    "ks:ks_type":"HABITATION",
    "name:eng_x_preferred":[
        "Madhliwadi"
    ],
    "wof:name":"Madhliwadi",
    "wof:placetype":"locality",
    "wof:population":189
},
  "geometry": {"coordinates":[73.51747,16.267274],"type":"Point"}
}