{
  "type": "Feature",
  "properties": {
    "gn:admin1_code":"36",
    "gn:admin2_code":"148.0",
    "gn:asciiname":"Bilsara",
    "gn:country_code":"IN",
    "gn:dem":156,
    "gn:feature_class":"P",
    "gn:feature_code":"PPL",
    "gn:name":"Bilsara",
    "gn:population":0,
    "gn:timezone":"Asia/Kolkata",
    "iso:country":"IN",
    "ks:ks_name":"Bilsara",
    "ks:ks_pop":1113,
    "ks:ks_type":"VILLAGE",
    "ks:ks_uagg_main":0,
    "name:eng_x_preferred":[
        "Bilsara"
    ],
    "wof:name":"Bilsara",
    "wof:placetype":"neighbourhood",
    "wof:population":1113
},
  "geometry": {"coordinates":[79.25691999999999,27.253147],"type":"Point"}
}