{
  "type": "Feature",
  "properties": {
    "iso:country":"IN",
    "ks:ks_name":"Kamol Faliya",
    "ks:ks_pop":486,
    "ks:ks_type":"HABITATION",
    "name:eng_x_preferred":[
        "Kamol Faliya"
    ],
    "wof:name":"Kamol Faliya",
    "wof:placetype":"locality",
    "wof:population":486
},
  "geometry": {"coordinates":[73.96550000000001,23.091528],"type":"Point"}
}