{
  "type": "Feature",
  "properties": {
    "iso:country":"IN",
    "ks:ks_name":"Orea",
    "ks:ks_pop":339,
    "ks:ks_type":"VILLAGE",
    "name:eng_x_preferred":[
        "Orea"
    ],
    "wof:name":"Orea",
    "wof:placetype":"locality",
    "wof:population":339
},
  "geometry": {"coordinates":[84.39476000000001,23.668847],"type":"Point"}
}