{
  "type": "Feature",
  "properties": {
    "iso:country":"IN",
    "ks:ks_name":"Pauhari Ka Churaha",
    "ks:ks_pop":312,
    "ks:ks_type":"HABITATION",
    "name:eng_x_preferred":[
        "Pauhari Ka Churaha"
    ],
    "wof:name":"Pauhari Ka Churaha",
    "wof:placetype":"locality",
    "wof:population":312
},
  "geometry": {"coordinates":[83.92671300000001,26.697922],"type":"Point"}
}