{
  "type": "Feature",
  "properties": {
    "iso:country":"IN",
    "ks:ks_name":"Mangchu Forest",
    "ks:ks_pop":800,
    "ks:ks_type":"VILLAGE",
    "name:eng_x_preferred":[
        "Mangchu Forest"
    ],
    "wof:name":"Mangchu Forest",
    "wof:placetype":"locality",
    "wof:population":800
},
  "geometry": {"coordinates":[88.550836,27.158348],"type":"Point"}
}