{
  "type": "Feature",
  "properties": {
    "iso:country":"IN",
    "ks:ks_name":"Bettampady",
    "ks:ks_pop":1150,
    "ks:ks_type":"HABITATION",
    "name:eng_x_preferred":[
        "Bettampady"
    ],
    "wof:name":"Bettampady",
    "wof:placetype":"locality",
    "wof:population":1150
},
  "geometry": {"coordinates":[74.86334600000001,12.766782],"type":"Point"}
}