{
  "type": "Feature",
  "properties": {
    "iso:country":"IN",
    "ks:ks_name":"Kadokata",
    "ks:ks_pop":57,
    "ks:ks_type":"VILLAGE",
    "name:eng_x_preferred":[
        "Kadokata"
    ],
    "wof:name":"Kadokata",
    "wof:placetype":"locality",
    "wof:population":57
},
  "geometry": {"coordinates":[87.458027,22.824249],"type":"Point"}
}