{
  "type": "Feature",
  "properties": {
    "iso:country":"IN",
    "ks:ks_name":"Bhamarkachchh",
    "ks:ks_pop":10,
    "ks:ks_type":"HABITATION",
    "name:eng_x_preferred":[
        "Bhamarkachchh"
    ],
    "wof:name":"Bhamarkachchh",
    "wof:placetype":"locality",
    "wof:population":10
},
  "geometry": {"coordinates":[81.417226,25.016605],"type":"Point"}
}