{
  "type": "Feature",
  "properties": {
    "iso:country":"IN",
    "ks:ks_alt_nam":"Habi Dhuli TE",
    "ks:ks_name":"Habi Dhuli Te",
    "ks:ks_pop":215,
    "ks:ks_type":"HABITATION",
    "name:eng_x_preferred":[
        "Habi Dhuli Te"
    ],
    "wof:name":"Habi Dhuli Te",
    "wof:placetype":"locality",
    "wof:population":215
},
  "geometry": {"coordinates":[95.46508900000001,27.419215],"type":"Point"}
}