{
  "type": "Feature",
  "properties": {
    "gn:admin1_code":"12.0",
    "gn:admin2_code":"1.0",
    "gn:asciiname":"Danna Baihk",
    "gn:country_code":"IN",
    "gn:dem":2165,
    "gn:feature_class":"P",
    "gn:feature_code":"PPL",
    "gn:name":"Danna Baihk",
    "gn:population":0,
    "gn:timezone":"Asia/Kolkata",
    "iso:country":"IN",
    "wof:name":"Danna Baihk",
    "wof:placetype":"locality"
},
  "geometry": {"coordinates":[74.36060000000001,34.51721],"type":"Point"}
}