{
  "type": "Feature",
  "properties": {
    "gn:admin1_code":"11.0",
    "gn:admin2_code":"33.0",
    "gn:asciiname":"Lamba Jubar",
    "gn:country_code":"IN",
    "gn:dem":2118,
    "gn:feature_class":"P",
    "gn:feature_code":"PPL",
    "gn:name":"Lamba Jubar",
    "gn:population":0,
    "gn:timezone":"Asia/Kolkata",
    "iso:country":"IN",
    "wof:name":"Lamba Jubar",
    "wof:placetype":"locality"
},
  "geometry": {"coordinates":[77.55802,31.30222],"type":"Point"}
}