{
  "type": "Feature",
  "properties": {
    "iso:country":"IN",
    "ks:ks_alt_nam":"umminamane",
    "ks:ks_name":"Umminamane",
    "ks:ks_pop":25,
    "ks:ks_type":"HABITATION",
    "name:eng_x_preferred":[
        "Umminamane"
    ],
    "wof:name":"Umminamane",
    "wof:placetype":"locality",
    "wof:population":25
},
  "geometry": {"coordinates":[75.158722,13.819622],"type":"Point"}
}