{
  "type": "Feature",
  "properties": {
    "iso:country":"IN",
    "ks:ks_name":"Kanakanandal",
    "ks:ks_pop":1251,
    "ks:ks_type":"VILLAGE",
    "ks:ks_uagg_main":0,
    "name:eng_x_preferred":[
        "Kanakanandal"
    ],
    "wof:name":"Kanakanandal",
    "wof:placetype":"neighbourhood",
    "wof:population":1251
},
  "geometry": {"coordinates":[79.175516,11.938086],"type":"Point"}
}