{
  "type": "Feature",
  "properties": {
    "iso:country":"IN",
    "ks:ks_name":"Marhai Khudana",
    "ks:ks_pop":86,
    "ks:ks_type":"HABITATION",
    "ks:ks_uagg_main":0,
    "name:eng_x_preferred":[
        "Marhai Khudana"
    ],
    "wof:name":"Marhai Khudana",
    "wof:placetype":"neighbourhood",
    "wof:population":86
},
  "geometry": {"coordinates":[81.514557,27.560227],"type":"Point"}
}