{
  "type": "Feature",
  "properties": {
    "iso:country":"IN",
    "ks:ks_name":"Padam Lal East",
    "ks:ks_pop":179,
    "ks:ks_type":"HABITATION",
    "name:eng_x_preferred":[
        "Padam Lal East"
    ],
    "wof:name":"Padam Lal East",
    "wof:placetype":"locality",
    "wof:population":179
},
  "geometry": {"coordinates":[87.694633,26.286673],"type":"Point"}
}