{
  "type": "Feature",
  "properties": {
    "iso:country":"IN",
    "ks:ks_name":"Doladanga",
    "ks:ks_pop":58,
    "ks:ks_type":"VILLAGE",
    "name:eng_x_preferred":[
        "Doladanga"
    ],
    "wof:name":"Doladanga",
    "wof:placetype":"locality",
    "wof:population":58
},
  "geometry": {"coordinates":[86.709219,22.970157],"type":"Point"}
}