{
  "type": "Feature",
  "properties": {
    "gn:admin1_code":"35.0",
    "gn:admin2_code":"437.0",
    "gn:asciiname":"Mahuria Khalsa",
    "gn:country_code":"IN",
    "gn:dem":532,
    "gn:feature_class":"P",
    "gn:feature_code":"PPL",
    "gn:name":"Mahuria Kh\u0101lsa",
    "gn:population":0,
    "gn:timezone":"Asia/Kolkata",
    "iso:country":"IN",
    "ks:ks_name":"Mahudiya Khalsa",
    "ks:ks_pop":599,
    "ks:ks_type":"VILLAGE",
    "ks:ks_uagg_main":0,
    "name:eng_x_preferred":[
        "Mahudiya Khalsa"
    ],
    "wof:name":"Mahudiya Khalsa",
    "wof:placetype":"neighbourhood",
    "wof:population":599
},
  "geometry": {"coordinates":[76.462144,22.792173],"type":"Point"}
}