{
  "type": "Feature",
  "properties": {
    "iso:country":"IN",
    "name:ara_x_preferred":[
        "\u0643\u0648\u0644\u0627\u0628\u0643\u0627\u0645"
    ],
    "name:ben_bn_x_preferred":[
        "\u0995\u09cb\u09b2\u09be\u09aa\u09be\u0995\u09cd\u0995\u09be\u09ae"
    ],
    "name:ben_in_x_preferred":[
        "\u0995\u09cb\u09b2\u09be\u09aa\u09be\u0995\u09cd\u0995\u09be\u09ae"
    ],
    "name:guj_x_preferred":[
        "\u0a95\u0acb\u0ab2\u0abe\u0aaa\u0a95\u0acd\u0a95\u0aae"
    ],
    "name:hin_x_preferred":[
        "\u0915\u094b\u0932\u093e\u092a\u0915\u094d\u0915\u092e"
    ],
    "name:kan_x_preferred":[
        "\u0c95\u0cca\u0cb2\u0caa\u0c95\u0ccd\u0c95\u0cae\u0ccd"
    ],
    "name:mal_x_preferred":[
        "\u0d15\u0d4b\u0d32\u0d2a\u0d4d\u0d2a\u0d3e\u0d15\u0d4d\u0d15\u0d02"
    ],
    "name:mar_x_preferred":[
        "\u0915\u094b\u0932\u093e\u092a\u0915\u094d\u0915\u092e"
    ],
    "name:pan_x_preferred":[
        "\u0a15\u0a4b\u0a32\u0a3e\u0a2a\u0a71\u0a15\u0a2e"
    ],
    "name:tam_x_preferred":[
        "\u0b95\u0bcb\u0bb2\u0baa\u0bcd\u0baa\u0bbe\u0b95\u0bcd\u0b95\u0bae\u0bcd"
    ],
    "name:tel_x_preferred":[
        "\u0c15\u0c4b\u0c32\u0c2a\u0c15\u0c4d\u0c15\u0c02"
    ],
    "name:urd_x_preferred":[
        "\u06a9\u0648\u0644\u0627\u067e\u0627\u06a9\u0651\u0645"
    ],
    "qs:name":"Kolapakkam",
    "qs:name_adm0":"India",
    "qs:name_adm1":"Tamil Nadu",
    "qs:photos":2,
    "qs:photos_1k":1,
    "qs:photos_9k":1,
    "qs:photos_9r":1,
    "qs:photos_all":2,
    "qs:photos_sr":1,
    "qs:placetype":"Suburb",
    "qs:pop_sr":"0",
    "wof:name":"Kolapakkam",
    "wof:placetype":"neighbourhood"
},
  "geometry": {"coordinates":[80.121917,12.946261],"type":"Point"}
}