{
  "type": "Feature",
  "properties": {
    "iso:country":"IN",
    "qs:name":"Kolapakkam",
    "qs:name_adm0":"India",
    "qs:name_adm1":"Tamil Nadu",
    "qs:photos":2,
    "qs:photos_1k":1,
    "qs:photos_9k":1,
    "qs:photos_9r":1,
    "qs:photos_all":2,
    "qs:photos_sr":1,
    "qs:placetype":"Suburb",
    "qs:pop_sr":"0",
    "wof:name":"Kolapakkam",
    "wof:placetype":"neighbourhood"
},
  "geometry": {"coordinates":[80.121917,12.946261],"type":"Point"}
}