{
  "type": "Feature",
  "properties": {
    "iso:country":"IN",
    "ks:ks_name":"Bordi",
    "ks:ks_pop":0,
    "ks:ks_type":"VILLAGE",
    "name:eng_x_preferred":[
        "Bordi"
    ],
    "wof:name":"Bordi",
    "wof:placetype":"locality",
    "wof:population":0
},
  "geometry": {"coordinates":[85.270805,24.648009],"type":"Point"}
}