{
  "type": "Feature",
  "properties": {
    "gn:admin1_code":"36",
    "gn:admin2_code":"142.0",
    "gn:asciiname":"Fatehpur Nagla Hari",
    "gn:country_code":"IN",
    "gn:dem":198,
    "gn:feature_class":"P",
    "gn:feature_code":"PPL",
    "gn:name":"Fatehp\u016br Nagla Hari",
    "gn:population":0,
    "gn:timezone":"Asia/Kolkata",
    "iso:country":"IN",
    "wof:name":"Fatehpur Nagla Hari",
    "wof:placetype":"locality"
},
  "geometry": {"coordinates":[78.0968,28.31844],"type":"Point"}
}