{
  "type": "Feature",
  "properties": {
    "iso:country":"IN",
    "ks:ks_name":"Hosahoklu",
    "ks:ks_pop":48,
    "ks:ks_type":"HABITATION",
    "name:eng_x_preferred":[
        "Hosahoklu"
    ],
    "wof:name":"Hosahoklu",
    "wof:placetype":"locality",
    "wof:population":48
},
  "geometry": {"coordinates":[75.21491899999999,12.785673],"type":"Point"}
}