{
  "type": "Feature",
  "properties": {
    "gn:admin1_code":"36",
    "gn:admin2_code":"156.0",
    "gn:asciiname":"Kundra Khera",
    "gn:country_code":"IN",
    "gn:dem":129,
    "gn:feature_class":"P",
    "gn:feature_code":"PPL",
    "gn:name":"Kundra Khera",
    "gn:population":0,
    "gn:timezone":"Asia/Kolkata",
    "iso:country":"IN",
    "wof:name":"Kundra Khera",
    "wof:placetype":"neighbourhood"
},
  "geometry": {"coordinates":[80.75013,26.5246],"type":"Point"}
}