{
  "type": "Feature",
  "properties": {
    "iso:country":"IN",
    "ks:ks_name":"Nagri",
    "ks:ks_pop":380,
    "ks:ks_type":"VILLAGE",
    "name:eng_x_preferred":[
        "Nagri"
    ],
    "wof:name":"Nagri",
    "wof:placetype":"locality",
    "wof:population":380
},
  "geometry": {"coordinates":[86.46982,24.528247],"type":"Point"}
}