{
  "type": "Feature",
  "properties": {
    "iso:country":"IN",
    "ks:ks_name":"Warchiwadi",
    "ks:ks_pop":96,
    "ks:ks_type":"HABITATION",
    "name:eng_x_preferred":[
        "Warchiwadi"
    ],
    "wof:name":"Warchiwadi",
    "wof:placetype":"locality",
    "wof:population":96
},
  "geometry": {"coordinates":[73.516763,16.105526],"type":"Point"}
}