{
  "type": "Feature",
  "properties": {
    "gn:admin1_code":"11.0",
    "gn:admin2_code":"33.0",
    "gn:asciiname":"Sendor",
    "gn:country_code":"IN",
    "gn:dem":1471,
    "gn:feature_class":"P",
    "gn:feature_code":"PPL",
    "gn:name":"Sendor",
    "gn:population":0,
    "gn:timezone":"Asia/Kolkata",
    "iso:country":"IN",
    "wof:name":"Sendor",
    "wof:placetype":"locality"
},
  "geometry": {"coordinates":[77.73175000000001,31.16292],"type":"Point"}
}