{
  "type": "Feature",
  "properties": {
    "gn:admin1_code":"35",
    "gn:admin2_code":"451.0",
    "gn:asciiname":"Sarra",
    "gn:country_code":"IN",
    "gn:dem":377,
    "gn:feature_class":"P",
    "gn:feature_code":"PPL",
    "gn:name":"Sarra",
    "gn:population":0,
    "gn:timezone":"Asia/Kolkata",
    "iso:country":"IN",
    "ks:ks_name":"Sarra",
    "ks:ks_pop":155,
    "ks:ks_type":"VILLAGE",
    "name:bre_x_preferred":[
        "Sarra"
    ],
    "name:deu_x_preferred":[
        "Sarra"
    ],
    "name:eng_x_preferred":[
        "Sarra"
    ],
    "name:ita_x_preferred":[
        "Sarra"
    ],
    "name:rus_x_preferred":[
        "\u0421\u0430\u0440\u0440\u0430"
    ],
    "wof:name":"Sarra",
    "wof:placetype":"locality",
    "wof:population":155
},
  "geometry": {"coordinates":[79.608754,23.064114],"type":"Point"}
}