{
  "type": "Feature",
  "properties": {
    "gn:admin1_code":"19.0",
    "gn:admin2_code":"572.0",
    "gn:asciiname":"Bikanhalli",
    "gn:country_code":"IN",
    "gn:dem":889,
    "gn:feature_class":"P",
    "gn:feature_code":"PPL",
    "gn:name":"Bikanhalli",
    "gn:population":0,
    "gn:timezone":"Asia/Kolkata",
    "iso:country":"IN",
    "wof:name":"Bikanhalli",
    "wof:placetype":"locality"
},
  "geometry": {"coordinates":[77.75941999999998,12.83737],"type":"Point"}
}