{
  "type": "Feature",
  "properties": {
    "gn:admin1_code":"12.0",
    "gn:admin2_code":"9.0",
    "gn:asciiname":"Khidar",
    "gn:country_code":"IN",
    "gn:dem":2611,
    "gn:feature_class":"P",
    "gn:feature_code":"PPL",
    "gn:name":"Khidar",
    "gn:population":0,
    "gn:timezone":"Asia/Kolkata",
    "iso:country":"IN",
    "name:eng_x_preferred":[
        "Khidar"
    ],
    "wof:name":"Khidar",
    "wof:placetype":"locality"
},
  "geometry": {"coordinates":[74.51306,34.46678],"type":"Point"}
}