{
  "type": "Feature",
  "properties": {
    "iso:country":"IN",
    "ks:ks_name":"Urugonda",
    "ks:ks_pop":300,
    "ks:ks_type":"HABITATION",
    "name:eng_x_preferred":[
        "Urugonda"
    ],
    "wof:name":"Urugonda",
    "wof:placetype":"locality",
    "wof:population":300
},
  "geometry": {"coordinates":[82.549952,18.140141],"type":"Point"}
}