{
  "type": "Feature",
  "properties": {
    "iso:country":"IN",
    "ks:ks_name":"Zechamalai",
    "ks:ks_pop":505,
    "ks:ks_type":"HABITATION",
    "name:eng_x_preferred":[
        "Zechamalai"
    ],
    "wof:name":"Zechamalai",
    "wof:placetype":"locality",
    "wof:population":505
},
  "geometry": {"coordinates":[77.56788,10.164623],"type":"Point"}
}