{
  "type": "Feature",
  "properties": {
    "gn:admin1_code":"12.0",
    "gn:asciiname":"Nakka Baihk",
    "gn:country_code":"IN",
    "gn:dem":3088,
    "gn:feature_class":"P",
    "gn:feature_code":"PPL",
    "gn:name":"Nakka Baihk",
    "gn:population":0,
    "gn:timezone":"Asia/Kolkata",
    "iso:country":"IN",
    "wof:name":"Nakka Baihk",
    "wof:placetype":"locality"
},
  "geometry": {"coordinates":[74.09811999999999,34.60616],"type":"Point"}
}