{
  "type": "Feature",
  "properties": {
    "gn:admin1_code":"2",
    "gn:admin2_code":"544.0",
    "gn:asciiname":"Rampul",
    "gn:country_code":"IN",
    "gn:dem":885,
    "gn:feature_class":"P",
    "gn:feature_code":"PPL",
    "gn:name":"Rampul",
    "gn:population":0,
    "gn:timezone":"Asia/Kolkata",
    "iso:country":"IN",
    "ks:ks_name":"Rampulu",
    "ks:ks_pop":908,
    "ks:ks_type":"VILLAGE",
    "name:eng_x_preferred":[
        "Rampulu"
    ],
    "name:eng_x_variant":[
        "Rampul"
    ],
    "wof:name":"Rampulu",
    "wof:placetype":"locality",
    "wof:population":908
},
  "geometry": {"coordinates":[82.308173,17.753321],"type":"Point"}
}