{
  "type": "Feature",
  "properties": {
    "gn:admin1_code":"2",
    "gn:admin2_code":"544.0",
    "gn:asciiname":"Rampul",
    "gn:country_code":"IN",
    "gn:dem":885,
    "gn:feature_class":"P",
    "gn:feature_code":"PPL",
    "gn:name":"Rampul",
    "gn:population":0,
    "gn:timezone":"Asia/Kolkata",
    "iso:country":"IN",
    "wof:name":"Rampul",
    "wof:placetype":"locality"
},
  "geometry": {"coordinates":[82.30828000000002,17.75277999999999],"type":"Point"}
}