{
  "type": "Feature",
  "properties": {
    "iso:country":"IN",
    "ks:ks_alt_nam":"Vaili faliya",
    "ks:ks_name":"Vaili Faliya",
    "ks:ks_pop":285,
    "ks:ks_type":"HABITATION",
    "name:eng_x_preferred":[
        "Vaili Faliya"
    ],
    "wof:name":"Vaili Faliya",
    "wof:placetype":"locality",
    "wof:population":285
},
  "geometry": {"coordinates":[73.235405,20.590957],"type":"Point"}
}