{
  "type": "Feature",
  "properties": {
    "gn:admin1_code":"28.0",
    "gn:admin2_code":"327.0",
    "gn:asciiname":"Bong",
    "gn:country_code":"IN",
    "gn:dem":837,
    "gn:feature_class":"P",
    "gn:feature_code":"PPL",
    "gn:name":"Bong",
    "gn:population":0,
    "gn:timezone":"Asia/Kolkata",
    "iso:country":"IN",
    "name:bul_x_preferred":[
        "\u0411\u043e\u043d\u0433"
    ],
    "name:ces_x_preferred":[
        "Bong"
    ],
    "name:dan_x_preferred":[
        "Bong"
    ],
    "name:deu_x_preferred":[
        "Bong"
    ],
    "name:epo_x_preferred":[
        "Akvopipo"
    ],
    "name:fin_x_preferred":[
        "Vesipiippu"
    ],
    "name:heb_x_preferred":[
        "\u05d1\u05d0\u05e0\u05d2"
    ],
    "name:ita_x_preferred":[
        "Bong"
    ],
    "name:lit_x_preferred":[
        "Bongas"
    ],
    "name:nds_x_preferred":[
        "Bong"
    ],
    "name:nld_x_preferred":[
        "Bong"
    ],
    "name:nor_x_preferred":[
        "Bong"
    ],
    "name:pol_x_preferred":[
        "Fajka wodna"
    ],
    "name:por_x_preferred":[
        "Bong"
    ],
    "name:ron_x_preferred":[
        "Bong"
    ],
    "name:rus_x_preferred":[
        "\u0411\u043e\u043d\u0433"
    ],
    "name:spa_x_preferred":[
        "Bong"
    ],
    "name:swe_x_preferred":[
        "Bong"
    ],
    "name:tha_x_preferred":[
        "\u0e1a\u0e49\u0e2d\u0e07"
    ],
    "name:ukr_x_preferred":[
        "\u0411\u043e\u043d\u0433"
    ],
    "wof:name":"Bong",
    "wof:placetype":"locality"
},
  "geometry": {"coordinates":[88.48329,27.04222],"type":"Point"}
}