{
  "type": "Feature",
  "properties": {
    "iso:country":"IN",
    "ks:ks_name":"Hanotiya Raimal",
    "ks:ks_pop":340,
    "ks:ks_type":"VILLAGE",
    "ks:ks_uagg_main":0,
    "name:eng_x_preferred":[
        "Hanotiya Raimal"
    ],
    "wof:name":"Hanotiya Raimal",
    "wof:placetype":"neighbourhood",
    "wof:population":340
},
  "geometry": {"coordinates":[75.95638099999999,24.262798],"type":"Point"}
}