{
  "type": "Feature",
  "properties": {
    "iso:country":"IN",
    "ks:ks_name":"Chumoni",
    "ks:ks_pop":835,
    "ks:ks_type":"VILLAGE",
    "name:eng_x_preferred":[
        "Chumoni"
    ],
    "wof:name":"Chumoni",
    "wof:placetype":"locality",
    "wof:population":835
},
  "geometry": {"coordinates":[94.80123,26.931618],"type":"Point"}
}