{
  "type": "Feature",
  "properties": {
    "gn:admin1_code":"23",
    "gn:admin2_code":"35.0",
    "gn:asciiname":"Buche Nangal",
    "gn:country_code":"IN",
    "gn:dem":249,
    "gn:feature_class":"P",
    "gn:feature_code":"PPL",
    "gn:name":"Buche Nangal",
    "gn:population":0,
    "gn:timezone":"Asia/Kolkata",
    "iso:country":"IN",
    "name:hin_x_colloquial":[
        "\u092c\u0941\u091a\u0947 \u0928\u0902\u0917\u0932"
    ],
    "name:hin_x_preferred":[
        "\u092c\u0941\u091a\u0947 \u0928\u0902\u0917\u0932"
    ],
    "name:pan_x_colloquial":[
        "\u0a2c\u0a41\u0a1a\u0a47 \u0a28\u0a70\u0a17\u0a32"
    ],
    "name:pan_x_preferred":[
        "\u0a2c\u0a41\u0a1a\u0a47 \u0a28\u0a70\u0a17\u0a32"
    ],
    "wof:name":"Buche Nangal",
    "wof:placetype":"locality"
},
  "geometry": {"coordinates":[75.22749,31.9793],"type":"Point"}
}