{
  "type": "Feature",
  "properties": {
    "iso:country":"IN",
    "ks:ks_name":"Shiarsol",
    "ks:ks_pop":0,
    "ks:ks_type":"VILLAGE",
    "name:eng_x_preferred":[
        "Shiarsol"
    ],
    "wof:name":"Shiarsol",
    "wof:placetype":"locality",
    "wof:population":0
},
  "geometry": {"coordinates":[87.274587,23.790373],"type":"Point"}
}