{
  "type": "Feature",
  "properties": {
    "iso:country":"IN",
    "ks:ks_name":"Chiphalti Lagga Gawali Danda",
    "ks:ks_pop":71,
    "ks:ks_type":"HABITATION",
    "name:eng_x_preferred":[
        "Chiphalti Lagga Gawali Danda"
    ],
    "wof:name":"Chiphalti Lagga Gawali Danda",
    "wof:placetype":"locality",
    "wof:population":71
},
  "geometry": {"coordinates":[78.174344,30.327656],"type":"Point"}
}