{
  "type": "Feature",
  "properties": {
    "iso:country":"IN",
    "ks:ks_name":"Gadhvewasti",
    "ks:ks_pop":120,
    "ks:ks_type":"HABITATION",
    "name:eng_x_preferred":[
        "Gadhvewasti"
    ],
    "wof:name":"Gadhvewasti",
    "wof:placetype":"locality",
    "wof:population":120
},
  "geometry": {"coordinates":[75.05570400000001,17.761781],"type":"Point"}
}